{
  "type": "Feature",
  "properties": {
    "addr:full":"159 Gordon Rd Ilford Essex IG1 2XS",
    "addr:housenumber":"159",
    "addr:postcode":"ig1 2xs",
    "addr:street":"Gordon Rd",
    "iso:country":"GB",
    "sg:address":"159 Gordon Rd",
    "sg:city":"Ilford",
    "sg:classifiers":[
        {
            "category":"Coffee & Tea",
            "type":"Food & Drink"
        }
    ],
    "sg:phone":"+44 20 8478 0192",
    "sg:postcode":"IG1 2XS",
    "sg:province":"Essex",
    "wof:name":"Holland,Norman,",
    "wof:placetype":"venue"
},
  "geometry": {"coordinates":[0.088278,51.552357],"type":"Point"}
}