{
  "type": "Feature",
  "properties": {
    "addr:full":"231 Wallacewell Road, Balornock Glasgow East Dunbartonshire G21 3PR",
    "addr:housenumber":"231",
    "addr:postcode":"g21 3pr",
    "addr:street":"Wallacewell Road",
    "iso:country":"GB",
    "sg:address":"231 Wallacewell Road, Balornock",
    "sg:city":"Glasgow",
    "sg:classifiers":[
        {
            "category":"Fast Food",
            "type":"Food & Drink"
        }
    ],
    "sg:postcode":"G21 3PR",
    "sg:province":"East Dunbartonshire",
    "sg:tags":[
        "away",
        "take"
    ],
    "wof:name":"Tandoori Express",
    "wof:placetype":"venue"
},
  "geometry": {"coordinates":[-4.2038431168,55.8915405273],"type":"Point"}
}