{
  "type": "Feature",
  "properties": {
    "addr:full":"Wrexham Road Mold Denbighshire CH7 1HS",
    "addr:postcode":"ch7 1hs",
    "addr:street":"Wrexham Road",
    "iso:country":"GB",
    "sg:address":"Wrexham Road",
    "sg:city":"Mold",
    "sg:classifiers":[
        {
            "category":"Autos & Motor Vehicles",
            "subcategory":"Auto Supplies",
            "type":"Retail Goods"
        }
    ],
    "sg:phone":"+44 1352 753682",
    "sg:postcode":"CH7 1HS",
    "sg:province":"Denbighshire",
    "sg:tags":[
        "tyre"
    ],
    "wof:name":"Ats",
    "wof:placetype":"venue"
},
  "geometry": {"coordinates":[-3.1318199635,53.1570892334],"type":"Point"}
}