{
  "type": "Feature",
  "properties": {
    "addr:full":"11 Berkeley Road Birchington Kent CT7 9JN",
    "addr:housenumber":"11",
    "addr:postcode":"ct7 9jn",
    "addr:street":"Berkeley Road",
    "iso:country":"GB",
    "sg:address":"11 Berkeley Road",
    "sg:city":"Birchington",
    "sg:classifiers":[
        {
            "category":"Professional",
            "type":"Services"
        },
        {
            "category":"Social Services",
            "subcategory":"Job Training",
            "type":"Services"
        }
    ],
    "sg:phone":"+44 1843 847701",
    "sg:postcode":"CT7 9JN",
    "sg:province":"Kent",
    "sg:tags":[
        "translator",
        "interpreter",
        "translation",
        "activity"
    ],
    "wof:name":"B J Translations",
    "wof:placetype":"venue"
},
  "geometry": {"coordinates":[1.300087,51.379631],"type":"Point"}
}