{
  "type": "Feature",
  "properties": {
    "addr:full":"Pretoria, Upleadon Newent Gloucestershire GL18 1EH",
    "addr:postcode":"gl18 1eh",
    "iso:country":"GB",
    "sg:address":"Pretoria, Upleadon",
    "sg:city":"Newent",
    "sg:classifiers":[
        {
            "category":"Professional",
            "subcategory":"Engineering",
            "type":"Services"
        }
    ],
    "sg:phone":"+44 1531 820323",
    "sg:postcode":"GL18 1EH",
    "sg:province":"Gloucestershire",
    "sg:tags":[
        "contractor",
        "electrical",
        "engineer"
    ],
    "wof:name":"F J Hamer",
    "wof:placetype":"venue"
},
  "geometry": {"coordinates":[-2.4061338902,51.9308280945],"type":"Point"}
}