{
  "type": "Feature",
  "properties": {
    "addr:full":"Devonia House, Durham Road Bromley Kent BR2 0SG",
    "addr:postcode":"br2 0sg",
    "addr:street":"Durham Road",
    "iso:country":"GB",
    "sg:address":"Devonia House, Durham Road",
    "sg:city":"Bromley",
    "sg:classifiers":[
        {
            "category":"Professional",
            "subcategory":"Accounting & Tax Preparation",
            "type":"Services"
        }
    ],
    "sg:postcode":"BR2 0SG",
    "sg:province":"Kent",
    "sg:tags":[
        "accountant"
    ],
    "wof:name":"Durrant & Co",
    "wof:placetype":"venue"
},
  "geometry": {"coordinates":[0.0074959998,51.4002838135],"type":"Point"}
}