{
  "type": "Feature",
  "properties": {
    "iso:country":"GB",
    "sg:address":"Penrhiw Farm, Lower Cwmtwrch",
    "sg:city":"Swansea",
    "sg:classifiers":[
        {
            "category":"Home & Garden",
            "subcategory":"Household Appliances",
            "type":"Retail Goods"
        },
        {
            "category":"Retail",
            "subcategory":"Repair Shop",
            "type":"Services"
        }
    ],
    "sg:phone":"+44 1639 845941",
    "sg:postcode":"SA9 2QH",
    "sg:province":"Carmarthenshire",
    "sg:tags":[
        "machine",
        "electrical",
        "washing"
    ],
    "wof:name":"Washing Machine Centre",
    "wof:placetype":"venue"
},
  "geometry": {"coordinates":[-3.76538,51.79163],"type":"Point"}
}