{
  "type": "Feature",
  "properties": {
    "iso:country":"GB",
    "sg:address":"26 Clarence Road, Linslade",
    "sg:city":"Leighton Buzzard",
    "sg:classifiers":[
        {
            "category":"Building & Trades",
            "subcategory":"Landscaping Services",
            "type":"Services"
        }
    ],
    "sg:phone":"+44 1525 377390",
    "sg:postcode":"LU7 3EJ",
    "sg:province":"Bedfordshire",
    "sg:tags":[
        "consultant"
    ],
    "wof:name":"Arrow Design",
    "wof:placetype":"venue"
},
  "geometry": {"coordinates":[-0.6579920053,51.9241142273],"type":"Point"}
}