{
  "type": "Feature",
  "properties": {
    "addr:full":"113 Lanehouse Road, Thornaby Stockton-on-tees Durham TS17 8AB",
    "addr:housenumber":"113",
    "addr:postcode":"ts17 8ab",
    "addr:street":"Lanehouse Road",
    "iso:country":"GB",
    "sg:address":"113 Lanehouse Road, Thornaby",
    "sg:city":"Stockton-on-tees",
    "sg:classifiers":[
        {
            "category":"Shopping",
            "subcategory":"Pharmacy",
            "type":"Retail Goods"
        }
    ],
    "sg:phone":"+44 1642 676842",
    "sg:postcode":"TS17 8AB",
    "sg:province":"Durham",
    "sg:tags":[
        "pharmacist",
        "chemist"
    ],
    "wof:name":"Peter Milburn",
    "wof:placetype":"venue"
},
  "geometry": {"coordinates":[-1.299661994,54.5509376526],"type":"Point"}
}