{
  "type": "Feature",
  "properties": {
    "iso:country":"GB",
    "sg:address":"6 Cressex Enterprise Centre, Lincoln Road",
    "sg:city":"High Wycombe",
    "sg:classifiers":[
        {
            "category":"Professional",
            "subcategory":"Employment Agencies",
            "type":"Services"
        }
    ],
    "sg:postcode":"HP12 3RL",
    "sg:province":"Buckinghamshire",
    "sg:tags":[
        "consultant"
    ],
    "wof:name":"Professional Appointments",
    "wof:placetype":"venue"
},
  "geometry": {"coordinates":[-0.77107,51.625961],"type":"Point"}
}