{
  "type": "Feature",
  "properties": {
    "addr:full":"Unit 5 Edward Street Industrial Estate Darlington Durham DL1 2UP",
    "addr:housenumber":"unit 5;estate",
    "addr:postcode":"dl1 2up",
    "addr:street":"Edward Street Industrial",
    "iso:country":"GB",
    "sg:address":"Unit 5 Edward Street Industrial Estate",
    "sg:city":"Darlington",
    "sg:classifiers":[
        {
            "category":"Building & Trades",
            "subcategory":"Plumbing",
            "type":"Services"
        },
        {
            "category":"Home & Garden",
            "subcategory":"Hardware",
            "type":"Retail Goods"
        }
    ],
    "sg:phone":"+44 1325 240006",
    "sg:postcode":"DL1 2UP",
    "sg:province":"Durham",
    "sg:tags":[
        "equipment",
        "plumber",
        "central",
        "heating"
    ],
    "wof:name":"T P S BOILER SPARES LTD",
    "wof:placetype":"venue"
},
  "geometry": {"coordinates":[-1.544091,54.534622],"type":"Point"}
}