{
  "type": "Feature",
  "properties": {
    "addr:full":"Wholesale House, Sandall Carr Road, Kirk Sandall Industrial Estate Doncaster South Yorkshire DN3 1QL",
    "addr:housenumber":"estate",
    "addr:postcode":"dn3 1ql",
    "addr:street":"Sandall Carr Road Kirk;Industrial",
    "iso:country":"GB",
    "sg:address":"Wholesale House, Sandall Carr Road, Kirk Sandall Industrial Estate",
    "sg:city":"Doncaster",
    "sg:classifiers":[
        {
            "category":"Shopping",
            "subcategory":"Clothing, Apparel, & Fashions",
            "type":"Retail Goods"
        }
    ],
    "sg:phone":"+44 1302 881737",
    "sg:postcode":"DN3 1QL",
    "sg:province":"South Yorkshire",
    "sg:tags":[
        "ladieswear"
    ],
    "wof:name":"Factory Shop One",
    "wof:placetype":"venue"
},
  "geometry": {"coordinates":[-1.0775140524,53.5580101013],"type":"Point"}
}