{
  "type": "Feature",
  "properties": {
    "addr:full":"11 Northfield Road Tetbury Gloucestershire GL8 8HB",
    "addr:housenumber":"11",
    "addr:postcode":"gl8 8hb",
    "addr:street":"Northfield Road",
    "iso:country":"GB",
    "sg:address":"11 Northfield Road",
    "sg:city":"Tetbury",
    "sg:classifiers":[
        {
            "category":"Manufacturing",
            "subcategory":"Wood Products",
            "type":"Manufacturing & Wholesale Goods"
        }
    ],
    "sg:phone":"+44 1666 502877",
    "sg:postcode":"GL8 8HB",
    "sg:province":"Gloucestershire",
    "sg:tags":[
        "maker",
        "cabinet"
    ],
    "sg:website":"http://www.tesco.co.uk",
    "wof:name":"W Cook",
    "wof:placetype":"venue"
},
  "geometry": {"coordinates":[-2.1551001072,51.6409988403],"type":"Point"}
}