{
  "type": "Feature",
  "properties": {
    "iso:country":"GB",
    "sg:address":"208a Ashley Road, Hale",
    "sg:city":"Altrincham",
    "sg:classifiers":[
        {
            "category":"Banks & Credit Unions",
            "subcategory":"Bank",
            "type":"Services"
        }
    ],
    "sg:phone":"+44 161 929 4296",
    "sg:postcode":"WA15 9SN",
    "sg:province":"Cheshire",
    "sg:tags":[
        "broker",
        "mortgage"
    ],
    "wof:name":"Nationwide Mortgage Services Ltd.",
    "wof:placetype":"venue"
},
  "geometry": {"coordinates":[-2.344337,53.376038],"type":"Point"}
}