{
  "type": "Feature",
  "properties": {
    "iso:country":"GB",
    "sg:address":"Estate Office, Trafford Park Road",
    "sg:city":"Manchester",
    "sg:classifiers":[
        {
            "category":"Structure",
            "subcategory":"Warehouse",
            "type":"Public Place"
        }
    ],
    "sg:phone":"+44 161 872 2411",
    "sg:postcode":"M17 1AU",
    "sg:province":"Cheshire",
    "wof:name":"Port of Manchester Warehouses Ltd.",
    "wof:placetype":"venue"
},
  "geometry": {"coordinates":[-2.308359,53.46814],"type":"Point"}
}