{
  "type": "Feature",
  "properties": {
    "addr:full":"Tudor House, Catherine Road Benfleet Essex SS7 1HY",
    "addr:postcode":"ss7 1hy",
    "addr:street":"Catherine Road",
    "iso:country":"GB",
    "sg:address":"Tudor House, Catherine Road",
    "sg:city":"Benfleet",
    "sg:classifiers":[
        {
            "category":"Professional",
            "subcategory":"Computer Services",
            "type":"Services"
        }
    ],
    "sg:phone":"+44 1268 759398",
    "sg:postcode":"SS7 1HY",
    "sg:province":"Essex",
    "sg:tags":[
        "consultant"
    ],
    "wof:name":"Att & C",
    "wof:placetype":"venue"
},
  "geometry": {"coordinates":[0.56264,51.543316],"type":"Point"}
}