{
  "type": "Feature",
  "properties": {
    "iso:country":"GB",
    "sg:address":"144 Port Dundas Road",
    "sg:city":"Glasgow",
    "sg:classifiers":[
        {
            "category":"Communications",
            "subcategory":"Newspaper",
            "type":"Services"
        }
    ],
    "sg:phone":"+44 141 332 9933",
    "sg:postcode":"G4 0HZ",
    "sg:province":"Glasgow City",
    "sg:tags":[
        "magazine"
    ],
    "wof:name":"Sunday Post",
    "wof:placetype":"venue"
},
  "geometry": {"coordinates":[-4.254798,55.869022],"type":"Point"}
}