{
  "type": "Feature",
  "properties": {
    "iso:country":"GB",
    "sg:address":"13 Station Road",
    "sg:city":"Stoke-on-trent",
    "sg:classifiers":[
        {
            "category":"Shopping",
            "subcategory":"Shoes",
            "type":"Retail Goods"
        }
    ],
    "sg:phone":"+44 1782 513347",
    "sg:postcode":"ST8 6BL",
    "sg:province":"Staffordshire",
    "sg:tags":[
        "shop"
    ],
    "wof:name":"Brammer's",
    "wof:placetype":"venue"
},
  "geometry": {"coordinates":[-2.175986,53.117813],"type":"Point"}
}