{
  "type": "Feature",
  "properties": {
    "addr:full":"Unit 1a, Knowle Industrial Estate Braunton Devon EX33 2NE",
    "addr:housenumber":"unit 1a",
    "addr:postcode":"ex33 2ne",
    "addr:street":"Knowle Industrial Estate",
    "iso:country":"GB",
    "sg:address":"Unit 1a, Knowle Industrial Estate",
    "sg:city":"Braunton",
    "sg:classifiers":[
        {
            "category":"Shopping",
            "subcategory":"Discount & Variety Stores",
            "type":"Retail Goods"
        }
    ],
    "sg:phone":"+44 1271 816334",
    "sg:postcode":"EX33 2NE",
    "sg:province":"Devon",
    "sg:tags":[
        "cleaning",
        "supply"
    ],
    "wof:name":"P A C Chemical & Paper Products",
    "wof:placetype":"venue"
},
  "geometry": {"coordinates":[-4.161649,51.109818],"type":"Point"}
}