{
  "type": "Feature",
  "properties": {
    "iso:country":"GB",
    "sg:address":"14 Main Street, Stoneyburn",
    "sg:city":"Bathgate",
    "sg:classifiers":[
        {
            "category":"Bars & Pubs",
            "type":"Food & Drink"
        },
        {
            "category":"Community Center",
            "subcategory":"Social",
            "type":"Public Place"
        }
    ],
    "sg:phone":"+44 1501 762168",
    "sg:postcode":"EH47 8BA",
    "sg:province":"North Lanarkshire",
    "sg:tags":[
        "pubs",
        "house",
        "inn",
        "activity"
    ],
    "wof:name":"THE GREEN TREE",
    "wof:placetype":"venue"
},
  "geometry": {"coordinates":[-3.679202,55.84446],"type":"Point"}
}