{
  "type": "Feature",
  "properties": {
    "iso:country":"GB",
    "sg:address":"15 East Street",
    "sg:city":"Newquay",
    "sg:classifiers":[
        {
            "category":"Shopping",
            "subcategory":"Gifts & Souvenirs",
            "type":"Retail Goods"
        }
    ],
    "sg:postcode":"TR7 1DN",
    "sg:province":"Cornwall",
    "sg:tags":[
        "shop"
    ],
    "wof:name":"Nice Things",
    "wof:placetype":"venue"
},
  "geometry": {"coordinates":[-5.081343,50.414036],"type":"Point"}
}