{
  "type": "Feature",
  "properties": {
    "addr:full":"7 The Downs Altrincham Cheshire WA14 2QD",
    "addr:housenumber":"7",
    "addr:postcode":"wa14 2qd",
    "addr:street":"The Downs",
    "iso:country":"GB",
    "sg:address":"7 The Downs",
    "sg:city":"Altrincham",
    "sg:classifiers":[
        {
            "category":"Communications",
            "subcategory":"Newspaper",
            "type":"Services"
        }
    ],
    "sg:phone":"+44 161 928 5759",
    "sg:postcode":"WA14 2QD",
    "sg:province":"Cheshire",
    "sg:tags":[
        "magazine"
    ],
    "wof:name":"Sale & Altrincham Messenger",
    "wof:placetype":"venue"
},
  "geometry": {"coordinates":[-2.352231,53.384315],"type":"Point"}
}