{
  "type": "Feature",
  "properties": {
    "addr:full":"109 Lots Road London Greater London SW10 0RN",
    "addr:housenumber":"109",
    "addr:postcode":"sw10 0rn",
    "addr:street":"Lots Road",
    "iso:country":"GB",
    "sg:address":"109 Lots Road",
    "sg:city":"London",
    "sg:classifiers":[
        {
            "category":"Professional",
            "subcategory":"Art Services",
            "type":"Services"
        },
        {
            "category":"Shopping",
            "subcategory":"Computers & Home Electronics",
            "type":"Retail Goods"
        }
    ],
    "sg:phone":"+44 20 7351 1755",
    "sg:postcode":"SW10 0RN",
    "sg:province":"Greater London",
    "sg:tags":[
        "interior",
        "designer"
    ],
    "wof:name":"Nordic Style Ltd.",
    "wof:placetype":"venue"
},
  "geometry": {"coordinates":[-0.185354,51.479527],"type":"Point"}
}