{
  "type": "Feature",
  "properties": {
    "iso:country":"GB",
    "sg:address":"24 Broadway",
    "sg:city":"Wolverhampton",
    "sg:classifiers":[
        {
            "category":"Shopping",
            "subcategory":"Pets & Pet Supplies",
            "type":"Retail Goods"
        }
    ],
    "sg:phone":"+44 1902 782690",
    "sg:postcode":"WV10 8EB",
    "sg:province":"Staffordshire",
    "wof:name":"Fairview Pets",
    "wof:placetype":"venue"
},
  "geometry": {"coordinates":[-2.115424,52.623016],"type":"Point"}
}