{
  "type": "Feature",
  "properties": {
    "addr:full":"10 St Peters Hill Stamford Cambridgeshire PE9 2PE",
    "addr:housenumber":"10",
    "addr:postcode":"pe9 2pe",
    "addr:street":"St Peters Hill",
    "iso:country":"GB",
    "sg:address":"10 St Peters Hill",
    "sg:city":"Stamford",
    "sg:classifiers":[
        {
            "category":"Communications",
            "subcategory":"Film & Video Production",
            "type":"Services"
        }
    ],
    "sg:postcode":"PE9 2PE",
    "sg:province":"Cambridgeshire",
    "sg:tags":[
        "recording",
        "studio"
    ],
    "wof:name":"Air Transference & Technologies Ltd.",
    "wof:placetype":"venue"
},
  "geometry": {"coordinates":[-0.482629,52.651573],"type":"Point"}
}