{
  "type": "Feature",
  "properties": {
    "addr:full":"3 The Boardwalk Glasgow South Lanarkshire G75 0YW",
    "addr:housenumber":"3",
    "addr:postcode":"g75 0yw",
    "addr:street":"The Boardwalk",
    "iso:country":"GB",
    "sg:address":"3 The Boardwalk",
    "sg:city":"Glasgow",
    "sg:classifiers":[
        {
            "category":"Restaurant",
            "type":"Food & Drink"
        },
        {
            "category":"Organizations",
            "subcategory":"Membership Organization",
            "type":"Services"
        }
    ],
    "sg:phone":"+44 1355 260681",
    "sg:postcode":"G75 0YW",
    "sg:province":"South Lanarkshire",
    "sg:tags":[
        "club",
        "indian",
        "-"
    ],
    "wof:name":"Atrium Court",
    "wof:placetype":"venue"
},
  "geometry": {"coordinates":[-4.16148,55.751579],"type":"Point"}
}