{
  "type": "Feature",
  "properties": {
    "iso:country":"GB",
    "sg:address":"11 Well Street",
    "sg:city":"Exeter",
    "sg:classifiers":[
        {
            "category":"Professional",
            "subcategory":"Accounting & Tax Preparation",
            "type":"Services"
        }
    ],
    "sg:phone":"+44 1392 437111",
    "sg:postcode":"EX4 6QR",
    "sg:province":"Devon",
    "sg:tags":[
        "accountant"
    ],
    "wof:name":"Small Business Centres (Devon & Cornwall) Ltd.",
    "wof:placetype":"venue"
},
  "geometry": {"coordinates":[-3.523428,50.728752],"type":"Point"}
}