{
  "type": "Feature",
  "properties": {
    "iso:country":"GB",
    "sg:address":"77 Ilderton Road, Bermondsey",
    "sg:city":"London",
    "sg:classifiers":[
        {
            "category":"Building & Trades",
            "subcategory":"Construction",
            "type":"Services"
        }
    ],
    "sg:phone":"+44 20 7232 1553",
    "sg:postcode":"SE16 3JZ",
    "sg:province":"Greater London",
    "sg:tags":[
        "joinery"
    ],
    "wof:name":"Thistle Joinery Ltd.",
    "wof:placetype":"venue"
},
  "geometry": {"coordinates":[-0.0549030006,51.4876327515],"type":"Point"}
}