{
  "type": "Feature",
  "properties": {
    "iso:country":"GB",
    "sg:address":"Former Middle School, Lamb Gdn St.giles",
    "sg:city":"Lincoln",
    "sg:classifiers":[
        {
            "category":"Organizations",
            "subcategory":"Non-profit Organization",
            "type":"Services"
        }
    ],
    "sg:postcode":"LN2 4EG",
    "sg:province":"Lincolnshire",
    "sg:tags":[
        "organisation",
        "voluntary",
        "charity"
    ],
    "wof:name":"St.Giles Enterprise & Access Centre",
    "wof:placetype":"venue"
},
  "geometry": {"coordinates":[-0.52199,53.24556],"type":"Point"}
}