{
  "type": "Feature",
  "properties": {
    "iso:country":"GB",
    "sg:address":"66 Station Road, Waddington",
    "sg:city":"Lincoln",
    "sg:classifiers":[
        {
            "category":"Home & Garden",
            "subcategory":"Garden Supply",
            "type":"Retail Goods"
        }
    ],
    "sg:phone":"+44 1522 723017",
    "sg:postcode":"LN5 9QW",
    "sg:province":"Lincolnshire",
    "sg:tags":[
        "supplier",
        "turf",
        "turfing",
        "contractor"
    ],
    "wof:name":"Lincolnshire Turf Farms",
    "wof:placetype":"venue"
},
  "geometry": {"coordinates":[-0.5503879786,53.1727180481],"type":"Point"}
}