{
  "type": "Feature",
  "properties": {
    "addr:full":"341 West End Lane London Greater London NW6 1RS",
    "addr:housenumber":"341",
    "addr:postcode":"nw6 1rs",
    "addr:street":"West End Lane",
    "iso:country":"GB",
    "sg:address":"341 West End Lane",
    "sg:city":"London",
    "sg:classifiers":[
        {
            "category":"Shopping",
            "subcategory":"News",
            "type":"Retail Goods"
        }
    ],
    "sg:postcode":"NW6 1RS",
    "sg:province":"Greater London",
    "sg:tags":[
        "newsagent"
    ],
    "wof:name":"The Corner Shop",
    "wof:placetype":"venue"
},
  "geometry": {"coordinates":[-0.193064,51.552082],"type":"Point"}
}