{
  "type": "Feature",
  "properties": {
    "iso:country":"GB",
    "sg:address":"Camping & Caravan Site, Hawford",
    "sg:city":"Worcester",
    "sg:classifiers":[
        {
            "category":"Recreation",
            "subcategory":"Campground",
            "type":"Entertainment"
        }
    ],
    "sg:postcode":"WR3 7SE",
    "sg:province":"Worcestershire",
    "sg:tags":[
        "site",
        "camping"
    ],
    "wof:name":"Mill House",
    "wof:placetype":"venue"
},
  "geometry": {"coordinates":[-2.2276799679,52.2375488281],"type":"Point"}
}