{
  "type": "Feature",
  "properties": {
    "addr:full":"18-20 Dickens Avenue South Shields Tyne and Wear NE34 9SY",
    "addr:housenumber":"18-20",
    "addr:postcode":"ne34 9sy",
    "addr:street":"Dickens Avenue",
    "iso:country":"GB",
    "sg:address":"18-20 Dickens Avenue",
    "sg:city":"South Shields",
    "sg:classifiers":[
        {
            "category":"Shopping",
            "subcategory":"News",
            "type":"Retail Goods"
        }
    ],
    "sg:phone":"+44 191 536 2228",
    "sg:postcode":"NE34 9SY",
    "sg:province":"Tyne and Wear",
    "sg:tags":[
        "newsagent"
    ],
    "wof:name":"Carters Newsagency",
    "wof:placetype":"venue"
},
  "geometry": {"coordinates":[-1.4403740168,54.9626998901],"type":"Point"}
}