{
  "type": "Feature",
  "properties": {
    "addr:full":"Talardd, Golden Gro Carmarthen Carmarthenshire SA32 8NN",
    "addr:postcode":"sa32 8nn",
    "addr:street":"Gro;Carmarthenshire",
    "iso:country":"GB",
    "sg:address":"Talardd, Golden Gro",
    "sg:city":"Carmarthen",
    "sg:classifiers":[
        {
            "category":"Farming",
            "subcategory":"Livestock Farm",
            "type":"Manufacturing & Wholesale Goods"
        }
    ],
    "sg:phone":"+44 1558 822418",
    "sg:postcode":"SA32 8NN",
    "sg:province":"Carmarthenshire",
    "sg:tags":[
        "others"
    ],
    "wof:name":"D W G Mainwaring",
    "wof:placetype":"venue"
},
  "geometry": {"coordinates":[-4.0082998276,51.8655586243],"type":"Point"}
}