{
  "type": "Feature",
  "properties": {
    "addr:full":"119 Cozens Road Ware Hertfordshire SG12 7HX",
    "addr:housenumber":"119",
    "addr:postcode":"sg12 7hx",
    "addr:street":"Cozens Road Ware",
    "iso:country":"GB",
    "sg:address":"119 Cozens Road",
    "sg:city":"Ware",
    "sg:classifiers":[
        {
            "category":"Building & Trades",
            "subcategory":"Construction",
            "type":"Services"
        }
    ],
    "sg:postcode":"SG12 7HX",
    "sg:province":"Hertfordshire",
    "sg:tags":[
        "decorator",
        "painter"
    ],
    "wof:name":"A V Wall",
    "wof:placetype":"venue"
},
  "geometry": {"coordinates":[-0.0134509997,51.8165397644],"type":"Point"}
}