{
  "type": "Feature",
  "properties": {
    "iso:country":"GB",
    "sg:address":"10 Sellerdale Rise, Wyke",
    "sg:city":"Bradford",
    "sg:classifiers":[
        {
            "category":"Manufacturing",
            "subcategory":"Wood Products",
            "type":"Manufacturing & Wholesale Goods"
        }
    ],
    "sg:postcode":"BD12 9LL",
    "sg:province":"West Yorkshire",
    "wof:name":"Classic Horse Clothing Ltd",
    "wof:placetype":"venue"
},
  "geometry": {"coordinates":[-1.7649,53.733421],"type":"Point"}
}