{
  "type": "Feature",
  "properties": {
    "iso:country":"GB",
    "sg:address":"5 Dadbrook Close, Cuddington",
    "sg:city":"Aylesbury",
    "sg:classifiers":[
        {
            "category":"Building & Trades",
            "subcategory":"Construction",
            "type":"Services"
        }
    ],
    "sg:postcode":"HP18 0AH",
    "sg:province":"Buckinghamshire",
    "sg:tags":[
        "contractor",
        "paving",
        "driveway"
    ],
    "wof:name":"Bennetts Paving",
    "wof:placetype":"venue"
},
  "geometry": {"coordinates":[-0.929414,51.791859],"type":"Point"}
}