{
  "type": "Feature",
  "properties": {
    "iso:country":"GB",
    "sg:address":"Sidford Farm House, School Street, Sidford",
    "sg:city":"Sidmouth",
    "sg:classifiers":[
        {
            "category":"Food & Beverages",
            "subcategory":"Meat & Fish",
            "type":"Retail Goods"
        }
    ],
    "sg:phone":"+44 1395 512874",
    "sg:postcode":"EX10 9PF",
    "sg:province":"Devon",
    "sg:tags":[
        "butcher"
    ],
    "wof:name":"D & J Baker Butchers",
    "wof:placetype":"venue"
},
  "geometry": {"coordinates":[-3.237619,50.68745],"type":"Point"}
}