{
  "type": "Feature",
  "properties": {
    "addr:full":"77 Rectory Wood Harlow Essex CM20 1RE",
    "addr:housenumber":"77",
    "addr:postcode":"cm20 1re",
    "addr:street":"Rectory Wood",
    "iso:country":"GB",
    "sg:address":"77 Rectory Wood",
    "sg:city":"Harlow",
    "sg:classifiers":[
        {
            "category":"Shopping",
            "subcategory":"Clothing, Apparel, & Fashions",
            "type":"Retail Goods"
        }
    ],
    "sg:phone":"+44 1279 304811",
    "sg:postcode":"CM20 1RE",
    "sg:province":"Essex",
    "sg:tags":[
        "t-shirt"
    ],
    "wof:name":"Logo Wear",
    "wof:placetype":"venue"
},
  "geometry": {"coordinates":[0.088445,51.773796],"type":"Point"}
}