{
  "type": "Feature",
  "properties": {
    "addr:full":"8 Laighcartside St Johnstone Renfrewshire PA5 8DB",
    "addr:housenumber":"8",
    "addr:postcode":"pa5 8db",
    "addr:street":"Laighcartside St;Renfrewshire",
    "iso:country":"GB",
    "sg:address":"8 Laighcartside St",
    "sg:city":"Johnstone",
    "sg:classifiers":[
        {
            "category":"Health Services",
            "subcategory":"Dentist",
            "type":"Services"
        }
    ],
    "sg:phone":"+44 1505 320700",
    "sg:postcode":"PA5 8DB",
    "sg:province":"Renfrewshire",
    "wof:name":"R Secker",
    "wof:placetype":"venue"
},
  "geometry": {"coordinates":[-4.506963,55.83638],"type":"Point"}
}