{
  "type": "Feature",
  "properties": {
    "iso:country":"GB",
    "sg:address":"25 Brown Street, Balloch",
    "sg:city":"Alexandria",
    "sg:classifiers":[
        {
            "category":"Shopping",
            "subcategory":"News",
            "type":"Retail Goods"
        }
    ],
    "sg:postcode":"G83 8HJ",
    "sg:province":"Argyll and Bute",
    "sg:tags":[
        "newsagent"
    ],
    "wof:name":"Newsmarket",
    "wof:placetype":"venue"
},
  "geometry": {"coordinates":[-4.564266,56.002132],"type":"Point"}
}