{
  "type": "Feature",
  "properties": {
    "addr:full":"Buckton Bridlington East Riding of Yorkshire YO15 1DH",
    "addr:postcode":"yo15 1dh",
    "iso:country":"GB",
    "sg:address":"Buckton",
    "sg:city":"Bridlington",
    "sg:classifiers":[
        {
            "category":"Farming",
            "subcategory":"Farm",
            "type":"Manufacturing & Wholesale Goods"
        }
    ],
    "sg:postcode":"YO15 1DH",
    "sg:province":"East Riding of Yorkshire",
    "sg:tags":[
        "mixed",
        "crop"
    ],
    "wof:name":"Anthony E Towse",
    "wof:placetype":"venue"
},
  "geometry": {"coordinates":[-0.191489,54.137547],"type":"Point"}
}