{
  "type": "Feature",
  "properties": {
    "addr:full":"Kinver Street Stourbridge Staffordshire DY8 5AB",
    "addr:postcode":"dy8 5ab",
    "addr:street":"Kinver Street",
    "iso:country":"GB",
    "sg:address":"Kinver Street",
    "sg:city":"Stourbridge",
    "sg:classifiers":[
        {
            "category":"Retail",
            "subcategory":"Auto Repair",
            "type":"Services"
        }
    ],
    "sg:phone":"+44 1384 265076",
    "sg:postcode":"DY8 5AB",
    "sg:province":"Staffordshire",
    "sg:tags":[
        "body",
        "car",
        "repairer"
    ],
    "wof:name":"W P Car Repairs",
    "wof:placetype":"venue"
},
  "geometry": {"coordinates":[-2.1615889072,52.4774436951],"type":"Point"}
}