{
  "type": "Feature",
  "properties": {
    "addr:full":"Holden House, Sissinghurst Road, Biddenden Ashford Kent TN27 8EX",
    "addr:postcode":"tn27 8ex",
    "addr:street":"Sissinghurst Road",
    "iso:country":"GB",
    "sg:address":"Holden House, Sissinghurst Road, Biddenden",
    "sg:city":"Ashford",
    "sg:classifiers":[
        {
            "category":"Professional",
            "subcategory":"Accounting & Tax Preparation",
            "type":"Services"
        }
    ],
    "sg:phone":"+44 1580 291799",
    "sg:postcode":"TN27 8EX",
    "sg:province":"Kent",
    "sg:tags":[
        "accountant"
    ],
    "wof:name":"E G McDonald & Co",
    "wof:placetype":"venue"
},
  "geometry": {"coordinates":[0.6165779829,51.1169166565],"type":"Point"}
}