{
  "type": "Feature",
  "properties": {
    "iso:country":"GB",
    "sg:address":"178 Felixstowe Road",
    "sg:city":"Ipswich",
    "sg:classifiers":[
        {
            "category":"Government",
            "subcategory":"Post Office",
            "type":"Public Place"
        }
    ],
    "sg:phone":"+44 1473 728494",
    "sg:postcode":"IP3 8EE",
    "sg:province":"Suffolk",
    "wof:name":"Felixstowe Road Post Office",
    "wof:placetype":"venue"
},
  "geometry": {"coordinates":[1.18081,52.047829],"type":"Point"}
}