{
  "type": "Feature",
  "properties": {
    "addr:full":"Maidenhayne Farm, Maidenhayne Lane, Musbury Axminster Devon EX13 8AG",
    "addr:postcode":"ex13 8ag",
    "addr:street":"Maidenhayne Lane",
    "iso:country":"GB",
    "sg:address":"Maidenhayne Farm, Maidenhayne Lane, Musbury",
    "sg:city":"Axminster",
    "sg:classifiers":[
        {
            "category":"Farming",
            "subcategory":"Livestock Farm",
            "type":"Manufacturing & Wholesale Goods"
        }
    ],
    "sg:postcode":"EX13 8AG",
    "sg:province":"Devon",
    "sg:tags":[
        "others"
    ],
    "wof:name":"R Johnson",
    "wof:placetype":"venue"
},
  "geometry": {"coordinates":[-3.030104,50.749016],"type":"Point"}
}