{
  "type": "Feature",
  "properties": {
    "iso:country":"GB",
    "sg:address":"Unit 6 Station Road, Reddish",
    "sg:city":"Stockport",
    "sg:classifiers":[
        {
            "category":"Freight",
            "type":"Transportation"
        }
    ],
    "sg:phone":"+44 161 432 9700",
    "sg:postcode":"SK5 6ND",
    "sg:province":"Cheshire",
    "sg:tags":[
        "haulage",
        "road"
    ],
    "wof:name":"Paul Hamlett Transport",
    "wof:placetype":"venue"
},
  "geometry": {"coordinates":[-2.158059,53.44976],"type":"Point"}
}