{
  "type": "Feature",
  "properties": {
    "addr:full":"12 High Street Malmesbury Wiltshire SN16 0LQ",
    "addr:housenumber":"12",
    "addr:postcode":"sn16 0lq",
    "addr:street":"High Street",
    "iso:country":"GB",
    "sg:address":"12 High Street",
    "sg:city":"Malmesbury",
    "sg:classifiers":[
        {
            "category":"Home & Garden",
            "subcategory":"Hardware",
            "type":"Retail Goods"
        }
    ],
    "sg:phone":"+44 1666 823214",
    "sg:postcode":"SN16 0LQ",
    "sg:province":"Wiltshire",
    "wof:name":"E & S Shops Ltd.",
    "wof:placetype":"venue"
},
  "geometry": {"coordinates":[-2.0977880955,51.5836181641],"type":"Point"}
}