{
  "type": "Feature",
  "properties": {
    "addr:full":"1 Bryn Tirion, Nebo Road Llanrwst Conwy LL26 0HL",
    "addr:housenumber":"1",
    "addr:postcode":"llanrwst;ll26 0hl",
    "addr:street":"Bryn Tirion Nebo Road",
    "iso:country":"GB",
    "sg:address":"1 Bryn Tirion, Nebo Road",
    "sg:city":"Llanrwst",
    "sg:classifiers":[
        {
            "category":"Professional",
            "subcategory":"Computer Services",
            "type":"Services"
        }
    ],
    "sg:phone":"+44 1492 641548",
    "sg:postcode":"LL26 0HL",
    "sg:province":"Conwy",
    "sg:tags":[
        "system",
        "software"
    ],
    "wof:name":"Cavalier Software",
    "wof:placetype":"venue"
},
  "geometry": {"coordinates":[-3.7977,53.137661],"type":"Point"}
}