{
  "type": "Feature",
  "properties": {
    "addr:full":"80 Gorsewood Rd Liverpool Merseyside L25 2QW",
    "addr:housenumber":"80",
    "addr:postcode":"l25 2qw",
    "addr:street":"Gorsewood Rd",
    "iso:country":"GB",
    "sg:address":"80 Gorsewood Rd",
    "sg:city":"Liverpool",
    "sg:classifiers":[
        {
            "category":"Shopping",
            "subcategory":"Party Supplies",
            "type":"Retail Goods"
        }
    ],
    "sg:postcode":"L25 2QW",
    "sg:province":"Merseyside",
    "sg:tags":[
        "inflatables",
        "bouncy",
        "castle"
    ],
    "wof:name":"Niblock,Paul,",
    "wof:placetype":"venue"
},
  "geometry": {"coordinates":[-2.86078,53.386513],"type":"Point"}
}