{
  "type": "Feature",
  "properties": {
    "addr:full":"77 Pound Road Banstead Surrey SM7 2HS",
    "addr:housenumber":"77",
    "addr:postcode":"sm7 2hs",
    "addr:street":"Pound Road",
    "iso:country":"GB",
    "sg:address":"77 Pound Road",
    "sg:city":"Banstead",
    "sg:classifiers":[
        {
            "category":"Health Services",
            "subcategory":"Dentist",
            "type":"Services"
        }
    ],
    "sg:phone":"+44 1737 362273",
    "sg:postcode":"SM7 2HS",
    "sg:province":"Surrey",
    "sg:tags":[
        "technician",
        "dental"
    ],
    "wof:name":"Andrew Dale Dental Studios",
    "wof:placetype":"venue"
},
  "geometry": {"coordinates":[-0.206626,51.315212],"type":"Point"}
}