{
  "type": "Feature",
  "properties": {
    "iso:country":"GB",
    "sg:address":"Holly Hill Drive",
    "sg:city":"Banstead",
    "sg:classifiers":[
        {
            "category":"Social Services",
            "subcategory":"Retirement Home",
            "type":"Services"
        }
    ],
    "sg:phone":"+44 1737 356685",
    "sg:postcode":"SM7 2BD",
    "sg:province":"Surrey",
    "sg:tags":[
        "rest"
    ],
    "wof:name":"Roseacre",
    "wof:placetype":"venue"
},
  "geometry": {"coordinates":[-0.201335,51.316883],"type":"Point"}
}