{
  "type": "Feature",
  "properties": {
    "iso:country":"GB",
    "sg:address":"The Old Bakery, Hawk Lane, Battlesbridge",
    "sg:city":"Wickford",
    "sg:classifiers":[
        {
            "category":"Home & Garden",
            "subcategory":"Building Materials",
            "type":"Retail Goods"
        }
    ],
    "sg:phone":"+44 1268 732184",
    "sg:postcode":"SS11 7RL",
    "sg:province":"Essex",
    "sg:tags":[
        "fencing"
    ],
    "wof:name":"Jack Stock Essex Fencing",
    "wof:placetype":"venue"
},
  "geometry": {"coordinates":[0.570253,51.622868],"type":"Point"}
}