{
  "type": "Feature",
  "properties": {
    "iso:country":"GB",
    "sg:address":"The Quay",
    "sg:city":"Burnham-on-crouch",
    "sg:classifiers":[
        {
            "category":"Farming",
            "subcategory":"Fish & Marine Products",
            "type":"Manufacturing & Wholesale Goods"
        }
    ],
    "sg:phone":"+44 1621 785051",
    "sg:postcode":"CM0 8AS",
    "sg:province":"Essex",
    "sg:tags":[
        "fishmonger"
    ],
    "wof:name":"Dengie Shellfish",
    "wof:placetype":"venue"
},
  "geometry": {"coordinates":[0.81813,51.624695],"type":"Point"}
}