{
  "type": "Feature",
  "properties": {
    "addr:full":"34 Caerphilly Road, Bassaleg Newport Caerphilly NP10 8LE",
    "addr:housenumber":"34",
    "addr:postcode":"np10 8le",
    "addr:street":"Caerphilly Road",
    "iso:country":"GB",
    "sg:address":"34 Caerphilly Road, Bassaleg",
    "sg:city":"Newport",
    "sg:classifiers":[
        {
            "category":"Government",
            "subcategory":"Post Office",
            "type":"Public Place"
        }
    ],
    "sg:postcode":"NP10 8LE",
    "sg:province":"Caerphilly",
    "wof:name":"Bassaleg Post Office",
    "wof:placetype":"venue"
},
  "geometry": {"coordinates":[-3.0625669956,51.5781784058],"type":"Point"}
}