{
  "type": "Feature",
  "properties": {
    "iso:country":"GB",
    "sg:address":"13 Easterhouse Township Centre, Shandwick Square",
    "sg:city":"Glasgow",
    "sg:classifiers":[
        {
            "category":"Cinema",
            "subcategory":"Movie Rental",
            "type":"Entertainment"
        }
    ],
    "sg:phone":"+44 141 880 8726",
    "sg:postcode":"G34 9DT",
    "sg:province":"Glasgow City",
    "sg:tags":[
        "video",
        "library"
    ],
    "wof:name":"Azad Video",
    "wof:placetype":"venue"
},
  "geometry": {"coordinates":[-4.12194,55.867329],"type":"Point"}
}