{
  "type": "Feature",
  "properties": {
    "iso:country":"GB",
    "sg:address":"11 Acorn Road",
    "sg:city":"Newcastle-upon-tyne",
    "sg:classifiers":[
        {
            "category":"Personal",
            "subcategory":"Shoe Repair & Shine",
            "type":"Services"
        },
        {
            "category":"Shopping",
            "subcategory":"Shoes",
            "type":"Retail Goods"
        }
    ],
    "sg:phone":"+44 191 281 2467",
    "sg:postcode":"NE2 2DJ",
    "sg:province":"Tyne and Wear",
    "wof:name":"E H Martyn",
    "wof:placetype":"venue"
},
  "geometry": {"coordinates":[-1.6044579744,54.992603302],"type":"Point"}
}