{
  "type": "Feature",
  "properties": {
    "addr:full":"Wirral Metropolitan College, Borough Rd Birkenhead Merseyside CH42 9QD",
    "addr:postcode":"ch42 9qd",
    "addr:street":"Borough Rd",
    "iso:country":"GB",
    "sg:address":"Wirral Metropolitan College, Borough Rd",
    "sg:city":"Birkenhead",
    "sg:classifiers":[
        {
            "category":"Food & Beverages",
            "subcategory":"Bakery",
            "type":"Retail Goods"
        }
    ],
    "sg:postcode":"CH42 9QD",
    "sg:province":"Merseyside",
    "sg:tags":[
        "baker"
    ],
    "wof:name":"Shakeshaft,Glynn,",
    "wof:placetype":"venue"
},
  "geometry": {"coordinates":[-3.0348498821,53.3792991638],"type":"Point"}
}