{
  "type": "Feature",
  "properties": {
    "addr:full":"Paddon Gate, Sutcombe Holsworthy Cornwall EX22 7QG",
    "addr:postcode":"ex22 7qg",
    "addr:street":"Paddon Gate",
    "iso:country":"GB",
    "sg:address":"Paddon Gate, Sutcombe",
    "sg:city":"Holsworthy",
    "sg:classifiers":[
        {
            "category":"Professional",
            "subcategory":"Engineering",
            "type":"Services"
        }
    ],
    "sg:phone":"+44 1409 261425",
    "sg:postcode":"EX22 7QG",
    "sg:province":"Cornwall",
    "sg:tags":[
        "agricultural",
        "engineer"
    ],
    "wof:name":"ALAN SNOW AGRICULTURAL ENGINEERS",
    "wof:placetype":"venue"
},
  "geometry": {"coordinates":[-4.349627018,50.8741149902],"type":"Point"}
}