{
  "type": "Feature",
  "properties": {
    "addr:full":"8 Colleton Cre Exeter Devon EX2 4DG",
    "addr:housenumber":"8",
    "addr:postcode":"ex2 4dg",
    "addr:street":"Colleton Cre",
    "iso:country":"GB",
    "sg:address":"8 Colleton Cre",
    "sg:city":"Exeter",
    "sg:classifiers":[
        {
            "category":"Banks & Credit Unions",
            "subcategory":"Financial Services",
            "type":"Services"
        }
    ],
    "sg:phone":"+44 1392 678220",
    "sg:postcode":"EX2 4DG",
    "sg:province":"Devon",
    "sg:tags":[
        "adviser"
    ],
    "wof:name":"Russell Nash Consultants Ltd.",
    "wof:placetype":"venue"
},
  "geometry": {"coordinates":[-3.528373003,50.7178192139],"type":"Point"}
}