{
  "type": "Feature",
  "properties": {
    "addr:full":"46 Heathcote Road, Whitnash Leamington Spa Warwickshire CV31 2NF",
    "addr:housenumber":"46",
    "addr:postcode":"cv31 2nf",
    "addr:street":"Heathcote Road",
    "iso:country":"GB",
    "sg:address":"46 Heathcote Road, Whitnash",
    "sg:city":"Leamington Spa",
    "sg:classifiers":[
        {
            "category":"Building & Trades",
            "subcategory":"Construction",
            "type":"Services"
        }
    ],
    "sg:phone":"+44 1926 339700",
    "sg:postcode":"CV31 2NF",
    "sg:province":"Warwickshire",
    "sg:tags":[
        "builder"
    ],
    "wof:name":"G H Kennard & Son",
    "wof:placetype":"venue"
},
  "geometry": {"coordinates":[-1.526067,52.268112],"type":"Point"}
}