{
  "type": "Feature",
  "properties": {
    "iso:country":"GB",
    "sg:address":"35-37 Westoe Road",
    "sg:city":"South Shields",
    "sg:classifiers":[
        {
            "category":"Retail",
            "subcategory":"Portrait Studio",
            "type":"Services"
        },
        {
            "category":"Professional",
            "subcategory":"Art Services",
            "type":"Services"
        }
    ],
    "sg:phone":"+44 191 427 6225",
    "sg:postcode":"NE33 4LU",
    "sg:province":"Tyne and Wear",
    "sg:tags":[
        "photographer",
        "commercial"
    ],
    "wof:name":"JOHN HERRING (PHOTOGRAPHY) LTD",
    "wof:placetype":"venue"
},
  "geometry": {"coordinates":[-1.428523,54.992889],"type":"Point"}
}