{
  "type": "Feature",
  "properties": {
    "addr:full":"Mill Lane, South Kirkby Pontefract West Yorkshire WF9 3EZ",
    "addr:postcode":"wf9 3ez",
    "addr:street":"Mill Lane South;West",
    "iso:country":"GB",
    "sg:address":"Mill Lane, South Kirkby",
    "sg:city":"Pontefract",
    "sg:classifiers":[
        {
            "category":"Organizations",
            "subcategory":"Membership Organization",
            "type":"Services"
        }
    ],
    "sg:phone":"+44 1977 642830",
    "sg:postcode":"WF9 3EZ",
    "sg:province":"West Yorkshire",
    "sg:tags":[
        "club",
        "social"
    ],
    "wof:name":"Mill Lane Working Mens Club",
    "wof:placetype":"venue"
},
  "geometry": {"coordinates":[-1.3288340569,53.5920639038],"type":"Point"}
}