{
  "type": "Feature",
  "properties": {
    "addr:full":"535 Oxford Road Reading Berkshire RG30 1HJ",
    "addr:housenumber":"535",
    "addr:postcode":"rg30 1hj",
    "addr:street":"Oxford Road",
    "iso:country":"GB",
    "sg:address":"535 Oxford Road",
    "sg:city":"Reading",
    "sg:classifiers":[
        {
            "category":"Organizations",
            "subcategory":"Community Association",
            "type":"Services"
        },
        {
            "category":"Organizations",
            "subcategory":"Membership Organization",
            "type":"Services"
        }
    ],
    "sg:phone":"+44 118 950 7317",
    "sg:postcode":"RG30 1HJ",
    "sg:province":"Berkshire",
    "sg:tags":[
        "club",
        "social"
    ],
    "wof:name":"West Reading Social Club",
    "wof:placetype":"venue"
},
  "geometry": {"coordinates":[-1.0011270046,51.457824707],"type":"Point"}
}