{
  "type": "Feature",
  "properties": {
    "addr:full":"Musland Farm, Wolfscastle Haverfordwest Pembrokeshire SA62 5NA",
    "addr:postcode":"sa62 5na",
    "addr:street":"Musland",
    "iso:country":"GB",
    "sg:address":"Musland Farm, Wolfscastle",
    "sg:city":"Haverfordwest",
    "sg:classifiers":[
        {
            "category":"Farming",
            "subcategory":"Farm",
            "type":"Manufacturing & Wholesale Goods"
        }
    ],
    "sg:phone":"+44 1348 840370",
    "sg:postcode":"SA62 5NA",
    "sg:province":"Pembrokeshire",
    "sg:tags":[
        "mixed",
        "crop"
    ],
    "wof:name":"K H Evans",
    "wof:placetype":"venue"
},
  "geometry": {"coordinates":[-4.9705729485,51.8971366882],"type":"Point"}
}