{
  "type": "Feature",
  "properties": {
    "addr:full":"Unit 13d Barton Business Park, New Dover Road Canterbury Kent CT1 3AA",
    "addr:housenumber":"13d",
    "addr:postcode":"ct1 3aa",
    "addr:street":"Barton Business Park New Dover Road",
    "iso:country":"GB",
    "sg:address":"Unit 13d Barton Business Park, New Dover Road",
    "sg:city":"Canterbury",
    "sg:classifiers":[
        {
            "category":"Wholesale",
            "subcategory":"Non-durable Goods",
            "type":"Manufacturing & Wholesale Goods"
        }
    ],
    "sg:phone":"+44 1227 785971",
    "sg:postcode":"CT1 3AA",
    "sg:province":"Kent",
    "sg:tags":[
        "carry",
        "cash"
    ],
    "wof:name":"Bell So Trading",
    "wof:placetype":"venue"
},
  "geometry": {"coordinates":[1.07561,51.27597],"type":"Point"}
}