{
  "type": "Feature",
  "properties": {
    "iso:country":"GB",
    "sg:address":"57 Bedford Road, Willington",
    "sg:city":"Bedford",
    "sg:classifiers":[
        {
            "category":"Shopping",
            "type":"Retail Goods"
        }
    ],
    "sg:postcode":"MK44 3PP",
    "sg:province":"Bedfordshire",
    "sg:tags":[
        "bag"
    ],
    "wof:name":"Kempston Paper & Paper Bag Co.",
    "wof:placetype":"venue"
},
  "geometry": {"coordinates":[-0.3370899856,52.1296653748],"type":"Point"}
}