{
  "type": "Feature",
  "properties": {
    "iso:country":"GB",
    "sg:address":"46 Court Street",
    "sg:city":"Haddington",
    "sg:classifiers":[
        {
            "category":"Banks & Credit Unions",
            "subcategory":"Investment Brokerage",
            "type":"Services"
        }
    ],
    "sg:phone":"+44 1620 825867",
    "sg:postcode":"EH41 3NP",
    "sg:province":"East Lothian",
    "wof:name":"McInroy & Wood Ltd.",
    "wof:placetype":"venue"
},
  "geometry": {"coordinates":[-2.7829129696,55.9552001953],"type":"Point"}
}