{
  "type": "Feature",
  "properties": {
    "addr:full":"167-169 Station Road, Stechford Birmingham West Midlands B33 8BA",
    "addr:housenumber":"167-169",
    "addr:postcode":"8ba",
    "addr:street":"Station Road",
    "iso:country":"GB",
    "sg:address":"167-169 Station Road, Stechford",
    "sg:city":"Birmingham",
    "sg:classifiers":[
        {
            "category":"Restaurant",
            "type":"Food & Drink"
        }
    ],
    "sg:phone":"+44 121 785 2775",
    "sg:postcode":"B33 8BA",
    "sg:province":"West Midlands",
    "sg:tags":[
        "indian",
        "-"
    ],
    "wof:name":"Modubon International",
    "wof:placetype":"venue"
},
  "geometry": {"coordinates":[-1.8102869987,52.484046936],"type":"Point"}
}