{
  "type": "Feature",
  "properties": {
    "addr:full":"Unit 7, Whitemoor Court, Nuthall Road Nottingham Nottinghamshire NG8 5BY",
    "addr:housenumber":"unit 7",
    "addr:postcode":"ng8 5by",
    "addr:street":"Whitemoor Court Nuthall Road",
    "iso:country":"GB",
    "sg:address":"Unit 7, Whitemoor Court, Nuthall Road",
    "sg:city":"Nottingham",
    "sg:classifiers":[
        {
            "category":"Sports & Exercise",
            "subcategory":"Golf",
            "type":"Entertainment"
        }
    ],
    "sg:phone":"+44 115 929 1271",
    "sg:postcode":"NG8 5BY",
    "sg:province":"Nottinghamshire",
    "sg:tags":[
        "greeting",
        "card"
    ],
    "wof:name":"Paul White Ltd.",
    "wof:placetype":"venue"
},
  "geometry": {"coordinates":[-1.1949640512,52.9814949036],"type":"Point"}
}