{
  "type": "Feature",
  "properties": {
    "addr:full":"4 Brunell Close, Eddlake Industrial Estate Verwood Dorset BH31 6BA",
    "addr:housenumber":"4",
    "addr:postcode":"bh31 6ba",
    "addr:street":"Brunell Close;Industrial Estate",
    "iso:country":"GB",
    "sg:address":"4 Brunell Close, Eddlake Industrial Estate",
    "sg:city":"Verwood",
    "sg:classifiers":[
        {
            "category":"Recreation",
            "subcategory":"Water Park",
            "type":"Entertainment"
        }
    ],
    "sg:phone":"+44 1202 813413",
    "sg:postcode":"BH31 6BA",
    "sg:province":"Dorset",
    "sg:tags":[
        "sport"
    ],
    "wof:name":"604 Distribution Ltd.",
    "wof:placetype":"venue"
},
  "geometry": {"coordinates":[-1.854054,50.869133],"type":"Point"}
}