{
  "type": "Feature",
  "properties": {
    "addr:full":"Burney Carbis, Roche St Austell Cornwall PL26 8JZ",
    "addr:postcode":"pl26 8jz",
    "addr:street":"Roche St",
    "iso:country":"GB",
    "sg:address":"Burney Carbis, Roche",
    "sg:city":"St Austell",
    "sg:classifiers":[
        {
            "category":"Utilities",
            "subcategory":"Refuse",
            "type":"Services"
        }
    ],
    "sg:phone":"+44 1726 890442",
    "sg:postcode":"PL26 8JZ",
    "sg:province":"Cornwall",
    "sg:tags":[
        "skip",
        "hire"
    ],
    "wof:name":"Roche Mini Skips & Crane Hire",
    "wof:placetype":"venue"
},
  "geometry": {"coordinates":[-4.833774,50.40641],"type":"Point"}
}