{
  "type": "Feature",
  "properties": {
    "iso:country":"GB",
    "sg:address":"83 Forest Road, Piddington",
    "sg:city":"Northampton",
    "sg:classifiers":[
        {
            "category":"Autos & Motor Vehicles",
            "subcategory":"Auto Supplies",
            "type":"Retail Goods"
        }
    ],
    "sg:postcode":"NN7 2DA",
    "sg:province":"Buckinghamshire",
    "sg:tags":[
        "car",
        "audio"
    ],
    "wof:name":"Safe N' Sound",
    "wof:placetype":"venue"
},
  "geometry": {"coordinates":[-0.8244270086,52.1784934998],"type":"Point"}
}