{
  "type": "Feature",
  "properties": {
    "iso:country":"GB",
    "sg:address":"Longburrow, Park Lane, Stokenchurch",
    "sg:city":"High Wycombe",
    "sg:classifiers":[
        {
            "category":"Retail",
            "subcategory":"Event Space",
            "type":"Services"
        },
        {
            "category":"Government",
            "subcategory":"Office",
            "type":"Public Place"
        }
    ],
    "sg:phone":"+44 1494 482403",
    "sg:postcode":"HP14 3TQ",
    "sg:province":"Buckinghamshire",
    "sg:tags":[
        "function",
        "hire",
        "local",
        "room",
        "hall"
    ],
    "wof:name":"STOKENCHURCH PARISH COUNCIL",
    "wof:placetype":"venue"
},
  "geometry": {"coordinates":[-0.899139,51.659168],"type":"Point"}
}