{
  "type": "Feature",
  "properties": {
    "iso:country":"GB",
    "sg:address":"The Firs, Holme Lane, Holme Pierrepont",
    "sg:city":"Nottingham",
    "sg:classifiers":[
        {
            "category":"Building & Trades",
            "subcategory":"Construction",
            "type":"Services"
        }
    ],
    "sg:phone":"+44 115 933 4432",
    "sg:postcode":"NG12 2LD",
    "sg:province":"Nottinghamshire",
    "sg:tags":[
        "joinery"
    ],
    "wof:name":"G Marriott",
    "wof:placetype":"venue"
},
  "geometry": {"coordinates":[-1.064099,52.945923],"type":"Point"}
}