{
  "type": "Feature",
  "properties": {
    "addr:full":"Unit 17 Shillinghill Alloa Clackmannanshire FK10 1JX",
    "addr:housenumber":"unit 17",
    "addr:postcode":"fk10 1jx",
    "addr:street":"Shillinghill",
    "iso:country":"GB",
    "sg:address":"Unit 17 Shillinghill",
    "sg:city":"Alloa",
    "sg:classifiers":[
        {
            "category":"Food & Beverages",
            "subcategory":"Fruits & Vegetables",
            "type":"Retail Goods"
        }
    ],
    "sg:postcode":"FK10 1JX",
    "sg:province":"Clackmannanshire",
    "sg:tags":[
        "greengrocer"
    ],
    "wof:name":"McAleer,Brian,",
    "wof:placetype":"venue"
},
  "geometry": {"coordinates":[-3.789099,56.11599],"type":"Point"}
}