{
  "type": "Feature",
  "properties": {
    "iso:country":"GB",
    "sg:address":"232 Spring Bank",
    "sg:city":"Hull",
    "sg:classifiers":[
        {
            "category":"Travel",
            "subcategory":"Hotels & Motels",
            "type":"Entertainment"
        }
    ],
    "sg:phone":"+44 1482 224479",
    "sg:postcode":"HU3 1LU",
    "sg:province":"East Riding of Yorkshire",
    "wof:name":"Marlborough Hotel",
    "wof:placetype":"venue"
},
  "geometry": {"coordinates":[-0.360377,53.751747],"type":"Point"}
}