{
  "type": "Feature",
  "properties": {
    "iso:country":"GB",
    "sg:address":"28 Kirkaig Avenue",
    "sg:city":"Renfrew",
    "sg:classifiers":[
        {
            "category":"Retail",
            "subcategory":"Driving School",
            "type":"Services"
        }
    ],
    "sg:phone":"+44 141 885 2191",
    "sg:postcode":"PA4 0YH",
    "sg:province":"Renfrewshire",
    "wof:name":"Video Drive",
    "wof:placetype":"venue"
},
  "geometry": {"coordinates":[-4.37333,55.870956],"type":"Point"}
}