{
  "type": "Feature",
  "properties": {
    "addr:full":"Unit 1 Bridge Road, Business Park, 30 Bridge Road Haywards Heath East Sussex RH16 1TX",
    "addr:housenumber":"unit 1;30",
    "addr:postcode":"rh16 1tx",
    "addr:street":"Bridge Road Business Park;Bridge Road",
    "iso:country":"GB",
    "sg:address":"Unit 1 Bridge Road, Business Park, 30 Bridge Road",
    "sg:city":"Haywards Heath",
    "sg:classifiers":[
        {
            "category":"Home & Garden",
            "subcategory":"Hardware",
            "type":"Retail Goods"
        }
    ],
    "sg:postcode":"RH16 1TX",
    "sg:province":"East Sussex",
    "wof:name":"Market Row",
    "wof:placetype":"venue"
},
  "geometry": {"coordinates":[-0.1020469964,50.9966583252],"type":"Point"}
}