{
  "type": "Feature",
  "properties": {
    "iso:country":"GB",
    "sg:address":"23 Horsefair",
    "sg:city":"Kidderminster",
    "sg:classifiers":[
        {
            "category":"Food & Beverages",
            "subcategory":"Meat & Fish",
            "type":"Retail Goods"
        }
    ],
    "sg:phone":"+44 1562 745194",
    "sg:postcode":"DY10 2EP",
    "sg:province":"Staffordshire",
    "sg:tags":[
        "chip"
    ],
    "wof:name":"Mario's",
    "wof:placetype":"venue"
},
  "geometry": {"coordinates":[-2.2464408875,52.392375946],"type":"Point"}
}