{
  "type": "Feature",
  "properties": {
    "addr:full":"55 White Hart Lane, Collier Row Romford Essex RM7 8JB",
    "addr:housenumber":"55",
    "addr:postcode":"rm7 8jb",
    "addr:street":"White Hart Lane",
    "iso:country":"GB",
    "sg:address":"55 White Hart Lane, Collier Row",
    "sg:city":"Romford",
    "sg:classifiers":[
        {
            "category":"Manufacturing",
            "subcategory":"Tools & Machinery",
            "type":"Manufacturing & Wholesale Goods"
        }
    ],
    "sg:phone":"+44 1708 761041",
    "sg:postcode":"RM7 8JB",
    "sg:province":"Essex",
    "sg:tags":[
        "society",
        "friendly"
    ],
    "wof:name":"White Hart Ltd.",
    "wof:placetype":"venue"
},
  "geometry": {"coordinates":[0.15785,51.590874],"type":"Point"}
}