{
  "type": "Feature",
  "properties": {
    "iso:country":"GB",
    "sg:address":"60 Woodham Road",
    "sg:city":"Woking",
    "sg:classifiers":[
        {
            "category":"Travel",
            "subcategory":"Hotels & Motels",
            "type":"Entertainment"
        }
    ],
    "sg:phone":"+44 1483 724255",
    "sg:postcode":"GU21 4EQ",
    "sg:province":"Surrey",
    "sg:tags":[
        "house",
        "guest"
    ],
    "wof:name":"The Dutch",
    "wof:placetype":"venue"
},
  "geometry": {"coordinates":[-0.548033,51.332462],"type":"Point"}
}