{
  "type": "Feature",
  "properties": {
    "addr:full":"189 High Street Egham Surrey TW20 9ED",
    "addr:housenumber":"189",
    "addr:postcode":"tw20 9ed",
    "addr:street":"High Street",
    "iso:country":"GB",
    "sg:address":"189 High Street",
    "sg:city":"Egham",
    "sg:classifiers":[
        {
            "category":"Banks & Credit Unions",
            "subcategory":"Financial Services",
            "type":"Services"
        }
    ],
    "sg:phone":"+44 1784 437611",
    "sg:postcode":"TW20 9ED",
    "sg:province":"Surrey",
    "sg:tags":[
        "adviser"
    ],
    "wof:name":"Regency Investment Services (Surrey) Ltd.",
    "wof:placetype":"venue"
},
  "geometry": {"coordinates":[-0.5447340012,51.4326400757],"type":"Point"}
}