{
  "type": "Feature",
  "properties": {
    "iso:country":"GB",
    "sg:address":"P O Box 1008",
    "sg:city":"Pulborough",
    "sg:classifiers":[
        {
            "category":"Organizations",
            "subcategory":"Non-profit Organization",
            "type":"Services"
        }
    ],
    "sg:phone":"+44 1798 813932",
    "sg:postcode":"RH20 3YJ",
    "sg:province":"West Sussex",
    "sg:tags":[
        "organisation",
        "voluntary",
        "charity"
    ],
    "wof:name":"Mary Howell Trust For Cancer Prevention",
    "wof:placetype":"venue"
},
  "geometry": {"coordinates":[-0.511879,50.957077],"type":"Point"}
}