{
  "type": "Feature",
  "properties": {
    "addr:full":"Belle Isle, Haworth Keighley North Yorkshire BD22 8PB",
    "addr:postcode":"bd22 8pb",
    "addr:street":"Isle",
    "iso:country":"GB",
    "sg:address":"Belle Isle, Haworth",
    "sg:city":"Keighley",
    "sg:classifiers":[
        {
            "category":"Travel",
            "subcategory":"Hotels & Motels",
            "type":"Entertainment"
        }
    ],
    "sg:phone":"+44 1535 646814",
    "sg:postcode":"BD22 8PB",
    "sg:province":"North Yorkshire",
    "sg:tags":[
        "house",
        "guest"
    ],
    "wof:name":"Woodlands Grange Hotel",
    "wof:placetype":"venue"
},
  "geometry": {"coordinates":[-1.95540905,53.8310852051],"type":"Point"}
}