{
  "type": "Feature",
  "properties": {
    "iso:country":"GB",
    "sg:address":"Clock Mill, Upper Mill Street",
    "sg:city":"Tillicoultry",
    "sg:classifiers":[
        {
            "category":"Social Services",
            "subcategory":"Job Training",
            "type":"Services"
        }
    ],
    "sg:phone":"+44 1259 755255",
    "sg:postcode":"FK13 6AX",
    "sg:province":"Clackmannanshire",
    "sg:tags":[
        "translator",
        "interpreter"
    ],
    "wof:name":"Quality Documentation Solutions",
    "wof:placetype":"venue"
},
  "geometry": {"coordinates":[-3.742110014,56.1532669067],"type":"Point"}
}