{
  "type": "Feature",
  "properties": {
    "addr:full":"Braewood House, The Priory, Horsley Stroud Gloucestershire GL6 0QR",
    "addr:housenumber":"the",
    "addr:postcode":"gl6 0qr",
    "iso:country":"GB",
    "sg:address":"Braewood House, The Priory, Horsley",
    "sg:city":"Stroud",
    "sg:classifiers":[
        {
            "category":"Home & Garden",
            "subcategory":"Home Furnishings",
            "type":"Retail Goods"
        }
    ],
    "sg:postcode":"GL6 0QR",
    "sg:province":"Gloucestershire",
    "sg:tags":[
        "patio",
        "furniture"
    ],
    "wof:name":"Greenaway Designs",
    "wof:placetype":"venue"
},
  "geometry": {"coordinates":[-2.234274,51.681034],"type":"Point"}
}