{
  "type": "Feature",
  "properties": {
    "addr:full":"6 Sutton Park Road Kidderminster Staffordshire DY11 6LB",
    "addr:housenumber":"6",
    "addr:postcode":"dy11 6lb",
    "addr:street":"Sutton Park Road",
    "iso:country":"GB",
    "sg:address":"6 Sutton Park Road",
    "sg:city":"Kidderminster",
    "sg:classifiers":[
        {
            "category":"Real Estate",
            "subcategory":"Real Estate Operator",
            "type":"Services"
        }
    ],
    "sg:phone":"+44 1562 633633",
    "sg:postcode":"DY11 6LB",
    "sg:province":"Staffordshire",
    "sg:tags":[
        "letting",
        "agent"
    ],
    "wof:name":"Home Line Lettings",
    "wof:placetype":"venue"
},
  "geometry": {"coordinates":[-2.260844,52.376205],"type":"Point"}
}