{
  "type": "Feature",
  "properties": {
    "addr:full":"22 Dukes Way, Teeside Industrial Estate, Thornaby Stockton-on-tees Durham TS17 9LT",
    "addr:housenumber":"22",
    "addr:postcode":"ts17 9lt",
    "addr:street":"Dukes Way Teeside Industrial Estate",
    "iso:country":"GB",
    "sg:address":"22 Dukes Way, Teeside Industrial Estate, Thornaby",
    "sg:city":"Stockton-on-tees",
    "sg:classifiers":[
        {
            "category":"Professional",
            "subcategory":"Engineering",
            "type":"Services"
        }
    ],
    "sg:phone":"+44 1642 750303",
    "sg:postcode":"TS17 9LT",
    "sg:province":"Durham",
    "wof:name":"Bowater Engineering Ltd.",
    "wof:placetype":"venue"
},
  "geometry": {"coordinates":[-1.296511,54.525074],"type":"Point"}
}