{
  "type": "Feature",
  "properties": {
    "addr:full":"25 St Athan Close, Bowerhill Melksham Wiltshire SN12 6XP",
    "addr:housenumber":"25",
    "addr:postcode":"sn12 6xp",
    "addr:street":"St Athan Close",
    "iso:country":"GB",
    "sg:address":"25 St Athan Close, Bowerhill",
    "sg:city":"Melksham",
    "sg:classifiers":[
        {
            "category":"Home & Garden",
            "subcategory":"Building Materials",
            "type":"Retail Goods"
        }
    ],
    "sg:phone":"+44 1225 791793",
    "sg:postcode":"SN12 6XP",
    "sg:province":"Wiltshire",
    "sg:tags":[
        "garage",
        "door"
    ],
    "wof:name":"Garage Door Associates",
    "wof:placetype":"venue"
},
  "geometry": {"coordinates":[-2.123004,51.353004],"type":"Point"}
}