{
  "type": "Feature",
  "properties": {
    "addr:full":"Great Western Rd Maida Vale Greater London W9 3NW",
    "addr:postcode":"w9 3nw",
    "addr:street":"Great Western Rd",
    "iso:country":"GB",
    "sg:address":"Great Western Rd",
    "sg:city":"Maida Vale",
    "sg:classifiers":[
        {
            "category":"Home & Garden",
            "subcategory":"Building Materials",
            "type":"Retail Goods"
        }
    ],
    "sg:phone":"+44 20 7229 6260",
    "sg:postcode":"W9 3NW",
    "sg:province":"Greater London",
    "sg:tags":[
        "ready",
        "mixed",
        "concrete"
    ],
    "wof:name":"Tarmac Topmix Ltd",
    "wof:placetype":"venue"
},
  "geometry": {"coordinates":[-0.1952590048,51.5258712769],"type":"Point"}
}