{
  "type": "Feature",
  "properties": {
    "iso:country":"GB",
    "sg:address":"Thames House Roentgen Road",
    "sg:city":"Basingstoke",
    "sg:classifiers":[
        {
            "category":"Utilities",
            "subcategory":"Fuel Oil & Lpg",
            "type":"Services"
        }
    ],
    "sg:phone":"+44 845 723 6005",
    "sg:postcode":"RG24 8NT",
    "sg:province":"Hampshire",
    "sg:tags":[
        "distributor"
    ],
    "wof:name":"Brtish Bensal",
    "wof:placetype":"venue"
},
  "geometry": {"coordinates":[-1.062637,51.272579],"type":"Point"}
}