{
  "type": "Feature",
  "properties": {
    "addr:full":"132 Alum Rock Road, Alum Rock Birmingham West Midlands B8 1HU",
    "addr:housenumber":"132",
    "addr:postcode":"b8 1hu",
    "addr:street":"Alum Rock Road",
    "iso:country":"GB",
    "sg:address":"132 Alum Rock Road, Alum Rock",
    "sg:city":"Birmingham",
    "sg:classifiers":[
        {
            "category":"Autos & Motor Vehicles",
            "subcategory":"Auto Supplies",
            "type":"Retail Goods"
        }
    ],
    "sg:phone":"+44 121 327 1114",
    "sg:postcode":"B8 1HU",
    "sg:province":"West Midlands",
    "sg:tags":[
        "tyre"
    ],
    "wof:name":"Mohammed Qubir",
    "wof:placetype":"venue"
},
  "geometry": {"coordinates":[-1.853221,52.489735],"type":"Point"}
}