{
  "type": "Feature",
  "properties": {
    "iso:country":"GB",
    "sg:address":"Unit 2 Abbey Manufacturing Estat, E",
    "sg:city":"Wembley",
    "sg:classifiers":[
        {
            "category":"Utilities",
            "subcategory":"Natural Gas",
            "type":"Services"
        }
    ],
    "sg:phone":"+44 20 8900 0671",
    "sg:postcode":"HA0 1RR",
    "sg:province":"Greater London",
    "sg:tags":[
        "control",
        "energy",
        "management",
        "system"
    ],
    "wof:name":"C P Electronic Ltd",
    "wof:placetype":"venue"
},
  "geometry": {"coordinates":[-0.29167,51.540421],"type":"Point"}
}