{
  "type": "Feature",
  "properties": {
    "addr:full":"7 Clipstone Gardens Sheffield South Yorkshire S9 5EZ",
    "addr:housenumber":"7",
    "addr:postcode":"s9 5ez",
    "addr:street":"Clipstone Gardens",
    "iso:country":"GB",
    "sg:address":"7 Clipstone Gardens",
    "sg:city":"Sheffield",
    "sg:classifiers":[
        {
            "category":"Food & Beverages",
            "subcategory":"Meat & Fish",
            "type":"Retail Goods"
        }
    ],
    "sg:phone":"+44 114 243 1837",
    "sg:postcode":"S9 5EZ",
    "sg:province":"South Yorkshire",
    "sg:tags":[
        "chip"
    ],
    "wof:name":"Patricia Ann Bibby",
    "wof:placetype":"venue"
},
  "geometry": {"coordinates":[-1.4145740271,53.3952293396],"type":"Point"}
}