{
  "type": "Feature",
  "properties": {
    "addr:full":"1 Crouch Close, Bettws Newport Newport NP20 7RW",
    "addr:housenumber":"1",
    "addr:postcode":"np20 7rw",
    "addr:street":"Crouch Close",
    "iso:country":"GB",
    "sg:address":"1 Crouch Close, Bettws",
    "sg:city":"Newport",
    "sg:classifiers":[
        {
            "category":"Health Services",
            "subcategory":"Nursing And Care Facility",
            "type":"Services"
        },
        {
            "category":"Social Services",
            "subcategory":"Retirement Home",
            "type":"Services"
        },
        {
            "category":"Government",
            "subcategory":"Office",
            "type":"Public Place"
        }
    ],
    "sg:phone":"+44 1633 821184",
    "sg:postcode":"NP20 7RW",
    "sg:province":"Newport",
    "sg:tags":[
        "residential",
        "local"
    ],
    "wof:name":"Crouch Close",
    "wof:placetype":"venue"
},
  "geometry": {"coordinates":[-3.030981,51.606537],"type":"Point"}
}