{
  "type": "Feature",
  "properties": {
    "addr:full":"11 Crescent Way Orpington Kent BR6 9LP",
    "addr:housenumber":"11",
    "addr:postcode":"br6 9lp",
    "addr:street":"Crescent Way",
    "iso:country":"GB",
    "sg:address":"11 Crescent Way",
    "sg:city":"Orpington",
    "sg:classifiers":[
        {
            "category":"Fast Food",
            "type":"Food & Drink"
        }
    ],
    "sg:phone":"+44 1689 860089",
    "sg:postcode":"BR6 9LP",
    "sg:province":"Kent",
    "sg:tags":[
        "away",
        "take"
    ],
    "wof:name":"Bamboo",
    "wof:placetype":"venue"
},
  "geometry": {"coordinates":[0.088245,51.360741],"type":"Point"}
}