{
  "type": "Feature",
  "properties": {
    "iso:country":"GB",
    "sg:address":"Long St, Dordon",
    "sg:city":"Tamworth",
    "sg:classifiers":[
        {
            "category":"Organizations",
            "subcategory":"Membership Organization",
            "type":"Services"
        }
    ],
    "sg:postcode":"B78 1PZ",
    "sg:province":"Staffordshire",
    "sg:tags":[
        "club"
    ],
    "wof:name":"Dordon Working Mens Club",
    "wof:placetype":"venue"
},
  "geometry": {"coordinates":[-1.614444,52.602455],"type":"Point"}
}