{
  "type": "Feature",
  "properties": {
    "iso:country":"GB",
    "sg:address":"62 Holbrook Lane",
    "sg:city":"Coventry",
    "sg:classifiers":[
        {
            "category":"Manufacturing",
            "subcategory":"Tools & Machinery",
            "type":"Manufacturing & Wholesale Goods"
        },
        {
            "category":"Insurance",
            "subcategory":"Insurance Agent",
            "type":"Services"
        }
    ],
    "sg:phone":"+44 24 7666 4674",
    "sg:postcode":"CV6 4AB",
    "sg:province":"Warwickshire",
    "sg:tags":[
        "society",
        "friendly"
    ],
    "wof:name":"Westminster Insurance Services",
    "wof:placetype":"venue"
},
  "geometry": {"coordinates":[-1.505764,52.435215],"type":"Point"}
}