{
  "type": "Feature",
  "properties": {
    "addr:full":"15 Wymering Avenue Wolverhampton Staffordshire WV11 2PH",
    "addr:housenumber":"15",
    "addr:postcode":"wv11 2ph",
    "addr:street":"Wymering Avenue",
    "iso:country":"GB",
    "sg:address":"15 Wymering Avenue",
    "sg:city":"Wolverhampton",
    "sg:classifiers":[
        {
            "category":"Building & Trades",
            "subcategory":"Construction",
            "type":"Services"
        }
    ],
    "sg:postcode":"WV11 2PH",
    "sg:province":"Staffordshire",
    "sg:tags":[
        "joiner",
        "carpenter"
    ],
    "wof:name":"G Crook",
    "wof:placetype":"venue"
},
  "geometry": {"coordinates":[-2.0634200573,52.6108169556],"type":"Point"}
}