{
  "type": "Feature",
  "properties": {
    "addr:full":"Stonebridge House, Back Lane, Shearsby Lutterworth Leicestershire LE17 6PN",
    "addr:postcode":"le17 6pn",
    "addr:street":"Back Lane",
    "iso:country":"GB",
    "sg:address":"Stonebridge House, Back Lane, Shearsby",
    "sg:city":"Lutterworth",
    "sg:classifiers":[
        {
            "category":"Professional",
            "subcategory":"Engineering",
            "type":"Services"
        },
        {
            "category":"Building & Trades",
            "subcategory":"Electrical",
            "type":"Services"
        }
    ],
    "sg:phone":"+44 116 247 8077",
    "sg:postcode":"LE17 6PN",
    "sg:province":"Leicestershire",
    "sg:tags":[
        "engineer",
        "electrician",
        "contractor"
    ],
    "wof:name":"Barry Jones Electrical Contractor",
    "wof:placetype":"venue"
},
  "geometry": {"coordinates":[-1.076739,52.510811],"type":"Point"}
}