{
  "type": "Feature",
  "properties": {
    "addr:full":"1 Ladybarn Lane Manchester Greater Manchester M14 6NQ",
    "addr:housenumber":"1",
    "addr:postcode":"m14 6nq",
    "addr:street":"Ladybarn Lane",
    "iso:country":"GB",
    "sg:address":"1 Ladybarn Lane",
    "sg:city":"Manchester",
    "sg:classifiers":[
        {
            "category":"Food & Beverages",
            "subcategory":"Meat & Fish",
            "type":"Retail Goods"
        }
    ],
    "sg:phone":"+44 161 224 2379",
    "sg:postcode":"M14 6NQ",
    "sg:province":"Greater Manchester",
    "sg:tags":[
        "chip"
    ],
    "wof:name":"Battered Cod",
    "wof:placetype":"venue"
},
  "geometry": {"coordinates":[-2.2140450478,53.4416465759],"type":"Point"}
}