{
  "type": "Feature",
  "properties": {
    "addr:full":"1 Rushbrook Close, Longstowe Cambridge Cambridgeshire CB3 7UL",
    "addr:housenumber":"1",
    "addr:postcode":"cb3 7ul",
    "addr:street":"Rushbrook Close",
    "iso:country":"GB",
    "sg:address":"1 Rushbrook Close, Longstowe",
    "sg:city":"Cambridge",
    "sg:classifiers":[
        {
            "category":"Utilities",
            "subcategory":"Fuel Oil & Lpg",
            "type":"Services"
        }
    ],
    "sg:postcode":"CB3 7UL",
    "sg:province":"Cambridgeshire",
    "sg:tags":[
        "coal",
        "smokeless"
    ],
    "wof:name":"H Piper",
    "wof:placetype":"venue"
},
  "geometry": {"coordinates":[-0.08737,52.17841],"type":"Point"}
}