{
  "type": "Feature",
  "properties": {
    "iso:country":"GB",
    "sg:address":"1 Bury Court Cottage, Wigmore",
    "sg:city":"Leominster",
    "sg:classifiers":[
        {
            "category":"Banks & Credit Unions",
            "subcategory":"Investment Brokerage",
            "type":"Services"
        }
    ],
    "sg:postcode":"HR6 9UP",
    "sg:province":"Herefordshire",
    "sg:tags":[
        "contractor"
    ],
    "wof:name":"Stead,Trevor E,",
    "wof:placetype":"venue"
},
  "geometry": {"coordinates":[-2.861084,52.316029],"type":"Point"}
}