{
  "type": "Feature",
  "properties": {
    "addr:full":"Priory Farm Consett Durham DH8 9DW",
    "addr:postcode":"dh8 9dw",
    "addr:street":"Consett",
    "iso:country":"GB",
    "sg:address":"Priory Farm",
    "sg:city":"Consett",
    "sg:classifiers":[
        {
            "category":"Professional",
            "subcategory":"Engineering",
            "type":"Services"
        },
        {
            "category":"Utilities",
            "subcategory":"Natural Gas",
            "type":"Services"
        }
    ],
    "sg:phone":"+44 1207 255365",
    "sg:postcode":"DH8 9DW",
    "sg:province":"Durham",
    "sg:tags":[
        "windmill",
        "wind",
        "power"
    ],
    "wof:name":"Hugh Jennings Ltd.",
    "wof:placetype":"venue"
},
  "geometry": {"coordinates":[-1.835914,54.860989],"type":"Point"}
}