{
  "type": "Feature",
  "properties": {
    "addr:full":"62 Lower Richmond Road, Putney London Greater London SW15 1JT",
    "addr:housenumber":"62",
    "addr:postcode":"sw15 1jt",
    "addr:street":"Lower Richmond Road",
    "iso:country":"GB",
    "sg:address":"62 Lower Richmond Road, Putney",
    "sg:city":"London",
    "sg:classifiers":[
        {
            "category":"Real Estate",
            "subcategory":"Real Estate Agent",
            "type":"Services"
        }
    ],
    "sg:phone":"+44 20 8789 1945",
    "sg:postcode":"SW15 1JT",
    "sg:province":"Greater London",
    "wof:name":"Hugh Henry Ltd.",
    "wof:placetype":"venue"
},
  "geometry": {"coordinates":[-0.2203480005,51.4675559998],"type":"Point"}
}