{
  "type": "Feature",
  "properties": {
    "addr:full":"5 Leicester Street Northwich Cheshire CW9 5LA",
    "addr:housenumber":"5",
    "addr:postcode":"cw9 5la",
    "addr:street":"Leicester Street",
    "iso:country":"GB",
    "sg:address":"5 Leicester Street",
    "sg:city":"Northwich",
    "sg:classifiers":[
        {
            "category":"Shopping",
            "subcategory":"Beauty & Cosmetics",
            "type":"Retail Goods"
        }
    ],
    "sg:postcode":"CW9 5LA",
    "sg:province":"Cheshire",
    "sg:tags":[
        "product"
    ],
    "wof:name":"The Body & Face Place",
    "wof:placetype":"venue"
},
  "geometry": {"coordinates":[-2.511678,53.263462],"type":"Point"}
}