{
  "type": "Feature",
  "properties": {
    "iso:country":"GB",
    "sg:address":"Quinton Lodge, Binswood Avenue",
    "sg:city":"Leamington Spa",
    "sg:classifiers":[
        {
            "category":"Professional",
            "subcategory":"Computer Services",
            "type":"Services"
        }
    ],
    "sg:postcode":"CV32 5RX",
    "sg:province":"Warwickshire",
    "sg:tags":[
        "system",
        "software"
    ],
    "wof:name":"Dash Associates",
    "wof:placetype":"venue"
},
  "geometry": {"coordinates":[-1.535324,52.289139],"type":"Point"}
}