{
  "type": "Feature",
  "properties": {
    "addr:full":"37 St Swithuns Road Bournemouth Dorset BH1 3RG",
    "addr:housenumber":"37",
    "addr:postcode":"bh1 3rg",
    "addr:street":"St Swithuns Road",
    "iso:country":"GB",
    "sg:address":"37 St Swithuns Road",
    "sg:city":"Bournemouth",
    "sg:classifiers":[
        {
            "category":"Retail",
            "subcategory":"Auto Repair",
            "type":"Services"
        }
    ],
    "sg:phone":"+44 1202 553666",
    "sg:postcode":"BH1 3RG",
    "sg:province":"Dorset",
    "sg:tags":[
        "body",
        "car"
    ],
    "wof:name":"Damion Winter",
    "wof:placetype":"venue"
},
  "geometry": {"coordinates":[-1.8612420559,50.7249488831],"type":"Point"}
}