{
  "type": "Feature",
  "properties": {
    "iso:country":"GB",
    "sg:address":"1 Sunniside La",
    "sg:city":"Sunderland",
    "sg:classifiers":[
        {
            "category":"Retail",
            "subcategory":"Event Space",
            "type":"Services"
        }
    ],
    "sg:postcode":"SR6 7UZ",
    "sg:province":"Tyne and Wear",
    "sg:tags":[
        "exhibition",
        "organiser"
    ],
    "wof:name":"Great North Motor Show (The)",
    "wof:placetype":"venue"
},
  "geometry": {"coordinates":[-1.399600029,54.9549598694],"type":"Point"}
}