{
  "type": "Feature",
  "properties": {
    "addr:full":"11 Broad Oak Tunbridge Wells East Sussex TN3 9SD",
    "addr:housenumber":"11",
    "addr:postcode":"tn3 9sd",
    "addr:street":"Broad Oak",
    "iso:country":"GB",
    "sg:address":"11 Broad Oak",
    "sg:city":"Tunbridge Wells",
    "sg:classifiers":[
        {
            "category":"Professional",
            "type":"Services"
        }
    ],
    "sg:phone":"+44 1892 864644",
    "sg:postcode":"TN3 9SD",
    "sg:province":"East Sussex",
    "sg:tags":[
        "interior",
        "furnishers",
        "designer"
    ],
    "wof:name":"Shoe-String Interiors",
    "wof:placetype":"venue"
},
  "geometry": {"coordinates":[0.1855510026,51.111492157],"type":"Point"}
}