{
  "type": "Feature",
  "properties": {
    "iso:country":"GB",
    "sg:address":"44 Lowood Lane, Birstall",
    "sg:city":"Batley",
    "sg:classifiers":[
        {
            "category":"Fast Food",
            "type":"Food & Drink"
        },
        {
            "category":"Food & Beverages",
            "subcategory":"Meat & Fish",
            "type":"Retail Goods"
        }
    ],
    "sg:phone":"+44 1924 444799",
    "sg:postcode":"WF17 9DN",
    "sg:province":"West Yorkshire",
    "sg:tags":[
        "shop",
        "chip"
    ],
    "wof:name":"The Chippy",
    "wof:placetype":"venue"
},
  "geometry": {"coordinates":[-1.6577579975,53.7391624451],"type":"Point"}
}