{
  "type": "Feature",
  "properties": {
    "iso:country":"GB",
    "sg:address":"Victoria Wharf, Riverbank",
    "sg:city":"Newport",
    "sg:classifiers":[
        {
            "category":"Freight",
            "type":"Transportation"
        }
    ],
    "sg:postcode":"NP20 2BS",
    "sg:province":"Newport",
    "sg:tags":[
        "haulage",
        "road"
    ],
    "wof:name":"R J Mason Enterprises Ltd.",
    "wof:placetype":"venue"
},
  "geometry": {"coordinates":[-2.98537,51.582211],"type":"Point"}
}