{
  "type": "Feature",
  "properties": {
    "iso:country":"GB",
    "sg:address":"63 Gladstone Lane",
    "sg:city":"Scarborough",
    "sg:classifiers":[
        {
            "category":"Personal",
            "subcategory":"Beauty Salon",
            "type":"Services"
        }
    ],
    "sg:postcode":"YO12 7BS",
    "sg:province":"North Yorkshire",
    "sg:tags":[
        "unisex",
        "hairdresser"
    ],
    "wof:name":"Jakyta's Hair Design",
    "wof:placetype":"venue"
},
  "geometry": {"coordinates":[-0.414231,54.28159],"type":"Point"}
}