{
  "type": "Feature",
  "properties": {
    "addr:full":"17 Stockfield Road, Acocks Grn Birmingham West Midlands B27 6AP",
    "addr:housenumber":"17",
    "addr:postcode":"b27 6ap",
    "addr:street":"Stockfield Road Acocks Grn",
    "iso:country":"GB",
    "sg:address":"17 Stockfield Road, Acocks Grn",
    "sg:city":"Birmingham",
    "sg:classifiers":[
        {
            "category":"Home & Garden",
            "subcategory":"Hardware",
            "type":"Retail Goods"
        },
        {
            "category":"Shopping",
            "subcategory":"Discount & Variety Stores",
            "type":"Retail Goods"
        }
    ],
    "sg:phone":"+44 121 706 5771",
    "sg:postcode":"B27 6AP",
    "sg:province":"West Midlands",
    "sg:tags":[
        "equipment",
        "material",
        "cleaning",
        "supply"
    ],
    "wof:name":"Dowding & Plummer Ltd.",
    "wof:placetype":"venue"
},
  "geometry": {"coordinates":[-1.831202,52.452606],"type":"Point"}
}