{
  "type": "Feature",
  "properties": {
    "iso:country":"GB",
    "sg:address":"37a Torwood Street",
    "sg:city":"Torquay",
    "sg:classifiers":[
        {
            "category":"Shopping",
            "subcategory":"Pharmacy",
            "type":"Retail Goods"
        }
    ],
    "sg:phone":"+44 1803 292458",
    "sg:postcode":"TQ1 1ED",
    "sg:province":"Devon",
    "sg:tags":[
        "pharmacist",
        "dispensing",
        "chemist"
    ],
    "wof:name":"Quants Pharmacy",
    "wof:placetype":"venue"
},
  "geometry": {"coordinates":[-3.52158,50.461273],"type":"Point"}
}