{
  "type": "Feature",
  "properties": {
    "addr:full":"8 Manor Farm Clo Norwich Norfolk NR8 6EE",
    "addr:housenumber":"8",
    "addr:postcode":"nr8 6ee",
    "addr:street":"Manor Farm Clo Norwich Norfolk",
    "iso:country":"GB",
    "sg:address":"8 Manor Farm Clo",
    "sg:city":"Norwich",
    "sg:classifiers":[
        {
            "category":"Health Services",
            "subcategory":"Doctor",
            "type":"Services"
        }
    ],
    "sg:phone":"+44 1603 867532",
    "sg:postcode":"NR8 6EE",
    "sg:province":"Norfolk",
    "sg:tags":[
        "practitioners"
    ],
    "wof:name":"Leeming, D J",
    "wof:placetype":"venue"
},
  "geometry": {"coordinates":[1.22587502,52.6794128418],"type":"Point"}
}