{
  "type": "Feature",
  "properties": {
    "addr:full":"Barnsley Road, South Elmsall Pontefract West Yorkshire WF9 2QW",
    "addr:postcode":"wf9 2qw",
    "addr:street":"Barnsley Road South;Pontefract West",
    "iso:country":"GB",
    "sg:address":"Barnsley Road, South Elmsall",
    "sg:city":"Pontefract",
    "sg:classifiers":[
        {
            "category":"Shopping",
            "subcategory":"Bicycles & Sporting Goods",
            "type":"Retail Goods"
        }
    ],
    "sg:phone":"+44 1977 642593",
    "sg:postcode":"WF9 2QW",
    "sg:province":"West Yorkshire",
    "sg:tags":[
        "cycle",
        "accessory"
    ],
    "wof:name":"Dons Cycles",
    "wof:placetype":"venue"
},
  "geometry": {"coordinates":[-1.291194,53.594994],"type":"Point"}
}