{
  "type": "Feature",
  "properties": {
    "addr:full":"3 Bessemer Close, Grangetown Cardiff Cardiff CF11 8DL",
    "addr:housenumber":"3",
    "addr:postcode":"cf11 8dl",
    "addr:street":"Bessemer Close",
    "iso:country":"GB",
    "sg:address":"3 Bessemer Close, Grangetown",
    "sg:city":"Cardiff",
    "sg:classifiers":[
        {
            "category":"Professional",
            "subcategory":"Engineering",
            "type":"Services"
        },
        {
            "category":"Building & Trades",
            "subcategory":"Construction",
            "type":"Services"
        }
    ],
    "sg:phone":"+44 29 2034 5826",
    "sg:postcode":"CF11 8DL",
    "sg:province":"Cardiff",
    "sg:tags":[
        "installers",
        "gas",
        "engineer"
    ],
    "wof:name":"Industrial Gases & Medical Pipelines Ltd.",
    "wof:placetype":"venue"
},
  "geometry": {"coordinates":[-3.2018539906,51.4658164978],"type":"Point"}
}