{
  "type": "Feature",
  "properties": {
    "addr:full":"Homefield Farm, Sherford Kingsbridge Devon TQ7 2AT",
    "addr:postcode":"tq7 2at",
    "addr:street":"Sherford",
    "iso:country":"GB",
    "sg:address":"Homefield Farm, Sherford",
    "sg:city":"Kingsbridge",
    "sg:classifiers":[
        {
            "category":"Shopping",
            "subcategory":"Stationery & Office Supplies",
            "type":"Retail Goods"
        }
    ],
    "sg:phone":"+44 1548 531733",
    "sg:postcode":"TQ7 2AT",
    "sg:province":"Devon",
    "sg:tags":[
        "equipment",
        "school"
    ],
    "wof:name":"Kettle of Fish Designs Ltd.",
    "wof:placetype":"venue"
},
  "geometry": {"coordinates":[-3.7150299549,50.2853469849],"type":"Point"}
}