{
  "type": "Feature",
  "properties": {
    "addr:full":"1 Marlborough Hill Harrow Greater London HA1 1TX",
    "addr:housenumber":"1",
    "addr:postcode":"ha1 1tx",
    "addr:street":"Marlborough Hill",
    "iso:country":"GB",
    "sg:address":"1 Marlborough Hill",
    "sg:city":"Harrow",
    "sg:classifiers":[
        {
            "category":"Professional",
            "subcategory":"Printing & Photocopies",
            "type":"Services"
        }
    ],
    "sg:phone":"+44 20 8427 9006",
    "sg:postcode":"HA1 1TX",
    "sg:province":"Greater London",
    "sg:tags":[
        "plate",
        "lithographic",
        "maker"
    ],
    "wof:name":"Imros",
    "wof:placetype":"venue"
},
  "geometry": {"coordinates":[-0.335539,51.590569],"type":"Point"}
}