{
  "type": "Feature",
  "properties": {
    "addr:full":"11a Bell Place Bagshot Berkshire GU19 5NE",
    "addr:housenumber":"11a",
    "addr:postcode":"gu19 5ne",
    "addr:street":"Bell Place",
    "iso:country":"GB",
    "sg:address":"11a Bell Place",
    "sg:city":"Bagshot",
    "sg:classifiers":[
        {
            "category":"Place Of Worship",
            "type":"Public Place"
        }
    ],
    "sg:phone":"+44 1276 473525",
    "sg:postcode":"GU19 5NE",
    "sg:province":"Berkshire",
    "wof:name":"Christ the King R.C Church",
    "wof:placetype":"venue"
},
  "geometry": {"coordinates":[-0.6853320003,51.3611946106],"type":"Point"}
}