{
  "type": "Feature",
  "properties": {
    "iso:country":"GB",
    "sg:address":"Low Grange, Louth Rd",
    "sg:city":"Market Rasen",
    "sg:classifiers":[
        {
            "category":"Farming",
            "subcategory":"Farm",
            "type":"Manufacturing & Wholesale Goods"
        }
    ],
    "sg:phone":"+44 1673 857063",
    "sg:postcode":"LN8 5LF",
    "sg:province":"Lincolnshire",
    "sg:tags":[
        "mixed",
        "crop"
    ],
    "wof:name":"L S Robinson",
    "wof:placetype":"venue"
},
  "geometry": {"coordinates":[-0.333068,53.386787],"type":"Point"}
}