{
  "type": "Feature",
  "properties": {
    "iso:country":"GB",
    "sg:address":"The Lodge Lane",
    "sg:city":"Chalfont St Giles",
    "sg:classifiers":[
        {
            "category":"Retail",
            "subcategory":"Auto Repair",
            "type":"Services"
        }
    ],
    "sg:phone":"+44 1494 762073",
    "sg:postcode":"HP8 4AL",
    "sg:province":"Buckinghamshire",
    "sg:tags":[
        "modification",
        "car",
        "vehicle",
        "commercial",
        "garage"
    ],
    "wof:name":"F Honour & Sons Ltd",
    "wof:placetype":"venue"
},
  "geometry": {"coordinates":[-0.547219,51.661362],"type":"Point"}
}