{
  "type": "Feature",
  "properties": {
    "iso:country":"GB",
    "sg:address":"84a Weston Park",
    "sg:city":"London",
    "sg:classifiers":[
        {
            "category":"Professional",
            "subcategory":"Lawyer & Legal Services",
            "type":"Services"
        }
    ],
    "sg:postcode":"N8 9PP",
    "sg:province":"Greater London",
    "sg:tags":[
        "solicitor"
    ],
    "wof:name":"Richard Poynter",
    "wof:placetype":"venue"
},
  "geometry": {"coordinates":[-0.116132,51.580597],"type":"Point"}
}