{
  "type": "Feature",
  "properties": {
    "addr:full":"200-204 Watford Rd Wembley Greater London HA0 3HA",
    "addr:housenumber":"200-204",
    "addr:postcode":"ha0 3ha",
    "addr:street":"Watford Rd",
    "iso:country":"GB",
    "sg:address":"200-204 Watford Rd",
    "sg:city":"Wembley",
    "sg:classifiers":[
        {
            "category":"Autos & Motor Vehicles",
            "subcategory":"Automobile Sales",
            "type":"Retail Goods"
        }
    ],
    "sg:postcode":"HA0 3HA",
    "sg:province":"Greater London",
    "sg:tags":[
        "car"
    ],
    "wof:name":"Wilkins,Phillip,",
    "wof:placetype":"venue"
},
  "geometry": {"coordinates":[-0.3196890056,51.5616111755],"type":"Point"}
}