{
  "type": "Feature",
  "properties": {
    "addr:full":"12 Fenton Way Basildon Essex SS15 6TY",
    "addr:housenumber":"12",
    "addr:postcode":"ss15 6ty",
    "addr:street":"Fenton Way",
    "iso:country":"GB",
    "sg:address":"12 Fenton Way",
    "sg:city":"Basildon",
    "sg:classifiers":[
        {
            "category":"Professional",
            "subcategory":"Management & Consulting",
            "type":"Services"
        }
    ],
    "sg:phone":"+44 1268 419343",
    "sg:postcode":"SS15 6TY",
    "sg:province":"Essex",
    "sg:tags":[
        "marketing",
        "consultant"
    ],
    "wof:name":"M B O Solutions",
    "wof:placetype":"venue"
},
  "geometry": {"coordinates":[0.4089849889,51.5755271912],"type":"Point"}
}