{
  "type": "Feature",
  "properties": {
    "iso:country":"GB",
    "sg:address":"12 Bradshaw Way",
    "sg:city":"Stafford",
    "sg:classifiers":[
        {
            "category":"Home & Garden",
            "subcategory":"Household Appliances",
            "type":"Retail Goods"
        }
    ],
    "sg:postcode":"ST16 1TH",
    "sg:province":"Staffordshire",
    "sg:tags":[
        "electrical"
    ],
    "wof:name":"Steven A Edwards",
    "wof:placetype":"venue"
},
  "geometry": {"coordinates":[-2.1239230633,52.8300094604],"type":"Point"}
}