{
  "type": "Feature",
  "properties": {
    "iso:country":"GB",
    "sg:address":"14 Third Drove, Little Downham",
    "sg:city":"Ely",
    "sg:classifiers":[
        {
            "category":"Freight",
            "type":"Transportation"
        }
    ],
    "sg:postcode":"CB6 2UE",
    "sg:province":"Cambridgeshire",
    "sg:tags":[
        "haulage",
        "road"
    ],
    "wof:name":"Robert W Yarrow",
    "wof:placetype":"venue"
},
  "geometry": {"coordinates":[0.241555,52.43325],"type":"Point"}
}