{
  "type": "Feature",
  "properties": {
    "addr:full":"76 Bedford Place Southampton Hampshire SO15 2DF",
    "addr:housenumber":"76",
    "addr:postcode":"so15 2df",
    "addr:street":"Bedford Place",
    "iso:country":"GB",
    "sg:address":"76 Bedford Place",
    "sg:city":"Southampton",
    "sg:classifiers":[
        {
            "category":"Arts & Performance",
            "subcategory":"Art Gallery",
            "type":"Entertainment"
        }
    ],
    "sg:phone":"+44 23 8033 0660",
    "sg:postcode":"SO15 2DF",
    "sg:province":"Hampshire",
    "wof:name":"On Line Gallery",
    "wof:placetype":"venue"
},
  "geometry": {"coordinates":[-1.406572,50.912704],"type":"Point"}
}