{
  "type": "Feature",
  "properties": {
    "addr:full":"Basin Road South, Aldrington Basin, Portslade Brighton East Sussex BN41 1WF",
    "addr:postcode":"bn41 1wf",
    "addr:street":"Basin Road South",
    "iso:country":"GB",
    "sg:address":"Basin Road South, Aldrington Basin, Portslade",
    "sg:city":"Brighton",
    "sg:classifiers":[
        {
            "category":"Personal",
            "type":"Services"
        }
    ],
    "sg:phone":"+44 1273 410684",
    "sg:postcode":"BN41 1WF",
    "sg:province":"East Sussex",
    "sg:tags":[
        "delivery"
    ],
    "wof:name":"Brighton Carrier Service",
    "wof:placetype":"venue"
},
  "geometry": {"coordinates":[-0.2126699984,50.8301048279],"type":"Point"}
}