{
  "type": "Feature",
  "properties": {
    "addr:full":"Mayville, Pulford Lane Chester Cheshire CH4 9NN",
    "addr:postcode":"ch4 9nn",
    "addr:street":"Pulford Lane",
    "iso:country":"GB",
    "sg:address":"Mayville, Pulford Lane",
    "sg:city":"Chester",
    "sg:classifiers":[
        {
            "category":"Wholesale",
            "subcategory":"Machinery & Supplies",
            "type":"Manufacturing & Wholesale Goods"
        },
        {
            "category":"Farming",
            "subcategory":"Livestock Farm",
            "type":"Manufacturing & Wholesale Goods"
        },
        {
            "category":"Farming",
            "subcategory":"Farm",
            "type":"Manufacturing & Wholesale Goods"
        }
    ],
    "sg:phone":"+44 1244 660691",
    "sg:postcode":"CH4 9NN",
    "sg:province":"Cheshire",
    "sg:tags":[
        "agricultural",
        "others"
    ],
    "wof:name":"Motor & General Engineers",
    "wof:placetype":"venue"
},
  "geometry": {"coordinates":[-2.933814,53.123676],"type":"Point"}
}