{
  "type": "Feature",
  "properties": {
    "addr:full":"The Bothy, Auchlunies Gardens, Blairs Aberdeen Aberdeen City AB12 5YS",
    "addr:postcode":"ab12 5ys",
    "addr:street":"Auchlunies Gardens Blairs",
    "iso:country":"GB",
    "sg:address":"The Bothy, Auchlunies Gardens, Blairs",
    "sg:city":"Aberdeen",
    "sg:classifiers":[
        {
            "category":"Professional",
            "subcategory":"Testing Lab",
            "type":"Services"
        }
    ],
    "sg:postcode":"AB12 5YS",
    "sg:province":"Aberdeen City",
    "sg:tags":[
        "inspection",
        "calibration"
    ],
    "wof:name":"Alan Ellis Gauges Ltd.",
    "wof:placetype":"venue"
},
  "geometry": {"coordinates":[-2.186516,57.090481],"type":"Point"}
}