{
  "type": "Feature",
  "properties": {
    "addr:full":"Albany Rd Bristol City of Bristol BS6 5LQ",
    "addr:postcode":"bs6 5lq",
    "addr:street":"Albany Rd",
    "iso:country":"GB",
    "sg:address":"Albany Rd",
    "sg:city":"Bristol",
    "sg:classifiers":[
        {
            "category":"Education",
            "subcategory":"School",
            "type":"Public Place"
        },
        {
            "category":"Government",
            "subcategory":"Office",
            "type":"Public Place"
        }
    ],
    "sg:phone":"+44 117 955 3178",
    "sg:postcode":"BS6 5LQ",
    "sg:province":"City of Bristol",
    "sg:tags":[
        "local",
        "authority"
    ],
    "wof:name":"Bristol City Council",
    "wof:placetype":"venue"
},
  "geometry": {"coordinates":[-2.580611,51.467701],"type":"Point"}
}