{
  "type": "Feature",
  "properties": {
    "addr:full":"28 St Johns Road, Belton Great Yarmouth Norfolk NR31 9NS",
    "addr:housenumber":"28",
    "addr:postcode":"nr31 9ns",
    "addr:street":"St Johns Road;Great Yarmouth",
    "iso:country":"GB",
    "sg:address":"28 St Johns Road, Belton",
    "sg:city":"Great Yarmouth",
    "sg:classifiers":[
        {
            "category":"Professional",
            "subcategory":"Engineering",
            "type":"Services"
        },
        {
            "category":"Building & Trades",
            "subcategory":"Electrical",
            "type":"Services"
        }
    ],
    "sg:phone":"+44 1493 782320",
    "sg:postcode":"NR31 9NS",
    "sg:province":"Norfolk",
    "sg:tags":[
        "engineer",
        "electrician",
        "contractor"
    ],
    "wof:name":"C J Electrical",
    "wof:placetype":"venue"
},
  "geometry": {"coordinates":[1.6577329636,52.571182251],"type":"Point"}
}