{
  "type": "Feature",
  "properties": {
    "addr:full":"Clitheroe Works, Clitheroe Street Skipton Lancashire BD23 1SU",
    "addr:postcode":"bd23 1su",
    "addr:street":"Clitheroe Street",
    "iso:country":"GB",
    "sg:address":"Clitheroe Works, Clitheroe Street",
    "sg:city":"Skipton",
    "sg:classifiers":[
        {
            "category":"Manufacturing",
            "subcategory":"Building Materials",
            "type":"Manufacturing & Wholesale Goods"
        }
    ],
    "sg:postcode":"BD23 1SU",
    "sg:province":"Lancashire",
    "sg:tags":[
        "merchant",
        "builder"
    ],
    "wof:name":"Ogden's Building Supplies",
    "wof:placetype":"venue"
},
  "geometry": {"coordinates":[-2.018514,53.960201],"type":"Point"}
}