{
  "type": "Feature",
  "properties": {
    "addr:full":"113 Ebury Street London Greater London SW1W 9QU",
    "addr:housenumber":"113",
    "addr:postcode":"sw1w 9qu",
    "addr:street":"Ebury Street",
    "iso:country":"GB",
    "sg:address":"113 Ebury Street",
    "sg:city":"London",
    "sg:classifiers":[
        {
            "category":"Travel",
            "subcategory":"Hotels & Motels",
            "type":"Entertainment"
        }
    ],
    "sg:phone":"+44 20 7730 4032",
    "sg:postcode":"SW1W 9QU",
    "sg:province":"Greater London",
    "wof:name":"Lynton Hotel",
    "wof:placetype":"venue"
},
  "geometry": {"coordinates":[-0.1493110061,51.493888855],"type":"Point"}
}