{
  "type": "Feature",
  "properties": {
    "addr:full":"1 Brow Road Huddersfield West Yorkshire HD1 4TP",
    "addr:housenumber":"1",
    "addr:postcode":"hd1 4tp",
    "addr:street":"Brow Road",
    "iso:country":"GB",
    "sg:address":"1 Brow Road",
    "sg:city":"Huddersfield",
    "sg:classifiers":[
        {
            "category":"Personal",
            "subcategory":"Beauty Salon",
            "type":"Services"
        }
    ],
    "sg:phone":"+44 1484 426944",
    "sg:postcode":"HD1 4TP",
    "sg:province":"West Yorkshire",
    "sg:tags":[
        "unisex",
        "hairdresser"
    ],
    "wof:name":"S Double Beauty Parlour & Haidresser",
    "wof:placetype":"venue"
},
  "geometry": {"coordinates":[-1.8023790121,53.6422691345],"type":"Point"}
}