{
  "type": "Feature",
  "properties": {
    "iso:country":"GB",
    "sg:address":"35 Hospital Fields Road, Fulford Industrial Estate",
    "sg:city":"York",
    "sg:classifiers":[
        {
            "category":"Wholesale",
            "subcategory":"Electrical",
            "type":"Manufacturing & Wholesale Goods"
        },
        {
            "category":"Shopping",
            "subcategory":"Computers & Home Electronics",
            "type":"Retail Goods"
        }
    ],
    "sg:phone":"+44 1904 640055",
    "sg:postcode":"YO10 4DZ",
    "sg:province":"North Yorkshire",
    "sg:tags":[
        "wholesaler"
    ],
    "wof:name":"Reeds Electrical Supplies",
    "wof:placetype":"venue"
},
  "geometry": {"coordinates":[-1.0780889988,53.9450759888],"type":"Point"}
}