{
  "type": "Feature",
  "properties": {
    "iso:country":"GB",
    "sg:address":"Warley Road, Great Warley",
    "sg:city":"Brentwood",
    "sg:classifiers":[
        {
            "category":"Health Services",
            "subcategory":"Nursing And Care Facility",
            "type":"Services"
        },
        {
            "category":"Social Services",
            "subcategory":"Retirement Home",
            "type":"Services"
        }
    ],
    "sg:phone":"+44 1277 224308",
    "sg:postcode":"CM13 3HX",
    "sg:province":"Essex",
    "sg:tags":[
        "residential"
    ],
    "wof:name":"THE SQUIRRELS CARE CENTRE",
    "wof:placetype":"venue"
},
  "geometry": {"coordinates":[0.29226,51.601135],"type":"Point"}
}