{
  "type": "Feature",
  "properties": {
    "addr:full":"28 Mortimer Street London Greater London W1W 7RD",
    "addr:housenumber":"28",
    "addr:postcode":"w1w 7rd",
    "addr:street":"Mortimer Street",
    "iso:country":"GB",
    "sg:address":"28 Mortimer Street",
    "sg:city":"London",
    "sg:classifiers":[
        {
            "category":"Professional",
            "subcategory":"Employment Agencies",
            "type":"Services"
        }
    ],
    "sg:phone":"+44 20 7637 9227",
    "sg:postcode":"W1W 7RD",
    "sg:province":"Greater London",
    "sg:tags":[
        "consultant"
    ],
    "wof:name":"Media Network Recruitment Consultants (The)",
    "wof:placetype":"venue"
},
  "geometry": {"coordinates":[-0.139557004,51.518119812],"type":"Point"}
}