{
  "type": "Feature",
  "properties": {
    "iso:country":"GB",
    "sg:address":"54/57 London Road",
    "sg:city":"Tunbridge Wells",
    "sg:classifiers":[
        {
            "category":"Travel",
            "subcategory":"Hotels & Motels",
            "type":"Entertainment"
        }
    ],
    "sg:phone":"+44 1892 525580",
    "sg:postcode":"TN1 1DS",
    "sg:province":"Kent",
    "wof:name":"South of England Hotel Services Ltd.",
    "wof:placetype":"venue"
},
  "geometry": {"coordinates":[0.2594259977,51.130279541],"type":"Point"}
}