{
  "type": "Feature",
  "properties": {
    "iso:country":"GB",
    "sg:address":"Cobb Hall Yard, St Pauls Lane",
    "sg:city":"Lincoln",
    "sg:classifiers":[
        {
            "category":"Sports & Exercise",
            "subcategory":"Sports Center",
            "type":"Entertainment"
        }
    ],
    "sg:postcode":"LN1 3AX",
    "sg:province":"Lincolnshire",
    "sg:tags":[
        "shop",
        "good"
    ],
    "wof:name":"Kymano Fitness",
    "wof:placetype":"venue"
},
  "geometry": {"coordinates":[-0.5395,53.235519],"type":"Point"}
}