{
  "type": "Feature",
  "properties": {
    "addr:full":"Central Road Morden Surrey SM4 5SE",
    "addr:postcode":"sm4 5se",
    "addr:street":"Central Road",
    "iso:country":"GB",
    "sg:address":"Central Road",
    "sg:city":"Morden",
    "sg:classifiers":[
        {
            "category":"Education",
            "subcategory":"School",
            "type":"Public Place"
        }
    ],
    "sg:phone":"+44 20 8648 4993",
    "sg:postcode":"SM4 5SE",
    "sg:province":"Surrey",
    "sg:tags":[
        "college"
    ],
    "wof:name":"Phoenix College",
    "wof:placetype":"venue"
},
  "geometry": {"coordinates":[-0.194004,51.394886],"type":"Point"}
}