{
  "type": "Feature",
  "properties": {
    "addr:full":"47 Whitgift Avenue South Croydon Surrey CR2 6AZ",
    "addr:housenumber":"47",
    "addr:postcode":"cr2 6az",
    "addr:street":"Whitgift Avenue",
    "iso:country":"GB",
    "sg:address":"47 Whitgift Avenue",
    "sg:city":"South Croydon",
    "sg:classifiers":[
        {
            "category":"Building & Trades",
            "subcategory":"Construction",
            "type":"Services"
        }
    ],
    "sg:phone":"+44 20 8681 0056",
    "sg:postcode":"CR2 6AZ",
    "sg:province":"Surrey",
    "sg:tags":[
        "builder"
    ],
    "wof:name":"C.T Restorick Ltd",
    "wof:placetype":"venue"
},
  "geometry": {"coordinates":[-0.1058709994,51.3609962463],"type":"Point"}
}