{
  "type": "Feature",
  "properties": {
    "addr:full":"45 George Street Brighton East Sussex BN2 1RJ",
    "addr:housenumber":"45",
    "addr:postcode":"bn2 1rj",
    "addr:street":"George Street",
    "iso:country":"GB",
    "sg:address":"45 George Street",
    "sg:city":"Brighton",
    "sg:classifiers":[
        {
            "category":"Shopping",
            "subcategory":"Bicycles & Sporting Goods",
            "type":"Retail Goods"
        }
    ],
    "sg:phone":"+44 1273 681698",
    "sg:postcode":"BN2 1RJ",
    "sg:province":"East Sussex",
    "sg:tags":[
        "cycle",
        "accessory"
    ],
    "wof:name":"Freedom Bikes",
    "wof:placetype":"venue"
},
  "geometry": {"coordinates":[-0.134143,50.821934],"type":"Point"}
}