{
  "type": "Feature",
  "properties": {
    "addr:full":"120 Queensway, Bletchley Milton Keynes Buckinghamshire MK2 2RH",
    "addr:housenumber":"120",
    "addr:postcode":"mk2 2rh",
    "addr:street":"Queensway",
    "iso:country":"GB",
    "sg:address":"120 Queensway, Bletchley",
    "sg:city":"Milton Keynes",
    "sg:classifiers":[
        {
            "category":"Shopping",
            "subcategory":"Clothing, Apparel, & Fashions",
            "type":"Retail Goods"
        }
    ],
    "sg:phone":"+44 1908 647993",
    "sg:postcode":"MK2 2RH",
    "sg:province":"Buckinghamshire",
    "sg:tags":[
        "ladieswear"
    ],
    "wof:name":"Dorothy Perkins",
    "wof:placetype":"venue"
},
  "geometry": {"coordinates":[-0.7305669785,51.9946289062],"type":"Point"}
}