{
  "type": "Feature",
  "properties": {
    "iso:country":"GB",
    "sg:address":"Higher Hurst Post Office, 169 Kings Road",
    "sg:city":"Ashton-under-lyne",
    "sg:classifiers":[
        {
            "category":"Government",
            "subcategory":"Post Office",
            "type":"Public Place"
        }
    ],
    "sg:phone":"+44 161 330 1709",
    "sg:postcode":"OL6 8HD",
    "sg:province":"Greater Manchester",
    "wof:name":"Higher Hurst Sub Post Office",
    "wof:placetype":"venue"
},
  "geometry": {"coordinates":[-2.079027,53.500542],"type":"Point"}
}