{
  "type": "Feature",
  "properties": {
    "addr:full":"California House, Leathley Road Leeds West Yorkshire LS10 1BG",
    "addr:postcode":"ls10 1bg",
    "addr:street":"Leathley Road",
    "iso:country":"GB",
    "sg:address":"California House, Leathley Road",
    "sg:city":"Leeds",
    "sg:classifiers":[
        {
            "category":"Professional",
            "type":"Services"
        }
    ],
    "sg:postcode":"LS10 1BG",
    "sg:province":"West Yorkshire",
    "sg:tags":[
        "shopfitters"
    ],
    "wof:name":"H B Aluminium Fabrications Ltd.",
    "wof:placetype":"venue"
},
  "geometry": {"coordinates":[-1.5357149839,53.7880134583],"type":"Point"}
}