{
  "type": "Feature",
  "properties": {
    "addr:full":"Barnford Farm, Dalrymple Ayr East Ayrshire KA6 6BA",
    "addr:postcode":"ka6 6ba",
    "addr:street":"Dalrymple;East",
    "iso:country":"GB",
    "sg:address":"Barnford Farm, Dalrymple",
    "sg:city":"Ayr",
    "sg:classifiers":[
        {
            "category":"Farming",
            "subcategory":"Livestock Farm",
            "type":"Manufacturing & Wholesale Goods"
        }
    ],
    "sg:phone":"+44 1292 560327",
    "sg:postcode":"KA6 6BA",
    "sg:province":"East Ayrshire",
    "sg:tags":[
        "others"
    ],
    "wof:name":"David Goldie",
    "wof:placetype":"venue"
},
  "geometry": {"coordinates":[-4.5891208649,55.3982467651],"type":"Point"}
}