{
  "type": "Feature",
  "properties": {
    "addr:full":"60a North Street, Old Town Swindon Wiltshire SN1 3JY",
    "addr:housenumber":"60a",
    "addr:postcode":"sn1 3jy",
    "addr:street":"North Street",
    "iso:country":"GB",
    "sg:address":"60a North Street, Old Town",
    "sg:city":"Swindon",
    "sg:classifiers":[
        {
            "category":"Retail",
            "subcategory":"Auto Repair",
            "type":"Services"
        }
    ],
    "sg:phone":"+44 1793 618810",
    "sg:postcode":"SN1 3JY",
    "sg:province":"Wiltshire",
    "sg:tags":[
        "modification",
        "garage"
    ],
    "wof:name":"J W D Autorite",
    "wof:placetype":"venue"
},
  "geometry": {"coordinates":[-1.779574,51.555256],"type":"Point"}
}