{
  "type": "Feature",
  "properties": {
    "addr:full":"Manor Farm, Shipton Gorge Bridport Dorset DT6 4NJ",
    "addr:postcode":"dt6 4nj",
    "addr:street":"Manor",
    "iso:country":"GB",
    "sg:address":"Manor Farm, Shipton Gorge",
    "sg:city":"Bridport",
    "sg:classifiers":[
        {
            "category":"Building & Trades",
            "subcategory":"Landscaping Services",
            "type":"Services"
        },
        {
            "category":"Banks & Credit Unions",
            "subcategory":"Investment Brokerage",
            "type":"Services"
        }
    ],
    "sg:phone":"+44 1308 897861",
    "sg:postcode":"DT6 4NJ",
    "sg:province":"Dorset",
    "sg:tags":[
        "gardening",
        "contractor"
    ],
    "wof:name":"ROGER SORRELL",
    "wof:placetype":"venue"
},
  "geometry": {"coordinates":[-2.716203928,50.7220802307],"type":"Point"}
}