{
  "type": "Feature",
  "properties": {
    "addr:full":"2-4 Beecholme Av Mitcham Greater London CR4 2HT",
    "addr:housenumber":"2-4",
    "addr:postcode":"cr4 2ht",
    "addr:street":"Av",
    "iso:country":"GB",
    "sg:address":"2-4 Beecholme Av",
    "sg:city":"Mitcham",
    "sg:classifiers":[
        {
            "category":"Social Services",
            "subcategory":"Retirement Home",
            "type":"Services"
        }
    ],
    "sg:phone":"+44 20 8288 9797",
    "sg:postcode":"CR4 2HT",
    "sg:province":"Greater London",
    "sg:tags":[
        "residential",
        "care"
    ],
    "wof:name":"Beecholme House",
    "wof:placetype":"venue"
},
  "geometry": {"coordinates":[-0.1521259993,51.4144325256],"type":"Point"}
}