{
  "type": "Feature",
  "properties": {
    "iso:country":"GB",
    "sg:address":"Queries, Milton Surgery, Millrise Rd",
    "sg:city":"Stoke On Trent",
    "sg:classifiers":[
        {
            "category":"Health Services",
            "subcategory":"Doctor",
            "type":"Services"
        }
    ],
    "sg:phone":"+44 1782 536600",
    "sg:postcode":"ST2 7BW",
    "sg:province":"Staffordshire",
    "sg:tags":[
        "practitioners"
    ],
    "wof:name":"Bartlam, A",
    "wof:placetype":"venue"
},
  "geometry": {"coordinates":[-2.14156,53.049622],"type":"Point"}
}