{
  "type": "Feature",
  "properties": {
    "addr:full":"Wordsworth Crescent Kidderminster Staffordshire DY10 3HA",
    "addr:postcode":"dy10 3ha",
    "addr:street":"Wordsworth Crescent",
    "iso:country":"GB",
    "sg:address":"Wordsworth Crescent",
    "sg:city":"Kidderminster",
    "sg:classifiers":[
        {
            "category":"Education",
            "subcategory":"School",
            "type":"Public Place"
        }
    ],
    "sg:phone":"+44 1562 753934",
    "sg:postcode":"DY10 3HA",
    "sg:province":"Staffordshire",
    "sg:tags":[
        "local",
        "authority"
    ],
    "wof:name":"Offmore First School",
    "wof:placetype":"venue"
},
  "geometry": {"coordinates":[-2.226116,52.388855],"type":"Point"}
}