{
  "type": "Feature",
  "properties": {
    "addr:full":"4 Caludon Road Coventry Warwickshire CV2 4LP",
    "addr:housenumber":"4",
    "addr:postcode":"cv2 4lp",
    "addr:street":"Caludon Road",
    "iso:country":"GB",
    "sg:address":"4 Caludon Road",
    "sg:city":"Coventry",
    "sg:classifiers":[
        {
            "category":"Autos & Motor Vehicles",
            "subcategory":"Automobile Sales",
            "type":"Retail Goods"
        }
    ],
    "sg:phone":"+44 24 7645 8635",
    "sg:postcode":"CV2 4LP",
    "sg:province":"Warwickshire",
    "sg:tags":[
        "car",
        "used"
    ],
    "wof:name":"Andrews Garage",
    "wof:placetype":"venue"
},
  "geometry": {"coordinates":[-1.4861630201,52.4132003784],"type":"Point"}
}