{
  "type": "Feature",
  "properties": {
    "iso:country":"GB",
    "sg:address":"Bank House, 84 High Street, Farnborough Village",
    "sg:city":"Orpington",
    "sg:classifiers":[
        {
            "category":"Health Services",
            "subcategory":"Doctor",
            "type":"Services"
        }
    ],
    "sg:phone":"+44 1689 857691",
    "sg:postcode":"BR6 7BA",
    "sg:province":"Kent",
    "sg:tags":[
        "practitioners"
    ],
    "wof:name":"J Black Surgery",
    "wof:placetype":"venue"
},
  "geometry": {"coordinates":[0.069348,51.3593101501],"type":"Point"}
}