{
  "type": "Feature",
  "properties": {
    "iso:country":"GB",
    "sg:address":"1236 Royston Road",
    "sg:city":"Glasgow",
    "sg:classifiers":[
        {
            "category":"Shopping",
            "subcategory":"Pharmacy",
            "type":"Retail Goods"
        }
    ],
    "sg:phone":"+44 141 770 4063",
    "sg:postcode":"G33 1EX",
    "sg:province":"Glasgow City",
    "sg:tags":[
        "pharmacist",
        "chemist"
    ],
    "wof:name":"D G Tarbet",
    "wof:placetype":"venue"
},
  "geometry": {"coordinates":[-4.191654,55.878597],"type":"Point"}
}