{
  "type": "Feature",
  "properties": {
    "iso:country":"GB",
    "sg:address":"456a Hern Road Ramsey St Marys, Ramsey",
    "sg:city":"Huntingdon",
    "sg:classifiers":[
        {
            "category":"Professional",
            "subcategory":"Engineering",
            "type":"Services"
        }
    ],
    "sg:phone":"+44 1733 844642",
    "sg:postcode":"PE26 2TJ",
    "sg:province":"Cambridgeshire",
    "sg:tags":[
        "agricultural",
        "engineer"
    ],
    "wof:name":"G & J Peck Ltd",
    "wof:placetype":"venue"
},
  "geometry": {"coordinates":[-0.143123,52.511818],"type":"Point"}
}