{
  "type": "Feature",
  "properties": {
    "iso:country":"GB",
    "sg:address":"Within Dacre Lakeside Park, New Rd, Brandesburton",
    "sg:city":"Driffield",
    "sg:classifiers":[
        {
            "category":"Recreation",
            "subcategory":"Water Park",
            "type":"Entertainment"
        }
    ],
    "sg:phone":"+44 1964 544040",
    "sg:postcode":"YO25 8RX",
    "sg:province":"East Riding of Yorkshire",
    "sg:tags":[
        "sport"
    ],
    "wof:name":"Dacre Windsurfing",
    "wof:placetype":"venue"
},
  "geometry": {"coordinates":[-0.3021189868,53.9109992981],"type":"Point"}
}