{
  "type": "Feature",
  "properties": {
    "addr:full":"8 Victoria Road Exmouth Devon EX8 1DL",
    "addr:housenumber":"8",
    "addr:postcode":"ex8 1dl",
    "addr:street":"Victoria Road",
    "iso:country":"GB",
    "sg:address":"8 Victoria Road",
    "sg:city":"Exmouth",
    "sg:classifiers":[
        {
            "category":"Bars & Pubs",
            "type":"Food & Drink"
        }
    ],
    "sg:phone":"+44 1395 225440",
    "sg:postcode":"EX8 1DL",
    "sg:province":"Devon",
    "sg:tags":[
        "pubs",
        "inn"
    ],
    "wof:name":"Reilly's",
    "wof:placetype":"venue"
},
  "geometry": {"coordinates":[-3.415998,50.619297],"type":"Point"}
}