{
  "type": "Feature",
  "properties": {
    "addr:full":"P O Box 251 Hemel Hempstead Hertfordshire HP3 9FX",
    "addr:housenumber":"251",
    "addr:postcode":"hp3 9fx",
    "addr:street":"P O Box;Hempstead",
    "iso:country":"GB",
    "sg:address":"P O Box 251",
    "sg:city":"Hemel Hempstead",
    "sg:classifiers":[
        {
            "category":"Utilities",
            "type":"Services"
        }
    ],
    "sg:phone":"+44 1923 400231",
    "sg:postcode":"HP3 9FX",
    "sg:province":"Hertfordshire",
    "sg:tags":[
        "internet"
    ],
    "wof:name":"Internet-Ads",
    "wof:placetype":"venue"
},
  "geometry": {"coordinates":[-0.4620899856,51.7406997681],"type":"Point"}
}