{
  "type": "Feature",
  "properties": {
    "addr:full":"1 West Mill Wynd Lasswade City of Edinburgh EH18 1LZ",
    "addr:housenumber":"1",
    "addr:postcode":"eh18 1lz",
    "addr:street":"West Mill Wynd",
    "iso:country":"GB",
    "sg:address":"1 West Mill Wynd",
    "sg:city":"Lasswade",
    "sg:classifiers":[
        {
            "category":"Professional",
            "subcategory":"Art Services",
            "type":"Services"
        }
    ],
    "sg:phone":"+44 131 654 2582",
    "sg:postcode":"EH18 1LZ",
    "sg:province":"City of Edinburgh",
    "sg:tags":[
        "graphic",
        "designer"
    ],
    "wof:name":"Adam Design",
    "wof:placetype":"venue"
},
  "geometry": {"coordinates":[-3.116271,55.881798],"type":"Point"}
}