{
  "type": "Feature",
  "properties": {
    "addr:full":"4 Mansion Avenue Port Glasgow Inverclyde PA14 6QF",
    "addr:housenumber":"4",
    "addr:postcode":"pa14 6qf",
    "addr:street":"Mansion Avenue",
    "iso:country":"GB",
    "sg:address":"4 Mansion Avenue",
    "sg:city":"Port Glasgow",
    "sg:classifiers":[
        {
            "category":"Farming",
            "subcategory":"Nursery",
            "type":"Manufacturing & Wholesale Goods"
        }
    ],
    "sg:phone":"+44 1475 700500",
    "sg:postcode":"PA14 6QF",
    "sg:province":"Inverclyde",
    "sg:tags":[
        "creche"
    ],
    "wof:name":"Treetops Community Nursery",
    "wof:placetype":"venue"
},
  "geometry": {"coordinates":[-4.6506299973,55.9288101196],"type":"Point"}
}