{
  "type": "Feature",
  "properties": {
    "iso:country":"GB",
    "sg:address":"9 Gilbert Close",
    "sg:city":"Rayleigh",
    "sg:classifiers":[
        {
            "category":"Organizations",
            "subcategory":"Non-profit Organization",
            "type":"Services"
        }
    ],
    "sg:phone":"+44 1268 778997",
    "sg:postcode":"SS6 8QR",
    "sg:province":"Essex",
    "sg:tags":[
        "organisation",
        "voluntary",
        "charity"
    ],
    "wof:name":"Royal National Institute for the Blind",
    "wof:placetype":"venue"
},
  "geometry": {"coordinates":[0.622667,51.585396],"type":"Point"}
}