{
  "type": "Feature",
  "properties": {
    "iso:country":"GB",
    "sg:address":"33 Woollham Rd",
    "sg:city":"Telford",
    "sg:classifiers":[
        {
            "category":"Retail",
            "subcategory":"Driving School",
            "type":"Services"
        }
    ],
    "sg:phone":"+44 1952 403345",
    "sg:postcode":"TF1 2LP",
    "sg:province":"Shropshire",
    "wof:name":"Telford Driver Training",
    "wof:placetype":"venue"
},
  "geometry": {"coordinates":[-2.4982700348,52.6944313049],"type":"Point"}
}