{
  "type": "Feature",
  "properties": {
    "addr:full":"282 Hagley Road West Oldbury West Midlands B68 0NR",
    "addr:housenumber":"282",
    "addr:postcode":"b68 0nr",
    "addr:street":"Hagley Road West Oldbury",
    "iso:country":"GB",
    "sg:address":"282 Hagley Road West",
    "sg:city":"Oldbury",
    "sg:classifiers":[
        {
            "category":"Personal",
            "subcategory":"Beauty Salon",
            "type":"Services"
        }
    ],
    "sg:postcode":"B68 0NR",
    "sg:province":"West Midlands",
    "sg:tags":[
        "unisex",
        "hairdresser"
    ],
    "wof:name":"Demay Hair Art",
    "wof:placetype":"venue"
},
  "geometry": {"coordinates":[-1.999779,52.468941],"type":"Point"}
}