{
  "type": "Feature",
  "properties": {
    "addr:full":"49 Vasterne Close, Purton Swindon Wiltshire SN5 4EZ",
    "addr:housenumber":"49",
    "addr:postcode":"sn5 4ez",
    "addr:street":"Vasterne Close",
    "iso:country":"GB",
    "sg:address":"49 Vasterne Close, Purton",
    "sg:city":"Swindon",
    "sg:classifiers":[
        {
            "category":"Building & Trades",
            "subcategory":"Landscaping Services",
            "type":"Services"
        },
        {
            "category":"Building & Trades",
            "subcategory":"Construction",
            "type":"Services"
        }
    ],
    "sg:postcode":"SN5 4EZ",
    "sg:province":"Wiltshire",
    "sg:tags":[
        "gardening",
        "decorator",
        "painter"
    ],
    "wof:name":"Home & Garden Maintenance",
    "wof:placetype":"venue"
},
  "geometry": {"coordinates":[-1.8728510141,51.5916099548],"type":"Point"}
}