{
  "type": "Feature",
  "properties": {
    "addr:full":"Heart Of The City Lancaster Lancashire LA1 1HA",
    "addr:postcode":"la1 1ha",
    "iso:country":"GB",
    "sg:address":"Heart Of The City",
    "sg:city":"Lancaster",
    "sg:classifiers":[
        {
            "category":"Organizations",
            "subcategory":"Non-profit Organization",
            "type":"Services"
        }
    ],
    "sg:phone":"+44 1524 32737",
    "sg:postcode":"LA1 1HA",
    "sg:province":"Lancashire",
    "sg:tags":[
        "organisation",
        "voluntary",
        "charity"
    ],
    "wof:name":"Y M C A",
    "wof:placetype":"venue"
},
  "geometry": {"coordinates":[-2.799029,54.044537],"type":"Point"}
}