{
  "type": "Feature",
  "properties": {
    "addr:full":"1 The Swan Centre, Rosemary Road London Greater London SW17 0AR",
    "addr:housenumber":"1",
    "addr:postcode":"sw17 0ar",
    "addr:street":"The;Rosemary Road",
    "iso:country":"GB",
    "sg:address":"1 The Swan Centre, Rosemary Road",
    "sg:city":"London",
    "sg:classifiers":[
        {
            "category":"Home & Garden",
            "subcategory":"Hardware",
            "type":"Retail Goods"
        },
        {
            "category":"Travel",
            "subcategory":"Bed & Breakfast",
            "type":"Entertainment"
        }
    ],
    "sg:phone":"+44 20 8879 7599",
    "sg:postcode":"SW17 0AR",
    "sg:province":"Greater London",
    "sg:tags":[
        "ladder",
        "tarpaulin"
    ],
    "wof:name":"M & S Supplies",
    "wof:placetype":"venue"
},
  "geometry": {"coordinates":[-0.1884,51.433651],"type":"Point"}
}