{
  "type": "Feature",
  "properties": {
    "iso:country":"GB",
    "sg:address":"232 Mare Street",
    "sg:city":"London",
    "sg:classifiers":[
        {
            "category":"Professional",
            "subcategory":"Art Services",
            "type":"Services"
        }
    ],
    "sg:postcode":"E8 1HE",
    "sg:province":"Greater London",
    "sg:tags":[
        "carver",
        "sculptor"
    ],
    "wof:name":"Sculpture Culture",
    "wof:placetype":"venue"
},
  "geometry": {"coordinates":[-0.055149,51.544231],"type":"Point"}
}