{
  "type": "Feature",
  "properties": {
    "iso:country":"GB",
    "sg:address":"Mannercey Cottage, Witchfield, Shelf",
    "sg:city":"Halifax",
    "sg:classifiers":[
        {
            "category":"Real Estate",
            "subcategory":"Architect",
            "type":"Services"
        }
    ],
    "sg:phone":"+44 1274 600762",
    "sg:postcode":"HX3 7QX",
    "sg:province":"West Yorkshire",
    "wof:name":"Richard M Vogel",
    "wof:placetype":"venue"
},
  "geometry": {"coordinates":[-1.816379,53.752666],"type":"Point"}
}