{
  "type": "Feature",
  "properties": {
    "addr:full":"Po Box, 108 Low Green, Rawdon Leeds West Yorkshire LS19 6HB",
    "addr:housenumber":"po",
    "addr:postcode":"ls19 6hb",
    "addr:street":"Box 108 Low Green",
    "iso:country":"GB",
    "sg:address":"Po Box, 108 Low Green, Rawdon",
    "sg:city":"Leeds",
    "sg:classifiers":[
        {
            "category":"Professional",
            "subcategory":"Engineering",
            "type":"Services"
        }
    ],
    "sg:phone":"+44 113 250 1055",
    "sg:postcode":"LS19 6HB",
    "sg:province":"West Yorkshire",
    "sg:tags":[
        "engineer"
    ],
    "wof:name":"North Atlantic Section",
    "wof:placetype":"venue"
},
  "geometry": {"coordinates":[-1.6820679903,53.8558921814],"type":"Point"}
}