{
  "type": "Feature",
  "properties": {
    "iso:country":"GB",
    "sg:address":"15 Watford Rd",
    "sg:city":"Birmingham",
    "sg:classifiers":[
        {
            "category":"Food & Beverages",
            "subcategory":"Candy",
            "type":"Retail Goods"
        }
    ],
    "sg:postcode":"B30 1JB",
    "sg:province":"West Midlands",
    "sg:tags":[
        "confectioner"
    ],
    "wof:name":"Shaw,A B,",
    "wof:placetype":"venue"
},
  "geometry": {"coordinates":[-1.930866003,52.416595459],"type":"Point"}
}