{
  "type": "Feature",
  "properties": {
    "iso:country":"GB",
    "sg:address":"Silver Street, Kincardine",
    "sg:city":"Alloa",
    "sg:classifiers":[
        {
            "category":"Health Services",
            "subcategory":"Nursing And Care Facility",
            "type":"Services"
        }
    ],
    "sg:phone":"+44 1259 731730",
    "sg:postcode":"FK10 4NS",
    "sg:province":"Clackmannanshire",
    "sg:tags":[
        "home"
    ],
    "wof:name":"Kincardine Bridge Nursing Home",
    "wof:placetype":"venue"
},
  "geometry": {"coordinates":[-3.719558,56.066666],"type":"Point"}
}