{
  "type": "Feature",
  "properties": {
    "addr:full":"27 Finch Road Southsea Hampshire PO4 9LT",
    "addr:housenumber":"27",
    "addr:postcode":"po4 9lt",
    "addr:street":"Finch Road",
    "iso:country":"GB",
    "sg:address":"27 Finch Road",
    "sg:city":"Southsea",
    "sg:classifiers":[
        {
            "category":"Education",
            "subcategory":"Preschool",
            "type":"Public Place"
        }
    ],
    "sg:phone":"+44 23 9229 6455",
    "sg:postcode":"PO4 9LT",
    "sg:province":"Hampshire",
    "sg:tags":[
        "pre-school",
        "playgroups"
    ],
    "wof:name":"Pipit Playgroup",
    "wof:placetype":"venue"
},
  "geometry": {"coordinates":[-1.0414969921,50.7889823914],"type":"Point"}
}