{
  "type": "Feature",
  "properties": {
    "addr:full":"Unit 18 Brandon Way Industrial Estate, Brandon Way West Bromwich West Midlands B70 9PW",
    "addr:housenumber":"unit 18;estate",
    "addr:postcode":"b70 9pw",
    "addr:street":"Brandon;Industrial;Brandon Way",
    "iso:country":"GB",
    "sg:address":"Unit 18 Brandon Way Industrial Estate, Brandon Way",
    "sg:city":"West Bromwich",
    "sg:classifiers":[
        {
            "category":"Wholesale",
            "subcategory":"Scrap",
            "type":"Manufacturing & Wholesale Goods"
        }
    ],
    "sg:postcode":"B70 9PW",
    "sg:province":"West Midlands",
    "sg:tags":[
        "breaker",
        "dismantlers"
    ],
    "wof:name":"Hi-Way Vehicle Services",
    "wof:placetype":"venue"
},
  "geometry": {"coordinates":[-2.0168099403,52.5172691345],"type":"Point"}
}