{
  "type": "Feature",
  "properties": {
    "iso:country":"GB",
    "sg:address":"Holly Cottage, Horndon",
    "sg:city":"Tavistock",
    "sg:classifiers":[
        {
            "category":"Freight",
            "type":"Transportation"
        }
    ],
    "sg:phone":"+44 1822 810879",
    "sg:postcode":"PL19 9NF",
    "sg:province":"Devon",
    "sg:tags":[
        "haulage",
        "road"
    ],
    "wof:name":"Langdon Transport",
    "wof:placetype":"venue"
},
  "geometry": {"coordinates":[-4.144739,50.549934],"type":"Point"}
}