{
  "type": "Feature",
  "properties": {
    "addr:full":"Unit 8/9, Sea Street Herne Bay Kent CT6 8LD",
    "addr:housenumber":"unit 8 / 9",
    "addr:postcode":"ct6 8ld",
    "addr:street":"Sea Street",
    "iso:country":"GB",
    "sg:address":"Unit 8/9, Sea Street",
    "sg:city":"Herne Bay",
    "sg:classifiers":[
        {
            "category":"Shopping",
            "subcategory":"Computers & Home Electronics",
            "type":"Retail Goods"
        },
        {
            "category":"Professional",
            "subcategory":"Computer Services",
            "type":"Services"
        }
    ],
    "sg:phone":"+44 1227 741741",
    "sg:postcode":"CT6 8LD",
    "sg:province":"Kent",
    "sg:tags":[
        "aided",
        "radio",
        "design",
        "equipment"
    ],
    "wof:name":"Icom (U K) Ltd.",
    "wof:placetype":"venue"
},
  "geometry": {"coordinates":[1.1148719788,51.3702278137],"type":"Point"}
}