{
  "type": "Feature",
  "properties": {
    "iso:country":"GB",
    "sg:address":"Inshes Retail Pk",
    "sg:city":"Inverness",
    "sg:classifiers":[
        {
            "category":"Shopping",
            "subcategory":"Hobbies, Toys, & Games",
            "type":"Retail Goods"
        }
    ],
    "sg:postcode":"IV2 3TW",
    "sg:province":"Highland",
    "sg:tags":[
        "shop",
        "toy"
    ],
    "wof:name":"Jolly Giant Toy Superstore Ltd (The)",
    "wof:placetype":"venue"
},
  "geometry": {"coordinates":[-4.20031,57.467602],"type":"Point"}
}