{
  "type": "Feature",
  "properties": {
    "iso:country":"GB",
    "sg:address":"The Grain Store, Pury Hill",
    "sg:city":"Towcester",
    "sg:classifiers":[
        {
            "category":"Professional",
            "subcategory":"Computer Services",
            "type":"Services"
        }
    ],
    "sg:postcode":"NN12 7LS",
    "sg:province":"Buckinghamshire",
    "sg:tags":[
        "consultant"
    ],
    "wof:name":"K C L",
    "wof:placetype":"venue"
},
  "geometry": {"coordinates":[-0.955279,52.102486],"type":"Point"}
}