{
  "type": "Feature",
  "properties": {
    "addr:full":"Unit 1 Second Avenue, Westfield Industrial Estate, Midsomer Norton Bath Somerset BA3 4BH",
    "addr:housenumber":"unit 1",
    "addr:postcode":"ba3 4bh",
    "addr:street":"Second Avenue;Industrial Estate",
    "iso:country":"GB",
    "sg:address":"Unit 1 Second Avenue, Westfield Industrial Estate, Midsomer Norton",
    "sg:city":"Bath",
    "sg:classifiers":[
        {
            "category":"Retail",
            "subcategory":"Repair Shop",
            "type":"Services"
        }
    ],
    "sg:postcode":"BA3 4BH",
    "sg:province":"Somerset",
    "sg:tags":[
        "radio",
        "television",
        "video"
    ],
    "wof:name":"Teletone",
    "wof:placetype":"venue"
},
  "geometry": {"coordinates":[-2.4673678875,51.2794494629],"type":"Point"}
}