{
  "type": "Feature",
  "properties": {
    "iso:country":"GB",
    "sg:address":"7 Old Road",
    "sg:city":"Leighton Buzzard",
    "sg:classifiers":[
        {
            "category":"Food & Beverages",
            "subcategory":"Meat & Fish",
            "type":"Retail Goods"
        }
    ],
    "sg:phone":"+44 1525 373489",
    "sg:postcode":"LU7 2RB",
    "sg:province":"Bedfordshire",
    "sg:tags":[
        "butcher"
    ],
    "wof:name":"William Yirrell Ltd",
    "wof:placetype":"venue"
},
  "geometry": {"coordinates":[-0.671734,51.916759],"type":"Point"}
}