{
  "type": "Feature",
  "properties": {
    "iso:country":"GB",
    "sg:address":", Roch",
    "sg:city":"Haverfordwest",
    "sg:classifiers":[
        {
            "category":"Bars & Pubs",
            "type":"Food & Drink"
        }
    ],
    "sg:phone":"+44 1437 710426",
    "sg:postcode":"SA62 6AW",
    "sg:province":"Pembrokeshire",
    "sg:tags":[
        "pubs",
        "inn"
    ],
    "wof:name":"Victoria Inn",
    "wof:placetype":"venue"
},
  "geometry": {"coordinates":[-5.093248,51.856144],"type":"Point"}
}