{
  "type": "Feature",
  "properties": {
    "addr:full":"111 Bell Street Glasgow Glasgow City G4 0UA",
    "addr:housenumber":"111",
    "addr:postcode":"g4 0ua",
    "addr:street":"Bell Street",
    "iso:country":"GB",
    "sg:address":"111 Bell Street",
    "sg:city":"Glasgow",
    "sg:classifiers":[
        {
            "category":"Insurance",
            "subcategory":"Insurance Agent",
            "type":"Services"
        }
    ],
    "sg:phone":"+44 141 566 9651",
    "sg:postcode":"G4 0UA",
    "sg:province":"Glasgow City",
    "sg:tags":[
        "broker"
    ],
    "wof:name":"Cuthbert Service & Jackson Ltd.",
    "wof:placetype":"venue"
},
  "geometry": {"coordinates":[-4.2424769402,55.8575973511],"type":"Point"}
}