{
  "type": "Feature",
  "properties": {
    "iso:country":"GB",
    "sg:address":"Wooton Business Park, Besselsleigh Road",
    "sg:city":"Abingdon",
    "sg:classifiers":[
        {
            "category":"Shopping",
            "type":"Retail Goods"
        }
    ],
    "sg:phone":"+44 1865 327777",
    "sg:postcode":"OX13 6TP",
    "sg:province":"Oxfordshire",
    "sg:tags":[
        "part",
        "accessory"
    ],
    "wof:name":"Hartwell Ford",
    "wof:placetype":"venue"
},
  "geometry": {"coordinates":[-1.259489,51.756207],"type":"Point"}
}