{
  "type": "Feature",
  "properties": {
    "addr:full":"C S L National Bee Unit Bush F, Arm, Flowton Ipswich Suffolk IP8 4LN",
    "addr:housenumber":"unit",
    "addr:postcode":"ip8 4ln",
    "addr:street":"C S;F",
    "iso:country":"GB",
    "sg:address":"C S L National Bee Unit Bush F, Arm, Flowton",
    "sg:city":"Ipswich",
    "sg:classifiers":[
        {
            "category":"Sports & Exercise",
            "subcategory":"Swimming Pool",
            "type":"Entertainment"
        }
    ],
    "sg:phone":"+44 1473 658078",
    "sg:postcode":"IP8 4LN",
    "sg:province":"Suffolk",
    "sg:tags":[
        "bee"
    ],
    "wof:name":"John Blakesley Regional Bee Inspector",
    "wof:placetype":"venue"
},
  "geometry": {"coordinates":[1.037295,52.080494],"type":"Point"}
}