{
  "type": "Feature",
  "properties": {
    "addr:full":"275 Rumbush Lane, Earlswood Solihull Warwickshire B94 5LX",
    "addr:housenumber":"275",
    "addr:postcode":"b94 5lx",
    "addr:street":"Rumbush Lane",
    "iso:country":"GB",
    "sg:address":"275 Rumbush Lane, Earlswood",
    "sg:city":"Solihull",
    "sg:classifiers":[
        {
            "category":"Building & Trades",
            "subcategory":"Construction",
            "type":"Services"
        }
    ],
    "sg:postcode":"B94 5LX",
    "sg:province":"Warwickshire",
    "sg:tags":[
        "decorator",
        "painter"
    ],
    "wof:name":"Last,A V,",
    "wof:placetype":"venue"
},
  "geometry": {"coordinates":[-1.8471820354,52.3751716614],"type":"Point"}
}