{
  "type": "Feature",
  "properties": {
    "addr:full":"28 Church St, Rothwell Leeds West Yorkshire LS26 0QL",
    "addr:housenumber":"28",
    "addr:postcode":"ls26 0ql",
    "addr:street":"Church St",
    "iso:country":"GB",
    "sg:address":"28 Church St, Rothwell",
    "sg:city":"Leeds",
    "sg:classifiers":[
        {
            "category":"Retail",
            "subcategory":"Auto Repair",
            "type":"Services"
        }
    ],
    "sg:postcode":"LS26 0QL",
    "sg:province":"West Yorkshire",
    "sg:tags":[
        "modification",
        "garage"
    ],
    "wof:name":"Wrigglesworth,Ian,",
    "wof:placetype":"venue"
},
  "geometry": {"coordinates":[-1.4808180332,53.749370575],"type":"Point"}
}