{
  "type": "Feature",
  "properties": {
    "addr:full":"52 Brook Street Chester Cheshire CH1 3DN",
    "addr:housenumber":"52",
    "addr:postcode":"ch1 3dn",
    "addr:street":"Brook Street",
    "iso:country":"GB",
    "sg:address":"52 Brook Street",
    "sg:city":"Chester",
    "sg:classifiers":[
        {
            "category":"Organizations",
            "subcategory":"Non-profit Organization",
            "type":"Services"
        }
    ],
    "sg:phone":"+44 1244 401236",
    "sg:postcode":"CH1 3DN",
    "sg:province":"Cheshire",
    "sg:tags":[
        "charitable",
        "organisation",
        "voluntary",
        "charity"
    ],
    "wof:name":"Lache Animal Sanctuary Charity Shop Trustees",
    "wof:placetype":"venue"
},
  "geometry": {"coordinates":[-2.885511,53.195362],"type":"Point"}
}