{
  "type": "Feature",
  "properties": {
    "iso:country":"GB",
    "sg:address":"13 Willowfield Crescent",
    "sg:city":"Bradford",
    "sg:classifiers":[
        {
            "category":"Professional",
            "subcategory":"Management & Consulting",
            "type":"Services"
        }
    ],
    "sg:phone":"+44 1274 611677",
    "sg:postcode":"BD2 1LJ",
    "sg:province":"West Yorkshire",
    "sg:tags":[
        "consultant",
        "training"
    ],
    "wof:name":"Saunderson Allan Associates",
    "wof:placetype":"venue"
},
  "geometry": {"coordinates":[-1.738556,53.824848],"type":"Point"}
}