{
  "type": "Feature",
  "properties": {
    "iso:country":"GB",
    "sg:address":"5th Floor Quadrant House, 80-82 Regent St",
    "sg:city":"West End",
    "sg:classifiers":[
        {
            "category":"Travel",
            "subcategory":"Travel Agent",
            "type":"Entertainment"
        }
    ],
    "sg:phone":"+44 20 7287 9060",
    "sg:postcode":"W1R 6JB",
    "sg:province":"Hampshire",
    "wof:name":"Radisson Seven Seas Cruises",
    "wof:placetype":"venue"
},
  "geometry": {"coordinates":[-0.136881,51.510014],"type":"Point"}
}