{
  "type": "Feature",
  "properties": {
    "iso:country":"GB",
    "sg:address":"20 Lawford Gardens",
    "sg:city":"Dartford",
    "sg:classifiers":[
        {
            "category":"Home & Garden",
            "subcategory":"Household Appliances",
            "type":"Retail Goods"
        }
    ],
    "sg:phone":"+44 1322 284850",
    "sg:postcode":"DA1 3AL",
    "sg:province":"Kent",
    "sg:tags":[
        "repairs",
        "electrical",
        "domestic",
        "servicing"
    ],
    "wof:name":"P T Electrics",
    "wof:placetype":"venue"
},
  "geometry": {"coordinates":[0.2043,51.449276],"type":"Point"}
}