{
  "type": "Feature",
  "properties": {
    "iso:country":"GB",
    "sg:address":"166 Riverford Road, Pollockshaws",
    "sg:city":"Glasgow",
    "sg:classifiers":[
        {
            "category":"Professional",
            "subcategory":"Printing & Photocopies",
            "type":"Services"
        }
    ],
    "sg:phone":"+44 1325 467576",
    "sg:postcode":"G43 1PT",
    "sg:province":"Glasgow City",
    "sg:tags":[
        "plate",
        "lithographic",
        "maker"
    ],
    "wof:name":"S C A Packaging C P S Ltd.",
    "wof:placetype":"venue"
},
  "geometry": {"coordinates":[-4.29187,55.822723],"type":"Point"}
}