{
  "type": "Feature",
  "properties": {
    "addr:full":"Bishopton Road West Stockton-on-tees Durham TS19 0QB",
    "addr:postcode":"ts19 0qb",
    "addr:street":"Bishopton Road West",
    "iso:country":"GB",
    "sg:address":"Bishopton Road West",
    "sg:city":"Stockton-on-tees",
    "sg:classifiers":[
        {
            "category":"Bars & Pubs",
            "type":"Food & Drink"
        }
    ],
    "sg:phone":"+44 1642 672060",
    "sg:postcode":"TS19 0QB",
    "sg:province":"Durham",
    "sg:tags":[
        "pubs",
        "inn"
    ],
    "wof:name":"Whitbread Hotel Co. Ltd.",
    "wof:placetype":"venue"
},
  "geometry": {"coordinates":[-1.340674,54.57148],"type":"Point"}
}