{
  "type": "Feature",
  "properties": {
    "iso:country":"GB",
    "sg:address":"Cromwell Street",
    "sg:city":"Leeds",
    "sg:classifiers":[
        {
            "category":"Education",
            "subcategory":"School",
            "type":"Public Place"
        }
    ],
    "sg:phone":"+44 113 293 4411",
    "sg:postcode":"LS9 7SG",
    "sg:province":"West Yorkshire",
    "sg:tags":[
        "local",
        "authority"
    ],
    "wof:name":"St Peters C of E (Aided) Primary School",
    "wof:placetype":"venue"
},
  "geometry": {"coordinates":[-1.527804,53.80175],"type":"Point"}
}