{
  "type": "Feature",
  "properties": {
    "addr:full":"Unit 5, Bolney Avenue Peacehaven East Sussex BN10 8NA",
    "addr:housenumber":"unit 5",
    "addr:postcode":"bn10 8na",
    "addr:street":"Bolney Avenue Peacehaven",
    "iso:country":"GB",
    "sg:address":"Unit 5, Bolney Avenue",
    "sg:city":"Peacehaven",
    "sg:classifiers":[
        {
            "category":"Shopping",
            "subcategory":"Beauty & Cosmetics",
            "type":"Retail Goods"
        }
    ],
    "sg:phone":"+44 1273 582667",
    "sg:postcode":"BN10 8NA",
    "sg:province":"East Sussex",
    "wof:name":"The Robertier Collection",
    "wof:placetype":"venue"
},
  "geometry": {"coordinates":[0.005045,50.7918510437],"type":"Point"}
}