{
  "type": "Feature",
  "properties": {
    "iso:country":"GB",
    "sg:address":"Unit 10 Faraday Pk, West Portway Indstl Est",
    "sg:city":"Andover",
    "sg:classifiers":[
        {
            "category":"Retail",
            "subcategory":"Auto Repair",
            "type":"Services"
        }
    ],
    "sg:postcode":"SP10 3SA",
    "sg:province":"Hampshire",
    "sg:tags":[
        "modification",
        "garage"
    ],
    "wof:name":"James,Peter W,",
    "wof:placetype":"venue"
},
  "geometry": {"coordinates":[-1.476779,51.206493],"type":"Point"}
}