{
  "type": "Feature",
  "properties": {
    "addr:full":"21 Rib Vale Hertford Hertfordshire SG14 3LE",
    "addr:housenumber":"21",
    "addr:postcode":"sg14 3le",
    "addr:street":"Rib Vale",
    "iso:country":"GB",
    "sg:address":"21 Rib Vale",
    "sg:city":"Hertford",
    "sg:classifiers":[
        {
            "category":"Shopping",
            "subcategory":"Pharmacy",
            "type":"Retail Goods"
        }
    ],
    "sg:phone":"+44 1992 500922",
    "sg:postcode":"SG14 3LE",
    "sg:province":"Hertfordshire",
    "sg:tags":[
        "medicine",
        "therapy"
    ],
    "wof:name":"V C Boterill",
    "wof:placetype":"venue"
},
  "geometry": {"coordinates":[-0.073706001,51.8088722229],"type":"Point"}
}