{
  "type": "Feature",
  "properties": {
    "addr:full":"Bessemer Way Great Yarmouth Norfolk NR31 0LX",
    "addr:postcode":"nr31 0lx",
    "addr:street":"Bessemer Way",
    "iso:country":"GB",
    "sg:address":"Bessemer Way",
    "sg:city":"Great Yarmouth",
    "sg:classifiers":[
        {
            "category":"Home & Garden",
            "subcategory":"Home Furnishings",
            "type":"Retail Goods"
        },
        {
            "category":"Utilities",
            "subcategory":"Fuel Oil & Lpg",
            "type":"Services"
        }
    ],
    "sg:phone":"+44 1493 601548",
    "sg:postcode":"NR31 0LX",
    "sg:province":"Norfolk",
    "sg:tags":[
        "pipe",
        "fitting",
        "gas"
    ],
    "sg:website":"http://www.tubecare.co.uk",
    "wof:name":"Tube Care Inspection Ltd",
    "wof:placetype":"venue"
},
  "geometry": {"coordinates":[1.715335,52.594776],"type":"Point"}
}