{
  "type": "Feature",
  "properties": {
    "iso:country":"GB",
    "sg:address":"34 Meadowside, Mosterton",
    "sg:city":"Beaminster",
    "sg:classifiers":[
        {
            "category":"Shopping",
            "subcategory":"Pharmacy",
            "type":"Retail Goods"
        }
    ],
    "sg:postcode":"DT8 3LP",
    "sg:province":"Dorset",
    "sg:tags":[
        "medicine",
        "therapy"
    ],
    "wof:name":"The White Flower Centre",
    "wof:placetype":"venue"
},
  "geometry": {"coordinates":[-2.738894,50.809006],"type":"Point"}
}