{
  "type": "Feature",
  "properties": {
    "iso:country":"GB",
    "sg:address":"198 The Avenue",
    "sg:city":"Sunbury-on-thames",
    "sg:classifiers":[
        {
            "category":"Health Services",
            "subcategory":"Dentist",
            "type":"Services"
        }
    ],
    "sg:phone":"+44 1932 783801",
    "sg:postcode":"TW16 5DX",
    "sg:province":"Surrey",
    "wof:name":"Mr Urdang Surgery",
    "wof:placetype":"venue"
},
  "geometry": {"coordinates":[-0.411912,51.418072],"type":"Point"}
}