{
  "type": "Feature",
  "properties": {
    "addr:full":"33 Marionville Road Edinburgh City of Edinburgh EH7 5UD",
    "addr:housenumber":"33",
    "addr:postcode":"eh7 5ud",
    "addr:street":"Marionville Road",
    "iso:country":"GB",
    "sg:address":"33 Marionville Road",
    "sg:city":"Edinburgh",
    "sg:classifiers":[
        {
            "category":"Bars & Pubs",
            "type":"Food & Drink"
        },
        {
            "category":"Community Center",
            "subcategory":"Social",
            "type":"Public Place"
        }
    ],
    "sg:phone":"+44 131 661 4502",
    "sg:postcode":"EH7 5UD",
    "sg:province":"City of Edinburgh",
    "sg:tags":[
        "pubs",
        "house",
        "inn",
        "activity"
    ],
    "wof:name":"Marionville Bar",
    "wof:placetype":"venue"
},
  "geometry": {"coordinates":[-3.161169,55.957512],"type":"Point"}
}