{
  "type": "Feature",
  "properties": {
    "addr:full":"254 Kingsbury Road, Kingsbury London Greater London NW9 0BT",
    "addr:housenumber":"254",
    "addr:postcode":"nw9 0bt",
    "addr:street":"Kingsbury Road",
    "iso:country":"GB",
    "sg:address":"254 Kingsbury Road, Kingsbury",
    "sg:city":"London",
    "sg:classifiers":[
        {
            "category":"Real Estate",
            "subcategory":"Real Estate Operator",
            "type":"Services"
        }
    ],
    "sg:phone":"+44 20 8204 0075",
    "sg:postcode":"NW9 0BT",
    "sg:province":"Greater London",
    "sg:tags":[
        "letting",
        "agent"
    ],
    "wof:name":"Falcon Property Services",
    "wof:placetype":"venue"
},
  "geometry": {"coordinates":[-0.264362,51.583977],"type":"Point"}
}