{
  "type": "Feature",
  "properties": {
    "addr:full":"1 Redwood Lane, Lees Oldham Lancashire OL4 3JT",
    "addr:housenumber":"1",
    "addr:postcode":"ol4 3jt",
    "addr:street":"Redwood Lane",
    "iso:country":"GB",
    "sg:address":"1 Redwood Lane, Lees",
    "sg:city":"Oldham",
    "sg:classifiers":[
        {
            "category":"Building & Trades",
            "subcategory":"Construction",
            "type":"Services"
        }
    ],
    "sg:postcode":"OL4 3JT",
    "sg:province":"Lancashire",
    "sg:tags":[
        "dry",
        "lining",
        "plasterers",
        "screeders"
    ],
    "wof:name":"Tony Stott",
    "wof:placetype":"venue"
},
  "geometry": {"coordinates":[-2.068483,53.545692],"type":"Point"}
}