{
  "type": "Feature",
  "properties": {
    "addr:full":"Cromwell Business Centre, 10 Howard Way Interchange Park Newport Pagnell Buckinghamshire MK16 9QS",
    "addr:housenumber":"10",
    "addr:postcode":"mk16 9qs",
    "addr:street":"Howard Way Interchange Park",
    "iso:country":"GB",
    "sg:address":"Cromwell Business Centre, 10 Howard Way Interchange Park",
    "sg:city":"Newport Pagnell",
    "sg:phone":"+44 1908 611127",
    "sg:postcode":"MK16 9QS",
    "sg:province":"Buckinghamshire",
    "wof:name":"Schunk Intec Ltd.",
    "wof:placetype":"venue"
},
  "geometry": {"coordinates":[-0.7027390003,52.0816345215],"type":"Point"}
}