{
  "type": "Feature",
  "properties": {
    "addr:full":"140 High St Honiton Devon EX14 8JP",
    "addr:housenumber":"140",
    "addr:postcode":"ex14 8jp",
    "addr:street":"High St",
    "iso:country":"GB",
    "sg:address":"140 High St",
    "sg:city":"Honiton",
    "sg:classifiers":[
        {
            "category":"Museum",
            "subcategory":"Art Museum",
            "type":"Entertainment"
        }
    ],
    "sg:phone":"+44 1404 47869",
    "sg:postcode":"EX14 8JP",
    "sg:province":"Devon",
    "sg:tags":[
        "gallery"
    ],
    "wof:name":"La Lanterne Magique",
    "wof:placetype":"venue"
},
  "geometry": {"coordinates":[-3.1921219826,50.7986679077],"type":"Point"}
}