{
  "type": "Feature",
  "properties": {
    "addr:full":"41 High Street Sandbach Cheshire CW11 1AL",
    "addr:housenumber":"41",
    "addr:postcode":"cw11 1al",
    "addr:street":"High Street",
    "iso:country":"GB",
    "sg:address":"41 High Street",
    "sg:city":"Sandbach",
    "sg:classifiers":[
        {
            "category":"Professional",
            "subcategory":"Accounting & Tax Preparation",
            "type":"Services"
        }
    ],
    "sg:phone":"+44 1270 767126",
    "sg:postcode":"CW11 1AL",
    "sg:province":"Cheshire",
    "sg:tags":[
        "accountant"
    ],
    "wof:name":"Cunningham & Co",
    "wof:placetype":"venue"
},
  "geometry": {"coordinates":[-2.36081,53.142895],"type":"Point"}
}