{
  "type": "Feature",
  "properties": {
    "addr:full":"31 Grantham Close, Nerafield, Plympton Plymouth Devon PL7 3UL",
    "addr:housenumber":"31",
    "addr:postcode":"pl7 3ul",
    "addr:street":"Grantham Close",
    "iso:country":"GB",
    "sg:address":"31 Grantham Close, Nerafield, Plympton",
    "sg:city":"Plymouth",
    "sg:classifiers":[
        {
            "category":"Building & Trades",
            "subcategory":"Construction",
            "type":"Services"
        }
    ],
    "sg:phone":"+44 1752 341069",
    "sg:postcode":"PL7 3UL",
    "sg:province":"Devon",
    "sg:tags":[
        "decorator",
        "painter"
    ],
    "wof:name":"R & R Plymouth Interior & Exterior Decorators",
    "wof:placetype":"venue"
},
  "geometry": {"coordinates":[-4.05039,50.387829],"type":"Point"}
}