{
  "type": "Feature",
  "properties": {
    "iso:country":"GB",
    "sg:address":"5 Lancaster Lodge, 85 Lancaster Road",
    "sg:city":"London",
    "sg:classifiers":[
        {
            "category":"Retail",
            "subcategory":"Storage",
            "type":"Services"
        }
    ],
    "sg:phone":"+44 20 7221 2327",
    "sg:postcode":"W11 1QH",
    "sg:province":"Greater London",
    "sg:tags":[
        "household",
        "removal"
    ],
    "wof:name":"A-Van & Driver",
    "wof:placetype":"venue"
},
  "geometry": {"coordinates":[-0.209143,51.516823],"type":"Point"}
}