{
  "type": "Feature",
  "properties": {
    "iso:country":"GB",
    "sg:address":"Unit 24 Cave Industrial Estate",
    "sg:city":"Cambridge",
    "sg:classifiers":[
        {
            "category":"Coffee & Tea",
            "type":"Food & Drink"
        }
    ],
    "sg:phone":"+44 1223 425849",
    "sg:postcode":"CB4 1UN",
    "sg:province":"Cambridgeshire",
    "wof:name":"Coffee World Co.",
    "wof:placetype":"venue"
},
  "geometry": {"coordinates":[0.15726,52.22102],"type":"Point"}
}