{
  "type": "Feature",
  "properties": {
    "iso:country":"GB",
    "sg:address":"49 High Street, Nailsea",
    "sg:city":"Bristol",
    "sg:classifiers":[
        {
            "category":"Real Estate",
            "subcategory":"Real Estate Agent",
            "type":"Services"
        }
    ],
    "sg:postcode":"BS48 1AW",
    "sg:province":"Somerset",
    "wof:name":"Milligan Properties Limited",
    "wof:placetype":"venue"
},
  "geometry": {"coordinates":[-2.7520771027,51.4359550476],"type":"Point"}
}