{
  "type": "Feature",
  "properties": {
    "iso:country":"GB",
    "sg:address":"Unit 8d Victoria Industrial Estate, Victoria Road West",
    "sg:city":"Hebburn",
    "sg:classifiers":[
        {
            "category":"Manufacturing",
            "subcategory":"Metals",
            "type":"Manufacturing & Wholesale Goods"
        }
    ],
    "sg:postcode":"NE31 1UB",
    "sg:province":"Tyne and Wear",
    "sg:tags":[
        "work",
        "sheet"
    ],
    "wof:name":"Eezi-Fit",
    "wof:placetype":"venue"
},
  "geometry": {"coordinates":[-1.526224,54.962078],"type":"Point"}
}