{
  "type": "Feature",
  "properties": {
    "addr:full":"Pilsworth Road, Pilsworth Industrial Estate Bury Lancashire BL9 8RS",
    "addr:postcode":"bl9 8rs",
    "addr:street":"Pilsworth Road Pilsworth Industrial Estate",
    "iso:country":"GB",
    "sg:address":"Pilsworth Road, Pilsworth Industrial Estate",
    "sg:city":"Bury",
    "sg:classifiers":[
        {
            "category":"Food & Beverages",
            "subcategory":"Supermarket",
            "type":"Retail Goods"
        }
    ],
    "sg:phone":"+44 161 766 9735",
    "sg:postcode":"BL9 8RS",
    "sg:province":"Lancashire",
    "wof:name":"Asda Stores Ltd.",
    "wof:placetype":"venue"
},
  "geometry": {"coordinates":[-2.274137,53.578487],"type":"Point"}
}