{
  "type": "Feature",
  "properties": {
    "addr:full":"1 Sans Walk Clerkenwell Greater London EC1R 0LT",
    "addr:housenumber":"1",
    "addr:postcode":"ec1r 0lt",
    "addr:street":"Sans Walk",
    "iso:country":"GB",
    "sg:address":"1 Sans Walk",
    "sg:city":"Clerkenwell",
    "sg:classifiers":[
        {
            "category":"Real Estate",
            "subcategory":"Architect",
            "type":"Services"
        }
    ],
    "sg:phone":"+44 20 7251 9119",
    "sg:postcode":"EC1R 0LT",
    "sg:province":"Greater London",
    "sg:tags":[
        "architectural"
    ],
    "wof:name":"View",
    "wof:placetype":"venue"
},
  "geometry": {"coordinates":[-0.1048590019,51.524684906],"type":"Point"}
}