{
  "type": "Feature",
  "properties": {
    "addr:full":"30 Heath Street, Hampstead London Greater London NW3 6TE",
    "addr:housenumber":"30",
    "addr:postcode":"nw3 6te",
    "addr:street":"Heath Street",
    "iso:country":"GB",
    "sg:address":"30 Heath Street, Hampstead",
    "sg:city":"London",
    "sg:classifiers":[
        {
            "category":"Shopping",
            "subcategory":"Clothing, Apparel, & Fashions",
            "type":"Retail Goods"
        },
        {
            "category":"Food & Beverages",
            "subcategory":"Meat & Fish",
            "type":"Retail Goods"
        }
    ],
    "sg:phone":"+44 20 7794 8863",
    "sg:postcode":"NW3 6TE",
    "sg:province":"Greater London",
    "sg:tags":[
        "butcher",
        "ladieswear"
    ],
    "wof:name":"van Gelder Betty Ltd.",
    "wof:placetype":"venue"
},
  "geometry": {"coordinates":[-0.1784700006,51.5560073853],"type":"Point"}
}