{
  "type": "Feature",
  "properties": {
    "addr:full":"Coppice Lodge Donington Park, Castle Donington Derby Leicestershire DE74 2RP",
    "addr:postcode":"de74 2rp",
    "addr:street":"Donington Park",
    "iso:country":"GB",
    "sg:address":"Coppice Lodge Donington Park, Castle Donington",
    "sg:city":"Derby",
    "sg:classifiers":[
        {
            "category":"Professional",
            "subcategory":"Detective & Security Services",
            "type":"Services"
        }
    ],
    "sg:phone":"+44 1332 811254",
    "sg:postcode":"DE74 2RP",
    "sg:province":"Leicestershire",
    "wof:name":"A Spencer",
    "wof:placetype":"venue"
},
  "geometry": {"coordinates":[-1.3373839855,52.8448791504],"type":"Point"}
}