{
  "type": "Feature",
  "properties": {
    "addr:full":"Ardonachie Farm, Bankfoot Perth Perth and Kinross PH1 4DY",
    "addr:postcode":"ph1 4dy",
    "addr:street":"Bankfoot",
    "iso:country":"GB",
    "sg:address":"Ardonachie Farm, Bankfoot",
    "sg:city":"Perth",
    "sg:classifiers":[
        {
            "category":"Farming",
            "subcategory":"Livestock Farm",
            "type":"Manufacturing & Wholesale Goods"
        },
        {
            "category":"Farming",
            "subcategory":"Farm",
            "type":"Manufacturing & Wholesale Goods"
        }
    ],
    "sg:phone":"+44 1738 787376",
    "sg:postcode":"PH1 4DY",
    "sg:province":"Perth and Kinross",
    "sg:tags":[
        "mixed",
        "crop",
        "others"
    ],
    "wof:name":"Joseph W Smith",
    "wof:placetype":"venue"
},
  "geometry": {"coordinates":[-3.5158538818,56.5012893677],"type":"Point"}
}