{
  "type": "Feature",
  "properties": {
    "addr:full":"Braxted Park, Great Braxted Witham Essex CM8 3XB",
    "addr:postcode":"cm8 3xb",
    "iso:country":"GB",
    "sg:address":"Braxted Park, Great Braxted",
    "sg:city":"Witham",
    "sg:classifiers":[
        {
            "category":"Banks & Credit Unions",
            "subcategory":"Financial Services",
            "type":"Services"
        }
    ],
    "sg:phone":"+44 1621 893633",
    "sg:postcode":"CM8 3XB",
    "sg:province":"Essex",
    "sg:tags":[
        "adviser"
    ],
    "wof:name":"David Steers",
    "wof:placetype":"venue"
},
  "geometry": {"coordinates":[0.668602,51.816315],"type":"Point"}
}