{
  "type": "Feature",
  "properties": {
    "iso:country":"GB",
    "sg:address":"New Road, Tankersley",
    "sg:city":"Barnsley",
    "sg:classifiers":[
        {
            "category":"Wholesale",
            "subcategory":"Non-durable Goods",
            "type":"Manufacturing & Wholesale Goods"
        },
        {
            "category":"Structure",
            "subcategory":"Warehouse",
            "type":"Public Place"
        }
    ],
    "sg:phone":"+44 1226 748371",
    "sg:postcode":"S75 3BQ",
    "sg:province":"South Yorkshire",
    "sg:tags":[
        "carry",
        "cash"
    ],
    "wof:name":"Co. Shop Ltd.",
    "wof:placetype":"venue"
},
  "geometry": {"coordinates":[-1.482897,53.495152],"type":"Point"}
}