{
  "type": "Feature",
  "properties": {
    "iso:country":"GB",
    "sg:address":"4 Old Bank Road",
    "sg:city":"Mirfield",
    "sg:classifiers":[
        {
            "category":"Food & Beverages",
            "subcategory":"Meat & Fish",
            "type":"Retail Goods"
        }
    ],
    "sg:phone":"+44 1924 493201",
    "sg:postcode":"WF14 0HS",
    "sg:province":"West Yorkshire",
    "sg:tags":[
        "butcher"
    ],
    "wof:name":"Malcolm Hilton",
    "wof:placetype":"venue"
},
  "geometry": {"coordinates":[-1.6962629557,53.6858825684],"type":"Point"}
}