{
  "type": "Feature",
  "properties": {
    "addr:full":"25 Hines La Cambridge Cambridgeshire CB3 7BZ",
    "addr:housenumber":"25",
    "addr:postcode":"cb3 7bz",
    "addr:street":"Hines La",
    "iso:country":"GB",
    "sg:address":"25 Hines La",
    "sg:city":"Cambridge",
    "sg:classifiers":[
        {
            "category":"Retail",
            "subcategory":"Driving School",
            "type":"Services"
        }
    ],
    "sg:phone":"+44 1223 262678",
    "sg:postcode":"CB3 7BZ",
    "sg:province":"Cambridgeshire",
    "wof:name":"King School Of Motoring",
    "wof:placetype":"venue"
},
  "geometry": {"coordinates":[0.019931,52.188148],"type":"Point"}
}