{
  "type": "Feature",
  "properties": {
    "addr:full":"32 Priory Road, Knowle Bristol City of Bristol BS4 2NL",
    "addr:housenumber":"32",
    "addr:postcode":"bs4 2nl",
    "addr:street":"Priory Road",
    "iso:country":"GB",
    "sg:address":"32 Priory Road, Knowle",
    "sg:city":"Bristol",
    "sg:classifiers":[
        {
            "category":"Shopping",
            "subcategory":"Antiques",
            "type":"Retail Goods"
        }
    ],
    "sg:postcode":"BS4 2NL",
    "sg:province":"City of Bristol",
    "wof:name":"Ray Harrop Services",
    "wof:placetype":"venue"
},
  "geometry": {"coordinates":[-2.563618,51.43528],"type":"Point"}
}