{
  "type": "Feature",
  "properties": {
    "addr:full":"94 Grange Lane Barnsley South Yorkshire S71 5QF",
    "addr:housenumber":"94",
    "addr:postcode":"s71 5qf",
    "addr:street":"Grange Lane;Yorkshire",
    "iso:country":"GB",
    "sg:address":"94 Grange Lane",
    "sg:city":"Barnsley",
    "sg:classifiers":[
        {
            "category":"Utilities",
            "subcategory":"Natural Gas",
            "type":"Services"
        }
    ],
    "sg:phone":"+44 1226 201332",
    "sg:postcode":"S71 5QF",
    "sg:province":"South Yorkshire",
    "sg:tags":[
        "supplier"
    ],
    "wof:name":"Castle Gas",
    "wof:placetype":"venue"
},
  "geometry": {"coordinates":[-1.4408659935,53.5545120239],"type":"Point"}
}