{
  "type": "Feature",
  "properties": {
    "iso:country":"GB",
    "sg:address":"569 Chorley Old Road",
    "sg:city":"Bolton",
    "sg:classifiers":[
        {
            "category":"Professional",
            "type":"Services"
        },
        {
            "category":"Real Estate",
            "subcategory":"Surveying",
            "type":"Services"
        }
    ],
    "sg:phone":"+44 1204 400500",
    "sg:postcode":"BL1 6BL",
    "sg:province":"Lancashire",
    "sg:tags":[
        "interior",
        "furnishers",
        "designer",
        "valuer",
        "surveyor"
    ],
    "wof:name":"Designas",
    "wof:placetype":"venue"
},
  "geometry": {"coordinates":[-2.464445,53.588421],"type":"Point"}
}