{
  "type": "Feature",
  "properties": {
    "iso:country":"GB",
    "sg:address":"Crowland Road, Eye",
    "sg:city":"Peterborough",
    "sg:classifiers":[
        {
            "category":"Education",
            "subcategory":"Library",
            "type":"Public Place"
        }
    ],
    "sg:phone":"+44 1733 222531",
    "sg:postcode":"PE6 7TN",
    "sg:province":"Cambridgeshire",
    "sg:tags":[
        "book"
    ],
    "wof:name":"Eye Library",
    "wof:placetype":"venue"
},
  "geometry": {"coordinates":[-0.185747996,52.6242637634],"type":"Point"}
}