{
  "type": "Feature",
  "properties": {
    "iso:country":"GB",
    "sg:address":"133 The Moor",
    "sg:city":"Sheffield",
    "sg:classifiers":[
        {
            "category":"Retail",
            "subcategory":"Laundry & Dry Cleaning",
            "type":"Services"
        }
    ],
    "sg:phone":"+44 114 272 1339",
    "sg:postcode":"S1 4PH",
    "sg:province":"South Yorkshire",
    "sg:tags":[
        "alteration"
    ],
    "wof:name":"Crockatt Cleaning",
    "wof:placetype":"venue"
},
  "geometry": {"coordinates":[-1.474367,53.375168],"type":"Point"}
}