{
  "type": "Feature",
  "properties": {
    "iso:country":"GB",
    "sg:address":"33 Argyll Arcade",
    "sg:city":"Glasgow",
    "sg:classifiers":[
        {
            "category":"Shopping",
            "subcategory":"Jewelry",
            "type":"Retail Goods"
        },
        {
            "category":"Manufacturing",
            "subcategory":"Jewelry",
            "type":"Manufacturing & Wholesale Goods"
        },
        {
            "category":"Shopping",
            "subcategory":"Comic Books",
            "type":"Retail Goods"
        }
    ],
    "sg:phone":"+44 141 221 9969",
    "sg:postcode":"G2 8BA",
    "sg:province":"Glasgow City",
    "sg:tags":[
        "repair",
        "jeweller",
        "sale",
        "jewellery"
    ],
    "wof:name":"Mr Harold & Son",
    "wof:placetype":"venue"
},
  "geometry": {"coordinates":[-4.261059,55.858749],"type":"Point"}
}