{
  "type": "Feature",
  "properties": {
    "iso:country":"GB",
    "sg:address":"25 White Hart Street",
    "sg:city":"High Wycombe",
    "sg:classifiers":[
        {
            "category":"Travel",
            "subcategory":"Travel Agent",
            "type":"Entertainment"
        }
    ],
    "sg:phone":"+44 1494 657200",
    "sg:postcode":"HP11 2HL",
    "sg:province":"Buckinghamshire",
    "wof:name":"Thomas Cook",
    "wof:placetype":"venue"
},
  "geometry": {"coordinates":[-0.752604,51.629929],"type":"Point"}
}