{
  "type": "Feature",
  "properties": {
    "addr:full":"106 The Baulk Biggleswade Bedfordshire SG18 0QA",
    "addr:housenumber":"106",
    "addr:postcode":"sg18 0qa",
    "addr:street":"The Baulk",
    "iso:country":"GB",
    "sg:address":"106 The Baulk",
    "sg:city":"Biggleswade",
    "sg:classifiers":[
        {
            "category":"Professional",
            "subcategory":"Secretarial Services",
            "type":"Services"
        }
    ],
    "sg:phone":"+44 1767 310216",
    "sg:postcode":"SG18 0QA",
    "sg:province":"Bedfordshire",
    "wof:name":"Complete Business Service",
    "wof:placetype":"venue"
},
  "geometry": {"coordinates":[-0.2541829944,52.0874176025],"type":"Point"}
}