{
  "type": "Feature",
  "properties": {
    "addr:full":"Connought House Colchester Essex CO4 9QB",
    "addr:postcode":"co4 9qb",
    "iso:country":"GB",
    "sg:address":"Connought House",
    "sg:city":"Colchester",
    "sg:classifiers":[
        {
            "category":"Health Services",
            "subcategory":"Nursing And Care Facility",
            "type":"Services"
        }
    ],
    "sg:phone":"+44 1206 517318",
    "sg:postcode":"CO4 9QB",
    "sg:province":"Essex",
    "sg:tags":[
        "agency"
    ],
    "wof:name":"Haven Care Ltd.",
    "wof:placetype":"venue"
},
  "geometry": {"coordinates":[0.92138,51.915852],"type":"Point"}
}