{
  "type": "Feature",
  "properties": {
    "addr:full":"Unit 3, Blacknest Road, Blacknest Alton Hampshire GU34 4PX",
    "addr:housenumber":"unit 3",
    "addr:postcode":"gu34 4px",
    "addr:street":"Blacknest Road Blacknest",
    "iso:country":"GB",
    "sg:address":"Unit 3, Blacknest Road, Blacknest",
    "sg:city":"Alton",
    "sg:classifiers":[
        {
            "category":"Home & Garden",
            "subcategory":"Household Appliances",
            "type":"Retail Goods"
        },
        {
            "category":"Building & Trades",
            "subcategory":"Electrical",
            "type":"Services"
        }
    ],
    "sg:phone":"+44 1420 22622",
    "sg:postcode":"GU34 4PX",
    "sg:province":"Hampshire",
    "sg:tags":[
        "equipment",
        "contractor",
        "air conditioning"
    ],
    "wof:name":"C F ENVIRONMENTAL SERVICES (GROUP) LTD",
    "wof:placetype":"venue"
},
  "geometry": {"coordinates":[-0.8672620058,51.1741447449],"type":"Point"}
}