{
  "type": "Feature",
  "properties": {
    "addr:full":"6 Marine Parade Hastings East Sussex TN34 3AG",
    "addr:housenumber":"6",
    "addr:postcode":"tn34 3ag",
    "addr:street":"Marine Parade",
    "iso:country":"GB",
    "sg:address":"6 Marine Parade",
    "sg:city":"Hastings",
    "sg:classifiers":[
        {
            "category":"Cafe",
            "type":"Food & Drink"
        }
    ],
    "sg:phone":"+44 1424 714010",
    "sg:postcode":"TN34 3AG",
    "sg:province":"East Sussex",
    "sg:tags":[
        "tea",
        "room"
    ],
    "wof:name":"The Pie & Mash Shop",
    "wof:placetype":"venue"
},
  "geometry": {"coordinates":[0.58797,50.855331],"type":"Point"}
}