{
  "type": "Feature",
  "properties": {
    "iso:country":"GB",
    "sg:address":"25 Rattray",
    "sg:city":"Erskine",
    "sg:classifiers":[
        {
            "category":"Autos & Motor Vehicles",
            "subcategory":"Auto Supplies",
            "type":"Retail Goods"
        }
    ],
    "sg:phone":"+44 141 812 5395",
    "sg:postcode":"PA8 6ET",
    "sg:province":"Renfrewshire",
    "sg:tags":[
        "windscreen"
    ],
    "wof:name":"Direct Windscreen",
    "wof:placetype":"venue"
},
  "geometry": {"coordinates":[-4.464069,55.906677],"type":"Point"}
}