{
  "type": "Feature",
  "properties": {
    "addr:full":"6 Camross Drive Shrewsbury Shropshire SY1 3XH",
    "addr:housenumber":"6",
    "addr:postcode":"sy1 3xh",
    "addr:street":"Camross Drive",
    "iso:country":"GB",
    "sg:address":"6 Camross Drive",
    "sg:city":"Shrewsbury",
    "sg:classifiers":[
        {
            "category":"Building & Trades",
            "subcategory":"Landscaping Services",
            "type":"Services"
        },
        {
            "category":"Home & Garden",
            "subcategory":"Hardware",
            "type":"Retail Goods"
        }
    ],
    "sg:phone":"+44 1743 243833",
    "sg:postcode":"SY1 3XH",
    "sg:province":"Shropshire",
    "sg:tags":[
        "horticultural",
        "generator",
        "consultant"
    ],
    "wof:name":"U P S Direct",
    "wof:placetype":"venue"
},
  "geometry": {"coordinates":[-2.751436,52.727661],"type":"Point"}
}