{
  "type": "Feature",
  "properties": {
    "addr:full":"Ashburton Avenue Ilford Essex IG3 9EL",
    "addr:postcode":"ig3 9el",
    "addr:street":"Ashburton Avenue Ilford",
    "iso:country":"GB",
    "sg:address":"Ashburton Avenue",
    "sg:city":"Ilford",
    "sg:classifiers":[
        {
            "category":"Freight",
            "type":"Transportation"
        }
    ],
    "sg:phone":"+44 1702 298161",
    "sg:postcode":"IG3 9EL",
    "sg:province":"Essex",
    "sg:tags":[
        "haulage",
        "road"
    ],
    "wof:name":"D L Jones",
    "wof:placetype":"venue"
},
  "geometry": {"coordinates":[0.103483,51.552406],"type":"Point"}
}