{
  "type": "Feature",
  "properties": {
    "iso:country":"GB",
    "sg:address":"Daimler Drive, Cowpen Lane Industrial Estate",
    "sg:city":"Billingham",
    "sg:classifiers":[
        {
            "category":"Retail",
            "subcategory":"Storage",
            "type":"Services"
        }
    ],
    "sg:phone":"+44 1642 565182",
    "sg:postcode":"TS23 4JD",
    "sg:province":"Durham",
    "sg:tags":[
        "household",
        "removal"
    ],
    "wof:name":"Britannia Devereux Movers International",
    "wof:placetype":"venue"
},
  "geometry": {"coordinates":[-1.2604739666,54.6105041504],"type":"Point"}
}