{
  "type": "Feature",
  "properties": {
    "iso:country":"GB",
    "sg:address":"909 Aldridge Road, Great Barr",
    "sg:city":"Birmingham",
    "sg:classifiers":[
        {
            "category":"Professional",
            "subcategory":"Art Services",
            "type":"Services"
        }
    ],
    "sg:phone":"+44 121 325 1060",
    "sg:postcode":"B44 8NS",
    "sg:province":"West Midlands",
    "sg:tags":[
        "consultant",
        "design"
    ],
    "wof:name":"This & That Incorporated Ltd.",
    "wof:placetype":"venue"
},
  "geometry": {"coordinates":[-1.9027119875,52.5434684753],"type":"Point"}
}