{
  "type": "Feature",
  "properties": {
    "addr:full":"2 Market Street Watford Hertfordshire WD18 0PD",
    "addr:housenumber":"2",
    "addr:postcode":"wd18 0pd",
    "addr:street":"Market Street",
    "iso:country":"GB",
    "sg:address":"2 Market Street",
    "sg:city":"Watford",
    "sg:classifiers":[
        {
            "category":"Shopping",
            "subcategory":"Photographic Equipment",
            "type":"Retail Goods"
        }
    ],
    "sg:phone":"+44 1923 240021",
    "sg:postcode":"WD18 0PD",
    "sg:province":"Hertfordshire",
    "sg:tags":[
        "supply"
    ],
    "wof:name":"Jessop Photo Video Centre",
    "wof:placetype":"venue"
},
  "geometry": {"coordinates":[-0.397391,51.655323],"type":"Point"}
}