{
  "type": "Feature",
  "properties": {
    "iso:country":"GB",
    "sg:address":"6 Rowantrees, Rednal",
    "sg:city":"Birmingham",
    "sg:classifiers":[
        {
            "category":"Retail",
            "subcategory":"Storage",
            "type":"Services"
        }
    ],
    "sg:phone":"+44 800 037 1329",
    "sg:postcode":"B45 8DP",
    "sg:province":"West Midlands",
    "sg:tags":[
        "household",
        "removal"
    ],
    "wof:name":"A C Removals & Storage",
    "wof:placetype":"venue"
},
  "geometry": {"coordinates":[-2.003631,52.385319],"type":"Point"}
}