{
  "type": "Feature",
  "properties": {
    "addr:full":"251 High St Leven Fife KY8 3ED",
    "addr:housenumber":"251",
    "addr:postcode":"ky8 3ed",
    "addr:street":"High St",
    "iso:country":"GB",
    "sg:address":"251 High St",
    "sg:city":"Leven",
    "sg:classifiers":[
        {
            "category":"Food & Beverages",
            "subcategory":"Meat & Fish",
            "type":"Retail Goods"
        }
    ],
    "sg:phone":"+44 1333 423484",
    "sg:postcode":"KY8 3ED",
    "sg:province":"Fife",
    "sg:tags":[
        "butcher"
    ],
    "wof:name":"McRobb The Butcher",
    "wof:placetype":"venue"
},
  "geometry": {"coordinates":[-3.008137,56.18644],"type":"Point"}
}