{
  "type": "Feature",
  "properties": {
    "iso:country":"GB",
    "sg:address":"2-4 Westway, Maghull",
    "sg:city":"Liverpool",
    "sg:classifiers":[
        {
            "category":"Shopping",
            "subcategory":"Clothing, Apparel, & Fashions",
            "type":"Retail Goods"
        },
        {
            "category":"Shopping",
            "subcategory":"Baby Store",
            "type":"Retail Goods"
        }
    ],
    "sg:phone":"+44 151 531 6502",
    "sg:postcode":"L31 0DQ",
    "sg:province":"Lancashire",
    "sg:tags":[
        "child",
        "childrens",
        "babywear"
    ],
    "wof:name":"Ethel Austin Ltd",
    "wof:placetype":"venue"
},
  "geometry": {"coordinates":[-2.94125,53.51638],"type":"Point"}
}