{
  "type": "Feature",
  "properties": {
    "iso:country":"GB",
    "sg:address":"41 Abercorn Terrace",
    "sg:city":"Edinburgh",
    "sg:classifiers":[
        {
            "category":"Travel",
            "subcategory":"Hotels & Motels",
            "type":"Entertainment"
        }
    ],
    "sg:phone":"+44 131 669 5678",
    "sg:postcode":"EH15 2DG",
    "sg:province":"City of Edinburgh",
    "sg:tags":[
        "house",
        "guest"
    ],
    "wof:name":"The Robert Burns Hotel",
    "wof:placetype":"venue"
},
  "geometry": {"coordinates":[-3.103543,55.95002],"type":"Point"}
}