{
  "type": "Feature",
  "properties": {
    "addr:full":"54 High Street, Ramsey Huntingdon Cambridgeshire PE26 1AA",
    "addr:housenumber":"54",
    "addr:postcode":"pe26 1aa",
    "addr:street":"High Street",
    "iso:country":"GB",
    "sg:address":"54 High Street, Ramsey",
    "sg:city":"Huntingdon",
    "sg:classifiers":[
        {
            "category":"Shopping",
            "subcategory":"Clothing, Apparel, & Fashions",
            "type":"Retail Goods"
        }
    ],
    "sg:phone":"+44 1487 812007",
    "sg:postcode":"PE26 1AA",
    "sg:province":"Cambridgeshire",
    "sg:tags":[
        "shop"
    ],
    "wof:name":"Huntgate Ltd.",
    "wof:placetype":"venue"
},
  "geometry": {"coordinates":[-0.107297,52.448254],"type":"Point"}
}