{
  "type": "Feature",
  "properties": {
    "iso:country":"GB",
    "sg:address":"12 Creek Rd",
    "sg:city":"Hayling Island",
    "sg:classifiers":[
        {
            "category":"Bars & Pubs",
            "type":"Food & Drink"
        }
    ],
    "sg:phone":"+44 23 9246 1771",
    "sg:postcode":"PO11 9RD",
    "sg:province":"Hampshire",
    "sg:tags":[
        "pubs",
        "inn"
    ],
    "wof:name":"Lily Sugars",
    "wof:placetype":"venue"
},
  "geometry": {"coordinates":[-0.952081,50.779015],"type":"Point"}
}