{
  "type": "Feature",
  "properties": {
    "addr:full":"181 Park Rd Loughborough Leicestershire LE11 2HE",
    "addr:housenumber":"181",
    "addr:postcode":"le11 2he",
    "addr:street":"Park Rd",
    "iso:country":"GB",
    "sg:address":"181 Park Rd",
    "sg:city":"Loughborough",
    "sg:classifiers":[
        {
            "category":"Building & Trades",
            "subcategory":"Construction",
            "type":"Services"
        }
    ],
    "sg:phone":"+44 1509 236334",
    "sg:postcode":"LE11 2HE",
    "sg:province":"Leicestershire",
    "sg:tags":[
        "flooring"
    ],
    "wof:name":"Ace Flooring",
    "wof:placetype":"venue"
},
  "geometry": {"coordinates":[-1.2061589956,52.7596130371],"type":"Point"}
}