{
  "type": "Feature",
  "properties": {
    "iso:country":"GB",
    "sg:address":"5 Stainburne Rd, Offerton",
    "sg:city":"Stockport",
    "sg:classifiers":[
        {
            "category":"Building & Trades",
            "subcategory":"Construction",
            "type":"Services"
        }
    ],
    "sg:postcode":"SK2 6BB",
    "sg:province":"Cheshire",
    "sg:tags":[
        "bricklaying"
    ],
    "wof:name":"Nunn,Carl,",
    "wof:placetype":"venue"
},
  "geometry": {"coordinates":[-2.128972,53.393021],"type":"Point"}
}