{
  "type": "Feature",
  "properties": {
    "addr:full":"The Wath, Newbiggin-on-lune Kirkby Stephen Cumbria CA17 4NB",
    "addr:postcode":"ca17 4nb",
    "iso:country":"GB",
    "sg:address":"The Wath, Newbiggin-on-lune",
    "sg:city":"Kirkby Stephen",
    "sg:classifiers":[
        {
            "category":"Farming",
            "subcategory":"Livestock Farm",
            "type":"Manufacturing & Wholesale Goods"
        }
    ],
    "sg:phone":"+44 15396 23260",
    "sg:postcode":"CA17 4NB",
    "sg:province":"Cumbria",
    "sg:tags":[
        "others"
    ],
    "wof:name":"PHILIP WILSON",
    "wof:placetype":"venue"
},
  "geometry": {"coordinates":[-2.3486230373,54.4727172852],"type":"Point"}
}