{
  "type": "Feature",
  "properties": {
    "iso:country":"GB",
    "sg:address":"1 Marketgate North, Crail",
    "sg:city":"Anstruther",
    "sg:classifiers":[
        {
            "category":"Travel",
            "subcategory":"Hotels & Motels",
            "type":"Entertainment"
        }
    ],
    "sg:phone":"+44 1333 450253",
    "sg:postcode":"KY10 3TQ",
    "sg:province":"Fife",
    "sg:tags":[
        "house",
        "guest"
    ],
    "wof:name":"Denburn House B & B",
    "wof:placetype":"venue"
},
  "geometry": {"coordinates":[-2.662959,56.24297],"type":"Point"}
}