{
  "type": "Feature",
  "properties": {
    "addr:full":"33 Emsworth Road Havant Hampshire PO9 2SN",
    "addr:housenumber":"33",
    "addr:postcode":"po9 2sn",
    "addr:street":"Emsworth Road",
    "iso:country":"GB",
    "sg:address":"33 Emsworth Road",
    "sg:city":"Havant",
    "sg:classifiers":[
        {
            "category":"Organizations",
            "subcategory":"Membership Organization",
            "type":"Services"
        }
    ],
    "sg:phone":"+44 23 9249 2280",
    "sg:postcode":"PO9 2SN",
    "sg:province":"Hampshire",
    "sg:tags":[
        "club",
        "social"
    ],
    "sg:website":"http://www.denvilleshouse.com",
    "wof:name":"Langstone Conservative Club Ltd",
    "wof:placetype":"venue"
},
  "geometry": {"coordinates":[-0.9744539857,50.8505439758],"type":"Point"}
}