{
  "type": "Feature",
  "properties": {
    "addr:full":"36 Albert Rd Manchester Greater Manchester M19 2AB",
    "addr:housenumber":"36",
    "addr:postcode":"m19 2ab",
    "addr:street":"Albert Rd",
    "iso:country":"GB",
    "sg:address":"36 Albert Rd",
    "sg:city":"Manchester",
    "sg:classifiers":[
        {
            "category":"Retail",
            "subcategory":"Laundry & Dry Cleaning",
            "type":"Services"
        }
    ],
    "sg:phone":"+44 161 224 0928",
    "sg:postcode":"M19 2AB",
    "sg:province":"Greater Manchester",
    "sg:tags":[
        "launderette"
    ],
    "wof:name":"M & J Launderette",
    "wof:placetype":"venue"
},
  "geometry": {"coordinates":[-2.19490695,53.4441490173],"type":"Point"}
}