{
  "type": "Feature",
  "properties": {
    "iso:country":"GB",
    "sg:address":"22-28 Wellingborough Road",
    "sg:city":"Northampton",
    "sg:classifiers":[
        {
            "category":"Home & Garden",
            "subcategory":"Furniture",
            "type":"Retail Goods"
        }
    ],
    "sg:phone":"+44 1604 637524",
    "sg:postcode":"NN1 4DN",
    "sg:province":"Northamptonshire",
    "wof:name":"Woodlows Ltd.",
    "wof:placetype":"venue"
},
  "geometry": {"coordinates":[-0.887443,52.240192],"type":"Point"}
}