{
  "type": "Feature",
  "properties": {
    "iso:country":"GB",
    "sg:address":"5 Leicester Road, Blaby",
    "sg:city":"Leicester",
    "sg:classifiers":[
        {
            "category":"Shopping",
            "subcategory":"Jewelry",
            "type":"Retail Goods"
        },
        {
            "category":"Shopping",
            "subcategory":"Comic Books",
            "type":"Retail Goods"
        }
    ],
    "sg:phone":"+44 116 277 2877",
    "sg:postcode":"LE8 4GR",
    "sg:province":"Leicestershire",
    "sg:tags":[
        "jeweller",
        "sale",
        "jewellery"
    ],
    "wof:name":"Barry Bott Jewellers",
    "wof:placetype":"venue"
},
  "geometry": {"coordinates":[-1.163133,52.576019],"type":"Point"}
}