{
  "type": "Feature",
  "properties": {
    "iso:country":"GB",
    "sg:address":"31 Greendale Close",
    "sg:city":"Atherstone",
    "sg:classifiers":[
        {
            "category":"Arts & Performance",
            "subcategory":"Music",
            "type":"Entertainment"
        }
    ],
    "sg:postcode":"CV9 1PR",
    "sg:province":"Leicestershire",
    "sg:tags":[
        "mobile",
        "disco"
    ],
    "wof:name":"White Lightning Disco",
    "wof:placetype":"venue"
},
  "geometry": {"coordinates":[-1.53731,52.571491],"type":"Point"}
}