{
  "type": "Feature",
  "properties": {
    "addr:full":"5 Enterprise Court, Lakes Road Braintree Essex CM7 3QS",
    "addr:housenumber":"5",
    "addr:postcode":"cm7 3qs",
    "addr:street":"Enterprise Court Lakes Road",
    "iso:country":"GB",
    "sg:address":"5 Enterprise Court, Lakes Road",
    "sg:city":"Braintree",
    "sg:classifiers":[
        {
            "category":"Home & Garden",
            "subcategory":"Household Appliances",
            "type":"Retail Goods"
        },
        {
            "category":"Communications",
            "type":"Services"
        }
    ],
    "sg:phone":"+44 1376 320390",
    "sg:postcode":"CM7 3QS",
    "sg:province":"Essex",
    "sg:tags":[
        "cleaner",
        "tv",
        "domestic",
        "video",
        "vacuum",
        "radio"
    ],
    "wof:name":"Vac Doctors Braintree",
    "wof:placetype":"venue"
},
  "geometry": {"coordinates":[0.563845,51.876579],"type":"Point"}
}