{
  "type": "Feature",
  "properties": {
    "iso:country":"GB",
    "sg:address":"Arle Court",
    "sg:city":"Cheltenham",
    "sg:classifiers":[
        {
            "category":"Professional",
            "type":"Services"
        },
        {
            "category":"Wholesale",
            "subcategory":"Machinery & Supplies",
            "type":"Manufacturing & Wholesale Goods"
        }
    ],
    "sg:phone":"+44 1242 221155",
    "sg:postcode":"GL51 0TP",
    "sg:province":"Gloucestershire",
    "sg:tags":[
        "pump",
        "-",
        "aircraft"
    ],
    "wof:name":"Smiths Aerospace Actuation Systems",
    "wof:placetype":"venue"
},
  "geometry": {"coordinates":[-2.0935239792,51.9048995972],"type":"Point"}
}