{
  "type": "Feature",
  "properties": {
    "addr:full":"184 Chester Road, Hartford Northwich Cheshire CW8 1LG",
    "addr:housenumber":"184",
    "addr:postcode":"cw8 1lg",
    "addr:street":"Chester Road",
    "iso:country":"GB",
    "sg:address":"184 Chester Road, Hartford",
    "sg:city":"Northwich",
    "sg:classifiers":[
        {
            "category":"Freight",
            "type":"Transportation"
        }
    ],
    "sg:phone":"+44 1606 783653",
    "sg:postcode":"CW8 1LG",
    "sg:province":"Cheshire",
    "sg:tags":[
        "haulage",
        "road"
    ],
    "wof:name":"Harrison Transport",
    "wof:placetype":"venue"
},
  "geometry": {"coordinates":[-2.5367250443,53.2509231567],"type":"Point"}
}