{
  "type": "Feature",
  "properties": {
    "addr:full":"Odeon Bldgs, Rochdale Rd Bury Lancashire BL9 0PL",
    "addr:postcode":"bl9 0pl",
    "addr:street":"Rochdale Rd",
    "iso:country":"GB",
    "sg:address":"Odeon Bldgs, Rochdale Rd",
    "sg:city":"Bury",
    "sg:classifiers":[
        {
            "category":"Insurance",
            "subcategory":"Insurance Agent",
            "type":"Services"
        }
    ],
    "sg:postcode":"BL9 0PL",
    "sg:province":"Lancashire",
    "wof:name":"Hudson,J,",
    "wof:placetype":"venue"
},
  "geometry": {"coordinates":[-2.3010540009,53.5897331238],"type":"Point"}
}