{
  "type": "Feature",
  "properties": {
    "iso:country":"GB",
    "sg:address":"16 Leeds Rd",
    "sg:city":"Leeds",
    "sg:classifiers":[
        {
            "category":"Bars & Pubs",
            "type":"Food & Drink"
        }
    ],
    "sg:phone":"+44 113 282 2370",
    "sg:postcode":"LS26 8JU",
    "sg:province":"West Yorkshire",
    "sg:tags":[
        "pubs",
        "house",
        "inn",
        "public",
        "activity"
    ],
    "wof:name":"Three Horse Shoes",
    "wof:placetype":"venue"
},
  "geometry": {"coordinates":[-1.454302,53.748314],"type":"Point"}
}