{
  "type": "Feature",
  "properties": {
    "addr:full":"39 Sidwell Street Exeter Devon EX4 6NS",
    "addr:housenumber":"39",
    "addr:postcode":"ex4 6ns",
    "addr:street":"Sidwell Street",
    "iso:country":"GB",
    "sg:address":"39 Sidwell Street",
    "sg:city":"Exeter",
    "sg:classifiers":[
        {
            "category":"Shopping",
            "subcategory":"Discount & Variety Stores",
            "type":"Retail Goods"
        }
    ],
    "sg:phone":"+44 1392 435118",
    "sg:postcode":"EX4 6NS",
    "sg:province":"Devon",
    "sg:tags":[
        "shop",
        "model"
    ],
    "wof:name":"Exeter Model Centre",
    "wof:placetype":"venue"
},
  "geometry": {"coordinates":[-3.524212,50.727211],"type":"Point"}
}