{
  "type": "Feature",
  "properties": {
    "addr:full":"7 Prior Avenue Sutton Surrey SM2 5HX",
    "addr:housenumber":"7",
    "addr:postcode":"sm2 5hx",
    "addr:street":"Prior Avenue",
    "iso:country":"GB",
    "sg:address":"7 Prior Avenue",
    "sg:city":"Sutton",
    "sg:classifiers":[
        {
            "category":"Home & Garden",
            "subcategory":"Home Furnishings",
            "type":"Retail Goods"
        }
    ],
    "sg:postcode":"SM2 5HX",
    "sg:province":"Surrey",
    "sg:tags":[
        "furnishers",
        "planner",
        "kitchen"
    ],
    "wof:name":"Shallcross A J & Co.",
    "wof:placetype":"venue"
},
  "geometry": {"coordinates":[-0.175894,51.356163],"type":"Point"}
}