{
  "type": "Feature",
  "properties": {
    "addr:full":"Reynoldston Swansea Swansea SA3 3EH",
    "addr:postcode":"sa3 3eh",
    "addr:street":"Reynoldston Swansea",
    "iso:country":"GB",
    "sg:address":"Reynoldston",
    "sg:city":"Swansea",
    "sg:classifiers":[
        {
            "category":"Place Of Worship",
            "type":"Public Place"
        }
    ],
    "sg:phone":"+44 1792 232867",
    "sg:postcode":"SA3 3EH",
    "sg:province":"Swansea",
    "wof:name":"Reynoldston Methodist Church",
    "wof:placetype":"venue"
},
  "geometry": {"coordinates":[-4.05254,51.585541],"type":"Point"}
}