{
  "type": "Feature",
  "properties": {
    "iso:country":"GB",
    "sg:address":"65 Orchard Street",
    "sg:city":"Weston-super-mare",
    "sg:classifiers":[
        {
            "category":"Professional",
            "subcategory":"Printing & Photocopies",
            "type":"Services"
        }
    ],
    "sg:phone":"+44 1934 626263",
    "sg:postcode":"BS23 1RJ",
    "sg:province":"Somerset",
    "sg:tags":[
        "printer"
    ],
    "wof:name":"Kall-Kwik Printing (U K) Ltd.",
    "wof:placetype":"venue"
},
  "geometry": {"coordinates":[-2.975854,51.349602],"type":"Point"}
}