{
  "type": "Feature",
  "properties": {
    "iso:country":"GB",
    "sg:address":"82a Whitchurch Road",
    "sg:city":"Cardiff",
    "sg:classifiers":[
        {
            "category":"Banks & Credit Unions",
            "subcategory":"Financial Services",
            "type":"Services"
        }
    ],
    "sg:postcode":"CF14 3LX",
    "sg:province":"Cardiff",
    "sg:tags":[
        "consultant"
    ],
    "wof:name":"P.H. & G. Investments Ltd",
    "wof:placetype":"venue"
},
  "geometry": {"coordinates":[-3.186987,51.500446],"type":"Point"}
}