{
  "type": "Feature",
  "properties": {
    "iso:country":"GB",
    "sg:address":"Scottish College, Higher Education",
    "sg:city":"Montrose",
    "sg:classifiers":[
        {
            "category":"Education",
            "subcategory":"University",
            "type":"Public Place"
        }
    ],
    "sg:postcode":"DD10 8PU",
    "sg:province":"Aberdeenshire",
    "sg:tags":[
        "higher"
    ],
    "wof:name":"Scottish College of Higher Learning",
    "wof:placetype":"venue"
},
  "geometry": {"coordinates":[-2.4661839008,56.7214393616],"type":"Point"}
}