{
  "type": "Feature",
  "properties": {
    "iso:country":"GB",
    "sg:address":"Upshire Farm, Racing Stables, Hungerford Hill, Lambourn",
    "sg:city":"Hungerford",
    "sg:classifiers":[
        {
            "category":"Personal",
            "subcategory":"Adult",
            "type":"Services"
        }
    ],
    "sg:phone":"+44 1488 73483",
    "sg:postcode":"RG17 7LE",
    "sg:province":"Berkshire",
    "sg:tags":[
        "equestrian"
    ],
    "wof:name":"Speedmerchant Racing Ltd",
    "wof:placetype":"venue"
},
  "geometry": {"coordinates":[-1.53323,51.50256],"type":"Point"}
}