{
  "type": "Feature",
  "properties": {
    "iso:country":"GB",
    "sg:address":"36 Worple Road",
    "sg:city":"Staines",
    "sg:classifiers":[
        {
            "category":"Food & Beverages",
            "subcategory":"Groceries & Convenience Stores",
            "type":"Retail Goods"
        }
    ],
    "sg:phone":"+44 1784 452500",
    "sg:postcode":"TW18 1EA",
    "sg:province":"Berkshire",
    "wof:name":"Spar Store",
    "wof:placetype":"venue"
},
  "geometry": {"coordinates":[-0.494838,51.426907],"type":"Point"}
}