{
  "type": "Feature",
  "properties": {
    "addr:full":"43-45 Enterprise Drive Sutton Coldfield Staffordshire B74 2DS",
    "addr:housenumber":"43-45",
    "addr:postcode":"b74 2ds",
    "addr:street":"Enterprise Drive",
    "iso:country":"GB",
    "sg:address":"43-45 Enterprise Drive",
    "sg:city":"Sutton Coldfield",
    "sg:classifiers":[
        {
            "category":"Manufacturing",
            "subcategory":"Petroleum Products",
            "type":"Manufacturing & Wholesale Goods"
        }
    ],
    "sg:phone":"+44 121 352 1880",
    "sg:postcode":"B74 2DS",
    "sg:province":"Staffordshire",
    "sg:tags":[
        "double",
        "glazing"
    ],
    "wof:name":"B & K Windows Ltd.",
    "wof:placetype":"venue"
},
  "geometry": {"coordinates":[-1.893089056,52.5721168518],"type":"Point"}
}