{
  "type": "Feature",
  "properties": {
    "addr:full":"4 Central Pavement Chesterfield Derbyshire S40 1PQ",
    "addr:housenumber":"4",
    "addr:postcode":"s40 1pq",
    "addr:street":"Central Pavement",
    "iso:country":"GB",
    "sg:address":"4 Central Pavement",
    "sg:city":"Chesterfield",
    "sg:classifiers":[
        {
            "category":"Banks & Credit Unions",
            "subcategory":"Bureau De Change",
            "type":"Services"
        }
    ],
    "sg:phone":"+44 1246 557662",
    "sg:postcode":"S40 1PQ",
    "sg:province":"Derbyshire",
    "wof:name":"Eurochange Ltd.",
    "wof:placetype":"venue"
},
  "geometry": {"coordinates":[-1.4265140295,53.2365379333],"type":"Point"}
}