{
  "type": "Feature",
  "properties": {
    "addr:full":"95 Southwark Park Rd Sth Bermondsey Greater London SE16 3TY",
    "addr:housenumber":"95",
    "addr:postcode":"se16 3ty",
    "addr:street":"Southwark Park Rd",
    "iso:country":"GB",
    "sg:address":"95 Southwark Park Rd",
    "sg:city":"Sth Bermondsey",
    "sg:classifiers":[
        {
            "category":"Social Services",
            "subcategory":"Adult Care",
            "type":"Services"
        }
    ],
    "sg:phone":"+44 20 7237 0860",
    "sg:postcode":"SE16 3TY",
    "sg:province":"Greater London",
    "sg:tags":[
        "day",
        "centre"
    ],
    "wof:name":"Yalding Day Centre",
    "wof:placetype":"venue"
},
  "geometry": {"coordinates":[-0.1006629989,51.5057754517],"type":"Point"}
}