{
  "type": "Feature",
  "properties": {
    "addr:full":"13 Tinkers La Wareham Dorset BH20 4QR",
    "addr:postcode":"bh20 4qr",
    "iso:country":"GB",
    "sg:address":"13 Tinkers La",
    "sg:city":"Wareham",
    "sg:classifiers":[
        {
            "category":"Banks & Credit Unions",
            "subcategory":"Investment Brokerage",
            "type":"Services"
        },
        {
            "category":"Retail",
            "subcategory":"Veterinary Services",
            "type":"Services"
        }
    ],
    "sg:postcode":"BH20 4QR",
    "sg:province":"Dorset",
    "sg:tags":[
        "surgeon",
        "contractor"
    ],
    "wof:name":"Baker,Conrad,",
    "wof:placetype":"venue"
},
  "geometry": {"coordinates":[-2.1143939495,50.6874542236],"type":"Point"}
}