{
  "type": "Feature",
  "properties": {
    "addr:full":"Load Street Bewdley Shropshire DY12 2EQ",
    "addr:postcode":"dy12 2eq",
    "addr:street":"Load Street",
    "iso:country":"GB",
    "sg:address":"Load Street",
    "sg:city":"Bewdley",
    "sg:classifiers":[
        {
            "category":"Education",
            "subcategory":"Library",
            "type":"Public Place"
        }
    ],
    "sg:phone":"+44 1299 403303",
    "sg:postcode":"DY12 2EQ",
    "sg:province":"Shropshire",
    "sg:tags":[
        "book"
    ],
    "wof:name":"Bewdley Library",
    "wof:placetype":"venue"
},
  "geometry": {"coordinates":[-2.314414,52.376217],"type":"Point"}
}