{
  "type": "Feature",
  "properties": {
    "addr:full":"Creswell Leisure Centre, Duke Street, Creswell Worksop Nottinghamshire S80 4AS",
    "addr:postcode":"s80 4as",
    "addr:street":"Duke Street",
    "iso:country":"GB",
    "sg:address":"Creswell Leisure Centre, Duke Street, Creswell",
    "sg:city":"Worksop",
    "sg:classifiers":[
        {
            "category":"Community Center",
            "type":"Public Place"
        }
    ],
    "sg:phone":"+44 1909 721371",
    "sg:postcode":"S80 4AS",
    "sg:province":"Nottinghamshire",
    "sg:tags":[
        "recreation",
        "leisure",
        "centre"
    ],
    "wof:name":"Creswell Leisure Centre",
    "wof:placetype":"venue"
},
  "geometry": {"coordinates":[-1.217444,53.26239],"type":"Point"}
}