{
  "type": "Feature",
  "properties": {
    "iso:country":"GB",
    "sg:address":"130b Old Bedford Rd",
    "sg:city":"Luton",
    "sg:classifiers":[
        {
            "category":"Social Services",
            "subcategory":"Retirement Home",
            "type":"Services"
        }
    ],
    "sg:phone":"+44 1442 256928",
    "sg:postcode":"LU2 7HH",
    "sg:province":"Bedfordshire",
    "sg:tags":[
        "glazing",
        "safety"
    ],
    "wof:name":"H G & S J Barnett Ltd",
    "wof:placetype":"venue"
},
  "geometry": {"coordinates":[-0.418777,51.887825],"type":"Point"}
}