{
  "type": "Feature",
  "properties": {
    "addr:full":"Penre Isa, Mount Road St Asaph Conwy LL17 0DH",
    "addr:postcode":"ll17 0dh",
    "addr:street":"Mount Road St",
    "iso:country":"GB",
    "sg:address":"Penre Isa, Mount Road",
    "sg:city":"St Asaph",
    "sg:classifiers":[
        {
            "category":"Building & Trades",
            "subcategory":"Construction",
            "type":"Services"
        }
    ],
    "sg:phone":"+44 1745 590500",
    "sg:postcode":"LL17 0DH",
    "sg:province":"Conwy",
    "sg:tags":[
        "roofing",
        "contracting"
    ],
    "wof:name":"Holdsworth Roofing Ltd",
    "wof:placetype":"venue"
},
  "geometry": {"coordinates":[-3.444865942,53.2568626404],"type":"Point"}
}