{
  "type": "Feature",
  "properties": {
    "iso:country":"GB",
    "sg:address":"24 Riverside",
    "sg:city":"Staines",
    "sg:classifiers":[
        {
            "category":"Professional",
            "subcategory":"Secretarial Services",
            "type":"Services"
        }
    ],
    "sg:phone":"+44 7973 889494",
    "sg:postcode":"TW19 5JN",
    "sg:province":"Berkshire",
    "wof:name":"Artright",
    "wof:placetype":"venue"
},
  "geometry": {"coordinates":[-0.5720019937,51.4540367126],"type":"Point"}
}