{
  "type": "Feature",
  "properties": {
    "addr:full":"National Stud Newmarket Cambridgeshire CB8 0XE",
    "addr:postcode":"cb8 0xe",
    "addr:street":"Newmarket",
    "iso:country":"GB",
    "sg:address":"National Stud",
    "sg:city":"Newmarket",
    "sg:classifiers":[
        {
            "category":"Farming",
            "subcategory":"Livestock Farm",
            "type":"Manufacturing & Wholesale Goods"
        }
    ],
    "sg:phone":"+44 1638 663464",
    "sg:postcode":"CB8 0XE",
    "sg:province":"Cambridgeshire",
    "sg:tags":[
        "stud"
    ],
    "wof:name":"The National stud",
    "wof:placetype":"venue"
},
  "geometry": {"coordinates":[0.399166,52.249817],"type":"Point"}
}