{
  "type": "Feature",
  "properties": {
    "addr:full":"275 High Road Leytonstone, Leytonstone London Greater London E11 4HH",
    "addr:housenumber":"275",
    "addr:postcode":"e11 4hh",
    "addr:street":"High Road Leytonstone",
    "iso:country":"GB",
    "sg:address":"275 High Road Leytonstone, Leytonstone",
    "sg:city":"London",
    "sg:classifiers":[
        {
            "category":"Autos & Motor Vehicles",
            "subcategory":"Auto Supplies",
            "type":"Retail Goods"
        },
        {
            "category":"Shopping",
            "type":"Retail Goods"
        }
    ],
    "sg:phone":"+44 20 8519 5381",
    "sg:postcode":"E11 4HH",
    "sg:province":"Greater London",
    "sg:tags":[
        "car",
        "part",
        "accessory"
    ],
    "wof:name":"Budget Auto Spares",
    "wof:placetype":"venue"
},
  "geometry": {"coordinates":[0.00508,51.5534591675],"type":"Point"}
}