{
  "type": "Feature",
  "properties": {
    "iso:country":"GB",
    "sg:address":"121 St Peters Road",
    "sg:city":"Dudley",
    "sg:classifiers":[
        {
            "category":"Bus Charters",
            "type":"Transportation"
        }
    ],
    "sg:phone":"+44 1384 564751",
    "sg:postcode":"DY2 9HX",
    "sg:province":"West Midlands",
    "sg:tags":[
        "hire",
        "coach"
    ],
    "wof:name":"J C Coaches",
    "wof:placetype":"venue"
},
  "geometry": {"coordinates":[-2.0727488995,52.4885063171],"type":"Point"}
}