{
  "type": "Feature",
  "properties": {
    "addr:full":"Smilt House Oswestry Shropshire SY10 9RA",
    "addr:postcode":"sy10 9ra",
    "iso:country":"GB",
    "sg:address":"Smilt House",
    "sg:city":"Oswestry",
    "sg:classifiers":[
        {
            "category":"Utilities",
            "subcategory":"Fuel Oil & Lpg",
            "type":"Services"
        }
    ],
    "sg:phone":"+44 1691 830315",
    "sg:postcode":"SY10 9RA",
    "sg:province":"Shropshire",
    "sg:tags":[
        "coal",
        "smokeless"
    ],
    "wof:name":"S Owen & Son",
    "wof:placetype":"venue"
},
  "geometry": {"coordinates":[-3.109068,52.814892],"type":"Point"}
}