{
  "type": "Feature",
  "properties": {
    "addr:full":"High Street Halifax West Yorkshire HX3 7NF",
    "addr:postcode":"hx3 7nf",
    "addr:street":"High Street",
    "iso:country":"GB",
    "sg:address":"High Street",
    "sg:city":"Halifax",
    "sg:classifiers":[
        {
            "category":"Building & Trades",
            "subcategory":"Plumbing",
            "type":"Services"
        }
    ],
    "sg:phone":"+44 1274 674026",
    "sg:postcode":"HX3 7NF",
    "sg:province":"West Yorkshire",
    "sg:tags":[
        "heating"
    ],
    "wof:name":"J.H. Young Plumbing & Heating Engineers",
    "wof:placetype":"venue"
},
  "geometry": {"coordinates":[-1.8657989502,53.7200050354],"type":"Point"}
}