{
  "type": "Feature",
  "properties": {
    "addr:full":"The Pavillion, Buccleuch St Dalkeith City of Edinburgh EH22 1HA",
    "addr:postcode":"eh22 1ha",
    "addr:street":"Buccleuch St",
    "iso:country":"GB",
    "sg:address":"The Pavillion, Buccleuch St",
    "sg:city":"Dalkeith",
    "sg:classifiers":[
        {
            "category":"Organizations",
            "subcategory":"Political Organization",
            "type":"Services"
        }
    ],
    "sg:phone":"+44 131 663 2109",
    "sg:postcode":"EH22 1HA",
    "sg:province":"City of Edinburgh",
    "sg:tags":[
        "promoter",
        "pool"
    ],
    "wof:name":"Carlton Bingo",
    "wof:placetype":"venue"
},
  "geometry": {"coordinates":[-3.0686130524,55.8928794861],"type":"Point"}
}