{
  "type": "Feature",
  "properties": {
    "addr:full":"3 Railway Street North Shields Tyne and Wear NE29 6QD",
    "addr:housenumber":"3",
    "addr:postcode":"ne29 6qd",
    "addr:street":"Railway Street",
    "iso:country":"GB",
    "sg:address":"3 Railway Street",
    "sg:city":"North Shields",
    "sg:classifiers":[
        {
            "category":"Travel",
            "subcategory":"Travel Agent",
            "type":"Entertainment"
        }
    ],
    "sg:phone":"+44 191 257 6982",
    "sg:postcode":"NE29 6QD",
    "sg:province":"Tyne and Wear",
    "wof:name":"Travelcare",
    "wof:placetype":"venue"
},
  "geometry": {"coordinates":[-1.4478019476,55.008518219],"type":"Point"}
}