{
  "type": "Feature",
  "properties": {
    "addr:full":"8 Sturdee Place Hastings East Sussex TN34 3AJ",
    "addr:housenumber":"8",
    "addr:postcode":"tn34 3aj",
    "addr:street":"Sturdee Place Hastings",
    "iso:country":"GB",
    "sg:address":"8 Sturdee Place",
    "sg:city":"Hastings",
    "sg:classifiers":[
        {
            "category":"Shopping",
            "subcategory":"Gifts & Souvenirs",
            "type":"Retail Goods"
        }
    ],
    "sg:postcode":"TN34 3AJ",
    "sg:province":"East Sussex",
    "sg:tags":[
        "shop"
    ],
    "wof:name":"Joyce's Gift & Shell Shop",
    "wof:placetype":"venue"
},
  "geometry": {"coordinates":[0.586828,50.85532],"type":"Point"}
}