{
  "type": "Feature",
  "properties": {
    "addr:full":"Home Farm, Fetteresso Stonehaven Aberdeenshire AB3 2UR",
    "addr:housenumber":"fetteresso",
    "addr:postcode":"ab3 2ur",
    "addr:street":"Stonehaven",
    "iso:country":"GB",
    "sg:address":"Home Farm, Fetteresso",
    "sg:city":"Stonehaven",
    "sg:classifiers":[
        {
            "category":"Farming",
            "subcategory":"Livestock Farm",
            "type":"Manufacturing & Wholesale Goods"
        }
    ],
    "sg:phone":"+44 1569 763197",
    "sg:postcode":"AB3 2UR",
    "sg:province":"Aberdeenshire",
    "sg:tags":[
        "others"
    ],
    "wof:name":"David Martin",
    "wof:placetype":"venue"
},
  "geometry": {"coordinates":[-2.2087500095,56.963848114],"type":"Point"}
}