{
  "type": "Feature",
  "properties": {
    "addr:full":"46 Vernon Street, Farnworth Bolton Lancashire BL4 7RD",
    "addr:housenumber":"46",
    "addr:postcode":"bl4 7rd",
    "addr:street":"Vernon Street",
    "iso:country":"GB",
    "sg:address":"46 Vernon Street, Farnworth",
    "sg:city":"Bolton",
    "sg:classifiers":[
        {
            "category":"Food & Beverages",
            "subcategory":"Liquor & Beverages",
            "type":"Retail Goods"
        }
    ],
    "sg:postcode":"BL4 7RD",
    "sg:province":"Lancashire",
    "sg:tags":[
        "beer",
        "spirit",
        "wines"
    ],
    "wof:name":"J W Small",
    "wof:placetype":"venue"
},
  "geometry": {"coordinates":[-2.3921220303,53.5503311157],"type":"Point"}
}