{
  "type": "Feature",
  "properties": {
    "addr:full":"10 Marketgate Lancaster Lancashire LA1 1JF",
    "addr:housenumber":"10",
    "addr:postcode":"la1 1jf",
    "addr:street":"Marketgate",
    "iso:country":"GB",
    "sg:address":"10 Marketgate",
    "sg:city":"Lancaster",
    "sg:classifiers":[
        {
            "category":"Restaurant",
            "type":"Food & Drink"
        }
    ],
    "sg:phone":"+44 1524 389799",
    "sg:postcode":"LA1 1JF",
    "sg:province":"Lancashire",
    "wof:name":"Country Larder",
    "wof:placetype":"venue"
},
  "geometry": {"coordinates":[-2.800974,54.048103],"type":"Point"}
}