{
  "type": "Feature",
  "properties": {
    "iso:country":"GB",
    "sg:address":"Craigiebrae",
    "sg:city":"Castle Douglas",
    "sg:classifiers":[
        {
            "category":"Building & Trades",
            "subcategory":"Plumbing",
            "type":"Services"
        }
    ],
    "sg:postcode":"DG7 2BA",
    "sg:province":"Dumfries and Galloway",
    "sg:tags":[
        "heating"
    ],
    "wof:name":"Brian Redden",
    "wof:placetype":"venue"
},
  "geometry": {"coordinates":[-4.176569,54.876419],"type":"Point"}
}