{
  "type": "Feature",
  "properties": {
    "iso:country":"GB",
    "sg:address":"Redwell Wood Farm, Ridge",
    "sg:city":"Potters Bar",
    "sg:classifiers":[
        {
            "category":"Farming",
            "subcategory":"Livestock Farm",
            "type":"Manufacturing & Wholesale Goods"
        }
    ],
    "sg:postcode":"EN6 3NA",
    "sg:province":"Greater London",
    "sg:tags":[
        "others"
    ],
    "wof:name":"B J Luffman",
    "wof:placetype":"venue"
},
  "geometry": {"coordinates":[-0.178424,51.693012],"type":"Point"}
}