{
  "type": "Feature",
  "properties": {
    "iso:country":"GB",
    "sg:address":"256 Trysull Road",
    "sg:city":"Wolverhampton",
    "sg:classifiers":[
        {
            "category":"Home & Garden",
            "subcategory":"Hardware",
            "type":"Retail Goods"
        }
    ],
    "sg:postcode":"WV3 7LB",
    "sg:province":"Staffordshire",
    "sg:tags":[
        "lawnmowers",
        "machinery"
    ],
    "wof:name":"Daniel Bate Lawnmover",
    "wof:placetype":"venue"
},
  "geometry": {"coordinates":[-2.170107,52.571354],"type":"Point"}
}