{
  "type": "Feature",
  "properties": {
    "iso:country":"GB",
    "sg:address":"Nelson House, 58 Wimbledon Hill Rd",
    "sg:city":"London",
    "sg:classifiers":[
        {
            "category":"Shopping",
            "subcategory":"Computers & Home Electronics",
            "type":"Retail Goods"
        }
    ],
    "sg:postcode":"SW19 7PA",
    "sg:province":"Greater London",
    "sg:tags":[
        "hi-fi",
        "equipment",
        "mnfr"
    ],
    "wof:name":"Republic Enterprises Ltd",
    "wof:placetype":"venue"
},
  "geometry": {"coordinates":[-0.2093590051,51.4225997925],"type":"Point"}
}