{
  "type": "Feature",
  "properties": {
    "addr:full":"Red Cedars, Haughley Grn, Haughley Stowmarket Suffolk IP14 3RR",
    "addr:postcode":"ip14 3rr",
    "addr:street":"Red;Haughley Grn",
    "iso:country":"GB",
    "sg:address":"Red Cedars, Haughley Grn, Haughley",
    "sg:city":"Stowmarket",
    "sg:classifiers":[
        {
            "category":"Organizations",
            "subcategory":"Non-profit Organization",
            "type":"Services"
        }
    ],
    "sg:phone":"+44 1449 774018",
    "sg:postcode":"IP14 3RR",
    "sg:province":"Suffolk",
    "sg:tags":[
        "organisation",
        "voluntary",
        "charity"
    ],
    "wof:name":"Alzheimer's Disease Society",
    "wof:placetype":"venue"
},
  "geometry": {"coordinates":[0.9713249803,52.2197265625],"type":"Point"}
}