{
  "type": "Feature",
  "properties": {
    "addr:full":"Unit 2 Newspaper House, Tannery Lane, Penketh Warrington Cheshire WA5 2UD",
    "addr:housenumber":"unit 2 newspaper house",
    "addr:postcode":"wa5 2ud",
    "addr:street":"Tannery Lane",
    "iso:country":"GB",
    "sg:address":"Unit 2 Newspaper House, Tannery Lane, Penketh",
    "sg:city":"Warrington",
    "sg:classifiers":[
        {
            "category":"Professional",
            "subcategory":"Testing Lab",
            "type":"Services"
        }
    ],
    "sg:phone":"+44 1925 726677",
    "sg:postcode":"WA5 2UD",
    "sg:province":"Cheshire",
    "sg:tags":[
        "inspection",
        "calibration"
    ],
    "wof:name":"E & I Hire Ltd.",
    "wof:placetype":"venue"
},
  "geometry": {"coordinates":[-2.6718459129,53.3796386719],"type":"Point"}
}