{
  "type": "Feature",
  "properties": {
    "iso:country":"GB",
    "sg:address":"North Green Street",
    "sg:city":"Bristol",
    "sg:classifiers":[
        {
            "category":"Retail",
            "subcategory":"Auto Repair",
            "type":"Services"
        }
    ],
    "sg:postcode":"BS8 4NE",
    "sg:province":"City of Bristol",
    "sg:tags":[
        "body",
        "car"
    ],
    "wof:name":"Polygon Garage",
    "wof:placetype":"venue"
},
  "geometry": {"coordinates":[-2.620869,51.451195],"type":"Point"}
}