{
  "type": "Feature",
  "properties": {
    "iso:country":"GB",
    "sg:address":"12 Rose Hill Ave",
    "sg:city":"Blackburn",
    "sg:classifiers":[
        {
            "category":"Home & Garden",
            "subcategory":"Building Materials",
            "type":"Retail Goods"
        }
    ],
    "sg:postcode":"BB1 1YF",
    "sg:province":"Lancashire",
    "sg:tags":[
        "ironwork",
        "diy",
        "wrought"
    ],
    "wof:name":"Beck,Joe,",
    "wof:placetype":"venue"
},
  "geometry": {"coordinates":[-2.469885,53.747131],"type":"Point"}
}