{
  "type": "Feature",
  "properties": {
    "addr:full":"15 Inchgarvie Park South Queensferry City of Edinburgh EH30 9RN",
    "addr:housenumber":"15",
    "addr:postcode":"eh30 9rn",
    "addr:street":"Inchgarvie Park South",
    "iso:country":"GB",
    "sg:address":"15 Inchgarvie Park",
    "sg:city":"South Queensferry",
    "sg:classifiers":[
        {
            "category":"Retail",
            "subcategory":"Laundry & Dry Cleaning",
            "type":"Services"
        }
    ],
    "sg:postcode":"EH30 9RN",
    "sg:province":"City of Edinburgh",
    "sg:tags":[
        "alteration"
    ],
    "wof:name":"Stitch by Stitch",
    "wof:placetype":"venue"
},
  "geometry": {"coordinates":[-3.4085659981,55.9910316467],"type":"Point"}
}