{
  "type": "Feature",
  "properties": {
    "addr:full":"46 Green Street Gillingham Kent ME7 1XA",
    "addr:housenumber":"46",
    "addr:postcode":"me7 1xa",
    "addr:street":"Green Street",
    "iso:country":"GB",
    "sg:address":"46 Green Street",
    "sg:city":"Gillingham",
    "sg:classifiers":[
        {
            "category":"Organizations",
            "subcategory":"Non-profit Organization",
            "type":"Services"
        }
    ],
    "sg:phone":"+44 1634 570717",
    "sg:postcode":"ME7 1XA",
    "sg:province":"Kent",
    "sg:tags":[
        "organisation",
        "voluntary",
        "charity"
    ],
    "wof:name":"Medway Home-Start",
    "wof:placetype":"venue"
},
  "geometry": {"coordinates":[0.546565,51.385986],"type":"Point"}
}