{
  "type": "Feature",
  "properties": {
    "addr:full":"15 Drysdale Street Liverpool Merseyside L8 9XA",
    "addr:housenumber":"15",
    "addr:postcode":"l8 9xa",
    "addr:street":"Drysdale Street",
    "iso:country":"GB",
    "sg:address":"15 Drysdale Street",
    "sg:city":"Liverpool",
    "sg:classifiers":[
        {
            "category":"Travel",
            "subcategory":"Hostel",
            "type":"Entertainment"
        },
        {
            "category":"Government",
            "subcategory":"Office",
            "type":"Public Place"
        }
    ],
    "sg:phone":"+44 151 727 4591",
    "sg:postcode":"L8 9XA",
    "sg:province":"Merseyside",
    "sg:tags":[
        "local"
    ],
    "wof:name":"Drysdale Street Hostel",
    "wof:placetype":"venue"
},
  "geometry": {"coordinates":[-2.9663090706,53.380191803],"type":"Point"}
}