{
  "type": "Feature",
  "properties": {
    "addr:full":"43a Bells La Burntwood Staffordshire WS7 8PD",
    "addr:housenumber":"43a",
    "addr:postcode":"ws7 8pd",
    "addr:street":"Bells La Burntwood",
    "iso:country":"GB",
    "sg:address":"43a Bells La",
    "sg:city":"Burntwood",
    "sg:classifiers":[
        {
            "category":"Shopping",
            "subcategory":"Department Store",
            "type":"Retail Goods"
        }
    ],
    "sg:phone":"+44 1543 675869",
    "sg:postcode":"WS7 8PD",
    "sg:province":"Staffordshire",
    "wof:name":"Spinney Stores",
    "wof:placetype":"venue"
},
  "geometry": {"coordinates":[-1.928264,52.689297],"type":"Point"}
}