{
  "type": "Feature",
  "properties": {
    "addr:full":"786 Wimborne Road Bournemouth Dorset BH9 2DX",
    "addr:housenumber":"786",
    "addr:postcode":"bh9 2dx",
    "addr:street":"Wimborne Road",
    "iso:country":"GB",
    "sg:address":"786 Wimborne Road",
    "sg:city":"Bournemouth",
    "sg:classifiers":[
        {
            "category":"Manufacturing",
            "subcategory":"Petroleum Products",
            "type":"Manufacturing & Wholesale Goods"
        },
        {
            "category":"Building & Trades",
            "subcategory":"Construction",
            "type":"Services"
        }
    ],
    "sg:postcode":"BH9 2DX",
    "sg:province":"Dorset",
    "sg:tags":[
        "double",
        "window",
        "glazing",
        "replacement"
    ],
    "wof:name":"Weru Windows & Doors",
    "wof:placetype":"venue"
},
  "geometry": {"coordinates":[-1.8771049976,50.7511367798],"type":"Point"}
}