{
  "type": "Feature",
  "properties": {
    "addr:full":"44 Stamford St East Ashton-under-lyne Greater Manchester OL6 6QH",
    "addr:housenumber":"44",
    "addr:postcode":"ol6 6qh",
    "addr:street":"Stamford St",
    "iso:country":"GB",
    "sg:address":"44 Stamford St East",
    "sg:city":"Ashton-under-lyne",
    "sg:classifiers":[
        {
            "category":"Professional",
            "subcategory":"Employment Agencies",
            "type":"Services"
        }
    ],
    "sg:phone":"+44 161 343 5190",
    "sg:postcode":"OL6 6QH",
    "sg:province":"Greater Manchester",
    "sg:tags":[
        "consultant"
    ],
    "wof:name":"Labour Pool Ltd.",
    "wof:placetype":"venue"
},
  "geometry": {"coordinates":[-2.086711,53.488174],"type":"Point"}
}