{
  "type": "Feature",
  "properties": {
    "iso:country":"GB",
    "sg:address":"Unit 1 Harris Rd",
    "sg:city":"Calne",
    "sg:classifiers":[
        {
            "category":"Manufacturing",
            "subcategory":"Electronics",
            "type":"Manufacturing & Wholesale Goods"
        }
    ],
    "sg:phone":"+44 1249 822122",
    "sg:postcode":"SN11 9PT",
    "sg:province":"Wiltshire",
    "sg:tags":[
        "control",
        "component",
        "-",
        "electronic"
    ],
    "wof:name":"Molypress Ltd",
    "wof:placetype":"venue"
},
  "geometry": {"coordinates":[-1.997309,51.450031],"type":"Point"}
}