{
  "type": "Feature",
  "properties": {
    "addr:full":"143 Northdown Road, Cliftonville Margate Kent CT9 2QY",
    "addr:housenumber":"143",
    "addr:postcode":"ct9 2qy",
    "addr:street":"Northdown Road;Margate",
    "iso:country":"GB",
    "sg:address":"143 Northdown Road, Cliftonville",
    "sg:city":"Margate",
    "sg:classifiers":[
        {
            "category":"Building & Trades",
            "subcategory":"Construction",
            "type":"Services"
        }
    ],
    "sg:phone":"+44 1843 221506",
    "sg:postcode":"CT9 2QY",
    "sg:province":"Kent",
    "sg:tags":[
        "tiling",
        "contractor"
    ],
    "wof:name":"Maurice Blackman Ltd.",
    "wof:placetype":"venue"
},
  "geometry": {"coordinates":[1.3959800005,51.388217926],"type":"Point"}
}