{
  "type": "Feature",
  "properties": {
    "iso:country":"GB",
    "sg:address":"The Laurels",
    "sg:city":"Blandford Forum",
    "sg:classifiers":[
        {
            "category":"Real Estate",
            "subcategory":"Developer",
            "type":"Services"
        }
    ],
    "sg:phone":"+44 1258 480399",
    "sg:postcode":"DT11 9AF",
    "sg:province":"Dorset",
    "sg:tags":[
        "property"
    ],
    "wof:name":"L G Developments",
    "wof:placetype":"venue"
},
  "geometry": {"coordinates":[-2.2015020847,50.9142951965],"type":"Point"}
}