{
  "type": "Feature",
  "properties": {
    "addr:full":"Sutton Centre, High Pavement Sutton-in-ashfield Nottinghamshire NG17 1EE",
    "addr:housenumber":"sutton-in-ashfield",
    "addr:postcode":"ng17 1ee",
    "addr:street":"High Pavement",
    "iso:country":"GB",
    "sg:address":"Sutton Centre, High Pavement",
    "sg:city":"Sutton-in-ashfield",
    "sg:classifiers":[
        {
            "category":"Education",
            "subcategory":"Special Training",
            "type":"Public Place"
        },
        {
            "category":"Government",
            "subcategory":"Office",
            "type":"Public Place"
        }
    ],
    "sg:phone":"+44 1623 441310",
    "sg:postcode":"NG17 1EE",
    "sg:province":"Nottinghamshire",
    "sg:tags":[
        "product",
        "local",
        "centre"
    ],
    "wof:name":"Sutton Centre",
    "wof:placetype":"venue"
},
  "geometry": {"coordinates":[-1.2625470161,53.1222267151],"type":"Point"}
}