{
  "type": "Feature",
  "properties": {
    "addr:full":"Mayorality House, The Quay Looe Cornwall PL13 2BU",
    "addr:postcode":"pl13 2bu",
    "addr:street":"The Quay",
    "iso:country":"GB",
    "sg:address":"Mayorality House, The Quay",
    "sg:city":"Looe",
    "sg:classifiers":[
        {
            "category":"Organizations",
            "subcategory":"Membership Organization",
            "type":"Services"
        }
    ],
    "sg:phone":"+44 1503 262479",
    "sg:postcode":"PL13 2BU",
    "sg:province":"Cornwall",
    "sg:tags":[
        "club"
    ],
    "wof:name":"Looe Social Club",
    "wof:placetype":"venue"
},
  "geometry": {"coordinates":[-4.4623551369,50.3561210632],"type":"Point"}
}