{
  "type": "Feature",
  "properties": {
    "iso:country":"GB",
    "sg:address":"Lords Oak",
    "sg:city":"Salisbury",
    "sg:classifiers":[
        {
            "category":"Personal",
            "type":"Services"
        }
    ],
    "sg:postcode":"SP5 2DW",
    "sg:province":"Dorset",
    "sg:tags":[
        "wedding"
    ],
    "wof:name":"New Forest Wedding Car Hire",
    "wof:placetype":"venue"
},
  "geometry": {"coordinates":[-1.63033,50.95929],"type":"Point"}
}