{
  "type": "Feature",
  "properties": {
    "iso:country":"GB",
    "sg:address":"Unit 3 Borough Rd",
    "sg:city":"Brackley",
    "sg:classifiers":[
        {
            "category":"Home & Garden",
            "subcategory":"Furniture",
            "type":"Retail Goods"
        }
    ],
    "sg:postcode":"NN13 7BE",
    "sg:province":"Buckinghamshire",
    "wof:name":"Simmons,Geraldine,",
    "wof:placetype":"venue"
},
  "geometry": {"coordinates":[-1.141674,52.023457],"type":"Point"}
}