{
  "type": "Feature",
  "properties": {
    "iso:country":"GB",
    "sg:address":"5 Mill Bridge",
    "sg:city":"Skipton",
    "sg:classifiers":[
        {
            "category":"Personal",
            "subcategory":"Beauty Salon",
            "type":"Services"
        }
    ],
    "sg:postcode":"BD23 1NJ",
    "sg:province":"Lancashire",
    "sg:tags":[
        "unisex",
        "hairdresser"
    ],
    "wof:name":"Meghan Wright",
    "wof:placetype":"venue"
},
  "geometry": {"coordinates":[-2.0168430805,53.9633026123],"type":"Point"}
}