{
  "type": "Feature",
  "properties": {
    "iso:country":"GB",
    "sg:address":"West End Road, Stratton St Margaret",
    "sg:city":"Swindon",
    "sg:classifiers":[
        {
            "category":"Retail",
            "subcategory":"Auto Repair",
            "type":"Services"
        }
    ],
    "sg:postcode":"SN3 4PG",
    "sg:province":"Wiltshire",
    "sg:tags":[
        "modification",
        "garage"
    ],
    "wof:name":"Stratton Crash Repairs",
    "wof:placetype":"venue"
},
  "geometry": {"coordinates":[-1.754804,51.57653],"type":"Point"}
}