{
  "type": "Feature",
  "properties": {
    "iso:country":"GB",
    "sg:address":"15 Heron Clo",
    "sg:city":"Bradford",
    "sg:classifiers":[
        {
            "category":"Education",
            "subcategory":"Special Training",
            "type":"Public Place"
        }
    ],
    "sg:phone":"+44 1274 818346",
    "sg:postcode":"BD13 1NR",
    "sg:province":"West Yorkshire",
    "sg:tags":[
        "product",
        "centre"
    ],
    "wof:name":"Training Consortium The",
    "wof:placetype":"venue"
},
  "geometry": {"coordinates":[-1.862764,53.773891],"type":"Point"}
}