{
  "type": "Feature",
  "properties": {
    "addr:full":"Walthamstow, 6-10 Church Hill London Greater London E17 3RY",
    "addr:housenumber":"6-10",
    "addr:postcode":"e17 3ry",
    "addr:street":"Church Hill",
    "iso:country":"GB",
    "sg:address":"Walthamstow, 6-10 Church Hill",
    "sg:city":"London",
    "sg:classifiers":[
        {
            "category":"Government",
            "subcategory":"Office",
            "type":"Public Place"
        }
    ],
    "sg:phone":"+44 20885218821",
    "sg:postcode":"E17 3RY",
    "sg:province":"Greater London",
    "sg:tags":[
        "inland",
        "revenue"
    ],
    "wof:name":"Inland Revenue",
    "wof:placetype":"venue"
},
  "geometry": {"coordinates":[-0.01235,51.585739],"type":"Point"}
}