{
  "type": "Feature",
  "properties": {
    "iso:country":"GB",
    "sg:address":"Thelnetham Rd",
    "sg:city":"Diss",
    "sg:classifiers":[
        {
            "category":"Shopping",
            "subcategory":"Department Store",
            "type":"Retail Goods"
        }
    ],
    "sg:postcode":"IP22 2QY",
    "sg:province":"Norfolk",
    "wof:name":"Norfolk House Stores",
    "wof:placetype":"venue"
},
  "geometry": {"coordinates":[0.9559720159,52.3751373291],"type":"Point"}
}