{
  "type": "Feature",
  "properties": {
    "iso:country":"GB",
    "sg:address":"Bassett Street",
    "sg:city":"Cardiff",
    "sg:classifiers":[
        {
            "category":"Social Services",
            "subcategory":"Adult Care",
            "type":"Services"
        },
        {
            "category":"Social Services",
            "subcategory":"Retirement Home",
            "type":"Services"
        }
    ],
    "sg:phone":"+44 29 2038 3177",
    "sg:postcode":"CF5 1PY",
    "sg:province":"Cardiff",
    "sg:tags":[
        "housing",
        "sheltered",
        "accommodation"
    ],
    "wof:name":"Great Western Court",
    "wof:placetype":"venue"
},
  "geometry": {"coordinates":[-3.2044439316,51.4785957336],"type":"Point"}
}