{
  "type": "Feature",
  "properties": {
    "iso:country":"GB",
    "sg:address":"Bellamy Ho, 13 West St",
    "sg:city":"Cromer",
    "sg:classifiers":[
        {
            "category":"Building & Trades",
            "subcategory":"Construction",
            "type":"Services"
        }
    ],
    "sg:phone":"+44 1263 512907",
    "sg:postcode":"NR27 9HZ",
    "sg:province":"Norfolk",
    "sg:tags":[
        "builder"
    ],
    "wof:name":"McCoy Construction Ltd",
    "wof:placetype":"venue"
},
  "geometry": {"coordinates":[1.30311,52.928814],"type":"Point"}
}