{
  "type": "Feature",
  "properties": {
    "iso:country":"GB",
    "sg:address":"406 Railway Arches, Long Street",
    "sg:city":"London",
    "sg:classifiers":[
        {
            "category":"Education",
            "subcategory":"Library",
            "type":"Public Place"
        }
    ],
    "sg:phone":"+44 20 7739 5622",
    "sg:postcode":"E2 8HG",
    "sg:province":"Greater London",
    "sg:tags":[
        "reproduction",
        "furniture"
    ],
    "wof:name":"Elva Wholesale Ltd.",
    "wof:placetype":"venue"
},
  "geometry": {"coordinates":[-0.0759499967,51.5299415588],"type":"Point"}
}