{
  "type": "Feature",
  "properties": {
    "addr:full":"38 Heol Pwll-y-pant Caerphilly Caerphilly CF83 2ND",
    "addr:housenumber":"38",
    "addr:postcode":"cf83 2nd",
    "addr:street":"Heol Pwll-Y-Pant",
    "iso:country":"GB",
    "sg:address":"38 Heol Pwll-y-pant",
    "sg:city":"Caerphilly",
    "sg:classifiers":[
        {
            "category":"Manufacturing",
            "subcategory":"Tools & Machinery",
            "type":"Manufacturing & Wholesale Goods"
        }
    ],
    "sg:phone":"+44 29 2085 1680",
    "sg:postcode":"CF83 2ND",
    "sg:province":"Caerphilly",
    "sg:tags":[
        "polishing",
        "cleaning",
        "floor"
    ],
    "wof:name":"Flawless Flooring",
    "wof:placetype":"venue"
},
  "geometry": {"coordinates":[-3.2315809727,51.5904006958],"type":"Point"}
}