{
  "type": "Feature",
  "properties": {
    "addr:full":"135 Caldbeck Avenue Worcester Park Surrey KT4 8BJ",
    "addr:housenumber":"135",
    "addr:postcode":"kt4 8bj",
    "addr:street":"Caldbeck Avenue",
    "iso:country":"GB",
    "sg:address":"135 Caldbeck Avenue",
    "sg:city":"Worcester Park",
    "sg:classifiers":[
        {
            "category":"Professional",
            "subcategory":"Printing & Photocopies",
            "type":"Services"
        }
    ],
    "sg:postcode":"KT4 8BJ",
    "sg:province":"Surrey",
    "sg:tags":[
        "process",
        "screen",
        "printer"
    ],
    "wof:name":"D C Signs",
    "wof:placetype":"venue"
},
  "geometry": {"coordinates":[-0.2385240048,51.382434845],"type":"Point"}
}