{
  "type": "Feature",
  "properties": {
    "addr:full":"8 Cheapside, North Circular Rd Palmers Green Greater London N13 5ED",
    "addr:housenumber":"8",
    "addr:postcode":"n13 5ed",
    "addr:street":"Cheapside North Circular Rd",
    "iso:country":"GB",
    "sg:address":"8 Cheapside, North Circular Rd",
    "sg:city":"Palmers Green",
    "sg:classifiers":[
        {
            "category":"Autos & Motor Vehicles",
            "subcategory":"Auto Supplies",
            "type":"Retail Goods"
        }
    ],
    "sg:phone":"+44 20 8803 4823",
    "sg:postcode":"N13 5ED",
    "sg:province":"Greater London",
    "sg:tags":[
        "windscreen"
    ],
    "wof:name":"Silver Shield Automotive Windscreens",
    "wof:placetype":"venue"
},
  "geometry": {"coordinates":[-0.08748,51.61673],"type":"Point"}
}