{
  "type": "Feature",
  "properties": {
    "iso:country":"GB",
    "sg:address":"66 Newport Road",
    "sg:city":"Barnstaple",
    "sg:classifiers":[
        {
            "category":"Food & Beverages",
            "subcategory":"Meat & Fish",
            "type":"Retail Goods"
        }
    ],
    "sg:phone":"+44 1271 344914",
    "sg:postcode":"EX32 9BG",
    "sg:province":"Devon",
    "sg:tags":[
        "butcher"
    ],
    "wof:name":"M B Norman",
    "wof:placetype":"venue"
},
  "geometry": {"coordinates":[-4.0477881432,51.0717926025],"type":"Point"}
}