{
  "type": "Feature",
  "properties": {
    "addr:full":"29 North Street Pembroke Dock Pembrokeshire SA72 6QT",
    "addr:housenumber":"29",
    "addr:postcode":"sa72 6qt",
    "addr:street":"North Street",
    "iso:country":"GB",
    "sg:address":"29 North Street",
    "sg:city":"Pembroke Dock",
    "sg:classifiers":[
        {
            "category":"Professional",
            "subcategory":"Business Services",
            "type":"Services"
        }
    ],
    "sg:phone":"+44 1646 621497",
    "sg:postcode":"SA72 6QT",
    "sg:province":"Pembrokeshire",
    "wof:name":"Llojen",
    "wof:placetype":"venue"
},
  "geometry": {"coordinates":[-4.9441828728,51.6870422363],"type":"Point"}
}