{
  "type": "Feature",
  "properties": {
    "iso:country":"GB",
    "sg:address":"Unit 6 Northside Centre",
    "sg:city":"Street",
    "sg:classifiers":[
        {
            "category":"Shopping",
            "subcategory":"Pharmacy",
            "type":"Retail Goods"
        }
    ],
    "sg:phone":"+44 1458 447227",
    "sg:postcode":"BA16 0HN",
    "sg:province":"Somerset",
    "sg:tags":[
        "store",
        "drug"
    ],
    "wof:name":"Lloyds Health & Beauty",
    "wof:placetype":"venue"
},
  "geometry": {"coordinates":[-2.740859,51.126251],"type":"Point"}
}