{
  "type": "Feature",
  "properties": {
    "addr:full":"189f South Coast Road Peacehaven East Sussex BN10 8NS",
    "addr:housenumber":"189f",
    "addr:postcode":"bn10 8ns",
    "addr:street":"South Coast Road Peacehaven",
    "iso:country":"GB",
    "sg:address":"189f South Coast Road",
    "sg:city":"Peacehaven",
    "sg:classifiers":[
        {
            "category":"Professional",
            "subcategory":"Computer Services",
            "type":"Services"
        }
    ],
    "sg:phone":"+44 1273 243030",
    "sg:postcode":"BN10 8NS",
    "sg:province":"East Sussex",
    "sg:tags":[
        "system",
        "software"
    ],
    "wof:name":"Giant Technologies Ltd.",
    "wof:placetype":"venue"
},
  "geometry": {"coordinates":[0.002595,50.7907295227],"type":"Point"}
}