{
  "type": "Feature",
  "properties": {
    "iso:country":"GB",
    "sg:address":"Hetton Resource Centre, Office Pl",
    "sg:city":"Houghton Le Spring",
    "sg:classifiers":[
        {
            "category":"Social Services",
            "subcategory":"Retirement Home",
            "type":"Services"
        }
    ],
    "sg:phone":"+44 191 517 1479",
    "sg:postcode":"DH5 9JG",
    "sg:province":"Durham",
    "sg:tags":[
        "care"
    ],
    "wof:name":"Hetton Home Care Service",
    "wof:placetype":"venue"
},
  "geometry": {"coordinates":[-1.468647,54.838879],"type":"Point"}
}