{
  "type": "Feature",
  "properties": {
    "addr:full":"88 Coupe Drive Stoke-on-trent Staffordshire ST3 5HS",
    "addr:housenumber":"88",
    "addr:postcode":"st3 5hs",
    "addr:street":"Coupe Drive",
    "iso:country":"GB",
    "sg:address":"88 Coupe Drive",
    "sg:city":"Stoke-on-trent",
    "sg:classifiers":[
        {
            "category":"Building & Trades",
            "subcategory":"Construction",
            "type":"Services"
        }
    ],
    "sg:phone":"+44 1782 315931",
    "sg:postcode":"ST3 5HS",
    "sg:province":"Staffordshire",
    "sg:tags":[
        "decorator",
        "painter"
    ],
    "wof:name":"Graham Bourne",
    "wof:placetype":"venue"
},
  "geometry": {"coordinates":[-2.0984930992,52.9958114624],"type":"Point"}
}