{
  "type": "Feature",
  "properties": {
    "iso:country":"GB",
    "sg:address":"52 Horton Road",
    "sg:city":"Poole",
    "sg:classifiers":[
        {
            "category":"Professional",
            "subcategory":"Printing & Photocopies",
            "type":"Services"
        }
    ],
    "sg:phone":"+44 1202 631831",
    "sg:postcode":"BH16 6LQ",
    "sg:province":"Dorset",
    "sg:tags":[
        "plate",
        "lithographic",
        "maker"
    ],
    "wof:name":"Willow Studios",
    "wof:placetype":"venue"
},
  "geometry": {"coordinates":[-2.0723690987,50.7335395813],"type":"Point"}
}