{
  "type": "Feature",
  "properties": {
    "addr:full":"9-11 High Street Hampton Greater London TW12 2SA",
    "addr:housenumber":"9-11",
    "addr:postcode":"tw12 2sa",
    "addr:street":"High Street",
    "iso:country":"GB",
    "sg:address":"9-11 High Street",
    "sg:city":"Hampton",
    "sg:classifiers":[
        {
            "category":"Professional",
            "subcategory":"Art Services",
            "type":"Services"
        }
    ],
    "sg:phone":"+44 20 8941 7755",
    "sg:postcode":"TW12 2SA",
    "sg:province":"Greater London",
    "sg:tags":[
        "graphic",
        "designer"
    ],
    "wof:name":"Cooling Brown",
    "wof:placetype":"venue"
},
  "geometry": {"coordinates":[-0.3625690043,51.4136199951],"type":"Point"}
}