{
  "type": "Feature",
  "properties": {
    "iso:country":"GB",
    "sg:address":"Unit 6 Perivale Industrial Park, Horsenden Lane South",
    "sg:city":"Greenford",
    "sg:classifiers":[
        {
            "category":"Manufacturing",
            "subcategory":"Metals",
            "type":"Manufacturing & Wholesale Goods"
        }
    ],
    "sg:phone":"+44 20 8998 4321",
    "sg:postcode":"UB6 7RL",
    "sg:province":"Greater London",
    "sg:tags":[
        "steel",
        "mnfrs"
    ],
    "wof:name":"Fendor Hansen",
    "wof:placetype":"venue"
},
  "geometry": {"coordinates":[-0.3399,51.549271],"type":"Point"}
}