{
  "type": "Feature",
  "properties": {
    "iso:country":"GB",
    "sg:address":"The Stable Block, Cornbury Park, Charlbury",
    "sg:city":"Chipping Norton",
    "sg:classifiers":[
        {
            "category":"Wholesale",
            "subcategory":"Medical Equipment & Supplies",
            "type":"Manufacturing & Wholesale Goods"
        }
    ],
    "sg:phone":"+44 1608 811822",
    "sg:postcode":"OX7 3EH",
    "sg:province":"Gloucestershire",
    "wof:name":"Steris Ltd.",
    "wof:placetype":"venue"
},
  "geometry": {"coordinates":[-1.4756430387,51.8729782104],"type":"Point"}
}