{
  "type": "Feature",
  "properties": {
    "addr:full":"114 Ruislip Road Greenford Greater London UB6 9QH",
    "addr:housenumber":"114",
    "addr:postcode":"ub6 9qh",
    "addr:street":"Ruislip Road",
    "iso:country":"GB",
    "sg:address":"114 Ruislip Road",
    "sg:city":"Greenford",
    "sg:classifiers":[
        {
            "category":"Shopping",
            "type":"Retail Goods"
        }
    ],
    "sg:postcode":"UB6 9QH",
    "sg:province":"Greater London",
    "sg:tags":[
        "part",
        "accessory"
    ],
    "wof:name":"Sound Around",
    "wof:placetype":"venue"
},
  "geometry": {"coordinates":[-0.363698,51.530018],"type":"Point"}
}