{
  "type": "Feature",
  "properties": {
    "addr:full":"14 Sycamore Way Chelmsford Essex CM2 9NA",
    "addr:housenumber":"14",
    "addr:postcode":"cm2 9na",
    "addr:street":"Sycamore Way",
    "iso:country":"GB",
    "sg:address":"14 Sycamore Way",
    "sg:city":"Chelmsford",
    "sg:classifiers":[
        {
            "category":"Building & Trades",
            "subcategory":"Plumbing",
            "type":"Services"
        }
    ],
    "sg:postcode":"CM2 9NA",
    "sg:province":"Essex",
    "sg:tags":[
        "heating"
    ],
    "wof:name":"Peter Lampey Plumbing & Heating",
    "wof:placetype":"venue"
},
  "geometry": {"coordinates":[0.4774520099,51.7150611877],"type":"Point"}
}