{
  "type": "Feature",
  "properties": {
    "iso:country":"GB",
    "sg:address":"Cyma Ho, Dunkirk Rd",
    "sg:city":"Lincoln",
    "sg:classifiers":[
        {
            "category":"Shopping",
            "subcategory":"Computers & Home Electronics",
            "type":"Retail Goods"
        }
    ],
    "sg:phone":"+44 1522 544000",
    "sg:postcode":"LN1 3UJ",
    "sg:province":"Lincolnshire",
    "wof:name":"Cyma Ltd",
    "wof:placetype":"venue"
},
  "geometry": {"coordinates":[-0.545066,53.245701],"type":"Point"}
}