{
  "type": "Feature",
  "properties": {
    "addr:full":"Navigator House Kingston-upon-thames Greater London KT1 4DB",
    "addr:postcode":"kt1 4db",
    "addr:street":"Kingston-Upon-Thames",
    "iso:country":"GB",
    "sg:address":"Navigator House",
    "sg:city":"Kingston-upon-thames",
    "sg:classifiers":[
        {
            "category":"Building & Trades",
            "subcategory":"Landscaping Services",
            "type":"Services"
        }
    ],
    "sg:phone":"+44 20 8977 3522",
    "sg:postcode":"KT1 4DB",
    "sg:province":"Greater London",
    "sg:tags":[
        "design",
        "garden"
    ],
    "wof:name":"Cleve West Garden Design",
    "wof:placetype":"venue"
},
  "geometry": {"coordinates":[-0.3092789948,51.4112167358],"type":"Point"}
}