{
  "type": "Feature",
  "properties": {
    "iso:country":"GB",
    "sg:address":"39 Southside Street",
    "sg:city":"Plymouth",
    "sg:classifiers":[
        {
            "category":"Home & Garden",
            "subcategory":"Home Furnishings",
            "type":"Retail Goods"
        }
    ],
    "sg:phone":"+44 1752 262555",
    "sg:postcode":"PL1 2LE",
    "sg:province":"Devon",
    "sg:tags":[
        "candle"
    ],
    "wof:name":"Aromoglow",
    "wof:placetype":"venue"
},
  "geometry": {"coordinates":[-4.135421,50.367294],"type":"Point"}
}