{
  "type": "Feature",
  "properties": {
    "addr:full":"50 Newhall Street Birmingham West Midlands B3 3QE",
    "addr:housenumber":"50",
    "addr:postcode":"b3 3qe",
    "addr:street":"Newhall Street",
    "iso:country":"GB",
    "sg:address":"50 Newhall Street",
    "sg:city":"Birmingham",
    "sg:classifiers":[
        {
            "category":"Professional",
            "subcategory":"Accounting & Tax Preparation",
            "type":"Services"
        }
    ],
    "sg:phone":"+44 121 248 4084",
    "sg:postcode":"B3 3QE",
    "sg:province":"West Midlands",
    "sg:tags":[
        "accountant"
    ],
    "wof:name":"Napiers Ltd.",
    "wof:placetype":"venue"
},
  "geometry": {"coordinates":[-1.902959,52.481827],"type":"Point"}
}