{
  "type": "Feature",
  "properties": {
    "addr:full":"Craven House, Craven Road Newbury Berkshire RG14 5NE",
    "addr:postcode":"rg14 5ne",
    "addr:street":"Craven Road",
    "iso:country":"GB",
    "sg:address":"Craven House, Craven Road",
    "sg:city":"Newbury",
    "sg:classifiers":[
        {
            "category":"Professional",
            "subcategory":"Printing & Photocopies",
            "type":"Services"
        }
    ],
    "sg:phone":"+44 1635 42492",
    "sg:postcode":"RG14 5NE",
    "sg:province":"Berkshire",
    "sg:tags":[
        "printer"
    ],
    "wof:name":"Pentalith Ltd.",
    "wof:placetype":"venue"
},
  "geometry": {"coordinates":[-1.3294500113,51.3991203308],"type":"Point"}
}