{
  "type": "Feature",
  "properties": {
    "iso:country":"GB",
    "sg:address":"127 Castle Rd",
    "sg:city":"Bedford",
    "sg:classifiers":[
        {
            "category":"Professional",
            "subcategory":"Engineering",
            "type":"Services"
        }
    ],
    "sg:phone":"+44 1234 351865",
    "sg:postcode":"MK40 3RT",
    "sg:province":"Bedfordshire",
    "sg:tags":[
        "ge",
        "engineer",
        "mechanical"
    ],
    "wof:name":"Advanced Magnetic Technology Ltd",
    "wof:placetype":"venue"
},
  "geometry": {"coordinates":[-0.4534809887,52.1370239258],"type":"Point"}
}