{
  "type": "Feature",
  "properties": {
    "addr:full":"Meridian Gate, 203 Marsh Wall London Greater London E14 9YT",
    "addr:housenumber":"203",
    "addr:postcode":"e14 9yt",
    "addr:street":"Meridian Gate;Marsh Wall",
    "iso:country":"GB",
    "sg:address":"Meridian Gate, 203 Marsh Wall",
    "sg:city":"London",
    "sg:classifiers":[
        {
            "category":"Travel",
            "subcategory":"Travel Agent",
            "type":"Entertainment"
        }
    ],
    "sg:phone":"+44 20 7363 6200",
    "sg:postcode":"E14 9YT",
    "sg:province":"Greater London",
    "wof:name":"Alan Kingston",
    "wof:placetype":"venue"
},
  "geometry": {"coordinates":[-0.01319,51.49992],"type":"Point"}
}