{
  "type": "Feature",
  "properties": {
    "iso:country":"GB",
    "sg:address":"Unit 1 Kirk Business Centre, Castle Road, Lerwick",
    "sg:city":"Shetland",
    "sg:classifiers":[
        {
            "category":"Professional",
            "subcategory":"Management & Consulting",
            "type":"Services"
        }
    ],
    "sg:phone":"+44 1595 880852",
    "sg:postcode":"ZE1 0TF",
    "sg:province":"Shetland Islands",
    "sg:tags":[
        "consultant",
        "business"
    ],
    "wof:name":"A B Associates Ltd.",
    "wof:placetype":"venue"
},
  "geometry": {"coordinates":[-1.170289,60.144829],"type":"Point"}
}