{
  "type": "Feature",
  "properties": {
    "addr:full":"17 Main Street, Methven Perth Perth and Kinross PH1 3PU",
    "addr:housenumber":"17",
    "addr:postcode":"ph1 3pu",
    "addr:street":"Main Street",
    "iso:country":"GB",
    "sg:address":"17 Main Street, Methven",
    "sg:city":"Perth",
    "sg:classifiers":[
        {
            "category":"Autos & Motor Vehicles",
            "subcategory":"Automobile Sales",
            "type":"Retail Goods"
        }
    ],
    "sg:postcode":"PH1 3PU",
    "sg:province":"Perth and Kinross",
    "sg:tags":[
        "car"
    ],
    "wof:name":"D S Motors Ltd.",
    "wof:placetype":"venue"
},
  "geometry": {"coordinates":[-3.5166149139,56.4165267944],"type":"Point"}
}