{
  "type": "Feature",
  "properties": {
    "addr:full":"18 Carlton Road, Smithies Barnsley South Yorkshire S71 1UA",
    "addr:housenumber":"18",
    "addr:postcode":"s71 1ua",
    "addr:street":"Carlton Road Smithies;Yorkshire",
    "iso:country":"GB",
    "sg:address":"18 Carlton Road, Smithies",
    "sg:city":"Barnsley",
    "sg:classifiers":[
        {
            "category":"Manufacturing",
            "subcategory":"Building Materials",
            "type":"Manufacturing & Wholesale Goods"
        }
    ],
    "sg:phone":"+44 1226 733722",
    "sg:postcode":"S71 1UA",
    "sg:province":"South Yorkshire",
    "sg:tags":[
        "merchant",
        "builder"
    ],
    "wof:name":"Hills Building Supplies Ltd.",
    "wof:placetype":"venue"
},
  "geometry": {"coordinates":[-1.4710170031,53.5698814392],"type":"Point"}
}