{
  "type": "Feature",
  "properties": {
    "iso:country":"GB",
    "sg:address":"8-10 Favell Road",
    "sg:city":"Sheffield",
    "sg:classifiers":[
        {
            "category":"Professional",
            "subcategory":"Employment Agencies",
            "type":"Services"
        },
        {
            "category":"Education",
            "subcategory":"University",
            "type":"Public Place"
        }
    ],
    "sg:phone":"+44 114 222 0954",
    "sg:postcode":"S3 7QX",
    "sg:province":"South Yorkshire",
    "sg:tags":[
        "consultant",
        "school",
        "medical"
    ],
    "wof:name":"Graduate Link",
    "wof:placetype":"venue"
},
  "geometry": {"coordinates":[-1.484946,53.381294],"type":"Point"}
}