{
  "type": "Feature",
  "properties": {
    "iso:country":"GB",
    "sg:address":"6 The Cent Crescent, Speke",
    "sg:city":"Liverpool",
    "sg:classifiers":[
        {
            "category":"Government",
            "subcategory":"Post Office",
            "type":"Public Place"
        }
    ],
    "sg:phone":"+44 151 486 1174",
    "sg:postcode":"L24 3TB",
    "sg:province":"Merseyside",
    "wof:name":"Crescent Sub Post Office",
    "wof:placetype":"venue"
},
  "geometry": {"coordinates":[-2.85717,53.346031],"type":"Point"}
}