{
  "type": "Feature",
  "properties": {
    "addr:full":"37 Sussex Crescent Castleford West Yorkshire WF10 3NX",
    "addr:housenumber":"37",
    "addr:postcode":"wf10 3nx",
    "addr:street":"Sussex Crescent",
    "iso:country":"GB",
    "sg:address":"37 Sussex Crescent",
    "sg:city":"Castleford",
    "sg:classifiers":[
        {
            "category":"Personal",
            "type":"Services"
        }
    ],
    "sg:phone":"+44 1977 556088",
    "sg:postcode":"WF10 3NX",
    "sg:province":"West Yorkshire",
    "sg:tags":[
        "wedding"
    ],
    "sg:website":"http://www.sice.co.uk",
    "wof:name":"Patrick Sice Photographer",
    "wof:placetype":"venue"
},
  "geometry": {"coordinates":[-1.3024599552,53.7239952087],"type":"Point"}
}