{
  "type": "Feature",
  "properties": {
    "addr:full":"Lydbury North Bucknell Herefordshire SY7 0AA",
    "addr:housenumber":"lydbury",
    "addr:postcode":"sy7 0aa",
    "addr:street":"North Bucknell Herefordshire",
    "iso:country":"GB",
    "sg:address":"Lydbury North",
    "sg:city":"Bucknell",
    "sg:classifiers":[
        {
            "category":"Education",
            "subcategory":"School",
            "type":"Public Place"
        }
    ],
    "sg:phone":"+44 1547 530264",
    "sg:postcode":"SY7 0AA",
    "sg:province":"Herefordshire",
    "sg:tags":[
        "local",
        "authority"
    ],
    "wof:name":"St.Mary's Bucknell C E (Aided) School",
    "wof:placetype":"venue"
},
  "geometry": {"coordinates":[-2.945099,52.359005],"type":"Point"}
}