{
  "type": "Feature",
  "properties": {
    "addr:full":"The Bastin Hall Exmouth Devon EX8 1DJ",
    "addr:postcode":"ex8 1dj",
    "iso:country":"GB",
    "sg:address":"The Bastin Hall",
    "sg:city":"Exmouth",
    "sg:classifiers":[
        {
            "category":"Education",
            "subcategory":"Special Training",
            "type":"Public Place"
        }
    ],
    "sg:phone":"+44 1395 273374",
    "sg:postcode":"EX8 1DJ",
    "sg:province":"Devon",
    "sg:tags":[
        "aid",
        "first"
    ],
    "wof:name":"St John Ambulance",
    "wof:placetype":"venue"
},
  "geometry": {"coordinates":[-3.4132890701,50.6194152832],"type":"Point"}
}