{
  "type": "Feature",
  "properties": {
    "iso:country":"GB",
    "sg:address":"7 Tall Pines, Plantation Road",
    "sg:city":"Leighton Buzzard",
    "sg:classifiers":[
        {
            "category":"Communications",
            "subcategory":"Film & Video Production",
            "type":"Services"
        }
    ],
    "sg:phone":"+44 1525 378880",
    "sg:postcode":"LU7 3FW",
    "sg:province":"Bedfordshire",
    "sg:tags":[
        "pr",
        "telemarketing"
    ],
    "wof:name":"Agentphone Ltd.",
    "wof:placetype":"venue"
},
  "geometry": {"coordinates":[-0.660612,51.92321],"type":"Point"}
}