{
  "type": "Feature",
  "properties": {
    "addr:full":"80 Station Road, Croston Preston Lancashire PR26 9RN",
    "addr:housenumber":"80",
    "addr:postcode":"pr26 9rn",
    "addr:street":"Station Road",
    "iso:country":"GB",
    "sg:address":"80 Station Road, Croston",
    "sg:city":"Preston",
    "sg:classifiers":[
        {
            "category":"Government",
            "subcategory":"Post Office",
            "type":"Public Place"
        }
    ],
    "sg:postcode":"PR26 9RN",
    "sg:province":"Lancashire",
    "wof:name":"Croston Post Office",
    "wof:placetype":"venue"
},
  "geometry": {"coordinates":[-2.7758710384,53.6637954712],"type":"Point"}
}