{
  "type": "Feature",
  "properties": {
    "addr:full":"Vicarage Hill, Rhostyllen Wrexham Wrexham LL14 4AR",
    "addr:postcode":"ll14 4ar",
    "addr:street":"Vicarage Hill Rhostyllen",
    "iso:country":"GB",
    "sg:address":"Vicarage Hill, Rhostyllen",
    "sg:city":"Wrexham",
    "sg:classifiers":[
        {
            "category":"Community Center",
            "type":"Public Place"
        },
        {
            "category":"Organizations",
            "subcategory":"Community Association",
            "type":"Services"
        }
    ],
    "sg:phone":"+44 1978 366491",
    "sg:postcode":"LL14 4AR",
    "sg:province":"Wrexham",
    "sg:tags":[
        "associations",
        "centre",
        "housing",
        "co-operatives",
        "trust",
        "societies"
    ],
    "wof:name":"EXCLUSHAM COMMUNITY COUNCIL",
    "wof:placetype":"venue"
},
  "geometry": {"coordinates":[-3.0189139843,53.0321731567],"type":"Point"}
}