{
  "type": "Feature",
  "properties": {
    "addr:full":"Danials Farm, Unit 4 Basildon Essex SS15 4AZ",
    "addr:housenumber":"unit 4",
    "addr:postcode":"ss15 4az",
    "iso:country":"GB",
    "sg:address":"Danials Farm, Unit 4",
    "sg:city":"Basildon",
    "sg:classifiers":[
        {
            "category":"Retail",
            "subcategory":"Auto Repair",
            "type":"Services"
        }
    ],
    "sg:phone":"+44 1268 520556",
    "sg:postcode":"SS15 4AZ",
    "sg:province":"Essex",
    "sg:tags":[
        "body",
        "car"
    ],
    "wof:name":"Crashbusters",
    "wof:placetype":"venue"
},
  "geometry": {"coordinates":[0.4445559978,51.5677947998],"type":"Point"}
}