{
  "type": "Feature",
  "properties": {
    "iso:country":"GB",
    "sg:address":"Darnfillan Farm",
    "sg:city":"Lanark",
    "sg:classifiers":[
        {
            "category":"Home & Garden",
            "subcategory":"Garden Supply",
            "type":"Retail Goods"
        },
        {
            "category":"Farming",
            "subcategory":"Farm",
            "type":"Manufacturing & Wholesale Goods"
        }
    ],
    "sg:phone":"+44 1555 892306",
    "sg:postcode":"ML11 9QB",
    "sg:province":"South Lanarkshire",
    "sg:tags":[
        "mixed",
        "bulb",
        "crop",
        "grower"
    ],
    "wof:name":"W H Wilson",
    "wof:placetype":"venue"
},
  "geometry": {"coordinates":[-3.781384,55.673866],"type":"Point"}
}