{
  "type": "Feature",
  "properties": {
    "addr:full":"Stather Road, Burton Upon Stather Scunthorpe Lincolnshire DN15 9DH",
    "addr:postcode":"dn15 9dh",
    "addr:street":"Stather Road",
    "iso:country":"GB",
    "sg:address":"Stather Road, Burton Upon Stather",
    "sg:city":"Scunthorpe",
    "sg:classifiers":[
        {
            "category":"Recreation",
            "subcategory":"Campground",
            "type":"Entertainment"
        }
    ],
    "sg:postcode":"DN15 9DH",
    "sg:province":"Lincolnshire",
    "sg:tags":[
        "caravan",
        "park"
    ],
    "wof:name":"Brookside Caravan Park",
    "wof:placetype":"venue"
},
  "geometry": {"coordinates":[-0.6915929914,53.6550064087],"type":"Point"}
}