{
  "type": "Feature",
  "properties": {
    "iso:country":"GB",
    "sg:address":"Gateway To Humberside Trading Estate, Broad Lane, Gilberdyke",
    "sg:city":"Brough",
    "sg:classifiers":[
        {
            "category":"Shopping",
            "subcategory":"Computers & Home Electronics",
            "type":"Retail Goods"
        }
    ],
    "sg:phone":"+44 1430 440661",
    "sg:postcode":"HU15 2TS",
    "sg:province":"East Riding of Yorkshire",
    "wof:name":"Smiths Furnishings",
    "wof:placetype":"venue"
},
  "geometry": {"coordinates":[-0.7396960258,53.7545166016],"type":"Point"}
}