{
  "type": "Feature",
  "properties": {
    "addr:full":"11 Berkeley Street London Greater London W1J 8BU",
    "addr:housenumber":"11",
    "addr:postcode":"w1j 8bu",
    "addr:street":"Berkeley Street",
    "iso:country":"GB",
    "sg:address":"11 Berkeley Street",
    "sg:city":"London",
    "sg:classifiers":[
        {
            "category":"Professional",
            "subcategory":"Business Services",
            "type":"Services"
        }
    ],
    "sg:phone":"+44 20 7355 5000",
    "sg:postcode":"W1J 8BU",
    "sg:province":"Greater London",
    "sg:tags":[
        "accomodation"
    ],
    "wof:name":"The Berkeley Executive Centre",
    "wof:placetype":"venue"
},
  "geometry": {"coordinates":[-0.143012,51.508171],"type":"Point"}
}