{
  "type": "Feature",
  "properties": {
    "iso:country":"GB",
    "sg:address":"Dorothy Pattison Hospital, Alumwell Close",
    "sg:city":"Walsall",
    "sg:classifiers":[
        {
            "category":"Health Services",
            "subcategory":"Hospital",
            "type":"Services"
        }
    ],
    "sg:phone":"+44 1922 746876",
    "sg:postcode":"WS2 9XH",
    "sg:province":"West Midlands",
    "wof:name":"Walsall Dialysis Unit",
    "wof:placetype":"venue"
},
  "geometry": {"coordinates":[-2.0024499893,52.5821113586],"type":"Point"}
}