{
  "type": "Feature",
  "properties": {
    "iso:country":"GB",
    "sg:address":"71 Broad Lane",
    "sg:city":"Seven Sisters",
    "sg:classifiers":[
        {
            "category":"Building & Trades",
            "subcategory":"Plumbing",
            "type":"Services"
        },
        {
            "category":"Manufacturing",
            "subcategory":"Building Materials",
            "type":"Manufacturing & Wholesale Goods"
        }
    ],
    "sg:phone":"+44 20 8885 3411",
    "sg:postcode":"N15 4DJ",
    "sg:province":"Greater London",
    "sg:tags":[
        "merchant",
        "builder",
        "plumbers'"
    ],
    "wof:name":"C B Tottenham Plumbing & Heating Merchants",
    "wof:placetype":"venue"
},
  "geometry": {"coordinates":[-0.068328999,51.5843086243],"type":"Point"}
}