{
  "type": "Feature",
  "properties": {
    "iso:country":"GB",
    "sg:address":"St Aidans Rc Presbytery, Station Road",
    "sg:city":"Ashington",
    "sg:classifiers":[
        {
            "category":"Community Center",
            "type":"Public Place"
        }
    ],
    "sg:phone":"+44 1670 814003",
    "sg:postcode":"NE63 8AD",
    "sg:province":"Northumberland",
    "sg:tags":[
        "centre"
    ],
    "wof:name":"St.Aidans Parish Centre",
    "wof:placetype":"venue"
},
  "geometry": {"coordinates":[-1.567809,55.178928],"type":"Point"}
}