{
  "type": "Feature",
  "properties": {
    "addr:full":"Office, 129 24 Nutford Place West End Greater London W1H 5YN",
    "addr:housenumber":"129",
    "addr:postcode":"24;w1h 5yn",
    "addr:street":"Nutford Place",
    "iso:country":"GB",
    "sg:address":"Office, 129 24 Nutford Place",
    "sg:city":"West End",
    "sg:classifiers":[
        {
            "category":"Professional",
            "subcategory":"Lawyer & Legal Services",
            "type":"Services"
        }
    ],
    "sg:phone":"+44 20 7724 5700",
    "sg:postcode":"W1H 5YN",
    "sg:province":"Greater London",
    "sg:tags":[
        "solicitor"
    ],
    "wof:name":"Omar & Partners",
    "wof:placetype":"venue"
},
  "geometry": {"coordinates":[-0.1643600017,51.5164794922],"type":"Point"}
}