{
  "type": "Feature",
  "properties": {
    "iso:country":"GB",
    "sg:address":"324 Harrogate Rd",
    "sg:city":"Bradford",
    "sg:classifiers":[
        {
            "category":"Retail",
            "subcategory":"Auto Repair",
            "type":"Services"
        }
    ],
    "sg:phone":"+44 1274 630111",
    "sg:postcode":"BD2 3TB",
    "sg:province":"West Yorkshire",
    "sg:tags":[
        "electrician"
    ],
    "wof:name":"Pro-Arm Security Services",
    "wof:placetype":"venue"
},
  "geometry": {"coordinates":[-1.716446,53.819248],"type":"Point"}
}