{
  "type": "Feature",
  "properties": {
    "addr:full":"23a Station Rd Knebworth Hertfordshire SG3 6AP",
    "addr:housenumber":"23a",
    "addr:postcode":"sg3 6ap",
    "addr:street":"Station Rd",
    "iso:country":"GB",
    "sg:address":"23a Station Rd",
    "sg:city":"Knebworth",
    "sg:classifiers":[
        {
            "category":"Shopping",
            "subcategory":"Florist",
            "type":"Retail Goods"
        }
    ],
    "sg:postcode":"SG3 6AP",
    "sg:province":"Hertfordshire",
    "wof:name":"Ward,Beverley,",
    "wof:placetype":"venue"
},
  "geometry": {"coordinates":[-0.184223,51.866531],"type":"Point"}
}