{
  "type": "Feature",
  "properties": {
    "addr:full":"Unit 3 Moorfields Industrial Estate, Moor Park Avenue Blackpool Lancashire FY2 0JY",
    "addr:housenumber":"unit 3",
    "addr:postcode":"fy2 0jy",
    "addr:street":"Moorfields Industrial Estate Moor Park Avenue",
    "iso:country":"GB",
    "sg:address":"Unit 3 Moorfields Industrial Estate, Moor Park Avenue",
    "sg:city":"Blackpool",
    "sg:classifiers":[
        {
            "category":"Personal",
            "type":"Services"
        }
    ],
    "sg:phone":"+44 1282 604346",
    "sg:postcode":"FY2 0JY",
    "sg:province":"Lancashire",
    "sg:tags":[
        "wedding"
    ],
    "wof:name":"Limelight Limousines",
    "wof:placetype":"venue"
},
  "geometry": {"coordinates":[-3.0223701,53.8507385254],"type":"Point"}
}