{
  "type": "Feature",
  "properties": {
    "addr:full":"19 Marrick Road Stockton-on-tees Durham TS18 5LW",
    "addr:housenumber":"19",
    "addr:postcode":"ts18 5lw",
    "addr:street":"Marrick Road",
    "iso:country":"GB",
    "sg:address":"19 Marrick Road",
    "sg:city":"Stockton-on-tees",
    "sg:classifiers":[
        {
            "category":"Wholesale",
            "subcategory":"Machinery & Supplies",
            "type":"Manufacturing & Wholesale Goods"
        }
    ],
    "sg:phone":"+44 1642 581677",
    "sg:postcode":"TS18 5LW",
    "sg:province":"Durham",
    "sg:tags":[
        "equipment",
        "handling",
        "lifting"
    ],
    "wof:name":"Solid Engineering Systems Ltd.",
    "wof:placetype":"venue"
},
  "geometry": {"coordinates":[-1.35259,54.55481],"type":"Point"}
}