{
  "type": "Feature",
  "properties": {
    "addr:full":"22 Crofts Bank Road, Urmston Manchester Cheshire M41 0TS",
    "addr:housenumber":"22",
    "addr:postcode":"m41 0ts",
    "addr:street":"Crofts Bank Road",
    "iso:country":"GB",
    "sg:address":"22 Crofts Bank Road, Urmston",
    "sg:city":"Manchester",
    "sg:classifiers":[
        {
            "category":"Shopping",
            "subcategory":"News",
            "type":"Retail Goods"
        }
    ],
    "sg:phone":"+44 161 748 1369",
    "sg:postcode":"M41 0TS",
    "sg:province":"Cheshire",
    "sg:tags":[
        "newsagent"
    ],
    "wof:name":"M & B Momen",
    "wof:placetype":"venue"
},
  "geometry": {"coordinates":[-2.352986,53.4492],"type":"Point"}
}