{
  "type": "Feature",
  "properties": {
    "iso:country":"GB",
    "sg:address":"97 Longfleet Rd",
    "sg:city":"Poole",
    "sg:classifiers":[
        {
            "category":"Home & Garden",
            "subcategory":"Hardware",
            "type":"Retail Goods"
        }
    ],
    "sg:phone":"+44 1202 461722",
    "sg:postcode":"BH15 2HP",
    "sg:province":"Dorset",
    "sg:tags":[
        "part",
        "accessory"
    ],
    "wof:name":"Harley Hire",
    "wof:placetype":"venue"
},
  "geometry": {"coordinates":[-1.973609,50.722221],"type":"Point"}
}