{
  "type": "Feature",
  "properties": {
    "addr:full":"Unit 19b Coppull Enterprise Ctre, Mill Lane, Coppull Chorley Lancashire PR7 5BW",
    "addr:housenumber":"unit 19b coppull",
    "addr:postcode":"pr7 5bw",
    "addr:street":"Mill Lane",
    "iso:country":"GB",
    "sg:address":"Unit 19b Coppull Enterprise Ctre, Mill Lane, Coppull",
    "sg:city":"Chorley",
    "sg:classifiers":[
        {
            "category":"Shopping",
            "subcategory":"Computers & Home Electronics",
            "type":"Retail Goods"
        }
    ],
    "sg:phone":"+44 1257 792937",
    "sg:postcode":"PR7 5BW",
    "sg:province":"Lancashire",
    "sg:tags":[
        "equipment",
        "audio-visual"
    ],
    "wof:name":"Robin Stephens Audio Visual Engineering",
    "wof:placetype":"venue"
},
  "geometry": {"coordinates":[-2.6609590054,53.622215271],"type":"Point"}
}