{
  "type": "Feature",
  "properties": {
    "iso:country":"GB",
    "sg:address":"High St, Hadlow",
    "sg:city":"Tonbridge",
    "sg:classifiers":[
        {
            "category":"Food & Beverages",
            "subcategory":"Bakery",
            "type":"Retail Goods"
        }
    ],
    "sg:phone":"+44 1732 850369",
    "sg:postcode":"TN11 0EF",
    "sg:province":"Kent",
    "sg:tags":[
        "baker"
    ],
    "wof:name":"B & D Bakery Ltd",
    "wof:placetype":"venue"
},
  "geometry": {"coordinates":[0.340865,51.226192],"type":"Point"}
}