{
  "type": "Feature",
  "properties": {
    "addr:full":"Monaco Ho, Bristol St Birmingham West Midlands B5 7AS",
    "addr:postcode":"b5 7as",
    "addr:street":"Bristol St",
    "iso:country":"GB",
    "sg:address":"Monaco Ho, Bristol St",
    "sg:city":"Birmingham",
    "sg:classifiers":[
        {
            "category":"Professional",
            "subcategory":"Employment Agencies",
            "type":"Services"
        }
    ],
    "sg:postcode":"B5 7AS",
    "sg:province":"West Midlands",
    "sg:tags":[
        "consultant"
    ],
    "wof:name":"Mda Resources Group Plc",
    "wof:placetype":"venue"
},
  "geometry": {"coordinates":[-1.8995800018,52.471031189],"type":"Point"}
}