{
  "type": "Feature",
  "properties": {
    "addr:full":"35 West Meadows Road, Cleadon Village Sunderland Tyne and Wear SR6 7TU",
    "addr:housenumber":"35",
    "addr:postcode":"sr6 7tu",
    "addr:street":"West Meadows Road",
    "iso:country":"GB",
    "sg:address":"35 West Meadows Road, Cleadon Village",
    "sg:city":"Sunderland",
    "sg:classifiers":[
        {
            "category":"Recreation",
            "subcategory":"Amusement Park",
            "type":"Entertainment"
        }
    ],
    "sg:postcode":"SR6 7TU",
    "sg:province":"Tyne and Wear",
    "sg:tags":[
        "arcade"
    ],
    "wof:name":"L E W Videos",
    "wof:placetype":"venue"
},
  "geometry": {"coordinates":[-1.3993799686,54.9468994141],"type":"Point"}
}