{
  "type": "Feature",
  "properties": {
    "iso:country":"GB",
    "sg:address":"22 Lower Park Row",
    "sg:city":"Bristol",
    "sg:classifiers":[
        {
            "category":"Military Area",
            "subcategory":"Restricted Area",
            "type":"Public Place"
        }
    ],
    "sg:phone":"+44 117 929 9330",
    "sg:postcode":"BS1 5BN",
    "sg:province":"City of Bristol",
    "wof:name":"Pastimes",
    "wof:placetype":"venue"
},
  "geometry": {"coordinates":[-2.597910881,51.4559593201],"type":"Point"}
}