{
  "type": "Feature",
  "properties": {
    "addr:full":"49 Katherine Dr Dunstable Bedfordshire LU5 4NP",
    "addr:housenumber":"49",
    "addr:postcode":"lu5 4np",
    "addr:street":"Katherine Dr",
    "iso:country":"GB",
    "sg:address":"49 Katherine Dr",
    "sg:city":"Dunstable",
    "sg:classifiers":[
        {
            "category":"Home & Garden",
            "subcategory":"Hardware",
            "type":"Retail Goods"
        }
    ],
    "sg:postcode":"LU5 4NP",
    "sg:province":"Bedfordshire",
    "sg:tags":[
        "retailer",
        "diy"
    ],
    "wof:name":"Woodford,Alec Richard,",
    "wof:placetype":"venue"
},
  "geometry": {"coordinates":[-0.498328,51.892612],"type":"Point"}
}