{
  "type": "Feature",
  "properties": {
    "iso:country":"GB",
    "sg:address":"Westcott Road",
    "sg:city":"Peterlee",
    "sg:classifiers":[
        {
            "category":"Health Services",
            "subcategory":"Nursing And Care Facility",
            "type":"Services"
        }
    ],
    "sg:phone":"+44 191 518 2872",
    "sg:postcode":"SR8 5JE",
    "sg:province":"Durham",
    "sg:tags":[
        "home"
    ],
    "wof:name":"Tamaris Healthcare (England) Ltd.",
    "wof:placetype":"venue"
},
  "geometry": {"coordinates":[-1.338467,54.764877],"type":"Point"}
}