{
  "type": "Feature",
  "properties": {
    "addr:full":"50 Exmoor Drive Worthing West Sussex BN13 2PH",
    "addr:housenumber":"50",
    "addr:postcode":"bn13 2ph",
    "addr:street":"Exmoor Drive",
    "iso:country":"GB",
    "sg:address":"50 Exmoor Drive",
    "sg:city":"Worthing",
    "sg:classifiers":[
        {
            "category":"Home & Garden",
            "subcategory":"Building Materials",
            "type":"Retail Goods"
        }
    ],
    "sg:phone":"+44 1903 691080",
    "sg:postcode":"BN13 2PH",
    "sg:province":"West Sussex",
    "sg:tags":[
        "polythene",
        "plastic"
    ],
    "wof:name":"Tools Are Us",
    "wof:placetype":"venue"
},
  "geometry": {"coordinates":[-0.4086239934,50.837474823],"type":"Point"}
}