{
  "type": "Feature",
  "properties": {
    "iso:country":"GB",
    "sg:address":"Ansley Common",
    "sg:city":"Nuneaton",
    "sg:classifiers":[
        {
            "category":"Education",
            "subcategory":"School",
            "type":"Public Place"
        }
    ],
    "sg:phone":"+44 24 7639 2318",
    "sg:postcode":"CV10 0PY",
    "sg:province":"Leicestershire",
    "sg:tags":[
        "local",
        "authority"
    ],
    "wof:name":"Nursery Hill Primary School",
    "wof:placetype":"venue"
},
  "geometry": {"coordinates":[-1.54034,52.53936],"type":"Point"}
}