{
  "type": "Feature",
  "properties": {
    "addr:full":"Cornhill Close, Lodge Farm Industrial Estate Northampton Northamptonshire NN5 7UB",
    "addr:housenumber":"estate",
    "addr:postcode":"nn5 7ub",
    "addr:street":"Cornhill Close Lodge Farm Industrial",
    "iso:country":"GB",
    "sg:address":"Cornhill Close, Lodge Farm Industrial Estate",
    "sg:city":"Northampton",
    "sg:classifiers":[
        {
            "category":"Manufacturing",
            "subcategory":"Wood Products",
            "type":"Manufacturing & Wholesale Goods"
        }
    ],
    "sg:phone":"+44 1604 752355",
    "sg:postcode":"NN5 7UB",
    "sg:province":"Northamptonshire",
    "sg:tags":[
        "packaging",
        "crate",
        "pallets"
    ],
    "wof:name":"Tuscarora Ltd.",
    "wof:placetype":"venue"
},
  "geometry": {"coordinates":[-0.945062,52.261608],"type":"Point"}
}