{
  "type": "Feature",
  "properties": {
    "iso:country":"GB",
    "sg:address":"44 Youngs Park Road",
    "sg:city":"Paignton",
    "sg:classifiers":[
        {
            "category":"Social Services",
            "subcategory":"Retirement Home",
            "type":"Services"
        }
    ],
    "sg:postcode":"TQ4 6BU",
    "sg:province":"Devon",
    "sg:tags":[
        "rest"
    ],
    "wof:name":"Youngs Park Rest Home",
    "wof:placetype":"venue"
},
  "geometry": {"coordinates":[-3.563925,50.429256],"type":"Point"}
}