{
  "type": "Feature",
  "properties": {
    "iso:country":"GB",
    "sg:address":"20 Cliff Road",
    "sg:city":"Newquay",
    "sg:classifiers":[
        {
            "category":"Professional",
            "subcategory":"Lawyer & Legal Services",
            "type":"Services"
        }
    ],
    "sg:phone":"+44 1637 872218",
    "sg:postcode":"TR7 1SG",
    "sg:province":"Cornwall",
    "sg:tags":[
        "solicitor"
    ],
    "wof:name":"Ralph & Co. Solicitors",
    "wof:placetype":"venue"
},
  "geometry": {"coordinates":[-5.077019,50.414547],"type":"Point"}
}