{
  "type": "Feature",
  "properties": {
    "addr:full":"119 Argyle Road Sheffield Derbyshire S8 9HJ",
    "addr:housenumber":"119",
    "addr:postcode":"s8 9hj",
    "addr:street":"Argyle Road",
    "iso:country":"GB",
    "sg:address":"119 Argyle Road",
    "sg:city":"Sheffield",
    "sg:classifiers":[
        {
            "category":"Building & Trades",
            "subcategory":"Construction",
            "type":"Services"
        }
    ],
    "sg:phone":"+44 114 255 3087",
    "sg:postcode":"S8 9HJ",
    "sg:province":"Derbyshire",
    "sg:tags":[
        "builder"
    ],
    "wof:name":"David Stanley & Susan Clarke",
    "wof:placetype":"venue"
},
  "geometry": {"coordinates":[-1.464854002,53.3545570374],"type":"Point"}
}