{
  "type": "Feature",
  "properties": {
    "addr:full":"19 High Street Bilston West Midlands WV14 0EH",
    "addr:housenumber":"19",
    "addr:postcode":"wv14 0eh",
    "addr:street":"High Street",
    "iso:country":"GB",
    "sg:address":"19 High Street",
    "sg:city":"Bilston",
    "sg:classifiers":[
        {
            "category":"Shopping",
            "subcategory":"Used Merchandise",
            "type":"Retail Goods"
        }
    ],
    "sg:postcode":"WV14 0EH",
    "sg:province":"West Midlands",
    "sg:tags":[
        "shop",
        "second-hand"
    ],
    "wof:name":"Treasure Chest",
    "wof:placetype":"venue"
},
  "geometry": {"coordinates":[-2.0792760849,52.5644454956],"type":"Point"}
}