{
  "type": "Feature",
  "properties": {
    "iso:country":"GB",
    "sg:address":"61 Avondale Road",
    "sg:city":"Darwen",
    "sg:classifiers":[
        {
            "category":"Retail",
            "subcategory":"Driving School",
            "type":"Services"
        }
    ],
    "sg:phone":"+44 1254 774031",
    "sg:postcode":"BB3 1NS",
    "sg:province":"Lancashire",
    "wof:name":"Westlund School of Motoring",
    "wof:placetype":"venue"
},
  "geometry": {"coordinates":[-2.479365,53.703156],"type":"Point"}
}