{
  "type": "Feature",
  "properties": {
    "iso:country":"GB",
    "sg:address":"Well La",
    "sg:city":"Cheltenham",
    "sg:classifiers":[
        {
            "category":"Shopping",
            "subcategory":"Used Merchandise",
            "type":"Retail Goods"
        }
    ],
    "sg:phone":"+44 1451 830829",
    "sg:postcode":"GL54 1DB",
    "sg:province":"Gloucestershire",
    "sg:tags":[
        "furniture"
    ],
    "wof:name":"Old Stables The",
    "wof:placetype":"venue"
},
  "geometry": {"coordinates":[-1.720519,51.929489],"type":"Point"}
}