{
  "type": "Feature",
  "properties": {
    "iso:country":"GB",
    "sg:address":"4 Church La",
    "sg:city":"York",
    "sg:classifiers":[
        {
            "category":"Fast Food",
            "type":"Food & Drink"
        }
    ],
    "sg:postcode":"YO1 9QT",
    "sg:province":"North Yorkshire",
    "sg:tags":[
        "away",
        "take"
    ],
    "wof:name":"Brunch Box",
    "wof:placetype":"venue"
},
  "geometry": {"coordinates":[-1.082951,53.957825],"type":"Point"}
}