{
  "type": "Feature",
  "properties": {
    "iso:country":"GB",
    "sg:address":"Bank St Garage, Bank Street",
    "sg:city":"Brierley Hill",
    "sg:classifiers":[
        {
            "category":"Retail",
            "subcategory":"Auto Repair",
            "type":"Services"
        }
    ],
    "sg:phone":"+44 1384 78566",
    "sg:postcode":"DY5 3DA",
    "sg:province":"West Midlands",
    "sg:tags":[
        "body",
        "car"
    ],
    "wof:name":"J Lowe",
    "wof:placetype":"venue"
},
  "geometry": {"coordinates":[-2.1237790585,52.4853591919],"type":"Point"}
}