{
  "type": "Feature",
  "properties": {
    "iso:country":"GB",
    "sg:address":"141 Wellfield St",
    "sg:city":"Warrington",
    "sg:classifiers":[
        {
            "category":"Professional",
            "subcategory":"Management & Consulting",
            "type":"Services"
        }
    ],
    "sg:phone":"+44 1925 632310",
    "sg:postcode":"WA5 1NU",
    "sg:province":"Cheshire",
    "sg:tags":[
        "consultant",
        "business"
    ],
    "wof:name":"Elenchus Approach The",
    "wof:placetype":"venue"
},
  "geometry": {"coordinates":[-2.613773,53.38982],"type":"Point"}
}