{
  "type": "Feature",
  "properties": {
    "addr:full":"62 Dove Rd Barnsley South Yorkshire S73 0TE",
    "addr:housenumber":"62",
    "addr:postcode":"s73 0te",
    "addr:street":"Dove Rd;Yorkshire",
    "iso:country":"GB",
    "sg:address":"62 Dove Rd",
    "sg:city":"Barnsley",
    "sg:classifiers":[
        {
            "category":"Place Of Worship",
            "type":"Public Place"
        }
    ],
    "sg:phone":"+44 1226 211101",
    "sg:postcode":"S73 0TE",
    "sg:province":"South Yorkshire",
    "wof:name":"Roger Evans",
    "wof:placetype":"venue"
},
  "geometry": {"coordinates":[-1.3875069618,53.5141296387],"type":"Point"}
}