{
  "type": "Feature",
  "properties": {
    "addr:full":"15 Bahram Gro Doncaster South Yorkshire DN11 0RA",
    "addr:housenumber":"15",
    "addr:postcode":"dn11 0ra",
    "addr:street":"Bahram Gro Doncaster South",
    "iso:country":"GB",
    "sg:address":"15 Bahram Gro",
    "sg:city":"Doncaster",
    "sg:classifiers":[
        {
            "category":"Building & Trades",
            "subcategory":"Construction",
            "type":"Services"
        }
    ],
    "sg:phone":"+44 1302 865706",
    "sg:postcode":"DN11 0RA",
    "sg:province":"South Yorkshire",
    "sg:tags":[
        "demolition",
        "contractor"
    ],
    "wof:name":"Reclaimed Brick",
    "wof:placetype":"venue"
},
  "geometry": {"coordinates":[-1.1305650473,53.5243911743],"type":"Point"}
}