{
  "type": "Feature",
  "properties": {
    "addr:full":"Unit 12 Black Rock Mills, Waingate Huddersfield West Yorkshire HD7 5NS",
    "addr:housenumber":"unit 12",
    "addr:postcode":"hd7 5ns",
    "addr:street":"Rock;Waingate;West",
    "iso:country":"GB",
    "sg:address":"Unit 12 Black Rock Mills, Waingate",
    "sg:city":"Huddersfield",
    "sg:classifiers":[
        {
            "category":"Building & Trades",
            "subcategory":"Construction",
            "type":"Services"
        }
    ],
    "sg:phone":"+44 1484 844600",
    "sg:postcode":"HD7 5NS",
    "sg:province":"West Yorkshire",
    "sg:tags":[
        "joinery",
        "joiner",
        "carpenter",
        "carpentry"
    ],
    "wof:name":"HILLBARN SERVICES LTD",
    "wof:placetype":"venue"
},
  "geometry": {"coordinates":[-1.8439669609,53.614982605],"type":"Point"}
}