{
  "type": "Feature",
  "properties": {
    "iso:country":"GB",
    "sg:address":"8 Phillips Close, Aston Lodge",
    "sg:city":"Stone",
    "sg:classifiers":[
        {
            "category":"Professional",
            "subcategory":"Computer Services",
            "type":"Services"
        }
    ],
    "sg:phone":"+44 1785 817722",
    "sg:postcode":"ST15 8GD",
    "sg:province":"Staffordshire",
    "sg:tags":[
        "consultant"
    ],
    "wof:name":"G C Associates Ltd.",
    "wof:placetype":"venue"
},
  "geometry": {"coordinates":[-2.122218,52.898148],"type":"Point"}
}