{
  "type": "Feature",
  "properties": {
    "iso:country":"GB",
    "sg:address":"40 House Lane",
    "sg:city":"Arlesey",
    "sg:classifiers":[
        {
            "category":"Communications",
            "type":"Services"
        }
    ],
    "sg:phone":"+44 1462 734391",
    "sg:postcode":"SG15 6XU",
    "sg:province":"Bedfordshire",
    "sg:tags":[
        "audio-visual"
    ],
    "wof:name":"Majestic Productions Ltd.",
    "wof:placetype":"venue"
},
  "geometry": {"coordinates":[-0.261299,52.021069],"type":"Point"}
}