{
  "type": "Feature",
  "properties": {
    "iso:country":"GB",
    "sg:address":"West Anstey Farm",
    "sg:city":"Dulverton",
    "sg:classifiers":[
        {
            "category":"Professional",
            "subcategory":"Engineering",
            "type":"Services"
        }
    ],
    "sg:postcode":"TA22 9RY",
    "sg:province":"Devon",
    "wof:name":"West Anstey Farm Riding Stables",
    "wof:placetype":"venue"
},
  "geometry": {"coordinates":[-3.5504629612,51.0399169922],"type":"Point"}
}