{
  "type": "Feature",
  "properties": {
    "addr:full":"Unit 5 Dannemora Drive, Greenland Road Sheffield South Yorkshire S9 5DF",
    "addr:housenumber":"unit 5",
    "addr:postcode":"s9 5df",
    "addr:street":"Dannemora Drive Greenland Road",
    "iso:country":"GB",
    "sg:address":"Unit 5 Dannemora Drive, Greenland Road",
    "sg:city":"Sheffield",
    "sg:classifiers":[
        {
            "category":"Shopping",
            "subcategory":"Computers & Home Electronics",
            "type":"Retail Goods"
        }
    ],
    "sg:phone":"+44 114 256 2407",
    "sg:postcode":"S9 5DF",
    "sg:province":"South Yorkshire",
    "sg:tags":[
        "electrical"
    ],
    "wof:name":"Park Electrical Services",
    "wof:placetype":"venue"
},
  "geometry": {"coordinates":[-1.4128789902,53.3981361389],"type":"Point"}
}