{
  "type": "Feature",
  "properties": {
    "addr:full":"6 Church St Heckmondwike West Yorkshire WF16 0LF",
    "addr:housenumber":"6",
    "addr:postcode":"wf16 0lf",
    "addr:street":"Church St",
    "iso:country":"GB",
    "sg:address":"6 Church St",
    "sg:city":"Heckmondwike",
    "sg:classifiers":[
        {
            "category":"Professional",
            "subcategory":"Accounting & Tax Preparation",
            "type":"Services"
        }
    ],
    "sg:phone":"+44 1924 401403",
    "sg:postcode":"WF16 0LF",
    "sg:province":"West Yorkshire",
    "sg:tags":[
        "accountant"
    ],
    "wof:name":"Kilner Johnson",
    "wof:placetype":"venue"
},
  "geometry": {"coordinates":[-1.6732330322,53.7052192688],"type":"Point"}
}