{
  "type": "Feature",
  "properties": {
    "addr:full":"15 Vane Hill Road Torquay Devon TQ1 2BZ",
    "addr:housenumber":"15",
    "addr:postcode":"tq1 2bz",
    "addr:street":"Vane Hill Road",
    "iso:country":"GB",
    "sg:address":"15 Vane Hill Road",
    "sg:city":"Torquay",
    "sg:classifiers":[
        {
            "category":"Social Services",
            "subcategory":"Retirement Home",
            "type":"Services"
        }
    ],
    "sg:phone":"+44 1803 214916",
    "sg:postcode":"TQ1 2BZ",
    "sg:province":"Devon",
    "sg:tags":[
        "residential",
        "care"
    ],
    "wof:name":"Vane Hill Residential Home",
    "wof:placetype":"venue"
},
  "geometry": {"coordinates":[-3.518814,50.459267],"type":"Point"}
}