{
  "type": "Feature",
  "properties": {
    "iso:country":"GB",
    "sg:address":"15 St Peters Street",
    "sg:city":"Chorley",
    "sg:classifiers":[
        {
            "category":"Professional",
            "type":"Services"
        }
    ],
    "sg:postcode":"PR6 0DS",
    "sg:province":"Lancashire",
    "sg:tags":[
        "interior",
        "furnishers",
        "designer"
    ],
    "wof:name":"Story Book Designs",
    "wof:placetype":"venue"
},
  "geometry": {"coordinates":[-2.6199760437,53.6596298218],"type":"Point"}
}