{
  "type": "Feature",
  "properties": {
    "addr:full":"26 Torbay Rd Paignton Devon TQ4 6AL",
    "addr:housenumber":"26",
    "addr:postcode":"tq4 6al",
    "addr:street":"Torbay Rd",
    "iso:country":"GB",
    "sg:address":"26 Torbay Rd",
    "sg:city":"Paignton",
    "sg:classifiers":[
        {
            "category":"Shopping",
            "subcategory":"Gifts & Souvenirs",
            "type":"Retail Goods"
        }
    ],
    "sg:phone":"+44 1803 554391",
    "sg:postcode":"TQ4 6AL",
    "sg:province":"Devon",
    "sg:tags":[
        "shop"
    ],
    "wof:name":"The Gift Centre",
    "wof:placetype":"venue"
},
  "geometry": {"coordinates":[-3.5625040531,50.4352035522],"type":"Point"}
}