{
  "type": "Feature",
  "properties": {
    "addr:full":"Strode Road Plymouth Devon PL7 4AY",
    "addr:postcode":"pl7 4ay",
    "addr:street":"Strode Road",
    "iso:country":"GB",
    "sg:address":"Strode Road",
    "sg:city":"Plymouth",
    "sg:classifiers":[
        {
            "category":"Cafe",
            "type":"Food & Drink"
        }
    ],
    "sg:phone":"+44 1752 331148",
    "sg:postcode":"PL7 4AY",
    "sg:province":"Devon",
    "sg:tags":[
        "tea",
        "room"
    ],
    "wof:name":"The Cabin",
    "wof:placetype":"venue"
},
  "geometry": {"coordinates":[-4.04773,50.395275],"type":"Point"}
}