{
  "type": "Feature",
  "properties": {
    "addr:full":"73 Main Street Cockermouth Cumbria CA13 9JS",
    "addr:housenumber":"73",
    "addr:postcode":"ca13 9js",
    "addr:street":"Main Street",
    "iso:country":"GB",
    "sg:address":"73 Main Street",
    "sg:city":"Cockermouth",
    "sg:classifiers":[
        {
            "category":"Cafe",
            "type":"Food & Drink"
        }
    ],
    "sg:phone":"+44 1900 824330",
    "sg:postcode":"CA13 9JS",
    "sg:province":"Cumbria",
    "sg:tags":[
        "tea",
        "snack",
        "bar",
        "room"
    ],
    "wof:name":"Norham Coffee House",
    "wof:placetype":"venue"
},
  "geometry": {"coordinates":[-3.366603,54.663456],"type":"Point"}
}