{
  "type": "Feature",
  "properties": {
    "addr:full":"Pocknedge Farm, Pocknedge Lane, Holymoorside Chesterfield Derbyshire S42 7HL",
    "addr:postcode":"s42 7hl",
    "addr:street":"Pocknedge Lane",
    "iso:country":"GB",
    "sg:address":"Pocknedge Farm, Pocknedge Lane, Holymoorside",
    "sg:city":"Chesterfield",
    "sg:classifiers":[
        {
            "category":"Farming",
            "subcategory":"Farm",
            "type":"Manufacturing & Wholesale Goods"
        }
    ],
    "sg:phone":"+44 1246 566052",
    "sg:postcode":"S42 7HL",
    "sg:province":"Derbyshire",
    "sg:tags":[
        "mixed",
        "crop"
    ],
    "wof:name":"N G Jackson",
    "wof:placetype":"venue"
},
  "geometry": {"coordinates":[-1.4937989712,53.2206916809],"type":"Point"}
}