{
  "type": "Feature",
  "properties": {
    "iso:country":"GB",
    "sg:address":"8 Roding Lane South",
    "sg:city":"Ilford",
    "sg:classifiers":[
        {
            "category":"Personal",
            "subcategory":"Beauty Salon",
            "type":"Services"
        }
    ],
    "sg:phone":"+44 20 8550 7000",
    "sg:postcode":"IG4 5NX",
    "sg:province":"Essex",
    "sg:tags":[
        "unisex",
        "hairdresser"
    ],
    "wof:name":"Hair City",
    "wof:placetype":"venue"
},
  "geometry": {"coordinates":[0.045367,51.577221],"type":"Point"}
}