{
  "type": "Feature",
  "properties": {
    "addr:full":"Tweed Road Northampton Northamptonshire NN5 5AF",
    "addr:postcode":"nn5 5af",
    "addr:street":"Tweed Road",
    "iso:country":"GB",
    "sg:address":"Tweed Road",
    "sg:city":"Northampton",
    "sg:classifiers":[
        {
            "category":"Wholesale",
            "subcategory":"Scrap",
            "type":"Manufacturing & Wholesale Goods"
        }
    ],
    "sg:phone":"+44 1604 586564",
    "sg:postcode":"NN5 5AF",
    "sg:province":"Northamptonshire",
    "sg:tags":[
        "breaker",
        "dismantlers"
    ],
    "wof:name":"Sixfields Autobreakers",
    "wof:placetype":"venue"
},
  "geometry": {"coordinates":[-0.929488,52.238689],"type":"Point"}
}