{
  "type": "Feature",
  "properties": {
    "addr:full":"4 St Pauls Square Perth Perth and Kinross PH1 5QW",
    "addr:housenumber":"4",
    "addr:postcode":"ph1 5qw",
    "addr:street":"St Pauls Square",
    "iso:country":"GB",
    "sg:address":"4 St Pauls Square",
    "sg:city":"Perth",
    "sg:classifiers":[
        {
            "category":"Shopping",
            "subcategory":"Department Store",
            "type":"Retail Goods"
        },
        {
            "category":"Shopping",
            "subcategory":"Comic Books",
            "type":"Retail Goods"
        }
    ],
    "sg:phone":"+44 1738 627505",
    "sg:postcode":"PH1 5QW",
    "sg:province":"Perth and Kinross",
    "sg:tags":[
        "jeweller"
    ],
    "wof:name":"Phineas A Barr",
    "wof:placetype":"venue"
},
  "geometry": {"coordinates":[-3.4352900982,56.3966064453],"type":"Point"}
}