{
  "type": "Feature",
  "properties": {
    "iso:country":"GB",
    "sg:address":"1 Hillview, Cwmfelinfach, Ynysddu",
    "sg:city":"Newport",
    "sg:classifiers":[
        {
            "category":"Professional",
            "subcategory":"Business Services",
            "type":"Services"
        }
    ],
    "sg:postcode":"NP11 7GW",
    "sg:province":"Blaenau Gwent",
    "sg:tags":[
        "bookmaker"
    ],
    "wof:name":"Brian Clayton Racing",
    "wof:placetype":"venue"
},
  "geometry": {"coordinates":[-3.184754,51.624725],"type":"Point"}
}