{
  "type": "Feature",
  "properties": {
    "iso:country":"GB",
    "sg:address":"69 Ditton Walk",
    "sg:city":"Cambridge",
    "sg:classifiers":[
        {
            "category":"Retail",
            "subcategory":"Auto Repair",
            "type":"Services"
        }
    ],
    "sg:phone":"+44 1223 241172",
    "sg:postcode":"CB5 8QD",
    "sg:province":"Cambridgeshire",
    "sg:tags":[
        "body",
        "car",
        "repairer"
    ],
    "wof:name":"G T Sprayers",
    "wof:placetype":"venue"
},
  "geometry": {"coordinates":[0.1548810005,52.2144317627],"type":"Point"}
}