{
  "type": "Feature",
  "properties": {
    "iso:country":"GB",
    "sg:address":"Dorrington Drive, Dorrington Industrial Park",
    "sg:city":"Stafford",
    "sg:classifiers":[
        {
            "category":"Home & Garden",
            "subcategory":"Household Appliances",
            "type":"Retail Goods"
        }
    ],
    "sg:phone":"+44 1785 254455",
    "sg:postcode":"ST16 3BF",
    "sg:province":"Staffordshire",
    "sg:tags":[
        "domestic",
        "centre"
    ],
    "wof:name":"D M L Ltd.",
    "wof:placetype":"venue"
},
  "geometry": {"coordinates":[-2.118823,52.820137],"type":"Point"}
}