{
  "type": "Feature",
  "properties": {
    "addr:full":"9 Finkle Street Selby East Riding of Yorkshire YO8 4DU",
    "addr:housenumber":"9",
    "addr:postcode":"yo8 4du",
    "addr:street":"Finkle Street",
    "iso:country":"GB",
    "sg:address":"9 Finkle Street",
    "sg:city":"Selby",
    "sg:classifiers":[
        {
            "category":"Shopping",
            "subcategory":"Stationery & Office Supplies",
            "type":"Retail Goods"
        }
    ],
    "sg:postcode":"YO8 4DU",
    "sg:province":"East Riding of Yorkshire",
    "wof:name":"E M Rimmington & Co",
    "wof:placetype":"venue"
},
  "geometry": {"coordinates":[-1.0693999529,53.7844085693],"type":"Point"}
}