{
  "type": "Feature",
  "properties": {
    "iso:country":"GB",
    "sg:address":"104 Hucknall Road",
    "sg:city":"Nottingham",
    "sg:classifiers":[
        {
            "category":"Fast Food",
            "type":"Food & Drink"
        }
    ],
    "sg:phone":"+44 115 910 3888",
    "sg:postcode":"NG5 1AD",
    "sg:province":"Nottinghamshire",
    "sg:tags":[
        "away",
        "take"
    ],
    "wof:name":"Good Grub",
    "wof:placetype":"venue"
},
  "geometry": {"coordinates":[-1.155371,52.97438],"type":"Point"}
}