{
  "type": "Feature",
  "properties": {
    "addr:full":"St Wilfreds R C (aided) Primary School, Queens Av Stoke On Trent Staffordshire ST6 6EE",
    "addr:postcode":"st6 6ee",
    "addr:street":"Queens Av Stoke On Trent",
    "iso:country":"GB",
    "sg:address":"St Wilfreds R C (aided) Primary School, Queens Av",
    "sg:city":"Stoke On Trent",
    "sg:classifiers":[
        {
            "category":"Government",
            "subcategory":"Office",
            "type":"Public Place"
        }
    ],
    "sg:phone":"+44 1782 838496",
    "sg:postcode":"ST6 6EE",
    "sg:province":"Staffordshire",
    "sg:tags":[
        "local"
    ],
    "wof:name":"Stoke On Trent City Council",
    "wof:placetype":"venue"
},
  "geometry": {"coordinates":[-2.198865,53.070332],"type":"Point"}
}