{
  "type": "Feature",
  "properties": {
    "iso:country":"GB",
    "sg:address":"Prospect Farm, Spond",
    "sg:city":"Kington",
    "sg:classifiers":[
        {
            "category":"Farming",
            "subcategory":"Livestock Farm",
            "type":"Manufacturing & Wholesale Goods"
        },
        {
            "category":"Farming",
            "subcategory":"Farm",
            "type":"Manufacturing & Wholesale Goods"
        }
    ],
    "sg:phone":"+44 1544 230442",
    "sg:postcode":"HR5 3LD",
    "sg:province":"Herefordshire",
    "sg:tags":[
        "mixed",
        "others"
    ],
    "wof:name":"J P Raymond",
    "wof:placetype":"venue"
},
  "geometry": {"coordinates":[-3.0162899494,52.1729011536],"type":"Point"}
}