{
  "type": "Feature",
  "properties": {
    "iso:country":"GB",
    "sg:address":"173 Blackmoorfoot Rd",
    "sg:city":"Huddersfield",
    "sg:classifiers":[
        {
            "category":"Wholesale",
            "subcategory":"Meat",
            "type":"Manufacturing & Wholesale Goods"
        }
    ],
    "sg:phone":"+44 1484 301166",
    "sg:postcode":"HD4 5AP",
    "sg:province":"West Yorkshire",
    "sg:tags":[
        "-"
    ],
    "wof:name":"Speedyfro",
    "wof:placetype":"venue"
},
  "geometry": {"coordinates":[-1.80798,53.637962],"type":"Point"}
}