{
  "type": "Feature",
  "properties": {
    "addr:full":"2 Silver Street, Buckden Huntingdon Cambridgeshire PE18 9TD",
    "addr:housenumber":"2",
    "addr:postcode":"pe18 9td",
    "addr:street":"Silver Street",
    "iso:country":"GB",
    "sg:address":"2 Silver Street, Buckden",
    "sg:city":"Huntingdon",
    "sg:classifiers":[
        {
            "category":"Professional",
            "subcategory":"Accounting & Tax Preparation",
            "type":"Services"
        }
    ],
    "sg:phone":"+44 1480 455575",
    "sg:postcode":"PE18 9TD",
    "sg:province":"Cambridgeshire",
    "sg:tags":[
        "accountant"
    ],
    "wof:name":"R J McMorran",
    "wof:placetype":"venue"
},
  "geometry": {"coordinates":[-0.2546,52.293201],"type":"Point"}
}