{
  "type": "Feature",
  "properties": {
    "addr:full":"Spring Gardens High Wycombe Buckinghamshire HP13 7AB",
    "addr:postcode":"hp13 7ab",
    "addr:street":"Spring Gardens",
    "iso:country":"GB",
    "sg:address":"Spring Gardens",
    "sg:city":"High Wycombe",
    "sg:classifiers":[
        {
            "category":"Shopping",
            "subcategory":"Computers & Home Electronics",
            "type":"Retail Goods"
        }
    ],
    "sg:phone":"+44 1494 525382",
    "sg:postcode":"HP13 7AB",
    "sg:province":"Buckinghamshire",
    "wof:name":"Cosy Comforter Ltd",
    "wof:placetype":"venue"
},
  "geometry": {"coordinates":[-0.729424,51.624058],"type":"Point"}
}