{
  "type": "Feature",
  "properties": {
    "iso:country":"GB",
    "sg:address":"23 Whitelot Way, Southwick",
    "sg:city":"Brighton",
    "sg:classifiers":[
        {
            "category":"Social Services",
            "type":"Services"
        }
    ],
    "sg:phone":"+44 1273 594122",
    "sg:postcode":"BN42 4YF",
    "sg:province":"West Sussex",
    "wof:name":"Whitelot Family Centre",
    "wof:placetype":"venue"
},
  "geometry": {"coordinates":[-0.238011,50.844646],"type":"Point"}
}