{
  "type": "Feature",
  "properties": {
    "addr:full":"1sr Floor Centurian Ho, Railway St Hertford Hertfordshire SG14 1BA",
    "addr:postcode":"sg14 1ba",
    "addr:street":"St",
    "iso:country":"GB",
    "sg:address":"1sr Floor Centurian Ho, Railway St",
    "sg:city":"Hertford",
    "sg:classifiers":[
        {
            "category":"Banks & Credit Unions",
            "subcategory":"Financial Services",
            "type":"Services"
        }
    ],
    "sg:phone":"+44 1992 584944",
    "sg:postcode":"SG14 1BA",
    "sg:province":"Hertfordshire",
    "sg:tags":[
        "consultant"
    ],
    "wof:name":"Sun Life Of Canada Group Of Companies",
    "wof:placetype":"venue"
},
  "geometry": {"coordinates":[-0.082699,51.796341],"type":"Point"}
}