{
  "type": "Feature",
  "properties": {
    "iso:country":"GB",
    "sg:address":"91 Horseshoe La East",
    "sg:city":"Guildford",
    "sg:classifiers":[
        {
            "category":"Professional",
            "type":"Services"
        }
    ],
    "sg:postcode":"GU1 2TW",
    "sg:province":"Surrey",
    "sg:tags":[
        "directory",
        "pub"
    ],
    "wof:name":"Walker,S,",
    "wof:placetype":"venue"
},
  "geometry": {"coordinates":[-0.540644,51.247147],"type":"Point"}
}