{
  "type": "Feature",
  "properties": {
    "iso:country":"GB",
    "sg:address":"Hepple Whitefield Farm, Hepple",
    "sg:city":"Morpeth",
    "sg:classifiers":[
        {
            "category":"Farming",
            "subcategory":"Livestock Farm",
            "type":"Manufacturing & Wholesale Goods"
        }
    ],
    "sg:phone":"+44 1669 640200",
    "sg:postcode":"NE65 7LN",
    "sg:province":"Northumberland",
    "sg:tags":[
        "others"
    ],
    "wof:name":"J Robson & Son",
    "wof:placetype":"venue"
},
  "geometry": {"coordinates":[-2.030427,55.297871],"type":"Point"}
}