{
  "type": "Feature",
  "properties": {
    "addr:full":"Clifford Road Stirling Stirling FK8 2AQ",
    "addr:postcode":"fk8 2aq",
    "addr:street":"Clifford Road",
    "iso:country":"GB",
    "sg:address":"Clifford Road",
    "sg:city":"Stirling",
    "sg:classifiers":[
        {
            "category":"Health Services",
            "subcategory":"Nursing And Care Facility",
            "type":"Services"
        },
        {
            "category":"Social Services",
            "subcategory":"Retirement Home",
            "type":"Services"
        }
    ],
    "sg:phone":"+44 1786 473848",
    "sg:postcode":"FK8 2AQ",
    "sg:province":"Stirling",
    "sg:tags":[
        "residential"
    ],
    "wof:name":"Westerlands Association",
    "wof:placetype":"venue"
},
  "geometry": {"coordinates":[-3.938639,56.108822],"type":"Point"}
}