{
  "type": "Feature",
  "properties": {
    "iso:country":"GB",
    "sg:address":"636 Bristol Road South, Northfield",
    "sg:city":"Birmingham",
    "sg:classifiers":[
        {
            "category":"Freight",
            "type":"Transportation"
        }
    ],
    "sg:postcode":"B31 2JR",
    "sg:province":"West Midlands",
    "sg:tags":[
        "haulage",
        "road"
    ],
    "wof:name":"Randell,Evelyn,",
    "wof:placetype":"venue"
},
  "geometry": {"coordinates":[-1.965609,52.41861],"type":"Point"}
}