{
  "type": "Feature",
  "properties": {
    "addr:full":"22-24 Vauxhall Street London Greater London SE11 5LG",
    "addr:housenumber":"22-24",
    "addr:postcode":"se11 5lg",
    "addr:street":"Vauxhall Street",
    "iso:country":"GB",
    "sg:address":"22-24 Vauxhall Street",
    "sg:city":"London",
    "sg:classifiers":[
        {
            "category":"Shopping",
            "subcategory":"Department Store",
            "type":"Retail Goods"
        },
        {
            "category":"Food & Beverages",
            "subcategory":"Groceries & Convenience Stores",
            "type":"Retail Goods"
        }
    ],
    "sg:phone":"+44 20 7582 0865",
    "sg:postcode":"SE11 5LG",
    "sg:province":"Greater London",
    "wof:name":"Maharvi Food Store",
    "wof:placetype":"venue"
},
  "geometry": {"coordinates":[-0.117346,51.489365],"type":"Point"}
}