{
  "type": "Feature",
  "properties": {
    "addr:full":"60 Central Hill Upper Norwood Greater London SE19 1DT",
    "addr:housenumber":"60",
    "addr:postcode":"se19 1dt",
    "addr:street":"Central Hill",
    "iso:country":"GB",
    "sg:address":"60 Central Hill",
    "sg:city":"Upper Norwood",
    "sg:classifiers":[
        {
            "category":"Health Services",
            "subcategory":"Doctor",
            "type":"Services"
        }
    ],
    "sg:phone":"+44 20 8670 7117",
    "sg:postcode":"SE19 1DT",
    "sg:province":"Greater London",
    "sg:tags":[
        "practitioners"
    ],
    "wof:name":"Lwin, T T",
    "wof:placetype":"venue"
},
  "geometry": {"coordinates":[-0.083973,51.419655],"type":"Point"}
}