{
  "type": "Feature",
  "properties": {
    "addr:full":"14 Queensberry Street Dumfries Dumfries and Galloway DG1 1EX",
    "addr:housenumber":"14",
    "addr:postcode":"dg1 1ex",
    "addr:street":"Queensberry Street",
    "iso:country":"GB",
    "sg:address":"14 Queensberry Street",
    "sg:city":"Dumfries",
    "sg:classifiers":[
        {
            "category":"Transit Center",
            "subcategory":"Freight",
            "type":"Transportation"
        },
        {
            "category":"Real Estate",
            "subcategory":"Real Estate Agent",
            "type":"Services"
        }
    ],
    "sg:phone":"+44 1387 254010",
    "sg:postcode":"DG1 1EX",
    "sg:province":"Dumfries and Galloway",
    "sg:tags":[
        "shop",
        "property"
    ],
    "sg:website":"http://www.dgspc.co.uk",
    "wof:name":"Solicitors Property Centre",
    "wof:placetype":"venue"
},
  "geometry": {"coordinates":[-3.6105489731,55.0693016052],"type":"Point"}
}