{
  "type": "Feature",
  "properties": {
    "addr:full":"61 Chandos Place London Greater London WC2N 4HG",
    "addr:housenumber":"61",
    "addr:postcode":"wc2n 4hg",
    "addr:street":"Chandos Place",
    "iso:country":"GB",
    "sg:address":"61 Chandos Place",
    "sg:city":"London",
    "sg:classifiers":[
        {
            "category":"Organizations",
            "subcategory":"Membership Organization",
            "type":"Services"
        }
    ],
    "sg:postcode":"WC2N 4HG",
    "sg:province":"Greater London",
    "sg:tags":[
        "club"
    ],
    "wof:name":"Ryewater Management Limited",
    "wof:placetype":"venue"
},
  "geometry": {"coordinates":[-0.1246699989,51.5101699829],"type":"Point"}
}