{
  "type": "Feature",
  "properties": {
    "addr:full":"Stanchester Community School, East Stoke Stoke-sub-hamdon Somerset TA14 6UQ",
    "addr:postcode":"ta14 6uq",
    "addr:street":"East Stoke",
    "iso:country":"GB",
    "sg:address":"Stanchester Community School, East Stoke",
    "sg:city":"Stoke-sub-hamdon",
    "sg:classifiers":[
        {
            "category":"Community Center",
            "type":"Public Place"
        },
        {
            "category":"Government",
            "subcategory":"Office",
            "type":"Public Place"
        }
    ],
    "sg:phone":"+44 1935 825261",
    "sg:postcode":"TA14 6UQ",
    "sg:province":"Somerset",
    "sg:tags":[
        "recreation",
        "local",
        "leisure",
        "centre"
    ],
    "wof:name":"Stanchester Sports Centre",
    "wof:placetype":"venue"
},
  "geometry": {"coordinates":[-2.7505779266,50.9558601379],"type":"Point"}
}