{
  "type": "Feature",
  "properties": {
    "addr:full":"Vinnicombe Barn, Binneford Crediton Devon EX17 5EZ",
    "addr:postcode":"ex17 5ez",
    "addr:street":"Binneford",
    "iso:country":"GB",
    "sg:address":"Vinnicombe Barn, Binneford",
    "sg:city":"Crediton",
    "sg:classifiers":[
        {
            "category":"Building & Trades",
            "subcategory":"Construction",
            "type":"Services"
        }
    ],
    "sg:phone":"+44 1647 24557",
    "sg:postcode":"EX17 5EZ",
    "sg:province":"Devon",
    "sg:tags":[
        "builder"
    ],
    "wof:name":"Harling D G",
    "wof:placetype":"venue"
},
  "geometry": {"coordinates":[-3.6614038944,50.7908363342],"type":"Point"}
}