{
  "type": "Feature",
  "properties": {
    "addr:full":"38 Upper Villiers St Wolverhampton West Midlands WV2 4NU",
    "addr:housenumber":"38",
    "addr:postcode":"wv2 4nu",
    "addr:street":"Upper Villiers St",
    "iso:country":"GB",
    "sg:address":"38 Upper Villiers St",
    "sg:city":"Wolverhampton",
    "sg:classifiers":[
        {
            "category":"Building & Trades",
            "subcategory":"Cleaning & Sanitation",
            "type":"Services"
        }
    ],
    "sg:phone":"+44 1902 337552",
    "sg:postcode":"WV2 4NU",
    "sg:province":"West Midlands",
    "sg:tags":[
        "dry",
        "control",
        "damp",
        "rot"
    ],
    "wof:name":"Elm Preservation Services",
    "wof:placetype":"venue"
},
  "geometry": {"coordinates":[-2.1328849792,52.5700531006],"type":"Point"}
}