{
  "type": "Feature",
  "properties": {
    "addr:full":"The Office Healey Hall, Healey Riding Mill Northumberland NE44 6BH",
    "addr:postcode":"ne44 6bh",
    "addr:street":"Healey;Northumberland",
    "iso:country":"GB",
    "sg:address":"The Office Healey Hall, Healey",
    "sg:city":"Riding Mill",
    "sg:classifiers":[
        {
            "category":"Professional",
            "subcategory":"Advertising",
            "type":"Services"
        }
    ],
    "sg:phone":"+44 1434 673961",
    "sg:postcode":"NE44 6BH",
    "sg:province":"Northumberland",
    "sg:tags":[
        "agency"
    ],
    "wof:name":"James Warde-Aldam",
    "wof:placetype":"venue"
},
  "geometry": {"coordinates":[-1.974789,54.948711],"type":"Point"}
}