{
  "type": "Feature",
  "properties": {
    "iso:country":"GB",
    "sg:address":"73a Toll End Road",
    "sg:city":"Tipton",
    "sg:classifiers":[
        {
            "category":"Military Area",
            "subcategory":"Air Force Base",
            "type":"Public Place"
        }
    ],
    "sg:phone":"+44 121 520 3131",
    "sg:postcode":"DY4 0EU",
    "sg:province":"West Midlands",
    "sg:tags":[
        "taxi",
        "hire",
        "private"
    ],
    "wof:name":"Dannys Taxis",
    "wof:placetype":"venue"
},
  "geometry": {"coordinates":[-2.038864,52.535259],"type":"Point"}
}