{
  "type": "Feature",
  "properties": {
    "addr:full":"53 St Albans Road Leicester Leicestershire LE2 1GF",
    "addr:housenumber":"53",
    "addr:postcode":"le2 1gf",
    "addr:street":"St Albans Road",
    "iso:country":"GB",
    "sg:address":"53 St Albans Road",
    "sg:city":"Leicester",
    "sg:classifiers":[
        {
            "category":"Bakery",
            "type":"Food & Drink"
        }
    ],
    "sg:phone":"+44 116 247 0654",
    "sg:postcode":"LE2 1GF",
    "sg:province":"Leicestershire",
    "sg:tags":[
        "cake",
        "maker"
    ],
    "wof:name":"The Cake Co",
    "wof:placetype":"venue"
},
  "geometry": {"coordinates":[-1.115912,52.62682],"type":"Point"}
}