{
  "type": "Feature",
  "properties": {
    "iso:country":"GB",
    "sg:address":"42 Harrington Ct",
    "sg:city":"Barnsley",
    "sg:classifiers":[
        {
            "category":"Professional",
            "subcategory":"Lawyer & Legal Services",
            "type":"Services"
        }
    ],
    "sg:phone":"+44 1226 236982",
    "sg:postcode":"S71 5JR",
    "sg:province":"South Yorkshire",
    "sg:tags":[
        "writing"
    ],
    "wof:name":"Heritage UK",
    "wof:placetype":"venue"
},
  "geometry": {"coordinates":[-1.435589,53.564091],"type":"Point"}
}