{
  "type": "Feature",
  "properties": {
    "addr:full":"14 Market Place Normanton West Yorkshire WF6 2AU",
    "addr:housenumber":"14",
    "addr:postcode":"wf6 2au",
    "addr:street":"Market Place",
    "iso:country":"GB",
    "sg:address":"14 Market Place",
    "sg:city":"Normanton",
    "sg:classifiers":[
        {
            "category":"Shopping",
            "subcategory":"Baby Store",
            "type":"Retail Goods"
        }
    ],
    "sg:postcode":"WF6 2AU",
    "sg:province":"West Yorkshire",
    "sg:tags":[
        "babywear",
        "childrens"
    ],
    "wof:name":"Cheeky Monkeys",
    "wof:placetype":"venue"
},
  "geometry": {"coordinates":[-1.42091,53.700096],"type":"Point"}
}