{
  "type": "Feature",
  "properties": {
    "iso:country":"GB",
    "sg:address":"220 Westbourne Gro",
    "sg:city":"London",
    "sg:classifiers":[
        {
            "category":"Shopping",
            "subcategory":"Antiques",
            "type":"Retail Goods"
        }
    ],
    "sg:phone":"+44 20 7792 8728",
    "sg:postcode":"W11 2RH",
    "sg:province":"Greater London",
    "wof:name":"Grove Antiques Ltd",
    "wof:placetype":"venue"
},
  "geometry": {"coordinates":[-0.204079,51.514439],"type":"Point"}
}