{
  "type": "Feature",
  "properties": {
    "addr:full":"Pump Lane Industrial Estate Hayes Greater London UB3 3NE",
    "addr:housenumber":"estate",
    "addr:postcode":"ub3 3ne",
    "addr:street":"Pump Lane Industrial",
    "iso:country":"GB",
    "sg:address":"Pump Lane Industrial Estate",
    "sg:city":"Hayes",
    "sg:classifiers":[
        {
            "category":"Manufacturing",
            "subcategory":"Rubber & Plastics",
            "type":"Manufacturing & Wholesale Goods"
        }
    ],
    "sg:phone":"+44 20 8569 3439",
    "sg:postcode":"UB3 3NE",
    "sg:province":"Greater London",
    "sg:tags":[
        "product",
        "moulding",
        "injection"
    ],
    "wof:name":"Pentech Moulding Co. Ltd.",
    "wof:placetype":"venue"
},
  "geometry": {"coordinates":[-0.417567,51.507027],"type":"Point"}
}