{
  "type": "Feature",
  "properties": {
    "iso:country":"GB",
    "sg:address":"31 Station Street",
    "sg:city":"Cockermouth",
    "sg:classifiers":[
        {
            "category":"Fast Food",
            "type":"Food & Drink"
        }
    ],
    "sg:phone":"+44 1900 828878",
    "sg:postcode":"CA13 9QW",
    "sg:province":"Cumbria",
    "sg:tags":[
        "away",
        "meal",
        "outlet",
        "take"
    ],
    "wof:name":"Chattanooga",
    "wof:placetype":"venue"
},
  "geometry": {"coordinates":[-3.364056,54.66272],"type":"Point"}
}