{
  "type": "Feature",
  "properties": {
    "addr:full":"New Farm, Meadow Lane, Earith Huntingdon Bedfordshire PE28 3QE",
    "addr:postcode":"pe28 3qe",
    "addr:street":"New Farm Meadow Lane",
    "iso:country":"GB",
    "sg:address":"New Farm, Meadow Lane, Earith",
    "sg:city":"Huntingdon",
    "sg:classifiers":[
        {
            "category":"Farming",
            "subcategory":"Livestock Farm",
            "type":"Manufacturing & Wholesale Goods"
        }
    ],
    "sg:phone":"+44 1487 841476",
    "sg:postcode":"PE28 3QE",
    "sg:province":"Bedfordshire",
    "sg:tags":[
        "others"
    ],
    "wof:name":"J A P Eddy",
    "wof:placetype":"venue"
},
  "geometry": {"coordinates":[0.030771,52.357189],"type":"Point"}
}