{
  "type": "Feature",
  "properties": {
    "addr:full":"16 High Street Ruislip Greater London HA4 7AN",
    "addr:housenumber":"16",
    "addr:postcode":"ha4 7an",
    "addr:street":"High Street",
    "iso:country":"GB",
    "sg:address":"16 High Street",
    "sg:city":"Ruislip",
    "sg:classifiers":[
        {
            "category":"Shopping",
            "subcategory":"Department Store",
            "type":"Retail Goods"
        },
        {
            "category":"Shopping",
            "subcategory":"Pharmacy",
            "type":"Retail Goods"
        }
    ],
    "sg:phone":"+44 1895 633446",
    "sg:postcode":"HA4 7AN",
    "sg:province":"Greater London",
    "sg:tags":[
        "departmental",
        "drug"
    ],
    "wof:name":"Super Value",
    "wof:placetype":"venue"
},
  "geometry": {"coordinates":[-0.426696,51.57608],"type":"Point"}
}