{
  "type": "Feature",
  "properties": {
    "addr:full":"Devonshire Road Cambridge Cambridgeshire CB1 2BJ",
    "addr:postcode":"cb1 2bj",
    "addr:street":"Devonshire Road",
    "iso:country":"GB",
    "sg:address":"Devonshire Road",
    "sg:city":"Cambridge",
    "sg:classifiers":[
        {
            "category":"Manufacturing",
            "subcategory":"Building Materials",
            "type":"Manufacturing & Wholesale Goods"
        }
    ],
    "sg:phone":"+44 1223 355484",
    "sg:postcode":"CB1 2BJ",
    "sg:province":"Cambridgeshire",
    "sg:tags":[
        "merchant",
        "builder"
    ],
    "wof:name":"Travis Perkins Trading Co. Ltd.",
    "wof:placetype":"venue"
},
  "geometry": {"coordinates":[0.13927,52.199009],"type":"Point"}
}