{
  "type": "Feature",
  "properties": {
    "addr:full":"764 Manchester Road Rochdale Lancashire OL11 3AW",
    "addr:housenumber":"764",
    "addr:postcode":"ol11 3aw",
    "addr:street":"Manchester Road",
    "iso:country":"GB",
    "sg:address":"764 Manchester Road",
    "sg:city":"Rochdale",
    "sg:classifiers":[
        {
            "category":"Food & Beverages",
            "subcategory":"Candy",
            "type":"Retail Goods"
        }
    ],
    "sg:phone":"+44 1706 632716",
    "sg:postcode":"OL11 3AW",
    "sg:province":"Lancashire",
    "sg:tags":[
        "confectioner"
    ],
    "wof:name":"Smith's Confectioners",
    "wof:placetype":"venue"
},
  "geometry": {"coordinates":[-2.1811819077,53.5931587219],"type":"Point"}
}