{
  "type": "Feature",
  "properties": {
    "addr:full":"35 Hall Lane Deeside Flintshire CH5 4LY",
    "addr:housenumber":"35",
    "addr:postcode":"ch5 4ly",
    "addr:street":"Hall Lane",
    "iso:country":"GB",
    "sg:address":"35 Hall Lane",
    "sg:city":"Deeside",
    "sg:classifiers":[
        {
            "category":"Building & Trades",
            "subcategory":"Construction",
            "type":"Services"
        }
    ],
    "sg:phone":"+44 1244 810255",
    "sg:postcode":"CH5 4LY",
    "sg:province":"Flintshire",
    "sg:tags":[
        "builder"
    ],
    "wof:name":"Stephen Betts",
    "wof:placetype":"venue"
},
  "geometry": {"coordinates":[-3.059352,53.210316],"type":"Point"}
}