{
  "type": "Feature",
  "properties": {
    "addr:full":"16a Howgate Shopping Centre, High Street Falkirk Falkirk FK1 1HG",
    "addr:housenumber":"16a",
    "addr:postcode":"fk1 1hg",
    "addr:street":"Howgate Shopping;High Street",
    "iso:country":"GB",
    "sg:address":"16a Howgate Shopping Centre, High Street",
    "sg:city":"Falkirk",
    "sg:classifiers":[
        {
            "category":"Shopping",
            "subcategory":"Hobbies, Toys, & Games",
            "type":"Retail Goods"
        },
        {
            "category":"Shopping",
            "subcategory":"News",
            "type":"Retail Goods"
        }
    ],
    "sg:phone":"+44 1324 639912",
    "sg:postcode":"FK1 1HG",
    "sg:province":"Falkirk",
    "sg:tags":[
        "shop",
        "toy",
        "newsagent",
        "sale"
    ],
    "sg:website":"http://www.elc.co.uk",
    "wof:name":"Early Learning Centre",
    "wof:placetype":"venue"
},
  "geometry": {"coordinates":[-3.7785921097,55.9874916077],"type":"Point"}
}