{
  "type": "Feature",
  "properties": {
    "iso:country":"GB",
    "sg:address":"Century Ho, 173a Chorley New Rd",
    "sg:city":"Bolton",
    "sg:classifiers":[
        {
            "category":"Real Estate",
            "subcategory":"Architect",
            "type":"Services"
        }
    ],
    "sg:postcode":"BL1 4QZ",
    "sg:province":"Lancashire",
    "wof:name":"Greenhalgh & Williams Partnership",
    "wof:placetype":"venue"
},
  "geometry": {"coordinates":[-2.426594,53.578289],"type":"Point"}
}