{
  "type": "Feature",
  "properties": {
    "iso:country":"GB",
    "sg:address":"19 Sharps Lane",
    "sg:city":"Dundee",
    "sg:classifiers":[
        {
            "category":"Building & Trades",
            "subcategory":"Construction",
            "type":"Services"
        }
    ],
    "sg:phone":"+44 1382 641751",
    "sg:postcode":"DD2 3EU",
    "sg:province":"Dundee City",
    "sg:tags":[
        "roofing"
    ],
    "wof:name":"Kean Slaters",
    "wof:placetype":"venue"
},
  "geometry": {"coordinates":[-3.017923,56.470161],"type":"Point"}
}