{
  "type": "Feature",
  "properties": {
    "iso:country":"GB",
    "sg:address":"Lower Sirhowy",
    "sg:city":"Tredegar",
    "sg:classifiers":[
        {
            "category":"Autos & Motor Vehicles",
            "subcategory":"Automobile Sales",
            "type":"Retail Goods"
        }
    ],
    "sg:phone":"+44 1495 725311",
    "sg:postcode":"NP2 4XL",
    "sg:province":"Blaenau Gwent",
    "sg:tags":[
        "car"
    ],
    "wof:name":"Tredegar Ford",
    "wof:placetype":"venue"
},
  "geometry": {"coordinates":[-3.23717,51.783661],"type":"Point"}
}