{
  "type": "Feature",
  "properties": {
    "addr:full":"17 Mereland Road Didcot Oxfordshire OX11 8AS",
    "addr:housenumber":"17",
    "addr:postcode":"ox11 8as",
    "addr:street":"Mereland Road",
    "iso:country":"GB",
    "sg:address":"17 Mereland Road",
    "sg:city":"Didcot",
    "sg:classifiers":[
        {
            "category":"Health Services",
            "subcategory":"Doctor",
            "type":"Services"
        },
        {
            "category":"Health Services",
            "subcategory":"Clinic",
            "type":"Services"
        }
    ],
    "sg:postcode":"OX11 8AS",
    "sg:province":"Oxfordshire",
    "sg:tags":[
        "nh",
        "practitioners"
    ],
    "wof:name":"Mereland Road Surgery",
    "wof:placetype":"venue"
},
  "geometry": {"coordinates":[-1.2398680449,51.6041526794],"type":"Point"}
}