{
  "type": "Feature",
  "properties": {
    "iso:country":"GB",
    "sg:address":"5 Newton Sidings, High Moor Lane, Shipton By Beningbrough",
    "sg:city":"York",
    "sg:classifiers":[
        {
            "category":"Building & Trades",
            "subcategory":"Cleaning & Sanitation",
            "type":"Services"
        },
        {
            "category":"Retail",
            "subcategory":"Repair Shop",
            "type":"Services"
        }
    ],
    "sg:phone":"+44 1904 470664",
    "sg:postcode":"YO30 1AT",
    "sg:province":"North Yorkshire",
    "sg:tags":[
        "plant",
        "machinery",
        "maintenance"
    ],
    "wof:name":"David J Johnson",
    "wof:placetype":"venue"
},
  "geometry": {"coordinates":[-1.1933729649,54.0126304626],"type":"Point"}
}