{
  "type": "Feature",
  "properties": {
    "addr:full":"Burlington Ho, 118 Burlington Rd New Malden Surrey KT3 4NR",
    "addr:housenumber":"118",
    "addr:postcode":"kt3 4nr",
    "addr:street":"Burlington Rd",
    "iso:country":"GB",
    "sg:address":"Burlington Ho, 118 Burlington Rd",
    "sg:city":"New Malden",
    "sg:classifiers":[
        {
            "category":"Farming",
            "subcategory":"Fish & Marine Products",
            "type":"Manufacturing & Wholesale Goods"
        }
    ],
    "sg:phone":"+44 20 8942 2488",
    "sg:postcode":"KT3 4NR",
    "sg:province":"Surrey",
    "sg:tags":[
        "equipment",
        "electrical"
    ],
    "wof:name":"Sperry Marine B V",
    "wof:placetype":"venue"
},
  "geometry": {"coordinates":[-0.2561939955,51.4017715454],"type":"Point"}
}