{
  "type": "Feature",
  "properties": {
    "addr:full":"11 London Street Swaffham Norfolk PE37 7BW",
    "addr:housenumber":"11",
    "addr:postcode":"pe37 7bw",
    "addr:street":"London Street",
    "iso:country":"GB",
    "sg:address":"11 London Street",
    "sg:city":"Swaffham",
    "sg:classifiers":[
        {
            "category":"Social Services",
            "subcategory":"Adult Care",
            "type":"Services"
        }
    ],
    "sg:postcode":"PE37 7BW",
    "sg:province":"Norfolk",
    "sg:tags":[
        "day",
        "centre"
    ],
    "wof:name":"John Chapman Day Centre Ltd.",
    "wof:placetype":"venue"
},
  "geometry": {"coordinates":[0.689019978,52.6463623047],"type":"Point"}
}