{
  "type": "Feature",
  "properties": {
    "iso:country":"GB",
    "sg:address":"7 Stratford Rd",
    "sg:city":"Leamington Spa",
    "sg:classifiers":[
        {
            "category":"Retail",
            "subcategory":"Driving School",
            "type":"Services"
        }
    ],
    "sg:phone":"+44 1926 641914",
    "sg:postcode":"CV33 9TN",
    "sg:province":"Warwickshire",
    "wof:name":"Mansell School Of Motoring",
    "wof:placetype":"venue"
},
  "geometry": {"coordinates":[-1.488517,52.199337],"type":"Point"}
}