{
  "type": "Feature",
  "properties": {
    "addr:full":"16 Moreton Wood Market Drayton Shropshire TF9 3RX",
    "addr:housenumber":"16",
    "addr:postcode":"tf9 3rx",
    "addr:street":"Moreton Wood",
    "iso:country":"GB",
    "sg:address":"16 Moreton Wood",
    "sg:city":"Market Drayton",
    "sg:classifiers":[
        {
            "category":"Building & Trades",
            "subcategory":"Construction",
            "type":"Services"
        }
    ],
    "sg:phone":"+44 1630 638880",
    "sg:postcode":"TF9 3RX",
    "sg:province":"Shropshire",
    "sg:tags":[
        "dry",
        "plastering",
        "plasterers",
        "lining",
        "related",
        "screeders"
    ],
    "wof:name":"Shropshire Plasterers",
    "wof:placetype":"venue"
},
  "geometry": {"coordinates":[-2.486172,52.904091],"type":"Point"}
}