{
  "type": "Feature",
  "properties": {
    "iso:country":"GB",
    "sg:address":"Penmaen Small Business Centre, Penmaen Rd, Pontllanfraith",
    "sg:city":"Blackwood",
    "sg:classifiers":[
        {
            "category":"Professional",
            "type":"Services"
        }
    ],
    "sg:phone":"+44 1495 220561",
    "sg:postcode":"NP12 2DZ",
    "sg:province":"Caerphilly",
    "sg:tags":[
        "repair",
        "tech",
        "maintenance"
    ],
    "wof:name":"Systems Unlimited",
    "wof:placetype":"venue"
},
  "geometry": {"coordinates":[-3.196165,51.649952],"type":"Point"}
}