{
  "type": "Feature",
  "properties": {
    "iso:country":"GB",
    "sg:address":"Liandawood, Tilford Road",
    "sg:city":"Hindhead",
    "sg:classifiers":[
        {
            "category":"Professional",
            "type":"Services"
        }
    ],
    "sg:phone":"+44 1428 608833",
    "sg:postcode":"GU26 6RB",
    "sg:province":"Hampshire",
    "sg:tags":[
        "interior",
        "furnishers",
        "designer"
    ],
    "wof:name":"I D C (Compton) Ltd.",
    "wof:placetype":"venue"
},
  "geometry": {"coordinates":[-0.7531679869,51.1218795776],"type":"Point"}
}