{
  "type": "Feature",
  "properties": {
    "addr:full":"17-19 Queens Square Crawley Surrey RH10 1EA",
    "addr:housenumber":"17-19",
    "addr:postcode":"rh10 1ea",
    "addr:street":"Queens Square",
    "iso:country":"GB",
    "sg:address":"17-19 Queens Square",
    "sg:city":"Crawley",
    "sg:classifiers":[
        {
            "category":"Shopping",
            "subcategory":"Department Store",
            "type":"Retail Goods"
        }
    ],
    "sg:phone":"+44 1293 516396",
    "sg:postcode":"RH10 1EA",
    "sg:province":"Surrey",
    "sg:tags":[
        "departmental"
    ],
    "wof:name":"Woolworths plc",
    "wof:placetype":"venue"
},
  "geometry": {"coordinates":[-0.186787,51.11562],"type":"Point"}
}