{
  "type": "Feature",
  "properties": {
    "addr:full":"5-9 Anerley, Station Road London Greater London SE20 8PY",
    "addr:housenumber":"5-9",
    "addr:postcode":"se20 8py",
    "addr:street":"Anerley Station Road",
    "iso:country":"GB",
    "sg:address":"5-9 Anerley, Station Road",
    "sg:city":"London",
    "sg:classifiers":[
        {
            "category":"Home & Garden",
            "subcategory":"Building Materials",
            "type":"Retail Goods"
        }
    ],
    "sg:phone":"+44 20 8776 7080",
    "sg:postcode":"SE20 8PY",
    "sg:province":"Greater London",
    "sg:tags":[
        "equipment",
        "disability"
    ],
    "wof:name":"Neves Mobility",
    "wof:placetype":"venue"
},
  "geometry": {"coordinates":[-0.0640750006,51.4125137329],"type":"Point"}
}