{
  "type": "Feature",
  "properties": {
    "addr:full":"16 South Market Place Alford Lincolnshire LN13 9AE",
    "addr:housenumber":"16",
    "addr:postcode":"ln13 9ae",
    "addr:street":"South Market Place",
    "iso:country":"GB",
    "sg:address":"16 South Market Place",
    "sg:city":"Alford",
    "sg:classifiers":[
        {
            "category":"Shopping",
            "subcategory":"Clothing, Apparel, & Fashions",
            "type":"Retail Goods"
        }
    ],
    "sg:postcode":"LN13 9AE",
    "sg:province":"Lincolnshire",
    "sg:tags":[
        "lingerie",
        "hosiery"
    ],
    "wof:name":"Jean & Peter Gell",
    "wof:placetype":"venue"
},
  "geometry": {"coordinates":[0.179908,53.260677],"type":"Point"}
}