{
  "type": "Feature",
  "properties": {
    "iso:country":"GB",
    "sg:address":"3 Pinfold La",
    "sg:city":"Sleaford",
    "sg:classifiers":[
        {
            "category":"Shopping",
            "subcategory":"Antiques",
            "type":"Retail Goods"
        }
    ],
    "sg:phone":"+44 1526 832057",
    "sg:postcode":"NG34 9EU",
    "sg:province":"Lincolnshire",
    "wof:name":"Pinfold Antiques",
    "wof:placetype":"venue"
},
  "geometry": {"coordinates":[-0.387503,53.047264],"type":"Point"}
}