{
  "type": "Feature",
  "properties": {
    "addr:full":", Carleton Carlisle Cumbria CA4 0AA",
    "addr:postcode":"ca4 0aa",
    "iso:country":"GB",
    "sg:address":", Carleton",
    "sg:city":"Carlisle",
    "sg:classifiers":[
        {
            "category":"Government",
            "subcategory":"Department Of Motor Vehicles",
            "type":"Public Place"
        },
        {
            "category":"Sports & Exercise",
            "subcategory":"Tennis Court",
            "type":"Entertainment"
        }
    ],
    "sg:phone":"+44 1228 527287",
    "sg:postcode":"CA4 0AA",
    "sg:province":"Cumbria",
    "sg:tags":[
        "breakdown",
        "car",
        "recovery"
    ],
    "wof:name":"Carleton Service Station",
    "wof:placetype":"venue"
},
  "geometry": {"coordinates":[-2.896109,54.870129],"type":"Point"}
}