{
  "type": "Feature",
  "properties": {
    "iso:country":"GB",
    "sg:address":"11 Vicarage Street",
    "sg:city":"Warminster",
    "sg:classifiers":[
        {
            "category":"Education",
            "subcategory":"School",
            "type":"Public Place"
        }
    ],
    "sg:phone":"+44 1985 210152",
    "sg:postcode":"BA12 8JG",
    "sg:province":"Somerset",
    "sg:tags":[
        "independent",
        "preparatory"
    ],
    "wof:name":"Warminster Preparatory School",
    "wof:placetype":"venue"
},
  "geometry": {"coordinates":[-2.189179,51.204693],"type":"Point"}
}