{
  "type": "Feature",
  "properties": {
    "addr:full":"52-56 Frodsham Street Chester Cheshire CH1 3JL",
    "addr:housenumber":"52-56",
    "addr:postcode":"ch1 3jl",
    "addr:street":"Frodsham Street",
    "iso:country":"GB",
    "sg:address":"52-56 Frodsham Street",
    "sg:city":"Chester",
    "sg:classifiers":[
        {
            "category":"Home & Garden",
            "subcategory":"Hardware",
            "type":"Retail Goods"
        }
    ],
    "sg:phone":"+44 1244 24752",
    "sg:postcode":"CH1 3JL",
    "sg:province":"Cheshire",
    "wof:name":"W E Clarke",
    "wof:placetype":"venue"
},
  "geometry": {"coordinates":[-2.8883910179,53.1926689148],"type":"Point"}
}