{
  "type": "Feature",
  "properties": {
    "iso:country":"GB",
    "sg:address":"180 The Common, Holt",
    "sg:city":"Trowbridge",
    "sg:classifiers":[
        {
            "category":"Government",
            "subcategory":"Post Office",
            "type":"Public Place"
        }
    ],
    "sg:phone":"+44 1225 782220",
    "sg:postcode":"BA14 6QL",
    "sg:province":"Wiltshire",
    "wof:name":"Holt P.O",
    "wof:placetype":"venue"
},
  "geometry": {"coordinates":[-2.194236,51.358574],"type":"Point"}
}