{
  "type": "Feature",
  "properties": {
    "iso:country":"GB",
    "sg:address":"12 Laurence Drive, Swinton",
    "sg:city":"Mexborough",
    "sg:classifiers":[
        {
            "category":"Building & Trades",
            "subcategory":"Plumbing",
            "type":"Services"
        }
    ],
    "sg:phone":"+44 1709 588655",
    "sg:postcode":"S64 8SN",
    "sg:province":"South Yorkshire",
    "sg:tags":[
        "heating"
    ],
    "wof:name":"Tony Epton",
    "wof:placetype":"venue"
},
  "geometry": {"coordinates":[-1.317869,53.487766],"type":"Point"}
}