{
  "type": "Feature",
  "properties": {
    "addr:full":"Civic Centre, John Dickie St Kilmarnock East Ayrshire KA1 1BY",
    "addr:postcode":"ka1 1by",
    "addr:street":"John Dickie St Kilmarnock East",
    "iso:country":"GB",
    "sg:address":"Civic Centre, John Dickie St",
    "sg:city":"Kilmarnock",
    "sg:classifiers":[
        {
            "category":"Government",
            "subcategory":"Office",
            "type":"Public Place"
        }
    ],
    "sg:phone":"+44 1563 524291",
    "sg:postcode":"KA1 1BY",
    "sg:province":"East Ayrshire",
    "sg:tags":[
        "local"
    ],
    "wof:name":"East Ayrshire Council",
    "wof:placetype":"venue"
},
  "geometry": {"coordinates":[-4.5060901642,55.6033210754],"type":"Point"}
}