{
  "type": "Feature",
  "properties": {
    "iso:country":"GB",
    "sg:address":"46 Jamaica St",
    "sg:city":"Liverpool",
    "sg:classifiers":[
        {
            "category":"Autos & Motor Vehicles",
            "subcategory":"Auto Supplies",
            "type":"Retail Goods"
        }
    ],
    "sg:phone":"+44 151 708 5333",
    "sg:postcode":"L1 0AF",
    "sg:province":"Merseyside",
    "sg:tags":[
        "part",
        "motorcycle",
        "accessory"
    ],
    "wof:name":"Digital Imaging",
    "wof:placetype":"venue"
},
  "geometry": {"coordinates":[-2.980242,53.397198],"type":"Point"}
}