{
  "type": "Feature",
  "properties": {
    "addr:full":"8 Pendlebury Road, Gatley Cheadle Cheshire SK8 4BH",
    "addr:housenumber":"8",
    "addr:postcode":"sk8 4bh",
    "addr:street":"Pendlebury Road;Cheadle",
    "iso:country":"GB",
    "sg:address":"8 Pendlebury Road, Gatley",
    "sg:city":"Cheadle",
    "sg:classifiers":[
        {
            "category":"Professional",
            "subcategory":"Business Services",
            "type":"Services"
        }
    ],
    "sg:phone":"+44 161 283 6656",
    "sg:postcode":"SK8 4BH",
    "sg:province":"Cheshire",
    "sg:tags":[
        "information"
    ],
    "wof:name":"Resource Services",
    "wof:placetype":"venue"
},
  "geometry": {"coordinates":[-2.2352058887,53.3944129944],"type":"Point"}
}