{
  "type": "Feature",
  "properties": {
    "addr:full":"9 St Pauls Sq Bromley Kent BR2 0XH",
    "addr:housenumber":"9",
    "addr:postcode":"br2 0xh",
    "addr:street":"St Pauls Sq",
    "iso:country":"GB",
    "sg:address":"9 St Pauls Sq",
    "sg:city":"Bromley",
    "sg:classifiers":[
        {
            "category":"Place Of Worship",
            "type":"Public Place"
        }
    ],
    "sg:phone":"+44 20 8460 6275",
    "sg:postcode":"BR2 0XH",
    "sg:province":"Kent",
    "wof:name":"Can P Lock",
    "wof:placetype":"venue"
},
  "geometry": {"coordinates":[0.011688,51.40543],"type":"Point"}
}