{
  "type": "Feature",
  "properties": {
    "iso:country":"GB",
    "sg:address":"Environtec House, The Street, Hatfield Peverel",
    "sg:city":"Chelmsford",
    "sg:classifiers":[
        {
            "category":"Professional",
            "subcategory":"Engineering",
            "type":"Services"
        },
        {
            "category":"Professional",
            "subcategory":"Management & Consulting",
            "type":"Services"
        }
    ],
    "sg:phone":"+44 1245 381900",
    "sg:postcode":"CM3 2EJ",
    "sg:province":"Essex",
    "sg:tags":[
        "environmental",
        "consultant",
        "engineer"
    ],
    "wof:name":"Environtec Ltd",
    "wof:placetype":"venue"
},
  "geometry": {"coordinates":[0.587216,51.774334],"type":"Point"}
}