{
  "type": "Feature",
  "properties": {
    "addr:full":"Unit 3 Victoria Parade Rossendale Lancashire BB4 9AB",
    "addr:housenumber":"unit 3",
    "addr:postcode":"bb4 9ab",
    "addr:street":"Victoria Parade",
    "iso:country":"GB",
    "sg:address":"Unit 3 Victoria Parade",
    "sg:city":"Rossendale",
    "sg:classifiers":[
        {
            "category":"Shopping",
            "subcategory":"Shoes",
            "type":"Retail Goods"
        }
    ],
    "sg:postcode":"BB4 9AB",
    "sg:province":"Lancashire",
    "sg:tags":[
        "footwear"
    ],
    "wof:name":"Trinity Footwear",
    "wof:placetype":"venue"
},
  "geometry": {"coordinates":[-2.253549099,53.6928062439],"type":"Point"}
}