{
  "type": "Feature",
  "properties": {
    "iso:country":"GB",
    "sg:address":"Northminster Road",
    "sg:city":"Peterborough",
    "sg:classifiers":[
        {
            "category":"Sports & Exercise",
            "subcategory":"Gym",
            "type":"Entertainment"
        }
    ],
    "sg:phone":"+44 1733 555466",
    "sg:postcode":"PE1 1FH",
    "sg:province":"Cambridgeshire",
    "sg:tags":[
        "fitness",
        "health",
        "centre"
    ],
    "wof:name":"Energy",
    "wof:placetype":"venue"
},
  "geometry": {"coordinates":[-0.2400680035,52.5759124756],"type":"Point"}
}