{
  "type": "Feature",
  "properties": {
    "addr:full":"28 Great Queen Street London Greater London WC2B 5BB",
    "addr:housenumber":"28",
    "addr:postcode":"wc2b 5bb",
    "addr:street":"Great Queen Street",
    "iso:country":"GB",
    "sg:address":"28 Great Queen Street",
    "sg:city":"London",
    "sg:classifiers":[
        {
            "category":"Professional",
            "subcategory":"Advertising",
            "type":"Services"
        }
    ],
    "sg:phone":"+44 20 7831 3636",
    "sg:postcode":"WC2B 5BB",
    "sg:province":"Greater London",
    "sg:tags":[
        "agency"
    ],
    "wof:name":"Luxford Advertising Ltd.",
    "wof:placetype":"venue"
},
  "geometry": {"coordinates":[-0.121428,51.515446],"type":"Point"}
}