{
  "type": "Feature",
  "properties": {
    "addr:full":"167 Capstone Road Chatham Kent ME5 7PP",
    "addr:housenumber":"167",
    "addr:postcode":"me5 7pp",
    "addr:street":"Capstone Road",
    "iso:country":"GB",
    "sg:address":"167 Capstone Road",
    "sg:city":"Chatham",
    "sg:classifiers":[
        {
            "category":"Home & Garden",
            "subcategory":"Home Furnishings",
            "type":"Retail Goods"
        }
    ],
    "sg:postcode":"ME5 7PP",
    "sg:province":"Kent",
    "sg:tags":[
        "homefurnishings"
    ],
    "wof:name":"The Old Forge",
    "wof:placetype":"venue"
},
  "geometry": {"coordinates":[0.554062,51.363998],"type":"Point"}
}