{
  "type": "Feature",
  "properties": {
    "addr:full":"27 Stretton Rd, West Cotes Leicester Leicestershire LE3 6BL",
    "addr:housenumber":"27",
    "addr:postcode":"le3 6bl",
    "addr:street":"Stretton Rd",
    "iso:country":"GB",
    "sg:address":"27 Stretton Rd, West Cotes",
    "sg:city":"Leicester",
    "sg:classifiers":[
        {
            "category":"Manufacturing",
            "subcategory":"Glass & Minerals",
            "type":"Manufacturing & Wholesale Goods"
        }
    ],
    "sg:phone":"+44 116 291 6088",
    "sg:postcode":"LE3 6BL",
    "sg:province":"Leicestershire",
    "sg:tags":[
        "stained",
        "designer"
    ],
    "wof:name":"Baroque Studios",
    "wof:placetype":"venue"
},
  "geometry": {"coordinates":[-1.153576,52.632927],"type":"Point"}
}