{
  "type": "Feature",
  "properties": {
    "addr:full":"36 Market Place Wetherby North Yorkshire LS22 6NE",
    "addr:housenumber":"36",
    "addr:postcode":"north;ls22 6ne",
    "addr:street":"Market Place",
    "iso:country":"GB",
    "sg:address":"36 Market Place",
    "sg:city":"Wetherby",
    "sg:classifiers":[
        {
            "category":"Personal",
            "subcategory":"Beauty Salon",
            "type":"Services"
        }
    ],
    "sg:phone":"+44 1937 584709",
    "sg:postcode":"LS22 6NE",
    "sg:province":"North Yorkshire",
    "sg:tags":[
        "ladies",
        "lady",
        "hairdresser"
    ],
    "wof:name":"Kathleens Hair Care",
    "wof:placetype":"venue"
},
  "geometry": {"coordinates":[-1.386715,53.928249],"type":"Point"}
}