{
  "type": "Feature",
  "properties": {
    "iso:country":"GB",
    "sg:address":"Unit 7 Fordsall House, Old Huddersfield Road, Halifax",
    "sg:city":"Huddersfield",
    "sg:classifiers":[
        {
            "category":"Wholesale",
            "subcategory":"Groceries",
            "type":"Manufacturing & Wholesale Goods"
        }
    ],
    "sg:postcode":"HD5 9DW",
    "sg:province":"West Yorkshire",
    "sg:tags":[
        "food",
        "supplier",
        "drink"
    ],
    "wof:name":"Crown Catering",
    "wof:placetype":"venue"
},
  "geometry": {"coordinates":[-1.76553,53.644459],"type":"Point"}
}