{
  "type": "Feature",
  "properties": {
    "iso:country":"GB",
    "sg:address":"78 Greenlands Avenue, Greenlands",
    "sg:city":"Redditch",
    "sg:classifiers":[
        {
            "category":"Building & Trades",
            "subcategory":"Construction",
            "type":"Services"
        }
    ],
    "sg:postcode":"B98 7PZ",
    "sg:province":"Warwickshire",
    "sg:tags":[
        "contractor",
        "paving",
        "driveway"
    ],
    "wof:name":"Andrews Driveways",
    "wof:placetype":"venue"
},
  "geometry": {"coordinates":[-1.922326,52.293045],"type":"Point"}
}