{
  "type": "Feature",
  "properties": {
    "iso:country":"GB",
    "sg:address":"Unit 3 Tregrehan Work Shop, Tregrehan Mills",
    "sg:city":"St Austell",
    "sg:classifiers":[
        {
            "category":"Professional",
            "subcategory":"Art Services",
            "type":"Services"
        }
    ],
    "sg:postcode":"PL25 3TQ",
    "sg:province":"Cornwall",
    "sg:tags":[
        "framing"
    ],
    "wof:name":"Justin the Frame",
    "wof:placetype":"venue"
},
  "geometry": {"coordinates":[-4.750194,50.351231],"type":"Point"}
}