{
  "type": "Feature",
  "properties": {
    "iso:country":"GB",
    "sg:address":"40 Market Place",
    "sg:city":"Carluke",
    "sg:classifiers":[
        {
            "category":"Personal",
            "subcategory":"Beauty Salon",
            "type":"Services"
        }
    ],
    "sg:phone":"+44 1555 771544",
    "sg:postcode":"ML8 4BP",
    "sg:province":"South Lanarkshire",
    "sg:tags":[
        "unisex",
        "hairdresser"
    ],
    "wof:name":"Alices Ladies and Gents Hairstylist",
    "wof:placetype":"venue"
},
  "geometry": {"coordinates":[-3.839372,55.735809],"type":"Point"}
}