{
  "type": "Feature",
  "properties": {
    "addr:full":"17 Victoria Clo Bury St Edmunds Suffolk IP31 3SX",
    "addr:housenumber":"17",
    "addr:postcode":"ip31 3sx",
    "addr:street":"Victoria Clo",
    "iso:country":"GB",
    "sg:address":"17 Victoria Clo",
    "sg:city":"Bury St Edmunds",
    "sg:classifiers":[
        {
            "category":"Personal",
            "type":"Services"
        }
    ],
    "sg:phone":"+44 1359 231434",
    "sg:postcode":"IP31 3SX",
    "sg:province":"Suffolk",
    "sg:tags":[
        "wedding"
    ],
    "wof:name":"Elite Cakes",
    "wof:placetype":"venue"
},
  "geometry": {"coordinates":[0.815877,52.251202],"type":"Point"}
}