{
  "type": "Feature",
  "properties": {
    "iso:country":"GB",
    "sg:address":"Ballintuim",
    "sg:city":"Blairgowrie",
    "sg:classifiers":[
        {
            "category":"Building & Trades",
            "subcategory":"Construction",
            "type":"Services"
        }
    ],
    "sg:phone":"+44 1250 886205",
    "sg:postcode":"PH10 7NJ",
    "sg:province":"Perth and Kinross",
    "sg:tags":[
        "joinery"
    ],
    "wof:name":"Fendersheds",
    "wof:placetype":"venue"
},
  "geometry": {"coordinates":[-3.3827490807,56.6536026001],"type":"Point"}
}