{
  "type": "Feature",
  "properties": {
    "addr:full":"8 Commercial Street Halifax West Yorkshire HX1 1TA",
    "addr:housenumber":"8",
    "addr:postcode":"hx1 1ta",
    "addr:street":"Commercial Street",
    "iso:country":"GB",
    "sg:address":"8 Commercial Street",
    "sg:city":"Halifax",
    "sg:classifiers":[
        {
            "category":"Shopping",
            "subcategory":"Optician",
            "type":"Retail Goods"
        }
    ],
    "sg:postcode":"HX1 1TA",
    "sg:province":"West Yorkshire",
    "wof:name":"Jbr1910 Ltd.",
    "wof:placetype":"venue"
},
  "geometry": {"coordinates":[-1.8614920378,53.7230949402],"type":"Point"}
}