{
  "type": "Feature",
  "properties": {
    "addr:full":"The Square, Wiveliscombe Taunton Devon TA4 2JT",
    "addr:postcode":"ta4 2jt",
    "addr:street":"The Square",
    "iso:country":"GB",
    "sg:address":"The Square, Wiveliscombe",
    "sg:city":"Taunton",
    "sg:classifiers":[
        {
            "category":"Shopping",
            "subcategory":"Hobbies, Toys, & Games",
            "type":"Retail Goods"
        }
    ],
    "sg:phone":"+44 1984 623829",
    "sg:postcode":"TA4 2JT",
    "sg:province":"Devon",
    "sg:tags":[
        "gunsmith"
    ],
    "wof:name":"West Country Guns",
    "wof:placetype":"venue"
},
  "geometry": {"coordinates":[-3.3124740124,51.0422706604],"type":"Point"}
}