{
  "type": "Feature",
  "properties": {
    "addr:full":"57 Cumbrian Way Southampton Hampshire SO16 4AT",
    "addr:housenumber":"57",
    "addr:postcode":"so16 4at",
    "addr:street":"Cumbrian Way",
    "iso:country":"GB",
    "sg:address":"57 Cumbrian Way",
    "sg:city":"Southampton",
    "sg:classifiers":[
        {
            "category":"Government",
            "subcategory":"Post Office",
            "type":"Public Place"
        }
    ],
    "sg:phone":"+44 23 8077 3711",
    "sg:postcode":"SO16 4AT",
    "sg:province":"Hampshire",
    "wof:name":"S G Fryer Ltd.",
    "wof:placetype":"venue"
},
  "geometry": {"coordinates":[-1.45262,50.921619],"type":"Point"}
}