{
  "type": "Feature",
  "properties": {
    "addr:full":"125 Dunstable Road Luton Bedfordshire LU1 1BW",
    "addr:housenumber":"125",
    "addr:postcode":"lu1 1bw",
    "addr:street":"Dunstable Road",
    "iso:country":"GB",
    "sg:address":"125 Dunstable Road",
    "sg:city":"Luton",
    "sg:classifiers":[
        {
            "category":"Real Estate",
            "subcategory":"Real Estate Operator",
            "type":"Services"
        }
    ],
    "sg:phone":"+44 1582 483879",
    "sg:postcode":"LU1 1BW",
    "sg:province":"Bedfordshire",
    "sg:tags":[
        "letting",
        "agent"
    ],
    "wof:name":"Western Accommodation Bureau",
    "wof:placetype":"venue"
},
  "geometry": {"coordinates":[-0.426395,51.883526],"type":"Point"}
}