{
  "type": "Feature",
  "properties": {
    "addr:full":"Century Farmhouse, Reading Street Tenterden Kent TN30 7HS",
    "addr:postcode":"tn30 7hs",
    "addr:street":"Reading Street",
    "iso:country":"GB",
    "sg:address":"Century Farmhouse, Reading Street",
    "sg:city":"Tenterden",
    "sg:classifiers":[
        {
            "category":"Professional",
            "subcategory":"Testing Lab",
            "type":"Services"
        }
    ],
    "sg:phone":"+44 70 0072 7832",
    "sg:postcode":"TN30 7HS",
    "sg:province":"Kent",
    "sg:tags":[
        "inspection",
        "calibration"
    ],
    "wof:name":"Sartec Analytical Systems Ltd.",
    "wof:placetype":"venue"
},
  "geometry": {"coordinates":[0.6940600276,51.0754051208],"type":"Point"}
}