{
  "type": "Feature",
  "properties": {
    "addr:full":"Brookside House, Tothall Lane, Salford Priors Evesham Gloucestershire WR11 8SG",
    "addr:postcode":"wr11 8sg",
    "addr:street":"Tothall Lane",
    "iso:country":"GB",
    "sg:address":"Brookside House, Tothall Lane, Salford Priors",
    "sg:city":"Evesham",
    "sg:classifiers":[
        {
            "category":"Real Estate",
            "subcategory":"Architect",
            "type":"Services"
        }
    ],
    "sg:phone":"+44 1789 778956",
    "sg:postcode":"WR11 8SG",
    "sg:province":"Gloucestershire",
    "wof:name":"T E Bury",
    "wof:placetype":"venue"
},
  "geometry": {"coordinates":[-1.8893239498,52.1581192017],"type":"Point"}
}