{
  "type": "Feature",
  "properties": {
    "addr:full":"Chevin, Molewood Road Hertford Hertfordshire SG14 3AJ",
    "addr:postcode":"sg14 3aj",
    "addr:street":"Molewood Road",
    "iso:country":"GB",
    "sg:address":"Chevin, Molewood Road",
    "sg:city":"Hertford",
    "sg:classifiers":[
        {
            "category":"Shopping",
            "subcategory":"Pets & Pet Supplies",
            "type":"Retail Goods"
        }
    ],
    "sg:postcode":"SG14 3AJ",
    "sg:province":"Hertfordshire",
    "wof:name":"Woodlands",
    "wof:placetype":"venue"
},
  "geometry": {"coordinates":[-0.0895259976,51.8041038513],"type":"Point"}
}