{
  "type": "Feature",
  "properties": {
    "addr:full":"Hockley Road Rayleigh Essex SS6 8EB",
    "addr:postcode":"ss6 8eb",
    "addr:street":"Hockley Road Rayleigh",
    "iso:country":"GB",
    "sg:address":"Hockley Road",
    "sg:city":"Rayleigh",
    "sg:classifiers":[
        {
            "category":"Professional",
            "subcategory":"Business Services",
            "type":"Services"
        }
    ],
    "sg:phone":"+44 1268 742254",
    "sg:postcode":"SS6 8EB",
    "sg:province":"Essex",
    "sg:tags":[
        "operator",
        "market"
    ],
    "wof:name":"Rayleigh Market Place",
    "wof:placetype":"venue"
},
  "geometry": {"coordinates":[0.624728024,51.5968971252],"type":"Point"}
}