{
  "type": "Feature",
  "properties": {
    "iso:country":"GB",
    "sg:address":"Bilbut Farm",
    "sg:city":"Mitcheldean",
    "sg:classifiers":[
        {
            "category":"Farming",
            "subcategory":"Farm",
            "type":"Manufacturing & Wholesale Goods"
        }
    ],
    "sg:phone":"+44 1989 750359",
    "sg:postcode":"GL17 0DR",
    "sg:province":"Gloucestershire",
    "sg:tags":[
        "mixed",
        "crop"
    ],
    "wof:name":"Jack Batt",
    "wof:placetype":"venue"
},
  "geometry": {"coordinates":[-2.488882,51.866436],"type":"Point"}
}