{
  "type": "Feature",
  "properties": {
    "addr:full":"7 Boss Hall Road, Sproughton Industrial Estate Ipswich Suffolk IP1 5BN",
    "addr:housenumber":"7",
    "addr:postcode":"ip1 5bn",
    "addr:street":"Boss Hall Road;Industrial Estate",
    "iso:country":"GB",
    "sg:address":"7 Boss Hall Road, Sproughton Industrial Estate",
    "sg:city":"Ipswich",
    "sg:classifiers":[
        {
            "category":"Autos & Motor Vehicles",
            "subcategory":"Auto Supplies",
            "type":"Retail Goods"
        }
    ],
    "sg:phone":"+44 1473 463621",
    "sg:postcode":"IP1 5BN",
    "sg:province":"Suffolk",
    "sg:tags":[
        "component"
    ],
    "wof:name":"Brown Bros",
    "wof:placetype":"venue"
},
  "geometry": {"coordinates":[1.1246529818,52.0652618408],"type":"Point"}
}