{
  "type": "Feature",
  "properties": {
    "iso:country":"GB",
    "sg:address":"79 Manchester Road",
    "sg:city":"Altrincham",
    "sg:classifiers":[
        {
            "category":"Banks & Credit Unions",
            "subcategory":"Financial Services",
            "type":"Services"
        }
    ],
    "sg:phone":"+44 161 929 0911",
    "sg:postcode":"WA14 4RJ",
    "sg:province":"Cheshire",
    "sg:tags":[
        "consultant"
    ],
    "wof:name":"London Scottish Finance",
    "wof:placetype":"venue"
},
  "geometry": {"coordinates":[-2.352424,53.396717],"type":"Point"}
}