{
  "type": "Feature",
  "properties": {
    "addr:full":"26 Mill Lane, Earley Reading Berkshire RG6 7JE",
    "addr:housenumber":"26",
    "addr:postcode":"rg6 7je",
    "addr:street":"Mill Lane",
    "iso:country":"GB",
    "sg:address":"26 Mill Lane, Earley",
    "sg:city":"Reading",
    "sg:classifiers":[
        {
            "category":"Professional",
            "subcategory":"Management & Consulting",
            "type":"Services"
        }
    ],
    "sg:phone":"+44 118 966 3503",
    "sg:postcode":"RG6 7JE",
    "sg:province":"Berkshire",
    "sg:tags":[
        "consultant",
        "business"
    ],
    "wof:name":"Flexiline Consultants Ltd.",
    "wof:placetype":"venue"
},
  "geometry": {"coordinates":[-0.907286,51.437065],"type":"Point"}
}