{
  "type": "Feature",
  "properties": {
    "iso:country":"GB",
    "sg:address":"47 Bro Deg",
    "sg:city":"Ruthin",
    "sg:classifiers":[
        {
            "category":"Building & Trades",
            "subcategory":"Construction",
            "type":"Services"
        }
    ],
    "sg:postcode":"LL15 1YQ",
    "sg:province":"Denbighshire",
    "sg:tags":[
        "joinery",
        "joiner",
        "carpenter",
        "carpentry"
    ],
    "wof:name":"ROBERT PAUL ARGENT",
    "wof:placetype":"venue"
},
  "geometry": {"coordinates":[-3.299875,53.107281],"type":"Point"}
}