{
  "type": "Feature",
  "properties": {
    "iso:country":"GB",
    "sg:address":"Old Ice Factory, Rolle Street",
    "sg:city":"Barnstaple",
    "sg:classifiers":[
        {
            "category":"Professional",
            "subcategory":"Printing & Photocopies",
            "type":"Services"
        }
    ],
    "sg:postcode":"EX31 1JP",
    "sg:province":"Devon",
    "sg:tags":[
        "printer"
    ],
    "wof:name":"Print Shop",
    "wof:placetype":"venue"
},
  "geometry": {"coordinates":[-4.06482,51.083969],"type":"Point"}
}