{
  "type": "Feature",
  "properties": {
    "addr:full":"1161 Chester Road, Erdington Birmingham West Midlands B24 0QY",
    "addr:housenumber":"1161",
    "addr:postcode":"b24 0qy",
    "addr:street":"Chester Road",
    "iso:country":"GB",
    "sg:address":"1161 Chester Road, Erdington",
    "sg:city":"Birmingham",
    "sg:classifiers":[
        {
            "category":"Wholesale",
            "subcategory":"Fruits & Vegetables",
            "type":"Manufacturing & Wholesale Goods"
        }
    ],
    "sg:phone":"+44 121 377 6418",
    "sg:postcode":"B24 0QY",
    "sg:province":"West Midlands",
    "wof:name":"Loves Plc",
    "wof:placetype":"venue"
},
  "geometry": {"coordinates":[-1.8022300005,52.5205764771],"type":"Point"}
}