{
  "type": "Feature",
  "properties": {
    "iso:country":"GB",
    "sg:address":"39 Gibbwin",
    "sg:city":"Milton Keynes",
    "sg:classifiers":[
        {
            "category":"Autos & Motor Vehicles",
            "subcategory":"Motorcycle Sales",
            "type":"Retail Goods"
        }
    ],
    "sg:phone":"+44 1908 674398",
    "sg:postcode":"MK14 5DW",
    "sg:province":"Buckinghamshire",
    "sg:tags":[
        "chauffeur",
        "driven",
        "car"
    ],
    "wof:name":"Carriage Enterprises Ltd.",
    "wof:placetype":"venue"
},
  "geometry": {"coordinates":[-0.761259973,52.0673713684],"type":"Point"}
}