{
  "type": "Feature",
  "properties": {
    "iso:country":"GB",
    "sg:address":"Millfield Nursery, Parsonage Lane, Kingston St Mary",
    "sg:city":"Taunton",
    "sg:classifiers":[
        {
            "category":"Building & Trades",
            "subcategory":"Landscaping Services",
            "type":"Services"
        }
    ],
    "sg:phone":"+44 1823 451256",
    "sg:postcode":"TA2 8HL",
    "sg:province":"Somerset",
    "sg:tags":[
        "gardening",
        "landscape",
        "contractor"
    ],
    "wof:name":"FOUR WINDS LANDSCAPING (TAUNTON) LTD",
    "wof:placetype":"venue"
},
  "geometry": {"coordinates":[-3.11736,51.056721],"type":"Point"}
}