{
  "type": "Feature",
  "properties": {
    "addr:full":"37 Rufford Avenue Leeds West Yorkshire LS19 7QR",
    "addr:housenumber":"37",
    "addr:postcode":"ls19 7qr",
    "addr:street":"Rufford Avenue",
    "iso:country":"GB",
    "sg:address":"37 Rufford Avenue",
    "sg:city":"Leeds",
    "sg:classifiers":[
        {
            "category":"Personal",
            "type":"Services"
        }
    ],
    "sg:postcode":"LS19 7QR",
    "sg:province":"West Yorkshire",
    "sg:tags":[
        "wedding"
    ],
    "wof:name":"Fairytales",
    "wof:placetype":"venue"
},
  "geometry": {"coordinates":[-1.6826100349,53.8629989624],"type":"Point"}
}