{
  "type": "Feature",
  "properties": {
    "addr:full":"Lower Fold Cottage, Belmont Road, Bromley Cross Bolton Lancashire BL7 9QS",
    "addr:postcode":"bl7 9qs",
    "addr:street":"Lower;Belmont Road",
    "iso:country":"GB",
    "sg:address":"Lower Fold Cottage, Belmont Road, Bromley Cross",
    "sg:city":"Bolton",
    "sg:classifiers":[
        {
            "category":"Building & Trades",
            "subcategory":"Construction",
            "type":"Services"
        }
    ],
    "sg:postcode":"BL7 9QS",
    "sg:province":"Lancashire",
    "sg:tags":[
        "builder"
    ],
    "wof:name":"F J Holmes",
    "wof:placetype":"venue"
},
  "geometry": {"coordinates":[-2.430099,53.622147],"type":"Point"}
}