{
  "type": "Feature",
  "properties": {
    "iso:country":"GB",
    "sg:address":"17 High Street, Long Sutton",
    "sg:city":"Spalding",
    "sg:classifiers":[
        {
            "category":"Personal",
            "subcategory":"Beauty Salon",
            "type":"Services"
        },
        {
            "category":"Personal",
            "subcategory":"Barber",
            "type":"Services"
        }
    ],
    "sg:phone":"+44 1406 363287",
    "sg:postcode":"PE12 9DB",
    "sg:province":"Cambridgeshire",
    "sg:tags":[
        "unisex",
        "hairdresser"
    ],
    "wof:name":"Scissors Hair Design",
    "wof:placetype":"venue"
},
  "geometry": {"coordinates":[0.122587,52.785412],"type":"Point"}
}