{
  "type": "Feature",
  "properties": {
    "iso:country":"GB",
    "sg:address":"Vale Mill, Vale Street",
    "sg:city":"Bolton",
    "sg:classifiers":[
        {
            "category":"Building & Trades",
            "subcategory":"Cleaning & Sanitation",
            "type":"Services"
        },
        {
            "category":"Home & Garden",
            "subcategory":"Home Furnishings",
            "type":"Retail Goods"
        }
    ],
    "sg:postcode":"BL2 6QF",
    "sg:province":"Lancashire",
    "sg:tags":[
        "homefurnishings",
        "blast"
    ],
    "wof:name":"E R D Shotblasting & Painting",
    "wof:placetype":"venue"
},
  "geometry": {"coordinates":[-2.37383,53.579479],"type":"Point"}
}