{
  "type": "Feature",
  "properties": {
    "iso:country":"GB",
    "sg:address":"Unit 105, In Shops, Swan Centre, Yardley",
    "sg:city":"Birmingham",
    "sg:classifiers":[
        {
            "category":"Professional",
            "subcategory":"Computer Services",
            "type":"Services"
        }
    ],
    "sg:phone":"+44 121 608 5229",
    "sg:postcode":"B26 3JB",
    "sg:province":"West Midlands",
    "sg:tags":[
        "system",
        "software"
    ],
    "wof:name":"Little Software Co",
    "wof:placetype":"venue"
},
  "geometry": {"coordinates":[-1.732246,52.452965],"type":"Point"}
}