{
  "type": "Feature",
  "properties": {
    "addr:full":"Unit 1, Parkgate Industrial Estate Knutsford Cheshire WA16 8HD",
    "addr:housenumber":"unit 1;estate",
    "addr:postcode":"wa16 8hd",
    "addr:street":"Parkgate Industrial",
    "iso:country":"GB",
    "sg:address":"Unit 1, Parkgate Industrial Estate",
    "sg:city":"Knutsford",
    "sg:classifiers":[
        {
            "category":"Shopping",
            "subcategory":"Stationery & Office Supplies",
            "type":"Retail Goods"
        }
    ],
    "sg:phone":"+44 1565 650162",
    "sg:postcode":"WA16 8HD",
    "sg:province":"Cheshire",
    "sg:tags":[
        "printers'"
    ],
    "wof:name":"B & S Swindells (Print Finishers) Ltd.",
    "wof:placetype":"venue"
},
  "geometry": {"coordinates":[-2.37624,53.304203],"type":"Point"}
}