{
  "type": "Feature",
  "properties": {
    "iso:country":"GB",
    "sg:address":"8a Old Liverpool Road",
    "sg:city":"Warrington",
    "sg:classifiers":[
        {
            "category":"Retail",
            "subcategory":"Auto Repair",
            "type":"Services"
        }
    ],
    "sg:phone":"+44 1925 632970",
    "sg:postcode":"WA5 1EE",
    "sg:province":"Cheshire",
    "sg:tags":[
        "modification",
        "garage"
    ],
    "wof:name":"Sankey Bridges Autos",
    "wof:placetype":"venue"
},
  "geometry": {"coordinates":[-2.6155190468,53.3849983215],"type":"Point"}
}