{
  "type": "Feature",
  "properties": {
    "addr:full":"The Wells Physiotherapy & Sports Clinic, 4 Clanricarde Garden Tunbridge Wells Kent TN1 1PE",
    "addr:housenumber":"4",
    "addr:postcode":"tn1 1pe",
    "addr:street":"Clanricarde Garden;Wells",
    "iso:country":"GB",
    "sg:address":"The Wells Physiotherapy & Sports Clinic, 4 Clanricarde Garden",
    "sg:city":"Tunbridge Wells",
    "sg:classifiers":[
        {
            "category":"Health Services",
            "subcategory":"Health Practitioner",
            "type":"Services"
        }
    ],
    "sg:phone":"+44 1892 525065",
    "sg:postcode":"TN1 1PE",
    "sg:province":"Kent",
    "sg:tags":[
        "osteopath"
    ],
    "wof:name":"Alison Scoble",
    "wof:placetype":"venue"
},
  "geometry": {"coordinates":[0.2616130114,51.1316566467],"type":"Point"}
}