{
  "type": "Feature",
  "properties": {
    "addr:full":"4 Church Terrace Richmond Greater London TW10 6SE",
    "addr:housenumber":"4",
    "addr:postcode":"tw10 6se",
    "addr:street":"Church Terrace",
    "iso:country":"GB",
    "sg:address":"4 Church Terrace",
    "sg:city":"Richmond",
    "sg:classifiers":[
        {
            "category":"Real Estate",
            "subcategory":"Surveying",
            "type":"Services"
        }
    ],
    "sg:phone":"+44 20 8948 5653",
    "sg:postcode":"TW10 6SE",
    "sg:province":"Greater London",
    "sg:tags":[
        "surveyor",
        "quantity"
    ],
    "wof:name":"Barrell & Barrell",
    "wof:placetype":"venue"
},
  "geometry": {"coordinates":[-0.303565,51.459293],"type":"Point"}
}