{
  "type": "Feature",
  "properties": {
    "iso:country":"GB",
    "sg:address":"Shields Road",
    "sg:city":"Glasgow",
    "sg:classifiers":[
        {
            "category":"Autos & Motor Vehicles",
            "subcategory":"Automobile Sales",
            "type":"Retail Goods"
        }
    ],
    "sg:phone":"+44 141 429 1616",
    "sg:postcode":"G41 1PA",
    "sg:province":"Glasgow City",
    "sg:tags":[
        "car"
    ],
    "wof:name":"Murray Chrysler & Jeep",
    "wof:placetype":"venue"
},
  "geometry": {"coordinates":[-4.2752590179,55.8455848694],"type":"Point"}
}