{
  "type": "Feature",
  "properties": {
    "iso:country":"GB",
    "sg:address":"54 Norfolk Road, Long Eaton",
    "sg:city":"Nottingham",
    "sg:classifiers":[
        {
            "category":"Retail",
            "subcategory":"Repair Shop",
            "type":"Services"
        }
    ],
    "sg:phone":"+44 115 972 4159",
    "sg:postcode":"NG10 2BL",
    "sg:province":"Derbyshire",
    "sg:tags":[
        "television",
        "good",
        "video",
        "servicing",
        "maintenance",
        "radio"
    ],
    "wof:name":"Phoenix TV's",
    "wof:placetype":"venue"
},
  "geometry": {"coordinates":[-1.26435,52.902782],"type":"Point"}
}