{
  "type": "Feature",
  "properties": {
    "iso:country":"GB",
    "sg:address":"Fowler Road, Cove",
    "sg:city":"Farnborough",
    "sg:classifiers":[
        {
            "category":"Education",
            "subcategory":"School",
            "type":"Public Place"
        }
    ],
    "sg:phone":"+44 1252 541786",
    "sg:postcode":"GU14 0BW",
    "sg:province":"Hampshire",
    "sg:tags":[
        "local",
        "authority"
    ],
    "wof:name":"Tower Hill County Primary School",
    "wof:placetype":"venue"
},
  "geometry": {"coordinates":[-0.770639,51.288158],"type":"Point"}
}