{
  "type": "Feature",
  "properties": {
    "addr:full":"49 King Street Great Yarmouth Norfolk NR30 2PW",
    "addr:housenumber":"49",
    "addr:postcode":"nr30 2pw",
    "addr:street":"King Street",
    "iso:country":"GB",
    "sg:address":"49 King Street",
    "sg:city":"Great Yarmouth",
    "sg:classifiers":[
        {
            "category":"Shopping",
            "subcategory":"Pets & Pet Supplies",
            "type":"Retail Goods"
        }
    ],
    "sg:postcode":"NR30 2PW",
    "sg:province":"Norfolk",
    "wof:name":"Scales & Tales",
    "wof:placetype":"venue"
},
  "geometry": {"coordinates":[1.729972,52.603531],"type":"Point"}
}