{
  "type": "Feature",
  "properties": {
    "iso:country":"GB",
    "sg:address":"Glenloy St",
    "sg:city":"Fort William",
    "sg:classifiers":[
        {
            "category":"Professional",
            "subcategory":"Employment Agencies",
            "type":"Services"
        }
    ],
    "sg:phone":"+44 1397 705771",
    "sg:postcode":"PH33 7DB",
    "sg:province":"Highland",
    "sg:tags":[
        "consultant"
    ],
    "wof:name":"Programme Centre",
    "wof:placetype":"venue"
},
  "geometry": {"coordinates":[-5.104244,56.838535],"type":"Point"}
}