{
  "type": "Feature",
  "properties": {
    "iso:country":"GB",
    "sg:address":"72-82 Fratton Rd",
    "sg:city":"Portsmouth",
    "sg:classifiers":[
        {
            "category":"Shopping",
            "subcategory":"Used Merchandise",
            "type":"Retail Goods"
        }
    ],
    "sg:phone":"+44 23 9273 7737",
    "sg:postcode":"PO1 5BZ",
    "sg:province":"Hampshire",
    "sg:tags":[
        "shop",
        "second-hand"
    ],
    "wof:name":"Fratton Bridge Furniture",
    "wof:placetype":"venue"
},
  "geometry": {"coordinates":[-1.0767409801,50.7982673645],"type":"Point"}
}