{
  "type": "Feature",
  "properties": {
    "addr:full":"3 Vale Road, Ashvale Aldershot Hampshire GU12 5HH",
    "addr:housenumber":"3",
    "addr:postcode":"gu12 5hh",
    "addr:street":"Vale Road Ashvale",
    "iso:country":"GB",
    "sg:address":"3 Vale Road, Ashvale",
    "sg:city":"Aldershot",
    "sg:classifiers":[
        {
            "category":"Building & Trades",
            "subcategory":"Plumbing",
            "type":"Services"
        }
    ],
    "sg:phone":"+44 1252 311259",
    "sg:postcode":"GU12 5HH",
    "sg:province":"Hampshire",
    "sg:tags":[
        "filtration",
        "system"
    ],
    "wof:name":"A T Systems",
    "wof:placetype":"venue"
},
  "geometry": {"coordinates":[-0.7215269804,51.2571525574],"type":"Point"}
}