{
  "type": "Feature",
  "properties": {
    "addr:full":"Unit 1 Court House Farm, Marsh La Bristol Somerset BS20 0NE",
    "addr:housenumber":"unit 1 court",
    "addr:postcode":"bs20 0ne",
    "addr:street":"Marsh La Bristol",
    "iso:country":"GB",
    "sg:address":"Unit 1 Court House Farm, Marsh La",
    "sg:city":"Bristol",
    "sg:classifiers":[
        {
            "category":"Manufacturing",
            "subcategory":"Metals",
            "type":"Manufacturing & Wholesale Goods"
        }
    ],
    "sg:phone":"+44 1275 371370",
    "sg:postcode":"BS20 0NE",
    "sg:province":"Somerset",
    "sg:tags":[
        "steel",
        "stockholder"
    ],
    "wof:name":"Chivers McAllister (Alloys) Ltd",
    "wof:placetype":"venue"
},
  "geometry": {"coordinates":[-2.706399,51.482159],"type":"Point"}
}