{
  "type": "Feature",
  "properties": {
    "addr:full":"87 Bruce Avenue Hornchurch Essex RM12 4HZ",
    "addr:housenumber":"87",
    "addr:postcode":"rm12 4hz",
    "addr:street":"Bruce Avenue",
    "iso:country":"GB",
    "sg:address":"87 Bruce Avenue",
    "sg:city":"Hornchurch",
    "sg:classifiers":[
        {
            "category":"Building & Trades",
            "subcategory":"Construction",
            "type":"Services"
        }
    ],
    "sg:phone":"+44 1708 444834",
    "sg:postcode":"RM12 4HZ",
    "sg:province":"Essex",
    "sg:tags":[
        "roofing"
    ],
    "wof:name":"Linnen Roofing Contractors",
    "wof:placetype":"venue"
},
  "geometry": {"coordinates":[0.215447,51.560707],"type":"Point"}
}