{
  "type": "Feature",
  "properties": {
    "addr:full":"33 Salisbury Avenue Barking Essex IG11 9XQ",
    "addr:housenumber":"33",
    "addr:postcode":"ig11 9xq",
    "addr:street":"Salisbury Avenue",
    "iso:country":"GB",
    "sg:address":"33 Salisbury Avenue",
    "sg:city":"Barking",
    "sg:classifiers":[
        {
            "category":"Professional",
            "subcategory":"Management & Consulting",
            "type":"Services"
        }
    ],
    "sg:postcode":"IG11 9XQ",
    "sg:province":"Essex",
    "sg:tags":[
        "consultant",
        "business"
    ],
    "wof:name":"Wordsley Ltd",
    "wof:placetype":"venue"
},
  "geometry": {"coordinates":[0.0836929977,51.5387878418],"type":"Point"}
}