{
  "type": "Feature",
  "properties": {
    "iso:country":"GB",
    "sg:address":"Battye Street, Laisterdyke",
    "sg:city":"Bradford",
    "sg:classifiers":[
        {
            "category":"Professional",
            "subcategory":"Printing & Photocopies",
            "type":"Services"
        }
    ],
    "sg:phone":"+44 1274 269300",
    "sg:postcode":"BD4 8AG",
    "sg:province":"West Yorkshire",
    "sg:tags":[
        "printer"
    ],
    "wof:name":"Smiths Colour Printers Ltd.",
    "wof:placetype":"venue"
},
  "geometry": {"coordinates":[-1.718969,53.791706],"type":"Point"}
}