{
  "type": "Feature",
  "properties": {
    "addr:full":"223 The Broadway Broadstone Dorset BH18 8DN",
    "addr:housenumber":"223",
    "addr:postcode":"bh18 8dn",
    "addr:street":"The Broadway",
    "iso:country":"GB",
    "sg:address":"223 The Broadway",
    "sg:city":"Broadstone",
    "sg:classifiers":[
        {
            "category":"Professional",
            "type":"Services"
        }
    ],
    "sg:postcode":"BH18 8DN",
    "sg:province":"Dorset",
    "sg:tags":[
        "caterer"
    ],
    "wof:name":"Mollies",
    "wof:placetype":"venue"
},
  "geometry": {"coordinates":[-1.9968789816,50.7625198364],"type":"Point"}
}