{
  "type": "Feature",
  "properties": {
    "iso:country":"GB",
    "sg:address":"Southover Grange, Southover High St",
    "sg:city":"Lewes",
    "sg:classifiers":[
        {
            "category":"Government",
            "subcategory":"Office",
            "type":"Public Place"
        }
    ],
    "sg:phone":"+44 1273 475589",
    "sg:postcode":"BN7 1TP",
    "sg:province":"East Sussex",
    "sg:tags":[
        "local"
    ],
    "wof:name":"Registration of Births Deaths & Marriages",
    "wof:placetype":"venue"
},
  "geometry": {"coordinates":[0.0109,50.871651],"type":"Point"}
}