{
  "type": "Feature",
  "properties": {
    "iso:country":"GB",
    "sg:address":"21 London Rd",
    "sg:city":"Morden",
    "sg:classifiers":[
        {
            "category":"Shopping",
            "subcategory":"Clothing, Apparel, & Fashions",
            "type":"Retail Goods"
        }
    ],
    "sg:phone":"+44 20 8640 0922",
    "sg:postcode":"SM4 5HT",
    "sg:province":"Surrey",
    "sg:tags":[
        "shop"
    ],
    "wof:name":"M & M Fashions",
    "wof:placetype":"venue"
},
  "geometry": {"coordinates":[-0.1928129941,51.4027862549],"type":"Point"}
}