{
  "type": "Feature",
  "properties": {
    "iso:country":"GB",
    "sg:address":"66 Station Road",
    "sg:city":"Ashington",
    "sg:classifiers":[
        {
            "category":"Shopping",
            "subcategory":"Jewelry",
            "type":"Retail Goods"
        },
        {
            "category":"Shopping",
            "subcategory":"Comic Books",
            "type":"Retail Goods"
        }
    ],
    "sg:phone":"+44 1670 812162",
    "sg:postcode":"NE63 8RN",
    "sg:province":"Northumberland",
    "sg:tags":[
        "jeweller",
        "sale",
        "jewellery"
    ],
    "wof:name":"Northern Jewellers",
    "wof:placetype":"venue"
},
  "geometry": {"coordinates":[-1.575044,55.183311],"type":"Point"}
}