{
  "type": "Feature",
  "properties": {
    "addr:full":"Unit 4 Cross St Wigan Lancashire WN3 4BQ",
    "addr:housenumber":"unit 4",
    "addr:postcode":"wn3 4bq",
    "addr:street":"Cross St",
    "iso:country":"GB",
    "sg:address":"Unit 4 Cross St",
    "sg:city":"Wigan",
    "sg:classifiers":[
        {
            "category":"Deli",
            "type":"Food & Drink"
        }
    ],
    "sg:phone":"+44 1942 235662",
    "sg:postcode":"WN3 4BQ",
    "sg:province":"Lancashire",
    "sg:tags":[
        "delivery",
        "sandwich"
    ],
    "wof:name":"Top Trough Food Services The",
    "wof:placetype":"venue"
},
  "geometry": {"coordinates":[-2.633554,53.540604],"type":"Point"}
}