{
  "type": "Feature",
  "properties": {
    "addr:full":"1 Archbold Terrace, Jesmond Newcastle-upon-tyne Tyne and Wear NE2 1DB",
    "addr:housenumber":"1",
    "addr:postcode":"ne2 1db",
    "addr:street":"Archbold Terrace",
    "iso:country":"GB",
    "sg:address":"1 Archbold Terrace, Jesmond",
    "sg:city":"Newcastle-upon-tyne",
    "sg:classifiers":[
        {
            "category":"Social Services",
            "subcategory":"Retirement Home",
            "type":"Services"
        }
    ],
    "sg:phone":"+44 191 212 0687",
    "sg:postcode":"NE2 1DB",
    "sg:province":"Tyne and Wear",
    "sg:tags":[
        "residential",
        "care"
    ],
    "wof:name":"Care Solutions Ltd.",
    "wof:placetype":"venue"
},
  "geometry": {"coordinates":[-1.60566,54.981468],"type":"Point"}
}