{
  "type": "Feature",
  "properties": {
    "iso:country":"GB",
    "sg:address":"Andrew Road, Eynesbury, St Neots",
    "sg:city":"Huntingdon",
    "sg:classifiers":[
        {
            "category":"Education",
            "subcategory":"School",
            "type":"Public Place"
        },
        {
            "category":"Government",
            "subcategory":"Office",
            "type":"Public Place"
        }
    ],
    "sg:phone":"+44 1480 375270",
    "sg:postcode":"PE19 2QE",
    "sg:province":"Bedfordshire",
    "sg:tags":[
        "local",
        "authority"
    ],
    "wof:name":"Middlefield Community Primary School",
    "wof:placetype":"venue"
},
  "geometry": {"coordinates":[-0.262951,52.214836],"type":"Point"}
}