{
  "type": "Feature",
  "properties": {
    "addr:full":"Hurst Street Birmingham West Midlands B5 4TB",
    "addr:postcode":"b5 4tb",
    "addr:street":"Hurst Street",
    "iso:country":"GB",
    "sg:address":"Hurst Street",
    "sg:city":"Birmingham",
    "sg:classifiers":[
        {
            "category":"Arts & Performance",
            "subcategory":"Theater",
            "type":"Entertainment"
        }
    ],
    "sg:phone":"+44 870 730 5555",
    "sg:postcode":"B5 4TB",
    "sg:province":"West Midlands",
    "sg:tags":[
        "hall",
        "theatre",
        "concert"
    ],
    "wof:name":"Birmingham Hippodrome Ltd.",
    "wof:placetype":"venue"
},
  "geometry": {"coordinates":[-1.898236,52.475323],"type":"Point"}
}