{
  "type": "Feature",
  "properties": {
    "iso:country":"GB",
    "sg:address":"The New Granary, Station Road, Newport",
    "sg:city":"Saffron Walden",
    "sg:classifiers":[
        {
            "category":"Communications",
            "type":"Services"
        }
    ],
    "sg:phone":"+44 1799 542620",
    "sg:postcode":"CB11 3PL",
    "sg:province":"Essex",
    "sg:tags":[
        "audio-visual"
    ],
    "wof:name":"Brainwave",
    "wof:placetype":"venue"
},
  "geometry": {"coordinates":[0.20879,52.005871],"type":"Point"}
}