{
  "type": "Feature",
  "properties": {
    "addr:full":"78 Craigiebuckler Avenue Aberdeen Aberdeen City AB15 8SU",
    "addr:housenumber":"78",
    "addr:postcode":"ab15 8su",
    "addr:street":"Craigiebuckler Avenue",
    "iso:country":"GB",
    "sg:address":"78 Craigiebuckler Avenue",
    "sg:city":"Aberdeen",
    "sg:classifiers":[
        {
            "category":"Government",
            "subcategory":"Fire Station",
            "type":"Public Place"
        },
        {
            "category":"Building & Trades",
            "subcategory":"Equipment Rental",
            "type":"Services"
        }
    ],
    "sg:postcode":"AB15 8SU",
    "sg:province":"Aberdeen City",
    "sg:tags":[
        "security",
        "firefighting"
    ],
    "wof:name":"Aberdeen Fire Protection Co.",
    "wof:placetype":"venue"
},
  "geometry": {"coordinates":[-2.162733,57.136478],"type":"Point"}
}