{
  "type": "Feature",
  "properties": {
    "addr:full":"Creda Cottage, Pleck Sturminster Newton Dorset DT10 2EF",
    "addr:postcode":"dt10 2ef",
    "addr:street":"Pleck",
    "iso:country":"GB",
    "sg:address":"Creda Cottage, Pleck",
    "sg:city":"Sturminster Newton",
    "sg:classifiers":[
        {
            "category":"Building & Trades",
            "subcategory":"Landscaping Services",
            "type":"Services"
        }
    ],
    "sg:phone":"+44 1258 817014",
    "sg:postcode":"DT10 2EF",
    "sg:province":"Dorset",
    "sg:tags":[
        "landscape",
        "contractor"
    ],
    "wof:name":"P J Courage",
    "wof:placetype":"venue"
},
  "geometry": {"coordinates":[-2.3128418922,50.9198112488],"type":"Point"}
}