{
  "type": "Feature",
  "properties": {
    "addr:full":"270 Uxbridge Road London Greater London W12 7JA",
    "addr:housenumber":"270",
    "addr:postcode":"w12 7ja",
    "addr:street":"Uxbridge Road",
    "iso:country":"GB",
    "sg:address":"270 Uxbridge Road",
    "sg:city":"London",
    "sg:classifiers":[
        {
            "category":"Restaurant",
            "type":"Food & Drink"
        }
    ],
    "sg:phone":"+44 20 8743 5500",
    "sg:postcode":"W12 7JA",
    "sg:province":"Greater London",
    "wof:name":"Gioia Mia",
    "wof:placetype":"venue"
},
  "geometry": {"coordinates":[-0.229786,51.506203],"type":"Point"}
}