{
  "type": "Feature",
  "properties": {
    "addr:full":"9 Clinton Terrace, Manor Lane Sutton Surrey SM1 4BS",
    "addr:housenumber":"9",
    "addr:postcode":"sm1 4bs",
    "addr:street":"Clinton Terrace Manor Lane",
    "iso:country":"GB",
    "sg:address":"9 Clinton Terrace, Manor Lane",
    "sg:city":"Sutton",
    "sg:classifiers":[
        {
            "category":"Shopping",
            "subcategory":"Party Supplies",
            "type":"Retail Goods"
        }
    ],
    "sg:phone":"+44 20 8642 6855",
    "sg:postcode":"SM1 4BS",
    "sg:province":"Surrey",
    "sg:tags":[
        "inflatables",
        "bouncy",
        "castle"
    ],
    "wof:name":"Acrobounce Bouncy Castles",
    "wof:placetype":"venue"
},
  "geometry": {"coordinates":[-0.1975580007,51.3611907959],"type":"Point"}
}