{
  "type": "Feature",
  "properties": {
    "iso:country":"GB",
    "sg:address":"Town End",
    "sg:city":"Huddersfield",
    "sg:classifiers":[
        {
            "category":"Professional",
            "subcategory":"Printing & Photocopies",
            "type":"Services"
        }
    ],
    "sg:phone":"+44 1484 653228",
    "sg:postcode":"HD7 4QQ",
    "sg:province":"West Yorkshire",
    "sg:tags":[
        "printer"
    ],
    "wof:name":"B T Printing",
    "wof:placetype":"venue"
},
  "geometry": {"coordinates":[-1.8559930325,53.6398887634],"type":"Point"}
}