{
  "type": "Feature",
  "properties": {
    "addr:full":"2 Old Mill Lane Barnsley South Yorkshire S70 2LA",
    "addr:housenumber":"2",
    "addr:postcode":"s70 2la",
    "addr:street":"Old Mill Lane;Yorkshire",
    "iso:country":"GB",
    "sg:address":"2 Old Mill Lane",
    "sg:city":"Barnsley",
    "sg:classifiers":[
        {
            "category":"Professional",
            "subcategory":"Art Services",
            "type":"Services"
        }
    ],
    "sg:phone":"+44 1226 281915",
    "sg:postcode":"S70 2LA",
    "sg:province":"South Yorkshire",
    "sg:tags":[
        "photographer"
    ],
    "wof:name":"Stan Plus Stan Two",
    "wof:placetype":"venue"
},
  "geometry": {"coordinates":[-1.483471036,53.5570487976],"type":"Point"}
}