{
  "type": "Feature",
  "properties": {
    "iso:country":"GB",
    "sg:address":"Lower Ground Floor 360-364 City Rd",
    "sg:city":"Clerkenwell",
    "sg:classifiers":[
        {
            "category":"Professional",
            "subcategory":"Printing & Photocopies",
            "type":"Services"
        }
    ],
    "sg:phone":"+44 20 7833 9406",
    "sg:postcode":"EC1V 2PY",
    "sg:province":"Greater London",
    "sg:tags":[
        "printer"
    ],
    "wof:name":"Thumbprint",
    "wof:placetype":"venue"
},
  "geometry": {"coordinates":[-0.10255,51.53104],"type":"Point"}
}