{
  "type": "Feature",
  "properties": {
    "addr:full":"7 Pavilion Row, Doncaster Road Scunthorpe Lincolnshire DN15 7RD",
    "addr:housenumber":"7",
    "addr:postcode":"dn15 7rd",
    "addr:street":"Pavilion Row Doncaster Road",
    "iso:country":"GB",
    "sg:address":"7 Pavilion Row, Doncaster Road",
    "sg:city":"Scunthorpe",
    "sg:classifiers":[
        {
            "category":"Fast Food",
            "type":"Food & Drink"
        }
    ],
    "sg:phone":"+44 1724 854356",
    "sg:postcode":"DN15 7RD",
    "sg:province":"Lincolnshire",
    "sg:tags":[
        "away",
        "take"
    ],
    "wof:name":"K F C",
    "wof:placetype":"venue"
},
  "geometry": {"coordinates":[-0.651811,53.586502],"type":"Point"}
}