{
  "type": "Feature",
  "properties": {
    "iso:country":"GB",
    "sg:address":"Kiln Bank Cres",
    "sg:city":"Market Drayton",
    "sg:classifiers":[
        {
            "category":"Building & Trades",
            "subcategory":"Construction",
            "type":"Services"
        }
    ],
    "sg:phone":"+44 1630 652207",
    "sg:postcode":"TF9 1LD",
    "sg:province":"Shropshire",
    "sg:tags":[
        "builder"
    ],
    "wof:name":"Bill Poole",
    "wof:placetype":"venue"
},
  "geometry": {"coordinates":[-2.489888,52.89938],"type":"Point"}
}