{
  "type": "Feature",
  "properties": {
    "iso:country":"GB",
    "sg:address":"140 High Street",
    "sg:city":"Invergordon",
    "sg:classifiers":[
        {
            "category":"Organizations",
            "subcategory":"Community Association",
            "type":"Services"
        },
        {
            "category":"Organizations",
            "subcategory":"Membership Organization",
            "type":"Services"
        }
    ],
    "sg:phone":"+44 1349 852381",
    "sg:postcode":"IV18 0AE",
    "sg:province":"Highland",
    "sg:tags":[
        "club",
        "social"
    ],
    "wof:name":"THE ROYAL BRITISH LEGION",
    "wof:placetype":"venue"
},
  "geometry": {"coordinates":[-4.161883,57.68898],"type":"Point"}
}