{
  "type": "Feature",
  "properties": {
    "iso:country":"GB",
    "sg:address":"2-2a Abington Street",
    "sg:city":"Northampton",
    "sg:classifiers":[
        {
            "category":"Banks & Credit Unions",
            "subcategory":"Financial Services",
            "type":"Services"
        }
    ],
    "sg:postcode":"NN1 2AJ",
    "sg:province":"Northamptonshire",
    "sg:tags":[
        "building",
        "society"
    ],
    "wof:name":"Skipton Building Society",
    "wof:placetype":"venue"
},
  "geometry": {"coordinates":[-0.892619,52.23859],"type":"Point"}
}