{
  "type": "Feature",
  "properties": {
    "addr:full":"Boundary Industrial Estate Stafford Road, Fordhouses Wolverhampton Staffordshire WV10 7ER",
    "addr:housenumber":"estate",
    "addr:postcode":"wv10 7er",
    "addr:street":"Boundary Industrial;Stafford Road Fordhouses",
    "iso:country":"GB",
    "sg:address":"Boundary Industrial Estate Stafford Road, Fordhouses",
    "sg:city":"Wolverhampton",
    "sg:classifiers":[
        {
            "category":"Manufacturing",
            "subcategory":"Metals",
            "type":"Manufacturing & Wholesale Goods"
        }
    ],
    "sg:phone":"+44 1902 398000",
    "sg:postcode":"WV10 7ER",
    "sg:province":"Staffordshire",
    "sg:tags":[
        "steel",
        "stockholder"
    ],
    "wof:name":"Bsd Strip Products Midlands",
    "wof:placetype":"venue"
},
  "geometry": {"coordinates":[-2.1260080338,52.6352806091],"type":"Point"}
}