{
  "type": "Feature",
  "properties": {
    "addr:full":"Housing Caretaker, Brittany Ho, Station Clo Fareham Hampshire PO17 5JY",
    "addr:postcode":"po17 5jy",
    "addr:street":"Caretaker;Clo",
    "iso:country":"GB",
    "sg:address":"Housing Caretaker, Brittany Ho, Station Clo",
    "sg:city":"Fareham",
    "sg:classifiers":[
        {
            "category":"Government",
            "subcategory":"Office",
            "type":"Public Place"
        }
    ],
    "sg:phone":"+44 1329 832341",
    "sg:postcode":"PO17 5JY",
    "sg:province":"Hampshire",
    "sg:tags":[
        "local"
    ],
    "wof:name":"Winchester City Council",
    "wof:placetype":"venue"
},
  "geometry": {"coordinates":[-1.18423,50.90163],"type":"Point"}
}