{
  "type": "Feature",
  "properties": {
    "addr:full":"13 Lyndhurst Terrace London Greater London NW3 5QA",
    "addr:housenumber":"13",
    "addr:postcode":"nw3 5qa",
    "addr:street":"Lyndhurst Terrace",
    "iso:country":"GB",
    "sg:address":"13 Lyndhurst Terrace",
    "sg:city":"London",
    "sg:classifiers":[
        {
            "category":"Education",
            "subcategory":"Special Training",
            "type":"Public Place"
        }
    ],
    "sg:phone":"+44 20 7794 8111",
    "sg:postcode":"NW3 5QA",
    "sg:province":"Greater London",
    "sg:tags":[
        "school",
        "language"
    ],
    "sg:website":"http://www.lsi.edu.co.uk",
    "wof:name":"Language Studies International Ltd.",
    "wof:placetype":"venue"
},
  "geometry": {"coordinates":[-0.174846,51.552711],"type":"Point"}
}