{
  "type": "Feature",
  "properties": {
    "addr:full":"4 High Street, Ruabon Wrexham Wrexham LL14 6NH",
    "addr:housenumber":"4",
    "addr:postcode":"ll14 6nh",
    "addr:street":"High Street",
    "iso:country":"GB",
    "sg:address":"4 High Street, Ruabon",
    "sg:city":"Wrexham",
    "sg:classifiers":[
        {
            "category":"Food & Beverages",
            "subcategory":"Meat & Fish",
            "type":"Retail Goods"
        }
    ],
    "sg:postcode":"LL14 6NH",
    "sg:province":"Wrexham",
    "sg:tags":[
        "butcher"
    ],
    "wof:name":"Village Butchers",
    "wof:placetype":"venue"
},
  "geometry": {"coordinates":[-3.039158,52.987732],"type":"Point"}
}