{
  "type": "Feature",
  "properties": {
    "addr:full":"34 Aplins Close Harpenden Hertfordshire AL5 2QB",
    "addr:housenumber":"34",
    "addr:postcode":"al5 2qb",
    "addr:street":"Aplins Close",
    "iso:country":"GB",
    "sg:address":"34 Aplins Close",
    "sg:city":"Harpenden",
    "sg:classifiers":[
        {
            "category":"Professional",
            "subcategory":"Computer Services",
            "type":"Services"
        }
    ],
    "sg:phone":"+44 1582 769382",
    "sg:postcode":"AL5 2QB",
    "sg:province":"Hertfordshire",
    "sg:tags":[
        "consultant"
    ],
    "wof:name":"Newland Systems Ltd.",
    "wof:placetype":"venue"
},
  "geometry": {"coordinates":[-0.362083,51.819908],"type":"Point"}
}