{
  "type": "Feature",
  "properties": {
    "iso:country":"GB",
    "sg:address":"The Barn, Mortimers Lane, Foxton",
    "sg:city":"Cambridge",
    "sg:classifiers":[
        {
            "category":"Manufacturing",
            "subcategory":"Wood Products",
            "type":"Manufacturing & Wholesale Goods"
        }
    ],
    "sg:phone":"+44 1223 870817",
    "sg:postcode":"CB2 6RR",
    "sg:province":"Cambridgeshire",
    "wof:name":"Cambridge I Q Ltd.",
    "wof:placetype":"venue"
},
  "geometry": {"coordinates":[0.0610570014,52.1158599854],"type":"Point"}
}