{
  "type": "Feature",
  "properties": {
    "addr:full":"39 Yew Tree Way, Churchdown Gloucester Gloucestershire GL3 2SY",
    "addr:housenumber":"39",
    "addr:postcode":"gl3 2sy",
    "addr:street":"Yew Tree Way",
    "iso:country":"GB",
    "sg:address":"39 Yew Tree Way, Churchdown",
    "sg:city":"Gloucester",
    "sg:classifiers":[
        {
            "category":"Building & Trades",
            "subcategory":"Plumbing",
            "type":"Services"
        }
    ],
    "sg:postcode":"GL3 2SY",
    "sg:province":"Gloucestershire",
    "sg:tags":[
        "heating"
    ],
    "wof:name":"Plumbing Services",
    "wof:placetype":"venue"
},
  "geometry": {"coordinates":[-2.1905319691,51.8824424744],"type":"Point"}
}