{
  "type": "Feature",
  "properties": {
    "iso:country":"GB",
    "sg:address":"10 Beauty Bank",
    "sg:city":"Cradley Heath",
    "sg:classifiers":[
        {
            "category":"Real Estate",
            "subcategory":"Architect",
            "type":"Services"
        }
    ],
    "sg:postcode":"B64 7HY",
    "sg:province":"West Midlands",
    "sg:tags":[
        "technologist",
        "architectural"
    ],
    "wof:name":"Architectural Design Services",
    "wof:placetype":"venue"
},
  "geometry": {"coordinates":[-2.05844,52.471123],"type":"Point"}
}