{
  "type": "Feature",
  "properties": {
    "iso:country":"GB",
    "sg:address":"Po Box 620",
    "sg:city":"Gillingham",
    "sg:classifiers":[
        {
            "category":"Professional",
            "subcategory":"Management & Consulting",
            "type":"Services"
        }
    ],
    "sg:phone":"+44 1634 262226",
    "sg:postcode":"ME8 6JN",
    "sg:province":"Kent",
    "sg:tags":[
        "environmental",
        "consultant"
    ],
    "wof:name":"Davey Enviromental Consultants",
    "wof:placetype":"venue"
},
  "geometry": {"coordinates":[0.58223,51.374401],"type":"Point"}
}