{
  "type": "Feature",
  "properties": {
    "iso:country":"GB",
    "sg:address":"Cox House, Seymer Road",
    "sg:city":"Romford",
    "sg:classifiers":[
        {
            "category":"Wholesale",
            "subcategory":"Groceries",
            "type":"Manufacturing & Wholesale Goods"
        }
    ],
    "sg:phone":"+44 1708 764143",
    "sg:postcode":"RM1 4LA",
    "sg:province":"Essex",
    "sg:tags":[
        "food",
        "supplier",
        "drink"
    ],
    "wof:name":"Wendys Sandwiches",
    "wof:placetype":"venue"
},
  "geometry": {"coordinates":[0.176232,51.585899],"type":"Point"}
}