{
  "type": "Feature",
  "properties": {
    "iso:country":"GB",
    "sg:address":"Estate Road 1, South Humberside Indust Est",
    "sg:city":"Grimsby",
    "sg:classifiers":[
        {
            "category":"Professional",
            "subcategory":"Detective & Security Services",
            "type":"Services"
        }
    ],
    "sg:phone":"+44 1472 359032",
    "sg:postcode":"DN31 2TB",
    "sg:province":"Lincolnshire",
    "wof:name":"Securicor Cash Services",
    "wof:placetype":"venue"
},
  "geometry": {"coordinates":[-0.116379,53.580593],"type":"Point"}
}