{
  "type": "Feature",
  "properties": {
    "iso:country":"GB",
    "sg:address":"136 Westwood Road",
    "sg:city":"Broadstairs",
    "sg:classifiers":[
        {
            "category":"Shopping",
            "subcategory":"Crafts & Fabrics",
            "type":"Retail Goods"
        }
    ],
    "sg:postcode":"CT10 2PB",
    "sg:province":"Kent",
    "sg:tags":[
        "ceramic"
    ],
    "wof:name":"Studio Valerie",
    "wof:placetype":"venue"
},
  "geometry": {"coordinates":[1.401266,51.360855],"type":"Point"}
}