{
  "type": "Feature",
  "properties": {
    "addr:full":"12 Wheeler Avenue, Eastwood Nottingham Derbyshire NG16 2AN",
    "addr:housenumber":"12",
    "addr:postcode":"ng16 2an",
    "addr:street":"Wheeler Avenue",
    "iso:country":"GB",
    "sg:address":"12 Wheeler Avenue, Eastwood",
    "sg:city":"Nottingham",
    "sg:classifiers":[
        {
            "category":"Professional",
            "subcategory":"Accounting & Tax Preparation",
            "type":"Services"
        }
    ],
    "sg:postcode":"NG16 2AN",
    "sg:province":"Derbyshire",
    "sg:tags":[
        "accountant"
    ],
    "wof:name":"Allan Hill Business Services",
    "wof:placetype":"venue"
},
  "geometry": {"coordinates":[-1.2879389524,53.0116615295],"type":"Point"}
}