{
  "type": "Feature",
  "properties": {
    "addr:full":"4 Pound Place Aberystwyth Ceredigion SY23 1LX",
    "addr:housenumber":"4",
    "addr:postcode":"sy23 1lx",
    "addr:street":"Pound Place",
    "iso:country":"GB",
    "sg:address":"4 Pound Place",
    "sg:city":"Aberystwyth",
    "sg:classifiers":[
        {
            "category":"Organizations",
            "subcategory":"Non-profit Organization",
            "type":"Services"
        }
    ],
    "sg:phone":"+44 1970 612748",
    "sg:postcode":"SY23 1LX",
    "sg:province":"Ceredigion",
    "sg:tags":[
        "organisation",
        "voluntary",
        "charity"
    ],
    "wof:name":"Welsh Womens Aid",
    "wof:placetype":"venue"
},
  "geometry": {"coordinates":[-4.078164,52.415874],"type":"Point"}
}