{
  "type": "Feature",
  "properties": {
    "iso:country":"GB",
    "sg:address":"Libanus",
    "sg:city":"Brecon",
    "sg:classifiers":[
        {
            "category":"Shopping",
            "subcategory":"Hobbies, Toys, & Games",
            "type":"Retail Goods"
        },
        {
            "category":"Recreation",
            "type":"Entertainment"
        }
    ],
    "sg:phone":"+44 1874 623598",
    "sg:postcode":"LD3 8NL",
    "sg:province":"Powys",
    "sg:tags":[
        "equipment",
        "outdoor",
        "pursuit",
        "leisure",
        "organiser"
    ],
    "wof:name":"Storey Arms Outdoor Education Centre",
    "wof:placetype":"venue"
},
  "geometry": {"coordinates":[-3.463616,51.923943],"type":"Point"}
}