{
  "type": "Feature",
  "properties": {
    "iso:country":"GB",
    "sg:address":"45 High St",
    "sg:city":"Kidderminster",
    "sg:classifiers":[
        {
            "category":"Shopping",
            "subcategory":"Department Store",
            "type":"Retail Goods"
        }
    ],
    "sg:phone":"+44 1299 270393",
    "sg:postcode":"DY14 8DQ",
    "sg:province":"Shropshire",
    "wof:name":"S T Knowles",
    "wof:placetype":"venue"
},
  "geometry": {"coordinates":[-2.483347,52.378662],"type":"Point"}
}