{
  "type": "Feature",
  "properties": {
    "addr:full":"Council Offices, Church Road, Rainford St Helens Lancashire WA11 8HB",
    "addr:postcode":"wa11 8hb",
    "addr:street":"Church Road Rainford",
    "iso:country":"GB",
    "sg:address":"Council Offices, Church Road, Rainford",
    "sg:city":"St Helens",
    "sg:classifiers":[
        {
            "category":"Government",
            "subcategory":"City Hall",
            "type":"Public Place"
        }
    ],
    "sg:phone":"+44 1744 884709",
    "sg:postcode":"WA11 8HB",
    "sg:province":"Lancashire",
    "wof:name":"Rainford Parish Council",
    "wof:placetype":"venue"
},
  "geometry": {"coordinates":[-2.788924,53.502769],"type":"Point"}
}