{
  "type": "Feature",
  "properties": {
    "iso:country":"GB",
    "sg:address":"Monks Road",
    "sg:city":"Lincoln",
    "sg:classifiers":[
        {
            "category":"Education",
            "subcategory":"School",
            "type":"Public Place"
        }
    ],
    "sg:phone":"+44 1522 544010",
    "sg:postcode":"LN2 5HG",
    "sg:province":"Lincolnshire",
    "sg:tags":[
        "local",
        "authority"
    ],
    "wof:name":"Health & Beauty Clinic",
    "wof:placetype":"venue"
},
  "geometry": {"coordinates":[-0.5076389909,53.2310791016],"type":"Point"}
}