{
  "type": "Feature",
  "properties": {
    "addr:full":"84 Station Road, Arksey Doncaster South Yorkshire DN5 0SD",
    "addr:housenumber":"84",
    "addr:postcode":"dn5 0sd",
    "addr:street":"Station Road",
    "iso:country":"GB",
    "sg:address":"84 Station Road, Arksey",
    "sg:city":"Doncaster",
    "sg:classifiers":[
        {
            "category":"Personal",
            "subcategory":"Beauty Salon",
            "type":"Services"
        }
    ],
    "sg:postcode":"DN5 0SD",
    "sg:province":"South Yorkshire",
    "sg:tags":[
        "unisex",
        "hairdresser"
    ],
    "wof:name":"Angela's Unisex Salon",
    "wof:placetype":"venue"
},
  "geometry": {"coordinates":[-1.1288429499,53.5540885925],"type":"Point"}
}