{
  "type": "Feature",
  "properties": {
    "iso:country":"GB",
    "sg:address":"2164a Coventry Road, Sheldon",
    "sg:city":"Birmingham",
    "sg:classifiers":[
        {
            "category":"Shopping",
            "subcategory":"Shoes",
            "type":"Retail Goods"
        }
    ],
    "sg:phone":"+44 121 743 0341",
    "sg:postcode":"B26 3JL",
    "sg:province":"West Midlands",
    "wof:name":"Minit (U K) Plc",
    "wof:placetype":"venue"
},
  "geometry": {"coordinates":[-1.783917,52.452312],"type":"Point"}
}