{
  "type": "Feature",
  "properties": {
    "addr:full":"110 Maison Dieu Rd Dover Kent CT16 1RT",
    "addr:housenumber":"110",
    "addr:postcode":"ct16 1rt",
    "addr:street":"Maison Dieu Rd",
    "iso:country":"GB",
    "sg:address":"110 Maison Dieu Rd",
    "sg:city":"Dover",
    "sg:classifiers":[
        {
            "category":"Professional",
            "subcategory":"Lawyer & Legal Services",
            "type":"Services"
        }
    ],
    "sg:phone":"+44 1304 206850",
    "sg:postcode":"CT16 1RT",
    "sg:province":"Kent",
    "sg:tags":[
        "solicitor"
    ],
    "wof:name":"J R Garner",
    "wof:placetype":"venue"
},
  "geometry": {"coordinates":[1.31554,51.127617],"type":"Point"}
}