{
  "type": "Feature",
  "properties": {
    "iso:country":"GB",
    "sg:address":"28 High Street",
    "sg:city":"Sheringham",
    "sg:classifiers":[
        {
            "category":"Restaurant",
            "type":"Food & Drink"
        },
        {
            "category":"Cafe",
            "type":"Food & Drink"
        }
    ],
    "sg:phone":"+44 1263 822078",
    "sg:postcode":"NR26 8JR",
    "sg:province":"Norfolk",
    "sg:tags":[
        "tea",
        "room"
    ],
    "wof:name":"Carol Long",
    "wof:placetype":"venue"
},
  "geometry": {"coordinates":[1.211729,52.944332],"type":"Point"}
}