{
  "type": "Feature",
  "properties": {
    "addr:full":"Clearway Court, 139-141 Croydon Road Caterham Surrey CR3 6PF",
    "addr:housenumber":"139-141",
    "addr:postcode":"cr3 6pf",
    "addr:street":"Clearway;Croydon Road",
    "iso:country":"GB",
    "sg:address":"Clearway Court, 139-141 Croydon Road",
    "sg:city":"Caterham",
    "sg:classifiers":[
        {
            "category":"Building & Trades",
            "subcategory":"Electrical",
            "type":"Services"
        }
    ],
    "sg:phone":"+44 1883 346573",
    "sg:postcode":"CR3 6PF",
    "sg:province":"Surrey",
    "sg:tags":[
        "lighting"
    ],
    "wof:name":"Melac Services Ltd.",
    "wof:placetype":"venue"
},
  "geometry": {"coordinates":[-0.078576,51.287022],"type":"Point"}
}