{
  "type": "Feature",
  "properties": {
    "addr:full":"Main Road, Boreham Chelmsford Essex CM3 3HE",
    "addr:postcode":"cm3 3he",
    "addr:street":"Main Road",
    "iso:country":"GB",
    "sg:address":"Main Road, Boreham",
    "sg:city":"Chelmsford",
    "sg:classifiers":[
        {
            "category":"Shopping",
            "subcategory":"Department Store",
            "type":"Retail Goods"
        }
    ],
    "sg:phone":"+44 1245 464544",
    "sg:postcode":"CM3 3HE",
    "sg:province":"Essex",
    "wof:name":"Shaun Bevan",
    "wof:placetype":"venue"
},
  "geometry": {"coordinates":[0.5607519746,51.7686805725],"type":"Point"}
}