{
  "type": "Feature",
  "properties": {
    "iso:country":"GB",
    "sg:address":"43 Lindfield Road, Ealing",
    "sg:city":"London",
    "sg:classifiers":[
        {
            "category":"Professional",
            "subcategory":"Computer Services",
            "type":"Services"
        }
    ],
    "sg:phone":"+44 20 8566 8659",
    "sg:postcode":"W5 1QS",
    "sg:province":"Greater London",
    "sg:tags":[
        "consultant"
    ],
    "wof:name":"Grasshopper Computers Limited",
    "wof:placetype":"venue"
},
  "geometry": {"coordinates":[-0.3130089939,51.5276527405],"type":"Point"}
}