{
  "type": "Feature",
  "properties": {
    "iso:country":"GB",
    "sg:address":"21 Leicester Road",
    "sg:city":"Lewes",
    "sg:classifiers":[
        {
            "category":"Professional",
            "subcategory":"Computer Services",
            "type":"Services"
        }
    ],
    "sg:postcode":"BN7 1SU",
    "sg:province":"East Sussex",
    "sg:tags":[
        "system",
        "software"
    ],
    "wof:name":"Icarus",
    "wof:placetype":"venue"
},
  "geometry": {"coordinates":[-0.002112,50.874626],"type":"Point"}
}