{
  "type": "Feature",
  "properties": {
    "iso:country":"GB",
    "sg:address":"35 Norwich Street",
    "sg:city":"Fakenham",
    "sg:classifiers":[
        {
            "category":"Shopping",
            "subcategory":"Mobile Phones",
            "type":"Retail Goods"
        },
        {
            "category":"Communications",
            "type":"Services"
        }
    ],
    "sg:phone":"+44 1328 856566",
    "sg:postcode":"NR21 9AF",
    "sg:province":"Norfolk",
    "sg:tags":[
        "supplier",
        "telecommunication"
    ],
    "wof:name":"MARTIN CORRIGAN DEVLIN",
    "wof:placetype":"venue"
},
  "geometry": {"coordinates":[0.8500139713,52.8303604126],"type":"Point"}
}