{
  "type": "Feature",
  "properties": {
    "addr:full":"44 Mill Street Kidderminster Staffordshire DY11 6XB",
    "addr:housenumber":"44",
    "addr:postcode":"dy11 6xb",
    "addr:street":"Mill Street",
    "iso:country":"GB",
    "sg:address":"44 Mill Street",
    "sg:city":"Kidderminster",
    "sg:classifiers":[
        {
            "category":"Autos & Motor Vehicles",
            "subcategory":"Fuel & Gas Station",
            "type":"Retail Goods"
        },
        {
            "category":"Home & Garden",
            "subcategory":"Hardware",
            "type":"Retail Goods"
        }
    ],
    "sg:phone":"+44 1562 865112",
    "sg:postcode":"DY11 6XB",
    "sg:province":"Staffordshire",
    "sg:tags":[
        "equipment",
        "heating",
        "aga",
        "cooker"
    ],
    "wof:name":"A G A Shop",
    "wof:placetype":"venue"
},
  "geometry": {"coordinates":[-2.253946,52.388954],"type":"Point"}
}