{
  "type": "Feature",
  "properties": {
    "addr:full":"Roundswell District Centre, Gratton Way, Roundswell Barnstaple Devon EX31 3NH",
    "addr:postcode":"ex31 3nh",
    "addr:street":"Gratton Way Roundswell",
    "iso:country":"GB",
    "sg:address":"Roundswell District Centre, Gratton Way, Roundswell",
    "sg:city":"Barnstaple",
    "sg:classifiers":[
        {
            "category":"Food & Beverages",
            "subcategory":"Supermarket",
            "type":"Retail Goods"
        }
    ],
    "sg:phone":"+44 1271 325498",
    "sg:postcode":"EX31 3NH",
    "sg:province":"Devon",
    "wof:name":"J Sainsbury",
    "wof:placetype":"venue"
},
  "geometry": {"coordinates":[-4.082881,51.064312],"type":"Point"}
}