{
  "type": "Feature",
  "properties": {
    "addr:full":"26-27 Shaftesbury Road Bath Somerset BA2 3LJ",
    "addr:housenumber":"26-27",
    "addr:postcode":"ba2 3lj",
    "addr:street":"Shaftesbury Road",
    "iso:country":"GB",
    "sg:address":"26-27 Shaftesbury Road",
    "sg:city":"Bath",
    "sg:classifiers":[
        {
            "category":"Shopping",
            "type":"Retail Goods"
        }
    ],
    "sg:phone":"+44 1225 447773",
    "sg:postcode":"BA2 3LJ",
    "sg:province":"Somerset",
    "sg:tags":[
        "part",
        "accessory"
    ],
    "wof:name":"Third Avenue Motor Parts",
    "wof:placetype":"venue"
},
  "geometry": {"coordinates":[-2.378166914,51.3763313293],"type":"Point"}
}