{
  "type": "Feature",
  "properties": {
    "addr:full":"115a Gilesgate Durham Durham DH1 1QG",
    "addr:housenumber":"115a",
    "addr:postcode":"dh1 1qg",
    "addr:street":"Gilesgate",
    "iso:country":"GB",
    "sg:address":"115a Gilesgate",
    "sg:city":"Durham",
    "sg:classifiers":[
        {
            "category":"Organizations",
            "subcategory":"Non-profit Organization",
            "type":"Services"
        }
    ],
    "sg:phone":"+44 191 383 9318",
    "sg:postcode":"DH1 1QG",
    "sg:province":"Durham",
    "sg:tags":[
        "organisation",
        "voluntary",
        "charity"
    ],
    "wof:name":"D I S C",
    "wof:placetype":"venue"
},
  "geometry": {"coordinates":[-1.5565420389,54.778968811],"type":"Point"}
}