{
  "type": "Feature",
  "properties": {
    "addr:full":"1 Barnes Wallis Court, Wellington Road, Cressex Business Park High Wycombe Buckinghamshire HP12 3PS",
    "addr:housenumber":"1",
    "addr:postcode":"hp12 3ps",
    "addr:street":"Barnes Wallis Court Wellington Road Cressex Business Park High",
    "iso:country":"GB",
    "sg:address":"1 Barnes Wallis Court, Wellington Road, Cressex Business Park",
    "sg:city":"High Wycombe",
    "sg:classifiers":[
        {
            "category":"Professional",
            "subcategory":"Business Services",
            "type":"Services"
        }
    ],
    "sg:phone":"+44 1494 511022",
    "sg:postcode":"HP12 3PS",
    "sg:province":"Buckinghamshire",
    "sg:tags":[
        "code",
        "bar"
    ],
    "wof:name":"A D C Bar Code Systems Ltd.",
    "wof:placetype":"venue"
},
  "geometry": {"coordinates":[-0.768216,51.618961],"type":"Point"}
}