{
  "type": "Feature",
  "properties": {
    "addr:full":"104 Beulah Rd Thornton Heath Surrey CR7 8JF",
    "addr:housenumber":"104",
    "addr:postcode":"cr7 8jf",
    "addr:street":"Beulah Rd",
    "iso:country":"GB",
    "sg:address":"104 Beulah Rd",
    "sg:city":"Thornton Heath",
    "sg:classifiers":[
        {
            "category":"Manufacturing",
            "subcategory":"Tools & Machinery",
            "type":"Manufacturing & Wholesale Goods"
        }
    ],
    "sg:postcode":"CR7 8JF",
    "sg:province":"Surrey",
    "sg:tags":[
        "power"
    ],
    "wof:name":"S T F (Construction Supplies) Ltd",
    "wof:placetype":"venue"
},
  "geometry": {"coordinates":[-0.099574998,51.4045143127],"type":"Point"}
}