{
  "type": "Feature",
  "properties": {
    "iso:country":"GB",
    "sg:address":"195 St Helens Road",
    "sg:city":"Bolton",
    "sg:classifiers":[
        {
            "category":"Manufacturing",
            "subcategory":"Signs",
            "type":"Manufacturing & Wholesale Goods"
        }
    ],
    "sg:phone":"+44 1204 657123",
    "sg:postcode":"BL3 3PY",
    "sg:province":"Lancashire",
    "sg:tags":[
        "nameplate"
    ],
    "wof:name":"North West Graphics",
    "wof:placetype":"venue"
},
  "geometry": {"coordinates":[-2.452316,53.562531],"type":"Point"}
}