{
  "type": "Feature",
  "properties": {
    "addr:full":"Central Station Tunbridge Wells Kent TN1 1BT",
    "addr:postcode":"tn1 1bt",
    "addr:street":"Tunbridge Wells",
    "iso:country":"GB",
    "sg:address":"Central Station",
    "sg:city":"Tunbridge Wells",
    "sg:classifiers":[
        {
            "category":"Building & Trades",
            "subcategory":"Construction",
            "type":"Services"
        }
    ],
    "sg:postcode":"TN1 1BT",
    "sg:province":"Kent",
    "sg:tags":[
        "management"
    ],
    "wof:name":"Contract Project Management Limited",
    "wof:placetype":"venue"
},
  "geometry": {"coordinates":[0.26355,51.133373],"type":"Point"}
}