{
  "type": "Feature",
  "properties": {
    "iso:country":"GB",
    "sg:address":"70-74 Plymstock Rd",
    "sg:city":"Plymouth",
    "sg:classifiers":[
        {
            "category":"Place Of Worship",
            "type":"Public Place"
        }
    ],
    "sg:phone":"+44 1752 401294",
    "sg:postcode":"PL9 7NX",
    "sg:province":"Devon",
    "wof:name":"Plymstock United Church",
    "wof:placetype":"venue"
},
  "geometry": {"coordinates":[-4.0997657776,50.3604774475],"type":"Point"}
}