{
  "type": "Feature",
  "properties": {
    "addr:full":"84 Birnam Rd Kirkcaldy Fife KY2 6NH",
    "addr:housenumber":"84",
    "addr:postcode":"ky2 6nh",
    "addr:street":"Birnam Rd",
    "iso:country":"GB",
    "sg:address":"84 Birnam Rd",
    "sg:city":"Kirkcaldy",
    "sg:classifiers":[
        {
            "category":"Food & Beverages",
            "subcategory":"Meat & Fish",
            "type":"Retail Goods"
        }
    ],
    "sg:phone":"+44 1592 266560",
    "sg:postcode":"KY2 6NH",
    "sg:province":"Fife",
    "sg:tags":[
        "chip"
    ],
    "wof:name":"Neptune's Larder",
    "wof:placetype":"venue"
},
  "geometry": {"coordinates":[-3.1930770874,56.1304855347],"type":"Point"}
}