{
  "type": "Feature",
  "properties": {
    "addr:full":"242 Blackwell Rd Sutton In Ashfield Nottinghamshire NG17 2RF",
    "addr:housenumber":"242",
    "addr:postcode":"ng17 2rf",
    "addr:street":"Blackwell Rd",
    "iso:country":"GB",
    "sg:address":"242 Blackwell Rd",
    "sg:city":"Sutton In Ashfield",
    "sg:classifiers":[
        {
            "category":"Transit Center",
            "subcategory":"Passenger",
            "type":"Transportation"
        }
    ],
    "sg:phone":"+44 1623 511552",
    "sg:postcode":"NG17 2RF",
    "sg:province":"Nottinghamshire",
    "sg:tags":[
        "boarding",
        "kennel",
        "catteries"
    ],
    "wof:name":"Border Cottage Kennels",
    "wof:placetype":"venue"
},
  "geometry": {"coordinates":[-1.3155070543,53.1260566711],"type":"Point"}
}