{
  "type": "Feature",
  "properties": {
    "addr:full":"Waites Farm, New Leake Boston Lincolnshire PE22 8JD",
    "addr:housenumber":"new leake",
    "addr:postcode":"pe22 8jd",
    "iso:country":"GB",
    "sg:address":"Waites Farm, New Leake",
    "sg:city":"Boston",
    "sg:classifiers":[
        {
            "category":"Farming",
            "subcategory":"Livestock Farm",
            "type":"Manufacturing & Wholesale Goods"
        }
    ],
    "sg:postcode":"PE22 8JD",
    "sg:province":"Lincolnshire",
    "sg:tags":[
        "others"
    ],
    "wof:name":"A J Horry",
    "wof:placetype":"venue"
},
  "geometry": {"coordinates":[0.078398,53.091511],"type":"Point"}
}