{
  "type": "Feature",
  "properties": {
    "addr:full":"46 Ninian Road Cardiff Cardiff CF23 5EH",
    "addr:housenumber":"46",
    "addr:postcode":"cf23 5eh",
    "addr:street":"Ninian Road",
    "iso:country":"GB",
    "sg:address":"46 Ninian Road",
    "sg:city":"Cardiff",
    "sg:classifiers":[
        {
            "category":"Social Services",
            "subcategory":"Adult Care",
            "type":"Services"
        },
        {
            "category":"Social Services",
            "subcategory":"Retirement Home",
            "type":"Services"
        }
    ],
    "sg:postcode":"CF23 5EH",
    "sg:province":"Cardiff",
    "sg:tags":[
        "help",
        "private"
    ],
    "wof:name":"Around the Clock Care",
    "wof:placetype":"venue"
},
  "geometry": {"coordinates":[-3.1687219143,51.4980659485],"type":"Point"}
}