{
  "type": "Feature",
  "properties": {
    "addr:full":"Unit 2 Frohock House, 22 Mill Road Cambridge Cambridgeshire CB1 3NF",
    "addr:housenumber":"unit 2 frohock house 22",
    "addr:postcode":"cb1 3nf",
    "addr:street":"Mill Road",
    "iso:country":"GB",
    "sg:address":"Unit 2 Frohock House, 22 Mill Road",
    "sg:city":"Cambridge",
    "sg:classifiers":[
        {
            "category":"Shopping",
            "subcategory":"Pharmacy",
            "type":"Retail Goods"
        }
    ],
    "sg:postcode":"CB1 3NF",
    "sg:province":"Cambridgeshire",
    "sg:tags":[
        "medicine",
        "therapy"
    ],
    "wof:name":"Hope Street Holistic Centre",
    "wof:placetype":"venue"
},
  "geometry": {"coordinates":[0.14202,52.198349],"type":"Point"}
}