{
  "type": "Feature",
  "properties": {
    "addr:full":"Main Street, Ratby Leicester Leicestershire LE6 0LL",
    "addr:postcode":"le6 0ll",
    "addr:street":"Main Street",
    "iso:country":"GB",
    "sg:address":"Main Street, Ratby",
    "sg:city":"Leicester",
    "sg:classifiers":[
        {
            "category":"Retail",
            "subcategory":"Auto Repair",
            "type":"Services"
        }
    ],
    "sg:phone":"+44 116 239 4966",
    "sg:postcode":"LE6 0LL",
    "sg:province":"Leicestershire",
    "sg:tags":[
        "modification",
        "garage"
    ],
    "wof:name":"The Service Garage",
    "wof:placetype":"venue"
},
  "geometry": {"coordinates":[-1.243679,52.650173],"type":"Point"}
}