{
  "type": "Feature",
  "properties": {
    "addr:full":"Mealhouse La Chorley Lancashire PR7 1DZ",
    "addr:postcode":"pr7 1dz",
    "iso:country":"GB",
    "sg:address":"Mealhouse La",
    "sg:city":"Chorley",
    "sg:classifiers":[
        {
            "category":"Bars & Pubs",
            "type":"Food & Drink"
        }
    ],
    "sg:phone":"+44 1257 262016",
    "sg:postcode":"PR7 1DZ",
    "sg:province":"Lancashire",
    "sg:tags":[
        "pubs",
        "inn"
    ],
    "wof:name":"White Hart The",
    "wof:placetype":"venue"
},
  "geometry": {"coordinates":[-2.6332828999,53.65417099],"type":"Point"}
}