{
  "type": "Feature",
  "properties": {
    "addr:full":"6 Ruby Gardens Nottingham Nottinghamshire NG17 7QH",
    "addr:housenumber":"6",
    "addr:postcode":"ng17 7qh",
    "addr:street":"Ruby Gardens",
    "iso:country":"GB",
    "sg:address":"6 Ruby Gardens",
    "sg:city":"Nottingham",
    "sg:classifiers":[
        {
            "category":"Building & Trades",
            "subcategory":"Plumbing",
            "type":"Services"
        }
    ],
    "sg:phone":"+44 1623 755259",
    "sg:postcode":"NG17 7QH",
    "sg:province":"Nottinghamshire",
    "sg:tags":[
        "heating"
    ],
    "wof:name":"J K D Builders",
    "wof:placetype":"venue"
},
  "geometry": {"coordinates":[-1.231408,53.09771],"type":"Point"}
}