{
  "type": "Feature",
  "properties": {
    "iso:country":"GB",
    "sg:address":"15 St Machar Drive",
    "sg:city":"Aberdeen",
    "sg:classifiers":[
        {
            "category":"Professional",
            "subcategory":"Printing & Photocopies",
            "type":"Services"
        }
    ],
    "sg:phone":"+44 1224 276222",
    "sg:postcode":"AB243YJ",
    "sg:province":"Aberdeen City",
    "sg:tags":[
        "plate",
        "lithographic",
        "maker"
    ],
    "wof:name":"Winters",
    "wof:placetype":"venue"
},
  "geometry": {"coordinates":[-2.1127378941,57.1674613953],"type":"Point"}
}