{
  "type": "Feature",
  "properties": {
    "iso:country":"GB",
    "sg:address":"67 Colney Road",
    "sg:city":"Dartford",
    "sg:classifiers":[
        {
            "category":"Building & Trades",
            "subcategory":"Construction",
            "type":"Services"
        }
    ],
    "sg:phone":"+44 1322 220341",
    "sg:postcode":"DA1 1TQ",
    "sg:province":"Kent",
    "sg:tags":[
        "dry",
        "plastering",
        "plasterers",
        "lining",
        "related",
        "screeders"
    ],
    "wof:name":"Craig Baker",
    "wof:placetype":"venue"
},
  "geometry": {"coordinates":[0.22896,51.444633],"type":"Point"}
}