{
  "type": "Feature",
  "properties": {
    "addr:full":"10 Blowers Wood Gro, Hempstead Gillingham Kent ME7 3RD",
    "addr:housenumber":"10",
    "addr:postcode":"me7 3rd",
    "addr:street":"Blowers Wood Gro",
    "iso:country":"GB",
    "sg:address":"10 Blowers Wood Gro, Hempstead",
    "sg:city":"Gillingham",
    "sg:classifiers":[
        {
            "category":"Building & Trades",
            "subcategory":"Construction",
            "type":"Services"
        }
    ],
    "sg:phone":"+44 1634 363322",
    "sg:postcode":"ME7 3RD",
    "sg:province":"Kent",
    "sg:tags":[
        "joiner",
        "carpenter"
    ],
    "wof:name":"Merit Contracts",
    "wof:placetype":"venue"
},
  "geometry": {"coordinates":[0.57106,51.351429],"type":"Point"}
}