{
  "type": "Feature",
  "properties": {
    "addr:full":"4 Cranbourne Street Brighton East Sussex BN1 2RD",
    "addr:housenumber":"4",
    "addr:postcode":"bn1 2rd",
    "addr:street":"Cranbourne Street",
    "iso:country":"GB",
    "sg:address":"4 Cranbourne Street",
    "sg:city":"Brighton",
    "sg:classifiers":[
        {
            "category":"Retail",
            "subcategory":"Laundry & Dry Cleaning",
            "type":"Services"
        }
    ],
    "sg:postcode":"BN1 2RD",
    "sg:province":"East Sussex",
    "sg:tags":[
        "alteration"
    ],
    "wof:name":"Altered Image",
    "wof:placetype":"venue"
},
  "geometry": {"coordinates":[-0.1445969939,50.8233299255],"type":"Point"}
}