{
  "type": "Feature",
  "properties": {
    "addr:full":"1a Earl Street Hastings East Sussex TN34 1RX",
    "addr:housenumber":"1a",
    "addr:postcode":"tn34 1rx",
    "addr:street":"Earl Street",
    "iso:country":"GB",
    "sg:address":"1a Earl Street",
    "sg:city":"Hastings",
    "sg:classifiers":[
        {
            "category":"Manufacturing",
            "subcategory":"Metals",
            "type":"Manufacturing & Wholesale Goods"
        }
    ],
    "sg:phone":"+44 1424 425834",
    "sg:postcode":"TN34 1RX",
    "sg:province":"East Sussex",
    "sg:tags":[
        "steel",
        "fabricator",
        "erectors"
    ],
    "wof:name":"Hartnells Hastings",
    "wof:placetype":"venue"
},
  "geometry": {"coordinates":[0.581337,50.859684],"type":"Point"}
}