{
  "type": "Feature",
  "properties": {
    "addr:full":"46 Ormesby Bank Middlesbrough North Yorkshire TS7 9EB",
    "addr:housenumber":"46",
    "addr:postcode":"ts7 9eb",
    "addr:street":"Ormesby Bank",
    "iso:country":"GB",
    "sg:address":"46 Ormesby Bank",
    "sg:city":"Middlesbrough",
    "sg:classifiers":[
        {
            "category":"Building & Trades",
            "subcategory":"Construction",
            "type":"Services"
        }
    ],
    "sg:phone":"+44 1642 300489",
    "sg:postcode":"TS7 9EB",
    "sg:province":"North Yorkshire",
    "sg:tags":[
        "dry",
        "lining",
        "plasterers",
        "screeders"
    ],
    "wof:name":"Scott Ankers",
    "wof:placetype":"venue"
},
  "geometry": {"coordinates":[-1.171429038,54.539932251],"type":"Point"}
}