{
  "type": "Feature",
  "properties": {
    "addr:full":"115a Baker St West End Hampshire W1M 1FE",
    "addr:housenumber":"115a",
    "addr:postcode":"w1m 1fe",
    "addr:street":"Baker St",
    "iso:country":"GB",
    "sg:address":"115a Baker St",
    "sg:city":"West End",
    "sg:classifiers":[
        {
            "category":"Professional",
            "subcategory":"Computer Services",
            "type":"Services"
        }
    ],
    "sg:phone":"+44 20 7486 4500",
    "sg:postcode":"W1M 1FE",
    "sg:province":"Hampshire",
    "sg:tags":[
        "system",
        "software"
    ],
    "wof:name":"On-Track Computer Training",
    "wof:placetype":"venue"
},
  "geometry": {"coordinates":[-0.157346,51.521351],"type":"Point"}
}