{
  "type": "Feature",
  "properties": {
    "iso:country":"GB",
    "sg:address":"47 Forres Avenue, Giffnock",
    "sg:city":"Glasgow",
    "sg:classifiers":[
        {
            "category":"Retail",
            "subcategory":"Driving School",
            "type":"Services"
        }
    ],
    "sg:postcode":"G46 6LF",
    "sg:province":"East Renfrewshire",
    "wof:name":"Ken Eadie",
    "wof:placetype":"venue"
},
  "geometry": {"coordinates":[-4.2906708717,55.8039207458],"type":"Point"}
}