{
  "type": "Feature",
  "properties": {
    "addr:full":"501 Bloxwich Road Walsall Staffordshire WS3 2XA",
    "addr:housenumber":"501",
    "addr:postcode":"ws3 2xa",
    "addr:street":"Bloxwich Road",
    "iso:country":"GB",
    "sg:address":"501 Bloxwich Road",
    "sg:city":"Walsall",
    "sg:classifiers":[
        {
            "category":"Shopping",
            "subcategory":"Clothing, Apparel, & Fashions",
            "type":"Retail Goods"
        },
        {
            "category":"Shopping",
            "type":"Retail Goods"
        }
    ],
    "sg:phone":"+44 1922 710055",
    "sg:postcode":"WS3 2XA",
    "sg:province":"Staffordshire",
    "sg:tags":[
        "equipment",
        "workwear",
        "protective",
        "safety",
        "clothing"
    ],
    "wof:name":"Rushall Protective Clothing Co. Ltd.",
    "wof:placetype":"venue"
},
  "geometry": {"coordinates":[-1.9919509888,52.6049766541],"type":"Point"}
}