{
  "type": "Feature",
  "properties": {
    "addr:full":"29 Dorset Square London Greater London NW1 6QJ",
    "addr:housenumber":"29",
    "addr:postcode":"nw1 6qj",
    "addr:street":"Dorset Square",
    "iso:country":"GB",
    "sg:address":"29 Dorset Square",
    "sg:city":"London",
    "sg:classifiers":[
        {
            "category":"Professional",
            "subcategory":"Business Services",
            "type":"Services"
        }
    ],
    "sg:postcode":"NW1 6QJ",
    "sg:province":"Greater London",
    "sg:tags":[
        "holding"
    ],
    "wof:name":"Anglo-Sino Developments Ltd.",
    "wof:placetype":"venue"
},
  "geometry": {"coordinates":[-0.1612990052,51.522403717],"type":"Point"}
}