{
  "type": "Feature",
  "properties": {
    "addr:full":"Brightside Lane Sheffield South Yorkshire S9 2SN",
    "addr:postcode":"s9 2sn",
    "addr:street":"Brightside Lane",
    "iso:country":"GB",
    "sg:address":"Brightside Lane",
    "sg:city":"Sheffield",
    "sg:classifiers":[
        {
            "category":"Wholesale",
            "subcategory":"Scrap",
            "type":"Manufacturing & Wholesale Goods"
        },
        {
            "category":"Wholesale",
            "subcategory":"Auto Parts",
            "type":"Manufacturing & Wholesale Goods"
        }
    ],
    "sg:phone":"+44 114 244 0441",
    "sg:postcode":"S9 2SN",
    "sg:province":"South Yorkshire",
    "sg:tags":[
        "car",
        "breaker",
        "dismantlers"
    ],
    "wof:name":"Charlotte Motor Salvage",
    "wof:placetype":"venue"
},
  "geometry": {"coordinates":[-1.435649,53.400814],"type":"Point"}
}