{
  "type": "Feature",
  "properties": {
    "addr:full":"1 Elmhurst, Egginton Derby Derbyshire DE65 6HQ",
    "addr:housenumber":"1",
    "addr:postcode":"de65 6hq",
    "addr:street":"Elmhurst",
    "iso:country":"GB",
    "sg:address":"1 Elmhurst, Egginton",
    "sg:city":"Derby",
    "sg:classifiers":[
        {
            "category":"Professional",
            "subcategory":"Management & Consulting",
            "type":"Services"
        }
    ],
    "sg:phone":"+44 1283 734145",
    "sg:postcode":"DE65 6HQ",
    "sg:province":"Derbyshire",
    "sg:tags":[
        "consultant",
        "business"
    ],
    "wof:name":"Aqumen Solutions Ltd.",
    "wof:placetype":"venue"
},
  "geometry": {"coordinates":[-1.5673029423,52.8636398315],"type":"Point"}
}