{
  "type": "Feature",
  "properties": {
    "addr:full":"Suite 3, Somerton House, Lloyd Street Newport Newport NP19 0JN",
    "addr:housenumber":"suite 3 somerton house",
    "addr:postcode":"np19 0jn",
    "addr:street":"Lloyd Street",
    "iso:country":"GB",
    "sg:address":"Suite 3, Somerton House, Lloyd Street",
    "sg:city":"Newport",
    "sg:classifiers":[
        {
            "category":"Professional",
            "subcategory":"Detective & Security Services",
            "type":"Services"
        }
    ],
    "sg:phone":"+44 1633 272726",
    "sg:postcode":"NP19 0JN",
    "sg:province":"Newport",
    "wof:name":"Guardian Security Services Ltd.",
    "wof:placetype":"venue"
},
  "geometry": {"coordinates":[-2.9623990059,51.5820007324],"type":"Point"}
}