{
  "type": "Feature",
  "properties": {
    "addr:full":"Portakabin, Plantation Avenue Poulton-le-fylde Lancashire FY6 0AT",
    "addr:postcode":"fy6 0at",
    "addr:street":"Plantation Avenue Poulton-Le-Fylde",
    "iso:country":"GB",
    "sg:address":"Portakabin, Plantation Avenue",
    "sg:city":"Poulton-le-fylde",
    "sg:classifiers":[
        {
            "category":"Professional",
            "subcategory":"Computer Services",
            "type":"Services"
        }
    ],
    "sg:postcode":"FY6 0AT",
    "sg:province":"Lancashire",
    "sg:tags":[
        "information"
    ],
    "wof:name":"The Over Wyre Community Care Network",
    "wof:placetype":"venue"
},
  "geometry": {"coordinates":[-2.9859941006,53.9276924133],"type":"Point"}
}