{
  "type": "Feature",
  "properties": {
    "iso:country":"GB",
    "sg:address":"Intec No 3, Intec Businees Park",
    "sg:city":"Basingstoke",
    "sg:classifiers":[
        {
            "category":"Retail",
            "subcategory":"Laundry & Dry Cleaning",
            "type":"Services"
        }
    ],
    "sg:phone":"+44 1256 339221",
    "sg:postcode":"RG24 8NE",
    "sg:province":"Hampshire",
    "sg:tags":[
        "alteration"
    ],
    "wof:name":"Lakeland Pennine Group Plc",
    "wof:placetype":"venue"
},
  "geometry": {"coordinates":[-1.06609,51.27914],"type":"Point"}
}