{
  "type": "Feature",
  "properties": {
    "iso:country":"GB",
    "sg:address":"60-62 Shortmead Street",
    "sg:city":"Biggleswade",
    "sg:classifiers":[
        {
            "category":"Personal",
            "subcategory":"Barber",
            "type":"Services"
        }
    ],
    "sg:postcode":"SG18 0AP",
    "sg:province":"Bedfordshire",
    "sg:tags":[
        "men's",
        "hairdresser"
    ],
    "wof:name":"Bernard's",
    "wof:placetype":"venue"
},
  "geometry": {"coordinates":[-0.267111,52.089111],"type":"Point"}
}