{
  "type": "Feature",
  "properties": {
    "addr:full":"The Hollies, Longnor Stafford Shropshire ST19 5QN",
    "addr:postcode":"st19 5qn",
    "addr:street":"Longnor",
    "iso:country":"GB",
    "sg:address":"The Hollies, Longnor",
    "sg:city":"Stafford",
    "sg:classifiers":[
        {
            "category":"Professional",
            "subcategory":"Engineering",
            "type":"Services"
        }
    ],
    "sg:phone":"+44 1785 841212",
    "sg:postcode":"ST19 5QN",
    "sg:province":"Shropshire",
    "sg:tags":[
        "contractor",
        "electrical",
        "engineer"
    ],
    "wof:name":"Modern Electrical Ltd.",
    "wof:placetype":"venue"
},
  "geometry": {"coordinates":[-2.19796,52.724689],"type":"Point"}
}