{
  "type": "Feature",
  "properties": {
    "addr:full":"18 Courtlands Way, Felpham Bognor Regis West Sussex PO22 6AW",
    "addr:housenumber":"18",
    "addr:postcode":"po22 6aw",
    "addr:street":"Courtlands Way",
    "iso:country":"GB",
    "sg:address":"18 Courtlands Way, Felpham",
    "sg:city":"Bognor Regis",
    "sg:classifiers":[
        {
            "category":"Professional",
            "subcategory":"Art Services",
            "type":"Services"
        }
    ],
    "sg:postcode":"PO22 6AW",
    "sg:province":"West Sussex",
    "sg:tags":[
        "photographer"
    ],
    "wof:name":"Murrays Photography",
    "wof:placetype":"venue"
},
  "geometry": {"coordinates":[-0.6342759728,50.7976646423],"type":"Point"}
}