{
  "type": "Feature",
  "properties": {
    "addr:full":"Portsmouth Road Surbiton Surrey KT6 4ES",
    "addr:postcode":"kt6 4es",
    "addr:street":"Portsmouth Road",
    "iso:country":"GB",
    "sg:address":"Portsmouth Road",
    "sg:city":"Surbiton",
    "sg:classifiers":[
        {
            "category":"Restaurant",
            "type":"Food & Drink"
        }
    ],
    "sg:phone":"+44 20 8399 7515",
    "sg:postcode":"KT6 4ES",
    "sg:province":"Surrey",
    "wof:name":"Harts Boat Yard",
    "wof:placetype":"venue"
},
  "geometry": {"coordinates":[-0.309574,51.398846],"type":"Point"}
}