{
  "type": "Feature",
  "properties": {
    "iso:country":"GB",
    "sg:address":"3 Shopping Precinct, Middleton Road, Chadderton",
    "sg:city":"Oldham",
    "sg:classifiers":[
        {
            "category":"Food & Beverages",
            "subcategory":"Bakery",
            "type":"Retail Goods"
        }
    ],
    "sg:phone":"+44 161 620 8336",
    "sg:postcode":"OL9 0LQ",
    "sg:province":"Lancashire",
    "sg:tags":[
        "shop",
        "baker"
    ],
    "wof:name":"Greggs plc",
    "wof:placetype":"venue"
},
  "geometry": {"coordinates":[-2.14196,53.545368],"type":"Point"}
}