{
  "type": "Feature",
  "properties": {
    "iso:country":"GB",
    "sg:address":"5 Clarendon Grove",
    "sg:city":"Mitcham",
    "sg:classifiers":[
        {
            "category":"Retail",
            "subcategory":"Auto Repair",
            "type":"Services"
        }
    ],
    "sg:phone":"+44 20 8640 8828",
    "sg:postcode":"CR4 2PH",
    "sg:province":"Greater London",
    "sg:tags":[
        "modification",
        "garage"
    ],
    "wof:name":"Trevor Taylor Conversions",
    "wof:placetype":"venue"
},
  "geometry": {"coordinates":[-0.1625889987,51.4046783447],"type":"Point"}
}