{
  "type": "Feature",
  "properties": {
    "iso:country":"GB",
    "sg:address":"Dental Surgery, 18b Thames Dr",
    "sg:city":"Leigh On Sea",
    "sg:classifiers":[
        {
            "category":"Health Services",
            "subcategory":"Dentist",
            "type":"Services"
        }
    ],
    "sg:phone":"+44 1702 478494",
    "sg:postcode":"SS9 2XD",
    "sg:province":"Essex",
    "wof:name":"M C R McMahon",
    "wof:placetype":"venue"
},
  "geometry": {"coordinates":[0.6509950161,51.5484809875],"type":"Point"}
}