{
  "type": "Feature",
  "properties": {
    "iso:country":"GB",
    "sg:address":"Chaucer House, Stone Street, Petham",
    "sg:city":"Canterbury",
    "sg:classifiers":[
        {
            "category":"Retail",
            "subcategory":"Auto Repair",
            "type":"Services"
        }
    ],
    "sg:postcode":"CT4 5PW",
    "sg:province":"Kent",
    "sg:tags":[
        "garage"
    ],
    "wof:name":"Chaucer Garage Equipment",
    "wof:placetype":"venue"
},
  "geometry": {"coordinates":[1.0461440086,51.2234191895],"type":"Point"}
}