{
  "type": "Feature",
  "properties": {
    "addr:full":"29 Tower Road Bournemouth Dorset BH1 4LA",
    "addr:housenumber":"29",
    "addr:postcode":"bh1 4la",
    "addr:street":"Tower Road",
    "iso:country":"GB",
    "sg:address":"29 Tower Road",
    "sg:city":"Bournemouth",
    "sg:classifiers":[
        {
            "category":"Professional",
            "subcategory":"Engineering",
            "type":"Services"
        },
        {
            "category":"Building & Trades",
            "subcategory":"Electrical",
            "type":"Services"
        }
    ],
    "sg:phone":"+44 1202 301294",
    "sg:postcode":"BH1 4LA",
    "sg:province":"Dorset",
    "sg:tags":[
        "engineer",
        "electrician",
        "contractor"
    ],
    "wof:name":"Stuart Barton Electrical",
    "wof:placetype":"venue"
},
  "geometry": {"coordinates":[-1.8424259424,50.7302894592],"type":"Point"}
}