{
  "type": "Feature",
  "properties": {
    "iso:country":"GB",
    "sg:address":"Horton Depot, Stanwell Road",
    "sg:city":"Slough",
    "sg:classifiers":[
        {
            "category":"Building & Trades",
            "subcategory":"Landscaping Services",
            "type":"Services"
        }
    ],
    "sg:phone":"+44 1753 670184",
    "sg:postcode":"SL3 9PE",
    "sg:province":"Berkshire",
    "sg:tags":[
        "landscape",
        "contractor"
    ],
    "wof:name":"County Landscapes",
    "wof:placetype":"venue"
},
  "geometry": {"coordinates":[-0.542158,51.47316],"type":"Point"}
}