{
  "type": "Feature",
  "properties": {
    "addr:full":"22b New Greenmarket Newcastle-upon-tyne Tyne and Wear NE1 7YA",
    "addr:housenumber":"22b",
    "addr:postcode":"ne1 7ya",
    "addr:street":"New Greenmarket",
    "iso:country":"GB",
    "sg:address":"22b New Greenmarket",
    "sg:city":"Newcastle-upon-tyne",
    "sg:classifiers":[
        {
            "category":"Shopping",
            "subcategory":"Clothing, Apparel, & Fashions",
            "type":"Retail Goods"
        }
    ],
    "sg:phone":"+44 191 261 1382",
    "sg:postcode":"NE1 7YA",
    "sg:province":"Tyne and Wear",
    "sg:tags":[
        "clothing",
        "fabric"
    ],
    "wof:name":"Beech Tree (Marketing)",
    "wof:placetype":"venue"
},
  "geometry": {"coordinates":[-1.6123689413,54.9779167175],"type":"Point"}
}