{
  "type": "Feature",
  "properties": {
    "addr:full":"Three Lane Ends Farm, Newborough Burton-on-trent Derbyshire DE13 8RY",
    "addr:postcode":"de13 8ry",
    "addr:street":"Three;Ends",
    "iso:country":"GB",
    "sg:address":"Three Lane Ends Farm, Newborough",
    "sg:city":"Burton-on-trent",
    "sg:classifiers":[
        {
            "category":"Farming",
            "subcategory":"Livestock Farm",
            "type":"Manufacturing & Wholesale Goods"
        }
    ],
    "sg:phone":"+44 1283 820391",
    "sg:postcode":"DE13 8RY",
    "sg:province":"Derbyshire",
    "sg:tags":[
        "others"
    ],
    "wof:name":"John W Latchford",
    "wof:placetype":"venue"
},
  "geometry": {"coordinates":[-1.800559,52.826126],"type":"Point"}
}