{
  "type": "Feature",
  "properties": {
    "addr:full":"The Kop, Gables Road, Church Crookham Fleet Hampshire GU52 6QY",
    "addr:postcode":"gu52 6qy",
    "addr:street":"Gables Road",
    "iso:country":"GB",
    "sg:address":"The Kop, Gables Road, Church Crookham",
    "sg:city":"Fleet",
    "sg:classifiers":[
        {
            "category":"Education",
            "subcategory":"Dance Studio",
            "type":"Public Place"
        }
    ],
    "sg:postcode":"GU52 6QY",
    "sg:province":"Hampshire",
    "sg:tags":[
        "ballet",
        "school"
    ],
    "wof:name":"Sandra Shelton School of Ballet",
    "wof:placetype":"venue"
},
  "geometry": {"coordinates":[-0.8322889805,51.2678337097],"type":"Point"}
}