{
  "type": "Feature",
  "properties": {
    "addr:full":"42 Pingle Drive Bicester Oxfordshire OX26 6WD",
    "addr:housenumber":"42",
    "addr:postcode":"ox26 6wd",
    "addr:street":"Pingle Drive",
    "iso:country":"GB",
    "sg:address":"42 Pingle Drive",
    "sg:city":"Bicester",
    "sg:classifiers":[
        {
            "category":"Shopping",
            "subcategory":"Clothing, Apparel, & Fashions",
            "type":"Retail Goods"
        }
    ],
    "sg:phone":"+44 1869 369370",
    "sg:postcode":"OX26 6WD",
    "sg:province":"Oxfordshire",
    "sg:tags":[
        "ladieswear"
    ],
    "wof:name":"Episode (G B) Ltd.",
    "wof:placetype":"venue"
},
  "geometry": {"coordinates":[-1.1563600302,51.893081665],"type":"Point"}
}