{
  "type": "Feature",
  "properties": {
    "iso:country":"GB",
    "sg:address":"C/o J Bruce Andrew & Co, Glenfield Auction Market, Glenfield Rd",
    "sg:city":"Paisley",
    "sg:classifiers":[
        {
            "category":"Building & Trades",
            "subcategory":"Plumbing",
            "type":"Services"
        }
    ],
    "sg:postcode":"PA2 8TF",
    "sg:province":"East Renfrewshire",
    "sg:tags":[
        "central",
        "heating"
    ],
    "wof:name":"Andrew Gas Services Ltd",
    "wof:placetype":"venue"
},
  "geometry": {"coordinates":[-4.4266,55.817699],"type":"Point"}
}