{
  "type": "Feature",
  "properties": {
    "iso:country":"GB",
    "sg:address":"119 Chamberlayne Road",
    "sg:city":"London",
    "sg:classifiers":[
        {
            "category":"Shopping",
            "subcategory":"Department Store",
            "type":"Retail Goods"
        }
    ],
    "sg:phone":"+44 20 8969 3830",
    "sg:postcode":"NW10 3NS",
    "sg:province":"Greater London",
    "wof:name":"Riseway",
    "wof:placetype":"venue"
},
  "geometry": {"coordinates":[-0.219984,51.535233],"type":"Point"}
}