{
  "type": "Feature",
  "properties": {
    "iso:country":"GB",
    "sg:address":"58 Meadow Croft",
    "sg:city":"Penrith",
    "sg:classifiers":[
        {
            "category":"Building & Trades",
            "subcategory":"Plumbing",
            "type":"Services"
        }
    ],
    "sg:phone":"+44 1768 891688",
    "sg:postcode":"CA11 8EH",
    "sg:province":"Cumbria",
    "sg:tags":[
        "central",
        "heating"
    ],
    "wof:name":"K Long",
    "wof:placetype":"venue"
},
  "geometry": {"coordinates":[-2.737799,54.665039],"type":"Point"}
}