{
  "type": "Feature",
  "properties": {
    "addr:full":"47 Newmarket Street Ayr South Ayrshire KA7 1LL",
    "addr:housenumber":"47",
    "addr:postcode":"ka7 1ll",
    "addr:street":"Newmarket Street",
    "iso:country":"GB",
    "sg:address":"47 Newmarket Street",
    "sg:city":"Ayr",
    "sg:classifiers":[
        {
            "category":"Personal",
            "subcategory":"Beauty Salon",
            "type":"Services"
        }
    ],
    "sg:postcode":"KA7 1LL",
    "sg:province":"South Ayrshire",
    "sg:tags":[
        "unisex",
        "hairdresser"
    ],
    "wof:name":"Hairstopper",
    "wof:placetype":"venue"
},
  "geometry": {"coordinates":[-4.630426,55.463406],"type":"Point"}
}