{
  "type": "Feature",
  "properties": {
    "iso:country":"GB",
    "sg:address":"31-33 Merritts Brook La",
    "sg:city":"Birmingham",
    "sg:classifiers":[
        {
            "category":"Organizations",
            "subcategory":"Non-profit Organization",
            "type":"Services"
        }
    ],
    "sg:phone":"+44 121 477 8006",
    "sg:postcode":"B31 1PP",
    "sg:province":"West Midlands",
    "sg:tags":[
        "organisation",
        "voluntary",
        "charity"
    ],
    "wof:name":"Middlemore Family Centre",
    "wof:placetype":"venue"
},
  "geometry": {"coordinates":[-1.976717,52.420269],"type":"Point"}
}