{
  "type": "Feature",
  "properties": {
    "iso:country":"GB",
    "sg:address":"148 Arthur Rd",
    "sg:city":"Wimbledon",
    "sg:classifiers":[
        {
            "category":"Real Estate",
            "subcategory":"Real Estate Operator",
            "type":"Services"
        }
    ],
    "sg:phone":"+44 20 8946 3913",
    "sg:postcode":"SW19 8AQ",
    "sg:province":"Greater London",
    "sg:tags":[
        "letting",
        "agent"
    ],
    "wof:name":"Aveyron Villas",
    "wof:placetype":"venue"
},
  "geometry": {"coordinates":[-0.1977390051,51.4348106384],"type":"Point"}
}