{
  "type": "Feature",
  "properties": {
    "iso:country":"GB",
    "sg:address":"Scott's Road",
    "sg:city":"Kirkwall",
    "sg:classifiers":[
        {
            "category":"Building & Trades",
            "subcategory":"Plumbing",
            "type":"Services"
        }
    ],
    "sg:phone":"+44 1856 872540",
    "sg:postcode":"KW15 1GR",
    "sg:province":"Orkney Islands",
    "sg:tags":[
        "merchant",
        "plumbers'"
    ],
    "wof:name":"D A G Kynoch Ltd.",
    "wof:placetype":"venue"
},
  "geometry": {"coordinates":[-2.97507,58.988129],"type":"Point"}
}