{
  "type": "Feature",
  "properties": {
    "addr:full":"Station Rd Chesterfield Derbyshire S41 9EX",
    "addr:postcode":"s41 9ex",
    "addr:street":"Station Rd",
    "iso:country":"GB",
    "sg:address":"Station Rd",
    "sg:city":"Chesterfield",
    "sg:classifiers":[
        {
            "category":"Autos & Motor Vehicles",
            "subcategory":"Automobile Sales",
            "type":"Retail Goods"
        }
    ],
    "sg:phone":"+44 1246 454522",
    "sg:postcode":"S41 9EX",
    "sg:province":"Derbyshire",
    "sg:tags":[
        "car"
    ],
    "wof:name":"Autoworld",
    "wof:placetype":"venue"
},
  "geometry": {"coordinates":[-1.428059,53.263699],"type":"Point"}
}