{
  "type": "Feature",
  "properties": {
    "addr:full":"Marshbrook Way, Muxton Telford Shropshire TF2 8SA",
    "addr:postcode":"tf2 8sa",
    "addr:street":"Marshbrook Way",
    "iso:country":"GB",
    "sg:address":"Marshbrook Way, Muxton",
    "sg:city":"Telford",
    "sg:classifiers":[
        {
            "category":"Education",
            "subcategory":"School",
            "type":"Public Place"
        }
    ],
    "sg:phone":"+44 1952 608002",
    "sg:postcode":"TF2 8SA",
    "sg:province":"Shropshire",
    "sg:tags":[
        "local",
        "authority"
    ],
    "wof:name":"Muxton Primary School",
    "wof:placetype":"venue"
},
  "geometry": {"coordinates":[-2.42019,52.724594],"type":"Point"}
}