{
  "type": "Feature",
  "properties": {
    "addr:full":"Stoddah Bank, Penruddock Penrith Cumbria CA11 0RY",
    "addr:postcode":"ca11 0ry",
    "addr:street":"Penruddock",
    "iso:country":"GB",
    "sg:address":"Stoddah Bank, Penruddock",
    "sg:city":"Penrith",
    "sg:classifiers":[
        {
            "category":"Building & Trades",
            "subcategory":"Landscaping Services",
            "type":"Services"
        }
    ],
    "sg:phone":"+44 17684 83372",
    "sg:postcode":"CA11 0RY",
    "sg:province":"Cumbria",
    "sg:tags":[
        "forestry",
        "tree"
    ],
    "wof:name":"Treecare",
    "wof:placetype":"venue"
},
  "geometry": {"coordinates":[-2.886304,54.640072],"type":"Point"}
}