{
  "type": "Feature",
  "properties": {
    "iso:country":"GB",
    "sg:address":"23 Ledbury Dr",
    "sg:city":"Leeds",
    "sg:classifiers":[
        {
            "category":"Wholesale",
            "subcategory":"Music Publishers",
            "type":"Manufacturing & Wholesale Goods"
        }
    ],
    "sg:phone":"+44 113 272 0350",
    "sg:postcode":"LS10 4RX",
    "sg:province":"West Yorkshire",
    "sg:tags":[
        "record"
    ],
    "wof:name":"Fletcher House Productions Ltd",
    "wof:placetype":"venue"
},
  "geometry": {"coordinates":[-1.522158,53.746597],"type":"Point"}
}