{
  "type": "Feature",
  "properties": {
    "iso:country":"GB",
    "sg:address":"Haf House, Mead Lane",
    "sg:city":"Hertford",
    "sg:classifiers":[
        {
            "category":"Home & Garden",
            "subcategory":"Hardware",
            "type":"Retail Goods"
        }
    ],
    "sg:phone":"+44 1992 505655",
    "sg:postcode":"SG13 7AP",
    "sg:province":"Hertfordshire",
    "wof:name":"Handles & Fittings Ltd.",
    "wof:placetype":"venue"
},
  "geometry": {"coordinates":[-0.061766,51.801926],"type":"Point"}
}