{
  "type": "Feature",
  "properties": {
    "addr:full":"191 High St West Drayton Greater London UB7 7XW",
    "addr:housenumber":"191",
    "addr:postcode":"ub7 7xw",
    "addr:street":"High St",
    "iso:country":"GB",
    "sg:address":"191 High St",
    "sg:city":"West Drayton",
    "sg:classifiers":[
        {
            "category":"Wholesale",
            "subcategory":"Scrap",
            "type":"Manufacturing & Wholesale Goods"
        }
    ],
    "sg:phone":"+44 1895 444714",
    "sg:postcode":"UB7 7XW",
    "sg:province":"Greater London",
    "sg:tags":[
        "waste",
        "metal"
    ],
    "wof:name":"R E G Uk",
    "wof:placetype":"venue"
},
  "geometry": {"coordinates":[-0.4746089876,51.5153503418],"type":"Point"}
}