{
  "type": "Feature",
  "properties": {
    "iso:country":"GB",
    "sg:address":"Springfield, Hangersley Hill",
    "sg:city":"Ringwood",
    "sg:classifiers":[
        {
            "category":"Communications",
            "subcategory":"News Services",
            "type":"Services"
        }
    ],
    "sg:phone":"+44 1425 470946",
    "sg:postcode":"BH24 3JN",
    "sg:province":"Dorset",
    "sg:tags":[
        "journalist"
    ],
    "wof:name":"Adele Evans Associates",
    "wof:placetype":"venue"
},
  "geometry": {"coordinates":[-1.755333,50.855183],"type":"Point"}
}