{
  "type": "Feature",
  "properties": {
    "iso:country":"GB",
    "sg:address":"34a Muirhouse Crescent",
    "sg:city":"Edinburgh",
    "sg:classifiers":[
        {
            "category":"Organizations",
            "subcategory":"Non-profit Organization",
            "type":"Services"
        }
    ],
    "sg:phone":"+44 131 332 2124",
    "sg:postcode":"EH4 4QL",
    "sg:province":"City of Edinburgh",
    "sg:tags":[
        "organisation",
        "voluntary",
        "charity"
    ],
    "wof:name":"Muirhouse Six Circle Project",
    "wof:placetype":"venue"
},
  "geometry": {"coordinates":[-3.253751,55.972069],"type":"Point"}
}