{
  "type": "Feature",
  "properties": {
    "addr:full":"82 Devonshire Road Blackpool Lancashire FY3 8AN",
    "addr:housenumber":"82",
    "addr:postcode":"fy3 8an",
    "addr:street":"Devonshire Road",
    "iso:country":"GB",
    "sg:address":"82 Devonshire Road",
    "sg:city":"Blackpool",
    "sg:classifiers":[
        {
            "category":"Retail",
            "subcategory":"Laundry & Dry Cleaning",
            "type":"Services"
        }
    ],
    "sg:phone":"+44 1253 397179",
    "sg:postcode":"FY3 8AN",
    "sg:province":"Lancashire",
    "sg:tags":[
        "alteration"
    ],
    "wof:name":"Linda's Alterations",
    "wof:placetype":"venue"
},
  "geometry": {"coordinates":[-3.0392189026,53.8233146667],"type":"Point"}
}