{
  "type": "Feature",
  "properties": {
    "addr:full":"The Vicarage, 28 Cromwell Rd Chesterfield Derbyshire S40 4TH",
    "addr:housenumber":"28",
    "addr:postcode":"s40 4th",
    "addr:street":"Cromwell Rd",
    "iso:country":"GB",
    "sg:address":"The Vicarage, 28 Cromwell Rd",
    "sg:city":"Chesterfield",
    "sg:classifiers":[
        {
            "category":"Place Of Worship",
            "type":"Public Place"
        }
    ],
    "sg:phone":"+44 1246 232937",
    "sg:postcode":"S40 4TH",
    "sg:province":"Derbyshire",
    "wof:name":"St Leonard C Of E Church",
    "wof:placetype":"venue"
},
  "geometry": {"coordinates":[-1.4377,53.24255],"type":"Point"}
}