{
  "type": "Feature",
  "properties": {
    "addr:full":"Bell Lane, Hawstead Bury St Edmunds Suffolk IP29 5NW",
    "addr:postcode":"ip29 5nw",
    "addr:street":"Bell Lane",
    "iso:country":"GB",
    "sg:address":"Bell Lane, Hawstead",
    "sg:city":"Bury St Edmunds",
    "sg:classifiers":[
        {
            "category":"Shopping",
            "subcategory":"Crafts & Fabrics",
            "type":"Retail Goods"
        },
        {
            "category":"Manufacturing",
            "subcategory":"Building Materials",
            "type":"Manufacturing & Wholesale Goods"
        }
    ],
    "sg:phone":"+44 1284 386447",
    "sg:postcode":"IP29 5NW",
    "sg:province":"Suffolk",
    "sg:tags":[
        "boiler",
        "manufacturer"
    ],
    "wof:name":"Cornwell Heat Ltd",
    "wof:placetype":"venue"
},
  "geometry": {"coordinates":[0.721265,52.194996],"type":"Point"}
}