{
  "type": "Feature",
  "properties": {
    "addr:full":"The Wharf, Dudbridge Stroud Gloucestershire GL5 3ET",
    "addr:postcode":"gl5 3et",
    "iso:country":"GB",
    "sg:address":"The Wharf, Dudbridge",
    "sg:city":"Stroud",
    "sg:classifiers":[
        {
            "category":"Freight",
            "type":"Transportation"
        }
    ],
    "sg:phone":"+44 1453 764017",
    "sg:postcode":"GL5 3ET",
    "sg:province":"Gloucestershire",
    "sg:tags":[
        "haulage",
        "road"
    ],
    "wof:name":"H Wiggall & Sons Ltd.",
    "wof:placetype":"venue"
},
  "geometry": {"coordinates":[-2.23913,51.742512],"type":"Point"}
}