{
  "type": "Feature",
  "properties": {
    "iso:country":"GB",
    "sg:address":"348 Leigh Road",
    "sg:city":"Wigan",
    "sg:classifiers":[
        {
            "category":"Shopping",
            "type":"Retail Goods"
        }
    ],
    "sg:phone":"+44 1942 522093",
    "sg:postcode":"WN2 4XL",
    "sg:province":"Lancashire",
    "sg:tags":[
        "part",
        "accessory"
    ],
    "wof:name":"B & D Autospares",
    "wof:placetype":"venue"
},
  "geometry": {"coordinates":[-2.546392,53.513916],"type":"Point"}
}