{
  "type": "Feature",
  "properties": {
    "addr:full":"Pleasance, Penwartha Helston Cornwall TR12 6RS",
    "addr:postcode":"tr12 6rs",
    "iso:country":"GB",
    "sg:address":"Pleasance, Penwartha",
    "sg:city":"Helston",
    "sg:classifiers":[
        {
            "category":"Organizations",
            "subcategory":"Community Association",
            "type":"Services"
        }
    ],
    "sg:phone":"+44 1326 280416",
    "sg:postcode":"TR12 6RS",
    "sg:province":"Cornwall",
    "sg:tags":[
        "relation",
        "public"
    ],
    "wof:name":"Bartlett Associates (Midlands) Ltd.",
    "wof:placetype":"venue"
},
  "geometry": {"coordinates":[-5.1387181282,50.0647964478],"type":"Point"}
}