{
  "type": "Feature",
  "properties": {
    "addr:full":"173 Highgate Kendal Cumbria LA9 4EN",
    "addr:housenumber":"173",
    "addr:postcode":"la9 4en",
    "addr:street":"Highgate",
    "iso:country":"GB",
    "sg:address":"173 Highgate",
    "sg:city":"Kendal",
    "sg:classifiers":[
        {
            "category":"Retail",
            "subcategory":"Veterinary Services",
            "type":"Services"
        }
    ],
    "sg:phone":"+44 1539 721344",
    "sg:postcode":"LA9 4EN",
    "sg:province":"Cumbria",
    "sg:tags":[
        "surgeon",
        "activity"
    ],
    "wof:name":"Highgate Veterinary Clinic",
    "wof:placetype":"venue"
},
  "geometry": {"coordinates":[-2.74706,54.323708],"type":"Point"}
}