{
  "type": "Feature",
  "properties": {
    "addr:full":"10 Parkend Drive Leigh Lancashire WN7 3UH",
    "addr:housenumber":"10",
    "addr:postcode":"wn7 3uh",
    "addr:street":"Parkend Drive Leigh",
    "iso:country":"GB",
    "sg:address":"10 Parkend Drive",
    "sg:city":"Leigh",
    "sg:classifiers":[
        {
            "category":"Professional",
            "subcategory":"Detective & Security Services",
            "type":"Services"
        }
    ],
    "sg:phone":"+44 1942 607349",
    "sg:postcode":"WN7 3UH",
    "sg:province":"Lancashire",
    "sg:tags":[
        "alarm",
        "burglar",
        "system"
    ],
    "wof:name":"P M Alarms",
    "wof:placetype":"venue"
},
  "geometry": {"coordinates":[-2.5287330151,53.4858055115],"type":"Point"}
}