{
  "type": "Feature",
  "properties": {
    "iso:country":"GB",
    "sg:address":"Unit 9e Spencer Carter Works, Tregoniggie Indust Est",
    "sg:city":"Falmouth",
    "sg:classifiers":[
        {
            "category":"Manufacturing",
            "subcategory":"Building Materials",
            "type":"Manufacturing & Wholesale Goods"
        }
    ],
    "sg:phone":"+44 1326 373143",
    "sg:postcode":"TR11 4SN",
    "sg:province":"Cornwall",
    "sg:tags":[
        "extrusion"
    ],
    "wof:name":"Plastic & Rubber Extrusions",
    "wof:placetype":"venue"
},
  "geometry": {"coordinates":[-5.0800328255,50.1522064209],"type":"Point"}
}