{
  "type": "Feature",
  "properties": {
    "addr:full":"2 Aintree Rd Bootle Merseyside L20 9DN",
    "addr:housenumber":"2",
    "addr:postcode":"l20 9dn",
    "addr:street":"Aintree Rd",
    "iso:country":"GB",
    "sg:address":"2 Aintree Rd",
    "sg:city":"Bootle",
    "sg:classifiers":[
        {
            "category":"Health Services",
            "subcategory":"Doctor",
            "type":"Services"
        }
    ],
    "sg:phone":"+44 151 922 1768",
    "sg:postcode":"L20 9DN",
    "sg:province":"Merseyside",
    "sg:tags":[
        "practitioners"
    ],
    "wof:name":"Aintree Road Surgery",
    "wof:placetype":"venue"
},
  "geometry": {"coordinates":[-2.982008,53.45612],"type":"Point"}
}