{
  "type": "Feature",
  "properties": {
    "addr:full":"25 Wolverhampton Road Stafford Staffordshire ST17 4BP",
    "addr:housenumber":"25",
    "addr:postcode":"st17 4bp",
    "addr:street":"Wolverhampton Road",
    "iso:country":"GB",
    "sg:address":"25 Wolverhampton Road",
    "sg:city":"Stafford",
    "sg:classifiers":[
        {
            "category":"Shopping",
            "subcategory":"News",
            "type":"Retail Goods"
        }
    ],
    "sg:phone":"+44 1785 251624",
    "sg:postcode":"ST17 4BP",
    "sg:province":"Staffordshire",
    "sg:tags":[
        "newsagent"
    ],
    "wof:name":"Wolverhampton Road News",
    "wof:placetype":"venue"
},
  "geometry": {"coordinates":[-2.114116,52.801167],"type":"Point"}
}