{
  "type": "Feature",
  "properties": {
    "iso:country":"GB",
    "sg:address":"30a York Street",
    "sg:city":"Twickenham",
    "sg:classifiers":[
        {
            "category":"Professional",
            "subcategory":"Credit Reporting & Collection",
            "type":"Services"
        }
    ],
    "sg:postcode":"TW1 3LJ",
    "sg:province":"Greater London",
    "sg:tags":[
        "bailiff"
    ],
    "wof:name":"Wells Tickner & Co.",
    "wof:placetype":"venue"
},
  "geometry": {"coordinates":[-0.3270899951,51.4473381042],"type":"Point"}
}