{
  "type": "Feature",
  "properties": {
    "addr:full":"354 St Albans Road Watford Hertfordshire WD24 6PQ",
    "addr:housenumber":"354",
    "addr:postcode":"wd24 6pq",
    "addr:street":"St Albans Road",
    "iso:country":"GB",
    "sg:address":"354 St Albans Road",
    "sg:city":"Watford",
    "sg:classifiers":[
        {
            "category":"Building & Trades",
            "subcategory":"Plumbing",
            "type":"Services"
        }
    ],
    "sg:phone":"+44 1923 242952",
    "sg:postcode":"WD24 6PQ",
    "sg:province":"Hertfordshire",
    "sg:tags":[
        "heating"
    ],
    "wof:name":"James Day",
    "wof:placetype":"venue"
},
  "geometry": {"coordinates":[-0.396548003,51.6751823425],"type":"Point"}
}