{
  "type": "Feature",
  "properties": {
    "addr:full":"1 Langley Road Staines Berkshire TW18 2EH",
    "addr:housenumber":"1",
    "addr:postcode":"tw18 2eh",
    "addr:street":"Langley Road",
    "iso:country":"GB",
    "sg:address":"1 Langley Road",
    "sg:city":"Staines",
    "sg:classifiers":[
        {
            "category":"Building & Trades",
            "subcategory":"Construction",
            "type":"Services"
        }
    ],
    "sg:phone":"+44 1784 243092",
    "sg:postcode":"TW18 2EH",
    "sg:province":"Berkshire",
    "sg:tags":[
        "joiner",
        "carpenter"
    ],
    "wof:name":"Mastercraft Construction Ltd.",
    "wof:placetype":"venue"
},
  "geometry": {"coordinates":[-0.5071769953,51.4279212952],"type":"Point"}
}