{
  "type": "Feature",
  "properties": {
    "iso:country":"GB",
    "sg:address":"6 Arkle Croft",
    "sg:city":"Rowley Regis",
    "sg:classifiers":[
        {
            "category":"Building & Trades",
            "subcategory":"Construction",
            "type":"Services"
        }
    ],
    "sg:phone":"+44 1384 255641",
    "sg:postcode":"B65 8QF",
    "sg:province":"West Midlands",
    "sg:tags":[
        "glazier",
        "decorator",
        "painter"
    ],
    "wof:name":"K Hooper Painting & Decorating Service",
    "wof:placetype":"venue"
},
  "geometry": {"coordinates":[-2.0634639263,52.4966201782],"type":"Point"}
}