{
  "type": "Feature",
  "properties": {
    "addr:full":"Daglingworth Quarry, Gloucester Rd Cirencester Gloucestershire GL7 7JB",
    "addr:postcode":"gl7 7jb",
    "addr:street":"Daglingworth;Gloucester Rd",
    "iso:country":"GB",
    "sg:address":"Daglingworth Quarry, Gloucester Rd",
    "sg:city":"Cirencester",
    "sg:classifiers":[
        {
            "category":"Manufacturing",
            "subcategory":"Glass & Minerals",
            "type":"Manufacturing & Wholesale Goods"
        }
    ],
    "sg:phone":"+44 1285 652905",
    "sg:postcode":"GL7 7JB",
    "sg:province":"Gloucestershire",
    "sg:tags":[
        "chalk",
        "stone",
        "slate"
    ],
    "wof:name":"ARC Southern",
    "wof:placetype":"venue"
},
  "geometry": {"coordinates":[-1.9535410404,51.718547821],"type":"Point"}
}