{
  "type": "Feature",
  "properties": {
    "addr:full":"The Hungerford Surgery, The Croft Hungerford Berkshire RG17 0HY",
    "addr:postcode":"rg17 0hy",
    "addr:street":"The Croft",
    "iso:country":"GB",
    "sg:address":"The Hungerford Surgery, The Croft",
    "sg:city":"Hungerford",
    "sg:classifiers":[
        {
            "category":"Health Services",
            "subcategory":"Health Practitioner",
            "type":"Services"
        }
    ],
    "sg:phone":"+44 1488 681695",
    "sg:postcode":"RG17 0HY",
    "sg:province":"Berkshire",
    "sg:tags":[
        "osteopath"
    ],
    "wof:name":"D R Hamm",
    "wof:placetype":"venue"
},
  "geometry": {"coordinates":[-1.516156,51.413197],"type":"Point"}
}