{
  "type": "Feature",
  "properties": {
    "addr:full":"17 Market Place Pickering North Yorkshire YO18 7AE",
    "addr:housenumber":"17",
    "addr:postcode":"yo18 7ae",
    "addr:street":"Market Place",
    "iso:country":"GB",
    "sg:address":"17 Market Place",
    "sg:city":"Pickering",
    "sg:classifiers":[
        {
            "category":"Shopping",
            "subcategory":"Clothing, Apparel, & Fashions",
            "type":"Retail Goods"
        },
        {
            "category":"Recreation",
            "type":"Entertainment"
        }
    ],
    "sg:phone":"+44 1751 475183",
    "sg:postcode":"YO18 7AE",
    "sg:province":"North Yorkshire",
    "sg:tags":[
        "equipment",
        "outdoor",
        "clothing",
        "pursuit"
    ],
    "wof:name":"Ryedale Rambler",
    "wof:placetype":"venue"
},
  "geometry": {"coordinates":[-0.7780550122,54.2458648682],"type":"Point"}
}