{
  "type": "Feature",
  "properties": {
    "iso:country":"GB",
    "sg:address":"9 Branscombe Close",
    "sg:city":"Torquay",
    "sg:classifiers":[
        {
            "category":"Building & Trades",
            "subcategory":"Plumbing",
            "type":"Services"
        }
    ],
    "sg:postcode":"TQ1 3UQ",
    "sg:province":"Devon",
    "sg:tags":[
        "heating"
    ],
    "wof:name":"Kenneth Tompkins",
    "wof:placetype":"venue"
},
  "geometry": {"coordinates":[-3.512865,50.474007],"type":"Point"}
}