{
  "type": "Feature",
  "properties": {
    "iso:country":"GB",
    "sg:address":"54a High Street",
    "sg:city":"Shaftesbury",
    "sg:classifiers":[
        {
            "category":"Professional",
            "subcategory":"Accounting & Tax Preparation",
            "type":"Services"
        }
    ],
    "sg:phone":"+44 1747 52524",
    "sg:postcode":"SP7 8AA",
    "sg:province":"Dorset",
    "sg:tags":[
        "accountant"
    ],
    "wof:name":"Lanham & Francis",
    "wof:placetype":"venue"
},
  "geometry": {"coordinates":[-2.194429,51.006409],"type":"Point"}
}