{
  "type": "Feature",
  "properties": {
    "iso:country":"GB",
    "sg:address":"Glentoran, Hillcrest Drive, Ashington",
    "sg:city":"Pulborough",
    "sg:classifiers":[
        {
            "category":"Home & Garden",
            "subcategory":"Household Appliances",
            "type":"Retail Goods"
        }
    ],
    "sg:postcode":"RH20 3LB",
    "sg:province":"West Sussex",
    "sg:tags":[
        "electrical"
    ],
    "wof:name":"T R Kearney",
    "wof:placetype":"venue"
},
  "geometry": {"coordinates":[-0.389984,50.933418],"type":"Point"}
}