{
  "type": "Feature",
  "properties": {
    "addr:full":"39 Roseburn Street Edinburgh City of Edinburgh EH12 5PE",
    "addr:housenumber":"39",
    "addr:postcode":"eh12 5pe",
    "addr:street":"Roseburn Street",
    "iso:country":"GB",
    "sg:address":"39 Roseburn Street",
    "sg:city":"Edinburgh",
    "sg:classifiers":[
        {
            "category":"Retail",
            "subcategory":"Auto Rental",
            "type":"Services"
        }
    ],
    "sg:phone":"+44 131 337 8686",
    "sg:postcode":"EH12 5PE",
    "sg:province":"City of Edinburgh",
    "sg:tags":[
        "car"
    ],
    "wof:name":"National Car Rentals",
    "wof:placetype":"venue"
},
  "geometry": {"coordinates":[-3.2376270294,55.9422988892],"type":"Point"}
}