{
  "type": "Feature",
  "properties": {
    "iso:country":"GB",
    "sg:address":"Hilders Cliff",
    "sg:city":"Rye",
    "sg:classifiers":[
        {
            "category":"Travel",
            "subcategory":"Hotels & Motels",
            "type":"Entertainment"
        }
    ],
    "sg:phone":"+44 1797 223838",
    "sg:postcode":"TN31 7LD",
    "sg:province":"East Sussex",
    "wof:name":"Rye Lodge Ltd.",
    "wof:placetype":"venue"
},
  "geometry": {"coordinates":[0.735337019,50.9520187378],"type":"Point"}
}