{
  "type": "Feature",
  "properties": {
    "addr:full":"Coronation Street South Shields Tyne and Wear NE33 1AZ",
    "addr:postcode":"ne33 1az",
    "addr:street":"Coronation Street",
    "iso:country":"GB",
    "sg:address":"Coronation Street",
    "sg:city":"South Shields",
    "sg:classifiers":[
        {
            "category":"Autos & Motor Vehicles",
            "subcategory":"Auto Supplies",
            "type":"Retail Goods"
        }
    ],
    "sg:phone":"+44 191 455 5094",
    "sg:postcode":"NE33 1AZ",
    "sg:province":"Tyne and Wear",
    "sg:tags":[
        "tyre"
    ],
    "wof:name":"Sutherlands",
    "wof:placetype":"venue"
},
  "geometry": {"coordinates":[-1.4354840517,54.9966545105],"type":"Point"}
}