{
  "type": "Feature",
  "properties": {
    "iso:country":"GB",
    "sg:address":"36 Chester Av",
    "sg:city":"Poulton Le Fylde",
    "sg:classifiers":[
        {
            "category":"Home & Garden",
            "subcategory":"Home Furnishings",
            "type":"Retail Goods"
        }
    ],
    "sg:phone":"+44 1253 882240",
    "sg:postcode":"FY6 7RY",
    "sg:province":"Lancashire",
    "sg:tags":[
        "loose",
        "cover"
    ],
    "wof:name":"Biagi Upholstery",
    "wof:placetype":"venue"
},
  "geometry": {"coordinates":[-2.997641,53.84795],"type":"Point"}
}