{
  "type": "Feature",
  "properties": {
    "iso:country":"GB",
    "sg:address":"New Street",
    "sg:city":"Herne Bay",
    "sg:classifiers":[
        {
            "category":"Sports & Exercise",
            "subcategory":"Gym",
            "type":"Entertainment"
        }
    ],
    "sg:phone":"+44 1227 367111",
    "sg:postcode":"CT6 5AH",
    "sg:province":"Kent",
    "sg:tags":[
        "club",
        "fitness",
        "health",
        "centre"
    ],
    "wof:name":"Chequers Fitness Studio",
    "wof:placetype":"venue"
},
  "geometry": {"coordinates":[1.1293250322,51.371006012],"type":"Point"}
}