{
  "type": "Feature",
  "properties": {
    "addr:full":"3 Falcon Dr Crewe Cheshire CW1 3RX",
    "addr:housenumber":"3",
    "addr:postcode":"cw1 3rx",
    "addr:street":"Falcon Dr",
    "iso:country":"GB",
    "sg:address":"3 Falcon Dr",
    "sg:city":"Crewe",
    "sg:classifiers":[
        {
            "category":"Building & Trades",
            "subcategory":"Plumbing",
            "type":"Services"
        }
    ],
    "sg:postcode":"CW1 3RX",
    "sg:province":"Cheshire",
    "sg:tags":[
        "heating"
    ],
    "wof:name":"Swain,Mark,",
    "wof:placetype":"venue"
},
  "geometry": {"coordinates":[-2.453682,53.113888],"type":"Point"}
}