{
  "type": "Feature",
  "properties": {
    "addr:full":"Unit 10 The Elms Industrial Estate, Church Rd Romford Essex RM3 0JU",
    "addr:housenumber":"unit 10;estate",
    "addr:postcode":"rm3 0ju",
    "addr:street":"The Elms Industrial;Church Rd",
    "iso:country":"GB",
    "sg:address":"Unit 10 The Elms Industrial Estate, Church Rd",
    "sg:city":"Romford",
    "sg:classifiers":[
        {
            "category":"Home & Garden",
            "subcategory":"Building Materials",
            "type":"Retail Goods"
        }
    ],
    "sg:phone":"+44 1708 384574",
    "sg:postcode":"RM3 0JU",
    "sg:province":"Essex",
    "sg:tags":[
        "furnishers",
        "bathroom",
        "planner"
    ],
    "wof:name":"Metal Kris Ltd",
    "wof:placetype":"venue"
},
  "geometry": {"coordinates":[0.24528,51.599579],"type":"Point"}
}