{
  "type": "Feature",
  "properties": {
    "iso:country":"GB",
    "sg:address":"150 Seabrook Road",
    "sg:city":"Hythe",
    "sg:classifiers":[
        {
            "category":"Health Services",
            "subcategory":"Podiatrist",
            "type":"Services"
        }
    ],
    "sg:phone":"+44 1303 264190",
    "sg:postcode":"CT21 5RA",
    "sg:province":"Kent",
    "sg:tags":[
        "podiatrists",
        "chiropodist"
    ],
    "wof:name":"Debra Lawless",
    "wof:placetype":"venue"
},
  "geometry": {"coordinates":[1.1128400564,51.0721282959],"type":"Point"}
}