{
  "type": "Feature",
  "properties": {
    "addr:full":"Guild Hall Place, Off St Mary Street Cardiff Cardiff CF10 1DY",
    "addr:postcode":"cf10 1dy",
    "addr:street":"Hall Place Off St Mary Street",
    "iso:country":"GB",
    "sg:address":"Guild Hall Place, Off St Mary Street",
    "sg:city":"Cardiff",
    "sg:classifiers":[
        {
            "category":"Bars & Pubs",
            "type":"Food & Drink"
        }
    ],
    "sg:phone":"+44 29 2034 4511",
    "sg:postcode":"CF10 1DY",
    "sg:province":"Cardiff",
    "sg:tags":[
        "pubs",
        "inn"
    ],
    "wof:name":"The Retreat",
    "wof:placetype":"venue"
},
  "geometry": {"coordinates":[-3.179569,51.47937],"type":"Point"}
}