{
  "type": "Feature",
  "properties": {
    "addr:full":"Briscoe Community Centre, Felmores End Basildon Essex SS13 1PN",
    "addr:postcode":"ss13 1pn",
    "addr:street":"End",
    "iso:country":"GB",
    "sg:address":"Briscoe Community Centre, Felmores End",
    "sg:city":"Basildon",
    "sg:classifiers":[
        {
            "category":"Community Center",
            "type":"Public Place"
        }
    ],
    "sg:phone":"+44 1268 475101",
    "sg:postcode":"SS13 1PN",
    "sg:province":"Essex",
    "sg:tags":[
        "centre"
    ],
    "wof:name":"Briscoe Community Association",
    "wof:placetype":"venue"
},
  "geometry": {"coordinates":[0.5074099898,51.5785217285],"type":"Point"}
}