{
  "type": "Feature",
  "properties": {
    "iso:country":"GB",
    "sg:address":"Jockey Lane, Monks Cross Huntington",
    "sg:city":"York",
    "sg:classifiers":[
        {
            "category":"Retail",
            "subcategory":"Auto Repair",
            "type":"Services"
        }
    ],
    "sg:phone":"+44 1904 625371",
    "sg:postcode":"YO3 9GY",
    "sg:province":"East Riding of Yorkshire",
    "sg:tags":[
        "body",
        "car"
    ],
    "wof:name":"Polar Ford",
    "wof:placetype":"venue"
},
  "geometry": {"coordinates":[-1.06837,53.988232],"type":"Point"}
}