{
  "type": "Feature",
  "properties": {
    "addr:full":"West End House, 39 Legrams Lane Bradford West Yorkshire BD7 1NH",
    "addr:housenumber":"39",
    "addr:postcode":"bd7 1nh",
    "addr:street":"Legrams Lane",
    "iso:country":"GB",
    "sg:address":"West End House, 39 Legrams Lane",
    "sg:city":"Bradford",
    "sg:classifiers":[
        {
            "category":"Shopping",
            "subcategory":"Mobile Phones",
            "type":"Retail Goods"
        }
    ],
    "sg:phone":"+44 1274 724900",
    "sg:postcode":"BD7 1NH",
    "sg:province":"West Yorkshire",
    "wof:name":"Call Centre",
    "wof:placetype":"venue"
},
  "geometry": {"coordinates":[-1.772983,53.792522],"type":"Point"}
}