{
  "type": "Feature",
  "properties": {
    "iso:country":"GB",
    "sg:address":"Simon Charles Ho, 33 Chester Sq",
    "sg:city":"Ashton Under Lyne",
    "sg:classifiers":[
        {
            "category":"Professional",
            "type":"Services"
        }
    ],
    "sg:phone":"+44 161 330 1842",
    "sg:postcode":"OL6 7TW",
    "sg:province":"Greater Manchester",
    "sg:tags":[
        "auctioneer"
    ],
    "wof:name":"Simon Charles",
    "wof:placetype":"venue"
},
  "geometry": {"coordinates":[-2.088242,53.489239],"type":"Point"}
}