{
  "type": "Feature",
  "properties": {
    "addr:full":"107b Lansbury Drive Hayes Greater London UB4 8RP",
    "addr:housenumber":"107b",
    "addr:postcode":"ub4 8rp",
    "addr:street":"Lansbury Drive",
    "iso:country":"GB",
    "sg:address":"107b Lansbury Drive",
    "sg:city":"Hayes",
    "sg:classifiers":[
        {
            "category":"Banks & Credit Unions",
            "subcategory":"Bank",
            "type":"Services"
        },
        {
            "category":"Banks & Credit Unions",
            "subcategory":"Financial Services",
            "type":"Services"
        }
    ],
    "sg:phone":"+44 20 8848 1979",
    "sg:postcode":"UB4 8RP",
    "sg:province":"Greater London",
    "sg:tags":[
        "consultant",
        "institution"
    ],
    "wof:name":"C C Financial Services",
    "wof:placetype":"venue"
},
  "geometry": {"coordinates":[-0.4193589985,51.5263442993],"type":"Point"}
}