{
  "type": "Feature",
  "properties": {
    "iso:country":"GB",
    "sg:address":"3 Gayhurst Avenue, Fearnhead",
    "sg:city":"Warrington",
    "sg:classifiers":[
        {
            "category":"Real Estate",
            "subcategory":"Architect",
            "type":"Services"
        }
    ],
    "sg:postcode":"WA2 0AB",
    "sg:province":"Cheshire",
    "sg:tags":[
        "architectural"
    ],
    "wof:name":"Teal Design Services",
    "wof:placetype":"venue"
},
  "geometry": {"coordinates":[-2.5588920116,53.4124526978],"type":"Point"}
}