{
  "type": "Feature",
  "properties": {
    "iso:country":"GB",
    "sg:address":"530 Bexhill Road",
    "sg:city":"St Leonards-on-sea",
    "sg:classifiers":[
        {
            "category":"Bars & Pubs",
            "type":"Food & Drink"
        }
    ],
    "sg:phone":"+44 1424 424984",
    "sg:postcode":"TN38 8AY",
    "sg:province":"East Sussex",
    "sg:tags":[
        "pubs",
        "inn"
    ],
    "wof:name":"The Bull Inn",
    "wof:placetype":"venue"
},
  "geometry": {"coordinates":[0.510825,50.846291],"type":"Point"}
}