{
  "type": "Feature",
  "properties": {
    "iso:country":"GB",
    "sg:address":"32 St Marys Road",
    "sg:city":"Market Harborough",
    "sg:classifiers":[
        {
            "category":"Sports & Exercise",
            "subcategory":"Sports Center",
            "type":"Entertainment"
        }
    ],
    "sg:phone":"+44 1858 468464",
    "sg:postcode":"LE16 7DU",
    "sg:province":"Leicestershire",
    "sg:tags":[
        "shop",
        "good"
    ],
    "wof:name":"M D H Sports & Leisure",
    "wof:placetype":"venue"
},
  "geometry": {"coordinates":[-0.9176769853,52.4778785706],"type":"Point"}
}