{
  "type": "Feature",
  "properties": {
    "iso:country":"GB",
    "sg:address":"19 Massetts Road",
    "sg:city":"Horley",
    "sg:classifiers":[
        {
            "category":"Farming",
            "subcategory":"Nursery",
            "type":"Manufacturing & Wholesale Goods"
        }
    ],
    "sg:phone":"+44 1293 823500",
    "sg:postcode":"RH6 7DQ",
    "sg:province":"Surrey",
    "sg:tags":[
        "creche"
    ],
    "wof:name":"Little Jacks",
    "wof:placetype":"venue"
},
  "geometry": {"coordinates":[-0.1648299992,51.1708488464],"type":"Point"}
}