{
  "type": "Feature",
  "properties": {
    "addr:full":"Laployd Barton, Bridford Exeter Devon EX6 7LW",
    "addr:housenumber":"bridford",
    "addr:postcode":"ex6 7lw",
    "iso:country":"GB",
    "sg:address":"Laployd Barton, Bridford",
    "sg:city":"Exeter",
    "sg:classifiers":[
        {
            "category":"Farming",
            "subcategory":"Livestock Farm",
            "type":"Manufacturing & Wholesale Goods"
        }
    ],
    "sg:phone":"+44 1647 252356",
    "sg:postcode":"EX6 7LW",
    "sg:province":"Devon",
    "sg:tags":[
        "others"
    ],
    "wof:name":"J P Verdonck",
    "wof:placetype":"venue"
},
  "geometry": {"coordinates":[-3.6738460064,50.6656990051],"type":"Point"}
}