{
  "type": "Feature",
  "properties": {
    "addr:full":"50 High Street, Cricklade Swindon Gloucestershire SN6 6DA",
    "addr:housenumber":"50",
    "addr:postcode":"sn6 6da",
    "addr:street":"High Street",
    "iso:country":"GB",
    "sg:address":"50 High Street, Cricklade",
    "sg:city":"Swindon",
    "sg:classifiers":[
        {
            "category":"Bars & Pubs",
            "type":"Food & Drink"
        }
    ],
    "sg:phone":"+44 1793 750999",
    "sg:postcode":"SN6 6DA",
    "sg:province":"Gloucestershire",
    "sg:tags":[
        "pubs",
        "inn"
    ],
    "wof:name":"The White Lion",
    "wof:placetype":"venue"
},
  "geometry": {"coordinates":[-1.855597,51.642635],"type":"Point"}
}