{
  "type": "Feature",
  "properties": {
    "iso:country":"GB",
    "sg:address":"141 Bramhall Lane South, Bramhall",
    "sg:city":"Stockport",
    "sg:classifiers":[
        {
            "category":"Professional",
            "subcategory":"Management & Consulting",
            "type":"Services"
        },
        {
            "category":"Professional",
            "subcategory":"Computer Services",
            "type":"Services"
        }
    ],
    "sg:phone":"+44 161 440 8577",
    "sg:postcode":"SK7 2PP",
    "sg:province":"Cheshire",
    "sg:tags":[
        "information",
        "consultant",
        "business",
        "marketing"
    ],
    "wof:name":"MDC Global Ltd",
    "wof:placetype":"venue"
},
  "geometry": {"coordinates":[-2.1622641087,53.3682289124],"type":"Point"}
}