{
  "type": "Feature",
  "properties": {
    "iso:country":"GB",
    "sg:address":"5 North Mews",
    "sg:city":"Bloomsbury",
    "sg:classifiers":[
        {
            "category":"Building & Trades",
            "subcategory":"Plumbing",
            "type":"Services"
        }
    ],
    "sg:phone":"+44 20 7831 4829",
    "sg:postcode":"WC1N 2JP",
    "sg:province":"Greater London",
    "sg:tags":[
        "heating"
    ],
    "wof:name":"Holborn Plumbing Services",
    "wof:placetype":"venue"
},
  "geometry": {"coordinates":[-0.114577,51.522633],"type":"Point"}
}