{
  "type": "Feature",
  "properties": {
    "iso:country":"GB",
    "sg:address":"Moormeadow, Hunscote Lane, Wellesbourne",
    "sg:city":"Warwick",
    "sg:classifiers":[
        {
            "category":"Transit Center",
            "subcategory":"Passenger",
            "type":"Transportation"
        },
        {
            "category":"Retail",
            "subcategory":"Pet Boarding",
            "type":"Services"
        }
    ],
    "sg:phone":"+44 1789 840472",
    "sg:postcode":"CV35 9EX",
    "sg:province":"Warwickshire",
    "sg:tags":[
        "kennel",
        "catteries"
    ],
    "wof:name":"Hunscote Kennels & Cattery",
    "wof:placetype":"venue"
},
  "geometry": {"coordinates":[-1.6002260447,52.1912651062],"type":"Point"}
}