{
  "type": "Feature",
  "properties": {
    "iso:country":"GB",
    "sg:address":"Simonswood Industrial Park, Stopgate Lane, Knowsley",
    "sg:city":"Prescot",
    "sg:classifiers":[
        {
            "category":"Communications",
            "subcategory":"Film & Video Production",
            "type":"Services"
        }
    ],
    "sg:phone":"+44 151 545 1321",
    "sg:postcode":"L33 4YA",
    "sg:province":"Lancashire",
    "sg:tags":[
        "container"
    ],
    "wof:name":"Mersey Container Services Ltd.",
    "wof:placetype":"venue"
},
  "geometry": {"coordinates":[-2.86273,53.500118],"type":"Point"}
}