{
  "type": "Feature",
  "properties": {
    "iso:country":"GB",
    "sg:address":"Po Box 3",
    "sg:city":"London",
    "sg:classifiers":[
        {
            "category":"Organizations",
            "subcategory":"Non-profit Organization",
            "type":"Services"
        }
    ],
    "sg:phone":"+44 20 7377 4200",
    "sg:postcode":"E1 1WP",
    "sg:province":"Greater London",
    "sg:tags":[
        "organisation",
        "voluntary",
        "charity"
    ],
    "wof:name":"Muslim Aid",
    "wof:placetype":"venue"
},
  "geometry": {"coordinates":[-0.0580499992,51.5190010071],"type":"Point"}
}