{
  "type": "Feature",
  "properties": {
    "addr:full":"7 Mayflower Rd Southampton Hampshire SO15 3LU",
    "addr:housenumber":"7",
    "addr:postcode":"so15 3lu",
    "addr:street":"Mayflower Rd",
    "iso:country":"GB",
    "sg:address":"7 Mayflower Rd",
    "sg:city":"Southampton",
    "sg:classifiers":[
        {
            "category":"Professional",
            "subcategory":"Advertising",
            "type":"Services"
        }
    ],
    "sg:postcode":"SO15 3LU",
    "sg:province":"Hampshire",
    "sg:tags":[
        "agency"
    ],
    "wof:name":"David Nutley Advertising",
    "wof:placetype":"venue"
},
  "geometry": {"coordinates":[-1.432236,50.920715],"type":"Point"}
}