{
  "type": "Feature",
  "properties": {
    "addr:full":"35 Kelvin Gro Newcastle-upon-tyne Tyne and Wear NE2 1RL",
    "addr:housenumber":"35",
    "addr:postcode":"ne2 1rl",
    "addr:street":"Kelvin Gro",
    "iso:country":"GB",
    "sg:address":"35 Kelvin Gro",
    "sg:city":"Newcastle-upon-tyne",
    "sg:classifiers":[
        {
            "category":"Building & Trades",
            "subcategory":"Construction",
            "type":"Services"
        }
    ],
    "sg:phone":"+44 191 261 4587",
    "sg:postcode":"NE2 1RL",
    "sg:province":"Tyne and Wear",
    "sg:tags":[
        "decorator",
        "painter"
    ],
    "wof:name":"Trotter Enterprises",
    "wof:placetype":"venue"
},
  "geometry": {"coordinates":[-1.59807,54.98267],"type":"Point"}
}