{
  "type": "Feature",
  "properties": {
    "iso:country":"GB",
    "sg:address":"1 Montgomery St",
    "sg:city":"Edinburgh",
    "sg:classifiers":[
        {
            "category":"Shopping",
            "subcategory":"Department Store",
            "type":"Retail Goods"
        }
    ],
    "sg:postcode":"EH7 5JU",
    "sg:province":"City of Edinburgh",
    "wof:name":"Singh,Ranjitt,",
    "wof:placetype":"venue"
},
  "geometry": {"coordinates":[-3.1785271168,55.9594154358],"type":"Point"}
}