{
  "type": "Feature",
  "properties": {
    "iso:country":"GB",
    "sg:address":"Unit 5 Victoria Business Centre, Rochsolloch Rd",
    "sg:city":"Airdrie",
    "sg:classifiers":[
        {
            "category":"Building & Trades",
            "subcategory":"Construction",
            "type":"Services"
        }
    ],
    "sg:phone":"+44 1236 755490",
    "sg:postcode":"ML6 9BG",
    "sg:province":"North Lanarkshire",
    "sg:tags":[
        "decorator",
        "painter"
    ],
    "wof:name":"S Broadley",
    "wof:placetype":"venue"
},
  "geometry": {"coordinates":[-3.9994499683,55.85987854],"type":"Point"}
}