{
  "type": "Feature",
  "properties": {
    "iso:country":"GB",
    "sg:address":"Unit 17a Dominion Indust Est, Dominion Rd",
    "sg:city":"Southall",
    "sg:classifiers":[
        {
            "category":"Manufacturing",
            "subcategory":"Signs",
            "type":"Manufacturing & Wholesale Goods"
        }
    ],
    "sg:phone":"+44 20 8893 9943",
    "sg:postcode":"UB2 5DP",
    "sg:province":"Greater London",
    "sg:tags":[
        "nameplate"
    ],
    "wof:name":"Fine Art Studio",
    "wof:placetype":"venue"
},
  "geometry": {"coordinates":[-0.3833090067,51.5033531189],"type":"Point"}
}