{
  "type": "Feature",
  "properties": {
    "iso:country":"GB",
    "sg:address":"Cannon St",
    "sg:city":"Accrington",
    "sg:classifiers":[
        {
            "category":"Place Of Worship",
            "type":"Public Place"
        }
    ],
    "sg:phone":"+44 1254 393742",
    "sg:postcode":"BB5 1NJ",
    "sg:province":"Lancashire",
    "wof:name":"Cannon Street Baptist Church",
    "wof:placetype":"venue"
},
  "geometry": {"coordinates":[-2.367358923,53.7522010803],"type":"Point"}
}