{
  "type": "Feature",
  "properties": {
    "addr:full":"Bridge Ho Bethlehem Rd Llandeilo Carmarthenshire SA19 6SY",
    "addr:postcode":"sa19 6sy",
    "addr:street":"Bethlehem Rd",
    "iso:country":"GB",
    "sg:address":"Bridge Ho Bethlehem Rd",
    "sg:city":"Llandeilo",
    "sg:classifiers":[
        {
            "category":"Home & Garden",
            "subcategory":"Carpets & Floor Coverings",
            "type":"Retail Goods"
        }
    ],
    "sg:phone":"+44 1558 823800",
    "sg:postcode":"SA19 6SY",
    "sg:province":"Carmarthenshire",
    "sg:tags":[
        "cleaner",
        "upholstery"
    ],
    "wof:name":"Chem Dry",
    "wof:placetype":"venue"
},
  "geometry": {"coordinates":[-3.991857,51.884136],"type":"Point"}
}