{
  "type": "Feature",
  "properties": {
    "iso:country":"GB",
    "sg:address":"The Old Bell House, Alveley",
    "sg:city":"Bridgnorth",
    "sg:classifiers":[
        {
            "category":"Home & Garden",
            "subcategory":"Home Furnishings",
            "type":"Retail Goods"
        }
    ],
    "sg:phone":"+44 1746 780860",
    "sg:postcode":"WV15 6NE",
    "sg:province":"Shropshire",
    "sg:tags":[
        "blind",
        "curtain",
        "fitting"
    ],
    "wof:name":"Sheridan Fabrics",
    "wof:placetype":"venue"
},
  "geometry": {"coordinates":[-2.34337,52.458767],"type":"Point"}
}