{
  "type": "Feature",
  "properties": {
    "iso:country":"GB",
    "sg:address":"145 Godstone Road",
    "sg:city":"Whyteleafe",
    "sg:classifiers":[
        {
            "category":"Manufacturing",
            "subcategory":"Signs",
            "type":"Manufacturing & Wholesale Goods"
        }
    ],
    "sg:phone":"+44 20 8667 9966",
    "sg:postcode":"CR3 0EH",
    "sg:province":"Surrey",
    "sg:tags":[
        "maker"
    ],
    "wof:name":"Plotter Technology Ltd.",
    "wof:placetype":"venue"
},
  "geometry": {"coordinates":[-0.079961,51.311211],"type":"Point"}
}