{
  "type": "Feature",
  "properties": {
    "iso:country":"GB",
    "sg:address":"5 Hadfield Clo",
    "sg:city":"Widnes",
    "sg:classifiers":[
        {
            "category":"Retail",
            "subcategory":"Auto Repair",
            "type":"Services"
        }
    ],
    "sg:phone":"+44 151 420 5368",
    "sg:postcode":"WA8 0BD",
    "sg:province":"Cheshire",
    "sg:tags":[
        "modification",
        "garage"
    ],
    "wof:name":"Widnes Carburettors",
    "wof:placetype":"venue"
},
  "geometry": {"coordinates":[-2.7332439423,53.3740310669],"type":"Point"}
}