{
  "type": "Feature",
  "properties": {
    "addr:full":"1 Craigpark Glasgow Glasgow City G31 2NF",
    "addr:housenumber":"1",
    "addr:postcode":"g31 2nf",
    "addr:street":"Craigpark",
    "iso:country":"GB",
    "sg:address":"1 Craigpark",
    "sg:city":"Glasgow",
    "sg:classifiers":[
        {
            "category":"Fast Food",
            "type":"Food & Drink"
        }
    ],
    "sg:postcode":"G31 2NF",
    "sg:province":"Glasgow City",
    "sg:tags":[
        "away",
        "take"
    ],
    "wof:name":"Morgan,Adam,",
    "wof:placetype":"venue"
},
  "geometry": {"coordinates":[-4.222063,55.858952],"type":"Point"}
}