{
  "type": "Feature",
  "properties": {
    "iso:country":"GB",
    "sg:address":"22c Vyse Street, Hockley",
    "sg:city":"Birmingham",
    "sg:classifiers":[
        {
            "category":"Shopping",
            "subcategory":"Jewelry",
            "type":"Retail Goods"
        },
        {
            "category":"Manufacturing",
            "subcategory":"Jewelry",
            "type":"Manufacturing & Wholesale Goods"
        }
    ],
    "sg:phone":"+44 121 551 7360",
    "sg:postcode":"B18 6LE",
    "sg:province":"West Midlands",
    "sg:tags":[
        "repair",
        "sale",
        "jewellery"
    ],
    "wof:name":"David T Nutt",
    "wof:placetype":"venue"
},
  "geometry": {"coordinates":[-1.91276,52.488922],"type":"Point"}
}