{
  "type": "Feature",
  "properties": {
    "addr:full":"Woods Close, Stanford Bishop Worcester Herefordshire WR6 5UB",
    "addr:postcode":"wr6 5ub",
    "addr:street":"Woods Close",
    "iso:country":"GB",
    "sg:address":"Woods Close, Stanford Bishop",
    "sg:city":"Worcester",
    "sg:classifiers":[
        {
            "category":"Freight",
            "type":"Transportation"
        }
    ],
    "sg:phone":"+44 1886 884382",
    "sg:postcode":"WR6 5UB",
    "sg:province":"Herefordshire",
    "sg:tags":[
        "haulage",
        "road"
    ],
    "wof:name":"W Matthews Transport",
    "wof:placetype":"venue"
},
  "geometry": {"coordinates":[-2.4510700703,52.1745910645],"type":"Point"}
}