{
  "type": "Feature",
  "properties": {
    "addr:full":"7 Palk St Torquay Devon TQ2 5EL",
    "addr:housenumber":"7",
    "addr:postcode":"tq2 5el",
    "addr:street":"Palk St",
    "iso:country":"GB",
    "sg:address":"7 Palk St",
    "sg:city":"Torquay",
    "sg:classifiers":[
        {
            "category":"Social Services",
            "type":"Services"
        }
    ],
    "sg:postcode":"TQ2 5EL",
    "sg:province":"Devon",
    "sg:tags":[
        "need",
        "disability",
        "special"
    ],
    "wof:name":"Complete Care",
    "wof:placetype":"venue"
},
  "geometry": {"coordinates":[-3.5256888866,50.4615097046],"type":"Point"}
}