{
  "type": "Feature",
  "properties": {
    "addr:full":"82 Waverdale Way South Shields Tyne and Wear NE33 4SJ",
    "addr:housenumber":"82",
    "addr:postcode":"ne33 4sj",
    "addr:street":"Waverdale Way",
    "iso:country":"GB",
    "sg:address":"82 Waverdale Way",
    "sg:city":"South Shields",
    "sg:classifiers":[
        {
            "category":"Shopping",
            "subcategory":"Musical Instruments",
            "type":"Retail Goods"
        }
    ],
    "sg:phone":"+44 191 454 1244",
    "sg:postcode":"NE33 4SJ",
    "sg:province":"Tyne and Wear",
    "sg:tags":[
        "piano",
        "tuning",
        "maintenance"
    ],
    "wof:name":"Michael Swann",
    "wof:placetype":"venue"
},
  "geometry": {"coordinates":[-1.4413319826,54.9777488708],"type":"Point"}
}