{
  "type": "Feature",
  "properties": {
    "addr:full":"14 Cain Lane, Southowram Halifax West Yorkshire HX3 9SB",
    "addr:housenumber":"14",
    "addr:postcode":"hx3 9sb",
    "addr:street":"Cain Lane",
    "iso:country":"GB",
    "sg:address":"14 Cain Lane, Southowram",
    "sg:city":"Halifax",
    "sg:classifiers":[
        {
            "category":"Bars & Pubs",
            "type":"Food & Drink"
        }
    ],
    "sg:phone":"+44 1422 361101",
    "sg:postcode":"HX3 9SB",
    "sg:province":"West Yorkshire",
    "sg:tags":[
        "pubs",
        "inn"
    ],
    "wof:name":"The Shoulder of Mutton",
    "wof:placetype":"venue"
},
  "geometry": {"coordinates":[-1.8307980299,53.7098770142],"type":"Point"}
}