{
  "type": "Feature",
  "properties": {
    "addr:full":"26 The Hornet Chichester West Sussex PO19 7JG",
    "addr:housenumber":"26",
    "addr:postcode":"po19 7jg",
    "addr:street":"The Hornet",
    "iso:country":"GB",
    "sg:address":"26 The Hornet",
    "sg:city":"Chichester",
    "sg:classifiers":[
        {
            "category":"Personal",
            "subcategory":"Beauty Salon",
            "type":"Services"
        }
    ],
    "sg:postcode":"PO19 7JG",
    "sg:province":"West Sussex",
    "sg:tags":[
        "unisex",
        "hairdresser"
    ],
    "wof:name":"Michael Kent",
    "wof:placetype":"venue"
},
  "geometry": {"coordinates":[-0.7725909948,50.8360824585],"type":"Point"}
}