{
  "type": "Feature",
  "properties": {
    "addr:full":"Ventureforth House, South Denes Road Great Yarmouth Norfolk NR30 3PT",
    "addr:postcode":"nr30 3pt",
    "addr:street":"South Denes Road",
    "iso:country":"GB",
    "sg:address":"Ventureforth House, South Denes Road",
    "sg:city":"Great Yarmouth",
    "sg:classifiers":[
        {
            "category":"Professional",
            "type":"Services"
        }
    ],
    "sg:phone":"+44 1493 332031",
    "sg:postcode":"NR30 3PT",
    "sg:province":"Norfolk",
    "sg:tags":[
        "shopfitters"
    ],
    "wof:name":"Chameleon Projects Ltd.",
    "wof:placetype":"venue"
},
  "geometry": {"coordinates":[1.73058,52.587502],"type":"Point"}
}