{
  "type": "Feature",
  "properties": {
    "iso:country":"GB",
    "sg:address":"Ermin House, Bristol Road",
    "sg:city":"Gloucester",
    "sg:classifiers":[
        {
            "category":"Professional",
            "subcategory":"Detective & Security Services",
            "type":"Services"
        }
    ],
    "sg:phone":"+44 1452 417100",
    "sg:postcode":"GL2 5DF",
    "sg:province":"Gloucestershire",
    "sg:tags":[
        "equipment",
        "installers"
    ],
    "wof:name":"Monark Ltd.",
    "wof:placetype":"venue"
},
  "geometry": {"coordinates":[-2.261968,51.846905],"type":"Point"}
}