{
  "type": "Feature",
  "properties": {
    "addr:full":"Hilltop Farm Brockenhurst Hampshire SO42 7YR",
    "addr:housenumber":"brockenhurst",
    "addr:postcode":"so42 7yr",
    "addr:street":"Hampshire",
    "iso:country":"GB",
    "sg:address":"Hilltop Farm",
    "sg:city":"Brockenhurst",
    "sg:classifiers":[
        {
            "category":"Building & Trades",
            "subcategory":"Construction",
            "type":"Services"
        }
    ],
    "sg:phone":"+44 1590 612074",
    "sg:postcode":"SO42 7YR",
    "sg:province":"Hampshire",
    "sg:tags":[
        "builder"
    ],
    "wof:name":"Norris & Taylor",
    "wof:placetype":"venue"
},
  "geometry": {"coordinates":[-1.5720039606,50.8186416626],"type":"Point"}
}