{
  "type": "Feature",
  "properties": {
    "iso:country":"GB",
    "sg:address":"Adamson House, Pomona Docks",
    "sg:city":"Manchester",
    "sg:classifiers":[
        {
            "category":"Manufacturing",
            "subcategory":"Electronics",
            "type":"Manufacturing & Wholesale Goods"
        }
    ],
    "sg:phone":"+44 161 877 8844",
    "sg:postcode":"M15 4NE",
    "sg:province":"Cheshire",
    "sg:tags":[
        "control",
        "component",
        "-",
        "electronic"
    ],
    "wof:name":"Future Active Industries",
    "wof:placetype":"venue"
},
  "geometry": {"coordinates":[-2.26977,53.469398],"type":"Point"}
}