{
  "type": "Feature",
  "properties": {
    "addr:full":"16 Timberley Lane Birmingham West Midlands B34 7EH",
    "addr:housenumber":"16",
    "addr:postcode":"7eh",
    "addr:street":"Timberley Lane",
    "iso:country":"GB",
    "sg:address":"16 Timberley Lane",
    "sg:city":"Birmingham",
    "sg:classifiers":[
        {
            "category":"Shopping",
            "subcategory":"Pharmacy",
            "type":"Retail Goods"
        }
    ],
    "sg:phone":"+44 121 748 1501",
    "sg:postcode":"B34 7EH",
    "sg:province":"West Midlands",
    "sg:tags":[
        "pharmacist",
        "dispensing",
        "chemist"
    ],
    "wof:name":"Chesteers Pharmacy",
    "wof:placetype":"venue"
},
  "geometry": {"coordinates":[-1.7713630199,52.5011711121],"type":"Point"}
}