{
  "type": "Feature",
  "properties": {
    "addr:full":"90a Montpelier Rd Peckham Greater London SE15 2HE",
    "addr:housenumber":"90a",
    "addr:postcode":"se15 2he",
    "addr:street":"Montpelier Rd",
    "iso:country":"GB",
    "sg:address":"90a Montpelier Rd",
    "sg:city":"Peckham",
    "sg:classifiers":[
        {
            "category":"Professional",
            "subcategory":"Advertising",
            "type":"Services"
        }
    ],
    "sg:phone":"+44 20 7732 1015",
    "sg:postcode":"SE15 2HE",
    "sg:province":"Greater London",
    "sg:tags":[
        "mail",
        "direct"
    ],
    "wof:name":"Quality Mailings",
    "wof:placetype":"venue"
},
  "geometry": {"coordinates":[-0.0596720017,51.476688385],"type":"Point"}
}