{
  "type": "Feature",
  "properties": {
    "iso:country":"GB",
    "sg:address":"11 Denman Drive",
    "sg:city":"Ashford",
    "sg:classifiers":[
        {
            "category":"Professional",
            "subcategory":"Art Services",
            "type":"Services"
        }
    ],
    "sg:phone":"+44 1784 256422",
    "sg:postcode":"TW15 2AN",
    "sg:province":"Greater London",
    "sg:tags":[
        "photographer"
    ],
    "wof:name":"Clifford Tanner Photography",
    "wof:placetype":"venue"
},
  "geometry": {"coordinates":[-0.452153,51.42485],"type":"Point"}
}