{
  "type": "Feature",
  "properties": {
    "addr:full":"12 High Street Haverhill Essex CB9 8AR",
    "addr:housenumber":"12",
    "addr:postcode":"cb9 8ar",
    "addr:street":"High Street",
    "iso:country":"GB",
    "sg:address":"12 High Street",
    "sg:city":"Haverhill",
    "sg:classifiers":[
        {
            "category":"Professional",
            "subcategory":"Business Services",
            "type":"Services"
        }
    ],
    "sg:phone":"+44 1440 714798",
    "sg:postcode":"CB9 8AR",
    "sg:province":"Essex",
    "sg:tags":[
        "import",
        "export",
        "agent"
    ],
    "wof:name":"Pets & Plants",
    "wof:placetype":"venue"
},
  "geometry": {"coordinates":[0.4394409955,52.0818328857],"type":"Point"}
}