{
  "type": "Feature",
  "properties": {
    "iso:country":"GB",
    "sg:address":"33 Bond Street",
    "sg:city":"Blackpool",
    "sg:classifiers":[
        {
            "category":"Personal",
            "subcategory":"Beauty Salon",
            "type":"Services"
        }
    ],
    "sg:postcode":"FY4 1BQ",
    "sg:province":"Lancashire",
    "sg:tags":[
        "unisex",
        "hairdresser"
    ],
    "wof:name":"Classy Set",
    "wof:placetype":"venue"
},
  "geometry": {"coordinates":[-3.054272,53.797756],"type":"Point"}
}