{
  "type": "Feature",
  "properties": {
    "iso:country":"GB",
    "sg:address":"King House, Ludlow Road",
    "sg:city":"Redditch",
    "sg:classifiers":[
        {
            "category":"Professional",
            "subcategory":"Engineering",
            "type":"Services"
        }
    ],
    "sg:phone":"+44 1527 591120",
    "sg:postcode":"B97 4EN",
    "sg:province":"Warwickshire",
    "sg:tags":[
        "design",
        "engineer"
    ],
    "wof:name":"Peter Court",
    "wof:placetype":"venue"
},
  "geometry": {"coordinates":[-1.942704,52.302784],"type":"Point"}
}