{
  "type": "Feature",
  "properties": {
    "iso:country":"GB",
    "sg:address":"81 Caxton End, Bourn",
    "sg:city":"Cambridge",
    "sg:classifiers":[
        {
            "category":"Building & Trades",
            "subcategory":"Construction",
            "type":"Services"
        }
    ],
    "sg:phone":"+44 1954 719795",
    "sg:postcode":"CB3 7SS",
    "sg:province":"Cambridgeshire",
    "sg:tags":[
        "joiner",
        "carpenter"
    ],
    "wof:name":"Nicole & Price",
    "wof:placetype":"venue"
},
  "geometry": {"coordinates":[-0.069159,52.19529],"type":"Point"}
}