{
  "type": "Feature",
  "properties": {
    "addr:full":"112 Wyke Cop Road, Scarisbrick Southport Lancashire PR8 5LS",
    "addr:housenumber":"112",
    "addr:postcode":"pr8 5ls",
    "addr:street":"Wyke Cop Road",
    "iso:country":"GB",
    "sg:address":"112 Wyke Cop Road, Scarisbrick",
    "sg:city":"Southport",
    "sg:classifiers":[
        {
            "category":"Building & Trades",
            "subcategory":"Construction",
            "type":"Services"
        }
    ],
    "sg:phone":"+44 1704 880670",
    "sg:postcode":"PR8 5LS",
    "sg:province":"Lancashire",
    "sg:tags":[
        "roofing"
    ],
    "wof:name":"Sean Lea Roofing Specialist",
    "wof:placetype":"venue"
},
  "geometry": {"coordinates":[-2.9392530918,53.6240272522],"type":"Point"}
}