{
  "type": "Feature",
  "properties": {
    "iso:country":"GB",
    "sg:address":"Nantwich Rd",
    "sg:city":"Crewe",
    "sg:classifiers":[
        {
            "category":"Restaurant",
            "type":"Food & Drink"
        }
    ],
    "sg:phone":"+44 1270 662326",
    "sg:postcode":"CW2 6PB",
    "sg:province":"Cheshire",
    "wof:name":"Ye Olde Manor",
    "wof:placetype":"venue"
},
  "geometry": {"coordinates":[-2.4387640953,53.0888748169],"type":"Point"}
}