{
  "type": "Feature",
  "properties": {
    "iso:country":"GB",
    "sg:address":"1b School Lane, Didsbury",
    "sg:city":"Manchester",
    "sg:classifiers":[
        {
            "category":"Health Services",
            "subcategory":"Dentist",
            "type":"Services"
        }
    ],
    "sg:phone":"+44 161 445 5459",
    "sg:postcode":"M20 6RD",
    "sg:province":"Greater Manchester",
    "wof:name":"N M & M J Owen",
    "wof:placetype":"venue"
},
  "geometry": {"coordinates":[-2.2289919853,53.4174919128],"type":"Point"}
}