{
  "type": "Feature",
  "properties": {
    "iso:country":"GB",
    "sg:address":"32-34 High Street",
    "sg:city":"Denbigh",
    "sg:classifiers":[
        {
            "category":"Home & Garden",
            "subcategory":"Hardware",
            "type":"Retail Goods"
        }
    ],
    "sg:phone":"+44 1745 814875",
    "sg:postcode":"LL16 3RY",
    "sg:province":"Conwy",
    "sg:tags":[
        "shop",
        "retailer",
        "diy"
    ],
    "wof:name":"W Bevan & Sons Ltd",
    "wof:placetype":"venue"
},
  "geometry": {"coordinates":[-3.4200439453,53.1834259033],"type":"Point"}
}