{
  "type": "Feature",
  "properties": {
    "iso:country":"GB",
    "sg:address":"The Old Telephone Exchange, Common Lane, Culcheth",
    "sg:city":"Warrington",
    "sg:classifiers":[
        {
            "category":"Personal",
            "subcategory":"Nail Salon",
            "type":"Services"
        }
    ],
    "sg:phone":"+44 1925 767676",
    "sg:postcode":"WA3 4HA",
    "sg:province":"Cheshire",
    "sg:tags":[
        "solarium",
        "tanning"
    ],
    "wof:name":"Culcheth Sun Centre Ltd.",
    "wof:placetype":"venue"
},
  "geometry": {"coordinates":[-2.5228729248,53.4537353516],"type":"Point"}
}