{
  "type": "Feature",
  "properties": {
    "iso:country":"GB",
    "sg:address":"347 Brighton Road",
    "sg:city":"South Croydon",
    "sg:classifiers":[
        {
            "category":"Organizations",
            "subcategory":"Non-profit Organization",
            "type":"Services"
        }
    ],
    "sg:phone":"+44 20 8662 8674",
    "sg:postcode":"CR2 6ER",
    "sg:province":"Surrey",
    "sg:tags":[
        "alarm",
        "system"
    ],
    "wof:name":"Security Direct Ltd.",
    "wof:placetype":"venue"
},
  "geometry": {"coordinates":[-0.098814,51.351494],"type":"Point"}
}