{
  "type": "Feature",
  "properties": {
    "iso:country":"GB",
    "sg:address":"18 Watford Road",
    "sg:city":"Wembley",
    "sg:classifiers":[
        {
            "category":"Restaurant",
            "type":"Food & Drink"
        }
    ],
    "sg:phone":"+44 20 8904 7848",
    "sg:postcode":"HA0 3EP",
    "sg:province":"Greater London",
    "sg:tags":[
        "ethiopian",
        "-"
    ],
    "wof:name":"The Seasons Restaurant",
    "wof:placetype":"venue"
},
  "geometry": {"coordinates":[-0.316971,51.556679],"type":"Point"}
}