{
  "type": "Feature",
  "properties": {
    "iso:country":"GB",
    "sg:address":"Box Cottage, Chawston",
    "sg:city":"Bedford",
    "sg:classifiers":[
        {
            "category":"Retail",
            "subcategory":"Auto Repair",
            "type":"Services"
        }
    ],
    "sg:postcode":"MK44 2BH",
    "sg:province":"Bedfordshire",
    "sg:tags":[
        "modification",
        "garage"
    ],
    "wof:name":"Hudson Motors",
    "wof:placetype":"venue"
},
  "geometry": {"coordinates":[-0.38291,52.251789],"type":"Point"}
}