{
  "type": "Feature",
  "properties": {
    "iso:country":"GB",
    "sg:address":"59 Victoria Rd",
    "sg:city":"St. Austell",
    "sg:classifiers":[
        {
            "category":"Cinema",
            "subcategory":"Movie Rental",
            "type":"Entertainment"
        }
    ],
    "sg:phone":"+44 1726 65521",
    "sg:postcode":"PL25 4QF",
    "sg:province":"Cornwall",
    "sg:tags":[
        "video",
        "library"
    ],
    "wof:name":"CARLYON VIDEO",
    "wof:placetype":"venue"
},
  "geometry": {"coordinates":[-4.776135,50.33844],"type":"Point"}
}