{
  "type": "Feature",
  "properties": {
    "addr:full":"Commerce Court, Challenge Way, Cutler Heights Lane Bradford West Yorkshire BD4 8NW",
    "addr:postcode":"bd4 8nw",
    "addr:street":"Commerce;Challenge Way Cutler Heights Lane",
    "iso:country":"GB",
    "sg:address":"Commerce Court, Challenge Way, Cutler Heights Lane",
    "sg:city":"Bradford",
    "sg:classifiers":[
        {
            "category":"Real Estate",
            "subcategory":"Real Estate Agent",
            "type":"Services"
        }
    ],
    "sg:phone":"+44 1274 667266",
    "sg:postcode":"BD4 8NW",
    "sg:province":"West Yorkshire",
    "wof:name":"Commerce Court Ltd.",
    "wof:placetype":"venue"
},
  "geometry": {"coordinates":[-1.7164800167,53.7829399109],"type":"Point"}
}