{
  "type": "Feature",
  "properties": {
    "addr:full":"Woodland Terrace, Maesycoed Pontypridd Caerphilly CF37 1HZ",
    "addr:postcode":"cf37 1hz",
    "addr:street":"Woodland Terrace Maesycoed",
    "iso:country":"GB",
    "sg:address":"Woodland Terrace, Maesycoed",
    "sg:city":"Pontypridd",
    "sg:classifiers":[
        {
            "category":"Professional",
            "subcategory":"Business Services",
            "type":"Services"
        }
    ],
    "sg:phone":"+44 1443 403031",
    "sg:postcode":"CF37 1HZ",
    "sg:province":"Caerphilly",
    "sg:tags":[
        "bookmaker"
    ],
    "wof:name":"Roger Thomas",
    "wof:placetype":"venue"
},
  "geometry": {"coordinates":[-3.3309590816,51.5975494385],"type":"Point"}
}