{
  "type": "Feature",
  "properties": {
    "addr:full":"14 North La Bedford Bedfordshire MK45 3PW",
    "addr:housenumber":"14",
    "addr:postcode":"mk45 3pw",
    "addr:street":"North La",
    "iso:country":"GB",
    "sg:address":"14 North La",
    "sg:city":"Bedford",
    "sg:classifiers":[
        {
            "category":"Recreation",
            "subcategory":"Dog Park",
            "type":"Entertainment"
        }
    ],
    "sg:phone":"+44 1234 381493",
    "sg:postcode":"MK45 3PW",
    "sg:province":"Bedfordshire",
    "wof:name":"Animal Crackers",
    "wof:placetype":"venue"
},
  "geometry": {"coordinates":[-0.4043720067,52.0686187744],"type":"Point"}
}