{
  "type": "Feature",
  "properties": {
    "iso:country":"GB",
    "sg:address":"8 Lawrance Road",
    "sg:city":"St Albans",
    "sg:classifiers":[
        {
            "category":"Building & Trades",
            "subcategory":"Cleaning & Sanitation",
            "type":"Services"
        }
    ],
    "sg:phone":"+44 7768 611275",
    "sg:postcode":"AL3 6EA",
    "sg:province":"Hertfordshire",
    "sg:tags":[
        "contracting",
        "commercial"
    ],
    "wof:name":"Thompson Cleaning Services",
    "wof:placetype":"venue"
},
  "geometry": {"coordinates":[-0.34512,51.769196],"type":"Point"}
}