{
  "type": "Feature",
  "properties": {
    "addr:full":"2 Elmwood Chase, Barwick In Elmet Leeds West Yorkshire LS15 4JZ",
    "addr:housenumber":"2",
    "addr:postcode":"ls15 4jz",
    "addr:street":"Elmwood Chase;West",
    "iso:country":"GB",
    "sg:address":"2 Elmwood Chase, Barwick In Elmet",
    "sg:city":"Leeds",
    "sg:classifiers":[
        {
            "category":"Retail",
            "subcategory":"Storage",
            "type":"Services"
        }
    ],
    "sg:phone":"+44 113 281 2027",
    "sg:postcode":"LS15 4JZ",
    "sg:province":"West Yorkshire",
    "sg:tags":[
        "shelving",
        "system"
    ],
    "wof:name":"D C M Associates",
    "wof:placetype":"venue"
},
  "geometry": {"coordinates":[-1.395822,53.830879],"type":"Point"}
}