{
  "type": "Feature",
  "properties": {
    "addr:full":"11 The Ride, Leedon Leighton Buzzard Bedfordshire LU7 3LL",
    "addr:housenumber":"11",
    "addr:postcode":"lu7 3ll",
    "addr:street":"The;Leedon",
    "iso:country":"GB",
    "sg:address":"11 The Ride, Leedon",
    "sg:city":"Leighton Buzzard",
    "sg:classifiers":[
        {
            "category":"Home & Garden",
            "subcategory":"Carpets & Floor Coverings",
            "type":"Retail Goods"
        }
    ],
    "sg:postcode":"LU7 3LL",
    "sg:province":"Bedfordshire",
    "sg:tags":[
        "cleaner",
        "upholstery"
    ],
    "wof:name":"Trueclean",
    "wof:placetype":"venue"
},
  "geometry": {"coordinates":[-0.6362230182,51.9203681946],"type":"Point"}
}