{
  "type": "Feature",
  "properties": {
    "addr:full":"2 Priory St Milford Haven Pembrokeshire SA73 2AD",
    "addr:housenumber":"2",
    "addr:postcode":"sa73 2ad",
    "addr:street":"Priory St",
    "iso:country":"GB",
    "sg:address":"2 Priory St",
    "sg:city":"Milford Haven",
    "sg:classifiers":[
        {
            "category":"Professional",
            "subcategory":"Lawyer & Legal Services",
            "type":"Services"
        }
    ],
    "sg:phone":"+44 1646 690327",
    "sg:postcode":"SA73 2AD",
    "sg:province":"Pembrokeshire",
    "sg:tags":[
        "advice",
        "counselling"
    ],
    "wof:name":"Pembrokeshire Drug Advice Service",
    "wof:placetype":"venue"
},
  "geometry": {"coordinates":[-5.03566,51.713703],"type":"Point"}
}