{
  "type": "Feature",
  "properties": {
    "addr:full":"Greenbank, Old Greasby Road, Upton Wirral Merseyside CH49 6NS",
    "addr:postcode":"ch49 6ns",
    "addr:street":"Old Greasby Road",
    "iso:country":"GB",
    "sg:address":"Greenbank, Old Greasby Road, Upton",
    "sg:city":"Wirral",
    "sg:classifiers":[
        {
            "category":"Retail",
            "subcategory":"Funeral Services",
            "type":"Services"
        }
    ],
    "sg:phone":"+44 151 678 9944",
    "sg:postcode":"CH49 6NS",
    "sg:province":"Merseyside",
    "sg:tags":[
        "director"
    ],
    "wof:name":"Alex Taylor",
    "wof:placetype":"venue"
},
  "geometry": {"coordinates":[-3.103714,53.384338],"type":"Point"}
}