{
  "type": "Feature",
  "properties": {
    "addr:full":"19 Market Place Dereham Norfolk NR19 2AX",
    "addr:housenumber":"19",
    "addr:postcode":"nr19 2ax",
    "addr:street":"Market Place Dereham",
    "iso:country":"GB",
    "sg:address":"19 Market Place",
    "sg:city":"Dereham",
    "sg:classifiers":[
        {
            "category":"Bakery",
            "type":"Food & Drink"
        }
    ],
    "sg:phone":"+44 1362 698440",
    "sg:postcode":"NR19 2AX",
    "sg:province":"Norfolk",
    "sg:tags":[
        "cake",
        "maker"
    ],
    "wof:name":"Russell's of Dereham",
    "wof:placetype":"venue"
},
  "geometry": {"coordinates":[0.9455890059,52.6801681519],"type":"Point"}
}