{
  "type": "Feature",
  "properties": {
    "addr:full":"35 The Hedgerows, Northfleet Gravesend Kent DA11 8BE",
    "addr:housenumber":"35",
    "addr:postcode":"da11 8be",
    "addr:street":"The Hedgerows Northfleet",
    "iso:country":"GB",
    "sg:address":"35 The Hedgerows, Northfleet",
    "sg:city":"Gravesend",
    "sg:classifiers":[
        {
            "category":"Retail",
            "subcategory":"Repair Shop",
            "type":"Services"
        },
        {
            "category":"Manufacturing",
            "subcategory":"Building Materials",
            "type":"Manufacturing & Wholesale Goods"
        }
    ],
    "sg:phone":"+44 1474 323323",
    "sg:postcode":"DA11 8BE",
    "sg:province":"Kent",
    "sg:tags":[
        "shutter",
        "supp",
        "door"
    ],
    "wof:name":"Crown Industrial Door Engineers",
    "wof:placetype":"venue"
},
  "geometry": {"coordinates":[0.346426,51.428802],"type":"Point"}
}