{
  "type": "Feature",
  "properties": {
    "addr:full":"136-144 Freeman Street Grimsby Lincolnshire DN32 7AN",
    "addr:housenumber":"136-144",
    "addr:postcode":"dn32 7an",
    "addr:street":"Freeman Street",
    "iso:country":"GB",
    "sg:address":"136-144 Freeman Street",
    "sg:city":"Grimsby",
    "sg:classifiers":[
        {
            "category":"Home & Garden",
            "subcategory":"Household Appliances",
            "type":"Retail Goods"
        }
    ],
    "sg:phone":"+44 1472 358766",
    "sg:postcode":"DN32 7AN",
    "sg:province":"Lincolnshire",
    "sg:tags":[
        "electrical",
        "domestic"
    ],
    "wof:name":"J Rayner & Sons (Grimsby) Ltd.",
    "wof:placetype":"venue"
},
  "geometry": {"coordinates":[-0.074173,53.570339],"type":"Point"}
}