{
  "type": "Feature",
  "properties": {
    "addr:full":"No 5a The Old Dairy, Sancreed Penzance Cornwall TR20 8QW",
    "addr:housenumber":"5a",
    "addr:postcode":"tr20 8qw",
    "addr:street":"No;The Old",
    "iso:country":"GB",
    "sg:address":"No 5a The Old Dairy, Sancreed",
    "sg:city":"Penzance",
    "sg:classifiers":[
        {
            "category":"Home & Garden",
            "subcategory":"Home Furnishings",
            "type":"Retail Goods"
        }
    ],
    "sg:phone":"+44 1202 742662",
    "sg:postcode":"TR20 8QW",
    "sg:province":"Cornwall",
    "sg:tags":[
        "homefurnishings"
    ],
    "wof:name":"Acanthus Interiors Ltd.",
    "wof:placetype":"venue"
},
  "geometry": {"coordinates":[-5.6100239754,50.1080818176],"type":"Point"}
}