{
  "type": "Feature",
  "properties": {
    "iso:country":"GB",
    "sg:address":"143 Fore Street",
    "sg:city":"Saltash",
    "sg:classifiers":[
        {
            "category":"Health Services",
            "subcategory":"Health Practitioner",
            "type":"Services"
        }
    ],
    "sg:postcode":"PL12 6PA",
    "sg:province":"Cornwall",
    "sg:tags":[
        "psychotherapist"
    ],
    "wof:name":"The Place to Be",
    "wof:placetype":"venue"
},
  "geometry": {"coordinates":[-4.21467,50.408791],"type":"Point"}
}