{
  "type": "Feature",
  "properties": {
    "iso:country":"GB",
    "sg:address":"44 Nickson Road",
    "sg:city":"Coventry",
    "sg:classifiers":[
        {
            "category":"Shopping",
            "subcategory":"News",
            "type":"Retail Goods"
        }
    ],
    "sg:phone":"+44 24 7646 6848",
    "sg:postcode":"CV4 9RU",
    "sg:province":"Warwickshire",
    "sg:tags":[
        "newsagent"
    ],
    "wof:name":"Terrys News",
    "wof:placetype":"venue"
},
  "geometry": {"coordinates":[-1.584702,52.400963],"type":"Point"}
}