{
  "type": "Feature",
  "properties": {
    "addr:full":"21 Chandos Road Worthing West Sussex BN11 1TJ",
    "addr:housenumber":"21",
    "addr:postcode":"bn11 1tj",
    "addr:street":"Chandos Road",
    "iso:country":"GB",
    "sg:address":"21 Chandos Road",
    "sg:city":"Worthing",
    "sg:classifiers":[
        {
            "category":"Organizations",
            "subcategory":"Community Association",
            "type":"Services"
        }
    ],
    "sg:postcode":"BN11 1TJ",
    "sg:province":"West Sussex",
    "sg:tags":[
        "society",
        "housing"
    ],
    "wof:name":"Anchor Trust",
    "wof:placetype":"venue"
},
  "geometry": {"coordinates":[-0.373227,50.810925],"type":"Point"}
}