{
  "type": "Feature",
  "properties": {
    "iso:country":"GB",
    "sg:address":"The Gables, Top St, Bolney",
    "sg:city":"Haywards Heath",
    "sg:classifiers":[
        {
            "category":"Shopping",
            "subcategory":"Clothing, Apparel, & Fashions",
            "type":"Retail Goods"
        }
    ],
    "sg:phone":"+44 1444 881900",
    "sg:postcode":"RH17 5PP",
    "sg:province":"East Sussex",
    "sg:tags":[
        "sportswear"
    ],
    "wof:name":"C & L Products",
    "wof:placetype":"venue"
},
  "geometry": {"coordinates":[-0.204452,50.990582],"type":"Point"}
}