{
  "type": "Feature",
  "properties": {
    "addr:full":"Rear Of Station Parade Virginia Water Surrey GU25 4AA",
    "addr:housenumber":"rear of",
    "addr:postcode":"gu25 4aa",
    "addr:street":"Parade",
    "iso:country":"GB",
    "sg:address":"Rear Of Station Parade",
    "sg:city":"Virginia Water",
    "sg:classifiers":[
        {
            "category":"Government",
            "subcategory":"City Hall",
            "type":"Public Place"
        }
    ],
    "sg:phone":"+44 1344 844946",
    "sg:postcode":"GU25 4AA",
    "sg:province":"Surrey",
    "wof:name":"Christ Church Hall",
    "wof:placetype":"venue"
},
  "geometry": {"coordinates":[-0.5616539717,51.4019203186],"type":"Point"}
}