{
  "type": "Feature",
  "properties": {
    "iso:country":"GB",
    "sg:address":"Tara-ki Cottage, Maybush Lane",
    "sg:city":"Southampton",
    "sg:classifiers":[
        {
            "category":"Building & Trades",
            "subcategory":"Construction",
            "type":"Services"
        }
    ],
    "sg:postcode":"SO32 3QF",
    "sg:province":"Hampshire",
    "sg:tags":[
        "builder"
    ],
    "wof:name":"Alfred Shirley Tucker",
    "wof:placetype":"venue"
},
  "geometry": {"coordinates":[-1.13585,50.92313],"type":"Point"}
}