{
  "type": "Feature",
  "properties": {
    "addr:full":"Chapelknowe Rd Motherwell North Lanarkshire ML1 5LF",
    "addr:postcode":"ml1 5lf",
    "addr:street":"Chapelknowe Rd",
    "iso:country":"GB",
    "sg:address":"Chapelknowe Rd",
    "sg:city":"Motherwell",
    "sg:classifiers":[
        {
            "category":"Utilities",
            "subcategory":"Natural Gas",
            "type":"Services"
        }
    ],
    "sg:phone":"+44 1698 860721",
    "sg:postcode":"ML1 5LF",
    "sg:province":"North Lanarkshire",
    "sg:tags":[
        "supplier"
    ],
    "wof:name":"BOC Gases",
    "wof:placetype":"venue"
},
  "geometry": {"coordinates":[-3.9349989891,55.8116416931],"type":"Point"}
}