{
  "type": "Feature",
  "properties": {
    "addr:full":"13 Crafnant Rd, Rhos On Sea Colwyn Bay Conwy LL28 4SS",
    "addr:housenumber":"13",
    "addr:postcode":"ll28 4ss",
    "addr:street":"Crafnant Rd",
    "iso:country":"GB",
    "sg:address":"13 Crafnant Rd, Rhos On Sea",
    "sg:city":"Colwyn Bay",
    "sg:classifiers":[
        {
            "category":"Professional",
            "type":"Services"
        }
    ],
    "sg:phone":"+44 1492 547456",
    "sg:postcode":"LL28 4SS",
    "sg:province":"Conwy",
    "sg:tags":[
        "entertainer"
    ],
    "wof:name":"Apra its Party Time",
    "wof:placetype":"venue"
},
  "geometry": {"coordinates":[-3.7618420124,53.3015708923],"type":"Point"}
}