{
  "type": "Feature",
  "properties": {
    "iso:country":"GB",
    "sg:address":"6 Church Lane, Appleby",
    "sg:city":"Scunthorpe",
    "sg:classifiers":[
        {
            "category":"Farming",
            "subcategory":"Livestock Farm",
            "type":"Manufacturing & Wholesale Goods"
        }
    ],
    "sg:phone":"+44 1724 732810",
    "sg:postcode":"DN15 0AG",
    "sg:province":"Lincolnshire",
    "sg:tags":[
        "others"
    ],
    "wof:name":"P R Bletcher",
    "wof:placetype":"venue"
},
  "geometry": {"coordinates":[-0.564073,53.622551],"type":"Point"}
}