{
  "type": "Feature",
  "properties": {
    "iso:country":"GB",
    "sg:address":"Unit 2a, Rutherfords Business Park, Marley Lane",
    "sg:city":"Battle",
    "sg:classifiers":[
        {
            "category":"Home & Garden",
            "subcategory":"Hardware",
            "type":"Retail Goods"
        }
    ],
    "sg:phone":"+44 1424 775404",
    "sg:postcode":"TN33 0TY",
    "sg:province":"East Sussex",
    "sg:tags":[
        "lawnmowers",
        "machinery"
    ],
    "wof:name":"Cutting Edges Mower Services",
    "wof:placetype":"venue"
},
  "geometry": {"coordinates":[0.489025,50.914616],"type":"Point"}
}