{
  "type": "Feature",
  "properties": {
    "addr:full":"59 Maidstone Road Rochester Kent ME1 1RL",
    "addr:housenumber":"59",
    "addr:postcode":"me1 1rl",
    "addr:street":"Maidstone Road Rochester",
    "iso:country":"GB",
    "sg:address":"59 Maidstone Road",
    "sg:city":"Rochester",
    "sg:classifiers":[
        {
            "category":"Shopping",
            "subcategory":"Bicycles & Sporting Goods",
            "type":"Retail Goods"
        }
    ],
    "sg:phone":"+44 1634 815527",
    "sg:postcode":"ME1 1RL",
    "sg:province":"Kent",
    "sg:tags":[
        "cycle",
        "accessory"
    ],
    "wof:name":"Cyclerama",
    "wof:placetype":"venue"
},
  "geometry": {"coordinates":[0.5038980246,51.3848876953],"type":"Point"}
}