{
  "type": "Feature",
  "properties": {
    "iso:country":"GB",
    "sg:address":"Arch 13, Kingsdown Close",
    "sg:city":"London",
    "sg:classifiers":[
        {
            "category":"Retail",
            "subcategory":"Auto Repair",
            "type":"Services"
        }
    ],
    "sg:postcode":"W10 6SW",
    "sg:province":"Greater London",
    "sg:tags":[
        "modification",
        "garage"
    ],
    "wof:name":"Acacia Avenue Imports",
    "wof:placetype":"venue"
},
  "geometry": {"coordinates":[-0.21496,51.515549],"type":"Point"}
}