{
  "type": "Feature",
  "properties": {
    "addr:full":"11 Cheshire Street Market Drayton Shropshire TF9 1PD",
    "addr:housenumber":"11",
    "addr:postcode":"tf9 1pd",
    "addr:street":"Cheshire Street",
    "iso:country":"GB",
    "sg:address":"11 Cheshire Street",
    "sg:city":"Market Drayton",
    "sg:classifiers":[
        {
            "category":"Insurance",
            "subcategory":"Insurance Agent",
            "type":"Services"
        }
    ],
    "sg:phone":"+44 1630 658455",
    "sg:postcode":"TF9 1PD",
    "sg:province":"Shropshire",
    "sg:tags":[
        "broker"
    ],
    "wof:name":"Meadons Insurance & Mortgage Brokers",
    "wof:placetype":"venue"
},
  "geometry": {"coordinates":[-2.4847259521,52.9041061401],"type":"Point"}
}