{
  "type": "Feature",
  "properties": {
    "iso:country":"GB",
    "sg:address":"150 Upper Street, Islington",
    "sg:city":"London",
    "sg:classifiers":[
        {
            "category":"Shopping",
            "subcategory":"Pharmacy",
            "type":"Retail Goods"
        }
    ],
    "sg:phone":"+44 20 7359 7595",
    "sg:postcode":"N1 1RA",
    "sg:province":"Greater London",
    "sg:tags":[
        "pharmacist",
        "dispensing",
        "chemist"
    ],
    "wof:name":"Clan Chemists",
    "wof:placetype":"venue"
},
  "geometry": {"coordinates":[-0.102818,51.540245],"type":"Point"}
}