{
  "type": "Feature",
  "properties": {
    "iso:country":"GB",
    "sg:address":"288 Charminster Road",
    "sg:city":"Bournemouth",
    "sg:classifiers":[
        {
            "category":"Fast Food",
            "type":"Food & Drink"
        }
    ],
    "sg:postcode":"BH8 9RP",
    "sg:province":"Dorset",
    "sg:tags":[
        "away",
        "take"
    ],
    "wof:name":"Charmans Catering",
    "wof:placetype":"venue"
},
  "geometry": {"coordinates":[-1.8633420467,50.740524292],"type":"Point"}
}