{
  "type": "Feature",
  "properties": {
    "addr:full":"21 High Street Cheadle Cheshire SK8 1AX",
    "addr:housenumber":"21",
    "addr:postcode":"sk8 1ax",
    "addr:street":"High Street Cheadle",
    "iso:country":"GB",
    "sg:address":"21 High Street",
    "sg:city":"Cheadle",
    "sg:classifiers":[
        {
            "category":"Health Services",
            "subcategory":"Optometrist",
            "type":"Services"
        }
    ],
    "sg:phone":"+44 161 491 4628",
    "sg:postcode":"SK8 1AX",
    "sg:province":"Cheshire",
    "sg:tags":[
        "optician"
    ],
    "wof:name":"Maloney Opticians",
    "wof:placetype":"venue"
},
  "geometry": {"coordinates":[-2.214197,53.394878],"type":"Point"}
}