{
  "type": "Feature",
  "properties": {
    "addr:full":"50 Murrayfield Fochabers Moray IV32 7EZ",
    "addr:housenumber":"50",
    "addr:postcode":"iv32 7ez",
    "addr:street":"Murrayfield Fochabers",
    "iso:country":"GB",
    "sg:address":"50 Murrayfield",
    "sg:city":"Fochabers",
    "sg:classifiers":[
        {
            "category":"Autos & Motor Vehicles",
            "subcategory":"Motorcycle Sales",
            "type":"Retail Goods"
        }
    ],
    "sg:postcode":"IV32 7EZ",
    "sg:province":"Moray",
    "sg:tags":[
        "chauffeur",
        "driven",
        "car"
    ],
    "wof:name":"Chrissie's Private Hire",
    "wof:placetype":"venue"
},
  "geometry": {"coordinates":[-3.093435,57.609089],"type":"Point"}
}