{
  "type": "Feature",
  "properties": {
    "addr:full":"37 Watson Avenue Chatham Kent ME5 9SJ",
    "addr:housenumber":"37",
    "addr:postcode":"me5 9sj",
    "addr:street":"Watson Avenue",
    "iso:country":"GB",
    "sg:address":"37 Watson Avenue",
    "sg:city":"Chatham",
    "sg:classifiers":[
        {
            "category":"Professional",
            "subcategory":"Accounting & Tax Preparation",
            "type":"Services"
        }
    ],
    "sg:phone":"+44 1634 868804",
    "sg:postcode":"ME5 9SJ",
    "sg:province":"Kent",
    "sg:tags":[
        "accountant"
    ],
    "wof:name":"Cornford Accounting Services",
    "wof:placetype":"venue"
},
  "geometry": {"coordinates":[0.511300981,51.3485031128],"type":"Point"}
}