{
  "type": "Feature",
  "properties": {
    "addr:full":"47 Church Street Littlehampton West Sussex BN17 5PY",
    "addr:housenumber":"47",
    "addr:postcode":"bn17 5py",
    "addr:street":"Church Street",
    "iso:country":"GB",
    "sg:address":"47 Church Street",
    "sg:city":"Littlehampton",
    "sg:classifiers":[
        {
            "category":"Health Services",
            "subcategory":"Nursing And Care Facility",
            "type":"Services"
        }
    ],
    "sg:phone":"+44 1903 714351",
    "sg:postcode":"BN17 5PY",
    "sg:province":"West Sussex",
    "sg:tags":[
        "home"
    ],
    "wof:name":"St.Francis Nursing Home",
    "wof:placetype":"venue"
},
  "geometry": {"coordinates":[-0.5345129967,50.8088989258],"type":"Point"}
}