{
  "type": "Feature",
  "properties": {
    "addr:full":"London Road, Trelawnyd Rhyl Conwy LL18 6DN",
    "addr:postcode":"ll18 6dn",
    "addr:street":"London Road Trelawnyd",
    "iso:country":"GB",
    "sg:address":"London Road, Trelawnyd",
    "sg:city":"Rhyl",
    "sg:classifiers":[
        {
            "category":"Government",
            "subcategory":"Post Office",
            "type":"Public Place"
        }
    ],
    "sg:postcode":"LL18 6DN",
    "sg:province":"Conwy",
    "wof:name":"The Post Office Store",
    "wof:placetype":"venue"
},
  "geometry": {"coordinates":[-3.3653140068,53.3067932129],"type":"Point"}
}