{
  "type": "Feature",
  "properties": {
    "addr:full":"19b Abbotts Road Cinderford Gloucestershire GL14 3BN",
    "addr:housenumber":"19b",
    "addr:postcode":"gl14 3bn",
    "addr:street":"Abbotts Road",
    "iso:country":"GB",
    "sg:address":"19b Abbotts Road",
    "sg:city":"Cinderford",
    "sg:classifiers":[
        {
            "category":"Building & Trades",
            "subcategory":"Construction",
            "type":"Services"
        }
    ],
    "sg:postcode":"GL14 3BN",
    "sg:province":"Gloucestershire",
    "sg:tags":[
        "builder"
    ],
    "wof:name":"Filterclean Water Technologies Ltd.",
    "wof:placetype":"venue"
},
  "geometry": {"coordinates":[-2.494035,51.817474],"type":"Point"}
}