{
  "type": "Feature",
  "properties": {
    "iso:country":"GB",
    "sg:address":"63-65 Woodburn Park",
    "sg:city":"Dalkeith",
    "sg:classifiers":[
        {
            "category":"Food & Beverages",
            "subcategory":"Fruits & Vegetables",
            "type":"Retail Goods"
        },
        {
            "category":"Food & Beverages",
            "subcategory":"Groceries & Convenience Stores",
            "type":"Retail Goods"
        }
    ],
    "sg:phone":"+44 131 663 0247",
    "sg:postcode":"EH22 2DE",
    "sg:province":"City of Edinburgh",
    "sg:tags":[
        "grocer",
        "greengrocer"
    ],
    "wof:name":"Its Nice to Be Nice",
    "wof:placetype":"venue"
},
  "geometry": {"coordinates":[-3.0474960804,55.8925819397],"type":"Point"}
}