{
  "type": "Feature",
  "properties": {
    "addr:full":"School Lane Dumfries Dumfries and Galloway DG2 7AJ",
    "addr:postcode":"dg2 7aj",
    "addr:street":"School Lane",
    "iso:country":"GB",
    "sg:address":"School Lane",
    "sg:city":"Dumfries",
    "sg:classifiers":[
        {
            "category":"Education",
            "subcategory":"School",
            "type":"Public Place"
        }
    ],
    "sg:phone":"+44 1387 252459",
    "sg:postcode":"DG2 7AJ",
    "sg:province":"Dumfries and Galloway",
    "sg:tags":[
        "local",
        "authority"
    ],
    "wof:name":"Laurieknowe School",
    "wof:placetype":"venue"
},
  "geometry": {"coordinates":[-3.622294,55.067474],"type":"Point"}
}