{
  "type": "Feature",
  "properties": {
    "iso:country":"GB",
    "sg:address":"Unit E, Abbey Wharf",
    "sg:city":"Barking",
    "sg:classifiers":[
        {
            "category":"Home & Garden",
            "subcategory":"Building Materials",
            "type":"Retail Goods"
        }
    ],
    "sg:phone":"+44 20 8594 4472",
    "sg:postcode":"IG11 0BD",
    "sg:province":"Essex",
    "sg:tags":[
        "veneer"
    ],
    "wof:name":"Holloway Products Ltd.",
    "wof:placetype":"venue"
},
  "geometry": {"coordinates":[0.081115,51.539101],"type":"Point"}
}