{
  "type": "Feature",
  "properties": {
    "iso:country":"GB",
    "sg:address":"Civic Way",
    "sg:city":"Burgess Hill",
    "sg:classifiers":[
        {
            "category":"Conference Center",
            "type":"Public Place"
        }
    ],
    "sg:phone":"+44 1444 242888",
    "sg:postcode":"RH15 9NN",
    "sg:province":"East Sussex",
    "wof:name":"Martlets Hall Burgess Hill",
    "wof:placetype":"venue"
},
  "geometry": {"coordinates":[-0.133913,50.956318],"type":"Point"}
}