{
  "type": "Feature",
  "properties": {
    "iso:country":"GB",
    "sg:address":"54 Manor View, Shafton",
    "sg:city":"Barnsley",
    "sg:classifiers":[
        {
            "category":"Building & Trades",
            "subcategory":"Construction",
            "type":"Services"
        }
    ],
    "sg:postcode":"S72 8NQ",
    "sg:province":"South Yorkshire",
    "sg:tags":[
        "builder"
    ],
    "wof:name":"D N A Builders",
    "wof:placetype":"venue"
},
  "geometry": {"coordinates":[-1.420647,53.573704],"type":"Point"}
}