{
  "type": "Feature",
  "properties": {
    "iso:country":"GB",
    "sg:address":"1a St Marys Road, Wrotham",
    "sg:city":"Sevenoaks",
    "sg:classifiers":[
        {
            "category":"Professional",
            "type":"Services"
        }
    ],
    "sg:phone":"+44 1732 882904",
    "sg:postcode":"TN15 7AL",
    "sg:province":"Kent",
    "sg:tags":[
        "interior",
        "furnishers",
        "designer"
    ],
    "wof:name":"Vine House Interiors",
    "wof:placetype":"venue"
},
  "geometry": {"coordinates":[0.31018,51.307842],"type":"Point"}
}