{
  "type": "Feature",
  "properties": {
    "iso:country":"GB",
    "sg:address":"60 Park Lane",
    "sg:city":"Tottenham",
    "sg:classifiers":[
        {
            "category":"Place Of Worship",
            "type":"Public Place"
        }
    ],
    "sg:phone":"+44 20 8808 7297",
    "sg:postcode":"N17 0JR",
    "sg:province":"Greater London",
    "wof:name":"St Pauls C Of E Church",
    "wof:placetype":"venue"
},
  "geometry": {"coordinates":[-0.0626209974,51.6023712158],"type":"Point"}
}