{
  "type": "Feature",
  "properties": {
    "iso:country":"GB",
    "sg:address":"11 Preston Street, Kirkham",
    "sg:city":"Preston",
    "sg:classifiers":[
        {
            "category":"Real Estate",
            "subcategory":"Real Estate Agent",
            "type":"Services"
        }
    ],
    "sg:phone":"+44 1772 683194",
    "sg:postcode":"PR4 2YA",
    "sg:province":"Lancashire",
    "wof:name":"Reeds Rains Ltd.",
    "wof:placetype":"venue"
},
  "geometry": {"coordinates":[-2.870483,53.782562],"type":"Point"}
}