{
  "type": "Feature",
  "properties": {
    "addr:full":"36 Anchor Lane Hemel Hempstead Hertfordshire HP1 1TY",
    "addr:housenumber":"36",
    "addr:postcode":"hp1 1ty",
    "addr:street":"Anchor Lane",
    "iso:country":"GB",
    "sg:address":"36 Anchor Lane",
    "sg:city":"Hemel Hempstead",
    "sg:classifiers":[
        {
            "category":"Building & Trades",
            "subcategory":"Construction",
            "type":"Services"
        }
    ],
    "sg:phone":"+44 1442 258842",
    "sg:postcode":"HP1 1TY",
    "sg:province":"Hertfordshire",
    "sg:tags":[
        "tiling",
        "contractor"
    ],
    "wof:name":"I S Ceramics Wall & Floor Tiling",
    "wof:placetype":"venue"
},
  "geometry": {"coordinates":[-0.4810380042,51.7488632202],"type":"Point"}
}