{
  "type": "Feature",
  "properties": {
    "addr:full":"5 Bouverie Road West Folkestone Kent CT20 2RX",
    "addr:housenumber":"5",
    "addr:postcode":"ct20 2rx",
    "addr:street":"Bouverie Road West",
    "iso:country":"GB",
    "sg:address":"5 Bouverie Road West",
    "sg:city":"Folkestone",
    "sg:classifiers":[
        {
            "category":"Food & Beverages",
            "subcategory":"Supermarket",
            "type":"Retail Goods"
        }
    ],
    "sg:phone":"+44 1303 242638",
    "sg:postcode":"CT20 2RX",
    "sg:province":"Kent",
    "wof:name":"J Sainsbury PLC",
    "wof:placetype":"venue"
},
  "geometry": {"coordinates":[1.1747549772,51.0786170959],"type":"Point"}
}