{
  "type": "Feature",
  "properties": {
    "iso:country":"GB",
    "sg:address":"3 Cobridge Rd",
    "sg:city":"Stoke On Trent",
    "sg:classifiers":[
        {
            "category":"Bars & Pubs",
            "type":"Food & Drink"
        }
    ],
    "sg:phone":"+44 1782 287266",
    "sg:postcode":"ST1 5JP",
    "sg:province":"Staffordshire",
    "sg:tags":[
        "pubs",
        "inn"
    ],
    "wof:name":"Evergreens",
    "wof:placetype":"venue"
},
  "geometry": {"coordinates":[-2.1888420582,53.0303192139],"type":"Point"}
}