{
  "type": "Feature",
  "properties": {
    "addr:full":"Nairn Street, South Leam Estate Jarrow Tyne and Wear NE32 4HX",
    "addr:postcode":"ne32 4hx",
    "addr:street":"Nairn Street South Leam Estate",
    "iso:country":"GB",
    "sg:address":"Nairn Street, South Leam Estate",
    "sg:city":"Jarrow",
    "sg:classifiers":[
        {
            "category":"Bars & Pubs",
            "subcategory":"Nightclub",
            "type":"Food & Drink"
        },
        {
            "category":"Organizations",
            "subcategory":"Membership Organization",
            "type":"Services"
        }
    ],
    "sg:phone":"+44 191 489 2540",
    "sg:postcode":"NE32 4HX",
    "sg:province":"Tyne and Wear",
    "sg:tags":[
        "club",
        "activity"
    ],
    "wof:name":"Neon Social Club & Institute Ltd",
    "wof:placetype":"venue"
},
  "geometry": {"coordinates":[-1.464539,54.962509],"type":"Point"}
}