{
  "type": "Feature",
  "properties": {
    "iso:country":"GB",
    "sg:address":"8 Upper High Street",
    "sg:city":"Thame",
    "sg:classifiers":[
        {
            "category":"Deli",
            "type":"Food & Drink"
        }
    ],
    "sg:phone":"+44 1844 212056",
    "sg:postcode":"OX9 3ER",
    "sg:province":"Buckinghamshire",
    "sg:tags":[
        "delicatessen"
    ],
    "wof:name":"Jordans",
    "wof:placetype":"venue"
},
  "geometry": {"coordinates":[-0.976381,51.746487],"type":"Point"}
}