{
  "type": "Feature",
  "properties": {
    "addr:full":"Bunbury House, Stour Park Blandford Forum Dorset DT11 7LQ",
    "addr:postcode":"dt11 7lq",
    "addr:street":"Stour Park",
    "iso:country":"GB",
    "sg:address":"Bunbury House, Stour Park",
    "sg:city":"Blandford Forum",
    "sg:classifiers":[
        {
            "category":"Professional",
            "subcategory":"Lawyer & Legal Services",
            "type":"Services"
        }
    ],
    "sg:postcode":"DT11 7LQ",
    "sg:province":"Dorset",
    "sg:tags":[
        "solicitor"
    ],
    "wof:name":"Blanchards",
    "wof:placetype":"venue"
},
  "geometry": {"coordinates":[-2.154624,50.855984],"type":"Point"}
}