{
  "type": "Feature",
  "properties": {
    "addr:full":"Wellend Farm, Marlow Rd Bourne End Berkshire SL8 5PJ",
    "addr:postcode":"sl8 5pj",
    "addr:street":"Marlow Rd",
    "iso:country":"GB",
    "sg:address":"Wellend Farm, Marlow Rd",
    "sg:city":"Bourne End",
    "sg:classifiers":[
        {
            "category":"Farming",
            "subcategory":"Livestock Farm",
            "type":"Manufacturing & Wholesale Goods"
        }
    ],
    "sg:phone":"+44 1628 520355",
    "sg:postcode":"SL8 5PJ",
    "sg:province":"Berkshire",
    "sg:tags":[
        "others"
    ],
    "wof:name":"J F Lunnon",
    "wof:placetype":"venue"
},
  "geometry": {"coordinates":[-0.713174,51.579506],"type":"Point"}
}