{
  "type": "Feature",
  "properties": {
    "iso:country":"GB",
    "sg:address":"Woldgate School, 90-92 Kilnwick Road",
    "sg:city":"York",
    "sg:classifiers":[
        {
            "category":"Education",
            "subcategory":"University",
            "type":"Public Place"
        }
    ],
    "sg:phone":"+44 1759 302409",
    "sg:postcode":"YO42 2LL",
    "sg:province":"East Riding of Yorkshire",
    "sg:tags":[
        "adult"
    ],
    "wof:name":"Pocklington Adult Education Centre",
    "wof:placetype":"venue"
},
  "geometry": {"coordinates":[-0.7640900016,53.93201828],"type":"Point"}
}