{
  "type": "Feature",
  "properties": {
    "addr:full":"315c Baring Rd Grove Park Greater London SE12 0DZ",
    "addr:housenumber":"315c",
    "addr:postcode":"se12 0dz",
    "addr:street":"Baring Rd",
    "iso:country":"GB",
    "sg:address":"315c Baring Rd",
    "sg:city":"Grove Park",
    "sg:classifiers":[
        {
            "category":"Home & Garden",
            "subcategory":"Household Appliances",
            "type":"Retail Goods"
        }
    ],
    "sg:phone":"+44 20 8851 3200",
    "sg:postcode":"SE12 0DZ",
    "sg:province":"Greater London",
    "sg:tags":[
        "electrical"
    ],
    "wof:name":"Bosch Appliances",
    "wof:placetype":"venue"
},
  "geometry": {"coordinates":[0.0214690007,51.4300270081],"type":"Point"}
}