{
  "type": "Feature",
  "properties": {
    "addr:full":"1 High Street Swanley Kent BR8 8AE",
    "addr:housenumber":"1",
    "addr:postcode":"br8 8ae",
    "addr:street":"High Street",
    "iso:country":"GB",
    "sg:address":"1 High Street",
    "sg:city":"Swanley",
    "sg:classifiers":[
        {
            "category":"Personal",
            "subcategory":"Beauty Salon",
            "type":"Services"
        }
    ],
    "sg:phone":"+44 1322 666223",
    "sg:postcode":"BR8 8AE",
    "sg:province":"Kent",
    "sg:tags":[
        "unisex",
        "hairdresser"
    ],
    "wof:name":"Sandy's",
    "wof:placetype":"venue"
},
  "geometry": {"coordinates":[0.1769679934,51.3955497742],"type":"Point"}
}