{
  "type": "Feature",
  "properties": {
    "addr:full":"First Avenue, Millbrook Trading Estate Southampton Hampshire SO15 0DE",
    "addr:postcode":"so15 0de",
    "addr:street":"First Avenue;Trading",
    "iso:country":"GB",
    "sg:address":"First Avenue, Millbrook Trading Estate",
    "sg:city":"Southampton",
    "sg:classifiers":[
        {
            "category":"Shopping",
            "subcategory":"Computers & Home Electronics",
            "type":"Retail Goods"
        },
        {
            "category":"Home & Garden",
            "subcategory":"Kitchen Supply",
            "type":"Retail Goods"
        }
    ],
    "sg:phone":"+44 23 8077 6458",
    "sg:postcode":"SO15 0DE",
    "sg:province":"Hampshire",
    "sg:tags":[
        "household",
        "ware",
        "store"
    ],
    "wof:name":"Paton Calvert Housewares Ltd",
    "wof:placetype":"venue"
},
  "geometry": {"coordinates":[-1.4571839571,50.9168815613],"type":"Point"}
}