{
  "type": "Feature",
  "properties": {
    "iso:country":"GB",
    "sg:address":"Terminal Building, Redhill Aerodrome, Kings Mill Lane",
    "sg:city":"Redhill",
    "sg:classifiers":[
        {
            "category":"Professional",
            "subcategory":"Printing & Photocopies",
            "type":"Services"
        }
    ],
    "sg:phone":"+44 1737 822636",
    "sg:postcode":"RH1 5YP",
    "sg:province":"Surrey",
    "sg:tags":[
        "printer"
    ],
    "wof:name":"Ekonoprint",
    "wof:placetype":"venue"
},
  "geometry": {"coordinates":[-0.168879,51.238178],"type":"Point"}
}