{
  "type": "Feature",
  "properties": {
    "addr:full":"41 Welbeck Street Worksop Nottinghamshire S80 4TF",
    "addr:housenumber":"41",
    "addr:postcode":"s80 4tf",
    "addr:street":"Welbeck Street",
    "iso:country":"GB",
    "sg:address":"41 Welbeck Street",
    "sg:city":"Worksop",
    "sg:classifiers":[
        {
            "category":"Retail",
            "subcategory":"Auto Repair",
            "type":"Services"
        }
    ],
    "sg:postcode":"S80 4TF",
    "sg:province":"Nottinghamshire",
    "sg:tags":[
        "modification",
        "garage"
    ],
    "wof:name":"Autospares",
    "wof:placetype":"venue"
},
  "geometry": {"coordinates":[-1.2148150206,53.2611274719],"type":"Point"}
}