{
  "type": "Feature",
  "properties": {
    "addr:full":"Wards Farm, Gladfen Hall Road, Greenstead Halstead Essex CO9 1RN",
    "addr:postcode":"co9 1rn",
    "addr:street":"Hall Road",
    "iso:country":"GB",
    "sg:address":"Wards Farm, Gladfen Hall Road, Greenstead",
    "sg:city":"Halstead",
    "sg:classifiers":[
        {
            "category":"Professional",
            "subcategory":"Business Services",
            "type":"Services"
        }
    ],
    "sg:phone":"+44 1787 474792",
    "sg:postcode":"CO9 1RN",
    "sg:province":"Essex",
    "sg:tags":[
        "import",
        "export",
        "agent"
    ],
    "wof:name":"Pu'r (U K) Drinks Ltd.",
    "wof:placetype":"venue"
},
  "geometry": {"coordinates":[0.6303799748,51.9226913452],"type":"Point"}
}