{
  "type": "Feature",
  "properties": {
    "iso:country":"GB",
    "sg:address":"63 Dalblair Road",
    "sg:city":"Ayr",
    "sg:classifiers":[
        {
            "category":"Transit Center",
            "subcategory":"Freight",
            "type":"Transportation"
        }
    ],
    "sg:postcode":"KA7 1UQ",
    "sg:province":"South Ayrshire",
    "sg:tags":[
        "shop",
        "craft",
        "centre"
    ],
    "wof:name":"Ayrcraft",
    "wof:placetype":"venue"
},
  "geometry": {"coordinates":[-4.6305031776,55.4589614868],"type":"Point"}
}