{
  "type": "Feature",
  "properties": {
    "addr:full":"25 Grenville Road, Hazel Gro Stockport Cheshire SK7 5AF",
    "addr:housenumber":"25",
    "addr:postcode":"sk7 5af",
    "addr:street":"Grenville Road",
    "iso:country":"GB",
    "sg:address":"25 Grenville Road, Hazel Gro",
    "sg:city":"Stockport",
    "sg:classifiers":[
        {
            "category":"Building & Trades",
            "subcategory":"Construction",
            "type":"Services"
        }
    ],
    "sg:postcode":"SK7 5AF",
    "sg:province":"Cheshire",
    "sg:tags":[
        "decorator",
        "painter"
    ],
    "wof:name":"B P J Decorating Services",
    "wof:placetype":"venue"
},
  "geometry": {"coordinates":[-2.128401,53.38224],"type":"Point"}
}