{
  "type": "Feature",
  "properties": {
    "addr:full":"7 Walcot Rd Swindon Wiltshire SN3 1BH",
    "addr:housenumber":"7",
    "addr:postcode":"sn3 1bh",
    "addr:street":"Walcot Rd",
    "iso:country":"GB",
    "sg:address":"7 Walcot Rd",
    "sg:city":"Swindon",
    "sg:classifiers":[
        {
            "category":"Building & Trades",
            "subcategory":"Plumbing",
            "type":"Services"
        }
    ],
    "sg:phone":"+44 1793 644062",
    "sg:postcode":"SN3 1BH",
    "sg:province":"Wiltshire",
    "sg:tags":[
        "heating"
    ],
    "wof:name":"Swift Installations",
    "wof:placetype":"venue"
},
  "geometry": {"coordinates":[-1.7717809677,51.5582008362],"type":"Point"}
}