{
  "type": "Feature",
  "properties": {
    "iso:country":"GB",
    "sg:address":"Richard House, Enstone Road",
    "sg:city":"Enfield",
    "sg:classifiers":[
        {
            "category":"Professional",
            "subcategory":"Art Services",
            "type":"Services"
        }
    ],
    "sg:phone":"+44 20 8350 8115",
    "sg:postcode":"EN3 7TB",
    "sg:province":"Greater London",
    "sg:tags":[
        "consultant",
        "design"
    ],
    "wof:name":"London Research & Development Ltd.",
    "wof:placetype":"venue"
},
  "geometry": {"coordinates":[-0.0321080014,51.6542701721],"type":"Point"}
}