{
  "type": "Feature",
  "properties": {
    "iso:country":"GB",
    "sg:address":"148 O'hare",
    "sg:city":"Alexandria",
    "sg:classifiers":[
        {
            "category":"Professional",
            "subcategory":"Computer Services",
            "type":"Services"
        }
    ],
    "sg:phone":"+44 1389 753092",
    "sg:postcode":"G83 9DX",
    "sg:province":"Argyll and Bute",
    "sg:tags":[
        "information"
    ],
    "wof:name":"Bonhill Community Council Information Centre",
    "wof:placetype":"venue"
},
  "geometry": {"coordinates":[-4.5846967697,55.9993934631],"type":"Point"}
}