{
  "type": "Feature",
  "properties": {
    "iso:country":"GB",
    "sg:address":"50a St. Johns Rd",
    "sg:city":"Tunbridge Wells",
    "sg:classifiers":[
        {
            "category":"Professional",
            "subcategory":"Computer Services",
            "type":"Services"
        }
    ],
    "sg:phone":"+44 1892 541729",
    "sg:postcode":"TN4 9NY",
    "sg:province":"Kent",
    "sg:tags":[
        "system",
        "software"
    ],
    "wof:name":"W W S Ltd",
    "wof:placetype":"venue"
},
  "geometry": {"coordinates":[0.260601,51.140778],"type":"Point"}
}