{
  "type": "Feature",
  "properties": {
    "iso:country":"GB",
    "sg:address":"The Medieval Bishops Palace",
    "sg:city":"Lincoln",
    "sg:classifiers":[
        {
            "category":"Landmark",
            "subcategory":"Tourist Attraction",
            "type":"Public Place"
        }
    ],
    "sg:postcode":"LN2 1PU",
    "sg:province":"Lincolnshire",
    "sg:tags":[
        "interest"
    ],
    "wof:name":"English Heritage",
    "wof:placetype":"venue"
},
  "geometry": {"coordinates":[-0.5371800065,53.2333488464],"type":"Point"}
}