{
  "type": "Feature",
  "properties": {
    "iso:country":"GB",
    "sg:address":"88 Wareham Road, Lytchett Matravers",
    "sg:city":"Poole",
    "sg:classifiers":[
        {
            "category":"Shopping",
            "subcategory":"Pharmacy",
            "type":"Retail Goods"
        }
    ],
    "sg:phone":"+44 1202 631815",
    "sg:postcode":"BH16 6DT",
    "sg:province":"Dorset",
    "sg:tags":[
        "pharmacist",
        "chemist"
    ],
    "wof:name":"Rexpharm Services Ltd.",
    "wof:placetype":"venue"
},
  "geometry": {"coordinates":[-2.079665,50.75301],"type":"Point"}
}