{
  "type": "Feature",
  "properties": {
    "addr:full":"Severn Crescent Stanley Durham DH9 7PX",
    "addr:postcode":"dh9 7px",
    "addr:street":"Severn Crescent",
    "iso:country":"GB",
    "sg:address":"Severn Crescent",
    "sg:city":"Stanley",
    "sg:classifiers":[
        {
            "category":"Organizations",
            "subcategory":"Membership Organization",
            "type":"Services"
        }
    ],
    "sg:phone":"+44 1207 232131",
    "sg:postcode":"DH9 7PX",
    "sg:province":"Durham",
    "sg:tags":[
        "club"
    ],
    "wof:name":"South Moor Social Working Mens Club",
    "wof:placetype":"venue"
},
  "geometry": {"coordinates":[-1.701543,54.862404],"type":"Point"}
}