{
  "type": "Feature",
  "properties": {
    "addr:full":"12 Chichester Road Ringwood Dorset BH24 1UE",
    "addr:housenumber":"12",
    "addr:postcode":"bh24 1ue",
    "addr:street":"Chichester Road",
    "iso:country":"GB",
    "sg:address":"12 Chichester Road",
    "sg:city":"Ringwood",
    "sg:classifiers":[
        {
            "category":"Building & Trades",
            "subcategory":"Construction",
            "type":"Services"
        }
    ],
    "sg:postcode":"BH24 1UE",
    "sg:province":"Dorset",
    "sg:tags":[
        "builder"
    ],
    "wof:name":"D A Taplin",
    "wof:placetype":"venue"
},
  "geometry": {"coordinates":[-1.7676980495,50.8542327881],"type":"Point"}
}