{
  "type": "Feature",
  "properties": {
    "addr:full":"85 Station Rd Lochgelly Fife KY5 0BW",
    "addr:housenumber":"85",
    "addr:postcode":"ky5 0bw",
    "addr:street":"Station Rd",
    "iso:country":"GB",
    "sg:address":"85 Station Rd",
    "sg:city":"Lochgelly",
    "sg:classifiers":[
        {
            "category":"Food & Beverages",
            "subcategory":"Fruits & Vegetables",
            "type":"Retail Goods"
        }
    ],
    "sg:phone":"+44 1592 721443",
    "sg:postcode":"KY5 0BW",
    "sg:province":"Fife",
    "sg:tags":[
        "greengrocer"
    ],
    "wof:name":"M Ali",
    "wof:placetype":"venue"
},
  "geometry": {"coordinates":[-3.261646986,56.1457061768],"type":"Point"}
}