{
  "type": "Feature",
  "properties": {
    "addr:full":"217 Green Lane, Stoneycroft Liverpool Merseyside L13 6RH",
    "addr:housenumber":"217",
    "addr:postcode":"l13 6rh",
    "addr:street":"Green Lane",
    "iso:country":"GB",
    "sg:address":"217 Green Lane, Stoneycroft",
    "sg:city":"Liverpool",
    "sg:classifiers":[
        {
            "category":"Bars & Pubs",
            "type":"Food & Drink"
        }
    ],
    "sg:phone":"+44 151 228 1184",
    "sg:postcode":"L13 6RH",
    "sg:province":"Merseyside",
    "sg:tags":[
        "pubs",
        "inn"
    ],
    "wof:name":"The Wellington",
    "wof:placetype":"venue"
},
  "geometry": {"coordinates":[-2.920722,53.417377],"type":"Point"}
}