{
  "type": "Feature",
  "properties": {
    "addr:full":"90 Kings Road Brentwood Essex CM14 4DU",
    "addr:housenumber":"90",
    "addr:postcode":"cm14 4du",
    "addr:street":"Kings Road",
    "iso:country":"GB",
    "sg:address":"90 Kings Road",
    "sg:city":"Brentwood",
    "sg:classifiers":[
        {
            "category":"Shopping",
            "subcategory":"Pawn Shop",
            "type":"Retail Goods"
        }
    ],
    "sg:phone":"+44 1277 227022",
    "sg:postcode":"CM14 4DU",
    "sg:province":"Essex",
    "sg:tags":[
        "pawnbroker"
    ],
    "wof:name":"R J & J A MARSDEN",
    "wof:placetype":"venue"
},
  "geometry": {"coordinates":[0.299836,51.616226],"type":"Point"}
}