{
  "type": "Feature",
  "properties": {
    "addr:full":"86 Marden Road South Whitley Bay Northumberland NE25 8PL",
    "addr:housenumber":"86",
    "addr:postcode":"ne25 8pl",
    "addr:street":"Marden Road South",
    "iso:country":"GB",
    "sg:address":"86 Marden Road South",
    "sg:city":"Whitley Bay",
    "sg:classifiers":[
        {
            "category":"Food & Beverages",
            "subcategory":"Liquor & Beverages",
            "type":"Retail Goods"
        }
    ],
    "sg:phone":"+44 191 297 0340",
    "sg:postcode":"NE25 8PL",
    "sg:province":"Northumberland",
    "sg:tags":[
        "beer",
        "wine",
        "spirit",
        "wines"
    ],
    "wof:name":"The Discount Centre",
    "wof:placetype":"venue"
},
  "geometry": {"coordinates":[-1.4432229996,55.0362701416],"type":"Point"}
}