{
  "type": "Feature",
  "properties": {
    "iso:country":"GB",
    "sg:address":"18 Digdens Rise",
    "sg:city":"Epsom",
    "sg:classifiers":[
        {
            "category":"Retail",
            "subcategory":"Auto Repair",
            "type":"Services"
        }
    ],
    "sg:phone":"+44 1372 721641",
    "sg:postcode":"KT18 7DL",
    "sg:province":"Surrey",
    "sg:tags":[
        "modification",
        "garage"
    ],
    "wof:name":"Fleetline Transmissions Ltd.",
    "wof:placetype":"venue"
},
  "geometry": {"coordinates":[-0.275055,51.323681],"type":"Point"}
}