{
  "type": "Feature",
  "properties": {
    "addr:full":"Rectory La Maidstone Kent ME17 1HS",
    "addr:postcode":"me17 1hs",
    "addr:street":"La Maidstone",
    "iso:country":"GB",
    "sg:address":"Rectory La",
    "sg:city":"Maidstone",
    "sg:classifiers":[
        {
            "category":"Social Services",
            "subcategory":"Adult Care",
            "type":"Services"
        }
    ],
    "sg:phone":"+44 1622 851123",
    "sg:postcode":"ME17 1HS",
    "sg:province":"Kent",
    "sg:tags":[
        "day",
        "centre"
    ],
    "wof:name":"Church House Day Care Centre",
    "wof:placetype":"venue"
},
  "geometry": {"coordinates":[0.6814659834,51.2409210205],"type":"Point"}
}