{
  "type": "Feature",
  "properties": {
    "iso:country":"GB",
    "sg:address":"Gibbet Oak Farm, Appledore Road",
    "sg:city":"Tenterden",
    "sg:classifiers":[
        {
            "category":"Wholesale",
            "subcategory":"Fruits & Vegetables",
            "type":"Manufacturing & Wholesale Goods"
        }
    ],
    "sg:phone":"+44 1580 763938",
    "sg:postcode":"TN30 7DH",
    "sg:province":"Kent",
    "wof:name":"R H Nightingale & Partners",
    "wof:placetype":"venue"
},
  "geometry": {"coordinates":[0.6940600276,51.0754051208],"type":"Point"}
}