{
  "type": "Feature",
  "properties": {
    "addr:full":"13 The Holt Wallington Surrey SM6 7LG",
    "addr:housenumber":"13",
    "addr:postcode":"sm6 7lg",
    "addr:street":"The Holt",
    "iso:country":"GB",
    "sg:address":"13 The Holt",
    "sg:city":"Wallington",
    "sg:classifiers":[
        {
            "category":"Building & Trades",
            "subcategory":"Construction",
            "type":"Services"
        }
    ],
    "sg:phone":"+44 20 8773 8751",
    "sg:postcode":"SM6 7LG",
    "sg:province":"Surrey",
    "sg:tags":[
        "dry",
        "lining",
        "plasterers",
        "screeders"
    ],
    "wof:name":"T Gale Pebbledashing Specialist",
    "wof:placetype":"venue"
},
  "geometry": {"coordinates":[-0.1457809955,51.3685073853],"type":"Point"}
}