{
  "type": "Feature",
  "properties": {
    "iso:country":"GB",
    "sg:address":"28a Boulevard",
    "sg:city":"Crawley",
    "sg:classifiers":[
        {
            "category":"Banks & Credit Unions",
            "subcategory":"Financial Services",
            "type":"Services"
        }
    ],
    "sg:phone":"+44 1293 401293",
    "sg:postcode":"RH10 1XP",
    "sg:province":"Surrey",
    "sg:tags":[
        "adviser"
    ],
    "wof:name":"Fund Control Ltd.",
    "wof:placetype":"venue"
},
  "geometry": {"coordinates":[-0.187384,51.11615],"type":"Point"}
}