{
  "type": "Feature",
  "properties": {
    "addr:full":"Waldegrave Farm, Waldegrave La, West Mersea Colchester Essex CO5 8SE",
    "addr:housenumber":"mersea",
    "addr:postcode":"co5 8se",
    "addr:street":"Waldegrave;Waldegrave La West;Colchester",
    "iso:country":"GB",
    "sg:address":"Waldegrave Farm, Waldegrave La, West Mersea",
    "sg:city":"Colchester",
    "sg:classifiers":[
        {
            "category":"Autos & Motor Vehicles",
            "subcategory":"Auto Supplies",
            "type":"Retail Goods"
        }
    ],
    "sg:postcode":"CO5 8SE",
    "sg:province":"Essex",
    "sg:tags":[
        "car",
        "accessory"
    ],
    "wof:name":"West Mersea Trailers Ltd",
    "wof:placetype":"venue"
},
  "geometry": {"coordinates":[0.9128630161,51.7795906067],"type":"Point"}
}