{
  "type": "Feature",
  "properties": {
    "addr:full":"28 Carlisle Street, Splott Cardiff Cardiff CF24 2DS",
    "addr:housenumber":"28",
    "addr:postcode":"cf24 2ds",
    "addr:street":"Carlisle Street",
    "iso:country":"GB",
    "sg:address":"28 Carlisle Street, Splott",
    "sg:city":"Cardiff",
    "sg:classifiers":[
        {
            "category":"Health Services",
            "subcategory":"Nursing And Care Facility",
            "type":"Services"
        }
    ],
    "sg:phone":"+44 29 2045 5300",
    "sg:postcode":"CF24 2DS",
    "sg:province":"Cardiff",
    "sg:tags":[
        "agency"
    ],
    "wof:name":"Everycare Ltd.",
    "wof:placetype":"venue"
},
  "geometry": {"coordinates":[-3.15301,51.48217],"type":"Point"}
}