{
  "type": "Feature",
  "properties": {
    "iso:country":"GB",
    "sg:address":"123 West Street",
    "sg:city":"Glasgow",
    "sg:classifiers":[
        {
            "category":"Organizations",
            "subcategory":"Non-profit Organization",
            "type":"Services"
        }
    ],
    "sg:phone":"+44 141 418 0882",
    "sg:postcode":"G5 8BA",
    "sg:province":"Glasgow City",
    "sg:tags":[
        "organisation",
        "voluntary",
        "charity"
    ],
    "wof:name":"Enhance R D P",
    "wof:placetype":"venue"
},
  "geometry": {"coordinates":[-4.2645020485,55.853515625],"type":"Point"}
}