{
  "type": "Feature",
  "properties": {
    "addr:full":"25 The Avenue Bournemouth Dorset BH9 2UN",
    "addr:housenumber":"25",
    "addr:postcode":"bh9 2un",
    "addr:street":"The Avenue",
    "iso:country":"GB",
    "sg:address":"25 The Avenue",
    "sg:city":"Bournemouth",
    "sg:classifiers":[
        {
            "category":"Building & Trades",
            "subcategory":"Construction",
            "type":"Services"
        }
    ],
    "sg:phone":"+44 1202 515471",
    "sg:postcode":"BH9 2UN",
    "sg:province":"Dorset",
    "sg:tags":[
        "roofing",
        "contracting"
    ],
    "wof:name":"R E Parsons",
    "wof:placetype":"venue"
},
  "geometry": {"coordinates":[-1.876845,50.754559],"type":"Point"}
}