{
  "type": "Feature",
  "properties": {
    "addr:full":"68 Chandos Place London Greater London WC2N 4HG",
    "addr:housenumber":"68",
    "addr:postcode":"wc2n 4hg",
    "addr:street":"Chandos Place",
    "iso:country":"GB",
    "sg:address":"68 Chandos Place",
    "sg:city":"London",
    "sg:classifiers":[
        {
            "category":"Professional",
            "subcategory":"Management & Consulting",
            "type":"Services"
        }
    ],
    "sg:phone":"+44 20 7836 5575",
    "sg:postcode":"WC2N 4HG",
    "sg:province":"Greater London",
    "sg:tags":[
        "consultant",
        "business"
    ],
    "wof:name":"The Kingstree Group (U K) Ltd.",
    "wof:placetype":"venue"
},
  "geometry": {"coordinates":[-0.1246699989,51.5101699829],"type":"Point"}
}