{
  "type": "Feature",
  "properties": {
    "addr:full":"Hertford Road Hoddesdon Essex EN11 9BU",
    "addr:postcode":"en11 9bu",
    "addr:street":"Hertford Road",
    "iso:country":"GB",
    "sg:address":"Hertford Road",
    "sg:city":"Hoddesdon",
    "sg:classifiers":[
        {
            "category":"Shopping",
            "subcategory":"Pharmacy",
            "type":"Retail Goods"
        }
    ],
    "sg:phone":"+44 1992 467272",
    "sg:postcode":"EN11 9BU",
    "sg:province":"Essex",
    "sg:tags":[
        "pharmaceutical"
    ],
    "wof:name":"Merck Sharp & Dohme Ltd.",
    "wof:placetype":"venue"
},
  "geometry": {"coordinates":[-0.0124289999,51.7656593323],"type":"Point"}
}