{
  "type": "Feature",
  "properties": {
    "iso:country":"GB",
    "sg:address":"77 Acre Lane",
    "sg:city":"London",
    "sg:classifiers":[
        {
            "category":"Fast Food",
            "type":"Food & Drink"
        }
    ],
    "sg:phone":"+44 20 7738 7870",
    "sg:postcode":"SW2 5TN",
    "sg:province":"Greater London",
    "sg:tags":[
        "away",
        "take"
    ],
    "wof:name":"Express Take Away",
    "wof:placetype":"venue"
},
  "geometry": {"coordinates":[-0.124108,51.459507],"type":"Point"}
}