{
  "type": "Feature",
  "properties": {
    "addr:full":"Rossiniere, Pikes Hey Road Wirral Merseyside CH48 1PA",
    "addr:postcode":"ch48 1pa",
    "addr:street":"Rossiniere Pikes Hey Road",
    "iso:country":"GB",
    "sg:address":"Rossiniere, Pikes Hey Road",
    "sg:city":"Wirral",
    "sg:classifiers":[
        {
            "category":"Professional",
            "subcategory":"Business Services",
            "type":"Services"
        }
    ],
    "sg:postcode":"CH48 1PA",
    "sg:province":"Merseyside",
    "sg:tags":[
        "accomodation"
    ],
    "wof:name":"Thorncrest Ventures Ltd",
    "wof:placetype":"venue"
},
  "geometry": {"coordinates":[-3.14531,53.360531],"type":"Point"}
}