{
  "type": "Feature",
  "properties": {
    "addr:full":"426 Holderness Road Hull East Riding of Yorkshire HU9 3DW",
    "addr:housenumber":"426",
    "addr:postcode":"hu9 3dw",
    "addr:street":"Holderness Road",
    "iso:country":"GB",
    "sg:address":"426 Holderness Road",
    "sg:city":"Hull",
    "sg:classifiers":[
        {
            "category":"Shopping",
            "subcategory":"Clothing, Apparel, & Fashions",
            "type":"Retail Goods"
        }
    ],
    "sg:phone":"+44 1482 708030",
    "sg:postcode":"HU9 3DW",
    "sg:province":"East Riding of Yorkshire",
    "sg:tags":[
        "shop",
        "dress",
        "fancy"
    ],
    "wof:name":"Mascarade",
    "wof:placetype":"venue"
},
  "geometry": {"coordinates":[-0.304927,53.759205],"type":"Point"}
}