{
  "type": "Feature",
  "properties": {
    "addr:full":"11 Marlborough Close Billingham Durham TS23 1BJ",
    "addr:housenumber":"11",
    "addr:postcode":"ts23 1bj",
    "addr:street":"Marlborough Close",
    "iso:country":"GB",
    "sg:address":"11 Marlborough Close",
    "sg:city":"Billingham",
    "sg:classifiers":[
        {
            "category":"Personal",
            "type":"Services"
        }
    ],
    "sg:phone":"+44 1642 553120",
    "sg:postcode":"TS23 1BJ",
    "sg:province":"Durham",
    "sg:tags":[
        "wedding"
    ],
    "wof:name":"Bryan McIvor Film Entertainments",
    "wof:placetype":"venue"
},
  "geometry": {"coordinates":[-1.291971,54.591251],"type":"Point"}
}