{
  "type": "Feature",
  "properties": {
    "iso:country":"GB",
    "sg:address":"188 Central Drive",
    "sg:city":"Blackpool",
    "sg:classifiers":[
        {
            "category":"Cafe",
            "type":"Food & Drink"
        }
    ],
    "sg:phone":"+44 1253 621095",
    "sg:postcode":"FY1 5EB",
    "sg:province":"Lancashire",
    "sg:tags":[
        "tea",
        "snack",
        "bar",
        "room"
    ],
    "wof:name":"Central Cafe",
    "wof:placetype":"venue"
},
  "geometry": {"coordinates":[-3.047132,53.810383],"type":"Point"}
}