{
  "type": "Feature",
  "properties": {
    "iso:country":"GB",
    "sg:address":"1 Mangrove Drive",
    "sg:city":"Hertford",
    "sg:classifiers":[
        {
            "category":"Professional",
            "subcategory":"Accounting & Tax Preparation",
            "type":"Services"
        }
    ],
    "sg:phone":"+44 1290 822827",
    "sg:postcode":"SG13 8AW",
    "sg:province":"Hertfordshire",
    "sg:tags":[
        "accountant"
    ],
    "wof:name":"Richard Perren",
    "wof:placetype":"venue"
},
  "geometry": {"coordinates":[-0.069874,51.789467],"type":"Point"}
}