{
  "type": "Feature",
  "properties": {
    "addr:full":"21 Headingley Lane Leeds West Yorkshire LS6 1BL",
    "addr:housenumber":"21",
    "addr:postcode":"ls6 1bl",
    "addr:street":"Headingley Lane",
    "iso:country":"GB",
    "sg:address":"21 Headingley Lane",
    "sg:city":"Leeds",
    "sg:classifiers":[
        {
            "category":"Shopping",
            "subcategory":"Florist",
            "type":"Retail Goods"
        }
    ],
    "sg:phone":"+44 113 275 5045",
    "sg:postcode":"LS6 1BL",
    "sg:province":"West Yorkshire",
    "wof:name":"Jean Crowther Florists",
    "wof:placetype":"venue"
},
  "geometry": {"coordinates":[-1.5634950399,53.8153114319],"type":"Point"}
}