{
  "type": "Feature",
  "properties": {
    "addr:full":"Bramingham La Luton Bedfordshire LU3 3NT",
    "addr:postcode":"lu3 3nt",
    "addr:street":"La",
    "iso:country":"GB",
    "sg:address":"Bramingham La",
    "sg:city":"Luton",
    "sg:classifiers":[
        {
            "category":"Health Services",
            "subcategory":"Hospice",
            "type":"Services"
        }
    ],
    "sg:phone":"+44 1582 492339",
    "sg:postcode":"LU3 3NT",
    "sg:province":"Bedfordshire",
    "wof:name":"Luton & South Beds Hospice",
    "wof:placetype":"venue"
},
  "geometry": {"coordinates":[-0.4535749853,51.9100837708],"type":"Point"}
}