{
  "type": "Feature",
  "properties": {
    "addr:full":"54 Main Street, Linton Swadlincote Derbyshire DE12 6PZ",
    "addr:housenumber":"54",
    "addr:postcode":"de12 6pz",
    "addr:street":"Main Street",
    "iso:country":"GB",
    "sg:address":"54 Main Street, Linton",
    "sg:city":"Swadlincote",
    "sg:classifiers":[
        {
            "category":"Shopping",
            "subcategory":"News",
            "type":"Retail Goods"
        },
        {
            "category":"Government",
            "subcategory":"Post Office",
            "type":"Public Place"
        }
    ],
    "sg:phone":"+44 1283 760480",
    "sg:postcode":"DE12 6PZ",
    "sg:province":"Derbyshire",
    "sg:tags":[
        "newsagent"
    ],
    "wof:name":"T BOWLER",
    "wof:placetype":"venue"
},
  "geometry": {"coordinates":[-1.596019,52.748264],"type":"Point"}
}