{
  "type": "Feature",
  "properties": {
    "addr:full":"Hilltown Farm, Molland Botreaux South Molton Devon EX36 3NW",
    "addr:housenumber":"molton",
    "addr:postcode":"ex36 3nw",
    "addr:street":"Hilltown;Molland Botreaux South",
    "iso:country":"GB",
    "sg:address":"Hilltown Farm, Molland Botreaux",
    "sg:city":"South Molton",
    "sg:classifiers":[
        {
            "category":"Home & Garden",
            "subcategory":"Garden Supply",
            "type":"Retail Goods"
        },
        {
            "category":"Farming",
            "subcategory":"Farm",
            "type":"Manufacturing & Wholesale Goods"
        }
    ],
    "sg:phone":"+44 1769 550364",
    "sg:postcode":"EX36 3NW",
    "sg:province":"Devon",
    "sg:tags":[
        "mixed",
        "bulb",
        "crop",
        "grower"
    ],
    "wof:name":"MESSRS NICHOLLS",
    "wof:placetype":"venue"
},
  "geometry": {"coordinates":[-3.8318240643,51.0176467896],"type":"Point"}
}