{
  "type": "Feature",
  "properties": {
    "iso:country":"GB",
    "sg:address":"54 Well Street",
    "sg:city":"London",
    "sg:classifiers":[
        {
            "category":"Travel",
            "subcategory":"Hotels & Motels",
            "type":"Entertainment"
        }
    ],
    "sg:phone":"+44 20 8985 9720",
    "sg:postcode":"E9 7PX",
    "sg:province":"Greater London",
    "wof:name":"Wells Hotel",
    "wof:placetype":"venue"
},
  "geometry": {"coordinates":[-0.0535040013,51.5399856567],"type":"Point"}
}