{
  "type": "Feature",
  "properties": {
    "addr:full":"117 St James Street Newport Isle of Wight PO30 5HB",
    "addr:housenumber":"117",
    "addr:postcode":"po30 5hb",
    "addr:street":"St James Street",
    "iso:country":"GB",
    "sg:address":"117 St James Street",
    "sg:city":"Newport",
    "sg:classifiers":[
        {
            "category":"Shopping",
            "subcategory":"Shoes",
            "type":"Retail Goods"
        }
    ],
    "sg:postcode":"PO30 5HB",
    "sg:province":"Isle of Wight",
    "sg:tags":[
        "shop"
    ],
    "wof:name":"Clogs",
    "wof:placetype":"venue"
},
  "geometry": {"coordinates":[-1.2970130444,50.7019805908],"type":"Point"}
}