{
  "type": "Feature",
  "properties": {
    "addr:full":"White Carr, Lancaster Rd, Forton Preston Lancashire PR3 0BP",
    "addr:postcode":"pr3 0bp",
    "addr:street":"White Carr Lancaster Rd",
    "iso:country":"GB",
    "sg:address":"White Carr, Lancaster Rd, Forton",
    "sg:city":"Preston",
    "sg:classifiers":[
        {
            "category":"Travel",
            "subcategory":"Hotels & Motels",
            "type":"Entertainment"
        }
    ],
    "sg:postcode":"PR3 0BP",
    "sg:province":"Lancashire",
    "sg:tags":[
        "house",
        "guest"
    ],
    "wof:name":"Young,E T,",
    "wof:placetype":"venue"
},
  "geometry": {"coordinates":[-2.7814939022,53.9563865662],"type":"Point"}
}