{
  "type": "Feature",
  "properties": {
    "addr:full":"2 Brinsworth Lane, Brinsworth Rotherham South Yorkshire S60 5BS",
    "addr:housenumber":"2",
    "addr:postcode":"s60 5bs",
    "addr:street":"Brinsworth Lane",
    "iso:country":"GB",
    "sg:address":"2 Brinsworth Lane, Brinsworth",
    "sg:city":"Rotherham",
    "sg:classifiers":[
        {
            "category":"Food & Beverages",
            "subcategory":"Bakery",
            "type":"Retail Goods"
        }
    ],
    "sg:phone":"+44 1709 376312",
    "sg:postcode":"S60 5BS",
    "sg:province":"South Yorkshire",
    "sg:tags":[
        "shop",
        "baker"
    ],
    "wof:name":"Cooplands (Doncaster) Ltd.",
    "wof:placetype":"venue"
},
  "geometry": {"coordinates":[-1.3762630224,53.4037513733],"type":"Point"}
}