{
  "type": "Feature",
  "properties": {
    "addr:full":"53a Lesbourne Rd Reigate Surrey RH2 7JX",
    "addr:housenumber":"53a",
    "addr:postcode":"rh2 7jx",
    "addr:street":"Lesbourne Rd",
    "iso:country":"GB",
    "sg:address":"53a Lesbourne Rd",
    "sg:city":"Reigate",
    "sg:classifiers":[
        {
            "category":"Personal",
            "subcategory":"Beauty Salon",
            "type":"Services"
        }
    ],
    "sg:postcode":"RH2 7JX",
    "sg:province":"Surrey",
    "sg:tags":[
        "unisex",
        "hairdresser"
    ],
    "wof:name":"Evans,Karen,",
    "wof:placetype":"venue"
},
  "geometry": {"coordinates":[-0.1986189932,51.2337150574],"type":"Point"}
}