{
  "type": "Feature",
  "properties": {
    "iso:country":"GB",
    "sg:address":"339-340 Upper St",
    "sg:city":"London",
    "sg:classifiers":[
        {
            "category":"Professional",
            "subcategory":"Management & Consulting",
            "type":"Services"
        }
    ],
    "sg:postcode":"N1 0PD",
    "sg:province":"Greater London",
    "sg:tags":[
        "project"
    ],
    "wof:name":"Grand Management Agents Ltd",
    "wof:placetype":"venue"
},
  "geometry": {"coordinates":[-0.103913,51.535198],"type":"Point"}
}