{
  "type": "Feature",
  "properties": {
    "iso:country":"GB",
    "sg:address":"16 Petworth Avenue, Beeston",
    "sg:city":"Nottingham",
    "sg:classifiers":[
        {
            "category":"Wholesale",
            "subcategory":"Books, Periodicals, & Newspapers",
            "type":"Manufacturing & Wholesale Goods"
        }
    ],
    "sg:phone":"+44 115 946 9066",
    "sg:postcode":"NG9 6JF",
    "sg:province":"Nottinghamshire",
    "sg:tags":[
        "publishing"
    ],
    "wof:name":"H D Science Ltd.",
    "wof:placetype":"venue"
},
  "geometry": {"coordinates":[-1.259352,52.913815],"type":"Point"}
}