{
  "type": "Feature",
  "properties": {
    "iso:country":"GB",
    "sg:address":"Granary Rural Business Cen, Broad Farm North Street, Hellingly",
    "sg:city":"Hailsham",
    "sg:classifiers":[
        {
            "category":"Professional",
            "subcategory":"Engineering",
            "type":"Services"
        }
    ],
    "sg:postcode":"BN27 4DU",
    "sg:province":"East Sussex",
    "sg:tags":[
        "contractor",
        "electrical",
        "engineer"
    ],
    "wof:name":"K J Electrical",
    "wof:placetype":"venue"
},
  "geometry": {"coordinates":[0.25868,50.888432],"type":"Point"}
}