{
  "type": "Feature",
  "properties": {
    "iso:country":"GB",
    "sg:address":"5 Winnowsty Lane",
    "sg:city":"Lincoln",
    "sg:classifiers":[
        {
            "category":"Professional",
            "subcategory":"Art Services",
            "type":"Services"
        }
    ],
    "sg:postcode":"LN2 5RZ",
    "sg:province":"Lincolnshire",
    "sg:tags":[
        "graphic",
        "designer"
    ],
    "wof:name":"P Stafford",
    "wof:placetype":"venue"
},
  "geometry": {"coordinates":[-0.530925,53.234482],"type":"Point"}
}