{
  "type": "Feature",
  "properties": {
    "addr:full":"21 Grosvenor Clo Ringwood Dorset BH24 2HG",
    "addr:housenumber":"21;clo",
    "addr:postcode":"bh24 2hg",
    "addr:street":"Grosvenor",
    "iso:country":"GB",
    "sg:address":"21 Grosvenor Clo",
    "sg:city":"Ringwood",
    "sg:classifiers":[
        {
            "category":"Professional",
            "subcategory":"Computer Services",
            "type":"Services"
        }
    ],
    "sg:phone":"+44 1425 461661",
    "sg:postcode":"BH24 2HG",
    "sg:province":"Dorset",
    "sg:tags":[
        "consultant"
    ],
    "wof:name":"Jim & Penny Jackson",
    "wof:placetype":"venue"
},
  "geometry": {"coordinates":[-1.84871,50.83707],"type":"Point"}
}