{
  "type": "Feature",
  "properties": {
    "addr:full":"Pleasance Square Falkirk Falkirk FK1 1BQ",
    "addr:postcode":"fk1 1bq",
    "addr:street":"Pleasance Square",
    "iso:country":"GB",
    "sg:address":"Pleasance Square",
    "sg:city":"Falkirk",
    "sg:classifiers":[
        {
            "category":"Arena",
            "subcategory":"Sports Club",
            "type":"Entertainment"
        }
    ],
    "sg:phone":"+44 1324 629389",
    "sg:postcode":"FK1 1BQ",
    "sg:province":"Falkirk",
    "wof:name":"Adrian Bowling Club",
    "wof:placetype":"venue"
},
  "geometry": {"coordinates":[-3.7862739563,55.9979286194],"type":"Point"}
}