{
  "type": "Feature",
  "properties": {
    "addr:full":"4 Wakefield Road Pontefract North Yorkshire WF8 4HN",
    "addr:housenumber":"4",
    "addr:postcode":"wf8 4hn",
    "addr:street":"Wakefield Road",
    "iso:country":"GB",
    "sg:address":"4 Wakefield Road",
    "sg:city":"Pontefract",
    "sg:classifiers":[
        {
            "category":"Bars & Pubs",
            "type":"Food & Drink"
        }
    ],
    "sg:postcode":"WF8 4HN",
    "sg:province":"North Yorkshire",
    "sg:tags":[
        "pubs",
        "inn"
    ],
    "wof:name":"Robin Hood Inn",
    "wof:placetype":"venue"
},
  "geometry": {"coordinates":[-1.3148369789,53.6886901855],"type":"Point"}
}