{
  "type": "Feature",
  "properties": {
    "addr:full":"Home Farm, Tingrith Milton Keynes Bedfordshire MK17 9EW",
    "addr:postcode":"mk17 9ew",
    "iso:country":"GB",
    "sg:address":"Home Farm, Tingrith",
    "sg:city":"Milton Keynes",
    "sg:classifiers":[
        {
            "category":"Professional",
            "subcategory":"Business Services",
            "type":"Services"
        }
    ],
    "sg:postcode":"MK17 9EW",
    "sg:province":"Bedfordshire",
    "sg:tags":[
        "import",
        "export",
        "agent"
    ],
    "wof:name":"Chiltern Gas",
    "wof:placetype":"venue"
},
  "geometry": {"coordinates":[-0.5894820094,51.9668769836],"type":"Point"}
}