{
  "type": "Feature",
  "properties": {
    "addr:full":"12a Emanuel Avenue London Greater London W3 6JH",
    "addr:housenumber":"12a",
    "addr:postcode":"w3 6jh",
    "addr:street":"Emanuel Avenue",
    "iso:country":"GB",
    "sg:address":"12a Emanuel Avenue",
    "sg:city":"London",
    "sg:classifiers":[
        {
            "category":"Retail",
            "subcategory":"Auto Repair",
            "type":"Services"
        }
    ],
    "sg:phone":"+44 20 8992 2655",
    "sg:postcode":"W3 6JH",
    "sg:province":"Greater London",
    "sg:tags":[
        "modification",
        "garage",
        "related"
    ],
    "wof:name":"Knights Of London",
    "wof:placetype":"venue"
},
  "geometry": {"coordinates":[-0.266106,51.516171],"type":"Point"}
}