{
  "type": "Feature",
  "properties": {
    "addr:full":"Surveyors, 13 Southgate Street Winchester Hampshire SO23 9DZ",
    "addr:housenumber":"13",
    "addr:postcode":"so23 9dz",
    "addr:street":"Southgate Street",
    "iso:country":"GB",
    "sg:address":"Surveyors, 13 Southgate Street",
    "sg:city":"Winchester",
    "sg:classifiers":[
        {
            "category":"Real Estate",
            "subcategory":"Real Estate Agent",
            "type":"Services"
        }
    ],
    "sg:phone":"+44 1962 820157",
    "sg:postcode":"SO23 9DZ",
    "sg:province":"Hampshire",
    "wof:name":"Royal & Sun Alliance Insurance Plc",
    "wof:placetype":"venue"
},
  "geometry": {"coordinates":[-1.316809,51.063068],"type":"Point"}
}