{
  "type": "Feature",
  "properties": {
    "addr:full":"5 Hawk Yard, Greenfield Oldham Lancashire OL3 7NP",
    "addr:housenumber":"5",
    "addr:postcode":"ol3 7np",
    "addr:street":"Hawk Yard",
    "iso:country":"GB",
    "sg:address":"5 Hawk Yard, Greenfield",
    "sg:city":"Oldham",
    "sg:classifiers":[
        {
            "category":"Professional",
            "subcategory":"Management & Consulting",
            "type":"Services"
        }
    ],
    "sg:postcode":"OL3 7NP",
    "sg:province":"Lancashire",
    "sg:tags":[
        "consultant",
        "energy",
        "conservation"
    ],
    "wof:name":"Energy Inform Limited",
    "wof:placetype":"venue"
},
  "geometry": {"coordinates":[-2.0078439713,53.5329208374],"type":"Point"}
}