{
  "type": "Feature",
  "properties": {
    "iso:country":"GB",
    "sg:address":"23 High Street, Yeadon",
    "sg:city":"Leeds",
    "sg:classifiers":[
        {
            "category":"Food & Beverages",
            "subcategory":"Bakery",
            "type":"Retail Goods"
        }
    ],
    "sg:phone":"+44 113 250 1455",
    "sg:postcode":"LS19 7SP",
    "sg:province":"West Yorkshire",
    "sg:tags":[
        "baker"
    ],
    "wof:name":"Haighs Bakery",
    "wof:placetype":"venue"
},
  "geometry": {"coordinates":[-1.683738,53.866322],"type":"Point"}
}