{
  "type": "Feature",
  "properties": {
    "iso:country":"GB",
    "sg:address":"33 Market Row",
    "sg:city":"Great Yarmouth",
    "sg:classifiers":[
        {
            "category":"Shopping",
            "subcategory":"Clothing, Apparel, & Fashions",
            "type":"Retail Goods"
        }
    ],
    "sg:phone":"+44 1493 856527",
    "sg:postcode":"NR30 1PB",
    "sg:province":"Norfolk",
    "sg:tags":[
        "menswear"
    ],
    "wof:name":"Traddles",
    "wof:placetype":"venue"
},
  "geometry": {"coordinates":[1.726847,52.608635],"type":"Point"}
}