{
  "type": "Feature",
  "properties": {
    "iso:country":"GB",
    "sg:address":"Units 5 & 6 Rectory Lane",
    "sg:city":"Guisborough",
    "sg:classifiers":[
        {
            "category":"Manufacturing",
            "subcategory":"Signs",
            "type":"Manufacturing & Wholesale Goods"
        }
    ],
    "sg:postcode":"TS14 7DH",
    "sg:province":"North Yorkshire",
    "sg:tags":[
        "nameplate"
    ],
    "wof:name":"Buckle Signs",
    "wof:placetype":"venue"
},
  "geometry": {"coordinates":[-1.05863,54.530899],"type":"Point"}
}