{
  "type": "Feature",
  "properties": {
    "iso:country":"GB",
    "sg:address":"11 Clachnaharry Road",
    "sg:city":"Inverness",
    "sg:classifiers":[
        {
            "category":"Travel",
            "subcategory":"Hotels & Motels",
            "type":"Entertainment"
        }
    ],
    "sg:postcode":"IV3 8LT",
    "sg:province":"Highland",
    "wof:name":"Muirtown Lodge",
    "wof:placetype":"venue"
},
  "geometry": {"coordinates":[-4.249223,57.483601],"type":"Point"}
}