{
  "type": "Feature",
  "properties": {
    "addr:full":"Stansted Road Eastbourne East Sussex BN22 8LG",
    "addr:postcode":"bn22 8lg",
    "addr:street":"Stansted Road",
    "iso:country":"GB",
    "sg:address":"Stansted Road",
    "sg:city":"Eastbourne",
    "sg:classifiers":[
        {
            "category":"Retail",
            "subcategory":"Auto Repair",
            "type":"Services"
        }
    ],
    "sg:phone":"+44 1323 646016",
    "sg:postcode":"BN22 8LG",
    "sg:province":"East Sussex",
    "sg:tags":[
        "modification",
        "garage"
    ],
    "wof:name":"Westgate Motors",
    "wof:placetype":"venue"
},
  "geometry": {"coordinates":[0.2892009914,50.7760467529],"type":"Point"}
}