{
  "type": "Feature",
  "properties": {
    "addr:full":"24 Upper High Street Epsom Surrey KT17 4QJ",
    "addr:housenumber":"24",
    "addr:postcode":"kt17 4qj",
    "addr:street":"Upper High Street",
    "iso:country":"GB",
    "sg:address":"24 Upper High Street",
    "sg:city":"Epsom",
    "sg:classifiers":[
        {
            "category":"Professional",
            "subcategory":"Lawyer & Legal Services",
            "type":"Services"
        }
    ],
    "sg:phone":"+44 1372 741877",
    "sg:postcode":"KT17 4QJ",
    "sg:province":"Surrey",
    "sg:tags":[
        "solicitor"
    ],
    "wof:name":"Tavner & Co.",
    "wof:placetype":"venue"
},
  "geometry": {"coordinates":[-0.2616949975,51.3342323303],"type":"Point"}
}