{
  "type": "Feature",
  "properties": {
    "addr:full":"44 Barn Street Birmingham West Midlands B5 5QB",
    "addr:housenumber":"44",
    "addr:postcode":"b5 5qb",
    "addr:street":"Barn Street",
    "iso:country":"GB",
    "sg:address":"44 Barn Street",
    "sg:city":"Birmingham",
    "sg:classifiers":[
        {
            "category":"Autos & Motor Vehicles",
            "subcategory":"Automobile Sales",
            "type":"Retail Goods"
        },
        {
            "category":"Manufacturing",
            "subcategory":"Metals",
            "type":"Manufacturing & Wholesale Goods"
        }
    ],
    "sg:phone":"+44 121 643 0408",
    "sg:postcode":"B5 5QB",
    "sg:province":"West Midlands",
    "sg:tags":[
        "product",
        "barrow",
        "truck",
        "fabricated",
        "maker"
    ],
    "wof:name":"Avonstar Trading Co. Ltd.",
    "wof:placetype":"venue"
},
  "geometry": {"coordinates":[-1.8839880228,52.47864151],"type":"Point"}
}