{
  "type": "Feature",
  "properties": {
    "iso:country":"GB",
    "sg:address":"Clews Farm, Butterton Moor",
    "sg:city":"Leek",
    "sg:classifiers":[
        {
            "category":"Transit Center",
            "subcategory":"Passenger",
            "type":"Transportation"
        }
    ],
    "sg:phone":"+44 1538 304244",
    "sg:postcode":"ST13 7TQ",
    "sg:province":"Staffordshire",
    "sg:tags":[
        "boarding",
        "kennel",
        "catteries"
    ],
    "wof:name":"Chenoir Kennels",
    "wof:placetype":"venue"
},
  "geometry": {"coordinates":[-1.889406,53.105389],"type":"Point"}
}