{
  "type": "Feature",
  "properties": {
    "iso:country":"GB",
    "sg:address":"2 Munday Close, Bussage",
    "sg:city":"Stroud",
    "sg:classifiers":[
        {
            "category":"Organizations",
            "subcategory":"Non-profit Organization",
            "type":"Services"
        }
    ],
    "sg:phone":"+44 1453 886094",
    "sg:postcode":"GL6 8DG",
    "sg:province":"Gloucestershire",
    "sg:tags":[
        "organisation",
        "voluntary",
        "charity"
    ],
    "wof:name":"Leukaemia Research Fund",
    "wof:placetype":"venue"
},
  "geometry": {"coordinates":[-2.1653161049,51.7325515747],"type":"Point"}
}