{
  "type": "Feature",
  "properties": {
    "addr:full":"Whitehall Properties, Town Gate Bradford West Yorkshire BD12 9JQ",
    "addr:postcode":"bd12 9jq",
    "addr:street":"Town Gate Bradford West",
    "iso:country":"GB",
    "sg:address":"Whitehall Properties, Town Gate",
    "sg:city":"Bradford",
    "sg:classifiers":[
        {
            "category":"Professional",
            "subcategory":"Detective & Security Services",
            "type":"Services"
        }
    ],
    "sg:phone":"+44 1274 600251",
    "sg:postcode":"BD12 9JQ",
    "sg:province":"West Yorkshire",
    "wof:name":"J Reynolds Security",
    "wof:placetype":"venue"
},
  "geometry": {"coordinates":[-1.7583060265,53.7957382202],"type":"Point"}
}