{
  "type": "Feature",
  "properties": {
    "addr:full":"19 Malden Road London Greater London NW5 3HY",
    "addr:housenumber":"19",
    "addr:postcode":"nw5 3hy",
    "addr:street":"Malden Road",
    "iso:country":"GB",
    "sg:address":"19 Malden Road",
    "sg:city":"London",
    "sg:classifiers":[
        {
            "category":"Personal",
            "subcategory":"Beauty Salon",
            "type":"Services"
        }
    ],
    "sg:phone":"+44 20 7267 3975",
    "sg:postcode":"NW5 3HY",
    "sg:province":"Greater London",
    "sg:tags":[
        "unisex",
        "hairdresser"
    ],
    "wof:name":"Attractions",
    "wof:placetype":"venue"
},
  "geometry": {"coordinates":[-0.1516519934,51.5469512939],"type":"Point"}
}