{
  "type": "Feature",
  "properties": {
    "addr:full":"8 Stonleigh Park Road Epsom Surrey KT19 0QT",
    "addr:housenumber":"8",
    "addr:postcode":"kt19 0qt",
    "addr:street":"Stonleigh Park Road",
    "iso:country":"GB",
    "sg:address":"8 Stonleigh Park Road",
    "sg:city":"Epsom",
    "sg:classifiers":[
        {
            "category":"Taxi",
            "type":"Transportation"
        }
    ],
    "sg:phone":"+44 20 8393 9600",
    "sg:postcode":"KT19 0QT",
    "sg:province":"Surrey",
    "sg:tags":[
        "mini",
        "cab"
    ],
    "wof:name":"Ewell Comfy Cars",
    "wof:placetype":"venue"
},
  "geometry": {"coordinates":[-0.25213,51.360748],"type":"Point"}
}