{
  "type": "Feature",
  "properties": {
    "addr:full":"Speldhurst Place, Speldhurst Road Tunbridge Wells Kent TN4 0JB",
    "addr:postcode":"tn4 0jb",
    "addr:street":"Speldhurst Place Speldhurst Road",
    "iso:country":"GB",
    "sg:address":"Speldhurst Place, Speldhurst Road",
    "sg:city":"Tunbridge Wells",
    "sg:classifiers":[
        {
            "category":"Shopping",
            "subcategory":"Books",
            "type":"Retail Goods"
        }
    ],
    "sg:phone":"+44 1892 511600",
    "sg:postcode":"TN4 0JB",
    "sg:province":"Kent",
    "wof:name":"Wells Medical Ltd.",
    "wof:placetype":"venue"
},
  "geometry": {"coordinates":[0.2601949871,51.1537017822],"type":"Point"}
}