{
  "type": "Feature",
  "properties": {
    "iso:country":"GB",
    "sg:address":"39 Main Street, Branston",
    "sg:city":"Burton-on-trent",
    "sg:classifiers":[
        {
            "category":"Food & Beverages",
            "subcategory":"Meat & Fish",
            "type":"Retail Goods"
        }
    ],
    "sg:phone":"+44 1283 509251",
    "sg:postcode":"DE14 3EY",
    "sg:province":"Derbyshire",
    "sg:tags":[
        "chip"
    ],
    "wof:name":"The Golden Fry Take Away",
    "wof:placetype":"venue"
},
  "geometry": {"coordinates":[-1.659069,52.78764],"type":"Point"}
}