{
  "type": "Feature",
  "properties": {
    "addr:full":"271 Bath Road Hounslow Greater London TW3 3DA",
    "addr:housenumber":"271",
    "addr:postcode":"tw3 3da",
    "addr:street":"Bath Road",
    "iso:country":"GB",
    "sg:address":"271 Bath Road",
    "sg:city":"Hounslow",
    "sg:classifiers":[
        {
            "category":"Personal",
            "subcategory":"Beauty Salon",
            "type":"Services"
        }
    ],
    "sg:phone":"+44 20 8570 1892",
    "sg:postcode":"TW3 3DA",
    "sg:province":"Greater London",
    "sg:tags":[
        "unisex",
        "hairdresser"
    ],
    "wof:name":"Andrea & Pamela Hair Fashion",
    "wof:placetype":"venue"
},
  "geometry": {"coordinates":[-0.380872,51.471188],"type":"Point"}
}