{
  "type": "Feature",
  "properties": {
    "iso:country":"GB",
    "sg:address":"104 Pall Mall",
    "sg:city":"London",
    "sg:classifiers":[
        {
            "category":"Organizations",
            "subcategory":"Membership Organization",
            "type":"Services"
        }
    ],
    "sg:phone":"+44 20 7930 9374",
    "sg:postcode":"SW1Y 5EW",
    "sg:province":"Greater London",
    "sg:tags":[
        "club"
    ],
    "wof:name":"The Reform Club",
    "wof:placetype":"venue"
},
  "geometry": {"coordinates":[-0.1338990033,51.5067100525],"type":"Point"}
}