{
  "type": "Feature",
  "properties": {
    "addr:full":"Waterhall Road Cardiff Cardiff CF5 3LL",
    "addr:postcode":"cf5 3ll",
    "addr:street":"Waterhall Road",
    "iso:country":"GB",
    "sg:address":"Waterhall Road",
    "sg:city":"Cardiff",
    "sg:classifiers":[
        {
            "category":"Community Center",
            "type":"Public Place"
        },
        {
            "category":"Government",
            "subcategory":"Office",
            "type":"Public Place"
        }
    ],
    "sg:phone":"+44 29 2055 2210",
    "sg:postcode":"CF5 3LL",
    "sg:province":"Cardiff",
    "sg:tags":[
        "recreation",
        "local",
        "leisure",
        "centre"
    ],
    "wof:name":"Fairwater Leisure Centre",
    "wof:placetype":"venue"
},
  "geometry": {"coordinates":[-3.245579,51.499065],"type":"Point"}
}