{
  "type": "Feature",
  "properties": {
    "iso:country":"GB",
    "sg:address":"Esgairgyfela",
    "sg:city":"Aberdovey",
    "sg:classifiers":[
        {
            "category":"Farming",
            "subcategory":"Livestock Farm",
            "type":"Manufacturing & Wholesale Goods"
        }
    ],
    "sg:postcode":"LL35 0SP",
    "sg:province":"Gwynedd",
    "sg:tags":[
        "others"
    ],
    "wof:name":"D Owen & Co.",
    "wof:placetype":"venue"
},
  "geometry": {"coordinates":[-4.044138,52.544083],"type":"Point"}
}