{
  "type": "Feature",
  "properties": {
    "iso:country":"GB",
    "sg:address":"Bilston Lane",
    "sg:city":"Willenhall",
    "sg:classifiers":[
        {
            "category":"Organizations",
            "subcategory":"Membership Organization",
            "type":"Services"
        }
    ],
    "sg:phone":"+44 1902 605120",
    "sg:postcode":"WV13 2QF",
    "sg:province":"West Midlands",
    "sg:tags":[
        "club"
    ],
    "wof:name":"Crescent Friendship Club",
    "wof:placetype":"venue"
},
  "geometry": {"coordinates":[-2.0471169949,52.5802955627],"type":"Point"}
}