{
  "type": "Feature",
  "properties": {
    "iso:country":"GB",
    "sg:address":"Wraysbury Chambers, Crowborough Hill",
    "sg:city":"Crowborough",
    "sg:classifiers":[
        {
            "category":"Building & Trades",
            "subcategory":"Equipment Rental",
            "type":"Services"
        }
    ],
    "sg:phone":"+44 1892 662777",
    "sg:postcode":"TN6 2JE",
    "sg:province":"East Sussex",
    "sg:tags":[
        "plant",
        "hire",
        "tool",
        "machinery"
    ],
    "wof:name":"Coppard Plant Hire Ltd",
    "wof:placetype":"venue"
},
  "geometry": {"coordinates":[0.171893,51.053196],"type":"Point"}
}