{
  "type": "Feature",
  "properties": {
    "addr:full":"1-5 High Street, Soham Ely Cambridgeshire CB7 5HB",
    "addr:housenumber":"1-5",
    "addr:postcode":"cb7 5hb",
    "addr:street":"High Street",
    "iso:country":"GB",
    "sg:address":"1-5 High Street, Soham",
    "sg:city":"Ely",
    "sg:classifiers":[
        {
            "category":"Retail",
            "subcategory":"Auto Repair",
            "type":"Services"
        }
    ],
    "sg:phone":"+44 1353 720779",
    "sg:postcode":"CB7 5HB",
    "sg:province":"Cambridgeshire",
    "sg:tags":[
        "modification",
        "garage",
        "related"
    ],
    "wof:name":"Crown Garage Ltd",
    "wof:placetype":"venue"
},
  "geometry": {"coordinates":[0.3387419879,52.3310661316],"type":"Point"}
}