{
  "type": "Feature",
  "properties": {
    "addr:full":"Fishermans Walk Bembridge Isle of Wight PO35 5TH",
    "addr:postcode":"po35 5th",
    "addr:street":"Fishermans Walk",
    "iso:country":"GB",
    "sg:address":"Fishermans Walk",
    "sg:city":"Bembridge",
    "sg:classifiers":[
        {
            "category":"Recreation",
            "subcategory":"Campground",
            "type":"Entertainment"
        }
    ],
    "sg:phone":"+44 1983 873931",
    "sg:postcode":"PO35 5TH",
    "sg:province":"Isle of Wight",
    "sg:tags":[
        "holiday",
        "centre",
        "camp"
    ],
    "wof:name":"Bembridge Adult Village",
    "wof:placetype":"venue"
},
  "geometry": {"coordinates":[-1.071962,50.687988],"type":"Point"}
}