{
  "type": "Feature",
  "properties": {
    "iso:country":"GB",
    "sg:address":"59 Sussex Road",
    "sg:city":"Carshalton",
    "sg:classifiers":[
        {
            "category":"Shopping",
            "subcategory":"Florist",
            "type":"Retail Goods"
        }
    ],
    "sg:phone":"+44 20 8643 5710",
    "sg:postcode":"SM5 3LT",
    "sg:province":"Surrey",
    "wof:name":"Flower Ranger",
    "wof:placetype":"venue"
},
  "geometry": {"coordinates":[-0.165243,51.356663],"type":"Point"}
}