{
  "type": "Feature",
  "properties": {
    "addr:full":"Sandbed Hebden Bridge West Yorkshire HX7 6PT",
    "addr:postcode":"hx7 6pt",
    "addr:street":"West",
    "iso:country":"GB",
    "sg:address":"Sandbed",
    "sg:city":"Hebden Bridge",
    "sg:classifiers":[
        {
            "category":"Retail",
            "subcategory":"Auto Repair",
            "type":"Services"
        }
    ],
    "sg:phone":"+44 1422 842908",
    "sg:postcode":"HX7 6PT",
    "sg:province":"West Yorkshire",
    "sg:tags":[
        "modification",
        "garage",
        "related"
    ],
    "wof:name":"MURTS MOTORS CENTRE",
    "wof:placetype":"venue"
},
  "geometry": {"coordinates":[-2.046686,53.732517],"type":"Point"}
}