{
  "type": "Feature",
  "properties": {
    "addr:full":"43 Broad Street, Blaenavon Newport Monmouthshire NP4 9NH",
    "addr:housenumber":"43",
    "addr:postcode":"np4 9nh",
    "addr:street":"Broad Street",
    "iso:country":"GB",
    "sg:address":"43 Broad Street, Blaenavon",
    "sg:city":"Newport",
    "sg:classifiers":[
        {
            "category":"Bars & Pubs",
            "type":"Food & Drink"
        }
    ],
    "sg:phone":"+44 1495 790256",
    "sg:postcode":"NP4 9NH",
    "sg:province":"Monmouthshire",
    "sg:tags":[
        "pubs",
        "inn"
    ],
    "wof:name":"Rolling Mill",
    "wof:placetype":"venue"
},
  "geometry": {"coordinates":[-3.083929,51.774487],"type":"Point"}
}