{
  "type": "Feature",
  "properties": {
    "iso:country":"GB",
    "sg:address":"Mill St",
    "sg:city":"Watchet",
    "sg:classifiers":[
        {
            "category":"Home & Garden",
            "subcategory":"Building Materials",
            "type":"Retail Goods"
        }
    ],
    "sg:phone":"+44 1984 634825",
    "sg:postcode":"TA23 0AR",
    "sg:province":"Somerset",
    "sg:tags":[
        "garage",
        "door"
    ],
    "wof:name":"Browns Engineering Services",
    "wof:placetype":"venue"
},
  "geometry": {"coordinates":[-3.330244,51.180626],"type":"Point"}
}