{
  "type": "Feature",
  "properties": {
    "iso:country":"GB",
    "sg:address":"48 Farndale Road",
    "sg:city":"Knaresborough",
    "sg:classifiers":[
        {
            "category":"Banks & Credit Unions",
            "subcategory":"Bank",
            "type":"Services"
        },
        {
            "category":"Insurance",
            "subcategory":"Life Insurance",
            "type":"Services"
        }
    ],
    "sg:phone":"+44 1423 867905",
    "sg:postcode":"HG5 0NY",
    "sg:province":"North Yorkshire",
    "sg:tags":[
        "broker",
        "mortgage",
        "assurance"
    ],
    "wof:name":"Mount Financial Services",
    "wof:placetype":"venue"
},
  "geometry": {"coordinates":[-1.44667,54.01046],"type":"Point"}
}