{
  "type": "Feature",
  "properties": {
    "addr:full":"82 Muscliffe Road Bournemouth Dorset BH9 1PZ",
    "addr:housenumber":"82",
    "addr:postcode":"bh9 1pz",
    "addr:street":"Muscliffe Road",
    "iso:country":"GB",
    "sg:address":"82 Muscliffe Road",
    "sg:city":"Bournemouth",
    "sg:classifiers":[
        {
            "category":"Professional",
            "subcategory":"Engineering",
            "type":"Services"
        }
    ],
    "sg:phone":"+44 1202 510657",
    "sg:postcode":"BH9 1PZ",
    "sg:province":"Dorset",
    "sg:tags":[
        "hydraulic",
        "engineer"
    ],
    "wof:name":"Hydraulic Ram Engineering",
    "wof:placetype":"venue"
},
  "geometry": {"coordinates":[-1.8739949465,50.7481994629],"type":"Point"}
}