{
  "type": "Feature",
  "properties": {
    "iso:country":"GB",
    "sg:address":"69 Boothferry Road",
    "sg:city":"Goole",
    "sg:classifiers":[
        {
            "category":"Professional",
            "subcategory":"Art Services",
            "type":"Services"
        }
    ],
    "sg:phone":"+44 1405 763107",
    "sg:postcode":"DN14 6BB",
    "sg:province":"East Riding of Yorkshire",
    "sg:tags":[
        "photographer"
    ],
    "wof:name":"Burnitt's Fastfote",
    "wof:placetype":"venue"
},
  "geometry": {"coordinates":[-0.87608,53.705025],"type":"Point"}
}