{
  "type": "Feature",
  "properties": {
    "iso:country":"GB",
    "sg:address":"371 Dunstable Road",
    "sg:city":"Luton",
    "sg:classifiers":[
        {
            "category":"Food & Beverages",
            "subcategory":"Bakery",
            "type":"Retail Goods"
        },
        {
            "category":"Wholesale",
            "subcategory":"Groceries",
            "type":"Manufacturing & Wholesale Goods"
        }
    ],
    "sg:phone":"+44 1582 494455",
    "sg:postcode":"LU4 8BY",
    "sg:province":"Bedfordshire",
    "sg:tags":[
        "supplier",
        "pizza"
    ],
    "wof:name":"Dinos Dial A Pizza",
    "wof:placetype":"venue"
},
  "geometry": {"coordinates":[-0.441695,51.889786],"type":"Point"}
}