{
  "type": "Feature",
  "properties": {
    "addr:full":"11 Ladywell Rd Lewisham Greater London SE13 7UT",
    "addr:housenumber":"11",
    "addr:postcode":"se13 7ut",
    "addr:street":"Ladywell Rd",
    "iso:country":"GB",
    "sg:address":"11 Ladywell Rd",
    "sg:city":"Lewisham",
    "sg:classifiers":[
        {
            "category":"Shopping",
            "subcategory":"Used Merchandise",
            "type":"Retail Goods"
        }
    ],
    "sg:phone":"+44 20 8690 7879",
    "sg:postcode":"SE13 7UT",
    "sg:province":"Greater London",
    "sg:tags":[
        "furniture"
    ],
    "wof:name":"Glenview Secondhand Goods",
    "wof:placetype":"venue"
},
  "geometry": {"coordinates":[-0.01629,51.456802],"type":"Point"}
}