{
  "type": "Feature",
  "properties": {
    "addr:full":"64-64a Shepherds Bush Market Shepherd's Bush Greater London W12 8DQ",
    "addr:housenumber":"64-64a",
    "addr:postcode":"w12 8dq",
    "addr:street":"Shepherds Bush Market",
    "iso:country":"GB",
    "sg:address":"64-64a Shepherds Bush Market",
    "sg:city":"Shepherd's Bush",
    "sg:classifiers":[
        {
            "category":"Shopping",
            "subcategory":"Jewelry",
            "type":"Retail Goods"
        }
    ],
    "sg:phone":"+44 20 8749 6977",
    "sg:postcode":"W12 8DQ",
    "sg:province":"Greater London",
    "sg:tags":[
        "gold",
        "silversmith"
    ],
    "wof:name":"Rainbow Fashion Jewellery",
    "wof:placetype":"venue"
},
  "geometry": {"coordinates":[-0.22679,51.50325],"type":"Point"}
}