{
  "type": "Feature",
  "properties": {
    "iso:country":"GB",
    "sg:address":"Central Block, Kingsway, Team Valley Trading Estate",
    "sg:city":"Gateshead",
    "sg:classifiers":[
        {
            "category":"Professional",
            "subcategory":"Engineering",
            "type":"Services"
        }
    ],
    "sg:phone":"+44 191 491 1882",
    "sg:postcode":"NE11 0JT",
    "sg:province":"Tyne and Wear",
    "sg:tags":[
        "consulting",
        "engineer"
    ],
    "wof:name":"David Lambert Associates",
    "wof:placetype":"venue"
},
  "geometry": {"coordinates":[-1.620399,54.933113],"type":"Point"}
}