{
  "type": "Feature",
  "properties": {
    "addr:full":"5 Station Road Swanley Kent BR8 8ES",
    "addr:housenumber":"5",
    "addr:postcode":"br8 8es",
    "addr:street":"Station Road",
    "iso:country":"GB",
    "sg:address":"5 Station Road",
    "sg:city":"Swanley",
    "sg:classifiers":[
        {
            "category":"Retail",
            "subcategory":"Laundry & Dry Cleaning",
            "type":"Services"
        }
    ],
    "sg:phone":"+44 1322 666844",
    "sg:postcode":"BR8 8ES",
    "sg:province":"Kent",
    "sg:tags":[
        "alteration"
    ],
    "wof:name":"Discount Dry Cleaners",
    "wof:placetype":"venue"
},
  "geometry": {"coordinates":[0.176406,51.395184],"type":"Point"}
}