{
  "type": "Feature",
  "properties": {
    "iso:country":"GB",
    "sg:address":"5 Walm Lane",
    "sg:city":"London",
    "sg:classifiers":[
        {
            "category":"Wholesale",
            "subcategory":"Construction Materials",
            "type":"Manufacturing & Wholesale Goods"
        },
        {
            "category":"Shopping",
            "subcategory":"Pets & Pet Supplies",
            "type":"Retail Goods"
        }
    ],
    "sg:phone":"+44 20 8459 4799",
    "sg:postcode":"NW2 5SJ",
    "sg:province":"Greater London",
    "sg:tags":[
        "supplier",
        "pond",
        "aquarium"
    ],
    "wof:name":"Willesden Pet Centre",
    "wof:placetype":"venue"
},
  "geometry": {"coordinates":[-0.224614,51.547588],"type":"Point"}
}