{
  "type": "Feature",
  "properties": {
    "addr:full":"Room 835, Lloyds Of London 1 Lime St Monument Greater London EC3M 7HA",
    "addr:housenumber":"835;1",
    "addr:postcode":"ec3m 7ha",
    "addr:street":"Lloyds Of;Lime St",
    "iso:country":"GB",
    "sg:address":"Room 835, Lloyds Of London 1 Lime St",
    "sg:city":"Monument",
    "sg:classifiers":[
        {
            "category":"Professional",
            "subcategory":"Lawyer & Legal Services",
            "type":"Services"
        }
    ],
    "sg:phone":"+44 20 7327 8000",
    "sg:postcode":"EC3M 7HA",
    "sg:province":"Greater London",
    "wof:name":"Blatt Hammesfahr & Eaton",
    "wof:placetype":"venue"
},
  "geometry": {"coordinates":[-0.08214,51.512539],"type":"Point"}
}