{
  "type": "Feature",
  "properties": {
    "addr:full":"90 High Street Glenrothes Fife KY6 3DB",
    "addr:housenumber":"90",
    "addr:postcode":"ky6 3db",
    "addr:street":"High Street",
    "iso:country":"GB",
    "sg:address":"90 High Street",
    "sg:city":"Glenrothes",
    "sg:classifiers":[
        {
            "category":"Military Area",
            "subcategory":"Air Force Base",
            "type":"Public Place"
        }
    ],
    "sg:phone":"+44 1592 620720",
    "sg:postcode":"KY6 3DB",
    "sg:province":"Fife",
    "sg:tags":[
        "taxi",
        "hire",
        "private"
    ],
    "wof:name":"Robert Doherty",
    "wof:placetype":"venue"
},
  "geometry": {"coordinates":[-3.2057440281,56.203338623],"type":"Point"}
}