{
  "type": "Feature",
  "properties": {
    "iso:country":"GB",
    "sg:address":"Suite 2 Post Office House, 75 High Street",
    "sg:city":"Uckfield",
    "sg:classifiers":[
        {
            "category":"Professional",
            "subcategory":"Computer Services",
            "type":"Services"
        }
    ],
    "sg:postcode":"TN22 1AP",
    "sg:province":"East Sussex",
    "sg:tags":[
        "aided",
        "design"
    ],
    "wof:name":"Epsilon Computer Designs Ltd.",
    "wof:placetype":"venue"
},
  "geometry": {"coordinates":[0.096409,50.97134],"type":"Point"}
}