{
  "type": "Feature",
  "properties": {
    "addr:full":"Unit 4 Maxwell Square, Brucefield Industrial Park Livingston West Lothian EH54 9BL",
    "addr:housenumber":"unit 4",
    "addr:postcode":"eh54 9bl",
    "addr:street":"Maxwell Square Brucefield Industrial Park",
    "iso:country":"GB",
    "sg:address":"Unit 4 Maxwell Square, Brucefield Industrial Park",
    "sg:city":"Livingston",
    "sg:classifiers":[
        {
            "category":"Shopping",
            "subcategory":"Clothing, Apparel, & Fashions",
            "type":"Retail Goods"
        }
    ],
    "sg:phone":"+44 1506 409000",
    "sg:postcode":"EH54 9BL",
    "sg:province":"West Lothian",
    "sg:tags":[
        "wear",
        "leisure"
    ],
    "wof:name":"U S C Ltd.",
    "wof:placetype":"venue"
},
  "geometry": {"coordinates":[-3.5279328823,55.8671417236],"type":"Point"}
}