{
  "type": "Feature",
  "properties": {
    "iso:country":"GB",
    "sg:address":"73 Victoria Road",
    "sg:city":"Burgess Hill",
    "sg:classifiers":[
        {
            "category":"Autos & Motor Vehicles",
            "subcategory":"Fuel & Gas Station",
            "type":"Retail Goods"
        }
    ],
    "sg:phone":"+44 1444 244866",
    "sg:postcode":"RH15 9LP",
    "sg:province":"East Sussex",
    "sg:tags":[
        "engine",
        "sale"
    ],
    "wof:name":"Woodward Controls Uk Ltd.",
    "wof:placetype":"venue"
},
  "geometry": {"coordinates":[-0.149867,50.956532],"type":"Point"}
}