{
  "type": "Feature",
  "properties": {
    "addr:full":"5 Trinity Ct, Stoke Rd Bromsgrove Worcestershire B60 3EQ",
    "addr:housenumber":"5",
    "addr:postcode":"b60 3eq",
    "addr:street":"Trinity Ct Stoke Rd",
    "iso:country":"GB",
    "sg:address":"5 Trinity Ct, Stoke Rd",
    "sg:city":"Bromsgrove",
    "sg:classifiers":[
        {
            "category":"Health Services",
            "subcategory":"Dentist",
            "type":"Services"
        }
    ],
    "sg:phone":"+44 1527 575884",
    "sg:postcode":"B60 3EQ",
    "sg:province":"Worcestershire",
    "wof:name":"A S Damani",
    "wof:placetype":"venue"
},
  "geometry": {"coordinates":[-2.05029,52.322739],"type":"Point"}
}