{
  "type": "Feature",
  "properties": {
    "iso:country":"GB",
    "sg:address":"Silwex Ho, Quaker St",
    "sg:city":"Whitechapel",
    "sg:classifiers":[
        {
            "category":"Home & Garden",
            "subcategory":"Carpets & Floor Coverings",
            "type":"Retail Goods"
        }
    ],
    "sg:phone":"+44 20 7247 2171",
    "sg:postcode":"E1 6SN",
    "sg:province":"Greater London",
    "sg:tags":[
        "trimming",
        "trimmer"
    ],
    "wof:name":"D.L.K. Trading",
    "wof:placetype":"venue"
},
  "geometry": {"coordinates":[-0.0745640025,51.5221633911],"type":"Point"}
}