{
  "type": "Feature",
  "properties": {
    "iso:country":"GB",
    "sg:address":"Club House, Westcroft",
    "sg:city":"Chippenham",
    "sg:classifiers":[
        {
            "category":"Arena",
            "subcategory":"Sports Club",
            "type":"Entertainment"
        }
    ],
    "sg:phone":"+44 1249 445966",
    "sg:postcode":"SN14 0LZ",
    "sg:province":"Gloucestershire",
    "wof:name":"The North Wilts Indoor Bowls Club",
    "wof:placetype":"venue"
},
  "geometry": {"coordinates":[-2.13617,51.451569],"type":"Point"}
}