{
  "type": "Feature",
  "properties": {
    "iso:country":"GB",
    "sg:address":"105 Hague Lane, Renishaw",
    "sg:city":"Sheffield",
    "sg:classifiers":[
        {
            "category":"Professional",
            "subcategory":"Engineering",
            "type":"Services"
        },
        {
            "category":"Building & Trades",
            "subcategory":"Construction",
            "type":"Services"
        }
    ],
    "sg:phone":"+44 1246 436727",
    "sg:postcode":"S21 1GU",
    "sg:province":"Derbyshire",
    "sg:tags":[
        "civil",
        "builder",
        "engineer"
    ],
    "wof:name":"Depotbuild Ltd.",
    "wof:placetype":"venue"
},
  "geometry": {"coordinates":[-1.32407,53.31765],"type":"Point"}
}