{
  "type": "Feature",
  "properties": {
    "iso:country":"GB",
    "sg:address":"156 St Pauls Crescent",
    "sg:city":"London",
    "sg:classifiers":[
        {
            "category":"Education",
            "subcategory":"Preschool",
            "type":"Public Place"
        }
    ],
    "sg:phone":"+44 20 7482 1908",
    "sg:postcode":"NW1 9XZ",
    "sg:province":"Greater London",
    "sg:tags":[
        "pre-school",
        "playgroups"
    ],
    "wof:name":"Maiden Lane Pre-School Playgroup",
    "wof:placetype":"venue"
},
  "geometry": {"coordinates":[-0.1287100017,51.5415802002],"type":"Point"}
}