{
  "type": "Feature",
  "properties": {
    "iso:country":"GB",
    "sg:address":"57 Princes Avenue",
    "sg:city":"Hull",
    "sg:classifiers":[
        {
            "category":"Personal",
            "subcategory":"Beauty Salon",
            "type":"Services"
        }
    ],
    "sg:postcode":"HU5 3QY",
    "sg:province":"East Riding of Yorkshire",
    "wof:name":"Hair International",
    "wof:placetype":"venue"
},
  "geometry": {"coordinates":[-0.360534,53.753407],"type":"Point"}
}