{
  "type": "Feature",
  "properties": {
    "addr:full":"Crossgate Peth Durham Durham DH1 4QB",
    "addr:postcode":"dh1 4qb",
    "addr:street":"Crossgate Peth",
    "iso:country":"GB",
    "sg:address":"Crossgate Peth",
    "sg:city":"Durham",
    "sg:classifiers":[
        {
            "category":"Education",
            "subcategory":"School",
            "type":"Public Place"
        },
        {
            "category":"Government",
            "subcategory":"Office",
            "type":"Public Place"
        }
    ],
    "sg:phone":"+44 191 384 7331",
    "sg:postcode":"DH1 4QB",
    "sg:province":"Durham",
    "sg:tags":[
        "local",
        "authority"
    ],
    "wof:name":"St Margarets C of E Primary School",
    "wof:placetype":"venue"
},
  "geometry": {"coordinates":[-1.586495,54.77409],"type":"Point"}
}