{
  "type": "Feature",
  "properties": {
    "addr:full":"1 Highmeres Road Leicester Leicestershire LE4 9LZ",
    "addr:housenumber":"1",
    "addr:postcode":"le4 9lz",
    "addr:street":"Highmeres Road",
    "iso:country":"GB",
    "sg:address":"1 Highmeres Road",
    "sg:city":"Leicester",
    "sg:classifiers":[
        {
            "category":"Professional",
            "subcategory":"Engineering",
            "type":"Services"
        }
    ],
    "sg:phone":"+44 116 246 1810",
    "sg:postcode":"LE4 9LZ",
    "sg:province":"Leicestershire",
    "sg:tags":[
        "mechanical",
        "precision",
        "engineer"
    ],
    "wof:name":"Beacon Auto Engineering Ltd",
    "wof:placetype":"venue"
},
  "geometry": {"coordinates":[-1.0862970352,52.6605033875],"type":"Point"}
}