{
  "type": "Feature",
  "properties": {
    "iso:country":"GB",
    "sg:address":"Quay Rd",
    "sg:city":"Blyth",
    "sg:classifiers":[
        {
            "category":"Bus Charters",
            "type":"Transportation"
        }
    ],
    "sg:phone":"+44 1670 351111",
    "sg:postcode":"NE24 2AS",
    "sg:province":"Northumberland",
    "sg:tags":[
        "hire",
        "coach"
    ],
    "wof:name":"Premier Coach Hire",
    "wof:placetype":"venue"
},
  "geometry": {"coordinates":[-1.5038590431,55.1287117004],"type":"Point"}
}