{
  "type": "Feature",
  "properties": {
    "addr:full":"7 Market Place, South Normanton Alfreton Derbyshire DE55 2BN",
    "addr:housenumber":"7",
    "addr:postcode":"de55 2bn",
    "addr:street":"Market Place",
    "iso:country":"GB",
    "sg:address":"7 Market Place, South Normanton",
    "sg:city":"Alfreton",
    "sg:classifiers":[
        {
            "category":"Government",
            "subcategory":"Post Office",
            "type":"Public Place"
        }
    ],
    "sg:phone":"+44 1773 811217",
    "sg:postcode":"DE55 2BN",
    "sg:province":"Derbyshire",
    "wof:name":"South Normanton Post Office",
    "wof:placetype":"venue"
},
  "geometry": {"coordinates":[-1.3425639868,53.1063308716],"type":"Point"}
}