{
  "type": "Feature",
  "properties": {
    "iso:country":"GB",
    "sg:address":"Meadows Avenue",
    "sg:city":"Thornton Cleveleys",
    "sg:classifiers":[
        {
            "category":"Building & Trades",
            "subcategory":"Plumbing",
            "type":"Services"
        }
    ],
    "sg:phone":"+44 1253 829196",
    "sg:postcode":"FY5 2TW",
    "sg:province":"Lancashire",
    "sg:tags":[
        "central",
        "heating"
    ],
    "wof:name":"Heatserve-paul Mcivor",
    "wof:placetype":"venue"
},
  "geometry": {"coordinates":[-3.0223839283,53.8788414001],"type":"Point"}
}