{
  "type": "Feature",
  "properties": {
    "iso:country":"GB",
    "sg:address":"Burwell Drive",
    "sg:city":"Witney",
    "sg:classifiers":[
        {
            "category":"Education",
            "subcategory":"School",
            "type":"Public Place"
        }
    ],
    "sg:phone":"+44 1993 704770",
    "sg:postcode":"OX28 5LP",
    "sg:province":"Oxfordshire",
    "sg:tags":[
        "local",
        "authority"
    ],
    "wof:name":"Queen's Dyke Primary School",
    "wof:placetype":"venue"
},
  "geometry": {"coordinates":[-1.503309,51.781216],"type":"Point"}
}