{
  "type": "Feature",
  "properties": {
    "addr:full":"86 Tyrone Rd Southend On Sea Essex SS1 3HB",
    "addr:housenumber":"86",
    "addr:postcode":"ss1 3hb",
    "addr:street":"Tyrone Rd",
    "iso:country":"GB",
    "sg:address":"86 Tyrone Rd",
    "sg:city":"Southend On Sea",
    "sg:classifiers":[
        {
            "category":"Place Of Worship",
            "type":"Public Place"
        }
    ],
    "sg:phone":"+44 1702 587597",
    "sg:postcode":"SS1 3HB",
    "sg:province":"Essex",
    "wof:name":"St. Augustines Church",
    "wof:placetype":"venue"
},
  "geometry": {"coordinates":[0.758342,51.53421],"type":"Point"}
}