{
  "type": "Feature",
  "properties": {
    "addr:full":"Goose Grn, Gomshall Guildford Surrey GU5 9LJ",
    "addr:postcode":"gu5 9lj",
    "addr:street":"Goose Grn Gomshall",
    "iso:country":"GB",
    "sg:address":"Goose Grn, Gomshall",
    "sg:city":"Guildford",
    "sg:classifiers":[
        {
            "category":"Wholesale",
            "subcategory":"Medical Equipment & Supplies",
            "type":"Manufacturing & Wholesale Goods"
        },
        {
            "category":"Professional",
            "subcategory":"Testing Lab",
            "type":"Services"
        }
    ],
    "sg:phone":"+44 1483 202178",
    "sg:postcode":"GU5 9LJ",
    "sg:province":"Surrey",
    "sg:tags":[
        "manufacture",
        "laboratory"
    ],
    "wof:name":"Mickle Laboratory Engineering Co. Ltd.",
    "wof:placetype":"venue"
},
  "geometry": {"coordinates":[-0.4521780014,51.2178916931],"type":"Point"}
}