{
  "type": "Feature",
  "properties": {
    "addr:full":"Unit 5, Park Farm Saffron Walden Cambridgeshire CB10 1RN",
    "addr:housenumber":"unit 5",
    "addr:postcode":"cb10 1rn",
    "addr:street":"Park;Saffron Walden",
    "iso:country":"GB",
    "sg:address":"Unit 5, Park Farm",
    "sg:city":"Saffron Walden",
    "sg:classifiers":[
        {
            "category":"Communications",
            "subcategory":"Film & Video Production",
            "type":"Services"
        }
    ],
    "sg:postcode":"CB10 1RN",
    "sg:province":"Cambridgeshire",
    "sg:tags":[
        "supp",
        "window",
        "leaded"
    ],
    "wof:name":"Tony Sandles Glass",
    "wof:placetype":"venue"
},
  "geometry": {"coordinates":[0.2383950055,52.0230293274],"type":"Point"}
}