{
  "type": "Feature",
  "properties": {
    "addr:full":"Old Rectory, Main Street, Sudborough Kettering Northamptonshire NN14 3BX",
    "addr:postcode":"nn14 3bx",
    "addr:street":"Main Street",
    "iso:country":"GB",
    "sg:address":"Old Rectory, Main Street, Sudborough",
    "sg:city":"Kettering",
    "sg:classifiers":[
        {
            "category":"Professional",
            "type":"Services"
        }
    ],
    "sg:postcode":"NN14 3BX",
    "sg:province":"Northamptonshire",
    "sg:tags":[
        "interior",
        "furnishers",
        "designer"
    ],
    "wof:name":"Rectory Interior Designs",
    "wof:placetype":"venue"
},
  "geometry": {"coordinates":[-0.5787990093,52.4299850464],"type":"Point"}
}