{
  "type": "Feature",
  "properties": {
    "addr:full":"Brunswick Road Cannock Staffordshire WS11 2SF",
    "addr:postcode":"ws11 2sf",
    "addr:street":"Brunswick Road",
    "iso:country":"GB",
    "sg:address":"Brunswick Road",
    "sg:city":"Cannock",
    "sg:classifiers":[
        {
            "category":"Education",
            "subcategory":"School",
            "type":"Public Place"
        },
        {
            "category":"Government",
            "subcategory":"Office",
            "type":"Public Place"
        }
    ],
    "sg:phone":"+44 1543 510216",
    "sg:postcode":"WS11 2SF",
    "sg:province":"Staffordshire",
    "sg:tags":[
        "local",
        "authority"
    ],
    "wof:name":"Beecroft Hill School",
    "wof:placetype":"venue"
},
  "geometry": {"coordinates":[-2.033145,52.690952],"type":"Point"}
}