{
  "type": "Feature",
  "properties": {
    "addr:full":"Gelli Aur Stepaside Newtown Powys SY16 4JQ",
    "addr:postcode":"sy16 4jq",
    "addr:street":"Stepaside",
    "iso:country":"GB",
    "sg:address":"Gelli Aur Stepaside",
    "sg:city":"Newtown",
    "sg:classifiers":[
        {
            "category":"Professional",
            "subcategory":"Secretarial Services",
            "type":"Services"
        }
    ],
    "sg:phone":"+44 1686 621053",
    "sg:postcode":"SY16 4JQ",
    "sg:province":"Powys",
    "wof:name":"Words Writing Services",
    "wof:placetype":"venue"
},
  "geometry": {"coordinates":[-3.2797091007,52.49269104],"type":"Point"}
}