{
  "type": "Feature",
  "properties": {
    "addr:full":"Waterside House Mexborough South Yorkshire S64 9AQ",
    "addr:postcode":"s64 9aq",
    "addr:street":"Mexborough South",
    "iso:country":"GB",
    "sg:address":"Waterside House",
    "sg:city":"Mexborough",
    "sg:classifiers":[
        {
            "category":"Home & Garden",
            "subcategory":"Carpets & Floor Coverings",
            "type":"Retail Goods"
        }
    ],
    "sg:postcode":"S64 9AQ",
    "sg:province":"South Yorkshire",
    "sg:tags":[
        "carpets",
        "rug",
        "matting"
    ],
    "wof:name":"United Carpets & Beds",
    "wof:placetype":"venue"
},
  "geometry": {"coordinates":[-1.299808979,53.4953536987],"type":"Point"}
}