{
  "type": "Feature",
  "properties": {
    "iso:country":"GB",
    "sg:address":"5 North Walls",
    "sg:city":"Stafford",
    "sg:classifiers":[
        {
            "category":"Shopping",
            "subcategory":"Music",
            "type":"Retail Goods"
        }
    ],
    "sg:postcode":"ST16 3AD",
    "sg:province":"Staffordshire",
    "sg:tags":[
        "record",
        "tape",
        "cd"
    ],
    "wof:name":"Gorden,Mark,",
    "wof:placetype":"venue"
},
  "geometry": {"coordinates":[-2.116376,52.808197],"type":"Point"}
}