{
  "type": "Feature",
  "properties": {
    "iso:country":"GB",
    "sg:address":"53 Clifton Road",
    "sg:city":"Cambridge",
    "sg:classifiers":[
        {
            "category":"Autos & Motor Vehicles",
            "subcategory":"Auto Supplies",
            "type":"Retail Goods"
        }
    ],
    "sg:phone":"+44 1223 413223",
    "sg:postcode":"CB1 7ED",
    "sg:province":"Cambridgeshire",
    "sg:tags":[
        "tyre"
    ],
    "wof:name":"Discount Tyre Warehouse",
    "wof:placetype":"venue"
},
  "geometry": {"coordinates":[0.1397130042,52.1932029724],"type":"Point"}
}