{
  "type": "Feature",
  "properties": {
    "addr:full":"115 Church Street Preston Lancashire PR1 3BS",
    "addr:housenumber":"115",
    "addr:postcode":"pr1 3bs",
    "addr:street":"Church Street",
    "iso:country":"GB",
    "sg:address":"115 Church Street",
    "sg:city":"Preston",
    "sg:classifiers":[
        {
            "category":"Home & Garden",
            "subcategory":"Furniture",
            "type":"Retail Goods"
        }
    ],
    "sg:phone":"+44 1772 200707",
    "sg:postcode":"PR1 3BS",
    "sg:province":"Lancashire",
    "wof:name":"Your Choice",
    "wof:placetype":"venue"
},
  "geometry": {"coordinates":[-2.6933069229,53.7597885132],"type":"Point"}
}