{
  "type": "Feature",
  "properties": {
    "addr:full":"Strathnaver, Margnaheglish, Lamlash Brodick North Ayrshire KA27 8LL",
    "addr:postcode":"ka27 8ll",
    "iso:country":"GB",
    "sg:address":"Strathnaver, Margnaheglish, Lamlash",
    "sg:city":"Brodick",
    "sg:classifiers":[
        {
            "category":"Building & Trades",
            "subcategory":"Construction",
            "type":"Services"
        }
    ],
    "sg:phone":"+44 1770 600542",
    "sg:postcode":"KA27 8LL",
    "sg:province":"North Ayrshire",
    "sg:tags":[
        "joiner",
        "carpenter"
    ],
    "wof:name":"Peter Mackay (Joiner)",
    "wof:placetype":"venue"
},
  "geometry": {"coordinates":[-5.1523189545,55.5775756836],"type":"Point"}
}