{
  "type": "Feature",
  "properties": {
    "addr:full":"Chipping House, Chipping Buntingford Hertfordshire SG9 0PG",
    "addr:housenumber":"chipping",
    "addr:postcode":"sg9 0pg",
    "addr:street":"Chipping",
    "iso:country":"GB",
    "sg:address":"Chipping House, Chipping",
    "sg:city":"Buntingford",
    "sg:classifiers":[
        {
            "category":"Building & Trades",
            "subcategory":"Construction",
            "type":"Services"
        }
    ],
    "sg:postcode":"SG9 0PG",
    "sg:province":"Hertfordshire",
    "sg:tags":[
        "roofing"
    ],
    "wof:name":"Thompson Roofing Ltd.",
    "wof:placetype":"venue"
},
  "geometry": {"coordinates":[-0.0282240007,51.9668540955],"type":"Point"}
}