{
  "type": "Feature",
  "properties": {
    "iso:country":"GB",
    "sg:address":"15 Harbour View Road, Pagham",
    "sg:city":"Bognor Regis",
    "sg:classifiers":[
        {
            "category":"Building & Trades",
            "subcategory":"Construction",
            "type":"Services"
        }
    ],
    "sg:postcode":"PO21 4RG",
    "sg:province":"West Sussex",
    "sg:tags":[
        "decorator",
        "painter"
    ],
    "wof:name":"Morris Paul Decorator & Property Maintenance",
    "wof:placetype":"venue"
},
  "geometry": {"coordinates":[-0.736812,50.776546],"type":"Point"}
}