{
  "type": "Feature",
  "properties": {
    "iso:country":"GB",
    "sg:address":"30 Marlborough Road",
    "sg:city":"Ryde",
    "sg:classifiers":[
        {
            "category":"Social Services",
            "subcategory":"Retirement Home",
            "type":"Services"
        }
    ],
    "sg:phone":"+44 1983 611644",
    "sg:postcode":"PO33 1AB",
    "sg:province":"Isle of Wight",
    "sg:tags":[
        "rest"
    ],
    "wof:name":"Park Towers Residential Home",
    "wof:placetype":"venue"
},
  "geometry": {"coordinates":[-1.146097,50.721836],"type":"Point"}
}