{
  "type": "Feature",
  "properties": {
    "iso:country":"GB",
    "sg:address":"Mitre House, North Park Road",
    "sg:city":"Harrogate",
    "sg:classifiers":[
        {
            "category":"Professional",
            "subcategory":"Management & Consulting",
            "type":"Services"
        },
        {
            "category":"Banks & Credit Unions",
            "subcategory":"Financial Services",
            "type":"Services"
        }
    ],
    "sg:phone":"+44 113 297 0800",
    "sg:postcode":"HG1 5RX",
    "sg:province":"North Yorkshire",
    "sg:tags":[
        "consultant",
        "holding",
        "activity"
    ],
    "wof:name":"Wilton Investments Ltd.",
    "wof:placetype":"venue"
},
  "geometry": {"coordinates":[-1.529614,53.992451],"type":"Point"}
}