{
  "type": "Feature",
  "properties": {
    "addr:full":"Russell House, Bepton Road Midhurst West Sussex GU29 9NB",
    "addr:postcode":"gu29 9nb",
    "addr:street":"Bepton Road",
    "iso:country":"GB",
    "sg:address":"Russell House, Bepton Road",
    "sg:city":"Midhurst",
    "sg:classifiers":[
        {
            "category":"Bus Charters",
            "type":"Transportation"
        }
    ],
    "sg:phone":"+44 1730 813304",
    "sg:postcode":"GU29 9NB",
    "sg:province":"West Sussex",
    "sg:tags":[
        "hire",
        "coach"
    ],
    "wof:name":"Richardson Travel Ltd",
    "wof:placetype":"venue"
},
  "geometry": {"coordinates":[-0.740142,50.985313],"type":"Point"}
}