{
  "type": "Feature",
  "properties": {
    "iso:country":"GB",
    "sg:address":"86 Alma Road",
    "sg:city":"Bournemouth",
    "sg:classifiers":[
        {
            "category":"Food & Beverages",
            "subcategory":"Fruits & Vegetables",
            "type":"Retail Goods"
        }
    ],
    "sg:phone":"+44 1202 521750",
    "sg:postcode":"BH9 1AL",
    "sg:province":"Dorset",
    "sg:tags":[
        "greengrocer"
    ],
    "wof:name":"Brambles",
    "wof:placetype":"venue"
},
  "geometry": {"coordinates":[-1.872814,50.73856],"type":"Point"}
}