{
  "type": "Feature",
  "properties": {
    "iso:country":"GB",
    "sg:address":"1st Floor India Buildings, Brunswick St",
    "sg:city":"Liverpool",
    "sg:classifiers":[
        {
            "category":"Insurance",
            "subcategory":"Insurance Agent",
            "type":"Services"
        }
    ],
    "sg:phone":"+44 151 236 4511",
    "sg:postcode":"L3 9NG",
    "sg:province":"Merseyside",
    "sg:tags":[
        "broker"
    ],
    "wof:name":"Roland Smith",
    "wof:placetype":"venue"
},
  "geometry": {"coordinates":[-2.99334,53.409809],"type":"Point"}
}