{
  "type": "Feature",
  "properties": {
    "addr:full":"20-22 Bedford Row London Greater London WC1R 4JS",
    "addr:housenumber":"20-22",
    "addr:postcode":"wc1r 4js",
    "addr:street":"Bedford Row",
    "iso:country":"GB",
    "sg:address":"20-22 Bedford Row",
    "sg:city":"London",
    "sg:classifiers":[
        {
            "category":"Professional",
            "subcategory":"Management & Consulting",
            "type":"Services"
        }
    ],
    "sg:postcode":"WC1R 4JS",
    "sg:province":"Greater London",
    "sg:tags":[
        "consultant",
        "business"
    ],
    "wof:name":"Mount Charles Consultants Ltd.",
    "wof:placetype":"venue"
},
  "geometry": {"coordinates":[-0.116149,51.520439],"type":"Point"}
}