{
  "type": "Feature",
  "properties": {
    "iso:country":"GB",
    "sg:address":"562 Manchester Road",
    "sg:city":"Bradford",
    "sg:classifiers":[
        {
            "category":"Retail",
            "subcategory":"Laundry & Dry Cleaning",
            "type":"Services"
        }
    ],
    "sg:postcode":"BD5 7LR",
    "sg:province":"West Yorkshire",
    "sg:tags":[
        "alteration"
    ],
    "wof:name":"Metro Cleaners",
    "wof:placetype":"venue"
},
  "geometry": {"coordinates":[-1.760525,53.780197],"type":"Point"}
}