{
  "type": "Feature",
  "properties": {
    "iso:country":"GB",
    "sg:address":"1 Clarendon Rd",
    "sg:city":"Borehamwood",
    "sg:classifiers":[
        {
            "category":"Health Services",
            "subcategory":"Podiatrist",
            "type":"Services"
        }
    ],
    "sg:phone":"+44 20 8953 9052",
    "sg:postcode":"WD6 1BD",
    "sg:province":"Hertfordshire",
    "sg:tags":[
        "podiatrists",
        "chiropodist"
    ],
    "wof:name":"Chiropody Practice The",
    "wof:placetype":"venue"
},
  "geometry": {"coordinates":[-0.2746610045,51.6565818787],"type":"Point"}
}