{
  "type": "Feature",
  "properties": {
    "addr:full":"Braehead Farm Kilmarnock East Ayrshire KA1 5LN",
    "addr:housenumber":"braehead;kilmarnock",
    "addr:postcode":"ka1 5ln",
    "addr:street":"East",
    "iso:country":"GB",
    "sg:address":"Braehead Farm",
    "sg:city":"Kilmarnock",
    "sg:classifiers":[
        {
            "category":"Farming",
            "subcategory":"Crops",
            "type":"Manufacturing & Wholesale Goods"
        },
        {
            "category":"Farming",
            "subcategory":"Farm",
            "type":"Manufacturing & Wholesale Goods"
        }
    ],
    "sg:phone":"+44 1563 884272",
    "sg:postcode":"KA1 5LN",
    "sg:province":"East Ayrshire",
    "sg:tags":[
        "mixed",
        "arable"
    ],
    "wof:name":"Robert McFadzean",
    "wof:placetype":"venue"
},
  "geometry": {"coordinates":[-4.456954,55.600849],"type":"Point"}
}