{
  "type": "Feature",
  "properties": {
    "iso:country":"GB",
    "sg:address":"125 Woodlands Road",
    "sg:city":"Ilford",
    "sg:classifiers":[
        {
            "category":"Cinema",
            "subcategory":"Movie Rental",
            "type":"Entertainment"
        }
    ],
    "sg:phone":"+44 20 8514 2863",
    "sg:postcode":"IG1 1JP",
    "sg:province":"Essex",
    "sg:tags":[
        "video",
        "library"
    ],
    "wof:name":"Sunny's Video",
    "wof:placetype":"venue"
},
  "geometry": {"coordinates":[0.0787,51.553951],"type":"Point"}
}