{
  "type": "Feature",
  "properties": {
    "iso:country":"GB",
    "sg:address":"309 High Street West",
    "sg:city":"Sunderland",
    "sg:classifiers":[
        {
            "category":"Bars & Pubs",
            "type":"Food & Drink"
        }
    ],
    "sg:phone":"+44 191 567 5702",
    "sg:postcode":"SR1 3ET",
    "sg:province":"Tyne and Wear",
    "sg:tags":[
        "pubs",
        "inn"
    ],
    "wof:name":"Outpost The",
    "wof:placetype":"venue"
},
  "geometry": {"coordinates":[-1.387894,54.906307],"type":"Point"}
}