{
  "type": "Feature",
  "properties": {
    "iso:country":"GB",
    "sg:address":"52a Main St",
    "sg:city":"Cockermouth",
    "sg:classifiers":[
        {
            "category":"Professional",
            "subcategory":"Accounting & Tax Preparation",
            "type":"Services"
        }
    ],
    "sg:phone":"+44 1900 827447",
    "sg:postcode":"CA13 9LU",
    "sg:province":"Cumbria",
    "sg:tags":[
        "accountant"
    ],
    "wof:name":"Wilson Kinnair",
    "wof:placetype":"venue"
},
  "geometry": {"coordinates":[-3.3651440144,54.6638298035],"type":"Point"}
}