{
  "type": "Feature",
  "properties": {
    "iso:country":"GB",
    "sg:address":"11, 11a & 12 Queen St",
    "sg:city":"Gravesend",
    "sg:classifiers":[
        {
            "category":"Home & Garden",
            "subcategory":"Household Appliances",
            "type":"Retail Goods"
        }
    ],
    "sg:phone":"+44 1474 331977",
    "sg:postcode":"DA12 2EG",
    "sg:province":"Kent",
    "sg:tags":[
        "electrical"
    ],
    "wof:name":"Ajay Domestics",
    "wof:placetype":"venue"
},
  "geometry": {"coordinates":[0.371271,51.442444],"type":"Point"}
}