{
  "type": "Feature",
  "properties": {
    "addr:full":"Bryn Coed, Froncysyllte Llangollen Denbighshire LL20 7RY",
    "addr:postcode":"ll20 7ry",
    "iso:country":"GB",
    "sg:address":"Bryn Coed, Froncysyllte",
    "sg:city":"Llangollen",
    "sg:classifiers":[
        {
            "category":"Farming",
            "subcategory":"Livestock Farm",
            "type":"Manufacturing & Wholesale Goods"
        }
    ],
    "sg:phone":"+44 1691 772477",
    "sg:postcode":"LL20 7RY",
    "sg:province":"Denbighshire",
    "sg:tags":[
        "others"
    ],
    "wof:name":"E W Jones",
    "wof:placetype":"venue"
},
  "geometry": {"coordinates":[-3.084803,52.963226],"type":"Point"}
}