{
  "type": "Feature",
  "properties": {
    "addr:full":"Radnor Park Industrial Estate, Back Lane Congleton Cheshire CW12 4XJ",
    "addr:housenumber":"estate",
    "addr:postcode":"cw12 4xj",
    "addr:street":"Back Lane",
    "iso:country":"GB",
    "sg:address":"Radnor Park Industrial Estate, Back Lane",
    "sg:city":"Congleton",
    "sg:classifiers":[
        {
            "category":"Freight",
            "type":"Transportation"
        },
        {
            "category":"Professional",
            "subcategory":"Business Services",
            "type":"Services"
        }
    ],
    "sg:phone":"+44 1260 295777",
    "sg:postcode":"CW12 4XJ",
    "sg:province":"Cheshire",
    "sg:tags":[
        "haulage",
        "distribution",
        "transport",
        "road"
    ],
    "wof:name":"S T D Developments Ltd.",
    "wof:placetype":"venue"
},
  "geometry": {"coordinates":[-2.237007,53.171856],"type":"Point"}
}