{
  "type": "Feature",
  "properties": {
    "iso:country":"GB",
    "sg:address":"Round Spring Farm, Bridle Lane, Loudwater",
    "sg:city":"Rickmansworth",
    "sg:classifiers":[
        {
            "category":"Fast Food",
            "type":"Food & Drink"
        }
    ],
    "sg:phone":"+44 1923 775090",
    "sg:postcode":"WD3 4JQ",
    "sg:province":"Hertfordshire",
    "sg:tags":[
        "away",
        "take"
    ],
    "wof:name":"Traditional Foods Ltd.",
    "wof:placetype":"venue"
},
  "geometry": {"coordinates":[-0.478091,51.654293],"type":"Point"}
}