{
  "type": "Feature",
  "properties": {
    "iso:country":"GB",
    "sg:address":"648 Pershore Road, Selly Park",
    "sg:city":"Birmingham",
    "sg:classifiers":[
        {
            "category":"Personal",
            "subcategory":"Beauty Salon",
            "type":"Services"
        }
    ],
    "sg:postcode":"B29 7HG",
    "sg:province":"West Midlands",
    "sg:tags":[
        "unisex",
        "hairdresser"
    ],
    "wof:name":"Carnaby Cutting Room",
    "wof:placetype":"venue"
},
  "geometry": {"coordinates":[-1.9143229723,52.446105957],"type":"Point"}
}