{
  "type": "Feature",
  "properties": {
    "addr:full":"215-217 Promenade Blackpool Lancashire FY1 5DL",
    "addr:housenumber":"215-217",
    "addr:postcode":"fy1 5dl",
    "addr:street":"Promenade",
    "iso:country":"GB",
    "sg:address":"215-217 Promenade",
    "sg:city":"Blackpool",
    "sg:classifiers":[
        {
            "category":"Travel",
            "subcategory":"Hotels & Motels",
            "type":"Entertainment"
        }
    ],
    "sg:phone":"+44 1253 628624",
    "sg:postcode":"FY1 5DL",
    "sg:province":"Lancashire",
    "wof:name":"The Balmoral Hotel",
    "wof:placetype":"venue"
},
  "geometry": {"coordinates":[-3.055192,53.808128],"type":"Point"}
}