{
  "type": "Feature",
  "properties": {
    "iso:country":"GB",
    "sg:address":"16 Kingsway",
    "sg:city":"Bath",
    "sg:classifiers":[
        {
            "category":"Professional",
            "subcategory":"Art Services",
            "type":"Services"
        }
    ],
    "sg:postcode":"BA2 2NH",
    "sg:province":"Somerset",
    "sg:tags":[
        "consultant",
        "design"
    ],
    "wof:name":"B Barton",
    "wof:placetype":"venue"
},
  "geometry": {"coordinates":[-2.38759,51.367104],"type":"Point"}
}