{
  "type": "Feature",
  "properties": {
    "iso:country":"GB",
    "sg:address":"130 Warwick Avenue, Whitefield",
    "sg:city":"Manchester",
    "sg:classifiers":[
        {
            "category":"Manufacturing",
            "subcategory":"Petroleum Products",
            "type":"Manufacturing & Wholesale Goods"
        }
    ],
    "sg:postcode":"M45 6TX",
    "sg:province":"Lancashire",
    "sg:tags":[
        "double",
        "glazing"
    ],
    "wof:name":"F D Windows",
    "wof:placetype":"venue"
},
  "geometry": {"coordinates":[-2.275267,53.54388],"type":"Point"}
}