{
  "type": "Feature",
  "properties": {
    "addr:full":"10 Dorset Road Beckenham Kent BR3 4EA",
    "addr:housenumber":"10",
    "addr:postcode":"br3 4ea",
    "addr:street":"Dorset Road",
    "iso:country":"GB",
    "sg:address":"10 Dorset Road",
    "sg:city":"Beckenham",
    "sg:classifiers":[
        {
            "category":"Professional",
            "subcategory":"Management & Consulting",
            "type":"Services"
        }
    ],
    "sg:phone":"+44 20 8650 4071",
    "sg:postcode":"BR3 4EA",
    "sg:province":"Kent",
    "sg:tags":[
        "consultant",
        "business"
    ],
    "wof:name":"Glyn Everitt Marketing Services",
    "wof:placetype":"venue"
},
  "geometry": {"coordinates":[-0.050587,51.40118],"type":"Point"}
}