{
  "type": "Feature",
  "properties": {
    "addr:full":"38 Ware Road Hertford Hertfordshire SG13 7HH",
    "addr:housenumber":"38",
    "addr:postcode":"sg13 7hh",
    "addr:street":"Ware Road",
    "iso:country":"GB",
    "sg:address":"38 Ware Road",
    "sg:city":"Hertford",
    "sg:classifiers":[
        {
            "category":"Professional",
            "subcategory":"Business Services",
            "type":"Services"
        }
    ],
    "sg:phone":"+44 1992 509547",
    "sg:postcode":"SG13 7HH",
    "sg:province":"Hertfordshire",
    "sg:tags":[
        "import",
        "export",
        "agent"
    ],
    "wof:name":"Innovo International Ltd.",
    "wof:placetype":"venue"
},
  "geometry": {"coordinates":[-0.0133490004,51.777545929],"type":"Point"}
}