{
  "type": "Feature",
  "properties": {
    "iso:country":"GB",
    "sg:address":"40 Croydon Road",
    "sg:city":"West Wickham",
    "sg:classifiers":[
        {
            "category":"Professional",
            "subcategory":"Engineering",
            "type":"Services"
        }
    ],
    "sg:phone":"+44 20 8656 5446",
    "sg:postcode":"BR4 9HZ",
    "sg:province":"Kent",
    "sg:tags":[
        "engineer",
        "structural"
    ],
    "wof:name":"Goss Meades Partnership",
    "wof:placetype":"venue"
},
  "geometry": {"coordinates":[0.000453,51.3697738647],"type":"Point"}
}