{
  "type": "Feature",
  "properties": {
    "iso:country":"GB",
    "sg:address":"31 Stoney Grove",
    "sg:city":"Chesham",
    "sg:classifiers":[
        {
            "category":"Retail",
            "subcategory":"Auto Rental",
            "type":"Services"
        },
        {
            "category":"Autos & Motor Vehicles",
            "subcategory":"Motorcycle Sales",
            "type":"Retail Goods"
        }
    ],
    "sg:phone":"+44 1494 792988",
    "sg:postcode":"HP5 3BW",
    "sg:province":"Buckinghamshire",
    "sg:tags":[
        "chauffeur",
        "driven",
        "hire",
        "car"
    ],
    "wof:name":"Regency Private Car Hire",
    "wof:placetype":"venue"
},
  "geometry": {"coordinates":[-0.601737,51.711288],"type":"Point"}
}