{
  "type": "Feature",
  "properties": {
    "addr:full":"Ormonde House, Berwyn Street Llangollen Denbighshire LL20 8NB",
    "addr:postcode":"ll20 8nb",
    "addr:street":"Berwyn Street",
    "iso:country":"GB",
    "sg:address":"Ormonde House, Berwyn Street",
    "sg:city":"Llangollen",
    "sg:classifiers":[
        {
            "category":"Health Services",
            "subcategory":"Dentist",
            "type":"Services"
        }
    ],
    "sg:phone":"+44 1978 860682",
    "sg:postcode":"LL20 8NB",
    "sg:province":"Denbighshire",
    "wof:name":"M Bell",
    "wof:placetype":"venue"
},
  "geometry": {"coordinates":[-3.172186,52.969074],"type":"Point"}
}