{
  "type": "Feature",
  "properties": {
    "iso:country":"GB",
    "sg:address":"6 Beaufort St",
    "sg:city":"Southend On Sea",
    "sg:classifiers":[
        {
            "category":"Shopping",
            "subcategory":"Clothing, Apparel, & Fashions",
            "type":"Retail Goods"
        }
    ],
    "sg:phone":"+44 1702 611744",
    "sg:postcode":"SS2 4NH",
    "sg:province":"Essex",
    "sg:tags":[
        "shop"
    ],
    "wof:name":"Audreys Mobile Fashions",
    "wof:placetype":"venue"
},
  "geometry": {"coordinates":[0.7372419834,51.5423812866],"type":"Point"}
}