{
  "type": "Feature",
  "properties": {
    "addr:full":"70/72 Abbey Road Torquay Devon TQ2 5NH",
    "addr:housenumber":"70 / 72",
    "addr:postcode":"tq2 5nh",
    "addr:street":"Abbey Road",
    "iso:country":"GB",
    "sg:address":"70/72 Abbey Road",
    "sg:city":"Torquay",
    "sg:classifiers":[
        {
            "category":"Real Estate",
            "subcategory":"Architect",
            "type":"Services"
        }
    ],
    "sg:phone":"+44 1803 295982",
    "sg:postcode":"TQ2 5NH",
    "sg:province":"Devon",
    "sg:tags":[
        "technologist",
        "architectural"
    ],
    "wof:name":"Christopher Stacey Architecture",
    "wof:placetype":"venue"
},
  "geometry": {"coordinates":[-3.531192,50.465931],"type":"Point"}
}