{
  "type": "Feature",
  "properties": {
    "iso:country":"GB",
    "sg:address":"21 Willow Lane",
    "sg:city":"Amersham",
    "sg:classifiers":[
        {
            "category":"Shopping",
            "subcategory":"Pharmacy",
            "type":"Retail Goods"
        }
    ],
    "sg:postcode":"HP7 9DW",
    "sg:province":"Buckinghamshire",
    "sg:tags":[
        "pharmacist",
        "chemist"
    ],
    "wof:name":"Aquell Enterprises",
    "wof:placetype":"venue"
},
  "geometry": {"coordinates":[-0.589236021,51.660484314],"type":"Point"}
}