{
  "type": "Feature",
  "properties": {
    "addr:full":"33 Walpole Rd Cambridge Cambridgeshire CB1 3TH",
    "addr:housenumber":"33",
    "addr:postcode":"cb1 3th",
    "addr:street":"Walpole Rd",
    "iso:country":"GB",
    "sg:address":"33 Walpole Rd",
    "sg:city":"Cambridge",
    "sg:classifiers":[
        {
            "category":"Place Of Worship",
            "type":"Public Place"
        }
    ],
    "sg:phone":"+44 1223 211235",
    "sg:postcode":"CB1 3TH",
    "sg:province":"Cambridgeshire",
    "wof:name":"St. Philip Howard Catholic Church",
    "wof:placetype":"venue"
},
  "geometry": {"coordinates":[0.1625829935,52.1878166199],"type":"Point"}
}