{
  "type": "Feature",
  "properties": {
    "iso:country":"GB",
    "sg:address":"18 Chalk Lane",
    "sg:city":"Epsom",
    "sg:classifiers":[
        {
            "category":"Bars & Pubs",
            "type":"Food & Drink"
        }
    ],
    "sg:phone":"+44 1372 721085",
    "sg:postcode":"KT18 7AS",
    "sg:province":"Surrey",
    "sg:tags":[
        "pubs",
        "inn"
    ],
    "wof:name":"The Amato Inn",
    "wof:placetype":"venue"
},
  "geometry": {"coordinates":[-0.2677589953,51.3239402771],"type":"Point"}
}