{
  "type": "Feature",
  "properties": {
    "iso:country":"GB",
    "sg:address":"8 West Cross",
    "sg:city":"Tenterden",
    "sg:classifiers":[
        {
            "category":"Real Estate",
            "subcategory":"Real Estate Agent",
            "type":"Services"
        }
    ],
    "sg:phone":"+44 1580 765858",
    "sg:postcode":"TN30 6JL",
    "sg:province":"Kent",
    "wof:name":"Humberts",
    "wof:placetype":"venue"
},
  "geometry": {"coordinates":[0.681321,51.066517],"type":"Point"}
}