{
  "type": "Feature",
  "properties": {
    "addr:full":"3 Guildhall Street Grantham Lincolnshire NG31 6NJ",
    "addr:housenumber":"3",
    "addr:postcode":"ng31 6nj",
    "addr:street":"Guildhall Street",
    "iso:country":"GB",
    "sg:address":"3 Guildhall Street",
    "sg:city":"Grantham",
    "sg:classifiers":[
        {
            "category":"Personal",
            "subcategory":"Beauty Salon",
            "type":"Services"
        },
        {
            "category":"Personal",
            "subcategory":"Barber",
            "type":"Services"
        }
    ],
    "sg:phone":"+44 1476 591005",
    "sg:postcode":"NG31 6NJ",
    "sg:province":"Lincolnshire",
    "sg:tags":[
        "unisex",
        "lady",
        "hairdresser"
    ],
    "wof:name":"H C Hair Design",
    "wof:placetype":"venue"
},
  "geometry": {"coordinates":[-0.6424540281,52.9118537903],"type":"Point"}
}