{
  "type": "Feature",
  "properties": {
    "addr:full":"Houndgate Mews Darlington Durham DL1 5SG",
    "addr:postcode":"dl1 5sg",
    "addr:street":"Houndgate",
    "iso:country":"GB",
    "sg:address":"Houndgate Mews",
    "sg:city":"Darlington",
    "sg:classifiers":[
        {
            "category":"Personal",
            "subcategory":"Beauty Salon",
            "type":"Services"
        }
    ],
    "sg:postcode":"DL1 5SG",
    "sg:province":"Durham",
    "sg:tags":[
        "unisex",
        "hairdresser"
    ],
    "wof:name":"Replay",
    "wof:placetype":"venue"
},
  "geometry": {"coordinates":[-1.554719,54.523483],"type":"Point"}
}