{
  "type": "Feature",
  "properties": {
    "iso:country":"GB",
    "sg:address":"Neville Road Surgery, 5 Neville Rd",
    "sg:city":"Luton",
    "sg:classifiers":[
        {
            "category":"Health Services",
            "subcategory":"Doctor",
            "type":"Services"
        }
    ],
    "sg:phone":"+44 1582 563373",
    "sg:postcode":"LU3 2JG",
    "sg:province":"Bedfordshire",
    "sg:tags":[
        "practitioners"
    ],
    "wof:name":"Ar-Rikaby, H",
    "wof:placetype":"venue"
},
  "geometry": {"coordinates":[-0.44261,51.904881],"type":"Point"}
}