{
  "type": "Feature",
  "properties": {
    "addr:full":"Rear Of 128-134, 128-134 Mount Street Fleetwood Lancashire FY7 6LE",
    "addr:housenumber":"128-134 128-134",
    "addr:postcode":"fy7 6le",
    "addr:street":"Mount Street",
    "iso:country":"GB",
    "sg:address":"Rear Of 128-134, 128-134 Mount Street",
    "sg:city":"Fleetwood",
    "sg:classifiers":[
        {
            "category":"Professional",
            "type":"Services"
        },
        {
            "category":"Professional",
            "subcategory":"Printing & Photocopies",
            "type":"Services"
        }
    ],
    "sg:phone":"+44 1253 872003",
    "sg:postcode":"FY7 6LE",
    "sg:province":"Lancashire",
    "sg:tags":[
        "directory",
        "printer",
        "pub"
    ],
    "wof:name":"Panther Press",
    "wof:placetype":"venue"
},
  "geometry": {"coordinates":[-3.014669,53.92128],"type":"Point"}
}