{
  "type": "Feature",
  "properties": {
    "addr:full":"Angus House, Longmorn Elgin Moray IV30 8RJ",
    "addr:postcode":"iv30 8rj",
    "addr:street":"Longmorn",
    "iso:country":"GB",
    "sg:address":"Angus House, Longmorn",
    "sg:city":"Elgin",
    "sg:classifiers":[
        {
            "category":"Banks & Credit Unions",
            "subcategory":"Investment Brokerage",
            "type":"Services"
        }
    ],
    "sg:postcode":"IV30 8RJ",
    "sg:province":"Moray",
    "sg:tags":[
        "contractor"
    ],
    "wof:name":"W D Beaton Agricultural Contractors",
    "wof:placetype":"venue"
},
  "geometry": {"coordinates":[-3.2833,57.608089],"type":"Point"}
}