{
  "type": "Feature",
  "properties": {
    "iso:country":"GB",
    "sg:address":"The Street, Hatfield Peverel",
    "sg:city":"Chelmsford",
    "sg:classifiers":[
        {
            "category":"Bars & Pubs",
            "type":"Food & Drink"
        }
    ],
    "sg:phone":"+44 1245 380205",
    "sg:postcode":"CM3 2ET",
    "sg:province":"Essex",
    "sg:tags":[
        "pubs",
        "inn"
    ],
    "wof:name":"The William Boosey",
    "wof:placetype":"venue"
},
  "geometry": {"coordinates":[0.5707060099,51.8048782349],"type":"Point"}
}