{
  "type": "Feature",
  "properties": {
    "iso:country":"GB",
    "sg:address":"Engineering Enquiries, Bondgate Within",
    "sg:city":"Alnwick",
    "sg:classifiers":[
        {
            "category":"Utilities",
            "subcategory":"Electric",
            "type":"Services"
        }
    ],
    "sg:phone":"+44 1665 623590",
    "sg:postcode":"NE66 1SX",
    "sg:province":"Northumberland",
    "sg:tags":[
        "electricity"
    ],
    "wof:name":"Northern Electric Plc",
    "wof:placetype":"venue"
},
  "geometry": {"coordinates":[-1.703514,55.412601],"type":"Point"}
}