{
  "type": "Feature",
  "properties": {
    "addr:full":"10 Statham Close Lymm Cheshire WA13 9NN",
    "addr:housenumber":"10",
    "addr:postcode":"wa13 9nn",
    "addr:street":"Statham Close",
    "iso:country":"GB",
    "sg:address":"10 Statham Close",
    "sg:city":"Lymm",
    "sg:classifiers":[
        {
            "category":"Professional",
            "subcategory":"Secretarial Services",
            "type":"Services"
        }
    ],
    "sg:phone":"+44 1925 754375",
    "sg:postcode":"WA13 9NN",
    "sg:province":"Cheshire",
    "wof:name":"Wendervale Workshop",
    "wof:placetype":"venue"
},
  "geometry": {"coordinates":[-2.4869379997,53.3827972412],"type":"Point"}
}