{
  "type": "Feature",
  "properties": {
    "addr:full":"26 Regent St Leamington Spa Warwickshire CV32 5EH",
    "addr:housenumber":"26",
    "addr:postcode":"cv32 5eh",
    "addr:street":"Regent St",
    "iso:country":"GB",
    "sg:address":"26 Regent St",
    "sg:city":"Leamington Spa",
    "sg:classifiers":[
        {
            "category":"Shopping",
            "subcategory":"Department Store",
            "type":"Retail Goods"
        }
    ],
    "sg:postcode":"CV32 5EH",
    "sg:province":"Warwickshire",
    "wof:name":"Cadwallader,Colin L,",
    "wof:placetype":"venue"
},
  "geometry": {"coordinates":[-1.538416,52.290081],"type":"Point"}
}