{
  "type": "Feature",
  "properties": {
    "iso:country":"GB",
    "sg:address":"26-28 Lynmouth Road",
    "sg:city":"Reading",
    "sg:classifiers":[
        {
            "category":"Wholesale",
            "subcategory":"Meat",
            "type":"Manufacturing & Wholesale Goods"
        }
    ],
    "sg:phone":"+44 118 959 0243",
    "sg:postcode":"RG1 8DE",
    "sg:province":"Berkshire",
    "sg:tags":[
        "wholesaler",
        "-"
    ],
    "wof:name":"Associated Meat Companies Ltd.",
    "wof:placetype":"venue"
},
  "geometry": {"coordinates":[-0.9716529846,51.4622917175],"type":"Point"}
}