{
  "type": "Feature",
  "properties": {
    "addr:full":"Chanelle House, 86 New St Birmingham West Midlands B2 4BA",
    "addr:housenumber":"86",
    "addr:postcode":"b2 4ba",
    "addr:street":"New St",
    "iso:country":"GB",
    "sg:address":"Chanelle House, 86 New St",
    "sg:city":"Birmingham",
    "sg:classifiers":[
        {
            "category":"Professional",
            "subcategory":"Employment Agencies",
            "type":"Services"
        }
    ],
    "sg:phone":"+44 121 643 3911",
    "sg:postcode":"B2 4BA",
    "sg:province":"West Midlands",
    "sg:tags":[
        "consultant"
    ],
    "wof:name":"Windsor Consultancy Services",
    "wof:placetype":"venue"
},
  "geometry": {"coordinates":[-1.901707,52.479259],"type":"Point"}
}