{
  "type": "Feature",
  "properties": {
    "iso:country":"GB",
    "sg:address":"102-104 Morley Street",
    "sg:city":"Bradford",
    "sg:classifiers":[
        {
            "category":"Fast Food",
            "type":"Food & Drink"
        }
    ],
    "sg:phone":"+44 1274 394041",
    "sg:postcode":"BD7 1AF",
    "sg:province":"West Yorkshire",
    "sg:tags":[
        "delivery"
    ],
    "wof:name":"Pizza Torino",
    "wof:placetype":"venue"
},
  "geometry": {"coordinates":[-1.759487,53.790741],"type":"Point"}
}