{
  "type": "Feature",
  "properties": {
    "iso:country":"GB",
    "sg:address":"125a Craig Walk",
    "sg:city":"Windermere",
    "sg:classifiers":[
        {
            "category":"Building & Trades",
            "subcategory":"Construction",
            "type":"Services"
        }
    ],
    "sg:phone":"+44 15394 43797",
    "sg:postcode":"LA23 3AX",
    "sg:province":"Cumbria",
    "sg:tags":[
        "decorator",
        "painter"
    ],
    "wof:name":"F A Wade",
    "wof:placetype":"venue"
},
  "geometry": {"coordinates":[-2.9145040512,54.3662719727],"type":"Point"}
}