{
  "type": "Feature",
  "properties": {
    "addr:full":"Overend Rd, Congreaves Trading Est Cradley Heath West Midlands B64 7DH",
    "addr:postcode":"b64 7dh",
    "addr:street":"Overend Rd Congreaves",
    "iso:country":"GB",
    "sg:address":"Overend Rd, Congreaves Trading Est",
    "sg:city":"Cradley Heath",
    "sg:classifiers":[
        {
            "category":"Wholesale",
            "subcategory":"Metals & Minerals",
            "type":"Manufacturing & Wholesale Goods"
        }
    ],
    "sg:phone":"+44 1384 561199",
    "sg:postcode":"B64 7DH",
    "sg:province":"West Midlands",
    "sg:tags":[
        "non-ferrous"
    ],
    "wof:name":"Keltcrest Ltd",
    "wof:placetype":"venue"
},
  "geometry": {"coordinates":[-2.075994,52.4645],"type":"Point"}
}