{
  "type": "Feature",
  "properties": {
    "addr:full":"Ewelme Wallingford Oxfordshire OX10 6PJ",
    "addr:housenumber":"ewelme",
    "addr:postcode":"ox10 6pj",
    "iso:country":"GB",
    "sg:address":"Ewelme",
    "sg:city":"Wallingford",
    "sg:classifiers":[
        {
            "category":"Utilities",
            "subcategory":"Refuse",
            "type":"Services"
        }
    ],
    "sg:phone":"+44 1491 834311",
    "sg:postcode":"OX10 6PJ",
    "sg:province":"Oxfordshire",
    "sg:tags":[
        "disposal",
        "waste",
        "retail"
    ],
    "wof:name":"S Grundon (Services) Ltd.",
    "wof:placetype":"venue"
},
  "geometry": {"coordinates":[-1.072979,51.60997],"type":"Point"}
}