{
  "type": "Feature",
  "properties": {
    "iso:country":"GB",
    "sg:address":"115 Elvetham Road",
    "sg:city":"Fleet",
    "sg:classifiers":[
        {
            "category":"Food & Beverages",
            "subcategory":"Liquor & Beverages",
            "type":"Retail Goods"
        }
    ],
    "sg:phone":"+44 1544 327796",
    "sg:postcode":"GU13 8HW",
    "sg:province":"Dorset",
    "sg:tags":[
        "beer",
        "spirit",
        "wines"
    ],
    "wof:name":"Greywells Ltd.",
    "wof:placetype":"venue"
},
  "geometry": {"coordinates":[-0.8571810126,51.2880783081],"type":"Point"}
}