{
  "type": "Feature",
  "properties": {
    "iso:country":"GB",
    "sg:address":"Unit 30c & D Eagle Centre Mkt",
    "sg:city":"Derby",
    "sg:classifiers":[
        {
            "category":"Shopping",
            "subcategory":"Clothing, Apparel, & Fashions",
            "type":"Retail Goods"
        }
    ],
    "sg:phone":"+44 1332 366638",
    "sg:postcode":"DE1 2AZ",
    "sg:province":"Derbyshire",
    "sg:tags":[
        "shop"
    ],
    "wof:name":"Marks,Ronnie,",
    "wof:placetype":"venue"
},
  "geometry": {"coordinates":[-1.4727,52.920929],"type":"Point"}
}