{
  "type": "Feature",
  "properties": {
    "addr:full":"6 Cambridge Street Harrogate North Yorkshire HG1 1RX",
    "addr:housenumber":"6",
    "addr:postcode":"hg1 1rx",
    "addr:street":"Cambridge Street",
    "iso:country":"GB",
    "sg:address":"6 Cambridge Street",
    "sg:city":"Harrogate",
    "sg:classifiers":[
        {
            "category":"Travel",
            "subcategory":"Travel Agent",
            "type":"Entertainment"
        }
    ],
    "sg:phone":"+44 1423 564144",
    "sg:postcode":"HG1 1RX",
    "sg:province":"North Yorkshire",
    "wof:name":"Going Places",
    "wof:placetype":"venue"
},
  "geometry": {"coordinates":[-1.5388330221,53.9934425354],"type":"Point"}
}