{
  "type": "Feature",
  "properties": {
    "addr:full":"Station La, Enton Godalming Surrey GU8 5AE",
    "addr:postcode":"gu8 5ae",
    "addr:street":"Godalming",
    "iso:country":"GB",
    "sg:address":"Station La, Enton",
    "sg:city":"Godalming",
    "sg:classifiers":[
        {
            "category":"Food & Beverages",
            "subcategory":"Farmers Market",
            "type":"Retail Goods"
        }
    ],
    "sg:postcode":"GU8 5AE",
    "sg:province":"Surrey",
    "sg:tags":[
        "farm",
        "shop",
        "pyo"
    ],
    "wof:name":"Marsh Farm",
    "wof:placetype":"venue"
},
  "geometry": {"coordinates":[-0.6370289922,51.1630516052],"type":"Point"}
}