{
  "type": "Feature",
  "properties": {
    "iso:country":"GB",
    "sg:address":"13 Main Street, Bentham",
    "sg:city":"Lancaster",
    "sg:classifiers":[
        {
            "category":"Bars & Pubs",
            "type":"Food & Drink"
        }
    ],
    "sg:phone":"+44 15242 61213",
    "sg:postcode":"LA2 8JR",
    "sg:province":"Lancashire",
    "sg:tags":[
        "pubs",
        "inn"
    ],
    "wof:name":"The Black Bull Hotel",
    "wof:placetype":"venue"
},
  "geometry": {"coordinates":[-2.63604,54.109127],"type":"Point"}
}