{
  "type": "Feature",
  "properties": {
    "iso:country":"GB",
    "sg:address":"25 Appletree Close, Calmore",
    "sg:city":"Southampton",
    "sg:classifiers":[
        {
            "category":"Home & Garden",
            "subcategory":"Building Materials",
            "type":"Retail Goods"
        }
    ],
    "sg:postcode":"SO40 2UX",
    "sg:province":"Hampshire",
    "sg:tags":[
        "fencing"
    ],
    "wof:name":"Paul Lucas Fencing",
    "wof:placetype":"venue"
},
  "geometry": {"coordinates":[-1.514202,50.925072],"type":"Point"}
}