{
  "type": "Feature",
  "properties": {
    "addr:full":"Infusion House, Rougham Industrial Estate Bury St Edmunds Suffolk IP30 9ND",
    "addr:postcode":"ip30 9nd",
    "addr:street":"Industrial Estate;St",
    "iso:country":"GB",
    "sg:address":"Infusion House, Rougham Industrial Estate",
    "sg:city":"Bury St Edmunds",
    "sg:classifiers":[
        {
            "category":"Coffee & Tea",
            "type":"Food & Drink"
        }
    ],
    "sg:phone":"+44 1359 270679",
    "sg:postcode":"IP30 9ND",
    "sg:province":"Suffolk",
    "wof:name":"Accord Sevices Ltd.",
    "wof:placetype":"venue"
},
  "geometry": {"coordinates":[0.77528,52.241341],"type":"Point"}
}