{
  "type": "Feature",
  "properties": {
    "addr:full":"704 Huddersfield Road, Ravensthorpe Dewsbury West Yorkshire WF13 3HU",
    "addr:housenumber":"704",
    "addr:postcode":"wf13 3hu",
    "addr:street":"Huddersfield Road;West",
    "iso:country":"GB",
    "sg:address":"704 Huddersfield Road, Ravensthorpe",
    "sg:city":"Dewsbury",
    "sg:classifiers":[
        {
            "category":"Insurance",
            "subcategory":"Insurance Agent",
            "type":"Services"
        }
    ],
    "sg:phone":"+44 1924 499182",
    "sg:postcode":"WF13 3HU",
    "sg:province":"West Yorkshire",
    "sg:tags":[
        "broker"
    ],
    "sg:website":"http://www.brian-thornhill.co.uk",
    "wof:name":"Brian Thornhill & Co. (Insurance Brokers)",
    "wof:placetype":"venue"
},
  "geometry": {"coordinates":[-1.667998,53.677685],"type":"Point"}
}