{
  "type": "Feature",
  "properties": {
    "addr:full":"Cheswell Grange, Lilleshall Newport Shropshire TF10 9AE",
    "addr:postcode":"tf10 9ae",
    "iso:country":"GB",
    "sg:address":"Cheswell Grange, Lilleshall",
    "sg:city":"Newport",
    "sg:classifiers":[
        {
            "category":"Farming",
            "subcategory":"Livestock Farm",
            "type":"Manufacturing & Wholesale Goods"
        }
    ],
    "sg:postcode":"TF10 9AE",
    "sg:province":"Shropshire",
    "sg:tags":[
        "others"
    ],
    "wof:name":"G Whitfield & Son Ltd.",
    "wof:placetype":"venue"
},
  "geometry": {"coordinates":[-2.397581,52.738846],"type":"Point"}
}