{
  "type": "Feature",
  "properties": {
    "iso:country":"GB",
    "sg:address":"59a High Street, Wanstead",
    "sg:city":"London",
    "sg:classifiers":[
        {
            "category":"Shopping",
            "subcategory":"Pharmacy",
            "type":"Retail Goods"
        }
    ],
    "sg:phone":"+44 20 8989 0070",
    "sg:postcode":"E11 2AE",
    "sg:province":"Greater London",
    "sg:tags":[
        "pharmacist",
        "chemist"
    ],
    "wof:name":"Centre Point Pharmaceuticals",
    "wof:placetype":"venue"
},
  "geometry": {"coordinates":[0.02623,51.578178],"type":"Point"}
}