{
  "type": "Feature",
  "properties": {
    "addr:full":"12 Queens Road Norwich Norfolk NR1 3PR",
    "addr:housenumber":"12",
    "addr:postcode":"nr1 3pr",
    "addr:street":"Queens Road Norwich Norfolk",
    "iso:country":"GB",
    "sg:address":"12 Queens Road",
    "sg:city":"Norwich",
    "sg:classifiers":[
        {
            "category":"Shopping",
            "subcategory":"Thrift Store",
            "type":"Retail Goods"
        }
    ],
    "sg:phone":"+44 1603 765678",
    "sg:postcode":"NR1 3PR",
    "sg:province":"Norfolk",
    "sg:tags":[
        "shop",
        "charity"
    ],
    "wof:name":"Relate Charity Shop",
    "wof:placetype":"venue"
},
  "geometry": {"coordinates":[1.291933,52.623856],"type":"Point"}
}