{
  "type": "Feature",
  "properties": {
    "iso:country":"GB",
    "sg:address":"1 West Street, Ditchling",
    "sg:city":"Hassocks",
    "sg:classifiers":[
        {
            "category":"Professional",
            "type":"Services"
        }
    ],
    "sg:phone":"+44 1273 845497",
    "sg:postcode":"BN6 8TS",
    "sg:province":"East Sussex",
    "sg:tags":[
        "archaeologist"
    ],
    "wof:name":"Archaeology South East",
    "wof:placetype":"venue"
},
  "geometry": {"coordinates":[-0.1152150035,50.9208908081],"type":"Point"}
}