{
  "type": "Feature",
  "properties": {
    "iso:country":"GB",
    "sg:address":"190 Ashby Road",
    "sg:city":"Scunthorpe",
    "sg:classifiers":[
        {
            "category":"Retail",
            "subcategory":"Repair Shop",
            "type":"Services"
        },
        {
            "category":"Shopping",
            "subcategory":"Used Merchandise",
            "type":"Retail Goods"
        }
    ],
    "sg:phone":"+44 1724 278535",
    "sg:postcode":"DN16 2AR",
    "sg:province":"Lincolnshire",
    "sg:tags":[
        "sale",
        "second-hand"
    ],
    "wof:name":"The Answer",
    "wof:placetype":"venue"
},
  "geometry": {"coordinates":[-0.655448,53.573925],"type":"Point"}
}