{
  "type": "Feature",
  "properties": {
    "addr:full":"1 Ballinghall Close, Coldington Bedford Bedfordshire MK41 0AB",
    "addr:housenumber":"1",
    "addr:postcode":"mk41 0ab",
    "addr:street":"Ballinghall Close",
    "iso:country":"GB",
    "sg:address":"1 Ballinghall Close, Coldington",
    "sg:city":"Bedford",
    "sg:classifiers":[
        {
            "category":"Building & Trades",
            "subcategory":"Construction",
            "type":"Services"
        }
    ],
    "sg:postcode":"MK41 0AB",
    "sg:province":"Bedfordshire",
    "sg:tags":[
        "excavation",
        "groundwork",
        "contractor"
    ],
    "wof:name":"Claford Contractors Civil Engineering",
    "wof:placetype":"venue"
},
  "geometry": {"coordinates":[-0.432673,52.143047],"type":"Point"}
}