{
  "type": "Feature",
  "properties": {
    "addr:full":"28 South Road, Puckeridge Ware Hertfordshire SG11 1TH",
    "addr:housenumber":"28",
    "addr:postcode":"sg11 1th",
    "addr:street":"South Road;Ware",
    "iso:country":"GB",
    "sg:address":"28 South Road, Puckeridge",
    "sg:city":"Ware",
    "sg:classifiers":[
        {
            "category":"Building & Trades",
            "subcategory":"Landscaping Services",
            "type":"Services"
        }
    ],
    "sg:postcode":"SG11 1TH",
    "sg:province":"Hertfordshire",
    "sg:tags":[
        "gardening"
    ],
    "wof:name":"J F Sallows",
    "wof:placetype":"venue"
},
  "geometry": {"coordinates":[0.0168639999,51.8876495361],"type":"Point"}
}