{
  "type": "Feature",
  "properties": {
    "iso:country":"GB",
    "sg:address":"Omega House, 6 Buckingham Place, Bellfield Road",
    "sg:city":"High Wycombe",
    "sg:classifiers":[
        {
            "category":"Social Services",
            "subcategory":"Retirement Home",
            "type":"Services"
        }
    ],
    "sg:phone":"+44 1494 512266",
    "sg:postcode":"HP13 5HW",
    "sg:province":"Buckinghamshire",
    "sg:tags":[
        "care"
    ],
    "wof:name":"Community Careline Services",
    "wof:placetype":"venue"
},
  "geometry": {"coordinates":[-0.758771,51.633278],"type":"Point"}
}