{
  "type": "Feature",
  "properties": {
    "iso:country":"GB",
    "sg:address":"39-41 Fore Street",
    "sg:city":"Saltash",
    "sg:classifiers":[
        {
            "category":"Manufacturing",
            "subcategory":"Building Materials",
            "type":"Manufacturing & Wholesale Goods"
        }
    ],
    "sg:postcode":"PL12 6AF",
    "sg:province":"Cornwall",
    "sg:tags":[
        "merchant",
        "builder"
    ],
    "wof:name":"H P Thompson",
    "wof:placetype":"venue"
},
  "geometry": {"coordinates":[-4.211143,50.408478],"type":"Point"}
}