{
  "type": "Feature",
  "properties": {
    "addr:full":"10 Sandgate Road Folkestone Kent CT20 1DP",
    "addr:housenumber":"10",
    "addr:postcode":"ct20 1dp",
    "addr:street":"Sandgate Road",
    "iso:country":"GB",
    "sg:address":"10 Sandgate Road",
    "sg:city":"Folkestone",
    "sg:classifiers":[
        {
            "category":"Shopping",
            "subcategory":"Music",
            "type":"Retail Goods"
        }
    ],
    "sg:phone":"+44 1303 250654",
    "sg:postcode":"CT20 1DP",
    "sg:province":"Kent",
    "sg:tags":[
        "record",
        "tape",
        "cd"
    ],
    "wof:name":"Our Price",
    "wof:placetype":"venue"
},
  "geometry": {"coordinates":[1.153845,51.076168],"type":"Point"}
}