{
  "type": "Feature",
  "properties": {
    "addr:full":"Llyswen Brecon Powys LD3 0UR",
    "addr:postcode":"ld3 0ur",
    "iso:country":"GB",
    "sg:address":"Llyswen",
    "sg:city":"Brecon",
    "sg:classifiers":[
        {
            "category":"Autos & Motor Vehicles",
            "subcategory":"Fuel & Gas Station",
            "type":"Retail Goods"
        }
    ],
    "sg:phone":"+44 1874 754217",
    "sg:postcode":"LD3 0UR",
    "sg:province":"Powys",
    "sg:tags":[
        "petrol",
        "filling"
    ],
    "wof:name":"Wye Garage",
    "wof:placetype":"venue"
},
  "geometry": {"coordinates":[-3.2563259602,52.0041122437],"type":"Point"}
}