{
  "type": "Feature",
  "properties": {
    "iso:country":"GB",
    "sg:address":"2 Crompton Road, Wheatley",
    "sg:city":"Doncaster",
    "sg:classifiers":[
        {
            "category":"Food & Beverages",
            "subcategory":"Meat & Fish",
            "type":"Retail Goods"
        },
        {
            "category":"Food & Beverages",
            "subcategory":"Groceries & Convenience Stores",
            "type":"Retail Goods"
        }
    ],
    "sg:phone":"+44 1302 730206",
    "sg:postcode":"DN2 4PW",
    "sg:province":"South Yorkshire",
    "sg:tags":[
        "shop",
        "chip"
    ],
    "wof:name":"Golden Leas",
    "wof:placetype":"venue"
},
  "geometry": {"coordinates":[-1.095031023,53.5430335999],"type":"Point"}
}