{
  "type": "Feature",
  "properties": {
    "iso:country":"GB",
    "sg:address":"29 Victoria Road East, Thornton",
    "sg:city":"Thornton-cleveleys",
    "sg:classifiers":[
        {
            "category":"Retail",
            "subcategory":"Repair Shop",
            "type":"Services"
        }
    ],
    "sg:phone":"+44 1253 826136",
    "sg:postcode":"FY5 5BU",
    "sg:province":"Lancashire",
    "sg:tags":[
        "radio",
        "television",
        "video"
    ],
    "wof:name":"Fylde Colourvision",
    "wof:placetype":"venue"
},
  "geometry": {"coordinates":[-3.00201,53.870247],"type":"Point"}
}