{
  "type": "Feature",
  "properties": {
    "iso:country":"GB",
    "sg:address":"Old Bracknell House, Crowthorne Road North",
    "sg:city":"Bracknell",
    "sg:classifiers":[
        {
            "category":"Farming",
            "subcategory":"Nursery",
            "type":"Manufacturing & Wholesale Goods"
        }
    ],
    "sg:postcode":"RG12 7AJ",
    "sg:province":"Berkshire",
    "sg:tags":[
        "creche"
    ],
    "wof:name":"Bramleywood Day Nursery",
    "wof:placetype":"venue"
},
  "geometry": {"coordinates":[-0.7517099977,51.4109992981],"type":"Point"}
}