{
  "type": "Feature",
  "properties": {
    "addr:full":"2 Marlborough Court, Manaton Close, Matford Business Park Exeter Devon EX2 8PF",
    "addr:housenumber":"2",
    "addr:postcode":"ex2 8pf",
    "addr:street":"Marlborough Court Manaton Close Matford Business Park",
    "iso:country":"GB",
    "sg:address":"2 Marlborough Court, Manaton Close, Matford Business Park",
    "sg:city":"Exeter",
    "sg:classifiers":[
        {
            "category":"Organizations",
            "subcategory":"Professional Association",
            "type":"Services"
        }
    ],
    "sg:phone":"+44 1392 822500",
    "sg:postcode":"EX2 8PF",
    "sg:province":"Devon",
    "sg:tags":[
        "union",
        "trade"
    ],
    "wof:name":"N A S U W T",
    "wof:placetype":"venue"
},
  "geometry": {"coordinates":[-3.522329092,50.6919174194],"type":"Point"}
}