{
  "type": "Feature",
  "properties": {
    "addr:full":"Lake Road, Hooe Plymouth Devon PL9 9QY",
    "addr:postcode":"pl9 9qy",
    "addr:street":"Lake Road",
    "iso:country":"GB",
    "sg:address":"Lake Road, Hooe",
    "sg:city":"Plymouth",
    "sg:classifiers":[
        {
            "category":"Bars & Pubs",
            "type":"Food & Drink"
        }
    ],
    "sg:postcode":"PL9 9QY",
    "sg:province":"Devon",
    "sg:tags":[
        "pubs",
        "inn"
    ],
    "wof:name":"The Royal Oak",
    "wof:placetype":"venue"
},
  "geometry": {"coordinates":[-4.1086220741,50.3524436951],"type":"Point"}
}