{
  "type": "Feature",
  "properties": {
    "iso:country":"GB",
    "sg:address":"Portman Rd",
    "sg:city":"Bournemouth",
    "sg:classifiers":[
        {
            "category":"Place Of Worship",
            "type":"Public Place"
        }
    ],
    "sg:phone":"+44 1202 394622",
    "sg:postcode":"BH7 6EU",
    "sg:province":"Dorset",
    "wof:name":"St George's Methodist Church",
    "wof:placetype":"venue"
},
  "geometry": {"coordinates":[-1.837539,50.730518],"type":"Point"}
}