{
  "type": "Feature",
  "properties": {
    "addr:full":"20 The Deans, Portishead Bristol Somerset BS20 6EG",
    "addr:housenumber":"20",
    "addr:postcode":"bs20 6eg",
    "addr:street":"The Deans",
    "iso:country":"GB",
    "sg:address":"20 The Deans, Portishead",
    "sg:city":"Bristol",
    "sg:classifiers":[
        {
            "category":"Professional",
            "subcategory":"Engineering",
            "type":"Services"
        }
    ],
    "sg:phone":"+44 1275 848969",
    "sg:postcode":"BS20 6EG",
    "sg:province":"Somerset",
    "sg:tags":[
        "contractor",
        "electrical",
        "engineer"
    ],
    "wof:name":"D S Oliver",
    "wof:placetype":"venue"
},
  "geometry": {"coordinates":[-2.772819,51.480129],"type":"Point"}
}