{
  "type": "Feature",
  "properties": {
    "iso:country":"GB",
    "sg:address":"76 South Street",
    "sg:city":"Bishops Stortford",
    "sg:classifiers":[
        {
            "category":"Autos & Motor Vehicles",
            "subcategory":"Auto Supplies",
            "type":"Retail Goods"
        },
        {
            "category":"Shopping",
            "type":"Retail Goods"
        }
    ],
    "sg:phone":"+44 1279 651671",
    "sg:postcode":"CM23 3AZ",
    "sg:province":"Essex",
    "sg:tags":[
        "car",
        "part",
        "customisers",
        "accessory"
    ],
    "wof:name":"Motor World Ltd",
    "wof:placetype":"venue"
},
  "geometry": {"coordinates":[0.160701,51.868053],"type":"Point"}
}