{
  "type": "Feature",
  "properties": {
    "addr:full":"55 St Dunstans Street Canterbury Kent CT2 8BS",
    "addr:housenumber":"55",
    "addr:postcode":"ct2 8bs",
    "addr:street":"St Dunstans Street",
    "iso:country":"GB",
    "sg:address":"55 St Dunstans Street",
    "sg:city":"Canterbury",
    "sg:classifiers":[
        {
            "category":"Health Services",
            "subcategory":"Dentist",
            "type":"Services"
        }
    ],
    "sg:postcode":"CT2 8BS",
    "sg:province":"Kent",
    "wof:name":"Christopher Cox",
    "wof:placetype":"venue"
},
  "geometry": {"coordinates":[1.0744199753,51.2821311951],"type":"Point"}
}