{
  "type": "Feature",
  "properties": {
    "addr:full":"32 Duncan Road Gillingham Kent ME7 4LE",
    "addr:housenumber":"32",
    "addr:postcode":"me7 4le",
    "addr:street":"Duncan Road",
    "iso:country":"GB",
    "sg:address":"32 Duncan Road",
    "sg:city":"Gillingham",
    "sg:classifiers":[
        {
            "category":"Retail",
            "subcategory":"Auto Repair",
            "type":"Services"
        }
    ],
    "sg:phone":"+44 1634 851161",
    "sg:postcode":"ME7 4LE",
    "sg:province":"Kent",
    "sg:tags":[
        "electrician"
    ],
    "wof:name":"Lucas Service U K",
    "wof:placetype":"venue"
},
  "geometry": {"coordinates":[0.550472,51.384678],"type":"Point"}
}