{
  "type": "Feature",
  "properties": {
    "addr:full":"201 Newbattle Abbey Crescent Dalkeith City of Edinburgh EH22 3LU",
    "addr:housenumber":"201",
    "addr:postcode":"eh22 3lu",
    "addr:street":"Newbattle Abbey Crescent",
    "iso:country":"GB",
    "sg:address":"201 Newbattle Abbey Crescent",
    "sg:city":"Dalkeith",
    "sg:classifiers":[
        {
            "category":"Professional",
            "subcategory":"Accounting & Tax Preparation",
            "type":"Services"
        }
    ],
    "sg:phone":"+44 131 663 4389",
    "sg:postcode":"EH22 3LU",
    "sg:province":"City of Edinburgh",
    "sg:tags":[
        "accountant",
        "bookkeeping",
        "primarily",
        "activity"
    ],
    "wof:name":"C J H Book Keeping Services",
    "wof:placetype":"venue"
},
  "geometry": {"coordinates":[-3.0750670433,55.8801956177],"type":"Point"}
}