{
  "type": "Feature",
  "properties": {
    "addr:full":"Ruthin House, 135 Poulton Road Fleetwood Lancashire FY7 7AP",
    "addr:housenumber":"135",
    "addr:postcode":"fy7 7ap",
    "addr:street":"Poulton Road",
    "iso:country":"GB",
    "sg:address":"Ruthin House, 135 Poulton Road",
    "sg:city":"Fleetwood",
    "sg:classifiers":[
        {
            "category":"Retail",
            "subcategory":"Funeral Services",
            "type":"Services"
        }
    ],
    "sg:phone":"+44 1253 772111",
    "sg:postcode":"FY7 7AP",
    "sg:province":"Lancashire",
    "sg:tags":[
        "director"
    ],
    "wof:name":"Fleetwood Funeral Home",
    "wof:placetype":"venue"
},
  "geometry": {"coordinates":[-3.0146689415,53.9212799072],"type":"Point"}
}