{
  "type": "Feature",
  "properties": {
    "iso:country":"GB",
    "sg:address":"5 Chelford Road",
    "sg:city":"Macclesfield",
    "sg:classifiers":[
        {
            "category":"Professional",
            "subcategory":"Art Services",
            "type":"Services"
        }
    ],
    "sg:phone":"+44 1625 502121",
    "sg:postcode":"SK10 3LG",
    "sg:province":"Cheshire",
    "sg:tags":[
        "decorating",
        "painting"
    ],
    "wof:name":"Broken Cross Paint & Wallpaper Supplies Ltd.",
    "wof:placetype":"venue"
},
  "geometry": {"coordinates":[-2.161735,53.259617],"type":"Point"}
}