{
  "type": "Feature",
  "properties": {
    "iso:country":"GB",
    "sg:address":"16-18 Tower Road",
    "sg:city":"Bournemouth",
    "sg:classifiers":[
        {
            "category":"Health Services",
            "subcategory":"Clinic",
            "type":"Services"
        }
    ],
    "sg:phone":"+44 1202 443174",
    "sg:postcode":"BH1 4LB",
    "sg:province":"Dorset",
    "sg:tags":[
        "nh"
    ],
    "wof:name":"The Sedman Unit",
    "wof:placetype":"venue"
},
  "geometry": {"coordinates":[-1.8427729607,50.7299385071],"type":"Point"}
}