{
  "type": "Feature",
  "properties": {
    "iso:country":"GB",
    "sg:address":"Wessington Avenue",
    "sg:city":"Calne",
    "sg:classifiers":[
        {
            "category":"Building & Trades",
            "subcategory":"Plumbing",
            "type":"Services"
        },
        {
            "category":"Building & Trades",
            "subcategory":"Cleaning & Sanitation",
            "type":"Services"
        }
    ],
    "sg:phone":"+44 1249 812153",
    "sg:postcode":"SN11 0AP",
    "sg:province":"Wiltshire",
    "sg:tags":[
        "toilet",
        "portable"
    ],
    "wof:name":"Wessington Cabins Ltd",
    "wof:placetype":"venue"
},
  "geometry": {"coordinates":[-1.997964,51.430286],"type":"Point"}
}