{
  "type": "Feature",
  "properties": {
    "addr:full":"139-141 Oakbrook Road Sheffield Derbyshire S11 7EB",
    "addr:housenumber":"139-141",
    "addr:postcode":"s11 7eb",
    "addr:street":"Oakbrook Road",
    "iso:country":"GB",
    "sg:address":"139-141 Oakbrook Road",
    "sg:city":"Sheffield",
    "sg:classifiers":[
        {
            "category":"Fast Food",
            "type":"Food & Drink"
        }
    ],
    "sg:phone":"+44 114 230 8312",
    "sg:postcode":"S11 7EB",
    "sg:province":"Derbyshire",
    "sg:tags":[
        "away",
        "take"
    ],
    "wof:name":"THE SHEFFIELD & TANDOORI RESTAURANT",
    "wof:placetype":"venue"
},
  "geometry": {"coordinates":[-1.5193639994,53.3686256409],"type":"Point"}
}