{
  "type": "Feature",
  "properties": {
    "iso:country":"GB",
    "sg:address":"Hawbush Road",
    "sg:city":"Brierley Hill",
    "sg:classifiers":[
        {
            "category":"Education",
            "subcategory":"School",
            "type":"Public Place"
        },
        {
            "category":"Government",
            "subcategory":"Office",
            "type":"Public Place"
        }
    ],
    "sg:phone":"+44 1384 816930",
    "sg:postcode":"DY5 3NH",
    "sg:province":"West Midlands",
    "sg:tags":[
        "local",
        "authority"
    ],
    "wof:name":"Hawbush Primary School",
    "wof:placetype":"venue"
},
  "geometry": {"coordinates":[-2.1404690742,52.4815406799],"type":"Point"}
}