{
  "type": "Feature",
  "properties": {
    "addr:full":"21-23 Leeds Road Liversedge West Yorkshire WF15 6JB",
    "addr:housenumber":"21-23",
    "addr:postcode":"wf15 6jb",
    "addr:street":"Leeds Road",
    "iso:country":"GB",
    "sg:address":"21-23 Leeds Road",
    "sg:city":"Liversedge",
    "sg:classifiers":[
        {
            "category":"Home & Garden",
            "subcategory":"Carpets & Floor Coverings",
            "type":"Retail Goods"
        }
    ],
    "sg:phone":"+44 1924 407586",
    "sg:postcode":"WF15 6JB",
    "sg:province":"West Yorkshire",
    "sg:tags":[
        "carpets",
        "retailer",
        "rug",
        "matting"
    ],
    "wof:name":"Ringseam Ltd",
    "wof:placetype":"venue"
},
  "geometry": {"coordinates":[-1.6867790222,53.7102394104],"type":"Point"}
}