{
  "type": "Feature",
  "properties": {
    "addr:full":"Old Whitehouse Barn Wks Hereford Herefordshire HR3 5ET",
    "addr:postcode":"hr3 5et",
    "addr:street":"Old",
    "iso:country":"GB",
    "sg:address":"Old Whitehouse Barn Wks",
    "sg:city":"Hereford",
    "sg:classifiers":[
        {
            "category":"Manufacturing",
            "subcategory":"Rubber & Plastics",
            "type":"Manufacturing & Wholesale Goods"
        }
    ],
    "sg:postcode":"HR3 5ET",
    "sg:province":"Herefordshire",
    "sg:tags":[
        "product"
    ],
    "wof:name":"Mountway Marine & Development",
    "wof:placetype":"venue"
},
  "geometry": {"coordinates":[-3.0997900963,52.1068115234],"type":"Point"}
}