{
  "type": "Feature",
  "properties": {
    "addr:full":"108 Pitshanger Lane, North Ealing Ealing Greater London W5 1QP",
    "addr:housenumber":"108",
    "addr:postcode":"w5 1qp",
    "addr:street":"Pitshanger Lane North",
    "iso:country":"GB",
    "sg:address":"108 Pitshanger Lane, North Ealing",
    "sg:city":"Ealing",
    "sg:classifiers":[
        {
            "category":"Food & Beverages",
            "subcategory":"Liquor & Beverages",
            "type":"Retail Goods"
        }
    ],
    "sg:phone":"+44 20 8997 4666",
    "sg:postcode":"W5 1QP",
    "sg:province":"Greater London",
    "sg:tags":[
        "beer",
        "spirit",
        "wines"
    ],
    "wof:name":"Wine Rack",
    "wof:placetype":"venue"
},
  "geometry": {"coordinates":[-0.3131839931,51.5262756348],"type":"Point"}
}