{
  "type": "Feature",
  "properties": {
    "addr:full":"82 Shrewsbury Drive, Chesterton Newcastle Staffordshire ST5 7RQ",
    "addr:housenumber":"82",
    "addr:postcode":"st5 7rq",
    "addr:street":"Shrewsbury Drive",
    "iso:country":"GB",
    "sg:address":"82 Shrewsbury Drive, Chesterton",
    "sg:city":"Newcastle",
    "sg:classifiers":[
        {
            "category":"Banks & Credit Unions",
            "subcategory":"Bank",
            "type":"Services"
        }
    ],
    "sg:phone":"+44 1782 564134",
    "sg:postcode":"ST5 7RQ",
    "sg:province":"Staffordshire",
    "sg:tags":[
        "broker",
        "mortgage"
    ],
    "wof:name":"Maher & David Brownsword",
    "wof:placetype":"venue"
},
  "geometry": {"coordinates":[-2.253558,53.05608],"type":"Point"}
}