{
  "type": "Feature",
  "properties": {
    "addr:full":"Drome Road, Deeside Industrial Park Chester Flintshire CH5 2NY",
    "addr:postcode":"ch5 2ny",
    "addr:street":"Drome Road;Industrial Park",
    "iso:country":"GB",
    "sg:address":"Drome Road, Deeside Industrial Park",
    "sg:city":"Chester",
    "sg:classifiers":[
        {
            "category":"Autos & Motor Vehicles",
            "subcategory":"Auto Supplies",
            "type":"Retail Goods"
        }
    ],
    "sg:phone":"+44 1244 284500",
    "sg:postcode":"CH5 2NY",
    "sg:province":"Flintshire",
    "sg:tags":[
        "towing",
        "eqpt",
        "trailer"
    ],
    "wof:name":"C P Witter Ltd.",
    "wof:placetype":"venue"
},
  "geometry": {"coordinates":[-2.9981219769,53.2281036377],"type":"Point"}
}