{
  "type": "Feature",
  "properties": {
    "addr:full":"Kennington Avenue Loanhead Midlothian EH20 9HY",
    "addr:postcode":"eh20 9hy",
    "addr:street":"Kennington Avenue",
    "iso:country":"GB",
    "sg:address":"Kennington Avenue",
    "sg:city":"Loanhead",
    "sg:classifiers":[
        {
            "category":"Arena",
            "subcategory":"Sports Club",
            "type":"Entertainment"
        }
    ],
    "sg:phone":"+44 131 440 2940",
    "sg:postcode":"EH20 9HY",
    "sg:province":"Midlothian",
    "wof:name":"Loanhead Bowling Club",
    "wof:placetype":"venue"
},
  "geometry": {"coordinates":[-3.155364,55.877522],"type":"Point"}
}