{
  "type": "Feature",
  "properties": {
    "iso:country":"GB",
    "sg:address":"178 Shear Brow",
    "sg:city":"Blackburn",
    "sg:classifiers":[
        {
            "category":"Food & Beverages",
            "subcategory":"Meat & Fish",
            "type":"Retail Goods"
        }
    ],
    "sg:phone":"+44 1254 680199",
    "sg:postcode":"BB1 8DZ",
    "sg:province":"Lancashire",
    "sg:tags":[
        "chip"
    ],
    "wof:name":"Reno's",
    "wof:placetype":"venue"
},
  "geometry": {"coordinates":[-2.4872438908,53.7584648132],"type":"Point"}
}