{
  "type": "Feature",
  "properties": {
    "addr:full":"100 Gray Street, Broughty Ferry Dundee Angus DD5 2DN",
    "addr:housenumber":"100",
    "addr:postcode":"dd5 2dn",
    "addr:street":"Gray Street",
    "iso:country":"GB",
    "sg:address":"100 Gray Street, Broughty Ferry",
    "sg:city":"Dundee",
    "sg:classifiers":[
        {
            "category":"Personal",
            "subcategory":"Beauty Salon",
            "type":"Services"
        }
    ],
    "sg:phone":"+44 1382 778279",
    "sg:postcode":"DD5 2DN",
    "sg:province":"Angus",
    "sg:tags":[
        "unisex",
        "hairdresser"
    ],
    "wof:name":"Headline",
    "wof:placetype":"venue"
},
  "geometry": {"coordinates":[-2.8728270531,56.4672317505],"type":"Point"}
}