{
  "type": "Feature",
  "properties": {
    "iso:country":"GB",
    "sg:address":"7 Bullock Fair Clo",
    "sg:city":"Harleston",
    "sg:classifiers":[
        {
            "category":"Shopping",
            "subcategory":"Department Store",
            "type":"Retail Goods"
        },
        {
            "category":"Sports & Exercise",
            "subcategory":"Sports Center",
            "type":"Entertainment"
        }
    ],
    "sg:phone":"+44 1379 853431",
    "sg:postcode":"IP20 9AT",
    "sg:province":"Norfolk",
    "sg:tags":[
        "shop"
    ],
    "wof:name":"Bellamy,Michael,",
    "wof:placetype":"venue"
},
  "geometry": {"coordinates":[1.299863,52.403004],"type":"Point"}
}