{
  "type": "Feature",
  "properties": {
    "addr:full":"35 Stratford Road Ipswich Suffolk IP1 6EF",
    "addr:housenumber":"35",
    "addr:postcode":"ip1 6ef",
    "addr:street":"Stratford Road",
    "iso:country":"GB",
    "sg:address":"35 Stratford Road",
    "sg:city":"Ipswich",
    "sg:classifiers":[
        {
            "category":"Retail",
            "subcategory":"Auto Rental",
            "type":"Services"
        },
        {
            "category":"Autos & Motor Vehicles",
            "subcategory":"Motorcycle Sales",
            "type":"Retail Goods"
        }
    ],
    "sg:postcode":"IP1 6EF",
    "sg:province":"Suffolk",
    "sg:tags":[
        "chauffeur",
        "driven",
        "hire",
        "car"
    ],
    "wof:name":"MERCEDES WEDDING HIRE",
    "wof:placetype":"venue"
},
  "geometry": {"coordinates":[1.130442977,52.0797386169],"type":"Point"}
}