{
  "type": "Feature",
  "properties": {
    "addr:full":"96 Front Street Chester-le-street Durham DH3 3BB",
    "addr:housenumber":"96",
    "addr:postcode":"dh3 3bb",
    "addr:street":"Front Street",
    "iso:country":"GB",
    "sg:address":"96 Front Street",
    "sg:city":"Chester-le-street",
    "sg:classifiers":[
        {
            "category":"Travel",
            "subcategory":"Travel Agent",
            "type":"Entertainment"
        }
    ],
    "sg:phone":"+44 191 388 2615",
    "sg:postcode":"DH3 3BB",
    "sg:province":"Durham",
    "wof:name":"Going Places Leisure Travel",
    "wof:placetype":"venue"
},
  "geometry": {"coordinates":[-1.5735830069,54.8560829163],"type":"Point"}
}