{
  "type": "Feature",
  "properties": {
    "addr:full":"Unit 12 Dockray Hall Indust Est Kendal Cumbria LA9 4RU",
    "addr:housenumber":"unit 12",
    "addr:postcode":"la9 4ru",
    "addr:street":"Dockray Hall Indust Est",
    "iso:country":"GB",
    "sg:address":"Unit 12 Dockray Hall Indust Est",
    "sg:city":"Kendal",
    "sg:classifiers":[
        {
            "category":"Shopping",
            "subcategory":"Computers & Home Electronics",
            "type":"Retail Goods"
        }
    ],
    "sg:phone":"+44 1539 729588",
    "sg:postcode":"LA9 4RU",
    "sg:province":"Cumbria",
    "sg:tags":[
        "aerial",
        "television",
        "radio"
    ],
    "wof:name":"Jontec",
    "wof:placetype":"venue"
},
  "geometry": {"coordinates":[-2.7479379177,54.3352508545],"type":"Point"}
}