{
  "type": "Feature",
  "properties": {
    "iso:country":"GB",
    "sg:address":"11 Worcester Road",
    "sg:city":"Crawley",
    "sg:classifiers":[
        {
            "category":"Parking",
            "type":"Transportation"
        }
    ],
    "sg:phone":"+44 1293 409384",
    "sg:postcode":"RH10 5JF",
    "sg:province":"Surrey",
    "sg:tags":[
        "car",
        "valet"
    ],
    "wof:name":"Groves Cleaning Co.",
    "wof:placetype":"venue"
},
  "geometry": {"coordinates":[-0.182482,51.097813],"type":"Point"}
}