{
  "type": "Feature",
  "properties": {
    "addr:full":"2 Transport Avenue, Great West Road Brentford Greater London TW8 9HF",
    "addr:housenumber":"2",
    "addr:postcode":"tw8 9hf",
    "addr:street":"Transport Avenue;West Road",
    "iso:country":"GB",
    "sg:address":"2 Transport Avenue, Great West Road",
    "sg:city":"Brentford",
    "sg:classifiers":[
        {
            "category":"Building & Trades",
            "subcategory":"Cleaning & Sanitation",
            "type":"Services"
        },
        {
            "category":"Professional",
            "subcategory":"Employment Agencies",
            "type":"Services"
        }
    ],
    "sg:postcode":"TW8 9HF",
    "sg:province":"Greater London",
    "sg:tags":[
        "asbestos",
        "mnfrs",
        "removal"
    ],
    "wof:name":"Asbestech Ltd.",
    "wof:placetype":"venue"
},
  "geometry": {"coordinates":[-0.323458,51.490559],"type":"Point"}
}