{
  "type": "Feature",
  "properties": {
    "addr:full":"51 High St Banstead Surrey SM7 2NL",
    "addr:housenumber":"51",
    "addr:postcode":"sm7 2nl",
    "addr:street":"High St",
    "iso:country":"GB",
    "sg:address":"51 High St",
    "sg:city":"Banstead",
    "sg:classifiers":[
        {
            "category":"Food & Beverages",
            "subcategory":"Fruits & Vegetables",
            "type":"Retail Goods"
        }
    ],
    "sg:postcode":"SM7 2NL",
    "sg:province":"Surrey",
    "sg:tags":[
        "greengrocer"
    ],
    "wof:name":"Bourne,S & J,",
    "wof:placetype":"venue"
},
  "geometry": {"coordinates":[-0.201846,51.322636],"type":"Point"}
}