{
  "type": "Feature",
  "properties": {
    "iso:country":"GB",
    "sg:address":"1 Rous Road",
    "sg:city":"Newmarket",
    "sg:classifiers":[
        {
            "category":"Professional",
            "subcategory":"Accounting & Tax Preparation",
            "type":"Services"
        }
    ],
    "sg:phone":"+44 1638 664275",
    "sg:postcode":"CB8 8DH",
    "sg:province":"Cambridgeshire",
    "sg:tags":[
        "accountant"
    ],
    "wof:name":"Moore & Co.",
    "wof:placetype":"venue"
},
  "geometry": {"coordinates":[0.408936,52.245148],"type":"Point"}
}