{
  "type": "Feature",
  "properties": {
    "addr:full":"18 Burrows Close, Lawford Manningtree Essex CO11 2HE",
    "addr:housenumber":"18",
    "addr:postcode":"co11 2he",
    "addr:street":"Burrows Close",
    "iso:country":"GB",
    "sg:address":"18 Burrows Close, Lawford",
    "sg:city":"Manningtree",
    "sg:classifiers":[
        {
            "category":"Organizations",
            "subcategory":"Non-profit Organization",
            "type":"Services"
        }
    ],
    "sg:phone":"+44 1206 391640",
    "sg:postcode":"CO11 2HE",
    "sg:province":"Essex",
    "sg:tags":[
        "charitable",
        "organisation",
        "voluntary",
        "charity"
    ],
    "wof:name":"NATIONAL BACK PAIN ASSOCIATION",
    "wof:placetype":"venue"
},
  "geometry": {"coordinates":[1.053055,51.94574],"type":"Point"}
}