{
  "type": "Feature",
  "properties": {
    "addr:full":"42 Tower Rd Lancing West Sussex BN15 9HT",
    "addr:housenumber":"42",
    "addr:postcode":"bn15 9ht",
    "addr:street":"Tower Rd",
    "iso:country":"GB",
    "sg:address":"42 Tower Rd",
    "sg:city":"Lancing",
    "sg:classifiers":[
        {
            "category":"Building & Trades",
            "subcategory":"Construction",
            "type":"Services"
        }
    ],
    "sg:phone":"+44 1903 751874",
    "sg:postcode":"BN15 9HT",
    "sg:province":"West Sussex",
    "sg:tags":[
        "guttering"
    ],
    "wof:name":"Best Choice",
    "wof:placetype":"venue"
},
  "geometry": {"coordinates":[-0.3292410076,50.8267936707],"type":"Point"}
}