{
  "type": "Feature",
  "properties": {
    "addr:full":"Town St Garage, Town Street, South Killingholme Grimsby Lincolnshire DN40 3EL",
    "addr:postcode":"dn40 3el",
    "addr:street":"Town;Town Street South",
    "iso:country":"GB",
    "sg:address":"Town St Garage, Town Street, South Killingholme",
    "sg:city":"Grimsby",
    "sg:classifiers":[
        {
            "category":"Retail",
            "subcategory":"Auto Repair",
            "type":"Services"
        }
    ],
    "sg:phone":"+44 1469 540311",
    "sg:postcode":"DN40 3EL",
    "sg:province":"Lincolnshire",
    "sg:tags":[
        "modification",
        "garage",
        "related"
    ],
    "wof:name":"Mike Johnson",
    "wof:placetype":"venue"
},
  "geometry": {"coordinates":[-0.269954,53.639706],"type":"Point"}
}