{
  "type": "Feature",
  "properties": {
    "iso:country":"GB",
    "sg:address":"69 Briggs Av",
    "sg:city":"Castleford",
    "sg:classifiers":[
        {
            "category":"Retail",
            "subcategory":"Driving School",
            "type":"Services"
        }
    ],
    "sg:phone":"+44 1977 550878",
    "sg:postcode":"WF10 5BD",
    "sg:province":"West Yorkshire",
    "wof:name":"Steve Holmes",
    "wof:placetype":"venue"
},
  "geometry": {"coordinates":[-1.3492530584,53.716884613],"type":"Point"}
}