{
  "type": "Feature",
  "properties": {
    "addr:full":"18 The Ridgeway Marlow Berkshire SL7 3LL",
    "addr:housenumber":"18",
    "addr:postcode":"sl7 3ll",
    "addr:street":"The Ridgeway",
    "iso:country":"GB",
    "sg:address":"18 The Ridgeway",
    "sg:city":"Marlow",
    "sg:classifiers":[
        {
            "category":"Manufacturing",
            "subcategory":"Building Materials",
            "type":"Manufacturing & Wholesale Goods"
        }
    ],
    "sg:phone":"+44 1628 481046",
    "sg:postcode":"SL7 3LL",
    "sg:province":"Berkshire",
    "sg:tags":[
        "tarmac",
        "asphalt"
    ],
    "wof:name":"P Fountain",
    "wof:placetype":"venue"
},
  "geometry": {"coordinates":[-0.768994987,51.5830841064],"type":"Point"}
}