{
  "type": "Feature",
  "properties": {
    "addr:full":"35 Highland Road Southsea Hampshire PO4 9DA",
    "addr:housenumber":"35",
    "addr:postcode":"po4 9da",
    "addr:street":"Highland Road",
    "iso:country":"GB",
    "sg:address":"35 Highland Road",
    "sg:city":"Southsea",
    "sg:classifiers":[
        {
            "category":"Shopping",
            "subcategory":"Used Merchandise",
            "type":"Retail Goods"
        }
    ],
    "sg:phone":"+44 23 9234 2266",
    "sg:postcode":"PO4 9DA",
    "sg:province":"Hampshire",
    "sg:tags":[
        "shop",
        "second-hand"
    ],
    "wof:name":"R Willis & Sons",
    "wof:placetype":"venue"
},
  "geometry": {"coordinates":[-1.069097,50.786144],"type":"Point"}
}