{
  "type": "Feature",
  "properties": {
    "addr:full":"Putteridge Road Luton Bedfordshire LU2 8HJ",
    "addr:postcode":"lu2 8hj",
    "addr:street":"Putteridge Road",
    "iso:country":"GB",
    "sg:address":"Putteridge Road",
    "sg:city":"Luton",
    "sg:classifiers":[
        {
            "category":"Education",
            "subcategory":"University",
            "type":"Public Place"
        }
    ],
    "sg:phone":"+44 1582 415591",
    "sg:postcode":"LU2 8HJ",
    "sg:province":"Bedfordshire",
    "sg:tags":[
        "adult"
    ],
    "wof:name":"Putteridge Community College Adult Education",
    "wof:placetype":"venue"
},
  "geometry": {"coordinates":[-0.3805640042,51.9051361084],"type":"Point"}
}