{
  "type": "Feature",
  "properties": {
    "addr:full":"44 Fore Street, Edmonton London Greater London N18 2SS",
    "addr:housenumber":"44",
    "addr:postcode":"n18 2ss",
    "addr:street":"Fore Street",
    "iso:country":"GB",
    "sg:address":"44 Fore Street, Edmonton",
    "sg:city":"London",
    "sg:classifiers":[
        {
            "category":"Retail",
            "subcategory":"Driving School",
            "type":"Services"
        }
    ],
    "sg:phone":"+44 20 8807 0811",
    "sg:postcode":"N18 2SS",
    "sg:province":"Greater London",
    "wof:name":"Gordons School of Motoring",
    "wof:placetype":"venue"
},
  "geometry": {"coordinates":[-0.066,51.609772],"type":"Point"}
}