{
  "type": "Feature",
  "properties": {
    "iso:country":"GB",
    "sg:address":"Blaencowin, Cynwyl Elfed",
    "sg:city":"Carmarthen",
    "sg:classifiers":[
        {
            "category":"Farming",
            "subcategory":"Livestock Farm",
            "type":"Manufacturing & Wholesale Goods"
        }
    ],
    "sg:phone":"+44 1994 484381",
    "sg:postcode":"SA33 6TE",
    "sg:province":"Carmarthenshire",
    "sg:tags":[
        "others"
    ],
    "wof:name":"W D Dyfan",
    "wof:placetype":"venue"
},
  "geometry": {"coordinates":[-4.45206,51.9557],"type":"Point"}
}