{
  "type": "Feature",
  "properties": {
    "iso:country":"GB",
    "sg:address":"2 Harbin Road",
    "sg:city":"Swadlincote",
    "sg:classifiers":[
        {
            "category":"Building & Trades",
            "subcategory":"Plumbing",
            "type":"Services"
        }
    ],
    "sg:phone":"+44 1283 716541",
    "sg:postcode":"DE12 8NG",
    "sg:province":"Derbyshire",
    "sg:tags":[
        "heating"
    ],
    "wof:name":"Chisnall Plumbing & Heating",
    "wof:placetype":"venue"
},
  "geometry": {"coordinates":[-1.676193,52.760281],"type":"Point"}
}