{
  "type": "Feature",
  "properties": {
    "addr:full":"92 Churchdale Road Eastbourne East Sussex BN22 8RX",
    "addr:housenumber":"92",
    "addr:postcode":"bn22 8rx",
    "addr:street":"Churchdale Road",
    "iso:country":"GB",
    "sg:address":"92 Churchdale Road",
    "sg:city":"Eastbourne",
    "sg:classifiers":[
        {
            "category":"Building & Trades",
            "subcategory":"Plumbing",
            "type":"Services"
        }
    ],
    "sg:phone":"+44 1323 729652",
    "sg:postcode":"BN22 8RX",
    "sg:province":"East Sussex",
    "sg:tags":[
        "heating"
    ],
    "wof:name":"Adrian Leach",
    "wof:placetype":"venue"
},
  "geometry": {"coordinates":[0.295155,50.785324],"type":"Point"}
}