{
  "type": "Feature",
  "properties": {
    "addr:full":"31 St Neots Rd, Eaton Ford Huntingdon Bedfordshire PE19 3BA",
    "addr:housenumber":"31",
    "addr:postcode":"pe19 3ba",
    "addr:street":"St Neots Rd",
    "iso:country":"GB",
    "sg:address":"31 St Neots Rd, Eaton Ford",
    "sg:city":"Huntingdon",
    "sg:classifiers":[
        {
            "category":"Professional",
            "subcategory":"Lawyer & Legal Services",
            "type":"Services"
        }
    ],
    "sg:phone":"+44 1480 406633",
    "sg:postcode":"PE19 3BA",
    "sg:province":"Bedfordshire",
    "sg:tags":[
        "solicitor"
    ],
    "wof:name":"Keyworth & Co",
    "wof:placetype":"venue"
},
  "geometry": {"coordinates":[-0.2824200094,52.2279510498],"type":"Point"}
}