{
  "type": "Feature",
  "properties": {
    "iso:country":"GB",
    "sg:address":"16 Tithe Close, Gazeley",
    "sg:city":"Newmarket",
    "sg:classifiers":[
        {
            "category":"Professional",
            "subcategory":"Employment Agencies",
            "type":"Services"
        }
    ],
    "sg:phone":"+44 1638 750827",
    "sg:postcode":"CB8 8RS",
    "sg:province":"Cambridgeshire",
    "sg:tags":[
        "consultant"
    ],
    "wof:name":"Backup Recruitment",
    "wof:placetype":"venue"
},
  "geometry": {"coordinates":[0.523575,52.248394],"type":"Point"}
}