{
  "type": "Feature",
  "properties": {
    "iso:country":"GB",
    "sg:address":"21 Perry Vale",
    "sg:city":"London",
    "sg:classifiers":[
        {
            "category":"Real Estate",
            "subcategory":"Real Estate Operator",
            "type":"Services"
        }
    ],
    "sg:phone":"+44 20 8291 9198",
    "sg:postcode":"SE23 2NE",
    "sg:province":"Greater London",
    "sg:tags":[
        "letting",
        "agent"
    ],
    "wof:name":"Leasing Direct Ltd.",
    "wof:placetype":"venue"
},
  "geometry": {"coordinates":[-0.052327,51.439255],"type":"Point"}
}