{
  "type": "Feature",
  "properties": {
    "iso:country":"GB",
    "sg:address":"Hereford Road, Mardy",
    "sg:city":"Abergavenny",
    "sg:classifiers":[
        {
            "category":"Bars & Pubs",
            "type":"Food & Drink"
        }
    ],
    "sg:phone":"+44 1873 852295",
    "sg:postcode":"NP7 5PR",
    "sg:province":"Herefordshire",
    "sg:tags":[
        "pubs",
        "inn"
    ],
    "wof:name":"Crown & Sceptre Inn",
    "wof:placetype":"venue"
},
  "geometry": {"coordinates":[-3.02068,51.825008],"type":"Point"}
}