{
  "type": "Feature",
  "properties": {
    "addr:full":"Dennil Road Leeds West Yorkshire LS15 8SD",
    "addr:postcode":"ls15 8sd",
    "addr:street":"Dennil Road",
    "iso:country":"GB",
    "sg:address":"Dennil Road",
    "sg:city":"Leeds",
    "sg:classifiers":[
        {
            "category":"Education",
            "subcategory":"School",
            "type":"Public Place"
        }
    ],
    "sg:phone":"+44 113 214 1311",
    "sg:postcode":"LS15 8SD",
    "sg:province":"West Yorkshire",
    "sg:tags":[
        "local",
        "authority"
    ],
    "wof:name":"Manston Primary School",
    "wof:placetype":"venue"
},
  "geometry": {"coordinates":[-1.4460339546,53.8143081665],"type":"Point"}
}