{
  "type": "Feature",
  "properties": {
    "addr:full":"23 Fontwell Clo Littlehampton West Sussex BN16 2LL",
    "addr:housenumber":"23",
    "addr:postcode":"bn16 2ll",
    "addr:street":"Fontwell Clo",
    "iso:country":"GB",
    "sg:address":"23 Fontwell Clo",
    "sg:city":"Littlehampton",
    "sg:classifiers":[
        {
            "category":"Shopping",
            "subcategory":"Florist",
            "type":"Retail Goods"
        }
    ],
    "sg:phone":"+44 1903 787863",
    "sg:postcode":"BN16 2LL",
    "sg:province":"West Sussex",
    "wof:name":"Russel's",
    "wof:placetype":"venue"
},
  "geometry": {"coordinates":[-0.513057,50.804852],"type":"Point"}
}