{
  "type": "Feature",
  "properties": {
    "addr:full":"138 South Street Romford Essex RM1 1TE",
    "addr:housenumber":"138",
    "addr:postcode":"rm1 1te",
    "addr:street":"South Street",
    "iso:country":"GB",
    "sg:address":"138 South Street",
    "sg:city":"Romford",
    "sg:classifiers":[
        {
            "category":"Cafe",
            "type":"Food & Drink"
        }
    ],
    "sg:postcode":"RM1 1TE",
    "sg:province":"Essex",
    "sg:tags":[
        "tea",
        "room"
    ],
    "wof:name":"Cafe K",
    "wof:placetype":"venue"
},
  "geometry": {"coordinates":[0.183347,51.574894],"type":"Point"}
}