{
  "type": "Feature",
  "properties": {
    "addr:full":"Morris Square, Wolstanton Newcastle Staffordshire ST5 0EN",
    "addr:postcode":"st5 0en",
    "addr:street":"Morris Square",
    "iso:country":"GB",
    "sg:address":"Morris Square, Wolstanton",
    "sg:city":"Newcastle",
    "sg:classifiers":[
        {
            "category":"Food & Beverages",
            "subcategory":"Supermarket",
            "type":"Retail Goods"
        }
    ],
    "sg:phone":"+44 1782 632928",
    "sg:postcode":"ST5 0EN",
    "sg:province":"Staffordshire",
    "wof:name":"Kwik Save Foodstores",
    "wof:placetype":"venue"
},
  "geometry": {"coordinates":[-2.2156200409,53.031124115],"type":"Point"}
}