{
  "type": "Feature",
  "properties": {
    "iso:country":"GB",
    "sg:address":"Bakewell Rd",
    "sg:city":"Matlock",
    "sg:classifiers":[
        {
            "category":"Cafe",
            "type":"Food & Drink"
        }
    ],
    "sg:postcode":"DE4 2QJ",
    "sg:province":"Derbyshire",
    "sg:tags":[
        "tea",
        "room"
    ],
    "wof:name":"Sunflower Coffee Shop",
    "wof:placetype":"venue"
},
  "geometry": {"coordinates":[-1.5751689672,53.1499137878],"type":"Point"}
}