{
  "type": "Feature",
  "properties": {
    "iso:country":"GB",
    "sg:address":"37 Shaftesbury Parade, Shaftesbury Avenue, South Harrow",
    "sg:city":"Harrow",
    "sg:classifiers":[
        {
            "category":"Government",
            "subcategory":"Post Office",
            "type":"Public Place"
        }
    ],
    "sg:phone":"+44 20 8422 1554",
    "sg:postcode":"HA2 0AH",
    "sg:province":"Greater London",
    "wof:name":"Shaftesbury Avenue Sub Post Office",
    "wof:placetype":"venue"
},
  "geometry": {"coordinates":[-0.3538900018,51.5716590881],"type":"Point"}
}