{
  "type": "Feature",
  "properties": {
    "iso:country":"GB",
    "sg:address":"Badgers, Warren Lane, Cross In Hand",
    "sg:city":"Heathfield",
    "sg:classifiers":[
        {
            "category":"Professional",
            "subcategory":"Accounting & Tax Preparation",
            "type":"Services"
        }
    ],
    "sg:postcode":"TN21 0TB",
    "sg:province":"East Sussex",
    "sg:tags":[
        "accountant"
    ],
    "wof:name":"Dixon & Co",
    "wof:placetype":"venue"
},
  "geometry": {"coordinates":[0.225756,50.973572],"type":"Point"}
}