{
  "type": "Feature",
  "properties": {
    "addr:full":"Rear Of 367-369 Bentley Road Doncaster South Yorkshire DN5 9TJ",
    "addr:postcode":"367-369;dn5 9tj",
    "addr:street":"Bentley Road",
    "iso:country":"GB",
    "sg:address":"Rear Of 367-369 Bentley Road",
    "sg:city":"Doncaster",
    "sg:classifiers":[
        {
            "category":"Professional",
            "subcategory":"Printing & Photocopies",
            "type":"Services"
        }
    ],
    "sg:phone":"+44 1302 788791",
    "sg:postcode":"DN5 9TJ",
    "sg:province":"South Yorkshire",
    "sg:tags":[
        "printer"
    ],
    "wof:name":"GRADY'S PRINTERS LTD",
    "wof:placetype":"venue"
},
  "geometry": {"coordinates":[-1.1486400366,53.5398292542],"type":"Point"}
}