{
  "type": "Feature",
  "properties": {
    "iso:country":"GB",
    "sg:address":"Brooklyn Ho, North St, Langley Mill",
    "sg:city":"Nottingham",
    "sg:classifiers":[
        {
            "category":"Manufacturing",
            "subcategory":"Textiles",
            "type":"Manufacturing & Wholesale Goods"
        }
    ],
    "sg:postcode":"NG16 4BS",
    "sg:province":"Derbyshire",
    "sg:tags":[
        "made-up"
    ],
    "wof:name":"Steeples,J,",
    "wof:placetype":"venue"
},
  "geometry": {"coordinates":[-1.3343889713,53.0182189941],"type":"Point"}
}