{
  "type": "Feature",
  "properties": {
    "addr:full":"Browning Farm, Blackboys Uckfield East Sussex TN22 5HG",
    "addr:postcode":"tn22 5hg",
    "addr:street":"Blackboys",
    "iso:country":"GB",
    "sg:address":"Browning Farm, Blackboys",
    "sg:city":"Uckfield",
    "sg:classifiers":[
        {
            "category":"Organizations",
            "subcategory":"Non-profit Organization",
            "type":"Services"
        }
    ],
    "sg:phone":"+44 1825 890975",
    "sg:postcode":"TN22 5HG",
    "sg:province":"East Sussex",
    "sg:tags":[
        "organisation",
        "voluntary",
        "charity"
    ],
    "wof:name":"Council for the Protection of Rural England-Sussex",
    "wof:placetype":"venue"
},
  "geometry": {"coordinates":[0.1707649976,50.9645614624],"type":"Point"}
}