{
  "type": "Feature",
  "properties": {
    "iso:country":"GB",
    "sg:address":"50-54 Cross Brook Street, Cheshunt",
    "sg:city":"Waltham Cross",
    "sg:classifiers":[
        {
            "category":"Professional",
            "subcategory":"Employment Agencies",
            "type":"Services"
        },
        {
            "category":"Autos & Motor Vehicles",
            "subcategory":"Motorcycle Sales",
            "type":"Retail Goods"
        }
    ],
    "sg:phone":"+44 1992 625173",
    "sg:postcode":"EN8 8JQ",
    "sg:province":"Essex",
    "sg:tags":[
        "consultant"
    ],
    "wof:name":"Waltham Cross Motor Cycles Ltd.",
    "wof:placetype":"venue"
},
  "geometry": {"coordinates":[-0.034377,51.694317],"type":"Point"}
}