{
  "type": "Feature",
  "properties": {
    "addr:full":"40 Dryleaze Road Bristol City of Bristol BS16 1HL",
    "addr:housenumber":"40",
    "addr:postcode":"bs16 1hl",
    "addr:street":"Dryleaze Road",
    "iso:country":"GB",
    "sg:address":"40 Dryleaze Road",
    "sg:city":"Bristol",
    "sg:classifiers":[
        {
            "category":"Building & Trades",
            "subcategory":"Construction",
            "type":"Services"
        }
    ],
    "sg:postcode":"BS16 1HL",
    "sg:province":"City of Bristol",
    "sg:tags":[
        "dry",
        "lining",
        "plasterers",
        "screeders"
    ],
    "wof:name":"Steve Westlake Plastering",
    "wof:placetype":"venue"
},
  "geometry": {"coordinates":[-2.5370600224,51.4884605408],"type":"Point"}
}