{
  "type": "Feature",
  "properties": {
    "addr:full":"Yarde Pl Taunton Somerset TA1 1UR",
    "addr:postcode":"ta1 1ur",
    "addr:street":"Yarde Pl",
    "iso:country":"GB",
    "sg:address":"Yarde Pl",
    "sg:city":"Taunton",
    "sg:classifiers":[
        {
            "category":"Shopping",
            "subcategory":"Bicycles & Sporting Goods",
            "type":"Retail Goods"
        }
    ],
    "sg:phone":"+44 1823 327006",
    "sg:postcode":"TA1 1UR",
    "sg:province":"Somerset",
    "sg:tags":[
        "cycle",
        "accessory"
    ],
    "wof:name":"Bikes Own",
    "wof:placetype":"venue"
},
  "geometry": {"coordinates":[-3.106719,51.018929],"type":"Point"}
}