{
  "type": "Feature",
  "properties": {
    "iso:country":"GB",
    "sg:address":"8 Standard Road",
    "sg:city":"London",
    "sg:classifiers":[
        {
            "category":"Professional",
            "type":"Services"
        }
    ],
    "sg:phone":"+44 20 8961 3083",
    "sg:postcode":"NW10 6EU",
    "sg:province":"Greater London",
    "sg:tags":[
        "caterer"
    ],
    "wof:name":"The Deli",
    "wof:placetype":"venue"
},
  "geometry": {"coordinates":[-0.260088,51.528625],"type":"Point"}
}