{
  "type": "Feature",
  "properties": {
    "addr:full":"Indent Dental Practice, Health Centre, Main Rd Nottingham Nottinghamshire NG12 2GD",
    "addr:postcode":"ng12 2gd",
    "addr:street":"Main Rd",
    "iso:country":"GB",
    "sg:address":"Indent Dental Practice, Health Centre, Main Rd",
    "sg:city":"Nottingham",
    "sg:classifiers":[
        {
            "category":"Health Services",
            "subcategory":"Dentist",
            "type":"Services"
        }
    ],
    "sg:phone":"+44 115 933 3181",
    "sg:postcode":"NG12 2GD",
    "sg:province":"Nottinghamshire",
    "wof:name":"S A Andrews",
    "wof:placetype":"venue"
},
  "geometry": {"coordinates":[-1.1439239979,52.9492263794],"type":"Point"}
}