{
  "type": "Feature",
  "properties": {
    "iso:country":"GB",
    "sg:address":"20 Gordon Dr",
    "sg:city":"Chertsey",
    "sg:classifiers":[
        {
            "category":"Professional",
            "subcategory":"Management & Consulting",
            "type":"Services"
        }
    ],
    "sg:postcode":"KT16 9PP",
    "sg:province":"Surrey",
    "sg:tags":[
        "consultant",
        "business"
    ],
    "wof:name":"Sharkey,Mike,",
    "wof:placetype":"venue"
},
  "geometry": {"coordinates":[-0.516792,51.378307],"type":"Point"}
}