{
  "type": "Feature",
  "properties": {
    "iso:country":"GB",
    "sg:address":"St Marys Plain",
    "sg:city":"Norwich",
    "sg:classifiers":[
        {
            "category":"Professional",
            "subcategory":"Printing & Photocopies",
            "type":"Services"
        }
    ],
    "sg:phone":"+44 1603 625569",
    "sg:postcode":"NR3 3AF",
    "sg:province":"Norfolk",
    "sg:tags":[
        "engraving"
    ],
    "wof:name":"Apex Engraving Plus",
    "wof:placetype":"venue"
},
  "geometry": {"coordinates":[1.290784,52.63401],"type":"Point"}
}