{
  "type": "Feature",
  "properties": {
    "addr:full":"11 Faraday Avenue Birmingham West Midlands B32 1JP",
    "addr:housenumber":"11",
    "addr:postcode":"b32 1jp",
    "addr:street":"Faraday Avenue",
    "iso:country":"GB",
    "sg:address":"11 Faraday Avenue",
    "sg:city":"Birmingham",
    "sg:classifiers":[
        {
            "category":"Shopping",
            "subcategory":"Crafts & Fabrics",
            "type":"Retail Goods"
        }
    ],
    "sg:phone":"+44 121 423 2969",
    "sg:postcode":"B32 1JP",
    "sg:province":"West Midlands",
    "sg:tags":[
        "shop",
        "needlecraft",
        "wool"
    ],
    "wof:name":"Somal Fashions",
    "wof:placetype":"venue"
},
  "geometry": {"coordinates":[-1.991776,52.456779],"type":"Point"}
}