{
  "type": "Feature",
  "properties": {
    "addr:full":"West Park, Arlington Barnstaple Devon EX31 4SN",
    "addr:postcode":"ex31 4sn",
    "iso:country":"GB",
    "sg:address":"West Park, Arlington",
    "sg:city":"Barnstaple",
    "sg:classifiers":[
        {
            "category":"Military Area",
            "subcategory":"Naval Base",
            "type":"Public Place"
        },
        {
            "category":"Retail",
            "subcategory":"Auto Repair",
            "type":"Services"
        },
        {
            "category":"Retail",
            "subcategory":"Animal Services",
            "type":"Services"
        }
    ],
    "sg:phone":"+44 1271 850860",
    "sg:postcode":"EX31 4SN",
    "sg:province":"Devon",
    "sg:tags":[
        "box",
        "horse",
        "transportation",
        "equine",
        "repairer",
        "bodybuilder",
        "transporting"
    ],
    "wof:name":"J H Commercials",
    "wof:placetype":"venue"
},
  "geometry": {"coordinates":[-3.982579,51.148766],"type":"Point"}
}