{
  "type": "Feature",
  "properties": {
    "addr:full":"5 Mount Harry Road Lewes East Sussex BN7 1NS",
    "addr:housenumber":"5",
    "addr:postcode":"bn7 1ns",
    "addr:street":"Mount Harry Road",
    "iso:country":"GB",
    "sg:address":"5 Mount Harry Road",
    "sg:city":"Lewes",
    "sg:classifiers":[
        {
            "category":"Shopping",
            "subcategory":"News",
            "type":"Retail Goods"
        }
    ],
    "sg:phone":"+44 1273 474899",
    "sg:postcode":"BN7 1NS",
    "sg:province":"East Sussex",
    "sg:tags":[
        "newsagent"
    ],
    "wof:name":"Nevill Newsagents",
    "wof:placetype":"venue"
},
  "geometry": {"coordinates":[-0.0086859995,50.8793144226],"type":"Point"}
}