{
  "type": "Feature",
  "properties": {
    "iso:country":"GB",
    "sg:address":"131 High Lane, Burslem",
    "sg:city":"Stoke-on-trent",
    "sg:classifiers":[
        {
            "category":"Autos & Motor Vehicles",
            "subcategory":"Auto Supplies",
            "type":"Retail Goods"
        }
    ],
    "sg:phone":"+44 1782 834838",
    "sg:postcode":"ST6 7BS",
    "sg:province":"Staffordshire",
    "sg:tags":[
        "component"
    ],
    "wof:name":"Chappells",
    "wof:placetype":"venue"
},
  "geometry": {"coordinates":[-2.183856,53.051395],"type":"Point"}
}