{
  "type": "Feature",
  "properties": {
    "addr:full":"194 Charminster Road Bournemouth Dorset BH8 9RL",
    "addr:housenumber":"194",
    "addr:postcode":"bh8 9rl",
    "addr:street":"Charminster Road",
    "iso:country":"GB",
    "sg:address":"194 Charminster Road",
    "sg:city":"Bournemouth",
    "sg:classifiers":[
        {
            "category":"Organizations",
            "subcategory":"Membership Organization",
            "type":"Services"
        }
    ],
    "sg:phone":"+44 1202 240890",
    "sg:postcode":"BH8 9RL",
    "sg:province":"Dorset",
    "sg:tags":[
        "club",
        "social"
    ],
    "wof:name":"Richmond Park Conservative Club",
    "wof:placetype":"venue"
},
  "geometry": {"coordinates":[-1.8641309738,50.7373428345],"type":"Point"}
}