{
  "type": "Feature",
  "properties": {
    "addr:full":"15 The Broadway Newbury Berkshire RG14 1AS",
    "addr:housenumber":"15",
    "addr:postcode":"rg14 1as",
    "addr:street":"The Broadway",
    "iso:country":"GB",
    "sg:address":"15 The Broadway",
    "sg:city":"Newbury",
    "sg:classifiers":[
        {
            "category":"Bars & Pubs",
            "type":"Food & Drink"
        },
        {
            "category":"Community Center",
            "subcategory":"Social",
            "type":"Public Place"
        }
    ],
    "sg:phone":"+44 1635 43915",
    "sg:postcode":"RG14 1AS",
    "sg:province":"Berkshire",
    "sg:tags":[
        "pubs",
        "house",
        "inn",
        "activity"
    ],
    "wof:name":"Clock Tower Inn",
    "wof:placetype":"venue"
},
  "geometry": {"coordinates":[-1.3245639801,51.4022979736],"type":"Point"}
}