{
  "type": "Feature",
  "properties": {
    "iso:country":"GB",
    "sg:address":"5a Factory La",
    "sg:city":"Nottingham",
    "sg:classifiers":[
        {
            "category":"Building & Trades",
            "subcategory":"Construction",
            "type":"Services"
        }
    ],
    "sg:phone":"+44 115 922 1747",
    "sg:postcode":"NG9 4AA",
    "sg:province":"Nottinghamshire",
    "sg:tags":[
        "decorator",
        "painter"
    ],
    "wof:name":"Comro Services Ltd",
    "wof:placetype":"venue"
},
  "geometry": {"coordinates":[-1.221282,52.921631],"type":"Point"}
}