{
  "type": "Feature",
  "properties": {
    "iso:country":"GB",
    "sg:address":"King Street Surgery, 273 Bedford Rd",
    "sg:city":"Bedford",
    "sg:classifiers":[
        {
            "category":"Health Services",
            "subcategory":"Doctor",
            "type":"Services"
        }
    ],
    "sg:phone":"+44 1234 852222",
    "sg:postcode":"MK42 8QD",
    "sg:province":"Bedfordshire",
    "sg:tags":[
        "practitioners"
    ],
    "wof:name":"Farhoud, J S L",
    "wof:placetype":"venue"
},
  "geometry": {"coordinates":[-0.4953,52.118679],"type":"Point"}
}