{
  "type": "Feature",
  "properties": {
    "iso:country":"GB",
    "sg:address":"28 Manor Court, Monument Hill",
    "sg:city":"Weybridge",
    "sg:classifiers":[
        {
            "category":"Health Services",
            "subcategory":"Nursing And Care Facility",
            "type":"Services"
        }
    ],
    "sg:phone":"+44 1932 840495",
    "sg:postcode":"KT13 8RG",
    "sg:province":"Surrey",
    "sg:tags":[
        "home"
    ],
    "wof:name":"British Airways Staff Housing Society Ltd",
    "wof:placetype":"venue"
},
  "geometry": {"coordinates":[-0.4516119957,51.3728485107],"type":"Point"}
}