{
  "type": "Feature",
  "properties": {
    "addr:full":"Eaden House 34 Heskin Lane, Ormskirk Lancaster Lancashire L39 1LR",
    "addr:housenumber":"34",
    "addr:postcode":"l39 1lr",
    "addr:street":"Heskin Lane",
    "iso:country":"GB",
    "sg:address":"Eaden House 34 Heskin Lane, Ormskirk",
    "sg:city":"Lancaster",
    "sg:classifiers":[
        {
            "category":"Professional",
            "subcategory":"Engineering",
            "type":"Services"
        }
    ],
    "sg:phone":"+44 1695 574648",
    "sg:postcode":"L39 1LR",
    "sg:province":"Lancashire",
    "sg:tags":[
        "precision",
        "engineer"
    ],
    "wof:name":"Augmenta Group Ltd.",
    "wof:placetype":"venue"
},
  "geometry": {"coordinates":[-2.8934209347,53.5793266296],"type":"Point"}
}