{
  "type": "Feature",
  "properties": {
    "addr:full":"East Trumperton Farm, Letham Forfar Angus DD8 2PA",
    "addr:postcode":"dd8 2pa",
    "addr:street":"East",
    "iso:country":"GB",
    "sg:address":"East Trumperton Farm, Letham",
    "sg:city":"Forfar",
    "sg:classifiers":[
        {
            "category":"Fast Food",
            "type":"Food & Drink"
        },
        {
            "category":"Cafe",
            "type":"Food & Drink"
        }
    ],
    "sg:phone":"+44 1307 818325",
    "sg:postcode":"DD8 2PA",
    "sg:province":"Angus",
    "sg:tags":[
        "tea",
        "away",
        "room",
        "take"
    ],
    "wof:name":"Trumperton Forge Tearoom",
    "wof:placetype":"venue"
},
  "geometry": {"coordinates":[-2.7691690922,56.6276359558],"type":"Point"}
}