{
  "type": "Feature",
  "properties": {
    "addr:full":"52 Bury Old Rd Manchester Lancashire M45 6TL",
    "addr:housenumber":"52",
    "addr:postcode":"m45 6tl",
    "addr:street":"Bury Old Rd",
    "iso:country":"GB",
    "sg:address":"52 Bury Old Rd",
    "sg:city":"Manchester",
    "sg:classifiers":[
        {
            "category":"Professional",
            "subcategory":"Printing & Photocopies",
            "type":"Services"
        }
    ],
    "sg:postcode":"M45 6TL",
    "sg:province":"Lancashire",
    "sg:tags":[
        "printer"
    ],
    "wof:name":"Brown,Peter,",
    "wof:placetype":"venue"
},
  "geometry": {"coordinates":[-2.282888,53.539928],"type":"Point"}
}