{
  "type": "Feature",
  "properties": {
    "addr:full":"3 Blisworth Way, Swanwick Alfreton Derbyshire DE55 1EH",
    "addr:housenumber":"3",
    "addr:postcode":"de55 1eh",
    "addr:street":"Blisworth Way",
    "iso:country":"GB",
    "sg:address":"3 Blisworth Way, Swanwick",
    "sg:city":"Alfreton",
    "sg:classifiers":[
        {
            "category":"Building & Trades",
            "subcategory":"Landscaping Services",
            "type":"Services"
        }
    ],
    "sg:phone":"+44 1773 607735",
    "sg:postcode":"DE55 1EH",
    "sg:province":"Derbyshire",
    "sg:tags":[
        "gardening"
    ],
    "wof:name":"Alpha Garden Services",
    "wof:placetype":"venue"
},
  "geometry": {"coordinates":[-1.3913240433,53.0777359009],"type":"Point"}
}