{
  "type": "Feature",
  "properties": {
    "addr:full":"135 The Esplanade, Strand Shopping Centre Bootle Merseyside L20 4SP",
    "addr:housenumber":"135",
    "addr:postcode":"l20 4sp",
    "addr:street":"The Esplanade Strand Shopping",
    "iso:country":"GB",
    "sg:address":"135 The Esplanade, Strand Shopping Centre",
    "sg:city":"Bootle",
    "sg:classifiers":[
        {
            "category":"Shopping",
            "subcategory":"Clothing, Apparel, & Fashions",
            "type":"Retail Goods"
        }
    ],
    "sg:phone":"+44 151 922 1127",
    "sg:postcode":"L20 4SP",
    "sg:province":"Merseyside",
    "sg:tags":[
        "ladieswear"
    ],
    "wof:name":"Bon Marche Ltd.",
    "wof:placetype":"venue"
},
  "geometry": {"coordinates":[-2.9920499325,53.4516601562],"type":"Point"}
}