{
  "type": "Feature",
  "properties": {
    "iso:country":"GB",
    "sg:address":"Room 325 Concorde House, London Gatwick Airport",
    "sg:city":"Gatwick",
    "sg:classifiers":[
        {
            "category":"Airline",
            "type":"Transportation"
        }
    ],
    "sg:phone":"+44 1293 568748",
    "sg:postcode":"RH6 0DW",
    "sg:province":"Surrey",
    "sg:tags":[
        "rental",
        "charter",
        "leasing",
        "aircraft"
    ],
    "wof:name":"Goldcrest International",
    "wof:placetype":"venue"
},
  "geometry": {"coordinates":[-0.177139,51.166695],"type":"Point"}
}