{
  "type": "Feature",
  "properties": {
    "iso:country":"GB",
    "sg:address":"27 King Arthurs Drive, Strood",
    "sg:city":"Rochester",
    "sg:classifiers":[
        {
            "category":"Manufacturing",
            "subcategory":"Signs",
            "type":"Manufacturing & Wholesale Goods"
        }
    ],
    "sg:postcode":"ME2 3NA",
    "sg:province":"Kent",
    "sg:tags":[
        "poster",
        "writer"
    ],
    "wof:name":"Leo Graphics",
    "wof:placetype":"venue"
},
  "geometry": {"coordinates":[0.489732,51.4053],"type":"Point"}
}