{
  "type": "Feature",
  "properties": {
    "iso:country":"GB",
    "sg:address":"19 West St",
    "sg:city":"Swadlincote",
    "sg:classifiers":[
        {
            "category":"Food & Beverages",
            "subcategory":"Meat & Fish",
            "type":"Retail Goods"
        }
    ],
    "sg:phone":"+44 1283 217164",
    "sg:postcode":"DE11 9DG",
    "sg:province":"Derbyshire",
    "sg:tags":[
        "chip"
    ],
    "wof:name":"Andys Fish Bar",
    "wof:placetype":"venue"
},
  "geometry": {"coordinates":[-1.5585410595,52.7708015442],"type":"Point"}
}