{
  "type": "Feature",
  "properties": {
    "addr:full":"Holland House, 1-4 Bury Street London Greater London EC3A 5AT",
    "addr:housenumber":"1-4",
    "addr:postcode":"ec3a 5at",
    "addr:street":"Bury Street",
    "iso:country":"GB",
    "sg:address":"Holland House, 1-4 Bury Street",
    "sg:city":"London",
    "sg:classifiers":[
        {
            "category":"Professional",
            "subcategory":"Detective & Security Services",
            "type":"Services"
        }
    ],
    "sg:phone":"+44 20 7626 7877",
    "sg:postcode":"EC3A 5AT",
    "sg:province":"Greater London",
    "sg:tags":[
        "underwriter"
    ],
    "wof:name":"Morgan Feniman & Barber",
    "wof:placetype":"venue"
},
  "geometry": {"coordinates":[-0.0798709989,51.5141220093],"type":"Point"}
}