{
  "type": "Feature",
  "properties": {
    "addr:full":"Moor Farm, Eardiston Tenbury Wells Herefordshire WR15 8JJ",
    "addr:housenumber":"eardiston",
    "addr:postcode":"wr15 8jj",
    "iso:country":"GB",
    "sg:address":"Moor Farm, Eardiston",
    "sg:city":"Tenbury Wells",
    "sg:classifiers":[
        {
            "category":"Farming",
            "subcategory":"Farm",
            "type":"Manufacturing & Wholesale Goods"
        }
    ],
    "sg:postcode":"WR15 8JJ",
    "sg:province":"Herefordshire",
    "sg:tags":[
        "mixed",
        "crop"
    ],
    "wof:name":"Anthony B Sanderson",
    "wof:placetype":"venue"
},
  "geometry": {"coordinates":[-2.594178915,52.3125839233],"type":"Point"}
}