{
  "type": "Feature",
  "properties": {
    "addr:full":"25 Market Place Arbroath Angus DD11 1HR",
    "addr:housenumber":"25",
    "addr:postcode":"dd11 1hr",
    "addr:street":"Market Place",
    "iso:country":"GB",
    "sg:address":"25 Market Place",
    "sg:city":"Arbroath",
    "sg:classifiers":[
        {
            "category":"Shopping",
            "subcategory":"Florist",
            "type":"Retail Goods"
        }
    ],
    "sg:phone":"+44 1241 872210",
    "sg:postcode":"DD11 1HR",
    "sg:province":"Angus",
    "wof:name":"Ferriers",
    "wof:placetype":"venue"
},
  "geometry": {"coordinates":[-2.5829119682,56.5587806702],"type":"Point"}
}