{
  "type": "Feature",
  "properties": {
    "addr:full":"952 Eastern Avenue Ilford Essex IG2 7JD",
    "addr:housenumber":"952",
    "addr:postcode":"ig2 7jd",
    "addr:street":"Eastern Avenue",
    "iso:country":"GB",
    "sg:address":"952 Eastern Avenue",
    "sg:city":"Ilford",
    "sg:classifiers":[
        {
            "category":"Sports & Exercise",
            "subcategory":"Tennis Court",
            "type":"Entertainment"
        }
    ],
    "sg:phone":"+44 20 8983 8587",
    "sg:postcode":"IG2 7JD",
    "sg:province":"Essex",
    "sg:tags":[
        "breakdown",
        "recovery"
    ],
    "wof:name":"Advanced Recovery",
    "wof:placetype":"venue"
},
  "geometry": {"coordinates":[0.098437,51.577229],"type":"Point"}
}