{
  "type": "Feature",
  "properties": {
    "addr:full":"35 Winterbourne Rd Chichester West Sussex PO19 4PA",
    "addr:housenumber":"35",
    "addr:postcode":"po19 4pa",
    "addr:street":"Winterbourne Rd",
    "iso:country":"GB",
    "sg:address":"35 Winterbourne Rd",
    "sg:city":"Chichester",
    "sg:classifiers":[
        {
            "category":"Professional",
            "subcategory":"Computer Services",
            "type":"Services"
        }
    ],
    "sg:phone":"+44 1243 539461",
    "sg:postcode":"PO19 4PA",
    "sg:province":"West Sussex",
    "sg:tags":[
        "consultant"
    ],
    "wof:name":"J C A Ltd",
    "wof:placetype":"venue"
},
  "geometry": {"coordinates":[-0.774736,50.852821],"type":"Point"}
}