{
  "type": "Feature",
  "properties": {
    "iso:country":"GB",
    "sg:address":"63-65 Poulton Street, Kirkham",
    "sg:city":"Preston",
    "sg:classifiers":[
        {
            "category":"Shopping",
            "subcategory":"Gifts & Souvenirs",
            "type":"Retail Goods"
        }
    ],
    "sg:phone":"+44 1772 683547",
    "sg:postcode":"PR4 2AJ",
    "sg:province":"Lancashire",
    "sg:tags":[
        "shop"
    ],
    "wof:name":"Doreen Walsh",
    "wof:placetype":"venue"
},
  "geometry": {"coordinates":[-2.873945,53.782127],"type":"Point"}
}