{
  "type": "Feature",
  "properties": {
    "iso:country":"GB",
    "sg:address":"4 Wootton Road",
    "sg:city":"Bristol",
    "sg:classifiers":[
        {
            "category":"Shopping",
            "subcategory":"Department Store",
            "type":"Retail Goods"
        }
    ],
    "sg:postcode":"BS4 4AL",
    "sg:province":"City of Bristol",
    "wof:name":"Tony's",
    "wof:placetype":"venue"
},
  "geometry": {"coordinates":[-2.545592,51.453693],"type":"Point"}
}