{
  "type": "Feature",
  "properties": {
    "addr:full":"Pentwyn Farm, Pentwyn Pontypool Monmouthshire NP4 7TJ",
    "addr:postcode":"np4 7tj",
    "iso:country":"GB",
    "sg:address":"Pentwyn Farm, Pentwyn",
    "sg:city":"Pontypool",
    "sg:classifiers":[
        {
            "category":"Building & Trades",
            "subcategory":"Landscaping Services",
            "type":"Services"
        }
    ],
    "sg:phone":"+44 1495 774843",
    "sg:postcode":"NP4 7TJ",
    "sg:province":"Monmouthshire",
    "sg:tags":[
        "landscape",
        "contractor"
    ],
    "wof:name":"M P Landscape Fencing & Maintenance Contractor",
    "wof:placetype":"venue"
},
  "geometry": {"coordinates":[-3.064951,51.717751],"type":"Point"}
}