{
  "type": "Feature",
  "properties": {
    "iso:country":"GB",
    "sg:address":"2 Roden Gro, Wem",
    "sg:city":"Shrewsbury",
    "sg:classifiers":[
        {
            "category":"Building & Trades",
            "subcategory":"Construction",
            "type":"Services"
        }
    ],
    "sg:phone":"+44 1939 233454",
    "sg:postcode":"SY4 5HG",
    "sg:province":"Shropshire",
    "sg:tags":[
        "builder"
    ],
    "wof:name":"K & T Dodington Builders",
    "wof:placetype":"venue"
},
  "geometry": {"coordinates":[-2.727552,52.851715],"type":"Point"}
}