{
  "type": "Feature",
  "properties": {
    "addr:full":"287 Finchley Rd Hampstead Greater London NW3 6ND",
    "addr:housenumber":"287",
    "addr:postcode":"nw3 6nd",
    "addr:street":"Finchley Rd",
    "iso:country":"GB",
    "sg:address":"287 Finchley Rd",
    "sg:city":"Hampstead",
    "sg:classifiers":[
        {
            "category":"Professional",
            "subcategory":"Printing & Photocopies",
            "type":"Services"
        }
    ],
    "sg:phone":"+44 20 7724 5552",
    "sg:postcode":"NW3 6ND",
    "sg:province":"Greater London",
    "sg:tags":[
        "printer"
    ],
    "wof:name":"Printing Works",
    "wof:placetype":"venue"
},
  "geometry": {"coordinates":[-0.181673,51.549355],"type":"Point"}
}