{
  "type": "Feature",
  "properties": {
    "iso:country":"GB",
    "sg:address":"77 Clarkston Rd",
    "sg:city":"Glasgow",
    "sg:classifiers":[
        {
            "category":"Shopping",
            "subcategory":"Computers & Home Electronics",
            "type":"Retail Goods"
        }
    ],
    "sg:phone":"+44 141 633 0200",
    "sg:postcode":"G44 3BQ",
    "sg:province":"East Renfrewshire",
    "sg:tags":[
        "electrical"
    ],
    "wof:name":"Surelite UK",
    "wof:placetype":"venue"
},
  "geometry": {"coordinates":[-4.263257,55.816113],"type":"Point"}
}