{
  "type": "Feature",
  "properties": {
    "addr:full":"Park Barns, Ruleholme Carlisle Cumbria CA6 4NQ",
    "addr:postcode":"ca6 4nq",
    "addr:street":"Park;Ruleholme",
    "iso:country":"GB",
    "sg:address":"Park Barns, Ruleholme",
    "sg:city":"Carlisle",
    "sg:classifiers":[
        {
            "category":"Home & Garden",
            "subcategory":"Home Furnishings",
            "type":"Retail Goods"
        }
    ],
    "sg:phone":"+44 16977 41988",
    "sg:postcode":"CA6 4NQ",
    "sg:province":"Cumbria",
    "sg:tags":[
        "furnishers",
        "planner",
        "kitchen"
    ],
    "wof:name":"Richard Budniak",
    "wof:placetype":"venue"
},
  "geometry": {"coordinates":[-2.823059,54.93158],"type":"Point"}
}