{
  "type": "Feature",
  "properties": {
    "addr:full":"17 The Observatory, High St Slough Berkshire SL1 1LE",
    "addr:housenumber":"17",
    "addr:postcode":"sl1 1le",
    "addr:street":"The;High St",
    "iso:country":"GB",
    "sg:address":"17 The Observatory, High St",
    "sg:city":"Slough",
    "sg:classifiers":[
        {
            "category":"Shopping",
            "subcategory":"Clothing, Apparel, & Fashions",
            "type":"Retail Goods"
        }
    ],
    "sg:phone":"+44 1753 511766",
    "sg:postcode":"SL1 1LE",
    "sg:province":"Berkshire",
    "sg:tags":[
        "shop"
    ],
    "wof:name":"Chets",
    "wof:placetype":"venue"
},
  "geometry": {"coordinates":[-0.596417,51.507874],"type":"Point"}
}