{
  "type": "Feature",
  "properties": {
    "iso:country":"GB",
    "sg:address":"11 Station Road North",
    "sg:city":"Egham",
    "sg:classifiers":[
        {
            "category":"Shopping",
            "subcategory":"Shoes",
            "type":"Retail Goods"
        }
    ],
    "sg:phone":"+44 1784 435416",
    "sg:postcode":"TW20 9LD",
    "sg:province":"Surrey",
    "wof:name":"De Boers Shoe Repairs",
    "wof:placetype":"venue"
},
  "geometry": {"coordinates":[-0.5483210087,51.4313316345],"type":"Point"}
}