{
  "type": "Feature",
  "properties": {
    "addr:full":"114 Church Road, Yardley Birmingham West Midlands B25 8UX",
    "addr:housenumber":"114",
    "addr:postcode":"b25 8ux",
    "addr:street":"Church Road",
    "iso:country":"GB",
    "sg:address":"114 Church Road, Yardley",
    "sg:city":"Birmingham",
    "sg:classifiers":[
        {
            "category":"Shopping",
            "subcategory":"Pharmacy",
            "type":"Retail Goods"
        }
    ],
    "sg:phone":"+44 121 783 2403",
    "sg:postcode":"B25 8UX",
    "sg:province":"West Midlands",
    "sg:tags":[
        "pharmacist",
        "chemist"
    ],
    "wof:name":"Boots the Chemists",
    "wof:placetype":"venue"
},
  "geometry": {"coordinates":[-1.8097180128,52.4668998718],"type":"Point"}
}