{
  "type": "Feature",
  "properties": {
    "addr:full":"Heath House Farm, Ostlers Lane, Cheddleton Leek Staffordshire ST13 7DQ",
    "addr:postcode":"st13 7dq",
    "addr:street":"Heath House;Ostlers Lane",
    "iso:country":"GB",
    "sg:address":"Heath House Farm, Ostlers Lane, Cheddleton",
    "sg:city":"Leek",
    "sg:classifiers":[
        {
            "category":"Banks & Credit Unions",
            "subcategory":"Investment Brokerage",
            "type":"Services"
        }
    ],
    "sg:postcode":"ST13 7DQ",
    "sg:province":"Staffordshire",
    "sg:tags":[
        "contractor"
    ],
    "wof:name":"G Carr",
    "wof:placetype":"venue"
},
  "geometry": {"coordinates":[-2.0432031155,53.0643424988],"type":"Point"}
}