{
  "type": "Feature",
  "properties": {
    "iso:country":"GB",
    "sg:address":"1 Jerome Road",
    "sg:city":"Cannock",
    "sg:classifiers":[
        {
            "category":"Bars & Pubs",
            "type":"Food & Drink"
        }
    ],
    "sg:phone":"+44 1543 458406",
    "sg:postcode":"WS11 3TL",
    "sg:province":"Staffordshire",
    "sg:tags":[
        "pubs",
        "inn"
    ],
    "wof:name":"The Yew Tree",
    "wof:placetype":"venue"
},
  "geometry": {"coordinates":[-1.972345,52.672039],"type":"Point"}
}