{
  "type": "Feature",
  "properties": {
    "iso:country":"GB",
    "sg:address":"5 Whalley Road, Read",
    "sg:city":"Burnley",
    "sg:classifiers":[
        {
            "category":"Building & Trades",
            "subcategory":"Plumbing",
            "type":"Services"
        }
    ],
    "sg:phone":"+44 1282 774703",
    "sg:postcode":"BB12 7PB",
    "sg:province":"Lancashire",
    "sg:tags":[
        "plumber",
        "heating"
    ],
    "wof:name":"Haworths Plumbing Service",
    "wof:placetype":"venue"
},
  "geometry": {"coordinates":[-2.352452,53.806374],"type":"Point"}
}