{
  "type": "Feature",
  "properties": {
    "addr:full":"18 Worcester Rd Willenhall West Midlands WV13 2RZ",
    "addr:housenumber":"18",
    "addr:postcode":"wv13 2rz",
    "addr:street":"Worcester Rd",
    "iso:country":"GB",
    "sg:address":"18 Worcester Rd",
    "sg:city":"Willenhall",
    "sg:classifiers":[
        {
            "category":"Building & Trades",
            "subcategory":"Construction",
            "type":"Services"
        }
    ],
    "sg:phone":"+44 1902 631619",
    "sg:postcode":"WV13 2RZ",
    "sg:province":"West Midlands",
    "sg:tags":[
        "guttering"
    ],
    "wof:name":"Mercia Cladding",
    "wof:placetype":"venue"
},
  "geometry": {"coordinates":[-2.034217,52.586178],"type":"Point"}
}