{
  "type": "Feature",
  "properties": {
    "addr:full":"Red House Yard, Gislingham Rd Eye Suffolk IP23 8HH",
    "addr:postcode":"ip23 8hh",
    "addr:street":"Gislingham Rd",
    "iso:country":"GB",
    "sg:address":"Red House Yard, Gislingham Rd",
    "sg:city":"Eye",
    "sg:classifiers":[
        {
            "category":"Fast Food",
            "type":"Food & Drink"
        },
        {
            "category":"Cafe",
            "type":"Food & Drink"
        }
    ],
    "sg:postcode":"IP23 8HH",
    "sg:province":"Suffolk",
    "sg:tags":[
        "tea",
        "away",
        "room",
        "take"
    ],
    "wof:name":"Skipper,Morag,",
    "wof:placetype":"venue"
},
  "geometry": {"coordinates":[1.14587605,52.3220710754],"type":"Point"}
}