{
  "type": "Feature",
  "properties": {
    "iso:country":"GB",
    "sg:address":"26 Radwinter Road",
    "sg:city":"Saffron Walden",
    "sg:classifiers":[
        {
            "category":"Manufacturing",
            "subcategory":"Wood Products",
            "type":"Manufacturing & Wholesale Goods"
        }
    ],
    "sg:phone":"+44 1799 521506",
    "sg:postcode":"CB11 3JB",
    "sg:province":"Essex",
    "sg:tags":[
        "maker",
        "cabinet"
    ],
    "wof:name":"Robin Flack",
    "wof:placetype":"venue"
},
  "geometry": {"coordinates":[0.251209,52.023224],"type":"Point"}
}