{
  "type": "Feature",
  "properties": {
    "addr:full":"Gosforth, Wasdale Seascale Cumbria CA20 1ET",
    "addr:postcode":"ca20 1et",
    "iso:country":"GB",
    "sg:address":"Gosforth, Wasdale",
    "sg:city":"Seascale",
    "sg:classifiers":[
        {
            "category":"Travel",
            "subcategory":"Hotels & Motels",
            "type":"Entertainment"
        }
    ],
    "sg:phone":"+44 19467 26237",
    "sg:postcode":"CA20 1ET",
    "sg:province":"Cumbria",
    "wof:name":"Strands Hotel",
    "wof:placetype":"venue"
},
  "geometry": {"coordinates":[-3.4846200943,54.394821167],"type":"Point"}
}