{
  "type": "Feature",
  "properties": {
    "addr:full":"28-30 Bridge Street Dunfermline Fife KY12 8DA",
    "addr:housenumber":"28-30",
    "addr:postcode":"ky12 8da",
    "addr:street":"Bridge Street",
    "iso:country":"GB",
    "sg:address":"28-30 Bridge Street",
    "sg:city":"Dunfermline",
    "sg:classifiers":[
        {
            "category":"Shopping",
            "subcategory":"Gifts & Souvenirs",
            "type":"Retail Goods"
        }
    ],
    "sg:phone":"+44 1383 620373",
    "sg:postcode":"KY12 8DA",
    "sg:province":"Fife",
    "sg:tags":[
        "shop"
    ],
    "wof:name":"Pink String & Sealing Wax Gift Shop",
    "wof:placetype":"venue"
},
  "geometry": {"coordinates":[-3.4650650024,56.0713768005],"type":"Point"}
}