{
  "type": "Feature",
  "properties": {
    "addr:full":"17 Great Hampton Row Birmingham West Midlands B19 3JA",
    "addr:housenumber":"17",
    "addr:postcode":"b19 3ja",
    "addr:street":"Great Hampton Row",
    "iso:country":"GB",
    "sg:address":"17 Great Hampton Row",
    "sg:city":"Birmingham",
    "sg:classifiers":[
        {
            "category":"Bars & Pubs",
            "type":"Food & Drink"
        }
    ],
    "sg:postcode":"B19 3JA",
    "sg:province":"West Midlands",
    "sg:tags":[
        "pubs",
        "inn"
    ],
    "wof:name":"Minerva Vaults (The)",
    "wof:placetype":"venue"
},
  "geometry": {"coordinates":[-1.906165,52.489037],"type":"Point"}
}