{
  "type": "Feature",
  "properties": {
    "addr:full":"Unit 1, Romney House Ind Est, Wolverhampton St Wednesbury West Midlands WS10 8UB",
    "addr:housenumber":"unit 1 romney house ind",
    "addr:postcode":"ws10 8ub",
    "addr:street":"Wolverhampton St",
    "iso:country":"GB",
    "sg:address":"Unit 1, Romney House Ind Est, Wolverhampton St",
    "sg:city":"Wednesbury",
    "sg:classifiers":[
        {
            "category":"Retail",
            "subcategory":"Auto Repair",
            "type":"Services"
        }
    ],
    "sg:phone":"+44 121 526 5511",
    "sg:postcode":"WS10 8UB",
    "sg:province":"West Midlands",
    "sg:tags":[
        "modification",
        "garage"
    ],
    "wof:name":"M.D.B",
    "wof:placetype":"venue"
},
  "geometry": {"coordinates":[-2.0478689671,52.5711708069],"type":"Point"}
}