{
  "type": "Feature",
  "properties": {
    "addr:full":"18 Home Park, Stoke Plymouth Devon PL2 1BQ",
    "addr:housenumber":"18",
    "addr:postcode":"pl2 1bq",
    "addr:street":"Home Park",
    "iso:country":"GB",
    "sg:address":"18 Home Park, Stoke",
    "sg:city":"Plymouth",
    "sg:classifiers":[
        {
            "category":"Health Services",
            "subcategory":"Nursing And Care Facility",
            "type":"Services"
        },
        {
            "category":"Organizations",
            "subcategory":"Community Association",
            "type":"Services"
        }
    ],
    "sg:phone":"+44 1752 563362",
    "sg:postcode":"PL2 1BQ",
    "sg:province":"Devon",
    "sg:tags":[
        "residential",
        "housing",
        "society"
    ],
    "wof:name":"THE ABBEYFIELD PLYMOUTH SOCIETY LTD",
    "wof:placetype":"venue"
},
  "geometry": {"coordinates":[-4.1686258316,50.3800048828],"type":"Point"}
}