{
  "type": "Feature",
  "properties": {
    "addr:full":"84 Baghill Lane Pontefract North Yorkshire WF8 2HB",
    "addr:housenumber":"84",
    "addr:postcode":"wf8 2hb",
    "addr:street":"Baghill Lane",
    "iso:country":"GB",
    "sg:address":"84 Baghill Lane",
    "sg:city":"Pontefract",
    "sg:classifiers":[
        {
            "category":"Food & Beverages",
            "subcategory":"Groceries & Convenience Stores",
            "type":"Retail Goods"
        }
    ],
    "sg:phone":"+44 1977 794811",
    "sg:postcode":"WF8 2HB",
    "sg:province":"North Yorkshire",
    "wof:name":"Tates",
    "wof:placetype":"venue"
},
  "geometry": {"coordinates":[-1.294251,53.691662],"type":"Point"}
}