{
  "type": "Feature",
  "properties": {
    "addr:full":"3 Council House, Newton-by-toft Market Rasen Lincolnshire LN8 3NF",
    "addr:housenumber":"3",
    "addr:postcode":"ln8 3nf",
    "addr:street":"Market Rasen",
    "iso:country":"GB",
    "sg:address":"3 Council House, Newton-by-toft",
    "sg:city":"Market Rasen",
    "sg:classifiers":[
        {
            "category":"Freight",
            "type":"Transportation"
        }
    ],
    "sg:postcode":"LN8 3NF",
    "sg:province":"Lincolnshire",
    "sg:tags":[
        "haulage",
        "road"
    ],
    "wof:name":"J B Feather",
    "wof:placetype":"venue"
},
  "geometry": {"coordinates":[-0.3330680132,53.3867874146],"type":"Point"}
}