{
  "type": "Feature",
  "properties": {
    "iso:country":"GB",
    "sg:address":"5 Dudley Close, North Marston",
    "sg:city":"Buckingham",
    "sg:classifiers":[
        {
            "category":"Building & Trades",
            "subcategory":"Landscaping Services",
            "type":"Services"
        }
    ],
    "sg:phone":"+44 1296 670100",
    "sg:postcode":"MK18 3RA",
    "sg:province":"Buckinghamshire",
    "sg:tags":[
        "landscape",
        "contractor"
    ],
    "wof:name":"A D R & T A Lane",
    "wof:placetype":"venue"
},
  "geometry": {"coordinates":[-0.878068,51.898666],"type":"Point"}
}