{
  "type": "Feature",
  "properties": {
    "iso:country":"GB",
    "sg:address":"131 Main Street",
    "sg:city":"Kilwinning",
    "sg:classifiers":[
        {
            "category":"Government",
            "subcategory":"Post Office",
            "type":"Public Place"
        }
    ],
    "sg:phone":"+44 1294 552228",
    "sg:postcode":"KA13 6EG",
    "sg:province":"East Ayrshire",
    "wof:name":"Post Office Counters Ltd.",
    "wof:placetype":"venue"
},
  "geometry": {"coordinates":[-4.700220108,55.653591156],"type":"Point"}
}