{
  "type": "Feature",
  "properties": {
    "iso:country":"GB",
    "sg:address":"Heathfield Road, Handsworth",
    "sg:city":"Birmingham",
    "sg:classifiers":[
        {
            "category":"Health Services",
            "subcategory":"Clinic",
            "type":"Services"
        }
    ],
    "sg:phone":"+44 121 554 5504",
    "sg:postcode":"B19 1HJ",
    "sg:province":"West Midlands",
    "sg:tags":[
        "nh"
    ],
    "wof:name":"Mayfield Centre",
    "wof:placetype":"venue"
},
  "geometry": {"coordinates":[-1.904179,52.50845],"type":"Point"}
}