{
  "type": "Feature",
  "properties": {
    "addr:full":"Crown Ho, Kings Rd Evesham Gloucestershire WR11 3BE",
    "addr:postcode":"wr11 3be",
    "addr:street":"Kings Rd",
    "iso:country":"GB",
    "sg:address":"Crown Ho, Kings Rd",
    "sg:city":"Evesham",
    "sg:classifiers":[
        {
            "category":"Farming",
            "subcategory":"Nursery",
            "type":"Manufacturing & Wholesale Goods"
        }
    ],
    "sg:postcode":"WR11 3BE",
    "sg:province":"Gloucestershire",
    "sg:tags":[
        "creche"
    ],
    "wof:name":"Cygnets Baby Unit",
    "wof:placetype":"venue"
},
  "geometry": {"coordinates":[-1.943969,52.106392],"type":"Point"}
}