{
  "type": "Feature",
  "properties": {
    "addr:full":"16 Hafod, Emmer Grn Reading Berkshire RG4 8LZ",
    "addr:housenumber":"16",
    "addr:postcode":"rg4 8lz",
    "addr:street":"Hafod Emmer Grn",
    "iso:country":"GB",
    "sg:address":"16 Hafod, Emmer Grn",
    "sg:city":"Reading",
    "sg:classifiers":[
        {
            "category":"Professional",
            "subcategory":"Computer Services",
            "type":"Services"
        }
    ],
    "sg:phone":"+44 118 948 3300",
    "sg:postcode":"RG4 8LZ",
    "sg:province":"Berkshire",
    "sg:tags":[
        "system",
        "software"
    ],
    "wof:name":"Citinet Group Ltd.",
    "wof:placetype":"venue"
},
  "geometry": {"coordinates":[-0.9800069928,51.4850845337],"type":"Point"}
}