{
  "type": "Feature",
  "properties": {
    "iso:country":"GB",
    "sg:address":"142b High St, Cranfield",
    "sg:city":"Bedford",
    "sg:classifiers":[
        {
            "category":"Professional",
            "subcategory":"Employment Agencies",
            "type":"Services"
        }
    ],
    "sg:phone":"+44 1234 752193",
    "sg:postcode":"MK43 0EL",
    "sg:province":"Bedfordshire",
    "sg:tags":[
        "consultant"
    ],
    "wof:name":"Christopher Hamblyn Associates",
    "wof:placetype":"venue"
},
  "geometry": {"coordinates":[-0.606391,52.071041],"type":"Point"}
}