{
  "type": "Feature",
  "properties": {
    "addr:full":"180-190 High St, Lewisham Lewisham Greater London SE13 6JW",
    "addr:housenumber":"180-190",
    "addr:postcode":"se13 6jw",
    "addr:street":"High St",
    "iso:country":"GB",
    "sg:address":"180-190 High St, Lewisham",
    "sg:city":"Lewisham",
    "sg:classifiers":[
        {
            "category":"Shopping",
            "subcategory":"Clothing, Apparel, & Fashions",
            "type":"Retail Goods"
        }
    ],
    "sg:phone":"+44 20 8852 0022",
    "sg:postcode":"SE13 6JW",
    "sg:province":"Greater London",
    "sg:tags":[
        "shop"
    ],
    "wof:name":"C & A",
    "wof:placetype":"venue"
},
  "geometry": {"coordinates":[0.0515139997,51.5386657715],"type":"Point"}
}