{
  "type": "Feature",
  "properties": {
    "iso:country":"GB",
    "sg:address":"Brownsbrook, Whixall",
    "sg:city":"Whitchurch",
    "sg:classifiers":[
        {
            "category":"Education",
            "subcategory":"School",
            "type":"Public Place"
        }
    ],
    "sg:phone":"+44 1948 880330",
    "sg:postcode":"SY13 2SB",
    "sg:province":"Cheshire",
    "sg:tags":[
        "local",
        "authority"
    ],
    "wof:name":"Whixall C of E Primary School",
    "wof:placetype":"venue"
},
  "geometry": {"coordinates":[-2.720931,52.905739],"type":"Point"}
}