{
  "type": "Feature",
  "properties": {
    "iso:country":"GB",
    "sg:address":"1 Horsham Gates, North Street",
    "sg:city":"Horsham",
    "sg:classifiers":[
        {
            "category":"Wholesale",
            "subcategory":"Books, Periodicals, & Newspapers",
            "type":"Manufacturing & Wholesale Goods"
        }
    ],
    "sg:phone":"+44 1403 833200",
    "sg:postcode":"RH13 5PJ",
    "sg:province":"West Sussex",
    "sg:tags":[
        "publishing"
    ],
    "wof:name":"Dorling Kindersley Family Learning Ltd.",
    "wof:placetype":"venue"
},
  "geometry": {"coordinates":[-0.31707,51.067631],"type":"Point"}
}