{
  "type": "Feature",
  "properties": {
    "iso:country":"GB",
    "sg:address":"150 Valley Crescent, Wrenthorpe",
    "sg:city":"Wakefield",
    "sg:classifiers":[
        {
            "category":"Manufacturing",
            "subcategory":"Signs",
            "type":"Manufacturing & Wholesale Goods"
        }
    ],
    "sg:phone":"+44 1924 365800",
    "sg:postcode":"WF2 0ND",
    "sg:province":"West Yorkshire",
    "sg:tags":[
        "commercial",
        "maker"
    ],
    "wof:name":"Vital Signs Wakefield",
    "wof:placetype":"venue"
},
  "geometry": {"coordinates":[-1.5213860273,53.698677063],"type":"Point"}
}