{
  "type": "Feature",
  "properties": {
    "addr:full":"115 Chiltern Dr Surbiton Surrey KT5 8LS",
    "addr:housenumber":"115",
    "addr:postcode":"kt5 8ls",
    "addr:street":"Chiltern Dr",
    "iso:country":"GB",
    "sg:address":"115 Chiltern Dr",
    "sg:city":"Surbiton",
    "sg:classifiers":[
        {
            "category":"Food & Beverages",
            "subcategory":"Bakery",
            "type":"Retail Goods"
        }
    ],
    "sg:postcode":"KT5 8LS",
    "sg:province":"Surrey",
    "sg:tags":[
        "baker"
    ],
    "wof:name":"Duddy,Michael,",
    "wof:placetype":"venue"
},
  "geometry": {"coordinates":[-0.2803870142,51.3984527588],"type":"Point"}
}