{
  "type": "Feature",
  "properties": {
    "iso:country":"GB",
    "sg:address":"Redwall Hall Farm, Shotley Bridge",
    "sg:city":"Consett",
    "sg:classifiers":[
        {
            "category":"Farming",
            "subcategory":"Livestock Farm",
            "type":"Manufacturing & Wholesale Goods"
        }
    ],
    "sg:phone":"+44 1207 255216",
    "sg:postcode":"DH8 9TS",
    "sg:province":"Durham",
    "sg:tags":[
        "others"
    ],
    "wof:name":"P C WARD & SON",
    "wof:placetype":"venue"
},
  "geometry": {"coordinates":[-1.835914,54.860989],"type":"Point"}
}