{
  "type": "Feature",
  "properties": {
    "iso:country":"GB",
    "sg:address":"163 Burrowmoor Road",
    "sg:city":"March",
    "sg:classifiers":[
        {
            "category":"Farming",
            "subcategory":"Livestock Farm",
            "type":"Manufacturing & Wholesale Goods"
        }
    ],
    "sg:phone":"+44 1354 652046",
    "sg:postcode":"PE15 9SS",
    "sg:province":"Cambridgeshire",
    "sg:tags":[
        "others"
    ],
    "wof:name":"F Pollington & Son",
    "wof:placetype":"venue"
},
  "geometry": {"coordinates":[0.073315,52.545128],"type":"Point"}
}