{
  "type": "Feature",
  "properties": {
    "iso:country":"GB",
    "sg:address":"Turnpike Cottage, Woburn Road, Hockliffe",
    "sg:city":"Leighton Buzzard",
    "sg:classifiers":[
        {
            "category":"Transit Center",
            "subcategory":"Passenger",
            "type":"Transportation"
        }
    ],
    "sg:postcode":"LU7 9LL",
    "sg:province":"Bedfordshire",
    "sg:tags":[
        "boarding",
        "kennel",
        "catteries"
    ],
    "wof:name":"Dick Whittingtons Cattering",
    "wof:placetype":"venue"
},
  "geometry": {"coordinates":[-0.585949,51.932377],"type":"Point"}
}