{
  "type": "Feature",
  "properties": {
    "addr:full":"Wayside Farm Stroud Gloucestershire GL6 7EW",
    "addr:postcode":"gl6 7ew",
    "iso:country":"GB",
    "sg:address":"Wayside Farm",
    "sg:city":"Stroud",
    "sg:phone":"+44 1285 821631",
    "sg:postcode":"GL6 7EW",
    "sg:province":"Gloucestershire",
    "wof:name":"Cotswold Car Centre",
    "wof:placetype":"venue"
},
  "geometry": {"coordinates":[-2.1280100346,51.7913589478],"type":"Point"}
}