{
  "type": "Feature",
  "properties": {
    "iso:country":"GB",
    "sg:address":"3 Eccleston Close, Birchwood",
    "sg:city":"Warrington",
    "sg:classifiers":[
        {
            "category":"Personal",
            "type":"Services"
        }
    ],
    "sg:phone":"+44 1925 850042",
    "sg:postcode":"WA3 7NL",
    "sg:province":"Cheshire",
    "sg:tags":[
        "wedding"
    ],
    "wof:name":"Bespoke Wheels Vintage Car Hire",
    "wof:placetype":"venue"
},
  "geometry": {"coordinates":[-2.541788,53.423836],"type":"Point"}
}