{
  "type": "Feature",
  "properties": {
    "addr:full":"Allport House, Princes Street Southampton Hampshire SO14 5RP",
    "addr:postcode":"so14 5rp",
    "addr:street":"Princes Street",
    "iso:country":"GB",
    "sg:address":"Allport House, Princes Street",
    "sg:city":"Southampton",
    "sg:classifiers":[
        {
            "category":"Organizations",
            "subcategory":"Non-profit Organization",
            "type":"Services"
        }
    ],
    "sg:phone":"+44 23 8077 0254",
    "sg:postcode":"SO14 5RP",
    "sg:province":"Hampshire",
    "sg:tags":[
        "organisation",
        "voluntary",
        "charity"
    ],
    "wof:name":"Wessex Medical Trust",
    "wof:placetype":"venue"
},
  "geometry": {"coordinates":[-1.3875590563,50.9119606018],"type":"Point"}
}