{
  "type": "Feature",
  "properties": {
    "addr:full":"20b Queen St Bridgend Bridgend CF31 1HX",
    "addr:housenumber":"20b",
    "addr:postcode":"cf31 1hx",
    "addr:street":"Queen St",
    "iso:country":"GB",
    "sg:address":"20b Queen St",
    "sg:city":"Bridgend",
    "sg:classifiers":[
        {
            "category":"Shopping",
            "subcategory":"Antiques",
            "type":"Retail Goods"
        }
    ],
    "sg:postcode":"CF31 1HX",
    "sg:province":"Bridgend",
    "wof:name":"Sutton,Nigel,",
    "wof:placetype":"venue"
},
  "geometry": {"coordinates":[-3.578607,51.505215],"type":"Point"}
}