{
  "type": "Feature",
  "properties": {
    "addr:full":"43 Main Street West Calder South Lanarkshire EH55 8DL",
    "addr:housenumber":"43",
    "addr:postcode":"eh55 8dl",
    "addr:street":"Main Street",
    "iso:country":"GB",
    "sg:address":"43 Main Street",
    "sg:city":"West Calder",
    "sg:classifiers":[
        {
            "category":"Travel",
            "subcategory":"Hotels & Motels",
            "type":"Entertainment"
        }
    ],
    "sg:phone":"+44 1506 871475",
    "sg:postcode":"EH55 8DL",
    "sg:province":"South Lanarkshire",
    "wof:name":"Railway Inn",
    "wof:placetype":"venue"
},
  "geometry": {"coordinates":[-3.5715239048,55.8514442444],"type":"Point"}
}