{
  "type": "Feature",
  "properties": {
    "iso:country":"GB",
    "sg:address":"Suite 231 Kentish Town Road, Kentish Town",
    "sg:city":"London",
    "sg:classifiers":[
        {
            "category":"Professional",
            "subcategory":"Employment Agencies",
            "type":"Services"
        }
    ],
    "sg:postcode":"NW5 2JT",
    "sg:province":"Greater London",
    "sg:tags":[
        "consultant"
    ],
    "wof:name":"New Career Moves",
    "wof:placetype":"venue"
},
  "geometry": {"coordinates":[-0.141289,51.547901],"type":"Point"}
}