{
  "type": "Feature",
  "properties": {
    "addr:full":"Salisbury Street, Barton Hill Bristol City of Bristol BS5 9UD",
    "addr:postcode":"bs5 9ud",
    "addr:street":"Salisbury Street",
    "iso:country":"GB",
    "sg:address":"Salisbury Street, Barton Hill",
    "sg:city":"Bristol",
    "sg:classifiers":[
        {
            "category":"Professional",
            "subcategory":"Engineering",
            "type":"Services"
        }
    ],
    "sg:phone":"+44 117 955 0781",
    "sg:postcode":"BS5 9UD",
    "sg:province":"City of Bristol",
    "sg:tags":[
        "precision",
        "engineer"
    ],
    "wof:name":"Brown Rutter Ltd.",
    "wof:placetype":"venue"
},
  "geometry": {"coordinates":[-2.564079,51.452648],"type":"Point"}
}