{
  "type": "Feature",
  "properties": {
    "iso:country":"GB",
    "sg:address":"6 The Crescent",
    "sg:city":"Leeds",
    "sg:classifiers":[
        {
            "category":"Personal",
            "subcategory":"Beauty Salon",
            "type":"Services"
        }
    ],
    "sg:postcode":"LS16 6AA",
    "sg:province":"West Yorkshire",
    "sg:tags":[
        "unisex",
        "hairdresser"
    ],
    "wof:name":"The Padd Hair Studio",
    "wof:placetype":"venue"
},
  "geometry": {"coordinates":[-1.593121,53.851837],"type":"Point"}
}