{
  "type": "Feature",
  "properties": {
    "addr:full":"92 Trippet La Sheffield South Yorkshire S1 4EL",
    "addr:housenumber":"92",
    "addr:postcode":"s1 4el",
    "addr:street":"Trippet La Sheffield South",
    "iso:country":"GB",
    "sg:address":"92 Trippet La",
    "sg:city":"Sheffield",
    "sg:classifiers":[
        {
            "category":"Professional",
            "subcategory":"Computer Services",
            "type":"Services"
        }
    ],
    "sg:phone":"+44 114 296 9000",
    "sg:postcode":"S1 4EL",
    "sg:province":"South Yorkshire",
    "sg:tags":[
        "system",
        "software"
    ],
    "wof:name":"Project X",
    "wof:placetype":"venue"
},
  "geometry": {"coordinates":[-1.475519,53.381714],"type":"Point"}
}