{
  "type": "Feature",
  "properties": {
    "addr:full":"18 Woodland Avenue Slough Berkshire SL1 3BU",
    "addr:housenumber":"18",
    "addr:postcode":"sl1 3bu",
    "addr:street":"Woodland Avenue",
    "iso:country":"GB",
    "sg:address":"18 Woodland Avenue",
    "sg:city":"Slough",
    "sg:classifiers":[
        {
            "category":"Shopping",
            "subcategory":"Department Store",
            "type":"Retail Goods"
        },
        {
            "category":"Food & Beverages",
            "subcategory":"Groceries & Convenience Stores",
            "type":"Retail Goods"
        }
    ],
    "sg:phone":"+44 1753 525638",
    "sg:postcode":"SL1 3BU",
    "sg:province":"Berkshire",
    "wof:name":"Sandhu Food Stores",
    "wof:placetype":"venue"
},
  "geometry": {"coordinates":[-0.607279,51.517651],"type":"Point"}
}