{
  "type": "Feature",
  "properties": {
    "iso:country":"GB",
    "sg:address":"479 Oxford Road",
    "sg:city":"Reading",
    "sg:classifiers":[
        {
            "category":"Shopping",
            "subcategory":"Pharmacy",
            "type":"Retail Goods"
        }
    ],
    "sg:phone":"+44 118 957 1681",
    "sg:postcode":"RG30 1HF",
    "sg:province":"Berkshire",
    "sg:tags":[
        "pharmacist",
        "dispensing",
        "chemist"
    ],
    "wof:name":"Battle Pharmacy",
    "wof:placetype":"venue"
},
  "geometry": {"coordinates":[-0.9988129735,51.4572639465],"type":"Point"}
}