{
  "type": "Feature",
  "properties": {
    "addr:full":"85 Kentmere Road Bolton Lancashire BL2 5JN",
    "addr:housenumber":"85",
    "addr:postcode":"bl2 5jn",
    "addr:street":"Kentmere Road",
    "iso:country":"GB",
    "sg:address":"85 Kentmere Road",
    "sg:city":"Bolton",
    "sg:classifiers":[
        {
            "category":"Social Services",
            "subcategory":"Adult Care",
            "type":"Services"
        }
    ],
    "sg:phone":"+44 1204 457140",
    "sg:postcode":"BL2 5JN",
    "sg:province":"Lancashire",
    "sg:tags":[
        "domestic",
        "cleaning"
    ],
    "wof:name":"Gum Busters",
    "wof:placetype":"venue"
},
  "geometry": {"coordinates":[-2.382186,53.589787],"type":"Point"}
}