{
  "type": "Feature",
  "properties": {
    "addr:full":"Mineral Lane Chesham Buckinghamshire HP5 1NL",
    "addr:postcode":"hp5 1nl",
    "addr:street":"Mineral Lane",
    "iso:country":"GB",
    "sg:address":"Mineral Lane",
    "sg:city":"Chesham",
    "sg:classifiers":[
        {
            "category":"Professional",
            "subcategory":"Business Services",
            "type":"Services"
        },
        {
            "category":"Organizations",
            "subcategory":"Professional Association",
            "type":"Services"
        }
    ],
    "sg:phone":"+44 1494 782873",
    "sg:postcode":"HP5 1NL",
    "sg:province":"Buckinghamshire",
    "sg:tags":[
        "organisation",
        "trade"
    ],
    "sg:website":"http://www.bdta.org.uk",
    "wof:name":"The British Dental Trade Association Ltd.",
    "wof:placetype":"venue"
},
  "geometry": {"coordinates":[-0.6105319858,51.7007904053],"type":"Point"}
}