{
  "type": "Feature",
  "properties": {
    "iso:country":"GB",
    "sg:address":"Bradford Road",
    "sg:city":"Dewsbury",
    "sg:classifiers":[
        {
            "category":"Bars & Pubs",
            "type":"Food & Drink"
        }
    ],
    "sg:phone":"+44 1924 456284",
    "sg:postcode":"WF13 1EL",
    "sg:province":"West Yorkshire",
    "sg:tags":[
        "pubs",
        "inn"
    ],
    "wof:name":"G Moore",
    "wof:placetype":"venue"
},
  "geometry": {"coordinates":[-1.630629,53.69418],"type":"Point"}
}