{
  "type": "Feature",
  "properties": {
    "iso:country":"GB",
    "sg:address":"82-84 Broom Road East",
    "sg:city":"Glasgow",
    "sg:classifiers":[
        {
            "category":"Farming",
            "subcategory":"Nursery",
            "type":"Manufacturing & Wholesale Goods"
        },
        {
            "category":"Social Services",
            "subcategory":"Child Care",
            "type":"Services"
        }
    ],
    "sg:phone":"+44 141 639 8000",
    "sg:postcode":"G77 5SR",
    "sg:province":"East Ayrshire",
    "sg:tags":[
        "creche"
    ],
    "wof:name":"Kirkhillgait Nursery",
    "wof:placetype":"venue"
},
  "geometry": {"coordinates":[-4.305120945,55.7738990784],"type":"Point"}
}