{
  "type": "Feature",
  "properties": {
    "addr:full":"Unit 17, Tile Cross Trading Estate, Tile Cross Road Birmingham West Midlands B33 0NN",
    "addr:housenumber":"unit 17",
    "addr:postcode":"b33 0nn",
    "addr:street":"Tile Cross Trading Estate Tile Cross Road",
    "iso:country":"GB",
    "sg:address":"Unit 17, Tile Cross Trading Estate, Tile Cross Road",
    "sg:city":"Birmingham",
    "sg:classifiers":[
        {
            "category":"Home & Garden",
            "subcategory":"Furniture",
            "type":"Retail Goods"
        }
    ],
    "sg:postcode":"B33 0NN",
    "sg:province":"West Midlands",
    "wof:name":"House of Furniture",
    "wof:placetype":"venue"
},
  "geometry": {"coordinates":[-1.764914,52.473034],"type":"Point"}
}