{
  "type": "Feature",
  "properties": {
    "addr:full":"28 London Road Alderley Edge Cheshire SK9 7DZ",
    "addr:housenumber":"28",
    "addr:postcode":"sk9 7dz",
    "addr:street":"London Road",
    "iso:country":"GB",
    "sg:address":"28 London Road",
    "sg:city":"Alderley Edge",
    "sg:classifiers":[
        {
            "category":"Travel",
            "subcategory":"Travel Agent",
            "type":"Entertainment"
        }
    ],
    "sg:phone":"+44 1625 584195",
    "sg:postcode":"SK9 7DZ",
    "sg:province":"Cheshire",
    "sg:tags":[
        "agency",
        "activity"
    ],
    "wof:name":"Travel By Design Ltd",
    "wof:placetype":"venue"
},
  "geometry": {"coordinates":[-2.2363929749,53.3014450073],"type":"Point"}
}