{
  "type": "Feature",
  "properties": {
    "addr:full":"High Rd, Vange Basildon Essex SS16 4ND",
    "addr:postcode":"ss16 4nd",
    "addr:street":"High Rd",
    "iso:country":"GB",
    "sg:address":"High Rd, Vange",
    "sg:city":"Basildon",
    "sg:classifiers":[
        {
            "category":"Bars & Pubs",
            "type":"Food & Drink"
        }
    ],
    "sg:phone":"+44 1268 552212",
    "sg:postcode":"SS16 4ND",
    "sg:province":"Essex",
    "sg:tags":[
        "pubs",
        "inn"
    ],
    "wof:name":"The Barge Inn",
    "wof:placetype":"venue"
},
  "geometry": {"coordinates":[0.4823909998,51.5614967346],"type":"Point"}
}