{
  "type": "Feature",
  "properties": {
    "iso:country":"GB",
    "sg:address":"21 Pealsham Gardens",
    "sg:city":"Fordingbridge",
    "sg:classifiers":[
        {
            "category":"Taxi",
            "type":"Transportation"
        }
    ],
    "sg:phone":"+44 1425 650000",
    "sg:postcode":"SP6 1RD",
    "sg:province":"Dorset",
    "sg:tags":[
        "mini",
        "cab"
    ],
    "wof:name":"Red Express",
    "wof:placetype":"venue"
},
  "geometry": {"coordinates":[-1.798218,50.933315],"type":"Point"}
}