{
  "type": "Feature",
  "properties": {
    "addr:full":"56 Summerheath Road Hailsham East Sussex BN27 3DR",
    "addr:housenumber":"56",
    "addr:postcode":"bn27 3dr",
    "addr:street":"Summerheath Road",
    "iso:country":"GB",
    "sg:address":"56 Summerheath Road",
    "sg:city":"Hailsham",
    "sg:classifiers":[
        {
            "category":"Home & Garden",
            "subcategory":"Household Appliances",
            "type":"Retail Goods"
        }
    ],
    "sg:phone":"+44 1323 844103",
    "sg:postcode":"BN27 3DR",
    "sg:province":"East Sussex",
    "sg:tags":[
        "electrical"
    ],
    "wof:name":"H D E Electrical Services",
    "wof:placetype":"venue"
},
  "geometry": {"coordinates":[0.254249,50.863892],"type":"Point"}
}