{
  "type": "Feature",
  "properties": {
    "addr:full":"8 Church St Llangefni Gwynedd LL77 7DU",
    "addr:housenumber":"8",
    "addr:postcode":"ll77 7du",
    "addr:street":"Church St",
    "iso:country":"GB",
    "sg:address":"8 Church St",
    "sg:city":"Llangefni",
    "sg:classifiers":[
        {
            "category":"Home & Garden",
            "subcategory":"Building Materials",
            "type":"Retail Goods"
        }
    ],
    "sg:phone":"+44 1248 724733",
    "sg:postcode":"LL77 7DU",
    "sg:province":"Gwynedd",
    "sg:tags":[
        "hinge"
    ],
    "wof:name":"The Heel Bar",
    "wof:placetype":"venue"
},
  "geometry": {"coordinates":[-4.3113718033,53.2572097778],"type":"Point"}
}