{
  "type": "Feature",
  "properties": {
    "addr:full":"Ivy House, Silksworth Lane Sunderland Tyne and Wear SR3 3PP",
    "addr:postcode":"sr3 3pp",
    "addr:street":"Silksworth Lane",
    "iso:country":"GB",
    "sg:address":"Ivy House, Silksworth Lane",
    "sg:city":"Sunderland",
    "sg:classifiers":[
        {
            "category":"Education",
            "subcategory":"Music School",
            "type":"Public Place"
        }
    ],
    "sg:phone":"+44 191 528 1928",
    "sg:postcode":"SR3 3PP",
    "sg:province":"Tyne and Wear",
    "sg:tags":[
        "conservatory"
    ],
    "wof:name":"Ivy House Conservatories",
    "wof:placetype":"venue"
},
  "geometry": {"coordinates":[-1.417724,54.87722],"type":"Point"}
}