{
  "type": "Feature",
  "properties": {
    "iso:country":"GB",
    "sg:address":"Po Box 144",
    "sg:city":"Woking",
    "sg:classifiers":[
        {
            "category":"Professional",
            "subcategory":"Lawyer & Legal Services",
            "type":"Services"
        }
    ],
    "sg:phone":"+44 1483 751306",
    "sg:postcode":"GU22 7PW",
    "sg:province":"Surrey",
    "sg:tags":[
        "advice",
        "counselling"
    ],
    "wof:name":"Surrey Womens Aid",
    "wof:placetype":"venue"
},
  "geometry": {"coordinates":[-0.55609,51.314369],"type":"Point"}
}