{
  "type": "Feature",
  "properties": {
    "iso:country":"GB",
    "sg:address":"41 Paper Mill Lane, Bramford",
    "sg:city":"Ipswich",
    "sg:classifiers":[
        {
            "category":"Home & Garden",
            "subcategory":"Building Materials",
            "type":"Retail Goods"
        },
        {
            "category":"Building & Trades",
            "subcategory":"Construction",
            "type":"Services"
        }
    ],
    "sg:phone":"+44 1473 464600",
    "sg:postcode":"IP8 4BP",
    "sg:province":"Suffolk",
    "sg:tags":[
        "dry",
        "plasterers",
        "installers",
        "lining",
        "insulation",
        "screeders"
    ],
    "wof:name":"R Fowler Plastering",
    "wof:placetype":"venue"
},
  "geometry": {"coordinates":[1.105927,52.078621],"type":"Point"}
}