{
  "type": "Feature",
  "properties": {
    "iso:country":"GB",
    "sg:address":"Imperial House, 8 Oaklands Business Centre, Oaklands Park",
    "sg:city":"Wokingham",
    "sg:classifiers":[
        {
            "category":"Professional",
            "subcategory":"Computer Services",
            "type":"Services"
        }
    ],
    "sg:phone":"+44 118 936 4300",
    "sg:postcode":"RG41 2FD",
    "sg:province":"Berkshire",
    "sg:tags":[
        "consultant"
    ],
    "wof:name":"Targetfour Ltd.",
    "wof:placetype":"venue"
},
  "geometry": {"coordinates":[-0.84308,51.402992],"type":"Point"}
}