{
  "type": "Feature",
  "properties": {
    "addr:full":"Old Rectory Lane Pulborough West Sussex RH20 1AD",
    "addr:postcode":"rh20 1ad",
    "addr:street":"Rectory Lane",
    "iso:country":"GB",
    "sg:address":"Old Rectory Lane",
    "sg:city":"Pulborough",
    "sg:classifiers":[
        {
            "category":"Travel",
            "subcategory":"Hotels & Motels",
            "type":"Entertainment"
        }
    ],
    "sg:phone":"+44 1798 872486",
    "sg:postcode":"RH20 1AD",
    "sg:province":"West Sussex",
    "sg:website":"http://www.thechequers-hotel.com",
    "wof:name":"Chequers Hotel",
    "wof:placetype":"venue"
},
  "geometry": {"coordinates":[-0.507827,50.958683],"type":"Point"}
}