{
  "type": "Feature",
  "properties": {
    "addr:full":"9 Chapel Street Bridlington East Riding of Yorkshire YO15 2DR",
    "addr:housenumber":"9",
    "addr:postcode":"yo15 2dr",
    "addr:street":"Chapel Street",
    "iso:country":"GB",
    "sg:address":"9 Chapel Street",
    "sg:city":"Bridlington",
    "sg:classifiers":[
        {
            "category":"Shopping",
            "subcategory":"Clothing, Apparel, & Fashions",
            "type":"Retail Goods"
        }
    ],
    "sg:phone":"+44 1262 604743",
    "sg:postcode":"YO15 2DR",
    "sg:province":"East Riding of Yorkshire",
    "sg:tags":[
        "ladieswear"
    ],
    "wof:name":"Tamaras",
    "wof:placetype":"venue"
},
  "geometry": {"coordinates":[-0.191372,54.082958],"type":"Point"}
}