{
  "type": "Feature",
  "properties": {
    "addr:full":"23 Dene Rd Bradford West Yorkshire BD6 3PJ",
    "addr:housenumber":"23",
    "addr:postcode":"bd6 3pj",
    "addr:street":"Dene Rd",
    "iso:country":"GB",
    "sg:address":"23 Dene Rd",
    "sg:city":"Bradford",
    "sg:classifiers":[
        {
            "category":"Building & Trades",
            "subcategory":"Cleaning & Sanitation",
            "type":"Services"
        }
    ],
    "sg:phone":"+44 1274 783723",
    "sg:postcode":"BD6 3PJ",
    "sg:province":"West Yorkshire",
    "sg:tags":[
        "dry",
        "control",
        "damp",
        "rot"
    ],
    "wof:name":"S.U. Dampcourse & Timber Treatment Specialist",
    "wof:placetype":"venue"
},
  "geometry": {"coordinates":[-1.8075239658,53.7700195312],"type":"Point"}
}