{
  "type": "Feature",
  "properties": {
    "addr:full":"Ernest English House, Buckwell Street Plymouth Devon PL1 2DA",
    "addr:postcode":"pl1 2da",
    "addr:street":"Buckwell Street",
    "iso:country":"GB",
    "sg:address":"Ernest English House, Buckwell Street",
    "sg:city":"Plymouth",
    "sg:classifiers":[
        {
            "category":"Personal",
            "type":"Services"
        },
        {
            "category":"Professional",
            "subcategory":"Lawyer & Legal Services",
            "type":"Services"
        }
    ],
    "sg:phone":"+44 1752 201766",
    "sg:postcode":"PL1 2DA",
    "sg:province":"Devon",
    "sg:tags":[
        "advice",
        "counselling"
    ],
    "wof:name":"Plymouth Guild of Voluntary Service Ltd.",
    "wof:placetype":"venue"
},
  "geometry": {"coordinates":[-4.1379442215,50.3691558838],"type":"Point"}
}