{
  "type": "Feature",
  "properties": {
    "addr:full":"10 Church Rd High Wycombe Buckinghamshire HP10 8NX",
    "addr:housenumber":"10",
    "addr:postcode":"hp10 8nx",
    "addr:street":"Church Rd",
    "iso:country":"GB",
    "sg:address":"10 Church Rd",
    "sg:city":"High Wycombe",
    "sg:classifiers":[
        {
            "category":"Social Services",
            "subcategory":"Retirement Home",
            "type":"Services"
        }
    ],
    "sg:phone":"+44 1494 813365",
    "sg:postcode":"HP10 8NX",
    "sg:province":"Buckinghamshire",
    "sg:tags":[
        "rest"
    ],
    "wof:name":"Alde House",
    "wof:placetype":"venue"
},
  "geometry": {"coordinates":[-0.676358,51.631306],"type":"Point"}
}