{
  "type": "Feature",
  "properties": {
    "iso:country":"GB",
    "sg:address":"The Maltings",
    "sg:city":"Sawbridgeworth",
    "sg:classifiers":[
        {
            "category":"Real Estate",
            "subcategory":"Real Estate Operator",
            "type":"Services"
        }
    ],
    "sg:phone":"+44 1279 725872",
    "sg:postcode":"CM21 9JX",
    "sg:province":"Essex",
    "sg:tags":[
        "letting",
        "agent"
    ],
    "wof:name":"Shavemead Ltd.",
    "wof:placetype":"venue"
},
  "geometry": {"coordinates":[0.147223,51.812527],"type":"Point"}
}