{
  "type": "Feature",
  "properties": {
    "iso:country":"GB",
    "sg:address":"55 Melville St",
    "sg:city":"Edinburgh",
    "sg:classifiers":[
        {
            "category":"Wholesale",
            "subcategory":"Books, Periodicals, & Newspapers",
            "type":"Manufacturing & Wholesale Goods"
        }
    ],
    "sg:phone":"+44 131 220 5380",
    "sg:postcode":"EH3 7HL",
    "sg:province":"City of Edinburgh",
    "sg:tags":[
        "publishing"
    ],
    "wof:name":"Johnstone Media Ltd",
    "wof:placetype":"venue"
},
  "geometry": {"coordinates":[-3.2152578831,55.9492645264],"type":"Point"}
}