{
  "type": "Feature",
  "properties": {
    "addr:full":"55 Melville St Edinburgh City of Edinburgh EH3 7HL",
    "addr:housenumber":"55",
    "addr:postcode":"eh3 7hl",
    "addr:street":"Melville St Edinburgh",
    "iso:country":"GB",
    "sg:address":"55 Melville St",
    "sg:city":"Edinburgh",
    "sg:classifiers":[
        {
            "category":"Wholesale",
            "subcategory":"Books, Periodicals, & Newspapers",
            "type":"Manufacturing & Wholesale Goods"
        }
    ],
    "sg:phone":"+44 131 220 5380",
    "sg:postcode":"EH3 7HL",
    "sg:province":"City of Edinburgh",
    "sg:tags":[
        "publishing"
    ],
    "wof:name":"Johnstone Media Ltd",
    "wof:placetype":"venue"
},
  "geometry": {"coordinates":[-3.2152578831,55.9492645264],"type":"Point"}
}