{
  "type": "Feature",
  "properties": {
    "addr:full":"2 Eaton Road Margate Kent CT9 1XE",
    "addr:housenumber":"2",
    "addr:postcode":"ct9 1xe",
    "addr:street":"Eaton Road",
    "iso:country":"GB",
    "sg:address":"2 Eaton Road",
    "sg:city":"Margate",
    "sg:classifiers":[
        {
            "category":"Health Services",
            "subcategory":"Nursing And Care Facility",
            "type":"Services"
        },
        {
            "category":"Social Services",
            "subcategory":"Retirement Home",
            "type":"Services"
        }
    ],
    "sg:phone":"+44 1843 223240",
    "sg:postcode":"CT9 1XE",
    "sg:province":"Kent",
    "sg:tags":[
        "residential"
    ],
    "wof:name":"Rose Lawn Retirement Home",
    "wof:placetype":"venue"
},
  "geometry": {"coordinates":[1.379663,51.386295],"type":"Point"}
}