{
  "type": "Feature",
  "properties": {
    "iso:country":"GB",
    "sg:address":"55 Irving St",
    "sg:city":"Birmingham",
    "sg:classifiers":[
        {
            "category":"Restaurant",
            "type":"Food & Drink"
        }
    ],
    "sg:phone":"+44 121 622 4925",
    "sg:postcode":"B1 1DH",
    "sg:province":"West Midlands",
    "wof:name":"Hotel Ibis",
    "wof:placetype":"venue"
},
  "geometry": {"coordinates":[-1.9024369717,52.4726829529],"type":"Point"}
}