{
  "type": "Feature",
  "properties": {
    "addr:full":"1216 Melton Rd Leicester Leicestershire LE7 2HB",
    "addr:housenumber":"1216",
    "addr:postcode":"le7 2hb",
    "addr:street":"Melton Rd",
    "iso:country":"GB",
    "sg:address":"1216 Melton Rd",
    "sg:city":"Leicester",
    "sg:classifiers":[
        {
            "category":"Cafe",
            "type":"Food & Drink"
        }
    ],
    "sg:phone":"+44 116 269 8662",
    "sg:postcode":"LE7 2HB",
    "sg:province":"Leicestershire",
    "sg:tags":[
        "tea",
        "room"
    ],
    "wof:name":"Stovies",
    "wof:placetype":"venue"
},
  "geometry": {"coordinates":[-1.0757449865,52.6972427368],"type":"Point"}
}