{
  "type": "Feature",
  "properties": {
    "addr:full":"Unit 12/13, Lincolns Park Business Centre, Lincoln Road High Wycombe Buckinghamshire HP12 3RD",
    "addr:housenumber":"unit 12 / 13",
    "addr:postcode":"hp12 3rd",
    "addr:street":"Lincolns Park;Lincoln Road",
    "iso:country":"GB",
    "sg:address":"Unit 12/13, Lincolns Park Business Centre, Lincoln Road",
    "sg:city":"High Wycombe",
    "sg:classifiers":[
        {
            "category":"Wholesale",
            "subcategory":"Machinery & Supplies",
            "type":"Manufacturing & Wholesale Goods"
        }
    ],
    "sg:phone":"+44 1494 440166",
    "sg:postcode":"HP12 3RD",
    "sg:province":"Buckinghamshire",
    "sg:tags":[
        "equipment",
        "pneumatic",
        "system"
    ],
    "wof:name":"Chiltern Pneumatics Ltd.",
    "wof:placetype":"venue"
},
  "geometry": {"coordinates":[-0.773434,51.62553],"type":"Point"}
}