{
  "type": "Feature",
  "properties": {
    "iso:country":"GB",
    "sg:address":"229 Lower Clapton Road",
    "sg:city":"London",
    "sg:classifiers":[
        {
            "category":"Bars & Pubs",
            "subcategory":"Nightclub",
            "type":"Food & Drink"
        }
    ],
    "sg:phone":"+44 20 8986 2993",
    "sg:postcode":"E5 8EG",
    "sg:province":"Greater London",
    "sg:tags":[
        "club",
        "night",
        "activity"
    ],
    "wof:name":"Elite Nightclub",
    "wof:placetype":"venue"
},
  "geometry": {"coordinates":[-0.056077,51.557232],"type":"Point"}
}