{
  "type": "Feature",
  "properties": {
    "addr:full":"13 High Street Heathfield East Sussex TN21 8LU",
    "addr:housenumber":"13",
    "addr:postcode":"tn21 8lu",
    "addr:street":"High Street",
    "iso:country":"GB",
    "sg:address":"13 High Street",
    "sg:city":"Heathfield",
    "sg:classifiers":[
        {
            "category":"Manufacturing",
            "subcategory":"Petroleum Products",
            "type":"Manufacturing & Wholesale Goods"
        },
        {
            "category":"Building & Trades",
            "subcategory":"Construction",
            "type":"Services"
        }
    ],
    "sg:phone":"+44 1435 866456",
    "sg:postcode":"TN21 8LU",
    "sg:province":"East Sussex",
    "sg:tags":[
        "double",
        "glazing",
        "installers"
    ],
    "wof:name":"Celuclad Ltd.",
    "wof:placetype":"venue"
},
  "geometry": {"coordinates":[0.252529,50.971764],"type":"Point"}
}