{
  "type": "Feature",
  "properties": {
    "iso:country":"GB",
    "sg:address":"Featherston Road",
    "sg:city":"Stevenage",
    "sg:classifiers":[
        {
            "category":"Education",
            "subcategory":"School",
            "type":"Public Place"
        }
    ],
    "sg:phone":"+44 1438 235550",
    "sg:postcode":"SG2 9PP",
    "sg:province":"Hertfordshire",
    "sg:tags":[
        "local",
        "authority"
    ],
    "wof:name":"Featherston Wood Primary School",
    "wof:placetype":"venue"
},
  "geometry": {"coordinates":[-0.1642889977,51.8945655823],"type":"Point"}
}