{
  "type": "Feature",
  "properties": {
    "addr:full":"Nell Gwynn House, Draycott Avenue London Greater London SW3 3AU",
    "addr:postcode":"sw3 3au",
    "addr:street":"Draycott Avenue",
    "iso:country":"GB",
    "sg:address":"Nell Gwynn House, Draycott Avenue",
    "sg:city":"London",
    "sg:classifiers":[
        {
            "category":"Retail",
            "subcategory":"Auto Repair",
            "type":"Services"
        }
    ],
    "sg:phone":"+44 20 7584 8363",
    "sg:postcode":"SW3 3AU",
    "sg:province":"Greater London",
    "sg:tags":[
        "modification",
        "garage"
    ],
    "wof:name":"The Chelsea Workshop Ltd.",
    "wof:placetype":"venue"
},
  "geometry": {"coordinates":[-0.1646299958,51.4917297363],"type":"Point"}
}