{
  "type": "Feature",
  "properties": {
    "iso:country":"GB",
    "sg:address":"36 Lees Road, Mapperley",
    "sg:city":"Nottingham",
    "sg:classifiers":[
        {
            "category":"Manufacturing",
            "subcategory":"Textiles",
            "type":"Manufacturing & Wholesale Goods"
        }
    ],
    "sg:phone":"+44 115 952 1323",
    "sg:postcode":"NG3 6GZ",
    "sg:province":"Nottinghamshire",
    "sg:tags":[
        "designer"
    ],
    "wof:name":"Raberco",
    "wof:placetype":"venue"
},
  "geometry": {"coordinates":[-1.118813,52.977474],"type":"Point"}
}