{
  "type": "Feature",
  "properties": {
    "iso:country":"GB",
    "sg:address":"Foredown Rd",
    "sg:city":"Brighton",
    "sg:classifiers":[
        {
            "category":"Social Services",
            "subcategory":"Retirement Home",
            "type":"Services"
        }
    ],
    "sg:phone":"+44 1273 416977",
    "sg:postcode":"BN41 2FU",
    "sg:province":"East Sussex",
    "sg:tags":[
        "residential",
        "care"
    ],
    "wof:name":"Hillcrest Residential Care",
    "wof:placetype":"venue"
},
  "geometry": {"coordinates":[-0.214139,50.847706],"type":"Point"}
}