{
  "type": "Feature",
  "properties": {
    "addr:full":"12 Haywards Road, Patcham Brighton East Sussex BN1 8TN",
    "addr:housenumber":"12",
    "addr:postcode":"bn1 8tn",
    "addr:street":"Haywards Road",
    "iso:country":"GB",
    "sg:address":"12 Haywards Road, Patcham",
    "sg:city":"Brighton",
    "sg:classifiers":[
        {
            "category":"Building & Trades",
            "subcategory":"Landscaping Services",
            "type":"Services"
        }
    ],
    "sg:postcode":"BN1 8TN",
    "sg:province":"East Sussex",
    "sg:tags":[
        "landscape",
        "contractor"
    ],
    "wof:name":"G J Standen",
    "wof:placetype":"venue"
},
  "geometry": {"coordinates":[-0.1356949955,50.8633460999],"type":"Point"}
}