{
  "type": "Feature",
  "properties": {
    "addr:full":"10 Bridgeman Croft, Castle Bromwich Birmingham West Midlands B36 0AF",
    "addr:housenumber":"10",
    "addr:postcode":"b36 0af",
    "addr:street":"Bridgeman Croft Castle",
    "iso:country":"GB",
    "sg:address":"10 Bridgeman Croft, Castle Bromwich",
    "sg:city":"Birmingham",
    "sg:classifiers":[
        {
            "category":"Building & Trades",
            "subcategory":"Plumbing",
            "type":"Services"
        }
    ],
    "sg:phone":"+44 121 749 4096",
    "sg:postcode":"B36 0AF",
    "sg:province":"West Midlands",
    "sg:tags":[
        "central",
        "heating"
    ],
    "wof:name":"Castle Bromwich Heating & Plumbing",
    "wof:placetype":"venue"
},
  "geometry": {"coordinates":[-1.7741719484,52.503326416],"type":"Point"}
}