{
  "type": "Feature",
  "properties": {
    "addr:full":"Po Box 6329 London Greater London N15 6WP",
    "addr:housenumber":"po",
    "addr:postcode":"n15 6wp",
    "addr:street":"Box 6329",
    "iso:country":"GB",
    "sg:address":"Po Box 6329",
    "sg:city":"London",
    "sg:classifiers":[
        {
            "category":"Utilities",
            "subcategory":"Natural Gas",
            "type":"Services"
        }
    ],
    "sg:phone":"+44 20 8211 0011",
    "sg:postcode":"N15 6WP",
    "sg:province":"Greater London",
    "sg:tags":[
        "supplier"
    ],
    "wof:name":"I C D Gas Ltd.",
    "wof:placetype":"venue"
},
  "geometry": {"coordinates":[-0.0756400004,51.5776786804],"type":"Point"}
}