{
  "type": "Feature",
  "properties": {
    "iso:country":"GB",
    "sg:address":"27 Church Street",
    "sg:city":"Blackpool",
    "sg:classifiers":[
        {
            "category":"Shopping",
            "subcategory":"Mobile Phones",
            "type":"Retail Goods"
        }
    ],
    "sg:phone":"+44 1253 292685",
    "sg:postcode":"FY1 1HJ",
    "sg:province":"Lancashire",
    "sg:tags":[
        "supplier"
    ],
    "wof:name":"Vodafone Retail",
    "wof:placetype":"venue"
},
  "geometry": {"coordinates":[-3.053967,53.817303],"type":"Point"}
}