{
  "type": "Feature",
  "properties": {
    "addr:full":"285 Buchanan Road Sheffield South Yorkshire S5 8AU",
    "addr:housenumber":"285",
    "addr:postcode":"s5 8au",
    "addr:street":"Buchanan Road",
    "iso:country":"GB",
    "sg:address":"285 Buchanan Road",
    "sg:city":"Sheffield",
    "sg:classifiers":[
        {
            "category":"Fast Food",
            "type":"Food & Drink"
        }
    ],
    "sg:phone":"+44 114 232 1728",
    "sg:postcode":"S5 8AU",
    "sg:province":"South Yorkshire",
    "sg:tags":[
        "away",
        "take"
    ],
    "wof:name":"The Golden Palace",
    "wof:placetype":"venue"
},
  "geometry": {"coordinates":[-1.485061,53.426552],"type":"Point"}
}