{
  "type": "Feature",
  "properties": {
    "addr:full":"114 Drury Road Harrow Greater London HA1 4BW",
    "addr:housenumber":"114",
    "addr:postcode":"ha1 4bw",
    "addr:street":"Drury Road",
    "iso:country":"GB",
    "sg:address":"114 Drury Road",
    "sg:city":"Harrow",
    "sg:classifiers":[
        {
            "category":"Building & Trades",
            "subcategory":"Landscaping Services",
            "type":"Services"
        }
    ],
    "sg:phone":"+44 20 8423 3582",
    "sg:postcode":"HA1 4BW",
    "sg:province":"Greater London",
    "sg:tags":[
        "landscape",
        "contractor"
    ],
    "wof:name":"Bill & Ben Landscapes",
    "wof:placetype":"venue"
},
  "geometry": {"coordinates":[-0.3519969881,51.5756759644],"type":"Point"}
}