{
  "type": "Feature",
  "properties": {
    "iso:country":"GB",
    "sg:address":"97-101 Bournemouth Road",
    "sg:city":"Poole",
    "sg:classifiers":[
        {
            "category":"Shopping",
            "subcategory":"Antiques",
            "type":"Retail Goods"
        },
        {
            "category":"Shopping",
            "subcategory":"Used Merchandise",
            "type":"Retail Goods"
        }
    ],
    "sg:postcode":"BH14 0ER",
    "sg:province":"Dorset",
    "sg:tags":[
        "shop",
        "second-hand"
    ],
    "wof:name":"Wiffens Antiques",
    "wof:placetype":"venue"
},
  "geometry": {"coordinates":[-1.9397089481,50.7248764038],"type":"Point"}
}