{
  "type": "Feature",
  "properties": {
    "addr:full":"11 Rivermead Close Gloucester Gloucestershire GL2 9AG",
    "addr:housenumber":"11",
    "addr:postcode":"gl2 9ag",
    "addr:street":"Rivermead Close",
    "iso:country":"GB",
    "sg:address":"11 Rivermead Close",
    "sg:city":"Gloucester",
    "sg:classifiers":[
        {
            "category":"Professional",
            "subcategory":"Art Services",
            "type":"Services"
        },
        {
            "category":"Building & Trades",
            "subcategory":"Construction",
            "type":"Services"
        }
    ],
    "sg:phone":"+44 1452 414987",
    "sg:postcode":"GL2 9AG",
    "sg:province":"Gloucestershire",
    "sg:tags":[
        "decorator",
        "painter"
    ],
    "wof:name":"DAVID HOWARTH",
    "wof:placetype":"venue"
},
  "geometry": {"coordinates":[-2.242349,51.878208],"type":"Point"}
}