{
  "type": "Feature",
  "properties": {
    "addr:full":"35 Kensington Liverpool Merseyside L7 8UX",
    "addr:housenumber":"35",
    "addr:postcode":"l7 8ux",
    "addr:street":"Kensington",
    "iso:country":"GB",
    "sg:address":"35 Kensington",
    "sg:city":"Liverpool",
    "sg:classifiers":[
        {
            "category":"Place Of Worship",
            "type":"Public Place"
        }
    ],
    "sg:phone":"+44 151 264 8044",
    "sg:postcode":"L7 8UX",
    "sg:province":"Merseyside",
    "wof:name":"Seventh Day Adventist Church",
    "wof:placetype":"venue"
},
  "geometry": {"coordinates":[-2.95897,53.411449],"type":"Point"}
}