{
  "type": "Feature",
  "properties": {
    "iso:country":"GB",
    "sg:address":"Unit 21 Johal Building, 11 Nansen Road",
    "sg:city":"Leicester",
    "sg:classifiers":[
        {
            "category":"Professional",
            "subcategory":"Printing & Photocopies",
            "type":"Services"
        }
    ],
    "sg:postcode":"LE5 5FY",
    "sg:province":"Leicestershire",
    "sg:tags":[
        "process",
        "screen",
        "printer"
    ],
    "wof:name":"Venture Graphics Ltd.",
    "wof:placetype":"venue"
},
  "geometry": {"coordinates":[-1.09456,52.63089],"type":"Point"}
}