{
  "type": "Feature",
  "properties": {
    "addr:full":"64 Salacre La, Upton Wirral Merseyside CH42 9NF",
    "addr:housenumber":"64",
    "addr:postcode":"ch42 9nf",
    "addr:street":"Salacre La Upton",
    "iso:country":"GB",
    "sg:address":"64 Salacre La, Upton",
    "sg:city":"Wirral",
    "sg:classifiers":[
        {
            "category":"Building & Trades",
            "subcategory":"Construction",
            "type":"Services"
        }
    ],
    "sg:postcode":"CH42 9NF",
    "sg:province":"Merseyside",
    "sg:tags":[
        "builder"
    ],
    "wof:name":"Smith,Derek E,",
    "wof:placetype":"venue"
},
  "geometry": {"coordinates":[-3.0350699425,53.3819885254],"type":"Point"}
}