{
  "type": "Feature",
  "properties": {
    "addr:full":"115 St Margarets Road Twickenham Greater London TW1 2LH",
    "addr:housenumber":"115",
    "addr:postcode":"tw1 2lh",
    "addr:street":"St Margarets Road",
    "iso:country":"GB",
    "sg:address":"115 St Margarets Road",
    "sg:city":"Twickenham",
    "sg:classifiers":[
        {
            "category":"Food & Beverages",
            "subcategory":"Bakery",
            "type":"Retail Goods"
        }
    ],
    "sg:phone":"+44 20 8892 1980",
    "sg:postcode":"TW1 2LH",
    "sg:province":"Greater London",
    "sg:tags":[
        "baker"
    ],
    "wof:name":"Koblers Anglo-Swiss Confectionary",
    "wof:placetype":"venue"
},
  "geometry": {"coordinates":[-0.319812,51.454983],"type":"Point"}
}