{
  "type": "Feature",
  "properties": {
    "addr:full":"Brookhouse Farm, Newcastle Road Crewe Cheshire CW3 9JT",
    "addr:postcode":"cw3 9jt",
    "addr:street":"Newcastle Road",
    "iso:country":"GB",
    "sg:address":"Brookhouse Farm, Newcastle Road",
    "sg:city":"Crewe",
    "sg:classifiers":[
        {
            "category":"Building & Trades",
            "subcategory":"Equipment Rental",
            "type":"Services"
        }
    ],
    "sg:phone":"+44 1782 751227",
    "sg:postcode":"CW3 9JT",
    "sg:province":"Cheshire",
    "sg:tags":[
        "plant",
        "machinery"
    ],
    "wof:name":"Ashley Plant Hire",
    "wof:placetype":"venue"
},
  "geometry": {"coordinates":[-2.335724,52.996136],"type":"Point"}
}