{
  "type": "Feature",
  "properties": {
    "addr:full":"Queensway House, 57 Livery St Birmingham West Midlands B3 1HA",
    "addr:housenumber":"57",
    "addr:postcode":"b3 1ha",
    "addr:street":"Livery St",
    "iso:country":"GB",
    "sg:address":"Queensway House, 57 Livery St",
    "sg:city":"Birmingham",
    "sg:classifiers":[
        {
            "category":"Real Estate",
            "subcategory":"Surveying",
            "type":"Services"
        }
    ],
    "sg:phone":"+44 121 236 6151",
    "sg:postcode":"B3 1HA",
    "sg:province":"West Midlands",
    "sg:tags":[
        "surveyor",
        "valuer"
    ],
    "wof:name":"T P Edsall",
    "wof:placetype":"venue"
},
  "geometry": {"coordinates":[-1.902121,52.484886],"type":"Point"}
}