{
  "type": "Feature",
  "properties": {
    "addr:full":"Unit 2-6 North Road Industrial Estate Okehampton Devon EX20 1BQ",
    "addr:housenumber":"unit 2-6",
    "addr:postcode":"ex20 1bq",
    "addr:street":"North Road Industrial Estate",
    "iso:country":"GB",
    "sg:address":"Unit 2-6 North Road Industrial Estate",
    "sg:city":"Okehampton",
    "sg:classifiers":[
        {
            "category":"Wholesale",
            "subcategory":"Construction Materials",
            "type":"Manufacturing & Wholesale Goods"
        }
    ],
    "sg:phone":"+44 1837 55442",
    "sg:postcode":"EX20 1BQ",
    "sg:province":"Devon",
    "sg:tags":[
        "sawdust",
        "sawmills",
        "shaving"
    ],
    "wof:name":"Snowflake (Devon)",
    "wof:placetype":"venue"
},
  "geometry": {"coordinates":[-4.0004267693,50.7426681519],"type":"Point"}
}