{
  "type": "Feature",
  "properties": {
    "iso:country":"GB",
    "sg:address":"Beatlands Road",
    "sg:city":"Sidmouth",
    "sg:classifiers":[
        {
            "category":"Travel",
            "subcategory":"Hotels & Motels",
            "type":"Entertainment"
        }
    ],
    "sg:phone":"+44 1395 514697",
    "sg:postcode":"EX10 8JQ",
    "sg:province":"Devon",
    "wof:name":"Salcombe Hill House Hotel",
    "wof:placetype":"venue"
},
  "geometry": {"coordinates":[-3.23423,50.681721],"type":"Point"}
}