{
  "type": "Feature",
  "properties": {
    "addr:full":"Eastern Gardens, Esplanade Ryde Isle of Wight PO33 2DY",
    "addr:postcode":"po33 2dy",
    "addr:street":"Eastern Gardens Esplanade",
    "iso:country":"GB",
    "sg:address":"Eastern Gardens, Esplanade",
    "sg:city":"Ryde",
    "sg:classifiers":[
        {
            "category":"Farming",
            "subcategory":"Fish & Marine Products",
            "type":"Manufacturing & Wholesale Goods"
        }
    ],
    "sg:phone":"+44 1983 812990",
    "sg:postcode":"PO33 2DY",
    "sg:province":"Isle of Wight",
    "sg:tags":[
        "fishmonger"
    ],
    "wof:name":"The Seafood Cabin",
    "wof:placetype":"venue"
},
  "geometry": {"coordinates":[-1.168666,50.727566],"type":"Point"}
}