{
  "type": "Feature",
  "properties": {
    "addr:full":"400 Stamfordham Road Newcastle-upon-tyne Tyne and Wear NE5 5HH",
    "addr:housenumber":"400",
    "addr:postcode":"ne5 5hh",
    "addr:street":"Stamfordham Road",
    "iso:country":"GB",
    "sg:address":"400 Stamfordham Road",
    "sg:city":"Newcastle-upon-tyne",
    "sg:classifiers":[
        {
            "category":"Food & Beverages",
            "subcategory":"Meat & Fish",
            "type":"Retail Goods"
        }
    ],
    "sg:postcode":"NE5 5HH",
    "sg:province":"Tyne and Wear",
    "sg:tags":[
        "chip"
    ],
    "wof:name":"Gorman's Fish Bar",
    "wof:placetype":"venue"
},
  "geometry": {"coordinates":[-1.6949989796,55.0002174377],"type":"Point"}
}