{
  "type": "Feature",
  "properties": {
    "iso:country":"GB",
    "sg:address":"Frithville",
    "sg:city":"Boston",
    "sg:classifiers":[
        {
            "category":"Professional",
            "subcategory":"Engineering",
            "type":"Services"
        }
    ],
    "sg:phone":"+44 1205 750367",
    "sg:postcode":"PE22 7DU",
    "sg:province":"Lincolnshire",
    "sg:tags":[
        "agricultural",
        "engineer"
    ],
    "sg:website":"http://www.rhcrawford.com",
    "wof:name":"Robert H Crawford & Son",
    "wof:placetype":"venue"
},
  "geometry": {"coordinates":[-0.03498,53.036339],"type":"Point"}
}