{
  "type": "Feature",
  "properties": {
    "iso:country":"GB",
    "sg:address":"12 College Place",
    "sg:city":"Southampton",
    "sg:classifiers":[
        {
            "category":"Manufacturing",
            "subcategory":"Tools & Machinery",
            "type":"Manufacturing & Wholesale Goods"
        }
    ],
    "sg:phone":"+44 23 8022 9655",
    "sg:postcode":"SO15 2FE",
    "sg:province":"Hampshire",
    "sg:tags":[
        "society",
        "friendly"
    ],
    "wof:name":"Ancient Order of Foresters",
    "wof:placetype":"venue"
},
  "geometry": {"coordinates":[-1.401965,50.913803],"type":"Point"}
}