{
  "type": "Feature",
  "properties": {
    "addr:full":"11 Marine Parade, Tankerton Whitstable Kent CT5 2BQ",
    "addr:housenumber":"11",
    "addr:postcode":"ct5 2bq",
    "addr:street":"Marine Parade Tankerton Whitstable",
    "iso:country":"GB",
    "sg:address":"11 Marine Parade, Tankerton",
    "sg:city":"Whitstable",
    "sg:classifiers":[
        {
            "category":"Social Services",
            "subcategory":"Retirement Home",
            "type":"Services"
        }
    ],
    "sg:phone":"+44 1227 272281",
    "sg:postcode":"CT5 2BQ",
    "sg:province":"Kent",
    "sg:tags":[
        "residential",
        "care"
    ],
    "wof:name":"Methodist Homes for the Aged",
    "wof:placetype":"venue"
},
  "geometry": {"coordinates":[1.0387949944,51.3644447327],"type":"Point"}
}