{
  "type": "Feature",
  "properties": {
    "addr:full":"12 Brook Square Rugeley Staffordshire WS15 2DR",
    "addr:housenumber":"12",
    "addr:postcode":"ws15 2dr",
    "addr:street":"Brook Square",
    "iso:country":"GB",
    "sg:address":"12 Brook Square",
    "sg:city":"Rugeley",
    "sg:classifiers":[
        {
            "category":"Shopping",
            "subcategory":"Shoes",
            "type":"Retail Goods"
        }
    ],
    "sg:postcode":"WS15 2DR",
    "sg:province":"Staffordshire",
    "sg:tags":[
        "shop"
    ],
    "wof:name":"Wendy's Footwear",
    "wof:placetype":"venue"
},
  "geometry": {"coordinates":[-1.935352,52.757557],"type":"Point"}
}