{
  "type": "Feature",
  "properties": {
    "addr:full":"Gaston Green Bishops Stortford Essex CM22 7QS",
    "addr:postcode":"cm22 7qs",
    "addr:street":"Gaston Green",
    "iso:country":"GB",
    "sg:address":"Gaston Green",
    "sg:city":"Bishops Stortford",
    "sg:classifiers":[
        {
            "category":"Professional",
            "subcategory":"Printing & Photocopies",
            "type":"Services"
        }
    ],
    "sg:phone":"+44 1279 600711",
    "sg:postcode":"CM22 7QS",
    "sg:province":"Essex",
    "sg:tags":[
        "engraving"
    ],
    "wof:name":"F S Group",
    "wof:placetype":"venue"
},
  "geometry": {"coordinates":[0.173793003,51.8402519226],"type":"Point"}
}