{
  "type": "Feature",
  "properties": {
    "addr:full":"33 Hammerwater Drive, Warsop Mansfield Derbyshire NG20 0DJ",
    "addr:housenumber":"33",
    "addr:postcode":"ng20 0dj",
    "addr:street":"Hammerwater Drive",
    "iso:country":"GB",
    "sg:address":"33 Hammerwater Drive, Warsop",
    "sg:city":"Mansfield",
    "sg:classifiers":[
        {
            "category":"Retail",
            "subcategory":"Driving School",
            "type":"Services"
        }
    ],
    "sg:postcode":"NG20 0DJ",
    "sg:province":"Derbyshire",
    "wof:name":"Glenn Clarke",
    "wof:placetype":"venue"
},
  "geometry": {"coordinates":[-1.1605429649,53.2011566162],"type":"Point"}
}