{
  "type": "Feature",
  "properties": {
    "addr:full":"Church Road, Pangbourne Reading Berkshire RG8 7AR",
    "addr:postcode":"rg8 7ar",
    "addr:street":"Church Road",
    "iso:country":"GB",
    "sg:address":"Church Road, Pangbourne",
    "sg:city":"Reading",
    "sg:classifiers":[
        {
            "category":"Bars & Pubs",
            "type":"Food & Drink"
        }
    ],
    "sg:postcode":"RG8 7AR",
    "sg:province":"Berkshire",
    "sg:tags":[
        "pubs",
        "inn"
    ],
    "wof:name":"Greene King Leasing No 1 Ltd.",
    "wof:placetype":"venue"
},
  "geometry": {"coordinates":[-1.0873379707,51.482208252],"type":"Point"}
}