{
  "type": "Feature",
  "properties": {
    "iso:country":"GB",
    "sg:address":"P O Box 1732",
    "sg:city":"Andover",
    "sg:classifiers":[
        {
            "category":"Professional",
            "subcategory":"Business Services",
            "type":"Services"
        }
    ],
    "sg:phone":"+44 1264 337764",
    "sg:postcode":"SP11 7TU",
    "sg:province":"Hampshire",
    "sg:tags":[
        "import",
        "export",
        "agent"
    ],
    "wof:name":"Melaxe Ltd.",
    "wof:placetype":"venue"
},
  "geometry": {"coordinates":[-1.518509,51.176506],"type":"Point"}
}