{
  "type": "Feature",
  "properties": {
    "addr:full":"22 Sanders Drive Colchester Essex CO3 3SG",
    "addr:housenumber":"22",
    "addr:postcode":"co3 3sg",
    "addr:street":"Sanders Drive",
    "iso:country":"GB",
    "sg:address":"22 Sanders Drive",
    "sg:city":"Colchester",
    "sg:classifiers":[
        {
            "category":"Shopping",
            "subcategory":"Stationery & Office Supplies",
            "type":"Retail Goods"
        }
    ],
    "sg:phone":"+44 1206 766272",
    "sg:postcode":"CO3 3SG",
    "sg:province":"Essex",
    "sg:tags":[
        "postcard"
    ],
    "wof:name":"Maxam Cards",
    "wof:placetype":"venue"
},
  "geometry": {"coordinates":[0.8747429848,51.89012146],"type":"Point"}
}