{
  "type": "Feature",
  "properties": {
    "addr:full":"153 Congleton Road Macclesfield Cheshire SK11 7XD",
    "addr:housenumber":"153",
    "addr:postcode":"sk11 7xd",
    "addr:street":"Congleton Road",
    "iso:country":"GB",
    "sg:address":"153 Congleton Road",
    "sg:city":"Macclesfield",
    "sg:classifiers":[
        {
            "category":"Professional",
            "subcategory":"Engineering",
            "type":"Services"
        },
        {
            "category":"Building & Trades",
            "subcategory":"Electrical",
            "type":"Services"
        }
    ],
    "sg:phone":"+44 1625 619943",
    "sg:postcode":"SK11 7XD",
    "sg:province":"Cheshire",
    "sg:tags":[
        "engineer",
        "electrician",
        "contractor"
    ],
    "wof:name":"Mark A Russell",
    "wof:placetype":"venue"
},
  "geometry": {"coordinates":[-2.1501870155,53.2425346375],"type":"Point"}
}