{
  "type": "Feature",
  "properties": {
    "addr:full":"46 Gunter Gro London Greater London SW10 0UJ",
    "addr:housenumber":"46",
    "addr:postcode":"sw10 0uj",
    "addr:street":"Gunter Gro",
    "iso:country":"GB",
    "sg:address":"46 Gunter Gro",
    "sg:city":"London",
    "sg:classifiers":[
        {
            "category":"Organizations",
            "subcategory":"Membership Organization",
            "type":"Services"
        }
    ],
    "sg:phone":"+44 20 7823 3341",
    "sg:postcode":"SW10 0UJ",
    "sg:province":"Greater London",
    "sg:tags":[
        "club"
    ],
    "wof:name":"46 Gunter Grove Management Ltd.",
    "wof:placetype":"venue"
},
  "geometry": {"coordinates":[-0.183599,51.481312],"type":"Point"}
}