{
  "type": "Feature",
  "properties": {
    "addr:full":"75 High Street Bedford Bedfordshire MK40 1NE",
    "addr:housenumber":"75",
    "addr:postcode":"mk40 1ne",
    "addr:street":"High Street",
    "iso:country":"GB",
    "sg:address":"75 High Street",
    "sg:city":"Bedford",
    "sg:classifiers":[
        {
            "category":"Shopping",
            "subcategory":"Clothing, Apparel, & Fashions",
            "type":"Retail Goods"
        }
    ],
    "sg:phone":"+44 1234 211416",
    "sg:postcode":"MK40 1NE",
    "sg:province":"Bedfordshire",
    "sg:tags":[
        "shop"
    ],
    "wof:name":"Laura Ashley",
    "wof:placetype":"venue"
},
  "geometry": {"coordinates":[-0.466477,52.1371],"type":"Point"}
}