{
  "type": "Feature",
  "properties": {
    "iso:country":"GB",
    "sg:address":"Cedarbank, Ladywell",
    "sg:city":"Livingston",
    "sg:classifiers":[
        {
            "category":"Education",
            "subcategory":"Special Training",
            "type":"Public Place"
        },
        {
            "category":"Education",
            "subcategory":"School",
            "type":"Public Place"
        },
        {
            "category":"Government",
            "subcategory":"Office",
            "type":"Public Place"
        }
    ],
    "sg:phone":"+44 1506 442172",
    "sg:postcode":"EH54 6DR",
    "sg:province":"West Lothian",
    "sg:tags":[
        "local"
    ],
    "wof:name":"Cedarbank Special School",
    "wof:placetype":"venue"
},
  "geometry": {"coordinates":[-3.509834,55.886246],"type":"Point"}
}