{
  "type": "Feature",
  "properties": {
    "addr:full":"Unit 11 Central Warehouse, Lincoln Street Rotherham South Yorkshire S60 1RP",
    "addr:housenumber":"unit 11",
    "addr:postcode":"s60 1rp",
    "addr:street":"Central;Lincoln Street",
    "iso:country":"GB",
    "sg:address":"Unit 11 Central Warehouse, Lincoln Street",
    "sg:city":"Rotherham",
    "sg:classifiers":[
        {
            "category":"Home & Garden",
            "subcategory":"Home Furnishings",
            "type":"Retail Goods"
        }
    ],
    "sg:phone":"+44 1709 837378",
    "sg:postcode":"S60 1RP",
    "sg:province":"South Yorkshire",
    "sg:tags":[
        "beds",
        "bedding",
        "blanket"
    ],
    "wof:name":"Brittain Lawson & Son",
    "wof:placetype":"venue"
},
  "geometry": {"coordinates":[-1.354243,53.429874],"type":"Point"}
}