{
  "type": "Feature",
  "properties": {
    "iso:country":"GB",
    "sg:address":"22 Derby Rd",
    "sg:city":"Cambridge",
    "sg:classifiers":[
        {
            "category":"Professional",
            "subcategory":"Art Services",
            "type":"Services"
        }
    ],
    "sg:postcode":"CB1 7BU",
    "sg:province":"Cambridgeshire",
    "sg:tags":[
        "photographer",
        "graphic",
        "designer"
    ],
    "wof:name":"Norman,Jane,",
    "wof:placetype":"venue"
},
  "geometry": {"coordinates":[0.142942,52.188427],"type":"Point"}
}