{
  "type": "Feature",
  "properties": {
    "addr:full":"Nursery Lane Surgery, Nursery La Halifax West Yorkshire HX3 5TE",
    "addr:postcode":"hx3 5te",
    "addr:street":"Nursery;La;West",
    "iso:country":"GB",
    "sg:address":"Nursery Lane Surgery, Nursery La",
    "sg:city":"Halifax",
    "sg:classifiers":[
        {
            "category":"Health Services",
            "subcategory":"Doctor",
            "type":"Services"
        }
    ],
    "sg:phone":"+44 1422 345798",
    "sg:postcode":"HX3 5TE",
    "sg:province":"West Yorkshire",
    "sg:tags":[
        "practitioners"
    ],
    "wof:name":"Rastall, M",
    "wof:placetype":"venue"
},
  "geometry": {"coordinates":[-1.881019,53.742016],"type":"Point"}
}