{
  "type": "Feature",
  "properties": {
    "iso:country":"GB",
    "sg:address":"2a West Bar Street",
    "sg:city":"Banbury",
    "sg:classifiers":[
        {
            "category":"Professional",
            "subcategory":"Printing & Photocopies",
            "type":"Services"
        }
    ],
    "sg:phone":"+44 1295 271838",
    "sg:postcode":"OX16 9RR",
    "sg:province":"Oxfordshire",
    "sg:tags":[
        "printer"
    ],
    "wof:name":"Kall Kwik Printing Centre 1233",
    "wof:placetype":"venue"
},
  "geometry": {"coordinates":[-1.340542,52.060188],"type":"Point"}
}