{
  "type": "Feature",
  "properties": {
    "addr:full":"6 Singer Road, Kelvin Industrial Estate Glasgow South Lanarkshire G75 0XS",
    "addr:housenumber":"6",
    "addr:postcode":"g75 0xs",
    "addr:street":"Singer Road Kelvin Industrial Estate",
    "iso:country":"GB",
    "sg:address":"6 Singer Road, Kelvin Industrial Estate",
    "sg:city":"Glasgow",
    "sg:classifiers":[
        {
            "category":"Manufacturing",
            "subcategory":"Electronics",
            "type":"Manufacturing & Wholesale Goods"
        },
        {
            "category":"Military Area",
            "subcategory":"Air Force Base",
            "type":"Public Place"
        }
    ],
    "sg:phone":"+44 1355 249225",
    "sg:postcode":"G75 0XS",
    "sg:province":"South Lanarkshire",
    "sg:tags":[
        "control",
        "laser",
        "-",
        "component",
        "cutting",
        "electronic"
    ],
    "wof:name":"Quality Components Ltd.",
    "wof:placetype":"venue"
},
  "geometry": {"coordinates":[-4.1707382202,55.748626709],"type":"Point"}
}