{
  "type": "Feature",
  "properties": {
    "addr:full":"30 John Kempe Way Birmingham West Midlands B12 0HU",
    "addr:housenumber":"30",
    "addr:postcode":"b12 0hu",
    "addr:street":"John Kempe Way",
    "iso:country":"GB",
    "sg:address":"30 John Kempe Way",
    "sg:city":"Birmingham",
    "sg:classifiers":[
        {
            "category":"Government",
            "subcategory":"Department Of Motor Vehicles",
            "type":"Public Place"
        }
    ],
    "sg:postcode":"B12 0HU",
    "sg:province":"West Midlands",
    "sg:tags":[
        "machine",
        "industrial",
        "sewing"
    ],
    "wof:name":"Protector Ltd",
    "wof:placetype":"venue"
},
  "geometry": {"coordinates":[-1.880015,52.46703],"type":"Point"}
}