{
  "type": "Feature",
  "properties": {
    "iso:country":"GB",
    "sg:address":"Southover High Street",
    "sg:city":"Lewes",
    "sg:classifiers":[
        {
            "category":"Bars & Pubs",
            "type":"Food & Drink"
        }
    ],
    "sg:phone":"+44 1273 480211",
    "sg:postcode":"BN7 1HU",
    "sg:province":"East Sussex",
    "sg:tags":[
        "pubs",
        "inn"
    ],
    "wof:name":"The Swan Inn",
    "wof:placetype":"venue"
},
  "geometry": {"coordinates":[0.006885,50.869373],"type":"Point"}
}