{
  "type": "Feature",
  "properties": {
    "addr:full":"40 Farne Av Wakefield West Yorkshire WF2 9ED",
    "addr:housenumber":"40",
    "addr:postcode":"wf2 9ed",
    "addr:street":"Farne Av Wakefield West",
    "iso:country":"GB",
    "sg:address":"40 Farne Av",
    "sg:city":"Wakefield",
    "sg:classifiers":[
        {
            "category":"Autos & Motor Vehicles",
            "subcategory":"Auto Supplies",
            "type":"Retail Goods"
        }
    ],
    "sg:phone":"+44 1924 370233",
    "sg:postcode":"WF2 9ED",
    "sg:province":"West Yorkshire",
    "sg:tags":[
        "electric"
    ],
    "wof:name":"Horbury Rewind Service",
    "wof:placetype":"venue"
},
  "geometry": {"coordinates":[-1.5216150284,53.6803092957],"type":"Point"}
}