{
  "type": "Feature",
  "properties": {
    "addr:full":"708 Great Horton Road Bradford West Yorkshire BD7 4EY",
    "addr:housenumber":"708",
    "addr:postcode":"bd7 4ey",
    "addr:street":"Great Horton Road",
    "iso:country":"GB",
    "sg:address":"708 Great Horton Road",
    "sg:city":"Bradford",
    "sg:classifiers":[
        {
            "category":"Professional",
            "subcategory":"Testing Lab",
            "type":"Services"
        },
        {
            "category":"Retail",
            "subcategory":"Auto Repair",
            "type":"Services"
        }
    ],
    "sg:phone":"+44 1274 572157",
    "sg:postcode":"BD7 4EY",
    "sg:province":"West Yorkshire",
    "sg:tags":[
        "garage",
        "related",
        "mot"
    ],
    "wof:name":"Gohil Motors",
    "wof:placetype":"venue"
},
  "geometry": {"coordinates":[-1.78779,53.77924],"type":"Point"}
}