{
  "type": "Feature",
  "properties": {
    "iso:country":"GB",
    "sg:address":"Kershaw Lane, Off Audenshaw Road, Audenshaw",
    "sg:city":"Manchester",
    "sg:classifiers":[
        {
            "category":"Education",
            "subcategory":"Preschool",
            "type":"Public Place"
        }
    ],
    "sg:phone":"+44 161 301 3520",
    "sg:postcode":"M34 5WS",
    "sg:province":"Greater Manchester",
    "sg:tags":[
        "pre",
        "school",
        "playgroups",
        "pre-school"
    ],
    "wof:name":"PEACOCK PRE-SCHOOL",
    "wof:placetype":"venue"
},
  "geometry": {"coordinates":[-2.1356389523,53.479888916],"type":"Point"}
}