{
  "type": "Feature",
  "properties": {
    "addr:full":"Northway Centre, Dora Carr Close, Headington Oxford Oxfordshire OX3 9RU",
    "addr:postcode":"ox3 9ru",
    "addr:street":"Dora Carr Close",
    "iso:country":"GB",
    "sg:address":"Northway Centre, Dora Carr Close, Headington",
    "sg:city":"Oxford",
    "sg:classifiers":[
        {
            "category":"Education",
            "subcategory":"University",
            "type":"Public Place"
        }
    ],
    "sg:phone":"+44 1865 768359",
    "sg:postcode":"OX3 9RU",
    "sg:province":"Oxfordshire",
    "sg:tags":[
        "adult"
    ],
    "wof:name":"Oxfordshire County Council",
    "wof:placetype":"venue"
},
  "geometry": {"coordinates":[-1.218379,51.757835],"type":"Point"}
}