{
  "type": "Feature",
  "properties": {
    "addr:full":"1 Peterville St Agnes Cornwall TR5 0QU",
    "addr:housenumber":"1",
    "addr:postcode":"tr5 0qu",
    "addr:street":"Peterville St",
    "iso:country":"GB",
    "sg:address":"1 Peterville",
    "sg:city":"St Agnes",
    "sg:classifiers":[
        {
            "category":"Bars & Pubs",
            "type":"Food & Drink"
        }
    ],
    "sg:phone":"+44 1872 553095",
    "sg:postcode":"TR5 0QU",
    "sg:province":"Cornwall",
    "sg:tags":[
        "pubs",
        "inn"
    ],
    "wof:name":"The Tap House",
    "wof:placetype":"venue"
},
  "geometry": {"coordinates":[-5.1991991997,50.3120994568],"type":"Point"}
}