{
  "type": "Feature",
  "properties": {
    "iso:country":"GB",
    "sg:address":"12 Montfort Place, Wimbledon",
    "sg:city":"London",
    "sg:classifiers":[
        {
            "category":"Personal",
            "subcategory":"Beauty Salon",
            "type":"Services"
        }
    ],
    "sg:phone":"+44 20 8788 7726",
    "sg:postcode":"SW19 6QL",
    "sg:province":"Greater London",
    "sg:tags":[
        "lady",
        "hairdresser"
    ],
    "wof:name":"Highlights",
    "wof:placetype":"venue"
},
  "geometry": {"coordinates":[-0.2175869942,51.4470252991],"type":"Point"}
}