{
  "type": "Feature",
  "properties": {
    "iso:country":"GB",
    "sg:address":"Unit 19 Navigation Business Vill, Age Navigation Wa",
    "sg:city":"Preston",
    "sg:classifiers":[
        {
            "category":"Banks & Credit Unions",
            "subcategory":"Investment Brokerage",
            "type":"Services"
        },
        {
            "category":"Banks & Credit Unions",
            "subcategory":"Bank",
            "type":"Services"
        },
        {
            "category":"Banks & Credit Unions",
            "subcategory":"Financial Services",
            "type":"Services"
        }
    ],
    "sg:phone":"+44 1772 729742",
    "sg:postcode":"PR2 2YP",
    "sg:province":"Lancashire",
    "sg:tags":[
        "consultant",
        "broker",
        "mortgage"
    ],
    "sg:website":"http://www.springfield-financial.co.uk",
    "wof:name":"Springfield Financial Services Ltd",
    "wof:placetype":"venue"
},
  "geometry": {"coordinates":[-2.744316,53.761452],"type":"Point"}
}