{
  "type": "Feature",
  "properties": {
    "addr:full":"The Unit, Mount Pleasant, Denby Road Ripley Derbyshire DE5 8NN",
    "addr:housenumber":"unit mount",
    "addr:postcode":"de5 8nn",
    "addr:street":"Denby Road",
    "iso:country":"GB",
    "sg:address":"The Unit, Mount Pleasant, Denby Road",
    "sg:city":"Ripley",
    "sg:classifiers":[
        {
            "category":"Manufacturing",
            "subcategory":"Wood Products",
            "type":"Manufacturing & Wholesale Goods"
        },
        {
            "category":"Manufacturing",
            "subcategory":"Lumber",
            "type":"Manufacturing & Wholesale Goods"
        }
    ],
    "sg:phone":"+44 1773 570577",
    "sg:postcode":"DE5 8NN",
    "sg:province":"Derbyshire",
    "sg:tags":[
        "merchants",
        "joinery",
        "agent",
        "importer",
        "timber",
        "manufacturer"
    ],
    "wof:name":"Mitech Joinery",
    "wof:placetype":"venue"
},
  "geometry": {"coordinates":[-1.412279,53.012726],"type":"Point"}
}