{
  "type": "Feature",
  "properties": {
    "addr:full":"59 East Street Stanley Durham DH9 0UF",
    "addr:housenumber":"59",
    "addr:postcode":"dh9 0uf",
    "addr:street":"East Street",
    "iso:country":"GB",
    "sg:address":"59 East Street",
    "sg:city":"Stanley",
    "sg:classifiers":[
        {
            "category":"Professional",
            "subcategory":"Engineering",
            "type":"Services"
        }
    ],
    "sg:postcode":"DH9 0UF",
    "sg:province":"Durham",
    "wof:name":"H H Belgers",
    "wof:placetype":"venue"
},
  "geometry": {"coordinates":[-1.679859,54.874371],"type":"Point"}
}