{
  "type": "Feature",
  "properties": {
    "iso:country":"GB",
    "sg:address":"Glidden",
    "sg:city":"Waterlooville",
    "sg:classifiers":[
        {
            "category":"Professional",
            "subcategory":"Engineering",
            "type":"Services"
        }
    ],
    "sg:phone":"+44 23 9263 2506",
    "sg:postcode":"PO7 4SD",
    "sg:province":"Hampshire",
    "sg:tags":[
        "consultant",
        "structural"
    ],
    "wof:name":"G E Robertson",
    "wof:placetype":"venue"
},
  "geometry": {"coordinates":[-1.0701479912,50.9334869385],"type":"Point"}
}