{
  "type": "Feature",
  "properties": {
    "addr:full":"12-14 Gowthorpe Selby East Riding of Yorkshire YO8 4ET",
    "addr:housenumber":"12-14",
    "addr:postcode":"yo8 4et",
    "addr:street":"Gowthorpe",
    "iso:country":"GB",
    "sg:address":"12-14 Gowthorpe",
    "sg:city":"Selby",
    "sg:classifiers":[
        {
            "category":"Shopping",
            "subcategory":"Pharmacy",
            "type":"Retail Goods"
        }
    ],
    "sg:phone":"+44 1757 709463",
    "sg:postcode":"YO8 4ET",
    "sg:province":"East Riding of Yorkshire",
    "sg:tags":[
        "store",
        "drug"
    ],
    "wof:name":"Superdrug Stores Plc",
    "wof:placetype":"venue"
},
  "geometry": {"coordinates":[-1.070082,53.784019],"type":"Point"}
}