{
  "type": "Feature",
  "properties": {
    "addr:full":"6 Clarence Terrace, Warwick Street Leamington Spa Warwickshire CV32 5LD",
    "addr:housenumber":"6",
    "addr:postcode":"cv32 5ld",
    "addr:street":"Clarence Terrace Warwick Street",
    "iso:country":"GB",
    "sg:address":"6 Clarence Terrace, Warwick Street",
    "sg:city":"Leamington Spa",
    "sg:classifiers":[
        {
            "category":"Organizations",
            "subcategory":"Membership Organization",
            "type":"Services"
        }
    ],
    "sg:phone":"+44 1926 424112",
    "sg:postcode":"CV32 5LD",
    "sg:province":"Warwickshire",
    "sg:tags":[
        "club"
    ],
    "wof:name":"The Odd Fellows Friendly Society",
    "wof:placetype":"venue"
},
  "geometry": {"coordinates":[-1.539656,52.291721],"type":"Point"}
}