{
  "type": "Feature",
  "properties": {
    "iso:country":"GB",
    "sg:address":"Doncaster Road",
    "sg:city":"Rotherham",
    "sg:classifiers":[
        {
            "category":"Shopping",
            "subcategory":"Clothing, Apparel, & Fashions",
            "type":"Retail Goods"
        }
    ],
    "sg:phone":"+44 1709 378239",
    "sg:postcode":"S65 2UF",
    "sg:province":"South Yorkshire",
    "sg:tags":[
        "clothing",
        "fabric"
    ],
    "wof:name":"S R Gent",
    "wof:placetype":"venue"
},
  "geometry": {"coordinates":[-1.324774,53.440372],"type":"Point"}
}