{
  "type": "Feature",
  "properties": {
    "addr:full":"Unit 254 9 Slater St Liverpool Merseyside L1 4BW",
    "addr:housenumber":"254 9",
    "addr:postcode":"l1 4bw",
    "addr:street":"Slater St",
    "iso:country":"GB",
    "sg:address":"Unit 254 9 Slater St",
    "sg:city":"Liverpool",
    "sg:classifiers":[
        {
            "category":"Professional",
            "subcategory":"Art Services",
            "type":"Services"
        }
    ],
    "sg:phone":"+44 151 707 9228",
    "sg:postcode":"L1 4BW",
    "sg:province":"Merseyside",
    "sg:tags":[
        "graphic",
        "designer"
    ],
    "wof:name":"Future Design & Marketing",
    "wof:placetype":"venue"
},
  "geometry": {"coordinates":[-2.9790539742,53.4028244019],"type":"Point"}
}