{
  "type": "Feature",
  "properties": {
    "iso:country":"GB",
    "sg:address":"24 Woodfield Street, Morriston",
    "sg:city":"Swansea",
    "sg:classifiers":[
        {
            "category":"Real Estate",
            "subcategory":"Real Estate Agent",
            "type":"Services"
        }
    ],
    "sg:phone":"+44 1792 700456",
    "sg:postcode":"SA6 8AB",
    "sg:province":"Swansea",
    "wof:name":"Ashley Jones & Partners",
    "wof:placetype":"venue"
},
  "geometry": {"coordinates":[-3.925669,51.665154],"type":"Point"}
}