{
  "type": "Feature",
  "properties": {
    "iso:country":"GB",
    "sg:address":"Century House, 100 Stratford Rd, Shirley",
    "sg:city":"Birmingham",
    "sg:classifiers":[
        {
            "category":"Retail",
            "subcategory":"Auto Rental",
            "type":"Services"
        }
    ],
    "sg:phone":"+44 121 733 3311",
    "sg:postcode":"B90 3BH",
    "sg:province":"West Midlands",
    "sg:tags":[
        "car",
        "hire",
        "truck"
    ],
    "wof:name":"British Car Contracts Ltd",
    "wof:placetype":"venue"
},
  "geometry": {"coordinates":[-1.829024,52.414902],"type":"Point"}
}