{
  "type": "Feature",
  "properties": {
    "addr:full":"154 Kennington Lane Lambeth Greater London SE11 4EZ",
    "addr:housenumber":"154",
    "addr:postcode":"se11 4ez",
    "addr:street":"Kennington Lane",
    "iso:country":"GB",
    "sg:address":"154 Kennington Lane",
    "sg:city":"Lambeth",
    "sg:classifiers":[
        {
            "category":"Organizations",
            "subcategory":"Non-profit Organization",
            "type":"Services"
        }
    ],
    "sg:phone":"+44 20 7820 6487",
    "sg:postcode":"SE11 4EZ",
    "sg:province":"Greater London",
    "sg:tags":[
        "organisation",
        "voluntary",
        "charity"
    ],
    "wof:name":"The Place to Be",
    "wof:placetype":"venue"
},
  "geometry": {"coordinates":[-0.108096,51.486454],"type":"Point"}
}