{
  "type": "Feature",
  "properties": {
    "addr:full":"Diddington Hall, Kenilworth Road Coventry Warwickshire CV7 7HQ",
    "addr:housenumber":"diddington",
    "addr:postcode":"cv7 7hq",
    "addr:street":"Hall Kenilworth Road",
    "iso:country":"GB",
    "sg:address":"Diddington Hall, Kenilworth Road",
    "sg:city":"Coventry",
    "sg:classifiers":[
        {
            "category":"Building & Trades",
            "subcategory":"Construction",
            "type":"Services"
        }
    ],
    "sg:phone":"+44 1675 444222",
    "sg:postcode":"CV7 7HQ",
    "sg:province":"Warwickshire",
    "sg:tags":[
        "builder"
    ],
    "wof:name":"Chase Norton Maintenance",
    "wof:placetype":"venue"
},
  "geometry": {"coordinates":[-1.6875300407,52.4421005249],"type":"Point"}
}