{
  "type": "Feature",
  "properties": {
    "iso:country":"GB",
    "sg:address":"Stainforth Basin, Stainforth",
    "sg:city":"Doncaster",
    "sg:classifiers":[
        {
            "category":"Recreation",
            "subcategory":"Marina",
            "type":"Entertainment"
        }
    ],
    "sg:phone":"+44 1302 846720",
    "sg:postcode":"DN3 1AA",
    "sg:province":"South Yorkshire",
    "wof:name":"Thorne Cruising Club",
    "wof:placetype":"venue"
},
  "geometry": {"coordinates":[-1.065614,53.579899],"type":"Point"}
}