{
  "type": "Feature",
  "properties": {
    "iso:country":"GB",
    "sg:address":"62a Bootham",
    "sg:city":"York",
    "sg:classifiers":[
        {
            "category":"Manufacturing",
            "subcategory":"Tools & Machinery",
            "type":"Manufacturing & Wholesale Goods"
        }
    ],
    "sg:phone":"+44 1904 647916",
    "sg:postcode":"YO3 7BZ",
    "sg:province":"East Riding of Yorkshire",
    "sg:tags":[
        "society",
        "friendly"
    ],
    "wof:name":"Gardners Financial Services Ltd",
    "wof:placetype":"venue"
},
  "geometry": {"coordinates":[-1.088430047,53.9643669128],"type":"Point"}
}