{
  "type": "Feature",
  "properties": {
    "iso:country":"GB",
    "sg:address":"202 High Street",
    "sg:city":"Cheltenham",
    "sg:classifiers":[
        {
            "category":"Personal",
            "subcategory":"Shoe Repair & Shine",
            "type":"Services"
        },
        {
            "category":"Shopping",
            "subcategory":"Shoes",
            "type":"Retail Goods"
        }
    ],
    "sg:phone":"+44 1242 235494",
    "sg:postcode":"GL50 3HD",
    "sg:province":"Gloucestershire",
    "wof:name":"Cobblers Corner",
    "wof:placetype":"venue"
},
  "geometry": {"coordinates":[-2.075409,51.901459],"type":"Point"}
}