{
  "type": "Feature",
  "properties": {
    "iso:country":"GB",
    "sg:address":"7-11 Woodcote Road",
    "sg:city":"Wallington",
    "sg:classifiers":[
        {
            "category":"Wholesale",
            "subcategory":"Scrap",
            "type":"Manufacturing & Wholesale Goods"
        }
    ],
    "sg:postcode":"SM6 0LH",
    "sg:province":"Surrey",
    "sg:tags":[
        "car",
        "breaker",
        "dismantlers"
    ],
    "wof:name":"Charlton Motor Works Ltd",
    "wof:placetype":"venue"
},
  "geometry": {"coordinates":[-0.14906,51.357094],"type":"Point"}
}