{
  "type": "Feature",
  "properties": {
    "iso:country":"GB",
    "sg:address":"Oakeys Farm, O'keys Lane, Fernhill Heath",
    "sg:city":"Worcester",
    "sg:classifiers":[
        {
            "category":"Farming",
            "subcategory":"Dairy Farm",
            "type":"Manufacturing & Wholesale Goods"
        }
    ],
    "sg:phone":"+44 1905 452360",
    "sg:postcode":"WR3 8RL",
    "sg:province":"Worcestershire",
    "wof:name":"C A Bowen",
    "wof:placetype":"venue"
},
  "geometry": {"coordinates":[-2.1885,52.229309],"type":"Point"}
}