{
  "type": "Feature",
  "properties": {
    "iso:country":"GB",
    "sg:address":"9 Blackmore Drive",
    "sg:city":"Bath",
    "sg:classifiers":[
        {
            "category":"Building & Trades",
            "subcategory":"Plumbing",
            "type":"Services"
        }
    ],
    "sg:phone":"+44 1225 330908",
    "sg:postcode":"BA2 1JW",
    "sg:province":"Somerset",
    "sg:tags":[
        "central",
        "heating"
    ],
    "wof:name":"Paul Reynolds",
    "wof:placetype":"venue"
},
  "geometry": {"coordinates":[-2.388631,51.375725],"type":"Point"}
}