{
  "type": "Feature",
  "properties": {
    "iso:country":"GB",
    "sg:address":"Mill Bank Farm, Mill La, Goostrey",
    "sg:city":"Crewe",
    "sg:classifiers":[
        {
            "category":"Farming",
            "subcategory":"Livestock Farm",
            "type":"Manufacturing & Wholesale Goods"
        }
    ],
    "sg:postcode":"CW4 8PW",
    "sg:province":"Cheshire",
    "sg:tags":[
        "others"
    ],
    "wof:name":"Goostrey,R L,",
    "wof:placetype":"venue"
},
  "geometry": {"coordinates":[-2.341768,53.227795],"type":"Point"}
}