{
  "type": "Feature",
  "properties": {
    "iso:country":"GB",
    "sg:address":"50 Bolton Street",
    "sg:city":"Chorley",
    "sg:classifiers":[
        {
            "category":"Food & Beverages",
            "subcategory":"Meat & Fish",
            "type":"Retail Goods"
        }
    ],
    "sg:postcode":"PR7 3DL",
    "sg:province":"Lancashire",
    "sg:tags":[
        "butcher"
    ],
    "wof:name":"J M Higgens & Sons",
    "wof:placetype":"venue"
},
  "geometry": {"coordinates":[-2.624772,53.645653],"type":"Point"}
}