{
  "type": "Feature",
  "properties": {
    "iso:country":"GB",
    "sg:address":"95 High St",
    "sg:city":"Tonbridge",
    "sg:classifiers":[
        {
            "category":"Banks & Credit Unions",
            "subcategory":"Investment Brokerage",
            "type":"Services"
        }
    ],
    "sg:phone":"+44 1732 360029",
    "sg:postcode":"TN9 1DR",
    "sg:province":"Kent",
    "sg:tags":[
        "fund",
        "raising"
    ],
    "wof:name":"Senateview Ltd",
    "wof:placetype":"venue"
},
  "geometry": {"coordinates":[0.275297,51.19556],"type":"Point"}
}