{
  "type": "Feature",
  "properties": {
    "addr:full":"Station Road, Norwood Grn Halifax West Yorkshire HX3 8QD",
    "addr:postcode":"hx3 8qd",
    "addr:street":"Station Road;Grn",
    "iso:country":"GB",
    "sg:address":"Station Road, Norwood Grn",
    "sg:city":"Halifax",
    "sg:classifiers":[
        {
            "category":"Bars & Pubs",
            "type":"Food & Drink"
        }
    ],
    "sg:phone":"+44 1274 676036",
    "sg:postcode":"HX3 8QD",
    "sg:province":"West Yorkshire",
    "sg:tags":[
        "pubs",
        "inn"
    ],
    "wof:name":"The Pear Tree Inn",
    "wof:placetype":"venue"
},
  "geometry": {"coordinates":[-1.8181979656,53.7244415283],"type":"Point"}
}