{
  "type": "Feature",
  "properties": {
    "addr:full":"108 Garrison Lane Birmingham West Midlands B9 4BS",
    "addr:housenumber":"108",
    "addr:postcode":"b9 4bs",
    "addr:street":"Garrison Lane",
    "iso:country":"GB",
    "sg:address":"108 Garrison Lane",
    "sg:city":"Birmingham",
    "sg:classifiers":[
        {
            "category":"Deli",
            "type":"Food & Drink"
        }
    ],
    "sg:phone":"+44 121 772 2514",
    "sg:postcode":"B9 4BS",
    "sg:province":"West Midlands",
    "sg:tags":[
        "delivery",
        "sandwich"
    ],
    "wof:name":"The Griffin Sandwich Bar & Newsagents",
    "wof:placetype":"venue"
},
  "geometry": {"coordinates":[-1.874207,52.480545],"type":"Point"}
}