{
  "type": "Feature",
  "properties": {
    "iso:country":"GB",
    "sg:address":"1 The Maltings",
    "sg:city":"Uttoxeter",
    "sg:classifiers":[
        {
            "category":"Home & Garden",
            "subcategory":"Kitchen Supply",
            "type":"Retail Goods"
        }
    ],
    "sg:phone":"+44 1889 565328",
    "sg:postcode":"ST14 7LN",
    "sg:province":"Derbyshire",
    "sg:tags":[
        "glassware",
        "china"
    ],
    "wof:name":"County China & Glass",
    "wof:placetype":"venue"
},
  "geometry": {"coordinates":[-1.865519,52.899891],"type":"Point"}
}