{
  "type": "Feature",
  "properties": {
    "addr:full":"Grampian Rd Elgin Moray IV30 1XN",
    "addr:postcode":"iv30 1xn",
    "addr:street":"Grampian Rd",
    "iso:country":"GB",
    "sg:address":"Grampian Rd",
    "sg:city":"Elgin",
    "sg:classifiers":[
        {
            "category":"Retail",
            "subcategory":"Storage",
            "type":"Services"
        }
    ],
    "sg:phone":"+44 1343 547050",
    "sg:postcode":"IV30 1XN",
    "sg:province":"Moray",
    "sg:tags":[
        "household",
        "removal"
    ],
    "wof:name":"Pickfords Removals",
    "wof:placetype":"venue"
},
  "geometry": {"coordinates":[-3.317868948,57.6493682861],"type":"Point"}
}