{
  "type": "Feature",
  "properties": {
    "addr:full":"Rear Of 5-7 Reede Road Dagenham Essex RM10 8DP",
    "addr:housenumber":"rear of 5-7",
    "addr:postcode":"rm10 8dp",
    "addr:street":"Reede Road",
    "iso:country":"GB",
    "sg:address":"Rear Of 5-7 Reede Road",
    "sg:city":"Dagenham",
    "sg:classifiers":[
        {
            "category":"Sports & Exercise",
            "subcategory":"Gym",
            "type":"Entertainment"
        }
    ],
    "sg:phone":"+44 20 8592 0828",
    "sg:postcode":"RM10 8DP",
    "sg:province":"Essex",
    "sg:tags":[
        "fitness",
        "health",
        "centre"
    ],
    "wof:name":"Peak Fitness",
    "wof:placetype":"venue"
},
  "geometry": {"coordinates":[0.147961,51.541618],"type":"Point"}
}