{
  "type": "Feature",
  "properties": {
    "iso:country":"GB",
    "sg:address":"38 Redden Court Road, Harold Wood",
    "sg:city":"Romford",
    "sg:classifiers":[
        {
            "category":"Building & Trades",
            "subcategory":"Construction",
            "type":"Services"
        }
    ],
    "sg:phone":"+44 1708 342240",
    "sg:postcode":"RM3 0XA",
    "sg:province":"Essex",
    "sg:tags":[
        "contractor"
    ],
    "wof:name":"Smith & Samuel Construction Ltd.",
    "wof:placetype":"venue"
},
  "geometry": {"coordinates":[0.228464,51.585728],"type":"Point"}
}