{
  "type": "Feature",
  "properties": {
    "addr:full":"Unit 9 Eclipse Business Park, 30 West Hill Epsom Surrey KT19 8JD",
    "addr:housenumber":"unit 9;30",
    "addr:postcode":"kt19 8jd",
    "addr:street":"Eclipse Business Park;West",
    "iso:country":"GB",
    "sg:address":"Unit 9 Eclipse Business Park, 30 West Hill",
    "sg:city":"Epsom",
    "sg:classifiers":[
        {
            "category":"Professional",
            "subcategory":"Engineering",
            "type":"Services"
        }
    ],
    "sg:postcode":"KT19 8JD",
    "sg:province":"Surrey",
    "sg:tags":[
        "consulting",
        "engineer"
    ],
    "wof:name":"Bws Partnership Ltd.",
    "wof:placetype":"venue"
},
  "geometry": {"coordinates":[-0.2711060047,51.3330078125],"type":"Point"}
}