{
  "type": "Feature",
  "properties": {
    "iso:country":"GB",
    "sg:address":"Police Station, 99 Gloucester Av",
    "sg:city":"Chelmsford",
    "sg:classifiers":[
        {
            "category":"Government",
            "subcategory":"Police Station",
            "type":"Public Place"
        }
    ],
    "sg:phone":"+44 1245 490296",
    "sg:postcode":"CM2 9DS",
    "sg:province":"Essex",
    "sg:tags":[
        "support"
    ],
    "wof:name":"Moulsham Police",
    "wof:placetype":"venue"
},
  "geometry": {"coordinates":[0.477891,51.731918],"type":"Point"}
}