{
  "type": "Feature",
  "properties": {
    "addr:full":"Higher Dan Bank Farm, Dan Bank, Marple Stockport Cheshire SK6 7EH",
    "addr:postcode":"sk6 7eh",
    "iso:country":"GB",
    "sg:address":"Higher Dan Bank Farm, Dan Bank, Marple",
    "sg:city":"Stockport",
    "sg:classifiers":[
        {
            "category":"Utilities",
            "subcategory":"Refuse",
            "type":"Services"
        }
    ],
    "sg:phone":"+44 161 427 5580",
    "sg:postcode":"SK6 7EH",
    "sg:province":"Cheshire",
    "sg:tags":[
        "skip",
        "hire"
    ],
    "wof:name":"Marple Skip Hire",
    "wof:placetype":"venue"
},
  "geometry": {"coordinates":[-2.09205,53.394901],"type":"Point"}
}