{
  "type": "Feature",
  "properties": {
    "addr:full":"Sandford Lane Wareham Dorset BH20 4DY",
    "addr:postcode":"bh20 4dy",
    "addr:street":"Sandford Lane",
    "iso:country":"GB",
    "sg:address":"Sandford Lane",
    "sg:city":"Wareham",
    "sg:classifiers":[
        {
            "category":"Retail",
            "subcategory":"Storage",
            "type":"Services"
        }
    ],
    "sg:phone":"+44 1929 553223",
    "sg:postcode":"BH20 4DY",
    "sg:province":"Dorset",
    "sg:tags":[
        "household",
        "removal"
    ],
    "wof:name":"Churchills Removals",
    "wof:placetype":"venue"
},
  "geometry": {"coordinates":[-2.1138799191,50.6932296753],"type":"Point"}
}