{
  "type": "Feature",
  "properties": {
    "iso:country":"GB",
    "sg:address":"11 Hunter Road, Willesborough",
    "sg:city":"Ashford",
    "sg:classifiers":[
        {
            "category":"Shopping",
            "subcategory":"Crafts & Fabrics",
            "type":"Retail Goods"
        }
    ],
    "sg:phone":"+44 1233 639962",
    "sg:postcode":"TN24 0RY",
    "sg:province":"Kent",
    "sg:tags":[
        "shop",
        "needlecraft",
        "wool"
    ],
    "wof:name":"The Forum",
    "wof:placetype":"venue"
},
  "geometry": {"coordinates":[0.893666,51.143673],"type":"Point"}
}