{
  "type": "Feature",
  "properties": {
    "iso:country":"GB",
    "sg:address":"37 Alma Vale Road",
    "sg:city":"Bristol",
    "sg:classifiers":[
        {
            "category":"Personal",
            "subcategory":"Beauty Salon",
            "type":"Services"
        }
    ],
    "sg:phone":"+44 117 970 6706",
    "sg:postcode":"BS8 2HL",
    "sg:province":"City of Bristol",
    "sg:tags":[
        "unisex",
        "hairdresser"
    ],
    "wof:name":"Cavill Design",
    "wof:placetype":"venue"
},
  "geometry": {"coordinates":[-2.6142089367,51.462474823],"type":"Point"}
}