{
  "type": "Feature",
  "properties": {
    "iso:country":"GB",
    "sg:address":"12 Whinneyfield Road, Walkergate",
    "sg:city":"Newcastle-upon-tyne",
    "sg:classifiers":[
        {
            "category":"Building & Trades",
            "subcategory":"Construction",
            "type":"Services"
        }
    ],
    "sg:phone":"+44 191 265 0112",
    "sg:postcode":"NE6 4HX",
    "sg:province":"Tyne and Wear",
    "sg:tags":[
        "roofing"
    ],
    "wof:name":"Shaun W Cullen",
    "wof:placetype":"venue"
},
  "geometry": {"coordinates":[-1.5553760529,54.9795036316],"type":"Point"}
}