{
  "type": "Feature",
  "properties": {
    "addr:full":"54 Cirrus Gardens Southampton Hampshire SO31 4RH",
    "addr:housenumber":"54",
    "addr:postcode":"so31 4rh",
    "addr:street":"Cirrus Gardens",
    "iso:country":"GB",
    "sg:address":"54 Cirrus Gardens",
    "sg:city":"Southampton",
    "sg:classifiers":[
        {
            "category":"Home & Garden",
            "subcategory":"Building Materials",
            "type":"Retail Goods"
        }
    ],
    "sg:postcode":"SO31 4RH",
    "sg:province":"Hampshire",
    "sg:tags":[
        "insulation",
        "installers"
    ],
    "wof:name":"M P Byrne",
    "wof:placetype":"venue"
},
  "geometry": {"coordinates":[-1.31942,50.860023],"type":"Point"}
}