{
  "type": "Feature",
  "properties": {
    "iso:country":"GB",
    "sg:address":"692 Llangyfelach Road, Treboeth",
    "sg:city":"Swansea",
    "sg:classifiers":[
        {
            "category":"Organizations",
            "subcategory":"Membership Organization",
            "type":"Services"
        }
    ],
    "sg:phone":"+44 1792 414141",
    "sg:postcode":"SA5 9EL",
    "sg:province":"Swansea",
    "sg:tags":[
        "club"
    ],
    "wof:name":"The Pines Country Club (Swansea) Ltd.",
    "wof:placetype":"venue"
},
  "geometry": {"coordinates":[-3.948804,51.65118],"type":"Point"}
}