{
  "type": "Feature",
  "properties": {
    "addr:full":"Rear 39 Weston Rd Stoke-on-trent Staffordshire ST3 6AB",
    "addr:housenumber":"39",
    "addr:postcode":"st3 6ab",
    "addr:street":"Rear;Weston Rd",
    "iso:country":"GB",
    "sg:address":"Rear 39 Weston Rd",
    "sg:city":"Stoke-on-trent",
    "sg:classifiers":[
        {
            "category":"Home & Garden",
            "subcategory":"Hardware",
            "type":"Retail Goods"
        }
    ],
    "sg:postcode":"ST3 6AB",
    "sg:province":"Staffordshire",
    "sg:tags":[
        "retailer",
        "diy"
    ],
    "wof:name":"Multi-Craft Supplies",
    "wof:placetype":"venue"
},
  "geometry": {"coordinates":[-2.0952858925,52.9961242676],"type":"Point"}
}