{
  "type": "Feature",
  "properties": {
    "addr:full":"15 Belhaven Terrace Glasgow Glasgow City G12 0TG",
    "addr:housenumber":"15",
    "addr:postcode":"g12 0tg",
    "addr:street":"Belhaven Terrace",
    "iso:country":"GB",
    "sg:address":"15 Belhaven Terrace",
    "sg:city":"Glasgow",
    "sg:classifiers":[
        {
            "category":"Travel",
            "subcategory":"Hotels & Motels",
            "type":"Entertainment"
        }
    ],
    "sg:phone":"+44 141 339 3222",
    "sg:postcode":"G12 0TG",
    "sg:province":"Glasgow City",
    "wof:name":"The Belhaven Hotel",
    "wof:placetype":"venue"
},
  "geometry": {"coordinates":[-4.296943,55.879986],"type":"Point"}
}