{
  "type": "Feature",
  "properties": {
    "addr:full":"147 Eastcote Road Pinner Greater London HA5 1EX",
    "addr:housenumber":"147",
    "addr:postcode":"ha5 1ex",
    "addr:street":"Eastcote Road",
    "iso:country":"GB",
    "sg:address":"147 Eastcote Road",
    "sg:city":"Pinner",
    "sg:classifiers":[
        {
            "category":"Autos & Motor Vehicles",
            "subcategory":"Automobile Sales",
            "type":"Retail Goods"
        }
    ],
    "sg:postcode":"HA5 1EX",
    "sg:province":"Greater London",
    "sg:tags":[
        "car"
    ],
    "wof:name":"B C Motors",
    "wof:placetype":"venue"
},
  "geometry": {"coordinates":[-0.39098,51.584606],"type":"Point"}
}