{
  "type": "Feature",
  "properties": {
    "iso:country":"GB",
    "sg:address":"85 Church Road, Tiptree",
    "sg:city":"Colchester",
    "sg:classifiers":[
        {
            "category":"Farming",
            "subcategory":"Fish & Marine Products",
            "type":"Manufacturing & Wholesale Goods"
        },
        {
            "category":"Food & Beverages",
            "subcategory":"Meat & Fish",
            "type":"Retail Goods"
        }
    ],
    "sg:phone":"+44 1621 815796",
    "sg:postcode":"CO5 0HB",
    "sg:province":"Essex",
    "sg:tags":[
        "fishmonger",
        "butcher"
    ],
    "wof:name":"G Millin & Sons",
    "wof:placetype":"venue"
},
  "geometry": {"coordinates":[0.7514110208,51.8100318909],"type":"Point"}
}