{
  "type": "Feature",
  "properties": {
    "iso:country":"GB",
    "sg:address":"108 South End, Garsington",
    "sg:city":"Oxford",
    "sg:classifiers":[
        {
            "category":"Communications",
            "subcategory":"Film & Video Production",
            "type":"Services"
        }
    ],
    "sg:phone":"+44 1865 368227",
    "sg:postcode":"OX44 9DL",
    "sg:province":"Oxfordshire",
    "sg:tags":[
        "tv"
    ],
    "wof:name":"Manor Tv",
    "wof:placetype":"venue"
},
  "geometry": {"coordinates":[-1.1602590084,51.7172050476],"type":"Point"}
}