{
  "type": "Feature",
  "properties": {
    "addr:full":"98 New Bond Street London Greater London W1S 1SN",
    "addr:housenumber":"98",
    "addr:postcode":"w1s 1sn",
    "addr:street":"New Bond Street",
    "iso:country":"GB",
    "sg:address":"98 New Bond Street",
    "sg:city":"London",
    "sg:classifiers":[
        {
            "category":"Home & Garden",
            "subcategory":"Home Furnishings",
            "type":"Retail Goods"
        }
    ],
    "sg:phone":"+44 20 7629 5517",
    "sg:postcode":"W1S 1SN",
    "sg:province":"Greater London",
    "sg:tags":[
        "beds",
        "bedding",
        "blanket"
    ],
    "wof:name":"Frette Ltd.",
    "wof:placetype":"venue"
},
  "geometry": {"coordinates":[-0.14626,51.513786],"type":"Point"}
}