{
  "type": "Feature",
  "properties": {
    "iso:country":"GB",
    "sg:address":"55 Yelland Road, Fremington",
    "sg:city":"Barnstaple",
    "sg:classifiers":[
        {
            "category":"Military Area",
            "subcategory":"Air Force Base",
            "type":"Public Place"
        }
    ],
    "sg:postcode":"EX31 3DS",
    "sg:province":"Devon",
    "sg:tags":[
        "taxi",
        "hire",
        "private"
    ],
    "wof:name":"Black Cabs",
    "wof:placetype":"venue"
},
  "geometry": {"coordinates":[-4.1389698982,51.0694465637],"type":"Point"}
}