{
  "type": "Feature",
  "properties": {
    "addr:full":"50 Hawks Rd Kingston-upon-thames Greater London KT1 3EE",
    "addr:housenumber":"50",
    "addr:postcode":"kt1 3ee",
    "addr:street":"Hawks Rd",
    "iso:country":"GB",
    "sg:address":"50 Hawks Rd",
    "sg:city":"Kingston-upon-thames",
    "sg:classifiers":[
        {
            "category":"Shopping",
            "subcategory":"News",
            "type":"Retail Goods"
        }
    ],
    "sg:postcode":"KT1 3EE",
    "sg:province":"Greater London",
    "sg:tags":[
        "newsagent"
    ],
    "wof:name":"Davdra,D,",
    "wof:placetype":"venue"
},
  "geometry": {"coordinates":[-0.2894600034,51.409526825],"type":"Point"}
}