{
  "type": "Feature",
  "properties": {
    "addr:full":"84 Blandford Road Reading Berkshire RG2 8RW",
    "addr:housenumber":"84",
    "addr:postcode":"rg2 8rw",
    "addr:street":"Blandford Road",
    "iso:country":"GB",
    "sg:address":"84 Blandford Road",
    "sg:city":"Reading",
    "sg:classifiers":[
        {
            "category":"Professional",
            "subcategory":"Accounting & Tax Preparation",
            "type":"Services"
        }
    ],
    "sg:postcode":"RG2 8RW",
    "sg:province":"Berkshire",
    "sg:tags":[
        "consultant"
    ],
    "wof:name":"The Thames Valley Tax Practice Ltd",
    "wof:placetype":"venue"
},
  "geometry": {"coordinates":[-0.9638910294,51.4202575684],"type":"Point"}
}