{
  "type": "Feature",
  "properties": {
    "addr:full":"Hanchurch Crossroad Fleetwood Lancashire FY7 6HR",
    "addr:postcode":"fy7 6hr",
    "addr:street":"Hanchurch Crossroad",
    "iso:country":"GB",
    "sg:address":"Hanchurch Crossroad",
    "sg:city":"Fleetwood",
    "sg:classifiers":[
        {
            "category":"Freight",
            "type":"Transportation"
        }
    ],
    "sg:phone":"+44 1253 615733",
    "sg:postcode":"FY7 6HR",
    "sg:province":"Lancashire",
    "sg:tags":[
        "haulage",
        "road"
    ],
    "wof:name":"P&o Ferry Masters Ltd",
    "wof:placetype":"venue"
},
  "geometry": {"coordinates":[-3.014669,53.92128],"type":"Point"}
}