{
  "type": "Feature",
  "properties": {
    "addr:full":"212 Braunstone Avenue, Braunstone Leicester Leicestershire LE3 1EG",
    "addr:housenumber":"212",
    "addr:postcode":"le3 1eg",
    "addr:street":"Braunstone Avenue",
    "iso:country":"GB",
    "sg:address":"212 Braunstone Avenue, Braunstone",
    "sg:city":"Leicester",
    "sg:classifiers":[
        {
            "category":"Building & Trades",
            "subcategory":"Construction",
            "type":"Services"
        }
    ],
    "sg:postcode":"LE3 1EG",
    "sg:province":"Leicestershire",
    "sg:tags":[
        "tiling",
        "contractor"
    ],
    "wof:name":"M & J French Ltd.",
    "wof:placetype":"venue"
},
  "geometry": {"coordinates":[-1.1711770296,52.620388031],"type":"Point"}
}