{
  "type": "Feature",
  "properties": {
    "addr:full":"13a Bolton Street Brixham Devon TQ5 9TZ",
    "addr:housenumber":"13a",
    "addr:postcode":"tq5 9tz",
    "addr:street":"Bolton Street",
    "iso:country":"GB",
    "sg:address":"13a Bolton Street",
    "sg:city":"Brixham",
    "sg:classifiers":[
        {
            "category":"Shopping",
            "subcategory":"Pharmacy",
            "type":"Retail Goods"
        }
    ],
    "sg:phone":"+44 1803 853368",
    "sg:postcode":"TQ5 9TZ",
    "sg:province":"Devon",
    "sg:tags":[
        "pharmacist",
        "chemist"
    ],
    "wof:name":"M K Wright (Pharmacy) Ltd.",
    "wof:placetype":"venue"
},
  "geometry": {"coordinates":[-3.516175,50.393703],"type":"Point"}
}