{
  "type": "Feature",
  "properties": {
    "iso:country":"GB",
    "sg:address":"67a Sherwood Park Road",
    "sg:city":"Mitcham",
    "sg:classifiers":[
        {
            "category":"Autos & Motor Vehicles",
            "subcategory":"Auto Supplies",
            "type":"Retail Goods"
        },
        {
            "category":"Wholesale",
            "subcategory":"Scrap",
            "type":"Manufacturing & Wholesale Goods"
        }
    ],
    "sg:phone":"+44 20 8288 0598",
    "sg:postcode":"CR4 1NB",
    "sg:province":"Greater London",
    "sg:tags":[
        "car",
        "part",
        "breaker",
        "dismantlers",
        "accessory"
    ],
    "wof:name":"K D Motor Spares",
    "wof:placetype":"venue"
},
  "geometry": {"coordinates":[-0.14228,51.399471],"type":"Point"}
}