{
  "type": "Feature",
  "properties": {
    "addr:full":"253 Mary Vale Road, Bournvill Birmingham West Midlands B30 1PN",
    "addr:housenumber":"253",
    "addr:postcode":"b30 1pn",
    "addr:street":"Mary Vale Road",
    "iso:country":"GB",
    "sg:address":"253 Mary Vale Road, Bournvill",
    "sg:city":"Birmingham",
    "sg:classifiers":[
        {
            "category":"Shopping",
            "subcategory":"News",
            "type":"Retail Goods"
        }
    ],
    "sg:phone":"+44 121 458 2804",
    "sg:postcode":"B30 1PN",
    "sg:province":"West Midlands",
    "sg:tags":[
        "newsagent"
    ],
    "wof:name":"L & S Hoffman",
    "wof:placetype":"venue"
},
  "geometry": {"coordinates":[-1.9345339537,52.4241409302],"type":"Point"}
}