{
  "type": "Feature",
  "properties": {
    "addr:full":"Unidoor House, Eyncourt Road, Woodside Estate Dunstable Bedfordshire LU5 4TS",
    "addr:postcode":"lu5 4ts",
    "addr:street":"Eyncourt Road",
    "iso:country":"GB",
    "sg:address":"Unidoor House, Eyncourt Road, Woodside Estate",
    "sg:city":"Dunstable",
    "sg:classifiers":[
        {
            "category":"Professional",
            "subcategory":"Business Services",
            "type":"Services"
        }
    ],
    "sg:postcode":"LU5 4TS",
    "sg:province":"Bedfordshire",
    "sg:tags":[
        "import",
        "export",
        "agent"
    ],
    "wof:name":"Mozaik Ltd.",
    "wof:placetype":"venue"
},
  "geometry": {"coordinates":[-0.5093349814,51.8950119019],"type":"Point"}
}