{
  "type": "Feature",
  "properties": {
    "addr:full":"11 Main Street, Stamford Bridge York East Riding of Yorkshire YO41 1AE",
    "addr:housenumber":"11",
    "addr:postcode":"yo41 1ae",
    "addr:street":"Main Street",
    "iso:country":"GB",
    "sg:address":"11 Main Street, Stamford Bridge",
    "sg:city":"York",
    "sg:classifiers":[
        {
            "category":"Communications",
            "subcategory":"Film & Video Production",
            "type":"Services"
        },
        {
            "category":"Communications",
            "type":"Services"
        }
    ],
    "sg:phone":"+44 1759 371239",
    "sg:postcode":"YO41 1AE",
    "sg:province":"East Riding of Yorkshire",
    "sg:tags":[
        "tv",
        "studio",
        "radio"
    ],
    "wof:name":"R Rutherford & Sons",
    "wof:placetype":"venue"
},
  "geometry": {"coordinates":[-0.912358,53.991459],"type":"Point"}
}