{
  "type": "Feature",
  "properties": {
    "addr:full":"8 Cricklewood Broadway London Greater London NW2 3HD",
    "addr:housenumber":"8",
    "addr:postcode":"nw2 3hd",
    "addr:street":"Cricklewood Broadway",
    "iso:country":"GB",
    "sg:address":"8 Cricklewood Broadway",
    "sg:city":"London",
    "sg:classifiers":[
        {
            "category":"Autos & Motor Vehicles",
            "subcategory":"Automobile Sales",
            "type":"Retail Goods"
        }
    ],
    "sg:phone":"+44 20 8450 9726",
    "sg:postcode":"NW2 3HD",
    "sg:province":"Greater London",
    "sg:tags":[
        "car"
    ],
    "wof:name":"Sai Motors",
    "wof:placetype":"venue"
},
  "geometry": {"coordinates":[-0.210311,51.552673],"type":"Point"}
}