{
  "type": "Feature",
  "properties": {
    "iso:country":"GB",
    "sg:address":"325 Meltham Road",
    "sg:city":"Huddersfield",
    "sg:classifiers":[
        {
            "category":"Shopping",
            "subcategory":"Pharmacy",
            "type":"Retail Goods"
        }
    ],
    "sg:phone":"+44 1484 661263",
    "sg:postcode":"HD4 7EX",
    "sg:province":"West Yorkshire",
    "sg:tags":[
        "pharmacist",
        "dispensing",
        "chemist"
    ],
    "wof:name":"K & M Pharmacy",
    "wof:placetype":"venue"
},
  "geometry": {"coordinates":[-1.8143359423,53.6145896912],"type":"Point"}
}