{
  "type": "Feature",
  "properties": {
    "addr:full":"18 Avonmore Road London Greater London W14 8RR",
    "addr:housenumber":"18",
    "addr:postcode":"w14 8rr",
    "addr:street":"Avonmore Road",
    "iso:country":"GB",
    "sg:address":"18 Avonmore Road",
    "sg:city":"London",
    "sg:classifiers":[
        {
            "category":"Professional",
            "subcategory":"Printing & Photocopies",
            "type":"Services"
        }
    ],
    "sg:phone":"+44 20 7385 0800",
    "sg:postcode":"W14 8RR",
    "sg:province":"Greater London",
    "sg:tags":[
        "duplicating",
        "copying"
    ],
    "wof:name":"Call Print",
    "wof:placetype":"venue"
},
  "geometry": {"coordinates":[-0.2073300034,51.494682312],"type":"Point"}
}