{
  "type": "Feature",
  "properties": {
    "addr:full":"Shalford Barn, Shalford Hill, Aldermaston Reading Berkshire RG7 4NB",
    "addr:postcode":"rg7 4nb",
    "addr:street":"Shalford Hill",
    "iso:country":"GB",
    "sg:address":"Shalford Barn, Shalford Hill, Aldermaston",
    "sg:city":"Reading",
    "sg:classifiers":[
        {
            "category":"Autos & Motor Vehicles",
            "subcategory":"Automobile Sales",
            "type":"Retail Goods"
        }
    ],
    "sg:phone":"+44 118 971 3939",
    "sg:postcode":"RG7 4NB",
    "sg:province":"Berkshire",
    "sg:tags":[
        "commercial"
    ],
    "wof:name":"Independent Motor Co",
    "wof:placetype":"venue"
},
  "geometry": {"coordinates":[-1.152579,51.382935],"type":"Point"}
}