{
  "type": "Feature",
  "properties": {
    "addr:full":"55 Finlay Street London Greater London SW6 6HF",
    "addr:housenumber":"55",
    "addr:postcode":"sw6 6hf",
    "addr:street":"Finlay Street",
    "iso:country":"GB",
    "sg:address":"55 Finlay Street",
    "sg:city":"London",
    "sg:classifiers":[
        {
            "category":"Farming",
            "subcategory":"Nursery",
            "type":"Manufacturing & Wholesale Goods"
        }
    ],
    "sg:postcode":"SW6 6HF",
    "sg:province":"Greater London",
    "sg:tags":[
        "creche"
    ],
    "wof:name":"Melrose House Nursery School",
    "wof:placetype":"venue"
},
  "geometry": {"coordinates":[-0.2186170071,51.4752655029],"type":"Point"}
}