{
  "type": "Feature",
  "properties": {
    "addr:full":"Holehouse La Sturminster Newton Dorset DT10 2AA",
    "addr:housenumber":"newton",
    "addr:postcode":"dt10 2aa",
    "addr:street":"La;Dorset",
    "iso:country":"GB",
    "sg:address":"Holehouse La",
    "sg:city":"Sturminster Newton",
    "sg:classifiers":[
        {
            "category":"Home & Garden",
            "subcategory":"Kitchen Supply",
            "type":"Retail Goods"
        }
    ],
    "sg:phone":"+44 1258 471005",
    "sg:postcode":"DT10 2AA",
    "sg:province":"Dorset",
    "sg:tags":[
        "equipment",
        "brewer"
    ],
    "wof:name":"Caskmaster",
    "wof:placetype":"venue"
},
  "geometry": {"coordinates":[-2.3123939037,50.9168548584],"type":"Point"}
}