{
  "type": "Feature",
  "properties": {
    "iso:country":"GB",
    "sg:address":"Unit 2 Woodroyd Mills, South Parade",
    "sg:city":"Cleckheaton",
    "sg:classifiers":[
        {
            "category":"Wholesale",
            "subcategory":"Machinery & Supplies",
            "type":"Manufacturing & Wholesale Goods"
        },
        {
            "category":"Arts & Performance",
            "subcategory":"Theater",
            "type":"Entertainment"
        }
    ],
    "sg:phone":"+44 1274 872467",
    "sg:postcode":"BD19 3AF",
    "sg:province":"West Yorkshire",
    "sg:tags":[
        "constume",
        "theatrical",
        "supplier",
        "presentation"
    ],
    "wof:name":"B Authentic Uniforms & Costumes",
    "wof:placetype":"venue"
},
  "geometry": {"coordinates":[-1.711889,53.72517],"type":"Point"}
}