{
  "type": "Feature",
  "properties": {
    "iso:country":"GB",
    "sg:address":"245 High Street",
    "sg:city":"Lincoln",
    "sg:classifiers":[
        {
            "category":"Education",
            "subcategory":"College",
            "type":"Public Place"
        },
        {
            "category":"Education",
            "subcategory":"University",
            "type":"Public Place"
        }
    ],
    "sg:phone":"+44 1522 533459",
    "sg:postcode":"LN2 1HW",
    "sg:province":"Lincolnshire",
    "sg:tags":[
        "school",
        "outfitter"
    ],
    "sg:website":"http://www.schoolwear-centre.co.uk",
    "wof:name":"Justin Schoolwear Centre",
    "wof:placetype":"venue"
},
  "geometry": {"coordinates":[-0.539449,53.23151],"type":"Point"}
}