{
  "type": "Feature",
  "properties": {
    "iso:country":"GB",
    "sg:address":"19 Heythrop Close, Oadby",
    "sg:city":"Leicester",
    "sg:classifiers":[
        {
            "category":"Retail",
            "subcategory":"Repair Shop",
            "type":"Services"
        }
    ],
    "sg:phone":"+44 116 273 0444",
    "sg:postcode":"LE2 4SL",
    "sg:province":"Leicestershire",
    "sg:tags":[
        "television",
        "good",
        "video",
        "servicing",
        "maintenance",
        "radio"
    ],
    "wof:name":"SOUND & VISION CENTRE",
    "wof:placetype":"venue"
},
  "geometry": {"coordinates":[-1.0631649494,52.5923614502],"type":"Point"}
}