{
  "type": "Feature",
  "properties": {
    "addr:full":"11 Princes Drive, Littleover Derby Derbyshire DE23 6DX",
    "addr:housenumber":"11",
    "addr:postcode":"de23 6dx",
    "addr:street":"Princes Drive",
    "iso:country":"GB",
    "sg:address":"11 Princes Drive, Littleover",
    "sg:city":"Derby",
    "sg:classifiers":[
        {
            "category":"Building & Trades",
            "subcategory":"Plumbing",
            "type":"Services"
        }
    ],
    "sg:phone":"+44 1332 299351",
    "sg:postcode":"DE23 6DX",
    "sg:province":"Derbyshire",
    "sg:tags":[
        "plumber",
        "heating"
    ],
    "wof:name":"P A Newall",
    "wof:placetype":"venue"
},
  "geometry": {"coordinates":[-1.5100539923,52.9090690613],"type":"Point"}
}