{
  "type": "Feature",
  "properties": {
    "iso:country":"GB",
    "sg:address":"Rear Of 4 High Street, Saltney",
    "sg:city":"Chester",
    "sg:classifiers":[
        {
            "category":"Manufacturing",
            "subcategory":"Building Materials",
            "type":"Manufacturing & Wholesale Goods"
        }
    ],
    "sg:phone":"+44 1244 680224",
    "sg:postcode":"CH4 8SE",
    "sg:province":"Cheshire",
    "sg:tags":[
        "merchant",
        "builder"
    ],
    "wof:name":"Foden Enterprise Ltd.",
    "wof:placetype":"venue"
},
  "geometry": {"coordinates":[-2.9355139732,53.1743850708],"type":"Point"}
}