{
  "type": "Feature",
  "properties": {
    "addr:full":"Adswood Road Liverpool Merseyside L36 7XR",
    "addr:postcode":"l36 7xr",
    "addr:street":"Adswood Road",
    "iso:country":"GB",
    "sg:address":"Adswood Road",
    "sg:city":"Liverpool",
    "sg:classifiers":[
        {
            "category":"Place Of Worship",
            "type":"Public Place"
        },
        {
            "category":"Education",
            "subcategory":"School",
            "type":"Public Place"
        }
    ],
    "sg:phone":"+44 151 489 3221",
    "sg:postcode":"L36 7XR",
    "sg:province":"Merseyside",
    "sg:tags":[
        "local",
        "authority"
    ],
    "wof:name":"St Aidan's R C Primary School",
    "wof:placetype":"venue"
},
  "geometry": {"coordinates":[-2.8393359184,53.4169158936],"type":"Point"}
}