{
  "type": "Feature",
  "properties": {
    "addr:full":"Unit 2 Faraday Rd Swindon Wiltshire SN3 5HQ",
    "addr:housenumber":"unit 2",
    "addr:postcode":"sn3 5hq",
    "addr:street":"Faraday Rd",
    "iso:country":"GB",
    "sg:address":"Unit 2 Faraday Rd",
    "sg:city":"Swindon",
    "sg:classifiers":[
        {
            "category":"Manufacturing",
            "subcategory":"Tools & Machinery",
            "type":"Manufacturing & Wholesale Goods"
        }
    ],
    "sg:phone":"+44 1793 538988",
    "sg:postcode":"SN3 5HQ",
    "sg:province":"Wiltshire",
    "sg:tags":[
        "design",
        "maker"
    ],
    "wof:name":"Xmet",
    "wof:placetype":"venue"
},
  "geometry": {"coordinates":[-1.724604,51.554352],"type":"Point"}
}