{
  "type": "Feature",
  "properties": {
    "addr:full":"Pinkham Way Friern Barnet Greater London N11 2UU",
    "addr:postcode":"n11 2uu",
    "addr:street":"Pinkham Way",
    "iso:country":"GB",
    "sg:address":"Pinkham Way",
    "sg:city":"Friern Barnet",
    "sg:classifiers":[
        {
            "category":"Home & Garden",
            "subcategory":"Building Materials",
            "type":"Retail Goods"
        }
    ],
    "sg:phone":"+44 20 8368 2330",
    "sg:postcode":"N11 2UU",
    "sg:province":"Greater London",
    "sg:tags":[
        "furnishers",
        "bathroom",
        "planner"
    ],
    "wof:name":"Bathrooms Direct",
    "wof:placetype":"venue"
},
  "geometry": {"coordinates":[-0.149971,51.60693],"type":"Point"}
}