{
  "type": "Feature",
  "properties": {
    "addr:full":"156 Kensington Church Street London Greater London W8 4BN",
    "addr:housenumber":"156",
    "addr:postcode":"w8 4bn",
    "addr:street":"Kensington Church Street",
    "iso:country":"GB",
    "sg:address":"156 Kensington Church Street",
    "sg:city":"London",
    "sg:classifiers":[
        {
            "category":"Shopping",
            "subcategory":"Antiques",
            "type":"Retail Goods"
        }
    ],
    "sg:phone":"+44 20 7229 5866",
    "sg:postcode":"W8 4BN",
    "sg:province":"Greater London",
    "wof:name":"Denton Antiques",
    "wof:placetype":"venue"
},
  "geometry": {"coordinates":[-0.1948429942,51.5078163147],"type":"Point"}
}