{
  "type": "Feature",
  "properties": {
    "addr:full":"49 Calverley Road, The Precinct Tunbridge Wells Kent TN1 2TT",
    "addr:housenumber":"49",
    "addr:postcode":"tn1 2tt",
    "addr:street":"Calverley Road The Precinct Tunbridge Wells",
    "iso:country":"GB",
    "sg:address":"49 Calverley Road, The Precinct",
    "sg:city":"Tunbridge Wells",
    "sg:classifiers":[
        {
            "category":"Bars & Pubs",
            "subcategory":"Nightclub",
            "type":"Food & Drink"
        }
    ],
    "sg:postcode":"TN1 2TT",
    "sg:province":"Kent",
    "sg:tags":[
        "club",
        "night"
    ],
    "wof:name":"Chez Moi Nightclub",
    "wof:placetype":"venue"
},
  "geometry": {"coordinates":[0.2635500133,51.1333732605],"type":"Point"}
}