{
  "type": "Feature",
  "properties": {
    "addr:full":"Sadlers House, Gutter Lane, Cheapside Moorgate Greater London EC2V 6HS",
    "addr:postcode":"ec2v 6hs",
    "addr:street":"Gutter Lane;Moorgate",
    "iso:country":"GB",
    "sg:address":"Sadlers House, Gutter Lane, Cheapside",
    "sg:city":"Moorgate",
    "sg:classifiers":[
        {
            "category":"Real Estate",
            "subcategory":"Surveying",
            "type":"Services"
        }
    ],
    "sg:phone":"+44 20 7796 4000",
    "sg:postcode":"EC2V 6HS",
    "sg:province":"Greater London",
    "sg:tags":[
        "surveyor",
        "valuer"
    ],
    "wof:name":"Lambert Smith Hampton",
    "wof:placetype":"venue"
},
  "geometry": {"coordinates":[-0.095394,51.515244],"type":"Point"}
}