{
  "type": "Feature",
  "properties": {
    "addr:full":"45 Main Street, Dailly Girvan South Ayrshire KA26 9SB",
    "addr:housenumber":"45",
    "addr:postcode":"ka26 9sb",
    "addr:street":"Main Street Dailly",
    "iso:country":"GB",
    "sg:address":"45 Main Street, Dailly",
    "sg:city":"Girvan",
    "sg:classifiers":[
        {
            "category":"Travel",
            "subcategory":"Hotels & Motels",
            "type":"Entertainment"
        }
    ],
    "sg:phone":"+44 1465 811288",
    "sg:postcode":"KA26 9SB",
    "sg:province":"South Ayrshire",
    "wof:name":"Greenhead Hotel",
    "wof:placetype":"venue"
},
  "geometry": {"coordinates":[-4.7255358696,55.2778816223],"type":"Point"}
}