{
  "type": "Feature",
  "properties": {
    "addr:full":"36 Winchester Street Basingstoke Hampshire RG21 7EY",
    "addr:housenumber":"36",
    "addr:postcode":"rg21 7ey",
    "addr:street":"Winchester Street",
    "iso:country":"GB",
    "sg:address":"36 Winchester Street",
    "sg:city":"Basingstoke",
    "sg:classifiers":[
        {
            "category":"Real Estate",
            "subcategory":"Surveying",
            "type":"Services"
        }
    ],
    "sg:postcode":"RG21 7EY",
    "sg:province":"Hampshire",
    "sg:tags":[
        "surveyor",
        "valuer"
    ],
    "wof:name":"Brian Davies",
    "wof:placetype":"venue"
},
  "geometry": {"coordinates":[-1.0887329578,51.2624359131],"type":"Point"}
}