{
  "type": "Feature",
  "properties": {
    "addr:full":"5 Bridge Cross Road Walsall Staffordshire WS7 8BU",
    "addr:housenumber":"5",
    "addr:postcode":"ws7 8bu",
    "addr:street":"Bridge Cross Road",
    "iso:country":"GB",
    "sg:address":"5 Bridge Cross Road",
    "sg:city":"Walsall",
    "sg:classifiers":[
        {
            "category":"Professional",
            "subcategory":"Lawyer & Legal Services",
            "type":"Services"
        }
    ],
    "sg:postcode":"WS7 8BU",
    "sg:province":"Staffordshire",
    "sg:tags":[
        "solicitor"
    ],
    "wof:name":"Gillespies",
    "wof:placetype":"venue"
},
  "geometry": {"coordinates":[-1.93084,52.6814],"type":"Point"}
}