{
  "type": "Feature",
  "properties": {
    "iso:country":"GB",
    "sg:address":"12 Stephenson Street, Thornaby",
    "sg:city":"Stockton-on-tees",
    "sg:classifiers":[
        {
            "category":"Retail",
            "subcategory":"Auto Repair",
            "type":"Services"
        }
    ],
    "sg:phone":"+44 1642 617626",
    "sg:postcode":"TS17 6AL",
    "sg:province":"Durham",
    "sg:tags":[
        "modification",
        "garage",
        "related"
    ],
    "sg:website":"http://www.teessideautotech.co.uk",
    "wof:name":"Teesside Auto Technical Services",
    "wof:placetype":"venue"
},
  "geometry": {"coordinates":[-1.30103,54.557812],"type":"Point"}
}