{
  "type": "Feature",
  "properties": {
    "iso:country":"GB",
    "sg:address":"32 West Brook Rd",
    "sg:city":"Wirral",
    "sg:classifiers":[
        {
            "category":"Health Services",
            "subcategory":"Clinic",
            "type":"Services"
        }
    ],
    "sg:phone":"+44 151 678 4122",
    "sg:postcode":"CH46 5NN",
    "sg:province":"Merseyside",
    "sg:tags":[
        "aromatherapy"
    ],
    "wof:name":"Maggie Rowan",
    "wof:placetype":"venue"
},
  "geometry": {"coordinates":[-3.125714,53.393814],"type":"Point"}
}