{
  "type": "Feature",
  "properties": {
    "addr:full":"8 Colborne Way Worcester Park Surrey KT4 8LS",
    "addr:housenumber":"8",
    "addr:postcode":"kt4 8ls",
    "addr:street":"Colborne Way",
    "iso:country":"GB",
    "sg:address":"8 Colborne Way",
    "sg:city":"Worcester Park",
    "sg:classifiers":[
        {
            "category":"Manufacturing",
            "subcategory":"Electronics",
            "type":"Manufacturing & Wholesale Goods"
        }
    ],
    "sg:phone":"+44 20 8288 0747",
    "sg:postcode":"KT4 8LS",
    "sg:province":"Surrey",
    "sg:tags":[
        "computer",
        "-",
        "printed",
        "circuit"
    ],
    "wof:name":"Microtech Group Ltd",
    "wof:placetype":"venue"
},
  "geometry": {"coordinates":[-0.2328999937,51.3747558594],"type":"Point"}
}