{
  "type": "Feature",
  "properties": {
    "addr:full":"Bybrook Barn Garden Centre, Canterbury Rd, Kennington Ashford Kent TN24 9QB",
    "addr:postcode":"tn24 9qb",
    "addr:street":"Canterbury Rd",
    "iso:country":"GB",
    "sg:address":"Bybrook Barn Garden Centre, Canterbury Rd, Kennington",
    "sg:city":"Ashford",
    "sg:classifiers":[
        {
            "category":"Home & Garden",
            "subcategory":"Furniture",
            "type":"Retail Goods"
        }
    ],
    "sg:postcode":"TN24 9QB",
    "sg:province":"Kent",
    "wof:name":"P J S Lighting",
    "wof:placetype":"venue"
},
  "geometry": {"coordinates":[0.8954550028,51.1647872925],"type":"Point"}
}