{
  "type": "Feature",
  "properties": {
    "iso:country":"GB",
    "sg:address":"Dunston House, Dunston Rd, Sheepbridge",
    "sg:city":"Chesterfield",
    "sg:classifiers":[
        {
            "category":"Home & Garden",
            "subcategory":"Furniture",
            "type":"Retail Goods"
        }
    ],
    "sg:phone":"+44 1246 260350",
    "sg:postcode":"S41 9QD",
    "sg:province":"Derbyshire",
    "wof:name":"Lab Flex Ltd",
    "wof:placetype":"venue"
},
  "geometry": {"coordinates":[-1.4603480101,53.2647895813],"type":"Point"}
}