{
  "type": "Feature",
  "properties": {
    "addr:full":"21 Cardwell Pl Blackburn Lancashire BB2 1LG",
    "addr:housenumber":"21",
    "addr:postcode":"bb2 1lg",
    "addr:street":"Cardwell Pl",
    "iso:country":"GB",
    "sg:address":"21 Cardwell Pl",
    "sg:city":"Blackburn",
    "sg:classifiers":[
        {
            "category":"Communications",
            "type":"Services"
        }
    ],
    "sg:postcode":"BB2 1LG",
    "sg:province":"Lancashire",
    "sg:tags":[
        "tv",
        "video",
        "radio"
    ],
    "wof:name":"Fowler,Geoff,",
    "wof:placetype":"venue"
},
  "geometry": {"coordinates":[-2.4859108925,53.7476959229],"type":"Point"}
}