{
  "type": "Feature",
  "properties": {
    "addr:full":"202 Ealing Rd Wembley Greater London HA0 4QG",
    "addr:housenumber":"202",
    "addr:postcode":"ha0 4qg",
    "addr:street":"Ealing Rd",
    "iso:country":"GB",
    "sg:address":"202 Ealing Rd",
    "sg:city":"Wembley",
    "sg:classifiers":[
        {
            "category":"Shopping",
            "subcategory":"Luggage & Leather Goods",
            "type":"Retail Goods"
        }
    ],
    "sg:postcode":"HA0 4QG",
    "sg:province":"Greater London",
    "wof:name":"Maguire,John,",
    "wof:placetype":"venue"
},
  "geometry": {"coordinates":[-0.2971099913,51.5446891785],"type":"Point"}
}