{
  "type": "Feature",
  "properties": {
    "addr:full":"176a Renacres Lane, Halsall Ormskirk Lancashire L39 8SQ",
    "addr:housenumber":"176a",
    "addr:postcode":"l39 8sq",
    "addr:street":"Renacres Lane",
    "iso:country":"GB",
    "sg:address":"176a Renacres Lane, Halsall",
    "sg:city":"Ormskirk",
    "sg:classifiers":[
        {
            "category":"Home & Garden",
            "subcategory":"Building Materials",
            "type":"Retail Goods"
        }
    ],
    "sg:postcode":"L39 8SQ",
    "sg:province":"Lancashire",
    "sg:tags":[
        "system",
        "staircase"
    ],
    "wof:name":"Alan Grice Staircase Co",
    "wof:placetype":"venue"
},
  "geometry": {"coordinates":[-2.9754290581,53.6053924561],"type":"Point"}
}