{
  "type": "Feature",
  "properties": {
    "addr:full":"22a Oxford St Harrogate North Yorkshire HG1 1PU",
    "addr:housenumber":"22a",
    "addr:postcode":"hg1 1pu",
    "addr:street":"Oxford St",
    "iso:country":"GB",
    "sg:address":"22a Oxford St",
    "sg:city":"Harrogate",
    "sg:classifiers":[
        {
            "category":"Health Services",
            "subcategory":"Dentist",
            "type":"Services"
        }
    ],
    "sg:phone":"+44 1423 521999",
    "sg:postcode":"HG1 1PU",
    "sg:province":"North Yorkshire",
    "sg:tags":[
        "technician",
        "instrument",
        "dental"
    ],
    "wof:name":"Denture Express",
    "wof:placetype":"venue"
},
  "geometry": {"coordinates":[-1.5409,53.994102],"type":"Point"}
}