{
  "type": "Feature",
  "properties": {
    "addr:full":"13 Chapel Street Chorley Lancashire PR7 1BN",
    "addr:housenumber":"13",
    "addr:postcode":"pr7 1bn",
    "addr:street":"Chapel Street",
    "iso:country":"GB",
    "sg:address":"13 Chapel Street",
    "sg:city":"Chorley",
    "sg:classifiers":[
        {
            "category":"Home & Garden",
            "subcategory":"Kitchen Supply",
            "type":"Retail Goods"
        }
    ],
    "sg:phone":"+44 1257 233033",
    "sg:postcode":"PR7 1BN",
    "sg:province":"Lancashire",
    "sg:tags":[
        "ware"
    ],
    "wof:name":"Home Equipment Ltd.",
    "wof:placetype":"venue"
},
  "geometry": {"coordinates":[-2.6283490658,53.6524810791],"type":"Point"}
}