{
  "type": "Feature",
  "properties": {
    "addr:full":"8 The Parade, Queen Elizabeth Way Colchester Essex CO2 8LY",
    "addr:housenumber":"8",
    "addr:postcode":"co2 8ly",
    "addr:street":"The Parade Queen Elizabeth Way",
    "iso:country":"GB",
    "sg:address":"8 The Parade, Queen Elizabeth Way",
    "sg:city":"Colchester",
    "sg:classifiers":[
        {
            "category":"Retail",
            "subcategory":"Laundry & Dry Cleaning",
            "type":"Services"
        }
    ],
    "sg:phone":"+44 1206 762766",
    "sg:postcode":"CO2 8LY",
    "sg:province":"Essex",
    "sg:tags":[
        "launderette"
    ],
    "wof:name":"Washaway",
    "wof:placetype":"venue"
},
  "geometry": {"coordinates":[0.9095990062,51.8692512512],"type":"Point"}
}