{
  "type": "Feature",
  "properties": {
    "iso:country":"GB",
    "sg:address":"48 Ringwood Road",
    "sg:city":"Eastbourne",
    "sg:classifiers":[
        {
            "category":"Retail",
            "subcategory":"Driving School",
            "type":"Services"
        }
    ],
    "sg:phone":"+44 1323 644804",
    "sg:postcode":"BN22 8TB",
    "sg:province":"East Sussex",
    "sg:tags":[
        "instruction",
        "cycling",
        "motor"
    ],
    "wof:name":"County Rider Training",
    "wof:placetype":"venue"
},
  "geometry": {"coordinates":[0.2962189913,50.7787628174],"type":"Point"}
}