{
  "type": "Feature",
  "properties": {
    "iso:country":"GB",
    "sg:address":"Lion Lane, Clee Hill",
    "sg:city":"Ludlow",
    "sg:classifiers":[
        {
            "category":"Bars & Pubs",
            "type":"Food & Drink"
        }
    ],
    "sg:postcode":"SY8 3NJ",
    "sg:province":"Herefordshire",
    "sg:tags":[
        "pubs",
        "inn"
    ],
    "wof:name":"Golden Lion Inn",
    "wof:placetype":"venue"
},
  "geometry": {"coordinates":[-2.5922789574,52.3639678955],"type":"Point"}
}