{
  "type": "Feature",
  "properties": {
    "addr:full":"24 Mithchells Art & Craft Centre Sutton Coldfield Staffordshire B75 6NA",
    "addr:housenumber":"24",
    "addr:postcode":"b75 6na",
    "iso:country":"GB",
    "sg:address":"24 Mithchells Art & Craft Centre",
    "sg:city":"Sutton Coldfield",
    "sg:classifiers":[
        {
            "category":"Professional",
            "type":"Services"
        }
    ],
    "sg:phone":"+44 121 308 0009",
    "sg:postcode":"B75 6NA",
    "sg:province":"Staffordshire",
    "sg:tags":[
        "interior",
        "furnishers",
        "designer"
    ],
    "wof:name":"Bennett & Bowman Interiors Ltd.",
    "wof:placetype":"venue"
},
  "geometry": {"coordinates":[-1.80677,52.58429],"type":"Point"}
}