{
  "type": "Feature",
  "properties": {
    "iso:country":"GB",
    "sg:address":"70 Cowcross Street",
    "sg:city":"London",
    "sg:classifiers":[
        {
            "category":"Professional",
            "subcategory":"Management & Consulting",
            "type":"Services"
        }
    ],
    "sg:phone":"+44 20 7608 2409",
    "sg:postcode":"EC1M 6EJ",
    "sg:province":"Greater London",
    "sg:tags":[
        "conservation"
    ],
    "wof:name":"The Garden History Society",
    "wof:placetype":"venue"
},
  "geometry": {"coordinates":[-0.103638,51.520115],"type":"Point"}
}