{
  "type": "Feature",
  "properties": {
    "addr:full":"21 Princes Ct Wembley Greater London HA9 7JJ",
    "addr:housenumber":"21",
    "addr:postcode":"ha9 7jj",
    "addr:street":"Princes Ct",
    "iso:country":"GB",
    "sg:address":"21 Princes Ct",
    "sg:city":"Wembley",
    "sg:classifiers":[
        {
            "category":"Professional",
            "subcategory":"Management & Consulting",
            "type":"Services"
        }
    ],
    "sg:phone":"+44 20 8900 2443",
    "sg:postcode":"HA9 7JJ",
    "sg:province":"Greater London",
    "sg:tags":[
        "consultant",
        "business"
    ],
    "wof:name":"Change Management Consultants",
    "wof:placetype":"venue"
},
  "geometry": {"coordinates":[-0.2962169945,51.5553627014],"type":"Point"}
}