{
  "type": "Feature",
  "properties": {
    "addr:full":"Unit 5 Perseverance Mill, Burnley Road Blackburn Lancashire BB1 3HW",
    "addr:housenumber":"unit 5",
    "addr:postcode":"bb1 3hw",
    "addr:street":"Perseverance Mill Burnley Road",
    "iso:country":"GB",
    "sg:address":"Unit 5 Perseverance Mill, Burnley Road",
    "sg:city":"Blackburn",
    "sg:classifiers":[
        {
            "category":"Retail",
            "subcategory":"Auto Repair",
            "type":"Services"
        }
    ],
    "sg:phone":"+44 1254 581710",
    "sg:postcode":"BB1 3HW",
    "sg:province":"Lancashire",
    "sg:tags":[
        "body",
        "car",
        "repairer",
        "modification",
        "garage"
    ],
    "wof:name":"Whitebirk Car Body Repairs",
    "wof:placetype":"venue"
},
  "geometry": {"coordinates":[-2.480399,53.748516],"type":"Point"}
}