{
  "type": "Feature",
  "properties": {
    "addr:full":"3rd Floor Audrey House, 16/20 Ely Pla London Greater London EC1N 6SN",
    "addr:housenumber":"3rd floor audrey house 16 / 20",
    "addr:postcode":"ec1n 6sn",
    "addr:street":"Ely Pla",
    "iso:country":"GB",
    "sg:address":"3rd Floor Audrey House, 16/20 Ely Pla",
    "sg:city":"London",
    "sg:classifiers":[
        {
            "category":"Real Estate",
            "subcategory":"Architect",
            "type":"Services"
        }
    ],
    "sg:phone":"+44 131 228 3777",
    "sg:postcode":"EC1N 6SN",
    "sg:province":"Greater London",
    "wof:name":"Jamie Troughton & Partners Ltd.",
    "wof:placetype":"venue"
},
  "geometry": {"coordinates":[-0.10738,51.519039],"type":"Point"}
}