{
  "type": "Feature",
  "properties": {
    "addr:full":"196 Thurlbear Rd, Thurlbear Taunton Devon TA3 5DQ",
    "addr:housenumber":"196",
    "addr:postcode":"ta3 5dq",
    "addr:street":"Thurlbear Rd",
    "iso:country":"GB",
    "sg:address":"196 Thurlbear Rd, Thurlbear",
    "sg:city":"Taunton",
    "sg:classifiers":[
        {
            "category":"Building & Trades",
            "subcategory":"Construction",
            "type":"Services"
        }
    ],
    "sg:postcode":"TA3 5DQ",
    "sg:province":"Devon",
    "sg:tags":[
        "builder"
    ],
    "wof:name":"Sparks,Gary,",
    "wof:placetype":"venue"
},
  "geometry": {"coordinates":[-3.048148,50.986523],"type":"Point"}
}