{
  "type": "Feature",
  "properties": {
    "addr:full":"63 Houldsworth St Manchester Greater Manchester M1 2ES",
    "addr:housenumber":"63",
    "addr:postcode":"m1 2es",
    "addr:street":"Houldsworth St",
    "iso:country":"GB",
    "sg:address":"63 Houldsworth St",
    "sg:city":"Manchester",
    "sg:classifiers":[
        {
            "category":"Home & Garden",
            "subcategory":"Home Furnishings",
            "type":"Retail Goods"
        }
    ],
    "sg:phone":"+44 161 237 1022",
    "sg:postcode":"M1 2ES",
    "sg:province":"Greater Manchester",
    "sg:tags":[
        "homefurnishings"
    ],
    "wof:name":"R Jeffay",
    "wof:placetype":"venue"
},
  "geometry": {"coordinates":[-2.230013,53.4828],"type":"Point"}
}