{
  "type": "Feature",
  "properties": {
    "addr:full":"235 Walsall Wood Rd Walsall Staffordshire WS9 8HQ",
    "addr:housenumber":"235",
    "addr:postcode":"ws9 8hq",
    "addr:street":"Walsall Wood Rd",
    "iso:country":"GB",
    "sg:address":"235 Walsall Wood Rd",
    "sg:city":"Walsall",
    "sg:classifiers":[
        {
            "category":"Building & Trades",
            "subcategory":"Construction",
            "type":"Services"
        }
    ],
    "sg:phone":"+44 1922 744124",
    "sg:postcode":"WS9 8HQ",
    "sg:province":"Staffordshire",
    "sg:tags":[
        "decorator",
        "painter"
    ],
    "wof:name":"N.A Davis Decorators",
    "wof:placetype":"venue"
},
  "geometry": {"coordinates":[-1.918126,52.618465],"type":"Point"}
}