{
  "type": "Feature",
  "properties": {
    "iso:country":"GB",
    "sg:address":"Rusthall Farm, Tea Garden Lane",
    "sg:city":"Tunbridge Wells",
    "sg:classifiers":[
        {
            "category":"Home & Garden",
            "subcategory":"Household Appliances",
            "type":"Retail Goods"
        }
    ],
    "sg:phone":"+44 1892 535559",
    "sg:postcode":"TN3 9JH",
    "sg:province":"East Sussex",
    "sg:tags":[
        "electrical"
    ],
    "wof:name":"Stone Refrigeration",
    "wof:placetype":"venue"
},
  "geometry": {"coordinates":[0.23097,51.1292],"type":"Point"}
}