{
  "type": "Feature",
  "properties": {
    "iso:country":"GB",
    "sg:address":"Byres Rd",
    "sg:city":"Motherwell",
    "sg:classifiers":[
        {
            "category":"Social Services",
            "subcategory":"Child Care",
            "type":"Services"
        },
        {
            "category":"Social Services",
            "subcategory":"Adult Care",
            "type":"Services"
        }
    ],
    "sg:phone":"+44 1698 733929",
    "sg:postcode":"ML1 5BD",
    "sg:province":"North Lanarkshire",
    "sg:tags":[
        "day",
        "centre"
    ],
    "wof:name":"John Doyle Senior Citizens Centre",
    "wof:placetype":"venue"
},
  "geometry": {"coordinates":[-3.934999,55.811642],"type":"Point"}
}