{
  "type": "Feature",
  "properties": {
    "iso:country":"GB",
    "sg:address":"22 Southgate Street, Long Melford",
    "sg:city":"Sudbury",
    "sg:classifiers":[
        {
            "category":"Cinema",
            "subcategory":"Movie Rental",
            "type":"Entertainment"
        }
    ],
    "sg:postcode":"CO10 9HU",
    "sg:province":"Essex",
    "sg:tags":[
        "video",
        "library"
    ],
    "wof:name":"SUFFOLK VIDEO",
    "wof:placetype":"venue"
},
  "geometry": {"coordinates":[0.714109,52.068859],"type":"Point"}
}