{
  "type": "Feature",
  "properties": {
    "addr:full":"Perkins Way, Mansfield Rd Derby Derbyshire DE21 4BA",
    "addr:postcode":"de21 4ba",
    "addr:street":"Perkins Way Mansfield Rd",
    "iso:country":"GB",
    "sg:address":"Perkins Way, Mansfield Rd",
    "sg:city":"Derby",
    "sg:classifiers":[
        {
            "category":"Professional",
            "subcategory":"Business Services",
            "type":"Services"
        }
    ],
    "sg:phone":"+44 1332 293900",
    "sg:postcode":"DE21 4BA",
    "sg:province":"Derbyshire",
    "sg:tags":[
        "agent",
        "manufacturers'"
    ],
    "wof:name":"Acorn Confectionery Ltd",
    "wof:placetype":"venue"
},
  "geometry": {"coordinates":[-1.4745700359,52.9273796082],"type":"Point"}
}