{
  "type": "Feature",
  "properties": {
    "addr:full":"890 Hedon Road Hull East Riding of Yorkshire HU9 5PL",
    "addr:housenumber":"890",
    "addr:postcode":"hu9 5pl",
    "addr:street":"Hedon Road",
    "iso:country":"GB",
    "sg:address":"890 Hedon Road",
    "sg:city":"Hull",
    "sg:classifiers":[
        {
            "category":"Shopping",
            "subcategory":"Department Store",
            "type":"Retail Goods"
        }
    ],
    "sg:phone":"+44 1482 211053",
    "sg:postcode":"HU9 5PL",
    "sg:province":"East Riding of Yorkshire",
    "wof:name":"Discount Carpets",
    "wof:placetype":"venue"
},
  "geometry": {"coordinates":[-0.2856259942,53.7478790283],"type":"Point"}
}