{
  "type": "Feature",
  "properties": {
    "addr:full":"60 Brookley Road Brockenhurst Hampshire SO42 7RA",
    "addr:housenumber":"60",
    "addr:postcode":"so42 7ra",
    "addr:street":"Brookley Road",
    "iso:country":"GB",
    "sg:address":"60 Brookley Road",
    "sg:city":"Brockenhurst",
    "sg:classifiers":[
        {
            "category":"Shopping",
            "subcategory":"Gifts & Souvenirs",
            "type":"Retail Goods"
        }
    ],
    "sg:phone":"+44 1590 623779",
    "sg:postcode":"SO42 7RA",
    "sg:province":"Hampshire",
    "sg:tags":[
        "shop"
    ],
    "wof:name":"Pot Pourri",
    "wof:placetype":"venue"
},
  "geometry": {"coordinates":[-1.577419,50.819351],"type":"Point"}
}