{
  "type": "Feature",
  "properties": {
    "iso:country":"GB",
    "sg:address":"25-27 Brown Street",
    "sg:city":"Salisbury",
    "sg:classifiers":[
        {
            "category":"Shopping",
            "type":"Retail Goods"
        }
    ],
    "sg:phone":"+44 1722 328601",
    "sg:postcode":"SP1 2AS",
    "sg:province":"Wiltshire",
    "sg:tags":[
        "part",
        "accessory"
    ],
    "wof:name":"Motaman (Salisbury) Ltd.",
    "wof:placetype":"venue"
},
  "geometry": {"coordinates":[-1.7926,51.068356],"type":"Point"}
}