{
  "type": "Feature",
  "properties": {
    "iso:country":"GB",
    "sg:address":"14 Poplar Rd, Kings Heath",
    "sg:city":"Birmingham",
    "sg:classifiers":[
        {
            "category":"Shopping",
            "subcategory":"Gifts & Souvenirs",
            "type":"Retail Goods"
        },
        {
            "category":"Shopping",
            "type":"Retail Goods"
        }
    ],
    "sg:phone":"+44 121 443 5808",
    "sg:postcode":"B14 7AD",
    "sg:province":"West Midlands",
    "sg:tags":[
        "shop",
        "new age"
    ],
    "wof:name":"Armadillo",
    "wof:placetype":"venue"
},
  "geometry": {"coordinates":[-1.89207,52.435791],"type":"Point"}
}