{
  "type": "Feature",
  "properties": {
    "addr:full":"40 High Street Lewes East Sussex BN7 2LU",
    "addr:housenumber":"40",
    "addr:postcode":"bn7 2lu",
    "addr:street":"High Street",
    "iso:country":"GB",
    "sg:address":"40 High Street",
    "sg:city":"Lewes",
    "sg:classifiers":[
        {
            "category":"Home & Garden",
            "subcategory":"Carpets & Floor Coverings",
            "type":"Retail Goods"
        }
    ],
    "sg:phone":"+44 1273 478363",
    "sg:postcode":"BN7 2LU",
    "sg:province":"East Sussex",
    "sg:tags":[
        "carpets",
        "rug",
        "matting"
    ],
    "wof:name":"Barbican Carpets",
    "wof:placetype":"venue"
},
  "geometry": {"coordinates":[0.0111269997,50.8732948303],"type":"Point"}
}