{
  "type": "Feature",
  "properties": {
    "addr:full":"32 Crawley Grn Road Luton Bedfordshire LU2 0QX",
    "addr:housenumber":"32",
    "addr:postcode":"lu2 0qx",
    "addr:street":"Crawley Grn Road",
    "iso:country":"GB",
    "sg:address":"32 Crawley Grn Road",
    "sg:city":"Luton",
    "sg:classifiers":[
        {
            "category":"Professional",
            "subcategory":"Engineering",
            "type":"Services"
        },
        {
            "category":"Building & Trades",
            "subcategory":"Electrical",
            "type":"Services"
        }
    ],
    "sg:phone":"+44 1582 728016",
    "sg:postcode":"LU2 0QX",
    "sg:province":"Bedfordshire",
    "sg:tags":[
        "engineer",
        "electrician",
        "contractor"
    ],
    "wof:name":"Mcneilly Electrical Services",
    "wof:placetype":"venue"
},
  "geometry": {"coordinates":[-0.4022449851,51.8796730042],"type":"Point"}
}