{
  "type": "Feature",
  "properties": {
    "addr:full":"227 Crompton Road Macclesfield Cheshire SK11 8EZ",
    "addr:housenumber":"227",
    "addr:postcode":"sk11 8ez",
    "addr:street":"Crompton Road",
    "iso:country":"GB",
    "sg:address":"227 Crompton Road",
    "sg:city":"Macclesfield",
    "sg:classifiers":[
        {
            "category":"Fast Food",
            "type":"Food & Drink"
        },
        {
            "category":"Food & Beverages",
            "subcategory":"Meat & Fish",
            "type":"Retail Goods"
        }
    ],
    "sg:phone":"+44 1625 424984",
    "sg:postcode":"SK11 8EZ",
    "sg:province":"Cheshire",
    "sg:tags":[
        "shop",
        "chip"
    ],
    "wof:name":"Crompton Road Chippy",
    "wof:placetype":"venue"
},
  "geometry": {"coordinates":[-2.135525,53.254585],"type":"Point"}
}