{
  "type": "Feature",
  "properties": {
    "addr:full":"78 Hermit Road London Greater London E16 4LF",
    "addr:housenumber":"78",
    "addr:postcode":"e16 4lf",
    "addr:street":"Hermit Road",
    "iso:country":"GB",
    "sg:address":"78 Hermit Road",
    "sg:city":"London",
    "sg:classifiers":[
        {
            "category":"Fast Food",
            "type":"Food & Drink"
        }
    ],
    "sg:phone":"+44 20 7476 5476",
    "sg:postcode":"E16 4LF",
    "sg:province":"Greater London",
    "sg:tags":[
        "away",
        "take"
    ],
    "wof:name":"Georges Pie & Mash Shop",
    "wof:placetype":"venue"
},
  "geometry": {"coordinates":[0.012425,51.520336],"type":"Point"}
}