{
  "type": "Feature",
  "properties": {
    "addr:full":"17 Rowan Avenue, Dawley Telford Shropshire TF4 3PN",
    "addr:housenumber":"17",
    "addr:postcode":"tf4 3pn",
    "addr:street":"Rowan Avenue",
    "iso:country":"GB",
    "sg:address":"17 Rowan Avenue, Dawley",
    "sg:city":"Telford",
    "sg:classifiers":[
        {
            "category":"Organizations",
            "subcategory":"Non-profit Organization",
            "type":"Services"
        }
    ],
    "sg:phone":"+44 1952 591793",
    "sg:postcode":"TF4 3PN",
    "sg:province":"Shropshire",
    "sg:tags":[
        "organisation",
        "voluntary",
        "charity"
    ],
    "wof:name":"The Parkinson's Disease Society",
    "wof:placetype":"venue"
},
  "geometry": {"coordinates":[-2.459316,52.657993],"type":"Point"}
}