{
  "type": "Feature",
  "properties": {
    "addr:full":"Nine Acres, Stillington Road, Easingwold York North Yorkshire YO61 3DZ",
    "addr:postcode":"yo61 3dz",
    "addr:street":"Stillington Road",
    "iso:country":"GB",
    "sg:address":"Nine Acres, Stillington Road, Easingwold",
    "sg:city":"York",
    "sg:classifiers":[
        {
            "category":"Bus Charters",
            "type":"Transportation"
        }
    ],
    "sg:phone":"+44 1347 838990",
    "sg:postcode":"YO61 3DZ",
    "sg:province":"North Yorkshire",
    "sg:tags":[
        "hire",
        "coach"
    ],
    "wof:name":"Harry J Stephenson",
    "wof:placetype":"venue"
},
  "geometry": {"coordinates":[-1.1923099756,54.1214141846],"type":"Point"}
}