{
  "type": "Feature",
  "properties": {
    "addr:full":"Boghead Of Orrock Farm, Balmedie Aberdeen Aberdeen City AB23 8YA",
    "addr:postcode":"ab23 8ya",
    "addr:street":"Balmedie",
    "iso:country":"GB",
    "sg:address":"Boghead Of Orrock Farm, Balmedie",
    "sg:city":"Aberdeen",
    "sg:classifiers":[
        {
            "category":"Home & Garden",
            "subcategory":"Garden Supply",
            "type":"Retail Goods"
        },
        {
            "category":"Farming",
            "subcategory":"Farm",
            "type":"Manufacturing & Wholesale Goods"
        }
    ],
    "sg:postcode":"AB23 8YA",
    "sg:province":"Aberdeen City",
    "sg:tags":[
        "mixed",
        "bulb",
        "crop",
        "grower"
    ],
    "wof:name":"I & I Christie",
    "wof:placetype":"venue"
},
  "geometry": {"coordinates":[-2.056249,57.249691],"type":"Point"}
}