{
  "type": "Feature",
  "properties": {
    "iso:country":"GB",
    "sg:address":"11 Hill St",
    "sg:city":"Southport",
    "sg:classifiers":[
        {
            "category":"Professional",
            "subcategory":"Management & Consulting",
            "type":"Services"
        }
    ],
    "sg:phone":"+44 1704 547838",
    "sg:postcode":"PR9 0NW",
    "sg:province":"Lancashire",
    "sg:tags":[
        "consultant",
        "promotion",
        "sale"
    ],
    "wof:name":"Thurrock",
    "wof:placetype":"venue"
},
  "geometry": {"coordinates":[-3.000938,53.649536],"type":"Point"}
}