{
  "type": "Feature",
  "properties": {
    "addr:full":"6 The Willows, Glinton Peterborough Cambridgeshire PE6 7NE",
    "addr:housenumber":"6",
    "addr:postcode":"pe6 7ne",
    "addr:street":"The Willows",
    "iso:country":"GB",
    "sg:address":"6 The Willows, Glinton",
    "sg:city":"Peterborough",
    "sg:classifiers":[
        {
            "category":"Professional",
            "subcategory":"Employment Agencies",
            "type":"Services"
        }
    ],
    "sg:phone":"+44 1733 252799",
    "sg:postcode":"PE6 7NE",
    "sg:province":"Cambridgeshire",
    "sg:tags":[
        "career",
        "guidance"
    ],
    "wof:name":"Simon Bysshe & Associates",
    "wof:placetype":"venue"
},
  "geometry": {"coordinates":[-0.289705,52.635857],"type":"Point"}
}