{
  "type": "Feature",
  "properties": {
    "addr:full":"Broadway Grays Essex RM17 6EW",
    "addr:postcode":"rm17 6ew",
    "addr:street":"Broadway",
    "iso:country":"GB",
    "sg:address":"Broadway",
    "sg:city":"Grays",
    "sg:classifiers":[
        {
            "category":"Bars & Pubs",
            "type":"Food & Drink"
        }
    ],
    "sg:phone":"+44 1375 372628",
    "sg:postcode":"RM17 6EW",
    "sg:province":"Essex",
    "sg:tags":[
        "pubs",
        "inn"
    ],
    "wof:name":"Half Moon",
    "wof:placetype":"venue"
},
  "geometry": {"coordinates":[0.33755,51.476303],"type":"Point"}
}