{
  "type": "Feature",
  "properties": {
    "iso:country":"GB",
    "sg:address":"147 Westbourne St",
    "sg:city":"Hove",
    "sg:classifiers":[
        {
            "category":"Shopping",
            "subcategory":"News",
            "type":"Retail Goods"
        }
    ],
    "sg:postcode":"BN3 5FB",
    "sg:province":"East Sussex",
    "sg:tags":[
        "newsagent"
    ],
    "wof:name":"Sienkowski,Mavis,",
    "wof:placetype":"venue"
},
  "geometry": {"coordinates":[-0.1808539927,50.8348693848],"type":"Point"}
}