{
  "type": "Feature",
  "properties": {
    "iso:country":"GB",
    "sg:address":"89a Ten Acres Lane, Newton Heath",
    "sg:city":"Manchester",
    "sg:classifiers":[
        {
            "category":"Community Center",
            "type":"Public Place"
        }
    ],
    "sg:phone":"+44 161 205 0241",
    "sg:postcode":"M40 2SP",
    "sg:province":"Greater Manchester",
    "sg:tags":[
        "recreation",
        "leisure",
        "centre"
    ],
    "wof:name":"Ten Acres Complex",
    "wof:placetype":"venue"
},
  "geometry": {"coordinates":[-2.193731,53.497189],"type":"Point"}
}