{
  "type": "Feature",
  "properties": {
    "addr:full":"124 Harrowdene Road Wembley Greater London HA0 2JF",
    "addr:housenumber":"124",
    "addr:postcode":"ha0 2jf",
    "addr:street":"Harrowdene Road",
    "iso:country":"GB",
    "sg:address":"124 Harrowdene Road",
    "sg:city":"Wembley",
    "sg:classifiers":[
        {
            "category":"Health Services",
            "subcategory":"Nursing And Care Facility",
            "type":"Services"
        }
    ],
    "sg:phone":"+44 20 8904 8244",
    "sg:postcode":"HA0 2JF",
    "sg:province":"Greater London",
    "sg:tags":[
        "home"
    ],
    "wof:name":"Imalgo Ltd.",
    "wof:placetype":"venue"
},
  "geometry": {"coordinates":[-0.3042129874,51.5615882874],"type":"Point"}
}