{
  "type": "Feature",
  "properties": {
    "addr:full":"Rooms 14-15 Bar La Indust Est, Bar La Nottingham Nottinghamshire NG6 0JA",
    "addr:housenumber":"14-15",
    "addr:postcode":"ng6 0ja",
    "iso:country":"GB",
    "sg:address":"Rooms 14-15 Bar La Indust Est, Bar La",
    "sg:city":"Nottingham",
    "sg:classifiers":[
        {
            "category":"Education",
            "subcategory":"Dance Studio",
            "type":"Public Place"
        }
    ],
    "sg:postcode":"NG6 0JA",
    "sg:province":"Nottinghamshire",
    "sg:tags":[
        "toning"
    ],
    "wof:name":"Kent,Kathleen,",
    "wof:placetype":"venue"
},
  "geometry": {"coordinates":[-1.19021,52.978081],"type":"Point"}
}