{
  "type": "Feature",
  "properties": {
    "addr:full":"20 Estcourt Rd Great Yarmouth Norfolk NR30 4JG",
    "addr:housenumber":"20",
    "addr:postcode":"nr30 4jg",
    "addr:street":"Estcourt Rd",
    "iso:country":"GB",
    "sg:address":"20 Estcourt Rd",
    "sg:city":"Great Yarmouth",
    "sg:classifiers":[
        {
            "category":"Food & Beverages",
            "subcategory":"Groceries & Convenience Stores",
            "type":"Retail Goods"
        }
    ],
    "sg:phone":"+44 1493 332607",
    "sg:postcode":"NR30 4JG",
    "sg:province":"Norfolk",
    "sg:tags":[
        "merchant",
        "potato"
    ],
    "wof:name":"Norfolk Produce",
    "wof:placetype":"venue"
},
  "geometry": {"coordinates":[1.73146,52.616241],"type":"Point"}
}