{
  "type": "Feature",
  "properties": {
    "iso:country":"GB",
    "sg:address":"16 Morrison Place, Darfield",
    "sg:city":"Barnsley",
    "sg:classifiers":[
        {
            "category":"Building & Trades",
            "subcategory":"Cleaning & Sanitation",
            "type":"Services"
        }
    ],
    "sg:phone":"+44 1226 755132",
    "sg:postcode":"S73 9EF",
    "sg:province":"South Yorkshire",
    "sg:tags":[
        "sweep",
        "chimney"
    ],
    "wof:name":"Peter Molyneux",
    "wof:placetype":"venue"
},
  "geometry": {"coordinates":[-1.381466,53.536785],"type":"Point"}
}