{
  "type": "Feature",
  "properties": {
    "addr:full":"178-184 London Rd Sheffield South Yorkshire S2 4LT",
    "addr:housenumber":"178-184",
    "addr:postcode":"s2 4lt",
    "addr:street":"London Rd",
    "iso:country":"GB",
    "sg:address":"178-184 London Rd",
    "sg:city":"Sheffield",
    "sg:classifiers":[
        {
            "category":"Autos & Motor Vehicles",
            "subcategory":"Automobile Sales",
            "type":"Retail Goods"
        }
    ],
    "sg:postcode":"S2 4LT",
    "sg:province":"South Yorkshire",
    "sg:tags":[
        "car"
    ],
    "wof:name":"Carfour Sheffield Ltd",
    "wof:placetype":"venue"
},
  "geometry": {"coordinates":[-1.476845026,53.3690452576],"type":"Point"}
}