{
  "type": "Feature",
  "properties": {
    "addr:full":"79 Portland Rd South Norwood Greater London SE25 4UN",
    "addr:housenumber":"79",
    "addr:postcode":"se25 4un",
    "addr:street":"Portland Rd",
    "iso:country":"GB",
    "sg:address":"79 Portland Rd",
    "sg:city":"South Norwood",
    "sg:classifiers":[
        {
            "category":"Shopping",
            "subcategory":"Pets & Pet Supplies",
            "type":"Retail Goods"
        }
    ],
    "sg:phone":"+44 20 8654 3676",
    "sg:postcode":"SE25 4UN",
    "sg:province":"Greater London",
    "wof:name":"Portland Petshop",
    "wof:placetype":"venue"
},
  "geometry": {"coordinates":[-0.0712850019,51.3976097107],"type":"Point"}
}