{
  "type": "Feature",
  "properties": {
    "addr:full":"Tarporley Road, Lower Whitley Warrington Cheshire WA4 4EZ",
    "addr:postcode":"wa4 4ez",
    "addr:street":"Tarporley Road",
    "iso:country":"GB",
    "sg:address":"Tarporley Road, Lower Whitley",
    "sg:city":"Warrington",
    "sg:classifiers":[
        {
            "category":"Autos & Motor Vehicles",
            "subcategory":"Automobile Sales",
            "type":"Retail Goods"
        }
    ],
    "sg:phone":"+44 1928 717100",
    "sg:postcode":"WA4 4EZ",
    "sg:province":"Cheshire",
    "sg:tags":[
        "commercial"
    ],
    "wof:name":"H L Davies",
    "wof:placetype":"venue"
},
  "geometry": {"coordinates":[-2.574819,53.333324],"type":"Point"}
}