{
  "type": "Feature",
  "properties": {
    "addr:full":"Castle View Forge, Station Road Newcastle Emlyn Carmarthenshire SA38 9BX",
    "addr:postcode":"sa38 9bx",
    "addr:street":"Castle;Station Road",
    "iso:country":"GB",
    "sg:address":"Castle View Forge, Station Road",
    "sg:city":"Newcastle Emlyn",
    "sg:classifiers":[
        {
            "category":"Manufacturing",
            "subcategory":"Metals",
            "type":"Manufacturing & Wholesale Goods"
        }
    ],
    "sg:phone":"+44 1239 711337",
    "sg:postcode":"SA38 9BX",
    "sg:province":"Carmarthenshire",
    "sg:tags":[
        "blacksmith",
        "forgemasters"
    ],
    "wof:name":"B E M",
    "wof:placetype":"venue"
},
  "geometry": {"coordinates":[-4.467984,52.035919],"type":"Point"}
}