{
  "type": "Feature",
  "properties": {
    "addr:full":"Horsford Medical Centre, 205 Holt Rd Norwich Norfolk NR10 3DX",
    "addr:housenumber":"205",
    "addr:postcode":"nr10 3dx",
    "addr:street":"Holt Rd",
    "iso:country":"GB",
    "sg:address":"Horsford Medical Centre, 205 Holt Rd",
    "sg:city":"Norwich",
    "sg:classifiers":[
        {
            "category":"Health Services",
            "subcategory":"Doctor",
            "type":"Services"
        }
    ],
    "sg:phone":"+44 1603 897766",
    "sg:postcode":"NR10 3DX",
    "sg:province":"Norfolk",
    "sg:tags":[
        "practitioners"
    ],
    "wof:name":"O'Neill, H",
    "wof:placetype":"venue"
},
  "geometry": {"coordinates":[1.2948999405,52.6224937439],"type":"Point"}
}