{
  "type": "Feature",
  "properties": {
    "iso:country":"GB",
    "sg:address":"48 Springfields",
    "sg:city":"Wadhurst",
    "sg:classifiers":[
        {
            "category":"Professional",
            "subcategory":"Detective & Security Services",
            "type":"Services"
        }
    ],
    "sg:phone":"+44 1580 201427",
    "sg:postcode":"TN5 7BS",
    "sg:province":"East Sussex",
    "sg:tags":[
        "locksmith"
    ],
    "wof:name":"Lock & Safe Co The",
    "wof:placetype":"venue"
},
  "geometry": {"coordinates":[0.413096,51.046253],"type":"Point"}
}