{
  "type": "Feature",
  "properties": {
    "iso:country":"GB",
    "sg:address":"149 Newport Rd",
    "sg:city":"Stafford",
    "sg:classifiers":[
        {
            "category":"Banks & Credit Unions",
            "subcategory":"Financial Services",
            "type":"Services"
        }
    ],
    "sg:phone":"+44 1785 256590",
    "sg:postcode":"ST16 2EZ",
    "sg:province":"Staffordshire",
    "sg:tags":[
        "cashing",
        "cheque"
    ],
    "wof:name":"Cashflow",
    "wof:placetype":"venue"
},
  "geometry": {"coordinates":[-2.115727,52.803932],"type":"Point"}
}