{
  "type": "Feature",
  "properties": {
    "iso:country":"GB",
    "sg:address":"Llanyravon Way, Llanyravon",
    "sg:city":"Cwmbran",
    "sg:classifiers":[
        {
            "category":"Place Of Worship",
            "type":"Public Place"
        }
    ],
    "sg:phone":"+44 1633 870695",
    "sg:postcode":"NP44 8HW",
    "sg:province":"Monmouthshire",
    "wof:name":"Llanyravon Methodist Church",
    "wof:placetype":"venue"
},
  "geometry": {"coordinates":[-2.999225,51.642979],"type":"Point"}
}