{
  "type": "Feature",
  "properties": {
    "addr:full":"20 Holmwood Road, Cheam Sutton Surrey SM2 7JR",
    "addr:housenumber":"20",
    "addr:postcode":"sm2 7jr",
    "addr:street":"Holmwood Road",
    "iso:country":"GB",
    "sg:address":"20 Holmwood Road, Cheam",
    "sg:city":"Sutton",
    "sg:classifiers":[
        {
            "category":"Building & Trades",
            "subcategory":"Construction",
            "type":"Services"
        }
    ],
    "sg:phone":"+44 20 8394 0541",
    "sg:postcode":"SM2 7JR",
    "sg:province":"Surrey",
    "sg:tags":[
        "joinery",
        "joiner",
        "carpenter",
        "carpentry"
    ],
    "wof:name":"A M HILL",
    "wof:placetype":"venue"
},
  "geometry": {"coordinates":[-0.232287,51.348293],"type":"Point"}
}