{
  "type": "Feature",
  "properties": {
    "iso:country":"GB",
    "sg:address":"Bandywood Crescent",
    "sg:city":"Birmingham",
    "sg:classifiers":[
        {
            "category":"Place Of Worship",
            "type":"Public Place"
        },
        {
            "category":"Social Services",
            "subcategory":"Child Care",
            "type":"Services"
        },
        {
            "category":"Social Services",
            "subcategory":"Adult Care",
            "type":"Services"
        }
    ],
    "sg:phone":"+44 121 360 4298",
    "sg:postcode":"B44 9JX",
    "sg:province":"West Midlands",
    "sg:tags":[
        "day",
        "centre"
    ],
    "wof:name":"St Mark's Day Centre",
    "wof:placetype":"venue"
},
  "geometry": {"coordinates":[-1.888430953,52.5560951233],"type":"Point"}
}