{
  "type": "Feature",
  "properties": {
    "addr:full":"142-144 Northenden Road Sale Cheshire M33 3HE",
    "addr:housenumber":"142-144",
    "addr:postcode":"m33 3he",
    "addr:street":"Northenden Road",
    "iso:country":"GB",
    "sg:address":"142-144 Northenden Road",
    "sg:city":"Sale",
    "sg:classifiers":[
        {
            "category":"Retail",
            "subcategory":"Car Wash",
            "type":"Services"
        }
    ],
    "sg:phone":"+44 161 962 5673",
    "sg:postcode":"M33 3HE",
    "sg:province":"Cheshire",
    "sg:tags":[
        "polishing",
        "washing"
    ],
    "wof:name":"I M O Car Wash",
    "wof:placetype":"venue"
},
  "geometry": {"coordinates":[-2.304908,53.420124],"type":"Point"}
}