{
  "type": "Feature",
  "properties": {
    "iso:country":"GB",
    "sg:address":"Derwent Road",
    "sg:city":"Leighton Buzzard",
    "sg:classifiers":[
        {
            "category":"Education",
            "subcategory":"School",
            "type":"Public Place"
        }
    ],
    "sg:phone":"+44 1525 371735",
    "sg:postcode":"LU7 2XT",
    "sg:province":"Bedfordshire",
    "sg:tags":[
        "local",
        "authority"
    ],
    "wof:name":"Greenleas Lower School",
    "wof:placetype":"venue"
},
  "geometry": {"coordinates":[-0.690499,51.921803],"type":"Point"}
}