{
  "type": "Feature",
  "properties": {
    "addr:full":"8 Symington Street Northampton Northamptonshire NN5 7AU",
    "addr:housenumber":"8",
    "addr:postcode":"nn5 7au",
    "addr:street":"Symington Street",
    "iso:country":"GB",
    "sg:address":"8 Symington Street",
    "sg:city":"Northampton",
    "sg:classifiers":[
        {
            "category":"Health Services",
            "subcategory":"Hospital",
            "type":"Services"
        }
    ],
    "sg:postcode":"NN5 7AU",
    "sg:province":"Northamptonshire",
    "sg:tags":[
        "ambulance"
    ],
    "wof:name":"Northampton Private Ambulance Services",
    "wof:placetype":"venue"
},
  "geometry": {"coordinates":[-0.915525,52.241825],"type":"Point"}
}