{
  "type": "Feature",
  "properties": {
    "iso:country":"GB",
    "sg:address":", Llanilar",
    "sg:city":"Aberystwyth",
    "sg:classifiers":[
        {
            "category":"Retail",
            "subcategory":"Auto Repair",
            "type":"Services"
        }
    ],
    "sg:phone":"+44 1974 241267",
    "sg:postcode":"SY23 4NZ",
    "sg:province":"Ceredigion",
    "sg:tags":[
        "modification",
        "car",
        "vehicle",
        "commercial",
        "garage"
    ],
    "wof:name":"Ystwyth Garage",
    "wof:placetype":"venue"
},
  "geometry": {"coordinates":[-4.029389,52.356586],"type":"Point"}
}