{
  "type": "Feature",
  "properties": {
    "iso:country":"GB",
    "sg:address":"296-298 Great Western Rd",
    "sg:city":"Glasgow",
    "sg:classifiers":[
        {
            "category":"Autos & Motor Vehicles",
            "subcategory":"Motorcycle Sales",
            "type":"Retail Goods"
        }
    ],
    "sg:phone":"+44 141 332 8226",
    "sg:postcode":"G4 9EJ",
    "sg:province":"Glasgow City",
    "sg:tags":[
        "component"
    ],
    "wof:name":"Bike Sorce",
    "wof:placetype":"venue"
},
  "geometry": {"coordinates":[-4.2743320465,55.8731575012],"type":"Point"}
}