{
  "type": "Feature",
  "properties": {
    "addr:full":"14 Mortlock Street, Melbourn Royston Bedfordshire SG8 6DB",
    "addr:housenumber":"14",
    "addr:postcode":"sg8 6db",
    "addr:street":"Mortlock Street",
    "iso:country":"GB",
    "sg:address":"14 Mortlock Street, Melbourn",
    "sg:city":"Royston",
    "sg:classifiers":[
        {
            "category":"Retail",
            "subcategory":"Auto Repair",
            "type":"Services"
        }
    ],
    "sg:postcode":"SG8 6DB",
    "sg:province":"Bedfordshire",
    "sg:tags":[
        "body",
        "car"
    ],
    "wof:name":"P F Prime",
    "wof:placetype":"venue"
},
  "geometry": {"coordinates":[0.017076,52.082775],"type":"Point"}
}