{
  "type": "Feature",
  "properties": {
    "iso:country":"GB",
    "sg:address":"Racecourse Retail Park, Topham Dv",
    "sg:city":"Liverpool",
    "sg:classifiers":[
        {
            "category":"Home & Garden",
            "subcategory":"Home Furnishings",
            "type":"Retail Goods"
        }
    ],
    "sg:phone":"+44 151 525 0401",
    "sg:postcode":"L9 5AN",
    "sg:province":"Merseyside",
    "sg:tags":[
        "furnishers",
        "planner",
        "kitchen"
    ],
    "wof:name":"Magnet Ltd.",
    "wof:placetype":"venue"
},
  "geometry": {"coordinates":[-2.950484,53.482635],"type":"Point"}
}