{
  "type": "Feature",
  "properties": {
    "addr:full":"West Lambrook Farm, West Lambrook South Petherton Somerset TA13 5HA",
    "addr:housenumber":"farm",
    "addr:postcode":"ta13 5ha",
    "addr:street":"West Lambrook;West Lambrook",
    "iso:country":"GB",
    "sg:address":"West Lambrook Farm, West Lambrook",
    "sg:city":"South Petherton",
    "sg:classifiers":[
        {
            "category":"Farming",
            "subcategory":"Farm",
            "type":"Manufacturing & Wholesale Goods"
        }
    ],
    "sg:phone":"+44 1460 240318",
    "sg:postcode":"TA13 5HA",
    "sg:province":"Somerset",
    "sg:tags":[
        "mixed",
        "crop"
    ],
    "wof:name":"G & R  Batstone",
    "wof:placetype":"venue"
},
  "geometry": {"coordinates":[-2.805539,50.949532],"type":"Point"}
}