{
  "type": "Feature",
  "properties": {
    "iso:country":"GB",
    "sg:address":"Unit 8 Worcester Road, Hoobrook Enterprise Centre",
    "sg:city":"Kidderminster",
    "sg:classifiers":[
        {
            "category":"Transit Center",
            "subcategory":"Freight",
            "type":"Transportation"
        }
    ],
    "sg:postcode":"DY10 1HB",
    "sg:province":"Staffordshire",
    "sg:tags":[
        "piano",
        "accessory"
    ],
    "wof:name":"1st Pianos",
    "wof:placetype":"venue"
},
  "geometry": {"coordinates":[-2.2457818985,52.3859596252],"type":"Point"}
}