{
  "type": "Feature",
  "properties": {
    "iso:country":"GB",
    "sg:address":"36 Wade Avenue",
    "sg:city":"Ilkeston",
    "sg:classifiers":[
        {
            "category":"Building & Trades",
            "subcategory":"Construction",
            "type":"Services"
        }
    ],
    "sg:postcode":"DE7 5DU",
    "sg:province":"Derbyshire",
    "sg:tags":[
        "builder"
    ],
    "wof:name":"Mike Edwards",
    "wof:placetype":"venue"
},
  "geometry": {"coordinates":[-1.2946310043,52.9677238464],"type":"Point"}
}