{
  "type": "Feature",
  "properties": {
    "addr:full":"Newlands Farm, Canterbury Road, Selsted Dover Kent CT15 7HL",
    "addr:postcode":"ct15 7hl",
    "addr:street":"Canterbury Road;Dover",
    "iso:country":"GB",
    "sg:address":"Newlands Farm, Canterbury Road, Selsted",
    "sg:city":"Dover",
    "sg:classifiers":[
        {
            "category":"Retail",
            "subcategory":"Auto Repair",
            "type":"Services"
        }
    ],
    "sg:phone":"+44 1303 844408",
    "sg:postcode":"CT15 7HL",
    "sg:province":"Kent",
    "sg:tags":[
        "modification",
        "garage"
    ],
    "wof:name":"Selsted Motors",
    "wof:placetype":"venue"
},
  "geometry": {"coordinates":[1.172877,51.159199],"type":"Point"}
}