{
  "type": "Feature",
  "properties": {
    "iso:country":"GB",
    "sg:address":"Unit 4, Dicksons Corner, Farthing Rd Ind Est",
    "sg:city":"Ipswich",
    "sg:classifiers":[
        {
            "category":"Autos & Motor Vehicles",
            "subcategory":"Auto Supplies",
            "type":"Retail Goods"
        }
    ],
    "sg:phone":"+44 1473 240505",
    "sg:postcode":"IP1 5AP",
    "sg:province":"Suffolk",
    "sg:tags":[
        "electric"
    ],
    "wof:name":"Anglian Rewinds",
    "wof:placetype":"venue"
},
  "geometry": {"coordinates":[1.1120200157,52.0658798218],"type":"Point"}
}