{
  "type": "Feature",
  "properties": {
    "iso:country":"GB",
    "sg:address":"11 Stonepail Road, Gatley",
    "sg:city":"Cheadle",
    "sg:classifiers":[
        {
            "category":"Home & Garden",
            "subcategory":"Household Appliances",
            "type":"Retail Goods"
        }
    ],
    "sg:phone":"+44 161 428 6444",
    "sg:postcode":"SK8 4EZ",
    "sg:province":"Cheshire",
    "sg:tags":[
        "domestic",
        "centre"
    ],
    "wof:name":"Gatley Domestics",
    "wof:placetype":"venue"
},
  "geometry": {"coordinates":[-2.240221,53.391308],"type":"Point"}
}