{
  "type": "Feature",
  "properties": {
    "addr:full":"Cleaning Centre, 101 Mill Lane Newbury Berkshire RG14 5RE",
    "addr:housenumber":"101",
    "addr:postcode":"rg14 5re",
    "addr:street":"Mill Lane",
    "iso:country":"GB",
    "sg:address":"Cleaning Centre, 101 Mill Lane",
    "sg:city":"Newbury",
    "sg:classifiers":[
        {
            "category":"Home & Garden",
            "subcategory":"Carpets & Floor Coverings",
            "type":"Retail Goods"
        }
    ],
    "sg:phone":"+44 1635 38500",
    "sg:postcode":"RG14 5RE",
    "sg:province":"Berkshire",
    "sg:tags":[
        "cleaner",
        "upholstery"
    ],
    "wof:name":"Servicemaster Ltd",
    "wof:placetype":"venue"
},
  "geometry": {"coordinates":[-1.3258719444,51.405872345],"type":"Point"}
}