{
  "type": "Feature",
  "properties": {
    "iso:country":"GB",
    "sg:address":"Nettlehill Rd, Houstoun Industrial Estate",
    "sg:city":"Livingston",
    "sg:classifiers":[
        {
            "category":"Professional",
            "subcategory":"Business Services",
            "type":"Services"
        }
    ],
    "sg:phone":"+44 1506 442086",
    "sg:postcode":"EH54 5DL",
    "sg:province":"West Lothian",
    "sg:tags":[
        "distribution"
    ],
    "wof:name":"Hays Logistics Uk",
    "wof:placetype":"venue"
},
  "geometry": {"coordinates":[-3.5060040951,55.9179534912],"type":"Point"}
}