{
  "type": "Feature",
  "properties": {
    "iso:country":"GB",
    "sg:address":"71 Stourport Road",
    "sg:city":"Kidderminster",
    "sg:classifiers":[
        {
            "category":"Personal",
            "subcategory":"Beauty Salon",
            "type":"Services"
        },
        {
            "category":"Personal",
            "subcategory":"Barber",
            "type":"Services"
        }
    ],
    "sg:phone":"+44 1562 515941",
    "sg:postcode":"DY11 7BQ",
    "sg:province":"Staffordshire",
    "sg:tags":[
        "unisex",
        "hairdresser"
    ],
    "wof:name":"Hair Zone",
    "wof:placetype":"venue"
},
  "geometry": {"coordinates":[-2.259703,52.376537],"type":"Point"}
}