{
  "type": "Feature",
  "properties": {
    "iso:country":"GB",
    "sg:address":"The Paddock, Temple Lane, East Meon",
    "sg:city":"Petersfield",
    "sg:classifiers":[
        {
            "category":"Building & Trades",
            "subcategory":"Plumbing",
            "type":"Services"
        }
    ],
    "sg:phone":"+44 1730 823204",
    "sg:postcode":"GU32 1PZ",
    "sg:province":"Hampshire",
    "sg:tags":[
        "heating"
    ],
    "wof:name":"D A Colbourne",
    "wof:placetype":"venue"
},
  "geometry": {"coordinates":[-1.032609,50.995689],"type":"Point"}
}