{
  "type": "Feature",
  "properties": {
    "addr:full":"Grenig Road Ammanford Carmarthenshire SA18 1EX",
    "addr:postcode":"sa18 1ex",
    "addr:street":"Grenig Road",
    "iso:country":"GB",
    "sg:address":"Grenig Road",
    "sg:city":"Ammanford",
    "sg:classifiers":[
        {
            "category":"Retail",
            "subcategory":"Auto Repair",
            "type":"Services"
        }
    ],
    "sg:phone":"+44 1269 822024",
    "sg:postcode":"SA18 1EX",
    "sg:province":"Carmarthenshire",
    "sg:tags":[
        "modification",
        "garage"
    ],
    "wof:name":"Brynrhos Garage",
    "wof:placetype":"venue"
},
  "geometry": {"coordinates":[-3.9305229187,51.8032073975],"type":"Point"}
}