{
  "type": "Feature",
  "properties": {
    "iso:country":"GB",
    "sg:address":"53 Forest Road",
    "sg:city":"Aberdeen",
    "sg:classifiers":[
        {
            "category":"Real Estate",
            "subcategory":"Surveying",
            "type":"Services"
        },
        {
            "category":"Real Estate",
            "subcategory":"Architect",
            "type":"Services"
        }
    ],
    "sg:phone":"+44 1224 633300",
    "sg:postcode":"AB15 4BN",
    "sg:province":"Aberdeen City",
    "sg:tags":[
        "surveyor",
        "valuer"
    ],
    "wof:name":"Emslie Commercials & Property Services",
    "wof:placetype":"venue"
},
  "geometry": {"coordinates":[-2.1290988922,57.1367416382],"type":"Point"}
}