{
  "type": "Feature",
  "properties": {
    "addr:full":"Denham Lodge, Stone Road, Eccleshall Stafford Staffordshire ST21 6DL",
    "addr:postcode":"st21 6dl",
    "addr:street":"Stone Road",
    "iso:country":"GB",
    "sg:address":"Denham Lodge, Stone Road, Eccleshall",
    "sg:city":"Stafford",
    "sg:classifiers":[
        {
            "category":"Farming",
            "subcategory":"Dairy Farm",
            "type":"Manufacturing & Wholesale Goods"
        }
    ],
    "sg:postcode":"ST21 6DL",
    "sg:province":"Staffordshire",
    "wof:name":"A G Talbot & Dairymen",
    "wof:placetype":"venue"
},
  "geometry": {"coordinates":[-2.2514541149,52.859287262],"type":"Point"}
}