{
  "type": "Feature",
  "properties": {
    "iso:country":"GB",
    "sg:address":"Redhill Rd",
    "sg:city":"Cobham",
    "sg:classifiers":[
        {
            "category":"Sports & Exercise",
            "subcategory":"Race Track",
            "type":"Entertainment"
        }
    ],
    "sg:phone":"+44 1372 470282",
    "sg:postcode":"KT11 1EQ",
    "sg:province":"Surrey",
    "sg:tags":[
        "motor"
    ],
    "wof:name":"The Quad Bike Centre",
    "wof:placetype":"venue"
},
  "geometry": {"coordinates":[-0.451761,51.337963],"type":"Point"}
}