{
  "type": "Feature",
  "properties": {
    "addr:full":"St Margarets Road, Hooley Coulsdon Surrey CR5 3RB",
    "addr:postcode":"cr5 3rb",
    "addr:street":"St Margarets Road",
    "iso:country":"GB",
    "sg:address":"St Margarets Road, Hooley",
    "sg:city":"Coulsdon",
    "sg:classifiers":[
        {
            "category":"Organizations",
            "subcategory":"Community Association",
            "type":"Services"
        },
        {
            "category":"Organizations",
            "subcategory":"Membership Organization",
            "type":"Services"
        }
    ],
    "sg:phone":"+44 1737 552783",
    "sg:postcode":"CR5 3RB",
    "sg:province":"Surrey",
    "sg:tags":[
        "club",
        "social"
    ],
    "wof:name":"Hooley Social Club",
    "wof:placetype":"venue"
},
  "geometry": {"coordinates":[-0.15525,51.29377],"type":"Point"}
}