{
  "type": "Feature",
  "properties": {
    "iso:country":"GB",
    "sg:address":"Deepdale Nurseries, Kirkham Rd, Freckleton",
    "sg:city":"Preston",
    "sg:classifiers":[
        {
            "category":"Food & Beverages",
            "subcategory":"Farmers Market",
            "type":"Retail Goods"
        }
    ],
    "sg:phone":"+44 1772 632622",
    "sg:postcode":"PR4 1HU",
    "sg:province":"Lancashire",
    "sg:tags":[
        "gardener"
    ],
    "wof:name":"R Wilcock & Son",
    "wof:placetype":"venue"
},
  "geometry": {"coordinates":[-2.882638,53.751686],"type":"Point"}
}