{
  "type": "Feature",
  "properties": {
    "iso:country":"GB",
    "sg:address":"First Floor, 51-53 Church Rd",
    "sg:city":"Ashford",
    "sg:classifiers":[
        {
            "category":"Government",
            "subcategory":"Post Office",
            "type":"Public Place"
        }
    ],
    "sg:postcode":"TW15 2TY",
    "sg:province":"Greater London",
    "sg:tags":[
        "organisation",
        "soc",
        "research"
    ],
    "wof:name":"Skin Research Centre (Uk) Ltd",
    "wof:placetype":"venue"
},
  "geometry": {"coordinates":[-0.464282,51.43335],"type":"Point"}
}