{
  "type": "Feature",
  "properties": {
    "iso:country":"GB",
    "sg:address":"Bassetsbury Manor, Bassetsbury La",
    "sg:city":"High Wycombe",
    "sg:classifiers":[
        {
            "category":"Professional",
            "subcategory":"Management & Consulting",
            "type":"Services"
        }
    ],
    "sg:phone":"+44 1494 536930",
    "sg:postcode":"HP11 1QX",
    "sg:province":"Buckinghamshire",
    "sg:tags":[
        "conservation"
    ],
    "wof:name":"Wycombe Urban Wildlife Group",
    "wof:placetype":"venue"
},
  "geometry": {"coordinates":[-0.7344599962,51.6234703064],"type":"Point"}
}