{
  "type": "Feature",
  "properties": {
    "addr:full":"Goods Road Belper Derbyshire DE56 1UU",
    "addr:postcode":"de56 1uu",
    "addr:street":"Goods Road",
    "iso:country":"GB",
    "sg:address":"Goods Road",
    "sg:city":"Belper",
    "sg:classifiers":[
        {
            "category":"Bus Charters",
            "type":"Transportation"
        }
    ],
    "sg:postcode":"DE56 1UU",
    "sg:province":"Derbyshire",
    "sg:tags":[
        "hire",
        "coach"
    ],
    "wof:name":"Cox's of Belper",
    "wof:placetype":"venue"
},
  "geometry": {"coordinates":[-1.4849090576,53.0172538757],"type":"Point"}
}