{
  "type": "Feature",
  "properties": {
    "addr:full":"34 Bloomsbury Street London Greater London WC1B 3QJ",
    "addr:housenumber":"34",
    "addr:postcode":"wc1b 3qj",
    "addr:street":"Bloomsbury Street",
    "iso:country":"GB",
    "sg:address":"34 Bloomsbury Street",
    "sg:city":"London",
    "sg:classifiers":[
        {
            "category":"Organizations",
            "subcategory":"Community Association",
            "type":"Services"
        }
    ],
    "sg:phone":"+44 20 7637 2600",
    "sg:postcode":"WC1B 3QJ",
    "sg:province":"Greater London",
    "sg:tags":[
        "relation",
        "public"
    ],
    "wof:name":"McDonald & Rutter Ltd.",
    "wof:placetype":"venue"
},
  "geometry": {"coordinates":[-0.12781,51.518253],"type":"Point"}
}