{
  "type": "Feature",
  "properties": {
    "addr:full":"Camden Lock, Chalk Farm Rd Camden Greater London NW1 8AH",
    "addr:postcode":"nw1 8ah",
    "addr:street":"Camden;Chalk Farm Rd",
    "iso:country":"GB",
    "sg:address":"Camden Lock, Chalk Farm Rd",
    "sg:city":"Camden",
    "sg:classifiers":[
        {
            "category":"Shopping",
            "subcategory":"Pharmacy",
            "type":"Retail Goods"
        }
    ],
    "sg:phone":"+44 20 7284 4046",
    "sg:postcode":"NW1 8AH",
    "sg:province":"Greater London",
    "sg:tags":[
        "medicine",
        "therapy"
    ],
    "wof:name":"Rainbow Pathways",
    "wof:placetype":"venue"
},
  "geometry": {"coordinates":[-0.1464619935,51.5414733887],"type":"Point"}
}