{
  "type": "Feature",
  "properties": {
    "iso:country":"GB",
    "sg:address":"Dousland",
    "sg:city":"Yelverton",
    "sg:classifiers":[
        {
            "category":"Wholesale",
            "subcategory":"Construction Materials",
            "type":"Manufacturing & Wholesale Goods"
        }
    ],
    "sg:phone":"+44 1822 854877",
    "sg:postcode":"PL20 6NA",
    "sg:province":"Devon",
    "sg:tags":[
        "merchant",
        "stone"
    ],
    "wof:name":"M & J Trembath Yennadon Quarry",
    "wof:placetype":"venue"
},
  "geometry": {"coordinates":[-4.0804538727,50.494720459],"type":"Point"}
}