{
  "type": "Feature",
  "properties": {
    "addr:full":"Unit 3 Westmoreland Ho, Cumberland Park, Scrubs La Willesden Greater London NW10 6RE",
    "addr:housenumber":"unit 3",
    "addr:postcode":"nw10 6re",
    "iso:country":"GB",
    "sg:address":"Unit 3 Westmoreland Ho, Cumberland Park, Scrubs La",
    "sg:city":"Willesden",
    "sg:classifiers":[
        {
            "category":"Shopping",
            "subcategory":"Stationery & Office Supplies",
            "type":"Retail Goods"
        }
    ],
    "sg:phone":"+44 20 8960 3777",
    "sg:postcode":"NW10 6RE",
    "sg:province":"Greater London",
    "sg:tags":[
        "machine",
        "facsimile"
    ],
    "wof:name":"J V Electronics Europe Ltd",
    "wof:placetype":"venue"
},
  "geometry": {"coordinates":[-0.2372000068,51.5293312073],"type":"Point"}
}