{
  "type": "Feature",
  "properties": {
    "iso:country":"GB",
    "sg:address":"32 Woodland Grove, Penwortham",
    "sg:city":"Preston",
    "sg:classifiers":[
        {
            "category":"Retail",
            "subcategory":"Driving School",
            "type":"Services"
        }
    ],
    "sg:phone":"+44 1772 742400",
    "sg:postcode":"PR1 0JB",
    "sg:province":"Lancashire",
    "wof:name":"J.B Swallow",
    "wof:placetype":"venue"
},
  "geometry": {"coordinates":[-2.7346849442,53.7510871887],"type":"Point"}
}