{
  "type": "Feature",
  "properties": {
    "iso:country":"GB",
    "sg:address":"Wadbury Cott, Mells",
    "sg:city":"Frome",
    "sg:classifiers":[
        {
            "category":"Building & Trades",
            "subcategory":"Construction",
            "type":"Services"
        }
    ],
    "sg:postcode":"BA11 3PL",
    "sg:province":"Somerset",
    "sg:tags":[
        "decorator",
        "painter"
    ],
    "wof:name":"Ward,Robert Gerald,",
    "wof:placetype":"venue"
},
  "geometry": {"coordinates":[-2.395225,51.237499],"type":"Point"}
}