{
  "type": "Feature",
  "properties": {
    "addr:full":"17 Lorne Street Middlesbrough North Yorkshire TS1 5QY",
    "addr:housenumber":"17",
    "addr:postcode":"ts1 5qy",
    "addr:street":"Lorne Street",
    "iso:country":"GB",
    "sg:address":"17 Lorne Street",
    "sg:city":"Middlesbrough",
    "sg:classifiers":[
        {
            "category":"Building & Trades",
            "subcategory":"Construction",
            "type":"Services"
        }
    ],
    "sg:postcode":"TS1 5QY",
    "sg:province":"North Yorkshire",
    "sg:tags":[
        "decorator",
        "painter"
    ],
    "wof:name":"M S Gott",
    "wof:placetype":"venue"
},
  "geometry": {"coordinates":[-1.25015,54.570595],"type":"Point"}
}