{
  "type": "Feature",
  "properties": {
    "addr:full":"West Lane Farm Sheffield Derbyshire S31 0XS",
    "addr:postcode":"s31 0xs",
    "addr:street":"West Lane",
    "iso:country":"GB",
    "sg:address":"West Lane Farm",
    "sg:city":"Sheffield",
    "sg:classifiers":[
        {
            "category":"Farming",
            "subcategory":"Livestock Farm",
            "type":"Manufacturing & Wholesale Goods"
        }
    ],
    "sg:postcode":"S31 0XS",
    "sg:province":"Derbyshire",
    "sg:tags":[
        "others"
    ],
    "wof:name":"K F Middleton",
    "wof:placetype":"venue"
},
  "geometry": {"coordinates":[-1.46454,53.38311],"type":"Point"}
}