{
  "type": "Feature",
  "properties": {
    "iso:country":"GB",
    "sg:address":"Clover Hill, Crundale",
    "sg:city":"Haverfordwest",
    "sg:classifiers":[
        {
            "category":"Farming",
            "subcategory":"Dairy Farm",
            "type":"Manufacturing & Wholesale Goods"
        }
    ],
    "sg:phone":"+44 1437 731217",
    "sg:postcode":"SA62 4EL",
    "sg:province":"Pembrokeshire",
    "wof:name":"John Lewis Morgan",
    "wof:placetype":"venue"
},
  "geometry": {"coordinates":[-4.948219,51.824329],"type":"Point"}
}