{
  "type": "Feature",
  "properties": {
    "addr:full":"Grange Business Centre Belasis Av Billingham Durham TS23 1LG",
    "addr:postcode":"ts23 1lg",
    "addr:street":"Av Billingham",
    "iso:country":"GB",
    "sg:address":"Grange Business Centre Belasis Av",
    "sg:city":"Billingham",
    "sg:classifiers":[
        {
            "category":"Professional",
            "subcategory":"Engineering",
            "type":"Services"
        }
    ],
    "sg:phone":"+44 1642 361741",
    "sg:postcode":"TS23 1LG",
    "sg:province":"Durham",
    "sg:tags":[
        "consulting",
        "engineer"
    ],
    "wof:name":"E S U Services Ltd",
    "wof:placetype":"venue"
},
  "geometry": {"coordinates":[-1.27433,54.59967],"type":"Point"}
}