{
  "type": "Feature",
  "properties": {
    "addr:full":"Queens Drive Taunton Somerset TA1 4XW",
    "addr:postcode":"ta1 4xw",
    "addr:street":"Queens Drive",
    "iso:country":"GB",
    "sg:address":"Queens Drive",
    "sg:city":"Taunton",
    "sg:classifiers":[
        {
            "category":"Professional",
            "subcategory":"Business Services",
            "type":"Services"
        }
    ],
    "sg:phone":"+44 1823 252789",
    "sg:postcode":"TA1 4XW",
    "sg:province":"Somerset",
    "sg:tags":[
        "import",
        "export",
        "agent"
    ],
    "wof:name":"Russells Export Ltd.",
    "wof:placetype":"venue"
},
  "geometry": {"coordinates":[-3.114426,51.001453],"type":"Point"}
}