{
  "type": "Feature",
  "properties": {
    "iso:country":"GB",
    "sg:address":"15 Whitehouse Road, Springkerse Industrial Estate",
    "sg:city":"Stirling",
    "sg:classifiers":[
        {
            "category":"Building & Trades",
            "subcategory":"Construction",
            "type":"Services"
        },
        {
            "category":"Home & Garden",
            "subcategory":"Carpets & Floor Coverings",
            "type":"Retail Goods"
        }
    ],
    "sg:phone":"+44 1786 473706",
    "sg:postcode":"FK7 7SP",
    "sg:province":"Falkirk",
    "sg:tags":[
        "tiling",
        "retailer",
        "rug",
        "contractor"
    ],
    "wof:name":"William Lewis & Sons",
    "wof:placetype":"venue"
},
  "geometry": {"coordinates":[-3.919402,56.114536],"type":"Point"}
}