{
  "type": "Feature",
  "properties": {
    "addr:full":"9-11 Lowfield Street Dartford Kent DA1 1EN",
    "addr:housenumber":"9-11",
    "addr:postcode":"da1 1en",
    "addr:street":"Lowfield Street",
    "iso:country":"GB",
    "sg:address":"9-11 Lowfield Street",
    "sg:city":"Dartford",
    "sg:classifiers":[
        {
            "category":"Shopping",
            "subcategory":"Jewelry",
            "type":"Retail Goods"
        },
        {
            "category":"Shopping",
            "subcategory":"Comic Books",
            "type":"Retail Goods"
        }
    ],
    "sg:phone":"+44 1322 224490",
    "sg:postcode":"DA1 1EN",
    "sg:province":"Kent",
    "sg:tags":[
        "jeweller",
        "sale",
        "jewellery"
    ],
    "wof:name":"F Hinds Ltd.",
    "wof:placetype":"venue"
},
  "geometry": {"coordinates":[0.2167930007,51.4436035156],"type":"Point"}
}