{
  "type": "Feature",
  "properties": {
    "addr:full":"112 Wardles Lane, Great Wyrley Walsall Staffordshire WS6 6DY",
    "addr:housenumber":"112",
    "addr:postcode":"ws6 6dy",
    "addr:street":"Wardles Lane",
    "iso:country":"GB",
    "sg:address":"112 Wardles Lane, Great Wyrley",
    "sg:city":"Walsall",
    "sg:classifiers":[
        {
            "category":"Food & Beverages",
            "subcategory":"Fruits & Vegetables",
            "type":"Retail Goods"
        }
    ],
    "sg:phone":"+44 1922 412796",
    "sg:postcode":"WS6 6DY",
    "sg:province":"Staffordshire",
    "sg:tags":[
        "greengrocer"
    ],
    "wof:name":"The Garden Basket",
    "wof:placetype":"venue"
},
  "geometry": {"coordinates":[-2.0176029205,52.6579627991],"type":"Point"}
}