{
  "type": "Feature",
  "properties": {
    "iso:country":"GB",
    "sg:address":"13 Ashfield Parade",
    "sg:city":"London",
    "sg:classifiers":[
        {
            "category":"Personal",
            "subcategory":"Barber",
            "type":"Services"
        }
    ],
    "sg:postcode":"N14 5EH",
    "sg:province":"Greater London",
    "sg:tags":[
        "men's",
        "hairdresser"
    ],
    "wof:name":"Ali Barba",
    "wof:placetype":"venue"
},
  "geometry": {"coordinates":[-0.128192,51.631268],"type":"Point"}
}