{
  "type": "Feature",
  "properties": {
    "addr:full":"13 Long St, Middleton Manchester Greater Manchester M40 2EH",
    "addr:housenumber":"13",
    "addr:postcode":"m40 2eh",
    "addr:street":"Long St",
    "iso:country":"GB",
    "sg:address":"13 Long St, Middleton",
    "sg:city":"Manchester",
    "sg:classifiers":[
        {
            "category":"Professional",
            "subcategory":"Lawyer & Legal Services",
            "type":"Services"
        }
    ],
    "sg:phone":"+44 161 688 6660",
    "sg:postcode":"M40 2EH",
    "sg:province":"Greater Manchester",
    "sg:tags":[
        "solicitor"
    ],
    "wof:name":"Kristina Harrison",
    "wof:placetype":"venue"
},
  "geometry": {"coordinates":[-2.1849300861,53.5025482178],"type":"Point"}
}