{
  "type": "Feature",
  "properties": {
    "iso:country":"GB",
    "sg:address":"Heath Way, Heath Hayes",
    "sg:city":"Cannock",
    "sg:classifiers":[
        {
            "category":"Health Services",
            "subcategory":"Doctor",
            "type":"Services"
        },
        {
            "category":"Health Services",
            "subcategory":"Clinic",
            "type":"Services"
        }
    ],
    "sg:phone":"+44 1543 271313",
    "sg:postcode":"WS12 5XP",
    "sg:province":"Staffordshire",
    "sg:tags":[
        "nh",
        "practitioners"
    ],
    "wof:name":"Hawks Green Medical Centre",
    "wof:placetype":"venue"
},
  "geometry": {"coordinates":[-2.0003740788,52.6918106079],"type":"Point"}
}