{
  "type": "Feature",
  "properties": {
    "iso:country":"GB",
    "sg:address":"Falkland House, 28 Rickmansworth Lane, Chalfont St Peter",
    "sg:city":"Gerrards Cross",
    "sg:classifiers":[
        {
            "category":"Health Services",
            "subcategory":"Dentist",
            "type":"Services"
        }
    ],
    "sg:postcode":"SL9 0HS",
    "sg:province":"Buckinghamshire",
    "sg:tags":[
        "technician",
        "dental"
    ],
    "wof:name":"Chalfont Orthodontic Laboratories",
    "wof:placetype":"venue"
},
  "geometry": {"coordinates":[-0.537764,51.622147],"type":"Point"}
}