{
  "type": "Feature",
  "properties": {
    "iso:country":"GB",
    "sg:address":"Lower Road",
    "sg:city":"Ledbury",
    "sg:classifiers":[
        {
            "category":"Professional",
            "subcategory":"Engineering",
            "type":"Services"
        }
    ],
    "sg:phone":"+44 1531 634300",
    "sg:postcode":"HR8 2DH",
    "sg:province":"Gloucestershire",
    "sg:tags":[
        "precision",
        "engineer"
    ],
    "wof:name":"Intime Engineering (Ledbury) Ltd.",
    "wof:placetype":"venue"
},
  "geometry": {"coordinates":[-2.4351689816,52.0351295471],"type":"Point"}
}