{
  "type": "Feature",
  "properties": {
    "iso:country":"GB",
    "sg:address":"14 Coombe Pk, Four Oaks",
    "sg:city":"Sutton Coldfield",
    "sg:classifiers":[
        {
            "category":"Shopping",
            "subcategory":"Jewelry",
            "type":"Retail Goods"
        },
        {
            "category":"Manufacturing",
            "subcategory":"Jewelry",
            "type":"Manufacturing & Wholesale Goods"
        }
    ],
    "sg:phone":"+44 1543 264275",
    "sg:postcode":"B74 2QB",
    "sg:province":"Staffordshire",
    "sg:tags":[
        "repair",
        "jewellery",
        "gold",
        "silversmith"
    ],
    "wof:name":"Keyford Silverware (U K) Ltd",
    "wof:placetype":"venue"
},
  "geometry": {"coordinates":[-1.831205,52.580963],"type":"Point"}
}