{
  "type": "Feature",
  "properties": {
    "iso:country":"GB",
    "sg:address":"38 Lark Rise",
    "sg:city":"Liphook",
    "sg:classifiers":[
        {
            "category":"Health Services",
            "subcategory":"Podiatrist",
            "type":"Services"
        }
    ],
    "sg:phone":"+44 1428 722225",
    "sg:postcode":"GU30 7QT",
    "sg:province":"Hampshire",
    "sg:tags":[
        "podiatrists",
        "chiropodist"
    ],
    "wof:name":"G Y King",
    "wof:placetype":"venue"
},
  "geometry": {"coordinates":[-0.809772,51.081947],"type":"Point"}
}