{
  "type": "Feature",
  "properties": {
    "iso:country":"GB",
    "sg:address":"Northern Region, Carrhill",
    "sg:city":"Doncaster",
    "sg:classifiers":[
        {
            "category":"Home & Garden",
            "subcategory":"Building Materials",
            "type":"Retail Goods"
        }
    ],
    "sg:phone":"+44 191 586 2200",
    "sg:postcode":"DN4 8DE",
    "sg:province":"South Yorkshire",
    "sg:tags":[
        "fencing"
    ],
    "wof:name":"Darfen Durafencing",
    "wof:placetype":"venue"
},
  "geometry": {"coordinates":[-1.1422,53.507332],"type":"Point"}
}