{
  "type": "Feature",
  "properties": {
    "addr:full":"12a Oval Rd, Lockerley Romsey Hampshire SO51 0JB",
    "addr:housenumber":"12a",
    "addr:postcode":"so51 0jb",
    "addr:street":"Oval Rd",
    "iso:country":"GB",
    "sg:address":"12a Oval Rd, Lockerley",
    "sg:city":"Romsey",
    "sg:classifiers":[
        {
            "category":"Building & Trades",
            "subcategory":"Construction",
            "type":"Services"
        }
    ],
    "sg:phone":"+44 1794 341830",
    "sg:postcode":"SO51 0JB",
    "sg:province":"Hampshire",
    "sg:tags":[
        "flooring"
    ],
    "wof:name":"Buckingham Surfacing",
    "wof:placetype":"venue"
},
  "geometry": {"coordinates":[-1.5731890202,51.0330619812],"type":"Point"}
}