{
  "type": "Feature",
  "properties": {
    "addr:full":"Stone House, Llay Road, Rossett Wrexham Wrexham LL12 0HS",
    "addr:postcode":"ll12 0hs",
    "addr:street":"Llay Road",
    "iso:country":"GB",
    "sg:address":"Stone House, Llay Road, Rossett",
    "sg:city":"Wrexham",
    "sg:classifiers":[
        {
            "category":"Retail",
            "subcategory":"Repair Shop",
            "type":"Services"
        }
    ],
    "sg:postcode":"LL12 0HS",
    "sg:province":"Wrexham",
    "sg:tags":[
        "clocks",
        "watch"
    ],
    "wof:name":"David A Tennant",
    "wof:placetype":"venue"
},
  "geometry": {"coordinates":[-2.9652280807,53.1061935425],"type":"Point"}
}