{
  "type": "Feature",
  "properties": {
    "addr:full":"1 Old Bell Chambers, Bank Street Chepstow Gloucestershire NP16 5EN",
    "addr:housenumber":"1;bell",
    "addr:postcode":"np16 5en",
    "addr:street":"Old;Bank Street",
    "iso:country":"GB",
    "sg:address":"1 Old Bell Chambers, Bank Street",
    "sg:city":"Chepstow",
    "sg:classifiers":[
        {
            "category":"Professional",
            "subcategory":"Art Services",
            "type":"Services"
        }
    ],
    "sg:phone":"+44 1291 627262",
    "sg:postcode":"NP16 5EN",
    "sg:province":"Gloucestershire",
    "sg:tags":[
        "picture",
        "restoration",
        "framing"
    ],
    "wof:name":"Images Picture Framing Gallery & Photographic Stud",
    "wof:placetype":"venue"
},
  "geometry": {"coordinates":[-2.6798119545,51.637878418],"type":"Point"}
}