{
  "type": "Feature",
  "properties": {
    "iso:country":"GB",
    "sg:address":"Hayneside 40 Melton Road",
    "sg:city":"Oakham",
    "sg:classifiers":[
        {
            "category":"Professional",
            "subcategory":"Accounting & Tax Preparation",
            "type":"Services"
        }
    ],
    "sg:postcode":"LE15 6AY",
    "sg:province":"Leicestershire",
    "sg:tags":[
        "accountant"
    ],
    "wof:name":"Partner Accountants",
    "wof:placetype":"venue"
},
  "geometry": {"coordinates":[-0.730749,52.669979],"type":"Point"}
}