{
  "type": "Feature",
  "properties": {
    "addr:full":"27-33 Artillery La London Greater London E1 7LP",
    "addr:housenumber":"27-33",
    "addr:postcode":"e1 7lp",
    "addr:street":"Artillery La",
    "iso:country":"GB",
    "sg:address":"27-33 Artillery La",
    "sg:city":"London",
    "sg:classifiers":[
        {
            "category":"Manufacturing",
            "subcategory":"Tools & Machinery",
            "type":"Manufacturing & Wholesale Goods"
        },
        {
            "category":"Insurance",
            "subcategory":"Insurance Agent",
            "type":"Services"
        }
    ],
    "sg:phone":"+44 171 247 5433",
    "sg:postcode":"E1 7LP",
    "sg:province":"Greater London",
    "sg:tags":[
        "society",
        "broker",
        "friendly"
    ],
    "wof:name":"Gibbs Hartley Cooper Marine Ltd",
    "wof:placetype":"venue"
},
  "geometry": {"coordinates":[-0.0773319975,51.5180587769],"type":"Point"}
}