{
  "type": "Feature",
  "properties": {
    "addr:full":"Bushland Rd Northampton Northamptonshire NN3 2NS",
    "addr:postcode":"nn3 2ns",
    "addr:street":"Bushland Rd",
    "iso:country":"GB",
    "sg:address":"Bushland Rd",
    "sg:city":"Northampton",
    "sg:classifiers":[
        {
            "category":"Government",
            "subcategory":"Post Office",
            "type":"Public Place"
        }
    ],
    "sg:phone":"+44 1604 401103",
    "sg:postcode":"NN3 2NS",
    "sg:province":"Northamptonshire",
    "wof:name":"Bushland Rd P.O",
    "wof:placetype":"venue"
},
  "geometry": {"coordinates":[-0.852974,52.259457],"type":"Point"}
}