{
  "type": "Feature",
  "properties": {
    "addr:full":"Sealed Buildings, Telford Road Middlesbrough North Yorkshire TS3 8BL",
    "addr:postcode":"ts3 8bl",
    "addr:street":"Telford Road",
    "iso:country":"GB",
    "sg:address":"Sealed Buildings, Telford Road",
    "sg:city":"Middlesbrough",
    "sg:classifiers":[
        {
            "category":"Professional",
            "subcategory":"Art Services",
            "type":"Services"
        },
        {
            "category":"Building & Trades",
            "subcategory":"Construction",
            "type":"Services"
        }
    ],
    "sg:phone":"+44 1642 246964",
    "sg:postcode":"TS3 8BL",
    "sg:province":"North Yorkshire",
    "sg:tags":[
        "specialised",
        "stone",
        "restoration",
        "cleaning",
        "contractor"
    ],
    "wof:name":"ONETRAN LTD",
    "wof:placetype":"venue"
},
  "geometry": {"coordinates":[-1.1924500465,54.5734596252],"type":"Point"}
}