{
  "type": "Feature",
  "properties": {
    "iso:country":"GB",
    "sg:address":"Porters Loke, Burgh Castle",
    "sg:city":"Great Yarmouth",
    "sg:classifiers":[
        {
            "category":"Farming",
            "subcategory":"Livestock Farm",
            "type":"Manufacturing & Wholesale Goods"
        }
    ],
    "sg:phone":"+44 1493 780321",
    "sg:postcode":"NR31 9PX",
    "sg:province":"Norfolk",
    "sg:tags":[
        "others"
    ],
    "wof:name":"D W Smith",
    "wof:placetype":"venue"
},
  "geometry": {"coordinates":[1.656572,52.57629],"type":"Point"}
}