{
  "type": "Feature",
  "properties": {
    "iso:country":"GB",
    "sg:address":"Little Tillingham Hall, Dunnings La, West Horndon",
    "sg:city":"Brentwood",
    "sg:classifiers":[
        {
            "category":"Real Estate",
            "subcategory":"Architect",
            "type":"Services"
        }
    ],
    "sg:postcode":"CM13 3HE",
    "sg:province":"Essex",
    "wof:name":"Sewell Associates",
    "wof:placetype":"venue"
},
  "geometry": {"coordinates":[0.34282,51.568924],"type":"Point"}
}