{
  "type": "Feature",
  "properties": {
    "addr:full":"63 Middle Street South Driffield East Riding of Yorkshire YO25 7QG",
    "addr:housenumber":"63",
    "addr:postcode":"yo25 7qg",
    "addr:street":"Middle Street South",
    "iso:country":"GB",
    "sg:address":"63 Middle Street South",
    "sg:city":"Driffield",
    "sg:classifiers":[
        {
            "category":"Shopping",
            "subcategory":"Department Store",
            "type":"Retail Goods"
        }
    ],
    "sg:phone":"+44 1377 240788",
    "sg:postcode":"YO25 7QG",
    "sg:province":"East Riding of Yorkshire",
    "wof:name":"Boyes Department Store",
    "wof:placetype":"venue"
},
  "geometry": {"coordinates":[-0.437657,54.004318],"type":"Point"}
}