{
  "type": "Feature",
  "properties": {
    "iso:country":"GB",
    "sg:address":"Unit 2, Mangham Way",
    "sg:city":"Rotherham",
    "sg:classifiers":[
        {
            "category":"Manufacturing",
            "subcategory":"Petroleum Products",
            "type":"Manufacturing & Wholesale Goods"
        },
        {
            "category":"Building & Trades",
            "subcategory":"Construction",
            "type":"Services"
        }
    ],
    "sg:phone":"+44 1709 820420",
    "sg:postcode":"S61 4RL",
    "sg:province":"South Yorkshire",
    "sg:tags":[
        "double",
        "glazing",
        "installers"
    ],
    "wof:name":"Calendar Home Improvements Ltd",
    "wof:placetype":"venue"
},
  "geometry": {"coordinates":[-1.357944,53.442608],"type":"Point"}
}