{
  "type": "Feature",
  "properties": {
    "iso:country":"GB",
    "sg:address":"108 East St",
    "sg:city":"Southend On Sea",
    "sg:classifiers":[
        {
            "category":"Bars & Pubs",
            "type":"Food & Drink"
        }
    ],
    "sg:phone":"+44 1702 616214",
    "sg:postcode":"SS2 6LH",
    "sg:province":"Essex",
    "sg:tags":[
        "pubs",
        "inn"
    ],
    "wof:name":"Railway Tavern The",
    "wof:placetype":"venue"
},
  "geometry": {"coordinates":[0.709987998,51.5496292114],"type":"Point"}
}