{
  "type": "Feature",
  "properties": {
    "addr:full":"47d Broad Street Banbury Oxfordshire OX16 5BT",
    "addr:housenumber":"47d",
    "addr:postcode":"ox16 5bt",
    "addr:street":"Broad Street",
    "iso:country":"GB",
    "sg:address":"47d Broad Street",
    "sg:city":"Banbury",
    "sg:classifiers":[
        {
            "category":"Home & Garden",
            "subcategory":"Carpets & Floor Coverings",
            "type":"Retail Goods"
        }
    ],
    "sg:phone":"+44 1295 251310",
    "sg:postcode":"OX16 5BT",
    "sg:province":"Oxfordshire",
    "sg:tags":[
        "carpets",
        "retailer",
        "rug",
        "matting"
    ],
    "wof:name":"Cash & Carry Carpets",
    "wof:placetype":"venue"
},
  "geometry": {"coordinates":[-1.335588,52.059772],"type":"Point"}
}