{
  "type": "Feature",
  "properties": {
    "addr:full":"5 Edmonds Road, Lane End High Wycombe Buckinghamshire HP14 3EJ",
    "addr:housenumber":"5",
    "addr:postcode":"hp14 3ej",
    "addr:street":"Edmonds Road",
    "iso:country":"GB",
    "sg:address":"5 Edmonds Road, Lane End",
    "sg:city":"High Wycombe",
    "sg:classifiers":[
        {
            "category":"Cinema",
            "subcategory":"Movie Rental",
            "type":"Entertainment"
        }
    ],
    "sg:phone":"+44 1494 882346",
    "sg:postcode":"HP14 3EJ",
    "sg:province":"Buckinghamshire",
    "sg:tags":[
        "video",
        "library"
    ],
    "wof:name":"B & T Supermarket",
    "wof:placetype":"venue"
},
  "geometry": {"coordinates":[-0.832399,51.620251],"type":"Point"}
}