{
  "type": "Feature",
  "properties": {
    "addr:full":"99 The Downs, Wilford Nottingham Nottinghamshire NG11 7EA",
    "addr:housenumber":"99",
    "addr:postcode":"ng11 7ea",
    "addr:street":"The Downs Wilford",
    "iso:country":"GB",
    "sg:address":"99 The Downs, Wilford",
    "sg:city":"Nottingham",
    "sg:classifiers":[
        {
            "category":"Building & Trades",
            "subcategory":"Plumbing",
            "type":"Services"
        }
    ],
    "sg:postcode":"NG11 7EA",
    "sg:province":"Nottinghamshire",
    "sg:tags":[
        "central",
        "heating"
    ],
    "wof:name":"Michael Fish",
    "wof:placetype":"venue"
},
  "geometry": {"coordinates":[-1.157059,52.925636],"type":"Point"}
}