{
  "type": "Feature",
  "properties": {
    "iso:country":"GB",
    "sg:address":"4 Moorside Av",
    "sg:city":"Bolton",
    "sg:classifiers":[
        {
            "category":"Building & Trades",
            "subcategory":"Cleaning & Sanitation",
            "type":"Services"
        }
    ],
    "sg:phone":"+44 161 764 3727",
    "sg:postcode":"BL2 5RP",
    "sg:province":"Lancashire",
    "sg:tags":[
        "dry",
        "control",
        "damp",
        "rot"
    ],
    "wof:name":"Bates Builders",
    "wof:placetype":"venue"
},
  "geometry": {"coordinates":[-2.350903,53.587059],"type":"Point"}
}