{
  "type": "Feature",
  "properties": {
    "iso:country":"GB",
    "sg:address":"1 Lynbank, Lansdown",
    "sg:city":"Stroud",
    "sg:classifiers":[
        {
            "category":"Professional",
            "subcategory":"Engineering",
            "type":"Services"
        }
    ],
    "sg:postcode":"GL5 1BU",
    "sg:province":"Gloucestershire",
    "sg:tags":[
        "contractor",
        "electrical",
        "engineer"
    ],
    "wof:name":"Electromech",
    "wof:placetype":"venue"
},
  "geometry": {"coordinates":[-2.217167,51.746258],"type":"Point"}
}