{
  "type": "Feature",
  "properties": {
    "iso:country":"GB",
    "sg:address":"Salman House, 141 Woodlands Road",
    "sg:city":"Ilford",
    "sg:classifiers":[
        {
            "category":"Professional",
            "subcategory":"Accounting & Tax Preparation",
            "type":"Services"
        }
    ],
    "sg:phone":"+44 20 8478 9980",
    "sg:postcode":"IG1 1JR",
    "sg:province":"Essex",
    "sg:tags":[
        "accountant",
        "activity"
    ],
    "wof:name":"Salman Ross Chartered Accountants",
    "wof:placetype":"venue"
},
  "geometry": {"coordinates":[0.079108,51.553101],"type":"Point"}
}