{
  "type": "Feature",
  "properties": {
    "iso:country":"GB",
    "sg:address":"Thornhill Street",
    "sg:city":"Houghton-le-spring",
    "sg:classifiers":[
        {
            "category":"Organizations",
            "subcategory":"Non-profit Organization",
            "type":"Services"
        }
    ],
    "sg:phone":"+44 191 584 2294",
    "sg:postcode":"DH4 5BE",
    "sg:province":"Durham",
    "sg:tags":[
        "organisation",
        "voluntary",
        "charity"
    ],
    "wof:name":"Centre for the Blind Hougton le Spring District",
    "wof:placetype":"venue"
},
  "geometry": {"coordinates":[-1.476149,54.842442],"type":"Point"}
}