{
  "type": "Feature",
  "properties": {
    "addr:full":"20 Haywood Street Leek Staffordshire ST13 5JX",
    "addr:housenumber":"20",
    "addr:postcode":"st13 5jx",
    "addr:street":"Haywood Street",
    "iso:country":"GB",
    "sg:address":"20 Haywood Street",
    "sg:city":"Leek",
    "sg:classifiers":[
        {
            "category":"Cafe",
            "type":"Food & Drink"
        }
    ],
    "sg:phone":"+44 1538 383527",
    "sg:postcode":"ST13 5JX",
    "sg:province":"Staffordshire",
    "sg:tags":[
        "tea",
        "room"
    ],
    "wof:name":"Haywood Cafe",
    "wof:placetype":"venue"
},
  "geometry": {"coordinates":[-2.022715,53.104603],"type":"Point"}
}