{
  "type": "Feature",
  "properties": {
    "iso:country":"GB",
    "sg:address":"12 Trelawn Place",
    "sg:city":"Leeds",
    "sg:classifiers":[
        {
            "category":"Building & Trades",
            "subcategory":"Cleaning & Sanitation",
            "type":"Services"
        }
    ],
    "sg:phone":"+44 113 225 2080",
    "sg:postcode":"LS6 3JP",
    "sg:province":"West Yorkshire",
    "sg:tags":[
        "cleaner",
        "window"
    ],
    "wof:name":"Q Cleaners",
    "wof:placetype":"venue"
},
  "geometry": {"coordinates":[-1.581918,53.821342],"type":"Point"}
}