{
  "type": "Feature",
  "properties": {
    "addr:full":"Flat 3 2 Atholl Pl Edinburgh City of Edinburgh EH3 8HP",
    "addr:housenumber":"2",
    "addr:postcode":"eh3 8hp",
    "addr:street":"Atholl Pl",
    "iso:country":"GB",
    "sg:address":"Flat 3 2 Atholl Pl",
    "sg:city":"Edinburgh",
    "sg:classifiers":[
        {
            "category":"Building & Trades",
            "subcategory":"Construction",
            "type":"Services"
        }
    ],
    "sg:phone":"+44 131 467 9178",
    "sg:postcode":"EH3 8HP",
    "sg:province":"City of Edinburgh",
    "sg:tags":[
        "dry",
        "lining",
        "plasterers",
        "screeders"
    ],
    "wof:name":"A & K Parsons Plastering",
    "wof:placetype":"venue"
},
  "geometry": {"coordinates":[-3.2139799595,55.9474182129],"type":"Point"}
}