{
  "type": "Feature",
  "properties": {
    "iso:country":"GB",
    "sg:address":"589 Halifax Rd",
    "sg:city":"Bradford",
    "sg:classifiers":[
        {
            "category":"Shopping",
            "subcategory":"Department Store",
            "type":"Retail Goods"
        }
    ],
    "sg:phone":"+44 1274 600988",
    "sg:postcode":"BD6 2DU",
    "sg:province":"West Yorkshire",
    "wof:name":"D & M Wood",
    "wof:placetype":"venue"
},
  "geometry": {"coordinates":[-1.7922279835,53.7586479187],"type":"Point"}
}