{
  "type": "Feature",
  "properties": {
    "iso:country":"GB",
    "sg:address":"Peveril Rd",
    "sg:city":"Northampton",
    "sg:classifiers":[
        {
            "category":"Social Services",
            "type":"Services"
        },
        {
            "category":"Health Services",
            "subcategory":"Nursing And Care Facility",
            "type":"Services"
        }
    ],
    "sg:phone":"+44 1604 750731",
    "sg:postcode":"NN5 6JW",
    "sg:province":"Northamptonshire",
    "sg:tags":[
        "home"
    ],
    "wof:name":"Moray Lodge Community Mental Health Resource Centre",
    "wof:placetype":"venue"
},
  "geometry": {"coordinates":[-0.945734,52.245781],"type":"Point"}
}