{
  "type": "Feature",
  "properties": {
    "addr:full":"367 Maidstone Rd, Wigmore Gillingham Kent ME8 0HT",
    "addr:housenumber":"367",
    "addr:postcode":"me8 0ht",
    "addr:street":"Maidstone Rd",
    "iso:country":"GB",
    "sg:address":"367 Maidstone Rd, Wigmore",
    "sg:city":"Gillingham",
    "sg:classifiers":[
        {
            "category":"Health Services",
            "subcategory":"Dentist",
            "type":"Services"
        }
    ],
    "sg:phone":"+44 1634 232204",
    "sg:postcode":"ME8 0HT",
    "sg:province":"Kent",
    "wof:name":"Stephen Hill FDSRCS. MGDSRCPS",
    "wof:placetype":"venue"
},
  "geometry": {"coordinates":[0.590978,51.352425],"type":"Point"}
}