{
  "type": "Feature",
  "properties": {
    "addr:full":"Rear Of Benedicts Filling Station, Liverton Newton Abbot Devon TQ12 6HQ",
    "addr:housenumber":"rear of",
    "addr:postcode":"tq12 6hq",
    "iso:country":"GB",
    "sg:address":"Rear Of Benedicts Filling Station, Liverton",
    "sg:city":"Newton Abbot",
    "sg:classifiers":[
        {
            "category":"Retail",
            "subcategory":"Auto Repair",
            "type":"Services"
        }
    ],
    "sg:postcode":"TQ12 6HQ",
    "sg:province":"Devon",
    "sg:tags":[
        "body",
        "car"
    ],
    "wof:name":"Michael Powlesland",
    "wof:placetype":"venue"
},
  "geometry": {"coordinates":[-3.6863179207,50.5638656616],"type":"Point"}
}