{
  "type": "Feature",
  "properties": {
    "iso:country":"GB",
    "sg:address":"Sun House, Market Place, Reepham",
    "sg:city":"Norwich",
    "sg:classifiers":[
        {
            "category":"Food & Beverages",
            "subcategory":"Meat & Fish",
            "type":"Retail Goods"
        }
    ],
    "sg:phone":"+44 1603 871880",
    "sg:postcode":"NR10 4JJ",
    "sg:province":"Norfolk",
    "sg:tags":[
        "butcher"
    ],
    "wof:name":"Browns Family Butchers",
    "wof:placetype":"venue"
},
  "geometry": {"coordinates":[1.1103949547,52.7625656128],"type":"Point"}
}