{
  "type": "Feature",
  "properties": {
    "addr:full":"Daviot Inverurie Aberdeenshire AB51 0JL",
    "addr:postcode":"ab51 0jl",
    "iso:country":"GB",
    "sg:address":"Daviot",
    "sg:city":"Inverurie",
    "sg:classifiers":[
        {
            "category":"Shopping",
            "subcategory":"Department Store",
            "type":"Retail Goods"
        }
    ],
    "sg:postcode":"AB51 0JL",
    "sg:province":"Aberdeenshire",
    "wof:name":"Kirkdale Nurseries",
    "wof:placetype":"venue"
},
  "geometry": {"coordinates":[-2.417161,57.343018],"type":"Point"}
}