{
  "type": "Feature",
  "properties": {
    "addr:full":"62 Cornhill London Greater London EC3V 3NH",
    "addr:housenumber":"62",
    "addr:postcode":"ec3v 3nh",
    "addr:street":"Cornhill",
    "iso:country":"GB",
    "sg:address":"62 Cornhill",
    "sg:city":"London",
    "sg:classifiers":[
        {
            "category":"Banks & Credit Unions",
            "subcategory":"Investment Brokerage",
            "type":"Services"
        }
    ],
    "sg:phone":"+44 20 7283 9568",
    "sg:postcode":"EC3V 3NH",
    "sg:province":"Greater London",
    "wof:name":"Zenkyoren Europe Ltd.",
    "wof:placetype":"venue"
},
  "geometry": {"coordinates":[-0.0842910036,51.5134963989],"type":"Point"}
}