{
  "type": "Feature",
  "properties": {
    "iso:country":"GB",
    "sg:address":"5 Cornfield Avenue, Stoke Heath",
    "sg:city":"Bromsgrove",
    "sg:classifiers":[
        {
            "category":"Building & Trades",
            "subcategory":"Construction",
            "type":"Services"
        }
    ],
    "sg:phone":"+44 1527 570508",
    "sg:postcode":"B60 3QU",
    "sg:province":"Worcestershire",
    "sg:tags":[
        "roofing"
    ],
    "wof:name":"Vitesse Roofing Co",
    "wof:placetype":"venue"
},
  "geometry": {"coordinates":[-2.075613,52.317944],"type":"Point"}
}