{
  "type": "Feature",
  "properties": {
    "iso:country":"GB",
    "sg:address":"Unit 1, Boothferry Industrial Estate",
    "sg:city":"Goole",
    "sg:classifiers":[
        {
            "category":"Manufacturing",
            "subcategory":"Building Materials",
            "type":"Manufacturing & Wholesale Goods"
        }
    ],
    "sg:phone":"+44 1430 432161",
    "sg:postcode":"DN14 7DZ",
    "sg:province":"East Riding of Yorkshire",
    "sg:tags":[
        "distributor",
        "mnfrs",
        "cement"
    ],
    "wof:name":"C M S Pozament",
    "wof:placetype":"venue"
},
  "geometry": {"coordinates":[-0.8526870012,53.7484893799],"type":"Point"}
}