{
  "type": "Feature",
  "properties": {
    "iso:country":"GB",
    "sg:address":"40 Hylton Road",
    "sg:city":"Sunderland",
    "sg:classifiers":[
        {
            "category":"Shopping",
            "subcategory":"Used Merchandise",
            "type":"Retail Goods"
        }
    ],
    "sg:phone":"+44 191 565 4626",
    "sg:postcode":"SR4 7AA",
    "sg:province":"Tyne and Wear",
    "sg:tags":[
        "shop",
        "second-hand"
    ],
    "wof:name":"The Trading Post",
    "wof:placetype":"venue"
},
  "geometry": {"coordinates":[-1.395816,54.907227],"type":"Point"}
}