{
  "type": "Feature",
  "properties": {
    "addr:full":"40 Hylton Road Sunderland Tyne and Wear SR4 7AA",
    "addr:housenumber":"40",
    "addr:postcode":"sr4 7aa",
    "addr:street":"Hylton Road",
    "iso:country":"GB",
    "sg:address":"40 Hylton Road",
    "sg:city":"Sunderland",
    "sg:classifiers":[
        {
            "category":"Shopping",
            "subcategory":"Used Merchandise",
            "type":"Retail Goods"
        }
    ],
    "sg:phone":"+44 191 565 4626",
    "sg:postcode":"SR4 7AA",
    "sg:province":"Tyne and Wear",
    "sg:tags":[
        "shop",
        "second-hand"
    ],
    "wof:name":"The Trading Post",
    "wof:placetype":"venue"
},
  "geometry": {"coordinates":[-1.395816,54.907227],"type":"Point"}
}