{
  "type": "Feature",
  "properties": {
    "iso:country":"GB",
    "sg:address":"1a Balbirnie Craft Centre",
    "sg:city":"Glenrothes",
    "sg:classifiers":[
        {
            "category":"Manufacturing",
            "subcategory":"Retail Goods",
            "type":"Manufacturing & Wholesale Goods"
        },
        {
            "category":"Manufacturing",
            "subcategory":"Glass & Minerals",
            "type":"Manufacturing & Wholesale Goods"
        }
    ],
    "sg:phone":"+44 1592 611938",
    "sg:postcode":"KY7 6NR",
    "sg:province":"Fife",
    "sg:tags":[
        "giftware",
        "product",
        "manufacturer"
    ],
    "wof:name":"Jangles",
    "wof:placetype":"venue"
},
  "geometry": {"coordinates":[-3.1410639286,56.2030601501],"type":"Point"}
}