{
  "type": "Feature",
  "properties": {
    "iso:country":"GB",
    "sg:address":"Harris Court Mill, Ward Street",
    "sg:city":"Bradford",
    "sg:classifiers":[
        {
            "category":"Shopping",
            "subcategory":"Clothing, Apparel, & Fashions",
            "type":"Retail Goods"
        }
    ],
    "sg:phone":"+44 1274 522204",
    "sg:postcode":"BD7 4EQ",
    "sg:province":"West Yorkshire",
    "sg:tags":[
        "clothing",
        "fabric"
    ],
    "wof:name":"Louis Hoffman Clothing (1996) Ltd.",
    "wof:placetype":"venue"
},
  "geometry": {"coordinates":[-1.785964,53.77969],"type":"Point"}
}