{
  "type": "Feature",
  "properties": {
    "addr:full":"171 Victoria Road Horley Surrey RH6 7AR",
    "addr:housenumber":"171",
    "addr:postcode":"rh6 7ar",
    "addr:street":"Victoria Road",
    "iso:country":"GB",
    "sg:address":"171 Victoria Road",
    "sg:city":"Horley",
    "sg:classifiers":[
        {
            "category":"Fast Food",
            "type":"Food & Drink"
        }
    ],
    "sg:phone":"+44 1293 421873",
    "sg:postcode":"RH6 7AR",
    "sg:province":"Surrey",
    "sg:tags":[
        "away",
        "take"
    ],
    "wof:name":"The Horley Charcoal Grill",
    "wof:placetype":"venue"
},
  "geometry": {"coordinates":[-0.169277,51.173679],"type":"Point"}
}