{
  "type": "Feature",
  "properties": {
    "addr:full":"37-39 The Moor Sheffield South Yorkshire S1 4PF",
    "addr:housenumber":"37-39",
    "addr:postcode":"s1 4pf",
    "addr:street":"The Moor",
    "iso:country":"GB",
    "sg:address":"37-39 The Moor",
    "sg:city":"Sheffield",
    "sg:classifiers":[
        {
            "category":"Shopping",
            "subcategory":"Bicycles & Sporting Goods",
            "type":"Retail Goods"
        },
        {
            "category":"Sports & Exercise",
            "subcategory":"Sports Center",
            "type":"Entertainment"
        }
    ],
    "sg:phone":"+44 114 272 3792",
    "sg:postcode":"S1 4PF",
    "sg:province":"South Yorkshire",
    "sg:tags":[
        "shop",
        "sale"
    ],
    "wof:name":"J J B Sports Plc",
    "wof:placetype":"venue"
},
  "geometry": {"coordinates":[-1.472792,53.376736],"type":"Point"}
}