{
  "type": "Feature",
  "properties": {
    "addr:full":"Blindwells Tranent East Lothian EH33 1DX",
    "addr:postcode":"eh33 1dx",
    "iso:country":"GB",
    "sg:address":"Blindwells",
    "sg:city":"Tranent",
    "sg:classifiers":[
        {
            "category":"Mining & Drilling",
            "type":"Manufacturing & Wholesale Goods"
        }
    ],
    "sg:phone":"+44 1875 812943",
    "sg:postcode":"EH33 1DX",
    "sg:province":"East Lothian",
    "sg:tags":[
        "coal"
    ],
    "wof:name":"Scottish Coal",
    "wof:placetype":"venue"
},
  "geometry": {"coordinates":[-2.953759,55.944515],"type":"Point"}
}