{
  "type": "Feature",
  "properties": {
    "addr:full":"8 Burns Street Irvine North Ayrshire KA12 8RP",
    "addr:housenumber":"8",
    "addr:postcode":"ka12 8rp",
    "addr:street":"Burns Street",
    "iso:country":"GB",
    "sg:address":"8 Burns Street",
    "sg:city":"Irvine",
    "sg:classifiers":[
        {
            "category":"Manufacturing",
            "subcategory":"Wood Products",
            "type":"Manufacturing & Wholesale Goods"
        }
    ],
    "sg:phone":"+44 1294 311113",
    "sg:postcode":"KA12 8RP",
    "sg:province":"North Ayrshire",
    "sg:tags":[
        "maker",
        "cabinet"
    ],
    "wof:name":"Homeplanner",
    "wof:placetype":"venue"
},
  "geometry": {"coordinates":[-4.6689791679,55.6181106567],"type":"Point"}
}