{
  "type": "Feature",
  "properties": {
    "addr:full":"Birkbeck Food Stores, Birbeck Road London Greater London E8 2LD",
    "addr:postcode":"e8 2ld",
    "addr:street":"Birbeck Road",
    "iso:country":"GB",
    "sg:address":"Birkbeck Food Stores, Birbeck Road",
    "sg:city":"London",
    "sg:classifiers":[
        {
            "category":"Farming",
            "subcategory":"Farm",
            "type":"Manufacturing & Wholesale Goods"
        }
    ],
    "sg:postcode":"E8 2LD",
    "sg:province":"Greater London",
    "sg:tags":[
        "egg",
        "producer"
    ],
    "wof:name":"Julians",
    "wof:placetype":"venue"
},
  "geometry": {"coordinates":[-0.0742300004,51.5495986938],"type":"Point"}
}