{
  "type": "Feature",
  "properties": {
    "addr:full":"Italstyle Factory, Cambridge Road Harlow Essex CM20 2HE",
    "addr:postcode":"cm20 2he",
    "addr:street":"Cambridge Road",
    "iso:country":"GB",
    "sg:address":"Italstyle Factory, Cambridge Road",
    "sg:city":"Harlow",
    "sg:classifiers":[
        {
            "category":"Shopping",
            "subcategory":"Discount & Variety Stores",
            "type":"Retail Goods"
        }
    ],
    "sg:phone":"+44 1279 418942",
    "sg:postcode":"CM20 2HE",
    "sg:province":"Essex",
    "sg:tags":[
        "cleaning",
        "supply"
    ],
    "wof:name":"C C Hydrosonics Ltd.",
    "wof:placetype":"venue"
},
  "geometry": {"coordinates":[0.0975060016,51.7731513977],"type":"Point"}
}