{
  "type": "Feature",
  "properties": {
    "addr:full":"St Mildreds Gardens Westgate-on-sea Kent CT8 8TP",
    "addr:postcode":"ct8 8tp",
    "addr:street":"St Mildreds Gardens Westgate-On-Sea",
    "iso:country":"GB",
    "sg:address":"St Mildreds Gardens",
    "sg:city":"Westgate-on-sea",
    "sg:classifiers":[
        {
            "category":"Cafe",
            "type":"Food & Drink"
        }
    ],
    "sg:phone":"+44 1843 831851",
    "sg:postcode":"CT8 8TP",
    "sg:province":"Kent",
    "sg:tags":[
        "tea",
        "snack",
        "bar",
        "room"
    ],
    "wof:name":"Pavs Tea Gardens",
    "wof:placetype":"venue"
},
  "geometry": {"coordinates":[1.3422349691,51.3846092224],"type":"Point"}
}