{
  "type": "Feature",
  "properties": {
    "addr:full":"1 Bank Buildings, Princes St Moorgate Greater London EC2R 8EU",
    "addr:housenumber":"1",
    "addr:postcode":"ec2r 8eu",
    "addr:street":"Bank Buildings Princes St",
    "iso:country":"GB",
    "sg:address":"1 Bank Buildings, Princes St",
    "sg:city":"Moorgate",
    "sg:classifiers":[
        {
            "category":"Organizations",
            "subcategory":"Non-profit Organization",
            "type":"Services"
        }
    ],
    "sg:phone":"+44 20 7726 4961",
    "sg:postcode":"EC2R 8EU",
    "sg:province":"Greater London",
    "sg:tags":[
        "organisation",
        "voluntary",
        "charity"
    ],
    "wof:name":"Opportunities For People With Disabilities",
    "wof:placetype":"venue"
},
  "geometry": {"coordinates":[-0.08905,51.5144],"type":"Point"}
}