{
  "type": "Feature",
  "properties": {
    "addr:full":"Fairfax House, Fulwood Place London Greater London WC1V 6UB",
    "addr:postcode":"wc1v 6ub",
    "addr:street":"Fulwood Place",
    "iso:country":"GB",
    "sg:address":"Fairfax House, Fulwood Place",
    "sg:city":"London",
    "sg:classifiers":[
        {
            "category":"Shopping",
            "subcategory":"Department Store",
            "type":"Retail Goods"
        }
    ],
    "sg:postcode":"WC1V 6UB",
    "sg:province":"Greater London",
    "wof:name":"Speed-It Sales Ltd",
    "wof:placetype":"venue"
},
  "geometry": {"coordinates":[-0.11353,51.518726],"type":"Point"}
}