{
  "type": "Feature",
  "properties": {
    "iso:country":"GB",
    "sg:address":"4 Queens Parade",
    "sg:city":"Hove",
    "sg:classifiers":[
        {
            "category":"Personal",
            "subcategory":"Beauty Salon",
            "type":"Services"
        }
    ],
    "sg:phone":"+44 1273 772444",
    "sg:postcode":"BN3 8JG",
    "sg:province":"East Sussex",
    "sg:tags":[
        "unisex",
        "hairdresser"
    ],
    "wof:name":"The Rose",
    "wof:placetype":"venue"
},
  "geometry": {"coordinates":[-0.193939,50.845161],"type":"Point"}
}