{
  "type": "Feature",
  "properties": {
    "addr:full":"Lodge Farm, Braunston Road, Knossington Oakham Leicestershire LE15 8LW",
    "addr:postcode":"le15 8lw",
    "addr:street":"Lodge;Braunston Road",
    "iso:country":"GB",
    "sg:address":"Lodge Farm, Braunston Road, Knossington",
    "sg:city":"Oakham",
    "sg:classifiers":[
        {
            "category":"Farming",
            "subcategory":"Livestock Farm",
            "type":"Manufacturing & Wholesale Goods"
        },
        {
            "category":"Farming",
            "subcategory":"Farm",
            "type":"Manufacturing & Wholesale Goods"
        }
    ],
    "sg:phone":"+44 1664 454227",
    "sg:postcode":"LE15 8LW",
    "sg:province":"Leicestershire",
    "sg:tags":[
        "mixed",
        "crop",
        "others"
    ],
    "wof:name":"J D Duffin",
    "wof:placetype":"venue"
},
  "geometry": {"coordinates":[-0.815974,52.669209],"type":"Point"}
}