{
  "type": "Feature",
  "properties": {
    "iso:country":"GB",
    "sg:address":"7 Trafalgar Square",
    "sg:city":"Scarborough",
    "sg:classifiers":[
        {
            "category":"Travel",
            "subcategory":"Hotels & Motels",
            "type":"Entertainment"
        }
    ],
    "sg:phone":"+44 1723 374145",
    "sg:postcode":"YO12 7PZ",
    "sg:province":"North Yorkshire",
    "sg:tags":[
        "house",
        "guest"
    ],
    "wof:name":"St Andrews Guest House",
    "wof:placetype":"venue"
},
  "geometry": {"coordinates":[-0.4032129943,54.2880783081],"type":"Point"}
}