{
  "type": "Feature",
  "properties": {
    "iso:country":"GB",
    "sg:address":"Old Station Close, Coalville",
    "sg:city":"Leicester",
    "sg:classifiers":[
        {
            "category":"Building & Trades",
            "subcategory":"Construction",
            "type":"Services"
        }
    ],
    "sg:phone":"+44 1530 837014",
    "sg:postcode":"LE67 3FH",
    "sg:province":"Leicestershire",
    "sg:tags":[
        "glazier"
    ],
    "wof:name":"Coalville Glass & Glazing Co. Ltd.",
    "wof:placetype":"venue"
},
  "geometry": {"coordinates":[-1.3701210022,52.7255630493],"type":"Point"}
}