{
  "type": "Feature",
  "properties": {
    "addr:full":"Unit 16, Britannia Trading Estate, Britannia Road Huddersfield West Yorkshire HD3 4QG",
    "addr:housenumber":"unit 16;estate",
    "addr:postcode":"hd3 4qg",
    "addr:street":"Trading;Britannia Road",
    "iso:country":"GB",
    "sg:address":"Unit 16, Britannia Trading Estate, Britannia Road",
    "sg:city":"Huddersfield",
    "sg:classifiers":[
        {
            "category":"Taxi",
            "type":"Transportation"
        },
        {
            "category":"Military Area",
            "subcategory":"Air Force Base",
            "type":"Public Place"
        }
    ],
    "sg:postcode":"HD3 4QG",
    "sg:province":"West Yorkshire",
    "sg:tags":[
        "mini",
        "hire",
        "private",
        "cab"
    ],
    "wof:name":"Golcar Taxis",
    "wof:placetype":"venue"
},
  "geometry": {"coordinates":[-1.83737,53.63858],"type":"Point"}
}