{
  "type": "Feature",
  "properties": {
    "addr:full":"University Park Nottingham Nottinghamshire NG7 2RJ",
    "addr:postcode":"ng7 2rj",
    "iso:country":"GB",
    "sg:address":"University Park",
    "sg:city":"Nottingham",
    "sg:classifiers":[
        {
            "category":"Community Center",
            "type":"Public Place"
        },
        {
            "category":"Conference Center",
            "type":"Public Place"
        }
    ],
    "sg:phone":"+44 115 951 5000",
    "sg:postcode":"NG7 2RJ",
    "sg:province":"Nottinghamshire",
    "sg:tags":[
        "facility",
        "room",
        "centre"
    ],
    "wof:name":"East Midlands Conference Centre Ltd",
    "wof:placetype":"venue"
},
  "geometry": {"coordinates":[-1.1872489452,52.9377288818],"type":"Point"}
}