{
  "type": "Feature",
  "properties": {
    "iso:country":"GB",
    "sg:address":"60 North Promenade",
    "sg:city":"Lytham St Annes",
    "sg:classifiers":[
        {
            "category":"Health Services",
            "subcategory":"Nursing And Care Facility",
            "type":"Services"
        }
    ],
    "sg:phone":"+44 1253 721836",
    "sg:postcode":"FY8 2NH",
    "sg:province":"Lancashire",
    "sg:tags":[
        "home"
    ],
    "wof:name":"Sandlawns Nursing Home",
    "wof:placetype":"venue"
},
  "geometry": {"coordinates":[-3.040116,53.75494],"type":"Point"}
}