{
  "type": "Feature",
  "properties": {
    "addr:full":"Union Rd, Bradfield Reading Berkshire RG7 6AB",
    "addr:postcode":"rg7 6ab",
    "addr:street":"Union Rd",
    "iso:country":"GB",
    "sg:address":"Union Rd, Bradfield",
    "sg:city":"Reading",
    "sg:classifiers":[
        {
            "category":"Home & Garden",
            "subcategory":"Building Materials",
            "type":"Retail Goods"
        }
    ],
    "sg:phone":"+44 118 974 4808",
    "sg:postcode":"RG7 6AB",
    "sg:province":"Berkshire",
    "sg:tags":[
        "fencing"
    ],
    "wof:name":"Fencetec Ltd",
    "wof:placetype":"venue"
},
  "geometry": {"coordinates":[-1.134029,51.438824],"type":"Point"}
}