{
  "type": "Feature",
  "properties": {
    "iso:country":"GB",
    "sg:address":"27 Park Road, Stalbridge",
    "sg:city":"Sturminster Newton",
    "sg:classifiers":[
        {
            "category":"Building & Trades",
            "subcategory":"Construction",
            "type":"Services"
        }
    ],
    "sg:phone":"+44 1963 362874",
    "sg:postcode":"DT10 2RB",
    "sg:province":"Dorset",
    "sg:tags":[
        "builder"
    ],
    "wof:name":"Jeremy Paul Bastable",
    "wof:placetype":"venue"
},
  "geometry": {"coordinates":[-2.383903,50.958534],"type":"Point"}
}