{
  "type": "Feature",
  "properties": {
    "addr:full":"Trew Farm Beaworthy Devon EX21 5AT",
    "addr:housenumber":"beaworthy",
    "addr:postcode":"ex21 5at",
    "addr:street":"Devon",
    "iso:country":"GB",
    "sg:address":"Trew Farm",
    "sg:city":"Beaworthy",
    "sg:classifiers":[
        {
            "category":"Farming",
            "subcategory":"Dairy Farm",
            "type":"Manufacturing & Wholesale Goods"
        },
        {
            "category":"Farming",
            "subcategory":"Farm",
            "type":"Manufacturing & Wholesale Goods"
        }
    ],
    "sg:phone":"+44 1409 221139",
    "sg:postcode":"EX21 5AT",
    "sg:province":"Devon",
    "sg:tags":[
        "mixed"
    ],
    "wof:name":"R A J & B M & R J Balsdon",
    "wof:placetype":"venue"
},
  "geometry": {"coordinates":[-4.1833848953,50.7753067017],"type":"Point"}
}