{
  "type": "Feature",
  "properties": {
    "addr:full":"15 Coombe Road Kingston-upon-thames Greater London KT2 7AD",
    "addr:housenumber":"15",
    "addr:postcode":"kt2 7ad",
    "addr:street":"Coombe Road",
    "iso:country":"GB",
    "sg:address":"15 Coombe Road",
    "sg:city":"Kingston-upon-thames",
    "sg:classifiers":[
        {
            "category":"Autos & Motor Vehicles",
            "subcategory":"Automobile Sales",
            "type":"Retail Goods"
        }
    ],
    "sg:phone":"+44 20 8974 9944",
    "sg:postcode":"KT2 7AD",
    "sg:province":"Greater London",
    "sg:tags":[
        "car"
    ],
    "wof:name":"Lovekyn Garages Ltd.",
    "wof:placetype":"venue"
},
  "geometry": {"coordinates":[-0.2870219946,51.4126663208],"type":"Point"}
}