{
  "type": "Feature",
  "properties": {
    "addr:full":"Bogside Farm, Coylton Ayr East Ayrshire KA6 6HE",
    "addr:postcode":"ka6 6he",
    "addr:street":"Coylton;East",
    "iso:country":"GB",
    "sg:address":"Bogside Farm, Coylton",
    "sg:city":"Ayr",
    "sg:classifiers":[
        {
            "category":"Farming",
            "subcategory":"Dairy Farm",
            "type":"Manufacturing & Wholesale Goods"
        },
        {
            "category":"Farming",
            "subcategory":"Livestock Farm",
            "type":"Manufacturing & Wholesale Goods"
        }
    ],
    "sg:phone":"+44 1292 570293",
    "sg:postcode":"KA6 6HE",
    "sg:province":"East Ayrshire",
    "sg:tags":[
        "others",
        "farmer"
    ],
    "wof:name":"Bogside Dairy Farm",
    "wof:placetype":"venue"
},
  "geometry": {"coordinates":[-4.519444,55.44585],"type":"Point"}
}