{
  "type": "Feature",
  "properties": {
    "iso:country":"GB",
    "sg:address":"41 Victoria Place, Brightlingsea",
    "sg:city":"Colchester",
    "sg:classifiers":[
        {
            "category":"Bars & Pubs",
            "type":"Food & Drink"
        }
    ],
    "sg:phone":"+44 1206 304323",
    "sg:postcode":"CO7 0HT",
    "sg:province":"Essex",
    "sg:tags":[
        "pubs",
        "inn"
    ],
    "wof:name":"The Kings Head",
    "wof:placetype":"venue"
},
  "geometry": {"coordinates":[1.0243610144,51.811290741],"type":"Point"}
}