{
  "type": "Feature",
  "properties": {
    "addr:full":"Canal Forge, Lower Wharf, Northgate Street Devizes Wiltshire SN10 1JN",
    "addr:postcode":"sn10 1jn",
    "addr:street":"Canal Forge Lower Wharf Northgate Street",
    "iso:country":"GB",
    "sg:address":"Canal Forge, Lower Wharf, Northgate Street",
    "sg:city":"Devizes",
    "sg:classifiers":[
        {
            "category":"Home & Garden",
            "subcategory":"Building Materials",
            "type":"Retail Goods"
        },
        {
            "category":"Utilities",
            "subcategory":"Natural Gas",
            "type":"Services"
        }
    ],
    "sg:phone":"+44 1380 721759",
    "sg:postcode":"SN10 1JN",
    "sg:province":"Wiltshire",
    "sg:tags":[
        "blacksmith",
        "ironwork",
        "diy",
        "wrought"
    ],
    "wof:name":"JOHN GIRVAN",
    "wof:placetype":"venue"
},
  "geometry": {"coordinates":[-1.995031,51.351479],"type":"Point"}
}