{
  "type": "Feature",
  "properties": {
    "iso:country":"GB",
    "sg:address":"6 Union Street",
    "sg:city":"London",
    "sg:classifiers":[
        {
            "category":"Professional",
            "subcategory":"Art Services",
            "type":"Services"
        }
    ],
    "sg:phone":"+44 20 7407 3343",
    "sg:postcode":"SE1 1SZ",
    "sg:province":"Greater London",
    "sg:tags":[
        "consultant",
        "design"
    ],
    "wof:name":"Hudson Fuggle",
    "wof:placetype":"venue"
},
  "geometry": {"coordinates":[-0.092216,51.503456],"type":"Point"}
}