{
  "type": "Feature",
  "properties": {
    "iso:country":"GB",
    "sg:address":"43 Limpsfield Road, Sanderstead",
    "sg:city":"South Croydon",
    "sg:classifiers":[
        {
            "category":"Personal",
            "subcategory":"Beauty Salon",
            "type":"Services"
        }
    ],
    "sg:phone":"+44 20 8657 2057",
    "sg:postcode":"CR2 9LA",
    "sg:province":"Surrey",
    "sg:tags":[
        "lady",
        "hairdresser"
    ],
    "wof:name":"Gwen Barry",
    "wof:placetype":"venue"
},
  "geometry": {"coordinates":[-0.0763610005,51.3334846497],"type":"Point"}
}