{
  "type": "Feature",
  "properties": {
    "addr:full":"The Wood Street Studio, Wood Street Elland West Yorkshire HX5 9AP",
    "addr:postcode":"hx5 9ap",
    "addr:street":"The Wood Street Studio Wood Street",
    "iso:country":"GB",
    "sg:address":"The Wood Street Studio, Wood Street",
    "sg:city":"Elland",
    "sg:classifiers":[
        {
            "category":"Professional",
            "subcategory":"Art Services",
            "type":"Services"
        }
    ],
    "sg:postcode":"HX5 9AP",
    "sg:province":"West Yorkshire",
    "sg:tags":[
        "consultant",
        "design"
    ],
    "wof:name":"Black Peach Design",
    "wof:placetype":"venue"
},
  "geometry": {"coordinates":[-1.8337039948,53.6850357056],"type":"Point"}
}