{
  "type": "Feature",
  "properties": {
    "addr:full":"21 Mill St Perth Perth and Kinross PH1 5JQ",
    "addr:housenumber":"21",
    "addr:postcode":"ph1 5jq",
    "addr:street":"Mill St",
    "iso:country":"GB",
    "sg:address":"21 Mill St",
    "sg:city":"Perth",
    "sg:classifiers":[
        {
            "category":"Social Services",
            "type":"Services"
        }
    ],
    "sg:phone":"+44 1738 412000",
    "sg:postcode":"PH1 5JQ",
    "sg:province":"Perth and Kinross",
    "sg:tags":[
        "benefit",
        "agency"
    ],
    "wof:name":"Benefits Agency",
    "wof:placetype":"venue"
},
  "geometry": {"coordinates":[-3.4323968887,56.3977813721],"type":"Point"}
}