{
  "type": "Feature",
  "properties": {
    "iso:country":"GB",
    "sg:address":"28 Earl Street",
    "sg:city":"Coventry",
    "sg:classifiers":[
        {
            "category":"Food & Beverages",
            "subcategory":"Bakery",
            "type":"Retail Goods"
        }
    ],
    "sg:phone":"+44 24 7622 2951",
    "sg:postcode":"CV1 5RU",
    "sg:province":"West Midlands",
    "sg:tags":[
        "shop",
        "baker"
    ],
    "wof:name":"Three Cooks",
    "wof:placetype":"venue"
},
  "geometry": {"coordinates":[-1.5063669682,52.406791687],"type":"Point"}
}