{
  "type": "Feature",
  "properties": {
    "iso:country":"GB",
    "sg:address":"Belvedere, Barrow Hill",
    "sg:city":"Bury St Edmunds",
    "sg:classifiers":[
        {
            "category":"Building & Trades",
            "subcategory":"Construction",
            "type":"Services"
        }
    ],
    "sg:phone":"+44 1284 810170",
    "sg:postcode":"IP29 5DX",
    "sg:province":"Suffolk",
    "sg:tags":[
        "tiling",
        "contractor"
    ],
    "wof:name":"M A Smith Tiling Contractors",
    "wof:placetype":"venue"
},
  "geometry": {"coordinates":[0.5847399831,52.2387008667],"type":"Point"}
}