{
  "type": "Feature",
  "properties": {
    "addr:full":"Old Fallings Lane Wolverhampton Staffordshire WV10 8BJ",
    "addr:postcode":"wv10 8bj",
    "addr:street":"Old Fallings Lane",
    "iso:country":"GB",
    "sg:address":"Old Fallings Lane",
    "sg:city":"Wolverhampton",
    "sg:classifiers":[
        {
            "category":"Social Services",
            "type":"Services"
        }
    ],
    "sg:phone":"+44 1902 558371",
    "sg:postcode":"WV10 8BJ",
    "sg:province":"Staffordshire",
    "sg:tags":[
        "educational"
    ],
    "wof:name":"Sutherland Education & Training Agency",
    "wof:placetype":"venue"
},
  "geometry": {"coordinates":[-2.109626,52.616299],"type":"Point"}
}