{
  "type": "Feature",
  "properties": {
    "addr:full":"61 Bridge Street Aberystwyth Ceredigion SY23 1QD",
    "addr:housenumber":"61",
    "addr:postcode":"sy23 1qd",
    "addr:street":"Bridge Street",
    "iso:country":"GB",
    "sg:address":"61 Bridge Street",
    "sg:city":"Aberystwyth",
    "sg:classifiers":[
        {
            "category":"Food & Beverages",
            "subcategory":"Meat & Fish",
            "type":"Retail Goods"
        }
    ],
    "sg:postcode":"SY23 1QD",
    "sg:province":"Ceredigion",
    "sg:tags":[
        "butcher"
    ],
    "wof:name":"Bridgend Butcher Shop",
    "wof:placetype":"venue"
},
  "geometry": {"coordinates":[-4.085878849,52.4139137268],"type":"Point"}
}