{
  "type": "Feature",
  "properties": {
    "addr:full":"37 Wormgate Boston Lincolnshire PE21 6NR",
    "addr:housenumber":"37",
    "addr:postcode":"pe21 6nr",
    "addr:street":"Wormgate Boston",
    "iso:country":"GB",
    "sg:address":"37 Wormgate",
    "sg:city":"Boston",
    "sg:classifiers":[
        {
            "category":"Food & Beverages",
            "subcategory":"Meat & Fish",
            "type":"Retail Goods"
        }
    ],
    "sg:phone":"+44 1205 362625",
    "sg:postcode":"PE21 6NR",
    "sg:province":"Lincolnshire",
    "sg:tags":[
        "butcher"
    ],
    "wof:name":"Thomas Bycroft Butchers Ltd.",
    "wof:placetype":"venue"
},
  "geometry": {"coordinates":[-0.0262139998,52.9798774719],"type":"Point"}
}