{
  "type": "Feature",
  "properties": {
    "addr:full":"95 Main Street, Sedgeberrow Evesham Gloucestershire WR11 7UE",
    "addr:housenumber":"95",
    "addr:postcode":"wr11 7ue",
    "addr:street":"Main Street",
    "iso:country":"GB",
    "sg:address":"95 Main Street, Sedgeberrow",
    "sg:city":"Evesham",
    "sg:classifiers":[
        {
            "category":"Food & Beverages",
            "subcategory":"Farmers Market",
            "type":"Retail Goods"
        }
    ],
    "sg:phone":"+44 1386 881919",
    "sg:postcode":"WR11 7UE",
    "sg:province":"Gloucestershire",
    "sg:tags":[
        "gardener"
    ],
    "wof:name":"F B Hacklett & Sons",
    "wof:placetype":"venue"
},
  "geometry": {"coordinates":[-1.973099,52.043449],"type":"Point"}
}