{
  "type": "Feature",
  "properties": {
    "iso:country":"GB",
    "sg:address":"36 King Edward Avenue",
    "sg:city":"Blackpool",
    "sg:classifiers":[
        {
            "category":"Travel",
            "subcategory":"Hotels & Motels",
            "type":"Entertainment"
        }
    ],
    "sg:postcode":"FY2 9TA",
    "sg:province":"Lancashire",
    "wof:name":"Sunnyside Hotel",
    "wof:placetype":"venue"
},
  "geometry": {"coordinates":[-3.051752,53.83543],"type":"Point"}
}