{
  "type": "Feature",
  "properties": {
    "iso:country":"GB",
    "sg:address":"45 Boulton Road",
    "sg:city":"Reading",
    "sg:classifiers":[
        {
            "category":"Professional",
            "subcategory":"Computer Services",
            "type":"Services"
        }
    ],
    "sg:phone":"+44 118 931 4177",
    "sg:postcode":"RG2 0NH",
    "sg:province":"Berkshire",
    "sg:tags":[
        "system",
        "software"
    ],
    "wof:name":"Kaimet Systems",
    "wof:placetype":"venue"
},
  "geometry": {"coordinates":[-0.974067,51.43795],"type":"Point"}
}