{
  "type": "Feature",
  "properties": {
    "addr:full":"Unit 4 Turbury Retail Park, 891-895 Ringwood Road Bournemouth Dorset BH11 8LL",
    "addr:housenumber":"unit 4 turbury retail",
    "addr:postcode":"891-895;bh11 8ll",
    "addr:street":"Park;Ringwood Road",
    "iso:country":"GB",
    "sg:address":"Unit 4 Turbury Retail Park, 891-895 Ringwood Road",
    "sg:city":"Bournemouth",
    "sg:classifiers":[
        {
            "category":"Shopping",
            "subcategory":"Shoes",
            "type":"Retail Goods"
        }
    ],
    "sg:phone":"+44 1202 591906",
    "sg:postcode":"BH11 8LL",
    "sg:province":"Dorset",
    "sg:tags":[
        "shop"
    ],
    "wof:name":"Brantano",
    "wof:placetype":"venue"
},
  "geometry": {"coordinates":[-1.9279,50.756908],"type":"Point"}
}