{
  "type": "Feature",
  "properties": {
    "iso:country":"GB",
    "sg:address":"Hay Close, Calthwaite",
    "sg:city":"Penrith",
    "sg:classifiers":[
        {
            "category":"Farming",
            "subcategory":"Farm",
            "type":"Manufacturing & Wholesale Goods"
        }
    ],
    "sg:phone":"+44 1768 885371",
    "sg:postcode":"CA11 9PX",
    "sg:province":"Cumbria",
    "sg:tags":[
        "mixed",
        "crop"
    ],
    "wof:name":"Claremont Properties Newcastle Ltd",
    "wof:placetype":"venue"
},
  "geometry": {"coordinates":[-2.826264,54.753235],"type":"Point"}
}