{
  "type": "Feature",
  "properties": {
    "addr:full":"Wreking Retail Park, Arleston Telford Shropshire TF1 2DE",
    "addr:postcode":"tf1 2de",
    "iso:country":"GB",
    "sg:address":"Wreking Retail Park, Arleston",
    "sg:city":"Telford",
    "sg:classifiers":[
        {
            "category":"Home & Garden",
            "subcategory":"Hardware",
            "type":"Retail Goods"
        }
    ],
    "sg:phone":"+44 1952 261800",
    "sg:postcode":"TF1 2DE",
    "sg:province":"Shropshire",
    "sg:tags":[
        "retailer",
        "diy"
    ],
    "wof:name":"Homebase Ltd.",
    "wof:placetype":"venue"
},
  "geometry": {"coordinates":[-2.501864,52.696346],"type":"Point"}
}