{
  "type": "Feature",
  "properties": {
    "addr:full":"6 Stepfields Witham Essex CM8 3BY",
    "addr:housenumber":"6",
    "addr:postcode":"cm8 3by",
    "addr:street":"Stepfields Witham",
    "iso:country":"GB",
    "sg:address":"6 Stepfields",
    "sg:city":"Witham",
    "sg:classifiers":[
        {
            "category":"Home & Garden",
            "subcategory":"Home Furnishings",
            "type":"Retail Goods"
        },
        {
            "category":"Home & Garden",
            "subcategory":"Building Materials",
            "type":"Retail Goods"
        }
    ],
    "sg:phone":"+44 1376 512850",
    "sg:postcode":"CM8 3BY",
    "sg:province":"Essex",
    "sg:tags":[
        "installers",
        "planner",
        "kitchen",
        "furnishers"
    ],
    "wof:name":"South Essex Kitchens Ltd.",
    "wof:placetype":"venue"
},
  "geometry": {"coordinates":[0.6990399957,51.7952804565],"type":"Point"}
}