{
  "type": "Feature",
  "properties": {
    "addr:full":"314 Prescot Road Liverpool Merseyside L13 3AP",
    "addr:housenumber":"314",
    "addr:postcode":"l13 3ap",
    "addr:street":"Prescot Road",
    "iso:country":"GB",
    "sg:address":"314 Prescot Road",
    "sg:city":"Liverpool",
    "sg:classifiers":[
        {
            "category":"Autos & Motor Vehicles",
            "subcategory":"Auto Supplies",
            "type":"Retail Goods"
        }
    ],
    "sg:postcode":"L13 3AP",
    "sg:province":"Merseyside",
    "sg:tags":[
        "tyre"
    ],
    "wof:name":"Old Swan Tyres",
    "wof:placetype":"venue"
},
  "geometry": {"coordinates":[-2.9269390106,53.4148597717],"type":"Point"}
}