{
  "type": "Feature",
  "properties": {
    "iso:country":"GB",
    "sg:address":"8 Kew Walk",
    "sg:city":"Bristol",
    "sg:classifiers":[
        {
            "category":"Retail",
            "subcategory":"Laundry & Dry Cleaning",
            "type":"Services"
        }
    ],
    "sg:postcode":"BS4 5DU",
    "sg:province":"City of Bristol",
    "sg:tags":[
        "home",
        "ironing"
    ],
    "wof:name":"Ironing Maids",
    "wof:placetype":"venue"
},
  "geometry": {"coordinates":[-2.5563390255,51.4273376465],"type":"Point"}
}