{
  "type": "Feature",
  "properties": {
    "addr:full":"Rich's Sidings, Broadway Didcot Oxfordshire OX11 8AG",
    "addr:postcode":"ox11 8ag",
    "addr:street":"Rich'S Sidings",
    "iso:country":"GB",
    "sg:address":"Rich's Sidings, Broadway",
    "sg:city":"Didcot",
    "sg:classifiers":[
        {
            "category":"Home & Garden",
            "subcategory":"Building Materials",
            "type":"Retail Goods"
        }
    ],
    "sg:phone":"+44 1235 512025",
    "sg:postcode":"OX11 8AG",
    "sg:province":"Oxfordshire",
    "sg:tags":[
        "fencing"
    ],
    "wof:name":"Applin",
    "wof:placetype":"venue"
},
  "geometry": {"coordinates":[-1.233989954,51.6073799133],"type":"Point"}
}