{
  "type": "Feature",
  "properties": {
    "addr:full":"Belle Vue House, Tennyson Avenue Bridlington East Riding of Yorkshire YO15 2ET",
    "addr:postcode":"yo15 2et",
    "addr:street":"Belle;Tennyson Avenue",
    "iso:country":"GB",
    "sg:address":"Belle Vue House, Tennyson Avenue",
    "sg:city":"Bridlington",
    "sg:classifiers":[
        {
            "category":"Health Services",
            "subcategory":"Health Practitioner",
            "type":"Services"
        }
    ],
    "sg:phone":"+44 1262 678102",
    "sg:postcode":"YO15 2ET",
    "sg:province":"East Riding of Yorkshire",
    "sg:tags":[
        "therapist",
        "speech"
    ],
    "wof:name":"Natural Health Clinic",
    "wof:placetype":"venue"
},
  "geometry": {"coordinates":[-0.187399,54.08749],"type":"Point"}
}