{
  "type": "Feature",
  "properties": {
    "addr:full":"Lawford Close, Nechells Birmingham West Midlands B7 4HJ",
    "addr:postcode":"b7 4hj",
    "addr:street":"Lawford Close",
    "iso:country":"GB",
    "sg:address":"Lawford Close, Nechells",
    "sg:city":"Birmingham",
    "sg:classifiers":[
        {
            "category":"Home & Garden",
            "subcategory":"Hardware",
            "type":"Retail Goods"
        }
    ],
    "sg:phone":"+44 121 359 1155",
    "sg:postcode":"B7 4HJ",
    "sg:province":"West Midlands",
    "sg:tags":[
        "device",
        "fixing",
        "fastener"
    ],
    "wof:name":"Heads & Allthreads Ltd.",
    "wof:placetype":"venue"
},
  "geometry": {"coordinates":[-1.87865,52.483116],"type":"Point"}
}