{
  "type": "Feature",
  "properties": {
    "addr:full":"2 Eastbourne Road Portsmouth Hampshire PO3 6LN",
    "addr:housenumber":"2",
    "addr:postcode":"hampshire po3 6ln",
    "addr:street":"Eastbourne Road",
    "iso:country":"GB",
    "sg:address":"2 Eastbourne Road",
    "sg:city":"Portsmouth",
    "sg:classifiers":[
        {
            "category":"Professional",
            "subcategory":"Accounting & Tax Preparation",
            "type":"Services"
        }
    ],
    "sg:phone":"+44 23 9267 0646",
    "sg:postcode":"PO3 6LN",
    "sg:province":"Hampshire",
    "sg:tags":[
        "accountant",
        "bookkeeping",
        "primarily",
        "activity"
    ],
    "wof:name":"K H Watson",
    "wof:placetype":"venue"
},
  "geometry": {"coordinates":[-1.06134,50.811623],"type":"Point"}
}