{
  "type": "Feature",
  "properties": {
    "addr:full":"Idsall Court, Broadway Shifnal Shropshire TF11 8AZ",
    "addr:postcode":"tf11 8az",
    "addr:street":"Broadway",
    "iso:country":"GB",
    "sg:address":"Idsall Court, Broadway",
    "sg:city":"Shifnal",
    "sg:classifiers":[
        {
            "category":"Organizations",
            "subcategory":"Community Association",
            "type":"Services"
        }
    ],
    "sg:phone":"+44 1952 463603",
    "sg:postcode":"TF11 8AZ",
    "sg:province":"Shropshire",
    "sg:tags":[
        "co-operatives",
        "society",
        "housing",
        "trust"
    ],
    "wof:name":"Wednesfield Housing Association Ltd",
    "wof:placetype":"venue"
},
  "geometry": {"coordinates":[-2.369959,52.672825],"type":"Point"}
}