{
  "type": "Feature",
  "properties": {
    "addr:full":"Hog Lane, Ashley Green Chesham Buckinghamshire HP5 3PS",
    "addr:postcode":"hp5 3ps",
    "addr:street":"Hog Lane",
    "iso:country":"GB",
    "sg:address":"Hog Lane, Ashley Green",
    "sg:city":"Chesham",
    "sg:classifiers":[
        {
            "category":"Home & Garden",
            "subcategory":"Building Materials",
            "type":"Retail Goods"
        }
    ],
    "sg:phone":"+44 1442 866264",
    "sg:postcode":"HP5 3PS",
    "sg:province":"Buckinghamshire",
    "sg:tags":[
        "gate",
        "door",
        "barrier"
    ],
    "wof:name":"Manning G & M B Ltd.",
    "wof:placetype":"venue"
},
  "geometry": {"coordinates":[-0.590492,51.739323],"type":"Point"}
}