{
  "type": "Feature",
  "properties": {
    "addr:full":"Cross Park Farm, Burrington Umberleigh Devon EX37 9LA",
    "addr:housenumber":"burrington umberleigh",
    "addr:postcode":"ex37 9la",
    "addr:street":"Cross Park",
    "iso:country":"GB",
    "sg:address":"Cross Park Farm, Burrington",
    "sg:city":"Umberleigh",
    "sg:classifiers":[
        {
            "category":"Farming",
            "subcategory":"Dairy Farm",
            "type":"Manufacturing & Wholesale Goods"
        }
    ],
    "sg:phone":"+44 1769 520243",
    "sg:postcode":"EX37 9LA",
    "sg:province":"Devon",
    "sg:tags":[
        "farmer"
    ],
    "wof:name":"M W & S E Wooldridge",
    "wof:placetype":"venue"
},
  "geometry": {"coordinates":[-3.985345,50.995815],"type":"Point"}
}