{
  "type": "Feature",
  "properties": {
    "iso:country":"GB",
    "sg:address":"Leicester South Field College, Westcotes Campus, Upperton Road",
    "sg:city":"Leicester",
    "sg:classifiers":[
        {
            "category":"Education",
            "subcategory":"University",
            "type":"Public Place"
        }
    ],
    "sg:phone":"+44 116 224 2103",
    "sg:postcode":"LE1 3WL",
    "sg:province":"Leicestershire",
    "sg:tags":[
        "adult"
    ],
    "wof:name":"Employment Education & Training Access Centre",
    "wof:placetype":"venue"
},
  "geometry": {"coordinates":[-1.140365,52.637886],"type":"Point"}
}