{
  "type": "Feature",
  "properties": {
    "iso:country":"GB",
    "sg:address":"Suite 14 Armley Park Court, 9 Stanningley Road",
    "sg:city":"Leeds",
    "sg:classifiers":[
        {
            "category":"Professional",
            "subcategory":"Accounting & Tax Preparation",
            "type":"Services"
        }
    ],
    "sg:postcode":"LS12 2AE",
    "sg:province":"West Yorkshire",
    "sg:tags":[
        "accountant"
    ],
    "wof:name":"Northern Accounting",
    "wof:placetype":"venue"
},
  "geometry": {"coordinates":[-1.5887930393,53.7987556458],"type":"Point"}
}