{
  "type": "Feature",
  "properties": {
    "addr:full":"43 Hillary Road High Wycombe Buckinghamshire HP13 7RB",
    "addr:housenumber":"43",
    "addr:postcode":"hp13 7rb",
    "addr:street":"Hillary Road",
    "iso:country":"GB",
    "sg:address":"43 Hillary Road",
    "sg:city":"High Wycombe",
    "sg:classifiers":[
        {
            "category":"Retail",
            "subcategory":"Auto Repair",
            "type":"Services"
        }
    ],
    "sg:postcode":"HP13 7RB",
    "sg:province":"Buckinghamshire",
    "sg:tags":[
        "car",
        "upholsterer"
    ],
    "wof:name":"Burn Buster",
    "wof:placetype":"venue"
},
  "geometry": {"coordinates":[-0.728699,51.629017],"type":"Point"}
}