{
  "type": "Feature",
  "properties": {
    "iso:country":"GB",
    "sg:address":"127 Slaithwaite Rd",
    "sg:city":"Huddersfield",
    "sg:classifiers":[
        {
            "category":"Professional",
            "subcategory":"Employment Agencies",
            "type":"Services"
        }
    ],
    "sg:phone":"+44 1484 850731",
    "sg:postcode":"HD7 3PW",
    "sg:province":"West Yorkshire",
    "sg:tags":[
        "consultant"
    ],
    "wof:name":"D Lowe",
    "wof:placetype":"venue"
},
  "geometry": {"coordinates":[-1.8767980337,53.6403884888],"type":"Point"}
}