{
  "type": "Feature",
  "properties": {
    "iso:country":"GB",
    "sg:address":"4 Berry Square",
    "sg:city":"Paignton",
    "sg:classifiers":[
        {
            "category":"Travel",
            "subcategory":"Hotels & Motels",
            "type":"Entertainment"
        }
    ],
    "sg:phone":"+44 1803 557628",
    "sg:postcode":"TQ4 6AZ",
    "sg:province":"Devon",
    "sg:tags":[
        "house",
        "guest"
    ],
    "wof:name":"Dalehurst Guest House",
    "wof:placetype":"venue"
},
  "geometry": {"coordinates":[-3.5619440079,50.4359512329],"type":"Point"}
}