{
  "type": "Feature",
  "properties": {
    "addr:full":"Unit 20 Claro Court Business Centre, Claro Road Harrogate North Yorkshire HG1 4BA",
    "addr:housenumber":"unit 20",
    "addr:postcode":"hg1 4ba",
    "addr:street":"Claro Court;Claro Road",
    "iso:country":"GB",
    "sg:address":"Unit 20 Claro Court Business Centre, Claro Road",
    "sg:city":"Harrogate",
    "sg:classifiers":[
        {
            "category":"Brewery",
            "type":"Food & Drink"
        }
    ],
    "sg:phone":"+44 1423 561861",
    "sg:postcode":"HG1 4BA",
    "sg:province":"North Yorkshire",
    "sg:tags":[
        "brewer"
    ],
    "wof:name":"Rooster's Brewery",
    "wof:placetype":"venue"
},
  "geometry": {"coordinates":[-1.521849,54.003006],"type":"Point"}
}