{
  "type": "Feature",
  "properties": {
    "addr:full":"Church Farm, Llantrissent Usk Monmouthshire NP15 1LG",
    "addr:postcode":"np15 1lg",
    "iso:country":"GB",
    "sg:address":"Church Farm, Llantrissent",
    "sg:city":"Usk",
    "sg:classifiers":[
        {
            "category":"Manufacturing",
            "subcategory":"Food",
            "type":"Manufacturing & Wholesale Goods"
        },
        {
            "category":"Professional",
            "subcategory":"Business Services",
            "type":"Services"
        }
    ],
    "sg:phone":"+44 1291 673898",
    "sg:postcode":"NP15 1LG",
    "sg:province":"Monmouthshire",
    "sg:tags":[
        "import",
        "exporter",
        "export",
        "agent"
    ],
    "wof:name":"Euro Fresh Food Marketing",
    "wof:placetype":"venue"
},
  "geometry": {"coordinates":[-2.883728,51.667652],"type":"Point"}
}