{
  "type": "Feature",
  "properties": {
    "iso:country":"GB",
    "sg:address":"9 Burrows Close, Clifton",
    "sg:city":"Shefford",
    "sg:classifiers":[
        {
            "category":"Professional",
            "type":"Services"
        }
    ],
    "sg:phone":"+44 1462 635440",
    "sg:postcode":"SG17 5EG",
    "sg:province":"Bedfordshire",
    "sg:tags":[
        "interior",
        "furnishers",
        "designer"
    ],
    "wof:name":"Dragonfly",
    "wof:placetype":"venue"
},
  "geometry": {"coordinates":[-0.30866,52.036682],"type":"Point"}
}