{
  "type": "Feature",
  "properties": {
    "addr:full":"Unit 18 The Oasis, Meadowhall Centre Sheffield South Yorkshire S9 1EN",
    "addr:housenumber":"unit 18",
    "addr:postcode":"s9 1en",
    "addr:street":"The Oasis",
    "iso:country":"GB",
    "sg:address":"Unit 18 The Oasis, Meadowhall Centre",
    "sg:city":"Sheffield",
    "sg:classifiers":[
        {
            "category":"Shopping",
            "subcategory":"Beauty & Cosmetics",
            "type":"Retail Goods"
        }
    ],
    "sg:phone":"+44 114 256 8558",
    "sg:postcode":"S9 1EN",
    "sg:province":"South Yorkshire",
    "sg:tags":[
        "product"
    ],
    "wof:name":"Xtras",
    "wof:placetype":"venue"
},
  "geometry": {"coordinates":[-1.406079,53.41412],"type":"Point"}
}