{
  "type": "Feature",
  "properties": {
    "addr:full":"Tower Road, Tweedmouth Berwick-upon-tweed Northumberland TD15 2BD",
    "addr:postcode":"td15 2bd",
    "addr:street":"Tower Road",
    "iso:country":"GB",
    "sg:address":"Tower Road, Tweedmouth",
    "sg:city":"Berwick-upon-tweed",
    "sg:classifiers":[
        {
            "category":"Manufacturing",
            "subcategory":"Pottery",
            "type":"Manufacturing & Wholesale Goods"
        }
    ],
    "sg:postcode":"TD15 2BD",
    "sg:province":"Northumberland",
    "wof:name":"P & M Thomas Tower House Pottery",
    "wof:placetype":"venue"
},
  "geometry": {"coordinates":[-2.0078969002,55.7632102966],"type":"Point"}
}