{
  "type": "Feature",
  "properties": {
    "iso:country":"GB",
    "sg:address":"67 Lower Redland Road",
    "sg:city":"Bristol",
    "sg:classifiers":[
        {
            "category":"Real Estate",
            "subcategory":"Surveying",
            "type":"Services"
        }
    ],
    "sg:phone":"+44 117 908 1746",
    "sg:postcode":"BS6 6SP",
    "sg:province":"City of Bristol",
    "sg:tags":[
        "surveyor",
        "valuer"
    ],
    "wof:name":"Robert Cornish",
    "wof:placetype":"venue"
},
  "geometry": {"coordinates":[-2.608982,51.470802],"type":"Point"}
}