{
  "type": "Feature",
  "properties": {
    "addr:full":"Blackwood House, Roskear Camborne Cornwall TR14 8DL",
    "addr:postcode":"tr14 8dl",
    "iso:country":"GB",
    "sg:address":"Blackwood House, Roskear",
    "sg:city":"Camborne",
    "sg:classifiers":[
        {
            "category":"Social Services",
            "subcategory":"Retirement Home",
            "type":"Services"
        }
    ],
    "sg:phone":"+44 1209 713498",
    "sg:postcode":"TR14 8DL",
    "sg:province":"Cornwall",
    "sg:tags":[
        "residential",
        "care"
    ],
    "wof:name":"Cornwall Care Homes",
    "wof:placetype":"venue"
},
  "geometry": {"coordinates":[-5.287259,50.219456],"type":"Point"}
}