{
  "type": "Feature",
  "properties": {
    "addr:full":"15 Norman St Dover Kent CT17 9RS",
    "addr:housenumber":"15",
    "addr:postcode":"ct17 9rs",
    "addr:street":"Norman St",
    "iso:country":"GB",
    "sg:address":"15 Norman St",
    "sg:city":"Dover",
    "sg:classifiers":[
        {
            "category":"Building & Trades",
            "subcategory":"Construction",
            "type":"Services"
        }
    ],
    "sg:phone":"+44 1304 213337",
    "sg:postcode":"CT17 9RS",
    "sg:province":"Kent",
    "sg:tags":[
        "builder"
    ],
    "wof:name":"Re-Dec",
    "wof:placetype":"venue"
},
  "geometry": {"coordinates":[1.3086190224,51.127040863],"type":"Point"}
}