{
  "type": "Feature",
  "properties": {
    "iso:country":"GB",
    "sg:address":"Ironbridge Medical Practice, Trinity Hall, Dale Rd",
    "sg:city":"Telford",
    "sg:classifiers":[
        {
            "category":"Health Services",
            "subcategory":"Doctor",
            "type":"Services"
        }
    ],
    "sg:phone":"+44 1952 432568",
    "sg:postcode":"TF8 7DT",
    "sg:province":"Shropshire",
    "sg:tags":[
        "practitioners"
    ],
    "wof:name":"Elizabeth Rathbone",
    "wof:placetype":"venue"
},
  "geometry": {"coordinates":[-2.4753599167,52.6251754761],"type":"Point"}
}