{
  "type": "Feature",
  "properties": {
    "addr:full":"25 Blackwellgate Darlington Durham DL1 5HH",
    "addr:housenumber":"25",
    "addr:postcode":"dl1 5hh",
    "addr:street":"Blackwellgate Darlington",
    "iso:country":"GB",
    "sg:address":"25 Blackwellgate",
    "sg:city":"Darlington",
    "sg:classifiers":[
        {
            "category":"Shopping",
            "subcategory":"Musical Instruments",
            "type":"Retail Goods"
        }
    ],
    "sg:phone":"+44 16422042",
    "sg:postcode":"DL1 5HH",
    "sg:province":"Durham",
    "wof:name":"G.A.Williams",
    "wof:placetype":"venue"
},
  "geometry": {"coordinates":[-1.5559819937,54.5239372253],"type":"Point"}
}