{
  "type": "Feature",
  "properties": {
    "iso:country":"GB",
    "sg:address":"Greenmoor Hill Farm, Woodcote",
    "sg:city":"Reading",
    "sg:classifiers":[
        {
            "category":"Professional",
            "subcategory":"Business Services",
            "type":"Services"
        }
    ],
    "sg:postcode":"RG8 0RW",
    "sg:province":"Berkshire",
    "sg:tags":[
        "hospitality",
        "corporate"
    ],
    "wof:name":"Focus Events",
    "wof:placetype":"venue"
},
  "geometry": {"coordinates":[-1.0648399591,51.5318031311],"type":"Point"}
}