{
  "type": "Feature",
  "properties": {
    "iso:country":"GB",
    "sg:address":"Orchard House, Misburne Vale, Chalfont St Peter",
    "sg:city":"Gerrards Cross",
    "sg:classifiers":[
        {
            "category":"Manufacturing",
            "subcategory":"Textiles",
            "type":"Manufacturing & Wholesale Goods"
        }
    ],
    "sg:postcode":"SL9 0NN",
    "sg:province":"Buckinghamshire",
    "sg:tags":[
        "merchant",
        "agent"
    ],
    "wof:name":"Bell Textiles Ltd.",
    "wof:placetype":"venue"
},
  "geometry": {"coordinates":[-0.55725,51.620232],"type":"Point"}
}