{
  "type": "Feature",
  "properties": {
    "iso:country":"GB",
    "sg:address":"9 High Street, Wollaston",
    "sg:city":"Stourbridge",
    "sg:classifiers":[
        {
            "category":"Building & Trades",
            "subcategory":"Plumbing",
            "type":"Services"
        }
    ],
    "sg:phone":"+44 1384 374237",
    "sg:postcode":"DY8 4NH",
    "sg:province":"Staffordshire",
    "sg:tags":[
        "heating"
    ],
    "wof:name":"Audnam Plumbing & Heating Co. Ltd.",
    "wof:placetype":"venue"
},
  "geometry": {"coordinates":[-2.154356,52.469879],"type":"Point"}
}