{
  "type": "Feature",
  "properties": {
    "iso:country":"GB",
    "sg:address":"18 Lake Road",
    "sg:city":"Windermere",
    "sg:classifiers":[
        {
            "category":"Manufacturing",
            "subcategory":"Textiles",
            "type":"Manufacturing & Wholesale Goods"
        },
        {
            "category":"Shopping",
            "subcategory":"Crafts & Fabrics",
            "type":"Retail Goods"
        }
    ],
    "sg:phone":"+44 15394 46959",
    "sg:postcode":"LA23 3AP",
    "sg:province":"Cumbria",
    "sg:tags":[
        "shop",
        "linen",
        "made-up"
    ],
    "wof:name":"Spensley's Household Textiles",
    "wof:placetype":"venue"
},
  "geometry": {"coordinates":[-2.9159240723,54.3670349121],"type":"Point"}
}