{
  "type": "Feature",
  "properties": {
    "iso:country":"GB",
    "sg:address":"56 Fore Street",
    "sg:city":"Totnes",
    "sg:classifiers":[
        {
            "category":"Restaurant",
            "type":"Food & Drink"
        }
    ],
    "sg:phone":"+44 1803 863186",
    "sg:postcode":"TQ9 5RU",
    "sg:province":"Devon",
    "wof:name":"Christopher & Joanne Moon",
    "wof:placetype":"venue"
},
  "geometry": {"coordinates":[-3.686129,50.431149],"type":"Point"}
}