{
  "type": "Feature",
  "properties": {
    "addr:full":"23 Craven Common, Uffington Faringdon Oxfordshire SN7 7RN",
    "addr:housenumber":"23",
    "addr:postcode":"sn7 7rn",
    "addr:street":"Craven Common",
    "iso:country":"GB",
    "sg:address":"23 Craven Common, Uffington",
    "sg:city":"Faringdon",
    "sg:classifiers":[
        {
            "category":"Professional",
            "subcategory":"Engineering",
            "type":"Services"
        }
    ],
    "sg:postcode":"SN7 7RN",
    "sg:province":"Oxfordshire",
    "sg:tags":[
        "contractor",
        "electrical",
        "engineer"
    ],
    "wof:name":"Robin Haines",
    "wof:placetype":"venue"
},
  "geometry": {"coordinates":[-1.5557299852,51.6016998291],"type":"Point"}
}