{
  "type": "Feature",
  "properties": {
    "addr:full":"76 Church St Hartlepool Durham TS24 7DN",
    "addr:housenumber":"76",
    "addr:postcode":"ts24 7dn",
    "addr:street":"Church St",
    "iso:country":"GB",
    "sg:address":"76 Church St",
    "sg:city":"Hartlepool",
    "sg:classifiers":[
        {
            "category":"Organizations",
            "subcategory":"Non-profit Organization",
            "type":"Services"
        }
    ],
    "sg:phone":"+44 1429 424222",
    "sg:postcode":"TS24 7DN",
    "sg:province":"Durham",
    "sg:tags":[
        "organisation",
        "voluntary",
        "charity"
    ],
    "wof:name":"Barnardo's",
    "wof:placetype":"venue"
},
  "geometry": {"coordinates":[-1.2100989819,54.6844711304],"type":"Point"}
}