{
  "type": "Feature",
  "properties": {
    "iso:country":"GB",
    "sg:address":"Whiteway Hill Garage, Woodmancote",
    "sg:city":"Dursley",
    "sg:classifiers":[
        {
            "category":"Building & Trades",
            "subcategory":"Landscaping Services",
            "type":"Services"
        }
    ],
    "sg:phone":"+44 1453 548036",
    "sg:postcode":"GL11 4AJ",
    "sg:province":"Gloucestershire",
    "sg:tags":[
        "horticultural",
        "consultant"
    ],
    "wof:name":"Broadwell Industrial Services",
    "wof:placetype":"venue"
},
  "geometry": {"coordinates":[-2.3468470573,51.6739883423],"type":"Point"}
}