{
  "type": "Feature",
  "properties": {
    "addr:full":"113 Metchley Lane, Harborne Birmingham West Midlands B17 0JH",
    "addr:housenumber":"113",
    "addr:postcode":"b17 0jh",
    "addr:street":"Metchley Lane",
    "iso:country":"GB",
    "sg:address":"113 Metchley Lane, Harborne",
    "sg:city":"Birmingham",
    "sg:classifiers":[
        {
            "category":"Building & Trades",
            "subcategory":"Construction",
            "type":"Services"
        }
    ],
    "sg:postcode":"B17 0JH",
    "sg:province":"West Midlands",
    "sg:tags":[
        "decorator",
        "painter"
    ],
    "wof:name":"B D L Ltd.",
    "wof:placetype":"venue"
},
  "geometry": {"coordinates":[-1.9460940361,52.4527702332],"type":"Point"}
}