{
  "type": "Feature",
  "properties": {
    "iso:country":"GB",
    "sg:address":"Argraig",
    "sg:city":"Cemaes Bay",
    "sg:classifiers":[
        {
            "category":"Building & Trades",
            "subcategory":"Construction",
            "type":"Services"
        }
    ],
    "sg:phone":"+44 1407 710740",
    "sg:postcode":"LL67 0HB",
    "sg:province":"Isle of Anglesey",
    "sg:tags":[
        "builder"
    ],
    "wof:name":"Ifor A Jones",
    "wof:placetype":"venue"
},
  "geometry": {"coordinates":[-4.4518017769,53.4122467041],"type":"Point"}
}