{
  "type": "Feature",
  "properties": {
    "addr:full":"The Nook Ivybridge Devon PL21 0PF",
    "addr:postcode":"pl21 0pf",
    "iso:country":"GB",
    "sg:address":"The Nook",
    "sg:city":"Ivybridge",
    "sg:classifiers":[
        {
            "category":"Wholesale",
            "subcategory":"Poultry",
            "type":"Manufacturing & Wholesale Goods"
        }
    ],
    "sg:phone":"+44 1364 72132",
    "sg:postcode":"PL21 0PF",
    "sg:province":"Devon",
    "sg:tags":[
        "bird"
    ],
    "wof:name":"Bird Farm",
    "wof:placetype":"venue"
},
  "geometry": {"coordinates":[-3.87338,50.400887],"type":"Point"}
}