{
  "type": "Feature",
  "properties": {
    "iso:country":"GB",
    "sg:address":"59 Heath Road",
    "sg:city":"Glossop",
    "sg:classifiers":[
        {
            "category":"Shopping",
            "subcategory":"Discount & Variety Stores",
            "type":"Retail Goods"
        }
    ],
    "sg:phone":"+44 1457 865182",
    "sg:postcode":"SK13 7BA",
    "sg:province":"Derbyshire",
    "sg:tags":[
        "cleaning",
        "supply"
    ],
    "wof:name":"Sovereign Products Ltd.",
    "wof:placetype":"venue"
},
  "geometry": {"coordinates":[-1.948187,53.449833],"type":"Point"}
}