{
  "type": "Feature",
  "properties": {
    "addr:full":"48 Darnley Street Glasgow Glasgow City G41 2SE",
    "addr:housenumber":"48",
    "addr:postcode":"g41 2se",
    "addr:street":"Darnley Street",
    "iso:country":"GB",
    "sg:address":"48 Darnley Street",
    "sg:city":"Glasgow",
    "sg:classifiers":[
        {
            "category":"Building & Trades",
            "subcategory":"Construction",
            "type":"Services"
        }
    ],
    "sg:phone":"+44 141 420 3277",
    "sg:postcode":"G41 2SE",
    "sg:province":"Glasgow City",
    "sg:tags":[
        "builder"
    ],
    "wof:name":"Sutton Services International Ltd.",
    "wof:placetype":"venue"
},
  "geometry": {"coordinates":[-4.269251,55.842503],"type":"Point"}
}