{
  "type": "Feature",
  "properties": {
    "addr:full":"Elm Road Wisbech Cambridgeshire PE13 2TB",
    "addr:postcode":"pe13 2tb",
    "addr:street":"Elm Road",
    "iso:country":"GB",
    "sg:address":"Elm Road",
    "sg:city":"Wisbech",
    "sg:classifiers":[
        {
            "category":"Retail",
            "subcategory":"Emissions Testing",
            "type":"Services"
        },
        {
            "category":"Professional",
            "subcategory":"Testing Lab",
            "type":"Services"
        }
    ],
    "sg:phone":"+44 7774 763528",
    "sg:postcode":"PE13 2TB",
    "sg:province":"Cambridgeshire",
    "sg:tags":[
        "mot"
    ],
    "wof:name":"The Test & Service Centre",
    "wof:placetype":"venue"
},
  "geometry": {"coordinates":[0.165205,52.659828],"type":"Point"}
}