{
  "type": "Feature",
  "properties": {
    "addr:full":"26 Stodman Street Newark Nottinghamshire NG24 1AW",
    "addr:housenumber":"26",
    "addr:postcode":"ng24 1aw",
    "addr:street":"Stodman Street",
    "iso:country":"GB",
    "sg:address":"26 Stodman Street",
    "sg:city":"Newark",
    "sg:classifiers":[
        {
            "category":"Organizations",
            "subcategory":"Non-profit Organization",
            "type":"Services"
        }
    ],
    "sg:phone":"+44 1636 605047",
    "sg:postcode":"NG24 1AW",
    "sg:province":"Nottinghamshire",
    "sg:tags":[
        "organisation",
        "voluntary",
        "charity"
    ],
    "wof:name":"The Cancer Research Campaign",
    "wof:placetype":"venue"
},
  "geometry": {"coordinates":[-0.8115810156,53.0761947632],"type":"Point"}
}