{
  "type": "Feature",
  "properties": {
    "iso:country":"GB",
    "sg:address":"604 Dumbarton Road",
    "sg:city":"Glasgow",
    "sg:classifiers":[
        {
            "category":"Food & Beverages",
            "subcategory":"Fruits & Vegetables",
            "type":"Retail Goods"
        }
    ],
    "sg:postcode":"G11 6RJ",
    "sg:province":"Glasgow City",
    "sg:tags":[
        "greengrocer"
    ],
    "wof:name":"Fine Fruits",
    "wof:placetype":"venue"
},
  "geometry": {"coordinates":[-4.3169522285,55.870929718],"type":"Point"}
}