{
  "type": "Feature",
  "properties": {
    "addr:full":"32-34 St Leonard Street, Bromley By Bow London Greater London E3 3BT",
    "addr:housenumber":"32-34",
    "addr:postcode":"e3 3bt",
    "addr:street":"St Leonard Street",
    "iso:country":"GB",
    "sg:address":"32-34 St Leonard Street, Bromley By Bow",
    "sg:city":"London",
    "sg:classifiers":[
        {
            "category":"Home & Garden",
            "subcategory":"Furniture",
            "type":"Retail Goods"
        }
    ],
    "sg:postcode":"E3 3BT",
    "sg:province":"Greater London",
    "wof:name":"The Furniture Mill",
    "wof:placetype":"venue"
},
  "geometry": {"coordinates":[-0.0118699996,51.5257797241],"type":"Point"}
}