{
  "type": "Feature",
  "properties": {
    "addr:full":"1 North Sunderland Industrial Estate Seahouses Northumberland NE68 7RQ",
    "addr:housenumber":"1",
    "addr:postcode":"ne68 7rq",
    "addr:street":"North Sunderland Industrial Estate",
    "iso:country":"GB",
    "sg:address":"1 North Sunderland Industrial Estate",
    "sg:city":"Seahouses",
    "sg:classifiers":[
        {
            "category":"Retail",
            "subcategory":"Auto Repair",
            "type":"Services"
        }
    ],
    "sg:phone":"+44 1665 720431",
    "sg:postcode":"NE68 7RQ",
    "sg:province":"Northumberland",
    "sg:tags":[
        "modification",
        "garage"
    ],
    "wof:name":"B Gregory",
    "wof:placetype":"venue"
},
  "geometry": {"coordinates":[-1.6541240215,55.5811729431],"type":"Point"}
}