{
  "type": "Feature",
  "properties": {
    "addr:full":"Neville St Leeds West Yorkshire LS1 4BX",
    "addr:postcode":"ls1 4bx",
    "addr:street":"Neville St",
    "iso:country":"GB",
    "sg:address":"Neville St",
    "sg:city":"Leeds",
    "sg:classifiers":[
        {
            "category":"Restaurant",
            "type":"Food & Drink"
        }
    ],
    "sg:phone":"+44 113 243 1441",
    "sg:postcode":"LS1 4BX",
    "sg:province":"West Yorkshire",
    "wof:name":"Stakis Regency Club Restaurant",
    "wof:placetype":"venue"
},
  "geometry": {"coordinates":[-1.546945,53.792896],"type":"Point"}
}