{
  "type": "Feature",
  "properties": {
    "addr:full":"Park Rd Newport East Riding of Yorkshire NP1 6BJ",
    "addr:postcode":"np1 6bj",
    "addr:street":"Park Rd",
    "iso:country":"GB",
    "sg:address":"Park Rd",
    "sg:city":"Newport",
    "sg:classifiers":[
        {
            "category":"Professional",
            "subcategory":"Lawyer & Legal Services",
            "type":"Services"
        }
    ],
    "sg:phone":"+44 1633 614731",
    "sg:postcode":"NP1 6BJ",
    "sg:province":"East Riding of Yorkshire",
    "sg:tags":[
        "advice",
        "counselling"
    ],
    "wof:name":"Citizens Advice Bureau",
    "wof:placetype":"venue"
},
  "geometry": {"coordinates":[-3.0130729675,51.5821151733],"type":"Point"}
}