{
  "type": "Feature",
  "properties": {
    "addr:full":"3 Greentiles Tadworth Surrey KT20 7JE",
    "addr:housenumber":"3",
    "addr:postcode":"kt20 7je",
    "addr:street":"Greentiles Tadworth",
    "iso:country":"GB",
    "sg:address":"3 Greentiles",
    "sg:city":"Tadworth",
    "sg:classifiers":[
        {
            "category":"Shopping",
            "subcategory":"Department Store",
            "type":"Retail Goods"
        },
        {
            "category":"Food & Beverages",
            "subcategory":"Groceries & Convenience Stores",
            "type":"Retail Goods"
        }
    ],
    "sg:phone":"+44 1737 842127",
    "sg:postcode":"KT20 7JE",
    "sg:province":"Surrey",
    "wof:name":"Hilltop Stores",
    "wof:placetype":"venue"
},
  "geometry": {"coordinates":[-0.250214,51.273731],"type":"Point"}
}