{
  "type": "Feature",
  "properties": {
    "iso:country":"GB",
    "sg:address":"36 Goodwood Ave",
    "sg:city":"Brentwood",
    "sg:classifiers":[
        {
            "category":"Building & Trades",
            "subcategory":"Construction",
            "type":"Services"
        }
    ],
    "sg:postcode":"CM13 1PY",
    "sg:province":"Essex",
    "sg:tags":[
        "builder"
    ],
    "wof:name":"Moore,Robin,",
    "wof:placetype":"venue"
},
  "geometry": {"coordinates":[0.361508,51.633335],"type":"Point"}
}