{
  "type": "Feature",
  "properties": {
    "addr:full":"37a Monkton Pembroke Pembrokeshire SA71 4LS",
    "addr:housenumber":"37a",
    "addr:postcode":"sa71 4ls",
    "addr:street":"Monkton",
    "iso:country":"GB",
    "sg:address":"37a Monkton",
    "sg:city":"Pembroke",
    "sg:classifiers":[
        {
            "category":"Food & Beverages",
            "subcategory":"Meat & Fish",
            "type":"Retail Goods"
        }
    ],
    "sg:phone":"+44 1646 682739",
    "sg:postcode":"SA71 4LS",
    "sg:province":"Pembrokeshire",
    "sg:tags":[
        "butcher"
    ],
    "wof:name":"Monkton Meats",
    "wof:placetype":"venue"
},
  "geometry": {"coordinates":[-4.925715,51.674599],"type":"Point"}
}