{
  "type": "Feature",
  "properties": {
    "iso:country":"GB",
    "sg:address":"Little Well Farm, Fleets Lane, Tyler Hill",
    "sg:city":"Canterbury",
    "sg:classifiers":[
        {
            "category":"Wholesale",
            "subcategory":"Fruits & Vegetables",
            "type":"Manufacturing & Wholesale Goods"
        }
    ],
    "sg:phone":"+44 1227 471352",
    "sg:postcode":"CT2 9NA",
    "sg:province":"Kent",
    "wof:name":"G W & C E McCabe",
    "wof:placetype":"venue"
},
  "geometry": {"coordinates":[1.06993,51.306118],"type":"Point"}
}