{
  "type": "Feature",
  "properties": {
    "iso:country":"GB",
    "sg:address":"8 Kings Rd",
    "sg:city":"Sutton Coldfield",
    "sg:classifiers":[
        {
            "category":"Autos & Motor Vehicles",
            "subcategory":"Automobile Sales",
            "type":"Retail Goods"
        }
    ],
    "sg:phone":"+44 121 355 0100",
    "sg:postcode":"B73 5AF",
    "sg:province":"West Midlands",
    "sg:tags":[
        "car"
    ],
    "wof:name":"John S Leek International Cars",
    "wof:placetype":"venue"
},
  "geometry": {"coordinates":[-1.860201,52.548565],"type":"Point"}
}