{
  "type": "Feature",
  "properties": {
    "addr:full":"32 Reading Road South Fleet Hampshire GU52 7QL",
    "addr:housenumber":"32",
    "addr:postcode":"gu52 7ql",
    "addr:street":"Reading Road South Fleet",
    "iso:country":"GB",
    "sg:address":"32 Reading Road South",
    "sg:city":"Fleet",
    "sg:classifiers":[
        {
            "category":"Sports & Exercise",
            "subcategory":"Skate Park",
            "type":"Entertainment"
        }
    ],
    "sg:phone":"+44 1252 622333",
    "sg:postcode":"GU52 7QL",
    "sg:province":"Hampshire",
    "sg:tags":[
        "equipment",
        "grinding"
    ],
    "wof:name":"S E C O Engineering Co. Ltd.",
    "wof:placetype":"venue"
},
  "geometry": {"coordinates":[-0.8409489989,51.2751083374],"type":"Point"}
}