{
  "type": "Feature",
  "properties": {
    "addr:full":"Warden, 517 Bordesley Green Birmingham West Midlands B9 5XH",
    "addr:housenumber":"517",
    "addr:postcode":"b9 5xh",
    "addr:street":"Warden;Bordesley Green",
    "iso:country":"GB",
    "sg:address":"Warden, 517 Bordesley Green",
    "sg:city":"Birmingham",
    "sg:classifiers":[
        {
            "category":"Real Estate",
            "subcategory":"Real Estate Agent",
            "type":"Services"
        }
    ],
    "sg:phone":"+44 121 772 2901",
    "sg:postcode":"B9 5XH",
    "sg:province":"West Midlands",
    "wof:name":"Lakeland Street Sheltered Housing",
    "wof:placetype":"venue"
},
  "geometry": {"coordinates":[-1.84129,52.478531],"type":"Point"}
}