{
  "type": "Feature",
  "properties": {
    "addr:full":"Unit 4a Shifnal Indstl Est, Lamledge La Shifnal Shropshire TF11 8SD",
    "addr:housenumber":"unit 4a",
    "addr:postcode":"tf11 8sd",
    "addr:street":"Indstl Est;La Shifnal Shropshire",
    "iso:country":"GB",
    "sg:address":"Unit 4a Shifnal Indstl Est, Lamledge La",
    "sg:city":"Shifnal",
    "sg:classifiers":[
        {
            "category":"Building & Trades",
            "subcategory":"Construction",
            "type":"Services"
        }
    ],
    "sg:postcode":"TF11 8SD",
    "sg:province":"Shropshire",
    "sg:tags":[
        "joiner",
        "carpenter"
    ],
    "wof:name":"Onions,William Thomas,",
    "wof:placetype":"venue"
},
  "geometry": {"coordinates":[-2.3727788925,52.6654853821],"type":"Point"}
}