{
  "type": "Feature",
  "properties": {
    "iso:country":"GB",
    "sg:address":"Unit 4, Queen Street",
    "sg:city":"Walsall",
    "sg:classifiers":[
        {
            "category":"Building & Trades",
            "subcategory":"Cleaning & Sanitation",
            "type":"Services"
        },
        {
            "category":"Building & Trades",
            "subcategory":"Equipment Rental",
            "type":"Services"
        }
    ],
    "sg:phone":"+44 1922 634965",
    "sg:postcode":"WS2 9NU",
    "sg:province":"West Midlands",
    "sg:tags":[
        "hire",
        "commercial",
        "centre"
    ],
    "wof:name":"Relko Cleaning & Support Services Ltd.",
    "wof:placetype":"venue"
},
  "geometry": {"coordinates":[-1.9913339615,52.5818901062],"type":"Point"}
}