{
  "type": "Feature",
  "properties": {
    "addr:full":"21 Summerfields, St Stephens Saltash Cornwall PL12 4AB",
    "addr:housenumber":"21",
    "addr:postcode":"pl12 4ab",
    "addr:street":"Summerfields St Stephens",
    "iso:country":"GB",
    "sg:address":"21 Summerfields, St Stephens",
    "sg:city":"Saltash",
    "sg:classifiers":[
        {
            "category":"Professional",
            "subcategory":"Accounting & Tax Preparation",
            "type":"Services"
        }
    ],
    "sg:phone":"+44 1752 843285",
    "sg:postcode":"PL12 4AB",
    "sg:province":"Cornwall",
    "sg:tags":[
        "accountant"
    ],
    "wof:name":"Bills Books",
    "wof:placetype":"venue"
},
  "geometry": {"coordinates":[-4.230686,50.404091],"type":"Point"}
}