{
  "type": "Feature",
  "properties": {
    "addr:full":"Glandwr Street Abertillery Blaenau Gwent NP13 2AQ",
    "addr:postcode":"np13 2aq",
    "addr:street":"Glandwr Street;Gwent",
    "iso:country":"GB",
    "sg:address":"Glandwr Street",
    "sg:city":"Abertillery",
    "sg:classifiers":[
        {
            "category":"Retail",
            "subcategory":"Auto Repair",
            "type":"Services"
        }
    ],
    "sg:phone":"+44 1495 321948",
    "sg:postcode":"NP13 2AQ",
    "sg:province":"Blaenau Gwent",
    "sg:tags":[
        "modification",
        "garage"
    ],
    "wof:name":"Flyover Garage",
    "wof:placetype":"venue"
},
  "geometry": {"coordinates":[-3.145498991,51.7044944763],"type":"Point"}
}