{
  "type": "Feature",
  "properties": {
    "addr:full":"252 Weston Road Stoke-on-trent Staffordshire ST3 6EE",
    "addr:housenumber":"252",
    "addr:postcode":"st3 6ee",
    "addr:street":"Weston Road",
    "iso:country":"GB",
    "sg:address":"252 Weston Road",
    "sg:city":"Stoke-on-trent",
    "sg:classifiers":[
        {
            "category":"Building & Trades",
            "subcategory":"Construction",
            "type":"Services"
        }
    ],
    "sg:phone":"+44 1782 322807",
    "sg:postcode":"ST3 6EE",
    "sg:province":"Staffordshire",
    "sg:tags":[
        "dry",
        "lining",
        "plasterers",
        "screeders"
    ],
    "wof:name":"D V Rowley",
    "wof:placetype":"venue"
},
  "geometry": {"coordinates":[-2.1011450291,52.9857826233],"type":"Point"}
}