{
  "type": "Feature",
  "properties": {
    "addr:full":"Unit 6, Mercia Way, Bells Close Ind Est Newcastle Upon Tyne Northumberland NE15 6UG",
    "addr:housenumber":"unit 6",
    "addr:postcode":"ne15 6ug",
    "addr:street":"Mercia Way Bells Close;Est",
    "iso:country":"GB",
    "sg:address":"Unit 6, Mercia Way, Bells Close Ind Est",
    "sg:city":"Newcastle Upon Tyne",
    "sg:classifiers":[
        {
            "category":"Manufacturing",
            "subcategory":"Textiles",
            "type":"Manufacturing & Wholesale Goods"
        }
    ],
    "sg:phone":"+44 191 267 9419",
    "sg:postcode":"NE15 6UG",
    "sg:province":"Northumberland",
    "sg:tags":[
        "merchant",
        "agent"
    ],
    "wof:name":"Open Cast Aggregates Ltd",
    "wof:placetype":"venue"
},
  "geometry": {"coordinates":[-1.6997499466,54.9735717773],"type":"Point"}
}