{
  "type": "Feature",
  "properties": {
    "addr:full":"56-62 Railway Terr Rugby Warwickshire CV21 3EY",
    "addr:housenumber":"56-62",
    "addr:postcode":"cv21 3ey",
    "addr:street":"Railway Terr",
    "iso:country":"GB",
    "sg:address":"56-62 Railway Terr",
    "sg:city":"Rugby",
    "sg:classifiers":[
        {
            "category":"Autos & Motor Vehicles",
            "subcategory":"Auto Supplies",
            "type":"Retail Goods"
        }
    ],
    "sg:phone":"+44 1788 542502",
    "sg:postcode":"CV21 3EY",
    "sg:province":"Warwickshire",
    "sg:tags":[
        "tyre"
    ],
    "wof:name":"Central Tyre",
    "wof:placetype":"venue"
},
  "geometry": {"coordinates":[-1.256816,52.373711],"type":"Point"}
}