{
  "type": "Feature",
  "properties": {
    "addr:full":"Lindbergh Road Wallington Surrey SM6 9HB",
    "addr:postcode":"sm6 9hb",
    "addr:street":"Lindbergh Road",
    "iso:country":"GB",
    "sg:address":"Lindbergh Road",
    "sg:city":"Wallington",
    "sg:classifiers":[
        {
            "category":"Education",
            "subcategory":"Preschool",
            "type":"Public Place"
        },
        {
            "category":"Government",
            "subcategory":"Office",
            "type":"Public Place"
        }
    ],
    "sg:phone":"+44 20 8770 5000",
    "sg:postcode":"SM6 9HB",
    "sg:province":"Surrey",
    "sg:tags":[
        "local",
        "pre-school",
        "playgroups"
    ],
    "wof:name":"Lindbergh Play Centre",
    "wof:placetype":"venue"
},
  "geometry": {"coordinates":[-0.1498979926,51.3601226807],"type":"Point"}
}