{
  "type": "Feature",
  "properties": {
    "iso:country":"GB",
    "sg:address":"41 Stanhope Rd",
    "sg:city":"Deal",
    "sg:classifiers":[
        {
            "category":"Social Services",
            "subcategory":"Retirement Home",
            "type":"Services"
        }
    ],
    "sg:postcode":"CT14 6AD",
    "sg:province":"Kent",
    "sg:tags":[
        "residential",
        "care"
    ],
    "wof:name":"Clarmar",
    "wof:placetype":"venue"
},
  "geometry": {"coordinates":[1.400748,51.224316],"type":"Point"}
}