{
  "type": "Feature",
  "properties": {
    "addr:full":"Royal Farm, Kenwyn Truro Cornwall TR4 9BY",
    "addr:housenumber":"kenwyn",
    "addr:postcode":"tr4 9by",
    "iso:country":"GB",
    "sg:address":"Royal Farm, Kenwyn",
    "sg:city":"Truro",
    "sg:classifiers":[
        {
            "category":"Farming",
            "subcategory":"Farm",
            "type":"Manufacturing & Wholesale Goods"
        }
    ],
    "sg:postcode":"TR4 9BY",
    "sg:province":"Cornwall",
    "sg:tags":[
        "mixed",
        "crop"
    ],
    "wof:name":"Roger V Flexman",
    "wof:placetype":"venue"
},
  "geometry": {"coordinates":[-5.07342,50.280479],"type":"Point"}
}