{
  "type": "Feature",
  "properties": {
    "addr:full":"23 Chestnut Ave Esher Surrey KT10 8JF",
    "addr:housenumber":"23",
    "addr:postcode":"kt10 8jf",
    "addr:street":"Chestnut Ave",
    "iso:country":"GB",
    "sg:address":"23 Chestnut Ave",
    "sg:city":"Esher",
    "sg:classifiers":[
        {
            "category":"Professional",
            "subcategory":"Business Services",
            "type":"Services"
        }
    ],
    "sg:postcode":"KT10 8JF",
    "sg:province":"Surrey",
    "sg:tags":[
        "information"
    ],
    "wof:name":"Holistic Creations Network Ltd",
    "wof:placetype":"venue"
},
  "geometry": {"coordinates":[-0.3500939906,51.3858566284],"type":"Point"}
}