{
  "type": "Feature",
  "properties": {
    "iso:country":"GB",
    "sg:address":"5 Pratt Avenue",
    "sg:city":"Peterborough",
    "sg:classifiers":[
        {
            "category":"Building & Trades",
            "subcategory":"Construction",
            "type":"Services"
        },
        {
            "category":"Home & Garden",
            "subcategory":"Carpets & Floor Coverings",
            "type":"Retail Goods"
        }
    ],
    "sg:phone":"+44 1733 570059",
    "sg:postcode":"PE4 7XN",
    "sg:province":"Cambridgeshire",
    "sg:tags":[
        "carpets",
        "tiling",
        "rug",
        "matting",
        "contractor"
    ],
    "wof:name":"D T Lamb",
    "wof:placetype":"venue"
},
  "geometry": {"coordinates":[-0.24809,52.608971],"type":"Point"}
}