{
  "type": "Feature",
  "properties": {
    "addr:full":"2 Mill Street Melton Mowbray Leicestershire LE13 1AY",
    "addr:housenumber":"2",
    "addr:postcode":"le13 1ay",
    "addr:street":"Mill Street",
    "iso:country":"GB",
    "sg:address":"2 Mill Street",
    "sg:city":"Melton Mowbray",
    "sg:classifiers":[
        {
            "category":"Utilities",
            "subcategory":"Refuse",
            "type":"Services"
        }
    ],
    "sg:phone":"+44 1664 411521",
    "sg:postcode":"LE13 1AY",
    "sg:province":"Leicestershire",
    "sg:tags":[
        "disposal",
        "waste",
        "retail"
    ],
    "wof:name":"Wrg Waste Services Ltd.",
    "wof:placetype":"venue"
},
  "geometry": {"coordinates":[-0.8825839758,52.7626266479],"type":"Point"}
}