{
  "type": "Feature",
  "properties": {
    "iso:country":"GB",
    "sg:address":"Cannock Shopping, Centre Market Hall Street",
    "sg:city":"Cannock",
    "sg:classifiers":[
        {
            "category":"Food & Beverages",
            "subcategory":"Bakery",
            "type":"Retail Goods"
        }
    ],
    "sg:phone":"+44 1543 578511",
    "sg:postcode":"WS11 1EB",
    "sg:province":"Staffordshire",
    "sg:tags":[
        "baker"
    ],
    "wof:name":"Tennants Craft Bakery",
    "wof:placetype":"venue"
},
  "geometry": {"coordinates":[-2.033145,52.690952],"type":"Point"}
}