{
  "type": "Feature",
  "properties": {
    "iso:country":"GB",
    "sg:address":"178 Bushey Mill Lane",
    "sg:city":"Watford",
    "sg:classifiers":[
        {
            "category":"Shopping",
            "subcategory":"News",
            "type":"Retail Goods"
        }
    ],
    "sg:postcode":"WD24 7PB",
    "sg:province":"Hertfordshire",
    "sg:tags":[
        "newsagent"
    ],
    "wof:name":"D & D Newsagents",
    "wof:placetype":"venue"
},
  "geometry": {"coordinates":[-0.3863300085,51.6736030579],"type":"Point"}
}