{
  "type": "Feature",
  "properties": {
    "iso:country":"GB",
    "sg:address":"7 Eastfields Road, School Aycliffe",
    "sg:city":"Newton Aycliffe",
    "sg:classifiers":[
        {
            "category":"Government",
            "subcategory":"Post Office",
            "type":"Public Place"
        }
    ],
    "sg:postcode":"DL5 6QH",
    "sg:province":"Durham",
    "sg:tags":[
        "print",
        "typesetter"
    ],
    "wof:name":"First Impressions",
    "wof:placetype":"venue"
},
  "geometry": {"coordinates":[-1.59994,54.608204],"type":"Point"}
}