{
  "type": "Feature",
  "properties": {
    "iso:country":"GB",
    "sg:address":"325 Benton Road",
    "sg:city":"Newcastle-upon-tyne",
    "sg:classifiers":[
        {
            "category":"Autos & Motor Vehicles",
            "subcategory":"Automobile Sales",
            "type":"Retail Goods"
        }
    ],
    "sg:phone":"+44 191 266 3543",
    "sg:postcode":"NE7 7EE",
    "sg:province":"Tyne and Wear",
    "sg:tags":[
        "car"
    ],
    "wof:name":"Benton Car Sales Ltd.",
    "wof:placetype":"venue"
},
  "geometry": {"coordinates":[-1.578615,55.00758],"type":"Point"}
}