{
  "type": "Feature",
  "properties": {
    "iso:country":"GB",
    "sg:address":"298 Avery Hill Road",
    "sg:city":"London",
    "sg:classifiers":[
        {
            "category":"Building & Trades",
            "subcategory":"Construction",
            "type":"Services"
        }
    ],
    "sg:phone":"+44 20 8859 4565",
    "sg:postcode":"SE9 2JN",
    "sg:province":"Greater London",
    "sg:tags":[
        "builder"
    ],
    "wof:name":"Cleary Builders",
    "wof:placetype":"venue"
},
  "geometry": {"coordinates":[0.081487,51.4479217529],"type":"Point"}
}