{
  "type": "Feature",
  "properties": {
    "iso:country":"GB",
    "sg:address":"14 Jews Lane, Upper Gornal",
    "sg:city":"Dudley",
    "sg:classifiers":[
        {
            "category":"Food & Beverages",
            "subcategory":"Meat & Fish",
            "type":"Retail Goods"
        }
    ],
    "sg:postcode":"DY3 2AB",
    "sg:province":"Staffordshire",
    "sg:tags":[
        "chip"
    ],
    "wof:name":"Charlies Fish & Chips",
    "wof:placetype":"venue"
},
  "geometry": {"coordinates":[-2.113722,52.524853],"type":"Point"}
}