{
  "type": "Feature",
  "properties": {
    "iso:country":"GB",
    "sg:address":"3 Aspen Gro, Redwood Park, Chase Terrace",
    "sg:city":"Walsall",
    "sg:classifiers":[
        {
            "category":"Professional",
            "subcategory":"Engineering",
            "type":"Services"
        }
    ],
    "sg:phone":"+44 1543 675305",
    "sg:postcode":"WS7 8AT",
    "sg:province":"Staffordshire",
    "sg:tags":[
        "contractor",
        "electrical",
        "engineer"
    ],
    "wof:name":"A P H Electrical",
    "wof:placetype":"venue"
},
  "geometry": {"coordinates":[-1.92838,52.685299],"type":"Point"}
}