{
  "type": "Feature",
  "properties": {
    "addr:full":"20-21 Arcadia Avenue London Greater London N3 2JU",
    "addr:housenumber":"20-21",
    "addr:postcode":"n3 2ju",
    "addr:street":"Arcadia Avenue",
    "iso:country":"GB",
    "sg:address":"20-21 Arcadia Avenue",
    "sg:city":"London",
    "sg:classifiers":[
        {
            "category":"Communications",
            "subcategory":"Newspaper",
            "type":"Services"
        }
    ],
    "sg:phone":"+44 20 8371 8050",
    "sg:postcode":"N3 2JU",
    "sg:province":"Greater London",
    "sg:tags":[
        "magazine"
    ],
    "wof:name":"Time Plan",
    "wof:placetype":"venue"
},
  "geometry": {"coordinates":[-0.1949689984,51.5998382568],"type":"Point"}
}