{
  "type": "Feature",
  "properties": {
    "addr:full":"4 Lansbury Avenue Barking Essex IG11 9NN",
    "addr:housenumber":"4",
    "addr:postcode":"ig11 9nn",
    "addr:street":"Lansbury Avenue",
    "iso:country":"GB",
    "sg:address":"4 Lansbury Avenue",
    "sg:city":"Barking",
    "sg:classifiers":[
        {
            "category":"Manufacturing",
            "subcategory":"Signs",
            "type":"Manufacturing & Wholesale Goods"
        }
    ],
    "sg:postcode":"IG11 9NN",
    "sg:province":"Essex",
    "sg:tags":[
        "writer"
    ],
    "wof:name":"C T L Signs",
    "wof:placetype":"venue"
},
  "geometry": {"coordinates":[0.107285,51.537811],"type":"Point"}
}