{
  "type": "Feature",
  "properties": {
    "addr:full":"49-51 Cymbeline Way, Bilton Rugby Warwickshire CV22 6JZ",
    "addr:housenumber":"49-51",
    "addr:postcode":"cv22 6jz",
    "addr:street":"Cymbeline Way",
    "iso:country":"GB",
    "sg:address":"49-51 Cymbeline Way, Bilton",
    "sg:city":"Rugby",
    "sg:classifiers":[
        {
            "category":"Shopping",
            "subcategory":"Crafts & Fabrics",
            "type":"Retail Goods"
        }
    ],
    "sg:postcode":"CV22 6JZ",
    "sg:province":"Warwickshire",
    "sg:tags":[
        "shop",
        "needlecraft",
        "wool"
    ],
    "wof:name":"Woodlands Post Office & Newsagency",
    "wof:placetype":"venue"
},
  "geometry": {"coordinates":[-1.2828299999,52.3506011963],"type":"Point"}
}