{
  "type": "Feature",
  "properties": {
    "addr:full":"43 Ashton Road East Manchester Lancashire M35 9PT",
    "addr:housenumber":"43",
    "addr:postcode":"m35 9pt",
    "addr:street":"Ashton Road East",
    "iso:country":"GB",
    "sg:address":"43 Ashton Road East",
    "sg:city":"Manchester",
    "sg:classifiers":[
        {
            "category":"Retail",
            "subcategory":"Auto Repair",
            "type":"Services"
        }
    ],
    "sg:phone":"+44 161 688 8129",
    "sg:postcode":"M35 9PT",
    "sg:province":"Lancashire",
    "sg:tags":[
        "electrician"
    ],
    "wof:name":"Express Auto Electrics Of Failsworth",
    "wof:placetype":"venue"
},
  "geometry": {"coordinates":[-2.152244091,53.5105819702],"type":"Point"}
}