{
  "type": "Feature",
  "properties": {
    "addr:full":"11 Claylands Pl London Greater London SW8 1NL",
    "addr:housenumber":"11",
    "addr:postcode":"sw8 1nl",
    "addr:street":"Claylands Pl",
    "iso:country":"GB",
    "sg:address":"11 Claylands Pl",
    "sg:city":"London",
    "sg:classifiers":[
        {
            "category":"Real Estate",
            "subcategory":"Architect",
            "type":"Services"
        }
    ],
    "sg:postcode":"SW8 1NL",
    "sg:province":"Greater London",
    "wof:name":"Dalton Leaper Partnership",
    "wof:placetype":"venue"
},
  "geometry": {"coordinates":[-0.113999,51.481133],"type":"Point"}
}