{
  "type": "Feature",
  "properties": {
    "iso:country":"GB",
    "sg:address":"2 Weycock Road",
    "sg:city":"Barry",
    "sg:classifiers":[
        {
            "category":"Retail",
            "subcategory":"Auto Repair",
            "type":"Services"
        }
    ],
    "sg:postcode":"CF62 3AA",
    "sg:province":"The Vale of Glamorgan",
    "sg:tags":[
        "modification",
        "garage"
    ],
    "wof:name":"Auto-Service Group Mobile",
    "wof:placetype":"venue"
},
  "geometry": {"coordinates":[-3.3109269142,51.4159812927],"type":"Point"}
}