{
  "type": "Feature",
  "properties": {
    "iso:country":"GB",
    "sg:address":"893 Ashton New Road",
    "sg:city":"Manchester",
    "sg:classifiers":[
        {
            "category":"Taxi",
            "type":"Transportation"
        }
    ],
    "sg:postcode":"M11 4PB",
    "sg:province":"Greater Manchester",
    "sg:tags":[
        "mini",
        "cab"
    ],
    "wof:name":"Concorde Radio Cars",
    "wof:placetype":"venue"
},
  "geometry": {"coordinates":[-2.168451,53.481304],"type":"Point"}
}