{
  "type": "Feature",
  "properties": {
    "addr:full":"Unity Mills Poleacre Lane, Woodley Stockport Cheshire SK6 1PQ",
    "addr:postcode":"sk6 1pq",
    "addr:street":"Poleacre Lane",
    "iso:country":"GB",
    "sg:address":"Unity Mills Poleacre Lane, Woodley",
    "sg:city":"Stockport",
    "sg:classifiers":[
        {
            "category":"Wholesale",
            "subcategory":"Chemicals & Plastics",
            "type":"Manufacturing & Wholesale Goods"
        }
    ],
    "sg:phone":"+44 161 910 1500",
    "sg:postcode":"SK6 1PQ",
    "sg:province":"Cheshire",
    "sg:tags":[
        "product",
        "allied"
    ],
    "wof:name":"Rhodia Ltd.",
    "wof:placetype":"venue"
},
  "geometry": {"coordinates":[-2.0975420475,53.4265708923],"type":"Point"}
}