{
  "type": "Feature",
  "properties": {
    "addr:full":"Esgair Hir, Llanwrin Machynlleth Ceredigion SY20 8NB",
    "addr:postcode":"sy20 8nb",
    "iso:country":"GB",
    "sg:address":"Esgair Hir, Llanwrin",
    "sg:city":"Machynlleth",
    "sg:classifiers":[
        {
            "category":"Farming",
            "subcategory":"Livestock Farm",
            "type":"Manufacturing & Wholesale Goods"
        }
    ],
    "sg:postcode":"SY20 8NB",
    "sg:province":"Ceredigion",
    "sg:tags":[
        "others"
    ],
    "wof:name":"R M Evans",
    "wof:placetype":"venue"
},
  "geometry": {"coordinates":[-3.8467230797,52.5909614563],"type":"Point"}
}