{
  "type": "Feature",
  "properties": {
    "addr:full":"131 Middleton Blvd, Wollaton Nottingham Nottinghamshire NG8 1FW",
    "addr:housenumber":"131",
    "addr:postcode":"ng8 1fw",
    "addr:street":"Middleton Blvd",
    "iso:country":"GB",
    "sg:address":"131 Middleton Blvd, Wollaton",
    "sg:city":"Nottingham",
    "sg:classifiers":[
        {
            "category":"Cinema",
            "subcategory":"Movie Rental",
            "type":"Entertainment"
        }
    ],
    "sg:phone":"+44 115 928 0510",
    "sg:postcode":"NG8 1FW",
    "sg:province":"Nottinghamshire",
    "sg:tags":[
        "video",
        "library"
    ],
    "wof:name":"Hollywood Movie Store",
    "wof:placetype":"venue"
},
  "geometry": {"coordinates":[-1.1933890581,52.9547386169],"type":"Point"}
}