{
  "type": "Feature",
  "properties": {
    "addr:full":"1b St Catherines Way, Gorleston Great Yarmouth Norfolk NR31 7QB",
    "addr:housenumber":"1b",
    "addr:postcode":"nr31 7qb",
    "addr:street":"St Catherines Way",
    "iso:country":"GB",
    "sg:address":"1b St Catherines Way, Gorleston",
    "sg:city":"Great Yarmouth",
    "sg:classifiers":[
        {
            "category":"Health Services",
            "subcategory":"Nursing And Care Facility",
            "type":"Services"
        },
        {
            "category":"Social Services",
            "subcategory":"Retirement Home",
            "type":"Services"
        },
        {
            "category":"Government",
            "subcategory":"Office",
            "type":"Public Place"
        }
    ],
    "sg:phone":"+44 1493 653756",
    "sg:postcode":"NR31 7QB",
    "sg:province":"Norfolk",
    "sg:tags":[
        "residential",
        "local"
    ],
    "wof:name":"NORFOLK COUNTY COUNCIL",
    "wof:placetype":"venue"
},
  "geometry": {"coordinates":[1.715959,52.572945],"type":"Point"}
}