{
  "type": "Feature",
  "properties": {
    "iso:country":"GB",
    "sg:address":"89 Bassleton Lane, Thornaby",
    "sg:city":"Stockton On Tees",
    "sg:classifiers":[
        {
            "category":"Professional",
            "subcategory":"Engineering",
            "type":"Services"
        }
    ],
    "sg:phone":"+44 1642 763041",
    "sg:postcode":"TS17 0LD",
    "sg:province":"Durham",
    "sg:tags":[
        "engineer"
    ],
    "wof:name":"D.E Casson",
    "wof:placetype":"venue"
},
  "geometry": {"coordinates":[-1.310298,54.531826],"type":"Point"}
}