{
  "type": "Feature",
  "properties": {
    "addr:full":"Disley Mill Waterside, Disley Stockport Cheshire SK12 2HW",
    "addr:postcode":"sk12 2hw",
    "addr:street":"Disley",
    "iso:country":"GB",
    "sg:address":"Disley Mill Waterside, Disley",
    "sg:city":"Stockport",
    "sg:classifiers":[
        {
            "category":"Professional",
            "subcategory":"Computer Services",
            "type":"Services"
        }
    ],
    "sg:phone":"+44 161 962 3332",
    "sg:postcode":"SK12 2HW",
    "sg:province":"Cheshire",
    "sg:tags":[
        "consultant"
    ],
    "wof:name":"High Peak Computing Ltd.",
    "wof:placetype":"venue"
},
  "geometry": {"coordinates":[-2.0400369167,53.3586959839],"type":"Point"}
}