{
  "type": "Feature",
  "properties": {
    "iso:country":"GB",
    "sg:address":"Unit 9 Thornton Industrial Estate",
    "sg:city":"Milford Haven",
    "sg:classifiers":[
        {
            "category":"Food & Beverages",
            "subcategory":"Candy",
            "type":"Retail Goods"
        }
    ],
    "sg:postcode":"SA73 2SA",
    "sg:province":"Pembrokeshire",
    "sg:tags":[
        "merchant",
        "produce"
    ],
    "wof:name":"Ashlan Trading Ltd.",
    "wof:placetype":"venue"
},
  "geometry": {"coordinates":[-5.027044,51.716808],"type":"Point"}
}