{
  "type": "Feature",
  "properties": {
    "addr:full":"62 Priory Road Liverpool Merseyside L4 2RZ",
    "addr:housenumber":"62",
    "addr:postcode":"l4 2rz",
    "addr:street":"Priory Road",
    "iso:country":"GB",
    "sg:address":"62 Priory Road",
    "sg:city":"Liverpool",
    "sg:classifiers":[
        {
            "category":"Home & Garden",
            "subcategory":"Home Furnishings",
            "type":"Retail Goods"
        }
    ],
    "sg:phone":"+44 151 261 9091",
    "sg:postcode":"L4 2RZ",
    "sg:province":"Merseyside",
    "sg:tags":[
        "blind",
        "manufacture",
        "fitting",
        "curtain"
    ],
    "wof:name":"Priory Interiors",
    "wof:placetype":"venue"
},
  "geometry": {"coordinates":[-2.951296,53.430119],"type":"Point"}
}