{
  "type": "Feature",
  "properties": {
    "iso:country":"GB",
    "sg:address":"91 Bradmore Grn, Brookmans Park",
    "sg:city":"Hatfield",
    "sg:classifiers":[
        {
            "category":"Social Services",
            "type":"Services"
        }
    ],
    "sg:phone":"+44 1707 662868",
    "sg:postcode":"AL9 7QT",
    "sg:province":"Hertfordshire",
    "sg:tags":[
        "disability"
    ],
    "wof:name":"Home Counties Mobility",
    "wof:placetype":"venue"
},
  "geometry": {"coordinates":[-0.203086,51.721836],"type":"Point"}
}