{
  "type": "Feature",
  "properties": {
    "iso:country":"GB",
    "sg:address":"9 Church Road, Gatley",
    "sg:city":"Cheadle",
    "sg:classifiers":[
        {
            "category":"Food & Beverages",
            "subcategory":"Bakery",
            "type":"Retail Goods"
        }
    ],
    "sg:phone":"+44 161 491 0562",
    "sg:postcode":"SK8 4NG",
    "sg:province":"Cheshire",
    "sg:tags":[
        "baker"
    ],
    "wof:name":"Alexander Allison",
    "wof:placetype":"venue"
},
  "geometry": {"coordinates":[-2.2353000641,53.3921089172],"type":"Point"}
}