{
  "type": "Feature",
  "properties": {
    "addr:full":"60 Mill St Bideford Devon EX39 2JT",
    "addr:housenumber":"60",
    "addr:postcode":"ex39 2jt",
    "addr:street":"Mill St",
    "iso:country":"GB",
    "sg:address":"60 Mill St",
    "sg:city":"Bideford",
    "sg:classifiers":[
        {
            "category":"Shopping",
            "subcategory":"Books",
            "type":"Retail Goods"
        }
    ],
    "sg:phone":"+44 1237 475759",
    "sg:postcode":"EX39 2JT",
    "sg:province":"Devon",
    "sg:tags":[
        "bookseller"
    ],
    "wof:name":"Evangel Christian Shop",
    "wof:placetype":"venue"
},
  "geometry": {"coordinates":[-4.2060689926,51.0185203552],"type":"Point"}
}