{
  "type": "Feature",
  "properties": {
    "iso:country":"GB",
    "sg:address":"Meadow Farm, Cross Moor Lane",
    "sg:city":"York",
    "sg:classifiers":[
        {
            "category":"Manufacturing",
            "subcategory":"Metals",
            "type":"Manufacturing & Wholesale Goods"
        }
    ],
    "sg:postcode":"YO32 2QR",
    "sg:province":"North Yorkshire",
    "sg:tags":[
        "work",
        "sheet"
    ],
    "wof:name":"P Barton",
    "wof:placetype":"venue"
},
  "geometry": {"coordinates":[-1.0770939589,54.012966156],"type":"Point"}
}