{
  "type": "Feature",
  "properties": {
    "addr:full":"151-153 Blackfriars Road London Greater London SE1 8EL",
    "addr:housenumber":"151-153",
    "addr:postcode":"se1 8el",
    "addr:street":"Blackfriars Road",
    "iso:country":"GB",
    "sg:address":"151-153 Blackfriars Road",
    "sg:city":"London",
    "sg:classifiers":[
        {
            "category":"Health Services",
            "subcategory":"Clinic",
            "type":"Services"
        }
    ],
    "sg:phone":"+44 20 7620 1888",
    "sg:postcode":"SE1 8EL",
    "sg:province":"Greater London",
    "sg:tags":[
        "abuse",
        "drug"
    ],
    "wof:name":"Dual Team Community Drug & Alcohol Team",
    "wof:placetype":"venue"
},
  "geometry": {"coordinates":[-0.1044929996,51.4995880127],"type":"Point"}
}