{
  "type": "Feature",
  "properties": {
    "addr:full":"6 Oaker Road, Darley Bridge Matlock Derbyshire DE4 2JQ",
    "addr:housenumber":"6",
    "addr:postcode":"de4 2jq",
    "addr:street":"Oaker Road",
    "iso:country":"GB",
    "sg:address":"6 Oaker Road, Darley Bridge",
    "sg:city":"Matlock",
    "sg:classifiers":[
        {
            "category":"Building & Trades",
            "subcategory":"Construction",
            "type":"Services"
        }
    ],
    "sg:postcode":"DE4 2JQ",
    "sg:province":"Derbyshire",
    "sg:tags":[
        "tile",
        "fitting",
        "tiling",
        "laying",
        "contractor"
    ],
    "wof:name":"B Wheeler",
    "wof:placetype":"venue"
},
  "geometry": {"coordinates":[-1.597592,53.165619],"type":"Point"}
}