{
  "type": "Feature",
  "properties": {
    "addr:full":"40 High St Harrogate North Yorkshire HG3 5JU",
    "addr:housenumber":"40",
    "addr:postcode":"hg3 5ju",
    "addr:street":"High St",
    "iso:country":"GB",
    "sg:address":"40 High St",
    "sg:city":"Harrogate",
    "sg:classifiers":[
        {
            "category":"Professional",
            "subcategory":"Lawyer & Legal Services",
            "type":"Services"
        }
    ],
    "sg:phone":"+44 1423 711446",
    "sg:postcode":"HG3 5JU",
    "sg:province":"North Yorkshire",
    "sg:tags":[
        "solicitor"
    ],
    "wof:name":"Kirbys",
    "wof:placetype":"venue"
},
  "geometry": {"coordinates":[-1.7582219839,54.0864753723],"type":"Point"}
}