{
  "type": "Feature",
  "properties": {
    "iso:country":"GB",
    "sg:address":"34/34a Middleton Park Road",
    "sg:city":"Leeds",
    "sg:classifiers":[
        {
            "category":"Fast Food",
            "type":"Food & Drink"
        }
    ],
    "sg:phone":"+44 113 277 6751",
    "sg:postcode":"LS10 3ST",
    "sg:province":"West Yorkshire",
    "sg:tags":[
        "delivery"
    ],
    "wof:name":"Florence Pizza",
    "wof:placetype":"venue"
},
  "geometry": {"coordinates":[-1.541497,53.748772],"type":"Point"}
}