{
  "type": "Feature",
  "properties": {
    "iso:country":"GB",
    "sg:address":"11a Colyton Way",
    "sg:city":"Reading",
    "sg:classifiers":[
        {
            "category":"Manufacturing",
            "subcategory":"Building Materials",
            "type":"Manufacturing & Wholesale Goods"
        }
    ],
    "sg:phone":"+44 118 942 8009",
    "sg:postcode":"RG8 8BL",
    "sg:province":"Berkshire",
    "sg:tags":[
        "tarmac",
        "asphalt"
    ],
    "wof:name":"D Fletcher",
    "wof:placetype":"venue"
},
  "geometry": {"coordinates":[-1.043474,51.481899],"type":"Point"}
}