{
  "type": "Feature",
  "properties": {
    "addr:full":"17 Westbourne Terrace, Shiney Row Houghton-le-spring Durham DH4 7QJ",
    "addr:housenumber":"17",
    "addr:postcode":"dh4 7qj",
    "addr:street":"Westbourne Terrace",
    "iso:country":"GB",
    "sg:address":"17 Westbourne Terrace, Shiney Row",
    "sg:city":"Houghton-le-spring",
    "sg:classifiers":[
        {
            "category":"Personal",
            "subcategory":"Beauty Salon",
            "type":"Services"
        }
    ],
    "sg:postcode":"DH4 7QJ",
    "sg:province":"Durham",
    "sg:tags":[
        "unisex",
        "hairdresser"
    ],
    "wof:name":"Souls Barabers",
    "wof:placetype":"venue"
},
  "geometry": {"coordinates":[-1.49705,54.867081],"type":"Point"}
}