{
  "type": "Feature",
  "properties": {
    "iso:country":"GB",
    "sg:address":"79 Princes Road",
    "sg:city":"Feltham",
    "sg:classifiers":[
        {
            "category":"Building & Trades",
            "subcategory":"Construction",
            "type":"Services"
        }
    ],
    "sg:postcode":"TW13 4LB",
    "sg:province":"Greater London",
    "sg:tags":[
        "dry",
        "lining",
        "plasterers",
        "screeders"
    ],
    "wof:name":"Building & Plastering Contractors",
    "wof:placetype":"venue"
},
  "geometry": {"coordinates":[-0.419468,51.440182],"type":"Point"}
}