{
  "type": "Feature",
  "properties": {
    "iso:country":"GB",
    "sg:address":"92 Fishergate Walk, St Georges Shopping Centre",
    "sg:city":"Preston",
    "sg:classifiers":[
        {
            "category":"Retail",
            "subcategory":"Photofinishing",
            "type":"Services"
        }
    ],
    "sg:phone":"+44 1772 563254",
    "sg:postcode":"PR1 2NR",
    "sg:province":"Lancashire",
    "sg:tags":[
        "photographic",
        "processor"
    ],
    "wof:name":"Sketchley Retail Ltd.",
    "wof:placetype":"venue"
},
  "geometry": {"coordinates":[-2.705729,53.757961],"type":"Point"}
}