{
  "type": "Feature",
  "properties": {
    "addr:full":"1 Grovesnor House, Durkins Road East Grinstead East Sussex RH19 2RW",
    "addr:housenumber":"1",
    "addr:postcode":"rh19 2rw",
    "addr:street":"Durkins Road",
    "iso:country":"GB",
    "sg:address":"1 Grovesnor House, Durkins Road",
    "sg:city":"East Grinstead",
    "sg:classifiers":[
        {
            "category":"Building & Trades",
            "subcategory":"Construction",
            "type":"Services"
        }
    ],
    "sg:phone":"+44 1342 410464",
    "sg:postcode":"RH19 2RW",
    "sg:province":"East Sussex",
    "sg:tags":[
        "roofing"
    ],
    "wof:name":"Thornton Consulting Group Ltd.",
    "wof:placetype":"venue"
},
  "geometry": {"coordinates":[-0.007568,51.123981],"type":"Point"}
}