{
  "type": "Feature",
  "properties": {
    "addr:full":"13 Tamworth Street Lichfield Staffordshire WS13 6JP",
    "addr:housenumber":"13",
    "addr:postcode":"ws13 6jp",
    "addr:street":"Tamworth Street",
    "iso:country":"GB",
    "sg:address":"13 Tamworth Street",
    "sg:city":"Lichfield",
    "sg:classifiers":[
        {
            "category":"Professional",
            "subcategory":"Art Services",
            "type":"Services"
        }
    ],
    "sg:phone":"+44 1543 264777",
    "sg:postcode":"WS13 6JP",
    "sg:province":"Staffordshire",
    "sg:tags":[
        "framing"
    ],
    "wof:name":"Framework",
    "wof:placetype":"venue"
},
  "geometry": {"coordinates":[-1.8261009455,52.6838951111],"type":"Point"}
}