{
  "type": "Feature",
  "properties": {
    "iso:country":"GB",
    "sg:address":"August Pitts Farm, Churn Lane, Horsmonden",
    "sg:city":"Tonbridge",
    "sg:classifiers":[
        {
            "category":"Professional",
            "subcategory":"Business Services",
            "type":"Services"
        }
    ],
    "sg:phone":"+44 1892 723064",
    "sg:postcode":"TN12 8HW",
    "sg:province":"Kent",
    "sg:tags":[
        "food",
        "import",
        "export",
        "agent"
    ],
    "wof:name":"Matfield Fruit",
    "wof:placetype":"venue"
},
  "geometry": {"coordinates":[0.4291400015,51.1393013],"type":"Point"}
}