{
  "type": "Feature",
  "properties": {
    "addr:full":"5 Bicester Rd Kidlington Buckinghamshire OX5 2LA",
    "addr:housenumber":"5",
    "addr:postcode":"ox5 2la",
    "addr:street":"Bicester Rd",
    "iso:country":"GB",
    "sg:address":"5 Bicester Rd",
    "sg:city":"Kidlington",
    "sg:classifiers":[
        {
            "category":"Personal",
            "subcategory":"Beauty Salon",
            "type":"Services"
        },
        {
            "category":"Personal",
            "subcategory":"Barber",
            "type":"Services"
        }
    ],
    "sg:phone":"+44 1865 376422",
    "sg:postcode":"OX5 2LA",
    "sg:province":"Buckinghamshire",
    "sg:tags":[
        "unisex",
        "hairdresser"
    ],
    "wof:name":"Snips & Tanners",
    "wof:placetype":"venue"
},
  "geometry": {"coordinates":[-1.2814559937,51.8175086975],"type":"Point"}
}