{
  "type": "Feature",
  "properties": {
    "addr:full":"6 High Street Windermere Cumbria LA23 1AF",
    "addr:housenumber":"6",
    "addr:postcode":"la23 1af",
    "addr:street":"High Street",
    "iso:country":"GB",
    "sg:address":"6 High Street",
    "sg:city":"Windermere",
    "sg:classifiers":[
        {
            "category":"Insurance",
            "subcategory":"Insurance Agent",
            "type":"Services"
        }
    ],
    "sg:phone":"+44 15394 46631",
    "sg:postcode":"LA23 1AF",
    "sg:province":"Cumbria",
    "sg:tags":[
        "broker"
    ],
    "wof:name":"Simpson & Parsons",
    "wof:placetype":"venue"
},
  "geometry": {"coordinates":[-2.9060161114,54.3802185059],"type":"Point"}
}