{
  "type": "Feature",
  "properties": {
    "addr:full":"32 High Street, Merstham Redhill Surrey RH1 3EA",
    "addr:housenumber":"32",
    "addr:postcode":"rh1 3ea",
    "addr:street":"High Street;Redhill",
    "iso:country":"GB",
    "sg:address":"32 High Street, Merstham",
    "sg:city":"Redhill",
    "sg:classifiers":[
        {
            "category":"Shopping",
            "subcategory":"Clothing, Apparel, & Fashions",
            "type":"Retail Goods"
        }
    ],
    "sg:phone":"+44 1737 645976",
    "sg:postcode":"RH1 3EA",
    "sg:province":"Surrey",
    "sg:tags":[
        "shop",
        "dress",
        "outlet",
        "fancy"
    ],
    "wof:name":"Party Goers",
    "wof:placetype":"venue"
},
  "geometry": {"coordinates":[-0.152458,51.26458],"type":"Point"}
}