{
  "type": "Feature",
  "properties": {
    "addr:full":"Thomas Street Wks, 15 Clitheroe Rd, Brierfield Nelson Lancashire BB9 5PT",
    "addr:housenumber":"15",
    "addr:postcode":"bb9 5pt",
    "addr:street":"Thomas Street Wks;Clitheroe Rd",
    "iso:country":"GB",
    "sg:address":"Thomas Street Wks, 15 Clitheroe Rd, Brierfield",
    "sg:city":"Nelson",
    "sg:classifiers":[
        {
            "category":"Travel",
            "subcategory":"Bed & Breakfast",
            "type":"Entertainment"
        }
    ],
    "sg:phone":"+44 1282 772102",
    "sg:postcode":"BB9 5PT",
    "sg:province":"Lancashire",
    "sg:tags":[
        "ladder"
    ],
    "wof:name":"Ashton,Harry,& Sons Ltd",
    "wof:placetype":"venue"
},
  "geometry": {"coordinates":[-2.234284,53.823605],"type":"Point"}
}