{
  "type": "Feature",
  "properties": {
    "iso:country":"GB",
    "sg:address":"Low Farm, Walmsgate",
    "sg:city":"Louth",
    "sg:classifiers":[
        {
            "category":"Farming",
            "subcategory":"Livestock Farm",
            "type":"Manufacturing & Wholesale Goods"
        },
        {
            "category":"Retail",
            "subcategory":"Animal Services",
            "type":"Services"
        }
    ],
    "sg:phone":"+44 1507 480360",
    "sg:postcode":"LN11 8QN",
    "sg:province":"Lincolnshire",
    "sg:tags":[
        "breeder",
        "others"
    ],
    "wof:name":"Walmsgate Estates (Farming)",
    "wof:placetype":"venue"
},
  "geometry": {"coordinates":[0.045636,53.284489],"type":"Point"}
}