{
  "type": "Feature",
  "properties": {
    "iso:country":"GB",
    "sg:address":"73 Sheffield Road",
    "sg:city":"Rotherham",
    "sg:classifiers":[
        {
            "category":"Real Estate",
            "subcategory":"Developer",
            "type":"Services"
        }
    ],
    "sg:phone":"+44 1709 382244",
    "sg:postcode":"S60 1DA",
    "sg:province":"South Yorkshire",
    "sg:tags":[
        "property"
    ],
    "wof:name":"Action 2000 Ltd.",
    "wof:placetype":"venue"
},
  "geometry": {"coordinates":[-1.3609579802,53.4253883362],"type":"Point"}
}