{
  "type": "Feature",
  "properties": {
    "iso:country":"GB",
    "sg:address":"113 High Street",
    "sg:city":"Irvine",
    "sg:classifiers":[
        {
            "category":"Personal",
            "subcategory":"Barber",
            "type":"Services"
        },
        {
            "category":"Personal",
            "subcategory":"Nail Salon",
            "type":"Services"
        }
    ],
    "sg:phone":"+44 1294 313733",
    "sg:postcode":"KA12 8AA",
    "sg:province":"North Ayrshire",
    "sg:tags":[
        "unisex",
        "solarium",
        "tanning",
        "hairdresser"
    ],
    "wof:name":"The Fullworks",
    "wof:placetype":"venue"
},
  "geometry": {"coordinates":[-4.6677942276,55.6151008606],"type":"Point"}
}