{
  "type": "Feature",
  "properties": {
    "iso:country":"GB",
    "sg:address":"26 Bridle Lane",
    "sg:city":"Sutton Coldfield",
    "sg:classifiers":[
        {
            "category":"Place Of Worship",
            "type":"Public Place"
        }
    ],
    "sg:phone":"+44 121 353 3778",
    "sg:postcode":"B74 3HB",
    "sg:province":"Staffordshire",
    "wof:name":"St Annes R C Church",
    "wof:placetype":"venue"
},
  "geometry": {"coordinates":[-1.886479,52.576885],"type":"Point"}
}