{
  "type": "Feature",
  "properties": {
    "iso:country":"GB",
    "sg:address":"Office Suite Building No 8, Turweston Aerodrome",
    "sg:city":"Brackley",
    "sg:classifiers":[
        {
            "category":"Manufacturing",
            "subcategory":"Tools & Machinery",
            "type":"Manufacturing & Wholesale Goods"
        }
    ],
    "sg:phone":"+44 1280 706701",
    "sg:postcode":"NN13 5YD",
    "sg:province":"Buckinghamshire",
    "sg:tags":[
        "design",
        "maker"
    ],
    "wof:name":"Tube Runner Ltd.",
    "wof:placetype":"venue"
},
  "geometry": {"coordinates":[-1.079151,52.0564],"type":"Point"}
}