{
  "type": "Feature",
  "properties": {
    "addr:full":"Unit3, Wilsons Park, Monsall Road Manchester Greater Manchester M40 8WN",
    "addr:postcode":"m40 8wn",
    "addr:street":"Monsall Road",
    "iso:country":"GB",
    "sg:address":"Unit3, Wilsons Park, Monsall Road",
    "sg:city":"Manchester",
    "sg:classifiers":[
        {
            "category":"Social Services",
            "subcategory":"Child Care",
            "type":"Services"
        },
        {
            "category":"Farming",
            "subcategory":"Nursery",
            "type":"Manufacturing & Wholesale Goods"
        },
        {
            "category":"Retail",
            "subcategory":"Auto Rental",
            "type":"Services"
        }
    ],
    "sg:phone":"+44 161 203 4744",
    "sg:postcode":"M40 8WN",
    "sg:province":"Greater Manchester",
    "sg:tags":[
        "car",
        "creche"
    ],
    "wof:name":"Skittles Child Care Ltd",
    "wof:placetype":"venue"
},
  "geometry": {"coordinates":[-2.2115950584,53.4962158203],"type":"Point"}
}