{
  "type": "Feature",
  "properties": {
    "iso:country":"GB",
    "sg:address":"The Lodge, Low Road",
    "sg:city":"Brough",
    "sg:classifiers":[
        {
            "category":"Home & Garden",
            "subcategory":"Garden Supply",
            "type":"Retail Goods"
        }
    ],
    "sg:postcode":"HU15 2AD",
    "sg:province":"East Riding of Yorkshire",
    "sg:tags":[
        "nursery",
        "centre"
    ],
    "wof:name":"R A Majoram",
    "wof:placetype":"venue"
},
  "geometry": {"coordinates":[-0.572144,53.729919],"type":"Point"}
}