{
  "type": "Feature",
  "properties": {
    "addr:full":"9 Lansdowne Road Worthing West Sussex BN11 4NA",
    "addr:housenumber":"9",
    "addr:postcode":"bn11 4na",
    "addr:street":"Lansdowne Road",
    "iso:country":"GB",
    "sg:address":"9 Lansdowne Road",
    "sg:city":"Worthing",
    "sg:classifiers":[
        {
            "category":"Social Services",
            "subcategory":"Job Training",
            "type":"Services"
        }
    ],
    "sg:postcode":"BN11 4NA",
    "sg:province":"West Sussex",
    "sg:tags":[
        "draughtsman",
        "drawing"
    ],
    "wof:name":"B W B Design Services",
    "wof:placetype":"venue"
},
  "geometry": {"coordinates":[-0.3885920048,50.813205719],"type":"Point"}
}