{
  "type": "Feature",
  "properties": {
    "addr:full":"10 Jubilee Crescent Coventry Warwickshire CV6 3EX",
    "addr:housenumber":"10",
    "addr:postcode":"cv6 3ex",
    "addr:street":"Jubilee Crescent",
    "iso:country":"GB",
    "sg:address":"10 Jubilee Crescent",
    "sg:city":"Coventry",
    "sg:classifiers":[
        {
            "category":"Food & Beverages",
            "subcategory":"Meat & Fish",
            "type":"Retail Goods"
        }
    ],
    "sg:phone":"+44 24 7659 1155",
    "sg:postcode":"CV6 3EX",
    "sg:province":"Warwickshire",
    "sg:tags":[
        "butcher"
    ],
    "wof:name":"Flackies Meats of Lutterworth",
    "wof:placetype":"venue"
},
  "geometry": {"coordinates":[-1.5167089701,52.430770874],"type":"Point"}
}