{
  "type": "Feature",
  "properties": {
    "addr:full":"7 Windsor Place Merthyr Tydfil Caerphilly CF48 4SB",
    "addr:housenumber":"7",
    "addr:postcode":"cf48 4sb",
    "addr:street":"Windsor Place",
    "iso:country":"GB",
    "sg:address":"7 Windsor Place",
    "sg:city":"Merthyr Tydfil",
    "sg:classifiers":[
        {
            "category":"Shopping",
            "subcategory":"Department Store",
            "type":"Retail Goods"
        }
    ],
    "sg:postcode":"CF48 4SB",
    "sg:province":"Caerphilly",
    "wof:name":"Windsor Stores",
    "wof:placetype":"venue"
},
  "geometry": {"coordinates":[-3.350283,51.710728],"type":"Point"}
}