{
  "type": "Feature",
  "properties": {
    "addr:full":"Baker Street, Orsett Grays Essex RM16 3LJ",
    "addr:postcode":"rm16 3lj",
    "addr:street":"Baker Street",
    "iso:country":"GB",
    "sg:address":"Baker Street, Orsett",
    "sg:city":"Grays",
    "sg:classifiers":[
        {
            "category":"Sports & Exercise",
            "subcategory":"Stables",
            "type":"Entertainment"
        }
    ],
    "sg:phone":"+44 1375 891367",
    "sg:postcode":"RM16 3LJ",
    "sg:province":"Essex",
    "sg:tags":[
        "education",
        "equestrian"
    ],
    "wof:name":"Foxhound Riding School Ltd.",
    "wof:placetype":"venue"
},
  "geometry": {"coordinates":[0.35315,51.507889],"type":"Point"}
}