{
  "type": "Feature",
  "properties": {
    "iso:country":"GB",
    "sg:address":"11 High Street",
    "sg:city":"Sutton Coldfield",
    "sg:classifiers":[
        {
            "category":"Real Estate",
            "subcategory":"Real Estate Operator",
            "type":"Services"
        }
    ],
    "sg:phone":"+44 121 241 3030",
    "sg:postcode":"B72 1XH",
    "sg:province":"West Midlands",
    "sg:tags":[
        "letting",
        "agent"
    ],
    "wof:name":"Green & Co.",
    "wof:placetype":"venue"
},
  "geometry": {"coordinates":[-1.822948,52.565689],"type":"Point"}
}