{
  "type": "Feature",
  "properties": {
    "addr:full":"371 Green Lanes London Greater London N4 1DY",
    "addr:housenumber":"371",
    "addr:postcode":"n4 1dy",
    "addr:street":"Green Lanes",
    "iso:country":"GB",
    "sg:address":"371 Green Lanes",
    "sg:city":"London",
    "sg:classifiers":[
        {
            "category":"Real Estate",
            "subcategory":"Real Estate Operator",
            "type":"Services"
        }
    ],
    "sg:phone":"+44 20 8809 6144",
    "sg:postcode":"N4 1DY",
    "sg:province":"Greater London",
    "sg:tags":[
        "letting",
        "agent"
    ],
    "wof:name":"Alpha-Lets Ltd.",
    "wof:placetype":"venue"
},
  "geometry": {"coordinates":[-0.09889,51.57663],"type":"Point"}
}