{
  "type": "Feature",
  "properties": {
    "addr:full":"Unit 1 Marlborough Court, Pickford Street Macclesfield Cheshire SK11 6JD",
    "addr:housenumber":"unit 1",
    "addr:postcode":"sk11 6jd",
    "addr:street":"Marlborough Court Pickford Street",
    "iso:country":"GB",
    "sg:address":"Unit 1 Marlborough Court, Pickford Street",
    "sg:city":"Macclesfield",
    "sg:classifiers":[
        {
            "category":"Shopping",
            "subcategory":"Clothing, Apparel, & Fashions",
            "type":"Retail Goods"
        }
    ],
    "sg:phone":"+44 1625 618169",
    "sg:postcode":"SK11 6JD",
    "sg:province":"Cheshire",
    "sg:tags":[
        "shop"
    ],
    "wof:name":"Bousse",
    "wof:placetype":"venue"
},
  "geometry": {"coordinates":[-2.122799,53.257599],"type":"Point"}
}