{
  "type": "Feature",
  "properties": {
    "addr:full":"Oakhurst Rd Southend-on-sea Essex SS2 5DT",
    "addr:postcode":"ss2 5dt",
    "addr:street":"Oakhurst Rd",
    "iso:country":"GB",
    "sg:address":"Oakhurst Rd",
    "sg:city":"Southend-on-sea",
    "sg:classifiers":[
        {
            "category":"Retail",
            "subcategory":"Auto Repair",
            "type":"Services"
        }
    ],
    "sg:postcode":"SS2 5DT",
    "sg:province":"Essex",
    "sg:tags":[
        "modification",
        "garage"
    ],
    "wof:name":"Brook Bros",
    "wof:placetype":"venue"
},
  "geometry": {"coordinates":[0.713899,51.550064],"type":"Point"}
}