{
  "type": "Feature",
  "properties": {
    "iso:country":"GB",
    "sg:address":"31 Aldborough St",
    "sg:city":"Blyth",
    "sg:classifiers":[
        {
            "category":"Professional",
            "type":"Services"
        }
    ],
    "sg:phone":"+44 1670 369442",
    "sg:postcode":"NE24 2ET",
    "sg:province":"Northumberland",
    "sg:tags":[
        "repair",
        "tech",
        "maintenance"
    ],
    "wof:name":"Micro-surgery",
    "wof:placetype":"venue"
},
  "geometry": {"coordinates":[-1.509131,55.124763],"type":"Point"}
}