{
  "type": "Feature",
  "properties": {
    "iso:country":"GB",
    "sg:address":"30-32 Northgate",
    "sg:city":"Cottingham",
    "sg:classifiers":[
        {
            "category":"Professional",
            "subcategory":"Business Services",
            "type":"Services"
        }
    ],
    "sg:phone":"+44 1482 844114",
    "sg:postcode":"HU16 4EZ",
    "sg:province":"East Riding of Yorkshire",
    "sg:tags":[
        "tile",
        "stockist"
    ],
    "wof:name":"Millhouse Ceramics",
    "wof:placetype":"venue"
},
  "geometry": {"coordinates":[-0.4090819955,53.7851219177],"type":"Point"}
}