{
  "type": "Feature",
  "properties": {
    "iso:country":"GB",
    "sg:address":"443 New Cross Rd",
    "sg:city":"London",
    "sg:classifiers":[
        {
            "category":"Fast Food",
            "type":"Food & Drink"
        }
    ],
    "sg:postcode":"SE14 6TA",
    "sg:province":"Greater London",
    "sg:tags":[
        "away",
        "take"
    ],
    "wof:name":"Marlowe's",
    "wof:placetype":"venue"
},
  "geometry": {"coordinates":[-0.029471,51.475636],"type":"Point"}
}