{
  "type": "Feature",
  "properties": {
    "iso:country":"GB",
    "sg:address":"87 Hailgate, Howden",
    "sg:city":"Goole",
    "sg:classifiers":[
        {
            "category":"Retail",
            "subcategory":"Veterinary Services",
            "type":"Services"
        }
    ],
    "sg:phone":"+44 1430 430204",
    "sg:postcode":"DN14 7ST",
    "sg:province":"East Riding of Yorkshire",
    "sg:tags":[
        "surgeon"
    ],
    "wof:name":"Vermuyden Vetinary Practice",
    "wof:placetype":"venue"
},
  "geometry": {"coordinates":[-0.864117,53.743839],"type":"Point"}
}