{
  "type": "Feature",
  "properties": {
    "addr:full":"Merlwood, Kirkgunzeon Dumfries Dumfries and Galloway DG2 8JR",
    "addr:postcode":"dg2 8jr",
    "iso:country":"GB",
    "sg:address":"Merlwood, Kirkgunzeon",
    "sg:city":"Dumfries",
    "sg:classifiers":[
        {
            "category":"Professional",
            "subcategory":"Employment Agencies",
            "type":"Services"
        },
        {
            "category":"Recreation",
            "subcategory":"Gun Range",
            "type":"Entertainment"
        }
    ],
    "sg:phone":"+44 1556 610804",
    "sg:postcode":"DG2 8JR",
    "sg:province":"Dumfries and Galloway",
    "sg:tags":[
        "chainsaw",
        "sale"
    ],
    "wof:name":"John H Thomson",
    "wof:placetype":"venue"
},
  "geometry": {"coordinates":[-3.7755880356,54.9835014343],"type":"Point"}
}