{
  "type": "Feature",
  "properties": {
    "addr:full":"Sidegate Avenue Ipswich Suffolk IP4 4JJ",
    "addr:postcode":"ip4 4jj",
    "addr:street":"Sidegate Avenue",
    "iso:country":"GB",
    "sg:address":"Sidegate Avenue",
    "sg:city":"Ipswich",
    "sg:classifiers":[
        {
            "category":"Arena",
            "subcategory":"Sports Club",
            "type":"Entertainment"
        }
    ],
    "sg:phone":"+44 1473 726134",
    "sg:postcode":"IP4 4JJ",
    "sg:province":"Suffolk",
    "wof:name":"Ramsomes & Reavell Sports & Social Club",
    "wof:placetype":"venue"
},
  "geometry": {"coordinates":[1.183693,52.06715],"type":"Point"}
}