{
  "type": "Feature",
  "properties": {
    "addr:full":"287 Manchester Road Oldham Lancashire OL8 4RF",
    "addr:housenumber":"287",
    "addr:postcode":"ol8 4rf",
    "addr:street":"Manchester Road",
    "iso:country":"GB",
    "sg:address":"287 Manchester Road",
    "sg:city":"Oldham",
    "sg:classifiers":[
        {
            "category":"Bars & Pubs",
            "type":"Food & Drink"
        },
        {
            "category":"Community Center",
            "subcategory":"Social",
            "type":"Public Place"
        }
    ],
    "sg:phone":"+44 161 681 3243",
    "sg:postcode":"OL8 4RF",
    "sg:province":"Lancashire",
    "sg:tags":[
        "pubs",
        "house",
        "inn",
        "activity"
    ],
    "wof:name":"The Spinners Arms",
    "wof:placetype":"venue"
},
  "geometry": {"coordinates":[-2.141832,53.522278],"type":"Point"}
}