{
  "type": "Feature",
  "properties": {
    "addr:full":"59 Ambleside Drive Worcester Worcestershire WR4 9DA",
    "addr:housenumber":"59",
    "addr:postcode":"wr4 9da",
    "addr:street":"Ambleside Drive",
    "iso:country":"GB",
    "sg:address":"59 Ambleside Drive",
    "sg:city":"Worcester",
    "sg:classifiers":[
        {
            "category":"Personal",
            "subcategory":"Beauty Salon",
            "type":"Services"
        }
    ],
    "sg:postcode":"WR4 9DA",
    "sg:province":"Worcestershire",
    "sg:tags":[
        "unisex",
        "hairdresser"
    ],
    "wof:name":"Kaboodles",
    "wof:placetype":"venue"
},
  "geometry": {"coordinates":[-2.191124,52.203472],"type":"Point"}
}