{
  "type": "Feature",
  "properties": {
    "iso:country":"GB",
    "sg:address":"5 Lloyds Avenue",
    "sg:city":"London",
    "sg:classifiers":[
        {
            "category":"Insurance",
            "subcategory":"Insurance Agent",
            "type":"Services"
        }
    ],
    "sg:postcode":"EC3N 3AE",
    "sg:province":"Greater London",
    "wof:name":"Premier Direct Travel Insurance Services",
    "wof:placetype":"venue"
},
  "geometry": {"coordinates":[-0.077573,51.511974],"type":"Point"}
}