{
  "type": "Feature",
  "properties": {
    "iso:country":"GB",
    "sg:address":"44 Imperial Road",
    "sg:city":"Bristol",
    "sg:classifiers":[
        {
            "category":"Building & Trades",
            "subcategory":"Construction",
            "type":"Services"
        }
    ],
    "sg:postcode":"BS14 9ED",
    "sg:province":"City of Bristol",
    "sg:tags":[
        "builder"
    ],
    "wof:name":"D G Bradley",
    "wof:placetype":"venue"
},
  "geometry": {"coordinates":[-2.561388,51.423809],"type":"Point"}
}