{
  "type": "Feature",
  "properties": {
    "iso:country":"GB",
    "sg:address":"47 Abbey End",
    "sg:city":"Kenilworth",
    "sg:classifiers":[
        {
            "category":"Home & Garden",
            "subcategory":"Furniture",
            "type":"Retail Goods"
        }
    ],
    "sg:postcode":"CV8 1QJ",
    "sg:province":"Warwickshire",
    "wof:name":"Barbara D Suffield",
    "wof:placetype":"venue"
},
  "geometry": {"coordinates":[-1.580427,52.344292],"type":"Point"}
}