{
  "type": "Feature",
  "properties": {
    "iso:country":"GB",
    "sg:address":"Unit E Wylds Road",
    "sg:city":"Bridgwater",
    "sg:classifiers":[
        {
            "category":"Autos & Motor Vehicles",
            "subcategory":"Auto Supplies",
            "type":"Retail Goods"
        }
    ],
    "sg:phone":"+44 1278 433355",
    "sg:postcode":"TA6 4BH",
    "sg:province":"Somerset",
    "sg:tags":[
        "component"
    ],
    "wof:name":"Mill Auto Supplies Ltd.",
    "wof:placetype":"venue"
},
  "geometry": {"coordinates":[-3.013824,51.127556],"type":"Point"}
}