{
  "type": "Feature",
  "properties": {
    "addr:full":"Thongsbridge Huddersfield South Yorkshire HD9 7TD",
    "addr:postcode":"hd9 7td",
    "addr:street":"South",
    "iso:country":"GB",
    "sg:address":"Thongsbridge",
    "sg:city":"Huddersfield",
    "sg:classifiers":[
        {
            "category":"Military Area",
            "subcategory":"Air Force Base",
            "type":"Public Place"
        },
        {
            "category":"Recreation",
            "subcategory":"Campground",
            "type":"Entertainment"
        }
    ],
    "sg:phone":"+44 1484 665819",
    "sg:postcode":"HD9 7TD",
    "sg:province":"South Yorkshire",
    "sg:tags":[
        "taxi",
        "caravan",
        "hire",
        "park",
        "private"
    ],
    "wof:name":"Holme Valley Camping & Caravan Park",
    "wof:placetype":"venue"
},
  "geometry": {"coordinates":[-1.771412015,53.5852355957],"type":"Point"}
}