{
  "type": "Feature",
  "properties": {
    "iso:country":"GB",
    "sg:address":"13 Northampton Road Lavendon",
    "sg:city":"Olney",
    "sg:classifiers":[
        {
            "category":"Retail",
            "subcategory":"Repair Shop",
            "type":"Services"
        }
    ],
    "sg:postcode":"MK46 4EY",
    "sg:province":"Buckinghamshire",
    "sg:tags":[
        "maintenance"
    ],
    "wof:name":"Highline Profiles Ltd.",
    "wof:placetype":"venue"
},
  "geometry": {"coordinates":[-0.6627799869,52.1736030579],"type":"Point"}
}