{
  "type": "Feature",
  "properties": {
    "addr:full":"1 Guillemot Place, Clarendon Road, Off Coburg Road London Greater London N22 6XG",
    "addr:housenumber":"1",
    "addr:postcode":"n22 6xg",
    "addr:street":"Guillemot Place Clarendon Road Off Coburg Road",
    "iso:country":"GB",
    "sg:address":"1 Guillemot Place, Clarendon Road, Off Coburg Road",
    "sg:city":"London",
    "sg:classifiers":[
        {
            "category":"Shopping",
            "subcategory":"Clothing, Apparel, & Fashions",
            "type":"Retail Goods"
        },
        {
            "category":"Manufacturing",
            "subcategory":"Paper Products",
            "type":"Manufacturing & Wholesale Goods"
        }
    ],
    "sg:phone":"+44 20 8888 8833",
    "sg:postcode":"N22 6XG",
    "sg:province":"Greater London",
    "sg:tags":[
        "clothing",
        "fabric",
        "manufacturer"
    ],
    "wof:name":"Alandar Park Ltd",
    "wof:placetype":"venue"
},
  "geometry": {"coordinates":[-0.1141289994,51.5948982239],"type":"Point"}
}