{
  "type": "Feature",
  "properties": {
    "iso:country":"GB",
    "sg:address":"Yew Farm",
    "sg:city":"Cambridge",
    "sg:classifiers":[
        {
            "category":"Home & Garden",
            "subcategory":"Hardware",
            "type":"Retail Goods"
        }
    ],
    "sg:postcode":"CB1 6NX",
    "sg:province":"Cambridgeshire",
    "sg:tags":[
        "lawnmowers",
        "machinery"
    ],
    "wof:name":"Linton Lawnmowers",
    "wof:placetype":"venue"
},
  "geometry": {"coordinates":[0.27362,52.080002],"type":"Point"}
}