{
  "type": "Feature",
  "properties": {
    "addr:full":"73 High Grn Cannock Staffordshire WS11 1BN",
    "addr:housenumber":"73",
    "addr:postcode":"ws11 1bn",
    "addr:street":"High Grn",
    "iso:country":"GB",
    "sg:address":"73 High Grn",
    "sg:city":"Cannock",
    "sg:classifiers":[
        {
            "category":"Food & Beverages",
            "subcategory":"Meat & Fish",
            "type":"Retail Goods"
        }
    ],
    "sg:phone":"+44 1543 573234",
    "sg:postcode":"WS11 1BN",
    "sg:province":"Staffordshire",
    "sg:tags":[
        "chip"
    ],
    "wof:name":"High Green Fish Bar",
    "wof:placetype":"venue"
},
  "geometry": {"coordinates":[-2.0326449871,52.6896247864],"type":"Point"}
}