{
  "type": "Feature",
  "properties": {
    "addr:full":"90-91 Fleet Street London Greater London EC4Y 1DH",
    "addr:housenumber":"90-91",
    "addr:postcode":"ec4y 1dh",
    "addr:street":"Fleet Street",
    "iso:country":"GB",
    "sg:address":"90-91 Fleet Street",
    "sg:city":"London",
    "sg:classifiers":[
        {
            "category":"Cafe",
            "type":"Food & Drink"
        }
    ],
    "sg:phone":"+44 20 7731 4599",
    "sg:postcode":"EC4Y 1DH",
    "sg:province":"Greater London",
    "sg:tags":[
        "tea",
        "room"
    ],
    "wof:name":"Starbucks Coffee Co. (U K) Ltd.",
    "wof:placetype":"venue"
},
  "geometry": {"coordinates":[-0.1055549979,51.514087677],"type":"Point"}
}