{
  "type": "Feature",
  "properties": {
    "addr:full":"110 Bohemia Road St Leonards-on-sea East Sussex TN37 6RN",
    "addr:housenumber":"110",
    "addr:postcode":"leonards-on-sea;tn37 6rn",
    "addr:street":"Bohemia Road St",
    "iso:country":"GB",
    "sg:address":"110 Bohemia Road",
    "sg:city":"St Leonards-on-sea",
    "sg:classifiers":[
        {
            "category":"Organizations",
            "subcategory":"Non-profit Organization",
            "type":"Services"
        }
    ],
    "sg:postcode":"TN37 6RN",
    "sg:province":"East Sussex",
    "sg:tags":[
        "organisation",
        "voluntary",
        "charity"
    ],
    "wof:name":"Communique",
    "wof:placetype":"venue"
},
  "geometry": {"coordinates":[0.5596809983,50.8620872498],"type":"Point"}
}