{
  "type": "Feature",
  "properties": {
    "addr:full":"122 Brent Street London Greater London NW4 2DT",
    "addr:housenumber":"122",
    "addr:postcode":"nw4 2dt",
    "addr:street":"Brent Street",
    "iso:country":"GB",
    "sg:address":"122 Brent Street",
    "sg:city":"London",
    "sg:classifiers":[
        {
            "category":"Retail",
            "subcategory":"Laundry & Dry Cleaning",
            "type":"Services"
        }
    ],
    "sg:phone":"+44 20 8202 3057",
    "sg:postcode":"NW4 2DT",
    "sg:province":"Greater London",
    "sg:tags":[
        "cleaner",
        "alteration"
    ],
    "wof:name":"Diamond Dry Cleaners Ltd.",
    "wof:placetype":"venue"
},
  "geometry": {"coordinates":[-0.220338,51.586803],"type":"Point"}
}