{
  "type": "Feature",
  "properties": {
    "addr:full":"11 Finchley Lane London Greater London NW4 1BN",
    "addr:housenumber":"11",
    "addr:postcode":"nw4 1bn",
    "addr:street":"Finchley Lane",
    "iso:country":"GB",
    "sg:address":"11 Finchley Lane",
    "sg:city":"London",
    "sg:classifiers":[
        {
            "category":"Fast Food",
            "type":"Food & Drink"
        }
    ],
    "sg:phone":"+44 20 8203 4214",
    "sg:postcode":"NW4 1BN",
    "sg:province":"Greater London",
    "sg:tags":[
        "away",
        "take"
    ],
    "wof:name":"Topkape Steak & Kebab House",
    "wof:placetype":"venue"
},
  "geometry": {"coordinates":[-0.221111,51.589745],"type":"Point"}
}