{
  "type": "Feature",
  "properties": {
    "iso:country":"GB",
    "sg:address":"1 Crossfield Road, Hale",
    "sg:city":"Altrincham",
    "sg:classifiers":[
        {
            "category":"Health Services",
            "subcategory":"Health Practitioner",
            "type":"Services"
        }
    ],
    "sg:phone":"+44 161 903 9191",
    "sg:postcode":"WA15 8DU",
    "sg:province":"Cheshire",
    "sg:tags":[
        "physiotherapist"
    ],
    "wof:name":"Jack & Carolyn Kennedy",
    "wof:placetype":"venue"
},
  "geometry": {"coordinates":[-2.323592,53.379292],"type":"Point"}
}