{
  "type": "Feature",
  "properties": {
    "addr:full":"19 Longman Drive Inverness Highland IV1 1SU",
    "addr:housenumber":"19",
    "addr:postcode":"iv1 1su",
    "addr:street":"Longman Drive",
    "iso:country":"GB",
    "sg:address":"19 Longman Drive",
    "sg:city":"Inverness",
    "sg:classifiers":[
        {
            "category":"Wholesale",
            "subcategory":"Non-durable Goods",
            "type":"Manufacturing & Wholesale Goods"
        }
    ],
    "sg:phone":"+44 1463 235291",
    "sg:postcode":"IV1 1SU",
    "sg:province":"Highland",
    "sg:tags":[
        "carry",
        "cash"
    ],
    "wof:name":"Booker Cash & Carry",
    "wof:placetype":"venue"
},
  "geometry": {"coordinates":[-4.219136,57.492302],"type":"Point"}
}