{
  "type": "Feature",
  "properties": {
    "iso:country":"GB",
    "sg:address":"13 Red Lion Street",
    "sg:city":"Boston",
    "sg:classifiers":[
        {
            "category":"Food & Beverages",
            "subcategory":"Bakery",
            "type":"Retail Goods"
        }
    ],
    "sg:phone":"+44 1205 368200",
    "sg:postcode":"PE21 6NY",
    "sg:province":"Lincolnshire",
    "sg:tags":[
        "baker"
    ],
    "wof:name":"The Little French Bakery",
    "wof:placetype":"venue"
},
  "geometry": {"coordinates":[-0.0247510001,52.9802246094],"type":"Point"}
}