{
  "type": "Feature",
  "properties": {
    "addr:full":"Smithville Close, St Briavels Lydney Gloucestershire GL15 6TN",
    "addr:postcode":"gl15 6tn",
    "addr:street":"Smithville Close",
    "iso:country":"GB",
    "sg:address":"Smithville Close, St Briavels",
    "sg:city":"Lydney",
    "sg:classifiers":[
        {
            "category":"Health Services",
            "subcategory":"Doctor",
            "type":"Services"
        }
    ],
    "sg:phone":"+44 1594 530334",
    "sg:postcode":"GL15 6TN",
    "sg:province":"Gloucestershire",
    "sg:tags":[
        "practitioners"
    ],
    "wof:name":"The Wye Valley Practice",
    "wof:placetype":"venue"
},
  "geometry": {"coordinates":[-2.6083760262,51.6896133423],"type":"Point"}
}