{
  "type": "Feature",
  "properties": {
    "iso:country":"GB",
    "sg:address":"5a Factory La",
    "sg:city":"Nottingham",
    "sg:classifiers":[
        {
            "category":"Professional",
            "subcategory":"Detective & Security Services",
            "type":"Services"
        }
    ],
    "sg:phone":"+44 115 943 1207",
    "sg:postcode":"NG9 4AA",
    "sg:province":"Nottinghamshire",
    "sg:tags":[
        "alarm",
        "burglar",
        "system"
    ],
    "wof:name":"K C Electrical",
    "wof:placetype":"venue"
},
  "geometry": {"coordinates":[-1.221282,52.921631],"type":"Point"}
}