{
  "type": "Feature",
  "properties": {
    "addr:full":"Roman Ridge Road Sheffield South Yorkshire S9 1GB",
    "addr:postcode":"s9 1gb",
    "addr:street":"Roman Ridge Road",
    "iso:country":"GB",
    "sg:address":"Roman Ridge Road",
    "sg:city":"Sheffield",
    "sg:classifiers":[
        {
            "category":"Retail",
            "subcategory":"Storage",
            "type":"Services"
        }
    ],
    "sg:phone":"+44 114 243 4093",
    "sg:postcode":"S9 1GB",
    "sg:province":"South Yorkshire",
    "sg:tags":[
        "cold"
    ],
    "wof:name":"T D G Plc",
    "wof:placetype":"venue"
},
  "geometry": {"coordinates":[-1.418702,53.417698],"type":"Point"}
}