{
  "type": "Feature",
  "properties": {
    "iso:country":"GB",
    "sg:address":"7 Marchwood Road",
    "sg:city":"Sheffield",
    "sg:classifiers":[
        {
            "category":"Building & Trades",
            "subcategory":"Construction",
            "type":"Services"
        }
    ],
    "sg:postcode":"S6 5LB",
    "sg:province":"South Yorkshire",
    "sg:tags":[
        "decorator",
        "painter"
    ],
    "wof:name":"D Guite",
    "wof:placetype":"venue"
},
  "geometry": {"coordinates":[-1.5272270441,53.3967704773],"type":"Point"}
}