{
  "type": "Feature",
  "properties": {
    "addr:full":"1 Alexandra Road Corby Northamptonshire NN17 1PE",
    "addr:housenumber":"1",
    "addr:postcode":"nn17 1pe",
    "addr:street":"Alexandra Road",
    "iso:country":"GB",
    "sg:address":"1 Alexandra Road",
    "sg:city":"Corby",
    "sg:classifiers":[
        {
            "category":"Professional",
            "subcategory":"Lawyer & Legal Services",
            "type":"Services"
        }
    ],
    "sg:phone":"+44 1536 276300",
    "sg:postcode":"NN17 1PE",
    "sg:province":"Northamptonshire",
    "sg:tags":[
        "solicitor"
    ],
    "wof:name":"Paul Seaton & Co.",
    "wof:placetype":"venue"
},
  "geometry": {"coordinates":[-0.703583,52.488953],"type":"Point"}
}