{
  "type": "Feature",
  "properties": {
    "iso:country":"GB",
    "sg:address":"10 Galgate",
    "sg:city":"Barnard Castle",
    "sg:classifiers":[
        {
            "category":"Shopping",
            "subcategory":"Florist",
            "type":"Retail Goods"
        }
    ],
    "sg:phone":"+44 1833 631972",
    "sg:postcode":"DL12 8BG",
    "sg:province":"Cumbria",
    "wof:name":"Richardsons",
    "wof:placetype":"venue"
},
  "geometry": {"coordinates":[-1.92475,54.544998],"type":"Point"}
}