{
  "type": "Feature",
  "properties": {
    "addr:full":"233 Abbey Rd Huddersfield South Yorkshire HD8 8EP",
    "addr:housenumber":"233",
    "addr:postcode":"hd8 8ep",
    "addr:street":"Abbey Rd",
    "iso:country":"GB",
    "sg:address":"233 Abbey Rd",
    "sg:city":"Huddersfield",
    "sg:classifiers":[
        {
            "category":"Personal",
            "subcategory":"Beauty Salon",
            "type":"Services"
        }
    ],
    "sg:phone":"+44 1484 602220",
    "sg:postcode":"HD8 8EP",
    "sg:province":"South Yorkshire",
    "sg:tags":[
        "unisex",
        "hairdresser"
    ],
    "wof:name":"Angela's Expressions Of Hair",
    "wof:placetype":"venue"
},
  "geometry": {"coordinates":[-1.703639,53.585999],"type":"Point"}
}