{
  "type": "Feature",
  "properties": {
    "addr:full":"1 Redver Gardens Newport Isle of Wight PO30 5JJ",
    "addr:housenumber":"1",
    "addr:postcode":"po30 5jj",
    "addr:street":"Redver Gardens",
    "iso:country":"GB",
    "sg:address":"1 Redver Gardens",
    "sg:city":"Newport",
    "sg:classifiers":[
        {
            "category":"Building & Trades",
            "subcategory":"Construction",
            "type":"Services"
        }
    ],
    "sg:phone":"+44 1983 526817",
    "sg:postcode":"PO30 5JJ",
    "sg:province":"Isle of Wight",
    "sg:tags":[
        "builder"
    ],
    "wof:name":"Jonathan Urry",
    "wof:placetype":"venue"
},
  "geometry": {"coordinates":[-1.29969,50.704758],"type":"Point"}
}