{
  "type": "Feature",
  "properties": {
    "addr:full":"43 Regent St Swindon Wiltshire SN1 1JS",
    "addr:housenumber":"43",
    "addr:postcode":"sn1 1js",
    "addr:street":"Regent St",
    "iso:country":"GB",
    "sg:address":"43 Regent St",
    "sg:city":"Swindon",
    "sg:classifiers":[
        {
            "category":"Home & Garden",
            "subcategory":"Household Appliances",
            "type":"Retail Goods"
        }
    ],
    "sg:phone":"+44 1793 431042",
    "sg:postcode":"SN1 1JS",
    "sg:province":"Wiltshire",
    "sg:tags":[
        "gas"
    ],
    "wof:name":"British Gas Energy Centre",
    "wof:placetype":"venue"
},
  "geometry": {"coordinates":[-1.782735,51.559456],"type":"Point"}
}