{
  "type": "Feature",
  "properties": {
    "addr:full":"Ivy House Farm, Withers Lane, High Legh Knutsford Cheshire WA16 0SG",
    "addr:postcode":"wa16 0sg",
    "addr:street":"Withers Lane",
    "iso:country":"GB",
    "sg:address":"Ivy House Farm, Withers Lane, High Legh",
    "sg:city":"Knutsford",
    "sg:classifiers":[
        {
            "category":"Farming",
            "subcategory":"Livestock Farm",
            "type":"Manufacturing & Wholesale Goods"
        }
    ],
    "sg:postcode":"WA16 0SG",
    "sg:province":"Cheshire",
    "sg:tags":[
        "others"
    ],
    "wof:name":"J R Priestner",
    "wof:placetype":"venue"
},
  "geometry": {"coordinates":[-2.37624,53.304203],"type":"Point"}
}