{
  "type": "Feature",
  "properties": {
    "iso:country":"GB",
    "sg:address":"207 Park Road East, Calverton",
    "sg:city":"Nottingham",
    "sg:classifiers":[
        {
            "category":"Manufacturing",
            "subcategory":"Apparel",
            "type":"Manufacturing & Wholesale Goods"
        }
    ],
    "sg:phone":"+44 115 952 4454",
    "sg:postcode":"NG14 6PS",
    "sg:province":"Nottinghamshire",
    "sg:tags":[
        "shirt",
        "maker"
    ],
    "wof:name":"Pronto Design Associates Ltd.",
    "wof:placetype":"venue"
},
  "geometry": {"coordinates":[-1.075212,53.038834],"type":"Point"}
}