{
  "type": "Feature",
  "properties": {
    "addr:full":"1 Butlers Drive Carterton Gloucestershire OX18 3QX",
    "addr:housenumber":"1",
    "addr:postcode":"ox18 3qx",
    "addr:street":"Butlers Drive",
    "iso:country":"GB",
    "sg:address":"1 Butlers Drive",
    "sg:city":"Carterton",
    "sg:classifiers":[
        {
            "category":"Personal",
            "type":"Services"
        }
    ],
    "sg:postcode":"OX18 3QX",
    "sg:province":"Gloucestershire",
    "sg:tags":[
        "wedding"
    ],
    "wof:name":"Dorann Gold Service",
    "wof:placetype":"venue"
},
  "geometry": {"coordinates":[-1.593804,51.757133],"type":"Point"}
}