{
  "type": "Feature",
  "properties": {
    "iso:country":"GB",
    "sg:address":"114 Galgate",
    "sg:city":"Barnard Castle",
    "sg:classifiers":[
        {
            "category":"Personal",
            "subcategory":"Beauty Salon",
            "type":"Services"
        },
        {
            "category":"Personal",
            "subcategory":"Barber",
            "type":"Services"
        }
    ],
    "sg:phone":"+44 1833 637153",
    "sg:postcode":"DL12 8BJ",
    "sg:province":"Cumbria",
    "sg:tags":[
        "unisex",
        "hairdresser"
    ],
    "wof:name":"Hair Studio",
    "wof:placetype":"venue"
},
  "geometry": {"coordinates":[-1.91941,54.547272],"type":"Point"}
}