{
  "type": "Feature",
  "properties": {
    "addr:full":"London Road Coalville Leicestershire LE67 3JE",
    "addr:postcode":"le67 3je",
    "addr:street":"London Road",
    "iso:country":"GB",
    "sg:address":"London Road",
    "sg:city":"Coalville",
    "sg:classifiers":[
        {
            "category":"Retail",
            "subcategory":"Event Space",
            "type":"Services"
        }
    ],
    "sg:phone":"+44 1530 832342",
    "sg:postcode":"LE67 3JE",
    "sg:province":"Leicestershire",
    "sg:tags":[
        "function",
        "room"
    ],
    "wof:name":"European Leisure Retail Ltd.",
    "wof:placetype":"venue"
},
  "geometry": {"coordinates":[-1.3681639433,52.7235488892],"type":"Point"}
}