{
  "type": "Feature",
  "properties": {
    "addr:full":"125 Queensway, Coney Hall West Wickham Kent BR4 9DT",
    "addr:housenumber":"125",
    "addr:postcode":"br4 9dt",
    "addr:street":"Queensway;West Wickham",
    "iso:country":"GB",
    "sg:address":"125 Queensway, Coney Hall",
    "sg:city":"West Wickham",
    "sg:classifiers":[
        {
            "category":"Building & Trades",
            "subcategory":"Construction",
            "type":"Services"
        }
    ],
    "sg:postcode":"BR4 9DT",
    "sg:province":"Kent",
    "sg:tags":[
        "glazier"
    ],
    "wof:name":"Richmond,David,",
    "wof:placetype":"venue"
},
  "geometry": {"coordinates":[0.0067960001,51.3657951355],"type":"Point"}
}