{
  "type": "Feature",
  "properties": {
    "addr:full":"421 King Street, Fenton Stoke-on-trent Staffordshire ST4 3EE",
    "addr:housenumber":"421",
    "addr:postcode":"staffordshire st4 3ee",
    "addr:street":"King Street",
    "iso:country":"GB",
    "sg:address":"421 King Street, Fenton",
    "sg:city":"Stoke-on-trent",
    "sg:classifiers":[
        {
            "category":"Banks & Credit Unions",
            "subcategory":"Financial Services",
            "type":"Services"
        }
    ],
    "sg:phone":"+44 1782 334180",
    "sg:postcode":"ST4 3EE",
    "sg:province":"Staffordshire",
    "sg:tags":[
        "consultant"
    ],
    "wof:name":"Six Towns Finance Ltd.",
    "wof:placetype":"venue"
},
  "geometry": {"coordinates":[-2.1420021057,52.9928970337],"type":"Point"}
}