{
  "type": "Feature",
  "properties": {
    "addr:full":"7 Reynolds Road Ipswich Suffolk IP3 0JL",
    "addr:housenumber":"7",
    "addr:postcode":"ip3 0jl",
    "addr:street":"Reynolds Road",
    "iso:country":"GB",
    "sg:address":"7 Reynolds Road",
    "sg:city":"Ipswich",
    "sg:classifiers":[
        {
            "category":"Organizations",
            "subcategory":"Non-profit Organization",
            "type":"Services"
        }
    ],
    "sg:postcode":"IP3 0JL",
    "sg:province":"Suffolk",
    "sg:tags":[
        "organisation",
        "voluntary",
        "charity"
    ],
    "wof:name":"Jumble Land",
    "wof:placetype":"venue"
},
  "geometry": {"coordinates":[1.179838,52.035728],"type":"Point"}
}