{
  "type": "Feature",
  "properties": {
    "addr:full":"Unit 1 Holywell Business Centre, Osney Mead Oxford Oxfordshire OX2 0ES",
    "addr:housenumber":"unit 1",
    "addr:postcode":"ox2 0es",
    "addr:street":"Holywell Business Centre Osney Mead",
    "iso:country":"GB",
    "sg:address":"Unit 1 Holywell Business Centre, Osney Mead",
    "sg:city":"Oxford",
    "sg:classifiers":[
        {
            "category":"Professional",
            "subcategory":"Engineering",
            "type":"Services"
        }
    ],
    "sg:phone":"+44 1865 798338",
    "sg:postcode":"OX2 0ES",
    "sg:province":"Oxfordshire",
    "sg:tags":[
        "precision",
        "engineer"
    ],
    "wof:name":"Oxford Precision Components",
    "wof:placetype":"venue"
},
  "geometry": {"coordinates":[-1.27358,51.748501],"type":"Point"}
}