{
  "type": "Feature",
  "properties": {
    "addr:full":"88 Queen Victoria Road Llanelli Carmarthenshire SA15 2TH",
    "addr:housenumber":"88",
    "addr:postcode":"sa15 2th",
    "addr:street":"Queen Victoria Road",
    "iso:country":"GB",
    "sg:address":"88 Queen Victoria Road",
    "sg:city":"Llanelli",
    "sg:classifiers":[
        {
            "category":"Health Services",
            "subcategory":"Nursing And Care Facility",
            "type":"Services"
        }
    ],
    "sg:phone":"+44 1554 741703",
    "sg:postcode":"SA15 2TH",
    "sg:province":"Carmarthenshire",
    "sg:tags":[
        "home",
        "residential"
    ],
    "wof:name":"St Eili Nursing Home",
    "wof:placetype":"venue"
},
  "geometry": {"coordinates":[-4.1682472229,51.6775588989],"type":"Point"}
}