{
  "type": "Feature",
  "properties": {
    "addr:full":"11 Fulmar Close, Bowerhill Melksham Wiltshire SN12 6XU",
    "addr:housenumber":"11",
    "addr:postcode":"sn12 6xu",
    "addr:street":"Fulmar Close",
    "iso:country":"GB",
    "sg:address":"11 Fulmar Close, Bowerhill",
    "sg:city":"Melksham",
    "sg:classifiers":[
        {
            "category":"Professional",
            "subcategory":"Engineering",
            "type":"Services"
        },
        {
            "category":"Building & Trades",
            "subcategory":"Electrical",
            "type":"Services"
        }
    ],
    "sg:phone":"+44 1225 706637",
    "sg:postcode":"SN12 6XU",
    "sg:province":"Wiltshire",
    "sg:tags":[
        "engineer",
        "electrician",
        "contractor"
    ],
    "wof:name":"Michael Morley",
    "wof:placetype":"venue"
},
  "geometry": {"coordinates":[-2.120743,51.359413],"type":"Point"}
}