{
  "type": "Feature",
  "properties": {
    "addr:full":"46 High Street Bristol City of Bristol BS15 4NF",
    "addr:housenumber":"46",
    "addr:postcode":"bs15 4nf",
    "addr:street":"High Street",
    "iso:country":"GB",
    "sg:address":"46 High Street",
    "sg:city":"Bristol",
    "sg:classifiers":[
        {
            "category":"Bars & Pubs",
            "type":"Food & Drink"
        }
    ],
    "sg:phone":"+44 117 961 5198",
    "sg:postcode":"BS15 4NF",
    "sg:province":"City of Bristol",
    "sg:tags":[
        "pubs",
        "inn"
    ],
    "wof:name":"Station Master",
    "wof:placetype":"venue"
},
  "geometry": {"coordinates":[-2.4760200977,51.4597816467],"type":"Point"}
}