{
  "type": "Feature",
  "properties": {
    "iso:country":"GB",
    "sg:address":"11 Pigeonwick",
    "sg:city":"Harpenden",
    "sg:classifiers":[
        {
            "category":"Shopping",
            "subcategory":"Pharmacy",
            "type":"Retail Goods"
        }
    ],
    "sg:postcode":"AL5 4EZ",
    "sg:province":"Hertfordshire",
    "sg:tags":[
        "medicine",
        "therapy"
    ],
    "wof:name":"Anneli Densham",
    "wof:placetype":"venue"
},
  "geometry": {"coordinates":[-0.354377,51.822987],"type":"Point"}
}