{
  "type": "Feature",
  "properties": {
    "addr:full":"Tile Farm, Benjy Lane, Wheldrake York North Yorkshire YO19 6BH",
    "addr:postcode":"yo19 6bh",
    "addr:street":"Tile;Benjy Lane",
    "iso:country":"GB",
    "sg:address":"Tile Farm, Benjy Lane, Wheldrake",
    "sg:city":"York",
    "sg:classifiers":[
        {
            "category":"Home & Garden",
            "subcategory":"Carpets & Floor Coverings",
            "type":"Retail Goods"
        }
    ],
    "sg:phone":"+44 1757 270111",
    "sg:postcode":"YO19 6BH",
    "sg:province":"North Yorkshire",
    "sg:tags":[
        "carpets",
        "rug",
        "matting"
    ],
    "wof:name":"M L Noblett & Son",
    "wof:placetype":"venue"
},
  "geometry": {"coordinates":[-0.965982,53.89603],"type":"Point"}
}