{
  "type": "Feature",
  "properties": {
    "addr:full":"The Cottage, Green Walk, Bowdon Altrincham Cheshire WA14 2SJ",
    "addr:postcode":"wa14 2sj",
    "addr:street":"Green Walk",
    "iso:country":"GB",
    "sg:address":"The Cottage, Green Walk, Bowdon",
    "sg:city":"Altrincham",
    "sg:classifiers":[
        {
            "category":"Shopping",
            "subcategory":"Photographic Equipment",
            "type":"Retail Goods"
        }
    ],
    "sg:phone":"+44 161 929 6575",
    "sg:postcode":"WA14 2SJ",
    "sg:province":"Cheshire",
    "wof:name":"Studio Associates",
    "wof:placetype":"venue"
},
  "geometry": {"coordinates":[-2.3656699657,53.3789710999],"type":"Point"}
}