{
  "type": "Feature",
  "properties": {
    "iso:country":"GB",
    "sg:address":"26 Blake Road",
    "sg:city":"Great Yarmouth",
    "sg:classifiers":[
        {
            "category":"Social Services",
            "subcategory":"Adult Care",
            "type":"Services"
        },
        {
            "category":"Government",
            "subcategory":"Office",
            "type":"Public Place"
        }
    ],
    "sg:phone":"+44 1493 330369",
    "sg:postcode":"NR30 4LT",
    "sg:province":"Norfolk",
    "sg:tags":[
        "housing",
        "local",
        "sheltered"
    ],
    "wof:name":"Maygrove Estate Sheltered Housing",
    "wof:placetype":"venue"
},
  "geometry": {"coordinates":[1.7357039452,52.6210708618],"type":"Point"}
}