{
  "type": "Feature",
  "properties": {
    "addr:full":"75 Farmlands Pinner Greater London HA5 2LJ",
    "addr:housenumber":"75",
    "addr:postcode":"ha5 2lj",
    "addr:street":"Farmlands",
    "iso:country":"GB",
    "sg:address":"75 Farmlands",
    "sg:city":"Pinner",
    "sg:classifiers":[
        {
            "category":"Social Services",
            "subcategory":"Adult Care",
            "type":"Services"
        },
        {
            "category":"Social Services",
            "subcategory":"Retirement Home",
            "type":"Services"
        }
    ],
    "sg:phone":"+44 20 8868 7042",
    "sg:postcode":"HA5 2LJ",
    "sg:province":"Greater London",
    "sg:tags":[
        "housing",
        "sheltered",
        "accommodation"
    ],
    "wof:name":"Ascott Court",
    "wof:placetype":"venue"
},
  "geometry": {"coordinates":[-0.4080690145,51.591381073],"type":"Point"}
}