{
  "type": "Feature",
  "properties": {
    "addr:full":"42 Chancellor Street Glasgow Glasgow City G11 5QN",
    "addr:housenumber":"42",
    "addr:postcode":"g11 5qn",
    "addr:street":"Chancellor Street",
    "iso:country":"GB",
    "sg:address":"42 Chancellor Street",
    "sg:city":"Glasgow",
    "sg:classifiers":[
        {
            "category":"Education",
            "subcategory":"School",
            "type":"Public Place"
        },
        {
            "category":"Government",
            "subcategory":"Office",
            "type":"Public Place"
        }
    ],
    "sg:phone":"+44 141 339 1989",
    "sg:postcode":"G11 5QN",
    "sg:province":"Glasgow City",
    "sg:tags":[
        "local",
        "authority"
    ],
    "wof:name":"St Peters R C Primary School",
    "wof:placetype":"venue"
},
  "geometry": {"coordinates":[-4.300379,55.87207],"type":"Point"}
}