{
  "type": "Feature",
  "properties": {
    "addr:full":"5-7 Hoxton Road Scarborough North Yorkshire YO12 7ST",
    "addr:housenumber":"5-7",
    "addr:postcode":"yo12 7st",
    "addr:street":"Hoxton Road",
    "iso:country":"GB",
    "sg:address":"5-7 Hoxton Road",
    "sg:city":"Scarborough",
    "sg:classifiers":[
        {
            "category":"Autos & Motor Vehicles",
            "subcategory":"Motorcycle Sales",
            "type":"Retail Goods"
        }
    ],
    "sg:phone":"+44 1723 367660",
    "sg:postcode":"YO12 7ST",
    "sg:province":"North Yorkshire",
    "wof:name":"Andy Noble Motor Cycles",
    "wof:placetype":"venue"
},
  "geometry": {"coordinates":[-0.4056429863,54.2832756042],"type":"Point"}
}