{
  "type": "Feature",
  "properties": {
    "iso:country":"GB",
    "sg:address":"Summer Bridge",
    "sg:city":"Exeter",
    "sg:classifiers":[
        {
            "category":"Farming",
            "subcategory":"Dairy Farm",
            "type":"Manufacturing & Wholesale Goods"
        }
    ],
    "sg:phone":"+44 1404 822458",
    "sg:postcode":"EX5 2NY",
    "sg:province":"Devon",
    "wof:name":"Sommerbridge Farm Foods",
    "wof:placetype":"venue"
},
  "geometry": {"coordinates":[-3.4930210114,50.7376594543],"type":"Point"}
}