{
  "type": "Feature",
  "properties": {
    "addr:full":"The City Mill, 1 Water Lane Winchester Hampshire SO23 0EJ",
    "addr:housenumber":"1",
    "addr:postcode":"so23 0ej",
    "addr:street":"Water Lane",
    "iso:country":"GB",
    "sg:address":"The City Mill, 1 Water Lane",
    "sg:city":"Winchester",
    "sg:classifiers":[
        {
            "category":"Travel",
            "subcategory":"Hostel",
            "type":"Entertainment"
        }
    ],
    "sg:phone":"+44 1962 853723",
    "sg:postcode":"SO23 0EJ",
    "sg:province":"Hampshire",
    "sg:tags":[
        "youth"
    ],
    "wof:name":"Winchester Youth Hostel",
    "wof:placetype":"venue"
},
  "geometry": {"coordinates":[-1.3168090582,51.0630683899],"type":"Point"}
}