{
  "type": "Feature",
  "properties": {
    "addr:full":"9 River Gardens Carshalton Surrey SM5 2NH",
    "addr:housenumber":"9",
    "addr:postcode":"sm5 2nh",
    "addr:street":"River Gardens",
    "iso:country":"GB",
    "sg:address":"9 River Gardens",
    "sg:city":"Carshalton",
    "sg:classifiers":[
        {
            "category":"Building & Trades",
            "subcategory":"Landscaping Services",
            "type":"Services"
        }
    ],
    "sg:phone":"+44 20 8647 5929",
    "sg:postcode":"SM5 2NH",
    "sg:province":"Surrey",
    "sg:tags":[
        "landscape",
        "contractor"
    ],
    "wof:name":"J Coyle & Son",
    "wof:placetype":"venue"
},
  "geometry": {"coordinates":[-0.15947,51.373135],"type":"Point"}
}