{
  "type": "Feature",
  "properties": {
    "addr:full":"17 Riverside Close, Kingsnorth Ashford Kent TN23 3EL",
    "addr:housenumber":"17",
    "addr:postcode":"tn23 3el",
    "addr:street":"Riverside Close",
    "iso:country":"GB",
    "sg:address":"17 Riverside Close, Kingsnorth",
    "sg:city":"Ashford",
    "sg:classifiers":[
        {
            "category":"Home & Garden",
            "subcategory":"Household Appliances",
            "type":"Retail Goods"
        }
    ],
    "sg:phone":"+44 1233 631545",
    "sg:postcode":"TN23 3EL",
    "sg:province":"Kent",
    "sg:tags":[
        "electrical"
    ],
    "wof:name":"Freezecure",
    "wof:placetype":"venue"
},
  "geometry": {"coordinates":[0.8577359915,51.1202087402],"type":"Point"}
}