{
  "type": "Feature",
  "properties": {
    "iso:country":"GB",
    "sg:address":"333 Chester Road, Castle Bromwich",
    "sg:city":"Birmingham",
    "sg:classifiers":[
        {
            "category":"Real Estate",
            "subcategory":"Real Estate Agent",
            "type":"Services"
        }
    ],
    "sg:phone":"+44 121 749 4848",
    "sg:postcode":"B36 0JG",
    "sg:province":"West Midlands",
    "wof:name":"Dixons",
    "wof:placetype":"venue"
},
  "geometry": {"coordinates":[-1.761439,52.501396],"type":"Point"}
}