{
  "type": "Feature",
  "properties": {
    "addr:full":"4 Shide Road Newport Isle of Wight PO30 1YQ",
    "addr:housenumber":"4",
    "addr:postcode":"po30 1yq",
    "addr:street":"Shide Road",
    "iso:country":"GB",
    "sg:address":"4 Shide Road",
    "sg:city":"Newport",
    "sg:classifiers":[
        {
            "category":"Organizations",
            "subcategory":"Non-profit Organization",
            "type":"Services"
        }
    ],
    "sg:phone":"+44 1983 521511",
    "sg:postcode":"PO30 1YQ",
    "sg:province":"Isle of Wight",
    "sg:tags":[
        "organisation",
        "voluntary",
        "charity"
    ],
    "wof:name":"Isle of Wight Healthcare N H S Trust",
    "wof:placetype":"venue"
},
  "geometry": {"coordinates":[-1.292861,50.692268],"type":"Point"}
}