{
  "type": "Feature",
  "properties": {
    "addr:full":"29-31 Station Road South, Padgate Warrington Cheshire WA2 0PD",
    "addr:housenumber":"29-31",
    "addr:postcode":"wa2 0pd",
    "addr:street":"Station Road South Padgate",
    "iso:country":"GB",
    "sg:address":"29-31 Station Road South, Padgate",
    "sg:city":"Warrington",
    "sg:classifiers":[
        {
            "category":"Restaurant",
            "type":"Food & Drink"
        }
    ],
    "sg:phone":"+44 1925 633988",
    "sg:postcode":"WA2 0PD",
    "sg:province":"Cheshire",
    "sg:tags":[
        "chinese"
    ],
    "wof:name":"The Padgate Rose Restaurant",
    "wof:placetype":"venue"
},
  "geometry": {"coordinates":[-2.5561800003,53.4075813293],"type":"Point"}
}