{
  "type": "Feature",
  "properties": {
    "addr:full":"Unit 9 Iron Bridge House, Bridge App London Greater London NW1 8BD",
    "addr:housenumber":"unit 9",
    "addr:postcode":"nw1 8bd",
    "addr:street":"Iron;Bridge",
    "iso:country":"GB",
    "sg:address":"Unit 9 Iron Bridge House, Bridge App",
    "sg:city":"London",
    "sg:classifiers":[
        {
            "category":"Professional",
            "subcategory":"Business Services",
            "type":"Services"
        }
    ],
    "sg:phone":"+44 20 7586 3854",
    "sg:postcode":"NW1 8BD",
    "sg:province":"Greater London",
    "sg:tags":[
        "import",
        "export",
        "agent"
    ],
    "wof:name":"Catic Trading Development (U K) Ltd.",
    "wof:placetype":"venue"
},
  "geometry": {"coordinates":[-0.154879,51.543606],"type":"Point"}
}