{
  "type": "Feature",
  "properties": {
    "iso:country":"GB",
    "sg:address":"Ascot Road, Bedfont",
    "sg:city":"Feltham",
    "sg:classifiers":[
        {
            "category":"Freight",
            "type":"Transportation"
        }
    ],
    "sg:phone":"+44 1784 244408",
    "sg:postcode":"TW14 8QH",
    "sg:province":"Greater London",
    "sg:tags":[
        "forwarders"
    ],
    "wof:name":"S D B Airfreight",
    "wof:placetype":"venue"
},
  "geometry": {"coordinates":[-0.4445640147,51.449848175],"type":"Point"}
}