{
  "type": "Feature",
  "properties": {
    "addr:full":"41 Park Square North Leeds West Yorkshire LS1 2NS",
    "addr:housenumber":"41",
    "addr:postcode":"ls1 2ns",
    "addr:street":"Park Square North Leeds West",
    "iso:country":"GB",
    "sg:address":"41 Park Square North",
    "sg:city":"Leeds",
    "sg:classifiers":[
        {
            "category":"Banks & Credit Unions",
            "subcategory":"Financial Services",
            "type":"Services"
        }
    ],
    "sg:postcode":"LS1 2NS",
    "sg:province":"West Yorkshire",
    "sg:tags":[
        "consultant"
    ],
    "wof:name":"Pinsent Curtis Independent Trustees Ltd",
    "wof:placetype":"venue"
},
  "geometry": {"coordinates":[-1.5516320467,53.7992973328],"type":"Point"}
}