{
  "type": "Feature",
  "properties": {
    "iso:country":"GB",
    "sg:address":"47 East St",
    "sg:city":"Bridport",
    "sg:classifiers":[
        {
            "category":"Shopping",
            "subcategory":"Musical Instruments",
            "type":"Retail Goods"
        }
    ],
    "sg:phone":"+44 1308 427712",
    "sg:postcode":"DT6 3JX",
    "sg:province":"Dorset",
    "wof:name":"Harmony & Marland Music",
    "wof:placetype":"venue"
},
  "geometry": {"coordinates":[-2.7558469772,50.7334327698],"type":"Point"}
}