{
  "type": "Feature",
  "properties": {
    "iso:country":"GB",
    "sg:address":"Hemplow, Marsden",
    "sg:city":"Huddersfield",
    "sg:classifiers":[
        {
            "category":"Arena",
            "subcategory":"Sports Club",
            "type":"Entertainment"
        }
    ],
    "sg:phone":"+44 1484 844243",
    "sg:postcode":"HD7 6AF",
    "sg:province":"West Yorkshire",
    "wof:name":"Marsden Cricket & Bowling Club",
    "wof:placetype":"venue"
},
  "geometry": {"coordinates":[-1.9212440252,53.6021385193],"type":"Point"}
}