{
  "type": "Feature",
  "properties": {
    "iso:country":"GB",
    "sg:address":"19 Phillip Street, Manselton",
    "sg:city":"Swansea",
    "sg:classifiers":[
        {
            "category":"Retail",
            "subcategory":"Driving School",
            "type":"Services"
        }
    ],
    "sg:phone":"+44 1792 895810",
    "sg:postcode":"SA5 9NL",
    "sg:province":"Swansea",
    "wof:name":"Cymdu School of Motoring",
    "wof:placetype":"venue"
},
  "geometry": {"coordinates":[-3.9478979111,51.6378707886],"type":"Point"}
}