{
  "type": "Feature",
  "properties": {
    "iso:country":"GB",
    "sg:address":"Wallsend Business Centre, 6 - 10 Coach Road",
    "sg:city":"Wallsend",
    "sg:classifiers":[
        {
            "category":"Building & Trades",
            "subcategory":"Construction",
            "type":"Services"
        }
    ],
    "sg:phone":"+44 191 263 7154",
    "sg:postcode":"NE28 6JA",
    "sg:province":"Tyne and Wear",
    "sg:tags":[
        "dry",
        "lining",
        "plasterers",
        "screeders"
    ],
    "wof:name":"Anson Plastering Co. Ltd.",
    "wof:placetype":"venue"
},
  "geometry": {"coordinates":[-1.52518,54.991245],"type":"Point"}
}