{
  "type": "Feature",
  "properties": {
    "iso:country":"GB",
    "sg:address":"4 Chiltern Court, Back Street, Wendover",
    "sg:city":"Aylesbury",
    "sg:classifiers":[
        {
            "category":"Real Estate",
            "subcategory":"Real Estate Agent",
            "type":"Services"
        }
    ],
    "sg:phone":"+44 1296 622911",
    "sg:postcode":"HP22 6EP",
    "sg:province":"Buckinghamshire",
    "wof:name":"Martin Kemp",
    "wof:placetype":"venue"
},
  "geometry": {"coordinates":[-0.746255,51.76619],"type":"Point"}
}