{
  "type": "Feature",
  "properties": {
    "addr:full":"1 Malden Road, Cheam Sutton Surrey SM3 8QD",
    "addr:housenumber":"1",
    "addr:postcode":"sm3 8qd",
    "addr:street":"Malden Road",
    "iso:country":"GB",
    "sg:address":"1 Malden Road, Cheam",
    "sg:city":"Sutton",
    "sg:classifiers":[
        {
            "category":"Government",
            "subcategory":"Office",
            "type":"Public Place"
        },
        {
            "category":"Landmark",
            "subcategory":"Tourist Attraction",
            "type":"Public Place"
        }
    ],
    "sg:phone":"+44 20 8643 1236",
    "sg:postcode":"SM3 8QD",
    "sg:province":"Surrey",
    "sg:tags":[
        "local",
        "interest"
    ],
    "wof:name":"Whitehall",
    "wof:placetype":"venue"
},
  "geometry": {"coordinates":[-0.217039004,51.3594360352],"type":"Point"}
}