{
  "type": "Feature",
  "properties": {
    "iso:country":"GB",
    "sg:address":"288 Northwich Road, Hartford",
    "sg:city":"Northwich",
    "sg:classifiers":[
        {
            "category":"Building & Trades",
            "subcategory":"Construction",
            "type":"Services"
        }
    ],
    "sg:phone":"+44 1606 75807",
    "sg:postcode":"CW8 3AL",
    "sg:province":"Cheshire",
    "sg:tags":[
        "decorator",
        "painter"
    ],
    "wof:name":"Michael Leigh",
    "wof:placetype":"venue"
},
  "geometry": {"coordinates":[-2.553606,53.250416],"type":"Point"}
}