{
  "type": "Feature",
  "properties": {
    "iso:country":"GB",
    "sg:address":"56 Catley Road",
    "sg:city":"Sheffield",
    "sg:classifiers":[
        {
            "category":"Shopping",
            "subcategory":"Stationery & Office Supplies",
            "type":"Retail Goods"
        }
    ],
    "sg:phone":"+44 114 243 0773",
    "sg:postcode":"S9 5JF",
    "sg:province":"South Yorkshire",
    "sg:tags":[
        "printers'"
    ],
    "wof:name":"Aftaprint Ltd.",
    "wof:placetype":"venue"
},
  "geometry": {"coordinates":[-1.403853,53.388615],"type":"Point"}
}