{
  "type": "Feature",
  "properties": {
    "iso:country":"GB",
    "sg:address":"4a Churchill Way",
    "sg:city":"Cardiff",
    "sg:classifiers":[
        {
            "category":"Banks & Credit Unions",
            "subcategory":"Financial Services",
            "type":"Services"
        }
    ],
    "sg:phone":"+44 29 2037 2730",
    "sg:postcode":"CF10 2DW",
    "sg:province":"Cardiff",
    "sg:tags":[
        "building",
        "society"
    ],
    "wof:name":"Leeds & Holbeck Building Society",
    "wof:placetype":"venue"
},
  "geometry": {"coordinates":[-3.1733529568,51.4822654724],"type":"Point"}
}