{
  "type": "Feature",
  "properties": {
    "iso:country":"GB",
    "sg:address":"94 Mitcham Road, Tooting",
    "sg:city":"London",
    "sg:classifiers":[
        {
            "category":"Shopping",
            "subcategory":"Stationery & Office Supplies",
            "type":"Retail Goods"
        },
        {
            "category":"Arts & Performance",
            "subcategory":"Arts Center",
            "type":"Entertainment"
        }
    ],
    "sg:phone":"+44 20 8767 5149",
    "sg:postcode":"SW17 9NG",
    "sg:province":"Greater London",
    "sg:tags":[
        "centre"
    ],
    "wof:name":"K & K Stationers & Printers Ltd.",
    "wof:placetype":"venue"
},
  "geometry": {"coordinates":[-0.165432,51.425732],"type":"Point"}
}