{
  "type": "Feature",
  "properties": {
    "addr:full":"Old Library Centre, 65 Ombersley Street East, Droitwich Spa Droitwich Worcestershire WR9 8QS",
    "addr:housenumber":"65",
    "addr:postcode":"wr9 8qs",
    "addr:street":"Ombersley Street East",
    "iso:country":"GB",
    "sg:address":"Old Library Centre, 65 Ombersley Street East, Droitwich Spa",
    "sg:city":"Droitwich",
    "sg:classifiers":[
        {
            "category":"Organizations",
            "subcategory":"Non-profit Organization",
            "type":"Services"
        }
    ],
    "sg:phone":"+44 1905 795613",
    "sg:postcode":"WR9 8QS",
    "sg:province":"Worcestershire",
    "sg:tags":[
        "organisation",
        "voluntary",
        "charity"
    ],
    "wof:name":"Volunteer Development England",
    "wof:placetype":"venue"
},
  "geometry": {"coordinates":[-2.156488,52.268078],"type":"Point"}
}