{
  "type": "Feature",
  "properties": {
    "addr:full":"53 Priory Rd Hungerford Berkshire RG17 0AW",
    "addr:housenumber":"53",
    "addr:postcode":"rg17 0aw",
    "addr:street":"Priory Rd",
    "iso:country":"GB",
    "sg:address":"53 Priory Rd",
    "sg:city":"Hungerford",
    "sg:classifiers":[
        {
            "category":"Professional",
            "subcategory":"Art Services",
            "type":"Services"
        }
    ],
    "sg:phone":"+44 1488 683566",
    "sg:postcode":"RG17 0AW",
    "sg:province":"Berkshire",
    "sg:tags":[
        "graphic",
        "designer"
    ],
    "wof:name":"Viewpoint Design",
    "wof:placetype":"venue"
},
  "geometry": {"coordinates":[-1.5171240568,51.4081268311],"type":"Point"}
}