{
  "type": "Feature",
  "properties": {
    "addr:full":"Suez St, New Basford Nottingham Nottinghamshire NG7 7GB",
    "addr:postcode":"ng7 7gb",
    "addr:street":"Suez St",
    "iso:country":"GB",
    "sg:address":"Suez St, New Basford",
    "sg:city":"Nottingham",
    "sg:classifiers":[
        {
            "category":"Education",
            "subcategory":"School",
            "type":"Public Place"
        }
    ],
    "sg:phone":"+44 115 915 6896",
    "sg:postcode":"NG7 7GB",
    "sg:province":"Nottinghamshire",
    "sg:tags":[
        "local",
        "authority"
    ],
    "wof:name":"Northgate Primary School",
    "wof:placetype":"venue"
},
  "geometry": {"coordinates":[-1.1713839769,52.9759254456],"type":"Point"}
}