{
  "type": "Feature",
  "properties": {
    "addr:full":"Old School La Coalville Leicestershire LE67 1DB",
    "addr:postcode":"le67 1db",
    "addr:street":"La;Leicestershire",
    "iso:country":"GB",
    "sg:address":"Old School La",
    "sg:city":"Coalville",
    "sg:classifiers":[
        {
            "category":"Place Of Worship",
            "type":"Public Place"
        }
    ],
    "sg:phone":"+44 1530 242844",
    "sg:postcode":"LE67 1DB",
    "sg:province":"Leicestershire",
    "wof:name":"Holy Rood Church The",
    "wof:placetype":"venue"
},
  "geometry": {"coordinates":[-1.3648389578,52.6940536499],"type":"Point"}
}