{
  "type": "Feature",
  "properties": {
    "addr:full":"270 Upper Street, Islington London Greater London N1 2UH",
    "addr:housenumber":"270",
    "addr:postcode":"n1 2uh",
    "addr:street":"Upper Street",
    "iso:country":"GB",
    "sg:address":"270 Upper Street, Islington",
    "sg:city":"London",
    "sg:classifiers":[
        {
            "category":"Restaurant",
            "type":"Food & Drink"
        }
    ],
    "sg:phone":"+44 20 7226 1118",
    "sg:postcode":"N1 2UH",
    "sg:province":"Greater London",
    "sg:tags":[
        "oriental"
    ],
    "wof:name":"Tiger Lil's",
    "wof:placetype":"venue"
},
  "geometry": {"coordinates":[-0.1031690016,51.5459098816],"type":"Point"}
}