{
  "type": "Feature",
  "properties": {
    "addr:full":"12 Pontypridd Street Barry The Vale of Glamorgan CF63 2HH",
    "addr:housenumber":"12",
    "addr:postcode":"cf63 2hh",
    "addr:street":"Pontypridd Street;Vale",
    "iso:country":"GB",
    "sg:address":"12 Pontypridd Street",
    "sg:city":"Barry",
    "sg:classifiers":[
        {
            "category":"Professional",
            "subcategory":"Accounting & Tax Preparation",
            "type":"Services"
        }
    ],
    "sg:phone":"+44 1446 701110",
    "sg:postcode":"CF63 2HH",
    "sg:province":"The Vale of Glamorgan",
    "sg:tags":[
        "accountant",
        "bookkeeping",
        "primarily",
        "activity"
    ],
    "wof:name":"Philip  Jones",
    "wof:placetype":"venue"
},
  "geometry": {"coordinates":[-3.254588,51.412384],"type":"Point"}
}