{
  "type": "Feature",
  "properties": {
    "addr:full":"School Farm, Dartington Totnes Devon TQ9 6EB",
    "addr:postcode":"tq9 6eb",
    "iso:country":"GB",
    "sg:address":"School Farm, Dartington",
    "sg:city":"Totnes",
    "sg:classifiers":[
        {
            "category":"Education",
            "subcategory":"Special Training",
            "type":"Public Place"
        }
    ],
    "sg:phone":"+44 1803 867693",
    "sg:postcode":"TQ9 6EB",
    "sg:province":"Devon",
    "sg:tags":[
        "product",
        "centre"
    ],
    "wof:name":"Dartington Tech",
    "wof:placetype":"venue"
},
  "geometry": {"coordinates":[-3.7128589153,50.4455604553],"type":"Point"}
}