{
  "type": "Feature",
  "properties": {
    "iso:country":"GB",
    "sg:address":"Raglan House, Unit R1 St Peter Street",
    "sg:city":"Maidstone",
    "sg:classifiers":[
        {
            "category":"Manufacturing",
            "subcategory":"Jewelry",
            "type":"Manufacturing & Wholesale Goods"
        }
    ],
    "sg:phone":"+44 1622 753431",
    "sg:postcode":"ME16 0SN",
    "sg:province":"Kent",
    "sg:tags":[
        "manufacture",
        "repair",
        "jewellery"
    ],
    "wof:name":"Kent Jewellery Services",
    "wof:placetype":"venue"
},
  "geometry": {"coordinates":[0.5136150122,51.2772789001],"type":"Point"}
}