{
  "type": "Feature",
  "properties": {
    "addr:full":"Rockrose Rest Home, 10 Kingsfield Road Herne Bay Kent CT6 7EA",
    "addr:housenumber":"10",
    "addr:postcode":"ct6 7ea",
    "addr:street":"Kingsfield Road",
    "iso:country":"GB",
    "sg:address":"Rockrose Rest Home, 10 Kingsfield Road",
    "sg:city":"Herne Bay",
    "sg:classifiers":[
        {
            "category":"Social Services",
            "subcategory":"Retirement Home",
            "type":"Services"
        }
    ],
    "sg:phone":"+44 1227 740549",
    "sg:postcode":"CT6 7EA",
    "sg:province":"Kent",
    "sg:tags":[
        "rest"
    ],
    "wof:name":"Rockrose Rest Home",
    "wof:placetype":"venue"
},
  "geometry": {"coordinates":[1.142986,51.358826],"type":"Point"}
}