{
  "type": "Feature",
  "properties": {
    "iso:country":"GB",
    "sg:address":"Bell Meadow Yard, Watling St, Hockliffe",
    "sg:city":"Leighton Buzzard",
    "sg:classifiers":[
        {
            "category":"Retail",
            "subcategory":"Auto Repair",
            "type":"Services"
        }
    ],
    "sg:phone":"+44 1525 211121",
    "sg:postcode":"LU7 9NA",
    "sg:province":"Bedfordshire",
    "sg:tags":[
        "modification",
        "garage"
    ],
    "wof:name":"Chapman Auto Engineering",
    "wof:placetype":"venue"
},
  "geometry": {"coordinates":[-0.585949,51.932377],"type":"Point"}
}