{
  "type": "Feature",
  "properties": {
    "addr:full":"Mill Lane, Croughton Brackley Buckinghamshire NN13 5LU",
    "addr:postcode":"nn13 5lu",
    "addr:street":"Mill Lane",
    "iso:country":"GB",
    "sg:address":"Mill Lane, Croughton",
    "sg:city":"Brackley",
    "sg:classifiers":[
        {
            "category":"Building & Trades",
            "subcategory":"Construction",
            "type":"Services"
        }
    ],
    "sg:phone":"+44 1869 810260",
    "sg:postcode":"NN13 5LU",
    "sg:province":"Buckinghamshire",
    "sg:tags":[
        "builder"
    ],
    "wof:name":"Robco-Reed Ltd.",
    "wof:placetype":"venue"
},
  "geometry": {"coordinates":[-1.207046032,51.9983291626],"type":"Point"}
}