{
  "type": "Feature",
  "properties": {
    "addr:full":"82 Anerley Road, Upper Norwood London Greater London SE19 2AH",
    "addr:housenumber":"82",
    "addr:postcode":"se19 2ah",
    "addr:street":"Anerley Road",
    "iso:country":"GB",
    "sg:address":"82 Anerley Road, Upper Norwood",
    "sg:city":"London",
    "sg:classifiers":[
        {
            "category":"Shopping",
            "subcategory":"News",
            "type":"Retail Goods"
        }
    ],
    "sg:phone":"+44 20 8778 8641",
    "sg:postcode":"SE19 2AH",
    "sg:province":"Greater London",
    "sg:tags":[
        "newsagent"
    ],
    "wof:name":"Shillings News",
    "wof:placetype":"venue"
},
  "geometry": {"coordinates":[-0.0734099969,51.4168319702],"type":"Point"}
}