{
  "type": "Feature",
  "properties": {
    "iso:country":"GB",
    "sg:address":"Deeway, West Quey Rd",
    "sg:city":"Poole",
    "sg:classifiers":[
        {
            "category":"Recreation",
            "subcategory":"Marina",
            "type":"Entertainment"
        }
    ],
    "sg:phone":"+44 1202 680522",
    "sg:postcode":"BH15 1LJ",
    "sg:province":"Dorset",
    "sg:tags":[
        "mooring",
        "boat"
    ],
    "wof:name":"A B Marine",
    "wof:placetype":"venue"
},
  "geometry": {"coordinates":[-1.986739,50.714485],"type":"Point"}
}