{
  "type": "Feature",
  "properties": {
    "addr:full":"West Street Axminster Devon EX13 5NX",
    "addr:postcode":"ex13 5nx",
    "addr:street":"West Street",
    "iso:country":"GB",
    "sg:address":"West Street",
    "sg:city":"Axminster",
    "sg:classifiers":[
        {
            "category":"Professional",
            "subcategory":"Engineering",
            "type":"Services"
        },
        {
            "category":"Building & Trades",
            "subcategory":"Electrical",
            "type":"Services"
        }
    ],
    "sg:phone":"+44 1297 33144",
    "sg:postcode":"EX13 5NX",
    "sg:province":"Devon",
    "sg:tags":[
        "engineer",
        "electrician",
        "contractor"
    ],
    "wof:name":"Mike James",
    "wof:placetype":"venue"
},
  "geometry": {"coordinates":[-2.9998230934,50.7818183899],"type":"Point"}
}