{
  "type": "Feature",
  "properties": {
    "iso:country":"GB",
    "sg:address":"13 The Parade, Delta Gain",
    "sg:city":"Watford",
    "sg:classifiers":[
        {
            "category":"Health Services",
            "subcategory":"Dentist",
            "type":"Services"
        }
    ],
    "sg:phone":"+44 20 8428 8282",
    "sg:postcode":"WD1 5BL",
    "sg:province":"Hertfordshire",
    "wof:name":"S G Vasani",
    "wof:placetype":"venue"
},
  "geometry": {"coordinates":[-0.39072,51.652119],"type":"Point"}
}