{
  "type": "Feature",
  "properties": {
    "addr:full":"Greenbank Farm, 308 Lower Rainham Rd Gillingham Kent ME7 2XH",
    "addr:housenumber":"308",
    "addr:postcode":"me7 2xh",
    "addr:street":"Lower Rainham Rd",
    "iso:country":"GB",
    "sg:address":"Greenbank Farm, 308 Lower Rainham Rd",
    "sg:city":"Gillingham",
    "sg:classifiers":[
        {
            "category":"Manufacturing",
            "subcategory":"Wood Products",
            "type":"Manufacturing & Wholesale Goods"
        }
    ],
    "sg:phone":"+44 1634 262614",
    "sg:postcode":"ME7 2XH",
    "sg:province":"Kent",
    "sg:tags":[
        "packaging",
        "crate",
        "pallets"
    ],
    "wof:name":"Handworks",
    "wof:placetype":"venue"
},
  "geometry": {"coordinates":[0.5495430231,51.3864593506],"type":"Point"}
}