{
  "type": "Feature",
  "properties": {
    "addr:full":"Standbrook House London Greater London W1S 4PD",
    "addr:postcode":"w1s 4pd",
    "iso:country":"GB",
    "sg:address":"Standbrook House",
    "sg:city":"London",
    "sg:classifiers":[
        {
            "category":"Professional",
            "subcategory":"Employment Agencies",
            "type":"Services"
        }
    ],
    "sg:phone":"+44 20 7493 0156",
    "sg:postcode":"W1S 4PD",
    "sg:province":"Greater London",
    "sg:tags":[
        "consultant"
    ],
    "wof:name":"Phillips & Carpenter",
    "wof:placetype":"venue"
},
  "geometry": {"coordinates":[-0.0879139975,51.5073699951],"type":"Point"}
}