{
  "type": "Feature",
  "properties": {
    "addr:full":"21 Newerne Street Lydney Gloucestershire GL15 5RA",
    "addr:housenumber":"21",
    "addr:postcode":"gl15 5ra",
    "addr:street":"Newerne Street",
    "iso:country":"GB",
    "sg:address":"21 Newerne Street",
    "sg:city":"Lydney",
    "sg:classifiers":[
        {
            "category":"Banks & Credit Unions",
            "subcategory":"Bank",
            "type":"Services"
        },
        {
            "category":"Real Estate",
            "subcategory":"Real Estate Agent",
            "type":"Services"
        }
    ],
    "sg:phone":"+44 1594 843497",
    "sg:postcode":"GL15 5RA",
    "sg:province":"Gloucestershire",
    "wof:name":"Halifax Plc",
    "wof:placetype":"venue"
},
  "geometry": {"coordinates":[-2.529772,51.72702],"type":"Point"}
}