{
  "type": "Feature",
  "properties": {
    "addr:full":"Fieldway Croydon Surrey CR0 9AZ",
    "addr:postcode":"cr0 9az",
    "iso:country":"GB",
    "sg:address":"Fieldway",
    "sg:city":"Croydon",
    "sg:classifiers":[
        {
            "category":"Community Center",
            "type":"Public Place"
        }
    ],
    "sg:phone":"+44 1689 841688",
    "sg:postcode":"CR0 9AZ",
    "sg:province":"Surrey",
    "sg:tags":[
        "centre"
    ],
    "wof:name":"Timebridge Youth & Community Centre",
    "wof:placetype":"venue"
},
  "geometry": {"coordinates":[-0.019734,51.358894],"type":"Point"}
}