{
  "type": "Feature",
  "properties": {
    "addr:full":"80 Herne Bay Road, Swalecliffe Whitstable Kent CT5 2LX",
    "addr:housenumber":"80",
    "addr:postcode":"ct5 2lx",
    "addr:street":"Herne Bay Road",
    "iso:country":"GB",
    "sg:address":"80 Herne Bay Road, Swalecliffe",
    "sg:city":"Whitstable",
    "sg:classifiers":[
        {
            "category":"Fast Food",
            "type":"Food & Drink"
        }
    ],
    "sg:phone":"+44 1227 792632",
    "sg:postcode":"CT5 2LX",
    "sg:province":"Kent",
    "sg:tags":[
        "away",
        "take"
    ],
    "wof:name":"Sunsun Restaurant",
    "wof:placetype":"venue"
},
  "geometry": {"coordinates":[1.065728,51.361092],"type":"Point"}
}