{
  "type": "Feature",
  "properties": {
    "addr:full":"4a Spencer Court, Spencer Road Eastbourne East Sussex BN21 4PD",
    "addr:housenumber":"4a",
    "addr:postcode":"bn21 4pd",
    "addr:street":"Spencer Court Spencer Road",
    "iso:country":"GB",
    "sg:address":"4a Spencer Court, Spencer Road",
    "sg:city":"Eastbourne",
    "sg:classifiers":[
        {
            "category":"Health Services",
            "subcategory":"Doctor",
            "type":"Services"
        }
    ],
    "sg:phone":"+44 1323 417810",
    "sg:postcode":"BN21 4PD",
    "sg:province":"East Sussex",
    "sg:tags":[
        "practitioners"
    ],
    "wof:name":"Stepney Nick",
    "wof:placetype":"venue"
},
  "geometry": {"coordinates":[0.28236,50.765556],"type":"Point"}
}