{
  "type": "Feature",
  "properties": {
    "addr:full":"10 Carters Close Clacton-on-sea Essex CO16 7AT",
    "addr:housenumber":"10",
    "addr:postcode":"co16 7at",
    "addr:street":"Carters Close",
    "iso:country":"GB",
    "sg:address":"10 Carters Close",
    "sg:city":"Clacton-on-sea",
    "sg:classifiers":[
        {
            "category":"Real Estate",
            "subcategory":"Architect",
            "type":"Services"
        }
    ],
    "sg:phone":"+44 1255 435506",
    "sg:postcode":"CO16 7AT",
    "sg:province":"Essex",
    "sg:tags":[
        "architectural"
    ],
    "wof:name":"K O Designs",
    "wof:placetype":"venue"
},
  "geometry": {"coordinates":[1.1284120083,51.7950325012],"type":"Point"}
}