{
  "type": "Feature",
  "properties": {
    "addr:full":"15-17 Broadway London Greater London W13 9DA",
    "addr:housenumber":"15-17",
    "addr:postcode":"w13 9da",
    "addr:street":"Broadway",
    "iso:country":"GB",
    "sg:address":"15-17 Broadway",
    "sg:city":"London",
    "sg:classifiers":[
        {
            "category":"Building & Trades",
            "subcategory":"Electrical",
            "type":"Services"
        }
    ],
    "sg:phone":"+44 20 8567 6765",
    "sg:postcode":"W13 9DA",
    "sg:province":"Greater London",
    "sg:tags":[
        "consultant",
        "lighting"
    ],
    "wof:name":"Juliana's Leisure Services Ltd.",
    "wof:placetype":"venue"
},
  "geometry": {"coordinates":[-0.3230049908,51.5102348328],"type":"Point"}
}