{
  "type": "Feature",
  "properties": {
    "iso:country":"GB",
    "sg:address":"13 Colina Road",
    "sg:city":"London",
    "sg:classifiers":[
        {
            "category":"Professional",
            "subcategory":"Printing & Photocopies",
            "type":"Services"
        }
    ],
    "sg:postcode":"N15 3JA",
    "sg:province":"Greater London",
    "sg:tags":[
        "printer"
    ],
    "wof:name":"Collison & Son",
    "wof:placetype":"venue"
},
  "geometry": {"coordinates":[-0.0987180024,51.5838623047],"type":"Point"}
}