{
  "type": "Feature",
  "properties": {
    "addr:full":"1 Northgate Street Caernarfon Gwynedd LL55 1RW",
    "addr:housenumber":"1",
    "addr:postcode":"ll55 1rw",
    "addr:street":"Northgate Street",
    "iso:country":"GB",
    "sg:address":"1 Northgate Street",
    "sg:city":"Caernarfon",
    "sg:classifiers":[
        {
            "category":"Personal",
            "subcategory":"Beauty Salon",
            "type":"Services"
        },
        {
            "category":"Personal",
            "subcategory":"Barber",
            "type":"Services"
        }
    ],
    "sg:phone":"+44 1286 674066",
    "sg:postcode":"LL55 1RW",
    "sg:province":"Gwynedd",
    "sg:tags":[
        "unisex",
        "hairdresser"
    ],
    "wof:name":"Cutting Parlour",
    "wof:placetype":"venue"
},
  "geometry": {"coordinates":[-4.271809,53.142593],"type":"Point"}
}