{
  "type": "Feature",
  "properties": {
    "addr:full":"2 Bromley Common Bromley Kent BR2 9PD",
    "addr:housenumber":"2",
    "addr:postcode":"br2 9pd",
    "addr:street":"Bromley Common",
    "iso:country":"GB",
    "sg:address":"2 Bromley Common",
    "sg:city":"Bromley",
    "sg:classifiers":[
        {
            "category":"Professional",
            "subcategory":"Accounting & Tax Preparation",
            "type":"Services"
        }
    ],
    "sg:postcode":"BR2 9PD",
    "sg:province":"Kent",
    "sg:tags":[
        "accountant"
    ],
    "wof:name":"C Bajaria & Co",
    "wof:placetype":"venue"
},
  "geometry": {"coordinates":[0.0263989996,51.3948478699],"type":"Point"}
}