{
  "type": "Feature",
  "properties": {
    "addr:full":"Old Coach House, Banwell Rd Axbridge Somerset BS26 2XX",
    "addr:postcode":"bs26 2xx",
    "addr:street":"Old;Banwell Rd",
    "iso:country":"GB",
    "sg:address":"Old Coach House, Banwell Rd",
    "sg:city":"Axbridge",
    "sg:classifiers":[
        {
            "category":"Professional",
            "subcategory":"Management & Consulting",
            "type":"Services"
        }
    ],
    "sg:phone":"+44 1934 823769",
    "sg:postcode":"BS26 2XX",
    "sg:province":"Somerset",
    "sg:tags":[
        "consultant",
        "business"
    ],
    "wof:name":"Morgan Business Services",
    "wof:placetype":"venue"
},
  "geometry": {"coordinates":[-2.8184089661,51.2883911133],"type":"Point"}
}