{
  "type": "Feature",
  "properties": {
    "iso:country":"GB",
    "sg:address":"21 School Road, Finstock",
    "sg:city":"Oxford",
    "sg:classifiers":[
        {
            "category":"Building & Trades",
            "subcategory":"Construction",
            "type":"Services"
        }
    ],
    "sg:postcode":"OX7 3BN",
    "sg:province":"Gloucestershire",
    "sg:tags":[
        "heating",
        "contractor"
    ],
    "wof:name":"Alan Hemsley Plumbing & Heating",
    "wof:placetype":"venue"
},
  "geometry": {"coordinates":[-1.47706,51.845375],"type":"Point"}
}