{
  "type": "Feature",
  "properties": {
    "iso:country":"GB",
    "sg:address":"Key House, Sarum Hill",
    "sg:city":"Basingstoke",
    "sg:classifiers":[
        {
            "category":"Professional",
            "subcategory":"Computer Services",
            "type":"Services"
        }
    ],
    "sg:postcode":"RG21 8SR",
    "sg:province":"Hampshire",
    "sg:tags":[
        "system",
        "software"
    ],
    "wof:name":"S M S Europe",
    "wof:placetype":"venue"
},
  "geometry": {"coordinates":[-1.0918060541,51.2631072998],"type":"Point"}
}