{
  "type": "Feature",
  "properties": {
    "iso:country":"GB",
    "sg:address":"Wardens Bungalow, The Dubidges, Galley Lane Headley",
    "sg:city":"Newbury",
    "sg:classifiers":[
        {
            "category":"Organizations",
            "subcategory":"Non-profit Organization",
            "type":"Services"
        }
    ],
    "sg:phone":"+44 1635 268560",
    "sg:postcode":"RG19 8BP",
    "sg:province":"Berkshire",
    "sg:tags":[
        "organisation",
        "voluntary",
        "charity"
    ],
    "wof:name":"Kingsclere Charities",
    "wof:placetype":"venue"
},
  "geometry": {"coordinates":[-1.257991,51.358124],"type":"Point"}
}