{
  "type": "Feature",
  "properties": {
    "iso:country":"GB",
    "sg:address":"10 Cross Street",
    "sg:city":"Reading",
    "sg:classifiers":[
        {
            "category":"Banks & Credit Unions",
            "subcategory":"Financial Services",
            "type":"Services"
        }
    ],
    "sg:phone":"+44 118 957 5192",
    "sg:postcode":"RG1 1SN",
    "sg:province":"Berkshire",
    "sg:tags":[
        "building",
        "society"
    ],
    "wof:name":"Leeds & Holbeck Building Society",
    "wof:placetype":"venue"
},
  "geometry": {"coordinates":[-0.9715899825,51.4563713074],"type":"Point"}
}