{
  "type": "Feature",
  "properties": {
    "addr:full":"7 The Borough Betchworth Surrey RH3 7NB",
    "addr:housenumber":"7",
    "addr:postcode":"rh3 7nb",
    "addr:street":"The",
    "iso:country":"GB",
    "sg:address":"7 The Borough",
    "sg:city":"Betchworth",
    "sg:classifiers":[
        {
            "category":"Building & Trades",
            "subcategory":"Construction",
            "type":"Services"
        }
    ],
    "sg:postcode":"RH3 7NB",
    "sg:province":"Surrey",
    "sg:tags":[
        "builder"
    ],
    "wof:name":"Peter Buckell Building Contractors",
    "wof:placetype":"venue"
},
  "geometry": {"coordinates":[-0.2906160057,51.2338867188],"type":"Point"}
}