{
  "type": "Feature",
  "properties": {
    "iso:country":"GB",
    "sg:address":"417 Ansty Road",
    "sg:city":"Coventry",
    "sg:classifiers":[
        {
            "category":"Building & Trades",
            "subcategory":"Construction",
            "type":"Services"
        }
    ],
    "sg:phone":"+44 24 7661 9599",
    "sg:postcode":"CV2 3BQ",
    "sg:province":"Warwickshire",
    "sg:tags":[
        "dry",
        "plastering",
        "plasterers",
        "lining",
        "related",
        "screeders"
    ],
    "wof:name":"W Dunstan & Sons",
    "wof:placetype":"venue"
},
  "geometry": {"coordinates":[-1.4497439861,52.4221038818],"type":"Point"}
}