{
  "type": "Feature",
  "properties": {
    "addr:full":"59 Walsingham Avenue Kettering Northamptonshire NN15 5ER",
    "addr:housenumber":"59",
    "addr:postcode":"nn15 5er",
    "addr:street":"Walsingham Avenue",
    "iso:country":"GB",
    "sg:address":"59 Walsingham Avenue",
    "sg:city":"Kettering",
    "sg:classifiers":[
        {
            "category":"Building & Trades",
            "subcategory":"Construction",
            "type":"Services"
        }
    ],
    "sg:postcode":"NN15 5ER",
    "sg:province":"Northamptonshire",
    "sg:tags":[
        "decorator",
        "painter"
    ],
    "wof:name":"Anthony Bugg Decorating Services",
    "wof:placetype":"venue"
},
  "geometry": {"coordinates":[-0.696767,52.389172],"type":"Point"}
}