{
  "type": "Feature",
  "properties": {
    "iso:country":"GB",
    "sg:address":"8 Keswick Rd",
    "sg:city":"Worksop",
    "sg:classifiers":[
        {
            "category":"Professional",
            "subcategory":"Computer Services",
            "type":"Services"
        }
    ],
    "sg:postcode":"S81 7PT",
    "sg:province":"Nottinghamshire",
    "sg:tags":[
        "system",
        "software"
    ],
    "wof:name":"Anderson Business Services Ltd",
    "wof:placetype":"venue"
},
  "geometry": {"coordinates":[-1.122101,53.327007],"type":"Point"}
}