{
  "type": "Feature",
  "properties": {
    "addr:full":"Unit 23 Shopping Precinct, Palace Gardens Enfield Greater London EN2 6SN",
    "addr:housenumber":"unit",
    "addr:postcode":"en2 6sn",
    "addr:street":"Shopping;Palace Gardens",
    "iso:country":"GB",
    "sg:address":"Unit 23 Shopping Precinct, Palace Gardens",
    "sg:city":"Enfield",
    "sg:classifiers":[
        {
            "category":"Shopping",
            "subcategory":"Shoes",
            "type":"Retail Goods"
        }
    ],
    "sg:phone":"+44 20 8363 6570",
    "sg:postcode":"EN2 6SN",
    "sg:province":"Greater London",
    "sg:tags":[
        "shop"
    ],
    "wof:name":"Stylo Barratt Shoes Ltd.",
    "wof:placetype":"venue"
},
  "geometry": {"coordinates":[-0.087649,51.653107],"type":"Point"}
}