{
  "type": "Feature",
  "properties": {
    "iso:country":"GB",
    "sg:address":"The Meridian Centre",
    "sg:city":"Havant",
    "sg:classifiers":[
        {
            "category":"Organizations",
            "subcategory":"Community Association",
            "type":"Services"
        }
    ],
    "sg:phone":"+44 23 9279 4500",
    "sg:postcode":"PO9 1UN",
    "sg:province":"Hampshire",
    "sg:tags":[
        "society",
        "housing"
    ],
    "wof:name":"Hermitage Housing Association Ltd.",
    "wof:placetype":"venue"
},
  "geometry": {"coordinates":[-0.985544,50.854496],"type":"Point"}
}