{
  "type": "Feature",
  "properties": {
    "iso:country":"GB",
    "sg:address":"83 Boothferry Rd",
    "sg:city":"Goole",
    "sg:classifiers":[
        {
            "category":"Shopping",
            "subcategory":"Clothing, Apparel, & Fashions",
            "type":"Retail Goods"
        }
    ],
    "sg:postcode":"DN14 6BB",
    "sg:province":"East Riding of Yorkshire",
    "sg:tags":[
        "shop"
    ],
    "wof:name":"F S C",
    "wof:placetype":"venue"
},
  "geometry": {"coordinates":[-0.876699,53.705193],"type":"Point"}
}