{
  "type": "Feature",
  "properties": {
    "iso:country":"GB",
    "sg:address":"Wayside Garage, Kenn Road",
    "sg:city":"Clevedon",
    "sg:classifiers":[
        {
            "category":"Autos & Motor Vehicles",
            "subcategory":"Fuel & Gas Station",
            "type":"Retail Goods"
        }
    ],
    "sg:phone":"+44 1275 342838",
    "sg:postcode":"BS21 6TH",
    "sg:province":"Somerset",
    "sg:tags":[
        "petrol",
        "filling"
    ],
    "wof:name":"B W O C Ltd.",
    "wof:placetype":"venue"
},
  "geometry": {"coordinates":[-2.8550388813,51.43592453],"type":"Point"}
}