{
  "type": "Feature",
  "properties": {
    "iso:country":"GB",
    "sg:address":"Lucy Road",
    "sg:city":"Southend-on-sea",
    "sg:classifiers":[
        {
            "category":"Bars & Pubs",
            "subcategory":"Nightclub",
            "type":"Food & Drink"
        }
    ],
    "sg:phone":"+44 1702 467921",
    "sg:postcode":"SS1 2AU",
    "sg:province":"Essex",
    "sg:tags":[
        "club",
        "night"
    ],
    "wof:name":"Talk of the South Ltd.",
    "wof:placetype":"venue"
},
  "geometry": {"coordinates":[0.71756,51.533642],"type":"Point"}
}