{
  "type": "Feature",
  "properties": {
    "iso:country":"GB",
    "sg:address":"130 London Road, Holybourne",
    "sg:city":"Alton",
    "sg:classifiers":[
        {
            "category":"Shopping",
            "subcategory":"Department Store",
            "type":"Retail Goods"
        }
    ],
    "sg:phone":"+44 1420 83323",
    "sg:postcode":"GU34 4ES",
    "sg:province":"Hampshire",
    "wof:name":"Holybourne Shop",
    "wof:placetype":"venue"
},
  "geometry": {"coordinates":[-0.9477900267,51.1639518738],"type":"Point"}
}