{
  "type": "Feature",
  "properties": {
    "addr:full":"22 Raleigh Gardens, Brixton Hill Group Practice Brixton Greater London SW2 1AE",
    "addr:housenumber":"22",
    "addr:postcode":"sw2 1ae",
    "addr:street":"Raleigh Gardens",
    "iso:country":"GB",
    "sg:address":"22 Raleigh Gardens, Brixton Hill Group Practice",
    "sg:city":"Brixton",
    "sg:classifiers":[
        {
            "category":"Health Services",
            "subcategory":"Doctor",
            "type":"Services"
        }
    ],
    "sg:phone":"+44 20 8674 6376",
    "sg:postcode":"SW2 1AE",
    "sg:province":"Greater London",
    "sg:tags":[
        "practitioners"
    ],
    "wof:name":"Moor, S",
    "wof:placetype":"venue"
},
  "geometry": {"coordinates":[-0.12028,51.45216],"type":"Point"}
}