{
  "type": "Feature",
  "properties": {
    "iso:country":"GB",
    "sg:address":"125 Coverside Road, Great Glen",
    "sg:city":"Leicester",
    "sg:classifiers":[
        {
            "category":"Professional",
            "subcategory":"Management & Consulting",
            "type":"Services"
        }
    ],
    "sg:phone":"+44 116 259 3344",
    "sg:postcode":"LE8 9EB",
    "sg:province":"Leicestershire",
    "sg:tags":[
        "consultant",
        "business"
    ],
    "wof:name":"Competitive Advantage",
    "wof:placetype":"venue"
},
  "geometry": {"coordinates":[-1.029696,52.579594],"type":"Point"}
}