{
  "type": "Feature",
  "properties": {
    "addr:full":"397 Petre Street Sheffield South Yorkshire S4 8LL",
    "addr:housenumber":"397",
    "addr:postcode":"s4 8ll",
    "addr:street":"Petre Street",
    "iso:country":"GB",
    "sg:address":"397 Petre Street",
    "sg:city":"Sheffield",
    "sg:classifiers":[
        {
            "category":"Manufacturing",
            "subcategory":"Metals",
            "type":"Manufacturing & Wholesale Goods"
        }
    ],
    "sg:phone":"+44 114 243 3433",
    "sg:postcode":"S4 8LL",
    "sg:province":"South Yorkshire",
    "sg:tags":[
        "steel",
        "fabricator",
        "erectors"
    ],
    "wof:name":"Arms Park Developments Ltd.",
    "wof:placetype":"venue"
},
  "geometry": {"coordinates":[-1.4457600117,53.401676178],"type":"Point"}
}