{
  "type": "Feature",
  "properties": {
    "addr:full":"30 St Davids Close Farnborough Hampshire GU14 9AQ",
    "addr:housenumber":"30",
    "addr:postcode":"gu14 9aq",
    "addr:street":"St Davids Close",
    "iso:country":"GB",
    "sg:address":"30 St Davids Close",
    "sg:city":"Farnborough",
    "sg:classifiers":[
        {
            "category":"Shopping",
            "subcategory":"Catalog Store",
            "type":"Retail Goods"
        }
    ],
    "sg:phone":"+44 1276 32508",
    "sg:postcode":"GU14 9AQ",
    "sg:province":"Hampshire",
    "sg:tags":[
        "mail",
        "order"
    ],
    "wof:name":"Betterware North Hants",
    "wof:placetype":"venue"
},
  "geometry": {"coordinates":[-0.772449,51.312141],"type":"Point"}
}