{
  "type": "Feature",
  "properties": {
    "iso:country":"GB",
    "sg:address":"1 Inwood Road",
    "sg:city":"Hounslow",
    "sg:classifiers":[
        {
            "category":"Social Services",
            "subcategory":"Adult Care",
            "type":"Services"
        }
    ],
    "sg:postcode":"TW3 1UX",
    "sg:province":"Greater London",
    "sg:tags":[
        "domestic",
        "cleaning"
    ],
    "wof:name":"All Services Cleaning & Maintenance Ltd.",
    "wof:placetype":"venue"
},
  "geometry": {"coordinates":[-0.35839,51.468983],"type":"Point"}
}