{
  "type": "Feature",
  "properties": {
    "addr:full":"74 Glasgow Road, Blanefield Glasgow Argyll and Bute G63 9HX",
    "addr:housenumber":"74",
    "addr:postcode":"g63 9hx",
    "addr:street":"Glasgow Road",
    "iso:country":"GB",
    "sg:address":"74 Glasgow Road, Blanefield",
    "sg:city":"Glasgow",
    "sg:classifiers":[
        {
            "category":"Shopping",
            "subcategory":"Gifts & Souvenirs",
            "type":"Retail Goods"
        }
    ],
    "sg:phone":"+44 1360 770551",
    "sg:postcode":"G63 9HX",
    "sg:province":"Argyll and Bute",
    "sg:tags":[
        "shop"
    ],
    "wof:name":"Gifted",
    "wof:placetype":"venue"
},
  "geometry": {"coordinates":[-4.3198328018,55.9884643555],"type":"Point"}
}