{
  "type": "Feature",
  "properties": {
    "addr:full":"19 Old Windmill Way, Long Crendon Aylesbury Buckinghamshire HP18 9BQ",
    "addr:housenumber":"19",
    "addr:postcode":"hp18 9bq",
    "addr:street":"Old Windmill Way",
    "iso:country":"GB",
    "sg:address":"19 Old Windmill Way, Long Crendon",
    "sg:city":"Aylesbury",
    "sg:classifiers":[
        {
            "category":"Professional",
            "subcategory":"Management & Consulting",
            "type":"Services"
        }
    ],
    "sg:phone":"+44 1844 202248",
    "sg:postcode":"HP18 9BQ",
    "sg:province":"Buckinghamshire",
    "sg:tags":[
        "consultant",
        "business"
    ],
    "wof:name":"Peakform",
    "wof:placetype":"venue"
},
  "geometry": {"coordinates":[-0.9959700108,51.7779808044],"type":"Point"}
}