{
  "type": "Feature",
  "properties": {
    "iso:country":"GB",
    "sg:address":"191 Ridgeway",
    "sg:city":"Plymouth",
    "sg:classifiers":[
        {
            "category":"Bars & Pubs",
            "type":"Food & Drink"
        }
    ],
    "sg:phone":"+44 1752 336623",
    "sg:postcode":"PL7 3HJ",
    "sg:province":"Devon",
    "sg:tags":[
        "pubs",
        "inn"
    ],
    "wof:name":"Tibsco Ltd.",
    "wof:placetype":"venue"
},
  "geometry": {"coordinates":[-4.050114,50.387524],"type":"Point"}
}