{
  "type": "Feature",
  "properties": {
    "iso:country":"GB",
    "sg:address":"47 Long Acre",
    "sg:city":"London",
    "sg:classifiers":[
        {
            "category":"Shopping",
            "subcategory":"Clothing, Apparel, & Fashions",
            "type":"Retail Goods"
        }
    ],
    "sg:phone":"+44 20 7240 1020",
    "sg:postcode":"WC2E 9JR",
    "sg:province":"Greater London",
    "sg:tags":[
        "menswear"
    ],
    "wof:name":"Cecil Gee",
    "wof:placetype":"venue"
},
  "geometry": {"coordinates":[-0.123787,51.513256],"type":"Point"}
}