{
  "type": "Feature",
  "properties": {
    "addr:full":"204 Abbey St Derby Derbyshire DE22 3SU",
    "addr:housenumber":"204",
    "addr:postcode":"de22 3su",
    "addr:street":"Abbey St",
    "iso:country":"GB",
    "sg:address":"204 Abbey St",
    "sg:city":"Derby",
    "sg:classifiers":[
        {
            "category":"Bars & Pubs",
            "type":"Food & Drink"
        }
    ],
    "sg:phone":"+44 1332 343474",
    "sg:postcode":"DE22 3SU",
    "sg:province":"Derbyshire",
    "sg:tags":[
        "pubs",
        "inn"
    ],
    "wof:name":"Punch Retail Ltd",
    "wof:placetype":"venue"
},
  "geometry": {"coordinates":[-1.483537,52.917076],"type":"Point"}
}