{
  "type": "Feature",
  "properties": {
    "iso:country":"GB",
    "sg:address":"Milton Road, Windygates",
    "sg:city":"Leven",
    "sg:classifiers":[
        {
            "category":"Community Center",
            "type":"Public Place"
        }
    ],
    "sg:phone":"+44 1333 351514",
    "sg:postcode":"KY8 5DF",
    "sg:province":"Fife",
    "sg:tags":[
        "centre"
    ],
    "wof:name":"The Greig Institute",
    "wof:placetype":"venue"
},
  "geometry": {"coordinates":[-3.0545039177,56.1926383972],"type":"Point"}
}