{
  "type": "Feature",
  "properties": {
    "addr:full":"Unit 2, Tudor Rose Ind Est, Short Nightlayers Drove Chatteris Cambridgeshire PE16 6TY",
    "addr:housenumber":"unit 2",
    "addr:postcode":"pe16 6ty",
    "addr:street":"Tudor Rose;Nightlayers Drove",
    "iso:country":"GB",
    "sg:address":"Unit 2, Tudor Rose Ind Est, Short Nightlayers Drove",
    "sg:city":"Chatteris",
    "sg:classifiers":[
        {
            "category":"Government",
            "subcategory":"Post Office",
            "type":"Public Place"
        }
    ],
    "sg:phone":"+44 1354 696960",
    "sg:postcode":"PE16 6TY",
    "sg:province":"Cambridgeshire",
    "sg:tags":[
        "messenger",
        "courier"
    ],
    "wof:name":"COURIER COMPANY",
    "wof:placetype":"venue"
},
  "geometry": {"coordinates":[0.048651,52.463142],"type":"Point"}
}