{
  "type": "Feature",
  "properties": {
    "addr:full":"2 Herswell Cottages, West Buckland Wellington Devon TA21 9LT",
    "addr:housenumber":"2",
    "addr:postcode":"ta21 9lt",
    "addr:street":"Herswell Cottages",
    "iso:country":"GB",
    "sg:address":"2 Herswell Cottages, West Buckland",
    "sg:city":"Wellington",
    "sg:classifiers":[
        {
            "category":"Building & Trades",
            "subcategory":"Construction",
            "type":"Services"
        }
    ],
    "sg:phone":"+44 1823 461931",
    "sg:postcode":"TA21 9LT",
    "sg:province":"Devon",
    "sg:tags":[
        "joiner",
        "carpenter"
    ],
    "wof:name":"Plane Carpentry",
    "wof:placetype":"venue"
},
  "geometry": {"coordinates":[-3.1759340763,50.9775047302],"type":"Point"}
}