{
  "type": "Feature",
  "properties": {
    "addr:full":"Main Street, North Queensferry Inverkeithing Fife KY11 1JG",
    "addr:postcode":"ky11 1jg",
    "addr:street":"Main Street North;Inverkeithing",
    "iso:country":"GB",
    "sg:address":"Main Street, North Queensferry",
    "sg:city":"Inverkeithing",
    "sg:classifiers":[
        {
            "category":"Shopping",
            "subcategory":"Department Store",
            "type":"Retail Goods"
        }
    ],
    "sg:postcode":"KY11 1JG",
    "sg:province":"Fife",
    "wof:name":"Linda Pilch",
    "wof:placetype":"venue"
},
  "geometry": {"coordinates":[-3.3976790905,56.0311317444],"type":"Point"}
}