{
  "type": "Feature",
  "properties": {
    "addr:full":"2 Park Road Yeovil Somerset BA20 1DZ",
    "addr:housenumber":"2",
    "addr:postcode":"ba20 1dz",
    "addr:street":"Park Road",
    "iso:country":"GB",
    "sg:address":"2 Park Road",
    "sg:city":"Yeovil",
    "sg:classifiers":[
        {
            "category":"Shopping",
            "subcategory":"Books",
            "type":"Retail Goods"
        }
    ],
    "sg:phone":"+44 1935 426253",
    "sg:postcode":"BA20 1DZ",
    "sg:province":"Somerset",
    "sg:tags":[
        "bookseller"
    ],
    "wof:name":"Keith Jones (Yeovil)",
    "wof:placetype":"venue"
},
  "geometry": {"coordinates":[-2.6343309879,50.9430236816],"type":"Point"}
}