{
  "type": "Feature",
  "properties": {
    "addr:full":"Unit 5b, De Burgh Court, Walkerville Industrial Estate Catterick Garrison North Yorkshire DL9 4XB",
    "addr:housenumber":"unit 5b",
    "addr:postcode":"dl9 4xb",
    "addr:street":"De Burgh Court;Industrial Estate",
    "iso:country":"GB",
    "sg:address":"Unit 5b, De Burgh Court, Walkerville Industrial Estate",
    "sg:city":"Catterick Garrison",
    "sg:classifiers":[
        {
            "category":"Shopping",
            "subcategory":"Pharmacy",
            "type":"Retail Goods"
        }
    ],
    "sg:phone":"+44 1748 835050",
    "sg:postcode":"DL9 4XB",
    "sg:province":"North Yorkshire",
    "sg:tags":[
        "pharmaceutical"
    ],
    "wof:name":"Denselect Ltd.",
    "wof:placetype":"venue"
},
  "geometry": {"coordinates":[-1.680289,54.37923],"type":"Point"}
}