{
  "type": "Feature",
  "properties": {
    "addr:full":"22 Nelson St Kilmarnock East Ayrshire KA1 1BA",
    "addr:housenumber":"22",
    "addr:postcode":"ka1 1ba",
    "addr:street":"Nelson St",
    "iso:country":"GB",
    "sg:address":"22 Nelson St",
    "sg:city":"Kilmarnock",
    "sg:classifiers":[
        {
            "category":"Education",
            "subcategory":"Music School",
            "type":"Public Place"
        }
    ],
    "sg:phone":"+44 1563 573946",
    "sg:postcode":"KA1 1BA",
    "sg:province":"East Ayrshire",
    "wof:name":"Yamaha Music School",
    "wof:placetype":"venue"
},
  "geometry": {"coordinates":[-4.4992198944,55.6087112427],"type":"Point"}
}