{
  "type": "Feature",
  "properties": {
    "iso:country":"GB",
    "sg:address":"45 High Street",
    "sg:city":"Lewes",
    "sg:classifiers":[
        {
            "category":"Shopping",
            "subcategory":"Books",
            "type":"Retail Goods"
        }
    ],
    "sg:phone":"+44 1273 478467",
    "sg:postcode":"BN7 2DD",
    "sg:province":"East Sussex",
    "sg:tags":[
        "bookseller"
    ],
    "wof:name":"Unicorn Books Ltd.",
    "wof:placetype":"venue"
},
  "geometry": {"coordinates":[0.0107530002,50.8731384277],"type":"Point"}
}