{
  "type": "Feature",
  "properties": {
    "addr:full":"350 Essex Road London Greater London N1 3PD",
    "addr:housenumber":"350",
    "addr:postcode":"n1 3pd",
    "addr:street":"Essex Road",
    "iso:country":"GB",
    "sg:address":"350 Essex Road",
    "sg:city":"London",
    "sg:classifiers":[
        {
            "category":"Shopping",
            "type":"Retail Goods"
        }
    ],
    "sg:phone":"+44 20 7359 6308",
    "sg:postcode":"N1 3PD",
    "sg:province":"Greater London",
    "sg:tags":[
        "part",
        "accessory"
    ],
    "wof:name":"I M C Motor Parts",
    "wof:placetype":"venue"
},
  "geometry": {"coordinates":[-0.091459,51.542919],"type":"Point"}
}