{
  "type": "Feature",
  "properties": {
    "iso:country":"GB",
    "sg:address":"38 Shambles Street",
    "sg:city":"Barnsley",
    "sg:classifiers":[
        {
            "category":"Shopping",
            "subcategory":"Clothing, Apparel, & Fashions",
            "type":"Retail Goods"
        }
    ],
    "sg:postcode":"S70 2SH",
    "sg:province":"South Yorkshire",
    "sg:tags":[
        "dresswear"
    ],
    "wof:name":"Cloud Nine Dress Agency",
    "wof:placetype":"venue"
},
  "geometry": {"coordinates":[-1.4850239754,53.553024292],"type":"Point"}
}