{
  "type": "Feature",
  "properties": {
    "addr:full":"30 Great Sutton Street London Greater London EC1V 0DX",
    "addr:housenumber":"30",
    "addr:postcode":"ec1v 0dx",
    "addr:street":"Great Sutton Street",
    "iso:country":"GB",
    "sg:address":"30 Great Sutton Street",
    "sg:city":"London",
    "sg:classifiers":[
        {
            "category":"Professional",
            "subcategory":"Lawyer & Legal Services",
            "type":"Services"
        }
    ],
    "sg:postcode":"EC1V 0DX",
    "sg:province":"Greater London",
    "sg:tags":[
        "advice",
        "counselling"
    ],
    "wof:name":"Dawn",
    "wof:placetype":"venue"
},
  "geometry": {"coordinates":[-0.101974,51.523205],"type":"Point"}
}