{
  "type": "Feature",
  "properties": {
    "iso:country":"GB",
    "sg:address":"145 Lozells Road",
    "sg:city":"Birmingham",
    "sg:classifiers":[
        {
            "category":"Cinema",
            "subcategory":"Movie Rental",
            "type":"Entertainment"
        }
    ],
    "sg:phone":"+44 121 515 2598",
    "sg:postcode":"B19 2TP",
    "sg:province":"West Midlands",
    "sg:tags":[
        "video",
        "library"
    ],
    "wof:name":"Lozells Videos",
    "wof:placetype":"venue"
},
  "geometry": {"coordinates":[-1.9081480503,52.5031013489],"type":"Point"}
}