{
  "type": "Feature",
  "properties": {
    "addr:full":"42a West St Sheffield South Yorkshire S20 1EP",
    "addr:housenumber":"42a",
    "addr:postcode":"s20 1ep",
    "addr:street":"West St",
    "iso:country":"GB",
    "sg:address":"42a West St",
    "sg:city":"Sheffield",
    "sg:classifiers":[
        {
            "category":"Autos & Motor Vehicles",
            "subcategory":"Auto Supplies",
            "type":"Retail Goods"
        }
    ],
    "sg:phone":"+44 114 248 6325",
    "sg:postcode":"S20 1EP",
    "sg:province":"South Yorkshire",
    "sg:tags":[
        "towbars"
    ],
    "wof:name":"Mobile Towbar Services",
    "wof:placetype":"venue"
},
  "geometry": {"coordinates":[-1.3418400288,53.3428115845],"type":"Point"}
}