{
  "type": "Feature",
  "properties": {
    "iso:country":"GB",
    "sg:address":"Chowns Mill Business Park, Station Road, Irthlingborough",
    "sg:city":"Wellingborough",
    "sg:classifiers":[
        {
            "category":"Freight",
            "type":"Transportation"
        }
    ],
    "sg:phone":"+44 1933 651521",
    "sg:postcode":"NN9 5QQ",
    "sg:province":"Northamptonshire",
    "sg:tags":[
        "haulage",
        "road"
    ],
    "wof:name":"Freightroute Ltd.",
    "wof:placetype":"venue"
},
  "geometry": {"coordinates":[-0.614834,52.3251],"type":"Point"}
}