{
  "type": "Feature",
  "properties": {
    "addr:full":"84 Bridgeman St Bolton Lancashire BL3 6AZ",
    "addr:housenumber":"84",
    "addr:postcode":"bl3 6az",
    "addr:street":"Bridgeman St",
    "iso:country":"GB",
    "sg:address":"84 Bridgeman St",
    "sg:city":"Bolton",
    "sg:classifiers":[
        {
            "category":"Shopping",
            "subcategory":"Computers & Home Electronics",
            "type":"Retail Goods"
        }
    ],
    "sg:phone":"+44 1204 521666",
    "sg:postcode":"BL3 6AZ",
    "sg:province":"Lancashire",
    "sg:tags":[
        "electrical"
    ],
    "wof:name":"Wades Electrical Distributors",
    "wof:placetype":"venue"
},
  "geometry": {"coordinates":[-2.428045,53.572472],"type":"Point"}
}