{
  "type": "Feature",
  "properties": {
    "iso:country":"GB",
    "sg:address":"94 Edgware Way",
    "sg:city":"Edgware",
    "sg:classifiers":[
        {
            "category":"Shopping",
            "subcategory":"News",
            "type":"Retail Goods"
        }
    ],
    "sg:postcode":"HA8 8JS",
    "sg:province":"Greater London",
    "sg:tags":[
        "newsagent"
    ],
    "wof:name":"V Patel",
    "wof:placetype":"venue"
},
  "geometry": {"coordinates":[-0.299759,51.632664],"type":"Point"}
}