{
  "type": "Feature",
  "properties": {
    "addr:full":"1 Old Burlington Street London Greater London W1S 3NL",
    "addr:housenumber":"1",
    "addr:postcode":"w1s 3nl",
    "addr:street":"Old Burlington Street",
    "iso:country":"GB",
    "sg:address":"1 Old Burlington Street",
    "sg:city":"London",
    "sg:classifiers":[
        {
            "category":"Real Estate",
            "subcategory":"Developer",
            "type":"Services"
        }
    ],
    "sg:phone":"+44 20 7468 2600",
    "sg:postcode":"W1S 3NL",
    "sg:province":"Greater London",
    "sg:tags":[
        "property"
    ],
    "wof:name":"Plusdren Ltd.",
    "wof:placetype":"venue"
},
  "geometry": {"coordinates":[-0.140231,51.510181],"type":"Point"}
}