{
  "type": "Feature",
  "properties": {
    "addr:full":"1 The Butts Barnoldswick Lancashire BB18 5HP",
    "addr:housenumber":"1",
    "addr:postcode":"bb18 5hp",
    "addr:street":"The Butts",
    "iso:country":"GB",
    "sg:address":"1 The Butts",
    "sg:city":"Barnoldswick",
    "sg:classifiers":[
        {
            "category":"Personal",
            "subcategory":"Beauty Salon",
            "type":"Services"
        }
    ],
    "sg:phone":"+44 1282 813169",
    "sg:postcode":"BB18 5HP",
    "sg:province":"Lancashire",
    "sg:tags":[
        "unisex",
        "hairdresser"
    ],
    "wof:name":"Classicuts",
    "wof:placetype":"venue"
},
  "geometry": {"coordinates":[-2.188259,53.917412],"type":"Point"}
}