{
  "type": "Feature",
  "properties": {
    "addr:full":"8 William Street Ulverston Cumbria LA12 9AP",
    "addr:housenumber":"8",
    "addr:postcode":"la12 9ap",
    "addr:street":"William Street",
    "iso:country":"GB",
    "sg:address":"8 William Street",
    "sg:city":"Ulverston",
    "sg:classifiers":[
        {
            "category":"Taxi",
            "type":"Transportation"
        }
    ],
    "sg:phone":"+44 1229 587110",
    "sg:postcode":"LA12 9AP",
    "sg:province":"Cumbria",
    "sg:tags":[
        "mini",
        "cab"
    ],
    "wof:name":"D J's Taxis",
    "wof:placetype":"venue"
},
  "geometry": {"coordinates":[-3.0846779346,54.1958808899],"type":"Point"}
}