{
  "type": "Feature",
  "properties": {
    "addr:full":"Crookhorn Farm, Crookhorn La Horsham West Sussex RH13 7DA",
    "addr:housenumber":"crookhorn;crookhorn",
    "addr:postcode":"rh13 7da",
    "addr:street":"La Horsham",
    "iso:country":"GB",
    "sg:address":"Crookhorn Farm, Crookhorn La",
    "sg:city":"Horsham",
    "sg:classifiers":[
        {
            "category":"Farming",
            "subcategory":"Livestock Farm",
            "type":"Manufacturing & Wholesale Goods"
        }
    ],
    "sg:phone":"+44 1403 730442",
    "sg:postcode":"RH13 7DA",
    "sg:province":"West Sussex",
    "sg:tags":[
        "others"
    ],
    "wof:name":"D Kensett",
    "wof:placetype":"venue"
},
  "geometry": {"coordinates":[-0.3291000128,51.0651817322],"type":"Point"}
}