{
  "type": "Feature",
  "properties": {
    "addr:full":"1 Priory Terrace Leamington Spa Warwickshire CV31 1AA",
    "addr:housenumber":"1",
    "addr:postcode":"cv31 1aa",
    "addr:street":"Priory Terrace",
    "iso:country":"GB",
    "sg:address":"1 Priory Terrace",
    "sg:city":"Leamington Spa",
    "sg:classifiers":[
        {
            "category":"Government",
            "subcategory":"Post Office",
            "type":"Public Place"
        }
    ],
    "sg:phone":"+44 1926 888037",
    "sg:postcode":"CV31 1AA",
    "sg:province":"Warwickshire",
    "wof:name":"Priory Terrace Post Office",
    "wof:placetype":"venue"
},
  "geometry": {"coordinates":[-1.5325870514,52.286403656],"type":"Point"}
}