{
  "type": "Feature",
  "properties": {
    "addr:full":"The Green Southall Greater London UB2 4BH",
    "addr:postcode":"ub2 4bh",
    "addr:street":"Green",
    "iso:country":"GB",
    "sg:address":"The Green",
    "sg:city":"Southall",
    "sg:classifiers":[
        {
            "category":"Health Services",
            "subcategory":"Hospital",
            "type":"Services"
        }
    ],
    "sg:phone":"+44 20 8571 6110",
    "sg:postcode":"UB2 4BH",
    "sg:province":"Greater London",
    "wof:name":"Southhall Norward Hospital",
    "wof:placetype":"venue"
},
  "geometry": {"coordinates":[-0.379391,51.504959],"type":"Point"}
}