{
  "type": "Feature",
  "properties": {
    "iso:country":"GB",
    "sg:address":"66 Longmoor Road",
    "sg:city":"Liphook",
    "sg:classifiers":[
        {
            "category":"Professional",
            "subcategory":"Engineering",
            "type":"Services"
        },
        {
            "category":"Building & Trades",
            "subcategory":"Electrical",
            "type":"Services"
        }
    ],
    "sg:phone":"+44 1428 723798",
    "sg:postcode":"GU30 7NY",
    "sg:province":"Hampshire",
    "sg:tags":[
        "engineer",
        "electrician",
        "contractor"
    ],
    "wof:name":"David Hart Electrical Services",
    "wof:placetype":"venue"
},
  "geometry": {"coordinates":[-0.8101069927,51.0792922974],"type":"Point"}
}