{
  "type": "Feature",
  "properties": {
    "iso:country":"GB",
    "sg:address":"25-29 Well Rd",
    "sg:city":"Maidstone",
    "sg:classifiers":[
        {
            "category":"Food & Beverages",
            "subcategory":"Liquor & Beverages",
            "type":"Retail Goods"
        }
    ],
    "sg:phone":"+44 1622 695152",
    "sg:postcode":"ME14 1XL",
    "sg:province":"Kent",
    "sg:tags":[
        "beer",
        "spirit",
        "wines"
    ],
    "wof:name":"Tavern Wholesaling",
    "wof:placetype":"venue"
},
  "geometry": {"coordinates":[0.52584,51.279202],"type":"Point"}
}