{
  "type": "Feature",
  "properties": {
    "iso:country":"GB",
    "sg:address":"123 Stomp Road, Burnham",
    "sg:city":"Slough",
    "sg:classifiers":[
        {
            "category":"Personal",
            "subcategory":"Beauty Salon",
            "type":"Services"
        }
    ],
    "sg:phone":"+44 1628 604480",
    "sg:postcode":"SL1 7NN",
    "sg:province":"Berkshire",
    "sg:tags":[
        "unisex",
        "hairdresser"
    ],
    "wof:name":"Poppy's",
    "wof:placetype":"venue"
},
  "geometry": {"coordinates":[-0.6663429737,51.5269737244],"type":"Point"}
}