{
  "type": "Feature",
  "properties": {
    "addr:full":"34 Towgood Way, Great Paxton St Neots Bedfordshire PE19 6RP",
    "addr:housenumber":"34",
    "addr:postcode":"pe19 6rp",
    "addr:street":"Towgood Way",
    "iso:country":"GB",
    "sg:address":"34 Towgood Way, Great Paxton",
    "sg:city":"St Neots",
    "sg:classifiers":[
        {
            "category":"Professional",
            "subcategory":"Testing Lab",
            "type":"Services"
        }
    ],
    "sg:phone":"+44 1480 214235",
    "sg:postcode":"PE19 6RP",
    "sg:province":"Bedfordshire",
    "sg:tags":[
        "inspection",
        "calibration"
    ],
    "wof:name":"Curland Associates",
    "wof:placetype":"venue"
},
  "geometry": {"coordinates":[-0.2293249965,52.2591247559],"type":"Point"}
}