{
  "type": "Feature",
  "properties": {
    "addr:full":"6 Midwood House, Gerrard Street Widnes Cheshire WA8 6BH",
    "addr:housenumber":"6;house",
    "addr:postcode":"wa8 6bh",
    "addr:street":"Gerrard Street",
    "iso:country":"GB",
    "sg:address":"6 Midwood House, Gerrard Street",
    "sg:city":"Widnes",
    "sg:classifiers":[
        {
            "category":"Banks & Credit Unions",
            "subcategory":"Financial Services",
            "type":"Services"
        }
    ],
    "sg:phone":"+44 151 495 1785",
    "sg:postcode":"WA8 6BH",
    "sg:province":"Cheshire",
    "sg:tags":[
        "consultant"
    ],
    "wof:name":"Citifinancial Europe Plc",
    "wof:placetype":"venue"
},
  "geometry": {"coordinates":[-2.7332439423,53.3740310669],"type":"Point"}
}