{
  "type": "Feature",
  "properties": {
    "addr:full":"Unit 10c9, Ampthill Rd, Kempston Hardwick Bedford Bedfordshire MK45 3NL",
    "addr:housenumber":"10c9",
    "addr:postcode":"mk45 3nl",
    "addr:street":"Ampthill Rd",
    "iso:country":"GB",
    "sg:address":"Unit 10c9, Ampthill Rd, Kempston Hardwick",
    "sg:city":"Bedford",
    "sg:classifiers":[
        {
            "category":"Sports & Exercise",
            "subcategory":"Tennis Court",
            "type":"Entertainment"
        }
    ],
    "sg:phone":"+44 1234 740411",
    "sg:postcode":"MK45 3NL",
    "sg:province":"Bedfordshire",
    "sg:tags":[
        "breakdown",
        "recovery"
    ],
    "wof:name":"Mughal Autos",
    "wof:placetype":"venue"
},
  "geometry": {"coordinates":[-0.481479,52.111721],"type":"Point"}
}