{
  "type": "Feature",
  "properties": {
    "addr:full":"The Barn, Lapswater Farm, Howley Chard Devon TA20 3DU",
    "addr:housenumber":"lapswater",
    "addr:postcode":"ta20 3du",
    "iso:country":"GB",
    "sg:address":"The Barn, Lapswater Farm, Howley",
    "sg:city":"Chard",
    "sg:classifiers":[
        {
            "category":"Professional",
            "type":"Services"
        }
    ],
    "sg:phone":"+44 1460 65988",
    "sg:postcode":"TA20 3DU",
    "sg:province":"Devon",
    "sg:tags":[
        "interior",
        "furnishers",
        "designer"
    ],
    "wof:name":"Antell Design Associates",
    "wof:placetype":"venue"
},
  "geometry": {"coordinates":[-3.044711113,50.8824653625],"type":"Point"}
}