{
  "type": "Feature",
  "properties": {
    "iso:country":"GB",
    "sg:address":"65a High St",
    "sg:city":"Littlehampton",
    "sg:classifiers":[
        {
            "category":"Banks & Credit Unions",
            "subcategory":"Financial Services",
            "type":"Services"
        }
    ],
    "sg:phone":"+44 1903 713215",
    "sg:postcode":"BN17 5EJ",
    "sg:province":"West Sussex",
    "sg:tags":[
        "adviser"
    ],
    "wof:name":"M J B Partnership",
    "wof:placetype":"venue"
},
  "geometry": {"coordinates":[-0.5401520133,50.8094749451],"type":"Point"}
}