{
  "type": "Feature",
  "properties": {
    "iso:country":"GB",
    "sg:address":"19 Montpelier Avenue",
    "sg:city":"Bexley",
    "sg:classifiers":[
        {
            "category":"Professional",
            "subcategory":"Accounting & Tax Preparation",
            "type":"Services"
        }
    ],
    "sg:phone":"+44 20 8303 5909",
    "sg:postcode":"DA5 3AP",
    "sg:province":"Kent",
    "sg:tags":[
        "accountant",
        "activity"
    ],
    "wof:name":"Robson & Co",
    "wof:placetype":"venue"
},
  "geometry": {"coordinates":[0.1255519986,51.4422035217],"type":"Point"}
}