{
  "type": "Feature",
  "properties": {
    "iso:country":"GB",
    "sg:address":"Unit 4 Bestwood Park Drive West",
    "sg:city":"Nottingham",
    "sg:classifiers":[
        {
            "category":"Food & Beverages",
            "subcategory":"Fruits & Vegetables",
            "type":"Retail Goods"
        }
    ],
    "sg:phone":"+44 115 927 8262",
    "sg:postcode":"NG5 5EJ",
    "sg:province":"Nottinghamshire",
    "sg:tags":[
        "greengrocer"
    ],
    "wof:name":"G & J GILL",
    "wof:placetype":"venue"
},
  "geometry": {"coordinates":[-1.174069047,53.0100746155],"type":"Point"}
}