{
  "type": "Feature",
  "properties": {
    "addr:full":"16 Crammavill St Grays Essex RM16 2BD",
    "addr:housenumber":"16",
    "addr:postcode":"rm16 2bd",
    "addr:street":"Crammavill St",
    "iso:country":"GB",
    "sg:address":"16 Crammavill St",
    "sg:city":"Grays",
    "sg:classifiers":[
        {
            "category":"Shopping",
            "subcategory":"Pharmacy",
            "type":"Retail Goods"
        }
    ],
    "sg:phone":"+44 1375 385948",
    "sg:postcode":"RM16 2BD",
    "sg:province":"Essex",
    "sg:tags":[
        "pharmacist",
        "chemist"
    ],
    "wof:name":"Rickman Chemists",
    "wof:placetype":"venue"
},
  "geometry": {"coordinates":[0.3290419877,51.4979705811],"type":"Point"}
}