{
  "type": "Feature",
  "properties": {
    "iso:country":"GB",
    "sg:address":"9 Beeches Park, Boughrood",
    "sg:city":"Brecon",
    "sg:classifiers":[
        {
            "category":"Banks & Credit Unions",
            "subcategory":"Investment Brokerage",
            "type":"Services"
        }
    ],
    "sg:phone":"+44 1874 754288",
    "sg:postcode":"LD3 0YJ",
    "sg:province":"Powys",
    "sg:tags":[
        "contractor"
    ],
    "wof:name":"D J & G A Lloyd",
    "wof:placetype":"venue"
},
  "geometry": {"coordinates":[-3.267452,52.039589],"type":"Point"}
}