{
  "type": "Feature",
  "properties": {
    "addr:full":"Nordhous House, Nordhousness Business Park, Lerwick Shetland Shetland Islands ZE1 0LZ",
    "addr:postcode":"ze1 0lz",
    "addr:street":"Nordhousness Business Park",
    "iso:country":"GB",
    "sg:address":"Nordhous House, Nordhousness Business Park, Lerwick",
    "sg:city":"Shetland",
    "sg:classifiers":[
        {
            "category":"Professional",
            "subcategory":"Lawyer & Legal Services",
            "type":"Services"
        }
    ],
    "sg:phone":"+44 1595 695262",
    "sg:postcode":"ZE1 0LZ",
    "sg:province":"Shetland Islands",
    "sg:tags":[
        "solicitor"
    ],
    "wof:name":"NEIL RISK",
    "wof:placetype":"venue"
},
  "geometry": {"coordinates":[-1.1452239752,60.1518287659],"type":"Point"}
}