{
  "type": "Feature",
  "properties": {
    "iso:country":"GB",
    "sg:address":"7 Market Street",
    "sg:city":"Liskeard",
    "sg:classifiers":[
        {
            "category":"Home & Garden",
            "subcategory":"Home Furnishings",
            "type":"Retail Goods"
        }
    ],
    "sg:postcode":"PL14 3JH",
    "sg:province":"Cornwall",
    "sg:tags":[
        "homefurnishings"
    ],
    "wof:name":"Knotterwood Designs",
    "wof:placetype":"venue"
},
  "geometry": {"coordinates":[-4.4632329941,50.4548034668],"type":"Point"}
}