{
  "type": "Feature",
  "properties": {
    "addr:full":"36a Kenway Road London Greater London SW5 0RA",
    "addr:housenumber":"36a",
    "addr:postcode":"sw5 0ra",
    "addr:street":"Kenway Road",
    "iso:country":"GB",
    "sg:address":"36a Kenway Road",
    "sg:city":"London",
    "sg:classifiers":[
        {
            "category":"Restaurant",
            "type":"Food & Drink"
        }
    ],
    "sg:phone":"+44 20 7370 2533",
    "sg:postcode":"SW5 0RA",
    "sg:province":"Greater London",
    "sg:tags":[
        "oriental"
    ],
    "wof:name":"China Kitchen",
    "wof:placetype":"venue"
},
  "geometry": {"coordinates":[-0.192654,51.493431],"type":"Point"}
}