{
  "type": "Feature",
  "properties": {
    "addr:full":"Gipsy Lane Leicester Leicestershire LE5 0HD",
    "addr:postcode":"le5 0hd",
    "addr:street":"Gipsy Lane",
    "iso:country":"GB",
    "sg:address":"Gipsy Lane",
    "sg:city":"Leicester",
    "sg:classifiers":[
        {
            "category":"Education",
            "subcategory":"Preschool",
            "type":"Public Place"
        }
    ],
    "sg:phone":"+44 116 276 3720",
    "sg:postcode":"LE5 0HD",
    "sg:province":"Leicestershire",
    "sg:tags":[
        "pre-school",
        "playgroups"
    ],
    "wof:name":"Northfields Adventure Playground",
    "wof:placetype":"venue"
},
  "geometry": {"coordinates":[-1.0819079876,52.6488380432],"type":"Point"}
}