{
  "type": "Feature",
  "properties": {
    "addr:full":"North Maltings, Watton Rd Ware Hertfordshire SG12 0AA",
    "addr:postcode":"sg12 0aa",
    "addr:street":"North Maltings Watton Rd",
    "iso:country":"GB",
    "sg:address":"North Maltings, Watton Rd",
    "sg:city":"Ware",
    "sg:classifiers":[
        {
            "category":"Sports & Exercise",
            "subcategory":"Gym",
            "type":"Entertainment"
        }
    ],
    "sg:phone":"+44 1920 462212",
    "sg:postcode":"SG12 0AA",
    "sg:province":"Hertfordshire",
    "sg:tags":[
        "fitness",
        "health",
        "centre"
    ],
    "wof:name":"Staysharp Fitness Centre",
    "wof:placetype":"venue"
},
  "geometry": {"coordinates":[-0.035126999,51.8163375854],"type":"Point"}
}