{
  "type": "Feature",
  "properties": {
    "addr:full":"137 Heol-y-frenhines Bridgend Bridgend CF31 4RT",
    "addr:housenumber":"137",
    "addr:postcode":"cf31 4rt",
    "addr:street":"Heol-Y-Frenhines Bridgend",
    "iso:country":"GB",
    "sg:address":"137 Heol-y-frenhines",
    "sg:city":"Bridgend",
    "sg:classifiers":[
        {
            "category":"Retail",
            "subcategory":"Auto Repair",
            "type":"Services"
        }
    ],
    "sg:phone":"+44 1656 660225",
    "sg:postcode":"CF31 4RT",
    "sg:province":"Bridgend",
    "sg:tags":[
        "modification",
        "garage"
    ],
    "wof:name":"Peter Massjuk",
    "wof:placetype":"venue"
},
  "geometry": {"coordinates":[-3.6023769379,51.5101013184],"type":"Point"}
}