{
  "type": "Feature",
  "properties": {
    "addr:full":"Glenmoor, Belmont Road Durham Durham DH1 2QN",
    "addr:postcode":"dh1 2qn",
    "addr:street":"Belmont Road",
    "iso:country":"GB",
    "sg:address":"Glenmoor, Belmont Road",
    "sg:city":"Durham",
    "sg:classifiers":[
        {
            "category":"Building & Trades",
            "subcategory":"Construction",
            "type":"Services"
        }
    ],
    "sg:phone":"+44 191 384 1011",
    "sg:postcode":"DH1 2QN",
    "sg:province":"Durham",
    "sg:tags":[
        "builder"
    ],
    "wof:name":"C Smithson",
    "wof:placetype":"venue"
},
  "geometry": {"coordinates":[-1.5296859741,54.7829399109],"type":"Point"}
}