{
  "type": "Feature",
  "properties": {
    "iso:country":"GB",
    "sg:address":"13 Meadowside",
    "sg:city":"Braintree",
    "sg:classifiers":[
        {
            "category":"Retail",
            "subcategory":"Driving School",
            "type":"Services"
        }
    ],
    "sg:phone":"+44 1376 347177",
    "sg:postcode":"CM7 5UG",
    "sg:province":"Essex",
    "wof:name":"BENSON SCHOOL OF MOTORING",
    "wof:placetype":"venue"
},
  "geometry": {"coordinates":[0.5478950143,51.8874511719],"type":"Point"}
}