{
  "type": "Feature",
  "properties": {
    "addr:full":"7 Gladstone Road Scarborough North Yorkshire YO12 7BQ",
    "addr:housenumber":"7",
    "addr:postcode":"yo12 7bq",
    "addr:street":"Gladstone Road",
    "iso:country":"GB",
    "sg:address":"7 Gladstone Road",
    "sg:city":"Scarborough",
    "sg:classifiers":[
        {
            "category":"Personal",
            "subcategory":"Beauty Salon",
            "type":"Services"
        }
    ],
    "sg:phone":"+44 1723 500327",
    "sg:postcode":"YO12 7BQ",
    "sg:province":"North Yorkshire",
    "wof:name":"Beautique",
    "wof:placetype":"venue"
},
  "geometry": {"coordinates":[-0.41047,54.282524],"type":"Point"}
}