{
  "type": "Feature",
  "properties": {
    "iso:country":"GB",
    "sg:address":"69 Lumley Road",
    "sg:city":"Skegness",
    "sg:classifiers":[
        {
            "category":"Shopping",
            "subcategory":"Clothing, Apparel, & Fashions",
            "type":"Retail Goods"
        }
    ],
    "sg:phone":"+44 1754 768282",
    "sg:postcode":"PE25 3LS",
    "sg:province":"Lincolnshire",
    "sg:tags":[
        "lady",
        "fashionwear",
        "ladieswear"
    ],
    "wof:name":"Bon Marche",
    "wof:placetype":"venue"
},
  "geometry": {"coordinates":[0.3400030136,53.1429443359],"type":"Point"}
}