{
  "type": "Feature",
  "properties": {
    "iso:country":"GB",
    "sg:address":"The Kloofs, Sandhurst Lane, Whydown",
    "sg:city":"Bexhill-on-sea",
    "sg:classifiers":[
        {
            "category":"Recreation",
            "subcategory":"Campground",
            "type":"Entertainment"
        }
    ],
    "sg:postcode":"TN39 4RG",
    "sg:province":"East Sussex",
    "sg:tags":[
        "caravan",
        "park"
    ],
    "wof:name":"Kloofs Caravan Park",
    "wof:placetype":"venue"
},
  "geometry": {"coordinates":[0.4272400141,50.8563308716],"type":"Point"}
}