{
  "type": "Feature",
  "properties": {
    "addr:full":"58 Gipsy La Nuneaton Leicestershire CV11 4SE",
    "addr:housenumber":"58",
    "addr:postcode":"cv11 4se",
    "addr:street":"Gipsy La",
    "iso:country":"GB",
    "sg:address":"58 Gipsy La",
    "sg:city":"Nuneaton",
    "sg:classifiers":[
        {
            "category":"Building & Trades",
            "subcategory":"Construction",
            "type":"Services"
        }
    ],
    "sg:postcode":"CV11 4SE",
    "sg:province":"Leicestershire",
    "sg:tags":[
        "joiner",
        "carpenter"
    ],
    "wof:name":"Mousley,H E,",
    "wof:placetype":"venue"
},
  "geometry": {"coordinates":[-1.4413080215,52.5015182495],"type":"Point"}
}