{
  "type": "Feature",
  "properties": {
    "iso:country":"GB",
    "sg:address":"15 Stuart Crescent, Shirley",
    "sg:city":"Croydon",
    "sg:classifiers":[
        {
            "category":"Shopping",
            "subcategory":"Party Supplies",
            "type":"Retail Goods"
        }
    ],
    "sg:postcode":"CR0 8QP",
    "sg:province":"Surrey",
    "sg:tags":[
        "inflatables",
        "bouncy",
        "castle"
    ],
    "wof:name":"Action Bounce Inflatables",
    "wof:placetype":"venue"
},
  "geometry": {"coordinates":[-0.0352660008,51.3686408997],"type":"Point"}
}