{
  "type": "Feature",
  "properties": {
    "iso:country":"GB",
    "sg:address":"Helmshore Road, Haslingden",
    "sg:city":"Rossendale",
    "sg:classifiers":[
        {
            "category":"Government",
            "subcategory":"Office",
            "type":"Public Place"
        }
    ],
    "sg:phone":"+44 1706 227016",
    "sg:postcode":"BB4 4DW",
    "sg:province":"Lancashire",
    "sg:tags":[
        "local"
    ],
    "wof:name":"The Sports Centre",
    "wof:placetype":"venue"
},
  "geometry": {"coordinates":[-2.326064,53.703377],"type":"Point"}
}