{
  "type": "Feature",
  "properties": {
    "iso:country":"GB",
    "sg:address":"5 Tithe Barn St, Horbury",
    "sg:city":"Wakefield",
    "sg:classifiers":[
        {
            "category":"Professional",
            "subcategory":"Art Services",
            "type":"Services"
        }
    ],
    "sg:phone":"+44 1924 281010",
    "sg:postcode":"WF4 6HN",
    "sg:province":"West Yorkshire",
    "sg:tags":[
        "consultant",
        "design"
    ],
    "wof:name":"Monarch Computer Aided Design",
    "wof:placetype":"venue"
},
  "geometry": {"coordinates":[-1.5592269897,53.6608200073],"type":"Point"}
}