{
  "type": "Feature",
  "properties": {
    "addr:full":"164 Coach Road, Sleights Whitby North Yorkshire YO22 5EQ",
    "addr:housenumber":"164",
    "addr:postcode":"yo22 5eq",
    "addr:street":"Coach Road",
    "iso:country":"GB",
    "sg:address":"164 Coach Road, Sleights",
    "sg:city":"Whitby",
    "sg:classifiers":[
        {
            "category":"Shopping",
            "subcategory":"Antiques",
            "type":"Retail Goods"
        }
    ],
    "sg:phone":"+44 1947 810297",
    "sg:postcode":"YO22 5EQ",
    "sg:province":"North Yorkshire",
    "wof:name":"Eskdale Antiques",
    "wof:placetype":"venue"
},
  "geometry": {"coordinates":[-0.665988,54.450829],"type":"Point"}
}