{
  "type": "Feature",
  "properties": {
    "addr:full":"Unit W17, Lenton Business Centre, Lenton Boulevard, Lenton Nottingham Nottinghamshire NG7 2BY",
    "addr:postcode":"ng7 2by",
    "addr:street":"Lenton Boulevard",
    "iso:country":"GB",
    "sg:address":"Unit W17, Lenton Business Centre, Lenton Boulevard, Lenton",
    "sg:city":"Nottingham",
    "sg:classifiers":[
        {
            "category":"Home & Garden",
            "subcategory":"Kitchen Supply",
            "type":"Retail Goods"
        }
    ],
    "sg:phone":"+44 115 955 5531",
    "sg:postcode":"NG7 2BY",
    "sg:province":"Nottinghamshire",
    "sg:tags":[
        "equipment",
        "bakery"
    ],
    "wof:name":"The Bread Roll Company",
    "wof:placetype":"venue"
},
  "geometry": {"coordinates":[-1.1740139723,52.9476509094],"type":"Point"}
}