{
  "type": "Feature",
  "properties": {
    "addr:full":"34 High Street East Linton East Lothian EH40 3AB",
    "addr:housenumber":"34",
    "addr:postcode":"eh40 3ab",
    "addr:street":"High Street",
    "iso:country":"GB",
    "sg:address":"34 High Street",
    "sg:city":"East Linton",
    "sg:classifiers":[
        {
            "category":"Food & Beverages",
            "subcategory":"Bakery",
            "type":"Retail Goods"
        }
    ],
    "sg:phone":"+44 1620 861365",
    "sg:postcode":"EH40 3AB",
    "sg:province":"East Lothian",
    "sg:tags":[
        "baker"
    ],
    "wof:name":"The Bake House",
    "wof:placetype":"venue"
},
  "geometry": {"coordinates":[-2.6564381123,55.9876976013],"type":"Point"}
}