{
  "type": "Feature",
  "properties": {
    "addr:full":"4 High Street Leominster Herefordshire HR6 8LZ",
    "addr:housenumber":"4",
    "addr:postcode":"hr6 8lz",
    "addr:street":"High Street",
    "iso:country":"GB",
    "sg:address":"4 High Street",
    "sg:city":"Leominster",
    "sg:classifiers":[
        {
            "category":"Banks & Credit Unions",
            "subcategory":"Bureau De Change",
            "type":"Services"
        },
        {
            "category":"Food & Beverages",
            "subcategory":"Liquor & Beverages",
            "type":"Retail Goods"
        }
    ],
    "sg:phone":"+44 1568 611232",
    "sg:postcode":"HR6 8LZ",
    "sg:province":"Herefordshire",
    "sg:tags":[
        "beer",
        "wine",
        "spirit",
        "wines"
    ],
    "wof:name":"Orchard Hive & Vine",
    "wof:placetype":"venue"
},
  "geometry": {"coordinates":[-2.7389919758,52.2277641296],"type":"Point"}
}