{
  "type": "Feature",
  "properties": {
    "addr:full":"279 High St Croydon Surrey CR0 1QH",
    "addr:housenumber":"279",
    "addr:postcode":"cr0 1qh",
    "addr:street":"High St",
    "iso:country":"GB",
    "sg:address":"279 High St",
    "sg:city":"Croydon",
    "sg:classifiers":[
        {
            "category":"Insurance",
            "subcategory":"Health Insurance",
            "type":"Services"
        }
    ],
    "sg:phone":"+44 20 8667 1830",
    "sg:postcode":"CR0 1QH",
    "sg:province":"Surrey",
    "wof:name":"Columbus Overseas (Ex. Pat.) Ltd",
    "wof:placetype":"venue"
},
  "geometry": {"coordinates":[-0.099065,51.36821],"type":"Point"}
}