{
  "type": "Feature",
  "properties": {
    "iso:country":"GB",
    "sg:address":"Quantocks House, 178 Cheddon Rd",
    "sg:city":"Taunton",
    "sg:classifiers":[
        {
            "category":"Manufacturing",
            "subcategory":"Building Materials",
            "type":"Manufacturing & Wholesale Goods"
        }
    ],
    "sg:phone":"+44 1823 335556",
    "sg:postcode":"TA2 7AN",
    "sg:province":"Somerset",
    "sg:tags":[
        "merchant",
        "builder"
    ],
    "wof:name":"Swiftec Building Products",
    "wof:placetype":"venue"
},
  "geometry": {"coordinates":[-3.1005139351,51.0313491821],"type":"Point"}
}