{
  "type": "Feature",
  "properties": {
    "addr:full":"Unit 10, High Hazles Road, Cotgrave Nottingham Nottinghamshire NG12 3GZ",
    "addr:housenumber":"unit 10",
    "addr:postcode":"ng12 3gz",
    "addr:street":"High Hazles Road",
    "iso:country":"GB",
    "sg:address":"Unit 10, High Hazles Road, Cotgrave",
    "sg:city":"Nottingham",
    "sg:classifiers":[
        {
            "category":"Building & Trades",
            "subcategory":"Electrical",
            "type":"Services"
        }
    ],
    "sg:postcode":"NG12 3GZ",
    "sg:province":"Nottinghamshire",
    "sg:tags":[
        "lighting"
    ],
    "wof:name":"Perrin Neon",
    "wof:placetype":"venue"
},
  "geometry": {"coordinates":[-1.0342190266,52.9144592285],"type":"Point"}
}