{
  "type": "Feature",
  "properties": {
    "addr:full":"371 Millbrook Rd, Millbrook Southampton Hampshire SO15 0HW",
    "addr:housenumber":"371",
    "addr:postcode":"so15 0hw",
    "addr:street":"Millbrook Rd",
    "iso:country":"GB",
    "sg:address":"371 Millbrook Rd, Millbrook",
    "sg:city":"Southampton",
    "sg:classifiers":[
        {
            "category":"Banks & Credit Unions",
            "subcategory":"Financial Services",
            "type":"Services"
        }
    ],
    "sg:phone":"+44 23 8051 5000",
    "sg:postcode":"SO15 0HW",
    "sg:province":"Hampshire",
    "sg:tags":[
        "consultant"
    ],
    "wof:name":"First National Motor Finance",
    "wof:placetype":"venue"
},
  "geometry": {"coordinates":[-1.4444390535,50.91355896],"type":"Point"}
}