{
  "type": "Feature",
  "properties": {
    "addr:full":"41 High Street Wick Highland KW1 4BS",
    "addr:housenumber":"41",
    "addr:postcode":"kw1 4bs",
    "addr:street":"High Street",
    "iso:country":"GB",
    "sg:address":"41 High Street",
    "sg:city":"Wick",
    "sg:classifiers":[
        {
            "category":"Restaurant",
            "type":"Food & Drink"
        }
    ],
    "sg:phone":"+44 1955 603287",
    "sg:postcode":"KW1 4BS",
    "sg:province":"Highland",
    "wof:name":"Houstons Restaurant",
    "wof:placetype":"venue"
},
  "geometry": {"coordinates":[-3.092959,58.443081],"type":"Point"}
}