{
  "type": "Feature",
  "properties": {
    "addr:full":"412 Greenford Rd Greenford Greater London UB6 9AH",
    "addr:housenumber":"412",
    "addr:postcode":"ub6 9ah",
    "addr:street":"Greenford Rd",
    "iso:country":"GB",
    "sg:address":"412 Greenford Rd",
    "sg:city":"Greenford",
    "sg:classifiers":[
        {
            "category":"Autos & Motor Vehicles",
            "subcategory":"Fuel & Gas Station",
            "type":"Retail Goods"
        }
    ],
    "sg:phone":"+44 20 8578 6767",
    "sg:postcode":"UB6 9AH",
    "sg:province":"Greater London",
    "sg:tags":[
        "petrol",
        "filling"
    ],
    "wof:name":"Greenford Corner Service Station",
    "wof:placetype":"venue"
},
  "geometry": {"coordinates":[-0.352301,51.526917],"type":"Point"}
}