{
  "type": "Feature",
  "properties": {
    "iso:country":"GB",
    "sg:address":"Product Development Suite, 1q Mountjoy R",
    "sg:city":"Durham",
    "sg:classifiers":[
        {
            "category":"Building & Trades",
            "subcategory":"Construction",
            "type":"Services"
        }
    ],
    "sg:postcode":"DH1 3SW",
    "sg:province":"Durham",
    "sg:tags":[
        "builder"
    ],
    "wof:name":"Pendragon Innovations Ltd",
    "wof:placetype":"venue"
},
  "geometry": {"coordinates":[-1.574608,54.777534],"type":"Point"}
}