{
  "type": "Feature",
  "properties": {
    "addr:full":"3a Cannock Rd Burntwood Staffordshire WS7 0BL",
    "addr:housenumber":"3a",
    "addr:postcode":"ws7 0bl",
    "addr:street":"Cannock Rd",
    "iso:country":"GB",
    "sg:address":"3a Cannock Rd",
    "sg:city":"Burntwood",
    "sg:classifiers":[
        {
            "category":"Real Estate",
            "subcategory":"Real Estate Agent",
            "type":"Services"
        }
    ],
    "sg:phone":"+44 1543 677157",
    "sg:postcode":"WS7 0BL",
    "sg:province":"Staffordshire",
    "wof:name":"Halifax Property Services",
    "wof:placetype":"venue"
},
  "geometry": {"coordinates":[-1.9077179432,52.6778907776],"type":"Point"}
}