{
  "type": "Feature",
  "properties": {
    "iso:country":"GB",
    "sg:address":"9 St Michaels Avenue, Pontarddulais",
    "sg:city":"Swansea",
    "sg:classifiers":[
        {
            "category":"Organizations",
            "subcategory":"Membership Organization",
            "type":"Services"
        }
    ],
    "sg:phone":"+44 1792 882380",
    "sg:postcode":"SA4 8TE",
    "sg:province":"Carmarthenshire",
    "sg:tags":[
        "club"
    ],
    "wof:name":"Pontardulais & District Conservative & Unionist Club Ltd.",
    "wof:placetype":"venue"
},
  "geometry": {"coordinates":[-4.042406,51.715027],"type":"Point"}
}