{
  "type": "Feature",
  "properties": {
    "addr:full":"73 Livingstone Street Clydebank East Dunbartonshire G81 2XA",
    "addr:housenumber":"73",
    "addr:postcode":"g81 2xa",
    "addr:street":"Livingstone Street",
    "iso:country":"GB",
    "sg:address":"73 Livingstone Street",
    "sg:city":"Clydebank",
    "sg:classifiers":[
        {
            "category":"Utilities",
            "subcategory":"Electric",
            "type":"Services"
        }
    ],
    "sg:phone":"+44 141 951 1390",
    "sg:postcode":"G81 2XA",
    "sg:province":"East Dunbartonshire",
    "sg:tags":[
        "electricity"
    ],
    "wof:name":"Scottish Power",
    "wof:placetype":"venue"
},
  "geometry": {"coordinates":[-4.3909578323,55.9029769897],"type":"Point"}
}