{
  "type": "Feature",
  "properties": {
    "iso:country":"GB",
    "sg:address":"1 High Street",
    "sg:city":"Ayr",
    "sg:classifiers":[
        {
            "category":"Bars & Pubs",
            "type":"Food & Drink"
        }
    ],
    "sg:phone":"+44 1292 550203",
    "sg:postcode":"KA6 7QU",
    "sg:province":"East Ayrshire",
    "sg:tags":[
        "pubs",
        "inn"
    ],
    "wof:name":"The Doon Tavern",
    "wof:placetype":"venue"
},
  "geometry": {"coordinates":[-4.3968157768,55.3230934143],"type":"Point"}
}