{
  "type": "Feature",
  "properties": {
    "iso:country":"GB",
    "sg:address":"Grove Garage, Grove Rd",
    "sg:city":"Stoke On Trent",
    "sg:classifiers":[
        {
            "category":"Autos & Motor Vehicles",
            "subcategory":"Automobile Sales",
            "type":"Retail Goods"
        }
    ],
    "sg:phone":"+44 1782 594121",
    "sg:postcode":"ST4 4LP",
    "sg:province":"Staffordshire",
    "sg:tags":[
        "commercial"
    ],
    "wof:name":"J T Fernihough",
    "wof:placetype":"venue"
},
  "geometry": {"coordinates":[-2.1834599972,52.9898605347],"type":"Point"}
}