{
  "type": "Feature",
  "properties": {
    "iso:country":"GB",
    "sg:address":"First Floor Wilton Market, High Street, Erdington",
    "sg:city":"Birmingham",
    "sg:classifiers":[
        {
            "category":"Shopping",
            "subcategory":"Department Store",
            "type":"Retail Goods"
        }
    ],
    "sg:phone":"+44 121 681 1181",
    "sg:postcode":"B11 2EZ",
    "sg:province":"West Midlands",
    "wof:name":"Vinyl Frontier",
    "wof:placetype":"venue"
},
  "geometry": {"coordinates":[-1.84157,52.453049],"type":"Point"}
}