{
  "type": "Feature",
  "properties": {
    "addr:full":"28-30 Broad St Fraserburgh Aberdeenshire AB43 9AH",
    "addr:housenumber":"28-30",
    "addr:postcode":"ab43 9ah",
    "addr:street":"Broad St",
    "iso:country":"GB",
    "sg:address":"28-30 Broad St",
    "sg:city":"Fraserburgh",
    "sg:classifiers":[
        {
            "category":"Communications",
            "subcategory":"Film & Video Production",
            "type":"Services"
        }
    ],
    "sg:phone":"+44 1346 518885",
    "sg:postcode":"AB43 9AH",
    "sg:province":"Aberdeenshire",
    "sg:tags":[
        "tv"
    ],
    "wof:name":"Radio Rentals",
    "wof:placetype":"venue"
},
  "geometry": {"coordinates":[-2.017819,57.687931],"type":"Point"}
}