{
  "type": "Feature",
  "properties": {
    "addr:full":"Queen Street Broseley Shropshire TF12 5NB",
    "addr:postcode":"tf12 5nb",
    "addr:street":"Queen Street",
    "iso:country":"GB",
    "sg:address":"Queen Street",
    "sg:city":"Broseley",
    "sg:classifiers":[
        {
            "category":"Travel",
            "subcategory":"Hotels & Motels",
            "type":"Entertainment"
        }
    ],
    "sg:phone":"+44 1952 882301",
    "sg:postcode":"TF12 5NB",
    "sg:province":"Shropshire",
    "wof:name":"The Cumberland Hotel",
    "wof:placetype":"venue"
},
  "geometry": {"coordinates":[-2.4856410027,52.6157455444],"type":"Point"}
}