{
  "type": "Feature",
  "properties": {
    "addr:full":"13 Lipson Vale Plymouth Devon PL4 7HF",
    "addr:housenumber":"13",
    "addr:postcode":"pl4 7hf",
    "addr:street":"Lipson Vale",
    "iso:country":"GB",
    "sg:address":"13 Lipson Vale",
    "sg:city":"Plymouth",
    "sg:classifiers":[
        {
            "category":"Government",
            "subcategory":"Post Office",
            "type":"Public Place"
        }
    ],
    "sg:phone":"+44 1752 665200",
    "sg:postcode":"PL4 7HF",
    "sg:province":"Devon",
    "wof:name":"Lipson Vale P.O",
    "wof:placetype":"venue"
},
  "geometry": {"coordinates":[-4.121547,50.38171],"type":"Point"}
}