{
  "type": "Feature",
  "properties": {
    "iso:country":"GB",
    "sg:address":"Unit 5, Julie House, Warton Rd",
    "sg:city":"Hoddesdon",
    "sg:classifiers":[
        {
            "category":"Communications",
            "type":"Services"
        }
    ],
    "sg:phone":"+44 1992 479620",
    "sg:postcode":"EN11 0LN",
    "sg:province":"Essex",
    "sg:tags":[
        "audio-visual"
    ],
    "wof:name":"Lost It Productions",
    "wof:placetype":"venue"
},
  "geometry": {"coordinates":[-0.000659,51.7682],"type":"Point"}
}