{
  "type": "Feature",
  "properties": {
    "addr:full":"Kilncroft, Tile Kiln La Hemel Hempstead Hertfordshire HP3 8NQ",
    "addr:postcode":"hp3 8nq",
    "addr:street":"Hempstead",
    "iso:country":"GB",
    "sg:address":"Kilncroft, Tile Kiln La",
    "sg:city":"Hemel Hempstead",
    "sg:classifiers":[
        {
            "category":"Professional",
            "type":"Services"
        }
    ],
    "sg:phone":"+44 1442 211333",
    "sg:postcode":"HP3 8NQ",
    "sg:province":"Hertfordshire",
    "sg:tags":[
        "caterer"
    ],
    "wof:name":"2 B's Leisure",
    "wof:placetype":"venue"
},
  "geometry": {"coordinates":[-0.436994,51.750069],"type":"Point"}
}