{
  "type": "Feature",
  "properties": {
    "iso:country":"GB",
    "sg:address":"4-6 High Street",
    "sg:city":"Westerham",
    "sg:classifiers":[
        {
            "category":"Real Estate",
            "subcategory":"Real Estate Agent",
            "type":"Services"
        }
    ],
    "sg:phone":"+44 1959 564405",
    "sg:postcode":"TN16 1RF",
    "sg:province":"Kent",
    "wof:name":"Sheldon House Securities Ltd.",
    "wof:placetype":"venue"
},
  "geometry": {"coordinates":[0.068554,51.266117],"type":"Point"}
}