{
  "type": "Feature",
  "properties": {
    "addr:full":"Lamberlea, Nethertown Nurseries, Netherton Egremont Cumbria CA22 2UH",
    "addr:postcode":"ca22 2uh",
    "addr:street":"Netherton",
    "iso:country":"GB",
    "sg:address":"Lamberlea, Nethertown Nurseries, Netherton",
    "sg:city":"Egremont",
    "sg:classifiers":[
        {
            "category":"Home & Garden",
            "subcategory":"Garden Supply",
            "type":"Retail Goods"
        }
    ],
    "sg:postcode":"CA22 2UH",
    "sg:province":"Cumbria",
    "sg:tags":[
        "nursery",
        "centre"
    ],
    "wof:name":"Barry W Alderson",
    "wof:placetype":"venue"
},
  "geometry": {"coordinates":[-3.52831,54.482918],"type":"Point"}
}