{
  "type": "Feature",
  "properties": {
    "iso:country":"GB",
    "sg:address":"6 Mccarthy Road",
    "sg:city":"Loughborough",
    "sg:classifiers":[
        {
            "category":"Food & Beverages",
            "subcategory":"Groceries & Convenience Stores",
            "type":"Retail Goods"
        }
    ],
    "sg:phone":"+44 1509 504354",
    "sg:postcode":"LE12 9LR",
    "sg:province":"Leicestershire",
    "wof:name":"Dark Convenient Store",
    "wof:placetype":"venue"
},
  "geometry": {"coordinates":[-1.299909,52.771412],"type":"Point"}
}