{
  "type": "Feature",
  "properties": {
    "iso:country":"GB",
    "sg:address":"66 Dalton St",
    "sg:city":"Birmingham",
    "sg:classifiers":[
        {
            "category":"Personal",
            "subcategory":"Beauty Salon",
            "type":"Services"
        }
    ],
    "sg:phone":"+44 121 233 2020",
    "sg:postcode":"B4 7LX",
    "sg:province":"West Midlands",
    "sg:tags":[
        "unisex",
        "hairdresser"
    ],
    "wof:name":"Avorm Hair Fitness Studio",
    "wof:placetype":"venue"
},
  "geometry": {"coordinates":[-1.8934479952,52.4823265076],"type":"Point"}
}