{
  "type": "Feature",
  "properties": {
    "addr:full":"Penarth Road Cardiff Cardiff CF11 8UL",
    "addr:postcode":"cf11 8ul",
    "addr:street":"Penarth Road",
    "iso:country":"GB",
    "sg:address":"Penarth Road",
    "sg:city":"Cardiff",
    "sg:classifiers":[
        {
            "category":"Manufacturing",
            "subcategory":"Metals",
            "type":"Manufacturing & Wholesale Goods"
        }
    ],
    "sg:phone":"+44 29 2038 8182",
    "sg:postcode":"CF11 8UL",
    "sg:province":"Cardiff",
    "wof:name":"Poeton (Cardiff) Ltd.",
    "wof:placetype":"venue"
},
  "geometry": {"coordinates":[-3.193994,51.463406],"type":"Point"}
}