{
  "type": "Feature",
  "properties": {
    "addr:full":"27 Tavistock Road Edgware Greater London HA8 6DD",
    "addr:housenumber":"27",
    "addr:postcode":"ha8 6dd",
    "addr:street":"Tavistock Road",
    "iso:country":"GB",
    "sg:address":"27 Tavistock Road",
    "sg:city":"Edgware",
    "sg:classifiers":[
        {
            "category":"Professional",
            "subcategory":"Management & Consulting",
            "type":"Services"
        }
    ],
    "sg:phone":"+44 20 8952 1364",
    "sg:postcode":"HA8 6DD",
    "sg:province":"Greater London",
    "sg:tags":[
        "consultant",
        "business"
    ],
    "wof:name":"Mistery Associates Ltd.",
    "wof:placetype":"venue"
},
  "geometry": {"coordinates":[-0.282384,51.602345],"type":"Point"}
}