{
  "type": "Feature",
  "properties": {
    "addr:full":"Hilltop Indust Est, Dromintee Rd Coalville Leicestershire LE67 1TX",
    "addr:postcode":"le67 1tx",
    "addr:street":"Dromintee Rd",
    "iso:country":"GB",
    "sg:address":"Hilltop Indust Est, Dromintee Rd",
    "sg:city":"Coalville",
    "sg:classifiers":[
        {
            "category":"Professional",
            "subcategory":"Business Services",
            "type":"Services"
        }
    ],
    "sg:phone":"+44 1530 836422",
    "sg:postcode":"LE67 1TX",
    "sg:province":"Leicestershire",
    "sg:tags":[
        "distribution"
    ],
    "wof:name":"Wace Corporate Packaging",
    "wof:placetype":"venue"
},
  "geometry": {"coordinates":[-1.333794,52.702091],"type":"Point"}
}