{
  "type": "Feature",
  "properties": {
    "addr:full":"3 Sylvan Ave, Wood Green London Greater London N22 5HX",
    "addr:housenumber":"3",
    "addr:postcode":"n22 5hx",
    "addr:street":"Sylvan Ave",
    "iso:country":"GB",
    "sg:address":"3 Sylvan Ave, Wood Green",
    "sg:city":"London",
    "sg:classifiers":[
        {
            "category":"Shopping",
            "subcategory":"Department Store",
            "type":"Retail Goods"
        }
    ],
    "sg:postcode":"N22 5HX",
    "sg:province":"Greater London",
    "wof:name":"Slimodes Fashions Limited",
    "wof:placetype":"venue"
},
  "geometry": {"coordinates":[-0.110982,51.606049],"type":"Point"}
}