{
  "type": "Feature",
  "properties": {
    "addr:full":"East Terrace Penzance Cornwall TR18 2TD",
    "addr:postcode":"tr18 2td",
    "addr:street":"East Terrace",
    "iso:country":"GB",
    "sg:address":"East Terrace",
    "sg:city":"Penzance",
    "sg:classifiers":[
        {
            "category":"Retail",
            "subcategory":"Auto Repair",
            "type":"Services"
        }
    ],
    "sg:phone":"+44 1736 740555",
    "sg:postcode":"TR18 2TD",
    "sg:province":"Cornwall",
    "sg:tags":[
        "modification",
        "garage"
    ],
    "wof:name":"St.Michaels Garage",
    "wof:placetype":"venue"
},
  "geometry": {"coordinates":[-5.5349187851,50.119808197],"type":"Point"}
}