{
  "type": "Feature",
  "properties": {
    "addr:full":"197 Point Clear Road, St Osyth Clacton-on-sea Essex CO16 8JD",
    "addr:housenumber":"197",
    "addr:postcode":"co16 8jd",
    "addr:street":"Point Clear Road",
    "iso:country":"GB",
    "sg:address":"197 Point Clear Road, St Osyth",
    "sg:city":"Clacton-on-sea",
    "sg:classifiers":[
        {
            "category":"Manufacturing",
            "subcategory":"Wood Products",
            "type":"Manufacturing & Wholesale Goods"
        }
    ],
    "sg:postcode":"CO16 8JD",
    "sg:province":"Essex",
    "sg:tags":[
        "maker",
        "cabinet"
    ],
    "wof:name":"Michael Blakebrough",
    "wof:placetype":"venue"
},
  "geometry": {"coordinates":[1.0494699478,51.7944717407],"type":"Point"}
}