{
  "type": "Feature",
  "properties": {
    "addr:full":"2 Alverton St Penzance Cornwall TR18 2QW",
    "addr:housenumber":"2",
    "addr:postcode":"tr18 2qw",
    "addr:street":"Alverton St",
    "iso:country":"GB",
    "sg:address":"2 Alverton St",
    "sg:city":"Penzance",
    "sg:classifiers":[
        {
            "category":"Professional",
            "subcategory":"Employment Agencies",
            "type":"Services"
        }
    ],
    "sg:phone":"+44 1209 315171",
    "sg:postcode":"TR18 2QW",
    "sg:province":"Cornwall",
    "sg:tags":[
        "career",
        "guidance"
    ],
    "wof:name":"Cornwall & Devon Careers Ltd",
    "wof:placetype":"venue"
},
  "geometry": {"coordinates":[-5.538304,50.118454],"type":"Point"}
}