{
  "type": "Feature",
  "properties": {
    "addr:full":"Beresford Road Whitstable Kent CT5 1JP",
    "addr:postcode":"ct5 1jp",
    "addr:street":"Beresford Road",
    "iso:country":"GB",
    "sg:address":"Beresford Road",
    "sg:city":"Whitstable",
    "sg:classifiers":[
        {
            "category":"Retail",
            "subcategory":"Auto Repair",
            "type":"Services"
        }
    ],
    "sg:phone":"+44 1227 277940",
    "sg:postcode":"CT5 1JP",
    "sg:province":"Kent",
    "sg:tags":[
        "modification",
        "garage",
        "related"
    ],
    "wof:name":"Auto Tune",
    "wof:placetype":"venue"
},
  "geometry": {"coordinates":[1.029045,51.35733],"type":"Point"}
}