{
  "type": "Feature",
  "properties": {
    "iso:country":"GB",
    "sg:address":"150 Birkenhead Rd",
    "sg:city":"Wallasey",
    "sg:classifiers":[
        {
            "category":"Wholesale",
            "subcategory":"Furniture",
            "type":"Manufacturing & Wholesale Goods"
        }
    ],
    "sg:postcode":"CH44 7JN",
    "sg:province":"Merseyside",
    "sg:tags":[
        "shop",
        "fitting"
    ],
    "wof:name":"Rew,Graham,",
    "wof:placetype":"venue"
},
  "geometry": {"coordinates":[-3.020914,53.405266],"type":"Point"}
}