{
  "type": "Feature",
  "properties": {
    "iso:country":"GB",
    "sg:address":"10 Lambs Conduit Passage",
    "sg:city":"Bloomsbury",
    "sg:classifiers":[
        {
            "category":"Professional",
            "subcategory":"Art Services",
            "type":"Services"
        }
    ],
    "sg:phone":"+44 20 7419 9596",
    "sg:postcode":"WC1R 4RH",
    "sg:province":"Greater London",
    "sg:tags":[
        "consultant",
        "design"
    ],
    "wof:name":"Shop",
    "wof:placetype":"venue"
},
  "geometry": {"coordinates":[-0.118329,51.519611],"type":"Point"}
}