{
  "type": "Feature",
  "properties": {
    "addr:full":"Little Heath Farm, Gamlingay Sandy Bedfordshire SG19 3LL",
    "addr:postcode":"sg19 3ll",
    "addr:street":"Little Heath Farm",
    "iso:country":"GB",
    "sg:address":"Little Heath Farm, Gamlingay",
    "sg:city":"Sandy",
    "sg:classifiers":[
        {
            "category":"Recreation",
            "subcategory":"Fishing",
            "type":"Entertainment"
        }
    ],
    "sg:phone":"+44 1767 650301",
    "sg:postcode":"SG19 3LL",
    "sg:province":"Bedfordshire",
    "sg:tags":[
        "angling"
    ],
    "wof:name":"Little Heath Farm Trout Fishery",
    "wof:placetype":"venue"
},
  "geometry": {"coordinates":[-0.2019560039,52.1486587524],"type":"Point"}
}