{
  "type": "Feature",
  "properties": {
    "addr:full":"150 Cowick St Exeter Devon EX4 1AS",
    "addr:housenumber":"150",
    "addr:postcode":"ex4 1as",
    "addr:street":"Cowick St",
    "iso:country":"GB",
    "sg:address":"150 Cowick St",
    "sg:city":"Exeter",
    "sg:classifiers":[
        {
            "category":"Professional",
            "subcategory":"Business Services",
            "type":"Services"
        }
    ],
    "sg:postcode":"EX4 1AS",
    "sg:province":"Devon",
    "sg:tags":[
        "import",
        "export",
        "agent"
    ],
    "wof:name":"Kennedy,Terry,",
    "wof:placetype":"venue"
},
  "geometry": {"coordinates":[-3.541914,50.716282],"type":"Point"}
}