{
  "type": "Feature",
  "properties": {
    "addr:full":"322a Oldham Road, Failsworth Manchester Lancashire M35 0EN",
    "addr:housenumber":"322a",
    "addr:postcode":"m35 0en",
    "addr:street":"Oldham Road",
    "iso:country":"GB",
    "sg:address":"322a Oldham Road, Failsworth",
    "sg:city":"Manchester",
    "sg:classifiers":[
        {
            "category":"Personal",
            "subcategory":"Beauty Salon",
            "type":"Services"
        }
    ],
    "sg:phone":"+44 161 681 8712",
    "sg:postcode":"M35 0EN",
    "sg:province":"Lancashire",
    "sg:tags":[
        "unisex",
        "hairdresser"
    ],
    "wof:name":"Flair",
    "wof:placetype":"venue"
},
  "geometry": {"coordinates":[-2.1627969742,53.5086250305],"type":"Point"}
}