{
  "type": "Feature",
  "properties": {
    "addr:full":"136 Heaton Park Road Newcastle-upon-tyne Tyne and Wear NE6 5NR",
    "addr:housenumber":"136",
    "addr:postcode":"ne6 5nr",
    "addr:street":"Heaton Park Road",
    "iso:country":"GB",
    "sg:address":"136 Heaton Park Road",
    "sg:city":"Newcastle-upon-tyne",
    "sg:classifiers":[
        {
            "category":"Shopping",
            "subcategory":"Department Store",
            "type":"Retail Goods"
        },
        {
            "category":"Food & Beverages",
            "subcategory":"Groceries & Convenience Stores",
            "type":"Retail Goods"
        }
    ],
    "sg:phone":"+44 191 240 0587",
    "sg:postcode":"NE6 5NR",
    "sg:province":"Tyne and Wear",
    "wof:name":"Heaton Park Road Store & Off Licence",
    "wof:placetype":"venue"
},
  "geometry": {"coordinates":[-1.5858500004,54.9795150757],"type":"Point"}
}