{
  "type": "Feature",
  "properties": {
    "iso:country":"GB",
    "sg:address":"Unit 3 Wheatear, Perry Road",
    "sg:city":"Witham",
    "sg:classifiers":[
        {
            "category":"Cafe",
            "type":"Food & Drink"
        }
    ],
    "sg:phone":"+44 1376 520561",
    "sg:postcode":"CM8 3YY",
    "sg:province":"Essex",
    "sg:tags":[
        "tea",
        "room"
    ],
    "wof:name":"The Inn Place",
    "wof:placetype":"venue"
},
  "geometry": {"coordinates":[0.639991,51.800713],"type":"Point"}
}