{
  "type": "Feature",
  "properties": {
    "addr:full":"Selhurst Pk Stadium Holmesdale Rd London Greater London SE25 6PU",
    "addr:postcode":"se25 6pu",
    "addr:street":"Selhurst Pk Stadium Holmesdale Rd",
    "iso:country":"GB",
    "sg:address":"Selhurst Pk Stadium Holmesdale Rd",
    "sg:city":"London",
    "sg:classifiers":[
        {
            "category":"Travel",
            "subcategory":"Travel Agent",
            "type":"Entertainment"
        }
    ],
    "sg:postcode":"SE25 6PU",
    "sg:province":"Greater London",
    "wof:name":"Desouza,Adrian,",
    "wof:placetype":"venue"
},
  "geometry": {"coordinates":[-0.077764,51.397869],"type":"Point"}
}