{
  "type": "Feature",
  "properties": {
    "iso:country":"GB",
    "sg:address":"25 Oak Street, Quarry Bank",
    "sg:city":"Brierley Hill",
    "sg:classifiers":[
        {
            "category":"Government",
            "subcategory":"Post Office",
            "type":"Public Place"
        },
        {
            "category":"Real Estate",
            "subcategory":"Architect",
            "type":"Services"
        }
    ],
    "sg:phone":"+44 1384 561448",
    "sg:postcode":"DY5 2JH",
    "sg:province":"West Midlands",
    "sg:tags":[
        "cutting"
    ],
    "wof:name":"D M G Profiles",
    "wof:placetype":"venue"
},
  "geometry": {"coordinates":[-2.106546,52.473335],"type":"Point"}
}