{
  "type": "Feature",
  "properties": {
    "addr:full":"132a South Quay Great Yarmouth Norfolk NR30 3LD",
    "addr:housenumber":"132a",
    "addr:postcode":"nr30 3ld",
    "addr:street":"South Quay;Yarmouth",
    "iso:country":"GB",
    "sg:address":"132a South Quay",
    "sg:city":"Great Yarmouth",
    "sg:classifiers":[
        {
            "category":"Professional",
            "subcategory":"Printing & Photocopies",
            "type":"Services"
        }
    ],
    "sg:phone":"+44 1493 851102",
    "sg:postcode":"NR30 3LD",
    "sg:province":"Norfolk",
    "sg:tags":[
        "printer"
    ],
    "wof:name":"Prontaprint Ltd.",
    "wof:placetype":"venue"
},
  "geometry": {"coordinates":[1.7281099558,52.5993499756],"type":"Point"}
}