{
  "type": "Feature",
  "properties": {
    "addr:full":"25 Garrick Street London Greater London WC2E 9AX",
    "addr:housenumber":"25",
    "addr:postcode":"wc2e 9ax",
    "addr:street":"Garrick Street",
    "iso:country":"GB",
    "sg:address":"25 Garrick Street",
    "sg:city":"London",
    "sg:classifiers":[
        {
            "category":"Professional",
            "subcategory":"Management & Consulting",
            "type":"Services"
        }
    ],
    "sg:phone":"+44 20 7836 9878",
    "sg:postcode":"WC2E 9AX",
    "sg:province":"Greater London",
    "sg:tags":[
        "project"
    ],
    "wof:name":"A S A Private Clients Ltd.",
    "wof:placetype":"venue"
},
  "geometry": {"coordinates":[-0.1268440038,51.5118675232],"type":"Point"}
}