{
  "type": "Feature",
  "properties": {
    "iso:country":"GB",
    "sg:address":"156 Sudbury Heights Avenue",
    "sg:city":"Greenford",
    "sg:classifiers":[
        {
            "category":"Building & Trades",
            "subcategory":"Construction",
            "type":"Services"
        }
    ],
    "sg:phone":"+44 20 8902 3257",
    "sg:postcode":"UB6 0LY",
    "sg:province":"Greater London",
    "sg:tags":[
        "decorator",
        "painter"
    ],
    "wof:name":"James Galvin",
    "wof:placetype":"venue"
},
  "geometry": {"coordinates":[-0.3250049949,51.5539360046],"type":"Point"}
}