{
  "type": "Feature",
  "properties": {
    "addr:full":"343 Lower Addiscombe Road Croydon Surrey CR0 6RG",
    "addr:housenumber":"343",
    "addr:postcode":"cr0 6rg",
    "addr:street":"Lower Addiscombe Road",
    "iso:country":"GB",
    "sg:address":"343 Lower Addiscombe Road",
    "sg:city":"Croydon",
    "sg:classifiers":[
        {
            "category":"Retail",
            "subcategory":"Funeral Services",
            "type":"Services"
        }
    ],
    "sg:phone":"+44 20 8654 0990",
    "sg:postcode":"CR0 6RG",
    "sg:province":"Surrey",
    "wof:name":"A & H Morriss Sons Ltd.",
    "wof:placetype":"venue"
},
  "geometry": {"coordinates":[-0.0682319999,51.3824577332],"type":"Point"}
}