{
  "type": "Feature",
  "properties": {
    "iso:country":"GB",
    "sg:address":"Everite Road, Ditton",
    "sg:city":"Widnes",
    "sg:classifiers":[
        {
            "category":"Manufacturing",
            "subcategory":"Wood Products",
            "type":"Manufacturing & Wholesale Goods"
        }
    ],
    "sg:phone":"+44 151 423 5833",
    "sg:postcode":"WA8 8PT",
    "sg:province":"Cheshire",
    "sg:tags":[
        "packaging",
        "crate",
        "pallets"
    ],
    "wof:name":"P E C Pallet",
    "wof:placetype":"venue"
},
  "geometry": {"coordinates":[-2.77256,53.3601],"type":"Point"}
}