{
  "type": "Feature",
  "properties": {
    "addr:full":"178-180 Cricklewood Broadway Cricklewood Greater London NW2 3EB",
    "addr:housenumber":"178-180",
    "addr:postcode":"nw2 3eb",
    "addr:street":"Cricklewood Broadway",
    "iso:country":"GB",
    "sg:address":"178-180 Cricklewood Broadway",
    "sg:city":"Cricklewood",
    "sg:classifiers":[
        {
            "category":"Food & Beverages",
            "subcategory":"Groceries & Convenience Stores",
            "type":"Retail Goods"
        }
    ],
    "sg:phone":"+44 20 8452 2974",
    "sg:postcode":"NW2 3EB",
    "sg:province":"Greater London",
    "wof:name":"One Stop Mini Market",
    "wof:placetype":"venue"
},
  "geometry": {"coordinates":[-0.215463,51.557098],"type":"Point"}
}