{
  "type": "Feature",
  "properties": {
    "iso:country":"GB",
    "sg:address":"72 Beach Rd, Newton",
    "sg:city":"Porthcawl",
    "sg:classifiers":[
        {
            "category":"Social Services",
            "type":"Services"
        }
    ],
    "sg:postcode":"CF36 5NE",
    "sg:province":"Bridgend",
    "wof:name":"Blue Seas House",
    "wof:placetype":"venue"
},
  "geometry": {"coordinates":[-3.676822,51.478752],"type":"Point"}
}