{
  "type": "Feature",
  "properties": {
    "iso:country":"GB",
    "sg:address":"Cca, 350 Sauchiehall Street",
    "sg:city":"Glasgow",
    "sg:classifiers":[
        {
            "category":"Arts & Performance",
            "subcategory":"Theater",
            "type":"Entertainment"
        }
    ],
    "sg:postcode":"G2 3JD",
    "sg:province":"Glasgow City",
    "sg:tags":[
        "theatre"
    ],
    "wof:name":"Lookout Theatre Co  Ltd",
    "wof:placetype":"venue"
},
  "geometry": {"coordinates":[-4.26242,55.865349],"type":"Point"}
}