{
  "type": "Feature",
  "properties": {
    "iso:country":"GB",
    "sg:address":"75 Heather Crescent, Sketty",
    "sg:city":"Swansea",
    "sg:classifiers":[
        {
            "category":"Education",
            "subcategory":"Music School",
            "type":"Public Place"
        }
    ],
    "sg:phone":"+44 1792 207861",
    "sg:postcode":"SA2 8HS",
    "sg:province":"Swansea",
    "sg:tags":[
        "teacher"
    ],
    "wof:name":"Christopher Williams",
    "wof:placetype":"venue"
},
  "geometry": {"coordinates":[-3.997875,51.617931],"type":"Point"}
}