{
  "type": "Feature",
  "properties": {
    "iso:country":"GB",
    "sg:address":"Barford House, 15-16 Bishop Street",
    "sg:city":"Coventry",
    "sg:classifiers":[
        {
            "category":"Health Services",
            "subcategory":"Health Practitioner",
            "type":"Services"
        }
    ],
    "sg:postcode":"CV1 1HU",
    "sg:province":"West Midlands",
    "sg:tags":[
        "acupuncture"
    ],
    "wof:name":"One Stop Medical Centre",
    "wof:placetype":"venue"
},
  "geometry": {"coordinates":[-1.511589,52.411449],"type":"Point"}
}