{
  "type": "Feature",
  "properties": {
    "addr:full":"127 Brockley Rise London Greater London SE23 1JP",
    "addr:housenumber":"127",
    "addr:postcode":"se23 1jp",
    "addr:street":"Brockley Rise",
    "iso:country":"GB",
    "sg:address":"127 Brockley Rise",
    "sg:city":"London",
    "sg:classifiers":[
        {
            "category":"Autos & Motor Vehicles",
            "subcategory":"Automobile Sales",
            "type":"Retail Goods"
        }
    ],
    "sg:postcode":"SE23 1JP",
    "sg:province":"Greater London",
    "sg:tags":[
        "car"
    ],
    "wof:name":"Congreve Motor Co",
    "wof:placetype":"venue"
},
  "geometry": {"coordinates":[-0.041664999,51.4476623535],"type":"Point"}
}