{
  "type": "Feature",
  "properties": {
    "iso:country":"GB",
    "sg:address":"40 Tor Hill Rd",
    "sg:city":"Torquay",
    "sg:classifiers":[
        {
            "category":"Fast Food",
            "type":"Food & Drink"
        }
    ],
    "sg:postcode":"TQ2 5RF",
    "sg:province":"Devon",
    "sg:tags":[
        "away",
        "take"
    ],
    "wof:name":"German Sausage House Ltd",
    "wof:placetype":"venue"
},
  "geometry": {"coordinates":[-3.534134,50.468018],"type":"Point"}
}