{
  "type": "Feature",
  "properties": {
    "iso:country":"GB",
    "sg:address":"19 Stour Road",
    "sg:city":"Christchurch",
    "sg:classifiers":[
        {
            "category":"Professional",
            "subcategory":"Engineering",
            "type":"Services"
        }
    ],
    "sg:postcode":"BH23 1PL",
    "sg:province":"Dorset",
    "sg:tags":[
        "engineer",
        "structural"
    ],
    "wof:name":"Archibald Shaw (2005) Ltd.",
    "wof:placetype":"venue"
},
  "geometry": {"coordinates":[-1.783382,50.738235],"type":"Point"}
}