{
  "type": "Feature",
  "properties": {
    "iso:country":"GB",
    "sg:address":"Heythrop College, Kensington Square",
    "sg:city":"London",
    "sg:classifiers":[
        {
            "category":"Communications",
            "subcategory":"Newspaper",
            "type":"Services"
        },
        {
            "category":"Wholesale",
            "subcategory":"Books, Periodicals, & Newspapers",
            "type":"Manufacturing & Wholesale Goods"
        }
    ],
    "sg:phone":"+44 20 7795 4255",
    "sg:postcode":"W8 5HQ",
    "sg:province":"Greater London",
    "sg:tags":[
        "magazine",
        "publishing"
    ],
    "wof:name":"The Way Publications",
    "wof:placetype":"venue"
},
  "geometry": {"coordinates":[-0.19047,51.499519],"type":"Point"}
}