{
  "type": "Feature",
  "properties": {
    "addr:full":"113 Rose Street Edinburgh City of Edinburgh EH2 3DT",
    "addr:housenumber":"113",
    "addr:postcode":"eh2 3dt",
    "addr:street":"Rose Street",
    "iso:country":"GB",
    "sg:address":"113 Rose Street",
    "sg:city":"Edinburgh",
    "sg:classifiers":[
        {
            "category":"Manufacturing",
            "subcategory":"Tools & Machinery",
            "type":"Manufacturing & Wholesale Goods"
        },
        {
            "category":"Organizations",
            "subcategory":"Non-profit Organization",
            "type":"Services"
        }
    ],
    "sg:phone":"+44 131 220 2778",
    "sg:postcode":"EH2 3DT",
    "sg:province":"City of Edinburgh",
    "sg:tags":[
        "society",
        "organisation",
        "charity",
        "voluntary",
        "friendly"
    ],
    "wof:name":"Age Concern Scotland (Trading) Ltd.",
    "wof:placetype":"venue"
},
  "geometry": {"coordinates":[-3.201736927,55.952129364],"type":"Point"}
}