{
  "type": "Feature",
  "properties": {
    "addr:full":"27 High Street, Westcott Aylesbury Buckinghamshire HP18 0PQ",
    "addr:housenumber":"27",
    "addr:postcode":"hp18 0pq",
    "addr:street":"High Street",
    "iso:country":"GB",
    "sg:address":"27 High Street, Westcott",
    "sg:city":"Aylesbury",
    "sg:classifiers":[
        {
            "category":"Bars & Pubs",
            "type":"Food & Drink"
        }
    ],
    "sg:phone":"+44 1296 651455",
    "sg:postcode":"HP18 0PQ",
    "sg:province":"Buckinghamshire",
    "sg:tags":[
        "pubs",
        "inn"
    ],
    "wof:name":"The White Swan",
    "wof:placetype":"venue"
},
  "geometry": {"coordinates":[-0.9198030233,51.8460884094],"type":"Point"}
}