{
  "type": "Feature",
  "properties": {
    "iso:country":"GB",
    "sg:address":"33 Houghston Road",
    "sg:city":"Morecambe",
    "sg:classifiers":[
        {
            "category":"Personal",
            "subcategory":"Beauty Salon",
            "type":"Services"
        }
    ],
    "sg:postcode":"LA4 5DF",
    "sg:province":"Lancashire",
    "sg:tags":[
        "unisex",
        "hairdresser"
    ],
    "wof:name":"Gordoncarol",
    "wof:placetype":"venue"
},
  "geometry": {"coordinates":[-2.854494,54.070129],"type":"Point"}
}