{
  "type": "Feature",
  "properties": {
    "iso:country":"GB",
    "sg:address":"Unit 4 Haslemere Trading Estate, Sutton Road",
    "sg:city":"Maidstone",
    "sg:classifiers":[
        {
            "category":"Shopping",
            "subcategory":"Antiques",
            "type":"Retail Goods"
        },
        {
            "category":"Retail",
            "subcategory":"Storage",
            "type":"Services"
        }
    ],
    "sg:phone":"+44 1622 675332",
    "sg:postcode":"ME15 9NL",
    "sg:province":"Kent",
    "sg:tags":[
        "household",
        "removal"
    ],
    "wof:name":"Sutton Valence Antiques",
    "wof:placetype":"venue"
},
  "geometry": {"coordinates":[0.56092,51.24136],"type":"Point"}
}