{
  "type": "Feature",
  "properties": {
    "addr:full":"514 Doncaster Road, Stairfoot Barnsley South Yorkshire S70 3PE",
    "addr:housenumber":"514",
    "addr:postcode":"s70 3pe",
    "addr:street":"Doncaster Road Stairfoot;Yorkshire",
    "iso:country":"GB",
    "sg:address":"514 Doncaster Road, Stairfoot",
    "sg:city":"Barnsley",
    "sg:classifiers":[
        {
            "category":"Food & Beverages",
            "subcategory":"Bakery",
            "type":"Retail Goods"
        }
    ],
    "sg:phone":"+44 1226 291052",
    "sg:postcode":"S70 3PE",
    "sg:province":"South Yorkshire",
    "sg:tags":[
        "baker"
    ],
    "wof:name":"Potts (Bakers) Ltd.",
    "wof:placetype":"venue"
},
  "geometry": {"coordinates":[-1.441129,53.546036],"type":"Point"}
}