{
  "type": "Feature",
  "properties": {
    "iso:country":"GB",
    "sg:address":"204 Piercefield Terrace, Portobello Road, Piershill",
    "sg:city":"Edinburgh",
    "sg:classifiers":[
        {
            "category":"Building & Trades",
            "subcategory":"Construction",
            "type":"Services"
        }
    ],
    "sg:postcode":"EH8 7BN",
    "sg:province":"City of Edinburgh",
    "sg:tags":[
        "monumental",
        "mason"
    ],
    "wof:name":"Abercon Memorial Services",
    "wof:placetype":"venue"
},
  "geometry": {"coordinates":[-3.142376,55.955437],"type":"Point"}
}