{
  "type": "Feature",
  "properties": {
    "addr:full":"Bawtry Road, Hellaby Rotherham South Yorkshire S66 8EY",
    "addr:postcode":"s66 8ey",
    "addr:street":"Bawtry Road",
    "iso:country":"GB",
    "sg:address":"Bawtry Road, Hellaby",
    "sg:city":"Rotherham",
    "sg:classifiers":[
        {
            "category":"Autos & Motor Vehicles",
            "subcategory":"Automobile Sales",
            "type":"Retail Goods"
        }
    ],
    "sg:phone":"+44 1709 542810",
    "sg:postcode":"S66 8EY",
    "sg:province":"South Yorkshire",
    "sg:tags":[
        "car"
    ],
    "wof:name":"Douglas Paul Hyundai",
    "wof:placetype":"venue"
},
  "geometry": {"coordinates":[-1.243719,53.422825],"type":"Point"}
}