{
  "type": "Feature",
  "properties": {
    "addr:full":"Ebc House Townsend Lane London Greater London NW9 8LL",
    "addr:postcode":"nw9 8ll",
    "addr:street":"Townsend Lane",
    "iso:country":"GB",
    "sg:address":"Ebc House Townsend Lane",
    "sg:city":"London",
    "sg:classifiers":[
        {
            "category":"Professional",
            "subcategory":"Business Services",
            "type":"Services"
        }
    ],
    "sg:postcode":"NW9 8LL",
    "sg:province":"Greater London",
    "wof:name":"Ebc House Ltd.",
    "wof:placetype":"venue"
},
  "geometry": {"coordinates":[-0.2572799921,51.576751709],"type":"Point"}
}