{
  "type": "Feature",
  "properties": {
    "addr:full":"Den Holme, Long Lee Lane Keighley West Yorkshire BD21 4TS",
    "addr:postcode":"bd21 4ts",
    "addr:street":"Den Holme Long Lee Lane",
    "iso:country":"GB",
    "sg:address":"Den Holme, Long Lee Lane",
    "sg:city":"Keighley",
    "sg:classifiers":[
        {
            "category":"Building & Trades",
            "subcategory":"Construction",
            "type":"Services"
        }
    ],
    "sg:phone":"+44 1535 664268",
    "sg:postcode":"BD21 4TS",
    "sg:province":"West Yorkshire",
    "sg:tags":[
        "joiner",
        "carpenter"
    ],
    "wof:name":"Anthony K Potts",
    "wof:placetype":"venue"
},
  "geometry": {"coordinates":[-1.896379,53.859196],"type":"Point"}
}