{
  "type": "Feature",
  "properties": {
    "addr:full":"8 Lower Level, White Rose Shopping Centre Leeds West Yorkshire LS11 8LL",
    "addr:housenumber":"8",
    "addr:postcode":"ls11 8ll",
    "addr:street":"Lower Level White;West",
    "iso:country":"GB",
    "sg:address":"8 Lower Level, White Rose Shopping Centre",
    "sg:city":"Leeds",
    "sg:classifiers":[
        {
            "category":"Shopping",
            "subcategory":"Hobbies, Toys, & Games",
            "type":"Retail Goods"
        },
        {
            "category":"Shopping",
            "subcategory":"News",
            "type":"Retail Goods"
        }
    ],
    "sg:phone":"+44 113 271 2201",
    "sg:postcode":"LS11 8LL",
    "sg:province":"West Yorkshire",
    "sg:tags":[
        "shop",
        "toy",
        "newsagent",
        "sale"
    ],
    "sg:website":"http://www.elc.co.uk",
    "wof:name":"Early Learning Centre Ltd",
    "wof:placetype":"venue"
},
  "geometry": {"coordinates":[-1.546587,53.794495],"type":"Point"}
}