{
  "type": "Feature",
  "properties": {
    "addr:full":"21 Alexandra Road Worthing West Sussex BN11 2DX",
    "addr:housenumber":"21",
    "addr:postcode":"bn11 2dx",
    "addr:street":"Alexandra Road",
    "iso:country":"GB",
    "sg:address":"21 Alexandra Road",
    "sg:city":"Worthing",
    "sg:classifiers":[
        {
            "category":"Travel",
            "subcategory":"Hotels & Motels",
            "type":"Entertainment"
        }
    ],
    "sg:postcode":"BN11 2DX",
    "sg:province":"West Sussex",
    "sg:tags":[
        "house",
        "guest"
    ],
    "wof:name":"Glenhill Guest House",
    "wof:placetype":"venue"
},
  "geometry": {"coordinates":[-0.356537,50.813644],"type":"Point"}
}