{
  "type": "Feature",
  "properties": {
    "iso:country":"GB",
    "sg:address":"1 Cheddleton Heath Road",
    "sg:city":"Leek",
    "sg:classifiers":[
        {
            "category":"Building & Trades",
            "subcategory":"Construction",
            "type":"Services"
        }
    ],
    "sg:postcode":"ST13 7DX",
    "sg:province":"Staffordshire",
    "sg:tags":[
        "builder"
    ],
    "wof:name":"Michael Goodwin",
    "wof:placetype":"venue"
},
  "geometry": {"coordinates":[-2.0326120853,53.0760231018],"type":"Point"}
}