{
  "type": "Feature",
  "properties": {
    "iso:country":"GB",
    "sg:address":"16 Cotterdale View, Halton Moor",
    "sg:city":"Leeds",
    "sg:classifiers":[
        {
            "category":"Home & Garden",
            "subcategory":"Building Materials",
            "type":"Retail Goods"
        }
    ],
    "sg:postcode":"LS15 0AL",
    "sg:province":"West Yorkshire",
    "sg:tags":[
        "furnishers",
        "bathroom",
        "planner"
    ],
    "wof:name":"Philip Cooke",
    "wof:placetype":"venue"
},
  "geometry": {"coordinates":[-1.4786349535,53.7913398743],"type":"Point"}
}