{
  "type": "Feature",
  "properties": {
    "addr:full":"Unit 1 Gay Lane Otley North Yorkshire LS21 3BB",
    "addr:housenumber":"unit 1",
    "addr:postcode":"ls21 3bb",
    "addr:street":"Gay Lane",
    "iso:country":"GB",
    "sg:address":"Unit 1 Gay Lane",
    "sg:city":"Otley",
    "sg:classifiers":[
        {
            "category":"Retail",
            "subcategory":"Auto Repair",
            "type":"Services"
        }
    ],
    "sg:postcode":"LS21 3BB",
    "sg:province":"North Yorkshire",
    "sg:tags":[
        "modification",
        "garage"
    ],
    "wof:name":"The Mini Centre",
    "wof:placetype":"venue"
},
  "geometry": {"coordinates":[-1.6897189617,53.9019317627],"type":"Point"}
}