{
  "type": "Feature",
  "properties": {
    "addr:full":"7a Market Place Kettering Northamptonshire NN16 0AX",
    "addr:housenumber":"7a",
    "addr:postcode":"nn16 0ax",
    "addr:street":"Market Place",
    "iso:country":"GB",
    "sg:address":"7a Market Place",
    "sg:city":"Kettering",
    "sg:classifiers":[
        {
            "category":"Shopping",
            "subcategory":"Clothing, Apparel, & Fashions",
            "type":"Retail Goods"
        }
    ],
    "sg:phone":"+44 1536 312480",
    "sg:postcode":"NN16 0AX",
    "sg:province":"Northamptonshire",
    "sg:tags":[
        "shop"
    ],
    "wof:name":"Uptown Girl",
    "wof:placetype":"venue"
},
  "geometry": {"coordinates":[-0.727856,52.397854],"type":"Point"}
}