{
  "type": "Feature",
  "properties": {
    "iso:country":"GB",
    "sg:address":"55 Commercial Road",
    "sg:city":"Newport",
    "sg:classifiers":[
        {
            "category":"Shopping",
            "subcategory":"Clothing, Apparel, & Fashions",
            "type":"Retail Goods"
        }
    ],
    "sg:phone":"+44 1633 213563",
    "sg:postcode":"NP20 2PE",
    "sg:province":"Newport",
    "sg:tags":[
        "workwear",
        "protective"
    ],
    "wof:name":"B & L Industrial Clothing",
    "wof:placetype":"venue"
},
  "geometry": {"coordinates":[-2.989784956,51.5791702271],"type":"Point"}
}