{
  "type": "Feature",
  "properties": {
    "addr:full":"Love La Wakefield West Yorkshire WF2 9AQ",
    "addr:postcode":"wf2 9aq",
    "addr:street":"La Wakefield West",
    "iso:country":"GB",
    "sg:address":"Love La",
    "sg:city":"Wakefield",
    "sg:classifiers":[
        {
            "category":"Organizations",
            "subcategory":"Membership Organization",
            "type":"Services"
        }
    ],
    "sg:phone":"+44 1924 374882",
    "sg:postcode":"WF2 9AQ",
    "sg:province":"West Yorkshire",
    "sg:tags":[
        "club"
    ],
    "wof:name":"H M Prison Wakefield",
    "wof:placetype":"venue"
},
  "geometry": {"coordinates":[-1.508209,53.683365],"type":"Point"}
}