{
  "type": "Feature",
  "properties": {
    "iso:country":"GB",
    "sg:address":"133 Upper Wickham Lane",
    "sg:city":"Welling",
    "sg:classifiers":[
        {
            "category":"Autos & Motor Vehicles",
            "subcategory":"Automobile Sales",
            "type":"Retail Goods"
        }
    ],
    "sg:phone":"+44 20 8854 8037",
    "sg:postcode":"DA16 3AQ",
    "sg:province":"Kent",
    "sg:tags":[
        "car"
    ],
    "wof:name":"DW Leisure",
    "wof:placetype":"venue"
},
  "geometry": {"coordinates":[0.1105469987,51.4673194885],"type":"Point"}
}