{
  "type": "Feature",
  "properties": {
    "addr:full":"68 Grace Road, Downend Bristol City of Bristol BS16 5DU",
    "addr:housenumber":"68",
    "addr:postcode":"bs16 5du",
    "addr:street":"Grace Road",
    "iso:country":"GB",
    "sg:address":"68 Grace Road, Downend",
    "sg:city":"Bristol",
    "sg:classifiers":[
        {
            "category":"Banks & Credit Unions",
            "subcategory":"Financial Services",
            "type":"Services"
        }
    ],
    "sg:phone":"+44 117 970 2233",
    "sg:postcode":"BS16 5DU",
    "sg:province":"City of Bristol",
    "sg:tags":[
        "adviser"
    ],
    "wof:name":"Adams Consultancy",
    "wof:placetype":"venue"
},
  "geometry": {"coordinates":[-2.5146069527,51.484161377],"type":"Point"}
}