{
  "type": "Feature",
  "properties": {
    "addr:full":"Unit 10, Black Rock Mills, Waingate, Linthwaite Huddersfield West Yorkshire HD7 5NS",
    "addr:housenumber":"unit 10",
    "addr:postcode":"hd7 5ns",
    "addr:street":"Rock;Waingate;West",
    "iso:country":"GB",
    "sg:address":"Unit 10, Black Rock Mills, Waingate, Linthwaite",
    "sg:city":"Huddersfield",
    "sg:classifiers":[
        {
            "category":"Utilities",
            "subcategory":"Cable",
            "type":"Services"
        }
    ],
    "sg:phone":"+44 1484 847750",
    "sg:postcode":"HD7 5NS",
    "sg:province":"West Yorkshire",
    "sg:tags":[
        "rope",
        "hawser"
    ],
    "wof:name":"Whitwams",
    "wof:placetype":"venue"
},
  "geometry": {"coordinates":[-1.8474090099,53.6258544922],"type":"Point"}
}