{
  "type": "Feature",
  "properties": {
    "iso:country":"GB",
    "sg:address":"24 Earls Wood Drive",
    "sg:city":"Plymouth",
    "sg:classifiers":[
        {
            "category":"Building & Trades",
            "subcategory":"Construction",
            "type":"Services"
        }
    ],
    "sg:phone":"+44 1752 704966",
    "sg:postcode":"PL6 8SF",
    "sg:province":"Devon",
    "sg:tags":[
        "builder"
    ],
    "wof:name":"Westover Construction",
    "wof:placetype":"venue"
},
  "geometry": {"coordinates":[-4.088458,50.413445],"type":"Point"}
}