{
  "type": "Feature",
  "properties": {
    "iso:country":"GB",
    "sg:address":"160-164 Long Lane",
    "sg:city":"Bexleyheath",
    "sg:classifiers":[
        {
            "category":"Retail",
            "subcategory":"Auto Repair",
            "type":"Services"
        }
    ],
    "sg:phone":"+44 20 8303 2299",
    "sg:postcode":"DA7 5AQ",
    "sg:province":"Kent",
    "sg:tags":[
        "modification",
        "garage"
    ],
    "wof:name":"W J King (Garages) Ltd.",
    "wof:placetype":"venue"
},
  "geometry": {"coordinates":[0.145644,51.46629],"type":"Point"}
}