{
  "type": "Feature",
  "properties": {
    "iso:country":"GB",
    "sg:address":"Unit 4/5, Tweedbank Industrial Estate, Tweedbank",
    "sg:city":"Galashiels",
    "sg:classifiers":[
        {
            "category":"Shopping",
            "subcategory":"Stationery & Office Supplies",
            "type":"Retail Goods"
        }
    ],
    "sg:phone":"+44 1896 751555",
    "sg:postcode":"TD1 3RS",
    "sg:province":"Scottish Borders",
    "wof:name":"Lynch McQueen Ltd.",
    "wof:placetype":"venue"
},
  "geometry": {"coordinates":[-2.802979,55.612156],"type":"Point"}
}