{
  "type": "Feature",
  "properties": {
    "addr:full":"Unit 6, Farringdon Business Park, Gosport Rd, Lower Farringdon Alton Hampshire GU34 3DZ",
    "addr:housenumber":"unit 6",
    "addr:postcode":"gu34 3dz",
    "addr:street":"Business Park Gosport Rd",
    "iso:country":"GB",
    "sg:address":"Unit 6, Farringdon Business Park, Gosport Rd, Lower Farringdon",
    "sg:city":"Alton",
    "sg:classifiers":[
        {
            "category":"Personal",
            "type":"Services"
        }
    ],
    "sg:phone":"+44 1420 587231",
    "sg:postcode":"GU34 3DZ",
    "sg:province":"Hampshire",
    "sg:tags":[
        "delivery"
    ],
    "wof:name":"Interlink Express Parcels",
    "wof:placetype":"venue"
},
  "geometry": {"coordinates":[-0.993929,51.110569],"type":"Point"}
}