{
  "type": "Feature",
  "properties": {
    "addr:full":"Victoria Avenue Industrial Estate Swanage Dorset BH19 1AU",
    "addr:postcode":"bh19 1au",
    "addr:street":"Victoria Avenue Industrial",
    "iso:country":"GB",
    "sg:address":"Victoria Avenue Industrial Estate",
    "sg:city":"Swanage",
    "sg:classifiers":[
        {
            "category":"Bus Charters",
            "type":"Transportation"
        }
    ],
    "sg:phone":"+44 1929 423622",
    "sg:postcode":"BH19 1AU",
    "sg:province":"Dorset",
    "sg:tags":[
        "hire",
        "coach"
    ],
    "wof:name":"South Dorset Coaches Ltd.",
    "wof:placetype":"venue"
},
  "geometry": {"coordinates":[-1.968984,50.613049],"type":"Point"}
}