{
  "type": "Feature",
  "properties": {
    "addr:full":"15-17 Quay Street Haverfordwest Pembrokeshire SA61 1BG",
    "addr:housenumber":"15-17",
    "addr:postcode":"sa61 1bg",
    "addr:street":"Quay Street",
    "iso:country":"GB",
    "sg:address":"15-17 Quay Street",
    "sg:city":"Haverfordwest",
    "sg:classifiers":[
        {
            "category":"Food & Beverages",
            "subcategory":"Specialty",
            "type":"Retail Goods"
        },
        {
            "category":"Shopping",
            "subcategory":"Pharmacy",
            "type":"Retail Goods"
        },
        {
            "category":"Home & Garden",
            "subcategory":"Kitchen Supply",
            "type":"Retail Goods"
        }
    ],
    "sg:postcode":"SA61 1BG",
    "sg:province":"Pembrokeshire",
    "sg:tags":[
        "medicine",
        "therapy",
        "product",
        "brewing",
        "health"
    ],
    "wof:name":"The Natural Grocer & Home Brew Shop",
    "wof:placetype":"venue"
},
  "geometry": {"coordinates":[-4.967244,51.800911],"type":"Point"}
}