{
  "type": "Feature",
  "properties": {
    "iso:country":"GB",
    "sg:address":"Bridge Park",
    "sg:city":"Ivybridge",
    "sg:classifiers":[
        {
            "category":"Organizations",
            "subcategory":"Membership Organization",
            "type":"Services"
        }
    ],
    "sg:postcode":"PL21 0AT",
    "sg:province":"Devon",
    "sg:tags":[
        "club"
    ],
    "wof:name":"Stowford Mill (Ivybridge) Bowling Club",
    "wof:placetype":"venue"
},
  "geometry": {"coordinates":[-3.918314,50.391113],"type":"Point"}
}