{
  "type": "Feature",
  "properties": {
    "addr:full":"Stapenhill Farm, Prestwood Drive, Stourton Stourbridge Shropshire DY7 5QT",
    "addr:postcode":"dy7 5qt",
    "addr:street":"Prestwood Drive",
    "iso:country":"GB",
    "sg:address":"Stapenhill Farm, Prestwood Drive, Stourton",
    "sg:city":"Stourbridge",
    "sg:classifiers":[
        {
            "category":"Retail",
            "subcategory":"Funeral Services",
            "type":"Services"
        }
    ],
    "sg:phone":"+44 1384 873356",
    "sg:postcode":"DY7 5QT",
    "sg:province":"Shropshire",
    "sg:tags":[
        "cemetery",
        "crematorium"
    ],
    "wof:name":"Prestwood Cattery",
    "wof:placetype":"venue"
},
  "geometry": {"coordinates":[-2.18621,52.468788],"type":"Point"}
}