{
  "type": "Feature",
  "properties": {
    "addr:full":"6 Beech Road Dunblane Perth and Kinross FK15 0AA",
    "addr:housenumber":"6",
    "addr:postcode":"fk15 0aa",
    "addr:street":"Beech Road",
    "iso:country":"GB",
    "sg:address":"6 Beech Road",
    "sg:city":"Dunblane",
    "sg:classifiers":[
        {
            "category":"Real Estate",
            "subcategory":"Real Estate Agent",
            "type":"Services"
        }
    ],
    "sg:postcode":"FK15 0AA",
    "sg:province":"Perth and Kinross",
    "wof:name":"Thomsons Property Services",
    "wof:placetype":"venue"
},
  "geometry": {"coordinates":[-3.9633860588,56.1864051819],"type":"Point"}
}