{
  "type": "Feature",
  "properties": {
    "addr:full":"93 Blatchington Road Hove East Sussex BN3 3YG",
    "addr:housenumber":"93",
    "addr:postcode":"bn3 3yg",
    "addr:street":"Blatchington Road",
    "iso:country":"GB",
    "sg:address":"93 Blatchington Road",
    "sg:city":"Hove",
    "sg:classifiers":[
        {
            "category":"Shopping",
            "subcategory":"News",
            "type":"Retail Goods"
        }
    ],
    "sg:phone":"+44 1273 734411",
    "sg:postcode":"BN3 3YG",
    "sg:province":"East Sussex",
    "sg:tags":[
        "newsagent"
    ],
    "wof:name":"A 1 News",
    "wof:placetype":"venue"
},
  "geometry": {"coordinates":[-0.1738680005,50.8313179016],"type":"Point"}
}