{
  "type": "Feature",
  "properties": {
    "iso:country":"GB",
    "sg:address":"The Acre, Lawford Heath Lane, Lawford Heath",
    "sg:city":"Rugby",
    "sg:classifiers":[
        {
            "category":"Building & Trades",
            "subcategory":"Construction",
            "type":"Services"
        }
    ],
    "sg:phone":"+44 1788 535146",
    "sg:postcode":"CV23 9EU",
    "sg:province":"Northamptonshire",
    "sg:tags":[
        "welder"
    ],
    "wof:name":"Paul Cashmore",
    "wof:placetype":"venue"
},
  "geometry": {"coordinates":[-1.333754,52.355186],"type":"Point"}
}