{
  "type": "Feature",
  "properties": {
    "iso:country":"GB",
    "sg:address":"8 College Farm Buildings, Tetbury Road",
    "sg:city":"Cirencester",
    "sg:classifiers":[
        {
            "category":"Professional",
            "subcategory":"Art Services",
            "type":"Services"
        }
    ],
    "sg:postcode":"GL7 6PY",
    "sg:province":"Gloucestershire",
    "sg:tags":[
        "framing"
    ],
    "wof:name":"Creative Picture Framing",
    "wof:placetype":"venue"
},
  "geometry": {"coordinates":[-1.9535410404,51.718547821],"type":"Point"}
}