{
  "type": "Feature",
  "properties": {
    "addr:full":"153 Bethnal Green Road London Greater London E2 7DG",
    "addr:housenumber":"153",
    "addr:postcode":"e2 7dg",
    "addr:street":"Bethnal Green Road",
    "iso:country":"GB",
    "sg:address":"153 Bethnal Green Road",
    "sg:city":"London",
    "sg:classifiers":[
        {
            "category":"Personal",
            "subcategory":"Skin Care",
            "type":"Services"
        }
    ],
    "sg:phone":"+44 20 7739 1369",
    "sg:postcode":"E2 7DG",
    "sg:province":"Greater London",
    "sg:tags":[
        "leather",
        "merchant"
    ],
    "wof:name":"M & B Leather Ltd.",
    "wof:placetype":"venue"
},
  "geometry": {"coordinates":[-0.070729,51.525486],"type":"Point"}
}