{
  "type": "Feature",
  "properties": {
    "addr:full":"Goddards Farm, Bowling Alley Farnham Hampshire GU10 5RJ",
    "addr:housenumber":"farnham",
    "addr:postcode":"gu10 5rj",
    "addr:street":"Hampshire",
    "iso:country":"GB",
    "sg:address":"Goddards Farm, Bowling Alley",
    "sg:city":"Farnham",
    "sg:classifiers":[
        {
            "category":"Community Center",
            "type":"Public Place"
        }
    ],
    "sg:phone":"+44 1252 851145",
    "sg:postcode":"GU10 5RJ",
    "sg:province":"Hampshire",
    "sg:tags":[
        "nursery",
        "centre"
    ],
    "wof:name":"Goddards Nurseries",
    "wof:placetype":"venue"
},
  "geometry": {"coordinates":[-0.8008300066,51.2143211365],"type":"Point"}
}