{
  "type": "Feature",
  "properties": {
    "iso:country":"GB",
    "sg:address":"208 Middleton Road",
    "sg:city":"Manchester",
    "sg:classifiers":[
        {
            "category":"Professional",
            "subcategory":"Lawyer & Legal Services",
            "type":"Services"
        }
    ],
    "sg:phone":"+44 161 740 7420",
    "sg:postcode":"M8 4NA",
    "sg:province":"Greater Manchester",
    "sg:tags":[
        "advice",
        "counselling"
    ],
    "wof:name":"Carers Information Consultancy",
    "wof:placetype":"venue"
},
  "geometry": {"coordinates":[-2.248769,53.518696],"type":"Point"}
}