{
  "type": "Feature",
  "properties": {
    "addr:full":"Chiswick House, Chiswick House Grounds, Burlington Lane London Greater London W4 2RP",
    "addr:postcode":"w4 2rp",
    "addr:street":"Chiswick;Grounds Burlington Lane",
    "iso:country":"GB",
    "sg:address":"Chiswick House, Chiswick House Grounds, Burlington Lane",
    "sg:city":"London",
    "sg:classifiers":[
        {
            "category":"Cafe",
            "type":"Food & Drink"
        }
    ],
    "sg:postcode":"W4 2RP",
    "sg:province":"Greater London",
    "sg:tags":[
        "tea",
        "room"
    ],
    "wof:name":"Burlington's Cafe",
    "wof:placetype":"venue"
},
  "geometry": {"coordinates":[-0.25736,51.486038],"type":"Point"}
}