{
  "type": "Feature",
  "properties": {
    "addr:full":"85 Walmersley Rd Bury Lancashire BL9 5AN",
    "addr:housenumber":"85",
    "addr:postcode":"bl9 5an",
    "addr:street":"Walmersley Rd",
    "iso:country":"GB",
    "sg:address":"85 Walmersley Rd",
    "sg:city":"Bury",
    "sg:classifiers":[
        {
            "category":"Organizations",
            "subcategory":"Religious Organization",
            "type":"Services"
        }
    ],
    "sg:phone":"+44 161 764 1638",
    "sg:postcode":"BL9 5AN",
    "sg:province":"Lancashire",
    "sg:tags":[
        "organisation"
    ],
    "wof:name":"Khizra Mosque",
    "wof:placetype":"venue"
},
  "geometry": {"coordinates":[-2.290078,53.59938],"type":"Point"}
}