{
  "type": "Feature",
  "properties": {
    "iso:country":"GB",
    "sg:address":"Prospect Bungalow, Burrowmoor Road",
    "sg:city":"March",
    "sg:classifiers":[
        {
            "category":"Farming",
            "subcategory":"Livestock Farm",
            "type":"Manufacturing & Wholesale Goods"
        }
    ],
    "sg:phone":"+44 1354 652197",
    "sg:postcode":"PE15 0YX",
    "sg:province":"Cambridgeshire",
    "sg:tags":[
        "others"
    ],
    "wof:name":"A Hawkins (Potatoes) Ltd.",
    "wof:placetype":"venue"
},
  "geometry": {"coordinates":[0.088905,52.551254],"type":"Point"}
}