{
  "type": "Feature",
  "properties": {
    "addr:full":"South Parade, Thorne Doncaster East Riding of Yorkshire DN8 5DZ",
    "addr:postcode":"dn8 5dz",
    "addr:street":"South Parade;Riding",
    "iso:country":"GB",
    "sg:address":"South Parade, Thorne",
    "sg:city":"Doncaster",
    "sg:classifiers":[
        {
            "category":"Bars & Pubs",
            "type":"Food & Drink"
        }
    ],
    "sg:phone":"+44 1405 813688",
    "sg:postcode":"DN8 5DZ",
    "sg:province":"East Riding of Yorkshire",
    "sg:tags":[
        "pubs",
        "inn"
    ],
    "wof:name":"Canal Tavern",
    "wof:placetype":"venue"
},
  "geometry": {"coordinates":[-0.961637,53.611591],"type":"Point"}
}