{
  "type": "Feature",
  "properties": {
    "addr:full":"5 Litchard Cross Bridgend Bridgend CF31 1NZ",
    "addr:housenumber":"5",
    "addr:postcode":"cf31 1nz",
    "addr:street":"Litchard Cross",
    "iso:country":"GB",
    "sg:address":"5 Litchard Cross",
    "sg:city":"Bridgend",
    "sg:classifiers":[
        {
            "category":"Building & Trades",
            "subcategory":"Construction",
            "type":"Services"
        }
    ],
    "sg:phone":"+44 1656 647665",
    "sg:postcode":"CF31 1NZ",
    "sg:province":"Bridgend",
    "sg:tags":[
        "flooring"
    ],
    "wof:name":"Contract Flooring Services",
    "wof:placetype":"venue"
},
  "geometry": {"coordinates":[-3.573017,51.521507],"type":"Point"}
}