{
  "type": "Feature",
  "properties": {
    "iso:country":"GB",
    "sg:address":"27a Maxwell Road",
    "sg:city":"Northwood",
    "sg:classifiers":[
        {
            "category":"Professional",
            "subcategory":"Computer Services",
            "type":"Services"
        }
    ],
    "sg:phone":"+44 1895 623355",
    "sg:postcode":"HA6 2XY",
    "sg:province":"Greater London",
    "sg:tags":[
        "system",
        "software"
    ],
    "wof:name":"Sarbrook Ltd",
    "wof:placetype":"venue"
},
  "geometry": {"coordinates":[-0.425406,51.611111],"type":"Point"}
}