{
  "type": "Feature",
  "properties": {
    "addr:full":"Unit 2 Gidleys Meadow Exeter Devon EX6 7QB",
    "addr:housenumber":"unit 2",
    "addr:postcode":"ex6 7qb",
    "addr:street":"Gidleys Meadow",
    "iso:country":"GB",
    "sg:address":"Unit 2 Gidleys Meadow",
    "sg:city":"Exeter",
    "sg:classifiers":[
        {
            "category":"Food & Beverages",
            "subcategory":"Bakery",
            "type":"Retail Goods"
        },
        {
            "category":"Home & Garden",
            "subcategory":"Kitchen Supply",
            "type":"Retail Goods"
        }
    ],
    "sg:phone":"+44 1647 252917",
    "sg:postcode":"EX6 7QB",
    "sg:province":"Devon",
    "sg:tags":[
        "equipment",
        "baker"
    ],
    "wof:name":"Teign Valley Bakery",
    "wof:placetype":"venue"
},
  "geometry": {"coordinates":[-3.6445600986,50.6556510925],"type":"Point"}
}