{
  "type": "Feature",
  "properties": {
    "addr:full":"Catterall Gates Lane, Catterall, Garstang Preston Lancashire PR3 1XP",
    "addr:postcode":"pr3 1xp",
    "addr:street":"Gates Lane",
    "iso:country":"GB",
    "sg:address":"Catterall Gates Lane, Catterall, Garstang",
    "sg:city":"Preston",
    "sg:classifiers":[
        {
            "category":"Freight",
            "type":"Transportation"
        },
        {
            "category":"Manufacturing",
            "subcategory":"Building Materials",
            "type":"Manufacturing & Wholesale Goods"
        },
        {
            "category":"Home & Garden",
            "subcategory":"Furniture",
            "type":"Retail Goods"
        }
    ],
    "sg:phone":"+44 1995 603431",
    "sg:postcode":"PR3 1XP",
    "sg:province":"Lancashire",
    "sg:tags":[
        "product",
        "haulage",
        "concrete",
        "distributor",
        "mnfrs",
        "road"
    ],
    "wof:name":"Brierkrete Ltd.",
    "wof:placetype":"venue"
},
  "geometry": {"coordinates":[-2.7737839222,53.9073066711],"type":"Point"}
}