{
  "type": "Feature",
  "properties": {
    "addr:full":"Burrell Mead, 47 Beckenham Road West Wickham Kent BR4 0QS",
    "addr:housenumber":"47",
    "addr:postcode":"br4 0qs",
    "addr:street":"Burrell Mead;Beckenham Road",
    "iso:country":"GB",
    "sg:address":"Burrell Mead, 47 Beckenham Road",
    "sg:city":"West Wickham",
    "sg:classifiers":[
        {
            "category":"Health Services",
            "subcategory":"Nursing And Care Facility",
            "type":"Services"
        }
    ],
    "sg:phone":"+44 20 8776 0455",
    "sg:postcode":"BR4 0QS",
    "sg:province":"Kent",
    "sg:tags":[
        "home"
    ],
    "wof:name":"Westwood Housing Association Ltd.",
    "wof:placetype":"venue"
},
  "geometry": {"coordinates":[-0.0093240002,51.3745880127],"type":"Point"}
}