{
  "type": "Feature",
  "properties": {
    "addr:full":"Dukes Lane Chelmsford Essex CM2 6AD",
    "addr:postcode":"cm2 6ad",
    "addr:street":"Dukes Lane",
    "iso:country":"GB",
    "sg:address":"Dukes Lane",
    "sg:city":"Chelmsford",
    "sg:classifiers":[
        {
            "category":"Restaurant",
            "type":"Food & Drink"
        }
    ],
    "sg:phone":"+44 1245 450695",
    "sg:postcode":"CM2 6AD",
    "sg:province":"Essex",
    "wof:name":"Chelmer Tavern",
    "wof:placetype":"venue"
},
  "geometry": {"coordinates":[0.499115,51.740578],"type":"Point"}
}