{
  "type": "Feature",
  "properties": {
    "addr:full":"The Warehouse, Mere Rd Attleborough Norfolk NR17 1HP",
    "addr:postcode":"nr17 1hp",
    "addr:street":"Mere Rd",
    "iso:country":"GB",
    "sg:address":"The Warehouse, Mere Rd",
    "sg:city":"Attleborough",
    "sg:classifiers":[
        {
            "category":"Shopping",
            "subcategory":"Clothing, Apparel, & Fashions",
            "type":"Retail Goods"
        }
    ],
    "sg:phone":"+44 1953 483747",
    "sg:postcode":"NR17 1HP",
    "sg:province":"Norfolk",
    "sg:tags":[
        "ladieswear"
    ],
    "wof:name":"Zipps Ltd",
    "wof:placetype":"venue"
},
  "geometry": {"coordinates":[1.014435,52.519054],"type":"Point"}
}