{
  "type": "Feature",
  "properties": {
    "addr:full":"1 Mowlem Cotts, Tillyfourie Inverurie Aberdeenshire AB51 7SP",
    "addr:housenumber":"1;cotts tillyfourie",
    "addr:postcode":"ab51 7sp",
    "addr:street":"Mowlem;Inverurie",
    "iso:country":"GB",
    "sg:address":"1 Mowlem Cotts, Tillyfourie",
    "sg:city":"Inverurie",
    "sg:classifiers":[
        {
            "category":"Professional",
            "subcategory":"Management & Consulting",
            "type":"Services"
        }
    ],
    "sg:phone":"+44 1975 563763",
    "sg:postcode":"AB51 7SP",
    "sg:province":"Aberdeenshire",
    "sg:tags":[
        "consultant",
        "training"
    ],
    "wof:name":"C P D North",
    "wof:placetype":"venue"
},
  "geometry": {"coordinates":[-2.614248,57.209381],"type":"Point"}
}