{
  "type": "Feature",
  "properties": {
    "addr:full":"West One House, Saint Georges Road Cheltenham Gloucestershire GL50 3DT",
    "addr:postcode":"gl50 3dt",
    "addr:street":"Saint Georges Road",
    "iso:country":"GB",
    "sg:address":"West One House, Saint Georges Road",
    "sg:city":"Cheltenham",
    "sg:classifiers":[
        {
            "category":"Professional",
            "subcategory":"Computer Services",
            "type":"Services"
        }
    ],
    "sg:postcode":"GL50 3DT",
    "sg:province":"Gloucestershire",
    "sg:tags":[
        "consultant"
    ],
    "wof:name":"The Wheway Group Ltd",
    "wof:placetype":"venue"
},
  "geometry": {"coordinates":[-2.091276,51.9016],"type":"Point"}
}