{
  "type": "Feature",
  "properties": {
    "iso:country":"GB",
    "sg:address":"93 Selly Park Rd",
    "sg:city":"Birmingham",
    "sg:classifiers":[
        {
            "category":"Professional",
            "subcategory":"Computer Services",
            "type":"Services"
        }
    ],
    "sg:phone":"+44 121 472 0002",
    "sg:postcode":"B29 7LH",
    "sg:province":"West Midlands",
    "sg:tags":[
        "consultant"
    ],
    "wof:name":"J N C Computer Consultants Ltd",
    "wof:placetype":"venue"
},
  "geometry": {"coordinates":[-1.9223790169,52.4411621094],"type":"Point"}
}