{
  "type": "Feature",
  "properties": {
    "addr:full":"Kingfisher Center, Burnley Rd, Rautenstall Rossendale Lancashire BB4 8ES",
    "addr:postcode":"bb4 8es",
    "addr:street":"Burnley Rd",
    "iso:country":"GB",
    "sg:address":"Kingfisher Center, Burnley Rd, Rautenstall",
    "sg:city":"Rossendale",
    "sg:classifiers":[
        {
            "category":"Professional",
            "subcategory":"Detective & Security Services",
            "type":"Services"
        }
    ],
    "sg:phone":"+44 1706 226684",
    "sg:postcode":"BB4 8ES",
    "sg:province":"Lancashire",
    "wof:name":"Pentagon Secruity Services Uk Ltd",
    "wof:placetype":"venue"
},
  "geometry": {"coordinates":[-2.274824,53.708961],"type":"Point"}
}