{
  "type": "Feature",
  "properties": {
    "iso:country":"GB",
    "sg:address":"Princes Building, Bath Road",
    "sg:city":"Cowes",
    "sg:classifiers":[
        {
            "category":"Restaurant",
            "type":"Food & Drink"
        }
    ],
    "sg:postcode":"PO31 7QN",
    "sg:province":"Isle of Wight",
    "sg:tags":[
        "italian"
    ],
    "wof:name":"Capri Italian Restaurant",
    "wof:placetype":"venue"
},
  "geometry": {"coordinates":[-1.297866,50.758121],"type":"Point"}
}