{
  "type": "Feature",
  "properties": {
    "iso:country":"GB",
    "sg:address":"52 Brunels Way",
    "sg:city":"Highbridge",
    "sg:classifiers":[
        {
            "category":"Home & Garden",
            "subcategory":"Household Appliances",
            "type":"Retail Goods"
        }
    ],
    "sg:postcode":"TA9 3LG",
    "sg:province":"Somerset",
    "sg:tags":[
        "electrical"
    ],
    "wof:name":"Jeff Fisher Domestic Appliances",
    "wof:placetype":"venue"
},
  "geometry": {"coordinates":[-2.971564,51.22797],"type":"Point"}
}