{
  "type": "Feature",
  "properties": {
    "addr:full":"189 Upper Street London Greater London N1 1RQ",
    "addr:housenumber":"189",
    "addr:postcode":"n1 1rq",
    "addr:street":"Upper Street",
    "iso:country":"GB",
    "sg:address":"189 Upper Street",
    "sg:city":"London",
    "sg:classifiers":[
        {
            "category":"Restaurant",
            "type":"Food & Drink"
        }
    ],
    "sg:phone":"+44 20 7226 2305",
    "sg:postcode":"N1 1RQ",
    "sg:province":"Greater London",
    "wof:name":"Marsdens Restaurant",
    "wof:placetype":"venue"
},
  "geometry": {"coordinates":[-0.103194,51.542477],"type":"Point"}
}