{
  "type": "Feature",
  "properties": {
    "addr:full":"Sunnybank Yard, Off Hannah Street Darwen Lancashire BB3 2AH",
    "addr:postcode":"bb3 2ah",
    "addr:street":"Off Hannah Street",
    "iso:country":"GB",
    "sg:address":"Sunnybank Yard, Off Hannah Street",
    "sg:city":"Darwen",
    "sg:classifiers":[
        {
            "category":"Building & Trades",
            "subcategory":"Construction",
            "type":"Services"
        }
    ],
    "sg:phone":"+44 1254 702303",
    "sg:postcode":"BB3 2AH",
    "sg:province":"Lancashire",
    "sg:tags":[
        "builder"
    ],
    "wof:name":"George Aird Ltd.",
    "wof:placetype":"venue"
},
  "geometry": {"coordinates":[-2.467169,53.694199],"type":"Point"}
}