{
  "type": "Feature",
  "properties": {
    "addr:full":"37 Cherrywood Road, Streetly Sutton Coldfield Staffordshire B74 3RU",
    "addr:housenumber":"37",
    "addr:postcode":"b74 3ru",
    "addr:street":"Cherrywood Road",
    "iso:country":"GB",
    "sg:address":"37 Cherrywood Road, Streetly",
    "sg:city":"Sutton Coldfield",
    "sg:classifiers":[
        {
            "category":"Professional",
            "subcategory":"Accounting & Tax Preparation",
            "type":"Services"
        }
    ],
    "sg:phone":"+44 121 353 7742",
    "sg:postcode":"B74 3RU",
    "sg:province":"Staffordshire",
    "sg:tags":[
        "accountant"
    ],
    "wof:name":"Colin Flanagan",
    "wof:placetype":"venue"
},
  "geometry": {"coordinates":[-1.8987259865,52.5794792175],"type":"Point"}
}