{
  "type": "Feature",
  "properties": {
    "iso:country":"GB",
    "sg:address":"Tynevale Works, High Street, Newburn",
    "sg:city":"Newcastle-upon-tyne",
    "sg:classifiers":[
        {
            "category":"Manufacturing",
            "subcategory":"Glass & Minerals",
            "type":"Manufacturing & Wholesale Goods"
        }
    ],
    "sg:phone":"+44 191 264 6801",
    "sg:postcode":"NE15 8LN",
    "sg:province":"Northumberland",
    "sg:tags":[
        "product"
    ],
    "wof:name":"Multi-Lab Ltd.",
    "wof:placetype":"venue"
},
  "geometry": {"coordinates":[-1.743449,54.985004],"type":"Point"}
}