{
  "type": "Feature",
  "properties": {
    "addr:full":"183 Whitchurch Lane Edgware Greater London HA8 6QT",
    "addr:housenumber":"183",
    "addr:postcode":"ha8 6qt",
    "addr:street":"Whitchurch Lane",
    "iso:country":"GB",
    "sg:address":"183 Whitchurch Lane",
    "sg:city":"Edgware",
    "sg:classifiers":[
        {
            "category":"Building & Trades",
            "subcategory":"Construction",
            "type":"Services"
        }
    ],
    "sg:phone":"+44 20 8952 6967",
    "sg:postcode":"HA8 6QT",
    "sg:province":"Greater London",
    "sg:tags":[
        "builder"
    ],
    "wof:name":"Ivor Azzopardi",
    "wof:placetype":"venue"
},
  "geometry": {"coordinates":[-0.2906090021,51.6076622009],"type":"Point"}
}