{
  "type": "Feature",
  "properties": {
    "addr:full":"339 Fleet Rd Fleet Hampshire GU51 3BU",
    "addr:housenumber":"339",
    "addr:postcode":"gu51 3bu",
    "addr:street":"Fleet Rd",
    "iso:country":"GB",
    "sg:address":"339 Fleet Rd",
    "sg:city":"Fleet",
    "sg:classifiers":[
        {
            "category":"Shopping",
            "subcategory":"Bicycles & Sporting Goods",
            "type":"Retail Goods"
        }
    ],
    "sg:postcode":"GU51 3BU",
    "sg:province":"Hampshire",
    "sg:tags":[
        "cycle",
        "accessory"
    ],
    "wof:name":"Cycle Style",
    "wof:placetype":"venue"
},
  "geometry": {"coordinates":[-0.8375689983,51.2850112915],"type":"Point"}
}