{
  "type": "Feature",
  "properties": {
    "addr:full":"Software Support Line, 2 Lambridge Bath Bath and North East Somerset BA1 6BJ",
    "addr:postcode":"ba1 6bj",
    "addr:street":"Line 2 Lambridge",
    "iso:country":"GB",
    "sg:address":"Software Support Line, 2 Lambridge",
    "sg:city":"Bath",
    "sg:classifiers":[
        {
            "category":"Utilities",
            "subcategory":"Fuel Oil & Lpg",
            "type":"Services"
        }
    ],
    "sg:postcode":"BA1 6BJ",
    "sg:province":"Bath and North East Somerset",
    "sg:tags":[
        "gas"
    ],
    "wof:name":"Kappa Engineering",
    "wof:placetype":"venue"
},
  "geometry": {"coordinates":[-2.3460590839,51.3956718445],"type":"Point"}
}