{
  "type": "Feature",
  "properties": {
    "addr:full":"First Church, 16a Primrose Hill Chelmsford Essex CM1 2RQ",
    "addr:housenumber":"16a",
    "addr:postcode":"cm1 2rq",
    "addr:street":"Primrose Hill",
    "iso:country":"GB",
    "sg:address":"First Church, 16a Primrose Hill",
    "sg:city":"Chelmsford",
    "sg:classifiers":[
        {
            "category":"Place Of Worship",
            "type":"Public Place"
        },
        {
            "category":"Shopping",
            "subcategory":"Books",
            "type":"Retail Goods"
        }
    ],
    "sg:phone":"+44 1245 266108",
    "sg:postcode":"CM1 2RQ",
    "sg:province":"Essex",
    "sg:tags":[
        "bookseller"
    ],
    "wof:name":"Christian Science First Church",
    "wof:placetype":"venue"
},
  "geometry": {"coordinates":[0.46191,51.738312],"type":"Point"}
}