{
  "type": "Feature",
  "properties": {
    "iso:country":"GB",
    "sg:address":"Hilton House, Steynton Road",
    "sg:city":"Milford Haven",
    "sg:classifiers":[
        {
            "category":"Government",
            "subcategory":"Office",
            "type":"Public Place"
        },
        {
            "category":"Social Services",
            "subcategory":"Adult Care",
            "type":"Services"
        },
        {
            "category":"Social Services",
            "subcategory":"Retirement Home",
            "type":"Services"
        }
    ],
    "sg:phone":"+44 1646 693832",
    "sg:postcode":"SA73 1BD",
    "sg:province":"Pembrokeshire",
    "sg:tags":[
        "housing",
        "local",
        "accommodation",
        "sheltered"
    ],
    "wof:name":"Hilton House Sheltered Housing",
    "wof:placetype":"venue"
},
  "geometry": {"coordinates":[-5.019641,51.725224],"type":"Point"}
}