{
  "type": "Feature",
  "properties": {
    "addr:full":"19 Ratcliffe Road Fakenham Norfolk NR21 8AY",
    "addr:housenumber":"19",
    "addr:postcode":"nr21 8ay",
    "addr:street":"Ratcliffe Road",
    "iso:country":"GB",
    "sg:address":"19 Ratcliffe Road",
    "sg:city":"Fakenham",
    "sg:classifiers":[
        {
            "category":"Military Area",
            "subcategory":"Air Force Base",
            "type":"Public Place"
        }
    ],
    "sg:postcode":"NR21 8AY",
    "sg:province":"Norfolk",
    "sg:tags":[
        "taxi",
        "hire",
        "private"
    ],
    "wof:name":"Lavender Taxi Service",
    "wof:placetype":"venue"
},
  "geometry": {"coordinates":[0.8514860272,52.8291625977],"type":"Point"}
}