{
  "type": "Feature",
  "properties": {
    "addr:full":"Bowerbank Way, Gillwilly Industrial Estate Penrith Cumbria CA11 9BN",
    "addr:postcode":"ca11 9bn",
    "addr:street":"Bowerbank Way Gillwilly Industrial Estate",
    "iso:country":"GB",
    "sg:address":"Bowerbank Way, Gillwilly Industrial Estate",
    "sg:city":"Penrith",
    "sg:classifiers":[
        {
            "category":"Manufacturing",
            "subcategory":"Tools & Machinery",
            "type":"Manufacturing & Wholesale Goods"
        },
        {
            "category":"Shopping",
            "subcategory":"Discount & Variety Stores",
            "type":"Retail Goods"
        }
    ],
    "sg:phone":"+44 1768 868995",
    "sg:postcode":"CA11 9BN",
    "sg:province":"Cumbria",
    "sg:tags":[
        "cleaning",
        "supply"
    ],
    "wof:name":"Alto Cleaning Systems (U K) Ltd.",
    "wof:placetype":"venue"
},
  "geometry": {"coordinates":[-2.765873909,54.6674499512],"type":"Point"}
}