{
  "type": "Feature",
  "properties": {
    "addr:full":"Queen Street, Sturton Leeds West Yorkshire LS10 1SL",
    "addr:postcode":"ls10 1sl",
    "addr:street":"Queen Street",
    "iso:country":"GB",
    "sg:address":"Queen Street, Sturton",
    "sg:city":"Leeds",
    "sg:classifiers":[
        {
            "category":"Professional",
            "subcategory":"Engineering",
            "type":"Services"
        }
    ],
    "sg:phone":"+44 113 276 0020",
    "sg:postcode":"LS10 1SL",
    "sg:province":"West Yorkshire",
    "sg:tags":[
        "contractor",
        "electrical",
        "engineer"
    ],
    "wof:name":"C P M (Contracts) Ltd.",
    "wof:placetype":"venue"
},
  "geometry": {"coordinates":[-1.513201952,53.7721633911],"type":"Point"}
}