{
  "type": "Feature",
  "properties": {
    "addr:full":"6 Berryfields, Aldridge Walsall Staffordshire WS9 0EE",
    "addr:housenumber":"6",
    "addr:postcode":"ws9 0ee",
    "addr:street":"Berryfields",
    "iso:country":"GB",
    "sg:address":"6 Berryfields, Aldridge",
    "sg:city":"Walsall",
    "sg:classifiers":[
        {
            "category":"Building & Trades",
            "subcategory":"Plumbing",
            "type":"Services"
        }
    ],
    "sg:postcode":"WS9 0EE",
    "sg:province":"Staffordshire",
    "sg:tags":[
        "central",
        "heating"
    ],
    "wof:name":"Bird,Paul,",
    "wof:placetype":"venue"
},
  "geometry": {"coordinates":[-1.9411849976,52.5999908447],"type":"Point"}
}