{
  "type": "Feature",
  "properties": {
    "addr:full":"Vittoria House, 296 Price Street Birkenhead Merseyside CH41 3PT",
    "addr:housenumber":"296",
    "addr:postcode":"ch41 3pt",
    "addr:street":"Price Street",
    "iso:country":"GB",
    "sg:address":"Vittoria House, 296 Price Street",
    "sg:city":"Birkenhead",
    "sg:classifiers":[
        {
            "category":"Manufacturing",
            "subcategory":"Metals",
            "type":"Manufacturing & Wholesale Goods"
        },
        {
            "category":"Professional",
            "subcategory":"Engineering",
            "type":"Services"
        }
    ],
    "sg:phone":"+44 151 647 5531",
    "sg:postcode":"CH41 3PT",
    "sg:province":"Merseyside",
    "sg:tags":[
        "precision",
        "engineer"
    ],
    "sg:website":"http://www.CML-GROUP.COM",
    "wof:name":"C M L Group Ltd",
    "wof:placetype":"venue"
},
  "geometry": {"coordinates":[-3.0306360722,53.3971977234],"type":"Point"}
}