{
  "type": "Feature",
  "properties": {
    "iso:country":"GB",
    "sg:address":"Meadow Place, Wellmeadow",
    "sg:city":"Blairgowrie",
    "sg:classifiers":[
        {
            "category":"Shopping",
            "subcategory":"Books",
            "type":"Retail Goods"
        }
    ],
    "sg:phone":"+44 1250 875855",
    "sg:postcode":"PH10 6NQ",
    "sg:province":"Perth and Kinross",
    "sg:tags":[
        "second-hand"
    ],
    "wof:name":"Blairgowrie Books",
    "wof:placetype":"venue"
},
  "geometry": {"coordinates":[-3.336929,56.591431],"type":"Point"}
}