{
  "type": "Feature",
  "properties": {
    "addr:full":"56 Rowsley St Leicester Leicestershire LE5 5JL",
    "addr:housenumber":"56",
    "addr:postcode":"le5 5jl",
    "addr:street":"Rowsley St",
    "iso:country":"GB",
    "sg:address":"56 Rowsley St",
    "sg:city":"Leicester",
    "sg:classifiers":[
        {
            "category":"Health Services",
            "subcategory":"Clinic",
            "type":"Services"
        }
    ],
    "sg:phone":"+44 116 273 4599",
    "sg:postcode":"LE5 5JL",
    "sg:province":"Leicestershire",
    "sg:tags":[
        "private"
    ],
    "wof:name":"Atma-reiki Healing Centre",
    "wof:placetype":"venue"
},
  "geometry": {"coordinates":[-1.1064840555,52.6277351379],"type":"Point"}
}