{
  "type": "Feature",
  "properties": {
    "addr:full":"1 Rydal Street Carlisle Cumbria CA1 1SQ",
    "addr:housenumber":"1",
    "addr:postcode":"ca1 1sq",
    "addr:street":"Rydal Street",
    "iso:country":"GB",
    "sg:address":"1 Rydal Street",
    "sg:city":"Carlisle",
    "sg:classifiers":[
        {
            "category":"Organizations",
            "subcategory":"Non-profit Organization",
            "type":"Services"
        }
    ],
    "sg:phone":"+44 1228 819299",
    "sg:postcode":"CA1 1SQ",
    "sg:province":"Cumbria",
    "sg:tags":[
        "organisation",
        "voluntary",
        "charity"
    ],
    "wof:name":"Alzheimer's Society",
    "wof:placetype":"venue"
},
  "geometry": {"coordinates":[-2.9273579121,54.8895606995],"type":"Point"}
}