{
  "type": "Feature",
  "properties": {
    "addr:full":"Red Lion Lane London Greater London SE18 4LD",
    "addr:postcode":"se18 4ld",
    "addr:street":"Red Lion Lane",
    "iso:country":"GB",
    "sg:address":"Red Lion Lane",
    "sg:city":"London",
    "sg:classifiers":[
        {
            "category":"Education",
            "subcategory":"School",
            "type":"Public Place"
        },
        {
            "category":"Government",
            "subcategory":"Office",
            "type":"Public Place"
        }
    ],
    "sg:phone":"+44 20 8856 7156",
    "sg:postcode":"SE18 4LD",
    "sg:province":"Greater London",
    "sg:tags":[
        "local",
        "authority"
    ],
    "wof:name":"Eaglesfield Secondary School",
    "wof:placetype":"venue"
},
  "geometry": {"coordinates":[0.06133,51.473122],"type":"Point"}
}