{
  "type": "Feature",
  "properties": {
    "iso:country":"GB",
    "sg:address":"Unit 43, Okus Trading Estate, Okus Road",
    "sg:city":"Swindon",
    "sg:classifiers":[
        {
            "category":"Manufacturing",
            "subcategory":"Lumber",
            "type":"Manufacturing & Wholesale Goods"
        }
    ],
    "sg:phone":"+44 1793 615861",
    "sg:postcode":"SN1 4PA",
    "sg:province":"Wiltshire",
    "sg:tags":[
        "importer",
        "merchants",
        "agent",
        "timber"
    ],
    "wof:name":"D W Archer Ltd.",
    "wof:placetype":"venue"
},
  "geometry": {"coordinates":[-1.781814,51.561764],"type":"Point"}
}