{
  "type": "Feature",
  "properties": {
    "addr:full":"Flat 14, 147 Gloucester Terrace London Greater London W2 6DX",
    "addr:housenumber":"flat 14 147",
    "addr:postcode":"w2 6dx",
    "addr:street":"Gloucester Terrace",
    "iso:country":"GB",
    "sg:address":"Flat 14, 147 Gloucester Terrace",
    "sg:city":"London",
    "sg:classifiers":[
        {
            "category":"Professional",
            "subcategory":"Engineering",
            "type":"Services"
        }
    ],
    "sg:phone":"+44 20 7402 9534",
    "sg:postcode":"W2 6DX",
    "sg:province":"Greater London",
    "sg:tags":[
        "consultant",
        "consulting",
        "engineer",
        "structural"
    ],
    "wof:name":"R F Gill & Associates",
    "wof:placetype":"venue"
},
  "geometry": {"coordinates":[-0.1837390065,51.5170898438],"type":"Point"}
}