{
  "type": "Feature",
  "properties": {
    "addr:full":"Unit 18a, Ben Nevis Industrial Estate Fort William Highland PH33 6PR",
    "addr:housenumber":"unit 18a",
    "addr:postcode":"ph33 6pr",
    "addr:street":"Ben Nevis Industrial Estate",
    "iso:country":"GB",
    "sg:address":"Unit 18a, Ben Nevis Industrial Estate",
    "sg:city":"Fort William",
    "sg:classifiers":[
        {
            "category":"Building & Trades",
            "subcategory":"Construction",
            "type":"Services"
        }
    ],
    "sg:phone":"+44 1397 704188",
    "sg:postcode":"PH33 6PR",
    "sg:province":"Highland",
    "sg:tags":[
        "joiner",
        "carpenter"
    ],
    "wof:name":"G C F Joiners & Contractors",
    "wof:placetype":"venue"
},
  "geometry": {"coordinates":[-5.097840786,56.8211631775],"type":"Point"}
}