{
  "type": "Feature",
  "properties": {
    "addr:full":"52 Plassey St Penarth The Vale of Glamorgan CF64 1EN",
    "addr:housenumber":"52",
    "addr:postcode":"cf64 1en",
    "addr:street":"Plassey St;Vale",
    "iso:country":"GB",
    "sg:address":"52 Plassey St",
    "sg:city":"Penarth",
    "sg:classifiers":[
        {
            "category":"Shopping",
            "subcategory":"Books",
            "type":"Retail Goods"
        }
    ],
    "sg:postcode":"CF64 1EN",
    "sg:province":"The Vale of Glamorgan",
    "sg:tags":[
        "bookseller"
    ],
    "wof:name":"Edwards,Anne,",
    "wof:placetype":"venue"
},
  "geometry": {"coordinates":[-3.174996,51.440472],"type":"Point"}
}