{
  "type": "Feature",
  "properties": {
    "addr:full":"13 Terrace Road Aberystwyth Ceredigion SY23 1NY",
    "addr:housenumber":"13",
    "addr:postcode":"sy23 1ny",
    "addr:street":"Terrace Road",
    "iso:country":"GB",
    "sg:address":"13 Terrace Road",
    "sg:city":"Aberystwyth",
    "sg:classifiers":[
        {
            "category":"Utilities",
            "type":"Services"
        }
    ],
    "sg:postcode":"SY23 1NY",
    "sg:province":"Ceredigion",
    "sg:tags":[
        "internet"
    ],
    "wof:name":"Caffi'r Web Cafe",
    "wof:placetype":"venue"
},
  "geometry": {"coordinates":[-4.082356,52.41544],"type":"Point"}
}