{
  "type": "Feature",
  "properties": {
    "addr:full":"341 Station Road Harrow Greater London HA1 2AA",
    "addr:housenumber":"341",
    "addr:postcode":"ha1 2aa",
    "addr:street":"Station Road",
    "iso:country":"GB",
    "sg:address":"341 Station Road",
    "sg:city":"Harrow",
    "sg:classifiers":[
        {
            "category":"Shopping",
            "subcategory":"Thrift Store",
            "type":"Retail Goods"
        },
        {
            "category":"Organizations",
            "subcategory":"Non-profit Organization",
            "type":"Services"
        }
    ],
    "sg:phone":"+44 20 8427 9125",
    "sg:postcode":"HA1 2AA",
    "sg:province":"Greater London",
    "sg:tags":[
        "shop",
        "organisation",
        "voluntary",
        "charity"
    ],
    "wof:name":"Scope",
    "wof:placetype":"venue"
},
  "geometry": {"coordinates":[-0.334258,51.580463],"type":"Point"}
}