{
  "type": "Feature",
  "properties": {
    "addr:full":"Unit 3 Cock La High Wycombe Buckinghamshire HP13 7DE",
    "addr:housenumber":"unit 3",
    "addr:postcode":"hp13 7de",
    "addr:street":"Cock La High Wycombe",
    "iso:country":"GB",
    "sg:address":"Unit 3 Cock La",
    "sg:city":"High Wycombe",
    "sg:classifiers":[
        {
            "category":"Manufacturing",
            "subcategory":"Electronics",
            "type":"Manufacturing & Wholesale Goods"
        }
    ],
    "sg:phone":"+44 1494 510855",
    "sg:postcode":"HP13 7DE",
    "sg:province":"Buckinghamshire",
    "sg:tags":[
        "control",
        "component",
        "-",
        "electronic"
    ],
    "wof:name":"Protocol Technology",
    "wof:placetype":"venue"
},
  "geometry": {"coordinates":[-0.708979,51.62661],"type":"Point"}
}