{
  "type": "Feature",
  "properties": {
    "iso:country":"GB",
    "sg:address":"24 Ranelagh Road",
    "sg:city":"Wellingborough",
    "sg:classifiers":[
        {
            "category":"Farming",
            "subcategory":"Nursery",
            "type":"Manufacturing & Wholesale Goods"
        }
    ],
    "sg:phone":"+44 1933 442121",
    "sg:postcode":"NN8 1JG",
    "sg:province":"Northamptonshire",
    "sg:tags":[
        "creche"
    ],
    "wof:name":"Playmates Childrens Day Nursery",
    "wof:placetype":"venue"
},
  "geometry": {"coordinates":[-0.683912,52.30349],"type":"Point"}
}