{
  "type": "Feature",
  "properties": {
    "iso:country":"GB",
    "sg:address":"Great Clowes St",
    "sg:city":"Manchester",
    "sg:classifiers":[
        {
            "category":"Health Services",
            "subcategory":"Doctor",
            "type":"Services"
        }
    ],
    "sg:phone":"+44 161 839 2730",
    "sg:postcode":"M7 1RD",
    "sg:province":"Greater Manchester",
    "sg:tags":[
        "practitioners"
    ],
    "wof:name":"Sultan, M",
    "wof:placetype":"venue"
},
  "geometry": {"coordinates":[-2.25882,53.49358],"type":"Point"}
}