{
  "type": "Feature",
  "properties": {
    "addr:full":"Cragg End Farm, Rogerscale Cockermouth Cumbria CA13 0RG",
    "addr:postcode":"ca13 0rg",
    "addr:street":"Cragg;Rogerscale",
    "iso:country":"GB",
    "sg:address":"Cragg End Farm, Rogerscale",
    "sg:city":"Cockermouth",
    "sg:classifiers":[
        {
            "category":"Farming",
            "subcategory":"Farm",
            "type":"Manufacturing & Wholesale Goods"
        }
    ],
    "sg:postcode":"CA13 0RG",
    "sg:province":"Cumbria",
    "sg:tags":[
        "mixed",
        "crop"
    ],
    "wof:name":"J H Steel",
    "wof:placetype":"venue"
},
  "geometry": {"coordinates":[-3.4241859913,54.6712837219],"type":"Point"}
}