{
  "type": "Feature",
  "properties": {
    "addr:full":"Strathmore, Oyne Insch Aberdeenshire AB52 6QT",
    "addr:postcode":"ab52 6qt",
    "addr:street":"Oyne",
    "iso:country":"GB",
    "sg:address":"Strathmore, Oyne",
    "sg:city":"Insch",
    "sg:classifiers":[
        {
            "category":"Utilities",
            "subcategory":"Fuel Oil & Lpg",
            "type":"Services"
        }
    ],
    "sg:phone":"+44 1464 851495",
    "sg:postcode":"AB52 6QT",
    "sg:province":"Aberdeenshire",
    "sg:tags":[
        "gas"
    ],
    "wof:name":"Peter Walkley",
    "wof:placetype":"venue"
},
  "geometry": {"coordinates":[-2.6130108833,57.342918396],"type":"Point"}
}