{
  "type": "Feature",
  "properties": {
    "addr:full":"14a Airfield Road Christchurch Dorset BH23 3TG",
    "addr:housenumber":"14a",
    "addr:postcode":"bh23 3tg",
    "addr:street":"Airfield Road",
    "iso:country":"GB",
    "sg:address":"14a Airfield Road",
    "sg:city":"Christchurch",
    "sg:classifiers":[
        {
            "category":"Home & Garden",
            "subcategory":"Household Appliances",
            "type":"Retail Goods"
        }
    ],
    "sg:phone":"+44 1202 499149",
    "sg:postcode":"BH23 3TG",
    "sg:province":"Dorset",
    "sg:tags":[
        "cleaner",
        "vacuum"
    ],
    "wof:name":"Ashcroft Agencies Ltd.",
    "wof:placetype":"venue"
},
  "geometry": {"coordinates":[-1.7461060286,50.7357292175],"type":"Point"}
}