{
  "type": "Feature",
  "properties": {
    "addr:full":"46 Pemberton Road West Bromwich West Midlands B70 0JH",
    "addr:housenumber":"46",
    "addr:postcode":"b70 0jh",
    "addr:street":"Pemberton Road",
    "iso:country":"GB",
    "sg:address":"46 Pemberton Road",
    "sg:city":"West Bromwich",
    "sg:classifiers":[
        {
            "category":"Social Services",
            "subcategory":"Retirement Home",
            "type":"Services"
        }
    ],
    "sg:phone":"+44 121 520 0320",
    "sg:postcode":"B70 0JH",
    "sg:province":"West Midlands",
    "sg:tags":[
        "furrier"
    ],
    "wof:name":"Neilsons Furs",
    "wof:placetype":"venue"
},
  "geometry": {"coordinates":[-2.0131149292,52.5321884155],"type":"Point"}
}