{
  "type": "Feature",
  "properties": {
    "addr:full":"160 Harrowdene Gardens Teddington Greater London TW11 0DN",
    "addr:housenumber":"160",
    "addr:postcode":"tw11 0dn",
    "addr:street":"Harrowdene Gardens",
    "iso:country":"GB",
    "sg:address":"160 Harrowdene Gardens",
    "sg:city":"Teddington",
    "sg:classifiers":[
        {
            "category":"Retail",
            "subcategory":"Driving School",
            "type":"Services"
        }
    ],
    "sg:phone":"+44 20 8241 3400",
    "sg:postcode":"TW11 0DN",
    "sg:province":"Greater London",
    "wof:name":"Jeff Sullivan",
    "wof:placetype":"venue"
},
  "geometry": {"coordinates":[-0.3246819973,51.4198265076],"type":"Point"}
}