{
  "type": "Feature",
  "properties": {
    "addr:full":"52 Foxleys Watford Hertfordshire WD19 5DE",
    "addr:housenumber":"52",
    "addr:postcode":"wd19 5de",
    "addr:street":"Foxleys",
    "iso:country":"GB",
    "sg:address":"52 Foxleys",
    "sg:city":"Watford",
    "sg:classifiers":[
        {
            "category":"Sports & Exercise",
            "subcategory":"Sports Center",
            "type":"Entertainment"
        }
    ],
    "sg:phone":"+44 20 8420 2013",
    "sg:postcode":"WD19 5DE",
    "sg:province":"Hertfordshire",
    "sg:tags":[
        "coaching"
    ],
    "wof:name":"Making Waves With Cindy",
    "wof:placetype":"venue"
},
  "geometry": {"coordinates":[-0.377621,51.627357],"type":"Point"}
}