{
  "type": "Feature",
  "properties": {
    "addr:full":"9 Spital Terrace Gainsborough Lincolnshire DN21 2HD",
    "addr:housenumber":"9",
    "addr:postcode":"dn21 2hd",
    "addr:street":"Spital Terrace",
    "iso:country":"GB",
    "sg:address":"9 Spital Terrace",
    "sg:city":"Gainsborough",
    "sg:classifiers":[
        {
            "category":"Food & Beverages",
            "subcategory":"Meat & Fish",
            "type":"Retail Goods"
        }
    ],
    "sg:phone":"+44 1427 612977",
    "sg:postcode":"DN21 2HD",
    "sg:province":"Lincolnshire",
    "sg:tags":[
        "chip"
    ],
    "wof:name":"Jenny's Fish Shop",
    "wof:placetype":"venue"
},
  "geometry": {"coordinates":[-0.773378,53.400772],"type":"Point"}
}