{
  "type": "Feature",
  "properties": {
    "addr:full":"263 Kensal Road London Greater London W10 5DB",
    "addr:housenumber":"263",
    "addr:postcode":"w10 5db",
    "addr:street":"Kensal Road",
    "iso:country":"GB",
    "sg:address":"263 Kensal Road",
    "sg:city":"London",
    "sg:classifiers":[
        {
            "category":"Professional",
            "subcategory":"Art Services",
            "type":"Services"
        }
    ],
    "sg:postcode":"W10 5DB",
    "sg:province":"Greater London",
    "sg:tags":[
        "graphic",
        "designer"
    ],
    "wof:name":"International Marketing Publishing & Development S",
    "wof:placetype":"venue"
},
  "geometry": {"coordinates":[-0.212259,51.526176],"type":"Point"}
}