{
  "type": "Feature",
  "properties": {
    "addr:full":"Burton Road, Acresford Swadlincote Derbyshire DE12 8AP",
    "addr:postcode":"de12 8ap",
    "addr:street":"Burton Road Acresford",
    "iso:country":"GB",
    "sg:address":"Burton Road, Acresford",
    "sg:city":"Swadlincote",
    "sg:classifiers":[
        {
            "category":"Bars & Pubs",
            "type":"Food & Drink"
        }
    ],
    "sg:phone":"+44 1283 760359",
    "sg:postcode":"DE12 8AP",
    "sg:province":"Derbyshire",
    "sg:tags":[
        "pubs",
        "inn"
    ],
    "wof:name":"Cricketts Inn",
    "wof:placetype":"venue"
},
  "geometry": {"coordinates":[-1.5606989861,52.715839386],"type":"Point"}
}