{
  "type": "Feature",
  "properties": {
    "addr:full":"222 London Rd, Guildford Surrey GU1 1YR",
    "addr:housenumber":"222",
    "addr:postcode":"gu1 1yr",
    "addr:street":"London Rd",
    "iso:country":"GB",
    "sg:address":"222 London Rd,",
    "sg:city":"Guildford",
    "sg:classifiers":[
        {
            "category":"Autos & Motor Vehicles",
            "subcategory":"Automobile Sales",
            "type":"Retail Goods"
        }
    ],
    "sg:postcode":"GU1 1YR",
    "sg:province":"Surrey",
    "sg:tags":[
        "car"
    ],
    "wof:name":"Capitalbest Ltd",
    "wof:placetype":"venue"
},
  "geometry": {"coordinates":[-0.546258986,51.2576408386],"type":"Point"}
}