{
  "type": "Feature",
  "properties": {
    "iso:country":"GB",
    "sg:address":"Vestry Close",
    "sg:city":"Street",
    "sg:classifiers":[
        {
            "category":"Place Of Worship",
            "type":"Public Place"
        }
    ],
    "sg:phone":"+44 1458 442671",
    "sg:postcode":"BA16 0HX",
    "sg:province":"Somerset",
    "wof:name":"Holy Trinity Church & Mission Church",
    "wof:placetype":"venue"
},
  "geometry": {"coordinates":[-2.741269,51.124821],"type":"Point"}
}