{
  "type": "Feature",
  "properties": {
    "iso:country":"GB",
    "sg:address":"Lower Broad Lane",
    "sg:city":"Redruth",
    "sg:classifiers":[
        {
            "category":"Building & Trades",
            "subcategory":"Construction",
            "type":"Services"
        }
    ],
    "sg:phone":"+44 1209 217606",
    "sg:postcode":"TR15 3HJ",
    "sg:province":"Cornwall",
    "sg:tags":[
        "builder"
    ],
    "wof:name":"Derek Bell Builders",
    "wof:placetype":"venue"
},
  "geometry": {"coordinates":[-5.262349,50.237209],"type":"Point"}
}