{
  "type": "Feature",
  "properties": {
    "addr:full":"Prospect House, 24 Scriven Road Knaresborough North Yorkshire HG5 9EJ",
    "addr:housenumber":"24",
    "addr:postcode":"hg5 9ej",
    "addr:street":"Scriven Road",
    "iso:country":"GB",
    "sg:address":"Prospect House, 24 Scriven Road",
    "sg:city":"Knaresborough",
    "sg:classifiers":[
        {
            "category":"Professional",
            "subcategory":"Detective & Security Services",
            "type":"Services"
        }
    ],
    "sg:postcode":"HG5 9EJ",
    "sg:province":"North Yorkshire",
    "sg:tags":[
        "alarm",
        "burglar",
        "system"
    ],
    "wof:name":"Guardian Alarms",
    "wof:placetype":"venue"
},
  "geometry": {"coordinates":[-1.4683760405,54.0182571411],"type":"Point"}
}