{
  "type": "Feature",
  "properties": {
    "iso:country":"GB",
    "sg:address":"30 Brownroyd Hill Road",
    "sg:city":"Bradford",
    "sg:classifiers":[
        {
            "category":"Retail",
            "subcategory":"Auto Repair",
            "type":"Services"
        }
    ],
    "sg:postcode":"BD6 1SA",
    "sg:province":"West Yorkshire",
    "sg:tags":[
        "body",
        "garage",
        "modification",
        "car"
    ],
    "wof:name":"Panel Repair Service's",
    "wof:placetype":"venue"
},
  "geometry": {"coordinates":[-1.776084,53.772671],"type":"Point"}
}