{
  "type": "Feature",
  "properties": {
    "addr:full":"26 East Dock Street Dundee Dundee City DD1 3EY",
    "addr:housenumber":"26",
    "addr:postcode":"dd1 3ey",
    "addr:street":"East Dock Street",
    "iso:country":"GB",
    "sg:address":"26 East Dock Street",
    "sg:city":"Dundee",
    "sg:classifiers":[
        {
            "category":"Professional",
            "subcategory":"Employment Agencies",
            "type":"Services"
        }
    ],
    "sg:phone":"+44 1382 202400",
    "sg:postcode":"DD1 3EY",
    "sg:province":"Dundee City",
    "sg:tags":[
        "consultant"
    ],
    "wof:name":"Key Personnel (Dundee) Ltd.",
    "wof:placetype":"venue"
},
  "geometry": {"coordinates":[-2.963378,56.462261],"type":"Point"}
}