{
  "type": "Feature",
  "properties": {
    "iso:country":"GB",
    "sg:address":"2 The Grove, Lowton St Lukes",
    "sg:city":"Warrington",
    "sg:classifiers":[
        {
            "category":"Arts & Performance",
            "subcategory":"Music",
            "type":"Entertainment"
        }
    ],
    "sg:phone":"+44 1942 719819",
    "sg:postcode":"WA3 2HW",
    "sg:province":"Cheshire",
    "sg:tags":[
        "mobile",
        "disco"
    ],
    "wof:name":"Disco Fever",
    "wof:placetype":"venue"
},
  "geometry": {"coordinates":[-2.574965,53.478565],"type":"Point"}
}