{
  "type": "Feature",
  "properties": {
    "addr:full":"24 Runcorn Road Birmingham West Midlands B12 8RQ",
    "addr:housenumber":"24",
    "addr:postcode":"b12 8rq",
    "addr:street":"Runcorn Road",
    "iso:country":"GB",
    "sg:address":"24 Runcorn Road",
    "sg:city":"Birmingham",
    "sg:classifiers":[
        {
            "category":"Real Estate",
            "subcategory":"Real Estate Services",
            "type":"Services"
        },
        {
            "category":"Building & Trades",
            "subcategory":"Equipment Rental",
            "type":"Services"
        }
    ],
    "sg:phone":"+44 121 440 2538",
    "sg:postcode":"B12 8RQ",
    "sg:province":"West Midlands",
    "sg:tags":[
        "hire",
        "leasing",
        "plant",
        "machinery"
    ],
    "wof:name":"St.Clements Plant Ltd.",
    "wof:placetype":"venue"
},
  "geometry": {"coordinates":[-1.882898,52.455357],"type":"Point"}
}