{
  "type": "Feature",
  "properties": {
    "iso:country":"GB",
    "sg:address":"18 Tetlow Lane, Salford",
    "sg:city":"Manchester",
    "sg:classifiers":[
        {
            "category":"Health Services",
            "subcategory":"Nursing And Care Facility",
            "type":"Services"
        },
        {
            "category":"Social Services",
            "subcategory":"Retirement Home",
            "type":"Services"
        }
    ],
    "sg:phone":"+44 161 792 0993",
    "sg:postcode":"M7 4BU",
    "sg:province":"Greater Manchester",
    "sg:tags":[
        "residential"
    ],
    "wof:name":"Newlands Greater Manchester Jewish Housing Associa",
    "wof:placetype":"venue"
},
  "geometry": {"coordinates":[-2.2501749992,53.509929657],"type":"Point"}
}