{
  "type": "Feature",
  "properties": {
    "iso:country":"GB",
    "sg:address":"Osprey House, Richmond Road, Llanion Park",
    "sg:city":"Pembroke Dock",
    "sg:classifiers":[
        {
            "category":"Freight",
            "type":"Transportation"
        }
    ],
    "sg:postcode":"SA72 6TS",
    "sg:province":"Pembrokeshire",
    "sg:tags":[
        "overseas",
        "shipping",
        "removal"
    ],
    "wof:name":"O B C Burgess Ltd.",
    "wof:placetype":"venue"
},
  "geometry": {"coordinates":[-4.9389309883,51.6991081238],"type":"Point"}
}