{
  "type": "Feature",
  "properties": {
    "addr:full":"11 Bereweeke Way Winchester Hampshire SO22 6BJ",
    "addr:housenumber":"11",
    "addr:postcode":"so22 6bj",
    "addr:street":"Bereweeke Way",
    "iso:country":"GB",
    "sg:address":"11 Bereweeke Way",
    "sg:city":"Winchester",
    "sg:classifiers":[
        {
            "category":"Professional",
            "subcategory":"Business Services",
            "type":"Services"
        }
    ],
    "sg:phone":"+44 1962 853987",
    "sg:postcode":"SO22 6BJ",
    "sg:province":"Hampshire",
    "sg:tags":[
        "assessment",
        "quality"
    ],
    "wof:name":"P P M Winchester",
    "wof:placetype":"venue"
},
  "geometry": {"coordinates":[-1.3254189491,51.0726089478],"type":"Point"}
}