{
  "type": "Feature",
  "properties": {
    "addr:full":"49 Downing Street Farnham Surrey GU9 7PH",
    "addr:housenumber":"49",
    "addr:postcode":"gu9 7ph",
    "addr:street":"Downing Street",
    "iso:country":"GB",
    "sg:address":"49 Downing Street",
    "sg:city":"Farnham",
    "sg:classifiers":[
        {
            "category":"Shopping",
            "subcategory":"Baby Store",
            "type":"Retail Goods"
        }
    ],
    "sg:phone":"+44 1252 725009",
    "sg:postcode":"GU9 7PH",
    "sg:province":"Surrey",
    "sg:tags":[
        "babywear",
        "childrens"
    ],
    "wof:name":"Young Ones",
    "wof:placetype":"venue"
},
  "geometry": {"coordinates":[-0.799679,51.214447],"type":"Point"}
}