{
  "type": "Feature",
  "properties": {
    "addr:full":"Upper Gough Street Birmingham West Midlands B1 1JG",
    "addr:postcode":"b1 1jg",
    "addr:street":"Upper Gough Street",
    "iso:country":"GB",
    "sg:address":"Upper Gough Street",
    "sg:city":"Birmingham",
    "sg:classifiers":[
        {
            "category":"Bars & Pubs",
            "type":"Food & Drink"
        }
    ],
    "sg:phone":"+44 121 643 6756",
    "sg:postcode":"B1 1JG",
    "sg:province":"West Midlands",
    "sg:tags":[
        "pubs",
        "inn"
    ],
    "wof:name":"The Craven Arms",
    "wof:placetype":"venue"
},
  "geometry": {"coordinates":[-1.9040640593,52.4747505188],"type":"Point"}
}