{
  "type": "Feature",
  "properties": {
    "iso:country":"GB",
    "sg:address":"717-723 High Road Leyton, Leyton",
    "sg:city":"London",
    "sg:classifiers":[
        {
            "category":"Manufacturing",
            "subcategory":"Building Materials",
            "type":"Manufacturing & Wholesale Goods"
        }
    ],
    "sg:phone":"+44 20 8539 2948",
    "sg:postcode":"E10 5AB",
    "sg:province":"Greater London",
    "sg:tags":[
        "merchant",
        "builder"
    ],
    "wof:name":"Essex Building Supplies",
    "wof:placetype":"venue"
},
  "geometry": {"coordinates":[-0.0086070001,51.5725097656],"type":"Point"}
}