{
  "type": "Feature",
  "properties": {
    "iso:country":"GB",
    "sg:address":"16 Victoria Terrace",
    "sg:city":"Leamington Spa",
    "sg:classifiers":[
        {
            "category":"Personal",
            "subcategory":"Barber",
            "type":"Services"
        }
    ],
    "sg:phone":"+44 1926 429666",
    "sg:postcode":"CV31 3AB",
    "sg:province":"Warwickshire",
    "sg:tags":[
        "men's",
        "gents",
        "hairdresser"
    ],
    "wof:name":"William John",
    "wof:placetype":"venue"
},
  "geometry": {"coordinates":[-1.5333110094,52.2860832214],"type":"Point"}
}