{
  "type": "Feature",
  "properties": {
    "addr:full":"Church Square Shepperton Surrey TW17 9JY",
    "addr:postcode":"tw17 9jy",
    "addr:street":"Church Square",
    "iso:country":"GB",
    "sg:address":"Church Square",
    "sg:city":"Shepperton",
    "sg:classifiers":[
        {
            "category":"Shopping",
            "subcategory":"Antiques",
            "type":"Retail Goods"
        }
    ],
    "sg:phone":"+44 1932 243571",
    "sg:postcode":"TW17 9JY",
    "sg:province":"Surrey",
    "wof:name":"Rickett & Co",
    "wof:placetype":"venue"
},
  "geometry": {"coordinates":[-0.4538899958,51.3880386353],"type":"Point"}
}