{
  "type": "Feature",
  "properties": {
    "addr:full":"Cherry Tree Lane, Rostherne Altrincham Cheshire WA14 3RZ",
    "addr:postcode":"wa14 3rz",
    "addr:street":"Cherry Tree Lane",
    "iso:country":"GB",
    "sg:address":"Cherry Tree Lane, Rostherne",
    "sg:city":"Altrincham",
    "sg:classifiers":[
        {
            "category":"Shopping",
            "subcategory":"Stationery & Office Supplies",
            "type":"Retail Goods"
        }
    ],
    "sg:phone":"+44 1565 830213",
    "sg:postcode":"WA14 3RZ",
    "sg:province":"Cheshire",
    "sg:tags":[
        "printers'"
    ],
    "wof:name":"Principal Image Ltd.",
    "wof:placetype":"venue"
},
  "geometry": {"coordinates":[-2.394234,53.360439],"type":"Point"}
}