{
  "type": "Feature",
  "properties": {
    "iso:country":"GB",
    "sg:address":"236 Melton Road",
    "sg:city":"Leicester",
    "sg:classifiers":[
        {
            "category":"Shopping",
            "subcategory":"Jewelry",
            "type":"Retail Goods"
        },
        {
            "category":"Shopping",
            "subcategory":"Comic Books",
            "type":"Retail Goods"
        }
    ],
    "sg:phone":"+44 116 266 1868",
    "sg:postcode":"LE4 7PG",
    "sg:province":"Leicestershire",
    "sg:tags":[
        "jeweller",
        "sale",
        "jewellery"
    ],
    "wof:name":"D R Langley",
    "wof:placetype":"venue"
},
  "geometry": {"coordinates":[-1.1158790588,52.6584587097],"type":"Point"}
}