{
  "type": "Feature",
  "properties": {
    "addr:full":"27 Rosemary Road Clacton-on-sea Essex CO15 1PA",
    "addr:housenumber":"27",
    "addr:postcode":"co15 1pa",
    "addr:street":"Rosemary Road",
    "iso:country":"GB",
    "sg:address":"27 Rosemary Road",
    "sg:city":"Clacton-on-sea",
    "sg:classifiers":[
        {
            "category":"Food & Beverages",
            "subcategory":"Meat & Fish",
            "type":"Retail Goods"
        }
    ],
    "sg:phone":"+44 1255 423036",
    "sg:postcode":"CO15 1PA",
    "sg:province":"Essex",
    "sg:tags":[
        "butcher"
    ],
    "wof:name":"T Stobbs & Son",
    "wof:placetype":"venue"
},
  "geometry": {"coordinates":[1.1549170017,51.7893943787],"type":"Point"}
}