{
  "type": "Feature",
  "properties": {
    "addr:full":"210 Eastern Av Ilford Essex IG4 5AB",
    "addr:housenumber":"210",
    "addr:postcode":"ig4 5ab",
    "addr:street":"Eastern Av Ilford",
    "iso:country":"GB",
    "sg:address":"210 Eastern Av",
    "sg:city":"Ilford",
    "sg:classifiers":[
        {
            "category":"Shopping",
            "subcategory":"Hobbies, Toys, & Games",
            "type":"Retail Goods"
        }
    ],
    "sg:phone":"+44 20 8554 8687",
    "sg:postcode":"IG4 5AB",
    "sg:province":"Essex",
    "sg:tags":[
        "toy"
    ],
    "wof:name":"Just Novelties",
    "wof:placetype":"venue"
},
  "geometry": {"coordinates":[0.052707,51.576065],"type":"Point"}
}