{
  "type": "Feature",
  "properties": {
    "iso:country":"GB",
    "sg:address":"St Feock Church",
    "sg:city":"Truro",
    "sg:classifiers":[
        {
            "category":"Place Of Worship",
            "type":"Public Place"
        }
    ],
    "sg:phone":"+44 1872 862534",
    "sg:postcode":"TR3 6SD",
    "sg:province":"Cornwall",
    "wof:name":"St.Feock Church",
    "wof:placetype":"venue"
},
  "geometry": {"coordinates":[-5.051893,50.206764],"type":"Point"}
}