{
  "type": "Feature",
  "properties": {
    "addr:full":"56 Great Western Road London Greater London W9 3NT",
    "addr:housenumber":"56",
    "addr:postcode":"w9 3nt",
    "addr:street":"Great Western Road",
    "iso:country":"GB",
    "sg:address":"56 Great Western Road",
    "sg:city":"London",
    "sg:classifiers":[
        {
            "category":"Home & Garden",
            "subcategory":"Home Furnishings",
            "type":"Retail Goods"
        }
    ],
    "sg:phone":"+44 20 7221 5058",
    "sg:postcode":"W9 3NT",
    "sg:province":"Greater London",
    "sg:tags":[
        "beds",
        "bedding",
        "blanket"
    ],
    "wof:name":"Big Table Furniture Co-Operative Ltd.",
    "wof:placetype":"venue"
},
  "geometry": {"coordinates":[-0.2015590072,51.5229110718],"type":"Point"}
}