{
  "type": "Feature",
  "properties": {
    "addr:full":"152 Buckingham Palace Road London Greater London SW1W 9TR",
    "addr:housenumber":"152",
    "addr:postcode":"sw1w 9tr",
    "addr:street":"Buckingham Palace Road",
    "iso:country":"GB",
    "sg:address":"152 Buckingham Palace Road",
    "sg:city":"London",
    "sg:classifiers":[
        {
            "category":"Organizations",
            "subcategory":"Community Association",
            "type":"Services"
        }
    ],
    "sg:phone":"+44 20 7259 8000",
    "sg:postcode":"SW1W 9TR",
    "sg:province":"Greater London",
    "sg:tags":[
        "relation",
        "public"
    ],
    "wof:name":"Atkinson Courage Ltd.",
    "wof:placetype":"venue"
},
  "geometry": {"coordinates":[-0.147153005,51.4932250977],"type":"Point"}
}