{
  "type": "Feature",
  "properties": {
    "addr:full":"Bramble Byre, Howbarrow, Cartmel Grange-over-sands Cumbria LA11 7SS",
    "addr:postcode":"la11 7ss",
    "iso:country":"GB",
    "sg:address":"Bramble Byre, Howbarrow, Cartmel",
    "sg:city":"Grange-over-sands",
    "sg:classifiers":[
        {
            "category":"Home & Garden",
            "subcategory":"Garden Supply",
            "type":"Retail Goods"
        }
    ],
    "sg:phone":"+44 15395 34626",
    "sg:postcode":"LA11 7SS",
    "sg:province":"Cumbria",
    "sg:tags":[
        "turfing"
    ],
    "wof:name":"Whitewell Landscapes",
    "wof:placetype":"venue"
},
  "geometry": {"coordinates":[-2.9216399193,54.1841583252],"type":"Point"}
}