{
  "type": "Feature",
  "properties": {
    "addr:full":"Ivy Cottage, Upper Tadmarton Banbury Oxfordshire OX15 5TB",
    "addr:postcode":"ox15 5tb",
    "addr:street":"Upper",
    "iso:country":"GB",
    "sg:address":"Ivy Cottage, Upper Tadmarton",
    "sg:city":"Banbury",
    "sg:classifiers":[
        {
            "category":"Professional",
            "subcategory":"Accounting & Tax Preparation",
            "type":"Services"
        }
    ],
    "sg:phone":"+44 1295 788104",
    "sg:postcode":"OX15 5TB",
    "sg:province":"Oxfordshire",
    "sg:tags":[
        "accountant"
    ],
    "wof:name":"Christopher Dean & Co",
    "wof:placetype":"venue"
},
  "geometry": {"coordinates":[-1.429633975,52.0380973816],"type":"Point"}
}