{
  "type": "Feature",
  "properties": {
    "addr:full":"Chetwynd Manor, Chester Road Newport Shropshire TF10 8AB",
    "addr:postcode":"tf10 8ab",
    "addr:street":"Chester Road",
    "iso:country":"GB",
    "sg:address":"Chetwynd Manor, Chester Road",
    "sg:city":"Newport",
    "sg:classifiers":[
        {
            "category":"Organizations",
            "subcategory":"Community Association",
            "type":"Services"
        }
    ],
    "sg:postcode":"TF10 8AB",
    "sg:province":"Shropshire",
    "sg:tags":[
        "relation",
        "public"
    ],
    "wof:name":"Adrian Miles & Associates",
    "wof:placetype":"venue"
},
  "geometry": {"coordinates":[-2.424374,52.800396],"type":"Point"}
}