{
  "type": "Feature",
  "properties": {
    "addr:full":"49 Broomfield Avenue Northallerton North Yorkshire DL7 8RZ",
    "addr:housenumber":"49",
    "addr:postcode":"dl7 8rz",
    "addr:street":"Broomfield Avenue",
    "iso:country":"GB",
    "sg:address":"49 Broomfield Avenue",
    "sg:city":"Northallerton",
    "sg:classifiers":[
        {
            "category":"Home & Garden",
            "subcategory":"Building Materials",
            "type":"Retail Goods"
        }
    ],
    "sg:postcode":"DL7 8RZ",
    "sg:province":"North Yorkshire",
    "sg:tags":[
        "polythene",
        "plastic"
    ],
    "wof:name":"Roger M Pocock Manufacturers Agent Textile",
    "wof:placetype":"venue"
},
  "geometry": {"coordinates":[-1.43516,54.329582],"type":"Point"}
}