{
  "type": "Feature",
  "properties": {
    "iso:country":"GB",
    "sg:address":"92 Tredworth Road",
    "sg:city":"Gloucester",
    "sg:classifiers":[
        {
            "category":"Food & Beverages",
            "subcategory":"Meat & Fish",
            "type":"Retail Goods"
        },
        {
            "category":"Food & Beverages",
            "subcategory":"Groceries & Convenience Stores",
            "type":"Retail Goods"
        }
    ],
    "sg:phone":"+44 1452 421904",
    "sg:postcode":"GL1 4QS",
    "sg:province":"Gloucestershire",
    "sg:tags":[
        "shop",
        "chip"
    ],
    "wof:name":"Trafalgar Fish Bar",
    "wof:placetype":"venue"
},
  "geometry": {"coordinates":[-2.236966,51.851902],"type":"Point"}
}