{
  "type": "Feature",
  "properties": {
    "addr:full":"34 St Baldreds Road North Berwick East Lothian EH39 4PU",
    "addr:housenumber":"34",
    "addr:postcode":"eh39 4pu",
    "addr:street":"St Baldreds Road",
    "iso:country":"GB",
    "sg:address":"34 St Baldreds Road",
    "sg:city":"North Berwick",
    "sg:classifiers":[
        {
            "category":"Health Services",
            "subcategory":"Hospital",
            "type":"Services"
        }
    ],
    "sg:phone":"+44 1620 897040",
    "sg:postcode":"EH39 4PU",
    "sg:province":"East Lothian",
    "wof:name":"Edington Cottage Hospital",
    "wof:placetype":"venue"
},
  "geometry": {"coordinates":[-2.713876009,56.0554122925],"type":"Point"}
}