{
  "type": "Feature",
  "properties": {
    "iso:country":"GB",
    "sg:address":"Trewyn House, Trewyn Road",
    "sg:city":"Holsworthy",
    "sg:classifiers":[
        {
            "category":"Building & Trades",
            "subcategory":"Equipment Rental",
            "type":"Services"
        },
        {
            "category":"Building & Trades",
            "subcategory":"Construction",
            "type":"Services"
        }
    ],
    "sg:phone":"+44 1409 253472",
    "sg:postcode":"EX22 6HX",
    "sg:province":"Cornwall",
    "sg:tags":[
        "plant",
        "machinery"
    ],
    "wof:name":"R W & V Vanstone Contractors",
    "wof:placetype":"venue"
},
  "geometry": {"coordinates":[-4.357475,50.815006],"type":"Point"}
}