{
  "type": "Feature",
  "properties": {
    "addr:full":"Stanier Street Newcastle Staffordshire ST5 2SU",
    "addr:postcode":"st5 2su",
    "addr:street":"Stanier Street",
    "iso:country":"GB",
    "sg:address":"Stanier Street",
    "sg:city":"Newcastle",
    "sg:classifiers":[
        {
            "category":"Education",
            "subcategory":"School",
            "type":"Public Place"
        }
    ],
    "sg:phone":"+44 1782 619685",
    "sg:postcode":"ST5 2SU",
    "sg:province":"Staffordshire",
    "sg:tags":[
        "local",
        "authority"
    ],
    "wof:name":"Staffordshire County Council",
    "wof:placetype":"venue"
},
  "geometry": {"coordinates":[-2.2337639332,53.0123062134],"type":"Point"}
}