{
  "type": "Feature",
  "properties": {
    "addr:full":"Chancel House, Neasden Lane, Neasden London Greater London NW10 2UF",
    "addr:postcode":"nw10 2uf",
    "addr:street":"Neasden Lane",
    "iso:country":"GB",
    "sg:address":"Chancel House, Neasden Lane, Neasden",
    "sg:city":"London",
    "sg:classifiers":[
        {
            "category":"Building & Trades",
            "subcategory":"Construction",
            "type":"Services"
        }
    ],
    "sg:phone":"+44 20 8214 1426",
    "sg:postcode":"NW10 2UF",
    "sg:province":"Greater London",
    "sg:tags":[
        "builder"
    ],
    "wof:name":"London & Pacific Developments Ltd.",
    "wof:placetype":"venue"
},
  "geometry": {"coordinates":[-0.2487899959,51.5521965027],"type":"Point"}
}