{
  "type": "Feature",
  "properties": {
    "addr:full":"Magnell Annexe, High Street, Crofton Wakefield West Yorkshire WF4 1NF",
    "addr:postcode":"wf4 1nf",
    "addr:street":"High Street",
    "iso:country":"GB",
    "sg:address":"Magnell Annexe, High Street, Crofton",
    "sg:city":"Wakefield",
    "sg:classifiers":[
        {
            "category":"Community Center",
            "subcategory":"Youth",
            "type":"Public Place"
        }
    ],
    "sg:phone":"+44 1924 303965",
    "sg:postcode":"WF4 1NF",
    "sg:province":"West Yorkshire",
    "sg:tags":[
        "organisation",
        "centre"
    ],
    "wof:name":"Crofton Youth Club",
    "wof:placetype":"venue"
},
  "geometry": {"coordinates":[-1.4370290041,53.664981842],"type":"Point"}
}