{
  "type": "Feature",
  "properties": {
    "addr:full":"Haimo Centre, Haimo Rd Eltham Greater London SE9 6DY",
    "addr:postcode":"se9 6dy",
    "addr:street":"Haimo Rd",
    "iso:country":"GB",
    "sg:address":"Haimo Centre, Haimo Rd",
    "sg:city":"Eltham",
    "sg:classifiers":[
        {
            "category":"Education",
            "subcategory":"University",
            "type":"Public Place"
        }
    ],
    "sg:phone":"+44 20 8850 3632",
    "sg:postcode":"SE9 6DY",
    "sg:province":"Greater London",
    "sg:tags":[
        "adult"
    ],
    "wof:name":"Greenwich Community College",
    "wof:placetype":"venue"
},
  "geometry": {"coordinates":[0.051022,51.451023],"type":"Point"}
}