{
  "type": "Feature",
  "properties": {
    "iso:country":"GB",
    "sg:address":"Wimbledon Park Rd",
    "sg:city":"Wandsworth",
    "sg:classifiers":[
        {
            "category":"Place Of Worship",
            "type":"Public Place"
        }
    ],
    "sg:phone":"+44 20 8767 8970",
    "sg:postcode":"SW18 1LU",
    "sg:province":"Greater London",
    "wof:name":"Southfields New Testament Assembly Church",
    "wof:placetype":"venue"
},
  "geometry": {"coordinates":[-0.199549,51.452801],"type":"Point"}
}