{
  "type": "Feature",
  "properties": {
    "addr:full":"113 Cadzow Street Hamilton South Lanarkshire ML3 6HN",
    "addr:housenumber":"113",
    "addr:postcode":"ml3 6hn",
    "addr:street":"Cadzow Street",
    "iso:country":"GB",
    "sg:address":"113 Cadzow Street",
    "sg:city":"Hamilton",
    "sg:classifiers":[
        {
            "category":"Banks & Credit Unions",
            "subcategory":"Bank",
            "type":"Services"
        }
    ],
    "sg:phone":"+44 1698 487900",
    "sg:postcode":"ML3 6HN",
    "sg:province":"South Lanarkshire",
    "wof:name":"Bank of Scotland",
    "wof:placetype":"venue"
},
  "geometry": {"coordinates":[-4.0391669273,55.7774772644],"type":"Point"}
}