{
  "type": "Feature",
  "properties": {
    "iso:country":"GB",
    "sg:address":"1 Eastcote La",
    "sg:city":"Harrow",
    "sg:classifiers":[
        {
            "category":"Professional",
            "subcategory":"Accounting & Tax Preparation",
            "type":"Services"
        }
    ],
    "sg:phone":"+44 20 8864 4456",
    "sg:postcode":"HA2 8BW",
    "sg:province":"Greater London",
    "sg:tags":[
        "accountant"
    ],
    "wof:name":"Rushcott & Co",
    "wof:placetype":"venue"
},
  "geometry": {"coordinates":[-0.354278,51.564171],"type":"Point"}
}