{
  "type": "Feature",
  "properties": {
    "addr:full":"Limekiln Cottage, Barton Turf Norwich Norfolk NR12 8AR",
    "addr:postcode":"nr12 8ar",
    "addr:street":"Barton Turf Norwich",
    "iso:country":"GB",
    "sg:address":"Limekiln Cottage, Barton Turf",
    "sg:city":"Norwich",
    "sg:classifiers":[
        {
            "category":"Organizations",
            "subcategory":"Non-profit Organization",
            "type":"Services"
        }
    ],
    "sg:phone":"+44 1692 630631",
    "sg:postcode":"NR12 8AR",
    "sg:province":"Norfolk",
    "sg:tags":[
        "organisation",
        "voluntary",
        "charity"
    ],
    "wof:name":"Leukaemia Research Fund",
    "wof:placetype":"venue"
},
  "geometry": {"coordinates":[1.4864729643,52.7500991821],"type":"Point"}
}