{
  "type": "Feature",
  "properties": {
    "addr:full":"Stoneleigh House, Cheapside Rd Ascot Berkshire SL5 7QH",
    "addr:postcode":"sl5 7qh",
    "addr:street":"Cheapside Rd",
    "iso:country":"GB",
    "sg:address":"Stoneleigh House, Cheapside Rd",
    "sg:city":"Ascot",
    "sg:classifiers":[
        {
            "category":"Professional",
            "subcategory":"Management & Consulting",
            "type":"Services"
        }
    ],
    "sg:phone":"+44 1344 626623",
    "sg:postcode":"SL5 7QH",
    "sg:province":"Berkshire",
    "sg:tags":[
        "consultant",
        "business"
    ],
    "wof:name":"Guide Lines Training",
    "wof:placetype":"venue"
},
  "geometry": {"coordinates":[-0.6492040157,51.4166145325],"type":"Point"}
}