{
  "type": "Feature",
  "properties": {
    "iso:country":"GB",
    "sg:address":"Community Paediatrics Department, 2-4 Pyle St",
    "sg:city":"Newport",
    "sg:classifiers":[
        {
            "category":"Health Services",
            "subcategory":"Hospital",
            "type":"Services"
        }
    ],
    "sg:phone":"+44 1983 821388",
    "sg:postcode":"PO30 1JW",
    "sg:province":"Isle of Wight",
    "wof:name":"St Mary's NHS Trust",
    "wof:placetype":"venue"
},
  "geometry": {"coordinates":[-1.2959389687,50.7000999451],"type":"Point"}
}