{
  "type": "Feature",
  "properties": {
    "addr:full":"21 Dean St, Brewood Stafford Shropshire ST19 9BU",
    "addr:housenumber":"21",
    "addr:postcode":"st19 9bu",
    "addr:street":"Dean St",
    "iso:country":"GB",
    "sg:address":"21 Dean St, Brewood",
    "sg:city":"Stafford",
    "sg:classifiers":[
        {
            "category":"Bars & Pubs",
            "type":"Food & Drink"
        }
    ],
    "sg:phone":"+44 1902 850583",
    "sg:postcode":"ST19 9BU",
    "sg:province":"Shropshire",
    "sg:tags":[
        "pubs",
        "inn"
    ],
    "wof:name":"Punch Retail Ltd",
    "wof:placetype":"venue"
},
  "geometry": {"coordinates":[-2.174231,52.675304],"type":"Point"}
}