{
  "type": "Feature",
  "properties": {
    "iso:country":"GB",
    "sg:address":"26 Scarisbrick Street",
    "sg:city":"Ormskirk",
    "sg:classifiers":[
        {
            "category":"Professional",
            "subcategory":"Art Services",
            "type":"Services"
        },
        {
            "category":"Building & Trades",
            "subcategory":"Construction",
            "type":"Services"
        }
    ],
    "sg:phone":"+44 1695 578687",
    "sg:postcode":"L39 1QF",
    "sg:province":"Lancashire",
    "sg:tags":[
        "glazier",
        "decorator",
        "painter"
    ],
    "wof:name":"T J Dann",
    "wof:placetype":"venue"
},
  "geometry": {"coordinates":[-2.885139,53.571644],"type":"Point"}
}