{
  "type": "Feature",
  "properties": {
    "addr:full":"15-20  St Paul's Square Birmingham West Midlands B3 1QT",
    "addr:housenumber":"15-20",
    "addr:postcode":"b3 1qt",
    "addr:street":"St Paul'S Square",
    "iso:country":"GB",
    "sg:address":"15-20  St Paul's Square",
    "sg:city":"Birmingham",
    "sg:classifiers":[
        {
            "category":"Building & Trades",
            "subcategory":"Construction",
            "type":"Services"
        }
    ],
    "sg:postcode":"B3 1QT",
    "sg:province":"West Midlands",
    "sg:tags":[
        "builder"
    ],
    "wof:name":"Dunwell Erection Limited",
    "wof:placetype":"venue"
},
  "geometry": {"coordinates":[-1.90501,52.485901],"type":"Point"}
}