{
  "type": "Feature",
  "properties": {
    "addr:full":"9 Ogden St, Swinton Manchester Greater Manchester M27 5AU",
    "addr:housenumber":"9",
    "addr:postcode":"m27 5au",
    "addr:street":"Ogden St",
    "iso:country":"GB",
    "sg:address":"9 Ogden St, Swinton",
    "sg:city":"Manchester",
    "sg:classifiers":[
        {
            "category":"Manufacturing",
            "subcategory":"Building Materials",
            "type":"Manufacturing & Wholesale Goods"
        }
    ],
    "sg:phone":"+44 161 281 5947",
    "sg:postcode":"M27 5AU",
    "sg:province":"Greater Manchester",
    "sg:tags":[
        "tile",
        "mnfrs"
    ],
    "wof:name":"Concept Ceramics",
    "wof:placetype":"venue"
},
  "geometry": {"coordinates":[-2.3348679543,53.5078887939],"type":"Point"}
}