{
  "type": "Feature",
  "properties": {
    "iso:country":"GB",
    "sg:address":"Rookwood Hospital, Fairwater Road, Llandaff",
    "sg:city":"Cardiff",
    "sg:classifiers":[
        {
            "category":"Social Services",
            "type":"Services"
        }
    ],
    "sg:postcode":"CF5 2YN",
    "sg:province":"Cardiff",
    "sg:tags":[
        "need",
        "disability",
        "special"
    ],
    "wof:name":"Disabled Living Centre",
    "wof:placetype":"venue"
},
  "geometry": {"coordinates":[-3.214187,51.493484],"type":"Point"}
}