{
  "type": "Feature",
  "properties": {
    "addr:full":"Unit 4, Bakers Court Basildon Essex SS14 3EH",
    "addr:housenumber":"unit 4",
    "addr:postcode":"ss14 3eh",
    "addr:street":"Bakers Court",
    "iso:country":"GB",
    "sg:address":"Unit 4, Bakers Court",
    "sg:city":"Basildon",
    "sg:classifiers":[
        {
            "category":"Manufacturing",
            "subcategory":"Metals",
            "type":"Manufacturing & Wholesale Goods"
        }
    ],
    "sg:phone":"+44 1268 282809",
    "sg:postcode":"SS14 3EH",
    "sg:province":"Essex",
    "sg:tags":[
        "steel",
        "fabricator",
        "erectors"
    ],
    "wof:name":"J J  Donovan & Son Ltd.",
    "wof:placetype":"venue"
},
  "geometry": {"coordinates":[0.49684,51.588581],"type":"Point"}
}