{
  "type": "Feature",
  "properties": {
    "iso:country":"GB",
    "sg:address":"62 Spital Street",
    "sg:city":"Dartford",
    "sg:classifiers":[
        {
            "category":"Building & Trades",
            "subcategory":"Landscaping Services",
            "type":"Services"
        }
    ],
    "sg:phone":"+44 1322 276252",
    "sg:postcode":"DA1 2DT",
    "sg:province":"Kent",
    "sg:tags":[
        "pond",
        "aquarium"
    ],
    "wof:name":"Dartford Aquarium & Pet Centre",
    "wof:placetype":"venue"
},
  "geometry": {"coordinates":[0.213491,51.444931],"type":"Point"}
}