{
  "type": "Feature",
  "properties": {
    "iso:country":"GB",
    "sg:address":"The Gro",
    "sg:city":"Llanidloes",
    "sg:classifiers":[
        {
            "category":"Shopping",
            "subcategory":"Bicycles & Sporting Goods",
            "type":"Retail Goods"
        }
    ],
    "sg:phone":"+44 1686 412864",
    "sg:postcode":"SY18 6AB",
    "sg:province":"Powys",
    "sg:tags":[
        "cycle",
        "accessory"
    ],
    "wof:name":"The Cycle Shop",
    "wof:placetype":"venue"
},
  "geometry": {"coordinates":[-3.540166,52.445915],"type":"Point"}
}