{
  "type": "Feature",
  "properties": {
    "addr:full":"Eastgate St Winchester Hampshire SO23 8DZ",
    "addr:postcode":"so23 8dz",
    "addr:street":"Eastgate St",
    "iso:country":"GB",
    "sg:address":"Eastgate St",
    "sg:city":"Winchester",
    "sg:classifiers":[
        {
            "category":"Professional",
            "subcategory":"Employment Agencies",
            "type":"Services"
        }
    ],
    "sg:phone":"+44 1962 865456",
    "sg:postcode":"SO23 8DZ",
    "sg:province":"Hampshire",
    "sg:tags":[
        "consultant"
    ],
    "wof:name":"Cartwright Consulting",
    "wof:placetype":"venue"
},
  "geometry": {"coordinates":[-1.308174,51.063171],"type":"Point"}
}