{
  "type": "Feature",
  "properties": {
    "addr:full":"82 Roberts Rd Basildon Essex SS15 6AX",
    "addr:housenumber":"82",
    "addr:postcode":"ss15 6ax",
    "addr:street":"Roberts Rd",
    "iso:country":"GB",
    "sg:address":"82 Roberts Rd",
    "sg:city":"Basildon",
    "sg:classifiers":[
        {
            "category":"Building & Trades",
            "subcategory":"Construction",
            "type":"Services"
        }
    ],
    "sg:phone":"+44 1268 545215",
    "sg:postcode":"SS15 6AX",
    "sg:province":"Essex",
    "sg:tags":[
        "joiner",
        "carpenter"
    ],
    "wof:name":"F C Sheppard",
    "wof:placetype":"venue"
},
  "geometry": {"coordinates":[0.421342,51.578259],"type":"Point"}
}