{
  "type": "Feature",
  "properties": {
    "addr:full":"Chester Road, Aldridge Walsall Staffordshire WS9 0PH",
    "addr:postcode":"ws9 0ph",
    "addr:street":"Chester Road",
    "iso:country":"GB",
    "sg:address":"Chester Road, Aldridge",
    "sg:city":"Walsall",
    "sg:classifiers":[
        {
            "category":"Home & Garden",
            "subcategory":"Garden Supply",
            "type":"Retail Goods"
        }
    ],
    "sg:phone":"+44 121 353 4017",
    "sg:postcode":"WS9 0PH",
    "sg:province":"Staffordshire",
    "sg:tags":[
        "nursery",
        "centre"
    ],
    "wof:name":"Pacific Nurseries",
    "wof:placetype":"venue"
},
  "geometry": {"coordinates":[-1.8870539665,52.6161193848],"type":"Point"}
}