{
  "type": "Feature",
  "properties": {
    "iso:country":"GB",
    "sg:address":"7 St Nicholas Street",
    "sg:city":"Bristol",
    "sg:classifiers":[
        {
            "category":"Professional",
            "subcategory":"Lawyer & Legal Services",
            "type":"Services"
        }
    ],
    "sg:phone":"+44 117 927 3305",
    "sg:postcode":"BS1 1UE",
    "sg:province":"City of Bristol",
    "sg:tags":[
        "conveyancing"
    ],
    "wof:name":"Michael Prout & Co.",
    "wof:placetype":"venue"
},
  "geometry": {"coordinates":[-2.592931,51.453785],"type":"Point"}
}