{
  "type": "Feature",
  "properties": {
    "iso:country":"GB",
    "sg:address":"9 Market Hill",
    "sg:city":"Saffron Walden",
    "sg:classifiers":[
        {
            "category":"Shopping",
            "subcategory":"Thrift Store",
            "type":"Retail Goods"
        }
    ],
    "sg:phone":"+44 1799 525736",
    "sg:postcode":"CB10 1HQ",
    "sg:province":"Cambridgeshire",
    "sg:tags":[
        "shop",
        "charity"
    ],
    "wof:name":"Imperial Cancer Research Fund",
    "wof:placetype":"venue"
},
  "geometry": {"coordinates":[0.2405219972,52.0241622925],"type":"Point"}
}