{
  "type": "Feature",
  "properties": {
    "addr:full":"11 Station Road, Admaston Telford Shropshire TF5 0BW",
    "addr:housenumber":"11",
    "addr:postcode":"tf5 0bw",
    "addr:street":"Station Road",
    "iso:country":"GB",
    "sg:address":"11 Station Road, Admaston",
    "sg:city":"Telford",
    "sg:classifiers":[
        {
            "category":"Organizations",
            "subcategory":"Non-profit Organization",
            "type":"Services"
        }
    ],
    "sg:phone":"+44 1952 254456",
    "sg:postcode":"TF5 0BW",
    "sg:province":"Shropshire",
    "sg:tags":[
        "organisation",
        "voluntary",
        "charity"
    ],
    "wof:name":"Gideons International",
    "wof:placetype":"venue"
},
  "geometry": {"coordinates":[-2.5445289612,52.7132339478],"type":"Point"}
}