{
  "type": "Feature",
  "properties": {
    "addr:full":"21 Harmondsworth Road West Drayton Greater London UB7 9JJ",
    "addr:housenumber":"21",
    "addr:postcode":"ub7 9jj",
    "addr:street":"Harmondsworth Road",
    "iso:country":"GB",
    "sg:address":"21 Harmondsworth Road",
    "sg:city":"West Drayton",
    "sg:classifiers":[
        {
            "category":"Building & Trades",
            "subcategory":"Construction",
            "type":"Services"
        }
    ],
    "sg:phone":"+44 1895 442441",
    "sg:postcode":"UB7 9JJ",
    "sg:province":"Greater London",
    "sg:tags":[
        "monumental",
        "mason"
    ],
    "wof:name":"W J Lafford Ltd.",
    "wof:placetype":"venue"
},
  "geometry": {"coordinates":[-0.467131,51.501514],"type":"Point"}
}