{
  "type": "Feature",
  "properties": {
    "iso:country":"GB",
    "sg:address":"2 Maybush Cottage, Common Rd",
    "sg:city":"Thatcham",
    "sg:classifiers":[
        {
            "category":"Building & Trades",
            "subcategory":"Electrical",
            "type":"Services"
        }
    ],
    "sg:phone":"+44 1635 268805",
    "sg:postcode":"RG19 8LS",
    "sg:province":"Berkshire",
    "sg:tags":[
        "lighting"
    ],
    "wof:name":"High Technology Lighting & Heating Ltd",
    "wof:placetype":"venue"
},
  "geometry": {"coordinates":[-1.24873,51.35474],"type":"Point"}
}