{
  "type": "Feature",
  "properties": {
    "iso:country":"GB",
    "sg:address":"10 Tilton Road, Burbage",
    "sg:city":"Hinckley",
    "sg:classifiers":[
        {
            "category":"Shopping",
            "subcategory":"Clothing, Apparel, & Fashions",
            "type":"Retail Goods"
        }
    ],
    "sg:postcode":"LE10 2SE",
    "sg:province":"Leicestershire",
    "sg:tags":[
        "ladieswear"
    ],
    "wof:name":"Glenda Fashions",
    "wof:placetype":"venue"
},
  "geometry": {"coordinates":[-1.36161,52.530434],"type":"Point"}
}