{
  "type": "Feature",
  "properties": {
    "addr:full":"Unit 15, Bloomsgrove Industrial Estate Nottingham Nottinghamshire NG7 3JG",
    "addr:housenumber":"unit 15",
    "addr:postcode":"ng7 3jg",
    "addr:street":"Bloomsgrove Industrial Estate",
    "iso:country":"GB",
    "sg:address":"Unit 15, Bloomsgrove Industrial Estate",
    "sg:city":"Nottingham",
    "sg:classifiers":[
        {
            "category":"Shopping",
            "type":"Retail Goods"
        },
        {
            "category":"Professional",
            "subcategory":"Printing & Photocopies",
            "type":"Services"
        }
    ],
    "sg:phone":"+44 115 978 6172",
    "sg:postcode":"NG7 3JG",
    "sg:province":"Nottinghamshire",
    "sg:tags":[
        "packaging",
        "bag",
        "paper",
        "cardboard",
        "manufacturer"
    ],
    "wof:name":"Unita Packaging Ltd.",
    "wof:placetype":"venue"
},
  "geometry": {"coordinates":[-1.1719399691,52.9560966492],"type":"Point"}
}