{
  "type": "Feature",
  "properties": {
    "iso:country":"GB",
    "sg:address":"12 St Catherines Road",
    "sg:city":"Grantham",
    "sg:classifiers":[
        {
            "category":"Manufacturing",
            "subcategory":"Tools & Machinery",
            "type":"Manufacturing & Wholesale Goods"
        }
    ],
    "sg:phone":"+44 1476 564877",
    "sg:postcode":"NG31 6TS",
    "sg:province":"Lincolnshire",
    "sg:tags":[
        "society",
        "friendly"
    ],
    "wof:name":"Thomas & King Insurance Services",
    "wof:placetype":"venue"
},
  "geometry": {"coordinates":[-0.6385,52.909859],"type":"Point"}
}