{
  "type": "Feature",
  "properties": {
    "iso:country":"GB",
    "sg:address":"9 Central Avenue",
    "sg:city":"Canvey Island",
    "sg:classifiers":[
        {
            "category":"Retail",
            "subcategory":"Repair Shop",
            "type":"Services"
        }
    ],
    "sg:phone":"+44 1268 691416",
    "sg:postcode":"SS8 9QR",
    "sg:province":"Essex",
    "sg:tags":[
        "maintenance"
    ],
    "wof:name":"J S Jackson & Son",
    "wof:placetype":"venue"
},
  "geometry": {"coordinates":[0.568763,51.526031],"type":"Point"}
}