{
  "type": "Feature",
  "properties": {
    "addr:full":"342-344 Railway Arches, Sheridan Road London Greater London E7 9EF",
    "addr:housenumber":"342-344",
    "addr:postcode":"e7 9ef",
    "addr:street":"Railway Arches Sheridan Road",
    "iso:country":"GB",
    "sg:address":"342-344 Railway Arches, Sheridan Road",
    "sg:city":"London",
    "sg:classifiers":[
        {
            "category":"Building & Trades",
            "subcategory":"Construction",
            "type":"Services"
        }
    ],
    "sg:phone":"+44 20 8519 9595",
    "sg:postcode":"E7 9EF",
    "sg:province":"Greater London",
    "sg:tags":[
        "platform",
        "work",
        "scaffolding"
    ],
    "wof:name":"Premier Scaffolding Co. Ltd.",
    "wof:placetype":"venue"
},
  "geometry": {"coordinates":[0.01664,51.556389],"type":"Point"}
}