{
  "type": "Feature",
  "properties": {
    "iso:country":"GB",
    "sg:address":"23a Coopersale Rd",
    "sg:city":"Hackney",
    "sg:classifiers":[
        {
            "category":"Education",
            "subcategory":"Library",
            "type":"Public Place"
        }
    ],
    "sg:phone":"+44 20 8533 1189",
    "sg:postcode":"E9 6AU",
    "sg:province":"Greater London",
    "sg:tags":[
        "reproduction",
        "furniture"
    ],
    "wof:name":"Mascot Furnishers",
    "wof:placetype":"venue"
},
  "geometry": {"coordinates":[-0.0413290001,51.5494308472],"type":"Point"}
}