{
  "type": "Feature",
  "properties": {
    "addr:full":"28 High St Shepton Mallet Somerset BA4 5AN",
    "addr:housenumber":"28",
    "addr:postcode":"ba4 5an",
    "addr:street":"High St",
    "iso:country":"GB",
    "sg:address":"28 High St",
    "sg:city":"Shepton Mallet",
    "sg:classifiers":[
        {
            "category":"Building & Trades",
            "subcategory":"Pest Control",
            "type":"Services"
        }
    ],
    "sg:phone":"+44 1749 347000",
    "sg:postcode":"BA4 5AN",
    "sg:province":"Somerset",
    "sg:tags":[
        "-",
        "direct",
        "mortgage"
    ],
    "wof:name":"Future Homeowner",
    "wof:placetype":"venue"
},
  "geometry": {"coordinates":[-2.547777,51.18922],"type":"Point"}
}