{
  "type": "Feature",
  "properties": {
    "addr:full":"4 Hayes Gate Holdings, Hayesgate Chepstow Gloucestershire NP16 6LJ",
    "addr:housenumber":"4",
    "addr:postcode":"np16 6lj",
    "addr:street":"Hayes Gate Holdings Hayesgate",
    "iso:country":"GB",
    "sg:address":"4 Hayes Gate Holdings, Hayesgate",
    "sg:city":"Chepstow",
    "sg:classifiers":[
        {
            "category":"Farming",
            "subcategory":"Livestock Farm",
            "type":"Manufacturing & Wholesale Goods"
        },
        {
            "category":"Farming",
            "subcategory":"Farm",
            "type":"Manufacturing & Wholesale Goods"
        }
    ],
    "sg:postcode":"NP16 6LJ",
    "sg:province":"Gloucestershire",
    "sg:tags":[
        "mixed",
        "crop",
        "others"
    ],
    "wof:name":"Thomas John E Cracknell",
    "wof:placetype":"venue"
},
  "geometry": {"coordinates":[-2.708696,51.618622],"type":"Point"}
}