{
  "type": "Feature",
  "properties": {
    "addr:full":"52 George Street, China Town Manchester Greater Manchester M1 4HF",
    "addr:housenumber":"52",
    "addr:postcode":"m1 4hf",
    "addr:street":"George Street",
    "iso:country":"GB",
    "sg:address":"52 George Street, China Town",
    "sg:city":"Manchester",
    "sg:classifiers":[
        {
            "category":"Recreation",
            "subcategory":"Gun Range",
            "type":"Entertainment"
        },
        {
            "category":"Sports & Exercise",
            "subcategory":"Playing Field",
            "type":"Entertainment"
        }
    ],
    "sg:phone":"+44 161 236 6603",
    "sg:postcode":"M1 4HF",
    "sg:province":"Greater Manchester",
    "sg:tags":[
        "operator",
        "tour",
        "agency",
        "ticket",
        "airline"
    ],
    "wof:name":"Jetset Europe Ltd.",
    "wof:placetype":"venue"
},
  "geometry": {"coordinates":[-2.240456,53.479107],"type":"Point"}
}