{
  "type": "Feature",
  "properties": {
    "iso:country":"GB",
    "sg:address":"Porthdafarch Rd",
    "sg:city":"Holyhead",
    "sg:classifiers":[
        {
            "category":"Retail",
            "subcategory":"Auto Repair",
            "type":"Services"
        }
    ],
    "sg:postcode":"LL65 2SA",
    "sg:province":"Isle of Anglesey",
    "sg:tags":[
        "modification",
        "garage"
    ],
    "wof:name":"Davies,Paul,",
    "wof:placetype":"venue"
},
  "geometry": {"coordinates":[-4.630714,53.30637],"type":"Point"}
}