{
  "type": "Feature",
  "properties": {
    "addr:full":"17 Oxford Street Woodstock Oxfordshire OX20 1TH",
    "addr:housenumber":"17",
    "addr:postcode":"ox20 1th",
    "addr:street":"Oxford Street",
    "iso:country":"GB",
    "sg:address":"17 Oxford Street",
    "sg:city":"Woodstock",
    "sg:classifiers":[
        {
            "category":"Shopping",
            "subcategory":"Florist",
            "type":"Retail Goods"
        }
    ],
    "sg:phone":"+44 1993 811655",
    "sg:postcode":"OX20 1TH",
    "sg:province":"Oxfordshire",
    "wof:name":"The Dutch Connection",
    "wof:placetype":"venue"
},
  "geometry": {"coordinates":[-1.3539030552,51.8471794128],"type":"Point"}
}