{
  "type": "Feature",
  "properties": {
    "addr:full":"Unit A Salop St Bilston West Midlands WV14 0TQ",
    "addr:housenumber":"unit a",
    "addr:postcode":"wv14 0tq",
    "addr:street":"St",
    "iso:country":"GB",
    "sg:address":"Unit A Salop St",
    "sg:city":"Bilston",
    "sg:classifiers":[
        {
            "category":"Professional",
            "subcategory":"Engineering",
            "type":"Services"
        }
    ],
    "sg:phone":"+44 1902 490207",
    "sg:postcode":"WV14 0TQ",
    "sg:province":"West Midlands",
    "sg:tags":[
        "precision",
        "engineer"
    ],
    "wof:name":"B V Components Ltd",
    "wof:placetype":"venue"
},
  "geometry": {"coordinates":[-2.0744900703,52.5666351318],"type":"Point"}
}