{
  "type": "Feature",
  "properties": {
    "addr:full":"147 Fintry Drive Dundee Dundee City DD4 9HE",
    "addr:housenumber":"147",
    "addr:postcode":"dd4 9he",
    "addr:street":"Fintry Drive",
    "iso:country":"GB",
    "sg:address":"147 Fintry Drive",
    "sg:city":"Dundee",
    "sg:classifiers":[
        {
            "category":"Social Services",
            "subcategory":"Adult Care",
            "type":"Services"
        },
        {
            "category":"Organizations",
            "subcategory":"Community Association",
            "type":"Services"
        }
    ],
    "sg:phone":"+44 1382 903545",
    "sg:postcode":"DD4 9HE",
    "sg:province":"Dundee City",
    "sg:tags":[
        "co-operatives",
        "society",
        "housing",
        "trust",
        "sheltered"
    ],
    "wof:name":"Abertay Housing Association Ltd.",
    "wof:placetype":"venue"
},
  "geometry": {"coordinates":[-2.940458,56.490219],"type":"Point"}
}