{
  "type": "Feature",
  "properties": {
    "addr:full":"43 Ladies Mile Road Brighton East Sussex BN1 8TA",
    "addr:housenumber":"43",
    "addr:postcode":"bn1 8ta",
    "addr:street":"Ladies Mile Road",
    "iso:country":"GB",
    "sg:address":"43 Ladies Mile Road",
    "sg:city":"Brighton",
    "sg:classifiers":[
        {
            "category":"Farming",
            "subcategory":"Fish & Marine Products",
            "type":"Manufacturing & Wholesale Goods"
        },
        {
            "category":"Food & Beverages",
            "subcategory":"Meat & Fish",
            "type":"Retail Goods"
        }
    ],
    "sg:phone":"+44 1273 553162",
    "sg:postcode":"BN1 8TA",
    "sg:province":"East Sussex",
    "sg:tags":[
        "fishmonger",
        "butcher"
    ],
    "wof:name":"Chris Lewsey & Tim Cardigan",
    "wof:placetype":"venue"
},
  "geometry": {"coordinates":[-0.144635,50.863926],"type":"Point"}
}