{
  "type": "Feature",
  "properties": {
    "addr:full":"25 Sheffield Terrace London Greater London W8 7NQ",
    "addr:housenumber":"25",
    "addr:postcode":"w8 7nq",
    "addr:street":"Sheffield Terrace",
    "iso:country":"GB",
    "sg:address":"25 Sheffield Terrace",
    "sg:city":"London",
    "sg:classifiers":[
        {
            "category":"Organizations",
            "subcategory":"Non-profit Organization",
            "type":"Services"
        }
    ],
    "sg:phone":"+44 20 7727 5586",
    "sg:postcode":"W8 7NQ",
    "sg:province":"Greater London",
    "sg:tags":[
        "organisation",
        "voluntary",
        "charity"
    ],
    "wof:name":"The Pathfinder Fellowship",
    "wof:placetype":"venue"
},
  "geometry": {"coordinates":[-0.1959719956,51.5052833557],"type":"Point"}
}