{
  "type": "Feature",
  "properties": {
    "addr:full":"232 Bath Road Slough Berkshire SL1 3XE",
    "addr:housenumber":"232",
    "addr:postcode":"sl1 3xe",
    "addr:street":"Bath Road",
    "iso:country":"GB",
    "sg:address":"232 Bath Road",
    "sg:city":"Slough",
    "sg:classifiers":[
        {
            "category":"Autos & Motor Vehicles",
            "subcategory":"Fuel & Gas Station",
            "type":"Retail Goods"
        }
    ],
    "sg:phone":"+44 1753 533021",
    "sg:postcode":"SL1 3XE",
    "sg:province":"Berkshire",
    "sg:tags":[
        "hr",
        "petrol"
    ],
    "wof:name":"Jet Service Station",
    "wof:placetype":"venue"
},
  "geometry": {"coordinates":[-0.616197,51.513309],"type":"Point"}
}