{
  "type": "Feature",
  "properties": {
    "iso:country":"GB",
    "sg:address":"The Mill, Alpheton",
    "sg:city":"Sudbury",
    "sg:classifiers":[
        {
            "category":"Arts & Performance",
            "subcategory":"Theater",
            "type":"Entertainment"
        }
    ],
    "sg:phone":"+44 1787 247040",
    "sg:postcode":"CO10 9BG",
    "sg:province":"Essex",
    "sg:tags":[
        "equipment",
        "cinema"
    ],
    "wof:name":"Cinesales Ltd.",
    "wof:placetype":"venue"
},
  "geometry": {"coordinates":[0.748396,52.123398],"type":"Point"}
}