{
  "type": "Feature",
  "properties": {
    "addr:full":"Botany Bay Lane Chislehurst Kent BR7 5PT",
    "addr:postcode":"br7 5pt",
    "addr:street":"Botany Bay Lane",
    "iso:country":"GB",
    "sg:address":"Botany Bay Lane",
    "sg:city":"Chislehurst",
    "sg:classifiers":[
        {
            "category":"Home & Garden",
            "subcategory":"Home Furnishings",
            "type":"Retail Goods"
        }
    ],
    "sg:phone":"+44 20 8295 0539",
    "sg:postcode":"BR7 5PT",
    "sg:province":"Kent",
    "sg:tags":[
        "furnishers",
        "planner",
        "kitchen"
    ],
    "wof:name":"Enright Cabinets",
    "wof:placetype":"venue"
},
  "geometry": {"coordinates":[0.0712380037,51.4037361145],"type":"Point"}
}