{
  "type": "Feature",
  "properties": {
    "iso:country":"GB",
    "sg:address":"Estrayer Park Farm, Tavistock Road",
    "sg:city":"Okehampton",
    "sg:classifiers":[
        {
            "category":"Farming",
            "subcategory":"Farm",
            "type":"Manufacturing & Wholesale Goods"
        }
    ],
    "sg:phone":"+44 1837 52737",
    "sg:postcode":"EX20 4LR",
    "sg:province":"Devon",
    "sg:tags":[
        "mixed",
        "crop"
    ],
    "wof:name":"A C Littlejohns",
    "wof:placetype":"venue"
},
  "geometry": {"coordinates":[-4.0025148392,50.7392234802],"type":"Point"}
}