{
  "type": "Feature",
  "properties": {
    "addr:full":"Shepherds Grove Industrial Estate, Stanton West Bury St Edmunds Suffolk IP31 2AR",
    "addr:housenumber":"estate",
    "addr:postcode":"ip31 2ar",
    "addr:street":"Shepherds Grove Industrial;Stanton West",
    "iso:country":"GB",
    "sg:address":"Shepherds Grove Industrial Estate, Stanton West",
    "sg:city":"Bury St Edmunds",
    "sg:classifiers":[
        {
            "category":"Home & Garden",
            "subcategory":"Hardware",
            "type":"Retail Goods"
        }
    ],
    "sg:postcode":"IP31 2AR",
    "sg:province":"Suffolk",
    "sg:tags":[
        "fixing",
        "nuts",
        "bolt"
    ],
    "wof:name":"Anglia Stainless Ltd.",
    "wof:placetype":"venue"
},
  "geometry": {"coordinates":[0.882333,52.326672],"type":"Point"}
}