{
  "type": "Feature",
  "properties": {
    "addr:full":"1 Medbourne Close, Moulton Northampton Northamptonshire NN3 7LH",
    "addr:housenumber":"1",
    "addr:postcode":"nn3 7lh",
    "addr:street":"Medbourne Close",
    "iso:country":"GB",
    "sg:address":"1 Medbourne Close, Moulton",
    "sg:city":"Northampton",
    "sg:classifiers":[
        {
            "category":"Organizations",
            "subcategory":"Non-profit Organization",
            "type":"Services"
        }
    ],
    "sg:postcode":"NN3 7LH",
    "sg:province":"Northamptonshire",
    "sg:tags":[
        "organisation",
        "voluntary",
        "charity"
    ],
    "wof:name":"Multiple Sclerosis Society of Great Britain & Northern Ireland",
    "wof:placetype":"venue"
},
  "geometry": {"coordinates":[-0.861331,52.279903],"type":"Point"}
}