{
  "type": "Feature",
  "properties": {
    "addr:full":"74 Flatt Road Largs North Ayrshire KA30 9EB",
    "addr:housenumber":"74",
    "addr:postcode":"ka30 9eb",
    "addr:street":"Flatt Road",
    "iso:country":"GB",
    "sg:address":"74 Flatt Road",
    "sg:city":"Largs",
    "sg:classifiers":[
        {
            "category":"Professional",
            "subcategory":"Art Services",
            "type":"Services"
        },
        {
            "category":"Building & Trades",
            "subcategory":"Construction",
            "type":"Services"
        }
    ],
    "sg:phone":"+44 1475 674657",
    "sg:postcode":"KA30 9EB",
    "sg:province":"North Ayrshire",
    "sg:tags":[
        "decorator",
        "painter"
    ],
    "wof:name":"Linn Decorators",
    "wof:placetype":"venue"
},
  "geometry": {"coordinates":[-4.8548660278,55.7944488525],"type":"Point"}
}