{
  "type": "Feature",
  "properties": {
    "addr:full":"Caxton Point Bessemer Drive Stevenage Hertfordshire SG1 2DX",
    "addr:postcode":"sg1 2dx",
    "addr:street":"Bessemer Drive",
    "iso:country":"GB",
    "sg:address":"Caxton Point Bessemer Drive",
    "sg:city":"Stevenage",
    "sg:classifiers":[
        {
            "category":"Professional",
            "subcategory":"Advertising",
            "type":"Services"
        }
    ],
    "sg:phone":"+44 1438 352433",
    "sg:postcode":"SG1 2DX",
    "sg:province":"Hertfordshire",
    "wof:name":"M J R (Balloons) Ltd.",
    "wof:placetype":"venue"
},
  "geometry": {"coordinates":[-0.1886799932,51.9056091309],"type":"Point"}
}