{
  "type": "Feature",
  "properties": {
    "iso:country":"GB",
    "sg:address":"Calsay Cottage, 103 Newtrows Road",
    "sg:city":"Lanark",
    "sg:classifiers":[
        {
            "category":"Building & Trades",
            "subcategory":"Landscaping Services",
            "type":"Services"
        }
    ],
    "sg:postcode":"ML11 0ER",
    "sg:province":"South Lanarkshire",
    "sg:tags":[
        "landscape",
        "contractor"
    ],
    "wof:name":"J M Murray Landscapes",
    "wof:placetype":"venue"
},
  "geometry": {"coordinates":[-3.7813839912,55.673866272],"type":"Point"}
}