{
  "type": "Feature",
  "properties": {
    "addr:full":"23 Boot Lane, Dunton Biggleswade Bedfordshire SG18 8RP",
    "addr:housenumber":"23",
    "addr:postcode":"sg18 8rp",
    "addr:street":"Boot Lane",
    "iso:country":"GB",
    "sg:address":"23 Boot Lane, Dunton",
    "sg:city":"Biggleswade",
    "sg:classifiers":[
        {
            "category":"Home & Garden",
            "subcategory":"Household Appliances",
            "type":"Retail Goods"
        }
    ],
    "sg:phone":"+44 1767 312593",
    "sg:postcode":"SG18 8RP",
    "sg:province":"Bedfordshire",
    "sg:tags":[
        "electrical"
    ],
    "wof:name":"Michael J Whitby",
    "wof:placetype":"venue"
},
  "geometry": {"coordinates":[-0.196709007,52.0844955444],"type":"Point"}
}