{
  "type": "Feature",
  "properties": {
    "addr:full":"102 Mill Street Liverpool Merseyside L8 5UB",
    "addr:housenumber":"102",
    "addr:postcode":"l8 5ub",
    "addr:street":"Mill Street",
    "iso:country":"GB",
    "sg:address":"102 Mill Street",
    "sg:city":"Liverpool",
    "sg:classifiers":[
        {
            "category":"Manufacturing",
            "subcategory":"Petroleum Products",
            "type":"Manufacturing & Wholesale Goods"
        },
        {
            "category":"Home & Garden",
            "subcategory":"Hardware",
            "type":"Retail Goods"
        },
        {
            "category":"Building & Trades",
            "subcategory":"Construction",
            "type":"Services"
        }
    ],
    "sg:phone":"+44 151 708 0880",
    "sg:postcode":"L8 5UB",
    "sg:province":"Merseyside",
    "sg:tags":[
        "double",
        "glazing",
        "improvement",
        "installers",
        "centre"
    ],
    "wof:name":"Thermal-K-Shield (Liverpool) Ltd.",
    "wof:placetype":"venue"
},
  "geometry": {"coordinates":[-2.9745049477,53.3918037415],"type":"Point"}
}