{
  "type": "Feature",
  "properties": {
    "addr:full":"9 Adam & Eve Street Market Harborough Leicestershire LE16 7LT",
    "addr:housenumber":"9",
    "addr:postcode":"le16 7lt",
    "addr:street":"Adam & Eve Street",
    "iso:country":"GB",
    "sg:address":"9 Adam & Eve Street",
    "sg:city":"Market Harborough",
    "sg:classifiers":[
        {
            "category":"Shopping",
            "subcategory":"Musical Instruments",
            "type":"Retail Goods"
        }
    ],
    "sg:phone":"+44 1933 227837",
    "sg:postcode":"LE16 7LT",
    "sg:province":"Leicestershire",
    "sg:tags":[
        "music",
        "sheet"
    ],
    "wof:name":"Keyboard Kavern",
    "wof:placetype":"venue"
},
  "geometry": {"coordinates":[-0.92016,52.47842],"type":"Point"}
}