{
  "type": "Feature",
  "properties": {
    "iso:country":"GB",
    "sg:address":"Broomhill Industrial Estate, Kilsyth Road, Kirkintilloch",
    "sg:city":"Glasgow",
    "sg:classifiers":[
        {
            "category":"Wholesale",
            "subcategory":"Machinery & Supplies",
            "type":"Manufacturing & Wholesale Goods"
        }
    ],
    "sg:phone":"+44 141 776 6274",
    "sg:postcode":"G66 1TQ",
    "sg:province":"East Dunbartonshire",
    "sg:tags":[
        "pump"
    ],
    "wof:name":"Ritchie Mackenzie & Co. Ltd.",
    "wof:placetype":"venue"
},
  "geometry": {"coordinates":[-4.1405200958,55.9464111328],"type":"Point"}
}