{
  "type": "Feature",
  "properties": {
    "addr:full":"2 Downside, Adisham Road, Bekesbourne Canterbury Kent CT4 5HA",
    "addr:housenumber":"2",
    "addr:postcode":"ct4 5ha",
    "addr:street":"Downside Adisham Road",
    "iso:country":"GB",
    "sg:address":"2 Downside, Adisham Road, Bekesbourne",
    "sg:city":"Canterbury",
    "sg:classifiers":[
        {
            "category":"Building & Trades",
            "subcategory":"Construction",
            "type":"Services"
        }
    ],
    "sg:phone":"+44 1227 830789",
    "sg:postcode":"CT4 5HA",
    "sg:province":"Kent",
    "sg:tags":[
        "builder"
    ],
    "wof:name":"All Trades Group Services",
    "wof:placetype":"venue"
},
  "geometry": {"coordinates":[1.1442500353,51.2576599121],"type":"Point"}
}