{
  "type": "Feature",
  "properties": {
    "iso:country":"GB",
    "sg:address":"Morton Park Yarm Road",
    "sg:city":"Darlington",
    "sg:classifiers":[
        {
            "category":"Shopping",
            "subcategory":"Computers & Home Electronics",
            "type":"Retail Goods"
        }
    ],
    "sg:postcode":"DL1 4PJ",
    "sg:province":"Durham",
    "sg:tags":[
        "aerial",
        "television",
        "radio"
    ],
    "wof:name":"Earl Saddington & Associates Ltd.",
    "wof:placetype":"venue"
},
  "geometry": {"coordinates":[-1.536437,54.5154],"type":"Point"}
}