{
  "type": "Feature",
  "properties": {
    "iso:country":"GB",
    "sg:address":"Passfield Enterprise Centre",
    "sg:city":"Liphook",
    "sg:classifiers":[
        {
            "category":"Building & Trades",
            "subcategory":"Plumbing",
            "type":"Services"
        }
    ],
    "sg:phone":"+44 1428 751180",
    "sg:postcode":"GU35 0LP",
    "sg:province":"Hampshire",
    "sg:tags":[
        "heating"
    ],
    "wof:name":"A W Ball Building Contractors",
    "wof:placetype":"venue"
},
  "geometry": {"coordinates":[-0.8630899787,51.1183586121],"type":"Point"}
}