{
  "type": "Feature",
  "properties": {
    "addr:full":"32 Wilson Road, Blackeley Manchester Greater Manchester M9 8BQ",
    "addr:housenumber":"32",
    "addr:postcode":"m9 8bq",
    "addr:street":"Wilson Road",
    "iso:country":"GB",
    "sg:address":"32 Wilson Road, Blackeley",
    "sg:city":"Manchester",
    "sg:classifiers":[
        {
            "category":"Building & Trades",
            "subcategory":"Plumbing",
            "type":"Services"
        }
    ],
    "sg:postcode":"M9 8BQ",
    "sg:province":"Greater Manchester",
    "sg:tags":[
        "heating"
    ],
    "wof:name":"J A Doyle Plumbers & Builders",
    "wof:placetype":"venue"
},
  "geometry": {"coordinates":[-2.214518,53.51754],"type":"Point"}
}