{
  "type": "Feature",
  "properties": {
    "addr:full":"Vauxhall St, Queens Cross Dudley West Midlands DY1 1TA",
    "addr:postcode":"dy1 1ta",
    "addr:street":"Vauxhall St",
    "iso:country":"GB",
    "sg:address":"Vauxhall St, Queens Cross",
    "sg:city":"Dudley",
    "sg:classifiers":[
        {
            "category":"Manufacturing",
            "subcategory":"Metals",
            "type":"Manufacturing & Wholesale Goods"
        }
    ],
    "sg:phone":"+44 1384 250793",
    "sg:postcode":"DY1 1TA",
    "sg:province":"West Midlands",
    "sg:tags":[
        "work",
        "sheet"
    ],
    "wof:name":"Windmill Engineering",
    "wof:placetype":"venue"
},
  "geometry": {"coordinates":[-2.092004,52.507351],"type":"Point"}
}