{
  "type": "Feature",
  "properties": {
    "addr:full":"81-83 Mill Street Leek Staffordshire ST13 8EU",
    "addr:housenumber":"81-83",
    "addr:postcode":"st13 8eu",
    "addr:street":"Mill Street",
    "iso:country":"GB",
    "sg:address":"81-83 Mill Street",
    "sg:city":"Leek",
    "sg:classifiers":[
        {
            "category":"Bars & Pubs",
            "type":"Food & Drink"
        }
    ],
    "sg:phone":"+44 1538 382880",
    "sg:postcode":"ST13 8EU",
    "sg:province":"Staffordshire",
    "sg:tags":[
        "pubs",
        "inn"
    ],
    "wof:name":"The Jester Inn",
    "wof:placetype":"venue"
},
  "geometry": {"coordinates":[-2.031756,53.108036],"type":"Point"}
}