{
  "type": "Feature",
  "properties": {
    "addr:full":"1 Halesowen Road Halesowen West Midlands B62 9AA",
    "addr:housenumber":"1",
    "addr:postcode":"b62 9aa",
    "addr:street":"Halesowen Road",
    "iso:country":"GB",
    "sg:address":"1 Halesowen Road",
    "sg:city":"Halesowen",
    "sg:classifiers":[
        {
            "category":"Retail",
            "subcategory":"Laundry & Dry Cleaning",
            "type":"Services"
        }
    ],
    "sg:phone":"+44 121 421 7744",
    "sg:postcode":"B62 9AA",
    "sg:province":"West Midlands",
    "sg:tags":[
        "alteration"
    ],
    "wof:name":"Elegance Dry Cleaners",
    "wof:placetype":"venue"
},
  "geometry": {"coordinates":[-2.027148,52.461956],"type":"Point"}
}