{
  "type": "Feature",
  "properties": {
    "addr:full":"36 Waterloo Road Bedford Bedfordshire MK40 3PQ",
    "addr:housenumber":"36",
    "addr:postcode":"mk40 3pq",
    "addr:street":"Waterloo Road",
    "iso:country":"GB",
    "sg:address":"36 Waterloo Road",
    "sg:city":"Bedford",
    "sg:classifiers":[
        {
            "category":"Social Services",
            "subcategory":"Retirement Home",
            "type":"Services"
        }
    ],
    "sg:phone":"+44 1234 351608",
    "sg:postcode":"MK40 3PQ",
    "sg:province":"Bedfordshire",
    "sg:tags":[
        "residential",
        "care"
    ],
    "wof:name":"Milton Lodge Residential Home for the Elderly",
    "wof:placetype":"venue"
},
  "geometry": {"coordinates":[-0.4587489963,52.1360626221],"type":"Point"}
}