{
  "type": "Feature",
  "properties": {
    "addr:full":"24 Tuesday Market Place King's Lynn Norfolk PE30 1JJ",
    "addr:housenumber":"24",
    "addr:postcode":"pe30 1jj",
    "addr:street":"Market Place",
    "iso:country":"GB",
    "sg:address":"24 Tuesday Market Place",
    "sg:city":"King's Lynn",
    "sg:classifiers":[
        {
            "category":"Manufacturing",
            "subcategory":"Tools & Machinery",
            "type":"Manufacturing & Wholesale Goods"
        },
        {
            "category":"Insurance",
            "subcategory":"Insurance Agent",
            "type":"Services"
        }
    ],
    "sg:phone":"+44 1553 774301",
    "sg:postcode":"PE30 1JJ",
    "sg:province":"Norfolk",
    "sg:tags":[
        "society",
        "friendly"
    ],
    "wof:name":"West Norfolk Insurance Services Ltd",
    "wof:placetype":"venue"
},
  "geometry": {"coordinates":[0.39445,52.755779],"type":"Point"}
}