{
  "type": "Feature",
  "properties": {
    "iso:country":"GB",
    "sg:address":"Hi-tech Ho, 2 Eastcott Rd",
    "sg:city":"Swindon",
    "sg:classifiers":[
        {
            "category":"Building & Trades",
            "subcategory":"Construction",
            "type":"Services"
        }
    ],
    "sg:postcode":"SN1 3LS",
    "sg:province":"Wiltshire",
    "sg:tags":[
        "builder"
    ],
    "wof:name":"Toucan Construction",
    "wof:placetype":"venue"
},
  "geometry": {"coordinates":[-1.781814,51.561764],"type":"Point"}
}