{
  "type": "Feature",
  "properties": {
    "addr:full":"The Rear Of 141 High Road Loughton Essex IG10 4LT",
    "addr:housenumber":"of 141",
    "addr:postcode":"ig10 4lt",
    "addr:street":"High Road",
    "iso:country":"GB",
    "sg:address":"The Rear Of 141 High Road",
    "sg:city":"Loughton",
    "sg:classifiers":[
        {
            "category":"Recreation",
            "subcategory":"Dog Park",
            "type":"Entertainment"
        }
    ],
    "sg:phone":"+44 20 8502 2241",
    "sg:postcode":"IG10 4LT",
    "sg:province":"Essex",
    "wof:name":"Top Coats Grooming Parlour",
    "wof:placetype":"venue"
},
  "geometry": {"coordinates":[0.0551789999,51.6473731995],"type":"Point"}
}