{
  "type": "Feature",
  "properties": {
    "addr:full":"52 Standishgate Wigan Lancashire WN1 1RQ",
    "addr:housenumber":"52",
    "addr:postcode":"wn1 1rq",
    "addr:street":"Standishgate Wigan",
    "iso:country":"GB",
    "sg:address":"52 Standishgate",
    "sg:city":"Wigan",
    "sg:classifiers":[
        {
            "category":"Shopping",
            "subcategory":"Music",
            "type":"Retail Goods"
        }
    ],
    "sg:postcode":"WN1 1RQ",
    "sg:province":"Lancashire",
    "sg:tags":[
        "record",
        "tape",
        "cd"
    ],
    "wof:name":"Omega Music Ltd",
    "wof:placetype":"venue"
},
  "geometry": {"coordinates":[-2.6301810741,53.5486564636],"type":"Point"}
}