{
  "type": "Feature",
  "properties": {
    "iso:country":"GB",
    "sg:address":"151 High Street",
    "sg:city":"Ventnor",
    "sg:classifiers":[
        {
            "category":"Building & Trades",
            "subcategory":"Construction",
            "type":"Services"
        }
    ],
    "sg:phone":"+44 1983 854961",
    "sg:postcode":"PO38 1LZ",
    "sg:province":"Isle of Wight",
    "sg:tags":[
        "roofing",
        "builder"
    ],
    "wof:name":"David George Wheatley",
    "wof:placetype":"venue"
},
  "geometry": {"coordinates":[-1.199647,50.596821],"type":"Point"}
}