{
  "type": "Feature",
  "properties": {
    "iso:country":"GB",
    "sg:address":"5 New Street",
    "sg:city":"Margate",
    "sg:classifiers":[
        {
            "category":"Retail",
            "subcategory":"Laundry & Dry Cleaning",
            "type":"Services"
        }
    ],
    "sg:phone":"+44 1843 292571",
    "sg:postcode":"CT9 1EG",
    "sg:province":"Kent",
    "sg:tags":[
        "cleaner",
        "alteration"
    ],
    "wof:name":"Mark Michaels Valet Service",
    "wof:placetype":"venue"
},
  "geometry": {"coordinates":[1.381172,51.388706],"type":"Point"}
}