{
  "type": "Feature",
  "properties": {
    "addr:full":"15 Military Road Canterbury Kent CT1 1LN",
    "addr:housenumber":"15",
    "addr:postcode":"ct1 1ln",
    "addr:street":"Military Road",
    "iso:country":"GB",
    "sg:address":"15 Military Road",
    "sg:city":"Canterbury",
    "sg:classifiers":[
        {
            "category":"Food & Beverages",
            "subcategory":"Fruits & Vegetables",
            "type":"Retail Goods"
        }
    ],
    "sg:phone":"+44 1227 464881",
    "sg:postcode":"CT1 1LN",
    "sg:province":"Kent",
    "sg:tags":[
        "greengrocer"
    ],
    "wof:name":"Dumbrells",
    "wof:placetype":"venue"
},
  "geometry": {"coordinates":[1.0872910023,51.2821502686],"type":"Point"}
}