{
  "type": "Feature",
  "properties": {
    "addr:full":"3 Beakes Road, Warley Smethwick West Midlands B67 5RS",
    "addr:housenumber":"3",
    "addr:postcode":"b67 5rs",
    "addr:street":"Beakes Road",
    "iso:country":"GB",
    "sg:address":"3 Beakes Road, Warley",
    "sg:city":"Smethwick",
    "sg:classifiers":[
        {
            "category":"Building & Trades",
            "subcategory":"Construction",
            "type":"Services"
        }
    ],
    "sg:phone":"+44 121 420 2952",
    "sg:postcode":"B67 5RS",
    "sg:province":"West Midlands",
    "sg:tags":[
        "builder"
    ],
    "wof:name":"Timescale Construction Services",
    "wof:placetype":"venue"
},
  "geometry": {"coordinates":[-1.9705530405,52.4805831909],"type":"Point"}
}