{
  "type": "Feature",
  "properties": {
    "iso:country":"GB",
    "sg:address":"49 Newport Street",
    "sg:city":"Bolton",
    "sg:classifiers":[
        {
            "category":"Food & Beverages",
            "subcategory":"Bakery",
            "type":"Retail Goods"
        }
    ],
    "sg:phone":"+44 1204 521182",
    "sg:postcode":"BL1 1NE",
    "sg:province":"Lancashire",
    "sg:tags":[
        "baker"
    ],
    "wof:name":"Hampsons",
    "wof:placetype":"venue"
},
  "geometry": {"coordinates":[-2.4289391041,53.5769004822],"type":"Point"}
}