{
  "type": "Feature",
  "properties": {
    "addr:full":"142-144 High Street Staines Berkshire TW18 4AH",
    "addr:housenumber":"142-144",
    "addr:postcode":"tw18 4ah",
    "addr:street":"High Street",
    "iso:country":"GB",
    "sg:address":"142-144 High Street",
    "sg:city":"Staines",
    "sg:classifiers":[
        {
            "category":"Real Estate",
            "subcategory":"Real Estate Agent",
            "type":"Services"
        }
    ],
    "sg:phone":"+44 1784 455299",
    "sg:postcode":"TW18 4AH",
    "sg:province":"Berkshire",
    "wof:name":"Townends",
    "wof:placetype":"venue"
},
  "geometry": {"coordinates":[-0.5070109963,51.4351959229],"type":"Point"}
}