{
  "type": "Feature",
  "properties": {
    "addr:full":"The Old Warm Baths, 76 Shacklewell La, Dalston London Greater London E8 2EY",
    "addr:housenumber":"76",
    "addr:postcode":"e8 2ey",
    "addr:street":"La Dalston",
    "iso:country":"GB",
    "sg:address":"The Old Warm Baths, 76 Shacklewell La, Dalston",
    "sg:city":"London",
    "sg:classifiers":[
        {
            "category":"Community Center",
            "type":"Public Place"
        }
    ],
    "sg:postcode":"E8 2EY",
    "sg:province":"Greater London",
    "sg:tags":[
        "centre"
    ],
    "wof:name":"Dalston Childrens Centre",
    "wof:placetype":"venue"
},
  "geometry": {"coordinates":[-0.07197,51.551331],"type":"Point"}
}