{
  "type": "Feature",
  "properties": {
    "iso:country":"GB",
    "sg:address":"Citadel Ho, Brants Bridge",
    "sg:city":"Bracknell",
    "sg:classifiers":[
        {
            "category":"Professional",
            "subcategory":"Art Services",
            "type":"Services"
        }
    ],
    "sg:phone":"+44 1344 484515",
    "sg:postcode":"RG12 3BQ",
    "sg:province":"Berkshire",
    "sg:tags":[
        "graphic",
        "designer"
    ],
    "wof:name":"Adhands Design & Print",
    "wof:placetype":"venue"
},
  "geometry": {"coordinates":[-0.7525,51.397831],"type":"Point"}
}