{
  "type": "Feature",
  "properties": {
    "addr:full":"Wesley House, The Green, Brackenfield Alfreton Derbyshire DE55 6AR",
    "addr:postcode":"de55 6ar",
    "addr:street":"The Green",
    "iso:country":"GB",
    "sg:address":"Wesley House, The Green, Brackenfield",
    "sg:city":"Alfreton",
    "sg:classifiers":[
        {
            "category":"Freight",
            "type":"Transportation"
        }
    ],
    "sg:phone":"+44 1773 832084",
    "sg:postcode":"DE55 6AR",
    "sg:province":"Derbyshire",
    "sg:tags":[
        "haulage",
        "transport",
        "road"
    ],
    "wof:name":"G A  Burton",
    "wof:placetype":"venue"
},
  "geometry": {"coordinates":[-1.4446840286,53.1272468567],"type":"Point"}
}