{
  "type": "Feature",
  "properties": {
    "addr:full":"29 London Road, Stanway Colchester Essex CO3 0NR",
    "addr:housenumber":"29",
    "addr:postcode":"co3 0nr",
    "addr:street":"London Road",
    "iso:country":"GB",
    "sg:address":"29 London Road, Stanway",
    "sg:city":"Colchester",
    "sg:classifiers":[
        {
            "category":"Retail",
            "subcategory":"Emissions Testing",
            "type":"Services"
        },
        {
            "category":"Professional",
            "subcategory":"Testing Lab",
            "type":"Services"
        }
    ],
    "sg:phone":"+44 1206 576282",
    "sg:postcode":"CO3 0NR",
    "sg:province":"Essex",
    "sg:tags":[
        "mot"
    ],
    "wof:name":"Stanway Garage",
    "wof:placetype":"venue"
},
  "geometry": {"coordinates":[0.8423709869,51.8884735107],"type":"Point"}
}