{
  "type": "Feature",
  "properties": {
    "addr:full":"150 Dobbies Loan Glasgow Glasgow City G4 0JE",
    "addr:housenumber":"150",
    "addr:postcode":"g4 0je",
    "addr:street":"Dobbies Loan",
    "iso:country":"GB",
    "sg:address":"150 Dobbies Loan",
    "sg:city":"Glasgow",
    "sg:classifiers":[
        {
            "category":"Shopping",
            "subcategory":"Department Store",
            "type":"Retail Goods"
        },
        {
            "category":"Shopping",
            "subcategory":"Bicycles & Sporting Goods",
            "type":"Retail Goods"
        }
    ],
    "sg:phone":"+44 141 332 2705",
    "sg:postcode":"G4 0JE",
    "sg:province":"Glasgow City",
    "sg:tags":[
        "shop",
        "cycle"
    ],
    "wof:name":"Dales Cycles Ltd.",
    "wof:placetype":"venue"
},
  "geometry": {"coordinates":[-4.2485399246,55.8676719666],"type":"Point"}
}