{
  "type": "Feature",
  "properties": {
    "addr:full":"Tanglewood Park Lane, Sharnbrook Bedford Bedfordshire MK44 1LX",
    "addr:postcode":"mk44 1lx",
    "addr:street":"Park Lane",
    "iso:country":"GB",
    "sg:address":"Tanglewood Park Lane, Sharnbrook",
    "sg:city":"Bedford",
    "sg:classifiers":[
        {
            "category":"Wholesale",
            "subcategory":"Fruits & Vegetables",
            "type":"Manufacturing & Wholesale Goods"
        }
    ],
    "sg:postcode":"MK44 1LX",
    "sg:province":"Bedfordshire",
    "wof:name":"Tanglewood Nurseries",
    "wof:placetype":"venue"
},
  "geometry": {"coordinates":[-0.544024,52.225994],"type":"Point"}
}