{
  "type": "Feature",
  "properties": {
    "addr:full":"Care Of Bridon Ropes, Carr Hill, Balby Doncaster South Yorkshire DN4 8DG",
    "addr:postcode":"balby;dn4 8dg",
    "addr:street":"Ropes Carr Hill",
    "iso:country":"GB",
    "sg:address":"Care Of Bridon Ropes, Carr Hill, Balby",
    "sg:city":"Doncaster",
    "sg:classifiers":[
        {
            "category":"Real Estate",
            "subcategory":"Architect",
            "type":"Services"
        }
    ],
    "sg:postcode":"DN4 8DG",
    "sg:province":"South Yorkshire",
    "wof:name":"Randerson,Ivan,",
    "wof:placetype":"venue"
},
  "geometry": {"coordinates":[-1.14199,53.5089],"type":"Point"}
}