{
  "type": "Feature",
  "properties": {
    "addr:full":"26 Briar Lawn, Abbeydale Gloucester Gloucestershire GL4 5YU",
    "addr:housenumber":"26",
    "addr:postcode":"gl4 5yu",
    "addr:street":"Briar Lawn",
    "iso:country":"GB",
    "sg:address":"26 Briar Lawn, Abbeydale",
    "sg:city":"Gloucester",
    "sg:classifiers":[
        {
            "category":"Building & Trades",
            "subcategory":"Construction",
            "type":"Services"
        }
    ],
    "sg:postcode":"GL4 5YU",
    "sg:province":"Gloucestershire",
    "sg:tags":[
        "glazier",
        "decorator",
        "painter"
    ],
    "wof:name":"Peter M Gwilliam",
    "wof:placetype":"venue"
},
  "geometry": {"coordinates":[-2.208233,51.833107],"type":"Point"}
}