{
  "type": "Feature",
  "properties": {
    "addr:full":"287 High Road Romford Essex RM6 6AX",
    "addr:housenumber":"287",
    "addr:postcode":"rm6 6ax",
    "addr:street":"High Road",
    "iso:country":"GB",
    "sg:address":"287 High Road",
    "sg:city":"Romford",
    "sg:classifiers":[
        {
            "category":"Autos & Motor Vehicles",
            "subcategory":"Fuel & Gas Station",
            "type":"Retail Goods"
        }
    ],
    "sg:phone":"+44 20 8590 6594",
    "sg:postcode":"RM6 6AX",
    "sg:province":"Essex",
    "sg:tags":[
        "petrol",
        "filling"
    ],
    "wof:name":"Chadwell Heath Filling Station",
    "wof:placetype":"venue"
},
  "geometry": {"coordinates":[0.1453099996,51.5727005005],"type":"Point"}
}