{
  "type": "Feature",
  "properties": {
    "addr:full":"Watnall Road, Hucknall Nottingham Nottinghamshire NG15 7NG",
    "addr:postcode":"ng15 7ng",
    "addr:street":"Watnall Road",
    "iso:country":"GB",
    "sg:address":"Watnall Road, Hucknall",
    "sg:city":"Nottingham",
    "sg:classifiers":[
        {
            "category":"Organizations",
            "subcategory":"Membership Organization",
            "type":"Services"
        }
    ],
    "sg:phone":"+44 115 963 3413",
    "sg:postcode":"NG15 7NG",
    "sg:province":"Nottinghamshire",
    "sg:tags":[
        "club"
    ],
    "wof:name":"The Central Social Club",
    "wof:placetype":"venue"
},
  "geometry": {"coordinates":[-1.209209,53.032398],"type":"Point"}
}