{
  "type": "Feature",
  "properties": {
    "iso:country":"GB",
    "sg:address":"5 Tadley Close",
    "sg:city":"Fleet",
    "sg:classifiers":[
        {
            "category":"Education",
            "subcategory":"Music School",
            "type":"Public Place"
        },
        {
            "category":"Building & Trades",
            "subcategory":"Construction",
            "type":"Services"
        }
    ],
    "sg:phone":"+44 1252 617385",
    "sg:postcode":"GU51 1DS",
    "sg:province":"Hampshire",
    "sg:tags":[
        "double",
        "glazing",
        "installers",
        "conservatory"
    ],
    "wof:name":"Crown Conservatories & Windows",
    "wof:placetype":"venue"
},
  "geometry": {"coordinates":[-0.85432899,51.2938652039],"type":"Point"}
}