{
  "type": "Feature",
  "properties": {
    "iso:country":"GB",
    "sg:address":"11 Effingham Square",
    "sg:city":"Rotherham",
    "sg:classifiers":[
        {
            "category":"Shopping",
            "subcategory":"Photographic Equipment",
            "type":"Retail Goods"
        }
    ],
    "sg:phone":"+44 1709 375558",
    "sg:postcode":"S65 1AT",
    "sg:province":"South Yorkshire",
    "wof:name":"Mike Leng Photographer",
    "wof:placetype":"venue"
},
  "geometry": {"coordinates":[-1.355072,53.433674],"type":"Point"}
}