{
  "type": "Feature",
  "properties": {
    "addr:full":"4 Kay Close, Newnham Road Plymouth Devon PL7 4LU",
    "addr:housenumber":"4",
    "addr:postcode":"pl7 4lu",
    "addr:street":"Kay Close Newnham Road",
    "iso:country":"GB",
    "sg:address":"4 Kay Close, Newnham Road",
    "sg:city":"Plymouth",
    "sg:classifiers":[
        {
            "category":"Food & Beverages",
            "subcategory":"Meat & Fish",
            "type":"Retail Goods"
        }
    ],
    "sg:phone":"+44 1752 338902",
    "sg:postcode":"PL7 4LU",
    "sg:province":"Devon",
    "sg:tags":[
        "chip"
    ],
    "wof:name":"Kenaxe Ltd.",
    "wof:placetype":"venue"
},
  "geometry": {"coordinates":[-4.0427918434,50.3977127075],"type":"Point"}
}