{
  "type": "Feature",
  "properties": {
    "iso:country":"GB",
    "sg:address":"17 Swan Street, Sileby",
    "sg:city":"Loughborough",
    "sg:classifiers":[
        {
            "category":"Professional",
            "subcategory":"Accounting & Tax Preparation",
            "type":"Services"
        },
        {
            "category":"Professional",
            "type":"Services"
        }
    ],
    "sg:phone":"+44 1509 812840",
    "sg:postcode":"LE12 7NN",
    "sg:province":"Leicestershire",
    "sg:tags":[
        "pattern",
        "industrial",
        "maker"
    ],
    "wof:name":"Cromaston Ltd",
    "wof:placetype":"venue"
},
  "geometry": {"coordinates":[-1.106953,52.733017],"type":"Point"}
}