{
  "type": "Feature",
  "properties": {
    "iso:country":"GB",
    "sg:address":"106 Victoria Street",
    "sg:city":"Cwmbran",
    "sg:classifiers":[
        {
            "category":"Sports & Exercise",
            "subcategory":"Sports Center",
            "type":"Entertainment"
        }
    ],
    "sg:phone":"+44 1633 868440",
    "sg:postcode":"NP44 3JP",
    "sg:province":"Monmouthshire",
    "sg:tags":[
        "shop",
        "good"
    ],
    "wof:name":"The Dartbox",
    "wof:placetype":"venue"
},
  "geometry": {"coordinates":[-3.019438982,51.6456832886],"type":"Point"}
}