{
  "type": "Feature",
  "properties": {
    "addr:full":"26 Sunningdale Drive, Hopwood Heywood Lancashire OL10 2DB",
    "addr:housenumber":"26",
    "addr:postcode":"ol10 2db",
    "addr:street":"Sunningdale Drive",
    "iso:country":"GB",
    "sg:address":"26 Sunningdale Drive, Hopwood",
    "sg:city":"Heywood",
    "sg:classifiers":[
        {
            "category":"Building & Trades",
            "subcategory":"Construction",
            "type":"Services"
        }
    ],
    "sg:phone":"+44 1706 365051",
    "sg:postcode":"OL10 2DB",
    "sg:province":"Lancashire",
    "sg:tags":[
        "roofing",
        "contracting"
    ],
    "wof:name":"Eastridge Construction",
    "wof:placetype":"venue"
},
  "geometry": {"coordinates":[-2.217730999,53.5842475891],"type":"Point"}
}