{
  "type": "Feature",
  "properties": {
    "addr:full":"207 Broad Lane Leeds West Yorkshire LS13 2NJ",
    "addr:housenumber":"207",
    "addr:postcode":"ls13 2nj",
    "addr:street":"Broad Lane",
    "iso:country":"GB",
    "sg:address":"207 Broad Lane",
    "sg:city":"Leeds",
    "sg:classifiers":[
        {
            "category":"Building & Trades",
            "subcategory":"Construction",
            "type":"Services"
        }
    ],
    "sg:phone":"+44 113 256 2515",
    "sg:postcode":"LS13 2NJ",
    "sg:province":"West Yorkshire",
    "sg:tags":[
        "decorator",
        "painter"
    ],
    "wof:name":"M G Wood Painting Contractor",
    "wof:placetype":"venue"
},
  "geometry": {"coordinates":[-1.627997,53.816212],"type":"Point"}
}