{
  "type": "Feature",
  "properties": {
    "addr:full":"18 Citadel Rd Plymouth Devon PL1 3BA",
    "addr:housenumber":"18",
    "addr:postcode":"pl1 3ba",
    "addr:street":"Citadel Rd",
    "iso:country":"GB",
    "sg:address":"18 Citadel Rd",
    "sg:city":"Plymouth",
    "sg:classifiers":[
        {
            "category":"Organizations",
            "subcategory":"Community Association",
            "type":"Services"
        }
    ],
    "sg:phone":"+44 1752 668103",
    "sg:postcode":"PL1 3BA",
    "sg:province":"Devon",
    "sg:tags":[
        "society",
        "housing"
    ],
    "wof:name":"Sutton Hastow Housing Association Ltd",
    "wof:placetype":"venue"
},
  "geometry": {"coordinates":[-4.148039,50.366928],"type":"Point"}
}