{
  "type": "Feature",
  "properties": {
    "addr:full":"18 Royal Terrace Southend-on-sea Essex SS1 1DU",
    "addr:housenumber":"18",
    "addr:postcode":"ss1 1du",
    "addr:street":"Royal Terrace",
    "iso:country":"GB",
    "sg:address":"18 Royal Terrace",
    "sg:city":"Southend-on-sea",
    "sg:classifiers":[
        {
            "category":"Travel",
            "subcategory":"Hotels & Motels",
            "type":"Entertainment"
        }
    ],
    "sg:phone":"+44 1702 340747",
    "sg:postcode":"SS1 1DU",
    "sg:province":"Essex",
    "wof:name":"Regency Hotel & Apartments",
    "wof:placetype":"venue"
},
  "geometry": {"coordinates":[0.712292,51.534145],"type":"Point"}
}