{
  "type": "Feature",
  "properties": {
    "iso:country":"GB",
    "sg:address":"Teeside Combined Court Centre, Russell Street",
    "sg:city":"Middlesbrough",
    "sg:classifiers":[
        {
            "category":"Government",
            "subcategory":"Court House",
            "type":"Public Place"
        }
    ],
    "sg:phone":"+44 1642 340001",
    "sg:postcode":"TS1 2AE",
    "sg:province":"North Yorkshire",
    "wof:name":"Probate Registry",
    "wof:placetype":"venue"
},
  "geometry": {"coordinates":[-1.2283940315,54.5747833252],"type":"Point"}
}