{
  "type": "Feature",
  "properties": {
    "addr:full":"1613 Great Western Road Glasgow Glasgow City G13 1LT",
    "addr:housenumber":"1613",
    "addr:postcode":"glasgow;g13 1lt",
    "addr:street":"Great Western Road",
    "iso:country":"GB",
    "sg:address":"1613 Great Western Road",
    "sg:city":"Glasgow",
    "sg:classifiers":[
        {
            "category":"Shopping",
            "subcategory":"Florist",
            "type":"Retail Goods"
        }
    ],
    "sg:phone":"+44 141 959 2702",
    "sg:postcode":"G13 1LT",
    "sg:province":"Glasgow City",
    "wof:name":"Macdonald & Murdoch",
    "wof:placetype":"venue"
},
  "geometry": {"coordinates":[-4.3243360519,55.8895721436],"type":"Point"}
}