{
  "type": "Feature",
  "properties": {
    "iso:country":"GB",
    "sg:address":"High Street",
    "sg:city":"Llanidloes",
    "sg:classifiers":[
        {
            "category":"Bars & Pubs",
            "type":"Food & Drink"
        }
    ],
    "sg:phone":"+44 1686 412381",
    "sg:postcode":"SY18 6BY",
    "sg:province":"Powys",
    "sg:tags":[
        "pubs",
        "inn"
    ],
    "wof:name":"Angel Hotel",
    "wof:placetype":"venue"
},
  "geometry": {"coordinates":[-3.538188,52.447826],"type":"Point"}
}