{
  "type": "Feature",
  "properties": {
    "iso:country":"GB",
    "sg:address":"24 Post Office Walk",
    "sg:city":"Harlow",
    "sg:classifiers":[
        {
            "category":"Health Services",
            "subcategory":"Doctor",
            "type":"Services"
        }
    ],
    "sg:phone":"+44 1279 426888",
    "sg:postcode":"CM20 1BB",
    "sg:province":"Essex",
    "sg:tags":[
        "practitioners"
    ],
    "wof:name":"Tim-on Chinese Herbal Centre",
    "wof:placetype":"venue"
},
  "geometry": {"coordinates":[0.09443,51.771568],"type":"Point"}
}