{
  "type": "Feature",
  "properties": {
    "addr:full":"17 Jansons Road London Greater London N15 4JU",
    "addr:housenumber":"17",
    "addr:postcode":"n15 4ju",
    "addr:street":"Jansons Road",
    "iso:country":"GB",
    "sg:address":"17 Jansons Road",
    "sg:city":"London",
    "sg:classifiers":[
        {
            "category":"Retail",
            "subcategory":"Auto Repair",
            "type":"Services"
        }
    ],
    "sg:postcode":"N15 4JU",
    "sg:province":"Greater London",
    "sg:tags":[
        "modification",
        "garage",
        "related"
    ],
    "wof:name":"CLYDE GARAGE",
    "wof:placetype":"venue"
},
  "geometry": {"coordinates":[-0.0771510005,51.588508606],"type":"Point"}
}