{
  "type": "Feature",
  "properties": {
    "addr:full":"751-753 Ecclesall Road Sheffield Derbyshire S11 8TH",
    "addr:housenumber":"751-753",
    "addr:postcode":"s11 8th",
    "addr:street":"Ecclesall Road",
    "iso:country":"GB",
    "sg:address":"751-753 Ecclesall Road",
    "sg:city":"Sheffield",
    "sg:classifiers":[
        {
            "category":"Organizations",
            "subcategory":"Non-profit Organization",
            "type":"Services"
        }
    ],
    "sg:postcode":"S11 8TH",
    "sg:province":"Derbyshire",
    "sg:tags":[
        "organisation",
        "voluntary",
        "charity"
    ],
    "wof:name":"Sheffield & District Association for the Disabled",
    "wof:placetype":"venue"
},
  "geometry": {"coordinates":[-1.5064009428,53.366355896],"type":"Point"}
}