{
  "type": "Feature",
  "properties": {
    "iso:country":"GB",
    "sg:address":"825 Wimborne Road",
    "sg:city":"Bournemouth",
    "sg:classifiers":[
        {
            "category":"Shopping",
            "subcategory":"Florist",
            "type":"Retail Goods"
        }
    ],
    "sg:phone":"+44 1202 532664",
    "sg:postcode":"BH9 2BE",
    "sg:province":"Dorset",
    "wof:name":"Forever Green Florists",
    "wof:placetype":"venue"
},
  "geometry": {"coordinates":[-1.8762049675,50.752117157],"type":"Point"}
}