{
  "type": "Feature",
  "properties": {
    "iso:country":"GB",
    "sg:address":"Unit 43, Nursling Industrial Estate, Majestic Road",
    "sg:city":"Southampton",
    "sg:classifiers":[
        {
            "category":"Professional",
            "subcategory":"Accounting & Tax Preparation",
            "type":"Services"
        }
    ],
    "sg:phone":"+44 23 8073 9333",
    "sg:postcode":"SO16 0AF",
    "sg:province":"Hampshire",
    "sg:tags":[
        "payroll"
    ],
    "wof:name":"T W Metals Ltd.",
    "wof:placetype":"venue"
},
  "geometry": {"coordinates":[-1.47705,50.9403],"type":"Point"}
}