{
  "type": "Feature",
  "properties": {
    "addr:full":"Shore Acre Braunton Devon EX33 1LD",
    "addr:postcode":"ex33 1ld",
    "addr:street":"Shore",
    "iso:country":"GB",
    "sg:address":"Shore Acre",
    "sg:city":"Braunton",
    "sg:classifiers":[
        {
            "category":"Building & Trades",
            "subcategory":"Construction",
            "type":"Services"
        }
    ],
    "sg:phone":"+44 1271 890255",
    "sg:postcode":"EX33 1LD",
    "sg:province":"Devon",
    "sg:tags":[
        "builder"
    ],
    "wof:name":"A W Garness",
    "wof:placetype":"venue"
},
  "geometry": {"coordinates":[-4.161649,51.109818],"type":"Point"}
}