{
  "type": "Feature",
  "properties": {
    "addr:full":"18a Netherhall Gdns London Greater London NW3 5TH",
    "addr:housenumber":"18a",
    "addr:postcode":"nw3 5th",
    "addr:street":"Netherhall Gdns",
    "iso:country":"GB",
    "sg:address":"18a Netherhall Gdns",
    "sg:city":"London",
    "sg:classifiers":[
        {
            "category":"Real Estate",
            "subcategory":"Architect",
            "type":"Services"
        }
    ],
    "sg:phone":"+44 20 7794 1800",
    "sg:postcode":"NW3 5TH",
    "sg:province":"Greater London",
    "wof:name":"Castanon Rickman Ltd",
    "wof:placetype":"venue"
},
  "geometry": {"coordinates":[-0.178946,51.549732],"type":"Point"}
}