{
  "type": "Feature",
  "properties": {
    "addr:full":"65 Winner Street Paignton Devon TQ3 3BW",
    "addr:housenumber":"65",
    "addr:postcode":"tq3 3bw",
    "addr:street":"Winner Street",
    "iso:country":"GB",
    "sg:address":"65 Winner Street",
    "sg:city":"Paignton",
    "sg:classifiers":[
        {
            "category":"Fast Food",
            "type":"Food & Drink"
        }
    ],
    "sg:phone":"+44 1803 553805",
    "sg:postcode":"TQ3 3BW",
    "sg:province":"Devon",
    "sg:tags":[
        "away",
        "take"
    ],
    "wof:name":"Kings Chinese Takeaway",
    "wof:placetype":"venue"
},
  "geometry": {"coordinates":[-3.571876,50.434505],"type":"Point"}
}