{
  "type": "Feature",
  "properties": {
    "addr:full":"Ark Veterinary Centre, Glasgow Road Lockerbie Dumfries and Galloway DG11 2SE",
    "addr:postcode":"dg11 2se",
    "addr:street":"Glasgow Road",
    "iso:country":"GB",
    "sg:address":"Ark Veterinary Centre, Glasgow Road",
    "sg:city":"Lockerbie",
    "sg:classifiers":[
        {
            "category":"Retail",
            "subcategory":"Veterinary Services",
            "type":"Services"
        }
    ],
    "sg:postcode":"DG11 2SE",
    "sg:province":"Dumfries and Galloway",
    "sg:tags":[
        "surgeon"
    ],
    "wof:name":"Andrew Miller & Partners",
    "wof:placetype":"venue"
},
  "geometry": {"coordinates":[-3.3545689583,55.1217765808],"type":"Point"}
}