{
  "type": "Feature",
  "properties": {
    "iso:country":"GB",
    "sg:address":"Sanders House, 153 London Road",
    "sg:city":"Sittingbourne",
    "sg:classifiers":[
        {
            "category":"Organizations",
            "subcategory":"Non-profit Organization",
            "type":"Services"
        }
    ],
    "sg:postcode":"ME10 1PA",
    "sg:province":"Kent",
    "sg:tags":[
        "organisation",
        "voluntary",
        "charity"
    ],
    "wof:name":"Swale Mediation Service",
    "wof:placetype":"venue"
},
  "geometry": {"coordinates":[0.716573,51.3431587219],"type":"Point"}
}