{
  "type": "Feature",
  "properties": {
    "iso:country":"GB",
    "sg:address":"36 The Green",
    "sg:city":"Stoke On Trent",
    "sg:classifiers":[
        {
            "category":"Food & Beverages",
            "subcategory":"Liquor & Beverages",
            "type":"Retail Goods"
        }
    ],
    "sg:phone":"+44 1538 752266",
    "sg:postcode":"ST10 1PH",
    "sg:province":"Staffordshire",
    "sg:tags":[
        "beer",
        "spirit",
        "wines"
    ],
    "wof:name":"OFF On The Green",
    "wof:placetype":"venue"
},
  "geometry": {"coordinates":[-2.002332,52.983952],"type":"Point"}
}