{
  "type": "Feature",
  "properties": {
    "iso:country":"GB",
    "sg:address":"135 Farm Road",
    "sg:city":"Edgware",
    "sg:classifiers":[
        {
            "category":"Education",
            "subcategory":"School",
            "type":"Public Place"
        }
    ],
    "sg:postcode":"HA8 9LR",
    "sg:province":"Greater London",
    "sg:tags":[
        "private",
        "tuition"
    ],
    "wof:name":"A & B Maths & Computing",
    "wof:placetype":"venue"
},
  "geometry": {"coordinates":[-0.27019,51.613396],"type":"Point"}
}