{
  "type": "Feature",
  "properties": {
    "addr:full":"47 Woodside Avenue London Greater London N12 8TT",
    "addr:housenumber":"47",
    "addr:postcode":"n12 8tt",
    "addr:street":"Woodside Avenue",
    "iso:country":"GB",
    "sg:address":"47 Woodside Avenue",
    "sg:city":"London",
    "sg:classifiers":[
        {
            "category":"Health Services",
            "subcategory":"Hospice",
            "type":"Services"
        }
    ],
    "sg:phone":"+44 20 8343 8841",
    "sg:postcode":"N12 8TT",
    "sg:province":"Greater London",
    "wof:name":"North London Hospice",
    "wof:placetype":"venue"
},
  "geometry": {"coordinates":[-0.1801960021,51.6221656799],"type":"Point"}
}