{
  "type": "Feature",
  "properties": {
    "addr:full":"60 John Street Dunoon Argyll and Bute PA23 8BJ",
    "addr:housenumber":"60",
    "addr:postcode":"pa23 8bj",
    "addr:street":"John Street",
    "iso:country":"GB",
    "sg:address":"60 John Street",
    "sg:city":"Dunoon",
    "sg:classifiers":[
        {
            "category":"Shopping",
            "subcategory":"Thrift Store",
            "type":"Retail Goods"
        }
    ],
    "sg:phone":"+44 1369 701314",
    "sg:postcode":"PA23 8BJ",
    "sg:province":"Argyll and Bute",
    "sg:tags":[
        "shop",
        "charity"
    ],
    "wof:name":"British Red Cross Shop",
    "wof:placetype":"venue"
},
  "geometry": {"coordinates":[-4.927063942,55.9514656067],"type":"Point"}
}