{
  "type": "Feature",
  "properties": {
    "iso:country":"GB",
    "sg:address":"73 Aston Hall Rd",
    "sg:city":"Birmingham",
    "sg:classifiers":[
        {
            "category":"Manufacturing",
            "subcategory":"Metals",
            "type":"Manufacturing & Wholesale Goods"
        }
    ],
    "sg:postcode":"B6 7LP",
    "sg:province":"West Midlands",
    "sg:tags":[
        "heat",
        "-",
        "treatment"
    ],
    "wof:name":"Kearns,Michael,",
    "wof:placetype":"venue"
},
  "geometry": {"coordinates":[-1.872733,52.506241],"type":"Point"}
}