{
  "type": "Feature",
  "properties": {
    "addr:full":"92 Coleshill Road, Chapel End Nuneaton Leicestershire CV10 0PH",
    "addr:housenumber":"92",
    "addr:postcode":"cv10 0ph",
    "addr:street":"Coleshill Road;End",
    "iso:country":"GB",
    "sg:address":"92 Coleshill Road, Chapel End",
    "sg:city":"Nuneaton",
    "sg:classifiers":[
        {
            "category":"Travel",
            "subcategory":"Hotels & Motels",
            "type":"Entertainment"
        }
    ],
    "sg:postcode":"CV10 0PH",
    "sg:province":"Leicestershire",
    "sg:tags":[
        "house",
        "guest"
    ],
    "wof:name":"A Triple Lodge",
    "wof:placetype":"venue"
},
  "geometry": {"coordinates":[-1.535658,52.538452],"type":"Point"}
}