{
  "type": "Feature",
  "properties": {
    "addr:full":"50 Fairway Ave, Tilehurst Reading Berkshire RG30 4QA",
    "addr:housenumber":"50",
    "addr:postcode":"rg30 4qa",
    "addr:street":"Fairway Ave",
    "iso:country":"GB",
    "sg:address":"50 Fairway Ave, Tilehurst",
    "sg:city":"Reading",
    "sg:classifiers":[
        {
            "category":"Retail",
            "subcategory":"Auto Repair",
            "type":"Services"
        }
    ],
    "sg:postcode":"RG30 4QA",
    "sg:province":"Berkshire",
    "sg:tags":[
        "modification",
        "garage"
    ],
    "wof:name":"O'Dwyer,Richard,",
    "wof:placetype":"venue"
},
  "geometry": {"coordinates":[-1.038103,51.451054],"type":"Point"}
}