{
  "type": "Feature",
  "properties": {
    "iso:country":"GB",
    "sg:address":"Answerphone Service Only, Keeley House, 20-22 Keeley Road",
    "sg:city":"Croydon",
    "sg:classifiers":[
        {
            "category":"Real Estate",
            "subcategory":"Real Estate Agent",
            "type":"Services"
        }
    ],
    "sg:phone":"+44 20 8680 5679",
    "sg:postcode":"CR0 1TE",
    "sg:province":"Surrey",
    "wof:name":"Orbital Property Management Services",
    "wof:placetype":"venue"
},
  "geometry": {"coordinates":[-0.1026690006,51.3753013611],"type":"Point"}
}