{
  "type": "Feature",
  "properties": {
    "addr:full":"Lanark Road, Crossford Carluke South Lanarkshire ML8 5QQ",
    "addr:postcode":"ml8 5qq",
    "addr:street":"Lanark Road",
    "iso:country":"GB",
    "sg:address":"Lanark Road, Crossford",
    "sg:city":"Carluke",
    "sg:classifiers":[
        {
            "category":"Home & Garden",
            "subcategory":"Garden Supply",
            "type":"Retail Goods"
        }
    ],
    "sg:phone":"+44 1555 860623",
    "sg:postcode":"ML8 5QQ",
    "sg:province":"South Lanarkshire",
    "sg:tags":[
        "nursery",
        "centre"
    ],
    "wof:name":"Silverbirch Garden Centre (Crossford) Ltd.",
    "wof:placetype":"venue"
},
  "geometry": {"coordinates":[-3.832496,55.719448],"type":"Point"}
}