{
  "type": "Feature",
  "properties": {
    "addr:full":"16 Court Street, Moretonhampstead Newton Abbot Devon TQ13 8LG",
    "addr:housenumber":"16",
    "addr:postcode":"tq13 8lg",
    "addr:street":"Court Street",
    "iso:country":"GB",
    "sg:address":"16 Court Street, Moretonhampstead",
    "sg:city":"Newton Abbot",
    "sg:classifiers":[
        {
            "category":"Bars & Pubs",
            "type":"Food & Drink"
        }
    ],
    "sg:phone":"+44 1647 440266",
    "sg:postcode":"TQ13 8LG",
    "sg:province":"Devon",
    "sg:tags":[
        "pubs",
        "inn"
    ],
    "wof:name":"Plymouth Inn",
    "wof:placetype":"venue"
},
  "geometry": {"coordinates":[-3.7667980194,50.6606216431],"type":"Point"}
}