{
  "type": "Feature",
  "properties": {
    "iso:country":"GB",
    "sg:address":"The Cowshed, Strelley Hall, Main St, Strelley Village",
    "sg:city":"Nottingham",
    "sg:classifiers":[
        {
            "category":"Professional",
            "subcategory":"Computer Services",
            "type":"Services"
        }
    ],
    "sg:phone":"+44 115 942 6962",
    "sg:postcode":"NG8 6PE",
    "sg:province":"Nottinghamshire",
    "sg:tags":[
        "system",
        "software"
    ],
    "wof:name":"Charybdis Ltd",
    "wof:placetype":"venue"
},
  "geometry": {"coordinates":[-1.2475090027,52.9737358093],"type":"Point"}
}