{
  "type": "Feature",
  "properties": {
    "iso:country":"GB",
    "sg:address":"31 Geneva Drive, Westlands",
    "sg:city":"Newcastle",
    "sg:classifiers":[
        {
            "category":"Professional",
            "type":"Services"
        }
    ],
    "sg:phone":"+44 1782 617844",
    "sg:postcode":"ST5 2QQ",
    "sg:province":"Staffordshire",
    "sg:tags":[
        "caterer"
    ],
    "wof:name":"Point-to-Point Contracts Ltd.",
    "wof:placetype":"venue"
},
  "geometry": {"coordinates":[-2.2498989105,52.9998168945],"type":"Point"}
}