{
  "type": "Feature",
  "properties": {
    "iso:country":"GB",
    "sg:address":"128 Mepham Rd",
    "sg:city":"Bedford",
    "sg:classifiers":[
        {
            "category":"Health Services",
            "subcategory":"Dentist",
            "type":"Services"
        }
    ],
    "sg:phone":"+44 1234 766438",
    "sg:postcode":"MK43 9EW",
    "sg:province":"Bedfordshire",
    "sg:tags":[
        "technician",
        "dental"
    ],
    "wof:name":"Bedford Square Dental Laboratory",
    "wof:placetype":"venue"
},
  "geometry": {"coordinates":[-0.5304639935,52.1013870239],"type":"Point"}
}