{
  "type": "Feature",
  "properties": {
    "addr:full":"10 Hall Road, Hacconby Bourne Lincolnshire PE10 0UY",
    "addr:housenumber":"10",
    "addr:postcode":"pe10 0uy",
    "addr:street":"Hall Road Hacconby Bourne",
    "iso:country":"GB",
    "sg:address":"10 Hall Road, Hacconby",
    "sg:city":"Bourne",
    "sg:classifiers":[
        {
            "category":"Professional",
            "subcategory":"Engineering",
            "type":"Services"
        }
    ],
    "sg:postcode":"PE10 0UY",
    "sg:province":"Lincolnshire",
    "sg:tags":[
        "contractor",
        "electrical",
        "engineer"
    ],
    "wof:name":"Coopers Engineering Services",
    "wof:placetype":"venue"
},
  "geometry": {"coordinates":[-0.3693110049,52.8118629456],"type":"Point"}
}