{
  "type": "Feature",
  "properties": {
    "iso:country":"GB",
    "sg:address":"8 Kestrel Green",
    "sg:city":"Hatfield",
    "sg:classifiers":[
        {
            "category":"Real Estate",
            "subcategory":"Architect",
            "type":"Services"
        }
    ],
    "sg:postcode":"AL10 8QJ",
    "sg:province":"Hertfordshire",
    "wof:name":"Neil Goodman Ltd",
    "wof:placetype":"venue"
},
  "geometry": {"coordinates":[-0.2286539972,51.753276825],"type":"Point"}
}