{
  "type": "Feature",
  "properties": {
    "addr:full":"73 Moores Road Leicester Leicestershire LE4 6QR",
    "addr:housenumber":"73",
    "addr:postcode":"le4 6qr",
    "addr:street":"Moores Road",
    "iso:country":"GB",
    "sg:address":"73 Moores Road",
    "sg:city":"Leicester",
    "sg:classifiers":[
        {
            "category":"Shopping",
            "subcategory":"Clothing, Apparel, & Fashions",
            "type":"Retail Goods"
        }
    ],
    "sg:postcode":"LE4 6QR",
    "sg:province":"Leicestershire",
    "sg:tags":[
        "clothing",
        "fabric"
    ],
    "wof:name":"Khera Fashions Ltd",
    "wof:placetype":"venue"
},
  "geometry": {"coordinates":[-1.115558,52.655701],"type":"Point"}
}