{
  "type": "Feature",
  "properties": {
    "iso:country":"GB",
    "sg:address":"Orchard Street, Kempston",
    "sg:city":"Bedford",
    "sg:classifiers":[
        {
            "category":"Education",
            "subcategory":"School",
            "type":"Public Place"
        }
    ],
    "sg:phone":"+44 1234 400111",
    "sg:postcode":"MK42 7PS",
    "sg:province":"Bedfordshire",
    "sg:tags":[
        "local",
        "authority"
    ],
    "wof:name":"Daubeney Middle School",
    "wof:placetype":"venue"
},
  "geometry": {"coordinates":[-0.505067,52.114841],"type":"Point"}
}