{
  "type": "Feature",
  "properties": {
    "iso:country":"GB",
    "sg:address":"22a Alum Chine Rd",
    "sg:city":"Bournemouth",
    "sg:classifiers":[
        {
            "category":"Shopping",
            "subcategory":"Computers & Home Electronics",
            "type":"Retail Goods"
        }
    ],
    "sg:postcode":"BH4 8DX",
    "sg:province":"Dorset",
    "sg:tags":[
        "machine",
        "telex"
    ],
    "wof:name":"T G I Data Comms Ltd",
    "wof:placetype":"venue"
},
  "geometry": {"coordinates":[-1.902504,50.720596],"type":"Point"}
}