{
  "type": "Feature",
  "properties": {
    "addr:full":"56 Ebrington Street Plymouth Devon PL4 9AF",
    "addr:housenumber":"56",
    "addr:postcode":"pl4 9af",
    "addr:street":"Ebrington Street",
    "iso:country":"GB",
    "sg:address":"56 Ebrington Street",
    "sg:city":"Plymouth",
    "sg:classifiers":[
        {
            "category":"Arts & Performance",
            "subcategory":"Art Gallery",
            "type":"Entertainment"
        }
    ],
    "sg:postcode":"PL4 9AF",
    "sg:province":"Devon",
    "wof:name":"EMPIRE PUBLICATIONS",
    "wof:placetype":"venue"
},
  "geometry": {"coordinates":[-4.1344718933,50.3725242615],"type":"Point"}
}