{
  "type": "Feature",
  "properties": {
    "iso:country":"GB",
    "sg:address":"106-108 Greenheath Business Centre, Three Colts La",
    "sg:city":"London",
    "sg:classifiers":[
        {
            "category":"Shopping",
            "subcategory":"Clothing, Apparel, & Fashions",
            "type":"Retail Goods"
        }
    ],
    "sg:postcode":"E2 6JB",
    "sg:province":"Greater London",
    "sg:tags":[
        "clothing",
        "fabric"
    ],
    "wof:name":"Majif,M,",
    "wof:placetype":"venue"
},
  "geometry": {"coordinates":[-0.05743,51.52515],"type":"Point"}
}