{
  "type": "Feature",
  "properties": {
    "addr:full":"112-120 Brompton Rd Chelsea Greater London SW3 1JJ",
    "addr:housenumber":"112-120",
    "addr:postcode":"sw3 1jj",
    "addr:street":"Brompton Rd",
    "iso:country":"GB",
    "sg:address":"112-120 Brompton Rd",
    "sg:city":"Chelsea",
    "sg:classifiers":[
        {
            "category":"Home & Garden",
            "subcategory":"Home Furnishings",
            "type":"Retail Goods"
        }
    ],
    "sg:phone":"+44 20 7584 3344",
    "sg:postcode":"SW3 1JJ",
    "sg:province":"Greater London",
    "sg:tags":[
        "wall",
        "wallpaper",
        "covering"
    ],
    "wof:name":"Arthur Sanderson & Son",
    "wof:placetype":"venue"
},
  "geometry": {"coordinates":[-0.164454,51.499268],"type":"Point"}
}