{
  "type": "Feature",
  "properties": {
    "addr:full":"203 Brook Street, Broughty Ferry Dundee Angus DD5 2AG",
    "addr:housenumber":"203",
    "addr:postcode":"dd5 2ag",
    "addr:street":"Brook Street",
    "iso:country":"GB",
    "sg:address":"203 Brook Street, Broughty Ferry",
    "sg:city":"Dundee",
    "sg:classifiers":[
        {
            "category":"Shopping",
            "subcategory":"Shoes",
            "type":"Retail Goods"
        }
    ],
    "sg:phone":"+44 1382 477586",
    "sg:postcode":"DD5 2AG",
    "sg:province":"Angus",
    "sg:tags":[
        "shop",
        "retailer",
        "footwear"
    ],
    "sg:website":"http://www.deshoes.co.uk",
    "wof:name":"D E Shoes",
    "wof:placetype":"venue"
},
  "geometry": {"coordinates":[-2.875485,56.467522],"type":"Point"}
}