{
  "type": "Feature",
  "properties": {
    "addr:full":"343 Grays Inn Rd Bloomsbury Greater London WC1X 8PX",
    "addr:housenumber":"343",
    "addr:postcode":"wc1x 8px",
    "addr:street":"Grays Inn Rd",
    "iso:country":"GB",
    "sg:address":"343 Grays Inn Rd",
    "sg:city":"Bloomsbury",
    "sg:classifiers":[
        {
            "category":"Fast Food",
            "type":"Food & Drink"
        }
    ],
    "sg:phone":"+44 20 7837 5984",
    "sg:postcode":"WC1X 8PX",
    "sg:province":"Greater London",
    "sg:tags":[
        "away",
        "take"
    ],
    "wof:name":"KFC",
    "wof:placetype":"venue"
},
  "geometry": {"coordinates":[-0.122222,51.530396],"type":"Point"}
}