{
  "type": "Feature",
  "properties": {
    "iso:country":"GB",
    "sg:address":"11 Rivington Hall Clo",
    "sg:city":"Bury",
    "sg:classifiers":[
        {
            "category":"Education",
            "subcategory":"Music School",
            "type":"Public Place"
        }
    ],
    "sg:phone":"+44 1706 825666",
    "sg:postcode":"BL0 9YL",
    "sg:province":"Lancashire",
    "sg:tags":[
        "conservatory"
    ],
    "wof:name":"Elite Conservatories",
    "wof:placetype":"venue"
},
  "geometry": {"coordinates":[-2.317809,53.639561],"type":"Point"}
}