{
  "type": "Feature",
  "properties": {
    "addr:full":"213 Arbury Road, Stockingford Nuneaton Leicestershire CV10 7NH",
    "addr:housenumber":"213",
    "addr:postcode":"cv10 7nh",
    "addr:street":"Arbury Road",
    "iso:country":"GB",
    "sg:address":"213 Arbury Road, Stockingford",
    "sg:city":"Nuneaton",
    "sg:classifiers":[
        {
            "category":"Organizations",
            "subcategory":"Membership Organization",
            "type":"Services"
        }
    ],
    "sg:phone":"+44 24 7638 2910",
    "sg:postcode":"CV10 7NH",
    "sg:province":"Leicestershire",
    "sg:tags":[
        "club"
    ],
    "wof:name":"Stockingford Conservative Club",
    "wof:placetype":"venue"
},
  "geometry": {"coordinates":[-1.503798,52.515598],"type":"Point"}
}