{
  "type": "Feature",
  "properties": {
    "addr:full":"Springfield Road, Upper Biobohall Elgin Moray IV30 6YA",
    "addr:postcode":"iv30 6ya",
    "addr:street":"Springfield Road Upper Biobohall Elgin",
    "iso:country":"GB",
    "sg:address":"Springfield Road, Upper Biobohall",
    "sg:city":"Elgin",
    "sg:classifiers":[
        {
            "category":"Fast Food",
            "type":"Food & Drink"
        }
    ],
    "sg:phone":"+44 1343 551073",
    "sg:postcode":"IV30 6YA",
    "sg:province":"Moray",
    "sg:tags":[
        "away",
        "take"
    ],
    "wof:name":"Linda's Take Away",
    "wof:placetype":"venue"
},
  "geometry": {"coordinates":[-3.308179,57.637985],"type":"Point"}
}