{
  "type": "Feature",
  "properties": {
    "iso:country":"GB",
    "sg:address":"Sleaford Road, Bracebridge Heath",
    "sg:city":"Lincoln",
    "sg:classifiers":[
        {
            "category":"Freight",
            "type":"Transportation"
        }
    ],
    "sg:phone":"+44 1522 520251",
    "sg:postcode":"LN4 2NL",
    "sg:province":"Lincolnshire",
    "sg:tags":[
        "haulage",
        "transport",
        "road"
    ],
    "wof:name":"E H Lee Ltd.",
    "wof:placetype":"venue"
},
  "geometry": {"coordinates":[-0.5340099931,53.1955795288],"type":"Point"}
}