{
  "type": "Feature",
  "properties": {
    "addr:full":"The Old Bakery, Kiln Lane Swindon Wiltshire SN2 2NP",
    "addr:postcode":"sn2 2np",
    "addr:street":"Kiln Lane",
    "iso:country":"GB",
    "sg:address":"The Old Bakery, Kiln Lane",
    "sg:city":"Swindon",
    "sg:classifiers":[
        {
            "category":"Manufacturing",
            "subcategory":"Petroleum Products",
            "type":"Manufacturing & Wholesale Goods"
        }
    ],
    "sg:phone":"+44 1793 541154",
    "sg:postcode":"SN2 2NP",
    "sg:province":"Wiltshire",
    "sg:tags":[
        "double",
        "glazing"
    ],
    "wof:name":"Direct Window Supplies Ltd.",
    "wof:placetype":"venue"
},
  "geometry": {"coordinates":[-1.8031,51.573231],"type":"Point"}
}