{
  "type": "Feature",
  "properties": {
    "addr:full":"111 Hobs Moat Road Solihull West Midlands B92 8JN",
    "addr:housenumber":"111",
    "addr:postcode":"b92 8jn",
    "addr:street":"Hobs Moat Road",
    "iso:country":"GB",
    "sg:address":"111 Hobs Moat Road",
    "sg:city":"Solihull",
    "sg:classifiers":[
        {
            "category":"Food & Beverages",
            "subcategory":"Fruits & Vegetables",
            "type":"Retail Goods"
        }
    ],
    "sg:phone":"+44 121 742 3175",
    "sg:postcode":"B92 8JN",
    "sg:province":"West Midlands",
    "sg:tags":[
        "greengrocer"
    ],
    "wof:name":"Ripe 'N' Ready",
    "wof:placetype":"venue"
},
  "geometry": {"coordinates":[-1.785007,52.44479],"type":"Point"}
}