{
  "type": "Feature",
  "properties": {
    "addr:full":"18 Meyricks, Coedeva Cwmbran Monmouthshire NP44 6TU",
    "addr:housenumber":"18",
    "addr:postcode":"np44 6tu",
    "addr:street":"Meyricks Coedeva",
    "iso:country":"GB",
    "sg:address":"18 Meyricks, Coedeva",
    "sg:city":"Cwmbran",
    "sg:classifiers":[
        {
            "category":"Social Services",
            "subcategory":"Adult Care",
            "type":"Services"
        }
    ],
    "sg:phone":"+44 1633 875235",
    "sg:postcode":"NP44 6TU",
    "sg:province":"Monmouthshire",
    "sg:tags":[
        "domestic",
        "cleaning"
    ],
    "wof:name":"G How Clean",
    "wof:placetype":"venue"
},
  "geometry": {"coordinates":[-3.0557689667,51.6413803101],"type":"Point"}
}