{
  "type": "Feature",
  "properties": {
    "addr:full":"4 Town Lane, Benington Stevenage Hertfordshire SG2 7LA",
    "addr:housenumber":"4",
    "addr:postcode":"sg2 7la",
    "addr:street":"Town Lane",
    "iso:country":"GB",
    "sg:address":"4 Town Lane, Benington",
    "sg:city":"Stevenage",
    "sg:classifiers":[
        {
            "category":"Bars & Pubs",
            "type":"Food & Drink"
        }
    ],
    "sg:postcode":"SG2 7LA",
    "sg:province":"Hertfordshire",
    "sg:tags":[
        "pubs",
        "inn"
    ],
    "wof:name":"B & D Roberts",
    "wof:placetype":"venue"
},
  "geometry": {"coordinates":[-0.113504,51.8956375122],"type":"Point"}
}