{
  "type": "Feature",
  "properties": {
    "iso:country":"GB",
    "sg:address":"13 Stratford Place",
    "sg:city":"London",
    "sg:classifiers":[
        {
            "category":"Banks & Credit Unions",
            "subcategory":"Financial Services",
            "type":"Services"
        }
    ],
    "sg:phone":"+44 20 7495 4999",
    "sg:postcode":"W1C 1BD",
    "sg:province":"Greater London",
    "sg:tags":[
        "consultant"
    ],
    "wof:name":"Brompton Financial Services Plc",
    "wof:placetype":"venue"
},
  "geometry": {"coordinates":[-0.149519,51.514992],"type":"Point"}
}