{
  "type": "Feature",
  "properties": {
    "addr:full":"17 Bartholomew Street Newbury Berkshire RG14 5LY",
    "addr:housenumber":"17",
    "addr:postcode":"rg14 5ly",
    "addr:street":"Bartholomew Street",
    "iso:country":"GB",
    "sg:address":"17 Bartholomew Street",
    "sg:city":"Newbury",
    "sg:classifiers":[
        {
            "category":"Banks & Credit Unions",
            "subcategory":"Financial Services",
            "type":"Services"
        }
    ],
    "sg:phone":"+44 1635 555700",
    "sg:postcode":"RG14 5LY",
    "sg:province":"Berkshire",
    "sg:tags":[
        "building",
        "society"
    ],
    "sg:website":"http://www.newbury.co.uk",
    "wof:name":"Newbury Building Society",
    "wof:placetype":"venue"
},
  "geometry": {"coordinates":[-1.3248480558,51.4004096985],"type":"Point"}
}