{
  "type": "Feature",
  "properties": {
    "addr:full":"22 Orwell Road Clacton-on-sea Essex CO15 1PP",
    "addr:housenumber":"22",
    "addr:postcode":"co15 1pp",
    "addr:street":"Orwell Road",
    "iso:country":"GB",
    "sg:address":"22 Orwell Road",
    "sg:city":"Clacton-on-sea",
    "sg:classifiers":[
        {
            "category":"Retail",
            "subcategory":"Laundry & Dry Cleaning",
            "type":"Services"
        }
    ],
    "sg:postcode":"CO15 1PP",
    "sg:province":"Essex",
    "sg:tags":[
        "launderette",
        "alteration"
    ],
    "wof:name":"Washin Laundry Service",
    "wof:placetype":"venue"
},
  "geometry": {"coordinates":[1.1554820538,51.7891387939],"type":"Point"}
}