{
  "type": "Feature",
  "properties": {
    "addr:full":"Edward House Manchester Greater Manchester M3 7BE",
    "addr:postcode":"m3 7be",
    "addr:street":"Manchester",
    "iso:country":"GB",
    "sg:address":"Edward House",
    "sg:city":"Manchester",
    "sg:classifiers":[
        {
            "category":"Real Estate",
            "subcategory":"Surveying",
            "type":"Services"
        }
    ],
    "sg:phone":"+44 161 819 5252",
    "sg:postcode":"M3 7BE",
    "sg:province":"Greater Manchester",
    "sg:tags":[
        "surveyor",
        "valuer",
        "quantity"
    ],
    "wof:name":"STEPHEN DAVIES ASSOCIATES",
    "wof:placetype":"venue"
},
  "geometry": {"coordinates":[-2.248809,53.479622],"type":"Point"}
}