{
  "type": "Feature",
  "properties": {
    "iso:country":"GB",
    "sg:address":"Widemouth Bay",
    "sg:city":"Bude",
    "sg:classifiers":[
        {
            "category":"Travel",
            "subcategory":"Hotels & Motels",
            "type":"Entertainment"
        }
    ],
    "sg:phone":"+44 1288 361207",
    "sg:postcode":"EX23 0DF",
    "sg:province":"Cornwall",
    "wof:name":"Brocksmoor Hotel",
    "wof:placetype":"venue"
},
  "geometry": {"coordinates":[-4.5444779396,50.8283615112],"type":"Point"}
}