{
  "type": "Feature",
  "properties": {
    "iso:country":"GB",
    "sg:address":"15 Tilbrook Drive, Sutton",
    "sg:city":"St Helens",
    "sg:classifiers":[
        {
            "category":"Organizations",
            "subcategory":"Religious Organization",
            "type":"Services"
        }
    ],
    "sg:phone":"+44 1744 811601",
    "sg:postcode":"WA9 3WP",
    "sg:province":"Cheshire",
    "sg:tags":[
        "organisation"
    ],
    "wof:name":"Sisters of the Cross & Passion",
    "wof:placetype":"venue"
},
  "geometry": {"coordinates":[-2.7119309902,53.4316902161],"type":"Point"}
}