{
  "type": "Feature",
  "properties": {
    "addr:full":"115 Northdown Rd, Cliftonville Margate Kent CT9 2QY",
    "addr:housenumber":"115",
    "addr:postcode":"ct9 2qy",
    "addr:street":"Northdown Rd;Margate",
    "iso:country":"GB",
    "sg:address":"115 Northdown Rd, Cliftonville",
    "sg:city":"Margate",
    "sg:classifiers":[
        {
            "category":"Professional",
            "type":"Services"
        }
    ],
    "sg:postcode":"CT9 2QY",
    "sg:province":"Kent",
    "sg:tags":[
        "repair",
        "tech",
        "maintenance"
    ],
    "wof:name":"Logical Computer Systems Ltd",
    "wof:placetype":"venue"
},
  "geometry": {"coordinates":[1.3950959444,51.3884506226],"type":"Point"}
}