{
  "type": "Feature",
  "properties": {
    "addr:full":"135 London Road Waterlooville Hampshire PO7 7SH",
    "addr:housenumber":"135",
    "addr:postcode":"po7 7sh",
    "addr:street":"London Road",
    "iso:country":"GB",
    "sg:address":"135 London Road",
    "sg:city":"Waterlooville",
    "sg:classifiers":[
        {
            "category":"Health Services",
            "subcategory":"Nursing And Care Facility",
            "type":"Services"
        },
        {
            "category":"Social Services",
            "subcategory":"Retirement Home",
            "type":"Services"
        }
    ],
    "sg:phone":"+44 23 9226 1307",
    "sg:postcode":"PO7 7SH",
    "sg:province":"Hampshire",
    "sg:tags":[
        "residential"
    ],
    "wof:name":"Purbeck House",
    "wof:placetype":"venue"
},
  "geometry": {"coordinates":[-1.0285489559,50.8830490112],"type":"Point"}
}