{
  "type": "Feature",
  "properties": {
    "addr:full":"The Old Exchange, West Street Farnham Surrey GU9 7AP",
    "addr:postcode":"gu9 7ap",
    "addr:street":"West Street",
    "iso:country":"GB",
    "sg:address":"The Old Exchange, West Street",
    "sg:city":"Farnham",
    "sg:classifiers":[
        {
            "category":"Real Estate",
            "subcategory":"Developer",
            "type":"Services"
        }
    ],
    "sg:phone":"+44 1252 733622",
    "sg:postcode":"GU9 7AP",
    "sg:province":"Surrey",
    "sg:tags":[
        "property"
    ],
    "wof:name":"Arcadia Ventures Ltd.",
    "wof:placetype":"venue"
},
  "geometry": {"coordinates":[-0.8008369803,51.2143211365],"type":"Point"}
}