{
  "type": "Feature",
  "properties": {
    "addr:full":"Longshore Indstl Pk, Highfield Rd Blackburn Lancashire BB2 3AS",
    "addr:postcode":"bb2 3as",
    "addr:street":"Indstl Pk Highfield Rd",
    "iso:country":"GB",
    "sg:address":"Longshore Indstl Pk, Highfield Rd",
    "sg:city":"Blackburn",
    "sg:classifiers":[
        {
            "category":"Home & Garden",
            "subcategory":"Furniture",
            "type":"Retail Goods"
        }
    ],
    "sg:phone":"+44 1254 686110",
    "sg:postcode":"BB2 3AS",
    "sg:province":"Lancashire",
    "wof:name":"Wilson Wilcox Furnishings Ltd",
    "wof:placetype":"venue"
},
  "geometry": {"coordinates":[-2.4799399376,53.735748291],"type":"Point"}
}