{
  "type": "Feature",
  "properties": {
    "iso:country":"GB",
    "sg:address":"Merlin Studios, Tregwilym Road",
    "sg:city":"Newport",
    "sg:classifiers":[
        {
            "category":"Home & Garden",
            "subcategory":"Home Furnishings",
            "type":"Retail Goods"
        }
    ],
    "sg:phone":"+44 1633 896606",
    "sg:postcode":"NP10 9EJ",
    "sg:province":"Caerphilly",
    "sg:tags":[
        "blind",
        "curtain",
        "fitting"
    ],
    "wof:name":"Carter & Co. Interiors",
    "wof:placetype":"venue"
},
  "geometry": {"coordinates":[-3.05084,51.583729],"type":"Point"}
}