{
  "type": "Feature",
  "properties": {
    "addr:full":"Lowry Building, Harvey Street Stockport Cheshire SK1 1YD",
    "addr:postcode":"sk1 1yd",
    "addr:street":"Harvey Street",
    "iso:country":"GB",
    "sg:address":"Lowry Building, Harvey Street",
    "sg:city":"Stockport",
    "sg:classifiers":[
        {
            "category":"Wholesale",
            "subcategory":"Groceries",
            "type":"Manufacturing & Wholesale Goods"
        }
    ],
    "sg:phone":"+44 161 480 2084",
    "sg:postcode":"SK1 1YD",
    "sg:province":"Cheshire",
    "sg:tags":[
        "food",
        "supplier",
        "drink"
    ],
    "wof:name":"Just Deserts Patisserie",
    "wof:placetype":"venue"
},
  "geometry": {"coordinates":[-2.15565,53.41045],"type":"Point"}
}