{
  "type": "Feature",
  "properties": {
    "addr:full":"Unit 7 Industrial Estate Bala Gwynedd LL23 7NL",
    "addr:housenumber":"unit 7",
    "addr:postcode":"ll23 7nl",
    "addr:street":"Industrial Estate",
    "iso:country":"GB",
    "sg:address":"Unit 7 Industrial Estate",
    "sg:city":"Bala",
    "sg:classifiers":[
        {
            "category":"Professional",
            "subcategory":"Management & Consulting",
            "type":"Services"
        }
    ],
    "sg:phone":"+44 1678 520050",
    "sg:postcode":"LL23 7NL",
    "sg:province":"Gwynedd",
    "sg:tags":[
        "fire",
        "consultant",
        "protection"
    ],
    "wof:name":"Fireshield Cymru Ltd",
    "wof:placetype":"venue"
},
  "geometry": {"coordinates":[-3.5954670906,52.912147522],"type":"Point"}
}