{
  "type": "Feature",
  "properties": {
    "iso:country":"GB",
    "sg:address":"Unit 67 In Shops, Monmouth Square",
    "sg:city":"Cwmbran",
    "sg:classifiers":[
        {
            "category":"Shopping",
            "subcategory":"Photographic Equipment",
            "type":"Retail Goods"
        }
    ],
    "sg:phone":"+44 1633 875577",
    "sg:postcode":"NP44 1PE",
    "sg:province":"Monmouthshire",
    "wof:name":"Q.T. Portraits",
    "wof:placetype":"venue"
},
  "geometry": {"coordinates":[-3.0258638859,51.6574668884],"type":"Point"}
}