{
  "type": "Feature",
  "properties": {
    "addr:full":"Ceolmara Mallaig Highland PH41 4QH",
    "addr:postcode":"ph41 4qh",
    "iso:country":"GB",
    "sg:address":"Ceolmara",
    "sg:city":"Mallaig",
    "sg:classifiers":[
        {
            "category":"Food & Beverages",
            "subcategory":"Meat & Fish",
            "type":"Retail Goods"
        }
    ],
    "sg:phone":"+44 1687 462288",
    "sg:postcode":"PH41 4QH",
    "sg:province":"Highland",
    "sg:tags":[
        "merchant"
    ],
    "wof:name":"Kilkeel Enterprises",
    "wof:placetype":"venue"
},
  "geometry": {"coordinates":[-5.8291192055,57.0058250427],"type":"Point"}
}