{
  "type": "Feature",
  "properties": {
    "addr:full":"Pennllan Smithy, Llanfair Talhaiarn Abergele Conwy LL22 8ST",
    "addr:postcode":"ll22 8st",
    "iso:country":"GB",
    "sg:address":"Pennllan Smithy, Llanfair Talhaiarn",
    "sg:city":"Abergele",
    "sg:classifiers":[
        {
            "category":"Manufacturing",
            "subcategory":"Metals",
            "type":"Manufacturing & Wholesale Goods"
        }
    ],
    "sg:phone":"+44 1745 720204",
    "sg:postcode":"LL22 8ST",
    "sg:province":"Conwy",
    "sg:tags":[
        "steel",
        "fabricator",
        "erectors"
    ],
    "wof:name":"Davies Bros",
    "wof:placetype":"venue"
},
  "geometry": {"coordinates":[-3.5811440945,53.2843551636],"type":"Point"}
}