{
  "type": "Feature",
  "properties": {
    "addr:full":"38 The Calls Leeds West Yorkshire LS2 7EW",
    "addr:housenumber":"38",
    "addr:postcode":"ls2 7ew",
    "addr:street":"The Calls Leeds West",
    "iso:country":"GB",
    "sg:address":"38 The Calls",
    "sg:city":"Leeds",
    "sg:classifiers":[
        {
            "category":"Restaurant",
            "type":"Food & Drink"
        }
    ],
    "sg:phone":"+44 113 245 3870",
    "sg:postcode":"LS2 7EW",
    "sg:province":"West Yorkshire",
    "wof:name":"The Calls Grill",
    "wof:placetype":"venue"
},
  "geometry": {"coordinates":[-1.5382649899,53.7948112488],"type":"Point"}
}