{
  "type": "Feature",
  "properties": {
    "iso:country":"GB",
    "sg:address":"Publicity House, Station Works, Station Road",
    "sg:city":"Cottingham",
    "sg:classifiers":[
        {
            "category":"Professional",
            "subcategory":"Printing & Photocopies",
            "type":"Services"
        }
    ],
    "sg:phone":"+44 1482 842117",
    "sg:postcode":"HU16 4LE",
    "sg:province":"East Riding of Yorkshire",
    "sg:tags":[
        "printer"
    ],
    "wof:name":"Jacee Print & Publicity Ltd.",
    "wof:placetype":"venue"
},
  "geometry": {"coordinates":[-0.415944,53.779877],"type":"Point"}
}