{
  "type": "Feature",
  "properties": {
    "addr:full":"3 Wellington New Road Taunton Somerset TA1 5LU",
    "addr:housenumber":"3",
    "addr:postcode":"ta1 5lu",
    "addr:street":"Wellington New Road",
    "iso:country":"GB",
    "sg:address":"3 Wellington New Road",
    "sg:city":"Taunton",
    "sg:classifiers":[
        {
            "category":"Professional",
            "subcategory":"Advertising",
            "type":"Services"
        },
        {
            "category":"Manufacturing",
            "subcategory":"Signs",
            "type":"Manufacturing & Wholesale Goods"
        }
    ],
    "sg:phone":"+44 1823 336699",
    "sg:postcode":"TA1 5LU",
    "sg:province":"Somerset",
    "sg:tags":[
        "writer",
        "signwriters"
    ],
    "wof:name":"Signal Signs",
    "wof:placetype":"venue"
},
  "geometry": {"coordinates":[-3.1261689663,51.0130805969],"type":"Point"}
}