{
  "type": "Feature",
  "properties": {
    "addr:full":"27 Church Street Falmouth Cornwall TR11 3EQ",
    "addr:housenumber":"27",
    "addr:postcode":"tr11 3eq",
    "addr:street":"Church Street",
    "iso:country":"GB",
    "sg:address":"27 Church Street",
    "sg:city":"Falmouth",
    "sg:classifiers":[
        {
            "category":"Shopping",
            "subcategory":"Comic Books",
            "type":"Retail Goods"
        }
    ],
    "sg:phone":"+44 1326 314073",
    "sg:postcode":"TR11 3EQ",
    "sg:province":"Cornwall",
    "sg:tags":[
        "jeweller"
    ],
    "wof:name":"The Jewellery Workshop",
    "wof:placetype":"venue"
},
  "geometry": {"coordinates":[-5.068305,50.153675],"type":"Point"}
}