{
  "type": "Feature",
  "properties": {
    "iso:country":"GB",
    "sg:address":"Summerville, The Broadway",
    "sg:city":"Woodhall Spa",
    "sg:classifiers":[
        {
            "category":"Communications",
            "type":"Services"
        }
    ],
    "sg:phone":"+44 1526 834543",
    "sg:postcode":"LN10 6ST",
    "sg:province":"Lincolnshire",
    "sg:tags":[
        "telecommunication"
    ],
    "wof:name":"N.R.C Communications",
    "wof:placetype":"venue"
},
  "geometry": {"coordinates":[-0.2128439993,53.1524887085],"type":"Point"}
}