{
  "type": "Feature",
  "properties": {
    "addr:full":"18 New Street Ledbury Gloucestershire HR8 2DX",
    "addr:housenumber":"18",
    "addr:postcode":"hr8 2dx",
    "addr:street":"New Street",
    "iso:country":"GB",
    "sg:address":"18 New Street",
    "sg:city":"Ledbury",
    "sg:classifiers":[
        {
            "category":"Food & Beverages",
            "subcategory":"Fruits & Vegetables",
            "type":"Retail Goods"
        }
    ],
    "sg:phone":"+44 1531 633986",
    "sg:postcode":"HR8 2DX",
    "sg:province":"Gloucestershire",
    "sg:tags":[
        "greengrocer"
    ],
    "wof:name":"Gladwin & James",
    "wof:placetype":"venue"
},
  "geometry": {"coordinates":[-2.4236409664,52.0354995728],"type":"Point"}
}