{
  "type": "Feature",
  "properties": {
    "addr:full":"75a High Street Bedford Bedfordshire MK40 1NE",
    "addr:housenumber":"75a",
    "addr:postcode":"mk40 1ne",
    "addr:street":"High Street",
    "iso:country":"GB",
    "sg:address":"75a High Street",
    "sg:city":"Bedford",
    "sg:classifiers":[
        {
            "category":"Professional",
            "subcategory":"Employment Agencies",
            "type":"Services"
        }
    ],
    "sg:phone":"+44 1234 328446",
    "sg:postcode":"MK40 1NE",
    "sg:province":"Bedfordshire",
    "sg:tags":[
        "consultant"
    ],
    "wof:name":"Bedford Business Services Ltd.",
    "wof:placetype":"venue"
},
  "geometry": {"coordinates":[-0.466477,52.1371],"type":"Point"}
}