{
  "type": "Feature",
  "properties": {
    "iso:country":"GB",
    "sg:address":"460 Corporation Road",
    "sg:city":"Newport",
    "sg:classifiers":[
        {
            "category":"Communications",
            "type":"Services"
        }
    ],
    "sg:phone":"+44 1633 254050",
    "sg:postcode":"NP19 0GN",
    "sg:province":"Newport",
    "sg:tags":[
        "tv",
        "video",
        "radio"
    ],
    "wof:name":"Scan Satellite Systems",
    "wof:placetype":"venue"
},
  "geometry": {"coordinates":[-2.972858,51.581505],"type":"Point"}
}