{
  "type": "Feature",
  "properties": {
    "addr:full":"87 Worple Road Isleworth Greater London TW7 7AS",
    "addr:housenumber":"87",
    "addr:postcode":"tw7 7as",
    "addr:street":"Worple Road",
    "iso:country":"GB",
    "sg:address":"87 Worple Road",
    "sg:city":"Isleworth",
    "sg:classifiers":[
        {
            "category":"Utilities",
            "subcategory":"Refuse",
            "type":"Services"
        }
    ],
    "sg:phone":"+44 20 8979 9940",
    "sg:postcode":"TW7 7AS",
    "sg:province":"Greater London",
    "sg:tags":[
        "disposal",
        "waste",
        "retail"
    ],
    "wof:name":"C Wordsworth Transport Co",
    "wof:placetype":"venue"
},
  "geometry": {"coordinates":[-0.3276380002,51.4650382996],"type":"Point"}
}