{
  "type": "Feature",
  "properties": {
    "iso:country":"GB",
    "sg:address":"Smithfield Square",
    "sg:city":"Dolgellau",
    "sg:classifiers":[
        {
            "category":"Health Services",
            "subcategory":"Nursing And Care Facility",
            "type":"Services"
        },
        {
            "category":"Social Services",
            "subcategory":"Retirement Home",
            "type":"Services"
        }
    ],
    "sg:phone":"+44 1341 423703",
    "sg:postcode":"LL40 1ES",
    "sg:province":"Gwynedd",
    "sg:tags":[
        "residential"
    ],
    "wof:name":"Crossroads The Route To Independence",
    "wof:placetype":"venue"
},
  "geometry": {"coordinates":[-3.885034,52.744324],"type":"Point"}
}