{
  "type": "Feature",
  "properties": {
    "addr:full":"The Health Centre, Park Road, Denmead Waterlooville Hampshire PO7 6NE",
    "addr:postcode":"po7 6ne",
    "addr:street":"Centre Park Road",
    "iso:country":"GB",
    "sg:address":"The Health Centre, Park Road, Denmead",
    "sg:city":"Waterlooville",
    "sg:classifiers":[
        {
            "category":"Health Services",
            "subcategory":"Dentist",
            "type":"Services"
        }
    ],
    "sg:phone":"+44 23 9226 5444",
    "sg:postcode":"PO7 6NE",
    "sg:province":"Hampshire",
    "wof:name":"David Greenaway",
    "wof:placetype":"venue"
},
  "geometry": {"coordinates":[-1.0619159937,50.9017028809],"type":"Point"}
}