{
  "type": "Feature",
  "properties": {
    "addr:full":"54 Bradford Street Walsall West Midlands WS1 3QD",
    "addr:housenumber":"54",
    "addr:postcode":"ws1 3qd",
    "addr:street":"Bradford Street",
    "iso:country":"GB",
    "sg:address":"54 Bradford Street",
    "sg:city":"Walsall",
    "sg:classifiers":[
        {
            "category":"Health Services",
            "subcategory":"Doctor",
            "type":"Services"
        }
    ],
    "sg:phone":"+44 1922 622339",
    "sg:postcode":"WS1 3QD",
    "sg:province":"West Midlands",
    "sg:tags":[
        "practitioners"
    ],
    "wof:name":"Walsall Health Authority",
    "wof:placetype":"venue"
},
  "geometry": {"coordinates":[-1.985165,52.5809783936],"type":"Point"}
}