{
  "type": "Feature",
  "properties": {
    "iso:country":"GB",
    "sg:address":"500-502 Manchester Road, Stocksbridge",
    "sg:city":"Sheffield",
    "sg:classifiers":[
        {
            "category":"Shopping",
            "subcategory":"News",
            "type":"Retail Goods"
        }
    ],
    "sg:phone":"+44 114 288 2254",
    "sg:postcode":"S36 2DU",
    "sg:province":"South Yorkshire",
    "sg:tags":[
        "newsagent"
    ],
    "wof:name":"G T News",
    "wof:placetype":"venue"
},
  "geometry": {"coordinates":[-1.5884890556,53.4815216064],"type":"Point"}
}