{
  "type": "Feature",
  "properties": {
    "iso:country":"GB",
    "sg:address":"12 Payton Street",
    "sg:city":"Stratford-upon-avon",
    "sg:classifiers":[
        {
            "category":"Professional",
            "subcategory":"Accounting & Tax Preparation",
            "type":"Services"
        }
    ],
    "sg:postcode":"CV37 6UA",
    "sg:province":"Warwickshire",
    "sg:tags":[
        "accountant"
    ],
    "wof:name":"R Gravestock & Co.",
    "wof:placetype":"venue"
},
  "geometry": {"coordinates":[-1.704226,52.194363],"type":"Point"}
}