{
  "type": "Feature",
  "properties": {
    "addr:full":"3 Pickfords Wharf, Clink Street London Greater London SE1 9DG",
    "addr:housenumber":"3",
    "addr:postcode":"se1 9dg",
    "addr:street":"Pickfords Wharf Clink Street",
    "iso:country":"GB",
    "sg:address":"3 Pickfords Wharf, Clink Street",
    "sg:city":"London",
    "sg:classifiers":[
        {
            "category":"Shopping",
            "subcategory":"News",
            "type":"Retail Goods"
        }
    ],
    "sg:phone":"+44 20 7407 3085",
    "sg:postcode":"SE1 9DG",
    "sg:province":"Greater London",
    "sg:tags":[
        "newsagent"
    ],
    "wof:name":"Kays Newsagents",
    "wof:placetype":"venue"
},
  "geometry": {"coordinates":[-0.0910890028,51.5069618225],"type":"Point"}
}