{
  "type": "Feature",
  "properties": {
    "iso:country":"GB",
    "sg:address":"262 Haselbury Road",
    "sg:city":"London",
    "sg:classifiers":[
        {
            "category":"Retail",
            "subcategory":"Laundry & Dry Cleaning",
            "type":"Services"
        }
    ],
    "sg:phone":"+44 20 8807 7762",
    "sg:postcode":"N9 9TP",
    "sg:province":"Greater London",
    "sg:tags":[
        "launderette"
    ],
    "wof:name":"Clean Easy Launderette",
    "wof:placetype":"venue"
},
  "geometry": {"coordinates":[-0.073915,51.624393],"type":"Point"}
}