{
  "type": "Feature",
  "properties": {
    "iso:country":"GB",
    "sg:address":"Unit 16c Nortonthorpe Industrial Estate, Wakefield Road",
    "sg:city":"Huddersfield",
    "sg:classifiers":[
        {
            "category":"Professional",
            "type":"Services"
        }
    ],
    "sg:postcode":"HD8 9FB",
    "sg:province":"South Yorkshire",
    "sg:tags":[
        "interior",
        "furnishers",
        "designer"
    ],
    "wof:name":"R P C Design Ltd.",
    "wof:placetype":"venue"
},
  "geometry": {"coordinates":[-1.62888,53.58654],"type":"Point"}
}