{
  "type": "Feature",
  "properties": {
    "addr:full":"1 Northcourt Oast, Old Wives Lees Canterbury Kent CT4 8AZ",
    "addr:housenumber":"1",
    "addr:postcode":"ct4 8az",
    "addr:street":"Northcourt Oast;Lees",
    "iso:country":"GB",
    "sg:address":"1 Northcourt Oast, Old Wives Lees",
    "sg:city":"Canterbury",
    "sg:classifiers":[
        {
            "category":"Building & Trades",
            "subcategory":"Construction",
            "type":"Services"
        }
    ],
    "sg:phone":"+44 1227 730711",
    "sg:postcode":"CT4 8AZ",
    "sg:province":"Kent",
    "sg:tags":[
        "fork",
        "lift",
        "truck"
    ],
    "wof:name":"T & B Bedding",
    "wof:placetype":"venue"
},
  "geometry": {"coordinates":[0.97731,51.256489],"type":"Point"}
}