{
  "type": "Feature",
  "properties": {
    "addr:full":"8c Woodhouse Close Hayes Greater London UB3 1NJ",
    "addr:housenumber":"8c",
    "addr:postcode":"ub3 1nj",
    "addr:street":"Woodhouse Close",
    "iso:country":"GB",
    "sg:address":"8c Woodhouse Close",
    "sg:city":"Hayes",
    "sg:classifiers":[
        {
            "category":"Professional",
            "subcategory":"Engineering",
            "type":"Services"
        }
    ],
    "sg:phone":"+44 20 8575 6377",
    "sg:postcode":"UB3 1NJ",
    "sg:province":"Greater London",
    "sg:tags":[
        "industrial",
        "engineer"
    ],
    "wof:name":"Total Industrial Maintenance Engineering",
    "wof:placetype":"venue"
},
  "geometry": {"coordinates":[-0.4290409982,51.49949646],"type":"Point"}
}