{
  "type": "Feature",
  "properties": {
    "addr:full":"Raikes Lane Bradford West Yorkshire BD4 0RL",
    "addr:postcode":"bd4 0rl",
    "addr:street":"Raikes Lane",
    "iso:country":"GB",
    "sg:address":"Raikes Lane",
    "sg:city":"Bradford",
    "sg:classifiers":[
        {
            "category":"Personal",
            "type":"Services"
        },
        {
            "category":"Sports & Exercise",
            "subcategory":"Stables",
            "type":"Entertainment"
        }
    ],
    "sg:phone":"+44 1274 684722",
    "sg:postcode":"BD4 0RL",
    "sg:province":"West Yorkshire",
    "sg:tags":[
        "education",
        "equestrian",
        "wedding"
    ],
    "wof:name":"Raikes Hall Livery Centre",
    "wof:placetype":"venue"
},
  "geometry": {"coordinates":[-1.697678,53.772415],"type":"Point"}
}