{
  "type": "Feature",
  "properties": {
    "iso:country":"GB",
    "sg:address":"Commercial Street, Kenfig Hill",
    "sg:city":"Bridgend",
    "sg:classifiers":[
        {
            "category":"Education",
            "subcategory":"School",
            "type":"Public Place"
        }
    ],
    "sg:phone":"+44 1656 815710",
    "sg:postcode":"CF33 6DN",
    "sg:province":"Bridgend",
    "sg:tags":[
        "local",
        "authority"
    ],
    "wof:name":"Mynydd Cynffig Infant School",
    "wof:placetype":"venue"
},
  "geometry": {"coordinates":[-3.678299,51.533073],"type":"Point"}
}