{
  "type": "Feature",
  "properties": {
    "addr:full":"Unit 7 & 8 Cheadle Heath Works, Cheadle Heath Stockport Cheshire SK3 0PP",
    "addr:housenumber":"unit 7 & 8",
    "addr:postcode":"sk3 0pp",
    "iso:country":"GB",
    "sg:address":"Unit 7 & 8 Cheadle Heath Works, Cheadle Heath",
    "sg:city":"Stockport",
    "sg:classifiers":[
        {
            "category":"Professional",
            "subcategory":"Engineering",
            "type":"Services"
        }
    ],
    "sg:phone":"+44 161 428 8456",
    "sg:postcode":"SK3 0PP",
    "sg:province":"Cheshire",
    "sg:tags":[
        "hydraulic",
        "engineer"
    ],
    "wof:name":"A D F Specialised Services Ltd.",
    "wof:placetype":"venue"
},
  "geometry": {"coordinates":[-2.19784,53.398399],"type":"Point"}
}