{
  "type": "Feature",
  "properties": {
    "iso:country":"GB",
    "sg:address":"16 Park Cres",
    "sg:city":"Oswestry",
    "sg:classifiers":[
        {
            "category":"Building & Trades",
            "subcategory":"Plumbing",
            "type":"Services"
        }
    ],
    "sg:phone":"+44 1691 652683",
    "sg:postcode":"SY11 4AR",
    "sg:province":"Shropshire",
    "sg:tags":[
        "heating"
    ],
    "wof:name":"D J Williams",
    "wof:placetype":"venue"
},
  "geometry": {"coordinates":[-3.0281369686,52.8794975281],"type":"Point"}
}