{
  "type": "Feature",
  "properties": {
    "addr:full":"9 Bridge Street, Uffculme Cullompton Devon EX15 3AX",
    "addr:housenumber":"9",
    "addr:postcode":"ex15 3ax",
    "addr:street":"Bridge Street",
    "iso:country":"GB",
    "sg:address":"9 Bridge Street, Uffculme",
    "sg:city":"Cullompton",
    "sg:classifiers":[
        {
            "category":"Home & Garden",
            "subcategory":"Home Furnishings",
            "type":"Retail Goods"
        }
    ],
    "sg:phone":"+44 1884 840494",
    "sg:postcode":"EX15 3AX",
    "sg:province":"Devon",
    "sg:tags":[
        "blind",
        "curtain",
        "fitting"
    ],
    "wof:name":"Merlin Blinds",
    "wof:placetype":"venue"
},
  "geometry": {"coordinates":[-3.326086998,50.9057235718],"type":"Point"}
}