{
  "type": "Feature",
  "properties": {
    "addr:full":"6 Manor St Bolton Lancashire BL1 1TU",
    "addr:housenumber":"6",
    "addr:postcode":"bl1 1tu",
    "addr:street":"Manor St",
    "iso:country":"GB",
    "sg:address":"6 Manor St",
    "sg:city":"Bolton",
    "sg:classifiers":[
        {
            "category":"Education",
            "subcategory":"Dance Studio",
            "type":"Public Place"
        }
    ],
    "sg:phone":"+44 1204 300456",
    "sg:postcode":"BL1 1TU",
    "sg:province":"Lancashire",
    "sg:tags":[
        "school",
        "dancing"
    ],
    "wof:name":"The Academy of Classical Dance & Stage",
    "wof:placetype":"venue"
},
  "geometry": {"coordinates":[-2.4268391132,53.579750061],"type":"Point"}
}