{
  "type": "Feature",
  "properties": {
    "addr:full":"The Kiosk, Wivenhoe Train Station Colchester Essex CO7 9DJ",
    "addr:postcode":"co7 9dj",
    "addr:street":"Colchester",
    "iso:country":"GB",
    "sg:address":"The Kiosk, Wivenhoe Train Station",
    "sg:city":"Colchester",
    "sg:classifiers":[
        {
            "category":"Military Area",
            "subcategory":"Air Force Base",
            "type":"Public Place"
        }
    ],
    "sg:phone":"+44 1206 822020",
    "sg:postcode":"CO7 9DJ",
    "sg:province":"Essex",
    "sg:tags":[
        "taxi",
        "hire",
        "private"
    ],
    "wof:name":"Georgina Tolley",
    "wof:placetype":"venue"
},
  "geometry": {"coordinates":[0.95947,51.856838],"type":"Point"}
}