{
  "type": "Feature",
  "properties": {
    "iso:country":"GB",
    "sg:address":"25 Wellgarth Road, Featherstone, Purston",
    "sg:city":"Pontefract",
    "sg:classifiers":[
        {
            "category":"Retail",
            "subcategory":"Driving School",
            "type":"Services"
        }
    ],
    "sg:phone":"+44 1977 700921",
    "sg:postcode":"WF7 5LZ",
    "sg:province":"West Yorkshire",
    "wof:name":"Barbara Featherstone School Of Motoring",
    "wof:placetype":"venue"
},
  "geometry": {"coordinates":[-1.3468860388,53.6700820923],"type":"Point"}
}