{
  "type": "Feature",
  "properties": {
    "addr:full":"36 Russell Clo, Kensworth Dunstable Bedfordshire LU6 3RW",
    "addr:housenumber":"36",
    "addr:postcode":"lu6 3rw",
    "addr:street":"Russell Clo Kensworth",
    "iso:country":"GB",
    "sg:address":"36 Russell Clo, Kensworth",
    "sg:city":"Dunstable",
    "sg:classifiers":[
        {
            "category":"Retail",
            "subcategory":"Repair Shop",
            "type":"Services"
        },
        {
            "category":"Building & Trades",
            "subcategory":"Construction",
            "type":"Services"
        }
    ],
    "sg:postcode":"LU6 3RW",
    "sg:province":"Bedfordshire",
    "sg:tags":[
        "roofing",
        "maintenance"
    ],
    "wof:name":"Bates,Michael,",
    "wof:placetype":"venue"
},
  "geometry": {"coordinates":[-0.5026260018,51.849407196],"type":"Point"}
}