{
  "type": "Feature",
  "properties": {
    "iso:country":"GB",
    "sg:address":"40 Eastleigh Road",
    "sg:city":"Devizes",
    "sg:classifiers":[
        {
            "category":"Government",
            "subcategory":"Post Office",
            "type":"Public Place"
        },
        {
            "category":"Food & Beverages",
            "subcategory":"Groceries & Convenience Stores",
            "type":"Retail Goods"
        }
    ],
    "sg:phone":"+44 1380 723640",
    "sg:postcode":"SN10 3EQ",
    "sg:province":"Wiltshire",
    "wof:name":"Eastleigh Road Post Office",
    "wof:placetype":"venue"
},
  "geometry": {"coordinates":[-1.9787299633,51.3480796814],"type":"Point"}
}