{
  "type": "Feature",
  "properties": {
    "iso:country":"GB",
    "sg:address":"Waterside",
    "sg:city":"Stratford-upon-avon",
    "sg:classifiers":[
        {
            "category":"Building & Trades",
            "subcategory":"Cleaning & Sanitation",
            "type":"Services"
        }
    ],
    "sg:postcode":"CV37 6BA",
    "sg:province":"Warwickshire",
    "sg:tags":[
        "commercial"
    ],
    "wof:name":"Blue Ribbon Service Group (Northern) Ltd.",
    "wof:placetype":"venue"
},
  "geometry": {"coordinates":[-1.704019,52.19212],"type":"Point"}
}