{
  "type": "Feature",
  "properties": {
    "addr:full":"7 Regents Street London Greater London SW1Y 4LR",
    "addr:housenumber":"7",
    "addr:postcode":"sw1y 4lr",
    "addr:street":"Regents Street",
    "iso:country":"GB",
    "sg:address":"7 Regents Street",
    "sg:city":"London",
    "sg:classifiers":[
        {
            "category":"Airline",
            "type":"Transportation"
        }
    ],
    "sg:phone":"+44 20 8814 0707",
    "sg:postcode":"SW1Y 4LR",
    "sg:province":"Greater London",
    "wof:name":"Trans World Airlines Inc",
    "wof:placetype":"venue"
},
  "geometry": {"coordinates":[-0.133719,51.508228],"type":"Point"}
}