{
  "type": "Feature",
  "properties": {
    "iso:country":"GB",
    "sg:address":"Rye Bank Road, Firswood",
    "sg:city":"Manchester",
    "sg:classifiers":[
        {
            "category":"Education",
            "subcategory":"Special Training",
            "type":"Public Place"
        },
        {
            "category":"Education",
            "subcategory":"School",
            "type":"Public Place"
        }
    ],
    "sg:phone":"+44 161 881 7843",
    "sg:postcode":"M16 0EX",
    "sg:province":"Cheshire",
    "wof:name":"St John Vianney Upper School",
    "wof:placetype":"venue"
},
  "geometry": {"coordinates":[-2.2733490467,53.4528884888],"type":"Point"}
}