{
  "type": "Feature",
  "properties": {
    "addr:full":"24 Bedford Row London Greater London WC1R 4TQ",
    "addr:housenumber":"24",
    "addr:postcode":"wc1r 4tq",
    "addr:street":"Bedford Row",
    "iso:country":"GB",
    "sg:address":"24 Bedford Row",
    "sg:city":"London",
    "sg:classifiers":[
        {
            "category":"Professional",
            "subcategory":"Management & Consulting",
            "type":"Services"
        }
    ],
    "sg:postcode":"WC1R 4TQ",
    "sg:province":"Greater London",
    "sg:tags":[
        "consultant",
        "business"
    ],
    "wof:name":"At Associates Ltd.",
    "wof:placetype":"venue"
},
  "geometry": {"coordinates":[-0.1163399965,51.5206451416],"type":"Point"}
}