{
  "type": "Feature",
  "properties": {
    "addr:full":"123 Shaftesbury Av Harrow Greater London HA2 0AL",
    "addr:housenumber":"123",
    "addr:postcode":"ha2 0al",
    "addr:street":"Shaftesbury Av Harrow",
    "iso:country":"GB",
    "sg:address":"123 Shaftesbury Av",
    "sg:city":"Harrow",
    "sg:classifiers":[
        {
            "category":"Home & Garden",
            "subcategory":"Home Furnishings",
            "type":"Retail Goods"
        }
    ],
    "sg:phone":"+44 20 8864 3147",
    "sg:postcode":"HA2 0AL",
    "sg:province":"Greater London",
    "sg:tags":[
        "furnishers",
        "planner",
        "bedroom"
    ],
    "wof:name":"Ian Brodie",
    "wof:placetype":"venue"
},
  "geometry": {"coordinates":[-0.3543600142,51.5724563599],"type":"Point"}
}