{
  "type": "Feature",
  "properties": {
    "addr:full":"10 Tower Street King's Lynn Norfolk PE30 1EJ",
    "addr:housenumber":"10",
    "addr:postcode":"pe30 1ej",
    "addr:street":"Tower Street",
    "iso:country":"GB",
    "sg:address":"10 Tower Street",
    "sg:city":"King's Lynn",
    "sg:classifiers":[
        {
            "category":"Recreation",
            "subcategory":"Dog Park",
            "type":"Entertainment"
        }
    ],
    "sg:phone":"+44 1553 816400",
    "sg:postcode":"PE30 1EJ",
    "sg:province":"Norfolk",
    "wof:name":"Dezynadog",
    "wof:placetype":"venue"
},
  "geometry": {"coordinates":[0.397619009,52.7527732849],"type":"Point"}
}