{
  "type": "Feature",
  "properties": {
    "addr:full":"164 Sedlescombe Road North St Leonards-on-sea East Sussex TN37 7EN",
    "addr:housenumber":"164",
    "addr:postcode":"tn37 7en",
    "addr:street":"Sedlescombe Road North St Leonards-On-Sea",
    "iso:country":"GB",
    "sg:address":"164 Sedlescombe Road North",
    "sg:city":"St Leonards-on-sea",
    "sg:classifiers":[
        {
            "category":"Building & Trades",
            "subcategory":"Plumbing",
            "type":"Services"
        }
    ],
    "sg:phone":"+44 1424 434149",
    "sg:postcode":"TN37 7EN",
    "sg:province":"East Sussex",
    "sg:tags":[
        "heating"
    ],
    "wof:name":"B & G Heating & Plumbing Engineers",
    "wof:placetype":"venue"
},
  "geometry": {"coordinates":[0.5582550168,50.8739471436],"type":"Point"}
}