{
  "type": "Feature",
  "properties": {
    "addr:full":"14 Loders Clo Poole Dorset BH17 9BF",
    "addr:housenumber":"14",
    "addr:postcode":"bh17 9bf",
    "addr:street":"Loders Clo",
    "iso:country":"GB",
    "sg:address":"14 Loders Clo",
    "sg:city":"Poole",
    "sg:classifiers":[
        {
            "category":"Building & Trades",
            "subcategory":"Landscaping Services",
            "type":"Services"
        }
    ],
    "sg:phone":"+44 1202 699156",
    "sg:postcode":"BH17 9BF",
    "sg:province":"Dorset",
    "sg:tags":[
        "contractor",
        "drainage"
    ],
    "wof:name":"Poole Building Services",
    "wof:placetype":"venue"
},
  "geometry": {"coordinates":[-1.978813,50.757828],"type":"Point"}
}