{
  "type": "Feature",
  "properties": {
    "iso:country":"GB",
    "sg:address":"Longbenton Community High School, Hailsham Av",
    "sg:city":"Newcastle Upon Tyne",
    "sg:classifiers":[
        {
            "category":"Government",
            "subcategory":"Office",
            "type":"Public Place"
        }
    ],
    "sg:phone":"+44 191 200 7885",
    "sg:postcode":"NE12 8ER",
    "sg:province":"Tyne and Wear",
    "sg:tags":[
        "local"
    ],
    "wof:name":"Disability Resource Centre",
    "wof:placetype":"venue"
},
  "geometry": {"coordinates":[-1.57414,55.018581],"type":"Point"}
}