{
  "type": "Feature",
  "properties": {
    "iso:country":"GB",
    "sg:address":"64 Eccleston Square, Pimlico",
    "sg:city":"London",
    "sg:classifiers":[
        {
            "category":"Professional",
            "subcategory":"Computer Services",
            "type":"Services"
        }
    ],
    "sg:postcode":"SW1V 1PH",
    "sg:province":"Greater London",
    "sg:tags":[
        "system",
        "software"
    ],
    "wof:name":"Blue Ocean Technology Ltd",
    "wof:placetype":"venue"
},
  "geometry": {"coordinates":[-0.143719,51.49213],"type":"Point"}
}