{
  "type": "Feature",
  "properties": {
    "addr:full":"Unit 4, Stockingswater Lane Enfield Greater London EN3 7PH",
    "addr:housenumber":"unit 4",
    "addr:postcode":"en3 7ph",
    "addr:street":"Stockingswater Lane",
    "iso:country":"GB",
    "sg:address":"Unit 4, Stockingswater Lane",
    "sg:city":"Enfield",
    "sg:classifiers":[
        {
            "category":"Utilities",
            "subcategory":"Sewage",
            "type":"Services"
        }
    ],
    "sg:phone":"+44 20 8443 0099",
    "sg:postcode":"EN3 7PH",
    "sg:province":"Greater London",
    "sg:tags":[
        "acoustic",
        "consultant"
    ],
    "wof:name":"Trim Acoustics",
    "wof:placetype":"venue"
},
  "geometry": {"coordinates":[-0.026131,51.653847],"type":"Point"}
}