{
  "type": "Feature",
  "properties": {
    "addr:full":"Bleaklow House, Howard Town Mill, Victoria Street Glossop Derbyshire SK13 8HT",
    "addr:postcode":"sk13 8ht",
    "addr:street":"Howard Town;Victoria Street",
    "iso:country":"GB",
    "sg:address":"Bleaklow House, Howard Town Mill, Victoria Street",
    "sg:city":"Glossop",
    "sg:classifiers":[
        {
            "category":"Professional",
            "subcategory":"Management & Consulting",
            "type":"Services"
        }
    ],
    "sg:phone":"+44 1457 868003",
    "sg:postcode":"SK13 8HT",
    "sg:province":"Derbyshire",
    "sg:tags":[
        "consultant",
        "business"
    ],
    "wof:name":"Collective Enterprises Ltd.",
    "wof:placetype":"venue"
},
  "geometry": {"coordinates":[-1.9465700388,53.4433364868],"type":"Point"}
}