{
  "type": "Feature",
  "properties": {
    "addr:full":"Marley Hill Newcastle-upon-tyne Durham NE16 5EG",
    "addr:postcode":"ne16 5eg",
    "iso:country":"GB",
    "sg:address":"Marley Hill",
    "sg:city":"Newcastle-upon-tyne",
    "sg:classifiers":[
        {
            "category":"Farming",
            "subcategory":"Farm",
            "type":"Manufacturing & Wholesale Goods"
        }
    ],
    "sg:phone":"+44 1207 232707",
    "sg:postcode":"NE16 5EG",
    "sg:province":"Durham",
    "sg:tags":[
        "mixed",
        "crop"
    ],
    "wof:name":"John M Coxon",
    "wof:placetype":"venue"
},
  "geometry": {"coordinates":[-1.6782699823,54.9009895325],"type":"Point"}
}