{
  "type": "Feature",
  "properties": {
    "iso:country":"GB",
    "sg:address":"29 Doncaster Rd, Darfield",
    "sg:city":"Barnsley",
    "sg:classifiers":[
        {
            "category":"Building & Trades",
            "subcategory":"Construction",
            "type":"Services"
        }
    ],
    "sg:phone":"+44 1226 753754",
    "sg:postcode":"S73 9JB",
    "sg:province":"South Yorkshire",
    "sg:tags":[
        "builder"
    ],
    "wof:name":"M & R Builders",
    "wof:placetype":"venue"
},
  "geometry": {"coordinates":[-1.3586930037,53.5344619751],"type":"Point"}
}