{
  "type": "Feature",
  "properties": {
    "iso:country":"GB",
    "sg:address":"Building 470, Bournemouth International Airpor",
    "sg:city":"Christchurch",
    "sg:classifiers":[
        {
            "category":"Professional",
            "subcategory":"Management & Consulting",
            "type":"Services"
        },
        {
            "category":"Professional",
            "subcategory":"Business Services",
            "type":"Services"
        }
    ],
    "sg:phone":"+44 1202 597676",
    "sg:postcode":"BH23 6SE",
    "sg:province":"Dorset",
    "sg:tags":[
        "distribution",
        "holding",
        "activity"
    ],
    "wof:name":"Dart Group Plc",
    "wof:placetype":"venue"
},
  "geometry": {"coordinates":[-1.776564002,50.7340698242],"type":"Point"}
}