{
  "type": "Feature",
  "properties": {
    "addr:full":"Unit 1, 13 Richmond Road Ilford Essex IG1 1JF",
    "addr:housenumber":"unit;13",
    "addr:postcode":"ig1 1jf",
    "addr:street":"Richmond Road",
    "iso:country":"GB",
    "sg:address":"Unit 1, 13 Richmond Road",
    "sg:city":"Ilford",
    "sg:classifiers":[
        {
            "category":"Professional",
            "subcategory":"Management & Consulting",
            "type":"Services"
        },
        {
            "category":"Building & Trades",
            "subcategory":"Construction",
            "type":"Services"
        }
    ],
    "sg:phone":"+44 70 0078 4711",
    "sg:postcode":"IG1 1JF",
    "sg:province":"Essex",
    "sg:tags":[
        "consultant",
        "flooring",
        "business"
    ],
    "wof:name":"Abstract & Hart Ltd.",
    "wof:placetype":"venue"
},
  "geometry": {"coordinates":[0.078643,51.55801],"type":"Point"}
}