{
  "type": "Feature",
  "properties": {
    "addr:full":"85a Oldham Road, Grasscroft Oldham Lancashire OL4 4JF",
    "addr:housenumber":"85a",
    "addr:postcode":"ol4 4jf",
    "addr:street":"Oldham Road",
    "iso:country":"GB",
    "sg:address":"85a Oldham Road, Grasscroft",
    "sg:city":"Oldham",
    "sg:classifiers":[
        {
            "category":"Personal",
            "subcategory":"Beauty Salon",
            "type":"Services"
        }
    ],
    "sg:phone":"+44 1457 877218",
    "sg:postcode":"OL4 4JF",
    "sg:province":"Lancashire",
    "wof:name":"Triangle Beauty Centre",
    "wof:placetype":"venue"
},
  "geometry": {"coordinates":[-2.065351,53.537991],"type":"Point"}
}