{
  "type": "Feature",
  "properties": {
    "iso:country":"GB",
    "sg:address":"The Estate Office, High Street, Nayland",
    "sg:city":"Colchester",
    "sg:classifiers":[
        {
            "category":"Real Estate",
            "subcategory":"Real Estate Agent",
            "type":"Services"
        }
    ],
    "sg:postcode":"CO6 4JF",
    "sg:province":"Essex",
    "wof:name":"Roy Chapman & Sons",
    "wof:placetype":"venue"
},
  "geometry": {"coordinates":[0.871774,51.972328],"type":"Point"}
}