{
  "type": "Feature",
  "properties": {
    "addr:full":"Cleves Cross Ferryhill Durham DL17 8QY",
    "addr:postcode":"dl17 8qy",
    "addr:street":"Cross",
    "iso:country":"GB",
    "sg:address":"Cleves Cross",
    "sg:city":"Ferryhill",
    "sg:classifiers":[
        {
            "category":"Education",
            "subcategory":"School",
            "type":"Public Place"
        },
        {
            "category":"Government",
            "subcategory":"Office",
            "type":"Public Place"
        }
    ],
    "sg:phone":"+44 1740 651599",
    "sg:postcode":"DL17 8QY",
    "sg:province":"Durham",
    "sg:tags":[
        "local",
        "authority"
    ],
    "wof:name":"Cleves Cross Primary School",
    "wof:placetype":"venue"
},
  "geometry": {"coordinates":[-1.5576519966,54.6888122559],"type":"Point"}
}