{
  "type": "Feature",
  "properties": {
    "iso:country":"GB",
    "sg:address":"Kingsbury Road, Erdington",
    "sg:city":"Birmingham",
    "sg:classifiers":[
        {
            "category":"Cinema",
            "subcategory":"Movie Theater",
            "type":"Entertainment"
        }
    ],
    "sg:phone":"+44 121 382 9669",
    "sg:postcode":"B24 9QE",
    "sg:province":"West Midlands",
    "wof:name":"Showcase Cinemas Ltd",
    "wof:placetype":"venue"
},
  "geometry": {"coordinates":[-1.821254015,52.5170555115],"type":"Point"}
}