{
  "type": "Feature",
  "properties": {
    "iso:country":"GB",
    "sg:address":"Main Road, Rollesby",
    "sg:city":"Great Yarmouth",
    "sg:classifiers":[
        {
            "category":"Travel",
            "subcategory":"Hotels & Motels",
            "type":"Entertainment"
        }
    ],
    "sg:postcode":"NR29 5ER",
    "sg:province":"Norfolk",
    "wof:name":"Horse & Groom Motel",
    "wof:placetype":"venue"
},
  "geometry": {"coordinates":[1.620655,52.687416],"type":"Point"}
}