{
  "type": "Feature",
  "properties": {
    "addr:full":"169 The Cornfields, Worle Weston-super-mare Somerset BS22 9DZ",
    "addr:housenumber":"169",
    "addr:postcode":"bs22 9dz",
    "addr:street":"The Cornfields",
    "iso:country":"GB",
    "sg:address":"169 The Cornfields, Worle",
    "sg:city":"Weston-super-mare",
    "sg:classifiers":[
        {
            "category":"Home & Garden",
            "subcategory":"Hardware",
            "type":"Retail Goods"
        },
        {
            "category":"Farming",
            "subcategory":"Farm",
            "type":"Manufacturing & Wholesale Goods"
        }
    ],
    "sg:postcode":"BS22 9DZ",
    "sg:province":"Somerset",
    "sg:tags":[
        "compressor",
        "agricultural",
        "air"
    ],
    "wof:name":"Airline Installations",
    "wof:placetype":"venue"
},
  "geometry": {"coordinates":[-2.920203,51.371811],"type":"Point"}
}