{
  "type": "Feature",
  "properties": {
    "addr:full":"26 Old Mill Lane Barnsley South Yorkshire S70 2LA",
    "addr:housenumber":"26",
    "addr:postcode":"s70 2la",
    "addr:street":"Old Mill Lane;Yorkshire",
    "iso:country":"GB",
    "sg:address":"26 Old Mill Lane",
    "sg:city":"Barnsley",
    "sg:classifiers":[
        {
            "category":"Deli",
            "type":"Food & Drink"
        },
        {
            "category":"Food & Beverages",
            "subcategory":"Liquor & Beverages",
            "type":"Retail Goods"
        }
    ],
    "sg:phone":"+44 1226 203396",
    "sg:postcode":"S70 2LA",
    "sg:province":"South Yorkshire",
    "sg:tags":[
        "delicatessen",
        "beer",
        "spirit",
        "wines"
    ],
    "wof:name":"Mega Bites",
    "wof:placetype":"venue"
},
  "geometry": {"coordinates":[-1.4826339483,53.557258606],"type":"Point"}
}