{
  "type": "Feature",
  "properties": {
    "addr:full":"Unit 3 Damases Lane, Boreham Chelmsford Essex CM3 3AL",
    "addr:housenumber":"unit 3",
    "addr:postcode":"cm3 3al",
    "addr:street":"Damases Lane",
    "iso:country":"GB",
    "sg:address":"Unit 3 Damases Lane, Boreham",
    "sg:city":"Chelmsford",
    "sg:classifiers":[
        {
            "category":"Shopping",
            "subcategory":"Pets & Pet Supplies",
            "type":"Retail Goods"
        },
        {
            "category":"Health Services",
            "subcategory":"Dentist",
            "type":"Services"
        }
    ],
    "sg:phone":"+44 1245 464778",
    "sg:postcode":"CM3 3AL",
    "sg:province":"Essex",
    "sg:tags":[
        "food",
        "technician",
        "dental"
    ],
    "wof:name":"Beechcroft Orthodontic Laboratory",
    "wof:placetype":"venue"
},
  "geometry": {"coordinates":[0.5623019934,51.7659034729],"type":"Point"}
}