{
  "type": "Feature",
  "properties": {
    "iso:country":"GB",
    "sg:address":"10 Park Road",
    "sg:city":"Coventry",
    "sg:classifiers":[
        {
            "category":"Health Services",
            "subcategory":"Clinic",
            "type":"Services"
        },
        {
            "category":"Health Services",
            "subcategory":"Health Practitioner",
            "type":"Services"
        }
    ],
    "sg:phone":"+44 24 7622 2505",
    "sg:postcode":"CV1 2LA",
    "sg:province":"West Midlands",
    "sg:tags":[
        "homoeopathic",
        "private"
    ],
    "wof:name":"Park Practice",
    "wof:placetype":"venue"
},
  "geometry": {"coordinates":[-1.511066,52.401917],"type":"Point"}
}