{
  "type": "Feature",
  "properties": {
    "iso:country":"GB",
    "sg:address":"170 Shaw Heath",
    "sg:city":"Stockport",
    "sg:classifiers":[
        {
            "category":"Health Services",
            "subcategory":"Nursing And Care Facility",
            "type":"Services"
        },
        {
            "category":"Organizations",
            "subcategory":"Community Association",
            "type":"Services"
        }
    ],
    "sg:phone":"+44 161 477 8826",
    "sg:postcode":"SK2 6QX",
    "sg:province":"Cheshire",
    "sg:tags":[
        "co-operatives",
        "society",
        "housing",
        "trust",
        "home"
    ],
    "wof:name":"Manchester & District Housing Association Ltd.",
    "wof:placetype":"venue"
},
  "geometry": {"coordinates":[-2.157959,53.398277],"type":"Point"}
}