{
  "type": "Feature",
  "properties": {
    "iso:country":"GB",
    "sg:address":"6 Hainge Road, Tividale",
    "sg:city":"Oldbury",
    "sg:classifiers":[
        {
            "category":"Wholesale",
            "subcategory":"Construction Materials",
            "type":"Manufacturing & Wholesale Goods"
        },
        {
            "category":"Home & Garden",
            "subcategory":"Carpets & Floor Coverings",
            "type":"Retail Goods"
        }
    ],
    "sg:phone":"+44 121 522 4112",
    "sg:postcode":"B69 2NB",
    "sg:province":"West Midlands",
    "sg:tags":[
        "crane",
        "lift"
    ],
    "wof:name":"Colton Electrical",
    "wof:placetype":"venue"
},
  "geometry": {"coordinates":[-2.036774,52.511196],"type":"Point"}
}