{
  "type": "Feature",
  "properties": {
    "iso:country":"GB",
    "sg:address":"69 Ashdale Drive",
    "sg:city":"Birmingham",
    "sg:classifiers":[
        {
            "category":"Manufacturing",
            "subcategory":"Textiles",
            "type":"Manufacturing & Wholesale Goods"
        }
    ],
    "sg:phone":"+44 121 474 3873",
    "sg:postcode":"B14 4TX",
    "sg:province":"West Midlands",
    "sg:tags":[
        "made-up"
    ],
    "wof:name":"Curtains by Lynn Maturi",
    "wof:placetype":"venue"
},
  "geometry": {"coordinates":[-1.877804,52.402855],"type":"Point"}
}