{
  "type": "Feature",
  "properties": {
    "addr:full":"103 Waverley Avenue Chingford Greater London E4 8HS",
    "addr:housenumber":"103",
    "addr:postcode":"e4 8hs",
    "addr:street":"Waverley Avenue",
    "iso:country":"GB",
    "sg:address":"103 Waverley Avenue",
    "sg:city":"Chingford",
    "sg:classifiers":[
        {
            "category":"Building & Trades",
            "subcategory":"Construction",
            "type":"Services"
        }
    ],
    "sg:phone":"+44 20 8926 7206",
    "sg:postcode":"E4 8HS",
    "sg:province":"Greater London",
    "sg:tags":[
        "flooring"
    ],
    "wof:name":"Multi Floors",
    "wof:placetype":"venue"
},
  "geometry": {"coordinates":[-0.0284219999,51.6147537231],"type":"Point"}
}