{
  "type": "Feature",
  "properties": {
    "addr:full":"The Roundabout Centre, Bawtry Road Sheffield South Yorkshire S9 1UE",
    "addr:postcode":"s9 1ue",
    "addr:street":"Bawtry Road",
    "iso:country":"GB",
    "sg:address":"The Roundabout Centre, Bawtry Road",
    "sg:city":"Sheffield",
    "sg:classifiers":[
        {
            "category":"Education",
            "subcategory":"University",
            "type":"Public Place"
        }
    ],
    "sg:phone":"+44 114 243 1566",
    "sg:postcode":"S9 1UE",
    "sg:province":"South Yorkshire",
    "sg:tags":[
        "adult"
    ],
    "wof:name":"Tinsley Adult Education Centre",
    "wof:placetype":"venue"
},
  "geometry": {"coordinates":[-1.4019039869,53.4140167236],"type":"Point"}
}