{
  "type": "Feature",
  "properties": {
    "addr:full":"17 Humphrey Av Bromsgrove Worcestershire B60 3JB",
    "addr:housenumber":"17",
    "addr:postcode":"b60 3jb",
    "addr:street":"Humphrey Av",
    "iso:country":"GB",
    "sg:address":"17 Humphrey Av",
    "sg:city":"Bromsgrove",
    "sg:classifiers":[
        {
            "category":"Shopping",
            "subcategory":"News",
            "type":"Retail Goods"
        }
    ],
    "sg:phone":"+44 1527 831127",
    "sg:postcode":"B60 3JB",
    "sg:province":"Worcestershire",
    "sg:tags":[
        "newsagent"
    ],
    "wof:name":"Stars News Shops",
    "wof:placetype":"venue"
},
  "geometry": {"coordinates":[-2.0669898987,52.3223457336],"type":"Point"}
}