{
  "type": "Feature",
  "properties": {
    "addr:full":"6 The Drive Sevenoaks Kent TN13 3AE",
    "addr:housenumber":"6",
    "addr:postcode":"tn13 3ae",
    "addr:street":"The Drive",
    "iso:country":"GB",
    "sg:address":"6 The Drive",
    "sg:city":"Sevenoaks",
    "sg:classifiers":[
        {
            "category":"Place Of Worship",
            "type":"Public Place"
        }
    ],
    "sg:phone":"+44 1732 452870",
    "sg:postcode":"TN13 3AE",
    "sg:province":"Kent",
    "wof:name":"Drive Methodist Church The",
    "wof:placetype":"venue"
},
  "geometry": {"coordinates":[0.191952,51.274387],"type":"Point"}
}