{
  "type": "Feature",
  "properties": {
    "addr:full":"Belleau Bridge Trout Farm House Alford Lincolnshire LN13 0BP",
    "addr:postcode":"ln13 0bp",
    "addr:street":"Belleau;Trout",
    "iso:country":"GB",
    "sg:address":"Belleau Bridge Trout Farm House",
    "sg:city":"Alford",
    "sg:classifiers":[
        {
            "category":"Farming",
            "subcategory":"Farm",
            "type":"Manufacturing & Wholesale Goods"
        }
    ],
    "sg:postcode":"LN13 0BP",
    "sg:province":"Lincolnshire",
    "sg:tags":[
        "hatchery"
    ],
    "wof:name":"Belleau Bridge Trout Farm",
    "wof:placetype":"venue"
},
  "geometry": {"coordinates":[0.1467799991,53.2732315063],"type":"Point"}
}