{
  "type": "Feature",
  "properties": {
    "addr:full":"108b Blackford Av Edinburgh City of Edinburgh EH9 3HH",
    "addr:housenumber":"108b",
    "addr:postcode":"eh9 3hh",
    "addr:street":"Blackford Av Edinburgh",
    "iso:country":"GB",
    "sg:address":"108b Blackford Av",
    "sg:city":"Edinburgh",
    "sg:classifiers":[
        {
            "category":"Professional",
            "subcategory":"Engineering",
            "type":"Services"
        }
    ],
    "sg:phone":"+44 131 667 3187",
    "sg:postcode":"EH9 3HH",
    "sg:province":"City of Edinburgh",
    "sg:tags":[
        "contractor",
        "electrical",
        "engineer"
    ],
    "wof:name":"Adlec",
    "wof:placetype":"venue"
},
  "geometry": {"coordinates":[-3.1847751141,55.9263038635],"type":"Point"}
}