{
  "type": "Feature",
  "properties": {
    "iso:country":"GB",
    "sg:address":"Suite 2 Morritt House, 58 Station Approach",
    "sg:city":"Ruislip",
    "sg:classifiers":[
        {
            "category":"Retail",
            "subcategory":"Auto Repair",
            "type":"Services"
        }
    ],
    "sg:postcode":"HA4 6SA",
    "sg:province":"Greater London",
    "sg:tags":[
        "modification",
        "garage"
    ],
    "wof:name":"Carmeleon Ltd",
    "wof:placetype":"venue"
},
  "geometry": {"coordinates":[-0.4003329873,51.5553817749],"type":"Point"}
}