{
  "type": "Feature",
  "properties": {
    "addr:full":"Armthorpe Enterprise Centre, Rands Lane, Armthorpe Doncaster South Yorkshire DN3 3DY",
    "addr:housenumber":"armthorpe;centre",
    "addr:postcode":"dn3 3dy",
    "addr:street":"Rands Lane",
    "iso:country":"GB",
    "sg:address":"Armthorpe Enterprise Centre, Rands Lane, Armthorpe",
    "sg:city":"Doncaster",
    "sg:classifiers":[
        {
            "category":"Wholesale",
            "subcategory":"Electrical",
            "type":"Manufacturing & Wholesale Goods"
        },
        {
            "category":"Shopping",
            "subcategory":"Computers & Home Electronics",
            "type":"Retail Goods"
        }
    ],
    "sg:phone":"+44 1302 302344",
    "sg:postcode":"DN3 3DY",
    "sg:province":"South Yorkshire",
    "sg:tags":[
        "wholesaler"
    ],
    "wof:name":"Underwoods Electrical Distributors Ltd.",
    "wof:placetype":"venue"
},
  "geometry": {"coordinates":[-1.0564290285,53.5356292725],"type":"Point"}
}