{
  "type": "Feature",
  "properties": {
    "addr:full":"The Briars, Whiphill Top Lane, Branton Doncaster South Yorkshire DN3 3PQ",
    "addr:postcode":"dn3 3pq",
    "addr:street":"Top Lane",
    "iso:country":"GB",
    "sg:address":"The Briars, Whiphill Top Lane, Branton",
    "sg:city":"Doncaster",
    "sg:classifiers":[
        {
            "category":"Professional",
            "subcategory":"Engineering",
            "type":"Services"
        }
    ],
    "sg:phone":"+44 70 7122 2596",
    "sg:postcode":"DN3 3PQ",
    "sg:province":"South Yorkshire",
    "sg:tags":[
        "contractor",
        "electrical",
        "engineer"
    ],
    "wof:name":"Rase Lowe",
    "wof:placetype":"venue"
},
  "geometry": {"coordinates":[-1.0409439802,53.5078392029],"type":"Point"}
}