{
  "type": "Feature",
  "properties": {
    "iso:country":"GB",
    "sg:address":"74 Great King Street",
    "sg:city":"Edinburgh",
    "sg:classifiers":[
        {
            "category":"Real Estate",
            "subcategory":"Real Estate Agent",
            "type":"Services"
        }
    ],
    "sg:phone":"+44 131 557 5775",
    "sg:postcode":"EH3 6QU",
    "sg:province":"City of Edinburgh",
    "wof:name":"Your-Move Co. U K Ltd.",
    "wof:placetype":"venue"
},
  "geometry": {"coordinates":[-3.201784,55.957581],"type":"Point"}
}