{
  "type": "Feature",
  "properties": {
    "addr:full":"Firs Lane Leigh Lancashire WN7 4SB",
    "addr:postcode":"wn7 4sb",
    "addr:street":"Firs Lane",
    "iso:country":"GB",
    "sg:address":"Firs Lane",
    "sg:city":"Leigh",
    "sg:classifiers":[
        {
            "category":"Education",
            "subcategory":"School",
            "type":"Public Place"
        }
    ],
    "sg:phone":"+44 1942 672601",
    "sg:postcode":"WN7 4SB",
    "sg:province":"Lancashire",
    "sg:tags":[
        "local",
        "authority"
    ],
    "wof:name":"Wigan Metropolitan Borough Council",
    "wof:placetype":"venue"
},
  "geometry": {"coordinates":[-2.5374209881,53.498249054],"type":"Point"}
}