{
  "type": "Feature",
  "properties": {
    "addr:full":"100 Redhouse Lane Walsall Staffordshire WS9 0DB",
    "addr:housenumber":"100",
    "addr:postcode":"ws9 0db",
    "addr:street":"Redhouse Lane",
    "iso:country":"GB",
    "sg:address":"100 Redhouse Lane",
    "sg:city":"Walsall",
    "sg:classifiers":[
        {
            "category":"Food & Beverages",
            "subcategory":"Liquor & Beverages",
            "type":"Retail Goods"
        },
        {
            "category":"Utilities",
            "subcategory":"Natural Gas",
            "type":"Services"
        }
    ],
    "sg:phone":"+44 1922 745104",
    "sg:postcode":"WS9 0DB",
    "sg:province":"Staffordshire",
    "sg:tags":[
        "wholesale",
        "beer",
        "wine",
        "spirit",
        "wines"
    ],
    "wof:name":"Pagendam Pratt",
    "wof:placetype":"venue"
},
  "geometry": {"coordinates":[-1.931705,52.600079],"type":"Point"}
}