{
  "type": "Feature",
  "properties": {
    "addr:full":"4d Bradbourne Mews, St Johns Hill Sevenoaks Kent TN13 3NP",
    "addr:housenumber":"4d",
    "addr:postcode":"tn13 3np",
    "addr:street":"Bradbourne Mews St Johns Hill",
    "iso:country":"GB",
    "sg:address":"4d Bradbourne Mews, St Johns Hill",
    "sg:city":"Sevenoaks",
    "sg:classifiers":[
        {
            "category":"Building & Trades",
            "subcategory":"Landscaping Services",
            "type":"Services"
        }
    ],
    "sg:postcode":"TN13 3NP",
    "sg:province":"Kent",
    "sg:tags":[
        "steel"
    ],
    "wof:name":"Brett A Shortland Agricultural Roofer",
    "wof:placetype":"venue"
},
  "geometry": {"coordinates":[0.182235,51.279984],"type":"Point"}
}