{
  "type": "Feature",
  "properties": {
    "addr:full":"Jury Lane, Sidlesham Chichester West Sussex PO20 7PX",
    "addr:postcode":"po20 7px",
    "addr:street":"Jury Lane",
    "iso:country":"GB",
    "sg:address":"Jury Lane, Sidlesham",
    "sg:city":"Chichester",
    "sg:classifiers":[
        {
            "category":"Utilities",
            "subcategory":"Fuel Oil & Lpg",
            "type":"Services"
        }
    ],
    "sg:phone":"+44 1243 641230",
    "sg:postcode":"PO20 7PX",
    "sg:province":"West Sussex",
    "sg:tags":[
        "coal",
        "smokeless"
    ],
    "wof:name":"Jury Brick & Coal Co. Ltd.",
    "wof:placetype":"venue"
},
  "geometry": {"coordinates":[-0.787379,50.776985],"type":"Point"}
}