{
  "type": "Feature",
  "properties": {
    "iso:country":"GB",
    "sg:address":"Unit 1, 1 Old Timber Yard",
    "sg:city":"Tunbridge Wells",
    "sg:classifiers":[
        {
            "category":"Freight",
            "type":"Transportation"
        }
    ],
    "sg:postcode":"TN3 9LB",
    "sg:province":"East Sussex",
    "sg:tags":[
        "haulage",
        "road"
    ],
    "wof:name":"Nick's Business",
    "wof:placetype":"venue"
},
  "geometry": {"coordinates":[0.200000003,51.0901603699],"type":"Point"}
}