{
  "type": "Feature",
  "properties": {
    "iso:country":"GB",
    "sg:address":"93 Clewer Hill Road",
    "sg:city":"Windsor",
    "sg:classifiers":[
        {
            "category":"Personal",
            "subcategory":"Beauty Salon",
            "type":"Services"
        },
        {
            "category":"Personal",
            "subcategory":"Barber",
            "type":"Services"
        }
    ],
    "sg:phone":"+44 1753 851462",
    "sg:postcode":"SL4 4DE",
    "sg:province":"Berkshire",
    "sg:tags":[
        "unisex",
        "hairdresser"
    ],
    "wof:name":"New Images",
    "wof:placetype":"venue"
},
  "geometry": {"coordinates":[-0.6387760043,51.4738388062],"type":"Point"}
}