{
  "type": "Feature",
  "properties": {
    "iso:country":"GB",
    "sg:address":"Kingswood Fluid Power Building, Avondale Works, Woodland Way",
    "sg:city":"Bristol",
    "sg:classifiers":[
        {
            "category":"Professional",
            "type":"Services"
        }
    ],
    "sg:phone":"+44 117 935 2183",
    "sg:postcode":"BS15 1FP",
    "sg:province":"City of Bristol",
    "sg:tags":[
        "control",
        "system"
    ],
    "wof:name":"Britek Systems Ltd.",
    "wof:placetype":"venue"
},
  "geometry": {"coordinates":[-2.5914289951,51.453666687],"type":"Point"}
}