{
  "type": "Feature",
  "properties": {
    "iso:country":"GB",
    "sg:address":"112 High Street, Halling",
    "sg:city":"Rochester",
    "sg:classifiers":[
        {
            "category":"Wholesale",
            "subcategory":"Books, Periodicals, & Newspapers",
            "type":"Manufacturing & Wholesale Goods"
        }
    ],
    "sg:phone":"+44 1634 242907",
    "sg:postcode":"ME2 1BY",
    "sg:province":"Kent",
    "sg:tags":[
        "publishing"
    ],
    "wof:name":"Alad Ltd.",
    "wof:placetype":"venue"
},
  "geometry": {"coordinates":[0.4460859895,51.3496589661],"type":"Point"}
}