{
  "type": "Feature",
  "properties": {
    "iso:country":"GB",
    "sg:address":"77 Bethcar Street",
    "sg:city":"Ebbw Vale",
    "sg:classifiers":[
        {
            "category":"Home & Garden",
            "subcategory":"Household Appliances",
            "type":"Retail Goods"
        },
        {
            "category":"Retail",
            "subcategory":"Repair Shop",
            "type":"Services"
        }
    ],
    "sg:phone":"+44 1495 307484",
    "sg:postcode":"NP23 6HN",
    "sg:province":"Blaenau Gwent",
    "sg:tags":[
        "electrial",
        "electrical"
    ],
    "wof:name":"The Plug",
    "wof:placetype":"venue"
},
  "geometry": {"coordinates":[-3.2080740929,51.7764778137],"type":"Point"}
}