{
  "type": "Feature",
  "properties": {
    "addr:full":"159 Uxbridge Rd West Ealing Greater London W13 9AU",
    "addr:housenumber":"159",
    "addr:postcode":"w13 9au",
    "addr:street":"Uxbridge Rd",
    "iso:country":"GB",
    "sg:address":"159 Uxbridge Rd",
    "sg:city":"West Ealing",
    "sg:classifiers":[
        {
            "category":"Food & Beverages",
            "subcategory":"Supermarket",
            "type":"Retail Goods"
        }
    ],
    "sg:phone":"+44 20 8579 9500",
    "sg:postcode":"W13 9AU",
    "sg:province":"Greater London",
    "wof:name":"Super Ealing Forozan",
    "wof:placetype":"venue"
},
  "geometry": {"coordinates":[-0.319243,51.511063],"type":"Point"}
}