{
  "type": "Feature",
  "properties": {
    "addr:full":"2 North St Ashford Kent TN24 8TE",
    "addr:housenumber":"2",
    "addr:postcode":"tn24 8te",
    "addr:street":"North St",
    "iso:country":"GB",
    "sg:address":"2 North St",
    "sg:city":"Ashford",
    "sg:classifiers":[
        {
            "category":"Shopping",
            "subcategory":"Department Store",
            "type":"Retail Goods"
        },
        {
            "category":"Shopping",
            "subcategory":"Music",
            "type":"Retail Goods"
        }
    ],
    "sg:postcode":"TN24 8TE",
    "sg:province":"Kent",
    "sg:tags":[
        "record",
        "tape",
        "cd"
    ],
    "wof:name":"T M G U K-Delaware Inc",
    "wof:placetype":"venue"
},
  "geometry": {"coordinates":[0.8731790185,51.1493148804],"type":"Point"}
}