{
  "type": "Feature",
  "properties": {
    "iso:country":"GB",
    "sg:address":"Unit 29 Park Farm Centre, Allestree",
    "sg:city":"Derby",
    "sg:classifiers":[
        {
            "category":"Travel",
            "subcategory":"Travel Agent",
            "type":"Entertainment"
        }
    ],
    "sg:phone":"+44 1332 541000",
    "sg:postcode":"DE22 2QN",
    "sg:province":"Derbyshire",
    "wof:name":"Ilkeston Consumer Co-Op Travel",
    "wof:placetype":"venue"
},
  "geometry": {"coordinates":[-1.496814,52.943272],"type":"Point"}
}