{
  "type": "Feature",
  "properties": {
    "iso:country":"GB",
    "sg:address":"P O Box 465",
    "sg:city":"Amersham",
    "sg:classifiers":[
        {
            "category":"Professional",
            "subcategory":"Computer Services",
            "type":"Services"
        }
    ],
    "sg:phone":"+44 1494 728000",
    "sg:postcode":"HP6 6XW",
    "sg:province":"Buckinghamshire",
    "sg:tags":[
        "system",
        "software"
    ],
    "wof:name":"Auridian Consulting Ltd.",
    "wof:placetype":"venue"
},
  "geometry": {"coordinates":[-0.5831760168,51.6751976013],"type":"Point"}
}