{
  "type": "Feature",
  "properties": {
    "iso:country":"GB",
    "sg:address":"80 Dyke Rd",
    "sg:city":"Brighton",
    "sg:classifiers":[
        {
            "category":"Building & Trades",
            "subcategory":"Plumbing",
            "type":"Services"
        }
    ],
    "sg:phone":"+44 1273 329829",
    "sg:postcode":"BN1 3JD",
    "sg:province":"East Sussex",
    "sg:tags":[
        "central",
        "heating"
    ],
    "wof:name":"Parker Plumbing & Heating",
    "wof:placetype":"venue"
},
  "geometry": {"coordinates":[-0.147159,50.829536],"type":"Point"}
}