{
  "type": "Feature",
  "properties": {
    "addr:full":"92 Market Street Newton-le-willows Cheshire WA12 9BW",
    "addr:housenumber":"92",
    "addr:postcode":"wa12 9bw",
    "addr:street":"Market Street",
    "iso:country":"GB",
    "sg:address":"92 Market Street",
    "sg:city":"Newton-le-willows",
    "sg:classifiers":[
        {
            "category":"Retail",
            "subcategory":"Repair Shop",
            "type":"Services"
        }
    ],
    "sg:phone":"+44 1925 224553",
    "sg:postcode":"WA12 9BW",
    "sg:province":"Cheshire",
    "sg:tags":[
        "upholsterer"
    ],
    "wof:name":"H Battersby & Son",
    "wof:placetype":"venue"
},
  "geometry": {"coordinates":[-2.644489,53.453953],"type":"Point"}
}