{
  "type": "Feature",
  "properties": {
    "iso:country":"GB",
    "sg:address":"19 Raydon Way, Great Cornard",
    "sg:city":"Sudbury",
    "sg:classifiers":[
        {
            "category":"Social Services",
            "subcategory":"Child Care",
            "type":"Services"
        }
    ],
    "sg:phone":"+44 1787 881743",
    "sg:postcode":"CO10 0LE",
    "sg:province":"Essex",
    "sg:tags":[
        "agency",
        "nanny"
    ],
    "wof:name":"Helping Hands Nanny Agency",
    "wof:placetype":"venue"
},
  "geometry": {"coordinates":[0.755525,52.03336],"type":"Point"}
}