{
  "type": "Feature",
  "properties": {
    "addr:full":"Sandys Hill Dairy Farm, Little Keyford Frome Somerset BA11 5BE",
    "addr:postcode":"ba11 5be",
    "addr:street":"Sandys;Dairy;Little",
    "iso:country":"GB",
    "sg:address":"Sandys Hill Dairy Farm, Little Keyford",
    "sg:city":"Frome",
    "sg:classifiers":[
        {
            "category":"Farming",
            "subcategory":"Dairy Farm",
            "type":"Manufacturing & Wholesale Goods"
        }
    ],
    "sg:phone":"+44 1373 462854",
    "sg:postcode":"BA11 5BE",
    "sg:province":"Somerset",
    "sg:tags":[
        "farmer"
    ],
    "wof:name":"R & D Norris",
    "wof:placetype":"venue"
},
  "geometry": {"coordinates":[-2.3280351162,51.2153015137],"type":"Point"}
}