{
  "type": "Feature",
  "properties": {
    "iso:country":"GB",
    "sg:address":"8 Manor Farm Cotts, Garford",
    "sg:city":"Abingdon",
    "sg:classifiers":[
        {
            "category":"Building & Trades",
            "subcategory":"Construction",
            "type":"Services"
        }
    ],
    "sg:phone":"+44 1865 391632",
    "sg:postcode":"OX13 5PB",
    "sg:province":"Oxfordshire",
    "sg:tags":[
        "decorator",
        "painter"
    ],
    "wof:name":"N & A Bunce",
    "wof:placetype":"venue"
},
  "geometry": {"coordinates":[-1.383133,51.663025],"type":"Point"}
}