{
  "type": "Feature",
  "properties": {
    "addr:full":"New Farm, Main Street, Walbsey Newark Nottinghamshire NG22 9NU",
    "addr:postcode":"ng22 9nu",
    "addr:street":"Main Street",
    "iso:country":"GB",
    "sg:address":"New Farm, Main Street, Walbsey",
    "sg:city":"Newark",
    "sg:classifiers":[
        {
            "category":"Manufacturing",
            "subcategory":"Toys & Sporting Goods",
            "type":"Manufacturing & Wholesale Goods"
        },
        {
            "category":"Manufacturing",
            "subcategory":"Signs",
            "type":"Manufacturing & Wholesale Goods"
        }
    ],
    "sg:phone":"+44 1623 862480",
    "sg:postcode":"NG22 9NU",
    "sg:province":"Nottinghamshire",
    "sg:tags":[
        "marquee",
        "tent",
        "manufacturer"
    ],
    "wof:name":"Past Tents Ltd.",
    "wof:placetype":"venue"
},
  "geometry": {"coordinates":[-0.97724998,53.2286605835],"type":"Point"}
}