{
  "type": "Feature",
  "properties": {
    "iso:country":"GB",
    "sg:address":"Gatehouse Close",
    "sg:city":"Aylesbury",
    "sg:classifiers":[
        {
            "category":"Education",
            "subcategory":"Special Training",
            "type":"Public Place"
        }
    ],
    "sg:phone":"+44 1296 481818",
    "sg:postcode":"HP19 8DN",
    "sg:province":"Buckinghamshire",
    "sg:tags":[
        "product",
        "centre"
    ],
    "wof:name":"Aylesbury Training Group",
    "wof:placetype":"venue"
},
  "geometry": {"coordinates":[-0.8249269724,51.8185386658],"type":"Point"}
}