{
  "type": "Feature",
  "properties": {
    "addr:full":"Youth Centre, Thicket Av Bristol City of Bristol BS16 4EH",
    "addr:postcode":"bs16 4eh",
    "addr:street":"Thicket Av Bristol",
    "iso:country":"GB",
    "sg:address":"Youth Centre, Thicket Av",
    "sg:city":"Bristol",
    "sg:classifiers":[
        {
            "category":"Community Center",
            "subcategory":"Youth",
            "type":"Public Place"
        }
    ],
    "sg:phone":"+44 117 965 4135",
    "sg:postcode":"BS16 4EH",
    "sg:province":"City of Bristol",
    "sg:tags":[
        "organisation",
        "centre"
    ],
    "wof:name":"Hillfields Youth Project",
    "wof:placetype":"venue"
},
  "geometry": {"coordinates":[-2.5914289951,51.453666687],"type":"Point"}
}