{
  "type": "Feature",
  "properties": {
    "addr:full":"105 Brearley Street Birmingham West Midlands B19 3XJ",
    "addr:housenumber":"105",
    "addr:postcode":"b19 3xj",
    "addr:street":"Brearley Street",
    "iso:country":"GB",
    "sg:address":"105 Brearley Street",
    "sg:city":"Birmingham",
    "sg:classifiers":[
        {
            "category":"Retail",
            "subcategory":"Auto Repair",
            "type":"Services"
        }
    ],
    "sg:phone":"+44 121 359 7982",
    "sg:postcode":"B19 3XJ",
    "sg:province":"West Midlands",
    "sg:tags":[
        "modification",
        "garage"
    ],
    "wof:name":"Fearon Vehicle Repairs",
    "wof:placetype":"venue"
},
  "geometry": {"coordinates":[-1.8994100094,52.4918022156],"type":"Point"}
}