{
  "type": "Feature",
  "properties": {
    "iso:country":"GB",
    "sg:address":"The Pinfold, Pinfold La, Aldridge",
    "sg:city":"Walsall",
    "sg:classifiers":[
        {
            "category":"Shopping",
            "subcategory":"Pets & Pet Supplies",
            "type":"Retail Goods"
        }
    ],
    "sg:postcode":"WS9 0QT",
    "sg:province":"Staffordshire",
    "wof:name":"Pinfold Boarding Kennel & Cattery (The)",
    "wof:placetype":"venue"
},
  "geometry": {"coordinates":[-1.91614,52.567219],"type":"Point"}
}