{
  "type": "Feature",
  "properties": {
    "iso:country":"GB",
    "sg:address":"13 Strathmore Avenue, Denton",
    "sg:city":"Manchester",
    "sg:classifiers":[
        {
            "category":"Home & Garden",
            "subcategory":"Home Furnishings",
            "type":"Retail Goods"
        },
        {
            "category":"Building & Trades",
            "subcategory":"Landfill",
            "type":"Services"
        }
    ],
    "sg:phone":"+44 161 320 0458",
    "sg:postcode":"M34 7TT",
    "sg:province":"Greater Manchester",
    "sg:tags":[
        "blind",
        "awning",
        "canopy",
        "blinds"
    ],
    "wof:name":"Denton Blinds",
    "wof:placetype":"venue"
},
  "geometry": {"coordinates":[-2.0953609943,53.4487953186],"type":"Point"}
}