{
  "type": "Feature",
  "properties": {
    "addr:full":"90 Walm Lane London Greater London NW2 4QY",
    "addr:housenumber":"90",
    "addr:postcode":"nw2 4qy",
    "addr:street":"Walm Lane",
    "iso:country":"GB",
    "sg:address":"90 Walm Lane",
    "sg:city":"London",
    "sg:classifiers":[
        {
            "category":"Real Estate",
            "subcategory":"Real Estate Services",
            "type":"Services"
        },
        {
            "category":"Real Estate",
            "subcategory":"Real Estate Agent",
            "type":"Services"
        }
    ],
    "sg:phone":"+44 20 8459 0091",
    "sg:postcode":"NW2 4QY",
    "sg:province":"Greater London",
    "sg:tags":[
        "management"
    ],
    "wof:name":"Camerons",
    "wof:placetype":"venue"
},
  "geometry": {"coordinates":[-0.220892,51.54895],"type":"Point"}
}