{
  "type": "Feature",
  "properties": {
    "addr:full":"1 The Square, Fole Uttoxeter Derbyshire ST14 5EG",
    "addr:housenumber":"1",
    "addr:postcode":"st14 5eg",
    "addr:street":"The Square;Uttoxeter",
    "iso:country":"GB",
    "sg:address":"1 The Square, Fole",
    "sg:city":"Uttoxeter",
    "sg:classifiers":[
        {
            "category":"Professional",
            "subcategory":"Printing & Photocopies",
            "type":"Services"
        }
    ],
    "sg:phone":"+44 1889 507475",
    "sg:postcode":"ST14 5EG",
    "sg:province":"Derbyshire",
    "sg:tags":[
        "trophy"
    ],
    "wof:name":"Trophy Supplies",
    "wof:placetype":"venue"
},
  "geometry": {"coordinates":[-1.933769,52.933727],"type":"Point"}
}