{
  "type": "Feature",
  "properties": {
    "addr:full":"152 Norwich Rd Fakenham Norfolk NR21 8LL",
    "addr:housenumber":"152",
    "addr:postcode":"nr21 8ll",
    "addr:street":"Norwich Rd",
    "iso:country":"GB",
    "sg:address":"152 Norwich Rd",
    "sg:city":"Fakenham",
    "sg:classifiers":[
        {
            "category":"Manufacturing",
            "subcategory":"Signs",
            "type":"Manufacturing & Wholesale Goods"
        }
    ],
    "sg:phone":"+44 1328 862886",
    "sg:postcode":"NR21 8LL",
    "sg:province":"Norfolk",
    "sg:tags":[
        "writer"
    ],
    "wof:name":"Woodhouse Classic Signs",
    "wof:placetype":"venue"
},
  "geometry": {"coordinates":[0.872551,52.831409],"type":"Point"}
}