{
  "type": "Feature",
  "properties": {
    "iso:country":"GB",
    "sg:address":"15-17 Clemens Street",
    "sg:city":"Leamington Spa",
    "sg:classifiers":[
        {
            "category":"Autos & Motor Vehicles",
            "subcategory":"Motorcycle Sales",
            "type":"Retail Goods"
        }
    ],
    "sg:phone":"+44 1926 429214",
    "sg:postcode":"CV31 2DW",
    "sg:province":"Warwickshire",
    "sg:tags":[
        "scooter",
        "cycle"
    ],
    "sg:website":"http://www.frettons.co.uk",
    "wof:name":"Frettons Of Leamington Ltd",
    "wof:placetype":"venue"
},
  "geometry": {"coordinates":[-1.531522,52.283417],"type":"Point"}
}