{
  "type": "Feature",
  "properties": {
    "addr:full":"45 Watson Terrace, Drongan Ayr East Ayrshire KA6 7AB",
    "addr:housenumber":"45",
    "addr:postcode":"ka6 7ab",
    "addr:street":"Watson Terrace Drongan;East",
    "iso:country":"GB",
    "sg:address":"45 Watson Terrace, Drongan",
    "sg:city":"Ayr",
    "sg:classifiers":[
        {
            "category":"Home & Garden",
            "subcategory":"Building Materials",
            "type":"Retail Goods"
        }
    ],
    "sg:phone":"+44 1292 591600",
    "sg:postcode":"KA6 7AB",
    "sg:province":"East Ayrshire",
    "sg:tags":[
        "fencing"
    ],
    "wof:name":"Fenfab",
    "wof:placetype":"venue"
},
  "geometry": {"coordinates":[-4.464952,55.436226],"type":"Point"}
}