{
  "type": "Feature",
  "properties": {
    "addr:full":"Roberts House, De Havilland Avenue, Preston Farm Business Park Stockton On Tees Durham TS18 3TH",
    "addr:postcode":"ts18 3th",
    "addr:street":"De Havilland Avenue;Park",
    "iso:country":"GB",
    "sg:address":"Roberts House, De Havilland Avenue, Preston Farm Business Park",
    "sg:city":"Stockton On Tees",
    "sg:classifiers":[
        {
            "category":"Utilities",
            "subcategory":"Cable",
            "type":"Services"
        }
    ],
    "sg:phone":"+44 1642 642600",
    "sg:postcode":"TS18 3TH",
    "sg:province":"Durham",
    "sg:tags":[
        "tv"
    ],
    "wof:name":"Comcast Teesside Ltd",
    "wof:placetype":"venue"
},
  "geometry": {"coordinates":[-1.3297239542,54.5441703796],"type":"Point"}
}