{
  "type": "Feature",
  "properties": {
    "iso:country":"GB",
    "sg:address":"70 Cross Lane, Radcliffe",
    "sg:city":"Manchester",
    "sg:classifiers":[
        {
            "category":"Fast Food",
            "type":"Food & Drink"
        }
    ],
    "sg:phone":"+44 161 723 1635",
    "sg:postcode":"M26 2RF",
    "sg:province":"Greater Manchester",
    "sg:tags":[
        "away",
        "take"
    ],
    "wof:name":"C C Chu",
    "wof:placetype":"venue"
},
  "geometry": {"coordinates":[-2.315159,53.564793],"type":"Point"}
}