{
  "type": "Feature",
  "properties": {
    "addr:full":"34 Muirhouse Crescent Edinburgh City of Edinburgh EH4 4QL",
    "addr:housenumber":"34",
    "addr:postcode":"eh4 4ql",
    "addr:street":"Muirhouse Crescent",
    "iso:country":"GB",
    "sg:address":"34 Muirhouse Crescent",
    "sg:city":"Edinburgh",
    "sg:classifiers":[
        {
            "category":"Social Services",
            "type":"Services"
        }
    ],
    "sg:phone":"+44 131 343 1991",
    "sg:postcode":"EH4 4QL",
    "sg:province":"City of Edinburgh",
    "wof:name":"Muirhouse Crescent Social Work Centre",
    "wof:placetype":"venue"
},
  "geometry": {"coordinates":[-3.253751,55.972069],"type":"Point"}
}