{
  "type": "Feature",
  "properties": {
    "iso:country":"GB",
    "sg:address":"17 Asher Drive",
    "sg:city":"Ascot",
    "sg:classifiers":[
        {
            "category":"Education",
            "subcategory":"Music School",
            "type":"Public Place"
        },
        {
            "category":"Manufacturing",
            "subcategory":"Petroleum Products",
            "type":"Manufacturing & Wholesale Goods"
        }
    ],
    "sg:phone":"+44 1344 890275",
    "sg:postcode":"SL5 8LJ",
    "sg:province":"Berkshire",
    "sg:tags":[
        "conservatory",
        "glazing",
        "double"
    ],
    "wof:name":"Park Windows",
    "wof:placetype":"venue"
},
  "geometry": {"coordinates":[-0.702351,51.418877],"type":"Point"}
}