{
  "type": "Feature",
  "properties": {
    "iso:country":"GB",
    "sg:address":"Docklands House, 58 Orchard Place, Leamouth Wharf",
    "sg:city":"Poplar",
    "sg:classifiers":[
        {
            "category":"Real Estate",
            "subcategory":"Real Estate Services",
            "type":"Services"
        }
    ],
    "sg:phone":"+44 20 7987 0332",
    "sg:postcode":"E14 0JW",
    "sg:province":"Greater London",
    "sg:tags":[
        "management",
        "facility"
    ],
    "wof:name":"Synergy Facilities Management",
    "wof:placetype":"venue"
},
  "geometry": {"coordinates":[0.006395,51.508991],"type":"Point"}
}