{
  "type": "Feature",
  "properties": {
    "iso:country":"GB",
    "sg:address":"West Farm, Gayton Road",
    "sg:city":"Towcester",
    "sg:classifiers":[
        {
            "category":"Farming",
            "subcategory":"Livestock Farm",
            "type":"Manufacturing & Wholesale Goods"
        }
    ],
    "sg:postcode":"NN12 8NS",
    "sg:province":"Buckinghamshire",
    "sg:tags":[
        "others"
    ],
    "wof:name":"L Evans",
    "wof:placetype":"venue"
},
  "geometry": {"coordinates":[-0.9870089889,52.1305084229],"type":"Point"}
}