{
  "type": "Feature",
  "properties": {
    "iso:country":"GB",
    "sg:address":"1 Hayward St",
    "sg:city":"Bury",
    "sg:classifiers":[
        {
            "category":"Home & Garden",
            "subcategory":"Building Materials",
            "type":"Retail Goods"
        }
    ],
    "sg:phone":"+44 161 764 4800",
    "sg:postcode":"BL8 1LX",
    "sg:province":"Lancashire",
    "sg:tags":[
        "dust",
        "extraction",
        "system"
    ],
    "wof:name":"Advance Air Movements",
    "wof:placetype":"venue"
},
  "geometry": {"coordinates":[-2.313668,53.59927],"type":"Point"}
}