{
  "type": "Feature",
  "properties": {
    "addr:full":"235 Berrow Road Burnham-on-sea Somerset TA8 2JQ",
    "addr:housenumber":"235",
    "addr:postcode":"ta8 2jq",
    "addr:street":"Berrow Road",
    "iso:country":"GB",
    "sg:address":"235 Berrow Road",
    "sg:city":"Burnham-on-sea",
    "sg:classifiers":[
        {
            "category":"Government",
            "subcategory":"Post Office",
            "type":"Public Place"
        }
    ],
    "sg:phone":"+44 1278 783028",
    "sg:postcode":"TA8 2JQ",
    "sg:province":"Somerset",
    "wof:name":"Berrow News",
    "wof:placetype":"venue"
},
  "geometry": {"coordinates":[-3.0055150986,51.2586784363],"type":"Point"}
}