{
  "type": "Feature",
  "properties": {
    "addr:full":"15 Oaklands Road Bedford Bedfordshire MK40 3AG",
    "addr:housenumber":"15",
    "addr:postcode":"mk40 3ag",
    "addr:street":"Oaklands Road",
    "iso:country":"GB",
    "sg:address":"15 Oaklands Road",
    "sg:city":"Bedford",
    "sg:classifiers":[
        {
            "category":"Health Services",
            "subcategory":"Nursing And Care Facility",
            "type":"Services"
        },
        {
            "category":"Social Services",
            "subcategory":"Retirement Home",
            "type":"Services"
        }
    ],
    "sg:phone":"+44 1234 347822",
    "sg:postcode":"MK40 3AG",
    "sg:province":"Bedfordshire",
    "sg:tags":[
        "residential"
    ],
    "wof:name":"Oaklands Residential Home for Special Needs",
    "wof:placetype":"venue"
},
  "geometry": {"coordinates":[-0.4564709961,52.1433982849],"type":"Point"}
}