{
  "type": "Feature",
  "properties": {
    "addr:full":"113 Brickhill Dr Bedford Bedfordshire MK41 7QF",
    "addr:housenumber":"113",
    "addr:postcode":"mk41 7qf",
    "addr:street":"Brickhill Dr",
    "iso:country":"GB",
    "sg:address":"113 Brickhill Dr",
    "sg:city":"Bedford",
    "sg:classifiers":[
        {
            "category":"Food & Beverages",
            "subcategory":"Meat & Fish",
            "type":"Retail Goods"
        }
    ],
    "sg:phone":"+44 1234 262177",
    "sg:postcode":"MK41 7QF",
    "sg:province":"Bedfordshire",
    "sg:tags":[
        "butcher"
    ],
    "wof:name":"Meats Direct",
    "wof:placetype":"venue"
},
  "geometry": {"coordinates":[-0.465447,52.154087],"type":"Point"}
}