{
  "type": "Feature",
  "properties": {
    "iso:country":"GB",
    "sg:address":"Wentworth Castle, Stainborough",
    "sg:city":"Barnsley",
    "sg:classifiers":[
        {
            "category":"Education",
            "subcategory":"University",
            "type":"Public Place"
        }
    ],
    "sg:phone":"+44 1226 776000",
    "sg:postcode":"S75 3ET",
    "sg:province":"South Yorkshire",
    "sg:tags":[
        "higher"
    ],
    "wof:name":"The Northern College for Residential Adult Education Ltd.",
    "wof:placetype":"venue"
},
  "geometry": {"coordinates":[-1.51903,53.524151],"type":"Point"}
}