{
  "type": "Feature",
  "properties": {
    "iso:country":"GB",
    "sg:address":"St Peter's Centre, Reardon St",
    "sg:city":"Whitechapel",
    "sg:classifiers":[
        {
            "category":"Professional",
            "subcategory":"Lawyer & Legal Services",
            "type":"Services"
        }
    ],
    "sg:phone":"+44 20 7702 0498",
    "sg:postcode":"E1 9QH",
    "sg:province":"Greater London",
    "sg:tags":[
        "advice",
        "counselling"
    ],
    "wof:name":"Tower Hamlets Careers & Access Centres",
    "wof:placetype":"venue"
},
  "geometry": {"coordinates":[-0.0596019998,51.5071334839],"type":"Point"}
}