{
  "type": "Feature",
  "properties": {
    "iso:country":"GB",
    "sg:address":"Purley Road",
    "sg:city":"Cirencester",
    "sg:classifiers":[
        {
            "category":"Retail",
            "subcategory":"Auto Repair",
            "type":"Services"
        }
    ],
    "sg:phone":"+44 1285 652365",
    "sg:postcode":"GL7 1ER",
    "sg:province":"Gloucestershire",
    "sg:tags":[
        "modification",
        "garage"
    ],
    "wof:name":"Purley Road Garage",
    "wof:placetype":"venue"
},
  "geometry": {"coordinates":[-1.9607839584,51.715801239],"type":"Point"}
}