{
  "type": "Feature",
  "properties": {
    "addr:full":"37 Burnt Ash Road London Greater London SE12 8RF",
    "addr:housenumber":"37",
    "addr:postcode":"se12 8rf",
    "addr:street":"Burnt Ash Road",
    "iso:country":"GB",
    "sg:address":"37 Burnt Ash Road",
    "sg:city":"London",
    "sg:classifiers":[
        {
            "category":"Retail",
            "subcategory":"Auto Repair",
            "type":"Services"
        }
    ],
    "sg:postcode":"SE12 8RF",
    "sg:province":"Greater London",
    "sg:tags":[
        "modification",
        "garage"
    ],
    "wof:name":"Gear Shift Transmissions",
    "wof:placetype":"venue"
},
  "geometry": {"coordinates":[0.011934,51.454163],"type":"Point"}
}