{
  "type": "Feature",
  "properties": {
    "iso:country":"GB",
    "sg:address":"117 Wroxham Road",
    "sg:city":"Norwich",
    "sg:classifiers":[
        {
            "category":"Professional",
            "type":"Services"
        },
        {
            "category":"Building & Trades",
            "subcategory":"Cleaning & Sanitation",
            "type":"Services"
        }
    ],
    "sg:phone":"+44 1603 424642",
    "sg:postcode":"NR7 8AD",
    "sg:province":"Norfolk",
    "sg:tags":[
        "dry",
        "control",
        "damp",
        "rot",
        "preservation"
    ],
    "wof:name":"G A Baxter Preservations",
    "wof:placetype":"venue"
},
  "geometry": {"coordinates":[1.330739975,52.661151886],"type":"Point"}
}