{
  "type": "Feature",
  "properties": {
    "addr:full":"Riverside Ho, Plumpton Rd Hoddesdon Essex EN11 0LB",
    "addr:postcode":"en11 0lb",
    "addr:street":"Plumpton Rd",
    "iso:country":"GB",
    "sg:address":"Riverside Ho, Plumpton Rd",
    "sg:city":"Hoddesdon",
    "sg:classifiers":[
        {
            "category":"Professional",
            "subcategory":"Accounting & Tax Preparation",
            "type":"Services"
        }
    ],
    "sg:phone":"+44 1992 479929",
    "sg:postcode":"EN11 0LB",
    "sg:province":"Essex",
    "sg:tags":[
        "accountant"
    ],
    "wof:name":"D Redburn & Co",
    "wof:placetype":"venue"
},
  "geometry": {"coordinates":[-0.0132550001,51.7678413391],"type":"Point"}
}