{
  "type": "Feature",
  "properties": {
    "addr:full":"19 Kewferry Road Northwood Greater London HA6 2NS",
    "addr:housenumber":"19",
    "addr:postcode":"ha6 2ns",
    "addr:street":"Kewferry Road",
    "iso:country":"GB",
    "sg:address":"19 Kewferry Road",
    "sg:city":"Northwood",
    "sg:classifiers":[
        {
            "category":"Professional",
            "type":"Services"
        }
    ],
    "sg:phone":"+44 1923 820121",
    "sg:postcode":"HA6 2NS",
    "sg:province":"Greater London",
    "sg:tags":[
        "services",
        "belt",
        "conveyor"
    ],
    "wof:name":"Conveyor Services South",
    "wof:placetype":"venue"
},
  "geometry": {"coordinates":[-0.436037004,51.6154251099],"type":"Point"}
}