{
  "type": "Feature",
  "properties": {
    "addr:full":"Unit 3 Northway Gate, Ashchurch Tewkesbury Gloucestershire GL20 8JP",
    "addr:housenumber":"unit 3",
    "addr:postcode":"gl20 8jp",
    "addr:street":"Northway Gate Ashchurch",
    "iso:country":"GB",
    "sg:address":"Unit 3 Northway Gate, Ashchurch",
    "sg:city":"Tewkesbury",
    "sg:classifiers":[
        {
            "category":"Wholesale",
            "subcategory":"Metals & Minerals",
            "type":"Manufacturing & Wholesale Goods"
        }
    ],
    "sg:phone":"+44 1684 271335",
    "sg:postcode":"GL20 8JP",
    "sg:province":"Gloucestershire",
    "sg:tags":[
        "aluminium",
        "stockholder"
    ],
    "wof:name":"Architectonics Systems (Uk) Ltd.",
    "wof:placetype":"venue"
},
  "geometry": {"coordinates":[-2.1244709492,52.002784729],"type":"Point"}
}