{
  "type": "Feature",
  "properties": {
    "addr:full":"1 Pickford Lane Bexleyheath Kent DA7 4RD",
    "addr:housenumber":"1",
    "addr:postcode":"da7 4rd",
    "addr:street":"Pickford Lane",
    "iso:country":"GB",
    "sg:address":"1 Pickford Lane",
    "sg:city":"Bexleyheath",
    "sg:classifiers":[
        {
            "category":"Education",
            "subcategory":"College",
            "type":"Public Place"
        }
    ],
    "sg:phone":"+44 20 8298 9085",
    "sg:postcode":"DA7 4RD",
    "sg:province":"Kent",
    "sg:tags":[
        "school"
    ],
    "wof:name":"Boffins",
    "wof:placetype":"venue"
},
  "geometry": {"coordinates":[0.132441,51.463699],"type":"Point"}
}