{
  "type": "Feature",
  "properties": {
    "addr:full":"4 May Road, Heswall Wirral Merseyside CH60 5RA",
    "addr:housenumber":"4",
    "addr:postcode":"ch60 5ra",
    "addr:street":"May Road",
    "iso:country":"GB",
    "sg:address":"4 May Road, Heswall",
    "sg:city":"Wirral",
    "sg:classifiers":[
        {
            "category":"Building & Trades",
            "subcategory":"Construction",
            "type":"Services"
        }
    ],
    "sg:phone":"+44 151 342 7797",
    "sg:postcode":"CH60 5RA",
    "sg:province":"Merseyside",
    "sg:tags":[
        "builder"
    ],
    "wof:name":"P J Allison (Wirral) Ltd.",
    "wof:placetype":"venue"
},
  "geometry": {"coordinates":[-3.097867012,53.3292312622],"type":"Point"}
}