{
  "type": "Feature",
  "properties": {
    "addr:full":"4 The Crescent, West Rainton Houghton-le-spring Durham DH4 6SB",
    "addr:housenumber":"4",
    "addr:postcode":"dh4 6sb",
    "addr:street":"The Crescent West",
    "iso:country":"GB",
    "sg:address":"4 The Crescent, West Rainton",
    "sg:city":"Houghton-le-spring",
    "sg:classifiers":[
        {
            "category":"Taxi",
            "type":"Transportation"
        },
        {
            "category":"Military Area",
            "subcategory":"Air Force Base",
            "type":"Public Place"
        }
    ],
    "sg:phone":"+44 191 373 3400",
    "sg:postcode":"DH4 6SB",
    "sg:province":"Durham",
    "sg:tags":[
        "hire",
        "private"
    ],
    "wof:name":"CRESCENT CABS",
    "wof:placetype":"venue"
},
  "geometry": {"coordinates":[-1.51126,54.813473],"type":"Point"}
}