{
  "type": "Feature",
  "properties": {
    "addr:full":"Howard Av Glasgow South Lanarkshire G74 4QZ",
    "addr:postcode":"g74 4qz",
    "addr:street":"Howard Av",
    "iso:country":"GB",
    "sg:address":"Howard Av",
    "sg:city":"Glasgow",
    "sg:classifiers":[
        {
            "category":"Professional",
            "subcategory":"Computer Services",
            "type":"Services"
        }
    ],
    "sg:phone":"+44 1355 279234",
    "sg:postcode":"G74 4QZ",
    "sg:province":"South Lanarkshire",
    "sg:tags":[
        "system",
        "software"
    ],
    "wof:name":"P C World",
    "wof:placetype":"venue"
},
  "geometry": {"coordinates":[-4.165652,55.779247],"type":"Point"}
}