{
  "type": "Feature",
  "properties": {
    "iso:country":"GB",
    "sg:address":"123 Lord St",
    "sg:city":"Fleetwood",
    "sg:classifiers":[
        {
            "category":"Home & Garden",
            "subcategory":"Building Materials",
            "type":"Retail Goods"
        }
    ],
    "sg:phone":"+44 1253 777190",
    "sg:postcode":"FY7 6LB",
    "sg:province":"Lancashire",
    "sg:tags":[
        "brick"
    ],
    "wof:name":"Gas World",
    "wof:placetype":"venue"
},
  "geometry": {"coordinates":[-3.0134320259,53.9217224121],"type":"Point"}
}