{
  "type": "Feature",
  "properties": {
    "addr:full":"Tan-y-felin, Talwrn Llangefni Gwynedd LL77 8JB",
    "addr:postcode":"ll77 8jb",
    "addr:street":"Llangefni",
    "iso:country":"GB",
    "sg:address":"Tan-y-felin, Talwrn",
    "sg:city":"Llangefni",
    "sg:classifiers":[
        {
            "category":"Home & Garden",
            "subcategory":"Garden Supply",
            "type":"Retail Goods"
        }
    ],
    "sg:phone":"+44 1248 724859",
    "sg:postcode":"LL77 8JB",
    "sg:province":"Gwynedd",
    "sg:tags":[
        "nursery",
        "centre"
    ],
    "wof:name":"Hafod Nurseries",
    "wof:placetype":"venue"
},
  "geometry": {"coordinates":[-4.3084640503,53.2556037903],"type":"Point"}
}