{
  "type": "Feature",
  "properties": {
    "addr:full":"38 Caerau Lane, Ely Cardiff Cardiff CF5 5HQ",
    "addr:housenumber":"38",
    "addr:postcode":"cf5 5hq",
    "addr:street":"Caerau Lane",
    "iso:country":"GB",
    "sg:address":"38 Caerau Lane, Ely",
    "sg:city":"Cardiff",
    "sg:classifiers":[
        {
            "category":"Health Services",
            "subcategory":"Doctor",
            "type":"Services"
        }
    ],
    "sg:phone":"+44 29 2059 7055",
    "sg:postcode":"CF5 5HQ",
    "sg:province":"Cardiff",
    "sg:tags":[
        "practitioners"
    ],
    "wof:name":"Caerau Lane Superstore",
    "wof:placetype":"venue"
},
  "geometry": {"coordinates":[-3.2504429817,51.4737548828],"type":"Point"}
}