{
  "type": "Feature",
  "properties": {
    "addr:full":"81a High Street Burton-on-trent Derbyshire DE14 1LD",
    "addr:housenumber":"81a",
    "addr:postcode":"de14 1ld",
    "addr:street":"High Street",
    "iso:country":"GB",
    "sg:address":"81a High Street",
    "sg:city":"Burton-on-trent",
    "sg:classifiers":[
        {
            "category":"Taxi",
            "type":"Transportation"
        },
        {
            "category":"Military Area",
            "subcategory":"Air Force Base",
            "type":"Public Place"
        }
    ],
    "sg:postcode":"DE14 1LD",
    "sg:province":"Derbyshire",
    "sg:tags":[
        "mini",
        "hire",
        "private",
        "cab"
    ],
    "wof:name":"Mohammed Rafiq",
    "wof:placetype":"venue"
},
  "geometry": {"coordinates":[-1.629879,52.802593],"type":"Point"}
}