{
  "type": "Feature",
  "properties": {
    "addr:full":"1 Prieston Rd Bridge Of Weir Inverclyde PA11 3AJ",
    "addr:housenumber":"1",
    "addr:postcode":"pa11 3aj",
    "addr:street":"Prieston Rd",
    "iso:country":"GB",
    "sg:address":"1 Prieston Rd",
    "sg:city":"Bridge Of Weir",
    "sg:classifiers":[
        {
            "category":"Food & Beverages",
            "subcategory":"Groceries & Convenience Stores",
            "type":"Retail Goods"
        }
    ],
    "sg:phone":"+44 1505 612048",
    "sg:postcode":"PA11 3AJ",
    "sg:province":"Inverclyde",
    "wof:name":"Family Discount",
    "wof:placetype":"venue"
},
  "geometry": {"coordinates":[-4.582529068,55.8567199707],"type":"Point"}
}