{
  "type": "Feature",
  "properties": {
    "addr:full":"Orrell Road Liverpool Merseyside L21 8NU",
    "addr:postcode":"l21 8nu",
    "addr:street":"Orrell Road",
    "iso:country":"GB",
    "sg:address":"Orrell Road",
    "sg:city":"Liverpool",
    "sg:classifiers":[
        {
            "category":"Organizations",
            "subcategory":"Membership Organization",
            "type":"Services"
        }
    ],
    "sg:phone":"+44 151 928 2933",
    "sg:postcode":"L21 8NU",
    "sg:province":"Merseyside",
    "sg:tags":[
        "club"
    ],
    "wof:name":"The Royal British Legion",
    "wof:placetype":"venue"
},
  "geometry": {"coordinates":[-2.9952290058,53.470916748],"type":"Point"}
}