{
  "type": "Feature",
  "properties": {
    "iso:country":"GB",
    "sg:address":"49a St Werburgh Street",
    "sg:city":"Chester",
    "sg:classifiers":[
        {
            "category":"Shopping",
            "subcategory":"Jewelry",
            "type":"Retail Goods"
        },
        {
            "category":"Shopping",
            "subcategory":"Comic Books",
            "type":"Retail Goods"
        }
    ],
    "sg:phone":"+44 1244 345467",
    "sg:postcode":"CH1 2DY",
    "sg:province":"Cheshire",
    "sg:tags":[
        "jeweller",
        "sale",
        "jewellery"
    ],
    "wof:name":"Nigel Hughes Ltd",
    "wof:placetype":"venue"
},
  "geometry": {"coordinates":[-2.891737,53.19162],"type":"Point"}
}