{
  "type": "Feature",
  "properties": {
    "addr:full":"31 Abbey Close Axminster Devon EX13 5QU",
    "addr:housenumber":"31",
    "addr:postcode":"ex13 5qu",
    "addr:street":"Abbey Close",
    "iso:country":"GB",
    "sg:address":"31 Abbey Close",
    "sg:city":"Axminster",
    "sg:classifiers":[
        {
            "category":"Health Services",
            "subcategory":"Clinic",
            "type":"Services"
        }
    ],
    "sg:phone":"+44 1297 32403",
    "sg:postcode":"EX13 5QU",
    "sg:province":"Devon",
    "sg:tags":[
        "aromatherapy"
    ],
    "wof:name":"Jane Loader",
    "wof:placetype":"venue"
},
  "geometry": {"coordinates":[-3.0054221153,50.773563385],"type":"Point"}
}