{
  "type": "Feature",
  "properties": {
    "addr:full":"9 Castle St Hastings East Sussex TN34 3DY",
    "addr:housenumber":"9",
    "addr:postcode":"tn34 3dy",
    "addr:street":"Castle St",
    "iso:country":"GB",
    "sg:address":"9 Castle St",
    "sg:city":"Hastings",
    "sg:classifiers":[
        {
            "category":"Building & Trades",
            "subcategory":"Locksmith",
            "type":"Services"
        }
    ],
    "sg:phone":"+44 1424 437737",
    "sg:postcode":"TN34 3DY",
    "sg:province":"East Sussex",
    "sg:tags":[
        "cutting",
        "key"
    ],
    "wof:name":"Toms Heel Bar And Key Cutting Centre",
    "wof:placetype":"venue"
},
  "geometry": {"coordinates":[0.5826650262,50.8552780151],"type":"Point"}
}