{
  "type": "Feature",
  "properties": {
    "addr:full":"Slopes View, Colway Lane Lyme Regis Devon DT7 3AR",
    "addr:postcode":"dt7 3ar",
    "addr:street":"Slopes;Colway Lane",
    "iso:country":"GB",
    "sg:address":"Slopes View, Colway Lane",
    "sg:city":"Lyme Regis",
    "sg:classifiers":[
        {
            "category":"Building & Trades",
            "subcategory":"Construction",
            "type":"Services"
        }
    ],
    "sg:phone":"+44 1297 443043",
    "sg:postcode":"DT7 3AR",
    "sg:province":"Devon",
    "sg:tags":[
        "builder"
    ],
    "wof:name":"D Quick",
    "wof:placetype":"venue"
},
  "geometry": {"coordinates":[-2.943625927,50.7278938293],"type":"Point"}
}