{
  "type": "Feature",
  "properties": {
    "iso:country":"GB",
    "sg:address":"204 Stapleton Road",
    "sg:city":"Bristol",
    "sg:classifiers":[
        {
            "category":"Shopping",
            "subcategory":"Clothing, Apparel, & Fashions",
            "type":"Retail Goods"
        }
    ],
    "sg:postcode":"BS5 0NY",
    "sg:province":"City of Bristol",
    "sg:tags":[
        "shop"
    ],
    "wof:name":"C K S Fashions Bristol",
    "wof:placetype":"venue"
},
  "geometry": {"coordinates":[-2.5703520775,51.4643363953],"type":"Point"}
}