{
  "type": "Feature",
  "properties": {
    "addr:full":"1 Phillips Business Centre Chichester West Sussex PO19 8UL",
    "addr:housenumber":"1",
    "addr:postcode":"po19 8ul",
    "addr:street":"Phillips Business Centre",
    "iso:country":"GB",
    "sg:address":"1 Phillips Business Centre",
    "sg:city":"Chichester",
    "sg:classifiers":[
        {
            "category":"Manufacturing",
            "subcategory":"Petroleum Products",
            "type":"Manufacturing & Wholesale Goods"
        }
    ],
    "sg:postcode":"PO19 8UL",
    "sg:province":"West Sussex",
    "sg:tags":[
        "double",
        "glazing"
    ],
    "wof:name":"Chichester Window Co. Ltd.",
    "wof:placetype":"venue"
},
  "geometry": {"coordinates":[-0.775429,50.836166],"type":"Point"}
}