{
  "type": "Feature",
  "properties": {
    "addr:full":"40 Highgate West Hill Highgate Greater London N6 6LS",
    "addr:housenumber":"40",
    "addr:postcode":"n6 6ls",
    "addr:street":"Highgate;Highgate",
    "iso:country":"GB",
    "sg:address":"40 Highgate West Hill",
    "sg:city":"Highgate",
    "sg:classifiers":[
        {
            "category":"Wholesale",
            "subcategory":"Electrical",
            "type":"Manufacturing & Wholesale Goods"
        }
    ],
    "sg:phone":"+44 20 8340 8000",
    "sg:postcode":"N6 6LS",
    "sg:province":"Greater London",
    "sg:tags":[
        "equipment",
        "refrigeration"
    ],
    "wof:name":"Abacus Fan & Blower Co",
    "wof:placetype":"venue"
},
  "geometry": {"coordinates":[-0.153788,51.566109],"type":"Point"}
}