{
  "type": "Feature",
  "properties": {
    "addr:full":"595 Bath Road, Cippenham Slough Berkshire SL1 6AB",
    "addr:housenumber":"595",
    "addr:postcode":"sl1 6ab",
    "addr:street":"Bath Road",
    "iso:country":"GB",
    "sg:address":"595 Bath Road, Cippenham",
    "sg:city":"Slough",
    "sg:classifiers":[
        {
            "category":"Bars & Pubs",
            "type":"Food & Drink"
        }
    ],
    "sg:postcode":"SL1 6AB",
    "sg:province":"Berkshire",
    "sg:tags":[
        "pubs",
        "inn"
    ],
    "wof:name":"Huntercombe",
    "wof:placetype":"venue"
},
  "geometry": {"coordinates":[-0.65345,51.519859],"type":"Point"}
}