{
  "type": "Feature",
  "properties": {
    "addr:full":"5 Maddocks Ct Telford Shropshire TF1 1SQ",
    "addr:housenumber":"5",
    "addr:postcode":"tf1 1sq",
    "addr:street":"Maddocks Ct",
    "iso:country":"GB",
    "sg:address":"5 Maddocks Ct",
    "sg:city":"Telford",
    "sg:classifiers":[
        {
            "category":"Building & Trades",
            "subcategory":"Landscaping Services",
            "type":"Services"
        }
    ],
    "sg:phone":"+44 1952 240140",
    "sg:postcode":"TF1 1SQ",
    "sg:province":"Shropshire",
    "sg:tags":[
        "designer",
        "architect",
        "landscape"
    ],
    "wof:name":"Plan-Man Landscape Design",
    "wof:placetype":"venue"
},
  "geometry": {"coordinates":[-2.515456,52.697926],"type":"Point"}
}