{
  "type": "Feature",
  "properties": {
    "addr:full":"Devonshire Works, Pitt Street Keighley West Yorkshire BD21 4PF",
    "addr:postcode":"bd21 4pf",
    "addr:street":"Pitt Street",
    "iso:country":"GB",
    "sg:address":"Devonshire Works, Pitt Street",
    "sg:city":"Keighley",
    "sg:classifiers":[
        {
            "category":"Manufacturing",
            "subcategory":"Metals",
            "type":"Manufacturing & Wholesale Goods"
        }
    ],
    "sg:phone":"+44 1535 602191",
    "sg:postcode":"BD21 4PF",
    "sg:province":"West Yorkshire",
    "sg:tags":[
        "fab",
        "foundry"
    ],
    "wof:name":"J S Naylor Son",
    "wof:placetype":"venue"
},
  "geometry": {"coordinates":[-1.9096740484,53.8663635254],"type":"Point"}
}