{
  "type": "Feature",
  "properties": {
    "addr:full":"The Old Bakery, 8a Replingham Road London Greater London SW18 5LS",
    "addr:housenumber":"8a",
    "addr:postcode":"sw18 5ls",
    "addr:street":"Replingham Road",
    "iso:country":"GB",
    "sg:address":"The Old Bakery, 8a Replingham Road",
    "sg:city":"London",
    "sg:classifiers":[
        {
            "category":"Manufacturing",
            "subcategory":"Textiles",
            "type":"Manufacturing & Wholesale Goods"
        }
    ],
    "sg:postcode":"SW18 5LS",
    "sg:province":"Greater London",
    "sg:tags":[
        "merchant",
        "agent"
    ],
    "wof:name":"John Swinfield",
    "wof:placetype":"venue"
},
  "geometry": {"coordinates":[-0.205583,51.444622],"type":"Point"}
}