{
  "type": "Feature",
  "properties": {
    "addr:full":"4 Sutton Gardens Luton Bedfordshire LU3 3AF",
    "addr:housenumber":"4",
    "addr:postcode":"lu3 3af",
    "addr:street":"Sutton Gardens",
    "iso:country":"GB",
    "sg:address":"4 Sutton Gardens",
    "sg:city":"Luton",
    "sg:classifiers":[
        {
            "category":"Building & Trades",
            "subcategory":"Construction",
            "type":"Services"
        }
    ],
    "sg:phone":"+44 1582 571355",
    "sg:postcode":"LU3 3AF",
    "sg:province":"Bedfordshire",
    "sg:tags":[
        "dry",
        "lining",
        "plasterers",
        "screeders"
    ],
    "wof:name":"Robt Brigden",
    "wof:placetype":"venue"
},
  "geometry": {"coordinates":[-0.466788,51.912403],"type":"Point"}
}