{
  "type": "Feature",
  "properties": {
    "addr:full":"45 Guildhall Street Folkestone Kent CT20 1EF",
    "addr:housenumber":"45",
    "addr:postcode":"ct20 1ef",
    "addr:street":"Guildhall Street",
    "iso:country":"GB",
    "sg:address":"45 Guildhall Street",
    "sg:city":"Folkestone",
    "sg:classifiers":[
        {
            "category":"Organizations",
            "subcategory":"Community Association",
            "type":"Services"
        },
        {
            "category":"Organizations",
            "subcategory":"Membership Organization",
            "type":"Services"
        }
    ],
    "sg:phone":"+44 1303 253425",
    "sg:postcode":"CT20 1EF",
    "sg:province":"Kent",
    "sg:tags":[
        "club",
        "social"
    ],
    "wof:name":"Folkestone Constitutional Club",
    "wof:placetype":"venue"
},
  "geometry": {"coordinates":[1.17604,51.083721],"type":"Point"}
}