{
  "type": "Feature",
  "properties": {
    "addr:full":"Old Bank House, Bruce Street, Lochmaben Lockerbie Dumfries and Galloway DG11 1PD",
    "addr:postcode":"dg11 1pd",
    "addr:street":"Bruce Street",
    "iso:country":"GB",
    "sg:address":"Old Bank House, Bruce Street, Lochmaben",
    "sg:city":"Lockerbie",
    "sg:classifiers":[
        {
            "category":"Banks & Credit Unions",
            "subcategory":"Bureau De Change",
            "type":"Services"
        }
    ],
    "sg:postcode":"DG11 1PD",
    "sg:province":"Dumfries and Galloway",
    "sg:tags":[
        "town",
        "consultant",
        "planning"
    ],
    "wof:name":"Munroe Ian Planning & Development Consultant",
    "wof:placetype":"venue"
},
  "geometry": {"coordinates":[-3.4408390522,55.1284599304],"type":"Point"}
}