{
  "type": "Feature",
  "properties": {
    "addr:full":"2-3 Trinity Church Square Richmond North Yorkshire DL10 4HY",
    "addr:housenumber":"2-3",
    "addr:postcode":"dl10 4hy",
    "addr:street":"Trinity Church Square",
    "iso:country":"GB",
    "sg:address":"2-3 Trinity Church Square",
    "sg:city":"Richmond",
    "sg:classifiers":[
        {
            "category":"Retail",
            "subcategory":"Laundry & Dry Cleaning",
            "type":"Services"
        }
    ],
    "sg:phone":"+44 1748 850980",
    "sg:postcode":"DL10 4HY",
    "sg:province":"North Yorkshire",
    "sg:tags":[
        "alteration"
    ],
    "wof:name":"Johnsons The Cleaners",
    "wof:placetype":"venue"
},
  "geometry": {"coordinates":[-1.738159,54.40292],"type":"Point"}
}