{
  "type": "Feature",
  "properties": {
    "addr:full":"110 Pinner Road Northwood Greater London HA6 1BS",
    "addr:housenumber":"110",
    "addr:postcode":"ha6 1bs",
    "addr:street":"Pinner Road",
    "iso:country":"GB",
    "sg:address":"110 Pinner Road",
    "sg:city":"Northwood",
    "sg:classifiers":[
        {
            "category":"Professional",
            "subcategory":"Management & Consulting",
            "type":"Services"
        }
    ],
    "sg:phone":"+44 1923 822343",
    "sg:postcode":"HA6 1BS",
    "sg:province":"Greater London",
    "sg:tags":[
        "consultant",
        "specialist"
    ],
    "wof:name":"Petros Hair & Beauty",
    "wof:placetype":"venue"
},
  "geometry": {"coordinates":[-0.4157850146,51.6044845581],"type":"Point"}
}