{
  "type": "Feature",
  "properties": {
    "addr:full":"Unit 3, Tresidder Court, Tregoniggie Industrial Estate Falmouth Cornwall TR11 4SP",
    "addr:housenumber":"unit 3;estate",
    "addr:postcode":"tr11 4sp",
    "addr:street":"Tresidder Court Tregoniggie Industrial",
    "iso:country":"GB",
    "sg:address":"Unit 3, Tresidder Court, Tregoniggie Industrial Estate",
    "sg:city":"Falmouth",
    "sg:phone":"+44 1326 373310",
    "sg:postcode":"TR11 4SP",
    "sg:province":"Cornwall",
    "wof:name":"Stay Tensioner Services",
    "wof:placetype":"venue"
},
  "geometry": {"coordinates":[-5.0800328255,50.1522064209],"type":"Point"}
}