{
  "type": "Feature",
  "properties": {
    "addr:full":"37 North Station Road Colchester Essex CO1 1RQ",
    "addr:housenumber":"37",
    "addr:postcode":"co1 1rq",
    "addr:street":"North Station Road Colchester",
    "iso:country":"GB",
    "sg:address":"37 North Station Road",
    "sg:city":"Colchester",
    "sg:classifiers":[
        {
            "category":"Shopping",
            "subcategory":"News",
            "type":"Retail Goods"
        }
    ],
    "sg:phone":"+44 1206 575808",
    "sg:postcode":"CO1 1RQ",
    "sg:province":"Essex",
    "sg:tags":[
        "newsagent"
    ],
    "wof:name":"R K S Newsagent",
    "wof:placetype":"venue"
},
  "geometry": {"coordinates":[0.896033,51.895172],"type":"Point"}
}