{
  "type": "Feature",
  "properties": {
    "addr:full":"37 Bonny Gate Cupar Fife KY15 4BU",
    "addr:housenumber":"37",
    "addr:postcode":"ky15 4bu",
    "addr:street":"Bonny Gate",
    "iso:country":"GB",
    "sg:address":"37 Bonny Gate",
    "sg:city":"Cupar",
    "sg:classifiers":[
        {
            "category":"Professional",
            "type":"Services"
        }
    ],
    "sg:phone":"+44 1334 653247",
    "sg:postcode":"KY15 4BU",
    "sg:province":"Fife",
    "sg:tags":[
        "interior",
        "furnishers",
        "designer"
    ],
    "wof:name":"Wendy Wilson Interior Design",
    "wof:placetype":"venue"
},
  "geometry": {"coordinates":[-3.0131220818,56.3196563721],"type":"Point"}
}