{
  "type": "Feature",
  "properties": {
    "iso:country":"GB",
    "sg:address":"170 Colchester Road",
    "sg:city":"Ipswich",
    "sg:classifiers":[
        {
            "category":"Professional",
            "type":"Services"
        }
    ],
    "sg:postcode":"IP4 4RS",
    "sg:province":"Suffolk",
    "sg:tags":[
        "caterer"
    ],
    "wof:name":"Diamond Foods Ltd",
    "wof:placetype":"venue"
},
  "geometry": {"coordinates":[1.185863018,52.0675506592],"type":"Point"}
}