{
  "type": "Feature",
  "properties": {
    "addr:full":"Hope Street Peterhead Aberdeenshire AB42 6HE",
    "addr:postcode":"ab42 6he",
    "addr:street":"Hope Street",
    "iso:country":"GB",
    "sg:address":"Hope Street",
    "sg:city":"Peterhead",
    "sg:classifiers":[
        {
            "category":"Social Services",
            "subcategory":"Adult Care",
            "type":"Services"
        }
    ],
    "sg:phone":"+44 1779 479899",
    "sg:postcode":"AB42 6HE",
    "sg:province":"Aberdeenshire",
    "sg:tags":[
        "day",
        "centre"
    ],
    "wof:name":"Ugievale Day Centre",
    "wof:placetype":"venue"
},
  "geometry": {"coordinates":[-1.799454,57.513203],"type":"Point"}
}