{
  "type": "Feature",
  "properties": {
    "iso:country":"GB",
    "sg:address":"Unit 11, Weston Industrial Estate, Ponthir Road",
    "sg:city":"Newport",
    "sg:classifiers":[
        {
            "category":"Home & Garden",
            "subcategory":"Carpets & Floor Coverings",
            "type":"Retail Goods"
        }
    ],
    "sg:postcode":"NP18 3NN",
    "sg:province":"Monmouthshire",
    "sg:tags":[
        "rubber",
        "plastic"
    ],
    "wof:name":"Trendle Developments Ltd.",
    "wof:placetype":"venue"
},
  "geometry": {"coordinates":[-2.95937,51.618881],"type":"Point"}
}