{
  "type": "Feature",
  "properties": {
    "iso:country":"GB",
    "sg:address":"36 Hull Road, Howden",
    "sg:city":"Goole",
    "sg:classifiers":[
        {
            "category":"Professional",
            "subcategory":"Engineering",
            "type":"Services"
        }
    ],
    "sg:postcode":"DN14 7AT",
    "sg:province":"East Riding of Yorkshire",
    "sg:tags":[
        "contractor",
        "electrical",
        "engineer"
    ],
    "wof:name":"P Winter",
    "wof:placetype":"venue"
},
  "geometry": {"coordinates":[-0.853172,53.748928],"type":"Point"}
}