{
  "type": "Feature",
  "properties": {
    "addr:full":"1 Butten Meadow, Austerfield Doncaster Lincolnshire DN10 6SQ",
    "addr:housenumber":"1",
    "addr:postcode":"dn10 6sq",
    "addr:street":"Butten Meadow",
    "iso:country":"GB",
    "sg:address":"1 Butten Meadow, Austerfield",
    "sg:city":"Doncaster",
    "sg:classifiers":[
        {
            "category":"Building & Trades",
            "subcategory":"Plumbing",
            "type":"Services"
        }
    ],
    "sg:phone":"+44 1302 719209",
    "sg:postcode":"DN10 6SQ",
    "sg:province":"Lincolnshire",
    "sg:tags":[
        "central",
        "heating"
    ],
    "wof:name":"A C Plumbing",
    "wof:placetype":"venue"
},
  "geometry": {"coordinates":[-1.0059130192,53.4457244873],"type":"Point"}
}