{
  "type": "Feature",
  "properties": {
    "addr:full":"Unit 9/10, Hither Green Clevedon Somerset BS21 6XT",
    "addr:housenumber":"unit 9 / 10",
    "addr:postcode":"bs21 6xt",
    "iso:country":"GB",
    "sg:address":"Unit 9/10, Hither Green",
    "sg:city":"Clevedon",
    "sg:classifiers":[
        {
            "category":"Utilities",
            "subcategory":"Mobile Phone",
            "type":"Services"
        }
    ],
    "sg:postcode":"BS21 6XT",
    "sg:province":"Somerset",
    "sg:tags":[
        "battery",
        "supplier"
    ],
    "wof:name":"P B Design & Developments Ltd.",
    "wof:placetype":"venue"
},
  "geometry": {"coordinates":[-2.8400299549,51.4333114624],"type":"Point"}
}