{
  "type": "Feature",
  "properties": {
    "addr:full":"Avenue Road Freshwater Isle of Wight PO40 9UU",
    "addr:postcode":"po40 9uu",
    "addr:street":"Avenue Road",
    "iso:country":"GB",
    "sg:address":"Avenue Road",
    "sg:city":"Freshwater",
    "sg:classifiers":[
        {
            "category":"Retail",
            "subcategory":"Auto Repair",
            "type":"Services"
        }
    ],
    "sg:phone":"+44 1983 753074",
    "sg:postcode":"PO40 9UU",
    "sg:province":"Isle of Wight",
    "sg:tags":[
        "modification",
        "garage",
        "related"
    ],
    "wof:name":"Tennyson Garage",
    "wof:placetype":"venue"
},
  "geometry": {"coordinates":[-1.529724,50.684238],"type":"Point"}
}