{
  "type": "Feature",
  "properties": {
    "iso:country":"GB",
    "sg:address":"11 Crossway",
    "sg:city":"Walton-on-thames",
    "sg:classifiers":[
        {
            "category":"Education",
            "subcategory":"Special Training",
            "type":"Public Place"
        }
    ],
    "sg:phone":"+44 1932 225052",
    "sg:postcode":"KT12 3JA",
    "sg:province":"Surrey",
    "sg:tags":[
        "school",
        "language"
    ],
    "wof:name":"Eurotalk Language Centre",
    "wof:placetype":"venue"
},
  "geometry": {"coordinates":[-0.409338,51.378651],"type":"Point"}
}