{
  "type": "Feature",
  "properties": {
    "addr:full":"Mill Street, Gislingham Eye Suffolk IP23 8JT",
    "addr:postcode":"ip23 8jt",
    "addr:street":"Mill Street",
    "iso:country":"GB",
    "sg:address":"Mill Street, Gislingham",
    "sg:city":"Eye",
    "sg:classifiers":[
        {
            "category":"Travel",
            "subcategory":"Hotels & Motels",
            "type":"Entertainment"
        }
    ],
    "sg:postcode":"IP23 8JT",
    "sg:province":"Suffolk",
    "wof:name":"The Old Guildhall",
    "wof:placetype":"venue"
},
  "geometry": {"coordinates":[1.0417300463,52.3047561646],"type":"Point"}
}