{
  "type": "Feature",
  "properties": {
    "addr:full":"11 Shroton Street London Greater London NW1 6UG",
    "addr:housenumber":"11",
    "addr:postcode":"nw1 6ug",
    "addr:street":"Shroton Street",
    "iso:country":"GB",
    "sg:address":"11 Shroton Street",
    "sg:city":"London",
    "sg:classifiers":[
        {
            "category":"Bars & Pubs",
            "type":"Food & Drink"
        }
    ],
    "sg:phone":"+44 20 7723 7469",
    "sg:postcode":"NW1 6UG",
    "sg:province":"Greater London",
    "sg:tags":[
        "pubs",
        "inn"
    ],
    "wof:name":"The Perseverance",
    "wof:placetype":"venue"
},
  "geometry": {"coordinates":[-0.166348,51.52264],"type":"Point"}
}