{
  "type": "Feature",
  "properties": {
    "addr:full":"Stone Rd Stoke-on-trent Staffordshire ST12 9HA",
    "addr:postcode":"st12 9ha",
    "addr:street":"Stone Rd",
    "iso:country":"GB",
    "sg:address":"Stone Rd",
    "sg:city":"Stoke-on-trent",
    "sg:classifiers":[
        {
            "category":"Cafe",
            "type":"Food & Drink"
        }
    ],
    "sg:postcode":"ST12 9HA",
    "sg:province":"Staffordshire",
    "sg:tags":[
        "tea",
        "room"
    ],
    "wof:name":"Cottage Stores (The)",
    "wof:placetype":"venue"
},
  "geometry": {"coordinates":[-2.188007,52.936199],"type":"Point"}
}