{
  "type": "Feature",
  "properties": {
    "addr:full":"13 The Parade, Uttoxeter Road, Mickleover Derby Derbyshire DE3 0GB",
    "addr:housenumber":"13",
    "addr:postcode":"de3 0gb",
    "addr:street":"The Parade Uttoxeter Road",
    "iso:country":"GB",
    "sg:address":"13 The Parade, Uttoxeter Road, Mickleover",
    "sg:city":"Derby",
    "sg:classifiers":[
        {
            "category":"Government",
            "subcategory":"Post Office",
            "type":"Public Place"
        }
    ],
    "sg:phone":"+44 1332 515463",
    "sg:postcode":"DE3 0GB",
    "sg:province":"Derbyshire",
    "wof:name":"Mickleover Post Office",
    "wof:placetype":"venue"
},
  "geometry": {"coordinates":[-1.5460519791,52.9038581848],"type":"Point"}
}