{
  "type": "Feature",
  "properties": {
    "addr:full":"3 Copperhill Street Aberdovey Gwynedd LL35 0EU",
    "addr:housenumber":"3",
    "addr:postcode":"ll35 0eu",
    "addr:street":"Copperhill Street",
    "iso:country":"GB",
    "sg:address":"3 Copperhill Street",
    "sg:city":"Aberdovey",
    "sg:classifiers":[
        {
            "category":"Food & Beverages",
            "subcategory":"Meat & Fish",
            "type":"Retail Goods"
        }
    ],
    "sg:phone":"+44 1654 767223",
    "sg:postcode":"LL35 0EU",
    "sg:province":"Gwynedd",
    "sg:tags":[
        "butcher"
    ],
    "wof:name":"David Roberts Quality Meat Supplies",
    "wof:placetype":"venue"
},
  "geometry": {"coordinates":[-4.0465049744,52.5447235107],"type":"Point"}
}