{
  "type": "Feature",
  "properties": {
    "addr:full":"20 High Riggs Edinburgh City of Edinburgh EH3 7HU",
    "addr:housenumber":"20",
    "addr:postcode":"eh3 7hu",
    "addr:street":"High Riggs",
    "iso:country":"GB",
    "sg:address":"20 High Riggs",
    "sg:city":"Edinburgh",
    "sg:classifiers":[
        {
            "category":"Professional",
            "subcategory":"Employment Agencies",
            "type":"Services"
        }
    ],
    "sg:phone":"+44 131 456 4000",
    "sg:postcode":"EH3 7HU",
    "sg:province":"City of Edinburgh",
    "sg:tags":[
        "consultant"
    ],
    "wof:name":"Job Centre",
    "wof:placetype":"venue"
},
  "geometry": {"coordinates":[-3.2149810791,55.9524383545],"type":"Point"}
}