{
  "type": "Feature",
  "properties": {
    "addr:full":"36 Fydell Street Boston Lincolnshire PE21 8LF",
    "addr:housenumber":"36",
    "addr:postcode":"pe21 8lf",
    "addr:street":"Fydell Street",
    "iso:country":"GB",
    "sg:address":"36 Fydell Street",
    "sg:city":"Boston",
    "sg:classifiers":[
        {
            "category":"Bars & Pubs",
            "type":"Food & Drink"
        }
    ],
    "sg:postcode":"PE21 8LF",
    "sg:province":"Lincolnshire",
    "sg:tags":[
        "pubs",
        "inn"
    ],
    "wof:name":"New Castle Inn",
    "wof:placetype":"venue"
},
  "geometry": {"coordinates":[-0.0323089994,52.9811134338],"type":"Point"}
}