{
  "type": "Feature",
  "properties": {
    "addr:full":"The Active Business Centre, St Andrews C, 33 St Andrews Street South Bury St Edmunds Suffolk IP33 3PH",
    "addr:housenumber":"33",
    "addr:postcode":"ip33 3ph",
    "addr:street":"St Andrews Street South",
    "iso:country":"GB",
    "sg:address":"The Active Business Centre, St Andrews C, 33 St Andrews Street South",
    "sg:city":"Bury St Edmunds",
    "sg:classifiers":[
        {
            "category":"Professional",
            "type":"Services"
        }
    ],
    "sg:postcode":"IP33 3PH",
    "sg:province":"Suffolk",
    "sg:tags":[
        "entertainer"
    ],
    "wof:name":"Baumann,Diane,",
    "wof:placetype":"venue"
},
  "geometry": {"coordinates":[0.7110689878,52.242893219],"type":"Point"}
}