{
  "type": "Feature",
  "properties": {
    "iso:country":"GB",
    "sg:address":"Unit 19 Royal Dockyard",
    "sg:city":"Pembroke",
    "sg:classifiers":[
        {
            "category":"Building & Trades",
            "subcategory":"Construction",
            "type":"Services"
        }
    ],
    "sg:phone":"+44 1646 683109",
    "sg:postcode":"SA72 6TA",
    "sg:province":"Pembrokeshire",
    "sg:tags":[
        "joinery"
    ],
    "wof:name":"Port Pallets (Pembroke) Ltd.",
    "wof:placetype":"venue"
},
  "geometry": {"coordinates":[-4.944038868,51.6900291443],"type":"Point"}
}