{
  "type": "Feature",
  "properties": {
    "addr:full":"38 North Methven St Perth Perth and Kinross PH1 5PP",
    "addr:housenumber":"38",
    "addr:postcode":"ph1 5pp",
    "addr:street":"North Methven St",
    "iso:country":"GB",
    "sg:address":"38 North Methven St",
    "sg:city":"Perth",
    "sg:classifiers":[
        {
            "category":"Personal",
            "type":"Services"
        }
    ],
    "sg:phone":"+44 1738 624357",
    "sg:postcode":"PH1 5PP",
    "sg:province":"Perth and Kinross",
    "sg:tags":[
        "wedding"
    ],
    "wof:name":"Bellinghams of Perth",
    "wof:placetype":"venue"
},
  "geometry": {"coordinates":[-3.434947,56.398594],"type":"Point"}
}