{
  "type": "Feature",
  "properties": {
    "addr:full":"10 Park Street, Cross Keys Newport Blaenau Gwent NP11 7DF",
    "addr:housenumber":"10",
    "addr:postcode":"np11 7df",
    "addr:street":"Park Street",
    "iso:country":"GB",
    "sg:address":"10 Park Street, Cross Keys",
    "sg:city":"Newport",
    "sg:classifiers":[
        {
            "category":"Building & Trades",
            "subcategory":"Plumbing",
            "type":"Services"
        }
    ],
    "sg:phone":"+44 1495 272366",
    "sg:postcode":"NP11 7DF",
    "sg:province":"Blaenau Gwent",
    "sg:tags":[
        "drain",
        "clearance",
        "sewer"
    ],
    "wof:name":"A B C Drains",
    "wof:placetype":"venue"
},
  "geometry": {"coordinates":[-3.129046917,51.6357803345],"type":"Point"}
}