{
  "type": "Feature",
  "properties": {
    "addr:full":"7-9 Leys Avenue Letchworth Hertfordshire SG6 3EA",
    "addr:housenumber":"7-9",
    "addr:postcode":"sg6 3ea",
    "addr:street":"Leys Avenue Letchworth",
    "iso:country":"GB",
    "sg:address":"7-9 Leys Avenue",
    "sg:city":"Letchworth",
    "sg:classifiers":[
        {
            "category":"Professional",
            "subcategory":"Management & Consulting",
            "type":"Services"
        },
        {
            "category":"Shopping",
            "subcategory":"Shoes",
            "type":"Retail Goods"
        }
    ],
    "sg:phone":"+44 1462 686080",
    "sg:postcode":"SG6 3EA",
    "sg:province":"Hertfordshire",
    "sg:tags":[
        "shop",
        "consultant",
        "business"
    ],
    "wof:name":"Burrs",
    "wof:placetype":"venue"
},
  "geometry": {"coordinates":[-0.227348,51.979076],"type":"Point"}
}