{
  "type": "Feature",
  "properties": {
    "addr:full":"21 Princes Street London Greater London W1B 2ND",
    "addr:housenumber":"21",
    "addr:postcode":"w1b 2nd",
    "addr:street":"Princes Street",
    "iso:country":"GB",
    "sg:address":"21 Princes Street",
    "sg:city":"London",
    "sg:classifiers":[
        {
            "category":"Cafe",
            "type":"Food & Drink"
        }
    ],
    "sg:postcode":"W1B 2ND",
    "sg:province":"Greater London",
    "sg:tags":[
        "tea",
        "room"
    ],
    "wof:name":"The Light Fantastic",
    "wof:placetype":"venue"
},
  "geometry": {"coordinates":[-0.1426779926,51.5144195557],"type":"Point"}
}