{
  "type": "Feature",
  "properties": {
    "iso:country":"GB",
    "sg:address":"141 New London Road",
    "sg:city":"Chelmsford",
    "sg:classifiers":[
        {
            "category":"Professional",
            "subcategory":"Lawyer & Legal Services",
            "type":"Services"
        }
    ],
    "sg:phone":"+44 1245 264494",
    "sg:postcode":"CM2 0QT",
    "sg:province":"Essex",
    "sg:tags":[
        "solicitor"
    ],
    "wof:name":"Colemans",
    "wof:placetype":"venue"
},
  "geometry": {"coordinates":[0.467792,51.728771],"type":"Point"}
}