{
  "type": "Feature",
  "properties": {
    "iso:country":"GB",
    "sg:address":"156 Rutland Road",
    "sg:city":"Sheffield",
    "sg:classifiers":[
        {
            "category":"Building & Trades",
            "subcategory":"Construction",
            "type":"Services"
        }
    ],
    "sg:phone":"+44 114 272 1979",
    "sg:postcode":"S3 9PP",
    "sg:province":"South Yorkshire",
    "sg:tags":[
        "builder"
    ],
    "wof:name":"J Lee & Sons (Sheffield) Ltd.",
    "wof:placetype":"venue"
},
  "geometry": {"coordinates":[-1.471441,53.396309],"type":"Point"}
}