{
  "type": "Feature",
  "properties": {
    "iso:country":"GB",
    "sg:address":"141 Lytham Rd",
    "sg:city":"Preston",
    "sg:classifiers":[
        {
            "category":"Government",
            "subcategory":"Police Station",
            "type":"Public Place"
        }
    ],
    "sg:phone":"+44 1772 632979",
    "sg:postcode":"PR4 1AB",
    "sg:province":"Lancashire",
    "sg:tags":[
        "support",
        "force"
    ],
    "wof:name":"Police",
    "wof:placetype":"venue"
},
  "geometry": {"coordinates":[-2.878526,53.751972],"type":"Point"}
}