{
  "type": "Feature",
  "properties": {
    "addr:full":"Atlantic House, Beaufort Square Chepstow Gloucestershire NP16 5EP",
    "addr:postcode":"np16 5ep",
    "addr:street":"Beaufort Square",
    "iso:country":"GB",
    "sg:address":"Atlantic House, Beaufort Square",
    "sg:city":"Chepstow",
    "sg:classifiers":[
        {
            "category":"Manufacturing",
            "subcategory":"Metals",
            "type":"Manufacturing & Wholesale Goods"
        },
        {
            "category":"Wholesale",
            "subcategory":"Scrap",
            "type":"Manufacturing & Wholesale Goods"
        }
    ],
    "sg:phone":"+44 1291 625131",
    "sg:postcode":"NP16 5EP",
    "sg:province":"Gloucestershire",
    "sg:tags":[
        "industry",
        "waste",
        "f-a"
    ],
    "wof:name":"Allied Metals Ltd.",
    "wof:placetype":"venue"
},
  "geometry": {"coordinates":[-2.6747341156,51.6422386169],"type":"Point"}
}