{
  "type": "Feature",
  "properties": {
    "iso:country":"GB",
    "sg:address":"24 Elmgrove Gardens",
    "sg:city":"Harrow",
    "sg:classifiers":[
        {
            "category":"Home & Garden",
            "subcategory":"Household Appliances",
            "type":"Retail Goods"
        },
        {
            "category":"Retail",
            "subcategory":"Repair Shop",
            "type":"Services"
        }
    ],
    "sg:phone":"+44 20 8861 4557",
    "sg:postcode":"HA1 2QR",
    "sg:province":"Greater London",
    "sg:tags":[
        "machine",
        "electrical",
        "washing"
    ],
    "wof:name":"Primo Electrics",
    "wof:placetype":"venue"
},
  "geometry": {"coordinates":[-0.326129,51.58654],"type":"Point"}
}