{
  "type": "Feature",
  "properties": {
    "addr:full":"23 Gotham Road, Yardley Birmingham West Midlands B26 1LB",
    "addr:housenumber":"23",
    "addr:postcode":"b26 1lb",
    "addr:street":"Gotham Road",
    "iso:country":"GB",
    "sg:address":"23 Gotham Road, Yardley",
    "sg:city":"Birmingham",
    "sg:classifiers":[
        {
            "category":"Shopping",
            "subcategory":"Musical Instruments",
            "type":"Retail Goods"
        }
    ],
    "sg:postcode":"B26 1LB",
    "sg:province":"West Midlands",
    "wof:name":"P Lamb Piano Tunings & Repairs",
    "wof:placetype":"venue"
},
  "geometry": {"coordinates":[-1.804053,52.459587],"type":"Point"}
}