{
  "type": "Feature",
  "properties": {
    "addr:full":"Ringley Park House, 59 Reigate Road Reigate Surrey RH2 0QT",
    "addr:housenumber":"59",
    "addr:postcode":"rh2 0qt",
    "addr:street":"Ringley;Reigate Road",
    "iso:country":"GB",
    "sg:address":"Ringley Park House, 59 Reigate Road",
    "sg:city":"Reigate",
    "sg:classifiers":[
        {
            "category":"Professional",
            "subcategory":"Accounting & Tax Preparation",
            "type":"Services"
        }
    ],
    "sg:phone":"+44 1737 221911",
    "sg:postcode":"RH2 0QT",
    "sg:province":"Surrey",
    "sg:tags":[
        "accountant"
    ],
    "wof:name":"Jonathan C Woodbridge",
    "wof:placetype":"venue"
},
  "geometry": {"coordinates":[-0.190687,51.236992],"type":"Point"}
}