{
  "type": "Feature",
  "properties": {
    "addr:full":"86 Old Park Rd Bradford West Yorkshire BD10 9BG",
    "addr:housenumber":"86",
    "addr:postcode":"bd10 9bg",
    "addr:street":"Old Park Rd",
    "iso:country":"GB",
    "sg:address":"86 Old Park Rd",
    "sg:city":"Bradford",
    "sg:classifiers":[
        {
            "category":"Social Services",
            "type":"Services"
        }
    ],
    "sg:phone":"+44 1274 413991",
    "sg:postcode":"BD10 9BG",
    "sg:province":"West Yorkshire",
    "sg:tags":[
        "disability"
    ],
    "wof:name":"Safeline UK",
    "wof:placetype":"venue"
},
  "geometry": {"coordinates":[-1.7188960314,53.8308906555],"type":"Point"}
}