{
  "type": "Feature",
  "properties": {
    "iso:country":"GB",
    "sg:address":"162-164 Bath Road",
    "sg:city":"Cheltenham",
    "sg:classifiers":[
        {
            "category":"Banks & Credit Unions",
            "subcategory":"Bank",
            "type":"Services"
        }
    ],
    "sg:phone":"+44 1242 584825",
    "sg:postcode":"GL53 7NF",
    "sg:province":"Gloucestershire",
    "sg:tags":[
        "financial",
        "institution"
    ],
    "wof:name":"Cheltenham & Gloucester Plc",
    "wof:placetype":"venue"
},
  "geometry": {"coordinates":[-2.078808,51.889641],"type":"Point"}
}