{
  "type": "Feature",
  "properties": {
    "addr:full":"65 Horsforth Avenue Bridlington East Riding of Yorkshire YO15 3DH",
    "addr:housenumber":"65",
    "addr:postcode":"yo15 3dh",
    "addr:street":"Horsforth Avenue",
    "iso:country":"GB",
    "sg:address":"65 Horsforth Avenue",
    "sg:city":"Bridlington",
    "sg:classifiers":[
        {
            "category":"Travel",
            "subcategory":"Hotels & Motels",
            "type":"Entertainment"
        }
    ],
    "sg:phone":"+44 1262 602828",
    "sg:postcode":"YO15 3DH",
    "sg:province":"East Riding of Yorkshire",
    "wof:name":"Strathmore Hotel",
    "wof:placetype":"venue"
},
  "geometry": {"coordinates":[-0.2022739947,54.0790901184],"type":"Point"}
}