{
  "type": "Feature",
  "properties": {
    "addr:full":"The Grange, West Rudham King's Lynn Norfolk PE31 8SY",
    "addr:housenumber":"rudham",
    "addr:postcode":"pe31 8sy",
    "addr:street":"West;Lynn",
    "iso:country":"GB",
    "sg:address":"The Grange, West Rudham",
    "sg:city":"King's Lynn",
    "sg:classifiers":[
        {
            "category":"Retail",
            "subcategory":"Animal Services",
            "type":"Services"
        }
    ],
    "sg:phone":"+44 1485 528141",
    "sg:postcode":"PE31 8SY",
    "sg:province":"Norfolk",
    "sg:tags":[
        "pet"
    ],
    "wof:name":"Peaceful Pets",
    "wof:placetype":"venue"
},
  "geometry": {"coordinates":[0.6913200021,52.819519043],"type":"Point"}
}