{
  "type": "Feature",
  "properties": {
    "addr:full":"Dingles, 40 Royal Parade Plymouth Devon PL1 1DY",
    "addr:housenumber":"40",
    "addr:postcode":"pl1 1dy",
    "addr:street":"Dingles;Royal Parade",
    "iso:country":"GB",
    "sg:address":"Dingles, 40 Royal Parade",
    "sg:city":"Plymouth",
    "sg:classifiers":[
        {
            "category":"Shopping",
            "subcategory":"Clothing, Apparel, & Fashions",
            "type":"Retail Goods"
        }
    ],
    "sg:phone":"+44 1752 253811",
    "sg:postcode":"PL1 1DY",
    "sg:province":"Devon",
    "sg:tags":[
        "shop",
        "ladieswear"
    ],
    "wof:name":"COUNTRY CASUALS LTD",
    "wof:placetype":"venue"
},
  "geometry": {"coordinates":[-4.1421599388,50.3704185486],"type":"Point"}
}