{
  "type": "Feature",
  "properties": {
    "iso:country":"GB",
    "sg:address":"28 Chelsea Road",
    "sg:city":"Bristol",
    "sg:classifiers":[
        {
            "category":"Government",
            "subcategory":"Post Office",
            "type":"Public Place"
        }
    ],
    "sg:phone":"+44 117 939 3303",
    "sg:postcode":"BS5 6AF",
    "sg:province":"City of Bristol",
    "wof:name":"Chelsea Road Post Office",
    "wof:placetype":"venue"
},
  "geometry": {"coordinates":[-2.562968,51.463192],"type":"Point"}
}