{
  "type": "Feature",
  "properties": {
    "addr:full":"215a East La Wembley Greater London HA0 3NG",
    "addr:housenumber":"215a",
    "addr:postcode":"ha0 3ng",
    "addr:street":"East La Wembley",
    "iso:country":"GB",
    "sg:address":"215a East La",
    "sg:city":"Wembley",
    "sg:classifiers":[
        {
            "category":"Professional",
            "subcategory":"Printing & Photocopies",
            "type":"Services"
        }
    ],
    "sg:phone":"+44 20 8385 0880",
    "sg:postcode":"HA0 3NG",
    "sg:province":"Greater London",
    "sg:tags":[
        "printer"
    ],
    "wof:name":"Printernational Ltd",
    "wof:placetype":"venue"
},
  "geometry": {"coordinates":[-0.3061360121,51.5624313354],"type":"Point"}
}