{
  "type": "Feature",
  "properties": {
    "addr:full":"Unit 26 Jacks Pill Wharf Indstl Est Newport Newport NP20 2BR",
    "addr:housenumber":"unit 26",
    "addr:postcode":"np20 2br",
    "addr:street":"Pill Wharf Indstl Est",
    "iso:country":"GB",
    "sg:address":"Unit 26 Jacks Pill Wharf Indstl Est",
    "sg:city":"Newport",
    "sg:classifiers":[
        {
            "category":"Building & Trades",
            "subcategory":"Construction",
            "type":"Services"
        }
    ],
    "sg:postcode":"NP20 2BR",
    "sg:province":"Newport",
    "sg:tags":[
        "dry",
        "lining",
        "plasterers",
        "screeders"
    ],
    "wof:name":"Elite Plasterers Ltd",
    "wof:placetype":"venue"
},
  "geometry": {"coordinates":[-2.9900000095,51.5665092468],"type":"Point"}
}