{
  "type": "Feature",
  "properties": {
    "addr:full":"271 New Rd Porthcawl Bridgend CF36 5BG",
    "addr:housenumber":"271",
    "addr:postcode":"cf36 5bg",
    "addr:street":"New Rd",
    "iso:country":"GB",
    "sg:address":"271 New Rd",
    "sg:city":"Porthcawl",
    "sg:classifiers":[
        {
            "category":"Fast Food",
            "type":"Food & Drink"
        }
    ],
    "sg:phone":"+44 1656 773883",
    "sg:postcode":"CF36 5BG",
    "sg:province":"Bridgend",
    "sg:tags":[
        "away",
        "meal",
        "outlet",
        "take"
    ],
    "wof:name":"New Road Chinese",
    "wof:placetype":"venue"
},
  "geometry": {"coordinates":[-3.688039,51.483089],"type":"Point"}
}