{
  "type": "Feature",
  "properties": {
    "addr:full":"Compstall Mills Estate, Andrew Street, Compstall Stockport Cheshire SK6 5HN",
    "addr:postcode":"sk6 5hn",
    "addr:street":"Andrew Street",
    "iso:country":"GB",
    "sg:address":"Compstall Mills Estate, Andrew Street, Compstall",
    "sg:city":"Stockport",
    "sg:classifiers":[
        {
            "category":"Building & Trades",
            "subcategory":"Equipment Rental",
            "type":"Services"
        }
    ],
    "sg:phone":"+44 1625 251550",
    "sg:postcode":"SK6 5HN",
    "sg:province":"Cheshire",
    "sg:tags":[
        "marking",
        "id"
    ],
    "wof:name":"Eurocode",
    "wof:placetype":"venue"
},
  "geometry": {"coordinates":[-2.0530040264,53.4132995605],"type":"Point"}
}