{
  "type": "Feature",
  "properties": {
    "addr:full":"Higher Edgecumbe, Milton Abbot Tavistock Devon PL19 0QH",
    "addr:housenumber":"abbot",
    "addr:postcode":"pl19 0qh",
    "iso:country":"GB",
    "sg:address":"Higher Edgecumbe, Milton Abbot",
    "sg:city":"Tavistock",
    "sg:classifiers":[
        {
            "category":"Farming",
            "subcategory":"Farm",
            "type":"Manufacturing & Wholesale Goods"
        }
    ],
    "sg:postcode":"PL19 0QH",
    "sg:province":"Devon",
    "sg:tags":[
        "mixed",
        "crop"
    ],
    "wof:name":"T W & C & J W Spear",
    "wof:placetype":"venue"
},
  "geometry": {"coordinates":[-4.144739,50.549934],"type":"Point"}
}