{
  "type": "Feature",
  "properties": {
    "addr:full":"14 Queen Alexandra Road Seaham Durham SR7 7QZ",
    "addr:housenumber":"14",
    "addr:postcode":"sr7 7qz",
    "addr:street":"Queen Alexandra Road",
    "iso:country":"GB",
    "sg:address":"14 Queen Alexandra Road",
    "sg:city":"Seaham",
    "sg:classifiers":[
        {
            "category":"Government",
            "subcategory":"Post Office",
            "type":"Public Place"
        }
    ],
    "sg:phone":"+44 191 581 2106",
    "sg:postcode":"SR7 7QZ",
    "sg:province":"Durham",
    "wof:name":"Dawdon Post Office",
    "wof:placetype":"venue"
},
  "geometry": {"coordinates":[-1.3356260061,54.8301696777],"type":"Point"}
}