{
  "type": "Feature",
  "properties": {
    "addr:full":"4 Highview, Eglinton Hill, Plumstead Woolwich Greater London SE18 3PB",
    "addr:housenumber":"4",
    "addr:postcode":"se18 3pb",
    "addr:street":"Eglinton Hill",
    "iso:country":"GB",
    "sg:address":"4 Highview, Eglinton Hill, Plumstead",
    "sg:city":"Woolwich",
    "sg:classifiers":[
        {
            "category":"Retail",
            "subcategory":"Driving School",
            "type":"Services"
        }
    ],
    "sg:phone":"+44 20 8317 3225",
    "sg:postcode":"SE18 3PB",
    "sg:province":"Greater London",
    "wof:name":"Envoy Driving Tuition",
    "wof:placetype":"venue"
},
  "geometry": {"coordinates":[0.0650549978,51.4893951416],"type":"Point"}
}