{
  "type": "Feature",
  "properties": {
    "iso:country":"GB",
    "sg:address":"Tannington Long Road, Brundish",
    "sg:city":"Woodbridge",
    "sg:classifiers":[
        {
            "category":"Bars & Pubs",
            "type":"Food & Drink"
        }
    ],
    "sg:postcode":"IP13 8BE",
    "sg:province":"Suffolk",
    "sg:tags":[
        "pubs",
        "inn"
    ],
    "wof:name":"Crown Inn",
    "wof:placetype":"venue"
},
  "geometry": {"coordinates":[1.320981,52.278229],"type":"Point"}
}