{
  "type": "Feature",
  "properties": {
    "iso:country":"GB",
    "sg:address":"Craven St, Droylsden",
    "sg:city":"Manchester",
    "sg:classifiers":[
        {
            "category":"Manufacturing",
            "subcategory":"Metals",
            "type":"Manufacturing & Wholesale Goods"
        }
    ],
    "sg:phone":"+44 161 370 1617",
    "sg:postcode":"M43 7UD",
    "sg:province":"Greater Manchester",
    "sg:tags":[
        "steel",
        "fabricator",
        "erectors"
    ],
    "wof:name":"H Middleton Ltd",
    "wof:placetype":"venue"
},
  "geometry": {"coordinates":[-2.146412,53.479103],"type":"Point"}
}