{
  "type": "Feature",
  "properties": {
    "addr:full":"176 Luton Rd Chatham Kent ME4 5BP",
    "addr:housenumber":"176",
    "addr:postcode":"me4 5bp",
    "addr:street":"Luton Rd",
    "iso:country":"GB",
    "sg:address":"176 Luton Rd",
    "sg:city":"Chatham",
    "sg:classifiers":[
        {
            "category":"Home & Garden",
            "subcategory":"Household Appliances",
            "type":"Retail Goods"
        }
    ],
    "sg:postcode":"ME4 5BP",
    "sg:province":"Kent",
    "sg:tags":[
        "electrical"
    ],
    "wof:name":"Jenkins,James,",
    "wof:placetype":"venue"
},
  "geometry": {"coordinates":[0.5393670201,51.374420166],"type":"Point"}
}