{
  "type": "Feature",
  "properties": {
    "addr:full":"1 Herberts Cotts Didcot Oxfordshire OX11 9ER",
    "addr:housenumber":"1",
    "addr:postcode":"ox11 9er",
    "addr:street":"Herberts Cotts",
    "iso:country":"GB",
    "sg:address":"1 Herberts Cotts",
    "sg:city":"Didcot",
    "sg:classifiers":[
        {
            "category":"Farming",
            "subcategory":"Livestock Farm",
            "type":"Manufacturing & Wholesale Goods"
        }
    ],
    "sg:phone":"+44 1235 850300",
    "sg:postcode":"OX11 9ER",
    "sg:province":"Oxfordshire",
    "sg:tags":[
        "stud"
    ],
    "wof:name":"Aston Upthorpe stud & Farms Ltd.",
    "wof:placetype":"venue"
},
  "geometry": {"coordinates":[-1.232115,51.602383],"type":"Point"}
}