{
  "type": "Feature",
  "properties": {
    "addr:full":"98 Bold Street Liverpool Merseyside L1 4HY",
    "addr:housenumber":"98",
    "addr:postcode":"l1 4hy",
    "addr:street":"Bold Street",
    "iso:country":"GB",
    "sg:address":"98 Bold Street",
    "sg:city":"Liverpool",
    "sg:classifiers":[
        {
            "category":"Personal",
            "subcategory":"Beauty Salon",
            "type":"Services"
        }
    ],
    "sg:phone":"+44 151 709 5003",
    "sg:postcode":"L1 4HY",
    "sg:province":"Merseyside",
    "sg:tags":[
        "unisex",
        "hairdresser"
    ],
    "wof:name":"Exit Hairdressing Ltd.",
    "wof:placetype":"venue"
},
  "geometry": {"coordinates":[-2.977417,53.402504],"type":"Point"}
}