{
  "type": "Feature",
  "properties": {
    "iso:country":"GB",
    "sg:address":"58 Holtspur Avenue, Wooburn Grn",
    "sg:city":"High Wycombe",
    "sg:classifiers":[
        {
            "category":"Shopping",
            "subcategory":"Department Store",
            "type":"Retail Goods"
        },
        {
            "category":"Food & Beverages",
            "subcategory":"Groceries & Convenience Stores",
            "type":"Retail Goods"
        }
    ],
    "sg:phone":"+44 1628 524232",
    "sg:postcode":"HP10 0BG",
    "sg:province":"Buckinghamshire",
    "wof:name":"The Avenue Stores",
    "wof:placetype":"venue"
},
  "geometry": {"coordinates":[-0.678825,51.594608],"type":"Point"}
}