{
  "type": "Feature",
  "properties": {
    "iso:country":"GB",
    "sg:address":"Unit 13, Bessemer Park Trading Estate, 250 Milkwood Road",
    "sg:city":"London",
    "sg:classifiers":[
        {
            "category":"Food & Beverages",
            "subcategory":"Farmers Market",
            "type":"Retail Goods"
        },
        {
            "category":"Wholesale",
            "subcategory":"Fruits & Vegetables",
            "type":"Manufacturing & Wholesale Goods"
        }
    ],
    "sg:phone":"+44 20 7738 7474",
    "sg:postcode":"SE24 0HG",
    "sg:province":"Greater London",
    "sg:tags":[
        "herb",
        "grower"
    ],
    "wof:name":"Herbs Kingdom Co. Ltd.",
    "wof:placetype":"venue"
},
  "geometry": {"coordinates":[-0.1024300009,51.4590301514],"type":"Point"}
}