{
  "type": "Feature",
  "properties": {
    "iso:country":"GB",
    "sg:address":"Seawynds, St Catherines Road, Niton",
    "sg:city":"Ventnor",
    "sg:classifiers":[
        {
            "category":"Sports & Exercise",
            "subcategory":"Sports Center",
            "type":"Entertainment"
        }
    ],
    "sg:postcode":"PO38 2NA",
    "sg:province":"Isle of Wight",
    "sg:tags":[
        "coaching"
    ],
    "wof:name":"David Fothergill Tennis Coach",
    "wof:placetype":"venue"
},
  "geometry": {"coordinates":[-1.2848639488,50.5872459412],"type":"Point"}
}