{
  "type": "Feature",
  "properties": {
    "addr:full":"18 West Street, Moulton Northampton Northamptonshire NN3 7SB",
    "addr:housenumber":"18",
    "addr:postcode":"nn3 7sb",
    "addr:street":"West Street",
    "iso:country":"GB",
    "sg:address":"18 West Street, Moulton",
    "sg:city":"Northampton",
    "sg:classifiers":[
        {
            "category":"Autos & Motor Vehicles",
            "subcategory":"Auto Supplies",
            "type":"Retail Goods"
        }
    ],
    "sg:phone":"+44 1604 790291",
    "sg:postcode":"NN3 7SB",
    "sg:province":"Northamptonshire",
    "sg:tags":[
        "rubber",
        "tyre"
    ],
    "wof:name":"Moulton Auto Hire",
    "wof:placetype":"venue"
},
  "geometry": {"coordinates":[-0.8569880128,52.2898254395],"type":"Point"}
}