{
  "type": "Feature",
  "properties": {
    "iso:country":"GB",
    "sg:address":"Craven Close",
    "sg:city":"Margate",
    "sg:classifiers":[
        {
            "category":"Social Services",
            "subcategory":"Adult Care",
            "type":"Services"
        },
        {
            "category":"Social Services",
            "subcategory":"Retirement Home",
            "type":"Services"
        }
    ],
    "sg:phone":"+44 1843 292517",
    "sg:postcode":"CT9 5NW",
    "sg:province":"Kent",
    "sg:tags":[
        "housing",
        "sheltered",
        "accommodation"
    ],
    "wof:name":"Craven Court",
    "wof:placetype":"venue"
},
  "geometry": {"coordinates":[1.36213,51.376556],"type":"Point"}
}