{
  "type": "Feature",
  "properties": {
    "addr:full":"127 London Road Etchingham East Sussex TN19 7PN",
    "addr:housenumber":"127",
    "addr:postcode":"tn19 7pn",
    "addr:street":"London Road",
    "iso:country":"GB",
    "sg:address":"127 London Road",
    "sg:city":"Etchingham",
    "sg:classifiers":[
        {
            "category":"Shopping",
            "subcategory":"Computers & Home Electronics",
            "type":"Retail Goods"
        }
    ],
    "sg:postcode":"TN19 7PN",
    "sg:province":"East Sussex",
    "wof:name":"Fourposters",
    "wof:placetype":"venue"
},
  "geometry": {"coordinates":[0.474546,51.00869],"type":"Point"}
}