{
  "type": "Feature",
  "properties": {
    "addr:full":"Unit 1, European Terminal, Pantglas Ind Est, Bedwas Caerphilly Caerphilly CF83 8DR",
    "addr:housenumber":"unit",
    "addr:postcode":"cf83 8dr",
    "addr:street":"Pantglas Ind Est",
    "iso:country":"GB",
    "sg:address":"Unit 1, European Terminal, Pantglas Ind Est, Bedwas",
    "sg:city":"Caerphilly",
    "sg:classifiers":[
        {
            "category":"Retail",
            "subcategory":"Auto Repair",
            "type":"Services"
        }
    ],
    "sg:phone":"+44 29 2086 5557",
    "sg:postcode":"CF83 8DR",
    "sg:province":"Caerphilly",
    "sg:tags":[
        "body",
        "car"
    ],
    "wof:name":"Advanced Motors",
    "wof:placetype":"venue"
},
  "geometry": {"coordinates":[-3.189834,51.590469],"type":"Point"}
}