{
  "type": "Feature",
  "properties": {
    "addr:full":"Redgate Depot, Watling Street Nuneaton Leicestershire CV10 0RY",
    "addr:postcode":"cv10 0ry",
    "addr:street":"Redgate;Watling Street",
    "iso:country":"GB",
    "sg:address":"Redgate Depot, Watling Street",
    "sg:city":"Nuneaton",
    "sg:classifiers":[
        {
            "category":"Shopping",
            "type":"Retail Goods"
        }
    ],
    "sg:phone":"+44 24 7638 4730",
    "sg:postcode":"CV10 0RY",
    "sg:province":"Leicestershire",
    "sg:tags":[
        "merchant"
    ],
    "wof:name":"Countrywide Farmers Plc",
    "wof:placetype":"venue"
},
  "geometry": {"coordinates":[-1.487169981,52.5622406006],"type":"Point"}
}