{
  "type": "Feature",
  "properties": {
    "addr:full":"Bryn Yr Hydd, Maes Y Waen Bala Gwynedd LL23 7SH",
    "addr:postcode":"ll23 7sh",
    "addr:street":"Bryn Yr Hydd Maes Y Waen Bala",
    "iso:country":"GB",
    "sg:address":"Bryn Yr Hydd, Maes Y Waen",
    "sg:city":"Bala",
    "sg:classifiers":[
        {
            "category":"Building & Trades",
            "subcategory":"Construction",
            "type":"Services"
        }
    ],
    "sg:phone":"+44 1678 521002",
    "sg:postcode":"LL23 7SH",
    "sg:province":"Gwynedd",
    "sg:tags":[
        "roofing"
    ],
    "wof:name":"J T MORRIS & CO LTD",
    "wof:placetype":"venue"
},
  "geometry": {"coordinates":[-3.595467,52.912148],"type":"Point"}
}