{
  "type": "Feature",
  "properties": {
    "addr:full":"Unit F Argent Court, Hook Rise South Surbiton Surrey KT6 7LD",
    "addr:postcode":"kt6 7ld",
    "addr:street":"Argent Court Hook Rise South",
    "iso:country":"GB",
    "sg:address":"Unit F Argent Court, Hook Rise South",
    "sg:city":"Surbiton",
    "sg:classifiers":[
        {
            "category":"Professional",
            "subcategory":"Printing & Photocopies",
            "type":"Services"
        }
    ],
    "sg:phone":"+44 20 8391 5857",
    "sg:postcode":"KT6 7LD",
    "sg:province":"Surrey",
    "sg:tags":[
        "printer"
    ],
    "wof:name":"Chord Print",
    "wof:placetype":"venue"
},
  "geometry": {"coordinates":[-0.288747,51.373638],"type":"Point"}
}