{
  "type": "Feature",
  "properties": {
    "iso:country":"GB",
    "sg:address":"1 Kenmure Road",
    "sg:city":"Glasgow",
    "sg:classifiers":[
        {
            "category":"Health Services",
            "subcategory":"Health Practitioner",
            "type":"Services"
        }
    ],
    "sg:phone":"+44 141 577 5030",
    "sg:postcode":"G46 6TU",
    "sg:province":"East Renfrewshire",
    "sg:tags":[
        "physiotherapist"
    ],
    "wof:name":"Cherie Martin",
    "wof:placetype":"venue"
},
  "geometry": {"coordinates":[-4.303778,55.782791],"type":"Point"}
}