{
  "type": "Feature",
  "properties": {
    "addr:full":"9a Between Streets Cobham Surrey KT11 1AA",
    "addr:housenumber":"9a",
    "addr:postcode":"kt11 1aa",
    "addr:street":"Between Streets",
    "iso:country":"GB",
    "sg:address":"9a Between Streets",
    "sg:city":"Cobham",
    "sg:classifiers":[
        {
            "category":"Home & Garden",
            "subcategory":"Building Materials",
            "type":"Retail Goods"
        }
    ],
    "sg:phone":"+44 1932 860392",
    "sg:postcode":"KT11 1AA",
    "sg:province":"Surrey",
    "sg:tags":[
        "fencing"
    ],
    "wof:name":"Thielco (Grating) Ltd.",
    "wof:placetype":"venue"
},
  "geometry": {"coordinates":[-0.414112,51.329678],"type":"Point"}
}