{
  "type": "Feature",
  "properties": {
    "addr:full":"Unit 3 Titan House, 145 York Road Hartlepool Durham TS26 9HL",
    "addr:housenumber":"unit 3;145",
    "addr:postcode":"ts26 9hl",
    "addr:street":"York Road",
    "iso:country":"GB",
    "sg:address":"Unit 3 Titan House, 145 York Road",
    "sg:city":"Hartlepool",
    "sg:classifiers":[
        {
            "category":"Shopping",
            "subcategory":"Optician",
            "type":"Retail Goods"
        }
    ],
    "sg:phone":"+44 1429 221397",
    "sg:postcode":"TS26 9HL",
    "sg:province":"Durham",
    "wof:name":"Crown Optical Centre",
    "wof:placetype":"venue"
},
  "geometry": {"coordinates":[-1.2160539627,54.681350708],"type":"Point"}
}