{
  "type": "Feature",
  "properties": {
    "iso:country":"GB",
    "sg:address":"Unit 10, 6 Grange Way",
    "sg:city":"Colchester",
    "sg:classifiers":[
        {
            "category":"Home & Garden",
            "subcategory":"Home Furnishings",
            "type":"Retail Goods"
        }
    ],
    "sg:phone":"+44 1206 792793",
    "sg:postcode":"CO2 8HF",
    "sg:province":"Essex",
    "sg:tags":[
        "blind",
        "curtain",
        "fitting"
    ],
    "wof:name":"Gabrielle",
    "wof:placetype":"venue"
},
  "geometry": {"coordinates":[0.928994,51.87183],"type":"Point"}
}