{
  "type": "Feature",
  "properties": {
    "iso:country":"GB",
    "sg:address":"Upbury Manor Marlborough Rd",
    "sg:city":"Gillingham",
    "sg:classifiers":[
        {
            "category":"Professional",
            "type":"Services"
        }
    ],
    "sg:postcode":"ME7 5HR",
    "sg:province":"Kent",
    "sg:tags":[
        "repair",
        "tech",
        "maintenance"
    ],
    "wof:name":"Gibbs,Martin,",
    "wof:placetype":"venue"
},
  "geometry": {"coordinates":[0.5417299867,51.3882408142],"type":"Point"}
}