{
  "type": "Feature",
  "properties": {
    "iso:country":"GB",
    "sg:address":"Orby Road, Addlethorpe",
    "sg:city":"Skegness",
    "sg:classifiers":[
        {
            "category":"Bars & Pubs",
            "type":"Food & Drink"
        }
    ],
    "sg:postcode":"PE24 4TR",
    "sg:province":"Lincolnshire",
    "sg:tags":[
        "pubs",
        "inn"
    ],
    "wof:name":"Kings Head",
    "wof:placetype":"venue"
},
  "geometry": {"coordinates":[0.3173950016,53.1950645447],"type":"Point"}
}