{
  "type": "Feature",
  "properties": {
    "addr:full":"6 Lomond Place, Castlepark Irvine North Ayrshire KA12 9PG",
    "addr:housenumber":"6",
    "addr:postcode":"ka12 9pg",
    "addr:street":"Lomond Place Castlepark",
    "iso:country":"GB",
    "sg:address":"6 Lomond Place, Castlepark",
    "sg:city":"Irvine",
    "sg:classifiers":[
        {
            "category":"Building & Trades",
            "subcategory":"Construction",
            "type":"Services"
        }
    ],
    "sg:phone":"+44 1294 279645",
    "sg:postcode":"KA12 9PG",
    "sg:province":"North Ayrshire",
    "sg:tags":[
        "decorator",
        "painter"
    ],
    "wof:name":"E Paton Painter & Decorator",
    "wof:placetype":"venue"
},
  "geometry": {"coordinates":[-4.659861,55.633259],"type":"Point"}
}