{
  "type": "Feature",
  "properties": {
    "iso:country":"GB",
    "sg:address":"562a Scott Hall Road",
    "sg:city":"Leeds",
    "sg:classifiers":[
        {
            "category":"Health Services",
            "subcategory":"Health Practitioner",
            "type":"Services"
        }
    ],
    "sg:postcode":"LS7 3RD",
    "sg:province":"West Yorkshire",
    "sg:tags":[
        "psychologist"
    ],
    "wof:name":"D H Duckworth Psychologist",
    "wof:placetype":"venue"
},
  "geometry": {"coordinates":[-1.546305,53.829231],"type":"Point"}
}