{
  "type": "Feature",
  "properties": {
    "addr:full":"Unit 14 Avenue 1, Station Lane Witney Oxfordshire OX8 6XX",
    "addr:housenumber":"unit 14;1",
    "addr:postcode":"ox8 6xx",
    "addr:street":"Avenue;Station Lane",
    "iso:country":"GB",
    "sg:address":"Unit 14 Avenue 1, Station Lane",
    "sg:city":"Witney",
    "sg:classifiers":[
        {
            "category":"Shopping",
            "subcategory":"Stationery & Office Supplies",
            "type":"Retail Goods"
        }
    ],
    "sg:phone":"+44 1993 774681",
    "sg:postcode":"OX8 6XX",
    "sg:province":"Oxfordshire",
    "sg:tags":[
        "merchant",
        "paper"
    ],
    "wof:name":"Pollock & Searby",
    "wof:placetype":"venue"
},
  "geometry": {"coordinates":[-1.4895730019,51.7768325806],"type":"Point"}
}