{
  "type": "Feature",
  "properties": {
    "addr:full":"New County Building, Beghcar Street Ebbw Vale Herefordshire NP7 0LW",
    "addr:postcode":"np7 0lw",
    "addr:street":"Beghcar Street",
    "iso:country":"GB",
    "sg:address":"New County Building, Beghcar Street",
    "sg:city":"Ebbw Vale",
    "sg:classifiers":[
        {
            "category":"Professional",
            "subcategory":"Lawyer & Legal Services",
            "type":"Services"
        }
    ],
    "sg:phone":"+44 1495 303124",
    "sg:postcode":"NP7 0LW",
    "sg:province":"Herefordshire",
    "sg:tags":[
        "solicitor"
    ],
    "wof:name":"Fonseca & Co.",
    "wof:placetype":"venue"
},
  "geometry": {"coordinates":[-3.141010046,51.8056983948],"type":"Point"}
}