{
  "type": "Feature",
  "properties": {
    "iso:country":"GB",
    "sg:address":"8-14 Swinbourne Gro, Withington",
    "sg:city":"Manchester",
    "sg:classifiers":[
        {
            "category":"Social Services",
            "subcategory":"Retirement Home",
            "type":"Services"
        },
        {
            "category":"Organizations",
            "subcategory":"Community Association",
            "type":"Services"
        }
    ],
    "sg:phone":"+44 161 434 8717",
    "sg:postcode":"M20 4PP",
    "sg:province":"Greater Manchester",
    "sg:tags":[
        "residential",
        "housing",
        "care",
        "society"
    ],
    "wof:name":"Abbeyfield Mancunian Society Ltd.",
    "wof:placetype":"venue"
},
  "geometry": {"coordinates":[-2.22618,53.434059],"type":"Point"}
}