{
  "type": "Feature",
  "properties": {
    "addr:full":"Saltash College, Church Road Saltash Cornwall PL12 4AE",
    "addr:postcode":"pl12 4ae",
    "addr:street":"Church Road",
    "iso:country":"GB",
    "sg:address":"Saltash College, Church Road",
    "sg:city":"Saltash",
    "sg:classifiers":[
        {
            "category":"Education",
            "subcategory":"Special Training",
            "type":"Public Place"
        }
    ],
    "sg:phone":"+44 1752 840117",
    "sg:postcode":"PL12 4AE",
    "sg:province":"Cornwall",
    "sg:tags":[
        "product",
        "centre"
    ],
    "wof:name":"The Management Centre",
    "wof:placetype":"venue"
},
  "geometry": {"coordinates":[-4.212884,50.408749],"type":"Point"}
}