{
  "type": "Feature",
  "properties": {
    "addr:full":"2177 Paisley Road West Glasgow Glasgow City G52 3PF",
    "addr:housenumber":"2177",
    "addr:postcode":"g52 3pf",
    "addr:street":"Paisley Road West",
    "iso:country":"GB",
    "sg:address":"2177 Paisley Road West",
    "sg:city":"Glasgow",
    "sg:classifiers":[
        {
            "category":"Professional",
            "subcategory":"Business Services",
            "type":"Services"
        }
    ],
    "sg:phone":"+44 141 810 3442",
    "sg:postcode":"G52 3PF",
    "sg:province":"Glasgow City",
    "sg:tags":[
        "import",
        "export",
        "agent"
    ],
    "wof:name":"M E Foundation (The)",
    "wof:placetype":"venue"
},
  "geometry": {"coordinates":[-4.3571419716,55.8456344604],"type":"Point"}
}