{
  "type": "Feature",
  "properties": {
    "addr:full":"201-203 London Rd Liverpool Merseyside L3 8JG",
    "addr:housenumber":"201-203",
    "addr:postcode":"l3 8jg",
    "addr:street":"London Rd",
    "iso:country":"GB",
    "sg:address":"201-203 London Rd",
    "sg:city":"Liverpool",
    "sg:classifiers":[
        {
            "category":"Food & Beverages",
            "subcategory":"Fruits & Vegetables",
            "type":"Retail Goods"
        }
    ],
    "sg:postcode":"L3 8JG",
    "sg:province":"Merseyside",
    "sg:tags":[
        "greengrocer"
    ],
    "wof:name":"Farmhouse Produce (1936) Ltd",
    "wof:placetype":"venue"
},
  "geometry": {"coordinates":[-2.968621,53.410381],"type":"Point"}
}