{
  "type": "Feature",
  "properties": {
    "iso:country":"GB",
    "sg:address":"82 Westminster Drive, Bletchley",
    "sg:city":"Milton Keynes",
    "sg:classifiers":[
        {
            "category":"Building & Trades",
            "subcategory":"Construction",
            "type":"Services"
        }
    ],
    "sg:postcode":"MK3 6LY",
    "sg:province":"Buckinghamshire",
    "sg:tags":[
        "glazier"
    ],
    "wof:name":"Milton Keynes Cab Glazing Services",
    "wof:placetype":"venue"
},
  "geometry": {"coordinates":[-0.746569,52.004162],"type":"Point"}
}