{
  "type": "Feature",
  "properties": {
    "addr:full":"Le Molay, Bovey Tracey Newton Abbot Devon TQ13 9QP",
    "addr:postcode":"tq13 9qp",
    "iso:country":"GB",
    "sg:address":"Le Molay, Bovey Tracey",
    "sg:city":"Newton Abbot",
    "sg:classifiers":[
        {
            "category":"Health Services",
            "subcategory":"Doctor",
            "type":"Services"
        },
        {
            "category":"Health Services",
            "subcategory":"Clinic",
            "type":"Services"
        }
    ],
    "sg:phone":"+44 1626 832666",
    "sg:postcode":"TQ13 9QP",
    "sg:province":"Devon",
    "sg:tags":[
        "nh",
        "practitioners"
    ],
    "wof:name":"Riverside Surgery",
    "wof:placetype":"venue"
},
  "geometry": {"coordinates":[-3.675059,50.593208],"type":"Point"}
}