{
  "type": "Feature",
  "properties": {
    "addr:full":"A34 By-pass, Sutton Scotney Winchester Hampshire SO21 3JY",
    "addr:postcode":"so21 3jy",
    "addr:street":"A34 By-Pass",
    "iso:country":"GB",
    "sg:address":"A34 By-pass, Sutton Scotney",
    "sg:city":"Winchester",
    "sg:classifiers":[
        {
            "category":"Restaurant",
            "type":"Food & Drink"
        }
    ],
    "sg:phone":"+44 1962 760622",
    "sg:postcode":"SO21 3JY",
    "sg:province":"Hampshire",
    "wof:name":"Moto Hospitality Ltd.",
    "wof:placetype":"venue"
},
  "geometry": {"coordinates":[-1.3390510082,51.1757926941],"type":"Point"}
}