{
  "type": "Feature",
  "properties": {
    "iso:country":"GB",
    "sg:address":"Faraday House, Barnwood Business Centre, Barnett Way",
    "sg:city":"Gloucester",
    "sg:classifiers":[
        {
            "category":"Professional",
            "subcategory":"Computer Services",
            "type":"Services"
        }
    ],
    "sg:phone":"+44 1452 612021",
    "sg:postcode":"GL4 3RT",
    "sg:province":"Gloucestershire",
    "sg:tags":[
        "bureau",
        "facility"
    ],
    "wof:name":"Briton Data Services Ltd.",
    "wof:placetype":"venue"
},
  "geometry": {"coordinates":[-2.2093389034,51.8628005981],"type":"Point"}
}