{
  "type": "Feature",
  "properties": {
    "addr:full":"Civic Centre Poole Dorset BH15 2RX",
    "addr:postcode":"bh15 2rx",
    "iso:country":"GB",
    "sg:address":"Civic Centre",
    "sg:city":"Poole",
    "sg:classifiers":[
        {
            "category":"Government",
            "subcategory":"Office",
            "type":"Public Place"
        }
    ],
    "sg:phone":"+44 1202 633690",
    "sg:postcode":"BH15 2RX",
    "sg:province":"Dorset",
    "sg:tags":[
        "education",
        "agency",
        "authority"
    ],
    "wof:name":"Youth Afloat Festival Office",
    "wof:placetype":"venue"
},
  "geometry": {"coordinates":[-1.960983,50.722988],"type":"Point"}
}