{
  "type": "Feature",
  "properties": {
    "iso:country":"GB",
    "sg:address":"8 The Street",
    "sg:city":"Bath",
    "sg:classifiers":[
        {
            "category":"Shopping",
            "subcategory":"Crafts & Fabrics",
            "type":"Retail Goods"
        }
    ],
    "sg:phone":"+44 1761 433930",
    "sg:postcode":"BA3 3PL",
    "sg:province":"Somerset",
    "sg:tags":[
        "shop",
        "needlecraft",
        "wool"
    ],
    "wof:name":"The Knit in",
    "wof:placetype":"venue"
},
  "geometry": {"coordinates":[-2.44789,51.29187],"type":"Point"}
}