{
  "type": "Feature",
  "properties": {
    "iso:country":"GB",
    "sg:address":"16 Scutari Row, Taibach",
    "sg:city":"Port Talbot",
    "sg:classifiers":[
        {
            "category":"Professional",
            "subcategory":"Engineering",
            "type":"Services"
        }
    ],
    "sg:phone":"+44 1639 882662",
    "sg:postcode":"SA13 1TL",
    "sg:province":"Neath Port Talbot",
    "sg:tags":[
        "gas",
        "engineer"
    ],
    "wof:name":"Graham Davies Gas Services",
    "wof:placetype":"venue"
},
  "geometry": {"coordinates":[-3.770434,51.585625],"type":"Point"}
}