{
  "type": "Feature",
  "properties": {
    "iso:country":"GB",
    "sg:address":"192 Beechcroft Road",
    "sg:city":"Swindon",
    "sg:classifiers":[
        {
            "category":"Food & Beverages",
            "subcategory":"Meat & Fish",
            "type":"Retail Goods"
        }
    ],
    "sg:phone":"+44 1793 823084",
    "sg:postcode":"SN2 7QQ",
    "sg:province":"Wiltshire",
    "sg:tags":[
        "chip"
    ],
    "wof:name":"Sims Chippy",
    "wof:placetype":"venue"
},
  "geometry": {"coordinates":[-1.765185,51.589684],"type":"Point"}
}