{
  "type": "Feature",
  "properties": {
    "iso:country":"GB",
    "sg:address":"Elmlea, The Grn, Dunsfold",
    "sg:city":"Godalming",
    "sg:classifiers":[
        {
            "category":"Professional",
            "subcategory":"Management & Consulting",
            "type":"Services"
        }
    ],
    "sg:postcode":"GU8 4LY",
    "sg:province":"Surrey",
    "sg:tags":[
        "consultant",
        "business"
    ],
    "wof:name":"After-Thought Solutions Ltd.",
    "wof:placetype":"venue"
},
  "geometry": {"coordinates":[-0.5627390146,51.1166038513],"type":"Point"}
}