{
  "type": "Feature",
  "properties": {
    "iso:country":"GB",
    "sg:address":"Thame Road, Haddenham",
    "sg:city":"Aylesbury",
    "sg:classifiers":[
        {
            "category":"Building & Trades",
            "subcategory":"Cleaning & Sanitation",
            "type":"Services"
        }
    ],
    "sg:phone":"+44 1844 299244",
    "sg:postcode":"HP17 8BZ",
    "sg:province":"Buckinghamshire",
    "sg:tags":[
        "industrial",
        "business",
        "removal"
    ],
    "wof:name":"Multi-Link Storage Ltd.",
    "wof:placetype":"venue"
},
  "geometry": {"coordinates":[-0.921174,51.775661],"type":"Point"}
}