{
  "type": "Feature",
  "properties": {
    "addr:full":"26 Cabbell Rd Cromer Norfolk NR27 9HX",
    "addr:housenumber":"26",
    "addr:postcode":"nr27 9hx",
    "addr:street":"Cabbell Rd",
    "iso:country":"GB",
    "sg:address":"26 Cabbell Rd",
    "sg:city":"Cromer",
    "sg:classifiers":[
        {
            "category":"Organizations",
            "subcategory":"Non-profit Organization",
            "type":"Services"
        }
    ],
    "sg:phone":"+44 1263 511963",
    "sg:postcode":"NR27 9HX",
    "sg:province":"Norfolk",
    "sg:tags":[
        "organisation",
        "voluntary",
        "charity"
    ],
    "wof:name":"St Matthew Society",
    "wof:placetype":"venue"
},
  "geometry": {"coordinates":[1.295824,52.931507],"type":"Point"}
}