{
  "type": "Feature",
  "properties": {
    "iso:country":"GB",
    "sg:address":"1a West Hynish, Isle Of Tiree",
    "sg:city":"Scarinish",
    "sg:classifiers":[
        {
            "category":"Building & Trades",
            "subcategory":"Construction",
            "type":"Services"
        }
    ],
    "sg:phone":"+44 1879 220692",
    "sg:postcode":"PA77 6UF",
    "sg:province":"Argyll and Bute",
    "sg:tags":[
        "builder"
    ],
    "wof:name":"Bernard D.Smith & Son",
    "wof:placetype":"venue"
},
  "geometry": {"coordinates":[-6.807274,56.501076],"type":"Point"}
}