{
  "type": "Feature",
  "properties": {
    "addr:full":"Prescott Rd, Baschurch Shrewsbury Shropshire SY4 2DR",
    "addr:postcode":"sy4 2dr",
    "addr:street":"Prescott Rd",
    "iso:country":"GB",
    "sg:address":"Prescott Rd, Baschurch",
    "sg:city":"Shrewsbury",
    "sg:classifiers":[
        {
            "category":"Health Services",
            "subcategory":"Clinic",
            "type":"Services"
        }
    ],
    "sg:phone":"+44 1939 261348",
    "sg:postcode":"SY4 2DR",
    "sg:province":"Shropshire",
    "sg:tags":[
        "nh"
    ],
    "wof:name":"Prescott Surgery",
    "wof:placetype":"venue"
},
  "geometry": {"coordinates":[-2.8509800434,52.7883377075],"type":"Point"}
}