{
  "type": "Feature",
  "properties": {
    "iso:country":"GB",
    "sg:address":"Finmere Road",
    "sg:city":"Eastbourne",
    "sg:classifiers":[
        {
            "category":"Retail",
            "subcategory":"Auto Repair",
            "type":"Services"
        }
    ],
    "sg:phone":"+44 1323 643222",
    "sg:postcode":"BN22 8QL",
    "sg:province":"East Sussex",
    "sg:tags":[
        "modification",
        "garage"
    ],
    "wof:name":"Car & Commercial",
    "wof:placetype":"venue"
},
  "geometry": {"coordinates":[0.3021570146,50.7845687866],"type":"Point"}
}