{
  "type": "Feature",
  "properties": {
    "addr:full":"1 Hogarths Court, Great Holm Milton Keynes Buckinghamshire MK8 9HB",
    "addr:housenumber":"1",
    "addr:postcode":"mk8 9hb",
    "addr:street":"Hogarths Court",
    "iso:country":"GB",
    "sg:address":"1 Hogarths Court, Great Holm",
    "sg:city":"Milton Keynes",
    "sg:classifiers":[
        {
            "category":"Autos & Motor Vehicles",
            "subcategory":"Automobile Sales",
            "type":"Retail Goods"
        }
    ],
    "sg:phone":"+44 1908 560380",
    "sg:postcode":"MK8 9HB",
    "sg:province":"Buckinghamshire",
    "sg:tags":[
        "commercial"
    ],
    "wof:name":"Templehire",
    "wof:placetype":"venue"
},
  "geometry": {"coordinates":[-0.7939140201,52.037071228],"type":"Point"}
}