{
  "type": "Feature",
  "properties": {
    "addr:full":"Pullman Ho, Edington Station Yard Westbury Wiltshire BA13 4NT",
    "addr:postcode":"ba13 4nt",
    "iso:country":"GB",
    "sg:address":"Pullman Ho, Edington Station Yard",
    "sg:city":"Westbury",
    "sg:classifiers":[
        {
            "category":"Professional",
            "subcategory":"Detective & Security Services",
            "type":"Services"
        }
    ],
    "sg:phone":"+44 1380 830255",
    "sg:postcode":"BA13 4NT",
    "sg:province":"Wiltshire",
    "wof:name":"Bentham Dinsdale Security",
    "wof:placetype":"venue"
},
  "geometry": {"coordinates":[-2.0966939926,51.2789611816],"type":"Point"}
}