{
  "type": "Feature",
  "properties": {
    "iso:country":"GB",
    "sg:address":"65 Burnley Road, Hapton",
    "sg:city":"Burnley",
    "sg:classifiers":[
        {
            "category":"Shopping",
            "subcategory":"Catalog Store",
            "type":"Retail Goods"
        }
    ],
    "sg:phone":"+44 1282 771109",
    "sg:postcode":"BB11 5QR",
    "sg:province":"Lancashire",
    "sg:tags":[
        "mail",
        "order",
        "house"
    ],
    "wof:name":"B Marsh",
    "wof:placetype":"venue"
},
  "geometry": {"coordinates":[-2.317052,53.772148],"type":"Point"}
}