{
  "type": "Feature",
  "properties": {
    "iso:country":"GB",
    "sg:address":"76 Station Road",
    "sg:city":"Rushden",
    "sg:classifiers":[
        {
            "category":"Organizations",
            "subcategory":"Community Association",
            "type":"Services"
        },
        {
            "category":"Organizations",
            "subcategory":"Membership Organization",
            "type":"Services"
        }
    ],
    "sg:phone":"+44 1933 312587",
    "sg:postcode":"NN10 9SG",
    "sg:province":"Bedfordshire",
    "sg:tags":[
        "club",
        "social"
    ],
    "wof:name":"FOXFORD HOTELS LTD.",
    "wof:placetype":"venue"
},
  "geometry": {"coordinates":[-0.599478,52.293499],"type":"Point"}
}