{
  "type": "Feature",
  "properties": {
    "addr:full":"1st Floor 101 Bath Road, Longwell Grn Bristol Gloucestershire BS30 9DD",
    "addr:housenumber":"101",
    "addr:postcode":"bs30 9dd",
    "addr:street":"Bath Road Longwell Grn",
    "iso:country":"GB",
    "sg:address":"1st Floor 101 Bath Road, Longwell Grn",
    "sg:city":"Bristol",
    "sg:classifiers":[
        {
            "category":"Health Services",
            "subcategory":"Dentist",
            "type":"Services"
        }
    ],
    "sg:postcode":"BS30 9DD",
    "sg:province":"Gloucestershire",
    "wof:name":"Longwell Green Dental Practice",
    "wof:placetype":"venue"
},
  "geometry": {"coordinates":[-2.492867,51.437534],"type":"Point"}
}