{
  "type": "Feature",
  "properties": {
    "addr:full":"Unit 2, Church St, Caldewgate Carlisle Cumbria CA2 5TJ",
    "addr:housenumber":"unit 2",
    "addr:postcode":"ca2 5tj",
    "addr:street":"Church St",
    "iso:country":"GB",
    "sg:address":"Unit 2, Church St, Caldewgate",
    "sg:city":"Carlisle",
    "sg:classifiers":[
        {
            "category":"Professional",
            "subcategory":"Engineering",
            "type":"Services"
        }
    ],
    "sg:phone":"+44 1228 529222",
    "sg:postcode":"CA2 5TJ",
    "sg:province":"Cumbria",
    "sg:tags":[
        "engineer",
        "mechanical"
    ],
    "wof:name":"M Donald Engineering Services",
    "wof:placetype":"venue"
},
  "geometry": {"coordinates":[-2.9480700493,54.8940048218],"type":"Point"}
}