{
  "type": "Feature",
  "properties": {
    "addr:full":"22 Algitha Road Skegness Lincolnshire PE25 2AG",
    "addr:housenumber":"22",
    "addr:postcode":"pe25 2ag",
    "addr:street":"Algitha Road",
    "iso:country":"GB",
    "sg:address":"22 Algitha Road",
    "sg:city":"Skegness",
    "sg:classifiers":[
        {
            "category":"Real Estate",
            "subcategory":"Architect",
            "type":"Services"
        }
    ],
    "sg:postcode":"PE25 2AG",
    "sg:province":"Lincolnshire",
    "wof:name":"Meldrum Lee & Gillatt",
    "wof:placetype":"venue"
},
  "geometry": {"coordinates":[0.3387,53.14436],"type":"Point"}
}