{
  "type": "Feature",
  "properties": {
    "addr:full":"4 Claremont Bank Shrewsbury Shropshire SY1 1RS",
    "addr:housenumber":"4",
    "addr:postcode":"sy1 1rs",
    "addr:street":"Claremont Bank",
    "iso:country":"GB",
    "sg:address":"4 Claremont Bank",
    "sg:city":"Shrewsbury",
    "sg:classifiers":[
        {
            "category":"Professional",
            "subcategory":"Lawyer & Legal Services",
            "type":"Services"
        }
    ],
    "sg:phone":"+44 1743 350571",
    "sg:postcode":"SY1 1RS",
    "sg:province":"Shropshire",
    "sg:tags":[
        "solicitor"
    ],
    "wof:name":"Moss & Poulson",
    "wof:placetype":"venue"
},
  "geometry": {"coordinates":[-2.75894,52.708378],"type":"Point"}
}