{
  "type": "Feature",
  "properties": {
    "iso:country":"GB",
    "sg:address":"Swanlow Lane",
    "sg:city":"Winsford",
    "sg:classifiers":[
        {
            "category":"Bars & Pubs",
            "type":"Food & Drink"
        }
    ],
    "sg:phone":"+44 1606 592027",
    "sg:postcode":"CW7 4BL",
    "sg:province":"Cheshire",
    "sg:tags":[
        "pubs",
        "inn"
    ],
    "wof:name":"The Old Star Inn",
    "wof:placetype":"venue"
},
  "geometry": {"coordinates":[-2.5264348984,53.1772117615],"type":"Point"}
}