{
  "type": "Feature",
  "properties": {
    "addr:full":"Unit 8, Ash Court East Way, Lee Mill Ind Est Ivybridge Devon PL21 9GE",
    "addr:housenumber":"unit 8",
    "addr:postcode":"pl21 9ge",
    "addr:street":"Ash Court East Way Lee",
    "iso:country":"GB",
    "sg:address":"Unit 8, Ash Court East Way, Lee Mill Ind Est",
    "sg:city":"Ivybridge",
    "sg:classifiers":[
        {
            "category":"Wholesale",
            "subcategory":"Construction Materials",
            "type":"Manufacturing & Wholesale Goods"
        }
    ],
    "sg:phone":"+44 1752 698844",
    "sg:postcode":"PL21 9GE",
    "sg:province":"Devon",
    "sg:tags":[
        "cladding"
    ],
    "wof:name":"Jade Aden Sevices Ltd",
    "wof:placetype":"venue"
},
  "geometry": {"coordinates":[-3.9290390015,50.3872642517],"type":"Point"}
}