{
  "type": "Feature",
  "properties": {
    "addr:full":"Granville Road London Greater London N12 0JE",
    "addr:postcode":"n12 0je",
    "addr:street":"Granville Road",
    "iso:country":"GB",
    "sg:address":"Granville Road",
    "sg:city":"London",
    "sg:classifiers":[
        {
            "category":"Health Services",
            "subcategory":"Hospital",
            "type":"Services"
        }
    ],
    "sg:phone":"+44 845 389 2889",
    "sg:postcode":"N12 0JE",
    "sg:province":"Greater London",
    "wof:name":"Finchley Memorial Hospital",
    "wof:placetype":"venue"
},
  "geometry": {"coordinates":[-0.1808979958,51.6074867249],"type":"Point"}
}