{
  "type": "Feature",
  "properties": {
    "addr:full":"15 Manfred Street, Erskine Industrial Estate Liverpool Merseyside L6 1AU",
    "addr:housenumber":"15",
    "addr:postcode":"l6 1au",
    "addr:street":"Manfred Street;Industrial Estate",
    "iso:country":"GB",
    "sg:address":"15 Manfred Street, Erskine Industrial Estate",
    "sg:city":"Liverpool",
    "sg:classifiers":[
        {
            "category":"Home & Garden",
            "subcategory":"Carpets & Floor Coverings",
            "type":"Retail Goods"
        }
    ],
    "sg:phone":"+44 151 260 2000",
    "sg:postcode":"L6 1AU",
    "sg:province":"Merseyside",
    "sg:tags":[
        "wall",
        "tie",
        "replacement"
    ],
    "wof:name":"Clan Contracting Ltd.",
    "wof:placetype":"venue"
},
  "geometry": {"coordinates":[-2.9641079903,53.4115486145],"type":"Point"}
}