{
  "type": "Feature",
  "properties": {
    "addr:full":"7 Tythings Court Minehead Somerset TA24 5NT",
    "addr:housenumber":"7",
    "addr:postcode":"ta24 5nt",
    "addr:street":"Tythings Court",
    "iso:country":"GB",
    "sg:address":"7 Tythings Court",
    "sg:city":"Minehead",
    "sg:classifiers":[
        {
            "category":"Real Estate",
            "subcategory":"Real Estate Agent",
            "type":"Services"
        }
    ],
    "sg:phone":"+44 1643 702771",
    "sg:postcode":"TA24 5NT",
    "sg:province":"Somerset",
    "wof:name":"Renscombe Properties Ltd.",
    "wof:placetype":"venue"
},
  "geometry": {"coordinates":[-3.4803299904,51.2057228088],"type":"Point"}
}