{
  "type": "Feature",
  "properties": {
    "iso:country":"GB",
    "sg:address":"Unit 5-8 Barnes Road Industrial Estate",
    "sg:city":"Bradford",
    "sg:classifiers":[
        {
            "category":"Food & Beverages",
            "subcategory":"Liquor & Beverages",
            "type":"Retail Goods"
        }
    ],
    "sg:phone":"+44 1274 490290",
    "sg:postcode":"BD8 9TG",
    "sg:province":"West Yorkshire",
    "sg:tags":[
        "beer",
        "spirit",
        "wines"
    ],
    "wof:name":"Drinks Direct (U K) Ltd.",
    "wof:placetype":"venue"
},
  "geometry": {"coordinates":[-1.7908250093,53.7973518372],"type":"Point"}
}