{
  "type": "Feature",
  "properties": {
    "iso:country":"GB",
    "sg:address":"14 Mealcheapen St",
    "sg:city":"Worcester",
    "sg:classifiers":[
        {
            "category":"Health Services",
            "subcategory":"Podiatrist",
            "type":"Services"
        }
    ],
    "sg:phone":"+44 1905 25799",
    "sg:postcode":"WR1 2DQ",
    "sg:province":"Worcestershire",
    "sg:tags":[
        "podiatrists",
        "chiropodist"
    ],
    "wof:name":"Scholl Footcare Centres",
    "wof:placetype":"venue"
},
  "geometry": {"coordinates":[-2.222274,52.191067],"type":"Point"}
}