{
  "type": "Feature",
  "properties": {
    "addr:full":"81 King St Southport Lancashire PR8 1LQ",
    "addr:housenumber":"81",
    "addr:postcode":"pr8 1lq",
    "addr:street":"King St",
    "iso:country":"GB",
    "sg:address":"81 King St",
    "sg:city":"Southport",
    "sg:classifiers":[
        {
            "category":"Bars & Pubs",
            "type":"Food & Drink"
        }
    ],
    "sg:phone":"+44 1704 532178",
    "sg:postcode":"PR8 1LQ",
    "sg:province":"Lancashire",
    "sg:tags":[
        "pubs",
        "inn"
    ],
    "wof:name":"Punch Retail Ltd",
    "wof:placetype":"venue"
},
  "geometry": {"coordinates":[-3.0105230808,53.6437034607],"type":"Point"}
}