{
  "type": "Feature",
  "properties": {
    "iso:country":"GB",
    "sg:address":"75-77 Parade",
    "sg:city":"Leamington Spa",
    "sg:classifiers":[
        {
            "category":"Shopping",
            "subcategory":"Shoes",
            "type":"Retail Goods"
        }
    ],
    "sg:phone":"+44 1926 424872",
    "sg:postcode":"CV32 4AY",
    "sg:province":"Warwickshire",
    "sg:tags":[
        "shop"
    ],
    "wof:name":"C & J Clark International Ltd.",
    "wof:placetype":"venue"
},
  "geometry": {"coordinates":[-1.535319,52.290234],"type":"Point"}
}