{
  "type": "Feature",
  "properties": {
    "iso:country":"GB",
    "sg:address":"Huntingdon Business Centre, Blackstone Road, Stukeley Meadows Industrial Estate",
    "sg:city":"Huntingdon",
    "sg:classifiers":[
        {
            "category":"Professional",
            "subcategory":"Engineering",
            "type":"Services"
        }
    ],
    "sg:phone":"+44 1480 437701",
    "sg:postcode":"PE29 6EF",
    "sg:province":"Cambridgeshire",
    "sg:tags":[
        "civil",
        "engineer"
    ],
    "wof:name":"Jackson Civil Engineering Ltd",
    "wof:placetype":"venue"
},
  "geometry": {"coordinates":[-0.189304,52.33514],"type":"Point"}
}