{
  "type": "Feature",
  "properties": {
    "addr:full":"Unit 1 Boulters Road Aldershot Hampshire GU11 1TL",
    "addr:housenumber":"unit 1",
    "addr:postcode":"gu11 1tl",
    "addr:street":"Boulters Road",
    "iso:country":"GB",
    "sg:address":"Unit 1 Boulters Road",
    "sg:city":"Aldershot",
    "sg:classifiers":[
        {
            "category":"Retail",
            "subcategory":"Auto Repair",
            "type":"Services"
        }
    ],
    "sg:phone":"+44 1252 316800",
    "sg:postcode":"GU11 1TL",
    "sg:province":"Hampshire",
    "sg:tags":[
        "modification",
        "garage"
    ],
    "wof:name":"Aldershot Auto Repair Centre",
    "wof:placetype":"venue"
},
  "geometry": {"coordinates":[-0.75618,51.247089],"type":"Point"}
}