{
  "type": "Feature",
  "properties": {
    "addr:full":"277 Comiston Road Edinburgh City of Edinburgh EH10 6AA",
    "addr:housenumber":"277",
    "addr:postcode":"eh10 6aa",
    "addr:street":"Comiston Road",
    "iso:country":"GB",
    "sg:address":"277 Comiston Road",
    "sg:city":"Edinburgh",
    "sg:classifiers":[
        {
            "category":"Autos & Motor Vehicles",
            "subcategory":"Fuel & Gas Station",
            "type":"Retail Goods"
        }
    ],
    "sg:phone":"+44 131 452 8620",
    "sg:postcode":"EH10 6AA",
    "sg:province":"City of Edinburgh",
    "sg:tags":[
        "hr",
        "petrol"
    ],
    "wof:name":"Braidburn Self Serve",
    "wof:placetype":"venue"
},
  "geometry": {"coordinates":[-3.212858,55.918259],"type":"Point"}
}