{
  "type": "Feature",
  "properties": {
    "addr:full":"8 Park View Drive, Long Ashes Park, Threshfield Skipton Lancashire BD23 5PZ",
    "addr:housenumber":"8",
    "addr:postcode":"bd23 5pz",
    "addr:street":"Park View Drive;Ashes Park",
    "iso:country":"GB",
    "sg:address":"8 Park View Drive, Long Ashes Park, Threshfield",
    "sg:city":"Skipton",
    "sg:classifiers":[
        {
            "category":"Home & Garden",
            "subcategory":"Home Furnishings",
            "type":"Retail Goods"
        }
    ],
    "sg:postcode":"BD23 5PZ",
    "sg:province":"Lancashire",
    "sg:tags":[
        "awning",
        "canopy",
        "blinds"
    ],
    "wof:name":"Grassington Blinds",
    "wof:placetype":"venue"
},
  "geometry": {"coordinates":[-2.0311789513,54.0790328979],"type":"Point"}
}