{
  "type": "Feature",
  "properties": {
    "iso:country":"GB",
    "sg:address":"Morris And Associates, 4 Henrietta Street",
    "sg:city":"London",
    "sg:classifiers":[
        {
            "category":"Arts & Performance",
            "subcategory":"Theater",
            "type":"Entertainment"
        }
    ],
    "sg:phone":"+44 20 8302 7614",
    "sg:postcode":"WC2E 8PS",
    "sg:province":"Greater London",
    "sg:tags":[
        "theatrical",
        "agency"
    ],
    "wof:name":"Sally Vaughan  &  Richard Jordan Ltd",
    "wof:placetype":"venue"
},
  "geometry": {"coordinates":[-0.12387,51.510948],"type":"Point"}
}