{
  "type": "Feature",
  "properties": {
    "addr:full":"9 Quinton Parade Coventry Warwickshire CV3 5HW",
    "addr:housenumber":"9",
    "addr:postcode":"cv3 5hw",
    "addr:street":"Quinton Parade",
    "iso:country":"GB",
    "sg:address":"9 Quinton Parade",
    "sg:city":"Coventry",
    "sg:classifiers":[
        {
            "category":"Health Services",
            "subcategory":"Optometrist",
            "type":"Services"
        },
        {
            "category":"Shopping",
            "subcategory":"Optician",
            "type":"Retail Goods"
        }
    ],
    "sg:phone":"+44 24 7650 6300",
    "sg:postcode":"CV3 5HW",
    "sg:province":"Warwickshire",
    "sg:tags":[
        "ophthalmic"
    ],
    "wof:name":"Clarke Opticians",
    "wof:placetype":"venue"
},
  "geometry": {"coordinates":[-1.508181,52.398151],"type":"Point"}
}