{
  "type": "Feature",
  "properties": {
    "addr:full":"675 Oxford Road Reading Berkshire RG30 1HP",
    "addr:housenumber":"675",
    "addr:postcode":"rg30 1hp",
    "addr:street":"Oxford Road",
    "iso:country":"GB",
    "sg:address":"675 Oxford Road",
    "sg:city":"Reading",
    "sg:classifiers":[
        {
            "category":"Shopping",
            "subcategory":"News",
            "type":"Retail Goods"
        }
    ],
    "sg:postcode":"RG30 1HP",
    "sg:province":"Berkshire",
    "sg:tags":[
        "newsagent"
    ],
    "wof:name":"Raj Cornerstore",
    "wof:placetype":"venue"
},
  "geometry": {"coordinates":[-1.0080490112,51.4597663879],"type":"Point"}
}