{
  "type": "Feature",
  "properties": {
    "addr:full":"Holly Dene, Wenham Road, Copdock Ipswich Suffolk IP8 3EY",
    "addr:postcode":"ip8 3ey",
    "addr:street":"Dene Wenham Road",
    "iso:country":"GB",
    "sg:address":"Holly Dene, Wenham Road, Copdock",
    "sg:city":"Ipswich",
    "sg:classifiers":[
        {
            "category":"Building & Trades",
            "subcategory":"Landscaping Services",
            "type":"Services"
        }
    ],
    "sg:postcode":"IP8 3EY",
    "sg:province":"Suffolk",
    "sg:tags":[
        "forestry",
        "tree"
    ],
    "wof:name":"K A Potter",
    "wof:placetype":"venue"
},
  "geometry": {"coordinates":[1.082395,52.030773],"type":"Point"}
}