{
  "type": "Feature",
  "properties": {
    "addr:full":"15 Rydal Rd Streatham Greater London SW16 1QF",
    "addr:housenumber":"15",
    "addr:postcode":"sw16 1qf",
    "addr:street":"Rydal Rd",
    "iso:country":"GB",
    "sg:address":"15 Rydal Rd",
    "sg:city":"Streatham",
    "sg:classifiers":[
        {
            "category":"Professional",
            "subcategory":"Lawyer & Legal Services",
            "type":"Services"
        }
    ],
    "sg:phone":"+44 20 8696 0148",
    "sg:postcode":"SW16 1QF",
    "sg:province":"Greater London",
    "sg:tags":[
        "advice",
        "counselling"
    ],
    "wof:name":"Drink Crisis Centre Womens Services The",
    "wof:placetype":"venue"
},
  "geometry": {"coordinates":[-0.136018,51.428013],"type":"Point"}
}