{
  "type": "Feature",
  "properties": {
    "addr:full":"Terregles Street Dumfries Dumfries and Galloway DG2 9DX",
    "addr:postcode":"dg2 9dx",
    "addr:street":"Terregles Street",
    "iso:country":"GB",
    "sg:address":"Terregles Street",
    "sg:city":"Dumfries",
    "sg:classifiers":[
        {
            "category":"Sports & Exercise",
            "subcategory":"Tennis Court",
            "type":"Entertainment"
        }
    ],
    "sg:phone":"+44 1387 259009",
    "sg:postcode":"DG2 9DX",
    "sg:province":"Dumfries and Galloway",
    "sg:tags":[
        "breakdown",
        "recovery"
    ],
    "wof:name":"Border Cars Recovery",
    "wof:placetype":"venue"
},
  "geometry": {"coordinates":[-3.6270689964,55.070098877],"type":"Point"}
}