{
  "type": "Feature",
  "properties": {
    "addr:full":"Westbourne Manor, 17 Westbourne Rd Birmingham West Midlands B15 3TR",
    "addr:housenumber":"17",
    "addr:postcode":"b15 3tr",
    "addr:street":"Westbourne Rd",
    "iso:country":"GB",
    "sg:address":"Westbourne Manor, 17 Westbourne Rd",
    "sg:city":"Birmingham",
    "sg:classifiers":[
        {
            "category":"Retail",
            "subcategory":"Storage",
            "type":"Services"
        }
    ],
    "sg:phone":"+44 121 693 5555",
    "sg:postcode":"B15 3TR",
    "sg:province":"West Midlands",
    "sg:tags":[
        "household",
        "removal"
    ],
    "wof:name":"Pertemp Image Bureau",
    "wof:placetype":"venue"
},
  "geometry": {"coordinates":[-1.9086040258,52.4785957336],"type":"Point"}
}