{
  "type": "Feature",
  "properties": {
    "addr:full":"4 High Street, Twyford Reading Berkshire RG10 9AE",
    "addr:housenumber":"4",
    "addr:postcode":"rg10 9ae",
    "addr:street":"High Street",
    "iso:country":"GB",
    "sg:address":"4 High Street, Twyford",
    "sg:city":"Reading",
    "sg:classifiers":[
        {
            "category":"Manufacturing",
            "subcategory":"Electronics",
            "type":"Manufacturing & Wholesale Goods"
        }
    ],
    "sg:phone":"+44 118 934 2000",
    "sg:postcode":"RG10 9AE",
    "sg:province":"Berkshire",
    "sg:tags":[
        "printed",
        "circuit"
    ],
    "wof:name":"Abra Cad Plc",
    "wof:placetype":"venue"
},
  "geometry": {"coordinates":[-0.86727,51.477539],"type":"Point"}
}