{
  "type": "Feature",
  "properties": {
    "addr:full":"Hindsleys Pl, 29 Hindsleys Pl Forest Hill Greater London SE23 2NF",
    "addr:housenumber":"29",
    "addr:postcode":"se23 2nf",
    "addr:street":"Hindsleys Pl;Pl",
    "iso:country":"GB",
    "sg:address":"Hindsleys Pl, 29 Hindsleys Pl",
    "sg:city":"Forest Hill",
    "sg:classifiers":[
        {
            "category":"Professional",
            "subcategory":"Business Services",
            "type":"Services"
        }
    ],
    "sg:phone":"+44 20 8699 9948",
    "sg:postcode":"SE23 2NF",
    "sg:province":"Greater London",
    "sg:tags":[
        "accomodation"
    ],
    "wof:name":"Hindsleys Business Centre",
    "wof:placetype":"venue"
},
  "geometry": {"coordinates":[-0.048113,51.441051],"type":"Point"}
}