{
  "type": "Feature",
  "properties": {
    "addr:full":"105 North St Cambridge Cambridgeshire CB5 0BB",
    "addr:housenumber":"105",
    "addr:postcode":"cb5 0bb",
    "addr:street":"North St",
    "iso:country":"GB",
    "sg:address":"105 North St",
    "sg:city":"Cambridge",
    "sg:classifiers":[
        {
            "category":"Government",
            "subcategory":"Post Office",
            "type":"Public Place"
        }
    ],
    "sg:phone":"+44 1638 742617",
    "sg:postcode":"CB5 0BB",
    "sg:province":"Cambridgeshire",
    "sg:tags":[
        "messenger",
        "courier"
    ],
    "wof:name":"Sonic Express Transport",
    "wof:placetype":"venue"
},
  "geometry": {"coordinates":[0.326222986,52.2863731384],"type":"Point"}
}