{
  "type": "Feature",
  "properties": {
    "iso:country":"GB",
    "sg:address":"66 Albert Rd",
    "sg:city":"Wolverhampton",
    "sg:classifiers":[
        {
            "category":"Place Of Worship",
            "type":"Public Place"
        }
    ],
    "sg:phone":"+44 1902 712935",
    "sg:postcode":"WV6 0AF",
    "sg:province":"Shropshire",
    "wof:name":"St Andrew's Vicarage",
    "wof:placetype":"venue"
},
  "geometry": {"coordinates":[-2.1456689835,52.5915489197],"type":"Point"}
}