{
  "type": "Feature",
  "properties": {
    "iso:country":"GB",
    "sg:address":"5 East Street",
    "sg:city":"Shoreham-by-sea",
    "sg:classifiers":[
        {
            "category":"Freight",
            "type":"Transportation"
        }
    ],
    "sg:postcode":"BN43 5ZE",
    "sg:province":"West Sussex",
    "sg:tags":[
        "overseas",
        "shipping",
        "removal"
    ],
    "wof:name":"Abacus Freight Services",
    "wof:placetype":"venue"
},
  "geometry": {"coordinates":[-0.274699,50.83194],"type":"Point"}
}