{
  "type": "Feature",
  "properties": {
    "iso:country":"GB",
    "sg:address":"1 Wake Green Road",
    "sg:city":"Tipton",
    "sg:classifiers":[
        {
            "category":"Professional",
            "type":"Services"
        }
    ],
    "sg:phone":"+44 121 505 3236",
    "sg:postcode":"DY4 0AS",
    "sg:province":"West Midlands",
    "sg:tags":[
        "caterer"
    ],
    "wof:name":"Munchies",
    "wof:placetype":"venue"
},
  "geometry": {"coordinates":[-2.054328,52.546455],"type":"Point"}
}