{
  "type": "Feature",
  "properties": {
    "addr:full":"1770 Coventry Road, South Yardley Birmingham West Midlands B26 1PB",
    "addr:housenumber":"1770",
    "addr:postcode":"b26 1pb",
    "addr:street":"Coventry Road South",
    "iso:country":"GB",
    "sg:address":"1770 Coventry Road, South Yardley",
    "sg:city":"Birmingham",
    "sg:classifiers":[
        {
            "category":"Shopping",
            "subcategory":"Bicycles & Sporting Goods",
            "type":"Retail Goods"
        },
        {
            "category":"Recreation",
            "subcategory":"Fishing",
            "type":"Entertainment"
        }
    ],
    "sg:phone":"+44 121 743 0448",
    "sg:postcode":"B26 1PB",
    "sg:province":"West Midlands",
    "sg:tags":[
        "equipment",
        "angling"
    ],
    "wof:name":"The Fishing Lodge",
    "wof:placetype":"venue"
},
  "geometry": {"coordinates":[-1.802439,52.460629],"type":"Point"}
}