{
  "type": "Feature",
  "properties": {
    "addr:full":"Unit A7, The Dresser Centre, Openshaw Manchester Greater Manchester M11 2NE",
    "addr:housenumber":"a7",
    "addr:postcode":"m11 2ne",
    "addr:street":"The Dresser Centre",
    "iso:country":"GB",
    "sg:address":"Unit A7, The Dresser Centre, Openshaw",
    "sg:city":"Manchester",
    "sg:classifiers":[
        {
            "category":"Home & Garden",
            "subcategory":"Building Materials",
            "type":"Retail Goods"
        }
    ],
    "sg:phone":"+44 161 223 2640",
    "sg:postcode":"M11 2NE",
    "sg:province":"Greater Manchester",
    "sg:tags":[
        "insulation",
        "installers"
    ],
    "wof:name":"L Wynne & Co",
    "wof:placetype":"venue"
},
  "geometry": {"coordinates":[-2.1809539795,53.4734611511],"type":"Point"}
}