{
  "type": "Feature",
  "properties": {
    "addr:full":"Within Defence Mall Centre, 1-140a Pp3 Ivy Lane Portsmouth Hampshire PO1 3NH",
    "addr:housenumber":"1-140a",
    "addr:postcode":"hampshire po1 3nh",
    "addr:street":"Pp3 Ivy Lane",
    "iso:country":"GB",
    "sg:address":"Within Defence Mall Centre, 1-140a Pp3 Ivy Lane",
    "sg:city":"Portsmouth",
    "sg:classifiers":[
        {
            "category":"Building & Trades",
            "subcategory":"Cleaning & Sanitation",
            "type":"Services"
        }
    ],
    "sg:phone":"+44 23 9272 5473",
    "sg:postcode":"PO1 3NH",
    "sg:province":"Hampshire",
    "sg:tags":[
        "commercial"
    ],
    "wof:name":"Oceanclean Ltd",
    "wof:placetype":"venue"
},
  "geometry": {"coordinates":[-1.087284,50.804008],"type":"Point"}
}