{
  "type": "Feature",
  "properties": {
    "addr:full":"Woodbank House Stockport Cheshire SK1 1YJ",
    "addr:postcode":"sk1 1yj",
    "addr:street":"Stockport",
    "iso:country":"GB",
    "sg:address":"Woodbank House",
    "sg:city":"Stockport",
    "sg:classifiers":[
        {
            "category":"Professional",
            "subcategory":"Printing & Photocopies",
            "type":"Services"
        }
    ],
    "sg:phone":"+44 161 474 0085",
    "sg:postcode":"SK1 1YJ",
    "sg:province":"Cheshire",
    "sg:tags":[
        "duplicating",
        "copying"
    ],
    "wof:name":"Woodbank Office Supplies",
    "wof:placetype":"venue"
},
  "geometry": {"coordinates":[-2.15193,53.40921],"type":"Point"}
}