{
  "type": "Feature",
  "properties": {
    "addr:full":"60 Lichfield Road Tamworth Staffordshire B79 7QW",
    "addr:housenumber":"60",
    "addr:postcode":"b79 7qw",
    "addr:street":"Lichfield Road",
    "iso:country":"GB",
    "sg:address":"60 Lichfield Road",
    "sg:city":"Tamworth",
    "sg:classifiers":[
        {
            "category":"Travel",
            "subcategory":"Travel Agent",
            "type":"Entertainment"
        }
    ],
    "sg:phone":"+44 1827 311655",
    "sg:postcode":"B79 7QW",
    "sg:province":"Staffordshire",
    "wof:name":"Kwik Travel Ltd.",
    "wof:placetype":"venue"
},
  "geometry": {"coordinates":[-1.7102539539,52.6347351074],"type":"Point"}
}