{
  "type": "Feature",
  "properties": {
    "iso:country":"GB",
    "sg:address":"Railway Street, Earlestown",
    "sg:city":"Newton-le-willows",
    "sg:classifiers":[
        {
            "category":"Recreation",
            "type":"Entertainment"
        }
    ],
    "sg:postcode":"WA12 9QY",
    "sg:province":"Cheshire",
    "sg:tags":[
        "snooker",
        "billiards",
        "pool"
    ],
    "wof:name":"Top Break",
    "wof:placetype":"venue"
},
  "geometry": {"coordinates":[-2.6368989944,53.4515419006],"type":"Point"}
}