{
  "type": "Feature",
  "properties": {
    "iso:country":"GB",
    "sg:address":"11-19 Reform Street",
    "sg:city":"Dundee",
    "sg:classifiers":[
        {
            "category":"Professional",
            "subcategory":"Accounting & Tax Preparation",
            "type":"Services"
        }
    ],
    "sg:phone":"+44 1382 322637",
    "sg:postcode":"DD1 1SG",
    "sg:province":"Dundee City",
    "sg:tags":[
        "accountant",
        "chartered"
    ],
    "wof:name":"Johnstone Logie & Millar",
    "wof:placetype":"venue"
},
  "geometry": {"coordinates":[-2.970216,56.46096],"type":"Point"}
}