{
  "type": "Feature",
  "properties": {
    "addr:full":"The Old Cider Works, Totnes Road, Abbotskerswell Newton Abbot Devon TQ12 5NF",
    "addr:postcode":"tq12 5nf",
    "addr:street":"Totnes Road",
    "iso:country":"GB",
    "sg:address":"The Old Cider Works, Totnes Road, Abbotskerswell",
    "sg:city":"Newton Abbot",
    "sg:classifiers":[
        {
            "category":"Retail",
            "subcategory":"Auto Repair",
            "type":"Services"
        }
    ],
    "sg:postcode":"TQ12 5NF",
    "sg:province":"Devon",
    "sg:tags":[
        "body",
        "car"
    ],
    "wof:name":"Samsons Motors",
    "wof:placetype":"venue"
},
  "geometry": {"coordinates":[-3.614379,50.508598],"type":"Point"}
}