{
  "type": "Feature",
  "properties": {
    "addr:full":"4 Riley Street Jarrow Tyne and Wear NE32 3ND",
    "addr:housenumber":"4",
    "addr:postcode":"ne32 3nd",
    "addr:street":"Riley Street",
    "iso:country":"GB",
    "sg:address":"4 Riley Street",
    "sg:city":"Jarrow",
    "sg:classifiers":[
        {
            "category":"Wholesale",
            "subcategory":"Scrap",
            "type":"Manufacturing & Wholesale Goods"
        }
    ],
    "sg:postcode":"NE32 3ND",
    "sg:province":"Tyne and Wear",
    "sg:tags":[
        "breaker",
        "dismantlers"
    ],
    "wof:name":"Kings Auto Dismantlers",
    "wof:placetype":"venue"
},
  "geometry": {"coordinates":[-1.5003,54.982189],"type":"Point"}
}