{
  "type": "Feature",
  "properties": {
    "addr:full":"Unit 30 Ddole Enterprise Park Llandrindod Wells Powys LD1 6DS",
    "addr:housenumber":"unit 30 ddole",
    "addr:postcode":"ld1 6ds",
    "addr:street":"Enterprise Park",
    "iso:country":"GB",
    "sg:address":"Unit 30 Ddole Enterprise Park",
    "sg:city":"Llandrindod Wells",
    "sg:classifiers":[
        {
            "category":"Social Services",
            "type":"Services"
        }
    ],
    "sg:phone":"+44 1597 825989",
    "sg:postcode":"LD1 6DS",
    "sg:province":"Powys",
    "wof:name":"Citizens Advocacy Mid Powys",
    "wof:placetype":"venue"
},
  "geometry": {"coordinates":[-3.3754329681,52.2536621094],"type":"Point"}
}