{
  "type": "Feature",
  "properties": {
    "iso:country":"GB",
    "sg:address":"59 Albert Street, Western Hill",
    "sg:city":"Durham",
    "sg:classifiers":[
        {
            "category":"Arts & Performance",
            "subcategory":"Arts Center",
            "type":"Entertainment"
        }
    ],
    "sg:postcode":"DH1 4RJ",
    "sg:province":"Durham",
    "sg:tags":[
        "centre"
    ],
    "wof:name":"Chaplaincy to the Arts & Recreation",
    "wof:placetype":"venue"
},
  "geometry": {"coordinates":[-1.5860190392,54.7797393799],"type":"Point"}
}