{
  "type": "Feature",
  "properties": {
    "addr:full":"318 Lincoln Road Peterborough Cambridgeshire PE1 2ND",
    "addr:housenumber":"318",
    "addr:postcode":"pe1 2nd",
    "addr:street":"Lincoln Road",
    "iso:country":"GB",
    "sg:address":"318 Lincoln Road",
    "sg:city":"Peterborough",
    "sg:classifiers":[
        {
            "category":"Shopping",
            "subcategory":"News",
            "type":"Retail Goods"
        }
    ],
    "sg:phone":"+44 1733 754195",
    "sg:postcode":"PE1 2ND",
    "sg:province":"Cambridgeshire",
    "sg:tags":[
        "newsagent"
    ],
    "wof:name":"Bretts Newsagent",
    "wof:placetype":"venue"
},
  "geometry": {"coordinates":[-0.248249,52.588387],"type":"Point"}
}