{
  "type": "Feature",
  "properties": {
    "addr:full":"107a Turnbull Drive Leicester Leicestershire LE3 2JW",
    "addr:housenumber":"107a",
    "addr:postcode":"le3 2jw",
    "addr:street":"Turnbull Drive",
    "iso:country":"GB",
    "sg:address":"107a Turnbull Drive",
    "sg:city":"Leicester",
    "sg:classifiers":[
        {
            "category":"Shopping",
            "subcategory":"Pharmacy",
            "type":"Retail Goods"
        }
    ],
    "sg:postcode":"LE3 2JW",
    "sg:province":"Leicestershire",
    "sg:tags":[
        "pharmacist",
        "chemist"
    ],
    "wof:name":"Patel N P",
    "wof:placetype":"venue"
},
  "geometry": {"coordinates":[-1.1778290272,52.6098442078],"type":"Point"}
}