{
  "type": "Feature",
  "properties": {
    "addr:full":"Main Street, Burley In Wharfedale Ilkley North Yorkshire LS29 7DN",
    "addr:postcode":"ls29 7dn",
    "addr:street":"Main Street",
    "iso:country":"GB",
    "sg:address":"Main Street, Burley In Wharfedale",
    "sg:city":"Ilkley",
    "sg:classifiers":[
        {
            "category":"Retail",
            "subcategory":"Auto Repair",
            "type":"Services"
        }
    ],
    "sg:phone":"+44 1943 864808",
    "sg:postcode":"LS29 7DN",
    "sg:province":"North Yorkshire",
    "sg:tags":[
        "modification",
        "garage"
    ],
    "wof:name":"McC",
    "wof:placetype":"venue"
},
  "geometry": {"coordinates":[-1.753334,53.915257],"type":"Point"}
}