{
  "type": "Feature",
  "properties": {
    "addr:full":"655 High Road, Leyton London Greater London E10 6RA",
    "addr:housenumber":"655",
    "addr:postcode":"e10 6ra",
    "addr:street":"High Road",
    "iso:country":"GB",
    "sg:address":"655 High Road, Leyton",
    "sg:city":"London",
    "sg:classifiers":[
        {
            "category":"Retail",
            "subcategory":"Veterinary Services",
            "type":"Services"
        }
    ],
    "sg:phone":"+44 20 8539 3538",
    "sg:postcode":"E10 6RA",
    "sg:province":"Greater London",
    "sg:tags":[
        "surgeon"
    ],
    "wof:name":"R E Gardner & Associates",
    "wof:placetype":"venue"
},
  "geometry": {"coordinates":[-0.0085000005,51.570930481],"type":"Point"}
}