{
  "type": "Feature",
  "properties": {
    "iso:country":"GB",
    "sg:address":"70-72 Adelaide St",
    "sg:city":"Blackpool",
    "sg:classifiers":[
        {
            "category":"Travel",
            "subcategory":"Hotels & Motels",
            "type":"Entertainment"
        }
    ],
    "sg:phone":"+44 1253 623113",
    "sg:postcode":"FY1 4LA",
    "sg:province":"Lancashire",
    "wof:name":"New Central Hotel (The)",
    "wof:placetype":"venue"
},
  "geometry": {"coordinates":[-3.0490169525,53.8171272278],"type":"Point"}
}