{
  "type": "Feature",
  "properties": {
    "iso:country":"GB",
    "sg:address":"Marlborough Gardens",
    "sg:city":"Upminster",
    "sg:classifiers":[
        {
            "category":"Place Of Worship",
            "type":"Public Place"
        }
    ],
    "sg:phone":"+44 1708 222562",
    "sg:postcode":"RM14 1LD",
    "sg:province":"Essex",
    "wof:name":"Cranham Community Church",
    "wof:placetype":"venue"
},
  "geometry": {"coordinates":[0.266045,51.568424],"type":"Point"}
}