{
  "type": "Feature",
  "properties": {
    "addr:full":"Unit 15 Springvale Indust Est Cwmbran Monmouthshire NP44 5BA",
    "addr:housenumber":"unit 15",
    "addr:postcode":"np44 5ba",
    "iso:country":"GB",
    "sg:address":"Unit 15 Springvale Indust Est",
    "sg:city":"Cwmbran",
    "sg:classifiers":[
        {
            "category":"Professional",
            "subcategory":"Engineering",
            "type":"Services"
        }
    ],
    "sg:phone":"+44 1633 869141",
    "sg:postcode":"NP44 5BA",
    "sg:province":"Monmouthshire",
    "sg:tags":[
        "contractor",
        "electrical",
        "engineer"
    ],
    "wof:name":"Electrical Repairs Wales Ltd",
    "wof:placetype":"venue"
},
  "geometry": {"coordinates":[-3.0367639065,51.656703949],"type":"Point"}
}