{
  "type": "Feature",
  "properties": {
    "iso:country":"GB",
    "sg:address":"19-21 Barton Road, Worsley",
    "sg:city":"Manchester",
    "sg:classifiers":[
        {
            "category":"Shopping",
            "subcategory":"News",
            "type":"Retail Goods"
        }
    ],
    "sg:phone":"+44 161 794 1567",
    "sg:postcode":"M28 2PD",
    "sg:province":"Greater Manchester",
    "sg:tags":[
        "newsagent"
    ],
    "wof:name":"Village Newsagents",
    "wof:placetype":"venue"
},
  "geometry": {"coordinates":[-2.380588,53.498665],"type":"Point"}
}