{
  "type": "Feature",
  "properties": {
    "addr:full":"39a Friars Wk Lewes East Sussex BN7 2LG",
    "addr:housenumber":"39a",
    "addr:postcode":"bn7 2lg",
    "addr:street":"Friars Wk",
    "iso:country":"GB",
    "sg:address":"39a Friars Wk",
    "sg:city":"Lewes",
    "sg:classifiers":[
        {
            "category":"Autos & Motor Vehicles",
            "subcategory":"Auto Supplies",
            "type":"Retail Goods"
        }
    ],
    "sg:phone":"+44 1273 471000",
    "sg:postcode":"BN7 2LG",
    "sg:province":"East Sussex",
    "sg:tags":[
        "component"
    ],
    "wof:name":"Lewes Motor Factors",
    "wof:placetype":"venue"
},
  "geometry": {"coordinates":[0.0143200001,50.8734741211],"type":"Point"}
}