{
  "type": "Feature",
  "properties": {
    "iso:country":"GB",
    "sg:address":"Waterloo Road",
    "sg:city":"Clitheroe",
    "sg:classifiers":[
        {
            "category":"Real Estate",
            "subcategory":"Architect",
            "type":"Services"
        }
    ],
    "sg:postcode":"BB7 1LR",
    "sg:province":"Lancashire",
    "wof:name":"Ivan Wilson Architect",
    "wof:placetype":"venue"
},
  "geometry": {"coordinates":[-2.3868720531,53.8746376038],"type":"Point"}
}