{
  "type": "Feature",
  "properties": {
    "addr:full":"Springplace Mills, Shill Bank Lane Mirfield West Yorkshire WF14 0QX",
    "addr:postcode":"wf14 0qx",
    "addr:street":"Bank Lane",
    "iso:country":"GB",
    "sg:address":"Springplace Mills, Shill Bank Lane",
    "sg:city":"Mirfield",
    "sg:classifiers":[
        {
            "category":"Manufacturing",
            "subcategory":"Textiles",
            "type":"Manufacturing & Wholesale Goods"
        }
    ],
    "sg:phone":"+44 1924 493128",
    "sg:postcode":"WF14 0QX",
    "sg:province":"West Yorkshire",
    "sg:tags":[
        "knitwear"
    ],
    "wof:name":"Thornton Kelley & Co. Ltd.",
    "wof:placetype":"venue"
},
  "geometry": {"coordinates":[-1.6967099905,53.6749382019],"type":"Point"}
}