{
  "type": "Feature",
  "properties": {
    "addr:full":"50 Naval Ho, Naval Row London Greater London E14 9PS",
    "addr:housenumber":"50",
    "addr:postcode":"e14 9ps",
    "addr:street":"Naval Ho Naval Row",
    "iso:country":"GB",
    "sg:address":"50 Naval Ho, Naval Row",
    "sg:city":"London",
    "sg:classifiers":[
        {
            "category":"Professional",
            "subcategory":"Management & Consulting",
            "type":"Services"
        }
    ],
    "sg:phone":"+44 20 7538 9090",
    "sg:postcode":"E14 9PS",
    "sg:province":"Greater London",
    "sg:tags":[
        "consultant",
        "business"
    ],
    "wof:name":"Rexa Facilitations Ltd",
    "wof:placetype":"venue"
},
  "geometry": {"coordinates":[-0.005009,51.509178],"type":"Point"}
}