{
  "type": "Feature",
  "properties": {
    "addr:full":"44-45 Coombe St Lyme Regis Devon DT7 3PY",
    "addr:housenumber":"44-45",
    "addr:postcode":"dt7 3py",
    "addr:street":"Coombe St",
    "iso:country":"GB",
    "sg:address":"44-45 Coombe St",
    "sg:city":"Lyme Regis",
    "sg:classifiers":[
        {
            "category":"Shopping",
            "subcategory":"Antiques",
            "type":"Retail Goods"
        }
    ],
    "sg:phone":"+44 1297 445371",
    "sg:postcode":"DT7 3PY",
    "sg:province":"Devon",
    "wof:name":"Gemini",
    "wof:placetype":"venue"
},
  "geometry": {"coordinates":[-2.9328789711,50.7250976562],"type":"Point"}
}