{
  "type": "Feature",
  "properties": {
    "iso:country":"GB",
    "sg:address":"79 Dovehouse Close, Eynsham",
    "sg:city":"Witney",
    "sg:classifiers":[
        {
            "category":"Professional",
            "subcategory":"Management & Consulting",
            "type":"Services"
        },
        {
            "category":"Professional",
            "subcategory":"Computer Services",
            "type":"Services"
        }
    ],
    "sg:postcode":"OX29 4EW",
    "sg:province":"Oxfordshire",
    "sg:tags":[
        "development",
        "consultant",
        "business",
        "software"
    ],
    "wof:name":"H.M.D. Consultants Ltd",
    "wof:placetype":"venue"
},
  "geometry": {"coordinates":[-1.367637,51.785866],"type":"Point"}
}