{
  "type": "Feature",
  "properties": {
    "addr:full":"63-65 Clarence St Kingston-upon-thames Greater London KT1 1RB",
    "addr:housenumber":"63-65",
    "addr:postcode":"kt1 1rb",
    "addr:street":"Clarence St",
    "iso:country":"GB",
    "sg:address":"63-65 Clarence St",
    "sg:city":"Kingston-upon-thames",
    "sg:classifiers":[
        {
            "category":"Shopping",
            "subcategory":"Shoes",
            "type":"Retail Goods"
        }
    ],
    "sg:postcode":"KT1 1RB",
    "sg:province":"Greater London",
    "sg:tags":[
        "shop"
    ],
    "wof:name":"Stylo Barratt Shoes Ltd",
    "wof:placetype":"venue"
},
  "geometry": {"coordinates":[-0.3032400012,51.4109191895],"type":"Point"}
}