{
  "type": "Feature",
  "properties": {
    "addr:full":"155 Tamworth Road, Amington Tamworth Staffordshire B77 3BY",
    "addr:housenumber":"155",
    "addr:postcode":"b77 3by",
    "addr:street":"Tamworth Road",
    "iso:country":"GB",
    "sg:address":"155 Tamworth Road, Amington",
    "sg:city":"Tamworth",
    "sg:classifiers":[
        {
            "category":"Personal",
            "subcategory":"Beauty Salon",
            "type":"Services"
        }
    ],
    "sg:postcode":"B77 3BY",
    "sg:province":"Staffordshire",
    "sg:tags":[
        "unisex",
        "hairdresser"
    ],
    "wof:name":"Susan Marklew",
    "wof:placetype":"venue"
},
  "geometry": {"coordinates":[-1.658924,52.636238],"type":"Point"}
}