{
  "type": "Feature",
  "properties": {
    "iso:country":"GB",
    "sg:address":"1 Ramsden Road, Rotherwos",
    "sg:city":"Hereford",
    "sg:classifiers":[
        {
            "category":"Professional",
            "subcategory":"Business Services",
            "type":"Services"
        },
        {
            "category":"Manufacturing",
            "subcategory":"Building Materials",
            "type":"Manufacturing & Wholesale Goods"
        }
    ],
    "sg:phone":"+44 1432 277747",
    "sg:postcode":"HR2 6LR",
    "sg:province":"Herefordshire",
    "sg:tags":[
        "extrusion",
        "holding"
    ],
    "wof:name":"S P Metal U K Plc",
    "wof:placetype":"venue"
},
  "geometry": {"coordinates":[-2.6887600422,52.0354385376],"type":"Point"}
}