{
  "type": "Feature",
  "properties": {
    "iso:country":"GB",
    "sg:address":"44 Nithsdale Rd",
    "sg:city":"Glasgow",
    "sg:classifiers":[
        {
            "category":"Building & Trades",
            "subcategory":"Construction",
            "type":"Services"
        }
    ],
    "sg:phone":"+44 141 424 1755",
    "sg:postcode":"G41 2AN",
    "sg:province":"Glasgow City",
    "sg:tags":[
        "decorator",
        "painter"
    ],
    "wof:name":"Barr & Blair Ltd",
    "wof:placetype":"venue"
},
  "geometry": {"coordinates":[-4.271589,55.837173],"type":"Point"}
}