{
  "type": "Feature",
  "properties": {
    "addr:full":"35 Mallows Grn Harlow Essex CM19 5SA",
    "addr:housenumber":"35",
    "addr:postcode":"cm19 5sa",
    "addr:street":"Mallows Grn",
    "iso:country":"GB",
    "sg:address":"35 Mallows Grn",
    "sg:city":"Harlow",
    "sg:classifiers":[
        {
            "category":"Building & Trades",
            "subcategory":"Construction",
            "type":"Services"
        }
    ],
    "sg:postcode":"CM19 5SA",
    "sg:province":"Essex",
    "sg:tags":[
        "dry",
        "lining",
        "plasterers",
        "screeders"
    ],
    "wof:name":"Almond,Mike,",
    "wof:placetype":"venue"
},
  "geometry": {"coordinates":[0.0744440034,51.7482910156],"type":"Point"}
}