{
  "type": "Feature",
  "properties": {
    "iso:country":"GB",
    "sg:address":"Openwoodgate",
    "sg:city":"Belper",
    "sg:classifiers":[
        {
            "category":"Place Of Worship",
            "type":"Public Place"
        }
    ],
    "sg:phone":"+44 1773 825727",
    "sg:postcode":"DE56 0SD",
    "sg:province":"Derbyshire",
    "wof:name":"St Marks C Of E Church",
    "wof:placetype":"venue"
},
  "geometry": {"coordinates":[-1.452058,53.022114],"type":"Point"}
}