{
  "type": "Feature",
  "properties": {
    "addr:full":"172 Drury La London Greater London WC2B 5QR",
    "addr:housenumber":"172",
    "addr:postcode":"wc2b 5qr",
    "addr:street":"Drury La",
    "iso:country":"GB",
    "sg:address":"172 Drury La",
    "sg:city":"London",
    "sg:classifiers":[
        {
            "category":"Professional",
            "subcategory":"Management & Consulting",
            "type":"Services"
        }
    ],
    "sg:postcode":"WC2B 5QR",
    "sg:province":"Greater London",
    "sg:tags":[
        "sport"
    ],
    "wof:name":"Mercator International Holdings Ltd",
    "wof:placetype":"venue"
},
  "geometry": {"coordinates":[-0.123193,51.515438],"type":"Point"}
}