{
  "type": "Feature",
  "properties": {
    "addr:full":"67 Kimberley Road Bournemouth Dorset BH6 5DD",
    "addr:housenumber":"67",
    "addr:postcode":"bh6 5dd",
    "addr:street":"Kimberley Road",
    "iso:country":"GB",
    "sg:address":"67 Kimberley Road",
    "sg:city":"Bournemouth",
    "sg:classifiers":[
        {
            "category":"Shopping",
            "subcategory":"Clothing, Apparel, & Fashions",
            "type":"Retail Goods"
        }
    ],
    "sg:phone":"+44 1202 462712",
    "sg:postcode":"BH6 5DD",
    "sg:province":"Dorset",
    "sg:tags":[
        "staff",
        "wear",
        "uniform"
    ],
    "wof:name":"The Bournemouth Guide Shop Ltd.",
    "wof:placetype":"venue"
},
  "geometry": {"coordinates":[-1.8109819889,50.7305793762],"type":"Point"}
}