{
  "type": "Feature",
  "properties": {
    "iso:country":"GB",
    "sg:address":"Enterprise House, Geddington Road",
    "sg:city":"Corby",
    "sg:classifiers":[
        {
            "category":"Professional",
            "subcategory":"Business Services",
            "type":"Services"
        }
    ],
    "sg:postcode":"NN17 5LX",
    "sg:province":"Northamptonshire",
    "sg:tags":[
        "import",
        "export",
        "agent"
    ],
    "wof:name":"A C Business Machines",
    "wof:placetype":"venue"
},
  "geometry": {"coordinates":[-0.6747869849,52.4880142212],"type":"Point"}
}