{
  "type": "Feature",
  "properties": {
    "addr:full":"6 Vine Place Sunderland Tyne and Wear SR1 3NE",
    "addr:housenumber":"6",
    "addr:postcode":"sr1 3ne",
    "addr:street":"Vine Place",
    "iso:country":"GB",
    "sg:address":"6 Vine Place",
    "sg:city":"Sunderland",
    "sg:classifiers":[
        {
            "category":"Fast Food",
            "type":"Food & Drink"
        }
    ],
    "sg:phone":"+44 191 510 9931",
    "sg:postcode":"SR1 3NE",
    "sg:province":"Tyne and Wear",
    "sg:tags":[
        "away",
        "take"
    ],
    "wof:name":"Koochini",
    "wof:placetype":"venue"
},
  "geometry": {"coordinates":[-1.386192,54.904022],"type":"Point"}
}