{
  "type": "Feature",
  "properties": {
    "iso:country":"GB",
    "sg:address":"1 Windsor Dr",
    "sg:city":"Spalding",
    "sg:classifiers":[
        {
            "category":"Professional",
            "subcategory":"Computer Services",
            "type":"Services"
        }
    ],
    "sg:phone":"+44 1775 722759",
    "sg:postcode":"PE11 2RP",
    "sg:province":"Lincolnshire",
    "sg:tags":[
        "system",
        "software"
    ],
    "wof:name":"B M Consultants",
    "wof:placetype":"venue"
},
  "geometry": {"coordinates":[-0.151565,52.780029],"type":"Point"}
}