{
  "type": "Feature",
  "properties": {
    "addr:full":"Lions Paw Farm, Marshes Hill Brown Edge Stoke-on-trent Staffordshire ST6 8UF",
    "addr:postcode":"staffordshire st6 8uf",
    "addr:street":"Lions;Marshes Hill Brown",
    "iso:country":"GB",
    "sg:address":"Lions Paw Farm, Marshes Hill Brown Edge",
    "sg:city":"Stoke-on-trent",
    "sg:classifiers":[
        {
            "category":"Building & Trades",
            "subcategory":"Construction",
            "type":"Services"
        }
    ],
    "sg:phone":"+44 1782 512097",
    "sg:postcode":"ST6 8UF",
    "sg:province":"Staffordshire",
    "sg:tags":[
        "builder"
    ],
    "wof:name":"Goodwin Bros",
    "wof:placetype":"venue"
},
  "geometry": {"coordinates":[-2.136103,53.076977],"type":"Point"}
}