{
  "type": "Feature",
  "properties": {
    "addr:full":"Hamilton House, North Circular Road London Greater London NW10 7UB",
    "addr:postcode":"nw10 7ub",
    "addr:street":"North Circular Road",
    "iso:country":"GB",
    "sg:address":"Hamilton House, North Circular Road",
    "sg:city":"London",
    "sg:classifiers":[
        {
            "category":"Professional",
            "subcategory":"Computer Services",
            "type":"Services"
        }
    ],
    "sg:phone":"+44 20 8961 6777",
    "sg:postcode":"NW10 7UB",
    "sg:province":"Greater London",
    "sg:tags":[
        "system",
        "software"
    ],
    "wof:name":"Hamilton Rentals Plc",
    "wof:placetype":"venue"
},
  "geometry": {"coordinates":[-0.2872300148,51.536190033],"type":"Point"}
}