{
  "type": "Feature",
  "properties": {
    "addr:full":"Business & Innovations Centre, Love Lane, Aston Science Park Birmingham West Midlands B7 4BJ",
    "addr:postcode":"b7 4bj",
    "addr:street":"Love Lane Aston Science Park",
    "iso:country":"GB",
    "sg:address":"Business & Innovations Centre, Love Lane, Aston Science Park",
    "sg:city":"Birmingham",
    "sg:classifiers":[
        {
            "category":"Utilities",
            "type":"Services"
        }
    ],
    "sg:phone":"+44 121 243 5533",
    "sg:postcode":"B7 4BJ",
    "sg:province":"West Midlands",
    "sg:tags":[
        "internet"
    ],
    "wof:name":"Power Internet Ltd.",
    "wof:placetype":"venue"
},
  "geometry": {"coordinates":[-1.8871500492,52.489151001],"type":"Point"}
}