{
  "type": "Feature",
  "properties": {
    "iso:country":"GB",
    "sg:address":"Middle Farm, Church St, Goldsborough",
    "sg:city":"Knaresborough",
    "sg:classifiers":[
        {
            "category":"Recreation",
            "subcategory":"Barbecue",
            "type":"Entertainment"
        }
    ],
    "sg:postcode":"HG5 8NR",
    "sg:province":"North Yorkshire",
    "sg:tags":[
        "equipment",
        "retail"
    ],
    "wof:name":"Barbecue Co Ltd (The)",
    "wof:placetype":"venue"
},
  "geometry": {"coordinates":[-1.419296,54.001396],"type":"Point"}
}