{
  "type": "Feature",
  "properties": {
    "addr:full":"758 Henley Road Slough Berkshire SL1 4JW",
    "addr:housenumber":"758",
    "addr:postcode":"sl1 4jw",
    "addr:street":"Henley Road",
    "iso:country":"GB",
    "sg:address":"758 Henley Road",
    "sg:city":"Slough",
    "sg:classifiers":[
        {
            "category":"Building & Trades",
            "subcategory":"Construction",
            "type":"Services"
        }
    ],
    "sg:phone":"+44 1753 554950",
    "sg:postcode":"SL1 4JW",
    "sg:province":"Berkshire",
    "sg:tags":[
        "double",
        "window",
        "glazing",
        "installers",
        "replacement"
    ],
    "wof:name":"Zenith Windows",
    "wof:placetype":"venue"
},
  "geometry": {"coordinates":[-0.6405190229,51.5234298706],"type":"Point"}
}