{
  "type": "Feature",
  "properties": {
    "addr:full":"Unit 21, Imperial Park Rayleigh Essex SS6 9RS",
    "addr:housenumber":"unit 21",
    "addr:postcode":"ss6 9rs",
    "addr:street":"Imperial Park",
    "iso:country":"GB",
    "sg:address":"Unit 21, Imperial Park",
    "sg:city":"Rayleigh",
    "sg:classifiers":[
        {
            "category":"Manufacturing",
            "subcategory":"Lumber",
            "type":"Manufacturing & Wholesale Goods"
        }
    ],
    "sg:phone":"+44 845 130 4636",
    "sg:postcode":"SS6 9RS",
    "sg:province":"Essex",
    "sg:tags":[
        "importer",
        "merchants",
        "agent",
        "timber"
    ],
    "wof:name":"M D M Timber Ltd.",
    "wof:placetype":"venue"
},
  "geometry": {"coordinates":[0.600105,51.603474],"type":"Point"}
}