{
  "type": "Feature",
  "properties": {
    "addr:full":"Hoads Hill Service Station, Wickham Road Fareham Hampshire PO17 5BU",
    "addr:postcode":"po17 5bu",
    "addr:street":"Hoads;Wickham Road",
    "iso:country":"GB",
    "sg:address":"Hoads Hill Service Station, Wickham Road",
    "sg:city":"Fareham",
    "sg:classifiers":[
        {
            "category":"Autos & Motor Vehicles",
            "subcategory":"Automobile Sales",
            "type":"Retail Goods"
        },
        {
            "category":"Autos & Motor Vehicles",
            "subcategory":"Recreational Vehicle Sales",
            "type":"Retail Goods"
        }
    ],
    "sg:phone":"+44 1329 832116",
    "sg:postcode":"PO17 5BU",
    "sg:province":"Hampshire",
    "sg:tags":[
        "car",
        "used",
        "new"
    ],
    "sg:website":"http://www.cjsprattlimited.co.uk",
    "wof:name":"C J Spratt Ltd",
    "wof:placetype":"venue"
},
  "geometry": {"coordinates":[-1.183721,50.894718],"type":"Point"}
}