{
  "type": "Feature",
  "properties": {
    "iso:country":"GB",
    "sg:address":"2 Dale Road",
    "sg:city":"Matlock",
    "sg:classifiers":[
        {
            "category":"Cafe",
            "type":"Food & Drink"
        }
    ],
    "sg:phone":"+44 1629 760411",
    "sg:postcode":"DE4 3LT",
    "sg:province":"Derbyshire",
    "sg:tags":[
        "tea",
        "room"
    ],
    "wof:name":"Cafe Noir",
    "wof:placetype":"venue"
},
  "geometry": {"coordinates":[-1.556684,53.137585],"type":"Point"}
}