{
  "type": "Feature",
  "properties": {
    "iso:country":"GB",
    "sg:address":"41-51 Queen St",
    "sg:city":"Stoke On Trent",
    "sg:classifiers":[
        {
            "category":"Sports & Exercise",
            "subcategory":"Gym",
            "type":"Entertainment"
        }
    ],
    "sg:phone":"+44 7976 417288",
    "sg:postcode":"ST6 7AE",
    "sg:province":"Staffordshire",
    "sg:tags":[
        "fitness",
        "health",
        "centre"
    ],
    "wof:name":"Dance Ade",
    "wof:placetype":"venue"
},
  "geometry": {"coordinates":[-2.19802,53.044521],"type":"Point"}
}