{
  "type": "Feature",
  "properties": {
    "addr:full":"29 Southfield Barnet Hertfordshire EN5 2AT",
    "addr:housenumber":"29",
    "addr:postcode":"en5 2at",
    "addr:street":"Southfield",
    "iso:country":"GB",
    "sg:address":"29 Southfield",
    "sg:city":"Barnet",
    "sg:classifiers":[
        {
            "category":"Building & Trades",
            "subcategory":"Plumbing",
            "type":"Services"
        }
    ],
    "sg:phone":"+44 20 8441 3814",
    "sg:postcode":"EN5 2AT",
    "sg:province":"Hertfordshire",
    "sg:tags":[
        "central",
        "heating"
    ],
    "wof:name":"P & G Godfrey",
    "wof:placetype":"venue"
},
  "geometry": {"coordinates":[-0.215578,51.641911],"type":"Point"}
}