{
  "type": "Feature",
  "properties": {
    "addr:full":"Forge(the), Ravensworth Richmond Durham DL11 7EU",
    "addr:postcode":"dl11 7eu",
    "iso:country":"GB",
    "sg:address":"Forge(the), Ravensworth",
    "sg:city":"Richmond",
    "sg:classifiers":[
        {
            "category":"Professional",
            "subcategory":"Engineering",
            "type":"Services"
        }
    ],
    "sg:phone":"+44 1325 718242",
    "sg:postcode":"DL11 7EU",
    "sg:province":"Durham",
    "wof:name":"J S Wilson & Son",
    "wof:placetype":"venue"
},
  "geometry": {"coordinates":[-1.7851879597,54.4670906067],"type":"Point"}
}