{
  "type": "Feature",
  "properties": {
    "iso:country":"GB",
    "sg:address":"Kemys Way, Morriston",
    "sg:city":"Swansea",
    "sg:classifiers":[
        {
            "category":"Taxi",
            "type":"Transportation"
        }
    ],
    "sg:phone":"+44 1792 702702",
    "sg:postcode":"SA6 8QF",
    "sg:province":"Swansea",
    "sg:tags":[
        "mini",
        "cab"
    ],
    "wof:name":"Dylans Cab Co",
    "wof:placetype":"venue"
},
  "geometry": {"coordinates":[-3.918444,51.659386],"type":"Point"}
}