{
  "type": "Feature",
  "properties": {
    "addr:full":"Mid Street Keith Moray AB55 5BJ",
    "addr:postcode":"ab55 5bj",
    "addr:street":"Mid Street",
    "iso:country":"GB",
    "sg:address":"Mid Street",
    "sg:city":"Keith",
    "sg:classifiers":[
        {
            "category":"Restaurant",
            "type":"Food & Drink"
        }
    ],
    "sg:postcode":"AB55 5BJ",
    "sg:province":"Moray",
    "wof:name":"Cottage Restaurant 142A",
    "wof:placetype":"venue"
},
  "geometry": {"coordinates":[-2.9495990276,57.5428352356],"type":"Point"}
}