{
  "type": "Feature",
  "properties": {
    "iso:country":"GB",
    "sg:address":"Provost Davidson Drive",
    "sg:city":"Ellon",
    "sg:classifiers":[
        {
            "category":"Education",
            "subcategory":"School",
            "type":"Public Place"
        },
        {
            "category":"Government",
            "subcategory":"Office",
            "type":"Public Place"
        }
    ],
    "sg:phone":"+44 1358 721852",
    "sg:postcode":"AB41 9BQ",
    "sg:province":"Aberdeenshire",
    "sg:tags":[
        "local",
        "authority"
    ],
    "wof:name":"Meiklemill Primary School",
    "wof:placetype":"venue"
},
  "geometry": {"coordinates":[-2.0829639435,57.3614692688],"type":"Point"}
}