{
  "type": "Feature",
  "properties": {
    "iso:country":"GB",
    "sg:address":"440 Bristol Business Park, Coldharbour Lane",
    "sg:city":"Bristol",
    "sg:classifiers":[
        {
            "category":"Education",
            "subcategory":"Special Training",
            "type":"Public Place"
        }
    ],
    "sg:phone":"+44 117 974 8300",
    "sg:postcode":"BS16 1EJ",
    "sg:province":"City of Bristol",
    "sg:tags":[
        "product",
        "centre"
    ],
    "wof:name":"Admiral D P M T Training Centre",
    "wof:placetype":"venue"
},
  "geometry": {"coordinates":[-2.541844,51.500313],"type":"Point"}
}