{
  "type": "Feature",
  "properties": {
    "addr:full":"10 Carolines Crescent Ellon Aberdeenshire AB41 8BN",
    "addr:housenumber":"10",
    "addr:postcode":"ab41 8bn",
    "addr:street":"Carolines Crescent",
    "iso:country":"GB",
    "sg:address":"10 Carolines Crescent",
    "sg:city":"Ellon",
    "sg:classifiers":[
        {
            "category":"Insurance",
            "subcategory":"Life Insurance",
            "type":"Services"
        }
    ],
    "sg:phone":"+44 1358 720086",
    "sg:postcode":"AB41 8BN",
    "sg:province":"Aberdeenshire",
    "sg:tags":[
        "assurance"
    ],
    "wof:name":"Ian Macaulay Smith",
    "wof:placetype":"venue"
},
  "geometry": {"coordinates":[-2.07303,57.371014],"type":"Point"}
}