{
  "type": "Feature",
  "properties": {
    "addr:full":"156 Lawnswood Rd Stourbridge Staffordshire DY8 5LW",
    "addr:housenumber":"156",
    "addr:postcode":"dy8 5lw",
    "addr:street":"Lawnswood Rd",
    "iso:country":"GB",
    "sg:address":"156 Lawnswood Rd",
    "sg:city":"Stourbridge",
    "sg:classifiers":[
        {
            "category":"Building & Trades",
            "subcategory":"Landscaping Services",
            "type":"Services"
        }
    ],
    "sg:phone":"+44 1384 277228",
    "sg:postcode":"DY8 5LW",
    "sg:province":"Staffordshire",
    "sg:tags":[
        "landscape",
        "contractor"
    ],
    "wof:name":"Lawnswood Landscapes",
    "wof:placetype":"venue"
},
  "geometry": {"coordinates":[-2.17701,52.482914],"type":"Point"}
}