{
  "type": "Feature",
  "properties": {
    "addr:full":"Queensway Rochdale Lancashire OL11 2PR",
    "addr:postcode":"ol11 2pr",
    "iso:country":"GB",
    "sg:address":"Queensway",
    "sg:city":"Rochdale",
    "sg:classifiers":[
        {
            "category":"Building & Trades",
            "subcategory":"Construction",
            "type":"Services"
        }
    ],
    "sg:phone":"+44 1706 350350",
    "sg:postcode":"OL11 2PR",
    "sg:province":"Lancashire",
    "sg:tags":[
        "joinery"
    ],
    "wof:name":"Dale Joinery Ltd.",
    "wof:placetype":"venue"
},
  "geometry": {"coordinates":[-2.1477389336,53.6036567688],"type":"Point"}
}