{
  "type": "Feature",
  "properties": {
    "iso:country":"GB",
    "sg:address":"29 Willoughby Road",
    "sg:city":"London",
    "sg:classifiers":[
        {
            "category":"Health Services",
            "subcategory":"Doctor",
            "type":"Services"
        }
    ],
    "sg:phone":"+44 20 8348 7313",
    "sg:postcode":"N8 0JE",
    "sg:province":"Greater London",
    "sg:tags":[
        "practitioners"
    ],
    "wof:name":"Z Costa",
    "wof:placetype":"venue"
},
  "geometry": {"coordinates":[-0.173271,51.557331],"type":"Point"}
}