{
  "type": "Feature",
  "properties": {
    "addr:full":"Station Road Biggleswade Bedfordshire SG18 8AL",
    "addr:postcode":"sg18 8al",
    "addr:street":"Station Road",
    "iso:country":"GB",
    "sg:address":"Station Road",
    "sg:city":"Biggleswade",
    "sg:classifiers":[
        {
            "category":"Sports & Exercise",
            "subcategory":"Sports Center",
            "type":"Entertainment"
        }
    ],
    "sg:phone":"+44 1767 313310",
    "sg:postcode":"SG18 8AL",
    "sg:province":"Bedfordshire",
    "sg:tags":[
        "shop",
        "good"
    ],
    "wof:name":"Taylor & Co",
    "wof:placetype":"venue"
},
  "geometry": {"coordinates":[-0.2627080083,52.0853424072],"type":"Point"}
}