{
  "type": "Feature",
  "properties": {
    "addr:full":"59 Glebe Road Egham Surrey TW20 8BU",
    "addr:housenumber":"59",
    "addr:postcode":"tw20 8bu",
    "addr:street":"Glebe Road",
    "iso:country":"GB",
    "sg:address":"59 Glebe Road",
    "sg:city":"Egham",
    "sg:classifiers":[
        {
            "category":"Utilities",
            "subcategory":"Refuse",
            "type":"Services"
        }
    ],
    "sg:postcode":"TW20 8BU",
    "sg:province":"Surrey",
    "sg:tags":[
        "skip",
        "hire"
    ],
    "wof:name":"A & A Skip Hire",
    "wof:placetype":"venue"
},
  "geometry": {"coordinates":[-0.5287809968,51.4285964966],"type":"Point"}
}