{
  "type": "Feature",
  "properties": {
    "addr:full":"Greystone Lea, Gartocharn Alexandria Argyll and Bute G83 8SD",
    "addr:postcode":"g83 8sd",
    "iso:country":"GB",
    "sg:address":"Greystone Lea, Gartocharn",
    "sg:city":"Alexandria",
    "sg:classifiers":[
        {
            "category":"Building & Trades",
            "subcategory":"Landscaping Services",
            "type":"Services"
        }
    ],
    "sg:postcode":"G83 8SD",
    "sg:province":"Argyll and Bute",
    "sg:tags":[
        "landscape",
        "contractor"
    ],
    "wof:name":"Central Weed Contractors",
    "wof:placetype":"venue"
},
  "geometry": {"coordinates":[-4.5308089256,56.0404052734],"type":"Point"}
}