{
  "type": "Feature",
  "properties": {
    "addr:full":"64 Portland Street Lincoln Lincolnshire LN5 7LB",
    "addr:housenumber":"64",
    "addr:postcode":"ln5 7lb",
    "addr:street":"Portland Street",
    "iso:country":"GB",
    "sg:address":"64 Portland Street",
    "sg:city":"Lincoln",
    "sg:classifiers":[
        {
            "category":"Retail",
            "subcategory":"Laundry & Dry Cleaning",
            "type":"Services"
        }
    ],
    "sg:phone":"+44 1522 575404",
    "sg:postcode":"LN5 7LB",
    "sg:province":"Lincolnshire",
    "sg:tags":[
        "launderette"
    ],
    "wof:name":"Portland Clothes Care",
    "wof:placetype":"venue"
},
  "geometry": {"coordinates":[-0.539446,53.22377],"type":"Point"}
}