{
  "type": "Feature",
  "properties": {
    "iso:country":"GB",
    "sg:address":"3 Mid Shore",
    "sg:city":"Anstruther",
    "sg:classifiers":[
        {
            "category":"Shopping",
            "subcategory":"Department Store",
            "type":"Retail Goods"
        }
    ],
    "sg:postcode":"KY10 2NJ",
    "sg:province":"Fife",
    "wof:name":"Harbour Stores",
    "wof:placetype":"venue"
},
  "geometry": {"coordinates":[-2.730565,56.211872],"type":"Point"}
}