{
  "type": "Feature",
  "properties": {
    "addr:full":"11 Hurne Court Basingstoke Hampshire RG21 4DE",
    "addr:housenumber":"11",
    "addr:postcode":"rg21 4de",
    "addr:street":"Hurne Court",
    "iso:country":"GB",
    "sg:address":"11 Hurne Court",
    "sg:city":"Basingstoke",
    "sg:classifiers":[
        {
            "category":"Utilities",
            "type":"Services"
        }
    ],
    "sg:postcode":"RG21 4DE",
    "sg:province":"Hampshire",
    "sg:tags":[
        "internet"
    ],
    "wof:name":"Maidennet Ltd.",
    "wof:placetype":"venue"
},
  "geometry": {"coordinates":[-1.074819,51.264275],"type":"Point"}
}