{
  "type": "Feature",
  "properties": {
    "addr:full":"Ivanhoe Nurseries, Ironwell Lane Hockley Essex SS5 4JY",
    "addr:postcode":"ss5 4jy",
    "addr:street":"Ironwell Lane",
    "iso:country":"GB",
    "sg:address":"Ivanhoe Nurseries, Ironwell Lane",
    "sg:city":"Hockley",
    "sg:classifiers":[
        {
            "category":"Wholesale",
            "subcategory":"Fruits & Vegetables",
            "type":"Manufacturing & Wholesale Goods"
        }
    ],
    "sg:phone":"+44 1702 202071",
    "sg:postcode":"SS5 4JY",
    "sg:province":"Essex",
    "wof:name":"Widera & Sons",
    "wof:placetype":"venue"
},
  "geometry": {"coordinates":[0.666821003,51.6066627502],"type":"Point"}
}