{
  "type": "Feature",
  "properties": {
    "iso:country":"GB",
    "sg:address":"10 Pipers Lane Indust Estate, Pipers Lane",
    "sg:city":"Thatcham",
    "sg:classifiers":[
        {
            "category":"Government",
            "subcategory":"Post Office",
            "type":"Public Place"
        }
    ],
    "sg:phone":"+44 1635 873499",
    "sg:postcode":"RG19 4NA",
    "sg:province":"Berkshire",
    "sg:tags":[
        "messenger",
        "courier"
    ],
    "wof:name":"Wps Express",
    "wof:placetype":"venue"
},
  "geometry": {"coordinates":[-1.240406,51.39632],"type":"Point"}
}