{
  "type": "Feature",
  "properties": {
    "iso:country":"GB",
    "sg:address":"Roundstone By-pass, Angmering",
    "sg:city":"Littlehampton",
    "sg:classifiers":[
        {
            "category":"Home & Garden",
            "subcategory":"Garden Supply",
            "type":"Retail Goods"
        }
    ],
    "sg:phone":"+44 1903 770457",
    "sg:postcode":"BN16 4BD",
    "sg:province":"West Sussex",
    "sg:tags":[
        "nursery",
        "centre"
    ],
    "wof:name":"Lower Trees Nursery",
    "wof:placetype":"venue"
},
  "geometry": {"coordinates":[-0.4852240086,50.8281402588],"type":"Point"}
}