{
  "type": "Feature",
  "properties": {
    "iso:country":"GB",
    "sg:address":"212 Portland Rd",
    "sg:city":"Hove",
    "sg:classifiers":[
        {
            "category":"Professional",
            "subcategory":"Credit Reporting & Collection",
            "type":"Services"
        }
    ],
    "sg:phone":"+44 1273 202229",
    "sg:postcode":"BN3 5QT",
    "sg:province":"East Sussex",
    "sg:tags":[
        "collecting",
        "agency"
    ],
    "wof:name":"Robinson Way & Co",
    "wof:placetype":"venue"
},
  "geometry": {"coordinates":[-0.1883649975,50.8335227966],"type":"Point"}
}