{
  "type": "Feature",
  "properties": {
    "iso:country":"GB",
    "sg:address":"316 Uxbridge Rd",
    "sg:city":"Pinner",
    "sg:classifiers":[
        {
            "category":"Restaurant",
            "type":"Food & Drink"
        }
    ],
    "sg:phone":"+44 20 8421 2878",
    "sg:postcode":"HA5 4TR",
    "sg:province":"Greater London",
    "wof:name":"The Rotisserie",
    "wof:placetype":"venue"
},
  "geometry": {"coordinates":[-0.3647240102,51.6090316772],"type":"Point"}
}