{
  "type": "Feature",
  "properties": {
    "addr:full":"101 Mottram Old Road Stalybridge Greater Manchester SK15 2SZ",
    "addr:housenumber":"101",
    "addr:postcode":"sk15 2sz",
    "addr:street":"Mottram Old Road",
    "iso:country":"GB",
    "sg:address":"101 Mottram Old Road",
    "sg:city":"Stalybridge",
    "sg:classifiers":[
        {
            "category":"Wholesale",
            "subcategory":"Chemicals & Plastics",
            "type":"Manufacturing & Wholesale Goods"
        }
    ],
    "sg:phone":"+44 161 303 9028",
    "sg:postcode":"SK15 2SZ",
    "sg:province":"Greater Manchester",
    "sg:tags":[
        "retail",
        "freezer",
        "refrigerator"
    ],
    "wof:name":"Direct Cooling",
    "wof:placetype":"venue"
},
  "geometry": {"coordinates":[-2.03397,53.473179],"type":"Point"}
}