{
  "type": "Feature",
  "properties": {
    "iso:country":"GB",
    "sg:address":"Unit 4, Avocet Trading Estate",
    "sg:city":"High Wycombe",
    "sg:classifiers":[
        {
            "category":"Wholesale",
            "subcategory":"Machinery & Supplies",
            "type":"Manufacturing & Wholesale Goods"
        }
    ],
    "sg:postcode":"HP11 2SB",
    "sg:province":"Buckinghamshire",
    "sg:tags":[
        "equipment",
        "handling",
        "lifting"
    ],
    "wof:name":"Stekko Co. Ltd.",
    "wof:placetype":"venue"
},
  "geometry": {"coordinates":[-0.76305,51.63245],"type":"Point"}
}