{
  "type": "Feature",
  "properties": {
    "iso:country":"GB",
    "sg:address":"Mill Lane",
    "sg:city":"Reading",
    "sg:classifiers":[
        {
            "category":"Bus Charters",
            "type":"Transportation"
        }
    ],
    "sg:phone":"+44 118 957 3133",
    "sg:postcode":"RG1 2RW",
    "sg:province":"Berkshire",
    "sg:tags":[
        "coach"
    ],
    "wof:name":"Goldline Bus & Coach Hire",
    "wof:placetype":"venue"
},
  "geometry": {"coordinates":[-1.032684,51.443115],"type":"Point"}
}