{
  "type": "Feature",
  "properties": {
    "addr:full":"Electoral Registration, Hillside Ho, Laurelhill Business Park Stirling Falkirk FK7 9JQ",
    "addr:postcode":"fk7 9jq",
    "addr:street":"Hillside;Business Park",
    "iso:country":"GB",
    "sg:address":"Electoral Registration, Hillside Ho, Laurelhill Business Park",
    "sg:city":"Stirling",
    "sg:classifiers":[
        {
            "category":"Government",
            "subcategory":"Office",
            "type":"Public Place"
        }
    ],
    "sg:phone":"+44 1786 443535",
    "sg:postcode":"FK7 9JQ",
    "sg:province":"Falkirk",
    "sg:tags":[
        "local"
    ],
    "wof:name":"Central Scotland Assors",
    "wof:placetype":"venue"
},
  "geometry": {"coordinates":[-3.94804,56.110592],"type":"Point"}
}