{
  "type": "Feature",
  "properties": {
    "addr:full":"Romford Road, Aston Fields Industrial Estate Stafford Staffordshire ST16 3DZ",
    "addr:housenumber":"estate",
    "addr:postcode":"st16 3dz",
    "addr:street":"Romford Road Aston Fields Industrial",
    "iso:country":"GB",
    "sg:address":"Romford Road, Aston Fields Industrial Estate",
    "sg:city":"Stafford",
    "sg:classifiers":[
        {
            "category":"Home & Garden",
            "subcategory":"Building Materials",
            "type":"Retail Goods"
        }
    ],
    "sg:phone":"+44 1785 241084",
    "sg:postcode":"ST16 3DZ",
    "sg:province":"Staffordshire",
    "sg:tags":[
        "resin",
        "gum"
    ],
    "wof:name":"Resiblend Ltd.",
    "wof:placetype":"venue"
},
  "geometry": {"coordinates":[-2.1145870686,52.8201713562],"type":"Point"}
}