{
  "type": "Feature",
  "properties": {
    "addr:full":"44 East Bank Road Sheffield South Yorkshire S2 3QN",
    "addr:housenumber":"44",
    "addr:postcode":"s2 3qn",
    "addr:street":"East Bank Road",
    "iso:country":"GB",
    "sg:address":"44 East Bank Road",
    "sg:city":"Sheffield",
    "sg:classifiers":[
        {
            "category":"Military Area",
            "subcategory":"Air Force Base",
            "type":"Public Place"
        }
    ],
    "sg:phone":"+44 114 273 1151",
    "sg:postcode":"S2 3QN",
    "sg:province":"South Yorkshire",
    "sg:tags":[
        "plate",
        "number"
    ],
    "wof:name":"Jepson & Co. Ltd.",
    "wof:placetype":"venue"
},
  "geometry": {"coordinates":[-1.46146,53.37075],"type":"Point"}
}