{
  "type": "Feature",
  "properties": {
    "addr:full":"Ross Hall Hospital, 221 Crookston Rd Glasgow Glasgow City G52 3NQ",
    "addr:housenumber":"221",
    "addr:postcode":"g52 3nq",
    "addr:street":"Crookston Rd",
    "iso:country":"GB",
    "sg:address":"Ross Hall Hospital, 221 Crookston Rd",
    "sg:city":"Glasgow",
    "sg:classifiers":[
        {
            "category":"Health Services",
            "subcategory":"Health Practitioner",
            "type":"Services"
        }
    ],
    "sg:phone":"+44 1360 620845",
    "sg:postcode":"G52 3NQ",
    "sg:province":"Glasgow City",
    "sg:tags":[
        "psychologist"
    ],
    "wof:name":"U Fischer",
    "wof:placetype":"venue"
},
  "geometry": {"coordinates":[-4.36561,55.83847],"type":"Point"}
}