{
  "type": "Feature",
  "properties": {
    "iso:country":"GB",
    "sg:address":"6-8 Windermere Road, Clayton",
    "sg:city":"Newcastle",
    "sg:classifiers":[
        {
            "category":"Food & Beverages",
            "subcategory":"Liquor & Beverages",
            "type":"Retail Goods"
        }
    ],
    "sg:phone":"+44 1782 660191",
    "sg:postcode":"ST5 3HH",
    "sg:province":"Staffordshire",
    "sg:tags":[
        "beer",
        "spirit",
        "wines"
    ],
    "wof:name":"Thresher",
    "wof:placetype":"venue"
},
  "geometry": {"coordinates":[-2.225707,52.990952],"type":"Point"}
}