{
  "type": "Feature",
  "properties": {
    "iso:country":"GB",
    "sg:address":"11 Blackwell Dr, Springwood Indust Est",
    "sg:city":"Braintree",
    "sg:classifiers":[
        {
            "category":"Professional",
            "subcategory":"Engineering",
            "type":"Services"
        }
    ],
    "sg:phone":"+44 1376 348400",
    "sg:postcode":"CM7 2QJ",
    "sg:province":"Essex",
    "sg:tags":[
        "contractor",
        "electrical",
        "engineer"
    ],
    "wof:name":"Edison Controls",
    "wof:placetype":"venue"
},
  "geometry": {"coordinates":[0.533085,51.886868],"type":"Point"}
}