{
  "type": "Feature",
  "properties": {
    "iso:country":"GB",
    "sg:address":"385 Uxbridge Rd",
    "sg:city":"Pinner",
    "sg:classifiers":[
        {
            "category":"Personal",
            "subcategory":"Barber",
            "type":"Services"
        }
    ],
    "sg:phone":"+44 20 8421 5151",
    "sg:postcode":"HA5 4JN",
    "sg:province":"Greater London",
    "sg:tags":[
        "men's",
        "hairdresser"
    ],
    "wof:name":"Brothers",
    "wof:placetype":"venue"
},
  "geometry": {"coordinates":[-0.364724,51.609032],"type":"Point"}
}