{
  "type": "Feature",
  "properties": {
    "addr:full":"Station Road Industrial Estate Mauchline East Ayrshire KA5 5EQ",
    "addr:postcode":"ka5 5eq",
    "addr:street":"Station Road Industrial Estate Mauchline East",
    "iso:country":"GB",
    "sg:address":"Station Road Industrial Estate",
    "sg:city":"Mauchline",
    "sg:classifiers":[
        {
            "category":"Building & Trades",
            "subcategory":"Construction",
            "type":"Services"
        }
    ],
    "sg:phone":"+44 1290 551055",
    "sg:postcode":"KA5 5EQ",
    "sg:province":"East Ayrshire",
    "sg:tags":[
        "supplier",
        "installers",
        "cladding"
    ],
    "wof:name":"Craftsman Cladding",
    "wof:placetype":"venue"
},
  "geometry": {"coordinates":[-4.379469,55.510536],"type":"Point"}
}