{
  "type": "Feature",
  "properties": {
    "addr:full":"Garden Studios Business Centre, 11-15 Betterton Street London Greater London WC2H 9BP",
    "addr:housenumber":"11-15",
    "addr:postcode":"wc2h 9bp",
    "addr:street":"Betterton Street",
    "iso:country":"GB",
    "sg:address":"Garden Studios Business Centre, 11-15 Betterton Street",
    "sg:city":"London",
    "sg:classifiers":[
        {
            "category":"Professional",
            "subcategory":"Management & Consulting",
            "type":"Services"
        }
    ],
    "sg:postcode":"WC2H 9BP",
    "sg:province":"Greater London",
    "sg:tags":[
        "consultant",
        "business"
    ],
    "wof:name":"Mohawk Consulting Ltd",
    "wof:placetype":"venue"
},
  "geometry": {"coordinates":[-0.12351,51.515079],"type":"Point"}
}