{
  "type": "Feature",
  "properties": {
    "iso:country":"GB",
    "sg:address":"Craft Unit 5, Tredegar House",
    "sg:city":"Newport",
    "sg:classifiers":[
        {
            "category":"Manufacturing",
            "subcategory":"Glass & Minerals",
            "type":"Manufacturing & Wholesale Goods"
        }
    ],
    "sg:phone":"+44 1633 810612",
    "sg:postcode":"NP10 8YW",
    "sg:province":"Caerphilly",
    "sg:tags":[
        "stained"
    ],
    "wof:name":"Youngs Stained Glass",
    "wof:placetype":"venue"
},
  "geometry": {"coordinates":[-3.02814,51.561562],"type":"Point"}
}