{
  "type": "Feature",
  "properties": {
    "iso:country":"GB",
    "sg:address":"Clappers Farm, Aspatria",
    "sg:city":"Wigton",
    "sg:classifiers":[
        {
            "category":"Farming",
            "subcategory":"Farm",
            "type":"Manufacturing & Wholesale Goods"
        }
    ],
    "sg:phone":"+44 16973 20829",
    "sg:postcode":"CA7 3LG",
    "sg:province":"Cumbria",
    "sg:tags":[
        "mixed",
        "crop"
    ],
    "wof:name":"John J Brough",
    "wof:placetype":"venue"
},
  "geometry": {"coordinates":[-3.326297,54.764439],"type":"Point"}
}