{
  "type": "Feature",
  "properties": {
    "iso:country":"GB",
    "sg:address":"Porch House, Swan Hill",
    "sg:city":"Shrewsbury",
    "sg:classifiers":[
        {
            "category":"Transit Center",
            "subcategory":"Freight",
            "type":"Transportation"
        }
    ],
    "sg:postcode":"SY1 1NQ",
    "sg:province":"Shropshire",
    "sg:tags":[
        "shop",
        "craft",
        "centre"
    ],
    "wof:name":"The Design Workers Guild",
    "wof:placetype":"venue"
},
  "geometry": {"coordinates":[-2.756344,52.706493],"type":"Point"}
}