{
  "type": "Feature",
  "properties": {
    "addr:full":"10 Newfield Gardens Marlow Berkshire SL7 1JN",
    "addr:housenumber":"10",
    "addr:postcode":"sl7 1jn",
    "addr:street":"Newfield Gardens",
    "iso:country":"GB",
    "sg:address":"10 Newfield Gardens",
    "sg:city":"Marlow",
    "sg:classifiers":[
        {
            "category":"Building & Trades",
            "subcategory":"Cleaning & Sanitation",
            "type":"Services"
        }
    ],
    "sg:phone":"+44 7770 665273",
    "sg:postcode":"SL7 1JN",
    "sg:province":"Berkshire",
    "sg:tags":[
        "commercial"
    ],
    "wof:name":"D R Window Cleaners",
    "wof:placetype":"venue"
},
  "geometry": {"coordinates":[-0.7648109794,51.5744972229],"type":"Point"}
}