{
  "type": "Feature",
  "properties": {
    "iso:country":"GB",
    "sg:address":"Braystone, Salford Road",
    "sg:city":"Milton Keynes",
    "sg:classifiers":[
        {
            "category":"Building & Trades",
            "subcategory":"Landscaping Services",
            "type":"Services"
        }
    ],
    "sg:postcode":"MK17 8HY",
    "sg:province":"Bedfordshire",
    "sg:tags":[
        "landscape",
        "contractor"
    ],
    "wof:name":"P B Clarke",
    "wof:placetype":"venue"
},
  "geometry": {"coordinates":[-0.639135,52.044472],"type":"Point"}
}