{
  "type": "Feature",
  "properties": {
    "iso:country":"GB",
    "sg:address":"Beaver Lodge, St. Michaels Close",
    "sg:city":"Stourport On Severn",
    "sg:classifiers":[
        {
            "category":"Health Services",
            "subcategory":"Podiatrist",
            "type":"Services"
        }
    ],
    "sg:phone":"+44 1299 879052",
    "sg:postcode":"DY13 8EQ",
    "sg:province":"Worcestershire",
    "sg:tags":[
        "podiatrists",
        "chiropodist"
    ],
    "wof:name":"K Butler Chiropodist",
    "wof:placetype":"venue"
},
  "geometry": {"coordinates":[-2.276676,52.343903],"type":"Point"}
}