{
  "type": "Feature",
  "properties": {
    "iso:country":"GB",
    "sg:address":"Pinfold Cottage, Brook Lane",
    "sg:city":"Pickering",
    "sg:classifiers":[
        {
            "category":"Building & Trades",
            "subcategory":"Construction",
            "type":"Services"
        }
    ],
    "sg:postcode":"YO18 7RZ",
    "sg:province":"North Yorkshire",
    "sg:tags":[
        "joiner",
        "carpenter"
    ],
    "wof:name":"M Green",
    "wof:placetype":"venue"
},
  "geometry": {"coordinates":[-0.779388,54.24501],"type":"Point"}
}