{
  "type": "Feature",
  "properties": {
    "iso:country":"GB",
    "sg:address":"Ruffets, Southwater Street",
    "sg:city":"Horsham",
    "sg:classifiers":[
        {
            "category":"Building & Trades",
            "subcategory":"Equipment Rental",
            "type":"Services"
        }
    ],
    "sg:phone":"+44 1403 730400",
    "sg:postcode":"RH13 9BN",
    "sg:province":"West Sussex",
    "sg:tags":[
        "plant",
        "machinery"
    ],
    "wof:name":"D J Grover Grab Hire",
    "wof:placetype":"venue"
},
  "geometry": {"coordinates":[-0.352569,51.023506],"type":"Point"}
}