{
  "type": "Feature",
  "properties": {
    "iso:country":"GB",
    "sg:address":"Carrhill Mill, Manchester Road, Mossley",
    "sg:city":"Ashton-under-lyne",
    "sg:classifiers":[
        {
            "category":"Shopping",
            "subcategory":"Crafts & Fabrics",
            "type":"Retail Goods"
        }
    ],
    "sg:phone":"+44 1457 832802",
    "sg:postcode":"OL5 9AU",
    "sg:province":"Greater Manchester",
    "sg:tags":[
        "yarn",
        "supply"
    ],
    "wof:name":"Mossley Spinning Ltd.",
    "wof:placetype":"venue"
},
  "geometry": {"coordinates":[-2.04125,53.517082],"type":"Point"}
}