{
  "type": "Feature",
  "properties": {
    "addr:full":"100 Stamford New Rd Altrincham Cheshire WA14 1DG",
    "addr:housenumber":"100",
    "addr:postcode":"wa14 1dg",
    "addr:street":"Stamford New Rd",
    "iso:country":"GB",
    "sg:address":"100 Stamford New Rd",
    "sg:city":"Altrincham",
    "sg:classifiers":[
        {
            "category":"Travel",
            "subcategory":"Travel Agent",
            "type":"Entertainment"
        }
    ],
    "sg:phone":"+44 161 929 1222",
    "sg:postcode":"WA14 1DG",
    "sg:province":"Cheshire",
    "wof:name":"Altrincham Travel Centre",
    "wof:placetype":"venue"
},
  "geometry": {"coordinates":[-2.3512129784,53.3857460022],"type":"Point"}
}