{
  "type": "Feature",
  "properties": {
    "addr:full":"139 Cricklewood Bdwy London Greater London NW2 3HY",
    "addr:housenumber":"139",
    "addr:postcode":"nw2 3hy",
    "addr:street":"Cricklewood Bdwy",
    "iso:country":"GB",
    "sg:address":"139 Cricklewood Bdwy",
    "sg:city":"London",
    "sg:classifiers":[
        {
            "category":"Fast Food",
            "type":"Food & Drink"
        }
    ],
    "sg:phone":"+44 20 8830 5375",
    "sg:postcode":"NW2 3HY",
    "sg:province":"Greater London",
    "sg:tags":[
        "away",
        "take"
    ],
    "wof:name":"Burger King",
    "wof:placetype":"venue"
},
  "geometry": {"coordinates":[-0.213791,51.555454],"type":"Point"}
}