{
  "type": "Feature",
  "properties": {
    "iso:country":"GB",
    "sg:address":"18 High Street",
    "sg:city":"Shepton Mallet",
    "sg:classifiers":[
        {
            "category":"Shopping",
            "subcategory":"Pharmacy",
            "type":"Retail Goods"
        }
    ],
    "sg:phone":"+44 1749 342192",
    "sg:postcode":"BA4 5AN",
    "sg:province":"Somerset",
    "sg:tags":[
        "pharmacist",
        "chemist"
    ],
    "wof:name":"Watkins Chemists",
    "wof:placetype":"venue"
},
  "geometry": {"coordinates":[-2.547719,51.189388],"type":"Point"}
}