{
  "type": "Feature",
  "properties": {
    "addr:full":"Skerry Hill Mansfield Nottinghamshire NG18 2PP",
    "addr:postcode":"ng18 2pp",
    "addr:street":"Skerry",
    "iso:country":"GB",
    "sg:address":"Skerry Hill",
    "sg:city":"Mansfield",
    "sg:classifiers":[
        {
            "category":"Wholesale",
            "subcategory":"Construction Materials",
            "type":"Manufacturing & Wholesale Goods"
        }
    ],
    "sg:phone":"+44 1623 627563",
    "sg:postcode":"NG18 2PP",
    "sg:province":"Nottinghamshire",
    "sg:tags":[
        "merchant",
        "glass"
    ],
    "wof:name":"Bucklow & Stroud Ltd",
    "wof:placetype":"venue"
},
  "geometry": {"coordinates":[-1.1798189878,53.1438789368],"type":"Point"}
}