{
  "type": "Feature",
  "properties": {
    "iso:country":"GB",
    "sg:address":"12 Vauxhall Industrial Estate",
    "sg:city":"Wrexham",
    "sg:classifiers":[
        {
            "category":"Building & Trades",
            "subcategory":"Equipment Rental",
            "type":"Services"
        }
    ],
    "sg:phone":"+44 1978 821717",
    "sg:postcode":"LL14 6HA",
    "sg:province":"Wrexham",
    "sg:tags":[
        "hire",
        "machinery",
        "plant",
        "centre"
    ],
    "wof:name":"Hewden Plant Hire Ltd.",
    "wof:placetype":"venue"
},
  "geometry": {"coordinates":[-3.0409810543,53.0012130737],"type":"Point"}
}