{
  "type": "Feature",
  "properties": {
    "iso:country":"GB",
    "sg:address":"Unit 6 Teknol House Victoria Road",
    "sg:city":"Burgess Hill",
    "sg:classifiers":[
        {
            "category":"Building & Trades",
            "subcategory":"Construction",
            "type":"Services"
        }
    ],
    "sg:phone":"+44 1444 258243",
    "sg:postcode":"RH15 9LH",
    "sg:province":"East Sussex",
    "sg:tags":[
        "joiner",
        "carpenter"
    ],
    "wof:name":"Darrell Ward Joinery",
    "wof:placetype":"venue"
},
  "geometry": {"coordinates":[-0.149742,50.955669],"type":"Point"}
}