{
  "type": "Feature",
  "properties": {
    "addr:full":"189 Haslingden Old Road Rossendale Lancashire BB4 8RR",
    "addr:housenumber":"189",
    "addr:postcode":"bb4 8rr",
    "addr:street":"Haslingden Old Road",
    "iso:country":"GB",
    "sg:address":"189 Haslingden Old Road",
    "sg:city":"Rossendale",
    "sg:classifiers":[
        {
            "category":"Building & Trades",
            "subcategory":"Construction",
            "type":"Services"
        }
    ],
    "sg:phone":"+44 1706 215501",
    "sg:postcode":"BB4 8RR",
    "sg:province":"Lancashire",
    "sg:tags":[
        "builder"
    ],
    "wof:name":"Alan Lamberts",
    "wof:placetype":"venue"
},
  "geometry": {"coordinates":[-2.29396,53.703442],"type":"Point"}
}