{
  "type": "Feature",
  "properties": {
    "iso:country":"GB",
    "sg:address":"Nexus House, 2 Cray Road",
    "sg:city":"Sidcup",
    "sg:classifiers":[
        {
            "category":"Professional",
            "subcategory":"Engineering",
            "type":"Services"
        }
    ],
    "sg:postcode":"DA14 5DA",
    "sg:province":"Kent",
    "sg:tags":[
        "contractor",
        "electrical",
        "engineer"
    ],
    "wof:name":"Galco Ltd.",
    "wof:placetype":"venue"
},
  "geometry": {"coordinates":[0.117528,51.41803],"type":"Point"}
}