{
  "type": "Feature",
  "properties": {
    "iso:country":"GB",
    "sg:address":"55 Sandy Rd",
    "sg:city":"Addlestone",
    "sg:classifiers":[
        {
            "category":"Home & Garden",
            "subcategory":"Household Appliances",
            "type":"Retail Goods"
        }
    ],
    "sg:phone":"+44 1932 849499",
    "sg:postcode":"KT15 1HZ",
    "sg:province":"Surrey",
    "sg:tags":[
        "electrical"
    ],
    "wof:name":"Mike Hyatt",
    "wof:placetype":"venue"
},
  "geometry": {"coordinates":[-0.500611,51.364361],"type":"Point"}
}