{
  "type": "Feature",
  "properties": {
    "addr:full":"Gresham Ho, Gresham Rd Staines Berkshire TW18 2BE",
    "addr:postcode":"tw18 2be",
    "addr:street":"Gresham Rd",
    "iso:country":"GB",
    "sg:address":"Gresham Ho, Gresham Rd",
    "sg:city":"Staines",
    "sg:classifiers":[
        {
            "category":"Manufacturing",
            "subcategory":"Building Materials",
            "type":"Manufacturing & Wholesale Goods"
        }
    ],
    "sg:phone":"+44 1784 451244",
    "sg:postcode":"TW18 2BE",
    "sg:province":"Berkshire",
    "sg:tags":[
        "merchant",
        "builder"
    ],
    "wof:name":"Graham Builders Merchants",
    "wof:placetype":"venue"
},
  "geometry": {"coordinates":[-0.5003740191,51.4319648743],"type":"Point"}
}