{
  "type": "Feature",
  "properties": {
    "addr:full":"50 The Street, Puttenham Guildford Surrey GU3 1AR",
    "addr:housenumber":"50",
    "addr:postcode":"gu3 1ar",
    "addr:street":"The Street",
    "iso:country":"GB",
    "sg:address":"50 The Street, Puttenham",
    "sg:city":"Guildford",
    "sg:classifiers":[
        {
            "category":"Home & Garden",
            "subcategory":"Home Furnishings",
            "type":"Retail Goods"
        }
    ],
    "sg:phone":"+44 1483 810886",
    "sg:postcode":"GU3 1AR",
    "sg:province":"Surrey",
    "sg:tags":[
        "beds",
        "bedding",
        "blanket"
    ],
    "wof:name":"The Iron Bed Co",
    "wof:placetype":"venue"
},
  "geometry": {"coordinates":[-0.6669560075,51.222114563],"type":"Point"}
}