{
  "type": "Feature",
  "properties": {
    "iso:country":"GB",
    "sg:address":"Broadmead Lane, Keynsham",
    "sg:city":"Bristol",
    "sg:classifiers":[
        {
            "category":"Food & Beverages",
            "subcategory":"Supermarket",
            "type":"Retail Goods"
        }
    ],
    "sg:phone":"+44 117 986 0860",
    "sg:postcode":"BS31 1ST",
    "sg:province":"City of Bristol",
    "wof:name":"Co-Operative Pioneer",
    "wof:placetype":"venue"
},
  "geometry": {"coordinates":[-2.4838340282,51.4178733826],"type":"Point"}
}