{
  "type": "Feature",
  "properties": {
    "iso:country":"GB",
    "sg:address":"Royal Devon Yeomanry, D Squadron, Ta Centre",
    "sg:city":"Totnes",
    "sg:classifiers":[
        {
            "category":"Government",
            "subcategory":"Office",
            "type":"Public Place"
        }
    ],
    "sg:phone":"+44 1803 862856",
    "sg:postcode":"TQ9 5HW",
    "sg:province":"Devon",
    "sg:tags":[
        "armed",
        "reserve"
    ],
    "wof:name":"Territorial Auxiliary & Volunteer Reserve Associat",
    "wof:placetype":"venue"
},
  "geometry": {"coordinates":[-3.688093,50.434147],"type":"Point"}
}