{
  "type": "Feature",
  "properties": {
    "addr:full":"30 Osborne Road Potters Bar Greater London EN6 1SF",
    "addr:housenumber":"30",
    "addr:postcode":"en6 1sf",
    "addr:street":"Osborne Road",
    "iso:country":"GB",
    "sg:address":"30 Osborne Road",
    "sg:city":"Potters Bar",
    "sg:classifiers":[
        {
            "category":"Real Estate",
            "subcategory":"Architect",
            "type":"Services"
        }
    ],
    "sg:postcode":"EN6 1SF",
    "sg:province":"Greater London",
    "wof:name":"Lymingdale Ltd",
    "wof:placetype":"venue"
},
  "geometry": {"coordinates":[-0.1805029958,51.7060127258],"type":"Point"}
}