{
  "type": "Feature",
  "properties": {
    "iso:country":"GB",
    "sg:address":"8 Trostrey Close",
    "sg:city":"Pontypool",
    "sg:classifiers":[
        {
            "category":"Communications",
            "type":"Services"
        }
    ],
    "sg:postcode":"NP4 0NL",
    "sg:province":"Monmouthshire",
    "sg:tags":[
        "telecommunication"
    ],
    "wof:name":"Ajd Telecommunications Ltd.",
    "wof:placetype":"venue"
},
  "geometry": {"coordinates":[-3.002514,51.693153],"type":"Point"}
}