{
  "type": "Feature",
  "properties": {
    "addr:full":"Unit 1c, Uplyme Trading Estate, Uplyme Rd Lyme Regis Devon DT7 3LS",
    "addr:housenumber":"unit",
    "addr:postcode":"dt7 3ls",
    "addr:street":"Trading;Uplyme Rd",
    "iso:country":"GB",
    "sg:address":"Unit 1c, Uplyme Trading Estate, Uplyme Rd",
    "sg:city":"Lyme Regis",
    "sg:classifiers":[
        {
            "category":"Building & Trades",
            "subcategory":"Construction",
            "type":"Services"
        }
    ],
    "sg:phone":"+44 1297 444944",
    "sg:postcode":"DT7 3LS",
    "sg:province":"Devon",
    "sg:tags":[
        "builder"
    ],
    "wof:name":"M.F Lake Ltd",
    "wof:placetype":"venue"
},
  "geometry": {"coordinates":[-2.943626,50.727894],"type":"Point"}
}