{
  "type": "Feature",
  "properties": {
    "addr:full":"9 The Fairways, Southbourgh Tunbridge Wells Kent TN4 0DH",
    "addr:housenumber":"9",
    "addr:postcode":"tn4 0dh",
    "addr:street":"The Fairways Southbourgh Tunbridge Wells",
    "iso:country":"GB",
    "sg:address":"9 The Fairways, Southbourgh",
    "sg:city":"Tunbridge Wells",
    "sg:classifiers":[
        {
            "category":"Professional",
            "subcategory":"Engineering",
            "type":"Services"
        },
        {
            "category":"Building & Trades",
            "subcategory":"Electrical",
            "type":"Services"
        }
    ],
    "sg:phone":"+44 1892 545577",
    "sg:postcode":"TN4 0DH",
    "sg:province":"Kent",
    "sg:tags":[
        "engineer",
        "electrician",
        "contractor"
    ],
    "wof:name":"Graeme Gamage Electrician",
    "wof:placetype":"venue"
},
  "geometry": {"coordinates":[0.264526,51.150459],"type":"Point"}
}