{
  "type": "Feature",
  "properties": {
    "addr:full":"69 Rosebery Avenue Plymouth Devon PL4 8SU",
    "addr:housenumber":"69",
    "addr:postcode":"pl4 8su",
    "addr:street":"Rosebery Avenue",
    "iso:country":"GB",
    "sg:address":"69 Rosebery Avenue",
    "sg:city":"Plymouth",
    "sg:classifiers":[
        {
            "category":"Real Estate",
            "subcategory":"Architect",
            "type":"Services"
        }
    ],
    "sg:phone":"+44 1752 302077",
    "sg:postcode":"PL4 8SU",
    "sg:province":"Devon",
    "sg:tags":[
        "technologist",
        "architectural"
    ],
    "wof:name":"M.I Rawlings",
    "wof:placetype":"venue"
},
  "geometry": {"coordinates":[-4.1214971542,50.377117157],"type":"Point"}
}