{
  "type": "Feature",
  "properties": {
    "addr:full":"10 Badenheath Place, Westfield Ind Est, Cumbernauld Glasgow East Dunbartonshire G68 9HX",
    "addr:housenumber":"10",
    "addr:postcode":"g68 9hx",
    "addr:street":"Badenheath Place",
    "iso:country":"GB",
    "sg:address":"10 Badenheath Place, Westfield Ind Est, Cumbernauld",
    "sg:city":"Glasgow",
    "sg:classifiers":[
        {
            "category":"Freight",
            "type":"Transportation"
        }
    ],
    "sg:phone":"+44 1236 732444",
    "sg:postcode":"G68 9HX",
    "sg:province":"East Dunbartonshire",
    "sg:tags":[
        "haulage",
        "road"
    ],
    "wof:name":"A N C Glasgow North",
    "wof:placetype":"venue"
},
  "geometry": {"coordinates":[-4.0556740761,55.9277305603],"type":"Point"}
}