{
  "type": "Feature",
  "properties": {
    "addr:full":"154 Heath Road Hounslow Greater London TW3 2NS",
    "addr:housenumber":"154",
    "addr:postcode":"tw3 2ns",
    "addr:street":"Heath Road",
    "iso:country":"GB",
    "sg:address":"154 Heath Road",
    "sg:city":"Hounslow",
    "sg:classifiers":[
        {
            "category":"Building & Trades",
            "subcategory":"Construction",
            "type":"Services"
        }
    ],
    "sg:phone":"+44 20 8758 0954",
    "sg:postcode":"TW3 2NS",
    "sg:province":"Greater London",
    "sg:tags":[
        "builder"
    ],
    "wof:name":"Pinewood Enterprises",
    "wof:placetype":"venue"
},
  "geometry": {"coordinates":[-0.351437,51.465355],"type":"Point"}
}