{
  "type": "Feature",
  "properties": {
    "addr:full":"12 Cherry Clo Newbury Berkshire RG14 1LS",
    "addr:housenumber":"12",
    "addr:postcode":"rg14 1ls",
    "addr:street":"Cherry Clo",
    "iso:country":"GB",
    "sg:address":"12 Cherry Clo",
    "sg:city":"Newbury",
    "sg:classifiers":[
        {
            "category":"Professional",
            "subcategory":"Computer Services",
            "type":"Services"
        }
    ],
    "sg:phone":"+44 1635 821687",
    "sg:postcode":"RG14 1LS",
    "sg:province":"Berkshire",
    "sg:tags":[
        "consultant"
    ],
    "wof:name":"Graphical Magick Productions Ltd",
    "wof:placetype":"venue"
},
  "geometry": {"coordinates":[-1.325741,51.408863],"type":"Point"}
}