{
  "type": "Feature",
  "properties": {
    "addr:full":"19 Liddell Drive Llandudno Conwy LL30 1UH",
    "addr:housenumber":"19",
    "addr:postcode":"ll30 1uh",
    "addr:street":"Liddell Drive",
    "iso:country":"GB",
    "sg:address":"19 Liddell Drive",
    "sg:city":"Llandudno",
    "sg:classifiers":[
        {
            "category":"Banks & Credit Unions",
            "subcategory":"Bank",
            "type":"Services"
        }
    ],
    "sg:postcode":"LL30 1UH",
    "sg:province":"Conwy",
    "sg:tags":[
        "broker",
        "mortgage"
    ],
    "wof:name":"Brian Roberts Mortgage Services",
    "wof:placetype":"venue"
},
  "geometry": {"coordinates":[-3.815739,53.316036],"type":"Point"}
}