{
  "type": "Feature",
  "properties": {
    "addr:full":"Serendipity, Copthorne Common, Copthorne Crawley Surrey RH10 3JY",
    "addr:postcode":"rh10 3jy",
    "addr:street":"Common Copthorne",
    "iso:country":"GB",
    "sg:address":"Serendipity, Copthorne Common, Copthorne",
    "sg:city":"Crawley",
    "sg:classifiers":[
        {
            "category":"Personal",
            "type":"Services"
        }
    ],
    "sg:phone":"+44 1342 713828",
    "sg:postcode":"RH10 3JY",
    "sg:province":"Surrey",
    "sg:tags":[
        "wedding"
    ],
    "wof:name":"Serendipity Designer Tiaras",
    "wof:placetype":"venue"
},
  "geometry": {"coordinates":[-0.1219609976,51.1338768005],"type":"Point"}
}