{
  "type": "Feature",
  "properties": {
    "addr:full":"7-11 Longmoore Street London Greater London SW1V 1JH",
    "addr:housenumber":"7-11",
    "addr:postcode":"sw1v 1jh",
    "addr:street":"Longmoore Street",
    "iso:country":"GB",
    "sg:address":"7-11 Longmoore Street",
    "sg:city":"London",
    "sg:classifiers":[
        {
            "category":"Health Services",
            "subcategory":"Doctor",
            "type":"Services"
        },
        {
            "category":"Health Services",
            "subcategory":"Clinic",
            "type":"Services"
        }
    ],
    "sg:phone":"+44 20 7821 1531",
    "sg:postcode":"SW1V 1JH",
    "sg:province":"Greater London",
    "sg:tags":[
        "nh",
        "practitioners"
    ],
    "wof:name":"Victoria Medical Centre",
    "wof:placetype":"venue"
},
  "geometry": {"coordinates":[-0.1404770017,51.4924278259],"type":"Point"}
}