{
  "type": "Feature",
  "properties": {
    "addr:full":"25 Bond Street Brighton East Sussex BN1 1RD",
    "addr:housenumber":"25",
    "addr:postcode":"bn1 1rd",
    "addr:street":"Bond Street",
    "iso:country":"GB",
    "sg:address":"25 Bond Street",
    "sg:city":"Brighton",
    "sg:classifiers":[
        {
            "category":"Shopping",
            "subcategory":"Clothing, Apparel, & Fashions",
            "type":"Retail Goods"
        }
    ],
    "sg:phone":"+44 1273 325421",
    "sg:postcode":"BN1 1RD",
    "sg:province":"East Sussex",
    "sg:tags":[
        "menswear",
        "ladieswear"
    ],
    "wof:name":"Badger Clothing Co. Ltd.",
    "wof:placetype":"venue"
},
  "geometry": {"coordinates":[-0.139804,50.823975],"type":"Point"}
}