{
  "type": "Feature",
  "properties": {
    "iso:country":"GB",
    "sg:address":"65 Oldhill Street",
    "sg:city":"London",
    "sg:classifiers":[
        {
            "category":"Retail",
            "subcategory":"Laundry & Dry Cleaning",
            "type":"Services"
        }
    ],
    "sg:phone":"+44 20 8802 1111",
    "sg:postcode":"N16 6LU",
    "sg:province":"Greater London",
    "sg:tags":[
        "cleaner",
        "alteration"
    ],
    "wof:name":"Yumi's Dry Cleaners & Services Shoe Repair",
    "wof:placetype":"venue"
},
  "geometry": {"coordinates":[-0.0654020011,51.5687904358],"type":"Point"}
}