{
  "type": "Feature",
  "properties": {
    "addr:full":"21 Newbridge Way Truro Cornwall TR1 3LX",
    "addr:housenumber":"21",
    "addr:postcode":"tr1 3lx",
    "addr:street":"Newbridge Way",
    "iso:country":"GB",
    "sg:address":"21 Newbridge Way",
    "sg:city":"Truro",
    "sg:classifiers":[
        {
            "category":"Building & Trades",
            "subcategory":"Construction",
            "type":"Services"
        }
    ],
    "sg:postcode":"TR1 3LX",
    "sg:province":"Cornwall",
    "sg:tags":[
        "builder"
    ],
    "wof:name":"Keith Trethewey Builders",
    "wof:placetype":"venue"
},
  "geometry": {"coordinates":[-5.087872982,50.2602958679],"type":"Point"}
}