{
  "type": "Feature",
  "properties": {
    "iso:country":"GB",
    "sg:address":"69 South Dr, Bolton Upon Dearne",
    "sg:city":"Rotherham",
    "sg:classifiers":[
        {
            "category":"Arts & Performance",
            "subcategory":"Music",
            "type":"Entertainment"
        }
    ],
    "sg:postcode":"S63 8JZ",
    "sg:province":"South Yorkshire",
    "sg:tags":[
        "mobile",
        "disco"
    ],
    "wof:name":"Skitt,Leslie,",
    "wof:placetype":"venue"
},
  "geometry": {"coordinates":[-1.326068,53.514477],"type":"Point"}
}