{
  "type": "Feature",
  "properties": {
    "addr:full":"349-357 High Rd Wembley Greater London HA9 6BZ",
    "addr:housenumber":"349-357",
    "addr:postcode":"ha9 6bz",
    "addr:street":"High Rd",
    "iso:country":"GB",
    "sg:address":"349-357 High Rd",
    "sg:city":"Wembley",
    "sg:classifiers":[
        {
            "category":"Organizations",
            "subcategory":"Non-profit Organization",
            "type":"Services"
        }
    ],
    "sg:phone":"+44 20 8937 1980",
    "sg:postcode":"HA9 6BZ",
    "sg:province":"Greater London",
    "sg:tags":[
        "organisation",
        "voluntary",
        "charity"
    ],
    "wof:name":"A - Z Social Services",
    "wof:placetype":"venue"
},
  "geometry": {"coordinates":[-0.2905580103,51.5535087585],"type":"Point"}
}