{
  "type": "Feature",
  "properties": {
    "addr:full":", Lower Assendon Henley On Thames Berkshire RG9 6AH",
    "addr:postcode":"rg9 6ah",
    "addr:street":"Lower",
    "iso:country":"GB",
    "sg:address":", Lower Assendon",
    "sg:city":"Henley On Thames",
    "sg:classifiers":[
        {
            "category":"Bars & Pubs",
            "type":"Food & Drink"
        }
    ],
    "sg:phone":"+44 1491 574157",
    "sg:postcode":"RG9 6AH",
    "sg:province":"Berkshire",
    "sg:tags":[
        "pubs",
        "inn"
    ],
    "wof:name":"The Golden Ball",
    "wof:placetype":"venue"
},
  "geometry": {"coordinates":[-0.9031890035,51.5352973938],"type":"Point"}
}