{
  "type": "Feature",
  "properties": {
    "addr:full":"47 Walls Rd, Stoke Prior Bromsgrove Worcestershire B60 4LZ",
    "addr:housenumber":"47",
    "addr:postcode":"b60 4lz",
    "addr:street":"Walls Rd",
    "iso:country":"GB",
    "sg:address":"47 Walls Rd, Stoke Prior",
    "sg:city":"Bromsgrove",
    "sg:classifiers":[
        {
            "category":"Home & Garden",
            "subcategory":"Building Materials",
            "type":"Retail Goods"
        }
    ],
    "sg:postcode":"B60 4LZ",
    "sg:province":"Worcestershire",
    "sg:tags":[
        "fencing"
    ],
    "wof:name":"Ashmore Landscapes",
    "wof:placetype":"venue"
},
  "geometry": {"coordinates":[-2.086332,52.303932],"type":"Point"}
}