{
  "type": "Feature",
  "properties": {
    "addr:full":"Unit, 70 Station Road Whitstable Kent CT5 1LF",
    "addr:housenumber":"unit 70",
    "addr:postcode":"ct5 1lf",
    "addr:street":"Station Road",
    "iso:country":"GB",
    "sg:address":"Unit, 70 Station Road",
    "sg:city":"Whitstable",
    "sg:classifiers":[
        {
            "category":"Retail",
            "subcategory":"Auto Repair",
            "type":"Services"
        }
    ],
    "sg:phone":"+44 1227 272460",
    "sg:postcode":"CT5 1LF",
    "sg:province":"Kent",
    "sg:tags":[
        "modification",
        "garage",
        "related"
    ],
    "wof:name":"L & D Auto's",
    "wof:placetype":"venue"
},
  "geometry": {"coordinates":[1.0323129892,51.3624000549],"type":"Point"}
}