{
  "type": "Feature",
  "properties": {
    "addr:full":"Derby Street Heywood Lancashire OL10 4QJ",
    "addr:postcode":"ol10 4qj",
    "addr:street":"Derby Street",
    "iso:country":"GB",
    "sg:address":"Derby Street",
    "sg:city":"Heywood",
    "sg:classifiers":[
        {
            "category":"Organizations",
            "subcategory":"Non-profit Organization",
            "type":"Services"
        }
    ],
    "sg:phone":"+44 1706 366565",
    "sg:postcode":"OL10 4QJ",
    "sg:province":"Lancashire",
    "sg:tags":[
        "organisation",
        "voluntary",
        "charity"
    ],
    "wof:name":"Stonepark Children & Family Centre",
    "wof:placetype":"venue"
},
  "geometry": {"coordinates":[-2.2349588871,53.5945281982],"type":"Point"}
}