{
  "type": "Feature",
  "properties": {
    "addr:full":"The Vicarage, Church Av Banbury Northamptonshire OX17 3RJ",
    "addr:postcode":"ox17 3rj",
    "addr:street":"Church Av Banbury",
    "iso:country":"GB",
    "sg:address":"The Vicarage, Church Av",
    "sg:city":"Banbury",
    "sg:classifiers":[
        {
            "category":"Place Of Worship",
            "type":"Public Place"
        }
    ],
    "sg:phone":"+44 1295 811364",
    "sg:postcode":"OX17 3RJ",
    "sg:province":"Northamptonshire",
    "wof:name":"St Peter & St Paul",
    "wof:placetype":"venue"
},
  "geometry": {"coordinates":[-1.27661,52.021542],"type":"Point"}
}