{
  "type": "Feature",
  "properties": {
    "addr:full":"The Haven, Gilling East York North Yorkshire YO62 4JH",
    "addr:postcode":"yo62 4jh",
    "iso:country":"GB",
    "sg:address":"The Haven, Gilling East",
    "sg:city":"York",
    "sg:classifiers":[
        {
            "category":"Communications",
            "type":"Services"
        }
    ],
    "sg:postcode":"YO62 4JH",
    "sg:province":"North Yorkshire",
    "sg:tags":[
        "data",
        "network"
    ],
    "wof:name":"Wireless Networks Ltd",
    "wof:placetype":"venue"
},
  "geometry": {"coordinates":[-1.0588339567,54.1847686768],"type":"Point"}
}