{
  "type": "Feature",
  "properties": {
    "iso:country":"GB",
    "sg:address":"The Old Druids Head, Glendower Street",
    "sg:city":"Monmouth",
    "sg:classifiers":[
        {
            "category":"Organizations",
            "subcategory":"Community Association",
            "type":"Services"
        },
        {
            "category":"Organizations",
            "subcategory":"Membership Organization",
            "type":"Services"
        }
    ],
    "sg:phone":"+44 1600 712309",
    "sg:postcode":"NP25 3DG",
    "sg:province":"Gloucestershire",
    "sg:tags":[
        "club",
        "social"
    ],
    "wof:name":"Monmouth Rugby Football Club",
    "wof:placetype":"venue"
},
  "geometry": {"coordinates":[-2.7124109268,51.8207855225],"type":"Point"}
}