{
  "type": "Feature",
  "properties": {
    "iso:country":"GB",
    "sg:address":"15 The Thoroughfare",
    "sg:city":"Halesworth",
    "sg:classifiers":[
        {
            "category":"Shopping",
            "subcategory":"Comic Books",
            "type":"Retail Goods"
        }
    ],
    "sg:phone":"+44 1986 873209",
    "sg:postcode":"IP19 8AH",
    "sg:province":"Suffolk",
    "sg:tags":[
        "jeweller"
    ],
    "wof:name":"Densons Jewellers",
    "wof:placetype":"venue"
},
  "geometry": {"coordinates":[1.5027060509,52.3436012268],"type":"Point"}
}