{
  "type": "Feature",
  "properties": {
    "iso:country":"GB",
    "sg:address":"59 Palmerstone Rd, Wealdstone",
    "sg:city":"Harrow",
    "sg:classifiers":[
        {
            "category":"Manufacturing",
            "subcategory":"Petroleum Products",
            "type":"Manufacturing & Wholesale Goods"
        }
    ],
    "sg:postcode":"HA3 7RR",
    "sg:province":"Greater London",
    "sg:tags":[
        "double",
        "glazing"
    ],
    "wof:name":"Staylyte Units",
    "wof:placetype":"venue"
},
  "geometry": {"coordinates":[-0.3318910003,51.5931396484],"type":"Point"}
}