{
  "type": "Feature",
  "properties": {
    "iso:country":"GB",
    "sg:address":"74-75 Summer Lane, Hockley",
    "sg:city":"Birmingham",
    "sg:classifiers":[
        {
            "category":"Professional",
            "subcategory":"Engineering",
            "type":"Services"
        }
    ],
    "sg:phone":"+44 121 359 4545",
    "sg:postcode":"B19 3NG",
    "sg:province":"West Midlands",
    "sg:tags":[
        "contractor",
        "electrical",
        "engineer"
    ],
    "wof:name":"Moseley Electrics",
    "wof:placetype":"venue"
},
  "geometry": {"coordinates":[-1.8989260197,52.4911499023],"type":"Point"}
}