{
  "type": "Feature",
  "properties": {
    "addr:full":"Lion Works Old Market Street, Blackley Manchester Greater Manchester M9 3DU",
    "addr:postcode":"m9 3du",
    "addr:street":"Old Market Street",
    "iso:country":"GB",
    "sg:address":"Lion Works Old Market Street, Blackley",
    "sg:city":"Manchester",
    "sg:classifiers":[
        {
            "category":"Manufacturing",
            "subcategory":"Petroleum Products",
            "type":"Manufacturing & Wholesale Goods"
        }
    ],
    "sg:phone":"+44 161 721 4166",
    "sg:postcode":"M9 3DU",
    "sg:province":"Greater Manchester",
    "sg:tags":[
        "double",
        "glazing"
    ],
    "wof:name":"North West Windows Ltd.",
    "wof:placetype":"venue"
},
  "geometry": {"coordinates":[-2.2132198811,53.5185012817],"type":"Point"}
}