{
  "type": "Feature",
  "properties": {
    "addr:full":"Unit 7/8, Annat Point Industrial Estate, Corpach Fort William Highland PH33 7NA",
    "addr:housenumber":"unit 7 / 8",
    "addr:postcode":"ph33 7na",
    "addr:street":"Annat Point Industrial Estate;William",
    "iso:country":"GB",
    "sg:address":"Unit 7/8, Annat Point Industrial Estate, Corpach",
    "sg:city":"Fort William",
    "sg:classifiers":[
        {
            "category":"Farming",
            "subcategory":"Fish & Marine Products",
            "type":"Manufacturing & Wholesale Goods"
        }
    ],
    "sg:phone":"+44 1397 772036",
    "sg:postcode":"PH33 7NA",
    "sg:province":"Highland",
    "sg:tags":[
        "fishmonger"
    ],
    "wof:name":"Sco-Fro (Lochaber) Ltd.",
    "wof:placetype":"venue"
},
  "geometry": {"coordinates":[-5.1278648376,56.8438072205],"type":"Point"}
}