{
  "type": "Feature",
  "properties": {
    "addr:full":"Riverford Farm, Staverton Totnes Devon TQ9 6AF",
    "addr:housenumber":"riverford",
    "addr:postcode":"tq9 6af",
    "iso:country":"GB",
    "sg:address":"Riverford Farm, Staverton",
    "sg:city":"Totnes",
    "sg:classifiers":[
        {
            "category":"Farming",
            "subcategory":"Farm",
            "type":"Manufacturing & Wholesale Goods"
        }
    ],
    "sg:phone":"+44 1803 762571",
    "sg:postcode":"TQ9 6AF",
    "sg:province":"Devon",
    "sg:tags":[
        "mixed",
        "crop"
    ],
    "wof:name":"J R Watson",
    "wof:placetype":"venue"
},
  "geometry": {"coordinates":[-3.701889,50.463982],"type":"Point"}
}