{
  "type": "Feature",
  "properties": {
    "addr:full":"5 Sussex Clo Chalfont St Giles Buckinghamshire HP8 4PP",
    "addr:housenumber":"5",
    "addr:postcode":"hp8 4pp",
    "addr:street":"Sussex Clo;St",
    "iso:country":"GB",
    "sg:address":"5 Sussex Clo",
    "sg:city":"Chalfont St Giles",
    "sg:classifiers":[
        {
            "category":"Health Services",
            "subcategory":"Health Practitioner",
            "type":"Services"
        }
    ],
    "sg:phone":"+44 1494 872359",
    "sg:postcode":"HP8 4PP",
    "sg:province":"Buckinghamshire",
    "sg:tags":[
        "physiotherapist"
    ],
    "wof:name":"Ann Beavis",
    "wof:placetype":"venue"
},
  "geometry": {"coordinates":[-0.5741860271,51.6324310303],"type":"Point"}
}