{
  "type": "Feature",
  "properties": {
    "iso:country":"GB",
    "sg:address":"Cancellation Line, Ambulance Headquarters, Garstang Rd",
    "sg:city":"Preston",
    "sg:classifiers":[
        {
            "category":"Health Services",
            "subcategory":"Hospital",
            "type":"Services"
        }
    ],
    "sg:phone":"+44 1772 773077",
    "sg:postcode":"PR3 5LN",
    "sg:province":"Lancashire",
    "sg:tags":[
        "ambulance"
    ],
    "wof:name":"Patient Transport Services",
    "wof:placetype":"venue"
},
  "geometry": {"coordinates":[-2.72252,53.803612],"type":"Point"}
}