{
  "type": "Feature",
  "properties": {
    "addr:full":"28 Glanhowy Road, Wyllie Blackwood Caerphilly NP12 2HN",
    "addr:housenumber":"28",
    "addr:postcode":"np12 2hn",
    "addr:street":"Glanhowy Road",
    "iso:country":"GB",
    "sg:address":"28 Glanhowy Road, Wyllie",
    "sg:city":"Blackwood",
    "sg:classifiers":[
        {
            "category":"Government",
            "subcategory":"Post Office",
            "type":"Public Place"
        }
    ],
    "sg:phone":"+44 1495 200200",
    "sg:postcode":"NP12 2HN",
    "sg:province":"Caerphilly",
    "wof:name":"Wyllie Post Office",
    "wof:placetype":"venue"
},
  "geometry": {"coordinates":[-3.190054,51.641239],"type":"Point"}
}