{
  "type": "Feature",
  "properties": {
    "addr:full":"513a High Rd Wembley Greater London HA0 4AG",
    "addr:housenumber":"513a",
    "addr:postcode":"ha0 4ag",
    "addr:street":"High Rd",
    "iso:country":"GB",
    "sg:address":"513a High Rd",
    "sg:city":"Wembley",
    "sg:classifiers":[
        {
            "category":"Organizations",
            "subcategory":"Non-profit Organization",
            "type":"Services"
        }
    ],
    "sg:phone":"+44 20 8795 0657",
    "sg:postcode":"HA0 4AG",
    "sg:province":"Greater London",
    "sg:tags":[
        "organisation",
        "voluntary",
        "charity"
    ],
    "wof:name":"Somali Care & Cultural Society",
    "wof:placetype":"venue"
},
  "geometry": {"coordinates":[-0.298439,51.551929],"type":"Point"}
}