{
  "type": "Feature",
  "properties": {
    "iso:country":"GB",
    "sg:address":"15 Beverley Road",
    "sg:city":"Colchester",
    "sg:classifiers":[
        {
            "category":"Professional",
            "subcategory":"Lawyer & Legal Services",
            "type":"Services"
        }
    ],
    "sg:phone":"+44 1206 769342",
    "sg:postcode":"CO3 3NG",
    "sg:province":"Essex",
    "sg:tags":[
        "solicitor"
    ],
    "wof:name":"Sharon Coomber",
    "wof:placetype":"venue"
},
  "geometry": {"coordinates":[0.885108,51.886547],"type":"Point"}
}