{
  "type": "Feature",
  "properties": {
    "iso:country":"GB",
    "sg:address":"125 Fengate",
    "sg:city":"Peterborough",
    "sg:classifiers":[
        {
            "category":"Manufacturing",
            "subcategory":"Metals",
            "type":"Manufacturing & Wholesale Goods"
        },
        {
            "category":"Retail",
            "subcategory":"Animal Services",
            "type":"Services"
        }
    ],
    "sg:phone":"+44 1733 565677",
    "sg:postcode":"PE1 5BA",
    "sg:province":"Cambridgeshire",
    "sg:tags":[
        "blacksmith",
        "forgemasters",
        "farrier"
    ],
    "wof:name":"ROBERT JOHN MASON",
    "wof:placetype":"venue"
},
  "geometry": {"coordinates":[-0.2224259973,52.5710945129],"type":"Point"}
}