{
  "type": "Feature",
  "properties": {
    "addr:full":"84 Linthurst Newtown, Blackwell Bromsgrove Worcestershire B60 1BS",
    "addr:housenumber":"84",
    "addr:postcode":"b60 1bs",
    "addr:street":"Linthurst Newtown",
    "iso:country":"GB",
    "sg:address":"84 Linthurst Newtown, Blackwell",
    "sg:city":"Bromsgrove",
    "sg:classifiers":[
        {
            "category":"Organizations",
            "subcategory":"Community Association",
            "type":"Services"
        },
        {
            "category":"Organizations",
            "subcategory":"Membership Organization",
            "type":"Services"
        }
    ],
    "sg:phone":"+44 121 445 2134",
    "sg:postcode":"B60 1BS",
    "sg:province":"Worcestershire",
    "sg:tags":[
        "club",
        "social"
    ],
    "wof:name":"Blackwell Club",
    "wof:placetype":"venue"
},
  "geometry": {"coordinates":[-2.015969038,52.3483734131],"type":"Point"}
}