{
  "type": "Feature",
  "properties": {
    "addr:full":"110 Jermyn Street London Greater London SW1Y 6EE",
    "addr:housenumber":"110",
    "addr:postcode":"sw1y 6ee",
    "addr:street":"Jermyn Street",
    "iso:country":"GB",
    "sg:address":"110 Jermyn Street",
    "sg:city":"London",
    "sg:classifiers":[
        {
            "category":"Military Area",
            "subcategory":"Air Force Base",
            "type":"Public Place"
        }
    ],
    "sg:postcode":"SW1Y 6EE",
    "sg:province":"Greater London",
    "sg:tags":[
        "water",
        "treatment"
    ],
    "wof:name":"Fospur Ltd.",
    "wof:placetype":"venue"
},
  "geometry": {"coordinates":[-0.139229,51.507591],"type":"Point"}
}