{
  "type": "Feature",
  "properties": {
    "addr:full":"42 Quay Street Scarborough North Yorkshire YO11 1PL",
    "addr:housenumber":"42",
    "addr:postcode":"yo11 1pl",
    "addr:street":"Quay Street",
    "iso:country":"GB",
    "sg:address":"42 Quay Street",
    "sg:city":"Scarborough",
    "sg:classifiers":[
        {
            "category":"Organizations",
            "subcategory":"Non-profit Organization",
            "type":"Services"
        }
    ],
    "sg:phone":"+44 1723 374981",
    "sg:postcode":"YO11 1PL",
    "sg:province":"North Yorkshire",
    "sg:tags":[
        "organisation",
        "voluntary",
        "charity"
    ],
    "wof:name":"Scarborough Fishermans Wives Benevolent Association",
    "wof:placetype":"venue"
},
  "geometry": {"coordinates":[-0.3881410062,54.2845115662],"type":"Point"}
}