{
  "type": "Feature",
  "properties": {
    "addr:full":"195 London Road Croydon Surrey CR0 2RJ",
    "addr:housenumber":"195",
    "addr:postcode":"cr0 2rj",
    "addr:street":"London Road",
    "iso:country":"GB",
    "sg:address":"195 London Road",
    "sg:city":"Croydon",
    "sg:classifiers":[
        {
            "category":"Shopping",
            "subcategory":"Musical Instruments",
            "type":"Retail Goods"
        }
    ],
    "sg:phone":"+44 20 8769 5681",
    "sg:postcode":"CR0 2RJ",
    "sg:province":"Surrey",
    "sg:tags":[
        "music",
        "sheet"
    ],
    "wof:name":"Gigsounds Ltd.",
    "wof:placetype":"venue"
},
  "geometry": {"coordinates":[-0.1064210013,51.3820075989],"type":"Point"}
}