{
  "type": "Feature",
  "properties": {
    "addr:full":"Harehills Community Centre, Harehills Rd Leeds West Yorkshire LS8 5HS",
    "addr:postcode":"ls8 5hs",
    "addr:street":"Harehills Rd",
    "iso:country":"GB",
    "sg:address":"Harehills Community Centre, Harehills Rd",
    "sg:city":"Leeds",
    "sg:classifiers":[
        {
            "category":"Organizations",
            "subcategory":"Non-profit Organization",
            "type":"Services"
        }
    ],
    "sg:phone":"+44 113 249 2734",
    "sg:postcode":"LS8 5HS",
    "sg:province":"West Yorkshire",
    "sg:tags":[
        "organisation",
        "voluntary",
        "charity"
    ],
    "wof:name":"Leeds Festival Ltd (The)",
    "wof:placetype":"venue"
},
  "geometry": {"coordinates":[-1.515044,53.816872],"type":"Point"}
}