{
  "type": "Feature",
  "properties": {
    "addr:full":"Metro House, Pentre Industrial Estate, Chester Road Deeside Flintshire CH5 2DQ",
    "addr:postcode":"ch5 2dq",
    "addr:street":"Pentre Industrial Estate Chester Road",
    "iso:country":"GB",
    "sg:address":"Metro House, Pentre Industrial Estate, Chester Road",
    "sg:city":"Deeside",
    "sg:classifiers":[
        {
            "category":"Building & Trades",
            "subcategory":"Plumbing",
            "type":"Services"
        }
    ],
    "sg:phone":"+44 1244 520552",
    "sg:postcode":"CH5 2DQ",
    "sg:province":"Flintshire",
    "sg:tags":[
        "drain",
        "clearance",
        "sewer"
    ],
    "wof:name":"Metro Rod",
    "wof:placetype":"venue"
},
  "geometry": {"coordinates":[-3.024988,53.20248],"type":"Point"}
}