{
  "type": "Feature",
  "properties": {
    "addr:full":"The Vestry, St Clements Church, Treadgold Street London Greater London W11 4BP",
    "addr:postcode":"w11 4bp",
    "addr:street":"St Clements;Treadgold Street",
    "iso:country":"GB",
    "sg:address":"The Vestry, St Clements Church, Treadgold Street",
    "sg:city":"London",
    "sg:classifiers":[
        {
            "category":"Wholesale",
            "subcategory":"Construction Materials",
            "type":"Manufacturing & Wholesale Goods"
        },
        {
            "category":"Manufacturing",
            "subcategory":"Lumber",
            "type":"Manufacturing & Wholesale Goods"
        }
    ],
    "sg:phone":"+44 20 7221 7930",
    "sg:postcode":"W11 4BP",
    "sg:province":"Greater London",
    "sg:tags":[
        "merchant",
        "stone",
        "merchants",
        "agent",
        "importer",
        "timber"
    ],
    "wof:name":"Buffalo Granite (U K) Ltd.",
    "wof:placetype":"venue"
},
  "geometry": {"coordinates":[-0.2145899981,51.5123901367],"type":"Point"}
}