{
  "type": "Feature",
  "properties": {
    "iso:country":"GB",
    "sg:address":"6 Aveling Drive",
    "sg:city":"Southport",
    "sg:classifiers":[
        {
            "category":"Building & Trades",
            "subcategory":"Construction",
            "type":"Services"
        }
    ],
    "sg:phone":"+44 800 917 4031",
    "sg:postcode":"PR9 8BJ",
    "sg:province":"Lancashire",
    "sg:tags":[
        "window",
        "tinting",
        "replacement"
    ],
    "sg:website":"http://www.ukwindowfilm.co.uk",
    "wof:name":"Advanced Window Films",
    "wof:placetype":"venue"
},
  "geometry": {"coordinates":[-2.9218299389,53.6778335571],"type":"Point"}
}