{
  "type": "Feature",
  "properties": {
    "addr:full":"Unit 14 Eurolink Business Centre London Greater London SW2 1BZ",
    "addr:housenumber":"unit 14",
    "addr:postcode":"sw2 1bz",
    "addr:street":"Eurolink Business Centre",
    "iso:country":"GB",
    "sg:address":"Unit 14 Eurolink Business Centre",
    "sg:city":"London",
    "sg:classifiers":[
        {
            "category":"Education",
            "subcategory":"Special Training",
            "type":"Public Place"
        }
    ],
    "sg:phone":"+44 1494 422389",
    "sg:postcode":"SW2 1BZ",
    "sg:province":"Greater London",
    "sg:tags":[
        "product",
        "centre"
    ],
    "wof:name":"The Training Access Co.",
    "wof:placetype":"venue"
},
  "geometry": {"coordinates":[-0.11446,51.457581],"type":"Point"}
}