{
  "type": "Feature",
  "properties": {
    "addr:full":"The Chalet House, Golf Club Road Weybridge Surrey KT13 0NN",
    "addr:postcode":"kt13 0nn",
    "addr:street":"Club Road",
    "iso:country":"GB",
    "sg:address":"The Chalet House, Golf Club Road",
    "sg:city":"Weybridge",
    "sg:classifiers":[
        {
            "category":"Shopping",
            "subcategory":"Books",
            "type":"Retail Goods"
        }
    ],
    "sg:phone":"+44 1932 849293",
    "sg:postcode":"KT13 0NN",
    "sg:province":"Surrey",
    "wof:name":"M R Ali",
    "wof:placetype":"venue"
},
  "geometry": {"coordinates":[-0.445412,51.347359],"type":"Point"}
}