{
  "type": "Feature",
  "properties": {
    "iso:country":"GB",
    "sg:address":"30 Regent Road",
    "sg:city":"Great Yarmouth",
    "sg:classifiers":[
        {
            "category":"Shopping",
            "subcategory":"Gifts & Souvenirs",
            "type":"Retail Goods"
        }
    ],
    "sg:postcode":"NR30 2AF",
    "sg:province":"Norfolk",
    "sg:tags":[
        "shop"
    ],
    "wof:name":"Rosemary's",
    "wof:placetype":"venue"
},
  "geometry": {"coordinates":[1.732368,52.607719],"type":"Point"}
}