{
  "type": "Feature",
  "properties": {
    "addr:full":"70 Sayes Court Road Orpington Kent BR5 2PQ",
    "addr:housenumber":"70",
    "addr:postcode":"br5 2pq",
    "addr:street":"Sayes Court Road",
    "iso:country":"GB",
    "sg:address":"70 Sayes Court Road",
    "sg:city":"Orpington",
    "sg:classifiers":[
        {
            "category":"Personal",
            "subcategory":"Beauty Salon",
            "type":"Services"
        }
    ],
    "sg:postcode":"BR5 2PQ",
    "sg:province":"Kent",
    "wof:name":"Jofo Beauty Clinic",
    "wof:placetype":"venue"
},
  "geometry": {"coordinates":[0.1065300032,51.3954811096],"type":"Point"}
}