{
  "type": "Feature",
  "properties": {
    "iso:country":"GB",
    "sg:address":"Mossilee Farm",
    "sg:city":"Galashiels",
    "sg:classifiers":[
        {
            "category":"Farming",
            "subcategory":"Livestock Farm",
            "type":"Manufacturing & Wholesale Goods"
        }
    ],
    "sg:postcode":"TD1 1TE",
    "sg:province":"Scottish Borders",
    "sg:tags":[
        "others"
    ],
    "wof:name":"James Pate",
    "wof:placetype":"venue"
},
  "geometry": {"coordinates":[-2.8222289085,55.6166114807],"type":"Point"}
}