{
  "type": "Feature",
  "properties": {
    "addr:full":"127 Blackburn Road, Heapey Chorley Lancashire PR6 8EJ",
    "addr:housenumber":"127",
    "addr:postcode":"pr6 8ej",
    "addr:street":"Blackburn Road",
    "iso:country":"GB",
    "sg:address":"127 Blackburn Road, Heapey",
    "sg:city":"Chorley",
    "sg:classifiers":[
        {
            "category":"Retail",
            "subcategory":"Veterinary Services",
            "type":"Services"
        },
        {
            "category":"Retail",
            "subcategory":"Animal Services",
            "type":"Services"
        }
    ],
    "sg:phone":"+44 1257 249960",
    "sg:postcode":"PR6 8EJ",
    "sg:province":"Lancashire",
    "sg:tags":[
        "training",
        "dog",
        "activity"
    ],
    "wof:name":"Animal Behavioural Clinic",
    "wof:placetype":"venue"
},
  "geometry": {"coordinates":[-2.6108059883,53.6824455261],"type":"Point"}
}