{
  "type": "Feature",
  "properties": {
    "addr:full":"2 The Cottages, Shipton-on-cherwell Kidlington Buckinghamshire OX5 1JP",
    "addr:housenumber":"2",
    "addr:postcode":"ox5 1jp",
    "addr:street":"The;Shipton-On-Cherwell",
    "iso:country":"GB",
    "sg:address":"2 The Cottages, Shipton-on-cherwell",
    "sg:city":"Kidlington",
    "sg:classifiers":[
        {
            "category":"Building & Trades",
            "subcategory":"Construction",
            "type":"Services"
        }
    ],
    "sg:postcode":"OX5 1JP",
    "sg:province":"Buckinghamshire",
    "sg:tags":[
        "decorator",
        "painter"
    ],
    "wof:name":"Brenda Gratwicke",
    "wof:placetype":"venue"
},
  "geometry": {"coordinates":[-1.305844,51.847816],"type":"Point"}
}