{
  "type": "Feature",
  "properties": {
    "iso:country":"GB",
    "sg:address":"Unit 2 The Bridges",
    "sg:city":"Sunderland",
    "sg:classifiers":[
        {
            "category":"Home & Garden",
            "subcategory":"Household Appliances",
            "type":"Retail Goods"
        }
    ],
    "sg:phone":"+44 191 565 1211",
    "sg:postcode":"SR1 3LB",
    "sg:province":"Tyne and Wear",
    "sg:tags":[
        "gas"
    ],
    "wof:name":"British Gas Energy Centre",
    "wof:placetype":"venue"
},
  "geometry": {"coordinates":[-1.442099,54.91851],"type":"Point"}
}