{
  "type": "Feature",
  "properties": {
    "addr:full":"19 Market Place Barton-upon-humber Lincolnshire DN18 5DA",
    "addr:housenumber":"19",
    "addr:postcode":"dn18 5da",
    "addr:street":"Market Place",
    "iso:country":"GB",
    "sg:address":"19 Market Place",
    "sg:city":"Barton-upon-humber",
    "sg:classifiers":[
        {
            "category":"Real Estate",
            "subcategory":"Real Estate Agent",
            "type":"Services"
        }
    ],
    "sg:phone":"+44 1652 655151",
    "sg:postcode":"DN18 5DA",
    "sg:province":"Lincolnshire",
    "wof:name":"Bell Watson Estates",
    "wof:placetype":"venue"
},
  "geometry": {"coordinates":[-0.439101994,53.6827125549],"type":"Point"}
}