{
  "type": "Feature",
  "properties": {
    "iso:country":"GB",
    "sg:address":"39 Monarch Mews, Kettering Rd",
    "sg:city":"Northampton",
    "sg:classifiers":[
        {
            "category":"Shopping",
            "subcategory":"Clothing, Apparel, & Fashions",
            "type":"Retail Goods"
        }
    ],
    "sg:phone":"+44 1604 233177",
    "sg:postcode":"NN1 4AJ",
    "sg:province":"Northamptonshire",
    "sg:tags":[
        "shop"
    ],
    "wof:name":"The Score",
    "wof:placetype":"venue"
},
  "geometry": {"coordinates":[-0.895284,52.23394],"type":"Point"}
}