{
  "type": "Feature",
  "properties": {
    "iso:country":"GB",
    "sg:address":"3 Correen Close",
    "sg:city":"Lincoln",
    "sg:classifiers":[
        {
            "category":"Retail",
            "subcategory":"Driving School",
            "type":"Services"
        }
    ],
    "sg:phone":"+44 1522 720262",
    "sg:postcode":"LN5 9AT",
    "sg:province":"Lincolnshire",
    "wof:name":"Rodcraft School Of Motoring",
    "wof:placetype":"venue"
},
  "geometry": {"coordinates":[-0.555084,53.190933],"type":"Point"}
}