{
  "type": "Feature",
  "properties": {
    "addr:full":"The White Ho, Imperial Business & Retail Pk Gravesend Kent DA11 0DY",
    "addr:postcode":"da11 0dy",
    "addr:street":"Pk",
    "iso:country":"GB",
    "sg:address":"The White Ho, Imperial Business & Retail Pk",
    "sg:city":"Gravesend",
    "sg:classifiers":[
        {
            "category":"Shopping",
            "subcategory":"Computers & Home Electronics",
            "type":"Retail Goods"
        }
    ],
    "sg:phone":"+44 1474 327998",
    "sg:postcode":"DA11 0DY",
    "sg:province":"Kent",
    "sg:tags":[
        "system",
        "automation"
    ],
    "wof:name":"Marsh Systems Ltd",
    "wof:placetype":"venue"
},
  "geometry": {"coordinates":[0.36202,51.44521],"type":"Point"}
}