{
  "type": "Feature",
  "properties": {
    "addr:full":"45a High Street Oakham Leicestershire LE15 6AJ",
    "addr:housenumber":"45a",
    "addr:postcode":"le15 6aj",
    "addr:street":"High Street",
    "iso:country":"GB",
    "sg:address":"45a High Street",
    "sg:city":"Oakham",
    "sg:classifiers":[
        {
            "category":"Home & Garden",
            "subcategory":"Carpets & Floor Coverings",
            "type":"Retail Goods"
        }
    ],
    "sg:phone":"+44 1572 755926",
    "sg:postcode":"LE15 6AJ",
    "sg:province":"Leicestershire",
    "sg:tags":[
        "carpets",
        "rug",
        "matting"
    ],
    "wof:name":"Carpet World",
    "wof:placetype":"venue"
},
  "geometry": {"coordinates":[-0.731028,52.670174],"type":"Point"}
}