{
  "type": "Feature",
  "properties": {
    "iso:country":"GB",
    "sg:address":"10 Central Avenue",
    "sg:city":"Gravesend",
    "sg:classifiers":[
        {
            "category":"Building & Trades",
            "subcategory":"Construction",
            "type":"Services"
        }
    ],
    "sg:postcode":"DA12 5AD",
    "sg:province":"Kent",
    "sg:tags":[
        "builder"
    ],
    "wof:name":"A1 Roofing Services",
    "wof:placetype":"venue"
},
  "geometry": {"coordinates":[0.370565,51.429054],"type":"Point"}
}