{
  "type": "Feature",
  "properties": {
    "addr:full":", Blackpool Dartmouth Devon TQ6 0RG",
    "addr:postcode":"tq6 0rg",
    "iso:country":"GB",
    "sg:address":", Blackpool",
    "sg:city":"Dartmouth",
    "sg:classifiers":[
        {
            "category":"Community Center",
            "type":"Public Place"
        }
    ],
    "sg:phone":"+44 1803 770606",
    "sg:postcode":"TQ6 0RG",
    "sg:province":"Devon",
    "sg:tags":[
        "recreation",
        "leisure",
        "centre"
    ],
    "wof:name":"Blackpool Sands Utilities Co.Ltd",
    "wof:placetype":"venue"
},
  "geometry": {"coordinates":[-3.611919,50.32],"type":"Point"}
}