{
  "type": "Feature",
  "properties": {
    "iso:country":"GB",
    "sg:address":"4 Woodside Park Road, North Finchley",
    "sg:city":"London",
    "sg:classifiers":[
        {
            "category":"Travel",
            "subcategory":"Hotels & Motels",
            "type":"Entertainment"
        }
    ],
    "sg:phone":"+44 20 8445 0440",
    "sg:postcode":"N12 8RP",
    "sg:province":"Greater London",
    "wof:name":"The Glenlyn Hotel",
    "wof:placetype":"venue"
},
  "geometry": {"coordinates":[-0.177315,51.617237],"type":"Point"}
}