{
  "type": "Feature",
  "properties": {
    "addr:full":"664 Huddersfield Road Dewsbury West Yorkshire WF13 3HP",
    "addr:housenumber":"664",
    "addr:postcode":"wf13 3hp",
    "addr:street":"Huddersfield Road",
    "iso:country":"GB",
    "sg:address":"664 Huddersfield Road",
    "sg:city":"Dewsbury",
    "sg:classifiers":[
        {
            "category":"Fast Food",
            "type":"Food & Drink"
        }
    ],
    "sg:phone":"+44 1924 492972",
    "sg:postcode":"WF13 3HP",
    "sg:province":"West Yorkshire",
    "sg:tags":[
        "away",
        "meal",
        "outlet",
        "take"
    ],
    "wof:name":"The Snack Station",
    "wof:placetype":"venue"
},
  "geometry": {"coordinates":[-1.666443,53.678467],"type":"Point"}
}