{
  "type": "Feature",
  "properties": {
    "addr:full":"44-46 Church St Weybridge Surrey KT13 8DP",
    "addr:housenumber":"44-46",
    "addr:postcode":"kt13 8dp",
    "addr:street":"Church St",
    "iso:country":"GB",
    "sg:address":"44-46 Church St",
    "sg:city":"Weybridge",
    "sg:classifiers":[
        {
            "category":"Shopping",
            "subcategory":"Crafts & Fabrics",
            "type":"Retail Goods"
        }
    ],
    "sg:postcode":"KT13 8DP",
    "sg:province":"Surrey",
    "sg:tags":[
        "material",
        "art"
    ],
    "wof:name":"Cave's Picture Shop",
    "wof:placetype":"venue"
},
  "geometry": {"coordinates":[-0.4612610042,51.3722877502],"type":"Point"}
}