{
  "type": "Feature",
  "properties": {
    "addr:full":"5 Old Parish Hall, Dudley La Cramlington Northumberland NE23 6UW",
    "addr:housenumber":"5",
    "addr:postcode":"ne23 6uw",
    "addr:street":"Old Parish;La;Northumberland",
    "iso:country":"GB",
    "sg:address":"5 Old Parish Hall, Dudley La",
    "sg:city":"Cramlington",
    "sg:classifiers":[
        {
            "category":"Retail",
            "subcategory":"Photofinishing",
            "type":"Services"
        }
    ],
    "sg:phone":"+44 1670 739000",
    "sg:postcode":"NE23 6UW",
    "sg:province":"Northumberland",
    "sg:tags":[
        "photographic",
        "processor"
    ],
    "wof:name":"Picture Box Studio-Kwikphoto",
    "wof:placetype":"venue"
},
  "geometry": {"coordinates":[-1.5648570061,55.0781173706],"type":"Point"}
}