{
  "type": "Feature",
  "properties": {
    "addr:full":"372 Handsworth Rd Sheffield South Yorkshire S13 9BY",
    "addr:housenumber":"372",
    "addr:postcode":"s13 9by",
    "addr:street":"Handsworth Rd",
    "iso:country":"GB",
    "sg:address":"372 Handsworth Rd",
    "sg:city":"Sheffield",
    "sg:classifiers":[
        {
            "category":"Food & Beverages",
            "subcategory":"Liquor & Beverages",
            "type":"Retail Goods"
        }
    ],
    "sg:phone":"+44 114 269 9740",
    "sg:postcode":"S13 9BY",
    "sg:province":"South Yorkshire",
    "sg:tags":[
        "beer",
        "spirit",
        "wines"
    ],
    "wof:name":"Huttons",
    "wof:placetype":"venue"
},
  "geometry": {"coordinates":[-1.3862320185,53.3709907532],"type":"Point"}
}