{
  "type": "Feature",
  "properties": {
    "addr:full":"48 Holywell Hill St Albans Hertfordshire AL1 1BX",
    "addr:housenumber":"48",
    "addr:postcode":"al1 1bx",
    "addr:street":"Holywell Hill",
    "iso:country":"GB",
    "sg:address":"48 Holywell Hill",
    "sg:city":"St Albans",
    "sg:classifiers":[
        {
            "category":"Insurance",
            "subcategory":"Insurance Agent",
            "type":"Services"
        }
    ],
    "sg:postcode":"AL1 1BX",
    "sg:province":"Hertfordshire",
    "sg:tags":[
        "broker"
    ],
    "wof:name":"Patterson Maisey Insurance Services",
    "wof:placetype":"venue"
},
  "geometry": {"coordinates":[-0.340832,51.74934],"type":"Point"}
}