{
  "type": "Feature",
  "properties": {
    "iso:country":"GB",
    "sg:address":"Barkston Road, Carlton Industrial Estate",
    "sg:city":"Barnsley",
    "sg:classifiers":[
        {
            "category":"Shopping",
            "type":"Retail Goods"
        }
    ],
    "sg:phone":"+44 1226 243333",
    "sg:postcode":"S71 3HU",
    "sg:province":"South Yorkshire",
    "sg:tags":[
        "part",
        "accessory"
    ],
    "wof:name":"G & H Spares (Barnsley) Ltd.",
    "wof:placetype":"venue"
},
  "geometry": {"coordinates":[-1.4520109892,53.5839767456],"type":"Point"}
}