{
  "type": "Feature",
  "properties": {
    "iso:country":"GB",
    "sg:address":"Unit 45h, Langthwaite Grange Industrial Estate, South Elmsall",
    "sg:city":"Pontefract",
    "sg:classifiers":[
        {
            "category":"Autos & Motor Vehicles",
            "subcategory":"Automobile Sales",
            "type":"Retail Goods"
        },
        {
            "category":"Autos & Motor Vehicles",
            "subcategory":"Auto Supplies",
            "type":"Retail Goods"
        }
    ],
    "sg:phone":"+44 1977 649476",
    "sg:postcode":"WF9 3NR",
    "sg:province":"West Yorkshire",
    "sg:tags":[
        "car",
        "component"
    ],
    "wof:name":"South Kirkby Motor Factors Ltd",
    "wof:placetype":"venue"
},
  "geometry": {"coordinates":[-1.308569,53.588509],"type":"Point"}
}