{
  "type": "Feature",
  "properties": {
    "iso:country":"GB",
    "sg:address":"199 City Road",
    "sg:city":"Stoke-on-trent",
    "sg:classifiers":[
        {
            "category":"Manufacturing",
            "subcategory":"Signs",
            "type":"Manufacturing & Wholesale Goods"
        }
    ],
    "sg:phone":"+44 1782 844460",
    "sg:postcode":"ST4 2PL",
    "sg:province":"Staffordshire",
    "sg:tags":[
        "nameplate"
    ],
    "wof:name":"Stoke Signs Ltd.",
    "wof:placetype":"venue"
},
  "geometry": {"coordinates":[-2.1672461033,53.000038147],"type":"Point"}
}