{
  "type": "Feature",
  "properties": {
    "iso:country":"GB",
    "sg:address":"18 Northgate",
    "sg:city":"Bridgwater",
    "sg:classifiers":[
        {
            "category":"Professional",
            "subcategory":"Printing & Photocopies",
            "type":"Services"
        }
    ],
    "sg:phone":"+44 1278 423161",
    "sg:postcode":"TA6 3EU",
    "sg:province":"Somerset",
    "sg:tags":[
        "plate",
        "lithographic",
        "maker"
    ],
    "wof:name":"Laserprint (South West) Ltd.",
    "wof:placetype":"venue"
},
  "geometry": {"coordinates":[-3.004575,51.130001],"type":"Point"}
}