{
  "type": "Feature",
  "properties": {
    "iso:country":"GB",
    "sg:address":"Manor Road, Caister-on-sea",
    "sg:city":"Great Yarmouth",
    "sg:classifiers":[
        {
            "category":"Travel",
            "subcategory":"Hotels & Motels",
            "type":"Entertainment"
        }
    ],
    "sg:phone":"+44 1493 721630",
    "sg:postcode":"NR30 5HG",
    "sg:province":"Norfolk",
    "sg:tags":[
        "self",
        "catering"
    ],
    "wof:name":"G & M SAYER",
    "wof:placetype":"venue"
},
  "geometry": {"coordinates":[1.732875,52.649273],"type":"Point"}
}