{
  "type": "Feature",
  "properties": {
    "iso:country":"GB",
    "sg:address":"Water Farm, Stowting",
    "sg:city":"Ashford",
    "sg:classifiers":[
        {
            "category":"Recreation",
            "subcategory":"Fishing",
            "type":"Entertainment"
        }
    ],
    "sg:postcode":"TN25 6BA",
    "sg:province":"Kent",
    "sg:tags":[
        "angling"
    ],
    "wof:name":"Stowting Trout Lake",
    "wof:placetype":"venue"
},
  "geometry": {"coordinates":[1.035245,51.135841],"type":"Point"}
}