{
  "type": "Feature",
  "properties": {
    "iso:country":"GB",
    "sg:address":"7 Abergele Road",
    "sg:city":"Colwyn Bay",
    "sg:classifiers":[
        {
            "category":"Shopping",
            "subcategory":"Discount & Variety Stores",
            "type":"Retail Goods"
        }
    ],
    "sg:phone":"+44 1492 532143",
    "sg:postcode":"LL29 7RS",
    "sg:province":"Conwy",
    "sg:tags":[
        "centre"
    ],
    "wof:name":"A & A Cash & Carry",
    "wof:placetype":"venue"
},
  "geometry": {"coordinates":[-3.726901,53.29475],"type":"Point"}
}