{
  "type": "Feature",
  "properties": {
    "addr:full":"Unit 1, Finway, Dallow Road Luton Bedfordshire LU1 1WE",
    "addr:housenumber":"unit 1",
    "addr:postcode":"lu1 1we",
    "addr:street":"Dallow Road",
    "iso:country":"GB",
    "sg:address":"Unit 1, Finway, Dallow Road",
    "sg:city":"Luton",
    "sg:classifiers":[
        {
            "category":"Professional",
            "subcategory":"Computer Services",
            "type":"Services"
        }
    ],
    "sg:phone":"+44 870 729 5555",
    "sg:postcode":"LU1 1WE",
    "sg:province":"Bedfordshire",
    "sg:tags":[
        "system",
        "software"
    ],
    "wof:name":"Watford Electronics Ltd.",
    "wof:placetype":"venue"
},
  "geometry": {"coordinates":[-0.4572040141,51.8855323792],"type":"Point"}
}