{
  "type": "Feature",
  "properties": {
    "iso:country":"GB",
    "sg:address":"Beehive Farm, Lullington Rd, Rosliston",
    "sg:city":"Swadlincote",
    "sg:classifiers":[
        {
            "category":"Health Services",
            "subcategory":"Health Practitioner",
            "type":"Services"
        }
    ],
    "sg:phone":"+44 1283 760522",
    "sg:postcode":"DE12 8HZ",
    "sg:province":"Derbyshire",
    "sg:tags":[
        "osteopath"
    ],
    "wof:name":"Peter Sadler Natural Medicine D.O.Lic. Ac.",
    "wof:placetype":"venue"
},
  "geometry": {"coordinates":[-1.631482,52.714512],"type":"Point"}
}