{
  "type": "Feature",
  "properties": {
    "addr:full":"Preston Cold Store, Cromwell Rd, Ribbleton Preston Lancashire PR2 6YD",
    "addr:postcode":"pr2 6yd",
    "addr:street":"Cromwell Rd",
    "iso:country":"GB",
    "sg:address":"Preston Cold Store, Cromwell Rd, Ribbleton",
    "sg:city":"Preston",
    "sg:classifiers":[
        {
            "category":"Communications",
            "subcategory":"Film & Video Production",
            "type":"Services"
        }
    ],
    "sg:phone":"+44 1772 652371",
    "sg:postcode":"PR2 6YD",
    "sg:province":"Lancashire",
    "sg:tags":[
        "curers",
        "bacon",
        "ham"
    ],
    "wof:name":"N.J.M Bacon",
    "wof:placetype":"venue"
},
  "geometry": {"coordinates":[-2.668789,53.768978],"type":"Point"}
}