{
  "type": "Feature",
  "properties": {
    "addr:full":"Rickmansworth Rd, Chorleywood Rickmansworth Hertfordshire WD3 5BY",
    "addr:postcode":"wd3 5by",
    "addr:street":"Rickmansworth Rd",
    "iso:country":"GB",
    "sg:address":"Rickmansworth Rd, Chorleywood",
    "sg:city":"Rickmansworth",
    "sg:classifiers":[
        {
            "category":"Health Services",
            "subcategory":"Nursing And Care Facility",
            "type":"Services"
        }
    ],
    "sg:phone":"+44 1923 283111",
    "sg:postcode":"WD3 5BY",
    "sg:province":"Hertfordshire",
    "sg:tags":[
        "home"
    ],
    "wof:name":"Chorleywood Lodge",
    "wof:placetype":"venue"
},
  "geometry": {"coordinates":[-0.521474,51.654804],"type":"Point"}
}