{
  "type": "Feature",
  "properties": {
    "iso:country":"GB",
    "sg:address":"2 The Crescent, Speke",
    "sg:city":"Liverpool",
    "sg:classifiers":[
        {
            "category":"Shopping",
            "subcategory":"Discount & Variety Stores",
            "type":"Retail Goods"
        }
    ],
    "sg:postcode":"L24 3TB",
    "sg:province":"Merseyside",
    "sg:tags":[
        "centre"
    ],
    "wof:name":"Holly's Bargain Store",
    "wof:placetype":"venue"
},
  "geometry": {"coordinates":[-2.85717,53.346031],"type":"Point"}
}