{
  "type": "Feature",
  "properties": {
    "iso:country":"GB",
    "sg:address":"Metcalfe House, North Rd",
    "sg:city":"Durham",
    "sg:classifiers":[
        {
            "category":"Building & Trades",
            "subcategory":"Construction",
            "type":"Services"
        }
    ],
    "sg:phone":"+44 191 386 9517",
    "sg:postcode":"DH1 4UE",
    "sg:province":"Durham",
    "sg:tags":[
        "window",
        "replacement"
    ],
    "wof:name":"Anglian Home Improvements",
    "wof:placetype":"venue"
},
  "geometry": {"coordinates":[-1.583869,54.778557],"type":"Point"}
}