{
  "type": "Feature",
  "properties": {
    "addr:full":"108 Lawnswood Road Stourbridge Staffordshire DY8 5NA",
    "addr:housenumber":"108",
    "addr:postcode":"dy8 5na",
    "addr:street":"Lawnswood Road",
    "iso:country":"GB",
    "sg:address":"108 Lawnswood Road",
    "sg:city":"Stourbridge",
    "sg:classifiers":[
        {
            "category":"Professional",
            "type":"Services"
        }
    ],
    "sg:phone":"+44 1384 297497",
    "sg:postcode":"DY8 5NA",
    "sg:province":"Staffordshire",
    "sg:tags":[
        "caterer"
    ],
    "wof:name":"Mrs Bridges",
    "wof:placetype":"venue"
},
  "geometry": {"coordinates":[-2.174585,52.48262],"type":"Point"}
}