{
  "type": "Feature",
  "properties": {
    "addr:full":"29 St Georges Walk Croydon Surrey CR0 1YL",
    "addr:housenumber":"29",
    "addr:postcode":"cr0 1yl",
    "addr:street":"St Georges Walk",
    "iso:country":"GB",
    "sg:address":"29 St Georges Walk",
    "sg:city":"Croydon",
    "sg:classifiers":[
        {
            "category":"Shopping",
            "subcategory":"Discount & Variety Stores",
            "type":"Retail Goods"
        }
    ],
    "sg:phone":"+44 20 8686 0290",
    "sg:postcode":"CR0 1YL",
    "sg:province":"Surrey",
    "sg:tags":[
        "centre"
    ],
    "wof:name":"Whitecross Trade Sales",
    "wof:placetype":"venue"
},
  "geometry": {"coordinates":[-0.098341,51.372532],"type":"Point"}
}