{
  "type": "Feature",
  "properties": {
    "addr:full":"10 Mount Pleasant, Emley Huddersfield South Yorkshire HD8 9RY",
    "addr:housenumber":"10",
    "addr:postcode":"hd8 9ry",
    "addr:street":"Mount Pleasant",
    "iso:country":"GB",
    "sg:address":"10 Mount Pleasant, Emley",
    "sg:city":"Huddersfield",
    "sg:classifiers":[
        {
            "category":"Building & Trades",
            "subcategory":"Construction",
            "type":"Services"
        }
    ],
    "sg:phone":"+44 1924 840200",
    "sg:postcode":"HD8 9RY",
    "sg:province":"South Yorkshire",
    "sg:tags":[
        "roofing",
        "contracting"
    ],
    "wof:name":"COLIN HEPPLESTONE",
    "wof:placetype":"venue"
},
  "geometry": {"coordinates":[-1.6275810003,53.6134109497],"type":"Point"}
}