{
  "type": "Feature",
  "properties": {
    "iso:country":"GB",
    "sg:address":"93 Lowesmoor",
    "sg:city":"Worcester",
    "sg:classifiers":[
        {
            "category":"Health Services",
            "subcategory":"Doctor",
            "type":"Services"
        }
    ],
    "sg:phone":"+44 1905 723441",
    "sg:postcode":"WR1 2SA",
    "sg:province":"Worcestershire",
    "sg:tags":[
        "practitioners"
    ],
    "wof:name":"Allen, D J",
    "wof:placetype":"venue"
},
  "geometry": {"coordinates":[-2.216239,52.19508],"type":"Point"}
}