{
  "type": "Feature",
  "properties": {
    "iso:country":"GB",
    "sg:address":"Regency Works, 1a Shakleton Road, Earlsdon",
    "sg:city":"Coventry",
    "sg:classifiers":[
        {
            "category":"Retail",
            "subcategory":"Repair Shop",
            "type":"Services"
        }
    ],
    "sg:phone":"+44 24 7669 1199",
    "sg:postcode":"CV5 6HT",
    "sg:province":"West Midlands",
    "sg:tags":[
        "upholstering",
        "upholsterer"
    ],
    "wof:name":"W T Parkes Upholstery",
    "wof:placetype":"venue"
},
  "geometry": {"coordinates":[-1.52851,52.406509],"type":"Point"}
}