{
  "type": "Feature",
  "properties": {
    "addr:full":"Unit 6/7 The Arena, Roman Bank Bourne Lincolnshire PE10 9LQ",
    "addr:housenumber":"unit 6 / 7",
    "addr:postcode":"pe10 9lq",
    "addr:street":"The Arena Roman Bank Bourne",
    "iso:country":"GB",
    "sg:address":"Unit 6/7 The Arena, Roman Bank",
    "sg:city":"Bourne",
    "sg:classifiers":[
        {
            "category":"Shopping",
            "subcategory":"Hobbies, Toys, & Games",
            "type":"Retail Goods"
        }
    ],
    "sg:phone":"+44 1778 393813",
    "sg:postcode":"PE10 9LQ",
    "sg:province":"Lincolnshire",
    "wof:name":"Peterborough Game Co.",
    "wof:placetype":"venue"
},
  "geometry": {"coordinates":[-0.3770880103,52.7691955566],"type":"Point"}
}