{
  "type": "Feature",
  "properties": {
    "addr:full":"Unit 4 Beeches Community Enterprise, 1 B West Bromwich West Midlands B70 6QE",
    "addr:housenumber":"unit 4;1 b",
    "addr:postcode":"b70 6qe",
    "addr:street":"West",
    "iso:country":"GB",
    "sg:address":"Unit 4 Beeches Community Enterprise, 1 B",
    "sg:city":"West Bromwich",
    "sg:classifiers":[
        {
            "category":"Education",
            "subcategory":"Special Training",
            "type":"Public Place"
        }
    ],
    "sg:postcode":"B70 6QE",
    "sg:province":"West Midlands",
    "sg:tags":[
        "product",
        "centre"
    ],
    "wof:name":"West Bromwich Afro Caribbean Resource Ce",
    "wof:placetype":"venue"
},
  "geometry": {"coordinates":[-1.990224,52.518623],"type":"Point"}
}