{
  "type": "Feature",
  "properties": {
    "iso:country":"GB",
    "sg:address":"Suite 2 Market Ho, 19-21 Market Pl",
    "sg:city":"Wokingham",
    "sg:classifiers":[
        {
            "category":"Manufacturing",
            "subcategory":"Tools & Machinery",
            "type":"Manufacturing & Wholesale Goods"
        }
    ],
    "sg:postcode":"RG40 1AP",
    "sg:province":"Berkshire",
    "sg:tags":[
        "society",
        "friendly"
    ],
    "wof:name":"Claims Assessment Service Ltd",
    "wof:placetype":"venue"
},
  "geometry": {"coordinates":[-0.834594,51.410801],"type":"Point"}
}