{
  "type": "Feature",
  "properties": {
    "addr:full":"W T A The Graiseley Centre, Pool Street Wolverhampton West Midlands WV2 4NE",
    "addr:housenumber":"a",
    "addr:postcode":"wv2 4ne",
    "addr:street":"W;The Graiseley;Pool Street",
    "iso:country":"GB",
    "sg:address":"W T A The Graiseley Centre, Pool Street",
    "sg:city":"Wolverhampton",
    "sg:classifiers":[
        {
            "category":"Education",
            "subcategory":"School",
            "type":"Public Place"
        }
    ],
    "sg:phone":"+44 1902 429591",
    "sg:postcode":"WV2 4NE",
    "sg:province":"West Midlands",
    "sg:tags":[
        "local",
        "authority"
    ],
    "wof:name":"Wolverhampton Teachers Association",
    "wof:placetype":"venue"
},
  "geometry": {"coordinates":[-2.132600069,52.5761184692],"type":"Point"}
}