{
  "type": "Feature",
  "properties": {
    "iso:country":"GB",
    "sg:address":"10 Entry Hill Gardens",
    "sg:city":"Bath",
    "sg:classifiers":[
        {
            "category":"Professional",
            "subcategory":"Secretarial Services",
            "type":"Services"
        }
    ],
    "sg:phone":"+44 1225 444862",
    "sg:postcode":"BA2 5NR",
    "sg:province":"Somerset",
    "wof:name":"Heidi Toynbee",
    "wof:placetype":"venue"
},
  "geometry": {"coordinates":[-2.365533,51.367764],"type":"Point"}
}