{
  "type": "Feature",
  "properties": {
    "addr:full":"Boghead Garage, Broad Street Denny Falkirk FK6 6EH",
    "addr:postcode":"fk6 6eh",
    "addr:street":"Broad Street",
    "iso:country":"GB",
    "sg:address":"Boghead Garage, Broad Street",
    "sg:city":"Denny",
    "sg:classifiers":[
        {
            "category":"Freight",
            "type":"Transportation"
        }
    ],
    "sg:phone":"+44 1324 823823",
    "sg:postcode":"FK6 6EH",
    "sg:province":"Falkirk",
    "sg:tags":[
        "haulage",
        "road"
    ],
    "wof:name":"James Smith (Denny) Ltd.",
    "wof:placetype":"venue"
},
  "geometry": {"coordinates":[-3.9164040089,56.0145835876],"type":"Point"}
}