{
  "type": "Feature",
  "properties": {
    "addr:full":"272 London Rd Mitcham Greater London CR4 3NB",
    "addr:housenumber":"272",
    "addr:postcode":"cr4 3nb",
    "addr:street":"London Rd",
    "iso:country":"GB",
    "sg:address":"272 London Rd",
    "sg:city":"Mitcham",
    "sg:classifiers":[
        {
            "category":"Taxi",
            "type":"Transportation"
        }
    ],
    "sg:phone":"+44 20 8648 2933",
    "sg:postcode":"CR4 3NB",
    "sg:province":"Greater London",
    "sg:tags":[
        "mini",
        "cab"
    ],
    "wof:name":"Tracks",
    "wof:placetype":"venue"
},
  "geometry": {"coordinates":[-0.164614,51.404732],"type":"Point"}
}