{
  "type": "Feature",
  "properties": {
    "addr:full":"149 North End Croydon Surrey CR0 1TN",
    "addr:housenumber":"149",
    "addr:postcode":"cr0 1tn",
    "addr:street":"North End",
    "iso:country":"GB",
    "sg:address":"149 North End",
    "sg:city":"Croydon",
    "sg:classifiers":[
        {
            "category":"Shopping",
            "subcategory":"Tobacco",
            "type":"Retail Goods"
        },
        {
            "category":"Retail",
            "subcategory":"Event Space",
            "type":"Services"
        }
    ],
    "sg:phone":"+44 20 8680 2943",
    "sg:postcode":"CR0 1TN",
    "sg:province":"Surrey",
    "sg:tags":[
        "product",
        "tobacconist",
        "sale"
    ],
    "wof:name":"Richards Tobacconists",
    "wof:placetype":"venue"
},
  "geometry": {"coordinates":[-0.1024150029,51.3773536682],"type":"Point"}
}