{
  "type": "Feature",
  "properties": {
    "addr:full":"26 Sulivan Road London Greater London SW6 3DX",
    "addr:housenumber":"26",
    "addr:postcode":"sw6 3dx",
    "addr:street":"Sulivan Road",
    "iso:country":"GB",
    "sg:address":"26 Sulivan Road",
    "sg:city":"London",
    "sg:classifiers":[
        {
            "category":"Professional",
            "type":"Services"
        }
    ],
    "sg:phone":"+44 20 7731 8399",
    "sg:postcode":"SW6 3DX",
    "sg:province":"Greater London",
    "sg:tags":[
        "interior",
        "furnishers",
        "designer"
    ],
    "wof:name":"Woodstock Designs",
    "wof:placetype":"venue"
},
  "geometry": {"coordinates":[-0.1948129982,51.4670982361],"type":"Point"}
}