{
  "type": "Feature",
  "properties": {
    "addr:full":"5 Kestral House, Mill Street Trowbridge Wiltshire BA14 8BE",
    "addr:housenumber":"5",
    "addr:postcode":"ba14 8be",
    "addr:street":"Kestral House Mill Street",
    "iso:country":"GB",
    "sg:address":"5 Kestral House, Mill Street",
    "sg:city":"Trowbridge",
    "sg:classifiers":[
        {
            "category":"Autos & Motor Vehicles",
            "subcategory":"Auto Supplies",
            "type":"Retail Goods"
        }
    ],
    "sg:phone":"+44 1225 767864",
    "sg:postcode":"BA14 8BE",
    "sg:province":"Wiltshire",
    "sg:tags":[
        "car",
        "audio"
    ],
    "wof:name":"In-Car Sounds Ltd.",
    "wof:placetype":"venue"
},
  "geometry": {"coordinates":[-2.208374,51.315342],"type":"Point"}
}