{
  "type": "Feature",
  "properties": {
    "addr:full":"59 Bank Parade Burnley Lancashire BB11 1UG",
    "addr:housenumber":"59",
    "addr:postcode":"bb11 1ug",
    "addr:street":"Bank Parade",
    "iso:country":"GB",
    "sg:address":"59 Bank Parade",
    "sg:city":"Burnley",
    "sg:classifiers":[
        {
            "category":"Professional",
            "subcategory":"Computer Services",
            "type":"Services"
        }
    ],
    "sg:postcode":"BB11 1UG",
    "sg:province":"Lancashire",
    "sg:tags":[
        "system",
        "software"
    ],
    "wof:name":"Global Tek Corporation Ltd",
    "wof:placetype":"venue"
},
  "geometry": {"coordinates":[-2.2402760983,53.7913780212],"type":"Point"}
}