{
  "type": "Feature",
  "properties": {
    "addr:full":"Crown Chambers, Bridge Street Salisbury Wiltshire SP1 2LZ",
    "addr:postcode":"sp1 2lz",
    "addr:street":"Bridge Street",
    "iso:country":"GB",
    "sg:address":"Crown Chambers, Bridge Street",
    "sg:city":"Salisbury",
    "sg:classifiers":[
        {
            "category":"Professional",
            "subcategory":"Accounting & Tax Preparation",
            "type":"Services"
        }
    ],
    "sg:phone":"+44 1722 327801",
    "sg:postcode":"SP1 2LZ",
    "sg:province":"Wiltshire",
    "sg:tags":[
        "accountant"
    ],
    "wof:name":"Fletcher & Partners",
    "wof:placetype":"venue"
},
  "geometry": {"coordinates":[-1.798874,51.067509],"type":"Point"}
}