{
  "type": "Feature",
  "properties": {
    "addr:full":"31 Sandells Ave Ashford Greater London TW15 1AL",
    "addr:housenumber":"31",
    "addr:postcode":"tw15 1al",
    "addr:street":"Sandells Ave",
    "iso:country":"GB",
    "sg:address":"31 Sandells Ave",
    "sg:city":"Ashford",
    "sg:classifiers":[
        {
            "category":"Professional",
            "subcategory":"Business Services",
            "type":"Services"
        }
    ],
    "sg:postcode":"TW15 1AL",
    "sg:province":"Greater London",
    "sg:tags":[
        "food",
        "import",
        "export",
        "agent"
    ],
    "wof:name":"Bush Tucker Ltd",
    "wof:placetype":"venue"
},
  "geometry": {"coordinates":[-0.442443,51.431278],"type":"Point"}
}