{
  "type": "Feature",
  "properties": {
    "iso:country":"GB",
    "sg:address":"19 Trinity Walk",
    "sg:city":"Nuneaton",
    "sg:classifiers":[
        {
            "category":"Professional",
            "subcategory":"Printing & Photocopies",
            "type":"Services"
        }
    ],
    "sg:postcode":"CV11 4PH",
    "sg:province":"Leicestershire",
    "sg:tags":[
        "embroiderer"
    ],
    "wof:name":"Eastboro Trading",
    "wof:placetype":"venue"
},
  "geometry": {"coordinates":[-1.454837,52.515892],"type":"Point"}
}