{
  "type": "Feature",
  "properties": {
    "iso:country":"GB",
    "sg:address":"Tanhouse Farm, Tanhouse Lane, Yate",
    "sg:city":"Bristol",
    "sg:classifiers":[
        {
            "category":"Farming",
            "subcategory":"Livestock Farm",
            "type":"Manufacturing & Wholesale Goods"
        }
    ],
    "sg:phone":"+44 1454 228280",
    "sg:postcode":"BS37 7QL",
    "sg:province":"Gloucestershire",
    "sg:tags":[
        "others"
    ],
    "wof:name":"A J C James & Sons",
    "wof:placetype":"venue"
},
  "geometry": {"coordinates":[-2.4187,51.565071],"type":"Point"}
}