{
  "type": "Feature",
  "properties": {
    "addr:full":"Unit 59d South Nelson Indstl Est, South Nelson Rd Cramlington Northumberland NE23 1WF",
    "addr:housenumber":"59d",
    "addr:postcode":"ne23 1wf",
    "addr:street":"South Nelson Indstl Est South Nelson Rd;Northumberland",
    "iso:country":"GB",
    "sg:address":"Unit 59d South Nelson Indstl Est, South Nelson Rd",
    "sg:city":"Cramlington",
    "sg:classifiers":[
        {
            "category":"Home & Garden",
            "subcategory":"Home Furnishings",
            "type":"Retail Goods"
        }
    ],
    "sg:postcode":"NE23 1WF",
    "sg:province":"Northumberland",
    "sg:tags":[
        "furnishers",
        "planner",
        "kitchen"
    ],
    "wof:name":"Postins,Thomas,",
    "wof:placetype":"venue"
},
  "geometry": {"coordinates":[-1.588704,55.087231],"type":"Point"}
}