{
  "type": "Feature",
  "properties": {
    "addr:full":"The Grange Club, Portgower Pl Edinburgh City of Edinburgh EH4 1HQ",
    "addr:postcode":"eh4 1hq",
    "addr:street":"Portgower Pl",
    "iso:country":"GB",
    "sg:address":"The Grange Club, Portgower Pl",
    "sg:city":"Edinburgh",
    "sg:classifiers":[
        {
            "category":"Professional",
            "type":"Services"
        }
    ],
    "sg:phone":"+44 131 315 2265",
    "sg:postcode":"EH4 1HQ",
    "sg:province":"City of Edinburgh",
    "sg:tags":[
        "caterer"
    ],
    "wof:name":"Tuck In Outside Catering",
    "wof:placetype":"venue"
},
  "geometry": {"coordinates":[-3.2142899036,55.9597091675],"type":"Point"}
}