{
  "type": "Feature",
  "properties": {
    "addr:full":"Queensborough House, 2 Claremont Road Surbiton Surrey KT6 4QU",
    "addr:housenumber":"2",
    "addr:postcode":"kt6 4qu",
    "addr:street":"Claremont Road",
    "iso:country":"GB",
    "sg:address":"Queensborough House, 2 Claremont Road",
    "sg:city":"Surbiton",
    "sg:classifiers":[
        {
            "category":"Professional",
            "subcategory":"Management & Consulting",
            "type":"Services"
        }
    ],
    "sg:postcode":"KT6 4QU",
    "sg:province":"Surrey",
    "sg:tags":[
        "consultant",
        "business"
    ],
    "wof:name":"Virtua International Ltd",
    "wof:placetype":"venue"
},
  "geometry": {"coordinates":[-0.304197,51.393353],"type":"Point"}
}