{
  "type": "Feature",
  "properties": {
    "addr:full":"Housty Farm, Catton Hexham Northumberland NE47 9QB",
    "addr:postcode":"ne47 9qb",
    "addr:street":"Northumberland",
    "iso:country":"GB",
    "sg:address":"Housty Farm, Catton",
    "sg:city":"Hexham",
    "sg:classifiers":[
        {
            "category":"Farming",
            "subcategory":"Farm",
            "type":"Manufacturing & Wholesale Goods"
        }
    ],
    "sg:postcode":"NE47 9QB",
    "sg:province":"Northumberland",
    "sg:tags":[
        "mixed",
        "crop"
    ],
    "wof:name":"W H & J D Sparke",
    "wof:placetype":"venue"
},
  "geometry": {"coordinates":[-2.269684,54.915001],"type":"Point"}
}