{
  "type": "Feature",
  "properties": {
    "iso:country":"GB",
    "sg:address":"4 Newcastle Ho, Barkerend Rd",
    "sg:city":"Bradford",
    "sg:classifiers":[
        {
            "category":"Organizations",
            "subcategory":"Community Association",
            "type":"Services"
        }
    ],
    "sg:phone":"+44 1274 724212",
    "sg:postcode":"BD3 9AD",
    "sg:province":"West Yorkshire",
    "sg:tags":[
        "relation",
        "public"
    ],
    "wof:name":"Tempest Public Relations",
    "wof:placetype":"venue"
},
  "geometry": {"coordinates":[-1.73519,53.79422],"type":"Point"}
}