{
  "type": "Feature",
  "properties": {
    "iso:country":"GB",
    "sg:address":"Westfield Lane",
    "sg:city":"Mansfield",
    "sg:classifiers":[
        {
            "category":"Health Services",
            "subcategory":"Clinic",
            "type":"Services"
        }
    ],
    "sg:phone":"+44 1623 626895",
    "sg:postcode":"NG19 6HF",
    "sg:province":"Derbyshire",
    "sg:tags":[
        "private"
    ],
    "wof:name":"Abbott Rd Day Centre",
    "wof:placetype":"venue"
},
  "geometry": {"coordinates":[-1.2271640301,53.1536750793],"type":"Point"}
}