{
  "type": "Feature",
  "properties": {
    "addr:full":"Livingstone Road Poole Dorset BH12 3DX",
    "addr:postcode":"bh12 3dx",
    "addr:street":"Livingstone Road",
    "iso:country":"GB",
    "sg:address":"Livingstone Road",
    "sg:city":"Poole",
    "sg:classifiers":[
        {
            "category":"Education",
            "subcategory":"School",
            "type":"Public Place"
        }
    ],
    "sg:phone":"+44 1202 747966",
    "sg:postcode":"BH12 3DX",
    "sg:province":"Dorset",
    "sg:tags":[
        "local",
        "authority"
    ],
    "wof:name":"Branksome Heath Middle School",
    "wof:placetype":"venue"
},
  "geometry": {"coordinates":[-1.946104,50.735065],"type":"Point"}
}