{
  "type": "Feature",
  "properties": {
    "addr:full":"Whalley Bank Trading Est, Harrison St Blackburn Lancashire BB2 1NR",
    "addr:postcode":"bb2 1nr",
    "addr:street":"Whalley;Harrison St",
    "iso:country":"GB",
    "sg:address":"Whalley Bank Trading Est, Harrison St",
    "sg:city":"Blackburn",
    "sg:classifiers":[
        {
            "category":"Manufacturing",
            "subcategory":"Motor Vehicles & Parts",
            "type":"Manufacturing & Wholesale Goods"
        }
    ],
    "sg:phone":"+44 1254 662631",
    "sg:postcode":"BB2 1NR",
    "sg:province":"Lancashire",
    "sg:tags":[
        "bearing"
    ],
    "wof:name":"Bearing Power Ltd",
    "wof:placetype":"venue"
},
  "geometry": {"coordinates":[-2.490584,53.744656],"type":"Point"}
}