{
  "type": "Feature",
  "properties": {
    "addr:full":"74 Waldrons Moor, Kings Heath Birmingham West Midlands B14 6RT",
    "addr:housenumber":"74",
    "addr:postcode":"b14 6rt",
    "addr:street":"Waldrons Moor;Heath",
    "iso:country":"GB",
    "sg:address":"74 Waldrons Moor, Kings Heath",
    "sg:city":"Birmingham",
    "sg:classifiers":[
        {
            "category":"Retail",
            "subcategory":"Laundry & Dry Cleaning",
            "type":"Services"
        }
    ],
    "sg:phone":"+44 121 624 2790",
    "sg:postcode":"B14 6RT",
    "sg:province":"West Midlands",
    "sg:tags":[
        "home",
        "ironing"
    ],
    "wof:name":"Ironing Service",
    "wof:placetype":"venue"
},
  "geometry": {"coordinates":[-1.9081070423,52.4223175049],"type":"Point"}
}