{
  "type": "Feature",
  "properties": {
    "iso:country":"GB",
    "sg:address":"29 Lockhart Street, Stonehouse",
    "sg:city":"Larkhall",
    "sg:classifiers":[
        {
            "category":"Taxi",
            "type":"Transportation"
        },
        {
            "category":"Military Area",
            "subcategory":"Air Force Base",
            "type":"Public Place"
        }
    ],
    "sg:phone":"+44 1698 791337",
    "sg:postcode":"ML9 3LX",
    "sg:province":"South Lanarkshire",
    "sg:tags":[
        "hire",
        "private"
    ],
    "wof:name":"Kay Cars",
    "wof:placetype":"venue"
},
  "geometry": {"coordinates":[-3.976361,55.70142],"type":"Point"}
}