{
  "type": "Feature",
  "properties": {
    "iso:country":"GB",
    "sg:address":"62a Station Road, Burgh Le Marsh",
    "sg:city":"Skegness",
    "sg:classifiers":[
        {
            "category":"Professional",
            "subcategory":"Engineering",
            "type":"Services"
        },
        {
            "category":"Building & Trades",
            "subcategory":"Electrical",
            "type":"Services"
        }
    ],
    "sg:postcode":"PE24 5EP",
    "sg:province":"Lincolnshire",
    "sg:tags":[
        "engineer",
        "electrician",
        "contractor"
    ],
    "wof:name":"Derek Butcher",
    "wof:placetype":"venue"
},
  "geometry": {"coordinates":[0.230554,53.16494],"type":"Point"}
}