{
  "type": "Feature",
  "properties": {
    "iso:country":"GB",
    "sg:address":"47 High Street",
    "sg:city":"Skipton",
    "sg:classifiers":[
        {
            "category":"Autos & Motor Vehicles",
            "subcategory":"Auto Supplies",
            "type":"Retail Goods"
        },
        {
            "category":"Shopping",
            "type":"Retail Goods"
        }
    ],
    "sg:phone":"+44 1756 799753",
    "sg:postcode":"BD23 1DT",
    "sg:province":"Lancashire",
    "sg:tags":[
        "car",
        "part",
        "accessory"
    ],
    "wof:name":"Motor World Ltd",
    "wof:placetype":"venue"
},
  "geometry": {"coordinates":[-2.0163290501,53.9625015259],"type":"Point"}
}