{
  "type": "Feature",
  "properties": {
    "iso:country":"GB",
    "sg:address":"The Old Steamer, 3 Bedford Road",
    "sg:city":"Milton Keynes",
    "sg:classifiers":[
        {
            "category":"Building & Trades",
            "subcategory":"Plumbing",
            "type":"Services"
        }
    ],
    "sg:phone":"+44 1908 585182",
    "sg:postcode":"MK17 8DQ",
    "sg:province":"Bedfordshire",
    "sg:tags":[
        "plumber",
        "heating"
    ],
    "wof:name":"Ian Daniell Plumbing Contractors",
    "wof:placetype":"venue"
},
  "geometry": {"coordinates":[-0.727749,52.005856],"type":"Point"}
}