{
  "type": "Feature",
  "properties": {
    "iso:country":"GB",
    "sg:address":"114 Wood St",
    "sg:city":"Stoke-on-trent",
    "sg:classifiers":[
        {
            "category":"Shopping",
            "subcategory":"News",
            "type":"Retail Goods"
        }
    ],
    "sg:postcode":"ST3 1DH",
    "sg:province":"Staffordshire",
    "sg:tags":[
        "newsagent"
    ],
    "wof:name":"Wood Street News",
    "wof:placetype":"venue"
},
  "geometry": {"coordinates":[-2.1305658817,52.9926338196],"type":"Point"}
}