{
  "type": "Feature",
  "properties": {
    "addr:full":"Bryn Eithin, Penmachno Betws-y-coed Conwy LL24 0PR",
    "addr:postcode":"ll24 0pr",
    "addr:street":"Bryn;Penmachno",
    "iso:country":"GB",
    "sg:address":"Bryn Eithin, Penmachno",
    "sg:city":"Betws-y-coed",
    "sg:classifiers":[
        {
            "category":"Farming",
            "subcategory":"Livestock Farm",
            "type":"Manufacturing & Wholesale Goods"
        },
        {
            "category":"Farming",
            "subcategory":"Farm",
            "type":"Manufacturing & Wholesale Goods"
        }
    ],
    "sg:phone":"+44 1690 760275",
    "sg:postcode":"LL24 0PR",
    "sg:province":"Conwy",
    "sg:tags":[
        "mixed",
        "others"
    ],
    "wof:name":"G JONES",
    "wof:placetype":"venue"
},
  "geometry": {"coordinates":[-3.8023290634,53.0918197632],"type":"Point"}
}