{
  "type": "Feature",
  "properties": {
    "iso:country":"GB",
    "sg:address":"47 Church Street",
    "sg:city":"Oswestry",
    "sg:classifiers":[
        {
            "category":"Bars & Pubs",
            "type":"Food & Drink"
        }
    ],
    "sg:phone":"+44 1691 652304",
    "sg:postcode":"SY11 2SZ",
    "sg:province":"Shropshire",
    "sg:tags":[
        "pubs",
        "inn"
    ],
    "wof:name":"The Oak Inn",
    "wof:placetype":"venue"
},
  "geometry": {"coordinates":[-3.0569748878,52.857334137],"type":"Point"}
}