{
  "type": "Feature",
  "properties": {
    "iso:country":"GB",
    "sg:address":"Holme House Cottage, Radcliffe Rd, Holme Pierrepont",
    "sg:city":"Nottingham",
    "sg:classifiers":[
        {
            "category":"Banks & Credit Unions",
            "subcategory":"Financial Services",
            "type":"Services"
        }
    ],
    "sg:phone":"+44 115 933 2664",
    "sg:postcode":"NG12 2LT",
    "sg:province":"Nottinghamshire",
    "sg:tags":[
        "consultant"
    ],
    "wof:name":"Credit Connect UK",
    "wof:placetype":"venue"
},
  "geometry": {"coordinates":[-1.064099,52.945923],"type":"Point"}
}