{
  "type": "Feature",
  "properties": {
    "addr:full":"Oak Park East Rd Sleaford Lincolnshire NG34 7EQ",
    "addr:postcode":"ng34 7eq",
    "addr:street":"Park East Rd",
    "iso:country":"GB",
    "sg:address":"Oak Park East Rd",
    "sg:city":"Sleaford",
    "sg:classifiers":[
        {
            "category":"Professional",
            "subcategory":"Engineering",
            "type":"Services"
        }
    ],
    "sg:phone":"+44 1529 413117",
    "sg:postcode":"NG34 7EQ",
    "sg:province":"Lincolnshire",
    "sg:tags":[
        "contractor",
        "electrical",
        "engineer"
    ],
    "wof:name":"Hyder Infrastructure Services Ltd",
    "wof:placetype":"venue"
},
  "geometry": {"coordinates":[-0.411869,52.994587],"type":"Point"}
}