{
  "type": "Feature",
  "properties": {
    "addr:full":"Frimley Rd Camberley Berkshire GU15 2QB",
    "addr:postcode":"gu15 2qb",
    "addr:street":"Frimley Rd",
    "iso:country":"GB",
    "sg:address":"Frimley Rd",
    "sg:city":"Camberley",
    "sg:classifiers":[
        {
            "category":"Place Of Worship",
            "type":"Public Place"
        }
    ],
    "sg:phone":"+44 1276 61512",
    "sg:postcode":"GU15 2QB",
    "sg:province":"Berkshire",
    "wof:name":"Camberley Baptist Church",
    "wof:placetype":"venue"
},
  "geometry": {"coordinates":[-0.755509,51.328735],"type":"Point"}
}