{
  "type": "Feature",
  "properties": {
    "addr:full":"221 Chapeltown Road Leeds West Yorkshire LS7 3DX",
    "addr:housenumber":"221",
    "addr:postcode":"ls7 3dx",
    "addr:street":"Chapeltown Road",
    "iso:country":"GB",
    "sg:address":"221 Chapeltown Road",
    "sg:city":"Leeds",
    "sg:classifiers":[
        {
            "category":"Professional",
            "subcategory":"Lawyer & Legal Services",
            "type":"Services"
        }
    ],
    "sg:postcode":"LS7 3DX",
    "sg:province":"West Yorkshire",
    "sg:tags":[
        "solicitor"
    ],
    "wof:name":"Harrison Bundey & Co",
    "wof:placetype":"venue"
},
  "geometry": {"coordinates":[-1.531869,53.81625],"type":"Point"}
}