{
  "type": "Feature",
  "properties": {
    "iso:country":"GB",
    "sg:address":"1 Blackness Rd",
    "sg:city":"Linlithgow",
    "sg:classifiers":[
        {
            "category":"Sports & Exercise",
            "subcategory":"Tennis Court",
            "type":"Entertainment"
        }
    ],
    "sg:phone":"+44 1506 844802",
    "sg:postcode":"EH49 7HZ",
    "sg:province":"Falkirk",
    "sg:tags":[
        "school",
        "leisure"
    ],
    "wof:name":"Low Port Outdoor Education Centre",
    "wof:placetype":"venue"
},
  "geometry": {"coordinates":[-3.5962290764,55.9770507812],"type":"Point"}
}