{
  "type": "Feature",
  "properties": {
    "iso:country":"GB",
    "sg:address":"38 Anderson Close",
    "sg:city":"London",
    "sg:classifiers":[
        {
            "category":"Professional",
            "subcategory":"Engineering",
            "type":"Services"
        }
    ],
    "sg:postcode":"W3 6YJ",
    "sg:province":"Greater London",
    "sg:tags":[
        "engineer",
        "mechanical"
    ],
    "wof:name":"Jackal Developments Ltd",
    "wof:placetype":"venue"
},
  "geometry": {"coordinates":[-0.259591,51.517006],"type":"Point"}
}