{
  "type": "Feature",
  "properties": {
    "addr:full":"183 Liverpool Road North, Maghull Liverpool Lancashire L31 2HH",
    "addr:housenumber":"183",
    "addr:postcode":"l31 2hh",
    "addr:street":"Liverpool Road North",
    "iso:country":"GB",
    "sg:address":"183 Liverpool Road North, Maghull",
    "sg:city":"Liverpool",
    "sg:classifiers":[
        {
            "category":"Shopping",
            "subcategory":"Clothing, Apparel, & Fashions",
            "type":"Retail Goods"
        }
    ],
    "sg:phone":"+44 151 531 8899",
    "sg:postcode":"L31 2HH",
    "sg:province":"Lancashire",
    "sg:tags":[
        "shop"
    ],
    "wof:name":"Beaumonde",
    "wof:placetype":"venue"
},
  "geometry": {"coordinates":[-2.935689,53.528107],"type":"Point"}
}