{
  "type": "Feature",
  "properties": {
    "addr:full":"48 Pleasant Road Southend-on-sea Essex SS1 2HJ",
    "addr:housenumber":"48",
    "addr:postcode":"ss1 2hj",
    "addr:street":"Pleasant Road",
    "iso:country":"GB",
    "sg:address":"48 Pleasant Road",
    "sg:city":"Southend-on-sea",
    "sg:classifiers":[
        {
            "category":"Building & Trades",
            "subcategory":"Construction",
            "type":"Services"
        }
    ],
    "sg:phone":"+44 1702 613427",
    "sg:postcode":"SS1 2HJ",
    "sg:province":"Essex",
    "sg:tags":[
        "builder",
        "joiner",
        "carpenter"
    ],
    "wof:name":"Southend Construction",
    "wof:placetype":"venue"
},
  "geometry": {"coordinates":[0.722062,51.5345],"type":"Point"}
}