{
  "type": "Feature",
  "properties": {
    "iso:country":"GB",
    "sg:address":"Brunswick Industrial Estate, Brassey Street",
    "sg:city":"Halifax",
    "sg:classifiers":[
        {
            "category":"Manufacturing",
            "subcategory":"Wood Products",
            "type":"Manufacturing & Wholesale Goods"
        }
    ],
    "sg:phone":"+44 1422 349555",
    "sg:postcode":"HX1 2TQ",
    "sg:province":"West Yorkshire",
    "sg:tags":[
        "packaging",
        "crate",
        "pallets"
    ],
    "wof:name":"Lyncroft Presentation Packaging Ltd.",
    "wof:placetype":"venue"
},
  "geometry": {"coordinates":[-1.8622239828,53.7212333679],"type":"Point"}
}