{
  "type": "Feature",
  "properties": {
    "addr:full":"Unit C1 & C2, Canklow Meadows Industrial Estate, West Bawtry Road Rotherham South Yorkshire S60 2XL",
    "addr:housenumber":"estate",
    "addr:postcode":"s60 2xl",
    "addr:street":"Industrial;West Bawtry Road",
    "iso:country":"GB",
    "sg:address":"Unit C1 & C2, Canklow Meadows Industrial Estate, West Bawtry Road",
    "sg:city":"Rotherham",
    "sg:classifiers":[
        {
            "category":"Recreation",
            "subcategory":"Fishing",
            "type":"Entertainment"
        }
    ],
    "sg:phone":"+44 1709 370990",
    "sg:postcode":"S60 2XL",
    "sg:province":"South Yorkshire",
    "sg:tags":[
        "angling"
    ],
    "wof:name":"Nutrabaits Ltd.",
    "wof:placetype":"venue"
},
  "geometry": {"coordinates":[-1.3574399948,53.4064407349],"type":"Point"}
}