{
  "type": "Feature",
  "properties": {
    "addr:full":"34-36 King Street Ulverston Cumbria LA12 7DZ",
    "addr:housenumber":"34-36",
    "addr:postcode":"la12 7dz",
    "addr:street":"King Street",
    "iso:country":"GB",
    "sg:address":"34-36 King Street",
    "sg:city":"Ulverston",
    "sg:classifiers":[
        {
            "category":"Shopping",
            "subcategory":"News",
            "type":"Retail Goods"
        }
    ],
    "sg:phone":"+44 1229 582020",
    "sg:postcode":"LA12 7DZ",
    "sg:province":"Cumbria",
    "sg:tags":[
        "newsagent"
    ],
    "wof:name":"Greatorex Newsagents",
    "wof:placetype":"venue"
},
  "geometry": {"coordinates":[-3.0959830284,54.1969337463],"type":"Point"}
}