{
  "type": "Feature",
  "properties": {
    "iso:country":"GB",
    "sg:address":"4 Briars Close, Killamarsh",
    "sg:city":"Sheffield",
    "sg:classifiers":[
        {
            "category":"Home & Garden",
            "subcategory":"Building Materials",
            "type":"Retail Goods"
        }
    ],
    "sg:postcode":"S21 1EP",
    "sg:province":"Derbyshire",
    "sg:tags":[
        "insulation",
        "installers"
    ],
    "wof:name":"J & J Crump & Son Ltd.",
    "wof:placetype":"venue"
},
  "geometry": {"coordinates":[-1.313352,53.31707],"type":"Point"}
}