{
  "type": "Feature",
  "properties": {
    "addr:full":"37 Fore Street Wellington Devon TA21 8AG",
    "addr:housenumber":"37",
    "addr:postcode":"ta21 8ag",
    "addr:street":"Fore Street",
    "iso:country":"GB",
    "sg:address":"37 Fore Street",
    "sg:city":"Wellington",
    "sg:classifiers":[
        {
            "category":"Health Services",
            "subcategory":"Clinic",
            "type":"Services"
        }
    ],
    "sg:phone":"+44 1823 660515",
    "sg:postcode":"TA21 8AG",
    "sg:province":"Devon",
    "sg:tags":[
        "private"
    ],
    "wof:name":"Cleo's",
    "wof:placetype":"venue"
},
  "geometry": {"coordinates":[-3.2297410965,50.9772186279],"type":"Point"}
}