{
  "type": "Feature",
  "properties": {
    "addr:full":"Colman Ho, King St Maidstone Kent ME14 1DH",
    "addr:postcode":"me14 1dh",
    "addr:street":"St",
    "iso:country":"GB",
    "sg:address":"Colman Ho, King St",
    "sg:city":"Maidstone",
    "sg:classifiers":[
        {
            "category":"Building & Trades",
            "subcategory":"Construction",
            "type":"Services"
        }
    ],
    "sg:phone":"+44 1622 690772",
    "sg:postcode":"ME14 1DH",
    "sg:province":"Kent",
    "sg:tags":[
        "builder"
    ],
    "wof:name":"Haden Young Ltd",
    "wof:placetype":"venue"
},
  "geometry": {"coordinates":[0.525085,51.2738],"type":"Point"}
}