{
  "type": "Feature",
  "properties": {
    "addr:full":"Spital Farmhouse, Grimsbury Banbury Oxfordshire OX16 4RZ",
    "addr:postcode":"ox16 4rz",
    "addr:street":"Grimsbury",
    "iso:country":"GB",
    "sg:address":"Spital Farmhouse, Grimsbury",
    "sg:city":"Banbury",
    "sg:classifiers":[
        {
            "category":"Building & Trades",
            "subcategory":"Construction",
            "type":"Services"
        }
    ],
    "sg:phone":"+44 1295 252565",
    "sg:postcode":"OX16 4RZ",
    "sg:province":"Oxfordshire",
    "sg:tags":[
        "roofing"
    ],
    "wof:name":"Attleys Roofing Ltd.",
    "wof:placetype":"venue"
},
  "geometry": {"coordinates":[-1.3400280476,52.0611114502],"type":"Point"}
}