{
  "type": "Feature",
  "properties": {
    "addr:full":"321, Walsgrave Coventry Warwickshire CV2 2AP",
    "addr:housenumber":"321",
    "addr:postcode":"cv2 2ap",
    "addr:street":"Walsgrave",
    "iso:country":"GB",
    "sg:address":"321, Walsgrave",
    "sg:city":"Coventry",
    "sg:classifiers":[
        {
            "category":"Building & Trades",
            "subcategory":"Plumbing",
            "type":"Services"
        }
    ],
    "sg:postcode":"CV2 2AP",
    "sg:province":"Warwickshire",
    "sg:tags":[
        "drain",
        "clearance",
        "sewer"
    ],
    "wof:name":"Coventry Blockages",
    "wof:placetype":"venue"
},
  "geometry": {"coordinates":[-1.478597,52.411339],"type":"Point"}
}