{
  "type": "Feature",
  "properties": {
    "iso:country":"GB",
    "sg:address":"7 Richmond Hill",
    "sg:city":"Truro",
    "sg:classifiers":[
        {
            "category":"Bars & Pubs",
            "type":"Food & Drink"
        }
    ],
    "sg:phone":"+44 1872 278941",
    "sg:postcode":"TR1 3HS",
    "sg:province":"Cornwall",
    "sg:tags":[
        "pubs",
        "inn"
    ],
    "wof:name":"The Admiral Boscawen",
    "wof:placetype":"venue"
},
  "geometry": {"coordinates":[-5.059247,50.263023],"type":"Point"}
}