{
  "type": "Feature",
  "properties": {
    "addr:full":"90 Dunmow Road Bishops Stortford Essex CM23 5HN",
    "addr:housenumber":"90",
    "addr:postcode":"cm23 5hn",
    "addr:street":"Dunmow Road",
    "iso:country":"GB",
    "sg:address":"90 Dunmow Road",
    "sg:city":"Bishops Stortford",
    "sg:classifiers":[
        {
            "category":"Building & Trades",
            "subcategory":"Construction",
            "type":"Services"
        }
    ],
    "sg:postcode":"CM23 5HN",
    "sg:province":"Essex",
    "sg:tags":[
        "contractor",
        "paving",
        "driveway"
    ],
    "wof:name":"M & M Services",
    "wof:placetype":"venue"
},
  "geometry": {"coordinates":[0.1714340001,51.869594574],"type":"Point"}
}