{
  "type": "Feature",
  "properties": {
    "addr:full":"Reckleford Yeovil Somerset BA21 4EH",
    "addr:postcode":"ba21 4eh",
    "iso:country":"GB",
    "sg:address":"Reckleford",
    "sg:city":"Yeovil",
    "sg:classifiers":[
        {
            "category":"Autos & Motor Vehicles",
            "subcategory":"Fuel & Gas Station",
            "type":"Retail Goods"
        },
        {
            "category":"Autos & Motor Vehicles",
            "subcategory":"Automobile Sales",
            "type":"Retail Goods"
        }
    ],
    "sg:phone":"+44 1935 472381",
    "sg:postcode":"BA21 4EH",
    "sg:province":"Somerset",
    "sg:tags":[
        "hr",
        "petrol",
        "car"
    ],
    "wof:name":"HELSTON GARAGES LTD",
    "wof:placetype":"venue"
},
  "geometry": {"coordinates":[-2.631484,50.944096],"type":"Point"}
}