{
  "type": "Feature",
  "properties": {
    "iso:country":"GB",
    "sg:address":"34 Collingwood Street",
    "sg:city":"Newcastle Upon Tyne",
    "sg:classifiers":[
        {
            "category":"Utilities",
            "subcategory":"Telephone",
            "type":"Services"
        }
    ],
    "sg:phone":"+44 191 245 0404",
    "sg:postcode":"NE1 1JF",
    "sg:province":"Tyne and Wear",
    "sg:tags":[
        "telecommunication"
    ],
    "wof:name":"Telephone Exchange Installation Service",
    "wof:placetype":"venue"
},
  "geometry": {"coordinates":[-1.6137080193,54.9699668884],"type":"Point"}
}