{
  "type": "Feature",
  "properties": {
    "addr:full":"Unit 39, Phoenix International Industrial Estate, Estchar West Bromwich West Midlands B70 0AY",
    "addr:housenumber":"unit 39",
    "addr:postcode":"b70 0ay",
    "iso:country":"GB",
    "sg:address":"Unit 39, Phoenix International Industrial Estate, Estchar",
    "sg:city":"West Bromwich",
    "sg:classifiers":[
        {
            "category":"Shopping",
            "subcategory":"Stationery & Office Supplies",
            "type":"Retail Goods"
        }
    ],
    "sg:phone":"+44 121 520 2471",
    "sg:postcode":"B70 0AY",
    "sg:province":"West Midlands",
    "sg:tags":[
        "printers'"
    ],
    "wof:name":"European Macsim",
    "wof:placetype":"venue"
},
  "geometry": {"coordinates":[-2.0233900547,52.524974823],"type":"Point"}
}