{
  "type": "Feature",
  "properties": {
    "addr:full":"The Blackberry Patch, Parkstone Road Alresford Hampshire SO24 0EP",
    "addr:postcode":"so24 0ep",
    "addr:street":"Parkstone Road",
    "iso:country":"GB",
    "sg:address":"The Blackberry Patch, Parkstone Road",
    "sg:city":"Alresford",
    "sg:classifiers":[
        {
            "category":"Professional",
            "subcategory":"Accounting & Tax Preparation",
            "type":"Services"
        }
    ],
    "sg:phone":"+44 1962 773177",
    "sg:postcode":"SO24 0EP",
    "sg:province":"Hampshire",
    "sg:tags":[
        "accountant"
    ],
    "wof:name":"Lowndes & Associates Ltd.",
    "wof:placetype":"venue"
},
  "geometry": {"coordinates":[-1.0741000175,51.0714302063],"type":"Point"}
}