{
  "type": "Feature",
  "properties": {
    "addr:full":"Salesbury House Hinckley Leicestershire LE10 1YG",
    "addr:postcode":"le10 1yg",
    "iso:country":"GB",
    "sg:address":"Salesbury House",
    "sg:city":"Hinckley",
    "sg:classifiers":[
        {
            "category":"Professional",
            "subcategory":"Employment Agencies",
            "type":"Services"
        }
    ],
    "sg:phone":"+44 1455 613322",
    "sg:postcode":"LE10 1YG",
    "sg:province":"Leicestershire",
    "sg:tags":[
        "consultant"
    ],
    "wof:name":"Human Factor Recruitment Ltd.",
    "wof:placetype":"venue"
},
  "geometry": {"coordinates":[-1.372754,52.542439],"type":"Point"}
}