{
  "type": "Feature",
  "properties": {
    "addr:full":"40 Farley Road, Selsdon South Croydon Surrey CR2 7ND",
    "addr:housenumber":"40",
    "addr:postcode":"cr2 7nd",
    "addr:street":"Farley Road",
    "iso:country":"GB",
    "sg:address":"40 Farley Road, Selsdon",
    "sg:city":"South Croydon",
    "sg:classifiers":[
        {
            "category":"Professional",
            "subcategory":"Business Services",
            "type":"Services"
        }
    ],
    "sg:postcode":"CR2 7ND",
    "sg:province":"Surrey",
    "sg:tags":[
        "import",
        "export",
        "agent"
    ],
    "wof:name":"A J H Export Services",
    "wof:placetype":"venue"
},
  "geometry": {"coordinates":[-0.06567,51.345722],"type":"Point"}
}