{
  "type": "Feature",
  "properties": {
    "addr:full":"St. Anthonys Dr Preston Lancashire PR2 3SQ",
    "addr:postcode":"pr2 3sq",
    "iso:country":"GB",
    "sg:address":"St. Anthonys Dr",
    "sg:city":"Preston",
    "sg:classifiers":[
        {
            "category":"Government",
            "subcategory":"City Hall",
            "type":"Public Place"
        }
    ],
    "sg:phone":"+44 1772 728863",
    "sg:postcode":"PR2 3SQ",
    "sg:province":"Lancashire",
    "wof:name":"St. Anthony's Social Centre Annexe",
    "wof:placetype":"venue"
},
  "geometry": {"coordinates":[-2.7250039577,53.7799186707],"type":"Point"}
}