{
  "type": "Feature",
  "properties": {
    "addr:full":"44 Rothbury Road London Greater London E9 5HA",
    "addr:housenumber":"44",
    "addr:postcode":"e9 5ha",
    "addr:street":"Rothbury Road",
    "iso:country":"GB",
    "sg:address":"44 Rothbury Road",
    "sg:city":"London",
    "sg:classifiers":[
        {
            "category":"Wholesale",
            "subcategory":"Construction Materials",
            "type":"Manufacturing & Wholesale Goods"
        }
    ],
    "sg:phone":"+44 20 8985 1028",
    "sg:postcode":"E9 5HA",
    "sg:province":"Greater London",
    "sg:tags":[
        "merchant",
        "stone"
    ],
    "wof:name":"A Neale & Son",
    "wof:placetype":"venue"
},
  "geometry": {"coordinates":[-0.0267789997,51.5420417786],"type":"Point"}
}