{
  "type": "Feature",
  "properties": {
    "addr:full":"22 Bryn Castell Conwy Conwy LL32 8LF",
    "addr:housenumber":"22",
    "addr:postcode":"ll32 8lf",
    "addr:street":"Bryn Castell",
    "iso:country":"GB",
    "sg:address":"22 Bryn Castell",
    "sg:city":"Conwy",
    "sg:classifiers":[
        {
            "category":"Ice Cream",
            "type":"Food & Drink"
        }
    ],
    "sg:phone":"+44 1492 592772",
    "sg:postcode":"LL32 8LF",
    "sg:province":"Conwy",
    "sg:tags":[
        "mnfr"
    ],
    "wof:name":"Vincents Ice Cream",
    "wof:placetype":"venue"
},
  "geometry": {"coordinates":[-3.8310110569,53.2777862549],"type":"Point"}
}