{
  "type": "Feature",
  "properties": {
    "iso:country":"GB",
    "sg:address":"Unit 1 Blackness Industrial Centre, Altens",
    "sg:city":"Aberdeen",
    "sg:classifiers":[
        {
            "category":"Manufacturing",
            "subcategory":"Tools & Machinery",
            "type":"Manufacturing & Wholesale Goods"
        },
        {
            "category":"Building & Trades",
            "subcategory":"Construction",
            "type":"Services"
        }
    ],
    "sg:phone":"+44 1224 872990",
    "sg:postcode":"AB12 3LH",
    "sg:province":"Aberdeen City",
    "sg:tags":[
        "equipment"
    ],
    "wof:name":"Pipe Centre",
    "wof:placetype":"venue"
},
  "geometry": {"coordinates":[-2.075509,57.110714],"type":"Point"}
}