{
  "type": "Feature",
  "properties": {
    "addr:full":"6 Priory, Old London Rd, Canwell Sutton Coldfield Staffordshire B75 5SH",
    "addr:housenumber":"6",
    "addr:postcode":"b75 5sh",
    "addr:street":"Priory Old London Rd",
    "iso:country":"GB",
    "sg:address":"6 Priory, Old London Rd, Canwell",
    "sg:city":"Sutton Coldfield",
    "sg:classifiers":[
        {
            "category":"Manufacturing",
            "subcategory":"Metals",
            "type":"Manufacturing & Wholesale Goods"
        }
    ],
    "sg:phone":"+44 121 323 3823",
    "sg:postcode":"B75 5SH",
    "sg:province":"Staffordshire",
    "sg:tags":[
        "steel",
        "mnfrs"
    ],
    "wof:name":"Marchand International Ltd",
    "wof:placetype":"venue"
},
  "geometry": {"coordinates":[-1.7938200235,52.6011581421],"type":"Point"}
}