{
  "type": "Feature",
  "properties": {
    "iso:country":"GB",
    "sg:address":"15a Kirkgate",
    "sg:city":"Thirsk",
    "sg:classifiers":[
        {
            "category":"Organizations",
            "subcategory":"Non-profit Organization",
            "type":"Services"
        }
    ],
    "sg:phone":"+44 1845 526536",
    "sg:postcode":"YO7 1PQ",
    "sg:province":"North Yorkshire",
    "sg:tags":[
        "organisation",
        "voluntary",
        "charity"
    ],
    "wof:name":"Rural Arts North Yorkshire",
    "wof:placetype":"venue"
},
  "geometry": {"coordinates":[-1.3445500135,54.2331504822],"type":"Point"}
}