{
  "type": "Feature",
  "properties": {
    "addr:full":"P O Box 48, Alderton Road Towcester Buckinghamshire NN12 7ZY",
    "addr:housenumber":"box 48",
    "addr:postcode":"nn12 7zy",
    "addr:street":"P O;Alderton Road",
    "iso:country":"GB",
    "sg:address":"P O Box 48, Alderton Road",
    "sg:city":"Towcester",
    "sg:classifiers":[
        {
            "category":"Professional",
            "subcategory":"Management & Consulting",
            "type":"Services"
        }
    ],
    "sg:phone":"+44 1327 811518",
    "sg:postcode":"NN12 7ZY",
    "sg:province":"Buckinghamshire",
    "sg:tags":[
        "marketing",
        "consultant"
    ],
    "wof:name":"Duncan Alexander & Wilmshurst",
    "wof:placetype":"venue"
},
  "geometry": {"coordinates":[-0.9198380113,52.1147651672],"type":"Point"}
}