{
  "type": "Feature",
  "properties": {
    "iso:country":"GB",
    "sg:address":"Unit 6 Barnett Lane",
    "sg:city":"Brierley Hill",
    "sg:classifiers":[
        {
            "category":"Manufacturing",
            "subcategory":"Chemicals & Compounds",
            "type":"Manufacturing & Wholesale Goods"
        }
    ],
    "sg:phone":"+44 1384 401999",
    "sg:postcode":"DY6 9PJ",
    "sg:province":"Staffordshire",
    "wof:name":"Saxon Chemicals",
    "wof:placetype":"venue"
},
  "geometry": {"coordinates":[-2.1668400764,52.4871788025],"type":"Point"}
}