{
  "type": "Feature",
  "properties": {
    "addr:full":"Banwy View, Llangyniew Welshpool Shropshire SY21 9EJ",
    "addr:postcode":"sy21 9ej",
    "addr:street":"Banwy",
    "iso:country":"GB",
    "sg:address":"Banwy View, Llangyniew",
    "sg:city":"Welshpool",
    "sg:classifiers":[
        {
            "category":"Home & Garden",
            "subcategory":"Home Furnishings",
            "type":"Retail Goods"
        }
    ],
    "sg:postcode":"SY21 9EJ",
    "sg:province":"Shropshire",
    "sg:tags":[
        "furnishers",
        "planner",
        "kitchen"
    ],
    "wof:name":"Cosy Kitchens",
    "wof:placetype":"venue"
},
  "geometry": {"coordinates":[-3.2911169529,52.6757125854],"type":"Point"}
}