{
  "type": "Feature",
  "properties": {
    "addr:full":"Unit 3c Venture Indstl Pk, Fareham Rd Gosport Hampshire PO13 0BA",
    "addr:housenumber":"unit 3c",
    "addr:postcode":"po13 0ba",
    "addr:street":"Indstl Pk Fareham Rd",
    "iso:country":"GB",
    "sg:address":"Unit 3c Venture Indstl Pk, Fareham Rd",
    "sg:city":"Gosport",
    "sg:classifiers":[
        {
            "category":"Professional",
            "subcategory":"Printing & Photocopies",
            "type":"Services"
        }
    ],
    "sg:postcode":"PO13 0BA",
    "sg:province":"Hampshire",
    "sg:tags":[
        "embroiderer"
    ],
    "wof:name":"Eagle Embroidery",
    "wof:placetype":"venue"
},
  "geometry": {"coordinates":[-1.1641099453,50.8251113892],"type":"Point"}
}