{
  "type": "Feature",
  "properties": {
    "iso:country":"GB",
    "sg:address":"Unit 4 Henley Business Park, Trident Close, Medway City Estate",
    "sg:city":"Rochester",
    "sg:classifiers":[
        {
            "category":"Manufacturing",
            "subcategory":"Paper Products",
            "type":"Manufacturing & Wholesale Goods"
        }
    ],
    "sg:phone":"+44 1634 296176",
    "sg:postcode":"ME2 4ER",
    "sg:province":"Kent",
    "sg:tags":[
        "merchant",
        "waste"
    ],
    "wof:name":"Wastaway Waste Paper Merchants Ltd.",
    "wof:placetype":"venue"
},
  "geometry": {"coordinates":[0.488783,51.39637],"type":"Point"}
}