{
  "type": "Feature",
  "properties": {
    "iso:country":"GB",
    "sg:address":"24 Winter Hey La, Horwich",
    "sg:city":"Bolton",
    "sg:classifiers":[
        {
            "category":"Real Estate",
            "subcategory":"Real Estate Agent",
            "type":"Services"
        }
    ],
    "sg:phone":"+44 1204 695111",
    "sg:postcode":"BL6 7AA",
    "sg:province":"Lancashire",
    "wof:name":"Legal & General Estate Agency",
    "wof:placetype":"venue"
},
  "geometry": {"coordinates":[-2.5469460487,53.5991973877],"type":"Point"}
}