{
  "type": "Feature",
  "properties": {
    "addr:full":"High St, Scaldwell Northampton Northamptonshire NN6 9JT",
    "addr:postcode":"nn6 9jt",
    "addr:street":"High St",
    "iso:country":"GB",
    "sg:address":"High St, Scaldwell",
    "sg:city":"Northampton",
    "sg:classifiers":[
        {
            "category":"Professional",
            "subcategory":"Business Services",
            "type":"Services"
        }
    ],
    "sg:postcode":"NN6 9JT",
    "sg:province":"Northamptonshire",
    "sg:tags":[
        "holding"
    ],
    "wof:name":"Crawshaw Robbins (Holdings) Ltd",
    "wof:placetype":"venue"
},
  "geometry": {"coordinates":[-0.902161,52.332191],"type":"Point"}
}