{
  "type": "Feature",
  "properties": {
    "iso:country":"GB",
    "sg:address":"24 High Street, Earl Shilton",
    "sg:city":"Leicester",
    "sg:classifiers":[
        {
            "category":"Retail",
            "subcategory":"Emissions Testing",
            "type":"Services"
        },
        {
            "category":"Retail",
            "subcategory":"Auto Repair",
            "type":"Services"
        }
    ],
    "sg:phone":"+44 1455 840998",
    "sg:postcode":"LE9 7DG",
    "sg:province":"Leicestershire",
    "sg:tags":[
        "modification",
        "garage",
        "mot"
    ],
    "wof:name":"Hill Top Service Station Ltd.",
    "wof:placetype":"venue"
},
  "geometry": {"coordinates":[-1.3097749949,52.5786705017],"type":"Point"}
}