{
  "type": "Feature",
  "properties": {
    "addr:full":"5-7 Grant Avenue, Roundhay Rd Ind Est Leeds West Yorkshire LS7 1QB",
    "addr:housenumber":"5-7",
    "addr:postcode":"ls7 1qb",
    "addr:street":"Grant Avenue Roundhay Rd;West",
    "iso:country":"GB",
    "sg:address":"5-7 Grant Avenue, Roundhay Rd Ind Est",
    "sg:city":"Leeds",
    "sg:classifiers":[
        {
            "category":"Wholesale",
            "subcategory":"Vending Machines",
            "type":"Manufacturing & Wholesale Goods"
        }
    ],
    "sg:phone":"+44 113 249 4598",
    "sg:postcode":"LS7 1QB",
    "sg:province":"West Yorkshire",
    "sg:tags":[
        "sale"
    ],
    "wof:name":"Vendhall Ltd",
    "wof:placetype":"venue"
},
  "geometry": {"coordinates":[-1.5283789635,53.8098945618],"type":"Point"}
}