{
  "type": "Feature",
  "properties": {
    "addr:full":"27 West Lane Liverpool Lancashire L37 7AY",
    "addr:housenumber":"27",
    "addr:postcode":"l37 7ay",
    "addr:street":"West Lane",
    "iso:country":"GB",
    "sg:address":"27 West Lane",
    "sg:city":"Liverpool",
    "sg:classifiers":[
        {
            "category":"Professional",
            "subcategory":"Accounting & Tax Preparation",
            "type":"Services"
        }
    ],
    "sg:postcode":"L37 7AY",
    "sg:province":"Lancashire",
    "sg:tags":[
        "accountant"
    ],
    "wof:name":"J Hughes & Co",
    "wof:placetype":"venue"
},
  "geometry": {"coordinates":[-3.064865,53.571365],"type":"Point"}
}