{
  "type": "Feature",
  "properties": {
    "addr:full":"1 Hyde Green Stevenage Hertfordshire SG2 9XU",
    "addr:housenumber":"1",
    "addr:postcode":"sg2 9xu",
    "addr:street":"Hyde Green",
    "iso:country":"GB",
    "sg:address":"1 Hyde Green",
    "sg:city":"Stevenage",
    "sg:classifiers":[
        {
            "category":"Health Services",
            "subcategory":"Dentist",
            "type":"Services"
        }
    ],
    "sg:phone":"+44 1438 351548",
    "sg:postcode":"SG2 9XU",
    "sg:province":"Hertfordshire",
    "wof:name":"Hydean Dental Surgery",
    "wof:placetype":"venue"
},
  "geometry": {"coordinates":[-0.173585,51.893497],"type":"Point"}
}