{
  "type": "Feature",
  "properties": {
    "iso:country":"GB",
    "sg:address":"Bangor Road",
    "sg:city":"Penmaenmawr",
    "sg:classifiers":[
        {
            "category":"Shopping",
            "subcategory":"Department Store",
            "type":"Retail Goods"
        },
        {
            "category":"Food & Beverages",
            "subcategory":"Groceries & Convenience Stores",
            "type":"Retail Goods"
        }
    ],
    "sg:phone":"+44 1492 622416",
    "sg:postcode":"LL34 6DA",
    "sg:province":"Conwy",
    "wof:name":"Spar",
    "wof:placetype":"venue"
},
  "geometry": {"coordinates":[-3.9224491119,53.2682914734],"type":"Point"}
}