{
  "type": "Feature",
  "properties": {
    "addr:full":"34 High St Clacton On Sea Essex CO15 1UQ",
    "addr:housenumber":"34",
    "addr:postcode":"co15 1uq",
    "addr:street":"High St",
    "iso:country":"GB",
    "sg:address":"34 High St",
    "sg:city":"Clacton On Sea",
    "sg:classifiers":[
        {
            "category":"Farming",
            "subcategory":"Fish & Marine Products",
            "type":"Manufacturing & Wholesale Goods"
        }
    ],
    "sg:phone":"+44 1255 423357",
    "sg:postcode":"CO15 1UQ",
    "sg:province":"Essex",
    "sg:tags":[
        "fishmonger"
    ],
    "wof:name":"Le Pecheur",
    "wof:placetype":"venue"
},
  "geometry": {"coordinates":[1.1558890343,51.7906112671],"type":"Point"}
}