{
  "type": "Feature",
  "properties": {
    "addr:full":"22-24 Suffolk Road Lowestoft Suffolk NR32 1DZ",
    "addr:housenumber":"22-24",
    "addr:postcode":"nr32 1dz",
    "addr:street":"Suffolk Road",
    "iso:country":"GB",
    "sg:address":"22-24 Suffolk Road",
    "sg:city":"Lowestoft",
    "sg:classifiers":[
        {
            "category":"Professional",
            "subcategory":"Accounting & Tax Preparation",
            "type":"Services"
        }
    ],
    "sg:phone":"+44 1502 563522",
    "sg:postcode":"NR32 1DZ",
    "sg:province":"Suffolk",
    "sg:tags":[
        "accountant"
    ],
    "wof:name":"Giles Tubbs & Co",
    "wof:placetype":"venue"
},
  "geometry": {"coordinates":[1.7525000572,52.4741401672],"type":"Point"}
}