{
  "type": "Feature",
  "properties": {
    "iso:country":"GB",
    "sg:address":"63 Friar Gate",
    "sg:city":"Derby",
    "sg:classifiers":[
        {
            "category":"Professional",
            "subcategory":"Management & Consulting",
            "type":"Services"
        }
    ],
    "sg:postcode":"DE1 1QJ",
    "sg:province":"Derbyshire",
    "sg:tags":[
        "consultant",
        "business"
    ],
    "wof:name":"Earlglen Ltd",
    "wof:placetype":"venue"
},
  "geometry": {"coordinates":[-1.489924,52.925125],"type":"Point"}
}