{
  "type": "Feature",
  "properties": {
    "addr:full":"12 Cobden Street Dalton-in-furness Cumbria LA15 8SG",
    "addr:housenumber":"12",
    "addr:postcode":"la15 8sg",
    "addr:street":"Cobden Street",
    "iso:country":"GB",
    "sg:address":"12 Cobden Street",
    "sg:city":"Dalton-in-furness",
    "sg:classifiers":[
        {
            "category":"Professional",
            "subcategory":"Art Services",
            "type":"Services"
        },
        {
            "category":"Building & Trades",
            "subcategory":"Construction",
            "type":"Services"
        }
    ],
    "sg:phone":"+44 1229 465304",
    "sg:postcode":"LA15 8SG",
    "sg:province":"Cumbria",
    "sg:tags":[
        "decorator",
        "painter"
    ],
    "wof:name":"R Williamson",
    "wof:placetype":"venue"
},
  "geometry": {"coordinates":[-3.177803,54.160244],"type":"Point"}
}