{
  "type": "Feature",
  "properties": {
    "addr:full":"New Road, Rustington Littlehampton West Sussex BN16 3RT",
    "addr:postcode":"bn16 3rt",
    "addr:street":"New Road",
    "iso:country":"GB",
    "sg:address":"New Road, Rustington",
    "sg:city":"Littlehampton",
    "sg:classifiers":[
        {
            "category":"Home & Garden",
            "subcategory":"Hardware",
            "type":"Retail Goods"
        }
    ],
    "sg:phone":"+44 1903 787779",
    "sg:postcode":"BN16 3RT",
    "sg:province":"West Sussex",
    "sg:tags":[
        "retailer",
        "diy"
    ],
    "wof:name":"Focus",
    "wof:placetype":"venue"
},
  "geometry": {"coordinates":[-0.4988279939,50.8188705444],"type":"Point"}
}