{
  "type": "Feature",
  "properties": {
    "iso:country":"GB",
    "sg:address":"Clayton Street",
    "sg:city":"Wigan",
    "sg:classifiers":[
        {
            "category":"Retail",
            "subcategory":"Funeral Services",
            "type":"Services"
        }
    ],
    "sg:phone":"+44 1942 243331",
    "sg:postcode":"WN3 4DG",
    "sg:province":"Lancashire",
    "wof:name":"Thorley Smith Ltd.",
    "wof:placetype":"venue"
},
  "geometry": {"coordinates":[-2.638543,53.544338],"type":"Point"}
}