{
  "type": "Feature",
  "properties": {
    "iso:country":"GB",
    "sg:address":"Tower Farm, Chew Hill, Chew Manga",
    "sg:city":"Bristol",
    "sg:classifiers":[
        {
            "category":"Farming",
            "subcategory":"Dairy Farm",
            "type":"Manufacturing & Wholesale Goods"
        }
    ],
    "sg:phone":"+44 1275 332548",
    "sg:postcode":"BS40 8SB",
    "sg:province":"Somerset",
    "wof:name":"Ian Cox",
    "wof:placetype":"venue"
},
  "geometry": {"coordinates":[-2.61784,51.373821],"type":"Point"}
}