{
  "type": "Feature",
  "properties": {
    "iso:country":"GB",
    "sg:address":"116 High Road",
    "sg:city":"Chigwell",
    "sg:classifiers":[
        {
            "category":"Real Estate",
            "subcategory":"Real Estate Agent",
            "type":"Services"
        }
    ],
    "sg:phone":"+44 20 8281 0123",
    "sg:postcode":"IG7 5BJ",
    "sg:province":"Essex",
    "sg:website":"http://www.lawlors.co.uk",
    "wof:name":"Lawlors Property Services",
    "wof:placetype":"venue"
},
  "geometry": {"coordinates":[0.074602,51.618095],"type":"Point"}
}