{
  "type": "Feature",
  "properties": {
    "addr:full":"341-343 Pk La Macclesfield Cheshire SK11 8JR",
    "addr:postcode":"341-343;sk11 8jr",
    "addr:street":"Pk La Macclesfield",
    "iso:country":"GB",
    "sg:address":"341-343 Pk La",
    "sg:city":"Macclesfield",
    "sg:classifiers":[
        {
            "category":"Manufacturing",
            "subcategory":"Tools & Machinery",
            "type":"Manufacturing & Wholesale Goods"
        }
    ],
    "sg:postcode":"SK11 8JR",
    "sg:province":"Cheshire",
    "sg:tags":[
        "society",
        "friendly"
    ],
    "wof:name":"Earles,Simon,",
    "wof:placetype":"venue"
},
  "geometry": {"coordinates":[-2.1257560253,53.2556686401],"type":"Point"}
}