{
  "type": "Feature",
  "properties": {
    "addr:full":"11 South Elixa Place Edinburgh City of Edinburgh EH8 7PG",
    "addr:housenumber":"11",
    "addr:postcode":"eh8 7pg",
    "addr:street":"South Elixa Place Edinburgh",
    "iso:country":"GB",
    "sg:address":"11 South Elixa Place",
    "sg:city":"Edinburgh",
    "sg:classifiers":[
        {
            "category":"Building & Trades",
            "subcategory":"Cleaning & Sanitation",
            "type":"Services"
        }
    ],
    "sg:phone":"+44 131 661 6650",
    "sg:postcode":"EH8 7PG",
    "sg:province":"City of Edinburgh",
    "sg:tags":[
        "cleaner",
        "window"
    ],
    "wof:name":"David Grant",
    "wof:placetype":"venue"
},
  "geometry": {"coordinates":[-3.1415190697,55.9527702332],"type":"Point"}
}