{
  "type": "Feature",
  "properties": {
    "addr:full":"Bedford Street North Halifax West Yorkshire HX1 5BH",
    "addr:postcode":"hx1 5bh",
    "addr:street":"Bedford Street North",
    "iso:country":"GB",
    "sg:address":"Bedford Street North",
    "sg:city":"Halifax",
    "sg:classifiers":[
        {
            "category":"Wholesale",
            "subcategory":"Construction Materials",
            "type":"Manufacturing & Wholesale Goods"
        }
    ],
    "sg:phone":"+44 1422 347483",
    "sg:postcode":"HX1 5BH",
    "sg:province":"West Yorkshire",
    "sg:tags":[
        "merchant",
        "stone"
    ],
    "wof:name":"Walker May (Halifax) Ltd.",
    "wof:placetype":"venue"
},
  "geometry": {"coordinates":[-1.8673449755,53.7243461609],"type":"Point"}
}