{
  "type": "Feature",
  "properties": {
    "addr:full":"31 Clover Mead Taunton Somerset TA1 3XD",
    "addr:housenumber":"31",
    "addr:postcode":"ta1 3xd",
    "addr:street":"Clover Mead",
    "iso:country":"GB",
    "sg:address":"31 Clover Mead",
    "sg:city":"Taunton",
    "sg:classifiers":[
        {
            "category":"Building & Trades",
            "subcategory":"Construction",
            "type":"Services"
        }
    ],
    "sg:phone":"+44 1823 274808",
    "sg:postcode":"TA1 3XD",
    "sg:province":"Somerset",
    "sg:tags":[
        "roofing"
    ],
    "wof:name":"Clovermead Roofing",
    "wof:placetype":"venue"
},
  "geometry": {"coordinates":[-3.0834479332,51.0009918213],"type":"Point"}
}