{
  "type": "Feature",
  "properties": {
    "iso:country":"GB",
    "sg:address":"Solway, Serpentine Road",
    "sg:city":"Rothesay",
    "sg:classifiers":[
        {
            "category":"Military Area",
            "subcategory":"Air Force Base",
            "type":"Public Place"
        }
    ],
    "sg:postcode":"PA20 9HG",
    "sg:province":"Argyll and Bute",
    "sg:tags":[
        "taxi",
        "hire",
        "private"
    ],
    "wof:name":"Sandy Ross Taxis",
    "wof:placetype":"venue"
},
  "geometry": {"coordinates":[-5.054835,55.834675],"type":"Point"}
}