{
  "type": "Feature",
  "properties": {
    "addr:full":"Pywell Road, Willowbrook East Industrial Estate Corby Northamptonshire NN17 5XJ",
    "addr:postcode":"nn17 5xj",
    "addr:street":"Pywell Road;East Industrial Estate",
    "iso:country":"GB",
    "sg:address":"Pywell Road, Willowbrook East Industrial Estate",
    "sg:city":"Corby",
    "sg:classifiers":[
        {
            "category":"Wholesale",
            "subcategory":"Construction Materials",
            "type":"Manufacturing & Wholesale Goods"
        },
        {
            "category":"Real Estate",
            "subcategory":"Architect",
            "type":"Services"
        }
    ],
    "sg:phone":"+44 1536 409100",
    "sg:postcode":"NN17 5XJ",
    "sg:province":"Northamptonshire",
    "sg:tags":[
        "supplier",
        "double",
        "glazing",
        "architectural"
    ],
    "wof:name":"CORWIN LTD",
    "wof:placetype":"venue"
},
  "geometry": {"coordinates":[-0.661424,52.505531],"type":"Point"}
}