{
  "type": "Feature",
  "properties": {
    "addr:full":"24 Touch Wards Dunfermline Fife KY12 7TG",
    "addr:housenumber":"24",
    "addr:postcode":"ky12 7tg",
    "addr:street":"Touch Wards Dunfermline",
    "iso:country":"GB",
    "sg:address":"24 Touch Wards",
    "sg:city":"Dunfermline",
    "sg:classifiers":[
        {
            "category":"Shopping",
            "subcategory":"Department Store",
            "type":"Retail Goods"
        }
    ],
    "sg:postcode":"KY12 7TG",
    "sg:province":"Fife",
    "wof:name":"Watson,David,",
    "wof:placetype":"venue"
},
  "geometry": {"coordinates":[-3.428708,56.07431],"type":"Point"}
}