{
  "type": "Feature",
  "properties": {
    "iso:country":"GB",
    "sg:address":"Kinnerly",
    "sg:city":"Oswestry",
    "sg:classifiers":[
        {
            "category":"Building & Trades",
            "subcategory":"Cleaning & Sanitation",
            "type":"Services"
        }
    ],
    "sg:postcode":"SY10 8DH",
    "sg:province":"Shropshire",
    "sg:tags":[
        "door",
        "manufacturer"
    ],
    "wof:name":"Custom Doors Midwales",
    "wof:placetype":"venue"
},
  "geometry": {"coordinates":[-2.99338,52.7775],"type":"Point"}
}