{
  "type": "Feature",
  "properties": {
    "addr:full":"50 High Road, Byfleet West Byfleet Surrey KT14 7QL",
    "addr:housenumber":"50",
    "addr:postcode":"kt14 7ql",
    "addr:street":"High Road;West Byfleet",
    "iso:country":"GB",
    "sg:address":"50 High Road, Byfleet",
    "sg:city":"West Byfleet",
    "sg:classifiers":[
        {
            "category":"Retail",
            "subcategory":"Funeral Services",
            "type":"Services"
        }
    ],
    "sg:phone":"+44 1932 345037",
    "sg:postcode":"KT14 7QL",
    "sg:province":"Surrey",
    "sg:tags":[
        "director"
    ],
    "wof:name":"G Boutell & Son",
    "wof:placetype":"venue"
},
  "geometry": {"coordinates":[-0.477876,51.338783],"type":"Point"}
}