{
  "type": "Feature",
  "properties": {
    "addr:full":"Chancery La Stoke On Trent Cheshire ST7 2HE",
    "addr:postcode":"st7 2he",
    "addr:street":"Stoke On Trent",
    "iso:country":"GB",
    "sg:address":"Chancery La",
    "sg:city":"Stoke On Trent",
    "sg:classifiers":[
        {
            "category":"Retail",
            "subcategory":"Event Space",
            "type":"Services"
        }
    ],
    "sg:phone":"+44 1782 334422",
    "sg:postcode":"ST7 2HE",
    "sg:province":"Cheshire",
    "sg:tags":[
        "banqueting",
        "room"
    ],
    "wof:name":"Princess Suite & Pinewood Room",
    "wof:placetype":"venue"
},
  "geometry": {"coordinates":[-2.3145399094,53.0969734192],"type":"Point"}
}