{
  "type": "Feature",
  "properties": {
    "addr:full":"7 Shirburn Street Watlington Oxfordshire OX49 5BU",
    "addr:housenumber":"7",
    "addr:postcode":"ox49 5bu",
    "addr:street":"Shirburn Street",
    "iso:country":"GB",
    "sg:address":"7 Shirburn Street",
    "sg:city":"Watlington",
    "sg:classifiers":[
        {
            "category":"Health Services",
            "subcategory":"Dentist",
            "type":"Services"
        }
    ],
    "sg:postcode":"OX49 5BU",
    "sg:province":"Oxfordshire",
    "wof:name":"B F P Hagan Dental Practice",
    "wof:placetype":"venue"
},
  "geometry": {"coordinates":[-1.0038399696,51.6455421448],"type":"Point"}
}