{
  "type": "Feature",
  "properties": {
    "iso:country":"GB",
    "sg:address":"The Coach Ho, St. Margarets Rd, South Darenth",
    "sg:city":"Dartford",
    "sg:classifiers":[
        {
            "category":"Home & Garden",
            "subcategory":"Garden Supply",
            "type":"Retail Goods"
        },
        {
            "category":"Farming",
            "subcategory":"Farm",
            "type":"Manufacturing & Wholesale Goods"
        }
    ],
    "sg:postcode":"DA4 9LB",
    "sg:province":"Kent",
    "sg:tags":[
        "mixed",
        "bulb",
        "crop",
        "grower"
    ],
    "wof:name":"Stapleton,David,",
    "wof:placetype":"venue"
},
  "geometry": {"coordinates":[0.253455,51.401665],"type":"Point"}
}