{
  "type": "Feature",
  "properties": {
    "addr:full":"Tiptree Delivery Office, 1a Church Road, Tiptree Colchester Essex CO5 0LD",
    "addr:housenumber":"1a",
    "addr:postcode":"co5 0ld",
    "addr:street":"Church Road",
    "iso:country":"GB",
    "sg:address":"Tiptree Delivery Office, 1a Church Road, Tiptree",
    "sg:city":"Colchester",
    "sg:classifiers":[
        {
            "category":"Personal",
            "type":"Services"
        },
        {
            "category":"Government",
            "subcategory":"Post Office",
            "type":"Public Place"
        }
    ],
    "sg:phone":"+44 1621 817944",
    "sg:postcode":"CO5 0LD",
    "sg:province":"Essex",
    "sg:tags":[
        "delivery"
    ],
    "wof:name":"Royal Mail Delivery Office",
    "wof:placetype":"venue"
},
  "geometry": {"coordinates":[0.7453340292,51.8164634705],"type":"Point"}
}