{
  "type": "Feature",
  "properties": {
    "addr:full":"Rear Of 131 St Marks Road Enfield Greater London EN1 1BA",
    "addr:postcode":"en1 1ba",
    "addr:street":"St Marks Road",
    "iso:country":"GB",
    "sg:address":"Rear Of 131 St Marks Road",
    "sg:city":"Enfield",
    "sg:phone":"+44 20 8364 4246",
    "sg:postcode":"EN1 1BA",
    "sg:province":"Greater London",
    "wof:name":"M J Tanner",
    "wof:placetype":"venue"
},
  "geometry": {"coordinates":[-0.06878,51.641769],"type":"Point"}
}