{
  "type": "Feature",
  "properties": {
    "addr:full":"48 Liddymore Road Watchet Somerset TA23 0DS",
    "addr:housenumber":"48",
    "addr:postcode":"ta23 0ds",
    "addr:street":"Liddymore Road",
    "iso:country":"GB",
    "sg:address":"48 Liddymore Road",
    "sg:city":"Watchet",
    "sg:classifiers":[
        {
            "category":"Food & Beverages",
            "subcategory":"Meat & Fish",
            "type":"Retail Goods"
        }
    ],
    "sg:phone":"+44 1984 631397",
    "sg:postcode":"TA23 0DS",
    "sg:province":"Somerset",
    "sg:tags":[
        "chip"
    ],
    "wof:name":"A Perrone",
    "wof:placetype":"venue"
},
  "geometry": {"coordinates":[-3.3253059387,51.1778717041],"type":"Point"}
}