{
  "type": "Feature",
  "properties": {
    "iso:country":"GB",
    "sg:address":"137 High Street",
    "sg:city":"Rayleigh",
    "sg:classifiers":[
        {
            "category":"Home & Garden",
            "subcategory":"Furniture",
            "type":"Retail Goods"
        }
    ],
    "sg:phone":"+44 1268 770814",
    "sg:postcode":"SS6 7QA",
    "sg:province":"Essex",
    "wof:name":"Charnwood Furnishers",
    "wof:placetype":"venue"
},
  "geometry": {"coordinates":[0.603906,51.584763],"type":"Point"}
}