{
  "type": "Feature",
  "properties": {
    "addr:full":"Ritson House, Gale Road Prescot Lancashire L33 7YE",
    "addr:postcode":"l33 7ye",
    "addr:street":"Gale Road",
    "iso:country":"GB",
    "sg:address":"Ritson House, Gale Road",
    "sg:city":"Prescot",
    "sg:classifiers":[
        {
            "category":"Retail",
            "subcategory":"Auto Rental",
            "type":"Services"
        }
    ],
    "sg:phone":"+44 870043881",
    "sg:postcode":"L33 7YE",
    "sg:province":"Lancashire",
    "sg:tags":[
        "truck",
        "hire",
        "van"
    ],
    "wof:name":"Rockfield Union Ltd.",
    "wof:placetype":"venue"
},
  "geometry": {"coordinates":[-2.8554201126,53.4745407104],"type":"Point"}
}