{
  "type": "Feature",
  "properties": {
    "addr:full":"5/6 Dukes Court, Bognor Road Chichester West Sussex PO19 2FX",
    "addr:housenumber":"5 / 6",
    "addr:postcode":"po19 2fx",
    "addr:street":"Dukes Court Bognor Road",
    "iso:country":"GB",
    "sg:address":"5/6 Dukes Court, Bognor Road",
    "sg:city":"Chichester",
    "sg:classifiers":[
        {
            "category":"Professional",
            "subcategory":"Management & Consulting",
            "type":"Services"
        }
    ],
    "sg:postcode":"PO19 2FX",
    "sg:province":"West Sussex",
    "sg:tags":[
        "marketing",
        "consultant"
    ],
    "wof:name":"1ST Marketing Group Ltd",
    "wof:placetype":"venue"
},
  "geometry": {"coordinates":[-0.7754290104,50.8361663818],"type":"Point"}
}