{
  "type": "Feature",
  "properties": {
    "addr:full":"Liberal Hall Chambers, Dark St Haverfordwest Pembrokeshire SA61 2DS",
    "addr:postcode":"sa61 2ds",
    "addr:street":"Dark St",
    "iso:country":"GB",
    "sg:address":"Liberal Hall Chambers, Dark St",
    "sg:city":"Haverfordwest",
    "sg:classifiers":[
        {
            "category":"Communications",
            "type":"Services"
        }
    ],
    "sg:phone":"+44 1437 762844",
    "sg:postcode":"SA61 2DS",
    "sg:province":"Pembrokeshire",
    "sg:tags":[
        "tv",
        "video",
        "radio"
    ],
    "wof:name":"Quay Services",
    "wof:placetype":"venue"
},
  "geometry": {"coordinates":[-4.97735,51.798763],"type":"Point"}
}