{
  "type": "Feature",
  "properties": {
    "iso:country":"GB",
    "sg:address":"Fraser House, Bridge Lane",
    "sg:city":"Warrington",
    "sg:classifiers":[
        {
            "category":"Professional",
            "subcategory":"Accounting & Tax Preparation",
            "type":"Services"
        }
    ],
    "sg:postcode":"WA6 7HD",
    "sg:province":"Cheshire",
    "sg:tags":[
        "accountant"
    ],
    "wof:name":"Castletown Corporate Finance",
    "wof:placetype":"venue"
},
  "geometry": {"coordinates":[-2.7122929096,53.2994041443],"type":"Point"}
}