{
  "type": "Feature",
  "properties": {
    "addr:full":"279a Witton Road Birmingham West Midlands B6 6NT",
    "addr:housenumber":"279a",
    "addr:postcode":"b6 6nt",
    "addr:street":"Witton Road",
    "iso:country":"GB",
    "sg:address":"279a Witton Road",
    "sg:city":"Birmingham",
    "sg:classifiers":[
        {
            "category":"Shopping",
            "subcategory":"Pharmacy",
            "type":"Retail Goods"
        }
    ],
    "sg:phone":"+44 121 327 4383",
    "sg:postcode":"B6 6NT",
    "sg:province":"West Midlands",
    "sg:tags":[
        "pharmacist",
        "dispensing",
        "chemist"
    ],
    "wof:name":"Buckingham Chemists",
    "wof:placetype":"venue"
},
  "geometry": {"coordinates":[-1.8892769814,52.5098190308],"type":"Point"}
}