{
  "type": "Feature",
  "properties": {
    "iso:country":"GB",
    "sg:address":"Millenium House, 30 Junction Road",
    "sg:city":"Sheffield",
    "sg:classifiers":[
        {
            "category":"Banks & Credit Unions",
            "subcategory":"Financial Services",
            "type":"Services"
        }
    ],
    "sg:phone":"+44 114 267 8444",
    "sg:postcode":"S11 8XB",
    "sg:province":"Derbyshire",
    "sg:tags":[
        "adviser"
    ],
    "wof:name":"Rowan Financial Planning",
    "wof:placetype":"venue"
},
  "geometry": {"coordinates":[-1.500029,53.366482],"type":"Point"}
}