{
  "type": "Feature",
  "properties": {
    "addr:full":"Unit, Unit 71, Clywedog Road East, Wrexham Industrial Estate Wrexham Wrexham LL13 9XE",
    "addr:housenumber":"unit 71",
    "addr:postcode":"ll13 9xe",
    "addr:street":"Clywedog Road East;Industrial Estate",
    "iso:country":"GB",
    "sg:address":"Unit, Unit 71, Clywedog Road East, Wrexham Industrial Estate",
    "sg:city":"Wrexham",
    "sg:classifiers":[
        {
            "category":"Manufacturing",
            "subcategory":"Wood Products",
            "type":"Manufacturing & Wholesale Goods"
        },
        {
            "category":"Professional",
            "subcategory":"Employment Agencies",
            "type":"Services"
        }
    ],
    "sg:phone":"+44 1978 660400",
    "sg:postcode":"LL13 9XE",
    "sg:province":"Wrexham",
    "sg:tags":[
        "encapsulation",
        "lamination"
    ],
    "sg:website":"http://www.lamin8.ltd.uk",
    "wof:name":"Lamin 8 Ltd",
    "wof:placetype":"venue"
},
  "geometry": {"coordinates":[-2.9370789528,53.0381240845],"type":"Point"}
}