{
  "type": "Feature",
  "properties": {
    "iso:country":"GB",
    "sg:address":"53 Cobham Rd",
    "sg:city":"Wimborne",
    "sg:classifiers":[
        {
            "category":"Home & Garden",
            "subcategory":"Hardware",
            "type":"Retail Goods"
        }
    ],
    "sg:phone":"+44 1202 895996",
    "sg:postcode":"BH21 7RA",
    "sg:province":"Dorset",
    "sg:tags":[
        "tubing",
        "fitting",
        "hose",
        "diy"
    ],
    "wof:name":"Omegaflex Ltd",
    "wof:placetype":"venue"
},
  "geometry": {"coordinates":[-1.914142,50.81366],"type":"Point"}
}