{
  "type": "Feature",
  "properties": {
    "addr:full":"6 Bull Ring Horncastle Lincolnshire LN9 5HU",
    "addr:housenumber":"6",
    "addr:postcode":"ln9 5hu",
    "addr:street":"Bull Ring",
    "iso:country":"GB",
    "sg:address":"6 Bull Ring",
    "sg:city":"Horncastle",
    "sg:classifiers":[
        {
            "category":"Personal",
            "subcategory":"Barber",
            "type":"Services"
        }
    ],
    "sg:phone":"+44 1507 523575",
    "sg:postcode":"LN9 5HU",
    "sg:province":"Lincolnshire",
    "sg:tags":[
        "men's",
        "gents",
        "hairdresser"
    ],
    "wof:name":"Ron Short",
    "wof:placetype":"venue"
},
  "geometry": {"coordinates":[-0.114778,53.208908],"type":"Point"}
}