{
  "type": "Feature",
  "properties": {
    "addr:full":"88 Birmingham Road Bromsgrove Worcestershire B61 0DF",
    "addr:housenumber":"88",
    "addr:postcode":"b61 0df",
    "addr:street":"Birmingham Road",
    "iso:country":"GB",
    "sg:address":"88 Birmingham Road",
    "sg:city":"Bromsgrove",
    "sg:classifiers":[
        {
            "category":"Autos & Motor Vehicles",
            "subcategory":"Automobile Sales",
            "type":"Retail Goods"
        }
    ],
    "sg:phone":"+44 1527 877377",
    "sg:postcode":"B61 0DF",
    "sg:province":"Worcestershire",
    "sg:tags":[
        "car"
    ],
    "wof:name":"Expelbeck Ltd.",
    "wof:placetype":"venue"
},
  "geometry": {"coordinates":[-2.053767,52.340347],"type":"Point"}
}