{
  "type": "Feature",
  "properties": {
    "addr:full":"Stockton Road, Easington Peterlee Durham SR8 3AY",
    "addr:postcode":"sr8 3ay",
    "addr:street":"Stockton Road",
    "iso:country":"GB",
    "sg:address":"Stockton Road, Easington",
    "sg:city":"Peterlee",
    "sg:classifiers":[
        {
            "category":"Education",
            "subcategory":"School",
            "type":"Public Place"
        },
        {
            "category":"Government",
            "subcategory":"Office",
            "type":"Public Place"
        }
    ],
    "sg:phone":"+44 191 527 0757",
    "sg:postcode":"SR8 3AY",
    "sg:province":"Durham",
    "sg:tags":[
        "local",
        "authority"
    ],
    "wof:name":"Easington Comprehensive School",
    "wof:placetype":"venue"
},
  "geometry": {"coordinates":[-1.351969,54.784546],"type":"Point"}
}