{
  "type": "Feature",
  "properties": {
    "addr:full":"22 Bilton Rd, Kingsland Business Park Basingstoke Hampshire RG24 8NW",
    "addr:housenumber":"22",
    "addr:postcode":"rg24 8nw",
    "addr:street":"Bilton Rd",
    "iso:country":"GB",
    "sg:address":"22 Bilton Rd, Kingsland Business Park",
    "sg:city":"Basingstoke",
    "sg:classifiers":[
        {
            "category":"Shopping",
            "subcategory":"Computers & Home Electronics",
            "type":"Retail Goods"
        }
    ],
    "sg:phone":"+44 1256 404350",
    "sg:postcode":"RG24 8NW",
    "sg:province":"Hampshire",
    "sg:tags":[
        "electrical"
    ],
    "wof:name":"Otra UK Ltd",
    "wof:placetype":"venue"
},
  "geometry": {"coordinates":[-1.0679340363,51.2831382751],"type":"Point"}
}