{
  "type": "Feature",
  "properties": {
    "iso:country":"GB",
    "sg:address":"3 Station Road, Ollerton",
    "sg:city":"Newark",
    "sg:classifiers":[
        {
            "category":"Personal",
            "type":"Services"
        }
    ],
    "sg:phone":"+44 1623 825800",
    "sg:postcode":"NG22 9BW",
    "sg:province":"Nottinghamshire",
    "sg:tags":[
        "wedding"
    ],
    "wof:name":"All Things Bride & Beautiful",
    "wof:placetype":"venue"
},
  "geometry": {"coordinates":[-1.023972,53.198128],"type":"Point"}
}