{
  "type": "Feature",
  "properties": {
    "addr:full":"206 Ealing Road Wembley Greater London HA0 4QG",
    "addr:housenumber":"206",
    "addr:postcode":"ha0 4qg",
    "addr:street":"Ealing Road",
    "iso:country":"GB",
    "sg:address":"206 Ealing Road",
    "sg:city":"Wembley",
    "sg:classifiers":[
        {
            "category":"Food & Beverages",
            "subcategory":"Specialty",
            "type":"Retail Goods"
        }
    ],
    "sg:postcode":"HA0 4QG",
    "sg:province":"Greater London",
    "sg:tags":[
        "vegetarian"
    ],
    "wof:name":"Satkar Restaurant",
    "wof:placetype":"venue"
},
  "geometry": {"coordinates":[-0.2971540093,51.5446014404],"type":"Point"}
}