{
  "type": "Feature",
  "properties": {
    "iso:country":"GB",
    "sg:address":"Cedar Cres",
    "sg:city":"Barnsley",
    "sg:classifiers":[
        {
            "category":"Community Center",
            "type":"Public Place"
        }
    ],
    "sg:phone":"+44 1226 785959",
    "sg:postcode":"S70 3LP",
    "sg:province":"South Yorkshire",
    "sg:tags":[
        "centre"
    ],
    "wof:name":"Kendray Community Organisation",
    "wof:placetype":"venue"
},
  "geometry": {"coordinates":[-1.461251,53.542339],"type":"Point"}
}