{
  "type": "Feature",
  "properties": {
    "iso:country":"GB",
    "sg:address":"39b Hadrian Road",
    "sg:city":"Newcastle-upon-tyne",
    "sg:classifiers":[
        {
            "category":"Cinema",
            "subcategory":"Movie Rental",
            "type":"Entertainment"
        }
    ],
    "sg:phone":"+44 191 272 3099",
    "sg:postcode":"NE4 9HN",
    "sg:province":"Tyne and Wear",
    "sg:tags":[
        "video",
        "library"
    ],
    "wof:name":"Lalas Video & Music Store",
    "wof:placetype":"venue"
},
  "geometry": {"coordinates":[-1.650619,54.978241],"type":"Point"}
}