{
  "type": "Feature",
  "properties": {
    "iso:country":"GB",
    "sg:address":"1543 Stratford Road, Hall Grn",
    "sg:city":"Birmingham",
    "sg:classifiers":[
        {
            "category":"Insurance",
            "subcategory":"Insurance Agent",
            "type":"Services"
        }
    ],
    "sg:phone":"+44 121 733 6999",
    "sg:postcode":"B28 9JA",
    "sg:province":"West Midlands",
    "sg:tags":[
        "broker"
    ],
    "wof:name":"A PLAN INSURANCE GROUP",
    "wof:placetype":"venue"
},
  "geometry": {"coordinates":[-1.8362350464,52.4215087891],"type":"Point"}
}