{
  "type": "Feature",
  "properties": {
    "addr:full":"The Administrative Centre, Solutions The Bus Centre, Llangarrod Ross On Wye Gloucestershire HR9 6PG",
    "addr:postcode":"hr9 6pg",
    "iso:country":"GB",
    "sg:address":"The Administrative Centre, Solutions The Bus Centre, Llangarrod",
    "sg:city":"Ross On Wye",
    "sg:classifiers":[
        {
            "category":"Social Services",
            "subcategory":"Child Care",
            "type":"Services"
        }
    ],
    "sg:phone":"+44 1568 611412",
    "sg:postcode":"HR9 6PG",
    "sg:province":"Gloucestershire",
    "sg:tags":[
        "children's",
        "home"
    ],
    "wof:name":"Solutions Quality Care For Children",
    "wof:placetype":"venue"
},
  "geometry": {"coordinates":[-2.581733,51.916481],"type":"Point"}
}