{
  "type": "Feature",
  "properties": {
    "addr:full":"Unit 1 Station Rd, Armley Leeds West Yorkshire LS12 3EY",
    "addr:housenumber":"unit 1",
    "addr:postcode":"ls12 3ey",
    "addr:street":"Station Rd",
    "iso:country":"GB",
    "sg:address":"Unit 1 Station Rd, Armley",
    "sg:city":"Leeds",
    "sg:classifiers":[
        {
            "category":"Professional",
            "subcategory":"Engineering",
            "type":"Services"
        }
    ],
    "sg:phone":"+44 113 231 1380",
    "sg:postcode":"LS12 3EY",
    "sg:province":"West Yorkshire",
    "sg:tags":[
        "contractor",
        "electrical",
        "engineer"
    ],
    "wof:name":"Thompson Electrical (Leeds) Limited",
    "wof:placetype":"venue"
},
  "geometry": {"coordinates":[-1.594378,53.79631],"type":"Point"}
}