{
  "type": "Feature",
  "properties": {
    "iso:country":"GB",
    "sg:address":"226 St Marys La",
    "sg:city":"Upminster",
    "sg:classifiers":[
        {
            "category":"Health Services",
            "subcategory":"Doctor",
            "type":"Services"
        }
    ],
    "sg:phone":"+44 1708 251407",
    "sg:postcode":"RM14 3DH",
    "sg:province":"Essex",
    "sg:tags":[
        "practitioners"
    ],
    "wof:name":"Baig, S S",
    "wof:placetype":"venue"
},
  "geometry": {"coordinates":[0.2532970011,51.5564422607],"type":"Point"}
}