{
  "type": "Feature",
  "properties": {
    "addr:full":"11 King Edward Road Romford Essex RM1 2DH",
    "addr:housenumber":"11",
    "addr:postcode":"rm1 2dh",
    "addr:street":"King Edward Road",
    "iso:country":"GB",
    "sg:address":"11 King Edward Road",
    "sg:city":"Romford",
    "sg:classifiers":[
        {
            "category":"Building & Trades",
            "subcategory":"Construction",
            "type":"Services"
        }
    ],
    "sg:phone":"+44 1708 749974",
    "sg:postcode":"RM1 2DH",
    "sg:province":"Essex",
    "sg:tags":[
        "roofing"
    ],
    "wof:name":"Essex Flexible Flat Roofing Co",
    "wof:placetype":"venue"
},
  "geometry": {"coordinates":[0.187242,51.574295],"type":"Point"}
}