{
  "type": "Feature",
  "properties": {
    "iso:country":"GB",
    "sg:address":"51 High Street",
    "sg:city":"Hampton",
    "sg:classifiers":[
        {
            "category":"Real Estate",
            "subcategory":"Architect",
            "type":"Services"
        }
    ],
    "sg:phone":"+44 20 8941 2112",
    "sg:postcode":"TW12 2SX",
    "sg:province":"Greater London",
    "wof:name":"David Brown & Partners",
    "wof:placetype":"venue"
},
  "geometry": {"coordinates":[-0.360179,51.415173],"type":"Point"}
}