{
  "type": "Feature",
  "properties": {
    "addr:full":"5 Ashbourne Road Derby Derbyshire DE22 3FQ",
    "addr:housenumber":"5",
    "addr:postcode":"de22 3fq",
    "addr:street":"Ashbourne Road",
    "iso:country":"GB",
    "sg:address":"5 Ashbourne Road",
    "sg:city":"Derby",
    "sg:classifiers":[
        {
            "category":"Real Estate",
            "subcategory":"Real Estate Operator",
            "type":"Services"
        },
        {
            "category":"Real Estate",
            "subcategory":"Real Estate Services",
            "type":"Services"
        }
    ],
    "sg:phone":"+44 800 043 7995",
    "sg:postcode":"DE22 3FQ",
    "sg:province":"Derbyshire",
    "sg:tags":[
        "letting",
        "management",
        "agent"
    ],
    "wof:name":"Property Place",
    "wof:placetype":"venue"
},
  "geometry": {"coordinates":[-1.490948,52.925251],"type":"Point"}
}