{
  "type": "Feature",
  "properties": {
    "iso:country":"GB",
    "sg:address":"Betlands Farm, Burry, Reynoldston",
    "sg:city":"Swansea",
    "sg:classifiers":[
        {
            "category":"Farming",
            "subcategory":"Livestock Farm",
            "type":"Manufacturing & Wholesale Goods"
        },
        {
            "category":"Farming",
            "subcategory":"Farm",
            "type":"Manufacturing & Wholesale Goods"
        }
    ],
    "sg:postcode":"SA3 1BD",
    "sg:province":"Swansea",
    "sg:tags":[
        "mixed",
        "crop",
        "others"
    ],
    "wof:name":"David John Gambold",
    "wof:placetype":"venue"
},
  "geometry": {"coordinates":[-4.191699,51.588303],"type":"Point"}
}