{
  "type": "Feature",
  "properties": {
    "addr:full":"Shell Haven Refinery, The Mannerway Stanford-le-hope Essex SS17 9LD",
    "addr:postcode":"ss17 9ld",
    "addr:street":"Stanford-Le-Hope",
    "iso:country":"GB",
    "sg:address":"Shell Haven Refinery, The Mannerway",
    "sg:city":"Stanford-le-hope",
    "sg:classifiers":[
        {
            "category":"Autos & Motor Vehicles",
            "subcategory":"Fuel & Gas Station",
            "type":"Retail Goods"
        },
        {
            "category":"Mining & Drilling",
            "type":"Manufacturing & Wholesale Goods"
        }
    ],
    "sg:phone":"+44 1375 673333",
    "sg:postcode":"SS17 9LD",
    "sg:province":"Essex",
    "sg:tags":[
        "hr",
        "petrol",
        "oil",
        "petroleum"
    ],
    "wof:name":"Shell Uk Oil",
    "wof:placetype":"venue"
},
  "geometry": {"coordinates":[0.41475,51.513645],"type":"Point"}
}