{
  "type": "Feature",
  "properties": {
    "addr:full":"26 Bethcar Street Ebbw Vale Blaenau Gwent NP23 6HQ",
    "addr:housenumber":"26",
    "addr:postcode":"np23 6hq",
    "addr:street":"Bethcar Street",
    "iso:country":"GB",
    "sg:address":"26 Bethcar Street",
    "sg:city":"Ebbw Vale",
    "sg:classifiers":[
        {
            "category":"Shopping",
            "subcategory":"Discount & Variety Stores",
            "type":"Retail Goods"
        }
    ],
    "sg:phone":"+44 1495 304148",
    "sg:postcode":"NP23 6HQ",
    "sg:province":"Blaenau Gwent",
    "sg:tags":[
        "centre"
    ],
    "wof:name":"Concord Discounts",
    "wof:placetype":"venue"
},
  "geometry": {"coordinates":[-3.2082901001,51.7783660889],"type":"Point"}
}