{
  "type": "Feature",
  "properties": {
    "addr:full":"Meta House, Kings Road Fleet Hampshire GU51 3AD",
    "addr:postcode":"gu51 3ad",
    "addr:street":"Kings Road",
    "iso:country":"GB",
    "sg:address":"Meta House, Kings Road",
    "sg:city":"Fleet",
    "sg:classifiers":[
        {
            "category":"Professional",
            "subcategory":"Computer Services",
            "type":"Services"
        }
    ],
    "sg:phone":"+44 1252 811812",
    "sg:postcode":"GU51 3AD",
    "sg:province":"Hampshire",
    "sg:tags":[
        "system",
        "software"
    ],
    "wof:name":"Vecta Software Corporation Plc",
    "wof:placetype":"venue"
},
  "geometry": {"coordinates":[-0.83694,51.284763],"type":"Point"}
}