{
  "type": "Feature",
  "properties": {
    "iso:country":"GB",
    "sg:address":"6 Valley Road",
    "sg:city":"Welwyn Garden City",
    "sg:classifiers":[
        {
            "category":"Professional",
            "subcategory":"Computer Services",
            "type":"Services"
        }
    ],
    "sg:postcode":"AL8 7DF",
    "sg:province":"Hertfordshire",
    "sg:tags":[
        "system",
        "software"
    ],
    "wof:name":"Muxtech Ltd",
    "wof:placetype":"venue"
},
  "geometry": {"coordinates":[-0.214565,51.803688],"type":"Point"}
}