{
  "type": "Feature",
  "properties": {
    "addr:full":"96 Westmead Rd Sutton Surrey SM1 4HX",
    "addr:housenumber":"96",
    "addr:postcode":"sm1 4hx",
    "addr:street":"Westmead Rd",
    "iso:country":"GB",
    "sg:address":"96 Westmead Rd",
    "sg:city":"Sutton",
    "sg:classifiers":[
        {
            "category":"Health Services",
            "subcategory":"Dentist",
            "type":"Services"
        }
    ],
    "sg:phone":"+44 20 8643 7935",
    "sg:postcode":"SM1 4HX",
    "sg:province":"Surrey",
    "wof:name":"R C Fell",
    "wof:placetype":"venue"
},
  "geometry": {"coordinates":[-0.1813430041,51.3659896851],"type":"Point"}
}