{
  "type": "Feature",
  "properties": {
    "addr:full":"9 Cornmarket High Wycombe Buckinghamshire HP11 2AX",
    "addr:housenumber":"9",
    "addr:postcode":"hp11 2ax",
    "addr:street":"Cornmarket High",
    "iso:country":"GB",
    "sg:address":"9 Cornmarket",
    "sg:city":"High Wycombe",
    "sg:classifiers":[
        {
            "category":"Bars & Pubs",
            "type":"Food & Drink"
        }
    ],
    "sg:phone":"+44 1494 538610",
    "sg:postcode":"HP11 2AX",
    "sg:province":"Buckinghamshire",
    "sg:tags":[
        "pubs",
        "inn"
    ],
    "wof:name":"The Falcon",
    "wof:placetype":"venue"
},
  "geometry": {"coordinates":[-0.75118,51.629139],"type":"Point"}
}