{
  "type": "Feature",
  "properties": {
    "iso:country":"GB",
    "sg:address":"Overdene Ho, 49 Church St",
    "sg:city":"Reading",
    "sg:classifiers":[
        {
            "category":"Professional",
            "subcategory":"Management & Consulting",
            "type":"Services"
        }
    ],
    "sg:phone":"+44 1344 890200",
    "sg:postcode":"RG7 5BX",
    "sg:province":"Berkshire",
    "sg:tags":[
        "consultant",
        "promotion",
        "direct",
        "sale"
    ],
    "wof:name":"Point of Sale Solutions International Lt",
    "wof:placetype":"venue"
},
  "geometry": {"coordinates":[-1.08075,51.43642],"type":"Point"}
}