{
  "type": "Feature",
  "properties": {
    "addr:full":"1 Royle Rd Chorley Lancashire PR7 1JD",
    "addr:housenumber":"1",
    "addr:postcode":"pr7 1jd",
    "addr:street":"Royle Rd",
    "iso:country":"GB",
    "sg:address":"1 Royle Rd",
    "sg:city":"Chorley",
    "sg:classifiers":[
        {
            "category":"Real Estate",
            "subcategory":"Architect",
            "type":"Services"
        }
    ],
    "sg:postcode":"PR7 1JD",
    "sg:province":"Lancashire",
    "wof:name":"Parker,Michael,",
    "wof:placetype":"venue"
},
  "geometry": {"coordinates":[-2.636735,53.653625],"type":"Point"}
}