{
  "type": "Feature",
  "properties": {
    "iso:country":"GB",
    "sg:address":"Flint Ho, London Rd",
    "sg:city":"Hitchin",
    "sg:classifiers":[
        {
            "category":"Real Estate",
            "subcategory":"Architect",
            "type":"Services"
        }
    ],
    "sg:postcode":"SG4 7NF",
    "sg:province":"Hertfordshire",
    "wof:name":"Goss Associates",
    "wof:placetype":"venue"
},
  "geometry": {"coordinates":[-0.26693,51.931332],"type":"Point"}
}