{
  "type": "Feature",
  "properties": {
    "addr:full":"Building 558, Shoreham Road West, Heathrow Airport Hounslow Greater London TW6 3RN",
    "addr:housenumber":"558",
    "addr:postcode":"tw6 3rn",
    "addr:street":"Shoreham Road West Heathrow Airport",
    "iso:country":"GB",
    "sg:address":"Building 558, Shoreham Road West, Heathrow Airport",
    "sg:city":"Hounslow",
    "sg:classifiers":[
        {
            "category":"Freight",
            "type":"Transportation"
        }
    ],
    "sg:phone":"+44 20 8759 3963",
    "sg:postcode":"TW6 3RN",
    "sg:province":"Greater London",
    "sg:tags":[
        "cargo",
        "handling"
    ],
    "wof:name":"Heathrow Cargo Handling Ltd.",
    "wof:placetype":"venue"
},
  "geometry": {"coordinates":[-0.47068,51.460972],"type":"Point"}
}