{
  "type": "Feature",
  "properties": {
    "iso:country":"GB",
    "sg:address":"46 St Andrews Road",
    "sg:city":"Exmouth",
    "sg:classifiers":[
        {
            "category":"Food & Beverages",
            "subcategory":"Supermarket",
            "type":"Retail Goods"
        },
        {
            "category":"Food & Beverages",
            "subcategory":"Groceries & Convenience Stores",
            "type":"Retail Goods"
        }
    ],
    "sg:phone":"+44 1395 266032",
    "sg:postcode":"EX8 1AS",
    "sg:province":"Devon",
    "wof:name":"Londis",
    "wof:placetype":"venue"
},
  "geometry": {"coordinates":[-3.420729,50.61713],"type":"Point"}
}