{
  "type": "Feature",
  "properties": {
    "iso:country":"GB",
    "sg:address":"East Street",
    "sg:city":"Portland",
    "sg:classifiers":[
        {
            "category":"Organizations",
            "subcategory":"Community Association",
            "type":"Services"
        },
        {
            "category":"Organizations",
            "subcategory":"Membership Organization",
            "type":"Services"
        }
    ],
    "sg:phone":"+44 1305 820166",
    "sg:postcode":"DT5 1NF",
    "sg:province":"Dorset",
    "sg:tags":[
        "club",
        "social"
    ],
    "wof:name":"North Portland Working Mens Club",
    "wof:placetype":"venue"
},
  "geometry": {"coordinates":[-2.4359691143,50.5469017029],"type":"Point"}
}