{
  "type": "Feature",
  "properties": {
    "addr:full":"Powderham Lodge, 22 Hady Hill, Chesterfield Chesterfield Derbyshire S41 0DZ",
    "addr:housenumber":"powderham;22",
    "addr:postcode":"s41 0dz",
    "addr:street":"Hady Hill",
    "iso:country":"GB",
    "sg:address":"Powderham Lodge, 22 Hady Hill, Chesterfield",
    "sg:city":"Chesterfield",
    "sg:classifiers":[
        {
            "category":"Professional",
            "subcategory":"Computer Services",
            "type":"Services"
        }
    ],
    "sg:phone":"+44 114 249 3350",
    "sg:postcode":"S41 0DZ",
    "sg:province":"Derbyshire",
    "sg:tags":[
        "consultant"
    ],
    "wof:name":"Clark IT",
    "wof:placetype":"venue"
},
  "geometry": {"coordinates":[-1.4353189468,53.2428817749],"type":"Point"}
}