{
  "type": "Feature",
  "properties": {
    "iso:country":"GB",
    "sg:address":"14 High St",
    "sg:city":"Haverfordwest",
    "sg:classifiers":[
        {
            "category":"Government",
            "subcategory":"Police Station",
            "type":"Public Place"
        },
        {
            "category":"Government",
            "subcategory":"Office",
            "type":"Public Place"
        }
    ],
    "sg:phone":"+44 1437 762013",
    "sg:postcode":"SA61 2DA",
    "sg:province":"Pembrokeshire",
    "sg:tags":[
        "support",
        "central"
    ],
    "wof:name":"Dyfed Probation Service",
    "wof:placetype":"venue"
},
  "geometry": {"coordinates":[-4.970334,51.801613],"type":"Point"}
}