{
  "type": "Feature",
  "properties": {
    "addr:full":"246 Nottingham Road, Woodlinkin, Langley Mill Nottingham Derbyshire NG16 4HG",
    "addr:housenumber":"246",
    "addr:postcode":"ng16 4hg",
    "addr:street":"Nottingham Road Woodlinkin",
    "iso:country":"GB",
    "sg:address":"246 Nottingham Road, Woodlinkin, Langley Mill",
    "sg:city":"Nottingham",
    "sg:classifiers":[
        {
            "category":"Bars & Pubs",
            "type":"Food & Drink"
        }
    ],
    "sg:phone":"+44 1773 713851",
    "sg:postcode":"NG16 4HG",
    "sg:province":"Derbyshire",
    "sg:tags":[
        "pubs",
        "inn"
    ],
    "wof:name":"The Thorn Tree Inn",
    "wof:placetype":"venue"
},
  "geometry": {"coordinates":[-1.360519,53.03558],"type":"Point"}
}