{
  "type": "Feature",
  "properties": {
    "addr:full":"5 Fore Street Holsworthy Cornwall EX22 6EB",
    "addr:housenumber":"5",
    "addr:postcode":"ex22 6eb",
    "addr:street":"Fore Street",
    "iso:country":"GB",
    "sg:address":"5 Fore Street",
    "sg:city":"Holsworthy",
    "sg:classifiers":[
        {
            "category":"Shopping",
            "subcategory":"Computers & Home Electronics",
            "type":"Retail Goods"
        }
    ],
    "sg:postcode":"EX22 6EB",
    "sg:province":"Cornwall",
    "sg:tags":[
        "electrical"
    ],
    "wof:name":"J C O",
    "wof:placetype":"venue"
},
  "geometry": {"coordinates":[-4.3506717682,50.8155136108],"type":"Point"}
}