{
  "type": "Feature",
  "properties": {
    "iso:country":"GB",
    "sg:address":"2a Mountcastle Drive North",
    "sg:city":"Edinburgh",
    "sg:classifiers":[
        {
            "category":"Building & Trades",
            "subcategory":"Construction",
            "type":"Services"
        }
    ],
    "sg:phone":"+44 131 657 1446",
    "sg:postcode":"EH8 7SJ",
    "sg:province":"City of Edinburgh",
    "sg:tags":[
        "builder"
    ],
    "wof:name":"Matro Construction Co. Ltd.",
    "wof:placetype":"venue"
},
  "geometry": {"coordinates":[-3.1365330219,55.9523048401],"type":"Point"}
}