{
  "type": "Feature",
  "properties": {
    "iso:country":"GB",
    "sg:address":"Blakebrook",
    "sg:city":"Kidderminster",
    "sg:classifiers":[
        {
            "category":"Education",
            "subcategory":"School",
            "type":"Public Place"
        }
    ],
    "sg:phone":"+44 1562 752155",
    "sg:postcode":"DY11 6AP",
    "sg:province":"Staffordshire",
    "sg:tags":[
        "local",
        "authority"
    ],
    "wof:name":"St John'S C Of E Middle School",
    "wof:placetype":"venue"
},
  "geometry": {"coordinates":[-2.26445,52.387531],"type":"Point"}
}