{
  "type": "Feature",
  "properties": {
    "addr:full":"10 Borstal Hill Whitstable Kent CT5 4LX",
    "addr:housenumber":"10",
    "addr:postcode":"ct5 4lx",
    "addr:street":"Borstal Hill Whitstable",
    "iso:country":"GB",
    "sg:address":"10 Borstal Hill",
    "sg:city":"Whitstable",
    "sg:classifiers":[
        {
            "category":"Autos & Motor Vehicles",
            "subcategory":"Fuel & Gas Station",
            "type":"Retail Goods"
        }
    ],
    "sg:phone":"+44 1227 276622",
    "sg:postcode":"CT5 4LX",
    "sg:province":"Kent",
    "sg:tags":[
        "petrol",
        "filling"
    ],
    "wof:name":"Crusader Service Station",
    "wof:placetype":"venue"
},
  "geometry": {"coordinates":[1.021386,51.350246],"type":"Point"}
}