{
  "type": "Feature",
  "properties": {
    "iso:country":"GB",
    "sg:address":"The Atrium, North Caldeen Road",
    "sg:city":"Coatbridge",
    "sg:classifiers":[
        {
            "category":"Building & Trades",
            "subcategory":"Construction",
            "type":"Services"
        }
    ],
    "sg:postcode":"ML5 4EF",
    "sg:province":"North Lanarkshire",
    "sg:tags":[
        "flooring"
    ],
    "wof:name":"Wilson Mackay Driveways Ltd",
    "wof:placetype":"venue"
},
  "geometry": {"coordinates":[-4.012055,55.856117],"type":"Point"}
}