{
  "type": "Feature",
  "properties": {
    "iso:country":"GB",
    "sg:address":"99 St Martins Lane",
    "sg:city":"London",
    "sg:classifiers":[
        {
            "category":"Shopping",
            "subcategory":"Clothing, Apparel, & Fashions",
            "type":"Retail Goods"
        }
    ],
    "sg:phone":"+44 20 7379 4514",
    "sg:postcode":"WC2N 4AZ",
    "sg:province":"Greater London",
    "sg:tags":[
        "shop"
    ],
    "wof:name":"Droopy & Browns",
    "wof:placetype":"venue"
},
  "geometry": {"coordinates":[-0.12729,51.510471],"type":"Point"}
}