{
  "type": "Feature",
  "properties": {
    "addr:full":"Ardmore House, London Road Billericay Essex CM12 9HS",
    "addr:postcode":"cm12 9hs",
    "addr:street":"London Road",
    "iso:country":"GB",
    "sg:address":"Ardmore House, London Road",
    "sg:city":"Billericay",
    "sg:classifiers":[
        {
            "category":"Building & Trades",
            "subcategory":"Landscaping Services",
            "type":"Services"
        }
    ],
    "sg:phone":"+44 1277 650697",
    "sg:postcode":"CM12 9HS",
    "sg:province":"Essex",
    "sg:tags":[
        "landscape",
        "contractor"
    ],
    "wof:name":"Ground Control Ltd",
    "wof:placetype":"venue"
},
  "geometry": {"coordinates":[0.388278991,51.6275177002],"type":"Point"}
}