{
  "type": "Feature",
  "properties": {
    "iso:country":"GB",
    "sg:address":"Chesterfield Rd, Pleasley",
    "sg:city":"Mansfield",
    "sg:classifiers":[
        {
            "category":"Health Services",
            "subcategory":"Doctor",
            "type":"Services"
        },
        {
            "category":"Health Services",
            "subcategory":"Clinic",
            "type":"Services"
        }
    ],
    "sg:phone":"+44 1623 810249",
    "sg:postcode":"NG19 7PE",
    "sg:province":"Derbyshire",
    "sg:tags":[
        "nh",
        "practitioners"
    ],
    "wof:name":"Mansfield District Primary Care Trust",
    "wof:placetype":"venue"
},
  "geometry": {"coordinates":[-1.247434,53.176697],"type":"Point"}
}