{
  "type": "Feature",
  "properties": {
    "addr:full":"81 Chapel Street Thatcham Berkshire RG18 4JS",
    "addr:housenumber":"81",
    "addr:postcode":"rg18 4js",
    "addr:street":"Chapel Street",
    "iso:country":"GB",
    "sg:address":"81 Chapel Street",
    "sg:city":"Thatcham",
    "sg:classifiers":[
        {
            "category":"Bars & Pubs",
            "type":"Food & Drink"
        }
    ],
    "sg:phone":"+44 1635 860340",
    "sg:postcode":"RG18 4JS",
    "sg:province":"Berkshire",
    "sg:tags":[
        "pubs",
        "inn"
    ],
    "wof:name":"The Plough Inn",
    "wof:placetype":"venue"
},
  "geometry": {"coordinates":[-1.250479,51.403728],"type":"Point"}
}