{
  "type": "Feature",
  "properties": {
    "addr:full":"1 Headley Parade, Langley Vale Road Epsom Surrey KT18 6AW",
    "addr:housenumber":"1",
    "addr:postcode":"kt18 6aw",
    "addr:street":"Headley Parade;Vale Road",
    "iso:country":"GB",
    "sg:address":"1 Headley Parade, Langley Vale Road",
    "sg:city":"Epsom",
    "sg:classifiers":[
        {
            "category":"Shopping",
            "subcategory":"News",
            "type":"Retail Goods"
        }
    ],
    "sg:phone":"+44 1372 272820",
    "sg:postcode":"KT18 6AW",
    "sg:province":"Surrey",
    "sg:tags":[
        "newsagent"
    ],
    "wof:name":"The Shop on the Corner",
    "wof:placetype":"venue"
},
  "geometry": {"coordinates":[-0.278804,51.306728],"type":"Point"}
}