{
  "type": "Feature",
  "properties": {
    "addr:full":"Rose Cottage, Lochend Inverness Highland IV3 8JY",
    "addr:postcode":"iv3 8jy",
    "addr:street":"Lochend Inverness",
    "iso:country":"GB",
    "sg:address":"Rose Cottage, Lochend",
    "sg:city":"Inverness",
    "sg:classifiers":[
        {
            "category":"Manufacturing",
            "subcategory":"Building Materials",
            "type":"Manufacturing & Wholesale Goods"
        }
    ],
    "sg:postcode":"IV3 8JY",
    "sg:province":"Highland",
    "sg:tags":[
        "distributor",
        "concrete",
        "mnfrs"
    ],
    "wof:name":"William Mackay",
    "wof:placetype":"venue"
},
  "geometry": {"coordinates":[-4.3090991974,57.4288139343],"type":"Point"}
}