{
  "type": "Feature",
  "properties": {
    "iso:country":"GB",
    "sg:address":"Unit 5 Riverside Ct",
    "sg:city":"Cupar",
    "sg:classifiers":[
        {
            "category":"Real Estate",
            "subcategory":"Surveying",
            "type":"Services"
        }
    ],
    "sg:phone":"+44 1334 657781",
    "sg:postcode":"KY15 5JY",
    "sg:province":"Fife",
    "sg:tags":[
        "surveyor",
        "land"
    ],
    "wof:name":"Geodata Systems Ltd",
    "wof:placetype":"venue"
},
  "geometry": {"coordinates":[-3.0062990189,56.3191719055],"type":"Point"}
}