{
  "type": "Feature",
  "properties": {
    "addr:full":"Hob Lane, Balsall Common Coventry Warwickshire CV7 7GX",
    "addr:postcode":"cv7 7gx",
    "addr:street":"Hob Lane",
    "iso:country":"GB",
    "sg:address":"Hob Lane, Balsall Common",
    "sg:city":"Coventry",
    "sg:classifiers":[
        {
            "category":"Travel",
            "subcategory":"Hotels & Motels",
            "type":"Entertainment"
        }
    ],
    "sg:phone":"+44 1676 533804",
    "sg:postcode":"CV7 7GX",
    "sg:province":"Warwickshire",
    "sg:tags":[
        "house",
        "guest"
    ],
    "wof:name":"Camp Farm",
    "wof:placetype":"venue"
},
  "geometry": {"coordinates":[-1.626626,52.379898],"type":"Point"}
}