{
  "type": "Feature",
  "properties": {
    "addr:full":"Unit 9, Liberty Centre, Mount Pleasant Wembley Greater London HA0 1TX",
    "addr:housenumber":"unit 9",
    "addr:postcode":"ha0 1tx",
    "addr:street":"Liberty Centre",
    "iso:country":"GB",
    "sg:address":"Unit 9, Liberty Centre, Mount Pleasant",
    "sg:city":"Wembley",
    "sg:classifiers":[
        {
            "category":"Professional",
            "subcategory":"Detective & Security Services",
            "type":"Services"
        }
    ],
    "sg:phone":"+44 20 8902 2288",
    "sg:postcode":"HA0 1TX",
    "sg:province":"Greater London",
    "wof:name":"Makwana Engineering",
    "wof:placetype":"venue"
},
  "geometry": {"coordinates":[-0.295869,51.541996],"type":"Point"}
}