{
  "type": "Feature",
  "properties": {
    "addr:full":"2 Petersfield, Pembury Tunbridge Wells East Sussex TN2 4HD",
    "addr:housenumber":"2",
    "addr:postcode":"tn2 4hd",
    "addr:street":"Petersfield Pembury",
    "iso:country":"GB",
    "sg:address":"2 Petersfield, Pembury",
    "sg:city":"Tunbridge Wells",
    "sg:classifiers":[
        {
            "category":"Retail",
            "subcategory":"Auto Repair",
            "type":"Services"
        }
    ],
    "sg:phone":"+44 1892 822992",
    "sg:postcode":"TN2 4HD",
    "sg:province":"East Sussex",
    "sg:tags":[
        "body",
        "car",
        "repairer"
    ],
    "wof:name":"E G Green & Son",
    "wof:placetype":"venue"
},
  "geometry": {"coordinates":[0.330463,51.148983],"type":"Point"}
}