{
  "type": "Feature",
  "properties": {
    "addr:full":"Unit 6 Horndon Indstl Pk, West Horndon Brentwood Essex CM13 3XP",
    "addr:housenumber":"unit 6",
    "addr:postcode":"cm13 3xp",
    "addr:street":"Horndon Indstl Pk West Horndon",
    "iso:country":"GB",
    "sg:address":"Unit 6 Horndon Indstl Pk, West Horndon",
    "sg:city":"Brentwood",
    "sg:classifiers":[
        {
            "category":"Personal",
            "type":"Services"
        }
    ],
    "sg:postcode":"CM13 3XP",
    "sg:province":"Essex",
    "sg:tags":[
        "delivery"
    ],
    "wof:name":"T N T Express (U K) Ltd",
    "wof:placetype":"venue"
},
  "geometry": {"coordinates":[0.3428199887,51.5689201355],"type":"Point"}
}