{
  "type": "Feature",
  "properties": {
    "addr:full":"The Boathouse, Timsway Staines Berkshire TW18 3JY",
    "addr:postcode":"tw18 3jy",
    "iso:country":"GB",
    "sg:address":"The Boathouse, Timsway",
    "sg:city":"Staines",
    "sg:classifiers":[
        {
            "category":"Organizations",
            "subcategory":"Labor Organization",
            "type":"Services"
        }
    ],
    "sg:postcode":"TW18 3JY",
    "sg:province":"Berkshire",
    "sg:tags":[
        "woodworking",
        "machinery"
    ],
    "wof:name":"W R Engineering Doe",
    "wof:placetype":"venue"
},
  "geometry": {"coordinates":[-0.523614,51.433769],"type":"Point"}
}