{
  "type": "Feature",
  "properties": {
    "addr:full":"1 Brownsea Ct, 60 Clarence Rd Clapton Greater London E5 8EF",
    "addr:housenumber":"1;60",
    "addr:postcode":"e5 8ef",
    "addr:street":"Brownsea Ct;Clarence Rd",
    "iso:country":"GB",
    "sg:address":"1 Brownsea Ct, 60 Clarence Rd",
    "sg:city":"Clapton",
    "sg:classifiers":[
        {
            "category":"Organizations",
            "subcategory":"Religious Organization",
            "type":"Services"
        }
    ],
    "sg:phone":"+44 20 8985 3489",
    "sg:postcode":"E5 8EF",
    "sg:province":"Greater London",
    "sg:tags":[
        "organisation"
    ],
    "wof:name":"Servite Sisters",
    "wof:placetype":"venue"
},
  "geometry": {"coordinates":[-0.0558499992,51.5541191101],"type":"Point"}
}