{
  "type": "Feature",
  "properties": {
    "addr:full":"77 Crescent Road Kingston-upon-thames Greater London KT2 7RE",
    "addr:housenumber":"77",
    "addr:postcode":"kt2 7re",
    "addr:street":"Crescent Road",
    "iso:country":"GB",
    "sg:address":"77 Crescent Road",
    "sg:city":"Kingston-upon-thames",
    "sg:classifiers":[
        {
            "category":"Personal",
            "subcategory":"Beauty Salon",
            "type":"Services"
        },
        {
            "category":"Personal",
            "subcategory":"Barber",
            "type":"Services"
        }
    ],
    "sg:phone":"+44 20 8546 2577",
    "sg:postcode":"KT2 7RE",
    "sg:province":"Greater London",
    "sg:tags":[
        "unisex",
        "hairdresser"
    ],
    "wof:name":"The Cutting Club",
    "wof:placetype":"venue"
},
  "geometry": {"coordinates":[-0.278694,51.420303],"type":"Point"}
}