{
  "type": "Feature",
  "properties": {
    "addr:full":"6 The Bindells, Chickerell Weymouth Dorset DT3 4BF",
    "addr:housenumber":"6",
    "addr:postcode":"dt3 4bf",
    "addr:street":"The Bindells",
    "iso:country":"GB",
    "sg:address":"6 The Bindells, Chickerell",
    "sg:city":"Weymouth",
    "sg:classifiers":[
        {
            "category":"Professional",
            "subcategory":"Management & Consulting",
            "type":"Services"
        }
    ],
    "sg:postcode":"DT3 4BF",
    "sg:province":"Dorset",
    "sg:tags":[
        "consultant",
        "specialist"
    ],
    "wof:name":"Freeman,Nicki,",
    "wof:placetype":"venue"
},
  "geometry": {"coordinates":[-2.505325,50.622772],"type":"Point"}
}