{
  "type": "Feature",
  "properties": {
    "addr:full":"19 Y M C A Enterprise Cntr, Herrington Burn Houghton-le-spring Durham DH4 4JB",
    "addr:postcode":"dh4 4jb",
    "addr:street":"19",
    "iso:country":"GB",
    "sg:address":"19 Y M C A Enterprise Cntr, Herrington Burn",
    "sg:city":"Houghton-le-spring",
    "sg:classifiers":[
        {
            "category":"Building & Trades",
            "subcategory":"Equipment Rental",
            "type":"Services"
        }
    ],
    "sg:phone":"+44 191 584 9200",
    "sg:postcode":"DH4 4JB",
    "sg:province":"Durham",
    "sg:tags":[
        "hire",
        "catering"
    ],
    "wof:name":"Cairns Event Hire Ltd.",
    "wof:placetype":"venue"
},
  "geometry": {"coordinates":[-1.4818300009,54.8638916016],"type":"Point"}
}