{
  "type": "Feature",
  "properties": {
    "addr:full":"8 Beachley Road, Tutshill Chepstow Gloucestershire NP16 7EQ",
    "addr:housenumber":"8",
    "addr:postcode":"np16 7eq",
    "addr:street":"Beachley Road",
    "iso:country":"GB",
    "sg:address":"8 Beachley Road, Tutshill",
    "sg:city":"Chepstow",
    "sg:classifiers":[
        {
            "category":"Personal",
            "subcategory":"Beauty Salon",
            "type":"Services"
        }
    ],
    "sg:phone":"+44 1291 621833",
    "sg:postcode":"NP16 7EQ",
    "sg:province":"Gloucestershire",
    "sg:tags":[
        "unisex",
        "hairdresser"
    ],
    "wof:name":"Rhian Williams Mobile",
    "wof:placetype":"venue"
},
  "geometry": {"coordinates":[-2.659395,51.640442],"type":"Point"}
}