{
  "type": "Feature",
  "properties": {
    "iso:country":"GB",
    "sg:address":"10 High Street",
    "sg:city":"Ilfracombe",
    "sg:classifiers":[
        {
            "category":"Shopping",
            "subcategory":"Gifts & Souvenirs",
            "type":"Retail Goods"
        }
    ],
    "sg:postcode":"EX34 9DF",
    "sg:province":"Devon",
    "sg:tags":[
        "shop"
    ],
    "wof:name":"B R Retail",
    "wof:placetype":"venue"
},
  "geometry": {"coordinates":[-4.1215291023,51.2088928223],"type":"Point"}
}