{
  "type": "Feature",
  "properties": {
    "iso:country":"GB",
    "sg:address":"Farfield St",
    "sg:city":"Cleckheaton",
    "sg:classifiers":[
        {
            "category":"Wholesale",
            "subcategory":"Office Equipment",
            "type":"Manufacturing & Wholesale Goods"
        }
    ],
    "sg:phone":"+44 1274 852444",
    "sg:postcode":"BD19 3TX",
    "sg:province":"West Yorkshire",
    "sg:tags":[
        "register",
        "cash",
        "accessory"
    ],
    "wof:name":"Vanguard",
    "wof:placetype":"venue"
},
  "geometry": {"coordinates":[-1.717357,53.730755],"type":"Point"}
}