{
  "type": "Feature",
  "properties": {
    "addr:full":"5 Jamieson Road Darvel East Ayrshire KA17 0AU",
    "addr:housenumber":"5",
    "addr:postcode":"ka17 0au",
    "addr:street":"Jamieson Road",
    "iso:country":"GB",
    "sg:address":"5 Jamieson Road",
    "sg:city":"Darvel",
    "sg:classifiers":[
        {
            "category":"Building & Trades",
            "subcategory":"Construction",
            "type":"Services"
        }
    ],
    "sg:phone":"+44 1560 322951",
    "sg:postcode":"KA17 0AU",
    "sg:province":"East Ayrshire",
    "sg:tags":[
        "joiner",
        "carpenter"
    ],
    "wof:name":"Shaw & Paterson Ltd.",
    "wof:placetype":"venue"
},
  "geometry": {"coordinates":[-4.2809019089,55.6100502014],"type":"Point"}
}