{
  "type": "Feature",
  "properties": {
    "iso:country":"GB",
    "sg:address":"6 Fairport Road",
    "sg:city":"Arbroath",
    "sg:classifiers":[
        {
            "category":"Manufacturing",
            "subcategory":"Building Materials",
            "type":"Manufacturing & Wholesale Goods"
        }
    ],
    "sg:phone":"+44 1241 876146",
    "sg:postcode":"DD11 5EJ",
    "sg:province":"Angus",
    "sg:tags":[
        "tarmac",
        "asphalt"
    ],
    "wof:name":"Arbroath Tarmacadam",
    "wof:placetype":"venue"
},
  "geometry": {"coordinates":[-2.568959,56.568748],"type":"Point"}
}