{
  "type": "Feature",
  "properties": {
    "addr:full":"Unit 7 Yale Business Park, Blue Stem Road, Ransomes Industrial Estate Ipswich Suffolk IP3 9RR",
    "addr:housenumber":"unit 7",
    "addr:postcode":"ip3 9rr",
    "addr:street":"Yale Business Park;Stem Road Ransomes Industrial Estate",
    "iso:country":"GB",
    "sg:address":"Unit 7 Yale Business Park, Blue Stem Road, Ransomes Industrial Estate",
    "sg:city":"Ipswich",
    "sg:classifiers":[
        {
            "category":"Freight",
            "type":"Transportation"
        }
    ],
    "sg:phone":"+44 1473 717737",
    "sg:postcode":"IP3 9RR",
    "sg:province":"Suffolk",
    "sg:tags":[
        "forwarders"
    ],
    "wof:name":"Air Express International (Uk)",
    "wof:placetype":"venue"
},
  "geometry": {"coordinates":[1.2151600122,52.0282402039],"type":"Point"}
}