{
  "type": "Feature",
  "properties": {
    "addr:full":"Callywhite La Dronfield Derbyshire S18 2XR",
    "addr:postcode":"s18 2xr",
    "iso:country":"GB",
    "sg:address":"Callywhite La",
    "sg:city":"Dronfield",
    "sg:classifiers":[
        {
            "category":"Sports & Exercise",
            "subcategory":"Golf",
            "type":"Entertainment"
        }
    ],
    "sg:postcode":"S18 2XR",
    "sg:province":"Derbyshire",
    "sg:tags":[
        "range",
        "driving"
    ],
    "wof:name":"Dronfield Driving Range",
    "wof:placetype":"venue"
},
  "geometry": {"coordinates":[-1.4597300291,53.2998199463],"type":"Point"}
}