{
  "type": "Feature",
  "properties": {
    "addr:full":"6 Park Place Kirkcaldy Fife KY1 1XL",
    "addr:housenumber":"6",
    "addr:postcode":"ky1 1xl",
    "addr:street":"Park Place",
    "iso:country":"GB",
    "sg:address":"6 Park Place",
    "sg:city":"Kirkcaldy",
    "sg:classifiers":[
        {
            "category":"Insurance",
            "subcategory":"Insurance Agent",
            "type":"Services"
        }
    ],
    "sg:phone":"+44 1592 268681",
    "sg:postcode":"KY1 1XL",
    "sg:province":"Fife",
    "wof:name":"Hill House Hammond Ltd",
    "wof:placetype":"venue"
},
  "geometry": {"coordinates":[-3.162133,56.1087],"type":"Point"}
}