{
  "type": "Feature",
  "properties": {
    "addr:full":"Harlaxton Road Grantham Lincolnshire NG31 7SA",
    "addr:postcode":"ng31 7sa",
    "addr:street":"Harlaxton Road",
    "iso:country":"GB",
    "sg:address":"Harlaxton Road",
    "sg:city":"Grantham",
    "sg:classifiers":[
        {
            "category":"Bars & Pubs",
            "type":"Food & Drink"
        }
    ],
    "sg:phone":"+44 1476 564803",
    "sg:postcode":"NG31 7SA",
    "sg:province":"Lincolnshire",
    "sg:tags":[
        "pubs",
        "inn"
    ],
    "wof:name":"Sir Isaac Newton",
    "wof:placetype":"venue"
},
  "geometry": {"coordinates":[-0.646782,52.908497],"type":"Point"}
}