{
  "type": "Feature",
  "properties": {
    "addr:full":"Dore Field House, Peterchurch Hereford Herefordshire HR2 0SF",
    "addr:postcode":"hr2 0sf",
    "addr:street":"Dore",
    "iso:country":"GB",
    "sg:address":"Dore Field House, Peterchurch",
    "sg:city":"Hereford",
    "sg:classifiers":[
        {
            "category":"Building & Trades",
            "subcategory":"Construction",
            "type":"Services"
        }
    ],
    "sg:postcode":"HR2 0SF",
    "sg:province":"Herefordshire",
    "sg:tags":[
        "builder"
    ],
    "wof:name":"Peter & Susan Smith",
    "wof:placetype":"venue"
},
  "geometry": {"coordinates":[-2.9590930939,52.0460662842],"type":"Point"}
}