{
  "type": "Feature",
  "properties": {
    "iso:country":"GB",
    "sg:address":"Unit 2a 270 High St",
    "sg:city":"Waltham Cross",
    "sg:classifiers":[
        {
            "category":"Building & Trades",
            "subcategory":"Construction",
            "type":"Services"
        }
    ],
    "sg:phone":"+44 1992 626931",
    "sg:postcode":"EN8 7EA",
    "sg:province":"Essex",
    "sg:tags":[
        "builder"
    ],
    "wof:name":"S J G Builders",
    "wof:placetype":"venue"
},
  "geometry": {"coordinates":[-0.033866,51.691319],"type":"Point"}
}