{
  "type": "Feature",
  "properties": {
    "iso:country":"GB",
    "sg:address":"20a Upgate",
    "sg:city":"Louth",
    "sg:classifiers":[
        {
            "category":"Health Services",
            "subcategory":"Optometrist",
            "type":"Services"
        }
    ],
    "sg:postcode":"LN11 9ET",
    "sg:province":"Lincolnshire",
    "sg:tags":[
        "optician"
    ],
    "wof:name":"Colin R Stevens",
    "wof:placetype":"venue"
},
  "geometry": {"coordinates":[-0.006938,53.366016],"type":"Point"}
}