{
  "type": "Feature",
  "properties": {
    "iso:country":"GB",
    "sg:address":"Marchamont Ho, 116 High St",
    "sg:city":"Egham",
    "sg:classifiers":[
        {
            "category":"Real Estate",
            "subcategory":"Architect",
            "type":"Services"
        }
    ],
    "sg:phone":"+44 1784 430575",
    "sg:postcode":"TW20 9HQ",
    "sg:province":"Surrey",
    "wof:name":"Archadia Practice (The) Ltd",
    "wof:placetype":"venue"
},
  "geometry": {"coordinates":[-0.547489,51.430897],"type":"Point"}
}