{
  "type": "Feature",
  "properties": {
    "addr:full":"26 High Street, West Mersea Colchester Essex CO5 8QD",
    "addr:housenumber":"26",
    "addr:postcode":"co5 8qd",
    "addr:street":"High Street West;Colchester",
    "iso:country":"GB",
    "sg:address":"26 High Street, West Mersea",
    "sg:city":"Colchester",
    "sg:classifiers":[
        {
            "category":"Shopping",
            "subcategory":"Hobbies, Toys, & Games",
            "type":"Retail Goods"
        }
    ],
    "sg:postcode":"CO5 8QD",
    "sg:province":"Essex",
    "sg:tags":[
        "toy"
    ],
    "wof:name":"Celebrations",
    "wof:placetype":"venue"
},
  "geometry": {"coordinates":[0.9113919735,51.7759590149],"type":"Point"}
}