{
  "type": "Feature",
  "properties": {
    "iso:country":"GB",
    "sg:address":"44 Regent St, Stotfold",
    "sg:city":"Hitchin",
    "sg:classifiers":[
        {
            "category":"Taxi",
            "type":"Transportation"
        }
    ],
    "sg:phone":"+44 70 7120 2968",
    "sg:postcode":"SG5 4EA",
    "sg:province":"Bedfordshire",
    "sg:tags":[
        "mini",
        "cab"
    ],
    "wof:name":"Stotfold Cars",
    "wof:placetype":"venue"
},
  "geometry": {"coordinates":[-0.228618,52.018017],"type":"Point"}
}