{
  "type": "Feature",
  "properties": {
    "addr:full":"55a Brighton Road Southport Lancashire PR8 4DD",
    "addr:housenumber":"55a",
    "addr:postcode":"pr8 4dd",
    "addr:street":"Brighton Road",
    "iso:country":"GB",
    "sg:address":"55a Brighton Road",
    "sg:city":"Southport",
    "sg:classifiers":[
        {
            "category":"Retail",
            "subcategory":"Auto Repair",
            "type":"Services"
        }
    ],
    "sg:phone":"+44 1704 568835",
    "sg:postcode":"PR8 4DD",
    "sg:province":"Lancashire",
    "sg:tags":[
        "modification",
        "garage",
        "related"
    ],
    "wof:name":"S L Motors",
    "wof:placetype":"venue"
},
  "geometry": {"coordinates":[-3.0109,53.62812],"type":"Point"}
}