{
  "type": "Feature",
  "properties": {
    "iso:country":"GB",
    "sg:address":"99 Sanders Road, Defindon Industrial Estate",
    "sg:city":"Wellingborough",
    "sg:classifiers":[
        {
            "category":"Personal",
            "type":"Services"
        }
    ],
    "sg:phone":"+44 1933 443446",
    "sg:postcode":"NN8 4NL",
    "sg:province":"Northamptonshire",
    "sg:tags":[
        "gift"
    ],
    "wof:name":"Stribbons Uk Ltd.",
    "wof:placetype":"venue"
},
  "geometry": {"coordinates":[-0.687633,52.324314],"type":"Point"}
}