{
  "type": "Feature",
  "properties": {
    "addr:full":"Dunstall Green Road, Ousden Newmarket Cambridgeshire CB8 8TY",
    "addr:postcode":"cb8 8ty",
    "addr:street":"Dunstall Green Road",
    "iso:country":"GB",
    "sg:address":"Dunstall Green Road, Ousden",
    "sg:city":"Newmarket",
    "sg:classifiers":[
        {
            "category":"Retail",
            "subcategory":"Auto Repair",
            "type":"Services"
        }
    ],
    "sg:phone":"+44 1638 500080",
    "sg:postcode":"CB8 8TY",
    "sg:province":"Cambridgeshire",
    "sg:tags":[
        "body",
        "car"
    ],
    "wof:name":"Beck Bodyworks",
    "wof:placetype":"venue"
},
  "geometry": {"coordinates":[0.551452,52.205486],"type":"Point"}
}