{
  "type": "Feature",
  "properties": {
    "iso:country":"GB",
    "sg:address":"15a Wilmslow Road",
    "sg:city":"Cheadle",
    "sg:classifiers":[
        {
            "category":"Professional",
            "subcategory":"Accounting & Tax Preparation",
            "type":"Services"
        }
    ],
    "sg:phone":"+44 161 491 6819",
    "sg:postcode":"SK8 1DW",
    "sg:province":"Cheshire",
    "sg:tags":[
        "accountant"
    ],
    "wof:name":"Stevenson & Associates",
    "wof:placetype":"venue"
},
  "geometry": {"coordinates":[-2.21714,53.393021],"type":"Point"}
}