{
  "type": "Feature",
  "properties": {
    "iso:country":"GB",
    "sg:address":"The Grange, Darley Moor",
    "sg:city":"Ashbourne",
    "sg:classifiers":[
        {
            "category":"Farming",
            "subcategory":"Farm",
            "type":"Manufacturing & Wholesale Goods"
        }
    ],
    "sg:phone":"+44 1335 330278",
    "sg:postcode":"DE6 2ET",
    "sg:province":"Derbyshire",
    "sg:tags":[
        "mixed",
        "crop"
    ],
    "wof:name":"E F Chadfield",
    "wof:placetype":"venue"
},
  "geometry": {"coordinates":[-1.750504,52.972897],"type":"Point"}
}