{
  "type": "Feature",
  "properties": {
    "addr:full":"49 Montague Street Rothesay Argyll and Bute PA20 0BU",
    "addr:housenumber":"49",
    "addr:postcode":"pa20 0bu",
    "addr:street":"Montague Street",
    "iso:country":"GB",
    "sg:address":"49 Montague Street",
    "sg:city":"Rothesay",
    "sg:classifiers":[
        {
            "category":"Shopping",
            "subcategory":"News",
            "type":"Retail Goods"
        }
    ],
    "sg:postcode":"PA20 0BU",
    "sg:province":"Argyll and Bute",
    "sg:tags":[
        "newsagent"
    ],
    "wof:name":"T L Wilkinson & Son",
    "wof:placetype":"venue"
},
  "geometry": {"coordinates":[-5.0558791161,55.8375282288],"type":"Point"}
}