{
  "type": "Feature",
  "properties": {
    "iso:country":"GB",
    "sg:address":"Bridgend Road, Llanharan",
    "sg:city":"Pontyclun",
    "sg:classifiers":[
        {
            "category":"Arena",
            "subcategory":"Sports Club",
            "type":"Entertainment"
        }
    ],
    "sg:phone":"+44 1443 222209",
    "sg:postcode":"CF72 9RD",
    "sg:province":"Bridgend",
    "wof:name":"Llanharran Rugby Football Club",
    "wof:placetype":"venue"
},
  "geometry": {"coordinates":[-3.43465,51.537811],"type":"Point"}
}