{
  "type": "Feature",
  "properties": {
    "addr:full":"317 Penn Road Wolverhampton Staffordshire WV4 5QF",
    "addr:housenumber":"317",
    "addr:postcode":"wv4 5qf",
    "addr:street":"Penn Road",
    "iso:country":"GB",
    "sg:address":"317 Penn Road",
    "sg:city":"Wolverhampton",
    "sg:classifiers":[
        {
            "category":"Home & Garden",
            "subcategory":"Furniture",
            "type":"Retail Goods"
        }
    ],
    "sg:phone":"+44 1902 341641",
    "sg:postcode":"WV4 5QF",
    "sg:province":"Staffordshire",
    "wof:name":"Paula Jayne Interiors (West Midlands) Ltd.",
    "wof:placetype":"venue"
},
  "geometry": {"coordinates":[-2.153464,52.560524],"type":"Point"}
}