{
  "type": "Feature",
  "properties": {
    "addr:full":"Unit 9 Forbes Court, Forbes Road Falkirk Falkirk FK1 1SS",
    "addr:housenumber":"unit 9",
    "addr:postcode":"fk1 1ss",
    "addr:street":"Forbes Court;Road",
    "iso:country":"GB",
    "sg:address":"Unit 9 Forbes Court, Forbes Road",
    "sg:city":"Falkirk",
    "sg:classifiers":[
        {
            "category":"Home & Garden",
            "subcategory":"Home Furnishings",
            "type":"Retail Goods"
        },
        {
            "category":"Wholesale",
            "subcategory":"Home Furnishings",
            "type":"Manufacturing & Wholesale Goods"
        }
    ],
    "sg:phone":"+44 1324 630920",
    "sg:postcode":"FK1 1SS",
    "sg:province":"Falkirk",
    "sg:tags":[
        "merchant",
        "diy",
        "decorators'"
    ],
    "wof:name":"Leyland Decorators Centre",
    "wof:placetype":"venue"
},
  "geometry": {"coordinates":[-3.767029,55.998295],"type":"Point"}
}