{
  "type": "Feature",
  "properties": {
    "iso:country":"GB",
    "sg:address":"Hillside, Whitwell",
    "sg:city":"Worksop",
    "sg:classifiers":[
        {
            "category":"Food & Beverages",
            "subcategory":"Groceries & Convenience Stores",
            "type":"Retail Goods"
        }
    ],
    "sg:phone":"+44 1909 720715",
    "sg:postcode":"S80 4PF",
    "sg:province":"Nottinghamshire",
    "wof:name":"Hillside Stores",
    "wof:placetype":"venue"
},
  "geometry": {"coordinates":[-1.2087999582,53.2858200073],"type":"Point"}
}