{
  "type": "Feature",
  "properties": {
    "addr:full":"Cakebole Kidderminster Staffordshire DY10 4RG",
    "addr:postcode":"dy10 4rg",
    "addr:street":"Cakebole",
    "iso:country":"GB",
    "sg:address":"Cakebole",
    "sg:city":"Kidderminster",
    "sg:classifiers":[
        {
            "category":"Home & Garden",
            "subcategory":"Garden Supply",
            "type":"Retail Goods"
        }
    ],
    "sg:postcode":"DY10 4RG",
    "sg:province":"Staffordshire",
    "sg:tags":[
        "nursery",
        "centre"
    ],
    "wof:name":"Blakedown Nurseries Ltd.",
    "wof:placetype":"venue"
},
  "geometry": {"coordinates":[-2.174751997,52.349773407],"type":"Point"}
}