{
  "type": "Feature",
  "properties": {
    "iso:country":"GB",
    "sg:address":"8 John Islip Street",
    "sg:city":"London",
    "sg:classifiers":[
        {
            "category":"Fast Food",
            "type":"Food & Drink"
        }
    ],
    "sg:phone":"+44 20 7828 0628",
    "sg:postcode":"SW1P 4PY",
    "sg:province":"Greater London",
    "sg:tags":[
        "away",
        "take"
    ],
    "wof:name":"Relish",
    "wof:placetype":"venue"
},
  "geometry": {"coordinates":[-0.1301659942,51.4897384644],"type":"Point"}
}