{
  "type": "Feature",
  "properties": {
    "iso:country":"GB",
    "sg:address":"2a Frithville Gardens, Shepherds Bush",
    "sg:city":"London",
    "sg:classifiers":[
        {
            "category":"Communications",
            "subcategory":"Film & Video Production",
            "type":"Services"
        }
    ],
    "sg:phone":"+44 20 8740 8000",
    "sg:postcode":"W12 7JN",
    "sg:province":"Greater London",
    "sg:tags":[
        "tv",
        "studio"
    ],
    "wof:name":"Coach House Studios Ltd.",
    "wof:placetype":"venue"
},
  "geometry": {"coordinates":[-0.226833,51.505955],"type":"Point"}
}