{
  "type": "Feature",
  "properties": {
    "addr:full":"2a Sussex Street Blyth Northumberland NE24 2AY",
    "addr:housenumber":"2a",
    "addr:postcode":"ne24 2ay",
    "addr:street":"Sussex Street;Northumberland",
    "iso:country":"GB",
    "sg:address":"2a Sussex Street",
    "sg:city":"Blyth",
    "sg:classifiers":[
        {
            "category":"Retail",
            "subcategory":"Auto Repair",
            "type":"Services"
        }
    ],
    "sg:phone":"+44 1670 366066",
    "sg:postcode":"NE24 2AY",
    "sg:province":"Northumberland",
    "sg:tags":[
        "modification",
        "garage"
    ],
    "wof:name":"Riverside Auto Centre",
    "wof:placetype":"venue"
},
  "geometry": {"coordinates":[-1.5028649569,55.1279983521],"type":"Point"}
}