{
  "type": "Feature",
  "properties": {
    "addr:full":"169 Priory Road Hastings East Sussex TN34 3JD",
    "addr:housenumber":"169",
    "addr:postcode":"tn34 3jd",
    "addr:street":"Priory Road",
    "iso:country":"GB",
    "sg:address":"169 Priory Road",
    "sg:city":"Hastings",
    "sg:classifiers":[
        {
            "category":"Manufacturing",
            "subcategory":"Petroleum Products",
            "type":"Manufacturing & Wholesale Goods"
        }
    ],
    "sg:phone":"+44 1424 442999",
    "sg:postcode":"TN34 3JD",
    "sg:province":"East Sussex",
    "sg:tags":[
        "double",
        "glazing"
    ],
    "wof:name":"Erends Upvc Specialists",
    "wof:placetype":"venue"
},
  "geometry": {"coordinates":[0.5923569798,50.864025116],"type":"Point"}
}