{
  "type": "Feature",
  "properties": {
    "addr:full":"Church Road, Hartshill Nuneaton Leicestershire CV10 0NA",
    "addr:postcode":"cv10 0na",
    "addr:street":"Church Road",
    "iso:country":"GB",
    "sg:address":"Church Road, Hartshill",
    "sg:city":"Nuneaton",
    "sg:classifiers":[
        {
            "category":"Education",
            "subcategory":"School",
            "type":"Public Place"
        }
    ],
    "sg:phone":"+44 24 7639 2237",
    "sg:postcode":"CV10 0NA",
    "sg:province":"Leicestershire",
    "sg:tags":[
        "college"
    ],
    "wof:name":"Hartshill School",
    "wof:placetype":"venue"
},
  "geometry": {"coordinates":[-1.5196290016,52.5429267883],"type":"Point"}
}