{
  "type": "Feature",
  "properties": {
    "iso:country":"GB",
    "sg:address":"Buckwill Hill, Hertsmonceux",
    "sg:city":"Hailsham",
    "sg:classifiers":[
        {
            "category":"Autos & Motor Vehicles",
            "subcategory":"Automobile Sales",
            "type":"Retail Goods"
        }
    ],
    "sg:phone":"+44 1323 832211",
    "sg:postcode":"BN27 4JU",
    "sg:province":"East Sussex",
    "sg:tags":[
        "car"
    ],
    "wof:name":"George Collins (Engineers) Ltd.",
    "wof:placetype":"venue"
},
  "geometry": {"coordinates":[0.3173199892,50.8887710571],"type":"Point"}
}