{
  "type": "Feature",
  "properties": {
    "iso:country":"GB",
    "sg:address":"Balfour Business Centre, Balfour Road",
    "sg:city":"Southall",
    "sg:classifiers":[
        {
            "category":"Education",
            "subcategory":"Special Training",
            "type":"Public Place"
        }
    ],
    "sg:phone":"+44 20 8893 6071",
    "sg:postcode":"UB2 5BD",
    "sg:province":"Greater London",
    "sg:tags":[
        "product",
        "centre"
    ],
    "wof:name":"Namdhari Centre",
    "wof:placetype":"venue"
},
  "geometry": {"coordinates":[-0.394579,51.50359],"type":"Point"}
}