{
  "type": "Feature",
  "properties": {
    "addr:full":"17 The Precinct, Commercial Road, Totton Southampton Hampshire SO40 3BY",
    "addr:housenumber":"17",
    "addr:postcode":"so40 3by",
    "addr:street":"The Precinct Commercial Road",
    "iso:country":"GB",
    "sg:address":"17 The Precinct, Commercial Road, Totton",
    "sg:city":"Southampton",
    "sg:classifiers":[
        {
            "category":"Travel",
            "subcategory":"Travel Agent",
            "type":"Entertainment"
        }
    ],
    "sg:phone":"+44 23 8087 2882",
    "sg:postcode":"SO40 3BY",
    "sg:province":"Hampshire",
    "wof:name":"Going Places Leisure Travel",
    "wof:placetype":"venue"
},
  "geometry": {"coordinates":[-1.491189,50.91991],"type":"Point"}
}