{
  "type": "Feature",
  "properties": {
    "iso:country":"GB",
    "sg:address":"45-52 Head St",
    "sg:city":"Colchester",
    "sg:classifiers":[
        {
            "category":"Restaurant",
            "type":"Food & Drink"
        }
    ],
    "sg:phone":"+44 1206 763405",
    "sg:postcode":"CO1 1PB",
    "sg:province":"Essex",
    "wof:name":"Alice's",
    "wof:placetype":"venue"
},
  "geometry": {"coordinates":[0.896093,51.888187],"type":"Point"}
}