{
  "type": "Feature",
  "properties": {
    "addr:full":"729a Bristol Rd South, Northfield Birmingham West Midlands B31 2NG",
    "addr:housenumber":"729a",
    "addr:postcode":"b31 2ng",
    "addr:street":"Bristol Rd",
    "iso:country":"GB",
    "sg:address":"729a Bristol Rd South, Northfield",
    "sg:city":"Birmingham",
    "sg:classifiers":[
        {
            "category":"Communications",
            "subcategory":"Film & Video Production",
            "type":"Services"
        }
    ],
    "sg:phone":"+44 121 475 4415",
    "sg:postcode":"B31 2NG",
    "sg:province":"West Midlands",
    "sg:tags":[
        "tv"
    ],
    "wof:name":"Granada Home Technology",
    "wof:placetype":"venue"
},
  "geometry": {"coordinates":[-1.970302,52.416363],"type":"Point"}
}