{
  "type": "Feature",
  "properties": {
    "iso:country":"GB",
    "sg:address":"Unit F2b, Keighley Business Centre",
    "sg:city":"Keighley",
    "sg:classifiers":[
        {
            "category":"Communications",
            "type":"Services"
        }
    ],
    "sg:phone":"+44 1535 610300",
    "sg:postcode":"BD21 1AG",
    "sg:province":"West Yorkshire",
    "sg:tags":[
        "audio-visual"
    ],
    "wof:name":"Video Image Productions Ltd.",
    "wof:placetype":"venue"
},
  "geometry": {"coordinates":[-1.905754,53.87009],"type":"Point"}
}