{
  "type": "Feature",
  "properties": {
    "iso:country":"GB",
    "sg:address":"Foster Cliffe Farm South, Low Lane, Silsden",
    "sg:city":"Keighley",
    "sg:classifiers":[
        {
            "category":"Professional",
            "subcategory":"Engineering",
            "type":"Services"
        }
    ],
    "sg:phone":"+44 1535 652487",
    "sg:postcode":"BD20 9JH",
    "sg:province":"North Yorkshire",
    "wof:name":"Frankie Wainmain Racing",
    "wof:placetype":"venue"
},
  "geometry": {"coordinates":[-1.94654,53.930519],"type":"Point"}
}