{
  "type": "Feature",
  "properties": {
    "addr:full":"511 Aspley Lane Nottingham Nottinghamshire NG8 5RW",
    "addr:housenumber":"511",
    "addr:postcode":"ng8 5rw",
    "addr:street":"Aspley Lane",
    "iso:country":"GB",
    "sg:address":"511 Aspley Lane",
    "sg:city":"Nottingham",
    "sg:classifiers":[
        {
            "category":"Health Services",
            "subcategory":"Doctor",
            "type":"Services"
        }
    ],
    "sg:phone":"+44 115 929 2700",
    "sg:postcode":"NG8 5RW",
    "sg:province":"Nottinghamshire",
    "sg:tags":[
        "practitioners"
    ],
    "wof:name":"Aspley Medical Centre",
    "wof:placetype":"venue"
},
  "geometry": {"coordinates":[-1.206063,52.972282],"type":"Point"}
}