{
  "type": "Feature",
  "properties": {
    "addr:full":"190 Finchampstead Road Wokingham Berkshire RG40 3HB",
    "addr:housenumber":"190",
    "addr:postcode":"rg40 3hb",
    "addr:street":"Finchampstead Road",
    "iso:country":"GB",
    "sg:address":"190 Finchampstead Road",
    "sg:city":"Wokingham",
    "sg:classifiers":[
        {
            "category":"Building & Trades",
            "subcategory":"Landscaping Services",
            "type":"Services"
        }
    ],
    "sg:postcode":"RG40 3HB",
    "sg:province":"Berkshire",
    "sg:tags":[
        "design",
        "garden"
    ],
    "wof:name":"Chamarette Garden Designs",
    "wof:placetype":"venue"
},
  "geometry": {"coordinates":[-0.84354,51.397346],"type":"Point"}
}