{
  "type": "Feature",
  "properties": {
    "addr:full":"9 Witts End, Eversholt Milton Keynes Bedfordshire MK17 9DZ",
    "addr:housenumber":"9",
    "addr:postcode":"mk17 9dz",
    "addr:street":"Witts End",
    "iso:country":"GB",
    "sg:address":"9 Witts End, Eversholt",
    "sg:city":"Milton Keynes",
    "sg:classifiers":[
        {
            "category":"Retail",
            "subcategory":"Auto Repair",
            "type":"Services"
        }
    ],
    "sg:phone":"+44 1525 280138",
    "sg:postcode":"MK17 9DZ",
    "sg:province":"Bedfordshire",
    "sg:tags":[
        "modification",
        "garage",
        "related"
    ],
    "wof:name":"Eversholt Motors",
    "wof:placetype":"venue"
},
  "geometry": {"coordinates":[-0.561995,51.985481],"type":"Point"}
}