{
  "type": "Feature",
  "properties": {
    "addr:full":"82 Boswell Rd Oxford Oxfordshire OX4 3HP",
    "addr:housenumber":"82",
    "addr:postcode":"ox4 3hp",
    "addr:street":"Boswell Rd",
    "iso:country":"GB",
    "sg:address":"82 Boswell Rd",
    "sg:city":"Oxford",
    "sg:classifiers":[
        {
            "category":"Health Services",
            "subcategory":"Dentist",
            "type":"Services"
        }
    ],
    "sg:phone":"+44 1865 774833",
    "sg:postcode":"OX4 3HP",
    "sg:province":"Oxfordshire",
    "sg:tags":[
        "technician",
        "dental"
    ],
    "wof:name":"Adenture",
    "wof:placetype":"venue"
},
  "geometry": {"coordinates":[-1.210566,51.729561],"type":"Point"}
}