{
  "type": "Feature",
  "properties": {
    "iso:country":"GB",
    "sg:address":"Suite 2, 11 Marlborough Place",
    "sg:city":"Brighton",
    "sg:classifiers":[
        {
            "category":"Professional",
            "subcategory":"Management & Consulting",
            "type":"Services"
        }
    ],
    "sg:postcode":"BN1 1UB",
    "sg:province":"East Sussex",
    "sg:tags":[
        "sport"
    ],
    "wof:name":"Society Golf",
    "wof:placetype":"venue"
},
  "geometry": {"coordinates":[-0.137189,50.824371],"type":"Point"}
}