{
  "type": "Feature",
  "properties": {
    "iso:country":"GB",
    "sg:address":"13 Wolverhampton Road",
    "sg:city":"Cannock",
    "sg:classifiers":[
        {
            "category":"Real Estate",
            "subcategory":"Real Estate Agent",
            "type":"Services"
        }
    ],
    "sg:phone":"+44 1543 503678",
    "sg:postcode":"WS11 1AP",
    "sg:province":"Staffordshire",
    "wof:name":"Evans & Evans",
    "wof:placetype":"venue"
},
  "geometry": {"coordinates":[-2.031189,52.688179],"type":"Point"}
}