{
  "type": "Feature",
  "properties": {
    "iso:country":"GB",
    "sg:address":"1/2 The Vale Craft Studios, Findon Road",
    "sg:city":"Worthing",
    "sg:classifiers":[
        {
            "category":"Wholesale",
            "subcategory":"Metals & Minerals",
            "type":"Manufacturing & Wholesale Goods"
        }
    ],
    "sg:phone":"+44 1903 877037",
    "sg:postcode":"BN14 0RA",
    "sg:province":"West Sussex",
    "sg:tags":[
        "merchant"
    ],
    "wof:name":"The Mineral Warehouse",
    "wof:placetype":"venue"
},
  "geometry": {"coordinates":[-0.406484,50.872181],"type":"Point"}
}