{
  "type": "Feature",
  "properties": {
    "addr:full":"37 Steep Hill Lincoln Lincolnshire LN2 1LU",
    "addr:housenumber":"37",
    "addr:postcode":"ln2 1lu",
    "addr:street":"Steep Hill Lincoln",
    "iso:country":"GB",
    "sg:address":"37 Steep Hill",
    "sg:city":"Lincoln",
    "sg:classifiers":[
        {
            "category":"Farming",
            "subcategory":"Fish & Marine Products",
            "type":"Manufacturing & Wholesale Goods"
        }
    ],
    "sg:postcode":"LN2 1LU",
    "sg:province":"Lincolnshire",
    "sg:tags":[
        "fishmonger"
    ],
    "wof:name":"Skinner's",
    "wof:placetype":"venue"
},
  "geometry": {"coordinates":[-0.538273,53.233406],"type":"Point"}
}