{
  "type": "Feature",
  "properties": {
    "iso:country":"GB",
    "sg:address":"7 Ffrydd Terrace",
    "sg:city":"Knighton",
    "sg:classifiers":[
        {
            "category":"Freight",
            "type":"Transportation"
        }
    ],
    "sg:phone":"+44 1547 528019",
    "sg:postcode":"LD7 1DL",
    "sg:province":"Shropshire",
    "sg:tags":[
        "haulage",
        "road"
    ],
    "wof:name":"C Price",
    "wof:placetype":"venue"
},
  "geometry": {"coordinates":[-3.048315,52.342556],"type":"Point"}
}