{
  "type": "Feature",
  "properties": {
    "addr:full":"9 Church Street, Arnold Nottingham Nottinghamshire NG5 8FD",
    "addr:housenumber":"9",
    "addr:postcode":"ng5 8fd",
    "addr:street":"Church Street",
    "iso:country":"GB",
    "sg:address":"9 Church Street, Arnold",
    "sg:city":"Nottingham",
    "sg:classifiers":[
        {
            "category":"Building & Trades",
            "subcategory":"Construction",
            "type":"Services"
        }
    ],
    "sg:postcode":"NG5 8FD",
    "sg:province":"Nottinghamshire",
    "sg:tags":[
        "builder"
    ],
    "wof:name":"Saracen Builders",
    "wof:placetype":"venue"
},
  "geometry": {"coordinates":[-1.127465,53.00724],"type":"Point"}
}