{
  "type": "Feature",
  "properties": {
    "iso:country":"GB",
    "sg:address":"Church Road",
    "sg:city":"Redditch",
    "sg:classifiers":[
        {
            "category":"Building & Trades",
            "subcategory":"Construction",
            "type":"Services"
        }
    ],
    "sg:phone":"+44 1527 893541",
    "sg:postcode":"B96 6EH",
    "sg:province":"Warwickshire",
    "sg:tags":[
        "builder"
    ],
    "wof:name":"Jarvis T",
    "wof:placetype":"venue"
},
  "geometry": {"coordinates":[-1.938224,52.264015],"type":"Point"}
}