{
  "type": "Feature",
  "properties": {
    "addr:full":"Station Terrace Caerphilly Caerphilly CF8 1HD",
    "addr:postcode":"cf8 1hd",
    "addr:street":"Station Terrace",
    "iso:country":"GB",
    "sg:address":"Station Terrace",
    "sg:city":"Caerphilly",
    "sg:classifiers":[
        {
            "category":"Social Services",
            "subcategory":"Adult Care",
            "type":"Services"
        }
    ],
    "sg:phone":"+44 29 2085 2558",
    "sg:postcode":"CF8 1HD",
    "sg:province":"Caerphilly",
    "sg:tags":[
        "day",
        "centre"
    ],
    "wof:name":"Caerphilly Day Centre",
    "wof:placetype":"venue"
},
  "geometry": {"coordinates":[-3.219387,51.571999],"type":"Point"}
}