{
  "type": "Feature",
  "properties": {
    "addr:full":"St Benedict Rd, Nunnery La York East Riding of Yorkshire YO2 1YA",
    "addr:postcode":"york;yo2 1ya",
    "addr:street":"St Benedict Rd",
    "iso:country":"GB",
    "sg:address":"St Benedict Rd, Nunnery La",
    "sg:city":"York",
    "sg:classifiers":[
        {
            "category":"Social Services",
            "subcategory":"Retirement Home",
            "type":"Services"
        }
    ],
    "sg:phone":"+44 1904 654246",
    "sg:postcode":"YO2 1YA",
    "sg:province":"East Riding of Yorkshire",
    "sg:tags":[
        "residential",
        "care"
    ],
    "wof:name":"Barstow House Residential Care",
    "wof:placetype":"venue"
},
  "geometry": {"coordinates":[-1.0834200382,53.9533309937],"type":"Point"}
}