{
  "type": "Feature",
  "properties": {
    "addr:full":"11 Church Walk, Eastwood Nottingham Derbyshire NG16 3BG",
    "addr:housenumber":"11",
    "addr:postcode":"ng16 3bg",
    "addr:street":"Church Walk",
    "iso:country":"GB",
    "sg:address":"11 Church Walk, Eastwood",
    "sg:city":"Nottingham",
    "sg:classifiers":[
        {
            "category":"Building & Trades",
            "subcategory":"Construction",
            "type":"Services"
        }
    ],
    "sg:phone":"+44 1773 715042",
    "sg:postcode":"NG16 3BG",
    "sg:province":"Derbyshire",
    "sg:tags":[
        "builder"
    ],
    "wof:name":"Thomas W Braithwaite",
    "wof:placetype":"venue"
},
  "geometry": {"coordinates":[-1.3050529957,53.016544342],"type":"Point"}
}