{
  "type": "Feature",
  "properties": {
    "addr:full":"Midland House, 50-52 Midland Road Wellingborough Northamptonshire NN8 1LU",
    "addr:housenumber":"50-52",
    "addr:postcode":"nn8 1lu",
    "addr:street":"Midland Road",
    "iso:country":"GB",
    "sg:address":"Midland House, 50-52 Midland Road",
    "sg:city":"Wellingborough",
    "sg:classifiers":[
        {
            "category":"Shopping",
            "subcategory":"Department Store",
            "type":"Retail Goods"
        }
    ],
    "sg:postcode":"NN8 1LU",
    "sg:province":"Northamptonshire",
    "wof:name":"S P R Retail Ltd",
    "wof:placetype":"venue"
},
  "geometry": {"coordinates":[-0.6874939799,52.3012313843],"type":"Point"}
}