{
  "type": "Feature",
  "properties": {
    "addr:full":"East Common Lane Scunthorpe Lincolnshire DN16 1XD",
    "addr:postcode":"dn16 1xd",
    "addr:street":"East Common Lane",
    "iso:country":"GB",
    "sg:address":"East Common Lane",
    "sg:city":"Scunthorpe",
    "sg:classifiers":[
        {
            "category":"Retail",
            "subcategory":"Auto Rental",
            "type":"Services"
        }
    ],
    "sg:phone":"+44 1724 861223",
    "sg:postcode":"DN16 1XD",
    "sg:province":"Lincolnshire",
    "sg:tags":[
        "car"
    ],
    "wof:name":"K W Saddler Self-Drive Rental",
    "wof:placetype":"venue"
},
  "geometry": {"coordinates":[-0.630662024,53.577293396],"type":"Point"}
}