{
  "type": "Feature",
  "properties": {
    "addr:full":"38 Dicconson Lane, Westhoughton Bolton Lancashire BL5 3NN",
    "addr:housenumber":"38",
    "addr:postcode":"bl5 3nn",
    "addr:street":"Dicconson Lane",
    "iso:country":"GB",
    "sg:address":"38 Dicconson Lane, Westhoughton",
    "sg:city":"Bolton",
    "sg:classifiers":[
        {
            "category":"Home & Garden",
            "subcategory":"Building Materials",
            "type":"Retail Goods"
        }
    ],
    "sg:phone":"+44 1942 814168",
    "sg:postcode":"BL5 3NN",
    "sg:province":"Lancashire",
    "sg:tags":[
        "insulation",
        "installers"
    ],
    "wof:name":"Lee B Whittle",
    "wof:placetype":"venue"
},
  "geometry": {"coordinates":[-2.5545520782,53.5654258728],"type":"Point"}
}