{
  "type": "Feature",
  "properties": {
    "iso:country":"GB",
    "sg:address":"Pickwick Lodge Farm, Pickwick",
    "sg:city":"Corsham",
    "sg:classifiers":[
        {
            "category":"Farming",
            "subcategory":"Livestock Farm",
            "type":"Manufacturing & Wholesale Goods"
        }
    ],
    "sg:phone":"+44 1249 712207",
    "sg:postcode":"SN13 0PS",
    "sg:province":"Wiltshire",
    "sg:tags":[
        "others"
    ],
    "wof:name":"Gary B Stafford",
    "wof:placetype":"venue"
},
  "geometry": {"coordinates":[-2.196973,51.434982],"type":"Point"}
}