{
  "type": "Feature",
  "properties": {
    "addr:full":"168-170 Wellington Rd South Hounslow Greater London TW4 5JN",
    "addr:housenumber":"168-170",
    "addr:postcode":"tw4 5jn",
    "addr:street":"Wellington Rd",
    "iso:country":"GB",
    "sg:address":"168-170 Wellington Rd South",
    "sg:city":"Hounslow",
    "sg:classifiers":[
        {
            "category":"Building & Trades",
            "subcategory":"Cleaning & Sanitation",
            "type":"Services"
        },
        {
            "category":"Home & Garden",
            "subcategory":"Building Materials",
            "type":"Retail Goods"
        }
    ],
    "sg:phone":"+44 20 8754 6319",
    "sg:postcode":"TW4 5JN",
    "sg:province":"Greater London",
    "sg:tags":[
        "repair",
        "lift",
        "-",
        "stairlifts"
    ],
    "wof:name":"Kone Lifts Ltd",
    "wof:placetype":"venue"
},
  "geometry": {"coordinates":[-0.3771159947,51.4637413025],"type":"Point"}
}