{
  "type": "Feature",
  "properties": {
    "addr:full":"72 Moyser Road London Greater London SW16 6SQ",
    "addr:housenumber":"72",
    "addr:postcode":"sw16 6sq",
    "addr:street":"Moyser Road",
    "iso:country":"GB",
    "sg:address":"72 Moyser Road",
    "sg:city":"London",
    "sg:classifiers":[
        {
            "category":"Shopping",
            "subcategory":"Florist",
            "type":"Retail Goods"
        }
    ],
    "sg:phone":"+44 20 8677 0593",
    "sg:postcode":"SW16 6SQ",
    "sg:province":"Greater London",
    "wof:name":"Clarkes Florist",
    "wof:placetype":"venue"
},
  "geometry": {"coordinates":[-0.147128,51.424046],"type":"Point"}
}