{
  "type": "Feature",
  "properties": {
    "addr:full":"17 Fir View Gardens, Osgathorpe Drive Sheffield South Yorkshire S4 7BN",
    "addr:housenumber":"17",
    "addr:postcode":"s4 7bn",
    "addr:street":"Fir View Gardens Osgathorpe Drive",
    "iso:country":"GB",
    "sg:address":"17 Fir View Gardens, Osgathorpe Drive",
    "sg:city":"Sheffield",
    "sg:classifiers":[
        {
            "category":"Health Services",
            "subcategory":"Nursing And Care Facility",
            "type":"Services"
        }
    ],
    "sg:phone":"+44 114 242 2446",
    "sg:postcode":"S4 7BN",
    "sg:province":"South Yorkshire",
    "sg:tags":[
        "home"
    ],
    "wof:name":"North Cheshire Housing Association",
    "wof:placetype":"venue"
},
  "geometry": {"coordinates":[-1.4519000053,53.4025497437],"type":"Point"}
}