{
  "type": "Feature",
  "properties": {
    "addr:full":"27 Spencer Street Carlisle Cumbria CA1 1BE",
    "addr:housenumber":"27",
    "addr:postcode":"ca1 1be",
    "addr:street":"Spencer Street",
    "iso:country":"GB",
    "sg:address":"27 Spencer Street",
    "sg:city":"Carlisle",
    "sg:classifiers":[
        {
            "category":"Organizations",
            "subcategory":"Non-profit Organization",
            "type":"Services"
        },
        {
            "category":"Organizations",
            "subcategory":"Membership Organization",
            "type":"Services"
        }
    ],
    "sg:phone":"+44 1228 512513",
    "sg:postcode":"CA1 1BE",
    "sg:province":"Cumbria",
    "sg:tags":[
        "organisation",
        "voluntary",
        "charity"
    ],
    "wof:name":"Carlisle Council For Voluntary Service",
    "wof:placetype":"venue"
},
  "geometry": {"coordinates":[-2.930346,54.894627],"type":"Point"}
}