{
  "type": "Feature",
  "properties": {
    "iso:country":"GB",
    "sg:address":"28 Lingfield Rd",
    "sg:city":"Wimbledon",
    "sg:classifiers":[
        {
            "category":"Real Estate",
            "subcategory":"Architect",
            "type":"Services"
        }
    ],
    "sg:phone":"+44 20 8946 1382",
    "sg:postcode":"SW19 4PU",
    "sg:province":"Greater London",
    "sg:tags":[
        "architectural"
    ],
    "wof:name":"John Onken Architecture",
    "wof:placetype":"venue"
},
  "geometry": {"coordinates":[-0.2184289992,51.4239387512],"type":"Point"}
}