{
  "type": "Feature",
  "properties": {
    "addr:full":"82 Causeyside St Paisley Renfrewshire PA1 1YP",
    "addr:housenumber":"82",
    "addr:postcode":"pa1 1yp",
    "addr:street":"Causeyside St",
    "iso:country":"GB",
    "sg:address":"82 Causeyside St",
    "sg:city":"Paisley",
    "sg:classifiers":[
        {
            "category":"Place Of Worship",
            "type":"Public Place"
        }
    ],
    "sg:phone":"+44 141 889 7700",
    "sg:postcode":"PA1 1YP",
    "sg:province":"Renfrewshire",
    "wof:name":"Laigh Kirk",
    "wof:placetype":"venue"
},
  "geometry": {"coordinates":[-4.424469,55.840611],"type":"Point"}
}