{
  "type": "Feature",
  "properties": {
    "iso:country":"GB",
    "sg:address":"9 Albert Road",
    "sg:city":"Middlesbrough",
    "sg:classifiers":[
        {
            "category":"Professional",
            "subcategory":"Art Services",
            "type":"Services"
        },
        {
            "category":"Communications",
            "type":"Services"
        }
    ],
    "sg:phone":"+44 1642 230221",
    "sg:postcode":"TS1 1PQ",
    "sg:province":"North Yorkshire",
    "sg:tags":[
        "photographer",
        "audio-visual"
    ],
    "wof:name":"Video F X",
    "wof:placetype":"venue"
},
  "geometry": {"coordinates":[-1.2344399691,54.5778808594],"type":"Point"}
}