{
  "type": "Feature",
  "properties": {
    "addr:full":"19 Windsor Road, Griffithstown Pontypool Monmouthshire NP4 5HZ",
    "addr:housenumber":"19",
    "addr:postcode":"np4 5hz",
    "addr:street":"Windsor Road",
    "iso:country":"GB",
    "sg:address":"19 Windsor Road, Griffithstown",
    "sg:city":"Pontypool",
    "sg:classifiers":[
        {
            "category":"Military Area",
            "subcategory":"Army Base",
            "type":"Public Place"
        },
        {
            "category":"Retail",
            "subcategory":"Repair Shop",
            "type":"Services"
        }
    ],
    "sg:phone":"+44 1495 753383",
    "sg:postcode":"NP4 5HZ",
    "sg:province":"Monmouthshire",
    "sg:tags":[
        "bonsai",
        "clocks",
        "watch",
        "centre"
    ],
    "wof:name":"John Trenchard & Sons",
    "wof:placetype":"venue"
},
  "geometry": {"coordinates":[-3.0257720947,51.6869812012],"type":"Point"}
}