{
  "type": "Feature",
  "properties": {
    "addr:full":"401 Westborough Road Westcliff-on-sea Essex SS0 9TW",
    "addr:housenumber":"401",
    "addr:postcode":"ss0 9tw",
    "addr:street":"Westborough Road",
    "iso:country":"GB",
    "sg:address":"401 Westborough Road",
    "sg:city":"Westcliff-on-sea",
    "sg:classifiers":[
        {
            "category":"Health Services",
            "subcategory":"Doctor",
            "type":"Services"
        }
    ],
    "sg:phone":"+44 1702 346442",
    "sg:postcode":"SS0 9TW",
    "sg:province":"Essex",
    "sg:tags":[
        "practitioners"
    ],
    "wof:name":"M Velmurugan",
    "wof:placetype":"venue"
},
  "geometry": {"coordinates":[0.6814110279,51.5476074219],"type":"Point"}
}