{
  "type": "Feature",
  "properties": {
    "addr:full":"6 Cecil Aldin Drive, Tilehurst Reading Berkshire RG31 6YP",
    "addr:housenumber":"6",
    "addr:postcode":"rg31 6yp",
    "addr:street":"Cecil Aldin Drive",
    "iso:country":"GB",
    "sg:address":"6 Cecil Aldin Drive, Tilehurst",
    "sg:city":"Reading",
    "sg:classifiers":[
        {
            "category":"Professional",
            "subcategory":"Computer Services",
            "type":"Services"
        }
    ],
    "sg:postcode":"RG31 6YP",
    "sg:province":"Berkshire",
    "sg:tags":[
        "system",
        "software"
    ],
    "wof:name":"Macdonald Associates Ltd.",
    "wof:placetype":"venue"
},
  "geometry": {"coordinates":[-1.0492520332,51.4795074463],"type":"Point"}
}