{
  "type": "Feature",
  "properties": {
    "addr:full":"47 Brompton Drive Maidenhead Berkshire SL6 6SP",
    "addr:housenumber":"47",
    "addr:postcode":"sl6 6sp",
    "addr:street":"Brompton Drive",
    "iso:country":"GB",
    "sg:address":"47 Brompton Drive",
    "sg:city":"Maidenhead",
    "sg:classifiers":[
        {
            "category":"Communications",
            "subcategory":"News Services",
            "type":"Services"
        }
    ],
    "sg:phone":"+44 1628 788227",
    "sg:postcode":"SL6 6SP",
    "sg:province":"Berkshire",
    "sg:tags":[
        "illustrator"
    ],
    "wof:name":"Technographic",
    "wof:placetype":"venue"
},
  "geometry": {"coordinates":[-0.7458630204,51.5349235535],"type":"Point"}
}