{
  "type": "Feature",
  "properties": {
    "iso:country":"GB",
    "sg:address":"Pax Holt, Bossington Lane",
    "sg:city":"Minehead",
    "sg:classifiers":[
        {
            "category":"Professional",
            "subcategory":"Advertising",
            "type":"Services"
        }
    ],
    "sg:postcode":"TA24 8HD",
    "sg:province":"Somerset",
    "sg:tags":[
        "agency"
    ],
    "wof:name":"Peskett Promotional Services",
    "wof:placetype":"venue"
},
  "geometry": {"coordinates":[-3.579193,51.219833],"type":"Point"}
}