{
  "type": "Feature",
  "properties": {
    "addr:full":"14 Limes Walk, Oakengates Telford Shropshire TF2 6EP",
    "addr:housenumber":"14",
    "addr:postcode":"tf2 6ep",
    "addr:street":"Limes Walk",
    "iso:country":"GB",
    "sg:address":"14 Limes Walk, Oakengates",
    "sg:city":"Telford",
    "sg:classifiers":[
        {
            "category":"Retail",
            "subcategory":"Laundry & Dry Cleaning",
            "type":"Services"
        }
    ],
    "sg:postcode":"TF2 6EP",
    "sg:province":"Shropshire",
    "sg:tags":[
        "alteration"
    ],
    "wof:name":"Classic Dry Cleaners",
    "wof:placetype":"venue"
},
  "geometry": {"coordinates":[-2.44866395,52.7026634216],"type":"Point"}
}