{
  "type": "Feature",
  "properties": {
    "addr:full":"780 Chorley Old Rd Bolton Lancashire BL1 5QE",
    "addr:housenumber":"780",
    "addr:postcode":"bl1 5qe",
    "addr:street":"Chorley Old Rd",
    "iso:country":"GB",
    "sg:address":"780 Chorley Old Rd",
    "sg:city":"Bolton",
    "sg:classifiers":[
        {
            "category":"Bars & Pubs",
            "type":"Food & Drink"
        }
    ],
    "sg:phone":"+44 1204 843656",
    "sg:postcode":"BL1 5QE",
    "sg:province":"Lancashire",
    "sg:tags":[
        "pubs",
        "inn"
    ],
    "wof:name":"Punch Inns (U K) Ltd",
    "wof:placetype":"venue"
},
  "geometry": {"coordinates":[-2.4722781181,53.5899429321],"type":"Point"}
}