{
  "type": "Feature",
  "properties": {
    "addr:full":"96 Broad Street Chesham Buckinghamshire HP5 3ED",
    "addr:housenumber":"96",
    "addr:postcode":"hp5 3ed",
    "addr:street":"Broad Street",
    "iso:country":"GB",
    "sg:address":"96 Broad Street",
    "sg:city":"Chesham",
    "sg:classifiers":[
        {
            "category":"Fast Food",
            "type":"Food & Drink"
        }
    ],
    "sg:phone":"+44 1494 784021",
    "sg:postcode":"HP5 3ED",
    "sg:province":"Buckinghamshire",
    "sg:tags":[
        "away",
        "meal",
        "outlet",
        "take"
    ],
    "sg:website":"http://www.chatgaontandoori.co.uk",
    "wof:name":"Chatgaon Tandoori",
    "wof:placetype":"venue"
},
  "geometry": {"coordinates":[-0.6098160148,51.7101631165],"type":"Point"}
}