{
  "type": "Feature",
  "properties": {
    "addr:full":"23 Sandwash Close Rainford Indus, Trial Estate St Helens Lancashire WA11 8LY",
    "addr:housenumber":"23",
    "addr:postcode":"wa11 8ly",
    "addr:street":"Sandwash Close;Trial Estate",
    "iso:country":"GB",
    "sg:address":"23 Sandwash Close Rainford Indus, Trial Estate",
    "sg:city":"St Helens",
    "sg:classifiers":[
        {
            "category":"Organizations",
            "subcategory":"Non-profit Organization",
            "type":"Services"
        }
    ],
    "sg:phone":"+44 1744 884626",
    "sg:postcode":"WA11 8LY",
    "sg:province":"Lancashire",
    "sg:tags":[
        "organisation",
        "voluntary",
        "charity"
    ],
    "wof:name":"Northern Friends of Arms",
    "wof:placetype":"venue"
},
  "geometry": {"coordinates":[-2.772113,53.492466],"type":"Point"}
}