{
  "type": "Feature",
  "properties": {
    "addr:full":"4 Deakin Leas Tonbridge Kent TN9 2JU",
    "addr:housenumber":"4",
    "addr:postcode":"tn9 2ju",
    "addr:street":"Deakin Leas Tonbridge",
    "iso:country":"GB",
    "sg:address":"4 Deakin Leas",
    "sg:city":"Tonbridge",
    "sg:classifiers":[
        {
            "category":"Arts & Performance",
            "subcategory":"Music",
            "type":"Entertainment"
        }
    ],
    "sg:postcode":"TN9 2JU",
    "sg:province":"Kent",
    "sg:tags":[
        "mobile",
        "disco"
    ],
    "wof:name":"Shades Discotheques",
    "wof:placetype":"venue"
},
  "geometry": {"coordinates":[0.273942,51.186367],"type":"Point"}
}