{
  "type": "Feature",
  "properties": {
    "addr:full":"25 Cliff View Rd, Cliffsend Ramsgate Kent CT12 5ED",
    "addr:housenumber":"25",
    "addr:postcode":"ct12 5ed",
    "addr:street":"Cliff View Rd;Ramsgate",
    "iso:country":"GB",
    "sg:address":"25 Cliff View Rd, Cliffsend",
    "sg:city":"Ramsgate",
    "sg:classifiers":[
        {
            "category":"Building & Trades",
            "subcategory":"Construction",
            "type":"Services"
        }
    ],
    "sg:postcode":"CT12 5ED",
    "sg:province":"Kent",
    "sg:tags":[
        "builder"
    ],
    "wof:name":"Branson D E",
    "wof:placetype":"venue"
},
  "geometry": {"coordinates":[1.3659700155,51.3348236084],"type":"Point"}
}