{
  "type": "Feature",
  "properties": {
    "addr:full":"6 Ashleigh Close, Barby Rugby Northamptonshire CV23 8UG",
    "addr:housenumber":"6",
    "addr:postcode":"cv23 8ug",
    "addr:street":"Ashleigh Close",
    "iso:country":"GB",
    "sg:address":"6 Ashleigh Close, Barby",
    "sg:city":"Rugby",
    "sg:classifiers":[
        {
            "category":"Professional",
            "type":"Services"
        },
        {
            "category":"Building & Trades",
            "subcategory":"Construction",
            "type":"Services"
        }
    ],
    "sg:postcode":"CV23 8UG",
    "sg:province":"Northamptonshire",
    "sg:tags":[
        "contractor",
        "heating",
        "caterer"
    ],
    "wof:name":"P Devey",
    "wof:placetype":"venue"
},
  "geometry": {"coordinates":[-1.2019519806,52.3310394287],"type":"Point"}
}