{
  "type": "Feature",
  "properties": {
    "addr:full":"125 Longbridge Lane Birmingham West Midlands B31 4LF",
    "addr:housenumber":"125",
    "addr:postcode":"b31 4lf",
    "addr:street":"Longbridge Lane",
    "iso:country":"GB",
    "sg:address":"125 Longbridge Lane",
    "sg:city":"Birmingham",
    "sg:classifiers":[
        {
            "category":"Retail",
            "subcategory":"Auto Repair",
            "type":"Services"
        }
    ],
    "sg:phone":"+44 121 475 1310",
    "sg:postcode":"B31 4LF",
    "sg:province":"West Midlands",
    "sg:tags":[
        "modification",
        "garage",
        "related"
    ],
    "wof:name":"Lodge Hill Autos",
    "wof:placetype":"venue"
},
  "geometry": {"coordinates":[-1.9798979759,52.3957099915],"type":"Point"}
}