{
  "type": "Feature",
  "properties": {
    "iso:country":"GB",
    "sg:address":"55 Kirkgate, Ottley",
    "sg:city":"Leeds",
    "sg:classifiers":[
        {
            "category":"Retail",
            "subcategory":"Laundry & Dry Cleaning",
            "type":"Services"
        }
    ],
    "sg:phone":"+44 1943 463941",
    "sg:postcode":"LS21 3HN",
    "sg:province":"North Yorkshire",
    "sg:tags":[
        "alteration"
    ],
    "wof:name":"Johnson Cleaners U K Ltd.",
    "wof:placetype":"venue"
},
  "geometry": {"coordinates":[-1.694273,53.904266],"type":"Point"}
}