{
  "type": "Feature",
  "properties": {
    "addr:full":"Swan Ho, 52 Poland St West End Hampshire W1V 4HJ",
    "addr:housenumber":"52",
    "addr:postcode":"w1v 4hj",
    "addr:street":"Poland St",
    "iso:country":"GB",
    "sg:address":"Swan Ho, 52 Poland St",
    "sg:city":"West End",
    "sg:classifiers":[
        {
            "category":"Professional",
            "subcategory":"Computer Services",
            "type":"Services"
        }
    ],
    "sg:phone":"+44 20 7287 3877",
    "sg:postcode":"W1V 4HJ",
    "sg:province":"Hampshire",
    "sg:tags":[
        "information"
    ],
    "wof:name":"Talking Media",
    "wof:placetype":"venue"
},
  "geometry": {"coordinates":[-0.1369300038,51.5141220093],"type":"Point"}
}