{
  "type": "Feature",
  "properties": {
    "iso:country":"GB",
    "sg:address":"Carr Road, Wath-upon-dearne",
    "sg:city":"Rotherham",
    "sg:classifiers":[
        {
            "category":"Organizations",
            "subcategory":"Membership Organization",
            "type":"Services"
        }
    ],
    "sg:phone":"+44 1709 872263",
    "sg:postcode":"S63 7AA",
    "sg:province":"South Yorkshire",
    "sg:tags":[
        "club",
        "social"
    ],
    "wof:name":"Dunholme Social Club",
    "wof:placetype":"venue"
},
  "geometry": {"coordinates":[-1.3366190195,53.5014648438],"type":"Point"}
}