{
  "type": "Feature",
  "properties": {
    "iso:country":"GB",
    "sg:address":"Commercial St",
    "sg:city":"Pontypool",
    "sg:classifiers":[
        {
            "category":"Shopping",
            "subcategory":"Stationery & Office Supplies",
            "type":"Retail Goods"
        }
    ],
    "sg:phone":"+44 1495 755232",
    "sg:postcode":"NP4 6JG",
    "sg:province":"Monmouthshire",
    "wof:name":"Hughes Stationers",
    "wof:placetype":"venue"
},
  "geometry": {"coordinates":[-3.040251,51.702118],"type":"Point"}
}