{
  "type": "Feature",
  "properties": {
    "addr:full":"125a Northdown Road, Cliftonville Margate Kent CT9 2QY",
    "addr:housenumber":"125a",
    "addr:postcode":"ct9 2qy",
    "addr:street":"Northdown Road;Margate",
    "iso:country":"GB",
    "sg:address":"125a Northdown Road, Cliftonville",
    "sg:city":"Margate",
    "sg:classifiers":[
        {
            "category":"Personal",
            "subcategory":"Tattoo Parlor",
            "type":"Services"
        }
    ],
    "sg:postcode":"CT9 2QY",
    "sg:province":"Kent",
    "sg:tags":[
        "tattooing",
        "piercing"
    ],
    "wof:name":"The Kent Piercing Clinic",
    "wof:placetype":"venue"
},
  "geometry": {"coordinates":[1.3954119682,51.3883666992],"type":"Point"}
}