{
  "type": "Feature",
  "properties": {
    "iso:country":"GB",
    "sg:address":"38-40 St Stephens Rd",
    "sg:city":"Hounslow",
    "sg:classifiers":[
        {
            "category":"Organizations",
            "subcategory":"Community Association",
            "type":"Services"
        }
    ],
    "sg:phone":"+44 20 8572 8856",
    "sg:postcode":"TW3 2AX",
    "sg:province":"Greater London",
    "sg:tags":[
        "society",
        "housing"
    ],
    "wof:name":"Abbeyfield Hounslow Society",
    "wof:placetype":"venue"
},
  "geometry": {"coordinates":[-0.365404,51.461658],"type":"Point"}
}