{
  "type": "Feature",
  "properties": {
    "addr:full":"26 De Laune Street London Greater London SE17 3UU",
    "addr:postcode":"se17 3uu",
    "addr:street":"26 De Laune Street",
    "iso:country":"GB",
    "sg:address":"26 De Laune Street",
    "sg:city":"London",
    "sg:classifiers":[
        {
            "category":"Social Services",
            "type":"Services"
        }
    ],
    "sg:phone":"+44 20 7582 8082",
    "sg:postcode":"SE17 3UU",
    "sg:province":"Greater London",
    "sg:tags":[
        "educational"
    ],
    "wof:name":"A H A Courses Ltd.",
    "wof:placetype":"venue"
},
  "geometry": {"coordinates":[-0.1060120016,51.486743927],"type":"Point"}
}