{
  "type": "Feature",
  "properties": {
    "addr:full":"Old Boston Yard, Penny Lane, Haydock St Helens Lancashire WA11 9XP",
    "addr:postcode":"wa11 9xp",
    "addr:street":"Penny Lane Haydock",
    "iso:country":"GB",
    "sg:address":"Old Boston Yard, Penny Lane, Haydock",
    "sg:city":"St Helens",
    "sg:classifiers":[
        {
            "category":"Retail",
            "subcategory":"Auto Repair",
            "type":"Services"
        }
    ],
    "sg:phone":"+44 1942 402260",
    "sg:postcode":"WA11 9XP",
    "sg:province":"Lancashire",
    "sg:tags":[
        "bodybuilder",
        "repairer"
    ],
    "wof:name":"Pullman Fleet Services",
    "wof:placetype":"venue"
},
  "geometry": {"coordinates":[-2.6844398975,53.467628479],"type":"Point"}
}