{
  "type": "Feature",
  "properties": {
    "iso:country":"GB",
    "sg:address":"Borlum Farm",
    "sg:city":"Inverness",
    "sg:classifiers":[
        {
            "category":"Education",
            "subcategory":"Special Training",
            "type":"Public Place"
        }
    ],
    "sg:phone":"+44 1456 450588",
    "sg:postcode":"IV63 6XN",
    "sg:province":"Highland",
    "sg:tags":[
        "product",
        "centre"
    ],
    "wof:name":"Bridg'it Venture",
    "wof:placetype":"venue"
},
  "geometry": {"coordinates":[-4.4614500999,57.3279190063],"type":"Point"}
}