{
  "type": "Feature",
  "properties": {
    "addr:full":"Unit 15, Creek Mouth Industrial Estate Barking Essex IG11 0DA",
    "addr:housenumber":"unit 15",
    "addr:postcode":"ig11 0da",
    "addr:street":"Creek Mouth Industrial Estate",
    "iso:country":"GB",
    "sg:address":"Unit 15, Creek Mouth Industrial Estate",
    "sg:city":"Barking",
    "sg:classifiers":[
        {
            "category":"Building & Trades",
            "subcategory":"Construction",
            "type":"Services"
        }
    ],
    "sg:phone":"+44 20 8507 2233",
    "sg:postcode":"IG11 0DA",
    "sg:province":"Essex",
    "sg:tags":[
        "flooring"
    ],
    "wof:name":"Phillips Carpets",
    "wof:placetype":"venue"
},
  "geometry": {"coordinates":[0.104205,51.516819],"type":"Point"}
}