{
  "type": "Feature",
  "properties": {
    "iso:country":"GB",
    "sg:address":"12c Lawhill Road, Law",
    "sg:city":"Carluke",
    "sg:classifiers":[
        {
            "category":"Shopping",
            "subcategory":"Pharmacy",
            "type":"Retail Goods"
        }
    ],
    "sg:phone":"+44 1698 356312",
    "sg:postcode":"ML8 5JQ",
    "sg:province":"South Lanarkshire",
    "sg:tags":[
        "pharmacist",
        "chemist"
    ],
    "wof:name":"Harry Cockburn (Chemists) Ltd.",
    "wof:placetype":"venue"
},
  "geometry": {"coordinates":[-3.8832890987,55.7496490479],"type":"Point"}
}