{
  "type": "Feature",
  "properties": {
    "iso:country":"GB",
    "sg:address":"74 Sheil Rd",
    "sg:city":"Liverpool",
    "sg:classifiers":[
        {
            "category":"Health Services",
            "subcategory":"Dentist",
            "type":"Services"
        }
    ],
    "sg:phone":"+44 151 263 3088",
    "sg:postcode":"L6 3AF",
    "sg:province":"Merseyside",
    "wof:name":"Mr P Bardolia",
    "wof:placetype":"venue"
},
  "geometry": {"coordinates":[-2.9454290867,53.4151992798],"type":"Point"}
}