{
  "type": "Feature",
  "properties": {
    "iso:country":"GB",
    "sg:address":"The Cliffs Convalescent Centre, Old Teignmouth Rd",
    "sg:city":"Dawlish",
    "sg:classifiers":[
        {
            "category":"Health Services",
            "subcategory":"Nursing And Care Facility",
            "type":"Services"
        }
    ],
    "sg:phone":"+44 1626 888416",
    "sg:postcode":"EX7 0NJ",
    "sg:province":"Devon",
    "sg:tags":[
        "home"
    ],
    "wof:name":"Transport Hospital Fund",
    "wof:placetype":"venue"
},
  "geometry": {"coordinates":[-3.444837,50.59795],"type":"Point"}
}