{
  "type": "Feature",
  "properties": {
    "addr:full":"8 Campo Lane Sheffield South Yorkshire S1 2EF",
    "addr:housenumber":"8",
    "addr:postcode":"s1 2ef",
    "addr:street":"Campo Lane",
    "iso:country":"GB",
    "sg:address":"8 Campo Lane",
    "sg:city":"Sheffield",
    "sg:classifiers":[
        {
            "category":"Professional",
            "subcategory":"Lawyer & Legal Services",
            "type":"Services"
        }
    ],
    "sg:phone":"+44 114 272 3655",
    "sg:postcode":"S1 2EF",
    "sg:province":"South Yorkshire",
    "wof:name":"The Sheffield District Incorporated Law Society",
    "wof:placetype":"venue"
},
  "geometry": {"coordinates":[-1.469069,53.383808],"type":"Point"}
}