{
  "type": "Feature",
  "properties": {
    "addr:full":"14 Short Wyre Street Colchester Essex CO1 1LN",
    "addr:housenumber":"14",
    "addr:postcode":"co1 1ln",
    "addr:street":"Short Wyre Street",
    "iso:country":"GB",
    "sg:address":"14 Short Wyre Street",
    "sg:city":"Colchester",
    "sg:classifiers":[
        {
            "category":"Shopping",
            "subcategory":"Clothing, Apparel, & Fashions",
            "type":"Retail Goods"
        }
    ],
    "sg:phone":"+44 1206 579084",
    "sg:postcode":"CO1 1LN",
    "sg:province":"Essex",
    "sg:tags":[
        "shop"
    ],
    "wof:name":"Long Tall Sally Ltd.",
    "wof:placetype":"venue"
},
  "geometry": {"coordinates":[0.902727,51.888119],"type":"Point"}
}