{
  "type": "Feature",
  "properties": {
    "iso:country":"GB",
    "sg:address":"Parkinson House, 17-21 Vaughan Road",
    "sg:city":"Harpenden",
    "sg:classifiers":[
        {
            "category":"Shopping",
            "subcategory":"Clothing, Apparel, & Fashions",
            "type":"Retail Goods"
        }
    ],
    "sg:phone":"+44 1582 765688",
    "sg:postcode":"AL5 4EL",
    "sg:province":"Hertfordshire",
    "sg:tags":[
        "clothing",
        "fabric"
    ],
    "wof:name":"Albion Plc",
    "wof:placetype":"venue"
},
  "geometry": {"coordinates":[-0.353711,51.816086],"type":"Point"}
}