{
  "type": "Feature",
  "properties": {
    "addr:full":"71a Mafeking Avenue Brentford Greater London TW8 0NL",
    "addr:housenumber":"71a",
    "addr:postcode":"tw8 0nl",
    "addr:street":"Mafeking Avenue",
    "iso:country":"GB",
    "sg:address":"71a Mafeking Avenue",
    "sg:city":"Brentford",
    "sg:classifiers":[
        {
            "category":"Military Area",
            "subcategory":"Coast Guard Base",
            "type":"Public Place"
        }
    ],
    "sg:postcode":"TW8 0NL",
    "sg:province":"Greater London",
    "sg:tags":[
        "supplier",
        "meter"
    ],
    "wof:name":"National Contracts",
    "wof:placetype":"venue"
},
  "geometry": {"coordinates":[-0.302117,51.487171],"type":"Point"}
}