{
  "type": "Feature",
  "properties": {
    "addr:full":"Gwalia Workshops, Dulais Road, Pontarddulais Swansea Carmarthenshire SA4 8RH",
    "addr:postcode":"sa4 8rh",
    "addr:street":"Dulais Road",
    "iso:country":"GB",
    "sg:address":"Gwalia Workshops, Dulais Road, Pontarddulais",
    "sg:city":"Swansea",
    "sg:classifiers":[
        {
            "category":"Retail",
            "subcategory":"Auto Repair",
            "type":"Services"
        }
    ],
    "sg:phone":"+44 1792 885540",
    "sg:postcode":"SA4 8RH",
    "sg:province":"Carmarthenshire",
    "sg:tags":[
        "modification",
        "garage"
    ],
    "wof:name":"P Brock Autos",
    "wof:placetype":"venue"
},
  "geometry": {"coordinates":[-4.0357551575,51.7119483948],"type":"Point"}
}