{
  "type": "Feature",
  "properties": {
    "addr:full":"Station Road, Newchapel Stoke-on-trent Cheshire ST7 4QT",
    "addr:postcode":"st7 4qt",
    "addr:street":"Station Road",
    "iso:country":"GB",
    "sg:address":"Station Road, Newchapel",
    "sg:city":"Stoke-on-trent",
    "sg:classifiers":[
        {
            "category":"Bars & Pubs",
            "type":"Food & Drink"
        }
    ],
    "sg:postcode":"ST7 4QT",
    "sg:province":"Cheshire",
    "sg:tags":[
        "pubs",
        "inn"
    ],
    "wof:name":"The Grapes Inn",
    "wof:placetype":"venue"
},
  "geometry": {"coordinates":[-2.2063128948,53.0878562927],"type":"Point"}
}