{
  "type": "Feature",
  "properties": {
    "iso:country":"GB",
    "sg:address":"Amlwch",
    "sg:city":"Penysarn",
    "sg:classifiers":[
        {
            "category":"Government",
            "subcategory":"Post Office",
            "type":"Public Place"
        }
    ],
    "sg:phone":"+44 1407 831658",
    "sg:postcode":"LL69 9YB",
    "sg:province":"Isle of Anglesey",
    "wof:name":"Penysarn Post Office",
    "wof:placetype":"venue"
},
  "geometry": {"coordinates":[-4.3168268204,53.3896789551],"type":"Point"}
}