{
  "type": "Feature",
  "properties": {
    "iso:country":"GB",
    "sg:address":"The Health Centre, Park Dr",
    "sg:city":"Larbert",
    "sg:classifiers":[
        {
            "category":"Health Services",
            "subcategory":"Doctor",
            "type":"Services"
        }
    ],
    "sg:phone":"+44 1324 554136",
    "sg:postcode":"FK5 3BB",
    "sg:province":"Falkirk",
    "sg:tags":[
        "practitioners"
    ],
    "wof:name":"Brown, S",
    "wof:placetype":"venue"
},
  "geometry": {"coordinates":[-3.8243689537,56.0243835449],"type":"Point"}
}