{
  "type": "Feature",
  "properties": {
    "addr:full":"P O Box 243 Fareham Hampshire PO17 5YS",
    "addr:housenumber":"243",
    "addr:postcode":"po17 5ys",
    "addr:street":"P O Box",
    "iso:country":"GB",
    "sg:address":"P O Box 243",
    "sg:city":"Fareham",
    "sg:classifiers":[
        {
            "category":"Real Estate",
            "subcategory":"Developer",
            "type":"Services"
        },
        {
            "category":"Building & Trades",
            "subcategory":"Construction",
            "type":"Services"
        }
    ],
    "sg:phone":"+44 1329 833811",
    "sg:postcode":"PO17 5YS",
    "sg:province":"Hampshire",
    "sg:tags":[
        "builder",
        "property"
    ],
    "wof:name":"Gudgeon Developments Ltd",
    "wof:placetype":"venue"
},
  "geometry": {"coordinates":[-1.187789,50.898479],"type":"Point"}
}