{
  "type": "Feature",
  "properties": {
    "iso:country":"GB",
    "sg:address":"46 Walton Vale",
    "sg:city":"Liverpool",
    "sg:classifiers":[
        {
            "category":"Travel",
            "subcategory":"Travel Agent",
            "type":"Entertainment"
        }
    ],
    "sg:phone":"+44 151 525 6327",
    "sg:postcode":"L9 2BU",
    "sg:province":"Merseyside",
    "wof:name":"Carlson Worldchoice",
    "wof:placetype":"venue"
},
  "geometry": {"coordinates":[-2.961019,53.46204],"type":"Point"}
}