{
  "type": "Feature",
  "properties": {
    "iso:country":"GB",
    "sg:address":"Out Of Hours Service, Primary Care Centre, Devizes Community H",
    "sg:city":"Devizes",
    "sg:classifiers":[
        {
            "category":"Health Services",
            "subcategory":"Doctor",
            "type":"Services"
        }
    ],
    "sg:phone":"+44 1380 729466",
    "sg:postcode":"SN10 1EF",
    "sg:province":"Wiltshire",
    "sg:tags":[
        "practitioners"
    ],
    "wof:name":"Devizes Doctors",
    "wof:placetype":"venue"
},
  "geometry": {"coordinates":[-1.995031,51.351479],"type":"Point"}
}