{
  "type": "Feature",
  "properties": {
    "iso:country":"GB",
    "sg:address":"Harmony House, Pinhoe Road",
    "sg:city":"Exeter",
    "sg:classifiers":[
        {
            "category":"Wholesale",
            "subcategory":"Construction Materials",
            "type":"Manufacturing & Wholesale Goods"
        }
    ],
    "sg:phone":"+44 1392 202297",
    "sg:postcode":"EX4 7HZ",
    "sg:province":"Devon",
    "sg:tags":[
        "merchant",
        "glass"
    ],
    "wof:name":"Harmony Glass & Glazing",
    "wof:placetype":"venue"
},
  "geometry": {"coordinates":[-3.502459,50.731377],"type":"Point"}
}