{
  "type": "Feature",
  "properties": {
    "addr:full":"2 The Triangle, Bitterne Park Southampton Hampshire SO18 1FZ",
    "addr:housenumber":"2",
    "addr:postcode":"so18 1fz",
    "addr:street":"The Triangle",
    "iso:country":"GB",
    "sg:address":"2 The Triangle, Bitterne Park",
    "sg:city":"Southampton",
    "sg:classifiers":[
        {
            "category":"Retail",
            "subcategory":"Repair Shop",
            "type":"Services"
        }
    ],
    "sg:postcode":"SO18 1FZ",
    "sg:province":"Hampshire",
    "sg:tags":[
        "maintenance"
    ],
    "wof:name":"Acer Building Services",
    "wof:placetype":"venue"
},
  "geometry": {"coordinates":[-1.376161,50.924484],"type":"Point"}
}