{
  "type": "Feature",
  "properties": {
    "addr:full":"District Office, Woodlands Rd, Handforth Wilmslow Cheshire SK9 3AU",
    "addr:postcode":"sk9 3au",
    "addr:street":"Woodlands Rd",
    "iso:country":"GB",
    "sg:address":"District Office, Woodlands Rd, Handforth",
    "sg:city":"Wilmslow",
    "sg:classifiers":[
        {
            "category":"Place Of Worship",
            "type":"Public Place"
        }
    ],
    "sg:phone":"+44 1625 523480",
    "sg:postcode":"SK9 3AU",
    "sg:province":"Cheshire",
    "wof:name":"Methodist Church",
    "wof:placetype":"venue"
},
  "geometry": {"coordinates":[-2.216331,53.353123],"type":"Point"}
}