{
  "type": "Feature",
  "properties": {
    "addr:full":"Walker House, Skippers Lane, Skippers Lane Industrial Estate Middlesbrough North Yorkshire TS6 6HA",
    "addr:postcode":"ts6 6ha",
    "addr:street":"Walker;Skippers Lane Skippers Lane Industrial Estate",
    "iso:country":"GB",
    "sg:address":"Walker House, Skippers Lane, Skippers Lane Industrial Estate",
    "sg:city":"Middlesbrough",
    "sg:classifiers":[
        {
            "category":"Wholesale",
            "subcategory":"Toys & Hobbies",
            "type":"Manufacturing & Wholesale Goods"
        }
    ],
    "sg:phone":"+44 1642 460555",
    "sg:postcode":"TS6 6HA",
    "sg:province":"North Yorkshire",
    "sg:tags":[
        "game"
    ],
    "wof:name":"Kebrico Ltd.",
    "wof:placetype":"venue"
},
  "geometry": {"coordinates":[-1.182717,54.576523],"type":"Point"}
}