{
  "type": "Feature",
  "properties": {
    "addr:full":"Crosville, Liverpool Rd Chester Cheshire CH2 1AE",
    "addr:postcode":"ch2 1ae",
    "addr:street":"Crosville Liverpool Rd",
    "iso:country":"GB",
    "sg:address":"Crosville, Liverpool Rd",
    "sg:city":"Chester",
    "sg:classifiers":[
        {
            "category":"Bus Charters",
            "type":"Transportation"
        }
    ],
    "sg:phone":"+44 1244 372535",
    "sg:postcode":"CH2 1AE",
    "sg:province":"Cheshire",
    "sg:tags":[
        "coach"
    ],
    "wof:name":"Womens Safe Transport",
    "wof:placetype":"venue"
},
  "geometry": {"coordinates":[-2.896054,53.213322],"type":"Point"}
}