{
  "type": "Feature",
  "properties": {
    "addr:full":"10-12 Tay Walk, Cumbernauld Glasgow Falkirk G67 1BU",
    "addr:housenumber":"10-12",
    "addr:postcode":"g67 1bu",
    "addr:street":"Tay Walk",
    "iso:country":"GB",
    "sg:address":"10-12 Tay Walk, Cumbernauld",
    "sg:city":"Glasgow",
    "sg:classifiers":[
        {
            "category":"Communications",
            "subcategory":"Newspaper",
            "type":"Services"
        },
        {
            "category":"Wholesale",
            "subcategory":"Books, Periodicals, & Newspapers",
            "type":"Manufacturing & Wholesale Goods"
        }
    ],
    "sg:phone":"+44 1236 725578",
    "sg:postcode":"G67 1BU",
    "sg:province":"Falkirk",
    "sg:tags":[
        "magazine",
        "publishing"
    ],
    "wof:name":"Cumbernauld News",
    "wof:placetype":"venue"
},
  "geometry": {"coordinates":[-3.9907701015,55.9469108582],"type":"Point"}
}