{
  "type": "Feature",
  "properties": {
    "addr:full":"Longfield Clo Whitstable Kent CT5 2SP",
    "addr:postcode":"ct5 2sp",
    "iso:country":"GB",
    "sg:address":"Longfield Clo",
    "sg:city":"Whitstable",
    "sg:classifiers":[
        {
            "category":"Social Services",
            "type":"Services"
        }
    ],
    "sg:phone":"+44 1227 793440",
    "sg:postcode":"CT5 2SP",
    "sg:province":"Kent",
    "wof:name":"Swalecliffe Education Centre",
    "wof:placetype":"venue"
},
  "geometry": {"coordinates":[1.0687539577,51.3606185913],"type":"Point"}
}