{
  "type": "Feature",
  "properties": {
    "iso:country":"GB",
    "sg:address":"20 Sanderson Street",
    "sg:city":"Sheffield",
    "sg:classifiers":[
        {
            "category":"Professional",
            "subcategory":"Engineering",
            "type":"Services"
        }
    ],
    "sg:phone":"+44 114 244 3416",
    "sg:postcode":"S9 2TW",
    "sg:province":"South Yorkshire",
    "wof:name":"M C M Engineering",
    "wof:placetype":"venue"
},
  "geometry": {"coordinates":[-1.434632,53.399796],"type":"Point"}
}