{
  "type": "Feature",
  "properties": {
    "addr:full":"6 North Road Maidenhead Berkshire SL6 1PL",
    "addr:housenumber":"6",
    "addr:postcode":"sl6 1pl",
    "addr:street":"North Road",
    "iso:country":"GB",
    "sg:address":"6 North Road",
    "sg:city":"Maidenhead",
    "sg:classifiers":[
        {
            "category":"Social Services",
            "subcategory":"Adult Care",
            "type":"Services"
        }
    ],
    "sg:phone":"+44 1628 781644",
    "sg:postcode":"SL6 1PL",
    "sg:province":"Berkshire",
    "sg:tags":[
        "day",
        "centre"
    ],
    "wof:name":"Berkshire County Council",
    "wof:placetype":"venue"
},
  "geometry": {"coordinates":[-0.7275990248,51.5220489502],"type":"Point"}
}