{
  "type": "Feature",
  "properties": {
    "addr:full":"181 Clayfield View, Mexborough Rotherham South Yorkshire S64 0PR",
    "addr:housenumber":"181",
    "addr:postcode":"s64 0pr",
    "addr:street":"Clayfield View",
    "iso:country":"GB",
    "sg:address":"181 Clayfield View, Mexborough",
    "sg:city":"Rotherham",
    "sg:classifiers":[
        {
            "category":"Building & Trades",
            "subcategory":"Construction",
            "type":"Services"
        }
    ],
    "sg:phone":"+44 1709 583927",
    "sg:postcode":"S64 0PR",
    "sg:province":"South Yorkshire",
    "sg:tags":[
        "decorator",
        "painter"
    ],
    "wof:name":"Walter Boldan",
    "wof:placetype":"venue"
},
  "geometry": {"coordinates":[-1.2670559883,53.5005111694],"type":"Point"}
}