{
  "type": "Feature",
  "properties": {
    "addr:full":"55 Thistlewaite Road London Greater London E5 0DJ",
    "addr:housenumber":"55",
    "addr:postcode":"e5 0dj",
    "addr:street":"Thistlewaite Road",
    "iso:country":"GB",
    "sg:address":"55 Thistlewaite Road",
    "sg:city":"London",
    "sg:classifiers":[
        {
            "category":"Building & Trades",
            "subcategory":"Construction",
            "type":"Services"
        }
    ],
    "sg:phone":"+44 20 7258 1778",
    "sg:postcode":"E5 0DJ",
    "sg:province":"Greater London",
    "sg:tags":[
        "builder"
    ],
    "wof:name":"Lincoln White & Sons Ltd.",
    "wof:placetype":"venue"
},
  "geometry": {"coordinates":[-0.0533730015,51.558216095],"type":"Point"}
}