{
  "type": "Feature",
  "properties": {
    "addr:full":"Heanor Gate Industrial Estate, Delves Road Heanor Derbyshire DE7 5SJ",
    "addr:postcode":"de7 5sj",
    "addr:street":"Heanor Gate Industrial;Delves Road",
    "iso:country":"GB",
    "sg:address":"Heanor Gate Industrial Estate, Delves Road",
    "sg:city":"Heanor",
    "sg:classifiers":[
        {
            "category":"Professional",
            "subcategory":"Printing & Photocopies",
            "type":"Services"
        }
    ],
    "sg:postcode":"DE7 5SJ",
    "sg:province":"Derbyshire",
    "sg:tags":[
        "printer"
    ],
    "wof:name":"Heanor Gate Printing Ltd.",
    "wof:placetype":"venue"
},
  "geometry": {"coordinates":[-1.3534339666,53.0137367249],"type":"Point"}
}