{
  "type": "Feature",
  "properties": {
    "iso:country":"GB",
    "sg:address":"Stable Cottage, Buckland Manor, Southampton Road",
    "sg:city":"Lymington",
    "sg:classifiers":[
        {
            "category":"Professional",
            "subcategory":"Lawyer & Legal Services",
            "type":"Services"
        }
    ],
    "sg:phone":"+44 1590 672595",
    "sg:postcode":"SO41 8NP",
    "sg:province":"Hampshire",
    "sg:tags":[
        "solicitor"
    ],
    "wof:name":"Clive Sutton Solicitor",
    "wof:placetype":"venue"
},
  "geometry": {"coordinates":[-1.538910985,50.7589378357],"type":"Point"}
}