{
  "type": "Feature",
  "properties": {
    "addr:full":"40 Homesdale Road Bromley Kent BR2 9LD",
    "addr:housenumber":"40",
    "addr:postcode":"br2 9ld",
    "addr:street":"Homesdale Road",
    "iso:country":"GB",
    "sg:address":"40 Homesdale Road",
    "sg:city":"Bromley",
    "sg:classifiers":[
        {
            "category":"Shopping",
            "subcategory":"Stationery & Office Supplies",
            "type":"Retail Goods"
        }
    ],
    "sg:phone":"+44 20 8466 9899",
    "sg:postcode":"BR2 9LD",
    "sg:province":"Kent",
    "sg:tags":[
        "equipment"
    ],
    "wof:name":"G D Office Furniture",
    "wof:placetype":"venue"
},
  "geometry": {"coordinates":[0.029131,51.396786],"type":"Point"}
}