{
  "type": "Feature",
  "properties": {
    "addr:full":"287 Leicester Road Wigston Leicestershire LE18 1JW",
    "addr:housenumber":"287",
    "addr:postcode":"le18 1jw",
    "addr:street":"Leicester Road",
    "iso:country":"GB",
    "sg:address":"287 Leicester Road",
    "sg:city":"Wigston",
    "sg:classifiers":[
        {
            "category":"Health Services",
            "subcategory":"Dentist",
            "type":"Services"
        }
    ],
    "sg:phone":"+44 116 281 2935",
    "sg:postcode":"LE18 1JW",
    "sg:province":"Leicestershire",
    "wof:name":"Dental Practice",
    "wof:placetype":"venue"
},
  "geometry": {"coordinates":[-1.1110899448,52.5959396362],"type":"Point"}
}