{
  "type": "Feature",
  "properties": {
    "addr:full":"60 Midland Rd Wellingborough Northamptonshire NN8 1LU",
    "addr:housenumber":"60",
    "addr:postcode":"nn8 1lu",
    "addr:street":"Midland Rd",
    "iso:country":"GB",
    "sg:address":"60 Midland Rd",
    "sg:city":"Wellingborough",
    "sg:classifiers":[
        {
            "category":"Professional",
            "subcategory":"Accounting & Tax Preparation",
            "type":"Services"
        }
    ],
    "sg:phone":"+44 1933 222847",
    "sg:postcode":"NN8 1LU",
    "sg:province":"Northamptonshire",
    "sg:tags":[
        "accountant",
        "activity"
    ],
    "wof:name":"Thompson & Co",
    "wof:placetype":"venue"
},
  "geometry": {"coordinates":[-0.6863319874,52.3011131287],"type":"Point"}
}