{
  "type": "Feature",
  "properties": {
    "addr:full":"Chiddingstone Cause Way Tonbridge Kent TN11 8JP",
    "addr:postcode":"tn11 8jp",
    "addr:street":"Cause Way",
    "iso:country":"GB",
    "sg:address":"Chiddingstone Cause Way",
    "sg:city":"Tonbridge",
    "sg:classifiers":[
        {
            "category":"Shopping",
            "subcategory":"Pharmacy",
            "type":"Retail Goods"
        }
    ],
    "sg:phone":"+44 1892 871111",
    "sg:postcode":"TN11 8JP",
    "sg:province":"Kent",
    "sg:tags":[
        "medical"
    ],
    "wof:name":"Clayton First Aid Ltd.",
    "wof:placetype":"venue"
},
  "geometry": {"coordinates":[0.16981,51.198608],"type":"Point"}
}