{
  "type": "Feature",
  "properties": {
    "addr:full":"128 Burnham Rd Hockley Essex SS5 6HQ",
    "addr:housenumber":"128",
    "addr:postcode":"ss5 6hq",
    "addr:street":"Burnham Rd",
    "iso:country":"GB",
    "sg:address":"128 Burnham Rd",
    "sg:city":"Hockley",
    "sg:classifiers":[
        {
            "category":"Home & Garden",
            "subcategory":"Home Furnishings",
            "type":"Retail Goods"
        }
    ],
    "sg:phone":"+44 1702 231214",
    "sg:postcode":"SS5 6HQ",
    "sg:province":"Essex",
    "sg:tags":[
        "awning",
        "canopy",
        "blinds"
    ],
    "wof:name":"Harmony Blinds",
    "wof:placetype":"venue"
},
  "geometry": {"coordinates":[0.619227,51.622738],"type":"Point"}
}