{
  "type": "Feature",
  "properties": {
    "addr:full":"2nd Floor Sandringham House, 1 Exeter Park Road Bournemouth Dorset BH2 5BZ",
    "addr:housenumber":"2nd floor sandringham;1",
    "addr:postcode":"bh2 5bz",
    "addr:street":"Exeter Park Road",
    "iso:country":"GB",
    "sg:address":"2nd Floor Sandringham House, 1 Exeter Park Road",
    "sg:city":"Bournemouth",
    "sg:classifiers":[
        {
            "category":"Real Estate",
            "subcategory":"Real Estate Agent",
            "type":"Services"
        }
    ],
    "sg:phone":"+44 1202 299770",
    "sg:postcode":"BH2 5BZ",
    "sg:province":"Dorset",
    "wof:name":"Fox & Sons Estate Agents",
    "wof:placetype":"venue"
},
  "geometry": {"coordinates":[-1.878921032,50.7181549072],"type":"Point"}
}