{
  "type": "Feature",
  "properties": {
    "addr:full":"33 High Street Pontypool Monmouthshire NP4 6HB",
    "addr:housenumber":"33",
    "addr:postcode":"np4 6hb",
    "addr:street":"High Street",
    "iso:country":"GB",
    "sg:address":"33 High Street",
    "sg:city":"Pontypool",
    "sg:classifiers":[
        {
            "category":"Government",
            "subcategory":"Post Office",
            "type":"Public Place"
        }
    ],
    "sg:phone":"+44 1495 755567",
    "sg:postcode":"NP4 6HB",
    "sg:province":"Monmouthshire",
    "wof:name":"Pontypool Post Office",
    "wof:placetype":"venue"
},
  "geometry": {"coordinates":[-3.047077,51.700512],"type":"Point"}
}