{
  "type": "Feature",
  "properties": {
    "iso:country":"GB",
    "sg:address":"55 North View Road",
    "sg:city":"London",
    "sg:classifiers":[
        {
            "category":"Professional",
            "subcategory":"Art Services",
            "type":"Services"
        }
    ],
    "sg:phone":"+44 20 8348 3050",
    "sg:postcode":"N8 7LN",
    "sg:province":"Greater London",
    "sg:tags":[
        "photographer"
    ],
    "wof:name":"Phillip Bier Photography",
    "wof:placetype":"venue"
},
  "geometry": {"coordinates":[-0.122356,51.591587],"type":"Point"}
}