{
  "type": "Feature",
  "properties": {
    "iso:country":"GB",
    "sg:address":"70 Ratcliffe Gate",
    "sg:city":"Mansfield",
    "sg:classifiers":[
        {
            "category":"Cafe",
            "type":"Food & Drink"
        }
    ],
    "sg:phone":"+44 1623 636812",
    "sg:postcode":"NG18 2JL",
    "sg:province":"Nottinghamshire",
    "sg:tags":[
        "tea",
        "snack",
        "bar",
        "room"
    ],
    "wof:name":"Family Bakers",
    "wof:placetype":"venue"
},
  "geometry": {"coordinates":[-1.1868150234,53.142074585],"type":"Point"}
}