{
  "type": "Feature",
  "properties": {
    "iso:country":"GB",
    "sg:address":"7 Galgate",
    "sg:city":"Barnard Castle",
    "sg:classifiers":[
        {
            "category":"Bars & Pubs",
            "type":"Food & Drink"
        }
    ],
    "sg:postcode":"DL12 8EQ",
    "sg:province":"Cumbria",
    "sg:tags":[
        "pubs",
        "inn"
    ],
    "wof:name":"The Three Horse Shoes",
    "wof:placetype":"venue"
},
  "geometry": {"coordinates":[-1.924184,54.544605],"type":"Point"}
}