{
  "type": "Feature",
  "properties": {
    "addr:full":"13 The Smithfield Centre Leek Staffordshire ST13 5JW",
    "addr:housenumber":"13",
    "addr:postcode":"st13 5jw",
    "addr:street":"The Smithfield Centre",
    "iso:country":"GB",
    "sg:address":"13 The Smithfield Centre",
    "sg:city":"Leek",
    "sg:classifiers":[
        {
            "category":"Fast Food",
            "type":"Food & Drink"
        }
    ],
    "sg:postcode":"ST13 5JW",
    "sg:province":"Staffordshire",
    "sg:tags":[
        "away",
        "take"
    ],
    "wof:name":"Tasty Take Away",
    "wof:placetype":"venue"
},
  "geometry": {"coordinates":[-2.0218648911,53.1051330566],"type":"Point"}
}