{
  "type": "Feature",
  "properties": {
    "iso:country":"GB",
    "sg:address":"13 Victoria Square",
    "sg:city":"Droitwich",
    "sg:classifiers":[
        {
            "category":"Real Estate",
            "subcategory":"Real Estate Agent",
            "type":"Services"
        }
    ],
    "sg:phone":"+44 1905 772357",
    "sg:postcode":"WR9 8DE",
    "sg:province":"Worcestershire",
    "wof:name":"Evans & Jennings",
    "wof:placetype":"venue"
},
  "geometry": {"coordinates":[-2.150449,52.267109],"type":"Point"}
}