{
  "type": "Feature",
  "properties": {
    "addr:full":"12 Mair Court Rotherham South Yorkshire S60 3BJ",
    "addr:housenumber":"12",
    "addr:postcode":"s60 3bj",
    "addr:street":"Mair Court",
    "iso:country":"GB",
    "sg:address":"12 Mair Court",
    "sg:city":"Rotherham",
    "sg:classifiers":[
        {
            "category":"Professional",
            "subcategory":"Management & Consulting",
            "type":"Services"
        }
    ],
    "sg:postcode":"S60 3BJ",
    "sg:province":"South Yorkshire",
    "sg:tags":[
        "consultant",
        "business"
    ],
    "wof:name":"Applied Programming Consultancy Ltd.",
    "wof:placetype":"venue"
},
  "geometry": {"coordinates":[-1.3335520029,53.4093132019],"type":"Point"}
}