{
  "type": "Feature",
  "properties": {
    "iso:country":"GB",
    "sg:address":"46 Helmsdale Cl0, Tilehurst",
    "sg:city":"Reading",
    "sg:classifiers":[
        {
            "category":"Parking",
            "type":"Transportation"
        }
    ],
    "sg:phone":"+44 118 941 0858",
    "sg:postcode":"RG3 2PS",
    "sg:province":"Berkshire",
    "sg:tags":[
        "car",
        "valet"
    ],
    "wof:name":"D J Mobile Car Valeting",
    "wof:placetype":"venue"
},
  "geometry": {"coordinates":[-1.0365600586,51.4607696533],"type":"Point"}
}