{
  "type": "Feature",
  "properties": {
    "addr:full":"29 Chaucer Road Sittingbourne Kent ME10 1EZ",
    "addr:housenumber":"29",
    "addr:postcode":"me10 1ez",
    "addr:street":"Chaucer Road",
    "iso:country":"GB",
    "sg:address":"29 Chaucer Road",
    "sg:city":"Sittingbourne",
    "sg:classifiers":[
        {
            "category":"Food & Beverages",
            "subcategory":"Supermarket",
            "type":"Retail Goods"
        }
    ],
    "sg:phone":"+44 1795 472677",
    "sg:postcode":"ME10 1EZ",
    "sg:province":"Kent",
    "wof:name":"Happy Shopper",
    "wof:placetype":"venue"
},
  "geometry": {"coordinates":[0.725006,51.334686],"type":"Point"}
}