{
  "type": "Feature",
  "properties": {
    "addr:full":"635 Watford Way, Apex Corner London Greater London NW7 3JR",
    "addr:housenumber":"635",
    "addr:postcode":"nw7 3jr",
    "addr:street":"Watford Way;Corner",
    "iso:country":"GB",
    "sg:address":"635 Watford Way, Apex Corner",
    "sg:city":"London",
    "sg:classifiers":[
        {
            "category":"Shopping",
            "subcategory":"Clothing, Apparel, & Fashions",
            "type":"Retail Goods"
        }
    ],
    "sg:phone":"+44 20 8906 1661",
    "sg:postcode":"NW7 3JR",
    "sg:province":"Greater London",
    "sg:tags":[
        "menswear"
    ],
    "wof:name":"Eurosuits Ltd.",
    "wof:placetype":"venue"
},
  "geometry": {"coordinates":[-0.250011,51.619129],"type":"Point"}
}