{
  "type": "Feature",
  "properties": {
    "iso:country":"GB",
    "sg:address":"Old Fire Station, Mill Street",
    "sg:city":"Tewkesbury",
    "sg:classifiers":[
        {
            "category":"Professional",
            "subcategory":"Accounting & Tax Preparation",
            "type":"Services"
        }
    ],
    "sg:postcode":"GL20 5SB",
    "sg:province":"Gloucestershire",
    "sg:tags":[
        "accountant"
    ],
    "wof:name":"Morgan & Co.",
    "wof:placetype":"venue"
},
  "geometry": {"coordinates":[-2.149463,51.992958],"type":"Point"}
}