{
  "type": "Feature",
  "properties": {
    "addr:full":"Inchrorie, Fodderty Strathpeffer Highland IV14 9AD",
    "addr:postcode":"iv14 9ad",
    "iso:country":"GB",
    "sg:address":"Inchrorie, Fodderty",
    "sg:city":"Strathpeffer",
    "sg:classifiers":[
        {
            "category":"Building & Trades",
            "subcategory":"Cleaning & Sanitation",
            "type":"Services"
        }
    ],
    "sg:phone":"+44 1997 421401",
    "sg:postcode":"IV14 9AD",
    "sg:province":"Highland",
    "sg:tags":[
        "sweep",
        "chimney"
    ],
    "wof:name":"A S M S",
    "wof:placetype":"venue"
},
  "geometry": {"coordinates":[-4.5386638641,57.5871696472],"type":"Point"}
}