{
  "type": "Feature",
  "properties": {
    "addr:full":"30 Kingsway, Waterloo Liverpool Merseyside L22 4RQ",
    "addr:housenumber":"30",
    "addr:postcode":"l22 4rq",
    "addr:street":"Kingsway",
    "iso:country":"GB",
    "sg:address":"30 Kingsway, Waterloo",
    "sg:city":"Liverpool",
    "sg:classifiers":[
        {
            "category":"Health Services",
            "subcategory":"Doctor",
            "type":"Services"
        }
    ],
    "sg:phone":"+44 151 928 8668",
    "sg:postcode":"L22 4RQ",
    "sg:province":"Merseyside",
    "sg:tags":[
        "practitioners"
    ],
    "wof:name":"C.R Shaw",
    "wof:placetype":"venue"
},
  "geometry": {"coordinates":[-3.020597,53.481098],"type":"Point"}
}