{
  "type": "Feature",
  "properties": {
    "addr:full":"Blue House, Horsham Road, Forest Grn Dorking Surrey RH5 5SH",
    "addr:postcode":"rh5 5sh",
    "addr:street":"Horsham Road",
    "iso:country":"GB",
    "sg:address":"Blue House, Horsham Road, Forest Grn",
    "sg:city":"Dorking",
    "sg:classifiers":[
        {
            "category":"Professional",
            "subcategory":"Management & Consulting",
            "type":"Services"
        }
    ],
    "sg:phone":"+44 1306 621333",
    "sg:postcode":"RH5 5SH",
    "sg:province":"Surrey",
    "sg:tags":[
        "marketing",
        "consultant"
    ],
    "wof:name":"Indigo Wood Ltd.",
    "wof:placetype":"venue"
},
  "geometry": {"coordinates":[-0.3177259862,51.1606063843],"type":"Point"}
}