{
  "type": "Feature",
  "properties": {
    "addr:full":"156 Rein Road, West Ardsley Wakefield West Yorkshire WF3 1JD",
    "addr:housenumber":"156",
    "addr:postcode":"wf3 1jd",
    "addr:street":"Rein Road West Ardsley",
    "iso:country":"GB",
    "sg:address":"156 Rein Road, West Ardsley",
    "sg:city":"Wakefield",
    "sg:classifiers":[
        {
            "category":"Building & Trades",
            "subcategory":"Construction",
            "type":"Services"
        }
    ],
    "sg:postcode":"WF3 1JD",
    "sg:province":"West Yorkshire",
    "sg:tags":[
        "decorator",
        "painter"
    ],
    "wof:name":"D Hall",
    "wof:placetype":"venue"
},
  "geometry": {"coordinates":[-1.586264,53.727249],"type":"Point"}
}