{
  "type": "Feature",
  "properties": {
    "iso:country":"GB",
    "sg:address":"1 Marble Arch",
    "sg:city":"West End",
    "sg:classifiers":[
        {
            "category":"Travel",
            "subcategory":"Travel Agent",
            "type":"Entertainment"
        }
    ],
    "sg:phone":"+44 20 7530 7100",
    "sg:postcode":"W1H 8DP",
    "sg:province":"Greater London",
    "wof:name":"Thomas Cook Travel",
    "wof:placetype":"venue"
},
  "geometry": {"coordinates":[-0.15961,51.516178],"type":"Point"}
}