{
  "type": "Feature",
  "properties": {
    "iso:country":"GB",
    "sg:address":"3 Oldmarket Place",
    "sg:city":"Banff",
    "sg:classifiers":[
        {
            "category":"Real Estate",
            "subcategory":"Architect",
            "type":"Services"
        }
    ],
    "sg:phone":"+44 1261 812823",
    "sg:postcode":"AB45 1HE",
    "sg:province":"Aberdeenshire",
    "sg:tags":[
        "architectural"
    ],
    "wof:name":"G J Philip & Associates",
    "wof:placetype":"venue"
},
  "geometry": {"coordinates":[-2.518013,57.664837],"type":"Point"}
}