{
  "type": "Feature",
  "properties": {
    "iso:country":"GB",
    "sg:address":"Marsh View Farm, Hulver Road",
    "sg:city":"Beccles",
    "sg:classifiers":[
        {
            "category":"Sports & Exercise",
            "subcategory":"Swimming Pool",
            "type":"Entertainment"
        }
    ],
    "sg:phone":"+44 1502 476885",
    "sg:postcode":"NR34 7LA",
    "sg:province":"Norfolk",
    "sg:tags":[
        "tank",
        "septic"
    ],
    "wof:name":"Henstead Liquid Waste Disposal",
    "wof:placetype":"venue"
},
  "geometry": {"coordinates":[1.6303800344,52.4245262146],"type":"Point"}
}