{
  "type": "Feature",
  "properties": {
    "addr:full":"108 Dovecot Street Stockton-on-tees Durham TS18 1HG",
    "addr:housenumber":"108",
    "addr:postcode":"ts18 1hg",
    "addr:street":"Dovecot Street",
    "iso:country":"GB",
    "sg:address":"108 Dovecot Street",
    "sg:city":"Stockton-on-tees",
    "sg:classifiers":[
        {
            "category":"Personal",
            "subcategory":"Beauty Salon",
            "type":"Services"
        }
    ],
    "sg:phone":"+44 1642 670119",
    "sg:postcode":"TS18 1HG",
    "sg:province":"Durham",
    "sg:tags":[
        "unisex",
        "hairdresser"
    ],
    "wof:name":"Marie Ingladew",
    "wof:placetype":"venue"
},
  "geometry": {"coordinates":[-1.3202480078,54.5641975403],"type":"Point"}
}