{
  "type": "Feature",
  "properties": {
    "addr:full":"Cheapside Bridgend Bridgend CF31 3UN",
    "addr:postcode":"cf31 3un",
    "addr:street":"Cheapside",
    "iso:country":"GB",
    "sg:address":"Cheapside",
    "sg:city":"Bridgend",
    "sg:classifiers":[
        {
            "category":"Food & Beverages",
            "subcategory":"Meat & Fish",
            "type":"Retail Goods"
        }
    ],
    "sg:phone":"+44 1656 655066",
    "sg:postcode":"CF31 3UN",
    "sg:province":"Bridgend",
    "sg:tags":[
        "butcher"
    ],
    "wof:name":"Dewhurst Butchers Ltd.",
    "wof:placetype":"venue"
},
  "geometry": {"coordinates":[-3.5745000839,51.5047988892],"type":"Point"}
}