{
  "type": "Feature",
  "properties": {
    "iso:country":"GB",
    "sg:address":"25 Kenyan Road",
    "sg:city":"Nelson",
    "sg:classifiers":[
        {
            "category":"Retail",
            "subcategory":"Auto Repair",
            "type":"Services"
        }
    ],
    "sg:postcode":"BB9 5SP",
    "sg:province":"Lancashire",
    "sg:tags":[
        "modification",
        "garage"
    ],
    "wof:name":"Alan Bennett",
    "wof:placetype":"venue"
},
  "geometry": {"coordinates":[-2.233706,53.83226],"type":"Point"}
}