{
  "type": "Feature",
  "properties": {
    "addr:full":"35 Long Meadow Skipton Lancashire BD23 1BH",
    "addr:housenumber":"35",
    "addr:postcode":"bd23 1bh",
    "addr:street":"Long Meadow",
    "iso:country":"GB",
    "sg:address":"35 Long Meadow",
    "sg:city":"Skipton",
    "sg:classifiers":[
        {
            "category":"Utilities",
            "type":"Services"
        }
    ],
    "sg:phone":"+44 1274 759893",
    "sg:postcode":"BD23 1BH",
    "sg:province":"Lancashire",
    "sg:tags":[
        "internet"
    ],
    "wof:name":"Steadfast Computers Ltd.",
    "wof:placetype":"venue"
},
  "geometry": {"coordinates":[-2.005822897,53.9667701721],"type":"Point"}
}