{
  "type": "Feature",
  "properties": {
    "iso:country":"GB",
    "sg:address":"4b Eden Gro Road, Byfleet",
    "sg:city":"West Byfleet",
    "sg:classifiers":[
        {
            "category":"Building & Trades",
            "subcategory":"Construction",
            "type":"Services"
        }
    ],
    "sg:postcode":"KT14 7PH",
    "sg:province":"Surrey",
    "sg:tags":[
        "decorator",
        "painter"
    ],
    "wof:name":"Christopher White",
    "wof:placetype":"venue"
},
  "geometry": {"coordinates":[-0.4731259942,51.3366508484],"type":"Point"}
}