{
  "type": "Feature",
  "properties": {
    "addr:full":"Unit 6 Village Farm Industrial Estate, Pyle Bridgend Bridgend CF33 6BJ",
    "addr:housenumber":"unit 6;estate",
    "addr:postcode":"cf33 6bj",
    "addr:street":"Village;Pyle",
    "iso:country":"GB",
    "sg:address":"Unit 6 Village Farm Industrial Estate, Pyle",
    "sg:city":"Bridgend",
    "sg:classifiers":[
        {
            "category":"Building & Trades",
            "subcategory":"Equipment Rental",
            "type":"Services"
        }
    ],
    "sg:postcode":"CF33 6BJ",
    "sg:province":"Bridgend",
    "sg:tags":[
        "plant",
        "machinery"
    ],
    "wof:name":"C B L",
    "wof:placetype":"venue"
},
  "geometry": {"coordinates":[-3.687571,51.524128],"type":"Point"}
}