{
  "type": "Feature",
  "properties": {
    "addr:full":"8 Tudor Place Blackpool Lancashire FY4 1PQ",
    "addr:housenumber":"8",
    "addr:postcode":"fy4 1pq",
    "addr:street":"Tudor Place",
    "iso:country":"GB",
    "sg:address":"8 Tudor Place",
    "sg:city":"Blackpool",
    "sg:classifiers":[
        {
            "category":"Travel",
            "subcategory":"Hotels & Motels",
            "type":"Entertainment"
        }
    ],
    "sg:postcode":"FY4 1PQ",
    "sg:province":"Lancashire",
    "sg:tags":[
        "house",
        "guest"
    ],
    "wof:name":"Kingsmead Private Hotel",
    "wof:placetype":"venue"
},
  "geometry": {"coordinates":[-3.055328,53.78458],"type":"Point"}
}