{
  "type": "Feature",
  "properties": {
    "iso:country":"GB",
    "sg:address":"Nyddfa Yard, Commercial Street",
    "sg:city":"Blackwood",
    "sg:classifiers":[
        {
            "category":"Building & Trades",
            "subcategory":"Construction",
            "type":"Services"
        }
    ],
    "sg:phone":"+44 1443 875858",
    "sg:postcode":"NP12 3UZ",
    "sg:province":"Caerphilly",
    "sg:tags":[
        "builder"
    ],
    "wof:name":"Bernard Davies",
    "wof:placetype":"venue"
},
  "geometry": {"coordinates":[-3.223859,51.668449],"type":"Point"}
}