{
  "type": "Feature",
  "properties": {
    "addr:full":"Redhills Road, Milton Stoke-on-trent Staffordshire ST2 7NJ",
    "addr:postcode":"staffordshire st2 7nj",
    "addr:street":"Redhills Road",
    "iso:country":"GB",
    "sg:address":"Redhills Road, Milton",
    "sg:city":"Stoke-on-trent",
    "sg:classifiers":[
        {
            "category":"Building & Trades",
            "subcategory":"Cleaning & Sanitation",
            "type":"Services"
        }
    ],
    "sg:phone":"+44 1782 536895",
    "sg:postcode":"ST2 7NJ",
    "sg:province":"Staffordshire",
    "sg:tags":[
        "blast"
    ],
    "wof:name":"Ferro Blast Ltd.",
    "wof:placetype":"venue"
},
  "geometry": {"coordinates":[-2.152696,53.045212],"type":"Point"}
}