{
  "type": "Feature",
  "properties": {
    "iso:country":"GB",
    "sg:address":"249a Broomfield Rd",
    "sg:city":"Chelmsford",
    "sg:classifiers":[
        {
            "category":"Banks & Credit Unions",
            "subcategory":"Financial Services",
            "type":"Services"
        }
    ],
    "sg:phone":"+44 1245 496050",
    "sg:postcode":"CM1 4DP",
    "sg:province":"Essex",
    "sg:tags":[
        "consultant"
    ],
    "wof:name":"McGee Financial Services Ltd",
    "wof:placetype":"venue"
},
  "geometry": {"coordinates":[0.468596,51.751068],"type":"Point"}
}