{
  "type": "Feature",
  "properties": {
    "addr:full":"25-31 Market Place Henley-on-thames Berkshire RG9 2AA",
    "addr:housenumber":"25-31",
    "addr:postcode":"rg9 2aa",
    "addr:street":"Market Place",
    "iso:country":"GB",
    "sg:address":"25-31 Market Place",
    "sg:city":"Henley-on-thames",
    "sg:classifiers":[
        {
            "category":"Shopping",
            "subcategory":"Department Store",
            "type":"Retail Goods"
        }
    ],
    "sg:phone":"+44 1491 576969",
    "sg:postcode":"RG9 2AA",
    "sg:province":"Berkshire",
    "wof:name":"Facy of Henley (Properties) Ltd.",
    "wof:placetype":"venue"
},
  "geometry": {"coordinates":[-0.905515,51.537277],"type":"Point"}
}