{
  "type": "Feature",
  "properties": {
    "iso:country":"GB",
    "sg:address":"697 Llangyfelach Road, Treboeth",
    "sg:city":"Swansea",
    "sg:classifiers":[
        {
            "category":"Shopping",
            "subcategory":"Pharmacy",
            "type":"Retail Goods"
        }
    ],
    "sg:phone":"+44 1792 771646",
    "sg:postcode":"SA5 9EL",
    "sg:province":"Swansea",
    "sg:tags":[
        "pharmacist",
        "chemist"
    ],
    "wof:name":"W A & J B Lewis",
    "wof:placetype":"venue"
},
  "geometry": {"coordinates":[-3.948479,51.651718],"type":"Point"}
}