{
  "type": "Feature",
  "properties": {
    "addr:full":"10 High Street, Hucknall Nottingham Nottinghamshire NG15 7HD",
    "addr:housenumber":"10",
    "addr:postcode":"ng15 7hd",
    "addr:street":"High Street",
    "iso:country":"GB",
    "sg:address":"10 High Street, Hucknall",
    "sg:city":"Nottingham",
    "sg:classifiers":[
        {
            "category":"Food & Beverages",
            "subcategory":"Bakery",
            "type":"Retail Goods"
        }
    ],
    "sg:phone":"+44 115 955 0136",
    "sg:postcode":"NG15 7HD",
    "sg:province":"Nottinghamshire",
    "sg:tags":[
        "confectionery"
    ],
    "wof:name":"F & R Marshall",
    "wof:placetype":"venue"
},
  "geometry": {"coordinates":[-1.2005690336,53.0372200012],"type":"Point"}
}