{
  "type": "Feature",
  "properties": {
    "addr:full":"5a Stanhope Crescent, Arnold Nottingham Nottinghamshire NG5 7AZ",
    "addr:housenumber":"5a",
    "addr:postcode":"ng5 7az",
    "addr:street":"Stanhope Crescent",
    "iso:country":"GB",
    "sg:address":"5a Stanhope Crescent, Arnold",
    "sg:city":"Nottingham",
    "sg:classifiers":[
        {
            "category":"Personal",
            "subcategory":"Beauty Salon",
            "type":"Services"
        }
    ],
    "sg:phone":"+44 115 955 0355",
    "sg:postcode":"NG5 7AZ",
    "sg:province":"Nottinghamshire",
    "sg:tags":[
        "lady",
        "hairdresser"
    ],
    "wof:name":"Headlines",
    "wof:placetype":"venue"
},
  "geometry": {"coordinates":[-1.1331549883,53.0066375732],"type":"Point"}
}