{
  "type": "Feature",
  "properties": {
    "addr:full":"Canal Mill, Cheadle Road Uttoxeter Derbyshire ST14 7BS",
    "addr:postcode":"st14 7bs",
    "addr:street":"Canal Mill Cheadle Road",
    "iso:country":"GB",
    "sg:address":"Canal Mill, Cheadle Road",
    "sg:city":"Uttoxeter",
    "sg:classifiers":[
        {
            "category":"Shopping",
            "subcategory":"Computers & Home Electronics",
            "type":"Retail Goods"
        }
    ],
    "sg:phone":"+44 1889 569945",
    "sg:postcode":"ST14 7BS",
    "sg:province":"Derbyshire",
    "wof:name":"Forsbrook Furniture Ltd.",
    "wof:placetype":"venue"
},
  "geometry": {"coordinates":[-1.8696440458,52.896522522],"type":"Point"}
}