{
  "type": "Feature",
  "properties": {
    "iso:country":"GB",
    "sg:address":"14 Church Rd",
    "sg:city":"Sidcup",
    "sg:classifiers":[
        {
            "category":"Building & Trades",
            "subcategory":"Plumbing",
            "type":"Services"
        }
    ],
    "sg:phone":"+44 20 8302 4212",
    "sg:postcode":"DA14 6BX",
    "sg:province":"Kent",
    "sg:tags":[
        "merchant",
        "plumbers'"
    ],
    "wof:name":"Plumbing Trade Centre",
    "wof:placetype":"venue"
},
  "geometry": {"coordinates":[0.1050830036,51.4244346619],"type":"Point"}
}