{
  "type": "Feature",
  "properties": {
    "iso:country":"GB",
    "sg:address":"9 Hillside Ct",
    "sg:city":"Rotherham",
    "sg:classifiers":[
        {
            "category":"Professional",
            "subcategory":"Engineering",
            "type":"Services"
        }
    ],
    "sg:phone":"+44 1709 836647",
    "sg:postcode":"S61 4RP",
    "sg:province":"South Yorkshire",
    "sg:tags":[
        "hydraulic",
        "engineer"
    ],
    "wof:name":"Dunlop Hiflex Floud Power Ltd",
    "wof:placetype":"venue"
},
  "geometry": {"coordinates":[-1.354502,53.445255],"type":"Point"}
}