{
  "type": "Feature",
  "properties": {
    "addr:full":"169 Wellington Road South Stockport Cheshire SK1 3UA",
    "addr:housenumber":"169",
    "addr:postcode":"sk1 3ua",
    "addr:street":"Wellington Road South",
    "iso:country":"GB",
    "sg:address":"169 Wellington Road South",
    "sg:city":"Stockport",
    "sg:classifiers":[
        {
            "category":"Retail",
            "subcategory":"Event Space",
            "type":"Services"
        }
    ],
    "sg:phone":"+44 161 480 6531",
    "sg:postcode":"SK1 3UA",
    "sg:province":"Cheshire",
    "sg:tags":[
        "function",
        "room"
    ],
    "wof:name":"The Stockport Masonic Guildhall Ltd.",
    "wof:placetype":"venue"
},
  "geometry": {"coordinates":[-2.156689,53.40213],"type":"Point"}
}