{
  "type": "Feature",
  "properties": {
    "iso:country":"GB",
    "sg:address":"Po Box 6",
    "sg:city":"Chepstow",
    "sg:classifiers":[
        {
            "category":"Utilities",
            "subcategory":"Electric",
            "type":"Services"
        }
    ],
    "sg:phone":"+44 1291 630595",
    "sg:postcode":"NP16 7YP",
    "sg:province":"Gloucestershire",
    "sg:tags":[
        "electricity"
    ],
    "wof:name":"Enviropower Ltd.",
    "wof:placetype":"venue"
},
  "geometry": {"coordinates":[-2.655099,51.65556],"type":"Point"}
}