{
  "type": "Feature",
  "properties": {
    "addr:full":"140 Wincheap Canterbury Kent CT1 3RY",
    "addr:housenumber":"140",
    "addr:postcode":"ct1 3ry",
    "addr:street":"Wincheap Canterbury",
    "iso:country":"GB",
    "sg:address":"140 Wincheap",
    "sg:city":"Canterbury",
    "sg:classifiers":[
        {
            "category":"Travel",
            "subcategory":"Hotels & Motels",
            "type":"Entertainment"
        }
    ],
    "sg:phone":"+44 1227 453227",
    "sg:postcode":"CT1 3RY",
    "sg:province":"Kent",
    "wof:name":"Thanington Hotel",
    "wof:placetype":"venue"
},
  "geometry": {"coordinates":[1.069727,51.272797],"type":"Point"}
}