{
  "type": "Feature",
  "properties": {
    "addr:full":"40a Herbert St Hemel Hempstead Hertfordshire HP2 5HW",
    "addr:housenumber":"40a",
    "addr:postcode":"hp2 5hw",
    "addr:street":"Herbert St",
    "iso:country":"GB",
    "sg:address":"40a Herbert St",
    "sg:city":"Hemel Hempstead",
    "sg:classifiers":[
        {
            "category":"Health Services",
            "subcategory":"Clinic",
            "type":"Services"
        }
    ],
    "sg:phone":"+44 1442 236282",
    "sg:postcode":"HP2 5HW",
    "sg:province":"Hertfordshire",
    "sg:tags":[
        "aromatherapy"
    ],
    "wof:name":"Shirley Wilson",
    "wof:placetype":"venue"
},
  "geometry": {"coordinates":[-0.4678350091,51.7602539062],"type":"Point"}
}