{
  "type": "Feature",
  "properties": {
    "addr:full":"121 Sandy Lane Rochdale Lancashire OL11 5DG",
    "addr:housenumber":"121",
    "addr:postcode":"ol11 5dg",
    "addr:street":"Sandy Lane",
    "iso:country":"GB",
    "sg:address":"121 Sandy Lane",
    "sg:city":"Rochdale",
    "sg:classifiers":[
        {
            "category":"Shopping",
            "subcategory":"News",
            "type":"Retail Goods"
        }
    ],
    "sg:phone":"+44 1706 644365",
    "sg:postcode":"OL11 5DG",
    "sg:province":"Lancashire",
    "sg:tags":[
        "newsagent"
    ],
    "wof:name":"P & B Jones",
    "wof:placetype":"venue"
},
  "geometry": {"coordinates":[-2.1801640987,53.6176338196],"type":"Point"}
}