{
  "type": "Feature",
  "properties": {
    "iso:country":"GB",
    "sg:address":"Audit House, 260 Field End Road, Eastcote",
    "sg:city":"Pinner",
    "sg:classifiers":[
        {
            "category":"Wholesale",
            "subcategory":"Medical Equipment & Supplies",
            "type":"Manufacturing & Wholesale Goods"
        },
        {
            "category":"Building & Trades",
            "subcategory":"Equipment Rental",
            "type":"Services"
        }
    ],
    "sg:phone":"+44 20 8868 1500",
    "sg:postcode":"HA4 9YR",
    "sg:province":"Greater London",
    "sg:tags":[
        "supplier",
        "dental"
    ],
    "wof:name":"Periproducts Ltd",
    "wof:placetype":"venue"
},
  "geometry": {"coordinates":[-0.3973389864,51.5758171082],"type":"Point"}
}