{
  "type": "Feature",
  "properties": {
    "iso:country":"GB",
    "sg:address":"78 Colinton Mains Drive",
    "sg:city":"Edinburgh",
    "sg:classifiers":[
        {
            "category":"Cinema",
            "subcategory":"Movie Rental",
            "type":"Entertainment"
        }
    ],
    "sg:postcode":"EH13 9BJ",
    "sg:province":"City of Edinburgh",
    "sg:tags":[
        "video",
        "library"
    ],
    "wof:name":"Wendy McDonald",
    "wof:placetype":"venue"
},
  "geometry": {"coordinates":[-3.233289957,55.9096031189],"type":"Point"}
}