{
  "type": "Feature",
  "properties": {
    "addr:full":"99 Wickham Avenue, Cheam Sutton Surrey SM3 8EB",
    "addr:housenumber":"99",
    "addr:postcode":"sm3 8eb",
    "addr:street":"Wickham Avenue",
    "iso:country":"GB",
    "sg:address":"99 Wickham Avenue, Cheam",
    "sg:city":"Sutton",
    "sg:classifiers":[
        {
            "category":"Building & Trades",
            "subcategory":"Plumbing",
            "type":"Services"
        }
    ],
    "sg:phone":"+44 20 8641 0399",
    "sg:postcode":"SM3 8EB",
    "sg:province":"Surrey",
    "sg:tags":[
        "drain",
        "clearance",
        "sewer"
    ],
    "wof:name":"Able Plumbing Service",
    "wof:placetype":"venue"
},
  "geometry": {"coordinates":[-0.229936,51.364838],"type":"Point"}
}