{
  "type": "Feature",
  "properties": {
    "addr:full":"Thorne Ho, Eastville Yeovil Somerset BA21 4JD",
    "addr:postcode":"ba21 4jd",
    "iso:country":"GB",
    "sg:address":"Thorne Ho, Eastville",
    "sg:city":"Yeovil",
    "sg:classifiers":[
        {
            "category":"Education",
            "subcategory":"Special Training",
            "type":"Public Place"
        }
    ],
    "sg:phone":"+44 1935 411306",
    "sg:postcode":"BA21 4JD",
    "sg:province":"Somerset",
    "sg:tags":[
        "product",
        "centre"
    ],
    "wof:name":"Vantage Training",
    "wof:placetype":"venue"
},
  "geometry": {"coordinates":[-2.6234340668,50.9448013306],"type":"Point"}
}