{
  "type": "Feature",
  "properties": {
    "addr:full":"1 Fenay Lane, Almondbury Huddersfield West Yorkshire HD5 8UN",
    "addr:housenumber":"1",
    "addr:postcode":"hd5 8un",
    "addr:street":"Fenay Lane;West",
    "iso:country":"GB",
    "sg:address":"1 Fenay Lane, Almondbury",
    "sg:city":"Huddersfield",
    "sg:classifiers":[
        {
            "category":"Building & Trades",
            "subcategory":"Construction",
            "type":"Services"
        }
    ],
    "sg:phone":"+44 1484 549839",
    "sg:postcode":"HD5 8UN",
    "sg:province":"West Yorkshire",
    "sg:tags":[
        "dry",
        "lining",
        "plasterers",
        "screeders"
    ],
    "wof:name":"Richdard Bagley",
    "wof:placetype":"venue"
},
  "geometry": {"coordinates":[-1.7453269958,53.631275177],"type":"Point"}
}