{
  "type": "Feature",
  "properties": {
    "addr:full":"London Rd Sevenoaks Kent TN15 7RW",
    "addr:postcode":"tn15 7rw",
    "addr:street":"London Rd",
    "iso:country":"GB",
    "sg:address":"London Rd",
    "sg:city":"Sevenoaks",
    "sg:classifiers":[
        {
            "category":"Building & Trades",
            "subcategory":"Construction",
            "type":"Services"
        }
    ],
    "sg:phone":"+44 1732 780680",
    "sg:postcode":"TN15 7RW",
    "sg:province":"Kent",
    "sg:tags":[
        "roofing"
    ],
    "wof:name":"Marley Building Materials",
    "wof:placetype":"venue"
},
  "geometry": {"coordinates":[0.28510499,51.3281211853],"type":"Point"}
}