{
  "type": "Feature",
  "properties": {
    "addr:full":"10 Page Close Chippenham Gloucestershire SN14 0TG",
    "addr:housenumber":"10",
    "addr:postcode":"sn14 0tg",
    "addr:street":"Page Close",
    "iso:country":"GB",
    "sg:address":"10 Page Close",
    "sg:city":"Chippenham",
    "sg:classifiers":[
        {
            "category":"Manufacturing",
            "subcategory":"Pottery",
            "type":"Manufacturing & Wholesale Goods"
        }
    ],
    "sg:phone":"+44 1249 444287",
    "sg:postcode":"SN14 0TG",
    "sg:province":"Gloucestershire",
    "wof:name":"Latronicks Corporation",
    "wof:placetype":"venue"
},
  "geometry": {"coordinates":[-2.144326,51.45829],"type":"Point"}
}