{
  "type": "Feature",
  "properties": {
    "addr:full":"Bury House, 32 Bury Street Stowmarket Suffolk IP14 1HH",
    "addr:housenumber":"32",
    "addr:postcode":"ip14 1hh",
    "addr:street":"Bury Street",
    "iso:country":"GB",
    "sg:address":"Bury House, 32 Bury Street",
    "sg:city":"Stowmarket",
    "sg:classifiers":[
        {
            "category":"Health Services",
            "subcategory":"Dentist",
            "type":"Services"
        }
    ],
    "sg:phone":"+44 1449 612705",
    "sg:postcode":"IP14 1HH",
    "sg:province":"Suffolk",
    "wof:name":"L Gross",
    "wof:placetype":"venue"
},
  "geometry": {"coordinates":[0.995577,52.189236],"type":"Point"}
}