{
  "type": "Feature",
  "properties": {
    "addr:full":"138 Robert Street Milford Haven Pembrokeshire SA73 2HX",
    "addr:housenumber":"138",
    "addr:postcode":"sa73 2hx",
    "addr:street":"Robert Street",
    "iso:country":"GB",
    "sg:address":"138 Robert Street",
    "sg:city":"Milford Haven",
    "sg:classifiers":[
        {
            "category":"Building & Trades",
            "subcategory":"Construction",
            "type":"Services"
        }
    ],
    "sg:phone":"+44 1646 693490",
    "sg:postcode":"SA73 2HX",
    "sg:province":"Pembrokeshire",
    "sg:tags":[
        "builder"
    ],
    "wof:name":"Michael Dello",
    "wof:placetype":"venue"
},
  "geometry": {"coordinates":[-5.0333042145,51.7131347656],"type":"Point"}
}