{
  "type": "Feature",
  "properties": {
    "iso:country":"GB",
    "sg:address":"4 Green Meadow Square, St Dials",
    "sg:city":"Cwmbran",
    "sg:classifiers":[
        {
            "category":"Food & Beverages",
            "subcategory":"Bakery",
            "type":"Retail Goods"
        }
    ],
    "sg:postcode":"NP44 4LQ",
    "sg:province":"Monmouthshire",
    "sg:tags":[
        "baker"
    ],
    "wof:name":"Green Meadow Bakery",
    "wof:placetype":"venue"
},
  "geometry": {"coordinates":[-3.032714,51.6455],"type":"Point"}
}