{
  "type": "Feature",
  "properties": {
    "addr:full":"Gillbrae Road Dumfries Dumfries and Galloway DG1 4AT",
    "addr:postcode":"dg1 4at",
    "addr:street":"Gillbrae Road",
    "iso:country":"GB",
    "sg:address":"Gillbrae Road",
    "sg:city":"Dumfries",
    "sg:classifiers":[
        {
            "category":"Personal",
            "subcategory":"Beauty Salon",
            "type":"Services"
        }
    ],
    "sg:phone":"+44 1387 255162",
    "sg:postcode":"DG1 4AT",
    "sg:province":"Dumfries and Galloway",
    "sg:tags":[
        "unisex",
        "hairdresser"
    ],
    "wof:name":"Gemini",
    "wof:placetype":"venue"
},
  "geometry": {"coordinates":[-3.583988905,55.0648231506],"type":"Point"}
}