{
  "type": "Feature",
  "properties": {
    "addr:full":"3 Meadow Bank Close, West Kingsdown Sevenoaks Kent TN15 6UB",
    "addr:housenumber":"3",
    "addr:postcode":"tn15 6ub",
    "addr:street":"Meadow Bank Close West",
    "iso:country":"GB",
    "sg:address":"3 Meadow Bank Close, West Kingsdown",
    "sg:city":"Sevenoaks",
    "sg:classifiers":[
        {
            "category":"Autos & Motor Vehicles",
            "subcategory":"Motorcycle Sales",
            "type":"Retail Goods"
        }
    ],
    "sg:postcode":"TN15 6UB",
    "sg:province":"Kent",
    "sg:tags":[
        "chauffeur",
        "driven",
        "car"
    ],
    "wof:name":"County Car Service",
    "wof:placetype":"venue"
},
  "geometry": {"coordinates":[0.2621740103,51.3434295654],"type":"Point"}
}