{
  "type": "Feature",
  "properties": {
    "addr:full":"General Products, Spitalgate Indstl Est Grantham Lincolnshire NG31 7UP",
    "addr:postcode":"ng31 7up",
    "addr:street":"Spitalgate Indstl Est",
    "iso:country":"GB",
    "sg:address":"General Products, Spitalgate Indstl Est",
    "sg:city":"Grantham",
    "sg:classifiers":[
        {
            "category":"Manufacturing",
            "subcategory":"Metals",
            "type":"Manufacturing & Wholesale Goods"
        }
    ],
    "sg:phone":"+44 1476 565522",
    "sg:postcode":"NG31 7UP",
    "sg:province":"Lincolnshire",
    "sg:tags":[
        "steel",
        "stockholder"
    ],
    "wof:name":"B S D Steel Service Centres",
    "wof:placetype":"venue"
},
  "geometry": {"coordinates":[-0.6428589821,52.9131965637],"type":"Point"}
}