{
  "type": "Feature",
  "properties": {
    "iso:country":"GB",
    "sg:address":"282 Baldwins Lane, Hall Grn",
    "sg:city":"Birmingham",
    "sg:classifiers":[
        {
            "category":"Professional",
            "subcategory":"Computer Services",
            "type":"Services"
        }
    ],
    "sg:postcode":"B28 0XB",
    "sg:province":"West Midlands",
    "sg:tags":[
        "system",
        "software"
    ],
    "wof:name":"Abacas Consulting Ltd.",
    "wof:placetype":"venue"
},
  "geometry": {"coordinates":[-1.844386,52.414192],"type":"Point"}
}