{
  "type": "Feature",
  "properties": {
    "iso:country":"GB",
    "sg:address":"Meikle Colp Croft",
    "sg:city":"Turriff",
    "sg:classifiers":[
        {
            "category":"Freight",
            "type":"Transportation"
        }
    ],
    "sg:postcode":"AB53 8HJ",
    "sg:province":"Aberdeenshire",
    "sg:tags":[
        "haulage",
        "road"
    ],
    "wof:name":"Snowie,James Tait, Sandra Mary and Alexa",
    "wof:placetype":"venue"
},
  "geometry": {"coordinates":[-2.455229,57.539902],"type":"Point"}
}