{
  "type": "Feature",
  "properties": {
    "iso:country":"GB",
    "sg:address":"The Old Brewery Works, Lower Ellacombe Church Road",
    "sg:city":"Torquay",
    "sg:classifiers":[
        {
            "category":"Manufacturing",
            "subcategory":"Tools & Machinery",
            "type":"Manufacturing & Wholesale Goods"
        },
        {
            "category":"Utilities",
            "subcategory":"Mobile Phone",
            "type":"Services"
        }
    ],
    "sg:phone":"+44 1803 295430",
    "sg:postcode":"TQ1 1JH",
    "sg:province":"Devon",
    "sg:tags":[
        "mnfr",
        "electrical",
        "meter",
        "manufacturer"
    ],
    "wof:name":"Stephen P Wales",
    "wof:placetype":"venue"
},
  "geometry": {"coordinates":[-3.5217359066,50.4712905884],"type":"Point"}
}