{
  "type": "Feature",
  "properties": {
    "addr:full":"Unit 3 Norwood House, Rear Of 17 York Place Harrogate North Yorkshire HG1 1HL",
    "addr:housenumber":"unit 3;rear of 17",
    "addr:postcode":"hg1 1hl",
    "addr:street":"Norwood House;York Place",
    "iso:country":"GB",
    "sg:address":"Unit 3 Norwood House, Rear Of 17 York Place",
    "sg:city":"Harrogate",
    "sg:classifiers":[
        {
            "category":"Arts & Performance",
            "subcategory":"Music",
            "type":"Entertainment"
        }
    ],
    "sg:phone":"+44 1423 524955",
    "sg:postcode":"HG1 1HL",
    "sg:province":"North Yorkshire",
    "sg:tags":[
        "mobile",
        "disco"
    ],
    "wof:name":"Fun Time",
    "wof:placetype":"venue"
},
  "geometry": {"coordinates":[-1.5445239544,53.9946899414],"type":"Point"}
}