{
  "type": "Feature",
  "properties": {
    "iso:country":"GB",
    "sg:address":"29 Norwich Street",
    "sg:city":"Fakenham",
    "sg:classifiers":[
        {
            "category":"Food & Beverages",
            "subcategory":"Fruits & Vegetables",
            "type":"Retail Goods"
        }
    ],
    "sg:phone":"+44 1328 862199",
    "sg:postcode":"NR21 9AF",
    "sg:province":"Norfolk",
    "sg:tags":[
        "greengrocer"
    ],
    "wof:name":"Toppings Stores",
    "wof:placetype":"venue"
},
  "geometry": {"coordinates":[0.8497809768,52.8303527832],"type":"Point"}
}