{
  "type": "Feature",
  "properties": {
    "iso:country":"GB",
    "sg:address":"28 Westbourne Terrace",
    "sg:city":"Houghton-le-spring",
    "sg:classifiers":[
        {
            "category":"Personal",
            "type":"Services"
        }
    ],
    "sg:phone":"+44 191 385 7995",
    "sg:postcode":"DH4 4QT",
    "sg:province":"Durham",
    "sg:tags":[
        "wedding"
    ],
    "wof:name":"Linda Joyce Bridal Wear",
    "wof:placetype":"venue"
},
  "geometry": {"coordinates":[-1.493479,54.865105],"type":"Point"}
}