{
  "type": "Feature",
  "properties": {
    "addr:full":"24 Haselor Road, Boldmere Sutton Coldfield West Midlands B73 5DW",
    "addr:housenumber":"24",
    "addr:postcode":"b73 5dw",
    "addr:street":"Haselor Road",
    "iso:country":"GB",
    "sg:address":"24 Haselor Road, Boldmere",
    "sg:city":"Sutton Coldfield",
    "sg:classifiers":[
        {
            "category":"Building & Trades",
            "subcategory":"Construction",
            "type":"Services"
        }
    ],
    "sg:postcode":"B73 5DW",
    "sg:province":"West Midlands",
    "sg:tags":[
        "roofing"
    ],
    "wof:name":"Clarendon Roofing Specialist",
    "wof:placetype":"venue"
},
  "geometry": {"coordinates":[-1.84844,52.546303],"type":"Point"}
}