{
  "type": "Feature",
  "properties": {
    "iso:country":"GB",
    "sg:address":"33 South Cliff Road, Kirton Lindsey",
    "sg:city":"Gainsborough",
    "sg:classifiers":[
        {
            "category":"Professional",
            "subcategory":"Lawyer & Legal Services",
            "type":"Services"
        }
    ],
    "sg:phone":"+44 1652 648224",
    "sg:postcode":"DN21 4NR",
    "sg:province":"Lincolnshire",
    "sg:tags":[
        "solicitor"
    ],
    "wof:name":"Burton & Dyson",
    "wof:placetype":"venue"
},
  "geometry": {"coordinates":[-0.588354,53.474705],"type":"Point"}
}