{
  "type": "Feature",
  "properties": {
    "addr:full":"Radnor Park Av Folkestone Kent CT19 5BN",
    "addr:postcode":"ct19 5bn",
    "addr:street":"Park Av",
    "iso:country":"GB",
    "sg:address":"Radnor Park Av",
    "sg:city":"Folkestone",
    "sg:classifiers":[
        {
            "category":"Professional",
            "subcategory":"Lawyer & Legal Services",
            "type":"Services"
        }
    ],
    "sg:phone":"+44 1303 220018",
    "sg:postcode":"CT19 5BN",
    "sg:province":"Kent",
    "sg:tags":[
        "advice",
        "counselling"
    ],
    "wof:name":"Aids Counselling & Advice",
    "wof:placetype":"venue"
},
  "geometry": {"coordinates":[1.167666,51.086792],"type":"Point"}
}