{
  "type": "Feature",
  "properties": {
    "addr:full":"Unit 3 Manor La Deeside Flintshire CH5 3PP",
    "addr:housenumber":"unit 3",
    "addr:postcode":"ch5 3pp",
    "addr:street":"Manor La Deeside",
    "iso:country":"GB",
    "sg:address":"Unit 3 Manor La",
    "sg:city":"Deeside",
    "sg:classifiers":[
        {
            "category":"Home & Garden",
            "subcategory":"Kitchen Supply",
            "type":"Retail Goods"
        }
    ],
    "sg:phone":"+44 1244 538807",
    "sg:postcode":"CH5 3PP",
    "sg:province":"Flintshire",
    "sg:tags":[
        "equipment",
        "catering"
    ],
    "wof:name":"Grime Reaper UK",
    "wof:placetype":"venue"
},
  "geometry": {"coordinates":[-2.994590044,53.1780052185],"type":"Point"}
}