{
  "type": "Feature",
  "properties": {
    "addr:full":"388 Old Street, Shaw Ditch London Greater London EC1V 9LT",
    "addr:housenumber":"388",
    "addr:postcode":"ec1v 9lt",
    "addr:street":"Old Street;Ditch",
    "iso:country":"GB",
    "sg:address":"388 Old Street, Shaw Ditch",
    "sg:city":"London",
    "sg:classifiers":[
        {
            "category":"Utilities",
            "type":"Services"
        }
    ],
    "sg:phone":"+44 20 7739 4252",
    "sg:postcode":"EC1V 9LT",
    "sg:province":"Greater London",
    "sg:tags":[
        "internet"
    ],
    "wof:name":"O D Consultancy Ltd.",
    "wof:placetype":"venue"
},
  "geometry": {"coordinates":[-0.085599,51.526161],"type":"Point"}
}