{
  "type": "Feature",
  "properties": {
    "addr:full":"Wallis House, 24 High Street, Ewell Epsom Surrey KT17 1SJ",
    "addr:housenumber":"24",
    "addr:postcode":"kt17 1sj",
    "addr:street":"High Street",
    "iso:country":"GB",
    "sg:address":"Wallis House, 24 High Street, Ewell",
    "sg:city":"Epsom",
    "sg:classifiers":[
        {
            "category":"Professional",
            "subcategory":"Engineering",
            "type":"Services"
        }
    ],
    "sg:phone":"+44 20 8394 1555",
    "sg:postcode":"KT17 1SJ",
    "sg:province":"Surrey",
    "sg:tags":[
        "engineer",
        "structural"
    ],
    "wof:name":"Goodwin L F P Ltd.",
    "wof:placetype":"venue"
},
  "geometry": {"coordinates":[-0.250038,51.350155],"type":"Point"}
}