{
  "type": "Feature",
  "properties": {
    "iso:country":"GB",
    "sg:address":"Unit 3 Newton Moor Industrial Estate, Mill Street",
    "sg:city":"Hyde",
    "sg:classifiers":[
        {
            "category":"Shopping",
            "subcategory":"Gifts & Souvenirs",
            "type":"Retail Goods"
        }
    ],
    "sg:phone":"+44 161 368 0497",
    "sg:postcode":"SK14 4LF",
    "sg:province":"Cheshire",
    "sg:tags":[
        "ducting"
    ],
    "wof:name":"K G Ghilks Ltd.",
    "wof:placetype":"venue"
},
  "geometry": {"coordinates":[-2.080884,53.454311],"type":"Point"}
}