{
  "type": "Feature",
  "properties": {
    "addr:full":"Trumpsgreen House, Trumpsgreen Road Virginia Water Surrey GU25 4HX",
    "addr:postcode":"gu25 4hx",
    "addr:street":"Trumpsgreen Road",
    "iso:country":"GB",
    "sg:address":"Trumpsgreen House, Trumpsgreen Road",
    "sg:city":"Virginia Water",
    "sg:classifiers":[
        {
            "category":"Home & Garden",
            "subcategory":"Garden Supply",
            "type":"Retail Goods"
        }
    ],
    "sg:phone":"+44 1344 844155",
    "sg:postcode":"GU25 4HX",
    "sg:province":"Surrey",
    "sg:tags":[
        "sand",
        "gravel"
    ],
    "wof:name":"Foundation Materials (Merchants) Ltd.",
    "wof:placetype":"venue"
},
  "geometry": {"coordinates":[-0.560044,51.401031],"type":"Point"}
}