{
  "type": "Feature",
  "properties": {
    "iso:country":"GB",
    "sg:address":"27 Bruton Street",
    "sg:city":"London",
    "sg:classifiers":[
        {
            "category":"Shopping",
            "subcategory":"Antiques",
            "type":"Retail Goods"
        }
    ],
    "sg:phone":"+44 20 7491 1007",
    "sg:postcode":"W1J 6QN",
    "sg:province":"Greater London",
    "wof:name":"Antoine Cheneviere Fine Arts",
    "wof:placetype":"venue"
},
  "geometry": {"coordinates":[-0.1450390071,51.5105247498],"type":"Point"}
}