{
  "type": "Feature",
  "properties": {
    "iso:country":"GB",
    "sg:address":"12 Elizabeth Road",
    "sg:city":"Godalming",
    "sg:classifiers":[
        {
            "category":"Military Area",
            "subcategory":"Air Force Base",
            "type":"Public Place"
        }
    ],
    "sg:phone":"+44 1483 422722",
    "sg:postcode":"GU7 3QE",
    "sg:province":"Surrey",
    "sg:tags":[
        "taxi",
        "hire",
        "private"
    ],
    "wof:name":"APOLLO TAXIS",
    "wof:placetype":"venue"
},
  "geometry": {"coordinates":[-0.6088039875,51.1978645325],"type":"Point"}
}