{
  "type": "Feature",
  "properties": {
    "iso:country":"GB",
    "sg:address":"16 Woodward Close, Shouldham",
    "sg:city":"King's Lynn",
    "sg:classifiers":[
        {
            "category":"Building & Trades",
            "subcategory":"Cleaning & Sanitation",
            "type":"Services"
        },
        {
            "category":"Building & Trades",
            "subcategory":"Pest Control",
            "type":"Services"
        }
    ],
    "sg:phone":"+44 1366 347669",
    "sg:postcode":"PE33 0DE",
    "sg:province":"Norfolk",
    "sg:tags":[
        "use",
        "industrial",
        "door",
        "manufacturer"
    ],
    "wof:name":"Downham Door Services Ltd.",
    "wof:placetype":"venue"
},
  "geometry": {"coordinates":[0.4780800045,52.6529006958],"type":"Point"}
}