{
  "type": "Feature",
  "properties": {
    "addr:full":"Island Farm, Bishop Middleham Ferryhill Durham DL17 9ED",
    "addr:postcode":"dl17 9ed",
    "addr:street":"Bishop Middleham",
    "iso:country":"GB",
    "sg:address":"Island Farm, Bishop Middleham",
    "sg:city":"Ferryhill",
    "sg:classifiers":[
        {
            "category":"Farming",
            "subcategory":"Farm",
            "type":"Manufacturing & Wholesale Goods"
        }
    ],
    "sg:postcode":"DL17 9ED",
    "sg:province":"Durham",
    "sg:tags":[
        "mixed",
        "crop"
    ],
    "wof:name":"J Hirst & Son",
    "wof:placetype":"venue"
},
  "geometry": {"coordinates":[-1.4865059853,54.6800918579],"type":"Point"}
}