{
  "type": "Feature",
  "properties": {
    "iso:country":"GB",
    "sg:address":"8 Sefton Ave",
    "sg:city":"Nottingham",
    "sg:classifiers":[
        {
            "category":"Building & Trades",
            "subcategory":"Plumbing",
            "type":"Services"
        }
    ],
    "sg:postcode":"NG9 8EA",
    "sg:province":"Nottinghamshire",
    "sg:tags":[
        "heating"
    ],
    "wof:name":"Elite Plumbing & Glazing Services",
    "wof:placetype":"venue"
},
  "geometry": {"coordinates":[-1.266632,52.936333],"type":"Point"}
}