{
  "type": "Feature",
  "properties": {
    "addr:full":"Bronwydd, Tanygroes Cardigan Ceredigion SA43 2JS",
    "addr:postcode":"sa43 2js",
    "addr:street":"Tanygroes",
    "iso:country":"GB",
    "sg:address":"Bronwydd, Tanygroes",
    "sg:city":"Cardigan",
    "sg:classifiers":[
        {
            "category":"Farming",
            "subcategory":"Livestock Farm",
            "type":"Manufacturing & Wholesale Goods"
        }
    ],
    "sg:phone":"+44 1239 811134",
    "sg:postcode":"SA43 2JS",
    "sg:province":"Ceredigion",
    "sg:tags":[
        "others"
    ],
    "wof:name":"G & E L Jones",
    "wof:placetype":"venue"
},
  "geometry": {"coordinates":[-4.512942791,52.11510849],"type":"Point"}
}