{
  "type": "Feature",
  "properties": {
    "iso:country":"GB",
    "sg:address":"7 King Street",
    "sg:city":"Brighouse",
    "sg:classifiers":[
        {
            "category":"Shopping",
            "subcategory":"Pets & Pet Supplies",
            "type":"Retail Goods"
        }
    ],
    "sg:phone":"+44 1484 710584",
    "sg:postcode":"HD6 1NX",
    "sg:province":"West Yorkshire",
    "sg:tags":[
        "shop"
    ],
    "wof:name":"King Street Pet Stores",
    "wof:placetype":"venue"
},
  "geometry": {"coordinates":[-1.778846,53.702702],"type":"Point"}
}