{
  "type": "Feature",
  "properties": {
    "addr:full":"42 Bowly Rd Cirencester Gloucestershire GL7 1SF",
    "addr:housenumber":"42",
    "addr:postcode":"gl7 1sf",
    "addr:street":"Bowly Rd",
    "iso:country":"GB",
    "sg:address":"42 Bowly Rd",
    "sg:city":"Cirencester",
    "sg:classifiers":[
        {
            "category":"Military Area",
            "subcategory":"Air Force Base",
            "type":"Public Place"
        }
    ],
    "sg:phone":"+44 1285 640502",
    "sg:postcode":"GL7 1SF",
    "sg:province":"Gloucestershire",
    "sg:tags":[
        "taxi",
        "hire",
        "private"
    ],
    "wof:name":"I.P.S Taxis",
    "wof:placetype":"venue"
},
  "geometry": {"coordinates":[-1.977242,51.707489],"type":"Point"}
}