{
  "type": "Feature",
  "properties": {
    "addr:full":"Maltings Farm, Grange Road, Blunham Bedford Bedfordshire MK44 3NS",
    "addr:postcode":"mk44 3ns",
    "addr:street":"Grange Road",
    "iso:country":"GB",
    "sg:address":"Maltings Farm, Grange Road, Blunham",
    "sg:city":"Bedford",
    "sg:classifiers":[
        {
            "category":"Shopping",
            "subcategory":"Hobbies, Toys, & Games",
            "type":"Retail Goods"
        }
    ],
    "sg:postcode":"MK44 3NS",
    "sg:province":"Bedfordshire",
    "sg:tags":[
        "shop",
        "toy"
    ],
    "wof:name":"Carryhome Garden Toys A T C",
    "wof:placetype":"venue"
},
  "geometry": {"coordinates":[-0.3165520132,52.1467590332],"type":"Point"}
}