{
  "type": "Feature",
  "properties": {
    "iso:country":"GB",
    "sg:address":"430 Roman Road",
    "sg:city":"London",
    "sg:classifiers":[
        {
            "category":"Government",
            "subcategory":"Customs House",
            "type":"Public Place"
        }
    ],
    "sg:postcode":"E3 5LU",
    "sg:province":"Greater London",
    "sg:tags":[
        "clearance"
    ],
    "wof:name":"Restorer House Clearance",
    "wof:placetype":"venue"
},
  "geometry": {"coordinates":[-0.034632,51.531834],"type":"Point"}
}