{
  "type": "Feature",
  "properties": {
    "iso:country":"GB",
    "sg:address":"Old Coach Works, Prospect Garage, Distington",
    "sg:city":"Workington",
    "sg:classifiers":[
        {
            "category":"Freight",
            "type":"Transportation"
        }
    ],
    "sg:phone":"+44 1946 830333",
    "sg:postcode":"CA14 5XJ",
    "sg:province":"Cumbria",
    "sg:tags":[
        "haulage",
        "transport",
        "road"
    ],
    "wof:name":"Tyson H Burridge Ltd.",
    "wof:placetype":"venue"
},
  "geometry": {"coordinates":[-3.538829,54.597672],"type":"Point"}
}