{
  "type": "Feature",
  "properties": {
    "addr:full":"Grenville Workshops, 502 Hornsey Road London Greater London N19 4EF",
    "addr:housenumber":"502",
    "addr:postcode":"n19 4ef",
    "addr:street":"Hornsey Road",
    "iso:country":"GB",
    "sg:address":"Grenville Workshops, 502 Hornsey Road",
    "sg:city":"London",
    "sg:classifiers":[
        {
            "category":"Manufacturing",
            "subcategory":"Textiles",
            "type":"Manufacturing & Wholesale Goods"
        }
    ],
    "sg:phone":"+44 20 7281 4572",
    "sg:postcode":"N19 4EF",
    "sg:province":"Greater London",
    "sg:tags":[
        "merchant",
        "agent"
    ],
    "wof:name":"H Rich (Textiles) Ltd.",
    "wof:placetype":"venue"
},
  "geometry": {"coordinates":[-0.1221200004,51.5673408508],"type":"Point"}
}