{
  "type": "Feature",
  "properties": {
    "addr:full":"Bank Gate Mills, Bank Gate, Slaithwaite Huddersfield West Yorkshire HD7 5DL",
    "addr:postcode":"hd7 5dl",
    "addr:street":"Bank Gate Mills Bank Gate",
    "iso:country":"GB",
    "sg:address":"Bank Gate Mills, Bank Gate, Slaithwaite",
    "sg:city":"Huddersfield",
    "sg:classifiers":[
        {
            "category":"Home & Garden",
            "subcategory":"Carpets & Floor Coverings",
            "type":"Retail Goods"
        }
    ],
    "sg:phone":"+44 1484 845015",
    "sg:postcode":"HD7 5DL",
    "sg:province":"West Yorkshire",
    "sg:tags":[
        "rubber",
        "plastic"
    ],
    "wof:name":"Colne Valley Polymers Ltd.",
    "wof:placetype":"venue"
},
  "geometry": {"coordinates":[-1.870396018,53.6224212646],"type":"Point"}
}