{
  "type": "Feature",
  "properties": {
    "iso:country":"GB",
    "sg:address":"Wakefield Rd",
    "sg:city":"Normanton",
    "sg:classifiers":[
        {
            "category":"Community Center",
            "subcategory":"Youth",
            "type":"Public Place"
        }
    ],
    "sg:phone":"+44 1924 302545",
    "sg:postcode":"WF6 1BW",
    "sg:province":"West Yorkshire",
    "sg:tags":[
        "organisation",
        "centre"
    ],
    "wof:name":"Normanton Youth Club",
    "wof:placetype":"venue"
},
  "geometry": {"coordinates":[-1.422799,53.69693],"type":"Point"}
}