{
  "type": "Feature",
  "properties": {
    "iso:country":"GB",
    "sg:address":"Clayston Farm, Silver Stream",
    "sg:city":"Haverfordwest",
    "sg:classifiers":[
        {
            "category":"Retail",
            "subcategory":"Auto Repair",
            "type":"Services"
        }
    ],
    "sg:phone":"+44 1437 891064",
    "sg:postcode":"SA62 4HA",
    "sg:province":"Pembrokeshire",
    "sg:tags":[
        "modification",
        "garage"
    ],
    "wof:name":"Ivor D Jones",
    "wof:placetype":"venue"
},
  "geometry": {"coordinates":[-4.9598298073,51.7616195679],"type":"Point"}
}