{
  "type": "Feature",
  "properties": {
    "addr:full":"11 Lower Bond Street Hinckley Leicestershire LE10 1QU",
    "addr:housenumber":"11",
    "addr:postcode":"le10 1qu",
    "addr:street":"Lower Bond Street",
    "iso:country":"GB",
    "sg:address":"11 Lower Bond Street",
    "sg:city":"Hinckley",
    "sg:classifiers":[
        {
            "category":"Shopping",
            "subcategory":"Clothing, Apparel, & Fashions",
            "type":"Retail Goods"
        }
    ],
    "sg:phone":"+44 1455 613606",
    "sg:postcode":"LE10 1QU",
    "sg:province":"Leicestershire",
    "sg:tags":[
        "menswear"
    ],
    "wof:name":"Bradwards",
    "wof:placetype":"venue"
},
  "geometry": {"coordinates":[-1.3736219406,52.5425071716],"type":"Point"}
}