{
  "type": "Feature",
  "properties": {
    "iso:country":"GB",
    "sg:address":"Bratton Road",
    "sg:city":"Westbury",
    "sg:classifiers":[
        {
            "category":"Bars & Pubs",
            "type":"Food & Drink"
        }
    ],
    "sg:postcode":"BA13 3EN",
    "sg:province":"Wiltshire",
    "sg:tags":[
        "pubs",
        "inn"
    ],
    "wof:name":"The Castle Inn",
    "wof:placetype":"venue"
},
  "geometry": {"coordinates":[-2.179508,51.260265],"type":"Point"}
}