{
  "type": "Feature",
  "properties": {
    "addr:full":"Premier Centre, Abbey Park Romsey Hampshire SO51 9AQ",
    "addr:postcode":"so51 9aq",
    "addr:street":"Abbey Park",
    "iso:country":"GB",
    "sg:address":"Premier Centre, Abbey Park",
    "sg:city":"Romsey",
    "sg:classifiers":[
        {
            "category":"Retail",
            "subcategory":"Auto Repair",
            "type":"Services"
        }
    ],
    "sg:phone":"+44 1794 519955",
    "sg:postcode":"SO51 9AQ",
    "sg:province":"Hampshire",
    "sg:tags":[
        "modification",
        "garage"
    ],
    "wof:name":"K M W Services",
    "wof:placetype":"venue"
},
  "geometry": {"coordinates":[-1.4631940126,50.9825668335],"type":"Point"}
}