{
  "type": "Feature",
  "properties": {
    "iso:country":"GB",
    "sg:address":"Llewenydd, Pentwyn Road",
    "sg:city":"Treharris",
    "sg:classifiers":[
        {
            "category":"Real Estate",
            "subcategory":"Real Estate Services",
            "type":"Services"
        },
        {
            "category":"Building & Trades",
            "subcategory":"Equipment Rental",
            "type":"Services"
        }
    ],
    "sg:phone":"+44 1443 410042",
    "sg:postcode":"CF46 5BS",
    "sg:province":"Caerphilly",
    "sg:tags":[
        "hire",
        "leasing",
        "plant",
        "machinery"
    ],
    "wof:name":"Howard Miles Plant Hire",
    "wof:placetype":"venue"
},
  "geometry": {"coordinates":[-3.30647,51.664886],"type":"Point"}
}