{
  "type": "Feature",
  "properties": {
    "addr:full":"11 Jerusalem Passage, St John's Square Clerkenwell Greater London EC1V 4JP",
    "addr:housenumber":"11",
    "addr:postcode":"ec1v 4jp",
    "addr:street":"Jerusalem Passage St John'S Square",
    "iso:country":"GB",
    "sg:address":"11 Jerusalem Passage, St John's Square",
    "sg:city":"Clerkenwell",
    "sg:classifiers":[
        {
            "category":"Professional",
            "subcategory":"Employment Agencies",
            "type":"Services"
        }
    ],
    "sg:phone":"+44 20 7566 3537",
    "sg:postcode":"EC1V 4JP",
    "sg:province":"Greater London",
    "wof:name":"JobsGoPublic.com",
    "wof:placetype":"venue"
},
  "geometry": {"coordinates":[-0.101739,51.521111],"type":"Point"}
}