{
  "type": "Feature",
  "properties": {
    "addr:full":"103 Burton Road Lincoln Lincolnshire LN1 3LL",
    "addr:housenumber":"103",
    "addr:postcode":"ln1 3ll",
    "addr:street":"Burton Road",
    "iso:country":"GB",
    "sg:address":"103 Burton Road",
    "sg:city":"Lincoln",
    "sg:classifiers":[
        {
            "category":"Food & Beverages",
            "subcategory":"Bakery",
            "type":"Retail Goods"
        }
    ],
    "sg:phone":"+44 1522 543553",
    "sg:postcode":"LN1 3LL",
    "sg:province":"Lincolnshire",
    "sg:tags":[
        "shop",
        "baker",
        "confectionery"
    ],
    "wof:name":"J H Starbuck",
    "wof:placetype":"venue"
},
  "geometry": {"coordinates":[-0.544556,53.238972],"type":"Point"}
}