{
  "type": "Feature",
  "properties": {
    "addr:full":"Great George St Westminster Greater London SW1P 3AL",
    "addr:postcode":"sw1p 3al",
    "addr:street":"Great George St",
    "iso:country":"GB",
    "sg:address":"Great George St",
    "sg:city":"Westminster",
    "sg:classifiers":[
        {
            "category":"Government",
            "subcategory":"Office",
            "type":"Public Place"
        }
    ],
    "sg:phone":"+44 20 7270 6523",
    "sg:postcode":"SW1P 3AL",
    "sg:province":"Greater London",
    "sg:tags":[
        "central"
    ],
    "wof:name":"Cabinet Office The",
    "wof:placetype":"venue"
},
  "geometry": {"coordinates":[-0.127994,51.500065],"type":"Point"}
}