{
  "type": "Feature",
  "properties": {
    "addr:full":"Triumph House, 189 Regent St West End Hampshire W1R 7WE",
    "addr:housenumber":"189",
    "addr:postcode":"w1r 7we",
    "addr:street":"Regent St",
    "iso:country":"GB",
    "sg:address":"Triumph House, 189 Regent St",
    "sg:city":"West End",
    "sg:classifiers":[
        {
            "category":"Professional",
            "subcategory":"Employment Agencies",
            "type":"Services"
        }
    ],
    "sg:phone":"+44 20 7287 2225",
    "sg:postcode":"W1R 7WE",
    "sg:province":"Hampshire",
    "sg:tags":[
        "consultant"
    ],
    "wof:name":"The Recruitment Business",
    "wof:placetype":"venue"
},
  "geometry": {"coordinates":[-0.140526,51.512669],"type":"Point"}
}