{
  "type": "Feature",
  "properties": {
    "addr:full":"Queen St Barnstaple Devon EX32 8HQ",
    "addr:postcode":"ex32 8hq",
    "addr:street":"Queen St",
    "iso:country":"GB",
    "sg:address":"Queen St",
    "sg:city":"Barnstaple",
    "sg:classifiers":[
        {
            "category":"Autos & Motor Vehicles",
            "subcategory":"Auto Supplies",
            "type":"Retail Goods"
        }
    ],
    "sg:postcode":"EX32 8HQ",
    "sg:province":"Devon",
    "sg:tags":[
        "tyre"
    ],
    "wof:name":"National Tyre Service Ltd",
    "wof:placetype":"venue"
},
  "geometry": {"coordinates":[-4.056374073,51.0792312622],"type":"Point"}
}