{
  "type": "Feature",
  "properties": {
    "iso:country":"GB",
    "sg:address":"Springhouse Rd, Corringham",
    "sg:city":"Stanford-le-hope",
    "sg:classifiers":[
        {
            "category":"Community Center",
            "type":"Public Place"
        }
    ],
    "sg:phone":"+44 1375 678070",
    "sg:postcode":"SS17 7NB",
    "sg:province":"Essex",
    "sg:tags":[
        "recreation",
        "leisure",
        "centre"
    ],
    "wof:name":"Thurrock Community Leisure Ltd",
    "wof:placetype":"venue"
},
  "geometry": {"coordinates":[0.4398239851,51.5261650085],"type":"Point"}
}