{
  "type": "Feature",
  "properties": {
    "addr:full":"4 The Pound, Cholsey Wallingford Oxfordshire OX10 9NS",
    "addr:housenumber":"4;cholsey",
    "addr:postcode":"ox10 9ns",
    "addr:street":"The Pound",
    "iso:country":"GB",
    "sg:address":"4 The Pound, Cholsey",
    "sg:city":"Wallingford",
    "sg:classifiers":[
        {
            "category":"Professional",
            "subcategory":"Accounting & Tax Preparation",
            "type":"Services"
        }
    ],
    "sg:phone":"+44 1491 652853",
    "sg:postcode":"OX10 9NS",
    "sg:province":"Oxfordshire",
    "sg:tags":[
        "accountant"
    ],
    "wof:name":"David Mitchell & Co.",
    "wof:placetype":"venue"
},
  "geometry": {"coordinates":[-1.153429,51.57531],"type":"Point"}
}