{
  "type": "Feature",
  "properties": {
    "addr:full":"47 Maltese Road Chelmsford Essex CM1 2PB",
    "addr:housenumber":"47",
    "addr:postcode":"cm1 2pb",
    "addr:street":"Maltese Road",
    "iso:country":"GB",
    "sg:address":"47 Maltese Road",
    "sg:city":"Chelmsford",
    "sg:classifiers":[
        {
            "category":"Personal",
            "subcategory":"Sauna",
            "type":"Services"
        }
    ],
    "sg:phone":"+44 1245 344432",
    "sg:postcode":"CM1 2PB",
    "sg:province":"Essex",
    "sg:tags":[
        "equipment",
        "sunbed"
    ],
    "wof:name":"Norpe Saunas of Finland (U K) Ltd.",
    "wof:placetype":"venue"
},
  "geometry": {"coordinates":[0.461450994,51.7412567139],"type":"Point"}
}