{
  "type": "Feature",
  "properties": {
    "addr:full":"Runfold Granary, Runfold St George, Badshot Lea Farnham Hampshire GU10 1PL",
    "addr:postcode":"gu10 1pl",
    "addr:street":"Runfold",
    "iso:country":"GB",
    "sg:address":"Runfold Granary, Runfold St George, Badshot Lea",
    "sg:city":"Farnham",
    "sg:classifiers":[
        {
            "category":"Autos & Motor Vehicles",
            "subcategory":"Automobile Sales",
            "type":"Retail Goods"
        },
        {
            "category":"Professional",
            "subcategory":"Business Services",
            "type":"Services"
        }
    ],
    "sg:postcode":"GU10 1PL",
    "sg:province":"Hampshire",
    "sg:tags":[
        "car",
        "export",
        "agent",
        "import"
    ],
    "wof:name":"Mincon (U K) Ltd",
    "wof:placetype":"venue"
},
  "geometry": {"coordinates":[-0.7513639927,51.2205696106],"type":"Point"}
}