{
  "type": "Feature",
  "properties": {
    "addr:full":"Over Eden, Wetheral Carlisle Cumbria CA4 8JN",
    "addr:postcode":"ca4 8jn",
    "addr:street":"Over",
    "iso:country":"GB",
    "sg:address":"Over Eden, Wetheral",
    "sg:city":"Carlisle",
    "sg:classifiers":[
        {
            "category":"Health Services",
            "subcategory":"Podiatrist",
            "type":"Services"
        }
    ],
    "sg:phone":"+44 1228 560333",
    "sg:postcode":"CA4 8JN",
    "sg:province":"Cumbria",
    "sg:tags":[
        "podiatrists",
        "chiropodist"
    ],
    "wof:name":"G Bruce MSSCH",
    "wof:placetype":"venue"
},
  "geometry": {"coordinates":[-2.832806,54.886127],"type":"Point"}
}