{
  "type": "Feature",
  "properties": {
    "addr:full":"Unit A Horton Trading Estate, Stanwell Rd, Horton Slough Berkshire SL3 9PF",
    "addr:housenumber":"unit a",
    "addr:postcode":"sl3 9pf",
    "addr:street":"Horton Trading Estate Stanwell Rd",
    "iso:country":"GB",
    "sg:address":"Unit A Horton Trading Estate, Stanwell Rd, Horton",
    "sg:city":"Slough",
    "sg:classifiers":[
        {
            "category":"Professional",
            "subcategory":"Printing & Photocopies",
            "type":"Services"
        }
    ],
    "sg:phone":"+44 1753 767100",
    "sg:postcode":"SL3 9PF",
    "sg:province":"Berkshire",
    "sg:tags":[
        "printer"
    ],
    "wof:name":"Printer Technology",
    "wof:placetype":"venue"
},
  "geometry": {"coordinates":[-0.542158,51.47316],"type":"Point"}
}