{
  "type": "Feature",
  "properties": {
    "iso:country":"GB",
    "sg:address":"10 South Street",
    "sg:city":"St Austell",
    "sg:classifiers":[
        {
            "category":"Government",
            "subcategory":"Office",
            "type":"Public Place"
        }
    ],
    "sg:phone":"+44 1726 63443",
    "sg:postcode":"PL25 5BH",
    "sg:province":"Cornwall",
    "sg:tags":[
        "mp",
        "meps"
    ],
    "wof:name":"Matthew Taylor",
    "wof:placetype":"venue"
},
  "geometry": {"coordinates":[-4.792001,50.337807],"type":"Point"}
}