{
  "type": "Feature",
  "properties": {
    "addr:full":"Willowtree Marina, West Quay Drive, Yeading Hayes Greater London UB4 9TA",
    "addr:postcode":"ub4 9ta",
    "addr:street":"West Quay Drive",
    "iso:country":"GB",
    "sg:address":"Willowtree Marina, West Quay Drive, Yeading",
    "sg:city":"Hayes",
    "sg:classifiers":[
        {
            "category":"Shopping",
            "subcategory":"Pharmacy",
            "type":"Retail Goods"
        }
    ],
    "sg:phone":"+44 20 8842 3956",
    "sg:postcode":"UB4 9TA",
    "sg:province":"Greater London",
    "sg:tags":[
        "medicine",
        "therapy"
    ],
    "wof:name":"The Naturopathic Health & Beauty Co. Ltd.",
    "wof:placetype":"venue"
},
  "geometry": {"coordinates":[-0.395229,51.526684],"type":"Point"}
}