{
  "type": "Feature",
  "properties": {
    "addr:full":"Ty-llwyd, Felinfoel Llanelli Carmarthenshire SA15 4PB",
    "addr:postcode":"sa15 4pb",
    "iso:country":"GB",
    "sg:address":"Ty-llwyd, Felinfoel",
    "sg:city":"Llanelli",
    "sg:classifiers":[
        {
            "category":"Real Estate",
            "subcategory":"Surveying",
            "type":"Services"
        }
    ],
    "sg:postcode":"SA15 4PB",
    "sg:province":"Carmarthenshire",
    "sg:tags":[
        "surveyor",
        "land"
    ],
    "wof:name":"Surveys Gwalia",
    "wof:placetype":"venue"
},
  "geometry": {"coordinates":[-4.134299,51.682682],"type":"Point"}
}