{
  "type": "Feature",
  "properties": {
    "iso:country":"GB",
    "sg:address":"Regal House, Highfield St",
    "sg:city":"Oldham",
    "sg:classifiers":[
        {
            "category":"Manufacturing",
            "subcategory":"Tools & Machinery",
            "type":"Manufacturing & Wholesale Goods"
        }
    ],
    "sg:phone":"+44 161 628 6988",
    "sg:postcode":"OL9 6DT",
    "sg:province":"Lancashire",
    "sg:tags":[
        "society",
        "friendly"
    ],
    "wof:name":"Regal Warranties Ltd",
    "wof:placetype":"venue"
},
  "geometry": {"coordinates":[-2.122434,53.545486],"type":"Point"}
}