{
  "type": "Feature",
  "properties": {
    "iso:country":"GB",
    "sg:address":"2 Latimer Road",
    "sg:city":"Luton",
    "sg:classifiers":[
        {
            "category":"Autos & Motor Vehicles",
            "subcategory":"Automobile Sales",
            "type":"Retail Goods"
        }
    ],
    "sg:phone":"+44 1582 727727",
    "sg:postcode":"LU1 3TX",
    "sg:province":"Bedfordshire",
    "sg:tags":[
        "car"
    ],
    "wof:name":"Dunham Mazda",
    "wof:placetype":"venue"
},
  "geometry": {"coordinates":[-0.412811,51.875523],"type":"Point"}
}