{
  "type": "Feature",
  "properties": {
    "iso:country":"GB",
    "sg:address":"Clockhouse, Fambridge Road",
    "sg:city":"Maldon",
    "sg:classifiers":[
        {
            "category":"Professional",
            "subcategory":"Engineering",
            "type":"Services"
        }
    ],
    "sg:postcode":"CM9 6PH",
    "sg:province":"Essex",
    "sg:tags":[
        "contractor",
        "electrical",
        "engineer"
    ],
    "wof:name":"Turpin Electrical Engineers",
    "wof:placetype":"venue"
},
  "geometry": {"coordinates":[0.675249,51.731377],"type":"Point"}
}