{
  "type": "Feature",
  "properties": {
    "addr:full":"The Parade, High Street, Staplehurst Tonbridge Kent TN12 0LA",
    "addr:postcode":"tn12 0la",
    "addr:street":"The Parade High Street",
    "iso:country":"GB",
    "sg:address":"The Parade, High Street, Staplehurst",
    "sg:city":"Tonbridge",
    "sg:classifiers":[
        {
            "category":"Education",
            "subcategory":"Library",
            "type":"Public Place"
        }
    ],
    "sg:phone":"+44 1580 891929",
    "sg:postcode":"TN12 0LA",
    "sg:province":"Kent",
    "sg:tags":[
        "book"
    ],
    "wof:name":"Staplehurst Library",
    "wof:placetype":"venue"
},
  "geometry": {"coordinates":[0.552592,51.167049],"type":"Point"}
}