{
  "type": "Feature",
  "properties": {
    "iso:country":"GB",
    "sg:address":"Inglewood Residential Home, Lowmoor Road",
    "sg:city":"Wigton",
    "sg:classifiers":[
        {
            "category":"Social Services",
            "subcategory":"Retirement Home",
            "type":"Services"
        }
    ],
    "sg:phone":"+44 16973 42850",
    "sg:postcode":"CA7 9QL",
    "sg:province":"Cumbria",
    "sg:tags":[
        "residential",
        "care"
    ],
    "wof:name":"Cumbria County Council",
    "wof:placetype":"venue"
},
  "geometry": {"coordinates":[-3.160759,54.824348],"type":"Point"}
}