{
  "type": "Feature",
  "properties": {
    "addr:full":"3 Mercia Way, Bells Close Ind Est, Lemington Newcastle Upon Tyne Northumberland NE15 6UF",
    "addr:housenumber":"3",
    "addr:postcode":"ne15 6uf",
    "addr:street":"Mercia Way Bells Close",
    "iso:country":"GB",
    "sg:address":"3 Mercia Way, Bells Close Ind Est, Lemington",
    "sg:city":"Newcastle Upon Tyne",
    "sg:classifiers":[
        {
            "category":"Professional",
            "subcategory":"Engineering",
            "type":"Services"
        }
    ],
    "sg:phone":"+44 191 264 5222",
    "sg:postcode":"NE15 6UF",
    "sg:province":"Northumberland",
    "sg:tags":[
        "engineer",
        "mechanical"
    ],
    "wof:name":"Northumbrian Tool & Engineering Services",
    "wof:placetype":"venue"
},
  "geometry": {"coordinates":[-1.7002190351,54.973690033],"type":"Point"}
}