{
  "type": "Feature",
  "properties": {
    "iso:country":"GB",
    "sg:address":"The Vicarage, The Cloisters",
    "sg:city":"Wantage",
    "sg:classifiers":[
        {
            "category":"Place Of Worship",
            "type":"Public Place"
        }
    ],
    "sg:phone":"+44 1235 762214",
    "sg:postcode":"OX12 8AQ",
    "sg:province":"Berkshire",
    "wof:name":"Church Of England Parish Of Saints Peter & Paul",
    "wof:placetype":"venue"
},
  "geometry": {"coordinates":[-1.3869789839,51.5832481384],"type":"Point"}
}