{
  "type": "Feature",
  "properties": {
    "addr:full":"70 Widley Road Portsmouth Hampshire PO2 8PW",
    "addr:housenumber":"70",
    "addr:postcode":"hampshire po2 8pw",
    "addr:street":"Widley Road",
    "iso:country":"GB",
    "sg:address":"70 Widley Road",
    "sg:city":"Portsmouth",
    "sg:classifiers":[
        {
            "category":"Building & Trades",
            "subcategory":"Plumbing",
            "type":"Services"
        },
        {
            "category":"Building & Trades",
            "subcategory":"Equipment Rental",
            "type":"Services"
        }
    ],
    "sg:phone":"+44 23 9269 3923",
    "sg:postcode":"PO2 8PW",
    "sg:province":"Hampshire",
    "sg:tags":[
        "clearance",
        "drain",
        "sewer",
        "sewar"
    ],
    "wof:name":"All Hours Drain & Plumbing Services Ltd.",
    "wof:placetype":"venue"
},
  "geometry": {"coordinates":[-1.088766,50.821327],"type":"Point"}
}