{
  "type": "Feature",
  "properties": {
    "addr:full":"Unit 7, Manway Business Park, Canal Road Altrincham Cheshire WA14 1TD",
    "addr:housenumber":"unit 7",
    "addr:postcode":"wa14 1td",
    "addr:street":"Manway Business Park Canal Road",
    "iso:country":"GB",
    "sg:address":"Unit 7, Manway Business Park, Canal Road",
    "sg:city":"Altrincham",
    "sg:classifiers":[
        {
            "category":"Home & Garden",
            "subcategory":"Building Materials",
            "type":"Retail Goods"
        }
    ],
    "sg:phone":"+44 161 962 4813",
    "sg:postcode":"WA14 1TD",
    "sg:province":"Cheshire",
    "sg:tags":[
        "furnishers",
        "bathroom",
        "planner"
    ],
    "wof:name":"Michael Walker",
    "wof:placetype":"venue"
},
  "geometry": {"coordinates":[-2.349209,53.386726],"type":"Point"}
}