{
  "type": "Feature",
  "properties": {
    "iso:country":"GB",
    "sg:address":"Rodwell House, 100 Middlesex Street",
    "sg:city":"London",
    "sg:classifiers":[
        {
            "category":"Professional",
            "subcategory":"Management & Consulting",
            "type":"Services"
        }
    ],
    "sg:phone":"+44 20 7650 1402",
    "sg:postcode":"E1 7HD",
    "sg:province":"Greater London",
    "sg:tags":[
        "consultant",
        "training"
    ],
    "wof:name":"Alphatania Group",
    "wof:placetype":"venue"
},
  "geometry": {"coordinates":[-0.077095,51.517178],"type":"Point"}
}