{
  "type": "Feature",
  "properties": {
    "iso:country":"GB",
    "sg:address":"5 Blyburgate",
    "sg:city":"Beccles",
    "sg:classifiers":[
        {
            "category":"Transit Center",
            "subcategory":"Freight",
            "type":"Transportation"
        }
    ],
    "sg:phone":"+44 1502 713882",
    "sg:postcode":"NR34 9TA",
    "sg:province":"Norfolk",
    "sg:tags":[
        "shop",
        "craft",
        "centre"
    ],
    "wof:name":"Great Knits",
    "wof:placetype":"venue"
},
  "geometry": {"coordinates":[1.5643450022,52.4569244385],"type":"Point"}
}