{
  "type": "Feature",
  "properties": {
    "addr:full":"44 The Causeway March Cambridgeshire PE15 9NX",
    "addr:housenumber":"44",
    "addr:postcode":"pe15 9nx",
    "addr:street":"The Causeway",
    "iso:country":"GB",
    "sg:address":"44 The Causeway",
    "sg:city":"March",
    "sg:classifiers":[
        {
            "category":"Autos & Motor Vehicles",
            "subcategory":"Automobile Sales",
            "type":"Retail Goods"
        }
    ],
    "sg:postcode":"PE15 9NX",
    "sg:province":"Cambridgeshire",
    "sg:tags":[
        "car"
    ],
    "wof:name":"CAUSEWAY CARRIDGE",
    "wof:placetype":"venue"
},
  "geometry": {"coordinates":[0.0854559988,52.5396385193],"type":"Point"}
}