{
  "type": "Feature",
  "properties": {
    "addr:full":"Quantock House, Longdon Hill Evesham Gloucestershire WR11 7RP",
    "addr:postcode":"wr11 7rp",
    "addr:street":"Longdon Hill",
    "iso:country":"GB",
    "sg:address":"Quantock House, Longdon Hill",
    "sg:city":"Evesham",
    "sg:classifiers":[
        {
            "category":"Banks & Credit Unions",
            "subcategory":"Financial Services",
            "type":"Services"
        }
    ],
    "sg:phone":"+44 1386 833035",
    "sg:postcode":"WR11 7RP",
    "sg:province":"Gloucestershire",
    "sg:tags":[
        "consultant"
    ],
    "wof:name":"Quantock Finance Ltd.",
    "wof:placetype":"venue"
},
  "geometry": {"coordinates":[-1.9116829634,52.0731582642],"type":"Point"}
}