{
  "type": "Feature",
  "properties": {
    "iso:country":"GB",
    "sg:address":"High Street, Cheswardine",
    "sg:city":"Market Drayton",
    "sg:classifiers":[
        {
            "category":"Retail",
            "subcategory":"Auto Repair",
            "type":"Services"
        }
    ],
    "sg:phone":"+44 1630 661247",
    "sg:postcode":"TF9 2RS",
    "sg:province":"Shropshire",
    "sg:tags":[
        "modification",
        "garage"
    ],
    "wof:name":"H Lewis & Son",
    "wof:placetype":"venue"
},
  "geometry": {"coordinates":[-2.417275,52.863724],"type":"Point"}
}