{
  "type": "Feature",
  "properties": {
    "addr:full":"145 Sea Road, Methilhill Leven Fife KY8 2EE",
    "addr:housenumber":"145",
    "addr:postcode":"ky8 2ee",
    "addr:street":"Sea Road Methilhill Leven",
    "iso:country":"GB",
    "sg:address":"145 Sea Road, Methilhill",
    "sg:city":"Leven",
    "sg:classifiers":[
        {
            "category":"Shopping",
            "subcategory":"Crafts & Fabrics",
            "type":"Retail Goods"
        }
    ],
    "sg:phone":"+44 1592 714000",
    "sg:postcode":"KY8 2EE",
    "sg:province":"Fife",
    "sg:tags":[
        "ceramic"
    ],
    "wof:name":"Ceramic Tiling Services",
    "wof:placetype":"venue"
},
  "geometry": {"coordinates":[-3.031214,56.18549],"type":"Point"}
}