{
  "type": "Feature",
  "properties": {
    "addr:full":"1 Sheil Road Liverpool Merseyside L6 3AA",
    "addr:housenumber":"1",
    "addr:postcode":"l6 3aa",
    "addr:street":"Sheil Road",
    "iso:country":"GB",
    "sg:address":"1 Sheil Road",
    "sg:city":"Liverpool",
    "sg:classifiers":[
        {
            "category":"Bars & Pubs",
            "type":"Food & Drink"
        }
    ],
    "sg:phone":"+44 151 260 6934",
    "sg:postcode":"L6 3AA",
    "sg:province":"Merseyside",
    "sg:tags":[
        "pubs",
        "inn"
    ],
    "wof:name":"Sheil Park",
    "wof:placetype":"venue"
},
  "geometry": {"coordinates":[-2.944560051,53.4123954773],"type":"Point"}
}