{
  "type": "Feature",
  "properties": {
    "iso:country":"GB",
    "sg:address":"66 Mayfield Industrial Estate",
    "sg:city":"Dalkeith",
    "sg:classifiers":[
        {
            "category":"Freight",
            "type":"Transportation"
        },
        {
            "category":"Retail",
            "subcategory":"Storage",
            "type":"Services"
        }
    ],
    "sg:phone":"+44 131 663 6061",
    "sg:postcode":"EH22 4AD",
    "sg:province":"City of Edinburgh",
    "sg:tags":[
        "haulage",
        "activity",
        "domestic",
        "road",
        "removal"
    ],
    "wof:name":"RON BOYD LTD",
    "wof:placetype":"venue"
},
  "geometry": {"coordinates":[-3.052009,55.868851],"type":"Point"}
}