{
  "type": "Feature",
  "properties": {
    "addr:full":"18 York Rd Northampton Northamptonshire NN1 5QG",
    "addr:housenumber":"18",
    "addr:postcode":"nn1 5qg",
    "addr:street":"York Rd",
    "iso:country":"GB",
    "sg:address":"18 York Rd",
    "sg:city":"Northampton",
    "sg:classifiers":[
        {
            "category":"Communications",
            "subcategory":"Film & Video Production",
            "type":"Services"
        }
    ],
    "sg:postcode":"NN1 5QG",
    "sg:province":"Northamptonshire",
    "sg:tags":[
        "illustrator",
        "artist"
    ],
    "wof:name":"Garner,Phillip,",
    "wof:placetype":"venue"
},
  "geometry": {"coordinates":[-0.888939,52.239197],"type":"Point"}
}