{
  "type": "Feature",
  "properties": {
    "addr:full":"2 Deakin Road, Erdington Birmingham West Midlands B24 9AN",
    "addr:housenumber":"2",
    "addr:postcode":"b24 9an",
    "addr:street":"Deakin Road",
    "iso:country":"GB",
    "sg:address":"2 Deakin Road, Erdington",
    "sg:city":"Birmingham",
    "sg:classifiers":[
        {
            "category":"Building & Trades",
            "subcategory":"Landscaping Services",
            "type":"Services"
        }
    ],
    "sg:postcode":"B24 9AN",
    "sg:province":"West Midlands",
    "sg:tags":[
        "forestry",
        "tree"
    ],
    "wof:name":"P & M Garden Services",
    "wof:placetype":"venue"
},
  "geometry": {"coordinates":[-1.84108603,52.5192680359],"type":"Point"}
}