{
  "type": "Feature",
  "properties": {
    "addr:full":"131-133 Cardiff Rd Reading Berkshire RG1 8ES",
    "addr:housenumber":"131-133",
    "addr:postcode":"rg1 8es",
    "addr:street":"Cardiff Rd",
    "iso:country":"GB",
    "sg:address":"131-133 Cardiff Rd",
    "sg:city":"Reading",
    "sg:classifiers":[
        {
            "category":"Manufacturing",
            "subcategory":"Electronics",
            "type":"Manufacturing & Wholesale Goods"
        }
    ],
    "sg:phone":"+44 118 958 9898",
    "sg:postcode":"RG1 8ES",
    "sg:province":"Berkshire",
    "sg:tags":[
        "printed",
        "circuit"
    ],
    "wof:name":"GDS PCB Design",
    "wof:placetype":"venue"
},
  "geometry": {"coordinates":[-0.9829319715,51.4612045288],"type":"Point"}
}