{
  "type": "Feature",
  "properties": {
    "addr:full":"Fetterangus Peterhead Aberdeenshire AB42 4HE",
    "addr:postcode":"ab42 4he",
    "iso:country":"GB",
    "sg:address":"Fetterangus",
    "sg:city":"Peterhead",
    "sg:classifiers":[
        {
            "category":"Professional",
            "subcategory":"Engineering",
            "type":"Services"
        }
    ],
    "sg:phone":"+44 1771 623601",
    "sg:postcode":"AB42 4HE",
    "sg:province":"Aberdeenshire",
    "sg:tags":[
        "agricultural",
        "engineer"
    ],
    "wof:name":"G F Enterprise Ltd.",
    "wof:placetype":"venue"
},
  "geometry": {"coordinates":[-2.02539,57.547798],"type":"Point"}
}