{
  "type": "Feature",
  "properties": {
    "addr:full":"525a Chester Rd, Kingshurst Birmingham West Midlands B36 0JU",
    "addr:housenumber":"525a",
    "addr:postcode":"b36 0ju",
    "addr:street":"Chester Rd",
    "iso:country":"GB",
    "sg:address":"525a Chester Rd, Kingshurst",
    "sg:city":"Birmingham",
    "sg:classifiers":[
        {
            "category":"Communications",
            "type":"Services"
        }
    ],
    "sg:phone":"+44 121 250 5100",
    "sg:postcode":"B36 0JU",
    "sg:province":"West Midlands",
    "sg:tags":[
        "telecommunication"
    ],
    "wof:name":"Phone World",
    "wof:placetype":"venue"
},
  "geometry": {"coordinates":[-1.7508449554,52.497844696],"type":"Point"}
}