{
  "type": "Feature",
  "properties": {
    "iso:country":"GB",
    "sg:address":"3 Great Oak Street",
    "sg:city":"Llanidloes",
    "sg:classifiers":[
        {
            "category":"Food & Beverages",
            "subcategory":"Fruits & Vegetables",
            "type":"Retail Goods"
        }
    ],
    "sg:phone":"+44 1686 412960",
    "sg:postcode":"SY18 6BN",
    "sg:province":"Powys",
    "sg:tags":[
        "greengrocer"
    ],
    "wof:name":"Darren M Tonks",
    "wof:placetype":"venue"
},
  "geometry": {"coordinates":[-3.539652,52.448608],"type":"Point"}
}