{
  "type": "Feature",
  "properties": {
    "addr:full":"Ennerdale House, Garrigill Alston Cumbria CA9 3DY",
    "addr:postcode":"ca9 3dy",
    "addr:street":"Garrigill",
    "iso:country":"GB",
    "sg:address":"Ennerdale House, Garrigill",
    "sg:city":"Alston",
    "sg:classifiers":[
        {
            "category":"Recreation",
            "type":"Entertainment"
        }
    ],
    "sg:phone":"+44 1434 381966",
    "sg:postcode":"CA9 3DY",
    "sg:province":"Cumbria",
    "sg:tags":[
        "outdoor",
        "pursuit"
    ],
    "wof:name":"Adventure Education Training",
    "wof:placetype":"venue"
},
  "geometry": {"coordinates":[-2.438752,54.812382],"type":"Point"}
}