{
  "type": "Feature",
  "properties": {
    "iso:country":"GB",
    "sg:address":"Chapel Gate, East Parley",
    "sg:city":"Christchurch",
    "sg:classifiers":[
        {
            "category":"Arena",
            "subcategory":"Sports Club",
            "type":"Entertainment"
        },
        {
            "category":"Sports & Exercise",
            "subcategory":"Tennis Court",
            "type":"Entertainment"
        }
    ],
    "sg:postcode":"BH23 6DB",
    "sg:province":"Dorset",
    "sg:tags":[
        "squash"
    ],
    "wof:name":"Bournemouth Squash Club",
    "wof:placetype":"venue"
},
  "geometry": {"coordinates":[-1.859814,50.779079],"type":"Point"}
}