{
  "type": "Feature",
  "properties": {
    "addr:full":"8 Ledbury Mews North, Kensington London Greater London W11 2AF",
    "addr:housenumber":"8",
    "addr:postcode":"w11 2af",
    "addr:street":"Ledbury Mews",
    "iso:country":"GB",
    "sg:address":"8 Ledbury Mews North, Kensington",
    "sg:city":"London",
    "sg:classifiers":[
        {
            "category":"Real Estate",
            "subcategory":"Developer",
            "type":"Services"
        }
    ],
    "sg:phone":"+44 20 7221 1828",
    "sg:postcode":"W11 2AF",
    "sg:province":"Greater London",
    "sg:tags":[
        "property"
    ],
    "wof:name":"J E London Properties Ltd",
    "wof:placetype":"venue"
},
  "geometry": {"coordinates":[-0.1982080042,51.5140914917],"type":"Point"}
}