{
  "type": "Feature",
  "properties": {
    "addr:full":"42 Balmoral Place Aberdeen Aberdeen City AB10 6HP",
    "addr:housenumber":"42",
    "addr:postcode":"ab10 6hp",
    "addr:street":"Balmoral Place",
    "iso:country":"GB",
    "sg:address":"42 Balmoral Place",
    "sg:city":"Aberdeen",
    "sg:classifiers":[
        {
            "category":"Personal",
            "subcategory":"Beauty Salon",
            "type":"Services"
        }
    ],
    "sg:phone":"+44 1224 212192",
    "sg:postcode":"AB10 6HP",
    "sg:province":"Aberdeen City",
    "sg:tags":[
        "unisex",
        "hairdresser"
    ],
    "wof:name":"The Hair Shop",
    "wof:placetype":"venue"
},
  "geometry": {"coordinates":[-2.118521,57.135006],"type":"Point"}
}