{
  "type": "Feature",
  "properties": {
    "iso:country":"GB",
    "sg:address":"31 Market Place",
    "sg:city":"Egremont",
    "sg:classifiers":[
        {
            "category":"Shopping",
            "subcategory":"Pharmacy",
            "type":"Retail Goods"
        }
    ],
    "sg:phone":"+44 1946 820237",
    "sg:postcode":"CA22 2AG",
    "sg:province":"Cumbria",
    "sg:tags":[
        "pharmacist",
        "dispensing",
        "chemist"
    ],
    "wof:name":"J N Murray Ltd",
    "wof:placetype":"venue"
},
  "geometry": {"coordinates":[-3.5292880535,54.483417511],"type":"Point"}
}