{
  "type": "Feature",
  "properties": {
    "addr:full":"3 Brook Lane Peterhead Aberdeenshire AB42 1JW",
    "addr:housenumber":"3",
    "addr:postcode":"ab42 1jw",
    "addr:street":"Brook Lane",
    "iso:country":"GB",
    "sg:address":"3 Brook Lane",
    "sg:city":"Peterhead",
    "sg:classifiers":[
        {
            "category":"Wholesale",
            "subcategory":"Scrap",
            "type":"Manufacturing & Wholesale Goods"
        }
    ],
    "sg:phone":"+44 1779 480845",
    "sg:postcode":"AB42 1JW",
    "sg:province":"Aberdeenshire",
    "sg:tags":[
        "waste",
        "metal"
    ],
    "wof:name":"Brookside Metals",
    "wof:placetype":"venue"
},
  "geometry": {"coordinates":[-1.776291,57.507389],"type":"Point"}
}