{
  "type": "Feature",
  "properties": {
    "iso:country":"GB",
    "sg:address":"Holly Farm, Moreton Road, Owermoigne",
    "sg:city":"Dorchester",
    "sg:classifiers":[
        {
            "category":"Farming",
            "subcategory":"Dairy Farm",
            "type":"Manufacturing & Wholesale Goods"
        }
    ],
    "sg:phone":"+44 1305 852160",
    "sg:postcode":"DT2 8HZ",
    "sg:province":"Dorset",
    "sg:tags":[
        "farmer"
    ],
    "wof:name":"Albert Frampton",
    "wof:placetype":"venue"
},
  "geometry": {"coordinates":[-2.279344,50.703339],"type":"Point"}
}