{
  "type": "Feature",
  "properties": {
    "iso:country":"GB",
    "sg:address":"2 High Street",
    "sg:city":"Steyning",
    "sg:classifiers":[
        {
            "category":"Retail",
            "subcategory":"Veterinary Services",
            "type":"Services"
        }
    ],
    "sg:phone":"+44 1903 816428",
    "sg:postcode":"BN44 3GG",
    "sg:province":"West Sussex",
    "sg:tags":[
        "surgeon"
    ],
    "wof:name":"Crossways Veterinary Group",
    "wof:placetype":"venue"
},
  "geometry": {"coordinates":[-0.3263899982,50.8866539001],"type":"Point"}
}