{
  "type": "Feature",
  "properties": {
    "iso:country":"GB",
    "sg:address":"Downing Road, Whitford",
    "sg:city":"Holywell",
    "sg:classifiers":[
        {
            "category":"Recreation",
            "subcategory":"Fishing",
            "type":"Entertainment"
        }
    ],
    "sg:postcode":"CH8 9EQ",
    "sg:province":"Denbighshire",
    "sg:tags":[
        "angling"
    ],
    "wof:name":"Forest Hill Trout Farm",
    "wof:placetype":"venue"
},
  "geometry": {"coordinates":[-3.251179,53.302059],"type":"Point"}
}