{
  "type": "Feature",
  "properties": {
    "iso:country":"GB",
    "sg:address":"194 High St North",
    "sg:city":"East Ham",
    "sg:classifiers":[
        {
            "category":"Professional",
            "type":"Services"
        }
    ],
    "sg:phone":"+44 20 8552 0207",
    "sg:postcode":"E6 2JA",
    "sg:province":"Greater London",
    "sg:tags":[
        "repair",
        "tech",
        "maintenance"
    ],
    "wof:name":"Hi-phonix Technology",
    "wof:placetype":"venue"
},
  "geometry": {"coordinates":[0.0513399988,51.5383605957],"type":"Point"}
}