{
  "type": "Feature",
  "properties": {
    "addr:full":"Unit 5 Witheys Yard, 55 High Street Stroud Gloucestershire GL5 1AS",
    "addr:housenumber":"unit 5;55",
    "addr:postcode":"gl5 1as",
    "addr:street":"Witheys Yard;High Street",
    "iso:country":"GB",
    "sg:address":"Unit 5 Witheys Yard, 55 High Street",
    "sg:city":"Stroud",
    "sg:classifiers":[
        {
            "category":"Home & Garden",
            "subcategory":"Hardware",
            "type":"Retail Goods"
        },
        {
            "category":"Home & Garden",
            "subcategory":"Kitchen Supply",
            "type":"Retail Goods"
        }
    ],
    "sg:phone":"+44 1453 759880",
    "sg:postcode":"GL5 1AS",
    "sg:province":"Gloucestershire",
    "sg:tags":[
        "ware",
        "retailer",
        "diy"
    ],
    "wof:name":"Mills Kitchen Shop",
    "wof:placetype":"venue"
},
  "geometry": {"coordinates":[-2.2324409485,51.744934082],"type":"Point"}
}