{
  "type": "Feature",
  "properties": {
    "addr:full":"Cranbourne Farm, Cobham Gravesend Kent DA13 9AU",
    "addr:postcode":"da13 9au",
    "addr:street":"Cobham",
    "iso:country":"GB",
    "sg:address":"Cranbourne Farm, Cobham",
    "sg:city":"Gravesend",
    "sg:classifiers":[
        {
            "category":"Farming",
            "subcategory":"Livestock Farm",
            "type":"Manufacturing & Wholesale Goods"
        }
    ],
    "sg:postcode":"DA13 9AU",
    "sg:province":"Kent",
    "sg:tags":[
        "others"
    ],
    "wof:name":"John C Smith",
    "wof:placetype":"venue"
},
  "geometry": {"coordinates":[0.37041,51.3918],"type":"Point"}
}