{
  "type": "Feature",
  "properties": {
    "addr:full":"32 Clifton Street Blackpool Lancashire FY1 1JP",
    "addr:housenumber":"32",
    "addr:postcode":"fy1 1jp",
    "addr:street":"Clifton Street",
    "iso:country":"GB",
    "sg:address":"32 Clifton Street",
    "sg:city":"Blackpool",
    "sg:classifiers":[
        {
            "category":"Manufacturing",
            "subcategory":"Tools & Machinery",
            "type":"Manufacturing & Wholesale Goods"
        }
    ],
    "sg:phone":"+44 1253 22748",
    "sg:postcode":"FY1 1JP",
    "sg:province":"Lancashire",
    "sg:tags":[
        "society",
        "friendly"
    ],
    "wof:name":"Refuge Assurance Plc",
    "wof:placetype":"venue"
},
  "geometry": {"coordinates":[-3.0533909798,53.8189659119],"type":"Point"}
}