{
  "type": "Feature",
  "properties": {
    "addr:full":"Vicarage, Woodland Av Par Cornwall PL24 2PL",
    "addr:postcode":"pl24 2pl",
    "addr:street":"Woodland Av Par",
    "iso:country":"GB",
    "sg:address":"Vicarage, Woodland Av",
    "sg:city":"Par",
    "sg:classifiers":[
        {
            "category":"Place Of Worship",
            "type":"Public Place"
        }
    ],
    "sg:phone":"+44 1726 812998",
    "sg:postcode":"PL24 2PL",
    "sg:province":"Cornwall",
    "wof:name":"Tywardreath Parish Church",
    "wof:placetype":"venue"
},
  "geometry": {"coordinates":[-4.7191591263,50.3500862122],"type":"Point"}
}