{
  "type": "Feature",
  "properties": {
    "addr:full":"30 Church Street Gainsborough Lincolnshire DN21 2JH",
    "addr:housenumber":"30",
    "addr:postcode":"dn21 2jh",
    "addr:street":"Church Street",
    "iso:country":"GB",
    "sg:address":"30 Church Street",
    "sg:city":"Gainsborough",
    "sg:classifiers":[
        {
            "category":"Home & Garden",
            "subcategory":"Kitchen Supply",
            "type":"Retail Goods"
        }
    ],
    "sg:phone":"+44 1427 612405",
    "sg:postcode":"DN21 2JH",
    "sg:province":"Lincolnshire",
    "sg:tags":[
        "glassware",
        "china"
    ],
    "wof:name":"Alice Glass & China",
    "wof:placetype":"venue"
},
  "geometry": {"coordinates":[-0.775552,53.400612],"type":"Point"}
}