{
  "type": "Feature",
  "properties": {
    "iso:country":"GB",
    "sg:address":"Haulage Yard, Miners Road, Llay Industrial Estate",
    "sg:city":"Wrexham",
    "sg:classifiers":[
        {
            "category":"Freight",
            "type":"Transportation"
        }
    ],
    "sg:phone":"+44 1978 856979",
    "sg:postcode":"LL12 0PJ",
    "sg:province":"Wrexham",
    "sg:tags":[
        "haulage",
        "road"
    ],
    "wof:name":"Paul R Pugh",
    "wof:placetype":"venue"
},
  "geometry": {"coordinates":[-3.000814,53.093639],"type":"Point"}
}