{
  "type": "Feature",
  "properties": {
    "iso:country":"GB",
    "sg:address":"Mill House, 38 Dam St",
    "sg:city":"Lichfield",
    "sg:classifiers":[
        {
            "category":"Professional",
            "subcategory":"Lawyer & Legal Services",
            "type":"Services"
        }
    ],
    "sg:phone":"+44 1543 414426",
    "sg:postcode":"WS13 6AA",
    "sg:province":"Staffordshire",
    "sg:tags":[
        "solicitor"
    ],
    "wof:name":"R D Taylor",
    "wof:placetype":"venue"
},
  "geometry": {"coordinates":[-1.8288049698,52.6852302551],"type":"Point"}
}