{
  "type": "Feature",
  "properties": {
    "addr:full":"Headquarters, The Rosings, Narborough Leicester Leicestershire LE9 5EQ",
    "addr:postcode":"le9 5eq",
    "addr:street":"The",
    "iso:country":"GB",
    "sg:address":"Headquarters, The Rosings, Narborough",
    "sg:city":"Leicester",
    "sg:classifiers":[
        {
            "category":"Health Services",
            "subcategory":"Hospital",
            "type":"Services"
        }
    ],
    "sg:phone":"+44 116 275 0700",
    "sg:postcode":"LE9 5EQ",
    "sg:province":"Leicestershire",
    "sg:tags":[
        "ambulance"
    ],
    "wof:name":"Ambulance Service",
    "wof:placetype":"venue"
},
  "geometry": {"coordinates":[-1.21197,52.571739],"type":"Point"}
}