{
  "type": "Feature",
  "properties": {
    "iso:country":"GB",
    "sg:address":"Old Henley, Henley",
    "sg:city":"Haslemere",
    "sg:classifiers":[
        {
            "category":"Professional",
            "subcategory":"Computer Services",
            "type":"Services"
        }
    ],
    "sg:phone":"+44 1428 661695",
    "sg:postcode":"GU27 3HQ",
    "sg:province":"Hampshire",
    "sg:tags":[
        "consultant"
    ],
    "wof:name":"Allen & Associates",
    "wof:placetype":"venue"
},
  "geometry": {"coordinates":[-0.726914,51.022327],"type":"Point"}
}