{
  "type": "Feature",
  "properties": {
    "addr:full":"Stonebridge House, 28-32 Bridge Street Leatherhead Surrey KT22 8BZ",
    "addr:housenumber":"28-32",
    "addr:postcode":"kt22 8bz",
    "addr:street":"Bridge Street",
    "iso:country":"GB",
    "sg:address":"Stonebridge House, 28-32 Bridge Street",
    "sg:city":"Leatherhead",
    "sg:classifiers":[
        {
            "category":"Organizations",
            "subcategory":"Membership Organization",
            "type":"Services"
        }
    ],
    "sg:postcode":"KT22 8BZ",
    "sg:province":"Surrey",
    "sg:tags":[
        "club"
    ],
    "wof:name":"Howland Quay Residents Co Ltd",
    "wof:placetype":"venue"
},
  "geometry": {"coordinates":[-0.331601,51.294704],"type":"Point"}
}