{
  "type": "Feature",
  "properties": {
    "addr:full":"35 Fernhill Road Haverfordwest Pembrokeshire SA61 1LE",
    "addr:housenumber":"35",
    "addr:postcode":"sa61 1le",
    "addr:street":"Fernhill Road",
    "iso:country":"GB",
    "sg:address":"35 Fernhill Road",
    "sg:city":"Haverfordwest",
    "sg:classifiers":[
        {
            "category":"Professional",
            "subcategory":"Printing & Photocopies",
            "type":"Services"
        }
    ],
    "sg:postcode":"SA61 1LE",
    "sg:province":"Pembrokeshire",
    "sg:tags":[
        "printer"
    ],
    "wof:name":"George Blythe Printer",
    "wof:placetype":"venue"
},
  "geometry": {"coordinates":[-4.9686818123,51.7901687622],"type":"Point"}
}