{
  "type": "Feature",
  "properties": {
    "addr:full":"159 Ashbourne Rd Derby Derbyshire DE22 3AJ",
    "addr:housenumber":"159",
    "addr:postcode":"de22 3aj",
    "addr:street":"Ashbourne Rd",
    "iso:country":"GB",
    "sg:address":"159 Ashbourne Rd",
    "sg:city":"Derby",
    "sg:classifiers":[
        {
            "category":"Shopping",
            "subcategory":"Mobile Phones",
            "type":"Retail Goods"
        }
    ],
    "sg:phone":"+44 1283 740477",
    "sg:postcode":"DE22 3AJ",
    "sg:province":"Derbyshire",
    "wof:name":"Phonesworld",
    "wof:placetype":"venue"
},
  "geometry": {"coordinates":[-1.500294,52.927692],"type":"Point"}
}