{
  "type": "Feature",
  "properties": {
    "addr:full":"20 The Carfax Horsham West Sussex RH12 1EB",
    "addr:housenumber":"20",
    "addr:postcode":"rh12 1eb",
    "addr:street":"The Carfax",
    "iso:country":"GB",
    "sg:address":"20 The Carfax",
    "sg:city":"Horsham",
    "sg:classifiers":[
        {
            "category":"Deli",
            "type":"Food & Drink"
        }
    ],
    "sg:phone":"+44 1403 254272",
    "sg:postcode":"RH12 1EB",
    "sg:province":"West Sussex",
    "sg:tags":[
        "delicatessen"
    ],
    "wof:name":"Horsham Cheese Shop",
    "wof:placetype":"venue"
},
  "geometry": {"coordinates":[-0.3276000023,51.0631446838],"type":"Point"}
}