{
  "type": "Feature",
  "properties": {
    "addr:full":"Redoaks Hill, Ashdon Saffron Walden Cambridgeshire CB10 2LY",
    "addr:postcode":"cb10 2ly",
    "addr:street":"Redoaks Hill",
    "iso:country":"GB",
    "sg:address":"Redoaks Hill, Ashdon",
    "sg:city":"Saffron Walden",
    "sg:classifiers":[
        {
            "category":"Farming",
            "subcategory":"Livestock Farm",
            "type":"Manufacturing & Wholesale Goods"
        }
    ],
    "sg:postcode":"CB10 2LY",
    "sg:province":"Cambridgeshire",
    "sg:tags":[
        "others"
    ],
    "wof:name":"Ronald William Cayzer",
    "wof:placetype":"venue"
},
  "geometry": {"coordinates":[0.3137310147,52.0554428101],"type":"Point"}
}