{
  "type": "Feature",
  "properties": {
    "addr:full":"77 The Ridge, Dollis Valley Way Barnet Hertfordshire EN5 2TT",
    "addr:housenumber":"77",
    "addr:postcode":"hertfordshire en5 2tt",
    "addr:street":"The Ridge Dollis Valley Way",
    "iso:country":"GB",
    "sg:address":"77 The Ridge, Dollis Valley Way",
    "sg:city":"Barnet",
    "sg:classifiers":[
        {
            "category":"Building & Trades",
            "subcategory":"Construction",
            "type":"Services"
        }
    ],
    "sg:phone":"+44 20 8449 9930",
    "sg:postcode":"EN5 2TT",
    "sg:province":"Hertfordshire",
    "sg:tags":[
        "decorator",
        "painter"
    ],
    "wof:name":"Killick & Son",
    "wof:placetype":"venue"
},
  "geometry": {"coordinates":[-0.1958660036,51.6453056335],"type":"Point"}
}