{
  "type": "Feature",
  "properties": {
    "addr:full":"Mayfield Coach House, Ribchester Road Blackburn Lancashire BB1 9EE",
    "addr:postcode":"bb1 9ee",
    "addr:street":"Ribchester Road",
    "iso:country":"GB",
    "sg:address":"Mayfield Coach House, Ribchester Road",
    "sg:city":"Blackburn",
    "sg:classifiers":[
        {
            "category":"Real Estate",
            "subcategory":"Developer",
            "type":"Services"
        }
    ],
    "sg:phone":"+44 1254 248184",
    "sg:postcode":"BB1 9EE",
    "sg:province":"Lancashire",
    "sg:tags":[
        "property"
    ],
    "wof:name":"J Young Developments",
    "wof:placetype":"venue"
},
  "geometry": {"coordinates":[-2.514184,53.807835],"type":"Point"}
}