{
  "type": "Feature",
  "properties": {
    "addr:full":"15 Broom Way Liverpool Merseyside L26 1XN",
    "addr:housenumber":"15",
    "addr:postcode":"l26 1xn",
    "addr:street":"Broom Way",
    "iso:country":"GB",
    "sg:address":"15 Broom Way",
    "sg:city":"Liverpool",
    "sg:classifiers":[
        {
            "category":"Retail",
            "subcategory":"Storage",
            "type":"Services"
        }
    ],
    "sg:phone":"+44 151 486 6107",
    "sg:postcode":"L26 1XN",
    "sg:province":"Merseyside",
    "sg:tags":[
        "household",
        "removal"
    ],
    "wof:name":"A 2 B Delivery Service",
    "wof:placetype":"venue"
},
  "geometry": {"coordinates":[-2.84296,53.361004],"type":"Point"}
}