{
  "type": "Feature",
  "properties": {
    "addr:full":"Swan Centre X Pewsey Wiltshire SN9 5HL",
    "addr:postcode":"sn9 5hl",
    "addr:street":"Pewsey",
    "iso:country":"GB",
    "sg:address":"Swan Centre X",
    "sg:city":"Pewsey",
    "sg:classifiers":[
        {
            "category":"Professional",
            "type":"Services"
        }
    ],
    "sg:phone":"+44 1672 564648",
    "sg:postcode":"SN9 5HL",
    "sg:province":"Wiltshire",
    "sg:tags":[
        "repair",
        "tech",
        "maintenance"
    ],
    "wof:name":"Printer Genius Ltd.",
    "wof:placetype":"venue"
},
  "geometry": {"coordinates":[-1.762319,51.340286],"type":"Point"}
}