{
  "type": "Feature",
  "properties": {
    "addr:full":"54d Fraser Walk Kilmarnock East Ayrshire KA3 7NU",
    "addr:housenumber":"54d",
    "addr:postcode":"ka3 7nu",
    "addr:street":"Fraser Walk",
    "iso:country":"GB",
    "sg:address":"54d Fraser Walk",
    "sg:city":"Kilmarnock",
    "sg:classifiers":[
        {
            "category":"Building & Trades",
            "subcategory":"Construction",
            "type":"Services"
        }
    ],
    "sg:phone":"+44 1563 542435",
    "sg:postcode":"KA3 7NU",
    "sg:province":"East Ayrshire",
    "sg:tags":[
        "joiner",
        "carpenter"
    ],
    "wof:name":"William Law",
    "wof:placetype":"venue"
},
  "geometry": {"coordinates":[-4.47248,55.618191],"type":"Point"}
}