{
  "type": "Feature",
  "properties": {
    "addr:full":"Unit 3d Lillyburn Works, Campsie Road, Milton Of Campsie Glasgow East Dunbartonshire G66 8EE",
    "addr:housenumber":"unit",
    "addr:postcode":"g66 8ee",
    "addr:street":"Campsie Road",
    "iso:country":"GB",
    "sg:address":"Unit 3d Lillyburn Works, Campsie Road, Milton Of Campsie",
    "sg:city":"Glasgow",
    "sg:classifiers":[
        {
            "category":"Health Services",
            "subcategory":"Dentist",
            "type":"Services"
        }
    ],
    "sg:phone":"+44 1360 311979",
    "sg:postcode":"G66 8EE",
    "sg:province":"East Dunbartonshire",
    "sg:tags":[
        "technician",
        "instrument",
        "dental"
    ],
    "wof:name":"Appin Dental Laboratory",
    "wof:placetype":"venue"
},
  "geometry": {"coordinates":[-4.161323,55.964668],"type":"Point"}
}