{
  "type": "Feature",
  "properties": {
    "iso:country":"GB",
    "sg:address":"Lower Newhey Mill, Two Bridge Road Newhey",
    "sg:city":"Rochdale",
    "sg:classifiers":[
        {
            "category":"Professional",
            "subcategory":"Business Services",
            "type":"Services"
        }
    ],
    "sg:phone":"+44 1706 290008",
    "sg:postcode":"OL16 3SR",
    "sg:province":"Lancashire",
    "sg:tags":[
        "food",
        "import",
        "export",
        "agent"
    ],
    "wof:name":"P J  Beers (Wholesale) Ltd.",
    "wof:placetype":"venue"
},
  "geometry": {"coordinates":[-2.1038889885,53.6051864624],"type":"Point"}
}