{
  "type": "Feature",
  "properties": {
    "iso:country":"GB",
    "sg:address":"576 Leeds Rd, Outwood",
    "sg:city":"Wakefield",
    "sg:classifiers":[
        {
            "category":"Shopping",
            "subcategory":"Gifts & Souvenirs",
            "type":"Retail Goods"
        }
    ],
    "sg:phone":"+44 1924 871184",
    "sg:postcode":"WF1 2DT",
    "sg:province":"West Yorkshire",
    "sg:tags":[
        "shop"
    ],
    "wof:name":"Memories",
    "wof:placetype":"venue"
},
  "geometry": {"coordinates":[-1.5000649691,53.7118873596],"type":"Point"}
}