{
  "type": "Feature",
  "properties": {
    "iso:country":"GB",
    "sg:address":"61-63 Manse Road",
    "sg:city":"Motherwell",
    "sg:classifiers":[
        {
            "category":"Professional",
            "subcategory":"Engineering",
            "type":"Services"
        }
    ],
    "sg:phone":"+44 1698 267628",
    "sg:postcode":"ML1 2PW",
    "sg:province":"North Lanarkshire",
    "sg:tags":[
        "civil",
        "engineer"
    ],
    "wof:name":"D B M Consultants Ltd",
    "wof:placetype":"venue"
},
  "geometry": {"coordinates":[-3.982255,55.782051],"type":"Point"}
}