{
  "type": "Feature",
  "properties": {
    "addr:full":"Hurley Lane, Over Whitacre, Coleshill Birmingham Warwickshire B46 2LS",
    "addr:postcode":"b46 2ls",
    "addr:street":"Hurley Lane",
    "iso:country":"GB",
    "sg:address":"Hurley Lane, Over Whitacre, Coleshill",
    "sg:city":"Birmingham",
    "sg:classifiers":[
        {
            "category":"Farming",
            "subcategory":"Livestock Farm",
            "type":"Manufacturing & Wholesale Goods"
        }
    ],
    "sg:postcode":"B46 2LS",
    "sg:province":"Warwickshire",
    "sg:tags":[
        "others"
    ],
    "wof:name":"Grace Mary Knight & Son",
    "wof:placetype":"venue"
},
  "geometry": {"coordinates":[-1.629649,52.53492],"type":"Point"}
}