{
  "type": "Feature",
  "properties": {
    "addr:full":"Unit G, The Scope Complex, Wills Road Totnes Devon TQ9 5XN",
    "addr:housenumber":"unit g",
    "addr:postcode":"tq9 5xn",
    "addr:street":"The;Wills Road",
    "iso:country":"GB",
    "sg:address":"Unit G, The Scope Complex, Wills Road",
    "sg:city":"Totnes",
    "sg:classifiers":[
        {
            "category":"Professional",
            "subcategory":"Employment Agencies",
            "type":"Services"
        }
    ],
    "sg:phone":"+44 1803 862557",
    "sg:postcode":"TQ9 5XN",
    "sg:province":"Devon",
    "sg:tags":[
        "consultant"
    ],
    "wof:name":"South Hams Work Force",
    "wof:placetype":"venue"
},
  "geometry": {"coordinates":[-3.688092947,50.4341468811],"type":"Point"}
}