{
  "type": "Feature",
  "properties": {
    "iso:country":"GB",
    "sg:address":"47 Mill La",
    "sg:city":"Solihull",
    "sg:classifiers":[
        {
            "category":"Shopping",
            "subcategory":"Baby Store",
            "type":"Retail Goods"
        }
    ],
    "sg:phone":"+44 121 705 8825",
    "sg:postcode":"B91 3AT",
    "sg:province":"West Midlands",
    "sg:tags":[
        "nursery",
        "accessory"
    ],
    "wof:name":"Mothercare (U K) Ltd",
    "wof:placetype":"venue"
},
  "geometry": {"coordinates":[-1.7763370275,52.4145355225],"type":"Point"}
}