{
  "type": "Feature",
  "properties": {
    "addr:full":"Wynyard Development Offices, Salters House Billingham Durham TS22 5NQ",
    "addr:postcode":"ts22 5nq",
    "iso:country":"GB",
    "sg:address":"Wynyard Development Offices, Salters House",
    "sg:city":"Billingham",
    "sg:classifiers":[
        {
            "category":"Farming",
            "subcategory":"Livestock Farm",
            "type":"Manufacturing & Wholesale Goods"
        }
    ],
    "sg:postcode":"TS22 5NQ",
    "sg:province":"Durham",
    "sg:tags":[
        "others"
    ],
    "wof:name":"Cameron Hall Developments Ltd.",
    "wof:placetype":"venue"
},
  "geometry": {"coordinates":[-1.3074690104,54.6285095215],"type":"Point"}
}