{
  "type": "Feature",
  "properties": {
    "addr:full":"Bowker Bank Avenue Manchester Greater Manchester M8 4LD",
    "addr:postcode":"m8 4ld",
    "addr:street":"Bank Avenue",
    "iso:country":"GB",
    "sg:address":"Bowker Bank Avenue",
    "sg:city":"Manchester",
    "sg:classifiers":[
        {
            "category":"Retail",
            "subcategory":"Auto Repair",
            "type":"Services"
        }
    ],
    "sg:phone":"+44 161 795 9090",
    "sg:postcode":"M8 4LD",
    "sg:province":"Greater Manchester",
    "sg:tags":[
        "car",
        "upholsterer"
    ],
    "wof:name":"J & M Sherr",
    "wof:placetype":"venue"
},
  "geometry": {"coordinates":[-2.248769,53.518696],"type":"Point"}
}