{
  "type": "Feature",
  "properties": {
    "iso:country":"GB",
    "sg:address":"72 Ramsgate Road",
    "sg:city":"Margate",
    "sg:classifiers":[
        {
            "category":"Food & Beverages",
            "subcategory":"Bakery",
            "type":"Retail Goods"
        }
    ],
    "sg:phone":"+44 1843 293682",
    "sg:postcode":"CT9 5RY",
    "sg:province":"Kent",
    "sg:tags":[
        "baker"
    ],
    "wof:name":"The Bakehouse",
    "wof:placetype":"venue"
},
  "geometry": {"coordinates":[1.383891,51.379402],"type":"Point"}
}