{
  "type": "Feature",
  "properties": {
    "addr:full":"Lock House, Milby, Boroughbridge York North Yorkshire YO51 9BL",
    "addr:postcode":"yo51 9bl",
    "iso:country":"GB",
    "sg:address":"Lock House, Milby, Boroughbridge",
    "sg:city":"York",
    "sg:classifiers":[
        {
            "category":"Wholesale",
            "subcategory":"Construction Materials",
            "type":"Manufacturing & Wholesale Goods"
        }
    ],
    "sg:phone":"+44 1423 324626",
    "sg:postcode":"YO51 9BL",
    "sg:province":"North Yorkshire",
    "sg:tags":[
        "merchant",
        "brick"
    ],
    "wof:name":"Blockmere Brick & Tile Co",
    "wof:placetype":"venue"
},
  "geometry": {"coordinates":[-1.459394,54.091354],"type":"Point"}
}