{
  "type": "Feature",
  "properties": {
    "addr:full":"14 Quarry Park Ave, Plymstock Plymouth Devon PL9 7BE",
    "addr:housenumber":"14",
    "addr:postcode":"pl9 7be",
    "addr:street":"Quarry Park Ave",
    "iso:country":"GB",
    "sg:address":"14 Quarry Park Ave, Plymstock",
    "sg:city":"Plymouth",
    "sg:classifiers":[
        {
            "category":"Shopping",
            "subcategory":"Stationery & Office Supplies",
            "type":"Retail Goods"
        }
    ],
    "sg:postcode":"PL9 7BE",
    "sg:province":"Devon",
    "sg:tags":[
        "equipment"
    ],
    "wof:name":"Trenoweth,Kevin,",
    "wof:placetype":"venue"
},
  "geometry": {"coordinates":[-4.097934,50.358788],"type":"Point"}
}