{
  "type": "Feature",
  "properties": {
    "addr:full":"The Workshops, Kinleith Industrial Estate Currie City of Edinburgh EH14 6AA",
    "addr:postcode":"eh14 6aa",
    "addr:street":"Kinleith Industrial Estate",
    "iso:country":"GB",
    "sg:address":"The Workshops, Kinleith Industrial Estate",
    "sg:city":"Currie",
    "sg:classifiers":[
        {
            "category":"Manufacturing",
            "subcategory":"Furniture",
            "type":"Manufacturing & Wholesale Goods"
        }
    ],
    "sg:postcode":"EH14 6AA",
    "sg:province":"City of Edinburgh",
    "sg:tags":[
        "polishing",
        "french"
    ],
    "wof:name":"Stewart Sanderson French Polishing",
    "wof:placetype":"venue"
},
  "geometry": {"coordinates":[-3.307543993,55.8965950012],"type":"Point"}
}