{
  "type": "Feature",
  "properties": {
    "iso:country":"GB",
    "sg:address":"Lincoln Road",
    "sg:city":"Peterborough",
    "sg:classifiers":[
        {
            "category":"Bars & Pubs",
            "type":"Food & Drink"
        }
    ],
    "sg:phone":"+44 1733 571032",
    "sg:postcode":"PE4 6AX",
    "sg:province":"Cambridgeshire",
    "sg:tags":[
        "pubs",
        "inn"
    ],
    "wof:name":"Royal Oak Inn",
    "wof:placetype":"venue"
},
  "geometry": {"coordinates":[-0.284969,52.617874],"type":"Point"}
}