{
  "type": "Feature",
  "properties": {
    "iso:country":"GB",
    "sg:address":"5 Brampton Rd",
    "sg:city":"Bexleyheath",
    "sg:classifiers":[
        {
            "category":"Education",
            "subcategory":"University",
            "type":"Public Place"
        }
    ],
    "sg:phone":"+44 20 8303 2541",
    "sg:postcode":"DA7 4EZ",
    "sg:province":"Kent",
    "sg:tags":[
        "adult"
    ],
    "wof:name":"Adult Education College for Bexley",
    "wof:placetype":"venue"
},
  "geometry": {"coordinates":[0.126386,51.460884],"type":"Point"}
}