{
  "type": "Feature",
  "properties": {
    "addr:full":"82 Brattle Wood Sevenoaks Kent TN13 1QT",
    "addr:housenumber":"82",
    "addr:postcode":"tn13 1qt",
    "addr:street":"Brattle Wood",
    "iso:country":"GB",
    "sg:address":"82 Brattle Wood",
    "sg:city":"Sevenoaks",
    "sg:classifiers":[
        {
            "category":"Real Estate",
            "subcategory":"Architect",
            "type":"Services"
        }
    ],
    "sg:postcode":"TN13 1QT",
    "sg:province":"Kent",
    "wof:name":"Arthur Cooksey Chartered Architect",
    "wof:placetype":"venue"
},
  "geometry": {"coordinates":[0.1906069964,51.2520294189],"type":"Point"}
}