{
  "type": "Feature",
  "properties": {
    "addr:full":"6 Queen's Dr Tranent East Lothian EH34 5AP",
    "addr:housenumber":"6",
    "addr:postcode":"eh34 5ap",
    "addr:street":"Queen'S Dr",
    "iso:country":"GB",
    "sg:address":"6 Queen's Dr",
    "sg:city":"Tranent",
    "sg:classifiers":[
        {
            "category":"Health Services",
            "subcategory":"Clinic",
            "type":"Services"
        }
    ],
    "sg:phone":"+44 1875 340444",
    "sg:postcode":"EH34 5AP",
    "sg:province":"East Lothian",
    "sg:tags":[
        "aromatherapy"
    ],
    "wof:name":"Amanda Hazzard",
    "wof:placetype":"venue"
},
  "geometry": {"coordinates":[-2.974669,55.958305],"type":"Point"}
}