{
  "type": "Feature",
  "properties": {
    "iso:country":"GB",
    "sg:address":"Moorpark Road West",
    "sg:city":"Stevenston",
    "sg:classifiers":[
        {
            "category":"Sports & Exercise",
            "subcategory":"Golf",
            "type":"Entertainment"
        }
    ],
    "sg:phone":"+44 1294 603103",
    "sg:postcode":"KA20 3HU",
    "sg:province":"North Ayrshire",
    "sg:tags":[
        "club",
        "course"
    ],
    "wof:name":"Auchenharvie Golf Shop",
    "wof:placetype":"venue"
},
  "geometry": {"coordinates":[-4.754646,55.636108],"type":"Point"}
}