{
  "type": "Feature",
  "properties": {
    "addr:full":"Compton House, Carmarthen Road Llanelli Carmarthenshire SA14 7BA",
    "addr:postcode":"sa14 7ba",
    "addr:street":"Carmarthen Road",
    "iso:country":"GB",
    "sg:address":"Compton House, Carmarthen Road",
    "sg:city":"Llanelli",
    "sg:classifiers":[
        {
            "category":"Cafe",
            "type":"Food & Drink"
        }
    ],
    "sg:postcode":"SA14 7BA",
    "sg:province":"Carmarthenshire",
    "sg:tags":[
        "tea",
        "room"
    ],
    "wof:name":"Page 5 Cafe",
    "wof:placetype":"venue"
},
  "geometry": {"coordinates":[-4.1020641327,51.8008766174],"type":"Point"}
}