{
  "type": "Feature",
  "properties": {
    "addr:full":"Brackla Industrial Estate Bridgend Bridgend CF31 2AG",
    "addr:postcode":"cf31 2ag",
    "addr:street":"Estate",
    "iso:country":"GB",
    "sg:address":"Brackla Industrial Estate",
    "sg:city":"Bridgend",
    "sg:classifiers":[
        {
            "category":"Shopping",
            "subcategory":"Computers & Home Electronics",
            "type":"Retail Goods"
        }
    ],
    "sg:phone":"+44 1656 650680",
    "sg:postcode":"CF31 2AG",
    "sg:province":"Bridgend",
    "sg:tags":[
        "electrical"
    ],
    "wof:name":"Morris Line Equipment Co",
    "wof:placetype":"venue"
},
  "geometry": {"coordinates":[-3.5517749786,51.5041236877],"type":"Point"}
}