{
  "type": "Feature",
  "properties": {
    "iso:country":"GB",
    "sg:address":"6 Osier Close, Robinswood",
    "sg:city":"Gloucester",
    "sg:classifiers":[
        {
            "category":"Home & Garden",
            "subcategory":"Building Materials",
            "type":"Retail Goods"
        }
    ],
    "sg:phone":"+44 1452 301147",
    "sg:postcode":"GL4 6SP",
    "sg:province":"Gloucestershire",
    "sg:tags":[
        "ready",
        "mixed",
        "concrete"
    ],
    "wof:name":"P & P Concrete Mix",
    "wof:placetype":"venue"
},
  "geometry": {"coordinates":[-2.229627,51.841427],"type":"Point"}
}