{
  "type": "Feature",
  "properties": {
    "iso:country":"GB",
    "sg:address":"5a Ugie Road",
    "sg:city":"Peterhead",
    "sg:classifiers":[
        {
            "category":"Food & Beverages",
            "subcategory":"Bakery",
            "type":"Retail Goods"
        }
    ],
    "sg:phone":"+44 1779 470488",
    "sg:postcode":"AB42 1NA",
    "sg:province":"Aberdeenshire",
    "sg:tags":[
        "shop",
        "baker"
    ],
    "wof:name":"Ray Allan Ltd",
    "wof:placetype":"venue"
},
  "geometry": {"coordinates":[-1.789879,57.513908],"type":"Point"}
}