{
  "type": "Feature",
  "properties": {
    "iso:country":"GB",
    "sg:address":"7 North Parade Buildings",
    "sg:city":"Bath",
    "sg:classifiers":[
        {
            "category":"Organizations",
            "subcategory":"Non-profit Organization",
            "type":"Services"
        }
    ],
    "sg:phone":"+44 1225 477892",
    "sg:postcode":"BA1 1NY",
    "sg:province":"Bath and North East Somerset",
    "sg:tags":[
        "organisation",
        "voluntary",
        "charity"
    ],
    "wof:name":"Spa Care Line",
    "wof:placetype":"venue"
},
  "geometry": {"coordinates":[-2.3569829464,51.3806991577],"type":"Point"}
}