{
  "type": "Feature",
  "properties": {
    "addr:full":"44 Thornes Lane Wakefield West Yorkshire WF1 5RR",
    "addr:housenumber":"44",
    "addr:postcode":"wf1 5rr",
    "addr:street":"Thornes Lane",
    "iso:country":"GB",
    "sg:address":"44 Thornes Lane",
    "sg:city":"Wakefield",
    "sg:classifiers":[
        {
            "category":"Building & Trades",
            "subcategory":"Pest Control",
            "type":"Services"
        }
    ],
    "sg:phone":"+44 1924 380002",
    "sg:postcode":"WF1 5RR",
    "sg:province":"West Yorkshire",
    "sg:tags":[
        "corrosion",
        "prevention"
    ],
    "wof:name":"Counter Corrosion Engineering Ltd.",
    "wof:placetype":"venue"
},
  "geometry": {"coordinates":[-1.494414,53.674782],"type":"Point"}
}