{
  "type": "Feature",
  "properties": {
    "iso:country":"GB",
    "sg:address":"Hospital Road",
    "sg:city":"Builth Wells",
    "sg:classifiers":[
        {
            "category":"Travel",
            "subcategory":"Hotels & Motels",
            "type":"Entertainment"
        }
    ],
    "sg:phone":"+44 1982 553622",
    "sg:postcode":"LD2 3HH",
    "sg:province":"Powys",
    "sg:tags":[
        "self",
        "catering"
    ],
    "wof:name":"Little Lakes Ltd.",
    "wof:placetype":"venue"
},
  "geometry": {"coordinates":[-3.4075739384,52.1485099792],"type":"Point"}
}