{
  "type": "Feature",
  "properties": {
    "addr:full":"94 Stratford Road Birmingham West Midlands B11 1AN",
    "addr:housenumber":"94",
    "addr:postcode":"b11 1an",
    "addr:street":"Stratford Road",
    "iso:country":"GB",
    "sg:address":"94 Stratford Road",
    "sg:city":"Birmingham",
    "sg:classifiers":[
        {
            "category":"Autos & Motor Vehicles",
            "subcategory":"Auto Supplies",
            "type":"Retail Goods"
        },
        {
            "category":"Personal",
            "subcategory":"Skin Care",
            "type":"Services"
        }
    ],
    "sg:phone":"+44 121 773 9085",
    "sg:postcode":"B11 1AN",
    "sg:province":"West Midlands",
    "sg:tags":[
        "part",
        "motorcycle",
        "manufacturer",
        "accessory"
    ],
    "wof:name":"R G Spares",
    "wof:placetype":"venue"
},
  "geometry": {"coordinates":[-1.8773189783,52.4658317566],"type":"Point"}
}