{
  "type": "Feature",
  "properties": {
    "addr:full":"Clarendon House, 14 St Andrews Street Droitwich Worcestershire WR9 8DY",
    "addr:housenumber":"14",
    "addr:postcode":"wr9 8dy",
    "addr:street":"St Andrews Street",
    "iso:country":"GB",
    "sg:address":"Clarendon House, 14 St Andrews Street",
    "sg:city":"Droitwich",
    "sg:classifiers":[
        {
            "category":"Building & Trades",
            "subcategory":"Construction",
            "type":"Services"
        }
    ],
    "sg:phone":"+44 1905 840466",
    "sg:postcode":"WR9 8DY",
    "sg:province":"Worcestershire",
    "sg:tags":[
        "builder"
    ],
    "wof:name":"F I  Morris & Sons Ltd.",
    "wof:placetype":"venue"
},
  "geometry": {"coordinates":[-2.149228,52.267372],"type":"Point"}
}