{
  "type": "Feature",
  "properties": {
    "iso:country":"GB",
    "sg:address":"Central Retail Park, Great Ancoats Street",
    "sg:city":"Manchester",
    "sg:classifiers":[
        {
            "category":"Shopping",
            "subcategory":"Bicycles & Sporting Goods",
            "type":"Retail Goods"
        },
        {
            "category":"Sports & Exercise",
            "subcategory":"Sports Center",
            "type":"Entertainment"
        }
    ],
    "sg:phone":"+44 161 272 7270",
    "sg:postcode":"M4 6DJ",
    "sg:province":"Greater Manchester",
    "sg:tags":[
        "shop",
        "sale"
    ],
    "wof:name":"Sports Division Ltd.",
    "wof:placetype":"venue"
},
  "geometry": {"coordinates":[-2.2264471054,53.4816818237],"type":"Point"}
}