{
  "type": "Feature",
  "properties": {
    "addr:full":"35 West Street Trowbridge Wiltshire BA14 0AH",
    "addr:housenumber":"35",
    "addr:postcode":"ba14 0ah",
    "addr:street":"West Street",
    "iso:country":"GB",
    "sg:address":"35 West Street",
    "sg:city":"Trowbridge",
    "sg:classifiers":[
        {
            "category":"Health Services",
            "subcategory":"Clinic",
            "type":"Services"
        }
    ],
    "sg:phone":"+44 1225 353633",
    "sg:postcode":"BA14 0AH",
    "sg:province":"Wiltshire",
    "sg:tags":[
        "aromatherapy"
    ],
    "wof:name":"Sarah Charles",
    "wof:placetype":"venue"
},
  "geometry": {"coordinates":[-2.2158770561,51.3177185059],"type":"Point"}
}