{
  "type": "Feature",
  "properties": {
    "iso:country":"GB",
    "sg:address":"Po Box 39",
    "sg:city":"Blackburn",
    "sg:classifiers":[
        {
            "category":"Home & Garden",
            "subcategory":"Home Furnishings",
            "type":"Retail Goods"
        }
    ],
    "sg:phone":"+44 1254 691321",
    "sg:postcode":"BB1 3DB",
    "sg:province":"Lancashire",
    "sg:tags":[
        "wall",
        "wallpaper",
        "covering"
    ],
    "wof:name":"Graham & Brown Ltd.",
    "wof:placetype":"venue"
},
  "geometry": {"coordinates":[-2.453199,53.74966],"type":"Point"}
}