{
  "type": "Feature",
  "properties": {
    "addr:full":"Tudor House Farm, Oxlynch Stonehouse Gloucestershire GL10 3DF",
    "addr:postcode":"gl10 3df",
    "addr:street":"Oxlynch;Gloucestershire",
    "iso:country":"GB",
    "sg:address":"Tudor House Farm, Oxlynch",
    "sg:city":"Stonehouse",
    "sg:classifiers":[
        {
            "category":"Farming",
            "subcategory":"Livestock Farm",
            "type":"Manufacturing & Wholesale Goods"
        }
    ],
    "sg:phone":"+44 1453 822234",
    "sg:postcode":"GL10 3DF",
    "sg:province":"Gloucestershire",
    "sg:tags":[
        "others"
    ],
    "wof:name":"ALBERT B GALLOP",
    "wof:placetype":"venue"
},
  "geometry": {"coordinates":[-2.2618570328,51.7667579651],"type":"Point"}
}