{
  "type": "Feature",
  "properties": {
    "addr:full":"56a Upper Church Street Oswestry Shropshire SY11 2AF",
    "addr:housenumber":"56a",
    "addr:postcode":"sy11 2af",
    "addr:street":"Upper Church Street",
    "iso:country":"GB",
    "sg:address":"56a Upper Church Street",
    "sg:city":"Oswestry",
    "sg:classifiers":[
        {
            "category":"Retail",
            "subcategory":"Laundry & Dry Cleaning",
            "type":"Services"
        }
    ],
    "sg:phone":"+44 1691 659183",
    "sg:postcode":"SY11 2AF",
    "sg:province":"Shropshire",
    "sg:tags":[
        "launderette"
    ],
    "wof:name":"Oswestry Launderette",
    "wof:placetype":"venue"
},
  "geometry": {"coordinates":[-3.0583369732,52.8551750183],"type":"Point"}
}