{
  "type": "Feature",
  "properties": {
    "addr:full":"28a Ridgeway Crescent Tonbridge Kent TN10 4NP",
    "addr:housenumber":"28a",
    "addr:postcode":"tn10 4np",
    "addr:street":"Ridgeway Crescent",
    "iso:country":"GB",
    "sg:address":"28a Ridgeway Crescent",
    "sg:city":"Tonbridge",
    "sg:classifiers":[
        {
            "category":"Manufacturing",
            "subcategory":"Signs",
            "type":"Manufacturing & Wholesale Goods"
        }
    ],
    "sg:phone":"+44 1732 357824",
    "sg:postcode":"TN10 4NP",
    "sg:province":"Kent",
    "sg:tags":[
        "commercial",
        "maker"
    ],
    "wof:name":"Magnum Signs Ltd.",
    "wof:placetype":"venue"
},
  "geometry": {"coordinates":[0.288781,51.206528],"type":"Point"}
}