{
  "type": "Feature",
  "properties": {
    "addr:full":"64 The Moor Sheffield South Yorkshire S1 4PA",
    "addr:housenumber":"64",
    "addr:postcode":"s1 4pa",
    "addr:street":"The Moor",
    "iso:country":"GB",
    "sg:address":"64 The Moor",
    "sg:city":"Sheffield",
    "sg:classifiers":[
        {
            "category":"Shopping",
            "subcategory":"Clothing, Apparel, & Fashions",
            "type":"Retail Goods"
        }
    ],
    "sg:phone":"+44 114 249 3174",
    "sg:postcode":"S1 4PA",
    "sg:province":"South Yorkshire",
    "sg:tags":[
        "shop"
    ],
    "wof:name":"Melody Fashions",
    "wof:placetype":"venue"
},
  "geometry": {"coordinates":[-1.473636,53.376392],"type":"Point"}
}