{
  "type": "Feature",
  "properties": {
    "iso:country":"GB",
    "sg:address":"8 Ventura Centre, Ventura Pl",
    "sg:city":"Poole",
    "sg:classifiers":[
        {
            "category":"Home & Garden",
            "subcategory":"Building Materials",
            "type":"Retail Goods"
        }
    ],
    "sg:phone":"+44 1202 622405",
    "sg:postcode":"BH16 5SW",
    "sg:province":"Dorset",
    "sg:tags":[
        "ironwork",
        "diy",
        "wrought"
    ],
    "wof:name":"Quay Wrought Iron",
    "wof:placetype":"venue"
},
  "geometry": {"coordinates":[-2.02081,50.73521],"type":"Point"}
}