{
  "type": "Feature",
  "properties": {
    "addr:full":"Units 30 & 31 Sapcote Trading Centre, Powke Lane Cradley Heath West Midlands B64 5QR",
    "addr:housenumber":"units 30 & 31",
    "addr:postcode":"b64 5qr",
    "addr:street":"Powke Lane",
    "iso:country":"GB",
    "sg:address":"Units 30 & 31 Sapcote Trading Centre, Powke Lane",
    "sg:city":"Cradley Heath",
    "sg:classifiers":[
        {
            "category":"Building & Trades",
            "subcategory":"Electrical",
            "type":"Services"
        }
    ],
    "sg:postcode":"B64 5QR",
    "sg:province":"West Midlands",
    "sg:tags":[
        "galvanising"
    ],
    "wof:name":"Dudley Finishing Ltd",
    "wof:placetype":"venue"
},
  "geometry": {"coordinates":[-2.0631699562,52.4836502075],"type":"Point"}
}