{
  "type": "Feature",
  "properties": {
    "iso:country":"GB",
    "sg:address":"Heath House, Chester Road, Ternhill",
    "sg:city":"Market Drayton",
    "sg:classifiers":[
        {
            "category":"Home & Garden",
            "subcategory":"Garden Supply",
            "type":"Retail Goods"
        }
    ],
    "sg:postcode":"TF9 2JQ",
    "sg:province":"Shropshire",
    "sg:tags":[
        "merchant",
        "seed"
    ],
    "wof:name":"Eddie Palin Distribution Ltd.",
    "wof:placetype":"venue"
},
  "geometry": {"coordinates":[-2.51624,52.871471],"type":"Point"}
}