{
  "type": "Feature",
  "properties": {
    "iso:country":"GB",
    "sg:address":"Cymric House, Bethany Square",
    "sg:city":"Port Talbot",
    "sg:classifiers":[
        {
            "category":"Professional",
            "subcategory":"Business Services",
            "type":"Services"
        },
        {
            "category":"Government",
            "subcategory":"Office",
            "type":"Public Place"
        }
    ],
    "sg:phone":"+44 1639 895173",
    "sg:postcode":"SA13 1PQ",
    "sg:province":"Neath Port Talbot",
    "sg:tags":[
        "trade",
        "agency",
        "enterprise"
    ],
    "wof:name":"Business Connect Neath Port Talbot Ltd",
    "wof:placetype":"venue"
},
  "geometry": {"coordinates":[-3.7801,51.596191],"type":"Point"}
}