{
  "type": "Feature",
  "properties": {
    "addr:full":"16 Heather Court, Ty Canol Cwmbran Monmouthshire NP44 6JQ",
    "addr:housenumber":"16",
    "addr:postcode":"np44 6jq",
    "addr:street":"Heather Court Ty Canol",
    "iso:country":"GB",
    "sg:address":"16 Heather Court, Ty Canol",
    "sg:city":"Cwmbran",
    "sg:classifiers":[
        {
            "category":"Parking",
            "subcategory":"Bicycle",
            "type":"Transportation"
        }
    ],
    "sg:phone":"+44 1633 485573",
    "sg:postcode":"NP44 6JQ",
    "sg:province":"Monmouthshire",
    "sg:tags":[
        "accessory",
        "cycle"
    ],
    "wof:name":"Dragon Roofbox Company",
    "wof:placetype":"venue"
},
  "geometry": {"coordinates":[-3.059458,51.643307],"type":"Point"}
}