{
  "type": "Feature",
  "properties": {
    "addr:full":"Unit 1, Lido Centre, Ethelbert Terrace, Cliftonville Margate Margate Kent CT9 1RX",
    "addr:housenumber":"unit 1",
    "addr:postcode":"ct9 1rx",
    "addr:street":"Lido Centre Ethelbert Terrace;Margate Margate",
    "iso:country":"GB",
    "sg:address":"Unit 1, Lido Centre, Ethelbert Terrace, Cliftonville Margate",
    "sg:city":"Margate",
    "sg:classifiers":[
        {
            "category":"Communications",
            "subcategory":"Film & Video Production",
            "type":"Services"
        }
    ],
    "sg:phone":"+44 1843 225316",
    "sg:postcode":"CT9 1RX",
    "sg:province":"Kent",
    "sg:tags":[
        "illustrator",
        "artist"
    ],
    "wof:name":"A.L.G Mosaics",
    "wof:placetype":"venue"
},
  "geometry": {"coordinates":[1.379247,51.386662],"type":"Point"}
}