{
  "type": "Feature",
  "properties": {
    "addr:full":"2a Trinity Street Bungay Norfolk NR35 1EQ",
    "addr:housenumber":"2a",
    "addr:postcode":"nr35 1eq",
    "addr:street":"Trinity Street",
    "iso:country":"GB",
    "sg:address":"2a Trinity Street",
    "sg:city":"Bungay",
    "sg:classifiers":[
        {
            "category":"Home & Garden",
            "subcategory":"Furniture",
            "type":"Retail Goods"
        }
    ],
    "sg:phone":"+44 1986 892889",
    "sg:postcode":"NR35 1EQ",
    "sg:province":"Norfolk",
    "sg:tags":[
        "outlet"
    ],
    "wof:name":"H Wightman & Son Ltd.",
    "wof:placetype":"venue"
},
  "geometry": {"coordinates":[1.437735,52.456108],"type":"Point"}
}