{
  "type": "Feature",
  "properties": {
    "addr:full":"171 Glasgow Road Dumbarton Argyll and Bute G82 1RH",
    "addr:housenumber":"171",
    "addr:postcode":"g82 1rh",
    "addr:street":"Glasgow Road",
    "iso:country":"GB",
    "sg:address":"171 Glasgow Road",
    "sg:city":"Dumbarton",
    "sg:classifiers":[
        {
            "category":"Shopping",
            "subcategory":"News",
            "type":"Retail Goods"
        }
    ],
    "sg:postcode":"G82 1RH",
    "sg:province":"Argyll and Bute",
    "sg:tags":[
        "newsagent"
    ],
    "wof:name":"Station Newsagents",
    "wof:placetype":"venue"
},
  "geometry": {"coordinates":[-4.553298,55.942036],"type":"Point"}
}