{
  "type": "Feature",
  "properties": {
    "iso:country":"GB",
    "sg:address":"Banton Mill, Mill Road, Banton",
    "sg:city":"Glasgow",
    "sg:classifiers":[
        {
            "category":"Building & Trades",
            "subcategory":"Construction",
            "type":"Services"
        }
    ],
    "sg:phone":"+44 1236 823011",
    "sg:postcode":"G65 0QG",
    "sg:province":"East Dunbartonshire",
    "sg:tags":[
        "builder"
    ],
    "wof:name":"J B  Bennett Ltd.",
    "wof:placetype":"venue"
},
  "geometry": {"coordinates":[-4.01099,55.98785],"type":"Point"}
}