{
  "type": "Feature",
  "properties": {
    "addr:full":"Abernant Farm, Llandeloy Haverfordwest Pembrokeshire SA62 6ND",
    "addr:housenumber":"abernant",
    "addr:postcode":"sa62 6nd",
    "addr:street":"Llandeloy;Pembrokeshire",
    "iso:country":"GB",
    "sg:address":"Abernant Farm, Llandeloy",
    "sg:city":"Haverfordwest",
    "sg:classifiers":[
        {
            "category":"Farming",
            "subcategory":"Livestock Farm",
            "type":"Manufacturing & Wholesale Goods"
        }
    ],
    "sg:phone":"+44 1348 831227",
    "sg:postcode":"SA62 6ND",
    "sg:province":"Pembrokeshire",
    "sg:tags":[
        "others"
    ],
    "wof:name":"M L Thomas",
    "wof:placetype":"venue"
},
  "geometry": {"coordinates":[-5.1159591675,51.8984107971],"type":"Point"}
}