{
  "type": "Feature",
  "properties": {
    "addr:full":"52-56 High Street, Cheam Sutton Surrey SM3 8RW",
    "addr:housenumber":"52-56",
    "addr:postcode":"sm3 8rw",
    "addr:street":"High Street",
    "iso:country":"GB",
    "sg:address":"52-56 High Street, Cheam",
    "sg:city":"Sutton",
    "sg:classifiers":[
        {
            "category":"Personal",
            "subcategory":"Nail Salon",
            "type":"Services"
        }
    ],
    "sg:phone":"+44 20 8770 9026",
    "sg:postcode":"SM3 8RW",
    "sg:province":"Surrey",
    "sg:tags":[
        "solarium",
        "tanning"
    ],
    "wof:name":"Tanfastic",
    "wof:placetype":"venue"
},
  "geometry": {"coordinates":[-0.2147810012,51.3580551147],"type":"Point"}
}