{
  "type": "Feature",
  "properties": {
    "addr:full":"179 Lyndhurst Road Lyndhurst Hampshire SO40 7AR",
    "addr:housenumber":"179",
    "addr:postcode":"so40 7ar",
    "addr:street":"Lyndhurst Road",
    "iso:country":"GB",
    "sg:address":"179 Lyndhurst Road",
    "sg:city":"Lyndhurst",
    "sg:classifiers":[
        {
            "category":"Restaurant",
            "type":"Food & Drink"
        }
    ],
    "sg:phone":"+44 23 8029 2885",
    "sg:postcode":"SO40 7AR",
    "sg:province":"Hampshire",
    "sg:tags":[
        "indian"
    ],
    "wof:name":"Euro-Asia Indian Cuisine",
    "wof:placetype":"venue"
},
  "geometry": {"coordinates":[-1.5228600502,50.8921394348],"type":"Point"}
}