{
  "type": "Feature",
  "properties": {
    "addr:full":"32 South Rd Liverpool Merseyside L22 5PQ",
    "addr:housenumber":"32",
    "addr:postcode":"l22 5pq",
    "addr:street":"South Rd",
    "iso:country":"GB",
    "sg:address":"32 South Rd",
    "sg:city":"Liverpool",
    "sg:classifiers":[
        {
            "category":"Bars & Pubs",
            "type":"Food & Drink"
        },
        {
            "category":"Community Center",
            "subcategory":"Social",
            "type":"Public Place"
        }
    ],
    "sg:phone":"+44 151 928 4578",
    "sg:postcode":"L22 5PQ",
    "sg:province":"Merseyside",
    "sg:tags":[
        "pubs",
        "house",
        "inn",
        "activity"
    ],
    "wof:name":"Raven Hotel",
    "wof:placetype":"venue"
},
  "geometry": {"coordinates":[-3.0276489258,53.4740066528],"type":"Point"}
}