{
  "type": "Feature",
  "properties": {
    "addr:full":"Unit 13/14 Baltic Works, Effingham Road Sheffield South Yorkshire S9 3QA",
    "addr:housenumber":"unit 13 / 14 baltic works",
    "addr:postcode":"s9 3qa",
    "addr:street":"Effingham Road",
    "iso:country":"GB",
    "sg:address":"Unit 13/14 Baltic Works, Effingham Road",
    "sg:city":"Sheffield",
    "sg:classifiers":[
        {
            "category":"Professional",
            "subcategory":"Engineering",
            "type":"Services"
        }
    ],
    "sg:phone":"+44 114 244 3070",
    "sg:postcode":"S9 3QA",
    "sg:province":"South Yorkshire",
    "wof:name":"J & J Cowen Engineering",
    "wof:placetype":"venue"
},
  "geometry": {"coordinates":[-1.43967,53.38995],"type":"Point"}
}