{
  "type": "Feature",
  "properties": {
    "addr:full":"15 North Street Haverfordwest Pembrokeshire SA61 2JE",
    "addr:housenumber":"15",
    "addr:postcode":"sa61 2je",
    "addr:street":"North Street",
    "iso:country":"GB",
    "sg:address":"15 North Street",
    "sg:city":"Haverfordwest",
    "sg:classifiers":[
        {
            "category":"Health Services",
            "subcategory":"Health Practitioner",
            "type":"Services"
        }
    ],
    "sg:postcode":"SA61 2JE",
    "sg:province":"Pembrokeshire",
    "sg:tags":[
        "osteopath"
    ],
    "wof:name":"Richard Blacklaw-Jones",
    "wof:placetype":"venue"
},
  "geometry": {"coordinates":[-4.9718427658,51.803653717],"type":"Point"}
}