{
  "type": "Feature",
  "properties": {
    "iso:country":"GB",
    "sg:address":"Methlick",
    "sg:city":"Ellon",
    "sg:classifiers":[
        {
            "category":"Farming",
            "subcategory":"Farm",
            "type":"Manufacturing & Wholesale Goods"
        }
    ],
    "sg:phone":"+44 1651 806264",
    "sg:postcode":"AB41 7HB",
    "sg:province":"Aberdeenshire",
    "sg:tags":[
        "mixed",
        "crop"
    ],
    "wof:name":"George B Duncan",
    "wof:placetype":"venue"
},
  "geometry": {"coordinates":[-2.236974,57.423897],"type":"Point"}
}