{
  "type": "Feature",
  "properties": {
    "addr:full":"155 Cotterills Lane Birmingham West Midlands B8 3RY",
    "addr:housenumber":"155",
    "addr:postcode":"b8 3ry",
    "addr:street":"Cotterills Lane",
    "iso:country":"GB",
    "sg:address":"155 Cotterills Lane",
    "sg:city":"Birmingham",
    "sg:classifiers":[
        {
            "category":"Professional",
            "subcategory":"Lawyer & Legal Services",
            "type":"Services"
        },
        {
            "category":"Government",
            "subcategory":"Office",
            "type":"Public Place"
        }
    ],
    "sg:phone":"+44 121 327 0883",
    "sg:postcode":"B8 3RY",
    "sg:province":"West Midlands",
    "sg:tags":[
        "advice",
        "local",
        "counselling"
    ],
    "wof:name":"East Birmingham Allotment Holders' Association Ltd",
    "wof:placetype":"venue"
},
  "geometry": {"coordinates":[-1.8267240524,52.4859733582],"type":"Point"}
}