{
  "type": "Feature",
  "properties": {
    "addr:full":"6 Long House, Bush Fair Harlow Essex CM18 6NR",
    "addr:housenumber":"6",
    "addr:postcode":"cm18 6nr",
    "addr:street":"Long House Bush Fair",
    "iso:country":"GB",
    "sg:address":"6 Long House, Bush Fair",
    "sg:city":"Harlow",
    "sg:classifiers":[
        {
            "category":"Cinema",
            "subcategory":"Movie Rental",
            "type":"Entertainment"
        }
    ],
    "sg:postcode":"CM18 6NR",
    "sg:province":"Essex",
    "sg:tags":[
        "video",
        "library"
    ],
    "wof:name":"Chris Chisnell",
    "wof:placetype":"venue"
},
  "geometry": {"coordinates":[0.1126,51.757229],"type":"Point"}
}