{
  "type": "Feature",
  "properties": {
    "iso:country":"GB",
    "sg:address":"Gough House, Madeira Avenue",
    "sg:city":"Horsham",
    "sg:classifiers":[
        {
            "category":"Organizations",
            "subcategory":"Political Organization",
            "type":"Services"
        }
    ],
    "sg:phone":"+44 1403 242000",
    "sg:postcode":"RH12 1AB",
    "sg:province":"West Sussex",
    "sg:tags":[
        "party"
    ],
    "wof:name":"Horsham Conservative Association",
    "wof:placetype":"venue"
},
  "geometry": {"coordinates":[-0.326270014,51.0641021729],"type":"Point"}
}