{
  "type": "Feature",
  "properties": {
    "iso:country":"GB",
    "sg:address":"27 Andover Road",
    "sg:city":"Cheltenham",
    "sg:classifiers":[
        {
            "category":"Professional",
            "subcategory":"Management & Consulting",
            "type":"Services"
        }
    ],
    "sg:phone":"+44 1452 563056",
    "sg:postcode":"GL50 2TB",
    "sg:province":"Gloucestershire",
    "sg:tags":[
        "marketing",
        "consultant"
    ],
    "wof:name":"Hodsons Ltd.",
    "wof:placetype":"venue"
},
  "geometry": {"coordinates":[-2.0850560665,51.8919258118],"type":"Point"}
}