{
  "type": "Feature",
  "properties": {
    "addr:full":"176 Bransford Road, St John's Worcester Worcestershire WR2 4EX",
    "addr:housenumber":"176",
    "addr:postcode":"wr2 4ex",
    "addr:street":"Bransford Road",
    "iso:country":"GB",
    "sg:address":"176 Bransford Road, St John's",
    "sg:city":"Worcester",
    "sg:classifiers":[
        {
            "category":"Home & Garden",
            "subcategory":"Garden Supply",
            "type":"Retail Goods"
        }
    ],
    "sg:phone":"+44 1905 425854",
    "sg:postcode":"WR2 4EX",
    "sg:province":"Worcestershire",
    "sg:tags":[
        "fertiliser"
    ],
    "wof:name":"Soilrite",
    "wof:placetype":"venue"
},
  "geometry": {"coordinates":[-2.24422,52.185188],"type":"Point"}
}