{
  "type": "Feature",
  "properties": {
    "addr:full":"Trelawn House, 34 North Bar Street Banbury Oxfordshire OX16 0TH",
    "addr:housenumber":"34",
    "addr:postcode":"ox16 0th",
    "addr:street":"North Bar Street",
    "iso:country":"GB",
    "sg:address":"Trelawn House, 34 North Bar Street",
    "sg:city":"Banbury",
    "sg:classifiers":[
        {
            "category":"Social Services",
            "subcategory":"Job Training",
            "type":"Services"
        },
        {
            "category":"Education",
            "subcategory":"Special Training",
            "type":"Public Place"
        }
    ],
    "sg:phone":"+44 1295 253253",
    "sg:postcode":"OX16 0TH",
    "sg:province":"Oxfordshire",
    "sg:tags":[
        "product",
        "centre"
    ],
    "wof:name":"Baseline Projects Ltd",
    "wof:placetype":"venue"
},
  "geometry": {"coordinates":[-1.3396320343,52.0634765625],"type":"Point"}
}