{
  "type": "Feature",
  "properties": {
    "iso:country":"GB",
    "sg:address":"94 Hope St",
    "sg:city":"Glasgow",
    "sg:classifiers":[
        {
            "category":"Food & Beverages",
            "subcategory":"Meat & Fish",
            "type":"Retail Goods"
        }
    ],
    "sg:postcode":"G2 6QA",
    "sg:province":"Glasgow City",
    "sg:tags":[
        "merchant"
    ],
    "wof:name":"T R Shellfish Ltd",
    "wof:placetype":"venue"
},
  "geometry": {"coordinates":[-4.258401,55.861187],"type":"Point"}
}