{
  "type": "Feature",
  "properties": {
    "iso:country":"GB",
    "sg:address":"246 Albert Drive",
    "sg:city":"Glasgow",
    "sg:classifiers":[
        {
            "category":"Shopping",
            "subcategory":"Used Merchandise",
            "type":"Retail Goods"
        }
    ],
    "sg:phone":"+44 141 429 5014",
    "sg:postcode":"G41 2NL",
    "sg:province":"Glasgow City",
    "sg:tags":[
        "shop",
        "second-hand"
    ],
    "wof:name":"Hardware Superstore",
    "wof:placetype":"venue"
},
  "geometry": {"coordinates":[-4.2744889259,55.8426933289],"type":"Point"}
}