{
  "type": "Feature",
  "properties": {
    "addr:full":"127 Brook St Glasgow Glasgow City G40 3AP",
    "addr:housenumber":"127",
    "addr:postcode":"g40 3ap",
    "addr:street":"Brook St",
    "iso:country":"GB",
    "sg:address":"127 Brook St",
    "sg:city":"Glasgow",
    "sg:classifiers":[
        {
            "category":"Real Estate",
            "subcategory":"Real Estate Operator",
            "type":"Services"
        }
    ],
    "sg:phone":"+44 141 550 7215",
    "sg:postcode":"G40 3AP",
    "sg:province":"Glasgow City",
    "sg:tags":[
        "letting",
        "agent"
    ],
    "wof:name":"One To Let",
    "wof:placetype":"venue"
},
  "geometry": {"coordinates":[-4.2220110893,55.8500862122],"type":"Point"}
}