{
  "type": "Feature",
  "properties": {
    "addr:full":"128 Cooden Sea Road Bexhill-on-sea East Sussex TN39 4TA",
    "addr:housenumber":"128",
    "addr:postcode":"tn39 4ta",
    "addr:street":"Cooden Sea Road",
    "iso:country":"GB",
    "sg:address":"128 Cooden Sea Road",
    "sg:city":"Bexhill-on-sea",
    "sg:classifiers":[
        {
            "category":"Real Estate",
            "subcategory":"Architect",
            "type":"Services"
        }
    ],
    "sg:postcode":"TN39 4TA",
    "sg:province":"East Sussex",
    "sg:tags":[
        "architectural"
    ],
    "wof:name":"Brian King",
    "wof:placetype":"venue"
},
  "geometry": {"coordinates":[0.4319700003,50.8403053284],"type":"Point"}
}