{
  "type": "Feature",
  "properties": {
    "iso:country":"GB",
    "sg:address":"31 St Mary's Road, Ashvale",
    "sg:city":"Aldershot",
    "sg:classifiers":[
        {
            "category":"Building & Trades",
            "subcategory":"Construction",
            "type":"Services"
        }
    ],
    "sg:phone":"+44 1252 343223",
    "sg:postcode":"GU12 5JD",
    "sg:province":"Hampshire",
    "sg:tags":[
        "flooring"
    ],
    "wof:name":"M D C Flooring Services",
    "wof:placetype":"venue"
},
  "geometry": {"coordinates":[-0.730155,51.244076],"type":"Point"}
}