{
  "type": "Feature",
  "properties": {
    "iso:country":"GB",
    "sg:address":"32 The Rodings",
    "sg:city":"Leigh On Sea",
    "sg:classifiers":[
        {
            "category":"Retail",
            "subcategory":"Driving School",
            "type":"Services"
        }
    ],
    "sg:phone":"+44 1702 522343",
    "sg:postcode":"SS9 5AZ",
    "sg:province":"Essex",
    "wof:name":"Fairway School Of Motoring",
    "wof:placetype":"venue"
},
  "geometry": {"coordinates":[0.6495820284,51.5709495544],"type":"Point"}
}