{
  "type": "Feature",
  "properties": {
    "addr:full":"38 Mill Street, Armthorpe Doncaster South Yorkshire DN3 3DL",
    "addr:housenumber":"38",
    "addr:postcode":"dn3 3dl",
    "addr:street":"Mill Street",
    "iso:country":"GB",
    "sg:address":"38 Mill Street, Armthorpe",
    "sg:city":"Doncaster",
    "sg:classifiers":[
        {
            "category":"Food & Beverages",
            "subcategory":"Groceries & Convenience Stores",
            "type":"Retail Goods"
        }
    ],
    "sg:phone":"+44 1302 831603",
    "sg:postcode":"DN3 3DL",
    "sg:province":"South Yorkshire",
    "wof:name":"DAY & NITE STORES LTD",
    "wof:placetype":"venue"
},
  "geometry": {"coordinates":[-1.0508509874,53.5362091064],"type":"Point"}
}