{
  "type": "Feature",
  "properties": {
    "iso:country":"GB",
    "sg:address":"Stapol House, 10 Billing Road",
    "sg:city":"Northampton",
    "sg:classifiers":[
        {
            "category":"Wholesale",
            "subcategory":"Chemicals & Plastics",
            "type":"Manufacturing & Wholesale Goods"
        }
    ],
    "sg:phone":"+44 1469 572464",
    "sg:postcode":"NN1 5AW",
    "sg:province":"Northamptonshire",
    "sg:tags":[
        "product",
        "allied"
    ],
    "wof:name":"Cray Valley Kunstharze Gmbh",
    "wof:placetype":"venue"
},
  "geometry": {"coordinates":[-0.88583,52.237904],"type":"Point"}
}