{
  "type": "Feature",
  "properties": {
    "addr:full":"Abbotts Works, Northern Road Newark Nottinghamshire NG24 2EH",
    "addr:postcode":"ng24 2eh",
    "addr:street":"Northern Road",
    "iso:country":"GB",
    "sg:address":"Abbotts Works, Northern Road",
    "sg:city":"Newark",
    "sg:classifiers":[
        {
            "category":"Retail",
            "subcategory":"Auto Repair",
            "type":"Services"
        }
    ],
    "sg:postcode":"NG24 2EH",
    "sg:province":"Nottinghamshire",
    "sg:tags":[
        "modification",
        "garage"
    ],
    "wof:name":"T P M Citreon Service & Repairs",
    "wof:placetype":"venue"
},
  "geometry": {"coordinates":[-0.8093469739,53.0738945007],"type":"Point"}
}