{
  "type": "Feature",
  "properties": {
    "iso:country":"GB",
    "sg:address":"1 Saxon Court, High Street, Bidford On Avon",
    "sg:city":"Alcester",
    "sg:classifiers":[
        {
            "category":"Food & Beverages",
            "subcategory":"Meat & Fish",
            "type":"Retail Goods"
        }
    ],
    "sg:postcode":"B50 4AB",
    "sg:province":"Warwickshire",
    "sg:tags":[
        "butcher"
    ],
    "wof:name":"Gordon's High Class Butchers",
    "wof:placetype":"venue"
},
  "geometry": {"coordinates":[-1.856308,52.164665],"type":"Point"}
}