{
  "type": "Feature",
  "properties": {
    "addr:full":"3 Miles Ct, Bierton Aylesbury Buckinghamshire HP22 5BA",
    "addr:housenumber":"3",
    "addr:postcode":"hp22 5ba",
    "addr:street":"Miles Ct",
    "iso:country":"GB",
    "sg:address":"3 Miles Ct, Bierton",
    "sg:city":"Aylesbury",
    "sg:classifiers":[
        {
            "category":"Shopping",
            "subcategory":"Computers & Home Electronics",
            "type":"Retail Goods"
        }
    ],
    "sg:phone":"+44 1296 421253",
    "sg:postcode":"HP22 5BA",
    "sg:province":"Buckinghamshire",
    "sg:tags":[
        "equipment",
        "audio-visual"
    ],
    "wof:name":"Seretech (U K) Ltd",
    "wof:placetype":"venue"
},
  "geometry": {"coordinates":[-0.785949,51.831413],"type":"Point"}
}