{
  "type": "Feature",
  "properties": {
    "addr:full":"Summerhill Farm, Tremeirchion St Asaph Conwy LL17 0UE",
    "addr:postcode":"ll17 0ue",
    "addr:street":"Tremeirchion St Asaph",
    "iso:country":"GB",
    "sg:address":"Summerhill Farm, Tremeirchion",
    "sg:city":"St Asaph",
    "sg:classifiers":[
        {
            "category":"Professional",
            "type":"Services"
        },
        {
            "category":"Farming",
            "subcategory":"Livestock Farm",
            "type":"Manufacturing & Wholesale Goods"
        }
    ],
    "sg:phone":"+44 1745 710391",
    "sg:postcode":"LL17 0UE",
    "sg:province":"Conwy",
    "sg:tags":[
        "agricultural",
        "others",
        "contractor"
    ],
    "wof:name":"E W Evans",
    "wof:placetype":"venue"
},
  "geometry": {"coordinates":[-3.444866,53.256863],"type":"Point"}
}