{
  "type": "Feature",
  "properties": {
    "addr:full":"2-3 The Exchange, Purley Rd Purley Surrey CR8 2HA",
    "addr:housenumber":"2-3",
    "addr:postcode":"cr8 2ha",
    "addr:street":"The Exchange Purley Rd",
    "iso:country":"GB",
    "sg:address":"2-3 The Exchange, Purley Rd",
    "sg:city":"Purley",
    "sg:classifiers":[
        {
            "category":"Professional",
            "subcategory":"Accounting & Tax Preparation",
            "type":"Services"
        }
    ],
    "sg:phone":"+44 20 8660 6066",
    "sg:postcode":"CR8 2HA",
    "sg:province":"Surrey",
    "sg:tags":[
        "accountant"
    ],
    "wof:name":"Accounting Centre The",
    "wof:placetype":"venue"
},
  "geometry": {"coordinates":[-0.1167339981,51.3386650085],"type":"Point"}
}