{
  "type": "Feature",
  "properties": {
    "addr:full":"Stockdale Hall, Heads Nook Brampton Cumbria CA8 9AF",
    "addr:postcode":"ca8 9af",
    "iso:country":"GB",
    "sg:address":"Stockdale Hall, Heads Nook",
    "sg:city":"Brampton",
    "sg:classifiers":[
        {
            "category":"Home & Garden",
            "subcategory":"Garden Supply",
            "type":"Retail Goods"
        }
    ],
    "sg:postcode":"CA8 9AF",
    "sg:province":"Cumbria",
    "sg:tags":[
        "bulb",
        "grower"
    ],
    "wof:name":"Messrs G H Soulsby",
    "wof:placetype":"venue"
},
  "geometry": {"coordinates":[-2.7908840179,54.8896636963],"type":"Point"}
}