{
  "type": "Feature",
  "properties": {
    "addr:full":"Unit 1 Longmore House, Cromer Road Birmingham West Midlands B12 9QP",
    "addr:housenumber":"unit 1 longmore house",
    "addr:postcode":"b12 9qp",
    "addr:street":"Cromer Road",
    "iso:country":"GB",
    "sg:address":"Unit 1 Longmore House, Cromer Road",
    "sg:city":"Birmingham",
    "sg:classifiers":[
        {
            "category":"Professional",
            "subcategory":"Accounting & Tax Preparation",
            "type":"Services"
        }
    ],
    "sg:phone":"+44 121 449 4383",
    "sg:postcode":"B12 9QP",
    "sg:province":"West Midlands",
    "sg:tags":[
        "accountant"
    ],
    "wof:name":"J E L & Co",
    "wof:placetype":"venue"
},
  "geometry": {"coordinates":[-1.890833,52.454189],"type":"Point"}
}