{
  "type": "Feature",
  "properties": {
    "addr:full":"Unit 12 Kemps Farm Chapel Road, Ford Aylesbury Buckinghamshire HP17 8XG",
    "addr:housenumber":"unit 12",
    "addr:postcode":"hp17 8xg",
    "addr:street":"Kemps Farm Chapel Road",
    "iso:country":"GB",
    "sg:address":"Unit 12 Kemps Farm Chapel Road, Ford",
    "sg:city":"Aylesbury",
    "sg:classifiers":[
        {
            "category":"Manufacturing",
            "subcategory":"Metals",
            "type":"Manufacturing & Wholesale Goods"
        },
        {
            "category":"Building & Trades",
            "subcategory":"Construction",
            "type":"Services"
        }
    ],
    "sg:phone":"+44 1296 748995",
    "sg:postcode":"HP17 8XG",
    "sg:province":"Buckinghamshire",
    "sg:tags":[
        "steel",
        "fabricator",
        "welder",
        "erectors"
    ],
    "wof:name":"Bucks Welding & Fabrication",
    "wof:placetype":"venue"
},
  "geometry": {"coordinates":[-0.8747289777,51.7781295776],"type":"Point"}
}