{
  "type": "Feature",
  "properties": {
    "addr:full":"Wartell Bank, Kingswinford Brierley Hill Staffordshire DY6 7QJ",
    "addr:postcode":"dy6 7qj",
    "addr:street":"Kingswinford;Hill",
    "iso:country":"GB",
    "sg:address":"Wartell Bank, Kingswinford",
    "sg:city":"Brierley Hill",
    "sg:classifiers":[
        {
            "category":"Building & Trades",
            "subcategory":"Landscaping Services",
            "type":"Services"
        }
    ],
    "sg:postcode":"DY6 7QJ",
    "sg:province":"Staffordshire",
    "sg:tags":[
        "pond",
        "aquarium"
    ],
    "wof:name":"Wartell Bank Nursery & Aquatics",
    "wof:placetype":"venue"
},
  "geometry": {"coordinates":[-2.165039,52.501564],"type":"Point"}
}