{
  "type": "Feature",
  "properties": {
    "addr:full":"Unit 15 Smiths Clo, Chasetown Indust Est, Chase Terr Burntwood Staffordshire WS7 8FX",
    "addr:housenumber":"unit 15",
    "addr:postcode":"ws7 8fx",
    "addr:street":"Smiths Clo Chasetown Indust Est Chase Terr",
    "iso:country":"GB",
    "sg:address":"Unit 15 Smiths Clo, Chasetown Indust Est, Chase Terr",
    "sg:city":"Burntwood",
    "sg:classifiers":[
        {
            "category":"Home & Garden",
            "subcategory":"Hardware",
            "type":"Retail Goods"
        }
    ],
    "sg:phone":"+44 1543 673100",
    "sg:postcode":"WS7 8FX",
    "sg:province":"Staffordshire",
    "sg:tags":[
        "device",
        "fixing",
        "fastener"
    ],
    "wof:name":"Castle Industries",
    "wof:placetype":"venue"
},
  "geometry": {"coordinates":[-1.9200190306,52.6797599792],"type":"Point"}
}