{
  "type": "Feature",
  "properties": {
    "addr:full":"12 High Street Cardiff Cardiff CF10 1AX",
    "addr:housenumber":"12",
    "addr:postcode":"cf10 1ax",
    "addr:street":"High Street",
    "iso:country":"GB",
    "sg:address":"12 High Street",
    "sg:city":"Cardiff",
    "sg:classifiers":[
        {
            "category":"Shopping",
            "subcategory":"Shoes",
            "type":"Retail Goods"
        }
    ],
    "sg:phone":"+44 29 2066 8788",
    "sg:postcode":"CF10 1AX",
    "sg:province":"Cardiff",
    "sg:tags":[
        "shop"
    ],
    "wof:name":"Buzz & Co.",
    "wof:placetype":"venue"
},
  "geometry": {"coordinates":[-3.180472,51.481167],"type":"Point"}
}