{
  "type": "Feature",
  "properties": {
    "iso:country":"GB",
    "sg:address":"15 Coldicott Gardens",
    "sg:city":"Evesham",
    "sg:classifiers":[
        {
            "category":"Professional",
            "subcategory":"Management & Consulting",
            "type":"Services"
        }
    ],
    "sg:phone":"+44 1386 40050",
    "sg:postcode":"WR11 2JW",
    "sg:province":"Gloucestershire",
    "sg:tags":[
        "consultant",
        "business"
    ],
    "wof:name":"Pyxis Management Ltd.",
    "wof:placetype":"venue"
},
  "geometry": {"coordinates":[-1.9528050423,52.0850257874],"type":"Point"}
}