{
  "type": "Feature",
  "properties": {
    "addr:full":"26 The Cross Worcester Worcestershire WR1 3PZ",
    "addr:housenumber":"26",
    "addr:postcode":"wr1 3pz",
    "addr:street":"The Cross",
    "iso:country":"GB",
    "sg:address":"26 The Cross",
    "sg:city":"Worcester",
    "sg:classifiers":[
        {
            "category":"Fast Food",
            "type":"Food & Drink"
        }
    ],
    "sg:phone":"+44 1905 726655",
    "sg:postcode":"WR1 3PZ",
    "sg:province":"Worcestershire",
    "sg:tags":[
        "away",
        "take"
    ],
    "wof:name":"Favourite Fried Chicken",
    "wof:placetype":"venue"
},
  "geometry": {"coordinates":[-2.221281,52.193176],"type":"Point"}
}