{
  "type": "Feature",
  "properties": {
    "iso:country":"GB",
    "sg:address":"Forest Corner Farm, Hangersley Hill",
    "sg:city":"Ringwood",
    "sg:classifiers":[
        {
            "category":"Retail",
            "subcategory":"Auto Repair",
            "type":"Services"
        }
    ],
    "sg:phone":"+44 1425 480886",
    "sg:postcode":"BH24 3JW",
    "sg:province":"Dorset",
    "sg:tags":[
        "modification",
        "garage"
    ],
    "wof:name":"Forest Corner Garage",
    "wof:placetype":"venue"
},
  "geometry": {"coordinates":[-1.756717,50.843224],"type":"Point"}
}