{
  "type": "Feature",
  "properties": {
    "addr:full":"15 Pocket Nook St St. Helens Cheshire WA9 1LR",
    "addr:housenumber":"15",
    "addr:postcode":"wa9 1lr",
    "addr:street":"Pocket Nook St",
    "iso:country":"GB",
    "sg:address":"15 Pocket Nook St",
    "sg:city":"St. Helens",
    "sg:classifiers":[
        {
            "category":"Bars & Pubs",
            "type":"Food & Drink"
        }
    ],
    "sg:phone":"+44 1744 737073",
    "sg:postcode":"WA9 1LR",
    "sg:province":"Cheshire",
    "sg:tags":[
        "pubs",
        "inn"
    ],
    "wof:name":"The Victoria",
    "wof:placetype":"venue"
},
  "geometry": {"coordinates":[-2.724864006,53.4561653137],"type":"Point"}
}