{
  "type": "Feature",
  "properties": {
    "addr:full":"1 Granville Arcade London Greater London SW9 8PR",
    "addr:housenumber":"1",
    "addr:postcode":"sw9 8pr",
    "addr:street":"Granville Arcade",
    "iso:country":"GB",
    "sg:address":"1 Granville Arcade",
    "sg:city":"London",
    "sg:classifiers":[
        {
            "category":"Food & Beverages",
            "subcategory":"Bakery",
            "type":"Retail Goods"
        }
    ],
    "sg:postcode":"SW9 8PR",
    "sg:province":"Greater London",
    "sg:tags":[
        "baker"
    ],
    "wof:name":"Arcade Bakery",
    "wof:placetype":"venue"
},
  "geometry": {"coordinates":[-0.111515,51.462013],"type":"Point"}
}