{
  "type": "Feature",
  "properties": {
    "iso:country":"GB",
    "sg:address":"Alkham Valley Road, Alkham",
    "sg:city":"Dover",
    "sg:classifiers":[
        {
            "category":"Home & Garden",
            "subcategory":"Garden Supply",
            "type":"Retail Goods"
        }
    ],
    "sg:postcode":"CT15 7EW",
    "sg:province":"Kent",
    "sg:tags":[
        "nursery",
        "centre"
    ],
    "wof:name":"Alkham Valley Garden Centre",
    "wof:placetype":"venue"
},
  "geometry": {"coordinates":[1.2239450216,51.1357383728],"type":"Point"}
}