{
  "type": "Feature",
  "properties": {
    "addr:full":"Lwr Stone St Maidstone Kent ME15 6LN",
    "addr:housenumber":"lwr",
    "addr:postcode":"me15 6ln",
    "addr:street":"Stone St",
    "iso:country":"GB",
    "sg:address":"Lwr Stone St",
    "sg:city":"Maidstone",
    "sg:classifiers":[
        {
            "category":"Insurance",
            "subcategory":"Insurance Agent",
            "type":"Services"
        }
    ],
    "sg:phone":"+44 1622 691222",
    "sg:postcode":"ME15 6LN",
    "sg:province":"Kent",
    "wof:name":"Royal & Sun Alliance Insurance Group Plc",
    "wof:placetype":"venue"
},
  "geometry": {"coordinates":[0.525154,51.271042],"type":"Point"}
}