{
  "type": "Feature",
  "properties": {
    "addr:full":"64a Rokeby Street Newcastle-upon-tyne Northumberland NE15 8RP",
    "addr:housenumber":"64a",
    "addr:postcode":"ne15 8rp",
    "addr:street":"Rokeby Street",
    "iso:country":"GB",
    "sg:address":"64a Rokeby Street",
    "sg:city":"Newcastle-upon-tyne",
    "sg:classifiers":[
        {
            "category":"Home & Garden",
            "subcategory":"Hardware",
            "type":"Retail Goods"
        }
    ],
    "sg:phone":"+44 191 264 0303",
    "sg:postcode":"NE15 8RP",
    "sg:province":"Northumberland",
    "wof:name":"Jemms",
    "wof:placetype":"venue"
},
  "geometry": {"coordinates":[-1.70926404,54.9779434204],"type":"Point"}
}