{
  "type": "Feature",
  "properties": {
    "addr:full":"Edginswell Farm, Edginswell Lane Torquay Devon TQ2 7JF",
    "addr:postcode":"tq2 7jf",
    "addr:street":"Edginswell Lane",
    "iso:country":"GB",
    "sg:address":"Edginswell Farm, Edginswell Lane",
    "sg:city":"Torquay",
    "sg:classifiers":[
        {
            "category":"Home & Garden",
            "subcategory":"Hardware",
            "type":"Retail Goods"
        }
    ],
    "sg:postcode":"TQ2 7JF",
    "sg:province":"Devon",
    "sg:tags":[
        "lawnmowers",
        "machinery"
    ],
    "wof:name":"Chelston Lawnmower Services",
    "wof:placetype":"venue"
},
  "geometry": {"coordinates":[-3.5650880337,50.4851722717],"type":"Point"}
}