{
  "type": "Feature",
  "properties": {
    "iso:country":"GB",
    "sg:address":"270-272 High St",
    "sg:city":"Berkhamsted",
    "sg:classifiers":[
        {
            "category":"Food & Beverages",
            "subcategory":"Bakery",
            "type":"Retail Goods"
        }
    ],
    "sg:phone":"+44 1442 876726",
    "sg:postcode":"HP4 1AQ",
    "sg:province":"Bedfordshire",
    "sg:tags":[
        "baker"
    ],
    "wof:name":"Atkins Bakers",
    "wof:placetype":"venue"
},
  "geometry": {"coordinates":[-0.5696210265,51.7621612549],"type":"Point"}
}