{
  "type": "Feature",
  "properties": {
    "addr:full":"14-16 Newhall Street Cannock Staffordshire WS11 1AB",
    "addr:housenumber":"14-16",
    "addr:postcode":"ws11 1ab",
    "addr:street":"Newhall Street",
    "iso:country":"GB",
    "sg:address":"14-16 Newhall Street",
    "sg:city":"Cannock",
    "sg:classifiers":[
        {
            "category":"Health Services",
            "subcategory":"Doctor",
            "type":"Services"
        }
    ],
    "sg:phone":"+44 1543 506511",
    "sg:postcode":"WS11 1AB",
    "sg:province":"Staffordshire",
    "sg:tags":[
        "practitioners"
    ],
    "wof:name":"Dr A Verma Surgery",
    "wof:placetype":"venue"
},
  "geometry": {"coordinates":[-2.033308,52.688885],"type":"Point"}
}