{
  "type": "Feature",
  "properties": {
    "addr:full":"67-68 Wrawby Street Brigg Lincolnshire DN20 8JE",
    "addr:housenumber":"67-68",
    "addr:postcode":"dn20 8je",
    "addr:street":"Wrawby Street",
    "iso:country":"GB",
    "sg:address":"67-68 Wrawby Street",
    "sg:city":"Brigg",
    "sg:classifiers":[
        {
            "category":"Banks & Credit Unions",
            "subcategory":"Financial Services",
            "type":"Services"
        }
    ],
    "sg:postcode":"DN20 8JE",
    "sg:province":"Lincolnshire",
    "sg:tags":[
        "adviser"
    ],
    "wof:name":"J Rixon Matthews & Appleyard Ltd.",
    "wof:placetype":"venue"
},
  "geometry": {"coordinates":[-0.490942,53.552067],"type":"Point"}
}