{
  "type": "Feature",
  "properties": {
    "iso:country":"GB",
    "sg:address":"28 Greenway Road, Tranmere",
    "sg:city":"Birkenhead",
    "sg:classifiers":[
        {
            "category":"Building & Trades",
            "subcategory":"Construction",
            "type":"Services"
        }
    ],
    "sg:phone":"+44 151 652 8496",
    "sg:postcode":"CH42 0NG",
    "sg:province":"Merseyside",
    "sg:tags":[
        "builder"
    ],
    "wof:name":"John Murray",
    "wof:placetype":"venue"
},
  "geometry": {"coordinates":[-3.027274,53.377762],"type":"Point"}
}