{
  "type": "Feature",
  "properties": {
    "iso:country":"GB",
    "sg:address":"6 Fairweather Clo, Clyde Rd",
    "sg:city":"Seven Sisters",
    "sg:classifiers":[
        {
            "category":"Social Services",
            "subcategory":"Child Care",
            "type":"Services"
        }
    ],
    "sg:phone":"+44 20 8376 2840",
    "sg:postcode":"N15 4LL",
    "sg:province":"Greater London",
    "sg:tags":[
        "childminders"
    ],
    "wof:name":"F Campbell",
    "wof:placetype":"venue"
},
  "geometry": {"coordinates":[-0.0792599991,51.5879898071],"type":"Point"}
}