{
  "type": "Feature",
  "properties": {
    "addr:full":"123 Shelbourne Road Bournemouth Dorset BH8 8RD",
    "addr:housenumber":"123",
    "addr:postcode":"bh8 8rd",
    "addr:street":"Shelbourne Road",
    "iso:country":"GB",
    "sg:address":"123 Shelbourne Road",
    "sg:city":"Bournemouth",
    "sg:classifiers":[
        {
            "category":"Government",
            "subcategory":"City Hall",
            "type":"Public Place"
        }
    ],
    "sg:phone":"+44 1202 399950",
    "sg:postcode":"BH8 8RD",
    "sg:province":"Dorset",
    "wof:name":"St. Andrews Parish Centre",
    "wof:placetype":"venue"
},
  "geometry": {"coordinates":[-1.8641079664,50.7353248596],"type":"Point"}
}