{
  "type": "Feature",
  "properties": {
    "addr:full":"28 Hereward Cross Peterborough Cambridgeshire PE1 1TE",
    "addr:housenumber":"28",
    "addr:postcode":"pe1 1te",
    "addr:street":"Hereward Cross",
    "iso:country":"GB",
    "sg:address":"28 Hereward Cross",
    "sg:city":"Peterborough",
    "sg:classifiers":[
        {
            "category":"Autos & Motor Vehicles",
            "subcategory":"Automobile Sales",
            "type":"Retail Goods"
        }
    ],
    "sg:phone":"+44 1733 896550",
    "sg:postcode":"PE1 1TE",
    "sg:province":"Cambridgeshire",
    "sg:tags":[
        "car"
    ],
    "wof:name":"Car Sales Agency UK Ltd",
    "wof:placetype":"venue"
},
  "geometry": {"coordinates":[-0.241794,52.574455],"type":"Point"}
}