{
  "type": "Feature",
  "properties": {
    "addr:full":"Bismark House, Bower Street Oldham Lancashire OL1 3XB",
    "addr:postcode":"ol1 3xb",
    "addr:street":"Bower Street",
    "iso:country":"GB",
    "sg:address":"Bismark House, Bower Street",
    "sg:city":"Oldham",
    "sg:classifiers":[
        {
            "category":"Professional",
            "subcategory":"Business Services",
            "type":"Services"
        },
        {
            "category":"Sports & Exercise",
            "subcategory":"Playing Field",
            "type":"Entertainment"
        }
    ],
    "sg:phone":"+44 161 626 3366",
    "sg:postcode":"OL1 3XB",
    "sg:province":"Lancashire",
    "sg:tags":[
        "tile",
        "sanitary",
        "hygiene",
        "appliance",
        "stockist"
    ],
    "wof:name":"Northern Wall & Floor Ltd.",
    "wof:placetype":"venue"
},
  "geometry": {"coordinates":[-2.092239,53.547878],"type":"Point"}
}