{
  "type": "Feature",
  "properties": {
    "addr:full":"Clydebank Business Centre, 31 Clyde Street Clydebank East Dunbartonshire G81 1PF",
    "addr:housenumber":"31",
    "addr:postcode":"g81 1pf",
    "addr:street":"Clyde Street",
    "iso:country":"GB",
    "sg:address":"Clydebank Business Centre, 31 Clyde Street",
    "sg:city":"Clydebank",
    "sg:classifiers":[
        {
            "category":"Professional",
            "subcategory":"Art Services",
            "type":"Services"
        }
    ],
    "sg:phone":"+44 1389 380386",
    "sg:postcode":"G81 1PF",
    "sg:province":"East Dunbartonshire",
    "sg:tags":[
        "technical",
        "illustrator",
        "commercial"
    ],
    "wof:name":"Rtm Services Ltd.",
    "wof:placetype":"venue"
},
  "geometry": {"coordinates":[-4.403649,55.910858],"type":"Point"}
}