{
  "type": "Feature",
  "properties": {
    "addr:full":"Wrens Park Farm, North Hill, Horndon On The Hill Stanford-le-hope Essex SS17 8QA",
    "addr:postcode":"ss17 8qa",
    "addr:street":"Wrens;North Hill Horndon On",
    "iso:country":"GB",
    "sg:address":"Wrens Park Farm, North Hill, Horndon On The Hill",
    "sg:city":"Stanford-le-hope",
    "sg:classifiers":[
        {
            "category":"Farming",
            "subcategory":"Dairy Farm",
            "type":"Manufacturing & Wholesale Goods"
        }
    ],
    "sg:postcode":"SS17 8QA",
    "sg:province":"Essex",
    "wof:name":"C E McCheyne",
    "wof:placetype":"venue"
},
  "geometry": {"coordinates":[0.40201,51.526279],"type":"Point"}
}