{
  "type": "Feature",
  "properties": {
    "iso:country":"GB",
    "sg:address":"Pounds Farm, Trampers Lane, North Boarhunt",
    "sg:city":"Fareham",
    "sg:classifiers":[
        {
            "category":"Farming",
            "subcategory":"Livestock Farm",
            "type":"Manufacturing & Wholesale Goods"
        }
    ],
    "sg:postcode":"PO17 6DF",
    "sg:province":"Hampshire",
    "sg:tags":[
        "others"
    ],
    "wof:name":"R H Watson",
    "wof:placetype":"venue"
},
  "geometry": {"coordinates":[-1.14270401,50.8879394531],"type":"Point"}
}