{
  "type": "Feature",
  "properties": {
    "addr:full":"Pield Heath Rd Uxbridge Buckinghamshire UB8 3NN",
    "addr:postcode":"ub8 3nn",
    "addr:street":"Heath Rd",
    "iso:country":"GB",
    "sg:address":"Pield Heath Rd",
    "sg:city":"Uxbridge",
    "sg:classifiers":[
        {
            "category":"Shopping",
            "subcategory":"Florist",
            "type":"Retail Goods"
        }
    ],
    "sg:phone":"+44 1895 231850",
    "sg:postcode":"UB8 3NN",
    "sg:province":"Buckinghamshire",
    "wof:name":"Hillingdon Flowers",
    "wof:placetype":"venue"
},
  "geometry": {"coordinates":[-0.465703994,51.5276298523],"type":"Point"}
}