{
  "type": "Feature",
  "properties": {
    "iso:country":"GB",
    "sg:address":"12 Stockwell Head",
    "sg:city":"Hinckley",
    "sg:classifiers":[
        {
            "category":"Personal",
            "type":"Services"
        }
    ],
    "sg:phone":"+44 1455 234171",
    "sg:postcode":"LE10 1RE",
    "sg:province":"Leicestershire",
    "sg:tags":[
        "wedding"
    ],
    "wof:name":"Fair Lady of Hinckley",
    "wof:placetype":"venue"
},
  "geometry": {"coordinates":[-1.372868,52.542557],"type":"Point"}
}