{
  "type": "Feature",
  "properties": {
    "addr:full":"36 Comrie St Crieff Perth and Kinross PH7 4AX",
    "addr:housenumber":"36",
    "addr:postcode":"ph7 4ax",
    "addr:street":"Comrie St",
    "iso:country":"GB",
    "sg:address":"36 Comrie St",
    "sg:city":"Crieff",
    "sg:classifiers":[
        {
            "category":"Professional",
            "subcategory":"Business Services",
            "type":"Services"
        }
    ],
    "sg:phone":"+44 1764 655922",
    "sg:postcode":"PH7 4AX",
    "sg:province":"Perth and Kinross",
    "sg:tags":[
        "accomodation"
    ],
    "wof:name":"Westend Business Centre",
    "wof:placetype":"venue"
},
  "geometry": {"coordinates":[-3.843798,56.374306],"type":"Point"}
}