{
  "type": "Feature",
  "properties": {
    "addr:full":"1 Coleshill Street Sutton Coldfield West Midlands B72 1SD",
    "addr:housenumber":"1",
    "addr:postcode":"b72 1sd",
    "addr:street":"Coleshill Street",
    "iso:country":"GB",
    "sg:address":"1 Coleshill Street",
    "sg:city":"Sutton Coldfield",
    "sg:classifiers":[
        {
            "category":"Professional",
            "subcategory":"Accounting & Tax Preparation",
            "type":"Services"
        }
    ],
    "sg:phone":"+44 1675 466344",
    "sg:postcode":"B72 1SD",
    "sg:province":"West Midlands",
    "sg:tags":[
        "accountant",
        "chartered",
        "activity"
    ],
    "wof:name":"Harben Barker",
    "wof:placetype":"venue"
},
  "geometry": {"coordinates":[-1.821879,52.564892],"type":"Point"}
}