{
  "type": "Feature",
  "properties": {
    "addr:full":"2 Parkthorn View, Dundonald Kilmarnock East Ayrshire KA2 9EZ",
    "addr:housenumber":"2",
    "addr:postcode":"ka2 9ez",
    "addr:street":"Parkthorn View Dundonald Kilmarnock East",
    "iso:country":"GB",
    "sg:address":"2 Parkthorn View, Dundonald",
    "sg:city":"Kilmarnock",
    "sg:classifiers":[
        {
            "category":"Professional",
            "subcategory":"Engineering",
            "type":"Services"
        }
    ],
    "sg:phone":"+44 1563 851368",
    "sg:postcode":"KA2 9EZ",
    "sg:province":"East Ayrshire",
    "sg:tags":[
        "design",
        "engineer"
    ],
    "wof:name":"Maintec",
    "wof:placetype":"venue"
},
  "geometry": {"coordinates":[-4.5999422073,55.5791130066],"type":"Point"}
}