{
  "type": "Feature",
  "properties": {
    "iso:country":"GB",
    "sg:address":"55 Broad Park Road",
    "sg:city":"Coventry",
    "sg:classifiers":[
        {
            "category":"Shopping",
            "subcategory":"Clothing, Apparel, & Fashions",
            "type":"Retail Goods"
        }
    ],
    "sg:postcode":"CV2 1DB",
    "sg:province":"Warwickshire",
    "sg:tags":[
        "shop"
    ],
    "wof:name":"Carol Bowdler",
    "wof:placetype":"venue"
},
  "geometry": {"coordinates":[-1.4578119516,52.4310531616],"type":"Point"}
}