{
  "type": "Feature",
  "properties": {
    "addr:full":"Churchside Barn, Old Milverton Leamington Spa Warwickshire CV32 6SA",
    "addr:postcode":"cv32 6sa",
    "iso:country":"GB",
    "sg:address":"Churchside Barn, Old Milverton",
    "sg:city":"Leamington Spa",
    "sg:classifiers":[
        {
            "category":"Building & Trades",
            "subcategory":"Construction",
            "type":"Services"
        }
    ],
    "sg:phone":"+44 1926 336339",
    "sg:postcode":"CV32 6SA",
    "sg:province":"Warwickshire",
    "sg:tags":[
        "builder"
    ],
    "wof:name":"Graham H Hall",
    "wof:placetype":"venue"
},
  "geometry": {"coordinates":[-1.559633,52.304684],"type":"Point"}
}