{
  "type": "Feature",
  "properties": {
    "addr:full":"Noel Centre, South Gate, Sutton Hill Telford Shropshire TF7 4HG",
    "addr:postcode":"tf7 4hg",
    "addr:street":"Gate Sutton",
    "iso:country":"GB",
    "sg:address":"Noel Centre, South Gate, Sutton Hill",
    "sg:city":"Telford",
    "sg:classifiers":[
        {
            "category":"Organizations",
            "subcategory":"Non-profit Organization",
            "type":"Services"
        }
    ],
    "sg:phone":"+44 1952 581477",
    "sg:postcode":"TF7 4HG",
    "sg:province":"Shropshire",
    "sg:tags":[
        "organisation",
        "voluntary",
        "charity"
    ],
    "wof:name":"Madeley Area Pathway Project",
    "wof:placetype":"venue"
},
  "geometry": {"coordinates":[-2.4421899319,52.6299705505],"type":"Point"}
}