{
  "type": "Feature",
  "properties": {
    "addr:full":"The Garage, Clare Street Halifax West Yorkshire HX1 2LF",
    "addr:postcode":"hx1 2lf",
    "addr:street":"Clare Street",
    "iso:country":"GB",
    "sg:address":"The Garage, Clare Street",
    "sg:city":"Halifax",
    "sg:classifiers":[
        {
            "category":"Retail",
            "subcategory":"Auto Repair",
            "type":"Services"
        }
    ],
    "sg:phone":"+44 1422 362732",
    "sg:postcode":"HX1 2LF",
    "sg:province":"West Yorkshire",
    "sg:tags":[
        "modification",
        "garage"
    ],
    "wof:name":"Graham Wills",
    "wof:placetype":"venue"
},
  "geometry": {"coordinates":[-1.862224,53.721233],"type":"Point"}
}