{
  "type": "Feature",
  "properties": {
    "addr:full":"1 Tamar Road Tamworth Staffordshire B77 5QG",
    "addr:housenumber":"1",
    "addr:postcode":"b77 5qg",
    "addr:street":"Tamar Road",
    "iso:country":"GB",
    "sg:address":"1 Tamar Road",
    "sg:city":"Tamworth",
    "sg:classifiers":[
        {
            "category":"Building & Trades",
            "subcategory":"Construction",
            "type":"Services"
        }
    ],
    "sg:postcode":"B77 5QG",
    "sg:province":"Staffordshire",
    "sg:tags":[
        "joiner",
        "carpenter"
    ],
    "wof:name":"R Berry",
    "wof:placetype":"venue"
},
  "geometry": {"coordinates":[-1.6593660116,52.6004104614],"type":"Point"}
}