{
  "type": "Feature",
  "properties": {
    "addr:full":"Queens Crt Sunderland Tyne and Wear SR5 4PT",
    "addr:postcode":"sr5 4pt",
    "addr:street":"Queens Crt",
    "iso:country":"GB",
    "sg:address":"Queens Crt",
    "sg:city":"Sunderland",
    "sg:classifiers":[
        {
            "category":"Military Area",
            "subcategory":"Air Force Base",
            "type":"Public Place"
        }
    ],
    "sg:phone":"+44 191 519 0222",
    "sg:postcode":"SR5 4PT",
    "sg:province":"Tyne and Wear",
    "sg:tags":[
        "taxi",
        "hire",
        "private"
    ],
    "wof:name":"Townend Taxis",
    "wof:placetype":"venue"
},
  "geometry": {"coordinates":[-1.4548000097,54.9293899536],"type":"Point"}
}