{
  "type": "Feature",
  "properties": {
    "iso:country":"GB",
    "sg:address":"Backlane, Melbourn",
    "sg:city":"Royston",
    "sg:classifiers":[
        {
            "category":"Professional",
            "subcategory":"Management & Consulting",
            "type":"Services"
        }
    ],
    "sg:phone":"+44 1763 267016",
    "sg:postcode":"SG8 6DP",
    "sg:province":"Bedfordshire",
    "sg:tags":[
        "consultant",
        "business"
    ],
    "wof:name":"P A Consulting Group",
    "wof:placetype":"venue"
},
  "geometry": {"coordinates":[0.011957,52.087051],"type":"Point"}
}