{
  "type": "Feature",
  "properties": {
    "iso:country":"GB",
    "sg:address":"44a Nottingham Rd",
    "sg:city":"Nottingham",
    "sg:classifiers":[
        {
            "category":"Food & Beverages",
            "subcategory":"Fruits & Vegetables",
            "type":"Retail Goods"
        }
    ],
    "sg:postcode":"NG16 3NQ",
    "sg:province":"Derbyshire",
    "sg:tags":[
        "greengrocer"
    ],
    "wof:name":"Holmes,Neil,",
    "wof:placetype":"venue"
},
  "geometry": {"coordinates":[-1.306037,53.017849],"type":"Point"}
}