{
  "type": "Feature",
  "properties": {
    "iso:country":"GB",
    "sg:address":"1 High Street, Braunston",
    "sg:city":"Daventry",
    "sg:classifiers":[
        {
            "category":"Building & Trades",
            "subcategory":"Pest Control",
            "type":"Services"
        }
    ],
    "sg:phone":"+44 1788 890363",
    "sg:postcode":"NN11 7HR",
    "sg:province":"Northamptonshire",
    "sg:tags":[
        "vermin"
    ],
    "wof:name":"1a Terminator",
    "wof:placetype":"venue"
},
  "geometry": {"coordinates":[-1.205748,52.292046],"type":"Point"}
}