{
  "type": "Feature",
  "properties": {
    "iso:country":"GB",
    "sg:address":"23-24 Bishopgate Street",
    "sg:city":"York",
    "sg:classifiers":[
        {
            "category":"Shopping",
            "subcategory":"Antiques",
            "type":"Retail Goods"
        }
    ],
    "sg:phone":"+44 1904 623893",
    "sg:postcode":"YO23 1JH",
    "sg:province":"North Yorkshire",
    "wof:name":"Bishop Gate Antiques",
    "wof:placetype":"venue"
},
  "geometry": {"coordinates":[-1.083789,53.953098],"type":"Point"}
}