{
  "type": "Feature",
  "properties": {
    "addr:full":"Cromer Street London Greater London WC1H 8LF",
    "addr:postcode":"wc1h 8lf",
    "addr:street":"Cromer Street",
    "iso:country":"GB",
    "sg:address":"Cromer Street",
    "sg:city":"London",
    "sg:classifiers":[
        {
            "category":"Social Services",
            "subcategory":"Adult Care",
            "type":"Services"
        }
    ],
    "sg:phone":"+44 20 7278 5090",
    "sg:postcode":"WC1H 8LF",
    "sg:province":"Greater London",
    "sg:tags":[
        "day",
        "centre"
    ],
    "wof:name":"Camden Age Concern",
    "wof:placetype":"venue"
},
  "geometry": {"coordinates":[-0.1203389987,51.5281448364],"type":"Point"}
}