{
  "type": "Feature",
  "properties": {
    "addr:full":"20 Hazelhurst Road Bradford West Yorkshire BD9 6BJ",
    "addr:housenumber":"20",
    "addr:postcode":"bd9 6bj",
    "addr:street":"Hazelhurst Road",
    "iso:country":"GB",
    "sg:address":"20 Hazelhurst Road",
    "sg:city":"Bradford",
    "sg:classifiers":[
        {
            "category":"Farming",
            "subcategory":"Nursery",
            "type":"Manufacturing & Wholesale Goods"
        }
    ],
    "sg:postcode":"BD9 6BJ",
    "sg:province":"West Yorkshire",
    "sg:tags":[
        "creche"
    ],
    "wof:name":"Jollytots",
    "wof:placetype":"venue"
},
  "geometry": {"coordinates":[-1.8039339781,53.807094574],"type":"Point"}
}