{
  "type": "Feature",
  "properties": {
    "addr:full":"3 Belmont Road Ilfracombe Devon EX34 8DR",
    "addr:housenumber":"3",
    "addr:postcode":"ex34 8dr",
    "addr:street":"Belmont Road",
    "iso:country":"GB",
    "sg:address":"3 Belmont Road",
    "sg:city":"Ilfracombe",
    "sg:classifiers":[
        {
            "category":"Travel",
            "subcategory":"Hotels & Motels",
            "type":"Entertainment"
        }
    ],
    "sg:phone":"+44 1271 863955",
    "sg:postcode":"EX34 8DR",
    "sg:province":"Devon",
    "wof:name":"Darnley Hotel",
    "wof:placetype":"venue"
},
  "geometry": {"coordinates":[-4.128754,51.204548],"type":"Point"}
}