{
  "type": "Feature",
  "properties": {
    "iso:country":"GB",
    "sg:address":"124 Milehouse Road",
    "sg:city":"Plymouth",
    "sg:classifiers":[
        {
            "category":"Personal",
            "type":"Services"
        },
        {
            "category":"Professional",
            "subcategory":"Employment Agencies",
            "type":"Services"
        }
    ],
    "sg:phone":"+44 1752 550640",
    "sg:postcode":"PL3 4DE",
    "sg:province":"Devon",
    "sg:tags":[
        "modelling",
        "wedding"
    ],
    "wof:name":"Eric Thompson Photography",
    "wof:placetype":"venue"
},
  "geometry": {"coordinates":[-4.163327,50.382885],"type":"Point"}
}