{
  "type": "Feature",
  "properties": {
    "addr:full":"29 Market St, Westhoughton Bolton Lancashire BL5 3AG",
    "addr:housenumber":"29",
    "addr:postcode":"bl5 3ag",
    "addr:street":"Market St",
    "iso:country":"GB",
    "sg:address":"29 Market St, Westhoughton",
    "sg:city":"Bolton",
    "sg:classifiers":[
        {
            "category":"Professional",
            "subcategory":"Employment Agencies",
            "type":"Services"
        }
    ],
    "sg:phone":"+44 1942 814771",
    "sg:postcode":"BL5 3AG",
    "sg:province":"Lancashire",
    "sg:tags":[
        "consultant"
    ],
    "wof:name":"Jobcentre",
    "wof:placetype":"venue"
},
  "geometry": {"coordinates":[-2.5213930607,53.5487709045],"type":"Point"}
}