{
  "type": "Feature",
  "properties": {
    "iso:country":"GB",
    "sg:address":"Sudbury Road, Yoxall",
    "sg:city":"Burton-on-trent",
    "sg:classifiers":[
        {
            "category":"Retail",
            "subcategory":"Auto Repair",
            "type":"Services"
        }
    ],
    "sg:postcode":"DE13 8NA",
    "sg:province":"Derbyshire",
    "sg:tags":[
        "modification",
        "garage"
    ],
    "wof:name":"Denis Welch Motors Ltd.",
    "wof:placetype":"venue"
},
  "geometry": {"coordinates":[-1.793069,52.771446],"type":"Point"}
}