{
  "type": "Feature",
  "properties": {
    "iso:country":"GB",
    "sg:address":"Welton Hill",
    "sg:city":"Hawick",
    "sg:classifiers":[
        {
            "category":"Government",
            "subcategory":"Police Station",
            "type":"Public Place"
        }
    ],
    "sg:phone":"+44 1450 375051",
    "sg:postcode":"TD9 7JU",
    "sg:province":"Cumbria",
    "sg:tags":[
        "support"
    ],
    "wof:name":"Lothian & Borders Police Force",
    "wof:placetype":"venue"
},
  "geometry": {"coordinates":[-2.785274,55.429714],"type":"Point"}
}