{
  "type": "Feature",
  "properties": {
    "addr:full":"29-30 Horsefair Banbury Oxfordshire OX16 0AE",
    "addr:housenumber":"29-30",
    "addr:postcode":"ox16 0ae",
    "addr:street":"Horsefair Banbury",
    "iso:country":"GB",
    "sg:address":"29-30 Horsefair",
    "sg:city":"Banbury",
    "sg:classifiers":[
        {
            "category":"Manufacturing",
            "subcategory":"Wood Products",
            "type":"Manufacturing & Wholesale Goods"
        }
    ],
    "sg:phone":"+44 1295 275012",
    "sg:postcode":"OX16 0AE",
    "sg:province":"Oxfordshire",
    "wof:name":"Mabor Ltd.",
    "wof:placetype":"venue"
},
  "geometry": {"coordinates":[-1.339852,52.060955],"type":"Point"}
}