{
  "type": "Feature",
  "properties": {
    "addr:full":"12a Old Hall St Stoke On Trent Staffordshire ST1 1QT",
    "addr:housenumber":"12a",
    "addr:postcode":"st1 1qt",
    "addr:street":"Old Hall St",
    "iso:country":"GB",
    "sg:address":"12a Old Hall St",
    "sg:city":"Stoke On Trent",
    "sg:classifiers":[
        {
            "category":"Recreation",
            "type":"Entertainment"
        }
    ],
    "sg:phone":"+44 1782 285497",
    "sg:postcode":"ST1 1QT",
    "sg:province":"Staffordshire",
    "sg:tags":[
        "snooker",
        "billiards",
        "pool"
    ],
    "wof:name":"Premier Pool Club",
    "wof:placetype":"venue"
},
  "geometry": {"coordinates":[-2.1735510826,53.0248641968],"type":"Point"}
}