{
  "type": "Feature",
  "properties": {
    "iso:country":"GB",
    "sg:address":"Unit 9 Sovereign Wks, Deepdale La",
    "sg:city":"Dudley",
    "sg:classifiers":[
        {
            "category":"Wholesale",
            "subcategory":"Construction Materials",
            "type":"Manufacturing & Wholesale Goods"
        }
    ],
    "sg:postcode":"DY3 2AF",
    "sg:province":"Staffordshire",
    "sg:tags":[
        "lift"
    ],
    "wof:name":"Wolverhampton Lifting Equipment",
    "wof:placetype":"venue"
},
  "geometry": {"coordinates":[-2.11693,52.521019],"type":"Point"}
}