{
  "type": "Feature",
  "properties": {
    "iso:country":"GB",
    "sg:address":"Crichton Road",
    "sg:city":"Rothesay",
    "sg:classifiers":[
        {
            "category":"Travel",
            "subcategory":"Hotels & Motels",
            "type":"Entertainment"
        }
    ],
    "sg:postcode":"PA20 9JT",
    "sg:province":"Argyll and Bute",
    "wof:name":"Craigmore Hotel",
    "wof:placetype":"venue"
},
  "geometry": {"coordinates":[-5.054835,55.834675],"type":"Point"}
}