{
  "type": "Feature",
  "properties": {
    "iso:country":"GB",
    "sg:address":"Sanderson Hospital, Salters Road",
    "sg:city":"Newcastle-upon-tyne",
    "sg:classifiers":[
        {
            "category":"Health Services",
            "subcategory":"Health Practitioner",
            "type":"Services"
        },
        {
            "category":"Health Services",
            "subcategory":"Podiatrist",
            "type":"Services"
        }
    ],
    "sg:postcode":"NE3 4BL",
    "sg:province":"Tyne and Wear",
    "sg:tags":[
        "physiotherapist",
        "podiatrists",
        "chiropodist"
    ],
    "wof:name":"Newcastle Primary Care Trust",
    "wof:placetype":"venue"
},
  "geometry": {"coordinates":[-1.63735,54.999352],"type":"Point"}
}