{
  "type": "Feature",
  "properties": {
    "iso:country":"GB",
    "sg:address":"The Barn, Maltings Farm, & Stud, Malthouse Lane, Hurstpierpoint",
    "sg:city":"Hassocks",
    "sg:classifiers":[
        {
            "category":"Shopping",
            "subcategory":"Bicycles & Sporting Goods",
            "type":"Retail Goods"
        }
    ],
    "sg:phone":"+44 1273 833114",
    "sg:postcode":"BN6 9JZ",
    "sg:province":"East Sussex",
    "sg:tags":[
        "riding",
        "saddlery",
        "wear"
    ],
    "wof:name":"Diamond Saddlery",
    "wof:placetype":"venue"
},
  "geometry": {"coordinates":[-0.159,50.950001],"type":"Point"}
}