{
  "type": "Feature",
  "properties": {
    "addr:full":"9 Weavers Court Halstead Essex CO9 2JN",
    "addr:housenumber":"9",
    "addr:postcode":"co9 2jn",
    "addr:street":"Weavers Court",
    "iso:country":"GB",
    "sg:address":"9 Weavers Court",
    "sg:city":"Halstead",
    "sg:classifiers":[
        {
            "category":"Retail",
            "subcategory":"Laundry & Dry Cleaning",
            "type":"Services"
        }
    ],
    "sg:phone":"+44 1787 478189",
    "sg:postcode":"CO9 2JN",
    "sg:province":"Essex",
    "sg:tags":[
        "alteration"
    ],
    "wof:name":"Parishs",
    "wof:placetype":"venue"
},
  "geometry": {"coordinates":[0.6418759823,51.9428787231],"type":"Point"}
}