{
  "type": "Feature",
  "properties": {
    "addr:full":"51 Kensington Park Road London Greater London W11 1PA",
    "addr:housenumber":"51",
    "addr:postcode":"w11 1pa",
    "addr:street":"Kensington Park Road",
    "iso:country":"GB",
    "sg:address":"51 Kensington Park Road",
    "sg:city":"London",
    "sg:classifiers":[
        {
            "category":"Health Services",
            "subcategory":"Doctor",
            "type":"Services"
        }
    ],
    "sg:phone":"+44 20 7727 8212",
    "sg:postcode":"W11 1PA",
    "sg:province":"Greater London",
    "sg:tags":[
        "practitioners"
    ],
    "wof:name":"Colville Health Centre",
    "wof:placetype":"venue"
},
  "geometry": {"coordinates":[-0.2061890066,51.516078949],"type":"Point"}
}