{
  "type": "Feature",
  "properties": {
    "addr:full":"93 High Street Tewkesbury Gloucestershire GL20 5JZ",
    "addr:housenumber":"93",
    "addr:postcode":"gl20 5jz",
    "addr:street":"High Street",
    "iso:country":"GB",
    "sg:address":"93 High Street",
    "sg:city":"Tewkesbury",
    "sg:classifiers":[
        {
            "category":"Recreation",
            "type":"Entertainment"
        }
    ],
    "sg:phone":"+44 1684 292988",
    "sg:postcode":"GL20 5JZ",
    "sg:province":"Gloucestershire",
    "sg:tags":[
        "snooker",
        "billiards",
        "hall",
        "pool"
    ],
    "wof:name":"Tewkesbury Snooker Club",
    "wof:placetype":"venue"
},
  "geometry": {"coordinates":[-2.155914,51.995689],"type":"Point"}
}