{
  "type": "Feature",
  "properties": {
    "addr:full":"Oakwood Park, Peacock Lane Wokingham Berkshire RG40 3YZ",
    "addr:postcode":"rg40 3yz",
    "addr:street":"Oakwood;Peacock Lane",
    "iso:country":"GB",
    "sg:address":"Oakwood Park, Peacock Lane",
    "sg:city":"Wokingham",
    "sg:classifiers":[
        {
            "category":"Retail",
            "subcategory":"Pet Boarding",
            "type":"Services"
        },
        {
            "category":"Retail",
            "subcategory":"Animal Services",
            "type":"Services"
        }
    ],
    "sg:phone":"+44 118 979 3399",
    "sg:postcode":"RG40 3YZ",
    "sg:province":"Berkshire",
    "sg:tags":[
        "training",
        "dog",
        "kennel"
    ],
    "wof:name":"Oakwood Park Kennels",
    "wof:placetype":"venue"
},
  "geometry": {"coordinates":[-0.8345940113,51.4108009338],"type":"Point"}
}