{
  "type": "Feature",
  "properties": {
    "addr:full":"11 Oxford St Hungerford Berkshire RG17 8XS",
    "addr:housenumber":"11",
    "addr:postcode":"rg17 8xs",
    "addr:street":"Oxford St",
    "iso:country":"GB",
    "sg:address":"11 Oxford St",
    "sg:city":"Hungerford",
    "sg:classifiers":[
        {
            "category":"Shopping",
            "subcategory":"Crafts & Fabrics",
            "type":"Retail Goods"
        }
    ],
    "sg:phone":"+44 1488 72900",
    "sg:postcode":"RG17 8XS",
    "sg:province":"Berkshire",
    "sg:tags":[
        "ceramic"
    ],
    "wof:name":"Castaway Ceramics",
    "wof:placetype":"venue"
},
  "geometry": {"coordinates":[-1.529056,51.508739],"type":"Point"}
}