{
  "type": "Feature",
  "properties": {
    "iso:country":"GB",
    "sg:address":"Brynford",
    "sg:city":"Holywell",
    "sg:classifiers":[
        {
            "category":"Sports & Exercise",
            "subcategory":"Golf",
            "type":"Entertainment"
        }
    ],
    "sg:phone":"+44 1352 713937",
    "sg:postcode":"CH8 8LQ",
    "sg:province":"Denbighshire",
    "sg:tags":[
        "club",
        "course",
        "equipment"
    ],
    "wof:name":"Holywell Golf Club",
    "wof:placetype":"venue"
},
  "geometry": {"coordinates":[-3.223558,53.264217],"type":"Point"}
}