{
  "type": "Feature",
  "properties": {
    "iso:country":"GB",
    "sg:address":"53 Highridge Road, Bishopsworth",
    "sg:city":"Bristol",
    "sg:classifiers":[
        {
            "category":"Military Area",
            "subcategory":"Air Force Base",
            "type":"Public Place"
        }
    ],
    "sg:phone":"+44 117 964 4640",
    "sg:postcode":"BS13 8HJ",
    "sg:province":"City of Bristol",
    "sg:tags":[
        "taxi",
        "hire",
        "private"
    ],
    "wof:name":"Fryer's Taxis",
    "wof:placetype":"venue"
},
  "geometry": {"coordinates":[-2.6276330948,51.4178771973],"type":"Point"}
}