{
  "type": "Feature",
  "properties": {
    "addr:full":"1 Leesland Road Gosport Hampshire PO12 3ND",
    "addr:housenumber":"1",
    "addr:postcode":"po12 3nd",
    "addr:street":"Leesland Road",
    "iso:country":"GB",
    "sg:address":"1 Leesland Road",
    "sg:city":"Gosport",
    "sg:classifiers":[
        {
            "category":"Bars & Pubs",
            "type":"Food & Drink"
        }
    ],
    "sg:phone":"+44 23 9258 5140",
    "sg:postcode":"PO12 3ND",
    "sg:province":"Hampshire",
    "sg:tags":[
        "pubs",
        "house",
        "inn",
        "public",
        "activity"
    ],
    "wof:name":"Junction Tavern",
    "wof:placetype":"venue"
},
  "geometry": {"coordinates":[-1.144765,50.799217],"type":"Point"}
}