{
  "type": "Feature",
  "properties": {
    "addr:full":"33 Romsey Drive Benfleet Essex SS7 5TU",
    "addr:housenumber":"33",
    "addr:postcode":"ss7 5tu",
    "addr:street":"Romsey Drive",
    "iso:country":"GB",
    "sg:address":"33 Romsey Drive",
    "sg:city":"Benfleet",
    "sg:classifiers":[
        {
            "category":"Professional",
            "subcategory":"Detective & Security Services",
            "type":"Services"
        }
    ],
    "sg:postcode":"SS7 5TU",
    "sg:province":"Essex",
    "wof:name":"Saturn Security Ltd.",
    "wof:placetype":"venue"
},
  "geometry": {"coordinates":[0.5466189981,51.5665969849],"type":"Point"}
}