{
  "type": "Feature",
  "properties": {
    "addr:full":"161 Park Road Kingston-upon-thames Greater London KT2 6DQ",
    "addr:housenumber":"161",
    "addr:postcode":"kt2 6dq",
    "addr:street":"Park Road",
    "iso:country":"GB",
    "sg:address":"161 Park Road",
    "sg:city":"Kingston-upon-thames",
    "sg:classifiers":[
        {
            "category":"Food & Beverages",
            "subcategory":"Candy",
            "type":"Retail Goods"
        }
    ],
    "sg:phone":"+44 20 8546 0579",
    "sg:postcode":"KT2 6DQ",
    "sg:province":"Greater London",
    "sg:tags":[
        "confectioner"
    ],
    "wof:name":"Sweet Times",
    "wof:placetype":"venue"
},
  "geometry": {"coordinates":[-0.2890090048,51.4185943604],"type":"Point"}
}