{
  "type": "Feature",
  "properties": {
    "addr:full":"Durable Ho, Crabtree Manorway Belvedere Kent DA17 6AB",
    "addr:postcode":"da17 6ab",
    "iso:country":"GB",
    "sg:address":"Durable Ho, Crabtree Manorway",
    "sg:city":"Belvedere",
    "sg:classifiers":[
        {
            "category":"Autos & Motor Vehicles",
            "subcategory":"Automobile Sales",
            "type":"Retail Goods"
        }
    ],
    "sg:phone":"+44 20 8311 2006",
    "sg:postcode":"DA17 6AB",
    "sg:province":"Kent",
    "sg:tags":[
        "commercial"
    ],
    "wof:name":"G S Mountford",
    "wof:placetype":"venue"
},
  "geometry": {"coordinates":[0.152566,51.488422],"type":"Point"}
}