{
  "type": "Feature",
  "properties": {
    "addr:full":"318 Charminster Road Bournemouth Dorset BH8 9RT",
    "addr:housenumber":"318",
    "addr:postcode":"bh8 9rt",
    "addr:street":"Charminster Road",
    "iso:country":"GB",
    "sg:address":"318 Charminster Road",
    "sg:city":"Bournemouth",
    "sg:classifiers":[
        {
            "category":"Food & Beverages",
            "subcategory":"Meat & Fish",
            "type":"Retail Goods"
        }
    ],
    "sg:phone":"+44 1202 524056",
    "sg:postcode":"BH8 9RT",
    "sg:province":"Dorset",
    "sg:tags":[
        "chip"
    ],
    "wof:name":"Dolphin Fish Bar",
    "wof:placetype":"venue"
},
  "geometry": {"coordinates":[-1.8627079725,50.7409896851],"type":"Point"}
}