{
  "type": "Feature",
  "properties": {
    "addr:full":"31a Park Pde Harrogate North Yorkshire HG1 5AG",
    "addr:housenumber":"31a",
    "addr:postcode":"hg1 5ag",
    "addr:street":"Park Pde",
    "iso:country":"GB",
    "sg:address":"31a Park Pde",
    "sg:city":"Harrogate",
    "sg:classifiers":[
        {
            "category":"Retail",
            "subcategory":"Auto Repair",
            "type":"Services"
        }
    ],
    "sg:phone":"+44 1423 509100",
    "sg:postcode":"HG1 5AG",
    "sg:province":"North Yorkshire",
    "sg:tags":[
        "modification",
        "garage"
    ],
    "wof:name":"Service With A Smile",
    "wof:placetype":"venue"
},
  "geometry": {"coordinates":[-1.527674,53.99538],"type":"Point"}
}