{
  "type": "Feature",
  "properties": {
    "iso:country":"GB",
    "sg:address":"8 Bristol Road",
    "sg:city":"Brighton",
    "sg:classifiers":[
        {
            "category":"Retail",
            "subcategory":"Laundry & Dry Cleaning",
            "type":"Services"
        }
    ],
    "sg:phone":"+44 1273 681592",
    "sg:postcode":"BN2 1AP",
    "sg:province":"East Sussex",
    "sg:tags":[
        "cleaner",
        "alteration"
    ],
    "wof:name":"Kemptown Dry Cleaners",
    "wof:placetype":"venue"
},
  "geometry": {"coordinates":[-0.125023,50.819305],"type":"Point"}
}