{
  "type": "Feature",
  "properties": {
    "addr:full":"Holme St Nottingham Nottinghamshire NG2 3HB",
    "addr:postcode":"ng2 3hb",
    "addr:street":"Holme St",
    "iso:country":"GB",
    "sg:address":"Holme St",
    "sg:city":"Nottingham",
    "sg:classifiers":[
        {
            "category":"Retail",
            "subcategory":"Auto Rental",
            "type":"Services"
        }
    ],
    "sg:phone":"+44 115 986 2329",
    "sg:postcode":"NG2 3HB",
    "sg:province":"Nottinghamshire",
    "sg:tags":[
        "car"
    ],
    "wof:name":"Midland Car Contracts",
    "wof:placetype":"venue"
},
  "geometry": {"coordinates":[-1.131994,52.945065],"type":"Point"}
}