{
  "type": "Feature",
  "properties": {
    "addr:full":"3 Central Precinct, Brunswick Road Buckley Denbighshire CH7 2EF",
    "addr:housenumber":"3",
    "addr:postcode":"ch7 2ef",
    "addr:street":"Brunswick Road",
    "iso:country":"GB",
    "sg:address":"3 Central Precinct, Brunswick Road",
    "sg:city":"Buckley",
    "sg:classifiers":[
        {
            "category":"Shopping",
            "subcategory":"Pets & Pet Supplies",
            "type":"Retail Goods"
        }
    ],
    "sg:phone":"+44 1244 547444",
    "sg:postcode":"CH7 2EF",
    "sg:province":"Denbighshire",
    "sg:tags":[
        "food"
    ],
    "wof:name":"Pets Corner",
    "wof:placetype":"venue"
},
  "geometry": {"coordinates":[-3.090714,53.16819],"type":"Point"}
}