{
  "type": "Feature",
  "properties": {
    "addr:full":"Holden House, 2-8 Holden Road Leigh Lancashire WN7 1EX",
    "addr:housenumber":"2-8",
    "addr:postcode":"wn7 1ex",
    "addr:street":"Holden Road Leigh",
    "iso:country":"GB",
    "sg:address":"Holden House, 2-8 Holden Road",
    "sg:city":"Leigh",
    "sg:classifiers":[
        {
            "category":"Manufacturing",
            "subcategory":"Wood Products",
            "type":"Manufacturing & Wholesale Goods"
        }
    ],
    "sg:postcode":"WN7 1EX",
    "sg:province":"Lancashire",
    "sg:tags":[
        "encapsulation",
        "lamination"
    ],
    "wof:name":"Albert Barker & Son",
    "wof:placetype":"venue"
},
  "geometry": {"coordinates":[-2.516169,53.50037],"type":"Point"}
}