{
  "type": "Feature",
  "properties": {
    "addr:full":"Village Hall, Gravelly Bottom Road Maidstone Kent ME17 3NX",
    "addr:postcode":"me17 3nx",
    "addr:street":"Gravelly Bottom Road",
    "iso:country":"GB",
    "sg:address":"Village Hall, Gravelly Bottom Road",
    "sg:city":"Maidstone",
    "sg:classifiers":[
        {
            "category":"Education",
            "subcategory":"Preschool",
            "type":"Public Place"
        }
    ],
    "sg:postcode":"ME17 3NX",
    "sg:province":"Kent",
    "sg:tags":[
        "pre-school",
        "playgroups"
    ],
    "wof:name":"Kingswood Pre School Group",
    "wof:placetype":"venue"
},
  "geometry": {"coordinates":[0.6311240196,51.226650238],"type":"Point"}
}