{
  "type": "Feature",
  "properties": {
    "addr:full":"1a Winchester Road, Four Marks Alton Hampshire GU34 5HD",
    "addr:housenumber":"1a",
    "addr:postcode":"gu34 5hd",
    "addr:street":"Winchester Road",
    "iso:country":"GB",
    "sg:address":"1a Winchester Road, Four Marks",
    "sg:city":"Alton",
    "sg:classifiers":[
        {
            "category":"Retail",
            "subcategory":"Veterinary Services",
            "type":"Services"
        },
        {
            "category":"Organizations",
            "subcategory":"Non-profit Organization",
            "type":"Services"
        }
    ],
    "sg:phone":"+44 1420 562048",
    "sg:postcode":"GU34 5HD",
    "sg:province":"Hampshire",
    "sg:tags":[
        "organisation",
        "welfare",
        "animal",
        "activity"
    ],
    "wof:name":"Cedar Veterinary Group",
    "wof:placetype":"venue"
},
  "geometry": {"coordinates":[-1.026038,51.11903],"type":"Point"}
}