{
  "type": "Feature",
  "properties": {
    "addr:full":"1 Silver Street, Midsomer Norton Bath Somerset BA3 2ET",
    "addr:housenumber":"1",
    "addr:postcode":"ba3 2et",
    "addr:street":"Silver Street",
    "iso:country":"GB",
    "sg:address":"1 Silver Street, Midsomer Norton",
    "sg:city":"Bath",
    "sg:classifiers":[
        {
            "category":"Professional",
            "subcategory":"Engineering",
            "type":"Services"
        }
    ],
    "sg:phone":"+44 1761 411822",
    "sg:postcode":"BA3 2ET",
    "sg:province":"Somerset",
    "sg:tags":[
        "consulting",
        "engineer"
    ],
    "wof:name":"Geoffrey Hunt & Partners",
    "wof:placetype":"venue"
},
  "geometry": {"coordinates":[-2.4819331169,51.2847251892],"type":"Point"}
}