{
  "type": "Feature",
  "properties": {
    "iso:country":"GB",
    "sg:address":"C/o Netto Foodstore Ltd, Scotia Road",
    "sg:city":"Stoke-on-trent",
    "sg:classifiers":[
        {
            "category":"Shopping",
            "subcategory":"Pets & Pet Supplies",
            "type":"Retail Goods"
        }
    ],
    "sg:phone":"+44 1782 825087",
    "sg:postcode":"ST6 4HG",
    "sg:province":"Staffordshire",
    "sg:tags":[
        "food"
    ],
    "wof:name":"Pets First",
    "wof:placetype":"venue"
},
  "geometry": {"coordinates":[-2.2019300461,53.0542907715],"type":"Point"}
}