{
  "type": "Feature",
  "properties": {
    "addr:full":"2b Mount Pleasant Road, Lewisham London Greater London SE13 6RB",
    "addr:housenumber":"2b",
    "addr:postcode":"se13 6rb",
    "addr:street":"Mount Pleasant Road",
    "iso:country":"GB",
    "sg:address":"2b Mount Pleasant Road, Lewisham",
    "sg:city":"London",
    "sg:classifiers":[
        {
            "category":"Professional",
            "subcategory":"Printing & Photocopies",
            "type":"Services"
        }
    ],
    "sg:phone":"+44 20 8690 2696",
    "sg:postcode":"SE13 6RB",
    "sg:province":"Greater London",
    "sg:tags":[
        "printer"
    ],
    "wof:name":"The Whitmonth Press",
    "wof:placetype":"venue"
},
  "geometry": {"coordinates":[-0.016613,51.451725],"type":"Point"}
}