{
  "type": "Feature",
  "properties": {
    "iso:country":"GB",
    "sg:address":"225 St Leonards Road",
    "sg:city":"Windsor",
    "sg:classifiers":[
        {
            "category":"Shopping",
            "type":"Retail Goods"
        }
    ],
    "sg:phone":"+44 1753 833442",
    "sg:postcode":"SL4 3DR",
    "sg:province":"Berkshire",
    "sg:tags":[
        "part",
        "accessory"
    ],
    "wof:name":"Motor Traveller",
    "wof:placetype":"venue"
},
  "geometry": {"coordinates":[-0.6194329858,51.4709358215],"type":"Point"}
}