{
  "type": "Feature",
  "properties": {
    "iso:country":"GB",
    "sg:address":"4a Moston Road, Middleton Junction",
    "sg:city":"Manchester",
    "sg:classifiers":[
        {
            "category":"Professional",
            "subcategory":"Engineering",
            "type":"Services"
        }
    ],
    "sg:phone":"+44 161 653 8066",
    "sg:postcode":"M24 1SL",
    "sg:province":"Greater Manchester",
    "sg:tags":[
        "precision",
        "engineer"
    ],
    "wof:name":"Plastools Ltd.",
    "wof:placetype":"venue"
},
  "geometry": {"coordinates":[-2.174849,53.532921],"type":"Point"}
}