{
  "type": "Feature",
  "properties": {
    "addr:full":"Coton-in-the-clay, Sudbury Ashbourne Derbyshire DE6 5GY",
    "addr:postcode":"de6 5gy",
    "iso:country":"GB",
    "sg:address":"Coton-in-the-clay, Sudbury",
    "sg:city":"Ashbourne",
    "sg:classifiers":[
        {
            "category":"Freight",
            "type":"Transportation"
        }
    ],
    "sg:phone":"+44 1283 820271",
    "sg:postcode":"DE6 5GY",
    "sg:province":"Derbyshire",
    "sg:tags":[
        "haulage",
        "road"
    ],
    "wof:name":"W H Ratcliffe (Haulage) Ltd.",
    "wof:placetype":"venue"
},
  "geometry": {"coordinates":[-1.7625360489,52.8856391907],"type":"Point"}
}