{
  "type": "Feature",
  "properties": {
    "addr:full":"Rhos Wrexham Wrexham LL14 1NF",
    "addr:postcode":"ll14 1nf",
    "addr:street":"Rhos",
    "iso:country":"GB",
    "sg:address":"Rhos",
    "sg:city":"Wrexham",
    "sg:classifiers":[
        {
            "category":"Community Center",
            "subcategory":"Youth",
            "type":"Public Place"
        }
    ],
    "sg:phone":"+44 1978 846217",
    "sg:postcode":"LL14 1NF",
    "sg:province":"Wrexham",
    "sg:tags":[
        "organisation",
        "centre"
    ],
    "wof:name":"Rhosllannerchrugog Youth Club",
    "wof:placetype":"venue"
},
  "geometry": {"coordinates":[-3.0452599525,53.0091590881],"type":"Point"}
}