{
  "type": "Feature",
  "properties": {
    "iso:country":"GB",
    "sg:address":"Carters Yd, Gilbey Rd",
    "sg:city":"Grimsby",
    "sg:classifiers":[
        {
            "category":"Home & Garden",
            "subcategory":"Hardware",
            "type":"Retail Goods"
        },
        {
            "category":"Building & Trades",
            "subcategory":"Construction",
            "type":"Services"
        }
    ],
    "sg:postcode":"DN31 2RL",
    "sg:province":"Lincolnshire",
    "sg:tags":[
        "paint",
        "builder",
        "coating"
    ],
    "wof:name":"Allison,Nicholas,",
    "wof:placetype":"venue"
},
  "geometry": {"coordinates":[-0.09927,53.572552],"type":"Point"}
}