{
  "type": "Feature",
  "properties": {
    "addr:full":"6 Havens Head Milford Haven Pembrokeshire SA73 3QH",
    "addr:housenumber":"6",
    "addr:postcode":"sa73 3qh",
    "addr:street":"Havens Head Milford Haven",
    "iso:country":"GB",
    "sg:address":"6 Havens Head",
    "sg:city":"Milford Haven",
    "sg:classifiers":[
        {
            "category":"Home & Garden",
            "subcategory":"Kitchen Supply",
            "type":"Retail Goods"
        }
    ],
    "sg:phone":"+44 1646 695757",
    "sg:postcode":"SA73 3QH",
    "sg:province":"Pembrokeshire",
    "sg:tags":[
        "glassware",
        "china"
    ],
    "wof:name":"Lakeside",
    "wof:placetype":"venue"
},
  "geometry": {"coordinates":[-5.0567121506,51.7135353088],"type":"Point"}
}