{
  "type": "Feature",
  "properties": {
    "addr:full":"71 Wick Road Teddington Greater London TW11 9DN",
    "addr:housenumber":"71",
    "addr:postcode":"tw11 9dn",
    "addr:street":"Wick Road",
    "iso:country":"GB",
    "sg:address":"71 Wick Road",
    "sg:city":"Teddington",
    "sg:classifiers":[
        {
            "category":"Building & Trades",
            "subcategory":"Plumbing",
            "type":"Services"
        }
    ],
    "sg:phone":"+44 20 8977 4755",
    "sg:postcode":"TW11 9DN",
    "sg:province":"Greater London",
    "sg:tags":[
        "heating"
    ],
    "wof:name":"Aaron Plumbing Heating & Drainage",
    "wof:placetype":"venue"
},
  "geometry": {"coordinates":[-0.319534,51.418488],"type":"Point"}
}