{
  "type": "Feature",
  "properties": {
    "addr:full":"145 Union St Oldham Lancashire OL1 1TD",
    "addr:housenumber":"145",
    "addr:postcode":"ol1 1td",
    "addr:street":"Union St",
    "iso:country":"GB",
    "sg:address":"145 Union St",
    "sg:city":"Oldham",
    "sg:classifiers":[
        {
            "category":"Home & Garden",
            "subcategory":"Furniture",
            "type":"Retail Goods"
        }
    ],
    "sg:phone":"+44 161 628 9844",
    "sg:postcode":"OL1 1TD",
    "sg:province":"Lancashire",
    "wof:name":"Hutchins & Leigh Ltd",
    "wof:placetype":"venue"
},
  "geometry": {"coordinates":[-2.1060800552,53.5416374207],"type":"Point"}
}