{
  "type": "Feature",
  "properties": {
    "addr:full":"California Farm, Trowell Lane, Sutton Bonington Loughborough Leicestershire LE12 5RW",
    "addr:postcode":"le12 5rw",
    "addr:street":"Trowell Lane",
    "iso:country":"GB",
    "sg:address":"California Farm, Trowell Lane, Sutton Bonington",
    "sg:city":"Loughborough",
    "sg:classifiers":[
        {
            "category":"Farming",
            "subcategory":"Livestock Farm",
            "type":"Manufacturing & Wholesale Goods"
        }
    ],
    "sg:phone":"+44 1509 853781",
    "sg:postcode":"LE12 5RW",
    "sg:province":"Leicestershire",
    "sg:tags":[
        "others"
    ],
    "wof:name":"J T & B Armett & Sons",
    "wof:placetype":"venue"
},
  "geometry": {"coordinates":[-1.253779,52.823792],"type":"Point"}
}