{
  "type": "Feature",
  "properties": {
    "addr:full":"88 Westmeads Road Whitstable Kent CT5 1LW",
    "addr:housenumber":"88",
    "addr:postcode":"ct5 1lw",
    "addr:street":"Westmeads Road",
    "iso:country":"GB",
    "sg:address":"88 Westmeads Road",
    "sg:city":"Whitstable",
    "sg:classifiers":[
        {
            "category":"Personal",
            "type":"Services"
        }
    ],
    "sg:postcode":"CT5 1LW",
    "sg:province":"Kent",
    "sg:tags":[
        "stress",
        "management"
    ],
    "wof:name":"Stress & Anxiety Helpline",
    "wof:placetype":"venue"
},
  "geometry": {"coordinates":[1.0316319466,51.3617019653],"type":"Point"}
}