{
  "type": "Feature",
  "properties": {
    "addr:full":"Seedbed Centre, Avenue Rd Birmingham West Midlands B7 4NT",
    "addr:postcode":"b7 4nt",
    "addr:street":"Centre Avenue Rd",
    "iso:country":"GB",
    "sg:address":"Seedbed Centre, Avenue Rd",
    "sg:city":"Birmingham",
    "sg:classifiers":[
        {
            "category":"Professional",
            "subcategory":"Printing & Photocopies",
            "type":"Services"
        }
    ],
    "sg:phone":"+44 121 359 1210",
    "sg:postcode":"B7 4NT",
    "sg:province":"West Midlands",
    "sg:tags":[
        "emblem",
        "wholesale",
        "badge"
    ],
    "wof:name":"Kyd Products",
    "wof:placetype":"venue"
},
  "geometry": {"coordinates":[-1.8805789948,52.4953575134],"type":"Point"}
}