{
  "type": "Feature",
  "properties": {
    "iso:country":"GB",
    "sg:address":"23 Newbiggin Hall Centre",
    "sg:city":"Newcastle-upon-tyne",
    "sg:classifiers":[
        {
            "category":"Health Services",
            "subcategory":"Clinic",
            "type":"Services"
        },
        {
            "category":"Internet Cafe",
            "subcategory":"None",
            "type":"Food & Drink"
        }
    ],
    "sg:postcode":"NE5 4BR",
    "sg:province":"Tyne and Wear",
    "sg:tags":[
        "abuse",
        "drug"
    ],
    "wof:name":"C L E O",
    "wof:placetype":"venue"
},
  "geometry": {"coordinates":[-1.68761,55.006699],"type":"Point"}
}