{
  "type": "Feature",
  "properties": {
    "addr:full":"12 Nursery Parade, Leagrave Luton Bedfordshire LU3 2QP",
    "addr:housenumber":"12",
    "addr:postcode":"lu3 2qp",
    "addr:street":"Nursery Parade",
    "iso:country":"GB",
    "sg:address":"12 Nursery Parade, Leagrave",
    "sg:city":"Luton",
    "sg:classifiers":[
        {
            "category":"Shopping",
            "type":"Retail Goods"
        }
    ],
    "sg:phone":"+44 1582 595952",
    "sg:postcode":"LU3 2QP",
    "sg:province":"Bedfordshire",
    "sg:tags":[
        "part",
        "accessory"
    ],
    "wof:name":"The Motorist Centre",
    "wof:placetype":"venue"
},
  "geometry": {"coordinates":[-0.454034,51.904968],"type":"Point"}
}