{
  "type": "Feature",
  "properties": {
    "iso:country":"GB",
    "sg:address":"64 Castle Street",
    "sg:city":"Canterbury",
    "sg:classifiers":[
        {
            "category":"Restaurant",
            "type":"Food & Drink"
        }
    ],
    "sg:phone":"+44 1227 457538",
    "sg:postcode":"CT1 2PY",
    "sg:province":"Kent",
    "wof:name":"Pinocchio's",
    "wof:placetype":"venue"
},
  "geometry": {"coordinates":[1.076674,51.27692],"type":"Point"}
}