{
  "type": "Feature",
  "properties": {
    "addr:full":"Breach Road, Sandy Lane Stoke-on-trent Staffordshire ST6 8QF",
    "addr:postcode":"staffordshire st6 8qf",
    "addr:street":"Breach Road Sandy",
    "iso:country":"GB",
    "sg:address":"Breach Road, Sandy Lane",
    "sg:city":"Stoke-on-trent",
    "sg:classifiers":[
        {
            "category":"Organizations",
            "subcategory":"Membership Organization",
            "type":"Services"
        }
    ],
    "sg:postcode":"ST6 8QF",
    "sg:province":"Staffordshire",
    "sg:tags":[
        "club"
    ],
    "wof:name":"Brown Edge Working Men's Club & Institute Ltd.",
    "wof:placetype":"venue"
},
  "geometry": {"coordinates":[-2.1284620762,53.0770492554],"type":"Point"}
}