{
  "type": "Feature",
  "properties": {
    "addr:full":"45 Varley Street Derby Derbyshire DE24 8DE",
    "addr:housenumber":"45",
    "addr:postcode":"de24 8de",
    "addr:street":"Varley Street",
    "iso:country":"GB",
    "sg:address":"45 Varley Street",
    "sg:city":"Derby",
    "sg:classifiers":[
        {
            "category":"Professional",
            "subcategory":"Lawyer & Legal Services",
            "type":"Services"
        }
    ],
    "sg:phone":"+44 1332 732552",
    "sg:postcode":"DE24 8DE",
    "sg:province":"Derbyshire",
    "sg:tags":[
        "advice",
        "counselling"
    ],
    "wof:name":"OSMASTON COMMUNITY ASSOCIATION",
    "wof:placetype":"venue"
},
  "geometry": {"coordinates":[-1.454319,52.892349],"type":"Point"}
}