{
  "type": "Feature",
  "properties": {
    "iso:country":"GB",
    "sg:address":"248 Ashley Road",
    "sg:city":"Poole",
    "sg:classifiers":[
        {
            "category":"Shopping",
            "subcategory":"Party Supplies",
            "type":"Retail Goods"
        }
    ],
    "sg:phone":"+44 1202 716091",
    "sg:postcode":"BH14 9BZ",
    "sg:province":"Dorset",
    "sg:tags":[
        "equipment",
        "disco"
    ],
    "wof:name":"Intek Electronics",
    "wof:placetype":"venue"
},
  "geometry": {"coordinates":[-1.9332100153,50.7286148071],"type":"Point"}
}