{
  "type": "Feature",
  "properties": {
    "iso:country":"GB",
    "sg:address":"Banknock",
    "sg:city":"Bonnybridge",
    "sg:classifiers":[
        {
            "category":"Restaurant",
            "type":"Food & Drink"
        }
    ],
    "sg:phone":"+44 1324 840201",
    "sg:postcode":"FK4 1UF",
    "sg:province":"Falkirk",
    "wof:name":"Glenskirlie House Restaurant",
    "wof:placetype":"venue"
},
  "geometry": {"coordinates":[-3.8816180229,56.002948761],"type":"Point"}
}