{
  "type": "Feature",
  "properties": {
    "iso:country":"GB",
    "sg:address":"267 Bradford Road",
    "sg:city":"Batley",
    "sg:classifiers":[
        {
            "category":"Food & Beverages",
            "subcategory":"Groceries & Convenience Stores",
            "type":"Retail Goods"
        }
    ],
    "sg:phone":"+44 1924 472991",
    "sg:postcode":"WF17 6JG",
    "sg:province":"West Yorkshire",
    "wof:name":"Top Home Bargain Supply",
    "wof:placetype":"venue"
},
  "geometry": {"coordinates":[-1.6284530163,53.7050170898],"type":"Point"}
}