{
  "type": "Feature",
  "properties": {
    "addr:full":"33 Hudson Close Poole Dorset BH12 4PT",
    "addr:housenumber":"33",
    "addr:postcode":"bh12 4pt",
    "addr:street":"Hudson Close",
    "iso:country":"GB",
    "sg:address":"33 Hudson Close",
    "sg:city":"Poole",
    "sg:classifiers":[
        {
            "category":"Government",
            "subcategory":"Post Office",
            "type":"Public Place"
        }
    ],
    "sg:phone":"+44 1202 740264",
    "sg:postcode":"BH12 4PT",
    "sg:province":"Dorset",
    "sg:tags":[
        "messenger",
        "courier"
    ],
    "wof:name":"A & M Courier Service",
    "wof:placetype":"venue"
},
  "geometry": {"coordinates":[-1.9394210577,50.7510643005],"type":"Point"}
}