{
  "type": "Feature",
  "properties": {
    "addr:full":"Widnes Road Widnes Cheshire WA8 6AF",
    "addr:postcode":"wa8 6af",
    "addr:street":"Widnes Road",
    "iso:country":"GB",
    "sg:address":"Widnes Road",
    "sg:city":"Widnes",
    "sg:classifiers":[
        {
            "category":"Food & Beverages",
            "subcategory":"Fruits & Vegetables",
            "type":"Retail Goods"
        }
    ],
    "sg:postcode":"WA8 6AF",
    "sg:province":"Cheshire",
    "sg:tags":[
        "greengrocer"
    ],
    "wof:name":"Colemans",
    "wof:placetype":"venue"
},
  "geometry": {"coordinates":[-2.7275090218,53.3668785095],"type":"Point"}
}