{
  "type": "Feature",
  "properties": {
    "addr:full":"106 Wheatley Road Halifax West Yorkshire HX3 5LN",
    "addr:housenumber":"106",
    "addr:postcode":"hx3 5ln",
    "addr:street":"Wheatley Road",
    "iso:country":"GB",
    "sg:address":"106 Wheatley Road",
    "sg:city":"Halifax",
    "sg:classifiers":[
        {
            "category":"Bars & Pubs",
            "type":"Food & Drink"
        }
    ],
    "sg:phone":"+44 1422 346161",
    "sg:postcode":"HX3 5LN",
    "sg:province":"West Yorkshire",
    "sg:tags":[
        "pubs",
        "inn"
    ],
    "wof:name":"Wheatley Wells Inn",
    "wof:placetype":"venue"
},
  "geometry": {"coordinates":[-1.8852000237,53.7358665466],"type":"Point"}
}