{
  "type": "Feature",
  "properties": {
    "iso:country":"GB",
    "sg:address":"Hope Cove",
    "sg:city":"Kingsbridge",
    "sg:classifiers":[
        {
            "category":"Bars & Pubs",
            "type":"Food & Drink"
        }
    ],
    "sg:postcode":"TQ7 3HQ",
    "sg:province":"Devon",
    "sg:tags":[
        "pubs",
        "inn"
    ],
    "wof:name":"Lobster Pot Inn",
    "wof:placetype":"venue"
},
  "geometry": {"coordinates":[-3.777619,50.283104],"type":"Point"}
}