{
  "type": "Feature",
  "properties": {
    "addr:full":"Jacobs Well, West Street Newbury Berkshire RG14 1BD",
    "addr:postcode":"rg14 1bd",
    "addr:street":"West Street",
    "iso:country":"GB",
    "sg:address":"Jacobs Well, West Street",
    "sg:city":"Newbury",
    "sg:classifiers":[
        {
            "category":"Professional",
            "subcategory":"Computer Services",
            "type":"Services"
        }
    ],
    "sg:phone":"+44 1635 582555",
    "sg:postcode":"RG14 1BD",
    "sg:province":"Berkshire",
    "sg:tags":[
        "system",
        "software"
    ],
    "wof:name":"Micro Drainage Ltd.",
    "wof:placetype":"venue"
},
  "geometry": {"coordinates":[-1.3258719444,51.405872345],"type":"Point"}
}