{
  "type": "Feature",
  "properties": {
    "iso:country":"GB",
    "sg:address":"70 Heath Road, Downend",
    "sg:city":"Bristol",
    "sg:classifiers":[
        {
            "category":"Home & Garden",
            "subcategory":"Household Appliances",
            "type":"Retail Goods"
        }
    ],
    "sg:postcode":"BS16 6HB",
    "sg:province":"City of Bristol",
    "sg:tags":[
        "electrical"
    ],
    "wof:name":"Downend Refrigeration Services",
    "wof:placetype":"venue"
},
  "geometry": {"coordinates":[-2.507131,51.496887],"type":"Point"}
}