{
  "type": "Feature",
  "properties": {
    "iso:country":"GB",
    "sg:address":"Unit 1/3, Schola Green Lane",
    "sg:city":"Morecambe",
    "sg:classifiers":[
        {
            "category":"Food & Beverages",
            "subcategory":"Meat & Fish",
            "type":"Retail Goods"
        }
    ],
    "sg:phone":"+44 1524 411611",
    "sg:postcode":"LA4 5QT",
    "sg:province":"Lancashire",
    "sg:tags":[
        "butcher"
    ],
    "wof:name":"Udale Speciality Foods",
    "wof:placetype":"venue"
},
  "geometry": {"coordinates":[-2.8562190533,54.0707588196],"type":"Point"}
}