{
  "type": "Feature",
  "properties": {
    "iso:country":"GB",
    "sg:address":"Stortford Road",
    "sg:city":"Dunmow",
    "sg:classifiers":[
        {
            "category":"Autos & Motor Vehicles",
            "subcategory":"Automobile Sales",
            "type":"Retail Goods"
        }
    ],
    "sg:phone":"+44 1279 876467",
    "sg:postcode":"CM6 1RB",
    "sg:province":"Essex",
    "sg:tags":[
        "car"
    ],
    "wof:name":"Parklands Garage",
    "wof:placetype":"venue"
},
  "geometry": {"coordinates":[0.358995,51.873085],"type":"Point"}
}