{
  "type": "Feature",
  "properties": {
    "addr:full":"21 Bethel Street Neath Neath Port Talbot SA11 2HQ",
    "addr:housenumber":"21",
    "addr:postcode":"sa11 2hq",
    "addr:street":"Bethel Street",
    "iso:country":"GB",
    "sg:address":"21 Bethel Street",
    "sg:city":"Neath",
    "sg:classifiers":[
        {
            "category":"Bars & Pubs",
            "type":"Food & Drink"
        }
    ],
    "sg:phone":"+44 1639 821700",
    "sg:postcode":"SA11 2HQ",
    "sg:province":"Neath Port Talbot",
    "sg:tags":[
        "pubs",
        "house",
        "inn",
        "public",
        "activity"
    ],
    "wof:name":"Rose & Crown Inn",
    "wof:placetype":"venue"
},
  "geometry": {"coordinates":[-3.8209350109,51.6301193237],"type":"Point"}
}