{
  "type": "Feature",
  "properties": {
    "iso:country":"GB",
    "sg:address":"129 Vincent Clo, Old Hall",
    "sg:city":"Warrington",
    "sg:classifiers":[
        {
            "category":"Building & Trades",
            "subcategory":"Construction",
            "type":"Services"
        }
    ],
    "sg:phone":"+44 1925 650153",
    "sg:postcode":"WA5 5TB",
    "sg:province":"Cheshire",
    "sg:tags":[
        "builder"
    ],
    "wof:name":"Jupp Ken",
    "wof:placetype":"venue"
},
  "geometry": {"coordinates":[-2.62364,53.401241],"type":"Point"}
}