{
  "type": "Feature",
  "properties": {
    "iso:country":"GB",
    "sg:address":"25 - 27 Kew Road",
    "sg:city":"Richmond",
    "sg:classifiers":[
        {
            "category":"Organizations",
            "subcategory":"Membership Organization",
            "type":"Services"
        }
    ],
    "sg:phone":"+44 20 8948 3211",
    "sg:postcode":"TW9 2NQ",
    "sg:province":"Greater London",
    "sg:tags":[
        "club"
    ],
    "wof:name":"Shenstone Residents Co. (Ealing) Ltd.",
    "wof:placetype":"venue"
},
  "geometry": {"coordinates":[-0.3018549979,51.4638786316],"type":"Point"}
}