{
  "type": "Feature",
  "properties": {
    "iso:country":"GB",
    "sg:address":"44 Forest Road",
    "sg:city":"Loughton",
    "sg:classifiers":[
        {
            "category":"Home & Garden",
            "subcategory":"Furniture",
            "type":"Retail Goods"
        }
    ],
    "sg:postcode":"IG10 1EE",
    "sg:province":"Essex",
    "wof:name":"Loughton Chair Centre Ltd.",
    "wof:placetype":"venue"
},
  "geometry": {"coordinates":[0.053279,51.64772],"type":"Point"}
}