{
  "type": "Feature",
  "properties": {
    "addr:full":"Eggington Leighton Buzzard Bedfordshire LU7 9PA",
    "addr:postcode":"lu7 9pa",
    "iso:country":"GB",
    "sg:address":"Eggington",
    "sg:city":"Leighton Buzzard",
    "sg:classifiers":[
        {
            "category":"Farming",
            "subcategory":"Dairy Farm",
            "type":"Manufacturing & Wholesale Goods"
        }
    ],
    "sg:phone":"+44 1525 210281",
    "sg:postcode":"LU7 9PA",
    "sg:province":"Bedfordshire",
    "wof:name":"Steven Peck",
    "wof:placetype":"venue"
},
  "geometry": {"coordinates":[-0.61691,51.91967],"type":"Point"}
}