{
  "type": "Feature",
  "properties": {
    "iso:country":"GB",
    "sg:address":"Oaklands, Stow Road, Bledington",
    "sg:city":"Chipping Norton",
    "sg:classifiers":[
        {
            "category":"Sports & Exercise",
            "subcategory":"Swimming Pool",
            "type":"Entertainment"
        }
    ],
    "sg:phone":"+44 1451 831251",
    "sg:postcode":"OX7 6XL",
    "sg:province":"Gloucestershire",
    "sg:tags":[
        "bee"
    ],
    "wof:name":"Cotswold Bees",
    "wof:placetype":"venue"
},
  "geometry": {"coordinates":[-1.647899,51.903873],"type":"Point"}
}