{
  "type": "Feature",
  "properties": {
    "iso:country":"GB",
    "sg:address":"26 Pendula Drive",
    "sg:city":"Hayes",
    "sg:classifiers":[
        {
            "category":"Retail",
            "subcategory":"Driving School",
            "type":"Services"
        }
    ],
    "sg:phone":"+44 20 8841 1450",
    "sg:postcode":"UB4 9PF",
    "sg:province":"Greater London",
    "wof:name":"Dependable Driving Tuition",
    "wof:placetype":"venue"
},
  "geometry": {"coordinates":[-0.389452,51.525799],"type":"Point"}
}