{
  "type": "Feature",
  "properties": {
    "addr:full":"5 Grosvenor Terrace, Lake Road, Bowness On Windermere Windermere Cumbria LA23 3BS",
    "addr:housenumber":"5",
    "addr:postcode":"la23 3bs",
    "addr:street":"Grosvenor Terrace Lake Road",
    "iso:country":"GB",
    "sg:address":"5 Grosvenor Terrace, Lake Road, Bowness On Windermere",
    "sg:city":"Windermere",
    "sg:classifiers":[
        {
            "category":"Shopping",
            "subcategory":"Pharmacy",
            "type":"Retail Goods"
        }
    ],
    "sg:postcode":"LA23 3BS",
    "sg:province":"Cumbria",
    "sg:tags":[
        "pharmacist",
        "chemist"
    ],
    "wof:name":"I Aynsley",
    "wof:placetype":"venue"
},
  "geometry": {"coordinates":[-2.922436,54.362869],"type":"Point"}
}