{
  "type": "Feature",
  "properties": {
    "addr:full":"11 Church Lane, Sutton Waldron Blandford Forum Dorset DT11 8PA",
    "addr:housenumber":"11",
    "addr:postcode":"dt11 8pa",
    "addr:street":"Church Lane",
    "iso:country":"GB",
    "sg:address":"11 Church Lane, Sutton Waldron",
    "sg:city":"Blandford Forum",
    "sg:classifiers":[
        {
            "category":"Professional",
            "subcategory":"Art Services",
            "type":"Services"
        },
        {
            "category":"Building & Trades",
            "subcategory":"Construction",
            "type":"Services"
        }
    ],
    "sg:postcode":"DT11 8PA",
    "sg:province":"Dorset",
    "sg:tags":[
        "glazier",
        "decorator",
        "painter"
    ],
    "wof:name":"Christopher Fulluck",
    "wof:placetype":"venue"
},
  "geometry": {"coordinates":[-2.198631,50.942455],"type":"Point"}
}