{
  "type": "Feature",
  "properties": {
    "addr:full":"6-8 Wellington St Barnsley South Yorkshire S70 1SS",
    "addr:housenumber":"6-8",
    "addr:postcode":"s70 1ss",
    "addr:street":"Wellington St;Yorkshire",
    "iso:country":"GB",
    "sg:address":"6-8 Wellington St",
    "sg:city":"Barnsley",
    "sg:classifiers":[
        {
            "category":"Travel",
            "subcategory":"Travel Agent",
            "type":"Entertainment"
        }
    ],
    "sg:postcode":"S70 1SS",
    "sg:province":"South Yorkshire",
    "wof:name":"Lee,Mike,Travel",
    "wof:placetype":"venue"
},
  "geometry": {"coordinates":[-1.4818370342,53.5519981384],"type":"Point"}
}