{
  "type": "Feature",
  "properties": {
    "addr:full":"Downton Farm, Walton Presteigne Herefordshire LD8 2RD",
    "addr:housenumber":"presteigne",
    "addr:postcode":"ld8 2rd",
    "addr:street":"Walton",
    "iso:country":"GB",
    "sg:address":"Downton Farm, Walton",
    "sg:city":"Presteigne",
    "sg:classifiers":[
        {
            "category":"Farming",
            "subcategory":"Farm",
            "type":"Manufacturing & Wholesale Goods"
        }
    ],
    "sg:postcode":"LD8 2RD",
    "sg:province":"Herefordshire",
    "sg:tags":[
        "mixed",
        "crop"
    ],
    "wof:name":"A E Lloyd & Son",
    "wof:placetype":"venue"
},
  "geometry": {"coordinates":[-3.004454,52.270206],"type":"Point"}
}