{
  "type": "Feature",
  "properties": {
    "addr:full":"Lowfold Hall, Roberttown La Liversedge West Yorkshire WF15 7LY",
    "addr:postcode":"wf15 7ly",
    "addr:street":"La Liversedge West",
    "iso:country":"GB",
    "sg:address":"Lowfold Hall, Roberttown La",
    "sg:city":"Liversedge",
    "sg:classifiers":[
        {
            "category":"Building & Trades",
            "subcategory":"Construction",
            "type":"Services"
        }
    ],
    "sg:phone":"+44 1924 406677",
    "sg:postcode":"WF15 7LY",
    "sg:province":"West Yorkshire",
    "sg:tags":[
        "builder"
    ],
    "wof:name":"C J Wooller",
    "wof:placetype":"venue"
},
  "geometry": {"coordinates":[-1.7059789896,53.6989860535],"type":"Point"}
}