{
  "type": "Feature",
  "properties": {
    "addr:full":"Barbers Yard, The Grn, Old Buckenham Attleborough Norfolk NR17 1RN",
    "addr:postcode":"nr17 1rn",
    "addr:street":"The Grn;Buckenham",
    "iso:country":"GB",
    "sg:address":"Barbers Yard, The Grn, Old Buckenham",
    "sg:city":"Attleborough",
    "sg:classifiers":[
        {
            "category":"Freight",
            "type":"Transportation"
        }
    ],
    "sg:phone":"+44 1953 860342",
    "sg:postcode":"NR17 1RN",
    "sg:province":"Norfolk",
    "sg:tags":[
        "haulage",
        "road"
    ],
    "wof:name":"L C Hardy & Son Ltd.",
    "wof:placetype":"venue"
},
  "geometry": {"coordinates":[1.042462945,52.4819984436],"type":"Point"}
}