{
  "type": "Feature",
  "properties": {
    "iso:country":"GB",
    "sg:address":"308 Margate Road",
    "sg:city":"Ramsgate",
    "sg:classifiers":[
        {
            "category":"Shopping",
            "subcategory":"Department Store",
            "type":"Retail Goods"
        }
    ],
    "sg:phone":"+44 1843 586761",
    "sg:postcode":"CT12 6AN",
    "sg:province":"Kent",
    "wof:name":"Northwood Stores",
    "wof:placetype":"venue"
},
  "geometry": {"coordinates":[1.402328968,51.3521003723],"type":"Point"}
}