{
  "type": "Feature",
  "properties": {
    "addr:full":"Congleton Rd Stoke On Trent Cheshire ST7 1ND",
    "addr:postcode":"st7 1nd",
    "addr:street":"Congleton Rd",
    "iso:country":"GB",
    "sg:address":"Congleton Rd",
    "sg:city":"Stoke On Trent",
    "sg:classifiers":[
        {
            "category":"Organizations",
            "subcategory":"Non-profit Organization",
            "type":"Services"
        }
    ],
    "sg:phone":"+44 1782 783984",
    "sg:postcode":"ST7 1ND",
    "sg:province":"Cheshire",
    "sg:tags":[
        "organisation",
        "voluntary",
        "charity"
    ],
    "wof:name":"Women's Royal Voluntary Service",
    "wof:placetype":"venue"
},
  "geometry": {"coordinates":[-2.257695,53.088425],"type":"Point"}
}