{
  "type": "Feature",
  "properties": {
    "iso:country":"GB",
    "sg:address":"22 Christchurch St West",
    "sg:city":"Frome",
    "sg:classifiers":[
        {
            "category":"Personal",
            "subcategory":"Beauty Salon",
            "type":"Services"
        }
    ],
    "sg:phone":"+44 1373 462874",
    "sg:postcode":"BA11 1EE",
    "sg:province":"Somerset",
    "wof:name":"The Hawkins Clinic",
    "wof:placetype":"venue"
},
  "geometry": {"coordinates":[-2.3248751163,51.2297058105],"type":"Point"}
}