{
  "type": "Feature",
  "properties": {
    "iso:country":"GB",
    "sg:address":"65 Roman Rd",
    "sg:city":"Bethnal Green",
    "sg:classifiers":[
        {
            "category":"Museum",
            "subcategory":"Art Museum",
            "type":"Entertainment"
        }
    ],
    "sg:phone":"+44 20 8980 0100",
    "sg:postcode":"E2 0QN",
    "sg:province":"Greater London",
    "sg:tags":[
        "gallery"
    ],
    "wof:name":"IAP Fine Art",
    "wof:placetype":"venue"
},
  "geometry": {"coordinates":[-0.050571,51.528156],"type":"Point"}
}