{
  "type": "Feature",
  "properties": {
    "addr:full":"Russett Court, Fernhurst Haslemere Hampshire GU27 3JX",
    "addr:postcode":"gu27 3jx",
    "addr:street":"Russett Court",
    "iso:country":"GB",
    "sg:address":"Russett Court, Fernhurst",
    "sg:city":"Haslemere",
    "sg:classifiers":[
        {
            "category":"Social Services",
            "subcategory":"Adult Care",
            "type":"Services"
        },
        {
            "category":"Government",
            "subcategory":"Office",
            "type":"Public Place"
        }
    ],
    "sg:phone":"+44 1428 652040",
    "sg:postcode":"GU27 3JX",
    "sg:province":"Hampshire",
    "sg:tags":[
        "housing",
        "local",
        "sheltered"
    ],
    "wof:name":"Russett Court Sheltered Housing",
    "wof:placetype":"venue"
},
  "geometry": {"coordinates":[-0.725629,51.049732],"type":"Point"}
}