{
  "type": "Feature",
  "properties": {
    "addr:full":"149 Greenford Road Harrow Greater London HA1 3QN",
    "addr:housenumber":"149",
    "addr:postcode":"ha1 3qn",
    "addr:street":"Greenford Road",
    "iso:country":"GB",
    "sg:address":"149 Greenford Road",
    "sg:city":"Harrow",
    "sg:classifiers":[
        {
            "category":"Shopping",
            "subcategory":"Florist",
            "type":"Retail Goods"
        }
    ],
    "sg:phone":"+44 20 8864 0035",
    "sg:postcode":"HA1 3QN",
    "sg:province":"Greater London",
    "wof:name":"Mandy's Flower Shop",
    "wof:placetype":"venue"
},
  "geometry": {"coordinates":[-0.33557,51.557911],"type":"Point"}
}