{
  "type": "Feature",
  "properties": {
    "iso:country":"GB",
    "sg:address":"108 Gorton Road, Reddish",
    "sg:city":"Stockport",
    "sg:classifiers":[
        {
            "category":"Shopping",
            "subcategory":"Pets & Pet Supplies",
            "type":"Retail Goods"
        }
    ],
    "sg:postcode":"SK5 6UE",
    "sg:province":"Cheshire",
    "wof:name":"Reddish Pet Supplies",
    "wof:placetype":"venue"
},
  "geometry": {"coordinates":[-2.1586670876,53.4406051636],"type":"Point"}
}