{
  "type": "Feature",
  "properties": {
    "iso:country":"GB",
    "sg:address":"11b Church St",
    "sg:city":"Nottingham",
    "sg:classifiers":[
        {
            "category":"Health Services",
            "subcategory":"Doctor",
            "type":"Services"
        }
    ],
    "sg:phone":"+44 1773 712065",
    "sg:postcode":"NG16 3BS",
    "sg:province":"Derbyshire",
    "sg:tags":[
        "practitioners"
    ],
    "wof:name":"Exley, P",
    "wof:placetype":"venue"
},
  "geometry": {"coordinates":[-1.308011,53.016644],"type":"Point"}
}