{
  "type": "Feature",
  "properties": {
    "addr:full":"22 Old Town Chard Devon TA20 2BD",
    "addr:housenumber":"22",
    "addr:postcode":"ta20 2bd",
    "addr:street":"Old",
    "iso:country":"GB",
    "sg:address":"22 Old Town",
    "sg:city":"Chard",
    "sg:classifiers":[
        {
            "category":"Professional",
            "subcategory":"Engineering",
            "type":"Services"
        }
    ],
    "sg:phone":"+44 1460 62298",
    "sg:postcode":"TA20 2BD",
    "sg:province":"Devon",
    "wof:name":"Mike Lawson",
    "wof:placetype":"venue"
},
  "geometry": {"coordinates":[-2.9625608921,50.8700714111],"type":"Point"}
}