{
  "type": "Feature",
  "properties": {
    "iso:country":"GB",
    "sg:address":"Rhos Fach, Trimsaran Road",
    "sg:city":"Llanelli",
    "sg:classifiers":[
        {
            "category":"Farming",
            "subcategory":"Farm",
            "type":"Manufacturing & Wholesale Goods"
        }
    ],
    "sg:phone":"+44 1554 810671",
    "sg:postcode":"SA15 4RF",
    "sg:province":"Carmarthenshire",
    "sg:tags":[
        "egg",
        "producer"
    ],
    "wof:name":"G & L Cavill",
    "wof:placetype":"venue"
},
  "geometry": {"coordinates":[-4.229604,51.715439],"type":"Point"}
}