{
  "type": "Feature",
  "properties": {
    "addr:full":"1 Ker St Greenock Inverclyde PA15 1YP",
    "addr:housenumber":"1",
    "addr:postcode":"pa15 1yp",
    "addr:street":"Ker St Greenock",
    "iso:country":"GB",
    "sg:address":"1 Ker St",
    "sg:city":"Greenock",
    "sg:classifiers":[
        {
            "category":"Autos & Motor Vehicles",
            "subcategory":"Automobile Sales",
            "type":"Retail Goods"
        }
    ],
    "sg:phone":"+44 1475 888890",
    "sg:postcode":"PA15 1YP",
    "sg:province":"Inverclyde",
    "sg:tags":[
        "car"
    ],
    "wof:name":"Inverclyde Citroen Ltd",
    "wof:placetype":"venue"
},
  "geometry": {"coordinates":[-4.7626690865,55.9535255432],"type":"Point"}
}