{
  "type": "Feature",
  "properties": {
    "addr:full":"Bretton Court, Manor Road, Wales Village Sheffield South Yorkshire S26 5PS",
    "addr:postcode":"s26 5ps",
    "addr:street":"Bretton;Manor Road",
    "iso:country":"GB",
    "sg:address":"Bretton Court, Manor Road, Wales Village",
    "sg:city":"Sheffield",
    "sg:classifiers":[
        {
            "category":"Professional",
            "subcategory":"Computer Services",
            "type":"Services"
        }
    ],
    "sg:phone":"+44 845 644 1670",
    "sg:postcode":"S26 5PS",
    "sg:province":"South Yorkshire",
    "sg:tags":[
        "system",
        "software"
    ],
    "wof:name":"S & S Systems Ltd.",
    "wof:placetype":"venue"
},
  "geometry": {"coordinates":[-1.2816610336,53.3436393738],"type":"Point"}
}