{
  "type": "Feature",
  "properties": {
    "addr:full":"First Floor, 36 St Mary Street Cardiff Cardiff CF10 1AD",
    "addr:housenumber":"36",
    "addr:postcode":"cf10 1ad",
    "addr:street":"St Mary Street",
    "iso:country":"GB",
    "sg:address":"First Floor, 36 St Mary Street",
    "sg:city":"Cardiff",
    "sg:classifiers":[
        {
            "category":"Manufacturing",
            "subcategory":"Jewelry",
            "type":"Manufacturing & Wholesale Goods"
        }
    ],
    "sg:postcode":"CF10 1AD",
    "sg:province":"Cardiff",
    "sg:tags":[
        "repair",
        "jewellery"
    ],
    "wof:name":"Napier",
    "wof:placetype":"venue"
},
  "geometry": {"coordinates":[-3.177989,51.478401],"type":"Point"}
}