{
  "type": "Feature",
  "properties": {
    "addr:full":"Cattsford, Dingleden, Benenden Cranbrook Kent TN17 4JX",
    "addr:postcode":"tn17 4jx",
    "iso:country":"GB",
    "sg:address":"Cattsford, Dingleden, Benenden",
    "sg:city":"Cranbrook",
    "sg:classifiers":[
        {
            "category":"Building & Trades",
            "subcategory":"Plumbing",
            "type":"Services"
        }
    ],
    "sg:postcode":"TN17 4JX",
    "sg:province":"Kent",
    "sg:tags":[
        "heating"
    ],
    "wof:name":"Premier Property Maintenance",
    "wof:placetype":"venue"
},
  "geometry": {"coordinates":[0.5806949735,51.0668716431],"type":"Point"}
}