{
  "type": "Feature",
  "properties": {
    "iso:country":"GB",
    "sg:address":"Tre Wilmod Farm, Llaintock",
    "sg:city":"Holyhead",
    "sg:classifiers":[
        {
            "category":"Building & Trades",
            "subcategory":"Landscaping Services",
            "type":"Services"
        },
        {
            "category":"Home & Garden",
            "subcategory":"Garden Supply",
            "type":"Retail Goods"
        }
    ],
    "sg:phone":"+44 1407 762837",
    "sg:postcode":"LL65 1YT",
    "sg:province":"Isle of Anglesey",
    "sg:tags":[
        "planting",
        "nurseryman",
        "tree",
        "shrub"
    ],
    "wof:name":"B Murphy",
    "wof:placetype":"venue"
},
  "geometry": {"coordinates":[-4.6307139397,53.3063697815],"type":"Point"}
}