{
  "type": "Feature",
  "properties": {
    "iso:country":"GB",
    "sg:address":"Ringway, Neston",
    "sg:city":"Wirral",
    "sg:classifiers":[
        {
            "category":"Retail",
            "subcategory":"Auto Repair",
            "type":"Services"
        }
    ],
    "sg:phone":"+44 151 336 4672",
    "sg:postcode":"CH64 3RS",
    "sg:province":"Cheshire",
    "sg:tags":[
        "car",
        "specialist",
        "customizing"
    ],
    "wof:name":"Ats",
    "wof:placetype":"venue"
},
  "geometry": {"coordinates":[-3.057666,53.298172],"type":"Point"}
}