{
  "type": "Feature",
  "properties": {
    "iso:country":"GB",
    "sg:address":"1 Chalmers Crescent",
    "sg:city":"Edinburgh",
    "sg:classifiers":[
        {
            "category":"Farming",
            "subcategory":"Nursery",
            "type":"Manufacturing & Wholesale Goods"
        },
        {
            "category":"Social Services",
            "subcategory":"Child Care",
            "type":"Services"
        }
    ],
    "sg:phone":"+44 131 662 0364",
    "sg:postcode":"EH9 1TW",
    "sg:province":"City of Edinburgh",
    "sg:tags":[
        "creche"
    ],
    "wof:name":"Stepping Stones Nursery",
    "wof:placetype":"venue"
},
  "geometry": {"coordinates":[-3.191578,55.937916],"type":"Point"}
}