{
  "type": "Feature",
  "properties": {
    "addr:full":"34 Southway Lane Plymouth Devon PL6 7DJ",
    "addr:housenumber":"34",
    "addr:postcode":"pl6 7dj",
    "addr:street":"Southway Lane",
    "iso:country":"GB",
    "sg:address":"34 Southway Lane",
    "sg:city":"Plymouth",
    "sg:classifiers":[
        {
            "category":"Building & Trades",
            "subcategory":"Construction",
            "type":"Services"
        }
    ],
    "sg:postcode":"PL6 7DJ",
    "sg:province":"Devon",
    "sg:tags":[
        "platform",
        "work",
        "scaffolding"
    ],
    "wof:name":"Frank Mills Scaffolding",
    "wof:placetype":"venue"
},
  "geometry": {"coordinates":[-4.1164870262,50.4299545288],"type":"Point"}
}