{
  "type": "Feature",
  "properties": {
    "addr:full":"16 Fairgreen Ct, Fairgreen Barnet Hertfordshire EN4 0QT",
    "addr:housenumber":"16",
    "addr:postcode":"en4 0qt",
    "addr:street":"Fairgreen Ct",
    "iso:country":"GB",
    "sg:address":"16 Fairgreen Ct, Fairgreen",
    "sg:city":"Barnet",
    "sg:classifiers":[
        {
            "category":"Professional",
            "subcategory":"Business Services",
            "type":"Services"
        }
    ],
    "sg:phone":"+44 20 8275 0805",
    "sg:postcode":"EN4 0QT",
    "sg:province":"Hertfordshire",
    "sg:tags":[
        "fashion",
        "agent"
    ],
    "wof:name":"Newstream Ltd",
    "wof:placetype":"venue"
},
  "geometry": {"coordinates":[-0.15536,51.656174],"type":"Point"}
}