{
  "type": "Feature",
  "properties": {
    "addr:full":"34 Kings Rd Harrogate North Yorkshire HG1 5JW",
    "addr:housenumber":"34",
    "addr:postcode":"hg1 5jw",
    "addr:street":"Kings Rd",
    "iso:country":"GB",
    "sg:address":"34 Kings Rd",
    "sg:city":"Harrogate",
    "sg:classifiers":[
        {
            "category":"Travel",
            "subcategory":"Hotels & Motels",
            "type":"Entertainment"
        }
    ],
    "sg:postcode":"HG1 5JW",
    "sg:province":"North Yorkshire",
    "wof:name":"Smart,Linda M,",
    "wof:placetype":"venue"
},
  "geometry": {"coordinates":[-1.541762948,53.9958724976],"type":"Point"}
}