{
  "type": "Feature",
  "properties": {
    "iso:country":"GB",
    "sg:address":"45 Holmesdale Road",
    "sg:city":"London",
    "sg:classifiers":[
        {
            "category":"Building & Trades",
            "subcategory":"Construction",
            "type":"Services"
        },
        {
            "category":"Home & Garden",
            "subcategory":"Carpets & Floor Coverings",
            "type":"Retail Goods"
        }
    ],
    "sg:phone":"+44 20 8405 0451",
    "sg:postcode":"SE25 6JH",
    "sg:province":"Greater London",
    "sg:tags":[
        "builder",
        "carpets",
        "rug",
        "matting"
    ],
    "wof:name":"R Evans Building Services",
    "wof:placetype":"venue"
},
  "geometry": {"coordinates":[-0.0910919979,51.3943405151],"type":"Point"}
}