{
  "type": "Feature",
  "properties": {
    "addr:full":"Pidney, Hazelbury Bryan Sturminster Newton Dorset DT10 2EB",
    "addr:housenumber":"sturminster newton",
    "addr:postcode":"dt10 2eb",
    "iso:country":"GB",
    "sg:address":"Pidney, Hazelbury Bryan",
    "sg:city":"Sturminster Newton",
    "sg:classifiers":[
        {
            "category":"Bars & Pubs",
            "type":"Food & Drink"
        },
        {
            "category":"Community Center",
            "subcategory":"Social",
            "type":"Public Place"
        }
    ],
    "sg:phone":"+44 1258 817295",
    "sg:postcode":"DT10 2EB",
    "sg:province":"Dorset",
    "sg:tags":[
        "pubs",
        "house",
        "inn",
        "activity"
    ],
    "wof:name":"Antelope Inn",
    "wof:placetype":"venue"
},
  "geometry": {"coordinates":[-2.3578650951,50.876159668],"type":"Point"}
}