{
  "type": "Feature",
  "properties": {
    "addr:full":"104 Castleford Road Normanton West Yorkshire WF6 2EE",
    "addr:housenumber":"104",
    "addr:postcode":"wf6 2ee",
    "addr:street":"Castleford Road",
    "iso:country":"GB",
    "sg:address":"104 Castleford Road",
    "sg:city":"Normanton",
    "sg:classifiers":[
        {
            "category":"Shopping",
            "subcategory":"Pharmacy",
            "type":"Retail Goods"
        }
    ],
    "sg:phone":"+44 1924 220021",
    "sg:postcode":"WF6 2EE",
    "sg:province":"West Yorkshire",
    "sg:tags":[
        "pharmacist",
        "dispensing",
        "chemist"
    ],
    "wof:name":"M & A Dispensing Chemists Ltd",
    "wof:placetype":"venue"
},
  "geometry": {"coordinates":[-1.4113349915,53.7012901306],"type":"Point"}
}