{
  "type": "Feature",
  "properties": {
    "iso:country":"GB",
    "sg:address":"55a Oxford St",
    "sg:city":"Weston Super Mare",
    "sg:classifiers":[
        {
            "category":"Professional",
            "subcategory":"Lawyer & Legal Services",
            "type":"Services"
        }
    ],
    "sg:phone":"+44 1934 415376",
    "sg:postcode":"BS23 1TR",
    "sg:province":"Somerset",
    "sg:tags":[
        "advice",
        "counselling"
    ],
    "wof:name":"ACAD Advice & Counselling On Alcohol & Drugs",
    "wof:placetype":"venue"
},
  "geometry": {"coordinates":[-2.9769589901,51.3463363647],"type":"Point"}
}