{
  "type": "Feature",
  "properties": {
    "iso:country":"GB",
    "sg:address":"Unit, 25, Botley Works N. Hinksey Lane",
    "sg:city":"Oxford",
    "sg:classifiers":[
        {
            "category":"Shopping",
            "subcategory":"Computers & Home Electronics",
            "type":"Retail Goods"
        }
    ],
    "sg:phone":"+44 1865 726661",
    "sg:postcode":"OX2 0LX",
    "sg:province":"Oxfordshire",
    "sg:tags":[
        "electrical"
    ],
    "wof:name":"A.C Electrical Wholesale",
    "wof:placetype":"venue"
},
  "geometry": {"coordinates":[-1.29338,51.752579],"type":"Point"}
}