{
  "type": "Feature",
  "properties": {
    "addr:full":"3 Market Pl Woodstock Oxfordshire OX20 1SY",
    "addr:housenumber":"3",
    "addr:postcode":"ox20 1sy",
    "addr:street":"Market Pl",
    "iso:country":"GB",
    "sg:address":"3 Market Pl",
    "sg:city":"Woodstock",
    "sg:classifiers":[
        {
            "category":"Professional",
            "subcategory":"Computer Services",
            "type":"Services"
        }
    ],
    "sg:phone":"+44 1993 812277",
    "sg:postcode":"OX20 1SY",
    "sg:province":"Oxfordshire",
    "sg:tags":[
        "aided",
        "design"
    ],
    "wof:name":"Unidraft Computer Aided Drafting Ltd",
    "wof:placetype":"venue"
},
  "geometry": {"coordinates":[-1.355755,51.847458],"type":"Point"}
}