{
  "type": "Feature",
  "properties": {
    "addr:full":"2 King Street Llandeilo Carmarthenshire SA19 6AA",
    "addr:housenumber":"2",
    "addr:postcode":"sa19 6aa",
    "addr:street":"King Street",
    "iso:country":"GB",
    "sg:address":"2 King Street",
    "sg:city":"Llandeilo",
    "sg:classifiers":[
        {
            "category":"Shopping",
            "subcategory":"Antiques",
            "type":"Retail Goods"
        }
    ],
    "sg:phone":"+44 1558 822447",
    "sg:postcode":"SA19 6AA",
    "sg:province":"Carmarthenshire",
    "wof:name":"Alison Mostyn",
    "wof:placetype":"venue"
},
  "geometry": {"coordinates":[-3.99344,51.882591],"type":"Point"}
}