{
  "type": "Feature",
  "properties": {
    "addr:full":"134a St Marys Road, Garston Liverpool Merseyside L19 2JG",
    "addr:housenumber":"134a",
    "addr:postcode":"l19 2jg",
    "addr:street":"St Marys Road",
    "iso:country":"GB",
    "sg:address":"134a St Marys Road, Garston",
    "sg:city":"Liverpool",
    "sg:classifiers":[
        {
            "category":"Travel",
            "subcategory":"Hotels & Motels",
            "type":"Entertainment"
        }
    ],
    "sg:phone":"+44 151 427 4521",
    "sg:postcode":"L19 2JG",
    "sg:province":"Merseyside",
    "sg:tags":[
        "house",
        "guest"
    ],
    "wof:name":"STOURBRIDGE GUEST HOUSE",
    "wof:placetype":"venue"
},
  "geometry": {"coordinates":[-2.90266,53.3559],"type":"Point"}
}