{
  "type": "Feature",
  "properties": {
    "addr:full":"352 Farnborough Rd, Clifton Nottingham Nottinghamshire NG11 9AA",
    "addr:housenumber":"352",
    "addr:postcode":"ng11 9aa",
    "addr:street":"Farnborough Rd",
    "iso:country":"GB",
    "sg:address":"352 Farnborough Rd, Clifton",
    "sg:city":"Nottingham",
    "sg:classifiers":[
        {
            "category":"Building & Trades",
            "subcategory":"Construction",
            "type":"Services"
        }
    ],
    "sg:postcode":"NG11 9AA",
    "sg:province":"Nottinghamshire",
    "sg:tags":[
        "roofing"
    ],
    "wof:name":"Anchor Roofing & Guttering Services",
    "wof:placetype":"venue"
},
  "geometry": {"coordinates":[-1.1699949503,52.8989868164],"type":"Point"}
}