{
  "type": "Feature",
  "properties": {
    "addr:full":"23 Aigburth Drive, Sefton Park Liverpool Merseyside L17 4JQ",
    "addr:housenumber":"23",
    "addr:postcode":"l17 4jq",
    "addr:street":"Aigburth Drive;Park",
    "iso:country":"GB",
    "sg:address":"23 Aigburth Drive, Sefton Park",
    "sg:city":"Liverpool",
    "sg:classifiers":[
        {
            "category":"Travel",
            "subcategory":"Hotels & Motels",
            "type":"Entertainment"
        }
    ],
    "sg:phone":"+44 151 727 4754",
    "sg:postcode":"L17 4JQ",
    "sg:province":"Merseyside",
    "wof:name":"The Park Lane Hotel",
    "wof:placetype":"venue"
},
  "geometry": {"coordinates":[-2.941215,53.379009],"type":"Point"}
}