{
  "type": "Feature",
  "properties": {
    "iso:country":"GB",
    "sg:address":"62 Lansdowne Road",
    "sg:city":"Bournemouth",
    "sg:classifiers":[
        {
            "category":"Travel",
            "subcategory":"Hotels & Motels",
            "type":"Entertainment"
        }
    ],
    "sg:postcode":"BH1 1RS",
    "sg:province":"Dorset",
    "wof:name":"Dorset Westbury Hotel",
    "wof:placetype":"venue"
},
  "geometry": {"coordinates":[-1.87151,50.73011],"type":"Point"}
}