{
  "type": "Feature",
  "properties": {
    "addr:full":"Harvey Centre Harlow Essex CM20 1XT",
    "addr:postcode":"cm20 1xt",
    "addr:street":"Harvey Centre",
    "iso:country":"GB",
    "sg:address":"Harvey Centre",
    "sg:city":"Harlow",
    "sg:classifiers":[
        {
            "category":"Personal",
            "subcategory":"Beauty Salon",
            "type":"Services"
        }
    ],
    "sg:phone":"+44 1279 450207",
    "sg:postcode":"CM20 1XT",
    "sg:province":"Essex",
    "sg:tags":[
        "unisex",
        "hairdresser"
    ],
    "wof:name":"Regis Salon",
    "wof:placetype":"venue"
},
  "geometry": {"coordinates":[0.0942400023,51.7689208984],"type":"Point"}
}