{
  "type": "Feature",
  "properties": {
    "addr:full":"Rhodesia Lodge, Highland Avenue Brentwood Essex CM15 9DD",
    "addr:postcode":"cm15 9dd",
    "addr:street":"Highland Avenue",
    "iso:country":"GB",
    "sg:address":"Rhodesia Lodge, Highland Avenue",
    "sg:city":"Brentwood",
    "sg:classifiers":[
        {
            "category":"Professional",
            "subcategory":"Management & Consulting",
            "type":"Services"
        }
    ],
    "sg:phone":"+44 1277 224751",
    "sg:postcode":"CM15 9DD",
    "sg:province":"Essex",
    "sg:tags":[
        "marketing",
        "consultant"
    ],
    "wof:name":"Christian Doige Creative Marketing Ltd.",
    "wof:placetype":"venue"
},
  "geometry": {"coordinates":[0.30276,51.62542],"type":"Point"}
}