{
  "type": "Feature",
  "properties": {
    "iso:country":"GB",
    "sg:address":"307 Bourne Road, Pode Hole",
    "sg:city":"Spalding",
    "sg:classifiers":[
        {
            "category":"Professional",
            "type":"Services"
        },
        {
            "category":"Building & Trades",
            "subcategory":"Construction",
            "type":"Services"
        }
    ],
    "sg:phone":"+44 1775 724580",
    "sg:postcode":"PE11 3LW",
    "sg:province":"Lincolnshire",
    "sg:tags":[
        "interior",
        "furnishers",
        "builder",
        "designer"
    ],
    "wof:name":"Bohemia Creations",
    "wof:placetype":"venue"
},
  "geometry": {"coordinates":[-0.1976840049,52.7813987732],"type":"Point"}
}