{
  "type": "Feature",
  "properties": {
    "addr:full":"174 Pinner Rd Harrow Greater London HA1 4JP",
    "addr:housenumber":"174",
    "addr:postcode":"ha1 4jp",
    "addr:street":"Pinner Rd",
    "iso:country":"GB",
    "sg:address":"174 Pinner Rd",
    "sg:city":"Harrow",
    "sg:classifiers":[
        {
            "category":"Real Estate",
            "subcategory":"Real Estate Agent",
            "type":"Services"
        }
    ],
    "sg:phone":"+44 1708 722231",
    "sg:postcode":"HA1 4JP",
    "sg:province":"Greater London",
    "wof:name":"Homeowner Card Ltd",
    "wof:placetype":"venue"
},
  "geometry": {"coordinates":[-0.3515509963,51.5822105408],"type":"Point"}
}