{
  "type": "Feature",
  "properties": {
    "addr:full":"9 Balmoral Road, Winshill Burton-on-trent Derbyshire DE15 0JN",
    "addr:housenumber":"9",
    "addr:postcode":"de15 0jn",
    "addr:street":"Balmoral Road",
    "iso:country":"GB",
    "sg:address":"9 Balmoral Road, Winshill",
    "sg:city":"Burton-on-trent",
    "sg:classifiers":[
        {
            "category":"Retail",
            "subcategory":"Repair Shop",
            "type":"Services"
        }
    ],
    "sg:phone":"+44 1283 565796",
    "sg:postcode":"DE15 0JN",
    "sg:province":"Derbyshire",
    "sg:tags":[
        "radio",
        "television",
        "video"
    ],
    "wof:name":"Goldsmith Services",
    "wof:placetype":"venue"
},
  "geometry": {"coordinates":[-1.613141,52.80714],"type":"Point"}
}