{
  "type": "Feature",
  "properties": {
    "addr:full":"71 North Rd Durham Durham DH1 4SQ",
    "addr:housenumber":"71",
    "addr:postcode":"dh1 4sq",
    "addr:street":"North Rd",
    "iso:country":"GB",
    "sg:address":"71 North Rd",
    "sg:city":"Durham",
    "sg:classifiers":[
        {
            "category":"Shopping",
            "subcategory":"Florist",
            "type":"Retail Goods"
        }
    ],
    "sg:phone":"+44 191 384 4180",
    "sg:postcode":"DH1 4SQ",
    "sg:province":"Durham",
    "wof:name":"Metcalfe's Florists",
    "wof:placetype":"venue"
},
  "geometry": {"coordinates":[-1.58041,54.777065],"type":"Point"}
}