{
  "type": "Feature",
  "properties": {
    "addr:full":"Hut Grn, Weeland Road Goole East Riding of Yorkshire DN14 0RX",
    "addr:postcode":"dn14 0rx",
    "addr:street":"Hut Grn Weeland Road",
    "iso:country":"GB",
    "sg:address":"Hut Grn, Weeland Road",
    "sg:city":"Goole",
    "sg:classifiers":[
        {
            "category":"Retail",
            "subcategory":"Auto Repair",
            "type":"Services"
        }
    ],
    "sg:phone":"+44 1977 661399",
    "sg:postcode":"DN14 0RX",
    "sg:province":"East Riding of Yorkshire",
    "sg:tags":[
        "modification",
        "garage"
    ],
    "wof:name":"Eggborough Garage Services",
    "wof:placetype":"venue"
},
  "geometry": {"coordinates":[-1.198545,53.712917],"type":"Point"}
}