{
  "type": "Feature",
  "properties": {
    "addr:full":"67 Franklin Road Harrogate North Yorkshire HG1 5EH",
    "addr:housenumber":"67",
    "addr:postcode":"hg1 5eh",
    "addr:street":"Franklin Road",
    "iso:country":"GB",
    "sg:address":"67 Franklin Road",
    "sg:city":"Harrogate",
    "sg:classifiers":[
        {
            "category":"Travel",
            "subcategory":"Hotels & Motels",
            "type":"Entertainment"
        }
    ],
    "sg:phone":"+44 1423 505857",
    "sg:postcode":"HG1 5EH",
    "sg:province":"North Yorkshire",
    "sg:tags":[
        "house",
        "guest"
    ],
    "wof:name":"Murray House",
    "wof:placetype":"venue"
},
  "geometry": {"coordinates":[-1.538198,53.998096],"type":"Point"}
}