{
  "type": "Feature",
  "properties": {
    "addr:full":"18 Redgrave Place, Flanderwell Rotherham South Yorkshire S66 2XU",
    "addr:housenumber":"18",
    "addr:postcode":"s66 2xu",
    "addr:street":"Redgrave Place Flanderwell",
    "iso:country":"GB",
    "sg:address":"18 Redgrave Place, Flanderwell",
    "sg:city":"Rotherham",
    "sg:classifiers":[
        {
            "category":"Professional",
            "type":"Services"
        }
    ],
    "sg:phone":"+44 1709 700681",
    "sg:postcode":"S66 2XU",
    "sg:province":"South Yorkshire",
    "sg:tags":[
        "caterer"
    ],
    "wof:name":"Bizzy Bee'S Buffets",
    "wof:placetype":"venue"
},
  "geometry": {"coordinates":[-1.281624,53.430809],"type":"Point"}
}