{
  "type": "Feature",
  "properties": {
    "iso:country":"GB",
    "sg:address":"Fern Mills, Old Leeds Road",
    "sg:city":"Huddersfield",
    "sg:classifiers":[
        {
            "category":"Manufacturing",
            "subcategory":"Wood Products",
            "type":"Manufacturing & Wholesale Goods"
        }
    ],
    "sg:phone":"+44 1484 424514",
    "sg:postcode":"HD1 1SH",
    "sg:province":"West Yorkshire",
    "sg:tags":[
        "packaging",
        "crate",
        "pallets"
    ],
    "wof:name":"Beevers & Barrett Ltd.",
    "wof:placetype":"venue"
},
  "geometry": {"coordinates":[-1.782684,53.646954],"type":"Point"}
}