{
  "type": "Feature",
  "properties": {
    "iso:country":"GB",
    "sg:address":"3 Hammer Lane",
    "sg:city":"Hemel Hempstead",
    "sg:classifiers":[
        {
            "category":"Professional",
            "subcategory":"Art Services",
            "type":"Services"
        },
        {
            "category":"Building & Trades",
            "subcategory":"Construction",
            "type":"Services"
        }
    ],
    "sg:phone":"+44 1442 246071",
    "sg:postcode":"HP2 4EU",
    "sg:province":"Hertfordshire",
    "sg:tags":[
        "decorator",
        "painter"
    ],
    "wof:name":"Bradleys Painting & Decorating Contractors",
    "wof:placetype":"venue"
},
  "geometry": {"coordinates":[-0.452727,51.756226],"type":"Point"}
}