{
  "type": "Feature",
  "properties": {
    "addr:full":"Sheldon Honiton Devon EX14 4QS",
    "addr:postcode":"ex14 4qs",
    "iso:country":"GB",
    "sg:address":"Sheldon",
    "sg:city":"Honiton",
    "sg:classifiers":[
        {
            "category":"Farming",
            "subcategory":"Farm",
            "type":"Manufacturing & Wholesale Goods"
        }
    ],
    "sg:postcode":"EX14 4QS",
    "sg:province":"Devon",
    "sg:tags":[
        "hatchery"
    ],
    "wof:name":"Hollies Trout Farm",
    "wof:placetype":"venue"
},
  "geometry": {"coordinates":[-3.1956589222,50.8475914001],"type":"Point"}
}