{
  "type": "Feature",
  "properties": {
    "addr:full":"50 East Walk Barnet Hertfordshire EN4 8JU",
    "addr:housenumber":"50",
    "addr:postcode":"en4 8ju",
    "addr:street":"East Walk",
    "iso:country":"GB",
    "sg:address":"50 East Walk",
    "sg:city":"Barnet",
    "sg:classifiers":[
        {
            "category":"Professional",
            "subcategory":"Art Services",
            "type":"Services"
        }
    ],
    "sg:phone":"+44 20 8211 4998",
    "sg:postcode":"EN4 8JU",
    "sg:province":"Hertfordshire",
    "sg:tags":[
        "photographer"
    ],
    "wof:name":"Acrobat Imaging & Acrobat Art",
    "wof:placetype":"venue"
},
  "geometry": {"coordinates":[-0.156919,51.641361],"type":"Point"}
}