{
  "type": "Feature",
  "properties": {
    "addr:full":"Market Hall, Market Square Chesterfield Derbyshire S40 1AR",
    "addr:postcode":"s40 1ar",
    "addr:street":"Market Square",
    "iso:country":"GB",
    "sg:address":"Market Hall, Market Square",
    "sg:city":"Chesterfield",
    "sg:classifiers":[
        {
            "category":"Government",
            "subcategory":"Office",
            "type":"Public Place"
        }
    ],
    "sg:phone":"+44 1246 208267",
    "sg:postcode":"S40 1AR",
    "sg:province":"Derbyshire",
    "sg:tags":[
        "education",
        "agency",
        "authority"
    ],
    "wof:name":"Chesterfield Urban Studies Centre",
    "wof:placetype":"venue"
},
  "geometry": {"coordinates":[-1.429579,53.235661],"type":"Point"}
}