{
  "type": "Feature",
  "properties": {
    "iso:country":"GB",
    "sg:address":"3 Hungate Lane, Hunmanby",
    "sg:city":"Filey",
    "sg:classifiers":[
        {
            "category":"Transit Center",
            "subcategory":"Freight",
            "type":"Transportation"
        },
        {
            "category":"Shopping",
            "subcategory":"Crafts & Fabrics",
            "type":"Retail Goods"
        }
    ],
    "sg:phone":"+44 1723 890453",
    "sg:postcode":"YO14 0NN",
    "sg:province":"North Yorkshire",
    "sg:tags":[
        "shop",
        "outlet",
        "centre"
    ],
    "wof:name":"K DAVIS",
    "wof:placetype":"venue"
},
  "geometry": {"coordinates":[-0.319464,54.180733],"type":"Point"}
}