{
  "type": "Feature",
  "properties": {
    "addr:full":"260 Barley Lane Ilford Essex IG3 8XS",
    "addr:housenumber":"260",
    "addr:postcode":"ig3 8xs",
    "addr:street":"Barley Lane",
    "iso:country":"GB",
    "sg:address":"260 Barley Lane",
    "sg:city":"Ilford",
    "sg:classifiers":[
        {
            "category":"Retail",
            "subcategory":"Auto Repair",
            "type":"Services"
        }
    ],
    "sg:phone":"+44 20 8590 4601",
    "sg:postcode":"IG3 8XS",
    "sg:province":"Essex",
    "sg:tags":[
        "modification",
        "garage"
    ],
    "wof:name":"Patten Body Repairs",
    "wof:placetype":"venue"
},
  "geometry": {"coordinates":[0.115642,51.580311],"type":"Point"}
}