{
  "type": "Feature",
  "properties": {
    "iso:country":"GB",
    "sg:address":"52 Ince Green Lane, Ince",
    "sg:city":"Wigan",
    "sg:classifiers":[
        {
            "category":"Building & Trades",
            "subcategory":"Construction",
            "type":"Services"
        }
    ],
    "sg:phone":"+44 1942 492415",
    "sg:postcode":"WN2 2AR",
    "sg:province":"Lancashire",
    "sg:tags":[
        "glass",
        "replacement"
    ],
    "wof:name":"A Jones Glass & Glazing",
    "wof:placetype":"venue"
},
  "geometry": {"coordinates":[-2.606896,53.542034],"type":"Point"}
}