{
  "type": "Feature",
  "properties": {
    "iso:country":"GB",
    "sg:address":"21 Amesbury Crescent",
    "sg:city":"Hove",
    "sg:classifiers":[
        {
            "category":"Professional",
            "subcategory":"Employment Agencies",
            "type":"Services"
        }
    ],
    "sg:phone":"+44 1273 705959",
    "sg:postcode":"BN3 5RD",
    "sg:province":"East Sussex",
    "sg:tags":[
        "pair",
        "au"
    ],
    "wof:name":"Anglo Continental Au Pair Placement Agency",
    "wof:placetype":"venue"
},
  "geometry": {"coordinates":[-0.190975,50.83186],"type":"Point"}
}