{
  "type": "Feature",
  "properties": {
    "addr:full":"16 The Drive, Harold Wood Romford Essex RM3 0DU",
    "addr:housenumber":"16",
    "addr:postcode":"rm3 0du",
    "addr:street":"The Drive",
    "iso:country":"GB",
    "sg:address":"16 The Drive, Harold Wood",
    "sg:city":"Romford",
    "sg:classifiers":[
        {
            "category":"Wholesale",
            "subcategory":"Books, Periodicals, & Newspapers",
            "type":"Manufacturing & Wholesale Goods"
        }
    ],
    "sg:postcode":"RM3 0DU",
    "sg:province":"Essex",
    "sg:tags":[
        "publishing"
    ],
    "wof:name":"Printcall Ltd",
    "wof:placetype":"venue"
},
  "geometry": {"coordinates":[0.230696,51.594685],"type":"Point"}
}