{
  "type": "Feature",
  "properties": {
    "addr:full":"17 Beckford Street Manchester Greater Manchester M40 5AE",
    "addr:housenumber":"17",
    "addr:postcode":"m40 5ae",
    "addr:street":"Beckford Street",
    "iso:country":"GB",
    "sg:address":"17 Beckford Street",
    "sg:city":"Manchester",
    "sg:classifiers":[
        {
            "category":"Retail",
            "subcategory":"Auto Repair",
            "type":"Services"
        }
    ],
    "sg:phone":"+44 161 205 4979",
    "sg:postcode":"M40 5AE",
    "sg:province":"Greater Manchester",
    "sg:tags":[
        "modification",
        "garage",
        "related"
    ],
    "wof:name":"Crescent Motors",
    "wof:placetype":"venue"
},
  "geometry": {"coordinates":[-2.207242,53.49741],"type":"Point"}
}