{
  "type": "Feature",
  "properties": {
    "addr:full":"Brunell Buildings, Brunell Road Newton Abbot Devon TQ12 4PB",
    "addr:postcode":"tq12 4pb",
    "addr:street":"Brunell Road",
    "iso:country":"GB",
    "sg:address":"Brunell Buildings, Brunell Road",
    "sg:city":"Newton Abbot",
    "sg:classifiers":[
        {
            "category":"Shopping",
            "subcategory":"Crafts & Fabrics",
            "type":"Retail Goods"
        }
    ],
    "sg:postcode":"TQ12 4PB",
    "sg:province":"Devon",
    "sg:tags":[
        "ceramic"
    ],
    "wof:name":"Top Knobs Ltd.",
    "wof:placetype":"venue"
},
  "geometry": {"coordinates":[-3.6076591015,50.5288696289],"type":"Point"}
}