{
  "type": "Feature",
  "properties": {
    "addr:full":"145 Merry Street Motherwell North Lanarkshire ML1 1JP",
    "addr:housenumber":"145",
    "addr:postcode":"ml1 1jp",
    "addr:street":"Merry Street",
    "iso:country":"GB",
    "sg:address":"145 Merry Street",
    "sg:city":"Motherwell",
    "sg:classifiers":[
        {
            "category":"Recreation",
            "subcategory":"Fishing",
            "type":"Entertainment"
        }
    ],
    "sg:phone":"+44 1698 265777",
    "sg:postcode":"ML1 1JP",
    "sg:province":"North Lanarkshire",
    "sg:tags":[
        "angling"
    ],
    "wof:name":"The Rod and Gun Rack",
    "wof:placetype":"venue"
},
  "geometry": {"coordinates":[-3.9886379242,55.7929458618],"type":"Point"}
}