{
  "type": "Feature",
  "properties": {
    "addr:full":"Unit 1, St Mary's Road, Ramsey Huntingdon Cambridgeshire PE26 2SW",
    "addr:housenumber":"unit 1",
    "addr:postcode":"pe26 2sw",
    "addr:street":"St Mary'S Road",
    "iso:country":"GB",
    "sg:address":"Unit 1, St Mary's Road, Ramsey",
    "sg:city":"Huntingdon",
    "sg:classifiers":[
        {
            "category":"Building & Trades",
            "subcategory":"Construction",
            "type":"Services"
        }
    ],
    "sg:phone":"+44 1487 812148",
    "sg:postcode":"PE26 2SW",
    "sg:province":"Cambridgeshire",
    "sg:tags":[
        "builder"
    ],
    "wof:name":"C J Ingle Developments Ltd.",
    "wof:placetype":"venue"
},
  "geometry": {"coordinates":[-0.1147300005,52.4557418823],"type":"Point"}
}