{
  "type": "Feature",
  "properties": {
    "iso:country":"GB",
    "sg:address":"2 Hospital Road",
    "sg:city":"Bury St Edmunds",
    "sg:classifiers":[
        {
            "category":"Bars & Pubs",
            "type":"Food & Drink"
        },
        {
            "category":"Community Center",
            "subcategory":"Social",
            "type":"Public Place"
        }
    ],
    "sg:phone":"+44 1284 755570",
    "sg:postcode":"IP33 3JT",
    "sg:province":"Suffolk",
    "sg:tags":[
        "pubs",
        "house",
        "inn",
        "activity"
    ],
    "wof:name":"Elephant & Castle",
    "wof:placetype":"venue"
},
  "geometry": {"coordinates":[0.710796,52.241058],"type":"Point"}
}