{
  "type": "Feature",
  "properties": {
    "iso:country":"GB",
    "sg:address":"47 Somerset Av",
    "sg:city":"Luton",
    "sg:classifiers":[
        {
            "category":"Professional",
            "subcategory":"Business Services",
            "type":"Services"
        }
    ],
    "sg:phone":"+44 1582 418932",
    "sg:postcode":"LU2 0PL",
    "sg:province":"Bedfordshire",
    "sg:tags":[
        "distribution"
    ],
    "wof:name":"Luton Leaflet Distribution",
    "wof:placetype":"venue"
},
  "geometry": {"coordinates":[-0.396113,51.889339],"type":"Point"}
}