{
  "type": "Feature",
  "properties": {
    "iso:country":"GB",
    "sg:address":"67 Bredon Gro, Poolbrook",
    "sg:city":"Malvern",
    "sg:classifiers":[
        {
            "category":"Building & Trades",
            "subcategory":"Construction",
            "type":"Services"
        }
    ],
    "sg:phone":"+44 1684 562690",
    "sg:postcode":"WR14 3JS",
    "sg:province":"Herefordshire",
    "sg:tags":[
        "builder"
    ],
    "wof:name":"H & H Builders",
    "wof:placetype":"venue"
},
  "geometry": {"coordinates":[-2.30422,52.100952],"type":"Point"}
}