{
  "type": "Feature",
  "properties": {
    "iso:country":"GB",
    "sg:address":"Dawney Hill, Cemetery Pales",
    "sg:city":"Woking",
    "sg:classifiers":[
        {
            "category":"Retail",
            "subcategory":"Funeral Services",
            "type":"Services"
        }
    ],
    "sg:phone":"+44 1483 473237",
    "sg:postcode":"GU24 0BL",
    "sg:province":"Surrey",
    "sg:tags":[
        "cemetery",
        "crematorium"
    ],
    "wof:name":"American Battle Monument Commission",
    "wof:placetype":"venue"
},
  "geometry": {"coordinates":[-0.6468120217,51.3019943237],"type":"Point"}
}