{
  "type": "Feature",
  "properties": {
    "iso:country":"GB",
    "sg:address":"2-3 Brandreth Road",
    "sg:city":"Plymouth",
    "sg:classifiers":[
        {
            "category":"Health Services",
            "subcategory":"Nursing And Care Facility",
            "type":"Services"
        },
        {
            "category":"Social Services",
            "subcategory":"Retirement Home",
            "type":"Services"
        }
    ],
    "sg:phone":"+44 1752 665042",
    "sg:postcode":"PL3 5HQ",
    "sg:province":"Devon",
    "sg:tags":[
        "residential"
    ],
    "wof:name":"Evergreen Residential Home",
    "wof:placetype":"venue"
},
  "geometry": {"coordinates":[-4.128876,50.389744],"type":"Point"}
}