{
  "type": "Feature",
  "properties": {
    "addr:full":"41 Kirkleatham Street Redcar North Yorkshire TS10 1QH",
    "addr:housenumber":"41",
    "addr:postcode":"ts10 1qh",
    "addr:street":"Kirkleatham Street",
    "iso:country":"GB",
    "sg:address":"41 Kirkleatham Street",
    "sg:city":"Redcar",
    "sg:classifiers":[
        {
            "category":"Health Services",
            "subcategory":"Clinic",
            "type":"Services"
        }
    ],
    "sg:phone":"+44 1642 490881",
    "sg:postcode":"TS10 1QH",
    "sg:province":"North Yorkshire",
    "sg:tags":[
        "nh"
    ],
    "wof:name":"Newlands Community Mental Health Centre",
    "wof:placetype":"venue"
},
  "geometry": {"coordinates":[-1.0804309845,54.6160087585],"type":"Point"}
}