{
  "type": "Feature",
  "properties": {
    "iso:country":"GB",
    "sg:address":"67 High Street",
    "sg:city":"Glastonbury",
    "sg:classifiers":[
        {
            "category":"Shopping",
            "subcategory":"Crafts & Fabrics",
            "type":"Retail Goods"
        }
    ],
    "sg:phone":"+44 1458 832814",
    "sg:postcode":"BA6 9DS",
    "sg:province":"Somerset",
    "sg:tags":[
        "shop"
    ],
    "wof:name":"R W T",
    "wof:placetype":"venue"
},
  "geometry": {"coordinates":[-2.713017,51.148304],"type":"Point"}
}