{
  "type": "Feature",
  "properties": {
    "iso:country":"GB",
    "sg:address":"3 Deerness View, Ushaw Moor",
    "sg:city":"Durham",
    "sg:classifiers":[
        {
            "category":"Home & Garden",
            "subcategory":"Carpets & Floor Coverings",
            "type":"Retail Goods"
        }
    ],
    "sg:phone":"+44 191 373 0869",
    "sg:postcode":"DH7 7PR",
    "sg:province":"Durham",
    "sg:tags":[
        "cleaner",
        "upholstery"
    ],
    "wof:name":"Acme Cleaning",
    "wof:placetype":"venue"
},
  "geometry": {"coordinates":[-1.664449,54.780964],"type":"Point"}
}