{
  "type": "Feature",
  "properties": {
    "iso:country":"GB",
    "sg:address":"41 Broomfield Road",
    "sg:city":"Chelmsford",
    "sg:classifiers":[
        {
            "category":"Health Services",
            "subcategory":"Dentist",
            "type":"Services"
        }
    ],
    "sg:phone":"+44 1245 257181",
    "sg:postcode":"CM1 1SY",
    "sg:province":"Essex",
    "wof:name":"Goodleigh Dental Practice",
    "wof:placetype":"venue"
},
  "geometry": {"coordinates":[0.466007,51.738514],"type":"Point"}
}