{
  "type": "Feature",
  "properties": {
    "addr:full":"23 Station Road Ilkeston Derbyshire DE7 5LD",
    "addr:housenumber":"23",
    "addr:postcode":"de7 5ld",
    "addr:street":"Station Road",
    "iso:country":"GB",
    "sg:address":"23 Station Road",
    "sg:city":"Ilkeston",
    "sg:classifiers":[
        {
            "category":"Bars & Pubs",
            "type":"Food & Drink"
        },
        {
            "category":"Community Center",
            "subcategory":"Social",
            "type":"Public Place"
        }
    ],
    "sg:phone":"+44 115 930 2445",
    "sg:postcode":"DE7 5LD",
    "sg:province":"Derbyshire",
    "sg:tags":[
        "pubs",
        "house",
        "inn",
        "activity"
    ],
    "wof:name":"The Erewash Hotel",
    "wof:placetype":"venue"
},
  "geometry": {"coordinates":[-1.302579,52.975868],"type":"Point"}
}