{
  "type": "Feature",
  "properties": {
    "iso:country":"GB",
    "sg:address":"Bellingham",
    "sg:city":"Hexham",
    "sg:classifiers":[
        {
            "category":"Cafe",
            "type":"Food & Drink"
        }
    ],
    "sg:postcode":"NE48 2DE",
    "sg:province":"Northumberland",
    "sg:tags":[
        "tea",
        "room"
    ],
    "wof:name":"Fountain Cottage Tea Rooms",
    "wof:placetype":"venue"
},
  "geometry": {"coordinates":[-2.2537899017,55.1451797485],"type":"Point"}
}