{
  "type": "Feature",
  "properties": {
    "iso:country":"GB",
    "sg:address":"School Lane, Mistley",
    "sg:city":"Manningtree",
    "sg:classifiers":[
        {
            "category":"Building & Trades",
            "subcategory":"Construction",
            "type":"Services"
        }
    ],
    "sg:postcode":"CO11 1HW",
    "sg:province":"Essex",
    "sg:tags":[
        "builder"
    ],
    "wof:name":"Rose Builders Ltd.",
    "wof:placetype":"venue"
},
  "geometry": {"coordinates":[1.069968,51.967518],"type":"Point"}
}