{
  "type": "Feature",
  "properties": {
    "iso:country":"GB",
    "sg:address":"42 Sheep Street",
    "sg:city":"Shipston-on-stour",
    "sg:classifiers":[
        {
            "category":"Health Services",
            "subcategory":"Optometrist",
            "type":"Services"
        }
    ],
    "sg:phone":"+44 1608 661649",
    "sg:postcode":"CV36 4AE",
    "sg:province":"Warwickshire",
    "sg:tags":[
        "optician"
    ],
    "wof:name":"Walford & Round Opticians",
    "wof:placetype":"venue"
},
  "geometry": {"coordinates":[-1.6265100241,52.0631370544],"type":"Point"}
}