{
  "type": "Feature",
  "properties": {
    "addr:full":"Unit 25 Pitcliffe Way, Pitcliffe Bradford West Yorkshire BD5 7SG",
    "addr:housenumber":"unit 25",
    "addr:postcode":"bd5 7sg",
    "addr:street":"Pitcliffe Way Pitcliffe Bradford West",
    "iso:country":"GB",
    "sg:address":"Unit 25 Pitcliffe Way, Pitcliffe",
    "sg:city":"Bradford",
    "sg:classifiers":[
        {
            "category":"Home & Garden",
            "subcategory":"Home Furnishings",
            "type":"Retail Goods"
        }
    ],
    "sg:postcode":"BD5 7SG",
    "sg:province":"West Yorkshire",
    "sg:tags":[
        "awning",
        "canopy",
        "blinds"
    ],
    "wof:name":"Shackleton Mortimer & Sons Ltd.",
    "wof:placetype":"venue"
},
  "geometry": {"coordinates":[-1.750079,53.784416],"type":"Point"}
}