{
  "type": "Feature",
  "properties": {
    "iso:country":"GB",
    "sg:address":"Rear Of Wenicks, 30a Westfield Road",
    "sg:city":"Hinckley",
    "sg:classifiers":[
        {
            "category":"Professional",
            "subcategory":"Engineering",
            "type":"Services"
        }
    ],
    "sg:phone":"+44 1455 230622",
    "sg:postcode":"LE10 0QW",
    "sg:province":"Leicestershire",
    "sg:tags":[
        "precision",
        "engineer"
    ],
    "wof:name":"Newmax Precision Engineering Ltd",
    "wof:placetype":"venue"
},
  "geometry": {"coordinates":[-1.378771,52.535007],"type":"Point"}
}