{
  "type": "Feature",
  "properties": {
    "addr:full":"229 Lythalls Lane Coventry Warwickshire CV6 6FW",
    "addr:housenumber":"229",
    "addr:postcode":"cv6 6fw",
    "addr:street":"Lythalls Lane",
    "iso:country":"GB",
    "sg:address":"229 Lythalls Lane",
    "sg:city":"Coventry",
    "sg:classifiers":[
        {
            "category":"Retail",
            "subcategory":"Driving School",
            "type":"Services"
        }
    ],
    "sg:phone":"+44 24 7668 1887",
    "sg:postcode":"CV6 6FW",
    "sg:province":"Warwickshire",
    "wof:name":"Peter Salisbury",
    "wof:placetype":"venue"
},
  "geometry": {"coordinates":[-1.500424,52.441536],"type":"Point"}
}