{
  "type": "Feature",
  "properties": {
    "addr:full":"De Wyche Road, Wychbold Droitwich Worcestershire WR9 7PN",
    "addr:postcode":"wr9 7pn",
    "addr:street":"De Wyche Road;Droitwich",
    "iso:country":"GB",
    "sg:address":"De Wyche Road, Wychbold",
    "sg:city":"Droitwich",
    "sg:classifiers":[
        {
            "category":"Health Services",
            "subcategory":"Doctor",
            "type":"Services"
        }
    ],
    "sg:phone":"+44 1527 861638",
    "sg:postcode":"WR9 7PN",
    "sg:province":"Worcestershire",
    "sg:tags":[
        "practitioners"
    ],
    "wof:name":"The Surgery",
    "wof:placetype":"venue"
},
  "geometry": {"coordinates":[-2.1124169827,52.2907524109],"type":"Point"}
}