{
  "type": "Feature",
  "properties": {
    "addr:full":"Weavers Cottage, Drury Lane, Litcham King's Lynn Norfolk PE32 2YE",
    "addr:postcode":"pe32 2ye",
    "addr:street":"Drury Lane;Lynn",
    "iso:country":"GB",
    "sg:address":"Weavers Cottage, Drury Lane, Litcham",
    "sg:city":"King's Lynn",
    "sg:classifiers":[
        {
            "category":"Real Estate",
            "subcategory":"Architect",
            "type":"Services"
        }
    ],
    "sg:postcode":"PE32 2YE",
    "sg:province":"Norfolk",
    "wof:name":"K L Bradley",
    "wof:placetype":"venue"
},
  "geometry": {"coordinates":[0.7943,52.723961],"type":"Point"}
}