{
  "type": "Feature",
  "properties": {
    "addr:full":"Caladonian House, 6 Ninian Road, Aberdeen Airport Aberdeen Aberdeen City AB21 0PD",
    "addr:housenumber":"6",
    "addr:postcode":"ab21 0pd",
    "addr:street":"Ninian Road",
    "iso:country":"GB",
    "sg:address":"Caladonian House, 6 Ninian Road, Aberdeen Airport",
    "sg:city":"Aberdeen",
    "sg:classifiers":[
        {
            "category":"Professional",
            "subcategory":"Engineering",
            "type":"Services"
        }
    ],
    "sg:phone":"+44 1224 722274",
    "sg:postcode":"AB21 0PD",
    "sg:province":"Aberdeen City",
    "sg:tags":[
        "electronic",
        "engineer"
    ],
    "wof:name":"Caledonian Airborne Systems Ltd.",
    "wof:placetype":"venue"
},
  "geometry": {"coordinates":[-2.208889,57.20393],"type":"Point"}
}