{
  "type": "Feature",
  "properties": {
    "addr:full":"9 Sandy Crescent Hinckley Leicestershire LE10 0TG",
    "addr:housenumber":"9",
    "addr:postcode":"le10 0tg",
    "addr:street":"Sandy Crescent",
    "iso:country":"GB",
    "sg:address":"9 Sandy Crescent",
    "sg:city":"Hinckley",
    "sg:classifiers":[
        {
            "category":"Arts & Performance",
            "subcategory":"Theater",
            "type":"Entertainment"
        }
    ],
    "sg:phone":"+44 1455 440769",
    "sg:postcode":"LE10 0TG",
    "sg:province":"Leicestershire",
    "sg:tags":[
        "theatrical",
        "agency"
    ],
    "wof:name":"A Shires",
    "wof:placetype":"venue"
},
  "geometry": {"coordinates":[-1.3822590113,52.545135498],"type":"Point"}
}