{
  "type": "Feature",
  "properties": {
    "iso:country":"GB",
    "sg:address":"124a Thorntree Rd",
    "sg:city":"Stockton On Tees",
    "sg:classifiers":[
        {
            "category":"Personal",
            "type":"Services"
        }
    ],
    "sg:phone":"+44 1642 640522",
    "sg:postcode":"TS17 8LX",
    "sg:province":"Durham",
    "sg:tags":[
        "dressmaker"
    ],
    "wof:name":"Quick Stitch",
    "wof:placetype":"venue"
},
  "geometry": {"coordinates":[-1.298035,54.545044],"type":"Point"}
}