{
  "type": "Feature",
  "properties": {
    "iso:country":"GB",
    "sg:address":"Coleby Airfield",
    "sg:city":"Lincoln",
    "sg:classifiers":[
        {
            "category":"Professional",
            "subcategory":"Employment Agencies",
            "type":"Services"
        }
    ],
    "sg:phone":"+44 1522 810741",
    "sg:postcode":"LN5 0LR",
    "sg:province":"Lincolnshire",
    "sg:tags":[
        "agricultural",
        "advice"
    ],
    "wof:name":"Belvoir Horsefeeds",
    "wof:placetype":"venue"
},
  "geometry": {"coordinates":[-0.537589,53.133717],"type":"Point"}
}