{
  "type": "Feature",
  "properties": {
    "iso:country":"GB",
    "sg:address":"27 Flixton Road, Urmston",
    "sg:city":"Manchester",
    "sg:classifiers":[
        {
            "category":"Travel",
            "subcategory":"Travel Agent",
            "type":"Entertainment"
        }
    ],
    "sg:phone":"+44 161 746 8484",
    "sg:postcode":"M41 5EL",
    "sg:province":"Cheshire",
    "sg:tags":[
        "agency",
        "activity"
    ],
    "wof:name":"Miss Ellie's World Travel Ltd",
    "wof:placetype":"venue"
},
  "geometry": {"coordinates":[-2.3559920788,53.4482536316],"type":"Point"}
}