{
  "type": "Feature",
  "properties": {
    "iso:country":"GB",
    "sg:address":"1 Green Lane, Overton",
    "sg:city":"Wakefield",
    "sg:classifiers":[
        {
            "category":"Bars & Pubs",
            "type":"Food & Drink"
        }
    ],
    "sg:phone":"+44 1924 272114",
    "sg:postcode":"WF4 4RE",
    "sg:province":"West Yorkshire",
    "sg:tags":[
        "pubs",
        "inn"
    ],
    "wof:name":"Glen & Christine Evans",
    "wof:placetype":"venue"
},
  "geometry": {"coordinates":[-1.578407,53.642033],"type":"Point"}
}