{
  "type": "Feature",
  "properties": {
    "iso:country":"GB",
    "sg:address":"2 Russet Close, Bredon",
    "sg:city":"Tewkesbury",
    "sg:classifiers":[
        {
            "category":"Professional",
            "subcategory":"Art Services",
            "type":"Services"
        }
    ],
    "sg:phone":"+44 1684 772026",
    "sg:postcode":"GL20 7QE",
    "sg:province":"Gloucestershire",
    "sg:tags":[
        "photographer"
    ],
    "wof:name":"Ryan Vincent Bowler",
    "wof:placetype":"venue"
},
  "geometry": {"coordinates":[-2.103866,52.029129],"type":"Point"}
}