{
  "type": "Feature",
  "properties": {
    "addr:full":"104 Holburn St Aberdeen Aberdeen City AB10 6BY",
    "addr:housenumber":"104",
    "addr:postcode":"ab10 6by",
    "addr:street":"Holburn St",
    "iso:country":"GB",
    "sg:address":"104 Holburn St",
    "sg:city":"Aberdeen",
    "sg:classifiers":[
        {
            "category":"Shopping",
            "subcategory":"Department Store",
            "type":"Retail Goods"
        }
    ],
    "sg:postcode":"AB10 6BY",
    "sg:province":"Aberdeen City",
    "wof:name":"Flavill,K,",
    "wof:placetype":"venue"
},
  "geometry": {"coordinates":[-2.113654,57.140354],"type":"Point"}
}