{
  "type": "Feature",
  "properties": {
    "addr:full":"19 Queen Street Glasgow Glasgow City G1 3ED",
    "addr:housenumber":"19",
    "addr:postcode":"g1 3ed",
    "addr:street":"Queen Street",
    "iso:country":"GB",
    "sg:address":"19 Queen Street",
    "sg:city":"Glasgow",
    "sg:classifiers":[
        {
            "category":"Home & Garden",
            "subcategory":"Carpets & Floor Coverings",
            "type":"Retail Goods"
        }
    ],
    "sg:postcode":"G1 3ED",
    "sg:province":"Glasgow City",
    "sg:tags":[
        "carpets",
        "rug",
        "matting"
    ],
    "wof:name":"Carpet Discount House",
    "wof:placetype":"venue"
},
  "geometry": {"coordinates":[-4.252749,55.858013],"type":"Point"}
}