{
  "type": "Feature",
  "properties": {
    "addr:full":"Unit 12 Bemrose Indust Estate, Hanson Road Liverpool Merseyside L9 7BG",
    "addr:housenumber":"unit 12",
    "addr:postcode":"l9 7bg",
    "addr:street":"Bemrose Indust Estate Hanson Road",
    "iso:country":"GB",
    "sg:address":"Unit 12 Bemrose Indust Estate, Hanson Road",
    "sg:city":"Liverpool",
    "sg:classifiers":[
        {
            "category":"Home & Garden",
            "subcategory":"Hardware",
            "type":"Retail Goods"
        }
    ],
    "sg:phone":"+44 151 525 2232",
    "sg:postcode":"L9 7BG",
    "sg:province":"Merseyside",
    "sg:tags":[
        "product",
        "wire",
        "electrical"
    ],
    "wof:name":"Safe & Secure",
    "wof:placetype":"venue"
},
  "geometry": {"coordinates":[-2.94057,53.454208],"type":"Point"}
}