{
  "type": "Feature",
  "properties": {
    "iso:country":"GB",
    "sg:address":"677 Green Lane",
    "sg:city":"London",
    "sg:classifiers":[
        {
            "category":"Bars & Pubs",
            "type":"Food & Drink"
        }
    ],
    "sg:phone":"+44 20 8340 2921",
    "sg:postcode":"N8 0QY",
    "sg:province":"Greater London",
    "sg:tags":[
        "pubs",
        "inn"
    ],
    "wof:name":"Grandred Ltd.",
    "wof:placetype":"venue"
},
  "geometry": {"coordinates":[-0.10092,51.586472],"type":"Point"}
}