{
  "type": "Feature",
  "properties": {
    "iso:country":"GB",
    "sg:address":"46 Main Street",
    "sg:city":"Cockermouth",
    "sg:classifiers":[
        {
            "category":"Ice Cream",
            "type":"Food & Drink"
        }
    ],
    "sg:phone":"+44 1900 822377",
    "sg:postcode":"CA13 9LU",
    "sg:province":"Cumbria",
    "sg:tags":[
        "shop",
        "mobile",
        "parlour"
    ],
    "wof:name":"Hartleys Ice Cream",
    "wof:placetype":"venue"
},
  "geometry": {"coordinates":[-3.364866972,54.6638450623],"type":"Point"}
}