{
  "type": "Feature",
  "properties": {
    "addr:full":"Lansdowne Rd, Chadderton Oldham Lancashire OL9 9EF",
    "addr:postcode":"ol9 9ef",
    "addr:street":"Lansdowne Rd",
    "iso:country":"GB",
    "sg:address":"Lansdowne Rd, Chadderton",
    "sg:city":"Oldham",
    "sg:classifiers":[
        {
            "category":"Freight",
            "type":"Transportation"
        }
    ],
    "sg:phone":"+44 161 626 1141",
    "sg:postcode":"OL9 9EF",
    "sg:province":"Lancashire",
    "sg:tags":[
        "haulage",
        "road"
    ],
    "wof:name":"L T S Ltd",
    "wof:placetype":"venue"
},
  "geometry": {"coordinates":[-2.1405739784,53.5449447632],"type":"Point"}
}