{
  "type": "Feature",
  "properties": {
    "addr:full":"2 Station Road, Clayton Bradford West Yorkshire BD14 6JA",
    "addr:housenumber":"2",
    "addr:postcode":"bd14 6ja",
    "addr:street":"Station Road",
    "iso:country":"GB",
    "sg:address":"2 Station Road, Clayton",
    "sg:city":"Bradford",
    "sg:classifiers":[
        {
            "category":"Fast Food",
            "type":"Food & Drink"
        }
    ],
    "sg:phone":"+44 1274 818186",
    "sg:postcode":"BD14 6JA",
    "sg:province":"West Yorkshire",
    "sg:tags":[
        "away",
        "meal",
        "outlet",
        "take"
    ],
    "wof:name":"Casa Pizza",
    "wof:placetype":"venue"
},
  "geometry": {"coordinates":[-1.8169740438,53.7800827026],"type":"Point"}
}