{
  "type": "Feature",
  "properties": {
    "addr:full":"133 North End Croydon Surrey CR0 1TL",
    "addr:housenumber":"133",
    "addr:postcode":"cr0 1tl",
    "addr:street":"North End",
    "iso:country":"GB",
    "sg:address":"133 North End",
    "sg:city":"Croydon",
    "sg:classifiers":[
        {
            "category":"Shopping",
            "subcategory":"Mobile Phones",
            "type":"Retail Goods"
        }
    ],
    "sg:phone":"+44 20 8686 3377",
    "sg:postcode":"CR0 1TL",
    "sg:province":"Surrey",
    "wof:name":"The Carphone Warehouse Ltd.",
    "wof:placetype":"venue"
},
  "geometry": {"coordinates":[-0.1022389978,51.3770141602],"type":"Point"}
}