{
  "type": "Feature",
  "properties": {
    "addr:full":"2/4 Southampton Road Ringwood Dorset BH24 1HY",
    "addr:housenumber":"2 / 4",
    "addr:postcode":"bh24 1hy",
    "addr:street":"Southampton Road",
    "iso:country":"GB",
    "sg:address":"2/4 Southampton Road",
    "sg:city":"Ringwood",
    "sg:classifiers":[
        {
            "category":"Travel",
            "subcategory":"Hotels & Motels",
            "type":"Entertainment"
        }
    ],
    "sg:phone":"+44 1425 472708",
    "sg:postcode":"BH24 1HY",
    "sg:province":"Dorset",
    "wof:name":"Inntown Properties Ltd.",
    "wof:placetype":"venue"
},
  "geometry": {"coordinates":[-1.791221,50.846226],"type":"Point"}
}