{
  "type": "Feature",
  "properties": {
    "addr:full":"3 Blackwood Terrace Johnstone Renfrewshire PA5 0AX",
    "addr:housenumber":"3",
    "addr:postcode":"pa5 0ax",
    "addr:street":"Blackwood Terrace",
    "iso:country":"GB",
    "sg:address":"3 Blackwood Terrace",
    "sg:city":"Johnstone",
    "sg:classifiers":[
        {
            "category":"Building & Trades",
            "subcategory":"Pest Control",
            "type":"Services"
        }
    ],
    "sg:phone":"+44 1505 383737",
    "sg:postcode":"PA5 0AX",
    "sg:province":"Renfrewshire",
    "sg:tags":[
        "vermin"
    ],
    "wof:name":"Pestguard Services",
    "wof:placetype":"venue"
},
  "geometry": {"coordinates":[-4.5234498978,55.8249893188],"type":"Point"}
}