{
  "type": "Feature",
  "properties": {
    "iso:country":"GB",
    "sg:address":"Old Dominion House, 5 Gravel Hill",
    "sg:city":"Henley-on-thames",
    "sg:classifiers":[
        {
            "category":"Professional",
            "subcategory":"Art Services",
            "type":"Services"
        }
    ],
    "sg:phone":"+44 1491 411688",
    "sg:postcode":"RG9 2EG",
    "sg:province":"Berkshire",
    "sg:tags":[
        "consultant",
        "design"
    ],
    "wof:name":"Photobition Lea Design Ltd.",
    "wof:placetype":"venue"
},
  "geometry": {"coordinates":[-0.907882,51.536774],"type":"Point"}
}