{
  "type": "Feature",
  "properties": {
    "addr:full":"11 Brougham Street Greenock Inverclyde PA16 8AB",
    "addr:housenumber":"11",
    "addr:postcode":"pa16 8ab",
    "addr:street":"Brougham Street Greenock",
    "iso:country":"GB",
    "sg:address":"11 Brougham Street",
    "sg:city":"Greenock",
    "sg:classifiers":[
        {
            "category":"Recreation",
            "type":"Entertainment"
        }
    ],
    "sg:phone":"+44 1475 786225",
    "sg:postcode":"PA16 8AB",
    "sg:province":"Inverclyde",
    "sg:tags":[
        "snooker",
        "billiards",
        "pool"
    ],
    "wof:name":"Riley Snooker Club",
    "wof:placetype":"venue"
},
  "geometry": {"coordinates":[-4.766768,55.954067],"type":"Point"}
}