{
  "type": "Feature",
  "properties": {
    "addr:full":"11 Garmston Rd Shrewsbury Shropshire SY2 6HE",
    "addr:housenumber":"11",
    "addr:postcode":"sy2 6he",
    "addr:street":"Garmston Rd",
    "iso:country":"GB",
    "sg:address":"11 Garmston Rd",
    "sg:city":"Shrewsbury",
    "sg:classifiers":[
        {
            "category":"Shopping",
            "subcategory":"Party Supplies",
            "type":"Retail Goods"
        }
    ],
    "sg:phone":"+44 1743 231824",
    "sg:postcode":"SY2 6HE",
    "sg:province":"Shropshire",
    "sg:tags":[
        "inflatables",
        "bouncy",
        "castle"
    ],
    "wof:name":"Bounce Alot Bouncy Castles",
    "wof:placetype":"venue"
},
  "geometry": {"coordinates":[-2.7313389778,52.690372467],"type":"Point"}
}