{
  "type": "Feature",
  "properties": {
    "iso:country":"GB",
    "sg:address":"40 The Leys",
    "sg:city":"Northampton",
    "sg:classifiers":[
        {
            "category":"Building & Trades",
            "subcategory":"Construction",
            "type":"Services"
        }
    ],
    "sg:phone":"+44 1858 575388",
    "sg:postcode":"NN6 6HS",
    "sg:province":"Northamptonshire",
    "sg:tags":[
        "builder"
    ],
    "wof:name":"Tanser Bros Construction",
    "wof:placetype":"venue"
},
  "geometry": {"coordinates":[-1.059095,52.414806],"type":"Point"}
}