{
  "type": "Feature",
  "properties": {
    "iso:country":"GB",
    "sg:address":"15 Acorn Close",
    "sg:city":"Grantham",
    "sg:classifiers":[
        {
            "category":"Shopping",
            "subcategory":"News",
            "type":"Retail Goods"
        }
    ],
    "sg:postcode":"NG31 9JN",
    "sg:province":"Lincolnshire",
    "sg:tags":[
        "newsagent"
    ],
    "wof:name":"Goodley's (Newsagents) Limited",
    "wof:placetype":"venue"
},
  "geometry": {"coordinates":[-0.627974,52.925056],"type":"Point"}
}