{
  "type": "Feature",
  "properties": {
    "iso:country":"GB",
    "sg:address":"114 Market Street, Atherton",
    "sg:city":"Manchester",
    "sg:classifiers":[
        {
            "category":"Food & Beverages",
            "subcategory":"Fruits & Vegetables",
            "type":"Retail Goods"
        }
    ],
    "sg:postcode":"M46 0DP",
    "sg:province":"Greater Manchester",
    "sg:tags":[
        "greengrocer"
    ],
    "wof:name":"Fruit Market",
    "wof:placetype":"venue"
},
  "geometry": {"coordinates":[-2.495338,53.523605],"type":"Point"}
}