{
  "type": "Feature",
  "properties": {
    "addr:full":"4 Rempstone Road Swanage Dorset BH19 1DP",
    "addr:housenumber":"4",
    "addr:postcode":"bh19 1dp",
    "addr:street":"Rempstone Road",
    "iso:country":"GB",
    "sg:address":"4 Rempstone Road",
    "sg:city":"Swanage",
    "sg:classifiers":[
        {
            "category":"Professional",
            "subcategory":"Lawyer & Legal Services",
            "type":"Services"
        }
    ],
    "sg:phone":"+44 1929 423301",
    "sg:postcode":"BH19 1DP",
    "sg:province":"Dorset",
    "sg:tags":[
        "solicitor"
    ],
    "wof:name":"Humphries Kirk",
    "wof:placetype":"venue"
},
  "geometry": {"coordinates":[-1.9594620466,50.6106491089],"type":"Point"}
}