{
  "type": "Feature",
  "properties": {
    "iso:country":"GB",
    "sg:address":"Nicol St",
    "sg:city":"Kirkcaldy",
    "sg:classifiers":[
        {
            "category":"Retail",
            "subcategory":"Auto Rental",
            "type":"Services"
        }
    ],
    "sg:phone":"+44 1592 269955",
    "sg:postcode":"KY1 1PF",
    "sg:province":"Fife",
    "sg:tags":[
        "car"
    ],
    "wof:name":"Enterprise Rent A Car",
    "wof:placetype":"venue"
},
  "geometry": {"coordinates":[-3.1692988873,56.1078262329],"type":"Point"}
}