{
  "type": "Feature",
  "properties": {
    "addr:full":"8 Mercia Road Newark Nottinghamshire NG24 4NA",
    "addr:housenumber":"8",
    "addr:postcode":"ng24 4na",
    "addr:street":"Mercia Road",
    "iso:country":"GB",
    "sg:address":"8 Mercia Road",
    "sg:city":"Newark",
    "sg:classifiers":[
        {
            "category":"Military Area",
            "subcategory":"Air Force Base",
            "type":"Public Place"
        }
    ],
    "sg:phone":"+44 1636 610066",
    "sg:postcode":"NG24 4NA",
    "sg:province":"Nottinghamshire",
    "sg:tags":[
        "taxi",
        "hire",
        "private"
    ],
    "wof:name":"A C Taxis",
    "wof:placetype":"venue"
},
  "geometry": {"coordinates":[-0.8142079711,53.0599861145],"type":"Point"}
}