{
  "type": "Feature",
  "properties": {
    "addr:full":"2 The Parade, Pitsea Basildon Essex SS13 3BA",
    "addr:housenumber":"2",
    "addr:postcode":"ss13 3ba",
    "addr:street":"The Parade",
    "iso:country":"GB",
    "sg:address":"2 The Parade, Pitsea",
    "sg:city":"Basildon",
    "sg:classifiers":[
        {
            "category":"Home & Garden",
            "subcategory":"Household Appliances",
            "type":"Retail Goods"
        }
    ],
    "sg:phone":"+44 1268 551516",
    "sg:postcode":"SS13 3BA",
    "sg:province":"Essex",
    "sg:tags":[
        "electrical"
    ],
    "wof:name":"Pitsea Appliance Centre",
    "wof:placetype":"venue"
},
  "geometry": {"coordinates":[0.5033299923,51.5647583008],"type":"Point"}
}