{
  "type": "Feature",
  "properties": {
    "addr:full":"11 Colne Road Tonbridge Kent TN10 3JN",
    "addr:housenumber":"11",
    "addr:postcode":"tn10 3jn",
    "addr:street":"Colne Road",
    "iso:country":"GB",
    "sg:address":"11 Colne Road",
    "sg:city":"Tonbridge",
    "sg:classifiers":[
        {
            "category":"Personal",
            "type":"Services"
        }
    ],
    "sg:phone":"+44 1732 368897",
    "sg:postcode":"TN10 3JN",
    "sg:province":"Kent",
    "sg:tags":[
        "consultant",
        "fitness"
    ],
    "wof:name":"Francis Morrison",
    "wof:placetype":"venue"
},
  "geometry": {"coordinates":[0.273786,51.211502],"type":"Point"}
}