{
  "type": "Feature",
  "properties": {
    "addr:full":"Overross Industrial Estate, Netherton Road Ross-on-wye Gloucestershire HR9 7QQ",
    "addr:postcode":"hr9 7qq",
    "addr:street":"Estate Netherton Road",
    "iso:country":"GB",
    "sg:address":"Overross Industrial Estate, Netherton Road",
    "sg:city":"Ross-on-wye",
    "sg:classifiers":[
        {
            "category":"Professional",
            "subcategory":"Business Services",
            "type":"Services"
        }
    ],
    "sg:phone":"+44 1989 563020",
    "sg:postcode":"HR9 7QQ",
    "sg:province":"Gloucestershire",
    "sg:tags":[
        "distribution"
    ],
    "wof:name":"Wincanton Logistics",
    "wof:placetype":"venue"
},
  "geometry": {"coordinates":[-2.581733,51.916481],"type":"Point"}
}