{
  "type": "Feature",
  "properties": {
    "addr:full":"Unit 19 Glasgow Glasgow City G20 9BQ",
    "addr:housenumber":"unit 19",
    "addr:postcode":"g20 9bq",
    "iso:country":"GB",
    "sg:address":"Unit 19",
    "sg:city":"Glasgow",
    "sg:classifiers":[
        {
            "category":"Shopping",
            "subcategory":"Books",
            "type":"Retail Goods"
        }
    ],
    "sg:phone":"+44 141 945 5006",
    "sg:postcode":"G20 9BQ",
    "sg:province":"Glasgow City",
    "sg:tags":[
        "bookseller",
        "retailer"
    ],
    "wof:name":"KELVIN BOOKS LTD",
    "wof:placetype":"venue"
},
  "geometry": {"coordinates":[-4.2844500542,55.8880386353],"type":"Point"}
}