{
  "type": "Feature",
  "properties": {
    "addr:full":"Bolton St Brixham Devon TQ5 9DL",
    "addr:postcode":"tq5 9dl",
    "addr:street":"Bolton St",
    "iso:country":"GB",
    "sg:address":"Bolton St",
    "sg:city":"Brixham",
    "sg:classifiers":[
        {
            "category":"Social Services",
            "subcategory":"Adult Care",
            "type":"Services"
        }
    ],
    "sg:phone":"+44 1803 851111",
    "sg:postcode":"TQ5 9DL",
    "sg:province":"Devon",
    "sg:tags":[
        "housing",
        "sheltered"
    ],
    "wof:name":"Watermill Churchill Court",
    "wof:placetype":"venue"
},
  "geometry": {"coordinates":[-3.5145840645,50.3909339905],"type":"Point"}
}