{
  "type": "Feature",
  "properties": {
    "addr:full":"Sheridan Street, Sinfin Derby Derbyshire DE24 9HG",
    "addr:postcode":"de24 9hg",
    "addr:street":"Sheridan Street",
    "iso:country":"GB",
    "sg:address":"Sheridan Street, Sinfin",
    "sg:city":"Derby",
    "sg:classifiers":[
        {
            "category":"Professional",
            "subcategory":"Lawyer & Legal Services",
            "type":"Services"
        }
    ],
    "sg:phone":"+44 1332 271083",
    "sg:postcode":"DE24 9HG",
    "sg:province":"Derbyshire",
    "sg:tags":[
        "advice",
        "counselling"
    ],
    "wof:name":"S U P O R T Ltd.",
    "wof:placetype":"venue"
},
  "geometry": {"coordinates":[-1.486909,52.88512],"type":"Point"}
}