{
  "type": "Feature",
  "properties": {
    "iso:country":"GB",
    "sg:address":"5 Abbey Road",
    "sg:city":"Llangollen",
    "sg:classifiers":[
        {
            "category":"Shopping",
            "subcategory":"News",
            "type":"Retail Goods"
        }
    ],
    "sg:phone":"+44 1978 860596",
    "sg:postcode":"LL20 8SN",
    "sg:province":"Denbighshire",
    "sg:tags":[
        "newsagent"
    ],
    "wof:name":"Riverside Newsagents",
    "wof:placetype":"venue"
},
  "geometry": {"coordinates":[-3.175249,52.972416],"type":"Point"}
}