{
  "type": "Feature",
  "properties": {
    "iso:country":"GB",
    "sg:address":"3 Andover Road, Ludgershall",
    "sg:city":"Andover",
    "sg:classifiers":[
        {
            "category":"Professional",
            "type":"Services"
        }
    ],
    "sg:postcode":"SP11 9LU",
    "sg:province":"Hampshire",
    "sg:tags":[
        "interior",
        "furnishers",
        "designer"
    ],
    "wof:name":"Berkshire Furnishings",
    "wof:placetype":"venue"
},
  "geometry": {"coordinates":[-1.6216210127,51.2555770874],"type":"Point"}
}