{
  "type": "Feature",
  "properties": {
    "addr:full":"168 Ferry Lane, Woodmansey Beverley East Riding of Yorkshire HU17 0SE",
    "addr:housenumber":"168",
    "addr:postcode":"hu17 0se",
    "addr:street":"Ferry Lane",
    "iso:country":"GB",
    "sg:address":"168 Ferry Lane, Woodmansey",
    "sg:city":"Beverley",
    "sg:classifiers":[
        {
            "category":"Manufacturing",
            "subcategory":"Signs",
            "type":"Manufacturing & Wholesale Goods"
        },
        {
            "category":"Sports & Exercise",
            "subcategory":"Swimming Pool",
            "type":"Entertainment"
        }
    ],
    "sg:phone":"+44 1482 882380",
    "sg:postcode":"HU17 0SE",
    "sg:province":"East Riding of Yorkshire",
    "sg:tags":[
        "diver",
        "nameplate"
    ],
    "wof:name":"1ST Choice Graphics",
    "wof:placetype":"venue"
},
  "geometry": {"coordinates":[-0.370279,53.816311],"type":"Point"}
}