{
  "type": "Feature",
  "properties": {
    "iso:country":"GB",
    "sg:address":"630 Woodbridge Road",
    "sg:city":"Ipswich",
    "sg:classifiers":[
        {
            "category":"Manufacturing",
            "subcategory":"Furniture",
            "type":"Manufacturing & Wholesale Goods"
        }
    ],
    "sg:postcode":"IP4 4PG",
    "sg:province":"Suffolk",
    "sg:tags":[
        "polishing",
        "french"
    ],
    "wof:name":"Pheonix French Polishers",
    "wof:placetype":"venue"
},
  "geometry": {"coordinates":[1.191516,52.060143],"type":"Point"}
}