{
  "type": "Feature",
  "properties": {
    "addr:full":"22 Cadzow Place Edinburgh City of Edinburgh EH7 5SN",
    "addr:housenumber":"22",
    "addr:postcode":"eh7 5sn",
    "addr:street":"Cadzow Place Edinburgh",
    "iso:country":"GB",
    "sg:address":"22 Cadzow Place",
    "sg:city":"Edinburgh",
    "sg:classifiers":[
        {
            "category":"Building & Trades",
            "subcategory":"Plumbing",
            "type":"Services"
        }
    ],
    "sg:postcode":"EH7 5SN",
    "sg:province":"City of Edinburgh",
    "sg:tags":[
        "heating"
    ],
    "wof:name":"Y B Contracts",
    "wof:placetype":"venue"
},
  "geometry": {"coordinates":[-3.167932,55.957298],"type":"Point"}
}