{
  "type": "Feature",
  "properties": {
    "iso:country":"GB",
    "sg:address":"Bygot Wood, Bygot Rd, Cherry Burton",
    "sg:city":"Beverley",
    "sg:classifiers":[
        {
            "category":"Arena",
            "subcategory":"Sports Club",
            "type":"Entertainment"
        }
    ],
    "sg:postcode":"HU17 7RB",
    "sg:province":"East Riding of Yorkshire",
    "wof:name":"East Yorkshire Gun Club",
    "wof:placetype":"venue"
},
  "geometry": {"coordinates":[-0.498155,53.866222],"type":"Point"}
}