{
  "type": "Feature",
  "properties": {
    "iso:country":"GB",
    "sg:address":"Sanstone House",
    "sg:city":"Walsall",
    "sg:classifiers":[
        {
            "category":"Social Services",
            "subcategory":"Retirement Home",
            "type":"Services"
        },
        {
            "category":"Government",
            "subcategory":"Office",
            "type":"Public Place"
        }
    ],
    "sg:phone":"+44 1922 710572",
    "sg:postcode":"WS3 3SJ",
    "sg:province":"Staffordshire",
    "sg:tags":[
        "residential",
        "local",
        "care"
    ],
    "wof:name":"Sanstone House Resource Centre",
    "wof:placetype":"venue"
},
  "geometry": {"coordinates":[-1.998289,52.622631],"type":"Point"}
}