{
  "type": "Feature",
  "properties": {
    "iso:country":"GB",
    "sg:address":"Unit 5 White Hart Arcade",
    "sg:city":"Launceston",
    "sg:classifiers":[
        {
            "category":"Travel",
            "subcategory":"Travel Agent",
            "type":"Entertainment"
        }
    ],
    "sg:phone":"+44 1566 774484",
    "sg:postcode":"PL15 8AA",
    "sg:province":"Cornwall",
    "sg:tags":[
        "agency",
        "activity"
    ],
    "wof:name":"H L C Launceston Travel",
    "wof:placetype":"venue"
},
  "geometry": {"coordinates":[-4.363344,50.636707],"type":"Point"}
}