{
  "type": "Feature",
  "properties": {
    "addr:full":"1 Main St Doune Stirling FK16 6BJ",
    "addr:housenumber":"1",
    "addr:postcode":"fk16 6bj",
    "addr:street":"Main St",
    "iso:country":"GB",
    "sg:address":"1 Main St",
    "sg:city":"Doune",
    "sg:classifiers":[
        {
            "category":"Food & Beverages",
            "subcategory":"Meat & Fish",
            "type":"Retail Goods"
        }
    ],
    "sg:phone":"+44 1786 841458",
    "sg:postcode":"FK16 6BJ",
    "sg:province":"Stirling",
    "sg:tags":[
        "butcher"
    ],
    "wof:name":"Gray Butchers",
    "wof:placetype":"venue"
},
  "geometry": {"coordinates":[-4.052302,56.189754],"type":"Point"}
}