{
  "type": "Feature",
  "properties": {
    "iso:country":"GB",
    "sg:address":"23 The Galleria, Comet Way",
    "sg:city":"Hatfield",
    "sg:classifiers":[
        {
            "category":"Shopping",
            "subcategory":"Comic Books",
            "type":"Retail Goods"
        }
    ],
    "sg:phone":"+44 1707 270121",
    "sg:postcode":"AL10 0XS",
    "sg:province":"Hertfordshire",
    "sg:tags":[
        "jeweller"
    ],
    "wof:name":"Goldsmiths Plc",
    "wof:placetype":"venue"
},
  "geometry": {"coordinates":[-0.2339649945,51.7610282898],"type":"Point"}
}