{
  "type": "Feature",
  "properties": {
    "addr:full":"6 Exford Avenue Southampton Hampshire SO18 5DJ",
    "addr:housenumber":"6",
    "addr:postcode":"so18 5dj",
    "addr:street":"Exford Avenue",
    "iso:country":"GB",
    "sg:address":"6 Exford Avenue",
    "sg:city":"Southampton",
    "sg:classifiers":[
        {
            "category":"Shopping",
            "subcategory":"Pharmacy",
            "type":"Retail Goods"
        }
    ],
    "sg:phone":"+44 23 8047 2720",
    "sg:postcode":"SO18 5DJ",
    "sg:province":"Hampshire",
    "sg:tags":[
        "pharmacist",
        "chemist"
    ],
    "wof:name":"Oaklands Pharmacy",
    "wof:placetype":"venue"
},
  "geometry": {"coordinates":[-1.3429780006,50.9184913635],"type":"Point"}
}