{
  "type": "Feature",
  "properties": {
    "iso:country":"GB",
    "sg:address":"17 Edward St",
    "sg:city":"Louth",
    "sg:classifiers":[
        {
            "category":"Shopping",
            "subcategory":"Computers & Home Electronics",
            "type":"Retail Goods"
        }
    ],
    "sg:postcode":"LN11 9LA",
    "sg:province":"Lincolnshire",
    "sg:tags":[
        "aerial",
        "television",
        "radio"
    ],
    "wof:name":"Alpha Aerial Services",
    "wof:placetype":"venue"
},
  "geometry": {"coordinates":[-0.0085659996,53.3641090393],"type":"Point"}
}