{
  "type": "Feature",
  "properties": {
    "addr:full":"Bedewell Industrial Park Hebburn Tyne and Wear NE31 2XQ",
    "addr:postcode":"ne31 2xq",
    "iso:country":"GB",
    "sg:address":"Bedewell Industrial Park",
    "sg:city":"Hebburn",
    "sg:classifiers":[
        {
            "category":"Building & Trades",
            "subcategory":"Pest Control",
            "type":"Services"
        }
    ],
    "sg:phone":"+44 191 428 6873",
    "sg:postcode":"NE31 2XQ",
    "sg:province":"Tyne and Wear",
    "sg:tags":[
        "panel"
    ],
    "wof:name":"Select Control Systems Ltd.",
    "wof:placetype":"venue"
},
  "geometry": {"coordinates":[-1.4995390177,54.9726257324],"type":"Point"}
}