{
  "type": "Feature",
  "properties": {
    "addr:full":"Unit E, Blackhouse Ind Est Peterhead Aberdeenshire AB42 1BW",
    "addr:postcode":"ab42 1bw",
    "iso:country":"GB",
    "sg:address":"Unit E, Blackhouse Ind Est",
    "sg:city":"Peterhead",
    "sg:classifiers":[
        {
            "category":"Autos & Motor Vehicles",
            "subcategory":"Auto Supplies",
            "type":"Retail Goods"
        }
    ],
    "sg:phone":"+44 1779 481200",
    "sg:postcode":"AB42 1BW",
    "sg:province":"Aberdeenshire",
    "sg:tags":[
        "tyre"
    ],
    "wof:name":"CARTECH",
    "wof:placetype":"venue"
},
  "geometry": {"coordinates":[-1.7977440357,57.5146713257],"type":"Point"}
}