{
  "type": "Feature",
  "properties": {
    "addr:full":"Old Stocks, Alcester Road Wootton Wawen Solihull Warwickshire B95 6BQ",
    "addr:postcode":"b95 6bq",
    "addr:street":"Old Stocks Alcester Road",
    "iso:country":"GB",
    "sg:address":"Old Stocks, Alcester Road Wootton Wawen",
    "sg:city":"Solihull",
    "sg:classifiers":[
        {
            "category":"Professional",
            "subcategory":"Management & Consulting",
            "type":"Services"
        }
    ],
    "sg:postcode":"B95 6BQ",
    "sg:province":"Warwickshire",
    "sg:tags":[
        "consultant",
        "business"
    ],
    "wof:name":"Angelstar Consultants Ltd",
    "wof:placetype":"venue"
},
  "geometry": {"coordinates":[-1.7774089575,52.2667312622],"type":"Point"}
}