{
  "type": "Feature",
  "properties": {
    "addr:full":"Cavalry Hill Industrial Park, Weedon Northampton Buckinghamshire NN7 4PP",
    "addr:postcode":"nn7 4pp",
    "addr:street":"Hill Industrial Park",
    "iso:country":"GB",
    "sg:address":"Cavalry Hill Industrial Park, Weedon",
    "sg:city":"Northampton",
    "sg:classifiers":[
        {
            "category":"Health Services",
            "subcategory":"Nursing And Care Facility",
            "type":"Services"
        },
        {
            "category":"Shopping",
            "subcategory":"Pharmacy",
            "type":"Retail Goods"
        }
    ],
    "sg:phone":"+44 1327 342800",
    "sg:postcode":"NN7 4PP",
    "sg:province":"Buckinghamshire",
    "sg:tags":[
        "supplier",
        "pharmaceutical",
        "wholesaler",
        "pharmacist",
        "chemist"
    ],
    "wof:name":"A A H Pharmaceuticals Ltd.",
    "wof:placetype":"venue"
},
  "geometry": {"coordinates":[-1.088223,52.232647],"type":"Point"}
}