{
  "type": "Feature",
  "properties": {
    "iso:country":"GB",
    "sg:address":"Po Box 14455, 41 Stroma Way",
    "sg:city":"Glenrothes",
    "sg:classifiers":[
        {
            "category":"Professional",
            "type":"Services"
        }
    ],
    "sg:phone":"+44 1592 860222",
    "sg:postcode":"KY7 6ZG",
    "sg:province":"Fife",
    "sg:tags":[
        "entertainer"
    ],
    "wof:name":"Falcon Corporation",
    "wof:placetype":"venue"
},
  "geometry": {"coordinates":[-3.173744,56.197208],"type":"Point"}
}