{
  "type": "Feature",
  "properties": {
    "iso:country":"GB",
    "sg:address":"Holmpark Industrial Estate, Minnigaff",
    "sg:city":"Newton Stewart",
    "sg:classifiers":[
        {
            "category":"Autos & Motor Vehicles",
            "subcategory":"Auto Supplies",
            "type":"Retail Goods"
        }
    ],
    "sg:phone":"+44 1671 402148",
    "sg:postcode":"DG8 6AW",
    "sg:province":"Dumfries and Galloway",
    "sg:tags":[
        "tyre"
    ],
    "wof:name":"Tyre Services Great Britain Ltd.",
    "wof:placetype":"venue"
},
  "geometry": {"coordinates":[-4.482984,54.954784],"type":"Point"}
}