{
  "type": "Feature",
  "properties": {
    "addr:full":"1 Adelaide Sq Bedford Bedfordshire MK40 2RN",
    "addr:housenumber":"1",
    "addr:postcode":"mk40 2rn",
    "addr:street":"Adelaide Sq",
    "iso:country":"GB",
    "sg:address":"1 Adelaide Sq",
    "sg:city":"Bedford",
    "sg:classifiers":[
        {
            "category":"Health Services",
            "subcategory":"Dentist",
            "type":"Services"
        }
    ],
    "sg:phone":"+44 1234 268281",
    "sg:postcode":"MK40 2RN",
    "sg:province":"Bedfordshire",
    "wof:name":"T Rodgers",
    "wof:placetype":"venue"
},
  "geometry": {"coordinates":[-0.470742,52.139236],"type":"Point"}
}