{
  "type": "Feature",
  "properties": {
    "iso:country":"GB",
    "sg:address":"99 Brixton Hill, Brixton",
    "sg:city":"London",
    "sg:classifiers":[
        {
            "category":"Restaurant",
            "type":"Food & Drink"
        }
    ],
    "sg:postcode":"SW2 1AA",
    "sg:province":"Greater London",
    "sg:tags":[
        "indian"
    ],
    "wof:name":"Dawn of the Raj",
    "wof:placetype":"venue"
},
  "geometry": {"coordinates":[-0.11972,51.454479],"type":"Point"}
}