{
  "type": "Feature",
  "properties": {
    "iso:country":"GB",
    "sg:address":"Albury, Gorse Way, Hartley",
    "sg:city":"Longfield",
    "sg:classifiers":[
        {
            "category":"Professional",
            "subcategory":"Engineering",
            "type":"Services"
        },
        {
            "category":"Building & Trades",
            "subcategory":"Electrical",
            "type":"Services"
        }
    ],
    "sg:phone":"+44 1474 708805",
    "sg:postcode":"DA3 8AE",
    "sg:province":"Kent",
    "sg:tags":[
        "engineer",
        "electrician",
        "contractor"
    ],
    "wof:name":"Thompson Electrical Services Ltd",
    "wof:placetype":"venue"
},
  "geometry": {"coordinates":[0.3055849969,51.3831443787],"type":"Point"}
}