{
  "type": "Feature",
  "properties": {
    "addr:full":"Suite 5a, Business Centre, North Mill Bridge Foot Belper Derbyshire DE56 1YD",
    "addr:housenumber":"suite 5a business centre",
    "addr:postcode":"de56 1yd",
    "addr:street":"North Mill Bridge;Belper",
    "iso:country":"GB",
    "sg:address":"Suite 5a, Business Centre, North Mill Bridge Foot",
    "sg:city":"Belper",
    "sg:classifiers":[
        {
            "category":"Building & Trades",
            "subcategory":"Construction",
            "type":"Services"
        }
    ],
    "sg:phone":"+44 1773 827878",
    "sg:postcode":"DE56 1YD",
    "sg:province":"Derbyshire",
    "sg:tags":[
        "concrete"
    ],
    "wof:name":"MAS-cTI Ltd",
    "wof:placetype":"venue"
},
  "geometry": {"coordinates":[-1.4759819508,53.0286102295],"type":"Point"}
}