{
  "type": "Feature",
  "properties": {
    "addr:full":"129 Redwillow Harlow Essex CM19 5PD",
    "addr:housenumber":"129",
    "addr:postcode":"cm19 5pd",
    "addr:street":"Redwillow",
    "iso:country":"GB",
    "sg:address":"129 Redwillow",
    "sg:city":"Harlow",
    "sg:classifiers":[
        {
            "category":"Retail",
            "subcategory":"Driving School",
            "type":"Services"
        }
    ],
    "sg:phone":"+44 1279 301077",
    "sg:postcode":"CM19 5PD",
    "sg:province":"Essex",
    "wof:name":"Best Motoring School",
    "wof:placetype":"venue"
},
  "geometry": {"coordinates":[0.066791,51.754799],"type":"Point"}
}