{
  "type": "Feature",
  "properties": {
    "iso:country":"GB",
    "sg:address":"22 Woodland View",
    "sg:city":"Leeds",
    "sg:classifiers":[
        {
            "category":"Professional",
            "type":"Services"
        }
    ],
    "sg:phone":"+44 113 236 9038",
    "sg:postcode":"LS7 4QJ",
    "sg:province":"West Yorkshire",
    "sg:tags":[
        "reflexologists"
    ],
    "wof:name":"Neill-Higgins Christina",
    "wof:placetype":"venue"
},
  "geometry": {"coordinates":[-1.5368829966,53.8311576843],"type":"Point"}
}