{
  "type": "Feature",
  "properties": {
    "iso:country":"GB",
    "sg:address":"85-89 High Street, Long Eaton",
    "sg:city":"Nottingham",
    "sg:classifiers":[
        {
            "category":"Shopping",
            "subcategory":"Clothing, Apparel, & Fashions",
            "type":"Retail Goods"
        }
    ],
    "sg:phone":"+44 115 946 0924",
    "sg:postcode":"NG10 1JB",
    "sg:province":"Derbyshire",
    "sg:tags":[
        "ladieswear"
    ],
    "wof:name":"Dorothy Perkins",
    "wof:placetype":"venue"
},
  "geometry": {"coordinates":[-1.2704540491,52.8974113464],"type":"Point"}
}