{
  "type": "Feature",
  "properties": {
    "addr:full":"Meadow View, Collingham Lane, Long Itchington Warwick Warwickshire CV47 9QW",
    "addr:postcode":"cv47 9qw",
    "addr:street":"Collingham Lane",
    "iso:country":"GB",
    "sg:address":"Meadow View, Collingham Lane, Long Itchington",
    "sg:city":"Warwick",
    "sg:classifiers":[
        {
            "category":"Professional",
            "subcategory":"Accounting & Tax Preparation",
            "type":"Services"
        }
    ],
    "sg:phone":"+44 1926 815374",
    "sg:postcode":"CV47 9QW",
    "sg:province":"Warwickshire",
    "sg:tags":[
        "accountant"
    ],
    "wof:name":"Busy Bee Bookkeeping",
    "wof:placetype":"venue"
},
  "geometry": {"coordinates":[-1.392678,52.284271],"type":"Point"}
}