{
  "type": "Feature",
  "properties": {
    "iso:country":"GB",
    "sg:address":"87 Ridgeway, Chellaston",
    "sg:city":"Derby",
    "sg:classifiers":[
        {
            "category":"Personal",
            "subcategory":"Beauty Salon",
            "type":"Services"
        }
    ],
    "sg:phone":"+44 1332 700114",
    "sg:postcode":"DE73 1UJ",
    "sg:province":"Derbyshire",
    "sg:tags":[
        "unisex",
        "hairdresser"
    ],
    "wof:name":"Just William",
    "wof:placetype":"venue"
},
  "geometry": {"coordinates":[-1.43553,52.859898],"type":"Point"}
}