{
  "type": "Feature",
  "properties": {
    "addr:full":"37 Arnolds Crescent, Newbold Verdon Leicester Leicestershire LE9 9LD",
    "addr:housenumber":"37",
    "addr:postcode":"le9 9ld",
    "addr:street":"Arnolds Crescent",
    "iso:country":"GB",
    "sg:address":"37 Arnolds Crescent, Newbold Verdon",
    "sg:city":"Leicester",
    "sg:classifiers":[
        {
            "category":"Retail",
            "subcategory":"Repair Shop",
            "type":"Services"
        }
    ],
    "sg:postcode":"LE9 9LD",
    "sg:province":"Leicestershire",
    "sg:tags":[
        "radio",
        "television",
        "video"
    ],
    "wof:name":"T V Newbold Video & Microwave",
    "wof:placetype":"venue"
},
  "geometry": {"coordinates":[-1.3396309614,52.6273040771],"type":"Point"}
}