{
  "type": "Feature",
  "properties": {
    "addr:full":"Hubbards Drove, Hilgay Downham Market Cambridgeshire PE38 0JZ",
    "addr:postcode":"pe38 0jz",
    "addr:street":"Downham Market",
    "iso:country":"GB",
    "sg:address":"Hubbards Drove, Hilgay",
    "sg:city":"Downham Market",
    "sg:classifiers":[
        {
            "category":"Transit Center",
            "subcategory":"Passenger",
            "type":"Transportation"
        }
    ],
    "sg:postcode":"PE38 0JZ",
    "sg:province":"Cambridgeshire",
    "sg:tags":[
        "boarding",
        "kennel",
        "catteries"
    ],
    "wof:name":"The Cat's Whiskers",
    "wof:placetype":"venue"
},
  "geometry": {"coordinates":[0.38925,52.556808],"type":"Point"}
}