{
  "type": "Feature",
  "properties": {
    "iso:country":"GB",
    "sg:address":"17 Journeys End",
    "sg:city":"Bridport",
    "sg:classifiers":[
        {
            "category":"Building & Trades",
            "subcategory":"Plumbing",
            "type":"Services"
        }
    ],
    "sg:postcode":"DT6 5AU",
    "sg:province":"Dorset",
    "sg:tags":[
        "heating"
    ],
    "wof:name":"A S Gumbrill",
    "wof:placetype":"venue"
},
  "geometry": {"coordinates":[-2.766176,50.729801],"type":"Point"}
}