{
  "type": "Feature",
  "properties": {
    "addr:full":"35 Meadlands York East Riding of Yorkshire YO3 0NR",
    "addr:housenumber":"35",
    "addr:postcode":"yo3 0nr",
    "addr:street":"Meadlands York",
    "iso:country":"GB",
    "sg:address":"35 Meadlands",
    "sg:city":"York",
    "sg:classifiers":[
        {
            "category":"Organizations",
            "subcategory":"Non-profit Organization",
            "type":"Services"
        }
    ],
    "sg:phone":"+44 1904 415857",
    "sg:postcode":"YO3 0NR",
    "sg:province":"East Riding of Yorkshire",
    "sg:tags":[
        "organisation",
        "voluntary",
        "charity"
    ],
    "wof:name":"St Johns Ambulance",
    "wof:placetype":"venue"
},
  "geometry": {"coordinates":[-1.0410009623,53.9644813538],"type":"Point"}
}