{
  "type": "Feature",
  "properties": {
    "addr:full":"Unit 5, Yarrow Mill Yarrow Rd Chorley Lancashire PR6 0LP",
    "addr:housenumber":"unit 5",
    "addr:postcode":"pr6 0lp",
    "addr:street":"Yarrow Mill Yarrow Rd",
    "iso:country":"GB",
    "sg:address":"Unit 5, Yarrow Mill Yarrow Rd",
    "sg:city":"Chorley",
    "sg:classifiers":[
        {
            "category":"Professional",
            "type":"Services"
        }
    ],
    "sg:phone":"+44 1257 277683",
    "sg:postcode":"PR6 0LP",
    "sg:province":"Lancashire",
    "sg:tags":[
        "auctioneer"
    ],
    "wof:name":"Smith Hodgkinson Mcginty",
    "wof:placetype":"venue"
},
  "geometry": {"coordinates":[-2.617289,53.648716],"type":"Point"}
}