{
  "type": "Feature",
  "properties": {
    "addr:full":"103a Old Brompton Road London Greater London SW7 3LE",
    "addr:housenumber":"103a",
    "addr:postcode":"sw7 3le",
    "addr:street":"Old Brompton Road",
    "iso:country":"GB",
    "sg:address":"103a Old Brompton Road",
    "sg:city":"London",
    "sg:classifiers":[
        {
            "category":"Real Estate",
            "subcategory":"Real Estate Agent",
            "type":"Services"
        }
    ],
    "sg:phone":"+44 20 7581 5353",
    "sg:postcode":"SW7 3LE",
    "sg:province":"Greater London",
    "wof:name":"The American Agency Ltd.",
    "wof:placetype":"venue"
},
  "geometry": {"coordinates":[-0.1776620001,51.4922370911],"type":"Point"}
}