{
  "type": "Feature",
  "properties": {
    "iso:country":"GB",
    "sg:address":"80 Belmont Road",
    "sg:city":"Hereford",
    "sg:classifiers":[
        {
            "category":"Retail",
            "subcategory":"Laundry & Dry Cleaning",
            "type":"Services"
        }
    ],
    "sg:phone":"+44 1432 275179",
    "sg:postcode":"HR2 7JS",
    "sg:province":"Herefordshire",
    "sg:tags":[
        "launderette",
        "alteration"
    ],
    "wof:name":"Belmont Road Coin-Op Laundrette",
    "wof:placetype":"venue"
},
  "geometry": {"coordinates":[-2.723687,52.04715],"type":"Point"}
}