{
  "type": "Feature",
  "properties": {
    "addr:full":"8a Old Market St Thetford Norfolk IP24 2EQ",
    "addr:housenumber":"8a",
    "addr:postcode":"ip24 2eq",
    "addr:street":"Old Market St",
    "iso:country":"GB",
    "sg:address":"8a Old Market St",
    "sg:city":"Thetford",
    "sg:classifiers":[
        {
            "category":"Manufacturing",
            "subcategory":"Food",
            "type":"Manufacturing & Wholesale Goods"
        }
    ],
    "sg:postcode":"IP24 2EQ",
    "sg:province":"Norfolk",
    "sg:tags":[
        "processing"
    ],
    "wof:name":"J C Design",
    "wof:placetype":"venue"
},
  "geometry": {"coordinates":[0.7524629831,52.4105987549],"type":"Point"}
}