{
  "type": "Feature",
  "properties": {
    "addr:full":"11-13 Wellgate Rotherham South Yorkshire S60 2LT",
    "addr:housenumber":"11-13",
    "addr:postcode":"s60 2lt",
    "addr:street":"Wellgate Rotherham South",
    "iso:country":"GB",
    "sg:address":"11-13 Wellgate",
    "sg:city":"Rotherham",
    "sg:classifiers":[
        {
            "category":"Shopping",
            "subcategory":"Clothing, Apparel, & Fashions",
            "type":"Retail Goods"
        }
    ],
    "sg:phone":"+44 1709 382776",
    "sg:postcode":"S60 2LT",
    "sg:province":"South Yorkshire",
    "sg:tags":[
        "outdoor",
        "wear"
    ],
    "wof:name":"Wilbefort",
    "wof:placetype":"venue"
},
  "geometry": {"coordinates":[-1.3543169498,53.4304008484],"type":"Point"}
}