{
  "type": "Feature",
  "properties": {
    "iso:country":"GB",
    "sg:address":"29 Beechfield, Moulton",
    "sg:city":"Northwich",
    "sg:classifiers":[
        {
            "category":"Building & Trades",
            "subcategory":"Construction",
            "type":"Services"
        }
    ],
    "sg:phone":"+44 1606 594449",
    "sg:postcode":"CW9 8PF",
    "sg:province":"Cheshire",
    "sg:tags":[
        "decorator",
        "painter"
    ],
    "wof:name":"R Leach & Sons",
    "wof:placetype":"venue"
},
  "geometry": {"coordinates":[-2.510594,53.234489],"type":"Point"}
}