{
  "type": "Feature",
  "properties": {
    "addr:full":"Intergen House, 65-67 Western Road Hove East Sussex BN3 2JQ",
    "addr:housenumber":"65-67",
    "addr:postcode":"bn3 2jq",
    "addr:street":"Western Road",
    "iso:country":"GB",
    "sg:address":"Intergen House, 65-67 Western Road",
    "sg:city":"Hove",
    "sg:classifiers":[
        {
            "category":"Building & Trades",
            "subcategory":"Construction",
            "type":"Services"
        }
    ],
    "sg:postcode":"BN3 2JQ",
    "sg:province":"East Sussex",
    "sg:tags":[
        "contractor"
    ],
    "wof:name":"International Generics Ltd.",
    "wof:placetype":"venue"
},
  "geometry": {"coordinates":[-0.163432,50.826378],"type":"Point"}
}