{
  "type": "Feature",
  "properties": {
    "addr:full":"39-41 North Rd, London Greater London N7 9DP",
    "addr:housenumber":"39-41",
    "addr:postcode":"n7 9dp",
    "addr:street":"North Rd",
    "iso:country":"GB",
    "sg:address":"39-41 North Rd,",
    "sg:city":"London",
    "sg:classifiers":[
        {
            "category":"Communications",
            "subcategory":"Newspaper",
            "type":"Services"
        }
    ],
    "sg:postcode":"N7 9DP",
    "sg:province":"Greater London",
    "sg:tags":[
        "magazine"
    ],
    "wof:name":"Corporate Cover Publications Ltd",
    "wof:placetype":"venue"
},
  "geometry": {"coordinates":[-0.125579,51.547737],"type":"Point"}
}