{
  "type": "Feature",
  "properties": {
    "addr:full":"Butts Road Northampton Northamptonshire NN4 0UE",
    "addr:postcode":"nn4 0ue",
    "addr:street":"Butts Road",
    "iso:country":"GB",
    "sg:address":"Butts Road",
    "sg:city":"Northampton",
    "sg:classifiers":[
        {
            "category":"Bars & Pubs",
            "type":"Food & Drink"
        }
    ],
    "sg:phone":"+44 1604 665801",
    "sg:postcode":"NN4 0UE",
    "sg:province":"Northamptonshire",
    "sg:tags":[
        "pubs",
        "inn"
    ],
    "wof:name":"Brewster Taverns Ltd.",
    "wof:placetype":"venue"
},
  "geometry": {"coordinates":[-0.900862,52.205406],"type":"Point"}
}