{
  "type": "Feature",
  "properties": {
    "addr:full":"594 London Rd Ashford Greater London TW15 3AF",
    "addr:housenumber":"594",
    "addr:postcode":"tw15 3af",
    "addr:street":"London Rd",
    "iso:country":"GB",
    "sg:address":"594 London Rd",
    "sg:city":"Ashford",
    "sg:classifiers":[
        {
            "category":"Autos & Motor Vehicles",
            "subcategory":"Automobile Sales",
            "type":"Retail Goods"
        }
    ],
    "sg:phone":"+44 1784 252125",
    "sg:postcode":"TW15 3AF",
    "sg:province":"Greater London",
    "sg:tags":[
        "car"
    ],
    "wof:name":"E S Motors (Ashford) Ltd",
    "wof:placetype":"venue"
},
  "geometry": {"coordinates":[-0.471559,51.443272],"type":"Point"}
}