{
  "type": "Feature",
  "properties": {
    "addr:full":"91 Longdon Road Solihull Warwickshire B93 9HT",
    "addr:housenumber":"91",
    "addr:postcode":"b93 9ht",
    "addr:street":"Longdon Road",
    "iso:country":"GB",
    "sg:address":"91 Longdon Road",
    "sg:city":"Solihull",
    "sg:classifiers":[
        {
            "category":"Shopping",
            "subcategory":"Department Store",
            "type":"Retail Goods"
        },
        {
            "category":"Home & Garden",
            "subcategory":"Carpets & Floor Coverings",
            "type":"Retail Goods"
        }
    ],
    "sg:postcode":"B93 9HT",
    "sg:province":"Warwickshire",
    "sg:tags":[
        "carpets",
        "rug",
        "matting"
    ],
    "wof:name":"Don Arthur Mander",
    "wof:placetype":"venue"
},
  "geometry": {"coordinates":[-1.751797,52.38969],"type":"Point"}
}