{
  "type": "Feature",
  "properties": {
    "iso:country":"GB",
    "sg:address":", Cutnall Green",
    "sg:city":"Droitwich",
    "sg:classifiers":[
        {
            "category":"Bars & Pubs",
            "type":"Food & Drink"
        }
    ],
    "sg:phone":"+44 1299 851257",
    "sg:postcode":"WR9 0PW",
    "sg:province":"Worcestershire",
    "sg:tags":[
        "pubs",
        "inn"
    ],
    "wof:name":"Live & Let Live Inn",
    "wof:placetype":"venue"
},
  "geometry": {"coordinates":[-2.155477047,52.3361244202],"type":"Point"}
}