{
  "type": "Feature",
  "properties": {
    "iso:country":"GB",
    "sg:address":"75 Whalley New Road",
    "sg:city":"Blackburn",
    "sg:classifiers":[
        {
            "category":"Shopping",
            "subcategory":"Pharmacy",
            "type":"Retail Goods"
        }
    ],
    "sg:phone":"+44 1254 54461",
    "sg:postcode":"BB1 6JY",
    "sg:province":"Lancashire",
    "sg:tags":[
        "pharmacist",
        "dispensing",
        "chemist"
    ],
    "wof:name":"R H Wilson (Chemists) Ltd.",
    "wof:placetype":"venue"
},
  "geometry": {"coordinates":[-2.471927,53.757748],"type":"Point"}
}