{
  "type": "Feature",
  "properties": {
    "addr:full":"School Street, Kirkby In Ashfield Nottingham Nottinghamshire NG17 7BT",
    "addr:postcode":"ng17 7bt",
    "addr:street":"School Street",
    "iso:country":"GB",
    "sg:address":"School Street, Kirkby In Ashfield",
    "sg:city":"Nottingham",
    "sg:classifiers":[
        {
            "category":"Place Of Worship",
            "type":"Public Place"
        }
    ],
    "sg:phone":"+44 1623 754495",
    "sg:postcode":"NG17 7BT",
    "sg:province":"Nottinghamshire",
    "wof:name":"Our Lady Help Of Christians R C Church",
    "wof:placetype":"venue"
},
  "geometry": {"coordinates":[-1.241864,53.098797],"type":"Point"}
}