{
  "type": "Feature",
  "properties": {
    "addr:full":"Auchorthie, Maud Peterhead Aberdeenshire AB42 4QH",
    "addr:postcode":"ab42 4qh",
    "addr:street":"Auchorthie",
    "iso:country":"GB",
    "sg:address":"Auchorthie, Maud",
    "sg:city":"Peterhead",
    "sg:classifiers":[
        {
            "category":"Farming",
            "subcategory":"Farm",
            "type":"Manufacturing & Wholesale Goods"
        }
    ],
    "sg:phone":"+44 1771 613260",
    "sg:postcode":"AB42 4QH",
    "sg:province":"Aberdeenshire",
    "sg:tags":[
        "mixed",
        "crop"
    ],
    "wof:name":"John Milne",
    "wof:placetype":"venue"
},
  "geometry": {"coordinates":[-2.1288089752,57.5211257935],"type":"Point"}
}