{
  "type": "Feature",
  "properties": {
    "addr:full":"38d Ellesmere Ct, Leechmere Indust Est Sunderland Tyne and Wear SR2 9UA",
    "addr:housenumber":"38d",
    "addr:postcode":"sr2 9ua",
    "addr:street":"Ellesmere Ct;Indust",
    "iso:country":"GB",
    "sg:address":"38d Ellesmere Ct, Leechmere Indust Est",
    "sg:city":"Sunderland",
    "sg:classifiers":[
        {
            "category":"Building & Trades",
            "subcategory":"Construction",
            "type":"Services"
        }
    ],
    "sg:phone":"+44 191 523 7776",
    "sg:postcode":"SR2 9UA",
    "sg:province":"Tyne and Wear",
    "sg:tags":[
        "roofing"
    ],
    "wof:name":"Grange Roofing",
    "wof:placetype":"venue"
},
  "geometry": {"coordinates":[-1.375735,54.880726],"type":"Point"}
}