{
  "type": "Feature",
  "properties": {
    "iso:country":"GB",
    "sg:address":"4 Birling Road",
    "sg:city":"Tunbridge Wells",
    "sg:classifiers":[
        {
            "category":"Building & Trades",
            "subcategory":"Construction",
            "type":"Services"
        }
    ],
    "sg:phone":"+44 1892 536550",
    "sg:postcode":"TN2 5LX",
    "sg:province":"East Sussex",
    "sg:tags":[
        "flooring"
    ],
    "wof:name":"Tunbridge Wells Flooring Co.",
    "wof:placetype":"venue"
},
  "geometry": {"coordinates":[0.2601880133,51.1181221008],"type":"Point"}
}