{
  "type": "Feature",
  "properties": {
    "addr:full":"6 Rosehall Rd, Bellshill Industrial Estate Bellshill North Lanarkshire ML4 3NR",
    "addr:housenumber":"6",
    "addr:postcode":"ml4 3nr",
    "addr:street":"Rosehall Rd;Industrial Estate",
    "iso:country":"GB",
    "sg:address":"6 Rosehall Rd, Bellshill Industrial Estate",
    "sg:city":"Bellshill",
    "sg:classifiers":[
        {
            "category":"Social Services",
            "subcategory":"Job Training",
            "type":"Services"
        }
    ],
    "sg:phone":"+44 1698 748181",
    "sg:postcode":"ML4 3NR",
    "sg:province":"North Lanarkshire",
    "sg:tags":[
        "engineering",
        "marine"
    ],
    "wof:name":"C Power Ltd",
    "wof:placetype":"venue"
},
  "geometry": {"coordinates":[-4.0291919708,55.8234214783],"type":"Point"}
}