{
  "type": "Feature",
  "properties": {
    "iso:country":"GB",
    "sg:address":"Haverfordwest Business Centre, Merlins Court, Winch Lane",
    "sg:city":"Haverfordwest",
    "sg:classifiers":[
        {
            "category":"Real Estate",
            "subcategory":"Real Estate Services",
            "type":"Services"
        }
    ],
    "sg:phone":"+44 1437 763271",
    "sg:postcode":"SA61 1SB",
    "sg:province":"Pembrokeshire",
    "sg:tags":[
        "management",
        "facility"
    ],
    "wof:name":"W S Atkins Facilities Management",
    "wof:placetype":"venue"
},
  "geometry": {"coordinates":[-4.9688181877,51.7970161438],"type":"Point"}
}