{
  "type": "Feature",
  "properties": {
    "iso:country":"GB",
    "sg:address":"46 Village Dr",
    "sg:city":"Preston",
    "sg:classifiers":[
        {
            "category":"Building & Trades",
            "subcategory":"Construction",
            "type":"Services"
        }
    ],
    "sg:phone":"+44 1772 491468",
    "sg:postcode":"PR2 6JH",
    "sg:province":"Lancashire",
    "sg:tags":[
        "builder"
    ],
    "wof:name":"D Gallagher",
    "wof:placetype":"venue"
},
  "geometry": {"coordinates":[-2.6548879147,53.7687187195],"type":"Point"}
}