{
  "type": "Feature",
  "properties": {
    "iso:country":"GB",
    "sg:address":"143 Cambridge St",
    "sg:city":"Aylesbury",
    "sg:classifiers":[
        {
            "category":"Autos & Motor Vehicles",
            "subcategory":"Auto Supplies",
            "type":"Retail Goods"
        }
    ],
    "sg:postcode":"HP20 1BH",
    "sg:province":"Buckinghamshire",
    "sg:tags":[
        "exhaust",
        "absorber",
        "shock"
    ],
    "wof:name":"Kwik-Fit (G B) Ltd",
    "wof:placetype":"venue"
},
  "geometry": {"coordinates":[-0.8079140186,51.8196678162],"type":"Point"}
}