{
  "type": "Feature",
  "properties": {
    "iso:country":"GB",
    "sg:address":"82 Longfield Road",
    "sg:city":"Winchester",
    "sg:classifiers":[
        {
            "category":"Building & Trades",
            "subcategory":"Construction",
            "type":"Services"
        }
    ],
    "sg:phone":"+44 1962 861366",
    "sg:postcode":"SO23 0NT",
    "sg:province":"Hampshire",
    "sg:tags":[
        "roofing"
    ],
    "wof:name":"P M Roofing",
    "wof:placetype":"venue"
},
  "geometry": {"coordinates":[-1.294297,51.065968],"type":"Point"}
}