{
  "type": "Feature",
  "properties": {
    "iso:country":"GB",
    "sg:address":"The Grape Mill, New Coin Street",
    "sg:city":"Oldham",
    "sg:classifiers":[
        {
            "category":"Manufacturing",
            "subcategory":"Textiles",
            "type":"Manufacturing & Wholesale Goods"
        }
    ],
    "sg:phone":"+44 161 633 2241",
    "sg:postcode":"OL2 5JB",
    "sg:province":"Lancashire",
    "sg:tags":[
        "made-up"
    ],
    "wof:name":"Highams Group Ltd.",
    "wof:placetype":"venue"
},
  "geometry": {"coordinates":[-2.1269099712,53.5621490479],"type":"Point"}
}