{
  "type": "Feature",
  "properties": {
    "iso:country":"GB",
    "sg:address":"The Old Dairy, Highway Farm, Horsley Road",
    "sg:city":"Cobham",
    "sg:classifiers":[
        {
            "category":"Organizations",
            "subcategory":"Community Association",
            "type":"Services"
        }
    ],
    "sg:phone":"+44 1932 866010",
    "sg:postcode":"KT11 3JZ",
    "sg:province":"Surrey",
    "sg:tags":[
        "relation",
        "public"
    ],
    "wof:name":"Kavanagh Communications Ltd.",
    "wof:placetype":"venue"
},
  "geometry": {"coordinates":[-0.410454,51.328117],"type":"Point"}
}