{
  "type": "Feature",
  "properties": {
    "addr:full":"26 Banbury Lane, Byefield Daventry Northamptonshire NN11 6UX",
    "addr:housenumber":"26",
    "addr:postcode":"nn11 6ux",
    "addr:street":"Banbury Lane",
    "iso:country":"GB",
    "sg:address":"26 Banbury Lane, Byefield",
    "sg:city":"Daventry",
    "sg:classifiers":[
        {
            "category":"Organizations",
            "subcategory":"Non-profit Organization",
            "type":"Services"
        }
    ],
    "sg:phone":"+44 1327 260558",
    "sg:postcode":"NN11 6UX",
    "sg:province":"Northamptonshire",
    "sg:tags":[
        "organisation",
        "voluntary",
        "charity"
    ],
    "wof:name":"Kuwait & British Women Support Group",
    "wof:placetype":"venue"
},
  "geometry": {"coordinates":[-1.247432,52.174522],"type":"Point"}
}