{
  "type": "Feature",
  "properties": {
    "addr:full":"Aston House, Steeple Aston Bicester Oxfordshire OX25 4SG",
    "addr:postcode":"ox25 4sg",
    "iso:country":"GB",
    "sg:address":"Aston House, Steeple Aston",
    "sg:city":"Bicester",
    "sg:classifiers":[
        {
            "category":"Shopping",
            "subcategory":"Computers & Home Electronics",
            "type":"Retail Goods"
        }
    ],
    "sg:phone":"+44 1869 347899",
    "sg:postcode":"OX25 4SG",
    "sg:province":"Oxfordshire",
    "sg:tags":[
        "equipment",
        "radio"
    ],
    "wof:name":"Supertek Sales",
    "wof:placetype":"venue"
},
  "geometry": {"coordinates":[-1.239866,51.919247],"type":"Point"}
}