{
  "type": "Feature",
  "properties": {
    "addr:full":"Oakhanger Farm Bordon Hampshire GU35 9JA",
    "addr:postcode":"gu35 9ja",
    "iso:country":"GB",
    "sg:address":"Oakhanger Farm",
    "sg:city":"Bordon",
    "sg:classifiers":[
        {
            "category":"Sports & Exercise",
            "subcategory":"Stables",
            "type":"Entertainment"
        }
    ],
    "sg:postcode":"GU35 9JA",
    "sg:province":"Hampshire",
    "sg:tags":[
        "education",
        "equestrian"
    ],
    "wof:name":"R T Boyson",
    "wof:placetype":"venue"
},
  "geometry": {"coordinates":[-0.865114,51.108856],"type":"Point"}
}