{
  "type": "Feature",
  "properties": {
    "iso:country":"GB",
    "sg:address":", Cenarth",
    "sg:city":"Newcastle Emlyn",
    "sg:classifiers":[
        {
            "category":"Education",
            "subcategory":"School",
            "type":"Public Place"
        }
    ],
    "sg:phone":"+44 1239 710060",
    "sg:postcode":"SA38 9JL",
    "sg:province":"Carmarthenshire",
    "sg:tags":[
        "local",
        "authority"
    ],
    "wof:name":"Cenarth C.P School",
    "wof:placetype":"venue"
},
  "geometry": {"coordinates":[-4.467984,52.035919],"type":"Point"}
}