{
  "type": "Feature",
  "properties": {
    "addr:full":"12 Castle Street Macclesfield Cheshire SK11 6AF",
    "addr:housenumber":"12",
    "addr:postcode":"sk11 6af",
    "addr:street":"Castle Street",
    "iso:country":"GB",
    "sg:address":"12 Castle Street",
    "sg:city":"Macclesfield",
    "sg:classifiers":[
        {
            "category":"Banks & Credit Unions",
            "subcategory":"Financial Services",
            "type":"Services"
        }
    ],
    "sg:phone":"+44 1625 422997",
    "sg:postcode":"SK11 6AF",
    "sg:province":"Cheshire",
    "sg:tags":[
        "building",
        "society"
    ],
    "wof:name":"Britannia Building Society",
    "wof:placetype":"venue"
},
  "geometry": {"coordinates":[-2.126967,53.259815],"type":"Point"}
}