{
  "type": "Feature",
  "properties": {
    "addr:full":"11 Kings Drive, Wistaston Crewe Cheshire CW2 8HY",
    "addr:housenumber":"11",
    "addr:postcode":"cw2 8hy",
    "addr:street":"Kings Drive",
    "iso:country":"GB",
    "sg:address":"11 Kings Drive, Wistaston",
    "sg:city":"Crewe",
    "sg:classifiers":[
        {
            "category":"Food & Beverages",
            "subcategory":"Liquor & Beverages",
            "type":"Retail Goods"
        }
    ],
    "sg:phone":"+44 1270 663571",
    "sg:postcode":"CW2 8HY",
    "sg:province":"Cheshire",
    "sg:tags":[
        "beer",
        "spirit",
        "wines"
    ],
    "wof:name":"Bargain Booze",
    "wof:placetype":"venue"
},
  "geometry": {"coordinates":[-2.475793,53.080383],"type":"Point"}
}