{
  "type": "Feature",
  "properties": {
    "iso:country":"GB",
    "sg:address":"Phoenix Works, Claycliffe Road, Barugh",
    "sg:city":"Barnsley",
    "sg:classifiers":[
        {
            "category":"Home & Garden",
            "subcategory":"Hardware",
            "type":"Retail Goods"
        }
    ],
    "sg:phone":"+44 1226 388444",
    "sg:postcode":"S75 1HY",
    "sg:province":"South Yorkshire",
    "sg:tags":[
        "fixing",
        "nuts",
        "bolt"
    ],
    "wof:name":"Bapp Industrial Supplies Ltd.",
    "wof:placetype":"venue"
},
  "geometry": {"coordinates":[-1.5312290192,53.5679588318],"type":"Point"}
}