{
  "type": "Feature",
  "properties": {
    "iso:country":"GB",
    "sg:address":"2a St. Aidans Walk",
    "sg:city":"Bishop Auckland",
    "sg:classifiers":[
        {
            "category":"Health Services",
            "subcategory":"Clinic",
            "type":"Services"
        }
    ],
    "sg:phone":"+44 1388 663950",
    "sg:postcode":"DL14 6SA",
    "sg:province":"Durham",
    "sg:tags":[
        "nh"
    ],
    "wof:name":"Community Extended Care Unit",
    "wof:placetype":"venue"
},
  "geometry": {"coordinates":[-1.665804,54.650959],"type":"Point"}
}