{
  "type": "Feature",
  "properties": {
    "iso:country":"GB",
    "sg:address":"Clare Street, Denton",
    "sg:city":"Manchester",
    "sg:classifiers":[
        {
            "category":"Education",
            "subcategory":"School",
            "type":"Public Place"
        }
    ],
    "sg:phone":"+44 161 320 5186",
    "sg:postcode":"M34 3LQ",
    "sg:province":"Greater Manchester",
    "sg:tags":[
        "local",
        "authority"
    ],
    "wof:name":"Russell Scott Primary School",
    "wof:placetype":"venue"
},
  "geometry": {"coordinates":[-2.1164441109,53.4604148865],"type":"Point"}
}