{
  "type": "Feature",
  "properties": {
    "iso:country":"GB",
    "sg:address":"122 Broomhill Road",
    "sg:city":"Aberdeen",
    "sg:classifiers":[
        {
            "category":"Autos & Motor Vehicles",
            "subcategory":"Automobile Sales",
            "type":"Retail Goods"
        },
        {
            "category":"Government",
            "subcategory":"Department Of Motor Vehicles",
            "type":"Public Place"
        }
    ],
    "sg:phone":"+44 1224 581252",
    "sg:postcode":"AB10 6HX",
    "sg:province":"Aberdeen City",
    "sg:tags":[
        "car",
        "inspection"
    ],
    "wof:name":"John Clark (Aberdeen) Ltd.",
    "wof:placetype":"venue"
},
  "geometry": {"coordinates":[-2.12119,57.133698],"type":"Point"}
}