{
  "type": "Feature",
  "properties": {
    "iso:country":"GB",
    "sg:address":"Oxlow Lane",
    "sg:city":"Dagenham",
    "sg:classifiers":[
        {
            "category":"Organizations",
            "subcategory":"Membership Organization",
            "type":"Services"
        },
        {
            "category":"Organizations",
            "subcategory":"Non-profit Organization",
            "type":"Services"
        }
    ],
    "sg:phone":"+44 20 8592 1634",
    "sg:postcode":"RM9 5XJ",
    "sg:province":"Essex",
    "sg:tags":[
        "club",
        "charitable",
        "organisation",
        "charity"
    ],
    "wof:name":"The Holy Family Social Club",
    "wof:placetype":"venue"
},
  "geometry": {"coordinates":[0.146265,51.551121],"type":"Point"}
}