{
  "type": "Feature",
  "properties": {
    "iso:country":"GB",
    "sg:address":"Letitia House, Letitia Street",
    "sg:city":"Middlesbrough",
    "sg:classifiers":[
        {
            "category":"Health Services",
            "subcategory":"Nursing And Care Facility",
            "type":"Services"
        }
    ],
    "sg:phone":"+44 1642 252445",
    "sg:postcode":"TS5 4BE",
    "sg:province":"North Yorkshire",
    "sg:tags":[
        "home"
    ],
    "wof:name":"English Churches Housing Group Ltd.",
    "wof:placetype":"venue"
},
  "geometry": {"coordinates":[-1.259283,54.569756],"type":"Point"}
}