{
  "type": "Feature",
  "properties": {
    "iso:country":"GB",
    "sg:address":"Regency House, St Marys St. Penistone",
    "sg:city":"Sheffield",
    "sg:classifiers":[
        {
            "category":"Professional",
            "subcategory":"Detective & Security Services",
            "type":"Services"
        }
    ],
    "sg:phone":"+44 1226 761056",
    "sg:postcode":"S36 6DT",
    "sg:province":"South Yorkshire",
    "wof:name":"J H Security Management Ltd",
    "wof:placetype":"venue"
},
  "geometry": {"coordinates":[-1.631187,53.526421],"type":"Point"}
}