{
  "type": "Feature",
  "properties": {
    "iso:country":"GB",
    "sg:address":"357 Bethnal Green Rd",
    "sg:city":"London",
    "sg:classifiers":[
        {
            "category":"Professional",
            "subcategory":"Printing & Photocopies",
            "type":"Services"
        }
    ],
    "sg:postcode":"E2 6LG",
    "sg:province":"Greater London",
    "sg:tags":[
        "duplicating",
        "copying"
    ],
    "wof:name":"Harlequin Photocopy Systems",
    "wof:placetype":"venue"
},
  "geometry": {"coordinates":[-0.062202,51.526844],"type":"Point"}
}