{
  "type": "Feature",
  "properties": {
    "addr:full":"18 York Road London Greater London SW19 8TP",
    "addr:housenumber":"18",
    "addr:postcode":"sw19 8tp",
    "addr:street":"York Road",
    "iso:country":"GB",
    "sg:address":"18 York Road",
    "sg:city":"London",
    "sg:classifiers":[
        {
            "category":"Autos & Motor Vehicles",
            "subcategory":"Auto Supplies",
            "type":"Retail Goods"
        },
        {
            "category":"Shopping",
            "type":"Retail Goods"
        }
    ],
    "sg:phone":"+44 20 8543 7111",
    "sg:postcode":"SW19 8TP",
    "sg:province":"Greater London",
    "sg:tags":[
        "car",
        "part",
        "accessory"
    ],
    "wof:name":"Richbrook International Ltd.",
    "wof:placetype":"venue"
},
  "geometry": {"coordinates":[-0.189499,51.422112],"type":"Point"}
}