{
  "type": "Feature",
  "properties": {
    "iso:country":"GB",
    "sg:address":"Exeter Livestock Market, Matford Park Road",
    "sg:city":"Exeter",
    "sg:classifiers":[
        {
            "category":"Banks & Credit Unions",
            "subcategory":"Investment Brokerage",
            "type":"Services"
        },
        {
            "category":"Banks & Credit Unions",
            "subcategory":"Financial Services",
            "type":"Services"
        }
    ],
    "sg:phone":"+44 1392 425164",
    "sg:postcode":"EX2 8FD",
    "sg:province":"Devon",
    "sg:tags":[
        "adviser",
        "stockbroker"
    ],
    "wof:name":"WELCH & CO",
    "wof:placetype":"venue"
},
  "geometry": {"coordinates":[-3.522329,50.691917],"type":"Point"}
}