{
  "type": "Feature",
  "properties": {
    "iso:country":"GB",
    "sg:address":"Unit 9, Labtec Street, Wheatsheaf Trading Estate",
    "sg:city":"Manchester",
    "sg:classifiers":[
        {
            "category":"Wholesale",
            "subcategory":"Meat",
            "type":"Manufacturing & Wholesale Goods"
        }
    ],
    "sg:phone":"+44 161 794 2078",
    "sg:postcode":"M27 2TB",
    "sg:province":"Greater Manchester",
    "sg:tags":[
        "-"
    ],
    "wof:name":"Tenderoak Meats Ltd.",
    "wof:placetype":"venue"
},
  "geometry": {"coordinates":[-2.3312599659,53.5163497925],"type":"Point"}
}