{
  "type": "Feature",
  "properties": {
    "iso:country":"GB",
    "sg:address":"8 Hadley Business Park, Pond Hal Road",
    "sg:city":"Ipswich",
    "sg:classifiers":[
        {
            "category":"Wholesale",
            "subcategory":"Medical Equipment & Supplies",
            "type":"Manufacturing & Wholesale Goods"
        }
    ],
    "sg:phone":"+44 1473 829299",
    "sg:postcode":"IP7 5PW",
    "sg:province":"Suffolk",
    "sg:tags":[
        "dental"
    ],
    "wof:name":"Bicon Marketing Ltd.",
    "wof:placetype":"venue"
},
  "geometry": {"coordinates":[0.9842699766,52.0376205444],"type":"Point"}
}