{
  "type": "Feature",
  "properties": {
    "addr:full":"Unit 2 Burnsfield La Hemel Hempstead Hertfordshire HP2 7HY",
    "addr:housenumber":"unit 2",
    "addr:postcode":"hp2 7hy",
    "addr:street":"Burnsfield La Hemel Hempstead",
    "iso:country":"GB",
    "sg:address":"Unit 2 Burnsfield La",
    "sg:city":"Hemel Hempstead",
    "sg:classifiers":[
        {
            "category":"Retail",
            "subcategory":"Auto Repair",
            "type":"Services"
        }
    ],
    "sg:phone":"+44 1442 249494",
    "sg:postcode":"HP2 7HY",
    "sg:province":"Hertfordshire",
    "sg:tags":[
        "modification",
        "garage"
    ],
    "wof:name":"Marlowes Garage",
    "wof:placetype":"venue"
},
  "geometry": {"coordinates":[-0.4283879995,51.7576828003],"type":"Point"}
}