{
  "type": "Feature",
  "properties": {
    "addr:full":"3 Solihull La Birmingham West Midlands B28 9LS",
    "addr:housenumber":"3",
    "addr:postcode":"b28 9ls",
    "addr:street":"Solihull La Birmingham",
    "iso:country":"GB",
    "sg:address":"3 Solihull La",
    "sg:city":"Birmingham",
    "sg:classifiers":[
        {
            "category":"Retail",
            "subcategory":"Repair Shop",
            "type":"Services"
        }
    ],
    "sg:phone":"+44 121 744 5690",
    "sg:postcode":"B28 9LS",
    "sg:province":"West Midlands",
    "sg:tags":[
        "radio",
        "television",
        "video"
    ],
    "wof:name":"Hi-Tech Radio",
    "wof:placetype":"venue"
},
  "geometry": {"coordinates":[-1.835963,52.422363],"type":"Point"}
}