{
  "type": "Feature",
  "properties": {
    "addr:full":"176-178 Leagrave Rd Luton Bedfordshire LU3 1JD",
    "addr:housenumber":"176-178",
    "addr:postcode":"lu3 1jd",
    "addr:street":"Leagrave Rd",
    "iso:country":"GB",
    "sg:address":"176-178 Leagrave Rd",
    "sg:city":"Luton",
    "sg:classifiers":[
        {
            "category":"Building & Trades",
            "subcategory":"Equipment Rental",
            "type":"Services"
        }
    ],
    "sg:phone":"+44 1582 571439",
    "sg:postcode":"LU3 1JD",
    "sg:province":"Bedfordshire",
    "sg:tags":[
        "hire",
        "catering"
    ],
    "wof:name":"Caterplan Hire",
    "wof:placetype":"venue"
},
  "geometry": {"coordinates":[-0.432402,51.89032],"type":"Point"}
}