{
  "type": "Feature",
  "properties": {
    "iso:country":"GB",
    "sg:address":"402 Eastrea Road, Eastrea",
    "sg:city":"Peterborough",
    "sg:classifiers":[
        {
            "category":"Bars & Pubs",
            "type":"Food & Drink"
        },
        {
            "category":"Community Center",
            "subcategory":"Social",
            "type":"Public Place"
        }
    ],
    "sg:phone":"+44 1733 203333",
    "sg:postcode":"PE7 2AR",
    "sg:province":"Cambridgeshire",
    "sg:tags":[
        "pubs",
        "house",
        "inn",
        "activity"
    ],
    "wof:name":"The Nags Head",
    "wof:placetype":"venue"
},
  "geometry": {"coordinates":[-0.0941729993,52.5570487976],"type":"Point"}
}