{
  "type": "Feature",
  "properties": {
    "iso:country":"GB",
    "sg:address":"33a Bailey Street",
    "sg:city":"Oswestry",
    "sg:classifiers":[
        {
            "category":"Organizations",
            "subcategory":"Membership Organization",
            "type":"Services"
        }
    ],
    "sg:phone":"+44 1691 654103",
    "sg:postcode":"SY11 1PX",
    "sg:province":"Shropshire",
    "sg:tags":[
        "club"
    ],
    "wof:name":"Oswestry Combined Ex Service Men's Club Ltd.",
    "wof:placetype":"venue"
},
  "geometry": {"coordinates":[-3.054953,52.860241],"type":"Point"}
}