{
  "type": "Feature",
  "properties": {
    "iso:country":"GB",
    "sg:address":"5 The Crescent, Bebington",
    "sg:city":"Wirral",
    "sg:classifiers":[
        {
            "category":"Shopping",
            "subcategory":"News",
            "type":"Retail Goods"
        }
    ],
    "sg:phone":"+44 151 608 1176",
    "sg:postcode":"CH63 2NT",
    "sg:province":"Merseyside",
    "sg:tags":[
        "newsagent"
    ],
    "wof:name":"LESLIE G CARRUTHERS",
    "wof:placetype":"venue"
},
  "geometry": {"coordinates":[-3.020913,53.349609],"type":"Point"}
}