{
  "type": "Feature",
  "properties": {
    "addr:full":"58 Erpingham Road, Putney London Greater London SW15 1BG",
    "addr:housenumber":"58",
    "addr:postcode":"sw15 1bg",
    "addr:street":"Erpingham Road",
    "iso:country":"GB",
    "sg:address":"58 Erpingham Road, Putney",
    "sg:city":"London",
    "sg:classifiers":[
        {
            "category":"Professional",
            "subcategory":"Computer Services",
            "type":"Services"
        }
    ],
    "sg:postcode":"SW15 1BG",
    "sg:province":"Greater London",
    "sg:tags":[
        "system",
        "software"
    ],
    "wof:name":"Network  &  Computer Consulting Ltd",
    "wof:placetype":"venue"
},
  "geometry": {"coordinates":[-0.227468,51.466221],"type":"Point"}
}