{
  "type": "Feature",
  "properties": {
    "addr:full":"12/14 London Rd Guildford Surrey GU1 2AF",
    "addr:housenumber":"12 / 14",
    "addr:postcode":"gu1 2af",
    "addr:street":"London Rd",
    "iso:country":"GB",
    "sg:address":"12/14 London Rd",
    "sg:city":"Guildford",
    "sg:classifiers":[
        {
            "category":"Personal",
            "subcategory":"Beauty Salon",
            "type":"Services"
        }
    ],
    "sg:phone":"+44 1483 573080",
    "sg:postcode":"GU1 2AF",
    "sg:province":"Surrey",
    "sg:tags":[
        "unisex",
        "hairdresser"
    ],
    "wof:name":"Etienne's",
    "wof:placetype":"venue"
},
  "geometry": {"coordinates":[-0.565584,51.238125],"type":"Point"}
}