{
  "type": "Feature",
  "properties": {
    "addr:full":"Unit 1a Harropwell Lane Pontefract North Yorkshire WF8 1QY",
    "addr:housenumber":"unit 1a",
    "addr:postcode":"wf8 1qy",
    "addr:street":"Harropwell Lane",
    "iso:country":"GB",
    "sg:address":"Unit 1a Harropwell Lane",
    "sg:city":"Pontefract",
    "sg:classifiers":[
        {
            "category":"Autos & Motor Vehicles",
            "subcategory":"Motorcycle Sales",
            "type":"Retail Goods"
        }
    ],
    "sg:postcode":"WF8 1QY",
    "sg:province":"North Yorkshire",
    "wof:name":"Hanach Scooters",
    "wof:placetype":"venue"
},
  "geometry": {"coordinates":[-1.3052220345,53.692401886],"type":"Point"}
}