{
  "type": "Feature",
  "properties": {
    "iso:country":"GB",
    "sg:address":"3 Springwood Rd",
    "sg:city":"Leeds",
    "sg:classifiers":[
        {
            "category":"Professional",
            "subcategory":"Advertising",
            "type":"Services"
        }
    ],
    "sg:postcode":"LS8 2QA",
    "sg:province":"West Yorkshire",
    "sg:tags":[
        "agency"
    ],
    "wof:name":"Watt,Graham,",
    "wof:placetype":"venue"
},
  "geometry": {"coordinates":[-1.4994720221,53.8276062012],"type":"Point"}
}