{
  "type": "Feature",
  "properties": {
    "iso:country":"GB",
    "sg:address":"9 Lovells Close",
    "sg:city":"Lightwater",
    "sg:classifiers":[
        {
            "category":"Home & Garden",
            "subcategory":"Household Appliances",
            "type":"Retail Goods"
        }
    ],
    "sg:phone":"+44 1276 476184",
    "sg:postcode":"GU18 5RS",
    "sg:province":"Surrey",
    "sg:tags":[
        "electrical"
    ],
    "wof:name":"John May",
    "wof:placetype":"venue"
},
  "geometry": {"coordinates":[-0.668514,51.35276],"type":"Point"}
}