{
  "type": "Feature",
  "properties": {
    "iso:country":"GB",
    "sg:address":"60 Corstorphine High St",
    "sg:city":"Edinburgh",
    "sg:classifiers":[
        {
            "category":"Professional",
            "type":"Services"
        }
    ],
    "sg:phone":"+44 131 334 9666",
    "sg:postcode":"EH12 7SY",
    "sg:province":"City of Edinburgh",
    "sg:tags":[
        "interior",
        "furnishers",
        "designer"
    ],
    "wof:name":"Diana McIntosh Town & Country Interiors",
    "wof:placetype":"venue"
},
  "geometry": {"coordinates":[-3.2929999828,55.9420928955],"type":"Point"}
}