{
  "type": "Feature",
  "properties": {
    "addr:full":"59 Chestnut Avenue Kirkcaldy Fife KY1 2LS",
    "addr:housenumber":"59",
    "addr:postcode":"ky1 2ls",
    "addr:street":"Chestnut Avenue",
    "iso:country":"GB",
    "sg:address":"59 Chestnut Avenue",
    "sg:city":"Kirkcaldy",
    "sg:classifiers":[
        {
            "category":"Fast Food",
            "type":"Food & Drink"
        }
    ],
    "sg:phone":"+44 1592 646446",
    "sg:postcode":"KY1 2LS",
    "sg:province":"Fife",
    "sg:tags":[
        "away",
        "take"
    ],
    "wof:name":"Konya Take Away",
    "wof:placetype":"venue"
},
  "geometry": {"coordinates":[-3.1563949585,56.1279563904],"type":"Point"}
}