{
  "type": "Feature",
  "properties": {
    "iso:country":"GB",
    "sg:address":"30 Queens View",
    "sg:city":"Southampton",
    "sg:classifiers":[
        {
            "category":"Building & Trades",
            "subcategory":"Construction",
            "type":"Services"
        }
    ],
    "sg:phone":"+44 23 8045 6451",
    "sg:postcode":"SO31 5EA",
    "sg:province":"Hampshire",
    "sg:tags":[
        "decorator",
        "painter"
    ],
    "wof:name":"Dennetts Decor",
    "wof:placetype":"venue"
},
  "geometry": {"coordinates":[-1.349229,50.877316],"type":"Point"}
}