{
  "type": "Feature",
  "properties": {
    "addr:full":"413 Stratford Road, Shirley Birmingham West Midlands B90 4AA",
    "addr:housenumber":"413",
    "addr:postcode":"b90 4aa",
    "addr:street":"Stratford Road",
    "iso:country":"GB",
    "sg:address":"413 Stratford Road, Shirley",
    "sg:city":"Birmingham",
    "sg:classifiers":[
        {
            "category":"Shopping",
            "subcategory":"Pets & Pet Supplies",
            "type":"Retail Goods"
        }
    ],
    "sg:phone":"+44 121 745 9336",
    "sg:postcode":"B90 4AA",
    "sg:province":"West Midlands",
    "wof:name":"The Pet Centre Shirley Ltd.",
    "wof:placetype":"venue"
},
  "geometry": {"coordinates":[-1.822603,52.405205],"type":"Point"}
}