{
  "type": "Feature",
  "properties": {
    "iso:country":"GB",
    "sg:address":", Llangristiolus",
    "sg:city":"Bodorgan",
    "sg:classifiers":[
        {
            "category":"Education",
            "subcategory":"School",
            "type":"Public Place"
        }
    ],
    "sg:phone":"+44 1248 723944",
    "sg:postcode":"LL62 5DR",
    "sg:province":"Isle of Anglesey",
    "sg:tags":[
        "local",
        "authority"
    ],
    "wof:name":"Ysgol Henblas School",
    "wof:placetype":"venue"
},
  "geometry": {"coordinates":[-4.4229488373,53.1828117371],"type":"Point"}
}