{
  "type": "Feature",
  "properties": {
    "addr:full":"Congress House, 23-28 Great Russell St Bloomsbury Greater London WC1B 3PX",
    "addr:housenumber":"23-28",
    "addr:postcode":"wc1b 3px",
    "addr:street":"Great Russell St",
    "iso:country":"GB",
    "sg:address":"Congress House, 23-28 Great Russell St",
    "sg:city":"Bloomsbury",
    "sg:classifiers":[
        {
            "category":"Professional",
            "subcategory":"Advertising",
            "type":"Services"
        }
    ],
    "sg:phone":"+44 20 7753 0038",
    "sg:postcode":"WC1B 3PX",
    "sg:province":"Greater London",
    "sg:tags":[
        "medium"
    ],
    "wof:name":"Ideal Media Company",
    "wof:placetype":"venue"
},
  "geometry": {"coordinates":[-0.1304969937,51.517036438],"type":"Point"}
}