{
  "type": "Feature",
  "properties": {
    "addr:full":"Po Box 111 Chichester West Sussex PO19 5ZS",
    "addr:housenumber":"po",
    "addr:postcode":"po19 5zs",
    "addr:street":"Box 111",
    "iso:country":"GB",
    "sg:address":"Po Box 111",
    "sg:city":"Chichester",
    "sg:classifiers":[
        {
            "category":"Professional",
            "subcategory":"Engineering",
            "type":"Services"
        }
    ],
    "sg:postcode":"PO19 5ZS",
    "sg:province":"West Sussex",
    "sg:tags":[
        "electronic",
        "engineer"
    ],
    "wof:name":"Elmac Services",
    "wof:placetype":"venue"
},
  "geometry": {"coordinates":[-0.775429,50.836166],"type":"Point"}
}