{
  "type": "Feature",
  "properties": {
    "addr:full":"Midton Road Ayr South Ayrshire KA7 2SE",
    "addr:postcode":"ka7 2se",
    "addr:street":"Midton Road",
    "iso:country":"GB",
    "sg:address":"Midton Road",
    "sg:city":"Ayr",
    "sg:classifiers":[
        {
            "category":"Place Of Worship",
            "type":"Public Place"
        }
    ],
    "sg:phone":"+44 1292 269524",
    "sg:postcode":"KA7 2SE",
    "sg:province":"South Ayrshire",
    "wof:name":"ST COLUMBA CHURCH",
    "wof:placetype":"venue"
},
  "geometry": {"coordinates":[-4.629532,55.45583],"type":"Point"}
}