{
  "type": "Feature",
  "properties": {
    "iso:country":"GB",
    "sg:address":"129 Kilburn High Road, Kilburn",
    "sg:city":"London",
    "sg:classifiers":[
        {
            "category":"Fast Food",
            "type":"Food & Drink"
        }
    ],
    "sg:phone":"+44 20 7624 9559",
    "sg:postcode":"NW6 6JH",
    "sg:province":"Greater London",
    "sg:tags":[
        "away",
        "take"
    ],
    "wof:name":"McDonalds Restaurants Ltd.",
    "wof:placetype":"venue"
},
  "geometry": {"coordinates":[-0.1954289973,51.5395278931],"type":"Point"}
}