{
  "type": "Feature",
  "properties": {
    "addr:full":"2a Creighton Avenue, East Ham London Greater London E6 3DS",
    "addr:housenumber":"2a",
    "addr:postcode":"e6 3ds",
    "addr:street":"Creighton Avenue",
    "iso:country":"GB",
    "sg:address":"2a Creighton Avenue, East Ham",
    "sg:city":"London",
    "sg:classifiers":[
        {
            "category":"Building & Trades",
            "subcategory":"Construction",
            "type":"Services"
        }
    ],
    "sg:phone":"+44 7956 282300",
    "sg:postcode":"E6 3DS",
    "sg:province":"Greater London",
    "sg:tags":[
        "builder"
    ],
    "wof:name":"Carmelcrest Ltd.",
    "wof:placetype":"venue"
},
  "geometry": {"coordinates":[0.040733,51.53043],"type":"Point"}
}