{
  "type": "Feature",
  "properties": {
    "addr:full":"192c The Broadway Broadstone Dorset BH18 8DH",
    "addr:housenumber":"192c",
    "addr:postcode":"bh18 8dh",
    "addr:street":"The Broadway",
    "iso:country":"GB",
    "sg:address":"192c The Broadway",
    "sg:city":"Broadstone",
    "sg:classifiers":[
        {
            "category":"Shopping",
            "subcategory":"Pharmacy",
            "type":"Retail Goods"
        }
    ],
    "sg:phone":"+44 1202 692320",
    "sg:postcode":"BH18 8DH",
    "sg:province":"Dorset",
    "sg:tags":[
        "pharmacist",
        "chemist"
    ],
    "wof:name":"Hills Pharmacy",
    "wof:placetype":"venue"
},
  "geometry": {"coordinates":[-1.9968789816,50.7625198364],"type":"Point"}
}