{
  "type": "Feature",
  "properties": {
    "addr:full":"School Street, Ton Pentre Pentre Rhondda, Cynon, Taff CF41 7LS",
    "addr:postcode":"cf41 7ls",
    "addr:street":"School Street;Pentre Pentre;Cynon Taff",
    "iso:country":"GB",
    "sg:address":"School Street, Ton Pentre",
    "sg:city":"Pentre",
    "sg:classifiers":[
        {
            "category":"Education",
            "subcategory":"School",
            "type":"Public Place"
        }
    ],
    "sg:phone":"+44 1443 435438",
    "sg:postcode":"CF41 7LS",
    "sg:province":"Rhondda, Cynon, Taff",
    "sg:tags":[
        "local",
        "authority"
    ],
    "wof:name":"Ton Infant School",
    "wof:placetype":"venue"
},
  "geometry": {"coordinates":[-3.486203,51.644753],"type":"Point"}
}