{
  "type": "Feature",
  "properties": {
    "addr:full":"43 Holmhurst La St Leonards-on-sea East Sussex TN37 7LN",
    "addr:housenumber":"43;leonards-on-sea",
    "addr:postcode":"tn37 7ln",
    "addr:street":"Holmhurst La St",
    "iso:country":"GB",
    "sg:address":"43 Holmhurst La",
    "sg:city":"St Leonards-on-sea",
    "sg:classifiers":[
        {
            "category":"Building & Trades",
            "subcategory":"Construction",
            "type":"Services"
        }
    ],
    "sg:postcode":"TN37 7LN",
    "sg:province":"East Sussex",
    "sg:tags":[
        "builder"
    ],
    "wof:name":"M & O",
    "wof:placetype":"venue"
},
  "geometry": {"coordinates":[0.5525090098,50.8845291138],"type":"Point"}
}