{
  "type": "Feature",
  "properties": {
    "iso:country":"GB",
    "sg:address":"Henley Farm, Henley",
    "sg:city":"Ludlow",
    "sg:classifiers":[
        {
            "category":"Farming",
            "subcategory":"Farm",
            "type":"Manufacturing & Wholesale Goods"
        }
    ],
    "sg:phone":"+44 1584 872852",
    "sg:postcode":"SY8 3ET",
    "sg:province":"Herefordshire",
    "sg:tags":[
        "mixed",
        "crop"
    ],
    "wof:name":"T J Hamer & Son",
    "wof:placetype":"venue"
},
  "geometry": {"coordinates":[-2.6750440598,52.3835258484],"type":"Point"}
}