{
  "type": "Feature",
  "properties": {
    "addr:full":"58 Queen Ann Street London Greater London W1G 8LA",
    "addr:housenumber":"58",
    "addr:postcode":"w1g 8la",
    "addr:street":"Queen Ann Street",
    "iso:country":"GB",
    "sg:address":"58 Queen Ann Street",
    "sg:city":"London",
    "sg:classifiers":[
        {
            "category":"Organizations",
            "subcategory":"Community Association",
            "type":"Services"
        }
    ],
    "sg:phone":"+44 20 7224 4400",
    "sg:postcode":"W1G 8LA",
    "sg:province":"Greater London",
    "sg:tags":[
        "relation",
        "public"
    ],
    "wof:name":"Colin Lewis P R",
    "wof:placetype":"venue"
},
  "geometry": {"coordinates":[-0.1489800066,51.5178413391],"type":"Point"}
}