{
  "type": "Feature",
  "properties": {
    "iso:country":"GB",
    "sg:address":"24c St Johns Road",
    "sg:city":"Sandown",
    "sg:classifiers":[
        {
            "category":"Personal",
            "subcategory":"Beauty Salon",
            "type":"Services"
        }
    ],
    "sg:postcode":"PO36 8ES",
    "sg:province":"Isle of Wight",
    "sg:tags":[
        "unisex",
        "hairdresser"
    ],
    "wof:name":"Top Knot",
    "wof:placetype":"venue"
},
  "geometry": {"coordinates":[-1.154913,50.654972],"type":"Point"}
}