{
  "type": "Feature",
  "properties": {
    "iso:country":"GB",
    "sg:address":"Bramley Road",
    "sg:city":"London",
    "sg:classifiers":[
        {
            "category":"Sports & Exercise",
            "subcategory":"Stables",
            "type":"Entertainment"
        }
    ],
    "sg:phone":"+44 20 8363 8630",
    "sg:postcode":"N14 4XF",
    "sg:province":"Greater London",
    "sg:tags":[
        "education",
        "equestrian"
    ],
    "wof:name":"Trent Park Equestrian Centre",
    "wof:placetype":"venue"
},
  "geometry": {"coordinates":[-0.127761,51.650097],"type":"Point"}
}