{
  "type": "Feature",
  "properties": {
    "addr:full":"Meikle Barfil, Crocketford Dumfries Dumfries and Galloway DG2 8RP",
    "addr:postcode":"dg2 8rp",
    "iso:country":"GB",
    "sg:address":"Meikle Barfil, Crocketford",
    "sg:city":"Dumfries",
    "sg:classifiers":[
        {
            "category":"Professional",
            "subcategory":"Computer Services",
            "type":"Services"
        }
    ],
    "sg:phone":"+44 1556 690243",
    "sg:postcode":"DG2 8RP",
    "sg:province":"Dumfries and Galloway",
    "sg:tags":[
        "system",
        "software"
    ],
    "wof:name":"Alex Johnson",
    "wof:placetype":"venue"
},
  "geometry": {"coordinates":[-3.834654,55.03669],"type":"Point"}
}