{
  "type": "Feature",
  "properties": {
    "addr:full":"44 Hanbury Road, Stoke Heath Bromsgrove Worcestershire B60 4LU",
    "addr:housenumber":"44",
    "addr:postcode":"b60 4lu",
    "addr:street":"Hanbury Road",
    "iso:country":"GB",
    "sg:address":"44 Hanbury Road, Stoke Heath",
    "sg:city":"Bromsgrove",
    "sg:classifiers":[
        {
            "category":"Bars & Pubs",
            "type":"Food & Drink"
        },
        {
            "category":"Community Center",
            "subcategory":"Social",
            "type":"Public Place"
        }
    ],
    "sg:phone":"+44 1527 577187",
    "sg:postcode":"B60 4LU",
    "sg:province":"Worcestershire",
    "sg:tags":[
        "pubs",
        "house",
        "inn",
        "activity"
    ],
    "wof:name":"The Hanbury Turn",
    "wof:placetype":"venue"
},
  "geometry": {"coordinates":[-2.076574,52.311707],"type":"Point"}
}