{
  "type": "Feature",
  "properties": {
    "iso:country":"GB",
    "sg:address":"7 Deer Park Road, Moulton Park Industrial Estate",
    "sg:city":"Northampton",
    "sg:classifiers":[
        {
            "category":"Home & Garden",
            "subcategory":"Carpets & Floor Coverings",
            "type":"Retail Goods"
        }
    ],
    "sg:phone":"+44 1604 790080",
    "sg:postcode":"NN3 6RX",
    "sg:province":"Northamptonshire",
    "sg:tags":[
        "textile",
        "floorcoverings"
    ],
    "wof:name":"Kelgar Ltd.",
    "wof:placetype":"venue"
},
  "geometry": {"coordinates":[-0.871641,52.275829],"type":"Point"}
}