{
  "type": "Feature",
  "properties": {
    "iso:country":"GB",
    "sg:address":"23c St Peters Hill",
    "sg:city":"Grantham",
    "sg:classifiers":[
        {
            "category":"Arena",
            "subcategory":"Sports Club",
            "type":"Entertainment"
        }
    ],
    "sg:phone":"+44 1476 564525",
    "sg:postcode":"NG31 6QF",
    "sg:province":"Lincolnshire",
    "wof:name":"Grantham Billiard Club",
    "wof:placetype":"venue"
},
  "geometry": {"coordinates":[-0.640607,52.90992],"type":"Point"}
}