{
  "type": "Feature",
  "properties": {
    "addr:full":"7 Green Avenue London Greater London NW7 4PX",
    "addr:housenumber":"7",
    "addr:postcode":"nw7 4px",
    "addr:street":"Green Avenue",
    "iso:country":"GB",
    "sg:address":"7 Green Avenue",
    "sg:city":"London",
    "sg:classifiers":[
        {
            "category":"Professional",
            "type":"Services"
        }
    ],
    "sg:postcode":"NW7 4PX",
    "sg:province":"Greater London",
    "sg:tags":[
        "entertainer"
    ],
    "wof:name":"Bookers (U K) Theatrical Agency",
    "wof:placetype":"venue"
},
  "geometry": {"coordinates":[-0.2539359927,51.622177124],"type":"Point"}
}