{
  "type": "Feature",
  "properties": {
    "iso:country":"GB",
    "sg:address":"22 The Crown Mill, Princess St",
    "sg:city":"Lincoln",
    "sg:classifiers":[
        {
            "category":"Building & Trades",
            "subcategory":"Construction",
            "type":"Services"
        }
    ],
    "sg:postcode":"LN5 7QD",
    "sg:province":"Lincolnshire",
    "sg:tags":[
        "roofing"
    ],
    "wof:name":"Griffin,J C,Electrical Ltd",
    "wof:placetype":"venue"
},
  "geometry": {"coordinates":[-0.542038,53.226086],"type":"Point"}
}