{
  "type": "Feature",
  "properties": {
    "iso:country":"GB",
    "sg:address":"Rushton Hall, Tarrant Rushton",
    "sg:city":"Blandford Forum",
    "sg:classifiers":[
        {
            "category":"Banks & Credit Unions",
            "subcategory":"Financial Services",
            "type":"Services"
        }
    ],
    "sg:phone":"+44 1258 456000",
    "sg:postcode":"DT11 8SD",
    "sg:province":"Dorset",
    "sg:tags":[
        "adviser"
    ],
    "wof:name":"Denzil Beckhurst & Associates",
    "wof:placetype":"venue"
},
  "geometry": {"coordinates":[-2.091049,50.851601],"type":"Point"}
}