{
  "type": "Feature",
  "properties": {
    "iso:country":"GB",
    "sg:address":"43-46 Queens Road",
    "sg:city":"Brighton",
    "sg:classifiers":[
        {
            "category":"Banks & Credit Unions",
            "subcategory":"Financial Services",
            "type":"Services"
        }
    ],
    "sg:phone":"+44 1273 821177",
    "sg:postcode":"BN1 3XB",
    "sg:province":"East Sussex",
    "sg:tags":[
        "adviser"
    ],
    "wof:name":"R J Temple Plc",
    "wof:placetype":"venue"
},
  "geometry": {"coordinates":[-0.142266,50.826668],"type":"Point"}
}