{
  "type": "Feature",
  "properties": {
    "addr:full":"6 Kingsland Grange Warrington Cheshire WA1 4RW",
    "addr:housenumber":"6",
    "addr:postcode":"wa1 4rw",
    "addr:street":"Kingsland Grange",
    "iso:country":"GB",
    "sg:address":"6 Kingsland Grange",
    "sg:city":"Warrington",
    "sg:classifiers":[
        {
            "category":"Building & Trades",
            "subcategory":"Construction",
            "type":"Services"
        }
    ],
    "sg:phone":"+44 1925 817222",
    "sg:postcode":"WA1 4RW",
    "sg:province":"Cheshire",
    "sg:tags":[
        "fork",
        "lift",
        "truck"
    ],
    "wof:name":"B T Rolatruc Ltd.",
    "wof:placetype":"venue"
},
  "geometry": {"coordinates":[-2.5314490795,53.4093742371],"type":"Point"}
}