{
  "type": "Feature",
  "properties": {
    "addr:full":"G/1 Unit, Dudley Central Trading Estate, Shaw Road Dudley West Midlands DY2 8QX",
    "addr:housenumber":"/ 1 unit dudley;trading estate",
    "addr:postcode":"dy2 8qx",
    "addr:street":"Shaw Road",
    "iso:country":"GB",
    "sg:address":"G/1 Unit, Dudley Central Trading Estate, Shaw Road",
    "sg:city":"Dudley",
    "sg:classifiers":[
        {
            "category":"Manufacturing",
            "subcategory":"Metals",
            "type":"Manufacturing & Wholesale Goods"
        }
    ],
    "sg:phone":"+44 1384 240800",
    "sg:postcode":"DY2 8QX",
    "sg:province":"West Midlands",
    "sg:tags":[
        "steel",
        "stockholder"
    ],
    "wof:name":"Banding & Strapping Supplies Ltd",
    "wof:placetype":"venue"
},
  "geometry": {"coordinates":[-2.0835089684,52.5095214844],"type":"Point"}
}