{
  "type": "Feature",
  "properties": {
    "addr:full":"Unit 4, Rock Hill, 59 Wellsway, Keynsham Bristol City of Bristol BS31 1PF",
    "addr:housenumber":"unit 4;59",
    "addr:postcode":"bs31 1pf",
    "addr:street":"Rock Hill;Keynsham",
    "iso:country":"GB",
    "sg:address":"Unit 4, Rock Hill, 59 Wellsway, Keynsham",
    "sg:city":"Bristol",
    "sg:classifiers":[
        {
            "category":"Home & Garden",
            "subcategory":"Building Materials",
            "type":"Retail Goods"
        }
    ],
    "sg:phone":"+44 117 986 9882",
    "sg:postcode":"BS31 1PF",
    "sg:province":"City of Bristol",
    "sg:tags":[
        "wire",
        "cable"
    ],
    "wof:name":"M & M Cables Ltd",
    "wof:placetype":"venue"
},
  "geometry": {"coordinates":[-2.4964289665,51.4144706726],"type":"Point"}
}