{
  "type": "Feature",
  "properties": {
    "addr:full":"New Farm Frome Somerset BA11 5LY",
    "addr:postcode":"ba11 5ly",
    "iso:country":"GB",
    "sg:address":"New Farm",
    "sg:city":"Frome",
    "sg:classifiers":[
        {
            "category":"Farming",
            "subcategory":"Dairy Farm",
            "type":"Manufacturing & Wholesale Goods"
        }
    ],
    "sg:phone":"+44 1373 462663",
    "sg:postcode":"BA11 5LY",
    "sg:province":"Somerset",
    "wof:name":"P P Coleman",
    "wof:placetype":"venue"
},
  "geometry": {"coordinates":[-2.306053,51.230537],"type":"Point"}
}