{
  "type": "Feature",
  "properties": {
    "addr:full":"Old Buckenham Attleborough Norfolk NR17 1RS",
    "addr:housenumber":"old buckenham",
    "addr:postcode":"nr17 1rs",
    "iso:country":"GB",
    "sg:address":"Old Buckenham",
    "sg:city":"Attleborough",
    "sg:classifiers":[
        {
            "category":"Farming",
            "subcategory":"Livestock Farm",
            "type":"Manufacturing & Wholesale Goods"
        }
    ],
    "sg:phone":"+44 1953 860612",
    "sg:postcode":"NR17 1RS",
    "sg:province":"Norfolk",
    "sg:tags":[
        "stud"
    ],
    "wof:name":"Old Buckenham stud Ltd.",
    "wof:placetype":"venue"
},
  "geometry": {"coordinates":[1.0263750553,52.5102615356],"type":"Point"}
}