{
  "type": "Feature",
  "properties": {
    "addr:full":"65 New Road, Netley Abbey Southampton Hampshire SO31 5AD",
    "addr:housenumber":"65",
    "addr:postcode":"so31 5ad",
    "addr:street":"New Road",
    "iso:country":"GB",
    "sg:address":"65 New Road, Netley Abbey",
    "sg:city":"Southampton",
    "sg:classifiers":[
        {
            "category":"Retail",
            "subcategory":"Repair Shop",
            "type":"Services"
        }
    ],
    "sg:phone":"+44 23 8045 5250",
    "sg:postcode":"SO31 5AD",
    "sg:province":"Hampshire",
    "sg:tags":[
        "maintenance"
    ],
    "wof:name":"Refix Maintenance Ltd.",
    "wof:placetype":"venue"
},
  "geometry": {"coordinates":[-1.35175,50.873306],"type":"Point"}
}