{
  "type": "Feature",
  "properties": {
    "iso:country":"GB",
    "sg:address":"Adamton House, Monkton",
    "sg:city":"Prestwick",
    "sg:classifiers":[
        {
            "category":"Education",
            "subcategory":"Special Training",
            "type":"Public Place"
        }
    ],
    "sg:phone":"+44 1292 470722",
    "sg:postcode":"KA9 2SQ",
    "sg:province":"South Ayrshire",
    "sg:tags":[
        "school",
        "flying"
    ],
    "wof:name":"British Aerospace Flying College",
    "wof:placetype":"venue"
},
  "geometry": {"coordinates":[-4.5992507935,55.5167922974],"type":"Point"}
}