{
  "type": "Feature",
  "properties": {
    "addr:full":"Dept Of Micro Biology, Medical Bldgs, Peviot Pl Edinburgh City of Edinburgh EH8 9AG",
    "addr:postcode":"eh8 9ag",
    "addr:street":"Pl",
    "iso:country":"GB",
    "sg:address":"Dept Of Micro Biology, Medical Bldgs, Peviot Pl",
    "sg:city":"Edinburgh",
    "sg:classifiers":[
        {
            "category":"Education",
            "subcategory":"University",
            "type":"Public Place"
        }
    ],
    "sg:phone":"+44 131 650 1000",
    "sg:postcode":"EH8 9AG",
    "sg:province":"City of Edinburgh",
    "sg:tags":[
        "medical",
        "school"
    ],
    "wof:name":"University of Edinburgh (The)",
    "wof:placetype":"venue"
},
  "geometry": {"coordinates":[-3.190320015,55.9444503784],"type":"Point"}
}