{
  "type": "Feature",
  "properties": {
    "iso:country":"GB",
    "sg:address":"83 Tylacelyn Road, Pen Y Craig",
    "sg:city":"Tonypandy",
    "sg:classifiers":[
        {
            "category":"Communications",
            "type":"Services"
        },
        {
            "category":"Professional",
            "subcategory":"Computer Services",
            "type":"Services"
        }
    ],
    "sg:phone":"+44 1443 433520",
    "sg:postcode":"CF40 1LA",
    "sg:province":"Rhondda, Cynon, Taff",
    "sg:tags":[
        "tv",
        "video",
        "radio",
        "system",
        "software"
    ],
    "wof:name":"Robert L Gibbons",
    "wof:placetype":"venue"
},
  "geometry": {"coordinates":[-3.4482,51.614723],"type":"Point"}
}