{
  "type": "Feature",
  "properties": {
    "iso:country":"GB",
    "sg:address":"C/o Spear & Jackson, International Ltd Atlas Way",
    "sg:city":"Sheffield",
    "sg:classifiers":[
        {
            "category":"Professional",
            "subcategory":"Engineering",
            "type":"Services"
        }
    ],
    "sg:postcode":"S4 7QQ",
    "sg:province":"South Yorkshire",
    "wof:name":"Russell Bros (Sheffield) Ltd.",
    "wof:placetype":"venue"
},
  "geometry": {"coordinates":[-1.44325,53.39806],"type":"Point"}
}