{
  "type": "Feature",
  "properties": {
    "addr:full":"23 Lambeth Road Croydon Surrey CR0 3LS",
    "addr:housenumber":"23",
    "addr:postcode":"cr0 3ls",
    "addr:street":"Lambeth Road",
    "iso:country":"GB",
    "sg:address":"23 Lambeth Road",
    "sg:city":"Croydon",
    "sg:classifiers":[
        {
            "category":"Professional",
            "subcategory":"Engineering",
            "type":"Services"
        }
    ],
    "sg:postcode":"CR0 3LS",
    "sg:province":"Surrey",
    "sg:tags":[
        "contractor",
        "electrical",
        "engineer"
    ],
    "wof:name":"Scotts Electrical Services",
    "wof:placetype":"venue"
},
  "geometry": {"coordinates":[-0.111668,51.381805],"type":"Point"}
}