{
  "type": "Feature",
  "properties": {
    "addr:full":"270 Longford Road Cannock Staffordshire WS11 1NE",
    "addr:housenumber":"270",
    "addr:postcode":"ws11 1ne",
    "addr:street":"Longford Road",
    "iso:country":"GB",
    "sg:address":"270 Longford Road",
    "sg:city":"Cannock",
    "sg:classifiers":[
        {
            "category":"Health Services",
            "subcategory":"Clinic",
            "type":"Services"
        }
    ],
    "sg:phone":"+44 1543 462741",
    "sg:postcode":"WS11 1NE",
    "sg:province":"Staffordshire",
    "sg:tags":[
        "aromatherapy"
    ],
    "wof:name":"Victorian Collection Ltd.",
    "wof:placetype":"venue"
},
  "geometry": {"coordinates":[-2.0443890095,52.6870193481],"type":"Point"}
}