{
  "type": "Feature",
  "properties": {
    "iso:country":"GB",
    "sg:address":"Croft Bank, Croft",
    "sg:city":"Skegness",
    "sg:classifiers":[
        {
            "category":"Food & Beverages",
            "subcategory":"Chocolate",
            "type":"Retail Goods"
        }
    ],
    "sg:phone":"+44 1754 880431",
    "sg:postcode":"PE24 4AW",
    "sg:province":"Lincolnshire",
    "sg:tags":[
        "packer"
    ],
    "wof:name":"T A Smith & Co. (Farm Produce) Ltd.",
    "wof:placetype":"venue"
},
  "geometry": {"coordinates":[0.297668,53.135414],"type":"Point"}
}