{
  "type": "Feature",
  "properties": {
    "iso:country":"GB",
    "sg:address":"125 Victoria Road West",
    "sg:city":"Thornton-cleveleys",
    "sg:classifiers":[
        {
            "category":"Retail",
            "subcategory":"Repair Shop",
            "type":"Services"
        }
    ],
    "sg:phone":"+44 1253 853923",
    "sg:postcode":"FY5 3LA",
    "sg:province":"Lancashire",
    "sg:tags":[
        "clocks",
        "watch"
    ],
    "wof:name":"Geoffrey Tolson",
    "wof:placetype":"venue"
},
  "geometry": {"coordinates":[-3.0373311043,53.8766365051],"type":"Point"}
}