{
  "type": "Feature",
  "properties": {
    "iso:country":"GB",
    "sg:address":"Hillcrest Lodge, Overthorpe",
    "sg:city":"Banbury",
    "sg:classifiers":[
        {
            "category":"Professional",
            "subcategory":"Engineering",
            "type":"Services"
        }
    ],
    "sg:postcode":"OX17 2AF",
    "sg:province":"Northamptonshire",
    "sg:tags":[
        "consulting",
        "engineer"
    ],
    "wof:name":"O.D.P. Ltd",
    "wof:placetype":"venue"
},
  "geometry": {"coordinates":[-1.298669,52.062866],"type":"Point"}
}