{
  "type": "Feature",
  "properties": {
    "addr:full":"4 Briggate Leeds West Yorkshire LS1 4AF",
    "addr:housenumber":"4",
    "addr:postcode":"ls1 4af",
    "addr:street":"Briggate Leeds West",
    "iso:country":"GB",
    "sg:address":"4 Briggate",
    "sg:city":"Leeds",
    "sg:classifiers":[
        {
            "category":"Health Services",
            "subcategory":"Dentist",
            "type":"Services"
        }
    ],
    "sg:phone":"+44 113 245 2100",
    "sg:postcode":"LS1 4AF",
    "sg:province":"West Yorkshire",
    "wof:name":"Briggate Dental Practice",
    "wof:placetype":"venue"
},
  "geometry": {"coordinates":[-1.5424040556,53.7946243286],"type":"Point"}
}