{
  "type": "Feature",
  "properties": {
    "iso:country":"GB",
    "sg:address":"52 Findon Rd, Ifield",
    "sg:city":"Crawley",
    "sg:classifiers":[
        {
            "category":"Manufacturing",
            "subcategory":"Buildings",
            "type":"Manufacturing & Wholesale Goods"
        }
    ],
    "sg:phone":"+44 1293 615431",
    "sg:postcode":"RH11 0BQ",
    "sg:province":"West Sussex",
    "sg:tags":[
        "system",
        "air conditioning"
    ],
    "wof:name":"Dexair Services Ltd",
    "wof:placetype":"venue"
},
  "geometry": {"coordinates":[-0.20558,51.123394],"type":"Point"}
}