{
  "type": "Feature",
  "properties": {
    "addr:full":"2 Aston Clo Liversedge West Yorkshire WF15 7QW",
    "addr:housenumber":"2",
    "addr:postcode":"wf15 7qw",
    "addr:street":"Aston Clo Liversedge West",
    "iso:country":"GB",
    "sg:address":"2 Aston Clo",
    "sg:city":"Liversedge",
    "sg:classifiers":[
        {
            "category":"Farming",
            "subcategory":"Dairy Farm",
            "type":"Manufacturing & Wholesale Goods"
        }
    ],
    "sg:postcode":"WF15 7QW",
    "sg:province":"West Yorkshire",
    "wof:name":"Clough,Geoffrey,",
    "wof:placetype":"venue"
},
  "geometry": {"coordinates":[-1.701844,53.698612],"type":"Point"}
}