{
  "type": "Feature",
  "properties": {
    "addr:full":"14 Dornton Road South Croydon Surrey CR2 7DP",
    "addr:housenumber":"14",
    "addr:postcode":"cr2 7dp",
    "addr:street":"Dornton Road",
    "iso:country":"GB",
    "sg:address":"14 Dornton Road",
    "sg:city":"South Croydon",
    "sg:classifiers":[
        {
            "category":"Shopping",
            "subcategory":"Antiques",
            "type":"Retail Goods"
        }
    ],
    "sg:phone":"+44 20 8681 3010",
    "sg:postcode":"CR2 7DP",
    "sg:province":"Surrey",
    "wof:name":"Royston Restoration",
    "wof:placetype":"venue"
},
  "geometry": {"coordinates":[-0.0910950005,51.3608436584],"type":"Point"}
}