{
  "type": "Feature",
  "properties": {
    "addr:full":"52d Crossdale Street Cromer Norfolk NR27 9LB",
    "addr:housenumber":"52d",
    "addr:postcode":"nr27 9lb",
    "addr:street":"Crossdale Street",
    "iso:country":"GB",
    "sg:address":"52d Crossdale Street",
    "sg:city":"Cromer",
    "sg:classifiers":[
        {
            "category":"Building & Trades",
            "subcategory":"Construction",
            "type":"Services"
        }
    ],
    "sg:postcode":"NR27 9LB",
    "sg:province":"Norfolk",
    "sg:tags":[
        "builder"
    ],
    "wof:name":"R J Barber",
    "wof:placetype":"venue"
},
  "geometry": {"coordinates":[1.310449,52.898281],"type":"Point"}
}