{
  "type": "Feature",
  "properties": {
    "addr:full":"Colonial Bldgs, 59-61 Hatton Gdn London Greater London EC1N 8LS",
    "addr:housenumber":"59-61",
    "addr:postcode":"ec1n 8ls",
    "addr:street":"Hatton Gdn",
    "iso:country":"GB",
    "sg:address":"Colonial Bldgs, 59-61 Hatton Gdn",
    "sg:city":"London",
    "sg:classifiers":[
        {
            "category":"Manufacturing",
            "subcategory":"Jewelry",
            "type":"Manufacturing & Wholesale Goods"
        }
    ],
    "sg:postcode":"EC1N 8LS",
    "sg:province":"Greater London",
    "sg:tags":[
        "repair",
        "jewellery"
    ],
    "wof:name":"Panayi,Phodi,",
    "wof:placetype":"venue"
},
  "geometry": {"coordinates":[-0.1089899987,51.5214996338],"type":"Point"}
}