{
  "type": "Feature",
  "properties": {
    "addr:full":"189 Waterloo Road London Greater London SE1 8UX",
    "addr:housenumber":"189",
    "addr:postcode":"se1 8ux",
    "addr:street":"Waterloo Road",
    "iso:country":"GB",
    "sg:address":"189 Waterloo Road",
    "sg:city":"London",
    "sg:classifiers":[
        {
            "category":"Fast Food",
            "type":"Food & Drink"
        }
    ],
    "sg:phone":"+44 20 7928 5222",
    "sg:postcode":"SE1 8UX",
    "sg:province":"Greater London",
    "sg:tags":[
        "away",
        "take"
    ],
    "wof:name":"Chinese Canteen",
    "wof:placetype":"venue"
},
  "geometry": {"coordinates":[-0.108099,51.50061],"type":"Point"}
}