{
  "type": "Feature",
  "properties": {
    "addr:full":"79 The Close, Gunns Farm Liphook Hampshire GU30 7HL",
    "addr:housenumber":"79",
    "addr:postcode":"gu30 7hl",
    "addr:street":"The Close Gunns Farm Liphook",
    "iso:country":"GB",
    "sg:address":"79 The Close, Gunns Farm",
    "sg:city":"Liphook",
    "sg:classifiers":[
        {
            "category":"Building & Trades",
            "subcategory":"Cleaning & Sanitation",
            "type":"Services"
        }
    ],
    "sg:phone":"+44 1428 722979",
    "sg:postcode":"GU30 7HL",
    "sg:province":"Hampshire",
    "sg:tags":[
        "cleaner",
        "window"
    ],
    "wof:name":"I F Heath & Son",
    "wof:placetype":"venue"
},
  "geometry": {"coordinates":[-0.8004059792,51.0701522827],"type":"Point"}
}