{
  "type": "Feature",
  "properties": {
    "addr:full":"21-23 West Street Fareham Hampshire PO16 0BG",
    "addr:housenumber":"21-23",
    "addr:postcode":"po16 0bg",
    "addr:street":"West Street",
    "iso:country":"GB",
    "sg:address":"21-23 West Street",
    "sg:city":"Fareham",
    "sg:classifiers":[
        {
            "category":"Professional",
            "subcategory":"Employment Agencies",
            "type":"Services"
        }
    ],
    "sg:phone":"+44 1329 823211",
    "sg:postcode":"PO16 0BG",
    "sg:province":"Hampshire",
    "sg:tags":[
        "consultant"
    ],
    "wof:name":"Manpower Plc",
    "wof:placetype":"venue"
},
  "geometry": {"coordinates":[-1.1762100458,50.8524780273],"type":"Point"}
}