{
  "type": "Feature",
  "properties": {
    "iso:country":"GB",
    "sg:address":"East Warehouse, Glasgow Fruit Market, Blochairn Road",
    "sg:city":"Glasgow",
    "sg:classifiers":[
        {
            "category":"Wholesale",
            "subcategory":"Fruits & Vegetables",
            "type":"Manufacturing & Wholesale Goods"
        }
    ],
    "sg:phone":"+44 141 552 1131",
    "sg:postcode":"G21 2SW",
    "sg:province":"East Dunbartonshire",
    "wof:name":"Chiquita (Scotland) Ltd.",
    "wof:placetype":"venue"
},
  "geometry": {"coordinates":[-4.21461,55.867512],"type":"Point"}
}