{
  "type": "Feature",
  "properties": {
    "iso:country":"GB",
    "sg:address":"39 Bridge Street",
    "sg:city":"Fakenham",
    "sg:classifiers":[
        {
            "category":"Retail",
            "subcategory":"Repair Shop",
            "type":"Services"
        }
    ],
    "sg:phone":"+44 1328 862194",
    "sg:postcode":"NR21 9AG",
    "sg:province":"Norfolk",
    "sg:tags":[
        "upholstering",
        "upholsterer"
    ],
    "wof:name":"J Spalding & Son",
    "wof:placetype":"venue"
},
  "geometry": {"coordinates":[0.8488439918,52.8289375305],"type":"Point"}
}