{
  "type": "Feature",
  "properties": {
    "addr:full":"15 Arden Clo Market Harborough Leicestershire LE16 7DA",
    "addr:housenumber":"15;clo",
    "addr:postcode":"le16 7da",
    "addr:street":"Arden",
    "iso:country":"GB",
    "sg:address":"15 Arden Clo",
    "sg:city":"Market Harborough",
    "sg:classifiers":[
        {
            "category":"Professional",
            "subcategory":"Computer Services",
            "type":"Services"
        }
    ],
    "sg:phone":"+44 1858 465636",
    "sg:postcode":"LE16 7DA",
    "sg:province":"Leicestershire",
    "sg:tags":[
        "consultant"
    ],
    "wof:name":"Jaysys Computers",
    "wof:placetype":"venue"
},
  "geometry": {"coordinates":[-0.9110450149,52.4837913513],"type":"Point"}
}