{
  "type": "Feature",
  "properties": {
    "addr:full":"3 Horse St Bristol City of Bristol BS17 6DA",
    "addr:housenumber":"3",
    "addr:postcode":"bs17 6da",
    "addr:street":"Horse St",
    "iso:country":"GB",
    "sg:address":"3 Horse St",
    "sg:city":"Bristol",
    "sg:classifiers":[
        {
            "category":"Health Services",
            "subcategory":"Health Practitioner",
            "type":"Services"
        }
    ],
    "sg:phone":"+44 1454 326256",
    "sg:postcode":"BS17 6DA",
    "sg:province":"City of Bristol",
    "sg:tags":[
        "osteopath"
    ],
    "wof:name":"Nicolette Stevens",
    "wof:placetype":"venue"
},
  "geometry": {"coordinates":[-2.391568,51.538532],"type":"Point"}
}