{
  "type": "Feature",
  "properties": {
    "addr:full":"34 Maple Gro Brentford Greater London TW8 8NJ",
    "addr:housenumber":"34",
    "addr:postcode":"tw8 8nj",
    "addr:street":"Maple Gro Brentford",
    "iso:country":"GB",
    "sg:address":"34 Maple Gro",
    "sg:city":"Brentford",
    "sg:classifiers":[
        {
            "category":"Building & Trades",
            "subcategory":"Landscaping Services",
            "type":"Services"
        }
    ],
    "sg:phone":"+44 20 8560 9611",
    "sg:postcode":"TW8 8NJ",
    "sg:province":"Greater London",
    "sg:tags":[
        "gardening"
    ],
    "wof:name":"Ace Garden Services",
    "wof:placetype":"venue"
},
  "geometry": {"coordinates":[-0.319647,51.483566],"type":"Point"}
}