{
  "type": "Feature",
  "properties": {
    "addr:full":"63 High Street Alton Hampshire GU34 1AF",
    "addr:housenumber":"63",
    "addr:postcode":"gu34 1af",
    "addr:street":"High Street",
    "iso:country":"GB",
    "sg:address":"63 High Street",
    "sg:city":"Alton",
    "sg:classifiers":[
        {
            "category":"Professional",
            "subcategory":"Employment Agencies",
            "type":"Services"
        }
    ],
    "sg:postcode":"GU34 1AF",
    "sg:province":"Hampshire",
    "sg:tags":[
        "consultant"
    ],
    "wof:name":"Quest Recruitment Ltd.",
    "wof:placetype":"venue"
},
  "geometry": {"coordinates":[-0.9767199755,51.1477966309],"type":"Point"}
}