{
  "type": "Feature",
  "properties": {
    "addr:full":"Unit 5a East Grinstead East Sussex RH19 4DW",
    "addr:housenumber":"unit 5a",
    "addr:postcode":"rh19 4dw",
    "iso:country":"GB",
    "sg:address":"Unit 5a",
    "sg:city":"East Grinstead",
    "sg:classifiers":[
        {
            "category":"Home & Garden",
            "subcategory":"Household Appliances",
            "type":"Retail Goods"
        }
    ],
    "sg:phone":"+44 1342 325500",
    "sg:postcode":"RH19 4DW",
    "sg:province":"East Sussex",
    "sg:tags":[
        "domestic",
        "sales",
        "centre"
    ],
    "wof:name":"Top Of The Town",
    "wof:placetype":"venue"
},
  "geometry": {"coordinates":[-0.04551,51.106937],"type":"Point"}
}