{
  "type": "Feature",
  "properties": {
    "addr:full":"2 Potter Street, Spondon Derby Derbyshire DE21 7LH",
    "addr:housenumber":"2",
    "addr:postcode":"de21 7lh",
    "addr:street":"Potter Street",
    "iso:country":"GB",
    "sg:address":"2 Potter Street, Spondon",
    "sg:city":"Derby",
    "sg:classifiers":[
        {
            "category":"Utilities",
            "subcategory":"Fuel Oil & Lpg",
            "type":"Services"
        }
    ],
    "sg:phone":"+44 1332 663396",
    "sg:postcode":"DE21 7LH",
    "sg:province":"Derbyshire",
    "sg:tags":[
        "merchant",
        "coal",
        "smokeless"
    ],
    "wof:name":"G E Fearn",
    "wof:placetype":"venue"
},
  "geometry": {"coordinates":[-1.4074399471,52.9196014404],"type":"Point"}
}