{
  "type": "Feature",
  "properties": {
    "iso:country":"GB",
    "sg:address":"1412 High Rd",
    "sg:city":"Broxbourne",
    "sg:classifiers":[
        {
            "category":"Wholesale",
            "subcategory":"Books, Periodicals, & Newspapers",
            "type":"Manufacturing & Wholesale Goods"
        }
    ],
    "sg:phone":"+44 20 8449 1111",
    "sg:postcode":"EN10 7HP",
    "sg:province":"Essex",
    "sg:tags":[
        "publishing"
    ],
    "wof:name":"European Group,The",
    "wof:placetype":"venue"
},
  "geometry": {"coordinates":[-0.015664,51.752079],"type":"Point"}
}