{
  "type": "Feature",
  "properties": {
    "iso:country":"GB",
    "sg:address":"13 Livingstone Way, The Acorn Centre",
    "sg:city":"Taunton",
    "sg:classifiers":[
        {
            "category":"Manufacturing",
            "subcategory":"Petroleum Products",
            "type":"Manufacturing & Wholesale Goods"
        }
    ],
    "sg:phone":"+44 1823 279716",
    "sg:postcode":"TA2 6BD",
    "sg:province":"Somerset",
    "sg:tags":[
        "double",
        "glazing"
    ],
    "wof:name":"Pro-Fit Windows Ltd.",
    "wof:placetype":"venue"
},
  "geometry": {"coordinates":[-3.1277639866,51.0259513855],"type":"Point"}
}