{
  "type": "Feature",
  "properties": {
    "iso:country":"GB",
    "sg:address":"10 St  Leonards Rd",
    "sg:city":"Newton Abbot",
    "sg:classifiers":[
        {
            "category":"Social Services",
            "subcategory":"Child Care",
            "type":"Services"
        }
    ],
    "sg:postcode":"TQ12 1JX",
    "sg:province":"Devon",
    "sg:tags":[
        "childminders"
    ],
    "wof:name":"Fenson,Sarah,",
    "wof:placetype":"venue"
},
  "geometry": {"coordinates":[-3.614598,50.528675],"type":"Point"}
}