{
  "type": "Feature",
  "properties": {
    "iso:country":"GB",
    "sg:address":"125 Bad Bargain Lane",
    "sg:city":"York",
    "sg:classifiers":[
        {
            "category":"Food & Beverages",
            "subcategory":"Supermarket",
            "type":"Retail Goods"
        }
    ],
    "sg:phone":"+44 1904 415891",
    "sg:postcode":"YO3 0PF",
    "sg:province":"East Riding of Yorkshire",
    "wof:name":"Tates Late Shopper",
    "wof:placetype":"venue"
},
  "geometry": {"coordinates":[-1.0458929539,53.9656486511],"type":"Point"}
}