{
  "type": "Feature",
  "properties": {
    "iso:country":"GB",
    "sg:address":"Forest Road, New Ollerton",
    "sg:city":"Newark",
    "sg:classifiers":[
        {
            "category":"Bars & Pubs",
            "type":"Food & Drink"
        }
    ],
    "sg:phone":"+44 1623 860205",
    "sg:postcode":"NG22 9QS",
    "sg:province":"Nottinghamshire",
    "sg:tags":[
        "pubs",
        "inn"
    ],
    "wof:name":"The Plough Inn",
    "wof:placetype":"venue"
},
  "geometry": {"coordinates":[-1.012026,53.203442],"type":"Point"}
}