{
  "type": "Feature",
  "properties": {
    "iso:country":"GB",
    "sg:address":"Enterprise House, 127 Bute Street",
    "sg:city":"Cardiff",
    "sg:classifiers":[
        {
            "category":"Organizations",
            "subcategory":"Non-profit Organization",
            "type":"Services"
        }
    ],
    "sg:phone":"+44 29 2049 5875",
    "sg:postcode":"CF10 5LE",
    "sg:province":"Cardiff",
    "sg:tags":[
        "organisation",
        "voluntary",
        "charity"
    ],
    "wof:name":"The Princes Youth Business Trust",
    "wof:placetype":"venue"
},
  "geometry": {"coordinates":[-3.166631,51.466763],"type":"Point"}
}