{
  "type": "Feature",
  "properties": {
    "addr:full":"1 Sedlescombe Park Rugby Warwickshire CV22 6HL",
    "addr:housenumber":"1",
    "addr:postcode":"cv22 6hl",
    "addr:street":"Sedlescombe Park",
    "iso:country":"GB",
    "sg:address":"1 Sedlescombe Park",
    "sg:city":"Rugby",
    "sg:classifiers":[
        {
            "category":"Health Services",
            "subcategory":"Doctor",
            "type":"Services"
        }
    ],
    "sg:phone":"+44 1788 814476",
    "sg:postcode":"CV22 6HL",
    "sg:province":"Warwickshire",
    "sg:tags":[
        "surgeon"
    ],
    "wof:name":"G.A.G Mogg",
    "wof:placetype":"venue"
},
  "geometry": {"coordinates":[-1.269043,52.359211],"type":"Point"}
}