{
  "type": "Feature",
  "properties": {
    "iso:country":"GB",
    "sg:address":"5 Cornelia St",
    "sg:city":"Motherwell",
    "sg:classifiers":[
        {
            "category":"Building & Trades",
            "subcategory":"Landscaping Services",
            "type":"Services"
        }
    ],
    "sg:phone":"+44 1698 324959",
    "sg:postcode":"ML1 3RY",
    "sg:province":"North Lanarkshire",
    "sg:tags":[
        "gardening"
    ],
    "wof:name":"Landscape Gardening Services",
    "wof:placetype":"venue"
},
  "geometry": {"coordinates":[-4.01216,55.799656],"type":"Point"}
}