{
  "type": "Feature",
  "properties": {
    "addr:full":"61 Fullers Av Surbiton Surrey KT6 7TD",
    "addr:housenumber":"61",
    "addr:postcode":"kt6 7td",
    "addr:street":"Fullers Av",
    "iso:country":"GB",
    "sg:address":"61 Fullers Av",
    "sg:city":"Surbiton",
    "sg:classifiers":[
        {
            "category":"Home & Garden",
            "subcategory":"Carpets & Floor Coverings",
            "type":"Retail Goods"
        }
    ],
    "sg:phone":"+44 20 8397 9046",
    "sg:postcode":"KT6 7TD",
    "sg:province":"Surrey",
    "sg:tags":[
        "cleaner",
        "upholstery"
    ],
    "wof:name":"Carpet Care",
    "wof:placetype":"venue"
},
  "geometry": {"coordinates":[-0.2962290049,51.3772964478],"type":"Point"}
}