{
  "type": "Feature",
  "properties": {
    "addr:full":"34 Swan Street, Northgate Leicester Leicestershire LE3 5AW",
    "addr:housenumber":"34",
    "addr:postcode":"le3 5aw",
    "addr:street":"Swan Street",
    "iso:country":"GB",
    "sg:address":"34 Swan Street, Northgate",
    "sg:city":"Leicester",
    "sg:classifiers":[
        {
            "category":"Shopping",
            "subcategory":"Clothing, Apparel, & Fashions",
            "type":"Retail Goods"
        }
    ],
    "sg:phone":"+44 116 251 7221",
    "sg:postcode":"LE3 5AW",
    "sg:province":"Leicestershire",
    "sg:tags":[
        "clothing"
    ],
    "wof:name":"L H Barnett Ltd.",
    "wof:placetype":"venue"
},
  "geometry": {"coordinates":[-1.143282,52.639091],"type":"Point"}
}