{
  "type": "Feature",
  "properties": {
    "iso:country":"GB",
    "sg:address":"London Heathrow Airport",
    "sg:city":"Hounslow",
    "sg:classifiers":[
        {
            "category":"Shopping",
            "subcategory":"Shoes",
            "type":"Retail Goods"
        }
    ],
    "sg:phone":"+44 20 8897 0313",
    "sg:postcode":"TW6 1EW",
    "sg:province":"Greater London",
    "sg:tags":[
        "shop"
    ],
    "wof:name":"Bally Shoe Shop",
    "wof:placetype":"venue"
},
  "geometry": {"coordinates":[-0.452934,51.472454],"type":"Point"}
}