{
  "type": "Feature",
  "properties": {
    "addr:full":"Poynton House, Shropshire Street Market Drayton Shropshire TF9 3DD",
    "addr:postcode":"tf9 3dd",
    "addr:street":"Shropshire Street",
    "iso:country":"GB",
    "sg:address":"Poynton House, Shropshire Street",
    "sg:city":"Market Drayton",
    "sg:classifiers":[
        {
            "category":"Shopping",
            "type":"Retail Goods"
        }
    ],
    "sg:phone":"+44 1270 506840",
    "sg:postcode":"TF9 3DD",
    "sg:province":"Shropshire",
    "sg:tags":[
        "merchant"
    ],
    "wof:name":"Agriforce West Ltd.",
    "wof:placetype":"venue"
},
  "geometry": {"coordinates":[-2.484174,52.90374],"type":"Point"}
}