{
  "type": "Feature",
  "properties": {
    "iso:country":"GB",
    "sg:address":"New Museum Site, Downing St",
    "sg:city":"Cambridge",
    "sg:classifiers":[
        {
            "category":"Museum",
            "subcategory":"Art Museum",
            "type":"Entertainment"
        }
    ],
    "sg:phone":"+44 1223 336650",
    "sg:postcode":"CB2 3EJ",
    "sg:province":"Cambridgeshire",
    "sg:tags":[
        "gallery"
    ],
    "wof:name":"University Museum Of Zoology",
    "wof:placetype":"venue"
},
  "geometry": {"coordinates":[0.12156,52.202831],"type":"Point"}
}