{
  "type": "Feature",
  "properties": {
    "addr:full":"60 Union Street Ryde Isle of Wight PO33 2LG",
    "addr:housenumber":"60",
    "addr:postcode":"po33 2lg",
    "addr:street":"Union Street",
    "iso:country":"GB",
    "sg:address":"60 Union Street",
    "sg:city":"Ryde",
    "sg:classifiers":[
        {
            "category":"Manufacturing",
            "subcategory":"Jewelry",
            "type":"Manufacturing & Wholesale Goods"
        }
    ],
    "sg:phone":"+44 1983 563247",
    "sg:postcode":"PO33 2LG",
    "sg:province":"Isle of Wight",
    "sg:tags":[
        "repair",
        "jewellery"
    ],
    "wof:name":"Bernard Mitchell Ltd.",
    "wof:placetype":"venue"
},
  "geometry": {"coordinates":[-1.162036,50.731487],"type":"Point"}
}