{
  "type": "Feature",
  "properties": {
    "addr:full":"Headon Industrial Estate, Nether Headon Retford Nottinghamshire DN22 0PA",
    "addr:postcode":"dn22 0pa",
    "addr:street":"Estate Nether Headon",
    "iso:country":"GB",
    "sg:address":"Headon Industrial Estate, Nether Headon",
    "sg:city":"Retford",
    "sg:classifiers":[
        {
            "category":"Manufacturing",
            "subcategory":"Metals",
            "type":"Manufacturing & Wholesale Goods"
        }
    ],
    "sg:phone":"+44 1777 248250",
    "sg:postcode":"DN22 0PA",
    "sg:province":"Nottinghamshire",
    "sg:tags":[
        "steel",
        "fabricator",
        "erectors"
    ],
    "wof:name":"Crown Engineering Ltd.",
    "wof:placetype":"venue"
},
  "geometry": {"coordinates":[-0.878099,53.283855],"type":"Point"}
}