{
  "type": "Feature",
  "properties": {
    "iso:country":"GB",
    "sg:address":"Fore Street, Langtree",
    "sg:city":"Torrington",
    "sg:classifiers":[
        {
            "category":"Government",
            "subcategory":"Post Office",
            "type":"Public Place"
        }
    ],
    "sg:phone":"+44 1805 601209",
    "sg:postcode":"EX38 8NG",
    "sg:province":"Devon",
    "wof:name":"Langtree Post Office",
    "wof:placetype":"venue"
},
  "geometry": {"coordinates":[-4.142996,50.952316],"type":"Point"}
}