{
  "type": "Feature",
  "properties": {
    "iso:country":"GB",
    "sg:address":"2 Pilgrims Close, Chandlers Ford",
    "sg:city":"Southampton",
    "sg:classifiers":[
        {
            "category":"Personal",
            "subcategory":"Beauty Salon",
            "type":"Services"
        }
    ],
    "sg:phone":"+44 23 8025 3701",
    "sg:postcode":"SO53 4ST",
    "sg:province":"Hampshire",
    "sg:tags":[
        "unisex",
        "hairdresser"
    ],
    "wof:name":"March Hair",
    "wof:placetype":"venue"
},
  "geometry": {"coordinates":[-1.401509,50.978161],"type":"Point"}
}