{
  "type": "Feature",
  "properties": {
    "addr:full":"19 Ogbourne Close, Longlevens Gloucester Gloucestershire GL2 0HU",
    "addr:housenumber":"19",
    "addr:postcode":"gl2 0hu",
    "addr:street":"Ogbourne Close",
    "iso:country":"GB",
    "sg:address":"19 Ogbourne Close, Longlevens",
    "sg:city":"Gloucester",
    "sg:classifiers":[
        {
            "category":"Building & Trades",
            "subcategory":"Plumbing",
            "type":"Services"
        }
    ],
    "sg:phone":"+44 1452 306144",
    "sg:postcode":"GL2 0HU",
    "sg:province":"Gloucestershire",
    "sg:tags":[
        "heating"
    ],
    "wof:name":"Terry Gardner",
    "wof:placetype":"venue"
},
  "geometry": {"coordinates":[-2.2010450363,51.8741264343],"type":"Point"}
}