{
  "type": "Feature",
  "properties": {
    "addr:full":"36 Mortimore Road Gosport Hampshire PO12 3BJ",
    "addr:housenumber":"36",
    "addr:postcode":"po12 3bj",
    "addr:street":"Mortimore Road",
    "iso:country":"GB",
    "sg:address":"36 Mortimore Road",
    "sg:city":"Gosport",
    "sg:classifiers":[
        {
            "category":"Building & Trades",
            "subcategory":"Construction",
            "type":"Services"
        }
    ],
    "sg:postcode":"PO12 3BJ",
    "sg:province":"Hampshire",
    "sg:tags":[
        "dry",
        "lining",
        "plasterers",
        "screeders"
    ],
    "wof:name":"Albert Kemp",
    "wof:placetype":"venue"
},
  "geometry": {"coordinates":[-1.1533260345,50.8045082092],"type":"Point"}
}