{
  "type": "Feature",
  "properties": {
    "addr:full":"29 Sedlescombe Road North St Leonards-on-sea East Sussex TN37 7DA",
    "addr:housenumber":"29",
    "addr:postcode":"tn37 7da",
    "addr:street":"Sedlescombe Road North St Leonards-On-Sea",
    "iso:country":"GB",
    "sg:address":"29 Sedlescombe Road North",
    "sg:city":"St Leonards-on-sea",
    "sg:classifiers":[
        {
            "category":"Retail",
            "subcategory":"Funeral Services",
            "type":"Services"
        }
    ],
    "sg:postcode":"TN37 7DA",
    "sg:province":"East Sussex",
    "wof:name":"D C Mercer & Son",
    "wof:placetype":"venue"
},
  "geometry": {"coordinates":[0.556392,50.86853],"type":"Point"}
}