{
  "type": "Feature",
  "properties": {
    "iso:country":"GB",
    "sg:address":"Unit 17 Poulton Close Business Park, Coombe Valley Road",
    "sg:city":"Dover",
    "sg:classifiers":[
        {
            "category":"Autos & Motor Vehicles",
            "subcategory":"Automobile Sales",
            "type":"Retail Goods"
        }
    ],
    "sg:phone":"+44 1304 213040",
    "sg:postcode":"CT17 0HL",
    "sg:province":"Kent",
    "wof:name":"Seat Specialist Operations Centre",
    "wof:placetype":"venue"
},
  "geometry": {"coordinates":[1.284353,51.130348],"type":"Point"}
}