{
  "type": "Feature",
  "properties": {
    "addr:full":"18 Church Street, Eccles Manchester Greater Manchester M30 0DF",
    "addr:housenumber":"18",
    "addr:postcode":"m30 0df",
    "addr:street":"Church Street",
    "iso:country":"GB",
    "sg:address":"18 Church Street, Eccles",
    "sg:city":"Manchester",
    "sg:classifiers":[
        {
            "category":"Shopping",
            "subcategory":"Baby Store",
            "type":"Retail Goods"
        }
    ],
    "sg:phone":"+44 161 789 5579",
    "sg:postcode":"M30 0DF",
    "sg:province":"Greater Manchester",
    "sg:tags":[
        "nursery",
        "accessory"
    ],
    "wof:name":"Wheelaways",
    "wof:placetype":"venue"
},
  "geometry": {"coordinates":[-2.335052,53.484985],"type":"Point"}
}