{
  "type": "Feature",
  "properties": {
    "iso:country":"GB",
    "sg:address":"18 Church Street, Eccles",
    "sg:city":"Manchester",
    "sg:classifiers":[
        {
            "category":"Shopping",
            "subcategory":"Baby Store",
            "type":"Retail Goods"
        }
    ],
    "sg:phone":"+44 161 789 5579",
    "sg:postcode":"M30 0DF",
    "sg:province":"Greater Manchester",
    "sg:tags":[
        "nursery",
        "accessory"
    ],
    "wof:name":"Wheelaways",
    "wof:placetype":"venue"
},
  "geometry": {"coordinates":[-2.335052,53.484985],"type":"Point"}
}