{
  "type": "Feature",
  "properties": {
    "iso:country":"GB",
    "sg:address":"Presbytery, 57 East Meadway",
    "sg:city":"Birmingham",
    "sg:classifiers":[
        {
            "category":"Place Of Worship",
            "type":"Public Place"
        }
    ],
    "sg:phone":"+44 121 783 3537",
    "sg:postcode":"B33 0AU",
    "sg:province":"West Midlands",
    "wof:name":"Our Lady Help Of Christians",
    "wof:placetype":"venue"
},
  "geometry": {"coordinates":[-1.7615590096,52.4823913574],"type":"Point"}
}