{
  "type": "Feature",
  "properties": {
    "iso:country":"GB",
    "sg:address":"The Vicarage, London Rd",
    "sg:city":"Milton Keynes",
    "sg:classifiers":[
        {
            "category":"Place Of Worship",
            "type":"Public Place"
        }
    ],
    "sg:phone":"+44 1908 562148",
    "sg:postcode":"MK11 1JA",
    "sg:province":"Buckinghamshire",
    "wof:name":"Stony Stratford Parish Church",
    "wof:placetype":"venue"
},
  "geometry": {"coordinates":[-0.8499199748,52.0553512573],"type":"Point"}
}