{
  "type": "Feature",
  "properties": {
    "addr:full":"5 High Street, Silverstone Towcester Buckinghamshire NN12 8US",
    "addr:housenumber":"5",
    "addr:postcode":"nn12 8us",
    "addr:street":"High Street",
    "iso:country":"GB",
    "sg:address":"5 High Street, Silverstone",
    "sg:city":"Towcester",
    "sg:classifiers":[
        {
            "category":"Government",
            "subcategory":"Post Office",
            "type":"Public Place"
        }
    ],
    "sg:phone":"+44 1327 857244",
    "sg:postcode":"NN12 8US",
    "sg:province":"Buckinghamshire",
    "wof:name":"Silverstone Post Office & Stores",
    "wof:placetype":"venue"
},
  "geometry": {"coordinates":[-1.011103,52.172832],"type":"Point"}
}