{
  "type": "Feature",
  "properties": {
    "iso:country":"GB",
    "sg:address":"844-860 Garratt Lane, Tooting",
    "sg:city":"London",
    "sg:classifiers":[
        {
            "category":"Autos & Motor Vehicles",
            "subcategory":"Automobile Sales",
            "type":"Retail Goods"
        }
    ],
    "sg:phone":"+44 20 8672 1200",
    "sg:postcode":"SW17 0LP",
    "sg:province":"Greater London",
    "sg:tags":[
        "car"
    ],
    "wof:name":"Elite Motors Ltd.",
    "wof:placetype":"venue"
},
  "geometry": {"coordinates":[-0.17459,51.42997],"type":"Point"}
}