{
  "type": "Feature",
  "properties": {
    "addr:full":"97 Marsh Lane Bootle Merseyside L20 4JB",
    "addr:housenumber":"97",
    "addr:postcode":"l20 4jb",
    "addr:street":"Marsh Lane",
    "iso:country":"GB",
    "sg:address":"97 Marsh Lane",
    "sg:city":"Bootle",
    "sg:classifiers":[
        {
            "category":"Personal",
            "subcategory":"Beauty Salon",
            "type":"Services"
        }
    ],
    "sg:phone":"+44 151 933 8869",
    "sg:postcode":"L20 4JB",
    "sg:province":"Merseyside",
    "sg:tags":[
        "unisex",
        "hairdresser"
    ],
    "wof:name":"Creations",
    "wof:placetype":"venue"
},
  "geometry": {"coordinates":[-3.001455,53.455524],"type":"Point"}
}