{
  "type": "Feature",
  "properties": {
    "iso:country":"GB",
    "sg:address":"1 Copthall House, Station Square",
    "sg:city":"Coventry",
    "sg:classifiers":[
        {
            "category":"Real Estate",
            "subcategory":"Architect",
            "type":"Services"
        }
    ],
    "sg:postcode":"CV1 2FS",
    "sg:province":"West Midlands",
    "wof:name":"W H Saunders & Son",
    "wof:placetype":"venue"
},
  "geometry": {"coordinates":[-1.514168,52.402191],"type":"Point"}
}