{
  "type": "Feature",
  "properties": {
    "addr:full":"Unit4, Dane Road Industrial Estate Sale Cheshire M33 7BH",
    "addr:postcode":"m33 7bh",
    "addr:street":"Unit4 Dane Road Industrial Estate",
    "iso:country":"GB",
    "sg:address":"Unit4, Dane Road Industrial Estate",
    "sg:city":"Sale",
    "sg:classifiers":[
        {
            "category":"Shopping",
            "subcategory":"Stationery & Office Supplies",
            "type":"Retail Goods"
        },
        {
            "category":"Manufacturing",
            "subcategory":"Wood Products",
            "type":"Manufacturing & Wholesale Goods"
        }
    ],
    "sg:phone":"+44 161 976 2006",
    "sg:postcode":"M33 7BH",
    "sg:province":"Cheshire",
    "sg:tags":[
        "packaging",
        "equipment",
        "crate",
        "pallets"
    ],
    "sg:website":"http://www.protpack.com",
    "wof:name":"Protective Packaging Ltd",
    "wof:placetype":"venue"
},
  "geometry": {"coordinates":[-2.312294,53.430367],"type":"Point"}
}