{
  "type": "Feature",
  "properties": {
    "addr:full":"Queens Road Marlow Berkshire SL7 2PU",
    "addr:postcode":"sl7 2pu",
    "addr:street":"Queens Road",
    "iso:country":"GB",
    "sg:address":"Queens Road",
    "sg:city":"Marlow",
    "sg:classifiers":[
        {
            "category":"Social Services",
            "subcategory":"Adult Care",
            "type":"Services"
        }
    ],
    "sg:phone":"+44 1628 484357",
    "sg:postcode":"SL7 2PU",
    "sg:province":"Berkshire",
    "sg:tags":[
        "housing",
        "sheltered"
    ],
    "wof:name":"Mayorfield House",
    "wof:placetype":"venue"
},
  "geometry": {"coordinates":[-0.781314,51.574589],"type":"Point"}
}