{
  "type": "Feature",
  "properties": {
    "addr:full":"Unit F4, Moore Lane Business Centre, Moor Lane Widnes Cheshire WA8 7AQ",
    "addr:housenumber":"f4",
    "addr:postcode":"wa8 7aq",
    "addr:street":"Moore Lane;Moor Lane",
    "iso:country":"GB",
    "sg:address":"Unit F4, Moore Lane Business Centre, Moor Lane",
    "sg:city":"Widnes",
    "sg:classifiers":[
        {
            "category":"Manufacturing",
            "subcategory":"Tobacco Products",
            "type":"Manufacturing & Wholesale Goods"
        }
    ],
    "sg:phone":"+44 151 420 0800",
    "sg:postcode":"WA8 7AQ",
    "sg:province":"Cheshire",
    "wof:name":"Big Jays",
    "wof:placetype":"venue"
},
  "geometry": {"coordinates":[-2.7408440113,53.3619003296],"type":"Point"}
}