{
  "type": "Feature",
  "properties": {
    "addr:full":"Kingswell Road, Kingsthorpe Village Northampton Northamptonshire NN2 6QB",
    "addr:postcode":"nn2 6qb",
    "addr:street":"Kingswell Road",
    "iso:country":"GB",
    "sg:address":"Kingswell Road, Kingsthorpe Village",
    "sg:city":"Northampton",
    "sg:classifiers":[
        {
            "category":"Farming",
            "subcategory":"Nursery",
            "type":"Manufacturing & Wholesale Goods"
        },
        {
            "category":"Social Services",
            "subcategory":"Child Care",
            "type":"Services"
        }
    ],
    "sg:phone":"+44 1604 715558",
    "sg:postcode":"NN2 6QB",
    "sg:province":"Northamptonshire",
    "sg:tags":[
        "creche"
    ],
    "wof:name":"Alphabet Day Nursery",
    "wof:placetype":"venue"
},
  "geometry": {"coordinates":[-0.904344,52.261017],"type":"Point"}
}