{
  "type": "Feature",
  "properties": {
    "iso:country":"GB",
    "sg:address":"8 St Stephens Cres",
    "sg:city":"Bayswater",
    "sg:classifiers":[
        {
            "category":"Health Services",
            "subcategory":"Clinic",
            "type":"Services"
        }
    ],
    "sg:phone":"+44 20 7243 0577",
    "sg:postcode":"W2 5QT",
    "sg:province":"Greater London",
    "sg:tags":[
        "aromatherapy"
    ],
    "wof:name":"Massage Far Eastern",
    "wof:placetype":"venue"
},
  "geometry": {"coordinates":[-0.194472,51.5182380676],"type":"Point"}
}