{
  "type": "Feature",
  "properties": {
    "addr:full":"27 Baxtergate, Freshney Place Grimsby Lincolnshire DN31 1QL",
    "addr:housenumber":"27",
    "addr:postcode":"dn31 1ql",
    "addr:street":"Baxtergate Freshney Place",
    "iso:country":"GB",
    "sg:address":"27 Baxtergate, Freshney Place",
    "sg:city":"Grimsby",
    "sg:classifiers":[
        {
            "category":"Shopping",
            "subcategory":"Clothing, Apparel, & Fashions",
            "type":"Retail Goods"
        }
    ],
    "sg:phone":"+44 1472 348736",
    "sg:postcode":"DN31 1QL",
    "sg:province":"Lincolnshire",
    "sg:tags":[
        "lingerie",
        "hosiery"
    ],
    "wof:name":"La Senza",
    "wof:placetype":"venue"
},
  "geometry": {"coordinates":[-0.0868399963,53.5662689209],"type":"Point"}
}