{
  "type": "Feature",
  "properties": {
    "iso:country":"GB",
    "sg:address":"25 Longbraes Gardens",
    "sg:city":"Kirkcaldy",
    "sg:classifiers":[
        {
            "category":"Professional",
            "subcategory":"Art Services",
            "type":"Services"
        }
    ],
    "sg:phone":"+44 1592 640917",
    "sg:postcode":"KY2 5YJ",
    "sg:province":"Fife",
    "sg:tags":[
        "photographer"
    ],
    "wof:name":"Thomas Edward Parish",
    "wof:placetype":"venue"
},
  "geometry": {"coordinates":[-3.1926469803,56.1216545105],"type":"Point"}
}