{
  "type": "Feature",
  "properties": {
    "addr:full":"Swansea Road, Gorseinon Swansea Carmarthenshire SA4 2HQ",
    "addr:postcode":"sa4 2hq",
    "addr:street":"Swansea Road",
    "iso:country":"GB",
    "sg:address":"Swansea Road, Gorseinon",
    "sg:city":"Swansea",
    "sg:classifiers":[
        {
            "category":"Retail",
            "subcategory":"Funeral Services",
            "type":"Services"
        },
        {
            "category":"Government",
            "subcategory":"Office",
            "type":"Public Place"
        }
    ],
    "sg:phone":"+44 1792 892836",
    "sg:postcode":"SA4 2HQ",
    "sg:province":"Carmarthenshire",
    "sg:tags":[
        "cemetery",
        "local",
        "crematorium"
    ],
    "wof:name":"Kingsbridge Cemetery",
    "wof:placetype":"venue"
},
  "geometry": {"coordinates":[-4.0412201881,51.6666717529],"type":"Point"}
}