{
  "type": "Feature",
  "properties": {
    "addr:full":"6 Drayton Gardens, Sutton Farm Shrewsbury Shropshire SY2 6HG",
    "addr:housenumber":"6",
    "addr:postcode":"sy2 6hg",
    "addr:street":"Drayton Gardens",
    "iso:country":"GB",
    "sg:address":"6 Drayton Gardens, Sutton Farm",
    "sg:city":"Shrewsbury",
    "sg:classifiers":[
        {
            "category":"Real Estate",
            "subcategory":"Architect",
            "type":"Services"
        }
    ],
    "sg:postcode":"SY2 6HG",
    "sg:province":"Shropshire",
    "wof:name":"The Shrewsbury  &  District Model Engine",
    "wof:placetype":"venue"
},
  "geometry": {"coordinates":[-2.7307579517,52.6900558472],"type":"Point"}
}