{
  "type": "Feature",
  "properties": {
    "addr:full":"Ellemund House, Fieldhead, Chirk Wrexham Wrexham LL14 5PT",
    "addr:postcode":"ll14 5pt",
    "addr:street":"Fieldhead",
    "iso:country":"GB",
    "sg:address":"Ellemund House, Fieldhead, Chirk",
    "sg:city":"Wrexham",
    "sg:classifiers":[
        {
            "category":"Retail",
            "subcategory":"Funeral Services",
            "type":"Services"
        }
    ],
    "sg:phone":"+44 1691 772462",
    "sg:postcode":"LL14 5PT",
    "sg:province":"Wrexham",
    "wof:name":"Edmund Rowlands & Son",
    "wof:placetype":"venue"
},
  "geometry": {"coordinates":[-3.0569889545,52.9329566956],"type":"Point"}
}