{
  "type": "Feature",
  "properties": {
    "addr:full":"53 Main Road, Totton Southampton Hampshire SO40 7EL",
    "addr:housenumber":"53",
    "addr:postcode":"so40 7el",
    "addr:street":"Main Road",
    "iso:country":"GB",
    "sg:address":"53 Main Road, Totton",
    "sg:city":"Southampton",
    "sg:classifiers":[
        {
            "category":"Bus Charters",
            "type":"Transportation"
        }
    ],
    "sg:phone":"+44 1946 820205",
    "sg:postcode":"SO40 7EL",
    "sg:province":"Hampshire",
    "sg:tags":[
        "hire",
        "coach"
    ],
    "wof:name":"S H Brownrigg Ltd.",
    "wof:placetype":"venue"
},
  "geometry": {"coordinates":[-1.497038,50.907009],"type":"Point"}
}