{
  "type": "Feature",
  "properties": {
    "addr:full":"The Street Cranbrook Kent TN17 4DB",
    "addr:postcode":"tn17 4db",
    "addr:street":"The Street",
    "iso:country":"GB",
    "sg:address":"The Street",
    "sg:city":"Cranbrook",
    "sg:classifiers":[
        {
            "category":"Shopping",
            "subcategory":"Department Store",
            "type":"Retail Goods"
        }
    ],
    "sg:phone":"+44 1580 240508",
    "sg:postcode":"TN17 4DB",
    "sg:province":"Kent",
    "wof:name":"Benenden Village Shop",
    "wof:placetype":"venue"
},
  "geometry": {"coordinates":[0.5770350099,51.0680732727],"type":"Point"}
}