{
  "type": "Feature",
  "properties": {
    "iso:country":"GB",
    "sg:address":"2 Whitehall St, Hipperholme",
    "sg:city":"Halifax",
    "sg:classifiers":[
        {
            "category":"Health Services",
            "subcategory":"Clinic",
            "type":"Services"
        }
    ],
    "sg:phone":"+44 1422 204898",
    "sg:postcode":"HX3 8NB",
    "sg:province":"West Yorkshire",
    "sg:tags":[
        "aromatherapy"
    ],
    "wof:name":"Ambergris",
    "wof:placetype":"venue"
},
  "geometry": {"coordinates":[-1.811773,53.725685],"type":"Point"}
}