{
  "type": "Feature",
  "properties": {
    "iso:country":"GB",
    "sg:address":"94 Commercial Road",
    "sg:city":"London",
    "sg:classifiers":[
        {
            "category":"Shopping",
            "subcategory":"Clothing, Apparel, & Fashions",
            "type":"Retail Goods"
        },
        {
            "category":"Manufacturing",
            "subcategory":"Textiles",
            "type":"Manufacturing & Wholesale Goods"
        }
    ],
    "sg:phone":"+44 20 7488 0952",
    "sg:postcode":"E1 1NU",
    "sg:province":"Greater London",
    "sg:tags":[
        "merchant",
        "clothing",
        "agent"
    ],
    "wof:name":"Newtrent Ltd.",
    "wof:placetype":"venue"
},
  "geometry": {"coordinates":[-0.065214999,51.5147476196],"type":"Point"}
}