{
  "type": "Feature",
  "properties": {
    "iso:country":"GB",
    "sg:address":"42-43 Swain St",
    "sg:city":"Watchet",
    "sg:classifiers":[
        {
            "category":"Food & Beverages",
            "subcategory":"Groceries & Convenience Stores",
            "type":"Retail Goods"
        }
    ],
    "sg:phone":"+44 1984 632298",
    "sg:postcode":"TA23 0AE",
    "sg:province":"Somerset",
    "wof:name":"Vg Late Stop",
    "wof:placetype":"venue"
},
  "geometry": {"coordinates":[-3.330168,51.180676],"type":"Point"}
}