{
  "type": "Feature",
  "properties": {
    "iso:country":"GB",
    "sg:address":"825a Osmaston Road",
    "sg:city":"Derby",
    "sg:classifiers":[
        {
            "category":"Professional",
            "subcategory":"Lawyer & Legal Services",
            "type":"Services"
        }
    ],
    "sg:phone":"+44 1332 365497",
    "sg:postcode":"DE24 9BQ",
    "sg:province":"Derbyshire",
    "sg:tags":[
        "solicitor"
    ],
    "wof:name":"Flint Bishop & Barnett",
    "wof:placetype":"venue"
},
  "geometry": {"coordinates":[-1.451899,52.890839],"type":"Point"}
}