{
  "type": "Feature",
  "properties": {
    "addr:full":"Riverside Studios, Crisp Rd Hammersmith Greater London W6 9RL",
    "addr:postcode":"w6 9rl",
    "addr:street":"Crisp Rd",
    "iso:country":"GB",
    "sg:address":"Riverside Studios, Crisp Rd",
    "sg:city":"Hammersmith",
    "sg:classifiers":[
        {
            "category":"Community Center",
            "subcategory":"Youth",
            "type":"Public Place"
        }
    ],
    "sg:phone":"+44 20 8237 1000",
    "sg:postcode":"W6 9RL",
    "sg:province":"Greater London",
    "sg:tags":[
        "organisation",
        "centre"
    ],
    "wof:name":"Rapscallions Theatre Workshop",
    "wof:placetype":"venue"
},
  "geometry": {"coordinates":[-0.233049,51.491783],"type":"Point"}
}