{
  "type": "Feature",
  "properties": {
    "iso:country":"GB",
    "sg:address":"133 Furtherwick Road",
    "sg:city":"Canvey Island",
    "sg:classifiers":[
        {
            "category":"Retail",
            "subcategory":"Laundry & Dry Cleaning",
            "type":"Services"
        }
    ],
    "sg:phone":"+44 1268 684235",
    "sg:postcode":"SS8 7AT",
    "sg:province":"Essex",
    "sg:tags":[
        "alteration"
    ],
    "wof:name":"Rays Quality Dry Cleaning",
    "wof:placetype":"venue"
},
  "geometry": {"coordinates":[0.593083,51.519531],"type":"Point"}
}