{
  "type": "Feature",
  "properties": {
    "addr:full":"304 Carshalton Road Carshalton Surrey SM5 3QB",
    "addr:housenumber":"304",
    "addr:postcode":"sm5 3qb",
    "addr:street":"Carshalton Road",
    "iso:country":"GB",
    "sg:address":"304 Carshalton Road",
    "sg:city":"Carshalton",
    "sg:classifiers":[
        {
            "category":"Shopping",
            "subcategory":"Books",
            "type":"Retail Goods"
        },
        {
            "category":"Shopping",
            "subcategory":"Used Merchandise",
            "type":"Retail Goods"
        }
    ],
    "sg:phone":"+44 20 8643 6857",
    "sg:postcode":"SM5 3QB",
    "sg:province":"Surrey",
    "sg:tags":[
        "second-hand",
        "secondhand"
    ],
    "wof:name":"Croydon Bookshop",
    "wof:placetype":"venue"
},
  "geometry": {"coordinates":[-0.173667,51.362972],"type":"Point"}
}