{
  "type": "Feature",
  "properties": {
    "addr:full":"4 Portfield Retail Park, Portfield Way Chichester West Sussex PO19 7YH",
    "addr:housenumber":"4",
    "addr:postcode":"po19 7yh",
    "addr:street":"Portfield Retail Park Portfield Way",
    "iso:country":"GB",
    "sg:address":"4 Portfield Retail Park, Portfield Way",
    "sg:city":"Chichester",
    "sg:classifiers":[
        {
            "category":"Home & Garden",
            "subcategory":"Hardware",
            "type":"Retail Goods"
        }
    ],
    "sg:phone":"+44 1243 532221",
    "sg:postcode":"PO19 7YH",
    "sg:province":"West Sussex",
    "sg:tags":[
        "retailer",
        "diy"
    ],
    "wof:name":"Homebase Ltd.",
    "wof:placetype":"venue"
},
  "geometry": {"coordinates":[-0.7754290104,50.8361663818],"type":"Point"}
}