{
  "type": "Feature",
  "properties": {
    "addr:full":"46 Hanover Street Stranraer Dumfries and Galloway DG9 7RP",
    "addr:housenumber":"46",
    "addr:postcode":"dg9 7rp",
    "addr:street":"Hanover Street",
    "iso:country":"GB",
    "sg:address":"46 Hanover Street",
    "sg:city":"Stranraer",
    "sg:classifiers":[
        {
            "category":"Restaurant",
            "type":"Food & Drink"
        }
    ],
    "sg:postcode":"DG9 7RP",
    "sg:province":"Dumfries and Galloway",
    "wof:name":"The Venezia",
    "wof:placetype":"venue"
},
  "geometry": {"coordinates":[-5.0244350433,54.90366745],"type":"Point"}
}