{
  "type": "Feature",
  "properties": {
    "iso:country":"GB",
    "sg:address":"Bramble Cottage, Chillaton",
    "sg:city":"Lifton",
    "sg:classifiers":[
        {
            "category":"Professional",
            "subcategory":"Secretarial Services",
            "type":"Services"
        }
    ],
    "sg:postcode":"PL16 0HS",
    "sg:province":"Devon",
    "wof:name":"A A Secretarial & Print Services",
    "wof:placetype":"venue"
},
  "geometry": {"coordinates":[-4.2831530571,50.6431655884],"type":"Point"}
}