{
  "type": "Feature",
  "properties": {
    "iso:country":"GB",
    "sg:address":"Stanley Street",
    "sg:city":"Consett",
    "sg:classifiers":[
        {
            "category":"Education",
            "subcategory":"School",
            "type":"Public Place"
        },
        {
            "category":"Government",
            "subcategory":"Office",
            "type":"Public Place"
        }
    ],
    "sg:phone":"+44 1207 503982",
    "sg:postcode":"DH8 6LN",
    "sg:province":"Durham",
    "sg:tags":[
        "local",
        "authority"
    ],
    "wof:name":"St Patricks R C Primary School",
    "wof:placetype":"venue"
},
  "geometry": {"coordinates":[-1.830689,54.855358],"type":"Point"}
}