{
  "type": "Feature",
  "properties": {
    "iso:country":"GB",
    "sg:address":"Old School Ho",
    "sg:city":"Gloucester",
    "sg:classifiers":[
        {
            "category":"Building & Trades",
            "subcategory":"Construction",
            "type":"Services"
        }
    ],
    "sg:phone":"+44 1452 501478",
    "sg:postcode":"GL2 8HL",
    "sg:province":"Gloucestershire",
    "sg:tags":[
        "builder"
    ],
    "wof:name":"Able Building & Maintenance Contractors",
    "wof:placetype":"venue"
},
  "geometry": {"coordinates":[-2.27716,51.89043],"type":"Point"}
}