{
  "type": "Feature",
  "properties": {
    "addr:full":"The Dene Cntr, Dorking General Hospital, Horsham Road Dorking Surrey RH4 2AA",
    "addr:postcode":"rh4 2aa",
    "addr:street":"The Dene Cntr;Horsham Road",
    "iso:country":"GB",
    "sg:address":"The Dene Cntr, Dorking General Hospital, Horsham Road",
    "sg:city":"Dorking",
    "sg:classifiers":[
        {
            "category":"Health Services",
            "subcategory":"Clinic",
            "type":"Services"
        }
    ],
    "sg:phone":"+44 1306 885910",
    "sg:postcode":"RH4 2AA",
    "sg:province":"Surrey",
    "sg:tags":[
        "nh"
    ],
    "wof:name":"National Health Service Executive Headqu",
    "wof:placetype":"venue"
},
  "geometry": {"coordinates":[-0.3288139999,51.233341217],"type":"Point"}
}