{
  "type": "Feature",
  "properties": {
    "addr:full":"43 Ballards Walk Basildon Essex SS15 5HL",
    "addr:housenumber":"43",
    "addr:postcode":"ss15 5hl",
    "addr:street":"Ballards Walk",
    "iso:country":"GB",
    "sg:address":"43 Ballards Walk",
    "sg:city":"Basildon",
    "sg:classifiers":[
        {
            "category":"Home & Garden",
            "subcategory":"Hardware",
            "type":"Retail Goods"
        }
    ],
    "sg:phone":"+44 1268 545211",
    "sg:postcode":"SS15 5HL",
    "sg:province":"Essex",
    "wof:name":"Robert Pullen",
    "wof:placetype":"venue"
},
  "geometry": {"coordinates":[0.44252,51.573257],"type":"Point"}
}