{
  "type": "Feature",
  "properties": {
    "addr:full":"85 Kenwyn Street Truro Cornwall TR1 3BZ",
    "addr:housenumber":"85",
    "addr:postcode":"tr1 3bz",
    "addr:street":"Kenwyn Street",
    "iso:country":"GB",
    "sg:address":"85 Kenwyn Street",
    "sg:city":"Truro",
    "sg:classifiers":[
        {
            "category":"Bars & Pubs",
            "type":"Food & Drink"
        }
    ],
    "sg:phone":"+44 1872 277532",
    "sg:postcode":"TR1 3BZ",
    "sg:province":"Cornwall",
    "sg:tags":[
        "pubs",
        "inn"
    ],
    "wof:name":"The Royal Standard",
    "wof:placetype":"venue"
},
  "geometry": {"coordinates":[-5.05606,50.263107],"type":"Point"}
}