{
  "type": "Feature",
  "properties": {
    "addr:full":"2 Tillydrone Shopping Centre, Hayton Rd Aberdeen Aberdeen City AB24 2UY",
    "addr:housenumber":"2",
    "addr:postcode":"ab24 2uy",
    "addr:street":"Shopping;Hayton Rd",
    "iso:country":"GB",
    "sg:address":"2 Tillydrone Shopping Centre, Hayton Rd",
    "sg:city":"Aberdeen",
    "sg:classifiers":[
        {
            "category":"Professional",
            "subcategory":"Management & Consulting",
            "type":"Services"
        }
    ],
    "sg:phone":"+44 1224 277880",
    "sg:postcode":"AB24 2UY",
    "sg:province":"Aberdeen City",
    "sg:tags":[
        "marketing",
        "consultant"
    ],
    "wof:name":"Great Northern Development Company",
    "wof:placetype":"venue"
},
  "geometry": {"coordinates":[-2.11443,57.172451],"type":"Point"}
}