{
  "type": "Feature",
  "properties": {
    "iso:country":"GB",
    "sg:address":"4 Swallow Lane",
    "sg:city":"Huddersfield",
    "sg:classifiers":[
        {
            "category":"Food & Beverages",
            "subcategory":"Fruits & Vegetables",
            "type":"Retail Goods"
        }
    ],
    "sg:phone":"+44 1484 640481",
    "sg:postcode":"HD7 4LU",
    "sg:province":"West Yorkshire",
    "sg:tags":[
        "greengrocer"
    ],
    "wof:name":"Peter Shaw",
    "wof:placetype":"venue"
},
  "geometry": {"coordinates":[-1.8561060429,53.6403656006],"type":"Point"}
}