{
  "type": "Feature",
  "properties": {
    "addr:full":"Toll House, The Beach Clevedon Somerset BS21 7QU",
    "addr:postcode":"bs21 7qu",
    "iso:country":"GB",
    "sg:address":"Toll House, The Beach",
    "sg:city":"Clevedon",
    "sg:classifiers":[
        {
            "category":"Arts & Performance",
            "subcategory":"Art Gallery",
            "type":"Entertainment"
        },
        {
            "category":"Landmark",
            "subcategory":"Tourist Attraction",
            "type":"Public Place"
        }
    ],
    "sg:phone":"+44 1275 878846",
    "sg:postcode":"BS21 7QU",
    "sg:province":"Somerset",
    "sg:tags":[
        "interest"
    ],
    "wof:name":"Clevedon Pier & Heritage Trust Ltd.",
    "wof:placetype":"venue"
},
  "geometry": {"coordinates":[-2.861324,51.442726],"type":"Point"}
}