{
  "type": "Feature",
  "properties": {
    "iso:country":"GB",
    "sg:address":"3 Great Central Way, Woodford Halse",
    "sg:city":"Daventry",
    "sg:classifiers":[
        {
            "category":"Manufacturing",
            "subcategory":"Rubber & Plastics",
            "type":"Manufacturing & Wholesale Goods"
        }
    ],
    "sg:phone":"+44 1327 262600",
    "sg:postcode":"NN11 3PZ",
    "sg:province":"Northamptonshire",
    "sg:tags":[
        "mould"
    ],
    "wof:name":"Tema (Machinery) Ltd.",
    "wof:placetype":"venue"
},
  "geometry": {"coordinates":[-1.209879,52.17416],"type":"Point"}
}