{
  "type": "Feature",
  "properties": {
    "addr:full":"68 Alton Street Crewe Cheshire CW2 7QB",
    "addr:housenumber":"68",
    "addr:postcode":"cw2 7qb",
    "addr:street":"Alton Street",
    "iso:country":"GB",
    "sg:address":"68 Alton Street",
    "sg:city":"Crewe",
    "sg:classifiers":[
        {
            "category":"Freight",
            "type":"Transportation"
        },
        {
            "category":"Communications",
            "type":"Services"
        }
    ],
    "sg:phone":"+44 1270 665750",
    "sg:postcode":"CW2 7QB",
    "sg:province":"Cheshire",
    "sg:tags":[
        "forwarders",
        "audio-visual"
    ],
    "wof:name":"Trackline Music Services",
    "wof:placetype":"venue"
},
  "geometry": {"coordinates":[-2.448403,53.093811],"type":"Point"}
}