{
  "type": "Feature",
  "properties": {
    "iso:country":"GB",
    "sg:address":"194 Leeds Road",
    "sg:city":"Shipley",
    "sg:classifiers":[
        {
            "category":"Autos & Motor Vehicles",
            "subcategory":"Fuel & Gas Station",
            "type":"Retail Goods"
        }
    ],
    "sg:phone":"+44 1274 530220",
    "sg:postcode":"BD18 1EZ",
    "sg:province":"West Yorkshire",
    "sg:tags":[
        "petrol",
        "filling"
    ],
    "wof:name":"F A Roper",
    "wof:placetype":"venue"
},
  "geometry": {"coordinates":[-1.763377,53.83532],"type":"Point"}
}