{
  "type": "Feature",
  "properties": {
    "iso:country":"GB",
    "sg:address":"15 Small St",
    "sg:city":"Bristol",
    "sg:classifiers":[
        {
            "category":"Bars & Pubs",
            "type":"Food & Drink"
        }
    ],
    "sg:phone":"+44 117 929 1805",
    "sg:postcode":"BS1 1DE",
    "sg:province":"City of Bristol",
    "sg:tags":[
        "pubs",
        "inn"
    ],
    "wof:name":"Bar Oz",
    "wof:placetype":"venue"
},
  "geometry": {"coordinates":[-2.5949180126,51.45520401],"type":"Point"}
}