{
  "type": "Feature",
  "properties": {
    "addr:full":"Rosewood House, Meesons Lane Grays Essex RM17 5HR",
    "addr:postcode":"rm17 5hr",
    "addr:street":"Meesons Lane",
    "iso:country":"GB",
    "sg:address":"Rosewood House, Meesons Lane",
    "sg:city":"Grays",
    "sg:classifiers":[
        {
            "category":"Building & Trades",
            "subcategory":"Cleaning & Sanitation",
            "type":"Services"
        }
    ],
    "sg:phone":"+44 1375 390441",
    "sg:postcode":"RM17 5HR",
    "sg:province":"Essex",
    "sg:tags":[
        "commercial"
    ],
    "wof:name":"Alpha Cleanse Ltd",
    "wof:placetype":"venue"
},
  "geometry": {"coordinates":[0.326975,51.479614],"type":"Point"}
}