{
  "type": "Feature",
  "properties": {
    "addr:full":"207 Walworth Road London Greater London SE17 1RL",
    "addr:housenumber":"207",
    "addr:postcode":"se17 1rl",
    "addr:street":"Walworth Road",
    "iso:country":"GB",
    "sg:address":"207 Walworth Road",
    "sg:city":"London",
    "sg:classifiers":[
        {
            "category":"Shopping",
            "subcategory":"Baby Store",
            "type":"Retail Goods"
        },
        {
            "category":"Shopping",
            "subcategory":"Hobbies, Toys, & Games",
            "type":"Retail Goods"
        }
    ],
    "sg:phone":"+44 20 7703 6910",
    "sg:postcode":"SE17 1RL",
    "sg:province":"Greater London",
    "sg:tags":[
        "shop",
        "nursery",
        "toy",
        "accessory"
    ],
    "wof:name":"Next in Line Ltd.",
    "wof:placetype":"venue"
},
  "geometry": {"coordinates":[-0.0960170031,51.4890899658],"type":"Point"}
}