{
  "type": "Feature",
  "properties": {
    "addr:full":"Greenlane Industrial Estate, Pelaw Gateshead Tyne and Wear NE10 0UW",
    "addr:postcode":"ne10 0uw",
    "addr:street":"Greenlane Industrial Estate",
    "iso:country":"GB",
    "sg:address":"Greenlane Industrial Estate, Pelaw",
    "sg:city":"Gateshead",
    "sg:classifiers":[
        {
            "category":"Building & Trades",
            "subcategory":"Construction",
            "type":"Services"
        }
    ],
    "sg:phone":"+44 191 495 0777",
    "sg:postcode":"NE10 0UW",
    "sg:province":"Tyne and Wear",
    "sg:tags":[
        "flooring"
    ],
    "wof:name":"Sandafloor (1995) Ltd.",
    "wof:placetype":"venue"
},
  "geometry": {"coordinates":[-1.546889,54.953171],"type":"Point"}
}