{
  "type": "Feature",
  "properties": {
    "addr:full":"A Strang Dental Laboratories, Venture House, Crofs Street Macclesfield Cheshire SK11 7PG",
    "addr:postcode":"sk11 7pg",
    "addr:street":"A;Crofs Street",
    "iso:country":"GB",
    "sg:address":"A Strang Dental Laboratories, Venture House, Crofs Street",
    "sg:city":"Macclesfield",
    "sg:classifiers":[
        {
            "category":"Health Services",
            "subcategory":"Medical Lab",
            "type":"Services"
        }
    ],
    "sg:phone":"+44 1625 421368",
    "sg:postcode":"SK11 7PG",
    "sg:province":"Cheshire",
    "sg:tags":[
        "dental"
    ],
    "wof:name":"A Strang",
    "wof:placetype":"venue"
},
  "geometry": {"coordinates":[-2.125756,53.255669],"type":"Point"}
}