{
  "type": "Feature",
  "properties": {
    "addr:full":"11 Garner Close Bilston West Midlands WV14 8TA",
    "addr:housenumber":"11",
    "addr:postcode":"wv14 8ta",
    "addr:street":"Garner Close",
    "iso:country":"GB",
    "sg:address":"11 Garner Close",
    "sg:city":"Bilston",
    "sg:classifiers":[
        {
            "category":"Freight",
            "type":"Transportation"
        }
    ],
    "sg:phone":"+44 1902 826837",
    "sg:postcode":"WV14 8TA",
    "sg:province":"West Midlands",
    "sg:tags":[
        "haulage",
        "road"
    ],
    "wof:name":"R.C.T.S",
    "wof:placetype":"venue"
},
  "geometry": {"coordinates":[-2.0790560246,52.554359436],"type":"Point"}
}