{
  "type": "Feature",
  "properties": {
    "iso:country":"GB",
    "sg:address":"940 Leeds Road",
    "sg:city":"Huddersfield",
    "sg:classifiers":[
        {
            "category":"Fast Food",
            "type":"Food & Drink"
        }
    ],
    "sg:phone":"+44 1484 517144",
    "sg:postcode":"HD2 1XG",
    "sg:province":"West Yorkshire",
    "sg:tags":[
        "away",
        "meal",
        "outlet",
        "take"
    ],
    "wof:name":"Marstons Chicken Shop",
    "wof:placetype":"venue"
},
  "geometry": {"coordinates":[-1.767294,53.658798],"type":"Point"}
}