{
  "type": "Feature",
  "properties": {
    "addr:full":"Unit 2, Morris Street, Netherfield Nottingham Nottinghamshire NG4 2LH",
    "addr:housenumber":"unit 2",
    "addr:postcode":"ng4 2lh",
    "addr:street":"Morris Street",
    "iso:country":"GB",
    "sg:address":"Unit 2, Morris Street, Netherfield",
    "sg:city":"Nottingham",
    "sg:classifiers":[
        {
            "category":"Utilities",
            "subcategory":"Natural Gas",
            "type":"Services"
        }
    ],
    "sg:postcode":"NG4 2LH",
    "sg:province":"Nottinghamshire",
    "sg:tags":[
        "supplier"
    ],
    "wof:name":"The Bottle Gas Centre",
    "wof:placetype":"venue"
},
  "geometry": {"coordinates":[-1.076819,52.963921],"type":"Point"}
}