{
  "type": "Feature",
  "properties": {
    "iso:country":"GB",
    "sg:address":"26 Spencer Street",
    "sg:city":"Carlisle",
    "sg:classifiers":[
        {
            "category":"Health Services",
            "subcategory":"Optometrist",
            "type":"Services"
        },
        {
            "category":"Shopping",
            "subcategory":"Optician",
            "type":"Retail Goods"
        }
    ],
    "sg:phone":"+44 1228 521813",
    "sg:postcode":"CA1 1BG",
    "sg:province":"Cumbria",
    "sg:tags":[
        "ophthalmic"
    ],
    "wof:name":"K France Opticians",
    "wof:placetype":"venue"
},
  "geometry": {"coordinates":[-2.930629,54.894314],"type":"Point"}
}