{
  "type": "Feature",
  "properties": {
    "addr:full":"Lane End Industrial Park, High Street, Lane End High Wycombe Buckinghamshire HP14 3BY",
    "addr:postcode":"hp14 3by",
    "addr:street":"Industrial;High Street",
    "iso:country":"GB",
    "sg:address":"Lane End Industrial Park, High Street, Lane End",
    "sg:city":"High Wycombe",
    "sg:classifiers":[
        {
            "category":"Professional",
            "subcategory":"Computer Services",
            "type":"Services"
        }
    ],
    "sg:postcode":"HP14 3BY",
    "sg:province":"Buckinghamshire",
    "sg:tags":[
        "system",
        "software"
    ],
    "wof:name":"Professional I T (Logistics) Ltd.",
    "wof:placetype":"venue"
},
  "geometry": {"coordinates":[-0.834774971,51.6189079285],"type":"Point"}
}