{
  "type": "Feature",
  "properties": {
    "iso:country":"GB",
    "sg:address":"18 Blantyre Street",
    "sg:city":"London",
    "sg:classifiers":[
        {
            "category":"Education",
            "subcategory":"Preschool",
            "type":"Public Place"
        }
    ],
    "sg:phone":"+44 20 7351 1641",
    "sg:postcode":"SW10 0DS",
    "sg:province":"Greater London",
    "sg:tags":[
        "pre-school",
        "playgroups"
    ],
    "wof:name":"Worlds End Playgroup",
    "wof:placetype":"venue"
},
  "geometry": {"coordinates":[-0.178533,51.481113],"type":"Point"}
}