{
  "type": "Feature",
  "properties": {
    "addr:full":"5 Sloane Avenue London Greater London SW3 3JD",
    "addr:housenumber":"5",
    "addr:postcode":"sw3 3jd",
    "addr:street":"Sloane Avenue",
    "iso:country":"GB",
    "sg:address":"5 Sloane Avenue",
    "sg:city":"London",
    "sg:classifiers":[
        {
            "category":"Health Services",
            "subcategory":"Doctor",
            "type":"Services"
        }
    ],
    "sg:phone":"+44 20 7581 3187",
    "sg:postcode":"SW3 3JD",
    "sg:province":"Greater London",
    "sg:tags":[
        "practitioners"
    ],
    "wof:name":"Medical Surgery",
    "wof:placetype":"venue"
},
  "geometry": {"coordinates":[-0.163273,51.491093],"type":"Point"}
}