{
  "type": "Feature",
  "properties": {
    "iso:country":"GB",
    "sg:address":"78 Kilmarnock Road",
    "sg:city":"Glasgow",
    "sg:classifiers":[
        {
            "category":"Banks & Credit Unions",
            "subcategory":"Bank",
            "type":"Services"
        }
    ],
    "sg:phone":"+44 141 649 4903",
    "sg:postcode":"G41 3NN",
    "sg:province":"Glasgow City",
    "wof:name":"Woolwich Ltd.",
    "wof:placetype":"venue"
},
  "geometry": {"coordinates":[-4.2833709717,55.8289031982],"type":"Point"}
}