{
  "type": "Feature",
  "properties": {
    "iso:country":"GB",
    "sg:address":"Unit 4, Claro Court, Business Centre, Claro Rd",
    "sg:city":"Harrogate",
    "sg:classifiers":[
        {
            "category":"Professional",
            "subcategory":"Management & Consulting",
            "type":"Services"
        }
    ],
    "sg:phone":"+44 1423 565996",
    "sg:postcode":"HG1 4BA",
    "sg:province":"North Yorkshire",
    "sg:tags":[
        "marketing",
        "consultant"
    ],
    "wof:name":"M S M S",
    "wof:placetype":"venue"
},
  "geometry": {"coordinates":[-1.521849,54.003006],"type":"Point"}
}