{
  "type": "Feature",
  "properties": {
    "iso:country":"GB",
    "sg:address":"22 Kings Walk, Clarence St",
    "sg:city":"Gloucester",
    "sg:classifiers":[
        {
            "category":"Shopping",
            "subcategory":"Clothing, Apparel, & Fashions",
            "type":"Retail Goods"
        }
    ],
    "sg:phone":"+44 1452 525110",
    "sg:postcode":"GL1 1RW",
    "sg:province":"Gloucestershire",
    "sg:tags":[
        "lady",
        "fashionwear",
        "ladieswear"
    ],
    "wof:name":"Bay Trading Co",
    "wof:placetype":"venue"
},
  "geometry": {"coordinates":[-2.2424869537,51.8649215698],"type":"Point"}
}