{
  "type": "Feature",
  "properties": {
    "addr:full":"49 Stonerwood Avenue Birmingham West Midlands B28 0AX",
    "addr:housenumber":"49",
    "addr:postcode":"b28 0ax",
    "addr:street":"Stonerwood Avenue",
    "iso:country":"GB",
    "sg:address":"49 Stonerwood Avenue",
    "sg:city":"Birmingham",
    "sg:classifiers":[
        {
            "category":"Professional",
            "subcategory":"Engineering",
            "type":"Services"
        }
    ],
    "sg:phone":"+44 121 777 8532",
    "sg:postcode":"B28 0AX",
    "sg:province":"West Midlands",
    "sg:tags":[
        "contractor",
        "electrical",
        "engineer"
    ],
    "wof:name":"M & J Electrical",
    "wof:placetype":"venue"
},
  "geometry": {"coordinates":[-1.8512029648,52.4311027527],"type":"Point"}
}