{
  "type": "Feature",
  "properties": {
    "addr:full":"6 Celestine Close Chatham Kent ME5 9NG",
    "addr:housenumber":"6",
    "addr:postcode":"me5 9ng",
    "addr:street":"Celestine Close",
    "iso:country":"GB",
    "sg:address":"6 Celestine Close",
    "sg:city":"Chatham",
    "sg:classifiers":[
        {
            "category":"Building & Trades",
            "subcategory":"Cleaning & Sanitation",
            "type":"Services"
        },
        {
            "category":"Building & Trades",
            "subcategory":"Pest Control",
            "type":"Services"
        }
    ],
    "sg:phone":"+44 7836 755562",
    "sg:postcode":"ME5 9NG",
    "sg:province":"Kent",
    "sg:tags":[
        "use",
        "industrial",
        "door",
        "manufacturer"
    ],
    "wof:name":"A L Industrial Doors",
    "wof:placetype":"venue"
},
  "geometry": {"coordinates":[0.5286610126,51.3303260803],"type":"Point"}
}