{
  "type": "Feature",
  "properties": {
    "addr:full":"Unit 8 Weston Way, Lower Rd Aylesbury Buckinghamshire HP22 5XB",
    "addr:housenumber":"unit 8",
    "addr:postcode":"hp22 5xb",
    "addr:street":"Weston Way Lower Rd",
    "iso:country":"GB",
    "sg:address":"Unit 8 Weston Way, Lower Rd",
    "sg:city":"Aylesbury",
    "sg:classifiers":[
        {
            "category":"Shopping",
            "subcategory":"Stationery & Office Supplies",
            "type":"Retail Goods"
        }
    ],
    "sg:phone":"+44 1296 615665",
    "sg:postcode":"HP22 5XB",
    "sg:province":"Buckinghamshire",
    "sg:tags":[
        "printers'"
    ],
    "wof:name":"Finishing Line The",
    "wof:placetype":"venue"
},
  "geometry": {"coordinates":[-0.7393839955,51.7994194031],"type":"Point"}
}