{
  "type": "Feature",
  "properties": {
    "addr:full":"St Michaels House, Ditherington Road Shrewsbury Shropshire SY1 4AS",
    "addr:postcode":"sy1 4as",
    "addr:street":"Ditherington Road",
    "iso:country":"GB",
    "sg:address":"St Michaels House, Ditherington Road",
    "sg:city":"Shrewsbury",
    "sg:classifiers":[
        {
            "category":"Social Services",
            "type":"Services"
        }
    ],
    "sg:phone":"+44 1743 255843",
    "sg:postcode":"SY1 4AS",
    "sg:province":"Shropshire",
    "sg:tags":[
        "need",
        "disability",
        "special"
    ],
    "wof:name":"The Physical Disability Team West",
    "wof:placetype":"venue"
},
  "geometry": {"coordinates":[-2.738139,52.724594],"type":"Point"}
}