{
  "type": "Feature",
  "properties": {
    "addr:full":"11 Worcester Road, Cheadle Hulme Cheadle Cheshire SK8 5NW",
    "addr:housenumber":"11",
    "addr:postcode":"sk8 5nw",
    "addr:street":"Worcester Road",
    "iso:country":"GB",
    "sg:address":"11 Worcester Road, Cheadle Hulme",
    "sg:city":"Cheadle",
    "sg:classifiers":[
        {
            "category":"Professional",
            "subcategory":"Engineering",
            "type":"Services"
        }
    ],
    "sg:postcode":"SK8 5NW",
    "sg:province":"Cheshire",
    "sg:tags":[
        "engineer"
    ],
    "wof:name":"E W Equipment",
    "wof:placetype":"venue"
},
  "geometry": {"coordinates":[-2.193288,53.384567],"type":"Point"}
}