{
  "type": "Feature",
  "properties": {
    "addr:full":"8 Brigstock Parade, London Road Thornton Heath Surrey CR7 7HW",
    "addr:housenumber":"8",
    "addr:postcode":"cr7 7hw",
    "addr:street":"Brigstock Parade London Road",
    "iso:country":"GB",
    "sg:address":"8 Brigstock Parade, London Road",
    "sg:city":"Thornton Heath",
    "sg:classifiers":[
        {
            "category":"Shopping",
            "subcategory":"Books",
            "type":"Retail Goods"
        }
    ],
    "sg:phone":"+44 20 8665 0996",
    "sg:postcode":"CR7 7HW",
    "sg:province":"Surrey",
    "wof:name":"Scorpio Publishing Ltd.",
    "wof:placetype":"venue"
},
  "geometry": {"coordinates":[-0.111749,51.394291],"type":"Point"}
}