{
  "type": "Feature",
  "properties": {
    "iso:country":"GB",
    "sg:address":"Heybury Close",
    "sg:city":"Manchester",
    "sg:classifiers":[
        {
            "category":"Farming",
            "subcategory":"Nursery",
            "type":"Manufacturing & Wholesale Goods"
        },
        {
            "category":"Government",
            "subcategory":"Office",
            "type":"Public Place"
        }
    ],
    "sg:phone":"+44 161 223 2982",
    "sg:postcode":"M11 3TY",
    "sg:province":"Greater Manchester",
    "sg:tags":[
        "local",
        "creche"
    ],
    "wof:name":"Heybury Close Childrens Centre",
    "wof:placetype":"venue"
},
  "geometry": {"coordinates":[-2.202404,53.4753],"type":"Point"}
}