{
  "type": "Feature",
  "properties": {
    "addr:full":"71 Grange Road, Woodthorpe Nottingham Nottinghamshire NG5 4GA",
    "addr:housenumber":"71",
    "addr:postcode":"ng5 4ga",
    "addr:street":"Grange Road",
    "iso:country":"GB",
    "sg:address":"71 Grange Road, Woodthorpe",
    "sg:city":"Nottingham",
    "sg:classifiers":[
        {
            "category":"Banks & Credit Unions",
            "subcategory":"Bank",
            "type":"Services"
        }
    ],
    "sg:postcode":"NG5 4GA",
    "sg:province":"Nottinghamshire",
    "sg:tags":[
        "belt",
        "conveyor"
    ],
    "wof:name":"Bahn Systems Ltd",
    "wof:placetype":"venue"
},
  "geometry": {"coordinates":[-1.133241,52.990017],"type":"Point"}
}