{
  "type": "Feature",
  "properties": {
    "iso:country":"GB",
    "sg:address":"Farningham Road",
    "sg:city":"Crowborough",
    "sg:classifiers":[
        {
            "category":"Professional",
            "subcategory":"Business Services",
            "type":"Services"
        }
    ],
    "sg:phone":"+44 1892 667474",
    "sg:postcode":"TN6 2JR",
    "sg:province":"East Sussex",
    "sg:tags":[
        "tile",
        "stockist"
    ],
    "wof:name":"Pentagon Tile Distributors",
    "wof:placetype":"venue"
},
  "geometry": {"coordinates":[0.186059,51.045551],"type":"Point"}
}