{
  "type": "Feature",
  "properties": {
    "iso:country":"GB",
    "sg:address":"15 St James St",
    "sg:city":"Derby",
    "sg:classifiers":[
        {
            "category":"Shopping",
            "subcategory":"Clothing, Apparel, & Fashions",
            "type":"Retail Goods"
        }
    ],
    "sg:phone":"+44 1332 331939",
    "sg:postcode":"DE1 1QZ",
    "sg:province":"Derbyshire",
    "sg:tags":[
        "shop"
    ],
    "wof:name":"Factory Shop The",
    "wof:placetype":"venue"
},
  "geometry": {"coordinates":[-1.478209,52.922298],"type":"Point"}
}