{
  "type": "Feature",
  "properties": {
    "iso:country":"GB",
    "sg:address":"Glossop Road",
    "sg:city":"Cardiff",
    "sg:classifiers":[
        {
            "category":"Education",
            "subcategory":"School",
            "type":"Public Place"
        }
    ],
    "sg:phone":"+44 29 2045 0463",
    "sg:postcode":"CF24 0JT",
    "sg:province":"Cardiff",
    "sg:tags":[
        "local",
        "authority"
    ],
    "wof:name":"Tredegarville Church in Wales Primary School",
    "wof:placetype":"venue"
},
  "geometry": {"coordinates":[-3.164721,51.484886],"type":"Point"}
}