{
  "type": "Feature",
  "properties": {
    "iso:country":"GB",
    "sg:address":"1a Claughton Firs",
    "sg:city":"Birkenhead",
    "sg:classifiers":[
        {
            "category":"Food & Beverages",
            "subcategory":"Meat & Fish",
            "type":"Retail Goods"
        }
    ],
    "sg:phone":"+44 151 652 2017",
    "sg:postcode":"L43 5TG",
    "sg:province":"Merseyside",
    "sg:tags":[
        "butcher"
    ],
    "wof:name":"T & G Cairns",
    "wof:placetype":"venue"
},
  "geometry": {"coordinates":[-3.042736,53.382313],"type":"Point"}
}