{
  "type": "Feature",
  "properties": {
    "iso:country":"GB",
    "sg:address":"19 Cliffe High Street",
    "sg:city":"Lewes",
    "sg:classifiers":[
        {
            "category":"Health Services",
            "subcategory":"Optometrist",
            "type":"Services"
        }
    ],
    "sg:phone":"+44 1273 471893",
    "sg:postcode":"BN7 2AH",
    "sg:province":"East Sussex",
    "sg:tags":[
        "optician"
    ],
    "wof:name":"Keith Chapple Opthalmic Opticians",
    "wof:placetype":"venue"
},
  "geometry": {"coordinates":[0.0176849999,50.8743515015],"type":"Point"}
}