{
  "type": "Feature",
  "properties": {
    "addr:full":"64 Eastover Bridgwater Somerset TA6 5AR",
    "addr:housenumber":"64",
    "addr:postcode":"ta6 5ar",
    "addr:street":"Eastover",
    "iso:country":"GB",
    "sg:address":"64 Eastover",
    "sg:city":"Bridgwater",
    "sg:classifiers":[
        {
            "category":"Fast Food",
            "type":"Food & Drink"
        }
    ],
    "sg:postcode":"TA6 5AR",
    "sg:province":"Somerset",
    "sg:tags":[
        "away",
        "take"
    ],
    "wof:name":"Dragon Palace",
    "wof:placetype":"venue"
},
  "geometry": {"coordinates":[-2.9973659515,51.1290779114],"type":"Point"}
}