{
  "type": "Feature",
  "properties": {
    "addr:full":"16 The Granary, High St, Roydon Harlow Essex CM19 5EL",
    "addr:housenumber":"16",
    "addr:postcode":"cm19 5el",
    "addr:street":"The;High St",
    "iso:country":"GB",
    "sg:address":"16 The Granary, High St, Roydon",
    "sg:city":"Harlow",
    "sg:classifiers":[
        {
            "category":"Professional",
            "subcategory":"Printing & Photocopies",
            "type":"Services"
        }
    ],
    "sg:postcode":"CM19 5EL",
    "sg:province":"Essex",
    "sg:tags":[
        "printer"
    ],
    "wof:name":"Dunn,A,H,(Printers) Ltd",
    "wof:placetype":"venue"
},
  "geometry": {"coordinates":[0.0358409993,51.7746200562],"type":"Point"}
}