{
  "type": "Feature",
  "properties": {
    "addr:full":"West Hornby Dock Bootle Merseyside L20 1ET",
    "addr:postcode":"l20 1et",
    "addr:street":"West Hornby Dock Bootle",
    "iso:country":"GB",
    "sg:address":"West Hornby Dock",
    "sg:city":"Bootle",
    "sg:classifiers":[
        {
            "category":"Professional",
            "type":"Services"
        }
    ],
    "sg:phone":"+44 151 955 3001",
    "sg:postcode":"L20 1ET",
    "sg:province":"Merseyside",
    "sg:tags":[
        "marine"
    ],
    "wof:name":"Gulf Offshore N S Ltd.",
    "wof:placetype":"venue"
},
  "geometry": {"coordinates":[-3.0088539124,53.4517097473],"type":"Point"}
}