{
  "type": "Feature",
  "properties": {
    "iso:country":"GB",
    "sg:address":"247 Vicarage Road",
    "sg:city":"London",
    "sg:classifiers":[
        {
            "category":"Retail",
            "subcategory":"Driving School",
            "type":"Services"
        }
    ],
    "sg:phone":"+44 20 8539 1968",
    "sg:postcode":"E10 7HQ",
    "sg:province":"Greater London",
    "wof:name":"Brown Driving School",
    "wof:placetype":"venue"
},
  "geometry": {"coordinates":[-0.017866,51.571526],"type":"Point"}
}