{
  "type": "Feature",
  "properties": {
    "iso:country":"GB",
    "sg:address":"Education Service For Visually Handicapped, Wold Rd",
    "sg:city":"Hull",
    "sg:classifiers":[
        {
            "category":"Government",
            "subcategory":"Office",
            "type":"Public Place"
        }
    ],
    "sg:phone":"+44 1482 507906",
    "sg:postcode":"HU5 5QG",
    "sg:province":"East Riding of Yorkshire",
    "sg:tags":[
        "local"
    ],
    "wof:name":"North East Lincolnshire Council",
    "wof:placetype":"venue"
},
  "geometry": {"coordinates":[-0.4128,53.758999],"type":"Point"}
}