{
  "type": "Feature",
  "properties": {
    "iso:country":"GB",
    "sg:address":"955 Sheffield Rd",
    "sg:city":"Chesterfield",
    "sg:classifiers":[
        {
            "category":"Real Estate",
            "subcategory":"Surveying",
            "type":"Services"
        }
    ],
    "sg:phone":"+44 1246 452606",
    "sg:postcode":"S41 9EJ",
    "sg:province":"Derbyshire",
    "sg:tags":[
        "surveyor",
        "marine"
    ],
    "wof:name":"Paragon Marine Services",
    "wof:placetype":"venue"
},
  "geometry": {"coordinates":[-1.438322,53.280102],"type":"Point"}
}