{
  "type": "Feature",
  "properties": {
    "addr:full":"Factory 1 Bond Trading Estate, Bond Avenue, Bletchley Milton Keynes Buckinghamshire MK1 1JJ",
    "addr:housenumber":"1;estate",
    "addr:postcode":"mk1 1jj",
    "addr:street":"Bond Trading;Bond Avenue",
    "iso:country":"GB",
    "sg:address":"Factory 1 Bond Trading Estate, Bond Avenue, Bletchley",
    "sg:city":"Milton Keynes",
    "sg:classifiers":[
        {
            "category":"Wholesale",
            "subcategory":"Construction Materials",
            "type":"Manufacturing & Wholesale Goods"
        }
    ],
    "sg:phone":"+44 1908 649202",
    "sg:postcode":"MK1 1JJ",
    "sg:province":"Buckinghamshire",
    "sg:tags":[
        "lift"
    ],
    "wof:name":"R S J Lifting Services Ltd.",
    "wof:placetype":"venue"
},
  "geometry": {"coordinates":[-0.727749,52.005856],"type":"Point"}
}