{
  "type": "Feature",
  "properties": {
    "iso:country":"GB",
    "sg:address":"54 Camberwell Road",
    "sg:city":"London",
    "sg:classifiers":[
        {
            "category":"Organizations",
            "subcategory":"Non-profit Organization",
            "type":"Services"
        }
    ],
    "sg:phone":"+44 20 7701 0486",
    "sg:postcode":"SE5 0EN",
    "sg:province":"Greater London",
    "sg:tags":[
        "organisation",
        "voluntary",
        "charity"
    ],
    "wof:name":"Southwark African Family Support Services",
    "wof:placetype":"venue"
},
  "geometry": {"coordinates":[-0.0947479978,51.4826469421],"type":"Point"}
}