{
  "type": "Feature",
  "properties": {
    "addr:full":"1-6 Batemans Row Moorgate Greater London EC2A 3HH",
    "addr:housenumber":"1-6",
    "addr:postcode":"ec2a 3hh",
    "addr:street":"Batemans Row Moorgate",
    "iso:country":"GB",
    "sg:address":"1-6 Batemans Row",
    "sg:city":"Moorgate",
    "sg:classifiers":[
        {
            "category":"Shopping",
            "subcategory":"Crafts & Fabrics",
            "type":"Retail Goods"
        }
    ],
    "sg:phone":"+44 20 8969 6644",
    "sg:postcode":"EC2A 3HH",
    "sg:province":"Greater London",
    "sg:tags":[
        "material",
        "graphic",
        "art"
    ],
    "wof:name":"London Graphic Centre The",
    "wof:placetype":"venue"
},
  "geometry": {"coordinates":[-0.080126,51.525448],"type":"Point"}
}