{
  "type": "Feature",
  "properties": {
    "addr:full":"1 High Street, Loftus Saltburn-by-the-sea North Yorkshire TS13 4HW",
    "addr:housenumber":"1",
    "addr:postcode":"ts13 4hw",
    "addr:street":"High Street",
    "iso:country":"GB",
    "sg:address":"1 High Street, Loftus",
    "sg:city":"Saltburn-by-the-sea",
    "sg:classifiers":[
        {
            "category":"Building & Trades",
            "subcategory":"Construction",
            "type":"Services"
        }
    ],
    "sg:postcode":"TS13 4HW",
    "sg:province":"North Yorkshire",
    "sg:tags":[
        "monumental",
        "mason"
    ],
    "wof:name":"Mark Thompson",
    "wof:placetype":"venue"
},
  "geometry": {"coordinates":[-0.8990569711,54.5693206787],"type":"Point"}
}