{
  "type": "Feature",
  "properties": {
    "addr:full":"8 Harrismith Road, Penylan Cardiff Cardiff CF23 5DG",
    "addr:housenumber":"8",
    "addr:postcode":"cf23 5dg",
    "addr:street":"Harrismith Road",
    "iso:country":"GB",
    "sg:address":"8 Harrismith Road, Penylan",
    "sg:city":"Cardiff",
    "sg:classifiers":[
        {
            "category":"Government",
            "subcategory":"Post Office",
            "type":"Public Place"
        }
    ],
    "sg:phone":"+44 29 2048 5115",
    "sg:postcode":"CF23 5DG",
    "sg:province":"Cardiff",
    "sg:tags":[
        "organisation",
        "soc",
        "research"
    ],
    "wof:name":"Spencer Research Ltd.",
    "wof:placetype":"venue"
},
  "geometry": {"coordinates":[-3.161598,51.497726],"type":"Point"}
}