{
  "type": "Feature",
  "properties": {
    "iso:country":"GB",
    "sg:address":"King's Saltern Road",
    "sg:city":"Lymington",
    "sg:classifiers":[
        {
            "category":"Recreation",
            "subcategory":"Marina",
            "type":"Entertainment"
        }
    ],
    "sg:postcode":"SO41 3QD",
    "sg:province":"Hampshire",
    "wof:name":"Neyland Yacht Haven Ltd.",
    "wof:placetype":"venue"
},
  "geometry": {"coordinates":[-1.53057,50.75214],"type":"Point"}
}