{
  "type": "Feature",
  "properties": {
    "iso:country":"GB",
    "sg:address":"19-20 Great Sutton Street",
    "sg:city":"London",
    "sg:classifiers":[
        {
            "category":"Shopping",
            "subcategory":"Books",
            "type":"Retail Goods"
        },
        {
            "category":"Wholesale",
            "subcategory":"Books, Periodicals, & Newspapers",
            "type":"Manufacturing & Wholesale Goods"
        }
    ],
    "sg:phone":"+44 20 7608 9000",
    "sg:postcode":"EC1V 0DR",
    "sg:province":"Greater London",
    "sg:tags":[
        "publishing"
    ],
    "wof:name":"Pendragon Professional Information Ltd.",
    "wof:placetype":"venue"
},
  "geometry": {"coordinates":[-0.10059,51.52317],"type":"Point"}
}