{
  "type": "Feature",
  "properties": {
    "iso:country":"GB",
    "sg:address":"27 Ideal Mobile Home Pk, Bishopstoke Rd",
    "sg:city":"Eastleigh",
    "sg:classifiers":[
        {
            "category":"Taxi",
            "type":"Transportation"
        }
    ],
    "sg:postcode":"SO50 6HX",
    "sg:province":"Hampshire",
    "sg:tags":[
        "mini",
        "cab"
    ],
    "wof:name":"Hazel Taxis",
    "wof:placetype":"venue"
},
  "geometry": {"coordinates":[-1.350593,50.968323],"type":"Point"}
}