{
  "type": "Feature",
  "properties": {
    "addr:full":"12 Bath Passage, Longton Stoke-on-trent Staffordshire ST3 7DZ",
    "addr:housenumber":"12",
    "addr:postcode":"staffordshire st3 7dz",
    "addr:street":"Bath Passage",
    "iso:country":"GB",
    "sg:address":"12 Bath Passage, Longton",
    "sg:city":"Stoke-on-trent",
    "sg:classifiers":[
        {
            "category":"Home & Garden",
            "subcategory":"Home Furnishings",
            "type":"Retail Goods"
        }
    ],
    "sg:postcode":"ST3 7DZ",
    "sg:province":"Staffordshire",
    "sg:tags":[
        "wall",
        "wallpaper",
        "covering"
    ],
    "wof:name":"N Papers & Paints",
    "wof:placetype":"venue"
},
  "geometry": {"coordinates":[-2.10779,52.972511],"type":"Point"}
}