{
  "type": "Feature",
  "properties": {
    "iso:country":"GB",
    "sg:address":"Whitburn Road",
    "sg:city":"Bathgate",
    "sg:classifiers":[
        {
            "category":"Professional",
            "subcategory":"Computer Services",
            "type":"Services"
        }
    ],
    "sg:postcode":"EH48 1HH",
    "sg:province":"West Lothian",
    "sg:tags":[
        "system",
        "software"
    ],
    "wof:name":"Tiger Computers",
    "wof:placetype":"venue"
},
  "geometry": {"coordinates":[-3.6428389549,55.9001235962],"type":"Point"}
}