{
  "type": "Feature",
  "properties": {
    "addr:full":"56-58 East Street Barking Essex IG11 8EQ",
    "addr:housenumber":"56-58",
    "addr:postcode":"ig11 8eq",
    "addr:street":"East Street",
    "iso:country":"GB",
    "sg:address":"56-58 East Street",
    "sg:city":"Barking",
    "sg:classifiers":[
        {
            "category":"Shopping",
            "subcategory":"Clothing, Apparel, & Fashions",
            "type":"Retail Goods"
        }
    ],
    "sg:postcode":"IG11 8EQ",
    "sg:province":"Essex",
    "sg:tags":[
        "shop"
    ],
    "wof:name":"Jaspa (U K) Ltd.",
    "wof:placetype":"venue"
},
  "geometry": {"coordinates":[0.078982,51.537453],"type":"Point"}
}