{
  "type": "Feature",
  "properties": {
    "addr:full":"49 Craw Road Paisley East Renfrewshire PA2 6AE",
    "addr:housenumber":"49",
    "addr:postcode":"pa2 6ae",
    "addr:street":"Craw Road",
    "iso:country":"GB",
    "sg:address":"49 Craw Road",
    "sg:city":"Paisley",
    "sg:classifiers":[
        {
            "category":"Building & Trades",
            "subcategory":"Cleaning & Sanitation",
            "type":"Services"
        }
    ],
    "sg:phone":"+44 141 889 9839",
    "sg:postcode":"PA2 6AE",
    "sg:province":"East Renfrewshire",
    "sg:tags":[
        "cleaner",
        "window"
    ],
    "wof:name":"Skyline Window Cleaners",
    "wof:placetype":"venue"
},
  "geometry": {"coordinates":[-4.436319828,55.8378181458],"type":"Point"}
}