{
  "type": "Feature",
  "properties": {
    "addr:full":"37a Withens La Wallasey Merseyside L44 1BB",
    "addr:housenumber":"37a",
    "addr:postcode":"l44 1bb",
    "addr:street":"Withens La",
    "iso:country":"GB",
    "sg:address":"37a Withens La",
    "sg:city":"Wallasey",
    "sg:classifiers":[
        {
            "category":"Retail",
            "subcategory":"Auto Repair",
            "type":"Services"
        }
    ],
    "sg:phone":"+44 151 691 1965",
    "sg:postcode":"L44 1BB",
    "sg:province":"Merseyside",
    "sg:tags":[
        "engine",
        "car",
        "specialist"
    ],
    "wof:name":"D P Autos",
    "wof:placetype":"venue"
},
  "geometry": {"coordinates":[-3.0379810333,53.4218788147],"type":"Point"}
}