{
  "type": "Feature",
  "properties": {
    "addr:full":"2/3 Friary St Derby Derbyshire DE1 1JF",
    "addr:housenumber":"2 / 3",
    "addr:postcode":"de1 1jf",
    "addr:street":"Friary St",
    "iso:country":"GB",
    "sg:address":"2/3 Friary St",
    "sg:city":"Derby",
    "sg:classifiers":[
        {
            "category":"Travel",
            "subcategory":"Travel Agent",
            "type":"Entertainment"
        }
    ],
    "sg:postcode":"DE1 1JF",
    "sg:province":"Derbyshire",
    "wof:name":"Travel Wide",
    "wof:placetype":"venue"
},
  "geometry": {"coordinates":[-1.484059,52.922176],"type":"Point"}
}