{
  "type": "Feature",
  "properties": {
    "addr:full":"69 Chesterton Ave Harpenden Hertfordshire AL5 5SU",
    "addr:housenumber":"69",
    "addr:postcode":"al5 5su",
    "addr:street":"Chesterton Ave",
    "iso:country":"GB",
    "sg:address":"69 Chesterton Ave",
    "sg:city":"Harpenden",
    "sg:classifiers":[
        {
            "category":"Communications",
            "subcategory":"Film & Video Production",
            "type":"Services"
        }
    ],
    "sg:postcode":"AL5 5SU",
    "sg:province":"Hertfordshire",
    "sg:tags":[
        "product",
        "wire",
        "mfrs"
    ],
    "wof:name":"Phippin,T,",
    "wof:placetype":"venue"
},
  "geometry": {"coordinates":[-0.341122,51.813644],"type":"Point"}
}