{
  "type": "Feature",
  "properties": {
    "iso:country":"GB",
    "sg:address":"Aultmore Distillery",
    "sg:city":"Keith",
    "sg:classifiers":[
        {
            "category":"Distillery",
            "subcategory":"None",
            "type":"Food & Drink"
        }
    ],
    "sg:phone":"+44 1542 881800",
    "sg:postcode":"AB55 6QY",
    "sg:province":"Moray",
    "wof:name":"John Dewar & Sons Ltd",
    "wof:placetype":"venue"
},
  "geometry": {"coordinates":[-2.9519190788,57.558631897],"type":"Point"}
}