{
  "type": "Feature",
  "properties": {
    "iso:country":"GB",
    "sg:address":"99 Denver Road",
    "sg:city":"Dartford",
    "sg:classifiers":[
        {
            "category":"Professional",
            "subcategory":"Art Services",
            "type":"Services"
        },
        {
            "category":"Real Estate",
            "subcategory":"Architect",
            "type":"Services"
        }
    ],
    "sg:phone":"+44 1322 280012",
    "sg:postcode":"DA1 3JU",
    "sg:province":"Kent",
    "sg:tags":[
        "consultant",
        "design"
    ],
    "wof:name":"Schecter Editorial & Design",
    "wof:placetype":"venue"
},
  "geometry": {"coordinates":[0.190694,51.443108],"type":"Point"}
}