{
  "type": "Feature",
  "properties": {
    "addr:full":"124 Hoads Wood Road Hastings East Sussex TN34 2BA",
    "addr:housenumber":"124",
    "addr:postcode":"tn34 2ba",
    "addr:street":"Hoads Wood Road",
    "iso:country":"GB",
    "sg:address":"124 Hoads Wood Road",
    "sg:city":"Hastings",
    "sg:classifiers":[
        {
            "category":"Social Services",
            "subcategory":"Retirement Home",
            "type":"Services"
        }
    ],
    "sg:phone":"+44 1424 425693",
    "sg:postcode":"TN34 2BA",
    "sg:province":"East Sussex",
    "sg:tags":[
        "residential",
        "care"
    ],
    "wof:name":"The Hurst Rest Home",
    "wof:placetype":"venue"
},
  "geometry": {"coordinates":[0.592916,50.872898],"type":"Point"}
}