{
  "type": "Feature",
  "properties": {
    "iso:country":"GB",
    "sg:address":"Unit 1 Haven, Lullington Road",
    "sg:city":"Swadlincote",
    "sg:classifiers":[
        {
            "category":"Autos & Motor Vehicles",
            "subcategory":"Automobile Sales",
            "type":"Retail Goods"
        }
    ],
    "sg:phone":"+44 1283 763999",
    "sg:postcode":"DE12 8HZ",
    "sg:province":"Derbyshire",
    "sg:tags":[
        "car"
    ],
    "wof:name":"S D T",
    "wof:placetype":"venue"
},
  "geometry": {"coordinates":[-1.57761,52.730106],"type":"Point"}
}