{
  "type": "Feature",
  "properties": {
    "addr:full":"447 New Cross Road London Greater London SE14 6TH",
    "addr:housenumber":"447",
    "addr:postcode":"se14 6th",
    "addr:street":"New Cross Road",
    "iso:country":"GB",
    "sg:address":"447 New Cross Road",
    "sg:city":"London",
    "sg:classifiers":[
        {
            "category":"Organizations",
            "subcategory":"Community Association",
            "type":"Services"
        }
    ],
    "sg:phone":"+44 20 8691 4614",
    "sg:postcode":"SE14 6TH",
    "sg:province":"Greater London",
    "sg:tags":[
        "hire",
        "furniture"
    ],
    "wof:name":"S W Trading Office Equipment",
    "wof:placetype":"venue"
},
  "geometry": {"coordinates":[-0.029524,51.475628],"type":"Point"}
}