{
  "type": "Feature",
  "properties": {
    "addr:full":"6 Cottrell Av Bristol City of Bristol BS15 1LR",
    "addr:housenumber":"6",
    "addr:postcode":"bs15 1lr",
    "addr:street":"Cottrell Av Bristol",
    "iso:country":"GB",
    "sg:address":"6 Cottrell Av",
    "sg:city":"Bristol",
    "sg:classifiers":[
        {
            "category":"Deli",
            "type":"Food & Drink"
        }
    ],
    "sg:phone":"+44 117 961 0139",
    "sg:postcode":"BS15 1LR",
    "sg:province":"City of Bristol",
    "sg:tags":[
        "delivery",
        "sandwich"
    ],
    "wof:name":"Mr Walkers",
    "wof:placetype":"venue"
},
  "geometry": {"coordinates":[-2.520176,51.469646],"type":"Point"}
}