{
  "type": "Feature",
  "properties": {
    "addr:full":"10 Bryant Way, Higher Ferrers Rushden Bedfordshire NN10 8EG",
    "addr:housenumber":"10",
    "addr:postcode":"nn10 8eg",
    "addr:street":"Bryant Way;Bedfordshire",
    "iso:country":"GB",
    "sg:address":"10 Bryant Way, Higher Ferrers",
    "sg:city":"Rushden",
    "sg:classifiers":[
        {
            "category":"Building & Trades",
            "subcategory":"Plumbing",
            "type":"Services"
        }
    ],
    "sg:phone":"+44 1933 410409",
    "sg:postcode":"NN10 8EG",
    "sg:province":"Bedfordshire",
    "sg:tags":[
        "heating"
    ],
    "wof:name":"Neil G Young",
    "wof:placetype":"venue"
},
  "geometry": {"coordinates":[-0.598872,52.307751],"type":"Point"}
}