{
  "type": "Feature",
  "properties": {
    "iso:country":"GB",
    "sg:address":"403 Hunts Pond Road, Titchfield Common",
    "sg:city":"Fareham",
    "sg:classifiers":[
        {
            "category":"Transit Center",
            "subcategory":"Passenger",
            "type":"Transportation"
        },
        {
            "category":"Retail",
            "subcategory":"Pet Boarding",
            "type":"Services"
        }
    ],
    "sg:phone":"+44 1329 843386",
    "sg:postcode":"PO14 4PA",
    "sg:province":"Hampshire",
    "sg:tags":[
        "kennel",
        "catteries"
    ],
    "wof:name":"Pussy Galore",
    "wof:placetype":"venue"
},
  "geometry": {"coordinates":[-1.253337,50.849281],"type":"Point"}
}