{
  "type": "Feature",
  "properties": {
    "addr:full":"Elsinore House, Buckingham Street Aylesbury Buckinghamshire HP20 2NQ",
    "addr:postcode":"hp20 2nq",
    "addr:street":"Buckingham Street",
    "iso:country":"GB",
    "sg:address":"Elsinore House, Buckingham Street",
    "sg:city":"Aylesbury",
    "sg:classifiers":[
        {
            "category":"Real Estate",
            "subcategory":"Real Estate Agent",
            "type":"Services"
        }
    ],
    "sg:postcode":"HP20 2NQ",
    "sg:province":"Buckinghamshire",
    "wof:name":"Trophy Property Services Ltd",
    "wof:placetype":"venue"
},
  "geometry": {"coordinates":[-0.815438,51.819672],"type":"Point"}
}