{
  "type": "Feature",
  "properties": {
    "iso:country":"GB",
    "sg:address":"8 Church Road",
    "sg:city":"Thornton-cleveleys",
    "sg:classifiers":[
        {
            "category":"Building & Trades",
            "subcategory":"Construction",
            "type":"Services"
        }
    ],
    "sg:phone":"+44 1253 858800",
    "sg:postcode":"FY5 2TZ",
    "sg:province":"Lancashire",
    "sg:tags":[
        "builder"
    ],
    "wof:name":"Brian Henderson",
    "wof:placetype":"venue"
},
  "geometry": {"coordinates":[-3.014164,53.876656],"type":"Point"}
}