{
  "type": "Feature",
  "properties": {
    "addr:full":"Inkerman Hill, Hazlemere High Wycombe Buckinghamshire HP15 7JH",
    "addr:postcode":"hp15 7jh",
    "addr:street":"Inkerman Hill",
    "iso:country":"GB",
    "sg:address":"Inkerman Hill, Hazlemere",
    "sg:city":"High Wycombe",
    "sg:classifiers":[
        {
            "category":"Sports & Exercise",
            "subcategory":"Stables",
            "type":"Entertainment"
        }
    ],
    "sg:postcode":"HP15 7JH",
    "sg:province":"Buckinghamshire",
    "sg:tags":[
        "education",
        "equestrian"
    ],
    "wof:name":"Orchard End Liveries",
    "wof:placetype":"venue"
},
  "geometry": {"coordinates":[-0.708729,51.651031],"type":"Point"}
}