{
  "type": "Feature",
  "properties": {
    "addr:full":"6 Station Road, St Ives Huntingdon Cambridgeshire PE17 4BN",
    "addr:housenumber":"6",
    "addr:postcode":"pe17 4bn",
    "addr:street":"Station Road",
    "iso:country":"GB",
    "sg:address":"6 Station Road, St Ives",
    "sg:city":"Huntingdon",
    "sg:classifiers":[
        {
            "category":"Organizations",
            "subcategory":"Community Association",
            "type":"Services"
        }
    ],
    "sg:phone":"+44 1480 461868",
    "sg:postcode":"PE17 4BN",
    "sg:province":"Cambridgeshire",
    "sg:tags":[
        "society",
        "housing"
    ],
    "wof:name":"Nene Housing Society Ltd.",
    "wof:placetype":"venue"
},
  "geometry": {"coordinates":[-0.1893,52.33514],"type":"Point"}
}