{
  "type": "Feature",
  "properties": {
    "addr:full":"11 St Oswalds Road, Ashton In Makerfield Wigan Lancashire WN4 9NU",
    "addr:housenumber":"11",
    "addr:postcode":"wn4 9nu",
    "addr:street":"St Oswalds Road",
    "iso:country":"GB",
    "sg:address":"11 St Oswalds Road, Ashton In Makerfield",
    "sg:city":"Wigan",
    "sg:classifiers":[
        {
            "category":"Building & Trades",
            "subcategory":"Construction",
            "type":"Services"
        }
    ],
    "sg:postcode":"WN4 9NU",
    "sg:province":"Lancashire",
    "sg:tags":[
        "builder"
    ],
    "wof:name":"Tom Hill",
    "wof:placetype":"venue"
},
  "geometry": {"coordinates":[-2.6414849758,53.4835281372],"type":"Point"}
}