{
  "type": "Feature",
  "properties": {
    "iso:country":"GB",
    "sg:address":"50 Queen Street, Great Harwood",
    "sg:city":"Blackburn",
    "sg:classifiers":[
        {
            "category":"Shopping",
            "subcategory":"Pharmacy",
            "type":"Retail Goods"
        }
    ],
    "sg:phone":"+44 1254 884330",
    "sg:postcode":"BB6 7QQ",
    "sg:province":"Lancashire",
    "sg:tags":[
        "pharmacist",
        "chemist"
    ],
    "wof:name":"E B Haworth Ltd.",
    "wof:placetype":"venue"
},
  "geometry": {"coordinates":[-2.405191,53.786148],"type":"Point"}
}