{
  "type": "Feature",
  "properties": {
    "addr:full":"350 Cowbridge Road East Cardiff Cardiff CF5 1HD",
    "addr:housenumber":"350",
    "addr:postcode":"cf5 1hd",
    "addr:street":"Cowbridge Road East",
    "iso:country":"GB",
    "sg:address":"350 Cowbridge Road East",
    "sg:city":"Cardiff",
    "sg:classifiers":[
        {
            "category":"Professional",
            "subcategory":"Art Services",
            "type":"Services"
        }
    ],
    "sg:phone":"+44 1633 440677",
    "sg:postcode":"CF5 1HD",
    "sg:province":"Cardiff",
    "sg:tags":[
        "graphic",
        "designer"
    ],
    "wof:name":"Millenia Design",
    "wof:placetype":"venue"
},
  "geometry": {"coordinates":[-3.212045908,51.4826507568],"type":"Point"}
}