{
  "type": "Feature",
  "properties": {
    "iso:country":"GB",
    "sg:address":"35 Borough Rd",
    "sg:city":"Middlesbrough",
    "sg:classifiers":[
        {
            "category":"Professional",
            "subcategory":"Art Services",
            "type":"Services"
        }
    ],
    "sg:postcode":"TS1 4AD",
    "sg:province":"North Yorkshire",
    "sg:tags":[
        "graphic",
        "designer"
    ],
    "wof:name":"Digital Print Direct Ltd",
    "wof:placetype":"venue"
},
  "geometry": {"coordinates":[-1.239149,54.573036],"type":"Point"}
}