{
  "type": "Feature",
  "properties": {
    "addr:full":"3 Osborne Street Colchester Essex CO2 7DP",
    "addr:housenumber":"3",
    "addr:postcode":"co2 7dp",
    "addr:street":"Osborne Street",
    "iso:country":"GB",
    "sg:address":"3 Osborne Street",
    "sg:city":"Colchester",
    "sg:classifiers":[
        {
            "category":"Fast Food",
            "type":"Food & Drink"
        }
    ],
    "sg:phone":"+44 1206 763733",
    "sg:postcode":"CO2 7DP",
    "sg:province":"Essex",
    "sg:tags":[
        "away",
        "take"
    ],
    "wof:name":"Jasmin Chinese Takeaway",
    "wof:placetype":"venue"
},
  "geometry": {"coordinates":[0.9023820162,51.8870353699],"type":"Point"}
}