{
  "type": "Feature",
  "properties": {
    "iso:country":"GB",
    "sg:address":"Whitestone Lodge, Thirlby",
    "sg:city":"Thirsk",
    "sg:classifiers":[
        {
            "category":"Real Estate",
            "subcategory":"Architect",
            "type":"Services"
        }
    ],
    "sg:phone":"+44 1845 597328",
    "sg:postcode":"YO7 2DJ",
    "sg:province":"North Yorkshire",
    "wof:name":"H Vernon Kirk",
    "wof:placetype":"venue"
},
  "geometry": {"coordinates":[-1.2573039532,54.2496528625],"type":"Point"}
}