{
  "type": "Feature",
  "properties": {
    "addr:full":"Bedwas House Industrial Estate, Bedwas Caerphilly Caerphilly CF83 8XP",
    "addr:postcode":"cf83 8xp",
    "addr:street":"Industrial Estate",
    "iso:country":"GB",
    "sg:address":"Bedwas House Industrial Estate, Bedwas",
    "sg:city":"Caerphilly",
    "sg:classifiers":[
        {
            "category":"Wholesale",
            "subcategory":"Groceries",
            "type":"Manufacturing & Wholesale Goods"
        }
    ],
    "sg:phone":"+44 29 2086 9721",
    "sg:postcode":"CF83 8XP",
    "sg:province":"Caerphilly",
    "sg:tags":[
        "food",
        "supplier",
        "drink"
    ],
    "wof:name":"Peter's Savoury Products Ltd.",
    "wof:placetype":"venue"
},
  "geometry": {"coordinates":[-3.189834,51.590469],"type":"Point"}
}