{
  "type": "Feature",
  "properties": {
    "iso:country":"GB",
    "sg:address":"The Vicarage, 224 Tamworth Rd",
    "sg:city":"Tamworth",
    "sg:classifiers":[
        {
            "category":"Place Of Worship",
            "type":"Public Place"
        }
    ],
    "sg:phone":"+44 1827 62573",
    "sg:postcode":"B77 3DE",
    "sg:province":"Staffordshire",
    "wof:name":"Amington St Editha C Of E Church",
    "wof:placetype":"venue"
},
  "geometry": {"coordinates":[-1.6603499651,52.6358909607],"type":"Point"}
}