{
  "type": "Feature",
  "properties": {
    "addr:full":"37-41 High Street Edenbridge East Sussex TN8 5AD",
    "addr:housenumber":"37-41",
    "addr:postcode":"tn8 5ad",
    "addr:street":"High Street",
    "iso:country":"GB",
    "sg:address":"37-41 High Street",
    "sg:city":"Edenbridge",
    "sg:classifiers":[
        {
            "category":"Professional",
            "subcategory":"Employment Agencies",
            "type":"Services"
        }
    ],
    "sg:phone":"+44 1732 864777",
    "sg:postcode":"TN8 5AD",
    "sg:province":"East Sussex",
    "sg:tags":[
        "consultant",
        "recruitment"
    ],
    "sg:website":"http://www.whitehall.uk.com",
    "wof:name":"Whitehall Recruitment Ltd.",
    "wof:placetype":"venue"
},
  "geometry": {"coordinates":[0.064979,51.19735],"type":"Point"}
}