{
  "type": "Feature",
  "properties": {
    "addr:full":"2 Griston Road, Watton Thetford Norfolk IP25 6DL",
    "addr:housenumber":"2",
    "addr:postcode":"ip25 6dl",
    "addr:street":"Griston Road",
    "iso:country":"GB",
    "sg:address":"2 Griston Road, Watton",
    "sg:city":"Thetford",
    "sg:classifiers":[
        {
            "category":"Professional",
            "type":"Services"
        }
    ],
    "sg:phone":"+44 1953 883351",
    "sg:postcode":"IP25 6DL",
    "sg:province":"Norfolk",
    "sg:tags":[
        "caterer"
    ],
    "wof:name":"Town Caterers",
    "wof:placetype":"venue"
},
  "geometry": {"coordinates":[0.8365870118,52.5697517395],"type":"Point"}
}