{
  "type": "Feature",
  "properties": {
    "iso:country":"GB",
    "sg:address":"10b Canal Lane, Lofthouse",
    "sg:city":"Wakefield",
    "sg:classifiers":[
        {
            "category":"Personal",
            "subcategory":"Beauty Salon",
            "type":"Services"
        }
    ],
    "sg:phone":"+44 1924 822420",
    "sg:postcode":"WF3 3HN",
    "sg:province":"West Yorkshire",
    "sg:tags":[
        "unisex",
        "hairdresser"
    ],
    "wof:name":"Charisma",
    "wof:placetype":"venue"
},
  "geometry": {"coordinates":[-1.4951579571,53.7165145874],"type":"Point"}
}