{
  "type": "Feature",
  "properties": {
    "addr:full":"35 Church Street Nuneaton Leicestershire CV11 4AS",
    "addr:housenumber":"35",
    "addr:postcode":"cv11 4as",
    "addr:street":"Church Street",
    "iso:country":"GB",
    "sg:address":"35 Church Street",
    "sg:city":"Nuneaton",
    "sg:classifiers":[
        {
            "category":"Personal",
            "subcategory":"Beauty Salon",
            "type":"Services"
        },
        {
            "category":"Personal",
            "subcategory":"Barber",
            "type":"Services"
        }
    ],
    "sg:phone":"+44 24 7632 6391",
    "sg:postcode":"CV11 4AS",
    "sg:province":"Leicestershire",
    "sg:tags":[
        "unisex",
        "hairdresser"
    ],
    "wof:name":"O K Unisex Hairdressing",
    "wof:placetype":"venue"
},
  "geometry": {"coordinates":[-1.4644049406,52.5217208862],"type":"Point"}
}