{
  "type": "Feature",
  "properties": {
    "addr:full":"25 Paddington Street London Greater London W1U 5QX",
    "addr:housenumber":"25",
    "addr:postcode":"w1u 5qx",
    "addr:street":"Paddington Street",
    "iso:country":"GB",
    "sg:address":"25 Paddington Street",
    "sg:city":"London",
    "sg:classifiers":[
        {
            "category":"Restaurant",
            "type":"Food & Drink"
        }
    ],
    "sg:phone":"+44 20 7935 2883",
    "sg:postcode":"W1U 5QX",
    "sg:province":"Greater London",
    "sg:tags":[
        "french"
    ],
    "wof:name":"Le Muscadet",
    "wof:placetype":"venue"
},
  "geometry": {"coordinates":[-0.1550959945,51.5207138062],"type":"Point"}
}