{
  "type": "Feature",
  "properties": {
    "iso:country":"GB",
    "sg:address":"19 Back Bridge Street",
    "sg:city":"Manchester",
    "sg:classifiers":[
        {
            "category":"Restaurant",
            "type":"Food & Drink"
        },
        {
            "category":"Bars & Pubs",
            "subcategory":"Nightclub",
            "type":"Food & Drink"
        }
    ],
    "sg:phone":"+44 161 832 3117",
    "sg:postcode":"M3 2PB",
    "sg:province":"Greater Manchester",
    "sg:tags":[
        "club",
        "indian",
        "-",
        "night"
    ],
    "wof:name":"BRASSERIE BY LLOYD",
    "wof:placetype":"venue"
},
  "geometry": {"coordinates":[-2.2488090992,53.4796218872],"type":"Point"}
}