{
  "type": "Feature",
  "properties": {
    "iso:country":"GB",
    "sg:address":"2 Brookside, Dudley",
    "sg:city":"Cramlington",
    "sg:classifiers":[
        {
            "category":"Shopping",
            "subcategory":"Mobile Phones",
            "type":"Retail Goods"
        }
    ],
    "sg:postcode":"NE23 7DJ",
    "sg:province":"Northumberland",
    "sg:tags":[
        "answering",
        "telephone"
    ],
    "wof:name":"Main Office Ltd.",
    "wof:placetype":"venue"
},
  "geometry": {"coordinates":[-1.579949,55.06086],"type":"Point"}
}