{
  "type": "Feature",
  "properties": {
    "addr:full":"107 Burns Rd Willesden Greater London NW10 4DU",
    "addr:housenumber":"107",
    "addr:postcode":"nw10 4du",
    "addr:street":"Burns Rd",
    "iso:country":"GB",
    "sg:address":"107 Burns Rd",
    "sg:city":"Willesden",
    "sg:classifiers":[
        {
            "category":"Organizations",
            "subcategory":"Non-profit Organization",
            "type":"Services"
        }
    ],
    "sg:phone":"+44 20 8453 1880",
    "sg:postcode":"NW10 4DU",
    "sg:province":"Greater London",
    "sg:tags":[
        "organisation",
        "voluntary",
        "charity"
    ],
    "wof:name":"Brent Community Heath Project",
    "wof:placetype":"venue"
},
  "geometry": {"coordinates":[-0.2496079952,51.5409812927],"type":"Point"}
}