{
  "type": "Feature",
  "properties": {
    "addr:full":"52 Springfield Mount Leeds West Yorkshire LS18 5QE",
    "addr:housenumber":"52",
    "addr:postcode":"ls18 5qe",
    "addr:street":"Springfield Mount Leeds West",
    "iso:country":"GB",
    "sg:address":"52 Springfield Mount",
    "sg:city":"Leeds",
    "sg:classifiers":[
        {
            "category":"Manufacturing",
            "subcategory":"Rubber & Plastics",
            "type":"Manufacturing & Wholesale Goods"
        }
    ],
    "sg:phone":"+44 113 258 7063",
    "sg:postcode":"LS18 5QE",
    "sg:province":"West Yorkshire",
    "sg:tags":[
        "product"
    ],
    "wof:name":"P Gilpin Plastic Fabrications",
    "wof:placetype":"venue"
},
  "geometry": {"coordinates":[-1.6240539551,53.8389701843],"type":"Point"}
}