{
  "type": "Feature",
  "properties": {
    "addr:full":"126 The Oval, Clarkson Glasgow East Renfrewshire G76 8NA",
    "addr:housenumber":"126",
    "addr:postcode":"g76 8na",
    "addr:street":"The Oval",
    "iso:country":"GB",
    "sg:address":"126 The Oval, Clarkson",
    "sg:city":"Glasgow",
    "sg:classifiers":[
        {
            "category":"Professional",
            "subcategory":"Detective & Security Services",
            "type":"Services"
        }
    ],
    "sg:phone":"+44 141 571 2508",
    "sg:postcode":"G76 8NA",
    "sg:province":"East Renfrewshire",
    "sg:tags":[
        "video",
        "cctv"
    ],
    "wof:name":"Auto Electrical At Your Door",
    "wof:placetype":"venue"
},
  "geometry": {"coordinates":[-4.2689161301,55.7948455811],"type":"Point"}
}