{
  "type": "Feature",
  "properties": {
    "iso:country":"GB",
    "sg:address":"174 Whitchurch Road",
    "sg:city":"Cardiff",
    "sg:classifiers":[
        {
            "category":"Professional",
            "subcategory":"Art Services",
            "type":"Services"
        }
    ],
    "sg:phone":"+44 29 2061 3202",
    "sg:postcode":"CF14 3NB",
    "sg:province":"Cardiff",
    "sg:tags":[
        "decorating",
        "painting"
    ],
    "wof:name":"John Verrill",
    "wof:placetype":"venue"
},
  "geometry": {"coordinates":[-3.1901290417,51.5024337769],"type":"Point"}
}