{
  "type": "Feature",
  "properties": {
    "addr:full":"Prysgol, Y Ffor Pwllheli Gwynedd LL53 6UY",
    "addr:postcode":"ll53 6uy",
    "iso:country":"GB",
    "sg:address":"Prysgol, Y Ffor",
    "sg:city":"Pwllheli",
    "sg:classifiers":[
        {
            "category":"Farming",
            "subcategory":"Farm",
            "type":"Manufacturing & Wholesale Goods"
        }
    ],
    "sg:phone":"+44 1766 810100",
    "sg:postcode":"LL53 6UY",
    "sg:province":"Gwynedd",
    "sg:tags":[
        "mixed",
        "crop"
    ],
    "wof:name":"Richard Ellis",
    "wof:placetype":"venue"
},
  "geometry": {"coordinates":[-4.384869,52.925045],"type":"Point"}
}