{
  "type": "Feature",
  "properties": {
    "addr:full":"34 Clifton Road Welling Kent DA16 1QA",
    "addr:housenumber":"34",
    "addr:postcode":"da16 1qa",
    "addr:street":"Clifton Road",
    "iso:country":"GB",
    "sg:address":"34 Clifton Road",
    "sg:city":"Welling",
    "sg:classifiers":[
        {
            "category":"Building & Trades",
            "subcategory":"Plumbing",
            "type":"Services"
        }
    ],
    "sg:phone":"+44 20 8303 1273",
    "sg:postcode":"DA16 1QA",
    "sg:province":"Kent",
    "sg:tags":[
        "heating"
    ],
    "wof:name":"Gas Safe",
    "wof:placetype":"venue"
},
  "geometry": {"coordinates":[0.1158960015,51.4627342224],"type":"Point"}
}