{
  "type": "Feature",
  "properties": {
    "addr:full":"Commerce Rd Stranraer Dumfries and Galloway DG9 7DE",
    "addr:postcode":"dg9 7de",
    "addr:street":"Commerce Rd",
    "iso:country":"GB",
    "sg:address":"Commerce Rd",
    "sg:city":"Stranraer",
    "sg:classifiers":[
        {
            "category":"Manufacturing",
            "subcategory":"Building Materials",
            "type":"Manufacturing & Wholesale Goods"
        }
    ],
    "sg:phone":"+44 1776 889400",
    "sg:postcode":"DG9 7DE",
    "sg:province":"Dumfries and Galloway",
    "sg:tags":[
        "merchant",
        "builder"
    ],
    "wof:name":"Graham Builders Merchants",
    "wof:placetype":"venue"
},
  "geometry": {"coordinates":[-5.0190968513,54.8938560486],"type":"Point"}
}