{
  "type": "Feature",
  "properties": {
    "addr:full":"2, Sheen Road Richmond  TW9 1AE",
    "addr:housenumber":"2",
    "addr:postcode":"tw9 1ae",
    "addr:street":"Sheen Road",
    "iso:country":"GB",
    "sg:address":"2, Sheen Road",
    "sg:city":"Richmond",
    "sg:classifiers":[
        {
            "category":"Professional",
            "subcategory":"Computer Services",
            "type":"Services"
        }
    ],
    "sg:postcode":" TW9 1AE",
    "sg:tags":[
        "fraud",
        "financial",
        "users",
        "lost",
        "personal",
        "media",
        "identity",
        "theft",
        "access",
        "internet",
        "data"
    ],
    "sg:website":"http://www.garlik.com",
    "wof:name":"Garlik",
    "wof:placetype":"venue"
},
  "geometry": {"coordinates":[-0.295441,51.462108],"type":"Point"}
}