{
  "type": "Feature",
  "properties": {
    "addr:full":"Cook Lane Keighley West Yorkshire BD21 3PF",
    "addr:postcode":"bd21 3pf",
    "addr:street":"Cook Lane",
    "iso:country":"GB",
    "sg:address":"Cook Lane",
    "sg:city":"Keighley",
    "sg:classifiers":[
        {
            "category":"Community Center",
            "subcategory":"Social",
            "type":"Public Place"
        }
    ],
    "sg:phone":"+44 1535 690016",
    "sg:postcode":"BD21 3PF",
    "sg:province":"West Yorkshire",
    "sg:tags":[
        "frozen",
        "food",
        "freezer",
        "centre"
    ],
    "wof:name":"Farmfoods Freezer Centre",
    "wof:placetype":"venue"
},
  "geometry": {"coordinates":[-1.9084310532,53.8671531677],"type":"Point"}
}