{
  "type": "Feature",
  "properties": {
    "iso:country":"GB",
    "sg:address":"Unit 3, Grand Prix Buildings, Brough",
    "sg:city":"Kirkby Stephen",
    "sg:classifiers":[
        {
            "category":"Retail",
            "subcategory":"Car Wash",
            "type":"Services"
        },
        {
            "category":"Retail",
            "subcategory":"Auto Repair",
            "type":"Services"
        }
    ],
    "sg:phone":"+44 17683 42220",
    "sg:postcode":"CA17 4AY",
    "sg:province":"Cumbria",
    "sg:tags":[
        "body",
        "sprayer"
    ],
    "wof:name":"Brough Bodywork Services",
    "wof:placetype":"venue"
},
  "geometry": {"coordinates":[-2.348623,54.472717],"type":"Point"}
}