{
  "type": "Feature",
  "properties": {
    "iso:country":"GB",
    "sg:address":"72 Alston Drive, Bradwell Abbey",
    "sg:city":"Milton Keynes",
    "sg:classifiers":[
        {
            "category":"Professional",
            "subcategory":"Engineering",
            "type":"Services"
        }
    ],
    "sg:phone":"+44 1908 225858",
    "sg:postcode":"MK13 9HG",
    "sg:province":"Buckinghamshire",
    "sg:tags":[
        "precision",
        "engineer"
    ],
    "wof:name":"Abbey Precision Ltd.",
    "wof:placetype":"venue"
},
  "geometry": {"coordinates":[-0.793686,52.044975],"type":"Point"}
}