{
  "type": "Feature",
  "properties": {
    "addr:full":"15 Duke St Dartmouth Devon TQ6 9PY",
    "addr:housenumber":"15",
    "addr:postcode":"tq6 9py",
    "addr:street":"Duke St",
    "iso:country":"GB",
    "sg:address":"15 Duke St",
    "sg:city":"Dartmouth",
    "sg:classifiers":[
        {
            "category":"Shopping",
            "subcategory":"Books",
            "type":"Retail Goods"
        }
    ],
    "sg:phone":"+44 1803 833441",
    "sg:postcode":"TQ6 9PY",
    "sg:province":"Devon",
    "sg:tags":[
        "bookseller"
    ],
    "wof:name":"Bookends",
    "wof:placetype":"venue"
},
  "geometry": {"coordinates":[-3.579324007,50.3515586853],"type":"Point"}
}