{
  "type": "Feature",
  "properties": {
    "iso:country":"GB",
    "sg:address":"Pool Lane, Bromborough Pool",
    "sg:city":"Wirral",
    "sg:classifiers":[
        {
            "category":"Manufacturing",
            "subcategory":"Petroleum Products",
            "type":"Manufacturing & Wholesale Goods"
        },
        {
            "category":"Wholesale",
            "subcategory":"Chemicals & Plastics",
            "type":"Manufacturing & Wholesale Goods"
        }
    ],
    "sg:phone":"+44 151 643 3200",
    "sg:postcode":"CH62 4UF",
    "sg:province":"Cheshire",
    "sg:tags":[
        "allied",
        "producer"
    ],
    "wof:name":"Unichema Chemicals Ltd.",
    "wof:placetype":"venue"
},
  "geometry": {"coordinates":[-2.982345,53.35154],"type":"Point"}
}