{
  "type": "Feature",
  "properties": {
    "addr:full":"101-103 Union St Larkhall South Lanarkshire ML9 1EB",
    "addr:housenumber":"101-103",
    "addr:postcode":"ml9 1eb",
    "addr:street":"Union St",
    "iso:country":"GB",
    "sg:address":"101-103 Union St",
    "sg:city":"Larkhall",
    "sg:classifiers":[
        {
            "category":"Professional",
            "subcategory":"Business Services",
            "type":"Services"
        }
    ],
    "sg:phone":"+44 1698 888809",
    "sg:postcode":"ML9 1EB",
    "sg:province":"South Lanarkshire",
    "sg:tags":[
        "accomodation"
    ],
    "wof:name":"Larkhall Business Centre",
    "wof:placetype":"venue"
},
  "geometry": {"coordinates":[-3.973215,55.739101],"type":"Point"}
}