{
  "type": "Feature",
  "properties": {
    "addr:full":"21 Wote Street Basingstoke Hampshire RG21 7NE",
    "addr:housenumber":"21",
    "addr:postcode":"rg21 7ne",
    "addr:street":"Wote Street",
    "iso:country":"GB",
    "sg:address":"21 Wote Street",
    "sg:city":"Basingstoke",
    "sg:classifiers":[
        {
            "category":"Professional",
            "subcategory":"Employment Agencies",
            "type":"Services"
        }
    ],
    "sg:phone":"+44 1256 810400",
    "sg:postcode":"RG21 7NE",
    "sg:province":"Hampshire",
    "sg:tags":[
        "consultant"
    ],
    "wof:name":"Total Work Services Ltd.",
    "wof:placetype":"venue"
},
  "geometry": {"coordinates":[-1.0863410234,51.2634353638],"type":"Point"}
}