{
  "type": "Feature",
  "properties": {
    "iso:country":"GB",
    "sg:address":"Queen Elizabeth House, Queen Elizabeth Rd",
    "sg:city":"Wakefield",
    "sg:classifiers":[
        {
            "category":"Social Services",
            "subcategory":"Retirement Home",
            "type":"Services"
        }
    ],
    "sg:phone":"+44 1924 290990",
    "sg:postcode":"WF1 4AA",
    "sg:province":"West Yorkshire",
    "sg:tags":[
        "rest"
    ],
    "wof:name":"Wakefield & District N.V.Q Consortium",
    "wof:placetype":"venue"
},
  "geometry": {"coordinates":[-1.4875340462,53.6885910034],"type":"Point"}
}