{
  "type": "Feature",
  "properties": {
    "addr:full":"Green Barns Farm, Green Barns Lane Lichfield Staffordshire WS14 0QN",
    "addr:postcode":"ws14 0qn",
    "addr:street":"Farm Green Barns Lane",
    "iso:country":"GB",
    "sg:address":"Green Barns Farm, Green Barns Lane",
    "sg:city":"Lichfield",
    "sg:classifiers":[
        {
            "category":"Food & Beverages",
            "subcategory":"Farmers Market",
            "type":"Retail Goods"
        }
    ],
    "sg:phone":"+44 1543 481208",
    "sg:postcode":"WS14 0QN",
    "sg:province":"Staffordshire",
    "sg:tags":[
        "gardener"
    ],
    "wof:name":"K Morton & Sons",
    "wof:placetype":"venue"
},
  "geometry": {"coordinates":[-1.8222340345,52.6137046814],"type":"Point"}
}