{
  "type": "Feature",
  "properties": {
    "addr:full":"11 Larchwood Bishops Stortford Essex CM23 4JS",
    "addr:housenumber":"11",
    "addr:postcode":"cm23 4js",
    "addr:street":"Larchwood Bishops",
    "iso:country":"GB",
    "sg:address":"11 Larchwood",
    "sg:city":"Bishops Stortford",
    "sg:classifiers":[
        {
            "category":"Coffee & Tea",
            "type":"Food & Drink"
        }
    ],
    "sg:postcode":"CM23 4JS",
    "sg:province":"Essex",
    "wof:name":"McKewans Tea Shop",
    "wof:placetype":"venue"
},
  "geometry": {"coordinates":[0.1428570002,51.8599014282],"type":"Point"}
}