{
  "type": "Feature",
  "properties": {
    "addr:full":"Low Corner Farm, March Riverside, Upwell Wisbech Cambridgeshire PE14 9AT",
    "addr:postcode":"pe14 9at",
    "addr:street":"March Riverside",
    "iso:country":"GB",
    "sg:address":"Low Corner Farm, March Riverside, Upwell",
    "sg:city":"Wisbech",
    "sg:classifiers":[
        {
            "category":"Farming",
            "subcategory":"Livestock Farm",
            "type":"Manufacturing & Wholesale Goods"
        }
    ],
    "sg:phone":"+44 1945 773221",
    "sg:postcode":"PE14 9AT",
    "sg:province":"Cambridgeshire",
    "sg:tags":[
        "others"
    ],
    "wof:name":"C Clark & Sons",
    "wof:placetype":"venue"
},
  "geometry": {"coordinates":[0.211009,52.598125],"type":"Point"}
}