{
  "type": "Feature",
  "properties": {
    "addr:full":"10 Castleton Road, Hope Valley Sheffield Derbyshire S33 6RD",
    "addr:housenumber":"10",
    "addr:postcode":"s33 6rd",
    "addr:street":"Castleton Road",
    "iso:country":"GB",
    "sg:address":"10 Castleton Road, Hope Valley",
    "sg:city":"Sheffield",
    "sg:classifiers":[
        {
            "category":"Food & Beverages",
            "subcategory":"Fruits & Vegetables",
            "type":"Retail Goods"
        }
    ],
    "sg:phone":"+44 1433 620249",
    "sg:postcode":"S33 6RD",
    "sg:province":"Derbyshire",
    "sg:tags":[
        "greengrocer"
    ],
    "wof:name":"Peak Fruits",
    "wof:placetype":"venue"
},
  "geometry": {"coordinates":[-1.7505949736,53.3479728699],"type":"Point"}
}