{
  "type": "Feature",
  "properties": {
    "addr:full":"Glory Paper Mill, Wooburn Green High Wycombe Buckinghamshire HP10 0DB",
    "addr:postcode":"hp10 0db",
    "addr:street":"Wooburn Green",
    "iso:country":"GB",
    "sg:address":"Glory Paper Mill, Wooburn Green",
    "sg:city":"High Wycombe",
    "sg:classifiers":[
        {
            "category":"Manufacturing",
            "subcategory":"Paper Products",
            "type":"Manufacturing & Wholesale Goods"
        }
    ],
    "sg:phone":"+44 1628 524751",
    "sg:postcode":"HP10 0DB",
    "sg:province":"Buckinghamshire",
    "sg:tags":[
        "mill",
        "pulp"
    ],
    "wof:name":"Felix Schoeller Ltd",
    "wof:placetype":"venue"
},
  "geometry": {"coordinates":[-0.6836469769,51.5882453918],"type":"Point"}
}