{
  "type": "Feature",
  "properties": {
    "iso:country":"GB",
    "sg:address":"1 Briar Way, Tonteg",
    "sg:city":"Pontypridd",
    "sg:classifiers":[
        {
            "category":"Professional",
            "subcategory":"Business Services",
            "type":"Services"
        }
    ],
    "sg:postcode":"CF38 1NR",
    "sg:province":"Rhondda, Cynon, Taff",
    "sg:tags":[
        "accomodation"
    ],
    "wof:name":"Localplan Ltd",
    "wof:placetype":"venue"
},
  "geometry": {"coordinates":[-3.310068,51.566818],"type":"Point"}
}