{
  "type": "Feature",
  "properties": {
    "addr:full":"5 The Market Place Chesterfield Derbyshire S40 1TW",
    "addr:housenumber":"5",
    "addr:postcode":"s40 1tw",
    "addr:street":"The Market Place",
    "iso:country":"GB",
    "sg:address":"5 The Market Place",
    "sg:city":"Chesterfield",
    "sg:classifiers":[
        {
            "category":"Shopping",
            "subcategory":"Musical Instruments",
            "type":"Retail Goods"
        }
    ],
    "sg:phone":"+44 1246 271177",
    "sg:postcode":"S40 1TW",
    "sg:province":"Derbyshire",
    "sg:tags":[
        "music",
        "sheet"
    ],
    "wof:name":"C E Hudson & Son Ltd.",
    "wof:placetype":"venue"
},
  "geometry": {"coordinates":[-1.4280990362,53.2356109619],"type":"Point"}
}