{
  "type": "Feature",
  "properties": {
    "addr:full":"7 Limes Rd Folkestone Kent CT19 4AU",
    "addr:housenumber":"7",
    "addr:postcode":"ct19 4au",
    "addr:street":"Limes Rd",
    "iso:country":"GB",
    "sg:address":"7 Limes Rd",
    "sg:city":"Folkestone",
    "sg:classifiers":[
        {
            "category":"Personal",
            "type":"Services"
        }
    ],
    "sg:phone":"+44 1303 276207",
    "sg:postcode":"CT19 4AU",
    "sg:province":"Kent",
    "sg:tags":[
        "wedding"
    ],
    "wof:name":"Limelight",
    "wof:placetype":"venue"
},
  "geometry": {"coordinates":[1.1546510458,51.0851364136],"type":"Point"}
}