{
  "type": "Feature",
  "properties": {
    "addr:full":"16 Bradmore Grn, Brookmans Park Hatfield Hertfordshire AL9 7QW",
    "addr:housenumber":"16",
    "addr:postcode":"al9 7qw",
    "addr:street":"Bradmore Grn;Park",
    "iso:country":"GB",
    "sg:address":"16 Bradmore Grn, Brookmans Park",
    "sg:city":"Hatfield",
    "sg:classifiers":[
        {
            "category":"Restaurant",
            "type":"Food & Drink"
        }
    ],
    "sg:phone":"+44 1707 649171",
    "sg:postcode":"AL9 7QW",
    "sg:province":"Hertfordshire",
    "sg:tags":[
        "chinese"
    ],
    "wof:name":"Jade Cottage",
    "wof:placetype":"venue"
},
  "geometry": {"coordinates":[-0.202219,51.722157],"type":"Point"}
}