{
  "type": "Feature",
  "properties": {
    "iso:country":"GB",
    "sg:address":"Dutton House, Etnam Street",
    "sg:city":"Leominster",
    "sg:classifiers":[
        {
            "category":"Professional",
            "subcategory":"Art Services",
            "type":"Services"
        }
    ],
    "sg:phone":"+44 1568 612583",
    "sg:postcode":"HR6 8AQ",
    "sg:province":"Herefordshire",
    "sg:tags":[
        "photographer"
    ],
    "wof:name":"Dutton House Studios",
    "wof:placetype":"venue"
},
  "geometry": {"coordinates":[-2.732742,52.22646],"type":"Point"}
}