{
  "type": "Feature",
  "properties": {
    "iso:country":"GB",
    "sg:address":"19 New Heston Road, Heston",
    "sg:city":"Hounslow",
    "sg:classifiers":[
        {
            "category":"Fast Food",
            "type":"Food & Drink"
        }
    ],
    "sg:phone":"+44 20 8569 4772",
    "sg:postcode":"TW5 0LW",
    "sg:province":"Greater London",
    "sg:tags":[
        "away",
        "take"
    ],
    "wof:name":"Quick Bite Sandwich Bar",
    "wof:placetype":"venue"
},
  "geometry": {"coordinates":[-0.374888,51.485531],"type":"Point"}
}