{
  "type": "Feature",
  "properties": {
    "addr:full":"Unit 1 Esme House, Coronation Road Basingstoke Hampshire RG21 4ET",
    "addr:housenumber":"unit 1 esme house",
    "addr:postcode":"rg21 4et",
    "addr:street":"Coronation Road",
    "iso:country":"GB",
    "sg:address":"Unit 1 Esme House, Coronation Road",
    "sg:city":"Basingstoke",
    "sg:classifiers":[
        {
            "category":"Professional",
            "subcategory":"Engineering",
            "type":"Services"
        }
    ],
    "sg:phone":"+44 1256 326694",
    "sg:postcode":"RG21 4ET",
    "sg:province":"Hampshire",
    "sg:tags":[
        "precision",
        "engineer"
    ],
    "wof:name":"Ilsley & Challis Ltd.",
    "wof:placetype":"venue"
},
  "geometry": {"coordinates":[-1.077159,51.271366],"type":"Point"}
}