{
  "type": "Feature",
  "properties": {
    "iso:country":"GB",
    "sg:address":"Unit 1 Esme House, Coronation Road",
    "sg:city":"Basingstoke",
    "sg:classifiers":[
        {
            "category":"Professional",
            "subcategory":"Engineering",
            "type":"Services"
        }
    ],
    "sg:phone":"+44 1256 326694",
    "sg:postcode":"RG21 4ET",
    "sg:province":"Hampshire",
    "sg:tags":[
        "precision",
        "engineer"
    ],
    "wof:name":"Ilsley & Challis Ltd.",
    "wof:placetype":"venue"
},
  "geometry": {"coordinates":[-1.077159,51.271366],"type":"Point"}
}