{
  "type": "Feature",
  "properties": {
    "addr:full":"11 King St, Delph Oldham Lancashire OL3 5DL",
    "addr:housenumber":"11",
    "addr:postcode":"ol3 5dl",
    "addr:street":"King St",
    "iso:country":"GB",
    "sg:address":"11 King St, Delph",
    "sg:city":"Oldham",
    "sg:classifiers":[
        {
            "category":"Home & Garden",
            "subcategory":"Hardware",
            "type":"Retail Goods"
        }
    ],
    "sg:phone":"+44 1457 871026",
    "sg:postcode":"OL3 5DL",
    "sg:province":"Lancashire",
    "wof:name":"Cockcroft,Arthur,",
    "wof:placetype":"venue"
},
  "geometry": {"coordinates":[-2.023566,53.567356],"type":"Point"}
}