{
  "type": "Feature",
  "properties": {
    "addr:full":"3 St Johns Drive, North Rigton Leeds North Yorkshire LS17 0HD",
    "addr:housenumber":"3",
    "addr:postcode":"ls17 0hd",
    "addr:street":"St Johns Drive North Rigton Leeds",
    "iso:country":"GB",
    "sg:address":"3 St Johns Drive, North Rigton",
    "sg:city":"Leeds",
    "sg:classifiers":[
        {
            "category":"Real Estate",
            "subcategory":"Real Estate Agent",
            "type":"Services"
        }
    ],
    "sg:phone":"+44 1423 734007",
    "sg:postcode":"LS17 0HD",
    "sg:province":"North Yorkshire",
    "wof:name":"Rowbotham & Partners Chartered Surveyors",
    "wof:placetype":"venue"
},
  "geometry": {"coordinates":[-1.576480031,53.9369316101],"type":"Point"}
}