{
  "type": "Feature",
  "properties": {
    "iso:country":"GB",
    "sg:address":"42 High St",
    "sg:city":"Biggar",
    "sg:classifiers":[
        {
            "category":"Shopping",
            "subcategory":"Gifts & Souvenirs",
            "type":"Retail Goods"
        }
    ],
    "sg:phone":"+44 1899 220641",
    "sg:postcode":"ML12 6BJ",
    "sg:province":"Dumfries and Galloway",
    "sg:tags":[
        "shop"
    ],
    "wof:name":"Treasure Trove",
    "wof:placetype":"venue"
},
  "geometry": {"coordinates":[-3.525845,55.623253],"type":"Point"}
}