{
  "type": "Feature",
  "properties": {
    "iso:country":"GB",
    "sg:address":"Kwiksave, 20 Brighton Road",
    "sg:city":"Liverpool",
    "sg:classifiers":[
        {
            "category":"Fast Food",
            "type":"Food & Drink"
        }
    ],
    "sg:postcode":"L22 5NG",
    "sg:province":"Merseyside",
    "sg:tags":[
        "away",
        "take"
    ],
    "wof:name":"Robert Powell",
    "wof:placetype":"venue"
},
  "geometry": {"coordinates":[-3.02833,53.475842],"type":"Point"}
}