{
  "type": "Feature",
  "properties": {
    "addr:full":"C/o Appleton Commercials, The Distribution Centre, Lowfield Lane St Helens Cheshire WA9 5BH",
    "addr:postcode":"wa9 5bh",
    "addr:street":"C;Lowfield Lane",
    "iso:country":"GB",
    "sg:address":"C/o Appleton Commercials, The Distribution Centre, Lowfield Lane",
    "sg:city":"St Helens",
    "sg:classifiers":[
        {
            "category":"Retail",
            "subcategory":"Auto Rental",
            "type":"Services"
        }
    ],
    "sg:phone":"+44 1744 812022",
    "sg:postcode":"WA9 5BH",
    "sg:province":"Cheshire",
    "sg:tags":[
        "truck",
        "hire",
        "van"
    ],
    "wof:name":"City Transport Ltd.",
    "wof:placetype":"venue"
},
  "geometry": {"coordinates":[-2.7458999157,53.4241104126],"type":"Point"}
}