{
  "type": "Feature",
  "properties": {
    "iso:country":"GB",
    "sg:address":"34 Oxford Road",
    "sg:city":"Clacton-on-sea",
    "sg:classifiers":[
        {
            "category":"Professional",
            "subcategory":"Engineering",
            "type":"Services"
        }
    ],
    "sg:phone":"+44 1255 423723",
    "sg:postcode":"CO15 3TB",
    "sg:province":"Essex",
    "sg:tags":[
        "precision",
        "engineer"
    ],
    "wof:name":"Towler Engineering Ltd.",
    "wof:placetype":"venue"
},
  "geometry": {"coordinates":[1.154918,51.796112],"type":"Point"}
}