{
  "type": "Feature",
  "properties": {
    "addr:full":"14 Market Place, Oundle Peterborough Cambridgeshire PE8 4BQ",
    "addr:housenumber":"14",
    "addr:postcode":"pe8 4bq",
    "addr:street":"Market Place",
    "iso:country":"GB",
    "sg:address":"14 Market Place, Oundle",
    "sg:city":"Peterborough",
    "sg:classifiers":[
        {
            "category":"Food & Beverages",
            "subcategory":"Fruits & Vegetables",
            "type":"Retail Goods"
        }
    ],
    "sg:phone":"+44 1832 273545",
    "sg:postcode":"PE8 4BQ",
    "sg:province":"Cambridgeshire",
    "sg:tags":[
        "greengrocer"
    ],
    "wof:name":"J W Norman & Son",
    "wof:placetype":"venue"
},
  "geometry": {"coordinates":[-0.4675210118,52.4806175232],"type":"Point"}
}