{
  "type": "Feature",
  "properties": {
    "iso:country":"GB",
    "sg:address":"Unit H Business Centre, Brue Av, Colley Lane Indust Est",
    "sg:city":"Bridgwater",
    "sg:classifiers":[
        {
            "category":"Home & Garden",
            "subcategory":"Carpets & Floor Coverings",
            "type":"Retail Goods"
        }
    ],
    "sg:phone":"+44 1278 426442",
    "sg:postcode":"TA6 5LT",
    "sg:province":"Somerset",
    "sg:tags":[
        "cleaner",
        "upholstery"
    ],
    "wof:name":"Ace Carpet & Upholstery Cleaning",
    "wof:placetype":"venue"
},
  "geometry": {"coordinates":[-3.013824,51.127556],"type":"Point"}
}