{
  "type": "Feature",
  "properties": {
    "addr:full":"Booking Office, 17 Copperfield Dr Maidstone Kent ME17 1SY",
    "addr:housenumber":"17",
    "addr:postcode":"me17 1sy",
    "addr:street":"Copperfield Dr",
    "iso:country":"GB",
    "sg:address":"Booking Office, 17 Copperfield Dr",
    "sg:city":"Maidstone",
    "sg:classifiers":[
        {
            "category":"Government",
            "subcategory":"City Hall",
            "type":"Public Place"
        }
    ],
    "sg:phone":"+44 1622 861457",
    "sg:postcode":"ME17 1SY",
    "sg:province":"Kent",
    "wof:name":"Langley Village Hall",
    "wof:placetype":"venue"
},
  "geometry": {"coordinates":[0.5976499915,51.2364196777],"type":"Point"}
}