{
  "type": "Feature",
  "properties": {
    "addr:full":"102 Queens Drive Bedford Bedfordshire MK41 9BS",
    "addr:housenumber":"102",
    "addr:postcode":"mk41 9bs",
    "addr:street":"Queens Drive",
    "iso:country":"GB",
    "sg:address":"102 Queens Drive",
    "sg:city":"Bedford",
    "sg:classifiers":[
        {
            "category":"Personal",
            "subcategory":"Beauty Salon",
            "type":"Services"
        }
    ],
    "sg:phone":"+44 1234 267308",
    "sg:postcode":"MK41 9BS",
    "sg:province":"Bedfordshire",
    "sg:tags":[
        "lady",
        "hairdresser"
    ],
    "wof:name":"Style Ninety",
    "wof:placetype":"venue"
},
  "geometry": {"coordinates":[-0.439665,52.149174],"type":"Point"}
}