{
  "type": "Feature",
  "properties": {
    "addr:full":"12a Dragonville Industrial Park, Dragon Lane Durham Durham DH1 2XH",
    "addr:housenumber":"12a",
    "addr:postcode":"dh1 2xh",
    "addr:street":"Dragonville Industrial Park Dragon Lane",
    "iso:country":"GB",
    "sg:address":"12a Dragonville Industrial Park, Dragon Lane",
    "sg:city":"Durham",
    "sg:classifiers":[
        {
            "category":"Home & Garden",
            "subcategory":"Furniture",
            "type":"Retail Goods"
        }
    ],
    "sg:postcode":"DH1 2XH",
    "sg:province":"Durham",
    "wof:name":"The Suite Warehouse",
    "wof:placetype":"venue"
},
  "geometry": {"coordinates":[-1.5438840389,54.7763748169],"type":"Point"}
}