{
  "type": "Feature",
  "properties": {
    "addr:full":"7 Brookfield Gro Ashton-under-lyne Greater Manchester OL6 6TL",
    "addr:housenumber":"7",
    "addr:postcode":"ol6 6tl",
    "addr:street":"Brookfield Gro Ashton-Under-Lyne",
    "iso:country":"GB",
    "sg:address":"7 Brookfield Gro",
    "sg:city":"Ashton-under-lyne",
    "sg:classifiers":[
        {
            "category":"Personal",
            "type":"Services"
        }
    ],
    "sg:phone":"+44 161 343 3616",
    "sg:postcode":"OL6 6TL",
    "sg:province":"Greater Manchester",
    "sg:tags":[
        "delivery"
    ],
    "wof:name":"Smart Moves",
    "wof:placetype":"venue"
},
  "geometry": {"coordinates":[-2.082074,53.485615],"type":"Point"}
}