{
  "type": "Feature",
  "properties": {
    "addr:full":"Cliff Rd Wilmslow Cheshire SK9 4AA",
    "addr:postcode":"sk9 4aa",
    "addr:street":"Cliff Rd",
    "iso:country":"GB",
    "sg:address":"Cliff Rd",
    "sg:city":"Wilmslow",
    "sg:classifiers":[
        {
            "category":"Place Of Worship",
            "type":"Public Place"
        }
    ],
    "sg:phone":"+44 1625 539265",
    "sg:postcode":"SK9 4AA",
    "sg:province":"Cheshire",
    "wof:name":"St Bartholomew C Of E Parish Church",
    "wof:placetype":"venue"
},
  "geometry": {"coordinates":[-2.230374,53.33115],"type":"Point"}
}