{
  "type": "Feature",
  "properties": {
    "iso:country":"GB",
    "sg:address":"2 Oxford Rd",
    "sg:city":"Uxbridge",
    "sg:classifiers":[
        {
            "category":"Autos & Motor Vehicles",
            "subcategory":"Automobile Sales",
            "type":"Retail Goods"
        }
    ],
    "sg:phone":"+44 1895 231731",
    "sg:postcode":"UB9 4DQ",
    "sg:province":"Buckinghamshire",
    "sg:tags":[
        "car"
    ],
    "wof:name":"Motor Motion",
    "wof:placetype":"venue"
},
  "geometry": {"coordinates":[-0.486194998,51.5515098572],"type":"Point"}
}