{
  "type": "Feature",
  "properties": {
    "addr:full":"66-70 Cauldwell Street Bedford Bedfordshire MK42 9AL",
    "addr:housenumber":"66-70",
    "addr:postcode":"mk42 9al",
    "addr:street":"Cauldwell Street",
    "iso:country":"GB",
    "sg:address":"66-70 Cauldwell Street",
    "sg:city":"Bedford",
    "sg:classifiers":[
        {
            "category":"Building & Trades",
            "subcategory":"Equipment Rental",
            "type":"Services"
        }
    ],
    "sg:phone":"+44 1234 352223",
    "sg:postcode":"MK42 9AL",
    "sg:province":"Bedfordshire",
    "sg:tags":[
        "hire",
        "centre"
    ],
    "wof:name":"Hss Hire Shops",
    "wof:placetype":"venue"
},
  "geometry": {"coordinates":[-0.47169,52.130138],"type":"Point"}
}