{
  "type": "Feature",
  "properties": {
    "addr:full":"Kent House, Island Road Canterbury Kent CT3 4BZ",
    "addr:postcode":"ct3 4bz",
    "addr:street":"Island Road",
    "iso:country":"GB",
    "sg:address":"Kent House, Island Road",
    "sg:city":"Canterbury",
    "sg:classifiers":[
        {
            "category":"Banks & Credit Unions",
            "subcategory":"Financial Services",
            "type":"Services"
        }
    ],
    "sg:phone":"+44 1227 860175",
    "sg:postcode":"CT3 4BZ",
    "sg:province":"Kent",
    "sg:tags":[
        "adviser"
    ],
    "wof:name":"Richard Thomas Associates",
    "wof:placetype":"venue"
},
  "geometry": {"coordinates":[1.171161,51.316971],"type":"Point"}
}