{
  "type": "Feature",
  "properties": {
    "iso:country":"GB",
    "sg:address":"9 Tonbridge Chambers, Pembury Road",
    "sg:city":"Tonbridge",
    "sg:classifiers":[
        {
            "category":"Sports & Exercise",
            "subcategory":"Athletic Track",
            "type":"Entertainment"
        }
    ],
    "sg:phone":"+44 1732 363443",
    "sg:postcode":"TN9 2HZ",
    "sg:province":"Kent",
    "sg:tags":[
        "course",
        "damp",
        "mnfrs"
    ],
    "wof:name":"Z Led (D P C) Co. Ltd.",
    "wof:placetype":"venue"
},
  "geometry": {"coordinates":[0.27634,51.199829],"type":"Point"}
}