{
  "type": "Feature",
  "properties": {
    "addr:full":"Hall Green Stadium, York Road Birmingham West Midlands B28 8LQ",
    "addr:postcode":"b28 8lq",
    "addr:street":"York Road",
    "iso:country":"GB",
    "sg:address":"Hall Green Stadium, York Road",
    "sg:city":"Birmingham",
    "sg:classifiers":[
        {
            "category":"Travel",
            "subcategory":"Hotels & Motels",
            "type":"Entertainment"
        }
    ],
    "sg:phone":"+44 121 777 3480",
    "sg:postcode":"B28 8LQ",
    "sg:province":"West Midlands",
    "wof:name":"The Lodge At Hall Green",
    "wof:placetype":"venue"
},
  "geometry": {"coordinates":[-1.84055,52.438622],"type":"Point"}
}