{
  "type": "Feature",
  "properties": {
    "iso:country":"GB",
    "sg:address":"Oaks Cottage, Abbots Hill, Ospringe",
    "sg:city":"Faversham",
    "sg:classifiers":[
        {
            "category":"Building & Trades",
            "subcategory":"Construction",
            "type":"Services"
        }
    ],
    "sg:phone":"+44 1795 531021",
    "sg:postcode":"ME13 0RR",
    "sg:province":"Kent",
    "sg:tags":[
        "roofing",
        "contracting"
    ],
    "wof:name":"Alan Childs Roofing",
    "wof:placetype":"venue"
},
  "geometry": {"coordinates":[0.88344,51.309605],"type":"Point"}
}