{
  "type": "Feature",
  "properties": {
    "addr:full":"43 Main Street, Bainsford Falkirk Falkirk FK2 7NY",
    "addr:housenumber":"43",
    "addr:postcode":"fk2 7ny",
    "addr:street":"Main Street",
    "iso:country":"GB",
    "sg:address":"43 Main Street, Bainsford",
    "sg:city":"Falkirk",
    "sg:classifiers":[
        {
            "category":"Building & Trades",
            "subcategory":"Equipment Rental",
            "type":"Services"
        }
    ],
    "sg:phone":"+44 1324 612850",
    "sg:postcode":"FK2 7NY",
    "sg:province":"Falkirk",
    "sg:tags":[
        "plant",
        "tool",
        "hire",
        "centre"
    ],
    "sg:website":"http://www.hewden.co.uk",
    "wof:name":"Hewden Hire Centres Ltd",
    "wof:placetype":"venue"
},
  "geometry": {"coordinates":[-3.786999,56.011902],"type":"Point"}
}