{
  "type": "Feature",
  "properties": {
    "iso:country":"GB",
    "sg:address":"Meole Brace Retail Park",
    "sg:city":"Shrewsbury",
    "sg:classifiers":[
        {
            "category":"Fast Food",
            "type":"Food & Drink"
        }
    ],
    "sg:phone":"+44 1743 353259",
    "sg:postcode":"SY3 9NB",
    "sg:province":"Shropshire",
    "sg:tags":[
        "away",
        "take"
    ],
    "wof:name":"McDonalds Restaurants Ltd.",
    "wof:placetype":"venue"
},
  "geometry": {"coordinates":[-2.756254,52.69072],"type":"Point"}
}