{
  "type": "Feature",
  "properties": {
    "addr:full":"123 Longfield La, Hallam Fields Ilkeston Derbyshire DE7 4DD",
    "addr:housenumber":"123",
    "addr:postcode":"de7 4dd",
    "addr:street":"Longfield La Hallam",
    "iso:country":"GB",
    "sg:address":"123 Longfield La, Hallam Fields",
    "sg:city":"Ilkeston",
    "sg:classifiers":[
        {
            "category":"Travel",
            "subcategory":"Hotels & Motels",
            "type":"Entertainment"
        }
    ],
    "sg:phone":"+44 115 944 1061",
    "sg:postcode":"DE7 4DD",
    "sg:province":"Derbyshire",
    "sg:tags":[
        "house",
        "guest"
    ],
    "wof:name":"Wayside Guest House",
    "wof:placetype":"venue"
},
  "geometry": {"coordinates":[-1.3026390076,52.9569015503],"type":"Point"}
}