{
  "type": "Feature",
  "properties": {
    "addr:full":"Unit 5 Bosleake Rural Workshops, Whitcross Hill Redruth Cornwall TR15 3YG",
    "addr:housenumber":"unit 5",
    "addr:postcode":"tr15 3yg",
    "addr:street":"Bosleake;Whitcross Hill",
    "iso:country":"GB",
    "sg:address":"Unit 5 Bosleake Rural Workshops, Whitcross Hill",
    "sg:city":"Redruth",
    "sg:classifiers":[
        {
            "category":"Manufacturing",
            "subcategory":"Metals",
            "type":"Manufacturing & Wholesale Goods"
        }
    ],
    "sg:phone":"+44 1209 710621",
    "sg:postcode":"TR15 3YG",
    "sg:province":"Cornwall",
    "sg:tags":[
        "ore"
    ],
    "wof:name":"Robinco Mining Ltd.",
    "wof:placetype":"venue"
},
  "geometry": {"coordinates":[-5.2294340134,50.232509613],"type":"Point"}
}