{
  "type": "Feature",
  "properties": {
    "iso:country":"GB",
    "sg:address":"Bradley Road",
    "sg:city":"Newquay",
    "sg:classifiers":[
        {
            "category":"Education",
            "subcategory":"School",
            "type":"Public Place"
        }
    ],
    "sg:phone":"+44 1637 872076",
    "sg:postcode":"TR7 3JA",
    "sg:province":"Cornwall",
    "sg:tags":[
        "local",
        "authority"
    ],
    "wof:name":"Newquay Treviglas School",
    "wof:placetype":"venue"
},
  "geometry": {"coordinates":[-5.050159,50.419994],"type":"Point"}
}