{
  "type": "Feature",
  "properties": {
    "iso:country":"GB",
    "sg:address":"16 Station Road",
    "sg:city":"Normanton",
    "sg:classifiers":[
        {
            "category":"Utilities",
            "type":"Services"
        }
    ],
    "sg:phone":"+44 1924 895624",
    "sg:postcode":"WF6 2NE",
    "sg:province":"West Yorkshire",
    "sg:tags":[
        "broker"
    ],
    "wof:name":"Kilby Utility & Technical Services",
    "wof:placetype":"venue"
},
  "geometry": {"coordinates":[-1.4285570383,53.7043533325],"type":"Point"}
}