{
  "type": "Feature",
  "properties": {
    "iso:country":"GB",
    "sg:address":"839 Dunstable Road",
    "sg:city":"Luton",
    "sg:classifiers":[
        {
            "category":"Building & Trades",
            "subcategory":"Construction",
            "type":"Services"
        }
    ],
    "sg:phone":"+44 1582 583885",
    "sg:postcode":"LU4 0HW",
    "sg:province":"Bedfordshire",
    "sg:tags":[
        "contractor"
    ],
    "wof:name":"Brook View Construction",
    "wof:placetype":"venue"
},
  "geometry": {"coordinates":[-0.4810479879,51.8920669556],"type":"Point"}
}