{
  "type": "Feature",
  "properties": {
    "iso:country":"GB",
    "sg:address":"Spring Bank Road",
    "sg:city":"Chesterfield",
    "sg:classifiers":[
        {
            "category":"Community Center",
            "subcategory":"Youth",
            "type":"Public Place"
        }
    ],
    "sg:phone":"+44 1246 275876",
    "sg:postcode":"S40 1NL",
    "sg:province":"Derbyshire",
    "sg:tags":[
        "organisation",
        "centre"
    ],
    "wof:name":"Spring Bank Youth & Community Centre",
    "wof:placetype":"venue"
},
  "geometry": {"coordinates":[-1.437869,53.237514],"type":"Point"}
}