{
  "type": "Feature",
  "properties": {
    "addr:full":"21 Radstock Road, Stretford Manchester Cheshire M32 0AJ",
    "addr:housenumber":"21",
    "addr:postcode":"m32 0aj",
    "addr:street":"Radstock Road",
    "iso:country":"GB",
    "sg:address":"21 Radstock Road, Stretford",
    "sg:city":"Manchester",
    "sg:classifiers":[
        {
            "category":"Building & Trades",
            "subcategory":"Construction",
            "type":"Services"
        }
    ],
    "sg:phone":"+44 161 865 7620",
    "sg:postcode":"M32 0AJ",
    "sg:province":"Cheshire",
    "sg:tags":[
        "joiner",
        "carpenter"
    ],
    "wof:name":"B & J Joiner & Builder",
    "wof:placetype":"venue"
},
  "geometry": {"coordinates":[-2.3119499683,53.4509124756],"type":"Point"}
}