{
  "type": "Feature",
  "properties": {
    "addr:full":"Dock Office, Trafford Road Salford Greater Manchester M5 2XB",
    "addr:postcode":"m5 2xb",
    "addr:street":"Trafford Road",
    "iso:country":"GB",
    "sg:address":"Dock Office, Trafford Road",
    "sg:city":"Salford",
    "sg:classifiers":[
        {
            "category":"Communications",
            "type":"Services"
        }
    ],
    "sg:postcode":"M5 2XB",
    "sg:province":"Greater Manchester",
    "sg:tags":[
        "audio-visual"
    ],
    "wof:name":"Equinox Film & Tv Production",
    "wof:placetype":"venue"
},
  "geometry": {"coordinates":[-2.32564,53.468399],"type":"Point"}
}