{
  "type": "Feature",
  "properties": {
    "addr:full":"14 Causeway Avenue Warrington Cheshire WA4 6QQ",
    "addr:housenumber":"14",
    "addr:postcode":"wa4 6qq",
    "addr:street":"Causeway Avenue",
    "iso:country":"GB",
    "sg:address":"14 Causeway Avenue",
    "sg:city":"Warrington",
    "sg:classifiers":[
        {
            "category":"Building & Trades",
            "subcategory":"Construction",
            "type":"Services"
        }
    ],
    "sg:phone":"+44 1925 496969",
    "sg:postcode":"WA4 6QQ",
    "sg:province":"Cheshire",
    "sg:tags":[
        "builder"
    ],
    "wof:name":"C B S",
    "wof:placetype":"venue"
},
  "geometry": {"coordinates":[-2.5869760513,53.3800086975],"type":"Point"}
}