{
  "type": "Feature",
  "properties": {
    "addr:full":"Blackbraes Road, East Kilbride Glasgow South Lanarkshire G74 3JY",
    "addr:postcode":"g74 3jy",
    "addr:street":"Blackbraes Road",
    "iso:country":"GB",
    "sg:address":"Blackbraes Road, East Kilbride",
    "sg:city":"Glasgow",
    "sg:classifiers":[
        {
            "category":"Government",
            "subcategory":"City Hall",
            "type":"Public Place"
        },
        {
            "category":"Government",
            "subcategory":"Office",
            "type":"Public Place"
        }
    ],
    "sg:phone":"+44 1355 237776",
    "sg:postcode":"G74 3JY",
    "sg:province":"South Lanarkshire",
    "sg:tags":[
        "local"
    ],
    "wof:name":"Calderwood Community Hall",
    "wof:placetype":"venue"
},
  "geometry": {"coordinates":[-4.156378,55.776276],"type":"Point"}
}