{
  "type": "Feature",
  "properties": {
    "addr:full":"10 The Quay Dartmouth Devon TQ6 9PS",
    "addr:housenumber":"10",
    "addr:postcode":"tq6 9ps",
    "addr:street":"The Quay",
    "iso:country":"GB",
    "sg:address":"10 The Quay",
    "sg:city":"Dartmouth",
    "sg:classifiers":[
        {
            "category":"Health Services",
            "subcategory":"Optometrist",
            "type":"Services"
        }
    ],
    "sg:phone":"+44 1803 832727",
    "sg:postcode":"TQ6 9PS",
    "sg:province":"Devon",
    "sg:tags":[
        "optician"
    ],
    "wof:name":"Batemans (Opticians) Ltd.",
    "wof:placetype":"venue"
},
  "geometry": {"coordinates":[-3.5785830021,50.3514976501],"type":"Point"}
}