{
  "type": "Feature",
  "properties": {
    "addr:full":"Roxene, Deans Drove, Lytchett Matravers Poole Dorset BH16 6EQ",
    "addr:postcode":"bh16 6eq",
    "addr:street":"Deans Drove",
    "iso:country":"GB",
    "sg:address":"Roxene, Deans Drove, Lytchett Matravers",
    "sg:city":"Poole",
    "sg:classifiers":[
        {
            "category":"Retail",
            "subcategory":"Auto Repair",
            "type":"Services"
        }
    ],
    "sg:phone":"+44 1202 624105",
    "sg:postcode":"BH16 6EQ",
    "sg:province":"Dorset",
    "sg:tags":[
        "modification",
        "garage",
        "related"
    ],
    "wof:name":"Roy's Mobile Clutch Service",
    "wof:placetype":"venue"
},
  "geometry": {"coordinates":[-2.077753,50.751846],"type":"Point"}
}