{
  "type": "Feature",
  "properties": {
    "addr:full":"14 High Street Slough Berkshire SL1 1EE",
    "addr:housenumber":"14",
    "addr:postcode":"sl1 1ee",
    "addr:street":"High Street",
    "iso:country":"GB",
    "sg:address":"14 High Street",
    "sg:city":"Slough",
    "sg:classifiers":[
        {
            "category":"Professional",
            "type":"Services"
        }
    ],
    "sg:postcode":"SL1 1EE",
    "sg:province":"Berkshire",
    "sg:tags":[
        "caterer"
    ],
    "wof:name":"D & L Caterers",
    "wof:placetype":"venue"
},
  "geometry": {"coordinates":[-0.598089,51.510159],"type":"Point"}
}