{
  "type": "Feature",
  "properties": {
    "iso:country":"GB",
    "sg:address":"St Leonards Street",
    "sg:city":"Bedford",
    "sg:classifiers":[
        {
            "category":"Retail",
            "subcategory":"Repair Shop",
            "type":"Services"
        }
    ],
    "sg:phone":"+44 1234 360447",
    "sg:postcode":"MK42 9BS",
    "sg:province":"Bedfordshire",
    "sg:tags":[
        "radio",
        "television",
        "video"
    ],
    "wof:name":"Carlow Radio Ltd.",
    "wof:placetype":"venue"
},
  "geometry": {"coordinates":[-0.465724,52.129169],"type":"Point"}
}