{
  "type": "Feature",
  "properties": {
    "addr:full":"1 Thames Wharf, Rainville Road London Greater London W6 9HA",
    "addr:housenumber":"1",
    "addr:postcode":"w6 9ha",
    "addr:street":"Thames Wharf Rainville Road",
    "iso:country":"GB",
    "sg:address":"1 Thames Wharf, Rainville Road",
    "sg:city":"London",
    "sg:classifiers":[
        {
            "category":"Professional",
            "subcategory":"Management & Consulting",
            "type":"Services"
        }
    ],
    "sg:phone":"+44 20 7012 6000",
    "sg:postcode":"W6 9HA",
    "sg:province":"Greater London",
    "sg:tags":[
        "consultant",
        "promotion",
        "direct",
        "sale"
    ],
    "wof:name":"Marketing Drive Ltd.",
    "wof:placetype":"venue"
},
  "geometry": {"coordinates":[-0.2231899947,51.4825706482],"type":"Point"}
}