{
  "type": "Feature",
  "properties": {
    "addr:full":"37 Pettits Boulevard, Rise Park Romford Essex RM1 4PL",
    "addr:housenumber":"37",
    "addr:postcode":"rm1 4pl",
    "addr:street":"Pettits Boulevard Rise Park",
    "iso:country":"GB",
    "sg:address":"37 Pettits Boulevard, Rise Park",
    "sg:city":"Romford",
    "sg:classifiers":[
        {
            "category":"Arts & Performance",
            "subcategory":"Music",
            "type":"Entertainment"
        }
    ],
    "sg:phone":"+44 1708 722290",
    "sg:postcode":"RM1 4PL",
    "sg:province":"Essex",
    "sg:tags":[
        "mobile",
        "disco"
    ],
    "wof:name":"D & D Disco",
    "wof:placetype":"venue"
},
  "geometry": {"coordinates":[0.184812,51.593529],"type":"Point"}
}