{
  "type": "Feature",
  "properties": {
    "addr:full":"19-20 Galloway Street, Maxwelltown Dumfries Dumfries and Galloway DG2 7TL",
    "addr:housenumber":"19-20",
    "addr:postcode":"dg2 7tl",
    "addr:street":"Galloway Street",
    "iso:country":"GB",
    "sg:address":"19-20 Galloway Street, Maxwelltown",
    "sg:city":"Dumfries",
    "sg:classifiers":[
        {
            "category":"Home & Garden",
            "subcategory":"Home Furnishings",
            "type":"Retail Goods"
        }
    ],
    "sg:phone":"+44 1387 254641",
    "sg:postcode":"DG2 7TL",
    "sg:province":"Dumfries and Galloway",
    "sg:tags":[
        "wall",
        "wallpaper",
        "covering"
    ],
    "wof:name":"James Bell Decor Salon",
    "wof:placetype":"venue"
},
  "geometry": {"coordinates":[-3.6192159653,55.0684127808],"type":"Point"}
}