{
  "type": "Feature",
  "properties": {
    "iso:country":"GB",
    "sg:address":"3 Woodland Way",
    "sg:city":"Bristol",
    "sg:classifiers":[
        {
            "category":"Professional",
            "subcategory":"Engineering",
            "type":"Services"
        }
    ],
    "sg:phone":"+44 1275 392039",
    "sg:postcode":"BS8 3UJ",
    "sg:province":"City of Bristol",
    "sg:tags":[
        "contractor",
        "electrical",
        "engineer"
    ],
    "wof:name":"Key Alarms",
    "wof:placetype":"venue"
},
  "geometry": {"coordinates":[-2.6461589336,51.455039978],"type":"Point"}
}