{
  "type": "Feature",
  "properties": {
    "iso:country":"GB",
    "sg:address":"29a Union Street",
    "sg:city":"Hereford",
    "sg:classifiers":[
        {
            "category":"Shopping",
            "subcategory":"Musical Instruments",
            "type":"Retail Goods"
        }
    ],
    "sg:phone":"+44 1432 356194",
    "sg:postcode":"HR1 2BT",
    "sg:province":"Herefordshire",
    "sg:tags":[
        "music",
        "sheet"
    ],
    "wof:name":"Music Plus",
    "wof:placetype":"venue"
},
  "geometry": {"coordinates":[-2.71292,52.056709],"type":"Point"}
}