{
  "type": "Feature",
  "properties": {
    "addr:full":"Unit 2b Greyfriars Place Stafford Staffordshire ST16 2SD",
    "addr:housenumber":"unit 2b",
    "addr:postcode":"st16 2sd",
    "addr:street":"Greyfriars Place",
    "iso:country":"GB",
    "sg:address":"Unit 2b Greyfriars Place",
    "sg:city":"Stafford",
    "sg:classifiers":[
        {
            "category":"Home & Garden",
            "subcategory":"Furniture",
            "type":"Retail Goods"
        }
    ],
    "sg:phone":"+44 1785 222947",
    "sg:postcode":"ST16 2SD",
    "sg:province":"Staffordshire",
    "wof:name":"Harveys Furnishing Group Ltd.",
    "wof:placetype":"venue"
},
  "geometry": {"coordinates":[-2.123249054,52.8140335083],"type":"Point"}
}