{
  "type": "Feature",
  "properties": {
    "addr:full":"18 Backgate Peterhead Aberdeenshire AB42 6LN",
    "addr:housenumber":"18",
    "addr:postcode":"ab42 6ln",
    "addr:street":"Backgate",
    "iso:country":"GB",
    "sg:address":"18 Backgate",
    "sg:city":"Peterhead",
    "sg:classifiers":[
        {
            "category":"Personal",
            "subcategory":"Beauty Salon",
            "type":"Services"
        }
    ],
    "sg:postcode":"AB42 6LN",
    "sg:province":"Aberdeenshire",
    "sg:tags":[
        "unisex",
        "hairdresser"
    ],
    "wof:name":"Riah Hair Studio",
    "wof:placetype":"venue"
},
  "geometry": {"coordinates":[-1.7786359787,57.5061683655],"type":"Point"}
}