{
  "type": "Feature",
  "properties": {
    "iso:country":"GB",
    "sg:address":"201 New Church Road",
    "sg:city":"Hove",
    "sg:classifiers":[
        {
            "category":"Education",
            "subcategory":"School",
            "type":"Public Place"
        }
    ],
    "sg:phone":"+44 1273 410901",
    "sg:postcode":"BN3 4ED",
    "sg:province":"East Sussex",
    "sg:tags":[
        "independent",
        "preparatory"
    ],
    "wof:name":"The Fold School",
    "wof:placetype":"venue"
},
  "geometry": {"coordinates":[-0.202112,50.832386],"type":"Point"}
}