{
  "type": "Feature",
  "properties": {
    "addr:full":"34a High St Edenbridge East Sussex TN8 5AJ",
    "addr:housenumber":"34a",
    "addr:postcode":"tn8 5aj",
    "addr:street":"High St",
    "iso:country":"GB",
    "sg:address":"34a High St",
    "sg:city":"Edenbridge",
    "sg:classifiers":[
        {
            "category":"Professional",
            "subcategory":"Printing & Photocopies",
            "type":"Services"
        }
    ],
    "sg:phone":"+44 1732 867688",
    "sg:postcode":"TN8 5AJ",
    "sg:province":"East Sussex",
    "sg:tags":[
        "trophy",
        "medal"
    ],
    "wof:name":"A.C Trophies & Engraving",
    "wof:placetype":"venue"
},
  "geometry": {"coordinates":[0.064328,51.197906],"type":"Point"}
}