{
  "type": "Feature",
  "properties": {
    "addr:full":"53 John Street Porthcawl Bridgend CF36 3AY",
    "addr:housenumber":"53",
    "addr:postcode":"cf36 3ay",
    "addr:street":"John Street",
    "iso:country":"GB",
    "sg:address":"53 John Street",
    "sg:city":"Porthcawl",
    "sg:classifiers":[
        {
            "category":"Shopping",
            "subcategory":"Thrift Store",
            "type":"Retail Goods"
        },
        {
            "category":"Organizations",
            "subcategory":"Non-profit Organization",
            "type":"Services"
        }
    ],
    "sg:phone":"+44 1656 783778",
    "sg:postcode":"CF36 3AY",
    "sg:province":"Bridgend",
    "sg:tags":[
        "shop",
        "organisation",
        "voluntary",
        "charity"
    ],
    "wof:name":"Tenovus",
    "wof:placetype":"venue"
},
  "geometry": {"coordinates":[-3.7037460804,51.4782905579],"type":"Point"}
}