{
  "type": "Feature",
  "properties": {
    "addr:full":"Brookside Business Park, Cold Meece Stone Staffordshire ST15 0RZ",
    "addr:postcode":"st15 0rz",
    "addr:street":"Cold Meece",
    "iso:country":"GB",
    "sg:address":"Brookside Business Park, Cold Meece",
    "sg:city":"Stone",
    "sg:classifiers":[
        {
            "category":"Autos & Motor Vehicles",
            "subcategory":"Auto Supplies",
            "type":"Retail Goods"
        }
    ],
    "sg:phone":"+44 1785 761411",
    "sg:postcode":"ST15 0RZ",
    "sg:province":"Staffordshire",
    "sg:tags":[
        "towing",
        "eqpt",
        "trailer"
    ],
    "wof:name":"T I P Trailer Rental",
    "wof:placetype":"venue"
},
  "geometry": {"coordinates":[-2.215289,52.892574],"type":"Point"}
}