{
  "type": "Feature",
  "properties": {
    "addr:full":"Unit 2, Flixton Road, Urmston Manchester Cheshire M41 5BF",
    "addr:housenumber":"unit 2",
    "addr:postcode":"m41 5bf",
    "addr:street":"Flixton Road",
    "iso:country":"GB",
    "sg:address":"Unit 2, Flixton Road, Urmston",
    "sg:city":"Manchester",
    "sg:classifiers":[
        {
            "category":"Home & Garden",
            "subcategory":"Home Furnishings",
            "type":"Retail Goods"
        }
    ],
    "sg:phone":"+44 161 748 2164",
    "sg:postcode":"M41 5BF",
    "sg:province":"Cheshire",
    "sg:tags":[
        "furnishers",
        "planner",
        "bedroom"
    ],
    "wof:name":"J Brady Fitted Bedrooms and Kitchens",
    "wof:placetype":"venue"
},
  "geometry": {"coordinates":[-2.3672289848,53.4490432739],"type":"Point"}
}