{
  "type": "Feature",
  "properties": {
    "addr:full":"250 Halley Street, Yoker Glasgow Glasgow City G13 4DT",
    "addr:housenumber":"250",
    "addr:postcode":"g13 4dt",
    "addr:street":"Halley Street",
    "iso:country":"GB",
    "sg:address":"250 Halley Street, Yoker",
    "sg:city":"Glasgow",
    "sg:classifiers":[
        {
            "category":"Health Services",
            "subcategory":"Nursing And Care Facility",
            "type":"Services"
        }
    ],
    "sg:phone":"+44 141 951 4283",
    "sg:postcode":"G13 4DT",
    "sg:province":"Glasgow City",
    "sg:tags":[
        "home"
    ],
    "wof:name":"Quayside Nursing Home",
    "wof:placetype":"venue"
},
  "geometry": {"coordinates":[-4.3789391518,55.8926887512],"type":"Point"}
}