{
  "type": "Feature",
  "properties": {
    "addr:full":"42 Steyning Avenue Peacehaven East Sussex BN10 8HN",
    "addr:housenumber":"42",
    "addr:postcode":"bn10 8hn",
    "addr:street":"Steyning Avenue Peacehaven",
    "iso:country":"GB",
    "sg:address":"42 Steyning Avenue",
    "sg:city":"Peacehaven",
    "sg:classifiers":[
        {
            "category":"Building & Trades",
            "subcategory":"Construction",
            "type":"Services"
        }
    ],
    "sg:phone":"+44 1273 581285",
    "sg:postcode":"BN10 8HN",
    "sg:province":"East Sussex",
    "sg:tags":[
        "joiner",
        "carpenter"
    ],
    "wof:name":"Mick Burns Carpentry & Joinery",
    "wof:placetype":"venue"
},
  "geometry": {"coordinates":[0.002938,50.7924079895],"type":"Point"}
}