{
  "type": "Feature",
  "properties": {
    "addr:full":"48 Greywell Road, Leigh Park Havant Hampshire PO9 5AL",
    "addr:housenumber":"48",
    "addr:postcode":"po9 5al",
    "addr:street":"Greywell Road",
    "iso:country":"GB",
    "sg:address":"48 Greywell Road, Leigh Park",
    "sg:city":"Havant",
    "sg:classifiers":[
        {
            "category":"Sports & Exercise",
            "subcategory":"Sports Center",
            "type":"Entertainment"
        }
    ],
    "sg:phone":"+44 23 9247 5353",
    "sg:postcode":"PO9 5AL",
    "sg:province":"Hampshire",
    "sg:tags":[
        "shop",
        "good"
    ],
    "wof:name":"Sports Corner",
    "wof:placetype":"venue"
},
  "geometry": {"coordinates":[-0.985544,50.854496],"type":"Point"}
}