{
  "type": "Feature",
  "properties": {
    "iso:country":"GB",
    "sg:address":"Hazel Farm Road, Totton",
    "sg:city":"Southampton",
    "sg:classifiers":[
        {
            "category":"Health Services",
            "subcategory":"Dentist",
            "type":"Services"
        }
    ],
    "sg:phone":"+44 23 8066 3551",
    "sg:postcode":"SO40 8WU",
    "sg:province":"Hampshire",
    "wof:name":"Forest Gate Dental Practice",
    "wof:placetype":"venue"
},
  "geometry": {"coordinates":[-1.513814,50.91748],"type":"Point"}
}