{
  "type": "Feature",
  "properties": {
    "iso:country":"GB",
    "sg:address":"Unit 8 Mitchell Point, Ensign Business Park, Hamble",
    "sg:city":"Southampton",
    "sg:classifiers":[
        {
            "category":"Building & Trades",
            "subcategory":"Construction",
            "type":"Services"
        }
    ],
    "sg:phone":"+44 23 8045 7684",
    "sg:postcode":"SO31 4RF",
    "sg:province":"Hampshire",
    "sg:tags":[
        "decorator",
        "painter"
    ],
    "wof:name":"J & S Sedden Painting",
    "wof:placetype":"venue"
},
  "geometry": {"coordinates":[-1.327141,50.857323],"type":"Point"}
}