{
  "type": "Feature",
  "properties": {
    "addr:full":"Unity Garage, Claycliffe Road Barnsley South Yorkshire S75 1HS",
    "addr:postcode":"s75 1hs",
    "addr:street":"Claycliffe Road;Yorkshire",
    "iso:country":"GB",
    "sg:address":"Unity Garage, Claycliffe Road",
    "sg:city":"Barnsley",
    "sg:classifiers":[
        {
            "category":"Retail",
            "subcategory":"Auto Repair",
            "type":"Services"
        }
    ],
    "sg:phone":"+44 1226 382312",
    "sg:postcode":"S75 1HS",
    "sg:province":"South Yorkshire",
    "sg:tags":[
        "modification",
        "garage"
    ],
    "wof:name":"Dennis Moreton",
    "wof:placetype":"venue"
},
  "geometry": {"coordinates":[-1.5198600292,53.5694389343],"type":"Point"}
}