{
  "type": "Feature",
  "properties": {
    "addr:full":"10 Thurloe Street London Greater London SW7 2ST",
    "addr:housenumber":"10",
    "addr:postcode":"sw7 2st",
    "addr:street":"Thurloe Street",
    "iso:country":"GB",
    "sg:address":"10 Thurloe Street",
    "sg:city":"London",
    "sg:classifiers":[
        {
            "category":"Health Services",
            "subcategory":"Dentist",
            "type":"Services"
        }
    ],
    "sg:phone":"+44 20 7584 5551",
    "sg:postcode":"SW7 2ST",
    "sg:province":"Greater London",
    "wof:name":"M Mardarney",
    "wof:placetype":"venue"
},
  "geometry": {"coordinates":[-0.172627,51.494499],"type":"Point"}
}