{
  "type": "Feature",
  "properties": {
    "iso:country":"GB",
    "sg:address":"Nane Snugger, Uckfield Road, Ringmer",
    "sg:city":"Lewes",
    "sg:classifiers":[
        {
            "category":"Building & Trades",
            "subcategory":"Construction",
            "type":"Services"
        }
    ],
    "sg:postcode":"BN8 5RP",
    "sg:province":"East Sussex",
    "sg:tags":[
        "roofing"
    ],
    "wof:name":"M K Felt Roofing Contractors",
    "wof:placetype":"venue"
},
  "geometry": {"coordinates":[0.0590789989,50.894077301],"type":"Point"}
}