{
  "type": "Feature",
  "properties": {
    "addr:full":"Carlton Barn, Carlton Road, Kelsale Saxmundham Suffolk IP17 2NP",
    "addr:postcode":"ip17 2np",
    "addr:street":"Carlton Road",
    "iso:country":"GB",
    "sg:address":"Carlton Barn, Carlton Road, Kelsale",
    "sg:city":"Saxmundham",
    "sg:classifiers":[
        {
            "category":"Building & Trades",
            "subcategory":"Cleaning & Sanitation",
            "type":"Services"
        }
    ],
    "sg:postcode":"IP17 2NP",
    "sg:province":"Suffolk",
    "sg:tags":[
        "blast"
    ],
    "wof:name":"Nu-Blast",
    "wof:placetype":"venue"
},
  "geometry": {"coordinates":[1.48633,52.234638],"type":"Point"}
}