{
  "type": "Feature",
  "properties": {
    "addr:full":"Leamore Lane Walsall West Midlands WS2 7DA",
    "addr:postcode":"ws2 7da",
    "addr:street":"Leamore Lane",
    "iso:country":"GB",
    "sg:address":"Leamore Lane",
    "sg:city":"Walsall",
    "sg:classifiers":[
        {
            "category":"Shopping",
            "subcategory":"Stationery & Office Supplies",
            "type":"Retail Goods"
        }
    ],
    "sg:postcode":"WS2 7DA",
    "sg:province":"West Midlands",
    "sg:tags":[
        "box",
        "carton"
    ],
    "wof:name":"Lester Packing Materials",
    "wof:placetype":"venue"
},
  "geometry": {"coordinates":[-2.0027310848,52.6061782837],"type":"Point"}
}