{
  "type": "Feature",
  "properties": {
    "addr:full":"1 Melbourne Street Manchester Greater Manchester M9 4EH",
    "addr:housenumber":"1",
    "addr:postcode":"m9 4eh",
    "addr:street":"Melbourne Street",
    "iso:country":"GB",
    "sg:address":"1 Melbourne Street",
    "sg:city":"Manchester",
    "sg:classifiers":[
        {
            "category":"Health Services",
            "subcategory":"Dentist",
            "type":"Services"
        }
    ],
    "sg:phone":"+44 161 205 8326",
    "sg:postcode":"M9 4EH",
    "sg:province":"Greater Manchester",
    "sg:tags":[
        "technician",
        "dental"
    ],
    "wof:name":"Gordon Bouchier",
    "wof:placetype":"venue"
},
  "geometry": {"coordinates":[-2.2065010071,53.5134811401],"type":"Point"}
}