{
  "type": "Feature",
  "properties": {
    "addr:full":"375 Clifton Drive North Lytham St. Annes Lancashire FY8 2PA",
    "addr:housenumber":"375",
    "addr:postcode":"fy8 2pa",
    "addr:street":"Clifton Drive North Lytham St. Annes",
    "iso:country":"GB",
    "sg:address":"375 Clifton Drive North",
    "sg:city":"Lytham St. Annes",
    "sg:classifiers":[
        {
            "category":"Health Services",
            "subcategory":"Nursing And Care Facility",
            "type":"Services"
        }
    ],
    "sg:phone":"+44 1253 789934",
    "sg:postcode":"FY8 2PA",
    "sg:province":"Lancashire",
    "sg:tags":[
        "home"
    ],
    "wof:name":"Lytham St. Annes & Blackpool Homecare",
    "wof:placetype":"venue"
},
  "geometry": {"coordinates":[-3.0360059738,53.7533149719],"type":"Point"}
}