{
  "type": "Feature",
  "properties": {
    "iso:country":"GB",
    "sg:address":"67 Reginald St",
    "sg:city":"Luton",
    "sg:classifiers":[
        {
            "category":"Shopping",
            "subcategory":"Books",
            "type":"Retail Goods"
        }
    ],
    "sg:postcode":"LU2 7QZ",
    "sg:province":"Bedfordshire",
    "sg:tags":[
        "bookseller"
    ],
    "wof:name":"Hightown Christian Books",
    "wof:placetype":"venue"
},
  "geometry": {"coordinates":[-0.415945,51.887047],"type":"Point"}
}