{
  "type": "Feature",
  "properties": {
    "addr:full":"Spa Lane Norwich Norfolk NR11 6UE",
    "addr:postcode":"nr11 6ue",
    "addr:street":"Spa Lane",
    "iso:country":"GB",
    "sg:address":"Spa Lane",
    "sg:city":"Norwich",
    "sg:classifiers":[
        {
            "category":"Home & Garden",
            "subcategory":"Garden Supply",
            "type":"Retail Goods"
        },
        {
            "category":"Farming",
            "subcategory":"Farm",
            "type":"Manufacturing & Wholesale Goods"
        }
    ],
    "sg:phone":"+44 1263 732339",
    "sg:postcode":"NR11 6UE",
    "sg:province":"Norfolk",
    "sg:tags":[
        "mixed",
        "bulb",
        "crop",
        "grower"
    ],
    "wof:name":"P H & R E Gostling",
    "wof:placetype":"venue"
},
  "geometry": {"coordinates":[1.251069,52.783936],"type":"Point"}
}