{
  "type": "Feature",
  "properties": {
    "addr:full":"Unit 1 The Old Brickworks, Bakestonedale Road Macclesfield Cheshire SK10 5RX",
    "addr:housenumber":"unit 1",
    "addr:postcode":"sk10 5rx",
    "addr:street":"The Old Brickworks Bakestonedale Road",
    "iso:country":"GB",
    "sg:address":"Unit 1 The Old Brickworks, Bakestonedale Road",
    "sg:city":"Macclesfield",
    "sg:classifiers":[
        {
            "category":"Autos & Motor Vehicles",
            "subcategory":"Automobile Sales",
            "type":"Retail Goods"
        }
    ],
    "sg:phone":"+44 1625 560156",
    "sg:postcode":"SK10 5RX",
    "sg:province":"Cheshire",
    "sg:tags":[
        "specialist",
        "sales",
        "car",
        "classic"
    ],
    "wof:name":"S Isles",
    "wof:placetype":"venue"
},
  "geometry": {"coordinates":[-2.1165909767,53.281917572],"type":"Point"}
}