{
  "type": "Feature",
  "properties": {
    "iso:country":"GB",
    "sg:address":"72 New Road",
    "sg:city":"Gravesend",
    "sg:classifiers":[
        {
            "category":"Food & Beverages",
            "subcategory":"Supermarket",
            "type":"Retail Goods"
        }
    ],
    "sg:phone":"+44 845 677 9303",
    "sg:postcode":"DA11 0AF",
    "sg:province":"Kent",
    "wof:name":"Tesco Stores Ltd.",
    "wof:placetype":"venue"
},
  "geometry": {"coordinates":[0.366324,51.44244],"type":"Point"}
}