{
  "type": "Feature",
  "properties": {
    "addr:full":"Southdownview Way, Broadwater Trading Estate Worthing West Sussex BN14 8NL",
    "addr:postcode":"bn14 8nl",
    "addr:street":"Southdownview Way;Trading",
    "iso:country":"GB",
    "sg:address":"Southdownview Way, Broadwater Trading Estate",
    "sg:city":"Worthing",
    "sg:classifiers":[
        {
            "category":"Building & Trades",
            "subcategory":"Pest Control",
            "type":"Services"
        }
    ],
    "sg:phone":"+44 1903 238316",
    "sg:postcode":"BN14 8NL",
    "sg:province":"West Sussex",
    "sg:tags":[
        "woodworm"
    ],
    "wof:name":"R H Smith (Worthing) Ltd.",
    "wof:placetype":"venue"
},
  "geometry": {"coordinates":[-0.363187,50.829353],"type":"Point"}
}