{
  "type": "Feature",
  "properties": {
    "addr:full":"96 Tissington Court, Rotherhithe New Road London Greater London SE16 2SE",
    "addr:housenumber":"96",
    "addr:postcode":"se16 2se",
    "addr:street":"Tissington Court;New Road",
    "iso:country":"GB",
    "sg:address":"96 Tissington Court, Rotherhithe New Road",
    "sg:city":"London",
    "sg:classifiers":[
        {
            "category":"Professional",
            "subcategory":"Computer Services",
            "type":"Services"
        }
    ],
    "sg:postcode":"SE16 2SE",
    "sg:province":"Greater London",
    "sg:tags":[
        "system",
        "software"
    ],
    "wof:name":"Micro Seven Ltd.",
    "wof:placetype":"venue"
},
  "geometry": {"coordinates":[-0.0513189994,51.4955558777],"type":"Point"}
}