{
  "type": "Feature",
  "properties": {
    "addr:full":"23 Cornfield Close, Bomere Heath Shrewsbury Shropshire SY4 3PA",
    "addr:housenumber":"23",
    "addr:postcode":"sy4 3pa",
    "addr:street":"Cornfield Close",
    "iso:country":"GB",
    "sg:address":"23 Cornfield Close, Bomere Heath",
    "sg:city":"Shrewsbury",
    "sg:classifiers":[
        {
            "category":"Real Estate",
            "subcategory":"Architect",
            "type":"Services"
        }
    ],
    "sg:postcode":"SY4 3PA",
    "sg:province":"Shropshire",
    "wof:name":"Campbell Jones Associates Ltd.",
    "wof:placetype":"venue"
},
  "geometry": {"coordinates":[-2.77741,52.7743],"type":"Point"}
}