{
  "type": "Feature",
  "properties": {
    "iso:country":"GB",
    "sg:address":"S B S House, Blackthorn Road",
    "sg:city":"Slough",
    "sg:classifiers":[
        {
            "category":"Freight",
            "type":"Transportation"
        }
    ],
    "sg:phone":"+44 1753 210100",
    "sg:postcode":"SL3 0SB",
    "sg:province":"Berkshire",
    "sg:tags":[
        "forwarders"
    ],
    "wof:name":"S B S Worldwide Ltd.",
    "wof:placetype":"venue"
},
  "geometry": {"coordinates":[-0.5151389837,51.472946167],"type":"Point"}
}