{
  "type": "Feature",
  "properties": {
    "iso:country":"GB",
    "sg:address":"38a Dyer Street",
    "sg:city":"Cirencester",
    "sg:classifiers":[
        {
            "category":"Professional",
            "subcategory":"Management & Consulting",
            "type":"Services"
        }
    ],
    "sg:phone":"+44 1285 642200",
    "sg:postcode":"GL7 2PF",
    "sg:province":"Gloucestershire",
    "sg:tags":[
        "consultant",
        "business"
    ],
    "wof:name":"Insurance Management Consultants 2000 Ltd.",
    "wof:placetype":"venue"
},
  "geometry": {"coordinates":[-1.964285,51.716167],"type":"Point"}
}