{
  "type": "Feature",
  "properties": {
    "iso:country":"GB",
    "sg:address":"Houldsworth Mill, Houldsworth Street, Reddish",
    "sg:city":"Stockport",
    "sg:classifiers":[
        {
            "category":"Military Area",
            "subcategory":"Air Force Base",
            "type":"Public Place"
        }
    ],
    "sg:phone":"+44 161 431 5494",
    "sg:postcode":"SK5 6DA",
    "sg:province":"Cheshire",
    "sg:tags":[
        "taxi",
        "hire",
        "private"
    ],
    "wof:name":"Bravo Private Hire",
    "wof:placetype":"venue"
},
  "geometry": {"coordinates":[-2.1572139263,53.4456825256],"type":"Point"}
}