{
  "type": "Feature",
  "properties": {
    "addr:full":"33 Laurel Gro Liverpool Merseyside L36 5UD",
    "addr:housenumber":"33",
    "addr:postcode":"l36 5ud",
    "addr:street":"Laurel Gro",
    "iso:country":"GB",
    "sg:address":"33 Laurel Gro",
    "sg:city":"Liverpool",
    "sg:classifiers":[
        {
            "category":"Building & Trades",
            "subcategory":"Pest Control",
            "type":"Services"
        }
    ],
    "sg:postcode":"L36 5UD",
    "sg:province":"Merseyside",
    "sg:tags":[
        "vermin"
    ],
    "wof:name":"P C S Action",
    "wof:placetype":"venue"
},
  "geometry": {"coordinates":[-2.8426709175,53.4025268555],"type":"Point"}
}