{
  "type": "Feature",
  "properties": {
    "iso:country":"GB",
    "sg:address":"104-106 Winwick Street",
    "sg:city":"Warrington",
    "sg:classifiers":[
        {
            "category":"Military Area",
            "subcategory":"Air Force Base",
            "type":"Public Place"
        }
    ],
    "sg:postcode":"WA2 7TY",
    "sg:province":"Cheshire",
    "sg:tags":[
        "taxi",
        "hire",
        "private"
    ],
    "wof:name":"Benco Taxis",
    "wof:placetype":"venue"
},
  "geometry": {"coordinates":[-2.594259,53.393967],"type":"Point"}
}