{
  "type": "Feature",
  "properties": {
    "addr:full":"104-106 Winwick Street Warrington Cheshire WA2 7TY",
    "addr:postcode":"104-106;wa2 7ty",
    "addr:street":"Winwick Street",
    "iso:country":"GB",
    "sg:address":"104-106 Winwick Street",
    "sg:city":"Warrington",
    "sg:classifiers":[
        {
            "category":"Military Area",
            "subcategory":"Air Force Base",
            "type":"Public Place"
        }
    ],
    "sg:postcode":"WA2 7TY",
    "sg:province":"Cheshire",
    "sg:tags":[
        "taxi",
        "hire",
        "private"
    ],
    "wof:name":"Benco Taxis",
    "wof:placetype":"venue"
},
  "geometry": {"coordinates":[-2.594259,53.393967],"type":"Point"}
}