{
  "type": "Feature",
  "properties": {
    "addr:full":"23 Ashfield Drive Halifax West Yorkshire HX3 5PQ",
    "addr:housenumber":"23",
    "addr:postcode":"hx3 5pq",
    "addr:street":"Ashfield Drive",
    "iso:country":"GB",
    "sg:address":"23 Ashfield Drive",
    "sg:city":"Halifax",
    "sg:classifiers":[
        {
            "category":"Shopping",
            "subcategory":"Pets & Pet Supplies",
            "type":"Retail Goods"
        }
    ],
    "sg:postcode":"HX3 5PQ",
    "sg:province":"West Yorkshire",
    "wof:name":"Sitting Service",
    "wof:placetype":"venue"
},
  "geometry": {"coordinates":[-1.880839,53.737591],"type":"Point"}
}