{
  "type": "Feature",
  "properties": {
    "iso:country":"GB",
    "sg:address":"7 Hollybush Lane",
    "sg:city":"Wolverhampton",
    "sg:classifiers":[
        {
            "category":"Shopping",
            "subcategory":"Antiques",
            "type":"Retail Goods"
        }
    ],
    "sg:postcode":"WV4 4JJ",
    "sg:province":"Staffordshire",
    "wof:name":"The Red Shop",
    "wof:placetype":"venue"
},
  "geometry": {"coordinates":[-2.1678049564,52.5605964661],"type":"Point"}
}