{
  "type": "Feature",
  "properties": {
    "addr:full":"29 Magrath Avenue Cambridge Cambridgeshire CB4 3AH",
    "addr:housenumber":"29",
    "addr:postcode":"cb4 3ah",
    "addr:street":"Magrath Avenue",
    "iso:country":"GB",
    "sg:address":"29 Magrath Avenue",
    "sg:city":"Cambridge",
    "sg:classifiers":[
        {
            "category":"Health Services",
            "subcategory":"Nursing And Care Facility",
            "type":"Services"
        },
        {
            "category":"Social Services",
            "subcategory":"Retirement Home",
            "type":"Services"
        }
    ],
    "sg:phone":"+44 1223 361718",
    "sg:postcode":"CB4 3AH",
    "sg:province":"Cambridgeshire",
    "sg:tags":[
        "residential"
    ],
    "wof:name":"Granta Housing Society Ltd.",
    "wof:placetype":"venue"
},
  "geometry": {"coordinates":[0.1147539988,52.2136802673],"type":"Point"}
}