{
  "type": "Feature",
  "properties": {
    "iso:country":"GB",
    "sg:address":"61 Quarry Rigg, Park Rd",
    "sg:city":"Windermere",
    "sg:classifiers":[
        {
            "category":"Sports & Exercise",
            "subcategory":"Bicycle Rental",
            "type":"Entertainment"
        }
    ],
    "sg:phone":"+44 15394 47100",
    "sg:postcode":"LA23 2DH",
    "sg:province":"Cumbria",
    "sg:tags":[
        "renting",
        "cycle"
    ],
    "wof:name":"Blazing Saddles",
    "wof:placetype":"venue"
},
  "geometry": {"coordinates":[-2.906404,54.379665],"type":"Point"}
}