{
  "type": "Feature",
  "properties": {
    "addr:full":"417 Beulah Hill London Greater London SE19 3HB",
    "addr:housenumber":"417",
    "addr:postcode":"se19 3hb",
    "addr:street":"Beulah Hill",
    "iso:country":"GB",
    "sg:address":"417 Beulah Hill",
    "sg:city":"London",
    "sg:classifiers":[
        {
            "category":"Food & Beverages",
            "subcategory":"Bakery",
            "type":"Retail Goods"
        }
    ],
    "sg:postcode":"SE19 3HB",
    "sg:province":"Greater London",
    "sg:tags":[
        "baker"
    ],
    "wof:name":"Crusty Crown Bakery",
    "wof:placetype":"venue"
},
  "geometry": {"coordinates":[-0.1065789983,51.4200401306],"type":"Point"}
}