{
  "type": "Feature",
  "properties": {
    "iso:country":"GB",
    "sg:address":"263 Wakefield Road",
    "sg:city":"Huddersfield",
    "sg:classifiers":[
        {
            "category":"Fast Food",
            "type":"Food & Drink"
        }
    ],
    "sg:phone":"+44 1484 451500",
    "sg:postcode":"HD5 9BE",
    "sg:province":"West Yorkshire",
    "sg:tags":[
        "away",
        "take"
    ],
    "wof:name":"Masha Allah Indian Takeaway",
    "wof:placetype":"venue"
},
  "geometry": {"coordinates":[-1.76413,53.643208],"type":"Point"}
}