{
  "type": "Feature",
  "properties": {
    "iso:country":"GB",
    "sg:address":"Manor Farm, Eggington",
    "sg:city":"Leighton Buzzard",
    "sg:classifiers":[
        {
            "category":"Farming",
            "subcategory":"Livestock Farm",
            "type":"Manufacturing & Wholesale Goods"
        }
    ],
    "sg:phone":"+44 1525 210231",
    "sg:postcode":"LU7 9PQ",
    "sg:province":"Bedfordshire",
    "sg:tags":[
        "others"
    ],
    "wof:name":"G B Sear & Son",
    "wof:placetype":"venue"
},
  "geometry": {"coordinates":[-0.6101509929,51.9171333313],"type":"Point"}
}