{
  "type": "Feature",
  "properties": {
    "addr:full":"14 Dumbarton Road Stirling Stirling FK8 2LQ",
    "addr:housenumber":"14",
    "addr:postcode":"fk8 2lq",
    "addr:street":"Dumbarton Road",
    "iso:country":"GB",
    "sg:address":"14 Dumbarton Road",
    "sg:city":"Stirling",
    "sg:classifiers":[
        {
            "category":"Shopping",
            "subcategory":"Antiques",
            "type":"Retail Goods"
        }
    ],
    "sg:phone":"+44 1786 473414",
    "sg:postcode":"FK8 2LQ",
    "sg:province":"Stirling",
    "wof:name":"Stewart Antiques",
    "wof:placetype":"venue"
},
  "geometry": {"coordinates":[-3.9380118847,56.1170463562],"type":"Point"}
}