{
  "type": "Feature",
  "properties": {
    "iso:country":"GB",
    "sg:address":"The Bungalow, 30 Sim Balk La",
    "sg:city":"York",
    "sg:classifiers":[
        {
            "category":"Health Services",
            "subcategory":"Dentist",
            "type":"Services"
        }
    ],
    "sg:phone":"+44 1904 703427",
    "sg:postcode":"YO2 1QQ",
    "sg:province":"East Riding of Yorkshire",
    "wof:name":"P G Harris",
    "wof:placetype":"venue"
},
  "geometry": {"coordinates":[-1.08342,53.953331],"type":"Point"}
}