{
  "type": "Feature",
  "properties": {
    "iso:country":"GB",
    "sg:address":"39 Thurloe St",
    "sg:city":"South Kensington",
    "sg:classifiers":[
        {
            "category":"Real Estate",
            "subcategory":"Architect",
            "type":"Services"
        }
    ],
    "sg:phone":"+44 20 7823 7474",
    "sg:postcode":"SW7 2LQ",
    "sg:province":"Greater London",
    "sg:tags":[
        "architectural"
    ],
    "wof:name":"Legion Crowd Dynamics Ltd",
    "wof:placetype":"venue"
},
  "geometry": {"coordinates":[-0.1742449999,51.4944953918],"type":"Point"}
}