{
  "type": "Feature",
  "properties": {
    "addr:full":"8 Clarendon Terrace London Greater London W9 1BZ",
    "addr:housenumber":"8",
    "addr:postcode":"w9 1bz",
    "addr:street":"Clarendon Terrace",
    "iso:country":"GB",
    "sg:address":"8 Clarendon Terrace",
    "sg:city":"London",
    "sg:classifiers":[
        {
            "category":"Shopping",
            "subcategory":"Clothing, Apparel, & Fashions",
            "type":"Retail Goods"
        }
    ],
    "sg:phone":"+44 20 7289 8220",
    "sg:postcode":"W9 1BZ",
    "sg:province":"Greater London",
    "sg:tags":[
        "shop",
        "ladieswear"
    ],
    "wof:name":"The Fashion Gallery Ltd.",
    "wof:placetype":"venue"
},
  "geometry": {"coordinates":[-0.178568,51.525253],"type":"Point"}
}