{
  "type": "Feature",
  "properties": {
    "addr:full":"1 Hill Terrace, Crowd Hill, Fair Oak Eastleigh Hampshire SO50 7HD",
    "addr:housenumber":"1",
    "addr:postcode":"so50 7hd",
    "addr:street":"Hill Terrace Crowd Hill;Oak",
    "iso:country":"GB",
    "sg:address":"1 Hill Terrace, Crowd Hill, Fair Oak",
    "sg:city":"Eastleigh",
    "sg:classifiers":[
        {
            "category":"Building & Trades",
            "subcategory":"Construction",
            "type":"Services"
        }
    ],
    "sg:phone":"+44 23 8069 3553",
    "sg:postcode":"SO50 7HD",
    "sg:province":"Hampshire",
    "sg:tags":[
        "roofing"
    ],
    "wof:name":"S B M Flat Roofing",
    "wof:placetype":"venue"
},
  "geometry": {"coordinates":[-1.2907940149,50.9654312134],"type":"Point"}
}