{
  "type": "Feature",
  "properties": {
    "addr:full":"38 Victoria Park Road Malvern Herefordshire WR14 2JX",
    "addr:housenumber":"38",
    "addr:postcode":"wr14 2jx",
    "addr:street":"Victoria Park Road",
    "iso:country":"GB",
    "sg:address":"38 Victoria Park Road",
    "sg:city":"Malvern",
    "sg:classifiers":[
        {
            "category":"Professional",
            "subcategory":"Engineering",
            "type":"Services"
        }
    ],
    "sg:phone":"+44 1684 575204",
    "sg:postcode":"WR14 2JX",
    "sg:province":"Herefordshire",
    "sg:tags":[
        "contractor",
        "electrical",
        "engineer"
    ],
    "wof:name":"C-Brite Electrics Ltd.",
    "wof:placetype":"venue"
},
  "geometry": {"coordinates":[-2.311054,52.127937],"type":"Point"}
}