{
  "type": "Feature",
  "properties": {
    "addr:full":"C/o Asda Superstore, Utting Ave Liverpool Merseyside L4 9XU",
    "addr:postcode":"l4 9xu",
    "addr:street":"C / O;Utting Ave",
    "iso:country":"GB",
    "sg:address":"C/o Asda Superstore, Utting Ave",
    "sg:city":"Liverpool",
    "sg:classifiers":[
        {
            "category":"Shopping",
            "subcategory":"Pharmacy",
            "type":"Retail Goods"
        }
    ],
    "sg:postcode":"L4 9XU",
    "sg:province":"Merseyside",
    "sg:tags":[
        "pharmacist",
        "chemist"
    ],
    "wof:name":"O'Brien,G F,",
    "wof:placetype":"venue"
},
  "geometry": {"coordinates":[-2.94,53.44239],"type":"Point"}
}