{
  "type": "Feature",
  "properties": {
    "addr:full":"Langley Fold, Dawley Telford Shropshire TF4 3PT",
    "addr:postcode":"tf4 3pt",
    "addr:street":"Langley Fold",
    "iso:country":"GB",
    "sg:address":"Langley Fold, Dawley",
    "sg:city":"Telford",
    "sg:classifiers":[
        {
            "category":"Social Services",
            "subcategory":"Adult Care",
            "type":"Services"
        }
    ],
    "sg:phone":"+44 1952 592206",
    "sg:postcode":"TF4 3PT",
    "sg:province":"Shropshire",
    "sg:tags":[
        "housing",
        "sheltered"
    ],
    "wof:name":"Langley Fold Sheltered Housing",
    "wof:placetype":"venue"
},
  "geometry": {"coordinates":[-2.461224,52.660583],"type":"Point"}
}