{
  "type": "Feature",
  "properties": {
    "addr:full":"Acton Flat Farm, Kew Hill Elland West Yorkshire HD3 3SY",
    "addr:postcode":"hd3 3sy",
    "addr:street":"Kew Hill Elland West",
    "iso:country":"GB",
    "sg:address":"Acton Flat Farm, Kew Hill",
    "sg:city":"Elland",
    "sg:classifiers":[
        {
            "category":"Farming",
            "subcategory":"Dairy Farm",
            "type":"Manufacturing & Wholesale Goods"
        }
    ],
    "sg:postcode":"HD3 3SY",
    "sg:province":"West Yorkshire",
    "wof:name":"B Mitton",
    "wof:placetype":"venue"
},
  "geometry": {"coordinates":[-1.8392699957,53.6696281433],"type":"Point"}
}