{
  "type": "Feature",
  "properties": {
    "addr:full":"The Stores, Welburn York North Yorkshire YO60 7DX",
    "addr:housenumber":"welburn",
    "addr:postcode":"yo60 7dx",
    "addr:street":"York",
    "iso:country":"GB",
    "sg:address":"The Stores, Welburn",
    "sg:city":"York",
    "sg:classifiers":[
        {
            "category":"Government",
            "subcategory":"Post Office",
            "type":"Public Place"
        }
    ],
    "sg:phone":"+44 1653 618352",
    "sg:postcode":"YO60 7DX",
    "sg:province":"North Yorkshire",
    "wof:name":"Welburn P.O",
    "wof:placetype":"venue"
},
  "geometry": {"coordinates":[-0.8993489742,54.1030464172],"type":"Point"}
}