{
  "type": "Feature",
  "properties": {
    "iso:country":"GB",
    "sg:address":"Wilsontow, Forth",
    "sg:city":"Lanark",
    "sg:classifiers":[
        {
            "category":"Travel",
            "subcategory":"Hotels & Motels",
            "type":"Entertainment"
        }
    ],
    "sg:postcode":"ML11 8EP",
    "sg:province":"South Lanarkshire",
    "wof:name":"Mansewood Hotel",
    "wof:placetype":"venue"
},
  "geometry": {"coordinates":[-3.6883490086,55.7654800415],"type":"Point"}
}