{
  "type": "Feature",
  "properties": {
    "iso:country":"GB",
    "sg:address":"5b Turbary Road",
    "sg:city":"Ferndown",
    "sg:classifiers":[
        {
            "category":"Personal",
            "subcategory":"Beauty Salon",
            "type":"Services"
        }
    ],
    "sg:phone":"+44 1202 875600",
    "sg:postcode":"BH22 8AW",
    "sg:province":"Dorset",
    "sg:tags":[
        "unisex",
        "hairdresser"
    ],
    "wof:name":"Splash Hair Studio",
    "wof:placetype":"venue"
},
  "geometry": {"coordinates":[-1.878171,50.808784],"type":"Point"}
}