{
  "type": "Feature",
  "properties": {
    "iso:country":"GB",
    "sg:address":"147 Station Rd",
    "sg:city":"Chingford",
    "sg:classifiers":[
        {
            "category":"Professional",
            "subcategory":"Accounting & Tax Preparation",
            "type":"Services"
        }
    ],
    "sg:phone":"+44 20 8529 4236",
    "sg:postcode":"E4 6AG",
    "sg:province":"Greater London",
    "sg:tags":[
        "accountant"
    ],
    "wof:name":"Walkers",
    "wof:placetype":"venue"
},
  "geometry": {"coordinates":[0.008384,51.632835],"type":"Point"}
}