{
  "type": "Feature",
  "properties": {
    "addr:full":"7 North Road Maidenhead Berkshire SL6 1PE",
    "addr:housenumber":"7",
    "addr:postcode":"sl6 1pe",
    "addr:street":"North Road",
    "iso:country":"GB",
    "sg:address":"7 North Road",
    "sg:city":"Maidenhead",
    "sg:classifiers":[
        {
            "category":"Professional",
            "subcategory":"Management & Consulting",
            "type":"Services"
        },
        {
            "category":"Professional",
            "subcategory":"Business Services",
            "type":"Services"
        }
    ],
    "sg:phone":"+44 1628 526526",
    "sg:postcode":"SL6 1PE",
    "sg:province":"Berkshire",
    "sg:tags":[
        "marketing",
        "hospitality",
        "corporate",
        "consultant"
    ],
    "wof:name":"T L C Products & Services Ltd.",
    "wof:placetype":"venue"
},
  "geometry": {"coordinates":[-0.7280039787,51.5219993591],"type":"Point"}
}