{
  "type": "Feature",
  "properties": {
    "addr:full":"1 Barnsley Road Birmingham West Midlands B17 8EB",
    "addr:housenumber":"1",
    "addr:postcode":"b17 8eb",
    "addr:street":"Barnsley Road",
    "iso:country":"GB",
    "sg:address":"1 Barnsley Road",
    "sg:city":"Birmingham",
    "sg:classifiers":[
        {
            "category":"Professional",
            "subcategory":"Accounting & Tax Preparation",
            "type":"Services"
        }
    ],
    "sg:postcode":"B17 8EB",
    "sg:province":"West Midlands",
    "sg:tags":[
        "payroll"
    ],
    "wof:name":"Payroll First",
    "wof:placetype":"venue"
},
  "geometry": {"coordinates":[-1.9656,52.473415],"type":"Point"}
}