{
  "type": "Feature",
  "properties": {
    "iso:country":"GB",
    "sg:address":"109 Columbia Road",
    "sg:city":"Bournemouth",
    "sg:classifiers":[
        {
            "category":"Shopping",
            "subcategory":"News",
            "type":"Retail Goods"
        }
    ],
    "sg:phone":"+44 1202 515367",
    "sg:postcode":"BH10 4ED",
    "sg:province":"Dorset",
    "sg:tags":[
        "newsagent"
    ],
    "wof:name":"Columbia News",
    "wof:placetype":"venue"
},
  "geometry": {"coordinates":[-1.891736,50.752102],"type":"Point"}
}