{
  "type": "Feature",
  "properties": {
    "iso:country":"GB",
    "sg:address":"121 Bromford Lane",
    "sg:city":"Birmingham",
    "sg:classifiers":[
        {
            "category":"Sports & Exercise",
            "subcategory":"Tennis Court",
            "type":"Entertainment"
        }
    ],
    "sg:phone":"+44 7973 151594",
    "sg:postcode":"B24 8JP",
    "sg:province":"West Midlands",
    "sg:tags":[
        "breakdown",
        "recovery"
    ],
    "wof:name":"Autohelp Mobile Vehicle Repairs",
    "wof:placetype":"venue"
},
  "geometry": {"coordinates":[-1.834757,52.512081],"type":"Point"}
}