{
  "type": "Feature",
  "properties": {
    "iso:country":"GB",
    "sg:address":"Lord Street, Allenton",
    "sg:city":"Derby",
    "sg:classifiers":[
        {
            "category":"Farming",
            "subcategory":"Nursery",
            "type":"Manufacturing & Wholesale Goods"
        },
        {
            "category":"Education",
            "subcategory":"Preschool",
            "type":"Public Place"
        }
    ],
    "sg:phone":"+44 1332 349363",
    "sg:postcode":"DE24 9AX",
    "sg:province":"Derbyshire",
    "sg:tags":[
        "school",
        "creche"
    ],
    "wof:name":"Lord Street Community Nursery School",
    "wof:placetype":"venue"
},
  "geometry": {"coordinates":[-1.453469,52.89106],"type":"Point"}
}