{
  "type": "Feature",
  "properties": {
    "addr:full":"11 Castle Way Southampton Hampshire SO14 2BX",
    "addr:housenumber":"11",
    "addr:postcode":"so14 2bx",
    "addr:street":"Castle Way",
    "iso:country":"GB",
    "sg:address":"11 Castle Way",
    "sg:city":"Southampton",
    "sg:classifiers":[
        {
            "category":"Restaurant",
            "type":"Food & Drink"
        }
    ],
    "sg:phone":"+44 23 8063 0670",
    "sg:postcode":"SO14 2BX",
    "sg:province":"Hampshire",
    "sg:tags":[
        "thai",
        "-"
    ],
    "wof:name":"Taste of Thailand",
    "wof:placetype":"venue"
},
  "geometry": {"coordinates":[-1.4050049782,50.9019088745],"type":"Point"}
}