{
  "type": "Feature",
  "properties": {
    "iso:country":"GB",
    "sg:address":"386 Third Avenue, Trafford Park",
    "sg:city":"Manchester",
    "sg:classifiers":[
        {
            "category":"Shopping",
            "subcategory":"Gifts & Souvenirs",
            "type":"Retail Goods"
        }
    ],
    "sg:phone":"+44 161 877 8727",
    "sg:postcode":"M17 1JE",
    "sg:province":"Cheshire",
    "sg:tags":[
        "shop"
    ],
    "wof:name":"Trafford Park Heritage Shop",
    "wof:placetype":"venue"
},
  "geometry": {"coordinates":[-2.3103020191,53.4657592773],"type":"Point"}
}