{
  "type": "Feature",
  "properties": {
    "iso:country":"GB",
    "sg:address":"Haworth Street, Oswaldtwistle",
    "sg:city":"Accrington",
    "sg:classifiers":[
        {
            "category":"Education",
            "subcategory":"School",
            "type":"Public Place"
        },
        {
            "category":"Organizations",
            "subcategory":"Non-profit Organization",
            "type":"Services"
        }
    ],
    "sg:phone":"+44 1254 231051",
    "sg:postcode":"BB5 3EA",
    "sg:province":"Lancashire",
    "sg:tags":[
        "organisation",
        "local",
        "voluntary",
        "authority",
        "charity"
    ],
    "wof:name":"Rhyddings County High School",
    "wof:placetype":"venue"
},
  "geometry": {"coordinates":[-2.3973150253,53.7425842285],"type":"Point"}
}