{
  "type": "Feature",
  "properties": {
    "addr:full":"Llwyn Ifor Lane, Whitford Holywell Denbighshire CH8 9ER",
    "addr:postcode":"ch8 9er",
    "addr:street":"Llwyn Ifor Lane",
    "iso:country":"GB",
    "sg:address":"Llwyn Ifor Lane, Whitford",
    "sg:city":"Holywell",
    "sg:classifiers":[
        {
            "category":"Banks & Credit Unions",
            "subcategory":"Investment Brokerage",
            "type":"Services"
        }
    ],
    "sg:phone":"+44 1352 715200",
    "sg:postcode":"CH8 9ER",
    "sg:province":"Denbighshire",
    "sg:tags":[
        "contractor"
    ],
    "wof:name":"Agricultural Contracting",
    "wof:placetype":"venue"
},
  "geometry": {"coordinates":[-3.2510089874,53.2908973694],"type":"Point"}
}