{
  "type": "Feature",
  "properties": {
    "iso:country":"GB",
    "sg:address":"121 High Street, Lochee",
    "sg:city":"Dundee",
    "sg:classifiers":[
        {
            "category":"Farming",
            "subcategory":"Fish & Marine Products",
            "type":"Manufacturing & Wholesale Goods"
        },
        {
            "category":"Food & Beverages",
            "subcategory":"Meat & Fish",
            "type":"Retail Goods"
        }
    ],
    "sg:phone":"+44 1382 611613",
    "sg:postcode":"DD2 3BX",
    "sg:province":"Dundee City",
    "sg:tags":[
        "fishmonger",
        "butcher"
    ],
    "wof:name":"D Webster",
    "wof:placetype":"venue"
},
  "geometry": {"coordinates":[-3.009592,56.472576],"type":"Point"}
}