{
  "type": "Feature",
  "properties": {
    "iso:country":"GB",
    "sg:address":"Harrop Farm, Lane Side, Wilsden",
    "sg:city":"Bradford",
    "sg:classifiers":[
        {
            "category":"Recreation",
            "subcategory":"Dog Park",
            "type":"Entertainment"
        }
    ],
    "sg:postcode":"BD15 0DA",
    "sg:province":"West Yorkshire",
    "wof:name":"Harrop Labradors",
    "wof:placetype":"venue"
},
  "geometry": {"coordinates":[-1.860289,53.823013],"type":"Point"}
}