{
  "type": "Feature",
  "properties": {
    "addr:full":"123 Belgrave Gate Leicester Leicestershire LE1 3HS",
    "addr:housenumber":"123",
    "addr:postcode":"le1 3hs",
    "addr:street":"Belgrave Gate",
    "iso:country":"GB",
    "sg:address":"123 Belgrave Gate",
    "sg:city":"Leicester",
    "sg:classifiers":[
        {
            "category":"Home & Garden",
            "subcategory":"Home Furnishings",
            "type":"Retail Goods"
        }
    ],
    "sg:phone":"+44 116 233 5777",
    "sg:postcode":"LE1 3HS",
    "sg:province":"Leicestershire",
    "sg:tags":[
        "homefurnishings"
    ],
    "wof:name":"A1 Aspen Developments",
    "wof:placetype":"venue"
},
  "geometry": {"coordinates":[-1.130476,52.639801],"type":"Point"}
}