{
  "type": "Feature",
  "properties": {
    "iso:country":"GB",
    "sg:address":"7 Castlegreen Street",
    "sg:city":"Dumbarton",
    "sg:classifiers":[
        {
            "category":"Utilities",
            "subcategory":"Refuse",
            "type":"Services"
        }
    ],
    "sg:phone":"+44 1389 734770",
    "sg:postcode":"G82 1HN",
    "sg:province":"Argyll and Bute",
    "sg:tags":[
        "disposal",
        "waste"
    ],
    "wof:name":"Hoodem Ltd.",
    "wof:placetype":"venue"
},
  "geometry": {"coordinates":[-4.558486,55.940823],"type":"Point"}
}