{
  "type": "Feature",
  "properties": {
    "addr:full":"2 Birs Clo Wickford Essex SS11 7BS",
    "addr:housenumber":"2",
    "addr:postcode":"ss11 7bs",
    "addr:street":"Birs Clo",
    "iso:country":"GB",
    "sg:address":"2 Birs Clo",
    "sg:city":"Wickford",
    "sg:classifiers":[
        {
            "category":"Professional",
            "subcategory":"Printing & Photocopies",
            "type":"Services"
        }
    ],
    "sg:postcode":"SS11 7BS",
    "sg:province":"Essex",
    "sg:tags":[
        "printer"
    ],
    "wof:name":"Willets,Gary,",
    "wof:placetype":"venue"
},
  "geometry": {"coordinates":[0.522176981,51.6218833923],"type":"Point"}
}