{
  "type": "Feature",
  "properties": {
    "addr:full":"2 Cedar Street Bootle Merseyside L20 3HD",
    "addr:housenumber":"2",
    "addr:postcode":"l20 3hd",
    "addr:street":"Cedar Street",
    "iso:country":"GB",
    "sg:address":"2 Cedar Street",
    "sg:city":"Bootle",
    "sg:classifiers":[
        {
            "category":"Retail",
            "subcategory":"Auto Repair",
            "type":"Services"
        }
    ],
    "sg:phone":"+44 151 922 3149",
    "sg:postcode":"L20 3HD",
    "sg:province":"Merseyside",
    "sg:tags":[
        "bodybuilder",
        "repairer"
    ],
    "wof:name":"James Welsh & Son Ltd.",
    "wof:placetype":"venue"
},
  "geometry": {"coordinates":[-2.990095,53.453728],"type":"Point"}
}