{
  "type": "Feature",
  "properties": {
    "iso:country":"GB",
    "sg:address":"12 Nurserymans Rd, New Southgate",
    "sg:city":"Friern Barnet",
    "sg:classifiers":[
        {
            "category":"Building & Trades",
            "subcategory":"Construction",
            "type":"Services"
        }
    ],
    "sg:phone":"+44 20 8361 9396",
    "sg:postcode":"N11 1DZ",
    "sg:province":"Greater London",
    "sg:tags":[
        "joinery"
    ],
    "wof:name":"Ashcroft Fencing",
    "wof:placetype":"venue"
},
  "geometry": {"coordinates":[-0.1475870013,51.6278114319],"type":"Point"}
}