{
  "type": "Feature",
  "properties": {
    "addr:full":"87 Church Road, Wootton Bridge Ryde Isle of Wight PO33 4NH",
    "addr:housenumber":"87",
    "addr:postcode":"po33 4nh",
    "addr:street":"Church Road",
    "iso:country":"GB",
    "sg:address":"87 Church Road, Wootton Bridge",
    "sg:city":"Ryde",
    "sg:classifiers":[
        {
            "category":"Building & Trades",
            "subcategory":"Landscaping Services",
            "type":"Services"
        }
    ],
    "sg:postcode":"PO33 4NH",
    "sg:province":"Isle of Wight",
    "sg:tags":[
        "gardening"
    ],
    "wof:name":"Bob's Services",
    "wof:placetype":"venue"
},
  "geometry": {"coordinates":[-1.2364269495,50.7310600281],"type":"Point"}
}