{
  "type": "Feature",
  "properties": {
    "addr:full":"21 Staithe Street Wells-next-the-sea Norfolk NR23 1AG",
    "addr:housenumber":"21",
    "addr:postcode":"nr23 1ag",
    "addr:street":"Staithe Street",
    "iso:country":"GB",
    "sg:address":"21 Staithe Street",
    "sg:city":"Wells-next-the-sea",
    "sg:classifiers":[
        {
            "category":"Cafe",
            "type":"Food & Drink"
        }
    ],
    "sg:phone":"+44 1328 711650",
    "sg:postcode":"NR23 1AG",
    "sg:province":"Norfolk",
    "sg:tags":[
        "tea",
        "snack",
        "bar",
        "room"
    ],
    "wof:name":"Nelson's Coffee Shop",
    "wof:placetype":"venue"
},
  "geometry": {"coordinates":[0.852055,52.954956],"type":"Point"}
}