{
  "type": "Feature",
  "properties": {
    "iso:country":"GB",
    "sg:address":"82-84 Brandon Parade East",
    "sg:city":"Motherwell",
    "sg:classifiers":[
        {
            "category":"Organizations",
            "subcategory":"Community Association",
            "type":"Services"
        }
    ],
    "sg:phone":"+44 1698 268855",
    "sg:postcode":"ML1 1LY",
    "sg:province":"North Lanarkshire",
    "sg:tags":[
        "society",
        "housing"
    ],
    "wof:name":"Clyde Valley Housing",
    "wof:placetype":"venue"
},
  "geometry": {"coordinates":[-3.9915189743,55.7887649536],"type":"Point"}
}