{
  "type": "Feature",
  "properties": {
    "iso:country":"GB",
    "sg:address":"Unit 2 Oak Street",
    "sg:city":"Brierley Hill",
    "sg:classifiers":[
        {
            "category":"Retail",
            "subcategory":"Repair Shop",
            "type":"Services"
        }
    ],
    "sg:phone":"+44 1384 413631",
    "sg:postcode":"DY5 2JN",
    "sg:province":"West Midlands",
    "sg:tags":[
        "upholsterer"
    ],
    "wof:name":"Pro-Fab Upholstery",
    "wof:placetype":"venue"
},
  "geometry": {"coordinates":[-2.106326,52.473351],"type":"Point"}
}