{
  "type": "Feature",
  "properties": {
    "iso:country":"GB",
    "sg:address":"1258 Coventry Road, Yardley",
    "sg:city":"Birmingham",
    "sg:classifiers":[
        {
            "category":"Fast Food",
            "type":"Food & Drink"
        }
    ],
    "sg:phone":"+44 121 693 4888",
    "sg:postcode":"B25 8BJ",
    "sg:province":"West Midlands",
    "sg:tags":[
        "away",
        "take"
    ],
    "wof:name":"The Balti King",
    "wof:placetype":"venue"
},
  "geometry": {"coordinates":[-1.8274899721,52.4630203247],"type":"Point"}
}