{
  "type": "Feature",
  "properties": {
    "addr:full":"Temple Gro, Bakers Lane Chelmsford Essex CM2 8LQ",
    "addr:postcode":"cm2 8lq",
    "addr:street":"Gro Bakers Lane",
    "iso:country":"GB",
    "sg:address":"Temple Gro, Bakers Lane",
    "sg:city":"Chelmsford",
    "sg:classifiers":[
        {
            "category":"Manufacturing",
            "subcategory":"Buildings",
            "type":"Manufacturing & Wholesale Goods"
        }
    ],
    "sg:phone":"+44 1277 840241",
    "sg:postcode":"CM2 8LQ",
    "sg:province":"Essex",
    "sg:tags":[
        "mobile",
        "home"
    ],
    "wof:name":"The Berkeley Leisure Group",
    "wof:placetype":"venue"
},
  "geometry": {"coordinates":[0.4736810029,51.6855773926],"type":"Point"}
}