{
  "type": "Feature",
  "properties": {
    "iso:country":"GB",
    "sg:address":"23-25 Lake Bank",
    "sg:city":"Littleborough",
    "sg:classifiers":[
        {
            "category":"Restaurant",
            "type":"Food & Drink"
        }
    ],
    "sg:phone":"+44 1706 378333",
    "sg:postcode":"OL15 0DQ",
    "sg:province":"Lancashire",
    "sg:tags":[
        "-",
        "english"
    ],
    "wof:name":"Charlottes by the Lake",
    "wof:placetype":"venue"
},
  "geometry": {"coordinates":[-2.097314,53.633816],"type":"Point"}
}