{
  "type": "Feature",
  "properties": {
    "iso:country":"GB",
    "sg:address":"Leconfield House, Curzon St",
    "sg:city":"West End",
    "sg:classifiers":[
        {
            "category":"Retail",
            "subcategory":"Event Space",
            "type":"Services"
        }
    ],
    "sg:phone":"+44 20 7302 6262",
    "sg:postcode":"W1Y 7FB",
    "sg:province":"Hampshire",
    "sg:tags":[
        "product",
        "direct"
    ],
    "wof:name":"G E Capital Real Estate",
    "wof:placetype":"venue"
},
  "geometry": {"coordinates":[-0.144951,51.507957],"type":"Point"}
}