{
  "type": "Feature",
  "properties": {
    "addr:full":"Arndale House Bradford West Yorkshire BD1 1LN",
    "addr:postcode":"bd1 1ln",
    "addr:street":"Bradford West",
    "iso:country":"GB",
    "sg:address":"Arndale House",
    "sg:city":"Bradford",
    "sg:classifiers":[
        {
            "category":"Banks & Credit Unions",
            "subcategory":"Bureau De Change",
            "type":"Services"
        }
    ],
    "sg:phone":"+44 1274 305222",
    "sg:postcode":"BD1 1LN",
    "sg:province":"West Yorkshire",
    "wof:name":"American Express Europe Ltd.",
    "wof:placetype":"venue"
},
  "geometry": {"coordinates":[-1.758306,53.795738],"type":"Point"}
}