{
  "type": "Feature",
  "properties": {
    "iso:country":"GB",
    "sg:address":"1 Princess Way",
    "sg:city":"Camberley",
    "sg:classifiers":[
        {
            "category":"Travel",
            "subcategory":"Travel Agent",
            "type":"Entertainment"
        }
    ],
    "sg:phone":"+44 1276 685651",
    "sg:postcode":"GU15 3SP",
    "sg:province":"Berkshire",
    "wof:name":"Going Places Leisure Travel",
    "wof:placetype":"venue"
},
  "geometry": {"coordinates":[-0.7442219853,51.3374900818],"type":"Point"}
}