{
  "type": "Feature",
  "properties": {
    "iso:country":"GB",
    "sg:address":"2 South St",
    "sg:city":"Cupar",
    "sg:classifiers":[
        {
            "category":"Place Of Worship",
            "type":"Public Place"
        }
    ],
    "sg:phone":"+44 1337 831562",
    "sg:postcode":"KY15 7PL",
    "sg:province":"Fife",
    "wof:name":"Howe Of Fife Church Office",
    "wof:placetype":"venue"
},
  "geometry": {"coordinates":[-3.0091509819,56.3152046204],"type":"Point"}
}