{
  "type": "Feature",
  "properties": {
    "addr:full":"30 Erith Road Bexleyheath Kent DA7 6BP",
    "addr:housenumber":"30",
    "addr:postcode":"da7 6bp",
    "addr:street":"Erith Road",
    "iso:country":"GB",
    "sg:address":"30 Erith Road",
    "sg:city":"Bexleyheath",
    "sg:classifiers":[
        {
            "category":"Banks & Credit Unions",
            "subcategory":"Bank",
            "type":"Services"
        }
    ],
    "sg:phone":"+44 845 071 8392",
    "sg:postcode":"DA7 6BP",
    "sg:province":"Kent",
    "sg:tags":[
        "financial",
        "institution"
    ],
    "wof:name":"Woolwich Ltd",
    "wof:placetype":"venue"
},
  "geometry": {"coordinates":[0.153225,51.455841],"type":"Point"}
}