{
  "type": "Feature",
  "properties": {
    "iso:country":"GB",
    "sg:address":"11 Woodchurch Road",
    "sg:city":"Birkenhead",
    "sg:classifiers":[
        {
            "category":"Professional",
            "subcategory":"Business Services",
            "type":"Services"
        },
        {
            "category":"Casinos & Gambling",
            "type":"Entertainment"
        }
    ],
    "sg:phone":"+44 151 652 2705",
    "sg:postcode":"CH42 9LG",
    "sg:province":"Merseyside",
    "sg:tags":[
        "turf",
        "accountant",
        "bookmaker"
    ],
    "wof:name":"Chris Pluck",
    "wof:placetype":"venue"
},
  "geometry": {"coordinates":[-3.0370280743,53.3818206787],"type":"Point"}
}