{
  "type": "Feature",
  "properties": {
    "addr:full":"Newington Farm, Newington Doncaster Lincolnshire DN10 6DJ",
    "addr:postcode":"dn10 6dj",
    "iso:country":"GB",
    "sg:address":"Newington Farm, Newington",
    "sg:city":"Doncaster",
    "sg:classifiers":[
        {
            "category":"Shopping",
            "type":"Retail Goods"
        },
        {
            "category":"Wholesale",
            "subcategory":"Fruits & Vegetables",
            "type":"Manufacturing & Wholesale Goods"
        }
    ],
    "sg:phone":"+44 1302 719532",
    "sg:postcode":"DN10 6DJ",
    "sg:province":"Lincolnshire",
    "sg:tags":[
        "merchant",
        "grower",
        "mushroom"
    ],
    "wof:name":"Tunnel Tech North Ltd",
    "wof:placetype":"venue"
},
  "geometry": {"coordinates":[-0.997561,53.439117],"type":"Point"}
}