{
  "type": "Feature",
  "properties": {
    "addr:full":"2 Wyses Cottage Wyses Rd, Highwood Chelmsford Essex CM1 3SN",
    "addr:housenumber":"2",
    "addr:postcode":"cm1 3sn",
    "addr:street":"Wyses Rd",
    "iso:country":"GB",
    "sg:address":"2 Wyses Cottage Wyses Rd, Highwood",
    "sg:city":"Chelmsford",
    "sg:classifiers":[
        {
            "category":"Professional",
            "subcategory":"Detective & Security Services",
            "type":"Services"
        }
    ],
    "sg:postcode":"CM1 3SN",
    "sg:province":"Essex",
    "wof:name":"Tye Security",
    "wof:placetype":"venue"
},
  "geometry": {"coordinates":[0.3785490096,51.7151565552],"type":"Point"}
}