{
  "type": "Feature",
  "properties": {
    "iso:country":"GB",
    "sg:address":"37 High Street",
    "sg:city":"Ibstock",
    "sg:classifiers":[
        {
            "category":"Food & Beverages",
            "subcategory":"Fruits & Vegetables",
            "type":"Retail Goods"
        }
    ],
    "sg:postcode":"LE67 6LH",
    "sg:province":"Leicestershire",
    "sg:tags":[
        "greengrocer"
    ],
    "wof:name":"Harvest Fare",
    "wof:placetype":"venue"
},
  "geometry": {"coordinates":[-1.399053,52.686069],"type":"Point"}
}