{
  "type": "Feature",
  "properties": {
    "iso:country":"GB",
    "sg:address":"Reelig House, Reelig Estate",
    "sg:city":"Inverness",
    "sg:classifiers":[
        {
            "category":"Travel",
            "subcategory":"Hotels & Motels",
            "type":"Entertainment"
        },
        {
            "category":"Real Estate",
            "subcategory":"Real Estate Agent",
            "type":"Services"
        }
    ],
    "sg:phone":"+44 1463 831208",
    "sg:postcode":"IV5 7PP",
    "sg:province":"Highland",
    "sg:tags":[
        "house",
        "self",
        "guest",
        "catering"
    ],
    "wof:name":"Reelig Estate",
    "wof:placetype":"venue"
},
  "geometry": {"coordinates":[-4.40671,57.462448],"type":"Point"}
}