{
  "type": "Feature",
  "properties": {
    "addr:full":"10 Castle Business Park, Castle Foregate Shrewsbury Shropshire SY1 2EG",
    "addr:housenumber":"10",
    "addr:postcode":"sy1 2eg",
    "addr:street":"Castle Business Park;Foregate",
    "iso:country":"GB",
    "sg:address":"10 Castle Business Park, Castle Foregate",
    "sg:city":"Shrewsbury",
    "sg:classifiers":[
        {
            "category":"Farming",
            "subcategory":"Nursery",
            "type":"Manufacturing & Wholesale Goods"
        }
    ],
    "sg:postcode":"SY1 2EG",
    "sg:province":"Shropshire",
    "sg:tags":[
        "creche"
    ],
    "wof:name":"Sunshine Day Nursery",
    "wof:placetype":"venue"
},
  "geometry": {"coordinates":[-2.751284,52.706566],"type":"Point"}
}