{
  "type": "Feature",
  "properties": {
    "addr:full":"First Floor, Seymour House Walsall West Midlands WS2 8HE",
    "addr:postcode":"ws2 8he",
    "addr:street":"Walsall",
    "iso:country":"GB",
    "sg:address":"First Floor, Seymour House",
    "sg:city":"Walsall",
    "sg:classifiers":[
        {
            "category":"Shopping",
            "subcategory":"Baby Store",
            "type":"Retail Goods"
        }
    ],
    "sg:phone":"+44 1922 626466",
    "sg:postcode":"WS2 8HE",
    "sg:province":"West Midlands",
    "sg:tags":[
        "nursery",
        "accessory"
    ],
    "wof:name":"Kiddisave Ltd.",
    "wof:placetype":"venue"
},
  "geometry": {"coordinates":[-1.996169,52.590889],"type":"Point"}
}