{
  "type": "Feature",
  "properties": {
    "iso:country":"GB",
    "sg:address":"6 Colville Mews",
    "sg:city":"London",
    "sg:classifiers":[
        {
            "category":"Manufacturing",
            "subcategory":"Paper Products",
            "type":"Manufacturing & Wholesale Goods"
        }
    ],
    "sg:phone":"+44 20 7792 5561",
    "sg:postcode":"W11 2DA",
    "sg:province":"Greater London",
    "sg:tags":[
        "stationery",
        "mnfr"
    ],
    "wof:name":"Julie Bell Stationery",
    "wof:placetype":"venue"
},
  "geometry": {"coordinates":[-0.2037509978,51.5156135559],"type":"Point"}
}