{
  "type": "Feature",
  "properties": {
    "addr:full":"1-4 Cressy Street, Linthouse Glasgow Glasgow City G51 4RB",
    "addr:housenumber":"1-4",
    "addr:postcode":"g51 4rb",
    "addr:street":"Cressy Street",
    "iso:country":"GB",
    "sg:address":"1-4 Cressy Street, Linthouse",
    "sg:city":"Glasgow",
    "sg:classifiers":[
        {
            "category":"Organizations",
            "subcategory":"Membership Organization",
            "type":"Services"
        }
    ],
    "sg:phone":"+44 141 440 0771",
    "sg:postcode":"G51 4RB",
    "sg:province":"Glasgow City",
    "sg:tags":[
        "club"
    ],
    "wof:name":"The Reform Club",
    "wof:placetype":"venue"
},
  "geometry": {"coordinates":[-4.328891,55.8643],"type":"Point"}
}