{
  "type": "Feature",
  "properties": {
    "addr:full":"Barrows Hill Farm, East Chinnock Yeovil Dorset BA22 9EY",
    "addr:housenumber":"chinnock",
    "addr:postcode":"ba22 9ey",
    "addr:street":"Barrows Hill",
    "iso:country":"GB",
    "sg:address":"Barrows Hill Farm, East Chinnock",
    "sg:city":"Yeovil",
    "sg:classifiers":[
        {
            "category":"Building & Trades",
            "subcategory":"Construction",
            "type":"Services"
        }
    ],
    "sg:postcode":"BA22 9EY",
    "sg:province":"Dorset",
    "sg:tags":[
        "joiner",
        "carpenter"
    ],
    "wof:name":"Rainer Whittlin",
    "wof:placetype":"venue"
},
  "geometry": {"coordinates":[-2.7186939716,50.9156951904],"type":"Point"}
}