{
  "type": "Feature",
  "properties": {
    "iso:country":"GB",
    "sg:address":"14 Apollo Studios, Charlton Kings Rd",
    "sg:city":"Kentish Town",
    "sg:classifiers":[
        {
            "category":"Professional",
            "subcategory":"Art Services",
            "type":"Services"
        }
    ],
    "sg:phone":"+44 20 7482 4262",
    "sg:postcode":"NW5 2SB",
    "sg:province":"Greater London",
    "sg:tags":[
        "graphic",
        "designer"
    ],
    "wof:name":"Meco Ltd",
    "wof:placetype":"venue"
},
  "geometry": {"coordinates":[-0.131742999,51.5512542725],"type":"Point"}
}