{
  "type": "Feature",
  "properties": {
    "addr:full":"2 Regent Place Birmingham West Midlands B1 3NJ",
    "addr:housenumber":"2",
    "addr:postcode":"b1 3nj",
    "addr:street":"Regent Place",
    "iso:country":"GB",
    "sg:address":"2 Regent Place",
    "sg:city":"Birmingham",
    "sg:classifiers":[
        {
            "category":"Autos & Motor Vehicles",
            "subcategory":"Motorcycle Sales",
            "type":"Retail Goods"
        }
    ],
    "sg:phone":"+44 121 693 3333",
    "sg:postcode":"B1 3NJ",
    "sg:province":"West Midlands",
    "sg:tags":[
        "chauffeur",
        "driven",
        "car"
    ],
    "wof:name":"Brendon Brannigan",
    "wof:placetype":"venue"
},
  "geometry": {"coordinates":[-1.910775,52.485889],"type":"Point"}
}