{
  "type": "Feature",
  "properties": {
    "addr:full":"306a Queslett Road, Great Barr Birmingham West Midlands B43 7EX",
    "addr:housenumber":"306a",
    "addr:postcode":"b43 7ex",
    "addr:street":"Queslett Road",
    "iso:country":"GB",
    "sg:address":"306a Queslett Road, Great Barr",
    "sg:city":"Birmingham",
    "sg:classifiers":[
        {
            "category":"Professional",
            "subcategory":"Research",
            "type":"Services"
        }
    ],
    "sg:phone":"+44 845 050 2151",
    "sg:postcode":"B43 7EX",
    "sg:province":"West Midlands",
    "sg:tags":[
        "market"
    ],
    "wof:name":"Freeman Research",
    "wof:placetype":"venue"
},
  "geometry": {"coordinates":[-1.910112977,52.5533943176],"type":"Point"}
}