{
  "type": "Feature",
  "properties": {
    "addr:full":"26 Sticklepath Hill, Sticklepath Barnstaple Devon EX31 2BU",
    "addr:housenumber":"26",
    "addr:postcode":"ex31 2bu",
    "addr:street":"Sticklepath Hill",
    "iso:country":"GB",
    "sg:address":"26 Sticklepath Hill, Sticklepath",
    "sg:city":"Barnstaple",
    "sg:classifiers":[
        {
            "category":"Travel",
            "subcategory":"Hotels & Motels",
            "type":"Entertainment"
        }
    ],
    "sg:phone":"+44 1271 374022",
    "sg:postcode":"EX31 2BU",
    "sg:province":"Devon",
    "sg:tags":[
        "house",
        "guest"
    ],
    "wof:name":"Cresta Guest House",
    "wof:placetype":"venue"
},
  "geometry": {"coordinates":[-4.0733098984,51.0729370117],"type":"Point"}
}