{
  "type": "Feature",
  "properties": {
    "addr:full":"The Timber Yard, 26-28 Mill Hill Deal Kent CT14 9EW",
    "addr:housenumber":"26-28",
    "addr:postcode":"ct14 9ew",
    "addr:street":"Mill Hill Deal",
    "iso:country":"GB",
    "sg:address":"The Timber Yard, 26-28 Mill Hill",
    "sg:city":"Deal",
    "sg:classifiers":[
        {
            "category":"Home & Garden",
            "subcategory":"Building Materials",
            "type":"Retail Goods"
        }
    ],
    "sg:phone":"+44 1304 367331",
    "sg:postcode":"CT14 9EW",
    "sg:province":"Kent",
    "sg:tags":[
        "fencing"
    ],
    "wof:name":"E H Brown Fencing Ltd.",
    "wof:placetype":"venue"
},
  "geometry": {"coordinates":[1.403235,51.223129],"type":"Point"}
}