{
  "type": "Feature",
  "properties": {
    "iso:country":"GB",
    "sg:address":"2c Stafford Street, Eccleshall",
    "sg:city":"Stafford",
    "sg:classifiers":[
        {
            "category":"Professional",
            "subcategory":"Business Services",
            "type":"Services"
        }
    ],
    "sg:phone":"+44 1785 850350",
    "sg:postcode":"ST21 6BH",
    "sg:province":"Staffordshire",
    "sg:tags":[
        "bookmaker"
    ],
    "wof:name":"Keith Hill",
    "wof:placetype":"venue"
},
  "geometry": {"coordinates":[-2.251665,52.859638],"type":"Point"}
}