{
  "type": "Feature",
  "properties": {
    "iso:country":"GB",
    "sg:address":"4 Wellington Ho Cold Bath Rd",
    "sg:city":"Harrogate",
    "sg:classifiers":[
        {
            "category":"Professional",
            "subcategory":"Business Services",
            "type":"Services"
        }
    ],
    "sg:postcode":"HG2 0NA",
    "sg:province":"North Yorkshire",
    "sg:tags":[
        "import",
        "export",
        "agent"
    ],
    "wof:name":"Chappell,Julie,",
    "wof:placetype":"venue"
},
  "geometry": {"coordinates":[-1.5476590395,53.9918327332],"type":"Point"}
}