{
  "type": "Feature",
  "properties": {
    "iso:country":"GB",
    "sg:address":"10 Cross Cheaping",
    "sg:city":"Coventry",
    "sg:classifiers":[
        {
            "category":"Sports & Exercise",
            "subcategory":"Gym",
            "type":"Entertainment"
        }
    ],
    "sg:postcode":"CV1 1HG",
    "sg:province":"West Midlands",
    "sg:tags":[
        "fitness",
        "health",
        "centre"
    ],
    "wof:name":"Bodymasters Gym",
    "wof:placetype":"venue"
},
  "geometry": {"coordinates":[-1.510377,52.409557],"type":"Point"}
}