{
  "type": "Feature",
  "properties": {
    "addr:full":"The Garden House Southill Park, Southill Biggleswade Bedfordshire SG18 9LL",
    "addr:postcode":"sg18 9ll",
    "addr:street":"Southill Park",
    "iso:country":"GB",
    "sg:address":"The Garden House Southill Park, Southill",
    "sg:city":"Biggleswade",
    "sg:classifiers":[
        {
            "category":"Building & Trades",
            "subcategory":"Landscaping Services",
            "type":"Services"
        }
    ],
    "sg:postcode":"SG18 9LL",
    "sg:province":"Bedfordshire",
    "sg:tags":[
        "landscape",
        "contractor"
    ],
    "wof:name":"Hasmead Landscapes",
    "wof:placetype":"venue"
},
  "geometry": {"coordinates":[-0.292903,52.071125],"type":"Point"}
}