{
  "type": "Feature",
  "properties": {
    "addr:full":"4 Masons Rd Slough Berkshire SL1 5QJ",
    "addr:housenumber":"4",
    "addr:postcode":"sl1 5qj",
    "addr:street":"Masons Rd",
    "iso:country":"GB",
    "sg:address":"4 Masons Rd",
    "sg:city":"Slough",
    "sg:classifiers":[
        {
            "category":"Building & Trades",
            "subcategory":"Construction",
            "type":"Services"
        }
    ],
    "sg:phone":"+44 1628 602525",
    "sg:postcode":"SL1 5QJ",
    "sg:province":"Berkshire",
    "sg:tags":[
        "roofing"
    ],
    "wof:name":"Chaplin Bros",
    "wof:placetype":"venue"
},
  "geometry": {"coordinates":[-0.6414290071,51.518901825],"type":"Point"}
}