{
  "type": "Feature",
  "properties": {
    "iso:country":"GB",
    "sg:address":"1 Church View Villas, Hetton Le Hole",
    "sg:city":"Houghton-le-spring",
    "sg:classifiers":[
        {
            "category":"Fast Food",
            "type":"Food & Drink"
        }
    ],
    "sg:phone":"+44 191 517 1110",
    "sg:postcode":"DH5 9AD",
    "sg:province":"Durham",
    "sg:tags":[
        "away",
        "take"
    ],
    "wof:name":"Pizzasmatic",
    "wof:placetype":"venue"
},
  "geometry": {"coordinates":[-1.4514399767,54.8263397217],"type":"Point"}
}