{
  "type": "Feature",
  "properties": {
    "iso:country":"GB",
    "sg:address":"Greengate",
    "sg:city":"Hunstanton",
    "sg:classifiers":[
        {
            "category":"Shopping",
            "subcategory":"Gifts & Souvenirs",
            "type":"Retail Goods"
        }
    ],
    "sg:phone":"+44 1485 532101",
    "sg:postcode":"PE36 6AF",
    "sg:province":"Norfolk",
    "sg:tags":[
        "shop"
    ],
    "wof:name":"Tamworth House",
    "wof:placetype":"venue"
},
  "geometry": {"coordinates":[0.51158,52.949379],"type":"Point"}
}