{
  "type": "Feature",
  "properties": {
    "iso:country":"GB",
    "sg:address":"160 Rolfe St",
    "sg:city":"Smethwick",
    "sg:classifiers":[
        {
            "category":"Shopping",
            "subcategory":"Clothing, Apparel, & Fashions",
            "type":"Retail Goods"
        }
    ],
    "sg:phone":"+44 121 565 4475",
    "sg:postcode":"B66 2AU",
    "sg:province":"West Midlands",
    "sg:tags":[
        "clothing"
    ],
    "wof:name":"Monto Ltd",
    "wof:placetype":"venue"
},
  "geometry": {"coordinates":[-1.963503,52.497444],"type":"Point"}
}