{
  "type": "Feature",
  "properties": {
    "addr:full":"11 Marlons Hemel Hempstead Hertfordshire HP1 1LA",
    "addr:housenumber":"11",
    "addr:postcode":"hp1 1la",
    "addr:street":"Marlons Hemel Hempstead",
    "iso:country":"GB",
    "sg:address":"11 Marlons",
    "sg:city":"Hemel Hempstead",
    "sg:classifiers":[
        {
            "category":"Real Estate",
            "subcategory":"Real Estate Operator",
            "type":"Services"
        }
    ],
    "sg:phone":"+44 1442 242677",
    "sg:postcode":"HP1 1LA",
    "sg:province":"Hertfordshire",
    "sg:tags":[
        "letting",
        "agent"
    ],
    "wof:name":"Your Move",
    "wof:placetype":"venue"
},
  "geometry": {"coordinates":[-0.4750840068,51.7490005493],"type":"Point"}
}