{
  "type": "Feature",
  "properties": {
    "addr:full":"1004 Wimborne Rd Bournemouth Dorset BH9 2DE",
    "addr:housenumber":"1004",
    "addr:postcode":"bh9 2de",
    "addr:street":"Wimborne Rd",
    "iso:country":"GB",
    "sg:address":"1004 Wimborne Rd",
    "sg:city":"Bournemouth",
    "sg:classifiers":[
        {
            "category":"Retail",
            "subcategory":"Repair Shop",
            "type":"Services"
        }
    ],
    "sg:phone":"+44 1202 537547",
    "sg:postcode":"BH9 2DE",
    "sg:province":"Dorset",
    "sg:tags":[
        "upholsterer"
    ],
    "wof:name":"D Mansbridge",
    "wof:placetype":"venue"
},
  "geometry": {"coordinates":[-1.8736809492,50.7562522888],"type":"Point"}
}