{
  "type": "Feature",
  "properties": {
    "addr:full":"Collier St Johnstone Renfrewshire PA5 8AR",
    "addr:postcode":"pa5 8ar",
    "addr:street":"Collier St",
    "iso:country":"GB",
    "sg:address":"Collier St",
    "sg:city":"Johnstone",
    "sg:classifiers":[
        {
            "category":"Education",
            "subcategory":"Library",
            "type":"Public Place"
        }
    ],
    "sg:phone":"+44 1505 335522",
    "sg:postcode":"PA5 8AR",
    "sg:province":"Renfrewshire",
    "sg:tags":[
        "book"
    ],
    "wof:name":"Johnstone Teenage Library",
    "wof:placetype":"venue"
},
  "geometry": {"coordinates":[-4.511656,55.839298],"type":"Point"}
}