{
  "type": "Feature",
  "properties": {
    "addr:full":"4 Naylor Street Liverpool Merseyside L3 6DR",
    "addr:housenumber":"4",
    "addr:postcode":"l3 6dr",
    "addr:street":"Naylor Street",
    "iso:country":"GB",
    "sg:address":"4 Naylor Street",
    "sg:city":"Liverpool",
    "sg:classifiers":[
        {
            "category":"Retail",
            "subcategory":"Auto Repair",
            "type":"Services"
        }
    ],
    "sg:phone":"+44 151 236 2600",
    "sg:postcode":"L3 6DR",
    "sg:province":"Merseyside",
    "sg:tags":[
        "body",
        "car"
    ],
    "wof:name":"J Kerrigan & Co",
    "wof:placetype":"venue"
},
  "geometry": {"coordinates":[-2.987506,53.413792],"type":"Point"}
}