{
  "type": "Feature",
  "properties": {
    "addr:full":"Alexandra House, 153-159 Swinton Hall Road, Swinton Manchester Greater Manchester M27 4AU",
    "addr:housenumber":"153-159",
    "addr:postcode":"m27 4au",
    "addr:street":"Swinton Hall Road",
    "iso:country":"GB",
    "sg:address":"Alexandra House, 153-159 Swinton Hall Road, Swinton",
    "sg:city":"Manchester",
    "sg:classifiers":[
        {
            "category":"Wholesale",
            "subcategory":"Construction Materials",
            "type":"Manufacturing & Wholesale Goods"
        }
    ],
    "sg:phone":"+44 161 728 1201",
    "sg:postcode":"M27 4AU",
    "sg:province":"Greater Manchester",
    "sg:tags":[
        "merchant",
        "glass"
    ],
    "wof:name":"Swinton Glass & Glazing Co Ltd",
    "wof:placetype":"venue"
},
  "geometry": {"coordinates":[-2.3310689926,53.5116386414],"type":"Point"}
}