{
  "type": "Feature",
  "properties": {
    "addr:full":"67 Gordon Avenue Hornchurch Essex RM12 4EA",
    "addr:housenumber":"67",
    "addr:postcode":"rm12 4ea",
    "addr:street":"Gordon Avenue",
    "iso:country":"GB",
    "sg:address":"67 Gordon Avenue",
    "sg:city":"Hornchurch",
    "sg:classifiers":[
        {
            "category":"Retail",
            "subcategory":"Storage",
            "type":"Services"
        }
    ],
    "sg:phone":"+44 1708 438310",
    "sg:postcode":"RM12 4EA",
    "sg:province":"Essex",
    "sg:tags":[
        "household",
        "removal"
    ],
    "wof:name":"Relocate Removals Co",
    "wof:placetype":"venue"
},
  "geometry": {"coordinates":[0.1854799986,51.5608215332],"type":"Point"}
}