{
  "type": "Feature",
  "properties": {
    "addr:full":"17 Station Street East Coventry Warwickshire CV6 5FL",
    "addr:housenumber":"17",
    "addr:postcode":"cv6 5fl",
    "addr:street":"Station Street East",
    "iso:country":"GB",
    "sg:address":"17 Station Street East",
    "sg:city":"Coventry",
    "sg:classifiers":[
        {
            "category":"Shopping",
            "subcategory":"Pharmacy",
            "type":"Retail Goods"
        }
    ],
    "sg:phone":"+44 24 7666 5272",
    "sg:postcode":"CV6 5FL",
    "sg:province":"Warwickshire",
    "sg:tags":[
        "pharmacist",
        "dispensing",
        "chemist"
    ],
    "wof:name":"Dhaliwal Ltd",
    "wof:placetype":"venue"
},
  "geometry": {"coordinates":[-1.49758,52.429211],"type":"Point"}
}