{
  "type": "Feature",
  "properties": {
    "addr:full":"Tithe Farm, Alderminster Stratford-upon-avon Warwickshire CV37 8NX",
    "addr:housenumber":"tithe",
    "addr:postcode":"cv37 8nx",
    "iso:country":"GB",
    "sg:address":"Tithe Farm, Alderminster",
    "sg:city":"Stratford-upon-avon",
    "sg:classifiers":[
        {
            "category":"Building & Trades",
            "subcategory":"Landscaping Services",
            "type":"Services"
        },
        {
            "category":"Banks & Credit Unions",
            "subcategory":"Investment Brokerage",
            "type":"Services"
        },
        {
            "category":"Farming",
            "subcategory":"Farm & Veterinary Services",
            "type":"Manufacturing & Wholesale Goods"
        }
    ],
    "sg:phone":"+44 1789 450809",
    "sg:postcode":"CV37 8NX",
    "sg:province":"Warwickshire",
    "sg:tags":[
        "agricultural",
        "contractor"
    ],
    "wof:name":"J Meadows",
    "wof:placetype":"venue"
},
  "geometry": {"coordinates":[-1.6644799709,52.1351585388],"type":"Point"}
}