{
  "type": "Feature",
  "properties": {
    "addr:full":"197 Sloane Street London Greater London SW1X 9QX",
    "addr:housenumber":"197",
    "addr:postcode":"sw1x 9qx",
    "addr:street":"Sloane Street",
    "iso:country":"GB",
    "sg:address":"197 Sloane Street",
    "sg:city":"London",
    "sg:classifiers":[
        {
            "category":"Home & Garden",
            "subcategory":"Home Furnishings",
            "type":"Retail Goods"
        }
    ],
    "sg:phone":"+44 20 7235 7165",
    "sg:postcode":"SW1X 9QX",
    "sg:province":"Greater London",
    "sg:tags":[
        "beds",
        "bedding",
        "blanket"
    ],
    "wof:name":"Descamps Ltd.",
    "wof:placetype":"venue"
},
  "geometry": {"coordinates":[-0.1597059965,51.5005874634],"type":"Point"}
}