{
  "type": "Feature",
  "properties": {
    "iso:country":"GB",
    "sg:address":"30 Daley Rd",
    "sg:city":"Liverpool",
    "sg:classifiers":[
        {
            "category":"Home & Garden",
            "subcategory":"Carpets & Floor Coverings",
            "type":"Retail Goods"
        }
    ],
    "sg:postcode":"L21 7QQ",
    "sg:province":"Merseyside",
    "sg:tags":[
        "carpets",
        "rug",
        "matting"
    ],
    "wof:name":"Bentley,S,",
    "wof:placetype":"venue"
},
  "geometry": {"coordinates":[-2.99196,53.474831],"type":"Point"}
}