{
  "type": "Feature",
  "properties": {
    "addr:full":"7 Cole St Birkenhead Merseyside L43 4US",
    "addr:housenumber":"7",
    "addr:postcode":"l43 4us",
    "addr:street":"Cole St",
    "iso:country":"GB",
    "sg:address":"7 Cole St",
    "sg:city":"Birkenhead",
    "sg:classifiers":[
        {
            "category":"Professional",
            "subcategory":"Printing & Photocopies",
            "type":"Services"
        }
    ],
    "sg:phone":"+44 151 653 2636",
    "sg:postcode":"L43 4US",
    "sg:province":"Merseyside",
    "sg:tags":[
        "printer"
    ],
    "wof:name":"Premier Design & Print",
    "wof:placetype":"venue"
},
  "geometry": {"coordinates":[-3.0346009731,53.3897705078],"type":"Point"}
}