{
  "type": "Feature",
  "properties": {
    "addr:full":"Woodnook 9 Park Drive Bingley West Yorkshire BD16 3DF",
    "addr:housenumber":"9",
    "addr:postcode":"bd16 3df",
    "addr:street":"Woodnook;Park Drive",
    "iso:country":"GB",
    "sg:address":"Woodnook 9 Park Drive",
    "sg:city":"Bingley",
    "sg:classifiers":[
        {
            "category":"Manufacturing",
            "subcategory":"Metals",
            "type":"Manufacturing & Wholesale Goods"
        },
        {
            "category":"Building & Trades",
            "subcategory":"Cleaning & Sanitation",
            "type":"Services"
        }
    ],
    "sg:phone":"+44 1274 562057",
    "sg:postcode":"BD16 3DF",
    "sg:province":"West Yorkshire",
    "sg:tags":[
        "repair",
        "plant",
        "machinery",
        "maintenance"
    ],
    "wof:name":"PROTRAC",
    "wof:placetype":"venue"
},
  "geometry": {"coordinates":[-1.838927,53.849258],"type":"Point"}
}