{
  "type": "Feature",
  "properties": {
    "addr:full":"Unit S1b, The Business Station, Newport Road Middlesbrough North Yorkshire TS1 5AE",
    "addr:postcode":"ts1 5ae",
    "addr:street":"Newport Road",
    "iso:country":"GB",
    "sg:address":"Unit S1b, The Business Station, Newport Road",
    "sg:city":"Middlesbrough",
    "sg:classifiers":[
        {
            "category":"Shopping",
            "subcategory":"Clothing, Apparel, & Fashions",
            "type":"Retail Goods"
        }
    ],
    "sg:phone":"+44 1642 888711",
    "sg:postcode":"TS1 5AE",
    "sg:province":"North Yorkshire",
    "sg:tags":[
        "menswear"
    ],
    "wof:name":"The Box",
    "wof:placetype":"venue"
},
  "geometry": {"coordinates":[-1.236569,54.572971],"type":"Point"}
}