{
  "type": "Feature",
  "properties": {
    "iso:country":"GB",
    "sg:address":"198 Wellingborough Road",
    "sg:city":"Northampton",
    "sg:classifiers":[
        {
            "category":"Shopping",
            "subcategory":"Crafts & Fabrics",
            "type":"Retail Goods"
        }
    ],
    "sg:postcode":"NN1 4EB",
    "sg:province":"Northamptonshire",
    "sg:tags":[
        "shop",
        "needlecraft",
        "wool"
    ],
    "wof:name":"Pins & Needles",
    "wof:placetype":"venue"
},
  "geometry": {"coordinates":[-0.8783280253,52.2417030334],"type":"Point"}
}