{
  "type": "Feature",
  "properties": {
    "iso:country":"GB",
    "sg:address":"212 Church Street, Hilperton",
    "sg:city":"Trowbridge",
    "sg:classifiers":[
        {
            "category":"Building & Trades",
            "subcategory":"Construction",
            "type":"Services"
        }
    ],
    "sg:postcode":"BA14 7RG",
    "sg:province":"Wiltshire",
    "sg:tags":[
        "joinery",
        "joiner",
        "carpenter",
        "carpentry"
    ],
    "wof:name":"ROGER J BECKETT",
    "wof:placetype":"venue"
},
  "geometry": {"coordinates":[-2.1838700771,51.3304367065],"type":"Point"}
}