{
  "type": "Feature",
  "properties": {
    "iso:country":"GB",
    "sg:address":"16 Priory Street",
    "sg:city":"Milford Haven",
    "sg:classifiers":[
        {
            "category":"Food & Beverages",
            "subcategory":"Bakery",
            "type":"Retail Goods"
        }
    ],
    "sg:phone":"+44 1646 695183",
    "sg:postcode":"SA73 2AD",
    "sg:province":"Pembrokeshire",
    "sg:tags":[
        "baker"
    ],
    "wof:name":"Welsh Bakery",
    "wof:placetype":"venue"
},
  "geometry": {"coordinates":[-5.035406,51.714348],"type":"Point"}
}