{
  "type": "Feature",
  "properties": {
    "iso:country":"GB",
    "sg:address":"2 Fordwich Rd",
    "sg:city":"Canterbury",
    "sg:classifiers":[
        {
            "category":"Autos & Motor Vehicles",
            "subcategory":"Automobile Sales",
            "type":"Retail Goods"
        }
    ],
    "sg:phone":"+44 1227 710240",
    "sg:postcode":"CT2 0BN",
    "sg:province":"Kent",
    "sg:tags":[
        "car"
    ],
    "wof:name":"Fordwich Garage",
    "wof:placetype":"venue"
},
  "geometry": {"coordinates":[1.122292,51.298435],"type":"Point"}
}