{
  "type": "Feature",
  "properties": {
    "iso:country":"GB",
    "sg:address":"Bar Road, Saundby",
    "sg:city":"Retford",
    "sg:classifiers":[
        {
            "category":"Manufacturing",
            "subcategory":"Tools & Machinery",
            "type":"Manufacturing & Wholesale Goods"
        },
        {
            "category":"Home & Garden",
            "subcategory":"Garden Supply",
            "type":"Retail Goods"
        },
        {
            "category":"Building & Trades",
            "subcategory":"Landscaping Services",
            "type":"Services"
        }
    ],
    "sg:phone":"+44 1427 848696",
    "sg:postcode":"DN22 9EU",
    "sg:province":"Nottinghamshire",
    "sg:tags":[
        "consultant",
        "nursery",
        "horticultural",
        "centre"
    ],
    "wof:name":"Sunny Bank Garden Centre",
    "wof:placetype":"venue"
},
  "geometry": {"coordinates":[-0.8229590058,53.3857307434],"type":"Point"}
}