{
  "type": "Feature",
  "properties": {
    "addr:full":"126 Lichfield Street Walsall West Midlands WS1 1SY",
    "addr:housenumber":"126",
    "addr:postcode":"ws1 1sy",
    "addr:street":"Lichfield Street",
    "iso:country":"GB",
    "sg:address":"126 Lichfield Street",
    "sg:city":"Walsall",
    "sg:classifiers":[
        {
            "category":"Shopping",
            "subcategory":"Stationery & Office Supplies",
            "type":"Retail Goods"
        }
    ],
    "sg:phone":"+44 1922 632411",
    "sg:postcode":"WS1 1SY",
    "sg:province":"West Midlands",
    "wof:name":"Dartmouth Stationers (West Midlands) Ltd.",
    "wof:placetype":"venue"
},
  "geometry": {"coordinates":[-1.9775580168,52.5868911743],"type":"Point"}
}