{
  "type": "Feature",
  "properties": {
    "addr:full":"107 Cromwell Rd Manchester Greater Manchester M30 0RB",
    "addr:housenumber":"107",
    "addr:postcode":"m30 0rb",
    "addr:street":"Cromwell Rd",
    "iso:country":"GB",
    "sg:address":"107 Cromwell Rd",
    "sg:city":"Manchester",
    "sg:classifiers":[
        {
            "category":"Building & Trades",
            "subcategory":"Plumbing",
            "type":"Services"
        }
    ],
    "sg:phone":"+44 161 789 5315",
    "sg:postcode":"M30 0RB",
    "sg:province":"Greater Manchester",
    "sg:tags":[
        "central",
        "heating"
    ],
    "wof:name":"BKJ Heating Services",
    "wof:placetype":"venue"
},
  "geometry": {"coordinates":[-2.3540940285,53.484046936],"type":"Point"}
}