{
  "type": "Feature",
  "properties": {
    "addr:full":"207 Shields Road Newcastle-upon-tyne Tyne and Wear NE6 1DG",
    "addr:housenumber":"207",
    "addr:postcode":"ne6 1dg",
    "addr:street":"Shields Road",
    "iso:country":"GB",
    "sg:address":"207 Shields Road",
    "sg:city":"Newcastle-upon-tyne",
    "sg:classifiers":[
        {
            "category":"Retail",
            "subcategory":"Photofinishing",
            "type":"Services"
        }
    ],
    "sg:phone":"+44 191 276 3605",
    "sg:postcode":"NE6 1DG",
    "sg:province":"Tyne and Wear",
    "sg:tags":[
        "photographic",
        "processor"
    ],
    "wof:name":"Klick Photopoint",
    "wof:placetype":"venue"
},
  "geometry": {"coordinates":[-1.577863,54.977749],"type":"Point"}
}