{
  "type": "Feature",
  "properties": {
    "addr:full":"The Forge York North Yorkshire YO1 4SH",
    "addr:postcode":"yo1 4sh",
    "iso:country":"GB",
    "sg:address":"The Forge",
    "sg:city":"York",
    "sg:classifiers":[
        {
            "category":"Home & Garden",
            "subcategory":"Furniture",
            "type":"Retail Goods"
        }
    ],
    "sg:phone":"+44 1904 820626",
    "sg:postcode":"YO1 4SH",
    "sg:province":"North Yorkshire",
    "wof:name":"Original Bedrooms",
    "wof:placetype":"venue"
},
  "geometry": {"coordinates":[-1.08135,53.958771],"type":"Point"}
}