{
  "type": "Feature",
  "properties": {
    "addr:full":"425 Rocky Lane, Great Barr Birmingham West Midlands B42 1NL",
    "addr:housenumber":"425",
    "addr:postcode":"b42 1nl",
    "addr:street":"Rocky Lane",
    "iso:country":"GB",
    "sg:address":"425 Rocky Lane, Great Barr",
    "sg:city":"Birmingham",
    "sg:classifiers":[
        {
            "category":"Home & Garden",
            "subcategory":"Hardware",
            "type":"Retail Goods"
        }
    ],
    "sg:phone":"+44 121 358 4011",
    "sg:postcode":"B42 1NL",
    "sg:province":"West Midlands",
    "wof:name":"Second City Home & Garden",
    "wof:placetype":"venue"
},
  "geometry": {"coordinates":[-1.929146,52.53175],"type":"Point"}
}