{
  "type": "Feature",
  "properties": {
    "iso:country":"GB",
    "sg:address":"Dunchideock Barton Dunchideock",
    "sg:city":"Exeter",
    "sg:classifiers":[
        {
            "category":"Retail",
            "subcategory":"Auto Repair",
            "type":"Services"
        }
    ],
    "sg:postcode":"EX2 9TS",
    "sg:province":"Devon",
    "sg:tags":[
        "engine",
        "car",
        "specialist"
    ],
    "wof:name":"Crystal Engines",
    "wof:placetype":"venue"
},
  "geometry": {"coordinates":[-3.591664,50.677174],"type":"Point"}
}