{
  "type": "Feature",
  "properties": {
    "addr:full":"Bow House Business Centre, Bow Road London Greater London E3 2SE",
    "addr:postcode":"e3 2se",
    "addr:street":"Bow Road",
    "iso:country":"GB",
    "sg:address":"Bow House Business Centre, Bow Road",
    "sg:city":"London",
    "sg:classifiers":[
        {
            "category":"Professional",
            "subcategory":"Computer Services",
            "type":"Services"
        }
    ],
    "sg:phone":"+44 20 8875 2450",
    "sg:postcode":"E3 2SE",
    "sg:province":"Greater London",
    "sg:tags":[
        "system",
        "software"
    ],
    "wof:name":"Type Help",
    "wof:placetype":"venue"
},
  "geometry": {"coordinates":[-0.01987,51.5285110474],"type":"Point"}
}