{
  "type": "Feature",
  "properties": {
    "addr:full":"Millheugh Road Larkhall South Lanarkshire ML9 1QU",
    "addr:postcode":"ml9 1qu",
    "addr:street":"Millheugh Road",
    "iso:country":"GB",
    "sg:address":"Millheugh Road",
    "sg:city":"Larkhall",
    "sg:classifiers":[
        {
            "category":"Health Services",
            "subcategory":"Nursing And Care Facility",
            "type":"Services"
        }
    ],
    "sg:phone":"+44 1698 885140",
    "sg:postcode":"ML9 1QU",
    "sg:province":"South Lanarkshire",
    "sg:tags":[
        "home"
    ],
    "wof:name":"Brae House Nursing Home",
    "wof:placetype":"venue"
},
  "geometry": {"coordinates":[-3.973058939,55.7384796143],"type":"Point"}
}