{
  "type": "Feature",
  "properties": {
    "addr:full":"71a Woodhouse Hill, Fartown Huddersfield West Yorkshire HD2 1DH",
    "addr:housenumber":"71a",
    "addr:postcode":"hd2 1dh",
    "addr:street":"Woodhouse Hill Fartown",
    "iso:country":"GB",
    "sg:address":"71a Woodhouse Hill, Fartown",
    "sg:city":"Huddersfield",
    "sg:classifiers":[
        {
            "category":"Health Services",
            "subcategory":"Doctor",
            "type":"Services"
        }
    ],
    "sg:phone":"+44 1484 533833",
    "sg:postcode":"HD2 1DH",
    "sg:province":"West Yorkshire",
    "sg:tags":[
        "practitioners"
    ],
    "wof:name":"P K Das Surgery",
    "wof:placetype":"venue"
},
  "geometry": {"coordinates":[-1.771204,53.667068],"type":"Point"}
}