{
  "type": "Feature",
  "properties": {
    "iso:country":"GB",
    "sg:address":"Unit 6 Stonecross Business, Centre Laughton",
    "sg:city":"Lewes",
    "sg:classifiers":[
        {
            "category":"Shopping",
            "type":"Retail Goods"
        }
    ],
    "sg:postcode":"BN8 6BN",
    "sg:province":"East Sussex",
    "sg:tags":[
        "med",
        "scientific",
        "apparatus"
    ],
    "wof:name":"Uhv Design Ltd.",
    "wof:placetype":"venue"
},
  "geometry": {"coordinates":[0.13454,50.898365],"type":"Point"}
}