{
  "type": "Feature",
  "properties": {
    "iso:country":"GB",
    "sg:address":"11-13 George Street",
    "sg:city":"Montrose",
    "sg:classifiers":[
        {
            "category":"Personal",
            "subcategory":"Beauty Salon",
            "type":"Services"
        },
        {
            "category":"Personal",
            "subcategory":"Barber",
            "type":"Services"
        }
    ],
    "sg:phone":"+44 1674 677137",
    "sg:postcode":"DD10 8EN",
    "sg:province":"Aberdeenshire",
    "sg:tags":[
        "unisex",
        "hairdresser"
    ],
    "wof:name":"Head First Hair Design",
    "wof:placetype":"venue"
},
  "geometry": {"coordinates":[-2.467522,56.709652],"type":"Point"}
}