{
  "type": "Feature",
  "properties": {
    "addr:full":"3 Heathfield Way, Dallington Industrial Estate Northampton Northamptonshire NN5 7QP",
    "addr:housenumber":"3",
    "addr:postcode":"nn5 7qp",
    "addr:street":"Heathfield Way;Industrial Estate",
    "iso:country":"GB",
    "sg:address":"3 Heathfield Way, Dallington Industrial Estate",
    "sg:city":"Northampton",
    "sg:classifiers":[
        {
            "category":"Retail",
            "subcategory":"Auto Repair",
            "type":"Services"
        }
    ],
    "sg:phone":"+44 1604 587557",
    "sg:postcode":"NN5 7QP",
    "sg:province":"Northamptonshire",
    "sg:tags":[
        "modification",
        "garage"
    ],
    "wof:name":"3 Ways Garage",
    "wof:placetype":"venue"
},
  "geometry": {"coordinates":[-0.9124299884,52.2540206909],"type":"Point"}
}