{
  "type": "Feature",
  "properties": {
    "addr:full":"10 Wisteria Way Gloucester Gloucestershire GL3 1LQ",
    "addr:housenumber":"10",
    "addr:postcode":"gl3 1lq",
    "addr:street":"Wisteria Way",
    "iso:country":"GB",
    "sg:address":"10 Wisteria Way",
    "sg:city":"Gloucester",
    "sg:classifiers":[
        {
            "category":"Building & Trades",
            "subcategory":"Plumbing",
            "type":"Services"
        }
    ],
    "sg:postcode":"GL3 1LQ",
    "sg:province":"Gloucestershire",
    "sg:tags":[
        "heating"
    ],
    "wof:name":"Wakefield,Andy,",
    "wof:placetype":"venue"
},
  "geometry": {"coordinates":[-2.1897408962,51.8872413635],"type":"Point"}
}