{
  "type": "Feature",
  "properties": {
    "iso:country":"GB",
    "sg:address":"26 Gravel Walk",
    "sg:city":"Faringdon",
    "sg:classifiers":[
        {
            "category":"Manufacturing",
            "subcategory":"Jewelry",
            "type":"Manufacturing & Wholesale Goods"
        }
    ],
    "sg:phone":"+44 1367 241687",
    "sg:postcode":"SN7 7JW",
    "sg:province":"Oxfordshire",
    "sg:tags":[
        "repair",
        "jewellery"
    ],
    "wof:name":"Christopher J Coles",
    "wof:placetype":"venue"
},
  "geometry": {"coordinates":[-1.587879,51.657429],"type":"Point"}
}