{
  "type": "Feature",
  "properties": {
    "iso:country":"GB",
    "sg:address":"102 High Street",
    "sg:city":"Braintree",
    "sg:classifiers":[
        {
            "category":"Restaurant",
            "type":"Food & Drink"
        }
    ],
    "sg:phone":"+44 1376 327497",
    "sg:postcode":"CM7 1JP",
    "sg:province":"Essex",
    "sg:tags":[
        "indian"
    ],
    "wof:name":"Sunderban Tandoori Restaurant",
    "wof:placetype":"venue"
},
  "geometry": {"coordinates":[0.549486,51.877892],"type":"Point"}
}