{
  "type": "Feature",
  "properties": {
    "iso:country":"GB",
    "sg:address":"28 Cheriton Gro, Tonteg",
    "sg:city":"Pontypridd",
    "sg:classifiers":[
        {
            "category":"Building & Trades",
            "subcategory":"Construction",
            "type":"Services"
        }
    ],
    "sg:postcode":"CF38 1PF",
    "sg:province":"Rhondda, Cynon, Taff",
    "sg:tags":[
        "builder"
    ],
    "wof:name":"Andrew D Denton Builders",
    "wof:placetype":"venue"
},
  "geometry": {"coordinates":[-3.3071238995,51.5699462891],"type":"Point"}
}