{
  "type": "Feature",
  "properties": {
    "iso:country":"GB",
    "sg:address":"229 Boardwalk Place",
    "sg:city":"London",
    "sg:classifiers":[
        {
            "category":"Professional",
            "subcategory":"Computer Services",
            "type":"Services"
        }
    ],
    "sg:phone":"+44 20 7536 3828",
    "sg:postcode":"E14 5SQ",
    "sg:province":"Greater London",
    "sg:tags":[
        "development",
        "system",
        "software"
    ],
    "wof:name":"GEORDIE BAY OPERATIONS LTD",
    "wof:placetype":"venue"
},
  "geometry": {"coordinates":[-0.0104219997,51.5054779053],"type":"Point"}
}