{
  "type": "Feature",
  "properties": {
    "iso:country":"GB",
    "sg:address":"83-85 High Street, Great Wakering",
    "sg:city":"Southend-on-sea",
    "sg:classifiers":[
        {
            "category":"Cinema",
            "subcategory":"Movie Rental",
            "type":"Entertainment"
        }
    ],
    "sg:phone":"+44 1702 218624",
    "sg:postcode":"SS3 0ED",
    "sg:province":"Essex",
    "sg:tags":[
        "video",
        "library"
    ],
    "wof:name":"M & G Home Video",
    "wof:placetype":"venue"
},
  "geometry": {"coordinates":[0.804534018,51.5526924133],"type":"Point"}
}