{
  "type": "Feature",
  "properties": {
    "addr:full":"Lumb Farm, Park Lane, Cowling Keighley North Yorkshire BD22 0NL",
    "addr:postcode":"bd22 0nl",
    "addr:street":"Park Lane",
    "iso:country":"GB",
    "sg:address":"Lumb Farm, Park Lane, Cowling",
    "sg:city":"Keighley",
    "sg:classifiers":[
        {
            "category":"Farming",
            "subcategory":"Livestock Farm",
            "type":"Manufacturing & Wholesale Goods"
        }
    ],
    "sg:phone":"+44 1535 632635",
    "sg:postcode":"BD22 0NL",
    "sg:province":"North Yorkshire",
    "sg:tags":[
        "others"
    ],
    "wof:name":"T A & S Harrison",
    "wof:placetype":"venue"
},
  "geometry": {"coordinates":[-2.0646340847,53.880355835],"type":"Point"}
}