{
  "type": "Feature",
  "properties": {
    "addr:full":"48-50 Blackmore Road, Kelvedon Hatch Brentwood Essex CM15 0AZ",
    "addr:housenumber":"48-50",
    "addr:postcode":"cm15 0az",
    "addr:street":"Blackmore Road",
    "iso:country":"GB",
    "sg:address":"48-50 Blackmore Road, Kelvedon Hatch",
    "sg:city":"Brentwood",
    "sg:classifiers":[
        {
            "category":"Food & Beverages",
            "subcategory":"Supermarket",
            "type":"Retail Goods"
        }
    ],
    "sg:phone":"+44 1277 373833",
    "sg:postcode":"CM15 0AZ",
    "sg:province":"Essex",
    "wof:name":"Costcutters",
    "wof:placetype":"venue"
},
  "geometry": {"coordinates":[0.2922,51.673119],"type":"Point"}
}