{
  "type": "Feature",
  "properties": {
    "addr:full":"9 West Orchard Shaftesbury Dorset SP7 0LJ",
    "addr:housenumber":"9",
    "addr:postcode":"sp7 0lj",
    "addr:street":"West Orchard",
    "iso:country":"GB",
    "sg:address":"9 West Orchard",
    "sg:city":"Shaftesbury",
    "sg:classifiers":[
        {
            "category":"Military Area",
            "subcategory":"Air Force Base",
            "type":"Public Place"
        }
    ],
    "sg:phone":"+44 1258 472395",
    "sg:postcode":"SP7 0LJ",
    "sg:province":"Dorset",
    "sg:tags":[
        "taxi",
        "hire",
        "private"
    ],
    "wof:name":"Orchard Cars",
    "wof:placetype":"venue"
},
  "geometry": {"coordinates":[-2.1897230148,50.9792785645],"type":"Point"}
}