{
  "type": "Feature",
  "properties": {
    "addr:full":"8 Hewell Rd Birmingham West Midlands B45 8NE",
    "addr:housenumber":"8",
    "addr:postcode":"b45 8ne",
    "addr:street":"Hewell Rd",
    "iso:country":"GB",
    "sg:address":"8 Hewell Rd",
    "sg:city":"Birmingham",
    "sg:classifiers":[
        {
            "category":"Insurance",
            "subcategory":"Insurance Agent",
            "type":"Services"
        }
    ],
    "sg:phone":"+44 121 445 3875",
    "sg:postcode":"B45 8NE",
    "sg:province":"West Midlands",
    "wof:name":"Time To Insure",
    "wof:placetype":"venue"
},
  "geometry": {"coordinates":[-1.990398,52.361568],"type":"Point"}
}