{
  "type": "Feature",
  "properties": {
    "iso:country":"GB",
    "sg:address":"Farm Road, Taplow",
    "sg:city":"Maidenhead",
    "sg:classifiers":[
        {
            "category":"Farming",
            "subcategory":"Livestock Farm",
            "type":"Manufacturing & Wholesale Goods"
        }
    ],
    "sg:phone":"+44 1628 602003",
    "sg:postcode":"SL6 0PT",
    "sg:province":"Berkshire",
    "sg:tags":[
        "others"
    ],
    "wof:name":"West Town Farm",
    "wof:placetype":"venue"
},
  "geometry": {"coordinates":[-0.687149,51.532169],"type":"Point"}
}