{
  "type": "Feature",
  "properties": {
    "addr:full":"6 Penn Street Bristol City of Bristol BS1 3AN",
    "addr:housenumber":"6",
    "addr:postcode":"bs1 3an",
    "addr:street":"Penn Street",
    "iso:country":"GB",
    "sg:address":"6 Penn Street",
    "sg:city":"Bristol",
    "sg:classifiers":[
        {
            "category":"Personal",
            "subcategory":"Tattoo Parlor",
            "type":"Services"
        }
    ],
    "sg:phone":"+44 117 926 8323",
    "sg:postcode":"BS1 3AN",
    "sg:province":"City of Bristol",
    "sg:tags":[
        "razor",
        "blade"
    ],
    "wof:name":"Remington Shavers & Cutlery",
    "wof:placetype":"venue"
},
  "geometry": {"coordinates":[-2.585832119,51.4572639465],"type":"Point"}
}