{
  "type": "Feature",
  "properties": {
    "addr:full":"168b Fleet Road Fleet Hampshire GU51 4DA",
    "addr:housenumber":"168b",
    "addr:postcode":"gu51 4da",
    "addr:street":"Fleet Road",
    "iso:country":"GB",
    "sg:address":"168b Fleet Road",
    "sg:city":"Fleet",
    "sg:classifiers":[
        {
            "category":"Shopping",
            "subcategory":"Comic Books",
            "type":"Retail Goods"
        }
    ],
    "sg:phone":"+44 1252 811043",
    "sg:postcode":"GU51 4DA",
    "sg:province":"Hampshire",
    "sg:tags":[
        "jeweller"
    ],
    "wof:name":"Goldsmiths Ltd.",
    "wof:placetype":"venue"
},
  "geometry": {"coordinates":[-0.8425700068,51.2809867859],"type":"Point"}
}