{
  "type": "Feature",
  "properties": {
    "iso:country":"GB",
    "sg:address":"30 Devonport Road",
    "sg:city":"Plymouth",
    "sg:classifiers":[
        {
            "category":"Home & Garden",
            "subcategory":"Home Furnishings",
            "type":"Retail Goods"
        },
        {
            "category":"Home & Garden",
            "subcategory":"Kitchen Supply",
            "type":"Retail Goods"
        }
    ],
    "sg:phone":"+44 1752 551425",
    "sg:postcode":"PL3 4DH",
    "sg:province":"Devon",
    "sg:tags":[
        "equipment",
        "household",
        "china",
        "glassware",
        "catering"
    ],
    "wof:name":"Stoke Potteries",
    "wof:placetype":"venue"
},
  "geometry": {"coordinates":[-4.165426,50.381287],"type":"Point"}
}