{
  "type": "Feature",
  "properties": {
    "iso:country":"GB",
    "sg:address":"57 Alan Moss Road",
    "sg:city":"Loughborough",
    "sg:classifiers":[
        {
            "category":"Shopping",
            "subcategory":"Department Store",
            "type":"Retail Goods"
        }
    ],
    "sg:phone":"+44 1509 214419",
    "sg:postcode":"LE11 5LR",
    "sg:province":"Leicestershire",
    "wof:name":"Alan Moss Road Stores",
    "wof:placetype":"venue"
},
  "geometry": {"coordinates":[-1.2231110334,52.7757987976],"type":"Point"}
}