{
  "type": "Feature",
  "properties": {
    "addr:full":"P O Box 4529 Solihull West Midlands B90 4BP",
    "addr:housenumber":"p o;4529",
    "addr:postcode":"b90 4bp",
    "addr:street":"Solihull",
    "iso:country":"GB",
    "sg:address":"P O Box 4529",
    "sg:city":"Solihull",
    "sg:classifiers":[
        {
            "category":"Insurance",
            "subcategory":"Insurance Agent",
            "type":"Services"
        }
    ],
    "sg:phone":"+44 28 3832 2449",
    "sg:postcode":"B90 4BP",
    "sg:province":"West Midlands",
    "wof:name":"Wellinsured Direct",
    "wof:placetype":"venue"
},
  "geometry": {"coordinates":[-1.82037,52.377914],"type":"Point"}
}