{
  "type": "Feature",
  "properties": {
    "addr:full":"10 Pen-yr-heol, Broadlands Estate Bridgend Bridgend CF33 4EL",
    "addr:housenumber":"10",
    "addr:postcode":"cf33 4el",
    "addr:street":"Pen-Yr-Heol Broadlands Estate",
    "iso:country":"GB",
    "sg:address":"10 Pen-yr-heol, Broadlands Estate",
    "sg:city":"Bridgend",
    "sg:classifiers":[
        {
            "category":"Taxi",
            "type":"Transportation"
        },
        {
            "category":"Military Area",
            "subcategory":"Air Force Base",
            "type":"Public Place"
        }
    ],
    "sg:phone":"+44 1656 744136",
    "sg:postcode":"CF33 4EL",
    "sg:province":"Bridgend",
    "sg:tags":[
        "hire",
        "private"
    ],
    "wof:name":"Kenfig Cars",
    "wof:placetype":"venue"
},
  "geometry": {"coordinates":[-3.6981389523,51.5177612305],"type":"Point"}
}