{
  "type": "Feature",
  "properties": {
    "addr:full":"48 North Bridge Street Sunderland Tyne and Wear SR5 1AH",
    "addr:housenumber":"48",
    "addr:postcode":"sr5 1ah",
    "addr:street":"North Bridge Street",
    "iso:country":"GB",
    "sg:address":"48 North Bridge Street",
    "sg:city":"Sunderland",
    "sg:classifiers":[
        {
            "category":"Sports & Exercise",
            "subcategory":"Sports Center",
            "type":"Entertainment"
        }
    ],
    "sg:phone":"+44 191 514 7175",
    "sg:postcode":"SR5 1AH",
    "sg:province":"Tyne and Wear",
    "sg:tags":[
        "shop",
        "good"
    ],
    "wof:name":"Sun & Health Systems",
    "wof:placetype":"venue"
},
  "geometry": {"coordinates":[-1.38309,54.913864],"type":"Point"}
}