{
  "type": "Feature",
  "properties": {
    "addr:full":"Browns Lane, Allesley Coventry West Midlands CV5 9DR",
    "addr:postcode":"cv5 9dr",
    "addr:street":"Browns Lane",
    "iso:country":"GB",
    "sg:address":"Browns Lane, Allesley",
    "sg:city":"Coventry",
    "sg:classifiers":[
        {
            "category":"Professional",
            "type":"Services"
        }
    ],
    "sg:phone":"+44 24 7640 5561",
    "sg:postcode":"CV5 9DR",
    "sg:province":"West Midlands",
    "sg:tags":[
        "car",
        "transportation"
    ],
    "wof:name":"Axial",
    "wof:placetype":"venue"
},
  "geometry": {"coordinates":[-1.56447,52.424362],"type":"Point"}
}