{
  "type": "Feature",
  "properties": {
    "addr:full":"4 Prestbury Road Cheltenham Gloucestershire GL52 2PW",
    "addr:housenumber":"4",
    "addr:postcode":"gl52 2pw",
    "addr:street":"Prestbury Road",
    "iso:country":"GB",
    "sg:address":"4 Prestbury Road",
    "sg:city":"Cheltenham",
    "sg:classifiers":[
        {
            "category":"Banks & Credit Unions",
            "subcategory":"Financial Services",
            "type":"Services"
        }
    ],
    "sg:phone":"+44 1242 228822",
    "sg:postcode":"GL52 2PW",
    "sg:province":"Gloucestershire",
    "sg:tags":[
        "consultant"
    ],
    "wof:name":"J F S Independent Financial Advisers",
    "wof:placetype":"venue"
},
  "geometry": {"coordinates":[-2.068499,51.904453],"type":"Point"}
}