{
  "type": "Feature",
  "properties": {
    "addr:full":"12 Hyde Park Road Plymouth Devon PL3 4RJ",
    "addr:housenumber":"12",
    "addr:postcode":"pl3 4rj",
    "addr:street":"Hyde Park Road",
    "iso:country":"GB",
    "sg:address":"12 Hyde Park Road",
    "sg:city":"Plymouth",
    "sg:classifiers":[
        {
            "category":"Health Services",
            "subcategory":"Dentist",
            "type":"Services"
        }
    ],
    "sg:phone":"+44 1752 660674",
    "sg:postcode":"PL3 4RJ",
    "sg:province":"Devon",
    "wof:name":"R A P Gilding",
    "wof:placetype":"venue"
},
  "geometry": {"coordinates":[-4.135389,50.384537],"type":"Point"}
}