{
  "type": "Feature",
  "properties": {
    "iso:country":"GB",
    "sg:address":"Oakley Road",
    "sg:city":"Corby",
    "sg:classifiers":[
        {
            "category":"Retail",
            "subcategory":"Auto Repair",
            "type":"Services"
        }
    ],
    "sg:phone":"+44 1536 443455",
    "sg:postcode":"NN18 9NP",
    "sg:province":"Northamptonshire",
    "sg:tags":[
        "body",
        "car"
    ],
    "wof:name":"Negis Autos",
    "wof:placetype":"venue"
},
  "geometry": {"coordinates":[-0.707152,52.478733],"type":"Point"}
}