{
  "type": "Feature",
  "properties": {
    "iso:country":"GB",
    "sg:address":"2 Mamhead Road, Kenton",
    "sg:city":"Exeter",
    "sg:classifiers":[
        {
            "category":"Education",
            "subcategory":"School",
            "type":"Public Place"
        }
    ],
    "sg:phone":"+44 1626 890465",
    "sg:postcode":"EX6 8EX",
    "sg:province":"Devon",
    "sg:tags":[
        "local",
        "authority"
    ],
    "wof:name":"Kenton Primary School",
    "wof:placetype":"venue"
},
  "geometry": {"coordinates":[-3.4752700329,50.638835907],"type":"Point"}
}