{
  "type": "Feature",
  "properties": {
    "iso:country":"GB",
    "sg:address":"21 Frederick St, Hockley",
    "sg:city":"Birmingham",
    "sg:classifiers":[
        {
            "category":"Building & Trades",
            "subcategory":"Construction",
            "type":"Services"
        }
    ],
    "sg:phone":"+44 121 233 4464",
    "sg:postcode":"B1 3HE",
    "sg:province":"West Midlands",
    "sg:tags":[
        "heating",
        "contractor"
    ],
    "wof:name":"Burton Building Services Ltd",
    "wof:placetype":"venue"
},
  "geometry": {"coordinates":[-1.911814,52.485638],"type":"Point"}
}