{
  "type": "Feature",
  "properties": {
    "iso:country":"GB",
    "sg:address":"Balcletchie Farm",
    "sg:city":"Girvan",
    "sg:classifiers":[
        {
            "category":"Farming",
            "subcategory":"Livestock Farm",
            "type":"Manufacturing & Wholesale Goods"
        }
    ],
    "sg:phone":"+44 1465 861242",
    "sg:postcode":"KA26 9TH",
    "sg:province":"South Ayrshire",
    "sg:tags":[
        "others"
    ],
    "wof:name":"Firm of Tormitchell Farms",
    "wof:placetype":"venue"
},
  "geometry": {"coordinates":[-4.782769,55.26059],"type":"Point"}
}