{
  "type": "Feature",
  "properties": {
    "addr:full":"Post Office Buildings, Station Road, Albrighton Wolverhampton Shropshire WV7 3QH",
    "addr:postcode":"wv7 3qh",
    "addr:street":"Station Road",
    "iso:country":"GB",
    "sg:address":"Post Office Buildings, Station Road, Albrighton",
    "sg:city":"Wolverhampton",
    "sg:classifiers":[
        {
            "category":"Professional",
            "subcategory":"Lawyer & Legal Services",
            "type":"Services"
        }
    ],
    "sg:phone":"+44 1902 373000",
    "sg:postcode":"WV7 3QH",
    "sg:province":"Shropshire",
    "sg:tags":[
        "solicitor"
    ],
    "wof:name":"Geoffrey Milne",
    "wof:placetype":"venue"
},
  "geometry": {"coordinates":[-2.2715620995,52.6394767761],"type":"Point"}
}