{
  "type": "Feature",
  "properties": {
    "iso:country":"GB",
    "sg:address":"2 Market Place",
    "sg:city":"Loughborough",
    "sg:classifiers":[
        {
            "category":"Shopping",
            "subcategory":"Pharmacy",
            "type":"Retail Goods"
        }
    ],
    "sg:phone":"+44 1509 234476",
    "sg:postcode":"LE11 3EA",
    "sg:province":"Leicestershire",
    "sg:tags":[
        "dispensing",
        "store",
        "drug",
        "chemist"
    ],
    "sg:website":"http://www.superdrug.com",
    "wof:name":"Superdrug Stores",
    "wof:placetype":"venue"
},
  "geometry": {"coordinates":[-1.206945,52.77124],"type":"Point"}
}