{
  "type": "Feature",
  "properties": {
    "iso:country":"GB",
    "sg:address":"18 Benfleet Rd, Hadleigh",
    "sg:city":"Benfleet",
    "sg:classifiers":[
        {
            "category":"Retail",
            "subcategory":"Repair Shop",
            "type":"Services"
        }
    ],
    "sg:phone":"+44 1702 558444",
    "sg:postcode":"SS7 1QB",
    "sg:province":"Essex",
    "sg:tags":[
        "radio",
        "television",
        "video"
    ],
    "wof:name":"Service T.V",
    "wof:placetype":"venue"
},
  "geometry": {"coordinates":[0.59935,51.556725],"type":"Point"}
}