{
  "type": "Feature",
  "properties": {
    "addr:full":"29 Camden Road Sutton Surrey SM1 2SH",
    "addr:housenumber":"29",
    "addr:postcode":"sm1 2sh",
    "addr:street":"Camden Road",
    "iso:country":"GB",
    "sg:address":"29 Camden Road",
    "sg:city":"Sutton",
    "sg:classifiers":[
        {
            "category":"Taxi",
            "type":"Transportation"
        },
        {
            "category":"Military Area",
            "subcategory":"Air Force Base",
            "type":"Public Place"
        }
    ],
    "sg:phone":"+44 20 8715 1010",
    "sg:postcode":"SM1 2SH",
    "sg:province":"Surrey",
    "sg:tags":[
        "mini",
        "hire",
        "private",
        "cab"
    ],
    "wof:name":"Diamond Cars",
    "wof:placetype":"venue"
},
  "geometry": {"coordinates":[-0.1988279969,51.3626594543],"type":"Point"}
}