{
  "type": "Feature",
  "properties": {
    "iso:country":"GB",
    "sg:address":"Basin Rd South",
    "sg:city":"Brighton",
    "sg:classifiers":[
        {
            "category":"Building & Trades",
            "subcategory":"Construction",
            "type":"Services"
        }
    ],
    "sg:phone":"+44 1273 439651",
    "sg:postcode":"BN41 1WF",
    "sg:province":"East Sussex",
    "sg:tags":[
        "joiner",
        "carpenter"
    ],
    "wof:name":"Ace Joinery",
    "wof:placetype":"venue"
},
  "geometry": {"coordinates":[-0.2126699984,50.8301048279],"type":"Point"}
}