{
  "type": "Feature",
  "properties": {
    "addr:full":"Newington House, Newington Wallingford Oxfordshire OX10 7AG",
    "addr:postcode":"ox10 7ag",
    "addr:street":"Newington",
    "iso:country":"GB",
    "sg:address":"Newington House, Newington",
    "sg:city":"Wallingford",
    "sg:classifiers":[
        {
            "category":"Shopping",
            "subcategory":"Department Store",
            "type":"Retail Goods"
        }
    ],
    "sg:postcode":"OX10 7AG",
    "sg:province":"Oxfordshire",
    "wof:name":"Lilycell Ltd",
    "wof:placetype":"venue"
},
  "geometry": {"coordinates":[-1.1205790043,51.6664962769],"type":"Point"}
}