{
  "type": "Feature",
  "properties": {
    "iso:country":"GB",
    "sg:address":"36 Birmingham Rd",
    "sg:city":"Bromsgrove",
    "sg:classifiers":[
        {
            "category":"Shopping",
            "subcategory":"Pharmacy",
            "type":"Retail Goods"
        }
    ],
    "sg:postcode":"B61 0DD",
    "sg:province":"Worcestershire",
    "sg:tags":[
        "store",
        "drug"
    ],
    "wof:name":"Patel & N, Sodha K K,",
    "wof:placetype":"venue"
},
  "geometry": {"coordinates":[-2.064064,52.379505],"type":"Point"}
}