{
  "type": "Feature",
  "properties": {
    "addr:full":"36 Birmingham Rd Bromsgrove Worcestershire B61 0DD",
    "addr:housenumber":"36",
    "addr:postcode":"b61 0dd",
    "addr:street":"Birmingham Rd",
    "iso:country":"GB",
    "sg:address":"36 Birmingham Rd",
    "sg:city":"Bromsgrove",
    "sg:classifiers":[
        {
            "category":"Shopping",
            "subcategory":"Pharmacy",
            "type":"Retail Goods"
        }
    ],
    "sg:postcode":"B61 0DD",
    "sg:province":"Worcestershire",
    "sg:tags":[
        "store",
        "drug"
    ],
    "wof:name":"Patel & N, Sodha K K,",
    "wof:placetype":"venue"
},
  "geometry": {"coordinates":[-2.064064,52.379505],"type":"Point"}
}