{
  "type": "Feature",
  "properties": {
    "addr:full":"Mart Road Minehead Somerset TA24 5BJ",
    "addr:postcode":"ta24 5bj",
    "addr:street":"Mart Road",
    "iso:country":"GB",
    "sg:address":"Mart Road",
    "sg:city":"Minehead",
    "sg:classifiers":[
        {
            "category":"Shopping",
            "subcategory":"Discount & Variety Stores",
            "type":"Retail Goods"
        }
    ],
    "sg:phone":"+44 1643 705911",
    "sg:postcode":"TA24 5BJ",
    "sg:province":"Somerset",
    "sg:tags":[
        "centre"
    ],
    "wof:name":"The Original Factory Shop",
    "wof:placetype":"venue"
},
  "geometry": {"coordinates":[-3.469327,51.205158],"type":"Point"}
}