{
  "type": "Feature",
  "properties": {
    "addr:full":"28 Taylors Lane, St. Marys Bay Romney Marsh Kent TN29 0HB",
    "addr:housenumber":"28",
    "addr:postcode":"tn29 0hb",
    "addr:street":"Taylors Lane",
    "iso:country":"GB",
    "sg:address":"28 Taylors Lane, St. Marys Bay",
    "sg:city":"Romney Marsh",
    "sg:classifiers":[
        {
            "category":"Utilities",
            "subcategory":"Fuel Oil & Lpg",
            "type":"Services"
        }
    ],
    "sg:phone":"+44 1797 363034",
    "sg:postcode":"TN29 0HB",
    "sg:province":"Kent",
    "wof:name":"Hewlett Coal Merchant",
    "wof:placetype":"venue"
},
  "geometry": {"coordinates":[0.9713860154,51.0061569214],"type":"Point"}
}