{
  "type": "Feature",
  "properties": {
    "iso:country":"GB",
    "sg:address":"Horsley House, Leziate Drove Pott Row",
    "sg:city":"King's Lynn",
    "sg:classifiers":[
        {
            "category":"Train Station",
            "subcategory":"Rail",
            "type":"Transportation"
        }
    ],
    "sg:postcode":"PE32 1DB",
    "sg:province":"Norfolk",
    "sg:tags":[
        "caravan"
    ],
    "wof:name":"Bill Burgess Trailers",
    "wof:placetype":"venue"
},
  "geometry": {"coordinates":[0.5261899829,52.765171051],"type":"Point"}
}