{
  "type": "Feature",
  "properties": {
    "addr:full":"Exeter Road Braunton Devon EX33 2JL",
    "addr:postcode":"ex33 2jl",
    "addr:street":"Exeter Road",
    "iso:country":"GB",
    "sg:address":"Exeter Road",
    "sg:city":"Braunton",
    "sg:classifiers":[
        {
            "category":"Shopping",
            "subcategory":"Shoes",
            "type":"Retail Goods"
        }
    ],
    "sg:phone":"+44 1271 816571",
    "sg:postcode":"EX33 2JL",
    "sg:province":"Devon",
    "sg:tags":[
        "shop",
        "retailer",
        "footwear"
    ],
    "wof:name":"Two Ways Footwear",
    "wof:placetype":"venue"
},
  "geometry": {"coordinates":[-4.1612391472,51.1082763672],"type":"Point"}
}