{
  "type": "Feature",
  "properties": {
    "addr:full":"Wharfebank Business Centre, Ilkley Rd Otley North Yorkshire LS21 3JP",
    "addr:postcode":"ls21 3jp",
    "addr:street":"Ilkley Rd",
    "iso:country":"GB",
    "sg:address":"Wharfebank Business Centre, Ilkley Rd",
    "sg:city":"Otley",
    "sg:classifiers":[
        {
            "category":"Communications",
            "subcategory":"Newspaper",
            "type":"Services"
        }
    ],
    "sg:phone":"+44 1943 850860",
    "sg:postcode":"LS21 3JP",
    "sg:province":"North Yorkshire",
    "sg:tags":[
        "magazine"
    ],
    "wof:name":"U.F.O Magazine",
    "wof:placetype":"venue"
},
  "geometry": {"coordinates":[-1.705636,53.902916],"type":"Point"}
}