{
  "type": "Feature",
  "properties": {
    "addr:full":"Enterprise House, Meadow Drive, Hampton-in-arden Solihull West Midlands B92 0BD",
    "addr:postcode":"b92 0bd",
    "addr:street":"Meadow Drive",
    "iso:country":"GB",
    "sg:address":"Enterprise House, Meadow Drive, Hampton-in-arden",
    "sg:city":"Solihull",
    "sg:classifiers":[
        {
            "category":"Sports & Exercise",
            "subcategory":"Athletic Track",
            "type":"Entertainment"
        }
    ],
    "sg:phone":"+44 1675 443331",
    "sg:postcode":"B92 0BD",
    "sg:province":"West Midlands",
    "sg:tags":[
        "gauge",
        "maker"
    ],
    "wof:name":"Movomatic (U K) Ltd.",
    "wof:placetype":"venue"
},
  "geometry": {"coordinates":[-1.700071,52.426628],"type":"Point"}
}