{
  "type": "Feature",
  "properties": {
    "addr:full":"3 Holborn Bar London Greater London EC1N 2LL",
    "addr:housenumber":"3",
    "addr:postcode":"ec1n 2ll",
    "addr:street":"Holborn Bar",
    "iso:country":"GB",
    "sg:address":"3 Holborn Bar",
    "sg:city":"London",
    "sg:classifiers":[
        {
            "category":"Shopping",
            "subcategory":"Comic Books",
            "type":"Retail Goods"
        }
    ],
    "sg:phone":"+44 20 7405 2352",
    "sg:postcode":"EC1N 2LL",
    "sg:province":"Greater London",
    "sg:tags":[
        "jeweller"
    ],
    "wof:name":"Sanford Bros Ltd.",
    "wof:placetype":"venue"
},
  "geometry": {"coordinates":[-0.111006,51.518017],"type":"Point"}
}