{
  "type": "Feature",
  "properties": {
    "addr:full":"Pentax House Harrow Greater London HA2 0DU",
    "addr:postcode":"ha2 0du",
    "iso:country":"GB",
    "sg:address":"Pentax House",
    "sg:city":"Harrow",
    "sg:classifiers":[
        {
            "category":"Building & Trades",
            "subcategory":"Construction",
            "type":"Services"
        }
    ],
    "sg:phone":"+44 20 8938 4710",
    "sg:postcode":"HA2 0DU",
    "sg:province":"Greater London",
    "sg:tags":[
        "roofing"
    ],
    "wof:name":"A J L Roofing Contractors",
    "wof:placetype":"venue"
},
  "geometry": {"coordinates":[-0.35188,51.564629],"type":"Point"}
}