{
  "type": "Feature",
  "properties": {
    "iso:country":"GB",
    "sg:address":"Curds Road, Earls Colne",
    "sg:city":"Colchester",
    "sg:classifiers":[
        {
            "category":"Building & Trades",
            "subcategory":"Landscaping Services",
            "type":"Services"
        }
    ],
    "sg:phone":"+44 1787 223148",
    "sg:postcode":"CO6 2JT",
    "sg:province":"Essex",
    "sg:tags":[
        "forestry",
        "tree"
    ],
    "wof:name":"J F & D J Whiting",
    "wof:placetype":"venue"
},
  "geometry": {"coordinates":[0.699067,51.927967],"type":"Point"}
}