{
  "type": "Feature",
  "properties": {
    "iso:country":"GB",
    "sg:address":"10 Gillity Avenue",
    "sg:city":"Walsall",
    "sg:classifiers":[
        {
            "category":"Shopping",
            "subcategory":"News",
            "type":"Retail Goods"
        }
    ],
    "sg:postcode":"WS5 3PH",
    "sg:province":"West Midlands",
    "sg:tags":[
        "newsagent"
    ],
    "wof:name":"Stars News Shops",
    "wof:placetype":"venue"
},
  "geometry": {"coordinates":[-1.959819,52.577335],"type":"Point"}
}