{
  "type": "Feature",
  "properties": {
    "addr:full":"5 Brookhus Farm Rd Sutton Coldfield Warwickshire B76 1QP",
    "addr:housenumber":"5",
    "addr:postcode":"b76 1qp",
    "addr:street":"Brookhus Farm Rd",
    "iso:country":"GB",
    "sg:address":"5 Brookhus Farm Rd",
    "sg:city":"Sutton Coldfield",
    "sg:classifiers":[
        {
            "category":"Professional",
            "subcategory":"Computer Services",
            "type":"Services"
        }
    ],
    "sg:phone":"+44 121 313 1619",
    "sg:postcode":"B76 1QP",
    "sg:province":"Warwickshire",
    "sg:tags":[
        "system",
        "software"
    ],
    "wof:name":"Tecnocad",
    "wof:placetype":"venue"
},
  "geometry": {"coordinates":[-1.7909770012,52.5394058228],"type":"Point"}
}