{
  "type": "Feature",
  "properties": {
    "addr:full":"3 Kings Road Stamford Cambridgeshire PE9 1HD",
    "addr:housenumber":"3",
    "addr:postcode":"pe9 1hd",
    "addr:street":"Kings Road",
    "iso:country":"GB",
    "sg:address":"3 Kings Road",
    "sg:city":"Stamford",
    "sg:classifiers":[
        {
            "category":"Education",
            "subcategory":"Music School",
            "type":"Public Place"
        }
    ],
    "sg:postcode":"PE9 1HD",
    "sg:province":"Cambridgeshire",
    "wof:name":"Robina E Hill",
    "wof:placetype":"venue"
},
  "geometry": {"coordinates":[-0.479759,52.657814],"type":"Point"}
}