{
  "type": "Feature",
  "properties": {
    "addr:full":"1-2 Chapel Lane Pinner Greater London HA5 1AA",
    "addr:housenumber":"1-2",
    "addr:postcode":"ha5 1aa",
    "addr:street":"Chapel Lane",
    "iso:country":"GB",
    "sg:address":"1-2 Chapel Lane",
    "sg:city":"Pinner",
    "sg:classifiers":[
        {
            "category":"Community Center",
            "subcategory":"Youth",
            "type":"Public Place"
        },
        {
            "category":"Government",
            "subcategory":"Office",
            "type":"Public Place"
        }
    ],
    "sg:phone":"+44 20 8868 8865",
    "sg:postcode":"HA5 1AA",
    "sg:province":"Greater London",
    "sg:tags":[
        "organisation",
        "local",
        "centre"
    ],
    "wof:name":"Pinner Youth & Community Centre",
    "wof:placetype":"venue"
},
  "geometry": {"coordinates":[-0.385164,51.593704],"type":"Point"}
}