{
  "type": "Feature",
  "properties": {
    "addr:full":"6 Larch Clo Wellingborough Bedfordshire NN29 7HQ",
    "addr:housenumber":"6",
    "addr:postcode":"nn29 7hq",
    "addr:street":"Larch Clo",
    "iso:country":"GB",
    "sg:address":"6 Larch Clo",
    "sg:city":"Wellingborough",
    "sg:classifiers":[
        {
            "category":"Wholesale",
            "subcategory":"Chemicals & Plastics",
            "type":"Manufacturing & Wholesale Goods"
        }
    ],
    "sg:phone":"+44 1933 411711",
    "sg:postcode":"NN29 7HQ",
    "sg:province":"Bedfordshire",
    "sg:tags":[
        "ind"
    ],
    "wof:name":"P J Scrase",
    "wof:placetype":"venue"
},
  "geometry": {"coordinates":[-0.6525939703,52.27734375],"type":"Point"}
}