{
  "type": "Feature",
  "properties": {
    "iso:country":"GB",
    "sg:address":"Lings House, Billing Lings",
    "sg:city":"Northampton",
    "sg:classifiers":[
        {
            "category":"Professional",
            "subcategory":"Management & Consulting",
            "type":"Services"
        },
        {
            "category":"Organizations",
            "subcategory":"Community Association",
            "type":"Services"
        }
    ],
    "sg:phone":"+44 1604 405285",
    "sg:postcode":"NN3 8BE",
    "sg:province":"Northamptonshire",
    "sg:tags":[
        "organisation",
        "conservation"
    ],
    "wof:name":"Wildlife Trust For Bedfordshire Cambridgeshire N",
    "wof:placetype":"venue"
},
  "geometry": {"coordinates":[-0.8423389792,52.2731018066],"type":"Point"}
}