{
  "type": "Feature",
  "properties": {
    "iso:country":"GB",
    "sg:address":"Albany Court, Newcastle Business Park",
    "sg:city":"Newcastle-upon-tyne",
    "sg:classifiers":[
        {
            "category":"Professional",
            "subcategory":"Engineering",
            "type":"Services"
        }
    ],
    "sg:phone":"+44 191 273 0157",
    "sg:postcode":"NE4 7YB",
    "sg:province":"Tyne and Wear",
    "sg:tags":[
        "consulting",
        "engineer"
    ],
    "wof:name":"W S Atkins & Partners",
    "wof:placetype":"venue"
},
  "geometry": {"coordinates":[-1.64186,54.96212],"type":"Point"}
}