{
  "type": "Feature",
  "properties": {
    "iso:country":"GB",
    "sg:address":"Wessex Road",
    "sg:city":"Dorchester",
    "sg:classifiers":[
        {
            "category":"Utilities",
            "subcategory":"Water",
            "type":"Services"
        },
        {
            "category":"Building & Trades",
            "subcategory":"Plumbing",
            "type":"Services"
        }
    ],
    "sg:phone":"+44 1305 257788",
    "sg:postcode":"DT1 2NU",
    "sg:province":"Dorset",
    "sg:tags":[
        "heating"
    ],
    "wof:name":"Pipefix Ltd",
    "wof:placetype":"venue"
},
  "geometry": {"coordinates":[-2.452589035,50.7138595581],"type":"Point"}
}