{
  "type": "Feature",
  "properties": {
    "addr:full":"7 Rear Of Lucius Street Torquay Devon TQ2 5UW",
    "addr:housenumber":"7 rear of",
    "addr:postcode":"tq2 5uw",
    "addr:street":"Lucius Street",
    "iso:country":"GB",
    "sg:address":"7 Rear Of Lucius Street",
    "sg:city":"Torquay",
    "sg:classifiers":[
        {
            "category":"Personal",
            "subcategory":"Beauty Salon",
            "type":"Services"
        }
    ],
    "sg:postcode":"TQ2 5UW",
    "sg:province":"Devon",
    "sg:tags":[
        "lady",
        "hairdresser"
    ],
    "wof:name":"Christine's",
    "wof:placetype":"venue"
},
  "geometry": {"coordinates":[-3.5434639454,50.4671936035],"type":"Point"}
}