{
  "type": "Feature",
  "properties": {
    "addr:full":"6-7 North Weylands Industrial Estate, Molesey Road Walton-on-thames Surrey KT12 3PL",
    "addr:housenumber":"6-7",
    "addr:postcode":"kt12 3pl",
    "addr:street":"North Weylands Industrial Estate Molesey Road",
    "iso:country":"GB",
    "sg:address":"6-7 North Weylands Industrial Estate, Molesey Road",
    "sg:city":"Walton-on-thames",
    "sg:classifiers":[
        {
            "category":"Retail",
            "subcategory":"Auto Repair",
            "type":"Services"
        }
    ],
    "sg:phone":"+44 1932 228849",
    "sg:postcode":"KT12 3PL",
    "sg:province":"Surrey",
    "sg:tags":[
        "modification",
        "garage"
    ],
    "wof:name":"Oakrapid Ltd.",
    "wof:placetype":"venue"
},
  "geometry": {"coordinates":[-0.420704,51.384346],"type":"Point"}
}