{
  "type": "Feature",
  "properties": {
    "iso:country":"GB",
    "sg:address":"Goldcroft",
    "sg:city":"Yeovil",
    "sg:classifiers":[
        {
            "category":"Manufacturing",
            "subcategory":"Textiles",
            "type":"Manufacturing & Wholesale Goods"
        }
    ],
    "sg:postcode":"BA21 4DT",
    "sg:province":"Somerset",
    "sg:tags":[
        "merchant",
        "agent"
    ],
    "wof:name":"E T P Sales & Agencies",
    "wof:placetype":"venue"
},
  "geometry": {"coordinates":[-2.632154,50.948624],"type":"Point"}
}