{
  "type": "Feature",
  "properties": {
    "addr:full":"Seiont Mill Ho, Seiont Rd Caernarfon Gwynedd LL55 2YL",
    "addr:postcode":"ll55 2yl",
    "addr:street":"Seiont Rd",
    "iso:country":"GB",
    "sg:address":"Seiont Mill Ho, Seiont Rd",
    "sg:city":"Caernarfon",
    "sg:classifiers":[
        {
            "category":"Building & Trades",
            "subcategory":"Construction",
            "type":"Services"
        }
    ],
    "sg:postcode":"LL55 2YL",
    "sg:province":"Gwynedd",
    "sg:tags":[
        "builder"
    ],
    "wof:name":"Burgess,Michael,",
    "wof:placetype":"venue"
},
  "geometry": {"coordinates":[-4.265929,53.12883],"type":"Point"}
}