{
  "type": "Feature",
  "properties": {
    "addr:full":"3 Cross St Newcastle Upon Tyne Tyne and Wear NE1 4XE",
    "addr:housenumber":"3",
    "addr:postcode":"ne1 4xe",
    "addr:street":"Cross St",
    "iso:country":"GB",
    "sg:address":"3 Cross St",
    "sg:city":"Newcastle Upon Tyne",
    "sg:classifiers":[
        {
            "category":"Shopping",
            "subcategory":"Clothing, Apparel, & Fashions",
            "type":"Retail Goods"
        }
    ],
    "sg:phone":"+44 191 233 2650",
    "sg:postcode":"NE1 4XE",
    "sg:province":"Tyne and Wear",
    "sg:tags":[
        "shop"
    ],
    "wof:name":"Period Clothing Warehose",
    "wof:placetype":"venue"
},
  "geometry": {"coordinates":[-1.619459033,54.970741272],"type":"Point"}
}