{
  "type": "Feature",
  "properties": {
    "iso:country":"GB",
    "sg:address":"Kirkbank House",
    "sg:city":"Kelso",
    "sg:classifiers":[
        {
            "category":"Restaurant",
            "type":"Food & Drink"
        },
        {
            "category":"Food & Beverages",
            "subcategory":"Meat & Fish",
            "type":"Retail Goods"
        }
    ],
    "sg:phone":"+44 1835 850797",
    "sg:postcode":"TD5 8LE",
    "sg:province":"Scottish Borders",
    "sg:tags":[
        "merchant"
    ],
    "wof:name":"The Teviot Coffee Shop",
    "wof:placetype":"venue"
},
  "geometry": {"coordinates":[-2.479497,55.568378],"type":"Point"}
}