{
  "type": "Feature",
  "properties": {
    "addr:full":"Honeytree Court, Fairmeads, Pyrles Lane Loughton Essex IG10 2RD",
    "addr:postcode":"ig10 2rd",
    "addr:street":"Honeytree;Pyrles Lane",
    "iso:country":"GB",
    "sg:address":"Honeytree Court, Fairmeads, Pyrles Lane",
    "sg:city":"Loughton",
    "sg:classifiers":[
        {
            "category":"Health Services",
            "subcategory":"Nursing And Care Facility",
            "type":"Services"
        },
        {
            "category":"Organizations",
            "subcategory":"Community Association",
            "type":"Services"
        }
    ],
    "sg:phone":"+44 20 8502 4958",
    "sg:postcode":"IG10 2RD",
    "sg:province":"Essex",
    "sg:tags":[
        "residential",
        "housing",
        "society"
    ],
    "wof:name":"Honeytree Court",
    "wof:placetype":"venue"
},
  "geometry": {"coordinates":[0.076568,51.654846],"type":"Point"}
}