{
  "type": "Feature",
  "properties": {
    "iso:country":"GB",
    "sg:address":"Edgar House, Lockett Road",
    "sg:city":"Wigan",
    "sg:classifiers":[
        {
            "category":"Wholesale",
            "subcategory":"Chemicals & Plastics",
            "type":"Manufacturing & Wholesale Goods"
        }
    ],
    "sg:phone":"+44 1942 275400",
    "sg:postcode":"WN4 8DE",
    "sg:province":"Lancashire",
    "sg:tags":[
        "product",
        "allied"
    ],
    "wof:name":"Chemviron Carbon Ltd.",
    "wof:placetype":"venue"
},
  "geometry": {"coordinates":[-2.641844,53.500946],"type":"Point"}
}