{
  "type": "Feature",
  "properties": {
    "iso:country":"GB",
    "sg:address":"3-4 Fore Street, Williton",
    "sg:city":"Taunton",
    "sg:classifiers":[
        {
            "category":"Food & Beverages",
            "subcategory":"Fruits & Vegetables",
            "type":"Retail Goods"
        }
    ],
    "sg:phone":"+44 1984 633434",
    "sg:postcode":"TA4 4RJ",
    "sg:province":"Devon",
    "sg:tags":[
        "greengrocer"
    ],
    "wof:name":"J Jones & Son",
    "wof:placetype":"venue"
},
  "geometry": {"coordinates":[-3.321089,51.160389],"type":"Point"}
}