{
  "type": "Feature",
  "properties": {
    "addr:full":"1 Honeyholes Lane, Dunholme Lincoln Lincolnshire LN2 3SH",
    "addr:housenumber":"1",
    "addr:postcode":"ln2 3sh",
    "addr:street":"Honeyholes Lane",
    "iso:country":"GB",
    "sg:address":"1 Honeyholes Lane, Dunholme",
    "sg:city":"Lincoln",
    "sg:classifiers":[
        {
            "category":"Manufacturing",
            "subcategory":"Signs",
            "type":"Manufacturing & Wholesale Goods"
        }
    ],
    "sg:postcode":"LN2 3SH",
    "sg:province":"Lincolnshire",
    "sg:tags":[
        "nameplate"
    ],
    "wof:name":"Sherwood Signs",
    "wof:placetype":"venue"
},
  "geometry": {"coordinates":[-0.4690510035,53.3011131287],"type":"Point"}
}