{
  "type": "Feature",
  "properties": {
    "addr:full":"The Thatched House, The Street, Framingham Pigot Norwich Norfolk NR14 7QJ",
    "addr:postcode":"nr14 7qj",
    "addr:street":"The Street",
    "iso:country":"GB",
    "sg:address":"The Thatched House, The Street, Framingham Pigot",
    "sg:city":"Norwich",
    "sg:classifiers":[
        {
            "category":"Shopping",
            "subcategory":"Books",
            "type":"Retail Goods"
        }
    ],
    "sg:phone":"+44 1508 494418",
    "sg:postcode":"NR14 7QJ",
    "sg:province":"Norfolk",
    "wof:name":"Dairy Industry Newsletter",
    "wof:placetype":"venue"
},
  "geometry": {"coordinates":[1.385745,52.594742],"type":"Point"}
}