{
  "type": "Feature",
  "properties": {
    "addr:full":"Orchard Park Shopping Centre, Ellerburn Avenue Hull East Riding of Yorkshire HU6 9RR",
    "addr:postcode":"hu6 9rr",
    "addr:street":"Park;Avenue Hull",
    "iso:country":"GB",
    "sg:address":"Orchard Park Shopping Centre, Ellerburn Avenue",
    "sg:city":"Hull",
    "sg:classifiers":[
        {
            "category":"Fast Food",
            "type":"Food & Drink"
        }
    ],
    "sg:phone":"+44 1482 801632",
    "sg:postcode":"HU6 9RR",
    "sg:province":"East Riding of Yorkshire",
    "sg:tags":[
        "away",
        "take"
    ],
    "wof:name":"Kings Kebabs",
    "wof:placetype":"venue"
},
  "geometry": {"coordinates":[-0.381599,53.787106],"type":"Point"}
}