{
  "type": "Feature",
  "properties": {
    "iso:country":"GB",
    "sg:address":"Unit 7, Via Gellia Mill, Via Gellia Rd, Bonsall",
    "sg:city":"Matlock",
    "sg:classifiers":[
        {
            "category":"Wholesale",
            "subcategory":"Office Equipment",
            "type":"Manufacturing & Wholesale Goods"
        },
        {
            "category":"Manufacturing",
            "subcategory":"Printing",
            "type":"Manufacturing & Wholesale Goods"
        }
    ],
    "sg:phone":"+44 1629 822880",
    "sg:postcode":"DE4 2AJ",
    "sg:province":"Derbyshire",
    "sg:tags":[
        "bookbinder",
        "bookbinding"
    ],
    "wof:name":"Susan Wood",
    "wof:placetype":"venue"
},
  "geometry": {"coordinates":[-1.5947380066,53.1095581055],"type":"Point"}
}