{
  "type": "Feature",
  "properties": {
    "addr:full":"571 Cathcart Road Glasgow Glasgow City G42 8SG",
    "addr:housenumber":"571",
    "addr:postcode":"g42 8sg",
    "addr:street":"Cathcart Road",
    "iso:country":"GB",
    "sg:address":"571 Cathcart Road",
    "sg:city":"Glasgow",
    "sg:classifiers":[
        {
            "category":"Building & Trades",
            "subcategory":"Landscaping Services",
            "type":"Services"
        },
        {
            "category":"Building & Trades",
            "subcategory":"Plumbing",
            "type":"Services"
        }
    ],
    "sg:postcode":"G42 8SG",
    "sg:province":"Glasgow City",
    "sg:tags":[
        "clearance",
        "drain",
        "drainage",
        "sewer",
        "contractor"
    ],
    "wof:name":"GLASGOW DRAIN CLEARING SERVICES LTD",
    "wof:placetype":"venue"
},
  "geometry": {"coordinates":[-4.2567181587,55.8360176086],"type":"Point"}
}