{
  "type": "Feature",
  "properties": {
    "iso:country":"GB",
    "sg:address":"33 West Street",
    "sg:city":"Belford",
    "sg:classifiers":[
        {
            "category":"Social Services",
            "subcategory":"Retirement Home",
            "type":"Services"
        },
        {
            "category":"Organizations",
            "subcategory":"Non-profit Organization",
            "type":"Services"
        }
    ],
    "sg:phone":"+44 1668 219220",
    "sg:postcode":"NE70 7QB",
    "sg:province":"Northumberland",
    "sg:tags":[
        "charity",
        "residential",
        "organisation",
        "care",
        "charitable"
    ],
    "wof:name":"Bell View",
    "wof:placetype":"venue"
},
  "geometry": {"coordinates":[-1.832719,55.597794],"type":"Point"}
}