{
  "type": "Feature",
  "properties": {
    "addr:full":"Stamford Works, 1 Gillett Street Stoke Newington Greater London N16 8JH",
    "addr:housenumber":"1",
    "addr:postcode":"n16 8jh",
    "addr:street":"Gillett Street",
    "iso:country":"GB",
    "sg:address":"Stamford Works, 1 Gillett Street",
    "sg:city":"Stoke Newington",
    "sg:classifiers":[
        {
            "category":"Organizations",
            "subcategory":"Community Association",
            "type":"Services"
        }
    ],
    "sg:phone":"+44 20 7923 9255",
    "sg:postcode":"N16 8JH",
    "sg:province":"Greater London",
    "sg:tags":[
        "co-operatives",
        "society",
        "housing",
        "trust"
    ],
    "wof:name":"Peter Bedford",
    "wof:placetype":"venue"
},
  "geometry": {"coordinates":[-0.0756840035,51.5488853455],"type":"Point"}
}