{
  "type": "Feature",
  "properties": {
    "iso:country":"GB",
    "sg:address":"2 Abingdon House, Cumberland Business Centre",
    "sg:city":"Portsmouth",
    "sg:classifiers":[
        {
            "category":"Organizations",
            "subcategory":"Non-profit Organization",
            "type":"Services"
        }
    ],
    "sg:phone":"+44 23 9282 3186",
    "sg:postcode":"PO5 1DS",
    "sg:province":"Hampshire",
    "sg:tags":[
        "charitable",
        "organisation",
        "voluntary",
        "charity"
    ],
    "sg:website":"http://www.iheem.org.uk",
    "wof:name":"The Institute of Healthcare Engineering & Estate Management",
    "wof:placetype":"venue"
},
  "geometry": {"coordinates":[-1.07863,50.79583],"type":"Point"}
}