{
  "type": "Feature",
  "properties": {
    "addr:full":"Venzers Cottage, Puttenham Guildford Surrey GU3 1AU",
    "addr:postcode":"gu3 1au",
    "iso:country":"GB",
    "sg:address":"Venzers Cottage, Puttenham",
    "sg:city":"Guildford",
    "sg:classifiers":[
        {
            "category":"Communications",
            "subcategory":"Film & Video Production",
            "type":"Services"
        }
    ],
    "sg:phone":"+44 1483 810529",
    "sg:postcode":"GU3 1AU",
    "sg:province":"Surrey",
    "sg:tags":[
        "illustrator",
        "artist"
    ],
    "wof:name":"Alice Winter Sculptor and Designer",
    "wof:placetype":"venue"
},
  "geometry": {"coordinates":[-0.6627770066,51.2221260071],"type":"Point"}
}