{
  "type": "Feature",
  "properties": {
    "addr:full":"235 Canterbury Rd Morden Surrey SM4 6QB",
    "addr:housenumber":"235",
    "addr:postcode":"sm4 6qb",
    "addr:street":"Canterbury Rd",
    "iso:country":"GB",
    "sg:address":"235 Canterbury Rd",
    "sg:city":"Morden",
    "sg:classifiers":[
        {
            "category":"Professional",
            "subcategory":"Printing & Photocopies",
            "type":"Services"
        }
    ],
    "sg:phone":"+44 20 8715 4298",
    "sg:postcode":"SM4 6QB",
    "sg:province":"Surrey",
    "sg:tags":[
        "top",
        "publishing",
        "desk"
    ],
    "wof:name":"Mitchell Designs",
    "wof:placetype":"venue"
},
  "geometry": {"coordinates":[-0.191182,51.387508],"type":"Point"}
}