{
  "type": "Feature",
  "properties": {
    "iso:country":"GB",
    "sg:address":"9 Appleby House, Thornaby",
    "sg:city":"Stockton-on-tees",
    "sg:classifiers":[
        {
            "category":"Shopping",
            "subcategory":"Florist",
            "type":"Retail Goods"
        }
    ],
    "sg:phone":"+44 1642 762685",
    "sg:postcode":"TS17 9EX",
    "sg:province":"Durham",
    "wof:name":"Carl Banks Florist",
    "wof:placetype":"venue"
},
  "geometry": {"coordinates":[-1.292764,54.51828],"type":"Point"}
}