{
  "type": "Feature",
  "properties": {
    "iso:country":"GB",
    "sg:address":"214 Queenstown Rd",
    "sg:city":"London",
    "sg:classifiers":[
        {
            "category":"Professional",
            "subcategory":"Lawyer & Legal Services",
            "type":"Services"
        }
    ],
    "sg:postcode":"SW8 3NX",
    "sg:province":"Greater London",
    "sg:tags":[
        "solicitor"
    ],
    "wof:name":"Baring,J E,",
    "wof:placetype":"venue"
},
  "geometry": {"coordinates":[-0.1466220021,51.4742774963],"type":"Point"}
}