{
  "type": "Feature",
  "properties": {
    "addr:full":"Clock House, Dundas South Queensferry City of Edinburgh EH30 9SP",
    "addr:postcode":"eh30 9sp",
    "iso:country":"GB",
    "sg:address":"Clock House, Dundas",
    "sg:city":"South Queensferry",
    "sg:classifiers":[
        {
            "category":"Utilities",
            "type":"Services"
        }
    ],
    "sg:phone":"+44 131 319 2213",
    "sg:postcode":"EH30 9SP",
    "sg:province":"City of Edinburgh",
    "sg:tags":[
        "internet"
    ],
    "wof:name":"Cable Net Computing Ltd",
    "wof:placetype":"venue"
},
  "geometry": {"coordinates":[-3.391718,55.985435],"type":"Point"}
}