{
  "type": "Feature",
  "properties": {
    "addr:full":"London Rd Hemel Hempstead Hertfordshire HP3 9AA",
    "addr:postcode":"hp3 9aa",
    "addr:street":"London Rd",
    "iso:country":"GB",
    "sg:address":"London Rd",
    "sg:city":"Hemel Hempstead",
    "sg:classifiers":[
        {
            "category":"Autos & Motor Vehicles",
            "subcategory":"Automobile Sales",
            "type":"Retail Goods"
        }
    ],
    "sg:phone":"+44 1442 247969",
    "sg:postcode":"HP3 9AA",
    "sg:province":"Hertfordshire",
    "sg:tags":[
        "car"
    ],
    "wof:name":"Pilling Fiat",
    "wof:placetype":"venue"
},
  "geometry": {"coordinates":[-0.4848639965,51.7430763245],"type":"Point"}
}