{
  "type": "Feature",
  "properties": {
    "addr:full":"The Croft, North Rd Bath Somerset BA2 6HX",
    "addr:postcode":"ba2 6hx",
    "addr:street":"North Rd",
    "iso:country":"GB",
    "sg:address":"The Croft, North Rd",
    "sg:city":"Bath",
    "sg:classifiers":[
        {
            "category":"Professional",
            "subcategory":"Business Services",
            "type":"Services"
        }
    ],
    "sg:phone":"+44 1225 482048",
    "sg:postcode":"BA2 6HX",
    "sg:province":"Somerset",
    "sg:tags":[
        "hospitality",
        "corporate"
    ],
    "wof:name":"Virgil Fine Art",
    "wof:placetype":"venue"
},
  "geometry": {"coordinates":[-2.323809,51.39563],"type":"Point"}
}