{
  "type": "Feature",
  "properties": {
    "addr:full":"Kernow, Campfield Hill Truro Cornwall TR1 1HB",
    "addr:postcode":"tr1 1hb",
    "addr:street":"Campfield Hill",
    "iso:country":"GB",
    "sg:address":"Kernow, Campfield Hill",
    "sg:city":"Truro",
    "sg:classifiers":[
        {
            "category":"Military Area",
            "subcategory":"Air Force Base",
            "type":"Public Place"
        }
    ],
    "sg:phone":"+44 1872 264248",
    "sg:postcode":"TR1 1HB",
    "sg:province":"Cornwall",
    "sg:tags":[
        "taxi",
        "hire",
        "private"
    ],
    "wof:name":"Bills Taxis Of Truro",
    "wof:placetype":"venue"
},
  "geometry": {"coordinates":[-5.050044,50.265396],"type":"Point"}
}