{
  "type": "Feature",
  "properties": {
    "addr:full":"9 Eldon St Bury Lancashire BL9 5AZ",
    "addr:housenumber":"9",
    "addr:postcode":"bl9 5az",
    "addr:street":"Eldon St",
    "iso:country":"GB",
    "sg:address":"9 Eldon St",
    "sg:city":"Bury",
    "sg:classifiers":[
        {
            "category":"Health Services",
            "subcategory":"Podiatrist",
            "type":"Services"
        }
    ],
    "sg:phone":"+44 161 797 6564",
    "sg:postcode":"BL9 5AZ",
    "sg:province":"Lancashire",
    "sg:tags":[
        "podiatrists",
        "chiropodist"
    ],
    "wof:name":"Nuala McEntyre",
    "wof:placetype":"venue"
},
  "geometry": {"coordinates":[-2.29229,53.601429],"type":"Point"}
}