{
  "type": "Feature",
  "properties": {
    "iso:country":"GB",
    "sg:address":"Sterling House, Great Eastern Wharf, Parkgate Road",
    "sg:city":"London",
    "sg:classifiers":[
        {
            "category":"Professional",
            "subcategory":"Management & Consulting",
            "type":"Services"
        }
    ],
    "sg:phone":"+44 20 7585 3399",
    "sg:postcode":"SW11 4NQ",
    "sg:province":"Greater London",
    "sg:tags":[
        "consultant",
        "business"
    ],
    "wof:name":"Via International Ltd.",
    "wof:placetype":"venue"
},
  "geometry": {"coordinates":[-0.16771,51.48008],"type":"Point"}
}