{
  "type": "Feature",
  "properties": {
    "addr:full":"73 Fortune Green Road London Greater London NW6 1DR",
    "addr:housenumber":"73",
    "addr:postcode":"nw6 1dr",
    "addr:street":"Fortune Green Road",
    "iso:country":"GB",
    "sg:address":"73 Fortune Green Road",
    "sg:city":"London",
    "sg:classifiers":[
        {
            "category":"Health Services",
            "subcategory":"Health Practitioner",
            "type":"Services"
        }
    ],
    "sg:phone":"+44 20 7431 0837",
    "sg:postcode":"NW6 1DR",
    "sg:province":"Greater London",
    "sg:tags":[
        "psychotherapist"
    ],
    "wof:name":"Ruth Barnett",
    "wof:placetype":"venue"
},
  "geometry": {"coordinates":[-0.196314007,51.556930542],"type":"Point"}
}