{
  "type": "Feature",
  "properties": {
    "iso:country":"GB",
    "sg:address":"Unit 6 Hutton St, Boldon Colliery Indust Est",
    "sg:city":"Newcastle Upon Tyne",
    "sg:classifiers":[
        {
            "category":"Home & Garden",
            "subcategory":"Kitchen Supply",
            "type":"Retail Goods"
        }
    ],
    "sg:phone":"+44 191 519 4200",
    "sg:postcode":"NE3 3XN",
    "sg:province":"Tyne and Wear",
    "sg:tags":[
        "catering"
    ],
    "wof:name":"North East Catering Supplies",
    "wof:placetype":"venue"
},
  "geometry": {"coordinates":[-1.640096,55.009254],"type":"Point"}
}