{
  "type": "Feature",
  "properties": {
    "addr:full":"423 Bearwood Road Smethwick West Midlands B66 4DF",
    "addr:housenumber":"423",
    "addr:postcode":"b66 4df",
    "addr:street":"Bearwood Road",
    "iso:country":"GB",
    "sg:address":"423 Bearwood Road",
    "sg:city":"Smethwick",
    "sg:classifiers":[
        {
            "category":"Restaurant",
            "type":"Food & Drink"
        }
    ],
    "sg:phone":"+44 121 429 7857",
    "sg:postcode":"B66 4DF",
    "sg:province":"West Midlands",
    "sg:tags":[
        "indian",
        "-"
    ],
    "wof:name":"Raja Tandoori Restaurant",
    "wof:placetype":"venue"
},
  "geometry": {"coordinates":[-1.969744,52.47842],"type":"Point"}
}