{
  "type": "Feature",
  "properties": {
    "addr:full":"17 Church Rd Maidstone Kent ME15 6QX",
    "addr:housenumber":"17",
    "addr:postcode":"me15 6qx",
    "addr:street":"Church Rd",
    "iso:country":"GB",
    "sg:address":"17 Church Rd",
    "sg:city":"Maidstone",
    "sg:classifiers":[
        {
            "category":"Social Services",
            "subcategory":"Retirement Home",
            "type":"Services"
        }
    ],
    "sg:phone":"+44 1622 686865",
    "sg:postcode":"ME15 6QX",
    "sg:province":"Kent",
    "sg:tags":[
        "residential",
        "care"
    ],
    "wof:name":"Haven The",
    "wof:placetype":"venue"
},
  "geometry": {"coordinates":[0.511766,51.264236],"type":"Point"}
}