{
  "type": "Feature",
  "properties": {
    "addr:full":"Mere Green Clinic, Mere Green Rd Sutton Coldfield Staffordshire B75 5BL",
    "addr:postcode":"b75 5bl",
    "addr:street":"Mere Green Rd",
    "iso:country":"GB",
    "sg:address":"Mere Green Clinic, Mere Green Rd",
    "sg:city":"Sutton Coldfield",
    "sg:classifiers":[
        {
            "category":"Health Services",
            "subcategory":"Doctor",
            "type":"Services"
        }
    ],
    "sg:phone":"+44 121 308 2137",
    "sg:postcode":"B75 5BL",
    "sg:province":"Staffordshire",
    "sg:tags":[
        "practitioners"
    ],
    "wof:name":"Slominski, H B",
    "wof:placetype":"venue"
},
  "geometry": {"coordinates":[-1.8280550241,52.5853042603],"type":"Point"}
}