{
  "type": "Feature",
  "properties": {
    "iso:country":"GB",
    "sg:address":"64 Oughtrington Lane, Bridge Works",
    "sg:city":"Lymm",
    "sg:classifiers":[
        {
            "category":"Building & Trades",
            "subcategory":"Construction",
            "type":"Services"
        }
    ],
    "sg:postcode":"WA13 0QT",
    "sg:province":"Cheshire",
    "sg:tags":[
        "joiner",
        "carpenter"
    ],
    "wof:name":"David W Ackerley",
    "wof:placetype":"venue"
},
  "geometry": {"coordinates":[-2.4574561119,53.3824043274],"type":"Point"}
}