{
  "type": "Feature",
  "properties": {
    "iso:country":"GB",
    "sg:address":"13 Station Road",
    "sg:city":"Norwich",
    "sg:classifiers":[
        {
            "category":"Professional",
            "subcategory":"Art Services",
            "type":"Services"
        }
    ],
    "sg:phone":"+44 1263 720907",
    "sg:postcode":"NR11 8JH",
    "sg:province":"Norfolk",
    "sg:tags":[
        "framing"
    ],
    "wof:name":"Mundelsely Gallery",
    "wof:placetype":"venue"
},
  "geometry": {"coordinates":[1.4332100153,52.8767433167],"type":"Point"}
}