{
  "type": "Feature",
  "properties": {
    "iso:country":"GB",
    "sg:address":"54 Mount Pleasant Rd",
    "sg:city":"Wallasey",
    "sg:classifiers":[
        {
            "category":"Wholesale",
            "subcategory":"Office Equipment",
            "type":"Manufacturing & Wholesale Goods"
        }
    ],
    "sg:phone":"+44 151 638 2088",
    "sg:postcode":"L45 5EW",
    "sg:province":"Merseyside",
    "sg:tags":[
        "register",
        "cash",
        "accessory"
    ],
    "wof:name":"Stewart Roberts Associates",
    "wof:placetype":"venue"
},
  "geometry": {"coordinates":[-3.046716,53.430801],"type":"Point"}
}