{
  "type": "Feature",
  "properties": {
    "addr:full":"172 Fletchamstead Way Coventry Warwickshire CV4 7BB",
    "addr:housenumber":"172",
    "addr:postcode":"cv4 7bb",
    "addr:street":"Fletchamstead Way",
    "iso:country":"GB",
    "sg:address":"172 Fletchamstead Way",
    "sg:city":"Coventry",
    "sg:classifiers":[
        {
            "category":"Manufacturing",
            "subcategory":"Petroleum Products",
            "type":"Manufacturing & Wholesale Goods"
        }
    ],
    "sg:phone":"+44 24 7671 7472",
    "sg:postcode":"CV4 7BB",
    "sg:province":"Warwickshire",
    "sg:tags":[
        "double",
        "glazing"
    ],
    "wof:name":"Keith Jones",
    "wof:placetype":"venue"
},
  "geometry": {"coordinates":[-1.548867,52.391651],"type":"Point"}
}