{
  "type": "Feature",
  "properties": {
    "addr:full":"4 Bath Street Southport Lancashire PR9 0DA",
    "addr:housenumber":"4",
    "addr:postcode":"pr9 0da",
    "addr:street":"Bath Street",
    "iso:country":"GB",
    "sg:address":"4 Bath Street",
    "sg:city":"Southport",
    "sg:classifiers":[
        {
            "category":"Travel",
            "subcategory":"Hotels & Motels",
            "type":"Entertainment"
        }
    ],
    "sg:phone":"+44 1704 535838",
    "sg:postcode":"PR9 0DA",
    "sg:province":"Lancashire",
    "wof:name":"Brae Mar Hotel",
    "wof:placetype":"venue"
},
  "geometry": {"coordinates":[-3.005618,53.649841],"type":"Point"}
}