{
  "type": "Feature",
  "properties": {
    "addr:full":"Amalgam Park, Tinsley Park Rd Sheffield South Yorkshire S9 5DL",
    "addr:postcode":"s9 5dl",
    "addr:street":"Amalgam Park Tinsley Park Rd",
    "iso:country":"GB",
    "sg:address":"Amalgam Park, Tinsley Park Rd",
    "sg:city":"Sheffield",
    "sg:classifiers":[
        {
            "category":"Retail",
            "subcategory":"Auto Repair",
            "type":"Services"
        }
    ],
    "sg:phone":"+44 114 243 2171",
    "sg:postcode":"S9 5DL",
    "sg:province":"South Yorkshire",
    "sg:tags":[
        "modification",
        "garage"
    ],
    "wof:name":"Ecco Auto Services",
    "wof:placetype":"venue"
},
  "geometry": {"coordinates":[-1.410738945,53.3997764587],"type":"Point"}
}