{
  "type": "Feature",
  "properties": {
    "addr:full":"5 Orton Enterprise Centre, Bakewell Road, Orton Southgate Peterborough Cambridgeshire PE2 6XU",
    "addr:housenumber":"5",
    "addr:postcode":"pe2 6xu",
    "addr:street":"Orton Enterprise Centre Bakewell Road",
    "iso:country":"GB",
    "sg:address":"5 Orton Enterprise Centre, Bakewell Road, Orton Southgate",
    "sg:city":"Peterborough",
    "sg:classifiers":[
        {
            "category":"Building & Trades",
            "subcategory":"Landscaping Services",
            "type":"Services"
        },
        {
            "category":"Professional",
            "subcategory":"Business Services",
            "type":"Services"
        }
    ],
    "sg:phone":"+44 1733 230033",
    "sg:postcode":"PE2 6XU",
    "sg:province":"Cambridgeshire",
    "sg:tags":[
        "body",
        "regulatory",
        "assoc"
    ],
    "sg:website":"http://www.bsga.co.uk",
    "wof:name":"British Sign & Graphics Association Ltd.",
    "wof:placetype":"venue"
},
  "geometry": {"coordinates":[-0.319989,52.537899],"type":"Point"}
}