{
  "type": "Feature",
  "properties": {
    "iso:country":"GB",
    "sg:address":"150-152 West Granton Road",
    "sg:city":"Edinburgh",
    "sg:classifiers":[
        {
            "category":"Cinema",
            "subcategory":"Movie Rental",
            "type":"Entertainment"
        }
    ],
    "sg:phone":"+44 131 538 7285",
    "sg:postcode":"EH5 1PE",
    "sg:province":"City of Edinburgh",
    "sg:tags":[
        "video",
        "library"
    ],
    "wof:name":"Granton Film Centre",
    "wof:placetype":"venue"
},
  "geometry": {"coordinates":[-3.2328140736,55.9786605835],"type":"Point"}
}