{
  "type": "Feature",
  "properties": {
    "iso:country":"GB",
    "sg:address":"Carlton Farm, Beehive Lane, Galleywood",
    "sg:city":"Chelmsford",
    "sg:classifiers":[
        {
            "category":"Sports & Exercise",
            "subcategory":"Stables",
            "type":"Entertainment"
        }
    ],
    "sg:phone":"+44 1245 358116",
    "sg:postcode":"CM2 8RL",
    "sg:province":"Essex",
    "sg:tags":[
        "education",
        "equestrian"
    ],
    "wof:name":"Formglade Ltd.",
    "wof:placetype":"venue"
},
  "geometry": {"coordinates":[0.466357,51.69701],"type":"Point"}
}