{
  "type": "Feature",
  "properties": {
    "addr:full":"Wellwood, Eridge Rd Crowborough East Sussex TN6 2XA",
    "addr:postcode":"tn6 2xa",
    "addr:street":"Eridge Rd",
    "iso:country":"GB",
    "sg:address":"Wellwood, Eridge Rd",
    "sg:city":"Crowborough",
    "sg:classifiers":[
        {
            "category":"Shopping",
            "subcategory":"Jewelry",
            "type":"Retail Goods"
        }
    ],
    "sg:phone":"+44 1892 654484",
    "sg:postcode":"TN6 2XA",
    "sg:province":"East Sussex",
    "sg:tags":[
        "gold",
        "silversmith"
    ],
    "wof:name":"E G Evans",
    "wof:placetype":"venue"
},
  "geometry": {"coordinates":[0.171893,51.053196],"type":"Point"}
}