{
  "type": "Feature",
  "properties": {
    "addr:full":"Waterloo Road Industrial Estate Llandrindod Wells Powys LD1 6BH",
    "addr:postcode":"ld1 6bh",
    "addr:street":"Waterloo Road Industrial Estate",
    "iso:country":"GB",
    "sg:address":"Waterloo Road Industrial Estate",
    "sg:city":"Llandrindod Wells",
    "sg:classifiers":[
        {
            "category":"Manufacturing",
            "subcategory":"Apparel",
            "type":"Manufacturing & Wholesale Goods"
        }
    ],
    "sg:postcode":"LD1 6BH",
    "sg:province":"Powys",
    "sg:tags":[
        "mnfr",
        "footwear"
    ],
    "wof:name":"Essanti Textiles",
    "wof:placetype":"venue"
},
  "geometry": {"coordinates":[-3.3769741058,52.2479400635],"type":"Point"}
}