{
  "type": "Feature",
  "properties": {
    "iso:country":"GB",
    "sg:address":"41 Trent Vale Road, Beeston",
    "sg:city":"Nottingham",
    "sg:classifiers":[
        {
            "category":"Retail",
            "subcategory":"Auto Repair",
            "type":"Services"
        }
    ],
    "sg:phone":"+44 115 925 6750",
    "sg:postcode":"NG9 1ND",
    "sg:province":"Nottinghamshire",
    "sg:tags":[
        "body",
        "car"
    ],
    "wof:name":"Jays Auto Repairs",
    "wof:placetype":"venue"
},
  "geometry": {"coordinates":[-1.208384,52.914902],"type":"Point"}
}