{
  "type": "Feature",
  "properties": {
    "iso:country":"GB",
    "sg:address":"David Martin Estate Agent, 80 London Road",
    "sg:city":"Colchester",
    "sg:classifiers":[
        {
            "category":"Real Estate",
            "subcategory":"Real Estate Agent",
            "type":"Services"
        }
    ],
    "sg:postcode":"CO3 4DG",
    "sg:province":"Essex",
    "wof:name":"David Martin Estate Agents Ltd.",
    "wof:placetype":"venue"
},
  "geometry": {"coordinates":[0.8529599905,51.8895797729],"type":"Point"}
}