{
  "type": "Feature",
  "properties": {
    "iso:country":"GB",
    "sg:address":"52-62 Bishopsgate",
    "sg:city":"London",
    "sg:classifiers":[
        {
            "category":"Building & Trades",
            "subcategory":"Construction",
            "type":"Services"
        }
    ],
    "sg:phone":"+44 20 7382 9787",
    "sg:postcode":"EC2N 4AJ",
    "sg:province":"Greater London",
    "sg:tags":[
        "management"
    ],
    "wof:name":"Hasilwood House",
    "wof:placetype":"venue"
},
  "geometry": {"coordinates":[-0.0824889988,51.5153617859],"type":"Point"}
}