{
  "type": "Feature",
  "properties": {
    "addr:full":"71 Castle Hill Beccles Norfolk NR34 7BJ",
    "addr:housenumber":"71",
    "addr:postcode":"nr34 7bj",
    "addr:street":"Castle Hill",
    "iso:country":"GB",
    "sg:address":"71 Castle Hill",
    "sg:city":"Beccles",
    "sg:classifiers":[
        {
            "category":"Professional",
            "type":"Services"
        }
    ],
    "sg:postcode":"NR34 7BJ",
    "sg:province":"Norfolk",
    "sg:tags":[
        "repair",
        "tech",
        "maintenance"
    ],
    "wof:name":"John Gallagher",
    "wof:placetype":"venue"
},
  "geometry": {"coordinates":[1.576086,52.449623],"type":"Point"}
}