{
  "type": "Feature",
  "properties": {
    "iso:country":"GB",
    "sg:address":"243 Lozells Rd",
    "sg:city":"Birmingham",
    "sg:classifiers":[
        {
            "category":"Organizations",
            "subcategory":"Non-profit Organization",
            "type":"Services"
        }
    ],
    "sg:phone":"+44 121 551 5561",
    "sg:postcode":"B19 1RJ",
    "sg:province":"West Midlands",
    "sg:tags":[
        "organisation",
        "voluntary",
        "charity"
    ],
    "wof:name":"Young Mothers Relief Association",
    "wof:placetype":"venue"
},
  "geometry": {"coordinates":[-1.914031,52.502857],"type":"Point"}
}