{
  "type": "Feature",
  "properties": {
    "iso:country":"GB",
    "sg:address":"57 Dean Street, South Shore",
    "sg:city":"Blackpool",
    "sg:classifiers":[
        {
            "category":"Travel",
            "subcategory":"Hotels & Motels",
            "type":"Entertainment"
        }
    ],
    "sg:phone":"+44 1253 342436",
    "sg:postcode":"FY4 1BP",
    "sg:province":"Lancashire",
    "wof:name":"Lor-Dean Private Hotel",
    "wof:placetype":"venue"
},
  "geometry": {"coordinates":[-3.05061,53.796783],"type":"Point"}
}