{
  "type": "Feature",
  "properties": {
    "addr:full":"250 Ladypool Road Birmingham West Midlands B12 8JU",
    "addr:housenumber":"250",
    "addr:postcode":"b12 8ju",
    "addr:street":"Ladypool Road",
    "iso:country":"GB",
    "sg:address":"250 Ladypool Road",
    "sg:city":"Birmingham",
    "sg:classifiers":[
        {
            "category":"Restaurant",
            "type":"Food & Drink"
        }
    ],
    "sg:postcode":"B12 8JU",
    "sg:province":"West Midlands",
    "wof:name":"Ali Baba Restaurant",
    "wof:placetype":"venue"
},
  "geometry": {"coordinates":[-1.876697,52.455647],"type":"Point"}
}