{
  "type": "Feature",
  "properties": {
    "iso:country":"GB",
    "sg:address":"Fintree, Camp Rd",
    "sg:city":"Crieff",
    "sg:classifiers":[
        {
            "category":"Personal",
            "subcategory":"Tanning Parlor",
            "type":"Services"
        }
    ],
    "sg:phone":"+44 1764 670057",
    "sg:postcode":"PH6 2HA",
    "sg:province":"Perth and Kinross",
    "sg:tags":[
        "sunbeds"
    ],
    "wof:name":"Sun Hire",
    "wof:placetype":"venue"
},
  "geometry": {"coordinates":[-4.000459,56.37793],"type":"Point"}
}