{
  "type": "Feature",
  "properties": {
    "iso:country":"GB",
    "sg:address":"1018 Yardley Wood Rd",
    "sg:city":"Birmingham",
    "sg:classifiers":[
        {
            "category":"Retail",
            "subcategory":"Auto Repair",
            "type":"Services"
        }
    ],
    "sg:phone":"+44 121 436 7800",
    "sg:postcode":"B14 4BP",
    "sg:province":"West Midlands",
    "sg:tags":[
        "modification",
        "garage"
    ],
    "wof:name":"A1 Motors",
    "wof:placetype":"venue"
},
  "geometry": {"coordinates":[-1.870088,52.415241],"type":"Point"}
}