{
  "type": "Feature",
  "properties": {
    "addr:full":"160 Park View Road Welling Kent DA16 1ST",
    "addr:housenumber":"160",
    "addr:postcode":"da16 1st",
    "addr:street":"Park View Road",
    "iso:country":"GB",
    "sg:address":"160 Park View Road",
    "sg:city":"Welling",
    "sg:classifiers":[
        {
            "category":"Home & Garden",
            "subcategory":"Home Furnishings",
            "type":"Retail Goods"
        },
        {
            "category":"Social Services",
            "subcategory":"Adult Care",
            "type":"Services"
        }
    ],
    "sg:phone":"+44 20 8303 9011",
    "sg:postcode":"DA16 1ST",
    "sg:province":"Kent",
    "sg:tags":[
        "merchant",
        "decorator",
        "diy",
        "decorators'"
    ],
    "wof:name":"C Brewer & Sons Ltd.",
    "wof:placetype":"venue"
},
  "geometry": {"coordinates":[0.1148649976,51.46144104],"type":"Point"}
}