{
  "type": "Feature",
  "properties": {
    "addr:full":"Hurstlea, 106 Hatfield Rd St Albans Hertfordshire AL1 3RL",
    "addr:housenumber":"106",
    "addr:postcode":"al1 3rl",
    "addr:street":"Hatfield Rd",
    "iso:country":"GB",
    "sg:address":"Hurstlea, 106 Hatfield Rd",
    "sg:city":"St Albans",
    "sg:classifiers":[
        {
            "category":"Organizations",
            "subcategory":"Religious Organization",
            "type":"Services"
        }
    ],
    "sg:phone":"+44 1727 841890",
    "sg:postcode":"AL1 3RL",
    "sg:province":"Hertfordshire",
    "sg:tags":[
        "organisation"
    ],
    "wof:name":"Loreto Sisters",
    "wof:placetype":"venue"
},
  "geometry": {"coordinates":[-0.3377520144,51.7531890869],"type":"Point"}
}