{
  "type": "Feature",
  "properties": {
    "iso:country":"GB",
    "sg:address":"7 Surrey St",
    "sg:city":"Littlehampton",
    "sg:classifiers":[
        {
            "category":"Banks & Credit Unions",
            "subcategory":"Financial Services",
            "type":"Services"
        }
    ],
    "sg:phone":"+44 1903 733196",
    "sg:postcode":"BN17 5AZ",
    "sg:province":"West Sussex",
    "sg:tags":[
        "consultant"
    ],
    "wof:name":"Hambro Countrywide",
    "wof:placetype":"venue"
},
  "geometry": {"coordinates":[-0.543415,50.809437],"type":"Point"}
}