{
  "type": "Feature",
  "properties": {
    "addr:full":"Holyhead Road, Priorslee Telford Shropshire TF2 9TY",
    "addr:postcode":"tf2 9ty",
    "addr:street":"Holyhead Road",
    "iso:country":"GB",
    "sg:address":"Holyhead Road, Priorslee",
    "sg:city":"Telford",
    "sg:classifiers":[
        {
            "category":"Professional",
            "subcategory":"Engineering",
            "type":"Services"
        }
    ],
    "sg:phone":"+44 1952 292920",
    "sg:postcode":"TF2 9TY",
    "sg:province":"Shropshire",
    "sg:tags":[
        "precision",
        "engineer"
    ],
    "wof:name":"Kiyokuni Europe Ltd.",
    "wof:placetype":"venue"
},
  "geometry": {"coordinates":[-2.4211509228,52.6878204346],"type":"Point"}
}