{
  "type": "Feature",
  "properties": {
    "iso:country":"GB",
    "sg:address":"10 Carlton Road",
    "sg:city":"Worksop",
    "sg:classifiers":[
        {
            "category":"Personal",
            "subcategory":"Nail Salon",
            "type":"Services"
        }
    ],
    "sg:phone":"+44 1909 476611",
    "sg:postcode":"S80 1PH",
    "sg:province":"Nottinghamshire",
    "sg:tags":[
        "solarium",
        "tanning"
    ],
    "wof:name":"Pepsi Piro's Sunbeds",
    "wof:placetype":"venue"
},
  "geometry": {"coordinates":[-1.1222579479,53.3078956604],"type":"Point"}
}