{
  "type": "Feature",
  "properties": {
    "iso:country":"GB",
    "sg:address":"106 North Road, Combe Down",
    "sg:city":"Bath",
    "sg:classifiers":[
        {
            "category":"Professional",
            "subcategory":"Engineering",
            "type":"Services"
        }
    ],
    "sg:phone":"+44 1225 837582",
    "sg:postcode":"BA2 5DJ",
    "sg:province":"Somerset",
    "sg:tags":[
        "contractor",
        "electrical",
        "engineer"
    ],
    "wof:name":"Lloyd-Blackmore Ltd.",
    "wof:placetype":"venue"
},
  "geometry": {"coordinates":[-2.3444700241,51.3623924255],"type":"Point"}
}