{
  "type": "Feature",
  "properties": {
    "addr:full":"11 Hyde Gdn{s} Eastbourne East Sussex BN21 4PP",
    "addr:housenumber":"11",
    "addr:postcode":"bn21 4pp",
    "addr:street":"Hyde Gdn S Eastbourne",
    "iso:country":"GB",
    "sg:address":"11 Hyde Gdn{s}",
    "sg:city":"Eastbourne",
    "sg:classifiers":[
        {
            "category":"Professional",
            "subcategory":"Lawyer & Legal Services",
            "type":"Services"
        }
    ],
    "sg:phone":"+44 1323 734737",
    "sg:postcode":"BN21 4PP",
    "sg:province":"East Sussex",
    "sg:tags":[
        "solicitor"
    ],
    "wof:name":"Lawson Lewis & Co.",
    "wof:placetype":"venue"
},
  "geometry": {"coordinates":[0.282451,50.768002],"type":"Point"}
}