{
  "type": "Feature",
  "properties": {
    "iso:country":"GB",
    "sg:address":"Old Brewery Works",
    "sg:city":"Batley",
    "sg:classifiers":[
        {
            "category":"Professional",
            "subcategory":"Printing & Photocopies",
            "type":"Services"
        }
    ],
    "sg:postcode":"WF17 6LP",
    "sg:province":"West Yorkshire",
    "sg:tags":[
        "printer"
    ],
    "wof:name":"Pro Create",
    "wof:placetype":"venue"
},
  "geometry": {"coordinates":[-1.654499054,53.7264213562],"type":"Point"}
}