{
  "type": "Feature",
  "properties": {
    "iso:country":"GB",
    "sg:address":"469 New Cross Road",
    "sg:city":"London",
    "sg:classifiers":[
        {
            "category":"Personal",
            "subcategory":"Beauty Salon",
            "type":"Services"
        }
    ],
    "sg:postcode":"SE14 6TA",
    "sg:province":"Greater London",
    "sg:tags":[
        "lady",
        "hairdresser"
    ],
    "wof:name":"About U All",
    "wof:placetype":"venue"
},
  "geometry": {"coordinates":[-0.029946,51.475704],"type":"Point"}
}