{
  "type": "Feature",
  "properties": {
    "addr:full":"189 Lower Blandford Road, Lower Blandford Broadstone Dorset BH18 8DH",
    "addr:housenumber":"189",
    "addr:postcode":"bh18 8dh",
    "addr:street":"Lower Blandford Road Lower",
    "iso:country":"GB",
    "sg:address":"189 Lower Blandford Road, Lower Blandford",
    "sg:city":"Broadstone",
    "sg:classifiers":[
        {
            "category":"Communications",
            "type":"Services"
        }
    ],
    "sg:phone":"+44 1202 692391",
    "sg:postcode":"BH18 8DH",
    "sg:province":"Dorset",
    "sg:tags":[
        "tv",
        "video",
        "radio"
    ],
    "wof:name":"Harris & Nash Ltd.",
    "wof:placetype":"venue"
},
  "geometry": {"coordinates":[-1.9948890209,50.7602348328],"type":"Point"}
}