{
  "type": "Feature",
  "properties": {
    "addr:full":"302 Wells Road Bristol City of Bristol BS4 2QG",
    "addr:housenumber":"302",
    "addr:postcode":"bs4 2qg",
    "addr:street":"Wells Road",
    "iso:country":"GB",
    "sg:address":"302 Wells Road",
    "sg:city":"Bristol",
    "sg:classifiers":[
        {
            "category":"Banks & Credit Unions",
            "subcategory":"Financial Services",
            "type":"Services"
        }
    ],
    "sg:postcode":"BS4 2QG",
    "sg:province":"City of Bristol",
    "sg:tags":[
        "cashing",
        "cheque"
    ],
    "wof:name":"Mastercheque",
    "wof:placetype":"venue"
},
  "geometry": {"coordinates":[-2.5669798851,51.4348564148],"type":"Point"}
}