{
  "type": "Feature",
  "properties": {
    "addr:full":"Heol Dulais, Birchgrove Swansea Neath Port Talbot SA7 9LH",
    "addr:postcode":"sa7 9lh",
    "addr:street":"Heol Dulais",
    "iso:country":"GB",
    "sg:address":"Heol Dulais, Birchgrove",
    "sg:city":"Swansea",
    "sg:classifiers":[
        {
            "category":"Education",
            "subcategory":"School",
            "type":"Public Place"
        }
    ],
    "sg:phone":"+44 1792 814293",
    "sg:postcode":"SA7 9LH",
    "sg:province":"Neath Port Talbot",
    "sg:tags":[
        "local",
        "authority"
    ],
    "wof:name":"Birchgrove Junior School",
    "wof:placetype":"venue"
},
  "geometry": {"coordinates":[-3.8739008904,51.6656417847],"type":"Point"}
}