{
  "type": "Feature",
  "properties": {
    "addr:full":"20 Beeches End, Boston Spa Wetherby West Yorkshire LS23 6HL",
    "addr:housenumber":"20",
    "addr:postcode":"ls23 6hl",
    "addr:street":"Beeches End",
    "iso:country":"GB",
    "sg:address":"20 Beeches End, Boston Spa",
    "sg:city":"Wetherby",
    "sg:classifiers":[
        {
            "category":"Professional",
            "subcategory":"Engineering",
            "type":"Services"
        },
        {
            "category":"Building & Trades",
            "subcategory":"Electrical",
            "type":"Services"
        }
    ],
    "sg:phone":"+44 1937 843079",
    "sg:postcode":"LS23 6HL",
    "sg:province":"West Yorkshire",
    "sg:tags":[
        "engineer",
        "electrician",
        "contractor"
    ],
    "wof:name":"Anthony Hill",
    "wof:placetype":"venue"
},
  "geometry": {"coordinates":[-1.341899991,53.9019737244],"type":"Point"}
}