{
  "type": "Feature",
  "properties": {
    "addr:full":"28 Green Street Cambridge Cambridgeshire CB2 3JX",
    "addr:housenumber":"28",
    "addr:postcode":"cb2 3jx",
    "addr:street":"Green Street",
    "iso:country":"GB",
    "sg:address":"28 Green Street",
    "sg:city":"Cambridge",
    "sg:classifiers":[
        {
            "category":"Transit Center",
            "subcategory":"Freight",
            "type":"Transportation"
        },
        {
            "category":"Shopping",
            "subcategory":"Gifts & Souvenirs",
            "type":"Retail Goods"
        }
    ],
    "sg:postcode":"CB2 3JX",
    "sg:province":"Cambridgeshire",
    "sg:tags":[
        "shop",
        "craft",
        "centre"
    ],
    "wof:name":"PACHAMAMA",
    "wof:placetype":"venue"
},
  "geometry": {"coordinates":[0.1193000004,52.2066345215],"type":"Point"}
}