{
  "type": "Feature",
  "properties": {
    "addr:full":"7 Park Industrial Estate, Frogmore St Albans Hertfordshire AL2 2DR",
    "addr:housenumber":"7",
    "addr:postcode":"al2 2dr",
    "addr:street":"Park Industrial;Frogmore",
    "iso:country":"GB",
    "sg:address":"7 Park Industrial Estate, Frogmore",
    "sg:city":"St Albans",
    "sg:classifiers":[
        {
            "category":"Shopping",
            "subcategory":"Computers & Home Electronics",
            "type":"Retail Goods"
        },
        {
            "category":"Building & Trades",
            "subcategory":"Electrical",
            "type":"Services"
        }
    ],
    "sg:phone":"+44 1727 873922",
    "sg:postcode":"AL2 2DR",
    "sg:province":"Hertfordshire",
    "sg:tags":[
        "heating"
    ],
    "wof:name":"Brackenheath Ltd.",
    "wof:placetype":"venue"
},
  "geometry": {"coordinates":[-0.335496,51.719238],"type":"Point"}
}