{
  "type": "Feature",
  "properties": {
    "iso:country":"GB",
    "sg:address":"2 Castle Blvd",
    "sg:city":"Nottingham",
    "sg:classifiers":[
        {
            "category":"Professional",
            "subcategory":"Art Services",
            "type":"Services"
        }
    ],
    "sg:phone":"+44 115 947 4500",
    "sg:postcode":"NG7 1FB",
    "sg:province":"Nottinghamshire",
    "sg:tags":[
        "photographer"
    ],
    "wof:name":"Peter Thompson Photography",
    "wof:placetype":"venue"
},
  "geometry": {"coordinates":[-1.154899,52.94828],"type":"Point"}
}