{
  "type": "Feature",
  "properties": {
    "iso:country":"GB",
    "sg:address":"Unit 1, Long Meadow Industrial Estate, Ewyas Harold",
    "sg:city":"Hereford",
    "sg:classifiers":[
        {
            "category":"Home & Garden",
            "subcategory":"Kitchen Supply",
            "type":"Retail Goods"
        }
    ],
    "sg:phone":"+44 1981 241191",
    "sg:postcode":"HR2 0UA",
    "sg:province":"Herefordshire",
    "sg:tags":[
        "catering"
    ],
    "wof:name":"Neil Powell Catering",
    "wof:placetype":"venue"
},
  "geometry": {"coordinates":[-2.8832130432,51.9438018799],"type":"Point"}
}