{
  "type": "Feature",
  "properties": {
    "addr:full":"4 Bishops Road, Abbeymead Gloucester Gloucestershire GL4 5FP",
    "addr:housenumber":"4",
    "addr:postcode":"gl4 5fp",
    "addr:street":"Bishops Road",
    "iso:country":"GB",
    "sg:address":"4 Bishops Road, Abbeymead",
    "sg:city":"Gloucester",
    "sg:classifiers":[
        {
            "category":"Professional",
            "subcategory":"Computer Services",
            "type":"Services"
        }
    ],
    "sg:postcode":"GL4 5FP",
    "sg:province":"Gloucestershire",
    "sg:tags":[
        "system",
        "software"
    ],
    "wof:name":"Pre Press Training & Consultancy",
    "wof:placetype":"venue"
},
  "geometry": {"coordinates":[-2.1999220848,51.8492012024],"type":"Point"}
}