{
  "type": "Feature",
  "properties": {
    "addr:full":"Gibbons Cottage, Plex Lane Ormskirk Lancashire L39 7JZ",
    "addr:postcode":"l39 7jz",
    "addr:street":"Plex Lane",
    "iso:country":"GB",
    "sg:address":"Gibbons Cottage, Plex Lane",
    "sg:city":"Ormskirk",
    "sg:classifiers":[
        {
            "category":"Manufacturing",
            "subcategory":"Tools & Machinery",
            "type":"Manufacturing & Wholesale Goods"
        }
    ],
    "sg:phone":"+44 1704 841082",
    "sg:postcode":"L39 7JZ",
    "sg:province":"Lancashire",
    "sg:tags":[
        "society",
        "friendly"
    ],
    "wof:name":"Policy Trading Co. International Ltd.",
    "wof:placetype":"venue"
},
  "geometry": {"coordinates":[-2.8863,53.566277],"type":"Point"}
}