{
  "type": "Feature",
  "properties": {
    "addr:full":"7 Heathcote Drive, Sileby Loughborough Leicestershire LE12 7ND",
    "addr:housenumber":"7",
    "addr:postcode":"le12 7nd",
    "addr:street":"Heathcote Drive",
    "iso:country":"GB",
    "sg:address":"7 Heathcote Drive, Sileby",
    "sg:city":"Loughborough",
    "sg:classifiers":[
        {
            "category":"Building & Trades",
            "subcategory":"Cleaning & Sanitation",
            "type":"Services"
        },
        {
            "category":"Home & Garden",
            "subcategory":"Carpets & Floor Coverings",
            "type":"Retail Goods"
        }
    ],
    "sg:phone":"+44 1509 814193",
    "sg:postcode":"LE12 7ND",
    "sg:province":"Leicestershire",
    "sg:tags":[
        "cleaner",
        "upholstery"
    ],
    "wof:name":"Charnwood Cleaning Services",
    "wof:placetype":"venue"
},
  "geometry": {"coordinates":[-1.1010220051,52.7374992371],"type":"Point"}
}