{
  "type": "Feature",
  "properties": {
    "iso:country":"GB",
    "sg:address":"Limehouse Ct, 3-11 Dod St",
    "sg:city":"Poplar",
    "sg:classifiers":[
        {
            "category":"Communications",
            "subcategory":"Newspaper",
            "type":"Services"
        }
    ],
    "sg:phone":"+44 20 7538 9683",
    "sg:postcode":"E14 7EQ",
    "sg:province":"Greater London",
    "sg:tags":[
        "magazine"
    ],
    "wof:name":"Worldwide Christian Publications",
    "wof:placetype":"venue"
},
  "geometry": {"coordinates":[-0.02651,51.514],"type":"Point"}
}