{
  "type": "Feature",
  "properties": {
    "iso:country":"GB",
    "sg:address":"7 Churchill Corner",
    "sg:city":"Stansted",
    "sg:classifiers":[
        {
            "category":"Professional",
            "subcategory":"Detective & Security Services",
            "type":"Services"
        }
    ],
    "sg:postcode":"CM24 8UA",
    "sg:province":"Essex",
    "sg:tags":[
        "alarm",
        "burglar",
        "system"
    ],
    "wof:name":"Stevens Security",
    "wof:placetype":"venue"
},
  "geometry": {"coordinates":[0.204490006,51.8939781189],"type":"Point"}
}