{
  "type": "Feature",
  "properties": {
    "iso:country":"GB",
    "sg:address":"21 High Street, Upton-upon-severn",
    "sg:city":"Worcester",
    "sg:classifiers":[
        {
            "category":"Travel",
            "subcategory":"Hotels & Motels",
            "type":"Entertainment"
        }
    ],
    "sg:phone":"+44 1684 592551",
    "sg:postcode":"WR8 0HJ",
    "sg:province":"Gloucestershire",
    "wof:name":"The White Lion Hotel",
    "wof:placetype":"venue"
},
  "geometry": {"coordinates":[-2.217317,52.063553],"type":"Point"}
}