{
  "type": "Feature",
  "properties": {
    "iso:country":"GB",
    "sg:address":"7 Thornbera Close",
    "sg:city":"Bishops Stortford",
    "sg:classifiers":[
        {
            "category":"Building & Trades",
            "subcategory":"Cleaning & Sanitation",
            "type":"Services"
        }
    ],
    "sg:phone":"+44 1279 659758",
    "sg:postcode":"CM23 3NR",
    "sg:province":"Essex",
    "sg:tags":[
        "cleaner",
        "window"
    ],
    "wof:name":"Apple Cleaning Services",
    "wof:placetype":"venue"
},
  "geometry": {"coordinates":[0.156106,51.857143],"type":"Point"}
}