{
  "type": "Feature",
  "properties": {
    "addr:full":"9 Forge Ct, Reading Rd, Yateley Camberley Hampshire GU46 7RX",
    "addr:housenumber":"9",
    "addr:postcode":"gu46 7rx",
    "addr:street":"Forge Ct Reading Rd",
    "iso:country":"GB",
    "sg:address":"9 Forge Ct, Reading Rd, Yateley",
    "sg:city":"Camberley",
    "sg:classifiers":[
        {
            "category":"Professional",
            "subcategory":"Management & Consulting",
            "type":"Services"
        }
    ],
    "sg:phone":"+44 1252 860820",
    "sg:postcode":"GU46 7RX",
    "sg:province":"Hampshire",
    "sg:tags":[
        "consultant",
        "training"
    ],
    "wof:name":"Partners in Service Ltd",
    "wof:placetype":"venue"
},
  "geometry": {"coordinates":[-0.827109,51.342319],"type":"Point"}
}