{
  "type": "Feature",
  "properties": {
    "addr:full":"6 Lansdowne Mews London Greater London W11 3BH",
    "addr:housenumber":"6",
    "addr:postcode":"w11 3bh",
    "addr:street":"Lansdowne Mews",
    "iso:country":"GB",
    "sg:address":"6 Lansdowne Mews",
    "sg:city":"London",
    "sg:classifiers":[
        {
            "category":"Travel",
            "subcategory":"Travel Agent",
            "type":"Entertainment"
        }
    ],
    "sg:postcode":"W11 3BH",
    "sg:province":"Greater London",
    "wof:name":"Reef Touring Ltd",
    "wof:placetype":"venue"
},
  "geometry": {"coordinates":[-0.2064609975,51.5073852539],"type":"Point"}
}