{
  "type": "Feature",
  "properties": {
    "addr:full":"14 Redlin Court, Linkfield Lane Redhill Surrey RH1 1TB",
    "addr:housenumber":"14",
    "addr:postcode":"rh1 1tb",
    "addr:street":"Redlin Court Linkfield Lane",
    "iso:country":"GB",
    "sg:address":"14 Redlin Court, Linkfield Lane",
    "sg:city":"Redhill",
    "sg:classifiers":[
        {
            "category":"Retail",
            "subcategory":"Auto Repair",
            "type":"Services"
        }
    ],
    "sg:postcode":"RH1 1TB",
    "sg:province":"Surrey",
    "sg:tags":[
        "modification",
        "garage"
    ],
    "wof:name":"Sw Performance  &  Style Ltd",
    "wof:placetype":"venue"
},
  "geometry": {"coordinates":[-0.1688790023,51.2381782532],"type":"Point"}
}