{
  "type": "Feature",
  "properties": {
    "iso:country":"GB",
    "sg:address":"2a Gardyne St, Friockheim",
    "sg:city":"Arbroath",
    "sg:classifiers":[
        {
            "category":"Building & Trades",
            "subcategory":"Construction",
            "type":"Services"
        }
    ],
    "sg:postcode":"DD11 4SN",
    "sg:province":"Angus",
    "sg:tags":[
        "builder"
    ],
    "wof:name":"Jones,Gareth,",
    "wof:placetype":"venue"
},
  "geometry": {"coordinates":[-2.667843,56.637077],"type":"Point"}
}