{
  "type": "Feature",
  "properties": {
    "addr:full":"Towyn Farm, Tudweiliog Pwllheli Gwynedd LL53 8PD",
    "addr:housenumber":"tudweiliog",
    "addr:postcode":"ll53 8pd",
    "addr:street":"Pwllheli Gwynedd",
    "iso:country":"GB",
    "sg:address":"Towyn Farm, Tudweiliog",
    "sg:city":"Pwllheli",
    "sg:classifiers":[
        {
            "category":"Farming",
            "subcategory":"Livestock Farm",
            "type":"Manufacturing & Wholesale Goods"
        }
    ],
    "sg:phone":"+44 1758 770230",
    "sg:postcode":"LL53 8PD",
    "sg:province":"Gwynedd",
    "sg:tags":[
        "others"
    ],
    "wof:name":"R W Owen",
    "wof:placetype":"venue"
},
  "geometry": {"coordinates":[-4.6216039658,52.8992614746],"type":"Point"}
}