{
  "type": "Feature",
  "properties": {
    "iso:country":"GB",
    "sg:address":"Gordon Road",
    "sg:city":"High Wycombe",
    "sg:classifiers":[
        {
            "category":"Bars & Pubs",
            "type":"Food & Drink"
        },
        {
            "category":"Community Center",
            "subcategory":"Social",
            "type":"Public Place"
        }
    ],
    "sg:phone":"+44 1494 522977",
    "sg:postcode":"HP13 6EP",
    "sg:province":"Buckinghamshire",
    "sg:tags":[
        "pubs",
        "house",
        "inn",
        "activity"
    ],
    "wof:name":"Greene King Leasing No 1 Ltd.",
    "wof:placetype":"venue"
},
  "geometry": {"coordinates":[-0.737217,51.627586],"type":"Point"}
}