{
  "type": "Feature",
  "properties": {
    "addr:full":"White Gate Cottage, The Green, Coddenham Ipswich Suffolk IP6 9UN",
    "addr:postcode":"ip6 9un",
    "addr:street":"The Green",
    "iso:country":"GB",
    "sg:address":"White Gate Cottage, The Green, Coddenham",
    "sg:city":"Ipswich",
    "sg:classifiers":[
        {
            "category":"Professional",
            "subcategory":"Secretarial Services",
            "type":"Services"
        }
    ],
    "sg:postcode":"IP6 9UN",
    "sg:province":"Suffolk",
    "wof:name":"Top Copy Secretarial Services",
    "wof:placetype":"venue"
},
  "geometry": {"coordinates":[1.117276,52.14547],"type":"Point"}
}