{
  "type": "Feature",
  "properties": {
    "addr:full":"45 Maxy Rd Bristol City of Bristol BS4 2JQ",
    "addr:housenumber":"45",
    "addr:postcode":"bs4 2jq",
    "addr:street":"Maxy Rd",
    "iso:country":"GB",
    "sg:address":"45 Maxy Rd",
    "sg:city":"Bristol",
    "sg:classifiers":[
        {
            "category":"Professional",
            "type":"Services"
        }
    ],
    "sg:phone":"+44 117 971 1786",
    "sg:postcode":"BS4 2JQ",
    "sg:province":"City of Bristol",
    "sg:tags":[
        "interior",
        "furnishers",
        "designer"
    ],
    "wof:name":"AANDM Design Consultants",
    "wof:placetype":"venue"
},
  "geometry": {"coordinates":[-2.5667219162,51.4362945557],"type":"Point"}
}