{
  "type": "Feature",
  "properties": {
    "addr:full":"22 Ochil Street Wishaw North Lanarkshire ML2 7QA",
    "addr:housenumber":"22",
    "addr:postcode":"ml2 7qa",
    "addr:street":"Ochil Street",
    "iso:country":"GB",
    "sg:address":"22 Ochil Street",
    "sg:city":"Wishaw",
    "sg:classifiers":[
        {
            "category":"Shopping",
            "subcategory":"Department Store",
            "type":"Retail Goods"
        },
        {
            "category":"Food & Beverages",
            "subcategory":"Groceries & Convenience Stores",
            "type":"Retail Goods"
        }
    ],
    "sg:phone":"+44 1698 359813",
    "sg:postcode":"ML2 7QA",
    "sg:province":"North Lanarkshire",
    "wof:name":"SHER MOHAMMAD",
    "wof:placetype":"venue"
},
  "geometry": {"coordinates":[-3.9381189346,55.7778091431],"type":"Point"}
}