{
  "type": "Feature",
  "properties": {
    "iso:country":"GB",
    "sg:address":"33 Fournier St",
    "sg:city":"Whitechapel",
    "sg:classifiers":[
        {
            "category":"Manufacturing",
            "subcategory":"Textiles",
            "type":"Manufacturing & Wholesale Goods"
        }
    ],
    "sg:phone":"+44 20 7426 0745",
    "sg:postcode":"E1 6QE",
    "sg:province":"Greater London",
    "sg:tags":[
        "designer"
    ],
    "wof:name":"M H T Designs",
    "wof:placetype":"venue"
},
  "geometry": {"coordinates":[-0.0722820014,51.5194091797],"type":"Point"}
}