{
  "type": "Feature",
  "properties": {
    "addr:full":"29 Brandon Street Hamilton South Lanarkshire ML3 6DA",
    "addr:housenumber":"29",
    "addr:postcode":"ml3 6da",
    "addr:street":"Brandon Street",
    "iso:country":"GB",
    "sg:address":"29 Brandon Street",
    "sg:city":"Hamilton",
    "sg:classifiers":[
        {
            "category":"Professional",
            "subcategory":"Accounting & Tax Preparation",
            "type":"Services"
        }
    ],
    "sg:phone":"+44 1698 282062",
    "sg:postcode":"ML3 6DA",
    "sg:province":"South Lanarkshire",
    "sg:tags":[
        "accountant"
    ],
    "wof:name":"Sharles",
    "wof:placetype":"venue"
},
  "geometry": {"coordinates":[-4.040379,55.773933],"type":"Point"}
}