{
  "type": "Feature",
  "properties": {
    "iso:country":"GB",
    "sg:address":"Unit B4 Sterling Works, Rainham Road South",
    "sg:city":"Dagenham",
    "sg:classifiers":[
        {
            "category":"Professional",
            "subcategory":"Detective & Security Services",
            "type":"Services"
        }
    ],
    "sg:phone":"+44 20 8593 5355",
    "sg:postcode":"RM10 8TX",
    "sg:province":"Essex",
    "wof:name":"Sterling Secruity",
    "wof:placetype":"venue"
},
  "geometry": {"coordinates":[0.16578,51.543144],"type":"Point"}
}