{
  "type": "Feature",
  "properties": {
    "iso:country":"GB",
    "sg:address":"Rear Of 473 Romford Road, Forest Gate",
    "sg:city":"London",
    "sg:classifiers":[
        {
            "category":"Freight",
            "type":"Transportation"
        }
    ],
    "sg:phone":"+44 20 8470 3366",
    "sg:postcode":"E7 8AD",
    "sg:province":"Greater London",
    "sg:tags":[
        "overseas",
        "shipping",
        "removal"
    ],
    "wof:name":"Express Shipping Services",
    "wof:placetype":"venue"
},
  "geometry": {"coordinates":[0.03614,51.547722],"type":"Point"}
}