{
  "type": "Feature",
  "properties": {
    "addr:full":"Little Leighs Hall, Church La Chelmsford Essex CM3 1PG",
    "addr:postcode":"cm3 1pg",
    "addr:street":"La",
    "iso:country":"GB",
    "sg:address":"Little Leighs Hall, Church La",
    "sg:city":"Chelmsford",
    "sg:classifiers":[
        {
            "category":"Autos & Motor Vehicles",
            "subcategory":"Automobile Sales",
            "type":"Retail Goods"
        }
    ],
    "sg:phone":"+44 1245 362945",
    "sg:postcode":"CM3 1PG",
    "sg:province":"Essex",
    "sg:tags":[
        "car",
        "specialist",
        "sales",
        "classic"
    ],
    "wof:name":"Cottage Classics",
    "wof:placetype":"venue"
},
  "geometry": {"coordinates":[0.4929099977,51.8233146667],"type":"Point"}
}