{
  "type": "Feature",
  "properties": {
    "addr:full":"65 Waterloo Road London Greater London NW2 7TS",
    "addr:housenumber":"65",
    "addr:postcode":"nw2 7ts",
    "addr:street":"Waterloo Road",
    "iso:country":"GB",
    "sg:address":"65 Waterloo Road",
    "sg:city":"London",
    "sg:classifiers":[
        {
            "category":"Shopping",
            "subcategory":"Gifts & Souvenirs",
            "type":"Retail Goods"
        },
        {
            "category":"Wholesale",
            "subcategory":"Stationery",
            "type":"Manufacturing & Wholesale Goods"
        },
        {
            "category":"Retail",
            "subcategory":"Auto Repair",
            "type":"Services"
        }
    ],
    "sg:phone":"+44 20 8450 7834",
    "sg:postcode":"NW2 7TS",
    "sg:province":"Greater London",
    "sg:tags":[
        "modification",
        "garage",
        "giftware"
    ],
    "wof:name":"Opal Crafts Ltd",
    "wof:placetype":"venue"
},
  "geometry": {"coordinates":[-0.2363850027,51.5674133301],"type":"Point"}
}