{
  "type": "Feature",
  "properties": {
    "iso:country":"GB",
    "sg:address":"310 Burgess Road",
    "sg:city":"Southampton",
    "sg:classifiers":[
        {
            "category":"Utilities",
            "subcategory":"Natural Gas",
            "type":"Services"
        }
    ],
    "sg:postcode":"SO16 3BJ",
    "sg:province":"Hampshire",
    "sg:tags":[
        "supplier"
    ],
    "wof:name":"Southampton Bottled Gas Ltd.",
    "wof:placetype":"venue"
},
  "geometry": {"coordinates":[-1.383033,50.938499],"type":"Point"}
}