{
  "type": "Feature",
  "properties": {
    "addr:full":"44 Boswall Parkway Edinburgh City of Edinburgh EH5 2BX",
    "addr:housenumber":"44",
    "addr:postcode":"eh5 2bx",
    "addr:street":"Boswall Parkway",
    "iso:country":"GB",
    "sg:address":"44 Boswall Parkway",
    "sg:city":"Edinburgh",
    "sg:classifiers":[
        {
            "category":"Retail",
            "subcategory":"Storage",
            "type":"Services"
        }
    ],
    "sg:postcode":"EH5 2BX",
    "sg:province":"City of Edinburgh",
    "sg:tags":[
        "household",
        "removal"
    ],
    "wof:name":"Road Runner Removals",
    "wof:placetype":"venue"
},
  "geometry": {"coordinates":[-3.225326,55.975788],"type":"Point"}
}