{
  "type": "Feature",
  "properties": {
    "iso:country":"GB",
    "sg:address":"Moelifor",
    "sg:city":"Llanrhystud",
    "sg:classifiers":[
        {
            "category":"Farming",
            "subcategory":"Livestock Farm",
            "type":"Manufacturing & Wholesale Goods"
        }
    ],
    "sg:phone":"+44 1974 202256",
    "sg:postcode":"SY23 5DW",
    "sg:province":"Ceredigion",
    "sg:tags":[
        "others"
    ],
    "wof:name":"John E Evans",
    "wof:placetype":"venue"
},
  "geometry": {"coordinates":[-4.1406488419,52.3066596985],"type":"Point"}
}