{
  "type": "Feature",
  "properties": {
    "addr:full":"Seven Hills Road Iver Berkshire SL0 0NY",
    "addr:postcode":"sl0 0ny",
    "addr:street":"Seven Hills Road",
    "iso:country":"GB",
    "sg:address":"Seven Hills Road",
    "sg:city":"Iver",
    "sg:classifiers":[
        {
            "category":"Manufacturing",
            "subcategory":"Building Materials",
            "type":"Manufacturing & Wholesale Goods"
        }
    ],
    "sg:postcode":"SL0 0NY",
    "sg:province":"Berkshire",
    "sg:tags":[
        "tile",
        "mnfrs"
    ],
    "wof:name":"Jane Hogben Terracota",
    "wof:placetype":"venue"
},
  "geometry": {"coordinates":[-0.5264769793,51.552406311],"type":"Point"}
}