{
  "type": "Feature",
  "properties": {
    "iso:country":"GB",
    "sg:address":"16 Queen Square",
    "sg:city":"Bristol",
    "sg:classifiers":[
        {
            "category":"Real Estate",
            "subcategory":"Architect",
            "type":"Services"
        }
    ],
    "sg:phone":"+44 117 929 7676",
    "sg:postcode":"BS1 4NT",
    "sg:province":"City of Bristol",
    "wof:name":"Lipfriend Dawson & Partners",
    "wof:placetype":"venue"
},
  "geometry": {"coordinates":[-2.593412,51.450516],"type":"Point"}
}