{
  "type": "Feature",
  "properties": {
    "iso:country":"GB",
    "sg:address":"96 Pisgah Street, Pyle",
    "sg:city":"Bridgend",
    "sg:classifiers":[
        {
            "category":"Fast Food",
            "type":"Food & Drink"
        }
    ],
    "sg:phone":"+44 1656 744193",
    "sg:postcode":"CF33 6DA",
    "sg:province":"Bridgend",
    "sg:tags":[
        "away",
        "take"
    ],
    "wof:name":"Anarkali Tandoori Take Away",
    "wof:placetype":"venue"
},
  "geometry": {"coordinates":[-3.687426,51.53001],"type":"Point"}
}