{
  "type": "Feature",
  "properties": {
    "addr:full":"26 Grange Road, Small Heath Birmingham West Midlands B10 9QN",
    "addr:housenumber":"26",
    "addr:postcode":"b10 9qn",
    "addr:street":"Grange Road",
    "iso:country":"GB",
    "sg:address":"26 Grange Road, Small Heath",
    "sg:city":"Birmingham",
    "sg:classifiers":[
        {
            "category":"Real Estate",
            "subcategory":"Real Estate Agent",
            "type":"Services"
        }
    ],
    "sg:phone":"+44 121 772 7576",
    "sg:postcode":"B10 9QN",
    "sg:province":"West Midlands",
    "wof:name":"Paul & Sons Ltd.",
    "wof:placetype":"venue"
},
  "geometry": {"coordinates":[-1.8599539995,52.472278595],"type":"Point"}
}