{
  "type": "Feature",
  "properties": {
    "iso:country":"GB",
    "sg:address":"2 Alpha Street North",
    "sg:city":"Slough",
    "sg:classifiers":[
        {
            "category":"Shopping",
            "subcategory":"Florist",
            "type":"Retail Goods"
        }
    ],
    "sg:phone":"+44 1753 522659",
    "sg:postcode":"SL1 1RB",
    "sg:province":"Berkshire",
    "wof:name":"Mabs Florists",
    "wof:placetype":"venue"
},
  "geometry": {"coordinates":[-0.5889689922,51.5077400208],"type":"Point"}
}