{
  "type": "Feature",
  "properties": {
    "addr:full":"34 Orchard Street Swansea Neath Port Talbot SA1 5AW",
    "addr:housenumber":"34",
    "addr:postcode":"sa1 5aw",
    "addr:street":"Orchard Street",
    "iso:country":"GB",
    "sg:address":"34 Orchard Street",
    "sg:city":"Swansea",
    "sg:classifiers":[
        {
            "category":"Insurance",
            "subcategory":"Insurance Agent",
            "type":"Services"
        }
    ],
    "sg:postcode":"SA1 5AW",
    "sg:province":"Neath Port Talbot",
    "sg:tags":[
        "broker"
    ],
    "wof:name":"First Line Insurance",
    "wof:placetype":"venue"
},
  "geometry": {"coordinates":[-3.942788,51.623661],"type":"Point"}
}