{
  "type": "Feature",
  "properties": {
    "addr:full":"85 Kings Road, Chelsea London Greater London SW3 4NX",
    "addr:housenumber":"85",
    "addr:postcode":"sw3 4nx",
    "addr:street":"Kings Road",
    "iso:country":"GB",
    "sg:address":"85 Kings Road, Chelsea",
    "sg:city":"London",
    "sg:classifiers":[
        {
            "category":"Shopping",
            "subcategory":"Department Store",
            "type":"Retail Goods"
        }
    ],
    "sg:postcode":"SW3 4NX",
    "sg:province":"Greater London",
    "wof:name":"Marks & Spencer Plc",
    "wof:placetype":"venue"
},
  "geometry": {"coordinates":[-0.1644610018,51.4890289307],"type":"Point"}
}