{
  "type": "Feature",
  "properties": {
    "addr:full":"30 Louisa Dr Girvan South Ayrshire KA26 9AH",
    "addr:housenumber":"30",
    "addr:postcode":"ka26 9ah",
    "addr:street":"Louisa Dr",
    "iso:country":"GB",
    "sg:address":"30 Louisa Dr",
    "sg:city":"Girvan",
    "sg:classifiers":[
        {
            "category":"Travel",
            "subcategory":"Hotels & Motels",
            "type":"Entertainment"
        }
    ],
    "sg:postcode":"KA26 9AH",
    "sg:province":"South Ayrshire",
    "wof:name":"Auchendolly Hotel",
    "wof:placetype":"venue"
},
  "geometry": {"coordinates":[-4.860229969,55.2406845093],"type":"Point"}
}