{
  "type": "Feature",
  "properties": {
    "addr:full":"7 Southview Drive Walton On The Naze Essex CO14 8EP",
    "addr:housenumber":"7",
    "addr:postcode":"co14 8ep",
    "addr:street":"Southview Drive",
    "iso:country":"GB",
    "sg:address":"7 Southview Drive",
    "sg:city":"Walton On The Naze",
    "sg:classifiers":[
        {
            "category":"Autos & Motor Vehicles",
            "subcategory":"Motorcycle Sales",
            "type":"Retail Goods"
        }
    ],
    "sg:phone":"+44 1255 851932",
    "sg:postcode":"CO14 8EP",
    "sg:province":"Essex",
    "sg:tags":[
        "chauffeur",
        "driven",
        "car"
    ],
    "wof:name":"Chauffeured Car Services",
    "wof:placetype":"venue"
},
  "geometry": {"coordinates":[1.266239,51.844494],"type":"Point"}
}