{
  "type": "Feature",
  "properties": {
    "addr:full":"104 Commercial Road London Greater London E1 1NU",
    "addr:housenumber":"104",
    "addr:postcode":"e1 1nu",
    "addr:street":"Commercial Road",
    "iso:country":"GB",
    "sg:address":"104 Commercial Road",
    "sg:city":"London",
    "sg:classifiers":[
        {
            "category":"Wholesale",
            "subcategory":"Apparel",
            "type":"Manufacturing & Wholesale Goods"
        }
    ],
    "sg:phone":"+44 20 7488 3844",
    "sg:postcode":"E1 1NU",
    "sg:province":"Greater London",
    "sg:tags":[
        "w'sale",
        "ladieswear"
    ],
    "wof:name":"Switch (London) Ltd.",
    "wof:placetype":"venue"
},
  "geometry": {"coordinates":[-0.0646980032,51.514705658],"type":"Point"}
}