{
  "type": "Feature",
  "properties": {
    "iso:country":"GB",
    "sg:address":"51 Queen Square",
    "sg:city":"Bristol",
    "sg:classifiers":[
        {
            "category":"Shopping",
            "type":"Retail Goods"
        }
    ],
    "sg:phone":"+44 117 926 2231",
    "sg:postcode":"BS1 4LJ",
    "sg:province":"City of Bristol",
    "sg:tags":[
        "merchant"
    ],
    "wof:name":"Willett & Son (Bristol) Ltd.",
    "wof:placetype":"venue"
},
  "geometry": {"coordinates":[-2.596113,51.450253],"type":"Point"}
}