{
  "type": "Feature",
  "properties": {
    "iso:country":"GB",
    "sg:address":"115 Hamstead Road, Handsworth",
    "sg:city":"Birmingham",
    "sg:classifiers":[
        {
            "category":"Building & Trades",
            "subcategory":"Landscaping Services",
            "type":"Services"
        }
    ],
    "sg:phone":"+44 121 523 7854",
    "sg:postcode":"B20 2BT",
    "sg:province":"West Midlands",
    "sg:tags":[
        "gardening"
    ],
    "wof:name":"The Urban Gardening Co. Ltd.",
    "wof:placetype":"venue"
},
  "geometry": {"coordinates":[-1.919913,52.505215],"type":"Point"}
}