{
  "type": "Feature",
  "properties": {
    "addr:full":"51 Parkinson Street Blackburn Lancashire BB2 4BY",
    "addr:housenumber":"51",
    "addr:postcode":"bb2 4by",
    "addr:street":"Parkinson Street",
    "iso:country":"GB",
    "sg:address":"51 Parkinson Street",
    "sg:city":"Blackburn",
    "sg:classifiers":[
        {
            "category":"Arts & Performance",
            "subcategory":"Music",
            "type":"Entertainment"
        }
    ],
    "sg:phone":"+44 1254 676169",
    "sg:postcode":"BB2 4BY",
    "sg:province":"Lancashire",
    "sg:tags":[
        "mobile",
        "disco"
    ],
    "wof:name":"S D Rock Mobile Disco",
    "wof:placetype":"venue"
},
  "geometry": {"coordinates":[-2.501557,53.734997],"type":"Point"}
}