{
  "type": "Feature",
  "properties": {
    "addr:full":"Clovelly Road Doncaster South Yorkshire DN3 2PE",
    "addr:postcode":"dn3 2pe",
    "addr:street":"Clovelly Road",
    "iso:country":"GB",
    "sg:address":"Clovelly Road",
    "sg:city":"Doncaster",
    "sg:classifiers":[
        {
            "category":"Professional",
            "subcategory":"Testing Lab",
            "type":"Services"
        }
    ],
    "sg:postcode":"DN3 2PE",
    "sg:province":"South Yorkshire",
    "sg:tags":[
        "mot"
    ],
    "wof:name":"D.P. Auto Service Centre",
    "wof:placetype":"venue"
},
  "geometry": {"coordinates":[-1.0695320368,53.5539512634],"type":"Point"}
}