{
  "type": "Feature",
  "properties": {
    "addr:full":"9-10 Angel Place Shopping Centre Bridgwater Somerset TA6 3TQ",
    "addr:housenumber":"9-10",
    "addr:postcode":"ta6 3tq",
    "addr:street":"Angel Place Shopping",
    "iso:country":"GB",
    "sg:address":"9-10 Angel Place Shopping Centre",
    "sg:city":"Bridgwater",
    "sg:classifiers":[
        {
            "category":"Community Center",
            "subcategory":"Social",
            "type":"Public Place"
        }
    ],
    "sg:phone":"+44 1278 422099",
    "sg:postcode":"TA6 3TQ",
    "sg:province":"Somerset",
    "sg:tags":[
        "frozen",
        "food",
        "freezer",
        "centre"
    ],
    "wof:name":"Iceland Foods Plc",
    "wof:placetype":"venue"
},
  "geometry": {"coordinates":[-3.007009,51.128895],"type":"Point"}
}