{
  "type": "Feature",
  "properties": {
    "iso:country":"GB",
    "sg:address":"Britannia House, Mole Street",
    "sg:city":"Birmingham",
    "sg:classifiers":[
        {
            "category":"Food & Beverages",
            "subcategory":"Liquor & Beverages",
            "type":"Retail Goods"
        }
    ],
    "sg:phone":"+44 121 753 2322",
    "sg:postcode":"B11 1XA",
    "sg:province":"West Midlands",
    "sg:tags":[
        "beer",
        "spirit",
        "wines"
    ],
    "wof:name":"Central Beer Co",
    "wof:placetype":"venue"
},
  "geometry": {"coordinates":[-1.874664,52.459412],"type":"Point"}
}