{
  "type": "Feature",
  "properties": {
    "iso:country":"GB",
    "sg:address":"Warwick Row",
    "sg:city":"Coventry",
    "sg:classifiers":[
        {
            "category":"Place Of Worship",
            "type":"Public Place"
        }
    ],
    "sg:phone":"+44 247226050",
    "sg:postcode":"CV1 1EX",
    "sg:province":"West Midlands",
    "wof:name":"Warwick Road United Reformed Church",
    "wof:placetype":"venue"
},
  "geometry": {"coordinates":[-1.513924,52.404915],"type":"Point"}
}