{
  "type": "Feature",
  "properties": {
    "addr:full":"109 Bancroft Hitchin Bedfordshire SG5 1NB",
    "addr:housenumber":"109",
    "addr:postcode":"sg5 1nb",
    "addr:street":"Bancroft",
    "iso:country":"GB",
    "sg:address":"109 Bancroft",
    "sg:city":"Hitchin",
    "sg:classifiers":[
        {
            "category":"Professional",
            "subcategory":"Management & Consulting",
            "type":"Services"
        }
    ],
    "sg:postcode":"SG5 1NB",
    "sg:province":"Bedfordshire",
    "sg:tags":[
        "consultant",
        "business"
    ],
    "wof:name":"European Medical Advisory Services Ltd.",
    "wof:placetype":"venue"
},
  "geometry": {"coordinates":[-0.276771009,51.9500389099],"type":"Point"}
}