{
  "type": "Feature",
  "properties": {
    "addr:full":"29 Colchester Drive Pinner Greater London HA5 1DE",
    "addr:housenumber":"29",
    "addr:postcode":"ha5 1de",
    "addr:street":"Colchester Drive",
    "iso:country":"GB",
    "sg:address":"29 Colchester Drive",
    "sg:city":"Pinner",
    "sg:classifiers":[
        {
            "category":"Building & Trades",
            "subcategory":"Plumbing",
            "type":"Services"
        }
    ],
    "sg:phone":"+44 20 8866 4995",
    "sg:postcode":"HA5 1DE",
    "sg:province":"Greater London",
    "sg:tags":[
        "central",
        "installation",
        "system",
        "servicing",
        "heating"
    ],
    "wof:name":"N T Ward",
    "wof:placetype":"venue"
},
  "geometry": {"coordinates":[-0.3902029991,51.5862121582],"type":"Point"}
}