{
  "type": "Feature",
  "properties": {
    "iso:country":"GB",
    "sg:address":"The Square, Magor",
    "sg:city":"Caldicot",
    "sg:classifiers":[
        {
            "category":"Food & Beverages",
            "subcategory":"Liquor & Beverages",
            "type":"Retail Goods"
        }
    ],
    "sg:phone":"+44 1633 881040",
    "sg:postcode":"NP26 3HY",
    "sg:province":"Monmouthshire",
    "sg:tags":[
        "beer",
        "spirit",
        "wines"
    ],
    "wof:name":"Magor Cellar",
    "wof:placetype":"venue"
},
  "geometry": {"coordinates":[-2.8311800957,51.579990387],"type":"Point"}
}