{
  "type": "Feature",
  "properties": {
    "addr:full":"Dunchurch Infant School, School Street Rugby Warwickshire CV22 6PA",
    "addr:postcode":"cv22 6pa",
    "addr:street":"School Street",
    "iso:country":"GB",
    "sg:address":"Dunchurch Infant School, School Street",
    "sg:city":"Rugby",
    "sg:classifiers":[
        {
            "category":"Education",
            "subcategory":"School",
            "type":"Public Place"
        }
    ],
    "sg:phone":"+44 1788 810292",
    "sg:postcode":"CV22 6PA",
    "sg:province":"Warwickshire",
    "sg:tags":[
        "college",
        "local",
        "authority"
    ],
    "wof:name":"Dunchurch Infant School & Nursery",
    "wof:placetype":"venue"
},
  "geometry": {"coordinates":[-1.2607090473,52.3703384399],"type":"Point"}
}