{
  "type": "Feature",
  "properties": {
    "iso:country":"GB",
    "sg:address":"1 Daish Way, Dodnor Industrial Estate",
    "sg:city":"Newport",
    "sg:classifiers":[
        {
            "category":"Wholesale",
            "subcategory":"Meat",
            "type":"Manufacturing & Wholesale Goods"
        }
    ],
    "sg:phone":"+44 1983 526098",
    "sg:postcode":"PO30 5XB",
    "sg:province":"Isle of Wight",
    "sg:tags":[
        "wholesaler",
        "-"
    ],
    "wof:name":"Hamiltons Fine Foods",
    "wof:placetype":"venue"
},
  "geometry": {"coordinates":[-1.298093,50.709671],"type":"Point"}
}