{
  "type": "Feature",
  "properties": {
    "addr:full":"53 The Calls Leeds West Yorkshire LS2 7EY",
    "addr:housenumber":"53",
    "addr:postcode":"ls2 7ey",
    "addr:street":"The Calls Leeds West",
    "iso:country":"GB",
    "sg:address":"53 The Calls",
    "sg:city":"Leeds",
    "sg:classifiers":[
        {
            "category":"Professional",
            "type":"Services"
        }
    ],
    "sg:phone":"+44 113 244 9220",
    "sg:postcode":"LS2 7EY",
    "sg:province":"West Yorkshire",
    "sg:tags":[
        "exhibition"
    ],
    "wof:name":"Nomadic Display",
    "wof:placetype":"venue"
},
  "geometry": {"coordinates":[-1.5375640392,53.7946357727],"type":"Point"}
}