{
  "type": "Feature",
  "properties": {
    "iso:country":"GB",
    "sg:address":"17b Laithes Lane",
    "sg:city":"Barnsley",
    "sg:classifiers":[
        {
            "category":"Shopping",
            "subcategory":"Baby Store",
            "type":"Retail Goods"
        }
    ],
    "sg:postcode":"S71 3AA",
    "sg:province":"South Yorkshire",
    "sg:tags":[
        "babywear",
        "childrens"
    ],
    "wof:name":"Kids & Co.",
    "wof:placetype":"venue"
},
  "geometry": {"coordinates":[-1.4773739576,53.5797653198],"type":"Point"}
}