{
  "type": "Feature",
  "properties": {
    "addr:full":"45-47 Washington Rd Portsmouth Hampshire PO2 7DH",
    "addr:housenumber":"45-47",
    "addr:postcode":"hampshire po2 7dh",
    "addr:street":"Washington Rd",
    "iso:country":"GB",
    "sg:address":"45-47 Washington Rd",
    "sg:city":"Portsmouth",
    "sg:classifiers":[
        {
            "category":"Personal",
            "type":"Services"
        }
    ],
    "sg:phone":"+44 23 9282 6928",
    "sg:postcode":"PO2 7DH",
    "sg:province":"Hampshire",
    "sg:tags":[
        "tailor"
    ],
    "wof:name":"A F Miller Ladies Tailoring",
    "wof:placetype":"venue"
},
  "geometry": {"coordinates":[-1.079413,50.810326],"type":"Point"}
}