{
  "type": "Feature",
  "properties": {
    "addr:full":"Rivington View, Wood Lane Chorley Lancashire WN6 9SQ",
    "addr:postcode":"wn6 9sq",
    "addr:street":"Rivington View Wood Lane",
    "iso:country":"GB",
    "sg:address":"Rivington View, Wood Lane",
    "sg:city":"Chorley",
    "sg:classifiers":[
        {
            "category":"Manufacturing",
            "subcategory":"Signs",
            "type":"Manufacturing & Wholesale Goods"
        }
    ],
    "sg:phone":"+44 1257 451229",
    "sg:postcode":"WN6 9SQ",
    "sg:province":"Lancashire",
    "sg:tags":[
        "writer"
    ],
    "wof:name":"Paul Ashurst",
    "wof:placetype":"venue"
},
  "geometry": {"coordinates":[-2.7048799992,53.616268158],"type":"Point"}
}