{
  "type": "Feature",
  "properties": {
    "addr:full":"10a Hillside Rd Wellingborough Northamptonshire NN8 4AN",
    "addr:housenumber":"10a",
    "addr:postcode":"nn8 4an",
    "addr:street":"Hillside Rd",
    "iso:country":"GB",
    "sg:address":"10a Hillside Rd",
    "sg:city":"Wellingborough",
    "sg:classifiers":[
        {
            "category":"Shopping",
            "subcategory":"Computers & Home Electronics",
            "type":"Retail Goods"
        }
    ],
    "sg:phone":"+44 1933 383090",
    "sg:postcode":"NN8 4AN",
    "sg:province":"Northamptonshire",
    "wof:name":"CREATIVE INTERIORS",
    "wof:placetype":"venue"
},
  "geometry": {"coordinates":[-0.679929018,52.3122253418],"type":"Point"}
}