{
  "type": "Feature",
  "properties": {
    "addr:full":"Unit 1, Old Chapel Llanfairfechan Conwy LL33 0EB",
    "addr:housenumber":"unit 1",
    "addr:postcode":"ll33 0eb",
    "addr:street":"Old Chapel",
    "iso:country":"GB",
    "sg:address":"Unit 1, Old Chapel",
    "sg:city":"Llanfairfechan",
    "sg:classifiers":[
        {
            "category":"Home & Garden",
            "subcategory":"Furniture",
            "type":"Retail Goods"
        }
    ],
    "sg:phone":"+44 1248 681880",
    "sg:postcode":"LL33 0EB",
    "sg:province":"Conwy",
    "wof:name":"West Coast Factory",
    "wof:placetype":"venue"
},
  "geometry": {"coordinates":[-3.9798369408,53.2522544861],"type":"Point"}
}