{
  "type": "Feature",
  "properties": {
    "iso:country":"GB",
    "sg:address":"Blooms Hall, Malt Office Lane",
    "sg:city":"Halesworth",
    "sg:classifiers":[
        {
            "category":"Home & Garden",
            "subcategory":"Garden Supply",
            "type":"Retail Goods"
        },
        {
            "category":"Farming",
            "subcategory":"Farm",
            "type":"Manufacturing & Wholesale Goods"
        }
    ],
    "sg:postcode":"IP19 0JD",
    "sg:province":"Suffolk",
    "sg:tags":[
        "mixed",
        "bulb",
        "crop",
        "grower"
    ],
    "wof:name":"Gordon W Flatt",
    "wof:placetype":"venue"
},
  "geometry": {"coordinates":[1.4436450005,52.3811683655],"type":"Point"}
}