{
  "type": "Feature",
  "properties": {
    "addr:full":"Exwick Hill Exeter Devon EX4 2BG",
    "addr:postcode":"ex4 2bg",
    "addr:street":"Exwick Hill",
    "iso:country":"GB",
    "sg:address":"Exwick Hill",
    "sg:city":"Exeter",
    "sg:classifiers":[
        {
            "category":"Education",
            "subcategory":"School",
            "type":"Public Place"
        },
        {
            "category":"Government",
            "subcategory":"Office",
            "type":"Public Place"
        }
    ],
    "sg:phone":"+44 1392 273635",
    "sg:postcode":"EX4 2BG",
    "sg:province":"Devon",
    "sg:tags":[
        "local",
        "authority"
    ],
    "wof:name":"Exwick Middle School",
    "wof:placetype":"venue"
},
  "geometry": {"coordinates":[-3.548979044,50.7323455811],"type":"Point"}
}