{
  "type": "Feature",
  "properties": {
    "addr:full":"80-81 Southover Street Brighton East Sussex BN2 9UE",
    "addr:housenumber":"80-81",
    "addr:postcode":"bn2 9ue",
    "addr:street":"Southover Street",
    "iso:country":"GB",
    "sg:address":"80-81 Southover Street",
    "sg:city":"Brighton",
    "sg:classifiers":[
        {
            "category":"Food & Beverages",
            "subcategory":"Supermarket",
            "type":"Retail Goods"
        },
        {
            "category":"Utilities",
            "subcategory":"Natural Gas",
            "type":"Services"
        }
    ],
    "sg:postcode":"BN2 9UE",
    "sg:province":"East Sussex",
    "sg:tags":[
        "firework"
    ],
    "wof:name":"Pyroman Firework Co",
    "wof:placetype":"venue"
},
  "geometry": {"coordinates":[-0.1283649951,50.8278999329],"type":"Point"}
}