{
  "type": "Feature",
  "properties": {
    "addr:full":"80 Ramsbottom Road, Hawkshaw Bury Lancashire BL8 4JS",
    "addr:housenumber":"80",
    "addr:postcode":"bl8 4js",
    "addr:street":"Ramsbottom Road",
    "iso:country":"GB",
    "sg:address":"80 Ramsbottom Road, Hawkshaw",
    "sg:city":"Bury",
    "sg:classifiers":[
        {
            "category":"Home & Garden",
            "subcategory":"Building Materials",
            "type":"Retail Goods"
        }
    ],
    "sg:phone":"+44 1204 852963",
    "sg:postcode":"BL8 4JS",
    "sg:province":"Lancashire",
    "sg:tags":[
        "insulation",
        "installers"
    ],
    "wof:name":"P Warrall",
    "wof:placetype":"venue"
},
  "geometry": {"coordinates":[-2.3714590073,53.6314315796],"type":"Point"}
}