{
  "type": "Feature",
  "properties": {
    "addr:full":"West Farm, 2 Beckside Brigg Lincolnshire DN20 9EQ",
    "addr:housenumber":"2",
    "addr:postcode":"dn20 9eq",
    "addr:street":"Farm;Brigg",
    "iso:country":"GB",
    "sg:address":"West Farm, 2 Beckside",
    "sg:city":"Brigg",
    "sg:classifiers":[
        {
            "category":"Home & Garden",
            "subcategory":"Garden Supply",
            "type":"Retail Goods"
        }
    ],
    "sg:phone":"+44 1724 732540",
    "sg:postcode":"DN20 9EQ",
    "sg:province":"Lincolnshire",
    "sg:tags":[
        "bulb",
        "grower"
    ],
    "wof:name":"E W Ogg & Sons",
    "wof:placetype":"venue"
},
  "geometry": {"coordinates":[-0.4848789871,53.552986145],"type":"Point"}
}