{
  "type": "Feature",
  "properties": {
    "addr:full":"Unit 13, Blackburn Industrial Estate, Kinellar Aberdeen Aberdeen City AB21 0RX",
    "addr:housenumber":"unit 13",
    "addr:postcode":"ab21 0rx",
    "addr:street":"Blackburn Industrial Estate",
    "iso:country":"GB",
    "sg:address":"Unit 13, Blackburn Industrial Estate, Kinellar",
    "sg:city":"Aberdeen",
    "sg:classifiers":[
        {
            "category":"Building & Trades",
            "subcategory":"Landscaping Services",
            "type":"Services"
        }
    ],
    "sg:phone":"+44 1224 790404",
    "sg:postcode":"AB21 0RX",
    "sg:province":"Aberdeen City",
    "sg:tags":[
        "horticultural",
        "consultant"
    ],
    "wof:name":"Liebherr Great Britain Ltd.",
    "wof:placetype":"venue"
},
  "geometry": {"coordinates":[-2.3451750278,57.2167320251],"type":"Point"}
}