{
  "type": "Feature",
  "properties": {
    "addr:full":"The Whittern, Lyonshall Kington Herefordshire HR5 3JA",
    "addr:postcode":"hr5 3ja",
    "addr:street":"Lyonshall",
    "iso:country":"GB",
    "sg:address":"The Whittern, Lyonshall",
    "sg:city":"Kington",
    "sg:classifiers":[
        {
            "category":"Farming",
            "subcategory":"Poultry Farm",
            "type":"Manufacturing & Wholesale Goods"
        }
    ],
    "sg:phone":"+44 1544 340241",
    "sg:postcode":"HR5 3JA",
    "sg:province":"Herefordshire",
    "sg:tags":[
        "game"
    ],
    "wof:name":"The Whittern Farms Ltd.",
    "wof:placetype":"venue"
},
  "geometry": {"coordinates":[-3.0294780731,52.20362854],"type":"Point"}
}