{
  "type": "Feature",
  "properties": {
    "iso:country":"GB",
    "sg:address":"Old Hall Farm, Clockface Road, Bold",
    "sg:city":"Widnes",
    "sg:classifiers":[
        {
            "category":"Farming",
            "subcategory":"Farm",
            "type":"Manufacturing & Wholesale Goods"
        }
    ],
    "sg:phone":"+44 1744 812438",
    "sg:postcode":"WA8 3XJ",
    "sg:province":"Cheshire",
    "sg:tags":[
        "mixed",
        "crop"
    ],
    "wof:name":"John Billington",
    "wof:placetype":"venue"
},
  "geometry": {"coordinates":[-2.69107,53.408039],"type":"Point"}
}