{
  "type": "Feature",
  "properties": {
    "iso:country":"GB",
    "sg:address":"13 Broad Street, New Radnor",
    "sg:city":"Presteigne",
    "sg:classifiers":[
        {
            "category":"Shopping",
            "subcategory":"Department Store",
            "type":"Retail Goods"
        },
        {
            "category":"Food & Beverages",
            "subcategory":"Groceries & Convenience Stores",
            "type":"Retail Goods"
        }
    ],
    "sg:phone":"+44 1544 350251",
    "sg:postcode":"LD8 2SP",
    "sg:province":"Herefordshire",
    "wof:name":"The Stores",
    "wof:placetype":"venue"
},
  "geometry": {"coordinates":[-3.1537880898,52.2398376465],"type":"Point"}
}