{
  "type": "Feature",
  "properties": {
    "addr:full":"Grassrigg Farm, Killington Sedbergh Cumbria LA10 5EW",
    "addr:postcode":"la10 5ew",
    "iso:country":"GB",
    "sg:address":"Grassrigg Farm, Killington",
    "sg:city":"Sedbergh",
    "sg:classifiers":[
        {
            "category":"Farming",
            "subcategory":"Livestock Farm",
            "type":"Manufacturing & Wholesale Goods"
        }
    ],
    "sg:postcode":"LA10 5EW",
    "sg:province":"Cumbria",
    "sg:tags":[
        "others"
    ],
    "wof:name":"A Stainton",
    "wof:placetype":"venue"
},
  "geometry": {"coordinates":[-2.527837,54.321945],"type":"Point"}
}