{
  "type": "Feature",
  "properties": {
    "iso:country":"GB",
    "sg:address":"Main Street, East Challow",
    "sg:city":"Wantage",
    "sg:classifiers":[
        {
            "category":"Bars & Pubs",
            "type":"Food & Drink"
        }
    ],
    "sg:postcode":"OX12 9SW",
    "sg:province":"Berkshire",
    "sg:tags":[
        "pubs",
        "inn"
    ],
    "wof:name":"D A Glass & J Glass",
    "wof:placetype":"venue"
},
  "geometry": {"coordinates":[-1.4533859491,51.5935554504],"type":"Point"}
}