{
  "type": "Feature",
  "properties": {
    "addr:full":"16 Haweswater Close Bristol Gloucestershire BS30 5XS",
    "addr:housenumber":"16",
    "addr:postcode":"bs30 5xs",
    "addr:street":"Haweswater Close",
    "iso:country":"GB",
    "sg:address":"16 Haweswater Close",
    "sg:city":"Bristol",
    "sg:classifiers":[
        {
            "category":"Manufacturing",
            "subcategory":"Petroleum Products",
            "type":"Manufacturing & Wholesale Goods"
        }
    ],
    "sg:phone":"+44 117 961 4305",
    "sg:postcode":"BS30 5XS",
    "sg:province":"Gloucestershire",
    "sg:tags":[
        "double",
        "glazing"
    ],
    "wof:name":"Window Co Ltd",
    "wof:placetype":"venue"
},
  "geometry": {"coordinates":[-2.463129,51.454288],"type":"Point"}
}