{
  "type": "Feature",
  "properties": {
    "addr:full":"31 Tindale Crescent Bishop Auckland Durham DL14 9SX",
    "addr:housenumber":"31",
    "addr:postcode":"dl14 9sx",
    "addr:street":"Tindale Crescent",
    "iso:country":"GB",
    "sg:address":"31 Tindale Crescent",
    "sg:city":"Bishop Auckland",
    "sg:classifiers":[
        {
            "category":"Retail",
            "subcategory":"Funeral Services",
            "type":"Services"
        }
    ],
    "sg:phone":"+44 1388 662368",
    "sg:postcode":"DL14 9SX",
    "sg:province":"Durham",
    "wof:name":"Auckland Memorials",
    "wof:placetype":"venue"
},
  "geometry": {"coordinates":[-1.69159,54.641281],"type":"Point"}
}