{
  "type": "Feature",
  "properties": {
    "iso:country":"GB",
    "sg:address":"2nd Floor, 31-32 High St",
    "sg:city":"Brighton",
    "sg:classifiers":[
        {
            "category":"Military Area",
            "subcategory":"Air Force Base",
            "type":"Public Place"
        }
    ],
    "sg:phone":"+44 1273 696007",
    "sg:postcode":"BN2 1RP",
    "sg:province":"East Sussex",
    "sg:tags":[
        "fire",
        "protection"
    ],
    "wof:name":"Dorgard Ltd",
    "wof:placetype":"venue"
},
  "geometry": {"coordinates":[-0.1319209933,50.8219566345],"type":"Point"}
}