{
  "type": "Feature",
  "properties": {
    "iso:country":"GB",
    "sg:address":"37 High St",
    "sg:city":"Thornton Heath",
    "sg:classifiers":[
        {
            "category":"Shopping",
            "subcategory":"Baby Store",
            "type":"Retail Goods"
        }
    ],
    "sg:postcode":"CR7 8RU",
    "sg:province":"Surrey",
    "sg:tags":[
        "nursery",
        "accessory"
    ],
    "wof:name":"Max Best for Less Babywear",
    "wof:placetype":"venue"
},
  "geometry": {"coordinates":[-0.094445,51.398312],"type":"Point"}
}