{
  "type": "Feature",
  "properties": {
    "addr:full":"20 Trinity Trading Est, Tribune Dr Sittingbourne Kent ME10 2PG",
    "addr:housenumber":"20",
    "addr:postcode":"me10 2pg",
    "addr:street":"Tribune Dr",
    "iso:country":"GB",
    "sg:address":"20 Trinity Trading Est, Tribune Dr",
    "sg:city":"Sittingbourne",
    "sg:classifiers":[
        {
            "category":"Professional",
            "type":"Services"
        }
    ],
    "sg:phone":"+44 1795 477227",
    "sg:postcode":"ME10 2PG",
    "sg:province":"Kent",
    "sg:tags":[
        "shopfitters"
    ],
    "wof:name":"Bushbase Ltd",
    "wof:placetype":"venue"
},
  "geometry": {"coordinates":[0.7379099727,51.3408203125],"type":"Point"}
}