{
  "type": "Feature",
  "properties": {
    "iso:country":"GB",
    "sg:address":"Unit 11 Eleventh Avenue, Team Valley Trading Estate",
    "sg:city":"Gateshead",
    "sg:classifiers":[
        {
            "category":"Shopping",
            "subcategory":"Computers & Home Electronics",
            "type":"Retail Goods"
        }
    ],
    "sg:phone":"+44 191 482 4061",
    "sg:postcode":"NE11 0JR",
    "sg:province":"Tyne and Wear",
    "sg:tags":[
        "electrical"
    ],
    "wof:name":"B D C Independents",
    "wof:placetype":"venue"
},
  "geometry": {"coordinates":[-1.609354,54.923454],"type":"Point"}
}