{
  "type": "Feature",
  "properties": {
    "addr:full":"126 Sandbanks Road Poole Dorset BH14 8DA",
    "addr:housenumber":"126",
    "addr:postcode":"bh14 8da",
    "addr:street":"Sandbanks Road",
    "iso:country":"GB",
    "sg:address":"126 Sandbanks Road",
    "sg:city":"Poole",
    "sg:classifiers":[
        {
            "category":"Travel",
            "subcategory":"Hotels & Motels",
            "type":"Entertainment"
        }
    ],
    "sg:phone":"+44 1929 423088",
    "sg:postcode":"BH14 8DA",
    "sg:province":"Dorset",
    "sg:tags":[
        "house",
        "guest"
    ],
    "wof:name":"The Little Haven Guest House",
    "wof:placetype":"venue"
},
  "geometry": {"coordinates":[-1.953584,50.717663],"type":"Point"}
}