{
  "type": "Feature",
  "properties": {
    "iso:country":"GB",
    "sg:address":"19 Lambridge Place",
    "sg:city":"Bath",
    "sg:classifiers":[
        {
            "category":"Banks & Credit Unions",
            "subcategory":"Financial Services",
            "type":"Services"
        }
    ],
    "sg:phone":"+44 1225 336486",
    "sg:postcode":"BA1 6RU",
    "sg:province":"Bath and North East Somerset",
    "sg:tags":[
        "adviser"
    ],
    "wof:name":"Oliver Financial Planning",
    "wof:placetype":"venue"
},
  "geometry": {"coordinates":[-2.344867,51.39669],"type":"Point"}
}