{
  "type": "Feature",
  "properties": {
    "addr:full":"16 Rollestone Street Salisbury Wiltshire SP1 1DX",
    "addr:housenumber":"16",
    "addr:postcode":"sp1 1dx",
    "addr:street":"Rollestone Street",
    "iso:country":"GB",
    "sg:address":"16 Rollestone Street",
    "sg:city":"Salisbury",
    "sg:classifiers":[
        {
            "category":"Organizations",
            "subcategory":"Community Association",
            "type":"Services"
        }
    ],
    "sg:phone":"+44 1722 416300",
    "sg:postcode":"SP1 1DX",
    "sg:province":"Wiltshire",
    "sg:tags":[
        "society",
        "housing"
    ],
    "wof:name":"Shafesbury Housing Association",
    "wof:placetype":"venue"
},
  "geometry": {"coordinates":[-1.7932540178,51.0709571838],"type":"Point"}
}