{
  "type": "Feature",
  "properties": {
    "iso:country":"GB",
    "sg:address":"Magnolia Lake, Mamhead",
    "sg:city":"Exeter",
    "sg:classifiers":[
        {
            "category":"Communications",
            "subcategory":"Film & Video Production",
            "type":"Services"
        }
    ],
    "sg:phone":"+44 1626 888433",
    "sg:postcode":"EX6 8HG",
    "sg:province":"Devon",
    "sg:tags":[
        "tv",
        "studio"
    ],
    "wof:name":"Cine Power International Ltd",
    "wof:placetype":"venue"
},
  "geometry": {"coordinates":[-3.502994,50.620491],"type":"Point"}
}