{
  "type": "Feature",
  "properties": {
    "addr:full":"49 Orchard Street Weston-super-mare Somerset BS23 1RJ",
    "addr:housenumber":"49",
    "addr:postcode":"bs23 1rj",
    "addr:street":"Orchard Street",
    "iso:country":"GB",
    "sg:address":"49 Orchard Street",
    "sg:city":"Weston-super-mare",
    "sg:classifiers":[
        {
            "category":"Home & Garden",
            "subcategory":"Home Furnishings",
            "type":"Retail Goods"
        }
    ],
    "sg:phone":"+44 1934 412360",
    "sg:postcode":"BS23 1RJ",
    "sg:province":"Somerset",
    "sg:tags":[
        "awning",
        "canopy",
        "blinds"
    ],
    "wof:name":"Ashbury Blinds",
    "wof:placetype":"venue"
},
  "geometry": {"coordinates":[-2.975899,51.349236],"type":"Point"}
}