{
  "type": "Feature",
  "properties": {
    "addr:full":"3 Blake Street York North Yorkshire YO1 8QJ",
    "addr:housenumber":"3",
    "addr:postcode":"yo1 8qj",
    "addr:street":"Blake Street",
    "iso:country":"GB",
    "sg:address":"3 Blake Street",
    "sg:city":"York",
    "sg:classifiers":[
        {
            "category":"Communications",
            "subcategory":"Film & Video Production",
            "type":"Services"
        }
    ],
    "sg:phone":"+44 1904 655282",
    "sg:postcode":"YO1 8QJ",
    "sg:province":"North Yorkshire",
    "sg:tags":[
        "tv"
    ],
    "wof:name":"House & Son (Electric) Ltd.",
    "wof:placetype":"venue"
},
  "geometry": {"coordinates":[-1.084629,53.960892],"type":"Point"}
}