{
  "type": "Feature",
  "properties": {
    "addr:full":"8-10 Cricket Grn Mitcham Greater London CR4 4LA",
    "addr:housenumber":"8-10",
    "addr:postcode":"cr4 4la",
    "addr:street":"Cricket Grn",
    "iso:country":"GB",
    "sg:address":"8-10 Cricket Grn",
    "sg:city":"Mitcham",
    "sg:classifiers":[
        {
            "category":"Professional",
            "type":"Services"
        },
        {
            "category":"Professional",
            "subcategory":"Lawyer & Legal Services",
            "type":"Services"
        }
    ],
    "sg:phone":"+44 20 8648 4044",
    "sg:postcode":"CR4 4LA",
    "sg:province":"Greater London",
    "sg:tags":[
        "conveyancing"
    ],
    "wof:name":"Mason Collins",
    "wof:placetype":"venue"
},
  "geometry": {"coordinates":[-0.1657589972,51.3995780945],"type":"Point"}
}