{
  "type": "Feature",
  "properties": {
    "iso:country":"GB",
    "sg:address":"11 Lawford Rd",
    "sg:city":"Rugby",
    "sg:classifiers":[
        {
            "category":"Autos & Motor Vehicles",
            "subcategory":"Motorcycle Sales",
            "type":"Retail Goods"
        }
    ],
    "sg:phone":"+44 1788 562288",
    "sg:postcode":"CV21 2DZ",
    "sg:province":"Warwickshire",
    "sg:tags":[
        "chauffeur",
        "driven",
        "car"
    ],
    "wof:name":"Dashtarget Ltd",
    "wof:placetype":"venue"
},
  "geometry": {"coordinates":[-1.2669509649,52.371055603],"type":"Point"}
}