{
  "type": "Feature",
  "properties": {
    "iso:country":"GB",
    "sg:address":"13 West Clo",
    "sg:city":"Polegate",
    "sg:classifiers":[
        {
            "category":"Building & Trades",
            "subcategory":"Plumbing",
            "type":"Services"
        }
    ],
    "sg:postcode":"BN26 6EQ",
    "sg:province":"East Sussex",
    "sg:tags":[
        "central",
        "heating"
    ],
    "wof:name":"Lippiatt,P M,",
    "wof:placetype":"venue"
},
  "geometry": {"coordinates":[0.249416,50.82428],"type":"Point"}
}