{
  "type": "Feature",
  "properties": {
    "addr:full":"Campsie Road, Torrance Glasgow East Dunbartonshire G64 4BP",
    "addr:postcode":"g64 4bp",
    "addr:street":"Campsie Road",
    "iso:country":"GB",
    "sg:address":"Campsie Road, Torrance",
    "sg:city":"Glasgow",
    "sg:classifiers":[
        {
            "category":"Autos & Motor Vehicles",
            "subcategory":"Recreational Vehicle Sales",
            "type":"Retail Goods"
        },
        {
            "category":"Retail",
            "subcategory":"Auto Repair",
            "type":"Services"
        }
    ],
    "sg:phone":"+44 1360 620544",
    "sg:postcode":"G64 4BP",
    "sg:province":"East Dunbartonshire",
    "sg:tags":[
        "truck",
        "repairer",
        "van",
        "bodybuilder"
    ],
    "wof:name":"Ferrymill Motors",
    "wof:placetype":"venue"
},
  "geometry": {"coordinates":[-4.1952490807,55.9469223022],"type":"Point"}
}