{
  "type": "Feature",
  "properties": {
    "addr:full":"2 Drakes Cross, Hollywood, Wythall Birmingham Worcestershire B47 5DX",
    "addr:housenumber":"2",
    "addr:postcode":"b47 5dx",
    "addr:street":"Drakes Cross",
    "iso:country":"GB",
    "sg:address":"2 Drakes Cross, Hollywood, Wythall",
    "sg:city":"Birmingham",
    "sg:classifiers":[
        {
            "category":"Cinema",
            "subcategory":"Movie Rental",
            "type":"Entertainment"
        }
    ],
    "sg:phone":"+44 1564 822678",
    "sg:postcode":"B47 5DX",
    "sg:province":"Worcestershire",
    "sg:tags":[
        "video",
        "library"
    ],
    "wof:name":"Aphrodite Video",
    "wof:placetype":"venue"
},
  "geometry": {"coordinates":[-1.88372,52.385239],"type":"Point"}
}