{
  "type": "Feature",
  "properties": {
    "iso:country":"GB",
    "sg:address":"42 Copnor Road",
    "sg:city":"Portsmouth",
    "sg:classifiers":[
        {
            "category":"Food & Beverages",
            "subcategory":"Meat & Fish",
            "type":"Retail Goods"
        }
    ],
    "sg:phone":"+44 23 9265 5864",
    "sg:postcode":"PO3 5AH",
    "sg:province":"Hampshire",
    "sg:tags":[
        "chip"
    ],
    "wof:name":"The New Seahorse Fishbar",
    "wof:placetype":"venue"
},
  "geometry": {"coordinates":[-1.063735,50.810291],"type":"Point"}
}