{
  "type": "Feature",
  "properties": {
    "addr:full":"Acton Bridge, Weaverham Northwich Cheshire CW8 3QE",
    "addr:postcode":"cw8 3qe",
    "addr:street":"Acton Bridge",
    "iso:country":"GB",
    "sg:address":"Acton Bridge, Weaverham",
    "sg:city":"Northwich",
    "sg:classifiers":[
        {
            "category":"Place Of Worship",
            "type":"Public Place"
        }
    ],
    "sg:phone":"+44 1606 75002",
    "sg:postcode":"CW8 3QE",
    "sg:province":"Cheshire",
    "wof:name":"Acton Bridge Methodist Church",
    "wof:placetype":"venue"
},
  "geometry": {"coordinates":[-2.6139440536,53.2775497437],"type":"Point"}
}