{
  "type": "Feature",
  "properties": {
    "iso:country":"GB",
    "sg:address":"89 Moorland Rd",
    "sg:city":"Stockport",
    "sg:classifiers":[
        {
            "category":"Professional",
            "subcategory":"Art Services",
            "type":"Services"
        }
    ],
    "sg:phone":"+44 161 419 9699",
    "sg:postcode":"SK2 7AX",
    "sg:province":"Cheshire",
    "sg:tags":[
        "framing"
    ],
    "wof:name":"Framework",
    "wof:placetype":"venue"
},
  "geometry": {"coordinates":[-2.141274929,53.3871040344],"type":"Point"}
}