{
  "type": "Feature",
  "properties": {
    "addr:full":"The Benyon Centre, Commercial Rd Walsall West Midlands WS2 7NQ",
    "addr:postcode":"ws2 7nq",
    "addr:street":"Commercial Rd",
    "iso:country":"GB",
    "sg:address":"The Benyon Centre, Commercial Rd",
    "sg:city":"Walsall",
    "sg:classifiers":[
        {
            "category":"Professional",
            "subcategory":"Computer Services",
            "type":"Services"
        }
    ],
    "sg:phone":"+44 1922 491414",
    "sg:postcode":"WS2 7NQ",
    "sg:province":"West Midlands",
    "sg:tags":[
        "system",
        "software"
    ],
    "wof:name":"Flair Mark Ltd",
    "wof:placetype":"venue"
},
  "geometry": {"coordinates":[-2.01425,52.60915],"type":"Point"}
}