{
  "type": "Feature",
  "properties": {
    "addr:full":"80 High Street, Lees Oldham Lancashire OL4 5AA",
    "addr:housenumber":"80",
    "addr:postcode":"ol4 5aa",
    "addr:street":"High Street",
    "iso:country":"GB",
    "sg:address":"80 High Street, Lees",
    "sg:city":"Oldham",
    "sg:classifiers":[
        {
            "category":"Home & Garden",
            "subcategory":"Hardware",
            "type":"Retail Goods"
        }
    ],
    "sg:phone":"+44 161 678 7749",
    "sg:postcode":"OL4 5AA",
    "sg:province":"Lancashire",
    "sg:tags":[
        "retailer",
        "diy"
    ],
    "wof:name":"Lees Home & Garden",
    "wof:placetype":"venue"
},
  "geometry": {"coordinates":[-2.072651,53.538105],"type":"Point"}
}