{
  "type": "Feature",
  "properties": {
    "iso:country":"GB",
    "sg:address":"332 Christchurch Road, West Parley",
    "sg:city":"Ferndown",
    "sg:classifiers":[
        {
            "category":"Retail",
            "subcategory":"Repair Shop",
            "type":"Services"
        }
    ],
    "sg:postcode":"BH22 8SN",
    "sg:province":"Dorset",
    "sg:tags":[
        "maintenance"
    ],
    "wof:name":"N & P Coombes",
    "wof:placetype":"venue"
},
  "geometry": {"coordinates":[-1.874924,50.781219],"type":"Point"}
}