{
  "type": "Feature",
  "properties": {
    "addr:full":"64 Broadstone Road, Reddish Stockport Cheshire SK5 7AR",
    "addr:housenumber":"64",
    "addr:postcode":"sk5 7ar",
    "addr:street":"Broadstone Road",
    "iso:country":"GB",
    "sg:address":"64 Broadstone Road, Reddish",
    "sg:city":"Stockport",
    "sg:classifiers":[
        {
            "category":"Home & Garden",
            "subcategory":"Hardware",
            "type":"Retail Goods"
        }
    ],
    "sg:phone":"+44 161 432 2022",
    "sg:postcode":"SK5 7AR",
    "sg:province":"Cheshire",
    "sg:tags":[
        "retailer",
        "diy"
    ],
    "wof:name":"Little Ashford D I Y",
    "wof:placetype":"venue"
},
  "geometry": {"coordinates":[-2.1635799408,53.4357872009],"type":"Point"}
}