{
  "type": "Feature",
  "properties": {
    "addr:full":"249 Lower Addiscombe Rd Croydon Surrey CR0 6AD",
    "addr:housenumber":"249",
    "addr:postcode":"cr0 6ad",
    "addr:street":"Lower Addiscombe Rd",
    "iso:country":"GB",
    "sg:address":"249 Lower Addiscombe Rd",
    "sg:city":"Croydon",
    "sg:classifiers":[
        {
            "category":"Food & Beverages",
            "subcategory":"Liquor & Beverages",
            "type":"Retail Goods"
        }
    ],
    "sg:phone":"+44 20 8662 1070",
    "sg:postcode":"CR0 6AD",
    "sg:province":"Surrey",
    "sg:tags":[
        "beer",
        "spirit",
        "wines"
    ],
    "wof:name":"Victoria Wine",
    "wof:placetype":"venue"
},
  "geometry": {"coordinates":[-0.072503,51.380611],"type":"Point"}
}