{
  "type": "Feature",
  "properties": {
    "iso:country":"GB",
    "sg:address":"Ion Path, Road 3",
    "sg:city":"Winsford",
    "sg:classifiers":[
        {
            "category":"Shopping",
            "type":"Retail Goods"
        }
    ],
    "sg:phone":"+44 1606 548100",
    "sg:postcode":"CW7 3BX",
    "sg:province":"Cheshire",
    "sg:tags":[
        "med",
        "scientific",
        "apparatus"
    ],
    "wof:name":"Thermo Elemental Ltd.",
    "wof:placetype":"venue"
},
  "geometry": {"coordinates":[-2.490227,53.192623],"type":"Point"}
}