{
  "type": "Feature",
  "properties": {
    "iso:country":"GB",
    "sg:address":"3 Yorke Street",
    "sg:city":"Burnley",
    "sg:classifiers":[
        {
            "category":"Retail",
            "subcategory":"Laundry & Dry Cleaning",
            "type":"Services"
        }
    ],
    "sg:phone":"+44 1282 831081",
    "sg:postcode":"BB11 1HD",
    "sg:province":"Lancashire",
    "sg:tags":[
        "alteration"
    ],
    "wof:name":"Janet's Alterations",
    "wof:placetype":"venue"
},
  "geometry": {"coordinates":[-2.2441139221,53.7880134583],"type":"Point"}
}