{
  "type": "Feature",
  "properties": {
    "iso:country":"GB",
    "sg:address":"Cleveland, Green Street",
    "sg:city":"Sunbury-on-thames",
    "sg:classifiers":[
        {
            "category":"Taxi",
            "type":"Transportation"
        }
    ],
    "sg:phone":"+44 1932 785987",
    "sg:postcode":"TW16 6QJ",
    "sg:province":"Surrey",
    "sg:tags":[
        "mini",
        "cab"
    ],
    "wof:name":"Anthony's",
    "wof:placetype":"venue"
},
  "geometry": {"coordinates":[-0.411769,51.404179],"type":"Point"}
}