{
  "type": "Feature",
  "properties": {
    "iso:country":"GB",
    "sg:address":"167 Chelmsford Road, Shenfield",
    "sg:city":"Brentwood",
    "sg:classifiers":[
        {
            "category":"Professional",
            "subcategory":"Detective & Security Services",
            "type":"Services"
        },
        {
            "category":"Building & Trades",
            "subcategory":"Construction",
            "type":"Services"
        }
    ],
    "sg:phone":"+44 1277 260120",
    "sg:postcode":"CM15 8SA",
    "sg:province":"Essex",
    "sg:tags":[
        "builder",
        "activity"
    ],
    "wof:name":"Granville Construction Co. Ltd.",
    "wof:placetype":"venue"
},
  "geometry": {"coordinates":[0.332181,51.640575],"type":"Point"}
}