{
  "type": "Feature",
  "properties": {
    "iso:country":"GB",
    "sg:address":"Crystal House, Birley Street",
    "sg:city":"Preston",
    "sg:classifiers":[
        {
            "category":"Professional",
            "subcategory":"Lawyer & Legal Services",
            "type":"Services"
        }
    ],
    "sg:phone":"+44 1772 561663",
    "sg:postcode":"PR1 2AQ",
    "sg:province":"Lancashire",
    "sg:tags":[
        "solicitor"
    ],
    "wof:name":"Birchall Blackburn",
    "wof:placetype":"venue"
},
  "geometry": {"coordinates":[-2.698613,53.758606],"type":"Point"}
}