{
  "type": "Feature",
  "properties": {
    "addr:full":"Pennyfarthing, Bush End, Takeley Bishops Stortford Essex CM22 6NN",
    "addr:postcode":"cm22 6nn",
    "addr:street":"Pennyfarthing Bush End",
    "iso:country":"GB",
    "sg:address":"Pennyfarthing, Bush End, Takeley",
    "sg:city":"Bishops Stortford",
    "sg:classifiers":[
        {
            "category":"Professional",
            "subcategory":"Management & Consulting",
            "type":"Services"
        }
    ],
    "sg:phone":"+44 1279 870505",
    "sg:postcode":"CM22 6NN",
    "sg:province":"Essex",
    "sg:tags":[
        "consultant",
        "business"
    ],
    "wof:name":"Bastin Associates",
    "wof:placetype":"venue"
},
  "geometry": {"coordinates":[0.2668350041,51.8677711487],"type":"Point"}
}