{
  "type": "Feature",
  "properties": {
    "addr:full":"Station Road, Llanrug Caernarfon Gwynedd LL55 4BE",
    "addr:postcode":"ll55 4be",
    "addr:street":"Station Road",
    "iso:country":"GB",
    "sg:address":"Station Road, Llanrug",
    "sg:city":"Caernarfon",
    "sg:classifiers":[
        {
            "category":"Health Services",
            "subcategory":"Nursing And Care Facility",
            "type":"Services"
        },
        {
            "category":"Social Services",
            "subcategory":"Retirement Home",
            "type":"Services"
        }
    ],
    "sg:postcode":"LL55 4BE",
    "sg:province":"Gwynedd",
    "sg:tags":[
        "residential"
    ],
    "wof:name":"Foelas Residential Home Ltd",
    "wof:placetype":"venue"
},
  "geometry": {"coordinates":[-4.1930837631,53.1479797363],"type":"Point"}
}