{
  "type": "Feature",
  "properties": {
    "addr:full":"Magnet House, 32 Victoria Street Bristol City of Bristol BS1 6BS",
    "addr:housenumber":"32",
    "addr:postcode":"bs1 6bs",
    "addr:street":"Victoria Street",
    "iso:country":"GB",
    "sg:address":"Magnet House, 32 Victoria Street",
    "sg:city":"Bristol",
    "sg:classifiers":[
        {
            "category":"Home & Garden",
            "subcategory":"Building Materials",
            "type":"Retail Goods"
        }
    ],
    "sg:phone":"+44 117 927 7708",
    "sg:postcode":"BS1 6BS",
    "sg:province":"City of Bristol",
    "sg:tags":[
        "ventilator",
        "ventilation",
        "system"
    ],
    "wof:name":"Satchwell Control Systems Ltd.",
    "wof:placetype":"venue"
},
  "geometry": {"coordinates":[-2.5887749195,51.4526405334],"type":"Point"}
}