{
  "type": "Feature",
  "properties": {
    "addr:full":"99 Bearwood Hill Road Burton-on-trent Derbyshire DE15 0JP",
    "addr:housenumber":"99",
    "addr:postcode":"de15 0jp",
    "addr:street":"Bearwood Hill Road",
    "iso:country":"GB",
    "sg:address":"99 Bearwood Hill Road",
    "sg:city":"Burton-on-trent",
    "sg:classifiers":[
        {
            "category":"Personal",
            "subcategory":"Beauty Salon",
            "type":"Services"
        }
    ],
    "sg:postcode":"DE15 0JP",
    "sg:province":"Derbyshire",
    "sg:tags":[
        "unisex",
        "hairdresser"
    ],
    "wof:name":"Hairloom",
    "wof:placetype":"venue"
},
  "geometry": {"coordinates":[-1.607102,52.806725],"type":"Point"}
}