{
  "type": "Feature",
  "properties": {
    "iso:country":"GB",
    "sg:address":"2 Sandgate",
    "sg:city":"Penrith",
    "sg:classifiers":[
        {
            "category":"Arts & Performance",
            "subcategory":"Arts Center",
            "type":"Entertainment"
        },
        {
            "category":"Professional",
            "subcategory":"Management & Consulting",
            "type":"Services"
        }
    ],
    "sg:phone":"+44 1768 899444",
    "sg:postcode":"CA11 7TP",
    "sg:province":"Cumbria",
    "sg:tags":[
        "promotion",
        "performing",
        "music"
    ],
    "sg:website":"http://www.edenarts.co.uk",
    "wof:name":"Eden Arts Trust",
    "wof:placetype":"venue"
},
  "geometry": {"coordinates":[-2.750979,54.665409],"type":"Point"}
}