{
  "type": "Feature",
  "properties": {
    "addr:full":"O C M House, St Peter's Road Droitwich Worcestershire WR9 7BJ",
    "addr:postcode":"wr9 7bj",
    "addr:street":"O C;St Peter'S Road",
    "iso:country":"GB",
    "sg:address":"O C M House, St Peter's Road",
    "sg:city":"Droitwich",
    "sg:classifiers":[
        {
            "category":"Professional",
            "subcategory":"Computer Services",
            "type":"Services"
        }
    ],
    "sg:phone":"+44 1905 795001",
    "sg:postcode":"WR9 7BJ",
    "sg:province":"Worcestershire",
    "sg:tags":[
        "system",
        "software"
    ],
    "wof:name":"O C M Business Systems Ltd.",
    "wof:placetype":"venue"
},
  "geometry": {"coordinates":[-2.1518499851,52.2619285583],"type":"Point"}
}