{
  "type": "Feature",
  "properties": {
    "iso:country":"GB",
    "sg:address":"3 Main Street, Spittal",
    "sg:city":"Berwick-upon-tweed",
    "sg:classifiers":[
        {
            "category":"Sports & Exercise",
            "subcategory":"Gym",
            "type":"Entertainment"
        }
    ],
    "sg:phone":"+44 1289 302773",
    "sg:postcode":"TD15 1QY",
    "sg:province":"Northumberland",
    "sg:tags":[
        "club",
        "fitness",
        "health",
        "centre"
    ],
    "wof:name":"LANCE ROBSON",
    "wof:placetype":"venue"
},
  "geometry": {"coordinates":[-2.007024,55.771435],"type":"Point"}
}