{
  "type": "Feature",
  "properties": {
    "addr:full":"Dental Surgery, Pantiles, Portsmouth Road Kingston-upon-thames Greater London KT1 2LY",
    "addr:postcode":"kt1 2ly",
    "addr:street":"Pantiles Portsmouth Road",
    "iso:country":"GB",
    "sg:address":"Dental Surgery, Pantiles, Portsmouth Road",
    "sg:city":"Kingston-upon-thames",
    "sg:classifiers":[
        {
            "category":"Health Services",
            "subcategory":"Dentist",
            "type":"Services"
        }
    ],
    "sg:postcode":"KT1 2LY",
    "sg:province":"Greater London",
    "wof:name":"H B Brien",
    "wof:placetype":"venue"
},
  "geometry": {"coordinates":[-0.3075099885,51.4035186768],"type":"Point"}
}