{
  "type": "Feature",
  "properties": {
    "addr:full":"60 Blackstock Road London Greater London N4 2DW",
    "addr:housenumber":"60",
    "addr:postcode":"n4 2dw",
    "addr:street":"Blackstock Road",
    "iso:country":"GB",
    "sg:address":"60 Blackstock Road",
    "sg:city":"London",
    "sg:classifiers":[
        {
            "category":"Health Services",
            "subcategory":"Dentist",
            "type":"Services"
        }
    ],
    "sg:phone":"+44 20 7226 1372",
    "sg:postcode":"N4 2DW",
    "sg:province":"Greater London",
    "wof:name":"Blackstock Dental Care",
    "wof:placetype":"venue"
},
  "geometry": {"coordinates":[-0.1026630029,51.5634422302],"type":"Point"}
}