{
  "type": "Feature",
  "properties": {
    "addr:full":"130 Nelson Road Central Great Yarmouth Norfolk NR30 2JY",
    "addr:housenumber":"130",
    "addr:postcode":"nr30 2jy",
    "addr:street":"Nelson Road Central Great Yarmouth",
    "iso:country":"GB",
    "sg:address":"130 Nelson Road Central",
    "sg:city":"Great Yarmouth",
    "sg:classifiers":[
        {
            "category":"Bars & Pubs",
            "type":"Food & Drink"
        }
    ],
    "sg:postcode":"NR30 2JY",
    "sg:province":"Norfolk",
    "sg:tags":[
        "pubs",
        "inn"
    ],
    "wof:name":"The Colonel H",
    "wof:placetype":"venue"
},
  "geometry": {"coordinates":[1.732674,52.604492],"type":"Point"}
}