{
  "type": "Feature",
  "properties": {
    "iso:country":"GB",
    "sg:address":"Cross House, High Street, Easington Lane",
    "sg:city":"Houghton-le-spring",
    "sg:classifiers":[
        {
            "category":"Professional",
            "subcategory":"Art Services",
            "type":"Services"
        }
    ],
    "sg:phone":"+44 191 526 4267",
    "sg:postcode":"DH5 0JR",
    "sg:province":"Durham",
    "sg:tags":[
        "photographer"
    ],
    "wof:name":"Thomas Stephenson Photographers",
    "wof:placetype":"venue"
},
  "geometry": {"coordinates":[-1.437484026,54.80884552],"type":"Point"}
}