{
  "type": "Feature",
  "properties": {
    "addr:full":"79 Cocker Road Enfield Greater London EN1 4QH",
    "addr:housenumber":"79",
    "addr:postcode":"en1 4qh",
    "addr:street":"Cocker Road",
    "iso:country":"GB",
    "sg:address":"79 Cocker Road",
    "sg:city":"Enfield",
    "sg:classifiers":[
        {
            "category":"Social Services",
            "subcategory":"Adult Care",
            "type":"Services"
        }
    ],
    "sg:phone":"+44 1992 760352",
    "sg:postcode":"EN1 4QH",
    "sg:province":"Greater London",
    "sg:tags":[
        "housing",
        "sheltered"
    ],
    "wof:name":"Sheltered Housing",
    "wof:placetype":"venue"
},
  "geometry": {"coordinates":[-0.047811,51.674828],"type":"Point"}
}