{
  "type": "Feature",
  "properties": {
    "addr:full":"92 Crown Lane, Southgate London Greater London N14 5EN",
    "addr:housenumber":"92",
    "addr:postcode":"n14 5en",
    "addr:street":"Crown Lane",
    "iso:country":"GB",
    "sg:address":"92 Crown Lane, Southgate",
    "sg:city":"London",
    "sg:classifiers":[
        {
            "category":"Shopping",
            "subcategory":"Crafts & Fabrics",
            "type":"Retail Goods"
        }
    ],
    "sg:phone":"+44 20 8886 7273",
    "sg:postcode":"N14 5EN",
    "sg:province":"Greater London",
    "sg:tags":[
        "material",
        "art"
    ],
    "wof:name":"Rodwins Toys & Crafts",
    "wof:placetype":"venue"
},
  "geometry": {"coordinates":[-0.128714,51.632008],"type":"Point"}
}