{
  "type": "Feature",
  "properties": {
    "iso:country":"GB",
    "sg:address":"4 Morehouse Bldg(s), Pontmorlais",
    "sg:city":"Merthyr Tydfil",
    "sg:classifiers":[
        {
            "category":"Retail",
            "subcategory":"Laundry & Dry Cleaning",
            "type":"Services"
        }
    ],
    "sg:phone":"+44 1685 722933",
    "sg:postcode":"CF47 8UH",
    "sg:province":"Merthyr Tydfil",
    "sg:tags":[
        "launderette"
    ],
    "wof:name":"Dot Cotton's",
    "wof:placetype":"venue"
},
  "geometry": {"coordinates":[-3.376464,51.750439],"type":"Point"}
}