{
  "type": "Feature",
  "properties": {
    "iso:country":"GB",
    "sg:address":"Station Square",
    "sg:city":"Dingwall",
    "sg:classifiers":[
        {
            "category":"Cafe",
            "type":"Food & Drink"
        }
    ],
    "sg:phone":"+44 1349 865894",
    "sg:postcode":"IV15 9JD",
    "sg:province":"Highland",
    "sg:tags":[
        "tea",
        "snack",
        "bar",
        "room"
    ],
    "wof:name":"Station Tearoom & Craft Shop",
    "wof:placetype":"venue"
},
  "geometry": {"coordinates":[-4.4314479828,57.5961799622],"type":"Point"}
}