{
  "type": "Feature",
  "properties": {
    "iso:country":"GB",
    "sg:address":"155 Lower High Street",
    "sg:city":"Stourbridge",
    "sg:classifiers":[
        {
            "category":"Health Services",
            "subcategory":"Podiatrist",
            "type":"Services"
        }
    ],
    "sg:postcode":"DY8 1TT",
    "sg:province":"Staffordshire",
    "sg:tags":[
        "podiatrists",
        "chiropodist"
    ],
    "wof:name":"Paul & Louise Swiercz",
    "wof:placetype":"venue"
},
  "geometry": {"coordinates":[-2.147962,52.457943],"type":"Point"}
}