{
  "type": "Feature",
  "properties": {
    "addr:full":"Pennard House, 5 Eardley Road Sevenoaks Kent TN13 1XY",
    "addr:housenumber":"5",
    "addr:postcode":"tn13 1xy",
    "addr:street":"Eardley Road",
    "iso:country":"GB",
    "sg:address":"Pennard House, 5 Eardley Road",
    "sg:city":"Sevenoaks",
    "sg:classifiers":[
        {
            "category":"Transit Center",
            "subcategory":"Passenger",
            "type":"Transportation"
        }
    ],
    "sg:phone":"+44 1732 452344",
    "sg:postcode":"TN13 1XY",
    "sg:province":"Kent",
    "sg:tags":[
        "boarding",
        "kennel",
        "catteries"
    ],
    "wof:name":"Pennard Veterinary Group",
    "wof:placetype":"venue"
},
  "geometry": {"coordinates":[0.188443,51.273605],"type":"Point"}
}