{
  "type": "Feature",
  "properties": {
    "addr:full":"Highmeadow Farm, Chivery Tring Buckinghamshire HP23 6LD",
    "addr:postcode":"hp23 6ld",
    "addr:street":"Chivery",
    "iso:country":"GB",
    "sg:address":"Highmeadow Farm, Chivery",
    "sg:city":"Tring",
    "sg:classifiers":[
        {
            "category":"Farming",
            "subcategory":"Livestock Farm",
            "type":"Manufacturing & Wholesale Goods"
        }
    ],
    "sg:postcode":"HP23 6LD",
    "sg:province":"Buckinghamshire",
    "sg:tags":[
        "others"
    ],
    "wof:name":"H Payne & Sons Ltd.",
    "wof:placetype":"venue"
},
  "geometry": {"coordinates":[-0.694434,51.762299],"type":"Point"}
}