{
  "type": "Feature",
  "properties": {
    "iso:country":"GB",
    "sg:address":"14 Gwynne Park Avenue",
    "sg:city":"Woodford Green",
    "sg:classifiers":[
        {
            "category":"Health Services",
            "subcategory":"Health Practitioner",
            "type":"Services"
        }
    ],
    "sg:phone":"+44 20 8505 8453",
    "sg:postcode":"IG8 8AB",
    "sg:province":"Essex",
    "sg:tags":[
        "psychologist"
    ],
    "wof:name":"Occupational & Personality Testing",
    "wof:placetype":"venue"
},
  "geometry": {"coordinates":[0.0577870011,51.6052932739],"type":"Point"}
}