{
  "type": "Feature",
  "properties": {
    "iso:country":"GB",
    "sg:address":"Chardleigh House, Chardleigh Grn, Wadeford",
    "sg:city":"Chard",
    "sg:classifiers":[
        {
            "category":"Professional",
            "subcategory":"Art Services",
            "type":"Services"
        }
    ],
    "sg:phone":"+44 1460 65611",
    "sg:postcode":"TA20 3AJ",
    "sg:province":"Devon",
    "sg:tags":[
        "carver",
        "sculptor"
    ],
    "wof:name":"Gonzalez & Harms",
    "wof:placetype":"venue"
},
  "geometry": {"coordinates":[-2.9828848839,50.8906898499],"type":"Point"}
}