{
  "type": "Feature",
  "properties": {
    "addr:full":"Teasel Road Attleborough Norfolk NR17 1XX",
    "addr:postcode":"nr17 1xx",
    "addr:street":"Teasel Road",
    "iso:country":"GB",
    "sg:address":"Teasel Road",
    "sg:city":"Attleborough",
    "sg:classifiers":[
        {
            "category":"Real Estate",
            "subcategory":"Developer",
            "type":"Services"
        },
        {
            "category":"Building & Trades",
            "subcategory":"Construction",
            "type":"Services"
        }
    ],
    "sg:phone":"+44 1953 454108",
    "sg:postcode":"NR17 1XX",
    "sg:province":"Norfolk",
    "sg:tags":[
        "residential",
        "builder",
        "property"
    ],
    "wof:name":"WILCON HOMES ANGLIA LTD",
    "wof:placetype":"venue"
},
  "geometry": {"coordinates":[1.0017950535,52.5144500732],"type":"Point"}
}