{
  "type": "Feature",
  "properties": {
    "iso:country":"GB",
    "sg:address":"Great Western House, 34 Isambard Brunel Road",
    "sg:city":"Portsmouth",
    "sg:classifiers":[
        {
            "category":"Education",
            "subcategory":"Special Training",
            "type":"Public Place"
        }
    ],
    "sg:phone":"+44 23 9242 1850",
    "sg:postcode":"PO1 2RJ",
    "sg:province":"Hampshire",
    "sg:tags":[
        "product",
        "centre"
    ],
    "wof:name":"R P S City Training",
    "wof:placetype":"venue"
},
  "geometry": {"coordinates":[-1.0896199942,50.7972755432],"type":"Point"}
}