{
  "type": "Feature",
  "properties": {
    "addr:full":"29a Longmead Shaftesbury Dorset SP7 8PL",
    "addr:housenumber":"29a",
    "addr:postcode":"sp7 8pl",
    "addr:street":"Longmead",
    "iso:country":"GB",
    "sg:address":"29a Longmead",
    "sg:city":"Shaftesbury",
    "sg:classifiers":[
        {
            "category":"Home & Garden",
            "subcategory":"Furniture",
            "type":"Retail Goods"
        }
    ],
    "sg:postcode":"SP7 8PL",
    "sg:province":"Dorset",
    "wof:name":"Janet Leah Furnishings",
    "wof:placetype":"venue"
},
  "geometry": {"coordinates":[-2.190876,51.009705],"type":"Point"}
}