{
  "type": "Feature",
  "properties": {
    "addr:full":"27 Old St London Greater London EC1V 9HL",
    "addr:housenumber":"27",
    "addr:postcode":"ec1v 9hl",
    "addr:street":"Old St",
    "iso:country":"GB",
    "sg:address":"27 Old St",
    "sg:city":"London",
    "sg:classifiers":[
        {
            "category":"Banks & Credit Unions",
            "subcategory":"Bureau De Change",
            "type":"Services"
        }
    ],
    "sg:postcode":"EC1V 9HL",
    "sg:province":"Greater London",
    "sg:tags":[
        "town",
        "consultant",
        "planning"
    ],
    "wof:name":"Civix Ltd",
    "wof:placetype":"venue"
},
  "geometry": {"coordinates":[-0.0976179987,51.5237503052],"type":"Point"}
}