{
  "type": "Feature",
  "properties": {
    "addr:full":"Whitethorn Lane Letchworth Hertfordshire SG6 2DN",
    "addr:postcode":"sg6 2dn",
    "addr:street":"Whitethorn Lane",
    "iso:country":"GB",
    "sg:address":"Whitethorn Lane",
    "sg:city":"Letchworth",
    "sg:classifiers":[
        {
            "category":"Arena",
            "subcategory":"Sports Club",
            "type":"Entertainment"
        }
    ],
    "sg:phone":"+44 1462 684530",
    "sg:postcode":"SG6 2DN",
    "sg:province":"Hertfordshire",
    "wof:name":"Letchworth Corner Sports Club",
    "wof:placetype":"venue"
},
  "geometry": {"coordinates":[-0.222243,51.972549],"type":"Point"}
}