{
  "type": "Feature",
  "properties": {
    "iso:country":"GB",
    "sg:address":"5 Southernhay West",
    "sg:city":"Exeter",
    "sg:classifiers":[
        {
            "category":"Real Estate",
            "subcategory":"Real Estate Agent",
            "type":"Services"
        }
    ],
    "sg:phone":"+44 1392 412086",
    "sg:postcode":"EX1 1JG",
    "sg:province":"Devon",
    "wof:name":"Pow,T,",
    "wof:placetype":"venue"
},
  "geometry": {"coordinates":[-3.527649,50.72184],"type":"Point"}
}