{
  "type": "Feature",
  "properties": {
    "addr:full":"26 Waterloo Rd Wolverhampton West Midlands WV1 4BL",
    "addr:housenumber":"26",
    "addr:postcode":"wv1 4bl",
    "addr:street":"Waterloo Rd",
    "iso:country":"GB",
    "sg:address":"26 Waterloo Rd",
    "sg:city":"Wolverhampton",
    "sg:classifiers":[
        {
            "category":"Professional",
            "subcategory":"Lawyer & Legal Services",
            "type":"Services"
        }
    ],
    "sg:phone":"+44 1902 426222",
    "sg:postcode":"WV1 4BL",
    "sg:province":"West Midlands",
    "sg:tags":[
        "barrister"
    ],
    "wof:name":"Jonathan Gidney",
    "wof:placetype":"venue"
},
  "geometry": {"coordinates":[-2.1322290897,52.5868797302],"type":"Point"}
}