{
  "type": "Feature",
  "properties": {
    "addr:full":"Clearwater, Bourton Gillingham Dorset SP8 5DB",
    "addr:postcode":"sp8 5db",
    "iso:country":"GB",
    "sg:address":"Clearwater, Bourton",
    "sg:city":"Gillingham",
    "sg:classifiers":[
        {
            "category":"Home & Garden",
            "subcategory":"Building Materials",
            "type":"Retail Goods"
        }
    ],
    "sg:phone":"+44 1747 840516",
    "sg:postcode":"SP8 5DB",
    "sg:province":"Dorset",
    "sg:tags":[
        "polythene",
        "plastic"
    ],
    "wof:name":"O'Neil Roe Susan",
    "wof:placetype":"venue"
},
  "geometry": {"coordinates":[-2.322488,51.07539],"type":"Point"}
}