{
  "type": "Feature",
  "properties": {
    "addr:full":"40a West Street Alresford Hampshire SO24 9AU",
    "addr:housenumber":"40a",
    "addr:postcode":"so24 9au",
    "addr:street":"West Street",
    "iso:country":"GB",
    "sg:address":"40a West Street",
    "sg:city":"Alresford",
    "sg:classifiers":[
        {
            "category":"Shopping",
            "subcategory":"Comic Books",
            "type":"Retail Goods"
        }
    ],
    "sg:phone":"+44 1962 732200",
    "sg:postcode":"SO24 9AU",
    "sg:province":"Hampshire",
    "sg:tags":[
        "jeweller"
    ],
    "wof:name":"M P Stoodley & Son",
    "wof:placetype":"venue"
},
  "geometry": {"coordinates":[-1.1635400057,51.0902252197],"type":"Point"}
}