{
  "type": "Feature",
  "properties": {
    "addr:full":"4 White Hill, Kinver Stourbridge Shropshire DY7 6AD",
    "addr:housenumber":"4",
    "addr:postcode":"dy7 6ad",
    "addr:street":"White Hill",
    "iso:country":"GB",
    "sg:address":"4 White Hill, Kinver",
    "sg:city":"Stourbridge",
    "sg:classifiers":[
        {
            "category":"Government",
            "subcategory":"Post Office",
            "type":"Public Place"
        }
    ],
    "sg:postcode":"DY7 6AD",
    "sg:province":"Shropshire",
    "wof:name":"Potters Cross Post Office",
    "wof:placetype":"venue"
},
  "geometry": {"coordinates":[-2.235827,52.454514],"type":"Point"}
}