{
  "type": "Feature",
  "properties": {
    "iso:country":"GB",
    "sg:address":"85 Winchester Road, Countesthorpe",
    "sg:city":"Leicester",
    "sg:classifiers":[
        {
            "category":"Building & Trades",
            "subcategory":"Construction",
            "type":"Services"
        }
    ],
    "sg:phone":"+44 116 277 6678",
    "sg:postcode":"LE8 5PP",
    "sg:province":"Leicestershire",
    "sg:tags":[
        "dry",
        "plastering",
        "plasterers",
        "lining",
        "related",
        "screeders"
    ],
    "wof:name":"Roland G Shilton",
    "wof:placetype":"venue"
},
  "geometry": {"coordinates":[-1.158079,52.557777],"type":"Point"}
}