{
  "type": "Feature",
  "properties": {
    "addr:full":"2 Blackthorne Close Dudley West Midlands DY1 3TH",
    "addr:housenumber":"2",
    "addr:postcode":"3th",
    "addr:street":"Blackthorne Close",
    "iso:country":"GB",
    "sg:address":"2 Blackthorne Close",
    "sg:city":"Dudley",
    "sg:classifiers":[
        {
            "category":"Building & Trades",
            "subcategory":"Plumbing",
            "type":"Services"
        }
    ],
    "sg:phone":"+44 1902 672070",
    "sg:postcode":"DY1 3TH",
    "sg:province":"West Midlands",
    "sg:tags":[
        "heating"
    ],
    "wof:name":"C.W Baines Plmber",
    "wof:placetype":"venue"
},
  "geometry": {"coordinates":[-2.108494997,52.525188446],"type":"Point"}
}