{
  "type": "Feature",
  "properties": {
    "addr:full":"2 Tamar Street Torpoint Cornwall PL11 2AW",
    "addr:housenumber":"2",
    "addr:postcode":"pl11 2aw",
    "addr:street":"Tamar Street",
    "iso:country":"GB",
    "sg:address":"2 Tamar Street",
    "sg:city":"Torpoint",
    "sg:classifiers":[
        {
            "category":"Recreation",
            "subcategory":"Amusement Park",
            "type":"Entertainment"
        }
    ],
    "sg:phone":"+44 1752 814247",
    "sg:postcode":"PL11 2AW",
    "sg:province":"Cornwall",
    "sg:tags":[
        "arcade",
        "activity"
    ],
    "wof:name":"Tamar Leisure Spot",
    "wof:placetype":"venue"
},
  "geometry": {"coordinates":[-4.194478,50.375275],"type":"Point"}
}