{
  "type": "Feature",
  "properties": {
    "addr:full":"66 Woods Avenue Hatfield Hertfordshire AL10 8LY",
    "addr:housenumber":"66",
    "addr:postcode":"al10 8ly",
    "addr:street":"Woods Avenue",
    "iso:country":"GB",
    "sg:address":"66 Woods Avenue",
    "sg:city":"Hatfield",
    "sg:classifiers":[
        {
            "category":"Professional",
            "subcategory":"Engineering",
            "type":"Services"
        }
    ],
    "sg:postcode":"AL10 8LY",
    "sg:province":"Hertfordshire",
    "sg:tags":[
        "contractor",
        "electrical",
        "engineer"
    ],
    "wof:name":"L O L Electrical Services",
    "wof:placetype":"venue"
},
  "geometry": {"coordinates":[-0.229963,51.753841],"type":"Point"}
}