{
  "type": "Feature",
  "properties": {
    "addr:full":"9 Mansel St Carmarthen Carmarthenshire SA31 1PX",
    "addr:housenumber":"9",
    "addr:postcode":"sa31 1px",
    "addr:street":"Mansel St",
    "iso:country":"GB",
    "sg:address":"9 Mansel St",
    "sg:city":"Carmarthen",
    "sg:classifiers":[
        {
            "category":"Shopping",
            "subcategory":"Books",
            "type":"Retail Goods"
        }
    ],
    "sg:phone":"+44 1267 235676",
    "sg:postcode":"SA31 1PX",
    "sg:province":"Carmarthenshire",
    "sg:tags":[
        "second-hand"
    ],
    "wof:name":"Carmarthen Books",
    "wof:placetype":"venue"
},
  "geometry": {"coordinates":[-4.310092926,51.8566474915],"type":"Point"}
}