{
  "type": "Feature",
  "properties": {
    "addr:full":"62-64 Sherlock Avenue St Helens Lancashire WA11 0PQ",
    "addr:housenumber":"62-64",
    "addr:postcode":"wa11 0pq",
    "addr:street":"Sherlock Avenue",
    "iso:country":"GB",
    "sg:address":"62-64 Sherlock Avenue",
    "sg:city":"St Helens",
    "sg:classifiers":[
        {
            "category":"Food & Beverages",
            "subcategory":"Fruits & Vegetables",
            "type":"Retail Goods"
        }
    ],
    "sg:phone":"+44 1744 605789",
    "sg:postcode":"WA11 0PQ",
    "sg:province":"Lancashire",
    "sg:tags":[
        "greengrocer"
    ],
    "wof:name":"Haydock Mini Market",
    "wof:placetype":"venue"
},
  "geometry": {"coordinates":[-2.6607139111,53.4693908691],"type":"Point"}
}