{
  "type": "Feature",
  "properties": {
    "addr:full":"Kardelton Ho Vansittart Rd Est Windsor Berkshire SL4 1SE",
    "addr:postcode":"sl4 1se",
    "addr:street":"Vansittart Rd",
    "iso:country":"GB",
    "sg:address":"Kardelton Ho Vansittart Rd Est",
    "sg:city":"Windsor",
    "sg:classifiers":[
        {
            "category":"Professional",
            "subcategory":"Engineering",
            "type":"Services"
        },
        {
            "category":"Real Estate",
            "subcategory":"Architect",
            "type":"Services"
        }
    ],
    "sg:postcode":"SL4 1SE",
    "sg:province":"Berkshire",
    "sg:tags":[
        "consulting",
        "engineer"
    ],
    "wof:name":"Engineering and Business Network Ltd",
    "wof:placetype":"venue"
},
  "geometry": {"coordinates":[-0.612228,51.481735],"type":"Point"}
}