{
  "type": "Feature",
  "properties": {
    "addr:full":"174 White Lion Rd Amersham Buckinghamshire HP7 9NL",
    "addr:housenumber":"174",
    "addr:postcode":"hp7 9nl",
    "addr:street":"White Lion Rd",
    "iso:country":"GB",
    "sg:address":"174 White Lion Rd",
    "sg:city":"Amersham",
    "sg:classifiers":[
        {
            "category":"Retail",
            "subcategory":"Veterinary Services",
            "type":"Services"
        }
    ],
    "sg:phone":"+44 1494 782001",
    "sg:postcode":"HP7 9NL",
    "sg:province":"Buckinghamshire",
    "sg:tags":[
        "surgeon"
    ],
    "wof:name":"Wheel House Veterinary Hospital",
    "wof:placetype":"venue"
},
  "geometry": {"coordinates":[-0.571222,51.668686],"type":"Point"}
}