{
  "type": "Feature",
  "properties": {
    "iso:country":"GB",
    "sg:address":"193 Queens Rd",
    "sg:city":"Hastings",
    "sg:classifiers":[
        {
            "category":"Professional",
            "subcategory":"Lawyer & Legal Services",
            "type":"Services"
        }
    ],
    "sg:phone":"+44 1424 426666",
    "sg:postcode":"TN34 1RG",
    "sg:province":"East Sussex",
    "sg:tags":[
        "solicitor"
    ],
    "wof:name":"John Lester",
    "wof:placetype":"venue"
},
  "geometry": {"coordinates":[0.582791,50.858479],"type":"Point"}
}