{
  "type": "Feature",
  "properties": {
    "iso:country":"GB",
    "sg:address":"3 Moorgate Rd",
    "sg:city":"Rotherham",
    "sg:classifiers":[
        {
            "category":"Sports & Exercise",
            "subcategory":"Gym",
            "type":"Entertainment"
        }
    ],
    "sg:phone":"+44 1709 371903",
    "sg:postcode":"S60 2EN",
    "sg:province":"South Yorkshire",
    "sg:tags":[
        "fitness",
        "health",
        "centre"
    ],
    "wof:name":"Contour Plus",
    "wof:placetype":"venue"
},
  "geometry": {"coordinates":[-1.354097,53.427483],"type":"Point"}
}