{
  "type": "Feature",
  "properties": {
    "addr:full":"25 Shore Road Skelmorlie North Ayrshire PA17 5EH",
    "addr:housenumber":"25",
    "addr:postcode":"pa17 5eh",
    "addr:street":"Shore Road",
    "iso:country":"GB",
    "sg:address":"25 Shore Road",
    "sg:city":"Skelmorlie",
    "sg:classifiers":[
        {
            "category":"Travel",
            "subcategory":"Hotels & Motels",
            "type":"Entertainment"
        }
    ],
    "sg:phone":"+44 1475 521036",
    "sg:postcode":"PA17 5EH",
    "sg:province":"North Ayrshire",
    "wof:name":"Redcliffe House Hotel",
    "wof:placetype":"venue"
},
  "geometry": {"coordinates":[-4.8895010948,55.8614006042],"type":"Point"}
}