{
  "type": "Feature",
  "properties": {
    "iso:country":"GB",
    "sg:address":"54 Deveraux Drive",
    "sg:city":"Wallasey",
    "sg:classifiers":[
        {
            "category":"Shopping",
            "subcategory":"Photographic Equipment",
            "type":"Retail Goods"
        }
    ],
    "sg:phone":"+44 151 639 8664",
    "sg:postcode":"CH44 4DL",
    "sg:province":"Merseyside",
    "wof:name":"Walker Cameras",
    "wof:placetype":"venue"
},
  "geometry": {"coordinates":[-3.037969,53.413559],"type":"Point"}
}