{
  "type": "Feature",
  "properties": {
    "addr:full":"16 Mead Close, East Huntspill Highbridge Somerset TA9 3NF",
    "addr:housenumber":"16",
    "addr:postcode":"ta9 3nf",
    "addr:street":"Mead Close East",
    "iso:country":"GB",
    "sg:address":"16 Mead Close, East Huntspill",
    "sg:city":"Highbridge",
    "sg:classifiers":[
        {
            "category":"Building & Trades",
            "subcategory":"Construction",
            "type":"Services"
        }
    ],
    "sg:postcode":"TA9 3NF",
    "sg:province":"Somerset",
    "sg:tags":[
        "builder"
    ],
    "wof:name":"A P Builders",
    "wof:placetype":"venue"
},
  "geometry": {"coordinates":[-2.939535,51.205383],"type":"Point"}
}