{
  "type": "Feature",
  "properties": {
    "iso:country":"GB",
    "sg:address":"21 Commercial Street",
    "sg:city":"Maesteg",
    "sg:classifiers":[
        {
            "category":"Shopping",
            "subcategory":"Luggage & Leather Goods",
            "type":"Retail Goods"
        }
    ],
    "sg:phone":"+44 1656 737763",
    "sg:postcode":"CF34 9DF",
    "sg:province":"Bridgend",
    "sg:tags":[
        "shop",
        "leathergoods"
    ],
    "wof:name":"Harding's",
    "wof:placetype":"venue"
},
  "geometry": {"coordinates":[-3.6589279175,51.6079902649],"type":"Point"}
}