{
  "type": "Feature",
  "properties": {
    "addr:full":"33 Green Lane, Tupton Chesterfield Derbyshire S42 6XW",
    "addr:housenumber":"33",
    "addr:postcode":"s42 6xw",
    "addr:street":"Green Lane",
    "iso:country":"GB",
    "sg:address":"33 Green Lane, Tupton",
    "sg:city":"Chesterfield",
    "sg:classifiers":[
        {
            "category":"Bus Charters",
            "type":"Transportation"
        },
        {
            "category":"Military Area",
            "subcategory":"Air Force Base",
            "type":"Public Place"
        }
    ],
    "sg:phone":"+44 1246 864873",
    "sg:postcode":"S42 6XW",
    "sg:province":"Derbyshire",
    "sg:tags":[
        "taxi",
        "mini",
        "hire",
        "leasing",
        "private"
    ],
    "wof:name":"Mick's Minibus Hire",
    "wof:placetype":"venue"
},
  "geometry": {"coordinates":[-1.4091559649,53.1901817322],"type":"Point"}
}