{
  "type": "Feature",
  "properties": {
    "iso:country":"GB",
    "sg:address":"2 Cressy Road",
    "sg:city":"Alfreton",
    "sg:classifiers":[
        {
            "category":"Personal",
            "subcategory":"Beauty Salon",
            "type":"Services"
        }
    ],
    "sg:postcode":"DE55 7BR",
    "sg:province":"Derbyshire",
    "wof:name":"The Beauty Room",
    "wof:placetype":"venue"
},
  "geometry": {"coordinates":[-1.3853019476,53.0973510742],"type":"Point"}
}