{
  "type": "Feature",
  "properties": {
    "iso:country":"GB",
    "sg:address":"3 Cherry Tree Farm, Fauld",
    "sg:city":"Burton-on-trent",
    "sg:classifiers":[
        {
            "category":"Professional",
            "subcategory":"Management & Consulting",
            "type":"Services"
        },
        {
            "category":"Organizations",
            "subcategory":"Community Association",
            "type":"Services"
        }
    ],
    "sg:postcode":"DE13 9HS",
    "sg:province":"Derbyshire",
    "sg:tags":[
        "consultant",
        "relation",
        "public",
        "business"
    ],
    "wof:name":"Hunt,Carole,",
    "wof:placetype":"venue"
},
  "geometry": {"coordinates":[-1.71561,52.857269],"type":"Point"}
}