{
  "type": "Feature",
  "properties": {
    "iso:country":"GB",
    "sg:address":"Cambridge Road, New Wimpole",
    "sg:city":"Royston",
    "sg:classifiers":[
        {
            "category":"Personal",
            "subcategory":"Skin Care",
            "type":"Services"
        }
    ],
    "sg:phone":"+44 1223 208085",
    "sg:postcode":"SG8 5QD",
    "sg:province":"Bedfordshire",
    "sg:tags":[
        "surgery",
        "cosmetic"
    ],
    "wof:name":"Cambridge Private Hospital",
    "wof:placetype":"venue"
},
  "geometry": {"coordinates":[-0.028766,52.13221],"type":"Point"}
}