{
  "type": "Feature",
  "properties": {
    "iso:country":"GB",
    "sg:address":"Golf Course Road",
    "sg:city":"Ayr",
    "sg:classifiers":[
        {
            "category":"Sports & Exercise",
            "subcategory":"Golf",
            "type":"Entertainment"
        }
    ],
    "sg:phone":"+44 1465 811471",
    "sg:postcode":"KA26 9GD",
    "sg:province":"South Ayrshire",
    "sg:tags":[
        "club",
        "course"
    ],
    "wof:name":"Brunston Castle Golf Club",
    "wof:placetype":"venue"
},
  "geometry": {"coordinates":[-4.782769,55.26059],"type":"Point"}
}