{
  "type": "Feature",
  "properties": {
    "addr:full":"Unit 7 Charnham Lane Hungerford Berkshire RG17 0EY",
    "addr:housenumber":"unit 7",
    "addr:postcode":"rg17 0ey",
    "addr:street":"Charnham Lane",
    "iso:country":"GB",
    "sg:address":"Unit 7 Charnham Lane",
    "sg:city":"Hungerford",
    "sg:classifiers":[
        {
            "category":"Autos & Motor Vehicles",
            "subcategory":"Auto Supplies",
            "type":"Retail Goods"
        }
    ],
    "sg:phone":"+44 1488 683557",
    "sg:postcode":"RG17 0EY",
    "sg:province":"Berkshire",
    "sg:tags":[
        "tyre"
    ],
    "wof:name":"Kennet Tyre Service",
    "wof:placetype":"venue"
},
  "geometry": {"coordinates":[-1.516034,51.419617],"type":"Point"}
}