{
  "type": "Feature",
  "properties": {
    "addr:full":"14 Devonshire Place London Greater London W1G 6HU",
    "addr:housenumber":"14",
    "addr:postcode":"w1g 6hu",
    "addr:street":"Devonshire Place",
    "iso:country":"GB",
    "sg:address":"14 Devonshire Place",
    "sg:city":"London",
    "sg:classifiers":[
        {
            "category":"Health Services",
            "subcategory":"Clinic",
            "type":"Services"
        }
    ],
    "sg:phone":"+44 20 7935 0640",
    "sg:postcode":"W1G 6HU",
    "sg:province":"Greater London",
    "sg:tags":[
        "private"
    ],
    "wof:name":"Psychiatric & Psychological Consultant Services Ltd.",
    "wof:placetype":"venue"
},
  "geometry": {"coordinates":[-0.149969995,51.5225486755],"type":"Point"}
}