{
  "type": "Feature",
  "properties": {
    "iso:country":"GB",
    "sg:address":"46 Lightwood Road, Marsh Lane",
    "sg:city":"Sheffield",
    "sg:classifiers":[
        {
            "category":"Bars & Pubs",
            "type":"Food & Drink"
        }
    ],
    "sg:postcode":"S21 5RG",
    "sg:province":"Derbyshire",
    "sg:tags":[
        "pubs",
        "inn"
    ],
    "wof:name":"The George Inn",
    "wof:placetype":"venue"
},
  "geometry": {"coordinates":[-1.393532,53.305374],"type":"Point"}
}