{
  "type": "Feature",
  "properties": {
    "iso:country":"GB",
    "sg:address":"Care Of Coryton Refinery, The Manorway",
    "sg:city":"Stanford-le-hope",
    "sg:classifiers":[
        {
            "category":"Professional",
            "subcategory":"Engineering",
            "type":"Services"
        }
    ],
    "sg:phone":"+44 1375 673470",
    "sg:postcode":"SS17 9LL",
    "sg:province":"Essex",
    "wof:name":"Destec Engineering Ltd.",
    "wof:placetype":"venue"
},
  "geometry": {"coordinates":[0.50519,51.514969],"type":"Point"}
}