{
  "type": "Feature",
  "properties": {
    "iso:country":"GB",
    "sg:address":"Great Alne Memorial Hall, Great Alne",
    "sg:city":"Alcester",
    "sg:classifiers":[
        {
            "category":"Government",
            "subcategory":"Post Office",
            "type":"Public Place"
        }
    ],
    "sg:postcode":"B49 6HL",
    "sg:province":"Warwickshire",
    "wof:name":"J Woodhouse",
    "wof:placetype":"venue"
},
  "geometry": {"coordinates":[-1.8609919548,52.2217979431],"type":"Point"}
}