{
  "type": "Feature",
  "properties": {
    "addr:full":"451 Warwick Rd Solihull West Midlands B91 1AL",
    "addr:housenumber":"451",
    "addr:postcode":"b91 1al",
    "addr:street":"Warwick Rd",
    "iso:country":"GB",
    "sg:address":"451 Warwick Rd",
    "sg:city":"Solihull",
    "sg:classifiers":[
        {
            "category":"Health Services",
            "subcategory":"Chiropractor",
            "type":"Services"
        }
    ],
    "sg:phone":"+44 121 705 1876",
    "sg:postcode":"B91 1AL",
    "sg:province":"West Midlands",
    "wof:name":"The Chiropractors of Warwick Road",
    "wof:placetype":"venue"
},
  "geometry": {"coordinates":[-1.794851,52.424683],"type":"Point"}
}