{
  "type": "Feature",
  "properties": {
    "addr:full":"54-56 Moorland Road, Oldfield Park Bath Somerset BA2 3PJ",
    "addr:housenumber":"54-56",
    "addr:postcode":"ba2 3pj",
    "addr:street":"Moorland Road Oldfield Park",
    "iso:country":"GB",
    "sg:address":"54-56 Moorland Road, Oldfield Park",
    "sg:city":"Bath",
    "sg:classifiers":[
        {
            "category":"Shopping",
            "subcategory":"Department Store",
            "type":"Retail Goods"
        }
    ],
    "sg:phone":"+44 1225 424715",
    "sg:postcode":"BA2 3PJ",
    "sg:province":"Somerset",
    "sg:tags":[
        "departmental"
    ],
    "wof:name":"Woolworths Plc",
    "wof:placetype":"venue"
},
  "geometry": {"coordinates":[-2.378223896,51.3766098022],"type":"Point"}
}