{
  "type": "Feature",
  "properties": {
    "addr:full":"Market Pl Thirsk North Yorkshire YO7 1HA",
    "addr:postcode":"yo7 1ha",
    "addr:street":"Market Pl",
    "iso:country":"GB",
    "sg:address":"Market Pl",
    "sg:city":"Thirsk",
    "sg:classifiers":[
        {
            "category":"Shopping",
            "subcategory":"Gifts & Souvenirs",
            "type":"Retail Goods"
        }
    ],
    "sg:postcode":"YO7 1HA",
    "sg:province":"North Yorkshire",
    "sg:tags":[
        "shop"
    ],
    "wof:name":"Gallery (The)",
    "wof:placetype":"venue"
},
  "geometry": {"coordinates":[-1.3422529697,54.2326889038],"type":"Point"}
}