{
  "type": "Feature",
  "properties": {
    "addr:full":"276 Penn Road Wolverhampton Staffordshire WV4 4AD",
    "addr:housenumber":"276",
    "addr:postcode":"wv4 4ad",
    "addr:street":"Penn Road",
    "iso:country":"GB",
    "sg:address":"276 Penn Road",
    "sg:city":"Wolverhampton",
    "sg:classifiers":[
        {
            "category":"Health Services",
            "subcategory":"Chiropractor",
            "type":"Services"
        }
    ],
    "sg:postcode":"WV4 4AD",
    "sg:province":"Staffordshire",
    "wof:name":"Chris Bellew",
    "wof:placetype":"venue"
},
  "geometry": {"coordinates":[-2.1465640068,52.566028595],"type":"Point"}
}