{
  "type": "Feature",
  "properties": {
    "addr:full":"47 North Brink Wisbech Cambridgeshire PE13 1JX",
    "addr:housenumber":"47",
    "addr:postcode":"pe13 1jx",
    "addr:street":"North Brink",
    "iso:country":"GB",
    "sg:address":"47 North Brink",
    "sg:city":"Wisbech",
    "sg:classifiers":[
        {
            "category":"Education",
            "subcategory":"School",
            "type":"Public Place"
        }
    ],
    "sg:phone":"+44 1945 583631",
    "sg:postcode":"PE13 1JX",
    "sg:province":"Cambridgeshire",
    "sg:tags":[
        "independent",
        "preparatory"
    ],
    "wof:name":"Wisbech Grammar School",
    "wof:placetype":"venue"
},
  "geometry": {"coordinates":[0.1517480016,52.663734436],"type":"Point"}
}