{
  "type": "Feature",
  "properties": {
    "addr:full":"Stryd Vincent Swansea Neath Port Talbot SA1 3TY",
    "addr:postcode":"sa1 3ty",
    "addr:street":"Stryd Vincent",
    "iso:country":"GB",
    "sg:address":"Stryd Vincent",
    "sg:city":"Swansea",
    "sg:classifiers":[
        {
            "category":"Education",
            "subcategory":"School",
            "type":"Public Place"
        }
    ],
    "sg:phone":"+44 1792 649138",
    "sg:postcode":"SA1 3TY",
    "sg:province":"Neath Port Talbot",
    "sg:tags":[
        "local",
        "authority"
    ],
    "wof:name":"Canolfan Gymraeg San Helen",
    "wof:placetype":"venue"
},
  "geometry": {"coordinates":[-3.954334,51.615326],"type":"Point"}
}