{
  "type": "Feature",
  "properties": {
    "iso:country":"GB",
    "sg:address":"Bolling Rd, Ben Rhydding",
    "sg:city":"Ilkley",
    "sg:classifiers":[
        {
            "category":"Place Of Worship",
            "type":"Public Place"
        }
    ],
    "sg:phone":"+44 1943 601430",
    "sg:postcode":"LS29 8QA",
    "sg:province":"North Yorkshire",
    "wof:name":"St. John the Evangelist",
    "wof:placetype":"venue"
},
  "geometry": {"coordinates":[-1.821754,53.924461],"type":"Point"}
}