{
  "type": "Feature",
  "properties": {
    "addr:full":"1 Lynwood Drive Worcester Park Surrey KT4 7AA",
    "addr:housenumber":"1",
    "addr:postcode":"kt4 7aa",
    "addr:street":"Lynwood Drive",
    "iso:country":"GB",
    "sg:address":"1 Lynwood Drive",
    "sg:city":"Worcester Park",
    "sg:classifiers":[
        {
            "category":"Health Services",
            "subcategory":"Dentist",
            "type":"Services"
        }
    ],
    "sg:phone":"+44 20 8337 1140",
    "sg:postcode":"KT4 7AA",
    "sg:province":"Surrey",
    "wof:name":"The Dental Surgery",
    "wof:placetype":"venue"
},
  "geometry": {"coordinates":[-0.2441390008,51.3792915344],"type":"Point"}
}