{
  "type": "Feature",
  "properties": {
    "iso:country":"GB",
    "sg:address":"72 Dollis Rd",
    "sg:city":"London",
    "sg:classifiers":[
        {
            "category":"Professional",
            "subcategory":"Computer Services",
            "type":"Services"
        }
    ],
    "sg:postcode":"NW7 1JY",
    "sg:province":"Greater London",
    "sg:tags":[
        "system",
        "software"
    ],
    "wof:name":"Alborz Corporation Ltd",
    "wof:placetype":"venue"
},
  "geometry": {"coordinates":[-0.2053840011,51.6038551331],"type":"Point"}
}