{
  "type": "Feature",
  "properties": {
    "iso:country":"GB",
    "sg:address":"Blackwaters",
    "sg:city":"Newport",
    "sg:classifiers":[
        {
            "category":"Retail",
            "subcategory":"Funeral Services",
            "type":"Services"
        }
    ],
    "sg:phone":"+44 1983 522104",
    "sg:postcode":"PO30 3BH",
    "sg:province":"Isle of Wight",
    "wof:name":"A A & R J Westmore",
    "wof:placetype":"venue"
},
  "geometry": {"coordinates":[-1.288204,50.689548],"type":"Point"}
}