{
  "type": "Feature",
  "properties": {
    "addr:full":"Station Road, Skewen Neath Neath Port Talbot SA10 6HF",
    "addr:postcode":"sa10 6hf",
    "addr:street":"Station Road",
    "iso:country":"GB",
    "sg:address":"Station Road, Skewen",
    "sg:city":"Neath",
    "sg:classifiers":[
        {
            "category":"Professional",
            "subcategory":"Printing & Photocopies",
            "type":"Services"
        }
    ],
    "sg:phone":"+44 1792 817127",
    "sg:postcode":"SA10 6HF",
    "sg:province":"Neath Port Talbot",
    "sg:tags":[
        "printer"
    ],
    "wof:name":"Design Printers",
    "wof:placetype":"venue"
},
  "geometry": {"coordinates":[-3.846128,51.661552],"type":"Point"}
}