{
  "type": "Feature",
  "properties": {
    "iso:country":"GB",
    "sg:address":"23 Ashton Lane",
    "sg:city":"Glasgow",
    "sg:classifiers":[
        {
            "category":"Bars & Pubs",
            "type":"Food & Drink"
        },
        {
            "category":"Community Center",
            "subcategory":"Social",
            "type":"Public Place"
        }
    ],
    "sg:phone":"+44 141 339 0747",
    "sg:postcode":"G12 8SJ",
    "sg:province":"Glasgow City",
    "sg:tags":[
        "pubs",
        "house",
        "inn",
        "activity"
    ],
    "wof:name":"Jinty Mcguinty's",
    "wof:placetype":"venue"
},
  "geometry": {"coordinates":[-4.29285,55.874802],"type":"Point"}
}