{
  "type": "Feature",
  "properties": {
    "iso:country":"GB",
    "sg:address":"8 Denman Street",
    "sg:city":"London",
    "sg:classifiers":[
        {
            "category":"Cafe",
            "type":"Food & Drink"
        }
    ],
    "sg:postcode":"W1D 7HQ",
    "sg:province":"Greater London",
    "sg:tags":[
        "tea",
        "room"
    ],
    "wof:name":"The New Piccadilly",
    "wof:placetype":"venue"
},
  "geometry": {"coordinates":[-0.135154,51.510765],"type":"Point"}
}