{
  "type": "Feature",
  "properties": {
    "iso:country":"GB",
    "sg:address":"9 Church Street, Eccles",
    "sg:city":"Manchester",
    "sg:classifiers":[
        {
            "category":"Professional",
            "subcategory":"Lawyer & Legal Services",
            "type":"Services"
        }
    ],
    "sg:phone":"+44 161 707 3660",
    "sg:postcode":"M30 0DF",
    "sg:province":"Greater Manchester",
    "sg:tags":[
        "solicitor"
    ],
    "wof:name":"Martins",
    "wof:placetype":"venue"
},
  "geometry": {"coordinates":[-2.334501,53.485088],"type":"Point"}
}