{
  "type": "Feature",
  "properties": {
    "addr:full":"131a Balham High Rd Balham Greater London SW12 9AU",
    "addr:housenumber":"131a",
    "addr:postcode":"sw12 9au",
    "addr:street":"Balham High Rd",
    "iso:country":"GB",
    "sg:address":"131a Balham High Rd",
    "sg:city":"Balham",
    "sg:classifiers":[
        {
            "category":"Health Services",
            "subcategory":"Dentist",
            "type":"Services"
        }
    ],
    "sg:phone":"+44 20 8673 2379",
    "sg:postcode":"SW12 9AU",
    "sg:province":"Greater London",
    "wof:name":"B Da Costa Peres",
    "wof:placetype":"venue"
},
  "geometry": {"coordinates":[-0.1517349929,51.4446296692],"type":"Point"}
}