{
  "type": "Feature",
  "properties": {
    "addr:full":"24 Tamworth Drive, Brandlesholme Bury Lancashire BL8 1DP",
    "addr:housenumber":"24",
    "addr:postcode":"bl8 1dp",
    "addr:street":"Tamworth Drive",
    "iso:country":"GB",
    "sg:address":"24 Tamworth Drive, Brandlesholme",
    "sg:city":"Bury",
    "sg:classifiers":[
        {
            "category":"Building & Trades",
            "subcategory":"Construction",
            "type":"Services"
        }
    ],
    "sg:phone":"+44 161 797 8940",
    "sg:postcode":"BL8 1DP",
    "sg:province":"Lancashire",
    "sg:tags":[
        "contractor",
        "paving",
        "driveway"
    ],
    "wof:name":"Berry's Block Paving",
    "wof:placetype":"venue"
},
  "geometry": {"coordinates":[-2.3136489391,53.605506897],"type":"Point"}
}