{
  "type": "Feature",
  "properties": {
    "addr:full":"P O Box 2632 Tottenham Greater London N17 6BQ",
    "addr:housenumber":"p o;2632",
    "addr:postcode":"n17 6bq",
    "addr:street":"Tottenham",
    "iso:country":"GB",
    "sg:address":"P O Box 2632",
    "sg:city":"Tottenham",
    "sg:classifiers":[
        {
            "category":"Shopping",
            "subcategory":"Beauty & Cosmetics",
            "type":"Retail Goods"
        }
    ],
    "sg:phone":"+44 20 8880 3668",
    "sg:postcode":"N17 6BQ",
    "sg:province":"Greater London",
    "sg:tags":[
        "equipment",
        "supply",
        "hairdressing"
    ],
    "wof:name":"Luster Products Europe",
    "wof:placetype":"venue"
},
  "geometry": {"coordinates":[-0.0793839991,51.593120575],"type":"Point"}
}