{
  "type": "Feature",
  "properties": {
    "iso:country":"GB",
    "sg:address":"Unit 2 Murdock Road",
    "sg:city":"Bicester",
    "sg:classifiers":[
        {
            "category":"Shopping",
            "type":"Retail Goods"
        }
    ],
    "sg:postcode":"OX26 4PL",
    "sg:province":"Oxfordshire",
    "sg:tags":[
        "part",
        "accessory"
    ],
    "wof:name":"Spax Performance Ltd.",
    "wof:placetype":"venue"
},
  "geometry": {"coordinates":[-1.1424280405,51.9028778076],"type":"Point"}
}