{
  "type": "Feature",
  "properties": {
    "addr:full":"Longlands Dental Practice, 17 Ellingham Rd Hemel Hempstead Hertfordshire HP2 5LE",
    "addr:housenumber":"17",
    "addr:postcode":"hp2 5le",
    "addr:street":"Ellingham Rd",
    "iso:country":"GB",
    "sg:address":"Longlands Dental Practice, 17 Ellingham Rd",
    "sg:city":"Hemel Hempstead",
    "sg:classifiers":[
        {
            "category":"Health Services",
            "subcategory":"Dentist",
            "type":"Services"
        }
    ],
    "sg:phone":"+44 1442 264228",
    "sg:postcode":"HP2 5LE",
    "sg:province":"Hertfordshire",
    "wof:name":"Erica Koundouros",
    "wof:placetype":"venue"
},
  "geometry": {"coordinates":[-0.45425,51.759972],"type":"Point"}
}