{
  "type": "Feature",
  "properties": {
    "iso:country":"GB",
    "sg:address":"43 Woodfield Lane",
    "sg:city":"Ashtead",
    "sg:classifiers":[
        {
            "category":"Social Services",
            "subcategory":"Retirement Home",
            "type":"Services"
        }
    ],
    "sg:phone":"+44 1372 278039",
    "sg:postcode":"KT21 2BT",
    "sg:province":"Surrey",
    "sg:tags":[
        "residential",
        "care"
    ],
    "wof:name":"Mental After Care Association",
    "wof:placetype":"venue"
},
  "geometry": {"coordinates":[-0.3036839962,51.3146018982],"type":"Point"}
}