{
  "type": "Feature",
  "properties": {
    "addr:full":"Fox Howe Pardshaw Hall Cockermouth Cumbria CA13 0SP",
    "addr:postcode":"ca13 0sp",
    "iso:country":"GB",
    "sg:address":"Fox Howe Pardshaw Hall",
    "sg:city":"Cockermouth",
    "sg:classifiers":[
        {
            "category":"Professional",
            "subcategory":"Management & Consulting",
            "type":"Services"
        }
    ],
    "sg:phone":"+44 1900 827886",
    "sg:postcode":"CA13 0SP",
    "sg:province":"Cumbria",
    "sg:tags":[
        "consultant",
        "business"
    ],
    "wof:name":"JC Consult",
    "wof:placetype":"venue"
},
  "geometry": {"coordinates":[-3.402982,54.610409],"type":"Point"}
}