{
  "type": "Feature",
  "properties": {
    "iso:country":"GB",
    "sg:address":"217a Thornborough Road",
    "sg:city":"Coalville",
    "sg:classifiers":[
        {
            "category":"Retail",
            "subcategory":"Auto Repair",
            "type":"Services"
        }
    ],
    "sg:phone":"+44 1530 831791",
    "sg:postcode":"LE67 3TN",
    "sg:province":"Leicestershire",
    "sg:tags":[
        "modification",
        "car",
        "vehicle",
        "commercial",
        "garage"
    ],
    "wof:name":"Express Motor Services",
    "wof:placetype":"venue"
},
  "geometry": {"coordinates":[-1.3738440275,52.7342185974],"type":"Point"}
}