{
  "type": "Feature",
  "properties": {
    "iso:country":"GB",
    "sg:address":"Little Berrydown, Gidleigh, Chagford",
    "sg:city":"Newton Abbot",
    "sg:classifiers":[
        {
            "category":"Professional",
            "subcategory":"Accounting & Tax Preparation",
            "type":"Services"
        }
    ],
    "sg:phone":"+44 1647 433256",
    "sg:postcode":"TQ13 8HS",
    "sg:province":"Devon",
    "sg:tags":[
        "accountant"
    ],
    "wof:name":"J D West",
    "wof:placetype":"venue"
},
  "geometry": {"coordinates":[-3.834256,50.677418],"type":"Point"}
}