{
  "type": "Feature",
  "properties": {
    "addr:full":"15 Chesford Grange Warrington Cheshire WA1 4RQ",
    "addr:housenumber":"15",
    "addr:postcode":"wa1 4rq",
    "addr:street":"Chesford Grange",
    "iso:country":"GB",
    "sg:address":"15 Chesford Grange",
    "sg:city":"Warrington",
    "sg:classifiers":[
        {
            "category":"Home & Garden",
            "subcategory":"Building Materials",
            "type":"Retail Goods"
        }
    ],
    "sg:phone":"+44 1925 848001",
    "sg:postcode":"WA1 4RQ",
    "sg:province":"Cheshire",
    "sg:tags":[
        "wire",
        "cable"
    ],
    "wof:name":"Anixter Distribution",
    "wof:placetype":"venue"
},
  "geometry": {"coordinates":[-2.5160241127,53.4007835388],"type":"Point"}
}