{
  "type": "Feature",
  "properties": {
    "iso:country":"GB",
    "sg:address":"14 Main Street",
    "sg:city":"Campbeltown",
    "sg:classifiers":[
        {
            "category":"Shopping",
            "subcategory":"Books",
            "type":"Retail Goods"
        }
    ],
    "sg:phone":"+44 1586 552595",
    "sg:postcode":"PA28 6AG",
    "sg:province":"Argyll and Bute",
    "sg:tags":[
        "bookseller",
        "retailer"
    ],
    "wof:name":"EFRIC WHEATHERSPOON",
    "wof:placetype":"venue"
},
  "geometry": {"coordinates":[-5.6051311493,55.4245223999],"type":"Point"}
}