{
  "type": "Feature",
  "properties": {
    "addr:full":"5 Stamford Street Stalybridge Greater Manchester SK15 1JP",
    "addr:housenumber":"5",
    "addr:postcode":"sk15 1jp",
    "addr:street":"Stamford Street",
    "iso:country":"GB",
    "sg:address":"5 Stamford Street",
    "sg:city":"Stalybridge",
    "sg:classifiers":[
        {
            "category":"Professional",
            "subcategory":"Art Services",
            "type":"Services"
        }
    ],
    "sg:phone":"+44 161 338 3000",
    "sg:postcode":"SK15 1JP",
    "sg:province":"Greater Manchester",
    "sg:tags":[
        "photographer"
    ],
    "wof:name":"Studio 3000 Ltd.",
    "wof:placetype":"venue"
},
  "geometry": {"coordinates":[-2.054933,53.483765],"type":"Point"}
}