{
  "type": "Feature",
  "properties": {
    "addr:full":"29 Marlborough Building Bath Bath and North East Somerset BA1 2LY",
    "addr:housenumber":"29",
    "addr:postcode":"ba1 2ly",
    "addr:street":"Building Bath",
    "iso:country":"GB",
    "sg:address":"29 Marlborough Building",
    "sg:city":"Bath",
    "sg:classifiers":[
        {
            "category":"Arts & Performance",
            "subcategory":"Theater",
            "type":"Entertainment"
        }
    ],
    "sg:phone":"+44 7971 785970",
    "sg:postcode":"BA1 2LY",
    "sg:province":"Bath and North East Somerset",
    "sg:tags":[
        "hall",
        "theatre",
        "concert"
    ],
    "wof:name":"Bath Puppet Theatre",
    "wof:placetype":"venue"
},
  "geometry": {"coordinates":[-2.3699018955,51.3879394531],"type":"Point"}
}