{
  "type": "Feature",
  "properties": {
    "addr:full":"139 Albert Road Middlesbrough North Yorkshire TS1 2PP",
    "addr:housenumber":"139",
    "addr:postcode":"ts1 2pp",
    "addr:street":"Albert Road",
    "iso:country":"GB",
    "sg:address":"139 Albert Road",
    "sg:city":"Middlesbrough",
    "sg:classifiers":[
        {
            "category":"Professional",
            "subcategory":"Lawyer & Legal Services",
            "type":"Services"
        }
    ],
    "sg:phone":"+44 1642 217961",
    "sg:postcode":"TS1 2PP",
    "sg:province":"North Yorkshire",
    "sg:tags":[
        "solicitor"
    ],
    "wof:name":"Williamson & Hill",
    "wof:placetype":"venue"
},
  "geometry": {"coordinates":[-1.235337,54.574089],"type":"Point"}
}