{
  "type": "Feature",
  "properties": {
    "addr:full":"14 Redcliffe Square London Greater London SW10 9JZ",
    "addr:housenumber":"14",
    "addr:postcode":"sw10 9jz",
    "addr:street":"Redcliffe Square",
    "iso:country":"GB",
    "sg:address":"14 Redcliffe Square",
    "sg:city":"London",
    "sg:classifiers":[
        {
            "category":"Shopping",
            "subcategory":"Beauty & Cosmetics",
            "type":"Retail Goods"
        }
    ],
    "sg:postcode":"SW10 9JZ",
    "sg:province":"Greater London",
    "sg:tags":[
        "product"
    ],
    "wof:name":"Avroy Shlain Cosmetics",
    "wof:placetype":"venue"
},
  "geometry": {"coordinates":[-0.187712,51.488472],"type":"Point"}
}