{
  "type": "Feature",
  "properties": {
    "iso:country":"GB",
    "sg:address":"268 Burlington Road",
    "sg:city":"New Malden",
    "sg:classifiers":[
        {
            "category":"Building & Trades",
            "subcategory":"Equipment Rental",
            "type":"Services"
        },
        {
            "category":"Building & Trades",
            "subcategory":"Construction",
            "type":"Services"
        }
    ],
    "sg:phone":"+44 20 8949 0629",
    "sg:postcode":"KT3 4NL",
    "sg:province":"Surrey",
    "sg:tags":[
        "hire",
        "tool",
        "centre"
    ],
    "wof:name":"X L Tool & Plant Hire Ltd",
    "wof:placetype":"venue"
},
  "geometry": {"coordinates":[-0.2391179949,51.3999938965],"type":"Point"}
}