{
  "type": "Feature",
  "properties": {
    "addr:full":"24 Princes Avenue Hull East Riding of Yorkshire HU5 3QA",
    "addr:housenumber":"24",
    "addr:postcode":"hu5 3qa",
    "addr:street":"Princes Avenue",
    "iso:country":"GB",
    "sg:address":"24 Princes Avenue",
    "sg:city":"Hull",
    "sg:classifiers":[
        {
            "category":"Personal",
            "subcategory":"Beauty Salon",
            "type":"Services"
        }
    ],
    "sg:phone":"+44 1482 492444",
    "sg:postcode":"HU5 3QA",
    "sg:province":"East Riding of Yorkshire",
    "sg:tags":[
        "unisex",
        "hairdresser"
    ],
    "wof:name":"Kitch",
    "wof:placetype":"venue"
},
  "geometry": {"coordinates":[-0.359816,53.753891],"type":"Point"}
}