{
  "type": "Feature",
  "properties": {
    "iso:country":"GB",
    "sg:address":"2 Praed Road, Trafford Park",
    "sg:city":"Manchester",
    "sg:classifiers":[
        {
            "category":"Cafe",
            "type":"Food & Drink"
        }
    ],
    "sg:phone":"+44 161 877 6296",
    "sg:postcode":"M17 1PQ",
    "sg:province":"Cheshire",
    "sg:tags":[
        "tea",
        "room"
    ],
    "wof:name":"Praed Road Cafe",
    "wof:placetype":"venue"
},
  "geometry": {"coordinates":[-2.315333,53.465061],"type":"Point"}
}