{
  "type": "Feature",
  "properties": {
    "addr:full":"93-95 Broadway, New Moston Manchester Greater Manchester M40 3PH",
    "addr:housenumber":"93-95",
    "addr:postcode":"m40 3ph",
    "addr:street":"Broadway New",
    "iso:country":"GB",
    "sg:address":"93-95 Broadway, New Moston",
    "sg:city":"Manchester",
    "sg:classifiers":[
        {
            "category":"Shopping",
            "subcategory":"News",
            "type":"Retail Goods"
        }
    ],
    "sg:phone":"+44 161 681 2955",
    "sg:postcode":"M40 3PH",
    "sg:province":"Greater Manchester",
    "sg:tags":[
        "newsagent"
    ],
    "wof:name":"Shreeji News",
    "wof:placetype":"venue"
},
  "geometry": {"coordinates":[-2.1689488888,53.5170783997],"type":"Point"}
}