{
  "type": "Feature",
  "properties": {
    "iso:country":"GB",
    "sg:address":"27-29 New Hey Road, Rastrick",
    "sg:city":"Brighouse",
    "sg:classifiers":[
        {
            "category":"Professional",
            "subcategory":"Business Services",
            "type":"Services"
        }
    ],
    "sg:postcode":"HD6 3LP",
    "sg:province":"West Yorkshire",
    "sg:tags":[
        "import",
        "export",
        "agent"
    ],
    "wof:name":"Eurostar Commodities Ltd.",
    "wof:placetype":"venue"
},
  "geometry": {"coordinates":[-1.803249,53.680191],"type":"Point"}
}