{
  "type": "Feature",
  "properties": {
    "addr:full":"39 High Street Ventnor Isle of Wight PO38 1RZ",
    "addr:housenumber":"39",
    "addr:postcode":"po38 1rz",
    "addr:street":"High Street",
    "iso:country":"GB",
    "sg:address":"39 High Street",
    "sg:city":"Ventnor",
    "sg:classifiers":[
        {
            "category":"Travel",
            "subcategory":"Travel Agent",
            "type":"Entertainment"
        }
    ],
    "sg:postcode":"PO38 1RZ",
    "sg:province":"Isle of Wight",
    "wof:name":"Mercury Travel Services",
    "wof:placetype":"venue"
},
  "geometry": {"coordinates":[-1.2044160366,50.5955314636],"type":"Point"}
}