{
  "type": "Feature",
  "properties": {
    "addr:full":"410 Glasgow Rd Paisley Renfrewshire PA1 3BE",
    "addr:housenumber":"410",
    "addr:postcode":"pa1 3be",
    "addr:street":"Glasgow Rd",
    "iso:country":"GB",
    "sg:address":"410 Glasgow Rd",
    "sg:city":"Paisley",
    "sg:classifiers":[
        {
            "category":"Building & Trades",
            "subcategory":"Construction",
            "type":"Services"
        }
    ],
    "sg:phone":"+44 141 883 6339",
    "sg:postcode":"PA1 3BE",
    "sg:province":"Renfrewshire",
    "sg:tags":[
        "decorator",
        "painter"
    ],
    "wof:name":"David R Bett",
    "wof:placetype":"venue"
},
  "geometry": {"coordinates":[-4.371475,55.845547],"type":"Point"}
}