{
  "type": "Feature",
  "properties": {
    "iso:country":"GB",
    "sg:address":"21a Cornmarket",
    "sg:city":"Pontefract",
    "sg:classifiers":[
        {
            "category":"Health Services",
            "subcategory":"Chiropractor",
            "type":"Services"
        }
    ],
    "sg:phone":"+44 1977 690333",
    "sg:postcode":"WF8 1AN",
    "sg:province":"North Yorkshire",
    "wof:name":"Pontefract Chiropractic Clinic",
    "wof:placetype":"venue"
},
  "geometry": {"coordinates":[-1.314669,53.692005],"type":"Point"}
}