{
  "type": "Feature",
  "properties": {
    "iso:country":"GB",
    "sg:address":"Queensway Industrial Estate, Longbridge Hayes Road",
    "sg:city":"Stoke-on-trent",
    "sg:classifiers":[
        {
            "category":"Shopping",
            "subcategory":"Optical Goods",
            "type":"Retail Goods"
        }
    ],
    "sg:phone":"+44 1782 577055",
    "sg:postcode":"ST6 4DS",
    "sg:province":"Staffordshire",
    "sg:tags":[
        "medical"
    ],
    "wof:name":"Aai  Foster Grant Ltd.",
    "wof:placetype":"venue"
},
  "geometry": {"coordinates":[-2.219056,53.04356],"type":"Point"}
}