{
  "type": "Feature",
  "properties": {
    "iso:country":"GB",
    "sg:address":"Highview, Great Burches Road",
    "sg:city":"Benfleet",
    "sg:classifiers":[
        {
            "category":"Home & Garden",
            "subcategory":"Building Materials",
            "type":"Retail Goods"
        }
    ],
    "sg:phone":"+44 1268 773236",
    "sg:postcode":"SS7 3ND",
    "sg:province":"Essex",
    "sg:tags":[
        "insulation",
        "installers"
    ],
    "wof:name":"Fleet Insulation Co. Ltd.",
    "wof:placetype":"venue"
},
  "geometry": {"coordinates":[0.58212,51.572956],"type":"Point"}
}