{
  "type": "Feature",
  "properties": {
    "addr:full":", Norwood Harrogate North Yorkshire HG3 1SZ",
    "addr:postcode":"hg3 1sz",
    "iso:country":"GB",
    "sg:address":", Norwood",
    "sg:city":"Harrogate",
    "sg:classifiers":[
        {
            "category":"Bars & Pubs",
            "type":"Food & Drink"
        },
        {
            "category":"Community Center",
            "subcategory":"Social",
            "type":"Public Place"
        }
    ],
    "sg:phone":"+44 1943 880220",
    "sg:postcode":"HG3 1SZ",
    "sg:province":"North Yorkshire",
    "sg:tags":[
        "pubs",
        "house",
        "inn",
        "activity"
    ],
    "wof:name":"Sun Inn",
    "wof:placetype":"venue"
},
  "geometry": {"coordinates":[-1.6205819845,53.9688987732],"type":"Point"}
}