{
  "type": "Feature",
  "properties": {
    "iso:country":"GB",
    "sg:address":"P O Box 27",
    "sg:city":"Wilmslow",
    "sg:classifiers":[
        {
            "category":"Wholesale",
            "subcategory":"Books, Periodicals, & Newspapers",
            "type":"Manufacturing & Wholesale Goods"
        }
    ],
    "sg:postcode":"SK9 3EX",
    "sg:province":"Cheshire",
    "sg:tags":[
        "publishing"
    ],
    "wof:name":"Belvedere Fine Publishing Co",
    "wof:placetype":"venue"
},
  "geometry": {"coordinates":[-2.215459,53.350712],"type":"Point"}
}