{
  "type": "Feature",
  "properties": {
    "addr:full":"3 Raleigh House Bridgwater Somerset TA6 4RB",
    "addr:housenumber":"3 raleigh house",
    "addr:postcode":"ta6 4rb",
    "iso:country":"GB",
    "sg:address":"3 Raleigh House",
    "sg:city":"Bridgwater",
    "sg:classifiers":[
        {
            "category":"Food & Beverages",
            "subcategory":"Meat & Fish",
            "type":"Retail Goods"
        }
    ],
    "sg:phone":"+44 1278 445757",
    "sg:postcode":"TA6 4RB",
    "sg:province":"Somerset",
    "sg:tags":[
        "butcher"
    ],
    "wof:name":"T J Payton Traditional Butchers",
    "wof:placetype":"venue"
},
  "geometry": {"coordinates":[-2.9834840298,51.1314163208],"type":"Point"}
}