{
  "type": "Feature",
  "properties": {
    "iso:country":"GB",
    "sg:address":"River Bank Farm, Saxilby",
    "sg:city":"Lincoln",
    "sg:classifiers":[
        {
            "category":"Farming",
            "subcategory":"Dairy Farm",
            "type":"Manufacturing & Wholesale Goods"
        }
    ],
    "sg:phone":"+44 1522 702355",
    "sg:postcode":"LN1 2LT",
    "sg:province":"Lincolnshire",
    "wof:name":"J B & P F Clarke & Sons",
    "wof:placetype":"venue"
},
  "geometry": {"coordinates":[-0.6559759974,53.2714347839],"type":"Point"}
}