{
  "type": "Feature",
  "properties": {
    "iso:country":"GB",
    "sg:address":"43-45 East Smithfield",
    "sg:city":"London",
    "sg:classifiers":[
        {
            "category":"Bars & Pubs",
            "subcategory":"Nightclub",
            "type":"Food & Drink"
        }
    ],
    "sg:postcode":"E1 9AP",
    "sg:province":"Greater London",
    "sg:tags":[
        "club",
        "night"
    ],
    "wof:name":"Cherokee Leisure Plc",
    "wof:placetype":"venue"
},
  "geometry": {"coordinates":[-0.069563,51.508682],"type":"Point"}
}