{
  "type": "Feature",
  "properties": {
    "addr:full":"17 Elswick Road Newcastle-upon-tyne Tyne and Wear NE4 6ER",
    "addr:housenumber":"17",
    "addr:postcode":"ne4 6er",
    "addr:street":"Elswick Road",
    "iso:country":"GB",
    "sg:address":"17 Elswick Road",
    "sg:city":"Newcastle-upon-tyne",
    "sg:classifiers":[
        {
            "category":"Fast Food",
            "type":"Food & Drink"
        }
    ],
    "sg:postcode":"NE4 6ER",
    "sg:province":"Tyne and Wear",
    "sg:tags":[
        "away",
        "take"
    ],
    "wof:name":"Mr Buns Filling Station",
    "wof:placetype":"venue"
},
  "geometry": {"coordinates":[-1.629676,54.971638],"type":"Point"}
}