{
  "type": "Feature",
  "properties": {
    "addr:full":"Wootton Mount Bournemouth Dorset BH1 1PJ",
    "addr:postcode":"bh1 1pj",
    "addr:street":"Mount",
    "iso:country":"GB",
    "sg:address":"Wootton Mount",
    "sg:city":"Bournemouth",
    "sg:classifiers":[
        {
            "category":"Professional",
            "subcategory":"Advertising",
            "type":"Services"
        }
    ],
    "sg:phone":"+44 1202 414200",
    "sg:postcode":"BH1 1PJ",
    "sg:province":"Dorset",
    "sg:tags":[
        "agency"
    ],
    "wof:name":"WALKER BLAIR ADVERTISING LTD",
    "wof:placetype":"venue"
},
  "geometry": {"coordinates":[-1.86909,50.721642],"type":"Point"}
}