{
  "type": "Feature",
  "properties": {
    "addr:full":"Gershwin Road, Brighton Hill Basingstoke Hampshire RG22 4HH",
    "addr:postcode":"rg22 4hh",
    "addr:street":"Gershwin Road",
    "iso:country":"GB",
    "sg:address":"Gershwin Road, Brighton Hill",
    "sg:city":"Basingstoke",
    "sg:classifiers":[
        {
            "category":"Place Of Worship",
            "type":"Public Place"
        }
    ],
    "sg:phone":"+44 1256 324297",
    "sg:postcode":"RG22 4HH",
    "sg:province":"Hampshire",
    "wof:name":"Basingstoke baptist Church",
    "wof:placetype":"venue"
},
  "geometry": {"coordinates":[-1.121502,51.245071],"type":"Point"}
}