{
  "type": "Feature",
  "properties": {
    "iso:country":"GB",
    "sg:address":"8 Amble Clo",
    "sg:city":"Lincoln",
    "sg:classifiers":[
        {
            "category":"Building & Trades",
            "subcategory":"Plumbing",
            "type":"Services"
        }
    ],
    "sg:phone":"+44 1522 538005",
    "sg:postcode":"LN1 3PJ",
    "sg:province":"Lincolnshire",
    "sg:tags":[
        "drain",
        "clearance",
        "sewer"
    ],
    "wof:name":"Ajet",
    "wof:placetype":"venue"
},
  "geometry": {"coordinates":[-0.546801,53.250992],"type":"Point"}
}