{
  "type": "Feature",
  "properties": {
    "addr:full":"92 Lozells Road Birmingham West Midlands B19 2TB",
    "addr:housenumber":"92",
    "addr:postcode":"b19 2tb",
    "addr:street":"Lozells Road",
    "iso:country":"GB",
    "sg:address":"92 Lozells Road",
    "sg:city":"Birmingham",
    "sg:classifiers":[
        {
            "category":"Place Of Worship",
            "type":"Public Place"
        },
        {
            "category":"Organizations",
            "subcategory":"Religious Organization",
            "type":"Services"
        }
    ],
    "sg:phone":"+44 121 554 6471",
    "sg:postcode":"B19 2TB",
    "sg:province":"West Midlands",
    "sg:tags":[
        "organisation"
    ],
    "wof:name":"Scripture Union",
    "wof:placetype":"venue"
},
  "geometry": {"coordinates":[-1.9060549736,52.5027084351],"type":"Point"}
}