{
  "type": "Feature",
  "properties": {
    "addr:full":"118 Central Road Morden Surrey SM4 5RL",
    "addr:housenumber":"118",
    "addr:postcode":"sm4 5rl",
    "addr:street":"Central Road",
    "iso:country":"GB",
    "sg:address":"118 Central Road",
    "sg:city":"Morden",
    "sg:classifiers":[
        {
            "category":"Retail",
            "subcategory":"Auto Repair",
            "type":"Services"
        }
    ],
    "sg:postcode":"SM4 5RL",
    "sg:province":"Surrey",
    "sg:tags":[
        "modification",
        "garage"
    ],
    "wof:name":"Central Motor Spares",
    "wof:placetype":"venue"
},
  "geometry": {"coordinates":[-0.192506,51.395718],"type":"Point"}
}