{
  "type": "Feature",
  "properties": {
    "addr:full":"The Riverside Inn, 14 Bridge Street, Barrow On Soar Loughborough Leicestershire LE12 8PN",
    "addr:housenumber":"14",
    "addr:postcode":"soar;le12 8pn",
    "addr:street":"Bridge Street",
    "iso:country":"GB",
    "sg:address":"The Riverside Inn, 14 Bridge Street, Barrow On Soar",
    "sg:city":"Loughborough",
    "sg:classifiers":[
        {
            "category":"Recreation",
            "subcategory":"Boat Charter",
            "type":"Entertainment"
        }
    ],
    "sg:phone":"+44 1509 415001",
    "sg:postcode":"LE12 8PN",
    "sg:province":"Leicestershire",
    "sg:tags":[
        "excursion"
    ],
    "wof:name":"Barrow Boating",
    "wof:placetype":"venue"
},
  "geometry": {"coordinates":[-1.15188,52.750462],"type":"Point"}
}