{
  "type": "Feature",
  "properties": {
    "addr:full":"92 Wheat Street Nuneaton Leicestershire CV11 4BH",
    "addr:housenumber":"92",
    "addr:postcode":"cv11 4bh",
    "addr:street":"Wheat Street",
    "iso:country":"GB",
    "sg:address":"92 Wheat Street",
    "sg:city":"Nuneaton",
    "sg:classifiers":[
        {
            "category":"Banks & Credit Unions",
            "subcategory":"Financial Services",
            "type":"Services"
        }
    ],
    "sg:phone":"+44 24 7634 1231",
    "sg:postcode":"CV11 4BH",
    "sg:province":"Leicestershire",
    "sg:tags":[
        "consultant",
        "finance"
    ],
    "wof:name":"North Warwickshire Finance",
    "wof:placetype":"venue"
},
  "geometry": {"coordinates":[-1.461255,52.523617],"type":"Point"}
}