{
  "type": "Feature",
  "properties": {
    "iso:country":"GB",
    "sg:address":"Morton Post Office, 123 Newlaithes Avenue",
    "sg:city":"Carlisle",
    "sg:classifiers":[
        {
            "category":"Food & Beverages",
            "subcategory":"Supermarket",
            "type":"Retail Goods"
        },
        {
            "category":"Government",
            "subcategory":"Post Office",
            "type":"Public Place"
        }
    ],
    "sg:phone":"+44 1228 521750",
    "sg:postcode":"CA2 6PP",
    "sg:province":"Cumbria",
    "wof:name":"Morton Post Office",
    "wof:placetype":"venue"
},
  "geometry": {"coordinates":[-2.96329,54.87912],"type":"Point"}
}