{
  "type": "Feature",
  "properties": {
    "addr:full":"Brickfields, London Road West Malling Kent ME19 5AG",
    "addr:postcode":"me19 5ag",
    "addr:street":"London Road",
    "iso:country":"GB",
    "sg:address":"Brickfields, London Road",
    "sg:city":"West Malling",
    "sg:classifiers":[
        {
            "category":"Retail",
            "subcategory":"Auto Rental",
            "type":"Services"
        },
        {
            "category":"Retail",
            "subcategory":"Auto Repair",
            "type":"Services"
        }
    ],
    "sg:phone":"+44 1732 848516",
    "sg:postcode":"ME19 5AG",
    "sg:province":"Kent",
    "sg:tags":[
        "modification",
        "garage",
        "hire",
        "van"
    ],
    "wof:name":"D H Yates & Sons Transport Ltd",
    "wof:placetype":"venue"
},
  "geometry": {"coordinates":[0.4046199918,51.3005752563],"type":"Point"}
}