{
  "type": "Feature",
  "properties": {
    "addr:full":"10 High Street, Greatham Hartlepool Durham TS25 2EN",
    "addr:housenumber":"10",
    "addr:postcode":"ts25 2en",
    "addr:street":"High Street",
    "iso:country":"GB",
    "sg:address":"10 High Street, Greatham",
    "sg:city":"Hartlepool",
    "sg:classifiers":[
        {
            "category":"Transit Center",
            "subcategory":"Passenger",
            "type":"Transportation"
        }
    ],
    "sg:phone":"+44 1429 872376",
    "sg:postcode":"TS25 2EN",
    "sg:province":"Durham",
    "sg:tags":[
        "taxidermist"
    ],
    "wof:name":"Kevin Wilmot",
    "wof:placetype":"venue"
},
  "geometry": {"coordinates":[-1.239661,54.642998],"type":"Point"}
}