{
  "type": "Feature",
  "properties": {
    "addr:full":"37 Pen Y Lan Road Cardiff Cardiff CF24 3PG",
    "addr:housenumber":"37",
    "addr:postcode":"cf24 3pg",
    "addr:street":"Pen Y Lan Road",
    "iso:country":"GB",
    "sg:address":"37 Pen Y Lan Road",
    "sg:city":"Cardiff",
    "sg:classifiers":[
        {
            "category":"Museum",
            "subcategory":"Art Museum",
            "type":"Entertainment"
        }
    ],
    "sg:phone":"+44 29 2047 2595",
    "sg:postcode":"CF24 3PG",
    "sg:province":"Cardiff",
    "sg:tags":[
        "gallery"
    ],
    "wof:name":"Oriel Makers Ltd.",
    "wof:placetype":"venue"
},
  "geometry": {"coordinates":[-3.1648719311,51.4953269958],"type":"Point"}
}