{
  "type": "Feature",
  "properties": {
    "iso:country":"GB",
    "sg:address":"Unit 7-8, 35 East Duck Lees Lane, Ponders End Industrial Estate",
    "sg:city":"Enfield",
    "sg:classifiers":[
        {
            "category":"Professional",
            "subcategory":"Engineering",
            "type":"Services"
        }
    ],
    "sg:phone":"+44 20 8804 3191",
    "sg:postcode":"EN3 7UW",
    "sg:province":"Greater London",
    "wof:name":"Broadfields Engineering Co. Ltd.",
    "wof:placetype":"venue"
},
  "geometry": {"coordinates":[-0.0283540003,51.6473464966],"type":"Point"}
}