{
  "type": "Feature",
  "properties": {
    "iso:country":"GB",
    "sg:address":"9a Hill Av",
    "sg:city":"Amersham",
    "sg:classifiers":[
        {
            "category":"Health Services",
            "subcategory":"Dentist",
            "type":"Services"
        }
    ],
    "sg:phone":"+44 1494 727013",
    "sg:postcode":"HP6 5BD",
    "sg:province":"Buckinghamshire",
    "wof:name":"C M Fearn",
    "wof:placetype":"venue"
},
  "geometry": {"coordinates":[-0.607591,51.674839],"type":"Point"}
}