{
  "type": "Feature",
  "properties": {
    "addr:full":"9 Northcott Ave London Greater London N22 7DB",
    "addr:housenumber":"9",
    "addr:postcode":"n22 7db",
    "addr:street":"Northcott Ave",
    "iso:country":"GB",
    "sg:address":"9 Northcott Ave",
    "sg:city":"London",
    "sg:classifiers":[
        {
            "category":"Professional",
            "subcategory":"Accounting & Tax Preparation",
            "type":"Services"
        }
    ],
    "sg:postcode":"N22 7DB",
    "sg:province":"Greater London",
    "sg:tags":[
        "accountant"
    ],
    "wof:name":"Angan Cheong & Co",
    "wof:placetype":"venue"
},
  "geometry": {"coordinates":[-0.1188540012,51.6014137268],"type":"Point"}
}