{
  "type": "Feature",
  "properties": {
    "iso:country":"GB",
    "sg:address":"Mosley St",
    "sg:city":"Manchester",
    "sg:classifiers":[
        {
            "category":"Museum",
            "subcategory":"Art Museum",
            "type":"Entertainment"
        }
    ],
    "sg:phone":"+44 161 236 5244",
    "sg:postcode":"M2 3FX",
    "sg:province":"Greater Manchester",
    "sg:tags":[
        "gallery"
    ],
    "wof:name":"Manchester City Council",
    "wof:placetype":"venue"
},
  "geometry": {"coordinates":[-2.240279,53.480061],"type":"Point"}
}