{
  "type": "Feature",
  "properties": {
    "iso:country":"GB",
    "sg:address":"Ty Mawr Industrial Estate",
    "sg:city":"Llanybydder",
    "sg:classifiers":[
        {
            "category":"Manufacturing",
            "subcategory":"Wood Products",
            "type":"Manufacturing & Wholesale Goods"
        }
    ],
    "sg:phone":"+44 1570 480056",
    "sg:postcode":"SA40 9RN",
    "sg:province":"Carmarthenshire",
    "sg:tags":[
        "packaging",
        "crate",
        "pallets"
    ],
    "wof:name":"Citrim Ltd.",
    "wof:placetype":"venue"
},
  "geometry": {"coordinates":[-4.158361,52.073936],"type":"Point"}
}