{
  "type": "Feature",
  "properties": {
    "addr:full":"Appleby Business Centre Blackburn Lancashire BB1 3BL",
    "addr:postcode":"bb1 3bl",
    "iso:country":"GB",
    "sg:address":"Appleby Business Centre",
    "sg:city":"Blackburn",
    "sg:classifiers":[
        {
            "category":"Home & Garden",
            "subcategory":"Home Furnishings",
            "type":"Retail Goods"
        }
    ],
    "sg:phone":"+44 1254 691133",
    "sg:postcode":"BB1 3BL",
    "sg:province":"Lancashire",
    "sg:tags":[
        "wall",
        "wallpaper",
        "covering"
    ],
    "wof:name":"Alexander Beauchamp (Wallpaper & Fabrics) Ltd.",
    "wof:placetype":"venue"
},
  "geometry": {"coordinates":[-2.4665238857,53.7527961731],"type":"Point"}
}