{
  "type": "Feature",
  "properties": {
    "addr:full":"2 Clifton Wood Crescent, Clifton Wood Bristol City of Bristol BS8 4TU",
    "addr:housenumber":"2",
    "addr:postcode":"bs8 4tu",
    "addr:street":"Clifton Wood Crescent",
    "iso:country":"GB",
    "sg:address":"2 Clifton Wood Crescent, Clifton Wood",
    "sg:city":"Bristol",
    "sg:classifiers":[
        {
            "category":"Professional",
            "type":"Services"
        }
    ],
    "sg:postcode":"BS8 4TU",
    "sg:province":"City of Bristol",
    "sg:tags":[
        "writer"
    ],
    "wof:name":"Techword Ltd.",
    "wof:placetype":"venue"
},
  "geometry": {"coordinates":[-2.61255,51.45261],"type":"Point"}
}