{
  "type": "Feature",
  "properties": {
    "addr:full":"Low Chare Chester-le-street Durham DH3 3QS",
    "addr:postcode":"dh3 3qs",
    "addr:street":"Chare",
    "iso:country":"GB",
    "sg:address":"Low Chare",
    "sg:city":"Chester-le-street",
    "sg:classifiers":[
        {
            "category":"Home & Garden",
            "subcategory":"Home Furnishings",
            "type":"Retail Goods"
        }
    ],
    "sg:phone":"+44 191 387 1103",
    "sg:postcode":"DH3 3QS",
    "sg:province":"Durham",
    "sg:tags":[
        "wall",
        "wallpaper",
        "covering"
    ],
    "wof:name":"Direct Decor",
    "wof:placetype":"venue"
},
  "geometry": {"coordinates":[-1.5732090473,54.856678009],"type":"Point"}
}