{
  "type": "Feature",
  "properties": {
    "addr:full":"John Wesley House, Wesley Place Keighley North Yorkshire BD20 0PH",
    "addr:postcode":"bd20 0ph",
    "addr:street":"John;Wesley Place",
    "iso:country":"GB",
    "sg:address":"John Wesley House, Wesley Place",
    "sg:city":"Keighley",
    "sg:classifiers":[
        {
            "category":"Professional",
            "subcategory":"Accounting & Tax Preparation",
            "type":"Services"
        }
    ],
    "sg:phone":"+44 1535 652362",
    "sg:postcode":"BD20 0PH",
    "sg:province":"North Yorkshire",
    "sg:tags":[
        "accountant"
    ],
    "wof:name":"Meehan & Co Ltd",
    "wof:placetype":"venue"
},
  "geometry": {"coordinates":[-1.937474,53.914299],"type":"Point"}
}