{
  "type": "Feature",
  "properties": {
    "iso:country":"GB",
    "sg:address":"Stephenson House  15 Church Walk",
    "sg:city":"Peterborough",
    "sg:classifiers":[
        {
            "category":"Building & Trades",
            "subcategory":"Construction",
            "type":"Services"
        }
    ],
    "sg:postcode":"PE1 2TP",
    "sg:province":"Cambridgeshire",
    "sg:tags":[
        "platform",
        "work",
        "scaffolding"
    ],
    "wof:name":"R N Scaffolding Ltd",
    "wof:placetype":"venue"
},
  "geometry": {"coordinates":[-0.242329,52.578327],"type":"Point"}
}