{
  "type": "Feature",
  "properties": {
    "addr:full":"109 Fulham Palace Road London Greater London W6 8JA",
    "addr:housenumber":"109",
    "addr:postcode":"w6 8ja",
    "addr:street":"Fulham Palace Road",
    "iso:country":"GB",
    "sg:address":"109 Fulham Palace Road",
    "sg:city":"London",
    "sg:classifiers":[
        {
            "category":"Building & Trades",
            "subcategory":"Landscaping Services",
            "type":"Services"
        },
        {
            "category":"Food & Beverages",
            "subcategory":"Meat & Fish",
            "type":"Retail Goods"
        }
    ],
    "sg:phone":"+44 20 8563 1994",
    "sg:postcode":"W6 8JA",
    "sg:province":"Greater London",
    "sg:tags":[
        "body",
        "regulatory",
        "assoc",
        "butcher"
    ],
    "wof:name":"Halal Food Authority",
    "wof:placetype":"venue"
},
  "geometry": {"coordinates":[-0.22253,51.488331],"type":"Point"}
}