{
  "type": "Feature",
  "properties": {
    "addr:full":"Strawberry Hill, Dunsford Exeter Devon EX6 7HE",
    "addr:postcode":"ex6 7he",
    "addr:street":"Hill",
    "iso:country":"GB",
    "sg:address":"Strawberry Hill, Dunsford",
    "sg:city":"Exeter",
    "sg:classifiers":[
        {
            "category":"Home & Garden",
            "subcategory":"Garden Supply",
            "type":"Retail Goods"
        }
    ],
    "sg:phone":"+44 1647 253297",
    "sg:postcode":"EX6 7HE",
    "sg:province":"Devon",
    "sg:tags":[
        "nursery",
        "centre"
    ],
    "wof:name":"Strawberry Hill Nursery",
    "wof:placetype":"venue"
},
  "geometry": {"coordinates":[-3.6832220554,50.6899909973],"type":"Point"}
}