{
  "type": "Feature",
  "properties": {
    "iso:country":"GB",
    "sg:address":"8 Station Road",
    "sg:city":"Settle",
    "sg:classifiers":[
        {
            "category":"Professional",
            "subcategory":"Computer Services",
            "type":"Services"
        },
        {
            "category":"Utilities",
            "type":"Services"
        }
    ],
    "sg:postcode":"BD24 9AA",
    "sg:province":"North Yorkshire",
    "sg:tags":[
        "internet"
    ],
    "wof:name":"Web4orce Ltd.",
    "wof:placetype":"venue"
},
  "geometry": {"coordinates":[-2.2790629864,54.0675201416],"type":"Point"}
}