{
  "type": "Feature",
  "properties": {
    "iso:country":"GB",
    "sg:address":"Suite 1a, Riverside Pl, 1 St James St",
    "sg:city":"Taunton",
    "sg:classifiers":[
        {
            "category":"Utilities",
            "type":"Services"
        }
    ],
    "sg:phone":"+44 1823 351795",
    "sg:postcode":"TA1 1JH",
    "sg:province":"Somerset",
    "sg:tags":[
        "broker"
    ],
    "wof:name":"Ecocentre",
    "wof:placetype":"venue"
},
  "geometry": {"coordinates":[-3.1106989384,51.0104904175],"type":"Point"}
}