{
  "type": "Feature",
  "properties": {
    "addr:full":"Lower Ground, Hampstead Lodge, 77- Bell Street London Greater London NW1 6TA",
    "addr:housenumber":"77",
    "addr:postcode":"nw1 6ta",
    "addr:street":"Lower Ground;Bell Street",
    "iso:country":"GB",
    "sg:address":"Lower Ground, Hampstead Lodge, 77- Bell Street",
    "sg:city":"London",
    "sg:classifiers":[
        {
            "category":"Professional",
            "subcategory":"Engineering",
            "type":"Services"
        }
    ],
    "sg:phone":"+44 20 7724 0226",
    "sg:postcode":"NW1 6TA",
    "sg:province":"Greater London",
    "sg:tags":[
        "consultant",
        "structural"
    ],
    "wof:name":"Bolton Priestley Ltd.",
    "wof:placetype":"venue"
},
  "geometry": {"coordinates":[-0.16761,51.521561],"type":"Point"}
}