{
  "type": "Feature",
  "properties": {
    "addr:full":"Frome Road, Odd Down Bath Somerset BA2 5RF",
    "addr:postcode":"ba2 5rf",
    "addr:street":"Frome Road",
    "iso:country":"GB",
    "sg:address":"Frome Road, Odd Down",
    "sg:city":"Bath",
    "sg:classifiers":[
        {
            "category":"Education",
            "subcategory":"Special Training",
            "type":"Public Place"
        },
        {
            "category":"Education",
            "subcategory":"School",
            "type":"Public Place"
        }
    ],
    "sg:phone":"+44 1225 832212",
    "sg:postcode":"BA2 5RF",
    "sg:province":"Somerset",
    "wof:name":"Wansdyke Special School",
    "wof:placetype":"venue"
},
  "geometry": {"coordinates":[-2.3734300137,51.3575706482],"type":"Point"}
}