{
  "type": "Feature",
  "properties": {
    "addr:full":"161 Borough High St Southwark Greater London SE1 1HR",
    "addr:housenumber":"161",
    "addr:postcode":"se1 1hr",
    "addr:street":"Borough High St",
    "iso:country":"GB",
    "sg:address":"161 Borough High St",
    "sg:city":"Southwark",
    "sg:classifiers":[
        {
            "category":"Professional",
            "subcategory":"Business Services",
            "type":"Services"
        }
    ],
    "sg:phone":"+44 20 7940 0400",
    "sg:postcode":"SE1 1HR",
    "sg:province":"Greater London",
    "sg:tags":[
        "agent",
        "copyright"
    ],
    "wof:name":"Performing Artists Media Rights Association",
    "wof:placetype":"venue"
},
  "geometry": {"coordinates":[-0.091867,51.502705],"type":"Point"}
}