{
  "type": "Feature",
  "properties": {
    "addr:full":"31 Robertson Drive Sleaford Lincolnshire NG34 7AN",
    "addr:housenumber":"31",
    "addr:postcode":"ng34 7an",
    "addr:street":"Robertson Drive",
    "iso:country":"GB",
    "sg:address":"31 Robertson Drive",
    "sg:city":"Sleaford",
    "sg:classifiers":[
        {
            "category":"Military Area",
            "subcategory":"Air Force Base",
            "type":"Public Place"
        }
    ],
    "sg:postcode":"NG34 7AN",
    "sg:province":"Lincolnshire",
    "sg:tags":[
        "taxi",
        "hire",
        "private"
    ],
    "wof:name":"M & J Taxis",
    "wof:placetype":"venue"
},
  "geometry": {"coordinates":[-0.410089,53.005573],"type":"Point"}
}