{
  "type": "Feature",
  "properties": {
    "addr:full":"30 Broad St Bromyard Herefordshire HR7 4BS",
    "addr:housenumber":"30",
    "addr:postcode":"hr7 4bs",
    "addr:street":"Broad St",
    "iso:country":"GB",
    "sg:address":"30 Broad St",
    "sg:city":"Bromyard",
    "sg:classifiers":[
        {
            "category":"Food & Beverages",
            "subcategory":"Meat & Fish",
            "type":"Retail Goods"
        }
    ],
    "sg:phone":"+44 1885 483628",
    "sg:postcode":"HR7 4BS",
    "sg:province":"Herefordshire",
    "sg:tags":[
        "butcher"
    ],
    "wof:name":"Eric Geddes",
    "wof:placetype":"venue"
},
  "geometry": {"coordinates":[-2.5055689812,52.188533783],"type":"Point"}
}