{
  "type": "Feature",
  "properties": {
    "addr:full":"137 Bouverie Road, Hardingstone Northampton Northamptonshire NN4 6EG",
    "addr:housenumber":"137",
    "addr:postcode":"nn4 6eg",
    "addr:street":"Bouverie Road",
    "iso:country":"GB",
    "sg:address":"137 Bouverie Road, Hardingstone",
    "sg:city":"Northampton",
    "sg:classifiers":[
        {
            "category":"Government",
            "subcategory":"Post Office",
            "type":"Public Place"
        }
    ],
    "sg:phone":"+44 1604 761568",
    "sg:postcode":"NN4 6EG",
    "sg:province":"Northamptonshire",
    "wof:name":"Hardingstone Post Office",
    "wof:placetype":"venue"
},
  "geometry": {"coordinates":[-0.881909,52.211658],"type":"Point"}
}