{
  "type": "Feature",
  "properties": {
    "iso:country":"GB",
    "sg:address":"94 Springfield Blvd, Springfield",
    "sg:city":"Milton Keynes",
    "sg:classifiers":[
        {
            "category":"Health Services",
            "subcategory":"Health Practitioner",
            "type":"Services"
        }
    ],
    "sg:postcode":"MK6 3HY",
    "sg:province":"Buckinghamshire",
    "sg:tags":[
        "hypnotherapists"
    ],
    "wof:name":"Frank Matthews",
    "wof:placetype":"venue"
},
  "geometry": {"coordinates":[-0.733123,52.040905],"type":"Point"}
}