{
  "type": "Feature",
  "properties": {
    "addr:full":"184 Kedleston Road Derby Derbyshire DE22 1GT",
    "addr:housenumber":"184",
    "addr:postcode":"de22 1gt",
    "addr:street":"Kedleston Road",
    "iso:country":"GB",
    "sg:address":"184 Kedleston Road",
    "sg:city":"Derby",
    "sg:classifiers":[
        {
            "category":"Education",
            "subcategory":"Library",
            "type":"Public Place"
        },
        {
            "category":"Government",
            "subcategory":"Office",
            "type":"Public Place"
        }
    ],
    "sg:phone":"+44 1332 371921",
    "sg:postcode":"DE22 1GT",
    "sg:province":"Derbyshire",
    "sg:tags":[
        "book",
        "local"
    ],
    "wof:name":"School Library Service (Derbyshire & Derby)",
    "wof:placetype":"venue"
},
  "geometry": {"coordinates":[-1.4947379827,52.9334907532],"type":"Point"}
}