{
  "type": "Feature",
  "properties": {
    "iso:country":"GB",
    "sg:address":"8 Stratford Road, Wolverton",
    "sg:city":"Milton Keynes",
    "sg:classifiers":[
        {
            "category":"Retail",
            "subcategory":"Repair Shop",
            "type":"Services"
        }
    ],
    "sg:postcode":"MK12 5LJ",
    "sg:province":"Buckinghamshire",
    "sg:tags":[
        "radio",
        "television",
        "video"
    ],
    "wof:name":"Rentacet Tv & Video Hire",
    "wof:placetype":"venue"
},
  "geometry": {"coordinates":[-0.808822,52.063221],"type":"Point"}
}