{
  "type": "Feature",
  "properties": {
    "addr:full":"Bridgend Garden Centre, Freuchie Cupar Fife KY15 7HY",
    "addr:postcode":"ky15 7hy",
    "addr:street":"Bridgend;Freuchie",
    "iso:country":"GB",
    "sg:address":"Bridgend Garden Centre, Freuchie",
    "sg:city":"Cupar",
    "sg:classifiers":[
        {
            "category":"Cafe",
            "type":"Food & Drink"
        }
    ],
    "sg:postcode":"KY15 7HY",
    "sg:province":"Fife",
    "sg:tags":[
        "tea",
        "room"
    ],
    "wof:name":"Bridgend Coffee Shop",
    "wof:placetype":"venue"
},
  "geometry": {"coordinates":[-3.156949,56.247898],"type":"Point"}
}