{
  "type": "Feature",
  "properties": {
    "iso:country":"GB",
    "sg:address":"40a High Street, Highworth",
    "sg:city":"Swindon",
    "sg:classifiers":[
        {
            "category":"Real Estate",
            "subcategory":"Real Estate Agent",
            "type":"Services"
        }
    ],
    "sg:phone":"+44 1793 762407",
    "sg:postcode":"SN6 7AQ",
    "sg:province":"Gloucestershire",
    "wof:name":"Allen & Harris",
    "wof:placetype":"venue"
},
  "geometry": {"coordinates":[-1.7107360363,51.6307106018],"type":"Point"}
}