{
  "type": "Feature",
  "properties": {
    "addr:full":"4 Claridge Court, Lower Kings Road Berkhamsted Bedfordshire HP4 2AF",
    "addr:housenumber":"4",
    "addr:postcode":"hp4 2af",
    "addr:street":"Claridge Court;Kings Road",
    "iso:country":"GB",
    "sg:address":"4 Claridge Court, Lower Kings Road",
    "sg:city":"Berkhamsted",
    "sg:classifiers":[
        {
            "category":"Manufacturing",
            "subcategory":"Textiles",
            "type":"Manufacturing & Wholesale Goods"
        }
    ],
    "sg:phone":"+44 1442 877444",
    "sg:postcode":"HP4 2AF",
    "sg:province":"Bedfordshire",
    "sg:tags":[
        "made-up"
    ],
    "wof:name":"Westpoint Stevens (Europe) Ltd.",
    "wof:placetype":"venue"
},
  "geometry": {"coordinates":[-0.5645589828,51.7604141235],"type":"Point"}
}