{
  "type": "Feature",
  "properties": {
    "addr:full":"744 High Road London Greater London N12 9QG",
    "addr:housenumber":"744",
    "addr:postcode":"n12 9qg",
    "addr:street":"High Road",
    "iso:country":"GB",
    "sg:address":"744 High Road",
    "sg:city":"London",
    "sg:classifiers":[
        {
            "category":"Bars & Pubs",
            "type":"Food & Drink"
        },
        {
            "category":"Community Center",
            "subcategory":"Social",
            "type":"Public Place"
        }
    ],
    "sg:phone":"+44 20 8343 6951",
    "sg:postcode":"N12 9QG",
    "sg:province":"Greater London",
    "sg:tags":[
        "pubs",
        "house",
        "inn",
        "activity"
    ],
    "wof:name":"West Midlands Taverns Ltd.",
    "wof:placetype":"venue"
},
  "geometry": {"coordinates":[-0.1763450056,51.6148376465],"type":"Point"}
}