{
  "type": "Feature",
  "properties": {
    "iso:country":"GB",
    "sg:address":"Boothferry Rd",
    "sg:city":"Goole",
    "sg:classifiers":[
        {
            "category":"Community Center",
            "type":"Public Place"
        }
    ],
    "sg:phone":"+44 1405 837100",
    "sg:postcode":"DN14 6AE",
    "sg:province":"East Riding of Yorkshire",
    "sg:tags":[
        "centre"
    ],
    "wof:name":"Courtyard The",
    "wof:placetype":"venue"
},
  "geometry": {"coordinates":[-0.884182,53.707298],"type":"Point"}
}