{
  "type": "Feature",
  "properties": {
    "addr:full":"Baxtors Lane St Helens Cheshire WA9 3NE",
    "addr:postcode":"wa9 3ne",
    "addr:street":"Baxtors Lane",
    "iso:country":"GB",
    "sg:address":"Baxtors Lane",
    "sg:city":"St Helens",
    "sg:classifiers":[
        {
            "category":"Retail",
            "subcategory":"Storage",
            "type":"Services"
        }
    ],
    "sg:phone":"+44 161 969 4466",
    "sg:postcode":"WA9 3NE",
    "sg:province":"Cheshire",
    "sg:tags":[
        "household",
        "removal"
    ],
    "wof:name":"The Bowies International Removal Co",
    "wof:placetype":"venue"
},
  "geometry": {"coordinates":[-2.711569,53.44194],"type":"Point"}
}