{
  "type": "Feature",
  "properties": {
    "addr:full":"Franks Farm, Creek Fen March Cambridgeshire PE15 0BT",
    "addr:postcode":"pe15 0bt",
    "addr:street":"March",
    "iso:country":"GB",
    "sg:address":"Franks Farm, Creek Fen",
    "sg:city":"March",
    "sg:classifiers":[
        {
            "category":"Farming",
            "subcategory":"Livestock Farm",
            "type":"Manufacturing & Wholesale Goods"
        }
    ],
    "sg:phone":"+44 1354 652242",
    "sg:postcode":"PE15 0BT",
    "sg:province":"Cambridgeshire",
    "sg:tags":[
        "others"
    ],
    "wof:name":"D H Deptford",
    "wof:placetype":"venue"
},
  "geometry": {"coordinates":[0.0889049992,52.5512542725],"type":"Point"}
}