{
  "type": "Feature",
  "properties": {
    "addr:full":"14 Paddock Gardens London Greater London SE19 3SB",
    "addr:housenumber":"14",
    "addr:postcode":"se19 3sb",
    "addr:street":"Paddock Gardens",
    "iso:country":"GB",
    "sg:address":"14 Paddock Gardens",
    "sg:city":"London",
    "sg:classifiers":[
        {
            "category":"Arts & Performance",
            "subcategory":"Arts Center",
            "type":"Entertainment"
        },
        {
            "category":"Manufacturing",
            "subcategory":"Wood Products",
            "type":"Manufacturing & Wholesale Goods"
        }
    ],
    "sg:phone":"+44 20 8766 7865",
    "sg:postcode":"SE19 3SB",
    "sg:province":"Greater London",
    "sg:tags":[
        "cabinet",
        "maker",
        "centre"
    ],
    "wof:name":"Gypsyhill Workshop",
    "wof:placetype":"venue"
},
  "geometry": {"coordinates":[-0.082043,51.41943],"type":"Point"}
}