{
  "type": "Feature",
  "properties": {
    "addr:full":"498 Ashley Road Poole Dorset BH14 0AD",
    "addr:housenumber":"498",
    "addr:postcode":"bh14 0ad",
    "addr:street":"Ashley Road",
    "iso:country":"GB",
    "sg:address":"498 Ashley Road",
    "sg:city":"Poole",
    "sg:classifiers":[
        {
            "category":"Home & Garden",
            "subcategory":"Home Furnishings",
            "type":"Retail Goods"
        },
        {
            "category":"Home & Garden",
            "subcategory":"Building Materials",
            "type":"Retail Goods"
        }
    ],
    "sg:phone":"+44 1202 749290",
    "sg:postcode":"BH14 0AD",
    "sg:province":"Dorset",
    "sg:tags":[
        "merchant",
        "paint",
        "diy",
        "decorators'",
        "manufacturer"
    ],
    "wof:name":"HURST DECORATING SUPPLIES",
    "wof:placetype":"venue"
},
  "geometry": {"coordinates":[-1.943723,50.729156],"type":"Point"}
}