{
  "type": "Feature",
  "properties": {
    "addr:full":"569 Lanark Road Juniper Green City of Edinburgh EH14 5DB",
    "addr:housenumber":"569",
    "addr:postcode":"eh14 5db",
    "addr:street":"Lanark Road",
    "iso:country":"GB",
    "sg:address":"569 Lanark Road",
    "sg:city":"Juniper Green",
    "sg:classifiers":[
        {
            "category":"Professional",
            "subcategory":"Engineering",
            "type":"Services"
        }
    ],
    "sg:phone":"+44 131 453 3032",
    "sg:postcode":"EH14 5DB",
    "sg:province":"City of Edinburgh",
    "sg:tags":[
        "contractor",
        "electrical",
        "engineer"
    ],
    "wof:name":"George  Byers",
    "wof:placetype":"venue"
},
  "geometry": {"coordinates":[-3.2880840302,55.9022026062],"type":"Point"}
}