{
  "type": "Feature",
  "properties": {
    "addr:full":"2a Anning Street, Greenwich Kent London Greater London SE10 9PH",
    "addr:housenumber":"2a",
    "addr:postcode":"se10 9ph",
    "addr:street":"Anning Street",
    "iso:country":"GB",
    "sg:address":"2a Anning Street, Greenwich Kent",
    "sg:city":"London",
    "sg:classifiers":[
        {
            "category":"Shopping",
            "subcategory":"Pharmacy",
            "type":"Retail Goods"
        }
    ],
    "sg:phone":"+44 20 8293 4113",
    "sg:postcode":"SE10 9PH",
    "sg:province":"Greater London",
    "sg:tags":[
        "medicine",
        "therapy"
    ],
    "wof:name":"Ruthie Smith",
    "wof:placetype":"venue"
},
  "geometry": {"coordinates":[0.00077,51.4855804443],"type":"Point"}
}