{
  "type": "Feature",
  "properties": {
    "addr:full":"Suite 5, 423 Victoria Road Glasgow Glasgow City G42 8RW",
    "addr:housenumber":"suite 5 423",
    "addr:postcode":"g42 8rw",
    "addr:street":"Victoria Road",
    "iso:country":"GB",
    "sg:address":"Suite 5, 423 Victoria Road",
    "sg:city":"Glasgow",
    "sg:classifiers":[
        {
            "category":"Real Estate",
            "subcategory":"Real Estate Agent",
            "type":"Services"
        }
    ],
    "sg:postcode":"G42 8RW",
    "sg:province":"Glasgow City",
    "wof:name":"Knightswood Ltd",
    "wof:placetype":"venue"
},
  "geometry": {"coordinates":[-4.264774,55.83617],"type":"Point"}
}