{
  "type": "Feature",
  "properties": {
    "iso:country":"GB",
    "sg:address":"84 Lincoln Way",
    "sg:city":"Corby",
    "sg:classifiers":[
        {
            "category":"Food & Beverages",
            "subcategory":"Supermarket",
            "type":"Retail Goods"
        }
    ],
    "sg:phone":"+44 1536 741151",
    "sg:postcode":"NN18 9HN",
    "sg:province":"Northamptonshire",
    "wof:name":"Lincoln Way Store",
    "wof:placetype":"venue"
},
  "geometry": {"coordinates":[-0.715314,52.480484],"type":"Point"}
}