{
  "type": "Feature",
  "properties": {
    "addr:full":"Padmores, St Johns Mews, St Johns Woking Surrey GU21 7ZE",
    "addr:postcode":"gu21 7ze",
    "addr:street":"St Johns Mews St",
    "iso:country":"GB",
    "sg:address":"Padmores, St Johns Mews, St Johns",
    "sg:city":"Woking",
    "sg:classifiers":[
        {
            "category":"Professional",
            "subcategory":"Management & Consulting",
            "type":"Services"
        }
    ],
    "sg:phone":"+44 1483 776629",
    "sg:postcode":"GU21 7ZE",
    "sg:province":"Surrey",
    "sg:tags":[
        "consultant",
        "business"
    ],
    "wof:name":"W A S P Consulting Ltd.",
    "wof:placetype":"venue"
},
  "geometry": {"coordinates":[-0.59433,51.312801],"type":"Point"}
}