{
  "type": "Feature",
  "properties": {
    "addr:full":"3 Dunelm Ct, Sedgefield Stockton-on-tees Durham TS21 2JS",
    "addr:housenumber":"3",
    "addr:postcode":"ts21 2js",
    "addr:street":"Dunelm Ct",
    "iso:country":"GB",
    "sg:address":"3 Dunelm Ct, Sedgefield",
    "sg:city":"Stockton-on-tees",
    "sg:classifiers":[
        {
            "category":"Bus Charters",
            "type":"Transportation"
        }
    ],
    "sg:postcode":"TS21 2JS",
    "sg:province":"Durham",
    "sg:tags":[
        "hire",
        "coach"
    ],
    "wof:name":"Metcalfe,Brian,",
    "wof:placetype":"venue"
},
  "geometry": {"coordinates":[-1.4543850422,54.6515159607],"type":"Point"}
}