{
  "type": "Feature",
  "properties": {
    "iso:country":"GB",
    "sg:address":"17 Wrotham Rd",
    "sg:city":"Welling",
    "sg:classifiers":[
        {
            "category":"Organizations",
            "subcategory":"Political Organization",
            "type":"Services"
        }
    ],
    "sg:phone":"+44 20 8304 1461",
    "sg:postcode":"DA16 1LR",
    "sg:province":"Kent",
    "sg:tags":[
        "party"
    ],
    "wof:name":"Liberal Democrats (Trustees) Ltd (The)",
    "wof:placetype":"venue"
},
  "geometry": {"coordinates":[0.119232,51.469353],"type":"Point"}
}