{
  "type": "Feature",
  "properties": {
    "addr:full":"22 Church St Blackpool Lancashire FY1 1EW",
    "addr:housenumber":"22",
    "addr:postcode":"fy1 1ew",
    "addr:street":"Church St",
    "iso:country":"GB",
    "sg:address":"22 Church St",
    "sg:city":"Blackpool",
    "sg:classifiers":[
        {
            "category":"Shopping",
            "subcategory":"Bicycles & Sporting Goods",
            "type":"Retail Goods"
        }
    ],
    "sg:phone":"+44 1253 628430",
    "sg:postcode":"FY1 1EW",
    "sg:province":"Lancashire",
    "sg:tags":[
        "equipment",
        "camping"
    ],
    "wof:name":"Famous Army Stores Ltd",
    "wof:placetype":"venue"
},
  "geometry": {"coordinates":[-3.0547590256,53.8173599243],"type":"Point"}
}