{
  "type": "Feature",
  "properties": {
    "addr:full":"13 The Green Southall Greater London UB2 4AH",
    "addr:housenumber":"13",
    "addr:postcode":"ub2 4ah",
    "addr:street":"The Green",
    "iso:country":"GB",
    "sg:address":"13 The Green",
    "sg:city":"Southall",
    "sg:classifiers":[
        {
            "category":"Professional",
            "subcategory":"Accounting & Tax Preparation",
            "type":"Services"
        }
    ],
    "sg:phone":"+44 20 8574 0762",
    "sg:postcode":"UB2 4AH",
    "sg:province":"Greater London",
    "sg:tags":[
        "accountant",
        "activity"
    ],
    "wof:name":"Tack & Co",
    "wof:placetype":"venue"
},
  "geometry": {"coordinates":[-0.37955001,51.5047645569],"type":"Point"}
}