{
  "type": "Feature",
  "properties": {
    "addr:full":"7 Bordesley Green Rd Birmingham West Midlands B9 4TR",
    "addr:housenumber":"7",
    "addr:postcode":"b9 4tr",
    "addr:street":"Bordesley Green Rd",
    "iso:country":"GB",
    "sg:address":"7 Bordesley Green Rd",
    "sg:city":"Birmingham",
    "sg:classifiers":[
        {
            "category":"Home & Garden",
            "subcategory":"Household Appliances",
            "type":"Retail Goods"
        }
    ],
    "sg:phone":"+44 121 773 0450",
    "sg:postcode":"B9 4TR",
    "sg:province":"West Midlands",
    "sg:tags":[
        "domestic",
        "centre"
    ],
    "wof:name":"Discount Cookers",
    "wof:placetype":"venue"
},
  "geometry": {"coordinates":[-1.85682,52.477924],"type":"Point"}
}