{
  "type": "Feature",
  "properties": {
    "addr:full":"5 Station Rd York East Riding of Yorkshire YO3 3LR",
    "addr:housenumber":"5",
    "addr:postcode":"yo3 3lr",
    "addr:street":"Station Rd",
    "iso:country":"GB",
    "sg:address":"5 Station Rd",
    "sg:city":"York",
    "sg:classifiers":[
        {
            "category":"Conference Center",
            "type":"Public Place"
        }
    ],
    "sg:phone":"+44 1904 750066",
    "sg:postcode":"YO3 3LR",
    "sg:province":"East Riding of Yorkshire",
    "wof:name":"Creative Fact",
    "wof:placetype":"venue"
},
  "geometry": {"coordinates":[-1.0715210438,54.0161972046],"type":"Point"}
}