{
  "type": "Feature",
  "properties": {
    "addr:full":"26 Bridge Industries Fareham Hampshire PO16 8SX",
    "addr:housenumber":"26",
    "addr:postcode":"po16 8sx",
    "iso:country":"GB",
    "sg:address":"26 Bridge Industries",
    "sg:city":"Fareham",
    "sg:classifiers":[
        {
            "category":"Professional",
            "subcategory":"Detective & Security Services",
            "type":"Services"
        }
    ],
    "sg:phone":"+44 1329 235116",
    "sg:postcode":"PO16 8SX",
    "sg:province":"Hampshire",
    "sg:tags":[
        "alarm",
        "burglar",
        "system"
    ],
    "wof:name":"Alarmis Security Systems",
    "wof:placetype":"venue"
},
  "geometry": {"coordinates":[-1.171249,50.861115],"type":"Point"}
}