{
  "type": "Feature",
  "properties": {
    "addr:full":"Ford Manor Road Lingfield Surrey RH7 6PA",
    "addr:postcode":"rh7 6pa",
    "addr:street":"Manor Road",
    "iso:country":"GB",
    "sg:address":"Ford Manor Road",
    "sg:city":"Lingfield",
    "sg:classifiers":[
        {
            "category":"Organizations",
            "subcategory":"Community Association",
            "type":"Services"
        },
        {
            "category":"Landmark",
            "subcategory":"Tourist Attraction",
            "type":"Public Place"
        }
    ],
    "sg:phone":"+44 1342 832577",
    "sg:postcode":"RH7 6PA",
    "sg:province":"Surrey",
    "sg:tags":[
        "society",
        "housing",
        "interest"
    ],
    "wof:name":"Greathed Manor",
    "wof:placetype":"venue"
},
  "geometry": {"coordinates":[-0.019686,51.17482],"type":"Point"}
}