{
  "type": "Feature",
  "properties": {
    "iso:country":"GB",
    "sg:address":"48 Wollaton Rd",
    "sg:city":"Nottingham",
    "sg:classifiers":[
        {
            "category":"Banks & Credit Unions",
            "subcategory":"Financial Services",
            "type":"Services"
        }
    ],
    "sg:phone":"+44 115 943 1919",
    "sg:postcode":"NG9 2NR",
    "sg:province":"Nottinghamshire",
    "sg:tags":[
        "adviser"
    ],
    "wof:name":"D B IndependentFinancial Services",
    "wof:placetype":"venue"
},
  "geometry": {"coordinates":[-1.2167619467,52.9282073975],"type":"Point"}
}