{
  "type": "Feature",
  "properties": {
    "addr:full":"88 Commercial Street Edinburgh City of Edinburgh EH6 6LX",
    "addr:housenumber":"88",
    "addr:postcode":"eh6 6lx",
    "addr:street":"Commercial Street",
    "iso:country":"GB",
    "sg:address":"88 Commercial Street",
    "sg:city":"Edinburgh",
    "sg:classifiers":[
        {
            "category":"Restaurant",
            "type":"Food & Drink"
        }
    ],
    "sg:phone":"+44 131 553 5933",
    "sg:postcode":"EH6 6LX",
    "sg:province":"City of Edinburgh",
    "sg:tags":[
        "-",
        "french"
    ],
    "wof:name":"Daniel's Bistro",
    "wof:placetype":"venue"
},
  "geometry": {"coordinates":[-3.175213,55.977177],"type":"Point"}
}