{
  "type": "Feature",
  "properties": {
    "iso:country":"GB",
    "sg:address":"84 Old Bedford Road",
    "sg:city":"Luton",
    "sg:classifiers":[
        {
            "category":"Cafe",
            "type":"Food & Drink"
        }
    ],
    "sg:phone":"+44 1582 425896",
    "sg:postcode":"LU2 7PD",
    "sg:province":"Bedfordshire",
    "sg:tags":[
        "tea",
        "snack",
        "bar",
        "room"
    ],
    "wof:name":"Gino Cafe",
    "wof:placetype":"venue"
},
  "geometry": {"coordinates":[-0.418111,51.885929],"type":"Point"}
}