{
  "type": "Feature",
  "properties": {
    "addr:full":"1 Gun Street Reading Berkshire RG1 2JR",
    "addr:housenumber":"1",
    "addr:postcode":"rg1 2jr",
    "addr:street":"Gun Street",
    "iso:country":"GB",
    "sg:address":"1 Gun Street",
    "sg:city":"Reading",
    "sg:classifiers":[
        {
            "category":"Bars & Pubs",
            "type":"Food & Drink"
        }
    ],
    "sg:phone":"+44 118 950 9191",
    "sg:postcode":"RG1 2JR",
    "sg:province":"Berkshire",
    "sg:tags":[
        "pubs",
        "inn"
    ],
    "wof:name":"J W & Co",
    "wof:placetype":"venue"
},
  "geometry": {"coordinates":[-0.9735080004,51.4537887573],"type":"Point"}
}