{
  "type": "Feature",
  "properties": {
    "addr:full":"12 St John Street Bromsgrove Worcestershire B61 8QZ",
    "addr:housenumber":"12",
    "addr:postcode":"b61 8qz",
    "addr:street":"St John Street",
    "iso:country":"GB",
    "sg:address":"12 St John Street",
    "sg:city":"Bromsgrove",
    "sg:classifiers":[
        {
            "category":"Real Estate",
            "subcategory":"Real Estate Agent",
            "type":"Services"
        }
    ],
    "sg:phone":"+44 1527 832222",
    "sg:postcode":"B61 8QZ",
    "sg:province":"Worcestershire",
    "wof:name":"A Victor Powell",
    "wof:placetype":"venue"
},
  "geometry": {"coordinates":[-2.0639019012,52.333782196],"type":"Point"}
}