{
  "type": "Feature",
  "properties": {
    "iso:country":"GB",
    "sg:address":"34 Nunhouse Drive",
    "sg:city":"Winsford",
    "sg:classifiers":[
        {
            "category":"Manufacturing",
            "subcategory":"Petroleum Products",
            "type":"Manufacturing & Wholesale Goods"
        }
    ],
    "sg:postcode":"CW7 3JT",
    "sg:province":"Cheshire",
    "sg:tags":[
        "double",
        "glazing"
    ],
    "wof:name":"Steve Dunning Joiners",
    "wof:placetype":"venue"
},
  "geometry": {"coordinates":[-2.502187,53.19416],"type":"Point"}
}