{
  "type": "Feature",
  "properties": {
    "iso:country":"GB",
    "sg:address":"97 Wood Lane, Timperley",
    "sg:city":"Altrincham",
    "sg:classifiers":[
        {
            "category":"Personal",
            "subcategory":"Beauty Salon",
            "type":"Services"
        }
    ],
    "sg:phone":"+44 161 980 2331",
    "sg:postcode":"WA15 7PG",
    "sg:province":"Cheshire",
    "sg:tags":[
        "lady",
        "hairdresser"
    ],
    "wof:name":"Hairline",
    "wof:placetype":"venue"
},
  "geometry": {"coordinates":[-2.3206410408,53.3885688782],"type":"Point"}
}