{
  "type": "Feature",
  "properties": {
    "addr:full":"25 Waldgrave Road Liverpool Merseyside L15 7JL",
    "addr:housenumber":"25",
    "addr:postcode":"l15 7jl",
    "addr:street":"Waldgrave Road",
    "iso:country":"GB",
    "sg:address":"25 Waldgrave Road",
    "sg:city":"Liverpool",
    "sg:classifiers":[
        {
            "category":"Building & Trades",
            "subcategory":"Construction",
            "type":"Services"
        }
    ],
    "sg:postcode":"L15 7JL",
    "sg:province":"Merseyside",
    "sg:tags":[
        "builder"
    ],
    "wof:name":"Building Advisory Service",
    "wof:placetype":"venue"
},
  "geometry": {"coordinates":[-2.9116959572,53.4053268433],"type":"Point"}
}