{
  "type": "Feature",
  "properties": {
    "iso:country":"GB",
    "sg:address":"23 Linden Road",
    "sg:city":"Hinckley",
    "sg:classifiers":[
        {
            "category":"Communications",
            "subcategory":"Film & Video Production",
            "type":"Services"
        },
        {
            "category":"Professional",
            "subcategory":"Art Services",
            "type":"Services"
        }
    ],
    "sg:phone":"+44 1455 614013",
    "sg:postcode":"LE10 0AR",
    "sg:province":"Leicestershire",
    "sg:tags":[
        "photographer",
        "illustrator",
        "artist"
    ],
    "wof:name":"David G Hall",
    "wof:placetype":"venue"
},
  "geometry": {"coordinates":[-1.379102,52.54319],"type":"Point"}
}