{
  "type": "Feature",
  "properties": {
    "addr:full":"Mill Barn High Street, Whitwell Hitchin Hertfordshire SG4 8AG",
    "addr:postcode":"sg4 8ag",
    "addr:street":"High Street",
    "iso:country":"GB",
    "sg:address":"Mill Barn High Street, Whitwell",
    "sg:city":"Hitchin",
    "sg:classifiers":[
        {
            "category":"Shopping",
            "subcategory":"Antiques",
            "type":"Retail Goods"
        }
    ],
    "sg:postcode":"SG4 8AG",
    "sg:province":"Hertfordshire",
    "wof:name":"R & V Restorers",
    "wof:placetype":"venue"
},
  "geometry": {"coordinates":[-0.2825750113,51.8764190674],"type":"Point"}
}