{
  "type": "Feature",
  "properties": {
    "iso:country":"GB",
    "sg:address":"27 Cross Street",
    "sg:city":"Willenhall",
    "sg:classifiers":[
        {
            "category":"Shopping",
            "subcategory":"Florist",
            "type":"Retail Goods"
        }
    ],
    "sg:phone":"+44 1902 632636",
    "sg:postcode":"WV13 1PG",
    "sg:province":"West Midlands",
    "wof:name":"Belle Fleur",
    "wof:placetype":"venue"
},
  "geometry": {"coordinates":[-2.054229,52.583771],"type":"Point"}
}