{
  "type": "Feature",
  "properties": {
    "addr:full":"Lower House Farm, Kemeys Commander Usk Monmouthshire NP15 1JU",
    "addr:postcode":"np15 1ju",
    "addr:street":"Lower House",
    "iso:country":"GB",
    "sg:address":"Lower House Farm, Kemeys Commander",
    "sg:city":"Usk",
    "sg:classifiers":[
        {
            "category":"Farming",
            "subcategory":"Livestock Farm",
            "type":"Manufacturing & Wholesale Goods"
        },
        {
            "category":"Farming",
            "subcategory":"Farm",
            "type":"Manufacturing & Wholesale Goods"
        }
    ],
    "sg:phone":"+44 1873 880279",
    "sg:postcode":"NP15 1JU",
    "sg:province":"Monmouthshire",
    "sg:tags":[
        "mixed",
        "others"
    ],
    "wof:name":"J & G Morgan",
    "wof:placetype":"venue"
},
  "geometry": {"coordinates":[-2.902848959,51.7037353516],"type":"Point"}
}