{
  "type": "Feature",
  "properties": {
    "addr:full":"Allanton Mill Shotts North Lanarkshire ML7 5BX",
    "addr:postcode":"ml7 5bx",
    "addr:street":"Allanton",
    "iso:country":"GB",
    "sg:address":"Allanton Mill",
    "sg:city":"Shotts",
    "sg:classifiers":[
        {
            "category":"Wholesale",
            "subcategory":"Farm Supplies",
            "type":"Manufacturing & Wholesale Goods"
        }
    ],
    "sg:phone":"+44 1501 21714",
    "sg:postcode":"ML7 5BX",
    "sg:province":"North Lanarkshire",
    "sg:tags":[
        "merchant",
        "grain"
    ],
    "wof:name":"Galloway & Macleod Ltd",
    "wof:placetype":"venue"
},
  "geometry": {"coordinates":[-3.828625,55.801323],"type":"Point"}
}