{
  "type": "Feature",
  "properties": {
    "addr:full":"578 Roman Road London Greater London E3 5ES",
    "addr:housenumber":"578",
    "addr:postcode":"e3 5es",
    "addr:street":"Roman Road",
    "iso:country":"GB",
    "sg:address":"578 Roman Road",
    "sg:city":"London",
    "sg:classifiers":[
        {
            "category":"Food & Beverages",
            "subcategory":"Meat & Fish",
            "type":"Retail Goods"
        }
    ],
    "sg:phone":"+44 20 8980 3813",
    "sg:postcode":"E3 5ES",
    "sg:province":"Greater London",
    "sg:tags":[
        "butcher"
    ],
    "wof:name":"C Applegate Ltd.",
    "wof:placetype":"venue"
},
  "geometry": {"coordinates":[-0.02882,51.533218],"type":"Point"}
}