{
  "type": "Feature",
  "properties": {
    "addr:full":"Morrison Activity Centre, Slate Street Swansea Swansea SA6 8AA",
    "addr:postcode":"sa6 8aa",
    "addr:street":"Slate Street",
    "iso:country":"GB",
    "sg:address":"Morrison Activity Centre, Slate Street",
    "sg:city":"Swansea",
    "sg:classifiers":[
        {
            "category":"Organizations",
            "subcategory":"Non-profit Organization",
            "type":"Services"
        }
    ],
    "sg:postcode":"SA6 8AA",
    "sg:province":"Swansea",
    "sg:tags":[
        "organisation",
        "voluntary",
        "charity"
    ],
    "wof:name":"Lay Advocacy Ltd.",
    "wof:placetype":"venue"
},
  "geometry": {"coordinates":[-3.936699,51.647236],"type":"Point"}
}