{
  "type": "Feature",
  "properties": {
    "iso:country":"GB",
    "sg:address":"Dolcie Domun, Pound Lane, North Benfleet",
    "sg:city":"Wickford",
    "sg:classifiers":[
        {
            "category":"Retail",
            "subcategory":"Auto Repair",
            "type":"Services"
        }
    ],
    "sg:phone":"+44 1268 591198",
    "sg:postcode":"SS12 9JS",
    "sg:province":"Essex",
    "sg:tags":[
        "modification",
        "garage"
    ],
    "wof:name":"Thomas John Walker",
    "wof:placetype":"venue"
},
  "geometry": {"coordinates":[0.5343000293,51.5830802917],"type":"Point"}
}