{
  "type": "Feature",
  "properties": {
    "addr:full":"Milestone House, 105-109 Cannon Street London Greater London EC4N 5AD",
    "addr:housenumber":"105-109",
    "addr:postcode":"ec4n 5ad",
    "addr:street":"Cannon Street",
    "iso:country":"GB",
    "sg:address":"Milestone House, 105-109 Cannon Street",
    "sg:city":"London",
    "sg:classifiers":[
        {
            "category":"Banks & Credit Unions",
            "subcategory":"Bank",
            "type":"Services"
        }
    ],
    "sg:phone":"+44 845 765 4321",
    "sg:postcode":"EC4N 5AD",
    "sg:province":"Greater London",
    "wof:name":"Abbey National Plc",
    "wof:placetype":"venue"
},
  "geometry": {"coordinates":[-0.0906,51.51173],"type":"Point"}
}