{
  "type": "Feature",
  "properties": {
    "addr:full":"Stirling Works, Tewin Road Welwyn Garden City Hertfordshire AL7 1AG",
    "addr:postcode":"al7 1ag",
    "addr:street":"Tewin Road",
    "iso:country":"GB",
    "sg:address":"Stirling Works, Tewin Road",
    "sg:city":"Welwyn Garden City",
    "sg:classifiers":[
        {
            "category":"Manufacturing",
            "subcategory":"Metals",
            "type":"Manufacturing & Wholesale Goods"
        }
    ],
    "sg:phone":"+44 1707 324327",
    "sg:postcode":"AL7 1AG",
    "sg:province":"Hertfordshire",
    "sg:tags":[
        "steel",
        "stockholder"
    ],
    "wof:name":"Barnet Metal & Engineering Co. Ltd.",
    "wof:placetype":"venue"
},
  "geometry": {"coordinates":[-0.1942799985,51.8035011292],"type":"Point"}
}