{
  "type": "Feature",
  "properties": {
    "addr:full":"28 Murray Place Stirling Stirling FK8 2DD",
    "addr:housenumber":"28",
    "addr:postcode":"fk8 2dd",
    "addr:street":"Murray Place",
    "iso:country":"GB",
    "sg:address":"28 Murray Place",
    "sg:city":"Stirling",
    "sg:classifiers":[
        {
            "category":"Personal",
            "subcategory":"Beauty Salon",
            "type":"Services"
        },
        {
            "category":"Personal",
            "subcategory":"Barber",
            "type":"Services"
        }
    ],
    "sg:phone":"+44 1786 472424",
    "sg:postcode":"FK8 2DD",
    "sg:province":"Stirling",
    "sg:tags":[
        "unisex",
        "hairdresser"
    ],
    "wof:name":"Into Hair",
    "wof:placetype":"venue"
},
  "geometry": {"coordinates":[-3.9371490479,56.1194381714],"type":"Point"}
}