{
  "type": "Feature",
  "properties": {
    "addr:full":"280 High Street West Bromwich West Midlands B70 8AQ",
    "addr:housenumber":"280",
    "addr:postcode":"b70 8aq",
    "addr:street":"High Street",
    "iso:country":"GB",
    "sg:address":"280 High Street",
    "sg:city":"West Bromwich",
    "sg:classifiers":[
        {
            "category":"Shopping",
            "subcategory":"Mobile Phones",
            "type":"Retail Goods"
        }
    ],
    "sg:postcode":"B70 8AQ",
    "sg:province":"West Midlands",
    "wof:name":"A C Communications",
    "wof:placetype":"venue"
},
  "geometry": {"coordinates":[-1.995498,52.519257],"type":"Point"}
}