{
  "type": "Feature",
  "properties": {
    "addr:full":"Dyfnog Stud, Llanrhaeadr Denbigh Conwy LL16 4NG",
    "addr:postcode":"ll16 4ng",
    "addr:street":"Llanrhaeadr",
    "iso:country":"GB",
    "sg:address":"Dyfnog Stud, Llanrhaeadr",
    "sg:city":"Denbigh",
    "sg:classifiers":[
        {
            "category":"Shopping",
            "subcategory":"Bicycles & Sporting Goods",
            "type":"Retail Goods"
        }
    ],
    "sg:postcode":"LL16 4NG",
    "sg:province":"Conwy",
    "sg:tags":[
        "riding",
        "saddlery",
        "wear"
    ],
    "wof:name":"Dynfog Stud",
    "wof:placetype":"venue"
},
  "geometry": {"coordinates":[-3.373324,53.159065],"type":"Point"}
}