{
  "type": "Feature",
  "properties": {
    "addr:full":"3 Church Street Ilfracombe Devon EX34 8HA",
    "addr:housenumber":"3",
    "addr:postcode":"ex34 8ha",
    "addr:street":"Church Street",
    "iso:country":"GB",
    "sg:address":"3 Church Street",
    "sg:city":"Ilfracombe",
    "sg:classifiers":[
        {
            "category":"Travel",
            "subcategory":"Travel Agent",
            "type":"Entertainment"
        }
    ],
    "sg:phone":"+44 1271 862626",
    "sg:postcode":"EX34 8HA",
    "sg:province":"Devon",
    "wof:name":"Let's Go Travel",
    "wof:placetype":"venue"
},
  "geometry": {"coordinates":[-4.126362,51.206226],"type":"Point"}
}