{
  "type": "Feature",
  "properties": {
    "addr:full":"304 Wrythe Lane Carshalton Surrey SM5 1AF",
    "addr:housenumber":"304",
    "addr:postcode":"sm5 1af",
    "addr:street":"Wrythe Lane",
    "iso:country":"GB",
    "sg:address":"304 Wrythe Lane",
    "sg:city":"Carshalton",
    "sg:classifiers":[
        {
            "category":"Retail",
            "subcategory":"Funeral Services",
            "type":"Services"
        }
    ],
    "sg:phone":"+44 20 8644 9607",
    "sg:postcode":"SM5 1AF",
    "sg:province":"Surrey",
    "wof:name":"Alfred Smith Funeral Directors",
    "wof:placetype":"venue"
},
  "geometry": {"coordinates":[-0.1882089972,51.3833312988],"type":"Point"}
}