{
  "type": "Feature",
  "properties": {
    "iso:country":"GB",
    "sg:address":"Church Road, Coseley",
    "sg:city":"Bilston",
    "sg:classifiers":[
        {
            "category":"Education",
            "subcategory":"School",
            "type":"Public Place"
        },
        {
            "category":"Government",
            "subcategory":"Office",
            "type":"Public Place"
        }
    ],
    "sg:phone":"+44 1384 818375",
    "sg:postcode":"WV14 8YB",
    "sg:province":"West Midlands",
    "sg:tags":[
        "local",
        "authority"
    ],
    "wof:name":"Christ Church C of E Primary School",
    "wof:placetype":"venue"
},
  "geometry": {"coordinates":[-2.079603,52.546223],"type":"Point"}
}