{
  "type": "Feature",
  "properties": {
    "addr:full":"67 Rider Haggard Rd Norwich Norfolk NR7 9UA",
    "addr:housenumber":"67",
    "addr:postcode":"nr7 9ua",
    "addr:street":"Rider Haggard Rd",
    "iso:country":"GB",
    "sg:address":"67 Rider Haggard Rd",
    "sg:city":"Norwich",
    "sg:classifiers":[
        {
            "category":"Professional",
            "subcategory":"Art Services",
            "type":"Services"
        }
    ],
    "sg:phone":"+44 1603 438396",
    "sg:postcode":"NR7 9UA",
    "sg:province":"Norfolk",
    "sg:tags":[
        "photographer"
    ],
    "wof:name":"The Dog Portrait Co",
    "wof:placetype":"venue"
},
  "geometry": {"coordinates":[1.3311450481,52.6424026489],"type":"Point"}
}