{
  "type": "Feature",
  "properties": {
    "addr:full":"9 Ronaldsway Rhyl Conwy LL18 2LB",
    "addr:housenumber":"9",
    "addr:postcode":"ll18 2lb",
    "addr:street":"Ronaldsway",
    "iso:country":"GB",
    "sg:address":"9 Ronaldsway",
    "sg:city":"Rhyl",
    "sg:classifiers":[
        {
            "category":"Recreation",
            "subcategory":"Boat Charter",
            "type":"Entertainment"
        }
    ],
    "sg:postcode":"LL18 2LB",
    "sg:province":"Conwy",
    "sg:tags":[
        "excursion"
    ],
    "wof:name":"Blue Shark Sea Fishing Trips",
    "wof:placetype":"venue"
},
  "geometry": {"coordinates":[-3.4761989117,53.3122138977],"type":"Point"}
}