{
  "type": "Feature",
  "properties": {
    "addr:full":"Unit N Kingsway Industrial Estate, Kingsway Luton Bedfordshire LU1 1LP",
    "addr:housenumber":"estate",
    "addr:postcode":"lu1 1lp",
    "addr:street":"Kingsway Industrial;Kingsway",
    "iso:country":"GB",
    "sg:address":"Unit N Kingsway Industrial Estate, Kingsway",
    "sg:city":"Luton",
    "sg:classifiers":[
        {
            "category":"Utilities",
            "subcategory":"Electric",
            "type":"Services"
        },
        {
            "category":"Shopping",
            "subcategory":"Computers & Home Electronics",
            "type":"Retail Goods"
        }
    ],
    "sg:phone":"+44 1582 488800",
    "sg:postcode":"LU1 1LP",
    "sg:province":"Bedfordshire",
    "sg:tags":[
        "distribution",
        "electrical"
    ],
    "sg:website":"http://www.ambleelectrical.co.uk",
    "wof:name":"Amble Electrical Distributors Ltd.",
    "wof:placetype":"venue"
},
  "geometry": {"coordinates":[-0.442524,51.884666],"type":"Point"}
}