{
  "type": "Feature",
  "properties": {
    "iso:country":"GB",
    "sg:address":"1 Hartington Street",
    "sg:city":"Chester",
    "sg:classifiers":[
        {
            "category":"Bars & Pubs",
            "type":"Food & Drink"
        }
    ],
    "sg:phone":"+44 1244 671070",
    "sg:postcode":"CH4 7BN",
    "sg:province":"Cheshire",
    "sg:tags":[
        "pubs",
        "inn"
    ],
    "wof:name":"L F Tills",
    "wof:placetype":"venue"
},
  "geometry": {"coordinates":[-2.885029,53.18301],"type":"Point"}
}