{
  "type": "Feature",
  "properties": {
    "iso:country":"GB",
    "sg:address":"123 Oaklands Rd, Hanwell",
    "sg:city":"Hanwell",
    "sg:classifiers":[
        {
            "category":"Professional",
            "subcategory":"Accounting & Tax Preparation",
            "type":"Services"
        }
    ],
    "sg:phone":"+44 20 8567 5379",
    "sg:postcode":"W7 2DT",
    "sg:province":"Greater London",
    "sg:tags":[
        "accountant"
    ],
    "wof:name":"Johal & Co",
    "wof:placetype":"venue"
},
  "geometry": {"coordinates":[-0.327694,51.506683],"type":"Point"}
}