{
  "type": "Feature",
  "properties": {
    "addr:full":"5 Littlestone Rd New Romney Kent TN28 8LN",
    "addr:housenumber":"5",
    "addr:postcode":"tn28 8ln",
    "addr:street":"Littlestone Rd",
    "iso:country":"GB",
    "sg:address":"5 Littlestone Rd",
    "sg:city":"New Romney",
    "sg:classifiers":[
        {
            "category":"Shopping",
            "subcategory":"Gifts & Souvenirs",
            "type":"Retail Goods"
        }
    ],
    "sg:postcode":"TN28 8LN",
    "sg:province":"Kent",
    "sg:tags":[
        "shop"
    ],
    "wof:name":"Wood,P D,",
    "wof:placetype":"venue"
},
  "geometry": {"coordinates":[0.954107,50.985115],"type":"Point"}
}