{
  "type": "Feature",
  "properties": {
    "iso:country":"GB",
    "sg:address":"Crank School, Crank Hill, Crank",
    "sg:city":"St Helens",
    "sg:classifiers":[
        {
            "category":"Farming",
            "subcategory":"Nursery",
            "type":"Manufacturing & Wholesale Goods"
        }
    ],
    "sg:phone":"+44 1744 886166",
    "sg:postcode":"WA11 7SD",
    "sg:province":"Lancashire",
    "sg:tags":[
        "creche"
    ],
    "wof:name":"Crank Nursery Ltd.",
    "wof:placetype":"venue"
},
  "geometry": {"coordinates":[-2.7465600967,53.4915390015],"type":"Point"}
}