{
  "type": "Feature",
  "properties": {
    "iso:country":"GB",
    "sg:address":"Pino Ho, Ashleigh Indstl Est, Westmoor St",
    "sg:city":"London",
    "sg:classifiers":[
        {
            "category":"Sports & Exercise",
            "subcategory":"Athletic Track",
            "type":"Entertainment"
        }
    ],
    "sg:phone":"+44 181 305 1813",
    "sg:postcode":"SE7 8NQ",
    "sg:province":"Greater London",
    "sg:tags":[
        "bags",
        "accessory",
        "belt"
    ],
    "wof:name":"Pino Marketing Plc",
    "wof:placetype":"venue"
},
  "geometry": {"coordinates":[0.03799,51.492409],"type":"Point"}
}