{
  "type": "Feature",
  "properties": {
    "addr:full":"Allanbrook Road, Rosehill Industrial Estate Carlisle Cumbria CA1 2UX",
    "addr:housenumber":"estate",
    "addr:postcode":"ca1 2ux",
    "addr:street":"Allanbrook Road;Industrial",
    "iso:country":"GB",
    "sg:address":"Allanbrook Road, Rosehill Industrial Estate",
    "sg:city":"Carlisle",
    "sg:classifiers":[
        {
            "category":"Professional",
            "subcategory":"Employment Agencies",
            "type":"Services"
        }
    ],
    "sg:phone":"+44 1228 818058",
    "sg:postcode":"CA1 2UX",
    "sg:province":"Cumbria",
    "sg:tags":[
        "agricultural",
        "advice"
    ],
    "wof:name":"W C F Country Centres",
    "wof:placetype":"venue"
},
  "geometry": {"coordinates":[-2.894094944,54.8919448853],"type":"Point"}
}