{
  "type": "Feature",
  "properties": {
    "iso:country":"GB",
    "sg:address":"272 Harehills Lane",
    "sg:city":"Leeds",
    "sg:classifiers":[
        {
            "category":"Real Estate",
            "subcategory":"Real Estate Agent",
            "type":"Services"
        }
    ],
    "sg:phone":"+44 113 293 6030",
    "sg:postcode":"LS9 7BD",
    "sg:province":"West Yorkshire",
    "wof:name":"Adel Properties (Leeds) Ltd.",
    "wof:placetype":"venue"
},
  "geometry": {"coordinates":[-1.5110009909,53.810344696],"type":"Point"}
}