{
  "type": "Feature",
  "properties": {
    "addr:full":"72 Norwich Rd Dereham Norfolk NR20 3AR",
    "addr:housenumber":"72",
    "addr:postcode":"nr20 3ar",
    "addr:street":"Norwich Rd",
    "iso:country":"GB",
    "sg:address":"72 Norwich Rd",
    "sg:city":"Dereham",
    "sg:classifiers":[
        {
            "category":"Food & Beverages",
            "subcategory":"Fruits & Vegetables",
            "type":"Retail Goods"
        }
    ],
    "sg:phone":"+44 1362 697633",
    "sg:postcode":"NR20 3AR",
    "sg:province":"Norfolk",
    "sg:tags":[
        "greengrocer"
    ],
    "wof:name":"C C WELLS MARKETS",
    "wof:placetype":"venue"
},
  "geometry": {"coordinates":[0.952468,52.67934],"type":"Point"}
}