{
  "type": "Feature",
  "properties": {
    "iso:country":"GB",
    "sg:address":"Old Slaughterhouse",
    "sg:city":"Lockerbie",
    "sg:classifiers":[
        {
            "category":"Wholesale",
            "subcategory":"Meat",
            "type":"Manufacturing & Wholesale Goods"
        }
    ],
    "sg:phone":"+44 1576 202746",
    "sg:postcode":"DG11 2DE",
    "sg:province":"Dumfries and Galloway",
    "sg:tags":[
        "abattoir"
    ],
    "wof:name":"Lockerbie Abattoir",
    "wof:placetype":"venue"
},
  "geometry": {"coordinates":[-3.3545689583,55.1217765808],"type":"Point"}
}