{
  "type": "Feature",
  "properties": {
    "addr:full":"Unit 1, Estuary Business Park Barnstaple Devon EX31 3EZ",
    "addr:housenumber":"unit 1",
    "addr:postcode":"ex31 3ez",
    "addr:street":"Estuary Business Park",
    "iso:country":"GB",
    "sg:address":"Unit 1, Estuary Business Park",
    "sg:city":"Barnstaple",
    "sg:classifiers":[
        {
            "category":"Professional",
            "subcategory":"Computer Services",
            "type":"Services"
        }
    ],
    "sg:phone":"+44 1271 861414",
    "sg:postcode":"EX31 3EZ",
    "sg:province":"Devon",
    "sg:tags":[
        "system",
        "software"
    ],
    "wof:name":"Key Skills",
    "wof:placetype":"venue"
},
  "geometry": {"coordinates":[-4.164753,51.067776],"type":"Point"}
}