{
  "type": "Feature",
  "properties": {
    "addr:full":"Prospect Road Cleckheaton West Yorkshire BD19 3HD",
    "addr:postcode":"bd19 3hd",
    "addr:street":"Prospect Road",
    "iso:country":"GB",
    "sg:address":"Prospect Road",
    "sg:city":"Cleckheaton",
    "sg:classifiers":[
        {
            "category":"Travel",
            "subcategory":"Hotels & Motels",
            "type":"Entertainment"
        }
    ],
    "sg:phone":"+44 1274 873022",
    "sg:postcode":"BD19 3HD",
    "sg:province":"West Yorkshire",
    "wof:name":"P H Leisure Ltd.",
    "wof:placetype":"venue"
},
  "geometry": {"coordinates":[-1.7175290585,53.7260932922],"type":"Point"}
}