{
  "type": "Feature",
  "properties": {
    "addr:full":"34 Idris Villas Tywyn Gwynedd LL36 9AW",
    "addr:housenumber":"34",
    "addr:postcode":"ll36 9aw",
    "addr:street":"Idris Villas",
    "iso:country":"GB",
    "sg:address":"34 Idris Villas",
    "sg:city":"Tywyn",
    "sg:classifiers":[
        {
            "category":"Building & Trades",
            "subcategory":"Construction",
            "type":"Services"
        }
    ],
    "sg:phone":"+44 1654 711260",
    "sg:postcode":"LL36 9AW",
    "sg:province":"Gwynedd",
    "sg:tags":[
        "roofing",
        "contracting"
    ],
    "wof:name":"Robert Jones Roofing Specialist",
    "wof:placetype":"venue"
},
  "geometry": {"coordinates":[-4.09581,52.587025],"type":"Point"}
}