{
  "type": "Feature",
  "properties": {
    "iso:country":"GB",
    "sg:address":"Second Floor, 10 The Crescent",
    "sg:city":"Plymouth",
    "sg:classifiers":[
        {
            "category":"Professional",
            "subcategory":"Accounting & Tax Preparation",
            "type":"Services"
        }
    ],
    "sg:phone":"+44 1752 253545",
    "sg:postcode":"PL1 3AB",
    "sg:province":"Devon",
    "sg:tags":[
        "accountant",
        "activity"
    ],
    "wof:name":"Wills Accountants Ltd",
    "wof:placetype":"venue"
},
  "geometry": {"coordinates":[-4.147334,50.368267],"type":"Point"}
}