{
  "type": "Feature",
  "properties": {
    "addr:full":"226 Seymour Gro Manchester Cheshire M16 0DU",
    "addr:housenumber":"226",
    "addr:postcode":"m16 0du",
    "addr:street":"Seymour Gro",
    "iso:country":"GB",
    "sg:address":"226 Seymour Gro",
    "sg:city":"Manchester",
    "sg:classifiers":[
        {
            "category":"Professional",
            "subcategory":"Lawyer & Legal Services",
            "type":"Services"
        }
    ],
    "sg:phone":"+44 161 861 0101",
    "sg:postcode":"M16 0DU",
    "sg:province":"Cheshire",
    "sg:tags":[
        "advice",
        "counselling"
    ],
    "wof:name":"Trafford Carers Centre",
    "wof:placetype":"venue"
},
  "geometry": {"coordinates":[-2.273219,53.45192],"type":"Point"}
}