{
  "type": "Feature",
  "properties": {
    "addr:full":"14 Th Floor, Capital Tower Cardiff Cardiff CF10 3AG",
    "addr:housenumber":"14;floor",
    "addr:postcode":"cf10 3ag",
    "addr:street":"Th",
    "iso:country":"GB",
    "sg:address":"14 Th Floor, Capital Tower",
    "sg:city":"Cardiff",
    "sg:classifiers":[
        {
            "category":"Professional",
            "subcategory":"Employment Agencies",
            "type":"Services"
        }
    ],
    "sg:phone":"+44 29 2038 8752",
    "sg:postcode":"CF10 3AG",
    "sg:province":"Cardiff",
    "sg:tags":[
        "consultant"
    ],
    "wof:name":"Anders Glaser Wills",
    "wof:placetype":"venue"
},
  "geometry": {"coordinates":[-3.1806690693,51.4812583923],"type":"Point"}
}