{
  "type": "Feature",
  "properties": {
    "iso:country":"GB",
    "sg:address":"1st Floor, 104 London Rd",
    "sg:city":"Tunbridge Wells",
    "sg:classifiers":[
        {
            "category":"Autos & Motor Vehicles",
            "subcategory":"Fuel & Gas Station",
            "type":"Retail Goods"
        }
    ],
    "sg:phone":"+44 1892 546132",
    "sg:postcode":"TN4 0PW",
    "sg:province":"Kent",
    "sg:tags":[
        "aga",
        "cooker"
    ],
    "wof:name":"Cooker Man The",
    "wof:placetype":"venue"
},
  "geometry": {"coordinates":[0.25289,51.164719],"type":"Point"}
}