{
  "type": "Feature",
  "properties": {
    "addr:full":"Unit 7 Collingwood Ct, Riverside Park Middlesbrough Durham TS2 1RP",
    "addr:housenumber":"unit 7",
    "addr:postcode":"ts2 1rp",
    "addr:street":"Collingwood Ct",
    "iso:country":"GB",
    "sg:address":"Unit 7 Collingwood Ct, Riverside Park",
    "sg:city":"Middlesbrough",
    "sg:classifiers":[
        {
            "category":"Shopping",
            "subcategory":"Baby Store",
            "type":"Retail Goods"
        }
    ],
    "sg:phone":"+44 1642 253400",
    "sg:postcode":"TS2 1RP",
    "sg:province":"Durham",
    "sg:tags":[
        "nursery",
        "accessory"
    ],
    "wof:name":"Reason Front Ltd",
    "wof:placetype":"venue"
},
  "geometry": {"coordinates":[-1.2373789549,54.5848884583],"type":"Point"}
}