{
  "type": "Feature",
  "properties": {
    "addr:full":"9 Streatham Road Mitcham Greater London CR4 2AD",
    "addr:housenumber":"9",
    "addr:postcode":"cr4 2ad",
    "addr:street":"Streatham Road",
    "iso:country":"GB",
    "sg:address":"9 Streatham Road",
    "sg:city":"Mitcham",
    "sg:classifiers":[
        {
            "category":"Health Services",
            "subcategory":"Dentist",
            "type":"Services"
        }
    ],
    "sg:phone":"+44 20 8648 3294",
    "sg:postcode":"CR4 2AD",
    "sg:province":"Greater London",
    "wof:name":"HARRIS E YEE'CHONG",
    "wof:placetype":"venue"
},
  "geometry": {"coordinates":[-0.160168,51.411469],"type":"Point"}
}