{
  "type": "Feature",
  "properties": {
    "addr:full":"109 Poplar Gro Oxford Oxfordshire OX1 5QR",
    "addr:housenumber":"109",
    "addr:postcode":"ox1 5qr",
    "addr:street":"Poplar Gro",
    "iso:country":"GB",
    "sg:address":"109 Poplar Gro",
    "sg:city":"Oxford",
    "sg:classifiers":[
        {
            "category":"Building & Trades",
            "subcategory":"Construction",
            "type":"Services"
        }
    ],
    "sg:phone":"+44 1865 327733",
    "sg:postcode":"OX1 5QR",
    "sg:province":"Oxfordshire",
    "sg:tags":[
        "decorator",
        "painter"
    ],
    "wof:name":"Donoghue Decorating",
    "wof:placetype":"venue"
},
  "geometry": {"coordinates":[-1.2749990225,51.7196998596],"type":"Point"}
}