{
  "type": "Feature",
  "properties": {
    "addr:full":"P O Box 134 Borehamwood Hertfordshire WD6 5BF",
    "addr:housenumber":"134",
    "addr:postcode":"wd6 5bf",
    "addr:street":"P O Box",
    "iso:country":"GB",
    "sg:address":"P O Box 134",
    "sg:city":"Borehamwood",
    "sg:classifiers":[
        {
            "category":"Real Estate",
            "subcategory":"Real Estate Operator",
            "type":"Services"
        }
    ],
    "sg:phone":"+44 20 8207 1010",
    "sg:postcode":"WD6 5BF",
    "sg:province":"Hertfordshire",
    "sg:tags":[
        "letting",
        "agent"
    ],
    "wof:name":"Heartswood Estate Agents",
    "wof:placetype":"venue"
},
  "geometry": {"coordinates":[-0.2626389861,51.6666412354],"type":"Point"}
}