{
  "type": "Feature",
  "properties": {
    "addr:full":"9 Old Sq Holborn Greater London WC2A 3SR",
    "addr:housenumber":"9",
    "addr:postcode":"wc2a 3sr",
    "addr:street":"Old Sq",
    "iso:country":"GB",
    "sg:address":"9 Old Sq",
    "sg:city":"Holborn",
    "sg:classifiers":[
        {
            "category":"Professional",
            "subcategory":"Lawyer & Legal Services",
            "type":"Services"
        }
    ],
    "sg:phone":"+44 20 7405 4682",
    "sg:postcode":"WC2A 3SR",
    "sg:province":"Greater London",
    "wof:name":"Old Square",
    "wof:placetype":"venue"
},
  "geometry": {"coordinates":[-0.113108,51.516499],"type":"Point"}
}