{
  "type": "Feature",
  "properties": {
    "iso:country":"GB",
    "sg:address":"Toot Hill Rd",
    "sg:city":"Ongar",
    "sg:classifiers":[
        {
            "category":"Bars & Pubs",
            "type":"Food & Drink"
        }
    ],
    "sg:postcode":"CM5 9QR",
    "sg:province":"Essex",
    "sg:tags":[
        "pubs",
        "inn"
    ],
    "wof:name":"Carey,Maureen,",
    "wof:placetype":"venue"
},
  "geometry": {"coordinates":[0.210228,51.698761],"type":"Point"}
}