{
  "type": "Feature",
  "properties": {
    "addr:full":"Unit 7 Station Buildings Saltburn-by-the-sea North Yorkshire TS12 1AQ",
    "addr:housenumber":"unit 7 station",
    "addr:postcode":"ts12 1aq",
    "addr:street":"Saltburn-By-The-Sea",
    "iso:country":"GB",
    "sg:address":"Unit 7 Station Buildings",
    "sg:city":"Saltburn-by-the-sea",
    "sg:classifiers":[
        {
            "category":"Shopping",
            "subcategory":"Florist",
            "type":"Retail Goods"
        }
    ],
    "sg:phone":"+44 1287 625562",
    "sg:postcode":"TS12 1AQ",
    "sg:province":"North Yorkshire",
    "wof:name":"Station Florists",
    "wof:placetype":"venue"
},
  "geometry": {"coordinates":[-0.973924,54.583382],"type":"Point"}
}