{
  "type": "Feature",
  "properties": {
    "iso:country":"GB",
    "sg:address":"Unit 11 Maythorne Industrial Units, Maythorne",
    "sg:city":"Southwell",
    "sg:classifiers":[
        {
            "category":"Utilities",
            "subcategory":"Natural Gas",
            "type":"Services"
        }
    ],
    "sg:phone":"+44 1636 812722",
    "sg:postcode":"NG25 0RS",
    "sg:province":"Nottinghamshire",
    "sg:tags":[
        "supplier"
    ],
    "wof:name":"A P S Cellargas",
    "wof:placetype":"venue"
},
  "geometry": {"coordinates":[-0.9644190073,53.0906600952],"type":"Point"}
}