{
  "type": "Feature",
  "properties": {
    "addr:full":"46/48 Grosvenor Gardens, 29 Warwick Street London Greater London SW1W 0EB",
    "addr:housenumber":"46 / 48;29",
    "addr:postcode":"sw1w 0eb",
    "addr:street":"Grosvenor Gardens;Warwick Street",
    "iso:country":"GB",
    "sg:address":"46/48 Grosvenor Gardens, 29 Warwick Street",
    "sg:city":"London",
    "sg:classifiers":[
        {
            "category":"Organizations",
            "subcategory":"Non-profit Organization",
            "type":"Services"
        }
    ],
    "sg:phone":"+44 20 7881 9000",
    "sg:postcode":"SW1W 0EB",
    "sg:province":"Greater London",
    "sg:tags":[
        "organisation",
        "voluntary",
        "charity"
    ],
    "wof:name":"The Sir Robert Monde Trust",
    "wof:placetype":"venue"
},
  "geometry": {"coordinates":[-0.1460099965,51.4965400696],"type":"Point"}
}