{
  "type": "Feature",
  "properties": {
    "addr:full":"Unit 5 Venture House, Melcombe Road Bath Somerset BA2 3LR",
    "addr:housenumber":"unit 5",
    "addr:postcode":"ba2 3lr",
    "addr:street":"Melcombe Road",
    "iso:country":"GB",
    "sg:address":"Unit 5 Venture House, Melcombe Road",
    "sg:city":"Bath",
    "sg:classifiers":[
        {
            "category":"Home & Garden",
            "subcategory":"Building Materials",
            "type":"Retail Goods"
        },
        {
            "category":"Professional",
            "subcategory":"Art Services",
            "type":"Services"
        }
    ],
    "sg:postcode":"BA2 3LR",
    "sg:province":"Somerset",
    "sg:tags":[
        "roofing",
        "rafter",
        "framing",
        "beams"
    ],
    "wof:name":"Dermont McArdle",
    "wof:placetype":"venue"
},
  "geometry": {"coordinates":[-2.378608942,51.3743286133],"type":"Point"}
}