{
  "type": "Feature",
  "properties": {
    "iso:country":"GB",
    "sg:address":"Unit 3, Colebrook Industrial Estate, Longfield Road",
    "sg:city":"Tunbridge Wells",
    "sg:classifiers":[
        {
            "category":"Retail",
            "subcategory":"Auto Repair",
            "type":"Services"
        }
    ],
    "sg:postcode":"TN2 3EY",
    "sg:province":"East Sussex",
    "sg:tags":[
        "car",
        "servicing",
        "radiator"
    ],
    "wof:name":"Kent Radiator Service",
    "wof:placetype":"venue"
},
  "geometry": {"coordinates":[0.291687,51.155922],"type":"Point"}
}