{
  "type": "Feature",
  "properties": {
    "addr:full":"17 Langland Gardens London Greater London NW3 6QE",
    "addr:housenumber":"17",
    "addr:postcode":"nw3 6qe",
    "addr:street":"Langland Gardens",
    "iso:country":"GB",
    "sg:address":"17 Langland Gardens",
    "sg:city":"London",
    "sg:classifiers":[
        {
            "category":"Education",
            "subcategory":"Special Training",
            "type":"Public Place"
        }
    ],
    "sg:postcode":"NW3 6QE",
    "sg:province":"Greater London",
    "sg:tags":[
        "martial art",
        "instruction"
    ],
    "wof:name":"British Ki Aikido Association",
    "wof:placetype":"venue"
},
  "geometry": {"coordinates":[-0.184944,51.552979],"type":"Point"}
}