{
  "type": "Feature",
  "properties": {
    "iso:country":"GB",
    "sg:address":"Wallhouse Farm, Wallhouse Lane, Elcocks Brook",
    "sg:city":"Redditch",
    "sg:classifiers":[
        {
            "category":"Farming",
            "subcategory":"Dairy Farm",
            "type":"Manufacturing & Wholesale Goods"
        },
        {
            "category":"Farming",
            "subcategory":"Livestock Farm",
            "type":"Manufacturing & Wholesale Goods"
        }
    ],
    "sg:phone":"+44 1527 821212",
    "sg:postcode":"B97 5TJ",
    "sg:province":"Warwickshire",
    "sg:tags":[
        "others",
        "farmer"
    ],
    "wof:name":"A & D Badger",
    "wof:placetype":"venue"
},
  "geometry": {"coordinates":[-1.9866440296,52.2791633606],"type":"Point"}
}