{
  "type": "Feature",
  "properties": {
    "addr:full":"Brickfield Lane, Denbigh Road Ruthin Denbighshire LL15 2TN",
    "addr:postcode":"ll15 2tn",
    "addr:street":"Brickfield Lane Denbigh Road",
    "iso:country":"GB",
    "sg:address":"Brickfield Lane, Denbigh Road",
    "sg:city":"Ruthin",
    "sg:classifiers":[
        {
            "category":"Manufacturing",
            "subcategory":"Metals",
            "type":"Manufacturing & Wholesale Goods"
        }
    ],
    "sg:phone":"+44 1824 704991",
    "sg:postcode":"LL15 2TN",
    "sg:province":"Denbighshire",
    "sg:tags":[
        "anodisers",
        "mnfrs"
    ],
    "wof:name":"Optical Tools for Industry",
    "wof:placetype":"venue"
},
  "geometry": {"coordinates":[-3.304522,53.114017],"type":"Point"}
}