{
  "type": "Feature",
  "properties": {
    "addr:full":"1-3 The Cent Crescent, Hest Bank Lancaster Lancashire LA2 6DP",
    "addr:housenumber":"1-3",
    "addr:postcode":"la2 6dp",
    "addr:street":"The Cent Crescent",
    "iso:country":"GB",
    "sg:address":"1-3 The Cent Crescent, Hest Bank",
    "sg:city":"Lancaster",
    "sg:classifiers":[
        {
            "category":"Building & Trades",
            "subcategory":"Construction",
            "type":"Services"
        }
    ],
    "sg:postcode":"LA2 6DP",
    "sg:province":"Lancashire",
    "sg:tags":[
        "decorator",
        "painter"
    ],
    "wof:name":"Norman Gee",
    "wof:placetype":"venue"
},
  "geometry": {"coordinates":[-2.814938,54.090603],"type":"Point"}
}