{
  "type": "Feature",
  "properties": {
    "addr:full":"Information & Complaints, 15 Spa Rd Sth Bermondsey Greater London SE16 3QW",
    "addr:housenumber":"15",
    "addr:postcode":"se16 3qw",
    "addr:street":"Spa Rd",
    "iso:country":"GB",
    "sg:address":"Information & Complaints, 15 Spa Rd",
    "sg:city":"Sth Bermondsey",
    "sg:classifiers":[
        {
            "category":"Education",
            "subcategory":"Library",
            "type":"Public Place"
        }
    ],
    "sg:phone":"+44 20 7525 3716",
    "sg:postcode":"SE16 3QW",
    "sg:province":"Greater London",
    "sg:tags":[
        "book"
    ],
    "wof:name":"Southwark Library & Information Services",
    "wof:placetype":"venue"
},
  "geometry": {"coordinates":[-0.0757659972,51.4953269958],"type":"Point"}
}