{
  "type": "Feature",
  "properties": {
    "addr:full":"18 Templecombe, Templecombe Road, Bishopstoke Eastleigh Hampshire SO50 8QL",
    "addr:housenumber":"18",
    "addr:postcode":"so50 8ql",
    "addr:street":"Templecombe Templecombe Road",
    "iso:country":"GB",
    "sg:address":"18 Templecombe, Templecombe Road, Bishopstoke",
    "sg:city":"Eastleigh",
    "sg:classifiers":[
        {
            "category":"Building & Trades",
            "subcategory":"Landscaping Services",
            "type":"Services"
        }
    ],
    "sg:phone":"+44 23 8060 2071",
    "sg:postcode":"SO50 8QL",
    "sg:province":"Hampshire",
    "sg:tags":[
        "gardening"
    ],
    "wof:name":"Yew Tree Garden Care",
    "wof:placetype":"venue"
},
  "geometry": {"coordinates":[-1.316133,50.967113],"type":"Point"}
}