{
  "type": "Feature",
  "properties": {
    "iso:country":"GB",
    "sg:address":"Maelor Ho, High St",
    "sg:city":"Wrexham",
    "sg:classifiers":[
        {
            "category":"Health Services",
            "subcategory":"Doctor",
            "type":"Services"
        }
    ],
    "sg:phone":"+44 1978 752552",
    "sg:postcode":"LL11 6AW",
    "sg:province":"Wrexham",
    "sg:tags":[
        "practitioners"
    ],
    "wof:name":"Bates, G J",
    "wof:placetype":"venue"
},
  "geometry": {"coordinates":[-3.0379669666,53.070602417],"type":"Point"}
}