{
  "type": "Feature",
  "properties": {
    "addr:full":"Bond Street West Bromwich West Midlands B70 7DQ",
    "addr:postcode":"b70 7dq",
    "addr:street":"Bond Street",
    "iso:country":"GB",
    "sg:address":"Bond Street",
    "sg:city":"West Bromwich",
    "sg:classifiers":[
        {
            "category":"Building & Trades",
            "subcategory":"Electrical",
            "type":"Services"
        }
    ],
    "sg:phone":"+44 121 525 0750",
    "sg:postcode":"B70 7DQ",
    "sg:province":"West Midlands",
    "sg:tags":[
        "consultant",
        "lighting"
    ],
    "wof:name":"Woodhouse U K Plc",
    "wof:placetype":"venue"
},
  "geometry": {"coordinates":[-1.995206,52.514336],"type":"Point"}
}