{
  "type": "Feature",
  "properties": {
    "addr:full":"Unit 23 West Cannock Way, Cannock Chase Enterprise Centre, Hednesford Cannock Staffordshire WS12 5QU",
    "addr:housenumber":"unit 23",
    "addr:postcode":"ws12 5qu",
    "addr:street":"West Cannock Way;Hednesford",
    "iso:country":"GB",
    "sg:address":"Unit 23 West Cannock Way, Cannock Chase Enterprise Centre, Hednesford",
    "sg:city":"Cannock",
    "sg:classifiers":[
        {
            "category":"Home & Garden",
            "subcategory":"Hardware",
            "type":"Retail Goods"
        }
    ],
    "sg:phone":"+44 1543 451500",
    "sg:postcode":"WS12 5QU",
    "sg:province":"Staffordshire",
    "wof:name":"D  Newbould Ltd.",
    "wof:placetype":"venue"
},
  "geometry": {"coordinates":[-1.989769,52.724846],"type":"Point"}
}