{
  "type": "Feature",
  "properties": {
    "iso:country":"GB",
    "sg:address":"10 Main Road, Hoo",
    "sg:city":"Rochester",
    "sg:classifiers":[
        {
            "category":"Fast Food",
            "type":"Food & Drink"
        }
    ],
    "sg:phone":"+44 1634 253044",
    "sg:postcode":"ME3 9AD",
    "sg:province":"Kent",
    "sg:tags":[
        "away",
        "meal",
        "outlet",
        "take"
    ],
    "wof:name":"Surma Indian Take Away",
    "wof:placetype":"venue"
},
  "geometry": {"coordinates":[0.5625889897,51.4201583862],"type":"Point"}
}