{
  "type": "Feature",
  "properties": {
    "iso:country":"GB",
    "sg:address":"2 Littlefield Lane",
    "sg:city":"Grimsby",
    "sg:classifiers":[
        {
            "category":"Health Services",
            "subcategory":"Doctor",
            "type":"Services"
        },
        {
            "category":"Health Services",
            "subcategory":"Clinic",
            "type":"Services"
        }
    ],
    "sg:phone":"+44 1472 342250",
    "sg:postcode":"DN31 2LG",
    "sg:province":"Lincolnshire",
    "sg:tags":[
        "nh",
        "practitioners"
    ],
    "wof:name":"The Surgery",
    "wof:placetype":"venue"
},
  "geometry": {"coordinates":[-0.093092,53.564934],"type":"Point"}
}