{
  "type": "Feature",
  "properties": {
    "iso:country":"GB",
    "sg:address":"The Health Centre, Mudge Way",
    "sg:city":"Plymouth",
    "sg:classifiers":[
        {
            "category":"Health Services",
            "subcategory":"Doctor",
            "type":"Services"
        }
    ],
    "sg:phone":"+44 1752 346634",
    "sg:postcode":"PL7 1AD",
    "sg:province":"Devon",
    "sg:tags":[
        "practitioners"
    ],
    "wof:name":"Westwood, C N",
    "wof:placetype":"venue"
},
  "geometry": {"coordinates":[-4.0526900291,50.3861885071],"type":"Point"}
}