{
  "type": "Feature",
  "properties": {
    "addr:full":"Wilderness Farm, Wilderness Lane, Mark Beach Edenbridge East Sussex TN8 7LP",
    "addr:postcode":"tn8 7lp",
    "addr:street":"Wilderness Lane Mark",
    "iso:country":"GB",
    "sg:address":"Wilderness Farm, Wilderness Lane, Mark Beach",
    "sg:city":"Edenbridge",
    "sg:classifiers":[
        {
            "category":"Professional",
            "subcategory":"Engineering",
            "type":"Services"
        },
        {
            "category":"Banks & Credit Unions",
            "subcategory":"Investment Brokerage",
            "type":"Services"
        }
    ],
    "sg:phone":"+44 1342 850888",
    "sg:postcode":"TN8 7LP",
    "sg:province":"East Sussex",
    "sg:tags":[
        "contractor"
    ],
    "wof:name":"Leppard Engineering",
    "wof:placetype":"venue"
},
  "geometry": {"coordinates":[0.0647469983,51.1973876953],"type":"Point"}
}