{
  "type": "Feature",
  "properties": {
    "iso:country":"GB",
    "sg:address":"1c Sandys Road",
    "sg:city":"Basingstoke",
    "sg:classifiers":[
        {
            "category":"Building & Trades",
            "subcategory":"Construction",
            "type":"Services"
        }
    ],
    "sg:phone":"+44 1256 460806",
    "sg:postcode":"RG22 6AE",
    "sg:province":"Hampshire",
    "sg:tags":[
        "guttering"
    ],
    "wof:name":"R Hunt Guttering",
    "wof:placetype":"venue"
},
  "geometry": {"coordinates":[-1.110017,51.261955],"type":"Point"}
}