{
  "type": "Feature",
  "properties": {
    "iso:country":"GB",
    "sg:address":"189 Battersea Park Rd",
    "sg:city":"Battersea",
    "sg:classifiers":[
        {
            "category":"Professional",
            "subcategory":"Lawyer & Legal Services",
            "type":"Services"
        }
    ],
    "sg:phone":"+44 20 7627 3761",
    "sg:postcode":"SW11 4LB",
    "sg:province":"Greater London",
    "sg:tags":[
        "advice",
        "counselling"
    ],
    "wof:name":"Battersea Counselling Centre",
    "wof:placetype":"venue"
},
  "geometry": {"coordinates":[-0.149488,51.475849],"type":"Point"}
}