{
  "type": "Feature",
  "properties": {
    "addr:full":"110 Quarella Road Bridgend Bridgend CF31 1JT",
    "addr:housenumber":"110",
    "addr:postcode":"cf31 1jt",
    "addr:street":"Quarella Road",
    "iso:country":"GB",
    "sg:address":"110 Quarella Road",
    "sg:city":"Bridgend",
    "sg:classifiers":[
        {
            "category":"Building & Trades",
            "subcategory":"Construction",
            "type":"Services"
        }
    ],
    "sg:phone":"+44 1656 669329",
    "sg:postcode":"CF31 1JT",
    "sg:province":"Bridgend",
    "sg:tags":[
        "joiner",
        "carpenter"
    ],
    "wof:name":"Stuart Evans",
    "wof:placetype":"venue"
},
  "geometry": {"coordinates":[-3.580479,51.511009],"type":"Point"}
}