{
  "type": "Feature",
  "properties": {
    "iso:country":"GB",
    "sg:address":"Crawford Rd",
    "sg:city":"Wigan",
    "sg:classifiers":[
        {
            "category":"Place Of Worship",
            "type":"Public Place"
        }
    ],
    "sg:phone":"+44 1695 623334",
    "sg:postcode":"WN5 8TG",
    "sg:province":"Lancashire",
    "wof:name":"Crawford Methodist Church",
    "wof:placetype":"venue"
},
  "geometry": {"coordinates":[-2.627924,53.55431],"type":"Point"}
}