{
  "type": "Feature",
  "properties": {
    "iso:country":"GB",
    "sg:address":"Unit 1 Butterley St",
    "sg:city":"Leeds",
    "sg:classifiers":[
        {
            "category":"Home & Garden",
            "subcategory":"Home Furnishings",
            "type":"Retail Goods"
        }
    ],
    "sg:phone":"+44 113 246 1556",
    "sg:postcode":"LS10 1AU",
    "sg:province":"West Yorkshire",
    "sg:tags":[
        "decorative",
        "glass",
        "mirror"
    ],
    "wof:name":"A S Glass Decoration",
    "wof:placetype":"venue"
},
  "geometry": {"coordinates":[-1.538725,53.787205],"type":"Point"}
}