{
  "type": "Feature",
  "properties": {
    "iso:country":"GB",
    "sg:address":"Maen Valley, Goldenbank",
    "sg:city":"Falmouth",
    "sg:classifiers":[
        {
            "category":"Travel",
            "subcategory":"Hotels & Motels",
            "type":"Entertainment"
        }
    ],
    "sg:postcode":"TR11 5BL",
    "sg:province":"Cornwall",
    "wof:name":"Crill Manor Hotel",
    "wof:placetype":"venue"
},
  "geometry": {"coordinates":[-5.09646,50.139629],"type":"Point"}
}