{
  "type": "Feature",
  "properties": {
    "addr:full":"4 Holland Street London Greater London W8 4LT",
    "addr:housenumber":"4",
    "addr:postcode":"w8 4lt",
    "addr:street":"Holland Street",
    "iso:country":"GB",
    "sg:address":"4 Holland Street",
    "sg:city":"London",
    "sg:classifiers":[
        {
            "category":"Cafe",
            "type":"Food & Drink"
        }
    ],
    "sg:phone":"+44 20 7937 3001",
    "sg:postcode":"W8 4LT",
    "sg:province":"Greater London",
    "sg:tags":[
        "tea",
        "snack",
        "bar",
        "room"
    ],
    "wof:name":"Ananda Wijesiri",
    "wof:placetype":"venue"
},
  "geometry": {"coordinates":[-0.1923419982,51.5030288696],"type":"Point"}
}