{
  "type": "Feature",
  "properties": {
    "iso:country":"GB",
    "sg:address":"Kirkton Of Skene",
    "sg:city":"Westhill",
    "sg:classifiers":[
        {
            "category":"Health Services",
            "subcategory":"Nursing And Care Facility",
            "type":"Services"
        }
    ],
    "sg:phone":"+44 1224 742888",
    "sg:postcode":"AB32 6XD",
    "sg:province":"Aberdeen City",
    "sg:tags":[
        "home"
    ],
    "wof:name":"Pitcairn Lodge",
    "wof:placetype":"venue"
},
  "geometry": {"coordinates":[-2.2926840782,57.1494445801],"type":"Point"}
}