{
  "type": "Feature",
  "properties": {
    "iso:country":"GB",
    "sg:address":"9 East St",
    "sg:city":"Newton Abbot",
    "sg:classifiers":[
        {
            "category":"Home & Garden",
            "subcategory":"Garden Supply",
            "type":"Retail Goods"
        }
    ],
    "sg:phone":"+44 1803 812501",
    "sg:postcode":"TQ12 6DL",
    "sg:province":"Devon",
    "sg:tags":[
        "turfing"
    ],
    "wof:name":"Lawn Turf & Top Soil Torbay",
    "wof:placetype":"venue"
},
  "geometry": {"coordinates":[-3.660411,50.507973],"type":"Point"}
}