{
  "type": "Feature",
  "properties": {
    "addr:full":"88 Bingley Road, Salt Air, Shipley Bradford West Yorkshire BD18 4DJ",
    "addr:housenumber":"88;bradford",
    "addr:postcode":"bd18 4dj",
    "addr:street":"Bingley Road;Air Shipley",
    "iso:country":"GB",
    "sg:address":"88 Bingley Road, Salt Air, Shipley",
    "sg:city":"Bradford",
    "sg:classifiers":[
        {
            "category":"Freight",
            "type":"Transportation"
        }
    ],
    "sg:phone":"+44 1274 585208",
    "sg:postcode":"BD18 4DJ",
    "sg:province":"West Yorkshire",
    "sg:tags":[
        "haulage",
        "road"
    ],
    "wof:name":"Bell Freight (Uk) Ltd.",
    "wof:placetype":"venue"
},
  "geometry": {"coordinates":[-1.796664,53.835468],"type":"Point"}
}