{
  "type": "Feature",
  "properties": {
    "iso:country":"GB",
    "sg:address":"84 London Road",
    "sg:city":"Barking",
    "sg:classifiers":[
        {
            "category":"Professional",
            "type":"Services"
        }
    ],
    "sg:postcode":"IG11 8DD",
    "sg:province":"Essex",
    "sg:tags":[
        "caterer"
    ],
    "wof:name":"FATIMA SHEIKH",
    "wof:placetype":"venue"
},
  "geometry": {"coordinates":[0.075131,51.537945],"type":"Point"}
}