{
  "type": "Feature",
  "properties": {
    "addr:full":"Odd Down Post Office, 59 Frome Road Bath Somerset BA2 2PW",
    "addr:housenumber":"59",
    "addr:postcode":"ba2 2pw",
    "addr:street":"Frome Road",
    "iso:country":"GB",
    "sg:address":"Odd Down Post Office, 59 Frome Road",
    "sg:city":"Bath",
    "sg:classifiers":[
        {
            "category":"Government",
            "subcategory":"Post Office",
            "type":"Public Place"
        }
    ],
    "sg:phone":"+44 1225 832021",
    "sg:postcode":"BA2 2PW",
    "sg:province":"Somerset",
    "wof:name":"Odd Down Post Office",
    "wof:placetype":"venue"
},
  "geometry": {"coordinates":[-2.3781409264,51.3598022461],"type":"Point"}
}