{
  "type": "Feature",
  "properties": {
    "addr:full":"Unit M, Lambs Business Park, Tilburstow Hill Road Godstone Surrey RH9 8LJ",
    "addr:postcode":"rh9 8lj",
    "addr:street":"Business Park Tilburstow Hill Road",
    "iso:country":"GB",
    "sg:address":"Unit M, Lambs Business Park, Tilburstow Hill Road",
    "sg:city":"Godstone",
    "sg:classifiers":[
        {
            "category":"Autos & Motor Vehicles",
            "subcategory":"Motorcycle Sales",
            "type":"Retail Goods"
        }
    ],
    "sg:phone":"+44 1342 892888",
    "sg:postcode":"RH9 8LJ",
    "sg:province":"Surrey",
    "sg:tags":[
        "component"
    ],
    "wof:name":"Pro Twins Ltd.",
    "wof:placetype":"venue"
},
  "geometry": {"coordinates":[-0.066988,51.25008],"type":"Point"}
}