{
  "type": "Feature",
  "properties": {
    "addr:full":"210 Forest Road Loughborough Leicestershire LE11 3HU",
    "addr:housenumber":"210",
    "addr:postcode":"le11 3hu",
    "addr:street":"Forest Road",
    "iso:country":"GB",
    "sg:address":"210 Forest Road",
    "sg:city":"Loughborough",
    "sg:classifiers":[
        {
            "category":"Professional",
            "type":"Services"
        },
        {
            "category":"Fast Food",
            "type":"Food & Drink"
        }
    ],
    "sg:phone":"+44 1509 214730",
    "sg:postcode":"LE11 3HU",
    "sg:province":"Leicestershire",
    "sg:tags":[
        "away",
        "take",
        "caterer"
    ],
    "wof:name":"MILLER CATERING",
    "wof:placetype":"venue"
},
  "geometry": {"coordinates":[-1.2251529694,52.7617874146],"type":"Point"}
}