{
  "type": "Feature",
  "properties": {
    "addr:full":"Closworth Road, Halstock Yeovil Dorset BA22 9SZ",
    "addr:postcode":"ba22 9sz",
    "addr:street":"Closworth Road",
    "iso:country":"GB",
    "sg:address":"Closworth Road, Halstock",
    "sg:city":"Yeovil",
    "sg:classifiers":[
        {
            "category":"Farming",
            "subcategory":"Livestock Farm",
            "type":"Manufacturing & Wholesale Goods"
        }
    ],
    "sg:phone":"+44 1935 891581",
    "sg:postcode":"BA22 9SZ",
    "sg:province":"Dorset",
    "sg:tags":[
        "others"
    ],
    "wof:name":"R J & C A Buckland",
    "wof:placetype":"venue"
},
  "geometry": {"coordinates":[-2.613709,50.891472],"type":"Point"}
}