{
  "type": "Feature",
  "properties": {
    "addr:full":"Warland Garage Totnes Devon TQ9 5EL",
    "addr:postcode":"tq9 5el",
    "iso:country":"GB",
    "sg:address":"Warland Garage",
    "sg:city":"Totnes",
    "sg:classifiers":[
        {
            "category":"Professional",
            "subcategory":"Testing Lab",
            "type":"Services"
        },
        {
            "category":"Home & Garden",
            "subcategory":"Hardware",
            "type":"Retail Goods"
        }
    ],
    "sg:phone":"+44 1803 862493",
    "sg:postcode":"TQ9 5EL",
    "sg:province":"Devon",
    "sg:tags":[
        "part",
        "accessory",
        "mot"
    ],
    "wof:name":"B R Trott Motorcycles",
    "wof:placetype":"venue"
},
  "geometry": {"coordinates":[-3.688093,50.434147],"type":"Point"}
}