{
  "type": "Feature",
  "properties": {
    "iso:country":"GB",
    "sg:address":"14 Canterbury Road, Penn",
    "sg:city":"Wolverhampton",
    "sg:classifiers":[
        {
            "category":"Arts & Performance",
            "subcategory":"Music",
            "type":"Entertainment"
        }
    ],
    "sg:phone":"+44 1902 344148",
    "sg:postcode":"WV4 4EH",
    "sg:province":"Staffordshire",
    "sg:tags":[
        "mobile",
        "disco"
    ],
    "wof:name":"Multi-Media Entertainment Agency",
    "wof:placetype":"venue"
},
  "geometry": {"coordinates":[-2.162209,52.561813],"type":"Point"}
}