{
  "type": "Feature",
  "properties": {
    "iso:country":"GB",
    "sg:address":"Meurig Hall, Cilcennin",
    "sg:city":"Lampeter",
    "sg:classifiers":[
        {
            "category":"Recreation",
            "subcategory":"Dog Park",
            "type":"Entertainment"
        }
    ],
    "sg:phone":"+44 1570 470572",
    "sg:postcode":"SA48 8RS",
    "sg:province":"Carmarthenshire",
    "wof:name":"Meurig Kennels",
    "wof:placetype":"venue"
},
  "geometry": {"coordinates":[-4.16666,52.219395],"type":"Point"}
}