{
  "type": "Feature",
  "properties": {
    "addr:full":"4 Broadbent Close London Greater London N6 5JW",
    "addr:housenumber":"4",
    "addr:postcode":"n6 5jw",
    "addr:street":"Broadbent Close",
    "iso:country":"GB",
    "sg:address":"4 Broadbent Close",
    "sg:city":"London",
    "sg:classifiers":[
        {
            "category":"Manufacturing",
            "subcategory":"Apparel",
            "type":"Manufacturing & Wholesale Goods"
        }
    ],
    "sg:phone":"+44 20 8347 8181",
    "sg:postcode":"N6 5JW",
    "sg:province":"Greater London",
    "sg:tags":[
        "mnfr",
        "lingerie",
        "hosiery"
    ],
    "wof:name":"The First Department Ltd.",
    "wof:placetype":"venue"
},
  "geometry": {"coordinates":[-0.145218,51.571056],"type":"Point"}
}