{
  "type": "Feature",
  "properties": {
    "addr:full":"17-19 Mellor Road, Cheadle Hulme Cheadle Cheshire SK8 5AT",
    "addr:housenumber":"17-19",
    "addr:postcode":"sk8 5at",
    "addr:street":"Mellor Road",
    "iso:country":"GB",
    "sg:address":"17-19 Mellor Road, Cheadle Hulme",
    "sg:city":"Cheadle",
    "sg:classifiers":[
        {
            "category":"Farming",
            "subcategory":"Nursery",
            "type":"Manufacturing & Wholesale Goods"
        }
    ],
    "sg:phone":"+44 161 488 4242",
    "sg:postcode":"SK8 5AT",
    "sg:province":"Cheshire",
    "sg:tags":[
        "creche"
    ],
    "wof:name":"Tiny Toes Childrens Day Nursery",
    "wof:placetype":"venue"
},
  "geometry": {"coordinates":[-2.1884961128,53.3740615845],"type":"Point"}
}