{
  "type": "Feature",
  "properties": {
    "addr:full":"140 Sackville Road Hove East Sussex BN3 7AA",
    "addr:housenumber":"140",
    "addr:postcode":"bn3 7aa",
    "addr:street":"Sackville Road",
    "iso:country":"GB",
    "sg:address":"140 Sackville Road",
    "sg:city":"Hove",
    "sg:classifiers":[
        {
            "category":"Manufacturing",
            "subcategory":"Signs",
            "type":"Manufacturing & Wholesale Goods"
        }
    ],
    "sg:postcode":"BN3 7AA",
    "sg:province":"East Sussex",
    "sg:tags":[
        "nameplate"
    ],
    "wof:name":"Landmark Signs & Displays",
    "wof:placetype":"venue"
},
  "geometry": {"coordinates":[-0.1774449944,50.8369216919],"type":"Point"}
}