{
  "type": "Feature",
  "properties": {
    "iso:country":"GB",
    "sg:address":"Little Stonestile Farm, Selling",
    "sg:city":"Faversham",
    "sg:classifiers":[
        {
            "category":"Farming",
            "subcategory":"Livestock Farm",
            "type":"Manufacturing & Wholesale Goods"
        }
    ],
    "sg:postcode":"ME13 9SB",
    "sg:province":"Kent",
    "sg:tags":[
        "others"
    ],
    "wof:name":"J Garner",
    "wof:placetype":"venue"
},
  "geometry": {"coordinates":[0.921147,51.273659],"type":"Point"}
}