{
  "type": "Feature",
  "properties": {
    "addr:full":"27 King St, Thorne Doncaster East Riding of Yorkshire DN8 5AU",
    "addr:housenumber":"27",
    "addr:postcode":"dn8 5au",
    "addr:street":"King St;Riding",
    "iso:country":"GB",
    "sg:address":"27 King St, Thorne",
    "sg:city":"Doncaster",
    "sg:classifiers":[
        {
            "category":"Recreation",
            "subcategory":"Fishing",
            "type":"Entertainment"
        }
    ],
    "sg:phone":"+44 1405 814417",
    "sg:postcode":"DN8 5AU",
    "sg:province":"East Riding of Yorkshire",
    "sg:tags":[
        "angling"
    ],
    "wof:name":"TONYS TACKLE",
    "wof:placetype":"venue"
},
  "geometry": {"coordinates":[-0.963024,53.611996],"type":"Point"}
}