{
  "type": "Feature",
  "properties": {
    "iso:country":"GB",
    "sg:address":"4 Newcourt Road, Silverton",
    "sg:city":"Exeter",
    "sg:classifiers":[
        {
            "category":"Shopping",
            "subcategory":"News",
            "type":"Retail Goods"
        }
    ],
    "sg:phone":"+44 1392 860238",
    "sg:postcode":"EX5 4HR",
    "sg:province":"Devon",
    "sg:tags":[
        "newsagent"
    ],
    "wof:name":"D Goodwins",
    "wof:placetype":"venue"
},
  "geometry": {"coordinates":[-3.484181,50.815582],"type":"Point"}
}