{
  "type": "Feature",
  "properties": {
    "iso:country":"GB",
    "sg:address":"30 Low Etherley",
    "sg:city":"Bishop Auckland",
    "sg:classifiers":[
        {
            "category":"Building & Trades",
            "subcategory":"Construction",
            "type":"Services"
        }
    ],
    "sg:phone":"+44 1388 834273",
    "sg:postcode":"DL14 0EX",
    "sg:province":"Durham",
    "sg:tags":[
        "builder"
    ],
    "wof:name":"Kenneth Bowen",
    "wof:placetype":"venue"
},
  "geometry": {"coordinates":[-1.703150034,54.6555480957],"type":"Point"}
}