{
  "type": "Feature",
  "properties": {
    "addr:full":"99 Nursteed Road Devizes Wiltshire SN10 3DU",
    "addr:housenumber":"99",
    "addr:postcode":"sn10 3du",
    "addr:street":"Nursteed Road",
    "iso:country":"GB",
    "sg:address":"99 Nursteed Road",
    "sg:city":"Devizes",
    "sg:classifiers":[
        {
            "category":"Health Services",
            "subcategory":"Nursing And Care Facility",
            "type":"Services"
        },
        {
            "category":"Social Services",
            "subcategory":"Retirement Home",
            "type":"Services"
        }
    ],
    "sg:phone":"+44 1380 723720",
    "sg:postcode":"SN10 3DU",
    "sg:province":"Wiltshire",
    "sg:tags":[
        "residential"
    ],
    "wof:name":"Mayfield Residential Home",
    "wof:placetype":"venue"
},
  "geometry": {"coordinates":[-1.979102,51.345192],"type":"Point"}
}