{
  "type": "Feature",
  "properties": {
    "iso:country":"GB",
    "sg:address":"164 Allerton Road, Mossley Hill",
    "sg:city":"Liverpool",
    "sg:classifiers":[
        {
            "category":"Shopping",
            "subcategory":"Discount & Variety Stores",
            "type":"Retail Goods"
        }
    ],
    "sg:postcode":"L18 2DH",
    "sg:province":"Merseyside",
    "sg:tags":[
        "centre"
    ],
    "wof:name":"T J Morris Ltd.",
    "wof:placetype":"venue"
},
  "geometry": {"coordinates":[-2.908303,53.385509],"type":"Point"}
}