{
  "type": "Feature",
  "properties": {
    "iso:country":"GB",
    "sg:address":"91 South Coast Rd",
    "sg:city":"Peacehaven",
    "sg:classifiers":[
        {
            "category":"Shopping",
            "subcategory":"Florist",
            "type":"Retail Goods"
        }
    ],
    "sg:phone":"+44 1273 581854",
    "sg:postcode":"BN10 8QT",
    "sg:province":"East Sussex",
    "wof:name":"Silk N Stems",
    "wof:placetype":"venue"
},
  "geometry": {"coordinates":[0.011968,50.788731],"type":"Point"}
}