{
  "type": "Feature",
  "properties": {
    "addr:full":"17a Worcester Street Kidderminster Staffordshire DY10 1ED",
    "addr:housenumber":"17a",
    "addr:postcode":"dy10 1ed",
    "addr:street":"Worcester Street",
    "iso:country":"GB",
    "sg:address":"17a Worcester Street",
    "sg:city":"Kidderminster",
    "sg:classifiers":[
        {
            "category":"Organizations",
            "subcategory":"Non-profit Organization",
            "type":"Services"
        }
    ],
    "sg:phone":"+44 1562 865286",
    "sg:postcode":"DY10 1ED",
    "sg:province":"Staffordshire",
    "sg:tags":[
        "organisation",
        "voluntary",
        "charity"
    ],
    "wof:name":"The Cancer Research Campaign",
    "wof:placetype":"venue"
},
  "geometry": {"coordinates":[-2.2474849224,52.3872451782],"type":"Point"}
}