{
  "type": "Feature",
  "properties": {
    "iso:country":"GB",
    "sg:address":"7 Manners Corner, Manners Way, Prittlewell",
    "sg:city":"Southend-on-sea",
    "sg:classifiers":[
        {
            "category":"Shopping",
            "subcategory":"News",
            "type":"Retail Goods"
        }
    ],
    "sg:phone":"+44 1702 345107",
    "sg:postcode":"SS2 6QR",
    "sg:province":"Essex",
    "sg:tags":[
        "newsagent"
    ],
    "wof:name":"G A Suckling & Son",
    "wof:placetype":"venue"
},
  "geometry": {"coordinates":[0.701315,51.557056],"type":"Point"}
}