{
  "type": "Feature",
  "properties": {
    "addr:full":"Shakespeare Business Centre, 245a Coldharbour Lane Brixton Greater London SW9 8RR",
    "addr:housenumber":"245a",
    "addr:postcode":"sw9 8rr",
    "addr:street":"Coldharbour Lane",
    "iso:country":"GB",
    "sg:address":"Shakespeare Business Centre, 245a Coldharbour Lane",
    "sg:city":"Brixton",
    "sg:classifiers":[
        {
            "category":"Professional",
            "subcategory":"Art Services",
            "type":"Services"
        }
    ],
    "sg:phone":"+44 20 7737 6680",
    "sg:postcode":"SW9 8RR",
    "sg:province":"Greater London",
    "sg:tags":[
        "consultant",
        "design"
    ],
    "wof:name":"David Eckold",
    "wof:placetype":"venue"
},
  "geometry": {"coordinates":[-0.11117,51.462181],"type":"Point"}
}