{
  "type": "Feature",
  "properties": {
    "addr:full":"Skills Development Centre, Wiltshire Lane Pinner Greater London HA5 2NB",
    "addr:postcode":"ha5 2nb",
    "addr:street":"Wiltshire Lane",
    "iso:country":"GB",
    "sg:address":"Skills Development Centre, Wiltshire Lane",
    "sg:city":"Pinner",
    "sg:classifiers":[
        {
            "category":"Organizations",
            "subcategory":"Non-profit Organization",
            "type":"Services"
        }
    ],
    "sg:phone":"+44 20 8866 3711",
    "sg:postcode":"HA5 2NB",
    "sg:province":"Greater London",
    "sg:tags":[
        "organisation",
        "voluntary",
        "charity"
    ],
    "wof:name":"C M S S",
    "wof:placetype":"venue"
},
  "geometry": {"coordinates":[-0.3804889917,51.5909385681],"type":"Point"}
}