{
  "type": "Feature",
  "properties": {
    "addr:full":"264 Merton Road London Greater London SW18 5JL",
    "addr:housenumber":"264",
    "addr:postcode":"sw18 5jl",
    "addr:street":"Merton Road",
    "iso:country":"GB",
    "sg:address":"264 Merton Road",
    "sg:city":"London",
    "sg:classifiers":[
        {
            "category":"Professional",
            "subcategory":"Business Services",
            "type":"Services"
        }
    ],
    "sg:phone":"+44 20 8877 3377",
    "sg:postcode":"SW18 5JL",
    "sg:province":"Greater London",
    "sg:tags":[
        "hospitality",
        "corporate"
    ],
    "wof:name":"Business Entertainment Consultants Ltd.",
    "wof:placetype":"venue"
},
  "geometry": {"coordinates":[-0.199211,51.44812],"type":"Point"}
}