{
  "type": "Feature",
  "properties": {
    "addr:full":"196 Tottenham Court Road West End Hampshire W1P 9LD",
    "addr:housenumber":"196",
    "addr:postcode":"w1p 9ld",
    "addr:street":"Tottenham Court Road",
    "iso:country":"GB",
    "sg:address":"196 Tottenham Court Road",
    "sg:city":"West End",
    "sg:classifiers":[
        {
            "category":"Shopping",
            "subcategory":"Department Store",
            "type":"Retail Goods"
        }
    ],
    "sg:phone":"+44 20 7636 1666",
    "sg:postcode":"W1P 9LD",
    "sg:province":"Hampshire",
    "wof:name":"Heal & Son Ltd",
    "wof:placetype":"venue"
},
  "geometry": {"coordinates":[-0.13435,51.520859],"type":"Point"}
}