{
  "type": "Feature",
  "properties": {
    "addr:full":"Bronwydd Avenue Porth Bridgend CF39 9AQ",
    "addr:postcode":"cf39 9aq",
    "addr:street":"Bronwydd Avenue Porth",
    "iso:country":"GB",
    "sg:address":"Bronwydd Avenue",
    "sg:city":"Porth",
    "sg:classifiers":[
        {
            "category":"Social Services",
            "subcategory":"Retirement Home",
            "type":"Services"
        },
        {
            "category":"Government",
            "subcategory":"Office",
            "type":"Public Place"
        }
    ],
    "sg:phone":"+44 1443 685944",
    "sg:postcode":"CF39 9AQ",
    "sg:province":"Bridgend",
    "sg:tags":[
        "local",
        "rest"
    ],
    "wof:name":"Y Dan Mynydd Residential Care",
    "wof:placetype":"venue"
},
  "geometry": {"coordinates":[-3.4109508991,51.614982605],"type":"Point"}
}