{
  "type": "Feature",
  "properties": {
    "addr:full":"68 Victoria Park Drive North Glasgow Glasgow City G14 9PJ",
    "addr:housenumber":"68",
    "addr:postcode":"g14 9pj",
    "addr:street":"Victoria Park Drive North",
    "iso:country":"GB",
    "sg:address":"68 Victoria Park Drive North",
    "sg:city":"Glasgow",
    "sg:classifiers":[
        {
            "category":"Organizations",
            "subcategory":"Non-profit Organization",
            "type":"Services"
        }
    ],
    "sg:phone":"+44 141 959 9612",
    "sg:postcode":"G14 9PJ",
    "sg:province":"Glasgow City",
    "sg:tags":[
        "organisation",
        "voluntary",
        "charity"
    ],
    "wof:name":"Barnardo's",
    "wof:placetype":"venue"
},
  "geometry": {"coordinates":[-4.3372631073,55.8786468506],"type":"Point"}
}