{
  "type": "Feature",
  "properties": {
    "addr:full":"Transfer Station Leek Staffordshire ST13 5RJ",
    "addr:postcode":"st13 5rj",
    "iso:country":"GB",
    "sg:address":"Transfer Station",
    "sg:city":"Leek",
    "sg:classifiers":[
        {
            "category":"Utilities",
            "subcategory":"Refuse",
            "type":"Services"
        }
    ],
    "sg:phone":"+44 1538 399042",
    "sg:postcode":"ST13 5RJ",
    "sg:province":"Staffordshire",
    "sg:tags":[
        "skip",
        "hire"
    ],
    "wof:name":"L W D Waste Services",
    "wof:placetype":"venue"
},
  "geometry": {"coordinates":[-2.020884037,53.1064758301],"type":"Point"}
}