{
  "type": "Feature",
  "properties": {
    "addr:full":"6 Croft Bank Road, Urmston Manchester Cheshire M41 0TS",
    "addr:housenumber":"6",
    "addr:postcode":"m41 0ts",
    "addr:street":"Croft Bank Road",
    "iso:country":"GB",
    "sg:address":"6 Croft Bank Road, Urmston",
    "sg:city":"Manchester",
    "sg:classifiers":[
        {
            "category":"Shopping",
            "subcategory":"News",
            "type":"Retail Goods"
        }
    ],
    "sg:postcode":"M41 0TS",
    "sg:province":"Cheshire",
    "sg:tags":[
        "newsagent"
    ],
    "wof:name":"Card World",
    "wof:placetype":"venue"
},
  "geometry": {"coordinates":[-2.352842,53.448822],"type":"Point"}
}