{
  "type": "Feature",
  "properties": {
    "addr:full":"128 Portland Road Hove East Sussex BN3 5QL",
    "addr:housenumber":"128",
    "addr:postcode":"bn3 5ql",
    "addr:street":"Portland Road",
    "iso:country":"GB",
    "sg:address":"128 Portland Road",
    "sg:city":"Hove",
    "sg:classifiers":[
        {
            "category":"Shopping",
            "subcategory":"Discount & Variety Stores",
            "type":"Retail Goods"
        }
    ],
    "sg:phone":"+44 1273 770600",
    "sg:postcode":"BN3 5QL",
    "sg:province":"East Sussex",
    "sg:tags":[
        "centre"
    ],
    "wof:name":"Snips",
    "wof:placetype":"venue"
},
  "geometry": {"coordinates":[-0.1840080023,50.8329963684],"type":"Point"}
}