{
  "type": "Feature",
  "properties": {
    "addr:full":"41 Brownlow St Weymouth Dorset DT4 7HW",
    "addr:housenumber":"41",
    "addr:postcode":"dt4 7hw",
    "addr:street":"Brownlow St",
    "iso:country":"GB",
    "sg:address":"41 Brownlow St",
    "sg:city":"Weymouth",
    "sg:classifiers":[
        {
            "category":"Health Services",
            "subcategory":"Hospice",
            "type":"Services"
        }
    ],
    "sg:phone":"+44 1305 766665",
    "sg:postcode":"DT4 7HW",
    "sg:province":"Dorset",
    "wof:name":"Trimar Hospice Appeal",
    "wof:placetype":"venue"
},
  "geometry": {"coordinates":[-2.454200983,50.6173553467],"type":"Point"}
}