{
  "type": "Feature",
  "properties": {
    "iso:country":"GB",
    "sg:address":"9 Gloucester Place",
    "sg:city":"Darlington",
    "sg:classifiers":[
        {
            "category":"Professional",
            "subcategory":"Engineering",
            "type":"Services"
        }
    ],
    "sg:phone":"+44 1325 358648",
    "sg:postcode":"DL1 2LG",
    "sg:province":"Durham",
    "sg:tags":[
        "contractor",
        "electrical",
        "engineer"
    ],
    "wof:name":"Peter Robinson",
    "wof:placetype":"venue"
},
  "geometry": {"coordinates":[-1.531522,54.535412],"type":"Point"}
}