{
  "type": "Feature",
  "properties": {
    "iso:country":"GB",
    "sg:address":"Hockley Mill Stables, Church Lane, Twyford",
    "sg:city":"Winchester",
    "sg:classifiers":[
        {
            "category":"Building & Trades",
            "subcategory":"Construction",
            "type":"Services"
        }
    ],
    "sg:phone":"+44 1962 777788",
    "sg:postcode":"SO21 1NT",
    "sg:province":"Hampshire",
    "sg:tags":[
        "builder"
    ],
    "wof:name":"Ashby Renovations Ltd.",
    "wof:placetype":"venue"
},
  "geometry": {"coordinates":[-1.312739,51.02359],"type":"Point"}
}