{
  "type": "Feature",
  "properties": {
    "addr:full":"95 Mostyn Street Llandudno Conwy LL30 2NY",
    "addr:housenumber":"95",
    "addr:postcode":"ll30 2ny",
    "addr:street":"Mostyn Street",
    "iso:country":"GB",
    "sg:address":"95 Mostyn Street",
    "sg:city":"Llandudno",
    "sg:classifiers":[
        {
            "category":"Shopping",
            "subcategory":"Gifts & Souvenirs",
            "type":"Retail Goods"
        }
    ],
    "sg:phone":"+44 1492 860010",
    "sg:postcode":"LL30 2NY",
    "sg:province":"Conwy",
    "sg:tags":[
        "poster",
        "card"
    ],
    "wof:name":"Birthdays",
    "wof:placetype":"venue"
},
  "geometry": {"coordinates":[-3.8306560516,53.3248596191],"type":"Point"}
}