{
  "type": "Feature",
  "properties": {
    "addr:full":"48 East Main Street Broxburn City of Edinburgh EH52 5AE",
    "addr:housenumber":"48",
    "addr:postcode":"eh52 5ae",
    "addr:street":"East Main Street",
    "iso:country":"GB",
    "sg:address":"48 East Main Street",
    "sg:city":"Broxburn",
    "sg:classifiers":[
        {
            "category":"Shopping",
            "subcategory":"Shoes",
            "type":"Retail Goods"
        }
    ],
    "sg:phone":"+44 1506 856245",
    "sg:postcode":"EH52 5AE",
    "sg:province":"City of Edinburgh",
    "sg:tags":[
        "shop"
    ],
    "wof:name":"Oliver Timpson",
    "wof:placetype":"venue"
},
  "geometry": {"coordinates":[-3.4698569775,55.9341583252],"type":"Point"}
}