{
  "type": "Feature",
  "properties": {
    "iso:country":"GB",
    "sg:address":"40 Cameron Road",
    "sg:city":"Cambridge",
    "sg:classifiers":[
        {
            "category":"Autos & Motor Vehicles",
            "subcategory":"Auto Supplies",
            "type":"Retail Goods"
        }
    ],
    "sg:phone":"+44 1223 359855",
    "sg:postcode":"CB4 2LY",
    "sg:province":"Cambridgeshire",
    "sg:tags":[
        "windscreen"
    ],
    "wof:name":"Cambridge Windscreens",
    "wof:placetype":"venue"
},
  "geometry": {"coordinates":[0.129997,52.231079],"type":"Point"}
}