{
  "type": "Feature",
  "properties": {
    "iso:country":"GB",
    "sg:address":"Bell Close, Plympton",
    "sg:city":"Plymouth",
    "sg:classifiers":[
        {
            "category":"Social Services",
            "subcategory":"Adult Care",
            "type":"Services"
        },
        {
            "category":"Government",
            "subcategory":"Office",
            "type":"Public Place"
        }
    ],
    "sg:phone":"+44 1752 343474",
    "sg:postcode":"PL7 4JH",
    "sg:province":"Devon",
    "sg:tags":[
        "local",
        "day",
        "centre"
    ],
    "wof:name":"Newnham Community Resource Centre",
    "wof:placetype":"venue"
},
  "geometry": {"coordinates":[-4.0436348915,50.3950538635],"type":"Point"}
}