{
  "type": "Feature",
  "properties": {
    "addr:full":"57 Tooting High Street London Greater London SW17 0SP",
    "addr:housenumber":"57",
    "addr:postcode":"sw17 0sp",
    "addr:street":"Tooting High Street",
    "iso:country":"GB",
    "sg:address":"57 Tooting High Street",
    "sg:city":"London",
    "sg:classifiers":[
        {
            "category":"Shopping",
            "subcategory":"News",
            "type":"Retail Goods"
        }
    ],
    "sg:postcode":"SW17 0SP",
    "sg:province":"Greater London",
    "sg:tags":[
        "newsagent"
    ],
    "wof:name":"Neroshi News",
    "wof:placetype":"venue"
},
  "geometry": {"coordinates":[-0.167388007,51.4283332825],"type":"Point"}
}