{
  "type": "Feature",
  "properties": {
    "iso:country":"GB",
    "sg:address":"35 Ethelbert Road",
    "sg:city":"Canterbury",
    "sg:classifiers":[
        {
            "category":"Health Services",
            "subcategory":"Nursing And Care Facility",
            "type":"Services"
        }
    ],
    "sg:phone":"+44 1227 769654",
    "sg:postcode":"CT1 3NF",
    "sg:province":"Kent",
    "sg:tags":[
        "home"
    ],
    "wof:name":"The Beeches",
    "wof:placetype":"venue"
},
  "geometry": {"coordinates":[1.08753,51.268749],"type":"Point"}
}