{
  "type": "Feature",
  "properties": {
    "addr:full":"11 Church Lane, Bishopston Swansea Swansea SA3 3JT",
    "addr:housenumber":"11",
    "addr:postcode":"sa3 3jt",
    "addr:street":"Church Lane",
    "iso:country":"GB",
    "sg:address":"11 Church Lane, Bishopston",
    "sg:city":"Swansea",
    "sg:classifiers":[
        {
            "category":"Travel",
            "subcategory":"Hotels & Motels",
            "type":"Entertainment"
        }
    ],
    "sg:phone":"+44 1792 232074",
    "sg:postcode":"SA3 3JT",
    "sg:province":"Swansea",
    "wof:name":"Winston Private Hotel",
    "wof:placetype":"venue"
},
  "geometry": {"coordinates":[-4.053962,51.586197],"type":"Point"}
}