{
  "type": "Feature",
  "properties": {
    "iso:country":"GB",
    "sg:address":"2 Regent Road",
    "sg:city":"Altrincham",
    "sg:classifiers":[
        {
            "category":"Organizations",
            "subcategory":"Non-profit Organization",
            "type":"Services"
        }
    ],
    "sg:phone":"+44 161 929 0918",
    "sg:postcode":"WA14 1RE",
    "sg:province":"Cheshire",
    "sg:tags":[
        "organisation",
        "voluntary",
        "charity"
    ],
    "wof:name":"British Red Cross Society",
    "wof:placetype":"venue"
},
  "geometry": {"coordinates":[-2.351374,53.385612],"type":"Point"}
}