{
  "type": "Feature",
  "properties": {
    "addr:full":"308 Inia Mill Centre, India Mill Darwen Lancashire BB3 1AE",
    "addr:housenumber":"308",
    "addr:postcode":"bb3 1ae",
    "addr:street":"Inia Mill;Darwen",
    "iso:country":"GB",
    "sg:address":"308 Inia Mill Centre, India Mill",
    "sg:city":"Darwen",
    "sg:classifiers":[
        {
            "category":"Professional",
            "type":"Services"
        }
    ],
    "sg:phone":"+44 1254 775983",
    "sg:postcode":"BB3 1AE",
    "sg:province":"Lancashire",
    "sg:tags":[
        "shopfitters"
    ],
    "wof:name":"Corporate Developments Ltd.",
    "wof:placetype":"venue"
},
  "geometry": {"coordinates":[-2.4671690464,53.6941986084],"type":"Point"}
}