{
  "type": "Feature",
  "properties": {
    "addr:full":"77 Bank Top Blackburn Lancashire BB2 1TN",
    "addr:housenumber":"77",
    "addr:postcode":"bb2 1tn",
    "addr:street":"Bank Top",
    "iso:country":"GB",
    "sg:address":"77 Bank Top",
    "sg:city":"Blackburn",
    "sg:classifiers":[
        {
            "category":"Communications",
            "type":"Services"
        }
    ],
    "sg:phone":"+44 1254 678919",
    "sg:postcode":"BB2 1TN",
    "sg:province":"Lancashire",
    "sg:tags":[
        "tv",
        "video",
        "radio"
    ],
    "wof:name":"Telesat North West",
    "wof:placetype":"venue"
},
  "geometry": {"coordinates":[-2.497773,53.74258],"type":"Point"}
}