{
  "type": "Feature",
  "properties": {
    "addr:full":"26 Hempsted Lane Gloucester Gloucestershire GL2 5JF",
    "addr:housenumber":"26",
    "addr:postcode":"gl2 5jf",
    "addr:street":"Hempsted Lane",
    "iso:country":"GB",
    "sg:address":"26 Hempsted Lane",
    "sg:city":"Gloucester",
    "sg:classifiers":[
        {
            "category":"Freight",
            "type":"Transportation"
        }
    ],
    "sg:postcode":"GL2 5JF",
    "sg:province":"Gloucestershire",
    "sg:tags":[
        "haulage",
        "road"
    ],
    "wof:name":"Joseph Rice & Son Ltd.",
    "wof:placetype":"venue"
},
  "geometry": {"coordinates":[-2.2593541145,51.8596954346],"type":"Point"}
}