{
  "type": "Feature",
  "properties": {
    "iso:country":"GB",
    "sg:address":"9 Abbotsbury Rd",
    "sg:city":"Broadstone",
    "sg:classifiers":[
        {
            "category":"Professional",
            "subcategory":"Detective & Security Services",
            "type":"Services"
        }
    ],
    "sg:phone":"+44 1202 697842",
    "sg:postcode":"BH18 9DA",
    "sg:province":"Dorset",
    "sg:tags":[
        "alarm",
        "burglar",
        "system"
    ],
    "wof:name":"Abbotsbury Alarms",
    "wof:placetype":"venue"
},
  "geometry": {"coordinates":[-2.00488,50.763805],"type":"Point"}
}