{
  "type": "Feature",
  "properties": {
    "iso:country":"GB",
    "sg:address":"Unit 54, Old Mill Ind Est, Stoke Canon",
    "sg:city":"Exeter",
    "sg:classifiers":[
        {
            "category":"Building & Trades",
            "subcategory":"Equipment Rental",
            "type":"Services"
        }
    ],
    "sg:phone":"+44 1392 841715",
    "sg:postcode":"EX5 4RJ",
    "sg:province":"Devon",
    "sg:tags":[
        "plant",
        "machinery"
    ],
    "wof:name":"Fairwest",
    "wof:placetype":"venue"
},
  "geometry": {"coordinates":[-3.51058,50.763378],"type":"Point"}
}