{
  "type": "Feature",
  "properties": {
    "addr:full":"549 Wandsworth Rd South Lambeth Greater London SW8 3JD",
    "addr:housenumber":"549",
    "addr:postcode":"sw8 3jd",
    "addr:street":"Wandsworth Rd",
    "iso:country":"GB",
    "sg:address":"549 Wandsworth Rd",
    "sg:city":"South Lambeth",
    "sg:phone":"+44 20 7498 2675",
    "sg:postcode":"SW8 3JD",
    "sg:province":"Greater London",
    "wof:name":"A Crosby",
    "wof:placetype":"venue"
},
  "geometry": {"coordinates":[-0.1397020072,51.4700050354],"type":"Point"}
}