{
  "type": "Feature",
  "properties": {
    "addr:full":"Studio 116 Tedco Business Works South Shields Tyne and Wear NE33 1RF",
    "addr:postcode":"ne33 1rf",
    "iso:country":"GB",
    "sg:address":"Studio 116 Tedco Business Works",
    "sg:city":"South Shields",
    "sg:classifiers":[
        {
            "category":"Professional",
            "subcategory":"Management & Consulting",
            "type":"Services"
        }
    ],
    "sg:postcode":"NE33 1RF",
    "sg:province":"Tyne and Wear",
    "sg:tags":[
        "marketing",
        "consultant"
    ],
    "wof:name":"Marketing Concepts",
    "wof:placetype":"venue"
},
  "geometry": {"coordinates":[-1.430519,54.996464],"type":"Point"}
}