{
  "type": "Feature",
  "properties": {
    "iso:country":"GB",
    "sg:address":"Unit 2 East Dorset Trade Park, Nimrod Way, Ferndown Industrial Estate",
    "sg:city":"Wimborne",
    "sg:classifiers":[
        {
            "category":"Shopping",
            "subcategory":"Stationery & Office Supplies",
            "type":"Retail Goods"
        }
    ],
    "sg:phone":"+44 1202 861200",
    "sg:postcode":"BH21 7SH",
    "sg:province":"Dorset",
    "sg:tags":[
        "packaging",
        "equipment",
        "material"
    ],
    "wof:name":"Marden Edwards Ltd",
    "wof:placetype":"venue"
},
  "geometry": {"coordinates":[-1.988709,50.802235],"type":"Point"}
}