{
  "type": "Feature",
  "properties": {
    "iso:country":"GB",
    "sg:address":"324 Seaside",
    "sg:city":"Eastbourne",
    "sg:classifiers":[
        {
            "category":"Shopping",
            "subcategory":"Bicycles & Sporting Goods",
            "type":"Retail Goods"
        }
    ],
    "sg:phone":"+44 1323 411549",
    "sg:postcode":"BN22 7RH",
    "sg:province":"East Sussex",
    "sg:tags":[
        "cycle",
        "accessory"
    ],
    "wof:name":"Nevada Bikes",
    "wof:placetype":"venue"
},
  "geometry": {"coordinates":[0.300415,50.780098],"type":"Point"}
}