{
  "type": "Feature",
  "properties": {
    "iso:country":"GB",
    "sg:address":"6 The Walk",
    "sg:city":"Ipswich",
    "sg:classifiers":[
        {
            "category":"Professional",
            "subcategory":"Art Services",
            "type":"Services"
        }
    ],
    "sg:postcode":"IP1 1EE",
    "sg:province":"Suffolk",
    "sg:tags":[
        "picture",
        "framing"
    ],
    "wof:name":"Sam Durrant",
    "wof:placetype":"venue"
},
  "geometry": {"coordinates":[1.2344620228,52.0649452209],"type":"Point"}
}