{
  "type": "Feature",
  "properties": {
    "iso:country":"GB",
    "sg:address":"Foel Rd, Dyserth",
    "sg:city":"Rhyl",
    "sg:classifiers":[
        {
            "category":"Retail",
            "subcategory":"Auto Repair",
            "type":"Services"
        }
    ],
    "sg:postcode":"LL18 6AS",
    "sg:province":"Conwy",
    "sg:tags":[
        "modification",
        "garage"
    ],
    "wof:name":"Fordsham,John,",
    "wof:placetype":"venue"
},
  "geometry": {"coordinates":[-3.410848,53.300461],"type":"Point"}
}