{
  "type": "Feature",
  "properties": {
    "addr:full":"2-3 Longlands Close, Cheshunt Waltham Cross Essex EN8 8LW",
    "addr:housenumber":"2-3",
    "addr:postcode":"en8 8lw",
    "addr:street":"Longlands Close",
    "iso:country":"GB",
    "sg:address":"2-3 Longlands Close, Cheshunt",
    "sg:city":"Waltham Cross",
    "sg:classifiers":[
        {
            "category":"Organizations",
            "subcategory":"Religious Organization",
            "type":"Services"
        }
    ],
    "sg:phone":"+44 1992 621168",
    "sg:postcode":"EN8 8LW",
    "sg:province":"Essex",
    "sg:tags":[
        "organisation"
    ],
    "wof:name":"Holy Cross Canossian Convent",
    "wof:placetype":"venue"
},
  "geometry": {"coordinates":[-0.035768,51.694454],"type":"Point"}
}