{
  "type": "Feature",
  "properties": {
    "addr:full":"263 Bretch Hill Banbury Oxfordshire OX16 0JY",
    "addr:housenumber":"263",
    "addr:postcode":"ox16 0jy",
    "addr:street":"Bretch Hill",
    "iso:country":"GB",
    "sg:address":"263 Bretch Hill",
    "sg:city":"Banbury",
    "sg:classifiers":[
        {
            "category":"Building & Trades",
            "subcategory":"Cleaning & Sanitation",
            "type":"Services"
        }
    ],
    "sg:phone":"+44 1295 268916",
    "sg:postcode":"OX16 0JY",
    "sg:province":"Oxfordshire",
    "sg:tags":[
        "commercial"
    ],
    "wof:name":"Orbit Cleaning Services",
    "wof:placetype":"venue"
},
  "geometry": {"coordinates":[-1.3626840115,52.0586662292],"type":"Point"}
}