{
  "type": "Feature",
  "properties": {
    "iso:country":"GB",
    "sg:address":"70/72 Market Street",
    "sg:city":"Dalton-in-furness",
    "sg:classifiers":[
        {
            "category":"Shopping",
            "subcategory":"Department Store",
            "type":"Retail Goods"
        }
    ],
    "sg:phone":"+44 1229 462501",
    "sg:postcode":"LA15 8AA",
    "sg:province":"Cumbria",
    "wof:name":"Family Choice",
    "wof:placetype":"venue"
},
  "geometry": {"coordinates":[-3.1819200516,54.1563491821],"type":"Point"}
}