{
  "type": "Feature",
  "properties": {
    "iso:country":"GB",
    "sg:address":"Unit 9 Newbury Commercial Centre, Fairoak Close, Exeter Airport Business Park",
    "sg:city":"Exeter",
    "sg:classifiers":[
        {
            "category":"Shopping",
            "subcategory":"Stationery & Office Supplies",
            "type":"Retail Goods"
        }
    ],
    "sg:phone":"+44 1392 666755",
    "sg:postcode":"EX5 2UL",
    "sg:province":"Devon",
    "sg:tags":[
        "equipment"
    ],
    "wof:name":"Focus Office Interiors Ltd.",
    "wof:placetype":"venue"
},
  "geometry": {"coordinates":[-3.40881,50.729599],"type":"Point"}
}