{
  "type": "Feature",
  "properties": {
    "addr:full":"131 Main Rd, Cleeve Bristol Somerset BS49 4PW",
    "addr:housenumber":"131",
    "addr:postcode":"bs49 4pw",
    "addr:street":"Main Rd",
    "iso:country":"GB",
    "sg:address":"131 Main Rd, Cleeve",
    "sg:city":"Bristol",
    "sg:classifiers":[
        {
            "category":"Freight",
            "type":"Transportation"
        }
    ],
    "sg:postcode":"BS49 4PW",
    "sg:province":"Somerset",
    "sg:tags":[
        "haulage",
        "road"
    ],
    "wof:name":"A C T",
    "wof:placetype":"venue"
},
  "geometry": {"coordinates":[-2.779042,51.389381],"type":"Point"}
}