{
  "type": "Feature",
  "properties": {
    "iso:country":"GB",
    "sg:address":"97 Victoria Road",
    "sg:city":"Cambridge",
    "sg:classifiers":[
        {
            "category":"Professional",
            "subcategory":"Business Services",
            "type":"Services"
        },
        {
            "category":"Casinos & Gambling",
            "type":"Entertainment"
        }
    ],
    "sg:postcode":"CB4 3BS",
    "sg:province":"Cambridgeshire",
    "sg:tags":[
        "turf",
        "accountant",
        "bookmaker"
    ],
    "wof:name":"Bob Dixon & Sons Ltd.",
    "wof:placetype":"venue"
},
  "geometry": {"coordinates":[0.117817,52.215267],"type":"Point"}
}