{
  "type": "Feature",
  "properties": {
    "iso:country":"GB",
    "sg:address":"16 Blackwater Lane, Pound Hill",
    "sg:city":"Crawley",
    "sg:classifiers":[
        {
            "category":"Professional",
            "type":"Services"
        }
    ],
    "sg:postcode":"RH10 7RL",
    "sg:province":"Surrey",
    "sg:tags":[
        "entertainer"
    ],
    "wof:name":"Alan the Childrens Entertainer",
    "wof:placetype":"venue"
},
  "geometry": {"coordinates":[-0.148278,51.113815],"type":"Point"}
}