{
  "type": "Feature",
  "properties": {
    "iso:country":"GB",
    "sg:address":"39 Cherry Orchard",
    "sg:city":"Kidderminster",
    "sg:classifiers":[
        {
            "category":"Wholesale",
            "subcategory":"Electrical",
            "type":"Manufacturing & Wholesale Goods"
        },
        {
            "category":"Building & Trades",
            "subcategory":"Construction",
            "type":"Services"
        }
    ],
    "sg:phone":"+44 1562 748270",
    "sg:postcode":"DY10 1SH",
    "sg:province":"Staffordshire",
    "sg:tags":[
        "equipment",
        "refrigeration",
        "roofing"
    ],
    "wof:name":"Kidderminster Roofing",
    "wof:placetype":"venue"
},
  "geometry": {"coordinates":[-2.238704,52.38763],"type":"Point"}
}