{
  "type": "Feature",
  "properties": {
    "iso:country":"GB",
    "sg:address":"76 Park Road",
    "sg:city":"Dartford",
    "sg:classifiers":[
        {
            "category":"Wholesale",
            "subcategory":"Electrical",
            "type":"Manufacturing & Wholesale Goods"
        },
        {
            "category":"Building & Trades",
            "subcategory":"Electrical",
            "type":"Services"
        }
    ],
    "sg:phone":"+44 1322 221467",
    "sg:postcode":"DA1 1SY",
    "sg:province":"Kent",
    "sg:tags":[
        "contractor",
        "equipment",
        "refrigeration",
        "air conditioning"
    ],
    "wof:name":"R & P Refrigeration Ltd.",
    "wof:placetype":"venue"
},
  "geometry": {"coordinates":[0.232638,51.440174],"type":"Point"}
}