{
  "type": "Feature",
  "properties": {
    "addr:full":"Western Road Lewes East Sussex BN7 1RR",
    "addr:postcode":"bn7 1rr",
    "addr:street":"Western Road",
    "iso:country":"GB",
    "sg:address":"Western Road",
    "sg:city":"Lewes",
    "sg:classifiers":[
        {
            "category":"Retail",
            "subcategory":"Auto Repair",
            "type":"Services"
        }
    ],
    "sg:phone":"+44 1273 472434",
    "sg:postcode":"BN7 1RR",
    "sg:province":"East Sussex",
    "sg:tags":[
        "modification",
        "garage"
    ],
    "wof:name":"Morris Road Garage",
    "wof:placetype":"venue"
},
  "geometry": {"coordinates":[-0.001804,50.8730316162],"type":"Point"}
}