{
  "type": "Feature",
  "properties": {
    "addr:full":"271 Lillie Road London Greater London SW6 7LL",
    "addr:housenumber":"271",
    "addr:postcode":"sw6 7ll",
    "addr:street":"Lillie Road",
    "iso:country":"GB",
    "sg:address":"271 Lillie Road",
    "sg:city":"London",
    "sg:classifiers":[
        {
            "category":"Retail",
            "subcategory":"Storage",
            "type":"Services"
        }
    ],
    "sg:phone":"+44 20 7381 2450",
    "sg:postcode":"SW6 7LL",
    "sg:province":"Greater London",
    "sg:tags":[
        "household",
        "removal"
    ],
    "wof:name":"Lens Removals",
    "wof:placetype":"venue"
},
  "geometry": {"coordinates":[-0.2110989988,51.4829483032],"type":"Point"}
}