{
  "type": "Feature",
  "properties": {
    "addr:full":"Whitestone Precincourt, Lutterworth Rd Nuneaton Leicestershire CV11 6PF",
    "addr:postcode":"cv11 6pf",
    "addr:street":"Lutterworth Rd",
    "iso:country":"GB",
    "sg:address":"Whitestone Precincourt, Lutterworth Rd",
    "sg:city":"Nuneaton",
    "sg:classifiers":[
        {
            "category":"Banks & Credit Unions",
            "subcategory":"Financial Services",
            "type":"Services"
        }
    ],
    "sg:phone":"+44 24 7637 5433",
    "sg:postcode":"CV11 6PF",
    "sg:province":"Leicestershire",
    "sg:tags":[
        "building",
        "society"
    ],
    "wof:name":"Whitestone Financial Services",
    "wof:placetype":"venue"
},
  "geometry": {"coordinates":[-1.46445,52.52137],"type":"Point"}
}