{
  "type": "Feature",
  "properties": {
    "iso:country":"GB",
    "sg:address":"5 Chapel Street",
    "sg:city":"Billericay",
    "sg:classifiers":[
        {
            "category":"Insurance",
            "subcategory":"Insurance Agent",
            "type":"Services"
        }
    ],
    "sg:phone":"+44 1277 624864",
    "sg:postcode":"CM12 9LT",
    "sg:province":"Essex",
    "wof:name":"L C Strong Ltd",
    "wof:placetype":"venue"
},
  "geometry": {"coordinates":[0.4186,51.625923],"type":"Point"}
}