{
  "type": "Feature",
  "properties": {
    "addr:full":"C/o Mitchells,117 Jesmond Road Newcastle-upon-tyne Tyne and Wear NE2 1NW",
    "addr:housenumber":"/ o;117",
    "addr:postcode":"ne2 1nw",
    "addr:street":"C;Mitchells;Jesmond Road",
    "iso:country":"GB",
    "sg:address":"C/o Mitchells,117 Jesmond Road",
    "sg:city":"Newcastle-upon-tyne",
    "sg:classifiers":[
        {
            "category":"Organizations",
            "subcategory":"Membership Organization",
            "type":"Services"
        },
        {
            "category":"Sports & Exercise",
            "subcategory":"Golf",
            "type":"Entertainment"
        }
    ],
    "sg:postcode":"NE2 1NW",
    "sg:province":"Tyne and Wear",
    "sg:tags":[
        "club",
        "course"
    ],
    "wof:name":"Burgham Park Golf Club Ltd",
    "wof:placetype":"venue"
},
  "geometry": {"coordinates":[-1.59964,54.984501],"type":"Point"}
}