{
  "type": "Feature",
  "properties": {
    "iso:country":"GB",
    "sg:address":"788/790 Finchley Rd",
    "sg:city":"London",
    "sg:classifiers":[
        {
            "category":"Professional",
            "subcategory":"Computer Services",
            "type":"Services"
        }
    ],
    "sg:postcode":"NW11 7UR",
    "sg:province":"Greater London",
    "sg:tags":[
        "system",
        "software"
    ],
    "wof:name":"Pragmatik Consultancy Limited",
    "wof:placetype":"venue"
},
  "geometry": {"coordinates":[-0.196479,51.575459],"type":"Point"}
}