{
  "type": "Feature",
  "properties": {
    "addr:full":"74 Aslett St London Greater London SW18 2BQ",
    "addr:housenumber":"74",
    "addr:postcode":"sw18 2bq",
    "addr:street":"Aslett St",
    "iso:country":"GB",
    "sg:address":"74 Aslett St",
    "sg:city":"London",
    "sg:classifiers":[
        {
            "category":"Train Station",
            "subcategory":"Rail",
            "type":"Transportation"
        }
    ],
    "sg:postcode":"SW18 2BQ",
    "sg:province":"Greater London",
    "sg:tags":[
        "railway"
    ],
    "wof:name":"Deg Signal Ltd",
    "wof:placetype":"venue"
},
  "geometry": {"coordinates":[-0.186799,51.450977],"type":"Point"}
}