{
  "type": "Feature",
  "properties": {
    "iso:country":"GB",
    "sg:address":"Unit 24 1-10 Summer Street",
    "sg:city":"London",
    "sg:classifiers":[
        {
            "category":"Professional",
            "subcategory":"Art Services",
            "type":"Services"
        }
    ],
    "sg:phone":"+44 20 7713 1728",
    "sg:postcode":"EC1R 5BD",
    "sg:province":"Greater London",
    "sg:tags":[
        "photographer"
    ],
    "wof:name":"Jean Paul Frouget",
    "wof:placetype":"venue"
},
  "geometry": {"coordinates":[-0.109879002,51.5226364136],"type":"Point"}
}