{
  "type": "Feature",
  "properties": {
    "addr:full":"3 High Street Skegness Lincolnshire PE25 3NY",
    "addr:housenumber":"3",
    "addr:postcode":"pe25 3ny",
    "addr:street":"High Street",
    "iso:country":"GB",
    "sg:address":"3 High Street",
    "sg:city":"Skegness",
    "sg:classifiers":[
        {
            "category":"Fast Food",
            "type":"Food & Drink"
        }
    ],
    "sg:postcode":"PE25 3NY",
    "sg:province":"Lincolnshire",
    "sg:tags":[
        "away",
        "meal",
        "outlet",
        "take"
    ],
    "wof:name":"ELIZABETH ANN'S",
    "wof:placetype":"venue"
},
  "geometry": {"coordinates":[0.3359929919,53.1434745789],"type":"Point"}
}