{
  "type": "Feature",
  "properties": {
    "addr:full":"2 Coldside Rd Dundee Dundee City DD3 8DF",
    "addr:housenumber":"2",
    "addr:postcode":"dd3 8df",
    "addr:street":"Coldside Rd",
    "iso:country":"GB",
    "sg:address":"2 Coldside Rd",
    "sg:city":"Dundee",
    "sg:classifiers":[
        {
            "category":"Education",
            "subcategory":"Special Training",
            "type":"Public Place"
        }
    ],
    "sg:phone":"+44 1382 833747",
    "sg:postcode":"DD3 8DF",
    "sg:province":"Dundee City",
    "sg:tags":[
        "product",
        "centre"
    ],
    "wof:name":"Dudhope Castle Business Services",
    "wof:placetype":"venue"
},
  "geometry": {"coordinates":[-2.983506,56.476192],"type":"Point"}
}