{
  "type": "Feature",
  "properties": {
    "addr:full":"8c Market Parade, Hampton Road West Feltham Greater London TW13 6AL",
    "addr:housenumber":"8c",
    "addr:postcode":"tw13 6al",
    "addr:street":"Market Parade Hampton Road West",
    "iso:country":"GB",
    "sg:address":"8c Market Parade, Hampton Road West",
    "sg:city":"Feltham",
    "sg:classifiers":[
        {
            "category":"Retail",
            "subcategory":"Auto Repair",
            "type":"Services"
        }
    ],
    "sg:phone":"+44 20 8893 3959",
    "sg:postcode":"TW13 6AL",
    "sg:province":"Greater London",
    "sg:tags":[
        "electrician"
    ],
    "wof:name":"A T Auto Electricals",
    "wof:placetype":"venue"
},
  "geometry": {"coordinates":[-0.409204,51.447075],"type":"Point"}
}