{
  "type": "Feature",
  "properties": {
    "iso:country":"GB",
    "sg:address":"Castle End Farm, Lea",
    "sg:city":"Ross-on-wye",
    "sg:classifiers":[
        {
            "category":"Utilities",
            "subcategory":"Natural Gas",
            "type":"Services"
        }
    ],
    "sg:phone":"+44 1989 750265",
    "sg:postcode":"HR9 7JY",
    "sg:province":"Gloucestershire",
    "sg:tags":[
        "supplier"
    ],
    "wof:name":"Castle Gas",
    "wof:placetype":"venue"
},
  "geometry": {"coordinates":[-2.5817329884,51.9164810181],"type":"Point"}
}