{
  "type": "Feature",
  "properties": {
    "iso:country":"GB",
    "sg:address":"4 St Johns Road",
    "sg:city":"Huddersfield",
    "sg:classifiers":[
        {
            "category":"Shopping",
            "subcategory":"Baby Store",
            "type":"Retail Goods"
        }
    ],
    "sg:postcode":"HD1 5AT",
    "sg:province":"West Yorkshire",
    "sg:tags":[
        "nursery",
        "accessory"
    ],
    "wof:name":"Mr Baby",
    "wof:placetype":"venue"
},
  "geometry": {"coordinates":[-1.78405,53.650913],"type":"Point"}
}