{
  "type": "Feature",
  "properties": {
    "addr:full":"97b Hedworth, Badsey Lane Evesham Gloucestershire WR11 3EY",
    "addr:housenumber":"97b",
    "addr:postcode":"wr11 3ey",
    "addr:street":"Hedworth Badsey Lane",
    "iso:country":"GB",
    "sg:address":"97b Hedworth, Badsey Lane",
    "sg:city":"Evesham",
    "sg:classifiers":[
        {
            "category":"Arena",
            "subcategory":"Sports Club",
            "type":"Entertainment"
        }
    ],
    "sg:phone":"+44 1386 422821",
    "sg:postcode":"WR11 3EY",
    "sg:province":"Gloucestershire",
    "wof:name":"Evesham Fencing Club",
    "wof:placetype":"venue"
},
  "geometry": {"coordinates":[-1.9439690113,52.1063919067],"type":"Point"}
}