{
  "type": "Feature",
  "properties": {
    "iso:country":"GB",
    "sg:address":"Ashtor, 59colesdown Hill, Billacombe",
    "sg:city":"Plymouth",
    "sg:classifiers":[
        {
            "category":"Recreation",
            "subcategory":"Amusement Park",
            "type":"Entertainment"
        }
    ],
    "sg:phone":"+44 1752 402033",
    "sg:postcode":"PL9 8AG",
    "sg:province":"Devon",
    "sg:tags":[
        "arcade"
    ],
    "wof:name":"Jointmatics Ltd.",
    "wof:placetype":"venue"
},
  "geometry": {"coordinates":[-4.082484,50.366177],"type":"Point"}
}