{
  "type": "Feature",
  "properties": {
    "iso:country":"GB",
    "sg:address":"49 Wolseley Avenue, Wimbledon Parl",
    "sg:city":"London",
    "sg:classifiers":[
        {
            "category":"Building & Trades",
            "subcategory":"Construction",
            "type":"Services"
        }
    ],
    "sg:postcode":"SW19 8BG",
    "sg:province":"Greater London",
    "sg:tags":[
        "builder"
    ],
    "wof:name":"Fair Dinkum Builders Ltd",
    "wof:placetype":"venue"
},
  "geometry": {"coordinates":[-0.20008,51.439392],"type":"Point"}
}