{
  "type": "Feature",
  "properties": {
    "iso:country":"GB",
    "sg:address":"23a St Petersgate",
    "sg:city":"Stockport",
    "sg:classifiers":[
        {
            "category":"Shopping",
            "subcategory":"Clothing, Apparel, & Fashions",
            "type":"Retail Goods"
        }
    ],
    "sg:phone":"+44 161 476 3360",
    "sg:postcode":"SK1 1EB",
    "sg:province":"Cheshire",
    "sg:tags":[
        "dresswear"
    ],
    "wof:name":"Ryans Formal Hire",
    "wof:placetype":"venue"
},
  "geometry": {"coordinates":[-2.1581029892,53.4100418091],"type":"Point"}
}