{
  "type": "Feature",
  "properties": {
    "addr:full":"Westview House, 734 London Road Stoke-on-trent Staffordshire ST4 5NP",
    "addr:housenumber":"734",
    "addr:postcode":"st4 5np",
    "addr:street":"London Road",
    "iso:country":"GB",
    "sg:address":"Westview House, 734 London Road",
    "sg:city":"Stoke-on-trent",
    "sg:classifiers":[
        {
            "category":"Education",
            "subcategory":"Special Training",
            "type":"Public Place"
        }
    ],
    "sg:phone":"+44 1782 745944",
    "sg:postcode":"ST4 5NP",
    "sg:province":"Staffordshire",
    "sg:tags":[
        "product",
        "centre"
    ],
    "wof:name":"Neuro Hypnotic Programming Research Ltd.",
    "wof:placetype":"venue"
},
  "geometry": {"coordinates":[-2.1982409954,52.9905357361],"type":"Point"}
}