{
  "type": "Feature",
  "properties": {
    "addr:full":"Farthing Green House, 1 Beccles Road, Loddon Norwich Norfolk NR14 6LT",
    "addr:housenumber":"1",
    "addr:postcode":"nr14 6lt",
    "addr:street":"Beccles Road;Norwich",
    "iso:country":"GB",
    "sg:address":"Farthing Green House, 1 Beccles Road, Loddon",
    "sg:city":"Norwich",
    "sg:classifiers":[
        {
            "category":"Professional",
            "subcategory":"Management & Consulting",
            "type":"Services"
        }
    ],
    "sg:phone":"+44 1508 528465",
    "sg:postcode":"NR14 6LT",
    "sg:province":"Norfolk",
    "sg:tags":[
        "environmental",
        "consultant"
    ],
    "wof:name":"Risk & Policy Analysts Ltd.",
    "wof:placetype":"venue"
},
  "geometry": {"coordinates":[1.504629,52.522518],"type":"Point"}
}