{
  "type": "Feature",
  "properties": {
    "iso:country":"GB",
    "sg:address":"215 Queens Crescent",
    "sg:city":"London",
    "sg:classifiers":[
        {
            "category":"Farming",
            "subcategory":"Nursery",
            "type":"Manufacturing & Wholesale Goods"
        }
    ],
    "sg:phone":"+44 20 7485 1551",
    "sg:postcode":"NW5 4DP",
    "sg:province":"Greater London",
    "sg:tags":[
        "creche"
    ],
    "wof:name":"Cresswood Nursery",
    "wof:placetype":"venue"
},
  "geometry": {"coordinates":[-0.148819,51.551079],"type":"Point"}
}