{
  "type": "Feature",
  "properties": {
    "addr:full":"Gosbecks Road Colchester Essex CO2 9JT",
    "addr:postcode":"co2 9jt",
    "addr:street":"Gosbecks Road Colchester",
    "iso:country":"GB",
    "sg:address":"Gosbecks Road",
    "sg:city":"Colchester",
    "sg:classifiers":[
        {
            "category":"Real Estate",
            "subcategory":"Developer",
            "type":"Services"
        }
    ],
    "sg:phone":"+44 1206 764472",
    "sg:postcode":"CO2 9JT",
    "sg:province":"Essex",
    "sg:tags":[
        "property"
    ],
    "wof:name":"Prowting Homes Ltd.",
    "wof:placetype":"venue"
},
  "geometry": {"coordinates":[0.862265,51.872265],"type":"Point"}
}