{
  "type": "Feature",
  "properties": {
    "addr:full":"33 Front Street Consett Durham DH8 5AB",
    "addr:housenumber":"33",
    "addr:postcode":"dh8 5ab",
    "addr:street":"Front Street",
    "iso:country":"GB",
    "sg:address":"33 Front Street",
    "sg:city":"Consett",
    "sg:classifiers":[
        {
            "category":"Professional",
            "subcategory":"Lawyer & Legal Services",
            "type":"Services"
        }
    ],
    "sg:phone":"+44 1207 504141",
    "sg:postcode":"DH8 5AB",
    "sg:province":"Durham",
    "sg:tags":[
        "solicitor"
    ],
    "wof:name":"James Aylmore Davies Malone Solicitors",
    "wof:placetype":"venue"
},
  "geometry": {"coordinates":[-1.8320660591,54.851524353],"type":"Point"}
}