{
  "type": "Feature",
  "properties": {
    "addr:full":"49 Francis Avenue Southsea Hampshire PO4 0HL",
    "addr:housenumber":"49",
    "addr:postcode":"po4 0hl",
    "addr:street":"Francis Avenue",
    "iso:country":"GB",
    "sg:address":"49 Francis Avenue",
    "sg:city":"Southsea",
    "sg:classifiers":[
        {
            "category":"Health Services",
            "subcategory":"Podiatrist",
            "type":"Services"
        }
    ],
    "sg:phone":"+44 23 9273 1062",
    "sg:postcode":"PO4 0HL",
    "sg:province":"Hampshire",
    "sg:tags":[
        "podiatrists",
        "chiropodist"
    ],
    "wof:name":"P M Channon MSSCh MBChA",
    "wof:placetype":"venue"
},
  "geometry": {"coordinates":[-1.0722119808,50.7881851196],"type":"Point"}
}