{
  "type": "Feature",
  "properties": {
    "iso:country":"GB",
    "sg:address":"10 Wellington Street, Cambridge",
    "sg:city":"Cambridge",
    "sg:classifiers":[
        {
            "category":"Professional",
            "subcategory":"Accounting & Tax Preparation",
            "type":"Services"
        }
    ],
    "sg:postcode":"CB1 1HW",
    "sg:province":"Cambridgeshire",
    "sg:tags":[
        "consultant"
    ],
    "wof:name":"Andrew Webster Associates Ltd",
    "wof:placetype":"venue"
},
  "geometry": {"coordinates":[0.135089,52.207932],"type":"Point"}
}