{
  "type": "Feature",
  "properties": {
    "iso:country":"GB",
    "sg:address":"433 Tong St",
    "sg:city":"Bradford",
    "sg:classifiers":[
        {
            "category":"Food & Beverages",
            "subcategory":"Liquor & Beverages",
            "type":"Retail Goods"
        }
    ],
    "sg:phone":"+44 1274 681714",
    "sg:postcode":"BD4 6LX",
    "sg:province":"West Yorkshire",
    "sg:tags":[
        "beer",
        "spirit",
        "wines"
    ],
    "wof:name":"Tong Food Store",
    "wof:placetype":"venue"
},
  "geometry": {"coordinates":[-1.709547,53.767601],"type":"Point"}
}