{
  "type": "Feature",
  "properties": {
    "iso:country":"GB",
    "sg:address":"71 York Ave, Fartown",
    "sg:city":"Huddersfield",
    "sg:classifiers":[
        {
            "category":"Shopping",
            "subcategory":"Clothing, Apparel, & Fashions",
            "type":"Retail Goods"
        }
    ],
    "sg:postcode":"HD2 2PP",
    "sg:province":"West Yorkshire",
    "sg:tags":[
        "clothing"
    ],
    "wof:name":"Azam Bros",
    "wof:placetype":"venue"
},
  "geometry": {"coordinates":[-1.787662,53.664749],"type":"Point"}
}