{
  "type": "Feature",
  "properties": {
    "addr:full":"Bunkers Hill, Townshend Hayle Cornwall TR27 6ER",
    "addr:postcode":"tr27 6er",
    "iso:country":"GB",
    "sg:address":"Bunkers Hill, Townshend",
    "sg:city":"Hayle",
    "sg:classifiers":[
        {
            "category":"Community Center",
            "type":"Public Place"
        }
    ],
    "sg:phone":"+44 1736 850209",
    "sg:postcode":"TR27 6ER",
    "sg:province":"Cornwall",
    "sg:tags":[
        "recreation",
        "leisure",
        "centre"
    ],
    "wof:name":"Country Skittles Ltd.",
    "wof:placetype":"venue"
},
  "geometry": {"coordinates":[-5.371024,50.146721],"type":"Point"}
}