{
  "type": "Feature",
  "properties": {
    "addr:full":"11 Nottingham Road, Stapleford Nottingham Nottinghamshire NG9 8AB",
    "addr:housenumber":"11",
    "addr:postcode":"ng9 8ab",
    "addr:street":"Nottingham Road",
    "iso:country":"GB",
    "sg:address":"11 Nottingham Road, Stapleford",
    "sg:city":"Nottingham",
    "sg:classifiers":[
        {
            "category":"Personal",
            "subcategory":"Beauty Salon",
            "type":"Services"
        }
    ],
    "sg:phone":"+44 115 939 9680",
    "sg:postcode":"NG9 8AB",
    "sg:province":"Nottinghamshire",
    "wof:name":"Manor Beauty Parlour",
    "wof:placetype":"venue"
},
  "geometry": {"coordinates":[-1.2738820314,52.9297828674],"type":"Point"}
}