{
  "type": "Feature",
  "properties": {
    "iso:country":"GB",
    "sg:address":"5 Calverley Rd",
    "sg:city":"Eastbourne",
    "sg:classifiers":[
        {
            "category":"Health Services",
            "subcategory":"Hospital",
            "type":"Services"
        }
    ],
    "sg:phone":"+44 1323 411191",
    "sg:postcode":"BN21 4SR",
    "sg:province":"East Sussex",
    "sg:tags":[
        "ambulance"
    ],
    "wof:name":"Sussex Immediate Care",
    "wof:placetype":"venue"
},
  "geometry": {"coordinates":[0.280267,50.767059],"type":"Point"}
}