{
  "type": "Feature",
  "properties": {
    "iso:country":"GB",
    "sg:address":"51 Athol Terrace",
    "sg:city":"Bathgate",
    "sg:classifiers":[
        {
            "category":"Home & Garden",
            "subcategory":"Carpets & Floor Coverings",
            "type":"Retail Goods"
        }
    ],
    "sg:phone":"+44 1506 654689",
    "sg:postcode":"EH48 4DN",
    "sg:province":"West Lothian",
    "sg:tags":[
        "cleaner",
        "upholstery"
    ],
    "wof:name":"Royan Cleaning Services",
    "wof:placetype":"venue"
},
  "geometry": {"coordinates":[-3.6357591152,55.9082183838],"type":"Point"}
}