{
  "type": "Feature",
  "properties": {
    "iso:country":"GB",
    "sg:address":"3 Broadcroft, Highfield",
    "sg:city":"Hemel Hempstead",
    "sg:classifiers":[
        {
            "category":"Building & Trades",
            "subcategory":"Construction",
            "type":"Services"
        }
    ],
    "sg:postcode":"HP2 5YX",
    "sg:province":"Hertfordshire",
    "sg:tags":[
        "decorator",
        "painter"
    ],
    "wof:name":"Colin J Fuller",
    "wof:placetype":"venue"
},
  "geometry": {"coordinates":[-0.469186,51.764072],"type":"Point"}
}