{
  "type": "Feature",
  "properties": {
    "addr:full":"2 Edgefield Av Manningtree Essex CO11 2HD",
    "addr:housenumber":"2",
    "addr:postcode":"co11 2hd",
    "addr:street":"Edgefield Av Manningtree",
    "iso:country":"GB",
    "sg:address":"2 Edgefield Av",
    "sg:city":"Manningtree",
    "sg:classifiers":[
        {
            "category":"Health Services",
            "subcategory":"Doctor",
            "type":"Services"
        }
    ],
    "sg:phone":"+44 1206 392617",
    "sg:postcode":"CO11 2HD",
    "sg:province":"Essex",
    "sg:tags":[
        "practitioners"
    ],
    "wof:name":"Ahmad, H",
    "wof:placetype":"venue"
},
  "geometry": {"coordinates":[1.050566,51.940685],"type":"Point"}
}