{
  "type": "Feature",
  "properties": {
    "addr:full":"Hempstead Road Industrial Estate Holt Norfolk NR25 6DH",
    "addr:postcode":"nr25 6dh",
    "addr:street":"Hempstead Road Industrial Estate Holt",
    "iso:country":"GB",
    "sg:address":"Hempstead Road Industrial Estate",
    "sg:city":"Holt",
    "sg:classifiers":[
        {
            "category":"Professional",
            "subcategory":"Engineering",
            "type":"Services"
        }
    ],
    "sg:phone":"+44 1263 711648",
    "sg:postcode":"NR25 6DH",
    "sg:province":"Norfolk",
    "wof:name":"Crestbury Engineering",
    "wof:placetype":"venue"
},
  "geometry": {"coordinates":[1.095735,52.903622],"type":"Point"}
}