{
  "type": "Feature",
  "properties": {
    "addr:full":"Ashton Road Woodhouses, Failsworth Manchester Lancashire M35 9WL",
    "addr:postcode":"m35 9wl",
    "addr:street":"Ashton Road Woodhouses Failsworth",
    "iso:country":"GB",
    "sg:address":"Ashton Road Woodhouses, Failsworth",
    "sg:city":"Manchester",
    "sg:classifiers":[
        {
            "category":"Education",
            "subcategory":"School",
            "type":"Public Place"
        },
        {
            "category":"Government",
            "subcategory":"Office",
            "type":"Public Place"
        }
    ],
    "sg:phone":"+44 161 681 6793",
    "sg:postcode":"M35 9WL",
    "sg:province":"Lancashire",
    "sg:tags":[
        "local",
        "authority"
    ],
    "wof:name":"Woodhouses Voluntary Junior & Infant School",
    "wof:placetype":"venue"
},
  "geometry": {"coordinates":[-2.1307420731,53.5063819885],"type":"Point"}
}