{
  "type": "Feature",
  "properties": {
    "addr:full":"376 Washway Road Sale Cheshire M33 4HF",
    "addr:housenumber":"376",
    "addr:postcode":"m33 4hf",
    "addr:street":"Washway Road",
    "iso:country":"GB",
    "sg:address":"376 Washway Road",
    "sg:city":"Sale",
    "sg:classifiers":[
        {
            "category":"Health Services",
            "subcategory":"Health Practitioner",
            "type":"Services"
        }
    ],
    "sg:phone":"+44 161 973 1603",
    "sg:postcode":"M33 4HF",
    "sg:province":"Cheshire",
    "sg:tags":[
        "physiotherapist"
    ],
    "wof:name":"K Murphy",
    "wof:placetype":"venue"
},
  "geometry": {"coordinates":[-2.3440859318,53.4093437195],"type":"Point"}
}