{
  "type": "Feature",
  "properties": {
    "addr:full":"54 Knifesmithgate Chesterfield Derbyshire S40 1RQ",
    "addr:housenumber":"54",
    "addr:postcode":"s40 1rq",
    "addr:street":"Knifesmithgate",
    "iso:country":"GB",
    "sg:address":"54 Knifesmithgate",
    "sg:city":"Chesterfield",
    "sg:classifiers":[
        {
            "category":"Professional",
            "subcategory":"Printing & Photocopies",
            "type":"Services"
        }
    ],
    "sg:phone":"+44 1246 208057",
    "sg:postcode":"S40 1RQ",
    "sg:province":"Derbyshire",
    "sg:tags":[
        "printer"
    ],
    "wof:name":"Prontaprint",
    "wof:placetype":"venue"
},
  "geometry": {"coordinates":[-1.4262119532,53.2362518311],"type":"Point"}
}