{
  "type": "Feature",
  "properties": {
    "iso:country":"GB",
    "sg:address":"60 Alma Hill, Kimberley",
    "sg:city":"Nottingham",
    "sg:classifiers":[
        {
            "category":"Building & Trades",
            "subcategory":"Construction",
            "type":"Services"
        }
    ],
    "sg:postcode":"NG16 2JF",
    "sg:province":"Derbyshire",
    "sg:tags":[
        "supplier",
        "installers",
        "cladding"
    ],
    "wof:name":"Kirkham,Anthony,",
    "wof:placetype":"venue"
},
  "geometry": {"coordinates":[-1.267343,53.004871],"type":"Point"}
}