{
  "type": "Feature",
  "properties": {
    "iso:country":"GB",
    "sg:address":"18 Parker Street",
    "sg:city":"Manchester",
    "sg:classifiers":[
        {
            "category":"Banks & Credit Unions",
            "subcategory":"Financial Services",
            "type":"Services"
        }
    ],
    "sg:phone":"+44 161 228 3500",
    "sg:postcode":"M1 4AF",
    "sg:province":"Greater Manchester",
    "sg:tags":[
        "cashing",
        "cheque"
    ],
    "wof:name":"The Money Shop Ltd.",
    "wof:placetype":"venue"
},
  "geometry": {"coordinates":[-2.2385909557,53.4808197021],"type":"Point"}
}