{
  "type": "Feature",
  "properties": {
    "iso:country":"GB",
    "sg:address":"36 Tudor Way, Hillingdon",
    "sg:city":"Uxbridge",
    "sg:classifiers":[
        {
            "category":"Health Services",
            "subcategory":"Health Practitioner",
            "type":"Services"
        }
    ],
    "sg:postcode":"UB10 9AB",
    "sg:province":"Greater London",
    "sg:tags":[
        "acupuncture"
    ],
    "wof:name":"Ruth Saunders Health Clinic",
    "wof:placetype":"venue"
},
  "geometry": {"coordinates":[-0.452125,51.550274],"type":"Point"}
}