{
  "type": "Feature",
  "properties": {
    "addr:full":"5 Connemara Cres Fareham Hampshire PO15 7BN",
    "addr:housenumber":"5",
    "addr:postcode":"po15 7bn",
    "addr:street":"Connemara Cres",
    "iso:country":"GB",
    "sg:address":"5 Connemara Cres",
    "sg:city":"Fareham",
    "sg:classifiers":[
        {
            "category":"Building & Trades",
            "subcategory":"Construction",
            "type":"Services"
        }
    ],
    "sg:phone":"+44 1489 880260",
    "sg:postcode":"PO15 7BN",
    "sg:province":"Hampshire",
    "sg:tags":[
        "heating",
        "contractor"
    ],
    "wof:name":"J Walker",
    "wof:placetype":"venue"
},
  "geometry": {"coordinates":[-1.2652130127,50.8806762695],"type":"Point"}
}