{
  "type": "Feature",
  "properties": {
    "iso:country":"GB",
    "sg:address":"11 St Andrews Road",
    "sg:city":"London",
    "sg:classifiers":[
        {
            "category":"Manufacturing",
            "subcategory":"Tools & Machinery",
            "type":"Manufacturing & Wholesale Goods"
        }
    ],
    "sg:phone":"+44 20 8749 5939",
    "sg:postcode":"W3 7NE",
    "sg:province":"Greater London",
    "sg:tags":[
        "society",
        "friendly"
    ],
    "wof:name":"World of Insurance",
    "wof:placetype":"venue"
},
  "geometry": {"coordinates":[-0.2523800135,51.5148468018],"type":"Point"}
}