{
  "type": "Feature",
  "properties": {
    "addr:full":"33a Brookend St Ross On Wye Gloucestershire HR9 7EE",
    "addr:housenumber":"33a",
    "addr:postcode":"hr9 7ee",
    "addr:street":"Brookend St",
    "iso:country":"GB",
    "sg:address":"33a Brookend St",
    "sg:city":"Ross On Wye",
    "sg:classifiers":[
        {
            "category":"Shopping",
            "subcategory":"Books",
            "type":"Retail Goods"
        }
    ],
    "sg:phone":"+44 1989 768956",
    "sg:postcode":"HR9 7EE",
    "sg:province":"Gloucestershire",
    "wof:name":"The Flyer",
    "wof:placetype":"venue"
},
  "geometry": {"coordinates":[-2.5817229748,51.9160461426],"type":"Point"}
}