{
  "type": "Feature",
  "properties": {
    "addr:full":"5 Market Place Bishop Auckland Durham DL14 7NW",
    "addr:housenumber":"5",
    "addr:postcode":"dl14 7nw",
    "addr:street":"Market Place",
    "iso:country":"GB",
    "sg:address":"5 Market Place",
    "sg:city":"Bishop Auckland",
    "sg:classifiers":[
        {
            "category":"Professional",
            "subcategory":"Lawyer & Legal Services",
            "type":"Services"
        }
    ],
    "sg:phone":"+44 1388 604691",
    "sg:postcode":"DL14 7NW",
    "sg:province":"Durham",
    "sg:tags":[
        "solicitor"
    ],
    "wof:name":"Hewitt Brown-Humes & Hare",
    "wof:placetype":"venue"
},
  "geometry": {"coordinates":[-1.6729609966,54.6653327942],"type":"Point"}
}