{
  "type": "Feature",
  "properties": {
    "iso:country":"GB",
    "sg:address":"Unit 6 Sham Farm, Danegate",
    "sg:city":"Tunbridge Wells",
    "sg:classifiers":[
        {
            "category":"Professional",
            "subcategory":"Printing & Photocopies",
            "type":"Services"
        }
    ],
    "sg:phone":"+44 1892 752000",
    "sg:postcode":"TN3 9JA",
    "sg:province":"East Sussex",
    "sg:tags":[
        "printer"
    ],
    "wof:name":"Source (Ec) Ltd.",
    "wof:placetype":"venue"
},
  "geometry": {"coordinates":[0.219062,51.088963],"type":"Point"}
}