{
  "type": "Feature",
  "properties": {
    "iso:country":"GB",
    "sg:address":"137 Ermin Street, Stratton St Margaret",
    "sg:city":"Swindon",
    "sg:classifiers":[
        {
            "category":"Arts & Performance",
            "subcategory":"Music",
            "type":"Entertainment"
        }
    ],
    "sg:phone":"+44 1793 826700",
    "sg:postcode":"SN3 4NH",
    "sg:province":"Wiltshire",
    "sg:tags":[
        "mobile",
        "disco"
    ],
    "wof:name":"M 4 Roadshow",
    "wof:placetype":"venue"
},
  "geometry": {"coordinates":[-1.747019,51.582855],"type":"Point"}
}