{
  "type": "Feature",
  "properties": {
    "addr:full":"West View, Hurdle Drove Bury St Edmunds Cambridgeshire IP28 8RB",
    "addr:postcode":"ip28 8rb",
    "addr:street":"Hurdle Drove;St",
    "iso:country":"GB",
    "sg:address":"West View, Hurdle Drove",
    "sg:city":"Bury St Edmunds",
    "sg:classifiers":[
        {
            "category":"Communications",
            "type":"Services"
        }
    ],
    "sg:phone":"+44 1638 711220",
    "sg:postcode":"IP28 8RB",
    "sg:province":"Cambridgeshire",
    "sg:tags":[
        "tv",
        "video",
        "radio"
    ],
    "wof:name":"Mildenhall Satellite (Milsat)",
    "wof:placetype":"venue"
},
  "geometry": {"coordinates":[0.4597600102,52.3627090454],"type":"Point"}
}