{
  "type": "Feature",
  "properties": {
    "iso:country":"GB",
    "sg:address":"23 Honey End Lane",
    "sg:city":"Reading",
    "sg:classifiers":[
        {
            "category":"Professional",
            "subcategory":"Art Services",
            "type":"Services"
        }
    ],
    "sg:phone":"+44 118 957 3651",
    "sg:postcode":"RG30 4EL",
    "sg:province":"Berkshire",
    "sg:tags":[
        "graphic",
        "designer"
    ],
    "wof:name":"Barry Boulton Design",
    "wof:placetype":"venue"
},
  "geometry": {"coordinates":[-1.01596,51.446049],"type":"Point"}
}