{
  "type": "Feature",
  "properties": {
    "iso:country":"GB",
    "sg:address":"Bryn Y Neudd Hospital",
    "sg:city":"Llanfairfechan",
    "sg:classifiers":[
        {
            "category":"Organizations",
            "subcategory":"Professional Association",
            "type":"Services"
        }
    ],
    "sg:phone":"+44 1248 680891",
    "sg:postcode":"LL33 0HH",
    "sg:province":"Conwy",
    "sg:tags":[
        "union",
        "trade"
    ],
    "wof:name":"Unison Gwynedd Community Health Branch",
    "wof:placetype":"venue"
},
  "geometry": {"coordinates":[-3.978774,53.253571],"type":"Point"}
}