{
  "type": "Feature",
  "properties": {
    "iso:country":"GB",
    "sg:address":"East Barnton Avenue",
    "sg:city":"Edinburgh",
    "sg:classifiers":[
        {
            "category":"Education",
            "subcategory":"School",
            "type":"Public Place"
        }
    ],
    "sg:phone":"+44 131 336 2261",
    "sg:postcode":"EH4 6JP",
    "sg:province":"City of Edinburgh",
    "sg:tags":[
        "local",
        "authority"
    ],
    "wof:name":"The Royal High School",
    "wof:placetype":"venue"
},
  "geometry": {"coordinates":[-3.306225,55.96175],"type":"Point"}
}