{
  "type": "Feature",
  "properties": {
    "iso:country":"GB",
    "sg:address":"Atlas Ho, Cambridge Pl",
    "sg:city":"Cambridge",
    "sg:classifiers":[
        {
            "category":"Real Estate",
            "subcategory":"Architect",
            "type":"Services"
        }
    ],
    "sg:phone":"+44 1223 366313",
    "sg:postcode":"CB2 1NS",
    "sg:province":"Cambridgeshire",
    "wof:name":"P R C Fewster Ltd",
    "wof:placetype":"venue"
},
  "geometry": {"coordinates":[0.1307269931,52.1975364685],"type":"Point"}
}