{
  "type": "Feature",
  "properties": {
    "addr:full":"323 Gloucester Rd Bristol City of Bristol BS7 8PE",
    "addr:housenumber":"323",
    "addr:postcode":"bs7 8pe",
    "addr:street":"Gloucester Rd",
    "iso:country":"GB",
    "sg:address":"323 Gloucester Rd",
    "sg:city":"Bristol",
    "sg:classifiers":[
        {
            "category":"Bars & Pubs",
            "type":"Food & Drink"
        }
    ],
    "sg:phone":"+44 117 924 1769",
    "sg:postcode":"BS7 8PE",
    "sg:province":"City of Bristol",
    "sg:tags":[
        "pubs",
        "inn"
    ],
    "wof:name":"Showboat The",
    "wof:placetype":"venue"
},
  "geometry": {"coordinates":[-2.5883738995,51.4807815552],"type":"Point"}
}