{
  "type": "Feature",
  "properties": {
    "iso:country":"GB",
    "sg:address":"6 New Street",
    "sg:city":"Margate",
    "sg:classifiers":[
        {
            "category":"Personal",
            "subcategory":"Beauty Salon",
            "type":"Services"
        }
    ],
    "sg:phone":"+44 1843 294786",
    "sg:postcode":"CT9 1EG",
    "sg:province":"Kent",
    "sg:tags":[
        "lady",
        "hairdresser"
    ],
    "wof:name":"Head Turners Hairdressers",
    "wof:placetype":"venue"
},
  "geometry": {"coordinates":[1.381746,51.388355],"type":"Point"}
}