{
  "type": "Feature",
  "properties": {
    "addr:full":"13a Kyrle Street Hereford Herefordshire HR1 2ET",
    "addr:housenumber":"13a",
    "addr:postcode":"hr1 2et",
    "addr:street":"Kyrle Street",
    "iso:country":"GB",
    "sg:address":"13a Kyrle Street",
    "sg:city":"Hereford",
    "sg:classifiers":[
        {
            "category":"Taxi",
            "type":"Transportation"
        },
        {
            "category":"Military Area",
            "subcategory":"Air Force Base",
            "type":"Public Place"
        }
    ],
    "sg:phone":"+44 1432 278279",
    "sg:postcode":"HR1 2ET",
    "sg:province":"Herefordshire",
    "sg:tags":[
        "mini",
        "hire",
        "private",
        "cab"
    ],
    "wof:name":"Rank Taxis",
    "wof:placetype":"venue"
},
  "geometry": {"coordinates":[-2.7098040581,52.0574798584],"type":"Point"}
}