{
  "type": "Feature",
  "properties": {
    "addr:full":"Blyth Farm, Blyth Bridge West Linton Midlothian EH46 7DG",
    "addr:postcode":"eh46 7dg",
    "addr:street":"Blyth Farm Blyth Bridge West",
    "iso:country":"GB",
    "sg:address":"Blyth Farm, Blyth Bridge",
    "sg:city":"West Linton",
    "sg:classifiers":[
        {
            "category":"Farming",
            "subcategory":"Dairy Farm",
            "type":"Manufacturing & Wholesale Goods"
        }
    ],
    "sg:phone":"+44 1721 752695",
    "sg:postcode":"EH46 7DG",
    "sg:province":"Midlothian",
    "wof:name":"A Laird",
    "wof:placetype":"venue"
},
  "geometry": {"coordinates":[-3.356034,55.754299],"type":"Point"}
}