{
  "type": "Feature",
  "properties": {
    "iso:country":"GB",
    "sg:address":"38 Stanstead Crescent",
    "sg:city":"Havant",
    "sg:classifiers":[
        {
            "category":"Real Estate",
            "subcategory":"Architect",
            "type":"Services"
        }
    ],
    "sg:postcode":"PO9 5NN",
    "sg:province":"Hampshire",
    "wof:name":"Robin J Carver",
    "wof:placetype":"venue"
},
  "geometry": {"coordinates":[-0.969053,50.874344],"type":"Point"}
}