{
  "type": "Feature",
  "properties": {
    "addr:full":"Flat 6 Caroline House, High Street Bushey Hertfordshire WD23 1BH",
    "addr:housenumber":"6",
    "addr:postcode":"wd23 1bh",
    "addr:street":"Caroline;High Street",
    "iso:country":"GB",
    "sg:address":"Flat 6 Caroline House, High Street",
    "sg:city":"Bushey",
    "sg:classifiers":[
        {
            "category":"Organizations",
            "subcategory":"Membership Organization",
            "type":"Services"
        }
    ],
    "sg:phone":"+44 1753 661085",
    "sg:postcode":"WD23 1BH",
    "sg:province":"Hertfordshire",
    "sg:tags":[
        "club"
    ],
    "wof:name":"C H Management Ltd.",
    "wof:placetype":"venue"
},
  "geometry": {"coordinates":[-0.340327,51.633396],"type":"Point"}
}