{
  "type": "Feature",
  "properties": {
    "addr:full":"20 Market Place Fakenham Norfolk NR21 9BG",
    "addr:housenumber":"20",
    "addr:postcode":"nr21 9bg",
    "addr:street":"Market Place",
    "iso:country":"GB",
    "sg:address":"20 Market Place",
    "sg:city":"Fakenham",
    "sg:classifiers":[
        {
            "category":"Personal",
            "subcategory":"Beauty Salon",
            "type":"Services"
        }
    ],
    "sg:postcode":"NR21 9BG",
    "sg:province":"Norfolk",
    "sg:tags":[
        "unisex",
        "hairdresser"
    ],
    "wof:name":"The Hair Studio",
    "wof:placetype":"venue"
},
  "geometry": {"coordinates":[0.8475520015,52.8300018311],"type":"Point"}
}