{
  "type": "Feature",
  "properties": {
    "iso:country":"GB",
    "sg:address":"Adult Education Offices, Rosemount C E C, Belgrave Terr",
    "sg:city":"Aberdeen",
    "sg:classifiers":[
        {
            "category":"Government",
            "subcategory":"Office",
            "type":"Public Place"
        }
    ],
    "sg:phone":"+44 1224 644431",
    "sg:postcode":"AB25 2NS",
    "sg:province":"Aberdeen City",
    "sg:tags":[
        "local"
    ],
    "wof:name":"Aberdeen City Council",
    "wof:placetype":"venue"
},
  "geometry": {"coordinates":[-2.1190099716,57.1476516724],"type":"Point"}
}