{
  "type": "Feature",
  "properties": {
    "iso:country":"GB",
    "sg:address":"Kintyre House,, 70, High Street,",
    "sg:city":"Fareham",
    "sg:classifiers":[
        {
            "category":"Education",
            "subcategory":"Special Training",
            "type":"Public Place"
        }
    ],
    "sg:postcode":"PO16 7BB",
    "sg:province":"Hampshire",
    "sg:tags":[
        "product",
        "centre"
    ],
    "wof:name":"Radio School Limited",
    "wof:placetype":"venue"
},
  "geometry": {"coordinates":[-1.1819289923,50.8576011658],"type":"Point"}
}