{
  "type": "Feature",
  "properties": {
    "iso:country":"GB",
    "sg:address":"13 Woodchurch Rd",
    "sg:city":"Birkenhead",
    "sg:classifiers":[
        {
            "category":"Personal",
            "subcategory":"Barber",
            "type":"Services"
        }
    ],
    "sg:phone":"+44 151 652 7886",
    "sg:postcode":"L42 9LG",
    "sg:province":"Merseyside",
    "sg:tags":[
        "men's",
        "hairdresser"
    ],
    "wof:name":"Chopper Squad The",
    "wof:placetype":"venue"
},
  "geometry": {"coordinates":[-3.036143,53.383663],"type":"Point"}
}