{
  "type": "Feature",
  "properties": {
    "iso:country":"GB",
    "sg:address":"44 George Street",
    "sg:city":"Hove",
    "sg:classifiers":[
        {
            "category":"Shopping",
            "subcategory":"Comic Books",
            "type":"Retail Goods"
        }
    ],
    "sg:postcode":"BN3 3YB",
    "sg:province":"East Sussex",
    "sg:tags":[
        "jeweller"
    ],
    "wof:name":"James Fine Jewellers",
    "wof:placetype":"venue"
},
  "geometry": {"coordinates":[-0.1730110049,50.8301582336],"type":"Point"}
}