{
  "type": "Feature",
  "properties": {
    "iso:country":"GB",
    "sg:address":"Deacon Way, Oxford Rd",
    "sg:city":"Reading",
    "sg:classifiers":[
        {
            "category":"Food & Beverages",
            "subcategory":"Meat & Fish",
            "type":"Retail Goods"
        }
    ],
    "sg:phone":"+44 118 945 1788",
    "sg:postcode":"RG30 6AZ",
    "sg:province":"Berkshire",
    "sg:tags":[
        "butcher"
    ],
    "wof:name":"K C Meats",
    "wof:placetype":"venue"
},
  "geometry": {"coordinates":[-1.017661,51.465443],"type":"Point"}
}