{
  "type": "Feature",
  "properties": {
    "addr:full":"3-5 Spencer Street Ebbw Vale Blaenau Gwent NP23 6UJ",
    "addr:housenumber":"3-5",
    "addr:postcode":"np23 6uj",
    "addr:street":"Spencer Street",
    "iso:country":"GB",
    "sg:address":"3-5 Spencer Street",
    "sg:city":"Ebbw Vale",
    "sg:classifiers":[
        {
            "category":"Professional",
            "subcategory":"Printing & Photocopies",
            "type":"Services"
        }
    ],
    "sg:phone":"+44 1495 301338",
    "sg:postcode":"NP23 6UJ",
    "sg:province":"Blaenau Gwent",
    "sg:tags":[
        "printer"
    ],
    "wof:name":"Glasson Print Services",
    "wof:placetype":"venue"
},
  "geometry": {"coordinates":[-3.2070589066,51.7713890076],"type":"Point"}
}