{
  "type": "Feature",
  "properties": {
    "addr:full":"20 Clifton Road London Greater London N8 8JA",
    "addr:housenumber":"20",
    "addr:postcode":"n8 8ja",
    "addr:street":"Clifton Road",
    "iso:country":"GB",
    "sg:address":"20 Clifton Road",
    "sg:city":"London",
    "sg:classifiers":[
        {
            "category":"Professional",
            "subcategory":"Art Services",
            "type":"Services"
        }
    ],
    "sg:postcode":"N8 8JA",
    "sg:province":"Greater London",
    "sg:tags":[
        "graphic",
        "designer"
    ],
    "wof:name":"Bartlett Rice Associates",
    "wof:placetype":"venue"
},
  "geometry": {"coordinates":[-0.1296530068,51.5788116455],"type":"Point"}
}