{
  "type": "Feature",
  "properties": {
    "iso:country":"GB",
    "sg:address":"10 Beckbury Road, Weoley Castle",
    "sg:city":"Birmingham",
    "sg:classifiers":[
        {
            "category":"Retail",
            "subcategory":"Repair Shop",
            "type":"Services"
        }
    ],
    "sg:phone":"+44 121 426 3658",
    "sg:postcode":"B29 5HH",
    "sg:province":"West Midlands",
    "sg:tags":[
        "maintenance"
    ],
    "wof:name":"Hobson Builders",
    "wof:placetype":"venue"
},
  "geometry": {"coordinates":[-1.966836,52.440525],"type":"Point"}
}