{
  "type": "Feature",
  "properties": {
    "iso:country":"GB",
    "sg:address":"100 Wilderspool Causeway",
    "sg:city":"Warrington",
    "sg:classifiers":[
        {
            "category":"Professional",
            "subcategory":"Management & Consulting",
            "type":"Services"
        }
    ],
    "sg:phone":"+44 1925 455400",
    "sg:postcode":"WA4 6PU",
    "sg:province":"Cheshire",
    "sg:tags":[
        "marketing",
        "consultant"
    ],
    "wof:name":"Holiday Promotions UK Ltd",
    "wof:placetype":"venue"
},
  "geometry": {"coordinates":[-2.5909810066,53.3820343018],"type":"Point"}
}