{
  "type": "Feature",
  "properties": {
    "iso:country":"GB",
    "sg:address":"Central Garage, Otley Road, Killinghall",
    "sg:city":"Harrogate",
    "sg:classifiers":[
        {
            "category":"Autos & Motor Vehicles",
            "subcategory":"Automobile Sales",
            "type":"Retail Goods"
        }
    ],
    "sg:phone":"+44 1423 705005",
    "sg:postcode":"HG3 2DN",
    "sg:province":"North Yorkshire",
    "sg:tags":[
        "car"
    ],
    "wof:name":"John Gill Ltd.",
    "wof:placetype":"venue"
},
  "geometry": {"coordinates":[-1.5642559528,54.024055481],"type":"Point"}
}