{
  "type": "Feature",
  "properties": {
    "addr:full":"4 Crab Lane, Bradwell Great Yarmouth Norfolk NR31 8DJ",
    "addr:housenumber":"4",
    "addr:postcode":"nr31 8dj",
    "addr:street":"Crab Lane;Yarmouth",
    "iso:country":"GB",
    "sg:address":"4 Crab Lane, Bradwell",
    "sg:city":"Great Yarmouth",
    "sg:classifiers":[
        {
            "category":"Shopping",
            "subcategory":"News",
            "type":"Retail Goods"
        }
    ],
    "sg:phone":"+44 1493 661402",
    "sg:postcode":"NR31 8DJ",
    "sg:province":"Norfolk",
    "sg:tags":[
        "newsagent"
    ],
    "wof:name":"STOCKSON NEWSAGENT",
    "wof:placetype":"venue"
},
  "geometry": {"coordinates":[1.7067849636,52.5787124634],"type":"Point"}
}