{
  "type": "Feature",
  "properties": {
    "addr:full":"Weymouth Pavilion, The Esplanade Weymouth Dorset DT4 8ED",
    "addr:postcode":"dt4 8ed",
    "addr:street":"The Esplanade",
    "iso:country":"GB",
    "sg:address":"Weymouth Pavilion, The Esplanade",
    "sg:city":"Weymouth",
    "sg:classifiers":[
        {
            "category":"Professional",
            "subcategory":"Computer Services",
            "type":"Services"
        }
    ],
    "sg:postcode":"DT4 8ED",
    "sg:province":"Dorset",
    "sg:tags":[
        "information"
    ],
    "wof:name":"Weymouth & Portland Museum Service",
    "wof:placetype":"venue"
},
  "geometry": {"coordinates":[-2.4592061043,50.6099014282],"type":"Point"}
}