{
  "type": "Feature",
  "properties": {
    "addr:full":"64 Somerton Road Newport Newport NP19 0JE",
    "addr:housenumber":"64",
    "addr:postcode":"np19 0je",
    "addr:street":"Somerton Road",
    "iso:country":"GB",
    "sg:address":"64 Somerton Road",
    "sg:city":"Newport",
    "sg:classifiers":[
        {
            "category":"Food & Beverages",
            "subcategory":"Meat & Fish",
            "type":"Retail Goods"
        }
    ],
    "sg:phone":"+44 1633 275212",
    "sg:postcode":"NP19 0JE",
    "sg:province":"Newport",
    "sg:tags":[
        "chip"
    ],
    "wof:name":"K Seto Fish & Chip Shop",
    "wof:placetype":"venue"
},
  "geometry": {"coordinates":[-2.961748,51.581875],"type":"Point"}
}