{
  "type": "Feature",
  "properties": {
    "iso:country":"GB",
    "sg:address":"32 Middleton Road",
    "sg:city":"Salisbury",
    "sg:classifiers":[
        {
            "category":"Manufacturing",
            "subcategory":"Signs",
            "type":"Manufacturing & Wholesale Goods"
        }
    ],
    "sg:postcode":"SP2 7AY",
    "sg:province":"Wiltshire",
    "sg:tags":[
        "writer"
    ],
    "wof:name":"Smart Signs",
    "wof:placetype":"venue"
},
  "geometry": {"coordinates":[-1.8028130531,51.0743675232],"type":"Point"}
}