{
  "type": "Feature",
  "properties": {
    "addr:full":"19 Holme Leaze, Steeple Ashton Trowbridge Wiltshire BA14 6EH",
    "addr:housenumber":"19",
    "addr:postcode":"ba14 6eh",
    "addr:street":"Holme Leaze",
    "iso:country":"GB",
    "sg:address":"19 Holme Leaze, Steeple Ashton",
    "sg:city":"Trowbridge",
    "sg:classifiers":[
        {
            "category":"Organizations",
            "subcategory":"Non-profit Organization",
            "type":"Services"
        }
    ],
    "sg:phone":"+44 1380 870560",
    "sg:postcode":"BA14 6EH",
    "sg:province":"Wiltshire",
    "sg:tags":[
        "charitable",
        "organisation",
        "voluntary",
        "charity"
    ],
    "sg:website":"http://www.lrf.org.uk",
    "wof:name":"Leukaemia Research Fund",
    "wof:placetype":"venue"
},
  "geometry": {"coordinates":[-2.135014,51.310589],"type":"Point"}
}