{
  "type": "Feature",
  "properties": {
    "iso:country":"GB",
    "sg:address":"159 North Street",
    "sg:city":"Brighton",
    "sg:classifiers":[
        {
            "category":"Professional",
            "subcategory":"Employment Agencies",
            "type":"Services"
        }
    ],
    "sg:phone":"+44 1273 730006",
    "sg:postcode":"BN1 1EA",
    "sg:province":"East Sussex",
    "sg:tags":[
        "consultant"
    ],
    "wof:name":"The Network",
    "wof:placetype":"venue"
},
  "geometry": {"coordinates":[-0.140308,50.822994],"type":"Point"}
}