{
  "type": "Feature",
  "properties": {
    "iso:country":"GB",
    "sg:address":"Po Box 158",
    "sg:city":"Horley",
    "sg:classifiers":[
        {
            "category":"Communications",
            "type":"Services"
        }
    ],
    "sg:phone":"+44 1293 567747",
    "sg:postcode":"RH6 0YZ",
    "sg:province":"Surrey",
    "sg:tags":[
        "audio-visual"
    ],
    "wof:name":"Audio Visual Conference Technology",
    "wof:placetype":"venue"
},
  "geometry": {"coordinates":[-0.188379,51.160591],"type":"Point"}
}