{
  "type": "Feature",
  "properties": {
    "addr:full":"435 Cowbridge Road East, Victoria Park Cardiff Cardiff CF5 1JH",
    "addr:housenumber":"435",
    "addr:postcode":"cf5 1jh",
    "addr:street":"Cowbridge Road",
    "iso:country":"GB",
    "sg:address":"435 Cowbridge Road East, Victoria Park",
    "sg:city":"Cardiff",
    "sg:classifiers":[
        {
            "category":"Organizations",
            "subcategory":"Membership Organization",
            "type":"Services"
        }
    ],
    "sg:phone":"+44 29 2023 2296",
    "sg:postcode":"CF5 1JH",
    "sg:province":"Cardiff",
    "sg:tags":[
        "club"
    ],
    "wof:name":"The New Victoria Social Club",
    "wof:placetype":"venue"
},
  "geometry": {"coordinates":[-3.2112870216,51.4824676514],"type":"Point"}
}