{
  "type": "Feature",
  "properties": {
    "iso:country":"GB",
    "sg:address":"111 Broad Oaks Rd",
    "sg:city":"Solihull",
    "sg:classifiers":[
        {
            "category":"Building & Trades",
            "subcategory":"Construction",
            "type":"Services"
        }
    ],
    "sg:phone":"+44 121 704 0041",
    "sg:postcode":"B91 1HY",
    "sg:province":"West Midlands",
    "sg:tags":[
        "decorator",
        "painter"
    ],
    "wof:name":"Malone Painting & Decorating",
    "wof:placetype":"venue"
},
  "geometry": {"coordinates":[-1.7918909788,52.4183502197],"type":"Point"}
}