{
  "type": "Feature",
  "properties": {
    "addr:full":"Claylands Head Butterworth Hall, Water Lane, Butterworth Hall Rochdale Lancashire OL16 3TL",
    "addr:postcode":"lancashire ol16 3tl",
    "addr:street":"Claylands;Water Lane",
    "iso:country":"GB",
    "sg:address":"Claylands Head Butterworth Hall, Water Lane, Butterworth Hall",
    "sg:city":"Rochdale",
    "sg:classifiers":[
        {
            "category":"Building & Trades",
            "subcategory":"Construction",
            "type":"Services"
        }
    ],
    "sg:postcode":"OL16 3TL",
    "sg:province":"Lancashire",
    "sg:tags":[
        "platform",
        "work",
        "scaffolding"
    ],
    "wof:name":"Noslen Access Co",
    "wof:placetype":"venue"
},
  "geometry": {"coordinates":[-2.0966999531,53.6090087891],"type":"Point"}
}