{
  "type": "Feature",
  "properties": {
    "iso:country":"GB",
    "sg:address":"2 High Street",
    "sg:city":"Taunton",
    "sg:classifiers":[
        {
            "category":"Retail",
            "subcategory":"Photofinishing",
            "type":"Services"
        }
    ],
    "sg:phone":"+44 1823 352211",
    "sg:postcode":"TA1 3PG",
    "sg:province":"Somerset",
    "sg:tags":[
        "photographic",
        "processor"
    ],
    "wof:name":"Taunton Photo Express",
    "wof:placetype":"venue"
},
  "geometry": {"coordinates":[-3.1032390594,51.0141029358],"type":"Point"}
}