{
  "type": "Feature",
  "properties": {
    "addr:full":"Welllington Medical Centre Wellington Devon TA21 8PW",
    "addr:postcode":"ta21 8pw",
    "addr:street":"Wellington",
    "iso:country":"GB",
    "sg:address":"Welllington Medical Centre",
    "sg:city":"Wellington",
    "sg:classifiers":[
        {
            "category":"Professional",
            "subcategory":"Lawyer & Legal Services",
            "type":"Services"
        }
    ],
    "sg:phone":"+44 1823 666346",
    "sg:postcode":"TA21 8PW",
    "sg:province":"Devon",
    "sg:tags":[
        "advice",
        "counselling"
    ],
    "wof:name":"Jan Setterington Carer Support Worker",
    "wof:placetype":"venue"
},
  "geometry": {"coordinates":[-3.226639,50.979271],"type":"Point"}
}