{
  "type": "Feature",
  "properties": {
    "addr:full":"37 St Michaels Avenue, Bramhall Stockport Cheshire SK7 2PW",
    "addr:housenumber":"37",
    "addr:postcode":"sk7 2pw",
    "addr:street":"St Michaels Avenue",
    "iso:country":"GB",
    "sg:address":"37 St Michaels Avenue, Bramhall",
    "sg:city":"Stockport",
    "sg:classifiers":[
        {
            "category":"Manufacturing",
            "subcategory":"Textiles",
            "type":"Manufacturing & Wholesale Goods"
        }
    ],
    "sg:postcode":"SK7 2PW",
    "sg:province":"Cheshire",
    "sg:tags":[
        "knitwear"
    ],
    "wof:name":"James Rickwood & Co. Ltd.",
    "wof:placetype":"venue"
},
  "geometry": {"coordinates":[-2.1636810303,53.3676376343],"type":"Point"}
}