{
  "type": "Feature",
  "properties": {
    "addr:full":"Grange Of Bladnoch, Kirkcowan Newton Stewart Dumfries and Galloway DG8 0BY",
    "addr:postcode":"dg8 0by",
    "addr:street":"Stewart",
    "iso:country":"GB",
    "sg:address":"Grange Of Bladnoch, Kirkcowan",
    "sg:city":"Newton Stewart",
    "sg:classifiers":[
        {
            "category":"Farming",
            "subcategory":"Livestock Farm",
            "type":"Manufacturing & Wholesale Goods"
        },
        {
            "category":"Farming",
            "subcategory":"Farm",
            "type":"Manufacturing & Wholesale Goods"
        }
    ],
    "sg:postcode":"DG8 0BY",
    "sg:province":"Dumfries and Galloway",
    "sg:tags":[
        "mixed",
        "crop",
        "others"
    ],
    "wof:name":"A M Adams & Co",
    "wof:placetype":"venue"
},
  "geometry": {"coordinates":[-4.6083607674,54.9165992737],"type":"Point"}
}