{
  "type": "Feature",
  "properties": {
    "iso:country":"GB",
    "sg:address":"Camp Road Garage",
    "sg:city":"Grange-over-sands",
    "sg:classifiers":[
        {
            "category":"Retail",
            "subcategory":"Auto Repair",
            "type":"Services"
        }
    ],
    "sg:phone":"+44 15395 58254",
    "sg:postcode":"LA11 7LS",
    "sg:province":"Cumbria",
    "sg:tags":[
        "modification",
        "garage"
    ],
    "wof:name":"Camp Rd Garage",
    "wof:placetype":"venue"
},
  "geometry": {"coordinates":[-2.9216399193,54.1841583252],"type":"Point"}
}