{
  "type": "Feature",
  "properties": {
    "iso:country":"GB",
    "sg:address":"9 Furland Rd",
    "sg:city":"Crewkerne",
    "sg:classifiers":[
        {
            "category":"Military Area",
            "subcategory":"Air Force Base",
            "type":"Public Place"
        }
    ],
    "sg:phone":"+44 1460 78127",
    "sg:postcode":"TA18 8DE",
    "sg:province":"Dorset",
    "sg:tags":[
        "taxi",
        "hire",
        "private"
    ],
    "wof:name":"Brian's Taxis",
    "wof:placetype":"venue"
},
  "geometry": {"coordinates":[-2.795178,50.879986],"type":"Point"}
}