{
  "type": "Feature",
  "properties": {
    "addr:full":"1 Court Road Bridgend Bridgend CF31 1BE",
    "addr:housenumber":"1",
    "addr:postcode":"cf31 1be",
    "addr:street":"Court Road",
    "iso:country":"GB",
    "sg:address":"1 Court Road",
    "sg:city":"Bridgend",
    "sg:classifiers":[
        {
            "category":"Professional",
            "subcategory":"Business Services",
            "type":"Services"
        }
    ],
    "sg:phone":"+44 1656 648494",
    "sg:postcode":"CF31 1BE",
    "sg:province":"Bridgend",
    "sg:tags":[
        "trade"
    ],
    "wof:name":"S G S United Kingdom Ltd.",
    "wof:placetype":"venue"
},
  "geometry": {"coordinates":[-3.5766088963,51.5061569214],"type":"Point"}
}