{
  "type": "Feature",
  "properties": {
    "iso:country":"GB",
    "sg:address":"Carrant Brook Farm, Cheltenham Road, Ashton-under-hill",
    "sg:city":"Evesham",
    "sg:classifiers":[
        {
            "category":"Freight",
            "type":"Transportation"
        }
    ],
    "sg:phone":"+44 1386 881102",
    "sg:postcode":"WR11 7QT",
    "sg:province":"Gloucestershire",
    "sg:tags":[
        "haulage",
        "road"
    ],
    "wof:name":"Evale Services",
    "wof:placetype":"venue"
},
  "geometry": {"coordinates":[-2.005305,52.042847],"type":"Point"}
}