{
  "type": "Feature",
  "properties": {
    "addr:full":"61 St Dunstans Street Canterbury Kent CT2 8BS",
    "addr:housenumber":"61",
    "addr:postcode":"ct2 8bs",
    "addr:street":"St Dunstans Street",
    "iso:country":"GB",
    "sg:address":"61 St Dunstans Street",
    "sg:city":"Canterbury",
    "sg:classifiers":[
        {
            "category":"Bars & Pubs",
            "type":"Food & Drink"
        }
    ],
    "sg:phone":"+44 1227 463187",
    "sg:postcode":"CT2 8BS",
    "sg:province":"Kent",
    "sg:tags":[
        "pubs",
        "inn"
    ],
    "wof:name":"The Unicorn Inn",
    "wof:placetype":"venue"
},
  "geometry": {"coordinates":[1.0744199753,51.2821311951],"type":"Point"}
}