{
  "type": "Feature",
  "properties": {
    "iso:country":"GB",
    "sg:address":"17 Leys Ave",
    "sg:city":"Letchworth",
    "sg:classifiers":[
        {
            "category":"Home & Garden",
            "subcategory":"Furniture",
            "type":"Retail Goods"
        }
    ],
    "sg:postcode":"SG6 3EA",
    "sg:province":"Hertfordshire",
    "wof:name":"Harveys Furnishing Group Ltd",
    "wof:placetype":"venue"
},
  "geometry": {"coordinates":[-0.226873,51.978973],"type":"Point"}
}