{
  "type": "Feature",
  "properties": {
    "addr:full":"6 Benfleet Road Benfleet Essex SS7 1QB",
    "addr:housenumber":"6",
    "addr:postcode":"ss7 1qb",
    "addr:street":"Benfleet Road",
    "iso:country":"GB",
    "sg:address":"6 Benfleet Road",
    "sg:city":"Benfleet",
    "sg:classifiers":[
        {
            "category":"Shopping",
            "subcategory":"Florist",
            "type":"Retail Goods"
        }
    ],
    "sg:postcode":"SS7 1QB",
    "sg:province":"Essex",
    "wof:name":"Petite Fleur",
    "wof:placetype":"venue"
},
  "geometry": {"coordinates":[0.599468,51.557224],"type":"Point"}
}