{
  "type": "Feature",
  "properties": {
    "iso:country":"GB",
    "sg:address":"Vale Chambers, 462 Didsbury Road, Heaton Mersey",
    "sg:city":"Stockport",
    "sg:classifiers":[
        {
            "category":"Real Estate",
            "subcategory":"Architect",
            "type":"Services"
        }
    ],
    "sg:phone":"+44 161 432 2605",
    "sg:postcode":"SK4 3BS",
    "sg:province":"Cheshire",
    "wof:name":"Wilkinson Cowan Partnership",
    "wof:placetype":"venue"
},
  "geometry": {"coordinates":[-2.2002921104,53.4132347107],"type":"Point"}
}