{
  "type": "Feature",
  "properties": {
    "addr:full":"71 Holland Road Hove East Sussex BN3 1JN",
    "addr:housenumber":"71",
    "addr:postcode":"bn3 1jn",
    "addr:street":"Holland Road",
    "iso:country":"GB",
    "sg:address":"71 Holland Road",
    "sg:city":"Hove",
    "sg:classifiers":[
        {
            "category":"Place Of Worship",
            "type":"Public Place"
        }
    ],
    "sg:phone":"+44 1273 732111",
    "sg:postcode":"BN3 1JN",
    "sg:province":"East Sussex",
    "wof:name":"Holland Road baptist Church",
    "wof:placetype":"venue"
},
  "geometry": {"coordinates":[-0.161282,50.827419],"type":"Point"}
}