{
  "type": "Feature",
  "properties": {
    "addr:full":"11 & 12 Links Business Cntr, Raynham Road Bishops Stortford Essex CM23 5NZ",
    "addr:housenumber":"11 & 12 links",
    "addr:postcode":"cm23 5nz",
    "addr:street":"Business Cntr Raynham Road",
    "iso:country":"GB",
    "sg:address":"11 & 12 Links Business Cntr, Raynham Road",
    "sg:city":"Bishops Stortford",
    "sg:classifiers":[
        {
            "category":"Sports & Exercise",
            "subcategory":"Race Track",
            "type":"Entertainment"
        }
    ],
    "sg:phone":"+44 1279 755543",
    "sg:postcode":"CM23 5NZ",
    "sg:province":"Essex",
    "sg:tags":[
        "motor"
    ],
    "wof:name":"Solus Racing Engines Ltd.",
    "wof:placetype":"venue"
},
  "geometry": {"coordinates":[0.1700100005,51.8652801514],"type":"Point"}
}