{
  "type": "Feature",
  "properties": {
    "iso:country":"GB",
    "sg:address":"20 East St",
    "sg:city":"Tonbridge",
    "sg:classifiers":[
        {
            "category":"Professional",
            "subcategory":"Computer Services",
            "type":"Services"
        }
    ],
    "sg:phone":"+44 1732 369988",
    "sg:postcode":"TN9 1HA",
    "sg:province":"Kent",
    "sg:tags":[
        "system",
        "software"
    ],
    "wof:name":"System Development",
    "wof:placetype":"venue"
},
  "geometry": {"coordinates":[0.27885,51.197552],"type":"Point"}
}