{
  "type": "Feature",
  "properties": {
    "addr:full":"64 Overslade La Rugby Warwickshire CV22 6EF",
    "addr:housenumber":"64",
    "addr:postcode":"cv22 6ef",
    "addr:street":"Overslade La",
    "iso:country":"GB",
    "sg:address":"64 Overslade La",
    "sg:city":"Rugby",
    "sg:classifiers":[
        {
            "category":"Building & Trades",
            "subcategory":"Construction",
            "type":"Services"
        }
    ],
    "sg:phone":"+44 1788 334736",
    "sg:postcode":"CV22 6EF",
    "sg:province":"Warwickshire",
    "sg:tags":[
        "contractor",
        "paving",
        "driveway"
    ],
    "wof:name":"G. Pettifer Block Paving Specialist",
    "wof:placetype":"venue"
},
  "geometry": {"coordinates":[-1.281818,52.357071],"type":"Point"}
}