{
  "type": "Feature",
  "properties": {
    "iso:country":"GB",
    "sg:address":"Churchward Court, 15 Western Rd",
    "sg:city":"Lewes",
    "sg:classifiers":[
        {
            "category":"Professional",
            "subcategory":"Management & Consulting",
            "type":"Services"
        }
    ],
    "sg:postcode":"BN7 1RL",
    "sg:province":"East Sussex",
    "sg:tags":[
        "consultant",
        "business"
    ],
    "wof:name":"Hunter,Richard,",
    "wof:placetype":"venue"
},
  "geometry": {"coordinates":[0.001762,50.8726463318],"type":"Point"}
}