{
  "type": "Feature",
  "properties": {
    "addr:full":"214 Church Street Blackpool Lancashire FY1 3PT",
    "addr:housenumber":"214",
    "addr:postcode":"fy1 3pt",
    "addr:street":"Church Street",
    "iso:country":"GB",
    "sg:address":"214 Church Street",
    "sg:city":"Blackpool",
    "sg:classifiers":[
        {
            "category":"Building & Trades",
            "subcategory":"Cleaning & Sanitation",
            "type":"Services"
        }
    ],
    "sg:phone":"+44 1253 297397",
    "sg:postcode":"FY1 3PT",
    "sg:province":"Lancashire",
    "sg:tags":[
        "dry",
        "control",
        "damp",
        "rot"
    ],
    "wof:name":"P H Building & Roofing Ltd.",
    "wof:placetype":"venue"
},
  "geometry": {"coordinates":[-3.045382,53.81834],"type":"Point"}
}