{
  "type": "Feature",
  "properties": {
    "addr:full":"Bethesda St, Hanley Stoke On Trent Staffordshire ST1 3BP",
    "addr:postcode":"st1 3bp",
    "addr:street":"St",
    "iso:country":"GB",
    "sg:address":"Bethesda St, Hanley",
    "sg:city":"Stoke On Trent",
    "sg:classifiers":[
        {
            "category":"Government",
            "subcategory":"Court House",
            "type":"Public Place"
        }
    ],
    "sg:phone":"+44 1782 854065",
    "sg:postcode":"ST1 3BP",
    "sg:province":"Staffordshire",
    "wof:name":"Probate Court",
    "wof:placetype":"venue"
},
  "geometry": {"coordinates":[-2.176586,53.022152],"type":"Point"}
}