{
  "type": "Feature",
  "properties": {
    "iso:country":"GB",
    "sg:address":"41 Inchmuir Road, Whitehill Industrial Estate",
    "sg:city":"Bathgate",
    "sg:classifiers":[
        {
            "category":"Professional",
            "subcategory":"Business Services",
            "type":"Services"
        }
    ],
    "sg:phone":"+44 1506 634634",
    "sg:postcode":"EH48 2EP",
    "sg:province":"West Lothian",
    "sg:tags":[
        "distribution"
    ],
    "wof:name":"M R S (Distribution) Ltd.",
    "wof:placetype":"venue"
},
  "geometry": {"coordinates":[-3.628472,55.885345],"type":"Point"}
}