{
  "type": "Feature",
  "properties": {
    "iso:country":"GB",
    "sg:address":"25c The Bridges",
    "sg:city":"Sunderland",
    "sg:classifiers":[
        {
            "category":"Travel",
            "subcategory":"Travel Agent",
            "type":"Entertainment"
        }
    ],
    "sg:postcode":"SR1 3LB",
    "sg:province":"Tyne and Wear",
    "wof:name":"Thomas Cook",
    "wof:placetype":"venue"
},
  "geometry": {"coordinates":[-1.388749,54.904652],"type":"Point"}
}