{
  "type": "Feature",
  "properties": {
    "iso:country":"GB",
    "sg:address":"44 Carter Street",
    "sg:city":"Uttoxeter",
    "sg:classifiers":[
        {
            "category":"Organizations",
            "subcategory":"Non-profit Organization",
            "type":"Services"
        }
    ],
    "sg:phone":"+44 1889 568440",
    "sg:postcode":"ST14 8EU",
    "sg:province":"Derbyshire",
    "sg:tags":[
        "organisation",
        "voluntary",
        "charity"
    ],
    "wof:name":"Uttoxeter Mind",
    "wof:placetype":"venue"
},
  "geometry": {"coordinates":[-1.8676650524,52.8975067139],"type":"Point"}
}