{
  "type": "Feature",
  "properties": {
    "addr:full":"Holmes Chapel Road, Holmes Chapel Crewe Cheshire CW4 8AS",
    "addr:postcode":"cw4 8as",
    "addr:street":"Holmes Chapel Road",
    "iso:country":"GB",
    "sg:address":"Holmes Chapel Road, Holmes Chapel",
    "sg:city":"Crewe",
    "sg:classifiers":[
        {
            "category":"Farming",
            "subcategory":"Livestock Farm",
            "type":"Manufacturing & Wholesale Goods"
        }
    ],
    "sg:postcode":"CW4 8AS",
    "sg:province":"Cheshire",
    "sg:tags":[
        "others"
    ],
    "wof:name":"D M Beresford & Partners",
    "wof:placetype":"venue"
},
  "geometry": {"coordinates":[-2.3285639286,53.1924209595],"type":"Point"}
}