{
  "type": "Feature",
  "properties": {
    "iso:country":"GB",
    "sg:address":"Kingshill Farm, Kingshill, Old Warden",
    "sg:city":"Biggleswade",
    "sg:classifiers":[
        {
            "category":"Farming",
            "subcategory":"Livestock Farm",
            "type":"Manufacturing & Wholesale Goods"
        }
    ],
    "sg:phone":"+44 1767 316273",
    "sg:postcode":"SG18 9DS",
    "sg:province":"Bedfordshire",
    "sg:tags":[
        "others"
    ],
    "wof:name":"R L Capon",
    "wof:placetype":"venue"
},
  "geometry": {"coordinates":[-0.3459700048,52.0790138245],"type":"Point"}
}