{
  "type": "Feature",
  "properties": {
    "iso:country":"GB",
    "sg:address":"Maldon Road, Great Wigborough",
    "sg:city":"Colchester",
    "sg:classifiers":[
        {
            "category":"Farming",
            "subcategory":"Farm",
            "type":"Manufacturing & Wholesale Goods"
        }
    ],
    "sg:phone":"+44 1621 860273",
    "sg:postcode":"CO5 7RU",
    "sg:province":"Essex",
    "sg:tags":[
        "mixed",
        "crop"
    ],
    "wof:name":"C C ROOTS & SONS",
    "wof:placetype":"venue"
},
  "geometry": {"coordinates":[0.8532969952,51.7990722656],"type":"Point"}
}