{
  "type": "Feature",
  "properties": {
    "iso:country":"GB",
    "sg:address":"321 Holburn Street",
    "sg:city":"Aberdeen",
    "sg:classifiers":[
        {
            "category":"Home & Garden",
            "subcategory":"Carpets & Floor Coverings",
            "type":"Retail Goods"
        }
    ],
    "sg:phone":"+44 1224 210108",
    "sg:postcode":"AB10 7FP",
    "sg:province":"Aberdeen City",
    "sg:tags":[
        "carpets",
        "retailer",
        "rug",
        "matting"
    ],
    "wof:name":"Cosy Carpets Of Holburn",
    "wof:placetype":"venue"
},
  "geometry": {"coordinates":[-2.117149,57.130032],"type":"Point"}
}