{
  "type": "Feature",
  "properties": {
    "addr:full":"3 Norton Rd Chelmsford Essex CM1 2QP",
    "addr:housenumber":"3",
    "addr:postcode":"cm1 2qp",
    "addr:street":"Norton Rd",
    "iso:country":"GB",
    "sg:address":"3 Norton Rd",
    "sg:city":"Chelmsford",
    "sg:classifiers":[
        {
            "category":"Building & Trades",
            "subcategory":"Construction",
            "type":"Services"
        }
    ],
    "sg:phone":"+44 1245 257179",
    "sg:postcode":"CM1 2QP",
    "sg:province":"Essex",
    "sg:tags":[
        "builder"
    ],
    "wof:name":"Hodson & Southgate",
    "wof:placetype":"venue"
},
  "geometry": {"coordinates":[0.4620809853,51.7366676331],"type":"Point"}
}