{
  "type": "Feature",
  "properties": {
    "iso:country":"GB",
    "sg:address":"Lime Grove, Cherry Willingham",
    "sg:city":"Lincoln",
    "sg:classifiers":[
        {
            "category":"Education",
            "subcategory":"School",
            "type":"Public Place"
        },
        {
            "category":"Government",
            "subcategory":"Office",
            "type":"Public Place"
        }
    ],
    "sg:phone":"+44 1522 751148",
    "sg:postcode":"LN3 4BD",
    "sg:province":"Lincolnshire",
    "sg:tags":[
        "local",
        "authority"
    ],
    "wof:name":"Cherry Willingham County Primary School",
    "wof:placetype":"venue"
},
  "geometry": {"coordinates":[-0.46187,53.23774],"type":"Point"}
}