{
  "type": "Feature",
  "properties": {
    "iso:country":"GB",
    "sg:address":"6 Bancroft Road, Hale",
    "sg:city":"Altrincham",
    "sg:classifiers":[
        {
            "category":"Communications",
            "subcategory":"Film & Video Production",
            "type":"Services"
        }
    ],
    "sg:phone":"+44 161 904 8100",
    "sg:postcode":"WA15 8BG",
    "sg:province":"Cheshire",
    "sg:tags":[
        "pr",
        "telemarketing"
    ],
    "wof:name":"Telemark Appointments Ltd.",
    "wof:placetype":"venue"
},
  "geometry": {"coordinates":[-2.3314189911,53.3802108765],"type":"Point"}
}