{
  "type": "Feature",
  "properties": {
    "addr:full":"4 Latham Road Coventry West Midlands CV5 6HR",
    "addr:housenumber":"4",
    "addr:postcode":"cv5 6hr",
    "addr:street":"Latham Road",
    "iso:country":"GB",
    "sg:address":"4 Latham Road",
    "sg:city":"Coventry",
    "sg:classifiers":[
        {
            "category":"Building & Trades",
            "subcategory":"Plumbing",
            "type":"Services"
        },
        {
            "category":"Building & Trades",
            "subcategory":"Construction",
            "type":"Services"
        }
    ],
    "sg:phone":"+44 24 7671 2798",
    "sg:postcode":"CV5 6HR",
    "sg:province":"West Midlands",
    "sg:tags":[
        "central",
        "installation",
        "system",
        "servicing",
        "heating"
    ],
    "wof:name":"Phillip Howells",
    "wof:placetype":"venue"
},
  "geometry": {"coordinates":[-1.529693,52.407421],"type":"Point"}
}