{
  "type": "Feature",
  "properties": {
    "addr:full":"Colliery Yard, Jethro Street Bolton Lancashire BL2 2PT",
    "addr:postcode":"bl2 2pt",
    "addr:street":"Colliery;Jethro Street",
    "iso:country":"GB",
    "sg:address":"Colliery Yard, Jethro Street",
    "sg:city":"Bolton",
    "sg:classifiers":[
        {
            "category":"Wholesale",
            "subcategory":"Scrap",
            "type":"Manufacturing & Wholesale Goods"
        }
    ],
    "sg:phone":"+44 1204 525230",
    "sg:postcode":"BL2 2PT",
    "sg:province":"Lancashire",
    "sg:tags":[
        "car",
        "breaker",
        "dismantlers"
    ],
    "wof:name":"Track-a-part",
    "wof:placetype":"venue"
},
  "geometry": {"coordinates":[-2.4082400799,53.5818405151],"type":"Point"}
}