{
  "type": "Feature",
  "properties": {
    "addr:full":"41 St Michaels Avenue, Gedling Nottingham Nottinghamshire NG4 3NN",
    "addr:housenumber":"41",
    "addr:postcode":"ng4 3nn",
    "addr:street":"St Michaels Avenue",
    "iso:country":"GB",
    "sg:address":"41 St Michaels Avenue, Gedling",
    "sg:city":"Nottingham",
    "sg:classifiers":[
        {
            "category":"Professional",
            "type":"Services"
        }
    ],
    "sg:postcode":"NG4 3NN",
    "sg:province":"Nottinghamshire",
    "sg:tags":[
        "caterer"
    ],
    "wof:name":"Gedling Caterers",
    "wof:placetype":"venue"
},
  "geometry": {"coordinates":[-1.0874849558,52.9764595032],"type":"Point"}
}