{
  "type": "Feature",
  "properties": {
    "addr:full":"127 City Road Cardiff Cardiff CF24 3BP",
    "addr:housenumber":"127",
    "addr:postcode":"cf24 3bp",
    "addr:street":"City Road",
    "iso:country":"GB",
    "sg:address":"127 City Road",
    "sg:city":"Cardiff",
    "sg:classifiers":[
        {
            "category":"Fast Food",
            "type":"Food & Drink"
        }
    ],
    "sg:phone":"+44 29 2045 1411",
    "sg:postcode":"CF24 3BP",
    "sg:province":"Cardiff",
    "sg:tags":[
        "away",
        "take"
    ],
    "wof:name":"Golden Ricksaw",
    "wof:placetype":"venue"
},
  "geometry": {"coordinates":[-3.1689751148,51.4893913269],"type":"Point"}
}