{
  "type": "Feature",
  "properties": {
    "addr:full":"The Acorn Centre, Chestnut Avenue Biggleswade Bedfordshire SG18 0RA",
    "addr:postcode":"sg18 0ra",
    "addr:street":"Chestnut Avenue",
    "iso:country":"GB",
    "sg:address":"The Acorn Centre, Chestnut Avenue",
    "sg:city":"Biggleswade",
    "sg:classifiers":[
        {
            "category":"Communications",
            "type":"Services"
        }
    ],
    "sg:phone":"+44 1767 600090",
    "sg:postcode":"SG18 0RA",
    "sg:province":"Bedfordshire",
    "sg:tags":[
        "data",
        "network"
    ],
    "wof:name":"GPData Ltd",
    "wof:placetype":"venue"
},
  "geometry": {"coordinates":[-0.261729002,52.0869750977],"type":"Point"}
}