{
  "type": "Feature",
  "properties": {
    "addr:full":"Dargets Road Chatham Kent ME5 8BJ",
    "addr:postcode":"me5 8bj",
    "addr:street":"Dargets Road",
    "iso:country":"GB",
    "sg:address":"Dargets Road",
    "sg:city":"Chatham",
    "sg:classifiers":[
        {
            "category":"Education",
            "subcategory":"School",
            "type":"Public Place"
        }
    ],
    "sg:phone":"+44 1634 861660",
    "sg:postcode":"ME5 8BJ",
    "sg:province":"Kent",
    "sg:tags":[
        "local",
        "authority"
    ],
    "wof:name":"Walderslade County Primary School",
    "wof:placetype":"venue"
},
  "geometry": {"coordinates":[0.5318800211,51.3393135071],"type":"Point"}
}