{
  "type": "Feature",
  "properties": {
    "addr:full":"Bootham Crescent York North Yorkshire YO30 7AH",
    "addr:postcode":"yo30 7ah",
    "addr:street":"Bootham Crescent",
    "iso:country":"GB",
    "sg:address":"Bootham Crescent",
    "sg:city":"York",
    "sg:classifiers":[
        {
            "category":"Arena",
            "subcategory":"Sports Club",
            "type":"Entertainment"
        }
    ],
    "sg:phone":"+44 1904 624447",
    "sg:postcode":"YO30 7AH",
    "sg:province":"North Yorkshire",
    "wof:name":"York City Football & Athletic Club",
    "wof:placetype":"venue"
},
  "geometry": {"coordinates":[-1.0880800486,53.9693908691],"type":"Point"}
}