{
  "type": "Feature",
  "properties": {
    "addr:full":"35 Britten Close, Ash Aldershot Hampshire GU12 6LS",
    "addr:housenumber":"35",
    "addr:postcode":"gu12 6ls",
    "addr:street":"Britten Close",
    "iso:country":"GB",
    "sg:address":"35 Britten Close, Ash",
    "sg:city":"Aldershot",
    "sg:classifiers":[
        {
            "category":"Professional",
            "subcategory":"Computer Services",
            "type":"Services"
        }
    ],
    "sg:postcode":"GU12 6LS",
    "sg:province":"Hampshire",
    "sg:tags":[
        "system",
        "software"
    ],
    "wof:name":"Nibble-It Ltd",
    "wof:placetype":"venue"
},
  "geometry": {"coordinates":[-0.713565,51.249252],"type":"Point"}
}