{
  "type": "Feature",
  "properties": {
    "addr:full":"Shardlow Business Park, London Road, Shardlow Derby Derbyshire DE72 2GD",
    "addr:postcode":"de72 2gd",
    "addr:street":"Park London Road",
    "iso:country":"GB",
    "sg:address":"Shardlow Business Park, London Road, Shardlow",
    "sg:city":"Derby",
    "sg:classifiers":[
        {
            "category":"Professional",
            "subcategory":"Management & Consulting",
            "type":"Services"
        },
        {
            "category":"Manufacturing",
            "subcategory":"Food",
            "type":"Manufacturing & Wholesale Goods"
        }
    ],
    "sg:phone":"+44 1332 793000",
    "sg:postcode":"DE72 2GD",
    "sg:province":"Derbyshire",
    "sg:tags":[
        "consultant",
        "technologist",
        "business"
    ],
    "wof:name":"I L S LTD",
    "wof:placetype":"venue"
},
  "geometry": {"coordinates":[-1.3557640314,52.8694267273],"type":"Point"}
}