{
  "type": "Feature",
  "properties": {
    "addr:full":"1 Hill Street Dunfermline Fife KY12 0QR",
    "addr:housenumber":"1",
    "addr:postcode":"ky12 0qr",
    "addr:street":"Hill Street",
    "iso:country":"GB",
    "sg:address":"1 Hill Street",
    "sg:city":"Dunfermline",
    "sg:classifiers":[
        {
            "category":"Health Services",
            "subcategory":"Nursing And Care Facility",
            "type":"Services"
        },
        {
            "category":"Organizations",
            "subcategory":"Community Association",
            "type":"Services"
        }
    ],
    "sg:phone":"+44 1383 730182",
    "sg:postcode":"KY12 0QR",
    "sg:province":"Fife",
    "sg:tags":[
        "residential",
        "housing",
        "society"
    ],
    "wof:name":"ARK HOUSING ASSOCIATION LTD",
    "wof:placetype":"venue"
},
  "geometry": {"coordinates":[-3.4563660622,56.0757217407],"type":"Point"}
}