{
  "type": "Feature",
  "properties": {
    "addr:full":"22 Lombard Street West Bromwich West Midlands B70 8RT",
    "addr:housenumber":"22",
    "addr:postcode":"b70 8rt",
    "addr:street":"Lombard Street",
    "iso:country":"GB",
    "sg:address":"22 Lombard Street",
    "sg:city":"West Bromwich",
    "sg:classifiers":[
        {
            "category":"Government",
            "subcategory":"Office",
            "type":"Public Place"
        }
    ],
    "sg:postcode":"B70 8RT",
    "sg:province":"West Midlands",
    "sg:tags":[
        "development",
        "agency"
    ],
    "wof:name":"Sandwell Credit Union Development Agency Ltd.",
    "wof:placetype":"venue"
},
  "geometry": {"coordinates":[-1.9954260588,52.5213165283],"type":"Point"}
}