{
  "type": "Feature",
  "properties": {
    "addr:full":"131 St. Saviours Rd, Coley Pk Reading Berkshire RG1 6EP",
    "addr:housenumber":"131",
    "addr:postcode":"rg1 6ep",
    "addr:street":"St. Saviours Rd;Pk",
    "iso:country":"GB",
    "sg:address":"131 St. Saviours Rd, Coley Pk",
    "sg:city":"Reading",
    "sg:classifiers":[
        {
            "category":"Building & Trades",
            "subcategory":"Construction",
            "type":"Services"
        }
    ],
    "sg:phone":"+44 118 961 2190",
    "sg:postcode":"RG1 6EP",
    "sg:province":"Berkshire",
    "sg:tags":[
        "builder"
    ],
    "wof:name":"J S J King Ltd",
    "wof:placetype":"venue"
},
  "geometry": {"coordinates":[-0.9781590104,51.4471282959],"type":"Point"}
}