{
  "type": "Feature",
  "properties": {
    "addr:full":"1 Brunswick Grove Cobham Surrey KT11 1HP",
    "addr:housenumber":"1",
    "addr:postcode":"kt11 1hp",
    "addr:street":"Brunswick Grove",
    "iso:country":"GB",
    "sg:address":"1 Brunswick Grove",
    "sg:city":"Cobham",
    "sg:classifiers":[
        {
            "category":"Education",
            "subcategory":"Music School",
            "type":"Public Place"
        }
    ],
    "sg:phone":"+44 1932 862233",
    "sg:postcode":"KT11 1HP",
    "sg:province":"Surrey",
    "sg:tags":[
        "conservatory"
    ],
    "wof:name":"Oakleigh Conservatories",
    "wof:placetype":"venue"
},
  "geometry": {"coordinates":[-0.404961,51.337116],"type":"Point"}
}