{
  "type": "Feature",
  "properties": {
    "addr:full":"17-19 Commercial Way Woking Surrey GU21 6XR",
    "addr:housenumber":"17-19",
    "addr:postcode":"gu21 6xr",
    "addr:street":"Commercial Way",
    "iso:country":"GB",
    "sg:address":"17-19 Commercial Way",
    "sg:city":"Woking",
    "sg:classifiers":[
        {
            "category":"Education",
            "subcategory":"Music School",
            "type":"Public Place"
        },
        {
            "category":"Home & Garden",
            "subcategory":"Home Furnishings",
            "type":"Retail Goods"
        },
        {
            "category":"Home & Garden",
            "subcategory":"Building Materials",
            "type":"Retail Goods"
        }
    ],
    "sg:phone":"+44 1483 740518",
    "sg:postcode":"GU21 6XR",
    "sg:province":"Surrey",
    "sg:tags":[
        "conservatory",
        "bathroom",
        "planner",
        "kitchen",
        "furnishers"
    ],
    "wof:name":"Portland Conservatories",
    "wof:placetype":"venue"
},
  "geometry": {"coordinates":[-0.556977,51.319695],"type":"Point"}
}