{
  "type": "Feature",
  "properties": {
    "addr:full":"4 Havelock St Blyth Northumberland NE24 1AB",
    "addr:housenumber":"4",
    "addr:postcode":"ne24 1ab",
    "addr:street":"Havelock St;Northumberland",
    "iso:country":"GB",
    "sg:address":"4 Havelock St",
    "sg:city":"Blyth",
    "sg:classifiers":[
        {
            "category":"Shopping",
            "subcategory":"Clothing, Apparel, & Fashions",
            "type":"Retail Goods"
        }
    ],
    "sg:phone":"+44 1670 365242",
    "sg:postcode":"NE24 1AB",
    "sg:province":"Northumberland",
    "sg:tags":[
        "shop"
    ],
    "wof:name":"Seconds Ahead",
    "wof:placetype":"venue"
},
  "geometry": {"coordinates":[-1.5088980198,55.1269683838],"type":"Point"}
}