{
  "type": "Feature",
  "properties": {
    "iso:country":"GB",
    "sg:address":"219 Cricklewood Broadway",
    "sg:city":"London",
    "sg:classifiers":[
        {
            "category":"Food & Beverages",
            "subcategory":"Supermarket",
            "type":"Retail Goods"
        }
    ],
    "sg:phone":"+44 20 8450 6737",
    "sg:postcode":"NW2 3HP",
    "sg:province":"Greater London",
    "wof:name":"Superway",
    "wof:placetype":"venue"
},
  "geometry": {"coordinates":[-0.216804,51.55785],"type":"Point"}
}