{
  "type": "Feature",
  "properties": {
    "addr:full":"20 Greatfields Dr Uxbridge Buckinghamshire UB8 3QN",
    "addr:housenumber":"20",
    "addr:postcode":"ub8 3qn",
    "addr:street":"Greatfields Dr",
    "iso:country":"GB",
    "sg:address":"20 Greatfields Dr",
    "sg:city":"Uxbridge",
    "sg:classifiers":[
        {
            "category":"Shopping",
            "subcategory":"Clothing, Apparel, & Fashions",
            "type":"Retail Goods"
        }
    ],
    "sg:postcode":"UB8 3QN",
    "sg:province":"Buckinghamshire",
    "sg:tags":[
        "workwear",
        "protective"
    ],
    "wof:name":"Moore,Neil,",
    "wof:placetype":"venue"
},
  "geometry": {"coordinates":[-0.455389,51.52404],"type":"Point"}
}