{
  "type": "Feature",
  "properties": {
    "addr:full":"Europa House, 310 Europa Blvd, Gemini Business Park Warrington Cheshire WA5 7YQ",
    "addr:housenumber":"310",
    "addr:postcode":"wa5 7yq",
    "addr:street":"Europa Blvd Gemini Business Park",
    "iso:country":"GB",
    "sg:address":"Europa House, 310 Europa Blvd, Gemini Business Park",
    "sg:city":"Warrington",
    "sg:classifiers":[
        {
            "category":"Professional",
            "subcategory":"Engineering",
            "type":"Services"
        }
    ],
    "sg:phone":"+44 1925 444648",
    "sg:postcode":"WA5 7YQ",
    "sg:province":"Cheshire",
    "sg:tags":[
        "consulting",
        "engineer"
    ],
    "wof:name":"Vectra Group Ltd.",
    "wof:placetype":"venue"
},
  "geometry": {"coordinates":[-2.616957,53.416325],"type":"Point"}
}