{
  "type": "Feature",
  "properties": {
    "addr:full":"North Esplanade West Aberdeen Aberdeen City AB11 5RJ",
    "addr:postcode":"ab11 5rj",
    "addr:street":"North Esplanade West",
    "iso:country":"GB",
    "sg:address":"North Esplanade West",
    "sg:city":"Aberdeen",
    "sg:classifiers":[
        {
            "category":"Parking",
            "type":"Transportation"
        }
    ],
    "sg:phone":"+44 1224 576167",
    "sg:postcode":"AB11 5RJ",
    "sg:province":"Aberdeen City",
    "sg:tags":[
        "car",
        "valet"
    ],
    "wof:name":"I.M.O Car Wash",
    "wof:placetype":"venue"
},
  "geometry": {"coordinates":[-2.0909750462,57.1406326294],"type":"Point"}
}