{
  "type": "Feature",
  "properties": {
    "iso:country":"GB",
    "sg:address":"Perdix Lodge, Kelsey Road, Moortown",
    "sg:city":"Market Rasen",
    "sg:classifiers":[
        {
            "category":"Building & Trades",
            "subcategory":"Construction",
            "type":"Services"
        }
    ],
    "sg:postcode":"LN7 6JB",
    "sg:province":"Lincolnshire",
    "sg:tags":[
        "builder"
    ],
    "wof:name":"Malcolm Gordon William Denniss",
    "wof:placetype":"venue"
},
  "geometry": {"coordinates":[-0.386999,53.478596],"type":"Point"}
}