{
  "type": "Feature",
  "properties": {
    "addr:full":"65 Ebberns Rd, Apley Hemel Hempstead Hertfordshire HP3 9QR",
    "addr:housenumber":"65",
    "addr:postcode":"hp3 9qr",
    "addr:street":"Ebberns Rd;Hempstead",
    "iso:country":"GB",
    "sg:address":"65 Ebberns Rd, Apley",
    "sg:city":"Hemel Hempstead",
    "sg:classifiers":[
        {
            "category":"Manufacturing",
            "subcategory":"Signs",
            "type":"Manufacturing & Wholesale Goods"
        }
    ],
    "sg:phone":"+44 1442 243484",
    "sg:postcode":"HP3 9QR",
    "sg:province":"Hertfordshire",
    "sg:tags":[
        "commercial",
        "maker"
    ],
    "wof:name":"David Stanton Signs",
    "wof:placetype":"venue"
},
  "geometry": {"coordinates":[-0.465427,51.739307],"type":"Point"}
}