{
  "type": "Feature",
  "properties": {
    "iso:country":"GB",
    "sg:address":"13 Union La",
    "sg:city":"Perth",
    "sg:classifiers":[
        {
            "category":"Bars & Pubs",
            "type":"Food & Drink"
        }
    ],
    "sg:postcode":"PH1 5PU",
    "sg:province":"Perth and Kinross",
    "sg:tags":[
        "pubs",
        "inn"
    ],
    "wof:name":"Lamplight Lounge",
    "wof:placetype":"venue"
},
  "geometry": {"coordinates":[-3.433897,56.398857],"type":"Point"}
}