{
  "type": "Feature",
  "properties": {
    "addr:full":"77 Gurney Road, Costessey Norwich Norfolk NR5 0HL",
    "addr:housenumber":"77",
    "addr:postcode":"nr5 0hl",
    "addr:street":"Gurney Road;Norwich Norfolk",
    "iso:country":"GB",
    "sg:address":"77 Gurney Road, Costessey",
    "sg:city":"Norwich",
    "sg:classifiers":[
        {
            "category":"Building & Trades",
            "subcategory":"Construction",
            "type":"Services"
        }
    ],
    "sg:postcode":"NR5 0HL",
    "sg:province":"Norfolk",
    "sg:tags":[
        "joiner",
        "carpenter"
    ],
    "wof:name":"J A Chittock",
    "wof:placetype":"venue"
},
  "geometry": {"coordinates":[1.2272870541,52.6472358704],"type":"Point"}
}