{
  "type": "Feature",
  "properties": {
    "addr:full":"81 Market Street Bolton Lancashire BL4 9BS",
    "addr:housenumber":"81",
    "addr:postcode":"bl4 9bs",
    "addr:street":"Market Street",
    "iso:country":"GB",
    "sg:address":"81 Market Street",
    "sg:city":"Bolton",
    "sg:classifiers":[
        {
            "category":"Personal",
            "subcategory":"Beauty Salon",
            "type":"Services"
        }
    ],
    "sg:phone":"+44 1204 705752",
    "sg:postcode":"BL4 9BS",
    "sg:province":"Lancashire",
    "sg:tags":[
        "unisex",
        "hairdresser"
    ],
    "wof:name":"Powercut",
    "wof:placetype":"venue"
},
  "geometry": {"coordinates":[-2.393349,53.548641],"type":"Point"}
}