{
  "type": "Feature",
  "properties": {
    "addr:full":"11 Burton Ct, Burton Sq Stafford Staffordshire ST17 9LU",
    "addr:housenumber":"11",
    "addr:postcode":"ct;st17 9lu",
    "addr:street":"Burton;Sq",
    "iso:country":"GB",
    "sg:address":"11 Burton Ct, Burton Sq",
    "sg:city":"Stafford",
    "sg:classifiers":[
        {
            "category":"Professional",
            "subcategory":"Detective & Security Services",
            "type":"Services"
        }
    ],
    "sg:phone":"+44 1785 240659",
    "sg:postcode":"ST17 9LU",
    "sg:province":"Staffordshire",
    "wof:name":"Roger Crutchley",
    "wof:placetype":"venue"
},
  "geometry": {"coordinates":[-2.11862,52.78722],"type":"Point"}
}