{
  "type": "Feature",
  "properties": {
    "iso:country":"GB",
    "sg:address":"126 Harlequin Ave",
    "sg:city":"Brentford",
    "sg:classifiers":[
        {
            "category":"Food & Beverages",
            "subcategory":"Bakery",
            "type":"Retail Goods"
        }
    ],
    "sg:postcode":"TW8 9EW",
    "sg:province":"Greater London",
    "sg:tags":[
        "confectionery"
    ],
    "wof:name":"Happy Baker (The)",
    "wof:placetype":"venue"
},
  "geometry": {"coordinates":[-0.3264659941,51.4860992432],"type":"Point"}
}