{
  "type": "Feature",
  "properties": {
    "addr:full":"34 Queen Street Rushden Bedfordshire NN10 0AZ",
    "addr:housenumber":"34",
    "addr:postcode":"nn10 0az",
    "addr:street":"Queen Street",
    "iso:country":"GB",
    "sg:address":"34 Queen Street",
    "sg:city":"Rushden",
    "sg:classifiers":[
        {
            "category":"Home & Garden",
            "subcategory":"Home Furnishings",
            "type":"Retail Goods"
        },
        {
            "category":"Professional",
            "subcategory":"Business Services",
            "type":"Services"
        }
    ],
    "sg:phone":"+44 1933 412472",
    "sg:postcode":"NN10 0AZ",
    "sg:province":"Bedfordshire",
    "sg:tags":[
        "agent",
        "export",
        "awning",
        "import",
        "canopy",
        "blinds"
    ],
    "wof:name":"B E White Blind & Curtain Rail Services",
    "wof:placetype":"venue"
},
  "geometry": {"coordinates":[-0.5956919789,52.2921257019],"type":"Point"}
}