{
  "type": "Feature",
  "properties": {
    "addr:full":"Harris House, 92a Crwys Road Cardiff Cardiff CF24 4NP",
    "addr:housenumber":"92a",
    "addr:postcode":"cf24 4np",
    "addr:street":"Crwys Road",
    "iso:country":"GB",
    "sg:address":"Harris House, 92a Crwys Road",
    "sg:city":"Cardiff",
    "sg:classifiers":[
        {
            "category":"Professional",
            "subcategory":"Engineering",
            "type":"Services"
        }
    ],
    "sg:postcode":"CF24 4NP",
    "sg:province":"Cardiff",
    "sg:tags":[
        "consulting",
        "engineer"
    ],
    "wof:name":"U T C Associates",
    "wof:placetype":"venue"
},
  "geometry": {"coordinates":[-3.179461956,51.4959983826],"type":"Point"}
}