{
  "type": "Feature",
  "properties": {
    "addr:full":"78b Dickson Road Blackpool Lancashire FY1 2BU",
    "addr:housenumber":"78b",
    "addr:postcode":"fy1 2bu",
    "addr:street":"Dickson Road",
    "iso:country":"GB",
    "sg:address":"78b Dickson Road",
    "sg:city":"Blackpool",
    "sg:classifiers":[
        {
            "category":"Shopping",
            "subcategory":"Discount & Variety Stores",
            "type":"Retail Goods"
        }
    ],
    "sg:postcode":"FY1 2BU",
    "sg:province":"Lancashire",
    "sg:tags":[
        "shop",
        "model"
    ],
    "wof:name":"Exchange Model Shop",
    "wof:placetype":"venue"
},
  "geometry": {"coordinates":[-3.053709,53.823257],"type":"Point"}
}