{
  "type": "Feature",
  "properties": {
    "addr:full":"174 Woodseer Street London Greater London E1 5HQ",
    "addr:housenumber":"174",
    "addr:postcode":"e1 5hq",
    "addr:street":"Woodseer Street",
    "iso:country":"GB",
    "sg:address":"174 Woodseer Street",
    "sg:city":"London",
    "sg:classifiers":[
        {
            "category":"Health Services",
            "subcategory":"Health Practitioner",
            "type":"Services"
        }
    ],
    "sg:phone":"+44 20 7377 1367",
    "sg:postcode":"E1 5HQ",
    "sg:province":"Greater London",
    "sg:tags":[
        "physiotherapist"
    ],
    "wof:name":"Robert Laus",
    "wof:placetype":"venue"
},
  "geometry": {"coordinates":[-0.066267,51.520283],"type":"Point"}
}