{
  "type": "Feature",
  "properties": {
    "iso:country":"GB",
    "sg:address":"Unit 18 Erica Road, Stacey Bushes",
    "sg:city":"Milton Keynes",
    "sg:classifiers":[
        {
            "category":"Shopping Center",
            "type":"Public Place"
        }
    ],
    "sg:phone":"+44 1908 320320",
    "sg:postcode":"MK12 6HS",
    "sg:province":"Buckinghamshire",
    "sg:tags":[
        "clutch",
        "brake",
        "centre"
    ],
    "wof:name":"Mr Clutch Autocentres Ltd.",
    "wof:placetype":"venue"
},
  "geometry": {"coordinates":[-0.799914,52.050686],"type":"Point"}
}