{
  "type": "Feature",
  "properties": {
    "addr:full":"5-6 Triangle South Bristol City of Bristol BS8 1EY",
    "addr:housenumber":"5-6",
    "addr:postcode":"bs8 1ey",
    "addr:street":"Triangle South",
    "iso:country":"GB",
    "sg:address":"5-6 Triangle South",
    "sg:city":"Bristol",
    "sg:classifiers":[
        {
            "category":"Restaurant",
            "type":"Food & Drink"
        }
    ],
    "sg:phone":"+44 117 929 1975",
    "sg:postcode":"BS8 1EY",
    "sg:province":"City of Bristol",
    "wof:name":"Grand City Restaurant",
    "wof:placetype":"venue"
},
  "geometry": {"coordinates":[-2.6075789928,51.4561195374],"type":"Point"}
}