{
  "type": "Feature",
  "properties": {
    "addr:full":"Unit 2 Granville Street Normanton West Yorkshire WF6 2EQ",
    "addr:housenumber":"unit 2",
    "addr:postcode":"wf6 2eq",
    "addr:street":"Granville Street",
    "iso:country":"GB",
    "sg:address":"Unit 2 Granville Street",
    "sg:city":"Normanton",
    "sg:classifiers":[
        {
            "category":"Autos & Motor Vehicles",
            "subcategory":"Auto Supplies",
            "type":"Retail Goods"
        }
    ],
    "sg:phone":"+44 1924 223582",
    "sg:postcode":"WF6 2EQ",
    "sg:province":"West Yorkshire",
    "sg:tags":[
        "tyre"
    ],
    "wof:name":"Simon Jackson",
    "wof:placetype":"venue"
},
  "geometry": {"coordinates":[-1.410739,53.700386],"type":"Point"}
}