{
  "type": "Feature",
  "properties": {
    "addr:full":"20 West Street St Neots Bedfordshire PE19 1AH",
    "addr:housenumber":"20",
    "addr:postcode":"pe19 1ah",
    "addr:street":"West Street",
    "iso:country":"GB",
    "sg:address":"20 West Street",
    "sg:city":"St Neots",
    "sg:classifiers":[
        {
            "category":"Building & Trades",
            "subcategory":"Construction",
            "type":"Services"
        }
    ],
    "sg:phone":"+44 1480 811683",
    "sg:postcode":"PE19 1AH",
    "sg:province":"Bedfordshire",
    "sg:tags":[
        "builder"
    ],
    "wof:name":"M W S GENERAL BUILDERS AND ELECTRICAL CONTRACTORS",
    "wof:placetype":"venue"
},
  "geometry": {"coordinates":[-0.269858,52.229416],"type":"Point"}
}