{
  "type": "Feature",
  "properties": {
    "addr:full":"The Lodge, Ings Lane, Hibaldstow Brigg Lincolnshire DN20 9PJ",
    "addr:postcode":"dn20 9pj",
    "addr:street":"Ings Lane;Brigg",
    "iso:country":"GB",
    "sg:address":"The Lodge, Ings Lane, Hibaldstow",
    "sg:city":"Brigg",
    "sg:classifiers":[
        {
            "category":"Transit Center",
            "subcategory":"Passenger",
            "type":"Transportation"
        }
    ],
    "sg:phone":"+44 1652 657401",
    "sg:postcode":"DN20 9PJ",
    "sg:province":"Lincolnshire",
    "sg:tags":[
        "boarding",
        "kennel",
        "catteries"
    ],
    "wof:name":"Posh Paws Cattery",
    "wof:placetype":"venue"
},
  "geometry": {"coordinates":[-0.529014,53.512199],"type":"Point"}
}