{
  "type": "Feature",
  "properties": {
    "iso:country":"GB",
    "sg:address":"35 St Pauls Road",
    "sg:city":"Southsea",
    "sg:classifiers":[
        {
            "category":"Retail",
            "subcategory":"Auto Repair",
            "type":"Services"
        }
    ],
    "sg:phone":"+44 23 9282 2778",
    "sg:postcode":"PO5 4AA",
    "sg:province":"Hampshire",
    "sg:tags":[
        "body",
        "car",
        "repairer"
    ],
    "wof:name":"B A Motors",
    "wof:placetype":"venue"
},
  "geometry": {"coordinates":[-1.094479,50.791088],"type":"Point"}
}