{
  "type": "Feature",
  "properties": {
    "iso:country":"GB",
    "sg:address":"49 Stakesby Rd",
    "sg:city":"Whitby",
    "sg:classifiers":[
        {
            "category":"Building & Trades",
            "subcategory":"Construction",
            "type":"Services"
        }
    ],
    "sg:phone":"+44 1947 602333",
    "sg:postcode":"YO21 1JF",
    "sg:province":"North Yorkshire",
    "sg:tags":[
        "builder"
    ],
    "wof:name":"E Hall",
    "wof:placetype":"venue"
},
  "geometry": {"coordinates":[-0.6308500171,54.4868278503],"type":"Point"}
}