{
  "type": "Feature",
  "properties": {
    "iso:country":"GB",
    "sg:address":"194 St Enochs Road",
    "sg:city":"Bradford",
    "sg:classifiers":[
        {
            "category":"Professional",
            "subcategory":"Detective & Security Services",
            "type":"Services"
        }
    ],
    "sg:phone":"+44 1274 674032",
    "sg:postcode":"BD6 3BT",
    "sg:province":"West Yorkshire",
    "sg:tags":[
        "alarm",
        "burglar",
        "system"
    ],
    "wof:name":"P & P Property Protectors",
    "wof:placetype":"venue"
},
  "geometry": {"coordinates":[-1.7811030149,53.7679672241],"type":"Point"}
}