{
  "type": "Feature",
  "properties": {
    "addr:full":"Lakeside, P O Box 55 Manchester Cheshire M17 1HP",
    "addr:housenumber":"55",
    "addr:postcode":"m17 1hp",
    "addr:street":"P O;Manchester Cheshire",
    "iso:country":"GB",
    "sg:address":"Lakeside, P O Box 55",
    "sg:city":"Manchester",
    "sg:classifiers":[
        {
            "category":"Manufacturing",
            "subcategory":"Chemicals & Compounds",
            "type":"Manufacturing & Wholesale Goods"
        }
    ],
    "sg:phone":"+44 161 872 2381",
    "sg:postcode":"M17 1HP",
    "sg:province":"Cheshire",
    "sg:tags":[
        "abrasive",
        "product",
        "cleaning"
    ],
    "wof:name":"Carborundum Abrasives Plc",
    "wof:placetype":"venue"
},
  "geometry": {"coordinates":[-2.3196790218,53.4674415588],"type":"Point"}
}