{
  "type": "Feature",
  "properties": {
    "addr:full":"Sky House, 41/43 Checketts Lane Worcester Worcestershire WR3 7JN",
    "addr:housenumber":"41 / 43",
    "addr:postcode":"wr3 7jn",
    "addr:street":"Checketts Lane",
    "iso:country":"GB",
    "sg:address":"Sky House, 41/43 Checketts Lane",
    "sg:city":"Worcester",
    "sg:classifiers":[
        {
            "category":"Autos & Motor Vehicles",
            "subcategory":"Auto Supplies",
            "type":"Retail Goods"
        }
    ],
    "sg:phone":"+44 1905 452727",
    "sg:postcode":"WR3 7JN",
    "sg:province":"Worcestershire",
    "sg:tags":[
        "component"
    ],
    "wof:name":"Skyparts",
    "wof:placetype":"venue"
},
  "geometry": {"coordinates":[-2.223384,52.215645],"type":"Point"}
}