{
  "type": "Feature",
  "properties": {
    "addr:full":"8 Tom Amey Court, St Philips Road Cambridge Cambridgeshire CB1 3UX",
    "addr:housenumber":"8",
    "addr:postcode":"cb1 3ux",
    "addr:street":"Tom Amey Court St Philips Road",
    "iso:country":"GB",
    "sg:address":"8 Tom Amey Court, St Philips Road",
    "sg:city":"Cambridge",
    "sg:classifiers":[
        {
            "category":"Home & Garden",
            "subcategory":"Garden Supply",
            "type":"Retail Goods"
        }
    ],
    "sg:phone":"+44 1223 578998",
    "sg:postcode":"CB1 3UX",
    "sg:province":"Cambridgeshire",
    "sg:tags":[
        "turfing"
    ],
    "wof:name":"M 99",
    "wof:placetype":"venue"
},
  "geometry": {"coordinates":[0.14764,52.199051],"type":"Point"}
}