{
  "type": "Feature",
  "properties": {
    "addr:full":"34 Linkfield Rd Loughborough Leicestershire LE12 7DJ",
    "addr:housenumber":"34",
    "addr:postcode":"le12 7dj",
    "addr:street":"Linkfield Rd",
    "iso:country":"GB",
    "sg:address":"34 Linkfield Rd",
    "sg:city":"Loughborough",
    "sg:classifiers":[
        {
            "category":"Retail",
            "subcategory":"Auto Repair",
            "type":"Services"
        }
    ],
    "sg:phone":"+44 116 230 2440",
    "sg:postcode":"LE12 7DJ",
    "sg:province":"Leicestershire",
    "sg:tags":[
        "modification",
        "garage"
    ],
    "wof:name":"J. & B. Stone (Motor Services) Limited",
    "wof:placetype":"venue"
},
  "geometry": {"coordinates":[-1.135174036,52.7217521667],"type":"Point"}
}