{
  "type": "Feature",
  "properties": {
    "addr:full":"Marine Park Rest Home, 6 Marine Park, West Kirby Wirral Merseyside CH48 5HW",
    "addr:housenumber":"6",
    "addr:postcode":"ch48 5hw",
    "iso:country":"GB",
    "sg:address":"Marine Park Rest Home, 6 Marine Park, West Kirby",
    "sg:city":"Wirral",
    "sg:classifiers":[
        {
            "category":"Social Services",
            "subcategory":"Retirement Home",
            "type":"Services"
        }
    ],
    "sg:postcode":"CH48 5HW",
    "sg:province":"Merseyside",
    "sg:tags":[
        "residential",
        "care"
    ],
    "wof:name":"Marine Park Residential Home",
    "wof:placetype":"venue"
},
  "geometry": {"coordinates":[-3.1788098812,53.3777503967],"type":"Point"}
}