{
  "type": "Feature",
  "properties": {
    "iso:country":"GB",
    "sg:address":"80 High St",
    "sg:city":"Honiton",
    "sg:classifiers":[
        {
            "category":"Food & Beverages",
            "subcategory":"Fruits & Vegetables",
            "type":"Retail Goods"
        }
    ],
    "sg:postcode":"EX14 1LN",
    "sg:province":"Devon",
    "sg:tags":[
        "greengrocer"
    ],
    "wof:name":"Granny Smiths",
    "wof:placetype":"venue"
},
  "geometry": {"coordinates":[-3.188936,50.799599],"type":"Point"}
}