{
  "type": "Feature",
  "properties": {
    "addr:full":"6 Avenue Road Ramsgate Kent CT11 8ET",
    "addr:housenumber":"6",
    "addr:postcode":"ct11 8et",
    "addr:street":"Avenue Road Ramsgate",
    "iso:country":"GB",
    "sg:address":"6 Avenue Road",
    "sg:city":"Ramsgate",
    "sg:classifiers":[
        {
            "category":"Travel",
            "subcategory":"Hotels & Motels",
            "type":"Entertainment"
        }
    ],
    "sg:postcode":"CT11 8ET",
    "sg:province":"Kent",
    "wof:name":"Sealan Hotel",
    "wof:placetype":"venue"
},
  "geometry": {"coordinates":[1.4248290062,51.3371696472],"type":"Point"}
}