{
  "type": "Feature",
  "properties": {
    "addr:full":"Hoo Mill, Ingestre Stafford Staffordshire ST18 0RG",
    "addr:postcode":"st18 0rg",
    "addr:street":"Hoo",
    "iso:country":"GB",
    "sg:address":"Hoo Mill, Ingestre",
    "sg:city":"Stafford",
    "sg:classifiers":[
        {
            "category":"Airport",
            "subcategory":"General Aviation",
            "type":"Transportation"
        }
    ],
    "sg:phone":"+44 1889 881495",
    "sg:postcode":"ST18 0RG",
    "sg:province":"Staffordshire",
    "wof:name":"Soaring (Oxford) Ltd.",
    "wof:placetype":"venue"
},
  "geometry": {"coordinates":[-2.0302989483,52.8198471069],"type":"Point"}
}