{
  "type": "Feature",
  "properties": {
    "addr:full":"Goosehill, Portesham Weymouth Dorset DT3 4HE",
    "addr:housenumber":"portesham",
    "addr:postcode":"dt3 4he",
    "iso:country":"GB",
    "sg:address":"Goosehill, Portesham",
    "sg:city":"Weymouth",
    "sg:classifiers":[
        {
            "category":"Travel",
            "subcategory":"Hotels & Motels",
            "type":"Entertainment"
        }
    ],
    "sg:postcode":"DT3 4HE",
    "sg:province":"Dorset",
    "wof:name":"Millmead Country Hotel",
    "wof:placetype":"venue"
},
  "geometry": {"coordinates":[-2.564412117,50.6694526672],"type":"Point"}
}