{
  "type": "Feature",
  "properties": {
    "iso:country":"GB",
    "sg:address":"39 Derwent Drive, Upper Stratton",
    "sg:city":"Swindon",
    "sg:classifiers":[
        {
            "category":"Building & Trades",
            "subcategory":"Construction",
            "type":"Services"
        }
    ],
    "sg:phone":"+44 1793 824405",
    "sg:postcode":"SN2 7NL",
    "sg:province":"Wiltshire",
    "sg:tags":[
        "builder"
    ],
    "wof:name":"Jeffery Roberts",
    "wof:placetype":"venue"
},
  "geometry": {"coordinates":[-1.760181,51.589966],"type":"Point"}
}