{
  "type": "Feature",
  "properties": {
    "addr:full":"302 Tadcaster Road York North Yorkshire YO24 1HE",
    "addr:housenumber":"302",
    "addr:postcode":"yo24 1he",
    "addr:street":"Tadcaster Road",
    "iso:country":"GB",
    "sg:address":"302 Tadcaster Road",
    "sg:city":"York",
    "sg:classifiers":[
        {
            "category":"Travel",
            "subcategory":"Hotels & Motels",
            "type":"Entertainment"
        }
    ],
    "sg:phone":"+44 1904 702941",
    "sg:postcode":"YO24 1HE",
    "sg:province":"North Yorkshire",
    "wof:name":"Knavesmire Manor Hotel",
    "wof:placetype":"venue"
},
  "geometry": {"coordinates":[-1.10342,53.944412],"type":"Point"}
}