{
  "type": "Feature",
  "properties": {
    "addr:full":"15 London Road Newcastle Staffordshire ST5 1LQ",
    "addr:housenumber":"15",
    "addr:postcode":"st5 1lq",
    "addr:street":"London Road",
    "iso:country":"GB",
    "sg:address":"15 London Road",
    "sg:city":"Newcastle",
    "sg:classifiers":[
        {
            "category":"Restaurant",
            "type":"Food & Drink"
        }
    ],
    "sg:phone":"+44 1782 623824",
    "sg:postcode":"ST5 1LQ",
    "sg:province":"Staffordshire",
    "sg:tags":[
        "indian"
    ],
    "wof:name":"Amun Massala",
    "wof:placetype":"venue"
},
  "geometry": {"coordinates":[-2.2237110138,53.0086326599],"type":"Point"}
}