{
  "type": "Feature",
  "properties": {
    "iso:country":"GB",
    "sg:address":"17 Panmure Street, Broughty Ferry",
    "sg:city":"Dundee",
    "sg:classifiers":[
        {
            "category":"Food & Beverages",
            "subcategory":"Groceries & Convenience Stores",
            "type":"Retail Goods"
        }
    ],
    "sg:phone":"+44 1382 738118",
    "sg:postcode":"DD5 2ER",
    "sg:province":"Angus",
    "wof:name":"Morning Noon & Night Ltd.",
    "wof:placetype":"venue"
},
  "geometry": {"coordinates":[-2.862861,56.466835],"type":"Point"}
}