{
  "type": "Feature",
  "properties": {
    "iso:country":"GB",
    "sg:address":"60 Boutport St",
    "sg:city":"Barnstaple",
    "sg:classifiers":[
        {
            "category":"Shopping",
            "subcategory":"Clothing, Apparel, & Fashions",
            "type":"Retail Goods"
        }
    ],
    "sg:postcode":"EX31 1SH",
    "sg:province":"Devon",
    "sg:tags":[
        "shop"
    ],
    "wof:name":"Be-Wise Ltd",
    "wof:placetype":"venue"
},
  "geometry": {"coordinates":[-4.058524,51.079006],"type":"Point"}
}