{
  "type": "Feature",
  "properties": {
    "iso:country":"GB",
    "sg:address":"65 Middle Street",
    "sg:city":"Consett",
    "sg:classifiers":[
        {
            "category":"Shopping",
            "subcategory":"Department Store",
            "type":"Retail Goods"
        },
        {
            "category":"Shopping",
            "subcategory":"Music",
            "type":"Retail Goods"
        }
    ],
    "sg:phone":"+44 1207 503923",
    "sg:postcode":"DH8 5QG",
    "sg:province":"Durham",
    "sg:tags":[
        "record",
        "tape",
        "cd"
    ],
    "wof:name":"Ross Records & Tapes",
    "wof:placetype":"venue"
},
  "geometry": {"coordinates":[-1.834523,54.852875],"type":"Point"}
}