{
  "type": "Feature",
  "properties": {
    "iso:country":"GB",
    "sg:address":"86 Aberrhondda Road",
    "sg:city":"Porth",
    "sg:classifiers":[
        {
            "category":"Professional",
            "subcategory":"Detective & Security Services",
            "type":"Services"
        }
    ],
    "sg:phone":"+44 1443 686014",
    "sg:postcode":"CF39 0AU",
    "sg:province":"Bridgend",
    "sg:tags":[
        "alarm",
        "burglar",
        "system"
    ],
    "wof:name":"Taurus Alarms",
    "wof:placetype":"venue"
},
  "geometry": {"coordinates":[-3.4113969803,51.6211585999],"type":"Point"}
}