{
  "type": "Feature",
  "properties": {
    "addr:full":"The Post House, Newton Road, West Pennard Glastonbury Somerset BA6 8NL",
    "addr:postcode":"ba6 8nl",
    "addr:street":"Newton Road West",
    "iso:country":"GB",
    "sg:address":"The Post House, Newton Road, West Pennard",
    "sg:city":"Glastonbury",
    "sg:classifiers":[
        {
            "category":"Home & Garden",
            "subcategory":"Building Materials",
            "type":"Retail Goods"
        }
    ],
    "sg:phone":"+44 1458 832955",
    "sg:postcode":"BA6 8NL",
    "sg:province":"Somerset",
    "sg:tags":[
        "insulation",
        "installers"
    ],
    "wof:name":"Paul Homer",
    "wof:placetype":"venue"
},
  "geometry": {"coordinates":[-2.645499,51.145718],"type":"Point"}
}