{
  "type": "Feature",
  "properties": {
    "iso:country":"GB",
    "sg:address":"4 Henry St",
    "sg:city":"Lytham St Annes",
    "sg:classifiers":[
        {
            "category":"Cafe",
            "type":"Food & Drink"
        }
    ],
    "sg:postcode":"FY8 5LE",
    "sg:province":"Lancashire",
    "sg:tags":[
        "tea",
        "room"
    ],
    "wof:name":"Elizabeth of Lytham Cafe",
    "wof:placetype":"venue"
},
  "geometry": {"coordinates":[-2.963502,53.736488],"type":"Point"}
}