{
  "type": "Feature",
  "properties": {
    "addr:full":"4 Lower Mead Hill, Brow Road Liss Hampshire GU33 7RL",
    "addr:housenumber":"4",
    "addr:postcode":"gu33 7rl",
    "addr:street":"Lower Mead Hill Brow Road",
    "iso:country":"GB",
    "sg:address":"4 Lower Mead Hill, Brow Road",
    "sg:city":"Liss",
    "sg:classifiers":[
        {
            "category":"Shopping",
            "subcategory":"Pharmacy",
            "type":"Retail Goods"
        }
    ],
    "sg:phone":"+44 1730 893161",
    "sg:postcode":"GU33 7RL",
    "sg:province":"Hampshire",
    "sg:tags":[
        "pharmacist",
        "chemist"
    ],
    "wof:name":"Liss Pharmacy",
    "wof:placetype":"venue"
},
  "geometry": {"coordinates":[-0.8926500082,51.0430259705],"type":"Point"}
}