{
  "type": "Feature",
  "properties": {
    "iso:country":"GB",
    "sg:address":"Unit 7 Kingslea Works, Kingston Road",
    "sg:city":"Leatherhead",
    "sg:classifiers":[
        {
            "category":"Retail",
            "subcategory":"Auto Repair",
            "type":"Services"
        }
    ],
    "sg:phone":"+44 1372 370366",
    "sg:postcode":"KT22 7LE",
    "sg:province":"Surrey",
    "sg:tags":[
        "modification",
        "garage"
    ],
    "wof:name":"Carlssons Automotive",
    "wof:placetype":"venue"
},
  "geometry": {"coordinates":[-0.329419,51.29636],"type":"Point"}
}