{
  "type": "Feature",
  "properties": {
    "addr:full":"16 Horsecroft Pl Harlow Essex CM19 5BU",
    "addr:housenumber":"16",
    "addr:postcode":"cm19 5bu",
    "addr:street":"Horsecroft Pl",
    "iso:country":"GB",
    "sg:address":"16 Horsecroft Pl",
    "sg:city":"Harlow",
    "sg:classifiers":[
        {
            "category":"Manufacturing",
            "subcategory":"Signs",
            "type":"Manufacturing & Wholesale Goods"
        }
    ],
    "sg:phone":"+44 1279 431454",
    "sg:postcode":"CM19 5BU",
    "sg:province":"Essex",
    "sg:tags":[
        "nameplate"
    ],
    "wof:name":"Stonesigns Ltd",
    "wof:placetype":"venue"
},
  "geometry": {"coordinates":[0.0608559996,51.7647895813],"type":"Point"}
}