{
  "type": "Feature",
  "properties": {
    "addr:full":"457 London Road Northwich Cheshire CW9 8NH",
    "addr:housenumber":"457",
    "addr:postcode":"cw9 8nh",
    "addr:street":"London Road",
    "iso:country":"GB",
    "sg:address":"457 London Road",
    "sg:city":"Northwich",
    "sg:classifiers":[
        {
            "category":"Shopping",
            "subcategory":"Department Store",
            "type":"Retail Goods"
        },
        {
            "category":"Home & Garden",
            "subcategory":"Carpets & Floor Coverings",
            "type":"Retail Goods"
        }
    ],
    "sg:phone":"+44 1606 330977",
    "sg:postcode":"CW9 8NH",
    "sg:province":"Cheshire",
    "sg:tags":[
        "carpets",
        "rug",
        "matting"
    ],
    "wof:name":"Village Floor Coverings",
    "wof:placetype":"venue"
},
  "geometry": {"coordinates":[-2.5126390457,53.2414512634],"type":"Point"}
}