{
  "type": "Feature",
  "properties": {
    "iso:country":"GB",
    "sg:address":"The Lodge, Bramcote Hospital, Lutterworth Road, Bramcote",
    "sg:city":"Nuneaton",
    "sg:classifiers":[
        {
            "category":"Health Services",
            "subcategory":"Doctor",
            "type":"Services"
        }
    ],
    "sg:phone":"+44 24 7635 2902",
    "sg:postcode":"CV11 6QL",
    "sg:province":"Leicestershire",
    "sg:tags":[
        "practitioners"
    ],
    "wof:name":"Community Audiology Unit",
    "wof:placetype":"venue"
},
  "geometry": {"coordinates":[-1.404429,52.49696],"type":"Point"}
}