{
  "type": "Feature",
  "properties": {
    "iso:country":"GB",
    "sg:address":"South Fambridge Hall, South Fambridge",
    "sg:city":"Rochford",
    "sg:classifiers":[
        {
            "category":"Farming",
            "subcategory":"Livestock Farm",
            "type":"Manufacturing & Wholesale Goods"
        }
    ],
    "sg:phone":"+44 1702 202450",
    "sg:postcode":"SS4 3LS",
    "sg:province":"Essex",
    "sg:tags":[
        "others"
    ],
    "wof:name":"Gibbon Farms",
    "wof:placetype":"venue"
},
  "geometry": {"coordinates":[0.7013890147,51.5832214355],"type":"Point"}
}