{
  "type": "Feature",
  "properties": {
    "addr:full":"6 Beachfield Road Sandown Isle of Wight PO36 8NF",
    "addr:housenumber":"6",
    "addr:postcode":"po36 8nf",
    "addr:street":"Beachfield Road",
    "iso:country":"GB",
    "sg:address":"6 Beachfield Road",
    "sg:city":"Sandown",
    "sg:classifiers":[
        {
            "category":"Professional",
            "subcategory":"Engineering",
            "type":"Services"
        },
        {
            "category":"Building & Trades",
            "subcategory":"Electrical",
            "type":"Services"
        }
    ],
    "sg:phone":"+44 1983 402376",
    "sg:postcode":"PO36 8NF",
    "sg:province":"Isle of Wight",
    "sg:tags":[
        "engineer",
        "electrician",
        "contractor"
    ],
    "wof:name":"Robert D Compton",
    "wof:placetype":"venue"
},
  "geometry": {"coordinates":[-1.1607730389,50.6517791748],"type":"Point"}
}