{
  "type": "Feature",
  "properties": {
    "addr:full":"Park Crescent West Wigan Lancashire WN1 1SA",
    "addr:postcode":"wn1 1sa",
    "addr:street":"Park Crescent West",
    "iso:country":"GB",
    "sg:address":"Park Crescent West",
    "sg:city":"Wigan",
    "sg:classifiers":[
        {
            "category":"Arena",
            "subcategory":"Sports Club",
            "type":"Entertainment"
        }
    ],
    "sg:phone":"+44 1942 243823",
    "sg:postcode":"WN1 1SA",
    "sg:province":"Lancashire",
    "wof:name":"The Wigan Subscription (Park Road) Bowling Green Ltd.",
    "wof:placetype":"venue"
},
  "geometry": {"coordinates":[-2.6396489143,53.5515365601],"type":"Point"}
}