{
  "type": "Feature",
  "properties": {
    "addr:full":"Unit 20 Kingston Park Centre, Kinston Park Avenue Newcastle-upon-tyne Tyne and Wear NE3 2FP",
    "addr:housenumber":"unit 20",
    "addr:postcode":"ne3 2fp",
    "addr:street":"Kingston Park Centre Kinston Park Avenue",
    "iso:country":"GB",
    "sg:address":"Unit 20 Kingston Park Centre, Kinston Park Avenue",
    "sg:city":"Newcastle-upon-tyne",
    "sg:classifiers":[
        {
            "category":"Community Center",
            "subcategory":"Social",
            "type":"Public Place"
        }
    ],
    "sg:phone":"+44 191 271 1589",
    "sg:postcode":"NE3 2FP",
    "sg:province":"Tyne and Wear",
    "sg:tags":[
        "frozen",
        "food",
        "freezer",
        "centre"
    ],
    "wof:name":"Iceland Foods Plc",
    "wof:placetype":"venue"
},
  "geometry": {"coordinates":[-1.670658946,55.0184402466],"type":"Point"}
}