{
  "type": "Feature",
  "properties": {
    "iso:country":"GB",
    "sg:address":"1 Percy St",
    "sg:city":"West End",
    "sg:classifiers":[
        {
            "category":"Restaurant",
            "type":"Food & Drink"
        }
    ],
    "sg:phone":"+44 20 7636 8141",
    "sg:postcode":"W1P 0ET",
    "sg:province":"Hampshire",
    "wof:name":"No.1 Cigar Club of London",
    "wof:placetype":"venue"
},
  "geometry": {"coordinates":[-0.134064,51.517952],"type":"Point"}
}