{
  "type": "Feature",
  "properties": {
    "iso:country":"GB",
    "sg:address":"18 Stewart Place",
    "sg:city":"Kirkliston",
    "sg:classifiers":[
        {
            "category":"Professional",
            "subcategory":"Art Services",
            "type":"Services"
        },
        {
            "category":"Building & Trades",
            "subcategory":"Construction",
            "type":"Services"
        }
    ],
    "sg:phone":"+44 131 333 3453",
    "sg:postcode":"EH29 9BQ",
    "sg:province":"City of Edinburgh",
    "sg:tags":[
        "decorator",
        "painter"
    ],
    "wof:name":"D J Clark Decorators",
    "wof:placetype":"venue"
},
  "geometry": {"coordinates":[-3.402618885,55.95860672],"type":"Point"}
}