{
  "type": "Feature",
  "properties": {
    "addr:full":"204a Cheltenham Rd Bristol City of Bristol BS6 5QZ",
    "addr:housenumber":"204a",
    "addr:postcode":"bs6 5qz",
    "addr:street":"Cheltenham Rd",
    "iso:country":"GB",
    "sg:address":"204a Cheltenham Rd",
    "sg:city":"Bristol",
    "sg:classifiers":[
        {
            "category":"Military Area",
            "subcategory":"Air Force Base",
            "type":"Public Place"
        }
    ],
    "sg:phone":"+44 117 942 0033",
    "sg:postcode":"BS6 5QZ",
    "sg:province":"City of Bristol",
    "sg:tags":[
        "taxi",
        "hire",
        "private"
    ],
    "wof:name":"Bristol Taxi Co",
    "wof:placetype":"venue"
},
  "geometry": {"coordinates":[-2.592683,51.468849],"type":"Point"}
}