{
  "type": "Feature",
  "properties": {
    "addr:full":"Unit 12, Old Hall Farm, Business Park Crowland St Southport Lancashire PR9 7RJ",
    "addr:housenumber":"unit 12",
    "addr:postcode":"pr9 7rj",
    "addr:street":"Crowland St",
    "iso:country":"GB",
    "sg:address":"Unit 12, Old Hall Farm, Business Park Crowland St",
    "sg:city":"Southport",
    "sg:classifiers":[
        {
            "category":"Wholesale",
            "subcategory":"Electrical",
            "type":"Manufacturing & Wholesale Goods"
        },
        {
            "category":"Shopping",
            "subcategory":"Computers & Home Electronics",
            "type":"Retail Goods"
        }
    ],
    "sg:phone":"+44 1704 500198",
    "sg:postcode":"PR9 7RJ",
    "sg:province":"Lancashire",
    "sg:tags":[
        "wholesaler"
    ],
    "wof:name":"L P D Electrical Wholesalers Ltd",
    "wof:placetype":"venue"
},
  "geometry": {"coordinates":[-2.964509964,53.6480712891],"type":"Point"}
}