{
  "type": "Feature",
  "properties": {
    "addr:full":"3 Connaught La Plymouth Devon PL4 7BZ",
    "addr:housenumber":"3",
    "addr:postcode":"pl4 7bz",
    "addr:street":"Connaught La Plymouth",
    "iso:country":"GB",
    "sg:address":"3 Connaught La",
    "sg:city":"Plymouth",
    "sg:classifiers":[
        {
            "category":"Retail",
            "subcategory":"Auto Repair",
            "type":"Services"
        }
    ],
    "sg:phone":"+44 1752 668266",
    "sg:postcode":"PL4 7BZ",
    "sg:province":"Devon",
    "sg:tags":[
        "modification",
        "garage"
    ],
    "wof:name":"Astra Service Centre",
    "wof:placetype":"venue"
},
  "geometry": {"coordinates":[-4.132144,50.383381],"type":"Point"}
}