{
  "type": "Feature",
  "properties": {
    "addr:full":"Unit 23 Ibc House, Southway Wembley Greater London HA9 0TJ",
    "addr:housenumber":"unit 23",
    "addr:postcode":"ha9 0tj",
    "addr:street":"Southway",
    "iso:country":"GB",
    "sg:address":"Unit 23 Ibc House, Southway",
    "sg:city":"Wembley",
    "sg:classifiers":[
        {
            "category":"Building & Trades",
            "subcategory":"Construction",
            "type":"Services"
        }
    ],
    "sg:phone":"+44 20 8974 5223",
    "sg:postcode":"HA9 0TJ",
    "sg:province":"Greater London",
    "sg:tags":[
        "window",
        "replacement"
    ],
    "wof:name":"Sash Windows",
    "wof:placetype":"venue"
},
  "geometry": {"coordinates":[-0.27442,51.555519],"type":"Point"}
}