{
  "type": "Feature",
  "properties": {
    "addr:full":"Unit 4 The Grn, Nettleham Lincoln Lincolnshire LN2 2NR",
    "addr:housenumber":"unit 4",
    "addr:postcode":"ln2 2nr",
    "addr:street":"The Grn;Lincoln",
    "iso:country":"GB",
    "sg:address":"Unit 4 The Grn, Nettleham",
    "sg:city":"Lincoln",
    "sg:classifiers":[
        {
            "category":"Fast Food",
            "type":"Food & Drink"
        }
    ],
    "sg:phone":"+44 1522 595240",
    "sg:postcode":"LN2 2NR",
    "sg:province":"Lincolnshire",
    "sg:tags":[
        "away",
        "take"
    ],
    "wof:name":"Golden River Chinese Take Away",
    "wof:placetype":"venue"
},
  "geometry": {"coordinates":[-0.5045790076,53.2660713196],"type":"Point"}
}