{
  "type": "Feature",
  "properties": {
    "iso:country":"GB",
    "sg:address":"249 Holdenhurst Road",
    "sg:city":"Bournemouth",
    "sg:classifiers":[
        {
            "category":"Fast Food",
            "type":"Food & Drink"
        },
        {
            "category":"Cafe",
            "type":"Food & Drink"
        }
    ],
    "sg:phone":"+44 1202 399884",
    "sg:postcode":"BH8 8DA",
    "sg:province":"Dorset",
    "sg:tags":[
        "snack",
        "bar",
        "room",
        "tea",
        "away",
        "take"
    ],
    "wof:name":"Al's Diner",
    "wof:placetype":"venue"
},
  "geometry": {"coordinates":[-1.855471,50.730572],"type":"Point"}
}