{
  "type": "Feature",
  "properties": {
    "addr:full":"5 Wenlock Terrace York North Yorkshire YO10 4DU",
    "addr:housenumber":"5",
    "addr:postcode":"yo10 4du",
    "addr:street":"Wenlock Terrace",
    "iso:country":"GB",
    "sg:address":"5 Wenlock Terrace",
    "sg:city":"York",
    "sg:classifiers":[
        {
            "category":"Travel",
            "subcategory":"Hotels & Motels",
            "type":"Entertainment"
        }
    ],
    "sg:phone":"+44 1904 632301",
    "sg:postcode":"YO10 4DU",
    "sg:province":"North Yorkshire",
    "sg:tags":[
        "house",
        "guest"
    ],
    "wof:name":"Abacus Guest House",
    "wof:placetype":"venue"
},
  "geometry": {"coordinates":[-1.0746680498,53.9465179443],"type":"Point"}
}