{
  "type": "Feature",
  "properties": {
    "addr:full":"8 Sycamore Wk, Farsley Pudsey West Yorkshire LS28 5BS",
    "addr:housenumber":"8",
    "addr:postcode":"ls28 5bs",
    "addr:street":"Sycamore Wk;West",
    "iso:country":"GB",
    "sg:address":"8 Sycamore Wk, Farsley",
    "sg:city":"Pudsey",
    "sg:classifiers":[
        {
            "category":"Shopping",
            "subcategory":"Computers & Home Electronics",
            "type":"Retail Goods"
        }
    ],
    "sg:postcode":"LS28 5BS",
    "sg:province":"West Yorkshire",
    "sg:tags":[
        "sound",
        "equipment"
    ],
    "wof:name":"W M Crabtree & Son",
    "wof:placetype":"venue"
},
  "geometry": {"coordinates":[-1.671923995,53.8070030212],"type":"Point"}
}