{
  "type": "Feature",
  "properties": {
    "addr:full":"227 Gosbecks Road Colchester Essex CO1 1BN",
    "addr:housenumber":"227",
    "addr:postcode":"co1 1bn",
    "addr:street":"Gosbecks Road Colchester",
    "iso:country":"GB",
    "sg:address":"227 Gosbecks Road",
    "sg:city":"Colchester",
    "sg:classifiers":[
        {
            "category":"Organizations",
            "subcategory":"Non-profit Organization",
            "type":"Services"
        }
    ],
    "sg:phone":"+44 1206 561877",
    "sg:postcode":"CO1 1BN",
    "sg:province":"Essex",
    "sg:tags":[
        "organisation",
        "voluntary",
        "charity"
    ],
    "wof:name":"Essex Autistic Society",
    "wof:placetype":"venue"
},
  "geometry": {"coordinates":[0.8681650162,51.8681640625],"type":"Point"}
}