{
  "type": "Feature",
  "properties": {
    "iso:country":"GB",
    "sg:address":"102 Burley Rd",
    "sg:city":"Leeds",
    "sg:classifiers":[
        {
            "category":"Bars & Pubs",
            "type":"Food & Drink"
        }
    ],
    "sg:phone":"+44 113 293 1188",
    "sg:postcode":"LS3 1JP",
    "sg:province":"West Yorkshire",
    "sg:tags":[
        "pubs",
        "inn"
    ],
    "wof:name":"Punch Retail (Holdings) Ltd",
    "wof:placetype":"venue"
},
  "geometry": {"coordinates":[-1.56832,53.80434],"type":"Point"}
}