{
  "type": "Feature",
  "properties": {
    "addr:full":"201 Replingham Road London Greater London SW18 5LY",
    "addr:housenumber":"201",
    "addr:postcode":"sw18 5ly",
    "addr:street":"Replingham Road",
    "iso:country":"GB",
    "sg:address":"201 Replingham Road",
    "sg:city":"London",
    "sg:classifiers":[
        {
            "category":"Shopping",
            "subcategory":"Baby Store",
            "type":"Retail Goods"
        }
    ],
    "sg:phone":"+44 20 8875 1228",
    "sg:postcode":"SW18 5LY",
    "sg:province":"Greater London",
    "sg:tags":[
        "babywear",
        "childrens"
    ],
    "wof:name":"Bunnys",
    "wof:placetype":"venue"
},
  "geometry": {"coordinates":[-0.199766,51.445976],"type":"Point"}
}