{
  "type": "Feature",
  "properties": {
    "addr:full":"13 Stone Street Dudley West Midlands DY1 1NS",
    "addr:housenumber":"13",
    "addr:postcode":"dy1 1ns",
    "addr:street":"Stone Street",
    "iso:country":"GB",
    "sg:address":"13 Stone Street",
    "sg:city":"Dudley",
    "sg:classifiers":[
        {
            "category":"Banks & Credit Unions",
            "subcategory":"Financial Services",
            "type":"Services"
        }
    ],
    "sg:phone":"+44 1384 255204",
    "sg:postcode":"DY1 1NS",
    "sg:province":"West Midlands",
    "sg:tags":[
        "building",
        "society"
    ],
    "wof:name":"The Staffordshire",
    "wof:placetype":"venue"
},
  "geometry": {"coordinates":[-2.083807,52.510483],"type":"Point"}
}