{
  "type": "Feature",
  "properties": {
    "iso:country":"GB",
    "sg:address":"Stockport Road West, Ashton Road, Bredbury",
    "sg:city":"Stockport",
    "sg:classifiers":[
        {
            "category":"Autos & Motor Vehicles",
            "subcategory":"Fuel & Gas Station",
            "type":"Retail Goods"
        },
        {
            "category":"Food & Beverages",
            "subcategory":"Supermarket",
            "type":"Retail Goods"
        }
    ],
    "sg:phone":"+44 161 430 6997",
    "sg:postcode":"SK6 2BR",
    "sg:province":"Cheshire",
    "sg:tags":[
        "petrol",
        "filling"
    ],
    "wof:name":"Safeway Filling Station",
    "wof:placetype":"venue"
},
  "geometry": {"coordinates":[-2.132685,53.41674],"type":"Point"}
}