{
  "type": "Feature",
  "properties": {
    "addr:full":"87 Chadwick Avenue, Rednall Birmingham West Midlands B45 8ED",
    "addr:housenumber":"87",
    "addr:postcode":"b45 8ed",
    "addr:street":"Chadwick Avenue",
    "iso:country":"GB",
    "sg:address":"87 Chadwick Avenue, Rednall",
    "sg:city":"Birmingham",
    "sg:classifiers":[
        {
            "category":"Personal",
            "subcategory":"Beauty Salon",
            "type":"Services"
        }
    ],
    "sg:phone":"+44 121 453 2734",
    "sg:postcode":"B45 8ED",
    "sg:province":"West Midlands",
    "sg:tags":[
        "lady",
        "hairdresser"
    ],
    "wof:name":"Hair to Toe",
    "wof:placetype":"venue"
},
  "geometry": {"coordinates":[-2.0076799393,52.3910102844],"type":"Point"}
}