{
  "type": "Feature",
  "properties": {
    "addr:full":"4 Grosvenor Way London Greater London E5 9ND",
    "addr:housenumber":"4",
    "addr:postcode":"e5 9nd",
    "addr:street":"Grosvenor Way",
    "iso:country":"GB",
    "sg:address":"4 Grosvenor Way",
    "sg:city":"London",
    "sg:classifiers":[
        {
            "category":"Shopping",
            "subcategory":"Clothing, Apparel, & Fashions",
            "type":"Retail Goods"
        }
    ],
    "sg:phone":"+44 20 8806 9405",
    "sg:postcode":"E5 9ND",
    "sg:province":"Greater London",
    "sg:tags":[
        "clothing",
        "fabric"
    ],
    "wof:name":"Solarstar Ltd.",
    "wof:placetype":"venue"
},
  "geometry": {"coordinates":[-0.0534979999,51.564743042],"type":"Point"}
}