{
  "type": "Feature",
  "properties": {
    "iso:country":"GB",
    "sg:address":"Stocks Cottage, Munderfield",
    "sg:city":"Bromyard",
    "sg:classifiers":[
        {
            "category":"Building & Trades",
            "subcategory":"Equipment Rental",
            "type":"Services"
        },
        {
            "category":"Building & Trades",
            "subcategory":"Construction",
            "type":"Services"
        }
    ],
    "sg:postcode":"HR7 4JT",
    "sg:province":"Herefordshire",
    "sg:tags":[
        "plant",
        "machinery"
    ],
    "wof:name":"John Poyner",
    "wof:placetype":"venue"
},
  "geometry": {"coordinates":[-2.510399,52.189098],"type":"Point"}
}