{
  "type": "Feature",
  "properties": {
    "iso:country":"GB",
    "sg:address":"Main Street, Robin Hood Bay",
    "sg:city":"Whitby",
    "sg:classifiers":[
        {
            "category":"Food & Beverages",
            "subcategory":"Meat & Fish",
            "type":"Retail Goods"
        }
    ],
    "sg:phone":"+44 1947 880322",
    "sg:postcode":"YO22 4UA",
    "sg:province":"North Yorkshire",
    "sg:tags":[
        "butcher"
    ],
    "wof:name":"T M BARNARD",
    "wof:placetype":"venue"
},
  "geometry": {"coordinates":[-0.54879,54.431],"type":"Point"}
}