{
  "type": "Feature",
  "properties": {
    "addr:full":"41 Poole Rd Sheffield South Yorkshire S9 4JP",
    "addr:housenumber":"41",
    "addr:postcode":"s9 4jp",
    "addr:street":"Poole Rd",
    "iso:country":"GB",
    "sg:address":"41 Poole Rd",
    "sg:city":"Sheffield",
    "sg:classifiers":[
        {
            "category":"Shopping",
            "subcategory":"Department Store",
            "type":"Retail Goods"
        }
    ],
    "sg:phone":"+44 114 243 4755",
    "sg:postcode":"S9 4JP",
    "sg:province":"South Yorkshire",
    "wof:name":"Keiths Korner Shop",
    "wof:placetype":"venue"
},
  "geometry": {"coordinates":[-1.4122970104,53.3830986023],"type":"Point"}
}