{
  "type": "Feature",
  "properties": {
    "addr:full":"Enterprise Ho, Cheney Manor Indstl Est Swindon Wiltshire SN2 2YZ",
    "addr:postcode":"sn2 2yz",
    "addr:street":"Indstl Est",
    "iso:country":"GB",
    "sg:address":"Enterprise Ho, Cheney Manor Indstl Est",
    "sg:city":"Swindon",
    "sg:classifiers":[
        {
            "category":"Professional",
            "subcategory":"Art Services",
            "type":"Services"
        }
    ],
    "sg:phone":"+44 1793 420722",
    "sg:postcode":"SN2 2YZ",
    "sg:province":"Wiltshire",
    "sg:tags":[
        "consultant",
        "design"
    ],
    "wof:name":"P H Designs (U K) Ltd",
    "wof:placetype":"venue"
},
  "geometry": {"coordinates":[-1.808233,51.576378],"type":"Point"}
}