{
  "type": "Feature",
  "properties": {
    "addr:full":"14-16 Gedling St, Sneinton Market Square Nottingham Nottinghamshire NG1 1DS",
    "addr:housenumber":"14-16",
    "addr:postcode":"ng1 1ds",
    "addr:street":"Gedling St;Market Square",
    "iso:country":"GB",
    "sg:address":"14-16 Gedling St, Sneinton Market Square",
    "sg:city":"Nottingham",
    "sg:classifiers":[
        {
            "category":"Deli",
            "type":"Food & Drink"
        }
    ],
    "sg:phone":"+44 115 911 6098",
    "sg:postcode":"NG1 1DS",
    "sg:province":"Nottinghamshire",
    "sg:tags":[
        "delicatessen"
    ],
    "wof:name":"Marche Central",
    "wof:placetype":"venue"
},
  "geometry": {"coordinates":[-1.138899,52.954075],"type":"Point"}
}