{
  "type": "Feature",
  "properties": {
    "addr:full":"Station Road, Seghill Cramlington Northumberland NE23 7EJ",
    "addr:postcode":"ne23 7ej",
    "addr:street":"Station Road",
    "iso:country":"GB",
    "sg:address":"Station Road, Seghill",
    "sg:city":"Cramlington",
    "sg:classifiers":[
        {
            "category":"Shopping",
            "subcategory":"Department Store",
            "type":"Retail Goods"
        }
    ],
    "sg:postcode":"NE23 7EJ",
    "sg:province":"Northumberland",
    "wof:name":"Station House Store",
    "wof:placetype":"venue"
},
  "geometry": {"coordinates":[-1.5499,55.0634],"type":"Point"}
}