{
  "type": "Feature",
  "properties": {
    "iso:country":"GB",
    "sg:address":"2 Staveleigh Way",
    "sg:city":"Ashton-under-lyne",
    "sg:classifiers":[
        {
            "category":"Banks & Credit Unions",
            "subcategory":"Financial Services",
            "type":"Services"
        }
    ],
    "sg:phone":"+44 161 910 0500",
    "sg:postcode":"OL6 7JY",
    "sg:province":"Greater Manchester",
    "sg:tags":[
        "building",
        "society"
    ],
    "wof:name":"Nationwide Building Society",
    "wof:placetype":"venue"
},
  "geometry": {"coordinates":[-2.088242,53.489239],"type":"Point"}
}