{
  "type": "Feature",
  "properties": {
    "iso:country":"GB",
    "sg:address":"17 Green Wrythe Lane",
    "sg:city":"Carshalton",
    "sg:classifiers":[
        {
            "category":"Food & Beverages",
            "subcategory":"Supermarket",
            "type":"Retail Goods"
        }
    ],
    "sg:phone":"+44 20 8647 9499",
    "sg:postcode":"SM5 2DS",
    "sg:province":"Surrey",
    "wof:name":"Londis",
    "wof:placetype":"venue"
},
  "geometry": {"coordinates":[-0.168692,51.372913],"type":"Point"}
}