{
  "type": "Feature",
  "properties": {
    "iso:country":"GB",
    "sg:address":"31 St Judes Road, Englefield Grn",
    "sg:city":"Egham",
    "sg:classifiers":[
        {
            "category":"Personal",
            "subcategory":"Beauty Salon",
            "type":"Services"
        }
    ],
    "sg:phone":"+44 1784 432544",
    "sg:postcode":"TW20 0BY",
    "sg:province":"Surrey",
    "sg:tags":[
        "unisex",
        "hairdresser"
    ],
    "wof:name":"Lloyd Charles Hairdressing",
    "wof:placetype":"venue"
},
  "geometry": {"coordinates":[-0.572624,51.426849],"type":"Point"}
}