{
  "type": "Feature",
  "properties": {
    "addr:full":"204 Baker St Enfield Greater London EN1 3JY",
    "addr:housenumber":"204",
    "addr:postcode":"en1 3jy",
    "addr:street":"Baker St",
    "iso:country":"GB",
    "sg:address":"204 Baker St",
    "sg:city":"Enfield",
    "sg:classifiers":[
        {
            "category":"Shopping",
            "subcategory":"Crafts & Fabrics",
            "type":"Retail Goods"
        }
    ],
    "sg:phone":"+44 20 8363 2201",
    "sg:postcode":"EN1 3JY",
    "sg:province":"Greater London",
    "sg:tags":[
        "shop",
        "needlecraft",
        "wool"
    ],
    "wof:name":"Workbasket The",
    "wof:placetype":"venue"
},
  "geometry": {"coordinates":[-0.0794569999,51.6603507996],"type":"Point"}
}