{
  "type": "Feature",
  "properties": {
    "addr:full":"8 Western Court, Huntley Drive London Greater London N3 1NX",
    "addr:housenumber":"8",
    "addr:postcode":"n3 1nx",
    "addr:street":"Western Court Huntley Drive",
    "iso:country":"GB",
    "sg:address":"8 Western Court, Huntley Drive",
    "sg:city":"London",
    "sg:classifiers":[
        {
            "category":"Professional",
            "subcategory":"Computer Services",
            "type":"Services"
        }
    ],
    "sg:postcode":"N3 1NX",
    "sg:province":"Greater London",
    "sg:tags":[
        "consultant"
    ],
    "wof:name":"Kinetic Information Technology Ltd",
    "wof:placetype":"venue"
},
  "geometry": {"coordinates":[-0.1891800016,51.6083717346],"type":"Point"}
}