{
  "type": "Feature",
  "properties": {
    "addr:full":"29a-29b Church Street, Warsop Mansfield Derbyshire NG20 0AU",
    "addr:housenumber":"29a-29b",
    "addr:postcode":"ng20 0au",
    "addr:street":"Church Street",
    "iso:country":"GB",
    "sg:address":"29a-29b Church Street, Warsop",
    "sg:city":"Mansfield",
    "sg:classifiers":[
        {
            "category":"Home & Garden",
            "subcategory":"Furniture",
            "type":"Retail Goods"
        }
    ],
    "sg:phone":"+44 1623 847686",
    "sg:postcode":"NG20 0AU",
    "sg:province":"Derbyshire",
    "wof:name":"Every Second Counts",
    "wof:placetype":"venue"
},
  "geometry": {"coordinates":[-1.1522740126,53.2073554993],"type":"Point"}
}