{
  "type": "Feature",
  "properties": {
    "iso:country":"GB",
    "sg:address":"143 Victoria Street",
    "sg:city":"London",
    "sg:classifiers":[
        {
            "category":"Professional",
            "subcategory":"Employment Agencies",
            "type":"Services"
        }
    ],
    "sg:phone":"+44 20 7834 1801",
    "sg:postcode":"SW1E 5NH",
    "sg:province":"Greater London",
    "sg:tags":[
        "consultant"
    ],
    "wof:name":"Reed Employment",
    "wof:placetype":"venue"
},
  "geometry": {"coordinates":[-0.1394169927,51.496837616],"type":"Point"}
}