{
  "type": "Feature",
  "properties": {
    "addr:full":"High Lodge Farm, Dale Road, Stanton-by-dale Ilkeston Derbyshire DE7 4PE",
    "addr:postcode":"de7 4pe",
    "addr:street":"Farm Dale Road Stanton-By-Dale",
    "iso:country":"GB",
    "sg:address":"High Lodge Farm, Dale Road, Stanton-by-dale",
    "sg:city":"Ilkeston",
    "sg:classifiers":[
        {
            "category":"Farming",
            "subcategory":"Livestock Farm",
            "type":"Manufacturing & Wholesale Goods"
        }
    ],
    "sg:phone":"+44 115 932 1055",
    "sg:postcode":"DE7 4PE",
    "sg:province":"Derbyshire",
    "sg:tags":[
        "others"
    ],
    "wof:name":"J E Mills",
    "wof:placetype":"venue"
},
  "geometry": {"coordinates":[-1.3111590147,52.9368286133],"type":"Point"}
}