{
  "type": "Feature",
  "properties": {
    "addr:full":"45a Ridgeway Lane Bristol City of Bristol BS14 9PP",
    "addr:housenumber":"45a",
    "addr:postcode":"bs14 9pp",
    "addr:street":"Ridgeway Lane",
    "iso:country":"GB",
    "sg:address":"45a Ridgeway Lane",
    "sg:city":"Bristol",
    "sg:classifiers":[
        {
            "category":"Autos & Motor Vehicles",
            "subcategory":"Automobile Sales",
            "type":"Retail Goods"
        }
    ],
    "sg:phone":"+44 1275 892564",
    "sg:postcode":"BS14 9PP",
    "sg:province":"City of Bristol",
    "sg:tags":[
        "car"
    ],
    "wof:name":"A T Trading",
    "wof:placetype":"venue"
},
  "geometry": {"coordinates":[-2.5636100769,51.4091300964],"type":"Point"}
}