{
  "type": "Feature",
  "properties": {
    "iso:country":"GB",
    "sg:address":"Ginhouse Lane",
    "sg:city":"Rotherham",
    "sg:classifiers":[
        {
            "category":"Freight",
            "type":"Transportation"
        }
    ],
    "sg:phone":"+44 1709 820776",
    "sg:postcode":"S61 4QN",
    "sg:province":"South Yorkshire",
    "sg:tags":[
        "haulage",
        "road"
    ],
    "wof:name":"Dave Balmforth Transport Ltd",
    "wof:placetype":"venue"
},
  "geometry": {"coordinates":[-1.362983,53.44035],"type":"Point"}
}