{
  "type": "Feature",
  "properties": {
    "iso:country":"GB",
    "sg:address":"6 Southgate",
    "sg:city":"Sleaford",
    "sg:classifiers":[
        {
            "category":"Organizations",
            "subcategory":"Community Association",
            "type":"Services"
        },
        {
            "category":"Organizations",
            "subcategory":"Membership Organization",
            "type":"Services"
        }
    ],
    "sg:phone":"+44 1529 303280",
    "sg:postcode":"NG34 7RZ",
    "sg:province":"Lincolnshire",
    "sg:tags":[
        "club",
        "social"
    ],
    "wof:name":"Sleaford & District Legionnaires Club Ltd.",
    "wof:placetype":"venue"
},
  "geometry": {"coordinates":[-0.413209,52.998661],"type":"Point"}
}