{
  "type": "Feature",
  "properties": {
    "iso:country":"GB",
    "sg:address":"43 St Davids Road",
    "sg:city":"Southsea",
    "sg:classifiers":[
        {
            "category":"Professional",
            "subcategory":"Accounting & Tax Preparation",
            "type":"Services"
        }
    ],
    "sg:postcode":"PO5 1QJ",
    "sg:province":"Hampshire",
    "sg:tags":[
        "accountant"
    ],
    "wof:name":"Pamela Fontana & Co",
    "wof:placetype":"venue"
},
  "geometry": {"coordinates":[-1.081989,50.792778],"type":"Point"}
}