{
  "type": "Feature",
  "properties": {
    "iso:country":"GB",
    "sg:address":"Unit 8 Ashtree Retail Park, New Ashtree Street",
    "sg:city":"Wishaw",
    "sg:classifiers":[
        {
            "category":"Shopping",
            "subcategory":"Department Store",
            "type":"Retail Goods"
        }
    ],
    "sg:phone":"+44 1698 356390",
    "sg:postcode":"ML2 7UR",
    "sg:province":"North Lanarkshire",
    "wof:name":"W E W Group Plc",
    "wof:placetype":"venue"
},
  "geometry": {"coordinates":[-3.9208788872,55.7743911743],"type":"Point"}
}