{
  "type": "Feature",
  "properties": {
    "addr:full":"101 Upper Sutton St Birmingham West Midlands B6 5BN",
    "addr:housenumber":"101",
    "addr:postcode":"b6 5bn",
    "addr:street":"Upper Sutton St",
    "iso:country":"GB",
    "sg:address":"101 Upper Sutton St",
    "sg:city":"Birmingham",
    "sg:classifiers":[
        {
            "category":"Shopping",
            "subcategory":"News",
            "type":"Retail Goods"
        }
    ],
    "sg:phone":"+44 121 327 1648",
    "sg:postcode":"B6 5BN",
    "sg:province":"West Midlands",
    "sg:tags":[
        "newsagent"
    ],
    "wof:name":"S.K.Y News",
    "wof:placetype":"venue"
},
  "geometry": {"coordinates":[-1.887628,52.501377],"type":"Point"}
}