{
  "type": "Feature",
  "properties": {
    "iso:country":"GB",
    "sg:address":"St Margarets Farm",
    "sg:city":"Dartford",
    "sg:classifiers":[
        {
            "category":"Structure",
            "subcategory":"Warehouse",
            "type":"Public Place"
        }
    ],
    "sg:phone":"+44 1322 863267",
    "sg:postcode":"DA4 9LB",
    "sg:province":"Kent",
    "wof:name":"South Darenth Farms & Cold Store Co. Ltd.",
    "wof:placetype":"venue"
},
  "geometry": {"coordinates":[0.257957,51.407398],"type":"Point"}
}