{
  "type": "Feature",
  "properties": {
    "iso:country":"GB",
    "sg:address":"Chalcraft Lane",
    "sg:city":"Bognor Regis",
    "sg:classifiers":[
        {
            "category":"Home & Garden",
            "subcategory":"Garden Supply",
            "type":"Retail Goods"
        },
        {
            "category":"Wholesale",
            "subcategory":"Construction Materials",
            "type":"Manufacturing & Wholesale Goods"
        }
    ],
    "sg:phone":"+44 1243 842660",
    "sg:postcode":"PO21 5UA",
    "sg:province":"West Sussex",
    "sg:tags":[
        "water",
        "supplier",
        "aquarium",
        "pond"
    ],
    "wof:name":"Tropikoi Aquatic Centre",
    "wof:placetype":"venue"
},
  "geometry": {"coordinates":[-0.704805,50.792217],"type":"Point"}
}