{
  "type": "Feature",
  "properties": {
    "addr:full":"24 Queens Rd Stonehaven Aberdeenshire AB39 2HQ",
    "addr:housenumber":"24",
    "addr:postcode":"ab39 2hq",
    "addr:street":"Queens Rd",
    "iso:country":"GB",
    "sg:address":"24 Queens Rd",
    "sg:city":"Stonehaven",
    "sg:classifiers":[
        {
            "category":"Professional",
            "subcategory":"Computer Services",
            "type":"Services"
        }
    ],
    "sg:phone":"+44 1569 762454",
    "sg:postcode":"AB39 2HQ",
    "sg:province":"Aberdeenshire",
    "sg:tags":[
        "system",
        "software"
    ],
    "wof:name":"Axeon Ltd",
    "wof:placetype":"venue"
},
  "geometry": {"coordinates":[-2.2242391109,56.959980011],"type":"Point"}
}