{
  "type": "Feature",
  "properties": {
    "addr:full":"Pride House, Redfern Park Way, Tysley Birmingham West Midlands B11 2BF",
    "addr:postcode":"b11 2bf",
    "addr:street":"Redfern Park Way",
    "iso:country":"GB",
    "sg:address":"Pride House, Redfern Park Way, Tysley",
    "sg:city":"Birmingham",
    "sg:classifiers":[
        {
            "category":"Communications",
            "subcategory":"Film & Video Production",
            "type":"Services"
        }
    ],
    "sg:phone":"+44 121 706 2020",
    "sg:postcode":"B11 2BF",
    "sg:province":"West Midlands",
    "sg:tags":[
        "pr",
        "telemarketing"
    ],
    "wof:name":"Parade Telemarketing Ltd.",
    "wof:placetype":"venue"
},
  "geometry": {"coordinates":[-1.834549,52.455952],"type":"Point"}
}