{
  "type": "Feature",
  "properties": {
    "iso:country":"GB",
    "sg:address":"77 Abergele Road",
    "sg:city":"Colwyn Bay",
    "sg:classifiers":[
        {
            "category":"Home & Garden",
            "subcategory":"Furniture",
            "type":"Retail Goods"
        }
    ],
    "sg:postcode":"LL29 7RU",
    "sg:province":"Conwy",
    "wof:name":"Classic Suites & Beds",
    "wof:placetype":"venue"
},
  "geometry": {"coordinates":[-3.723577,53.293285],"type":"Point"}
}