{
  "type": "Feature",
  "properties": {
    "addr:full":"195 Warrington Road, Whiston Prescot Cheshire L35 5AF",
    "addr:housenumber":"195",
    "addr:postcode":"l35 5af",
    "addr:street":"Warrington Road",
    "iso:country":"GB",
    "sg:address":"195 Warrington Road, Whiston",
    "sg:city":"Prescot",
    "sg:classifiers":[
        {
            "category":"Food & Beverages",
            "subcategory":"Liquor & Beverages",
            "type":"Retail Goods"
        }
    ],
    "sg:phone":"+44 151 430 8316",
    "sg:postcode":"L35 5AF",
    "sg:province":"Cheshire",
    "sg:tags":[
        "beer",
        "spirit",
        "wines"
    ],
    "wof:name":"Victoria Wine",
    "wof:placetype":"venue"
},
  "geometry": {"coordinates":[-2.7881009579,53.4233818054],"type":"Point"}
}