{
  "type": "Feature",
  "properties": {
    "addr:full":"West Road, Nottage Porthcawl Bridgend CF36 3SN",
    "addr:postcode":"cf36 3sn",
    "addr:street":"West Road",
    "iso:country":"GB",
    "sg:address":"West Road, Nottage",
    "sg:city":"Porthcawl",
    "sg:classifiers":[
        {
            "category":"Education",
            "subcategory":"School",
            "type":"Public Place"
        }
    ],
    "sg:phone":"+44 1656 782719",
    "sg:postcode":"CF36 3SN",
    "sg:province":"Bridgend",
    "sg:tags":[
        "local",
        "authority"
    ],
    "wof:name":"West Park Primary School",
    "wof:placetype":"venue"
},
  "geometry": {"coordinates":[-3.701474905,51.4901542664],"type":"Point"}
}