{
  "type": "Feature",
  "properties": {
    "addr:full":"Welwyn Hatfield, Comm Wing Parkway Welwyn Garden City Hertfordshire AL8 6JD",
    "addr:postcode":"al8 6jd",
    "addr:street":"Wing Parkway",
    "iso:country":"GB",
    "sg:address":"Welwyn Hatfield, Comm Wing Parkway",
    "sg:city":"Welwyn Garden City",
    "sg:classifiers":[
        {
            "category":"Organizations",
            "subcategory":"Non-profit Organization",
            "type":"Services"
        }
    ],
    "sg:phone":"+44 1707 390060",
    "sg:postcode":"AL8 6JD",
    "sg:province":"Hertfordshire",
    "sg:tags":[
        "organisation",
        "voluntary",
        "charity"
    ],
    "wof:name":"Jobmate Link",
    "wof:placetype":"venue"
},
  "geometry": {"coordinates":[-0.2057289928,51.8014297485],"type":"Point"}
}