{
  "type": "Feature",
  "properties": {
    "iso:country":"GB",
    "sg:address":"652 Preston Rd, Clayton-le-woods",
    "sg:city":"Chorley",
    "sg:classifiers":[
        {
            "category":"Health Services",
            "subcategory":"Doctor",
            "type":"Services"
        }
    ],
    "sg:phone":"+44 1772 323021",
    "sg:postcode":"PR6 7EH",
    "sg:province":"Lancashire",
    "sg:tags":[
        "practitioners"
    ],
    "wof:name":"Dr E.S.M Dawoud",
    "wof:placetype":"venue"
},
  "geometry": {"coordinates":[-2.639739,53.704578],"type":"Point"}
}