{
  "type": "Feature",
  "properties": {
    "addr:full":"Portland House, Unit 20 Portland Business Park, Handsworth Sheffield South Yorkshire S13 8HS",
    "addr:housenumber":"unit 20",
    "addr:postcode":"s13 8hs",
    "addr:street":"Portland Business Park",
    "iso:country":"GB",
    "sg:address":"Portland House, Unit 20 Portland Business Park, Handsworth",
    "sg:city":"Sheffield",
    "sg:classifiers":[
        {
            "category":"Wholesale",
            "subcategory":"Non-durable Goods",
            "type":"Manufacturing & Wholesale Goods"
        }
    ],
    "sg:phone":"+44 114 261 0000",
    "sg:postcode":"S13 8HS",
    "sg:province":"South Yorkshire",
    "sg:tags":[
        "carry",
        "cash"
    ],
    "wof:name":"Big City Discounts Ltd.",
    "wof:placetype":"venue"
},
  "geometry": {"coordinates":[-1.4645440578,53.3831100464],"type":"Point"}
}