{
  "type": "Feature",
  "properties": {
    "addr:full":"The Veterinary Surgery, Victoria Terr Turriff Aberdeenshire AB53 4EE",
    "addr:postcode":"ab53 4ee",
    "addr:street":"Victoria Terr",
    "iso:country":"GB",
    "sg:address":"The Veterinary Surgery, Victoria Terr",
    "sg:city":"Turriff",
    "sg:classifiers":[
        {
            "category":"Retail",
            "subcategory":"Veterinary Services",
            "type":"Services"
        }
    ],
    "sg:phone":"+44 1888 563217",
    "sg:postcode":"AB53 4EE",
    "sg:province":"Aberdeenshire",
    "sg:tags":[
        "surgeon"
    ],
    "wof:name":"W Sleigh",
    "wof:placetype":"venue"
},
  "geometry": {"coordinates":[-2.455229044,57.5399017334],"type":"Point"}
}