{
  "type": "Feature",
  "properties": {
    "addr:full":"99 Coleridge Close Hitchin Hertfordshire SG4 0QY",
    "addr:housenumber":"99",
    "addr:postcode":"sg4 0qy",
    "addr:street":"Coleridge Close",
    "iso:country":"GB",
    "sg:address":"99 Coleridge Close",
    "sg:city":"Hitchin",
    "sg:classifiers":[
        {
            "category":"Freight",
            "type":"Transportation"
        }
    ],
    "sg:phone":"+44 1462 455377",
    "sg:postcode":"SG4 0QY",
    "sg:province":"Hertfordshire",
    "sg:tags":[
        "haulage",
        "road"
    ],
    "wof:name":"Mead Haulage",
    "wof:placetype":"venue"
},
  "geometry": {"coordinates":[-0.256862,51.951729],"type":"Point"}
}