{
  "type": "Feature",
  "properties": {
    "addr:full":"29-35 School Road, Tilehurst Reading Berkshire RG31 5AR",
    "addr:housenumber":"29-35",
    "addr:postcode":"rg31 5ar",
    "addr:street":"School Road",
    "iso:country":"GB",
    "sg:address":"29-35 School Road, Tilehurst",
    "sg:city":"Reading",
    "sg:classifiers":[
        {
            "category":"Food & Beverages",
            "subcategory":"Supermarket",
            "type":"Retail Goods"
        }
    ],
    "sg:phone":"+44 118 942 3361",
    "sg:postcode":"RG31 5AR",
    "sg:province":"Berkshire",
    "wof:name":"Co-Operative Pioneer",
    "wof:placetype":"venue"
},
  "geometry": {"coordinates":[-1.0400320292,51.4583091736],"type":"Point"}
}