{
  "type": "Feature",
  "properties": {
    "addr:full":"Somerset House, 7-49 London Road Redhill Surrey RH1 1LU",
    "addr:housenumber":"7-49",
    "addr:postcode":"rh1 1lu",
    "addr:street":"London Road",
    "iso:country":"GB",
    "sg:address":"Somerset House, 7-49 London Road",
    "sg:city":"Redhill",
    "sg:classifiers":[
        {
            "category":"Professional",
            "subcategory":"Engineering",
            "type":"Services"
        }
    ],
    "sg:phone":"+44 1737 784550",
    "sg:postcode":"RH1 1LU",
    "sg:province":"Surrey",
    "sg:tags":[
        "consulting",
        "engineer"
    ],
    "wof:name":"D H V International (U K) Ltd.",
    "wof:placetype":"venue"
},
  "geometry": {"coordinates":[-0.1677239984,51.2416343689],"type":"Point"}
}