{
  "type": "Feature",
  "properties": {
    "addr:full":"Collingswood Road, Bushbury Wolverhampton Staffordshire WV10 6RS",
    "addr:postcode":"wv10 6rs",
    "addr:street":"Collingswood Road",
    "iso:country":"GB",
    "sg:address":"Collingswood Road, Bushbury",
    "sg:city":"Wolverhampton",
    "sg:classifiers":[
        {
            "category":"Bars & Pubs",
            "type":"Food & Drink"
        }
    ],
    "sg:phone":"+44 1902 783226",
    "sg:postcode":"WV10 6RS",
    "sg:province":"Staffordshire",
    "sg:tags":[
        "pubs",
        "inn"
    ],
    "wof:name":"Staffordshire Volunteer",
    "wof:placetype":"venue"
},
  "geometry": {"coordinates":[-2.121669054,52.5886497498],"type":"Point"}
}