{
  "type": "Feature",
  "properties": {
    "addr:full":"3 Well Road, Pagham Bognor Regis West Sussex PO21 4SR",
    "addr:housenumber":"3",
    "addr:postcode":"po21 4sr",
    "addr:street":"Well Road",
    "iso:country":"GB",
    "sg:address":"3 Well Road, Pagham",
    "sg:city":"Bognor Regis",
    "sg:classifiers":[
        {
            "category":"Building & Trades",
            "subcategory":"Construction",
            "type":"Services"
        }
    ],
    "sg:phone":"+44 1243 265496",
    "sg:postcode":"PO21 4SR",
    "sg:province":"West Sussex",
    "sg:tags":[
        "roofing"
    ],
    "wof:name":"Parker & Nunn",
    "wof:placetype":"venue"
},
  "geometry": {"coordinates":[-0.739983,50.76862],"type":"Point"}
}