{
  "type": "Feature",
  "properties": {
    "addr:full":"1a Green Close, Brookmans Park Hatfield Hertfordshire AL9 7ST",
    "addr:housenumber":"1a",
    "addr:postcode":"al9 7st",
    "addr:street":"Green Close",
    "iso:country":"GB",
    "sg:address":"1a Green Close, Brookmans Park",
    "sg:city":"Hatfield",
    "sg:classifiers":[
        {
            "category":"Professional",
            "subcategory":"Business Services",
            "type":"Services"
        }
    ],
    "sg:phone":"+44 1707 649604",
    "sg:postcode":"AL9 7ST",
    "sg:province":"Hertfordshire",
    "sg:tags":[
        "distributor",
        "film"
    ],
    "wof:name":"Herts Film Services",
    "wof:placetype":"venue"
},
  "geometry": {"coordinates":[-0.203395,51.722069],"type":"Point"}
}