{
  "type": "Feature",
  "properties": {
    "addr:full":"Unit 16 The Railway Enterprise Centre, Shelton New Rd Stoke-on-trent Staffordshire ST4 7SH",
    "addr:housenumber":"unit 16;railway;centre",
    "addr:postcode":"st4 7sh",
    "addr:street":"The;New Rd",
    "iso:country":"GB",
    "sg:address":"Unit 16 The Railway Enterprise Centre, Shelton New Rd",
    "sg:city":"Stoke-on-trent",
    "sg:classifiers":[
        {
            "category":"Wholesale",
            "subcategory":"Non-durable Goods",
            "type":"Manufacturing & Wholesale Goods"
        }
    ],
    "sg:postcode":"ST4 7SH",
    "sg:province":"Staffordshire",
    "sg:tags":[
        "carry",
        "cash"
    ],
    "wof:name":"Lea Forge Investments Ltd",
    "wof:placetype":"venue"
},
  "geometry": {"coordinates":[-2.19351,53.013519],"type":"Point"}
}