{
  "type": "Feature",
  "properties": {
    "addr:full":"Brook Farm, Tortworth Wotton-under-edge Gloucestershire GL12 8BS",
    "addr:postcode":"gl12 8bs",
    "addr:street":"Brook",
    "iso:country":"GB",
    "sg:address":"Brook Farm, Tortworth",
    "sg:city":"Wotton-under-edge",
    "sg:classifiers":[
        {
            "category":"Farming",
            "subcategory":"Livestock Farm",
            "type":"Manufacturing & Wholesale Goods"
        }
    ],
    "sg:phone":"+44 1454 260263",
    "sg:postcode":"GL12 8BS",
    "sg:province":"Gloucestershire",
    "sg:tags":[
        "others"
    ],
    "wof:name":"A H Hook & Sons",
    "wof:placetype":"venue"
},
  "geometry": {"coordinates":[-2.4297571182,51.6373443604],"type":"Point"}
}