{
  "type": "Feature",
  "properties": {
    "iso:country":"GB",
    "sg:address":"480a Mansfield Road",
    "sg:city":"Nottingham",
    "sg:classifiers":[
        {
            "category":"Social Services",
            "subcategory":"Retirement Home",
            "type":"Services"
        }
    ],
    "sg:postcode":"NG5 2EL",
    "sg:province":"Nottinghamshire",
    "sg:tags":[
        "care"
    ],
    "wof:name":"Helping Hands Home Care",
    "wof:placetype":"venue"
},
  "geometry": {"coordinates":[-1.147945,52.978588],"type":"Point"}
}