{
  "type": "Feature",
  "properties": {
    "addr:full":"64 High Street, Cheshunt Waltham Cross Essex EN8 0AH",
    "addr:housenumber":"64",
    "addr:postcode":"en8 0ah",
    "addr:street":"High Street",
    "iso:country":"GB",
    "sg:address":"64 High Street, Cheshunt",
    "sg:city":"Waltham Cross",
    "sg:classifiers":[
        {
            "category":"Shopping",
            "subcategory":"Florist",
            "type":"Retail Goods"
        }
    ],
    "sg:phone":"+44 1992 624848",
    "sg:postcode":"EN8 0AH",
    "sg:province":"Essex",
    "wof:name":"John & Susan Bullock",
    "wof:placetype":"venue"
},
  "geometry": {"coordinates":[-0.0355480015,51.7096824646],"type":"Point"}
}