{
  "type": "Feature",
  "properties": {
    "addr:full":"6a St Annes Road Worcester Worcestershire WR3 7PE",
    "addr:housenumber":"6a",
    "addr:postcode":"wr3 7pe",
    "addr:street":"St Annes Road",
    "iso:country":"GB",
    "sg:address":"6a St Annes Road",
    "sg:city":"Worcester",
    "sg:classifiers":[
        {
            "category":"Shopping",
            "subcategory":"News",
            "type":"Retail Goods"
        }
    ],
    "sg:postcode":"WR3 7PE",
    "sg:province":"Worcestershire",
    "sg:tags":[
        "newsagent"
    ],
    "wof:name":"L J & V Ingram",
    "wof:placetype":"venue"
},
  "geometry": {"coordinates":[-2.223997,52.219868],"type":"Point"}
}