{
  "type": "Feature",
  "properties": {
    "addr:full":"29 Rushmere Place Haverhill Essex CB9 0HY",
    "addr:housenumber":"29",
    "addr:postcode":"cb9 0hy",
    "addr:street":"Rushmere Place",
    "iso:country":"GB",
    "sg:address":"29 Rushmere Place",
    "sg:city":"Haverhill",
    "sg:classifiers":[
        {
            "category":"Utilities",
            "subcategory":"Natural Gas",
            "type":"Services"
        }
    ],
    "sg:phone":"+44 1440 707964",
    "sg:postcode":"CB9 0HY",
    "sg:province":"Essex",
    "sg:tags":[
        "control",
        "energy",
        "management",
        "system"
    ],
    "wof:name":"T.H McNally",
    "wof:placetype":"venue"
},
  "geometry": {"coordinates":[0.447585,52.083172],"type":"Point"}
}