{
  "type": "Feature",
  "properties": {
    "addr:full":"39 Birmingham Street Smethwick West Midlands B69 4DY",
    "addr:housenumber":"39",
    "addr:postcode":"b69 4dy",
    "addr:street":"Birmingham Street",
    "iso:country":"GB",
    "sg:address":"39 Birmingham Street",
    "sg:city":"Smethwick",
    "sg:classifiers":[
        {
            "category":"Shopping",
            "subcategory":"News",
            "type":"Retail Goods"
        }
    ],
    "sg:phone":"+44 121 552 2142",
    "sg:postcode":"B69 4DY",
    "sg:province":"West Midlands",
    "sg:tags":[
        "newsagent"
    ],
    "wof:name":"R S News",
    "wof:placetype":"venue"
},
  "geometry": {"coordinates":[-2.0138,52.502899],"type":"Point"}
}