{
  "type": "Feature",
  "properties": {
    "addr:full":"533 Stanhope Rd South Shields Tyne and Wear NE33 4QX",
    "addr:housenumber":"533",
    "addr:postcode":"ne33 4qx",
    "addr:street":"Stanhope Rd",
    "iso:country":"GB",
    "sg:address":"533 Stanhope Rd",
    "sg:city":"South Shields",
    "sg:classifiers":[
        {
            "category":"Wholesale",
            "subcategory":"Fruits & Vegetables",
            "type":"Manufacturing & Wholesale Goods"
        }
    ],
    "sg:phone":"+44 191 454 2891",
    "sg:postcode":"NE33 4QX",
    "sg:province":"Tyne and Wear",
    "wof:name":"D & M Barlow",
    "wof:placetype":"venue"
},
  "geometry": {"coordinates":[-1.4399960041,54.9746131897],"type":"Point"}
}