{
  "type": "Feature",
  "properties": {
    "addr:full":"22 The Bridges, Wearside Sunderland Tyne and Wear SR1 3LB",
    "addr:housenumber":"22",
    "addr:postcode":"sr1 3lb",
    "addr:street":"The;Wearside",
    "iso:country":"GB",
    "sg:address":"22 The Bridges, Wearside",
    "sg:city":"Sunderland",
    "sg:classifiers":[
        {
            "category":"Shopping",
            "subcategory":"News",
            "type":"Retail Goods"
        }
    ],
    "sg:phone":"+44 191 514 0883",
    "sg:postcode":"SR1 3LB",
    "sg:province":"Tyne and Wear",
    "sg:tags":[
        "newsagent"
    ],
    "wof:name":"Martin Newsagents",
    "wof:placetype":"venue"
},
  "geometry": {"coordinates":[-1.388749,54.904652],"type":"Point"}
}