{
  "type": "Feature",
  "properties": {
    "addr:full":"2 Conway Avenue, Cleveleys Thornton-cleveleys Lancashire FY5 3JH",
    "addr:housenumber":"2",
    "addr:postcode":"fy5 3jh",
    "addr:street":"Conway Avenue Cleveleys Thornton-Cleveleys",
    "iso:country":"GB",
    "sg:address":"2 Conway Avenue, Cleveleys",
    "sg:city":"Thornton-cleveleys",
    "sg:classifiers":[
        {
            "category":"Social Services",
            "subcategory":"Retirement Home",
            "type":"Services"
        }
    ],
    "sg:phone":"+44 1253 852319",
    "sg:postcode":"FY5 3JH",
    "sg:province":"Lancashire",
    "sg:tags":[
        "rest"
    ],
    "wof:name":"Balmoral Residental Home",
    "wof:placetype":"venue"
},
  "geometry": {"coordinates":[-3.0428249836,53.8745880127],"type":"Point"}
}