{
  "type": "Feature",
  "properties": {
    "iso:country":"GB",
    "sg:address":"412 Manchester Road",
    "sg:city":"Stockport",
    "sg:classifiers":[
        {
            "category":"Personal",
            "subcategory":"Barber",
            "type":"Services"
        }
    ],
    "sg:phone":"+44 161 443 2008",
    "sg:postcode":"SK4 5BY",
    "sg:province":"Cheshire",
    "sg:tags":[
        "men's",
        "hairdresser"
    ],
    "wof:name":"Tony's Barber Shop",
    "wof:placetype":"venue"
},
  "geometry": {"coordinates":[-2.174768,53.428257],"type":"Point"}
}