{
  "type": "Feature",
  "properties": {
    "addr:full":"Crittenden House, Crittneden Road, Matfield Tonbridge Kent TN12 7EN",
    "addr:postcode":"tn12 7en",
    "addr:street":"Crittneden Road",
    "iso:country":"GB",
    "sg:address":"Crittenden House, Crittneden Road, Matfield",
    "sg:city":"Tonbridge",
    "sg:classifiers":[
        {
            "category":"Insurance",
            "subcategory":"Health Insurance",
            "type":"Services"
        }
    ],
    "sg:phone":"+44 1892 838124",
    "sg:postcode":"TN12 7EN",
    "sg:province":"Kent",
    "wof:name":"Berwick Devoil Healthcare Ltd.",
    "wof:placetype":"venue"
},
  "geometry": {"coordinates":[0.36967,51.164967],"type":"Point"}
}