{
  "type": "Feature",
  "properties": {
    "iso:country":"GB",
    "sg:address":"7 Woodcote Drive, Upton",
    "sg:city":"Poole",
    "sg:classifiers":[
        {
            "category":"Building & Trades",
            "subcategory":"Landscaping Services",
            "type":"Services"
        }
    ],
    "sg:phone":"+44 1202 631666",
    "sg:postcode":"BH16 5RA",
    "sg:province":"Dorset",
    "sg:tags":[
        "irrigation",
        "system"
    ],
    "wof:name":"Apple Landscapes",
    "wof:placetype":"venue"
},
  "geometry": {"coordinates":[-2.0316400528,50.7357788086],"type":"Point"}
}