{
  "type": "Feature",
  "properties": {
    "addr:full":"Sion House, Birchanger Lane, Birchanger Bishop's Stortford Essex CM23 5PU",
    "addr:postcode":"cm23 5pu",
    "addr:street":"Birchanger Lane;Bishop'S",
    "iso:country":"GB",
    "sg:address":"Sion House, Birchanger Lane, Birchanger",
    "sg:city":"Bishop's Stortford",
    "sg:classifiers":[
        {
            "category":"Conference Center",
            "type":"Public Place"
        }
    ],
    "sg:phone":"+44 1279 813276",
    "sg:postcode":"CM23 5PU",
    "sg:province":"Essex",
    "sg:tags":[
        "business",
        "centre"
    ],
    "wof:name":"Sion Park",
    "wof:placetype":"venue"
},
  "geometry": {"coordinates":[0.18558,51.889702],"type":"Point"}
}