{
  "type": "Feature",
  "properties": {
    "iso:country":"GB",
    "sg:address":"226 High Street",
    "sg:city":"Dalkeith",
    "sg:classifiers":[
        {
            "category":"Professional",
            "type":"Services"
        }
    ],
    "sg:phone":"+44 131 660 4430",
    "sg:postcode":"EH22 1AZ",
    "sg:province":"City of Edinburgh",
    "sg:tags":[
        "shopfitters"
    ],
    "wof:name":"Watco Design Ltd.",
    "wof:placetype":"venue"
},
  "geometry": {"coordinates":[-3.066618,55.897099],"type":"Point"}
}