{
  "type": "Feature",
  "properties": {
    "iso:country":"GB",
    "sg:address":"136 Commercial Road",
    "sg:city":"Newport",
    "sg:classifiers":[
        {
            "category":"Shopping",
            "type":"Retail Goods"
        }
    ],
    "sg:postcode":"NP20 2PH",
    "sg:province":"Newport",
    "sg:tags":[
        "part",
        "accessory"
    ],
    "wof:name":"Gwent Vw-Audi Centre",
    "wof:placetype":"venue"
},
  "geometry": {"coordinates":[-2.988814,51.577217],"type":"Point"}
}