{
  "type": "Feature",
  "properties": {
    "iso:country":"GB",
    "sg:address":"88 Fabis Drive, Clifton Grove",
    "sg:city":"Nottingham",
    "sg:classifiers":[
        {
            "category":"Building & Trades",
            "subcategory":"Construction",
            "type":"Services"
        }
    ],
    "sg:phone":"+44 115 984 2219",
    "sg:postcode":"NG11 8NZ",
    "sg:province":"Nottinghamshire",
    "sg:tags":[
        "decorator",
        "painter"
    ],
    "wof:name":"Allied Painters & Decorators",
    "wof:placetype":"venue"
},
  "geometry": {"coordinates":[-1.182667,52.915417],"type":"Point"}
}