{
  "type": "Feature",
  "properties": {
    "addr:full":"Unit 9 Weston Business Park, The Airport Weston Super Mare Somerset BS24 8RA",
    "addr:housenumber":"unit 9",
    "addr:postcode":"bs24 8ra",
    "addr:street":"Weston Business Park The Airport Weston",
    "iso:country":"GB",
    "sg:address":"Unit 9 Weston Business Park, The Airport",
    "sg:city":"Weston Super Mare",
    "sg:classifiers":[
        {
            "category":"Communications",
            "type":"Services"
        }
    ],
    "sg:phone":"+44 1934 415082",
    "sg:postcode":"BS24 8RA",
    "sg:province":"Somerset",
    "sg:tags":[
        "data",
        "network"
    ],
    "wof:name":"Acelec Installations",
    "wof:placetype":"venue"
},
  "geometry": {"coordinates":[-2.9287769794,51.3386573792],"type":"Point"}
}