{
  "type": "Feature",
  "properties": {
    "iso:country":"GB",
    "sg:address":"The Forge, Ashton",
    "sg:city":"Callington",
    "sg:classifiers":[
        {
            "category":"Communications",
            "subcategory":"Film & Video Production",
            "type":"Services"
        }
    ],
    "sg:postcode":"PL17 8AQ",
    "sg:province":"Cornwall",
    "sg:tags":[
        "illustrator",
        "artist"
    ],
    "wof:name":"Colloggett Ceramics",
    "wof:placetype":"venue"
},
  "geometry": {"coordinates":[-4.278927803,50.4926490784],"type":"Point"}
}