{
  "type": "Feature",
  "properties": {
    "iso:country":"GB",
    "sg:address":"Kilbride Container Store, Nicolson Way",
    "sg:city":"Burton-on-trent",
    "sg:classifiers":[
        {
            "category":"Freight",
            "type":"Transportation"
        },
        {
            "category":"Retail",
            "subcategory":"Storage",
            "type":"Services"
        }
    ],
    "sg:phone":"+44 1283 515633",
    "sg:postcode":"DE14 2AW",
    "sg:province":"Derbyshire",
    "sg:tags":[
        "haulage",
        "household",
        "road",
        "removal"
    ],
    "wof:name":"Premier Removals",
    "wof:placetype":"venue"
},
  "geometry": {"coordinates":[-1.647701025,52.8043518066],"type":"Point"}
}