{
  "type": "Feature",
  "properties": {
    "addr:full":"The Common, Abberley Worcester Herefordshire WR6 6AY",
    "addr:postcode":"wr6 6ay",
    "addr:street":"The Common",
    "iso:country":"GB",
    "sg:address":"The Common, Abberley",
    "sg:city":"Worcester",
    "sg:classifiers":[
        {
            "category":"Government",
            "subcategory":"Post Office",
            "type":"Public Place"
        }
    ],
    "sg:phone":"+44 1299 896213",
    "sg:postcode":"WR6 6AY",
    "sg:province":"Herefordshire",
    "wof:name":"Abberley Sub Post Office",
    "wof:placetype":"venue"
},
  "geometry": {"coordinates":[-2.3742539883,52.3078804016],"type":"Point"}
}