{
  "type": "Feature",
  "properties": {
    "addr:full":"19 Greaves Road High Wycombe Buckinghamshire HP13 7JU",
    "addr:housenumber":"19",
    "addr:postcode":"hp13 7ju",
    "addr:street":"Greaves Road",
    "iso:country":"GB",
    "sg:address":"19 Greaves Road",
    "sg:city":"High Wycombe",
    "sg:classifiers":[
        {
            "category":"Professional",
            "type":"Services"
        }
    ],
    "sg:phone":"+44 7956 564715",
    "sg:postcode":"HP13 7JU",
    "sg:province":"Buckinghamshire",
    "sg:tags":[
        "entertainer"
    ],
    "wof:name":"Trevor Smith's Animal World",
    "wof:placetype":"venue"
},
  "geometry": {"coordinates":[-0.732693,51.627338],"type":"Point"}
}