{
  "type": "Feature",
  "properties": {
    "iso:country":"GB",
    "sg:address":"36 Portman Road",
    "sg:city":"Melksham",
    "sg:classifiers":[
        {
            "category":"Building & Trades",
            "subcategory":"Construction",
            "type":"Services"
        }
    ],
    "sg:phone":"+44 1225 791671",
    "sg:postcode":"SN12 8AW",
    "sg:province":"Wiltshire",
    "sg:tags":[
        "builder"
    ],
    "wof:name":"Stephen L Turks",
    "wof:placetype":"venue"
},
  "geometry": {"coordinates":[-2.140302,51.381172],"type":"Point"}
}