{
  "type": "Feature",
  "properties": {
    "addr:full":"16 John Street Tunbridge Wells Kent TN4 9RU",
    "addr:housenumber":"16",
    "addr:postcode":"tn4 9ru",
    "addr:street":"John Street",
    "iso:country":"GB",
    "sg:address":"16 John Street",
    "sg:city":"Tunbridge Wells",
    "sg:classifiers":[
        {
            "category":"Manufacturing",
            "subcategory":"Wood Products",
            "type":"Manufacturing & Wholesale Goods"
        }
    ],
    "sg:phone":"+44 1892 510023",
    "sg:postcode":"TN4 9RU",
    "sg:province":"Kent",
    "sg:tags":[
        "packaging",
        "crate",
        "pallets"
    ],
    "wof:name":"Alcan Packaging (Uk Sales) Ltd.",
    "wof:placetype":"venue"
},
  "geometry": {"coordinates":[0.259806,51.141098],"type":"Point"}
}