{
  "type": "Feature",
  "properties": {
    "addr:full":"35 Bradford Road, Idle Bradford West Yorkshire BD10 9PB",
    "addr:housenumber":"35",
    "addr:postcode":"bd10 9pb",
    "addr:street":"Bradford Road",
    "iso:country":"GB",
    "sg:address":"35 Bradford Road, Idle",
    "sg:city":"Bradford",
    "sg:classifiers":[
        {
            "category":"Banks & Credit Unions",
            "subcategory":"Financial Services",
            "type":"Services"
        }
    ],
    "sg:phone":"+44 1274 614700",
    "sg:postcode":"BD10 9PB",
    "sg:province":"West Yorkshire",
    "sg:tags":[
        "consultant"
    ],
    "wof:name":"Airevalley Mortgages",
    "wof:placetype":"venue"
},
  "geometry": {"coordinates":[-1.730492,53.834145],"type":"Point"}
}