{
  "type": "Feature",
  "properties": {
    "iso:country":"GB",
    "sg:address":"Hazelmere Road, Creswell",
    "sg:city":"Worksop",
    "sg:classifiers":[
        {
            "category":"Travel",
            "subcategory":"Hotels & Motels",
            "type":"Entertainment"
        },
        {
            "category":"Farming",
            "subcategory":"Farm",
            "type":"Manufacturing & Wholesale Goods"
        }
    ],
    "sg:phone":"+44 1909 721258",
    "sg:postcode":"S80 4HS",
    "sg:province":"Nottinghamshire",
    "sg:tags":[
        "mixed",
        "house",
        "guest",
        "crop"
    ],
    "wof:name":"Janet Platts",
    "wof:placetype":"venue"
},
  "geometry": {"coordinates":[-1.217444,53.26239],"type":"Point"}
}