{
  "type": "Feature",
  "properties": {
    "addr:full":"104 New Chester Road Wirral Cheshire CH62 5AG",
    "addr:housenumber":"104",
    "addr:postcode":"ch62 5ag",
    "addr:street":"New Chester Road",
    "iso:country":"GB",
    "sg:address":"104 New Chester Road",
    "sg:city":"Wirral",
    "sg:classifiers":[
        {
            "category":"Shopping",
            "subcategory":"News",
            "type":"Retail Goods"
        }
    ],
    "sg:postcode":"CH62 5AG",
    "sg:province":"Cheshire",
    "sg:tags":[
        "newsagent"
    ],
    "wof:name":"Froggett,Gerald W, & D,",
    "wof:placetype":"venue"
},
  "geometry": {"coordinates":[-2.997138,53.360363],"type":"Point"}
}