{
  "type": "Feature",
  "properties": {
    "iso:country":"GB",
    "sg:address":"118 Burton Road",
    "sg:city":"Manchester",
    "sg:classifiers":[
        {
            "category":"Fast Food",
            "type":"Food & Drink"
        }
    ],
    "sg:phone":"+44 161 445 6193",
    "sg:postcode":"M20 1LP",
    "sg:province":"Greater Manchester",
    "sg:tags":[
        "away",
        "meal",
        "outlet",
        "take"
    ],
    "wof:name":"KISMET",
    "wof:placetype":"venue"
},
  "geometry": {"coordinates":[-2.2397940159,53.4293289185],"type":"Point"}
}