{
  "type": "Feature",
  "properties": {
    "addr:full":"Castle Douglas Careers Service, Market St Castle Douglas Dumfries and Galloway DG7 1BE",
    "addr:postcode":"galloway dg7 1be",
    "addr:street":"Market St",
    "iso:country":"GB",
    "sg:address":"Castle Douglas Careers Service, Market St",
    "sg:city":"Castle Douglas",
    "sg:classifiers":[
        {
            "category":"Professional",
            "subcategory":"Employment Agencies",
            "type":"Services"
        }
    ],
    "sg:phone":"+44 1556 502351",
    "sg:postcode":"DG7 1BE",
    "sg:province":"Dumfries and Galloway",
    "sg:tags":[
        "career",
        "guidance"
    ],
    "wof:name":"Career Develpment Services",
    "wof:placetype":"venue"
},
  "geometry": {"coordinates":[-3.9287040234,54.941619873],"type":"Point"}
}