{
  "type": "Feature",
  "properties": {
    "iso:country":"GB",
    "sg:address":"Yorkshire House, 41 Keighley Rd",
    "sg:city":"Keighley",
    "sg:classifiers":[
        {
            "category":"Home & Garden",
            "subcategory":"Kitchen Supply",
            "type":"Retail Goods"
        }
    ],
    "sg:phone":"+44 1535 654252",
    "sg:postcode":"BD20 0EA",
    "sg:province":"North Yorkshire",
    "sg:tags":[
        "equipment",
        "catering"
    ],
    "wof:name":"Airedale Food Service Counters Ltd",
    "wof:placetype":"venue"
},
  "geometry": {"coordinates":[-1.938233,53.911427],"type":"Point"}
}