{
  "type": "Feature",
  "properties": {
    "addr:full":"Unit 1, 224 Iverson Road London Greater London NW6 2HU",
    "addr:housenumber":"unit 1",
    "addr:postcode":"224;nw6 2hu",
    "addr:street":"Iverson Road",
    "iso:country":"GB",
    "sg:address":"Unit 1, 224 Iverson Road",
    "sg:city":"London",
    "sg:classifiers":[
        {
            "category":"Professional",
            "subcategory":"Advertising",
            "type":"Services"
        }
    ],
    "sg:phone":"+44 20 7625 7575",
    "sg:postcode":"NW6 2HU",
    "sg:province":"Greater London",
    "sg:tags":[
        "agency"
    ],
    "wof:name":"B B A Active Ltd.",
    "wof:placetype":"venue"
},
  "geometry": {"coordinates":[-0.1912350059,51.547832489],"type":"Point"}
}