{
  "type": "Feature",
  "properties": {
    "iso:country":"GB",
    "sg:address":"Westfield Complex",
    "sg:city":"Lochgelly",
    "sg:classifiers":[
        {
            "category":"Manufacturing",
            "subcategory":"Glass & Minerals",
            "type":"Manufacturing & Wholesale Goods"
        }
    ],
    "sg:phone":"+44 1592 720205",
    "sg:postcode":"KY5 0HN",
    "sg:province":"Fife",
    "sg:tags":[
        "chalk",
        "stone",
        "slate"
    ],
    "wof:name":"Tarmac Quarry Products Ltd",
    "wof:placetype":"venue"
},
  "geometry": {"coordinates":[-3.258904,56.14941],"type":"Point"}
}