{
  "type": "Feature",
  "properties": {
    "addr:full":"Bankfield Wing, Bankfield Road Liverpool Merseyside L13 0BE",
    "addr:postcode":"l13 0be",
    "addr:street":"Bankfield Road",
    "iso:country":"GB",
    "sg:address":"Bankfield Wing, Bankfield Road",
    "sg:city":"Liverpool",
    "sg:classifiers":[
        {
            "category":"Education",
            "subcategory":"University",
            "type":"Public Place"
        }
    ],
    "sg:phone":"+44 151 228 8628",
    "sg:postcode":"L13 0BE",
    "sg:province":"Merseyside",
    "sg:tags":[
        "adult"
    ],
    "wof:name":"Bankfield Adult Centre",
    "wof:placetype":"venue"
},
  "geometry": {"coordinates":[-2.9784810543,53.4097747803],"type":"Point"}
}