{
  "type": "Feature",
  "properties": {
    "addr:full":"Sterling House, 70 Bridgford Road, West Bridgford Nottingham Nottinghamshire NG2 6AP",
    "addr:housenumber":"70",
    "addr:postcode":"ng2 6ap",
    "addr:street":"Bridgford Road",
    "iso:country":"GB",
    "sg:address":"Sterling House, 70 Bridgford Road, West Bridgford",
    "sg:city":"Nottingham",
    "sg:classifiers":[
        {
            "category":"Professional",
            "subcategory":"Accounting & Tax Preparation",
            "type":"Services"
        }
    ],
    "sg:phone":"+44 115 981 0000",
    "sg:postcode":"NG2 6AP",
    "sg:province":"Nottinghamshire",
    "sg:tags":[
        "accountant"
    ],
    "wof:name":"Oldco 4 Ltd.",
    "wof:placetype":"venue"
},
  "geometry": {"coordinates":[-1.128175,52.933117],"type":"Point"}
}