{
  "type": "Feature",
  "properties": {
    "iso:country":"GB",
    "sg:address":"Holmwood Centre Point, Broadstone Way",
    "sg:city":"Bradford",
    "sg:classifiers":[
        {
            "category":"Organizations",
            "subcategory":"Non-profit Organization",
            "type":"Services"
        }
    ],
    "sg:phone":"+44 1274 689654",
    "sg:postcode":"BD4 9SA",
    "sg:province":"West Yorkshire",
    "sg:tags":[
        "organisation",
        "voluntary",
        "charity"
    ],
    "wof:name":"Homekey Project",
    "wof:placetype":"venue"
},
  "geometry": {"coordinates":[-1.7102600336,53.7707481384],"type":"Point"}
}