{
  "type": "Feature",
  "properties": {
    "addr:full":"7 South Tay Street Dundee Dundee City DD1 1NU",
    "addr:housenumber":"7",
    "addr:postcode":"dd1 1nu",
    "addr:street":"South Tay Street",
    "iso:country":"GB",
    "sg:address":"7 South Tay Street",
    "sg:city":"Dundee",
    "sg:classifiers":[
        {
            "category":"Real Estate",
            "subcategory":"Architect",
            "type":"Services"
        }
    ],
    "sg:phone":"+44 1382 224427",
    "sg:postcode":"DD1 1NU",
    "sg:province":"Dundee City",
    "wof:name":"Hiddleston & Feist",
    "wof:placetype":"venue"
},
  "geometry": {"coordinates":[-2.9753398895,56.4579734802],"type":"Point"}
}