{
  "type": "Feature",
  "properties": {
    "iso:country":"GB",
    "sg:address":"Hall Farm, Mill Road",
    "sg:city":"Melton Constable",
    "sg:classifiers":[
        {
            "category":"Retail",
            "subcategory":"Auto Repair",
            "type":"Services"
        }
    ],
    "sg:phone":"+44 1263 860977",
    "sg:postcode":"NR24 2JF",
    "sg:province":"Norfolk",
    "sg:tags":[
        "modification",
        "garage"
    ],
    "wof:name":"Gee-Dee Autos",
    "wof:placetype":"venue"
},
  "geometry": {"coordinates":[1.0384149551,52.8566246033],"type":"Point"}
}