{
  "type": "Feature",
  "properties": {
    "addr:full":"44 Courtland Drive Deeside Flintshire CH5 1UH",
    "addr:housenumber":"44",
    "addr:postcode":"ch5 1uh",
    "addr:street":"Courtland Drive",
    "iso:country":"GB",
    "sg:address":"44 Courtland Drive",
    "sg:city":"Deeside",
    "sg:classifiers":[
        {
            "category":"Freight",
            "type":"Transportation"
        }
    ],
    "sg:phone":"+44 1244 815855",
    "sg:postcode":"CH5 1UH",
    "sg:province":"Flintshire",
    "sg:tags":[
        "haulage",
        "road"
    ],
    "wof:name":"Barry T Jones",
    "wof:placetype":"venue"
},
  "geometry": {"coordinates":[-3.042424,53.199501],"type":"Point"}
}