{
  "type": "Feature",
  "properties": {
    "addr:full":"16 Blythwood Drive, Frimley Camberley Hampshire GU16 8TZ",
    "addr:housenumber":"16",
    "addr:postcode":"gu16 8tz",
    "addr:street":"Blythwood Drive",
    "iso:country":"GB",
    "sg:address":"16 Blythwood Drive, Frimley",
    "sg:city":"Camberley",
    "sg:classifiers":[
        {
            "category":"Education",
            "subcategory":"School",
            "type":"Public Place"
        }
    ],
    "sg:phone":"+44 1276 509399",
    "sg:postcode":"GU16 8TZ",
    "sg:province":"Hampshire",
    "sg:tags":[
        "private",
        "tuition"
    ],
    "wof:name":"Maths-Sci Tuition",
    "wof:placetype":"venue"
},
  "geometry": {"coordinates":[-0.7378900051,51.3229866028],"type":"Point"}
}