{
  "type": "Feature",
  "properties": {
    "iso:country":"GB",
    "sg:address":"58-62 Vestry Road",
    "sg:city":"Street",
    "sg:classifiers":[
        {
            "category":"Retail",
            "subcategory":"Funeral Services",
            "type":"Services"
        }
    ],
    "sg:phone":"+44 1458 840658",
    "sg:postcode":"BA16 0HX",
    "sg:province":"Somerset",
    "sg:tags":[
        "director"
    ],
    "wof:name":"G Holland & Son (Funeral Directors) Ltd.",
    "wof:placetype":"venue"
},
  "geometry": {"coordinates":[-2.738755,51.125095],"type":"Point"}
}