{
  "type": "Feature",
  "properties": {
    "iso:country":"GB",
    "sg:address":"Unit 27 Springfield Court",
    "sg:city":"Horsham",
    "sg:classifiers":[
        {
            "category":"Shopping",
            "subcategory":"Music",
            "type":"Retail Goods"
        }
    ],
    "sg:phone":"+44 1403 210039",
    "sg:postcode":"RH12 1PT",
    "sg:province":"West Sussex",
    "sg:tags":[
        "record",
        "tape",
        "cd"
    ],
    "wof:name":"Our Price",
    "wof:placetype":"venue"
},
  "geometry": {"coordinates":[-0.3319439888,51.0637283325],"type":"Point"}
}