{
  "type": "Feature",
  "properties": {
    "iso:country":"GB",
    "sg:address":"7 Murray Street",
    "sg:city":"London",
    "sg:classifiers":[
        {
            "category":"Restaurant",
            "type":"Food & Drink"
        }
    ],
    "sg:phone":"+44 20 7485 6400",
    "sg:postcode":"NW1 9RE",
    "sg:province":"Greater London",
    "wof:name":"A Baia Restaurant",
    "wof:placetype":"venue"
},
  "geometry": {"coordinates":[-0.132412,51.543453],"type":"Point"}
}