{
  "type": "Feature",
  "properties": {
    "addr:full":"Main Street, Winster Matlock Derbyshire DE4 2DH",
    "addr:postcode":"de4 2dh",
    "addr:street":"Main Street",
    "iso:country":"GB",
    "sg:address":"Main Street, Winster",
    "sg:city":"Matlock",
    "sg:classifiers":[
        {
            "category":"Government",
            "subcategory":"Post Office",
            "type":"Public Place"
        }
    ],
    "sg:phone":"+44 845 722 3344",
    "sg:postcode":"DE4 2DH",
    "sg:province":"Derbyshire",
    "wof:name":"Winster Post Office",
    "wof:placetype":"venue"
},
  "geometry": {"coordinates":[-1.637699008,53.1422538757],"type":"Point"}
}