{
  "type": "Feature",
  "properties": {
    "addr:full":"56-64 Ellison Street Jarrow Tyne and Wear NE32 3BX",
    "addr:housenumber":"56-64",
    "addr:postcode":"ne32 3bx",
    "addr:street":"Ellison Street",
    "iso:country":"GB",
    "sg:address":"56-64 Ellison Street",
    "sg:city":"Jarrow",
    "sg:classifiers":[
        {
            "category":"Organizations",
            "subcategory":"Non-profit Organization",
            "type":"Services"
        }
    ],
    "sg:phone":"+44 191 428 4392",
    "sg:postcode":"NE32 3BX",
    "sg:province":"Tyne and Wear",
    "sg:tags":[
        "organisation",
        "voluntary",
        "charity"
    ],
    "wof:name":"Ymca",
    "wof:placetype":"venue"
},
  "geometry": {"coordinates":[-1.490949,54.982262],"type":"Point"}
}