{
  "type": "Feature",
  "properties": {
    "addr:full":"1 Fore Street Port Isaac Cornwall PL29 3RB",
    "addr:housenumber":"1",
    "addr:postcode":"pl29 3rb",
    "addr:street":"Fore Street",
    "iso:country":"GB",
    "sg:address":"1 Fore Street",
    "sg:city":"Port Isaac",
    "sg:classifiers":[
        {
            "category":"Farming",
            "subcategory":"Fish & Marine Products",
            "type":"Manufacturing & Wholesale Goods"
        }
    ],
    "sg:postcode":"PL29 3RB",
    "sg:province":"Cornwall",
    "sg:tags":[
        "fishmonger"
    ],
    "wof:name":"Dennis Knight Fish Merchants",
    "wof:placetype":"venue"
},
  "geometry": {"coordinates":[-4.831875,50.592274],"type":"Point"}
}