{
  "type": "Feature",
  "properties": {
    "addr:full":"40 Stotfold Road Arlesey Bedfordshire SG15 6XT",
    "addr:housenumber":"40",
    "addr:postcode":"sg15 6xt",
    "addr:street":"Stotfold Road",
    "iso:country":"GB",
    "sg:address":"40 Stotfold Road",
    "sg:city":"Arlesey",
    "sg:classifiers":[
        {
            "category":"Professional",
            "subcategory":"Accounting & Tax Preparation",
            "type":"Services"
        }
    ],
    "sg:postcode":"SG15 6XT",
    "sg:province":"Bedfordshire",
    "sg:tags":[
        "accountant"
    ],
    "wof:name":"Lisa Taylor",
    "wof:placetype":"venue"
},
  "geometry": {"coordinates":[-0.26183,52.025105],"type":"Point"}
}