{
  "type": "Feature",
  "properties": {
    "iso:country":"GB",
    "sg:address":"40 Stotfold Road",
    "sg:city":"Arlesey",
    "sg:classifiers":[
        {
            "category":"Professional",
            "subcategory":"Accounting & Tax Preparation",
            "type":"Services"
        }
    ],
    "sg:postcode":"SG15 6XT",
    "sg:province":"Bedfordshire",
    "sg:tags":[
        "accountant"
    ],
    "wof:name":"Lisa Taylor",
    "wof:placetype":"venue"
},
  "geometry": {"coordinates":[-0.26183,52.025105],"type":"Point"}
}