{
  "type": "Feature",
  "properties": {
    "addr:full":"111 Brecon Road Merthyr Tydfil Merthyr Tydfil CF47 8NG",
    "addr:housenumber":"111",
    "addr:postcode":"cf47 8ng",
    "addr:street":"Brecon Road",
    "iso:country":"GB",
    "sg:address":"111 Brecon Road",
    "sg:city":"Merthyr Tydfil",
    "sg:classifiers":[
        {
            "category":"Shopping",
            "subcategory":"Clothing, Apparel, & Fashions",
            "type":"Retail Goods"
        }
    ],
    "sg:phone":"+44 1685 371120",
    "sg:postcode":"CF47 8NG",
    "sg:province":"Merthyr Tydfil",
    "sg:tags":[
        "ladieswear"
    ],
    "wof:name":"Carisa",
    "wof:placetype":"venue"
},
  "geometry": {"coordinates":[-3.3801009655,51.7498474121],"type":"Point"}
}