{
  "type": "Feature",
  "properties": {
    "addr:full":"Ash Gro, Beverley Road Hull East Riding of Yorkshire HU5 1LT",
    "addr:postcode":"hu5 1lt",
    "addr:street":"Gro Beverley Road",
    "iso:country":"GB",
    "sg:address":"Ash Gro, Beverley Road",
    "sg:city":"Hull",
    "sg:classifiers":[
        {
            "category":"Manufacturing",
            "subcategory":"Buildings",
            "type":"Manufacturing & Wholesale Goods"
        }
    ],
    "sg:phone":"+44 1482 444256",
    "sg:postcode":"HU5 1LT",
    "sg:province":"East Riding of Yorkshire",
    "sg:tags":[
        "shed",
        "greenhouse"
    ],
    "wof:name":"Newstar Sectional Buildings",
    "wof:placetype":"venue"
},
  "geometry": {"coordinates":[-0.353762,53.767769],"type":"Point"}
}