{
  "type": "Feature",
  "properties": {
    "iso:country":"GB",
    "sg:address":"36 Cannon Mill Avenue",
    "sg:city":"Chesham",
    "sg:classifiers":[
        {
            "category":"Building & Trades",
            "subcategory":"Construction",
            "type":"Services"
        }
    ],
    "sg:phone":"+44 1494 776323",
    "sg:postcode":"HP5 1QX",
    "sg:province":"Buckinghamshire",
    "sg:tags":[
        "bricklayer",
        "bricklaying"
    ],
    "wof:name":"D F Burgess",
    "wof:placetype":"venue"
},
  "geometry": {"coordinates":[-0.596585,51.694508],"type":"Point"}
}