{
  "type": "Feature",
  "properties": {
    "addr:full":"70 St James St Nottingham Nottinghamshire NG1 6FJ",
    "addr:housenumber":"70",
    "addr:postcode":"ng1 6fj",
    "addr:street":"St James St",
    "iso:country":"GB",
    "sg:address":"70 St James St",
    "sg:city":"Nottingham",
    "sg:classifiers":[
        {
            "category":"Professional",
            "subcategory":"Computer Services",
            "type":"Services"
        }
    ],
    "sg:postcode":"NG1 6FJ",
    "sg:province":"Nottinghamshire",
    "sg:tags":[
        "system",
        "software"
    ],
    "wof:name":"Point Four Ltd",
    "wof:placetype":"venue"
},
  "geometry": {"coordinates":[-1.1524260044,52.9529838562],"type":"Point"}
}