{
  "type": "Feature",
  "properties": {
    "iso:country":"GB",
    "sg:address":"208 Selby Rd",
    "sg:city":"Leeds",
    "sg:classifiers":[
        {
            "category":"Farming",
            "subcategory":"Fish & Marine Products",
            "type":"Manufacturing & Wholesale Goods"
        }
    ],
    "sg:postcode":"LS15 0LF",
    "sg:province":"West Yorkshire",
    "sg:tags":[
        "fishmonger"
    ],
    "wof:name":"Deacon,D,",
    "wof:placetype":"venue"
},
  "geometry": {"coordinates":[-1.4750590324,53.7972412109],"type":"Point"}
}