{
  "type": "Feature",
  "properties": {
    "addr:full":"142 The Crossways, Heaston Hounslow Greater London TW5 0JR",
    "addr:housenumber":"142",
    "addr:postcode":"tw5 0jr",
    "addr:street":"The;Heaston",
    "iso:country":"GB",
    "sg:address":"142 The Crossways, Heaston",
    "sg:city":"Hounslow",
    "sg:classifiers":[
        {
            "category":"Autos & Motor Vehicles",
            "subcategory":"Auto Supplies",
            "type":"Retail Goods"
        }
    ],
    "sg:phone":"+44 20 8577 6886",
    "sg:postcode":"TW5 0JR",
    "sg:province":"Greater London",
    "sg:tags":[
        "component"
    ],
    "wof:name":"Universal Co",
    "wof:placetype":"venue"
},
  "geometry": {"coordinates":[-0.3738160133,51.480632782],"type":"Point"}
}