{
  "type": "Feature",
  "properties": {
    "addr:full":"51 Goldhawk Road, Shepherd's Bush Shepherd's Bush Greater London W12 0ND",
    "addr:housenumber":"51",
    "addr:postcode":"w12 0nd",
    "addr:street":"Goldhawk Road",
    "iso:country":"GB",
    "sg:address":"51 Goldhawk Road, Shepherd's Bush",
    "sg:city":"Shepherd's Bush",
    "sg:classifiers":[
        {
            "category":"Manufacturing",
            "subcategory":"Textiles",
            "type":"Manufacturing & Wholesale Goods"
        }
    ],
    "sg:phone":"+44 20 8743 1488",
    "sg:postcode":"W12 0ND",
    "sg:province":"Greater London",
    "sg:tags":[
        "merchant",
        "agent"
    ],
    "wof:name":"Rajinder T S Dari",
    "wof:placetype":"venue"
},
  "geometry": {"coordinates":[-0.2260030061,51.5023956299],"type":"Point"}
}