{
  "type": "Feature",
  "properties": {
    "addr:full":"26 West Street London Greater London WC2H 9NA",
    "addr:housenumber":"26",
    "addr:postcode":"wc2h 9na",
    "addr:street":"West Street",
    "iso:country":"GB",
    "sg:address":"26 West Street",
    "sg:city":"London",
    "sg:classifiers":[
        {
            "category":"Professional",
            "subcategory":"Art Services",
            "type":"Services"
        }
    ],
    "sg:phone":"+44 20 7836 6018",
    "sg:postcode":"WC2H 9NA",
    "sg:province":"Greater London",
    "sg:tags":[
        "photographer"
    ],
    "wof:name":"John Wallace",
    "wof:placetype":"venue"
},
  "geometry": {"coordinates":[-0.1283300072,51.5132293701],"type":"Point"}
}