{
  "type": "Feature",
  "properties": {
    "addr:full":"193 King St Castle Douglas Dumfries and Galloway DG7 1DZ",
    "addr:housenumber":"193",
    "addr:postcode":"dg7 1dz",
    "addr:street":"King St",
    "iso:country":"GB",
    "sg:address":"193 King St",
    "sg:city":"Castle Douglas",
    "sg:classifiers":[
        {
            "category":"Restaurant",
            "type":"Food & Drink"
        }
    ],
    "sg:phone":"+44 1556 503692",
    "sg:postcode":"DG7 1DZ",
    "sg:province":"Dumfries and Galloway",
    "wof:name":"Merrick Hotel The",
    "wof:placetype":"venue"
},
  "geometry": {"coordinates":[-3.931648016,54.9391670227],"type":"Point"}
}