{
  "type": "Feature",
  "properties": {
    "addr:full":"56 Bridge Street Dollar Clackmannanshire FK14 7DG",
    "addr:housenumber":"56",
    "addr:postcode":"fk14 7dg",
    "addr:street":"Bridge Street",
    "iso:country":"GB",
    "sg:address":"56 Bridge Street",
    "sg:city":"Dollar",
    "sg:classifiers":[
        {
            "category":"Fast Food",
            "type":"Food & Drink"
        }
    ],
    "sg:phone":"+44 1259 742274",
    "sg:postcode":"FK14 7DG",
    "sg:province":"Clackmannanshire",
    "sg:tags":[
        "away",
        "take"
    ],
    "wof:name":"Mos Plaice",
    "wof:placetype":"venue"
},
  "geometry": {"coordinates":[-3.674177,56.162884],"type":"Point"}
}