{
  "type": "Feature",
  "properties": {
    "iso:country":"GB",
    "sg:address":"15 Searle Way, Eight Ash Grn",
    "sg:city":"Colchester",
    "sg:classifiers":[
        {
            "category":"Professional",
            "subcategory":"Accounting & Tax Preparation",
            "type":"Services"
        }
    ],
    "sg:postcode":"CO6 3QS",
    "sg:province":"Essex",
    "sg:tags":[
        "accountant"
    ],
    "wof:name":"Tilman & Co.",
    "wof:placetype":"venue"
},
  "geometry": {"coordinates":[0.8269960284,51.8997344971],"type":"Point"}
}