{
  "type": "Feature",
  "properties": {
    "iso:country":"GB",
    "sg:address":"Warham, Lewson Street, Norton",
    "sg:city":"Sittingbourne",
    "sg:classifiers":[
        {
            "category":"Building & Trades",
            "subcategory":"Construction",
            "type":"Services"
        }
    ],
    "sg:phone":"+44 1795 521832",
    "sg:postcode":"ME9 9JS",
    "sg:province":"Kent",
    "sg:tags":[
        "equipment"
    ],
    "wof:name":"R S Deacon",
    "wof:placetype":"venue"
},
  "geometry": {"coordinates":[0.820685,51.322605],"type":"Point"}
}