{
  "type": "Feature",
  "properties": {
    "addr:full":"24-26 Mkt Rd Doncaster South Yorkshire DN1 1LP",
    "addr:housenumber":"24-26",
    "addr:postcode":"dn1 1lp",
    "addr:street":"Mkt Rd",
    "iso:country":"GB",
    "sg:address":"24-26 Mkt Rd",
    "sg:city":"Doncaster",
    "sg:classifiers":[
        {
            "category":"Organizations",
            "subcategory":"Non-profit Organization",
            "type":"Services"
        }
    ],
    "sg:postcode":"DN1 1LP",
    "sg:province":"South Yorkshire",
    "sg:tags":[
        "organisation",
        "voluntary",
        "charity"
    ],
    "wof:name":"National Schizophrenia Fellowship",
    "wof:placetype":"venue"
},
  "geometry": {"coordinates":[-1.1309620142,53.5259666443],"type":"Point"}
}