{
  "type": "Feature",
  "properties": {
    "iso:country":"GB",
    "sg:address":"Reading Road South",
    "sg:city":"Fleet",
    "sg:classifiers":[
        {
            "category":"Education",
            "subcategory":"School",
            "type":"Public Place"
        }
    ],
    "sg:phone":"+44 1252 617928",
    "sg:postcode":"GU52 7TH",
    "sg:province":"Hampshire",
    "sg:tags":[
        "local",
        "authority"
    ],
    "wof:name":"Heatherside County Junior School",
    "wof:placetype":"venue"
},
  "geometry": {"coordinates":[-0.842354,51.276749],"type":"Point"}
}