{
  "type": "Feature",
  "properties": {
    "addr:full":"1 Potters Park, Brockencote Kidderminster Staffordshire DY10 4QA",
    "addr:housenumber":"1",
    "addr:postcode":"dy10 4qa",
    "addr:street":"Potters Park Brockencote",
    "iso:country":"GB",
    "sg:address":"1 Potters Park, Brockencote",
    "sg:city":"Kidderminster",
    "sg:classifiers":[
        {
            "category":"Food & Beverages",
            "subcategory":"Farmers Market",
            "type":"Retail Goods"
        }
    ],
    "sg:postcode":"DY10 4QA",
    "sg:province":"Staffordshire",
    "sg:tags":[
        "farm",
        "shop",
        "pyo"
    ],
    "wof:name":"Chaddesley Growers",
    "wof:placetype":"venue"
},
  "geometry": {"coordinates":[-2.249084,52.388111],"type":"Point"}
}