{
  "type": "Feature",
  "properties": {
    "iso:country":"GB",
    "sg:address":"161 High Road, Chadwell Heath",
    "sg:city":"Romford",
    "sg:classifiers":[
        {
            "category":"Fast Food",
            "type":"Food & Drink"
        }
    ],
    "sg:phone":"+44 20 8503 8222",
    "sg:postcode":"RM6 6NL",
    "sg:province":"Essex",
    "sg:tags":[
        "away",
        "take"
    ],
    "wof:name":"Bellam & Co. Ltd.",
    "wof:placetype":"venue"
},
  "geometry": {"coordinates":[0.137997,51.572105],"type":"Point"}
}