{
  "type": "Feature",
  "properties": {
    "addr:full":"Huntly Road, Hillington Industrial Estate Glasgow Glasgow City G52 4DZ",
    "addr:postcode":"g52 4dz",
    "addr:street":"Huntly Road;Industrial Estate",
    "iso:country":"GB",
    "sg:address":"Huntly Road, Hillington Industrial Estate",
    "sg:city":"Glasgow",
    "sg:classifiers":[
        {
            "category":"Building & Trades",
            "subcategory":"Plumbing",
            "type":"Services"
        }
    ],
    "sg:phone":"+44 141 445 5928",
    "sg:postcode":"G52 4DZ",
    "sg:province":"Glasgow City",
    "sg:tags":[
        "central",
        "heating"
    ],
    "wof:name":"C & K Heating",
    "wof:placetype":"venue"
},
  "geometry": {"coordinates":[-4.370089,55.863014],"type":"Point"}
}