{
  "type": "Feature",
  "properties": {
    "iso:country":"GB",
    "sg:address":"72 Avon Rd",
    "sg:city":"Bournemouth",
    "sg:classifiers":[
        {
            "category":"Communications",
            "subcategory":"Newspaper",
            "type":"Services"
        }
    ],
    "sg:phone":"+44 1202 247080",
    "sg:postcode":"BH8 8SF",
    "sg:province":"Dorset",
    "sg:tags":[
        "magazine"
    ],
    "wof:name":"Lepiege Fanzines",
    "wof:placetype":"venue"
},
  "geometry": {"coordinates":[-1.8537629843,50.7344512939],"type":"Point"}
}