{
  "type": "Feature",
  "properties": {
    "addr:full":"Dartfield Farm Stockbridge Hampshire SO20 6JS",
    "addr:housenumber":"stockbridge",
    "addr:postcode":"so20 6js",
    "addr:street":"Hampshire",
    "iso:country":"GB",
    "sg:address":"Dartfield Farm",
    "sg:city":"Stockbridge",
    "sg:classifiers":[
        {
            "category":"Farming",
            "subcategory":"Livestock Farm",
            "type":"Manufacturing & Wholesale Goods"
        }
    ],
    "sg:phone":"+44 1264 810664",
    "sg:postcode":"SO20 6JS",
    "sg:province":"Hampshire",
    "sg:tags":[
        "others"
    ],
    "wof:name":"A G Lambert & Partners",
    "wof:placetype":"venue"
},
  "geometry": {"coordinates":[-1.494102,51.114281],"type":"Point"}
}