{
  "type": "Feature",
  "properties": {
    "addr:full":"Unit 47 Second Avenue, Pensnet Trading Estate, Kingswinford Brierley Hill Staffordshire DY6 7UZ",
    "addr:housenumber":"unit 47",
    "addr:postcode":"dy6 7uz",
    "addr:street":"Second Avenue Pensnet Trading Estate",
    "iso:country":"GB",
    "sg:address":"Unit 47 Second Avenue, Pensnet Trading Estate, Kingswinford",
    "sg:city":"Brierley Hill",
    "sg:classifiers":[
        {
            "category":"Professional",
            "subcategory":"Engineering",
            "type":"Services"
        }
    ],
    "sg:phone":"+44 1384 401252",
    "sg:postcode":"DY6 7UZ",
    "sg:province":"Staffordshire",
    "sg:tags":[
        "contractor",
        "electrical",
        "engineer"
    ],
    "wof:name":"Watliff Co. Ltd.",
    "wof:placetype":"venue"
},
  "geometry": {"coordinates":[-2.1515390873,52.5058135986],"type":"Point"}
}