{
  "type": "Feature",
  "properties": {
    "addr:full":"12-14 Wood Street, Old Town Swindon Wiltshire SN1 4AB",
    "addr:housenumber":"12-14",
    "addr:postcode":"sn1 4ab",
    "addr:street":"Wood Street",
    "iso:country":"GB",
    "sg:address":"12-14 Wood Street, Old Town",
    "sg:city":"Swindon",
    "sg:classifiers":[
        {
            "category":"Restaurant",
            "type":"Food & Drink"
        }
    ],
    "sg:phone":"+44 1793 490265",
    "sg:postcode":"SN1 4AB",
    "sg:province":"Wiltshire",
    "sg:tags":[
        "indian"
    ],
    "wof:name":"The Biplob Tandoori Restaurant",
    "wof:placetype":"venue"
},
  "geometry": {"coordinates":[-1.775299,51.552589],"type":"Point"}
}