{
  "type": "Feature",
  "properties": {
    "iso:country":"GB",
    "sg:address":"White Ho, High St",
    "sg:city":"Bagshot",
    "sg:classifiers":[
        {
            "category":"Professional",
            "subcategory":"Accounting & Tax Preparation",
            "type":"Services"
        }
    ],
    "sg:phone":"+44 1276 477330",
    "sg:postcode":"GU19 5AH",
    "sg:province":"Berkshire",
    "sg:tags":[
        "accountant"
    ],
    "wof:name":"R & A Associates",
    "wof:placetype":"venue"
},
  "geometry": {"coordinates":[-0.6961200237,51.3587989807],"type":"Point"}
}