{
  "type": "Feature",
  "properties": {
    "addr:full":"11 Coombe Corner London Greater London N21 3PE",
    "addr:housenumber":"11",
    "addr:postcode":"n21 3pe",
    "addr:street":"Coombe Corner",
    "iso:country":"GB",
    "sg:address":"11 Coombe Corner",
    "sg:city":"London",
    "sg:classifiers":[
        {
            "category":"Professional",
            "subcategory":"Accounting & Tax Preparation",
            "type":"Services"
        }
    ],
    "sg:postcode":"N21 3PE",
    "sg:province":"Greater London",
    "sg:tags":[
        "accountant"
    ],
    "wof:name":"Coombe Mobile Book Keeping",
    "wof:placetype":"venue"
},
  "geometry": {"coordinates":[-0.0981469974,51.6305007935],"type":"Point"}
}