{
  "type": "Feature",
  "properties": {
    "addr:full":"17 Albert Street Slough Berkshire SL1 2BE",
    "addr:housenumber":"17",
    "addr:postcode":"sl1 2be",
    "addr:street":"Albert Street",
    "iso:country":"GB",
    "sg:address":"17 Albert Street",
    "sg:city":"Slough",
    "sg:classifiers":[
        {
            "category":"Building & Trades",
            "subcategory":"Electrical",
            "type":"Services"
        }
    ],
    "sg:postcode":"SL1 2BE",
    "sg:province":"Berkshire",
    "sg:tags":[
        "heating"
    ],
    "wof:name":"Realm Electrical Wholesale",
    "wof:placetype":"venue"
},
  "geometry": {"coordinates":[-0.592066,51.504593],"type":"Point"}
}