{
  "type": "Feature",
  "properties": {
    "iso:country":"GB",
    "sg:address":"65 Sandpiper Road",
    "sg:city":"Ipswich",
    "sg:classifiers":[
        {
            "category":"Professional",
            "subcategory":"Engineering",
            "type":"Services"
        },
        {
            "category":"Building & Trades",
            "subcategory":"Construction",
            "type":"Services"
        }
    ],
    "sg:phone":"+44 1473 603621",
    "sg:postcode":"IP2 9HU",
    "sg:province":"Suffolk",
    "sg:tags":[
        "installers",
        "gas",
        "engineer"
    ],
    "wof:name":"Five Star Gas Service",
    "wof:placetype":"venue"
},
  "geometry": {"coordinates":[1.123247,52.041203],"type":"Point"}
}