{
  "type": "Feature",
  "properties": {
    "addr:full":"89 Sitwell Street, Spondon Derby Derbyshire DE21 7FH",
    "addr:housenumber":"89",
    "addr:postcode":"de21 7fh",
    "addr:street":"Sitwell Street",
    "iso:country":"GB",
    "sg:address":"89 Sitwell Street, Spondon",
    "sg:city":"Derby",
    "sg:classifiers":[
        {
            "category":"Autos & Motor Vehicles",
            "subcategory":"Auto Supplies",
            "type":"Retail Goods"
        },
        {
            "category":"Shopping",
            "type":"Retail Goods"
        }
    ],
    "sg:phone":"+44 1332 662108",
    "sg:postcode":"DE21 7FH",
    "sg:province":"Derbyshire",
    "sg:tags":[
        "part",
        "accessory",
        "factor"
    ],
    "wof:name":"Romac Motor Factors",
    "wof:placetype":"venue"
},
  "geometry": {"coordinates":[-1.403853,52.920547],"type":"Point"}
}