{
  "type": "Feature",
  "properties": {
    "addr:full":"193 Halesowen Road Cradley Heath West Midlands B64 6HE",
    "addr:housenumber":"193",
    "addr:postcode":"b64 6he",
    "addr:street":"Halesowen Road",
    "iso:country":"GB",
    "sg:address":"193 Halesowen Road",
    "sg:city":"Cradley Heath",
    "sg:classifiers":[
        {
            "category":"Deli",
            "type":"Food & Drink"
        }
    ],
    "sg:phone":"+44 1384 567297",
    "sg:postcode":"B64 6HE",
    "sg:province":"West Midlands",
    "sg:tags":[
        "delicatessen"
    ],
    "wof:name":"The Cook Shop",
    "wof:placetype":"venue"
},
  "geometry": {"coordinates":[-2.0678100586,52.4760131836],"type":"Point"}
}