{
  "type": "Feature",
  "properties": {
    "addr:full":"Taxi Office, Station Forecourt Rickmansworth Hertfordshire WD3 1QY",
    "addr:postcode":"wd3 1qy",
    "addr:street":"Rickmansworth",
    "iso:country":"GB",
    "sg:address":"Taxi Office, Station Forecourt",
    "sg:city":"Rickmansworth",
    "sg:classifiers":[
        {
            "category":"Taxi",
            "type":"Transportation"
        }
    ],
    "sg:phone":"+44 1923 773626",
    "sg:postcode":"WD3 1QY",
    "sg:province":"Hertfordshire",
    "sg:tags":[
        "mini",
        "cab"
    ],
    "wof:name":"Boughton's Car Hire Ltd.",
    "wof:placetype":"venue"
},
  "geometry": {"coordinates":[-0.468275,51.641438],"type":"Point"}
}