{
  "type": "Feature",
  "properties": {
    "iso:country":"GB",
    "sg:address":"8 Kimberley Close, Thorpe Audlin",
    "sg:city":"Pontefract",
    "sg:classifiers":[
        {
            "category":"Freight",
            "type":"Transportation"
        }
    ],
    "sg:phone":"+44 1977 620054",
    "sg:postcode":"WF8 3ER",
    "sg:province":"North Yorkshire",
    "sg:tags":[
        "haulage",
        "road"
    ],
    "wof:name":"D & L PARKER TRANSPORT",
    "wof:placetype":"venue"
},
  "geometry": {"coordinates":[-1.282976,53.640697],"type":"Point"}
}