{
  "type": "Feature",
  "properties": {
    "iso:country":"GB",
    "sg:address":"East Street, Crescent Road",
    "sg:city":"Faversham",
    "sg:classifiers":[
        {
            "category":"Shopping",
            "subcategory":"Antiques",
            "type":"Retail Goods"
        }
    ],
    "sg:postcode":"ME13 8AD",
    "sg:province":"Kent",
    "wof:name":"Collectors Corner",
    "wof:placetype":"venue"
},
  "geometry": {"coordinates":[0.892345,51.315163],"type":"Point"}
}