{
  "type": "Feature",
  "properties": {
    "iso:country":"GB",
    "sg:address":"Hook Rise North",
    "sg:city":"Surbiton",
    "sg:classifiers":[
        {
            "category":"Bars & Pubs",
            "subcategory":"Wine Bar",
            "type":"Food & Drink"
        }
    ],
    "sg:postcode":"KT6 5AT",
    "sg:province":"Surrey",
    "wof:name":"Wallpole-Jones,Christian,",
    "wof:placetype":"venue"
},
  "geometry": {"coordinates":[-0.286404,51.374718],"type":"Point"}
}