{
  "type": "Feature",
  "properties": {
    "addr:full":"28 Macdowall Street Johnstone Renfrewshire PA5 8QL",
    "addr:housenumber":"28",
    "addr:postcode":"pa5 8ql",
    "addr:street":"Macdowall Street",
    "iso:country":"GB",
    "sg:address":"28 Macdowall Street",
    "sg:city":"Johnstone",
    "sg:classifiers":[
        {
            "category":"Shopping",
            "subcategory":"Florist",
            "type":"Retail Goods"
        }
    ],
    "sg:phone":"+44 1505 323753",
    "sg:postcode":"PA5 8QL",
    "sg:province":"Renfrewshire",
    "wof:name":"Margaret Livingstone",
    "wof:placetype":"venue"
},
  "geometry": {"coordinates":[-4.515877,55.836246],"type":"Point"}
}