{
  "type": "Feature",
  "properties": {
    "addr:full":"41 Greystone Avenue, Kelloholm Sanquhar Dumfries and Galloway DG4 6RB",
    "addr:housenumber":"41",
    "addr:postcode":"dg4 6rb",
    "addr:street":"Greystone Avenue Kelloholm Sanquhar",
    "iso:country":"GB",
    "sg:address":"41 Greystone Avenue, Kelloholm",
    "sg:city":"Sanquhar",
    "sg:classifiers":[
        {
            "category":"Taxi",
            "type":"Transportation"
        },
        {
            "category":"Military Area",
            "subcategory":"Air Force Base",
            "type":"Public Place"
        }
    ],
    "sg:phone":"+44 1659 67000",
    "sg:postcode":"DG4 6RB",
    "sg:province":"Dumfries and Galloway",
    "sg:tags":[
        "mini",
        "hire",
        "private",
        "cab"
    ],
    "wof:name":"Griersons Taxis",
    "wof:placetype":"venue"
},
  "geometry": {"coordinates":[-3.9913089275,55.3793258667],"type":"Point"}
}