{
  "type": "Feature",
  "properties": {
    "addr:full":"Market Place Arbroath Angus DD11 1HR",
    "addr:postcode":"dd11 1hr",
    "addr:street":"Market Place",
    "iso:country":"GB",
    "sg:address":"Market Place",
    "sg:city":"Arbroath",
    "sg:classifiers":[
        {
            "category":"Military Area",
            "subcategory":"Air Force Base",
            "type":"Public Place"
        }
    ],
    "sg:phone":"+44 1241 873107",
    "sg:postcode":"DD11 1HR",
    "sg:province":"Angus",
    "sg:tags":[
        "taxi",
        "hire",
        "private"
    ],
    "wof:name":"Brothock Taxis",
    "wof:placetype":"venue"
},
  "geometry": {"coordinates":[-2.582556963,56.5586891174],"type":"Point"}
}