{
  "type": "Feature",
  "properties": {
    "iso:country":"GB",
    "sg:address":"57 Bird Hill Road, Woodhouse Eaves",
    "sg:city":"Loughborough",
    "sg:classifiers":[
        {
            "category":"Building & Trades",
            "subcategory":"Plumbing",
            "type":"Services"
        }
    ],
    "sg:postcode":"LE12 8RP",
    "sg:province":"Leicestershire",
    "sg:tags":[
        "central",
        "heating"
    ],
    "wof:name":"G P Goddard & Son",
    "wof:placetype":"venue"
},
  "geometry": {"coordinates":[-1.220874,52.727455],"type":"Point"}
}