{
  "type": "Feature",
  "properties": {
    "iso:country":"GB",
    "sg:address":"2 Adams Way",
    "sg:city":"Tring",
    "sg:classifiers":[
        {
            "category":"Professional",
            "subcategory":"Computer Services",
            "type":"Services"
        }
    ],
    "sg:phone":"+44 1442 382995",
    "sg:postcode":"HP23 5DY",
    "sg:province":"Buckinghamshire",
    "sg:tags":[
        "system",
        "software"
    ],
    "wof:name":"Wren Associates Ltd.",
    "wof:placetype":"venue"
},
  "geometry": {"coordinates":[-0.659487,51.803139],"type":"Point"}
}