{
  "type": "Feature",
  "properties": {
    "iso:country":"GB",
    "sg:address":"235 Vardon Road, Pin Grn",
    "sg:city":"Stevenage",
    "sg:classifiers":[
        {
            "category":"Building & Trades",
            "subcategory":"Construction",
            "type":"Services"
        }
    ],
    "sg:postcode":"SG1 5PY",
    "sg:province":"Hertfordshire",
    "sg:tags":[
        "decorator",
        "painter"
    ],
    "wof:name":"Three Counties",
    "wof:placetype":"venue"
},
  "geometry": {"coordinates":[-0.1830690056,51.9166412354],"type":"Point"}
}