{
  "type": "Feature",
  "properties": {
    "addr:full":"Yew Tree House, Upper Moor Pershore Worcestershire WR10 2JR",
    "addr:postcode":"wr10 2jr",
    "addr:street":"Yew;Upper Moor Pershore",
    "iso:country":"GB",
    "sg:address":"Yew Tree House, Upper Moor",
    "sg:city":"Pershore",
    "sg:classifiers":[
        {
            "category":"Health Services",
            "subcategory":"Nursing And Care Facility",
            "type":"Services"
        }
    ],
    "sg:phone":"+44 1386 860262",
    "sg:postcode":"WR10 2JR",
    "sg:province":"Worcestershire",
    "sg:tags":[
        "agency"
    ],
    "wof:name":"A C M Nursing Associates",
    "wof:placetype":"venue"
},
  "geometry": {"coordinates":[-2.0365099907,52.1259765625],"type":"Point"}
}