{
  "type": "Feature",
  "properties": {
    "addr:full":"38 Swaffham Road, Watton Thetford Norfolk IP25 6LA",
    "addr:housenumber":"38",
    "addr:postcode":"ip25 6la",
    "addr:street":"Swaffham Road",
    "iso:country":"GB",
    "sg:address":"38 Swaffham Road, Watton",
    "sg:city":"Thetford",
    "sg:classifiers":[
        {
            "category":"Real Estate",
            "subcategory":"Architect",
            "type":"Services"
        }
    ],
    "sg:phone":"+44 1953 882341",
    "sg:postcode":"IP25 6LA",
    "sg:province":"Norfolk",
    "sg:tags":[
        "architectural"
    ],
    "wof:name":"A E Warby",
    "wof:placetype":"venue"
},
  "geometry": {"coordinates":[0.81148,52.572903],"type":"Point"}
}