{
  "type": "Feature",
  "properties": {
    "iso:country":"GB",
    "sg:address":"Newbigging",
    "sg:city":"Lockerbie",
    "sg:classifiers":[
        {
            "category":"Farming",
            "subcategory":"Livestock Farm",
            "type":"Manufacturing & Wholesale Goods"
        }
    ],
    "sg:phone":"+44 1576 610228",
    "sg:postcode":"DG11 2LA",
    "sg:province":"Dumfries and Galloway",
    "sg:tags":[
        "others"
    ],
    "wof:name":"W & W J Jardine",
    "wof:placetype":"venue"
},
  "geometry": {"coordinates":[-3.354569,55.121777],"type":"Point"}
}