{
  "type": "Feature",
  "properties": {
    "addr:full":"4 King Street Saffron Walden Cambridgeshire CB10 1ES",
    "addr:housenumber":"4",
    "addr:postcode":"cb10 1es",
    "addr:street":"King Street",
    "iso:country":"GB",
    "sg:address":"4 King Street",
    "sg:city":"Saffron Walden",
    "sg:classifiers":[
        {
            "category":"Shopping",
            "subcategory":"Comic Books",
            "type":"Retail Goods"
        }
    ],
    "sg:phone":"+44 1799 523316",
    "sg:postcode":"CB10 1ES",
    "sg:province":"Cambridgeshire",
    "sg:tags":[
        "jeweller"
    ],
    "wof:name":"A James (Jewellers) Ltd.",
    "wof:placetype":"venue"
},
  "geometry": {"coordinates":[0.2408030033,52.0237121582],"type":"Point"}
}