{
  "type": "Feature",
  "properties": {
    "addr:full":"20 Euston Road Morecambe Lancashire LA4 5DD",
    "addr:housenumber":"20",
    "addr:postcode":"la4 5dd",
    "addr:street":"Euston Road",
    "iso:country":"GB",
    "sg:address":"20 Euston Road",
    "sg:city":"Morecambe",
    "sg:classifiers":[
        {
            "category":"Retail",
            "subcategory":"Photofinishing",
            "type":"Services"
        }
    ],
    "sg:phone":"+44 1524 832077",
    "sg:postcode":"LA4 5DD",
    "sg:province":"Lancashire",
    "sg:tags":[
        "photographic",
        "processor"
    ],
    "wof:name":"Klick Photopoint",
    "wof:placetype":"venue"
},
  "geometry": {"coordinates":[-2.863879,54.071892],"type":"Point"}
}