{
  "type": "Feature",
  "properties": {
    "addr:full":"Lower Farm, Taston Chipping Norton Gloucestershire OX7 3JL",
    "addr:postcode":"norton;ox7 3jl",
    "addr:street":"Taston",
    "iso:country":"GB",
    "sg:address":"Lower Farm, Taston",
    "sg:city":"Chipping Norton",
    "sg:classifiers":[
        {
            "category":"Manufacturing",
            "subcategory":"Pottery",
            "type":"Manufacturing & Wholesale Goods"
        }
    ],
    "sg:postcode":"OX7 3JL",
    "sg:province":"Gloucestershire",
    "wof:name":"Designaway Ltd.",
    "wof:placetype":"venue"
},
  "geometry": {"coordinates":[-1.4805239439,51.8964309692],"type":"Point"}
}