{
  "type": "Feature",
  "properties": {
    "iso:country":"GB",
    "sg:address":"37 Water Street",
    "sg:city":"Neath",
    "sg:classifiers":[
        {
            "category":"Shopping",
            "subcategory":"Musical Instruments",
            "type":"Retail Goods"
        }
    ],
    "sg:phone":"+44 1639 631337",
    "sg:postcode":"SA11 3ET",
    "sg:province":"Neath Port Talbot",
    "sg:tags":[
        "retailer",
        "sheet",
        "music"
    ],
    "wof:name":"Neath Music Centre",
    "wof:placetype":"venue"
},
  "geometry": {"coordinates":[-3.801007,51.661896],"type":"Point"}
}