{
  "type": "Feature",
  "properties": {
    "iso:country":"GB",
    "sg:address":"Newabbey Road",
    "sg:city":"Dumfries",
    "sg:classifiers":[
        {
            "category":"Autos & Motor Vehicles",
            "subcategory":"Automobile Sales",
            "type":"Retail Goods"
        }
    ],
    "sg:phone":"+44 1387 263000",
    "sg:postcode":"DG2 8ER",
    "sg:province":"Dumfries and Galloway",
    "sg:tags":[
        "car"
    ],
    "wof:name":"Arnold Clark Automobiles",
    "wof:placetype":"venue"
},
  "geometry": {"coordinates":[-3.6225850582,55.0644454956],"type":"Point"}
}