{
  "type": "Feature",
  "properties": {
    "addr:full":"75 Pendas Way Leeds West Yorkshire LS15 8HU",
    "addr:housenumber":"75",
    "addr:postcode":"ls15 8hu",
    "addr:street":"Pendas Way",
    "iso:country":"GB",
    "sg:address":"75 Pendas Way",
    "sg:city":"Leeds",
    "sg:classifiers":[
        {
            "category":"Personal",
            "subcategory":"Beauty Salon",
            "type":"Services"
        },
        {
            "category":"Personal",
            "subcategory":"Barber",
            "type":"Services"
        }
    ],
    "sg:phone":"+44 113 264 5825",
    "sg:postcode":"LS15 8HU",
    "sg:province":"West Yorkshire",
    "sg:tags":[
        "unisex",
        "hairdresser"
    ],
    "wof:name":"Helen Paul Hair Studio",
    "wof:placetype":"venue"
},
  "geometry": {"coordinates":[-1.4396749735,53.8102035522],"type":"Point"}
}