{
  "type": "Feature",
  "properties": {
    "iso:country":"GB",
    "sg:address":"21 California Road, Mistley",
    "sg:city":"Manningtree",
    "sg:classifiers":[
        {
            "category":"Food & Beverages",
            "subcategory":"Meat & Fish",
            "type":"Retail Goods"
        }
    ],
    "sg:postcode":"CO11 1HX",
    "sg:province":"Essex",
    "sg:tags":[
        "chip"
    ],
    "wof:name":"Barry Soames",
    "wof:placetype":"venue"
},
  "geometry": {"coordinates":[1.085319,51.942917],"type":"Point"}
}