{
  "type": "Feature",
  "properties": {
    "addr:full":"85 Peverel Road Cambridge Cambridgeshire CB5 8RN",
    "addr:housenumber":"85",
    "addr:postcode":"cb5 8rn",
    "addr:street":"Peverel Road",
    "iso:country":"GB",
    "sg:address":"85 Peverel Road",
    "sg:city":"Cambridge",
    "sg:classifiers":[
        {
            "category":"Utilities",
            "subcategory":"Refuse",
            "type":"Services"
        }
    ],
    "sg:phone":"+44 1223 411377",
    "sg:postcode":"CB5 8RN",
    "sg:province":"Cambridgeshire",
    "sg:tags":[
        "skip",
        "hire"
    ],
    "wof:name":"Direct Skips",
    "wof:placetype":"venue"
},
  "geometry": {"coordinates":[0.1666990072,52.2109336853],"type":"Point"}
}