{
  "type": "Feature",
  "properties": {
    "iso:country":"GB",
    "sg:address":"65 Western Rd",
    "sg:city":"Lewes",
    "sg:classifiers":[
        {
            "category":"Shopping",
            "subcategory":"Department Store",
            "type":"Retail Goods"
        }
    ],
    "sg:postcode":"BN7 1RS",
    "sg:province":"East Sussex",
    "wof:name":"Patel,N,",
    "wof:placetype":"venue"
},
  "geometry": {"coordinates":[-0.000417,50.8731],"type":"Point"}
}