{
  "type": "Feature",
  "properties": {
    "iso:country":"GB",
    "sg:address":"The Granary, Coal Rd",
    "sg:city":"Cupar",
    "sg:classifiers":[
        {
            "category":"Professional",
            "subcategory":"Art Services",
            "type":"Services"
        }
    ],
    "sg:phone":"+44 1334 655550",
    "sg:postcode":"KY15 5YQ",
    "sg:province":"Fife",
    "sg:tags":[
        "consultant",
        "design"
    ],
    "wof:name":"Redgate Creative Communication",
    "wof:placetype":"venue"
},
  "geometry": {"coordinates":[-3.035587,56.307716],"type":"Point"}
}