{
  "type": "Feature",
  "properties": {
    "addr:full":"Abbots Way, Doonfoot Ayr South Ayrshire KA7 4DN",
    "addr:postcode":"ka7 4dn",
    "addr:street":"Abbots Way Doonfoot",
    "iso:country":"GB",
    "sg:address":"Abbots Way, Doonfoot",
    "sg:city":"Ayr",
    "sg:classifiers":[
        {
            "category":"Education",
            "subcategory":"Preschool",
            "type":"Public Place"
        }
    ],
    "sg:phone":"+44 1292 443243",
    "sg:postcode":"KA7 4DN",
    "sg:province":"South Ayrshire",
    "sg:tags":[
        "pre-school",
        "playgroups"
    ],
    "wof:name":"Doonfoot Community Playgroup",
    "wof:placetype":"venue"
},
  "geometry": {"coordinates":[-4.6541190147,55.4366035461],"type":"Point"}
}