{
  "type": "Feature",
  "properties": {
    "addr:full":"24 Littlehaven Lane Horsham West Sussex RH12 4JA",
    "addr:housenumber":"24",
    "addr:postcode":"rh12 4ja",
    "addr:street":"Littlehaven Lane",
    "iso:country":"GB",
    "sg:address":"24 Littlehaven Lane",
    "sg:city":"Horsham",
    "sg:classifiers":[
        {
            "category":"Professional",
            "subcategory":"Management & Consulting",
            "type":"Services"
        }
    ],
    "sg:postcode":"RH12 4JA",
    "sg:province":"West Sussex",
    "sg:tags":[
        "consultant",
        "business"
    ],
    "wof:name":"Forest Edge Consulting Ltd",
    "wof:placetype":"venue"
},
  "geometry": {"coordinates":[-0.3070330024,51.0767745972],"type":"Point"}
}