{
  "type": "Feature",
  "properties": {
    "addr:full":"61 Norfolk Road, Cliftonville Margate Kent CT9 2HX",
    "addr:housenumber":"61",
    "addr:postcode":"ct9 2hx",
    "addr:street":"Norfolk Road;Margate",
    "iso:country":"GB",
    "sg:address":"61 Norfolk Road, Cliftonville",
    "sg:city":"Margate",
    "sg:classifiers":[
        {
            "category":"Travel",
            "subcategory":"Hotels & Motels",
            "type":"Entertainment"
        }
    ],
    "sg:phone":"+44 1843 221053",
    "sg:postcode":"CT9 2HX",
    "sg:province":"Kent",
    "wof:name":"Lonsdale Court Hotel",
    "wof:placetype":"venue"
},
  "geometry": {"coordinates":[1.4011460543,51.3884468079],"type":"Point"}
}