{
  "type": "Feature",
  "properties": {
    "addr:full":"Angel Works, Angel Road London Greater London N18 3AH",
    "addr:postcode":"n18 3ah",
    "addr:street":"Angel Road",
    "iso:country":"GB",
    "sg:address":"Angel Works, Angel Road",
    "sg:city":"London",
    "sg:classifiers":[
        {
            "category":"Retail",
            "subcategory":"Auto Repair",
            "type":"Services"
        }
    ],
    "sg:postcode":"N18 3AH",
    "sg:province":"Greater London",
    "sg:tags":[
        "modification",
        "garage"
    ],
    "wof:name":"Kingdom Motors",
    "wof:placetype":"venue"
},
  "geometry": {"coordinates":[-0.045344,51.613365],"type":"Point"}
}