{
  "type": "Feature",
  "properties": {
    "iso:country":"GB",
    "sg:address":"Garratt Street",
    "sg:city":"West Bromwich",
    "sg:classifiers":[
        {
            "category":"Bars & Pubs",
            "type":"Food & Drink"
        }
    ],
    "sg:phone":"+44 121 553 3474",
    "sg:postcode":"B71 1NE",
    "sg:province":"West Midlands",
    "sg:tags":[
        "pubs",
        "inn"
    ],
    "wof:name":"Merry Go Round",
    "wof:placetype":"venue"
},
  "geometry": {"coordinates":[-2.000219,52.526749],"type":"Point"}
}