{
  "type": "Feature",
  "properties": {
    "addr:full":"Venn Farm, London Road, Milborne Port Sherborne Dorset DT9 5RA",
    "addr:postcode":"dt9 5ra",
    "addr:street":"Venn;London Road",
    "iso:country":"GB",
    "sg:address":"Venn Farm, London Road, Milborne Port",
    "sg:city":"Sherborne",
    "sg:classifiers":[
        {
            "category":"Farming",
            "subcategory":"Livestock Farm",
            "type":"Manufacturing & Wholesale Goods"
        }
    ],
    "sg:phone":"+44 1963 250598",
    "sg:postcode":"DT9 5RA",
    "sg:province":"Dorset",
    "sg:tags":[
        "others"
    ],
    "wof:name":"Venn Farm",
    "wof:placetype":"venue"
},
  "geometry": {"coordinates":[-2.4601790905,50.9662742615],"type":"Point"}
}