{
  "type": "Feature",
  "properties": {
    "addr:full":"47 Bierley Lane Bradford West Yorkshire BD4 6AD",
    "addr:housenumber":"47",
    "addr:postcode":"bd4 6ad",
    "addr:street":"Bierley Lane",
    "iso:country":"GB",
    "sg:address":"47 Bierley Lane",
    "sg:city":"Bradford",
    "sg:classifiers":[
        {
            "category":"Organizations",
            "subcategory":"Membership Organization",
            "type":"Services"
        }
    ],
    "sg:postcode":"BD4 6AD",
    "sg:province":"West Yorkshire",
    "sg:tags":[
        "club"
    ],
    "wof:name":"Currer House Social Club",
    "wof:placetype":"venue"
},
  "geometry": {"coordinates":[-1.732311964,53.7675857544],"type":"Point"}
}