{
  "type": "Feature",
  "properties": {
    "addr:full":"748-752 Alum Rock Road Birmingham West Midlands B8 2AG",
    "addr:postcode":"748-752;b8 2ag",
    "addr:street":"Alum Rock Road",
    "iso:country":"GB",
    "sg:address":"748-752 Alum Rock Road",
    "sg:city":"Birmingham",
    "sg:classifiers":[
        {
            "category":"Food & Beverages",
            "subcategory":"Supermarket",
            "type":"Retail Goods"
        }
    ],
    "sg:phone":"+44 121 328 4757",
    "sg:postcode":"B8 2AG",
    "sg:province":"West Midlands",
    "wof:name":"Pelham Discount Supermarket & Off Licence",
    "wof:placetype":"venue"
},
  "geometry": {"coordinates":[-1.830619,52.488941],"type":"Point"}
}