{
  "type": "Feature",
  "properties": {
    "addr:full":"20 Overend Way Sheffield South Yorkshire S14 1JF",
    "addr:housenumber":"20",
    "addr:postcode":"s14 1jf",
    "addr:street":"Overend Way",
    "iso:country":"GB",
    "sg:address":"20 Overend Way",
    "sg:city":"Sheffield",
    "sg:classifiers":[
        {
            "category":"Home & Garden",
            "subcategory":"Carpets & Floor Coverings",
            "type":"Retail Goods"
        }
    ],
    "sg:phone":"+44 114 264 4694",
    "sg:postcode":"S14 1JF",
    "sg:province":"South Yorkshire",
    "sg:tags":[
        "cleaner",
        "upholstery"
    ],
    "wof:name":"A1 Cleaning Services",
    "wof:placetype":"venue"
},
  "geometry": {"coordinates":[-1.446385026,53.3479309082],"type":"Point"}
}