{
  "type": "Feature",
  "properties": {
    "addr:full":"22 Frith Street London Greater London W1D 4RP",
    "addr:housenumber":"22",
    "addr:postcode":"w1d 4rp",
    "addr:street":"Frith Street",
    "iso:country":"GB",
    "sg:address":"22 Frith Street",
    "sg:city":"London",
    "sg:classifiers":[
        {
            "category":"Cafe",
            "type":"Food & Drink"
        }
    ],
    "sg:phone":"+44 20 7437 4520",
    "sg:postcode":"W1D 4RP",
    "sg:province":"Greater London",
    "sg:tags":[
        "tea",
        "room"
    ],
    "wof:name":"Bar Italia",
    "wof:placetype":"venue"
},
  "geometry": {"coordinates":[-0.131141,51.513397],"type":"Point"}
}