{
  "type": "Feature",
  "properties": {
    "addr:full":"P O Box 782 Maidenhead Berkshire SL6 1FR",
    "addr:housenumber":"782",
    "addr:postcode":"sl6 1fr",
    "addr:street":"P O Box",
    "iso:country":"GB",
    "sg:address":"P O Box 782",
    "sg:city":"Maidenhead",
    "sg:classifiers":[
        {
            "category":"Professional",
            "subcategory":"Management & Consulting",
            "type":"Services"
        }
    ],
    "sg:phone":"+44 1628 673946",
    "sg:postcode":"SL6 1FR",
    "sg:province":"Berkshire",
    "sg:tags":[
        "consultant",
        "business"
    ],
    "wof:name":"Arlington Associates Ltd.",
    "wof:placetype":"venue"
},
  "geometry": {"coordinates":[-0.7272570133,51.5223731995],"type":"Point"}
}