{
  "type": "Feature",
  "properties": {
    "addr:full":"35 Redhill Close, Derry Hill Calne Wiltshire SN11 9NY",
    "addr:housenumber":"35",
    "addr:postcode":"sn11 9ny",
    "addr:street":"Redhill Close",
    "iso:country":"GB",
    "sg:address":"35 Redhill Close, Derry Hill",
    "sg:city":"Calne",
    "sg:classifiers":[
        {
            "category":"Professional",
            "subcategory":"Management & Consulting",
            "type":"Services"
        }
    ],
    "sg:phone":"+44 20 7308 3474",
    "sg:postcode":"SN11 9NY",
    "sg:province":"Wiltshire",
    "sg:tags":[
        "consultant",
        "business"
    ],
    "wof:name":"Metrotek Consulting Ltd.",
    "wof:placetype":"venue"
},
  "geometry": {"coordinates":[-2.0605459213,51.436630249],"type":"Point"}
}