{
  "type": "Feature",
  "properties": {
    "addr:full":"4 Kyrle Street Hereford Herefordshire HR1 2EU",
    "addr:housenumber":"4",
    "addr:postcode":"hr1 2eu",
    "addr:street":"Kyrle Street",
    "iso:country":"GB",
    "sg:address":"4 Kyrle Street",
    "sg:city":"Hereford",
    "sg:classifiers":[
        {
            "category":"Insurance",
            "subcategory":"Insurance Agent",
            "type":"Services"
        }
    ],
    "sg:phone":"+44 1432 272912",
    "sg:postcode":"HR1 2EU",
    "sg:province":"Herefordshire",
    "wof:name":"Britannic Assurance Plc",
    "wof:placetype":"venue"
},
  "geometry": {"coordinates":[-2.7105360031,52.0566711426],"type":"Point"}
}