{
  "type": "Feature",
  "properties": {
    "addr:full":"3 Arnold Road Clacton-on-sea Essex CO15 1DD",
    "addr:housenumber":"3",
    "addr:postcode":"co15 1dd",
    "addr:street":"Arnold Road",
    "iso:country":"GB",
    "sg:address":"3 Arnold Road",
    "sg:city":"Clacton-on-sea",
    "sg:classifiers":[
        {
            "category":"Building & Trades",
            "subcategory":"Construction",
            "type":"Services"
        }
    ],
    "sg:phone":"+44 1255 422442",
    "sg:postcode":"CO15 1DD",
    "sg:province":"Essex",
    "sg:tags":[
        "builder"
    ],
    "wof:name":"Frank N Deans",
    "wof:placetype":"venue"
},
  "geometry": {"coordinates":[1.146242,51.786648],"type":"Point"}
}