{
  "type": "Feature",
  "properties": {
    "addr:full":"507 Ashingdon Road Rochford Essex SS4 3HE",
    "addr:housenumber":"507",
    "addr:postcode":"ss4 3he",
    "addr:street":"Ashingdon Road",
    "iso:country":"GB",
    "sg:address":"507 Ashingdon Road",
    "sg:city":"Rochford",
    "sg:classifiers":[
        {
            "category":"Shopping",
            "subcategory":"Computers & Home Electronics",
            "type":"Retail Goods"
        }
    ],
    "sg:phone":"+44 1702 549333",
    "sg:postcode":"SS4 3HE",
    "sg:province":"Essex",
    "sg:tags":[
        "electrical"
    ],
    "wof:name":"Solenoid Technology Ltd.",
    "wof:placetype":"venue"
},
  "geometry": {"coordinates":[0.6882100105,51.6105613708],"type":"Point"}
}