{
  "type": "Feature",
  "properties": {
    "addr:full":"41 Cleaveland Rd Surbiton Surrey KT6 4AH",
    "addr:housenumber":"41",
    "addr:postcode":"kt6 4ah",
    "addr:street":"Cleaveland Rd",
    "iso:country":"GB",
    "sg:address":"41 Cleaveland Rd",
    "sg:city":"Surbiton",
    "sg:classifiers":[
        {
            "category":"Fast Food",
            "type":"Food & Drink"
        }
    ],
    "sg:postcode":"KT6 4AH",
    "sg:province":"Surrey",
    "sg:tags":[
        "away",
        "take"
    ],
    "wof:name":"Lydlen,L,",
    "wof:placetype":"venue"
},
  "geometry": {"coordinates":[-0.311258,51.395603],"type":"Point"}
}