{
  "type": "Feature",
  "properties": {
    "addr:full":"Oak Farm, Hampton Lane, Catherine De Barnes Solihull West Midlands B92 0JB",
    "addr:postcode":"b92 0jb",
    "addr:street":"Oak;Hampton Lane;De Barnes",
    "iso:country":"GB",
    "sg:address":"Oak Farm, Hampton Lane, Catherine De Barnes",
    "sg:city":"Solihull",
    "sg:classifiers":[
        {
            "category":"Retail",
            "subcategory":"Storage",
            "type":"Services"
        }
    ],
    "sg:phone":"+44 121 705 5155",
    "sg:postcode":"B92 0JB",
    "sg:province":"West Midlands",
    "sg:tags":[
        "household",
        "removal"
    ],
    "wof:name":"Oak Farm",
    "wof:placetype":"venue"
},
  "geometry": {"coordinates":[-1.736199975,52.4213485718],"type":"Point"}
}