{
  "type": "Feature",
  "properties": {
    "addr:full":"2 Alpha Road Bristol City of Bristol BS3 1DH",
    "addr:housenumber":"2",
    "addr:postcode":"bs3 1dh",
    "addr:street":"Alpha Road",
    "iso:country":"GB",
    "sg:address":"2 Alpha Road",
    "sg:city":"Bristol",
    "sg:classifiers":[
        {
            "category":"Bars & Pubs",
            "type":"Food & Drink"
        }
    ],
    "sg:phone":"+44 117 953 5188",
    "sg:postcode":"BS3 1DH",
    "sg:province":"City of Bristol",
    "sg:tags":[
        "pubs",
        "inn"
    ],
    "wof:name":"The Imperial",
    "wof:placetype":"venue"
},
  "geometry": {"coordinates":[-2.597855,51.444778],"type":"Point"}
}