{
  "type": "Feature",
  "properties": {
    "addr:full":"E Center ?the}, Coobridge Way Alloa Clackmannanshire FK10 3LP",
    "addr:postcode":"fk10 3lp",
    "addr:street":"The Coobridge Way",
    "iso:country":"GB",
    "sg:address":"E Center ?the}, Coobridge Way",
    "sg:city":"Alloa",
    "sg:classifiers":[
        {
            "category":"Professional",
            "subcategory":"Management & Consulting",
            "type":"Services"
        }
    ],
    "sg:phone":"+44 1259 272158",
    "sg:postcode":"FK10 3LP",
    "sg:province":"Clackmannanshire",
    "sg:tags":[
        "consultant",
        "energy",
        "conservation"
    ],
    "wof:name":"Green Power",
    "wof:placetype":"venue"
},
  "geometry": {"coordinates":[-3.7951939106,56.1163215637],"type":"Point"}
}