{
  "type": "Feature",
  "properties": {
    "iso:country":"GB",
    "sg:address":"89 Market St, Chapel-en-le-frith, High Peak",
    "sg:city":"High Peak",
    "sg:classifiers":[
        {
            "category":"Food & Beverages",
            "subcategory":"Candy",
            "type":"Retail Goods"
        },
        {
            "category":"Food & Beverages",
            "subcategory":"Bakery",
            "type":"Retail Goods"
        }
    ],
    "sg:postcode":"SK23 0JD",
    "sg:province":"Cheshire",
    "sg:tags":[
        "confectioner",
        "baker"
    ],
    "wof:name":"Redfern,F & V,",
    "wof:placetype":"venue"
},
  "geometry": {"coordinates":[-1.910461,53.324467],"type":"Point"}
}