{
  "type": "Feature",
  "properties": {
    "addr:full":"58 Arlington Avenue, Goring-by-sea Worthing West Sussex BN12 4SR",
    "addr:housenumber":"58",
    "addr:postcode":"bn12 4sr",
    "addr:street":"Arlington Avenue",
    "iso:country":"GB",
    "sg:address":"58 Arlington Avenue, Goring-by-sea",
    "sg:city":"Worthing",
    "sg:classifiers":[
        {
            "category":"Arts & Performance",
            "subcategory":"Music",
            "type":"Entertainment"
        }
    ],
    "sg:postcode":"BN12 4SR",
    "sg:province":"West Sussex",
    "sg:tags":[
        "mobile",
        "disco"
    ],
    "wof:name":"Arizona Discos",
    "wof:placetype":"venue"
},
  "geometry": {"coordinates":[-0.427273,50.8092],"type":"Point"}
}