{
  "type": "Feature",
  "properties": {
    "iso:country":"GB",
    "sg:address":"152-158 Albert Road",
    "sg:city":"Plymouth",
    "sg:classifiers":[
        {
            "category":"Professional",
            "subcategory":"Testing Lab",
            "type":"Services"
        },
        {
            "category":"Autos & Motor Vehicles",
            "subcategory":"Motorcycle Sales",
            "type":"Retail Goods"
        }
    ],
    "sg:phone":"+44 1752 559063",
    "sg:postcode":"PL2 1AQ",
    "sg:province":"Devon",
    "sg:tags":[
        "mot"
    ],
    "wof:name":"G T Motorcycles (Plymouth)",
    "wof:placetype":"venue"
},
  "geometry": {"coordinates":[-4.174352,50.378925],"type":"Point"}
}