{
  "type": "Feature",
  "properties": {
    "iso:country":"GB",
    "sg:address":"34 Runnymede Ave",
    "sg:city":"Bournemouth",
    "sg:classifiers":[
        {
            "category":"Professional",
            "subcategory":"Engineering",
            "type":"Services"
        }
    ],
    "sg:postcode":"BH11 9SF",
    "sg:province":"Dorset",
    "sg:tags":[
        "contractor",
        "electrical",
        "engineer"
    ],
    "wof:name":"Hart,Alan,",
    "wof:placetype":"venue"
},
  "geometry": {"coordinates":[-1.931894,50.770344],"type":"Point"}
}