{
  "type": "Feature",
  "properties": {
    "addr:full":"14 Alexandra Road, Horsforth Leeds West Yorkshire LS18 4HD",
    "addr:housenumber":"14",
    "addr:postcode":"ls18 4hd",
    "addr:street":"Alexandra Road",
    "iso:country":"GB",
    "sg:address":"14 Alexandra Road, Horsforth",
    "sg:city":"Leeds",
    "sg:classifiers":[
        {
            "category":"Health Services",
            "subcategory":"Dentist",
            "type":"Services"
        }
    ],
    "sg:phone":"+44 113 259 0190",
    "sg:postcode":"LS18 4HD",
    "sg:province":"West Yorkshire",
    "wof:name":"Alexandra Road Dental Practice",
    "wof:placetype":"venue"
},
  "geometry": {"coordinates":[-1.6302160025,53.8373718262],"type":"Point"}
}