{
  "type": "Feature",
  "properties": {
    "addr:full":"2 South Avenue Richmond Greater London TW9 3LY",
    "addr:housenumber":"2",
    "addr:postcode":"tw9 3ly",
    "addr:street":"South Avenue",
    "iso:country":"GB",
    "sg:address":"2 South Avenue",
    "sg:city":"Richmond",
    "sg:classifiers":[
        {
            "category":"Health Services",
            "subcategory":"Doctor",
            "type":"Services"
        },
        {
            "category":"Shopping",
            "subcategory":"Gifts & Souvenirs",
            "type":"Retail Goods"
        }
    ],
    "sg:phone":"+44 20 8948 5077",
    "sg:postcode":"TW9 3LY",
    "sg:province":"Greater London",
    "sg:tags":[
        "surgeon",
        "christmas"
    ],
    "wof:name":"O Widmann Co. Ltd.",
    "wof:placetype":"venue"
},
  "geometry": {"coordinates":[-0.2863459885,51.4746894836],"type":"Point"}
}