{
  "type": "Feature",
  "properties": {
    "addr:full":"166 Windsor Street Liverpool Merseyside L8 8EH",
    "addr:housenumber":"166",
    "addr:postcode":"l8 8eh",
    "addr:street":"Windsor Street",
    "iso:country":"GB",
    "sg:address":"166 Windsor Street",
    "sg:city":"Liverpool",
    "sg:classifiers":[
        {
            "category":"Food & Beverages",
            "subcategory":"Liquor & Beverages",
            "type":"Retail Goods"
        }
    ],
    "sg:phone":"+44 151 280 2287",
    "sg:postcode":"L8 8EH",
    "sg:province":"Merseyside",
    "sg:tags":[
        "beer",
        "spirit",
        "wines"
    ],
    "wof:name":"Windsor Wines & Spirits",
    "wof:placetype":"venue"
},
  "geometry": {"coordinates":[-2.9665019512,53.3903961182],"type":"Point"}
}