{
  "type": "Feature",
  "properties": {
    "iso:country":"GB",
    "sg:address":"58 Bampton Street",
    "sg:city":"Tiverton",
    "sg:classifiers":[
        {
            "category":"Shopping",
            "subcategory":"Books",
            "type":"Retail Goods"
        }
    ],
    "sg:phone":"+44 1884 255769",
    "sg:postcode":"EX16 6AH",
    "sg:province":"Devon",
    "sg:tags":[
        "bookseller"
    ],
    "wof:name":"New Creation",
    "wof:placetype":"venue"
},
  "geometry": {"coordinates":[-3.486237,50.905567],"type":"Point"}
}