{
  "type": "Feature",
  "properties": {
    "iso:country":"GB",
    "sg:address":"Unit Q, Fiveways Ind Est, Westwells Rd, Hawthorn",
    "sg:city":"Corsham",
    "sg:classifiers":[
        {
            "category":"Manufacturing",
            "subcategory":"Building Materials",
            "type":"Manufacturing & Wholesale Goods"
        }
    ],
    "sg:phone":"+44 1225 812984",
    "sg:postcode":"SN13 9RG",
    "sg:province":"Wiltshire",
    "sg:tags":[
        "concrete",
        "product"
    ],
    "wof:name":"Corsham Patio Centre",
    "wof:placetype":"venue"
},
  "geometry": {"coordinates":[-2.1872389317,51.4314842224],"type":"Point"}
}