{
  "type": "Feature",
  "properties": {
    "addr:full":"4 Whitfield Street London Greater London W1T 2RF",
    "addr:housenumber":"4",
    "addr:postcode":"w1t 2rf",
    "addr:street":"Whitfield Street",
    "iso:country":"GB",
    "sg:address":"4 Whitfield Street",
    "sg:city":"London",
    "sg:classifiers":[
        {
            "category":"Wholesale",
            "subcategory":"Music Publishers",
            "type":"Manufacturing & Wholesale Goods"
        }
    ],
    "sg:phone":"+44 20 7681 8900",
    "sg:postcode":"W1T 2RF",
    "sg:province":"Greater London",
    "wof:name":"J W Media Music Ltd.",
    "wof:placetype":"venue"
},
  "geometry": {"coordinates":[-0.1336310059,51.5191307068],"type":"Point"}
}