{
  "type": "Feature",
  "properties": {
    "iso:country":"GB",
    "sg:address":"P O Box 1588",
    "sg:city":"London",
    "sg:classifiers":[
        {
            "category":"Professional",
            "subcategory":"Computer Services",
            "type":"Services"
        }
    ],
    "sg:phone":"+44 20 7727 4504",
    "sg:postcode":"SW10 9XF",
    "sg:province":"Greater London",
    "sg:tags":[
        "security",
        "retail"
    ],
    "wof:name":"Avant Guardian Ltd.",
    "wof:placetype":"venue"
},
  "geometry": {"coordinates":[-0.187059,51.485619],"type":"Point"}
}