{
  "type": "Feature",
  "properties": {
    "iso:country":"GB",
    "sg:address":"Tregolls Road",
    "sg:city":"Truro",
    "sg:classifiers":[
        {
            "category":"Home & Garden",
            "subcategory":"Furniture",
            "type":"Retail Goods"
        }
    ],
    "sg:phone":"+44 1872 222226",
    "sg:postcode":"TR1 1SB",
    "sg:province":"Cornwall",
    "wof:name":"Julian & Son Ltd.",
    "wof:placetype":"venue"
},
  "geometry": {"coordinates":[-5.036685,50.268459],"type":"Point"}
}