{
  "type": "Feature",
  "properties": {
    "iso:country":"GB",
    "sg:address":"Magdala House, Innes Park Road",
    "sg:city":"Skelmorlie",
    "sg:classifiers":[
        {
            "category":"Building & Trades",
            "subcategory":"Construction",
            "type":"Services"
        }
    ],
    "sg:phone":"+44 1475 520979",
    "sg:postcode":"PA17 5BA",
    "sg:province":"North Ayrshire",
    "sg:tags":[
        "glazier",
        "decorator",
        "painter"
    ],
    "wof:name":"Baillie Painters & Decorators",
    "wof:placetype":"venue"
},
  "geometry": {"coordinates":[-4.880654,55.871857],"type":"Point"}
}