{
  "type": "Feature",
  "properties": {
    "addr:full":"42 Mkt Sq Dunstable Bedfordshire LU5 6BS",
    "addr:housenumber":"42",
    "addr:postcode":"lu5 6bs",
    "addr:street":"Mkt Sq",
    "iso:country":"GB",
    "sg:address":"42 Mkt Sq",
    "sg:city":"Dunstable",
    "sg:classifiers":[
        {
            "category":"Travel",
            "subcategory":"Travel Agent",
            "type":"Entertainment"
        }
    ],
    "sg:postcode":"LU5 6BS",
    "sg:province":"Bedfordshire",
    "wof:name":"Elusive Spain Ltd",
    "wof:placetype":"venue"
},
  "geometry": {"coordinates":[-0.53263098,51.94871521],"type":"Point"}
}