{
  "type": "Feature",
  "properties": {
    "addr:full":"19 Church St Littlehampton West Sussex BN17 5EL",
    "addr:housenumber":"19",
    "addr:postcode":"bn17 5el",
    "addr:street":"Church St",
    "iso:country":"GB",
    "sg:address":"19 Church St",
    "sg:city":"Littlehampton",
    "sg:classifiers":[
        {
            "category":"Retail",
            "subcategory":"Storage",
            "type":"Services"
        }
    ],
    "sg:phone":"+44 1903 717837",
    "sg:postcode":"BN17 5EL",
    "sg:province":"West Sussex",
    "sg:tags":[
        "household",
        "removal"
    ],
    "wof:name":"Russells Man & Van Hire",
    "wof:placetype":"venue"
},
  "geometry": {"coordinates":[-0.5390170217,50.8096351624],"type":"Point"}
}