{
  "type": "Feature",
  "properties": {
    "addr:full":"121 Clarendon Rd Notting Hill Greater London W11 4JG",
    "addr:housenumber":"121",
    "addr:postcode":"w11 4jg",
    "addr:street":"Clarendon Rd",
    "iso:country":"GB",
    "sg:address":"121 Clarendon Rd",
    "sg:city":"Notting Hill",
    "sg:classifiers":[
        {
            "category":"Shopping",
            "subcategory":"Luggage & Leather Goods",
            "type":"Retail Goods"
        }
    ],
    "sg:phone":"+44 20 7221 1838",
    "sg:postcode":"W11 4JG",
    "sg:province":"Greater London",
    "sg:tags":[
        "shop",
        "leathergoods"
    ],
    "wof:name":"Maple Furs (Sheepskin Goods) Ltd",
    "wof:placetype":"venue"
},
  "geometry": {"coordinates":[-0.2112289965,51.5125045776],"type":"Point"}
}