{
  "type": "Feature",
  "properties": {
    "iso:country":"GB",
    "sg:address":"1-3 Hookrise South",
    "sg:city":"Surbiton",
    "sg:classifiers":[
        {
            "category":"Professional",
            "subcategory":"Computer Services",
            "type":"Services"
        }
    ],
    "sg:phone":"+44 20 8391 4488",
    "sg:postcode":"KT6 7LD",
    "sg:province":"Surrey",
    "sg:tags":[
        "system",
        "software"
    ],
    "wof:name":"Bluepoint Ltd",
    "wof:placetype":"venue"
},
  "geometry": {"coordinates":[-0.29077,51.373192],"type":"Point"}
}