{
  "type": "Feature",
  "properties": {
    "addr:full":"292 Vauxhall Bridge Road London Greater London SW1V 1AE",
    "addr:housenumber":"292",
    "addr:postcode":"sw1v 1ae",
    "addr:street":"Vauxhall Bridge Road",
    "iso:country":"GB",
    "sg:address":"292 Vauxhall Bridge Road",
    "sg:city":"London",
    "sg:classifiers":[
        {
            "category":"Banks & Credit Unions",
            "subcategory":"Bureau De Change",
            "type":"Services"
        }
    ],
    "sg:phone":"+44 20 7828 4953",
    "sg:postcode":"SW1V 1AE",
    "sg:province":"Greater London",
    "wof:name":"Corporate Foreign Exchange Ltd.",
    "wof:placetype":"venue"
},
  "geometry": {"coordinates":[-0.141695,51.49514],"type":"Point"}
}