{
  "type": "Feature",
  "properties": {
    "iso:country":"GB",
    "sg:address":"2 Lower Sandfields, Send",
    "sg:city":"Woking",
    "sg:classifiers":[
        {
            "category":"Building & Trades",
            "subcategory":"Landscaping Services",
            "type":"Services"
        }
    ],
    "sg:phone":"+44 1483 453645",
    "sg:postcode":"GU23 7AX",
    "sg:province":"Surrey",
    "sg:tags":[
        "gardening"
    ],
    "wof:name":"G Barrett",
    "wof:placetype":"venue"
},
  "geometry": {"coordinates":[-0.524238,51.287102],"type":"Point"}
}