{
  "type": "Feature",
  "properties": {
    "iso:country":"GB",
    "sg:address":"23 Mitchell Point",
    "sg:city":"Southampton",
    "sg:classifiers":[
        {
            "category":"Communications",
            "subcategory":"News Services",
            "type":"Services"
        }
    ],
    "sg:phone":"+44 23 8045 8800",
    "sg:postcode":"SO31 4RF",
    "sg:province":"Hampshire",
    "sg:tags":[
        "photo",
        "agency"
    ],
    "wof:name":"Solent News & Photo Agency",
    "wof:placetype":"venue"
},
  "geometry": {"coordinates":[-1.327141,50.857323],"type":"Point"}
}