{
  "type": "Feature",
  "properties": {
    "addr:full":"13 East Street Hythe Kent CT21 5ND",
    "addr:housenumber":"13",
    "addr:postcode":"ct21 5nd",
    "addr:street":"East Street",
    "iso:country":"GB",
    "sg:address":"13 East Street",
    "sg:city":"Hythe",
    "sg:classifiers":[
        {
            "category":"Shopping",
            "subcategory":"Pets & Pet Supplies",
            "type":"Retail Goods"
        }
    ],
    "sg:postcode":"CT21 5ND",
    "sg:province":"Kent",
    "sg:tags":[
        "food"
    ],
    "wof:name":"K C S Pet Foods",
    "wof:placetype":"venue"
},
  "geometry": {"coordinates":[1.0913850069,51.0724334717],"type":"Point"}
}