{
  "type": "Feature",
  "properties": {
    "iso:country":"GB",
    "sg:address":"13-14 Union Quay",
    "sg:city":"North Shields",
    "sg:classifiers":[
        {
            "category":"Farming",
            "subcategory":"Fish & Marine Products",
            "type":"Manufacturing & Wholesale Goods"
        }
    ],
    "sg:phone":"+44 191 296 1361",
    "sg:postcode":"NE30 1HJ",
    "sg:province":"Tyne and Wear",
    "sg:tags":[
        "fishmonger"
    ],
    "wof:name":"Hewison Seafoods",
    "wof:placetype":"venue"
},
  "geometry": {"coordinates":[-1.435812,55.009434],"type":"Point"}
}