{
  "type": "Feature",
  "properties": {
    "iso:country":"GB",
    "sg:address":"Cargo House, Prestwick Airport",
    "sg:city":"Prestwick",
    "sg:classifiers":[
        {
            "category":"Communications",
            "subcategory":"Newspaper",
            "type":"Services"
        }
    ],
    "sg:phone":"+44 1292 678877",
    "sg:postcode":"KA9 2PL",
    "sg:province":"South Ayrshire",
    "sg:tags":[
        "magazine"
    ],
    "wof:name":"Direct News",
    "wof:placetype":"venue"
},
  "geometry": {"coordinates":[-4.599251,55.516792],"type":"Point"}
}