{
  "type": "Feature",
  "properties": {
    "addr:full":"Great Oak Farm, Bignall End Stoke On Trent Cheshire ST7 8NF",
    "addr:postcode":"st7 8nf",
    "addr:street":"Great Oak Farm Bignall End Stoke On Trent",
    "iso:country":"GB",
    "sg:address":"Great Oak Farm, Bignall End",
    "sg:city":"Stoke On Trent",
    "sg:classifiers":[
        {
            "category":"Farming",
            "subcategory":"Farm",
            "type":"Manufacturing & Wholesale Goods"
        }
    ],
    "sg:phone":"+44 1782 720242",
    "sg:postcode":"ST7 8NF",
    "sg:province":"Cheshire",
    "sg:tags":[
        "mixed",
        "crop"
    ],
    "wof:name":"David Russell Cole",
    "wof:placetype":"venue"
},
  "geometry": {"coordinates":[-2.2893600464,53.0610198975],"type":"Point"}
}