{
  "type": "Feature",
  "properties": {
    "iso:country":"GB",
    "sg:address":"446 West Rd",
    "sg:city":"Newcastle Upon Tyne",
    "sg:classifiers":[
        {
            "category":"Organizations",
            "subcategory":"Membership Organization",
            "type":"Services"
        }
    ],
    "sg:phone":"+44 191 274 1288",
    "sg:postcode":"NE5 2ER",
    "sg:province":"Tyne and Wear",
    "sg:tags":[
        "club"
    ],
    "wof:name":"West Acres Club Ltd",
    "wof:placetype":"venue"
},
  "geometry": {"coordinates":[-1.672748,54.979813],"type":"Point"}
}