{
  "type": "Feature",
  "properties": {
    "addr:full":"7 Darnell Road Edinburgh City of Edinburgh EH5 3PQ",
    "addr:housenumber":"7",
    "addr:postcode":"eh5 3pq",
    "addr:street":"Darnell Road",
    "iso:country":"GB",
    "sg:address":"7 Darnell Road",
    "sg:city":"Edinburgh",
    "sg:classifiers":[
        {
            "category":"Shopping",
            "subcategory":"Gifts & Souvenirs",
            "type":"Retail Goods"
        }
    ],
    "sg:phone":"+44 131 552 3000",
    "sg:postcode":"EH5 3PQ",
    "sg:province":"City of Edinburgh",
    "sg:tags":[
        "greeting",
        "card"
    ],
    "wof:name":"Graeme Menzies",
    "wof:placetype":"venue"
},
  "geometry": {"coordinates":[-3.209721,55.973686],"type":"Point"}
}