{
  "type": "Feature",
  "properties": {
    "addr:full":"Callow Hall, Kirk Ireton Ashbourne Derbyshire DE6 3JY",
    "addr:postcode":"de6 3jy",
    "iso:country":"GB",
    "sg:address":"Callow Hall, Kirk Ireton",
    "sg:city":"Ashbourne",
    "sg:classifiers":[
        {
            "category":"Farming",
            "subcategory":"Dairy Farm",
            "type":"Manufacturing & Wholesale Goods"
        }
    ],
    "sg:postcode":"DE6 3JY",
    "sg:province":"Derbyshire",
    "wof:name":"Andrew Rowland",
    "wof:placetype":"venue"
},
  "geometry": {"coordinates":[-1.602169,53.048016],"type":"Point"}
}