{
  "type": "Feature",
  "properties": {
    "addr:full":"Bath Rd Maidenhead Berkshire SL6 3RQ",
    "addr:postcode":"sl6 3rq",
    "addr:street":"Bath Rd",
    "iso:country":"GB",
    "sg:address":"Bath Rd",
    "sg:city":"Maidenhead",
    "sg:classifiers":[
        {
            "category":"Autos & Motor Vehicles",
            "subcategory":"Automobile Sales",
            "type":"Retail Goods"
        }
    ],
    "sg:phone":"+44 1628 825152",
    "sg:postcode":"SL6 3RQ",
    "sg:province":"Berkshire",
    "sg:tags":[
        "car"
    ],
    "wof:name":"Whichford Maidenhead",
    "wof:placetype":"venue"
},
  "geometry": {"coordinates":[-0.774963975,51.5165100098],"type":"Point"}
}