{
  "type": "Feature",
  "properties": {
    "addr:full":"4 New Rd Spalding Lincolnshire PE11 1BS",
    "addr:housenumber":"4",
    "addr:postcode":"pe11 1bs",
    "addr:street":"New Rd",
    "iso:country":"GB",
    "sg:address":"4 New Rd",
    "sg:city":"Spalding",
    "sg:classifiers":[
        {
            "category":"Home & Garden",
            "subcategory":"Household Appliances",
            "type":"Retail Goods"
        }
    ],
    "sg:phone":"+44 1775 724402",
    "sg:postcode":"PE11 1BS",
    "sg:province":"Lincolnshire",
    "sg:tags":[
        "electrical"
    ],
    "wof:name":"Dean Turner",
    "wof:placetype":"venue"
},
  "geometry": {"coordinates":[-0.1523720026,52.7881774902],"type":"Point"}
}