{
  "type": "Feature",
  "properties": {
    "addr:full":"197 Rice Lane Liverpool Merseyside L9 1AQ",
    "addr:housenumber":"197",
    "addr:postcode":"l9 1aq",
    "addr:street":"Rice Lane",
    "iso:country":"GB",
    "sg:address":"197 Rice Lane",
    "sg:city":"Liverpool",
    "sg:classifiers":[
        {
            "category":"Food & Beverages",
            "subcategory":"Bakery",
            "type":"Retail Goods"
        }
    ],
    "sg:phone":"+44 151 525 1108",
    "sg:postcode":"L9 1AQ",
    "sg:province":"Merseyside",
    "sg:tags":[
        "baker"
    ],
    "wof:name":"E P Hepple",
    "wof:placetype":"venue"
},
  "geometry": {"coordinates":[-2.961928,53.454884],"type":"Point"}
}