{
  "type": "Feature",
  "properties": {
    "addr:full":"White Lion Court, High Street Beccles Norfolk NR34 8RL",
    "addr:postcode":"nr34 8rl",
    "addr:street":"High Street",
    "iso:country":"GB",
    "sg:address":"White Lion Court, High Street",
    "sg:city":"Beccles",
    "sg:classifiers":[
        {
            "category":"Wholesale",
            "subcategory":"Books, Periodicals, & Newspapers",
            "type":"Manufacturing & Wholesale Goods"
        }
    ],
    "sg:phone":"+44 1502 578416",
    "sg:postcode":"NR34 8RL",
    "sg:province":"Norfolk",
    "sg:tags":[
        "publishing"
    ],
    "wof:name":"Gilbey Collections Ltd.",
    "wof:placetype":"venue"
},
  "geometry": {"coordinates":[1.6220779419,52.3563194275],"type":"Point"}
}