{
  "type": "Feature",
  "properties": {
    "addr:full":"30 Wordsworth Road Wallington Surrey SM6 9RH",
    "addr:housenumber":"30",
    "addr:postcode":"sm6 9rh",
    "addr:street":"Wordsworth Road",
    "iso:country":"GB",
    "sg:address":"30 Wordsworth Road",
    "sg:city":"Wallington",
    "sg:classifiers":[
        {
            "category":"Building & Trades",
            "subcategory":"Construction",
            "type":"Services"
        },
        {
            "category":"Health Services",
            "subcategory":"Podiatrist",
            "type":"Services"
        }
    ],
    "sg:phone":"+44 20 8669 8631",
    "sg:postcode":"SM6 9RH",
    "sg:province":"Surrey",
    "sg:tags":[
        "bricklayer",
        "podiatrists",
        "chiropodist"
    ],
    "wof:name":"Wh Brickwork Contractors Ltd.",
    "wof:placetype":"venue"
},
  "geometry": {"coordinates":[-0.1407590061,51.3563308716],"type":"Point"}
}