{
  "type": "Feature",
  "properties": {
    "addr:full":"35 Brynhyfryd St Merthyr Tydfil Merthyr Tydfil CF47 9YN",
    "addr:housenumber":"35",
    "addr:postcode":"cf47 9yn",
    "addr:street":"Brynhyfryd St",
    "iso:country":"GB",
    "sg:address":"35 Brynhyfryd St",
    "sg:city":"Merthyr Tydfil",
    "sg:classifiers":[
        {
            "category":"Shopping",
            "subcategory":"Computers & Home Electronics",
            "type":"Retail Goods"
        }
    ],
    "sg:phone":"+44 1685 377561",
    "sg:postcode":"CF47 9YN",
    "sg:province":"Merthyr Tydfil",
    "sg:tags":[
        "sound",
        "equipment"
    ],
    "wof:name":"P G Disco Supplies",
    "wof:placetype":"venue"
},
  "geometry": {"coordinates":[-3.365942,51.758381],"type":"Point"}
}