{
  "type": "Feature",
  "properties": {
    "addr:full":"Station Street Stranraer Dumfries and Galloway DG9 7HJ",
    "addr:postcode":"dg9 7hj",
    "addr:street":"Station Street",
    "iso:country":"GB",
    "sg:address":"Station Street",
    "sg:city":"Stranraer",
    "sg:classifiers":[
        {
            "category":"Wholesale",
            "subcategory":"Construction Materials",
            "type":"Manufacturing & Wholesale Goods"
        }
    ],
    "sg:postcode":"DG9 7HJ",
    "sg:province":"Dumfries and Galloway",
    "sg:tags":[
        "merchant",
        "glass"
    ],
    "wof:name":"G C M Glass (Supplies)",
    "wof:placetype":"venue"
},
  "geometry": {"coordinates":[-5.017329216,54.9032211304],"type":"Point"}
}