{
  "type": "Feature",
  "properties": {
    "addr:full":"The Old Board Stores, Spencer Mews, Camden Road Tunbridge Wells Kent TN1 2PT",
    "addr:postcode":"tn1 2pt",
    "addr:street":"Spencer Mews Camden Road",
    "iso:country":"GB",
    "sg:address":"The Old Board Stores, Spencer Mews, Camden Road",
    "sg:city":"Tunbridge Wells",
    "sg:classifiers":[
        {
            "category":"Shopping",
            "subcategory":"Antiques",
            "type":"Retail Goods"
        }
    ],
    "sg:phone":"+44 1892 547515",
    "sg:postcode":"TN1 2PT",
    "sg:province":"Kent",
    "wof:name":"Trevor Hinton Restorations",
    "wof:placetype":"venue"
},
  "geometry": {"coordinates":[0.2635500133,51.1333732605],"type":"Point"}
}