{
  "type": "Feature",
  "properties": {
    "addr:full":"Lynn Road, Bawsey King's Lynn Norfolk PE32 1EU",
    "addr:postcode":"pe32 1eu",
    "addr:street":"Lynn Road;Lynn",
    "iso:country":"GB",
    "sg:address":"Lynn Road, Bawsey",
    "sg:city":"King's Lynn",
    "sg:classifiers":[
        {
            "category":"Farming",
            "subcategory":"Livestock Farm",
            "type":"Manufacturing & Wholesale Goods"
        }
    ],
    "sg:phone":"+44 1553 630279",
    "sg:postcode":"PE32 1EU",
    "sg:province":"Norfolk",
    "sg:tags":[
        "others"
    ],
    "wof:name":"R D Hancock",
    "wof:placetype":"venue"
},
  "geometry": {"coordinates":[0.4654699862,52.7521591187],"type":"Point"}
}