{
  "type": "Feature",
  "properties": {
    "addr:full":"87 Barrow Rd Bristol City of Bristol BS5 0AE",
    "addr:housenumber":"87",
    "addr:postcode":"bs5 0ae",
    "addr:street":"Barrow Rd",
    "iso:country":"GB",
    "sg:address":"87 Barrow Rd",
    "sg:city":"Bristol",
    "sg:classifiers":[
        {
            "category":"Bars & Pubs",
            "type":"Food & Drink"
        }
    ],
    "sg:postcode":"BS5 0AE",
    "sg:province":"City of Bristol",
    "sg:tags":[
        "pubs",
        "inn"
    ],
    "wof:name":"Ushers of Trowbridge Ltd",
    "wof:placetype":"venue"
},
  "geometry": {"coordinates":[-2.569064,51.45507],"type":"Point"}
}