{
  "type": "Feature",
  "properties": {
    "addr:full":"Unit 1 Stirling Road Dunblane Perth and Kinross FK15 9EP",
    "addr:housenumber":"unit 1",
    "addr:postcode":"fk15 9ep",
    "addr:street":"Stirling Road",
    "iso:country":"GB",
    "sg:address":"Unit 1 Stirling Road",
    "sg:city":"Dunblane",
    "sg:classifiers":[
        {
            "category":"Retail",
            "subcategory":"Auto Repair",
            "type":"Services"
        }
    ],
    "sg:phone":"+44 1786 822300",
    "sg:postcode":"FK15 9EP",
    "sg:province":"Perth and Kinross",
    "sg:tags":[
        "modification",
        "garage"
    ],
    "wof:name":"Roy & Stephen McIntyre",
    "wof:placetype":"venue"
},
  "geometry": {"coordinates":[-3.964936018,56.1860847473],"type":"Point"}
}