{
  "type": "Feature",
  "properties": {
    "addr:full":"46 Eastwood Drive Rainham Essex RM13 9HH",
    "addr:housenumber":"46",
    "addr:postcode":"rm13 9hh",
    "addr:street":"Eastwood Drive",
    "iso:country":"GB",
    "sg:address":"46 Eastwood Drive",
    "sg:city":"Rainham",
    "sg:classifiers":[
        {
            "category":"Home & Garden",
            "subcategory":"Household Appliances",
            "type":"Retail Goods"
        }
    ],
    "sg:phone":"+44 1708 520981",
    "sg:postcode":"RM13 9HH",
    "sg:province":"Essex",
    "sg:tags":[
        "electrical"
    ],
    "wof:name":"G D S",
    "wof:placetype":"venue"
},
  "geometry": {"coordinates":[0.2024040073,51.5109939575],"type":"Point"}
}