{
  "type": "Feature",
  "properties": {
    "addr:full":"56 Westgate Shipley West Yorkshire BD18 3QX",
    "addr:housenumber":"56",
    "addr:postcode":"bd18 3qx",
    "addr:street":"Westgate Shipley West",
    "iso:country":"GB",
    "sg:address":"56 Westgate",
    "sg:city":"Shipley",
    "sg:classifiers":[
        {
            "category":"Fast Food",
            "type":"Food & Drink"
        }
    ],
    "sg:phone":"+44 1274 580252",
    "sg:postcode":"BD18 3QX",
    "sg:province":"West Yorkshire",
    "sg:tags":[
        "away",
        "meal",
        "outlet",
        "take"
    ],
    "wof:name":"The New Cedar Tree",
    "wof:placetype":"venue"
},
  "geometry": {"coordinates":[-1.77937,53.83482],"type":"Point"}
}