{
  "type": "Feature",
  "properties": {
    "iso:country":"GB",
    "sg:address":"6 Princes Square",
    "sg:city":"Wolverhampton",
    "sg:classifiers":[
        {
            "category":"Shopping",
            "subcategory":"Shoes",
            "type":"Retail Goods"
        }
    ],
    "sg:phone":"+44 1902 681902",
    "sg:postcode":"WV1 1ED",
    "sg:province":"West Midlands",
    "sg:tags":[
        "shop"
    ],
    "wof:name":"Primadonna (Wolverhampton) Ltd.",
    "wof:placetype":"venue"
},
  "geometry": {"coordinates":[-2.125566,52.586952],"type":"Point"}
}