{
  "type": "Feature",
  "properties": {
    "addr:full":"Jetty Cliff Cromer Norfolk NR27 9HG",
    "addr:postcode":"nr27 9hg",
    "addr:street":"Jetty Cliff Cromer",
    "iso:country":"GB",
    "sg:address":"Jetty Cliff",
    "sg:city":"Cromer",
    "sg:classifiers":[
        {
            "category":"Travel",
            "subcategory":"Hotels & Motels",
            "type":"Entertainment"
        }
    ],
    "sg:phone":"+44 1263 513141",
    "sg:postcode":"NR27 9HG",
    "sg:province":"Norfolk",
    "wof:name":"Leisureplex Ltd",
    "wof:placetype":"venue"
},
  "geometry": {"coordinates":[1.298525,52.932732],"type":"Point"}
}