{
  "type": "Feature",
  "properties": {
    "iso:country":"GB",
    "sg:address":"21 Market St",
    "sg:city":"Ely",
    "sg:classifiers":[
        {
            "category":"Bars & Pubs",
            "type":"Food & Drink"
        }
    ],
    "sg:phone":"+44 1638 720414",
    "sg:postcode":"CB7 5LQ",
    "sg:province":"Cambridgeshire",
    "sg:tags":[
        "pubs",
        "inn"
    ],
    "wof:name":"Greyhound The",
    "wof:placetype":"venue"
},
  "geometry": {"coordinates":[0.383963,52.307316],"type":"Point"}
}