{
  "type": "Feature",
  "properties": {
    "addr:full":"8 High Street Newhaven East Sussex BN9 9PE",
    "addr:housenumber":"8",
    "addr:postcode":"bn9 9pe",
    "addr:street":"High Street",
    "iso:country":"GB",
    "sg:address":"8 High Street",
    "sg:city":"Newhaven",
    "sg:classifiers":[
        {
            "category":"Professional",
            "subcategory":"Accounting & Tax Preparation",
            "type":"Services"
        }
    ],
    "sg:postcode":"BN9 9PE",
    "sg:province":"East Sussex",
    "sg:tags":[
        "accountant"
    ],
    "wof:name":"Christopher Bruce Hayman",
    "wof:placetype":"venue"
},
  "geometry": {"coordinates":[0.049198,50.794624],"type":"Point"}
}