{
  "type": "Feature",
  "properties": {
    "addr:full":"58 High St Newport Pagnell Buckinghamshire MK16 8AQ",
    "addr:housenumber":"58",
    "addr:postcode":"mk16 8aq",
    "addr:street":"High St",
    "iso:country":"GB",
    "sg:address":"58 High St",
    "sg:city":"Newport Pagnell",
    "sg:classifiers":[
        {
            "category":"Retail",
            "subcategory":"Repair Shop",
            "type":"Services"
        }
    ],
    "sg:phone":"+44 1908 610625",
    "sg:postcode":"MK16 8AQ",
    "sg:province":"Buckinghamshire",
    "sg:tags":[
        "radio",
        "television",
        "video"
    ],
    "wof:name":"Communications Centre",
    "wof:placetype":"venue"
},
  "geometry": {"coordinates":[-0.723016,52.086834],"type":"Point"}
}