{
  "type": "Feature",
  "properties": {
    "addr:full":"138 Main Road, Sundridge Sevenoaks Kent TN14 6ET",
    "addr:housenumber":"138",
    "addr:postcode":"tn14 6et",
    "addr:street":"Main Road",
    "iso:country":"GB",
    "sg:address":"138 Main Road, Sundridge",
    "sg:city":"Sevenoaks",
    "sg:classifiers":[
        {
            "category":"Manufacturing",
            "subcategory":"Metals",
            "type":"Manufacturing & Wholesale Goods"
        }
    ],
    "sg:phone":"+44 1959 563849",
    "sg:postcode":"TN14 6ET",
    "sg:province":"Kent",
    "sg:tags":[
        "steel",
        "fabricator",
        "erectors"
    ],
    "wof:name":"F Lane & Sons",
    "wof:placetype":"venue"
},
  "geometry": {"coordinates":[0.1239759997,51.278137207],"type":"Point"}
}