{
  "type": "Feature",
  "properties": {
    "addr:full":"31 Brecon Road, Ystradgynlais Swansea Carmarthenshire SA9 1HE",
    "addr:housenumber":"31",
    "addr:postcode":"sa9 1he",
    "addr:street":"Brecon Road",
    "iso:country":"GB",
    "sg:address":"31 Brecon Road, Ystradgynlais",
    "sg:city":"Swansea",
    "sg:classifiers":[
        {
            "category":"Personal",
            "subcategory":"Barber",
            "type":"Services"
        }
    ],
    "sg:phone":"+44 1639 842073",
    "sg:postcode":"SA9 1HE",
    "sg:province":"Carmarthenshire",
    "sg:tags":[
        "men's",
        "hairdresser"
    ],
    "wof:name":"Just Gents",
    "wof:placetype":"venue"
},
  "geometry": {"coordinates":[-3.757209,51.777657],"type":"Point"}
}