{
  "type": "Feature",
  "properties": {
    "addr:full":"70-72 Longrow Campbeltown Argyll and Bute PA28 6DD",
    "addr:housenumber":"70-72",
    "addr:postcode":"pa28 6dd",
    "addr:street":"Longrow Campbeltown",
    "iso:country":"GB",
    "sg:address":"70-72 Longrow",
    "sg:city":"Campbeltown",
    "sg:classifiers":[
        {
            "category":"Restaurant",
            "type":"Food & Drink"
        }
    ],
    "sg:phone":"+44 1586 553181",
    "sg:postcode":"PA28 6DD",
    "sg:province":"Argyll and Bute",
    "sg:tags":[
        "-",
        "chinese"
    ],
    "wof:name":"Golden Ocean Chinese Restaurant",
    "wof:placetype":"venue"
},
  "geometry": {"coordinates":[-5.6073889732,55.4259376526],"type":"Point"}
}