{
  "type": "Feature",
  "properties": {
    "addr:full":"The Mills, Icklingham Bury St Edmunds Cambridgeshire IP28 6PT",
    "addr:postcode":"ip28 6pt",
    "addr:street":"St",
    "iso:country":"GB",
    "sg:address":"The Mills, Icklingham",
    "sg:city":"Bury St Edmunds",
    "sg:classifiers":[
        {
            "category":"Manufacturing",
            "subcategory":"Food",
            "type":"Manufacturing & Wholesale Goods"
        }
    ],
    "sg:phone":"+44 1638 712387",
    "sg:postcode":"IP28 6PT",
    "sg:province":"Cambridgeshire",
    "sg:tags":[
        "miller",
        "mill"
    ],
    "wof:name":"C Marston & Sons (Icklingham) Ltd.",
    "wof:placetype":"venue"
},
  "geometry": {"coordinates":[0.5958399773,52.3266105652],"type":"Point"}
}