{
  "type": "Feature",
  "properties": {
    "iso:country":"GB",
    "sg:address":"Church Hill",
    "sg:city":"Minehead",
    "sg:classifiers":[
        {
            "category":"Manufacturing",
            "subcategory":"Petroleum Products",
            "type":"Manufacturing & Wholesale Goods"
        }
    ],
    "sg:postcode":"TA24 7PP",
    "sg:province":"Somerset",
    "sg:tags":[
        "double",
        "glazing"
    ],
    "wof:name":"Exmoor Agricultural",
    "wof:placetype":"venue"
},
  "geometry": {"coordinates":[-3.6389319897,51.1335678101],"type":"Point"}
}