{
  "type": "Feature",
  "properties": {
    "iso:country":"GB",
    "sg:address":"25 Hambledon Road, Worle",
    "sg:city":"Weston Super Mare",
    "sg:classifiers":[
        {
            "category":"Banks & Credit Unions",
            "subcategory":"Financial Services",
            "type":"Services"
        }
    ],
    "sg:phone":"+44 1934 623388",
    "sg:postcode":"BS22 7GJ",
    "sg:province":"Somerset",
    "sg:tags":[
        "adviser"
    ],
    "wof:name":"Baker Independent Financial Services",
    "wof:placetype":"venue"
},
  "geometry": {"coordinates":[-2.90472,51.369919],"type":"Point"}
}