{
  "type": "Feature",
  "properties": {
    "iso:country":"GB",
    "sg:address":"41 Canal St",
    "sg:city":"Macclesfield",
    "sg:classifiers":[
        {
            "category":"Retail",
            "subcategory":"Auto Repair",
            "type":"Services"
        }
    ],
    "sg:postcode":"SK10 1JG",
    "sg:province":"Cheshire",
    "sg:tags":[
        "modification",
        "garage"
    ],
    "wof:name":"Canal St Motors",
    "wof:placetype":"venue"
},
  "geometry": {"coordinates":[-2.120008,53.258595],"type":"Point"}
}