{
  "type": "Feature",
  "properties": {
    "iso:country":"GB",
    "sg:address":"1 Pond Road",
    "sg:city":"London",
    "sg:classifiers":[
        {
            "category":"Place Of Worship",
            "type":"Public Place"
        }
    ],
    "sg:phone":"+44 20 8852 1205",
    "sg:postcode":"SE3 9JL",
    "sg:province":"Greater London",
    "wof:name":"St. Michael & All Angels Church Office",
    "wof:placetype":"venue"
},
  "geometry": {"coordinates":[0.01374,51.464958],"type":"Point"}
}