{
  "type": "Feature",
  "properties": {
    "addr:full":"6 Market Place Belper Derbyshire DE56 1FZ",
    "addr:housenumber":"6",
    "addr:postcode":"de56 1fz",
    "addr:street":"Market Place",
    "iso:country":"GB",
    "sg:address":"6 Market Place",
    "sg:city":"Belper",
    "sg:classifiers":[
        {
            "category":"Fast Food",
            "type":"Food & Drink"
        }
    ],
    "sg:phone":"+44 1773 823340",
    "sg:postcode":"DE56 1FZ",
    "sg:province":"Derbyshire",
    "sg:tags":[
        "away",
        "meal",
        "outlet",
        "take"
    ],
    "wof:name":"Oriental Villa",
    "wof:placetype":"venue"
},
  "geometry": {"coordinates":[-1.479029,53.023361],"type":"Point"}
}