{
  "type": "Feature",
  "properties": {
    "iso:country":"GB",
    "sg:address":"Mercer Ho, Thames Side",
    "sg:city":"Windsor",
    "sg:classifiers":[
        {
            "category":"Shopping",
            "subcategory":"Stationery & Office Supplies",
            "type":"Retail Goods"
        }
    ],
    "sg:phone":"+44 1753 850451",
    "sg:postcode":"SL4 1QN",
    "sg:province":"Berkshire",
    "sg:tags":[
        "box",
        "carton"
    ],
    "wof:name":"Smurfit Cartons Ltd",
    "wof:placetype":"venue"
},
  "geometry": {"coordinates":[-0.612228,51.481735],"type":"Point"}
}