{
  "type": "Feature",
  "properties": {
    "addr:full":"Forest Gate, New Invention Willenhall West Midlands WV12 5LF",
    "addr:postcode":"wv12 5lf",
    "addr:street":"Forest Gate",
    "iso:country":"GB",
    "sg:address":"Forest Gate, New Invention",
    "sg:city":"Willenhall",
    "sg:classifiers":[
        {
            "category":"Place Of Worship",
            "type":"Public Place"
        }
    ],
    "sg:phone":"+44 1902 605043",
    "sg:postcode":"WV12 5LF",
    "sg:province":"West Midlands",
    "wof:name":"St Edmund Genning's Church",
    "wof:placetype":"venue"
},
  "geometry": {"coordinates":[-2.036204,52.612404],"type":"Point"}
}