{
  "type": "Feature",
  "properties": {
    "iso:country":"GB",
    "sg:address":"Festival Works, Coombs Rd",
    "sg:city":"Halesowen",
    "sg:classifiers":[
        {
            "category":"Professional",
            "subcategory":"Testing Lab",
            "type":"Services"
        }
    ],
    "sg:phone":"+44 121 559 1570",
    "sg:postcode":"B62 8AA",
    "sg:province":"West Midlands",
    "sg:tags":[
        "mot"
    ],
    "wof:name":"Halesowen Auto Centre",
    "wof:placetype":"venue"
},
  "geometry": {"coordinates":[-2.04918,52.461208],"type":"Point"}
}