{
  "type": "Feature",
  "properties": {
    "iso:country":"GB",
    "sg:address":"Boat Road Cottage, Goldcliffe",
    "sg:city":"Newport",
    "sg:classifiers":[
        {
            "category":"Home & Garden",
            "subcategory":"Building Materials",
            "type":"Retail Goods"
        }
    ],
    "sg:postcode":"NP18 2AU",
    "sg:province":"Monmouthshire",
    "sg:tags":[
        "insulation",
        "installers"
    ],
    "wof:name":"Four Winds Insulation Contractors",
    "wof:placetype":"venue"
},
  "geometry": {"coordinates":[-2.9243741035,51.5423088074],"type":"Point"}
}