{
  "type": "Feature",
  "properties": {
    "addr:full":"The Rookery, Great North Road Hatfield Hertfordshire AL9 5SF",
    "addr:postcode":"al9 5sf",
    "addr:street":"Great North Road",
    "iso:country":"GB",
    "sg:address":"The Rookery, Great North Road",
    "sg:city":"Hatfield",
    "sg:classifiers":[
        {
            "category":"Cafe",
            "type":"Food & Drink"
        }
    ],
    "sg:postcode":"AL9 5SF",
    "sg:province":"Hertfordshire",
    "sg:tags":[
        "tea",
        "room"
    ],
    "wof:name":"The Rookery Cafe",
    "wof:placetype":"venue"
},
  "geometry": {"coordinates":[-0.2172120064,51.7725601196],"type":"Point"}
}