{
  "type": "Feature",
  "properties": {
    "addr:full":"Broadway, Haslingden Rossendale Lancashire BB4 4EY",
    "addr:postcode":"bb4 4ey",
    "addr:street":"Broadway",
    "iso:country":"GB",
    "sg:address":"Broadway, Haslingden",
    "sg:city":"Rossendale",
    "sg:classifiers":[
        {
            "category":"Education",
            "subcategory":"School",
            "type":"Public Place"
        }
    ],
    "sg:phone":"+44 1706 215726",
    "sg:postcode":"BB4 4EY",
    "sg:province":"Lancashire",
    "sg:tags":[
        "local",
        "authority"
    ],
    "wof:name":"Haslingden High School",
    "wof:placetype":"venue"
},
  "geometry": {"coordinates":[-2.327514,53.691429],"type":"Point"}
}