{
  "type": "Feature",
  "properties": {
    "addr:full":"1 Museum Street Montrose Aberdeenshire DD10 8HE",
    "addr:housenumber":"1",
    "addr:postcode":"dd10 8he",
    "addr:street":"Museum Street",
    "iso:country":"GB",
    "sg:address":"1 Museum Street",
    "sg:city":"Montrose",
    "sg:classifiers":[
        {
            "category":"Shopping",
            "subcategory":"Antiques",
            "type":"Retail Goods"
        }
    ],
    "sg:postcode":"DD10 8HE",
    "sg:province":"Aberdeenshire",
    "wof:name":"James Bros Antiques",
    "wof:placetype":"venue"
},
  "geometry": {"coordinates":[-2.4651639462,56.710395813],"type":"Point"}
}