{
  "type": "Feature",
  "properties": {
    "iso:country":"GB",
    "sg:address":"6 London Road",
    "sg:city":"Faversham",
    "sg:classifiers":[
        {
            "category":"Professional",
            "subcategory":"Art Services",
            "type":"Services"
        }
    ],
    "sg:phone":"+44 1795 531174",
    "sg:postcode":"ME13 8RX",
    "sg:province":"Kent",
    "sg:tags":[
        "photographer"
    ],
    "wof:name":"Dylan Woolf Photography",
    "wof:placetype":"venue"
},
  "geometry": {"coordinates":[0.8871009946,51.309047699],"type":"Point"}
}