{
  "type": "Feature",
  "properties": {
    "addr:full":"162 New Cross Road London Greater London SE14 5AA",
    "addr:housenumber":"162",
    "addr:postcode":"se14 5aa",
    "addr:street":"New Cross Road",
    "iso:country":"GB",
    "sg:address":"162 New Cross Road",
    "sg:city":"London",
    "sg:classifiers":[
        {
            "category":"Retail",
            "subcategory":"Auto Repair",
            "type":"Services"
        }
    ],
    "sg:phone":"+44 20 8635 6461",
    "sg:postcode":"SE14 5AA",
    "sg:province":"Greater London",
    "sg:tags":[
        "body",
        "car"
    ],
    "wof:name":"Besson Street Garage",
    "wof:placetype":"venue"
},
  "geometry": {"coordinates":[-0.046789,51.474812],"type":"Point"}
}