{
  "type": "Feature",
  "properties": {
    "iso:country":"GB",
    "sg:address":"Georgefield",
    "sg:city":"Lockerbie",
    "sg:classifiers":[
        {
            "category":"Building & Trades",
            "subcategory":"Equipment Rental",
            "type":"Services"
        }
    ],
    "sg:phone":"+44 1461 800226",
    "sg:postcode":"DG11 3AU",
    "sg:province":"Dumfries and Galloway",
    "sg:tags":[
        "plant",
        "machinery"
    ],
    "wof:name":"Scott Welding Services",
    "wof:placetype":"venue"
},
  "geometry": {"coordinates":[-3.205599,55.055771],"type":"Point"}
}