{
  "type": "Feature",
  "properties": {
    "iso:country":"GB",
    "sg:address":"Meridian Cottage, Barkway Road",
    "sg:city":"Royston",
    "sg:classifiers":[
        {
            "category":"Building & Trades",
            "subcategory":"Construction",
            "type":"Services"
        }
    ],
    "sg:phone":"+44 1763 247883",
    "sg:postcode":"SG8 9NB",
    "sg:province":"Bedfordshire",
    "sg:tags":[
        "bricklaying"
    ],
    "wof:name":"G J Beetles",
    "wof:placetype":"venue"
},
  "geometry": {"coordinates":[-0.0219839998,52.048210144],"type":"Point"}
}