{
  "type": "Feature",
  "properties": {
    "iso:country":"GB",
    "sg:address":"49 Courtenay Street",
    "sg:city":"Newton Abbot",
    "sg:classifiers":[
        {
            "category":"Real Estate",
            "subcategory":"Real Estate Agent",
            "type":"Services"
        }
    ],
    "sg:phone":"+44 1626 351143",
    "sg:postcode":"TQ12 2DT",
    "sg:province":"Devon",
    "wof:name":"Constables",
    "wof:placetype":"venue"
},
  "geometry": {"coordinates":[-3.609659,50.531048],"type":"Point"}
}