{
  "type": "Feature",
  "properties": {
    "iso:country":"GB",
    "sg:address":"54 Sandy Lane",
    "sg:city":"Eastleigh",
    "sg:classifiers":[
        {
            "category":"Shopping",
            "subcategory":"News",
            "type":"Retail Goods"
        }
    ],
    "sg:phone":"+44 23 8069 2853",
    "sg:postcode":"SO50 8GB",
    "sg:province":"Hampshire",
    "sg:tags":[
        "newsagent"
    ],
    "wof:name":"Sandy News",
    "wof:placetype":"venue"
},
  "geometry": {"coordinates":[-1.304228,50.967918],"type":"Point"}
}