{
  "type": "Feature",
  "properties": {
    "addr:full":"Rear Of 3 High Street, Nelson Treharris Caerphilly CF46 6EU",
    "addr:housenumber":"rear of 3",
    "addr:postcode":"cf46 6eu",
    "addr:street":"High Street",
    "iso:country":"GB",
    "sg:address":"Rear Of 3 High Street, Nelson",
    "sg:city":"Treharris",
    "sg:classifiers":[
        {
            "category":"Food & Beverages",
            "subcategory":"Bakery",
            "type":"Retail Goods"
        }
    ],
    "sg:phone":"+44 1443 451006",
    "sg:postcode":"CF46 6EU",
    "sg:province":"Caerphilly",
    "sg:tags":[
        "baker"
    ],
    "wof:name":"Davies's Bakery",
    "wof:placetype":"venue"
},
  "geometry": {"coordinates":[-3.284114,51.652679],"type":"Point"}
}