{
  "type": "Feature",
  "properties": {
    "addr:full":"Barrow Cliff Cott Warrington Cheshire WA2 8ST",
    "addr:postcode":"wa2 8st",
    "addr:street":"Barrow Cliff",
    "iso:country":"GB",
    "sg:address":"Barrow Cliff Cott",
    "sg:city":"Warrington",
    "sg:classifiers":[
        {
            "category":"Building & Trades",
            "subcategory":"Construction",
            "type":"Services"
        }
    ],
    "sg:postcode":"WA2 8ST",
    "sg:province":"Cheshire",
    "sg:tags":[
        "builder"
    ],
    "wof:name":"Cliffe,A & M,Builders",
    "wof:placetype":"venue"
},
  "geometry": {"coordinates":[-2.587149,53.448399],"type":"Point"}
}