{
  "type": "Feature",
  "properties": {
    "addr:full":"Unit 8 B G W Business Park, Aston Fields Bromsgrove Worcestershire B60 3DR",
    "addr:housenumber":"unit 8 b",
    "addr:postcode":"b60 3dr",
    "addr:street":"G W Business Park Aston Fields",
    "iso:country":"GB",
    "sg:address":"Unit 8 B G W Business Park, Aston Fields",
    "sg:city":"Bromsgrove",
    "sg:classifiers":[
        {
            "category":"Professional",
            "subcategory":"Computer Services",
            "type":"Services"
        }
    ],
    "sg:phone":"+44 1527 574611",
    "sg:postcode":"B60 3DR",
    "sg:province":"Worcestershire",
    "sg:tags":[
        "system",
        "software"
    ],
    "wof:name":"Midland Equipment Brokers",
    "wof:placetype":"venue"
},
  "geometry": {"coordinates":[-2.05734,52.319611],"type":"Point"}
}