{
  "type": "Feature",
  "properties": {
    "iso:country":"GB",
    "sg:address":"57 Leigh Road",
    "sg:city":"Eastleigh",
    "sg:classifiers":[
        {
            "category":"Health Services",
            "subcategory":"Dentist",
            "type":"Services"
        }
    ],
    "sg:postcode":"SO50 9DF",
    "sg:province":"Hampshire",
    "wof:name":"P B Sommereux & Associates",
    "wof:placetype":"venue"
},
  "geometry": {"coordinates":[-1.355089,50.969494],"type":"Point"}
}