{
  "type": "Feature",
  "properties": {
    "addr:full":"19 Barrow Street St Helens Merseyside WA10 1RX",
    "addr:housenumber":"19",
    "addr:postcode":"wa10 1rx",
    "addr:street":"Barrow Street",
    "iso:country":"GB",
    "sg:address":"19 Barrow Street",
    "sg:city":"St Helens",
    "sg:classifiers":[
        {
            "category":"Real Estate",
            "subcategory":"Real Estate Agent",
            "type":"Services"
        }
    ],
    "sg:phone":"+44 1744 736800",
    "sg:postcode":"WA10 1RX",
    "sg:province":"Merseyside",
    "wof:name":"David Davies Estate Agent Ltd.",
    "wof:placetype":"venue"
},
  "geometry": {"coordinates":[-2.736282,53.453911],"type":"Point"}
}