{
  "type": "Feature",
  "properties": {
    "addr:full":"32 Broad St Ely Cambridgeshire CB7 4AH",
    "addr:housenumber":"32",
    "addr:postcode":"cb7 4ah",
    "addr:street":"Broad St",
    "iso:country":"GB",
    "sg:address":"32 Broad St",
    "sg:city":"Ely",
    "sg:classifiers":[
        {
            "category":"Professional",
            "subcategory":"Business Services",
            "type":"Services"
        }
    ],
    "sg:phone":"+44 1353 669009",
    "sg:postcode":"CB7 4AH",
    "sg:province":"Cambridgeshire",
    "sg:tags":[
        "import",
        "export",
        "agent"
    ],
    "wof:name":"Alston-Barry (UK) Ltd",
    "wof:placetype":"venue"
},
  "geometry": {"coordinates":[0.267375,52.396835],"type":"Point"}
}