{
  "type": "Feature",
  "properties": {
    "addr:full":"Yew Tree House, Ombersley Droitwich Worcestershire WR9 0JX",
    "addr:postcode":"wr9 0jx",
    "addr:street":"Yew;Droitwich",
    "iso:country":"GB",
    "sg:address":"Yew Tree House, Ombersley",
    "sg:city":"Droitwich",
    "sg:classifiers":[
        {
            "category":"Professional",
            "subcategory":"Business Services",
            "type":"Services"
        }
    ],
    "sg:phone":"+44 1905 620848",
    "sg:postcode":"WR9 0JX",
    "sg:province":"Worcestershire",
    "sg:tags":[
        "hospitality",
        "corporate"
    ],
    "wof:name":"Moyles Masterkey Ltd.",
    "wof:placetype":"venue"
},
  "geometry": {"coordinates":[-2.1763689518,52.2631988525],"type":"Point"}
}