{
  "type": "Feature",
  "properties": {
    "addr:full":"6 High Street, Caister On Sea Great Yarmouth Norfolk NR30 5EP",
    "addr:housenumber":"6",
    "addr:postcode":"nr30 5ep",
    "addr:street":"High Street;Great Yarmouth",
    "iso:country":"GB",
    "sg:address":"6 High Street, Caister On Sea",
    "sg:city":"Great Yarmouth",
    "sg:classifiers":[
        {
            "category":"Shopping",
            "subcategory":"Florist",
            "type":"Retail Goods"
        }
    ],
    "sg:postcode":"NR30 5EP",
    "sg:province":"Norfolk",
    "wof:name":"Arcade Florists",
    "wof:placetype":"venue"
},
  "geometry": {"coordinates":[1.72921,52.645977],"type":"Point"}
}