{
  "type": "Feature",
  "properties": {
    "addr:full":"1 Crown Court Yard Evesham Gloucestershire WR11 4RY",
    "addr:housenumber":"1",
    "addr:postcode":"wr11 4ry",
    "addr:street":"Crown Court Yard",
    "iso:country":"GB",
    "sg:address":"1 Crown Court Yard",
    "sg:city":"Evesham",
    "sg:classifiers":[
        {
            "category":"Professional",
            "subcategory":"Lawyer & Legal Services",
            "type":"Services"
        }
    ],
    "sg:phone":"+44 1386 442558",
    "sg:postcode":"WR11 4RY",
    "sg:province":"Gloucestershire",
    "sg:tags":[
        "solicitor"
    ],
    "wof:name":"Saunders Roberts",
    "wof:placetype":"venue"
},
  "geometry": {"coordinates":[-1.943969,52.106392],"type":"Point"}
}