{
  "type": "Feature",
  "properties": {
    "addr:full":"8 Grovehill Drive Falmouth Cornwall TR11 3HS",
    "addr:housenumber":"8",
    "addr:postcode":"tr11 3hs",
    "addr:street":"Grovehill Drive",
    "iso:country":"GB",
    "sg:address":"8 Grovehill Drive",
    "sg:city":"Falmouth",
    "sg:classifiers":[
        {
            "category":"Organizations",
            "subcategory":"Community Association",
            "type":"Services"
        }
    ],
    "sg:postcode":"TR11 3HS",
    "sg:province":"Cornwall",
    "sg:tags":[
        "relation",
        "public"
    ],
    "wof:name":"Westcountry P R Services",
    "wof:placetype":"venue"
},
  "geometry": {"coordinates":[-5.066334,50.149139],"type":"Point"}
}