{
  "type": "Feature",
  "properties": {
    "iso:country":"GB",
    "sg:address":"6 Waterfront East",
    "sg:city":"Brierley Hill",
    "sg:classifiers":[
        {
            "category":"Restaurant",
            "type":"Food & Drink"
        }
    ],
    "sg:phone":"+44 1384 820001",
    "sg:postcode":"DY5 1XE",
    "sg:province":"West Midlands",
    "sg:tags":[
        "greek"
    ],
    "wof:name":"Spiros",
    "wof:placetype":"venue"
},
  "geometry": {"coordinates":[-2.109274,52.488426],"type":"Point"}
}