{
  "type": "Feature",
  "properties": {
    "addr:full":"2 Mandalay Clo Delabole Cornwall PL33 9DN",
    "addr:housenumber":"2",
    "addr:postcode":"pl33 9dn",
    "addr:street":"Mandalay Clo Delabole",
    "iso:country":"GB",
    "sg:address":"2 Mandalay Clo",
    "sg:city":"Delabole",
    "sg:classifiers":[
        {
            "category":"Farming",
            "subcategory":"Livestock Farm",
            "type":"Manufacturing & Wholesale Goods"
        }
    ],
    "sg:phone":"+44 1840 213146",
    "sg:postcode":"PL33 9DN",
    "sg:province":"Cornwall",
    "sg:tags":[
        "stud"
    ],
    "wof:name":"Tylands Arabian Stud",
    "wof:placetype":"venue"
},
  "geometry": {"coordinates":[-4.731349,50.623653],"type":"Point"}
}