{
  "type": "Feature",
  "properties": {
    "addr:full":"Court Road Barry The Vale of Glamorgan CF63 4ER",
    "addr:postcode":"cf63 4er",
    "addr:street":"Court Road;Vale",
    "iso:country":"GB",
    "sg:address":"Court Road",
    "sg:city":"Barry",
    "sg:classifiers":[
        {
            "category":"Place Of Worship",
            "type":"Public Place"
        }
    ],
    "sg:phone":"+44 1446 734508",
    "sg:postcode":"CF63 4ER",
    "sg:province":"The Vale of Glamorgan",
    "wof:name":"Crossway Methodist Church",
    "wof:placetype":"venue"
},
  "geometry": {"coordinates":[-3.2632489204,51.4096755981],"type":"Point"}
}