{
  "type": "Feature",
  "properties": {
    "iso:country":"GB",
    "sg:address":"Unit 7 Glengallen Road, Crannog Lane",
    "sg:city":"Oban",
    "sg:classifiers":[
        {
            "category":"Taxi",
            "type":"Transportation"
        },
        {
            "category":"Military Area",
            "subcategory":"Air Force Base",
            "type":"Public Place"
        }
    ],
    "sg:phone":"+44 1631 566676",
    "sg:postcode":"PA34 4HB",
    "sg:province":"Argyll and Bute",
    "sg:tags":[
        "mini",
        "hire",
        "private",
        "cab"
    ],
    "wof:name":"Alba's Taxis",
    "wof:placetype":"venue"
},
  "geometry": {"coordinates":[-5.4870882034,56.3964767456],"type":"Point"}
}