{
  "type": "Feature",
  "properties": {
    "addr:full":"297 Hertford Road London Greater London N9 7ET",
    "addr:housenumber":"297",
    "addr:postcode":"n9 7et",
    "addr:street":"Hertford Road",
    "iso:country":"GB",
    "sg:address":"297 Hertford Road",
    "sg:city":"London",
    "sg:classifiers":[
        {
            "category":"Military Area",
            "subcategory":"Air Force Base",
            "type":"Public Place"
        }
    ],
    "sg:postcode":"N9 7ET",
    "sg:province":"Greater London",
    "sg:tags":[
        "taxi",
        "hire",
        "private"
    ],
    "wof:name":"Kwik Car Service Ltd.",
    "wof:placetype":"venue"
},
  "geometry": {"coordinates":[-0.0527289994,51.6349182129],"type":"Point"}
}