{
  "type": "Feature",
  "properties": {
    "addr:full":"Fairacres, Blackpool Road, Newton Preston Lancashire PR4 3RE",
    "addr:postcode":"pr4 3re",
    "addr:street":"Blackpool Road",
    "iso:country":"GB",
    "sg:address":"Fairacres, Blackpool Road, Newton",
    "sg:city":"Preston",
    "sg:classifiers":[
        {
            "category":"Shopping",
            "subcategory":"Party Supplies",
            "type":"Retail Goods"
        }
    ],
    "sg:phone":"+44 1772 682137",
    "sg:postcode":"PR4 3RE",
    "sg:province":"Lancashire",
    "sg:tags":[
        "marquees",
        "floor",
        "tent"
    ],
    "wof:name":"J & S Marquee Hire",
    "wof:placetype":"venue"
},
  "geometry": {"coordinates":[-2.840045929,53.7740516663],"type":"Point"}
}