{
  "type": "Feature",
  "properties": {
    "addr:full":"Unit 1a, 103-149 Cornwall Rd London Greater London N15 5AX",
    "addr:housenumber":"unit 1a",
    "addr:postcode":"103-149;n15 5ax",
    "addr:street":"Cornwall Rd",
    "iso:country":"GB",
    "sg:address":"Unit 1a, 103-149 Cornwall Rd",
    "sg:city":"London",
    "sg:classifiers":[
        {
            "category":"Home & Garden",
            "subcategory":"Carpets & Floor Coverings",
            "type":"Retail Goods"
        }
    ],
    "sg:phone":"+44 20 8800 5339",
    "sg:postcode":"N15 5AX",
    "sg:province":"Greater London",
    "sg:tags":[
        "trimming",
        "trimmer"
    ],
    "wof:name":"Anchor Trimmings Ltd",
    "wof:placetype":"venue"
},
  "geometry": {"coordinates":[-0.087443,51.583443],"type":"Point"}
}