{
  "type": "Feature",
  "properties": {
    "iso:country":"GB",
    "sg:address":"North Arscott Farm",
    "sg:city":"Holsworthy",
    "sg:classifiers":[
        {
            "category":"Farming",
            "subcategory":"Livestock Farm",
            "type":"Manufacturing & Wholesale Goods"
        }
    ],
    "sg:phone":"+44 1409 241391",
    "sg:postcode":"EX22 7NJ",
    "sg:province":"Cornwall",
    "sg:tags":[
        "others"
    ],
    "wof:name":"Ivor Prouse",
    "wof:placetype":"venue"
},
  "geometry": {"coordinates":[-4.3882880211,50.90599823],"type":"Point"}
}