{
  "type": "Feature",
  "properties": {
    "addr:full":"Blandford St Ashton Under Lyne Greater Manchester OL6 7DW",
    "addr:postcode":"ol6 7dw",
    "addr:street":"Blandford St;Under Lyne",
    "iso:country":"GB",
    "sg:address":"Blandford St",
    "sg:city":"Ashton Under Lyne",
    "sg:classifiers":[
        {
            "category":"Building & Trades",
            "subcategory":"Construction",
            "type":"Services"
        }
    ],
    "sg:phone":"+44 161 308 3494",
    "sg:postcode":"OL6 7DW",
    "sg:province":"Greater Manchester",
    "sg:tags":[
        "builder"
    ],
    "wof:name":"E P H Fabrications & Constructions",
    "wof:placetype":"venue"
},
  "geometry": {"coordinates":[-2.099754,53.48938],"type":"Point"}
}