{
  "type": "Feature",
  "properties": {
    "iso:country":"GB",
    "sg:address":"Woodbridge Road",
    "sg:city":"Guildford",
    "sg:classifiers":[
        {
            "category":"Autos & Motor Vehicles",
            "subcategory":"Fuel & Gas Station",
            "type":"Retail Goods"
        }
    ],
    "sg:postcode":"GU1 1DX",
    "sg:province":"Surrey",
    "sg:tags":[
        "hr",
        "petrol"
    ],
    "wof:name":"Woodbridge Service Station",
    "wof:placetype":"venue"
},
  "geometry": {"coordinates":[-0.577029,51.245178],"type":"Point"}
}