{
  "type": "Feature",
  "properties": {
    "iso:country":"GB",
    "sg:address":"9 Lugar Street",
    "sg:city":"Cumnock",
    "sg:classifiers":[
        {
            "category":"Home & Garden",
            "subcategory":"Hardware",
            "type":"Retail Goods"
        },
        {
            "category":"Shopping",
            "subcategory":"Discount & Variety Stores",
            "type":"Retail Goods"
        }
    ],
    "sg:phone":"+44 1290 422298",
    "sg:postcode":"KA18 1AD",
    "sg:province":"East Ayrshire",
    "sg:tags":[
        "centre"
    ],
    "wof:name":"Crowdstopper",
    "wof:placetype":"venue"
},
  "geometry": {"coordinates":[-4.266566,55.454449],"type":"Point"}
}