{
  "type": "Feature",
  "properties": {
    "addr:full":"154 Kinghorn Road Burntisland Fife KY3 9JU",
    "addr:housenumber":"154",
    "addr:postcode":"ky3 9ju",
    "addr:street":"Kinghorn Road",
    "iso:country":"GB",
    "sg:address":"154 Kinghorn Road",
    "sg:city":"Burntisland",
    "sg:classifiers":[
        {
            "category":"Building & Trades",
            "subcategory":"Construction",
            "type":"Services"
        }
    ],
    "sg:postcode":"KY3 9JU",
    "sg:province":"Fife",
    "sg:tags":[
        "builder"
    ],
    "wof:name":"Sharp & Condi",
    "wof:placetype":"venue"
},
  "geometry": {"coordinates":[-3.2171070576,56.0642547607],"type":"Point"}
}