{
  "type": "Feature",
  "properties": {
    "addr:full":"14 Rabin Hill Sturminster Newton Dorset DT10 1EU",
    "addr:housenumber":"14",
    "addr:postcode":"dt10 1eu",
    "addr:street":"Rabin Hill",
    "iso:country":"GB",
    "sg:address":"14 Rabin Hill",
    "sg:city":"Sturminster Newton",
    "sg:classifiers":[
        {
            "category":"Coffee & Tea",
            "type":"Food & Drink"
        }
    ],
    "sg:phone":"+44 1258 473610",
    "sg:postcode":"DT10 1EU",
    "sg:province":"Dorset",
    "wof:name":"Ashby's Tea & Coffee",
    "wof:placetype":"venue"
},
  "geometry": {"coordinates":[-2.302592,50.93161],"type":"Point"}
}