{
  "type": "Feature",
  "properties": {
    "addr:full":"94 High Street, Stetchworth Newmarket Cambridgeshire CB8 9TJ",
    "addr:housenumber":"94",
    "addr:postcode":"cb8 9tj",
    "addr:street":"High Street",
    "iso:country":"GB",
    "sg:address":"94 High Street, Stetchworth",
    "sg:city":"Newmarket",
    "sg:classifiers":[
        {
            "category":"Bars & Pubs",
            "type":"Food & Drink"
        },
        {
            "category":"Community Center",
            "subcategory":"Social",
            "type":"Public Place"
        }
    ],
    "sg:phone":"+44 1638 507628",
    "sg:postcode":"CB8 9TJ",
    "sg:province":"Cambridgeshire",
    "sg:tags":[
        "pubs",
        "house",
        "inn",
        "activity"
    ],
    "wof:name":"The Marquis of Granby",
    "wof:placetype":"venue"
},
  "geometry": {"coordinates":[0.399412,52.199444],"type":"Point"}
}