{
  "type": "Feature",
  "properties": {
    "iso:country":"GB",
    "sg:address":"40 Keptie Street",
    "sg:city":"Arbroath",
    "sg:classifiers":[
        {
            "category":"Shopping",
            "subcategory":"Florist",
            "type":"Retail Goods"
        }
    ],
    "sg:phone":"+44 1241 874144",
    "sg:postcode":"DD11 3AF",
    "sg:province":"Angus",
    "wof:name":"Flower Design",
    "wof:placetype":"venue"
},
  "geometry": {"coordinates":[-2.590362072,56.559337616],"type":"Point"}
}