{
  "type": "Feature",
  "properties": {
    "addr:full":"67 Gatwick Road Crawley Surrey RH10 9RD",
    "addr:housenumber":"67",
    "addr:postcode":"rh10 9rd",
    "addr:street":"Gatwick Road",
    "iso:country":"GB",
    "sg:address":"67 Gatwick Road",
    "sg:city":"Crawley",
    "sg:classifiers":[
        {
            "category":"Professional",
            "subcategory":"Engineering",
            "type":"Services"
        }
    ],
    "sg:phone":"+44 1293 514906",
    "sg:postcode":"RH10 9RD",
    "sg:province":"Surrey",
    "wof:name":"Datoc Engineering Ltd.",
    "wof:placetype":"venue"
},
  "geometry": {"coordinates":[-0.164689,51.138519],"type":"Point"}
}