{
  "type": "Feature",
  "properties": {
    "addr:full":"Auchnashag, Newmachar Aberdeen Aberdeen City AB21 0RR",
    "addr:postcode":"ab21 0rr",
    "iso:country":"GB",
    "sg:address":"Auchnashag, Newmachar",
    "sg:city":"Aberdeen",
    "sg:classifiers":[
        {
            "category":"Building & Trades",
            "subcategory":"Equipment Rental",
            "type":"Services"
        }
    ],
    "sg:phone":"+44 1651 862952",
    "sg:postcode":"AB21 0RR",
    "sg:province":"Aberdeen City",
    "sg:tags":[
        "diver"
    ],
    "wof:name":"Prowin Ltd",
    "wof:placetype":"venue"
},
  "geometry": {"coordinates":[-2.1900589466,57.2652511597],"type":"Point"}
}