{
  "type": "Feature",
  "properties": {
    "addr:full":"45 Church Road Hove East Sussex BN3 2BE",
    "addr:housenumber":"45",
    "addr:postcode":"bn3 2be",
    "addr:street":"Church Road",
    "iso:country":"GB",
    "sg:address":"45 Church Road",
    "sg:city":"Hove",
    "sg:classifiers":[
        {
            "category":"Personal",
            "type":"Services"
        }
    ],
    "sg:phone":"+44 1273 205007",
    "sg:postcode":"BN3 2BE",
    "sg:province":"East Sussex",
    "sg:tags":[
        "wedding"
    ],
    "wof:name":"Miju Haute Couture",
    "wof:placetype":"venue"
},
  "geometry": {"coordinates":[-0.164816007,50.8271255493],"type":"Point"}
}