{
  "type": "Feature",
  "properties": {
    "iso:country":"GB",
    "sg:address":"469 Badsley Moor Lane",
    "sg:city":"Rotherham",
    "sg:classifiers":[
        {
            "category":"Fast Food",
            "type":"Food & Drink"
        }
    ],
    "sg:phone":"+44 1709 378546",
    "sg:postcode":"S65 2QS",
    "sg:province":"South Yorkshire",
    "sg:tags":[
        "away",
        "meal",
        "outlet",
        "take"
    ],
    "wof:name":"Moon House",
    "wof:placetype":"venue"
},
  "geometry": {"coordinates":[-1.327308,53.430702],"type":"Point"}
}