{
  "type": "Feature",
  "properties": {
    "addr:full":"The Gladstone Community Centre, 162 Anson Road London Greater London NW2 6BH",
    "addr:housenumber":"162",
    "addr:postcode":"nw2 6bh",
    "addr:street":"Anson Road",
    "iso:country":"GB",
    "sg:address":"The Gladstone Community Centre, 162 Anson Road",
    "sg:city":"London",
    "sg:classifiers":[
        {
            "category":"Farming",
            "subcategory":"Nursery",
            "type":"Manufacturing & Wholesale Goods"
        }
    ],
    "sg:phone":"+44 20 8452 6272",
    "sg:postcode":"NW2 6BH",
    "sg:province":"Greater London",
    "sg:tags":[
        "creche"
    ],
    "wof:name":"Ellen Louise Nursery",
    "wof:placetype":"venue"
},
  "geometry": {"coordinates":[-0.220729,51.560909],"type":"Point"}
}