{
  "type": "Feature",
  "properties": {
    "addr:full":"Unit 8d Gadwey House, Leigh Street High Wycombe Buckinghamshire HP11 2QU",
    "addr:housenumber":"unit;gadwey",
    "addr:postcode":"hp11 2qu",
    "addr:street":"Leigh Street",
    "iso:country":"GB",
    "sg:address":"Unit 8d Gadwey House, Leigh Street",
    "sg:city":"High Wycombe",
    "sg:classifiers":[
        {
            "category":"Professional",
            "subcategory":"Engineering",
            "type":"Services"
        }
    ],
    "sg:postcode":"HP11 2QU",
    "sg:province":"Buckinghamshire",
    "wof:name":"Heath End Engineering",
    "wof:placetype":"venue"
},
  "geometry": {"coordinates":[-0.7643790245,51.6316108704],"type":"Point"}
}