{
  "type": "Feature",
  "properties": {
    "iso:country":"GB",
    "sg:address":"47 Bulwer Rd",
    "sg:city":"Leicester",
    "sg:classifiers":[
        {
            "category":"Arts & Performance",
            "subcategory":"Music",
            "type":"Entertainment"
        }
    ],
    "sg:phone":"+44 116 270 1983",
    "sg:postcode":"LE2 3BW",
    "sg:province":"Leicestershire",
    "sg:tags":[
        "musician",
        "composer"
    ],
    "wof:name":"Roger Pugh",
    "wof:placetype":"venue"
},
  "geometry": {"coordinates":[-1.1186920404,52.6157073975],"type":"Point"}
}