{
  "type": "Feature",
  "properties": {
    "addr:full":"Post Office, Warren Road Gravesend Kent DA13 9NN",
    "addr:postcode":"da13 9nn",
    "addr:street":"Warren Road",
    "iso:country":"GB",
    "sg:address":"Post Office, Warren Road",
    "sg:city":"Gravesend",
    "sg:classifiers":[
        {
            "category":"Shopping",
            "subcategory":"Department Store",
            "type":"Retail Goods"
        }
    ],
    "sg:postcode":"DA13 9NN",
    "sg:province":"Kent",
    "wof:name":"John A Saunders",
    "wof:placetype":"venue"
},
  "geometry": {"coordinates":[0.3208599985,51.4161682129],"type":"Point"}
}