{
  "type": "Feature",
  "properties": {
    "addr:full":"Station Yard Sedbergh Cumbria LA10 5HP",
    "addr:postcode":"la10 5hp",
    "iso:country":"GB",
    "sg:address":"Station Yard",
    "sg:city":"Sedbergh",
    "sg:classifiers":[
        {
            "category":"Utilities",
            "subcategory":"Fuel Oil & Lpg",
            "type":"Services"
        }
    ],
    "sg:postcode":"LA10 5HP",
    "sg:province":"Cumbria",
    "wof:name":"W Dawson & Son",
    "wof:placetype":"venue"
},
  "geometry": {"coordinates":[-2.527837,54.321945],"type":"Point"}
}