{
  "type": "Feature",
  "properties": {
    "addr:full":"Bellyeoman Surgery, Bellyeoman Rd Dunfermline Fife KY12 0AE",
    "addr:postcode":"ky12 0ae",
    "addr:street":"Bellyeoman Rd",
    "iso:country":"GB",
    "sg:address":"Bellyeoman Surgery, Bellyeoman Rd",
    "sg:city":"Dunfermline",
    "sg:classifiers":[
        {
            "category":"Health Services",
            "subcategory":"Doctor",
            "type":"Services"
        }
    ],
    "sg:phone":"+44 1383 721266",
    "sg:postcode":"KY12 0AE",
    "sg:province":"Fife",
    "sg:tags":[
        "practitioners"
    ],
    "wof:name":"Lester, R",
    "wof:placetype":"venue"
},
  "geometry": {"coordinates":[-3.4613740444,56.0748443604],"type":"Point"}
}