{
  "type": "Feature",
  "properties": {
    "addr:full":"18 Salisbury Road Romford Essex RM2 5TP",
    "addr:housenumber":"18",
    "addr:postcode":"rm2 5tp",
    "addr:street":"Salisbury Road",
    "iso:country":"GB",
    "sg:address":"18 Salisbury Road",
    "sg:city":"Romford",
    "sg:classifiers":[
        {
            "category":"Building & Trades",
            "subcategory":"Construction",
            "type":"Services"
        }
    ],
    "sg:phone":"+44 1708 454096",
    "sg:postcode":"RM2 5TP",
    "sg:province":"Essex",
    "sg:tags":[
        "tiling",
        "contractor"
    ],
    "wof:name":"Salisbury Tiling",
    "wof:placetype":"venue"
},
  "geometry": {"coordinates":[0.204835,51.577141],"type":"Point"}
}