{
  "type": "Feature",
  "properties": {
    "iso:country":"GB",
    "sg:address":"45 Doncaster Rd, Armthorpe",
    "sg:city":"Doncaster",
    "sg:classifiers":[
        {
            "category":"Personal",
            "subcategory":"Beauty Salon",
            "type":"Services"
        }
    ],
    "sg:postcode":"DN3 2BU",
    "sg:province":"South Yorkshire",
    "sg:tags":[
        "unisex",
        "hairdresser"
    ],
    "wof:name":"Gravill,Joanne,",
    "wof:placetype":"venue"
},
  "geometry": {"coordinates":[-1.0688780546,53.5379180908],"type":"Point"}
}