{
  "type": "Feature",
  "properties": {
    "iso:country":"GB",
    "sg:address":"Ifton Industrial Estate, St Martins",
    "sg:city":"Oswestry",
    "sg:classifiers":[
        {
            "category":"Wholesale",
            "subcategory":"Scrap",
            "type":"Manufacturing & Wholesale Goods"
        }
    ],
    "sg:phone":"+44 1691 778363",
    "sg:postcode":"SY11 3DA",
    "sg:province":"Shropshire",
    "sg:tags":[
        "waste",
        "metal"
    ],
    "wof:name":"G D Wilson & Son",
    "wof:placetype":"venue"
},
  "geometry": {"coordinates":[-3.048089,52.863602],"type":"Point"}
}