{
  "type": "Feature",
  "properties": {
    "addr:full":"60 Grenville Avenue, Locking Weston-super-mare Somerset BS24 8AR",
    "addr:housenumber":"60",
    "addr:postcode":"bs24 8ar",
    "addr:street":"Grenville Avenue",
    "iso:country":"GB",
    "sg:address":"60 Grenville Avenue, Locking",
    "sg:city":"Weston-super-mare",
    "sg:classifiers":[
        {
            "category":"Personal",
            "subcategory":"Beauty Salon",
            "type":"Services"
        }
    ],
    "sg:phone":"+44 1934 820001",
    "sg:postcode":"BS24 8AR",
    "sg:province":"Somerset",
    "sg:tags":[
        "unisex",
        "hairdresser"
    ],
    "wof:name":"Partners",
    "wof:placetype":"venue"
},
  "geometry": {"coordinates":[-2.915435,51.333328],"type":"Point"}
}