{
  "type": "Feature",
  "properties": {
    "iso:country":"GB",
    "sg:address":"Flat 281, Cromwell Tower, Barbican",
    "sg:city":"Moorgate",
    "sg:classifiers":[
        {
            "category":"Professional",
            "subcategory":"Computer Services",
            "type":"Services"
        }
    ],
    "sg:phone":"+44 20 7628 9727",
    "sg:postcode":"EC2Y 8DD",
    "sg:province":"Greater London",
    "sg:tags":[
        "system",
        "software"
    ],
    "wof:name":"Stowe Computing (UK) Ltd",
    "wof:placetype":"venue"
},
  "geometry": {"coordinates":[-0.09277,51.52042],"type":"Point"}
}