{
  "type": "Feature",
  "properties": {
    "iso:country":"GB",
    "sg:address":"The Harrison Centre, Boulting Avenue",
    "sg:city":"Warrington",
    "sg:classifiers":[
        {
            "category":"Government",
            "subcategory":"Office",
            "type":"Public Place"
        }
    ],
    "sg:phone":"+44 1925 240904",
    "sg:postcode":"WA5 5HG",
    "sg:province":"Cheshire",
    "sg:tags":[
        "local"
    ],
    "wof:name":"Warrington Borough Employment Services",
    "wof:placetype":"venue"
},
  "geometry": {"coordinates":[-2.6486,53.405991],"type":"Point"}
}