{
  "type": "Feature",
  "properties": {
    "addr:full":"1000 Pollokshaws Road Glasgow Glasgow City G41 2HG",
    "addr:housenumber":"1000",
    "addr:postcode":"g41 2hg",
    "addr:street":"Pollokshaws Road",
    "iso:country":"GB",
    "sg:address":"1000 Pollokshaws Road",
    "sg:city":"Glasgow",
    "sg:classifiers":[
        {
            "category":"Shopping",
            "subcategory":"Clothing, Apparel, & Fashions",
            "type":"Retail Goods"
        }
    ],
    "sg:phone":"+44 141 632 4530",
    "sg:postcode":"G41 2HG",
    "sg:province":"Glasgow City",
    "sg:tags":[
        "accessory"
    ],
    "wof:name":"Accessories Studio",
    "wof:placetype":"venue"
},
  "geometry": {"coordinates":[-4.278125,55.832291],"type":"Point"}
}