{
  "type": "Feature",
  "properties": {
    "iso:country":"GB",
    "sg:address":"522 Christchurch Road, Boscombe",
    "sg:city":"Bournemouth",
    "sg:classifiers":[
        {
            "category":"Shopping",
            "subcategory":"Used Merchandise",
            "type":"Retail Goods"
        }
    ],
    "sg:phone":"+44 1202 393696",
    "sg:postcode":"BH1 4BE",
    "sg:province":"Dorset",
    "sg:tags":[
        "furniture"
    ],
    "wof:name":"The Furniture Shop",
    "wof:placetype":"venue"
},
  "geometry": {"coordinates":[-1.842465,50.72591],"type":"Point"}
}