{
  "type": "Feature",
  "properties": {
    "addr:full":"Pittern Hill House, Kineton Warwick Warwickshire CV35 0JF",
    "addr:postcode":"cv35 0jf",
    "addr:street":"Pittern;Kineton",
    "iso:country":"GB",
    "sg:address":"Pittern Hill House, Kineton",
    "sg:city":"Warwick",
    "sg:classifiers":[
        {
            "category":"Building & Trades",
            "subcategory":"Construction",
            "type":"Services"
        }
    ],
    "sg:phone":"+44 1926 641356",
    "sg:postcode":"CV35 0JF",
    "sg:province":"Warwickshire",
    "sg:tags":[
        "builder"
    ],
    "wof:name":"Roger Latham Ltd.",
    "wof:placetype":"venue"
},
  "geometry": {"coordinates":[-1.5106090307,52.1565742493],"type":"Point"}
}