{
  "type": "Feature",
  "properties": {
    "iso:country":"GB",
    "sg:address":"24 Broad Street",
    "sg:city":"Lyme Regis",
    "sg:classifiers":[
        {
            "category":"Social Services",
            "subcategory":"Retirement Home",
            "type":"Services"
        }
    ],
    "sg:postcode":"DT7 3QE",
    "sg:province":"Devon",
    "sg:tags":[
        "residential",
        "care"
    ],
    "wof:name":"Holmcroft",
    "wof:placetype":"venue"
},
  "geometry": {"coordinates":[-2.935519,50.724842],"type":"Point"}
}