{
  "type": "Feature",
  "properties": {
    "addr:full":"137 Marlowes Hemel Hempstead Hertfordshire HP1 1BB",
    "addr:housenumber":"137",
    "addr:postcode":"hp1 1bb",
    "addr:street":"Marlowes Hemel Hempstead",
    "iso:country":"GB",
    "sg:address":"137 Marlowes",
    "sg:city":"Hemel Hempstead",
    "sg:classifiers":[
        {
            "category":"Banks & Credit Unions",
            "subcategory":"Bank",
            "type":"Services"
        }
    ],
    "sg:phone":"+44 1442 236388",
    "sg:postcode":"HP1 1BB",
    "sg:province":"Hertfordshire",
    "wof:name":"Yorkshire Bank Plc",
    "wof:placetype":"venue"
},
  "geometry": {"coordinates":[-0.472125,51.75206],"type":"Point"}
}