{
  "type": "Feature",
  "properties": {
    "iso:country":"GB",
    "sg:address":"226 Grovehill Road",
    "sg:city":"Beverley",
    "sg:classifiers":[
        {
            "category":"Shopping",
            "type":"Retail Goods"
        }
    ],
    "sg:phone":"+44 1482 860969",
    "sg:postcode":"HU17 0ES",
    "sg:province":"East Riding of Yorkshire",
    "sg:tags":[
        "part",
        "accessory"
    ],
    "wof:name":"Motorcount",
    "wof:placetype":"venue"
},
  "geometry": {"coordinates":[-0.41279,53.843719],"type":"Point"}
}