{
  "type": "Feature",
  "properties": {
    "addr:full":"Unit 1a, Huddersfield Rd, Birstall Batley West Yorkshire WF17 9AY",
    "addr:housenumber":"unit 1a",
    "addr:postcode":"wf17 9ay",
    "addr:street":"Huddersfield Rd",
    "iso:country":"GB",
    "sg:address":"Unit 1a, Huddersfield Rd, Birstall",
    "sg:city":"Batley",
    "sg:classifiers":[
        {
            "category":"Autos & Motor Vehicles",
            "subcategory":"Automobile Sales",
            "type":"Retail Goods"
        }
    ],
    "sg:phone":"+44 1924 475382",
    "sg:postcode":"WF17 9AY",
    "sg:province":"West Yorkshire",
    "sg:tags":[
        "commercial"
    ],
    "wof:name":"Steve Graves Motors",
    "wof:placetype":"venue"
},
  "geometry": {"coordinates":[-1.659419,53.730583],"type":"Point"}
}