{
  "type": "Feature",
  "properties": {
    "iso:country":"GB",
    "sg:address":"1 Stone Lane",
    "sg:city":"Gosport",
    "sg:classifiers":[
        {
            "category":"Autos & Motor Vehicles",
            "subcategory":"Boat Sales",
            "type":"Retail Goods"
        }
    ],
    "sg:phone":"+44 23 9252 4488",
    "sg:postcode":"PO12 1SS",
    "sg:province":"Hampshire",
    "sg:tags":[
        "surveyor",
        "yacht"
    ],
    "wof:name":"Yacht Services International Ltd.",
    "wof:placetype":"venue"
},
  "geometry": {"coordinates":[-1.137985,50.79171],"type":"Point"}
}