{
  "type": "Feature",
  "properties": {
    "iso:country":"GB",
    "sg:address":"114 Whitehorse Rd",
    "sg:city":"Croydon",
    "sg:classifiers":[
        {
            "category":"Manufacturing",
            "subcategory":"Petroleum Products",
            "type":"Manufacturing & Wholesale Goods"
        }
    ],
    "sg:phone":"+44 20 8683 3880",
    "sg:postcode":"CR0 2JF",
    "sg:province":"Surrey",
    "sg:tags":[
        "double",
        "glazing"
    ],
    "wof:name":"Wades Windows & Conservatories Ltd",
    "wof:placetype":"venue"
},
  "geometry": {"coordinates":[-0.096581,51.386433],"type":"Point"}
}