{
  "type": "Feature",
  "properties": {
    "addr:full":"24 East Port Dunfermline Fife KY12 7JB",
    "addr:housenumber":"24",
    "addr:postcode":"ky12 7jb",
    "addr:street":"East Port Dunfermline",
    "iso:country":"GB",
    "sg:address":"24 East Port",
    "sg:city":"Dunfermline",
    "sg:classifiers":[
        {
            "category":"Shopping",
            "subcategory":"Pharmacy",
            "type":"Retail Goods"
        }
    ],
    "sg:phone":"+44 1383 723571",
    "sg:postcode":"KY12 7JB",
    "sg:province":"Fife",
    "sg:tags":[
        "pharmacist",
        "chemist"
    ],
    "wof:name":"John B B Dick",
    "wof:placetype":"venue"
},
  "geometry": {"coordinates":[-3.4584441185,56.0718460083],"type":"Point"}
}