{
  "type": "Feature",
  "properties": {
    "iso:country":"GB",
    "sg:address":"4 Blacklands Dr",
    "sg:city":"Hastings",
    "sg:classifiers":[
        {
            "category":"Building & Trades",
            "subcategory":"Construction",
            "type":"Services"
        }
    ],
    "sg:phone":"+44 1424 435773",
    "sg:postcode":"TN34 2DH",
    "sg:province":"East Sussex",
    "sg:tags":[
        "dry",
        "lining",
        "plasterers",
        "screeders"
    ],
    "wof:name":"All Aspects Of Plastering",
    "wof:placetype":"venue"
},
  "geometry": {"coordinates":[0.580953,50.868271],"type":"Point"}
}