{
  "type": "Feature",
  "properties": {
    "addr:full":"47 Nevill Rd Uckfield East Sussex TN22 1NZ",
    "addr:housenumber":"47",
    "addr:postcode":"tn22 1nz",
    "addr:street":"Nevill Rd",
    "iso:country":"GB",
    "sg:address":"47 Nevill Rd",
    "sg:city":"Uckfield",
    "sg:classifiers":[
        {
            "category":"Professional",
            "subcategory":"Engineering",
            "type":"Services"
        }
    ],
    "sg:phone":"+44 1825 763433",
    "sg:postcode":"TN22 1NZ",
    "sg:province":"East Sussex",
    "sg:tags":[
        "contractor",
        "electrical",
        "engineer"
    ],
    "wof:name":"T.W Acus",
    "wof:placetype":"venue"
},
  "geometry": {"coordinates":[0.1043990031,50.9814224243],"type":"Point"}
}