{
  "type": "Feature",
  "properties": {
    "addr:full":"Unit 8, Bolholt Industrial Park, Walshaw Road Bury Lancashire BL8 1PL",
    "addr:housenumber":"unit 8",
    "addr:postcode":"bl8 1pl",
    "addr:street":"Bolholt Industrial Park Walshaw Road",
    "iso:country":"GB",
    "sg:address":"Unit 8, Bolholt Industrial Park, Walshaw Road",
    "sg:city":"Bury",
    "sg:classifiers":[
        {
            "category":"Shopping",
            "subcategory":"Clothing, Apparel, & Fashions",
            "type":"Retail Goods"
        }
    ],
    "sg:phone":"+44 161 705 1466",
    "sg:postcode":"BL8 1PL",
    "sg:province":"Lancashire",
    "sg:tags":[
        "sportswear"
    ],
    "wof:name":"Merlin Sports & Leisurewear",
    "wof:placetype":"venue"
},
  "geometry": {"coordinates":[-2.32444,53.600754],"type":"Point"}
}