{
  "type": "Feature",
  "properties": {
    "iso:country":"GB",
    "sg:address":"Lester House, 255 Water Road, Alperton",
    "sg:city":"Wembley",
    "sg:classifiers":[
        {
            "category":"Professional",
            "subcategory":"Business Services",
            "type":"Services"
        }
    ],
    "sg:phone":"+44 20 8991 0311",
    "sg:postcode":"HA0 1JW",
    "sg:province":"Greater London",
    "sg:tags":[
        "import",
        "export",
        "agent"
    ],
    "wof:name":"Lester Group Plc",
    "wof:placetype":"venue"
},
  "geometry": {"coordinates":[-0.285997,51.537739],"type":"Point"}
}