{
  "type": "Feature",
  "properties": {
    "iso:country":"GB",
    "sg:address":"Moorland Road, Drighlington",
    "sg:city":"Bradford",
    "sg:classifiers":[
        {
            "category":"Education",
            "subcategory":"School",
            "type":"Public Place"
        }
    ],
    "sg:phone":"+44 113 285 2031",
    "sg:postcode":"BD11 1JY",
    "sg:province":"West Yorkshire",
    "sg:tags":[
        "local",
        "authority"
    ],
    "wof:name":"Drighlington Infants School",
    "wof:placetype":"venue"
},
  "geometry": {"coordinates":[-1.66225,53.756592],"type":"Point"}
}