{
  "type": "Feature",
  "properties": {
    "addr:full":"20 Shelly Road, Ashton-on-ribble Preston Lancashire PR2 2DB",
    "addr:housenumber":"20",
    "addr:postcode":"pr2 2db",
    "addr:street":"Shelly Road",
    "iso:country":"GB",
    "sg:address":"20 Shelly Road, Ashton-on-ribble",
    "sg:city":"Preston",
    "sg:classifiers":[
        {
            "category":"Government",
            "subcategory":"Department Of Motor Vehicles",
            "type":"Public Place"
        }
    ],
    "sg:phone":"+44 1772 556800",
    "sg:postcode":"PR2 2DB",
    "sg:province":"Lancashire",
    "sg:tags":[
        "engine",
        "component"
    ],
    "wof:name":"Motor Radiator Specialists",
    "wof:placetype":"venue"
},
  "geometry": {"coordinates":[-2.7252590656,53.7714805603],"type":"Point"}
}