{
  "type": "Feature",
  "properties": {
    "addr:full":"Farnborough Road Farnborough Hampshire GU14 7JU",
    "addr:postcode":"gu14 7ju",
    "addr:street":"Farnborough Road",
    "iso:country":"GB",
    "sg:address":"Farnborough Road",
    "sg:city":"Farnborough",
    "sg:classifiers":[
        {
            "category":"Government",
            "subcategory":"Office",
            "type":"Public Place"
        }
    ],
    "sg:phone":"+44 1252 398398",
    "sg:postcode":"GU14 7JU",
    "sg:province":"Hampshire",
    "sg:tags":[
        "local"
    ],
    "wof:name":"Rushmoor Borough Council",
    "wof:placetype":"venue"
},
  "geometry": {"coordinates":[-0.7532340288,51.2965698242],"type":"Point"}
}