{
  "type": "Feature",
  "properties": {
    "addr:full":"Mill House, High Street, Brasted Westerham Kent TN16 1JA",
    "addr:postcode":"tn16 1ja",
    "addr:street":"High Street",
    "iso:country":"GB",
    "sg:address":"Mill House, High Street, Brasted",
    "sg:city":"Westerham",
    "sg:classifiers":[
        {
            "category":"Retail",
            "subcategory":"Auto Repair",
            "type":"Services"
        }
    ],
    "sg:phone":"+44 1959 562677",
    "sg:postcode":"TN16 1JA",
    "sg:province":"Kent",
    "sg:tags":[
        "bodybuilder",
        "repairer"
    ],
    "wof:name":"Fisk & Dailly",
    "wof:placetype":"venue"
},
  "geometry": {"coordinates":[0.0712649971,51.267074585],"type":"Point"}
}