{
  "type": "Feature",
  "properties": {
    "addr:full":"7 Maes Glas Cardiff Cardiff CF14 1NW",
    "addr:housenumber":"7",
    "addr:postcode":"cf14 1nw",
    "addr:street":"Maes Glas",
    "iso:country":"GB",
    "sg:address":"7 Maes Glas",
    "sg:city":"Cardiff",
    "sg:classifiers":[
        {
            "category":"Autos & Motor Vehicles",
            "subcategory":"Boat Sales",
            "type":"Retail Goods"
        }
    ],
    "sg:phone":"+44 29 2061 1192",
    "sg:postcode":"CF14 1NW",
    "sg:province":"Cardiff",
    "sg:tags":[
        "surveyor",
        "yacht"
    ],
    "wof:name":"M.J Phillips",
    "wof:placetype":"venue"
},
  "geometry": {"coordinates":[-3.221036,51.507912],"type":"Point"}
}