{
  "type": "Feature",
  "properties": {
    "iso:country":"GB",
    "sg:address":"Chandos Gro",
    "sg:city":"Salford",
    "sg:classifiers":[
        {
            "category":"Organizations",
            "subcategory":"Membership Organization",
            "type":"Services"
        }
    ],
    "sg:phone":"+44 161 736 9161",
    "sg:postcode":"M5 2LJ",
    "sg:province":"Greater Manchester",
    "sg:tags":[
        "club"
    ],
    "wof:name":"Chandos Sports & Social Club",
    "wof:placetype":"venue"
},
  "geometry": {"coordinates":[-2.2843,53.489731],"type":"Point"}
}