{
  "type": "Feature",
  "properties": {
    "addr:full":"Tenax Road, Trafford Park Manchester Cheshire M17 1JT",
    "addr:postcode":"m17 1jt",
    "addr:street":"Tenax Road",
    "iso:country":"GB",
    "sg:address":"Tenax Road, Trafford Park",
    "sg:city":"Manchester",
    "sg:classifiers":[
        {
            "category":"Wholesale",
            "subcategory":"Scrap",
            "type":"Manufacturing & Wholesale Goods"
        }
    ],
    "sg:phone":"+44 161 872 0466",
    "sg:postcode":"M17 1JT",
    "sg:province":"Cheshire",
    "sg:tags":[
        "waste",
        "metal"
    ],
    "wof:name":"S Norton",
    "wof:placetype":"venue"
},
  "geometry": {"coordinates":[-2.3248369694,53.4723167419],"type":"Point"}
}