{
  "type": "Feature",
  "properties": {
    "iso:country":"GB",
    "sg:address":"Daleside Road",
    "sg:city":"Nottingham",
    "sg:classifiers":[
        {
            "category":"Manufacturing",
            "subcategory":"Motor Vehicles & Parts",
            "type":"Manufacturing & Wholesale Goods"
        }
    ],
    "sg:phone":"+44 115 958 3900",
    "sg:postcode":"NG2 4EF",
    "sg:province":"Nottinghamshire",
    "sg:tags":[
        "bearing"
    ],
    "wof:name":"Olympic-Chevin",
    "wof:placetype":"venue"
},
  "geometry": {"coordinates":[-1.127574,52.94627],"type":"Point"}
}