{
  "type": "Feature",
  "properties": {
    "addr:full":"146 Seabank Rd Wallasey Merseyside L45 1HG",
    "addr:housenumber":"146",
    "addr:postcode":"l45 1hg",
    "addr:street":"Seabank Rd",
    "iso:country":"GB",
    "sg:address":"146 Seabank Rd",
    "sg:city":"Wallasey",
    "sg:classifiers":[
        {
            "category":"Autos & Motor Vehicles",
            "subcategory":"Automobile Sales",
            "type":"Retail Goods"
        }
    ],
    "sg:phone":"+44 151 639 0706",
    "sg:postcode":"L45 1HG",
    "sg:province":"Merseyside",
    "sg:tags":[
        "car"
    ],
    "wof:name":"New Brighton Car Sales",
    "wof:placetype":"venue"
},
  "geometry": {"coordinates":[-3.0394039154,53.4315032959],"type":"Point"}
}