{
  "type": "Feature",
  "properties": {
    "addr:full":"35 Lloyd Street Oswestry Shropshire SY11 1NL",
    "addr:housenumber":"35",
    "addr:postcode":"sy11 1nl",
    "addr:street":"Lloyd Street",
    "iso:country":"GB",
    "sg:address":"35 Lloyd Street",
    "sg:city":"Oswestry",
    "sg:classifiers":[
        {
            "category":"Organizations",
            "subcategory":"Non-profit Organization",
            "type":"Services"
        }
    ],
    "sg:postcode":"SY11 1NL",
    "sg:province":"Shropshire",
    "sg:tags":[
        "organisation",
        "voluntary",
        "charity"
    ],
    "wof:name":"The Salvation Army",
    "wof:placetype":"venue"
},
  "geometry": {"coordinates":[-3.0542891026,52.8638038635],"type":"Point"}
}