{
  "type": "Feature",
  "properties": {
    "addr:full":"377-379 Bitterne Village, Bitterne Road Southampton Hampshire SO18 5RR",
    "addr:housenumber":"377-379",
    "addr:postcode":"so18 5rr",
    "addr:street":"Bitterne Village Bitterne Road",
    "iso:country":"GB",
    "sg:address":"377-379 Bitterne Village, Bitterne Road",
    "sg:city":"Southampton",
    "sg:classifiers":[
        {
            "category":"Real Estate",
            "subcategory":"Real Estate Agent",
            "type":"Services"
        }
    ],
    "sg:phone":"+44 23 8044 5800",
    "sg:postcode":"SO18 5RR",
    "sg:province":"Hampshire",
    "wof:name":"Bradford & Bingley Morris Dibben",
    "wof:placetype":"venue"
},
  "geometry": {"coordinates":[-1.3604300022,50.9146194458],"type":"Point"}
}