{
  "type": "Feature",
  "properties": {
    "iso:country":"GB",
    "sg:address":"Swan House, Knowle Grn",
    "sg:city":"Staines",
    "sg:classifiers":[
        {
            "category":"Social Services",
            "type":"Services"
        }
    ],
    "sg:phone":"+44 1784 459341",
    "sg:postcode":"TW18 1XB",
    "sg:province":"Berkshire",
    "wof:name":"Godalming  &  District Citizens Advice B",
    "wof:placetype":"venue"
},
  "geometry": {"coordinates":[-0.498494,51.430294],"type":"Point"}
}