{
  "type": "Feature",
  "properties": {
    "iso:country":"GB",
    "sg:address":"31 Poulton St",
    "sg:city":"Preston",
    "sg:classifiers":[
        {
            "category":"Professional",
            "subcategory":"Lawyer & Legal Services",
            "type":"Services"
        }
    ],
    "sg:phone":"+44 1772 671666",
    "sg:postcode":"PR4 2AA",
    "sg:province":"Lancashire",
    "sg:tags":[
        "solicitor"
    ],
    "wof:name":"Dickson Haslam",
    "wof:placetype":"venue"
},
  "geometry": {"coordinates":[-2.87227,53.782314],"type":"Point"}
}