{
  "type": "Feature",
  "properties": {
    "addr:full":"84 Miller St Glasgow Glasgow City G1 1DT",
    "addr:housenumber":"84",
    "addr:postcode":"g1 1dt",
    "addr:street":"Miller St",
    "iso:country":"GB",
    "sg:address":"84 Miller St",
    "sg:city":"Glasgow",
    "sg:classifiers":[
        {
            "category":"Professional",
            "subcategory":"Management & Consulting",
            "type":"Services"
        }
    ],
    "sg:phone":"+44 141 204 5466",
    "sg:postcode":"G1 1DT",
    "sg:province":"Glasgow City",
    "sg:tags":[
        "consultant",
        "promotion",
        "sale"
    ],
    "wof:name":"Free Enterprise Corporation",
    "wof:placetype":"venue"
},
  "geometry": {"coordinates":[-4.250617981,55.8593444824],"type":"Point"}
}