{
  "type": "Feature",
  "properties": {
    "addr:full":"514 College Road, Erdington Birmingham West Midlands B44 0HL",
    "addr:housenumber":"514",
    "addr:postcode":"b44 0hl",
    "addr:street":"College Road",
    "iso:country":"GB",
    "sg:address":"514 College Road, Erdington",
    "sg:city":"Birmingham",
    "sg:classifiers":[
        {
            "category":"Utilities",
            "subcategory":"Mobile Phone",
            "type":"Services"
        }
    ],
    "sg:phone":"+44 121 382 7675",
    "sg:postcode":"B44 0HL",
    "sg:province":"West Midlands",
    "sg:tags":[
        "battery",
        "supplier"
    ],
    "wof:name":"Gill Batteries",
    "wof:placetype":"venue"
},
  "geometry": {"coordinates":[-1.872795,52.537861],"type":"Point"}
}