{
  "type": "Feature",
  "properties": {
    "iso:country":"GB",
    "sg:address":"65 Drake Avenue, Minster On Sea",
    "sg:city":"Sheerness",
    "sg:classifiers":[
        {
            "category":"Banks & Credit Unions",
            "subcategory":"Financial Services",
            "type":"Services"
        }
    ],
    "sg:phone":"+44 1795 871345",
    "sg:postcode":"ME12 3RZ",
    "sg:province":"Kent",
    "sg:tags":[
        "adviser",
        "independent"
    ],
    "wof:name":"Barham Financial Services",
    "wof:placetype":"venue"
},
  "geometry": {"coordinates":[0.8148409724,51.4160423279],"type":"Point"}
}