{
  "type": "Feature",
  "properties": {
    "addr:full":"Shaldon Road Newton Abbot Devon TQ12 4AU",
    "addr:postcode":"tq12 4au",
    "addr:street":"Shaldon Road",
    "iso:country":"GB",
    "sg:address":"Shaldon Road",
    "sg:city":"Newton Abbot",
    "sg:classifiers":[
        {
            "category":"Autos & Motor Vehicles",
            "subcategory":"Automobile Sales",
            "type":"Retail Goods"
        }
    ],
    "sg:phone":"+44 1626 332833",
    "sg:postcode":"TQ12 4AU",
    "sg:province":"Devon",
    "sg:tags":[
        "car"
    ],
    "wof:name":"Milber Motors",
    "wof:placetype":"venue"
},
  "geometry": {"coordinates":[-3.5877790451,50.5247421265],"type":"Point"}
}