{
  "type": "Feature",
  "properties": {
    "addr:full":"265 Stowey Rd Bristol City of Bristol BS19 4QX",
    "addr:housenumber":"265",
    "addr:postcode":"bs19 4qx",
    "addr:street":"Stowey Rd",
    "iso:country":"GB",
    "sg:address":"265 Stowey Rd",
    "sg:city":"Bristol",
    "sg:classifiers":[
        {
            "category":"Professional",
            "subcategory":"Management & Consulting",
            "type":"Services"
        }
    ],
    "sg:phone":"+44 1934 877097",
    "sg:postcode":"BS19 4QX",
    "sg:province":"City of Bristol",
    "sg:tags":[
        "consultant",
        "business"
    ],
    "wof:name":"Kember Associates",
    "wof:placetype":"venue"
},
  "geometry": {"coordinates":[-2.823114,51.391087],"type":"Point"}
}