{
  "type": "Feature",
  "properties": {
    "iso:country":"GB",
    "sg:address":"Northumberland House, Drake Avenue",
    "sg:city":"Staines",
    "sg:classifiers":[
        {
            "category":"Professional",
            "subcategory":"Employment Agencies",
            "type":"Services"
        }
    ],
    "sg:phone":"+44 1784 440144",
    "sg:postcode":"TW18 2AP",
    "sg:province":"Berkshire",
    "sg:tags":[
        "consultant"
    ],
    "wof:name":"Anthony Marigold",
    "wof:placetype":"venue"
},
  "geometry": {"coordinates":[-0.505894,51.431622],"type":"Point"}
}