{
  "type": "Feature",
  "properties": {
    "addr:full":"16 Dovedale Drive Burnley Lancashire BB12 8XD",
    "addr:housenumber":"16",
    "addr:postcode":"bb12 8xd",
    "addr:street":"Dovedale Drive",
    "iso:country":"GB",
    "sg:address":"16 Dovedale Drive",
    "sg:city":"Burnley",
    "sg:classifiers":[
        {
            "category":"Building & Trades",
            "subcategory":"Plumbing",
            "type":"Services"
        }
    ],
    "sg:phone":"+44 1282 412689",
    "sg:postcode":"BB12 8XD",
    "sg:province":"Lancashire",
    "sg:tags":[
        "plumber",
        "heating"
    ],
    "wof:name":"G Stubbs",
    "wof:placetype":"venue"
},
  "geometry": {"coordinates":[-2.2736060619,53.8002128601],"type":"Point"}
}