{
  "type": "Feature",
  "properties": {
    "iso:country":"GB",
    "sg:address":"Broadwalk, Darley Dale",
    "sg:city":"Matlock",
    "sg:classifiers":[
        {
            "category":"Food & Beverages",
            "subcategory":"Meat & Fish",
            "type":"Retail Goods"
        }
    ],
    "sg:phone":"+44 1629 733639",
    "sg:postcode":"DE4 2HX",
    "sg:province":"Derbyshire",
    "sg:tags":[
        "butcher"
    ],
    "wof:name":"Hollands Butchers Ltd.",
    "wof:placetype":"venue"
},
  "geometry": {"coordinates":[-1.601634,53.164104],"type":"Point"}
}