{
  "type": "Feature",
  "properties": {
    "iso:country":"GB",
    "sg:address":"383 High Road, Harrow Weald",
    "sg:city":"Harrow",
    "sg:classifiers":[
        {
            "category":"Shopping",
            "subcategory":"Computers & Home Electronics",
            "type":"Retail Goods"
        },
        {
            "category":"Communications",
            "type":"Services"
        }
    ],
    "sg:phone":"+44 20 8427 3180",
    "sg:postcode":"HA3 6EL",
    "sg:province":"Greater London",
    "sg:tags":[
        "tv",
        "radio",
        "television",
        "video",
        "sale"
    ],
    "wof:name":"Peter J Sorrell & Son",
    "wof:placetype":"venue"
},
  "geometry": {"coordinates":[-0.3402239978,51.6047325134],"type":"Point"}
}