{
  "type": "Feature",
  "properties": {
    "addr:full":"Glasgow Airport, Abbotsinch Paisley Renfrewshire PA3 2SG",
    "addr:postcode":"pa3 2sg",
    "iso:country":"GB",
    "sg:address":"Glasgow Airport, Abbotsinch",
    "sg:city":"Paisley",
    "sg:classifiers":[
        {
            "category":"Airline",
            "type":"Transportation"
        }
    ],
    "sg:phone":"+44 141 889 0660",
    "sg:postcode":"PA3 2SG",
    "sg:province":"Renfrewshire",
    "wof:name":"British Midland Airways Ltd.",
    "wof:placetype":"venue"
},
  "geometry": {"coordinates":[-4.4253501892,55.8653411865],"type":"Point"}
}