{
  "type": "Feature",
  "properties": {
    "addr:full":"5-7 Bridgegate Retford Nottinghamshire DN22 6AF",
    "addr:housenumber":"5-7",
    "addr:postcode":"dn22 6af",
    "addr:street":"Bridgegate",
    "iso:country":"GB",
    "sg:address":"5-7 Bridgegate",
    "sg:city":"Retford",
    "sg:classifiers":[
        {
            "category":"Education",
            "subcategory":"Special Training",
            "type":"Public Place"
        }
    ],
    "sg:phone":"+44 1777 702877",
    "sg:postcode":"DN22 6AF",
    "sg:province":"Nottinghamshire",
    "sg:tags":[
        "product",
        "centre"
    ],
    "wof:name":"Spring Skills",
    "wof:placetype":"venue"
},
  "geometry": {"coordinates":[-0.943475,53.323456],"type":"Point"}
}