{
  "type": "Feature",
  "properties": {
    "iso:country":"GB",
    "sg:address":"37 Beech Avenue",
    "sg:city":"Bourne",
    "sg:classifiers":[
        {
            "category":"Freight",
            "type":"Transportation"
        }
    ],
    "sg:postcode":"PE10 9RR",
    "sg:province":"Lincolnshire",
    "sg:tags":[
        "haulage",
        "road"
    ],
    "wof:name":"Ken Shepherd & Son Haulage",
    "wof:placetype":"venue"
},
  "geometry": {"coordinates":[-0.392228,52.771175],"type":"Point"}
}