{
  "type": "Feature",
  "properties": {
    "iso:country":"GB",
    "sg:address":"High Street, Avebury",
    "sg:city":"Marlborough",
    "sg:classifiers":[
        {
            "category":"Shopping",
            "subcategory":"Antiques",
            "type":"Retail Goods"
        }
    ],
    "sg:phone":"+44 1672 539436",
    "sg:postcode":"SN8 1RF",
    "sg:province":"Berkshire",
    "wof:name":"Avebury Antiques",
    "wof:placetype":"venue"
},
  "geometry": {"coordinates":[-1.729889,51.421333],"type":"Point"}
}