{
  "type": "Feature",
  "properties": {
    "addr:full":"Union Farm, Thornhill Stirling Stirling FK8 3QL",
    "addr:postcode":"fk8 3ql",
    "iso:country":"GB",
    "sg:address":"Union Farm, Thornhill",
    "sg:city":"Stirling",
    "sg:classifiers":[
        {
            "category":"Building & Trades",
            "subcategory":"Equipment Rental",
            "type":"Services"
        }
    ],
    "sg:postcode":"FK8 3QL",
    "sg:province":"Stirling",
    "sg:tags":[
        "plant",
        "machinery"
    ],
    "wof:name":"Stewart McDonald (Plant) Ltd.",
    "wof:placetype":"venue"
},
  "geometry": {"coordinates":[-4.1453437805,56.1740531921],"type":"Point"}
}