{
  "type": "Feature",
  "properties": {
    "addr:full":"80 Station Road, Ainsdale Southport Lancashire PR8 3HW",
    "addr:housenumber":"80",
    "addr:postcode":"pr8 3hw",
    "addr:street":"Station Road",
    "iso:country":"GB",
    "sg:address":"80 Station Road, Ainsdale",
    "sg:city":"Southport",
    "sg:classifiers":[
        {
            "category":"Farming",
            "subcategory":"Fish & Marine Products",
            "type":"Manufacturing & Wholesale Goods"
        }
    ],
    "sg:postcode":"PR8 3HW",
    "sg:province":"Lancashire",
    "sg:tags":[
        "fishmonger"
    ],
    "wof:name":"Seafoods",
    "wof:placetype":"venue"
},
  "geometry": {"coordinates":[-3.039598,53.602238],"type":"Point"}
}