{
  "type": "Feature",
  "properties": {
    "addr:full":"14 South Lodge Avenue Mitcham Greater London CR4 1LU",
    "addr:housenumber":"14",
    "addr:postcode":"cr4 1lu",
    "addr:street":"South Lodge Avenue",
    "iso:country":"GB",
    "sg:address":"14 South Lodge Avenue",
    "sg:city":"Mitcham",
    "sg:classifiers":[
        {
            "category":"Shopping",
            "subcategory":"Pharmacy",
            "type":"Retail Goods"
        }
    ],
    "sg:phone":"+44 20 8764 6107",
    "sg:postcode":"CR4 1LU",
    "sg:province":"Greater London",
    "sg:tags":[
        "pharmacist",
        "chemist"
    ],
    "wof:name":"Aksam Ltd.",
    "wof:placetype":"venue"
},
  "geometry": {"coordinates":[-0.132757,51.399849],"type":"Point"}
}