{
  "type": "Feature",
  "properties": {
    "addr:full":"15 Silver St Wells Somerset BA5 1UN",
    "addr:housenumber":"15",
    "addr:postcode":"ba5 1un",
    "addr:street":"Silver St",
    "iso:country":"GB",
    "sg:address":"15 Silver St",
    "sg:city":"Wells",
    "sg:classifiers":[
        {
            "category":"Retail",
            "subcategory":"Auto Repair",
            "type":"Services"
        }
    ],
    "sg:phone":"+44 1749 673996",
    "sg:postcode":"BA5 1UN",
    "sg:province":"Somerset",
    "sg:tags":[
        "modification",
        "garage"
    ],
    "wof:name":"Wells Auto Services",
    "wof:placetype":"venue"
},
  "geometry": {"coordinates":[-2.6447188854,51.2069664001],"type":"Point"}
}