{
  "type": "Feature",
  "properties": {
    "iso:country":"GB",
    "sg:address":"Copy Farm, Helions Bumpstead",
    "sg:city":"Haverhill",
    "sg:classifiers":[
        {
            "category":"Farming",
            "subcategory":"Farm",
            "type":"Manufacturing & Wholesale Goods"
        }
    ],
    "sg:postcode":"CB9 7AB",
    "sg:province":"Essex",
    "sg:tags":[
        "mixed",
        "crop"
    ],
    "wof:name":"J J & T H Haylock Ltd.",
    "wof:placetype":"venue"
},
  "geometry": {"coordinates":[0.439355,52.072327],"type":"Point"}
}