{
  "type": "Feature",
  "properties": {
    "addr:full":"20 High Street, Stoke Goldington Newport Pagnell Buckinghamshire MK16 8NR",
    "addr:housenumber":"20",
    "addr:postcode":"mk16 8nr",
    "addr:street":"High Street",
    "iso:country":"GB",
    "sg:address":"20 High Street, Stoke Goldington",
    "sg:city":"Newport Pagnell",
    "sg:classifiers":[
        {
            "category":"Bars & Pubs",
            "type":"Food & Drink"
        }
    ],
    "sg:phone":"+44 1908 551233",
    "sg:postcode":"MK16 8NR",
    "sg:province":"Buckinghamshire",
    "sg:tags":[
        "pubs",
        "inn"
    ],
    "wof:name":"The Lamb",
    "wof:placetype":"venue"
},
  "geometry": {"coordinates":[-0.7206329703,52.0873565674],"type":"Point"}
}