{
  "type": "Feature",
  "properties": {
    "iso:country":"GB",
    "sg:address":"83 Fitzjohn Avenue",
    "sg:city":"Barnet",
    "sg:classifiers":[
        {
            "category":"Professional",
            "subcategory":"Art Services",
            "type":"Services"
        }
    ],
    "sg:phone":"+44 20 8364 9003",
    "sg:postcode":"EN5 2HR",
    "sg:province":"Hertfordshire",
    "sg:tags":[
        "graphic",
        "designer"
    ],
    "wof:name":"Carruthers & Hobbs",
    "wof:placetype":"venue"
},
  "geometry": {"coordinates":[-0.201767,51.649014],"type":"Point"}
}