{
  "type": "Feature",
  "properties": {
    "addr:full":"Unit C, 28 Lancaster Road Barnet Hertfordshire EN4 8AP",
    "addr:housenumber":"unit c 28",
    "addr:postcode":"en4 8ap",
    "addr:street":"Lancaster Road",
    "iso:country":"GB",
    "sg:address":"Unit C, 28 Lancaster Road",
    "sg:city":"Barnet",
    "sg:classifiers":[
        {
            "category":"Professional",
            "subcategory":"Engineering",
            "type":"Services"
        }
    ],
    "sg:phone":"+44 20 8440 4805",
    "sg:postcode":"EN4 8AP",
    "sg:province":"Hertfordshire",
    "sg:tags":[
        "precision",
        "engineer"
    ],
    "wof:name":"Balcombe Engineering Ltd",
    "wof:placetype":"venue"
},
  "geometry": {"coordinates":[-0.161705,51.644211],"type":"Point"}
}