{
  "type": "Feature",
  "properties": {
    "addr:full":"5 Bothwell Street Hammersmith Greater London W6 8DY",
    "addr:housenumber":"5",
    "addr:postcode":"w6 8dy",
    "addr:street":"Bothwell Street",
    "iso:country":"GB",
    "sg:address":"5 Bothwell Street",
    "sg:city":"Hammersmith",
    "sg:classifiers":[
        {
            "category":"Real Estate",
            "subcategory":"Architect",
            "type":"Services"
        }
    ],
    "sg:phone":"+44 20 7385 4243",
    "sg:postcode":"W6 8DY",
    "sg:province":"Greater London",
    "wof:name":"Dominic Architects Warren",
    "wof:placetype":"venue"
},
  "geometry": {"coordinates":[-0.218,51.483799],"type":"Point"}
}