{
  "type": "Feature",
  "properties": {
    "addr:full":"169 Victoria Rd Middlesbrough North Yorkshire TS1 3HR",
    "addr:housenumber":"169",
    "addr:postcode":"ts1 3hr",
    "addr:street":"Victoria Rd",
    "iso:country":"GB",
    "sg:address":"169 Victoria Rd",
    "sg:city":"Middlesbrough",
    "sg:classifiers":[
        {
            "category":"Community Center",
            "type":"Public Place"
        }
    ],
    "sg:phone":"+44 1642 863090",
    "sg:postcode":"TS1 3HR",
    "sg:province":"North Yorkshire",
    "sg:tags":[
        "centre"
    ],
    "wof:name":"Victoria Road Health & Community House",
    "wof:placetype":"venue"
},
  "geometry": {"coordinates":[-1.2275240421,54.5688858032],"type":"Point"}
}