{
  "type": "Feature",
  "properties": {
    "iso:country":"GB",
    "sg:address":"Brighton Road, Bolney",
    "sg:city":"Haywards Heath",
    "sg:classifiers":[
        {
            "category":"Manufacturing",
            "subcategory":"Rubber & Plastics",
            "type":"Manufacturing & Wholesale Goods"
        }
    ],
    "sg:phone":"+44 1444 881960",
    "sg:postcode":"RH17 5NA",
    "sg:province":"East Sussex",
    "sg:tags":[
        "injection",
        "moulding"
    ],
    "wof:name":"Plas-Tech",
    "wof:placetype":"venue"
},
  "geometry": {"coordinates":[-0.1944590062,51.0178909302],"type":"Point"}
}