{
  "type": "Feature",
  "properties": {
    "addr:full":"6 Deansgate Lane, Timperley Altrincham Cheshire WA15 6SB",
    "addr:housenumber":"6",
    "addr:postcode":"wa15 6sb",
    "addr:street":"Deansgate Lane",
    "iso:country":"GB",
    "sg:address":"6 Deansgate Lane, Timperley",
    "sg:city":"Altrincham",
    "sg:classifiers":[
        {
            "category":"Personal",
            "subcategory":"Beauty Salon",
            "type":"Services"
        }
    ],
    "sg:phone":"+44 161 928 0499",
    "sg:postcode":"WA15 6SB",
    "sg:province":"Cheshire",
    "sg:tags":[
        "unisex",
        "hairdresser"
    ],
    "wof:name":"Haircharm",
    "wof:placetype":"venue"
},
  "geometry": {"coordinates":[-2.3397629261,53.3973121643],"type":"Point"}
}