{
  "type": "Feature",
  "properties": {
    "iso:country":"GB",
    "sg:address":"3 Violet Way, Middleton",
    "sg:city":"Manchester",
    "sg:classifiers":[
        {
            "category":"Retail",
            "subcategory":"Driving School",
            "type":"Services"
        }
    ],
    "sg:phone":"+44 161 653 1319",
    "sg:postcode":"M24 2TE",
    "sg:province":"Greater Manchester",
    "wof:name":"Anthony Lawton",
    "wof:placetype":"venue"
},
  "geometry": {"coordinates":[-2.17009,53.545052],"type":"Point"}
}