{
  "type": "Feature",
  "properties": {
    "addr:full":"8 Bankhead Crossway North Edinburgh City of Edinburgh EH11 4BR",
    "addr:housenumber":"8",
    "addr:postcode":"eh11 4br",
    "addr:street":"Bankhead Crossway North Edinburgh",
    "iso:country":"GB",
    "sg:address":"8 Bankhead Crossway North",
    "sg:city":"Edinburgh",
    "sg:classifiers":[
        {
            "category":"Professional",
            "subcategory":"Business Services",
            "type":"Services"
        }
    ],
    "sg:phone":"+44 131 523 6666",
    "sg:postcode":"EH11 4BR",
    "sg:province":"City of Edinburgh",
    "sg:tags":[
        "registrar"
    ],
    "wof:name":"Computershare Services Plc",
    "wof:placetype":"venue"
},
  "geometry": {"coordinates":[-3.297836,55.926445],"type":"Point"}
}