{
  "type": "Feature",
  "properties": {
    "iso:country":"GB",
    "sg:address":"Island Road",
    "sg:city":"St Ives",
    "sg:classifiers":[
        {
            "category":"Travel",
            "subcategory":"Hotels & Motels",
            "type":"Entertainment"
        }
    ],
    "sg:postcode":"TR26 1NT",
    "sg:province":"Cornwall",
    "sg:tags":[
        "self",
        "catering"
    ],
    "wof:name":"Rockcliff Holiday Flats",
    "wof:placetype":"venue"
},
  "geometry": {"coordinates":[-5.478034,50.216221],"type":"Point"}
}