{
  "type": "Feature",
  "properties": {
    "addr:full":"6 The Strand Barnstaple Devon EX31 1EU",
    "addr:housenumber":"6",
    "addr:postcode":"ex31 1eu",
    "addr:street":"The Strand",
    "iso:country":"GB",
    "sg:address":"6 The Strand",
    "sg:city":"Barnstaple",
    "sg:classifiers":[
        {
            "category":"Professional",
            "subcategory":"Art Services",
            "type":"Services"
        }
    ],
    "sg:phone":"+44 1271 343941",
    "sg:postcode":"EX31 1EU",
    "sg:province":"Devon",
    "sg:tags":[
        "photographer"
    ],
    "wof:name":"Baths Photographic",
    "wof:placetype":"venue"
},
  "geometry": {"coordinates":[-4.059252,51.07835],"type":"Point"}
}