{
  "type": "Feature",
  "properties": {
    "addr:full":"The Arcade, Kent St, Upr Gornel Dudley Staffordshire DY3 2DA",
    "addr:postcode":"dy3 2da",
    "addr:street":"Kent St",
    "iso:country":"GB",
    "sg:address":"The Arcade, Kent St, Upr Gornel",
    "sg:city":"Dudley",
    "sg:classifiers":[
        {
            "category":"Professional",
            "subcategory":"Business Services",
            "type":"Services"
        }
    ],
    "sg:postcode":"DY3 2DA",
    "sg:province":"Staffordshire",
    "sg:tags":[
        "import",
        "export",
        "agent"
    ],
    "wof:name":"Hickman,Victor,",
    "wof:placetype":"venue"
},
  "geometry": {"coordinates":[-2.1152,52.526482],"type":"Point"}
}