{
  "type": "Feature",
  "properties": {
    "iso:country":"GB",
    "sg:address":"89 Lynncroft, Eastwood",
    "sg:city":"Nottingham",
    "sg:classifiers":[
        {
            "category":"Building & Trades",
            "subcategory":"Construction",
            "type":"Services"
        }
    ],
    "sg:postcode":"NG16 3ER",
    "sg:province":"Derbyshire",
    "sg:tags":[
        "builder"
    ],
    "wof:name":"Keith Scrimshaw Building Services",
    "wof:placetype":"venue"
},
  "geometry": {"coordinates":[-1.309359,53.018269],"type":"Point"}
}