{
  "type": "Feature",
  "properties": {
    "iso:country":"GB",
    "sg:address":"27 Jury Street",
    "sg:city":"Warwick",
    "sg:classifiers":[
        {
            "category":"Shopping",
            "subcategory":"Antiques",
            "type":"Retail Goods"
        }
    ],
    "sg:postcode":"CV34 4EH",
    "sg:province":"Warwickshire",
    "wof:name":"Fynewood Antiques",
    "wof:placetype":"venue"
},
  "geometry": {"coordinates":[-1.5861150026,52.2820091248],"type":"Point"}
}