{
  "type": "Feature",
  "properties": {
    "addr:full":"382 Gloucester Rd Bristol City of Bristol BS7 8TR",
    "addr:housenumber":"382",
    "addr:postcode":"bs7 8tr",
    "addr:street":"Gloucester Rd",
    "iso:country":"GB",
    "sg:address":"382 Gloucester Rd",
    "sg:city":"Bristol",
    "sg:classifiers":[
        {
            "category":"Health Services",
            "subcategory":"Dentist",
            "type":"Services"
        }
    ],
    "sg:phone":"+44 117 924 7005",
    "sg:postcode":"BS7 8TR",
    "sg:province":"City of Bristol",
    "wof:name":"A H Reed",
    "wof:placetype":"venue"
},
  "geometry": {"coordinates":[-2.586961031,51.4839134216],"type":"Point"}
}