{
  "type": "Feature",
  "properties": {
    "addr:full":"Brackla Street Bridgend Bridgend CF31 1DA",
    "addr:postcode":"cf31 1da",
    "addr:street":"Brackla Street",
    "iso:country":"GB",
    "sg:address":"Brackla Street",
    "sg:city":"Bridgend",
    "sg:classifiers":[
        {
            "category":"Building & Trades",
            "subcategory":"Plumbing",
            "type":"Services"
        }
    ],
    "sg:phone":"+44 1656 653563",
    "sg:postcode":"CF31 1DA",
    "sg:province":"Bridgend",
    "sg:tags":[
        "central",
        "heating"
    ],
    "wof:name":"Lorne Stewart Building Services Engineers",
    "wof:placetype":"venue"
},
  "geometry": {"coordinates":[-3.5746440887,51.5056686401],"type":"Point"}
}