{
  "type": "Feature",
  "properties": {
    "addr:full":"Hollafrench, North Tamerton Holsworthy Cornwall EX22 6SF",
    "addr:postcode":"tamerton;ex22 6sf",
    "addr:street":"North",
    "iso:country":"GB",
    "sg:address":"Hollafrench, North Tamerton",
    "sg:city":"Holsworthy",
    "sg:classifiers":[
        {
            "category":"Farming",
            "subcategory":"Dairy Farm",
            "type":"Manufacturing & Wholesale Goods"
        }
    ],
    "sg:phone":"+44 1409 271224",
    "sg:postcode":"EX22 6SF",
    "sg:province":"Cornwall",
    "sg:tags":[
        "farmer"
    ],
    "wof:name":"W S Jose",
    "wof:placetype":"venue"
},
  "geometry": {"coordinates":[-4.3527340889,50.8100128174],"type":"Point"}
}