{
  "type": "Feature",
  "properties": {
    "addr:full":"9 Lyon Road Crowthorne Berkshire RG45 6RX",
    "addr:housenumber":"9",
    "addr:postcode":"rg45 6rx",
    "addr:street":"Lyon Road",
    "iso:country":"GB",
    "sg:address":"9 Lyon Road",
    "sg:city":"Crowthorne",
    "sg:classifiers":[
        {
            "category":"Professional",
            "subcategory":"Management & Consulting",
            "type":"Services"
        }
    ],
    "sg:postcode":"RG45 6RX",
    "sg:province":"Berkshire",
    "sg:tags":[
        "consultant",
        "business"
    ],
    "wof:name":"Simon Roberts Consulting Ltd.",
    "wof:placetype":"venue"
},
  "geometry": {"coordinates":[-0.7920449972,51.3752326965],"type":"Point"}
}