{
  "type": "Feature",
  "properties": {
    "iso:country":"GB",
    "sg:address":"Block 4 Fordbrook Business Centr, E Marlborough Roa",
    "sg:city":"Pewsey",
    "sg:classifiers":[
        {
            "category":"Professional",
            "subcategory":"Management & Consulting",
            "type":"Services"
        },
        {
            "category":"Organizations",
            "subcategory":"Community Association",
            "type":"Services"
        }
    ],
    "sg:phone":"+44 1672 564099",
    "sg:postcode":"SN9 5NU",
    "sg:province":"Wiltshire",
    "sg:tags":[
        "consultant",
        "relation",
        "public"
    ],
    "wof:name":"Rawlingson Lane Publicity Ltd",
    "wof:placetype":"venue"
},
  "geometry": {"coordinates":[-1.762319,51.340286],"type":"Point"}
}