{
  "type": "Feature",
  "properties": {
    "addr:full":"48 Smawthorne Lane Castleford West Yorkshire WF10 4EW",
    "addr:housenumber":"48",
    "addr:postcode":"wf10 4ew",
    "addr:street":"Smawthorne Lane",
    "iso:country":"GB",
    "sg:address":"48 Smawthorne Lane",
    "sg:city":"Castleford",
    "sg:classifiers":[
        {
            "category":"Transit Center",
            "subcategory":"Passenger",
            "type":"Transportation"
        }
    ],
    "sg:postcode":"WF10 4EW",
    "sg:province":"West Yorkshire",
    "sg:tags":[
        "taxidermist"
    ],
    "wof:name":"Wildlife & Country Craft",
    "wof:placetype":"venue"
},
  "geometry": {"coordinates":[-1.352786,53.721119],"type":"Point"}
}