{
  "type": "Feature",
  "properties": {
    "addr:full":"Grenville House Haig Court, Haig Road, Parkgate Industrial Estate Knutsford Cheshire WA16 8XZ",
    "addr:housenumber":"estate",
    "addr:postcode":"wa16 8xz",
    "addr:street":"Haig Court Haig Road Parkgate Industrial",
    "iso:country":"GB",
    "sg:address":"Grenville House Haig Court, Haig Road, Parkgate Industrial Estate",
    "sg:city":"Knutsford",
    "sg:classifiers":[
        {
            "category":"Professional",
            "subcategory":"Computer Services",
            "type":"Services"
        }
    ],
    "sg:phone":"+44 1565 757900",
    "sg:postcode":"WA16 8XZ",
    "sg:province":"Cheshire",
    "sg:tags":[
        "consultant"
    ],
    "wof:name":"Grenville Consulting (Uk) Ltd.",
    "wof:placetype":"venue"
},
  "geometry": {"coordinates":[-2.357394,53.312328],"type":"Point"}
}