{
  "type": "Feature",
  "properties": {
    "iso:country":"GB",
    "sg:address":"5 Southbourne Grove",
    "sg:city":"Westcliff-on-sea",
    "sg:classifiers":[
        {
            "category":"Shopping",
            "subcategory":"Florist",
            "type":"Retail Goods"
        }
    ],
    "sg:postcode":"SS0 9UW",
    "sg:province":"Essex",
    "wof:name":"Frost,Nola,",
    "wof:placetype":"venue"
},
  "geometry": {"coordinates":[0.677724,51.545815],"type":"Point"}
}