{
  "type": "Feature",
  "properties": {
    "addr:full":"25 Low Street, South Milford Leeds North Yorkshire LS25 5AS",
    "addr:housenumber":"25",
    "addr:postcode":"ls25 5as",
    "addr:street":"Low Street",
    "iso:country":"GB",
    "sg:address":"25 Low Street, South Milford",
    "sg:city":"Leeds",
    "sg:classifiers":[
        {
            "category":"Freight",
            "type":"Transportation"
        }
    ],
    "sg:phone":"+44 7946 162770",
    "sg:postcode":"LS25 5AS",
    "sg:province":"North Yorkshire",
    "sg:tags":[
        "haulage",
        "road"
    ],
    "wof:name":"Hollins Farm Ltd.",
    "wof:placetype":"venue"
},
  "geometry": {"coordinates":[-1.2476819754,53.778427124],"type":"Point"}
}