{
  "type": "Feature",
  "properties": {
    "addr:full":"Unit 1 Lion Mills, Bradiford Barnstaple Devon EX31 4AW",
    "addr:housenumber":"unit 1",
    "addr:postcode":"ex31 4aw",
    "addr:street":"Lion Mills Bradiford",
    "iso:country":"GB",
    "sg:address":"Unit 1 Lion Mills, Bradiford",
    "sg:city":"Barnstaple",
    "sg:classifiers":[
        {
            "category":"Building & Trades",
            "subcategory":"Plumbing",
            "type":"Services"
        }
    ],
    "sg:phone":"+44 1271 375021",
    "sg:postcode":"EX31 4AW",
    "sg:province":"Devon",
    "sg:tags":[
        "heating"
    ],
    "wof:name":"Westway Heating",
    "wof:placetype":"venue"
},
  "geometry": {"coordinates":[-4.070844,51.090786],"type":"Point"}
}