{
  "type": "Feature",
  "properties": {
    "addr:full":"The Gables, Mill Lane, Gedney Hill Spalding Cambridgeshire PE12 0PW",
    "addr:postcode":"pe12 0pw",
    "addr:street":"Mill Lane",
    "iso:country":"GB",
    "sg:address":"The Gables, Mill Lane, Gedney Hill",
    "sg:city":"Spalding",
    "sg:classifiers":[
        {
            "category":"Wholesale",
            "subcategory":"Fruits & Vegetables",
            "type":"Manufacturing & Wholesale Goods"
        },
        {
            "category":"Community Center",
            "type":"Public Place"
        }
    ],
    "sg:phone":"+44 1406 330967",
    "sg:postcode":"PE12 0PW",
    "sg:province":"Cambridgeshire",
    "sg:tags":[
        "producers",
        "nursery",
        "centre"
    ],
    "wof:name":"G Geerlings & Son",
    "wof:placetype":"venue"
},
  "geometry": {"coordinates":[-0.021216,52.682877],"type":"Point"}
}