{
  "type": "Feature",
  "properties": {
    "iso:country":"GB",
    "sg:address":"1 Worthington Drive",
    "sg:city":"Salford",
    "sg:classifiers":[
        {
            "category":"Communications",
            "type":"Services"
        }
    ],
    "sg:phone":"+44 161 708 9072",
    "sg:postcode":"M7 4HG",
    "sg:province":"Greater Manchester",
    "sg:tags":[
        "telecommunication"
    ],
    "wof:name":"J Robinson",
    "wof:placetype":"venue"
},
  "geometry": {"coordinates":[-2.2633059025,53.514667511],"type":"Point"}
}