{
  "type": "Feature",
  "properties": {
    "iso:country":"GB",
    "sg:address":"140 High Street",
    "sg:city":"Honiton",
    "sg:classifiers":[
        {
            "category":"Government",
            "subcategory":"Customs House",
            "type":"Public Place"
        },
        {
            "category":"Shopping",
            "subcategory":"Used Merchandise",
            "type":"Retail Goods"
        }
    ],
    "sg:phone":"+44 1404 45781",
    "sg:postcode":"EX14 1JP",
    "sg:province":"Devon",
    "sg:tags":[
        "shop",
        "clearance",
        "second-hand"
    ],
    "wof:name":"Tat 'N' Treasure",
    "wof:placetype":"venue"
},
  "geometry": {"coordinates":[-3.192122,50.798668],"type":"Point"}
}