{
  "type": "Feature",
  "properties": {
    "addr:full":"4a High Street Cardigan Ceredigion SA43 1HF",
    "addr:housenumber":"4a",
    "addr:postcode":"sa43 1hf",
    "addr:street":"High Street",
    "iso:country":"GB",
    "sg:address":"4a High Street",
    "sg:city":"Cardigan",
    "sg:classifiers":[
        {
            "category":"Education",
            "subcategory":"Special Training",
            "type":"Public Place"
        }
    ],
    "sg:phone":"+44 1239 614988",
    "sg:postcode":"SA43 1HF",
    "sg:province":"Ceredigion",
    "sg:tags":[
        "product",
        "centre"
    ],
    "wof:name":"Hyfforddiant Ceredigion Training",
    "wof:placetype":"venue"
},
  "geometry": {"coordinates":[-4.6615290642,52.082408905],"type":"Point"}
}