{
  "type": "Feature",
  "properties": {
    "addr:full":"Unit A Stoke-on-trent Staffordshire ST4 7BP",
    "addr:housenumber":"unit a",
    "addr:postcode":"st4 7bp",
    "iso:country":"GB",
    "sg:address":"Unit A",
    "sg:city":"Stoke-on-trent",
    "sg:classifiers":[
        {
            "category":"Home & Garden",
            "subcategory":"Building Materials",
            "type":"Retail Goods"
        }
    ],
    "sg:phone":"+44 1782 219330",
    "sg:postcode":"ST4 7BP",
    "sg:province":"Staffordshire",
    "sg:tags":[
        "ventilator",
        "ventilation",
        "system"
    ],
    "wof:name":"Victoria Heating & Ventilating Co. Ltd.",
    "wof:placetype":"venue"
},
  "geometry": {"coordinates":[-2.20407,53.01778],"type":"Point"}
}