{
  "type": "Feature",
  "properties": {
    "addr:full":"18 Nursery Road Montrose Aberdeenshire DD10 9AW",
    "addr:housenumber":"18",
    "addr:postcode":"dd10 9aw",
    "addr:street":"Nursery Road",
    "iso:country":"GB",
    "sg:address":"18 Nursery Road",
    "sg:city":"Montrose",
    "sg:classifiers":[
        {
            "category":"Personal",
            "subcategory":"Beauty Salon",
            "type":"Services"
        }
    ],
    "sg:phone":"+44 1674 676468",
    "sg:postcode":"DD10 9AW",
    "sg:province":"Aberdeenshire",
    "sg:tags":[
        "lady",
        "hairdresser"
    ],
    "wof:name":"Nutters Salon",
    "wof:placetype":"venue"
},
  "geometry": {"coordinates":[-2.467638,56.719574],"type":"Point"}
}