{
  "type": "Feature",
  "properties": {
    "iso:country":"GB",
    "sg:address":"Unit 12 Trinity Court, Brunel Road",
    "sg:city":"Southampton",
    "sg:classifiers":[
        {
            "category":"Shopping",
            "subcategory":"Computers & Home Electronics",
            "type":"Retail Goods"
        }
    ],
    "sg:phone":"+44 23 8066 6333",
    "sg:postcode":"SO40 3WX",
    "sg:province":"Hampshire",
    "sg:tags":[
        "equipment",
        "radio"
    ],
    "wof:name":"T H Communications Ltd.",
    "wof:placetype":"venue"
},
  "geometry": {"coordinates":[-1.506689,50.934074],"type":"Point"}
}