{
  "type": "Feature",
  "properties": {
    "addr:full":"Ellesmere St Manchester Cheshire M15 4LZ",
    "addr:postcode":"m15 4lz",
    "addr:street":"Ellesmere St",
    "iso:country":"GB",
    "sg:address":"Ellesmere St",
    "sg:city":"Manchester",
    "sg:classifiers":[
        {
            "category":"Professional",
            "subcategory":"Management & Consulting",
            "type":"Services"
        }
    ],
    "sg:postcode":"M15 4LZ",
    "sg:province":"Cheshire",
    "sg:tags":[
        "consultant",
        "training"
    ],
    "wof:name":"Onward Training",
    "wof:placetype":"venue"
},
  "geometry": {"coordinates":[-2.2642230988,53.4708175659],"type":"Point"}
}