{
  "type": "Feature",
  "properties": {
    "addr:full":"63 High Street, Bradford Road Birmingham West Midlands B36 9AQ",
    "addr:housenumber":"63",
    "addr:postcode":"b36 9aq",
    "addr:street":"High Street Bradford Road",
    "iso:country":"GB",
    "sg:address":"63 High Street, Bradford Road",
    "sg:city":"Birmingham",
    "sg:classifiers":[
        {
            "category":"Shopping",
            "subcategory":"Clothing, Apparel, & Fashions",
            "type":"Retail Goods"
        }
    ],
    "sg:phone":"+44 1978 351501",
    "sg:postcode":"B36 9AQ",
    "sg:province":"West Midlands",
    "sg:tags":[
        "ladieswear"
    ],
    "wof:name":"Margarets (Bala) Ltd.",
    "wof:placetype":"venue"
},
  "geometry": {"coordinates":[-1.7803299427,52.5018806458],"type":"Point"}
}