{
  "type": "Feature",
  "properties": {
    "addr:full":"Westbrook, Oakhill Road Ryde Isle of Wight PO33 1PU",
    "addr:postcode":"po33 1pu",
    "addr:street":"Oakhill Road",
    "iso:country":"GB",
    "sg:address":"Westbrook, Oakhill Road",
    "sg:city":"Ryde",
    "sg:classifiers":[
        {
            "category":"Community Center",
            "subcategory":"Youth",
            "type":"Public Place"
        }
    ],
    "sg:phone":"+44 1983 811118",
    "sg:postcode":"PO33 1PU",
    "sg:province":"Isle of Wight",
    "sg:tags":[
        "organisation",
        "centre"
    ],
    "wof:name":"Crusader Centre",
    "wof:placetype":"venue"
},
  "geometry": {"coordinates":[-1.1686660051,50.7275657654],"type":"Point"}
}