{
  "type": "Feature",
  "properties": {
    "iso:country":"GB",
    "sg:address":"364 Meltham Road, Netherton",
    "sg:city":"Huddersfield",
    "sg:classifiers":[
        {
            "category":"Personal",
            "subcategory":"Beauty Salon",
            "type":"Services"
        }
    ],
    "sg:postcode":"HD4 7EH",
    "sg:province":"West Yorkshire",
    "sg:tags":[
        "unisex",
        "hairdresser"
    ],
    "wof:name":"Generations Unisex Hairstylist",
    "wof:placetype":"venue"
},
  "geometry": {"coordinates":[-1.8159660101,53.61378479],"type":"Point"}
}