{
  "type": "Feature",
  "properties": {
    "iso:country":"GB",
    "sg:address":"Crit Hall Farm, Cranbrook Road",
    "sg:city":"Cranbrook",
    "sg:classifiers":[
        {
            "category":"Education",
            "subcategory":"Library",
            "type":"Public Place"
        }
    ],
    "sg:postcode":"TN17 4EU",
    "sg:province":"Kent",
    "sg:tags":[
        "reproduction",
        "furniture"
    ],
    "wof:name":"Edward Honess",
    "wof:placetype":"venue"
},
  "geometry": {"coordinates":[0.5352450013,51.0965003967],"type":"Point"}
}