{
  "type": "Feature",
  "properties": {
    "iso:country":"GB",
    "sg:address":"Park Lane, Alderholt",
    "sg:city":"Fordingbridge",
    "sg:classifiers":[
        {
            "category":"Education",
            "subcategory":"School",
            "type":"Public Place"
        }
    ],
    "sg:phone":"+44 1425 653063",
    "sg:postcode":"SP6 3AJ",
    "sg:province":"Dorset",
    "sg:tags":[
        "local",
        "authority"
    ],
    "wof:name":"St. James C of E Vc First School",
    "wof:placetype":"venue"
},
  "geometry": {"coordinates":[-1.8385089636,50.9115791321],"type":"Point"}
}