{
  "type": "Feature",
  "properties": {
    "iso:country":"GB",
    "sg:address":"41 Eastfield Rd",
    "sg:city":"Peterborough",
    "sg:classifiers":[
        {
            "category":"Organizations",
            "subcategory":"Non-profit Organization",
            "type":"Services"
        }
    ],
    "sg:phone":"+44 1733 764848",
    "sg:postcode":"PE1 4AP",
    "sg:province":"Cambridgeshire",
    "sg:tags":[
        "organisation",
        "voluntary",
        "charity"
    ],
    "wof:name":"Samaritans The",
    "wof:placetype":"venue"
},
  "geometry": {"coordinates":[-0.234361,52.578266],"type":"Point"}
}