{
  "type": "Feature",
  "properties": {
    "iso:country":"GB",
    "sg:address":"19 Guildhill Rd",
    "sg:city":"Bournemouth",
    "sg:classifiers":[
        {
            "category":"Personal",
            "subcategory":"Psychics & Astrologers",
            "type":"Services"
        }
    ],
    "sg:phone":"+44 1202 421700",
    "sg:postcode":"BH6 3EY",
    "sg:province":"Dorset",
    "wof:name":"Janette Werrey-Easterbrook",
    "wof:placetype":"venue"
},
  "geometry": {"coordinates":[-1.797524,50.724976],"type":"Point"}
}