{
  "type": "Feature",
  "properties": {
    "addr:full":"51 Park Road, Adlington Chorley Lancashire PR7 4HZ",
    "addr:housenumber":"51",
    "addr:postcode":"pr7 4hz",
    "addr:street":"Park Road",
    "iso:country":"GB",
    "sg:address":"51 Park Road, Adlington",
    "sg:city":"Chorley",
    "sg:classifiers":[
        {
            "category":"Food & Beverages",
            "subcategory":"Fruits & Vegetables",
            "type":"Retail Goods"
        }
    ],
    "sg:phone":"+44 1257 480307",
    "sg:postcode":"PR7 4HZ",
    "sg:province":"Lancashire",
    "sg:tags":[
        "greengrocer"
    ],
    "wof:name":"Ron Burgess",
    "wof:placetype":"venue"
},
  "geometry": {"coordinates":[-2.6093919277,53.6119995117],"type":"Point"}
}