{
  "type": "Feature",
  "properties": {
    "iso:country":"GB",
    "sg:address":"Unit 1c Shaw Lane",
    "sg:city":"Bromsgrove",
    "sg:classifiers":[
        {
            "category":"Manufacturing",
            "subcategory":"Wood Products",
            "type":"Manufacturing & Wholesale Goods"
        }
    ],
    "sg:phone":"+44 1527 579229",
    "sg:postcode":"B60 4DY",
    "sg:province":"Worcestershire",
    "sg:tags":[
        "sawmill",
        "shaving"
    ],
    "wof:name":"Peter Sullivan",
    "wof:placetype":"venue"
},
  "geometry": {"coordinates":[-2.0874519348,52.2926826477],"type":"Point"}
}