{
  "type": "Feature",
  "properties": {
    "iso:country":"GB",
    "sg:address":"Brixington Lane",
    "sg:city":"Exmouth",
    "sg:classifiers":[
        {
            "category":"Health Services",
            "subcategory":"Nursing And Care Facility",
            "type":"Services"
        }
    ],
    "sg:phone":"+44 1395 263643",
    "sg:postcode":"EX8 5DL",
    "sg:province":"Devon",
    "sg:tags":[
        "home"
    ],
    "wof:name":"Knapp Cross",
    "wof:placetype":"venue"
},
  "geometry": {"coordinates":[-3.390709,50.642529],"type":"Point"}
}