{
  "type": "Feature",
  "properties": {
    "addr:full":"68 George St Oldham Lancashire OL1 1LS",
    "addr:housenumber":"68",
    "addr:postcode":"ol1 1ls",
    "addr:street":"George St",
    "iso:country":"GB",
    "sg:address":"68 George St",
    "sg:city":"Oldham",
    "sg:classifiers":[
        {
            "category":"Professional",
            "subcategory":"Employment Agencies",
            "type":"Services"
        }
    ],
    "sg:phone":"+44 161 626 5758",
    "sg:postcode":"OL1 1LS",
    "sg:province":"Lancashire",
    "sg:tags":[
        "consultant"
    ],
    "wof:name":"Kinetic plc",
    "wof:placetype":"venue"
},
  "geometry": {"coordinates":[-2.085241,53.582699],"type":"Point"}
}