{
  "type": "Feature",
  "properties": {
    "iso:country":"GB",
    "sg:address":"Robinson Court, Richmond Road",
    "sg:city":"Barnoldswick",
    "sg:classifiers":[
        {
            "category":"Organizations",
            "subcategory":"Community Association",
            "type":"Services"
        }
    ],
    "sg:postcode":"BB18 5JA",
    "sg:province":"Lancashire",
    "sg:tags":[
        "society",
        "housing"
    ],
    "wof:name":"Anchor Trust",
    "wof:placetype":"venue"
},
  "geometry": {"coordinates":[-2.1931090355,53.9199333191],"type":"Point"}
}