{
  "type": "Feature",
  "properties": {
    "iso:country":"GB",
    "sg:address":"18 Clovelly Road, North Hayling",
    "sg:city":"Hayling Island",
    "sg:classifiers":[
        {
            "category":"Home & Garden",
            "subcategory":"Building Materials",
            "type":"Retail Goods"
        }
    ],
    "sg:postcode":"PO11 0SD",
    "sg:province":"Hampshire",
    "sg:tags":[
        "gate",
        "door",
        "barrier"
    ],
    "wof:name":"Michael R Hawes",
    "wof:placetype":"venue"
},
  "geometry": {"coordinates":[-0.961609,50.826443],"type":"Point"}
}