{
  "type": "Feature",
  "properties": {
    "iso:country":"GB",
    "sg:address":"7 Seacroft Arcade",
    "sg:city":"Leeds",
    "sg:classifiers":[
        {
            "category":"Food & Beverages",
            "subcategory":"Fruits & Vegetables",
            "type":"Retail Goods"
        }
    ],
    "sg:postcode":"LS14 6NR",
    "sg:province":"West Yorkshire",
    "sg:tags":[
        "greengrocer"
    ],
    "wof:name":"Food Weighouse (The)",
    "wof:placetype":"venue"
},
  "geometry": {"coordinates":[-1.460135,53.823166],"type":"Point"}
}