{
  "type": "Feature",
  "properties": {
    "iso:country":"GB",
    "sg:address":"59 Paisley Rd",
    "sg:city":"Renfrew",
    "sg:classifiers":[
        {
            "category":"Health Services",
            "subcategory":"Dentist",
            "type":"Services"
        }
    ],
    "sg:phone":"+44 141 886 2049",
    "sg:postcode":"PA4 8LQ",
    "sg:province":"Renfrewshire",
    "wof:name":"James P Craig",
    "wof:placetype":"venue"
},
  "geometry": {"coordinates":[-4.3945279121,55.8737373352],"type":"Point"}
}