{
  "type": "Feature",
  "properties": {
    "addr:full":"17 Beatrice Street Oswestry Shropshire SY11 1QE",
    "addr:housenumber":"17",
    "addr:postcode":"sy11 1qe",
    "addr:street":"Beatrice Street",
    "iso:country":"GB",
    "sg:address":"17 Beatrice Street",
    "sg:city":"Oswestry",
    "sg:classifiers":[
        {
            "category":"Food & Beverages",
            "subcategory":"Liquor & Beverages",
            "type":"Retail Goods"
        }
    ],
    "sg:phone":"+44 1691 655990",
    "sg:postcode":"SY11 1QE",
    "sg:province":"Shropshire",
    "sg:tags":[
        "beer",
        "spirit",
        "wines"
    ],
    "wof:name":"Grapevine Off Licence",
    "wof:placetype":"venue"
},
  "geometry": {"coordinates":[-3.053079,52.861038],"type":"Point"}
}