{
  "type": "Feature",
  "properties": {
    "iso:country":"GB",
    "sg:address":"8 Kingsley Road",
    "sg:city":"Hounslow",
    "sg:classifiers":[
        {
            "category":"Real Estate",
            "subcategory":"Real Estate Agent",
            "type":"Services"
        }
    ],
    "sg:phone":"+44 20 8569 5244",
    "sg:postcode":"TW3 1NP",
    "sg:province":"Greater London",
    "wof:name":"Lambourne Estate Agents Ltd.",
    "wof:placetype":"venue"
},
  "geometry": {"coordinates":[-0.3554,51.470924],"type":"Point"}
}