{
  "type": "Feature",
  "properties": {
    "iso:country":"GB",
    "sg:address":"Dashwood Road",
    "sg:city":"Gravesend",
    "sg:classifiers":[
        {
            "category":"Education",
            "subcategory":"Library",
            "type":"Public Place"
        }
    ],
    "sg:phone":"+44 1474 365489",
    "sg:postcode":"DA11 7LY",
    "sg:province":"Kent",
    "sg:tags":[
        "book"
    ],
    "wof:name":"Dashwood Library",
    "wof:placetype":"venue"
},
  "geometry": {"coordinates":[0.3611570001,51.430015564],"type":"Point"}
}