{
  "type": "Feature",
  "properties": {
    "addr:full":"32 Tottenhall Road, Palmers Grn London Greater London N13 6HX",
    "addr:housenumber":"32",
    "addr:postcode":"n13 6hx",
    "addr:street":"Tottenhall Road Palmers Grn",
    "iso:country":"GB",
    "sg:address":"32 Tottenhall Road, Palmers Grn",
    "sg:city":"London",
    "sg:classifiers":[
        {
            "category":"Shopping",
            "subcategory":"Gifts & Souvenirs",
            "type":"Retail Goods"
        },
        {
            "category":"Education",
            "subcategory":"School",
            "type":"Public Place"
        }
    ],
    "sg:phone":"+44 20 8888 9088",
    "sg:postcode":"N13 6HX",
    "sg:province":"Greater London",
    "sg:tags":[
        "giftware",
        "local",
        "authority"
    ],
    "wof:name":"Amar Enterprises",
    "wof:placetype":"venue"
},
  "geometry": {"coordinates":[-0.107297,51.611053],"type":"Point"}
}