{
  "type": "Feature",
  "properties": {
    "iso:country":"GB",
    "sg:address":"Manor Farm, East Street, Bole",
    "sg:city":"Retford",
    "sg:classifiers":[
        {
            "category":"Farming",
            "subcategory":"Farm",
            "type":"Manufacturing & Wholesale Goods"
        }
    ],
    "sg:postcode":"DN22 9EW",
    "sg:province":"Nottinghamshire",
    "sg:tags":[
        "mixed",
        "crop"
    ],
    "wof:name":"W E Proudley & Sons",
    "wof:placetype":"venue"
},
  "geometry": {"coordinates":[-0.8106790185,53.3746032715],"type":"Point"}
}