{
  "type": "Feature",
  "properties": {
    "iso:country":"GB",
    "sg:address":"New River Green",
    "sg:city":"Newmarket",
    "sg:classifiers":[
        {
            "category":"Place Of Worship",
            "type":"Public Place"
        }
    ],
    "sg:phone":"+44 1638 577413",
    "sg:postcode":"CB8 7HS",
    "sg:province":"Cambridgeshire",
    "wof:name":"St Martin Exning",
    "wof:placetype":"venue"
},
  "geometry": {"coordinates":[0.3716509938,52.2646598816],"type":"Point"}
}