{
  "type": "Feature",
  "properties": {
    "addr:full":"Manchester House, Abberley Worcester Herefordshire WR6 6AP",
    "addr:postcode":"wr6 6ap",
    "iso:country":"GB",
    "sg:address":"Manchester House, Abberley",
    "sg:city":"Worcester",
    "sg:classifiers":[
        {
            "category":"Food & Beverages",
            "subcategory":"Supermarket",
            "type":"Retail Goods"
        }
    ],
    "sg:phone":"+44 1299 896384",
    "sg:postcode":"WR6 6AP",
    "sg:province":"Herefordshire",
    "wof:name":"William M Flello",
    "wof:placetype":"venue"
},
  "geometry": {"coordinates":[-2.3742539883,52.3078804016],"type":"Point"}
}