{
  "type": "Feature",
  "properties": {
    "addr:full":"Alexandra Road Chapel, Alexandra Road Newport Newport NP20 4AQ",
    "addr:postcode":"np20 4aq",
    "addr:street":"Alexandra Road;Alexandra Road",
    "iso:country":"GB",
    "sg:address":"Alexandra Road Chapel, Alexandra Road",
    "sg:city":"Newport",
    "sg:classifiers":[
        {
            "category":"Organizations",
            "subcategory":"Non-profit Organization",
            "type":"Services"
        }
    ],
    "sg:phone":"+44 1633 214566",
    "sg:postcode":"NP20 4AQ",
    "sg:province":"Newport",
    "sg:tags":[
        "organisation",
        "voluntary",
        "charity"
    ],
    "wof:name":"Multi-International Aid",
    "wof:placetype":"venue"
},
  "geometry": {"coordinates":[-2.9982500076,51.587928772],"type":"Point"}
}