{
  "type": "Feature",
  "properties": {
    "addr:full":"10 Hart Wynd, Bannockburn Stirling Falkirk FK7 8PS",
    "addr:housenumber":"10",
    "addr:postcode":"fk7 8ps",
    "addr:street":"Hart Wynd",
    "iso:country":"GB",
    "sg:address":"10 Hart Wynd, Bannockburn",
    "sg:city":"Stirling",
    "sg:classifiers":[
        {
            "category":"Home & Garden",
            "subcategory":"Carpets & Floor Coverings",
            "type":"Retail Goods"
        }
    ],
    "sg:postcode":"FK7 8PS",
    "sg:province":"Falkirk",
    "sg:tags":[
        "carpets",
        "rug",
        "matting"
    ],
    "wof:name":"I D Carpets",
    "wof:placetype":"venue"
},
  "geometry": {"coordinates":[-3.9051349163,56.0805778503],"type":"Point"}
}