{
  "type": "Feature",
  "properties": {
    "addr:full":"317 Alum Rock Road Birmingham West Midlands B8 3BL",
    "addr:housenumber":"317",
    "addr:postcode":"b8 3bl",
    "addr:street":"Alum Rock Road",
    "iso:country":"GB",
    "sg:address":"317 Alum Rock Road",
    "sg:city":"Birmingham",
    "sg:classifiers":[
        {
            "category":"Personal",
            "subcategory":"Beauty Salon",
            "type":"Services"
        }
    ],
    "sg:phone":"+44 121 326 9538",
    "sg:postcode":"B8 3BL",
    "sg:province":"West Midlands",
    "sg:tags":[
        "unisex",
        "hairdresser"
    ],
    "wof:name":"Noir Hair Salon",
    "wof:placetype":"venue"
},
  "geometry": {"coordinates":[-1.846143961,52.4881706238],"type":"Point"}
}