{
  "type": "Feature",
  "properties": {
    "iso:country":"GB",
    "sg:address":"Trevelgue Road",
    "sg:city":"Newquay",
    "sg:classifiers":[
        {
            "category":"Recreation",
            "subcategory":"Campground",
            "type":"Entertainment"
        }
    ],
    "sg:phone":"+44 1637 852000",
    "sg:postcode":"TR8 4AS",
    "sg:province":"Cornwall",
    "sg:tags":[
        "caravan",
        "park"
    ],
    "wof:name":"Smugglers Haven",
    "wof:placetype":"venue"
},
  "geometry": {"coordinates":[-5.050173,50.428616],"type":"Point"}
}