{
  "type": "Feature",
  "properties": {
    "iso:country":"GB",
    "sg:address":"Brent House, Harlow Common",
    "sg:city":"Harlow",
    "sg:classifiers":[
        {
            "category":"Retail",
            "subcategory":"Auto Repair",
            "type":"Services"
        }
    ],
    "sg:phone":"+44 1279 426211",
    "sg:postcode":"CM17 9JD",
    "sg:province":"Essex",
    "sg:tags":[
        "electrician"
    ],
    "wof:name":"R H L Auto Electrical",
    "wof:placetype":"venue"
},
  "geometry": {"coordinates":[0.14903,51.7577133179],"type":"Point"}
}