{
  "type": "Feature",
  "properties": {
    "addr:full":"The Granary, 1 Downs Court Aylesford Kent ME18 6AL",
    "addr:housenumber":"1",
    "addr:postcode":"me18 6al",
    "addr:street":"Downs Court",
    "iso:country":"GB",
    "sg:address":"The Granary, 1 Downs Court",
    "sg:city":"Aylesford",
    "sg:classifiers":[
        {
            "category":"Building & Trades",
            "subcategory":"Construction",
            "type":"Services"
        }
    ],
    "sg:phone":"+44 1622 817999",
    "sg:postcode":"ME18 6AL",
    "sg:province":"Kent",
    "sg:tags":[
        "heating",
        "contractor"
    ],
    "wof:name":"Stilebridge Mechanical Services Ltd.",
    "wof:placetype":"venue"
},
  "geometry": {"coordinates":[0.4407599866,51.2358093262],"type":"Point"}
}