{
  "type": "Feature",
  "properties": {
    "addr:full":"2 Bitterton House, Scarlet Avenue Port Talbot Neath Port Talbot SA12 7PN",
    "addr:housenumber":"2;house",
    "addr:postcode":"sa12 7pn",
    "addr:street":"Scarlet Avenue",
    "iso:country":"GB",
    "sg:address":"2 Bitterton House, Scarlet Avenue",
    "sg:city":"Port Talbot",
    "sg:classifiers":[
        {
            "category":"Professional",
            "subcategory":"Engineering",
            "type":"Services"
        }
    ],
    "sg:phone":"+44 1639 897608",
    "sg:postcode":"SA12 7PN",
    "sg:province":"Neath Port Talbot",
    "sg:tags":[
        "contractor",
        "electrical",
        "engineer"
    ],
    "wof:name":"Alan Headon Electrical",
    "wof:placetype":"venue"
},
  "geometry": {"coordinates":[-3.8023691177,51.5913848877],"type":"Point"}
}