{
  "type": "Feature",
  "properties": {
    "addr:full":"41 Gerrard Road London Greater London N1 8AX",
    "addr:housenumber":"41",
    "addr:postcode":"n1 8ax",
    "addr:street":"Gerrard Road",
    "iso:country":"GB",
    "sg:address":"41 Gerrard Road",
    "sg:city":"London",
    "sg:classifiers":[
        {
            "category":"Professional",
            "subcategory":"Business Services",
            "type":"Services"
        }
    ],
    "sg:phone":"+44 20 7704 6199",
    "sg:postcode":"N1 8AX",
    "sg:province":"Greater London",
    "sg:tags":[
        "shop",
        "cleaning"
    ],
    "wof:name":"Simply Better Services",
    "wof:placetype":"venue"
},
  "geometry": {"coordinates":[-0.1013849974,51.5340156555],"type":"Point"}
}