{
  "type": "Feature",
  "properties": {
    "addr:full":"5 High Street Daventry Northamptonshire NN11 4BG",
    "addr:housenumber":"5",
    "addr:postcode":"nn11 4bg",
    "addr:street":"High Street",
    "iso:country":"GB",
    "sg:address":"5 High Street",
    "sg:city":"Daventry",
    "sg:classifiers":[
        {
            "category":"Personal",
            "subcategory":"Beauty Salon",
            "type":"Services"
        }
    ],
    "sg:phone":"+44 1327 703894",
    "sg:postcode":"NN11 4BG",
    "sg:province":"Northamptonshire",
    "sg:tags":[
        "unisex",
        "hairdresser"
    ],
    "wof:name":"Robert James Hairdressing",
    "wof:placetype":"venue"
},
  "geometry": {"coordinates":[-1.160586,52.25819],"type":"Point"}
}