{
  "type": "Feature",
  "properties": {
    "iso:country":"GB",
    "sg:address":"New England Street",
    "sg:city":"Brighton",
    "sg:classifiers":[
        {
            "category":"Shopping",
            "subcategory":"Bicycles & Sporting Goods",
            "type":"Retail Goods"
        }
    ],
    "sg:phone":"+44 1273 684000",
    "sg:postcode":"BN1 4GQ",
    "sg:province":"East Sussex",
    "sg:tags":[
        "equipment",
        "camping"
    ],
    "wof:name":"Johns Camping International",
    "wof:placetype":"venue"
},
  "geometry": {"coordinates":[-0.1403609961,50.8331565857],"type":"Point"}
}