{
  "type": "Feature",
  "properties": {
    "iso:country":"GB",
    "sg:address":"Progress Way",
    "sg:city":"Darlington",
    "sg:classifiers":[
        {
            "category":"Home & Garden",
            "subcategory":"Furniture",
            "type":"Retail Goods"
        }
    ],
    "sg:postcode":"DL1 1TE",
    "sg:province":"Durham",
    "wof:name":"Harris,Michael,",
    "wof:placetype":"venue"
},
  "geometry": {"coordinates":[-1.5519239902,54.5325050354],"type":"Point"}
}