{
  "type": "Feature",
  "properties": {
    "addr:full":"68-72 Old Hall Street Liverpool Merseyside L3 9PP",
    "addr:housenumber":"68-72",
    "addr:postcode":"l3 9pp",
    "addr:street":"Old Hall Street",
    "iso:country":"GB",
    "sg:address":"68-72 Old Hall Street",
    "sg:city":"Liverpool",
    "sg:classifiers":[
        {
            "category":"Shopping",
            "subcategory":"News",
            "type":"Retail Goods"
        }
    ],
    "sg:phone":"+44 151 236 4959",
    "sg:postcode":"L3 9PP",
    "sg:province":"Merseyside",
    "sg:tags":[
        "newsagent"
    ],
    "wof:name":"City News",
    "wof:placetype":"venue"
},
  "geometry": {"coordinates":[-2.9940319061,53.4092788696],"type":"Point"}
}