{
  "type": "Feature",
  "properties": {
    "addr:full":"48 Dalton Avenue, Stretford Manchester Cheshire M32 9TP",
    "addr:housenumber":"48",
    "addr:postcode":"m32 9tp",
    "addr:street":"Dalton Avenue",
    "iso:country":"GB",
    "sg:address":"48 Dalton Avenue, Stretford",
    "sg:city":"Manchester",
    "sg:classifiers":[
        {
            "category":"Building & Trades",
            "subcategory":"Plumbing",
            "type":"Services"
        }
    ],
    "sg:phone":"+44 161 747 7634",
    "sg:postcode":"M32 9TP",
    "sg:province":"Cheshire",
    "sg:tags":[
        "central",
        "heating"
    ],
    "wof:name":"P T Roberts",
    "wof:placetype":"venue"
},
  "geometry": {"coordinates":[-2.327473,53.449219],"type":"Point"}
}