{
  "type": "Feature",
  "properties": {
    "addr:full":"27 Ettington Close, Wellesbourne Warwick Warwickshire CV35 9RJ",
    "addr:housenumber":"27",
    "addr:postcode":"cv35 9rj",
    "addr:street":"Ettington Close Wellesbourne",
    "iso:country":"GB",
    "sg:address":"27 Ettington Close, Wellesbourne",
    "sg:city":"Warwick",
    "sg:classifiers":[
        {
            "category":"Professional",
            "subcategory":"Accounting & Tax Preparation",
            "type":"Services"
        }
    ],
    "sg:phone":"+44 1789 840159",
    "sg:postcode":"CV35 9RJ",
    "sg:province":"Warwickshire",
    "sg:tags":[
        "accountant"
    ],
    "wof:name":"Budget Accounting",
    "wof:placetype":"venue"
},
  "geometry": {"coordinates":[-1.5965930223,52.1924705505],"type":"Point"}
}