{
  "type": "Feature",
  "properties": {
    "addr:full":"1 Promenade, Arnside Carnforth Cumbria LA5 0HF",
    "addr:housenumber":"1",
    "addr:postcode":"la5 0hf",
    "addr:street":"Promenade",
    "iso:country":"GB",
    "sg:address":"1 Promenade, Arnside",
    "sg:city":"Carnforth",
    "sg:classifiers":[
        {
            "category":"Food & Beverages",
            "subcategory":"Meat & Fish",
            "type":"Retail Goods"
        },
        {
            "category":"Food & Beverages",
            "subcategory":"Groceries & Convenience Stores",
            "type":"Retail Goods"
        }
    ],
    "sg:phone":"+44 1524 761874",
    "sg:postcode":"LA5 0HF",
    "sg:province":"Cumbria",
    "sg:tags":[
        "shop",
        "chip"
    ],
    "wof:name":"Arnside Chip Shop",
    "wof:placetype":"venue"
},
  "geometry": {"coordinates":[-2.7680590153,54.1284790039],"type":"Point"}
}