{
  "type": "Feature",
  "properties": {
    "addr:full":"61 Stafford Road Wallington Surrey SM6 9AP",
    "addr:housenumber":"61",
    "addr:postcode":"sm6 9ap",
    "addr:street":"Stafford Road",
    "iso:country":"GB",
    "sg:address":"61 Stafford Road",
    "sg:city":"Wallington",
    "sg:classifiers":[
        {
            "category":"Real Estate",
            "subcategory":"Real Estate Services",
            "type":"Services"
        },
        {
            "category":"Building & Trades",
            "subcategory":"Construction",
            "type":"Services"
        }
    ],
    "sg:phone":"+44 20 8773 4792",
    "sg:postcode":"SM6 9AP",
    "sg:province":"Surrey",
    "sg:tags":[
        "property",
        "restoration",
        "refurbishment",
        "maintenance"
    ],
    "wof:name":"Mantech Maintenance Ltd.",
    "wof:placetype":"venue"
},
  "geometry": {"coordinates":[-0.144124,51.358467],"type":"Point"}
}