{
  "type": "Feature",
  "properties": {
    "iso:country":"GB",
    "sg:address":"34 Jane Street",
    "sg:city":"Edinburgh",
    "sg:classifiers":[
        {
            "category":"Retail",
            "subcategory":"Auto Repair",
            "type":"Services"
        }
    ],
    "sg:phone":"+44 131 554 6670",
    "sg:postcode":"EH6 5HD",
    "sg:province":"City of Edinburgh",
    "sg:tags":[
        "modification",
        "garage"
    ],
    "wof:name":"Autojack",
    "wof:placetype":"venue"
},
  "geometry": {"coordinates":[-3.174446,55.969822],"type":"Point"}
}