{
  "type": "Feature",
  "properties": {
    "iso:country":"GB",
    "sg:address":"31 Calgary Drive",
    "sg:city":"Worcester",
    "sg:classifiers":[
        {
            "category":"Professional",
            "subcategory":"Lawyer & Legal Services",
            "type":"Services"
        }
    ],
    "sg:postcode":"WR2 4DW",
    "sg:province":"Worcestershire",
    "sg:tags":[
        "advice",
        "counselling"
    ],
    "wof:name":"Cancer Support Group",
    "wof:placetype":"venue"
},
  "geometry": {"coordinates":[-2.240528,52.175274],"type":"Point"}
}