{
  "type": "Feature",
  "properties": {
    "iso:country":"GB",
    "sg:address":"180 Thornliebank Road, Thornliebank",
    "sg:city":"Glasgow",
    "sg:classifiers":[
        {
            "category":"Arena",
            "subcategory":"Sports Club",
            "type":"Entertainment"
        }
    ],
    "sg:phone":"+44 141 632 4298",
    "sg:postcode":"G46 7RQ",
    "sg:province":"East Renfrewshire",
    "sg:tags":[
        "ground"
    ],
    "wof:name":"Hutchesons' St.Aloysians Rugby Football Club",
    "wof:placetype":"venue"
},
  "geometry": {"coordinates":[-4.3107409477,55.812171936],"type":"Point"}
}