{
  "type": "Feature",
  "properties": {
    "iso:country":"GB",
    "sg:address":"33-35 High Street",
    "sg:city":"Fraserburgh",
    "sg:classifiers":[
        {
            "category":"Shopping",
            "subcategory":"Jewelry",
            "type":"Retail Goods"
        },
        {
            "category":"Shopping",
            "subcategory":"Comic Books",
            "type":"Retail Goods"
        }
    ],
    "sg:phone":"+44 1346 511611",
    "sg:postcode":"AB43 9AP",
    "sg:province":"Aberdeenshire",
    "sg:tags":[
        "jeweller",
        "sale",
        "jewellery"
    ],
    "sg:website":"http://www.ajwest.co.uk",
    "wof:name":"A J West",
    "wof:placetype":"venue"
},
  "geometry": {"coordinates":[-2.0069921017,57.6936912537],"type":"Point"}
}