{
  "type": "Feature",
  "properties": {
    "addr:full":"16 Glenallan Terrace Motherwell North Lanarkshire ML1 3XX",
    "addr:housenumber":"16",
    "addr:postcode":"ml1 3xx",
    "addr:street":"Glenallan Terrace",
    "iso:country":"GB",
    "sg:address":"16 Glenallan Terrace",
    "sg:city":"Motherwell",
    "sg:classifiers":[
        {
            "category":"Arts & Performance",
            "subcategory":"Music",
            "type":"Entertainment"
        }
    ],
    "sg:postcode":"ML1 3XX",
    "sg:province":"North Lanarkshire",
    "sg:tags":[
        "mobile",
        "disco"
    ],
    "wof:name":"Soundhouse Entertainments",
    "wof:placetype":"venue"
},
  "geometry": {"coordinates":[-4.0007600784,55.8035087585],"type":"Point"}
}