{
  "type": "Feature",
  "properties": {
    "iso:country":"GB",
    "sg:address":"63 Slade Close",
    "sg:city":"Ottery St Mary",
    "sg:classifiers":[
        {
            "category":"Utilities",
            "subcategory":"Refuse",
            "type":"Services"
        }
    ],
    "sg:phone":"+44 1404 815321",
    "sg:postcode":"EX11 1SY",
    "sg:province":"Devon",
    "sg:tags":[
        "skip",
        "hire"
    ],
    "wof:name":"Exmouth Mini Skips",
    "wof:placetype":"venue"
},
  "geometry": {"coordinates":[-3.268002,50.752724],"type":"Point"}
}