{
  "type": "Feature",
  "properties": {
    "iso:country":"GB",
    "sg:address":"2a High St, Amblecote",
    "sg:city":"Stourbridge",
    "sg:classifiers":[
        {
            "category":"Professional",
            "subcategory":"Accounting & Tax Preparation",
            "type":"Services"
        }
    ],
    "sg:postcode":"DY8 4BX",
    "sg:province":"Staffordshire",
    "sg:tags":[
        "accountant"
    ],
    "wof:name":"Holder,David,",
    "wof:placetype":"venue"
},
  "geometry": {"coordinates":[-2.1545689106,52.4704208374],"type":"Point"}
}