{
  "type": "Feature",
  "properties": {
    "addr:full":"The Broadway Pontypridd Caerphilly CF37 2EH",
    "addr:postcode":"cf37 2eh",
    "addr:street":"The Broadway",
    "iso:country":"GB",
    "sg:address":"The Broadway",
    "sg:city":"Pontypridd",
    "sg:classifiers":[
        {
            "category":"Recreation",
            "subcategory":"Amusement Park",
            "type":"Entertainment"
        }
    ],
    "sg:phone":"+44 1443 402430",
    "sg:postcode":"CF37 2EH",
    "sg:province":"Caerphilly",
    "sg:tags":[
        "arcade"
    ],
    "wof:name":"Clubs Automatics Ltd",
    "wof:placetype":"venue"
},
  "geometry": {"coordinates":[-3.3309590816,51.5975494385],"type":"Point"}
}