{
  "type": "Feature",
  "properties": {
    "iso:country":"GB",
    "sg:address":"New Homes, 184 Upper Richmond Road",
    "sg:city":"London",
    "sg:classifiers":[
        {
            "category":"Real Estate",
            "subcategory":"Real Estate Agent",
            "type":"Services"
        }
    ],
    "sg:phone":"+44 20 8780 1642",
    "sg:postcode":"SW15 2SH",
    "sg:province":"Greater London",
    "wof:name":"Allen Briegel",
    "wof:placetype":"venue"
},
  "geometry": {"coordinates":[-0.2155500054,51.4605789185],"type":"Point"}
}