{
  "type": "Feature",
  "properties": {
    "iso:country":"GB",
    "sg:address":"Boroughbridge Rd",
    "sg:city":"Knaresborough",
    "sg:classifiers":[
        {
            "category":"Autos & Motor Vehicles",
            "subcategory":"Automobile Sales",
            "type":"Retail Goods"
        }
    ],
    "sg:phone":"+44 1423 863102",
    "sg:postcode":"HG5 0LZ",
    "sg:province":"North Yorkshire",
    "sg:tags":[
        "car"
    ],
    "wof:name":"Bentley's Of Knaresborough",
    "wof:placetype":"venue"
},
  "geometry": {"coordinates":[-1.462414,54.019699],"type":"Point"}
}