{
  "type": "Feature",
  "properties": {
    "iso:country":"GB",
    "sg:address":"Unit 1, Easton Business Centre",
    "sg:city":"Bristol",
    "sg:classifiers":[
        {
            "category":"Building & Trades",
            "subcategory":"Construction",
            "type":"Services"
        }
    ],
    "sg:postcode":"BS5 0HE",
    "sg:province":"City of Bristol",
    "sg:tags":[
        "valve"
    ],
    "wof:name":"Connexion Developments Ltd.",
    "wof:placetype":"venue"
},
  "geometry": {"coordinates":[-2.691005,51.478111],"type":"Point"}
}