{
  "type": "Feature",
  "properties": {
    "addr:full":"52-54 Rose Street Aberdeen Aberdeen City AB10 1HA",
    "addr:housenumber":"52-54",
    "addr:postcode":"ab10 1ha",
    "addr:street":"Rose Street",
    "iso:country":"GB",
    "sg:address":"52-54 Rose Street",
    "sg:city":"Aberdeen",
    "sg:classifiers":[
        {
            "category":"Autos & Motor Vehicles",
            "subcategory":"Automobile Sales",
            "type":"Retail Goods"
        }
    ],
    "sg:phone":"+44 1224 408517",
    "sg:postcode":"AB10 1HA",
    "sg:province":"Aberdeen City",
    "sg:tags":[
        "car"
    ],
    "wof:name":"Supermarques Ltd.",
    "wof:placetype":"venue"
},
  "geometry": {"coordinates":[-2.111453,57.145332],"type":"Point"}
}