{
  "type": "Feature",
  "properties": {
    "iso:country":"GB",
    "sg:address":"2 Hamlet Court Rd",
    "sg:city":"Westcliff On Sea",
    "sg:classifiers":[
        {
            "category":"Building & Trades",
            "subcategory":"Construction",
            "type":"Services"
        }
    ],
    "sg:phone":"+44 1702 213239",
    "sg:postcode":"SS0 7LX",
    "sg:province":"Essex",
    "sg:tags":[
        "builder"
    ],
    "wof:name":"Panache Interiors",
    "wof:placetype":"venue"
},
  "geometry": {"coordinates":[0.69286,51.537415],"type":"Point"}
}