{
  "type": "Feature",
  "properties": {
    "iso:country":"GB",
    "sg:address":"39 Greenwood Crescent, Boughton",
    "sg:city":"Newark",
    "sg:classifiers":[
        {
            "category":"Manufacturing",
            "subcategory":"Signs",
            "type":"Manufacturing & Wholesale Goods"
        }
    ],
    "sg:phone":"+44 1623 860298",
    "sg:postcode":"NG22 9HX",
    "sg:province":"Nottinghamshire",
    "sg:tags":[
        "commercial",
        "maker"
    ],
    "wof:name":"Wood Graphics",
    "wof:placetype":"venue"
},
  "geometry": {"coordinates":[-0.9946309924,53.2060813904],"type":"Point"}
}