{
  "type": "Feature",
  "properties": {
    "iso:country":"GB",
    "sg:address":"406 Lobley Hill Rd",
    "sg:city":"Gateshead",
    "sg:classifiers":[
        {
            "category":"Health Services",
            "subcategory":"Doctor",
            "type":"Services"
        }
    ],
    "sg:phone":"+44 191 460 4380",
    "sg:postcode":"NE11 0BS",
    "sg:province":"Tyne and Wear",
    "sg:tags":[
        "practitioners"
    ],
    "wof:name":"Pannu, U K",
    "wof:placetype":"venue"
},
  "geometry": {"coordinates":[-1.631519,54.940121],"type":"Point"}
}