{
  "type": "Feature",
  "properties": {
    "addr:full":"2-4 Albert Street Shildon Durham DL4 2DW",
    "addr:housenumber":"2-4",
    "addr:postcode":"dl4 2dw",
    "addr:street":"Albert Street",
    "iso:country":"GB",
    "sg:address":"2-4 Albert Street",
    "sg:city":"Shildon",
    "sg:classifiers":[
        {
            "category":"Professional",
            "subcategory":"Business Services",
            "type":"Services"
        }
    ],
    "sg:phone":"+44 1388 772446",
    "sg:postcode":"DL4 2DW",
    "sg:province":"Durham",
    "sg:tags":[
        "bookmaker"
    ],
    "wof:name":"Chisholm Bookmakers Ltd.",
    "wof:placetype":"venue"
},
  "geometry": {"coordinates":[-1.6414359808,54.6343345642],"type":"Point"}
}