{
  "type": "Feature",
  "properties": {
    "addr:full":"7 Westfield Terrace, Longford Gloucester Gloucestershire GL2 9AZ",
    "addr:housenumber":"7",
    "addr:postcode":"gl2 9az",
    "addr:street":"Westfield Terrace",
    "iso:country":"GB",
    "sg:address":"7 Westfield Terrace, Longford",
    "sg:city":"Gloucester",
    "sg:classifiers":[
        {
            "category":"Freight",
            "type":"Transportation"
        }
    ],
    "sg:postcode":"GL2 9AZ",
    "sg:province":"Gloucestershire",
    "sg:tags":[
        "haulage",
        "road"
    ],
    "wof:name":"John Wilfred Coxhead",
    "wof:placetype":"venue"
},
  "geometry": {"coordinates":[-2.2420480251,51.8792152405],"type":"Point"}
}