{
  "type": "Feature",
  "properties": {
    "addr:full":"4 Priory Clo Chepstow Gloucestershire NP6 5ND",
    "addr:housenumber":"4",
    "addr:postcode":"np6 5nd",
    "addr:street":"Priory Clo",
    "iso:country":"GB",
    "sg:address":"4 Priory Clo",
    "sg:city":"Chepstow",
    "sg:classifiers":[
        {
            "category":"Organizations",
            "subcategory":"Non-profit Organization",
            "type":"Services"
        }
    ],
    "sg:phone":"+44 1291 620370",
    "sg:postcode":"NP6 5ND",
    "sg:province":"Gloucestershire",
    "sg:tags":[
        "organisation",
        "voluntary",
        "charity"
    ],
    "wof:name":"Gwent Disabled Motorists Club",
    "wof:placetype":"venue"
},
  "geometry": {"coordinates":[-2.6848299503,51.6446113586],"type":"Point"}
}