{
  "type": "Feature",
  "properties": {
    "addr:full":"Railway Street, Hetton Le Hole Houghton-le-spring Durham DH5 9HY",
    "addr:postcode":"dh5 9hy",
    "addr:street":"Railway Street",
    "iso:country":"GB",
    "sg:address":"Railway Street, Hetton Le Hole",
    "sg:city":"Houghton-le-spring",
    "sg:classifiers":[
        {
            "category":"Bars & Pubs",
            "type":"Food & Drink"
        }
    ],
    "sg:postcode":"DH5 9HY",
    "sg:province":"Durham",
    "sg:tags":[
        "pubs",
        "inn"
    ],
    "wof:name":"The Crown Inn",
    "wof:placetype":"venue"
},
  "geometry": {"coordinates":[-1.450349,54.821548],"type":"Point"}
}