{
  "type": "Feature",
  "properties": {
    "addr:full":"Waterton Road, Waterton Bridgend Bridgend CF31 3YS",
    "addr:postcode":"cf31 3ys",
    "addr:street":"Waterton Road",
    "iso:country":"GB",
    "sg:address":"Waterton Road, Waterton",
    "sg:city":"Bridgend",
    "sg:classifiers":[
        {
            "category":"Freight",
            "type":"Transportation"
        }
    ],
    "sg:phone":"+44 1656 302200",
    "sg:postcode":"CF31 3YS",
    "sg:province":"Bridgend",
    "sg:tags":[
        "haulage",
        "road"
    ],
    "wof:name":"Carline Transport Ltd.",
    "wof:placetype":"venue"
},
  "geometry": {"coordinates":[-3.545669,51.494995],"type":"Point"}
}