{
  "type": "Feature",
  "properties": {
    "addr:full":"5 Filey Close, Biggin Hill Westerham Kent TN16 3PE",
    "addr:housenumber":"5",
    "addr:postcode":"tn16 3pe",
    "addr:street":"Filey Close",
    "iso:country":"GB",
    "sg:address":"5 Filey Close, Biggin Hill",
    "sg:city":"Westerham",
    "sg:classifiers":[
        {
            "category":"Building & Trades",
            "subcategory":"Equipment Rental",
            "type":"Services"
        }
    ],
    "sg:phone":"+44 1959 574438",
    "sg:postcode":"TN16 3PE",
    "sg:province":"Kent",
    "sg:tags":[
        "hire",
        "catering"
    ],
    "wof:name":"Magical Marquees",
    "wof:placetype":"venue"
},
  "geometry": {"coordinates":[0.018417,51.301739],"type":"Point"}
}