{
  "type": "Feature",
  "properties": {
    "addr:full":"29-31 Bridge Street Burnley Lancashire BB11 1AH",
    "addr:housenumber":"29-31",
    "addr:postcode":"bb11 1ah",
    "addr:street":"Bridge Street",
    "iso:country":"GB",
    "sg:address":"29-31 Bridge Street",
    "sg:city":"Burnley",
    "sg:classifiers":[
        {
            "category":"Cafe",
            "type":"Food & Drink"
        }
    ],
    "sg:phone":"+44 1282 455717",
    "sg:postcode":"BB11 1AH",
    "sg:province":"Lancashire",
    "sg:tags":[
        "tea",
        "room"
    ],
    "wof:name":"Cafe Bridges",
    "wof:placetype":"venue"
},
  "geometry": {"coordinates":[-2.2416930199,53.790309906],"type":"Point"}
}