{
  "type": "Feature",
  "properties": {
    "addr:full":"Meals On Wheels, Victoria Centre, Church St Oswestry Shropshire SY11 2SY",
    "addr:postcode":"sy11 2sy",
    "addr:street":"Church St",
    "iso:country":"GB",
    "sg:address":"Meals On Wheels, Victoria Centre, Church St",
    "sg:city":"Oswestry",
    "sg:classifiers":[
        {
            "category":"Organizations",
            "subcategory":"Non-profit Organization",
            "type":"Services"
        }
    ],
    "sg:phone":"+44 1691 670589",
    "sg:postcode":"SY11 2SY",
    "sg:province":"Shropshire",
    "sg:tags":[
        "organisation",
        "voluntary",
        "charity"
    ],
    "wof:name":"WRVS",
    "wof:placetype":"venue"
},
  "geometry": {"coordinates":[-3.0480890274,52.8636016846],"type":"Point"}
}