{
  "type": "Feature",
  "properties": {
    "addr:full":"27 Happy Land North, St Johns Worcester Worcestershire WR2 5DH",
    "addr:housenumber":"27",
    "addr:postcode":"wr2 5dh",
    "addr:street":"Happy Land North St Johns",
    "iso:country":"GB",
    "sg:address":"27 Happy Land North, St Johns",
    "sg:city":"Worcester",
    "sg:classifiers":[
        {
            "category":"Manufacturing",
            "subcategory":"Petroleum Products",
            "type":"Manufacturing & Wholesale Goods"
        }
    ],
    "sg:phone":"+44 1905 423979",
    "sg:postcode":"WR2 5DH",
    "sg:province":"Worcestershire",
    "sg:tags":[
        "double",
        "glazing"
    ],
    "wof:name":"Windowarm Double Window Glaziers",
    "wof:placetype":"venue"
},
  "geometry": {"coordinates":[-2.242149,52.188179],"type":"Point"}
}