{
  "type": "Feature",
  "properties": {
    "addr:full":"291 Cowbridge Road East Cardiff Cardiff CF5 1JB",
    "addr:housenumber":"291",
    "addr:postcode":"cf5 1jb",
    "addr:street":"Cowbridge Road East",
    "iso:country":"GB",
    "sg:address":"291 Cowbridge Road East",
    "sg:city":"Cardiff",
    "sg:classifiers":[
        {
            "category":"Building & Trades",
            "subcategory":"Construction",
            "type":"Services"
        }
    ],
    "sg:postcode":"CF5 1JB",
    "sg:province":"Cardiff",
    "sg:tags":[
        "builder"
    ],
    "wof:name":"Parle,Patrick A,",
    "wof:placetype":"venue"
},
  "geometry": {"coordinates":[-3.2025749683,51.4816093445],"type":"Point"}
}