{
  "type": "Feature",
  "properties": {
    "addr:full":"Winchester Road Romsey Hampshire SO51 9BQ",
    "addr:postcode":"so51 9bq",
    "addr:street":"Winchester Road",
    "iso:country":"GB",
    "sg:address":"Winchester Road",
    "sg:city":"Romsey",
    "sg:classifiers":[
        {
            "category":"Building & Trades",
            "subcategory":"Construction",
            "type":"Services"
        }
    ],
    "sg:phone":"+44 23 8025 4321",
    "sg:postcode":"SO51 9BQ",
    "sg:province":"Hampshire",
    "sg:tags":[
        "builder"
    ],
    "wof:name":"Dunning & Sons",
    "wof:placetype":"venue"
},
  "geometry": {"coordinates":[-1.4636809826,50.9973678589],"type":"Point"}
}