{
  "type": "Feature",
  "properties": {
    "addr:full":"Care Of 6 Renishaw Dr Leicester Leicestershire LE5 5TY",
    "addr:postcode":"le5 5ty",
    "addr:street":"Renishaw Dr",
    "iso:country":"GB",
    "sg:address":"Care Of 6 Renishaw Dr",
    "sg:city":"Leicester",
    "sg:classifiers":[
        {
            "category":"Home & Garden",
            "subcategory":"Hardware",
            "type":"Retail Goods"
        }
    ],
    "sg:phone":"+44 116 270 3585",
    "sg:postcode":"LE5 5TY",
    "sg:province":"Leicestershire",
    "sg:tags":[
        "compressor",
        "air"
    ],
    "wof:name":"East Midland Pneumatic (Peterborough) Ltd",
    "wof:placetype":"venue"
},
  "geometry": {"coordinates":[-1.0934200287,52.6185188293],"type":"Point"}
}