{
  "type": "Feature",
  "properties": {
    "iso:country":"GB",
    "sg:address":"Moorland Road",
    "sg:city":"Lytham St Annes",
    "sg:classifiers":[
        {
            "category":"Government",
            "subcategory":"Office",
            "type":"Public Place"
        }
    ],
    "sg:phone":"+44 1253 714114",
    "sg:postcode":"FY8 3ZZ",
    "sg:province":"Lancashire",
    "sg:tags":[
        "central",
        "local"
    ],
    "wof:name":"Department for Work & Pensions",
    "wof:placetype":"venue"
},
  "geometry": {"coordinates":[-3.0099990368,53.7543296814],"type":"Point"}
}