{
  "type": "Feature",
  "properties": {
    "addr:full":"115 Queensway Orpington Kent BR5 1PP",
    "addr:housenumber":"115",
    "addr:postcode":"br5 1pp",
    "addr:street":"Queensway Orpington",
    "iso:country":"GB",
    "sg:address":"115 Queensway",
    "sg:city":"Orpington",
    "sg:classifiers":[
        {
            "category":"Shopping",
            "subcategory":"Crafts & Fabrics",
            "type":"Retail Goods"
        }
    ],
    "sg:postcode":"BR5 1PP",
    "sg:province":"Kent",
    "sg:tags":[
        "shop",
        "needlecraft",
        "wool"
    ],
    "wof:name":"Woolcraft",
    "wof:placetype":"venue"
},
  "geometry": {"coordinates":[0.0721890032,51.3893852234],"type":"Point"}
}