{
  "type": "Feature",
  "properties": {
    "addr:full":"43 High Street Bagshot Berkshire GU19 5AF",
    "addr:housenumber":"43",
    "addr:postcode":"gu19 5af",
    "addr:street":"High Street",
    "iso:country":"GB",
    "sg:address":"43 High Street",
    "sg:city":"Bagshot",
    "sg:classifiers":[
        {
            "category":"Personal",
            "subcategory":"Beauty Salon",
            "type":"Services"
        },
        {
            "category":"Personal",
            "subcategory":"Barber",
            "type":"Services"
        }
    ],
    "sg:phone":"+44 1276 471707",
    "sg:postcode":"GU19 5AF",
    "sg:province":"Berkshire",
    "sg:tags":[
        "unisex",
        "hairdresser"
    ],
    "wof:name":"Brooks Hair Salon",
    "wof:placetype":"venue"
},
  "geometry": {"coordinates":[-0.6918929815,51.3619842529],"type":"Point"}
}