{
  "type": "Feature",
  "properties": {
    "addr:full":"The Studio High View, Hare Street Buntingford Hertfordshire SG9 0DZ",
    "addr:postcode":"sg9 0dz",
    "addr:street":"Hare Street",
    "iso:country":"GB",
    "sg:address":"The Studio High View, Hare Street",
    "sg:city":"Buntingford",
    "sg:classifiers":[
        {
            "category":"Professional",
            "subcategory":"Art Services",
            "type":"Services"
        }
    ],
    "sg:phone":"+44 1763 289779",
    "sg:postcode":"SG9 0DZ",
    "sg:province":"Hertfordshire",
    "sg:tags":[
        "consultant",
        "design"
    ],
    "wof:name":"Chris Rodgers Design",
    "wof:placetype":"venue"
},
  "geometry": {"coordinates":[0.016465,51.948196],"type":"Point"}
}