{
  "type": "Feature",
  "properties": {
    "iso:country":"GB",
    "sg:address":"Ripley, Bransgore",
    "sg:city":"Christchurch",
    "sg:classifiers":[
        {
            "category":"Farming",
            "subcategory":"Dairy Farm",
            "type":"Manufacturing & Wholesale Goods"
        }
    ],
    "sg:postcode":"BH23 8ES",
    "sg:province":"Dorset",
    "wof:name":"J R Mitchell",
    "wof:placetype":"venue"
},
  "geometry": {"coordinates":[-1.733091,50.7799],"type":"Point"}
}