{
  "type": "Feature",
  "properties": {
    "addr:full":"64 Church St, Swinton Mexborough South Yorkshire S64 8EG",
    "addr:housenumber":"64",
    "addr:postcode":"s64 8eg",
    "addr:street":"Church St",
    "iso:country":"GB",
    "sg:address":"64 Church St, Swinton",
    "sg:city":"Mexborough",
    "sg:classifiers":[
        {
            "category":"Recreation",
            "subcategory":"Arcade",
            "type":"Entertainment"
        }
    ],
    "sg:phone":"+44 1709 584240",
    "sg:postcode":"S64 8EG",
    "sg:province":"South Yorkshire",
    "sg:tags":[
        "machine",
        "amusement"
    ],
    "wof:name":"Y.P.P Amusements & Leisure",
    "wof:placetype":"venue"
},
  "geometry": {"coordinates":[-1.3213880062,53.4887428284],"type":"Point"}
}