{
  "type": "Feature",
  "properties": {
    "addr:full":"Bankfield Ho, Bankfield St Bacup Lancashire OL13 8LW",
    "addr:postcode":"ol13 8lw",
    "addr:street":"St",
    "iso:country":"GB",
    "sg:address":"Bankfield Ho, Bankfield St",
    "sg:city":"Bacup",
    "sg:classifiers":[
        {
            "category":"Health Services",
            "subcategory":"Health Practitioner",
            "type":"Services"
        }
    ],
    "sg:phone":"+44 1706 875911",
    "sg:postcode":"OL13 8LW",
    "sg:province":"Lancashire",
    "sg:tags":[
        "psychologist"
    ],
    "wof:name":"R S Bogart",
    "wof:placetype":"venue"
},
  "geometry": {"coordinates":[-2.2011039257,53.7027168274],"type":"Point"}
}