{
  "type": "Feature",
  "properties": {
    "addr:full":"144 Hartsbourne Avenue Liverpool Merseyside L25 1PZ",
    "addr:housenumber":"144",
    "addr:postcode":"l25 1pz",
    "addr:street":"Hartsbourne Avenue",
    "iso:country":"GB",
    "sg:address":"144 Hartsbourne Avenue",
    "sg:city":"Liverpool",
    "sg:classifiers":[
        {
            "category":"Government",
            "subcategory":"Post Office",
            "type":"Public Place"
        }
    ],
    "sg:postcode":"L25 1PZ",
    "sg:province":"Merseyside",
    "wof:name":"J F & C J Hoolihan",
    "wof:placetype":"venue"
},
  "geometry": {"coordinates":[-2.8723781109,53.3962783813],"type":"Point"}
}