{
  "type": "Feature",
  "properties": {
    "addr:full":"Ringstones Industrial Park, Bridgemont, Whaley Bridge Stockport Cheshire SK23 7PD",
    "addr:postcode":"sk23 7pd",
    "iso:country":"GB",
    "sg:address":"Ringstones Industrial Park, Bridgemont, Whaley Bridge",
    "sg:city":"Stockport",
    "sg:classifiers":[
        {
            "category":"Home & Garden",
            "subcategory":"Hardware",
            "type":"Retail Goods"
        }
    ],
    "sg:phone":"+44 1663 732607",
    "sg:postcode":"SK23 7PD",
    "sg:province":"Cheshire",
    "sg:tags":[
        "product",
        "wire",
        "electrical"
    ],
    "wof:name":"Hill & Sons",
    "wof:placetype":"venue"
},
  "geometry": {"coordinates":[-1.9839639664,53.3296051025],"type":"Point"}
}