{
  "type": "Feature",
  "properties": {
    "iso:country":"GB",
    "sg:address":"Unit 9 Kellythorpe Industrial Estate",
    "sg:city":"Driffield",
    "sg:classifiers":[
        {
            "category":"Professional",
            "subcategory":"Business Services",
            "type":"Services"
        }
    ],
    "sg:phone":"+44 1377 253900",
    "sg:postcode":"YO25 9DJ",
    "sg:province":"East Riding of Yorkshire",
    "sg:tags":[
        "trade"
    ],
    "wof:name":"Association Of Creative Crafts & Arts Lt",
    "wof:placetype":"venue"
},
  "geometry": {"coordinates":[-0.501039,53.96265],"type":"Point"}
}