{
  "type": "Feature",
  "properties": {
    "iso:country":"GB",
    "sg:address":"102 Runcorn Shopping City",
    "sg:city":"Runcorn",
    "sg:classifiers":[
        {
            "category":"Banks & Credit Unions",
            "subcategory":"Bank",
            "type":"Services"
        }
    ],
    "sg:phone":"+44 1928 714040",
    "sg:postcode":"WA7 2HA",
    "sg:province":"Cheshire",
    "wof:name":"H F C Bank Plc",
    "wof:placetype":"venue"
},
  "geometry": {"coordinates":[-2.6987650394,53.3268890381],"type":"Point"}
}