{
  "type": "Feature",
  "properties": {
    "addr:full":"15 Pilch Lane East, Huyton Liverpool Merseyside L36 4HZ",
    "addr:housenumber":"15",
    "addr:postcode":"l36 4hz",
    "addr:street":"Pilch Lane East Huyton",
    "iso:country":"GB",
    "sg:address":"15 Pilch Lane East, Huyton",
    "sg:city":"Liverpool",
    "sg:classifiers":[
        {
            "category":"Retail",
            "subcategory":"Auto Repair",
            "type":"Services"
        }
    ],
    "sg:phone":"+44 151 708 6654",
    "sg:postcode":"L36 4HZ",
    "sg:province":"Merseyside",
    "sg:tags":[
        "engine",
        "car",
        "specialist"
    ],
    "wof:name":"Hometune Motoring Services",
    "wof:placetype":"venue"
},
  "geometry": {"coordinates":[-2.8671529293,53.4101905823],"type":"Point"}
}