{
  "type": "Feature",
  "properties": {
    "addr:full":"26 The Croft Kidderminster Staffordshire DY11 6LX",
    "addr:housenumber":"26",
    "addr:postcode":"dy11 6lx",
    "addr:street":"The Croft",
    "iso:country":"GB",
    "sg:address":"26 The Croft",
    "sg:city":"Kidderminster",
    "sg:classifiers":[
        {
            "category":"Professional",
            "subcategory":"Management & Consulting",
            "type":"Services"
        }
    ],
    "sg:postcode":"DY11 6LX",
    "sg:province":"Staffordshire",
    "sg:tags":[
        "consultant",
        "business"
    ],
    "wof:name":"James Dudley International Ltd.",
    "wof:placetype":"venue"
},
  "geometry": {"coordinates":[-2.273299,52.377804],"type":"Point"}
}