{
  "type": "Feature",
  "properties": {
    "addr:full":"Cambridge Services, 300 Penistone Rd Sheffield South Yorkshire S6 2FU",
    "addr:housenumber":"300",
    "addr:postcode":"s6 2fu",
    "addr:street":"Penistone Rd",
    "iso:country":"GB",
    "sg:address":"Cambridge Services, 300 Penistone Rd",
    "sg:city":"Sheffield",
    "sg:classifiers":[
        {
            "category":"Retail",
            "subcategory":"Auto Rental",
            "type":"Services"
        }
    ],
    "sg:phone":"+44 114 231 2131",
    "sg:postcode":"S6 2FU",
    "sg:province":"South Yorkshire",
    "sg:tags":[
        "truck",
        "hire",
        "van"
    ],
    "wof:name":"Practical Car & Van Rental",
    "wof:placetype":"venue"
},
  "geometry": {"coordinates":[-1.492849946,53.4027900696],"type":"Point"}
}