{
  "type": "Feature",
  "properties": {
    "iso:country":"GB",
    "sg:address":"Lyncastle Road, Appleton Thorn Industrial Estate",
    "sg:city":"Warrington",
    "sg:classifiers":[
        {
            "category":"Building & Trades",
            "subcategory":"Construction",
            "type":"Services"
        }
    ],
    "sg:phone":"+44 1925 261888",
    "sg:postcode":"WA4 4RJ",
    "sg:province":"Cheshire",
    "sg:tags":[
        "equipment"
    ],
    "wof:name":"Hewden Crane Hire Ltd.",
    "wof:placetype":"venue"
},
  "geometry": {"coordinates":[-2.5300838947,53.35105896],"type":"Point"}
}