{
  "type": "Feature",
  "properties": {
    "iso:country":"GB",
    "sg:address":"36-38 St Aubyns",
    "sg:city":"Hove",
    "sg:classifiers":[
        {
            "category":"Education",
            "subcategory":"Special Training",
            "type":"Public Place"
        }
    ],
    "sg:phone":"+44 1273 733640",
    "sg:postcode":"BN3 2TD",
    "sg:province":"East Sussex",
    "sg:tags":[
        "school",
        "language"
    ],
    "wof:name":"Ef International Student Centre",
    "wof:placetype":"venue"
},
  "geometry": {"coordinates":[-0.176693,50.826881],"type":"Point"}
}