{
  "type": "Feature",
  "properties": {
    "addr:full":"Beach Cafe Oasis Shop, Overcombe Corner, Preston Weymouth Dorset DT3 6PN",
    "addr:postcode":"weymouth;dt3 6pn",
    "iso:country":"GB",
    "sg:address":"Beach Cafe Oasis Shop, Overcombe Corner, Preston",
    "sg:city":"Weymouth",
    "sg:classifiers":[
        {
            "category":"Shopping",
            "subcategory":"Gifts & Souvenirs",
            "type":"Retail Goods"
        }
    ],
    "sg:phone":"+44 1305 834069",
    "sg:postcode":"DT3 6PN",
    "sg:province":"Dorset",
    "sg:tags":[
        "shop"
    ],
    "wof:name":"Overcombe Corner Gift Shop",
    "wof:placetype":"venue"
},
  "geometry": {"coordinates":[-2.4289290905,50.6443214417],"type":"Point"}
}