{
  "type": "Feature",
  "properties": {
    "iso:country":"GB",
    "sg:address":"Hippodrome House, Birchett Road",
    "sg:city":"Aldershot",
    "sg:classifiers":[
        {
            "category":"Real Estate",
            "subcategory":"Real Estate Agent",
            "type":"Services"
        }
    ],
    "sg:phone":"+44 1252 325566",
    "sg:postcode":"GU11 1LZ",
    "sg:province":"Hampshire",
    "wof:name":"Willow Management",
    "wof:placetype":"venue"
},
  "geometry": {"coordinates":[-0.764234,51.247704],"type":"Point"}
}