{
  "type": "Feature",
  "properties": {
    "addr:full":"5 St Johns Road Harrow Greater London HA1 2EL",
    "addr:housenumber":"5",
    "addr:postcode":"ha1 2el",
    "addr:street":"St Johns Road",
    "iso:country":"GB",
    "sg:address":"5 St Johns Road",
    "sg:city":"Harrow",
    "sg:classifiers":[
        {
            "category":"Professional",
            "subcategory":"Employment Agencies",
            "type":"Services"
        }
    ],
    "sg:phone":"+44 20 8210 5800",
    "sg:postcode":"HA1 2EL",
    "sg:province":"Greater London",
    "sg:tags":[
        "consultant"
    ],
    "wof:name":"Harrow Garden House Job Centre",
    "wof:placetype":"venue"
},
  "geometry": {"coordinates":[-0.332099,51.581581],"type":"Point"}
}