{
  "type": "Feature",
  "properties": {
    "addr:full":"81 St Aubyns Hove East Sussex BN3 2TL",
    "addr:housenumber":"81",
    "addr:postcode":"bn3 2tl",
    "addr:street":"St Aubyns Hove",
    "iso:country":"GB",
    "sg:address":"81 St Aubyns",
    "sg:city":"Hove",
    "sg:classifiers":[
        {
            "category":"Shopping",
            "subcategory":"Pharmacy",
            "type":"Retail Goods"
        }
    ],
    "sg:phone":"+44 1273 771233",
    "sg:postcode":"BN3 2TL",
    "sg:province":"East Sussex",
    "sg:tags":[
        "medicine",
        "therapy"
    ],
    "wof:name":"Transcendental Meditation",
    "wof:placetype":"venue"
},
  "geometry": {"coordinates":[-0.175518,50.827694],"type":"Point"}
}