{
  "type": "Feature",
  "properties": {
    "iso:country":"GB",
    "sg:address":"Nant Hall Rd",
    "sg:city":"Prestatyn",
    "sg:classifiers":[
        {
            "category":"Food & Beverages",
            "subcategory":"Fruits & Vegetables",
            "type":"Retail Goods"
        }
    ],
    "sg:phone":"+44 1745 853361",
    "sg:postcode":"LL19 9LR",
    "sg:province":"Denbighshire",
    "sg:tags":[
        "greengrocer"
    ],
    "wof:name":"Kwik Fruit",
    "wof:placetype":"venue"
},
  "geometry": {"coordinates":[-3.394244,53.336121],"type":"Point"}
}