{
  "type": "Feature",
  "properties": {
    "iso:country":"GB",
    "sg:address":"2nd Floor, 40-41 Longmillgate",
    "sg:city":"Manchester",
    "sg:classifiers":[
        {
            "category":"Shopping",
            "subcategory":"Jewelry",
            "type":"Retail Goods"
        }
    ],
    "sg:phone":"+44 161 832 9448",
    "sg:postcode":"M3 1NX",
    "sg:province":"Greater Manchester",
    "sg:tags":[
        "gold",
        "silversmith"
    ],
    "wof:name":"A J Keeley",
    "wof:placetype":"venue"
},
  "geometry": {"coordinates":[-2.243408,53.485546],"type":"Point"}
}