{
  "type": "Feature",
  "properties": {
    "addr:full":"5 Salisbury Close Bishops Stortford Essex CM23 3NS",
    "addr:housenumber":"5",
    "addr:postcode":"cm23 3ns",
    "addr:street":"Salisbury Close",
    "iso:country":"GB",
    "sg:address":"5 Salisbury Close",
    "sg:city":"Bishops Stortford",
    "sg:classifiers":[
        {
            "category":"Health Services",
            "subcategory":"Podiatrist",
            "type":"Services"
        }
    ],
    "sg:phone":"+44 1279 657177",
    "sg:postcode":"CM23 3NS",
    "sg:province":"Essex",
    "sg:tags":[
        "podiatrists",
        "chiropodist"
    ],
    "wof:name":"Barry J Clark",
    "wof:placetype":"venue"
},
  "geometry": {"coordinates":[0.159639,51.860714],"type":"Point"}
}