{
  "type": "Feature",
  "properties": {
    "addr:full":"170 Taylifers Harlow Essex CM19 5RQ",
    "addr:housenumber":"170",
    "addr:postcode":"cm19 5rq",
    "addr:street":"Taylifers",
    "iso:country":"GB",
    "sg:address":"170 Taylifers",
    "sg:city":"Harlow",
    "sg:classifiers":[
        {
            "category":"Shopping",
            "subcategory":"Stationery & Office Supplies",
            "type":"Retail Goods"
        },
        {
            "category":"Professional",
            "subcategory":"Testing Lab",
            "type":"Services"
        }
    ],
    "sg:phone":"+44 1279 419694",
    "sg:postcode":"CM19 5RQ",
    "sg:province":"Essex",
    "sg:tags":[
        "recording",
        "machine",
        "time",
        "inspection",
        "calibration"
    ],
    "wof:name":"Emefco Ltd.",
    "wof:placetype":"venue"
},
  "geometry": {"coordinates":[0.071214,51.746952],"type":"Point"}
}