{
  "type": "Feature",
  "properties": {
    "addr:full":"15 Knightcrest Park, Milford Road, Everton Lymington Hampshire SO41 0BA",
    "addr:housenumber":"15",
    "addr:postcode":"so41 0ba",
    "addr:street":"Knightcrest Park Milford Road",
    "iso:country":"GB",
    "sg:address":"15 Knightcrest Park, Milford Road, Everton",
    "sg:city":"Lymington",
    "sg:classifiers":[
        {
            "category":"Home & Garden",
            "subcategory":"Carpets & Floor Coverings",
            "type":"Retail Goods"
        }
    ],
    "sg:phone":"+44 1590 644832",
    "sg:postcode":"SO41 0BA",
    "sg:province":"Hampshire",
    "sg:tags":[
        "carpets",
        "rug",
        "matting"
    ],
    "wof:name":"John Reid",
    "wof:placetype":"venue"
},
  "geometry": {"coordinates":[-1.5824739933,50.7451553345],"type":"Point"}
}