{
  "type": "Feature",
  "properties": {
    "addr:full":"West Tollcross Edinburgh City of Edinburgh EH3 9BP",
    "addr:postcode":"eh3 9bp",
    "addr:street":"West Tollcross",
    "iso:country":"GB",
    "sg:address":"West Tollcross",
    "sg:city":"Edinburgh",
    "sg:classifiers":[
        {
            "category":"Government",
            "subcategory":"City Hall",
            "type":"Public Place"
        },
        {
            "category":"Place Of Worship",
            "type":"Public Place"
        }
    ],
    "sg:postcode":"EH3 9BP",
    "sg:province":"City of Edinburgh",
    "wof:name":"Edinburgh Methodist Mission",
    "wof:placetype":"venue"
},
  "geometry": {"coordinates":[-3.203404,55.943901],"type":"Point"}
}