{
  "type": "Feature",
  "properties": {
    "addr:full":"Ventnor Botanic Garden, The Undercliffe Drive Ventnor Isle of Wight PO38 1UL",
    "addr:postcode":"po38 1ul",
    "addr:street":"Undercliffe Drive",
    "iso:country":"GB",
    "sg:address":"Ventnor Botanic Garden, The Undercliffe Drive",
    "sg:city":"Ventnor",
    "sg:classifiers":[
        {
            "category":"Museum",
            "subcategory":"Art Museum",
            "type":"Entertainment"
        }
    ],
    "sg:phone":"+44 1983 853677",
    "sg:postcode":"PO38 1UL",
    "sg:province":"Isle of Wight",
    "sg:tags":[
        "gallery"
    ],
    "wof:name":"The Museum of Smuggling History",
    "wof:placetype":"venue"
},
  "geometry": {"coordinates":[-1.2004890442,50.5965270996],"type":"Point"}
}