{
  "type": "Feature",
  "properties": {
    "iso:country":"GB",
    "sg:address":"1 Trafalgar Square",
    "sg:city":"Scarborough",
    "sg:classifiers":[
        {
            "category":"Travel",
            "subcategory":"Hotels & Motels",
            "type":"Entertainment"
        }
    ],
    "sg:postcode":"YO12 7PZ",
    "sg:province":"North Yorkshire",
    "sg:tags":[
        "house",
        "guest"
    ],
    "wof:name":"Number One",
    "wof:placetype":"venue"
},
  "geometry": {"coordinates":[-0.4029040039,54.2881126404],"type":"Point"}
}