{
  "type": "Feature",
  "properties": {
    "addr:full":"28 Aylesford Street Leamington Spa Warwickshire CV31 2AH",
    "addr:housenumber":"28",
    "addr:postcode":"cv31 2ah",
    "addr:street":"Aylesford Street",
    "iso:country":"GB",
    "sg:address":"28 Aylesford Street",
    "sg:city":"Leamington Spa",
    "sg:classifiers":[
        {
            "category":"Arts & Performance",
            "subcategory":"Theater",
            "type":"Entertainment"
        }
    ],
    "sg:phone":"+44 1926 421055",
    "sg:postcode":"CV31 2AH",
    "sg:province":"Warwickshire",
    "sg:tags":[
        "hall",
        "theatre",
        "concert"
    ],
    "wof:name":"Sez-U Community Theatre Ltd.",
    "wof:placetype":"venue"
},
  "geometry": {"coordinates":[-1.5280050039,52.2799072266],"type":"Point"}
}