{
  "type": "Feature",
  "properties": {
    "addr:full":"16 High Street Wellington Devon TA21 8RA",
    "addr:housenumber":"16",
    "addr:postcode":"ta21 8ra",
    "addr:street":"High Street",
    "iso:country":"GB",
    "sg:address":"16 High Street",
    "sg:city":"Wellington",
    "sg:classifiers":[
        {
            "category":"Shopping",
            "subcategory":"Jewelry",
            "type":"Retail Goods"
        },
        {
            "category":"Shopping",
            "subcategory":"Comic Books",
            "type":"Retail Goods"
        }
    ],
    "sg:phone":"+44 1823 663155",
    "sg:postcode":"TA21 8RA",
    "sg:province":"Devon",
    "sg:tags":[
        "jeweller",
        "sale",
        "jewellery"
    ],
    "wof:name":"HERBERT WHITE",
    "wof:placetype":"venue"
},
  "geometry": {"coordinates":[-3.226775,50.978962],"type":"Point"}
}