{
  "type": "Feature",
  "properties": {
    "addr:full":"47 High Street Witney Oxfordshire OX28 6JA",
    "addr:housenumber":"47",
    "addr:postcode":"ox28 6ja",
    "addr:street":"High Street",
    "iso:country":"GB",
    "sg:address":"47 High Street",
    "sg:city":"Witney",
    "sg:classifiers":[
        {
            "category":"Fast Food",
            "type":"Food & Drink"
        }
    ],
    "sg:phone":"+44 1993 709220",
    "sg:postcode":"OX28 6JA",
    "sg:province":"Oxfordshire",
    "sg:tags":[
        "away",
        "take"
    ],
    "wof:name":"Bishop Pubs & Restaurant Ltd.",
    "wof:placetype":"venue"
},
  "geometry": {"coordinates":[-1.4845349789,51.7870292664],"type":"Point"}
}