{
  "type": "Feature",
  "properties": {
    "iso:country":"GB",
    "sg:address":"Ashley Oak, Batemans Lane, Reymerston",
    "sg:city":"Norwich",
    "sg:classifiers":[
        {
            "category":"Building & Trades",
            "subcategory":"Construction",
            "type":"Services"
        }
    ],
    "sg:phone":"+44 1362 850419",
    "sg:postcode":"NR9 4AG",
    "sg:province":"Norfolk",
    "sg:tags":[
        "heating",
        "contractor"
    ],
    "wof:name":"B R Parker",
    "wof:placetype":"venue"
},
  "geometry": {"coordinates":[0.984125,52.61467],"type":"Point"}
}