{
  "type": "Feature",
  "properties": {
    "iso:country":"GB",
    "sg:address":"Chilcomb Lane, Chilcomb",
    "sg:city":"Winchester",
    "sg:classifiers":[
        {
            "category":"Manufacturing",
            "subcategory":"Wood Products",
            "type":"Manufacturing & Wholesale Goods"
        }
    ],
    "sg:phone":"+44 1962 868688",
    "sg:postcode":"SO21 1HU",
    "sg:province":"Hampshire",
    "sg:tags":[
        "packaging",
        "crate",
        "pallets"
    ],
    "wof:name":"Plasco Products & Marketing Services",
    "wof:placetype":"venue"
},
  "geometry": {"coordinates":[-1.2757140398,51.0518302917],"type":"Point"}
}