{
  "type": "Feature",
  "properties": {
    "addr:full":"218b Preston Road Weymouth Dorset DT3 6BJ",
    "addr:housenumber":"218b",
    "addr:postcode":"dt3 6bj",
    "addr:street":"Preston Road",
    "iso:country":"GB",
    "sg:address":"218b Preston Road",
    "sg:city":"Weymouth",
    "sg:classifiers":[
        {
            "category":"Restaurant",
            "type":"Food & Drink"
        }
    ],
    "sg:phone":"+44 1305 833500",
    "sg:postcode":"DT3 6BJ",
    "sg:province":"Dorset",
    "sg:tags":[
        "italian"
    ],
    "wof:name":"Michelangelo Pasta Pizza Restaurant & Cappuccino Bar",
    "wof:placetype":"venue"
},
  "geometry": {"coordinates":[-2.420666,50.646481],"type":"Point"}
}