{
  "type": "Feature",
  "properties": {
    "addr:full":"11a Grape La York North Yorkshire YO1 7HU",
    "addr:housenumber":"11a",
    "addr:postcode":"yo1 7hu",
    "addr:street":"Grape La York",
    "iso:country":"GB",
    "sg:address":"11a Grape La",
    "sg:city":"York",
    "sg:classifiers":[
        {
            "category":"Professional",
            "subcategory":"Art Services",
            "type":"Services"
        }
    ],
    "sg:postcode":"YO1 7HU",
    "sg:province":"North Yorkshire",
    "sg:tags":[
        "framing"
    ],
    "wof:name":"Beech,N T,",
    "wof:placetype":"venue"
},
  "geometry": {"coordinates":[-1.082215,53.960804],"type":"Point"}
}