{
  "type": "Feature",
  "properties": {
    "addr:full":"82a West Street Wareham Dorset BH20 7HL",
    "addr:housenumber":"82a",
    "addr:postcode":"bh20 7hl",
    "addr:street":"West Street",
    "iso:country":"GB",
    "sg:address":"82a West Street",
    "sg:city":"Wareham",
    "sg:classifiers":[
        {
            "category":"Retail",
            "subcategory":"Repair Shop",
            "type":"Services"
        }
    ],
    "sg:postcode":"BH20 7HL",
    "sg:province":"Dorset",
    "sg:tags":[
        "upholsterer"
    ],
    "wof:name":"Roy E Hogg",
    "wof:placetype":"venue"
},
  "geometry": {"coordinates":[-2.219243,50.753754],"type":"Point"}
}