{
  "type": "Feature",
  "properties": {
    "iso:country":"GB",
    "sg:address":"12 Sturmer Close, Yate",
    "sg:city":"Bristol",
    "sg:classifiers":[
        {
            "category":"Home & Garden",
            "subcategory":"Building Materials",
            "type":"Retail Goods"
        }
    ],
    "sg:postcode":"BS37 5UR",
    "sg:province":"Gloucestershire",
    "sg:tags":[
        "fencing"
    ],
    "wof:name":"Kenneth Charles Ball",
    "wof:placetype":"venue"
},
  "geometry": {"coordinates":[-2.416279,51.550537],"type":"Point"}
}