{
  "type": "Feature",
  "properties": {
    "iso:country":"GB",
    "sg:address":"Chapel Farm, Luton Road, Chalton",
    "sg:city":"Luton",
    "sg:classifiers":[
        {
            "category":"Farming",
            "subcategory":"Livestock Farm",
            "type":"Manufacturing & Wholesale Goods"
        },
        {
            "category":"Farming",
            "subcategory":"Farm",
            "type":"Manufacturing & Wholesale Goods"
        }
    ],
    "sg:phone":"+44 1525 873949",
    "sg:postcode":"LU4 9UJ",
    "sg:province":"Bedfordshire",
    "sg:tags":[
        "mixed",
        "crop",
        "others"
    ],
    "wof:name":"D & S Hazel",
    "wof:placetype":"venue"
},
  "geometry": {"coordinates":[-0.500811,51.925846],"type":"Point"}
}