{
  "type": "Feature",
  "properties": {
    "iso:country":"GB",
    "sg:address":"31 Station Road, Epworth",
    "sg:city":"Doncaster",
    "sg:classifiers":[
        {
            "category":"Building & Trades",
            "subcategory":"Pest Control",
            "type":"Services"
        },
        {
            "category":"Manufacturing",
            "subcategory":"Building Materials",
            "type":"Manufacturing & Wholesale Goods"
        }
    ],
    "sg:phone":"+44 1427 872111",
    "sg:postcode":"DN9 1JY",
    "sg:province":"Lincolnshire",
    "sg:tags":[
        "use",
        "industrial",
        "door",
        "supp",
        "shutter",
        "manufacturer"
    ],
    "wof:name":"Epworth Industrial Doors Ltd",
    "wof:placetype":"venue"
},
  "geometry": {"coordinates":[-0.832666,53.530994],"type":"Point"}
}