{
  "type": "Feature",
  "properties": {
    "iso:country":"GB",
    "sg:address":"Kettering Road, Rothwell",
    "sg:city":"Kettering",
    "sg:classifiers":[
        {
            "category":"Communications",
            "type":"Services"
        }
    ],
    "sg:phone":"+44 1536 509368",
    "sg:postcode":"NN14 6JR",
    "sg:province":"Northamptonshire",
    "sg:tags":[
        "data",
        "network"
    ],
    "wof:name":"Innovateer Ltd.",
    "wof:placetype":"venue"
},
  "geometry": {"coordinates":[-0.803138,52.422359],"type":"Point"}
}