{
  "type": "Feature",
  "properties": {
    "iso:country":"GB",
    "sg:address":"Southam School, Welsh Road West",
    "sg:city":"Southam",
    "sg:classifiers":[
        {
            "category":"Education",
            "subcategory":"University",
            "type":"Public Place"
        }
    ],
    "sg:phone":"+44 1926 814264",
    "sg:postcode":"CV47 0JW",
    "sg:province":"Warwickshire",
    "sg:tags":[
        "adult"
    ],
    "wof:name":"Southam Adult Centre",
    "wof:placetype":"venue"
},
  "geometry": {"coordinates":[-1.39864,52.257446],"type":"Point"}
}