{
  "type": "Feature",
  "properties": {
    "addr:full":"The Populars Mill End, Bradwell On Sea Southminster Essex CM0 7HJ",
    "addr:postcode":"cm0 7hj",
    "addr:street":"Mill End;Sea",
    "iso:country":"GB",
    "sg:address":"The Populars Mill End, Bradwell On Sea",
    "sg:city":"Southminster",
    "sg:classifiers":[
        {
            "category":"Building & Trades",
            "subcategory":"Construction",
            "type":"Services"
        }
    ],
    "sg:phone":"+44 1621 776201",
    "sg:postcode":"CM0 7HJ",
    "sg:province":"Essex",
    "sg:tags":[
        "joiner",
        "carpenter"
    ],
    "wof:name":"Techforce Developments Ltd",
    "wof:placetype":"venue"
},
  "geometry": {"coordinates":[0.82919,51.662418],"type":"Point"}
}