{
  "type": "Feature",
  "properties": {
    "addr:full":"St. Marys Rd Luton Bedfordshire LU1 3JA",
    "addr:postcode":"lu1 3ja",
    "addr:street":"St. Marys Rd",
    "iso:country":"GB",
    "sg:address":"St. Marys Rd",
    "sg:city":"Luton",
    "sg:classifiers":[
        {
            "category":"Community Center",
            "subcategory":"Youth",
            "type":"Public Place"
        }
    ],
    "sg:phone":"+44 1582 480324",
    "sg:postcode":"LU1 3JA",
    "sg:province":"Bedfordshire",
    "sg:tags":[
        "organisation",
        "centre"
    ],
    "wof:name":"Luton Youth House",
    "wof:placetype":"venue"
},
  "geometry": {"coordinates":[-0.4107339978,51.8799667358],"type":"Point"}
}