{
  "type": "Feature",
  "properties": {
    "iso:country":"GB",
    "sg:address":"66 Shirley Road",
    "sg:city":"Croydon",
    "sg:classifiers":[
        {
            "category":"Food & Beverages",
            "subcategory":"Meat & Fish",
            "type":"Retail Goods"
        }
    ],
    "sg:phone":"+44 20 8654 0222",
    "sg:postcode":"CR0 7EP",
    "sg:province":"Surrey",
    "sg:tags":[
        "chip"
    ],
    "wof:name":"Andreou's Fish Shop",
    "wof:placetype":"venue"
},
  "geometry": {"coordinates":[-0.063306,51.381496],"type":"Point"}
}