{
  "type": "Feature",
  "properties": {
    "addr:full":"30 Market Street, Whittlesey Peterborough Cambridgeshire PE7 1BD",
    "addr:housenumber":"30",
    "addr:postcode":"pe7 1bd",
    "addr:street":"Market Street",
    "iso:country":"GB",
    "sg:address":"30 Market Street, Whittlesey",
    "sg:city":"Peterborough",
    "sg:classifiers":[
        {
            "category":"Retail",
            "subcategory":"Laundry & Dry Cleaning",
            "type":"Services"
        }
    ],
    "sg:phone":"+44 1733 350655",
    "sg:postcode":"PE7 1BD",
    "sg:province":"Cambridgeshire",
    "sg:tags":[
        "cleaner",
        "alteration"
    ],
    "wof:name":"Goldcrest Dry Cleaners",
    "wof:placetype":"venue"
},
  "geometry": {"coordinates":[-0.1295679957,52.5566482544],"type":"Point"}
}