{
  "type": "Feature",
  "properties": {
    "iso:country":"GB",
    "sg:address":"32 Hillary Close",
    "sg:city":"Aylesbury",
    "sg:classifiers":[
        {
            "category":"Taxi",
            "type":"Transportation"
        }
    ],
    "sg:phone":"+44 1296 433970",
    "sg:postcode":"HP21 9TN",
    "sg:province":"Buckinghamshire",
    "sg:tags":[
        "mini",
        "cab"
    ],
    "wof:name":"Club Class Travel Airport Services",
    "wof:placetype":"venue"
},
  "geometry": {"coordinates":[-0.795682,51.802265],"type":"Point"}
}