{
  "type": "Feature",
  "properties": {
    "addr:full":"Westbourne Manor, 17 Westborne Road, Edgbaston Birmingham West Midlands B15 3TR",
    "addr:housenumber":"17",
    "addr:postcode":"b15 3tr",
    "addr:street":"Westborne Road",
    "iso:country":"GB",
    "sg:address":"Westbourne Manor, 17 Westborne Road, Edgbaston",
    "sg:city":"Birmingham",
    "sg:classifiers":[
        {
            "category":"Building & Trades",
            "subcategory":"Cleaning & Sanitation",
            "type":"Services"
        }
    ],
    "sg:phone":"+44 121 353 6090",
    "sg:postcode":"B15 3TR",
    "sg:province":"West Midlands",
    "sg:tags":[
        "facility"
    ],
    "wof:name":"Pertemps Managed Services Ltd.",
    "wof:placetype":"venue"
},
  "geometry": {"coordinates":[-1.9352940321,52.4654350281],"type":"Point"}
}