{
  "type": "Feature",
  "properties": {
    "addr:full":"199 Bishopsgate Moorgate Greater London EC2M 3TY",
    "addr:housenumber":"199",
    "addr:postcode":"ec2m 3ty",
    "addr:street":"Bishopsgate Moorgate",
    "iso:country":"GB",
    "sg:address":"199 Bishopsgate",
    "sg:city":"Moorgate",
    "sg:classifiers":[
        {
            "category":"Professional",
            "subcategory":"Management & Consulting",
            "type":"Services"
        }
    ],
    "sg:phone":"+44 20 7814 6603",
    "sg:postcode":"EC2M 3TY",
    "sg:province":"Greater London",
    "sg:tags":[
        "consultant",
        "business"
    ],
    "wof:name":"Ralph Griffith & Partners",
    "wof:placetype":"venue"
},
  "geometry": {"coordinates":[-0.080959,51.516972],"type":"Point"}
}