{
  "type": "Feature",
  "properties": {
    "iso:country":"GB",
    "sg:address":"1 Granville Square",
    "sg:city":"Stone",
    "sg:classifiers":[
        {
            "category":"Government",
            "subcategory":"Post Office",
            "type":"Public Place"
        }
    ],
    "sg:phone":"+44 1785 814222",
    "sg:postcode":"ST15 8AB",
    "sg:province":"Staffordshire",
    "wof:name":"Stone Post Office Counters",
    "wof:placetype":"venue"
},
  "geometry": {"coordinates":[-2.1484270096,52.9035453796],"type":"Point"}
}