{
  "type": "Feature",
  "properties": {
    "iso:country":"GB",
    "sg:address":"41 King St",
    "sg:city":"Stroud",
    "sg:classifiers":[
        {
            "category":"Travel",
            "subcategory":"Travel Agent",
            "type":"Entertainment"
        }
    ],
    "sg:phone":"+44 1453 750333",
    "sg:postcode":"GL5 1AQ",
    "sg:province":"Gloucestershire",
    "wof:name":"Bakers Dolphin Travel",
    "wof:placetype":"venue"
},
  "geometry": {"coordinates":[-2.217629,51.746021],"type":"Point"}
}