{
  "type": "Feature",
  "properties": {
    "addr:full":"Lessley Cottage, High Street, Rattray Blairgowrie Perth and Kinross PH10 7DE",
    "addr:postcode":"ph10 7de",
    "addr:street":"High Street",
    "iso:country":"GB",
    "sg:address":"Lessley Cottage, High Street, Rattray",
    "sg:city":"Blairgowrie",
    "sg:classifiers":[
        {
            "category":"Arts & Performance",
            "subcategory":"Art Gallery",
            "type":"Entertainment"
        }
    ],
    "sg:phone":"+44 1250 876990",
    "sg:postcode":"PH10 7DE",
    "sg:province":"Perth and Kinross",
    "wof:name":"Virtual Concept",
    "wof:placetype":"venue"
},
  "geometry": {"coordinates":[-3.333314,56.594173],"type":"Point"}
}