{
  "type": "Feature",
  "properties": {
    "addr:full":"12 Hawthorn Road Sutton Surrey SM1 4PF",
    "addr:housenumber":"12",
    "addr:postcode":"sm1 4pf",
    "addr:street":"Hawthorn Road",
    "iso:country":"GB",
    "sg:address":"12 Hawthorn Road",
    "sg:city":"Sutton",
    "sg:classifiers":[
        {
            "category":"Retail",
            "subcategory":"Repair Shop",
            "type":"Services"
        },
        {
            "category":"Home & Garden",
            "subcategory":"Home Furnishings",
            "type":"Retail Goods"
        }
    ],
    "sg:phone":"+44 20 8643 7953",
    "sg:postcode":"SM1 4PF",
    "sg:province":"Surrey",
    "sg:tags":[
        "blind",
        "television",
        "fitting",
        "video",
        "curtain",
        "radio"
    ],
    "wof:name":"Able Sew",
    "wof:placetype":"venue"
},
  "geometry": {"coordinates":[-0.176962,51.360538],"type":"Point"}
}