{
  "type": "Feature",
  "properties": {
    "addr:full":"23 Chapel St Buckfastleigh Devon TQ11 0AQ",
    "addr:housenumber":"23",
    "addr:postcode":"tq11 0aq",
    "addr:street":"Chapel St",
    "iso:country":"GB",
    "sg:address":"23 Chapel St",
    "sg:city":"Buckfastleigh",
    "sg:classifiers":[
        {
            "category":"Place Of Worship",
            "type":"Public Place"
        }
    ],
    "sg:phone":"+44 1364 644272",
    "sg:postcode":"TQ11 0AQ",
    "sg:province":"Devon",
    "wof:name":"The Christian Community In Devon",
    "wof:placetype":"venue"
},
  "geometry": {"coordinates":[-3.7822420597,50.481136322],"type":"Point"}
}