{
  "type": "Feature",
  "properties": {
    "iso:country":"GB",
    "sg:address":"4 Millfield Close, Higher Bebington, Bebington",
    "sg:city":"Wirral",
    "sg:classifiers":[
        {
            "category":"Building & Trades",
            "subcategory":"Construction",
            "type":"Services"
        }
    ],
    "sg:phone":"+44 151 608 6565",
    "sg:postcode":"CH63 2QN",
    "sg:province":"Merseyside",
    "sg:tags":[
        "window",
        "tinting",
        "replacement"
    ],
    "wof:name":"Solar Control Services Ltd",
    "wof:placetype":"venue"
},
  "geometry": {"coordinates":[-3.029439,53.353134],"type":"Point"}
}