{
  "type": "Feature",
  "properties": {
    "iso:country":"GB",
    "sg:address":"14a Byegrove Road",
    "sg:city":"London",
    "sg:classifiers":[
        {
            "category":"Building & Trades",
            "subcategory":"Construction",
            "type":"Services"
        }
    ],
    "sg:phone":"+44 20 8543 8772",
    "sg:postcode":"SW19 2AY",
    "sg:province":"Greater London",
    "sg:tags":[
        "builder"
    ],
    "wof:name":"Clarke Builders",
    "wof:placetype":"venue"
},
  "geometry": {"coordinates":[-0.179182,51.420361],"type":"Point"}
}