{
  "type": "Feature",
  "properties": {
    "iso:country":"GB",
    "sg:address":"Unit 4, 53-79 Highgate Road",
    "sg:city":"London",
    "sg:classifiers":[
        {
            "category":"Home & Garden",
            "subcategory":"Carpets & Floor Coverings",
            "type":"Retail Goods"
        }
    ],
    "sg:phone":"+44 20 7284 4805",
    "sg:postcode":"NW5 1TL",
    "sg:province":"Greater London",
    "sg:tags":[
        "carpets",
        "rug",
        "matting"
    ],
    "wof:name":"Oriental Carpets",
    "wof:placetype":"venue"
},
  "geometry": {"coordinates":[-0.144722,51.55447],"type":"Point"}
}