{
  "type": "Feature",
  "properties": {
    "iso:country":"GB",
    "sg:address":"21 Dassett Road",
    "sg:city":"London",
    "sg:classifiers":[
        {
            "category":"Building & Trades",
            "subcategory":"Construction",
            "type":"Services"
        }
    ],
    "sg:phone":"+44 20 8670 1867",
    "sg:postcode":"SE27 0UF",
    "sg:province":"Greater London",
    "sg:tags":[
        "decorator",
        "painter"
    ],
    "wof:name":"David Cross",
    "wof:placetype":"venue"
},
  "geometry": {"coordinates":[-0.103825,51.42561],"type":"Point"}
}