{
  "type": "Feature",
  "properties": {
    "iso:country":"GB",
    "sg:address":"1248 Wimborne Road, Northbourne",
    "sg:city":"Bournemouth",
    "sg:classifiers":[
        {
            "category":"Retail",
            "subcategory":"Auto Repair",
            "type":"Services"
        }
    ],
    "sg:phone":"+44 1202 577508",
    "sg:postcode":"BH10 7AG",
    "sg:province":"Dorset",
    "sg:tags":[
        "modification",
        "garage",
        "related"
    ],
    "wof:name":"Ensbury Garage",
    "wof:placetype":"venue"
},
  "geometry": {"coordinates":[-1.885437,50.767498],"type":"Point"}
}