{
  "type": "Feature",
  "properties": {
    "addr:full":"Newbury Road, Kingsclere Newbury Berkshire RG20 4SY",
    "addr:postcode":"rg20 4sy",
    "addr:street":"Newbury Road",
    "iso:country":"GB",
    "sg:address":"Newbury Road, Kingsclere",
    "sg:city":"Newbury",
    "sg:classifiers":[
        {
            "category":"Building & Trades",
            "subcategory":"Landscaping Services",
            "type":"Services"
        }
    ],
    "sg:phone":"+44 1635 299100",
    "sg:postcode":"RG20 4SY",
    "sg:province":"Berkshire",
    "sg:tags":[
        "pond",
        "aquarium"
    ],
    "wof:name":"Cottismore Aquatics",
    "wof:placetype":"venue"
},
  "geometry": {"coordinates":[-1.257060051,51.3480491638],"type":"Point"}
}