{
  "type": "Feature",
  "properties": {
    "addr:full":"1 Aidan Road, Amble Morpeth Northumberland NE65 0EQ",
    "addr:housenumber":"1",
    "addr:postcode":"ne65 0eq",
    "addr:street":"Aidan Road",
    "iso:country":"GB",
    "sg:address":"1 Aidan Road, Amble",
    "sg:city":"Morpeth",
    "sg:classifiers":[
        {
            "category":"Freight",
            "type":"Transportation"
        }
    ],
    "sg:postcode":"NE65 0EQ",
    "sg:province":"Northumberland",
    "sg:tags":[
        "haulage",
        "road"
    ],
    "wof:name":"L C Baston (Haulage)",
    "wof:placetype":"venue"
},
  "geometry": {"coordinates":[-1.5859190226,55.3307228088],"type":"Point"}
}