{
  "type": "Feature",
  "properties": {
    "iso:country":"GB",
    "sg:address":"83 Church Street, Werrington",
    "sg:city":"Peterborough",
    "sg:classifiers":[
        {
            "category":"Personal",
            "subcategory":"Beauty Salon",
            "type":"Services"
        }
    ],
    "sg:postcode":"PE4 6QE",
    "sg:province":"Cambridgeshire",
    "wof:name":"Salon Nicole",
    "wof:placetype":"venue"
},
  "geometry": {"coordinates":[-0.273639,52.613422],"type":"Point"}
}