{
  "type": "Feature",
  "properties": {
    "iso:country":"GB",
    "sg:address":"The Hatch, Burghfield",
    "sg:city":"Reading",
    "sg:classifiers":[
        {
            "category":"Personal",
            "type":"Services"
        }
    ],
    "sg:phone":"+44 118 983 1770",
    "sg:postcode":"RG30 3TH",
    "sg:province":"Berkshire",
    "sg:tags":[
        "gift"
    ],
    "wof:name":"Calleva Pewterware",
    "wof:placetype":"venue"
},
  "geometry": {"coordinates":[-1.043148,51.410873],"type":"Point"}
}