{
  "type": "Feature",
  "properties": {
    "addr:full":"144 Wokingham Rd Reading Berkshire RG6 1JL",
    "addr:housenumber":"144",
    "addr:postcode":"rg6 1jl",
    "addr:street":"Wokingham Rd",
    "iso:country":"GB",
    "sg:address":"144 Wokingham Rd",
    "sg:city":"Reading",
    "sg:classifiers":[
        {
            "category":"Food & Beverages",
            "subcategory":"Meat & Fish",
            "type":"Retail Goods"
        }
    ],
    "sg:phone":"+44 118 926 1868",
    "sg:postcode":"RG6 1JL",
    "sg:province":"Berkshire",
    "sg:tags":[
        "chip"
    ],
    "wof:name":"Lings Garden",
    "wof:placetype":"venue"
},
  "geometry": {"coordinates":[-0.9404479861,51.4507331848],"type":"Point"}
}