{
  "type": "Feature",
  "properties": {
    "addr:full":"Unit 1 Wilton Street, Holderness Road Hull East Riding of Yorkshire HU8 7LT",
    "addr:housenumber":"unit 1",
    "addr:postcode":"hu8 7lt",
    "addr:street":"Wilton Street Holderness Road",
    "iso:country":"GB",
    "sg:address":"Unit 1 Wilton Street, Holderness Road",
    "sg:city":"Hull",
    "sg:classifiers":[
        {
            "category":"Manufacturing",
            "subcategory":"Metals",
            "type":"Manufacturing & Wholesale Goods"
        }
    ],
    "sg:phone":"+44 1482 212555",
    "sg:postcode":"HU8 7LT",
    "sg:province":"East Riding of Yorkshire",
    "sg:tags":[
        "work",
        "sheet"
    ],
    "wof:name":"H & M Engineering & Welding",
    "wof:placetype":"venue"
},
  "geometry": {"coordinates":[-0.3212890029,53.7498817444],"type":"Point"}
}