{
  "type": "Feature",
  "properties": {
    "addr:full":"70 Balcarres Road Preston Lancashire PR25 3ED",
    "addr:housenumber":"70",
    "addr:postcode":"pr25 3ed",
    "addr:street":"Balcarres Road",
    "iso:country":"GB",
    "sg:address":"70 Balcarres Road",
    "sg:city":"Preston",
    "sg:classifiers":[
        {
            "category":"Building & Trades",
            "subcategory":"Construction",
            "type":"Services"
        }
    ],
    "sg:phone":"+44 1772 423493",
    "sg:postcode":"PR25 3ED",
    "sg:province":"Lancashire",
    "sg:tags":[
        "roofing"
    ],
    "wof:name":"A B C Roofing",
    "wof:placetype":"venue"
},
  "geometry": {"coordinates":[-2.7246689796,53.7715911865],"type":"Point"}
}