{
  "type": "Feature",
  "properties": {
    "addr:full":"7a Lichfield Road Burntwood Staffordshire WS7 0HQ",
    "addr:housenumber":"7a",
    "addr:postcode":"ws7 0hq",
    "addr:street":"Lichfield Road",
    "iso:country":"GB",
    "sg:address":"7a Lichfield Road",
    "sg:city":"Burntwood",
    "sg:classifiers":[
        {
            "category":"Shopping",
            "subcategory":"Clothing, Apparel, & Fashions",
            "type":"Retail Goods"
        }
    ],
    "sg:phone":"+44 1543 684633",
    "sg:postcode":"WS7 0HQ",
    "sg:province":"Staffordshire",
    "sg:tags":[
        "haberdasher"
    ],
    "wof:name":"S & V Darlington",
    "wof:placetype":"venue"
},
  "geometry": {"coordinates":[-1.9062980413,52.6779823303],"type":"Point"}
}