{
  "type": "Feature",
  "properties": {
    "addr:full":"109 Bath Road Hounslow Greater London TW3 3BT",
    "addr:housenumber":"109",
    "addr:postcode":"tw3 3bt",
    "addr:street":"Bath Road",
    "iso:country":"GB",
    "sg:address":"109 Bath Road",
    "sg:city":"Hounslow",
    "sg:classifiers":[
        {
            "category":"Manufacturing",
            "subcategory":"Tools & Machinery",
            "type":"Manufacturing & Wholesale Goods"
        },
        {
            "category":"Real Estate",
            "subcategory":"Real Estate Operator",
            "type":"Services"
        }
    ],
    "sg:phone":"+44 20 8572 1493",
    "sg:postcode":"TW3 3BT",
    "sg:province":"Greater London",
    "sg:tags":[
        "letting",
        "society",
        "friendly",
        "agent"
    ],
    "wof:name":"Din Dyal Verma",
    "wof:placetype":"venue"
},
  "geometry": {"coordinates":[-0.372825,51.469013],"type":"Point"}
}