{
  "type": "Feature",
  "properties": {
    "iso:country":"GB",
    "sg:address":"Bourne Hill",
    "sg:city":"Ipswich",
    "sg:classifiers":[
        {
            "category":"Wholesale",
            "subcategory":"Sporting Goods",
            "type":"Manufacturing & Wholesale Goods"
        }
    ],
    "sg:postcode":"IP2 8ND",
    "sg:province":"Suffolk",
    "sg:tags":[
        "mnfr",
        "sport",
        "equipment"
    ],
    "wof:name":"Golf Direct (East Anglia) Ltd.",
    "wof:placetype":"venue"
},
  "geometry": {"coordinates":[1.149569,52.03215],"type":"Point"}
}