{
  "type": "Feature",
  "properties": {
    "iso:country":"GB",
    "sg:address":"13 Marriott Clo, City Trading Est",
    "sg:city":"Norwich",
    "sg:classifiers":[
        {
            "category":"Deli",
            "type":"Food & Drink"
        }
    ],
    "sg:phone":"+44 1603 633267",
    "sg:postcode":"NR2 4UX",
    "sg:province":"Norfolk",
    "sg:tags":[
        "delicatessen"
    ],
    "wof:name":"Eleys Delicatessen Foods-Distributors",
    "wof:placetype":"venue"
},
  "geometry": {"coordinates":[1.28391,52.636887],"type":"Point"}
}