{
  "type": "Feature",
  "properties": {
    "addr:full":"12 Brick Lane London Greater London E1 6RF",
    "addr:housenumber":"12",
    "addr:postcode":"e1 6rf",
    "addr:street":"Brick Lane",
    "iso:country":"GB",
    "sg:address":"12 Brick Lane",
    "sg:city":"London",
    "sg:classifiers":[
        {
            "category":"Restaurant",
            "type":"Food & Drink"
        }
    ],
    "sg:phone":"+44 20 7377 8405",
    "sg:postcode":"E1 6RF",
    "sg:province":"Greater London",
    "sg:tags":[
        "indian",
        "-"
    ],
    "wof:name":"Bengal Cuisine",
    "wof:placetype":"venue"
},
  "geometry": {"coordinates":[-0.0707750022,51.5178337097],"type":"Point"}
}