{
  "type": "Feature",
  "properties": {
    "addr:full":"5 West Close March Cambridgeshire PE15 8EW",
    "addr:housenumber":"5",
    "addr:postcode":"pe15 8ew",
    "addr:street":"West Close",
    "iso:country":"GB",
    "sg:address":"5 West Close",
    "sg:city":"March",
    "sg:classifiers":[
        {
            "category":"Retail",
            "subcategory":"Storage",
            "type":"Services"
        }
    ],
    "sg:phone":"+44 1354 660600",
    "sg:postcode":"PE15 8EW",
    "sg:province":"Cambridgeshire",
    "sg:tags":[
        "household",
        "removal"
    ],
    "wof:name":"Cannons Removals",
    "wof:placetype":"venue"
},
  "geometry": {"coordinates":[0.073324,52.559032],"type":"Point"}
}