{
  "type": "Feature",
  "properties": {
    "addr:full":"11 Garden Court, Tewin Road Welwyn Garden City Hertfordshire AL7 1BH",
    "addr:housenumber":"11",
    "addr:postcode":"al7 1bh",
    "addr:street":"Garden Court Tewin Road",
    "iso:country":"GB",
    "sg:address":"11 Garden Court, Tewin Road",
    "sg:city":"Welwyn Garden City",
    "sg:classifiers":[
        {
            "category":"Professional",
            "subcategory":"Art Services",
            "type":"Services"
        }
    ],
    "sg:phone":"+44 1707 393120",
    "sg:postcode":"AL7 1BH",
    "sg:province":"Hertfordshire",
    "sg:tags":[
        "graphic",
        "designer"
    ],
    "wof:name":"Curtis Design Ltd.",
    "wof:placetype":"venue"
},
  "geometry": {"coordinates":[-0.1954929978,51.8016471863],"type":"Point"}
}