{
  "type": "Feature",
  "properties": {
    "addr:full":"23/2 Edina Place Edinburgh City of Edinburgh EH7 5RN",
    "addr:housenumber":"23 / 2",
    "addr:postcode":"eh7 5rn",
    "addr:street":"Edina Place Edinburgh",
    "iso:country":"GB",
    "sg:address":"23/2 Edina Place",
    "sg:city":"Edinburgh",
    "sg:classifiers":[
        {
            "category":"Utilities",
            "type":"Services"
        }
    ],
    "sg:postcode":"EH7 5RN",
    "sg:province":"City of Edinburgh",
    "sg:tags":[
        "internet"
    ],
    "wof:name":"Headroom Communications",
    "wof:placetype":"venue"
},
  "geometry": {"coordinates":[-3.170054,55.959312],"type":"Point"}
}