{
  "type": "Feature",
  "properties": {
    "addr:full":"51 Squirrel Lane High Wycombe Buckinghamshire HP12 4RY",
    "addr:housenumber":"51",
    "addr:postcode":"hp12 4ry",
    "addr:street":"Squirrel Lane",
    "iso:country":"GB",
    "sg:address":"51 Squirrel Lane",
    "sg:city":"High Wycombe",
    "sg:classifiers":[
        {
            "category":"Building & Trades",
            "subcategory":"Plumbing",
            "type":"Services"
        }
    ],
    "sg:phone":"+44 1494 443268",
    "sg:postcode":"HP12 4RY",
    "sg:province":"Buckinghamshire",
    "sg:tags":[
        "plumber",
        "heating"
    ],
    "wof:name":"Chris Judd",
    "wof:placetype":"venue"
},
  "geometry": {"coordinates":[-0.7888529897,51.6202850342],"type":"Point"}
}