{
  "type": "Feature",
  "properties": {
    "addr:full":"Capella House, Todmorden Road, Sharneyford Bacup Lancashire OL13 9UX",
    "addr:postcode":"ol13 9ux",
    "addr:street":"Todmorden Road Sharneyford Bacup",
    "iso:country":"GB",
    "sg:address":"Capella House, Todmorden Road, Sharneyford",
    "sg:city":"Bacup",
    "sg:classifiers":[
        {
            "category":"Building & Trades",
            "subcategory":"Construction",
            "type":"Services"
        }
    ],
    "sg:phone":"+44 1706 879487",
    "sg:postcode":"OL13 9UX",
    "sg:province":"Lancashire",
    "sg:tags":[
        "builder"
    ],
    "wof:name":"Geoff Smith Joiners",
    "wof:placetype":"venue"
},
  "geometry": {"coordinates":[-2.1887741089,53.7078704834],"type":"Point"}
}