{
  "type": "Feature",
  "properties": {
    "iso:country":"GB",
    "sg:address":"101 Desswood Pl",
    "sg:city":"Aberdeen",
    "sg:classifiers":[
        {
            "category":"Home & Garden",
            "subcategory":"Household Appliances",
            "type":"Retail Goods"
        }
    ],
    "sg:phone":"+44 1224 649393",
    "sg:postcode":"AB15 4DP",
    "sg:province":"Aberdeen City",
    "sg:tags":[
        "domestic",
        "oven",
        "microwave"
    ],
    "wof:name":"Kwik Kook",
    "wof:placetype":"venue"
},
  "geometry": {"coordinates":[-2.1313800812,57.1446609497],"type":"Point"}
}