{
  "type": "Feature",
  "properties": {
    "addr:full":"1b Ringslade Road, Wood Green London Greater London N22 7TE",
    "addr:housenumber":"1b",
    "addr:postcode":"n22 7te",
    "addr:street":"Ringslade Road",
    "iso:country":"GB",
    "sg:address":"1b Ringslade Road, Wood Green",
    "sg:city":"London",
    "sg:classifiers":[
        {
            "category":"Health Services",
            "subcategory":"Nursing And Care Facility",
            "type":"Services"
        }
    ],
    "sg:phone":"+44 1708 763331",
    "sg:postcode":"N22 7TE",
    "sg:province":"Greater London",
    "sg:tags":[
        "home"
    ],
    "wof:name":"Bupa Nursing",
    "wof:placetype":"venue"
},
  "geometry": {"coordinates":[-0.11357,51.597599],"type":"Point"}
}