{
  "type": "Feature",
  "properties": {
    "iso:country":"GB",
    "sg:address":"10 Rusland Circus, Emerson Valley",
    "sg:city":"Milton Keynes",
    "sg:classifiers":[
        {
            "category":"Building & Trades",
            "subcategory":"Construction",
            "type":"Services"
        }
    ],
    "sg:postcode":"MK4 2LH",
    "sg:province":"Buckinghamshire",
    "sg:tags":[
        "decorator",
        "painter"
    ],
    "wof:name":"D & K Decor Ltd.",
    "wof:placetype":"venue"
},
  "geometry": {"coordinates":[-0.77848,52.005909],"type":"Point"}
}