{
  "type": "Feature",
  "properties": {
    "iso:country":"GB",
    "sg:address":"489 High Rd",
    "sg:city":"Wembley",
    "sg:classifiers":[
        {
            "category":"Professional",
            "subcategory":"Art Services",
            "type":"Services"
        }
    ],
    "sg:phone":"+44 20 8900 1388",
    "sg:postcode":"HA9 7AG",
    "sg:province":"Greater London",
    "sg:tags":[
        "framing"
    ],
    "wof:name":"Sunbeam Management Ltd",
    "wof:placetype":"venue"
},
  "geometry": {"coordinates":[-0.2961679995,51.5525665283],"type":"Point"}
}