{
  "type": "Feature",
  "properties": {
    "addr:full":"44 Churchgate Loughborough Leicestershire LE11 1UE",
    "addr:housenumber":"44",
    "addr:postcode":"le11 1ue",
    "addr:street":"Churchgate",
    "iso:country":"GB",
    "sg:address":"44 Churchgate",
    "sg:city":"Loughborough",
    "sg:classifiers":[
        {
            "category":"Professional",
            "subcategory":"Lawyer & Legal Services",
            "type":"Services"
        }
    ],
    "sg:phone":"+44 1509 611061",
    "sg:postcode":"LE11 1UE",
    "sg:province":"Leicestershire",
    "sg:tags":[
        "solicitor"
    ],
    "wof:name":"Thomas Solicitors",
    "wof:placetype":"venue"
},
  "geometry": {"coordinates":[-1.2053339481,52.7732658386],"type":"Point"}
}