{
  "type": "Feature",
  "properties": {
    "addr:full":"9 Boyces Avenue Bristol City of Bristol BS8 4AA",
    "addr:housenumber":"9",
    "addr:postcode":"bs8 4aa",
    "addr:street":"Boyces Avenue",
    "iso:country":"GB",
    "sg:address":"9 Boyces Avenue",
    "sg:city":"Bristol",
    "sg:classifiers":[
        {
            "category":"Fast Food",
            "type":"Food & Drink"
        }
    ],
    "sg:phone":"+44 117 974 4125",
    "sg:postcode":"BS8 4AA",
    "sg:province":"City of Bristol",
    "sg:tags":[
        "away",
        "take"
    ],
    "wof:name":"Full Stop Sandwich Co (Thw)",
    "wof:placetype":"venue"
},
  "geometry": {"coordinates":[-2.618065,51.455254],"type":"Point"}
}