{
  "type": "Feature",
  "properties": {
    "iso:country":"GB",
    "sg:address":"60 Bishopton Lane",
    "sg:city":"Stockton-on-tees",
    "sg:classifiers":[
        {
            "category":"Personal",
            "subcategory":"Beauty Salon",
            "type":"Services"
        }
    ],
    "sg:postcode":"TS18 2AJ",
    "sg:province":"Durham",
    "sg:tags":[
        "unisex",
        "hairdresser"
    ],
    "wof:name":"Hair Trax",
    "wof:placetype":"venue"
},
  "geometry": {"coordinates":[-1.316719,54.568371],"type":"Point"}
}