{
  "type": "Feature",
  "properties": {
    "addr:full":"Green Street County First School, Green St High Wycombe Buckinghamshire HP11 2RA",
    "addr:postcode":"hp11 2ra",
    "addr:street":"Green Street;Green St",
    "iso:country":"GB",
    "sg:address":"Green Street County First School, Green St",
    "sg:city":"High Wycombe",
    "sg:classifiers":[
        {
            "category":"Education",
            "subcategory":"Special Training",
            "type":"Public Place"
        }
    ],
    "sg:phone":"+44 1494 473141",
    "sg:postcode":"HP11 2RA",
    "sg:province":"Buckinghamshire",
    "sg:tags":[
        "product",
        "centre"
    ],
    "wof:name":"Special Needs I T Resource Base",
    "wof:placetype":"venue"
},
  "geometry": {"coordinates":[-0.7670289874,51.6328811646],"type":"Point"}
}