{
  "type": "Feature",
  "properties": {
    "addr:full":"8 Hafan Y Don, Killay Swansea Swansea SA2 7NT",
    "addr:housenumber":"8",
    "addr:postcode":"sa2 7nt",
    "addr:street":"Hafan Y Don",
    "iso:country":"GB",
    "sg:address":"8 Hafan Y Don, Killay",
    "sg:city":"Swansea",
    "sg:classifiers":[
        {
            "category":"Banks & Credit Unions",
            "subcategory":"Financial Services",
            "type":"Services"
        }
    ],
    "sg:phone":"+44 1792 299422",
    "sg:postcode":"SA2 7NT",
    "sg:province":"Swansea",
    "sg:tags":[
        "consultant"
    ],
    "wof:name":"Pm Leasing & Finance",
    "wof:placetype":"venue"
},
  "geometry": {"coordinates":[-4.0182089806,51.6240272522],"type":"Point"}
}