{
  "type": "Feature",
  "properties": {
    "addr:full":"15 Cedar Rd Brentwood Essex CM13 1NB",
    "addr:housenumber":"15",
    "addr:postcode":"cm13 1nb",
    "addr:street":"Cedar Rd",
    "iso:country":"GB",
    "sg:address":"15 Cedar Rd",
    "sg:city":"Brentwood",
    "sg:classifiers":[
        {
            "category":"Building & Trades",
            "subcategory":"Construction",
            "type":"Services"
        }
    ],
    "sg:phone":"+44 1277 234056",
    "sg:postcode":"CM13 1NB",
    "sg:province":"Essex",
    "sg:tags":[
        "roofing"
    ],
    "wof:name":"P Bridle",
    "wof:placetype":"venue"
},
  "geometry": {"coordinates":[0.3517209888,51.6320381165],"type":"Point"}
}