{
  "type": "Feature",
  "properties": {
    "iso:country":"GB",
    "sg:address":"31 Northwood Drive",
    "sg:city":"Newbury",
    "sg:classifiers":[
        {
            "category":"Retail",
            "subcategory":"Driving School",
            "type":"Services"
        }
    ],
    "sg:postcode":"RG14 2HB",
    "sg:province":"Berkshire",
    "wof:name":"Jill's School of Motoring",
    "wof:placetype":"venue"
},
  "geometry": {"coordinates":[-1.3082200289,51.4087333679],"type":"Point"}
}