{
  "type": "Feature",
  "properties": {
    "addr:full":"3 Falcondale Rd Warrington Cheshire WA2 8NB",
    "addr:housenumber":"3",
    "addr:postcode":"wa2 8nb",
    "addr:street":"Falcondale Rd",
    "iso:country":"GB",
    "sg:address":"3 Falcondale Rd",
    "sg:city":"Warrington",
    "sg:classifiers":[
        {
            "category":"Professional",
            "type":"Services"
        }
    ],
    "sg:phone":"+44 1925 659797",
    "sg:postcode":"WA2 8NB",
    "sg:province":"Cheshire",
    "sg:tags":[
        "entertainer"
    ],
    "wof:name":"Colourful Magic By Raymond Chard",
    "wof:placetype":"venue"
},
  "geometry": {"coordinates":[-2.588644,53.431461],"type":"Point"}
}