{
  "type": "Feature",
  "properties": {
    "addr:full":"27 High Street, Keynsham Bristol City of Bristol BS31 1DP",
    "addr:housenumber":"27",
    "addr:postcode":"bs31 1dp",
    "addr:street":"High Street",
    "iso:country":"GB",
    "sg:address":"27 High Street, Keynsham",
    "sg:city":"Bristol",
    "sg:classifiers":[
        {
            "category":"Shopping",
            "subcategory":"Clothing, Apparel, & Fashions",
            "type":"Retail Goods"
        },
        {
            "category":"Building & Trades",
            "subcategory":"Cleaning & Sanitation",
            "type":"Services"
        },
        {
            "category":"Shopping",
            "subcategory":"Comic Books",
            "type":"Retail Goods"
        }
    ],
    "sg:phone":"+44 117 986 7315",
    "sg:postcode":"BS31 1DP",
    "sg:province":"City of Bristol",
    "sg:tags":[
        "clothing",
        "jeweller",
        "commercial",
        "fabric"
    ],
    "wof:name":"Reflections",
    "wof:placetype":"venue"
},
  "geometry": {"coordinates":[-2.498636,51.416534],"type":"Point"}
}