{
  "type": "Feature",
  "properties": {
    "iso:country":"GB",
    "sg:address":"147 Upper Tooting Rd",
    "sg:city":"Tooting",
    "sg:classifiers":[
        {
            "category":"Autos & Motor Vehicles",
            "subcategory":"Automobile Sales",
            "type":"Retail Goods"
        }
    ],
    "sg:phone":"+44 20 8672 9999",
    "sg:postcode":"SW17 7TJ",
    "sg:province":"Greater London",
    "sg:tags":[
        "commercial"
    ],
    "wof:name":"Sirline",
    "wof:placetype":"venue"
},
  "geometry": {"coordinates":[-0.163784,51.432079],"type":"Point"}
}