{
  "type": "Feature",
  "properties": {
    "iso:country":"GB",
    "sg:address":"10 Thorn View",
    "sg:city":"Bury",
    "sg:classifiers":[
        {
            "category":"Building & Trades",
            "subcategory":"Construction",
            "type":"Services"
        }
    ],
    "sg:postcode":"BL9 7NW",
    "sg:province":"Lancashire",
    "sg:tags":[
        "decorator",
        "painter"
    ],
    "wof:name":"S & J Decorators",
    "wof:placetype":"venue"
},
  "geometry": {"coordinates":[-2.2676079273,53.5983581543],"type":"Point"}
}