{
  "type": "Feature",
  "properties": {
    "addr:full":"30 Kingsacre Road, Kings Park Glasgow East Renfrewshire G44 4LP",
    "addr:housenumber":"30",
    "addr:postcode":"g44 4lp",
    "addr:street":"Kingsacre Road",
    "iso:country":"GB",
    "sg:address":"30 Kingsacre Road, Kings Park",
    "sg:city":"Glasgow",
    "sg:classifiers":[
        {
            "category":"Professional",
            "subcategory":"Engineering",
            "type":"Services"
        },
        {
            "category":"Building & Trades",
            "subcategory":"Electrical",
            "type":"Services"
        }
    ],
    "sg:phone":"+44 141 632 0101",
    "sg:postcode":"G44 4LP",
    "sg:province":"East Renfrewshire",
    "sg:tags":[
        "engineer",
        "electrician",
        "contractor"
    ],
    "wof:name":"A10 Telecom Ltd",
    "wof:placetype":"venue"
},
  "geometry": {"coordinates":[-4.244572,55.822388],"type":"Point"}
}