{
  "type": "Feature",
  "properties": {
    "addr:full":"24 Hudson Street Whitby North Yorkshire YO21 3EP",
    "addr:housenumber":"24",
    "addr:postcode":"yo21 3ep",
    "addr:street":"Hudson Street",
    "iso:country":"GB",
    "sg:address":"24 Hudson Street",
    "sg:city":"Whitby",
    "sg:classifiers":[
        {
            "category":"Social Services",
            "subcategory":"Retirement Home",
            "type":"Services"
        }
    ],
    "sg:phone":"+44 1947 605277",
    "sg:postcode":"YO21 3EP",
    "sg:province":"North Yorkshire",
    "sg:tags":[
        "residential",
        "care"
    ],
    "wof:name":"J W & S Tappenden",
    "wof:placetype":"venue"
},
  "geometry": {"coordinates":[-0.617369,54.489044],"type":"Point"}
}