{
  "type": "Feature",
  "properties": {
    "iso:country":"GB",
    "sg:address":"Southampton Parkside, Queens Keep",
    "sg:city":"Southampton",
    "sg:classifiers":[
        {
            "category":"Government",
            "subcategory":"Office",
            "type":"Public Place"
        }
    ],
    "sg:phone":"+44 23 8020 4000",
    "sg:postcode":"SO15 2UN",
    "sg:province":"Hampshire",
    "sg:tags":[
        "inland",
        "revenue"
    ],
    "wof:name":"Inland Revenue",
    "wof:placetype":"venue"
},
  "geometry": {"coordinates":[-1.4073189497,50.9099388123],"type":"Point"}
}