{
  "type": "Feature",
  "properties": {
    "iso:country":"GB",
    "sg:address":"Westwood Lane, Normandy",
    "sg:city":"Guildford",
    "sg:classifiers":[
        {
            "category":"Shopping",
            "subcategory":"Department Store",
            "type":"Retail Goods"
        },
        {
            "category":"Food & Beverages",
            "subcategory":"Supermarket",
            "type":"Retail Goods"
        }
    ],
    "sg:phone":"+44 1483 811177",
    "sg:postcode":"GU3 2JJ",
    "sg:province":"Surrey",
    "wof:name":"Westwood Stores",
    "wof:placetype":"venue"
},
  "geometry": {"coordinates":[-0.666989,51.256756],"type":"Point"}
}