{
  "type": "Feature",
  "properties": {
    "addr:full":"Unit H, St Martins Industrial Estate, Nickel Close Winchester Hampshire SO23 7RJ",
    "addr:housenumber":"estate",
    "addr:postcode":"so23 7rj",
    "addr:street":"H;Nickel Close",
    "iso:country":"GB",
    "sg:address":"Unit H, St Martins Industrial Estate, Nickel Close",
    "sg:city":"Winchester",
    "sg:classifiers":[
        {
            "category":"Autos & Motor Vehicles",
            "subcategory":"Auto Supplies",
            "type":"Retail Goods"
        }
    ],
    "sg:phone":"+44 1962 844362",
    "sg:postcode":"SO23 7RJ",
    "sg:province":"Hampshire",
    "sg:tags":[
        "tyre"
    ],
    "wof:name":"J T Realisation Ltd.",
    "wof:placetype":"venue"
},
  "geometry": {"coordinates":[-1.3168090582,51.0630683899],"type":"Point"}
}