{
  "type": "Feature",
  "properties": {
    "addr:full":"5-9 Electric Avenue Brixton Greater London SW9 8JY",
    "addr:housenumber":"5-9",
    "addr:postcode":"sw9 8jy",
    "addr:street":"Electric Avenue",
    "iso:country":"GB",
    "sg:address":"5-9 Electric Avenue",
    "sg:city":"Brixton",
    "sg:classifiers":[
        {
            "category":"Food & Beverages",
            "subcategory":"Groceries & Convenience Stores",
            "type":"Retail Goods"
        },
        {
            "category":"Food & Beverages",
            "subcategory":"Meat & Fish",
            "type":"Retail Goods"
        }
    ],
    "sg:phone":"+44 20 7924 0568",
    "sg:postcode":"SW9 8JY",
    "sg:province":"Greater London",
    "sg:tags":[
        "butcher"
    ],
    "wof:name":"Brixton Foods",
    "wof:placetype":"venue"
},
  "geometry": {"coordinates":[-0.1146399975,51.462097168],"type":"Point"}
}