{
  "type": "Feature",
  "properties": {
    "iso:country":"GB",
    "sg:address":"Holme Road",
    "sg:city":"Burnley",
    "sg:classifiers":[
        {
            "category":"Farming",
            "subcategory":"Livestock Farm",
            "type":"Manufacturing & Wholesale Goods"
        }
    ],
    "sg:phone":"+44 1282 455435",
    "sg:postcode":"BB12 0RT",
    "sg:province":"Lancashire",
    "sg:tags":[
        "others"
    ],
    "wof:name":"P COATES FARMERS",
    "wof:placetype":"venue"
},
  "geometry": {"coordinates":[-2.2497439384,53.7957191467],"type":"Point"}
}