{
  "type": "Feature",
  "properties": {
    "iso:country":"GB",
    "sg:address":"61 Chapel Market",
    "sg:city":"London",
    "sg:classifiers":[
        {
            "category":"Food & Beverages",
            "subcategory":"Bakery",
            "type":"Retail Goods"
        }
    ],
    "sg:phone":"+44 20 7713 5192",
    "sg:postcode":"N1 9ER",
    "sg:province":"Greater London",
    "sg:tags":[
        "baker"
    ],
    "wof:name":"Sti Bakery",
    "wof:placetype":"venue"
},
  "geometry": {"coordinates":[-0.1082250029,51.5334968567],"type":"Point"}
}