{
  "type": "Feature",
  "properties": {
    "addr:full":"College House, 73 Breck Road Poulton-le-fylde Lancashire FY6 7AQ",
    "addr:housenumber":"73",
    "addr:postcode":"fy6 7aq",
    "addr:street":"Breck Road Poulton-Le-Fylde",
    "iso:country":"GB",
    "sg:address":"College House, 73 Breck Road",
    "sg:city":"Poulton-le-fylde",
    "sg:classifiers":[
        {
            "category":"Community Center",
            "subcategory":"Youth",
            "type":"Public Place"
        }
    ],
    "sg:phone":"+44 1253 893102",
    "sg:postcode":"FY6 7AQ",
    "sg:province":"Lancashire",
    "sg:tags":[
        "organisation",
        "centre"
    ],
    "wof:name":"Wyre District Youth & Community Service",
    "wof:placetype":"venue"
},
  "geometry": {"coordinates":[-2.98964,53.850258],"type":"Point"}
}