{
  "type": "Feature",
  "properties": {
    "iso:country":"GB",
    "sg:address":"34 Great Horton Road",
    "sg:city":"Bradford",
    "sg:classifiers":[
        {
            "category":"Restaurant",
            "type":"Food & Drink"
        }
    ],
    "sg:phone":"+44 1274 722834",
    "sg:postcode":"BD7 1AL",
    "sg:province":"West Yorkshire",
    "sg:tags":[
        "greek"
    ],
    "wof:name":"Kierna Restaurant & Grill",
    "wof:placetype":"venue"
},
  "geometry": {"coordinates":[-1.7589,53.791527],"type":"Point"}
}