{
  "type": "Feature",
  "properties": {
    "addr:full":"19-21 Pierson St Redcar North Yorkshire TS10 1SL",
    "addr:housenumber":"19-21",
    "addr:postcode":"ts10 1sl",
    "addr:street":"Pierson St",
    "iso:country":"GB",
    "sg:address":"19-21 Pierson St",
    "sg:city":"Redcar",
    "sg:classifiers":[
        {
            "category":"Farming",
            "subcategory":"Dairy Farm",
            "type":"Manufacturing & Wholesale Goods"
        }
    ],
    "sg:postcode":"TS10 1SL",
    "sg:province":"North Yorkshire",
    "wof:name":"Fox's Dairies",
    "wof:placetype":"venue"
},
  "geometry": {"coordinates":[-1.0738489628,54.6180763245],"type":"Point"}
}