{
  "type": "Feature",
  "properties": {
    "addr:full":"17 Queen Street, Woodman Road Brentwood Essex CM14 5JZ",
    "addr:housenumber":"17",
    "addr:postcode":"cm14 5jz",
    "addr:street":"Queen Street Woodman Road",
    "iso:country":"GB",
    "sg:address":"17 Queen Street, Woodman Road",
    "sg:city":"Brentwood",
    "sg:classifiers":[
        {
            "category":"Professional",
            "subcategory":"Computer Services",
            "type":"Services"
        }
    ],
    "sg:phone":"+44 1277 263943",
    "sg:postcode":"CM14 5JZ",
    "sg:province":"Essex",
    "sg:tags":[
        "system",
        "software"
    ],
    "wof:name":"Cassiopeia Ltd",
    "wof:placetype":"venue"
},
  "geometry": {"coordinates":[0.299745,51.607231],"type":"Point"}
}