{
  "type": "Feature",
  "properties": {
    "iso:country":"GB",
    "sg:address":"2ns Flr, Standard House, Half Moor Street",
    "sg:city":"Huddersfield",
    "sg:classifiers":[
        {
            "category":"Banks & Credit Unions",
            "subcategory":"Financial Services",
            "type":"Services"
        }
    ],
    "sg:phone":"+44 1484 224800",
    "sg:postcode":"HD1 2JF",
    "sg:province":"West Yorkshire",
    "sg:tags":[
        "consultant"
    ],
    "wof:name":"Allied Dunbar Assurance Plc",
    "wof:placetype":"venue"
},
  "geometry": {"coordinates":[-1.7826839685,53.6469535828],"type":"Point"}
}