{
  "type": "Feature",
  "properties": {
    "iso:country":"GB",
    "sg:address":"228-230 Yorkshire Street",
    "sg:city":"Rochdale",
    "sg:classifiers":[
        {
            "category":"Wholesale",
            "subcategory":"Non-durable Goods",
            "type":"Manufacturing & Wholesale Goods"
        }
    ],
    "sg:phone":"+44 1706 659990",
    "sg:postcode":"OL16 2DP",
    "sg:province":"Lancashire",
    "sg:tags":[
        "carry",
        "cash"
    ],
    "wof:name":"Watan Cash & Carry",
    "wof:placetype":"venue"
},
  "geometry": {"coordinates":[-2.150917,53.621124],"type":"Point"}
}