{
  "type": "Feature",
  "properties": {
    "addr:full":"29 Park Road Barry The Vale of Glamorgan CF62 6NX",
    "addr:housenumber":"29",
    "addr:postcode":"cf62 6nx",
    "addr:street":"Park Road;Vale",
    "iso:country":"GB",
    "sg:address":"29 Park Road",
    "sg:city":"Barry",
    "sg:classifiers":[
        {
            "category":"Shopping",
            "subcategory":"Crafts & Fabrics",
            "type":"Retail Goods"
        }
    ],
    "sg:phone":"+44 1446 749839",
    "sg:postcode":"CF62 6NX",
    "sg:province":"The Vale of Glamorgan",
    "sg:tags":[
        "shop",
        "needlecraft",
        "wool"
    ],
    "wof:name":"J Merryfield",
    "wof:placetype":"venue"
},
  "geometry": {"coordinates":[-3.295124054,51.3968544006],"type":"Point"}
}