{
  "type": "Feature",
  "properties": {
    "addr:full":"27 Riddings Road Ilkley North Yorkshire LS29 9LX",
    "addr:housenumber":"27",
    "addr:postcode":"ls29 9lx",
    "addr:street":"Riddings Road",
    "iso:country":"GB",
    "sg:address":"27 Riddings Road",
    "sg:city":"Ilkley",
    "sg:classifiers":[
        {
            "category":"Professional",
            "subcategory":"Lawyer & Legal Services",
            "type":"Services"
        }
    ],
    "sg:phone":"+44 1943 609969",
    "sg:postcode":"LS29 9LX",
    "sg:province":"North Yorkshire",
    "sg:tags":[
        "solicitor"
    ],
    "wof:name":"Kennedy Thompson & Davies",
    "wof:placetype":"venue"
},
  "geometry": {"coordinates":[-1.824259,53.92416],"type":"Point"}
}