{
  "type": "Feature",
  "properties": {
    "iso:country":"GB",
    "sg:address":"65a Cricklade Street",
    "sg:city":"Cirencester",
    "sg:classifiers":[
        {
            "category":"Travel",
            "subcategory":"Travel Agent",
            "type":"Entertainment"
        }
    ],
    "sg:phone":"+44 1285 659611",
    "sg:postcode":"GL7 1HY",
    "sg:province":"Gloucestershire",
    "wof:name":"Agentmust Ltd.",
    "wof:placetype":"venue"
},
  "geometry": {"coordinates":[-1.967235,51.715694],"type":"Point"}
}