{
  "type": "Feature",
  "properties": {
    "addr:full":"3 Hertford Close Leeds West Yorkshire LS15 9ER",
    "addr:housenumber":"3",
    "addr:postcode":"ls15 9er",
    "addr:street":"Hertford Close",
    "iso:country":"GB",
    "sg:address":"3 Hertford Close",
    "sg:city":"Leeds",
    "sg:classifiers":[
        {
            "category":"Home & Garden",
            "subcategory":"Household Appliances",
            "type":"Retail Goods"
        }
    ],
    "sg:phone":"+44 7785 760302",
    "sg:postcode":"LS15 9ER",
    "sg:province":"West Yorkshire",
    "sg:tags":[
        "electrical"
    ],
    "wof:name":"Appliance Repairs & Testing",
    "wof:placetype":"venue"
},
  "geometry": {"coordinates":[-1.446437,53.791302],"type":"Point"}
}