{
  "type": "Feature",
  "properties": {
    "addr:full":"Ickenham Rd Ruislip Greater London HA4 7BT",
    "addr:postcode":"ha4 7bt",
    "addr:street":"Ickenham Rd",
    "iso:country":"GB",
    "sg:address":"Ickenham Rd",
    "sg:city":"Ruislip",
    "sg:classifiers":[
        {
            "category":"Place Of Worship",
            "type":"Public Place"
        }
    ],
    "sg:phone":"+44 1895 632507",
    "sg:postcode":"HA4 7BT",
    "sg:province":"Greater London",
    "wof:name":"Methodist Church",
    "wof:placetype":"venue"
},
  "geometry": {"coordinates":[-0.425458,51.574169],"type":"Point"}
}