{
  "type": "Feature",
  "properties": {
    "iso:country":"GB",
    "sg:address":"14 Water Lane, Middlestown",
    "sg:city":"Wakefield",
    "sg:classifiers":[
        {
            "category":"Building & Trades",
            "subcategory":"Construction",
            "type":"Services"
        }
    ],
    "sg:phone":"+44 1924 275106",
    "sg:postcode":"WF4 4PX",
    "sg:province":"West Yorkshire",
    "sg:tags":[
        "decorator",
        "painter"
    ],
    "wof:name":"Plumtel Ltd",
    "wof:placetype":"venue"
},
  "geometry": {"coordinates":[-1.580619,53.655304],"type":"Point"}
}