{
  "type": "Feature",
  "properties": {
    "iso:country":"GB",
    "sg:address":"155a High St",
    "sg:city":"Poole",
    "sg:classifiers":[
        {
            "category":"Home & Garden",
            "subcategory":"Hardware",
            "type":"Retail Goods"
        },
        {
            "category":"Food & Beverages",
            "subcategory":"Supermarket",
            "type":"Retail Goods"
        }
    ],
    "sg:postcode":"BH15 1AU",
    "sg:province":"Dorset",
    "wof:name":"Cost Cutters",
    "wof:placetype":"venue"
},
  "geometry": {"coordinates":[-1.982819,50.716549],"type":"Point"}
}