{
  "type": "Feature",
  "properties": {
    "addr:full":"3a Archway Close London Greater London N19 3TD",
    "addr:housenumber":"3a",
    "addr:postcode":"n19 3td",
    "addr:street":"Archway Close",
    "iso:country":"GB",
    "sg:address":"3a Archway Close",
    "sg:city":"London",
    "sg:classifiers":[
        {
            "category":"Taxi",
            "type":"Transportation"
        }
    ],
    "sg:phone":"+44 20 7272 2222",
    "sg:postcode":"N19 3TD",
    "sg:province":"Greater London",
    "sg:tags":[
        "mini",
        "cab"
    ],
    "wof:name":"North London Flyers",
    "wof:placetype":"venue"
},
  "geometry": {"coordinates":[-0.1343290061,51.565776825],"type":"Point"}
}