{
  "type": "Feature",
  "properties": {
    "addr:full":"Tilsworth Road, Stanbridge Leighton Buzzard Bedfordshire LU7 9HY",
    "addr:postcode":"lu7 9hy",
    "addr:street":"Tilsworth Road",
    "iso:country":"GB",
    "sg:address":"Tilsworth Road, Stanbridge",
    "sg:city":"Leighton Buzzard",
    "sg:classifiers":[
        {
            "category":"Education",
            "subcategory":"School",
            "type":"Public Place"
        }
    ],
    "sg:phone":"+44 1525 210328",
    "sg:postcode":"LU7 9HY",
    "sg:province":"Bedfordshire",
    "sg:tags":[
        "local",
        "authority"
    ],
    "wof:name":"Stanbridge Lower School",
    "wof:placetype":"venue"
},
  "geometry": {"coordinates":[-0.596723,51.908657],"type":"Point"}
}