{
  "type": "Feature",
  "properties": {
    "addr:full":"164 Parrock Street Gravesend Kent DA12 1ER",
    "addr:housenumber":"164",
    "addr:postcode":"da12 1er",
    "addr:street":"Parrock Street",
    "iso:country":"GB",
    "sg:address":"164 Parrock Street",
    "sg:city":"Gravesend",
    "sg:classifiers":[
        {
            "category":"Fast Food",
            "type":"Food & Drink"
        }
    ],
    "sg:phone":"+44 1474 569651",
    "sg:postcode":"DA12 1ER",
    "sg:province":"Kent",
    "sg:tags":[
        "away",
        "take"
    ],
    "wof:name":"The Rickshaw",
    "wof:placetype":"venue"
},
  "geometry": {"coordinates":[0.370999,51.440212],"type":"Point"}
}