{
  "type": "Feature",
  "properties": {
    "addr:full":"Within Street Farm, Tetton Lane, Moston Middlewich Cheshire CW10 0HH",
    "addr:postcode":"cw10 0hh",
    "addr:street":"Within Street;Tetton Lane",
    "iso:country":"GB",
    "sg:address":"Within Street Farm, Tetton Lane, Moston",
    "sg:city":"Middlewich",
    "sg:classifiers":[
        {
            "category":"Farming",
            "subcategory":"Livestock Farm",
            "type":"Manufacturing & Wholesale Goods"
        }
    ],
    "sg:phone":"+44 1270 526271",
    "sg:postcode":"CW10 0HH",
    "sg:province":"Cheshire",
    "sg:tags":[
        "others"
    ],
    "wof:name":"E W Webster Ltd.",
    "wof:placetype":"venue"
},
  "geometry": {"coordinates":[-2.42951,53.164871],"type":"Point"}
}