{
  "type": "Feature",
  "properties": {
    "iso:country":"GB",
    "sg:address":"60 Pilgrims Way East",
    "sg:city":"Sevenoaks",
    "sg:classifiers":[
        {
            "category":"Professional",
            "subcategory":"Computer Services",
            "type":"Services"
        }
    ],
    "sg:phone":"+44 1959 522411",
    "sg:postcode":"TN14 5QW",
    "sg:province":"Kent",
    "sg:tags":[
        "system",
        "software"
    ],
    "wof:name":"Computer Database Services",
    "wof:placetype":"venue"
},
  "geometry": {"coordinates":[0.20504,51.312309],"type":"Point"}
}