{
  "type": "Feature",
  "properties": {
    "addr:full":"15 Mandeville Courtyard, 142 Battersea Park Road London Greater London SW11 4NB",
    "addr:housenumber":"15;142",
    "addr:postcode":"sw11 4nb",
    "addr:street":"Mandeville Courtyard;Battersea Park Road",
    "iso:country":"GB",
    "sg:address":"15 Mandeville Courtyard, 142 Battersea Park Road",
    "sg:city":"London",
    "sg:classifiers":[
        {
            "category":"Wholesale",
            "subcategory":"Books, Periodicals, & Newspapers",
            "type":"Manufacturing & Wholesale Goods"
        }
    ],
    "sg:phone":"+44 20 7627 1510",
    "sg:postcode":"SW11 4NB",
    "sg:province":"Greater London",
    "sg:tags":[
        "publishing"
    ],
    "wof:name":"S B Communication Group",
    "wof:placetype":"venue"
},
  "geometry": {"coordinates":[-0.15703,51.474312],"type":"Point"}
}