{
  "type": "Feature",
  "properties": {
    "addr:full":"76 Dukes Avenue, Theydon Bois Epping Essex CM16 7HF",
    "addr:housenumber":"76",
    "addr:postcode":"cm16 7hf",
    "addr:street":"Dukes Avenue",
    "iso:country":"GB",
    "sg:address":"76 Dukes Avenue, Theydon Bois",
    "sg:city":"Epping",
    "sg:classifiers":[
        {
            "category":"Professional",
            "type":"Services"
        },
        {
            "category":"Arts & Performance",
            "subcategory":"Music",
            "type":"Entertainment"
        }
    ],
    "sg:phone":"+44 1992 814677",
    "sg:postcode":"CM16 7HF",
    "sg:province":"Essex",
    "sg:tags":[
        "entertainer",
        "musician",
        "composer"
    ],
    "wof:name":"Artists 2000",
    "wof:placetype":"venue"
},
  "geometry": {"coordinates":[0.1017080024,51.6780700684],"type":"Point"}
}