{
  "type": "Feature",
  "properties": {
    "iso:country":"GB",
    "sg:address":"67 Manor Rd, Keyworth",
    "sg:city":"Nottingham",
    "sg:classifiers":[
        {
            "category":"Building & Trades",
            "subcategory":"Construction",
            "type":"Services"
        }
    ],
    "sg:postcode":"NG12 5HW",
    "sg:province":"Nottinghamshire",
    "sg:tags":[
        "decorator",
        "painter"
    ],
    "wof:name":"Hart,Brian,",
    "wof:placetype":"venue"
},
  "geometry": {"coordinates":[-1.092997,52.875507],"type":"Point"}
}