{
  "type": "Feature",
  "properties": {
    "addr:full":"57 Royal Navy Avenue, Keyham Plymouth Devon PL2 2AG",
    "addr:housenumber":"57",
    "addr:postcode":"pl2 2ag",
    "addr:street":"Royal Navy Avenue",
    "iso:country":"GB",
    "sg:address":"57 Royal Navy Avenue, Keyham",
    "sg:city":"Plymouth",
    "sg:classifiers":[
        {
            "category":"Bus Charters",
            "type":"Transportation"
        }
    ],
    "sg:phone":"+44 1752 568186",
    "sg:postcode":"PL2 2AG",
    "sg:province":"Devon",
    "sg:tags":[
        "hire",
        "coach"
    ],
    "wof:name":"Western Private Hire",
    "wof:placetype":"venue"
},
  "geometry": {"coordinates":[-4.172287941,50.3886184692],"type":"Point"}
}