{
  "type": "Feature",
  "properties": {
    "iso:country":"GB",
    "sg:address":"Ashburnham Road",
    "sg:city":"Bedford",
    "sg:classifiers":[
        {
            "category":"Home & Garden",
            "subcategory":"Hardware",
            "type":"Retail Goods"
        }
    ],
    "sg:phone":"+44 1234 327626",
    "sg:postcode":"MK40 1DX",
    "sg:province":"Bedfordshire",
    "sg:tags":[
        "retailer",
        "diy"
    ],
    "wof:name":"Do It All Ltd.",
    "wof:placetype":"venue"
},
  "geometry": {"coordinates":[-0.4796940088,52.1383056641],"type":"Point"}
}