{
  "type": "Feature",
  "properties": {
    "addr:full":"Tilegate Road Harlow Essex CM18 6LU",
    "addr:postcode":"cm18 6lu",
    "addr:street":"Tilegate Road",
    "iso:country":"GB",
    "sg:address":"Tilegate Road",
    "sg:city":"Harlow",
    "sg:classifiers":[
        {
            "category":"Community Center",
            "type":"Public Place"
        }
    ],
    "sg:phone":"+44 1279 866121",
    "sg:postcode":"CM18 6LU",
    "sg:province":"Essex",
    "sg:tags":[
        "centre"
    ],
    "wof:name":"Tye Green Community Centre",
    "wof:placetype":"venue"
},
  "geometry": {"coordinates":[0.1148540005,51.7587814331],"type":"Point"}
}