{
  "type": "Feature",
  "properties": {
    "iso:country":"GB",
    "sg:address":"14a King Street",
    "sg:city":"Thetford",
    "sg:classifiers":[
        {
            "category":"Shopping",
            "subcategory":"Clothing, Apparel, & Fashions",
            "type":"Retail Goods"
        }
    ],
    "sg:phone":"+44 1842 750756",
    "sg:postcode":"IP24 2AP",
    "sg:province":"Norfolk",
    "sg:tags":[
        "shop",
        "lady",
        "fashionwear"
    ],
    "wof:name":"SIZE UP CLOTHING STORES LTD",
    "wof:placetype":"venue"
},
  "geometry": {"coordinates":[0.749732,52.41396],"type":"Point"}
}