{
  "type": "Feature",
  "properties": {
    "addr:full":"28 Holmscroft Road Luton Bedfordshire LU3 2TJ",
    "addr:housenumber":"28",
    "addr:postcode":"lu3 2tj",
    "addr:street":"Holmscroft Road",
    "iso:country":"GB",
    "sg:address":"28 Holmscroft Road",
    "sg:city":"Luton",
    "sg:classifiers":[
        {
            "category":"Building & Trades",
            "subcategory":"Landscaping Services",
            "type":"Services"
        },
        {
            "category":"Real Estate",
            "subcategory":"Real Estate Services",
            "type":"Services"
        }
    ],
    "sg:phone":"+44 1582 494394",
    "sg:postcode":"LU3 2TJ",
    "sg:province":"Bedfordshire",
    "sg:tags":[
        "consultant",
        "plant",
        "leasing",
        "hire",
        "horticultural"
    ],
    "wof:name":"Dennis Diggin",
    "wof:placetype":"venue"
},
  "geometry": {"coordinates":[-0.4494040012,51.9092750549],"type":"Point"}
}