{
  "type": "Feature",
  "properties": {
    "addr:full":"7 St Ann Street Manchester Greater Manchester M2 7LG",
    "addr:housenumber":"7",
    "addr:postcode":"m2 7lg",
    "addr:street":"St Ann Street",
    "iso:country":"GB",
    "sg:address":"7 St Ann Street",
    "sg:city":"Manchester",
    "sg:classifiers":[
        {
            "category":"Shopping",
            "subcategory":"Clothing, Apparel, & Fashions",
            "type":"Retail Goods"
        }
    ],
    "sg:postcode":"M2 7LG",
    "sg:province":"Greater Manchester",
    "sg:tags":[
        "menswear"
    ],
    "wof:name":"Intro Menswear",
    "wof:placetype":"venue"
},
  "geometry": {"coordinates":[-2.246416,53.482037],"type":"Point"}
}