{
  "type": "Feature",
  "properties": {
    "addr:full":"109 Hotspur Street Glasgow Glasgow City G20 8LH",
    "addr:housenumber":"109",
    "addr:postcode":"g20 8lh",
    "addr:street":"Hotspur Street",
    "iso:country":"GB",
    "sg:address":"109 Hotspur Street",
    "sg:city":"Glasgow",
    "sg:classifiers":[
        {
            "category":"Education",
            "subcategory":"School",
            "type":"Public Place"
        }
    ],
    "sg:phone":"+44 141 946 1405",
    "sg:postcode":"G20 8LH",
    "sg:province":"Glasgow City",
    "sg:tags":[
        "local",
        "authority"
    ],
    "wof:name":"Kelbourne School",
    "wof:placetype":"venue"
},
  "geometry": {"coordinates":[-4.286372,55.883812],"type":"Point"}
}