{
  "type": "Feature",
  "properties": {
    "addr:full":"East Ewell Railway Stn, Cheam Rd Epsom Surrey KT17 1QR",
    "addr:postcode":"kt17 1qr",
    "addr:street":"East;Cheam Rd",
    "iso:country":"GB",
    "sg:address":"East Ewell Railway Stn, Cheam Rd",
    "sg:city":"Epsom",
    "sg:classifiers":[
        {
            "category":"Bus Charters",
            "type":"Transportation"
        }
    ],
    "sg:phone":"+44 20 8393 9982",
    "sg:postcode":"KT17 1QR",
    "sg:province":"Surrey",
    "sg:tags":[
        "hire",
        "coach"
    ],
    "wof:name":"Freeway Coach Services Ltd",
    "wof:placetype":"venue"
},
  "geometry": {"coordinates":[-0.2413100004,51.3451805115],"type":"Point"}
}