{
  "type": "Feature",
  "properties": {
    "addr:full":"30 Pittar Street Derby Derbyshire DE22 3UN",
    "addr:housenumber":"30",
    "addr:postcode":"de22 3un",
    "addr:street":"Pittar Street",
    "iso:country":"GB",
    "sg:address":"30 Pittar Street",
    "sg:city":"Derby",
    "sg:classifiers":[
        {
            "category":"Home & Garden",
            "subcategory":"Home Furnishings",
            "type":"Retail Goods"
        },
        {
            "category":"Home & Garden",
            "subcategory":"Carpets & Floor Coverings",
            "type":"Retail Goods"
        }
    ],
    "sg:phone":"+44 1332 332656",
    "sg:postcode":"DE22 3UN",
    "sg:province":"Derbyshire",
    "sg:tags":[
        "fitting",
        "rug",
        "matting",
        "carpets"
    ],
    "wof:name":"Stephen J Bull",
    "wof:placetype":"venue"
},
  "geometry": {"coordinates":[-1.485608,52.915844],"type":"Point"}
}