{
  "type": "Feature",
  "properties": {
    "iso:country":"GB",
    "sg:address":"16 West Bromwich Road",
    "sg:city":"Walsall",
    "sg:classifiers":[
        {
            "category":"Retail",
            "subcategory":"Driving School",
            "type":"Services"
        }
    ],
    "sg:phone":"+44 1922 644426",
    "sg:postcode":"WS1 3HS",
    "sg:province":"West Midlands",
    "wof:name":"Lets Go Driver Training",
    "wof:placetype":"venue"
},
  "geometry": {"coordinates":[-1.978592,52.572582],"type":"Point"}
}