{
  "type": "Feature",
  "properties": {
    "addr:full":"27 Alma Place, Sebastopol Pontypool Monmouthshire NP4 5EA",
    "addr:housenumber":"27",
    "addr:postcode":"np4 5ea",
    "addr:street":"Alma Place",
    "iso:country":"GB",
    "sg:address":"27 Alma Place, Sebastopol",
    "sg:city":"Pontypool",
    "sg:classifiers":[
        {
            "category":"Recreation",
            "subcategory":"Dance Hall",
            "type":"Entertainment"
        }
    ],
    "sg:postcode":"NP4 5EA",
    "sg:province":"Monmouthshire",
    "sg:tags":[
        "disco"
    ],
    "wof:name":"Sound Creation Disco",
    "wof:placetype":"venue"
},
  "geometry": {"coordinates":[-3.0244240761,51.6767082214],"type":"Point"}
}