{
  "type": "Feature",
  "properties": {
    "addr:full":"35 Barlow Moor Road, Didsbury Manchester Greater Manchester M20 6TW",
    "addr:housenumber":"35",
    "addr:postcode":"m20 6tw",
    "addr:street":"Barlow Moor Road",
    "iso:country":"GB",
    "sg:address":"35 Barlow Moor Road, Didsbury",
    "sg:city":"Manchester",
    "sg:classifiers":[
        {
            "category":"Real Estate",
            "subcategory":"Real Estate Agent",
            "type":"Services"
        }
    ],
    "sg:postcode":"M20 6TW",
    "sg:province":"Greater Manchester",
    "wof:name":"I  Goodman (Properties) Ltd.",
    "wof:placetype":"venue"
},
  "geometry": {"coordinates":[-2.2334029675,53.4180679321],"type":"Point"}
}