{
  "type": "Feature",
  "properties": {
    "addr:full":"69 St Thomas Street Weymouth Dorset DT4 8EL",
    "addr:housenumber":"69",
    "addr:postcode":"dt4 8el",
    "addr:street":"St Thomas Street",
    "iso:country":"GB",
    "sg:address":"69 St Thomas Street",
    "sg:city":"Weymouth",
    "sg:classifiers":[
        {
            "category":"Shopping",
            "subcategory":"Shoes",
            "type":"Retail Goods"
        }
    ],
    "sg:phone":"+44 1305 775794",
    "sg:postcode":"DT4 8EL",
    "sg:province":"Dorset",
    "sg:tags":[
        "shop"
    ],
    "wof:name":"Nicholsons",
    "wof:placetype":"venue"
},
  "geometry": {"coordinates":[-2.4550569057,50.6092262268],"type":"Point"}
}