{
  "type": "Feature",
  "properties": {
    "iso:country":"GB",
    "sg:address":"98 Franklin Avenue",
    "sg:city":"Tadley",
    "sg:classifiers":[
        {
            "category":"Food & Beverages",
            "subcategory":"Supermarket",
            "type":"Retail Goods"
        },
        {
            "category":"Food & Beverages",
            "subcategory":"Groceries & Convenience Stores",
            "type":"Retail Goods"
        }
    ],
    "sg:phone":"+44 118 981 3565",
    "sg:postcode":"RG26 4EU",
    "sg:province":"Berkshire",
    "wof:name":"SOUTHERN CO-OPERATIVES LTD",
    "wof:placetype":"venue"
},
  "geometry": {"coordinates":[-1.1520930529,51.3569488525],"type":"Point"}
}