{
  "type": "Feature",
  "properties": {
    "addr:full":"First Floor 25 Saxon Court, Marefair Northampton Northamptonshire NN1 1SR",
    "addr:housenumber":"25",
    "addr:postcode":"nn1 1sr",
    "addr:street":"Saxon Court Marefair",
    "iso:country":"GB",
    "sg:address":"First Floor 25 Saxon Court, Marefair",
    "sg:city":"Northampton",
    "sg:classifiers":[
        {
            "category":"Banks & Credit Unions",
            "subcategory":"Financial Services",
            "type":"Services"
        }
    ],
    "sg:phone":"+44 1604 633891",
    "sg:postcode":"NN1 1SR",
    "sg:province":"Northamptonshire",
    "sg:tags":[
        "consultant"
    ],
    "wof:name":"Shopacheck Financial Services Ltd.",
    "wof:placetype":"venue"
},
  "geometry": {"coordinates":[-0.902554,52.236355],"type":"Point"}
}