{
  "type": "Feature",
  "properties": {
    "addr:full":"286 High Street Lincoln Lincolnshire LN2 1AL",
    "addr:housenumber":"286",
    "addr:postcode":"ln2 1al",
    "addr:street":"High Street",
    "iso:country":"GB",
    "sg:address":"286 High Street",
    "sg:city":"Lincoln",
    "sg:classifiers":[
        {
            "category":"Shopping",
            "subcategory":"Jewelry",
            "type":"Retail Goods"
        },
        {
            "category":"Manufacturing",
            "subcategory":"Jewelry",
            "type":"Manufacturing & Wholesale Goods"
        }
    ],
    "sg:phone":"+44 1522 525988",
    "sg:postcode":"LN2 1AL",
    "sg:province":"Lincolnshire",
    "sg:tags":[
        "gold",
        "silversmith"
    ],
    "wof:name":"H W Franklin",
    "wof:placetype":"venue"
},
  "geometry": {"coordinates":[-0.5394489765,53.2315101624],"type":"Point"}
}