{
  "type": "Feature",
  "properties": {
    "iso:country":"GB",
    "sg:address":"Pottery Lane, Wrecclesham",
    "sg:city":"Farnham",
    "sg:classifiers":[
        {
            "category":"Manufacturing",
            "subcategory":"Pottery",
            "type":"Manufacturing & Wholesale Goods"
        }
    ],
    "sg:phone":"+44 1252 715318",
    "sg:postcode":"GU10 4QJ",
    "sg:province":"Hampshire",
    "wof:name":"A Harris & Sons",
    "wof:placetype":"venue"
},
  "geometry": {"coordinates":[-0.8176919818,51.200088501],"type":"Point"}
}