{
  "type": "Feature",
  "properties": {
    "addr:full":"The Poplars, Wrenbury Frith Nantwich Cheshire CW5 8HN",
    "addr:postcode":"cw5 8hn",
    "addr:street":"Wrenbury Frith",
    "iso:country":"GB",
    "sg:address":"The Poplars, Wrenbury Frith",
    "sg:city":"Nantwich",
    "sg:classifiers":[
        {
            "category":"Autos & Motor Vehicles",
            "subcategory":"Automobile Sales",
            "type":"Retail Goods"
        }
    ],
    "sg:phone":"+44 1270 780762",
    "sg:postcode":"CW5 8HN",
    "sg:province":"Cheshire",
    "sg:tags":[
        "car",
        "specialist",
        "sales",
        "classic"
    ],
    "wof:name":"The Mk 2 Centre Ltd.",
    "wof:placetype":"venue"
},
  "geometry": {"coordinates":[-2.6036388874,53.024055481],"type":"Point"}
}