{
  "type": "Feature",
  "properties": {
    "addr:full":"Park Lane Works, Northern Court Nottingham Nottinghamshire NG6 0BJ",
    "addr:postcode":"ng6 0bj",
    "addr:street":"Lane;Northern Court",
    "iso:country":"GB",
    "sg:address":"Park Lane Works, Northern Court",
    "sg:city":"Nottingham",
    "sg:classifiers":[
        {
            "category":"Manufacturing",
            "subcategory":"Metals",
            "type":"Manufacturing & Wholesale Goods"
        }
    ],
    "sg:phone":"+44 115 975 7524",
    "sg:postcode":"NG6 0BJ",
    "sg:province":"Nottinghamshire",
    "sg:tags":[
        "steel",
        "fabricator",
        "erectors"
    ],
    "wof:name":"Basford Fabrications (U K) Ltd.",
    "wof:placetype":"venue"
},
  "geometry": {"coordinates":[-1.175409,52.981087],"type":"Point"}
}