{
  "type": "Feature",
  "properties": {
    "iso:country":"GB",
    "sg:address":"31-35 Kirby St",
    "sg:city":"Clerkenwell",
    "sg:classifiers":[
        {
            "category":"Professional",
            "subcategory":"Printing & Photocopies",
            "type":"Services"
        }
    ],
    "sg:phone":"+44 20 7405 5187",
    "sg:postcode":"EC1N 8TE",
    "sg:province":"Greater London",
    "sg:tags":[
        "plate",
        "lithographic",
        "maker"
    ],
    "wof:name":"R H Wilkins Ltd",
    "wof:placetype":"venue"
},
  "geometry": {"coordinates":[-0.107617,51.52034],"type":"Point"}
}