{
  "type": "Feature",
  "properties": {
    "addr:full":"Unit 12, Blackmore Park, Hanley Swan Worcester Gloucestershire WR8 0EF",
    "addr:housenumber":"unit 12",
    "addr:postcode":"wr8 0ef",
    "addr:street":"Blackmore Park",
    "iso:country":"GB",
    "sg:address":"Unit 12, Blackmore Park, Hanley Swan",
    "sg:city":"Worcester",
    "sg:classifiers":[
        {
            "category":"Retail",
            "subcategory":"Auto Repair",
            "type":"Services"
        }
    ],
    "sg:postcode":"WR8 0EF",
    "sg:province":"Gloucestershire",
    "sg:tags":[
        "modification",
        "garage"
    ],
    "wof:name":"Graham Garage",
    "wof:placetype":"venue"
},
  "geometry": {"coordinates":[-2.2735788822,52.0839118958],"type":"Point"}
}