{
  "type": "Feature",
  "properties": {
    "addr:full":"27 Broomwood Rd Kingston Upon Thames Greater London KT1 4ER",
    "addr:housenumber":"27",
    "addr:postcode":"kt1 4er",
    "addr:street":"Broomwood Rd",
    "iso:country":"GB",
    "sg:address":"27 Broomwood Rd",
    "sg:city":"Kingston Upon Thames",
    "sg:classifiers":[
        {
            "category":"Health Services",
            "subcategory":"Health Practitioner",
            "type":"Services"
        }
    ],
    "sg:phone":"+44 20 8943 4794",
    "sg:postcode":"KT1 4ER",
    "sg:province":"Greater London",
    "sg:tags":[
        "hypnotherapists"
    ],
    "wof:name":"Kingston Hypnotherapy Centre",
    "wof:placetype":"venue"
},
  "geometry": {"coordinates":[-0.3105199933,51.4132499695],"type":"Point"}
}