{
  "type": "Feature",
  "properties": {
    "addr:full":"20 Station Road, Llanishen Cardiff Cardiff CF14 5LT",
    "addr:housenumber":"20",
    "addr:postcode":"cf14 5lt",
    "addr:street":"Station Road",
    "iso:country":"GB",
    "sg:address":"20 Station Road, Llanishen",
    "sg:city":"Cardiff",
    "sg:classifiers":[
        {
            "category":"Professional",
            "subcategory":"Engineering",
            "type":"Services"
        },
        {
            "category":"Professional",
            "subcategory":"Business Services",
            "type":"Services"
        }
    ],
    "sg:phone":"+44 29 2075 3859",
    "sg:postcode":"CF14 5LT",
    "sg:province":"Cardiff",
    "sg:tags":[
        "export",
        "engineer",
        "design",
        "agent",
        "import"
    ],
    "wof:name":"Daneway Sales & Marketing Ltd.",
    "wof:placetype":"venue"
},
  "geometry": {"coordinates":[-3.1888411045,51.5288887024],"type":"Point"}
}