{
  "type": "Feature",
  "properties": {
    "addr:full":"Woodredon Farm House Waltham Abbey Essex EN9 3SX",
    "addr:postcode":"en9 3sx",
    "addr:street":"Abbey",
    "iso:country":"GB",
    "sg:address":"Woodredon Farm House",
    "sg:city":"Waltham Abbey",
    "sg:classifiers":[
        {
            "category":"Professional",
            "subcategory":"Art Services",
            "type":"Services"
        }
    ],
    "sg:postcode":"EN9 3SX",
    "sg:province":"Essex",
    "sg:tags":[
        "graphic",
        "designer"
    ],
    "wof:name":"Nick Gill",
    "wof:placetype":"venue"
},
  "geometry": {"coordinates":[0.0014900001,51.6864204407],"type":"Point"}
}