{
  "type": "Feature",
  "properties": {
    "addr:full":"41 Gordon Place, Bridge Of Don Aberdeen Aberdeen City AB23 8RB",
    "addr:housenumber":"41",
    "addr:postcode":"ab23 8rb",
    "addr:street":"Gordon Place",
    "iso:country":"GB",
    "sg:address":"41 Gordon Place, Bridge Of Don",
    "sg:city":"Aberdeen",
    "sg:classifiers":[
        {
            "category":"Building & Trades",
            "subcategory":"Construction",
            "type":"Services"
        }
    ],
    "sg:phone":"+44 1224 703905",
    "sg:postcode":"AB23 8RB",
    "sg:province":"Aberdeen City",
    "sg:tags":[
        "dry",
        "plastering",
        "plasterers",
        "lining",
        "related",
        "screeders"
    ],
    "wof:name":"Gordon Graham Thomson",
    "wof:placetype":"venue"
},
  "geometry": {"coordinates":[-2.099842,57.185619],"type":"Point"}
}