{
  "type": "Feature",
  "properties": {
    "addr:full":"19 Ryhope Road London Greater London N11 1DR",
    "addr:housenumber":"19",
    "addr:postcode":"n11 1dr",
    "addr:street":"Ryhope Road",
    "iso:country":"GB",
    "sg:address":"19 Ryhope Road",
    "sg:city":"London",
    "sg:classifiers":[
        {
            "category":"Freight",
            "type":"Transportation"
        }
    ],
    "sg:phone":"+44 20 8368 9544",
    "sg:postcode":"N11 1DR",
    "sg:province":"Greater London",
    "sg:tags":[
        "overseas",
        "shipping",
        "removal"
    ],
    "wof:name":"Univest International",
    "wof:placetype":"venue"
},
  "geometry": {"coordinates":[-0.1395699978,51.6203765869],"type":"Point"}
}