{
  "type": "Feature",
  "properties": {
    "addr:full":"Dundridge Lane, Bishops Waltham Southampton Hampshire SO32 1GD",
    "addr:postcode":"so32 1gd",
    "addr:street":"Dundridge Lane",
    "iso:country":"GB",
    "sg:address":"Dundridge Lane, Bishops Waltham",
    "sg:city":"Southampton",
    "sg:classifiers":[
        {
            "category":"Bars & Pubs",
            "type":"Food & Drink"
        }
    ],
    "sg:phone":"+44 1489 892940",
    "sg:postcode":"SO32 1GD",
    "sg:province":"Hampshire",
    "sg:tags":[
        "pubs",
        "inn"
    ],
    "wof:name":"Hampshire Bowman",
    "wof:placetype":"venue"
},
  "geometry": {"coordinates":[-1.1547989845,50.969745636],"type":"Point"}
}