{
  "type": "Feature",
  "properties": {
    "iso:country":"GB",
    "sg:address":"Guardian Ho, Richardshaw La",
    "sg:city":"Pudsey",
    "sg:classifiers":[
        {
            "category":"Professional",
            "subcategory":"Credit Reporting & Collection",
            "type":"Services"
        }
    ],
    "sg:phone":"+44 113 255 8034",
    "sg:postcode":"LS28 7EL",
    "sg:province":"West Yorkshire",
    "sg:tags":[
        "collecting",
        "agency"
    ],
    "wof:name":"Guardian Group",
    "wof:placetype":"venue"
},
  "geometry": {"coordinates":[-1.6641290188,53.8004493713],"type":"Point"}
}