{
  "type": "Feature",
  "properties": {
    "addr:full":"Grange Farm, Postland Peterborough Cambridgeshire PE6 0ND",
    "addr:postcode":"pe6 0nd",
    "addr:street":"Postland Peterborough",
    "iso:country":"GB",
    "sg:address":"Grange Farm, Postland",
    "sg:city":"Peterborough",
    "sg:classifiers":[
        {
            "category":"Farming",
            "subcategory":"Livestock Farm",
            "type":"Manufacturing & Wholesale Goods"
        }
    ],
    "sg:postcode":"PE6 0ND",
    "sg:province":"Cambridgeshire",
    "sg:tags":[
        "others"
    ],
    "wof:name":"C Butcher & Sons",
    "wof:placetype":"venue"
},
  "geometry": {"coordinates":[-0.1195589975,52.663898468],"type":"Point"}
}