{
  "type": "Feature",
  "properties": {
    "addr:full":"Eagle House, 159 Right Street Renfrew Renfrewshire PA4 8AN",
    "addr:housenumber":"159",
    "addr:postcode":"pa4 8an",
    "addr:street":"Right Street",
    "iso:country":"GB",
    "sg:address":"Eagle House, 159 Right Street",
    "sg:city":"Renfrew",
    "sg:classifiers":[
        {
            "category":"Freight",
            "type":"Transportation"
        }
    ],
    "sg:phone":"+44 141 887 8877",
    "sg:postcode":"PA4 8AN",
    "sg:province":"Renfrewshire",
    "sg:tags":[
        "forwarders"
    ],
    "wof:name":"Air Sea Scotland Ltd",
    "wof:placetype":"venue"
},
  "geometry": {"coordinates":[-4.4185600281,55.8681793213],"type":"Point"}
}