{
  "type": "Feature",
  "properties": {
    "iso:country":"GB",
    "sg:address":"174 Enterprise Court, Eastways",
    "sg:city":"Witham",
    "sg:classifiers":[
        {
            "category":"Shopping",
            "subcategory":"Photographic Equipment",
            "type":"Retail Goods"
        }
    ],
    "sg:postcode":"CM8 3YS",
    "sg:province":"Essex",
    "wof:name":"Essex Sports Photography",
    "wof:placetype":"venue"
},
  "geometry": {"coordinates":[0.639991,51.800713],"type":"Point"}
}