{
  "type": "Feature",
  "properties": {
    "addr:full":"Cotswold Road Sutton Surrey SM2 5NF",
    "addr:postcode":"sm2 5nf",
    "addr:street":"Cotswold Road",
    "iso:country":"GB",
    "sg:address":"Cotswold Road",
    "sg:city":"Sutton",
    "sg:classifiers":[
        {
            "category":"Retail",
            "subcategory":"Auto Rental",
            "type":"Services"
        }
    ],
    "sg:phone":"+44 20 8296 4475",
    "sg:postcode":"SM2 5NF",
    "sg:province":"Surrey",
    "sg:tags":[
        "car"
    ],
    "wof:name":"Fleetcare",
    "wof:placetype":"venue"
},
  "geometry": {"coordinates":[-0.194464,51.343964],"type":"Point"}
}