{
  "type": "Feature",
  "properties": {
    "iso:country":"GB",
    "sg:address":"1 Throgmorton Avenue",
    "sg:city":"Moorgate",
    "sg:classifiers":[
        {
            "category":"Banks & Credit Unions",
            "subcategory":"Financial Services",
            "type":"Services"
        }
    ],
    "sg:phone":"+44 20 7588 0655",
    "sg:postcode":"EC2N 2JJ",
    "sg:province":"Greater London",
    "sg:tags":[
        "adviser"
    ],
    "wof:name":"Millennium Financial Group Incorporated",
    "wof:placetype":"venue"
},
  "geometry": {"coordinates":[-0.0859280005,51.5166893005],"type":"Point"}
}