{
  "type": "Feature",
  "properties": {
    "addr:full":"29 Tamworth St Lichfield Staffordshire WS13 6JP",
    "addr:housenumber":"29",
    "addr:postcode":"ws13 6jp",
    "addr:street":"Tamworth St",
    "iso:country":"GB",
    "sg:address":"29 Tamworth St",
    "sg:city":"Lichfield",
    "sg:classifiers":[
        {
            "category":"Professional",
            "subcategory":"Accounting & Tax Preparation",
            "type":"Services"
        }
    ],
    "sg:phone":"+44 1543 255333",
    "sg:postcode":"WS13 6JP",
    "sg:province":"Staffordshire",
    "sg:tags":[
        "accountant"
    ],
    "wof:name":"A.J Groucott & Co",
    "wof:placetype":"venue"
},
  "geometry": {"coordinates":[-1.8255579472,52.6840324402],"type":"Point"}
}