{
  "type": "Feature",
  "properties": {
    "addr:full":"6 Balornock Road Glasgow East Dunbartonshire G21 3UH",
    "addr:housenumber":"6",
    "addr:postcode":"g21 3uh",
    "addr:street":"Balornock Road",
    "iso:country":"GB",
    "sg:address":"6 Balornock Road",
    "sg:city":"Glasgow",
    "sg:classifiers":[
        {
            "category":"Food & Beverages",
            "subcategory":"Fruits & Vegetables",
            "type":"Retail Goods"
        }
    ],
    "sg:phone":"+44 141 557 0973",
    "sg:postcode":"G21 3UH",
    "sg:province":"East Dunbartonshire",
    "sg:tags":[
        "greengrocer"
    ],
    "wof:name":"Sohal Grocers",
    "wof:placetype":"venue"
},
  "geometry": {"coordinates":[-4.217889,55.888084],"type":"Point"}
}