{
  "type": "Feature",
  "properties": {
    "iso:country":"GB",
    "sg:address":"41 Broad Oak Rd",
    "sg:city":"Canterbury",
    "sg:classifiers":[
        {
            "category":"Real Estate",
            "subcategory":"Architect",
            "type":"Services"
        }
    ],
    "sg:phone":"+44 1227 765574",
    "sg:postcode":"CT2 7PN",
    "sg:province":"Kent",
    "wof:name":"Bob Combs",
    "wof:placetype":"venue"
},
  "geometry": {"coordinates":[1.0849870443,51.2881507874],"type":"Point"}
}