{
  "type": "Feature",
  "properties": {
    "addr:full":"19 Barton Lane Abingdon Oxfordshire OX14 3NB",
    "addr:housenumber":"19",
    "addr:postcode":"ox14 3nb",
    "addr:street":"Barton Lane",
    "iso:country":"GB",
    "sg:address":"19 Barton Lane",
    "sg:city":"Abingdon",
    "sg:classifiers":[
        {
            "category":"Manufacturing",
            "subcategory":"Chemicals & Compounds",
            "type":"Manufacturing & Wholesale Goods"
        },
        {
            "category":"Wholesale",
            "subcategory":"Chemicals & Plastics",
            "type":"Manufacturing & Wholesale Goods"
        }
    ],
    "sg:phone":"+44 1235 529449",
    "sg:postcode":"OX14 3NB",
    "sg:province":"Oxfordshire",
    "sg:tags":[
        "product",
        "allied"
    ],
    "wof:name":"R & D Systems Europe Ltd.",
    "wof:placetype":"venue"
},
  "geometry": {"coordinates":[-1.256854,51.671631],"type":"Point"}
}