{
  "type": "Feature",
  "properties": {
    "iso:country":"GB",
    "sg:address":"46 Station Road",
    "sg:city":"West Drayton",
    "sg:classifiers":[
        {
            "category":"Professional",
            "type":"Services"
        }
    ],
    "sg:phone":"+44 1895 446566",
    "sg:postcode":"UB7 7DD",
    "sg:province":"Greater London",
    "sg:tags":[
        "caterer"
    ],
    "wof:name":"Munchees",
    "wof:placetype":"venue"
},
  "geometry": {"coordinates":[-0.4735969901,51.5083122253],"type":"Point"}
}