{
  "type": "Feature",
  "properties": {
    "addr:full":"Kitchen, Christ Church C Of E Junior School, Woodcote Rd Wolverhampton Shropshire WV6 8LG",
    "addr:postcode":"wv6 8lg",
    "addr:street":"Woodcote Rd",
    "iso:country":"GB",
    "sg:address":"Kitchen, Christ Church C Of E Junior School, Woodcote Rd",
    "sg:city":"Wolverhampton",
    "sg:classifiers":[
        {
            "category":"Government",
            "subcategory":"Office",
            "type":"Public Place"
        }
    ],
    "sg:phone":"+44 1902 558008",
    "sg:postcode":"WV6 8LG",
    "sg:province":"Shropshire",
    "sg:tags":[
        "local"
    ],
    "wof:name":"Wolverhampton Borough Council",
    "wof:placetype":"venue"
},
  "geometry": {"coordinates":[-2.17656,52.595299],"type":"Point"}
}