{
  "type": "Feature",
  "properties": {
    "iso:country":"GB",
    "sg:address":"138 Woodhouse St",
    "sg:city":"Leeds",
    "sg:classifiers":[
        {
            "category":"Cinema",
            "subcategory":"Movie Rental",
            "type":"Entertainment"
        }
    ],
    "sg:phone":"+44 113 225 1400",
    "sg:postcode":"LS6 2JN",
    "sg:province":"West Yorkshire",
    "sg:tags":[
        "video",
        "library"
    ],
    "wof:name":"Video 2000",
    "wof:placetype":"venue"
},
  "geometry": {"coordinates":[-1.5534449816,53.814250946],"type":"Point"}
}