{
  "type": "Feature",
  "properties": {
    "addr:full":"14 St Pauls Rd Mirfield West Yorkshire WF14 8AX",
    "addr:housenumber":"14",
    "addr:postcode":"wf14 8ax",
    "addr:street":"St Pauls Rd",
    "iso:country":"GB",
    "sg:address":"14 St Pauls Rd",
    "sg:city":"Mirfield",
    "sg:classifiers":[
        {
            "category":"Retail",
            "subcategory":"Funeral Services",
            "type":"Services"
        }
    ],
    "sg:phone":"+44 1924 497352",
    "sg:postcode":"WF14 8AX",
    "sg:province":"West Yorkshire",
    "wof:name":"George Brooke",
    "wof:placetype":"venue"
},
  "geometry": {"coordinates":[-1.6951559782,53.6747207642],"type":"Point"}
}