{
  "type": "Feature",
  "properties": {
    "addr:full":"Tufthorn Avenue Coleford Gloucestershire GL16 8PR",
    "addr:postcode":"gl16 8pr",
    "addr:street":"Avenue",
    "iso:country":"GB",
    "sg:address":"Tufthorn Avenue",
    "sg:city":"Coleford",
    "sg:classifiers":[
        {
            "category":"Manufacturing",
            "subcategory":"Building Materials",
            "type":"Manufacturing & Wholesale Goods"
        }
    ],
    "sg:postcode":"GL16 8PR",
    "sg:province":"Gloucestershire",
    "sg:tags":[
        "concrete",
        "product"
    ],
    "wof:name":"Formpave Ltd.",
    "wof:placetype":"venue"
},
  "geometry": {"coordinates":[-2.6116840839,51.785533905],"type":"Point"}
}