{
  "type": "Feature",
  "properties": {
    "addr:full":"215 Great Brickkiln Street Wolverhampton Staffordshire WV3 0PN",
    "addr:housenumber":"215",
    "addr:postcode":"wv3 0pn",
    "addr:street":"Great Brickkiln Street",
    "iso:country":"GB",
    "sg:address":"215 Great Brickkiln Street",
    "sg:city":"Wolverhampton",
    "sg:classifiers":[
        {
            "category":"Place Of Worship",
            "type":"Public Place"
        }
    ],
    "sg:phone":"+44 1902 712229",
    "sg:postcode":"WV3 0PN",
    "sg:province":"Staffordshire",
    "wof:name":"Great Brickkiln Street Seventh Day Adventist Church",
    "wof:placetype":"venue"
},
  "geometry": {"coordinates":[-2.138175,52.581493],"type":"Point"}
}