{
  "type": "Feature",
  "properties": {
    "addr:full":"7 Windermere Road Haywards Heath East Sussex RH16 3JX",
    "addr:housenumber":"7",
    "addr:postcode":"rh16 3jx",
    "addr:street":"Windermere Road",
    "iso:country":"GB",
    "sg:address":"7 Windermere Road",
    "sg:city":"Haywards Heath",
    "sg:classifiers":[
        {
            "category":"Building & Trades",
            "subcategory":"Plumbing",
            "type":"Services"
        },
        {
            "category":"Utilities",
            "subcategory":"Electric",
            "type":"Services"
        }
    ],
    "sg:phone":"+44 1444 456058",
    "sg:postcode":"RH16 3JX",
    "sg:province":"East Sussex",
    "sg:tags":[
        "consultant",
        "system",
        "heating"
    ],
    "wof:name":"Mackay Design Services",
    "wof:placetype":"venue"
},
  "geometry": {"coordinates":[-0.094026,50.999878],"type":"Point"}
}