{
  "type": "Feature",
  "properties": {
    "iso:country":"GB",
    "sg:address":"29-31 Hampshire Terrace",
    "sg:city":"Portsmouth",
    "sg:classifiers":[
        {
            "category":"Travel",
            "subcategory":"Hotels & Motels",
            "type":"Entertainment"
        }
    ],
    "sg:postcode":"PO1 2QF",
    "sg:province":"Hampshire",
    "wof:name":"Hampshire Court Hotel",
    "wof:placetype":"venue"
},
  "geometry": {"coordinates":[-1.0958240032,50.7931556702],"type":"Point"}
}