{
  "type": "Feature",
  "properties": {
    "addr:full":"44 High Street, Barkingside Ilford Essex IG6 2DQ",
    "addr:housenumber":"44",
    "addr:postcode":"ig6 2dq",
    "addr:street":"High Street",
    "iso:country":"GB",
    "sg:address":"44 High Street, Barkingside",
    "sg:city":"Ilford",
    "sg:classifiers":[
        {
            "category":"Shopping",
            "subcategory":"News",
            "type":"Retail Goods"
        }
    ],
    "sg:phone":"+44 20 8550 1791",
    "sg:postcode":"IG6 2DQ",
    "sg:province":"Essex",
    "sg:tags":[
        "newsagent"
    ],
    "wof:name":"Essex News",
    "wof:placetype":"venue"
},
  "geometry": {"coordinates":[0.0818570033,51.5896224976],"type":"Point"}
}