{
  "type": "Feature",
  "properties": {
    "iso:country":"GB",
    "sg:address":"133 Cumbernauld Rd, Stepps",
    "sg:city":"Glasgow",
    "sg:classifiers":[
        {
            "category":"Shopping",
            "subcategory":"Department Store",
            "type":"Retail Goods"
        }
    ],
    "sg:postcode":"G33 6EY",
    "sg:province":"Glasgow City",
    "wof:name":"Johnson,Eileen,",
    "wof:placetype":"venue"
},
  "geometry": {"coordinates":[-4.145697,55.891392],"type":"Point"}
}