{
  "type": "Feature",
  "properties": {
    "iso:country":"GB",
    "sg:address":"Unit 1",
    "sg:city":"Glasgow",
    "sg:classifiers":[
        {
            "category":"Manufacturing",
            "subcategory":"Tools & Machinery",
            "type":"Manufacturing & Wholesale Goods"
        }
    ],
    "sg:phone":"+44 141 347 0707",
    "sg:postcode":"G22 7QQ",
    "sg:province":"Glasgow City",
    "sg:tags":[
        "design",
        "maker",
        "manufacturer"
    ],
    "wof:name":"Anderson Tool Manufacturing Ltd",
    "wof:placetype":"venue"
},
  "geometry": {"coordinates":[-4.262819767,55.897190094],"type":"Point"}
}