{
  "type": "Feature",
  "properties": {
    "addr:full":"15 Clarendon Rd Blackpool Lancashire FY1 6EF",
    "addr:housenumber":"15",
    "addr:postcode":"fy1 6ef",
    "addr:street":"Clarendon Rd",
    "iso:country":"GB",
    "sg:address":"15 Clarendon Rd",
    "sg:city":"Blackpool",
    "sg:classifiers":[
        {
            "category":"Travel",
            "subcategory":"Hotels & Motels",
            "type":"Entertainment"
        }
    ],
    "sg:phone":"+44 1253 345464",
    "sg:postcode":"FY1 6EF",
    "sg:province":"Lancashire",
    "sg:tags":[
        "house",
        "guest"
    ],
    "wof:name":"Tudor Guest House",
    "wof:placetype":"venue"
},
  "geometry": {"coordinates":[-3.051295042,53.804851532],"type":"Point"}
}