{
  "type": "Feature",
  "properties": {
    "addr:full":"25 Duke Street Sheffield South Yorkshire S2 5QA",
    "addr:housenumber":"25",
    "addr:postcode":"s2 5qa",
    "addr:street":"Duke Street",
    "iso:country":"GB",
    "sg:address":"25 Duke Street",
    "sg:city":"Sheffield",
    "sg:classifiers":[
        {
            "category":"Autos & Motor Vehicles",
            "subcategory":"Auto Supplies",
            "type":"Retail Goods"
        }
    ],
    "sg:phone":"+44 114 273 7175",
    "sg:postcode":"S2 5QA",
    "sg:province":"South Yorkshire",
    "sg:tags":[
        "car",
        "part",
        "tyre",
        "accessory"
    ],
    "wof:name":"Parkway Tyres",
    "wof:placetype":"venue"
},
  "geometry": {"coordinates":[-1.458556,53.382645],"type":"Point"}
}