{
  "type": "Feature",
  "properties": {
    "iso:country":"GB",
    "sg:address":"6 Northgate, Goosnargh",
    "sg:city":"Preston",
    "sg:classifiers":[
        {
            "category":"Building & Trades",
            "subcategory":"Cleaning & Sanitation",
            "type":"Services"
        },
        {
            "category":"Social Services",
            "subcategory":"Adult Care",
            "type":"Services"
        }
    ],
    "sg:phone":"+44 1772 866181",
    "sg:postcode":"PR3 2BB",
    "sg:province":"Lancashire",
    "sg:tags":[
        "contracting",
        "commercial",
        "domestic"
    ],
    "wof:name":"Selclene",
    "wof:placetype":"venue"
},
  "geometry": {"coordinates":[-2.672994,53.824333],"type":"Point"}
}