{
  "type": "Feature",
  "properties": {
    "addr:full":"193-197 Northdown Road, Cliftonville Margate Kent CT9 2PA",
    "addr:housenumber":"193-197",
    "addr:postcode":"ct9 2pa",
    "addr:street":"Northdown Road;Margate",
    "iso:country":"GB",
    "sg:address":"193-197 Northdown Road, Cliftonville",
    "sg:city":"Margate",
    "sg:classifiers":[
        {
            "category":"Cinema",
            "subcategory":"Movie Rental",
            "type":"Entertainment"
        }
    ],
    "sg:phone":"+44 1843 290033",
    "sg:postcode":"CT9 2PA",
    "sg:province":"Kent",
    "sg:tags":[
        "video",
        "library"
    ],
    "wof:name":"Apollo Home Entertainment",
    "wof:placetype":"venue"
},
  "geometry": {"coordinates":[1.398881,51.387566],"type":"Point"}
}