{
  "type": "Feature",
  "properties": {
    "addr:full":"222 Pollards Oak Road, Hurst Grn Oxted Surrey RH8 0JP",
    "addr:housenumber":"222",
    "addr:postcode":"rh8 0jp",
    "addr:street":"Pollards Oak Road",
    "iso:country":"GB",
    "sg:address":"222 Pollards Oak Road, Hurst Grn",
    "sg:city":"Oxted",
    "sg:classifiers":[
        {
            "category":"Shopping",
            "subcategory":"News",
            "type":"Retail Goods"
        }
    ],
    "sg:phone":"+44 1883 712282",
    "sg:postcode":"RH8 0JP",
    "sg:province":"Surrey",
    "sg:tags":[
        "newsagent"
    ],
    "wof:name":"Hurst Green Newsagents",
    "wof:placetype":"venue"
},
  "geometry": {"coordinates":[0.0061280001,51.2442512512],"type":"Point"}
}