{
  "type": "Feature",
  "properties": {
    "iso:country":"GB",
    "sg:address":"17 High Street",
    "sg:city":"Ayr",
    "sg:classifiers":[
        {
            "category":"Arts & Performance",
            "subcategory":"Art Gallery",
            "type":"Entertainment"
        },
        {
            "category":"Museum",
            "subcategory":"Art Museum",
            "type":"Entertainment"
        }
    ],
    "sg:phone":"+44 1292 281176",
    "sg:postcode":"KA7 1LU",
    "sg:province":"South Ayrshire",
    "wof:name":"The World of Art",
    "wof:placetype":"venue"
},
  "geometry": {"coordinates":[-4.631253,55.464161],"type":"Point"}
}