{
  "type": "Feature",
  "properties": {
    "addr:full":"4 Holywell Hill St. Albans Hertfordshire AL1 1BZ",
    "addr:housenumber":"4",
    "addr:postcode":"al1 1bz",
    "addr:street":"Holywell Hill",
    "iso:country":"GB",
    "sg:address":"4 Holywell Hill",
    "sg:city":"St. Albans",
    "sg:classifiers":[
        {
            "category":"Real Estate",
            "subcategory":"Real Estate Agent",
            "type":"Services"
        }
    ],
    "sg:phone":"+44 1727 847666",
    "sg:postcode":"AL1 1BZ",
    "sg:province":"Hertfordshire",
    "wof:name":"Steve Walker",
    "wof:placetype":"venue"
},
  "geometry": {"coordinates":[-0.340103,51.750748],"type":"Point"}
}