{
  "type": "Feature",
  "properties": {
    "addr:full":"1b Station St, Mansfield Woodhouse Mansfield Derbyshire NG19 8AE",
    "addr:housenumber":"1b",
    "addr:postcode":"ng19 8ae",
    "addr:street":"Station St",
    "iso:country":"GB",
    "sg:address":"1b Station St, Mansfield Woodhouse",
    "sg:city":"Mansfield",
    "sg:classifiers":[
        {
            "category":"Farming",
            "subcategory":"Livestock Farm",
            "type":"Manufacturing & Wholesale Goods"
        }
    ],
    "sg:postcode":"NG19 8AE",
    "sg:province":"Derbyshire",
    "sg:tags":[
        "breeder"
    ],
    "wof:name":"Floraflair",
    "wof:placetype":"venue"
},
  "geometry": {"coordinates":[-1.1940749884,53.1648254395],"type":"Point"}
}