{
  "type": "Feature",
  "properties": {
    "addr:full":"1 Moravian Street Crook Durham DL15 9HN",
    "addr:housenumber":"1",
    "addr:postcode":"dl15 9hn",
    "addr:street":"Moravian Street",
    "iso:country":"GB",
    "sg:address":"1 Moravian Street",
    "sg:city":"Crook",
    "sg:classifiers":[
        {
            "category":"Bus Charters",
            "type":"Transportation"
        }
    ],
    "sg:phone":"+44 1388 763241",
    "sg:postcode":"DL15 9HN",
    "sg:province":"Durham",
    "sg:tags":[
        "hire",
        "coach"
    ],
    "wof:name":"Savilles Taxis & Coaches",
    "wof:placetype":"venue"
},
  "geometry": {"coordinates":[-1.7483149767,54.71484375],"type":"Point"}
}