{
  "type": "Feature",
  "properties": {
    "iso:country":"GB",
    "sg:address":"Manor, Stallingborough Road, Healing",
    "sg:city":"Grimsby",
    "sg:classifiers":[
        {
            "category":"Farming",
            "subcategory":"Farm",
            "type":"Manufacturing & Wholesale Goods"
        }
    ],
    "sg:phone":"+44 1472 882437",
    "sg:postcode":"DN41 7QF",
    "sg:province":"Lincolnshire",
    "sg:tags":[
        "mixed",
        "crop"
    ],
    "wof:name":"N R Peasgood",
    "wof:placetype":"venue"
},
  "geometry": {"coordinates":[-0.163937,53.573849],"type":"Point"}
}