{
  "type": "Feature",
  "properties": {
    "addr:full":"39 Samlet Road Swansea Neath Port Talbot SA7 9AD",
    "addr:housenumber":"39",
    "addr:postcode":"sa7 9ad",
    "addr:street":"Samlet Road",
    "iso:country":"GB",
    "sg:address":"39 Samlet Road",
    "sg:city":"Swansea",
    "sg:classifiers":[
        {
            "category":"Shopping",
            "subcategory":"Department Store",
            "type":"Retail Goods"
        },
        {
            "category":"Retail",
            "subcategory":"Auto Repair",
            "type":"Services"
        }
    ],
    "sg:postcode":"SA7 9AD",
    "sg:province":"Neath Port Talbot",
    "sg:tags":[
        "modification",
        "garage"
    ],
    "wof:name":"Morriston Car Sales Ltd.",
    "wof:placetype":"venue"
},
  "geometry": {"coordinates":[-3.9076490402,51.6619262695],"type":"Point"}
}