{
  "type": "Feature",
  "properties": {
    "addr:full":"Block 2, Ward Street Alloa Clackmannanshire FK10 1ET",
    "addr:postcode":"fk10 1et",
    "addr:street":"Ward Street",
    "iso:country":"GB",
    "sg:address":"Block 2, Ward Street",
    "sg:city":"Alloa",
    "sg:classifiers":[
        {
            "category":"Professional",
            "type":"Services"
        },
        {
            "category":"Professional",
            "subcategory":"Business Services",
            "type":"Services"
        }
    ],
    "sg:phone":"+44 1259 219923",
    "sg:postcode":"FK10 1ET",
    "sg:province":"Clackmannanshire",
    "sg:tags":[
        "shopfitting",
        "shopfitters",
        "contractor"
    ],
    "wof:name":"Donaldson Construction Ltd",
    "wof:placetype":"venue"
},
  "geometry": {"coordinates":[-3.7951939106,56.1163215637],"type":"Point"}
}