{
  "type": "Feature",
  "properties": {
    "addr:full":"Front Street, Rothbury Morpeth Northumberland NE65 7UF",
    "addr:postcode":"ne65 7uf",
    "addr:street":"Front Street",
    "iso:country":"GB",
    "sg:address":"Front Street, Rothbury",
    "sg:city":"Morpeth",
    "sg:classifiers":[
        {
            "category":"Professional",
            "subcategory":"Printing & Photocopies",
            "type":"Services"
        }
    ],
    "sg:postcode":"NE65 7UF",
    "sg:province":"Northumberland",
    "sg:tags":[
        "trophy"
    ],
    "wof:name":"Coquetdale Trophies",
    "wof:placetype":"venue"
},
  "geometry": {"coordinates":[-1.913994,55.309254],"type":"Point"}
}