{
  "type": "Feature",
  "properties": {
    "addr:full":"73-75 Gravelly Hill North, Erdington Birmingham West Midlands B23 6BJ",
    "addr:housenumber":"73-75",
    "addr:postcode":"b23 6bj",
    "addr:street":"Gravelly Hill North",
    "iso:country":"GB",
    "sg:address":"73-75 Gravelly Hill North, Erdington",
    "sg:city":"Birmingham",
    "sg:classifiers":[
        {
            "category":"Retail",
            "subcategory":"Event Space",
            "type":"Services"
        },
        {
            "category":"Science Facility",
            "type":"Public Place"
        }
    ],
    "sg:phone":"+44 121 373 0417",
    "sg:postcode":"B23 6BJ",
    "sg:province":"West Midlands",
    "sg:tags":[
        "banqueting",
        "room"
    ],
    "wof:name":"Yenton Assembly Rooms Ltd",
    "wof:placetype":"venue"
},
  "geometry": {"coordinates":[-1.841279,52.528732],"type":"Point"}
}