{
  "type": "Feature",
  "properties": {
    "addr:full":"38-40 Egerton St, Farnworth Bolton Lancashire BL4 7LE",
    "addr:housenumber":"38-40",
    "addr:postcode":"bl4 7le",
    "addr:street":"Egerton St",
    "iso:country":"GB",
    "sg:address":"38-40 Egerton St, Farnworth",
    "sg:city":"Bolton",
    "sg:classifiers":[
        {
            "category":"Shopping",
            "subcategory":"Department Store",
            "type":"Retail Goods"
        },
        {
            "category":"Home & Garden",
            "subcategory":"Carpets & Floor Coverings",
            "type":"Retail Goods"
        }
    ],
    "sg:postcode":"BL4 7LE",
    "sg:province":"Lancashire",
    "sg:tags":[
        "carpets",
        "rug",
        "matting"
    ],
    "wof:name":"Ahmed,Bashir,",
    "wof:placetype":"venue"
},
  "geometry": {"coordinates":[-2.401819,53.55484],"type":"Point"}
}