{
  "type": "Feature",
  "properties": {
    "addr:full":"London Rd South Ockendon Essex RM15 4XS",
    "addr:postcode":"rm15 4xs",
    "addr:street":"London Rd",
    "iso:country":"GB",
    "sg:address":"London Rd",
    "sg:city":"South Ockendon",
    "sg:classifiers":[
        {
            "category":"Home & Garden",
            "subcategory":"Garden Supply",
            "type":"Retail Goods"
        }
    ],
    "sg:phone":"+44 1708 865882",
    "sg:postcode":"RM15 4XS",
    "sg:province":"Essex",
    "sg:tags":[
        "nursery",
        "centre"
    ],
    "wof:name":"Tunnel Nurseries",
    "wof:placetype":"venue"
},
  "geometry": {"coordinates":[0.2299,51.498894],"type":"Point"}
}