{
  "type": "Feature",
  "properties": {
    "addr:full":"Maple Road, Tankersley Barnsley South Yorkshire S75 3DN",
    "addr:postcode":"s75 3dn",
    "addr:street":"Maple Road;Yorkshire",
    "iso:country":"GB",
    "sg:address":"Maple Road, Tankersley",
    "sg:city":"Barnsley",
    "sg:classifiers":[
        {
            "category":"Professional",
            "subcategory":"Business Services",
            "type":"Services"
        }
    ],
    "sg:phone":"+44 1226 740033",
    "sg:postcode":"S75 3DN",
    "sg:province":"South Yorkshire",
    "sg:tags":[
        "distribution"
    ],
    "wof:name":"Wentworth Warehousing & Distribution Ltd",
    "wof:placetype":"venue"
},
  "geometry": {"coordinates":[-1.493915,53.487335],"type":"Point"}
}