{
  "type": "Feature",
  "properties": {
    "addr:full":"Queenborough Harbour, Town Quay, South Street Queenborough Kent ME11 5AF",
    "addr:postcode":"me11 5af",
    "addr:street":"Harbour Town Quay South Street",
    "iso:country":"GB",
    "sg:address":"Queenborough Harbour, Town Quay, South Street",
    "sg:city":"Queenborough",
    "sg:classifiers":[
        {
            "category":"Harbor",
            "type":"Transportation"
        },
        {
            "category":"Government",
            "subcategory":"Office",
            "type":"Public Place"
        }
    ],
    "sg:phone":"+44 1795 662051",
    "sg:postcode":"ME11 5AF",
    "sg:province":"Kent",
    "sg:tags":[
        "dock",
        "local",
        "ports",
        "harbour"
    ],
    "wof:name":"Swale Borough Council",
    "wof:placetype":"venue"
},
  "geometry": {"coordinates":[0.7538449764,51.414806366],"type":"Point"}
}