{
  "type": "Feature",
  "properties": {
    "iso:country":"GB",
    "sg:address":"67 Swanbury Drive",
    "sg:city":"Bournemouth",
    "sg:classifiers":[
        {
            "category":"Retail",
            "subcategory":"Driving School",
            "type":"Services"
        }
    ],
    "sg:phone":"+44 800 028 0734",
    "sg:postcode":"BH8 0LB",
    "sg:province":"Dorset",
    "wof:name":"Wayside Transport",
    "wof:placetype":"venue"
},
  "geometry": {"coordinates":[-1.8230019808,50.7529411316],"type":"Point"}
}