{
  "type": "Feature",
  "properties": {
    "addr:full":"Bourges Boulevard Peterborough Cambridgeshire PE1 1SE",
    "addr:postcode":"pe1 1se",
    "addr:street":"Bourges Boulevard",
    "iso:country":"GB",
    "sg:address":"Bourges Boulevard",
    "sg:city":"Peterborough",
    "sg:classifiers":[
        {
            "category":"Professional",
            "type":"Services"
        }
    ],
    "sg:phone":"+44 1733 350924",
    "sg:postcode":"PE1 1SE",
    "sg:province":"Cambridgeshire",
    "sg:tags":[
        "caterer"
    ],
    "wof:name":"S & S Catering",
    "wof:placetype":"venue"
},
  "geometry": {"coordinates":[-0.246345,52.571114],"type":"Point"}
}