{
  "type": "Feature",
  "properties": {
    "addr:full":"1 Williams Avenue Weymouth Dorset DT4 9BW",
    "addr:housenumber":"1",
    "addr:postcode":"dt4 9bw",
    "addr:street":"Williams Avenue",
    "iso:country":"GB",
    "sg:address":"1 Williams Avenue",
    "sg:city":"Weymouth",
    "sg:classifiers":[
        {
            "category":"Personal",
            "subcategory":"Beauty Salon",
            "type":"Services"
        }
    ],
    "sg:postcode":"DT4 9BW",
    "sg:province":"Dorset",
    "sg:tags":[
        "unisex",
        "hairdresser"
    ],
    "wof:name":"Blanche Hair Design",
    "wof:placetype":"venue"
},
  "geometry": {"coordinates":[-2.475068,50.594395],"type":"Point"}
}