{
  "type": "Feature",
  "properties": {
    "addr:full":"54 Bedford Rd Horsham West Sussex RH13 5BJ",
    "addr:housenumber":"54",
    "addr:postcode":"rh13 5bj",
    "addr:street":"Bedford Rd",
    "iso:country":"GB",
    "sg:address":"54 Bedford Rd",
    "sg:city":"Horsham",
    "sg:classifiers":[
        {
            "category":"Professional",
            "type":"Services"
        }
    ],
    "sg:postcode":"RH13 5BJ",
    "sg:province":"West Sussex",
    "sg:tags":[
        "caterer"
    ],
    "wof:name":"Crook,David,",
    "wof:placetype":"venue"
},
  "geometry": {"coordinates":[-0.3185099959,51.0610351562],"type":"Point"}
}