{
  "type": "Feature",
  "properties": {
    "addr:full":"33 Huntsmans Lane, Stamford Bridge York East Riding of Yorkshire YO41 1ES",
    "addr:housenumber":"33",
    "addr:postcode":"yo41 1es",
    "addr:street":"Huntsmans Lane",
    "iso:country":"GB",
    "sg:address":"33 Huntsmans Lane, Stamford Bridge",
    "sg:city":"York",
    "sg:classifiers":[
        {
            "category":"Building & Trades",
            "subcategory":"Plumbing",
            "type":"Services"
        }
    ],
    "sg:postcode":"YO41 1ES",
    "sg:province":"East Riding of Yorkshire",
    "sg:tags":[
        "heating"
    ],
    "wof:name":"John West & Son",
    "wof:placetype":"venue"
},
  "geometry": {"coordinates":[-0.921153,53.986797],"type":"Point"}
}