{
  "type": "Feature",
  "properties": {
    "addr:full":"20 Low Road, Drayton Norwich Norfolk NR8 6AA",
    "addr:housenumber":"20",
    "addr:postcode":"nr8 6aa",
    "addr:street":"Low Road;Norwich Norfolk",
    "iso:country":"GB",
    "sg:address":"20 Low Road, Drayton",
    "sg:city":"Norwich",
    "sg:classifiers":[
        {
            "category":"Manufacturing",
            "subcategory":"Metals",
            "type":"Manufacturing & Wholesale Goods"
        }
    ],
    "sg:phone":"+44 1603 868199",
    "sg:postcode":"NR8 6AA",
    "sg:province":"Norfolk",
    "sg:tags":[
        "fabricator",
        "aluminium",
        "mnfrs"
    ],
    "wof:name":"Drayton Windows Ltd.",
    "wof:placetype":"venue"
},
  "geometry": {"coordinates":[1.224429,52.674835],"type":"Point"}
}