{
  "type": "Feature",
  "properties": {
    "addr:full":"23 Brook Rd Wolverhampton Shropshire WV5 0EQ",
    "addr:housenumber":"23",
    "addr:postcode":"wv5 0eq",
    "addr:street":"Brook Rd",
    "iso:country":"GB",
    "sg:address":"23 Brook Rd",
    "sg:city":"Wolverhampton",
    "sg:classifiers":[
        {
            "category":"Building & Trades",
            "subcategory":"Landscaping Services",
            "type":"Services"
        }
    ],
    "sg:phone":"+44 1902 894373",
    "sg:postcode":"WV5 0EQ",
    "sg:province":"Shropshire",
    "sg:tags":[
        "landscape",
        "contractor"
    ],
    "wof:name":"J & D Garden Maintenance",
    "wof:placetype":"venue"
},
  "geometry": {"coordinates":[-2.1968140602,52.531211853],"type":"Point"}
}