{
  "type": "Feature",
  "properties": {
    "addr:full":"Newington Road Ramsgate Kent CT12 6ED",
    "addr:postcode":"ct12 6ed",
    "addr:street":"Newington Road Ramsgate",
    "iso:country":"GB",
    "sg:address":"Newington Road",
    "sg:city":"Ramsgate",
    "sg:classifiers":[
        {
            "category":"Building & Trades",
            "subcategory":"Construction",
            "type":"Services"
        }
    ],
    "sg:phone":"+44 1843 583147",
    "sg:postcode":"CT12 6ED",
    "sg:province":"Kent",
    "sg:tags":[
        "joinery"
    ],
    "wof:name":"Magnet",
    "wof:placetype":"venue"
},
  "geometry": {"coordinates":[1.4019149542,51.3520355225],"type":"Point"}
}