{
  "type": "Feature",
  "properties": {
    "addr:full":"226 South View Road Sheffield South Yorkshire S7 1DF",
    "addr:housenumber":"226",
    "addr:postcode":"s7 1df",
    "addr:street":"South View Road",
    "iso:country":"GB",
    "sg:address":"226 South View Road",
    "sg:city":"Sheffield",
    "sg:classifiers":[
        {
            "category":"Professional",
            "subcategory":"Accounting & Tax Preparation",
            "type":"Services"
        }
    ],
    "sg:phone":"+44 114 258 0332",
    "sg:postcode":"S7 1DF",
    "sg:province":"South Yorkshire",
    "sg:tags":[
        "accountant",
        "bookkeeping",
        "primarily",
        "activity"
    ],
    "wof:name":"K & M Commercial Services Ltd",
    "wof:placetype":"venue"
},
  "geometry": {"coordinates":[-1.4773939848,53.363483429],"type":"Point"}
}