{
  "type": "Feature",
  "properties": {
    "addr:full":"5 Staniland Way Peterborough Cambridgeshire PE4 6NA",
    "addr:housenumber":"5",
    "addr:postcode":"pe4 6na",
    "addr:street":"Staniland Way",
    "iso:country":"GB",
    "sg:address":"5 Staniland Way",
    "sg:city":"Peterborough",
    "sg:classifiers":[
        {
            "category":"Shopping",
            "subcategory":"Gifts & Souvenirs",
            "type":"Retail Goods"
        }
    ],
    "sg:phone":"+44 1733 321400",
    "sg:postcode":"PE4 6NA",
    "sg:province":"Cambridgeshire",
    "sg:tags":[
        "shop"
    ],
    "wof:name":"R & L Boothby",
    "wof:placetype":"venue"
},
  "geometry": {"coordinates":[-0.2685390115,52.6234474182],"type":"Point"}
}