{
  "type": "Feature",
  "properties": {
    "addr:full":"320 Old Farm Avenue Sidcup Kent DA15 8AR",
    "addr:housenumber":"320",
    "addr:postcode":"da15 8ar",
    "addr:street":"Old Farm Avenue",
    "iso:country":"GB",
    "sg:address":"320 Old Farm Avenue",
    "sg:city":"Sidcup",
    "sg:classifiers":[
        {
            "category":"Building & Trades",
            "subcategory":"Construction",
            "type":"Services"
        }
    ],
    "sg:phone":"+44 20 8309 0889",
    "sg:postcode":"DA15 8AR",
    "sg:province":"Kent",
    "sg:tags":[
        "builder"
    ],
    "wof:name":"D S Morris",
    "wof:placetype":"venue"
},
  "geometry": {"coordinates":[0.0825479999,51.4382858276],"type":"Point"}
}