{
  "type": "Feature",
  "properties": {
    "addr:full":"Unit 6 Southfield Rd Southam Warwickshire CV47 0FB",
    "addr:housenumber":"unit 6",
    "addr:postcode":"cv47 0fb",
    "addr:street":"Southfield Rd",
    "iso:country":"GB",
    "sg:address":"Unit 6 Southfield Rd",
    "sg:city":"Southam",
    "sg:classifiers":[
        {
            "category":"Professional",
            "subcategory":"Business Services",
            "type":"Services"
        }
    ],
    "sg:phone":"+44 1926 813043",
    "sg:postcode":"CV47 0FB",
    "sg:province":"Warwickshire",
    "sg:tags":[
        "agent",
        "manufacturers'"
    ],
    "wof:name":"Euromicrovision Co Ltd",
    "wof:placetype":"venue"
},
  "geometry": {"coordinates":[-1.3967469931,52.2448387146],"type":"Point"}
}