{
  "type": "Feature",
  "properties": {
    "iso:country":"GB",
    "sg:address":"30 New Street, Kilbarchan",
    "sg:city":"Johnstone",
    "sg:classifiers":[
        {
            "category":"Building & Trades",
            "subcategory":"Construction",
            "type":"Services"
        }
    ],
    "sg:phone":"+44 1505 702646",
    "sg:postcode":"PA10 2LN",
    "sg:province":"Renfrewshire",
    "sg:tags":[
        "roofing"
    ],
    "wof:name":"W S Borland",
    "wof:placetype":"venue"
},
  "geometry": {"coordinates":[-4.550116,55.838039],"type":"Point"}
}