{
  "type": "Feature",
  "properties": {
    "addr:full":"Ellesmere Court, Seymours Villas Penge Greater London SE20 8TY",
    "addr:postcode":"se20 8ty",
    "addr:street":"Ellesmere Court Seymours",
    "iso:country":"GB",
    "sg:address":"Ellesmere Court, Seymours Villas",
    "sg:city":"Penge",
    "sg:classifiers":[
        {
            "category":"Professional",
            "subcategory":"Advertising",
            "type":"Services"
        }
    ],
    "sg:phone":"+44 20 8659 3090",
    "sg:postcode":"SE20 8TY",
    "sg:province":"Greater London",
    "sg:tags":[
        "agency"
    ],
    "wof:name":"K-Trend Agency",
    "wof:placetype":"venue"
},
  "geometry": {"coordinates":[-0.066154,51.41008],"type":"Point"}
}