{
  "type": "Feature",
  "properties": {
    "iso:country":"GB",
    "sg:address":"Nortons Wood Lane",
    "sg:city":"Clevedon",
    "sg:classifiers":[
        {
            "category":"Manufacturing",
            "subcategory":"Building Materials",
            "type":"Manufacturing & Wholesale Goods"
        }
    ],
    "sg:phone":"+44 1275 873043",
    "sg:postcode":"BS21 7AE",
    "sg:province":"Somerset",
    "sg:tags":[
        "merchant",
        "builder"
    ],
    "wof:name":"Morrish Building & Garden Supplies",
    "wof:placetype":"venue"
},
  "geometry": {"coordinates":[-2.8257050514,51.4462928772],"type":"Point"}
}