{
  "type": "Feature",
  "properties": {
    "iso:country":"GB",
    "sg:address":"Bethal",
    "sg:city":"Bodorgan",
    "sg:classifiers":[
        {
            "category":"Autos & Motor Vehicles",
            "subcategory":"Fuel & Gas Station",
            "type":"Retail Goods"
        }
    ],
    "sg:postcode":"LL62 5NH",
    "sg:province":"Isle of Anglesey",
    "sg:tags":[
        "petrol",
        "filling"
    ],
    "wof:name":"Bodorgan Motors",
    "wof:placetype":"venue"
},
  "geometry": {"coordinates":[-4.394437,53.2061],"type":"Point"}
}