{
  "type": "Feature",
  "properties": {
    "iso:country":"GB",
    "sg:address":"17 The Slack",
    "sg:city":"Scunthorpe",
    "sg:classifiers":[
        {
            "category":"Building & Trades",
            "subcategory":"Plumbing",
            "type":"Services"
        }
    ],
    "sg:phone":"+44 1724 710698",
    "sg:postcode":"DN17 4LZ",
    "sg:province":"Lincolnshire",
    "sg:tags":[
        "heating"
    ],
    "wof:name":"Kevin W Maloney",
    "wof:placetype":"venue"
},
  "geometry": {"coordinates":[-0.8340809941,53.6124191284],"type":"Point"}
}