{
  "type": "Feature",
  "properties": {
    "iso:country":"GB",
    "sg:address":"15 Market Street",
    "sg:city":"Alnwick",
    "sg:classifiers":[
        {
            "category":"Home & Garden",
            "subcategory":"Hardware",
            "type":"Retail Goods"
        }
    ],
    "sg:postcode":"NE66 1SS",
    "sg:province":"Northumberland",
    "sg:tags":[
        "merchant",
        "ironmonger"
    ],
    "wof:name":"Reavell Bros Ltd.",
    "wof:placetype":"venue"
},
  "geometry": {"coordinates":[-1.706724,55.413063],"type":"Point"}
}