{
  "type": "Feature",
  "properties": {
    "iso:country":"GB",
    "sg:address":"83 Clerk Street",
    "sg:city":"Edinburgh",
    "sg:classifiers":[
        {
            "category":"Cafe",
            "type":"Food & Drink"
        }
    ],
    "sg:postcode":"EH8 9JG",
    "sg:province":"City of Edinburgh",
    "sg:tags":[
        "tea",
        "room"
    ],
    "wof:name":"Isobel's Cafe",
    "wof:placetype":"venue"
},
  "geometry": {"coordinates":[-3.181589,55.941341],"type":"Point"}
}