{
  "type": "Feature",
  "properties": {
    "iso:country":"GB",
    "sg:address":"6 Tower Place, West End",
    "sg:city":"Southampton",
    "sg:classifiers":[
        {
            "category":"Building & Trades",
            "subcategory":"Construction",
            "type":"Services"
        }
    ],
    "sg:postcode":"SO30 3DL",
    "sg:province":"Hampshire",
    "sg:tags":[
        "builder"
    ],
    "wof:name":"D Bryant",
    "wof:placetype":"venue"
},
  "geometry": {"coordinates":[-1.33591,50.92635],"type":"Point"}
}