{
  "type": "Feature",
  "properties": {
    "addr:full":"11 Richmond Place Brighton East Sussex BN2 9NA",
    "addr:housenumber":"11",
    "addr:postcode":"bn2 9na",
    "addr:street":"Richmond Place",
    "iso:country":"GB",
    "sg:address":"11 Richmond Place",
    "sg:city":"Brighton",
    "sg:classifiers":[
        {
            "category":"Real Estate",
            "subcategory":"Architect",
            "type":"Services"
        }
    ],
    "sg:postcode":"BN2 9NA",
    "sg:province":"East Sussex",
    "wof:name":"David Grey Associates",
    "wof:placetype":"venue"
},
  "geometry": {"coordinates":[-0.1342310011,50.8284034729],"type":"Point"}
}