{
  "type": "Feature",
  "properties": {
    "addr:full":"Argyle House, 29-31 Euston Road London Greater London NW1 2SD",
    "addr:housenumber":"29-31",
    "addr:postcode":"nw1 2sd",
    "addr:street":"Euston Road",
    "iso:country":"GB",
    "sg:address":"Argyle House, 29-31 Euston Road",
    "sg:city":"London",
    "sg:classifiers":[
        {
            "category":"Professional",
            "subcategory":"Computer Services",
            "type":"Services"
        }
    ],
    "sg:phone":"+44 20 7837 4800",
    "sg:postcode":"NW1 2SD",
    "sg:province":"Greater London",
    "sg:tags":[
        "consultant"
    ],
    "wof:name":"Direct Computer Training Ltd.",
    "wof:placetype":"venue"
},
  "geometry": {"coordinates":[-0.1309249997,51.5271644592],"type":"Point"}
}