{
  "type": "Feature",
  "properties": {
    "addr:full":"Unit 303, 16 Baldwins Gardens Clerkenwell Greater London EC1N 7RJ",
    "addr:housenumber":"303 16",
    "addr:postcode":"ec1n 7rj",
    "addr:street":"Baldwins Gardens",
    "iso:country":"GB",
    "sg:address":"Unit 303, 16 Baldwins Gardens",
    "sg:city":"Clerkenwell",
    "sg:classifiers":[
        {
            "category":"Real Estate",
            "subcategory":"Architect",
            "type":"Services"
        }
    ],
    "sg:phone":"+44 20 7430 9930",
    "sg:postcode":"EC1N 7RJ",
    "sg:province":"Greater London",
    "wof:name":"CGHP Architects",
    "wof:placetype":"venue"
},
  "geometry": {"coordinates":[-0.1096640006,51.5200881958],"type":"Point"}
}