{
  "type": "Feature",
  "properties": {
    "addr:full":"Unit C17 Malmo Clo, Tyne Tunnel Trad Est North Shields Tyne and Wear NE29 7SX",
    "addr:housenumber":"c17",
    "addr:postcode":"ne29 7sx",
    "iso:country":"GB",
    "sg:address":"Unit C17 Malmo Clo, Tyne Tunnel Trad Est",
    "sg:city":"North Shields",
    "sg:classifiers":[
        {
            "category":"Manufacturing",
            "subcategory":"Metals",
            "type":"Manufacturing & Wholesale Goods"
        }
    ],
    "sg:postcode":"NE29 7SX",
    "sg:province":"Tyne and Wear",
    "wof:name":"Precision Metal Polishers Ltd",
    "wof:placetype":"venue"
},
  "geometry": {"coordinates":[-1.48903,55.00631],"type":"Point"}
}