{
  "type": "Feature",
  "properties": {
    "addr:full":"Rear Of 527 High Rd, Off Curtis La Wembley Greater London HA0 2DH",
    "addr:housenumber":"527",
    "addr:postcode":"ha0 2dh",
    "addr:street":"High Rd Off Curtis La Wembley",
    "iso:country":"GB",
    "sg:address":"Rear Of 527 High Rd, Off Curtis La",
    "sg:city":"Wembley",
    "sg:classifiers":[
        {
            "category":"Retail",
            "subcategory":"Auto Repair",
            "type":"Services"
        }
    ],
    "sg:postcode":"HA0 2DH",
    "sg:province":"Greater London",
    "sg:tags":[
        "modification",
        "garage"
    ],
    "wof:name":"Carmichael,D I,",
    "wof:placetype":"venue"
},
  "geometry": {"coordinates":[-0.29787,51.551922],"type":"Point"}
}