{
  "type": "Feature",
  "properties": {
    "addr:full":"5 Fountain Street, Nailsworth Stroud Gloucestershire GL6 0BL",
    "addr:housenumber":"5",
    "addr:postcode":"gl6 0bl",
    "addr:street":"Fountain Street",
    "iso:country":"GB",
    "sg:address":"5 Fountain Street, Nailsworth",
    "sg:city":"Stroud",
    "sg:classifiers":[
        {
            "category":"Banks & Credit Unions",
            "subcategory":"Financial Services",
            "type":"Services"
        }
    ],
    "sg:phone":"+44 1453 833777",
    "sg:postcode":"GL6 0BL",
    "sg:province":"Gloucestershire",
    "sg:tags":[
        "building",
        "society"
    ],
    "wof:name":"Stroud & Swindon Building Society",
    "wof:placetype":"venue"
},
  "geometry": {"coordinates":[-2.218097,51.695396],"type":"Point"}
}