{
  "type": "Feature",
  "properties": {
    "addr:full":"11 Crescent Road Windermere Cumbria LA23 1EA",
    "addr:housenumber":"11",
    "addr:postcode":"la23 1ea",
    "addr:street":"Crescent Road",
    "iso:country":"GB",
    "sg:address":"11 Crescent Road",
    "sg:city":"Windermere",
    "sg:classifiers":[
        {
            "category":"Food & Beverages",
            "subcategory":"Liquor & Beverages",
            "type":"Retail Goods"
        }
    ],
    "sg:phone":"+44 15394 46891",
    "sg:postcode":"LA23 1EA",
    "sg:province":"Cumbria",
    "sg:tags":[
        "beer",
        "wine",
        "spirit",
        "wines"
    ],
    "wof:name":"Windermere Wine Stores Ltd.",
    "wof:placetype":"venue"
},
  "geometry": {"coordinates":[-2.9055299759,54.3785705566],"type":"Point"}
}