{
  "type": "Feature",
  "properties": {
    "iso:country":"GB",
    "sg:address":"Monkton Wyld Farm, Charmouth",
    "sg:city":"Bridport",
    "sg:classifiers":[
        {
            "category":"Farming",
            "subcategory":"Livestock Farm",
            "type":"Manufacturing & Wholesale Goods"
        },
        {
            "category":"Recreation",
            "subcategory":"Campground",
            "type":"Entertainment"
        }
    ],
    "sg:phone":"+44 1297 34525",
    "sg:postcode":"DT6 6DB",
    "sg:province":"Dorset",
    "sg:tags":[
        "caravan",
        "park",
        "others"
    ],
    "wof:name":"S S Kewley",
    "wof:placetype":"venue"
},
  "geometry": {"coordinates":[-2.9032599926,50.7386207581],"type":"Point"}
}