{
  "type": "Feature",
  "properties": {
    "iso:country":"GB",
    "sg:address":"38 The Vintners, Temple Farm Industrial Estate",
    "sg:city":"Southend-on-sea",
    "sg:classifiers":[
        {
            "category":"Home & Garden",
            "subcategory":"Building Materials",
            "type":"Retail Goods"
        },
        {
            "category":"Manufacturing",
            "subcategory":"Pottery",
            "type":"Manufacturing & Wholesale Goods"
        }
    ],
    "sg:phone":"+44 1702 468241",
    "sg:postcode":"SS2 5RZ",
    "sg:province":"Essex",
    "sg:tags":[
        "ventilator",
        "ventilation",
        "system"
    ],
    "wof:name":"Danhood Uk Sales & Marketing",
    "wof:placetype":"venue"
},
  "geometry": {"coordinates":[0.71052,51.563148],"type":"Point"}
}