{
  "type": "Feature",
  "properties": {
    "addr:full":"39 Victoria Road, Netley Abbey Southampton Hampshire SO31 5DG",
    "addr:housenumber":"39",
    "addr:postcode":"so31 5dg",
    "addr:street":"Victoria Road",
    "iso:country":"GB",
    "sg:address":"39 Victoria Road, Netley Abbey",
    "sg:city":"Southampton",
    "sg:classifiers":[
        {
            "category":"Organizations",
            "subcategory":"Membership Organization",
            "type":"Services"
        }
    ],
    "sg:phone":"+44 23 8045 3319",
    "sg:postcode":"SO31 5DG",
    "sg:province":"Hampshire",
    "sg:tags":[
        "club"
    ],
    "wof:name":"Netley Victoria Club & Institute",
    "wof:placetype":"venue"
},
  "geometry": {"coordinates":[-1.354507,50.874512],"type":"Point"}
}