{
  "type": "Feature",
  "properties": {
    "iso:country":"GB",
    "sg:address":"18 Avondale Road",
    "sg:city":"Southport",
    "sg:classifiers":[
        {
            "category":"Farming",
            "subcategory":"Nursery",
            "type":"Manufacturing & Wholesale Goods"
        },
        {
            "category":"Education",
            "subcategory":"Preschool",
            "type":"Public Place"
        }
    ],
    "sg:phone":"+44 1704 531256",
    "sg:postcode":"PR9 0ND",
    "sg:province":"Lancashire",
    "sg:tags":[
        "school",
        "creche"
    ],
    "wof:name":"Chatterbox Private Day Nursery",
    "wof:placetype":"venue"
},
  "geometry": {"coordinates":[-2.997879,53.655781],"type":"Point"}
}