{
  "type": "Feature",
  "properties": {
    "addr:full":"6 Shire Ct, Gloucester Cres Wigston Leicestershire LE18 4XJ",
    "addr:housenumber":"6",
    "addr:postcode":"le18 4xj",
    "addr:street":"Shire Ct;Cres",
    "iso:country":"GB",
    "sg:address":"6 Shire Ct, Gloucester Cres",
    "sg:city":"Wigston",
    "sg:classifiers":[
        {
            "category":"Food & Beverages",
            "subcategory":"Meat & Fish",
            "type":"Retail Goods"
        }
    ],
    "sg:phone":"+44 116 277 1199",
    "sg:postcode":"LE18 4XJ",
    "sg:province":"Leicestershire",
    "sg:tags":[
        "chip"
    ],
    "wof:name":"Premiere Fish Bar",
    "wof:placetype":"venue"
},
  "geometry": {"coordinates":[-1.138827,52.586498],"type":"Point"}
}