{
  "type": "Feature",
  "properties": {
    "addr:full":"51 Belsize Square Hampstead Greater London NW3 4HX",
    "addr:housenumber":"51",
    "addr:postcode":"nw3 4hx",
    "addr:street":"Belsize Square",
    "iso:country":"GB",
    "sg:address":"51 Belsize Square",
    "sg:city":"Hampstead",
    "sg:classifiers":[
        {
            "category":"Farming",
            "subcategory":"Nursery",
            "type":"Manufacturing & Wholesale Goods"
        },
        {
            "category":"Place Of Worship",
            "type":"Public Place"
        }
    ],
    "sg:phone":"+44 20 7431 3823",
    "sg:postcode":"NW3 4HX",
    "sg:province":"Greater London",
    "sg:tags":[
        "creche"
    ],
    "wof:name":"Belsize Square Synagogue Nursery School",
    "wof:placetype":"venue"
},
  "geometry": {"coordinates":[-0.17067,51.547459],"type":"Point"}
}