{
  "type": "Feature",
  "properties": {
    "iso:country":"GB",
    "sg:address":"3 Ellington Park",
    "sg:city":"Maidenhead",
    "sg:classifiers":[
        {
            "category":"Professional",
            "type":"Services"
        }
    ],
    "sg:phone":"+44 1628 629522",
    "sg:postcode":"SL6 7LQ",
    "sg:province":"Berkshire",
    "sg:tags":[
        "entertainer"
    ],
    "wof:name":"Pandora Childrens Entertainer",
    "wof:placetype":"venue"
},
  "geometry": {"coordinates":[-0.7257829905,51.5313949585],"type":"Point"}
}