{
  "type": "Feature",
  "properties": {
    "iso:country":"GB",
    "sg:address":"25 Pellau Rd",
    "sg:city":"Port Talbot",
    "sg:classifiers":[
        {
            "category":"Building & Trades",
            "subcategory":"Construction",
            "type":"Services"
        }
    ],
    "sg:phone":"+44 1639 895629",
    "sg:postcode":"SA13 2LF",
    "sg:province":"Neath Port Talbot",
    "sg:tags":[
        "builder"
    ],
    "wof:name":"P & L Building & Roofing",
    "wof:placetype":"venue"
},
  "geometry": {"coordinates":[-3.7586889267,51.5782394409],"type":"Point"}
}