{
  "type": "Feature",
  "properties": {
    "addr:full":"35 The Crescent, Sandgate Folkestone Kent CT20 3EE",
    "addr:housenumber":"35",
    "addr:postcode":"ct20 3ee",
    "addr:street":"The Crescent Sandgate",
    "iso:country":"GB",
    "sg:address":"35 The Crescent, Sandgate",
    "sg:city":"Folkestone",
    "sg:classifiers":[
        {
            "category":"Shopping",
            "subcategory":"Books",
            "type":"Retail Goods"
        }
    ],
    "sg:phone":"+44 1303 220277",
    "sg:postcode":"CT20 3EE",
    "sg:province":"Kent",
    "wof:name":"Japan Library",
    "wof:placetype":"venue"
},
  "geometry": {"coordinates":[1.144213,51.07391],"type":"Point"}
}