{
  "type": "Feature",
  "properties": {
    "addr:full":"223 High Street Watford Hertfordshire WD17 2HQ",
    "addr:housenumber":"223",
    "addr:postcode":"wd17 2hq",
    "addr:street":"High Street",
    "iso:country":"GB",
    "sg:address":"223 High Street",
    "sg:city":"Watford",
    "sg:classifiers":[
        {
            "category":"Autos & Motor Vehicles",
            "subcategory":"Auto Supplies",
            "type":"Retail Goods"
        }
    ],
    "sg:phone":"+44 1923 234666",
    "sg:postcode":"WD17 2HQ",
    "sg:province":"Hertfordshire",
    "sg:tags":[
        "tyre"
    ],
    "wof:name":"Stapleton Tyre & Exhaust Centre",
    "wof:placetype":"venue"
},
  "geometry": {"coordinates":[-0.3919290006,51.6530609131],"type":"Point"}
}