{
  "type": "Feature",
  "properties": {
    "addr:full":"3 Rochester Close, Weir Bacup Lancashire OL13 8RN",
    "addr:housenumber":"3",
    "addr:postcode":"weir;ol13 8rn",
    "addr:street":"Rochester Close",
    "iso:country":"GB",
    "sg:address":"3 Rochester Close, Weir",
    "sg:city":"Bacup",
    "sg:classifiers":[
        {
            "category":"Building & Trades",
            "subcategory":"Cleaning & Sanitation",
            "type":"Services"
        }
    ],
    "sg:phone":"+44 1706 876981",
    "sg:postcode":"OL13 8RN",
    "sg:province":"Lancashire",
    "sg:tags":[
        "commercial"
    ],
    "wof:name":"Crown Cleaning Services",
    "wof:placetype":"venue"
},
  "geometry": {"coordinates":[-2.1945939064,53.72473526],"type":"Point"}
}