{
  "type": "Feature",
  "properties": {
    "addr:full":"44 Moir Green Aberdeen Aberdeen City AB16 7GS",
    "addr:housenumber":"44",
    "addr:postcode":"ab16 7gs",
    "addr:street":"Moir Green",
    "iso:country":"GB",
    "sg:address":"44 Moir Green",
    "sg:city":"Aberdeen",
    "sg:classifiers":[
        {
            "category":"Government",
            "subcategory":"Post Office",
            "type":"Public Place"
        }
    ],
    "sg:phone":"+44 845 722 3344",
    "sg:postcode":"AB16 7GS",
    "sg:province":"Aberdeen City",
    "wof:name":"Cummings Park Sub Post Office",
    "wof:placetype":"venue"
},
  "geometry": {"coordinates":[-2.1444890499,57.1633682251],"type":"Point"}
}