{
  "type": "Feature",
  "properties": {
    "iso:country":"GB",
    "sg:address":"80 Moyser Rd",
    "sg:city":"London",
    "sg:classifiers":[
        {
            "category":"Shopping",
            "subcategory":"News",
            "type":"Retail Goods"
        }
    ],
    "sg:postcode":"SW16 6SQ",
    "sg:province":"Greater London",
    "sg:tags":[
        "newsagent"
    ],
    "wof:name":"Amber News",
    "wof:placetype":"venue"
},
  "geometry": {"coordinates":[-0.147537,51.424259],"type":"Point"}
}