{
  "type": "Feature",
  "properties": {
    "iso:country":"GB",
    "sg:address":"31 Cloudberry, Walnut Tree",
    "sg:city":"Milton Keynes",
    "sg:classifiers":[
        {
            "category":"Building & Trades",
            "subcategory":"Plumbing",
            "type":"Services"
        }
    ],
    "sg:postcode":"MK7 7DL",
    "sg:province":"Buckinghamshire",
    "sg:tags":[
        "heating"
    ],
    "wof:name":"Central Heating Services",
    "wof:placetype":"venue"
},
  "geometry": {"coordinates":[-0.699636,52.022507],"type":"Point"}
}