{
  "type": "Feature",
  "properties": {
    "iso:country":"GB",
    "sg:address":"The Gunshop, Lionmead, Shottermill",
    "sg:city":"Haslemere",
    "sg:classifiers":[
        {
            "category":"Shopping",
            "subcategory":"Hobbies, Toys, & Games",
            "type":"Retail Goods"
        }
    ],
    "sg:phone":"+44 1428 651913",
    "sg:postcode":"GU27 1LF",
    "sg:province":"Hampshire",
    "sg:tags":[
        "gunsmith"
    ],
    "wof:name":"Richard Wells Sporting Guns",
    "wof:placetype":"venue"
},
  "geometry": {"coordinates":[-0.740044,51.089066],"type":"Point"}
}