{
  "type": "Feature",
  "properties": {
    "addr:full":"Eastington Park Farm, Churchend, Eastington Stonehouse Gloucestershire GL10 3SB",
    "addr:postcode":"gl10 3sb",
    "addr:street":"Eastington;Eastington;Gloucestershire",
    "iso:country":"GB",
    "sg:address":"Eastington Park Farm, Churchend, Eastington",
    "sg:city":"Stonehouse",
    "sg:classifiers":[
        {
            "category":"Farming",
            "subcategory":"Dairy Farm",
            "type":"Manufacturing & Wholesale Goods"
        }
    ],
    "sg:phone":"+44 1453 822214",
    "sg:postcode":"GL10 3SB",
    "sg:province":"Gloucestershire",
    "sg:tags":[
        "farmer"
    ],
    "wof:name":"T & J S WYATT",
    "wof:placetype":"venue"
},
  "geometry": {"coordinates":[-2.325842,51.746082],"type":"Point"}
}