{
  "type": "Feature",
  "properties": {
    "addr:full":"Canalside Workshop, Cropredy Banbury Northamptonshire OX17 1PQ",
    "addr:housenumber":"cropredy",
    "addr:postcode":"ox17 1pq",
    "iso:country":"GB",
    "sg:address":"Canalside Workshop, Cropredy",
    "sg:city":"Banbury",
    "sg:classifiers":[
        {
            "category":"Shopping",
            "subcategory":"Bicycles & Sporting Goods",
            "type":"Retail Goods"
        }
    ],
    "sg:postcode":"OX17 1PQ",
    "sg:province":"Northamptonshire",
    "sg:tags":[
        "riding",
        "saddlery",
        "wear"
    ],
    "wof:name":"Pan Designs",
    "wof:placetype":"venue"
},
  "geometry": {"coordinates":[-1.3196979761,52.1168708801],"type":"Point"}
}