{
  "type": "Feature",
  "properties": {
    "addr:full":"Unit 3 Gunhills Lane Industrial Estate Doncaster South Yorkshire DN3 3EB",
    "addr:housenumber":"unit 3;estate",
    "addr:postcode":"dn3 3eb",
    "addr:street":"Gunhills Lane Industrial",
    "iso:country":"GB",
    "sg:address":"Unit 3 Gunhills Lane Industrial Estate",
    "sg:city":"Doncaster",
    "sg:classifiers":[
        {
            "category":"Retail",
            "subcategory":"Auto Repair",
            "type":"Services"
        }
    ],
    "sg:phone":"+44 1302 835293",
    "sg:postcode":"DN3 3EB",
    "sg:province":"South Yorkshire",
    "sg:tags":[
        "retreading",
        "tyre"
    ],
    "wof:name":"E J Cloghier",
    "wof:placetype":"venue"
},
  "geometry": {"coordinates":[-1.0455139875,53.5386695862],"type":"Point"}
}