{
  "type": "Feature",
  "properties": {
    "addr:full":"4 Trowbridge Retail Park, Bradley Road Trowbridge Wiltshire BA14 0RQ",
    "addr:housenumber":"4",
    "addr:postcode":"ba14 0rq",
    "addr:street":"Trowbridge Retail Park Bradley Road",
    "iso:country":"GB",
    "sg:address":"4 Trowbridge Retail Park, Bradley Road",
    "sg:city":"Trowbridge",
    "sg:classifiers":[
        {
            "category":"Home & Garden",
            "subcategory":"Furniture",
            "type":"Retail Goods"
        }
    ],
    "sg:phone":"+44 1225 777499",
    "sg:postcode":"BA14 0RQ",
    "sg:province":"Wiltshire",
    "wof:name":"Mfi Furniture Centre",
    "wof:placetype":"venue"
},
  "geometry": {"coordinates":[-2.208374,51.315342],"type":"Point"}
}