{
  "type": "Feature",
  "properties": {
    "iso:country":"GB",
    "sg:address":"Wolverhampton Rd, Heath Town",
    "sg:city":"Wolverhampton",
    "sg:classifiers":[
        {
            "category":"Food & Beverages",
            "subcategory":"Supermarket",
            "type":"Retail Goods"
        }
    ],
    "sg:phone":"+44 1902 458090",
    "sg:postcode":"WV10 0QR",
    "sg:province":"Staffordshire",
    "wof:name":"Kwik Save Foodstores",
    "wof:placetype":"venue"
},
  "geometry": {"coordinates":[-2.095994,52.596634],"type":"Point"}
}