{
  "type": "Feature",
  "properties": {
    "addr:full":"Upper Park Street Cheltenham Gloucestershire GL52 6SA",
    "addr:postcode":"gl52 6sa",
    "addr:street":"Upper Park Street",
    "iso:country":"GB",
    "sg:address":"Upper Park Street",
    "sg:city":"Cheltenham",
    "sg:classifiers":[
        {
            "category":"Organizations",
            "subcategory":"Community Association",
            "type":"Services"
        },
        {
            "category":"Organizations",
            "subcategory":"Membership Organization",
            "type":"Services"
        }
    ],
    "sg:phone":"+44 1242 522590",
    "sg:postcode":"GL52 6SA",
    "sg:province":"Gloucestershire",
    "sg:tags":[
        "club",
        "social"
    ],
    "wof:name":"Cheltenham Motor Club",
    "wof:placetype":"venue"
},
  "geometry": {"coordinates":[-2.062577,51.89304],"type":"Point"}
}