{
  "type": "Feature",
  "properties": {
    "addr:full":"24 Brick Lane London Greater London E1 6RF",
    "addr:housenumber":"24",
    "addr:postcode":"e1 6rf",
    "addr:street":"Brick Lane",
    "iso:country":"GB",
    "sg:address":"24 Brick Lane",
    "sg:city":"London",
    "sg:classifiers":[
        {
            "category":"Manufacturing",
            "subcategory":"Textiles",
            "type":"Manufacturing & Wholesale Goods"
        }
    ],
    "sg:phone":"+44 20 7247 7776",
    "sg:postcode":"E1 6RF",
    "sg:province":"Greater London",
    "sg:tags":[
        "merchant",
        "agent"
    ],
    "wof:name":"Z Butt Textiles",
    "wof:placetype":"venue"
},
  "geometry": {"coordinates":[-0.0713689998,51.5182228088],"type":"Point"}
}