{
  "type": "Feature",
  "properties": {
    "iso:country":"GB",
    "sg:address":"92a Broad Street",
    "sg:city":"Canterbury",
    "sg:classifiers":[
        {
            "category":"Professional",
            "type":"Services"
        },
        {
            "category":"Organizations",
            "subcategory":"Non-profit Organization",
            "type":"Services"
        }
    ],
    "sg:phone":"+44 1227 462062",
    "sg:postcode":"CT1 2LU",
    "sg:province":"Kent",
    "sg:tags":[
        "voluntary",
        "archaeologist",
        "organisation",
        "charity"
    ],
    "wof:name":"Canterbury Archaeological Trust Ltd.",
    "wof:placetype":"venue"
},
  "geometry": {"coordinates":[1.084665,51.281353],"type":"Point"}
}