{
  "type": "Feature",
  "properties": {
    "addr:full":"7 The Ruddings Selby East Riding of Yorkshire YO8 9AG",
    "addr:housenumber":"7",
    "addr:postcode":"yo8 9ag",
    "addr:street":"Selby",
    "iso:country":"GB",
    "sg:address":"7 The Ruddings",
    "sg:city":"Selby",
    "sg:classifiers":[
        {
            "category":"Professional",
            "subcategory":"Accounting & Tax Preparation",
            "type":"Services"
        }
    ],
    "sg:postcode":"YO8 9AG",
    "sg:province":"East Riding of Yorkshire",
    "sg:tags":[
        "accountant"
    ],
    "wof:name":"P C Associates",
    "wof:placetype":"venue"
},
  "geometry": {"coordinates":[-1.081165,53.777729],"type":"Point"}
}