{
  "type": "Feature",
  "properties": {
    "iso:country":"GB",
    "sg:address":"Tamar House, Thournbury Road, Estover",
    "sg:city":"Plymouth",
    "sg:classifiers":[
        {
            "category":"Shopping",
            "subcategory":"Pharmacy",
            "type":"Retail Goods"
        }
    ],
    "sg:phone":"+44 1752 730311",
    "sg:postcode":"PL6 7PW",
    "sg:province":"Devon",
    "sg:tags":[
        "pharmaceutical"
    ],
    "wof:name":"Stafford-Miller Ltd.",
    "wof:placetype":"venue"
},
  "geometry": {"coordinates":[-4.0951042175,50.4201812744],"type":"Point"}
}