{
  "type": "Feature",
  "properties": {
    "addr:full":"Hill Farm, Slamannan Falkirk Falkirk FK1 3DJ",
    "addr:postcode":"fk1 3dj",
    "addr:street":"Hill;Slamannan",
    "iso:country":"GB",
    "sg:address":"Hill Farm, Slamannan",
    "sg:city":"Falkirk",
    "sg:classifiers":[
        {
            "category":"Manufacturing",
            "subcategory":"Building Materials",
            "type":"Manufacturing & Wholesale Goods"
        }
    ],
    "sg:phone":"+44 1324 851005",
    "sg:postcode":"FK1 3DJ",
    "sg:province":"Falkirk",
    "sg:tags":[
        "concrete",
        "product"
    ],
    "wof:name":"Acheson & Glover Pre-cast",
    "wof:placetype":"venue"
},
  "geometry": {"coordinates":[-3.8340189457,55.9401283264],"type":"Point"}
}