{
  "type": "Feature",
  "properties": {
    "addr:full":"18 Cavendish Place Newport Isle of Wight PO30 5AE",
    "addr:housenumber":"18",
    "addr:postcode":"po30 5ae",
    "addr:street":"Cavendish Place",
    "iso:country":"GB",
    "sg:address":"18 Cavendish Place",
    "sg:city":"Newport",
    "sg:classifiers":[
        {
            "category":"Recreation",
            "subcategory":"Dog Park",
            "type":"Entertainment"
        }
    ],
    "sg:postcode":"PO30 5AE",
    "sg:province":"Isle of Wight",
    "wof:name":"A B C Grooming",
    "wof:placetype":"venue"
},
  "geometry": {"coordinates":[-1.3014760017,50.6980018616],"type":"Point"}
}