{
  "type": "Feature",
  "properties": {
    "addr:full":"7 The Square Forfar Angus DD8 2PZ",
    "addr:housenumber":"7",
    "addr:postcode":"dd8 2pz",
    "addr:street":"The Square",
    "iso:country":"GB",
    "sg:address":"7 The Square",
    "sg:city":"Forfar",
    "sg:classifiers":[
        {
            "category":"Food & Beverages",
            "subcategory":"Groceries & Convenience Stores",
            "type":"Retail Goods"
        }
    ],
    "sg:phone":"+44 1307 818183",
    "sg:postcode":"DD8 2PZ",
    "sg:province":"Angus",
    "sg:tags":[
        "merchant",
        "potato"
    ],
    "wof:name":"Worthdraw",
    "wof:placetype":"venue"
},
  "geometry": {"coordinates":[-2.7688760757,56.6288795471],"type":"Point"}
}