{
  "type": "Feature",
  "properties": {
    "iso:country":"GB",
    "sg:address":"132 Elphinston Rd, Lloyds Park, Walthamstow",
    "sg:city":"Walthamstow",
    "sg:classifiers":[
        {
            "category":"Professional",
            "subcategory":"Engineering",
            "type":"Services"
        }
    ],
    "sg:phone":"+44 20 8523 2755",
    "sg:postcode":"E17 5EX",
    "sg:province":"Greater London",
    "sg:tags":[
        "contractor",
        "electrical",
        "engineer"
    ],
    "wof:name":"Property Maintenance",
    "wof:placetype":"venue"
},
  "geometry": {"coordinates":[-0.0251850002,51.5952949524],"type":"Point"}
}