{
  "type": "Feature",
  "properties": {
    "addr:full":"Lowen Road Rainham Essex RM13 8QR",
    "addr:postcode":"rm13 8qr",
    "addr:street":"Lowen Road",
    "iso:country":"GB",
    "sg:address":"Lowen Road",
    "sg:city":"Rainham",
    "sg:classifiers":[
        {
            "category":"Education",
            "subcategory":"School",
            "type":"Public Place"
        }
    ],
    "sg:phone":"+44 1708 558613",
    "sg:postcode":"RM13 8QR",
    "sg:province":"Essex",
    "sg:tags":[
        "local",
        "authority"
    ],
    "wof:name":"Newtons Primary School",
    "wof:placetype":"venue"
},
  "geometry": {"coordinates":[0.1685249954,51.528755188],"type":"Point"}
}