{
  "type": "Feature",
  "properties": {
    "addr:full":"Knight Court, 70 Causewayhead Penzance Cornwall TR18 2SR",
    "addr:housenumber":"70",
    "addr:postcode":"tr18 2sr",
    "addr:street":"Knight;Causewayhead",
    "iso:country":"GB",
    "sg:address":"Knight Court, 70 Causewayhead",
    "sg:city":"Penzance",
    "sg:classifiers":[
        {
            "category":"Professional",
            "type":"Services"
        }
    ],
    "sg:phone":"+44 1736 363326",
    "sg:postcode":"TR18 2SR",
    "sg:province":"Cornwall",
    "sg:tags":[
        "directory",
        "pub"
    ],
    "wof:name":"Cornwall Locally Directories",
    "wof:placetype":"venue"
},
  "geometry": {"coordinates":[-5.538044,50.119247],"type":"Point"}
}