{
  "type": "Feature",
  "properties": {
    "iso:country":"GB",
    "sg:address":"10 Acorn Court",
    "sg:city":"Glenrothes",
    "sg:classifiers":[
        {
            "category":"Professional",
            "subcategory":"Lawyer & Legal Services",
            "type":"Services"
        }
    ],
    "sg:phone":"+44 1592 756449",
    "sg:postcode":"KY7 5LZ",
    "sg:province":"Fife",
    "sg:tags":[
        "solicitor"
    ],
    "wof:name":"Yvonne McKenna",
    "wof:placetype":"venue"
},
  "geometry": {"coordinates":[-3.162959,56.19783],"type":"Point"}
}