{
  "type": "Feature",
  "properties": {
    "iso:country":"GB",
    "sg:address":"Loscoe-denby Lane, Loscoe",
    "sg:city":"Heanor",
    "sg:classifiers":[
        {
            "category":"Education",
            "subcategory":"School",
            "type":"Public Place"
        }
    ],
    "sg:phone":"+44 1773 713396",
    "sg:postcode":"DE75 7RW",
    "sg:province":"Derbyshire",
    "sg:tags":[
        "local",
        "authority"
    ],
    "wof:name":"C Loscoe of E Primary School",
    "wof:placetype":"venue"
},
  "geometry": {"coordinates":[-1.3534339666,53.0137367249],"type":"Point"}
}