{
  "type": "Feature",
  "properties": {
    "iso:country":"GB",
    "sg:address":"8 Ascot Drive",
    "sg:city":"Doncaster",
    "sg:classifiers":[
        {
            "category":"Retail",
            "subcategory":"Driving School",
            "type":"Services"
        }
    ],
    "sg:phone":"+44 1302 785786",
    "sg:postcode":"DN5 8QA",
    "sg:province":"South Yorkshire",
    "wof:name":"Andy Wallace",
    "wof:placetype":"venue"
},
  "geometry": {"coordinates":[-1.176678,53.535496],"type":"Point"}
}