{
  "type": "Feature",
  "properties": {
    "addr:full":"Laurel Rise, Dorchester Hill, Blandford St Mary Blandford Forum Dorset DT11 9AB",
    "addr:postcode":"dt11 9ab",
    "addr:street":"Laurel Rise Dorchester Hill Blandford St",
    "iso:country":"GB",
    "sg:address":"Laurel Rise, Dorchester Hill, Blandford St Mary",
    "sg:city":"Blandford Forum",
    "sg:classifiers":[
        {
            "category":"Professional",
            "subcategory":"Management & Consulting",
            "type":"Services"
        },
        {
            "category":"Banks & Credit Unions",
            "subcategory":"Financial Services",
            "type":"Services"
        }
    ],
    "sg:phone":"+44 1258 454031",
    "sg:postcode":"DT11 9AB",
    "sg:province":"Dorset",
    "sg:tags":[
        "tied",
        "consultant",
        "agent",
        "business"
    ],
    "wof:name":"Square Route Solutions Ltd.",
    "wof:placetype":"venue"
},
  "geometry": {"coordinates":[-2.0672090054,50.8278884888],"type":"Point"}
}