{
  "type": "Feature",
  "properties": {
    "iso:country":"GB",
    "sg:address":"32 The St",
    "sg:city":"Reading",
    "sg:classifiers":[
        {
            "category":"Building & Trades",
            "subcategory":"Plumbing",
            "type":"Services"
        }
    ],
    "sg:postcode":"RG7 4LW",
    "sg:province":"Berkshire",
    "sg:tags":[
        "heating"
    ],
    "wof:name":"A Y S Plumbing & Heating",
    "wof:placetype":"venue"
},
  "geometry": {"coordinates":[-1.153128,51.383312],"type":"Point"}
}