{
  "type": "Feature",
  "properties": {
    "addr:full":"Vicarage, 99 Chatham St Stockport Cheshire SK3 9EG",
    "addr:housenumber":"99",
    "addr:postcode":"sk3 9eg",
    "addr:street":"Chatham St",
    "iso:country":"GB",
    "sg:address":"Vicarage, 99 Chatham St",
    "sg:city":"Stockport",
    "sg:classifiers":[
        {
            "category":"Place Of Worship",
            "type":"Public Place"
        }
    ],
    "sg:phone":"+44 161 480 5515",
    "sg:postcode":"SK3 9EG",
    "sg:province":"Cheshire",
    "wof:name":"St Matthews Church",
    "wof:placetype":"venue"
},
  "geometry": {"coordinates":[-2.1615159512,53.4084091187],"type":"Point"}
}