{
  "type": "Feature",
  "properties": {
    "iso:country":"GB",
    "sg:address":"27 Brookway, North Cheshire Trading Est",
    "sg:city":"Birkenhead",
    "sg:classifiers":[
        {
            "category":"Manufacturing",
            "subcategory":"Building Materials",
            "type":"Manufacturing & Wholesale Goods"
        }
    ],
    "sg:phone":"+44 151 608 2578",
    "sg:postcode":"L43 3DS",
    "sg:province":"Merseyside",
    "sg:tags":[
        "stonemason"
    ],
    "wof:name":"David Williams",
    "wof:placetype":"venue"
},
  "geometry": {"coordinates":[-3.02549,53.392559],"type":"Point"}
}