{
  "type": "Feature",
  "properties": {
    "iso:country":"GB",
    "sg:address":"8th Floor Hillgate House, 26 Old Bailey",
    "sg:city":"London",
    "sg:classifiers":[
        {
            "category":"Education",
            "subcategory":"Special Training",
            "type":"Public Place"
        }
    ],
    "sg:phone":"+44 1732 467300",
    "sg:postcode":"EC4M 7QA",
    "sg:province":"Greater London",
    "sg:tags":[
        "product",
        "centre"
    ],
    "wof:name":"C I T B",
    "wof:placetype":"venue"
},
  "geometry": {"coordinates":[-0.102525,51.514912],"type":"Point"}
}