{
  "type": "Feature",
  "properties": {
    "iso:country":"GB",
    "sg:address":"17-19 Rabling Road",
    "sg:city":"Swanage",
    "sg:classifiers":[
        {
            "category":"Social Services",
            "subcategory":"Retirement Home",
            "type":"Services"
        },
        {
            "category":"Real Estate",
            "subcategory":"Real Estate Agent",
            "type":"Services"
        }
    ],
    "sg:postcode":"BH19 1EB",
    "sg:province":"Dorset",
    "sg:tags":[
        "rest"
    ],
    "wof:name":"Weyhill Rest Home",
    "wof:placetype":"venue"
},
  "geometry": {"coordinates":[-1.961096,50.612431],"type":"Point"}
}