{
  "type": "Feature",
  "properties": {
    "addr:full":"The Old Church, Chittoe Chippenham Wiltshire SN15 2EL",
    "addr:postcode":"sn15 2el",
    "addr:street":"Chittoe",
    "iso:country":"GB",
    "sg:address":"The Old Church, Chittoe",
    "sg:city":"Chippenham",
    "sg:classifiers":[
        {
            "category":"Professional",
            "subcategory":"Management & Consulting",
            "type":"Services"
        }
    ],
    "sg:phone":"+44 1380 850334",
    "sg:postcode":"SN15 2EL",
    "sg:province":"Wiltshire",
    "sg:tags":[
        "consultant",
        "business"
    ],
    "wof:name":"Team Work Consulting Group",
    "wof:placetype":"venue"
},
  "geometry": {"coordinates":[-2.0641639233,51.3987045288],"type":"Point"}
}