{
  "type": "Feature",
  "properties": {
    "addr:full":"85 Pallance Road Cowes Isle of Wight PO31 8LS",
    "addr:housenumber":"85",
    "addr:postcode":"po31 8ls",
    "addr:street":"Pallance Road",
    "iso:country":"GB",
    "sg:address":"85 Pallance Road",
    "sg:city":"Cowes",
    "sg:classifiers":[
        {
            "category":"Bars & Pubs",
            "type":"Food & Drink"
        }
    ],
    "sg:phone":"+44 1983 298024",
    "sg:postcode":"PO31 8LS",
    "sg:province":"Isle of Wight",
    "sg:tags":[
        "pubs",
        "house",
        "inn",
        "public",
        "activity"
    ],
    "sg:website":"http://www.tjoy.co.uk",
    "wof:name":"The Travellers Joy",
    "wof:placetype":"venue"
},
  "geometry": {"coordinates":[-1.321534,50.740788],"type":"Point"}
}