{
  "type": "Feature",
  "properties": {
    "addr:full":"Maes Y Llan, Ruabon Wrexham Wrexham LL14 6AD",
    "addr:postcode":"ll14 6ad",
    "addr:street":"Maes Y Llan Ruabon",
    "iso:country":"GB",
    "sg:address":"Maes Y Llan, Ruabon",
    "sg:city":"Wrexham",
    "sg:classifiers":[
        {
            "category":"Shopping",
            "subcategory":"Pets & Pet Supplies",
            "type":"Retail Goods"
        },
        {
            "category":"Shopping",
            "type":"Retail Goods"
        }
    ],
    "sg:phone":"+44 1978 821707",
    "sg:postcode":"LL14 6AD",
    "sg:province":"Wrexham",
    "sg:tags":[
        "food",
        "merchant"
    ],
    "wof:name":"Norman Blake",
    "wof:placetype":"venue"
},
  "geometry": {"coordinates":[-3.0391139984,52.9874382019],"type":"Point"}
}