{
  "type": "Feature",
  "properties": {
    "iso:country":"GB",
    "sg:address":"19-23 Canute Road",
    "sg:city":"Southampton",
    "sg:classifiers":[
        {
            "category":"Professional",
            "subcategory":"Employment Agencies",
            "type":"Services"
        }
    ],
    "sg:phone":"+44 23 8022 3546",
    "sg:postcode":"SO14 3FJ",
    "sg:province":"Hampshire",
    "sg:tags":[
        "consultant"
    ],
    "wof:name":"Sealife Ltd.",
    "wof:placetype":"venue"
},
  "geometry": {"coordinates":[-1.3930720091,50.8972091675],"type":"Point"}
}