{
  "type": "Feature",
  "properties": {
    "iso:country":"GB",
    "sg:address":"75 Raglan Road",
    "sg:city":"Leeds",
    "sg:classifiers":[
        {
            "category":"Fast Food",
            "type":"Food & Drink"
        }
    ],
    "sg:phone":"+44 113 242 5672",
    "sg:postcode":"LS2 9DZ",
    "sg:province":"West Yorkshire",
    "sg:tags":[
        "away",
        "meal",
        "outlet",
        "take"
    ],
    "wof:name":"Pizza Milano",
    "wof:placetype":"venue"
},
  "geometry": {"coordinates":[-1.555978,53.811134],"type":"Point"}
}