{
  "type": "Feature",
  "properties": {
    "iso:country":"GB",
    "sg:address":"Highfield Farm, Highfield Lane, Newton Road",
    "sg:city":"Warrington",
    "sg:classifiers":[
        {
            "category":"Home & Garden",
            "subcategory":"Garden Supply",
            "type":"Retail Goods"
        },
        {
            "category":"Farming",
            "subcategory":"Livestock Farm",
            "type":"Manufacturing & Wholesale Goods"
        }
    ],
    "sg:phone":"+44 1925 226180",
    "sg:postcode":"WA3 1NY",
    "sg:province":"Cheshire",
    "sg:tags":[
        "bulb",
        "grower",
        "others"
    ],
    "wof:name":"Worlsley Bros",
    "wof:placetype":"venue"
},
  "geometry": {"coordinates":[-2.58328,53.45993],"type":"Point"}
}