{
  "type": "Feature",
  "properties": {
    "addr:full":"Unit 6a Alfred Court, Saxon Business Park, Hanbury Road Bromsgrove Worcestershire B60 4AD",
    "addr:housenumber":"unit 6a",
    "addr:postcode":"b60 4ad",
    "addr:street":"Alfred Court Saxon Business Park Hanbury Road",
    "iso:country":"GB",
    "sg:address":"Unit 6a Alfred Court, Saxon Business Park, Hanbury Road",
    "sg:city":"Bromsgrove",
    "sg:classifiers":[
        {
            "category":"Manufacturing",
            "subcategory":"Tools & Machinery",
            "type":"Manufacturing & Wholesale Goods"
        }
    ],
    "sg:phone":"+44 1527 570977",
    "sg:postcode":"B60 4AD",
    "sg:province":"Worcestershire",
    "sg:tags":[
        "manufacture",
        "supply",
        "powertools",
        "design",
        "maker",
        "manufacturer"
    ],
    "wof:name":"Locton Ltd",
    "wof:placetype":"venue"
},
  "geometry": {"coordinates":[-2.055703,52.2729],"type":"Point"}
}