{
  "type": "Feature",
  "properties": {
    "addr:full":"1 Tolcarne Road Newquay Cornwall TR7 2NQ",
    "addr:housenumber":"1",
    "addr:postcode":"tr7 2nq",
    "addr:street":"Tolcarne Road",
    "iso:country":"GB",
    "sg:address":"1 Tolcarne Road",
    "sg:city":"Newquay",
    "sg:classifiers":[
        {
            "category":"Travel",
            "subcategory":"Hotels & Motels",
            "type":"Entertainment"
        }
    ],
    "sg:phone":"+44 1637 874215",
    "sg:postcode":"TR7 2NQ",
    "sg:province":"Cornwall",
    "wof:name":"The Sea Scape Hotel",
    "wof:placetype":"venue"
},
  "geometry": {"coordinates":[-5.07509,50.415997],"type":"Point"}
}