{
  "type": "Feature",
  "properties": {
    "addr:full":"P O Box 3770, Charter Court, New Comen Way Colchester Essex CO4 4YH",
    "addr:housenumber":"p o;3770",
    "addr:postcode":"co4 4yh",
    "addr:street":"Charter Court;Comen Way",
    "iso:country":"GB",
    "sg:address":"P O Box 3770, Charter Court, New Comen Way",
    "sg:city":"Colchester",
    "sg:classifiers":[
        {
            "category":"Banks & Credit Unions",
            "subcategory":"Bank",
            "type":"Services"
        }
    ],
    "sg:phone":"+44 1206 284628",
    "sg:postcode":"CO4 4YH",
    "sg:province":"Essex",
    "wof:name":"Barclays Bank Plc",
    "wof:placetype":"venue"
},
  "geometry": {"coordinates":[0.9133599997,51.924331665],"type":"Point"}
}