{
  "type": "Feature",
  "properties": {
    "addr:full":"31 Marine Parade Lowestoft Suffolk NR33 0QN",
    "addr:housenumber":"31",
    "addr:postcode":"nr33 0qn",
    "addr:street":"Marine Parade",
    "iso:country":"GB",
    "sg:address":"31 Marine Parade",
    "sg:city":"Lowestoft",
    "sg:classifiers":[
        {
            "category":"Travel",
            "subcategory":"Hotels & Motels",
            "type":"Entertainment"
        }
    ],
    "sg:postcode":"NR33 0QN",
    "sg:province":"Suffolk",
    "sg:tags":[
        "house",
        "guest"
    ],
    "wof:name":"Wavecrest",
    "wof:placetype":"venue"
},
  "geometry": {"coordinates":[1.747365,52.469837],"type":"Point"}
}