{
  "type": "Feature",
  "properties": {
    "addr:full":"13 Ardmore Avenue, Broughty Ferry Dundee Angus DD5 2TU",
    "addr:housenumber":"13",
    "addr:postcode":"dd5 2tu",
    "addr:street":"Ardmore Avenue",
    "iso:country":"GB",
    "sg:address":"13 Ardmore Avenue, Broughty Ferry",
    "sg:city":"Dundee",
    "sg:classifiers":[
        {
            "category":"Professional",
            "type":"Services"
        }
    ],
    "sg:postcode":"DD5 2TU",
    "sg:province":"Angus",
    "sg:tags":[
        "caterer"
    ],
    "wof:name":"Catering Personally",
    "wof:placetype":"venue"
},
  "geometry": {"coordinates":[-2.844883,56.477409],"type":"Point"}
}