{
  "type": "Feature",
  "properties": {
    "addr:full":"23 Mansion St South Accrington Lancashire BB5 6SH",
    "addr:housenumber":"23",
    "addr:postcode":"bb5 6sh",
    "addr:street":"Mansion St South Accrington",
    "iso:country":"GB",
    "sg:address":"23 Mansion St South",
    "sg:city":"Accrington",
    "sg:classifiers":[
        {
            "category":"Building & Trades",
            "subcategory":"Construction",
            "type":"Services"
        }
    ],
    "sg:postcode":"BB5 6SH",
    "sg:province":"Lancashire",
    "sg:tags":[
        "builder"
    ],
    "wof:name":"Principal Builders",
    "wof:placetype":"venue"
},
  "geometry": {"coordinates":[-2.356276989,53.7531318665],"type":"Point"}
}