{
  "type": "Feature",
  "properties": {
    "iso:country":"GB",
    "sg:address":"Hugh Town,",
    "sg:city":"Isles Of Scilly",
    "sg:classifiers":[
        {
            "category":"Shopping",
            "subcategory":"Comic Books",
            "type":"Retail Goods"
        }
    ],
    "sg:postcode":"TR21 0LP",
    "sg:province":"Cornwall",
    "sg:tags":[
        "jeweller"
    ],
    "wof:name":"Zimber,P F,",
    "wof:placetype":"venue"
},
  "geometry": {"coordinates":[-6.31522,49.91433],"type":"Point"}
}