{
  "type": "Feature",
  "properties": {
    "addr:full":"35 Wallace Crescent Peterhead Aberdeenshire AB42 1GG",
    "addr:housenumber":"35",
    "addr:postcode":"ab42 1gg",
    "addr:street":"Wallace Crescent",
    "iso:country":"GB",
    "sg:address":"35 Wallace Crescent",
    "sg:city":"Peterhead",
    "sg:classifiers":[
        {
            "category":"Recreation",
            "subcategory":"Dog Park",
            "type":"Entertainment"
        }
    ],
    "sg:postcode":"AB42 1GG",
    "sg:province":"Aberdeenshire",
    "wof:name":"Paws Dog Grooming",
    "wof:placetype":"venue"
},
  "geometry": {"coordinates":[-1.815573,57.515972],"type":"Point"}
}