{
  "type": "Feature",
  "properties": {
    "iso:country":"GB",
    "sg:address":"Birkhouse Cottage, Cumberworth",
    "sg:city":"Huddersfield",
    "sg:classifiers":[
        {
            "category":"Building & Trades",
            "subcategory":"Plumbing",
            "type":"Services"
        }
    ],
    "sg:phone":"+44 1484 606288",
    "sg:postcode":"HD8 8XJ",
    "sg:province":"South Yorkshire",
    "sg:tags":[
        "heating"
    ],
    "wof:name":"Cyril Thorpe",
    "wof:placetype":"venue"
},
  "geometry": {"coordinates":[-1.690093,53.581829],"type":"Point"}
}