{
  "type": "Feature",
  "properties": {
    "addr:full":"Lime Kiln Barn, Colworth Chichester West Sussex PO20 6DS",
    "addr:postcode":"po20 6ds",
    "addr:street":"Colworth",
    "iso:country":"GB",
    "sg:address":"Lime Kiln Barn, Colworth",
    "sg:city":"Chichester",
    "sg:classifiers":[
        {
            "category":"Wholesale",
            "subcategory":"Books, Periodicals, & Newspapers",
            "type":"Manufacturing & Wholesale Goods"
        }
    ],
    "sg:phone":"+44 1243 787406",
    "sg:postcode":"PO20 6DS",
    "sg:province":"West Sussex",
    "sg:tags":[
        "maps",
        "globe",
        "chart",
        "pub"
    ],
    "wof:name":"Flat Earth Ltd.",
    "wof:placetype":"venue"
},
  "geometry": {"coordinates":[-0.70435,50.818169],"type":"Point"}
}