{
  "type": "Feature",
  "properties": {
    "addr:full":"5 High Banks, Stanbridge Leighton Buzzard Bedfordshire LU7 9HU",
    "addr:housenumber":"5",
    "addr:postcode":"lu7 9hu",
    "addr:street":"High Banks",
    "iso:country":"GB",
    "sg:address":"5 High Banks, Stanbridge",
    "sg:city":"Leighton Buzzard",
    "sg:classifiers":[
        {
            "category":"Professional",
            "subcategory":"Management & Consulting",
            "type":"Services"
        },
        {
            "category":"Organizations",
            "subcategory":"Community Association",
            "type":"Services"
        }
    ],
    "sg:phone":"+44 1525 211800",
    "sg:postcode":"LU7 9HU",
    "sg:province":"Bedfordshire",
    "sg:tags":[
        "consultant",
        "relation",
        "public"
    ],
    "wof:name":"Martin & Gail Duckworth",
    "wof:placetype":"venue"
},
  "geometry": {"coordinates":[-0.599534,51.91003],"type":"Point"}
}