{
  "type": "Feature",
  "properties": {
    "iso:country":"GB",
    "sg:address":"29 Brighton Pde",
    "sg:city":"Hebburn",
    "sg:classifiers":[
        {
            "category":"Shopping",
            "subcategory":"News",
            "type":"Retail Goods"
        }
    ],
    "sg:postcode":"NE31 2AZ",
    "sg:province":"Tyne and Wear",
    "sg:tags":[
        "newsagent"
    ],
    "wof:name":"J & P News",
    "wof:placetype":"venue"
},
  "geometry": {"coordinates":[-1.4988600016,54.9614601135],"type":"Point"}
}