{
  "type": "Feature",
  "properties": {
    "addr:full":"28 Galgate Barnard Castle Cumbria DL12 8BH",
    "addr:housenumber":"28",
    "addr:postcode":"dl12 8bh",
    "addr:street":"Galgate",
    "iso:country":"GB",
    "sg:address":"28 Galgate",
    "sg:city":"Barnard Castle",
    "sg:classifiers":[
        {
            "category":"Home & Garden",
            "subcategory":"Furniture",
            "type":"Retail Goods"
        }
    ],
    "sg:phone":"+44 1833 631555",
    "sg:postcode":"DL12 8BH",
    "sg:province":"Cumbria",
    "sg:tags":[
        "outlet"
    ],
    "wof:name":"P & R OLIVIER",
    "wof:placetype":"venue"
},
  "geometry": {"coordinates":[-1.924115,54.545334],"type":"Point"}
}