{
  "type": "Feature",
  "properties": {
    "iso:country":"GB",
    "sg:address":"Pytchley Road",
    "sg:city":"Kettering",
    "sg:classifiers":[
        {
            "category":"Professional",
            "subcategory":"Computer Services",
            "type":"Services"
        }
    ],
    "sg:postcode":"NN15 6NE",
    "sg:province":"Northamptonshire",
    "sg:tags":[
        "information"
    ],
    "wof:name":"Paul Samways",
    "wof:placetype":"venue"
},
  "geometry": {"coordinates":[-0.7144439816,52.3874092102],"type":"Point"}
}