{
  "type": "Feature",
  "properties": {
    "addr:full":"11 Charlotte St West End Hampshire W1P 1HD",
    "addr:housenumber":"11",
    "addr:postcode":"w1p 1hd",
    "addr:street":"Charlotte St",
    "iso:country":"GB",
    "sg:address":"11 Charlotte St",
    "sg:city":"West End",
    "sg:classifiers":[
        {
            "category":"Restaurant",
            "type":"Food & Drink"
        }
    ],
    "sg:phone":"+44 20 7436 0248",
    "sg:postcode":"W1P 1HD",
    "sg:province":"Hampshire",
    "sg:tags":[
        "french"
    ],
    "wof:name":"Pierre Victoire",
    "wof:placetype":"venue"
},
  "geometry": {"coordinates":[-0.1409479976,51.4927902222],"type":"Point"}
}