{
  "type": "Feature",
  "properties": {
    "iso:country":"GB",
    "sg:address":"21 Upper Mulgrave Road",
    "sg:city":"Sutton",
    "sg:classifiers":[
        {
            "category":"Health Services",
            "subcategory":"Clinic",
            "type":"Services"
        }
    ],
    "sg:phone":"+44 20 8770 0018",
    "sg:postcode":"SM2 7AY",
    "sg:province":"Surrey",
    "sg:tags":[
        "private"
    ],
    "wof:name":"Traditional Chinese Medicine",
    "wof:placetype":"venue"
},
  "geometry": {"coordinates":[-0.214743,51.354885],"type":"Point"}
}