{
  "type": "Feature",
  "properties": {
    "iso:country":"GB",
    "sg:address":"53a St Saviors Mall, Ealing Bdwy Centre, Ealing",
    "sg:city":"London",
    "sg:classifiers":[
        {
            "category":"Personal",
            "subcategory":"Beauty Salon",
            "type":"Services"
        },
        {
            "category":"Personal",
            "subcategory":"Barber",
            "type":"Services"
        }
    ],
    "sg:phone":"+44 20 8840 3755",
    "sg:postcode":"W5 5AW",
    "sg:province":"Greater London",
    "sg:tags":[
        "unisex",
        "men's",
        "hairdresser"
    ],
    "wof:name":"The Hair Shop",
    "wof:placetype":"venue"
},
  "geometry": {"coordinates":[-0.304917,51.5056],"type":"Point"}
}