{
  "type": "Feature",
  "properties": {
    "iso:country":"GB",
    "sg:address":"60a High Street, Leadenham",
    "sg:city":"Lincoln",
    "sg:classifiers":[
        {
            "category":"Retail",
            "subcategory":"Auto Repair",
            "type":"Services"
        }
    ],
    "sg:phone":"+44 1400 272898",
    "sg:postcode":"LN5 0PN",
    "sg:province":"Lincolnshire",
    "sg:tags":[
        "modification",
        "garage",
        "related"
    ],
    "wof:name":"M Hodson & Sons",
    "wof:placetype":"venue"
},
  "geometry": {"coordinates":[-0.6326670051,53.076877594],"type":"Point"}
}