{
  "type": "Feature",
  "properties": {
    "addr:full":"Marshall Street Coatbridge North Lanarkshire ML5 5PG",
    "addr:postcode":"ml5 5pg",
    "addr:street":"Marshall Street",
    "iso:country":"GB",
    "sg:address":"Marshall Street",
    "sg:city":"Coatbridge",
    "sg:classifiers":[
        {
            "category":"Community Center",
            "type":"Public Place"
        },
        {
            "category":"Government",
            "subcategory":"Office",
            "type":"Public Place"
        }
    ],
    "sg:phone":"+44 1236 428047",
    "sg:postcode":"ML5 5PG",
    "sg:province":"North Lanarkshire",
    "sg:tags":[
        "local",
        "centre"
    ],
    "wof:name":"Old Monkland Community Centre",
    "wof:placetype":"venue"
},
  "geometry": {"coordinates":[-4.046069,55.850979],"type":"Point"}
}