{
  "type": "Feature",
  "properties": {
    "addr:full":"16 Steele Road London Greater London NW10 7AS",
    "addr:housenumber":"16",
    "addr:postcode":"nw10 7as",
    "addr:street":"Steele Road",
    "iso:country":"GB",
    "sg:address":"16 Steele Road",
    "sg:city":"London",
    "sg:classifiers":[
        {
            "category":"Professional",
            "subcategory":"Engineering",
            "type":"Services"
        }
    ],
    "sg:phone":"+44 20 8965 4133",
    "sg:postcode":"NW10 7AS",
    "sg:province":"Greater London",
    "sg:tags":[
        "contractor",
        "electrical",
        "engineer"
    ],
    "wof:name":"Clarke Hamilton & Co. Ltd.",
    "wof:placetype":"venue"
},
  "geometry": {"coordinates":[-0.264259,51.53347],"type":"Point"}
}