{
  "type": "Feature",
  "properties": {
    "iso:country":"GB",
    "sg:address":"D'arcy House, Church Street, Gestingthorpe",
    "sg:city":"Halstead",
    "sg:classifiers":[
        {
            "category":"Food & Beverages",
            "subcategory":"Ethnic Foods",
            "type":"Retail Goods"
        }
    ],
    "sg:postcode":"CO9 3BA",
    "sg:province":"Essex",
    "sg:tags":[
        "merchant",
        "oil",
        "essential"
    ],
    "wof:name":"D'Arcy Sales & Marketing",
    "wof:placetype":"venue"
},
  "geometry": {"coordinates":[0.63903,52.01424],"type":"Point"}
}