{
  "type": "Feature",
  "properties": {
    "addr:full":"2 Queenshill Approach Leeds North Yorkshire LS17 6AY",
    "addr:housenumber":"2",
    "addr:postcode":"ls17 6ay",
    "addr:street":"Queenshill Approach",
    "iso:country":"GB",
    "sg:address":"2 Queenshill Approach",
    "sg:city":"Leeds",
    "sg:classifiers":[
        {
            "category":"Food & Beverages",
            "subcategory":"Supermarket",
            "type":"Retail Goods"
        },
        {
            "category":"Food & Beverages",
            "subcategory":"Groceries & Convenience Stores",
            "type":"Retail Goods"
        }
    ],
    "sg:phone":"+44 113 268 8345",
    "sg:postcode":"LS17 6AY",
    "sg:province":"North Yorkshire",
    "wof:name":"S Singh",
    "wof:placetype":"venue"
},
  "geometry": {"coordinates":[-1.54309,53.844734],"type":"Point"}
}