{
  "type": "Feature",
  "properties": {
    "iso:country":"GB",
    "sg:address":"Unit 68 Hotchkiss Way, Binley Industrial Estate",
    "sg:city":"Coventry",
    "sg:classifiers":[
        {
            "category":"Professional",
            "subcategory":"Engineering",
            "type":"Services"
        }
    ],
    "sg:phone":"+44 24 7645 4719",
    "sg:postcode":"CV3 2RL",
    "sg:province":"Warwickshire",
    "sg:tags":[
        "precision",
        "engineer"
    ],
    "wof:name":"Covington Developments Ltd.",
    "wof:placetype":"venue"
},
  "geometry": {"coordinates":[-1.441079,52.393356],"type":"Point"}
}