{
  "type": "Feature",
  "properties": {
    "iso:country":"GB",
    "sg:address":"Highstead, Border Court, Moorville",
    "sg:city":"Carlisle",
    "sg:classifiers":[
        {
            "category":"Professional",
            "subcategory":"Computer Services",
            "type":"Services"
        }
    ],
    "sg:phone":"+44 1228 515297",
    "sg:postcode":"CA3 0AD",
    "sg:province":"Cumbria",
    "sg:tags":[
        "aided",
        "design"
    ],
    "wof:name":"Concept Support",
    "wof:placetype":"venue"
},
  "geometry": {"coordinates":[-2.943204,54.916985],"type":"Point"}
}