{
  "type": "Feature",
  "properties": {
    "addr:full":"New Dunns Works Coleford Gloucestershire GL16 8JD",
    "addr:postcode":"gl16 8jd",
    "iso:country":"GB",
    "sg:address":"New Dunns Works",
    "sg:city":"Coleford",
    "sg:classifiers":[
        {
            "category":"Manufacturing",
            "subcategory":"Buildings",
            "type":"Manufacturing & Wholesale Goods"
        }
    ],
    "sg:postcode":"GL16 8JD",
    "sg:province":"Gloucestershire",
    "sg:tags":[
        "portable"
    ],
    "wof:name":"Energy Advantage (Finance) Ltd.",
    "wof:placetype":"venue"
},
  "geometry": {"coordinates":[-2.618529,51.793007],"type":"Point"}
}