{
  "type": "Feature",
  "properties": {
    "addr:full":"Unit 1 Avenue Farm, Off Birmingham Road Stratford-upon-avon Warwickshire CV37 0HR",
    "addr:housenumber":"unit 1",
    "addr:postcode":"cv37 0hr",
    "addr:street":"Avenue Farm Off Birmingham Road",
    "iso:country":"GB",
    "sg:address":"Unit 1 Avenue Farm, Off Birmingham Road",
    "sg:city":"Stratford-upon-avon",
    "sg:classifiers":[
        {
            "category":"Wholesale",
            "subcategory":"Construction Materials",
            "type":"Manufacturing & Wholesale Goods"
        },
        {
            "category":"Professional",
            "subcategory":"Business Services",
            "type":"Services"
        }
    ],
    "sg:phone":"+44 1789 299445",
    "sg:postcode":"CV37 0HR",
    "sg:province":"Warwickshire",
    "sg:tags":[
        "tile",
        "wholesaler",
        "supplier",
        "stockist"
    ],
    "sg:website":"http://www.stratfordtile.co.uk",
    "wof:name":"Stratford Tile Warehouse Ltd",
    "wof:placetype":"venue"
},
  "geometry": {"coordinates":[-1.7191640139,52.2022743225],"type":"Point"}
}