{
  "type": "Feature",
  "properties": {
    "addr:full":"1 St Marys Ct, Bute Rd Wallington Surrey SM6 8BU",
    "addr:housenumber":"1",
    "addr:postcode":"sm6 8bu",
    "addr:street":"St Marys Ct Bute Rd",
    "iso:country":"GB",
    "sg:address":"1 St Marys Ct, Bute Rd",
    "sg:city":"Wallington",
    "sg:classifiers":[
        {
            "category":"Organizations",
            "subcategory":"Non-profit Organization",
            "type":"Services"
        }
    ],
    "sg:phone":"+44 20 8647 7154",
    "sg:postcode":"SM6 8BU",
    "sg:province":"Surrey",
    "sg:tags":[
        "organisation",
        "voluntary",
        "charity"
    ],
    "wof:name":"Sutton Chest Heart & Stroke Care Committee",
    "wof:placetype":"venue"
},
  "geometry": {"coordinates":[-0.149898,51.360123],"type":"Point"}
}