{
  "type": "Feature",
  "properties": {
    "addr:full":"263 Barkham Rd Wokingham Berkshire RG41 4BY",
    "addr:housenumber":"263",
    "addr:postcode":"rg41 4by",
    "addr:street":"Barkham Rd",
    "iso:country":"GB",
    "sg:address":"263 Barkham Rd",
    "sg:city":"Wokingham",
    "sg:classifiers":[
        {
            "category":"Professional",
            "subcategory":"Accounting & Tax Preparation",
            "type":"Services"
        }
    ],
    "sg:phone":"+44 118 979 5995",
    "sg:postcode":"RG41 4BY",
    "sg:province":"Berkshire",
    "sg:tags":[
        "accountant"
    ],
    "wof:name":"J P Accountancy Services",
    "wof:placetype":"venue"
},
  "geometry": {"coordinates":[-0.8608189821,51.4037208557],"type":"Point"}
}