{
  "type": "Feature",
  "properties": {
    "addr:full":"Unit 16 Clos Pengarreg Craft Centre, Pan Aberaeron Ceredigion SA46 0EN",
    "addr:housenumber":"unit 16",
    "addr:postcode":"sa46 0en",
    "addr:street":"Clos Pengarreg",
    "iso:country":"GB",
    "sg:address":"Unit 16 Clos Pengarreg Craft Centre, Pan",
    "sg:city":"Aberaeron",
    "sg:classifiers":[
        {
            "category":"Transit Center",
            "subcategory":"Freight",
            "type":"Transportation"
        }
    ],
    "sg:postcode":"SA46 0EN",
    "sg:province":"Ceredigion",
    "sg:tags":[
        "shop",
        "craft",
        "centre"
    ],
    "wof:name":"Hearn,Philomena,",
    "wof:placetype":"venue"
},
  "geometry": {"coordinates":[-4.2596340179,52.2421188354],"type":"Point"}
}