{
  "type": "Feature",
  "properties": {
    "iso:country":"GB",
    "sg:address":"31 Westbourne Av",
    "sg:city":"Worthing",
    "sg:classifiers":[
        {
            "category":"Professional",
            "subcategory":"Management & Consulting",
            "type":"Services"
        }
    ],
    "sg:phone":"+44 1903 230866",
    "sg:postcode":"BN14 8DE",
    "sg:province":"West Sussex",
    "sg:tags":[
        "marketing",
        "consultant"
    ],
    "wof:name":"Hurley Partnership The",
    "wof:placetype":"venue"
},
  "geometry": {"coordinates":[-0.3707689941,50.8208351135],"type":"Point"}
}