{
  "type": "Feature",
  "properties": {
    "addr:full":"135 Evelyn Court London Greater London E8 2BH",
    "addr:housenumber":"135",
    "addr:postcode":"e8 2bh",
    "addr:street":"Evelyn Court",
    "iso:country":"GB",
    "sg:address":"135 Evelyn Court",
    "sg:city":"London",
    "sg:classifiers":[
        {
            "category":"Professional",
            "subcategory":"Accounting & Tax Preparation",
            "type":"Services"
        }
    ],
    "sg:phone":"+44 20 7249 8299",
    "sg:postcode":"E8 2BH",
    "sg:province":"Greater London",
    "sg:tags":[
        "accountant"
    ],
    "wof:name":"Response Networks Ltd.",
    "wof:placetype":"venue"
},
  "geometry": {"coordinates":[-0.0667200014,51.5532112122],"type":"Point"}
}