{
  "type": "Feature",
  "properties": {
    "addr:full":"Lumber Lane, Burtonwood Warrington Cheshire WA5 4AS",
    "addr:postcode":"wa5 4as",
    "addr:street":"Lumber Lane",
    "iso:country":"GB",
    "sg:address":"Lumber Lane, Burtonwood",
    "sg:city":"Warrington",
    "sg:classifiers":[
        {
            "category":"Sports & Exercise",
            "subcategory":"Stables",
            "type":"Entertainment"
        }
    ],
    "sg:phone":"+44 1925 291899",
    "sg:postcode":"WA5 4AS",
    "sg:province":"Cheshire",
    "sg:tags":[
        "education",
        "equestrian"
    ],
    "wof:name":"Burtonwood Riding School",
    "wof:placetype":"venue"
},
  "geometry": {"coordinates":[-2.6581139565,53.4385108948],"type":"Point"}
}