{
  "type": "Feature",
  "properties": {
    "addr:full":"The Oaks, 16 Harvey Lane Norwich Norfolk NR7 0BN",
    "addr:housenumber":"16",
    "addr:postcode":"nr7 0bn",
    "addr:street":"Harvey Lane",
    "iso:country":"GB",
    "sg:address":"The Oaks, 16 Harvey Lane",
    "sg:city":"Norwich",
    "sg:classifiers":[
        {
            "category":"Social Services",
            "type":"Services"
        },
        {
            "category":"Government",
            "subcategory":"Office",
            "type":"Public Place"
        }
    ],
    "sg:phone":"+44 1603 437811",
    "sg:postcode":"NR7 0BN",
    "sg:province":"Norfolk",
    "sg:tags":[
        "local",
        "ds"
    ],
    "wof:name":"Leaving Care Team",
    "wof:placetype":"venue"
},
  "geometry": {"coordinates":[1.32754,52.628899],"type":"Point"}
}