{
  "type": "Feature",
  "properties": {
    "addr:full":"125 Plaistow Rd Stratford Greater London E15 3ET",
    "addr:housenumber":"125",
    "addr:postcode":"e15 3et",
    "addr:street":"Plaistow Rd",
    "iso:country":"GB",
    "sg:address":"125 Plaistow Rd",
    "sg:city":"Stratford",
    "sg:classifiers":[
        {
            "category":"Shopping",
            "subcategory":"Clothing, Apparel, & Fashions",
            "type":"Retail Goods"
        }
    ],
    "sg:phone":"+44 181 555 5002",
    "sg:postcode":"E15 3ET",
    "sg:province":"Greater London",
    "sg:tags":[
        "shop"
    ],
    "wof:name":"Kumbaz Exclusive Fashions",
    "wof:placetype":"venue"
},
  "geometry": {"coordinates":[0.012001,51.533787],"type":"Point"}
}