{
  "type": "Feature",
  "properties": {
    "addr:full":"124 Churchill Way, Burton Latimer Kettering Northamptonshire NN15 5RR",
    "addr:housenumber":"124",
    "addr:postcode":"nn15 5rr",
    "addr:street":"Churchill Way",
    "iso:country":"GB",
    "sg:address":"124 Churchill Way, Burton Latimer",
    "sg:city":"Kettering",
    "sg:classifiers":[
        {
            "category":"Retail",
            "subcategory":"Driving School",
            "type":"Services"
        }
    ],
    "sg:postcode":"NN15 5RR",
    "sg:province":"Northamptonshire",
    "wof:name":"Churchill School of Motoring",
    "wof:placetype":"venue"
},
  "geometry": {"coordinates":[-0.6988360286,52.3907470703],"type":"Point"}
}