{
  "type": "Feature",
  "properties": {
    "iso:country":"GB",
    "sg:address":"Old House Farm, Llangovan",
    "sg:city":"Monmouth",
    "sg:classifiers":[
        {
            "category":"Farming",
            "subcategory":"Livestock Farm",
            "type":"Manufacturing & Wholesale Goods"
        }
    ],
    "sg:postcode":"NP25 4BT",
    "sg:province":"Gloucestershire",
    "sg:tags":[
        "others"
    ],
    "wof:name":"A G & M J Heath",
    "wof:placetype":"venue"
},
  "geometry": {"coordinates":[-2.7918241024,51.7400512695],"type":"Point"}
}