{
  "type": "Feature",
  "properties": {
    "addr:full":"Woodend Av Liverpool Merseyside L24 9WF",
    "addr:postcode":"l24 9wf",
    "addr:street":"Woodend Av",
    "iso:country":"GB",
    "sg:address":"Woodend Av",
    "sg:city":"Liverpool",
    "sg:classifiers":[
        {
            "category":"Shopping Center",
            "type":"Public Place"
        }
    ],
    "sg:phone":"+44 151 486 4040",
    "sg:postcode":"L24 9WF",
    "sg:province":"Merseyside",
    "sg:tags":[
        "clutch",
        "brake",
        "centre"
    ],
    "wof:name":"Speke Auto Tune",
    "wof:placetype":"venue"
},
  "geometry": {"coordinates":[-2.8533489704,53.35496521],"type":"Point"}
}