{
  "type": "Feature",
  "properties": {
    "addr:full":"Dell View, London Road, Spellbrook Bishops Stortford Essex CM23 5NE",
    "addr:postcode":"cm23 5ne",
    "addr:street":"Dell View London Road Spellbrook Bishops",
    "iso:country":"GB",
    "sg:address":"Dell View, London Road, Spellbrook",
    "sg:city":"Bishops Stortford",
    "sg:classifiers":[
        {
            "category":"Autos & Motor Vehicles",
            "subcategory":"Fuel & Gas Station",
            "type":"Retail Goods"
        }
    ],
    "sg:phone":"+44 1279 507769",
    "sg:postcode":"CM23 5NE",
    "sg:province":"Essex",
    "sg:tags":[
        "petrol",
        "filling"
    ],
    "wof:name":"Q8 Petoleum",
    "wof:placetype":"venue"
},
  "geometry": {"coordinates":[0.1619559973,51.8723564148],"type":"Point"}
}