{
  "type": "Feature",
  "properties": {
    "iso:country":"GB",
    "sg:address":"35-39 Chapel Hill",
    "sg:city":"Huddersfield",
    "sg:classifiers":[
        {
            "category":"Home & Garden",
            "subcategory":"Household Appliances",
            "type":"Retail Goods"
        }
    ],
    "sg:postcode":"HD1 3ED",
    "sg:province":"West Yorkshire",
    "sg:tags":[
        "electrical"
    ],
    "wof:name":"Domestic Appliance Service",
    "wof:placetype":"venue"
},
  "geometry": {"coordinates":[-1.785085,53.641052],"type":"Point"}
}