{
  "type": "Feature",
  "properties": {
    "iso:country":"GB",
    "sg:address":"30 Portsmouth Road, Woolston",
    "sg:city":"Southampton",
    "sg:classifiers":[
        {
            "category":"Food & Beverages",
            "subcategory":"Groceries & Convenience Stores",
            "type":"Retail Goods"
        }
    ],
    "sg:phone":"+44 23 8044 6207",
    "sg:postcode":"SO19 9AB",
    "sg:province":"Hampshire",
    "wof:name":"Alldays Stores Ltd.",
    "wof:placetype":"venue"
},
  "geometry": {"coordinates":[-1.378241,50.897911],"type":"Point"}
}