{
  "type": "Feature",
  "properties": {
    "iso:country":"GB",
    "sg:address":"Unit 29, Ledgard Bridge Mill",
    "sg:city":"Mirfield",
    "sg:classifiers":[
        {
            "category":"Building & Trades",
            "subcategory":"Construction",
            "type":"Services"
        }
    ],
    "sg:phone":"+44 1924 496901",
    "sg:postcode":"WF14 8NJ",
    "sg:province":"West Yorkshire",
    "sg:tags":[
        "platform",
        "work",
        "scaffolding"
    ],
    "wof:name":"M S L Services Ltd.",
    "wof:placetype":"venue"
},
  "geometry": {"coordinates":[-1.6967099905,53.6749382019],"type":"Point"}
}