{
  "type": "Feature",
  "properties": {
    "addr:full":"15 Market Street Poole Dorset BH15 1NB",
    "addr:housenumber":"15",
    "addr:postcode":"bh15 1nb",
    "addr:street":"Market Street",
    "iso:country":"GB",
    "sg:address":"15 Market Street",
    "sg:city":"Poole",
    "sg:classifiers":[
        {
            "category":"Bars & Pubs",
            "type":"Food & Drink"
        },
        {
            "category":"Community Center",
            "subcategory":"Social",
            "type":"Public Place"
        }
    ],
    "sg:phone":"+44 1202 671717",
    "sg:postcode":"BH15 1NB",
    "sg:province":"Dorset",
    "sg:tags":[
        "pubs",
        "house",
        "inn",
        "activity"
    ],
    "wof:name":"The Guildhall Tavern",
    "wof:placetype":"venue"
},
  "geometry": {"coordinates":[-1.987442,50.714279],"type":"Point"}
}