{
  "type": "Feature",
  "properties": {
    "addr:full":"13 Waterloo Avenue Basingstoke Hampshire RG23 8DL",
    "addr:housenumber":"13",
    "addr:postcode":"rg23 8dl",
    "addr:street":"Waterloo Avenue",
    "iso:country":"GB",
    "sg:address":"13 Waterloo Avenue",
    "sg:city":"Basingstoke",
    "sg:classifiers":[
        {
            "category":"Home & Garden",
            "subcategory":"Household Appliances",
            "type":"Retail Goods"
        },
        {
            "category":"Organizations",
            "subcategory":"Membership Organization",
            "type":"Services"
        }
    ],
    "sg:phone":"+44 1256 59357",
    "sg:postcode":"RG23 8DL",
    "sg:province":"Hampshire",
    "sg:tags":[
        "electrical"
    ],
    "wof:name":"The Knight Foundation For Cystic Fibrosis",
    "wof:placetype":"venue"
},
  "geometry": {"coordinates":[-1.123054,51.276115],"type":"Point"}
}