{
  "type": "Feature",
  "properties": {
    "addr:full":"43 Shields Crescent, Castle Donington Derby Leicestershire DE74 2JS",
    "addr:housenumber":"43",
    "addr:postcode":"de74 2js",
    "addr:street":"Shields Crescent",
    "iso:country":"GB",
    "sg:address":"43 Shields Crescent, Castle Donington",
    "sg:city":"Derby",
    "sg:classifiers":[
        {
            "category":"Professional",
            "subcategory":"Computer Services",
            "type":"Services"
        }
    ],
    "sg:postcode":"DE74 2JS",
    "sg:province":"Leicestershire",
    "sg:tags":[
        "system",
        "software"
    ],
    "wof:name":"Cripton Ltd",
    "wof:placetype":"venue"
},
  "geometry": {"coordinates":[-1.347558,52.839752],"type":"Point"}
}