{
  "type": "Feature",
  "properties": {
    "addr:full":"Loch Rd, Kirkintilloch Glasgow East Dunbartonshire G66 3EB",
    "addr:postcode":"g66 3eb",
    "addr:street":"Loch Rd",
    "iso:country":"GB",
    "sg:address":"Loch Rd, Kirkintilloch",
    "sg:city":"Glasgow",
    "sg:classifiers":[
        {
            "category":"Building & Trades",
            "subcategory":"Equipment Rental",
            "type":"Services"
        }
    ],
    "sg:postcode":"G66 3EB",
    "sg:province":"East Dunbartonshire",
    "sg:tags":[
        "plant",
        "machinery"
    ],
    "wof:name":"Mabey Hire Ltd",
    "wof:placetype":"venue"
},
  "geometry": {"coordinates":[-4.147414,55.934212],"type":"Point"}
}