{
  "type": "Feature",
  "properties": {
    "iso:country":"GB",
    "sg:address":"Fishing Lodge, Howwood",
    "sg:city":"Johnstone",
    "sg:classifiers":[
        {
            "category":"Recreation",
            "subcategory":"Fishing",
            "type":"Entertainment"
        }
    ],
    "sg:phone":"+44 1505 702688",
    "sg:postcode":"PA9 1DG",
    "sg:province":"Renfrewshire",
    "sg:tags":[
        "angling"
    ],
    "wof:name":"Howwood Trout Fishery",
    "wof:placetype":"venue"
},
  "geometry": {"coordinates":[-4.561974,55.808956],"type":"Point"}
}