{
  "type": "Feature",
  "properties": {
    "addr:full":"Unit 3 17 Pickwick Rd Corsham Wiltshire SN13 9BQ",
    "addr:housenumber":"unit;17",
    "addr:postcode":"sn13 9bq",
    "addr:street":"Pickwick Rd",
    "iso:country":"GB",
    "sg:address":"Unit 3 17 Pickwick Rd",
    "sg:city":"Corsham",
    "sg:classifiers":[
        {
            "category":"Health Services",
            "subcategory":"Dentist",
            "type":"Services"
        }
    ],
    "sg:phone":"+44 1249 701645",
    "sg:postcode":"SN13 9BQ",
    "sg:province":"Wiltshire",
    "sg:tags":[
        "technician",
        "dental"
    ],
    "wof:name":"Corsham Denture Repairs",
    "wof:placetype":"venue"
},
  "geometry": {"coordinates":[-2.186303,51.431362],"type":"Point"}
}