{
  "type": "Feature",
  "properties": {
    "iso:country":"GB",
    "sg:address":"The Theatre, Spring Street",
    "sg:city":"Chipping Norton",
    "sg:classifiers":[
        {
            "category":"Arts & Performance",
            "subcategory":"Theater",
            "type":"Entertainment"
        }
    ],
    "sg:phone":"+44 1608 642350",
    "sg:postcode":"OX7 5NL",
    "sg:province":"Gloucestershire",
    "sg:tags":[
        "hall",
        "theatre",
        "concert"
    ],
    "wof:name":"Chipping Norton Theatre",
    "wof:placetype":"venue"
},
  "geometry": {"coordinates":[-1.545913,51.940407],"type":"Point"}
}