{
  "type": "Feature",
  "properties": {
    "iso:country":"GB",
    "sg:address":"45 Main Street",
    "sg:city":"Aylesbury",
    "sg:classifiers":[
        {
            "category":"Building & Trades",
            "subcategory":"Plumbing",
            "type":"Services"
        },
        {
            "category":"Home & Garden",
            "subcategory":"Building Materials",
            "type":"Retail Goods"
        }
    ],
    "sg:phone":"+44 1296 612189",
    "sg:postcode":"HP22 5RW",
    "sg:province":"Buckinghamshire",
    "sg:tags":[
        "furnishers",
        "bathroom",
        "planner",
        "heating"
    ],
    "wof:name":"Bathroomcraft",
    "wof:placetype":"venue"
},
  "geometry": {"coordinates":[-0.760038,51.790745],"type":"Point"}
}