{
  "type": "Feature",
  "properties": {
    "addr:full":"South End Garage, Long Framlington Morpeth Northumberland NE65 8EF",
    "addr:postcode":"ne65 8ef",
    "addr:street":"Northumberland",
    "iso:country":"GB",
    "sg:address":"South End Garage, Long Framlington",
    "sg:city":"Morpeth",
    "sg:classifiers":[
        {
            "category":"Retail",
            "subcategory":"Auto Repair",
            "type":"Services"
        }
    ],
    "sg:phone":"+44 1665 570217",
    "sg:postcode":"NE65 8EF",
    "sg:province":"Northumberland",
    "sg:tags":[
        "modification",
        "garage"
    ],
    "wof:name":"E & M I Gilholme",
    "wof:placetype":"venue"
},
  "geometry": {"coordinates":[-1.7673009634,55.2451782227],"type":"Point"}
}