{
  "type": "Feature",
  "properties": {
    "addr:full":"34 High St Willesden Greater London NW10 4LS",
    "addr:housenumber":"34",
    "addr:postcode":"nw10 4ls",
    "addr:street":"High St",
    "iso:country":"GB",
    "sg:address":"34 High St",
    "sg:city":"Willesden",
    "sg:classifiers":[
        {
            "category":"Bars & Pubs",
            "type":"Food & Drink"
        }
    ],
    "sg:phone":"+44 20 8961 1018",
    "sg:postcode":"NW10 4LS",
    "sg:province":"Greater London",
    "sg:tags":[
        "pubs",
        "inn"
    ],
    "wof:name":"Crown Rat & Carrot The",
    "wof:placetype":"venue"
},
  "geometry": {"coordinates":[-0.248823002,51.5370025635],"type":"Point"}
}