{
  "type": "Feature",
  "properties": {
    "iso:country":"GB",
    "sg:address":"12 Cromlix Close",
    "sg:city":"Chislehurst",
    "sg:classifiers":[
        {
            "category":"Taxi",
            "type":"Transportation"
        }
    ],
    "sg:phone":"+44 20 8295 0101",
    "sg:postcode":"BR7 5SJ",
    "sg:province":"Kent",
    "sg:tags":[
        "mini",
        "cab"
    ],
    "wof:name":"Ladybirds",
    "wof:placetype":"venue"
},
  "geometry": {"coordinates":[0.062563,51.406097],"type":"Point"}
}