{
  "type": "Feature",
  "properties": {
    "addr:full":"Unit 5, Chapel Road, Smallfield Horley Surrey RH6 9NS",
    "addr:housenumber":"unit 5",
    "addr:postcode":"rh6 9ns",
    "addr:street":"Chapel Road Smallfield",
    "iso:country":"GB",
    "sg:address":"Unit 5, Chapel Road, Smallfield",
    "sg:city":"Horley",
    "sg:classifiers":[
        {
            "category":"Autos & Motor Vehicles",
            "subcategory":"Auto Supplies",
            "type":"Retail Goods"
        }
    ],
    "sg:phone":"+44 1342 842229",
    "sg:postcode":"RH6 9NS",
    "sg:province":"Surrey",
    "sg:tags":[
        "gearbox"
    ],
    "wof:name":"Automatic Transmission Services",
    "wof:placetype":"venue"
},
  "geometry": {"coordinates":[-0.116059,51.173519],"type":"Point"}
}