{
  "type": "Feature",
  "properties": {
    "addr:full":"408 Hickley Road Leicester Leicestershire LE3 0WA",
    "addr:housenumber":"408",
    "addr:postcode":"le3 0wa",
    "addr:street":"Hickley Road",
    "iso:country":"GB",
    "sg:address":"408 Hickley Road",
    "sg:city":"Leicester",
    "sg:classifiers":[
        {
            "category":"Professional",
            "subcategory":"Research",
            "type":"Services"
        }
    ],
    "sg:phone":"+44 116 285 8604",
    "sg:postcode":"LE3 0WA",
    "sg:province":"Leicestershire",
    "sg:tags":[
        "market"
    ],
    "wof:name":"Social Research Associates Ltd.",
    "wof:placetype":"venue"
},
  "geometry": {"coordinates":[-1.172828,52.633083],"type":"Point"}
}