{
  "type": "Feature",
  "properties": {
    "iso:country":"GB",
    "sg:address":"76 Moor End Lane",
    "sg:city":"Dewsbury",
    "sg:classifiers":[
        {
            "category":"Bars & Pubs",
            "type":"Food & Drink"
        }
    ],
    "sg:phone":"+44 1924 405860",
    "sg:postcode":"WF13 4PD",
    "sg:province":"West Yorkshire",
    "sg:tags":[
        "pubs",
        "inn"
    ],
    "wof:name":"John Wasilewski",
    "wof:placetype":"venue"
},
  "geometry": {"coordinates":[-1.658168,53.701931],"type":"Point"}
}