{
  "type": "Feature",
  "properties": {
    "addr:full":"537 Rainham Road South Dagenham Essex RM10 7XJ",
    "addr:housenumber":"537",
    "addr:postcode":"rm10 7xj",
    "addr:street":"Rainham Road South",
    "iso:country":"GB",
    "sg:address":"537 Rainham Road South",
    "sg:city":"Dagenham",
    "sg:classifiers":[
        {
            "category":"Fast Food",
            "type":"Food & Drink"
        }
    ],
    "sg:phone":"+44 20 8984 7336",
    "sg:postcode":"RM10 7XJ",
    "sg:province":"Essex",
    "sg:tags":[
        "away",
        "take"
    ],
    "wof:name":"The Cod Father",
    "wof:placetype":"venue"
},
  "geometry": {"coordinates":[0.1650889963,51.5458068848],"type":"Point"}
}