{
  "type": "Feature",
  "properties": {
    "iso:country":"GB",
    "sg:address":"8 Manor Street",
    "sg:city":"Bridlington",
    "sg:classifiers":[
        {
            "category":"Shopping",
            "subcategory":"Gifts & Souvenirs",
            "type":"Retail Goods"
        }
    ],
    "sg:postcode":"YO15 2SA",
    "sg:province":"East Riding of Yorkshire",
    "sg:tags":[
        "shop"
    ],
    "wof:name":"Goldings Coffee & Gift House",
    "wof:placetype":"venue"
},
  "geometry": {"coordinates":[-0.191982,54.082458],"type":"Point"}
}