{
  "type": "Feature",
  "properties": {
    "addr:full":"72 Fielding Road, Chiswick London Greater London W4 1DB",
    "addr:housenumber":"72",
    "addr:postcode":"w4 1db",
    "addr:street":"Fielding Road",
    "iso:country":"GB",
    "sg:address":"72 Fielding Road, Chiswick",
    "sg:city":"London",
    "sg:classifiers":[
        {
            "category":"Professional",
            "subcategory":"Computer Services",
            "type":"Services"
        }
    ],
    "sg:postcode":"W4 1DB",
    "sg:province":"Greater London",
    "sg:tags":[
        "consultant"
    ],
    "wof:name":"Lanlink Limited",
    "wof:placetype":"venue"
},
  "geometry": {"coordinates":[-0.257059,51.500534],"type":"Point"}
}