{
  "type": "Feature",
  "properties": {
    "addr:full":"92 Dosthill Road, Two Gates Tamworth Staffordshire B77 1JB",
    "addr:housenumber":"92",
    "addr:postcode":"b77 1jb",
    "addr:street":"Dosthill Road Two",
    "iso:country":"GB",
    "sg:address":"92 Dosthill Road, Two Gates",
    "sg:city":"Tamworth",
    "sg:classifiers":[
        {
            "category":"Professional",
            "type":"Services"
        },
        {
            "category":"Building & Trades",
            "subcategory":"Construction",
            "type":"Services"
        }
    ],
    "sg:phone":"+44 1827 251771",
    "sg:postcode":"B77 1JB",
    "sg:province":"Staffordshire",
    "sg:tags":[
        "joiner",
        "carpenter",
        "shopfitters"
    ],
    "wof:name":"Gordon Leighton Services",
    "wof:placetype":"venue"
},
  "geometry": {"coordinates":[-1.6827939749,52.6112556458],"type":"Point"}
}