{
  "type": "Feature",
  "properties": {
    "addr:full":"17 Chelsea Houses, Town Centre Basingstoke Hampshire RG21 7JR",
    "addr:housenumber":"17",
    "addr:postcode":"rg21 7jr",
    "addr:street":"Chelsea Houses",
    "iso:country":"GB",
    "sg:address":"17 Chelsea Houses, Town Centre",
    "sg:city":"Basingstoke",
    "sg:classifiers":[
        {
            "category":"Communications",
            "type":"Services"
        }
    ],
    "sg:phone":"+44 1256 355777",
    "sg:postcode":"RG21 7JR",
    "sg:province":"Hampshire",
    "sg:tags":[
        "tv",
        "video",
        "radio"
    ],
    "wof:name":"Milton's Audio Visual Ltd.",
    "wof:placetype":"venue"
},
  "geometry": {"coordinates":[-1.083088994,51.2624435425],"type":"Point"}
}