{
  "type": "Feature",
  "properties": {
    "addr:full":"Kenmure Road London Greater London E8 1HY",
    "addr:postcode":"e8 1hy",
    "addr:street":"Kenmure Road",
    "iso:country":"GB",
    "sg:address":"Kenmure Road",
    "sg:city":"London",
    "sg:classifiers":[
        {
            "category":"Shopping",
            "subcategory":"Gifts & Souvenirs",
            "type":"Retail Goods"
        }
    ],
    "sg:postcode":"E8 1HY",
    "sg:province":"Greater London",
    "sg:tags":[
        "giftware"
    ],
    "wof:name":"Vasoulla Stylianou",
    "wof:placetype":"venue"
},
  "geometry": {"coordinates":[-0.055379,51.548824],"type":"Point"}
}