{
  "type": "Feature",
  "properties": {
    "addr:full":"Draycote Rugby Northamptonshire CV23 9RB",
    "addr:postcode":"cv23 9rb",
    "iso:country":"GB",
    "sg:address":"Draycote",
    "sg:city":"Rugby",
    "sg:classifiers":[
        {
            "category":"Professional",
            "subcategory":"Employment Agencies",
            "type":"Services"
        }
    ],
    "sg:phone":"+44 1926 633006",
    "sg:postcode":"CV23 9RB",
    "sg:province":"Northamptonshire",
    "sg:tags":[
        "consultant"
    ],
    "wof:name":"Ingineur Ltd.",
    "wof:placetype":"venue"
},
  "geometry": {"coordinates":[-1.348889,52.325932],"type":"Point"}
}