{
  "type": "Feature",
  "properties": {
    "iso:country":"GB",
    "sg:address":"152 Loddon Bridge Road, Woodley",
    "sg:city":"Reading",
    "sg:classifiers":[
        {
            "category":"Professional",
            "subcategory":"Engineering",
            "type":"Services"
        }
    ],
    "sg:phone":"+44 118 969 6046",
    "sg:postcode":"RG5 4AB",
    "sg:province":"Berkshire",
    "sg:tags":[
        "consulting",
        "engineer"
    ],
    "wof:name":"Bentley Engineering Services",
    "wof:placetype":"venue"
},
  "geometry": {"coordinates":[-0.89909,51.44532],"type":"Point"}
}