{
  "type": "Feature",
  "properties": {
    "addr:full":"2 Lowther Park Kendal Cumbria LA9 6RS",
    "addr:housenumber":"2",
    "addr:postcode":"la9 6rs",
    "addr:street":"Lowther Park Kendal",
    "iso:country":"GB",
    "sg:address":"2 Lowther Park",
    "sg:city":"Kendal",
    "sg:classifiers":[
        {
            "category":"Utilities",
            "subcategory":"Refuse",
            "type":"Services"
        }
    ],
    "sg:postcode":"LA9 6RS",
    "sg:province":"Cumbria",
    "sg:tags":[
        "skip",
        "hire"
    ],
    "wof:name":"G Midi Skip Hire Stewart",
    "wof:placetype":"venue"
},
  "geometry": {"coordinates":[-2.72768,54.324623],"type":"Point"}
}