{
  "type": "Feature",
  "properties": {
    "addr:full":"68 Rose Green Road Bognor Regis West Sussex PO21 3EQ",
    "addr:housenumber":"68",
    "addr:postcode":"po21 3eq",
    "addr:street":"Rose Green Road",
    "iso:country":"GB",
    "sg:address":"68 Rose Green Road",
    "sg:city":"Bognor Regis",
    "sg:classifiers":[
        {
            "category":"Food & Beverages",
            "subcategory":"Supermarket",
            "type":"Retail Goods"
        },
        {
            "category":"Food & Beverages",
            "subcategory":"Groceries & Convenience Stores",
            "type":"Retail Goods"
        }
    ],
    "sg:phone":"+44 1243 262493",
    "sg:postcode":"PO21 3EQ",
    "sg:province":"West Sussex",
    "wof:name":"Southern Co-Operatives Ltd.",
    "wof:placetype":"venue"
},
  "geometry": {"coordinates":[-0.7157490253,50.7868118286],"type":"Point"}
}