{
  "type": "Feature",
  "properties": {
    "iso:country":"GB",
    "sg:address":"101 Garners Lane, Davenport",
    "sg:city":"Stockport",
    "sg:classifiers":[
        {
            "category":"Home & Garden",
            "subcategory":"Home Furnishings",
            "type":"Retail Goods"
        }
    ],
    "sg:phone":"+44 161 612 0583",
    "sg:postcode":"SK3 8QZ",
    "sg:province":"Cheshire",
    "sg:tags":[
        "tube",
        "fitting",
        "stockist"
    ],
    "wof:name":"European Tubes Ltd.",
    "wof:placetype":"venue"
},
  "geometry": {"coordinates":[-2.160247,53.391346],"type":"Point"}
}