{
  "type": "Feature",
  "properties": {
    "iso:country":"GB",
    "sg:address":"Parker Street",
    "sg:city":"Chorley",
    "sg:classifiers":[
        {
            "category":"Farming",
            "subcategory":"Nursery",
            "type":"Manufacturing & Wholesale Goods"
        },
        {
            "category":"Education",
            "subcategory":"Preschool",
            "type":"Public Place"
        }
    ],
    "sg:postcode":"PR7 1ES",
    "sg:province":"Lancashire",
    "sg:tags":[
        "school",
        "creche"
    ],
    "wof:name":"Old School House Nursery & Play Centre",
    "wof:placetype":"venue"
},
  "geometry": {"coordinates":[-2.6306340694,53.6583938599],"type":"Point"}
}