{
  "type": "Feature",
  "properties": {
    "iso:country":"GB",
    "sg:address":"154 Uplands Avenue, Connah's Quay",
    "sg:city":"Deeside",
    "sg:classifiers":[
        {
            "category":"Building & Trades",
            "subcategory":"Construction",
            "type":"Services"
        }
    ],
    "sg:phone":"+44 1244 822563",
    "sg:postcode":"CH5 4LG",
    "sg:province":"Flintshire",
    "sg:tags":[
        "tiling",
        "contractor"
    ],
    "wof:name":"Adrian Martin Wall & Floor Tiling",
    "wof:placetype":"venue"
},
  "geometry": {"coordinates":[-3.06659,53.206959],"type":"Point"}
}