{
  "type": "Feature",
  "properties": {
    "addr:full":"40-42 Bath Road Margate Kent CT9 1SJ",
    "addr:housenumber":"40-42",
    "addr:postcode":"ct9 1sj",
    "addr:street":"Bath Road",
    "iso:country":"GB",
    "sg:address":"40-42 Bath Road",
    "sg:city":"Margate",
    "sg:classifiers":[
        {
            "category":"Retail",
            "subcategory":"Laundry & Dry Cleaning",
            "type":"Services"
        }
    ],
    "sg:phone":"+44 1843 224494",
    "sg:postcode":"CT9 1SJ",
    "sg:province":"Kent",
    "sg:tags":[
        "launderette"
    ],
    "wof:name":"COINWASH",
    "wof:placetype":"venue"
},
  "geometry": {"coordinates":[1.389642,51.389305],"type":"Point"}
}