{
  "type": "Feature",
  "properties": {
    "iso:country":"GB",
    "sg:address":"5 Riverside Gardens, Langford",
    "sg:city":"Biggleswade",
    "sg:classifiers":[
        {
            "category":"Building & Trades",
            "subcategory":"Construction",
            "type":"Services"
        }
    ],
    "sg:phone":"+44 1462 700679",
    "sg:postcode":"SG18 9RZ",
    "sg:province":"Bedfordshire",
    "sg:tags":[
        "decorator",
        "painter"
    ],
    "wof:name":"I R Brown",
    "wof:placetype":"venue"
},
  "geometry": {"coordinates":[-0.2764210105,52.0476531982],"type":"Point"}
}