{
  "type": "Feature",
  "properties": {
    "addr:full":"Unit A12, Napier Mill, Atkinson Street Oldham Lancashire OL9 6QT",
    "addr:housenumber":"a12",
    "addr:postcode":"ol9 6qt",
    "addr:street":"Napier Mill Atkinson Street",
    "iso:country":"GB",
    "sg:address":"Unit A12, Napier Mill, Atkinson Street",
    "sg:city":"Oldham",
    "sg:classifiers":[
        {
            "category":"Home & Garden",
            "subcategory":"Home Furnishings",
            "type":"Retail Goods"
        },
        {
            "category":"Home & Garden",
            "subcategory":"Furniture",
            "type":"Retail Goods"
        }
    ],
    "sg:phone":"+44 1592 630440",
    "sg:postcode":"OL9 6QT",
    "sg:province":"Lancashire",
    "sg:tags":[
        "furnishers",
        "planner",
        "outlet",
        "bedroom"
    ],
    "wof:name":"PREMIER BEDROOMS LTD",
    "wof:placetype":"venue"
},
  "geometry": {"coordinates":[-2.1280400753,53.5481491089],"type":"Point"}
}