{
  "type": "Feature",
  "properties": {
    "addr:full":"13a-13b Unit, Hadley Park Industrial Estate, Hadley Park Road Telford Shropshire TF1 6PY",
    "addr:housenumber":"13a-13b unit hadley",
    "addr:postcode":"tf1 6py",
    "addr:street":"Park Industrial;Hadley Park Road",
    "iso:country":"GB",
    "sg:address":"13a-13b Unit, Hadley Park Industrial Estate, Hadley Park Road",
    "sg:city":"Telford",
    "sg:classifiers":[
        {
            "category":"Manufacturing",
            "subcategory":"Chemicals & Compounds",
            "type":"Manufacturing & Wholesale Goods"
        },
        {
            "category":"Autos & Motor Vehicles",
            "subcategory":"Auto Supplies",
            "type":"Retail Goods"
        }
    ],
    "sg:phone":"+44 1952 641774",
    "sg:postcode":"TF1 6PY",
    "sg:province":"Shropshire",
    "sg:tags":[
        "car",
        "manufacturer",
        "lacquer",
        "paint"
    ],
    "wof:name":"Autopaint Supplies",
    "wof:placetype":"venue"
},
  "geometry": {"coordinates":[-2.4859139919,52.7112960815],"type":"Point"}
}