{
  "type": "Feature",
  "properties": {
    "iso:country":"GB",
    "sg:address":"140 Tonge Moor Road",
    "sg:city":"Bolton",
    "sg:classifiers":[
        {
            "category":"Military Area",
            "subcategory":"Restricted Area",
            "type":"Public Place"
        }
    ],
    "sg:phone":"+44 1204 398717",
    "sg:postcode":"BL2 2DP",
    "sg:province":"Lancashire",
    "wof:name":"Overlord Militaria",
    "wof:placetype":"venue"
},
  "geometry": {"coordinates":[-2.4128699303,53.5879364014],"type":"Point"}
}