{
  "type": "Feature",
  "properties": {
    "addr:full":"110 Salamander Street Edinburgh City of Edinburgh EH6 7LA",
    "addr:housenumber":"110",
    "addr:postcode":"eh6 7la",
    "addr:street":"Salamander Street",
    "iso:country":"GB",
    "sg:address":"110 Salamander Street",
    "sg:city":"Edinburgh",
    "sg:classifiers":[
        {
            "category":"Building & Trades",
            "subcategory":"Construction",
            "type":"Services"
        }
    ],
    "sg:phone":"+44 131 467 7733",
    "sg:postcode":"EH6 7LA",
    "sg:province":"City of Edinburgh",
    "sg:tags":[
        "restoration",
        "refurbishment"
    ],
    "wof:name":"Castle Interior Contracts Ltd.",
    "wof:placetype":"venue"
},
  "geometry": {"coordinates":[-3.153019,55.97176],"type":"Point"}
}