{
  "type": "Feature",
  "properties": {
    "addr:full":"37 Dewhurst Clough Road, Egerton Bolton Lancashire BL7 9TY",
    "addr:housenumber":"37",
    "addr:postcode":"bl7 9ty",
    "addr:street":"Dewhurst Clough Road",
    "iso:country":"GB",
    "sg:address":"37 Dewhurst Clough Road, Egerton",
    "sg:city":"Bolton",
    "sg:classifiers":[
        {
            "category":"Farming",
            "subcategory":"Nursery",
            "type":"Manufacturing & Wholesale Goods"
        }
    ],
    "sg:postcode":"BL7 9TY",
    "sg:province":"Lancashire",
    "sg:tags":[
        "creche"
    ],
    "wof:name":"Dewhurst Private Day Nursery",
    "wof:placetype":"venue"
},
  "geometry": {"coordinates":[-2.444595,53.629696],"type":"Point"}
}