{
  "type": "Feature",
  "properties": {
    "iso:country":"GB",
    "sg:address":"Holtspur Way",
    "sg:city":"Beaconsfield",
    "sg:classifiers":[
        {
            "category":"Sports & Exercise",
            "subcategory":"Gym",
            "type":"Entertainment"
        }
    ],
    "sg:phone":"+44 1494 677764",
    "sg:postcode":"HP9 1DX",
    "sg:province":"Buckinghamshire",
    "sg:tags":[
        "fitness",
        "health",
        "centre"
    ],
    "wof:name":"The Beacon Centre",
    "wof:placetype":"venue"
},
  "geometry": {"coordinates":[-0.668234,51.601974],"type":"Point"}
}