{
  "type": "Feature",
  "properties": {
    "addr:full":"25 Market Street, Little Lever Bolton Lancashire BL3 1HH",
    "addr:housenumber":"25",
    "addr:postcode":"bl3 1hh",
    "addr:street":"Market Street",
    "iso:country":"GB",
    "sg:address":"25 Market Street, Little Lever",
    "sg:city":"Bolton",
    "sg:classifiers":[
        {
            "category":"Shopping",
            "subcategory":"News",
            "type":"Retail Goods"
        }
    ],
    "sg:postcode":"BL3 1HH",
    "sg:province":"Lancashire",
    "sg:tags":[
        "newsagent"
    ],
    "wof:name":"P & J Speakman",
    "wof:placetype":"venue"
},
  "geometry": {"coordinates":[-2.369864,53.561413],"type":"Point"}
}