{
  "type": "Feature",
  "properties": {
    "iso:country":"GB",
    "sg:address":"66 Ashdale Crescent, Droylsden",
    "sg:city":"Manchester",
    "sg:classifiers":[
        {
            "category":"Building & Trades",
            "subcategory":"Construction",
            "type":"Services"
        }
    ],
    "sg:phone":"+44 161 371 0095",
    "sg:postcode":"M43 6PT",
    "sg:province":"Greater Manchester",
    "sg:tags":[
        "builder"
    ],
    "wof:name":"Doughnot Construction",
    "wof:placetype":"venue"
},
  "geometry": {"coordinates":[-2.1546709538,53.4823989868],"type":"Point"}
}