{
  "type": "Feature",
  "properties": {
    "addr:full":"5a High Street Tunbridge Wells Kent TN1 1UL",
    "addr:housenumber":"5a",
    "addr:postcode":"tn1 1ul",
    "addr:street":"High Street",
    "iso:country":"GB",
    "sg:address":"5a High Street",
    "sg:city":"Tunbridge Wells",
    "sg:classifiers":[
        {
            "category":"Restaurant",
            "type":"Food & Drink"
        }
    ],
    "sg:phone":"+44 1892 549199",
    "sg:postcode":"TN1 1UL",
    "sg:province":"Kent",
    "sg:tags":[
        "italian"
    ],
    "wof:name":"Signor Franco Ristorante Ltd.",
    "wof:placetype":"venue"
},
  "geometry": {"coordinates":[0.263011992,51.1290969849],"type":"Point"}
}