{
  "type": "Feature",
  "properties": {
    "addr:full":"New Jubilee Market, Covent Garden London Greater London WC2E 8HB",
    "addr:postcode":"wc2e 8hb",
    "iso:country":"GB",
    "sg:address":"New Jubilee Market, Covent Garden",
    "sg:city":"London",
    "sg:classifiers":[
        {
            "category":"Sports & Exercise",
            "subcategory":"Athletic Track",
            "type":"Entertainment"
        }
    ],
    "sg:phone":"+44 20 7379 5323",
    "sg:postcode":"WC2E 8HB",
    "sg:province":"Greater London",
    "sg:tags":[
        "bags",
        "accessory",
        "belt"
    ],
    "wof:name":"A Graham",
    "wof:placetype":"venue"
},
  "geometry": {"coordinates":[-0.12294,51.512009],"type":"Point"}
}