{
  "type": "Feature",
  "properties": {
    "iso:country":"GB",
    "sg:address":"East Bank Road",
    "sg:city":"Sheffield",
    "sg:classifiers":[
        {
            "category":"Education",
            "subcategory":"School",
            "type":"Public Place"
        },
        {
            "category":"Government",
            "subcategory":"Office",
            "type":"Public Place"
        }
    ],
    "sg:phone":"+44 114 264 9574",
    "sg:postcode":"S2 2AL",
    "sg:province":"South Yorkshire",
    "sg:tags":[
        "local",
        "authority"
    ],
    "wof:name":"Myrtle Springs Secondary School",
    "wof:placetype":"venue"
},
  "geometry": {"coordinates":[-1.4499659538,53.3588066101],"type":"Point"}
}