{
  "type": "Feature",
  "properties": {
    "iso:country":"GB",
    "sg:address":"14 Avenue Road",
    "sg:city":"Shanklin",
    "sg:classifiers":[
        {
            "category":"Travel",
            "subcategory":"Hotels & Motels",
            "type":"Entertainment"
        }
    ],
    "sg:phone":"+44 1983 863156",
    "sg:postcode":"PO37 7BG",
    "sg:province":"Isle of Wight",
    "wof:name":"The Nook Hotel",
    "wof:placetype":"venue"
},
  "geometry": {"coordinates":[-1.175279,50.634197],"type":"Point"}
}