{
  "type": "Feature",
  "properties": {
    "addr:full":"Unit E, Edward House Grange, Business Park, Enderby Rd, Whetstone Leicester Leicestershire LE8 6EP",
    "addr:postcode":"le8 6ep",
    "addr:street":"Grange Business Park Enderby Rd",
    "iso:country":"GB",
    "sg:address":"Unit E, Edward House Grange, Business Park, Enderby Rd, Whetstone",
    "sg:city":"Leicester",
    "sg:classifiers":[
        {
            "category":"Professional",
            "subcategory":"Computer Services",
            "type":"Services"
        }
    ],
    "sg:phone":"+44 116 247 7177",
    "sg:postcode":"LE8 6EP",
    "sg:province":"Leicestershire",
    "sg:tags":[
        "system",
        "software"
    ],
    "wof:name":"Computerland UK plc",
    "wof:placetype":"venue"
},
  "geometry": {"coordinates":[-1.180494,52.564285],"type":"Point"}
}