{
  "type": "Feature",
  "properties": {
    "addr:full":"Oxford Road, Horspath Oxford Buckinghamshire OX33 1RT",
    "addr:postcode":"ox33 1rt",
    "addr:street":"Oxford Road",
    "iso:country":"GB",
    "sg:address":"Oxford Road, Horspath",
    "sg:city":"Oxford",
    "sg:classifiers":[
        {
            "category":"Retail",
            "subcategory":"Auto Repair",
            "type":"Services"
        }
    ],
    "sg:phone":"+44 1865 873349",
    "sg:postcode":"OX33 1RT",
    "sg:province":"Buckinghamshire",
    "sg:tags":[
        "modification",
        "garage",
        "related"
    ],
    "wof:name":"Horspath Service Station",
    "wof:placetype":"venue"
},
  "geometry": {"coordinates":[-1.1758660078,51.7368431091],"type":"Point"}
}