{
  "type": "Feature",
  "properties": {
    "addr:full":"540 Aigburth Road Liverpool Merseyside L19 3QG",
    "addr:housenumber":"540",
    "addr:postcode":"l19 3qg",
    "addr:street":"Aigburth Road",
    "iso:country":"GB",
    "sg:address":"540 Aigburth Road",
    "sg:city":"Liverpool",
    "sg:classifiers":[
        {
            "category":"Food & Beverages",
            "subcategory":"Liquor & Beverages",
            "type":"Retail Goods"
        }
    ],
    "sg:phone":"+44 151 494 9625",
    "sg:postcode":"L19 3QG",
    "sg:province":"Merseyside",
    "sg:tags":[
        "beer",
        "spirit",
        "wines"
    ],
    "wof:name":"William Davies",
    "wof:placetype":"venue"
},
  "geometry": {"coordinates":[-2.9166660309,53.3634109497],"type":"Point"}
}