{
  "type": "Feature",
  "properties": {
    "addr:full":"18 Market Place Ringwood Dorset BH24 1AW",
    "addr:housenumber":"18",
    "addr:postcode":"bh24 1aw",
    "addr:street":"Market Place",
    "iso:country":"GB",
    "sg:address":"18 Market Place",
    "sg:city":"Ringwood",
    "sg:classifiers":[
        {
            "category":"Real Estate",
            "subcategory":"Real Estate Agent",
            "type":"Services"
        }
    ],
    "sg:phone":"+44 1425 475511",
    "sg:postcode":"BH24 1AW",
    "sg:province":"Dorset",
    "wof:name":"Avon Valley Properties Ltd.",
    "wof:placetype":"venue"
},
  "geometry": {"coordinates":[-1.7944669724,50.8465881348],"type":"Point"}
}