{
  "type": "Feature",
  "properties": {
    "iso:country":"GB",
    "sg:address":"85 Unthank Road",
    "sg:city":"Norwich",
    "sg:classifiers":[
        {
            "category":"Retail",
            "subcategory":"Funeral Services",
            "type":"Services"
        }
    ],
    "sg:phone":"+44 1603 760787",
    "sg:postcode":"NR2 2PE",
    "sg:province":"Norfolk",
    "wof:name":"Anglia Funeral Services Ltd.",
    "wof:placetype":"venue"
},
  "geometry": {"coordinates":[1.278299,52.625229],"type":"Point"}
}