{
  "type": "Feature",
  "properties": {
    "iso:country":"GB",
    "sg:address":"49 Horsecastle Clo",
    "sg:city":"Bristol",
    "sg:classifiers":[
        {
            "category":"Professional",
            "subcategory":"Business Services",
            "type":"Services"
        }
    ],
    "sg:phone":"+44 1934 876099",
    "sg:postcode":"BS19 4AY",
    "sg:province":"City of Bristol",
    "sg:tags":[
        "import",
        "export",
        "agent"
    ],
    "wof:name":"T T B Ltd",
    "wof:placetype":"venue"
},
  "geometry": {"coordinates":[-2.828329,51.392616],"type":"Point"}
}