{
  "type": "Feature",
  "properties": {
    "addr:full":"Mengham Cottage, Mengham Lane Hayling Island Hampshire PO11 9JX",
    "addr:postcode":"po11 9jx",
    "addr:street":"Mengham Lane",
    "iso:country":"GB",
    "sg:address":"Mengham Cottage, Mengham Lane",
    "sg:city":"Hayling Island",
    "sg:classifiers":[
        {
            "category":"Recreation",
            "subcategory":"Water Park",
            "type":"Entertainment"
        }
    ],
    "sg:phone":"+44 23 9246 8831",
    "sg:postcode":"PO11 9JX",
    "sg:province":"Hampshire",
    "sg:tags":[
        "sport"
    ],
    "wof:name":"British Windsurfing Association",
    "wof:placetype":"venue"
},
  "geometry": {"coordinates":[-0.9776340127,50.8318405151],"type":"Point"}
}