{
  "type": "Feature",
  "properties": {
    "iso:country":"GB",
    "sg:address":"3 Old Forge Close, Alderholt",
    "sg:city":"Fordingbridge",
    "sg:classifiers":[
        {
            "category":"Professional",
            "subcategory":"Computer Services",
            "type":"Services"
        }
    ],
    "sg:postcode":"SP6 3AG",
    "sg:province":"Dorset",
    "sg:tags":[
        "system",
        "software"
    ],
    "wof:name":"Yieldstone Ltd.",
    "wof:placetype":"venue"
},
  "geometry": {"coordinates":[-1.8383580446,50.9117240906],"type":"Point"}
}