{
  "type": "Feature",
  "properties": {
    "iso:country":"GB",
    "sg:address":"The Coach Ho, The Old Vicarage, Vicarage Hill",
    "sg:city":"Solihull",
    "sg:classifiers":[
        {
            "category":"Professional",
            "subcategory":"Management & Consulting",
            "type":"Services"
        }
    ],
    "sg:phone":"+44 1564 741726",
    "sg:postcode":"B94 5EB",
    "sg:province":"Warwickshire",
    "sg:tags":[
        "marketing",
        "consultant"
    ],
    "wof:name":"Marketing & Training Team The",
    "wof:placetype":"venue"
},
  "geometry": {"coordinates":[-1.77785,52.415058],"type":"Point"}
}