{
  "type": "Feature",
  "properties": {
    "addr:full":"Unit 3, Orwell House, Ferry Lane Felixstowe Suffolk IP11 3QL",
    "addr:housenumber":"unit 3",
    "addr:postcode":"ip11 3ql",
    "addr:street":"Orwell House Ferry Lane",
    "iso:country":"GB",
    "sg:address":"Unit 3, Orwell House, Ferry Lane",
    "sg:city":"Felixstowe",
    "sg:classifiers":[
        {
            "category":"Freight",
            "type":"Transportation"
        }
    ],
    "sg:phone":"+44 1394 673466",
    "sg:postcode":"IP11 3QL",
    "sg:province":"Suffolk",
    "sg:tags":[
        "forwarders"
    ],
    "wof:name":"R J J Freight Ltd.",
    "wof:placetype":"venue"
},
  "geometry": {"coordinates":[1.316435,51.960079],"type":"Point"}
}