{
  "type": "Feature",
  "properties": {
    "addr:full":"229 Upper Tooting Rd London Greater London SW17 7TG",
    "addr:housenumber":"229",
    "addr:postcode":"sw17 7tg",
    "addr:street":"Upper Tooting Rd",
    "iso:country":"GB",
    "sg:address":"229 Upper Tooting Rd",
    "sg:city":"London",
    "sg:classifiers":[
        {
            "category":"Farming",
            "subcategory":"Fish & Marine Products",
            "type":"Manufacturing & Wholesale Goods"
        }
    ],
    "sg:postcode":"SW17 7TG",
    "sg:province":"Greater London",
    "sg:tags":[
        "fishmonger"
    ],
    "wof:name":"T & H Meat Shop",
    "wof:placetype":"venue"
},
  "geometry": {"coordinates":[-0.1655350029,51.4306144714],"type":"Point"}
}