{
  "type": "Feature",
  "properties": {
    "iso:country":"GB",
    "sg:address":"40 Huyton Lane",
    "sg:city":"Liverpool",
    "sg:classifiers":[
        {
            "category":"Organizations",
            "subcategory":"Non-profit Organization",
            "type":"Services"
        }
    ],
    "sg:postcode":"L36 7XG",
    "sg:province":"Merseyside",
    "sg:tags":[
        "organisation",
        "voluntary",
        "charity"
    ],
    "wof:name":"Lyndale Knowsley Cancer Support Centre Ltd.",
    "wof:placetype":"venue"
},
  "geometry": {"coordinates":[-2.8377819061,53.4143753052],"type":"Point"}
}