{
  "type": "Feature",
  "properties": {
    "iso:country":"GB",
    "sg:address":"Slwch Farm",
    "sg:city":"Brecon",
    "sg:classifiers":[
        {
            "category":"Farming",
            "subcategory":"Farm",
            "type":"Manufacturing & Wholesale Goods"
        }
    ],
    "sg:postcode":"LD3 9SP",
    "sg:province":"Powys",
    "sg:tags":[
        "mixed",
        "crop"
    ],
    "wof:name":"Gwyn Williams",
    "wof:placetype":"venue"
},
  "geometry": {"coordinates":[-3.3911418915,51.9497413635],"type":"Point"}
}