{
  "type": "Feature",
  "properties": {
    "addr:full":"5 New Steine Brighton East Sussex BN2 1PB",
    "addr:housenumber":"5",
    "addr:postcode":"bn2 1pb",
    "addr:street":"New Steine",
    "iso:country":"GB",
    "sg:address":"5 New Steine",
    "sg:city":"Brighton",
    "sg:classifiers":[
        {
            "category":"Travel",
            "subcategory":"Hotels & Motels",
            "type":"Entertainment"
        }
    ],
    "sg:phone":"+44 1273 686547",
    "sg:postcode":"BN2 1PB",
    "sg:province":"East Sussex",
    "sg:tags":[
        "house",
        "guest"
    ],
    "wof:name":"Aegean Hotel",
    "wof:placetype":"venue"
},
  "geometry": {"coordinates":[-0.132181,50.819744],"type":"Point"}
}