{
  "type": "Feature",
  "properties": {
    "addr:full":"Baconsthorpe Road, Hempstead Holt Norfolk NR25 6LD",
    "addr:postcode":"nr25 6ld",
    "addr:street":"Baconsthorpe Road",
    "iso:country":"GB",
    "sg:address":"Baconsthorpe Road, Hempstead",
    "sg:city":"Holt",
    "sg:classifiers":[
        {
            "category":"Bars & Pubs",
            "type":"Food & Drink"
        }
    ],
    "sg:postcode":"NR25 6LD",
    "sg:province":"Norfolk",
    "sg:tags":[
        "pubs",
        "inn"
    ],
    "wof:name":"Hare & Hounds",
    "wof:placetype":"venue"
},
  "geometry": {"coordinates":[1.0899460316,52.9030570984],"type":"Point"}
}