{
  "type": "Feature",
  "properties": {
    "addr:full":"13 Ewenny Road Bridgend Bridgend CF31 3HN",
    "addr:housenumber":"13",
    "addr:postcode":"cf31 3hn",
    "addr:street":"Ewenny Road",
    "iso:country":"GB",
    "sg:address":"13 Ewenny Road",
    "sg:city":"Bridgend",
    "sg:classifiers":[
        {
            "category":"Government",
            "subcategory":"Post Office",
            "type":"Public Place"
        }
    ],
    "sg:postcode":"CF31 3HN",
    "sg:province":"Bridgend",
    "wof:name":"Nolton Street Post Office",
    "wof:placetype":"venue"
},
  "geometry": {"coordinates":[-3.5759899616,51.5012588501],"type":"Point"}
}