{
  "type": "Feature",
  "properties": {
    "addr:full":"Trench Lane, Almondsbury Bristol Gloucestershire BS32 4JZ",
    "addr:postcode":"bs32 4jz",
    "addr:street":"Trench Lane",
    "iso:country":"GB",
    "sg:address":"Trench Lane, Almondsbury",
    "sg:city":"Bristol",
    "sg:classifiers":[
        {
            "category":"Organizations",
            "subcategory":"Membership Organization",
            "type":"Services"
        },
        {
            "category":"Sports & Exercise",
            "subcategory":"Golf",
            "type":"Entertainment"
        }
    ],
    "sg:phone":"+44 1454 618121",
    "sg:postcode":"BS32 4JZ",
    "sg:province":"Gloucestershire",
    "sg:tags":[
        "club",
        "course"
    ],
    "wof:name":"Woodlands Golf & Country Club",
    "wof:placetype":"venue"
},
  "geometry": {"coordinates":[-2.564619,51.556526],"type":"Point"}
}