{
  "type": "Feature",
  "properties": {
    "iso:country":"GB",
    "sg:address":"93 Replingham Road",
    "sg:city":"London",
    "sg:classifiers":[
        {
            "category":"Manufacturing",
            "subcategory":"Petroleum Products",
            "type":"Manufacturing & Wholesale Goods"
        }
    ],
    "sg:phone":"+44 20 8870 5765",
    "sg:postcode":"SW18 5LU",
    "sg:province":"Greater London",
    "sg:tags":[
        "double",
        "glazing"
    ],
    "wof:name":"The Window People",
    "wof:placetype":"venue"
},
  "geometry": {"coordinates":[-0.20258,51.445412],"type":"Point"}
}