{
  "type": "Feature",
  "properties": {
    "addr:full":"Hammingden Farm, Hammingden Lane, Ardingly Haywards Heath East Sussex RH17 6SS",
    "addr:postcode":"rh17 6ss",
    "addr:street":"Hammingden Lane",
    "iso:country":"GB",
    "sg:address":"Hammingden Farm, Hammingden Lane, Ardingly",
    "sg:city":"Haywards Heath",
    "sg:classifiers":[
        {
            "category":"Farming",
            "subcategory":"Livestock Farm",
            "type":"Manufacturing & Wholesale Goods"
        }
    ],
    "sg:phone":"+44 1444 892292",
    "sg:postcode":"RH17 6SS",
    "sg:province":"East Sussex",
    "sg:tags":[
        "others"
    ],
    "wof:name":"D J Kemp",
    "wof:placetype":"venue"
},
  "geometry": {"coordinates":[-0.0781690031,51.0487213135],"type":"Point"}
}