{
  "type": "Feature",
  "properties": {
    "iso:country":"GB",
    "sg:address":"152 Scargreen Avenue",
    "sg:city":"Liverpool",
    "sg:classifiers":[
        {
            "category":"Shopping",
            "subcategory":"Gifts & Souvenirs",
            "type":"Retail Goods"
        }
    ],
    "sg:postcode":"L11 3BE",
    "sg:province":"Merseyside",
    "sg:tags":[
        "shop"
    ],
    "wof:name":"Catch-A-Bargain",
    "wof:placetype":"venue"
},
  "geometry": {"coordinates":[-2.9195580482,53.4471817017],"type":"Point"}
}