{
  "type": "Feature",
  "properties": {
    "iso:country":"GB",
    "sg:address":"Unit 5 The Ickles",
    "sg:city":"Rotherham",
    "sg:classifiers":[
        {
            "category":"Wholesale",
            "subcategory":"Construction Materials",
            "type":"Manufacturing & Wholesale Goods"
        }
    ],
    "sg:phone":"+44 1709 375375",
    "sg:postcode":"S60 1BN",
    "sg:province":"South Yorkshire",
    "sg:tags":[
        "distributor",
        "spring"
    ],
    "wof:name":"Tekad Ltd.",
    "wof:placetype":"venue"
},
  "geometry": {"coordinates":[-1.374474,53.419445],"type":"Point"}
}