{
  "type": "Feature",
  "properties": {
    "iso:country":"GB",
    "sg:address":"1 Hill Cross, Ashford In The Water",
    "sg:city":"Bakewell",
    "sg:classifiers":[
        {
            "category":"Shopping",
            "subcategory":"Antiques",
            "type":"Retail Goods"
        }
    ],
    "sg:postcode":"DE45 1QL",
    "sg:province":"Derbyshire",
    "wof:name":"Peak Fairs",
    "wof:placetype":"venue"
},
  "geometry": {"coordinates":[-1.7087219954,53.2261543274],"type":"Point"}
}