{
  "type": "Feature",
  "properties": {
    "addr:full":"23 Sussex Street London Greater London SW1V 4RR",
    "addr:housenumber":"23",
    "addr:postcode":"sw1v 4rr",
    "addr:street":"Sussex Street",
    "iso:country":"GB",
    "sg:address":"23 Sussex Street",
    "sg:city":"London",
    "sg:classifiers":[
        {
            "category":"Insurance",
            "subcategory":"Insurance Agent",
            "type":"Services"
        }
    ],
    "sg:postcode":"SW1V 4RR",
    "sg:province":"Greater London",
    "wof:name":"Gabriel Consultants",
    "wof:placetype":"venue"
},
  "geometry": {"coordinates":[-0.144014,51.488598],"type":"Point"}
}