{
  "type": "Feature",
  "properties": {
    "addr:full":"21 Roods Kirriemuir Angus DD8 4EZ",
    "addr:housenumber":"21",
    "addr:postcode":"dd8 4ez",
    "addr:street":"Roods Kirriemuir",
    "iso:country":"GB",
    "sg:address":"21 Roods",
    "sg:city":"Kirriemuir",
    "sg:classifiers":[
        {
            "category":"Shopping",
            "subcategory":"Clothing, Apparel, & Fashions",
            "type":"Retail Goods"
        },
        {
            "category":"Shopping",
            "subcategory":"Crafts & Fabrics",
            "type":"Retail Goods"
        }
    ],
    "sg:phone":"+44 1575 573532",
    "sg:postcode":"DD8 4EZ",
    "sg:province":"Angus",
    "sg:tags":[
        "shop",
        "lady",
        "fashionwear"
    ],
    "wof:name":"Rebeccas",
    "wof:placetype":"venue"
},
  "geometry": {"coordinates":[-3.0047180653,56.6740188599],"type":"Point"}
}