{
  "type": "Feature",
  "properties": {
    "iso:country":"GB",
    "sg:address":"25-27 Barton Arcade",
    "sg:city":"Manchester",
    "sg:classifiers":[
        {
            "category":"Professional",
            "subcategory":"Employment Agencies",
            "type":"Services"
        }
    ],
    "sg:phone":"+44 161 833 0873",
    "sg:postcode":"M3 3BB",
    "sg:province":"Greater Manchester",
    "sg:tags":[
        "consultant"
    ],
    "wof:name":"Barclay Scott",
    "wof:placetype":"venue"
},
  "geometry": {"coordinates":[-2.250109,53.479568],"type":"Point"}
}