{
  "type": "Feature",
  "properties": {
    "iso:country":"GB",
    "sg:address":"146 Kinross Close",
    "sg:city":"Warrington",
    "sg:classifiers":[
        {
            "category":"Building & Trades",
            "subcategory":"Plumbing",
            "type":"Services"
        }
    ],
    "sg:phone":"+44 1925 828811",
    "sg:postcode":"WA2 0UR",
    "sg:province":"Cheshire",
    "sg:tags":[
        "central",
        "heating"
    ],
    "wof:name":"M Jackson Plumbing & Heating",
    "wof:placetype":"venue"
},
  "geometry": {"coordinates":[-2.565063,53.422729],"type":"Point"}
}