{
  "type": "Feature",
  "properties": {
    "addr:full":"3 West Street Epsom Surrey KT18 7RL",
    "addr:housenumber":"3",
    "addr:postcode":"kt18 7rl",
    "addr:street":"West Street",
    "iso:country":"GB",
    "sg:address":"3 West Street",
    "sg:city":"Epsom",
    "sg:classifiers":[
        {
            "category":"Real Estate",
            "subcategory":"Real Estate Agent",
            "type":"Services"
        }
    ],
    "sg:phone":"+44 1372 743033",
    "sg:postcode":"KT18 7RL",
    "sg:province":"Surrey",
    "sg:website":"http://www.cairds.co.uk",
    "wof:name":"Cairds The Estate Agents",
    "wof:placetype":"venue"
},
  "geometry": {"coordinates":[-0.2717689872,51.3331108093],"type":"Point"}
}