{
  "type": "Feature",
  "properties": {
    "addr:full":"Dentist Surgery, 83 Loughton Way Buckhurst Hill Essex IG9 6AS",
    "addr:housenumber":"83",
    "addr:postcode":"ig9 6as",
    "addr:street":"Loughton Way",
    "iso:country":"GB",
    "sg:address":"Dentist Surgery, 83 Loughton Way",
    "sg:city":"Buckhurst Hill",
    "sg:classifiers":[
        {
            "category":"Health Services",
            "subcategory":"Dentist",
            "type":"Services"
        }
    ],
    "sg:phone":"+44 20 8504 5787",
    "sg:postcode":"IG9 6AS",
    "sg:province":"Essex",
    "wof:name":"Graham Bond & Associates",
    "wof:placetype":"venue"
},
  "geometry": {"coordinates":[0.030989,51.624306],"type":"Point"}
}