{
  "type": "Feature",
  "properties": {
    "addr:full":"5-6 Marlborough Terrace Bridlington East Riding of Yorkshire YO15 2PA",
    "addr:housenumber":"5-6",
    "addr:postcode":"yo15 2pa",
    "addr:street":"Marlborough Terrace",
    "iso:country":"GB",
    "sg:address":"5-6 Marlborough Terrace",
    "sg:city":"Bridlington",
    "sg:classifiers":[
        {
            "category":"Travel",
            "subcategory":"Hotels & Motels",
            "type":"Entertainment"
        }
    ],
    "sg:phone":"+44 1262 673698",
    "sg:postcode":"YO15 2PA",
    "sg:province":"East Riding of Yorkshire",
    "sg:tags":[
        "self",
        "catering"
    ],
    "wof:name":"St.Margarets Holiday Flats",
    "wof:placetype":"venue"
},
  "geometry": {"coordinates":[-0.1873890013,54.0821685791],"type":"Point"}
}