{
  "type": "Feature",
  "properties": {
    "iso:country":"GB",
    "sg:address":"8 Johnson Street",
    "sg:city":"Mirfield",
    "sg:classifiers":[
        {
            "category":"Home & Garden",
            "subcategory":"Household Appliances",
            "type":"Retail Goods"
        }
    ],
    "sg:phone":"+44 1924 499654",
    "sg:postcode":"WF14 8PQ",
    "sg:province":"West Yorkshire",
    "sg:tags":[
        "electrical"
    ],
    "wof:name":"P B C Services",
    "wof:placetype":"venue"
},
  "geometry": {"coordinates":[-1.6979520321,53.6710014343],"type":"Point"}
}