{
  "type": "Feature",
  "properties": {
    "iso:country":"GB",
    "sg:address":"135 Stilligarry, Isle Of South Uist",
    "sg:city":"Lochboisdale",
    "sg:classifiers":[
        {
            "category":"Professional",
            "subcategory":"Management & Consulting",
            "type":"Services"
        },
        {
            "category":"Organizations",
            "subcategory":"Community Association",
            "type":"Services"
        }
    ],
    "sg:phone":"+44 1870 620238",
    "sg:postcode":"HS8 5RS",
    "sg:province":"Eilean Siar",
    "sg:tags":[
        "organisation",
        "conservation"
    ],
    "wof:name":"Scottish Natural Heritage",
    "wof:placetype":"venue"
},
  "geometry": {"coordinates":[-7.377899,57.32317],"type":"Point"}
}