{
  "type": "Feature",
  "properties": {
    "addr:full":"4 Woodcote Rd Reading Berkshire RG4 7BA",
    "addr:housenumber":"4",
    "addr:postcode":"rg4 7ba",
    "addr:street":"Woodcote Rd",
    "iso:country":"GB",
    "sg:address":"4 Woodcote Rd",
    "sg:city":"Reading",
    "sg:classifiers":[
        {
            "category":"Personal",
            "subcategory":"Beauty Salon",
            "type":"Services"
        }
    ],
    "sg:phone":"+44 118 946 2094",
    "sg:postcode":"RG4 7BA",
    "sg:province":"Berkshire",
    "sg:tags":[
        "unisex",
        "hairdresser"
    ],
    "wof:name":"Hair By Michelle",
    "wof:placetype":"venue"
},
  "geometry": {"coordinates":[-0.984844,51.471909],"type":"Point"}
}