{
  "type": "Feature",
  "properties": {
    "iso:country":"GB",
    "sg:address":"10-12 Perrins Court, Hampstead",
    "sg:city":"London",
    "sg:classifiers":[
        {
            "category":"Banks & Credit Unions",
            "subcategory":"Financial Services",
            "type":"Services"
        }
    ],
    "sg:phone":"+44 20 7431 6633",
    "sg:postcode":"NW3 1QS",
    "sg:province":"Greater London",
    "sg:tags":[
        "consultant"
    ],
    "wof:name":"Style Research Ltd.",
    "wof:placetype":"venue"
},
  "geometry": {"coordinates":[-0.177962,51.555672],"type":"Point"}
}