{
  "type": "Feature",
  "properties": {
    "addr:full":"63 London Road Twickenham Greater London TW1 3BZ",
    "addr:housenumber":"63",
    "addr:postcode":"tw1 3bz",
    "addr:street":"London Road",
    "iso:country":"GB",
    "sg:address":"63 London Road",
    "sg:city":"Twickenham",
    "sg:classifiers":[
        {
            "category":"Banks & Credit Unions",
            "subcategory":"Financial Services",
            "type":"Services"
        }
    ],
    "sg:phone":"+44 20 8891 5941",
    "sg:postcode":"TW1 3BZ",
    "sg:province":"Greater London",
    "sg:tags":[
        "consultant"
    ],
    "wof:name":"Avco Trust",
    "wof:placetype":"venue"
},
  "geometry": {"coordinates":[-0.3296360075,51.4486312866],"type":"Point"}
}