{
  "type": "Feature",
  "properties": {
    "iso:country":"GB",
    "sg:address":"148-150 Wood Street, Walthamstow",
    "sg:city":"London",
    "sg:classifiers":[
        {
            "category":"Government",
            "subcategory":"Post Office",
            "type":"Public Place"
        }
    ],
    "sg:phone":"+44 845 722 3344",
    "sg:postcode":"E17 3HX",
    "sg:province":"Greater London",
    "wof:name":"Post Office Ltd.",
    "wof:placetype":"venue"
},
  "geometry": {"coordinates":[-0.003763,51.587212],"type":"Point"}
}