{
  "type": "Feature",
  "properties": {
    "addr:full":"Church House, Crane St Salisbury Wiltshire SP1 2QB",
    "addr:postcode":"sp1 2qb",
    "addr:street":"Crane St",
    "iso:country":"GB",
    "sg:address":"Church House, Crane St",
    "sg:city":"Salisbury",
    "sg:classifiers":[
        {
            "category":"Organizations",
            "subcategory":"Religious Organization",
            "type":"Services"
        }
    ],
    "sg:phone":"+44 1722 411922",
    "sg:postcode":"SP1 2QB",
    "sg:province":"Wiltshire",
    "sg:tags":[
        "organisation"
    ],
    "wof:name":"Salisbury Diocese",
    "wof:placetype":"venue"
},
  "geometry": {"coordinates":[-1.7979040146,51.0674095154],"type":"Point"}
}