{
  "type": "Feature",
  "properties": {
    "addr:full":"20 Bennett Precinct, Longton Exchange Stoke On Trent Staffordshire ST3 2JA",
    "addr:housenumber":"20",
    "addr:postcode":"st3 2ja",
    "addr:street":"Bennett Precinct",
    "iso:country":"GB",
    "sg:address":"20 Bennett Precinct, Longton Exchange",
    "sg:city":"Stoke On Trent",
    "sg:classifiers":[
        {
            "category":"Shopping",
            "subcategory":"Shoes",
            "type":"Retail Goods"
        }
    ],
    "sg:phone":"+44 1782 319472",
    "sg:postcode":"ST3 2JA",
    "sg:province":"Staffordshire",
    "sg:tags":[
        "shop"
    ],
    "wof:name":"Shoe Value",
    "wof:placetype":"venue"
},
  "geometry": {"coordinates":[-2.13524,52.988041],"type":"Point"}
}