{
  "type": "Feature",
  "properties": {
    "iso:country":"GB",
    "sg:address":"19 Victoria Parade",
    "sg:city":"Broadstairs",
    "sg:classifiers":[
        {
            "category":"Government",
            "subcategory":"Post Office",
            "type":"Public Place"
        }
    ],
    "sg:phone":"+44 1843 866566",
    "sg:postcode":"CT10 1QL",
    "sg:province":"Kent",
    "sg:tags":[
        "print",
        "typesetter"
    ],
    "wof:name":"Blagdon",
    "wof:placetype":"venue"
},
  "geometry": {"coordinates":[1.4418090582,51.3568115234],"type":"Point"}
}