{
  "type": "Feature",
  "properties": {
    "addr:full":"Blaengarw Infants School, Station Street, Blaengarw Bridgend Bridgend CF32 8BA",
    "addr:postcode":"cf32 8ba",
    "addr:street":"Station Street",
    "iso:country":"GB",
    "sg:address":"Blaengarw Infants School, Station Street, Blaengarw",
    "sg:city":"Bridgend",
    "sg:classifiers":[
        {
            "category":"Education",
            "subcategory":"Library",
            "type":"Public Place"
        }
    ],
    "sg:phone":"+44 1656 871598",
    "sg:postcode":"CF32 8BA",
    "sg:province":"Bridgend",
    "sg:tags":[
        "book"
    ],
    "wof:name":"Bleangarw Library",
    "wof:placetype":"venue"
},
  "geometry": {"coordinates":[-3.587724,51.61932],"type":"Point"}
}