{
  "type": "Feature",
  "properties": {
    "addr:full":"Restaurant 9 Food Court Mezzani, Ne The Mall, Cribbs Causeway Pegasus Road Bristol City of Bristol BS12 5DG",
    "addr:housenumber":"9",
    "addr:postcode":"ne;bs12 5dg",
    "addr:street":"Food;Mall Cribbs Causeway Pegasus Road",
    "iso:country":"GB",
    "sg:address":"Restaurant 9 Food Court Mezzani, Ne The Mall, Cribbs Causeway Pegasus Road",
    "sg:city":"Bristol",
    "sg:classifiers":[
        {
            "category":"Cafe",
            "type":"Food & Drink"
        }
    ],
    "sg:phone":"+44 117 950 2922",
    "sg:postcode":"BS12 5DG",
    "sg:province":"City of Bristol",
    "sg:tags":[
        "tea",
        "room"
    ],
    "wof:name":"Starbucks Coffee Co. (U K) Ltd.",
    "wof:placetype":"venue"
},
  "geometry": {"coordinates":[-2.68866,51.482861],"type":"Point"}
}