{
  "type": "Feature",
  "properties": {
    "addr:full":"60 Hayes Way Beckenham Kent BR3 6RS",
    "addr:housenumber":"60",
    "addr:postcode":"br3 6rs",
    "addr:street":"Hayes Way",
    "iso:country":"GB",
    "sg:address":"60 Hayes Way",
    "sg:city":"Beckenham",
    "sg:classifiers":[
        {
            "category":"Professional",
            "type":"Services"
        }
    ],
    "sg:phone":"+44 20 8650 9437",
    "sg:postcode":"BR3 6RS",
    "sg:province":"Kent",
    "sg:tags":[
        "repair",
        "tech",
        "maintenance"
    ],
    "wof:name":"Superior Office Services Ltd.",
    "wof:placetype":"venue"
},
  "geometry": {"coordinates":[-0.006945,51.397354],"type":"Point"}
}