{
  "type": "Feature",
  "properties": {
    "addr:full":"33 New Street, Rothes Aberlour Moray AB38 7BQ",
    "addr:housenumber":"33",
    "addr:postcode":"ab38 7bq",
    "addr:street":"New Street",
    "iso:country":"GB",
    "sg:address":"33 New Street, Rothes",
    "sg:city":"Aberlour",
    "sg:classifiers":[
        {
            "category":"Personal",
            "subcategory":"Beauty Salon",
            "type":"Services"
        },
        {
            "category":"Personal",
            "subcategory":"Barber",
            "type":"Services"
        }
    ],
    "sg:phone":"+44 1340 831836",
    "sg:postcode":"AB38 7BQ",
    "sg:province":"Moray",
    "sg:tags":[
        "unisex",
        "hairdresser"
    ],
    "wof:name":"Rothes Hairdressers",
    "wof:placetype":"venue"
},
  "geometry": {"coordinates":[-3.2080841064,57.5283813477],"type":"Point"}
}