{
  "type": "Feature",
  "properties": {
    "addr:full":"9 Centenary Gardens Coatbridge North Lanarkshire ML5 4BY",
    "addr:housenumber":"9",
    "addr:postcode":"ml5 4by",
    "addr:street":"Centenary Gardens",
    "iso:country":"GB",
    "sg:address":"9 Centenary Gardens",
    "sg:city":"Coatbridge",
    "sg:classifiers":[
        {
            "category":"Health Services",
            "subcategory":"Doctor",
            "type":"Services"
        }
    ],
    "sg:phone":"+44 1236 423355",
    "sg:postcode":"ML5 4BY",
    "sg:province":"North Lanarkshire",
    "sg:tags":[
        "practitioners"
    ],
    "wof:name":"K H Ooi",
    "wof:placetype":"venue"
},
  "geometry": {"coordinates":[-4.030678,55.854057],"type":"Point"}
}