{
  "type": "Feature",
  "properties": {
    "addr:full":"11 Market St Braintree Essex CM7 3YA",
    "addr:housenumber":"11",
    "addr:postcode":"cm7 3ya",
    "addr:street":"Market St",
    "iso:country":"GB",
    "sg:address":"11 Market St",
    "sg:city":"Braintree",
    "sg:classifiers":[
        {
            "category":"Shopping",
            "subcategory":"Clothing, Apparel, & Fashions",
            "type":"Retail Goods"
        }
    ],
    "sg:phone":"+44 1376 323023",
    "sg:postcode":"CM7 3YA",
    "sg:province":"Essex",
    "sg:tags":[
        "shop"
    ],
    "wof:name":"Denim City Jean Co",
    "wof:placetype":"venue"
},
  "geometry": {"coordinates":[0.5523170233,51.8785743713],"type":"Point"}
}