{
  "type": "Feature",
  "properties": {
    "iso:country":"GB",
    "sg:address":"7 Salter Street",
    "sg:city":"Berkeley",
    "sg:classifiers":[
        {
            "category":"Shopping",
            "subcategory":"Clothing, Apparel, & Fashions",
            "type":"Retail Goods"
        }
    ],
    "sg:phone":"+44 1453 511881",
    "sg:postcode":"GL13 9BS",
    "sg:province":"Gloucestershire",
    "sg:tags":[
        "dresswear"
    ],
    "wof:name":"Madisons",
    "wof:placetype":"venue"
},
  "geometry": {"coordinates":[-2.4593520164,51.691192627],"type":"Point"}
}