{
  "type": "Feature",
  "properties": {
    "addr:full":"Unit 21 Imex Business Park, Flaxley Road, Stetchford Birmingham West Midlands B33 9AL",
    "addr:housenumber":"unit 21",
    "addr:postcode":"b33 9al",
    "addr:street":"Imex Business Park Flaxley Road",
    "iso:country":"GB",
    "sg:address":"Unit 21 Imex Business Park, Flaxley Road, Stetchford",
    "sg:city":"Birmingham",
    "sg:classifiers":[
        {
            "category":"Retail",
            "subcategory":"Auto Repair",
            "type":"Services"
        }
    ],
    "sg:phone":"+44 121 789 7893",
    "sg:postcode":"B33 9AL",
    "sg:province":"West Midlands",
    "sg:tags":[
        "modification",
        "garage"
    ],
    "wof:name":"A & D Car Spares & Repairs",
    "wof:placetype":"venue"
},
  "geometry": {"coordinates":[-1.81041,52.4879],"type":"Point"}
}