{
  "type": "Feature",
  "properties": {
    "iso:country":"GB",
    "sg:address":"Unit 6 Abernethy Square, Maritime Quarter",
    "sg:city":"Swansea",
    "sg:classifiers":[
        {
            "category":"Personal",
            "subcategory":"Beauty Salon",
            "type":"Services"
        },
        {
            "category":"Personal",
            "subcategory":"Barber",
            "type":"Services"
        }
    ],
    "sg:phone":"+44 1792 473253",
    "sg:postcode":"SA1 1UH",
    "sg:province":"Neath Port Talbot",
    "sg:tags":[
        "unisex",
        "hairdresser"
    ],
    "wof:name":"Hair By Walter",
    "wof:placetype":"venue"
},
  "geometry": {"coordinates":[-3.936039,51.616131],"type":"Point"}
}