{
  "type": "Feature",
  "properties": {
    "addr:full":"6 Berthon Road, Bull Point Plymouth Devon PL5 1EX",
    "addr:housenumber":"6",
    "addr:postcode":"pl5 1ex",
    "addr:street":"Berthon Road Bull Point",
    "iso:country":"GB",
    "sg:address":"6 Berthon Road, Bull Point",
    "sg:city":"Plymouth",
    "sg:classifiers":[
        {
            "category":"Social Services",
            "subcategory":"Child Care",
            "type":"Services"
        }
    ],
    "sg:phone":"+44 1752 365203",
    "sg:postcode":"PL5 1EX",
    "sg:province":"Devon",
    "sg:tags":[
        "children's",
        "home"
    ],
    "wof:name":"Alexandra House",
    "wof:placetype":"venue"
},
  "geometry": {"coordinates":[-4.1955571175,50.3963890076],"type":"Point"}
}