{
  "type": "Feature",
  "properties": {
    "addr:full":"23 New Mount St Manchester Greater Manchester M4 4DE",
    "addr:housenumber":"23",
    "addr:postcode":"m4 4de",
    "addr:street":"New Mount St",
    "iso:country":"GB",
    "sg:address":"23 New Mount St",
    "sg:city":"Manchester",
    "sg:classifiers":[
        {
            "category":"Professional",
            "subcategory":"Advertising",
            "type":"Services"
        }
    ],
    "sg:postcode":"M4 4DE",
    "sg:province":"Greater Manchester",
    "wof:name":"Dunmore,I,",
    "wof:placetype":"venue"
},
  "geometry": {"coordinates":[-2.2354021072,53.4882545471],"type":"Point"}
}