{
  "type": "Feature",
  "properties": {
    "iso:country":"GB",
    "sg:address":"8 Sackville Road",
    "sg:city":"Bexhill-on-sea",
    "sg:classifiers":[
        {
            "category":"Shopping",
            "subcategory":"Shoes",
            "type":"Retail Goods"
        }
    ],
    "sg:postcode":"TN39 3JA",
    "sg:province":"East Sussex",
    "wof:name":"Micks Shoe Repairs",
    "wof:placetype":"venue"
},
  "geometry": {"coordinates":[0.469408,50.840179],"type":"Point"}
}