{
  "type": "Feature",
  "properties": {
    "addr:full":"1a Knighton Grange Rd Leicester Leicestershire LE2 2LF",
    "addr:housenumber":"1a",
    "addr:postcode":"le2 2lf",
    "addr:street":"Knighton Grange Rd",
    "iso:country":"GB",
    "sg:address":"1a Knighton Grange Rd",
    "sg:city":"Leicester",
    "sg:classifiers":[
        {
            "category":"Health Services",
            "subcategory":"Dentist",
            "type":"Services"
        }
    ],
    "sg:phone":"+44 116 270 0550",
    "sg:postcode":"LE2 2LF",
    "sg:province":"Leicestershire",
    "wof:name":"J Farmer",
    "wof:placetype":"venue"
},
  "geometry": {"coordinates":[-1.1008189917,52.6119651794],"type":"Point"}
}