{
  "type": "Feature",
  "properties": {
    "addr:full":"Ward Road, Bond Avenue Milton Keynes Buckinghamshire MK1 1JA",
    "addr:postcode":"mk1 1ja",
    "addr:street":"Ward Road Bond Avenue",
    "iso:country":"GB",
    "sg:address":"Ward Road, Bond Avenue",
    "sg:city":"Milton Keynes",
    "sg:classifiers":[
        {
            "category":"Wholesale",
            "subcategory":"Construction Materials",
            "type":"Manufacturing & Wholesale Goods"
        }
    ],
    "sg:postcode":"MK1 1JA",
    "sg:province":"Buckinghamshire",
    "sg:tags":[
        "supplier",
        "colour"
    ],
    "wof:name":"Chinghall Ltd.",
    "wof:placetype":"venue"
},
  "geometry": {"coordinates":[-0.719171,52.006657],"type":"Point"}
}