{
  "type": "Feature",
  "properties": {
    "addr:full":"10 Eastcheap Letchworth Hertfordshire SG6 3DE",
    "addr:housenumber":"10",
    "addr:postcode":"sg6 3de",
    "addr:street":"Eastcheap Letchworth",
    "iso:country":"GB",
    "sg:address":"10 Eastcheap",
    "sg:city":"Letchworth",
    "sg:classifiers":[
        {
            "category":"Food & Beverages",
            "subcategory":"Bakery",
            "type":"Retail Goods"
        }
    ],
    "sg:phone":"+44 1462 684511",
    "sg:postcode":"SG6 3DE",
    "sg:province":"Hertfordshire",
    "sg:tags":[
        "baker"
    ],
    "wof:name":"Simmons Bakers",
    "wof:placetype":"venue"
},
  "geometry": {"coordinates":[-0.227955997,51.9789924622],"type":"Point"}
}