{
  "type": "Feature",
  "properties": {
    "iso:country":"GB",
    "sg:address":"552 Galleywood Rd",
    "sg:city":"Chelmsford",
    "sg:classifiers":[
        {
            "category":"Social Services",
            "subcategory":"Job Training",
            "type":"Services"
        }
    ],
    "sg:phone":"+44 1245 603285",
    "sg:postcode":"CM2 8BX",
    "sg:province":"Essex",
    "sg:tags":[
        "translator",
        "interpreter"
    ],
    "wof:name":"Richard Lynn Translator & Interpreter",
    "wof:placetype":"venue"
},
  "geometry": {"coordinates":[0.463188,51.71265],"type":"Point"}
}