{
  "type": "Feature",
  "properties": {
    "addr:full":"Boathouse, Ferry Rd Southsea Hampshire PO4 9LY",
    "addr:postcode":"po4 9ly",
    "addr:street":"Boathouse Ferry Rd",
    "iso:country":"GB",
    "sg:address":"Boathouse, Ferry Rd",
    "sg:city":"Southsea",
    "sg:classifiers":[
        {
            "category":"Organizations",
            "subcategory":"Non-profit Organization",
            "type":"Services"
        }
    ],
    "sg:phone":"+44 23 9281 4811",
    "sg:postcode":"PO4 9LY",
    "sg:province":"Hampshire",
    "sg:tags":[
        "organisation",
        "voluntary",
        "charity"
    ],
    "wof:name":"R N L I",
    "wof:placetype":"venue"
},
  "geometry": {"coordinates":[-1.0298700333,50.7927818298],"type":"Point"}
}