{
  "type": "Feature",
  "properties": {
    "iso:country":"GB",
    "sg:address":"Unit 2, Zetland Buildings, Longbeck Ind Est, Marske By The Sea",
    "sg:city":"Redcar",
    "sg:classifiers":[
        {
            "category":"Retail",
            "subcategory":"Auto Repair",
            "type":"Services"
        }
    ],
    "sg:phone":"+44 1642 480646",
    "sg:postcode":"TS11 6HB",
    "sg:province":"North Yorkshire",
    "sg:tags":[
        "modification",
        "garage"
    ],
    "wof:name":"Mike Richardson",
    "wof:placetype":"venue"
},
  "geometry": {"coordinates":[-1.019694,54.592369],"type":"Point"}
}