{
  "type": "Feature",
  "properties": {
    "addr:full":"Crockford Lane, Chineham Basingstoke Hampshire RG24 9AD",
    "addr:postcode":"rg24 9ad",
    "addr:street":"Crockford Lane",
    "iso:country":"GB",
    "sg:address":"Crockford Lane, Chineham",
    "sg:city":"Basingstoke",
    "sg:classifiers":[
        {
            "category":"Home & Garden",
            "subcategory":"Hardware",
            "type":"Retail Goods"
        }
    ],
    "sg:phone":"+44 1256 352411",
    "sg:postcode":"RG24 9AD",
    "sg:province":"Hampshire",
    "sg:tags":[
        "device",
        "fixing",
        "fastener"
    ],
    "wof:name":"Barlow Fasteners",
    "wof:placetype":"venue"
},
  "geometry": {"coordinates":[-1.0524,51.289009],"type":"Point"}
}