{
  "type": "Feature",
  "properties": {
    "addr:full":"667a Dumbarton Road, Dalmuir Glasgow East Dunbartonshire G81 4DN",
    "addr:housenumber":"667a",
    "addr:postcode":"g81 4dn",
    "addr:street":"Dumbarton Road",
    "iso:country":"GB",
    "sg:address":"667a Dumbarton Road, Dalmuir",
    "sg:city":"Glasgow",
    "sg:classifiers":[
        {
            "category":"Education",
            "subcategory":"Dance Studio",
            "type":"Public Place"
        }
    ],
    "sg:phone":"+44 141 952 9687",
    "sg:postcode":"G81 4DN",
    "sg:province":"East Dunbartonshire",
    "sg:tags":[
        "toning"
    ],
    "wof:name":"Slender World",
    "wof:placetype":"venue"
},
  "geometry": {"coordinates":[-4.4276518822,55.9102172852],"type":"Point"}
}