{
  "type": "Feature",
  "properties": {
    "addr:full":"37 Queen Street, Greetland Halifax West Yorkshire HX4 8DS",
    "addr:housenumber":"37",
    "addr:postcode":"hx4 8ds",
    "addr:street":"Queen Street",
    "iso:country":"GB",
    "sg:address":"37 Queen Street, Greetland",
    "sg:city":"Halifax",
    "sg:classifiers":[
        {
            "category":"Freight",
            "type":"Transportation"
        },
        {
            "category":"Utilities",
            "subcategory":"Fuel Oil & Lpg",
            "type":"Services"
        }
    ],
    "sg:phone":"+44 1422 372389",
    "sg:postcode":"HX4 8DS",
    "sg:province":"West Yorkshire",
    "sg:tags":[
        "haulage",
        "coal",
        "smokeless",
        "road"
    ],
    "wof:name":"Bryvale Fuels (Haulage)",
    "wof:placetype":"venue"
},
  "geometry": {"coordinates":[-1.857254982,53.6847343445],"type":"Point"}
}