{
  "type": "Feature",
  "properties": {
    "iso:country":"GB",
    "sg:address":"64 The Boulevard",
    "sg:city":"Stoke On Trent",
    "sg:classifiers":[
        {
            "category":"Communications",
            "type":"Services"
        }
    ],
    "sg:phone":"+44 1782 838830",
    "sg:postcode":"ST6 6DW",
    "sg:province":"Staffordshire",
    "sg:tags":[
        "tv",
        "video",
        "radio"
    ],
    "wof:name":"A & B Electrics",
    "wof:placetype":"venue"
},
  "geometry": {"coordinates":[-2.207428,53.058804],"type":"Point"}
}