{
  "type": "Feature",
  "properties": {
    "iso:country":"GB",
    "sg:address":"17 Bodorgan Rd",
    "sg:city":"Bournemouth",
    "sg:classifiers":[
        {
            "category":"Travel",
            "subcategory":"Hotels & Motels",
            "type":"Entertainment"
        }
    ],
    "sg:phone":"+44 1202 553684",
    "sg:postcode":"BH2 6NQ",
    "sg:province":"Dorset",
    "sg:tags":[
        "self",
        "catering"
    ],
    "wof:name":"Craven Grange Holiday Flats",
    "wof:placetype":"venue"
},
  "geometry": {"coordinates":[-1.878632,50.725464],"type":"Point"}
}