{
  "type": "Feature",
  "properties": {
    "addr:full":"Larberry Pastures, Longnewton Stockton-on-tees Durham TS21 1BN",
    "addr:postcode":"ts21 1bn",
    "addr:street":"Larberry",
    "iso:country":"GB",
    "sg:address":"Larberry Pastures, Longnewton",
    "sg:city":"Stockton-on-tees",
    "sg:classifiers":[
        {
            "category":"Farming",
            "subcategory":"Farm",
            "type":"Manufacturing & Wholesale Goods"
        }
    ],
    "sg:phone":"+44 1642 583823",
    "sg:postcode":"TS21 1BN",
    "sg:province":"Durham",
    "sg:tags":[
        "mixed",
        "crop"
    ],
    "wof:name":"K T & M Wade",
    "wof:placetype":"venue"
},
  "geometry": {"coordinates":[-1.4205600023,54.5560417175],"type":"Point"}
}