{
  "type": "Feature",
  "properties": {
    "iso:country":"GB",
    "sg:address":"79 Cazenove Road",
    "sg:city":"London",
    "sg:classifiers":[
        {
            "category":"Education",
            "subcategory":"School",
            "type":"Public Place"
        }
    ],
    "sg:phone":"+44 20 8806 4909",
    "sg:postcode":"N16 6BB",
    "sg:province":"Greater London",
    "sg:tags":[
        "independent",
        "preparatory"
    ],
    "wof:name":"Beis Rochel Satmar Girls School",
    "wof:placetype":"venue"
},
  "geometry": {"coordinates":[-0.067955,51.565544],"type":"Point"}
}