{
  "type": "Feature",
  "properties": {
    "addr:full":"18 Winterbrook Wallingford Oxfordshire OX10 9EF",
    "addr:housenumber":"18",
    "addr:postcode":"ox10 9ef",
    "addr:street":"Winterbrook",
    "iso:country":"GB",
    "sg:address":"18 Winterbrook",
    "sg:city":"Wallingford",
    "sg:classifiers":[
        {
            "category":"Health Services",
            "subcategory":"Nursing And Care Facility",
            "type":"Services"
        }
    ],
    "sg:phone":"+44 1491 833922",
    "sg:postcode":"OX10 9EF",
    "sg:province":"Oxfordshire",
    "sg:tags":[
        "home"
    ],
    "wof:name":"Winterbrook Nursing Home",
    "wof:placetype":"venue"
},
  "geometry": {"coordinates":[-1.1296379566,51.5917510986],"type":"Point"}
}