{
  "type": "Feature",
  "properties": {
    "addr:full":"25 Rosemary Avenue, Earley Reading Berkshire RG6 5YQ",
    "addr:housenumber":"25",
    "addr:postcode":"rg6 5yq",
    "addr:street":"Rosemary Avenue",
    "iso:country":"GB",
    "sg:address":"25 Rosemary Avenue, Earley",
    "sg:city":"Reading",
    "sg:classifiers":[
        {
            "category":"Banks & Credit Unions",
            "subcategory":"Financial Services",
            "type":"Services"
        }
    ],
    "sg:phone":"+44 118 975 2191",
    "sg:postcode":"RG6 5YQ",
    "sg:province":"Berkshire",
    "sg:tags":[
        "adviser"
    ],
    "wof:name":"Paul Townson Associates",
    "wof:placetype":"venue"
},
  "geometry": {"coordinates":[-0.9380990267,51.4253234863],"type":"Point"}
}