{
  "type": "Feature",
  "properties": {
    "addr:full":"23 Clarissa Road, Chadwell Heath Romford Essex RM6 4ND",
    "addr:housenumber":"23",
    "addr:postcode":"rm6 4nd",
    "addr:street":"Clarissa Road",
    "iso:country":"GB",
    "sg:address":"23 Clarissa Road, Chadwell Heath",
    "sg:city":"Romford",
    "sg:classifiers":[
        {
            "category":"Building & Trades",
            "subcategory":"Plumbing",
            "type":"Services"
        }
    ],
    "sg:phone":"+44 20 8599 4689",
    "sg:postcode":"RM6 4ND",
    "sg:province":"Essex",
    "sg:tags":[
        "heating"
    ],
    "wof:name":"24hr Plumbing Services",
    "wof:placetype":"venue"
},
  "geometry": {"coordinates":[0.127771005,51.5711936951],"type":"Point"}
}