{
  "type": "Feature",
  "properties": {
    "addr:full":"43 The Cut, Waterloo London Greater London SE1 8LF",
    "addr:housenumber":"43",
    "addr:postcode":"se1 8lf",
    "addr:street":"The Cut",
    "iso:country":"GB",
    "sg:address":"43 The Cut, Waterloo",
    "sg:city":"London",
    "sg:classifiers":[
        {
            "category":"Food & Beverages",
            "subcategory":"Meat & Fish",
            "type":"Retail Goods"
        }
    ],
    "sg:phone":"+44 20 7928 7211",
    "sg:postcode":"SE1 8LF",
    "sg:province":"Greater London",
    "sg:tags":[
        "seafood"
    ],
    "wof:name":"Livebait",
    "wof:placetype":"venue"
},
  "geometry": {"coordinates":[-0.1069340035,51.5031356812],"type":"Point"}
}