{
  "type": "Feature",
  "properties": {
    "iso:country":"GB",
    "sg:address":"407 Linthorpe Road",
    "sg:city":"Middlesbrough",
    "sg:classifiers":[
        {
            "category":"Professional",
            "subcategory":"Lawyer & Legal Services",
            "type":"Services"
        }
    ],
    "sg:phone":"+44 1642 812200",
    "sg:postcode":"TS5 6JN",
    "sg:province":"North Yorkshire",
    "sg:tags":[
        "solicitor"
    ],
    "wof:name":"Craig & Co",
    "wof:placetype":"venue"
},
  "geometry": {"coordinates":[-1.24238,54.562172],"type":"Point"}
}