{
  "type": "Feature",
  "properties": {
    "addr:full":"Stonyflats Farm, Bishopton Stockton-on-tees Durham TS21 1EY",
    "addr:postcode":"ts21 1ey",
    "iso:country":"GB",
    "sg:address":"Stonyflats Farm, Bishopton",
    "sg:city":"Stockton-on-tees",
    "sg:classifiers":[
        {
            "category":"Farming",
            "subcategory":"Livestock Farm",
            "type":"Manufacturing & Wholesale Goods"
        }
    ],
    "sg:phone":"+44 1740 630265",
    "sg:postcode":"TS21 1EY",
    "sg:province":"Durham",
    "sg:tags":[
        "others"
    ],
    "wof:name":"E C Robson",
    "wof:placetype":"venue"
},
  "geometry": {"coordinates":[-1.439239,54.585659],"type":"Point"}
}