{
  "type": "Feature",
  "properties": {
    "iso:country":"GB",
    "sg:address":"1 Sutherland Drive, Wombourne",
    "sg:city":"Wolverhampton",
    "sg:classifiers":[
        {
            "category":"Health Services",
            "subcategory":"Health Practitioner",
            "type":"Services"
        }
    ],
    "sg:phone":"+44 1902 892772",
    "sg:postcode":"WV5 9BB",
    "sg:province":"Shropshire",
    "sg:tags":[
        "hypnotherapists"
    ],
    "wof:name":"Denise Atkins",
    "wof:placetype":"venue"
},
  "geometry": {"coordinates":[-2.1909050941,52.5440368652],"type":"Point"}
}