{
  "type": "Feature",
  "properties": {
    "iso:country":"GB",
    "sg:address":"2 The Broadway",
    "sg:city":"Broadstairs",
    "sg:classifiers":[
        {
            "category":"Shopping",
            "subcategory":"Department Store",
            "type":"Retail Goods"
        }
    ],
    "sg:phone":"+44 1843 861709",
    "sg:postcode":"CT10 2AD",
    "sg:province":"Kent",
    "wof:name":"Anthonio Calzoni",
    "wof:placetype":"venue"
},
  "geometry": {"coordinates":[1.432889,51.360199],"type":"Point"}
}