{
  "type": "Feature",
  "properties": {
    "addr:full":"77 London Rd Newcastle Staffordshire ST5 7LR",
    "addr:housenumber":"77",
    "addr:postcode":"st5 7lr",
    "addr:street":"London Rd",
    "iso:country":"GB",
    "sg:address":"77 London Rd",
    "sg:city":"Newcastle",
    "sg:classifiers":[
        {
            "category":"Food & Beverages",
            "subcategory":"Liquor & Beverages",
            "type":"Retail Goods"
        }
    ],
    "sg:phone":"+44 1782 563652",
    "sg:postcode":"ST5 7LR",
    "sg:province":"Staffordshire",
    "sg:tags":[
        "beer",
        "spirit",
        "wines"
    ],
    "wof:name":"W E Cooper",
    "wof:placetype":"venue"
},
  "geometry": {"coordinates":[-2.249599,53.040737],"type":"Point"}
}