{
  "type": "Feature",
  "properties": {
    "addr:full":"43 The Mall London Greater London W5 3TJ",
    "addr:housenumber":"43",
    "addr:postcode":"w5 3tj",
    "addr:street":"The Mall",
    "iso:country":"GB",
    "sg:address":"43 The Mall",
    "sg:city":"London",
    "sg:classifiers":[
        {
            "category":"Retail",
            "subcategory":"Veterinary Services",
            "type":"Services"
        }
    ],
    "sg:phone":"+44 20 8567 2724",
    "sg:postcode":"W5 3TJ",
    "sg:province":"Greater London",
    "sg:tags":[
        "surgeon"
    ],
    "wof:name":"M & A Young",
    "wof:placetype":"venue"
},
  "geometry": {"coordinates":[-0.298283,51.513454],"type":"Point"}
}