{
  "type": "Feature",
  "properties": {
    "iso:country":"GB",
    "sg:address":"2 King Street",
    "sg:city":"Tavistock",
    "sg:classifiers":[
        {
            "category":"Retail",
            "subcategory":"Repair Shop",
            "type":"Services"
        }
    ],
    "sg:phone":"+44 1822 615318",
    "sg:postcode":"PL19 0DS",
    "sg:province":"Devon",
    "sg:tags":[
        "radio",
        "television",
        "video"
    ],
    "wof:name":"Tavistock Service Centre Ltd.",
    "wof:placetype":"venue"
},
  "geometry": {"coordinates":[-4.146876812,50.550617218],"type":"Point"}
}