{
  "type": "Feature",
  "properties": {
    "iso:country":"GB",
    "sg:address":"62 West Street",
    "sg:city":"Bridlington",
    "sg:classifiers":[
        {
            "category":"Personal",
            "subcategory":"Beauty Salon",
            "type":"Services"
        }
    ],
    "sg:postcode":"YO15 3DZ",
    "sg:province":"East Riding of Yorkshire",
    "sg:tags":[
        "unisex",
        "hairdresser"
    ],
    "wof:name":"Strands",
    "wof:placetype":"venue"
},
  "geometry": {"coordinates":[-0.196069,54.080643],"type":"Point"}
}