{
  "type": "Feature",
  "properties": {
    "iso:country":"GB",
    "sg:address":"Lower Grange Farm House, Chester Road, Kelsall",
    "sg:city":"Tarporley",
    "sg:classifiers":[
        {
            "category":"Health Services",
            "subcategory":"Health Practitioner",
            "type":"Services"
        }
    ],
    "sg:postcode":"CW6 0RJ",
    "sg:province":"Cheshire",
    "sg:tags":[
        "physiotherapist"
    ],
    "wof:name":"P J Oldroyd",
    "wof:placetype":"venue"
},
  "geometry": {"coordinates":[-2.6687550545,53.1593551636],"type":"Point"}
}