{
  "type": "Feature",
  "properties": {
    "addr:full":"97a Ilford Lane Ilford Essex IG1 2RJ",
    "addr:housenumber":"97a",
    "addr:postcode":"ig1 2rj",
    "addr:street":"Ilford Lane",
    "iso:country":"GB",
    "sg:address":"97a Ilford Lane",
    "sg:city":"Ilford",
    "sg:classifiers":[
        {
            "category":"Organizations",
            "subcategory":"Political Organization",
            "type":"Services"
        }
    ],
    "sg:phone":"+44 20 8514 2841",
    "sg:postcode":"IG1 2RJ",
    "sg:province":"Essex",
    "sg:tags":[
        "party"
    ],
    "wof:name":"Ilford North & South Labour Party",
    "wof:placetype":"venue"
},
  "geometry": {"coordinates":[0.0718379989,51.5555114746],"type":"Point"}
}