{
  "type": "Feature",
  "properties": {
    "addr:full":"17 Witley Ave Halesowen West Midlands B63 4DU",
    "addr:housenumber":"17",
    "addr:postcode":"b63 4du",
    "addr:street":"Witley Ave",
    "iso:country":"GB",
    "sg:address":"17 Witley Ave",
    "sg:city":"Halesowen",
    "sg:classifiers":[
        {
            "category":"Building & Trades",
            "subcategory":"Construction",
            "type":"Services"
        }
    ],
    "sg:phone":"+44 121 585 0350",
    "sg:postcode":"B63 4DU",
    "sg:province":"West Midlands",
    "sg:tags":[
        "roofing"
    ],
    "wof:name":"Milne,J,Electrical Services Ltd",
    "wof:placetype":"venue"
},
  "geometry": {"coordinates":[-2.069758,52.453472],"type":"Point"}
}