{
  "type": "Feature",
  "properties": {
    "iso:country":"GB",
    "sg:address":"Units 1-2 Highgrounds Way, Rhodesia",
    "sg:city":"Worksop",
    "sg:classifiers":[
        {
            "category":"Professional",
            "subcategory":"Computer Services",
            "type":"Services"
        }
    ],
    "sg:postcode":"S80 3AF",
    "sg:province":"Nottinghamshire",
    "sg:tags":[
        "system",
        "software"
    ],
    "wof:name":"Choice Peripherals",
    "wof:placetype":"venue"
},
  "geometry": {"coordinates":[-1.154359,53.314564],"type":"Point"}
}