{
  "type": "Feature",
  "properties": {
    "iso:country":"GB",
    "sg:address":"20 - 1-6 Batemans Row",
    "sg:city":"London",
    "sg:classifiers":[
        {
            "category":"Professional",
            "subcategory":"Accounting & Tax Preparation",
            "type":"Services"
        }
    ],
    "sg:postcode":"EC2A 3HH",
    "sg:province":"Greater London",
    "sg:tags":[
        "accountant"
    ],
    "wof:name":"Buckland Associates Ltd",
    "wof:placetype":"venue"
},
  "geometry": {"coordinates":[-0.07892,51.525398],"type":"Point"}
}