{
  "type": "Feature",
  "properties": {
    "addr:full":"Rectory Farm, Golden Lane Chipping Norton Gloucestershire OX7 5YZ",
    "addr:postcode":"ox7 5yz",
    "addr:street":"Rectory;Golden Lane",
    "iso:country":"GB",
    "sg:address":"Rectory Farm, Golden Lane",
    "sg:city":"Chipping Norton",
    "sg:classifiers":[
        {
            "category":"Recreation",
            "subcategory":"Fishing",
            "type":"Entertainment"
        }
    ],
    "sg:postcode":"OX7 5YZ",
    "sg:province":"Gloucestershire",
    "sg:tags":[
        "angling"
    ],
    "wof:name":"Salford Trout Lakes",
    "wof:placetype":"venue"
},
  "geometry": {"coordinates":[-1.545913,51.940407],"type":"Point"}
}