{
  "type": "Feature",
  "properties": {
    "addr:full":"3 Wellington Road, Horsehay Telford Shropshire TF4 3BT",
    "addr:housenumber":"3",
    "addr:postcode":"tf4 3bt",
    "addr:street":"Wellington Road",
    "iso:country":"GB",
    "sg:address":"3 Wellington Road, Horsehay",
    "sg:city":"Telford",
    "sg:classifiers":[
        {
            "category":"Government",
            "subcategory":"Post Office",
            "type":"Public Place"
        }
    ],
    "sg:phone":"+44 1952 630111",
    "sg:postcode":"TF4 3BT",
    "sg:province":"Shropshire",
    "sg:tags":[
        "messenger",
        "courier"
    ],
    "wof:name":"S O S Couriers",
    "wof:placetype":"venue"
},
  "geometry": {"coordinates":[-2.489449,52.658722],"type":"Point"}
}