{
  "type": "Feature",
  "properties": {
    "addr:full":"32 King Edward Avenue Castleford West Yorkshire WF10 2HA",
    "addr:housenumber":"32",
    "addr:postcode":"wf10 2ha",
    "addr:street":"King Edward Avenue",
    "iso:country":"GB",
    "sg:address":"32 King Edward Avenue",
    "sg:city":"Castleford",
    "sg:classifiers":[
        {
            "category":"Building & Trades",
            "subcategory":"Plumbing",
            "type":"Services"
        }
    ],
    "sg:postcode":"WF10 2HA",
    "sg:province":"West Yorkshire",
    "sg:tags":[
        "heating"
    ],
    "wof:name":"John Greenall",
    "wof:placetype":"venue"
},
  "geometry": {"coordinates":[-1.385635972,53.7526092529],"type":"Point"}
}