{
  "type": "Feature",
  "properties": {
    "iso:country":"GB",
    "sg:address":"5 Bracegirdle Road, Headington",
    "sg:city":"Oxford",
    "sg:classifiers":[
        {
            "category":"Place Of Worship",
            "type":"Public Place"
        }
    ],
    "sg:postcode":"OX3 8RJ",
    "sg:province":"Oxfordshire",
    "wof:name":"Assembly of God Oxford",
    "wof:placetype":"venue"
},
  "geometry": {"coordinates":[-1.19755,51.749748],"type":"Point"}
}