{
  "type": "Feature",
  "properties": {
    "addr:full":"1 North Street Bishops Stortford Essex CM23 2LQ",
    "addr:housenumber":"1",
    "addr:postcode":"cm23 2lq",
    "addr:street":"North Street",
    "iso:country":"GB",
    "sg:address":"1 North Street",
    "sg:city":"Bishops Stortford",
    "sg:classifiers":[
        {
            "category":"Travel",
            "subcategory":"Hotels & Motels",
            "type":"Entertainment"
        }
    ],
    "sg:phone":"+44 1279 504128",
    "sg:postcode":"CM23 2LQ",
    "sg:province":"Essex",
    "wof:name":"The George Hotel",
    "wof:placetype":"venue"
},
  "geometry": {"coordinates":[0.158641,51.871342],"type":"Point"}
}