{
  "type": "Feature",
  "properties": {
    "addr:full":"753 Enid Street London Greater London SE16 3RA",
    "addr:housenumber":"753",
    "addr:postcode":"se16 3ra",
    "addr:street":"Enid Street",
    "iso:country":"GB",
    "sg:address":"753 Enid Street",
    "sg:city":"London",
    "sg:classifiers":[
        {
            "category":"Food & Beverages",
            "subcategory":"Liquor & Beverages",
            "type":"Retail Goods"
        }
    ],
    "sg:phone":"+44 20 7608 1811",
    "sg:postcode":"SE16 3RA",
    "sg:province":"Greater London",
    "sg:tags":[
        "beer",
        "spirit",
        "wines"
    ],
    "wof:name":"City Wine Warehouses Ltd.",
    "wof:placetype":"venue"
},
  "geometry": {"coordinates":[-0.0717279986,51.4973869324],"type":"Point"}
}