{
  "type": "Feature",
  "properties": {
    "iso:country":"GB",
    "sg:address":"21 St Pauls Square",
    "sg:city":"Preston",
    "sg:classifiers":[
        {
            "category":"Bars & Pubs",
            "type":"Food & Drink"
        }
    ],
    "sg:phone":"+44 1772 201045",
    "sg:postcode":"PR1 1XA",
    "sg:province":"Lancashire",
    "sg:tags":[
        "pubs",
        "inn"
    ],
    "wof:name":"The Red Rose Inn",
    "wof:placetype":"venue"
},
  "geometry": {"coordinates":[-2.693998,53.763088],"type":"Point"}
}