{
  "type": "Feature",
  "properties": {
    "iso:country":"GB",
    "sg:address":"Ty Newydd, Islawr R-dref",
    "sg:city":"Dolgellau",
    "sg:classifiers":[
        {
            "category":"Real Estate",
            "subcategory":"Architect",
            "type":"Services"
        }
    ],
    "sg:postcode":"LL40 1TL",
    "sg:province":"Gwynedd",
    "wof:name":"Morris Higham",
    "wof:placetype":"venue"
},
  "geometry": {"coordinates":[-3.9201,52.72522],"type":"Point"}
}