{
  "type": "Feature",
  "properties": {
    "addr:full":"75 Wokingham Road Reading Berkshire RG6 1LH",
    "addr:housenumber":"75",
    "addr:postcode":"rg6 1lh",
    "addr:street":"Wokingham Road",
    "iso:country":"GB",
    "sg:address":"75 Wokingham Road",
    "sg:city":"Reading",
    "sg:classifiers":[
        {
            "category":"Government",
            "subcategory":"Post Office",
            "type":"Public Place"
        }
    ],
    "sg:phone":"+44 118 926 2423",
    "sg:postcode":"RG6 1LH",
    "sg:province":"Berkshire",
    "wof:name":"Wokingham Road Post Office",
    "wof:placetype":"venue"
},
  "geometry": {"coordinates":[-0.93687,51.448605],"type":"Point"}
}