{
  "type": "Feature",
  "properties": {
    "addr:full":"42 Chertsey Cres Croydon Surrey CR0 0DA",
    "addr:housenumber":"42",
    "addr:postcode":"cr0 0da",
    "addr:street":"Chertsey Cres",
    "iso:country":"GB",
    "sg:address":"42 Chertsey Cres",
    "sg:city":"Croydon",
    "sg:classifiers":[
        {
            "category":"Building & Trades",
            "subcategory":"Construction",
            "type":"Services"
        }
    ],
    "sg:phone":"+44 1689 800419",
    "sg:postcode":"CR0 0DA",
    "sg:province":"Surrey",
    "sg:tags":[
        "decorator",
        "painter"
    ],
    "wof:name":"M Bolton & Sons",
    "wof:placetype":"venue"
},
  "geometry": {"coordinates":[-0.0172400009,51.3408966064],"type":"Point"}
}