{
  "type": "Feature",
  "properties": {
    "addr:full":"49 The Belfry, Station Road Redhill Surrey RH1 1SE",
    "addr:housenumber":"49",
    "addr:postcode":"rh1 1se",
    "addr:street":"The;Station Road",
    "iso:country":"GB",
    "sg:address":"49 The Belfry, Station Road",
    "sg:city":"Redhill",
    "sg:classifiers":[
        {
            "category":"Personal",
            "subcategory":"Beauty Salon",
            "type":"Services"
        },
        {
            "category":"Personal",
            "subcategory":"Barber",
            "type":"Services"
        }
    ],
    "sg:phone":"+44 1737 780233",
    "sg:postcode":"RH1 1SE",
    "sg:province":"Surrey",
    "sg:tags":[
        "unisex",
        "hairdresser"
    ],
    "wof:name":"Supercuts",
    "wof:placetype":"venue"
},
  "geometry": {"coordinates":[-0.1688790023,51.2381782532],"type":"Point"}
}