{
  "type": "Feature",
  "properties": {
    "addr:full":"18 London Road Grays Essex RM17 5XY",
    "addr:housenumber":"18",
    "addr:postcode":"rm17 5xy",
    "addr:street":"London Road",
    "iso:country":"GB",
    "sg:address":"18 London Road",
    "sg:city":"Grays",
    "sg:classifiers":[
        {
            "category":"Professional",
            "subcategory":"Accounting & Tax Preparation",
            "type":"Services"
        }
    ],
    "sg:phone":"+44 1375 384782",
    "sg:postcode":"RM17 5XY",
    "sg:province":"Essex",
    "sg:tags":[
        "accountant",
        "chartered"
    ],
    "wof:name":"Berg Kaprow Lewis",
    "wof:placetype":"venue"
},
  "geometry": {"coordinates":[0.3218289912,51.4783706665],"type":"Point"}
}