{
  "type": "Feature",
  "properties": {
    "addr:full":"187 High Street Ryde Isle of Wight PO33 2PN",
    "addr:housenumber":"187",
    "addr:postcode":"po33 2pn",
    "addr:street":"High Street",
    "iso:country":"GB",
    "sg:address":"187 High Street",
    "sg:city":"Ryde",
    "sg:classifiers":[
        {
            "category":"Real Estate",
            "subcategory":"Real Estate Agent",
            "type":"Services"
        }
    ],
    "sg:phone":"+44 1983 611511",
    "sg:postcode":"PO33 2PN",
    "sg:province":"Isle of Wight",
    "wof:name":"The Wright Estate Agency",
    "wof:placetype":"venue"
},
  "geometry": {"coordinates":[-1.1634370089,50.7296905518],"type":"Point"}
}