{
  "type": "Feature",
  "properties": {
    "addr:full":"6a Victoria Arcade, Union Street Ryde Isle of Wight PO33 2LQ",
    "addr:housenumber":"6a;arcade",
    "addr:postcode":"po33 2lq",
    "addr:street":"Victoria;Union Street",
    "iso:country":"GB",
    "sg:address":"6a Victoria Arcade, Union Street",
    "sg:city":"Ryde",
    "sg:classifiers":[
        {
            "category":"Home & Garden",
            "subcategory":"Furniture",
            "type":"Retail Goods"
        }
    ],
    "sg:phone":"+44 1983 616979",
    "sg:postcode":"PO33 2LQ",
    "sg:province":"Isle of Wight",
    "wof:name":"K & K Fabrics",
    "wof:placetype":"venue"
},
  "geometry": {"coordinates":[-1.165197,50.728867],"type":"Point"}
}