{
  "type": "Feature",
  "properties": {
    "iso:country":"GB",
    "sg:address":"10 Queens Rd",
    "sg:city":"Norwich",
    "sg:classifiers":[
        {
            "category":"Fast Food",
            "type":"Food & Drink"
        }
    ],
    "sg:phone":"+44 1603 625092",
    "sg:postcode":"NR1 3PR",
    "sg:province":"Norfolk",
    "sg:tags":[
        "away",
        "take"
    ],
    "wof:name":"Jumbo Chinese Restaurant",
    "wof:placetype":"venue"
},
  "geometry": {"coordinates":[1.291761,52.623936],"type":"Point"}
}