{
  "type": "Feature",
  "properties": {
    "addr:full":"Piran House, Nettles Hill Redruth Cornwall TR15 1SN",
    "addr:postcode":"tr15 1sn",
    "addr:street":"Nettles Hill",
    "iso:country":"GB",
    "sg:address":"Piran House, Nettles Hill",
    "sg:city":"Redruth",
    "sg:classifiers":[
        {
            "category":"Government",
            "subcategory":"Office",
            "type":"Public Place"
        }
    ],
    "sg:phone":"+44 1209 310000",
    "sg:postcode":"TR15 1SN",
    "sg:province":"Cornwall",
    "sg:tags":[
        "inland",
        "revenue"
    ],
    "wof:name":"Board of Inland Revenue",
    "wof:placetype":"venue"
},
  "geometry": {"coordinates":[-5.2307338715,50.2351646423],"type":"Point"}
}