{
  "type": "Feature",
  "properties": {
    "addr:full":"The White Rose Centre, 13 High Street Rhyl Conwy LL18 1EN",
    "addr:housenumber":"13",
    "addr:postcode":"ll18 1en",
    "addr:street":"High Street",
    "iso:country":"GB",
    "sg:address":"The White Rose Centre, 13 High Street",
    "sg:city":"Rhyl",
    "sg:classifiers":[
        {
            "category":"Shopping",
            "subcategory":"Baby Store",
            "type":"Retail Goods"
        }
    ],
    "sg:phone":"+44 1745 343524",
    "sg:postcode":"LL18 1EN",
    "sg:province":"Conwy",
    "sg:tags":[
        "nursery",
        "accessory"
    ],
    "wof:name":"Mothercare (U K) Ltd.",
    "wof:placetype":"venue"
},
  "geometry": {"coordinates":[-3.472384,53.311581],"type":"Point"}
}