{
  "type": "Feature",
  "properties": {
    "iso:country":"GB",
    "sg:address":"Tatchbury La",
    "sg:city":"Southampton",
    "sg:classifiers":[
        {
            "category":"Health Services",
            "subcategory":"Nursing And Care Facility",
            "type":"Services"
        }
    ],
    "sg:phone":"+44 23 8081 2352",
    "sg:postcode":"SO40 2HA",
    "sg:province":"Hampshire",
    "sg:tags":[
        "home"
    ],
    "wof:name":"King Johns Hunting Lodge",
    "wof:placetype":"venue"
},
  "geometry": {"coordinates":[-1.535894,50.925003],"type":"Point"}
}