{
  "type": "Feature",
  "properties": {
    "iso:country":"GB",
    "sg:address":"95-105 Poulton Street, Kirkham",
    "sg:city":"Preston",
    "sg:classifiers":[
        {
            "category":"Professional",
            "subcategory":"Printing & Photocopies",
            "type":"Services"
        }
    ],
    "sg:phone":"+44 1772 684928",
    "sg:postcode":"PR4 2DH",
    "sg:province":"Lancashire",
    "sg:tags":[
        "printer"
    ],
    "wof:name":"Roberts Printers & Stationers",
    "wof:placetype":"venue"
},
  "geometry": {"coordinates":[-2.8752260208,53.7820358276],"type":"Point"}
}