{
  "type": "Feature",
  "properties": {
    "addr:full":"137 Becontree Avenue Dagenham Essex RM8 2UL",
    "addr:housenumber":"137",
    "addr:postcode":"rm8 2ul",
    "addr:street":"Becontree Avenue",
    "iso:country":"GB",
    "sg:address":"137 Becontree Avenue",
    "sg:city":"Dagenham",
    "sg:classifiers":[
        {
            "category":"Manufacturing",
            "subcategory":"Watercraft",
            "type":"Manufacturing & Wholesale Goods"
        }
    ],
    "sg:phone":"+44 20 8599 1413",
    "sg:postcode":"RM8 2UL",
    "sg:province":"Essex",
    "sg:tags":[
        "repairer",
        "sailmaker"
    ],
    "wof:name":"M Putt",
    "wof:placetype":"venue"
},
  "geometry": {"coordinates":[0.1178399995,51.55493927],"type":"Point"}
}