{
  "type": "Feature",
  "properties": {
    "addr:full":"41 Clerkenwell Road London Greater London EC1M 5RS",
    "addr:housenumber":"41",
    "addr:postcode":"ec1m 5rs",
    "addr:street":"Clerkenwell Road",
    "iso:country":"GB",
    "sg:address":"41 Clerkenwell Road",
    "sg:city":"London",
    "sg:classifiers":[
        {
            "category":"Shopping",
            "subcategory":"Clothing, Apparel, & Fashions",
            "type":"Retail Goods"
        }
    ],
    "sg:phone":"+44 20 7490 5229",
    "sg:postcode":"EC1M 5RS",
    "sg:province":"Greater London",
    "sg:tags":[
        "shop"
    ],
    "wof:name":"Malapa",
    "wof:placetype":"venue"
},
  "geometry": {"coordinates":[-0.104565002,51.5222854614],"type":"Point"}
}