{
  "type": "Feature",
  "properties": {
    "iso:country":"GB",
    "sg:address":"124 Sandbach Rd",
    "sg:city":"Stoke On Trent",
    "sg:classifiers":[
        {
            "category":"Wholesale",
            "subcategory":"Meat",
            "type":"Manufacturing & Wholesale Goods"
        }
    ],
    "sg:phone":"+44 1270 883751",
    "sg:postcode":"ST7 3RU",
    "sg:province":"Cheshire",
    "sg:tags":[
        "-"
    ],
    "wof:name":"Complimentary Food Co The",
    "wof:placetype":"venue"
},
  "geometry": {"coordinates":[-2.293535,53.113758],"type":"Point"}
}