{
  "type": "Feature",
  "properties": {
    "addr:full":"18 Grosvenor St West End Hampshire W1X 9FD",
    "addr:housenumber":"18",
    "addr:postcode":"w1x 9fd",
    "addr:street":"Grosvenor St",
    "iso:country":"GB",
    "sg:address":"18 Grosvenor St",
    "sg:city":"West End",
    "sg:classifiers":[
        {
            "category":"Professional",
            "subcategory":"Business Services",
            "type":"Services"
        }
    ],
    "sg:phone":"+44 20 7493 6070",
    "sg:postcode":"W1X 9FD",
    "sg:province":"Hampshire",
    "sg:tags":[
        "hospitality",
        "corporate"
    ],
    "wof:name":"As You Like It Productions",
    "wof:placetype":"venue"
},
  "geometry": {"coordinates":[-0.1465920061,51.5119628906],"type":"Point"}
}