{
  "type": "Feature",
  "properties": {
    "addr:full":"Thorney Road, Milking Nook, Newborough Peterborough Cambridgeshire PE6 7PJ",
    "addr:postcode":"pe6 7pj",
    "addr:street":"Thorney Road Milking;Newborough Peterborough",
    "iso:country":"GB",
    "sg:address":"Thorney Road, Milking Nook, Newborough",
    "sg:city":"Peterborough",
    "sg:classifiers":[
        {
            "category":"Wholesale",
            "subcategory":"Sporting Goods",
            "type":"Manufacturing & Wholesale Goods"
        }
    ],
    "sg:phone":"+44 1733 810537",
    "sg:postcode":"PE6 7PJ",
    "sg:province":"Cambridgeshire",
    "sg:tags":[
        "wholesaler",
        "mnfrs",
        "cycle"
    ],
    "wof:name":"Pell & Parker Ltd.",
    "wof:placetype":"venue"
},
  "geometry": {"coordinates":[-0.1844740063,52.6100883484],"type":"Point"}
}