{
  "type": "Feature",
  "properties": {
    "addr:full":"250 Penarth Road Cardiff Cardiff CF11 8TU",
    "addr:housenumber":"250",
    "addr:postcode":"cf11 8tu",
    "addr:street":"Penarth Road",
    "iso:country":"GB",
    "sg:address":"250 Penarth Road",
    "sg:city":"Cardiff",
    "sg:classifiers":[
        {
            "category":"Shopping",
            "subcategory":"Florist",
            "type":"Retail Goods"
        }
    ],
    "sg:phone":"+44 29 2022 5999",
    "sg:postcode":"CF11 8TU",
    "sg:province":"Cardiff",
    "wof:name":"Flowers Direct",
    "wof:placetype":"venue"
},
  "geometry": {"coordinates":[-3.196566,51.460922],"type":"Point"}
}