{
  "type": "Feature",
  "properties": {
    "addr:full":"Randolph Crescent, Garlieston Newton Stewart Dumfries and Galloway DG8 8BG",
    "addr:postcode":"dg8 8bg",
    "addr:street":"Randolph Crescent;Stewart",
    "iso:country":"GB",
    "sg:address":"Randolph Crescent, Garlieston",
    "sg:city":"Newton Stewart",
    "sg:classifiers":[
        {
            "category":"Education",
            "subcategory":"School",
            "type":"Public Place"
        },
        {
            "category":"Government",
            "subcategory":"Office",
            "type":"Public Place"
        }
    ],
    "sg:phone":"+44 1988 600277",
    "sg:postcode":"DG8 8BG",
    "sg:province":"Dumfries and Galloway",
    "sg:tags":[
        "local",
        "authority"
    ],
    "wof:name":"Garlieston Primary School",
    "wof:placetype":"venue"
},
  "geometry": {"coordinates":[-4.373729229,54.7892990112],"type":"Point"}
}