{
  "type": "Feature",
  "properties": {
    "iso:country":"GB",
    "sg:address":"98 Goldstone Villas",
    "sg:city":"Hove",
    "sg:classifiers":[
        {
            "category":"Professional",
            "subcategory":"Business Services",
            "type":"Services"
        }
    ],
    "sg:phone":"+44 1273 383828",
    "sg:postcode":"BN3 3RU",
    "sg:province":"East Sussex",
    "sg:tags":[
        "distributor",
        "film"
    ],
    "wof:name":"Mirage Video",
    "wof:placetype":"venue"
},
  "geometry": {"coordinates":[-0.171208,50.834709],"type":"Point"}
}