{
  "type": "Feature",
  "properties": {
    "iso:country":"GB",
    "sg:address":"Methodist Church Hall, 133b Hatfield Road",
    "sg:city":"St Albans",
    "sg:classifiers":[
        {
            "category":"Farming",
            "subcategory":"Nursery",
            "type":"Manufacturing & Wholesale Goods"
        },
        {
            "category":"Government",
            "subcategory":"Office",
            "type":"Public Place"
        }
    ],
    "sg:phone":"+44 1727 848411",
    "sg:postcode":"AL1 4JS",
    "sg:province":"Hertfordshire",
    "sg:tags":[
        "creche",
        "agency",
        "education",
        "authority"
    ],
    "wof:name":"Albany Montessori School",
    "wof:placetype":"venue"
},
  "geometry": {"coordinates":[-0.337752,51.753189],"type":"Point"}
}