{
  "type": "Feature",
  "properties": {
    "addr:full":"Unit 7, Cotteswold Dairy Estate, Northway Lane Tewkesbury Gloucestershire GL20 8JE",
    "addr:housenumber":"unit 7",
    "addr:postcode":"gl20 8je",
    "addr:street":"Northway Lane",
    "iso:country":"GB",
    "sg:address":"Unit 7, Cotteswold Dairy Estate, Northway Lane",
    "sg:city":"Tewkesbury",
    "sg:classifiers":[
        {
            "category":"Wholesale",
            "subcategory":"Machinery & Supplies",
            "type":"Manufacturing & Wholesale Goods"
        }
    ],
    "sg:phone":"+44 1684 298786",
    "sg:postcode":"GL20 8JE",
    "sg:province":"Gloucestershire",
    "sg:tags":[
        "hydraulic"
    ],
    "wof:name":"Cotswold Hydraulics Ltd.",
    "wof:placetype":"venue"
},
  "geometry": {"coordinates":[-2.1038041115,51.9978027344],"type":"Point"}
}