{
  "type": "Feature",
  "properties": {
    "iso:country":"GB",
    "sg:address":"Penny Street, Bridge Wharf",
    "sg:city":"Lancaster",
    "sg:classifiers":[
        {
            "category":"Recreation",
            "subcategory":"Boat Charter",
            "type":"Entertainment"
        },
        {
            "category":"Bars & Pubs",
            "subcategory":"Wine Bar",
            "type":"Food & Drink"
        }
    ],
    "sg:phone":"+44 1524 849484",
    "sg:postcode":"LA1 1XN",
    "sg:province":"Lancashire",
    "sg:tags":[
        "excursion"
    ],
    "wof:name":"Canal Cruises",
    "wof:placetype":"venue"
},
  "geometry": {"coordinates":[-2.799889,54.046597],"type":"Point"}
}