{
  "type": "Feature",
  "properties": {
    "addr:full":"45 The Square, Aldridge Walsall Staffordshire WS9 8QS",
    "addr:housenumber":"45",
    "addr:postcode":"ws9 8qs",
    "addr:street":"The Square",
    "iso:country":"GB",
    "sg:address":"45 The Square, Aldridge",
    "sg:city":"Walsall",
    "sg:classifiers":[
        {
            "category":"Community Center",
            "subcategory":"Social",
            "type":"Public Place"
        }
    ],
    "sg:phone":"+44 1922 459750",
    "sg:postcode":"WS9 8QS",
    "sg:province":"Staffordshire",
    "sg:tags":[
        "frozen",
        "food",
        "freezer",
        "centre"
    ],
    "wof:name":"Iceland Foods Plc",
    "wof:placetype":"venue"
},
  "geometry": {"coordinates":[-1.915706,52.603863],"type":"Point"}
}