{
  "type": "Feature",
  "properties": {
    "addr:full":"61 Charlotte St London Greater London W1T 4PF",
    "addr:housenumber":"61",
    "addr:postcode":"w1t 4pf",
    "addr:street":"Charlotte St",
    "iso:country":"GB",
    "sg:address":"61 Charlotte St",
    "sg:city":"London",
    "sg:classifiers":[
        {
            "category":"Professional",
            "subcategory":"Art Services",
            "type":"Services"
        }
    ],
    "sg:postcode":"W1T 4PF",
    "sg:province":"Greater London",
    "sg:tags":[
        "photographer"
    ],
    "wof:name":"Donaldson,Matthew,",
    "wof:placetype":"venue"
},
  "geometry": {"coordinates":[-0.136429,51.520111],"type":"Point"}
}