{
  "type": "Feature",
  "properties": {
    "iso:country":"GB",
    "sg:address":"537 Foxhall Road",
    "sg:city":"Ipswich",
    "sg:classifiers":[
        {
            "category":"Education",
            "subcategory":"Preschool",
            "type":"Public Place"
        }
    ],
    "sg:phone":"+44 1473 718296",
    "sg:postcode":"IP3 8LR",
    "sg:province":"Suffolk",
    "sg:tags":[
        "pre",
        "school",
        "playgroups",
        "pre-school"
    ],
    "wof:name":"A B C Pre School",
    "wof:placetype":"venue"
},
  "geometry": {"coordinates":[1.194347,52.05191],"type":"Point"}
}