{
  "type": "Feature",
  "properties": {
    "addr:full":"10 Victoria Street Felixstowe Suffolk IP11 7ER",
    "addr:housenumber":"10",
    "addr:postcode":"ip11 7er",
    "addr:street":"Victoria Street",
    "iso:country":"GB",
    "sg:address":"10 Victoria Street",
    "sg:city":"Felixstowe",
    "sg:classifiers":[
        {
            "category":"Professional",
            "type":"Services"
        },
        {
            "category":"Professional",
            "subcategory":"Lawyer & Legal Services",
            "type":"Services"
        }
    ],
    "sg:phone":"+44 1394 282527",
    "sg:postcode":"IP11 7ER",
    "sg:province":"Suffolk",
    "sg:tags":[
        "marine",
        "solicitor"
    ],
    "wof:name":"John Weston & Co",
    "wof:placetype":"venue"
},
  "geometry": {"coordinates":[1.352222,51.96151],"type":"Point"}
}