{
  "type": "Feature",
  "properties": {
    "addr:full":"65 Ashley Park Avenue Walton-on-thames Surrey KT12 1EU",
    "addr:housenumber":"65",
    "addr:postcode":"kt12 1eu",
    "addr:street":"Ashley Park Avenue",
    "iso:country":"GB",
    "sg:address":"65 Ashley Park Avenue",
    "sg:city":"Walton-on-thames",
    "sg:classifiers":[
        {
            "category":"Professional",
            "subcategory":"Accounting & Tax Preparation",
            "type":"Services"
        }
    ],
    "sg:phone":"+44 1932 246449",
    "sg:postcode":"KT12 1EU",
    "sg:province":"Surrey",
    "sg:tags":[
        "accountant",
        "activity"
    ],
    "wof:name":"K D Popat & Co",
    "wof:placetype":"venue"
},
  "geometry": {"coordinates":[-0.422411,51.37862],"type":"Point"}
}