{
  "type": "Feature",
  "properties": {
    "iso:country":"GB",
    "sg:address":"400 Attercliffe Road",
    "sg:city":"Sheffield",
    "sg:classifiers":[
        {
            "category":"Autos & Motor Vehicles",
            "subcategory":"Auto Supplies",
            "type":"Retail Goods"
        }
    ],
    "sg:phone":"+44 114 244 2779",
    "sg:postcode":"S9 3QN",
    "sg:province":"South Yorkshire",
    "sg:tags":[
        "tyre"
    ],
    "wof:name":"Attercliffe Tyres Ltd",
    "wof:placetype":"venue"
},
  "geometry": {"coordinates":[-1.439235,53.391106],"type":"Point"}
}