{
  "type": "Feature",
  "properties": {
    "iso:country":"GB",
    "sg:address":"89 Gardner Rd",
    "sg:city":"Maidenhead",
    "sg:classifiers":[
        {
            "category":"Sports & Exercise",
            "subcategory":"Tennis Court",
            "type":"Entertainment"
        }
    ],
    "sg:postcode":"SL6 7PR",
    "sg:province":"Berkshire",
    "sg:tags":[
        "breakdown",
        "recovery"
    ],
    "wof:name":"Dey,Mike,",
    "wof:placetype":"venue"
},
  "geometry": {"coordinates":[-0.732609,51.537544],"type":"Point"}
}