{
  "type": "Feature",
  "properties": {
    "addr:full":"9 Beauchamp Place Chelsea Greater London SW3 1NQ",
    "addr:housenumber":"9",
    "addr:postcode":"sw3 1nq",
    "addr:street":"Beauchamp Place",
    "iso:country":"GB",
    "sg:address":"9 Beauchamp Place",
    "sg:city":"Chelsea",
    "sg:classifiers":[
        {
            "category":"Banks & Credit Unions",
            "subcategory":"Financial Services",
            "type":"Services"
        }
    ],
    "sg:phone":"+44 20 7581 3100",
    "sg:postcode":"SW3 1NQ",
    "sg:province":"Greater London",
    "sg:tags":[
        "consultant"
    ],
    "wof:name":"Independent Fund Distribution",
    "wof:placetype":"venue"
},
  "geometry": {"coordinates":[-0.1651619971,51.49792099],"type":"Point"}
}