{
  "type": "Feature",
  "properties": {
    "iso:country":"GB",
    "sg:address":"Front Street, Acomb",
    "sg:city":"York",
    "sg:classifiers":[
        {
            "category":"Bars & Pubs",
            "type":"Food & Drink"
        }
    ],
    "sg:phone":"+44 1904 792532",
    "sg:postcode":"YO24 3BZ",
    "sg:province":"North Yorkshire",
    "sg:tags":[
        "pubs",
        "inn"
    ],
    "wof:name":"The Poacher",
    "wof:placetype":"venue"
},
  "geometry": {"coordinates":[-1.126494,53.954811],"type":"Point"}
}