{
  "type": "Feature",
  "properties": {
    "iso:country":"GB",
    "sg:address":"85 Easton St",
    "sg:city":"High Wycombe",
    "sg:classifiers":[
        {
            "category":"Professional",
            "subcategory":"Credit Reporting & Collection",
            "type":"Services"
        }
    ],
    "sg:phone":"+44 1494 446336",
    "sg:postcode":"HP11 1LT",
    "sg:province":"Buckinghamshire",
    "sg:tags":[
        "collecting",
        "agency"
    ],
    "wof:name":"Established 1956 Central Detective Agency",
    "wof:placetype":"venue"
},
  "geometry": {"coordinates":[-0.746366024,51.6278381348],"type":"Point"}
}