{
  "type": "Feature",
  "properties": {
    "addr:full":"237 Newcastle Street, Burslem Stoke-on-trent Staffordshire ST6 3QW",
    "addr:housenumber":"237",
    "addr:postcode":"staffordshire st6 3qw",
    "addr:street":"Newcastle Street",
    "iso:country":"GB",
    "sg:address":"237 Newcastle Street, Burslem",
    "sg:city":"Stoke-on-trent",
    "sg:classifiers":[
        {
            "category":"Food & Beverages",
            "subcategory":"Meat & Fish",
            "type":"Retail Goods"
        }
    ],
    "sg:phone":"+44 1782 835992",
    "sg:postcode":"ST6 3QW",
    "sg:province":"Staffordshire",
    "sg:tags":[
        "chip"
    ],
    "wof:name":"The Playful Pike",
    "wof:placetype":"venue"
},
  "geometry": {"coordinates":[-2.208142,53.043533],"type":"Point"}
}