{
  "type": "Feature",
  "properties": {
    "addr:full":"14 Meon Road, Oakley Basingstoke Hampshire RG23 7AL",
    "addr:housenumber":"14",
    "addr:postcode":"rg23 7al",
    "addr:street":"Meon Road",
    "iso:country":"GB",
    "sg:address":"14 Meon Road, Oakley",
    "sg:city":"Basingstoke",
    "sg:classifiers":[
        {
            "category":"Building & Trades",
            "subcategory":"Plumbing",
            "type":"Services"
        }
    ],
    "sg:phone":"+44 1256 782232",
    "sg:postcode":"RG23 7AL",
    "sg:province":"Hampshire",
    "sg:tags":[
        "drain",
        "clearance",
        "sewer"
    ],
    "wof:name":"Dyno-Rod Plc",
    "wof:placetype":"venue"
},
  "geometry": {"coordinates":[-1.1742240191,51.2493057251],"type":"Point"}
}