{
  "type": "Feature",
  "properties": {
    "iso:country":"GB",
    "sg:address":"Wattstown",
    "sg:city":"Porth",
    "sg:classifiers":[
        {
            "category":"Professional",
            "type":"Services"
        },
        {
            "category":"Professional",
            "subcategory":"Printing & Photocopies",
            "type":"Services"
        }
    ],
    "sg:phone":"+44 1443 730810",
    "sg:postcode":"CF39 0PE",
    "sg:province":"Bridgend",
    "sg:tags":[
        "directory",
        "printer",
        "pub"
    ],
    "wof:name":"Glenside Printing",
    "wof:placetype":"venue"
},
  "geometry": {"coordinates":[-3.4109508991,51.614982605],"type":"Point"}
}