{
  "type": "Feature",
  "properties": {
    "iso:country":"GB",
    "sg:address":"1-2 Baynes Mews",
    "sg:city":"London",
    "sg:classifiers":[
        {
            "category":"Retail",
            "subcategory":"Auto Repair",
            "type":"Services"
        }
    ],
    "sg:postcode":"NW3 5BH",
    "sg:province":"Greater London",
    "sg:tags":[
        "modification",
        "garage"
    ],
    "wof:name":"King,Ronald E,",
    "wof:placetype":"venue"
},
  "geometry": {"coordinates":[-0.172353,51.548859],"type":"Point"}
}