{
  "type": "Feature",
  "properties": {
    "iso:country":"GB",
    "sg:address":"169 Godstone Road",
    "sg:city":"Kenley",
    "sg:classifiers":[
        {
            "category":"Shopping",
            "subcategory":"Clothing, Apparel, & Fashions",
            "type":"Retail Goods"
        }
    ],
    "sg:phone":"+44 20 8660 7949",
    "sg:postcode":"CR8 5BL",
    "sg:province":"Surrey",
    "sg:tags":[
        "accessory"
    ],
    "sg:website":"http://www.crisco.co.uk",
    "wof:name":"M Criscuolo & Co. Ltd.",
    "wof:placetype":"venue"
},
  "geometry": {"coordinates":[-0.0873650014,51.3195304871],"type":"Point"}
}