{
  "type": "Feature",
  "properties": {
    "iso:country":"GB",
    "sg:address":"3 Callan Gro",
    "sg:city":"South Ockendon",
    "sg:classifiers":[
        {
            "category":"Retail",
            "subcategory":"Auto Repair",
            "type":"Services"
        }
    ],
    "sg:postcode":"RM15 5PW",
    "sg:province":"Essex",
    "sg:tags":[
        "modification",
        "garage"
    ],
    "wof:name":"Montague & Son Auto Repairs",
    "wof:placetype":"venue"
},
  "geometry": {"coordinates":[0.289517,51.50423],"type":"Point"}
}