{
  "type": "Feature",
  "properties": {
    "addr:full":"Response Agency, Callister Youth Club, 19 Argyle St Birkenhead Merseyside L41 1AD",
    "addr:housenumber":"19",
    "addr:postcode":"l41 1ad",
    "addr:street":"Argyle St",
    "iso:country":"GB",
    "sg:address":"Response Agency, Callister Youth Club, 19 Argyle St",
    "sg:city":"Birkenhead",
    "sg:classifiers":[
        {
            "category":"Government",
            "subcategory":"Office",
            "type":"Public Place"
        }
    ],
    "sg:phone":"+44 151 647 7762",
    "sg:postcode":"L41 1AD",
    "sg:province":"Merseyside",
    "sg:tags":[
        "local"
    ],
    "wof:name":"Wirral Metropolitan Borough Council",
    "wof:placetype":"venue"
},
  "geometry": {"coordinates":[-3.0254900455,53.3925590515],"type":"Point"}
}