{
  "type": "Feature",
  "properties": {
    "addr:full":"London Road Brighton West Sussex BN45 7FJ",
    "addr:postcode":"bn45 7fj",
    "addr:street":"London Road",
    "iso:country":"GB",
    "sg:address":"London Road",
    "sg:city":"Brighton",
    "sg:classifiers":[
        {
            "category":"Fast Food",
            "type":"Food & Drink"
        }
    ],
    "sg:phone":"+44 1273 843302",
    "sg:postcode":"BN45 7FJ",
    "sg:province":"West Sussex",
    "sg:tags":[
        "away",
        "take"
    ],
    "wof:name":"Hunger Pangs",
    "wof:placetype":"venue"
},
  "geometry": {"coordinates":[-0.1727029979,50.9004211426],"type":"Point"}
}