{
  "type": "Feature",
  "properties": {
    "iso:country":"GB",
    "sg:address":"Cedar Rd",
    "sg:city":"Liverpool",
    "sg:classifiers":[
        {
            "category":"Education",
            "subcategory":"School",
            "type":"Public Place"
        }
    ],
    "sg:phone":"+44 151 525 6326",
    "sg:postcode":"L9 9AF",
    "sg:province":"Merseyside",
    "sg:tags":[
        "local",
        "authority"
    ],
    "wof:name":"Archbishop Beck R.C High School",
    "wof:placetype":"venue"
},
  "geometry": {"coordinates":[-2.9575340748,53.4639511108],"type":"Point"}
}