{
  "type": "Feature",
  "properties": {
    "iso:country":"GB",
    "sg:address":"2 Knight Street",
    "sg:city":"Mountain Ash",
    "sg:classifiers":[
        {
            "category":"Personal",
            "subcategory":"Beauty Salon",
            "type":"Services"
        }
    ],
    "sg:phone":"+44 1443 472708",
    "sg:postcode":"CF45 3EY",
    "sg:province":"Rhondda, Cynon, Taff",
    "sg:tags":[
        "unisex",
        "hairdresser"
    ],
    "wof:name":"Jennys",
    "wof:placetype":"venue"
},
  "geometry": {"coordinates":[-3.379245,51.682514],"type":"Point"}
}