{
  "type": "Feature",
  "properties": {
    "iso:country":"GB",
    "sg:address":"97 Wolverhampton Rd, Pelsall",
    "sg:city":"Walsall",
    "sg:classifiers":[
        {
            "category":"Food & Beverages",
            "subcategory":"Liquor & Beverages",
            "type":"Retail Goods"
        }
    ],
    "sg:phone":"+44 1922 682502",
    "sg:postcode":"WS3 4AA",
    "sg:province":"Staffordshire",
    "sg:tags":[
        "beer",
        "spirit",
        "wines"
    ],
    "wof:name":"Leamore Wines",
    "wof:placetype":"venue"
},
  "geometry": {"coordinates":[-1.9713449478,52.6331825256],"type":"Point"}
}