{
  "type": "Feature",
  "properties": {
    "iso:country":"GB",
    "sg:address":"41 Borough Pavement, Grange Precinct",
    "sg:city":"Birkenhead",
    "sg:classifiers":[
        {
            "category":"Home & Garden",
            "subcategory":"Home Furnishings",
            "type":"Retail Goods"
        },
        {
            "category":"Home & Garden",
            "subcategory":"Furniture",
            "type":"Retail Goods"
        }
    ],
    "sg:phone":"+44 151 647 6851",
    "sg:postcode":"CH41 2XX",
    "sg:province":"Merseyside",
    "sg:tags":[
        "soft",
        "sale"
    ],
    "wof:name":"Waldmans",
    "wof:placetype":"venue"
},
  "geometry": {"coordinates":[-3.033011,53.38562],"type":"Point"}
}