{
  "type": "Feature",
  "properties": {
    "addr:full":"22 Buchanan Street, Balfron Glasgow Argyll and Bute G63 0TT",
    "addr:housenumber":"22",
    "addr:postcode":"g63 0tt",
    "addr:street":"Buchanan Street",
    "iso:country":"GB",
    "sg:address":"22 Buchanan Street, Balfron",
    "sg:city":"Glasgow",
    "sg:classifiers":[
        {
            "category":"Health Services",
            "subcategory":"Podiatrist",
            "type":"Services"
        }
    ],
    "sg:postcode":"G63 0TT",
    "sg:province":"Argyll and Bute",
    "sg:tags":[
        "podiatrists",
        "chiropodist"
    ],
    "wof:name":"Balfron Chiropody Practice",
    "wof:placetype":"venue"
},
  "geometry": {"coordinates":[-4.335574,56.067669],"type":"Point"}
}