{
  "type": "Feature",
  "properties": {
    "iso:country":"GB",
    "sg:address":"10 Barncliffe Drive",
    "sg:city":"Sheffield",
    "sg:classifiers":[
        {
            "category":"Manufacturing",
            "subcategory":"Tools & Machinery",
            "type":"Manufacturing & Wholesale Goods"
        }
    ],
    "sg:phone":"+44 114 230 5220",
    "sg:postcode":"S10 4DE",
    "sg:province":"South Yorkshire",
    "sg:tags":[
        "manufacture",
        "powertools",
        "power",
        "supply"
    ],
    "wof:name":"Haywood Industrial Supplies Ltd",
    "wof:placetype":"venue"
},
  "geometry": {"coordinates":[-1.551476,53.372307],"type":"Point"}
}