{
  "type": "Feature",
  "properties": {
    "addr:full":"54 Barrington Road Altrincham Cheshire WA14 1HY",
    "addr:housenumber":"54",
    "addr:postcode":"wa14 1hy",
    "addr:street":"Barrington Road",
    "iso:country":"GB",
    "sg:address":"54 Barrington Road",
    "sg:city":"Altrincham",
    "sg:classifiers":[
        {
            "category":"Travel",
            "subcategory":"Hotels & Motels",
            "type":"Entertainment"
        }
    ],
    "sg:phone":"+44 161 929 8545",
    "sg:postcode":"WA14 1HY",
    "sg:province":"Cheshire",
    "wof:name":"Gaskell House Service Apartments",
    "wof:placetype":"venue"
},
  "geometry": {"coordinates":[-2.349034071,53.3933448792],"type":"Point"}
}