{
  "type": "Feature",
  "properties": {
    "iso:country":"GB",
    "sg:address":"26 Ochil Street, Tullibody",
    "sg:city":"Alloa",
    "sg:classifiers":[
        {
            "category":"Food & Beverages",
            "subcategory":"Supermarket",
            "type":"Retail Goods"
        }
    ],
    "sg:phone":"+44 1259 218769",
    "sg:postcode":"FK10 2PT",
    "sg:province":"Clackmannanshire",
    "wof:name":"Scottish Co-Operative",
    "wof:placetype":"venue"
},
  "geometry": {"coordinates":[-3.837987,56.134258],"type":"Point"}
}