{
  "type": "Feature",
  "properties": {
    "addr:full":"Glebe Farm, Mildenhall Marlborough Berkshire SN8 2LR",
    "addr:postcode":"sn8 2lr",
    "iso:country":"GB",
    "sg:address":"Glebe Farm, Mildenhall",
    "sg:city":"Marlborough",
    "sg:classifiers":[
        {
            "category":"Building & Trades",
            "subcategory":"Construction",
            "type":"Services"
        }
    ],
    "sg:postcode":"SN8 2LR",
    "sg:province":"Berkshire",
    "sg:tags":[
        "builder"
    ],
    "wof:name":"Baverstock Properties Ltd.",
    "wof:placetype":"venue"
},
  "geometry": {"coordinates":[-1.6999690533,51.4256095886],"type":"Point"}
}