{
  "type": "Feature",
  "properties": {
    "iso:country":"GB",
    "sg:address":"7 Trafford Grove",
    "sg:city":"Leeds",
    "sg:classifiers":[
        {
            "category":"Retail",
            "subcategory":"Auto Repair",
            "type":"Services"
        }
    ],
    "sg:phone":"+44 113 249 0787",
    "sg:postcode":"LS9 6AH",
    "sg:province":"West Yorkshire",
    "sg:tags":[
        "modification",
        "garage",
        "related"
    ],
    "wof:name":"Primrose Garage",
    "wof:placetype":"venue"
},
  "geometry": {"coordinates":[-1.5069090128,53.8097496033],"type":"Point"}
}