{
  "type": "Feature",
  "properties": {
    "addr:full":"2 Arkwright Road Eastbourne East Sussex BN23 6QL",
    "addr:housenumber":"2",
    "addr:postcode":"bn23 6ql",
    "addr:street":"Arkwright Road",
    "iso:country":"GB",
    "sg:address":"2 Arkwright Road",
    "sg:city":"Eastbourne",
    "sg:classifiers":[
        {
            "category":"Retail",
            "subcategory":"Auto Repair",
            "type":"Services"
        }
    ],
    "sg:phone":"+44 1323 507887",
    "sg:postcode":"BN23 6QL",
    "sg:province":"East Sussex",
    "sg:tags":[
        "body",
        "car"
    ],
    "wof:name":"M V M Motors",
    "wof:placetype":"venue"
},
  "geometry": {"coordinates":[0.285421,50.796799],"type":"Point"}
}