{
  "type": "Feature",
  "properties": {
    "addr:full":"5 Suez St Warrington Cheshire WA1 1EF",
    "addr:housenumber":"5",
    "addr:postcode":"wa1 1ef",
    "addr:street":"Suez St",
    "iso:country":"GB",
    "sg:address":"5 Suez St",
    "sg:city":"Warrington",
    "sg:classifiers":[
        {
            "category":"Education",
            "subcategory":"Vocational School",
            "type":"Public Place"
        }
    ],
    "sg:phone":"+44 1925 414125",
    "sg:postcode":"WA1 1EF",
    "sg:province":"Cheshire",
    "sg:tags":[
        "hairdressing"
    ],
    "wof:name":"Hairdressing Training of Warrington",
    "wof:placetype":"venue"
},
  "geometry": {"coordinates":[-2.595197,53.387802],"type":"Point"}
}