{
  "type": "Feature",
  "properties": {
    "addr:full":"Unit 40 Darlaston Central Trading E, St Wednesbury West Midlands WS10 8XB",
    "addr:housenumber":"unit 40",
    "addr:postcode":"ws10 8xb",
    "addr:street":"E St",
    "iso:country":"GB",
    "sg:address":"Unit 40 Darlaston Central Trading E, St",
    "sg:city":"Wednesbury",
    "sg:classifiers":[
        {
            "category":"Professional",
            "subcategory":"Engineering",
            "type":"Services"
        }
    ],
    "sg:postcode":"WS10 8XB",
    "sg:province":"West Midlands",
    "wof:name":"Viking Engineering Services",
    "wof:placetype":"venue"
},
  "geometry": {"coordinates":[-2.019254,52.552731],"type":"Point"}
}