{
  "type": "Feature",
  "properties": {
    "addr:full":"302 Aigburth Road Liverpool Merseyside L17 9PW",
    "addr:housenumber":"302",
    "addr:postcode":"l17 9pw",
    "addr:street":"Aigburth Road",
    "iso:country":"GB",
    "sg:address":"302 Aigburth Road",
    "sg:city":"Liverpool",
    "sg:classifiers":[
        {
            "category":"Shopping",
            "subcategory":"News",
            "type":"Retail Goods"
        }
    ],
    "sg:phone":"+44 151 727 5187",
    "sg:postcode":"L17 9PW",
    "sg:province":"Merseyside",
    "sg:tags":[
        "newsagent"
    ],
    "wof:name":"Allsorts",
    "wof:placetype":"venue"
},
  "geometry": {"coordinates":[-2.938662,53.374767],"type":"Point"}
}