{
  "type": "Feature",
  "properties": {
    "addr:full":"Boundary Road Newark Nottinghamshire NG24 4AU",
    "addr:postcode":"ng24 4au",
    "addr:street":"Boundary Road",
    "iso:country":"GB",
    "sg:address":"Boundary Road",
    "sg:city":"Newark",
    "sg:classifiers":[
        {
            "category":"Place Of Worship",
            "type":"Public Place"
        },
        {
            "category":"Education",
            "subcategory":"School",
            "type":"Public Place"
        }
    ],
    "sg:phone":"+44 1636 689177",
    "sg:postcode":"NG24 4AU",
    "sg:province":"Nottinghamshire",
    "sg:tags":[
        "local",
        "authority"
    ],
    "wof:name":"Holy Trinity R C Primary & Nursery School",
    "wof:placetype":"venue"
},
  "geometry": {"coordinates":[-0.8171319962,53.0708274841],"type":"Point"}
}