{
  "type": "Feature",
  "properties": {
    "iso:country":"GB",
    "sg:address":"The Manor House, 7 Beam Street",
    "sg:city":"Nantwich",
    "sg:classifiers":[
        {
            "category":"Shopping",
            "subcategory":"Antiques",
            "type":"Retail Goods"
        }
    ],
    "sg:phone":"+44 1270 610615",
    "sg:postcode":"CW5 5LR",
    "sg:province":"Cheshire",
    "wof:name":"Nantwich Antiques",
    "wof:placetype":"venue"
},
  "geometry": {"coordinates":[-2.5227389336,53.0684127808],"type":"Point"}
}