{
  "type": "Feature",
  "properties": {
    "iso:country":"GB",
    "sg:address":"2 Rosecroft Lane",
    "sg:city":"Welwyn",
    "sg:classifiers":[
        {
            "category":"Banks & Credit Unions",
            "subcategory":"Financial Services",
            "type":"Services"
        }
    ],
    "sg:phone":"+44 1438 716766",
    "sg:postcode":"AL6 0UB",
    "sg:province":"Hertfordshire",
    "sg:tags":[
        "consultant"
    ],
    "wof:name":"McMurdock Barry Commercial Finacial Services",
    "wof:placetype":"venue"
},
  "geometry": {"coordinates":[-0.185772,51.845707],"type":"Point"}
}