{
  "type": "Feature",
  "properties": {
    "iso:country":"GB",
    "sg:address":"27 Lester Drive, Worle",
    "sg:city":"Weston Super Mare",
    "sg:classifiers":[
        {
            "category":"Building & Trades",
            "subcategory":"Construction",
            "type":"Services"
        }
    ],
    "sg:phone":"+44 1934 513500",
    "sg:postcode":"BS22 6NL",
    "sg:province":"Somerset",
    "sg:tags":[
        "tiling",
        "contractor"
    ],
    "wof:name":"Anthony P Thompson",
    "wof:placetype":"venue"
},
  "geometry": {"coordinates":[-2.918627,51.363216],"type":"Point"}
}