{
  "type": "Feature",
  "properties": {
    "addr:full":"37 Littlebeck Drive Darlington Durham DL1 2TN",
    "addr:housenumber":"37",
    "addr:postcode":"dl1 2tn",
    "addr:street":"Littlebeck Drive",
    "iso:country":"GB",
    "sg:address":"37 Littlebeck Drive",
    "sg:city":"Darlington",
    "sg:classifiers":[
        {
            "category":"Professional",
            "subcategory":"Engineering",
            "type":"Services"
        },
        {
            "category":"Professional",
            "subcategory":"Detective & Security Services",
            "type":"Services"
        }
    ],
    "sg:phone":"+44 1325 480254",
    "sg:postcode":"DL1 2TN",
    "sg:province":"Durham",
    "sg:tags":[
        "burglar",
        "alarm",
        "system",
        "contractor",
        "electrical",
        "engineer"
    ],
    "wof:name":"Alarmwise Security Services",
    "wof:placetype":"venue"
},
  "geometry": {"coordinates":[-1.5363260508,54.5407142639],"type":"Point"}
}