{
  "type": "Feature",
  "properties": {
    "iso:country":"GB",
    "sg:address":"12 Cronton La",
    "sg:city":"Widnes",
    "sg:classifiers":[
        {
            "category":"Shopping",
            "subcategory":"Clothing, Apparel, & Fashions",
            "type":"Retail Goods"
        }
    ],
    "sg:postcode":"WA8 5AJ",
    "sg:province":"Cheshire",
    "sg:tags":[
        "shop"
    ],
    "wof:name":"Whitehead,M,",
    "wof:placetype":"venue"
},
  "geometry": {"coordinates":[-2.7406289577,53.3897399902],"type":"Point"}
}