{
  "type": "Feature",
  "properties": {
    "addr:full":"24 Wyndham Street Bridgend Bridgend CF31 1EH",
    "addr:housenumber":"24",
    "addr:postcode":"cf31 1eh",
    "addr:street":"Wyndham Street",
    "iso:country":"GB",
    "sg:address":"24 Wyndham Street",
    "sg:city":"Bridgend",
    "sg:classifiers":[
        {
            "category":"Shopping",
            "subcategory":"Florist",
            "type":"Retail Goods"
        }
    ],
    "sg:phone":"+44 1656 652028",
    "sg:postcode":"CF31 1EH",
    "sg:province":"Bridgend",
    "wof:name":"A J Guttridge Florists",
    "wof:placetype":"venue"
},
  "geometry": {"coordinates":[-3.577222,51.507729],"type":"Point"}
}