{
  "type": "Feature",
  "properties": {
    "iso:country":"GB",
    "sg:address":"Bank Street, Pulham Market",
    "sg:city":"Diss",
    "sg:classifiers":[
        {
            "category":"Place Of Worship",
            "type":"Public Place"
        },
        {
            "category":"Organizations",
            "subcategory":"Non-profit Organization",
            "type":"Services"
        }
    ],
    "sg:phone":"+44 1379 852474",
    "sg:postcode":"IP21 4TG",
    "sg:province":"Norfolk",
    "sg:tags":[
        "charitable",
        "organisation",
        "charity"
    ],
    "wof:name":"Pulham Market Methodist Church",
    "wof:placetype":"venue"
},
  "geometry": {"coordinates":[1.229444,52.430771],"type":"Point"}
}