{
  "type": "Feature",
  "properties": {
    "addr:full":"6 Long Wyre St Colchester Essex CO1 1LH",
    "addr:housenumber":"6",
    "addr:postcode":"co1 1lh",
    "addr:street":"Long Wyre St",
    "iso:country":"GB",
    "sg:address":"6 Long Wyre St",
    "sg:city":"Colchester",
    "sg:classifiers":[
        {
            "category":"Shopping",
            "subcategory":"Discount & Variety Stores",
            "type":"Retail Goods"
        }
    ],
    "sg:phone":"+44 1206 766536",
    "sg:postcode":"CO1 1LH",
    "sg:province":"Essex",
    "sg:tags":[
        "shop",
        "model"
    ],
    "wof:name":"Beatties",
    "wof:placetype":"venue"
},
  "geometry": {"coordinates":[0.902113,51.888409],"type":"Point"}
}