{
  "type": "Feature",
  "properties": {
    "addr:full":"Leger Way Doncaster South Yorkshire DN2 5RW",
    "addr:postcode":"dn2 5rw",
    "addr:street":"Leger Way",
    "iso:country":"GB",
    "sg:address":"Leger Way",
    "sg:city":"Doncaster",
    "sg:classifiers":[
        {
            "category":"Education",
            "subcategory":"School",
            "type":"Public Place"
        },
        {
            "category":"Government",
            "subcategory":"Office",
            "type":"Public Place"
        }
    ],
    "sg:phone":"+44 1302 340287",
    "sg:postcode":"DN2 5RW",
    "sg:province":"South Yorkshire",
    "sg:tags":[
        "local",
        "authority"
    ],
    "wof:name":"Doncaster Metropolitan Borough Council",
    "wof:placetype":"venue"
},
  "geometry": {"coordinates":[-1.0881969929,53.5369300842],"type":"Point"}
}