{
  "type": "Feature",
  "properties": {
    "addr:full":"464 Edgware Road London Greater London W2 1EJ",
    "addr:housenumber":"464",
    "addr:postcode":"w2 1ej",
    "addr:street":"Edgware Road",
    "iso:country":"GB",
    "sg:address":"464 Edgware Road",
    "sg:city":"London",
    "sg:classifiers":[
        {
            "category":"Home & Garden",
            "subcategory":"Building Materials",
            "type":"Retail Goods"
        }
    ],
    "sg:phone":"+44 20 7723 0801",
    "sg:postcode":"W2 1EJ",
    "sg:province":"Greater London",
    "sg:tags":[
        "furnishers",
        "bathroom",
        "planner"
    ],
    "wof:name":"Embassy Bathroom Centre",
    "wof:placetype":"venue"
},
  "geometry": {"coordinates":[-0.1750860065,51.5235939026],"type":"Point"}
}