{
  "type": "Feature",
  "properties": {
    "iso:country":"GB",
    "sg:address":"100 Ewell By-pass",
    "sg:city":"Epsom",
    "sg:classifiers":[
        {
            "category":"Sports & Exercise",
            "subcategory":"Sports Center",
            "type":"Entertainment"
        }
    ],
    "sg:phone":"+44 20 8394 1987",
    "sg:postcode":"KT17 2PP",
    "sg:province":"Surrey",
    "sg:tags":[
        "shop",
        "good"
    ],
    "wof:name":"Mayfair (Surrey) Ltd.",
    "wof:placetype":"venue"
},
  "geometry": {"coordinates":[-0.245497,51.353676],"type":"Point"}
}