{
  "type": "Feature",
  "properties": {
    "addr:full":"Halse Taunton Devon TA4 3AQ",
    "addr:postcode":"ta4 3aq",
    "addr:street":"Halse",
    "iso:country":"GB",
    "sg:address":"Halse",
    "sg:city":"Taunton",
    "sg:classifiers":[
        {
            "category":"Professional",
            "subcategory":"Advertising",
            "type":"Services"
        },
        {
            "category":"Professional",
            "subcategory":"Printing & Photocopies",
            "type":"Services"
        }
    ],
    "sg:phone":"+44 1823 433917",
    "sg:postcode":"TA4 3AQ",
    "sg:province":"Devon",
    "sg:tags":[
        "agency",
        "printer"
    ],
    "wof:name":"The Ticket Wallet Co. Ltd.",
    "wof:placetype":"venue"
},
  "geometry": {"coordinates":[-3.2249,51.046791],"type":"Point"}
}