{
  "type": "Feature",
  "properties": {
    "addr:full":"Roseveare Residential Park, Gothers, St Dennis St Austell Cornwall PL26 8DG",
    "addr:postcode":"pl26 8dg",
    "addr:street":"St",
    "iso:country":"GB",
    "sg:address":"Roseveare Residential Park, Gothers, St Dennis",
    "sg:city":"St Austell",
    "sg:classifiers":[
        {
            "category":"Manufacturing",
            "subcategory":"Buildings",
            "type":"Manufacturing & Wholesale Goods"
        }
    ],
    "sg:phone":"+44 1726 822495",
    "sg:postcode":"PL26 8DG",
    "sg:province":"Cornwall",
    "sg:tags":[
        "mobile",
        "home"
    ],
    "wof:name":"Roseveare Residential Park",
    "wof:placetype":"venue"
},
  "geometry": {"coordinates":[-4.8632898331,50.3888282776],"type":"Point"}
}