{
  "type": "Feature",
  "properties": {
    "addr:full":"Turnpike Close Worcester Worcestershire WR2 6AB",
    "addr:postcode":"wr2 6ab",
    "addr:street":"Turnpike Close",
    "iso:country":"GB",
    "sg:address":"Turnpike Close",
    "sg:city":"Worcester",
    "sg:classifiers":[
        {
            "category":"Education",
            "subcategory":"Special Training",
            "type":"Public Place"
        }
    ],
    "sg:phone":"+44 1905 423403",
    "sg:postcode":"WR2 6AB",
    "sg:province":"Worcestershire",
    "sg:tags":[
        "school"
    ],
    "wof:name":"Manor Park Day Special School",
    "wof:placetype":"venue"
},
  "geometry": {"coordinates":[-2.2378690243,52.1972236633],"type":"Point"}
}