{
  "type": "Feature",
  "properties": {
    "iso:country":"GB",
    "sg:address":"1a Manorgate Road",
    "sg:city":"Kingston-upon-thames",
    "sg:classifiers":[
        {
            "category":"Retail",
            "subcategory":"Auto Repair",
            "type":"Services"
        }
    ],
    "sg:phone":"+44 20 8549 9299",
    "sg:postcode":"KT2 7AW",
    "sg:province":"Greater London",
    "sg:tags":[
        "modification",
        "garage"
    ],
    "wof:name":"National Clutch & Brake",
    "wof:placetype":"venue"
},
  "geometry": {"coordinates":[-0.2869279981,51.4138450623],"type":"Point"}
}