{
  "type": "Feature",
  "properties": {
    "addr:full":"7 Willow Court, Parkway Industrial Estate Plymouth Devon PL6 8LQ",
    "addr:housenumber":"7;estate",
    "addr:postcode":"pl6 8lq",
    "addr:street":"Willow Court Parkway Industrial",
    "iso:country":"GB",
    "sg:address":"7 Willow Court, Parkway Industrial Estate",
    "sg:city":"Plymouth",
    "sg:classifiers":[
        {
            "category":"Autos & Motor Vehicles",
            "subcategory":"Auto Supplies",
            "type":"Retail Goods"
        }
    ],
    "sg:phone":"+44 1752 669896",
    "sg:postcode":"PL6 8LQ",
    "sg:province":"Devon",
    "sg:tags":[
        "gearbox"
    ],
    "wof:name":"W J Jones Gearbox Repairs",
    "wof:placetype":"venue"
},
  "geometry": {"coordinates":[-4.093209,50.395966],"type":"Point"}
}