{
  "type": "Feature",
  "properties": {
    "addr:full":"1 Hansa Road King's Lynn Norfolk PE30 4HZ",
    "addr:housenumber":"1",
    "addr:postcode":"pe30 4hz",
    "addr:street":"Hansa Road",
    "iso:country":"GB",
    "sg:address":"1 Hansa Road",
    "sg:city":"King's Lynn",
    "sg:classifiers":[
        {
            "category":"Shopping",
            "subcategory":"Clothing, Apparel, & Fashions",
            "type":"Retail Goods"
        }
    ],
    "sg:phone":"+44 1553 732000",
    "sg:postcode":"PE30 4HZ",
    "sg:province":"Norfolk",
    "sg:tags":[
        "shop"
    ],
    "wof:name":"The Jaeger Co. Ltd.",
    "wof:placetype":"venue"
},
  "geometry": {"coordinates":[0.4108299911,52.7415008545],"type":"Point"}
}