{
  "type": "Feature",
  "properties": {
    "iso:country":"GB",
    "sg:address":"41 Summerfield Drive",
    "sg:city":"Leeds",
    "sg:classifiers":[
        {
            "category":"Fast Food",
            "type":"Food & Drink"
        }
    ],
    "sg:phone":"+44 113 236 3623",
    "sg:postcode":"LS13 1AJ",
    "sg:province":"West Yorkshire",
    "sg:tags":[
        "away",
        "meal",
        "outlet",
        "take"
    ],
    "wof:name":"Pizza Maria",
    "wof:placetype":"venue"
},
  "geometry": {"coordinates":[-1.649082,53.814091],"type":"Point"}
}