{
  "type": "Feature",
  "properties": {
    "iso:country":"GB",
    "sg:address":"100 Normandy Street",
    "sg:city":"Alton",
    "sg:classifiers":[
        {
            "category":"Organizations",
            "subcategory":"Non-profit Organization",
            "type":"Services"
        }
    ],
    "sg:phone":"+44 1420 542388",
    "sg:postcode":"GU34 1DH",
    "sg:province":"Hampshire",
    "sg:tags":[
        "organisation",
        "voluntary",
        "charity"
    ],
    "wof:name":"Home From Hospital",
    "wof:placetype":"venue"
},
  "geometry": {"coordinates":[-0.970031023,51.1524162292],"type":"Point"}
}