{
  "type": "Feature",
  "properties": {
    "iso:country":"GB",
    "sg:address":"Renown Close, Chandlers Ford",
    "sg:city":"Southampton",
    "sg:classifiers":[
        {
            "category":"Community Center",
            "type":"Public Place"
        }
    ],
    "sg:phone":"+44 23 8026 3399",
    "sg:postcode":"SO53 4HZ",
    "sg:province":"Hampshire",
    "sg:tags":[
        "recreation",
        "leisure",
        "centre"
    ],
    "wof:name":"Ashlett (U K) Ltd.",
    "wof:placetype":"venue"
},
  "geometry": {"coordinates":[-1.395442,50.98222],"type":"Point"}
}