{
  "type": "Feature",
  "properties": {
    "iso:country":"GB",
    "sg:address":"4 Beechwood Grove, Cheadle Hulme",
    "sg:city":"Cheadle",
    "sg:classifiers":[
        {
            "category":"Professional",
            "subcategory":"Business Services",
            "type":"Services"
        }
    ],
    "sg:phone":"+44 161 486 9422",
    "sg:postcode":"SK8 6HE",
    "sg:province":"Cheshire",
    "sg:tags":[
        "distributor",
        "film"
    ],
    "wof:name":"County Video",
    "wof:placetype":"venue"
},
  "geometry": {"coordinates":[-2.194143,53.370083],"type":"Point"}
}