{
  "type": "Feature",
  "properties": {
    "addr:full":"Broomhurst, Street End La Heathfield East Sussex TN21 8UB",
    "addr:postcode":"tn21 8ub",
    "addr:street":"Broomhurst Street End La Heathfield",
    "iso:country":"GB",
    "sg:address":"Broomhurst, Street End La",
    "sg:city":"Heathfield",
    "sg:classifiers":[
        {
            "category":"Farming",
            "subcategory":"Livestock Farm",
            "type":"Manufacturing & Wholesale Goods"
        }
    ],
    "sg:phone":"+44 1435 873256",
    "sg:postcode":"TN21 8UB",
    "sg:province":"East Sussex",
    "sg:tags":[
        "others"
    ],
    "wof:name":"J Chittenden",
    "wof:placetype":"venue"
},
  "geometry": {"coordinates":[0.252349,50.971859],"type":"Point"}
}