{
  "type": "Feature",
  "properties": {
    "addr:full":"1 Kilmarsh Rd Hammersmith Greater London W6 0PL",
    "addr:housenumber":"1",
    "addr:postcode":"w6 0pl",
    "addr:street":"Kilmarsh Rd",
    "iso:country":"GB",
    "sg:address":"1 Kilmarsh Rd",
    "sg:city":"Hammersmith",
    "sg:classifiers":[
        {
            "category":"Autos & Motor Vehicles",
            "subcategory":"Motorcycle Sales",
            "type":"Retail Goods"
        }
    ],
    "sg:phone":"+44 20 8741 0202",
    "sg:postcode":"W6 0PL",
    "sg:province":"Greater London",
    "sg:tags":[
        "chauffeur",
        "driven",
        "car"
    ],
    "wof:name":"Broadway Chauffeur Services",
    "wof:placetype":"venue"
},
  "geometry": {"coordinates":[-0.227907002,51.4955062866],"type":"Point"}
}