{
  "type": "Feature",
  "properties": {
    "addr:full":"Main Rd, Seaton Workington Cumbria CA14 1JD",
    "addr:postcode":"ca14 1jd",
    "addr:street":"Main Rd",
    "iso:country":"GB",
    "sg:address":"Main Rd, Seaton",
    "sg:city":"Workington",
    "sg:classifiers":[
        {
            "category":"Social Services",
            "subcategory":"Adult Care",
            "type":"Services"
        },
        {
            "category":"Social Services",
            "subcategory":"Retirement Home",
            "type":"Services"
        }
    ],
    "sg:phone":"+44 1900 605835",
    "sg:postcode":"CA14 1JD",
    "sg:province":"Cumbria",
    "sg:tags":[
        "accomodation",
        "housing",
        "sheltered"
    ],
    "wof:name":"CUMBRIA COUNTY COUNCIL",
    "wof:placetype":"venue"
},
  "geometry": {"coordinates":[-3.524929,54.66201],"type":"Point"}
}