{
  "type": "Feature",
  "properties": {
    "iso:country":"GB",
    "sg:address":"Po Box 115",
    "sg:city":"Knutsford",
    "sg:classifiers":[
        {
            "category":"Real Estate",
            "subcategory":"Real Estate Agent",
            "type":"Services"
        }
    ],
    "sg:phone":"+44 1565 654811",
    "sg:postcode":"WA16 0XA",
    "sg:province":"Cheshire",
    "wof:name":"Profile Property Research Ltd.",
    "wof:placetype":"venue"
},
  "geometry": {"coordinates":[-2.411069,53.309879],"type":"Point"}
}