{
  "type": "Feature",
  "properties": {
    "addr:full":"Ravensbridge Industrial Estate, Unit 4 Bridge Street Dewsbury West Yorkshire WF13 3EN",
    "addr:housenumber":"unit 4",
    "addr:postcode":"wf13 3en",
    "addr:street":"Bridge Street",
    "iso:country":"GB",
    "sg:address":"Ravensbridge Industrial Estate, Unit 4 Bridge Street",
    "sg:city":"Dewsbury",
    "sg:classifiers":[
        {
            "category":"Building & Trades",
            "subcategory":"Construction",
            "type":"Services"
        }
    ],
    "sg:phone":"+44 113 240 2902",
    "sg:postcode":"WF13 3EN",
    "sg:province":"West Yorkshire",
    "sg:tags":[
        "disposal",
        "waste",
        "unit"
    ],
    "wof:name":"Caledonian Waste Compactors",
    "wof:placetype":"venue"
},
  "geometry": {"coordinates":[-1.657583952,53.6947250366],"type":"Point"}
}