{
  "type": "Feature",
  "properties": {
    "addr:full":"2 Backbrae Street, Kilsyth Glasgow East Dunbartonshire G65 0NH",
    "addr:housenumber":"2",
    "addr:postcode":"g65 0nh",
    "addr:street":"Backbrae Street",
    "iso:country":"GB",
    "sg:address":"2 Backbrae Street, Kilsyth",
    "sg:city":"Glasgow",
    "sg:classifiers":[
        {
            "category":"Shopping",
            "subcategory":"News",
            "type":"Retail Goods"
        }
    ],
    "sg:phone":"+44 1236 823285",
    "sg:postcode":"G65 0NH",
    "sg:province":"East Dunbartonshire",
    "sg:tags":[
        "newsagent"
    ],
    "wof:name":"Hanif's Newsagent",
    "wof:placetype":"venue"
},
  "geometry": {"coordinates":[-4.0575270653,55.9775123596],"type":"Point"}
}