{
  "type": "Feature",
  "properties": {
    "addr:full":"Second Floor, 106 Whiteladies Road Bristol City of Bristol BS8 2QY",
    "addr:housenumber":"second;106",
    "addr:postcode":"bs8 2qy",
    "addr:street":"Whiteladies Road",
    "iso:country":"GB",
    "sg:address":"Second Floor, 106 Whiteladies Road",
    "sg:city":"Bristol",
    "sg:classifiers":[
        {
            "category":"Organizations",
            "subcategory":"Non-profit Organization",
            "type":"Services"
        }
    ],
    "sg:phone":"+44 117 970 6600",
    "sg:postcode":"BS8 2QY",
    "sg:province":"City of Bristol",
    "sg:tags":[
        "organisation",
        "voluntary",
        "charity"
    ],
    "wof:name":"The Prince's Youth Business Trust",
    "wof:placetype":"venue"
},
  "geometry": {"coordinates":[-2.6128230095,51.4677352905],"type":"Point"}
}