{
  "type": "Feature",
  "properties": {
    "addr:full":"37 Erlesmere Gardens London Greater London W13 9TZ",
    "addr:housenumber":"37",
    "addr:postcode":"w13 9tz",
    "addr:street":"Erlesmere Gardens",
    "iso:country":"GB",
    "sg:address":"37 Erlesmere Gardens",
    "sg:city":"London",
    "sg:classifiers":[
        {
            "category":"Health Services",
            "subcategory":"Health Practitioner",
            "type":"Services"
        }
    ],
    "sg:postcode":"W13 9TZ",
    "sg:province":"Greater London",
    "sg:tags":[
        "osteopath"
    ],
    "wof:name":"Christine Lister",
    "wof:placetype":"venue"
},
  "geometry": {"coordinates":[-0.325413,51.501671],"type":"Point"}
}