{
  "type": "Feature",
  "properties": {
    "addr:full":"12 Stannery Road, Stenalees St Austell Cornwall PL26 8SP",
    "addr:housenumber":"12",
    "addr:postcode":"pl26 8sp",
    "addr:street":"Stannery Road",
    "iso:country":"GB",
    "sg:address":"12 Stannery Road, Stenalees",
    "sg:city":"St Austell",
    "sg:classifiers":[
        {
            "category":"Education",
            "subcategory":"Special Training",
            "type":"Public Place"
        },
        {
            "category":"Sports & Exercise",
            "subcategory":"Sports Center",
            "type":"Entertainment"
        }
    ],
    "sg:phone":"+44 1726 851497",
    "sg:postcode":"PL26 8SP",
    "sg:province":"Cornwall",
    "sg:tags":[
        "shop",
        "good",
        "martial art",
        "instruction"
    ],
    "wof:name":"Ricochet Martial Arts Ltd.",
    "wof:placetype":"venue"
},
  "geometry": {"coordinates":[-4.796778,50.377365],"type":"Point"}
}