{
  "type": "Feature",
  "properties": {
    "iso:country":"GB",
    "sg:address":"Abbey Park, Clayhill Rd",
    "sg:city":"Reading",
    "sg:classifiers":[
        {
            "category":"Place Of Worship",
            "type":"Public Place"
        }
    ],
    "sg:phone":"+44 118 971 5222",
    "sg:postcode":"RG7 3HQ",
    "sg:province":"Berkshire",
    "wof:name":"St Oswalds RC Church",
    "wof:placetype":"venue"
},
  "geometry": {"coordinates":[-1.0704090595,51.4003944397],"type":"Point"}
}