{
  "type": "Feature",
  "properties": {
    "iso:country":"GB",
    "sg:address":"151 Regent St",
    "sg:city":"West End",
    "sg:classifiers":[
        {
            "category":"Shopping",
            "subcategory":"Clothing, Apparel, & Fashions",
            "type":"Retail Goods"
        }
    ],
    "sg:phone":"+44 20 7287 2426",
    "sg:postcode":"W1R 8LH",
    "sg:province":"Hampshire",
    "sg:tags":[
        "menswear"
    ],
    "wof:name":"Cougar Menswear",
    "wof:placetype":"venue"
},
  "geometry": {"coordinates":[-0.13948,51.511494],"type":"Point"}
}