{
  "type": "Feature",
  "properties": {
    "iso:country":"GB",
    "sg:address":"51 Church Street",
    "sg:city":"Seaham",
    "sg:classifiers":[
        {
            "category":"Home & Garden",
            "subcategory":"Household Appliances",
            "type":"Retail Goods"
        }
    ],
    "sg:phone":"+44 191 581 2237",
    "sg:postcode":"SR7 7HF",
    "sg:province":"Durham",
    "sg:tags":[
        "electrical",
        "domestic"
    ],
    "wof:name":"Northern Electric Retail Ltd.",
    "wof:placetype":"venue"
},
  "geometry": {"coordinates":[-1.335327,54.837112],"type":"Point"}
}