{
  "type": "Feature",
  "properties": {
    "addr:full":"53 Telford Avenue Leamington Spa Warwickshire CV32 7HQ",
    "addr:housenumber":"53",
    "addr:postcode":"cv32 7hq",
    "addr:street":"Telford Avenue",
    "iso:country":"GB",
    "sg:address":"53 Telford Avenue",
    "sg:city":"Leamington Spa",
    "sg:classifiers":[
        {
            "category":"Building & Trades",
            "subcategory":"Construction",
            "type":"Services"
        }
    ],
    "sg:phone":"+44 1926 312071",
    "sg:postcode":"CV32 7HQ",
    "sg:province":"Warwickshire",
    "sg:tags":[
        "roofing"
    ],
    "wof:name":"C J Property Maintenance",
    "wof:placetype":"venue"
},
  "geometry": {"coordinates":[-1.5182939768,52.3105392456],"type":"Point"}
}