{
  "type": "Feature",
  "properties": {
    "iso:country":"GB",
    "sg:address":"107 Trenthan Road, Dresden",
    "sg:city":"Stoke-on-trent",
    "sg:classifiers":[
        {
            "category":"Social Services",
            "subcategory":"Retirement Home",
            "type":"Services"
        }
    ],
    "sg:postcode":"ST3 4EG",
    "sg:province":"Staffordshire",
    "sg:tags":[
        "residential",
        "care"
    ],
    "wof:name":"Strathmore Associates",
    "wof:placetype":"venue"
},
  "geometry": {"coordinates":[-2.137738,52.978699],"type":"Point"}
}