{
  "type": "Feature",
  "properties": {
    "iso:country":"GB",
    "sg:address":"100 Peaks Lane, New Waltham",
    "sg:city":"Grimsby",
    "sg:classifiers":[
        {
            "category":"Manufacturing",
            "subcategory":"Printing",
            "type":"Manufacturing & Wholesale Goods"
        }
    ],
    "sg:postcode":"DN36 4LY",
    "sg:province":"Lincolnshire",
    "sg:tags":[
        "bookbinder"
    ],
    "wof:name":"Beaver Book Binding",
    "wof:placetype":"venue"
},
  "geometry": {"coordinates":[-0.059792,53.530289],"type":"Point"}
}