{
  "type": "Feature",
  "properties": {
    "addr:full":"60 Draycott Road, Cam Dursley Gloucestershire GL11 5LL",
    "addr:housenumber":"60",
    "addr:postcode":"gl11 5ll",
    "addr:street":"Draycott Road Cam Dursley",
    "iso:country":"GB",
    "sg:address":"60 Draycott Road, Cam",
    "sg:city":"Dursley",
    "sg:classifiers":[
        {
            "category":"Building & Trades",
            "subcategory":"Plumbing",
            "type":"Services"
        },
        {
            "category":"Government",
            "subcategory":"Post Office",
            "type":"Public Place"
        }
    ],
    "sg:phone":"+44 1453 545046",
    "sg:postcode":"GL11 5LL",
    "sg:province":"Gloucestershire",
    "sg:tags":[
        "clearance",
        "drain",
        "sewer",
        "sewar"
    ],
    "wof:name":"Dursley and Stroud Drain Services",
    "wof:placetype":"venue"
},
  "geometry": {"coordinates":[-2.36512,51.709877],"type":"Point"}
}