{
  "type": "Feature",
  "properties": {
    "iso:country":"GB",
    "sg:address":"G D H House, Green Lane",
    "sg:city":"Liverpool",
    "sg:classifiers":[
        {
            "category":"Professional",
            "subcategory":"Computer Services",
            "type":"Services"
        }
    ],
    "sg:phone":"+44 151 282 5555",
    "sg:postcode":"L13 7EB",
    "sg:province":"Merseyside",
    "sg:tags":[
        "system",
        "software"
    ],
    "wof:name":"David Hartley",
    "wof:placetype":"venue"
},
  "geometry": {"coordinates":[-2.929154,53.424259],"type":"Point"}
}