{
  "type": "Feature",
  "properties": {
    "iso:country":"GB",
    "sg:address":"3 Airevale House, Ross Mills, Rodley Lane",
    "sg:city":"Leeds",
    "sg:classifiers":[
        {
            "category":"Building & Trades",
            "subcategory":"Construction",
            "type":"Services"
        }
    ],
    "sg:phone":"+44 113 239 3240",
    "sg:postcode":"LS13 1BJ",
    "sg:province":"West Yorkshire",
    "sg:tags":[
        "platform",
        "work",
        "scaffolding"
    ],
    "wof:name":"Bee Jay Scaffolding Ltd.",
    "wof:placetype":"venue"
},
  "geometry": {"coordinates":[-1.661319,53.823101],"type":"Point"}
}