{
  "type": "Feature",
  "properties": {
    "addr:full":"22 Flintson Avenue, New Whittington Chesterfield Derbyshire S43 2DS",
    "addr:housenumber":"22",
    "addr:postcode":"s43 2ds",
    "addr:street":"Flintson Avenue",
    "iso:country":"GB",
    "sg:address":"22 Flintson Avenue, New Whittington",
    "sg:city":"Chesterfield",
    "sg:classifiers":[
        {
            "category":"Home & Garden",
            "subcategory":"Kitchen Supply",
            "type":"Retail Goods"
        }
    ],
    "sg:postcode":"S43 2DS",
    "sg:province":"Derbyshire",
    "sg:tags":[
        "catering"
    ],
    "wof:name":"Bewleys Coffeeman",
    "wof:placetype":"venue"
},
  "geometry": {"coordinates":[-1.4075449705,53.2768516541],"type":"Point"}
}