{
  "type": "Feature",
  "properties": {
    "iso:country":"GB",
    "sg:address":"Manor Farm, Haydon Wick",
    "sg:city":"Swindon",
    "sg:classifiers":[
        {
            "category":"Military Area",
            "subcategory":"Army Base",
            "type":"Public Place"
        }
    ],
    "sg:phone":"+44 1793 721335",
    "sg:postcode":"SN2 3JF",
    "sg:province":"Wiltshire",
    "sg:tags":[
        "transportation",
        "livestock"
    ],
    "wof:name":"M.F.P International Ltd",
    "wof:placetype":"venue"
},
  "geometry": {"coordinates":[-1.80451,51.5896],"type":"Point"}
}