{
  "type": "Feature",
  "properties": {
    "iso:country":"GB",
    "sg:address":"Unit 56-57 Second Av, Heatherhouse Industrial Estate",
    "sg:city":"Irvine",
    "sg:classifiers":[
        {
            "category":"Building & Trades",
            "subcategory":"Construction",
            "type":"Services"
        }
    ],
    "sg:phone":"+44 1294 272311",
    "sg:postcode":"KA12 8LZ",
    "sg:province":"North Ayrshire",
    "sg:tags":[
        "window",
        "sale"
    ],
    "wof:name":"Albann Windows Ltd",
    "wof:placetype":"venue"
},
  "geometry": {"coordinates":[-4.67006,55.605598],"type":"Point"}
}