{
  "type": "Feature",
  "properties": {
    "iso:country":"GB",
    "sg:address":"8 Hall Green Lane",
    "sg:city":"Brentwood",
    "sg:classifiers":[
        {
            "category":"Professional",
            "type":"Services"
        }
    ],
    "sg:postcode":"CM13 2RA",
    "sg:province":"Essex",
    "sg:tags":[
        "exhibition"
    ],
    "wof:name":"3d World Exhibitions",
    "wof:placetype":"venue"
},
  "geometry": {"coordinates":[0.344826,51.626926],"type":"Point"}
}