{
  "type": "Feature",
  "properties": {
    "addr:full":"157 Station Road, Stanley Derby Derbyshire DE7 6FJ",
    "addr:housenumber":"157",
    "addr:postcode":"de7 6fj",
    "addr:street":"Station Road",
    "iso:country":"GB",
    "sg:address":"157 Station Road, Stanley",
    "sg:city":"Derby",
    "sg:classifiers":[
        {
            "category":"Bus Charters",
            "type":"Transportation"
        }
    ],
    "sg:phone":"+44 115 932 5332",
    "sg:postcode":"DE7 6FJ",
    "sg:province":"Derbyshire",
    "sg:tags":[
        "hire",
        "coach"
    ],
    "wof:name":"Felix Bus Services Ltd",
    "wof:placetype":"venue"
},
  "geometry": {"coordinates":[-1.373699,52.9613],"type":"Point"}
}