{
  "type": "Feature",
  "properties": {
    "addr:full":"13 Oakmount Road, Chandlers Ford Eastleigh Hampshire SO53 2LG",
    "addr:housenumber":"13",
    "addr:postcode":"so53 2lg",
    "addr:street":"Oakmount Road",
    "iso:country":"GB",
    "sg:address":"13 Oakmount Road, Chandlers Ford",
    "sg:city":"Eastleigh",
    "sg:classifiers":[
        {
            "category":"Government",
            "subcategory":"Post Office",
            "type":"Public Place"
        }
    ],
    "sg:phone":"+44 23 8025 3930",
    "sg:postcode":"SO53 2LG",
    "sg:province":"Hampshire",
    "wof:name":"Fryern Hill Sub Post Office",
    "wof:placetype":"venue"
},
  "geometry": {"coordinates":[-1.3731360435,50.9869384766],"type":"Point"}
}