{
  "type": "Feature",
  "properties": {
    "addr:full":"Brook House, Bracknell Business Centre, Downmill Road Bracknell Berkshire RG12 1QS",
    "addr:housenumber":"bracknell business centre",
    "addr:postcode":"rg12 1qs",
    "addr:street":"Downmill Road",
    "iso:country":"GB",
    "sg:address":"Brook House, Bracknell Business Centre, Downmill Road",
    "sg:city":"Bracknell",
    "sg:classifiers":[
        {
            "category":"Personal",
            "type":"Services"
        }
    ],
    "sg:phone":"+44 1344 411311",
    "sg:postcode":"RG12 1QS",
    "sg:province":"Berkshire",
    "sg:tags":[
        "gift"
    ],
    "wof:name":"Alexander Dunn & Co. (Whisky Blenders) Ltd.",
    "wof:placetype":"venue"
},
  "geometry": {"coordinates":[-0.7614399791,51.4151382446],"type":"Point"}
}