{
  "type": "Feature",
  "properties": {
    "addr:full":"62a Pyle Street Newport Isle of Wight PO30 1UL",
    "addr:housenumber":"62a",
    "addr:postcode":"po30 1ul",
    "addr:street":"Pyle Street",
    "iso:country":"GB",
    "sg:address":"62a Pyle Street",
    "sg:city":"Newport",
    "sg:classifiers":[
        {
            "category":"Health Services",
            "subcategory":"Dentist",
            "type":"Services"
        }
    ],
    "sg:postcode":"PO30 1UL",
    "sg:province":"Isle of Wight",
    "wof:name":"B D Hamilton",
    "wof:placetype":"venue"
},
  "geometry": {"coordinates":[-1.295598,50.698944],"type":"Point"}
}