{
  "type": "Feature",
  "properties": {
    "addr:full":"Unit 13/14 Milburngate Shopping, Centre Durham Durham DH1 4SL",
    "addr:housenumber":"unit 13 / 14",
    "addr:postcode":"dh1 4sl",
    "addr:street":"Milburngate Shopping",
    "iso:country":"GB",
    "sg:address":"Unit 13/14 Milburngate Shopping, Centre",
    "sg:city":"Durham",
    "sg:classifiers":[
        {
            "category":"Shopping",
            "subcategory":"Crafts & Fabrics",
            "type":"Retail Goods"
        },
        {
            "category":"Manufacturing",
            "subcategory":"Textiles",
            "type":"Manufacturing & Wholesale Goods"
        }
    ],
    "sg:phone":"+44 191 383 1783",
    "sg:postcode":"DH1 4SL",
    "sg:province":"Durham",
    "sg:tags":[
        "made-up",
        "linen"
    ],
    "wof:name":"Ponden Mill Ltd",
    "wof:placetype":"venue"
},
  "geometry": {"coordinates":[-1.579435,54.776649],"type":"Point"}
}