{
  "type": "Feature",
  "properties": {
    "iso:country":"GB",
    "sg:address":"Unit 9 The Martlets, Diplocks Way",
    "sg:city":"Hailsham",
    "sg:classifiers":[
        {
            "category":"Manufacturing",
            "subcategory":"Tools & Machinery",
            "type":"Manufacturing & Wholesale Goods"
        },
        {
            "category":"Home & Garden",
            "subcategory":"Hardware",
            "type":"Retail Goods"
        }
    ],
    "sg:phone":"+44 1323 841916",
    "sg:postcode":"BN27 3JS",
    "sg:province":"East Sussex",
    "sg:tags":[
        "retailer",
        "diy",
        "power"
    ],
    "wof:name":"Macey Industrial Fixings",
    "wof:placetype":"venue"
},
  "geometry": {"coordinates":[0.24744,50.863106],"type":"Point"}
}