{
  "type": "Feature",
  "properties": {
    "iso:country":"GB",
    "sg:address":"345 Fernhill Road, Cove",
    "sg:city":"Farnborough",
    "sg:classifiers":[
        {
            "category":"Building & Trades",
            "subcategory":"Plumbing",
            "type":"Services"
        }
    ],
    "sg:phone":"+44 1276 31445",
    "sg:postcode":"GU14 9EN",
    "sg:province":"Hampshire",
    "sg:tags":[
        "heating"
    ],
    "wof:name":"Brady Plumbing",
    "wof:placetype":"venue"
},
  "geometry": {"coordinates":[-0.776645,51.315647],"type":"Point"}
}