{
  "type": "Feature",
  "properties": {
    "addr:full":"Northern Distribution Centre, Bahama Road, Haydock Industrial Estate St Helens Lancashire WA11 9XB",
    "addr:postcode":"wa11 9xb",
    "addr:street":"Bahama Road Haydock Industrial Estate",
    "iso:country":"GB",
    "sg:address":"Northern Distribution Centre, Bahama Road, Haydock Industrial Estate",
    "sg:city":"St Helens",
    "sg:classifiers":[
        {
            "category":"Farming",
            "subcategory":"Poultry Farm",
            "type":"Manufacturing & Wholesale Goods"
        }
    ],
    "sg:phone":"+44 1942 272277",
    "sg:postcode":"WA11 9XB",
    "sg:province":"Lancashire",
    "wof:name":"Faccenda Group Ltd.",
    "wof:placetype":"venue"
},
  "geometry": {"coordinates":[-2.6656401157,53.4745597839],"type":"Point"}
}