{
  "type": "Feature",
  "properties": {
    "addr:full":"Unit 1 Frederick Street Walsall West Midlands WS2 9NJ",
    "addr:housenumber":"unit 1",
    "addr:postcode":"ws2 9nj",
    "addr:street":"Frederick Street",
    "iso:country":"GB",
    "sg:address":"Unit 1 Frederick Street",
    "sg:city":"Walsall",
    "sg:classifiers":[
        {
            "category":"Professional",
            "subcategory":"Engineering",
            "type":"Services"
        }
    ],
    "sg:phone":"+44 1922 615616",
    "sg:postcode":"WS2 9NJ",
    "sg:province":"West Midlands",
    "sg:tags":[
        "industrial",
        "engineer"
    ],
    "wof:name":"Lee Beesley (Coventry) Ltd.",
    "wof:placetype":"venue"
},
  "geometry": {"coordinates":[-1.9909889698,52.5844612122],"type":"Point"}
}