{
  "type": "Feature",
  "properties": {
    "addr:full":"88 Meadow Head Av Sheffield Derbyshire S8 7RW",
    "addr:housenumber":"88",
    "addr:postcode":"s8 7rw",
    "addr:street":"Meadow Head Av",
    "iso:country":"GB",
    "sg:address":"88 Meadow Head Av",
    "sg:city":"Sheffield",
    "sg:classifiers":[
        {
            "category":"Professional",
            "subcategory":"Engineering",
            "type":"Services"
        }
    ],
    "sg:phone":"+44 114 274 5880",
    "sg:postcode":"S8 7RW",
    "sg:province":"Derbyshire",
    "sg:tags":[
        "contractor",
        "electrical",
        "engineer"
    ],
    "wof:name":"T T Cook",
    "wof:placetype":"venue"
},
  "geometry": {"coordinates":[-1.481629014,53.3377914429],"type":"Point"}
}