{
  "type": "Feature",
  "properties": {
    "addr:full":"23 Glen Farrar Way Kilmarnock East Ayrshire KA2 0LP",
    "addr:housenumber":"23",
    "addr:postcode":"ka2 0lp",
    "addr:street":"Glen Farrar Way",
    "iso:country":"GB",
    "sg:address":"23 Glen Farrar Way",
    "sg:city":"Kilmarnock",
    "sg:classifiers":[
        {
            "category":"Professional",
            "subcategory":"Printing & Photocopies",
            "type":"Services"
        }
    ],
    "sg:phone":"+44 1563 531720",
    "sg:postcode":"KA2 0LP",
    "sg:province":"East Ayrshire",
    "sg:tags":[
        "trophy"
    ],
    "wof:name":"Premier Promotions",
    "wof:placetype":"venue"
},
  "geometry": {"coordinates":[-4.519086,55.600731],"type":"Point"}
}