{
  "type": "Feature",
  "properties": {
    "addr:full":"Millway Cottage, Somerton Rd Somerton Somerset TA11 6NX",
    "addr:postcode":"ta11 6nx",
    "addr:street":"Somerton Rd",
    "iso:country":"GB",
    "sg:address":"Millway Cottage, Somerton Rd",
    "sg:city":"Somerton",
    "sg:classifiers":[
        {
            "category":"Banks & Credit Unions",
            "subcategory":"Investment Brokerage",
            "type":"Services"
        }
    ],
    "sg:phone":"+44 1458 272354",
    "sg:postcode":"TA11 6NX",
    "sg:province":"Somerset",
    "sg:tags":[
        "contractor"
    ],
    "wof:name":"I V Martin & Son",
    "wof:placetype":"venue"
},
  "geometry": {"coordinates":[-2.734899,51.054165],"type":"Point"}
}