{
  "type": "Feature",
  "properties": {
    "addr:full":"95 Olivers Battery Road South Winchester Hampshire SO22 4JQ",
    "addr:housenumber":"95",
    "addr:postcode":"so22 4jq",
    "addr:street":"Olivers Battery Road South",
    "iso:country":"GB",
    "sg:address":"95 Olivers Battery Road South",
    "sg:city":"Winchester",
    "sg:classifiers":[
        {
            "category":"Shopping",
            "subcategory":"Department Store",
            "type":"Retail Goods"
        }
    ],
    "sg:phone":"+44 1962 853256",
    "sg:postcode":"SO22 4JQ",
    "sg:province":"Hampshire",
    "wof:name":"Olivers Battery Post Office & Stores",
    "wof:placetype":"venue"
},
  "geometry": {"coordinates":[-1.347491,51.048134],"type":"Point"}
}