{
  "type": "Feature",
  "properties": {
    "addr:full":"1 Shepstye Road, Horbury Wakefield West Yorkshire WF4 5BE",
    "addr:housenumber":"1",
    "addr:postcode":"wf4 5be",
    "addr:street":"Shepstye Road;West",
    "iso:country":"GB",
    "sg:address":"1 Shepstye Road, Horbury",
    "sg:city":"Wakefield",
    "sg:classifiers":[
        {
            "category":"Manufacturing",
            "subcategory":"Metals",
            "type":"Manufacturing & Wholesale Goods"
        },
        {
            "category":"Wholesale",
            "subcategory":"Metals & Minerals",
            "type":"Manufacturing & Wholesale Goods"
        }
    ],
    "sg:phone":"+44 1924 276530",
    "sg:postcode":"WF4 5BE",
    "sg:province":"West Yorkshire",
    "sg:tags":[
        "fabricator",
        "work",
        "sheet"
    ],
    "wof:name":"Dick Webb Sheet Metal Worker",
    "wof:placetype":"venue"
},
  "geometry": {"coordinates":[-1.556791,53.658607],"type":"Point"}
}