{
  "type": "Feature",
  "properties": {
    "iso:country":"GB",
    "sg:address":"101a Alexandra Road",
    "sg:city":"St Austell",
    "sg:classifiers":[
        {
            "category":"Building & Trades",
            "subcategory":"Plumbing",
            "type":"Services"
        }
    ],
    "sg:phone":"+44 1726 75994",
    "sg:postcode":"PL25 4QL",
    "sg:province":"Cornwall",
    "sg:tags":[
        "plumber",
        "heating"
    ],
    "wof:name":"M J Martin",
    "wof:placetype":"venue"
},
  "geometry": {"coordinates":[-4.780415,50.338371],"type":"Point"}
}