{
  "type": "Feature",
  "properties": {
    "addr:full":"Unit 42 Hull Micro Firm Centre, 266-290 Wimcolmlee Hull East Riding of Yorkshire HU2 0PZ",
    "addr:housenumber":"unit 42;266-290",
    "addr:postcode":"hu2 0pz",
    "addr:street":"Wimcolmlee",
    "iso:country":"GB",
    "sg:address":"Unit 42 Hull Micro Firm Centre, 266-290 Wimcolmlee",
    "sg:city":"Hull",
    "sg:classifiers":[
        {
            "category":"Manufacturing",
            "subcategory":"Metals",
            "type":"Manufacturing & Wholesale Goods"
        },
        {
            "category":"Shopping",
            "subcategory":"Discount & Variety Stores",
            "type":"Retail Goods"
        }
    ],
    "sg:phone":"+44 1482 587274",
    "sg:postcode":"HU2 0PZ",
    "sg:province":"East Riding of Yorkshire",
    "sg:tags":[
        "cleaning",
        "product",
        "fabricated",
        "supply"
    ],
    "wof:name":"Target Products",
    "wof:placetype":"venue"
},
  "geometry": {"coordinates":[-0.3300899863,53.7541313171],"type":"Point"}
}