{
  "type": "Feature",
  "properties": {
    "addr:full":"21 Arlington Way London Greater London EC1R 1UY",
    "addr:housenumber":"21",
    "addr:postcode":"ec1r 1uy",
    "addr:street":"Arlington Way",
    "iso:country":"GB",
    "sg:address":"21 Arlington Way",
    "sg:city":"London",
    "sg:classifiers":[
        {
            "category":"Shopping",
            "subcategory":"Florist",
            "type":"Retail Goods"
        }
    ],
    "sg:postcode":"EC1R 1UY",
    "sg:province":"Greater London",
    "wof:name":"Michael Pooley Flowers",
    "wof:placetype":"venue"
},
  "geometry": {"coordinates":[-0.1060950011,51.5301170349],"type":"Point"}
}