{
  "type": "Feature",
  "properties": {
    "addr:full":"36 High Street, Harefield Uxbridge Buckinghamshire UB9 6BU",
    "addr:housenumber":"36",
    "addr:postcode":"ub9 6bu",
    "addr:street":"High Street",
    "iso:country":"GB",
    "sg:address":"36 High Street, Harefield",
    "sg:city":"Uxbridge",
    "sg:classifiers":[
        {
            "category":"Retail",
            "subcategory":"Funeral Services",
            "type":"Services"
        }
    ],
    "sg:phone":"+44 1895 822297",
    "sg:postcode":"UB9 6BU",
    "sg:province":"Buckinghamshire",
    "wof:name":"H C Grimstead Ltd.",
    "wof:placetype":"venue"
},
  "geometry": {"coordinates":[-0.4831849933,51.6027259827],"type":"Point"}
}