{
  "type": "Feature",
  "properties": {
    "addr:full":"72 Church Lane, Mill End Rickmansworth Hertfordshire WD3 8HE",
    "addr:housenumber":"72",
    "addr:postcode":"wd3 8he",
    "addr:street":"Church Lane",
    "iso:country":"GB",
    "sg:address":"72 Church Lane, Mill End",
    "sg:city":"Rickmansworth",
    "sg:classifiers":[
        {
            "category":"Food & Beverages",
            "subcategory":"Liquor & Beverages",
            "type":"Retail Goods"
        }
    ],
    "sg:phone":"+44 1923 777419",
    "sg:postcode":"WD3 8HE",
    "sg:province":"Hertfordshire",
    "sg:tags":[
        "beer",
        "spirit",
        "wines"
    ],
    "wof:name":"J K Wine Stores",
    "wof:placetype":"venue"
},
  "geometry": {"coordinates":[-0.493461,51.636913],"type":"Point"}
}