{
  "type": "Feature",
  "properties": {
    "addr:full":"14 Well Cross Road Gloucester Gloucestershire GL4 6SN",
    "addr:housenumber":"14",
    "addr:postcode":"gl4 6sn",
    "addr:street":"Well Cross Road",
    "iso:country":"GB",
    "sg:address":"14 Well Cross Road",
    "sg:city":"Gloucester",
    "sg:classifiers":[
        {
            "category":"Building & Trades",
            "subcategory":"Construction",
            "type":"Services"
        }
    ],
    "sg:phone":"+44 1452 331574",
    "sg:postcode":"GL4 6SN",
    "sg:province":"Gloucestershire",
    "sg:tags":[
        "builder"
    ],
    "wof:name":"V S Robinson & Son",
    "wof:placetype":"venue"
},
  "geometry": {"coordinates":[-2.230737,51.842258],"type":"Point"}
}