{
  "type": "Feature",
  "properties": {
    "addr:full":"Pontardawe Rd Swansea Swansea SA6 5PB",
    "addr:postcode":"sa6 5pb",
    "addr:street":"Pontardawe Rd",
    "iso:country":"GB",
    "sg:address":"Pontardawe Rd",
    "sg:city":"Swansea",
    "sg:classifiers":[
        {
            "category":"Retail",
            "subcategory":"Funeral Services",
            "type":"Services"
        }
    ],
    "sg:phone":"+44 1792 842148",
    "sg:postcode":"SA6 5PB",
    "sg:province":"Swansea",
    "sg:tags":[
        "cemetery",
        "crematorium"
    ],
    "wof:name":"Coed Gwilym Cemetery",
    "wof:placetype":"venue"
},
  "geometry": {"coordinates":[-3.875658989,51.7018852234],"type":"Point"}
}