{
  "type": "Feature",
  "properties": {
    "addr:full":"61-62 Brook Green London Greater London W6 7BE",
    "addr:housenumber":"61-62",
    "addr:postcode":"w6 7be",
    "addr:street":"Brook Green",
    "iso:country":"GB",
    "sg:address":"61-62 Brook Green",
    "sg:city":"London",
    "sg:classifiers":[
        {
            "category":"Social Services",
            "subcategory":"Retirement Home",
            "type":"Services"
        },
        {
            "category":"Government",
            "subcategory":"Office",
            "type":"Public Place"
        }
    ],
    "sg:phone":"+44 20 7603 5557",
    "sg:postcode":"W6 7BE",
    "sg:province":"Greater London",
    "sg:tags":[
        "housing",
        "local",
        "accommodation",
        "sheltered"
    ],
    "wof:name":"Planetree Court Sheltered Housing",
    "wof:placetype":"venue"
},
  "geometry": {"coordinates":[-0.218292,51.495888],"type":"Point"}
}