{
  "type": "Feature",
  "properties": {
    "iso:country":"GB",
    "sg:address":"The Grange, Messingham",
    "sg:city":"Scunthorpe",
    "sg:classifiers":[
        {
            "category":"Sports & Exercise",
            "subcategory":"Golf",
            "type":"Entertainment"
        }
    ],
    "sg:postcode":"DN17 3PP",
    "sg:province":"Lincolnshire",
    "sg:tags":[
        "club",
        "course"
    ],
    "wof:name":"Starks Ltd.",
    "wof:placetype":"venue"
},
  "geometry": {"coordinates":[-0.653699,53.528496],"type":"Point"}
}