{
  "type": "Feature",
  "properties": {
    "addr:full":"Verulam Road, Common Road Industrial Estate Cannock Staffordshire ST16 3EA",
    "addr:postcode":"st16 3ea",
    "addr:street":"Verulam Road Common Road Industrial Estate",
    "iso:country":"GB",
    "sg:address":"Verulam Road, Common Road Industrial Estate",
    "sg:city":"Cannock",
    "sg:classifiers":[
        {
            "category":"Professional",
            "subcategory":"Testing Lab",
            "type":"Services"
        }
    ],
    "sg:postcode":"ST16 3EA",
    "sg:province":"Staffordshire",
    "sg:tags":[
        "inspection",
        "calibration"
    ],
    "wof:name":"Professional Testing Services (Total Quality Management) Ltd.",
    "wof:placetype":"venue"
},
  "geometry": {"coordinates":[-2.115464,52.825531],"type":"Point"}
}