{
  "type": "Feature",
  "properties": {
    "iso:country":"GB",
    "sg:address":"Condover House, Tinkers Lane",
    "sg:city":"Tring",
    "sg:classifiers":[
        {
            "category":"Professional",
            "subcategory":"Management & Consulting",
            "type":"Services"
        }
    ],
    "sg:postcode":"HP23 6JB",
    "sg:province":"Buckinghamshire",
    "sg:tags":[
        "consultant",
        "business"
    ],
    "wof:name":"Old Mill Associates Ltd.",
    "wof:placetype":"venue"
},
  "geometry": {"coordinates":[-0.6205980182,51.7702026367],"type":"Point"}
}