{
  "type": "Feature",
  "properties": {
    "addr:full":"Rubery House, The Avenue, Rubery Birmingham West Midlands B45 9AL",
    "addr:postcode":"b45 9al",
    "addr:street":"The Avenue",
    "iso:country":"GB",
    "sg:address":"Rubery House, The Avenue, Rubery",
    "sg:city":"Birmingham",
    "sg:classifiers":[
        {
            "category":"Shopping",
            "subcategory":"Stationery & Office Supplies",
            "type":"Retail Goods"
        }
    ],
    "sg:phone":"+44 121 457 7371",
    "sg:postcode":"B45 9AL",
    "sg:province":"West Midlands",
    "sg:tags":[
        "equipment"
    ],
    "wof:name":"Thomas Chambers & Sons",
    "wof:placetype":"venue"
},
  "geometry": {"coordinates":[-2.0240991116,52.393901825],"type":"Point"}
}