{
  "type": "Feature",
  "properties": {
    "addr:full":"30 Clarence Street Southend-on-sea Essex SS1 1BD",
    "addr:housenumber":"30",
    "addr:postcode":"ss1 1bd",
    "addr:street":"Clarence Street",
    "iso:country":"GB",
    "sg:address":"30 Clarence Street",
    "sg:city":"Southend-on-sea",
    "sg:classifiers":[
        {
            "category":"Professional",
            "subcategory":"Management & Consulting",
            "type":"Services"
        }
    ],
    "sg:phone":"+44 1702 436663",
    "sg:postcode":"SS1 1BD",
    "sg:province":"Essex",
    "sg:tags":[
        "consultant",
        "business"
    ],
    "wof:name":"Personal & Corporate Financial Management",
    "wof:placetype":"venue"
},
  "geometry": {"coordinates":[0.712453,51.535866],"type":"Point"}
}