{
  "type": "Feature",
  "properties": {
    "iso:country":"GB",
    "sg:address":"Pennygillan Way, Pennygillan Industrial Estate",
    "sg:city":"Launceston",
    "sg:classifiers":[
        {
            "category":"Professional",
            "subcategory":"Detective & Security Services",
            "type":"Services"
        }
    ],
    "sg:postcode":"PL15 7ED",
    "sg:province":"Cornwall",
    "sg:tags":[
        "equipment"
    ],
    "wof:name":"C-Tech",
    "wof:placetype":"venue"
},
  "geometry": {"coordinates":[-4.3703489304,50.6277160645],"type":"Point"}
}