{
  "type": "Feature",
  "properties": {
    "iso:country":"GB",
    "sg:address":"Cae Lloi Farm, Aberthin",
    "sg:city":"Cowbridge",
    "sg:classifiers":[
        {
            "category":"Farming",
            "subcategory":"Livestock Farm",
            "type":"Manufacturing & Wholesale Goods"
        }
    ],
    "sg:phone":"+44 1446 772552",
    "sg:postcode":"CF71 7HB",
    "sg:province":"The Vale of Glamorgan",
    "sg:tags":[
        "others"
    ],
    "wof:name":"Glyn Evans",
    "wof:placetype":"venue"
},
  "geometry": {"coordinates":[-3.450425,51.462391],"type":"Point"}
}