{
  "type": "Feature",
  "properties": {
    "addr:full":"Griffs Works Stopes Road, Stannington Sheffield South Yorkshire S6 6BW",
    "addr:postcode":"s6 6bw",
    "addr:street":"Stopes Road",
    "iso:country":"GB",
    "sg:address":"Griffs Works Stopes Road, Stannington",
    "sg:city":"Sheffield",
    "sg:classifiers":[
        {
            "category":"Wholesale",
            "subcategory":"Construction Materials",
            "type":"Manufacturing & Wholesale Goods"
        }
    ],
    "sg:phone":"+44 114 234 8663",
    "sg:postcode":"S6 6BW",
    "sg:province":"South Yorkshire",
    "sg:tags":[
        "refractory"
    ],
    "wof:name":"Dyson Precision Ceramics",
    "wof:placetype":"venue"
},
  "geometry": {"coordinates":[-1.5470540524,53.3944091797],"type":"Point"}
}