{
  "type": "Feature",
  "properties": {
    "iso:country":"GB",
    "sg:address":"35 Meadowbank Avenue",
    "sg:city":"Strathaven",
    "sg:classifiers":[
        {
            "category":"Home & Garden",
            "subcategory":"Garden Supply",
            "type":"Retail Goods"
        }
    ],
    "sg:postcode":"ML10 6JS",
    "sg:province":"South Lanarkshire",
    "sg:tags":[
        "tree",
        "shrub"
    ],
    "wof:name":"Dorricott Landscaping Services",
    "wof:placetype":"venue"
},
  "geometry": {"coordinates":[-4.062253952,55.6814537048],"type":"Point"}
}