{
  "type": "Feature",
  "properties": {
    "iso:country":"GB",
    "sg:address":"9 Mill St",
    "sg:city":"Melton Mowbray",
    "sg:classifiers":[
        {
            "category":"Retail",
            "subcategory":"Laundry & Dry Cleaning",
            "type":"Services"
        }
    ],
    "sg:postcode":"LE13 1AY",
    "sg:province":"Leicestershire",
    "sg:tags":[
        "launderette",
        "alteration"
    ],
    "wof:name":"Gilbert,S T,",
    "wof:placetype":"venue"
},
  "geometry": {"coordinates":[-0.8830819726,52.763343811],"type":"Point"}
}