{
  "type": "Feature",
  "properties": {
    "iso:country":"GB",
    "sg:address":"1 Church Street, Heckington",
    "sg:city":"Sleaford",
    "sg:classifiers":[
        {
            "category":"Food & Beverages",
            "subcategory":"Fruits & Vegetables",
            "type":"Retail Goods"
        }
    ],
    "sg:postcode":"NG34 9RF",
    "sg:province":"Lincolnshire",
    "sg:tags":[
        "greengrocer"
    ],
    "wof:name":"The Windmill Shop",
    "wof:placetype":"venue"
},
  "geometry": {"coordinates":[-0.3391489983,53.0404624939],"type":"Point"}
}