{
  "type": "Feature",
  "properties": {
    "iso:country":"GB",
    "sg:address":"113 London Rd",
    "sg:city":"Hemel Hempstead",
    "sg:classifiers":[
        {
            "category":"Bars & Pubs",
            "type":"Food & Drink"
        }
    ],
    "sg:phone":"+44 1442 253340",
    "sg:postcode":"HP3 9SP",
    "sg:province":"Hertfordshire",
    "sg:tags":[
        "pubs",
        "inn"
    ],
    "wof:name":"The Oddfellows Arms",
    "wof:placetype":"venue"
},
  "geometry": {"coordinates":[-0.467951,51.736755],"type":"Point"}
}