{
  "type": "Feature",
  "properties": {
    "addr:full":"2nd Floor West Park, Silsoe Bedford Bedfordshire MK45 4HS",
    "addr:housenumber":"2nd floor",
    "addr:postcode":"mk45 4hs",
    "addr:street":"West Park",
    "iso:country":"GB",
    "sg:address":"2nd Floor West Park, Silsoe",
    "sg:city":"Bedford",
    "sg:classifiers":[
        {
            "category":"Professional",
            "subcategory":"Business Services",
            "type":"Services"
        }
    ],
    "sg:phone":"+44 1525 862555",
    "sg:postcode":"MK45 4HS",
    "sg:province":"Bedfordshire",
    "wof:name":"Retail Services Management Ltd.",
    "wof:placetype":"venue"
},
  "geometry": {"coordinates":[-0.42096,52.010838],"type":"Point"}
}