{
  "type": "Feature",
  "properties": {
    "iso:country":"GB",
    "sg:address":"9 Weston Road, Llanrumney",
    "sg:city":"Cardiff",
    "sg:classifiers":[
        {
            "category":"Building & Trades",
            "subcategory":"Construction",
            "type":"Services"
        }
    ],
    "sg:phone":"+44 29 2075 0089",
    "sg:postcode":"CF3 4DQ",
    "sg:province":"Caerphilly",
    "sg:tags":[
        "builder",
        "paving",
        "contractor"
    ],
    "wof:name":"Approach Driveways Ltd",
    "wof:placetype":"venue"
},
  "geometry": {"coordinates":[-3.1303789616,51.5135765076],"type":"Point"}
}