{
  "type": "Feature",
  "properties": {
    "iso:country":"GB",
    "sg:address":"Unit 36-36a Baltic Works, Effingham Road",
    "sg:city":"Sheffield",
    "sg:classifiers":[
        {
            "category":"Retail",
            "subcategory":"Repair Shop",
            "type":"Services"
        }
    ],
    "sg:postcode":"S9 3QU",
    "sg:province":"South Yorkshire",
    "sg:tags":[
        "sharpening",
        "tool"
    ],
    "wof:name":"A & I West",
    "wof:placetype":"venue"
},
  "geometry": {"coordinates":[-1.44075,53.391109],"type":"Point"}
}