{
  "type": "Feature",
  "properties": {
    "iso:country":"GB",
    "sg:address":"236 Grays Inn Road",
    "sg:city":"London",
    "sg:classifiers":[
        {
            "category":"Professional",
            "subcategory":"Employment Agencies",
            "type":"Services"
        }
    ],
    "sg:phone":"+44 20 7211 3000",
    "sg:postcode":"WC1X 8HL",
    "sg:province":"Greater London",
    "sg:tags":[
        "consultant"
    ],
    "wof:name":"Employment Service Jobcentre",
    "wof:placetype":"venue"
},
  "geometry": {"coordinates":[-0.115909,51.524361],"type":"Point"}
}