{
  "type": "Feature",
  "properties": {
    "iso:country":"GB",
    "sg:address":"Windhill Cottage",
    "sg:city":"Bishops Stortford",
    "sg:classifiers":[
        {
            "category":"Shopping",
            "subcategory":"Pharmacy",
            "type":"Retail Goods"
        }
    ],
    "sg:phone":"+44 1279 659292",
    "sg:postcode":"CM23 2NJ",
    "sg:province":"Essex",
    "sg:tags":[
        "medicine",
        "therapy"
    ],
    "wof:name":"Clarke Mo",
    "wof:placetype":"venue"
},
  "geometry": {"coordinates":[0.15606,51.870785],"type":"Point"}
}