{
  "type": "Feature",
  "properties": {
    "addr:full":"67 Falstone Avenue South Shields Tyne and Wear NE34 6SA",
    "addr:housenumber":"67",
    "addr:postcode":"ne34 6sa",
    "addr:street":"Falstone Avenue",
    "iso:country":"GB",
    "sg:address":"67 Falstone Avenue",
    "sg:city":"South Shields",
    "sg:classifiers":[
        {
            "category":"Organizations",
            "subcategory":"Community Association",
            "type":"Services"
        }
    ],
    "sg:phone":"+44 191 455 5504",
    "sg:postcode":"NE34 6SA",
    "sg:province":"Tyne and Wear",
    "sg:tags":[
        "society",
        "housing"
    ],
    "wof:name":"William Sutton Housing Trust",
    "wof:placetype":"venue"
},
  "geometry": {"coordinates":[-1.404197,54.978004],"type":"Point"}
}