{
  "type": "Feature",
  "properties": {
    "iso:country":"GB",
    "sg:address":"86 Jermyn St",
    "sg:city":"Westminster",
    "sg:classifiers":[
        {
            "category":"Retail",
            "subcategory":"Funeral Services",
            "type":"Services"
        }
    ],
    "sg:phone":"+44 20 7930 0515",
    "sg:postcode":"SW1Y 6JD",
    "sg:province":"Greater London",
    "wof:name":"S C I Press Office",
    "wof:placetype":"venue"
},
  "geometry": {"coordinates":[-0.137500003,51.5080032349],"type":"Point"}
}