{
  "type": "Feature",
  "properties": {
    "iso:country":"GB",
    "sg:address":"9 Watermore Road",
    "sg:city":"Cirencester",
    "sg:classifiers":[
        {
            "category":"Shopping",
            "subcategory":"Antiques",
            "type":"Retail Goods"
        }
    ],
    "sg:postcode":"GL7 2BX",
    "sg:province":"Gloucestershire",
    "wof:name":"P Hudson",
    "wof:placetype":"venue"
},
  "geometry": {"coordinates":[-1.976939,51.72654],"type":"Point"}
}