{
  "type": "Feature",
  "properties": {
    "iso:country":"GB",
    "sg:address":"The Coach House Barn Wards Farm, Woodcock Hill",
    "sg:city":"East Grinstead",
    "sg:classifiers":[
        {
            "category":"Retail",
            "subcategory":"Repair Shop",
            "type":"Services"
        },
        {
            "category":"Manufacturing",
            "subcategory":"Furniture",
            "type":"Manufacturing & Wholesale Goods"
        }
    ],
    "sg:phone":"+44 1342 314040",
    "sg:postcode":"RH19 2QZ",
    "sg:province":"East Sussex",
    "sg:tags":[
        "mnfr",
        "upholsterer"
    ],
    "wof:name":"Robert M Lines",
    "wof:placetype":"venue"
},
  "geometry": {"coordinates":[-0.007568,51.123981],"type":"Point"}
}