{
  "type": "Feature",
  "properties": {
    "addr:full":"117 Twiss Green Lane, Culcheth Warrington Cheshire WA3 4HX",
    "addr:housenumber":"117",
    "addr:postcode":"wa3 4hx",
    "addr:street":"Twiss Green Lane",
    "iso:country":"GB",
    "sg:address":"117 Twiss Green Lane, Culcheth",
    "sg:city":"Warrington",
    "sg:classifiers":[
        {
            "category":"Manufacturing",
            "subcategory":"Petroleum Products",
            "type":"Manufacturing & Wholesale Goods"
        }
    ],
    "sg:postcode":"WA3 4HX",
    "sg:province":"Cheshire",
    "sg:tags":[
        "double",
        "glazing"
    ],
    "wof:name":"Astra Seal",
    "wof:placetype":"venue"
},
  "geometry": {"coordinates":[-2.529736042,53.4582519531],"type":"Point"}
}