{
  "type": "Feature",
  "properties": {
    "iso:country":"GB",
    "sg:address":"39-47 Somerset Street",
    "sg:city":"Abertillery",
    "sg:classifiers":[
        {
            "category":"Home & Garden",
            "subcategory":"Home Furnishings",
            "type":"Retail Goods"
        }
    ],
    "sg:phone":"+44 1495 212860",
    "sg:postcode":"NP13 1DL",
    "sg:province":"Blaenau Gwent",
    "sg:tags":[
        "wall",
        "wallpaper",
        "covering"
    ],
    "wof:name":"Fads",
    "wof:placetype":"venue"
},
  "geometry": {"coordinates":[-3.134006,51.729248],"type":"Point"}
}