{
  "type": "Feature",
  "properties": {
    "addr:full":"Plas-yn-llan, Cilcain Mold Denbighshire CH7 5PA",
    "addr:postcode":"ch7 5pa",
    "iso:country":"GB",
    "sg:address":"Plas-yn-llan, Cilcain",
    "sg:city":"Mold",
    "sg:classifiers":[
        {
            "category":"Home & Garden",
            "subcategory":"Household Appliances",
            "type":"Retail Goods"
        }
    ],
    "sg:phone":"+44 1352 740136",
    "sg:postcode":"CH7 5PA",
    "sg:province":"Denbighshire",
    "sg:tags":[
        "spare",
        "heating"
    ],
    "wof:name":"The Cilcain Fireplace",
    "wof:placetype":"venue"
},
  "geometry": {"coordinates":[-3.231229,53.177673],"type":"Point"}
}