{
  "type": "Feature",
  "properties": {
    "iso:country":"GB",
    "sg:address":"93 Pottergate",
    "sg:city":"Norwich",
    "sg:classifiers":[
        {
            "category":"Professional",
            "subcategory":"Art Services",
            "type":"Services"
        }
    ],
    "sg:postcode":"NR2 1DZ",
    "sg:province":"Norfolk",
    "sg:tags":[
        "photographer"
    ],
    "wof:name":"Rampley Photography",
    "wof:placetype":"venue"
},
  "geometry": {"coordinates":[1.28759,52.630604],"type":"Point"}
}