{
  "type": "Feature",
  "properties": {
    "iso:country":"GB",
    "sg:address":"3 Little Clarenden Street",
    "sg:city":"Oxford",
    "sg:classifiers":[
        {
            "category":"Shopping",
            "subcategory":"News",
            "type":"Retail Goods"
        }
    ],
    "sg:phone":"+44 1865 310879",
    "sg:postcode":"OX1 2HP",
    "sg:province":"Oxfordshire",
    "sg:tags":[
        "newsagent"
    ],
    "wof:name":"Martin Retail Group Ltd.",
    "wof:placetype":"venue"
},
  "geometry": {"coordinates":[-1.26142,51.758839],"type":"Point"}
}