{
  "type": "Feature",
  "properties": {
    "addr:full":"22 High Street, Bawtry Doncaster Lincolnshire DN10 6JE",
    "addr:housenumber":"22",
    "addr:postcode":"dn10 6je",
    "addr:street":"High Street",
    "iso:country":"GB",
    "sg:address":"22 High Street, Bawtry",
    "sg:city":"Doncaster",
    "sg:classifiers":[
        {
            "category":"Shopping",
            "subcategory":"Optician",
            "type":"Retail Goods"
        }
    ],
    "sg:phone":"+44 1302 711655",
    "sg:postcode":"DN10 6JE",
    "sg:province":"Lincolnshire",
    "sg:tags":[
        "dispensing"
    ],
    "wof:name":"Jenny Hudson Optician & Hearing Services",
    "wof:placetype":"venue"
},
  "geometry": {"coordinates":[-1.021367,53.429665],"type":"Point"}
}