{
  "type": "Feature",
  "properties": {
    "addr:full":"2 Pear Tree La Gillingham Kent ME7 3RJ",
    "addr:housenumber":"2",
    "addr:postcode":"me7 3rj",
    "addr:street":"Pear;La Gillingham",
    "iso:country":"GB",
    "sg:address":"2 Pear Tree La",
    "sg:city":"Gillingham",
    "sg:classifiers":[
        {
            "category":"Personal",
            "type":"Services"
        }
    ],
    "sg:phone":"+44 1634 234551",
    "sg:postcode":"ME7 3RJ",
    "sg:province":"Kent",
    "sg:tags":[
        "wedding"
    ],
    "wof:name":"Kent Wedding Services",
    "wof:placetype":"venue"
},
  "geometry": {"coordinates":[0.572996974,51.3535995483],"type":"Point"}
}