{
  "type": "Feature",
  "properties": {
    "iso:country":"GB",
    "sg:address":"The Waterfalls, 58 Chanters Av",
    "sg:city":"Manchester",
    "sg:classifiers":[
        {
            "category":"Professional",
            "subcategory":"Detective & Security Services",
            "type":"Services"
        }
    ],
    "sg:phone":"+44 1942 895158",
    "sg:postcode":"M46 9EF",
    "sg:province":"Greater Manchester",
    "sg:tags":[
        "locksmith"
    ],
    "wof:name":"A M K Lock & Key",
    "wof:placetype":"venue"
},
  "geometry": {"coordinates":[-2.4816300869,53.5228881836],"type":"Point"}
}