{
  "type": "Feature",
  "properties": {
    "iso:country":"GB",
    "sg:address":"Thistle Street, Cleland",
    "sg:city":"Motherwell",
    "sg:classifiers":[
        {
            "category":"Organizations",
            "subcategory":"Membership Organization",
            "type":"Services"
        }
    ],
    "sg:phone":"+44 1698 860464",
    "sg:postcode":"ML1 5PA",
    "sg:province":"North Lanarkshire",
    "sg:tags":[
        "club"
    ],
    "wof:name":"Lodge Murdostoun Castle No 1096",
    "wof:placetype":"venue"
},
  "geometry": {"coordinates":[-3.9135389328,55.8030853271],"type":"Point"}
}