{
  "type": "Feature",
  "properties": {
    "addr:full":"Unit 10 The Long Room, Coppermill Lock, Canal Side Uxbridge Buckinghamshire UB9 6JA",
    "addr:housenumber":"unit 10",
    "addr:postcode":"ub9 6ja",
    "addr:street":"The;Canal Side",
    "iso:country":"GB",
    "sg:address":"Unit 10 The Long Room, Coppermill Lock, Canal Side",
    "sg:city":"Uxbridge",
    "sg:classifiers":[
        {
            "category":"Food & Beverages",
            "subcategory":"Bakery",
            "type":"Retail Goods"
        }
    ],
    "sg:phone":"+44 1895 821200",
    "sg:postcode":"UB9 6JA",
    "sg:province":"Buckinghamshire",
    "sg:tags":[
        "confectionery"
    ],
    "wof:name":"Caravan Brill Ltd.",
    "wof:placetype":"venue"
},
  "geometry": {"coordinates":[-0.4979119897,51.6095581055],"type":"Point"}
}