{
  "type": "Feature",
  "properties": {
    "iso:country":"GB",
    "sg:address":"48 North Street",
    "sg:city":"Chichester",
    "sg:classifiers":[
        {
            "category":"Fast Food",
            "type":"Food & Drink"
        },
        {
            "category":"Restaurant",
            "type":"Food & Drink"
        }
    ],
    "sg:phone":"+44 1243 533888",
    "sg:postcode":"PO19 1NF",
    "sg:province":"West Sussex",
    "sg:tags":[
        "away",
        "-",
        "take",
        "chinese"
    ],
    "wof:name":"Lotus House",
    "wof:placetype":"venue"
},
  "geometry": {"coordinates":[-0.7786880136,50.8397712708],"type":"Point"}
}