{
  "type": "Feature",
  "properties": {
    "addr:full":"14 Meadway Harpenden Hertfordshire AL5 1JL",
    "addr:housenumber":"14",
    "addr:postcode":"al5 1jl",
    "addr:street":"Meadway",
    "iso:country":"GB",
    "sg:address":"14 Meadway",
    "sg:city":"Harpenden",
    "sg:classifiers":[
        {
            "category":"Building & Trades",
            "subcategory":"Construction",
            "type":"Services"
        }
    ],
    "sg:postcode":"AL5 1JL",
    "sg:province":"Hertfordshire",
    "sg:tags":[
        "glazier"
    ],
    "wof:name":"Peter J Davies",
    "wof:placetype":"venue"
},
  "geometry": {"coordinates":[-0.3325870037,51.8054695129],"type":"Point"}
}