{
  "type": "Feature",
  "properties": {
    "iso:country":"GB",
    "sg:address":"Headcorn Aerodrome, Shenley Road",
    "sg:city":"Ashford",
    "sg:classifiers":[
        {
            "category":"Organizations",
            "subcategory":"Membership Organization",
            "type":"Services"
        }
    ],
    "sg:phone":"+44 1622 891017",
    "sg:postcode":"TN27 9HX",
    "sg:province":"Kent",
    "sg:tags":[
        "club"
    ],
    "wof:name":"The Tiger Club 1990 Ltd.",
    "wof:placetype":"venue"
},
  "geometry": {"coordinates":[0.6309300065,51.1669006348],"type":"Point"}
}