{
  "type": "Feature",
  "properties": {
    "addr:full":"Nodes Point Holiday Park, Nodes Rd Ryde Isle of Wight PO33 1YA",
    "addr:postcode":"po33 1ya",
    "addr:street":"Nodes;Nodes Rd",
    "iso:country":"GB",
    "sg:address":"Nodes Point Holiday Park, Nodes Rd",
    "sg:city":"Ryde",
    "sg:classifiers":[
        {
            "category":"Recreation",
            "subcategory":"Amusement Park",
            "type":"Entertainment"
        }
    ],
    "sg:phone":"+44 1983 874749",
    "sg:postcode":"PO33 1YA",
    "sg:province":"Isle of Wight",
    "sg:tags":[
        "arcade"
    ],
    "wof:name":"Rank Amusements Ltd",
    "wof:placetype":"venue"
},
  "geometry": {"coordinates":[-1.1686660051,50.7275657654],"type":"Point"}
}