{
  "type": "Feature",
  "properties": {
    "iso:country":"GB",
    "sg:address":"Unit 12, Panteg Industrial Estate, Station Road",
    "sg:city":"Pontypool",
    "sg:classifiers":[
        {
            "category":"Manufacturing",
            "subcategory":"Metals",
            "type":"Manufacturing & Wholesale Goods"
        }
    ],
    "sg:phone":"+44 1495 755111",
    "sg:postcode":"NP4 5LX",
    "sg:province":"Monmouthshire",
    "sg:tags":[
        "steel",
        "fabricator",
        "erectors"
    ],
    "wof:name":"Panteg Fabrication Ltd.",
    "wof:placetype":"venue"
},
  "geometry": {"coordinates":[-3.020679,51.684803],"type":"Point"}
}