{
  "type": "Feature",
  "properties": {
    "addr:full":"123 Wetherby Road Harrogate North Yorkshire HG2 7SH",
    "addr:housenumber":"123",
    "addr:postcode":"hg2 7sh",
    "addr:street":"Wetherby Road",
    "iso:country":"GB",
    "sg:address":"123 Wetherby Road",
    "sg:city":"Harrogate",
    "sg:classifiers":[
        {
            "category":"Arts & Performance",
            "subcategory":"Art Gallery",
            "type":"Entertainment"
        }
    ],
    "sg:phone":"+44 1423 888262",
    "sg:postcode":"HG2 7SH",
    "sg:province":"North Yorkshire",
    "wof:name":"Sandringham Fine Arts Ltd",
    "wof:placetype":"venue"
},
  "geometry": {"coordinates":[-1.50788,53.989174],"type":"Point"}
}