{
  "type": "Feature",
  "properties": {
    "iso:country":"GB",
    "sg:address":"159 Uplands Rd, Oadby",
    "sg:city":"Leicester",
    "sg:classifiers":[
        {
            "category":"Health Services",
            "subcategory":"Doctor",
            "type":"Services"
        }
    ],
    "sg:phone":"+44 116 271 9042",
    "sg:postcode":"LE2 4NW",
    "sg:province":"Leicestershire",
    "sg:tags":[
        "practitioners"
    ],
    "wof:name":"Drs Shanks Baker & London",
    "wof:placetype":"venue"
},
  "geometry": {"coordinates":[-1.0632410049,52.5990867615],"type":"Point"}
}