{
  "type": "Feature",
  "properties": {
    "addr:full":"64a Brixton Road London Greater London SW9 6BP",
    "addr:housenumber":"64a",
    "addr:postcode":"sw9 6bp",
    "addr:street":"Brixton Road",
    "iso:country":"GB",
    "sg:address":"64a Brixton Road",
    "sg:city":"London",
    "sg:classifiers":[
        {
            "category":"Restaurant",
            "type":"Food & Drink"
        }
    ],
    "sg:phone":"+44 20 7582 1415",
    "sg:postcode":"SW9 6BP",
    "sg:province":"Greater London",
    "sg:tags":[
        "indian"
    ],
    "wof:name":"Old Calcutta Tandoori Restaurant",
    "wof:placetype":"venue"
},
  "geometry": {"coordinates":[-0.112218,51.478622],"type":"Point"}
}