{
  "type": "Feature",
  "properties": {
    "addr:full":"5 Great Junction St Edinburgh City of Edinburgh EH6 5HX",
    "addr:housenumber":"5",
    "addr:postcode":"eh6 5hx",
    "addr:street":"Great Junction St Edinburgh",
    "iso:country":"GB",
    "sg:address":"5 Great Junction St",
    "sg:city":"Edinburgh",
    "sg:classifiers":[
        {
            "category":"Bars & Pubs",
            "type":"Food & Drink"
        }
    ],
    "sg:phone":"+44 131 467 7229",
    "sg:postcode":"EH6 5HX",
    "sg:province":"City of Edinburgh",
    "sg:tags":[
        "pubs",
        "inn"
    ],
    "wof:name":"Mac's Bar",
    "wof:placetype":"venue"
},
  "geometry": {"coordinates":[-3.177301,55.973923],"type":"Point"}
}