{
  "type": "Feature",
  "properties": {
    "addr:full":"Breckenridge House, 274 Sauchiehall Street Glasgow Glasgow City G2 3EH",
    "addr:housenumber":"274",
    "addr:postcode":"g2 3eh",
    "addr:street":"Sauchiehall Street",
    "iso:country":"GB",
    "sg:address":"Breckenridge House, 274 Sauchiehall Street",
    "sg:city":"Glasgow",
    "sg:classifiers":[
        {
            "category":"Insurance",
            "subcategory":"Insurance Agent",
            "type":"Services"
        },
        {
            "category":"Professional",
            "subcategory":"Business Services",
            "type":"Services"
        }
    ],
    "sg:phone":"+44 141 332 1862",
    "sg:postcode":"G2 3EH",
    "sg:province":"Glasgow City",
    "sg:tags":[
        "broker",
        "trade"
    ],
    "wof:name":"British Medical Associations",
    "wof:placetype":"venue"
},
  "geometry": {"coordinates":[-4.2620711327,55.8653869629],"type":"Point"}
}