{
  "type": "Feature",
  "properties": {
    "iso:country":"GB",
    "sg:address":"72 Burtondale",
    "sg:city":"Telford",
    "sg:classifiers":[
        {
            "category":"Building & Trades",
            "subcategory":"Construction",
            "type":"Services"
        }
    ],
    "sg:phone":"+44 1952 402953",
    "sg:postcode":"TF3 1PJ",
    "sg:province":"Shropshire",
    "sg:tags":[
        "roofing"
    ],
    "wof:name":"Weatherproof Roofing",
    "wof:placetype":"venue"
},
  "geometry": {"coordinates":[-2.440911,52.648975],"type":"Point"}
}