{
  "type": "Feature",
  "properties": {
    "addr:full":"Hardwicke Building, Mew Square London Greater London WC2A 3SB",
    "addr:postcode":"wc2a 3sb",
    "addr:street":"Mew Square",
    "iso:country":"GB",
    "sg:address":"Hardwicke Building, Mew Square",
    "sg:city":"London",
    "sg:classifiers":[
        {
            "category":"Professional",
            "subcategory":"Lawyer & Legal Services",
            "type":"Services"
        }
    ],
    "sg:phone":"+44 20 7402 2010",
    "sg:postcode":"WC2A 3SB",
    "sg:province":"Greater London",
    "wof:name":"Mosteshar Mackenzie",
    "wof:placetype":"venue"
},
  "geometry": {"coordinates":[-0.112909,51.515797],"type":"Point"}
}