{
  "type": "Feature",
  "properties": {
    "addr:full":"17 Southfield, Bolderton Newark Nottinghamshire NG24 3QB",
    "addr:housenumber":"17",
    "addr:postcode":"ng24 3qb",
    "addr:street":"Southfield Bolderton",
    "iso:country":"GB",
    "sg:address":"17 Southfield, Bolderton",
    "sg:city":"Newark",
    "sg:classifiers":[
        {
            "category":"Wholesale",
            "subcategory":"Office Equipment",
            "type":"Manufacturing & Wholesale Goods"
        }
    ],
    "sg:postcode":"NG24 3QB",
    "sg:province":"Nottinghamshire",
    "sg:tags":[
        "register",
        "cash",
        "accessory"
    ],
    "wof:name":"City Cash Registers",
    "wof:placetype":"venue"
},
  "geometry": {"coordinates":[-0.7947090268,53.0564613342],"type":"Point"}
}