{
  "type": "Feature",
  "properties": {
    "addr:full":"Frosts Garden Centre Newport Road, Woburn Sands Milton Keynes Bedfordshire MK17 8UE",
    "addr:postcode":"mk17 8ue",
    "addr:street":"Newport Road",
    "iso:country":"GB",
    "sg:address":"Frosts Garden Centre Newport Road, Woburn Sands",
    "sg:city":"Milton Keynes",
    "sg:classifiers":[
        {
            "category":"Shopping",
            "subcategory":"Pets & Pet Supplies",
            "type":"Retail Goods"
        }
    ],
    "sg:postcode":"MK17 8UE",
    "sg:province":"Bedfordshire",
    "wof:name":"County Pet Food Centre",
    "wof:placetype":"venue"
},
  "geometry": {"coordinates":[-0.6481159925,52.0134124756],"type":"Point"}
}