{
  "type": "Feature",
  "properties": {
    "iso:country":"GB",
    "sg:address":"Unit 1 Cross Lane Business Park, Headlands Road",
    "sg:city":"Liversedge",
    "sg:classifiers":[
        {
            "category":"Retail",
            "subcategory":"Auto Repair",
            "type":"Services"
        }
    ],
    "sg:phone":"+44 1924 404366",
    "sg:postcode":"WF15 6PR",
    "sg:province":"West Yorkshire",
    "sg:tags":[
        "modification",
        "garage",
        "related"
    ],
    "wof:name":"Springwell Motors",
    "wof:placetype":"venue"
},
  "geometry": {"coordinates":[-1.703635,53.710667],"type":"Point"}
}