{
  "type": "Feature",
  "properties": {
    "addr:full":"130 Blackburn Road Bolton Lancashire BL1 8DW",
    "addr:housenumber":"130",
    "addr:postcode":"bl1 8dw",
    "addr:street":"Blackburn Road",
    "iso:country":"GB",
    "sg:address":"130 Blackburn Road",
    "sg:city":"Bolton",
    "sg:classifiers":[
        {
            "category":"Food & Beverages",
            "subcategory":"Bakery",
            "type":"Retail Goods"
        }
    ],
    "sg:phone":"+44 1204 526982",
    "sg:postcode":"BL1 8DW",
    "sg:province":"Lancashire",
    "sg:tags":[
        "baker"
    ],
    "wof:name":"Kirk's",
    "wof:placetype":"venue"
},
  "geometry": {"coordinates":[-2.430542,53.590431],"type":"Point"}
}