{
  "type": "Feature",
  "properties": {
    "iso:country":"GB",
    "sg:address":"24 Market Hill",
    "sg:city":"Woodbridge",
    "sg:classifiers":[
        {
            "category":"Shopping",
            "subcategory":"Antiques",
            "type":"Retail Goods"
        }
    ],
    "sg:phone":"+44 1394 385830",
    "sg:postcode":"IP12 4LU",
    "sg:province":"Suffolk",
    "wof:name":"A G Voss Antiques",
    "wof:placetype":"venue"
},
  "geometry": {"coordinates":[1.3129329681,52.094078064],"type":"Point"}
}