{
  "type": "Feature",
  "properties": {
    "iso:country":"GB",
    "sg:address":"196 Liscard Rd",
    "sg:city":"Wallasey",
    "sg:classifiers":[
        {
            "category":"Food & Beverages",
            "subcategory":"Bakery",
            "type":"Retail Goods"
        }
    ],
    "sg:phone":"+44 151 691 0000",
    "sg:postcode":"L44 5TN",
    "sg:province":"Merseyside",
    "sg:tags":[
        "pizza"
    ],
    "wof:name":"Captain Tony's Pizza",
    "wof:placetype":"venue"
},
  "geometry": {"coordinates":[-3.0410439968,53.4183425903],"type":"Point"}
}