{
  "type": "Feature",
  "properties": {
    "iso:country":"GB",
    "sg:address":"Unit 3b The Gattinetis, Hadleigh Road",
    "sg:city":"Colchester",
    "sg:classifiers":[
        {
            "category":"Professional",
            "subcategory":"Printing & Photocopies",
            "type":"Services"
        }
    ],
    "sg:postcode":"CO7 6QT",
    "sg:province":"Essex",
    "sg:tags":[
        "print",
        "finisher"
    ],
    "wof:name":"Apple Binding Ltd.",
    "wof:placetype":"venue"
},
  "geometry": {"coordinates":[1.0097800493,51.9755897522],"type":"Point"}
}