{
  "type": "Feature",
  "properties": {
    "addr:full":"Mid Tarn Farm, Sellafield Seascale Cumbria CA20 1DT",
    "addr:postcode":"ca20 1dt",
    "addr:street":"Mid Tarn",
    "iso:country":"GB",
    "sg:address":"Mid Tarn Farm, Sellafield",
    "sg:city":"Seascale",
    "sg:classifiers":[
        {
            "category":"Farming",
            "subcategory":"Dairy Farm",
            "type":"Manufacturing & Wholesale Goods"
        }
    ],
    "sg:phone":"+44 1946 841386",
    "sg:postcode":"CA20 1DT",
    "sg:province":"Cumbria",
    "sg:tags":[
        "farmer"
    ],
    "wof:name":"ROBERT L JENKINSON",
    "wof:placetype":"venue"
},
  "geometry": {"coordinates":[-3.48462,54.394821],"type":"Point"}
}