{
  "type": "Feature",
  "properties": {
    "iso:country":"GB",
    "sg:address":"8a Station Road, Lyminge",
    "sg:city":"Folkestone",
    "sg:classifiers":[
        {
            "category":"Health Services",
            "subcategory":"Dentist",
            "type":"Services"
        }
    ],
    "sg:phone":"+44 1303 862479",
    "sg:postcode":"CT18 8HP",
    "sg:province":"Kent",
    "wof:name":"C J Francis",
    "wof:placetype":"venue"
},
  "geometry": {"coordinates":[1.090761,51.127186],"type":"Point"}
}