{
  "type": "Feature",
  "properties": {
    "iso:country":"GB",
    "sg:address":"52 Prospect St, Caversham",
    "sg:city":"Reading",
    "sg:classifiers":[
        {
            "category":"Shopping",
            "subcategory":"Used Merchandise",
            "type":"Retail Goods"
        }
    ],
    "sg:postcode":"RG4 8JL",
    "sg:province":"Berkshire",
    "sg:tags":[
        "shop",
        "second-hand"
    ],
    "wof:name":"Jill's Corner",
    "wof:placetype":"venue"
},
  "geometry": {"coordinates":[-0.9716110229,51.4687957764],"type":"Point"}
}