{
  "type": "Feature",
  "properties": {
    "addr:full":"8 School La Cambridge Cambridgeshire CB5 9PW",
    "addr:housenumber":"8",
    "addr:postcode":"cb5 9pw",
    "addr:street":"School La",
    "iso:country":"GB",
    "sg:address":"8 School La",
    "sg:city":"Cambridge",
    "sg:classifiers":[
        {
            "category":"Farming",
            "subcategory":"Fish & Marine Products",
            "type":"Manufacturing & Wholesale Goods"
        }
    ],
    "sg:phone":"+44 1223 861141",
    "sg:postcode":"CB5 9PW",
    "sg:province":"Cambridgeshire",
    "sg:tags":[
        "fishmonger"
    ],
    "wof:name":"Happy Sole",
    "wof:placetype":"venue"
},
  "geometry": {"coordinates":[0.1974669993,52.3065605164],"type":"Point"}
}