{
  "type": "Feature",
  "properties": {
    "addr:full":"4 Teyfant Road Bristol City of Bristol BS13 0RF",
    "addr:housenumber":"4",
    "addr:postcode":"bs13 0rf",
    "addr:street":"Teyfant Road",
    "iso:country":"GB",
    "sg:address":"4 Teyfant Road",
    "sg:city":"Bristol",
    "sg:classifiers":[
        {
            "category":"Food & Beverages",
            "subcategory":"Groceries & Convenience Stores",
            "type":"Retail Goods"
        }
    ],
    "sg:phone":"+44 117 964 1845",
    "sg:postcode":"BS13 0RF",
    "sg:province":"City of Bristol",
    "wof:name":"The Happy Shopper",
    "wof:placetype":"venue"
},
  "geometry": {"coordinates":[-2.59049,51.40493],"type":"Point"}
}