{
  "type": "Feature",
  "properties": {
    "addr:full":"6 Meadowfield, North Seaton Ashington Northumberland NE63 9TR",
    "addr:housenumber":"6",
    "addr:postcode":"ne63 9tr",
    "addr:street":"Meadowfield North",
    "iso:country":"GB",
    "sg:address":"6 Meadowfield, North Seaton",
    "sg:city":"Ashington",
    "sg:classifiers":[
        {
            "category":"Food & Beverages",
            "subcategory":"Meat & Fish",
            "type":"Retail Goods"
        }
    ],
    "sg:phone":"+44 1670 812461",
    "sg:postcode":"NE63 9TR",
    "sg:province":"Northumberland",
    "sg:tags":[
        "chip"
    ],
    "wof:name":"Biron Fisheries",
    "wof:placetype":"venue"
},
  "geometry": {"coordinates":[-1.5415569544,55.1739959717],"type":"Point"}
}