{
  "type": "Feature",
  "properties": {
    "addr:full":"Felling Health Centre, Stephenson Terrace, Felling Gateshead Tyne and Wear NE10 9QG",
    "addr:postcode":"ne10 9qg",
    "addr:street":"Stephenson Terrace",
    "iso:country":"GB",
    "sg:address":"Felling Health Centre, Stephenson Terrace, Felling",
    "sg:city":"Gateshead",
    "sg:classifiers":[
        {
            "category":"Health Services",
            "subcategory":"Doctor",
            "type":"Services"
        }
    ],
    "sg:phone":"+44 191 469 2311",
    "sg:postcode":"NE10 9QG",
    "sg:province":"Tyne and Wear",
    "sg:tags":[
        "practitioners"
    ],
    "wof:name":"Drs Rutenberg Megson Bowman & Smith",
    "wof:placetype":"venue"
},
  "geometry": {"coordinates":[-1.5691189766,54.9522285461],"type":"Point"}
}