{
  "type": "Feature",
  "properties": {
    "addr:full":"Shieldaig Farm Gairloch Highland IV21 2AN",
    "addr:postcode":"iv21 2an",
    "addr:street":"Gairloch",
    "iso:country":"GB",
    "sg:address":"Shieldaig Farm",
    "sg:city":"Gairloch",
    "sg:classifiers":[
        {
            "category":"Farming",
            "subcategory":"Livestock Farm",
            "type":"Manufacturing & Wholesale Goods"
        }
    ],
    "sg:phone":"+44 1445 741223",
    "sg:postcode":"IV21 2AN",
    "sg:province":"Highland",
    "sg:tags":[
        "others"
    ],
    "wof:name":"John Donald Macrae",
    "wof:placetype":"venue"
},
  "geometry": {"coordinates":[-5.6936888695,57.7286148071],"type":"Point"}
}