{
  "type": "Feature",
  "properties": {
    "addr:full":"4 London Road East Grinstead East Sussex RH19 1AG",
    "addr:housenumber":"4",
    "addr:postcode":"rh19 1ag",
    "addr:street":"London Road",
    "iso:country":"GB",
    "sg:address":"4 London Road",
    "sg:city":"East Grinstead",
    "sg:classifiers":[
        {
            "category":"Retail",
            "subcategory":"Photofinishing",
            "type":"Services"
        }
    ],
    "sg:phone":"+44 1342 322711",
    "sg:postcode":"RH19 1AG",
    "sg:province":"East Sussex",
    "sg:tags":[
        "photographic",
        "processor"
    ],
    "wof:name":"One Stop Photos",
    "wof:placetype":"venue"
},
  "geometry": {"coordinates":[-0.0085030003,51.1241798401],"type":"Point"}
}