{
  "type": "Feature",
  "properties": {
    "addr:full":"69 Cricketfield Road London Greater London E5 8NR",
    "addr:housenumber":"69",
    "addr:postcode":"e5 8nr",
    "addr:street":"Cricketfield Road",
    "iso:country":"GB",
    "sg:address":"69 Cricketfield Road",
    "sg:city":"London",
    "sg:classifiers":[
        {
            "category":"Organizations",
            "subcategory":"Community Association",
            "type":"Services"
        }
    ],
    "sg:phone":"+44 20 8986 6739",
    "sg:postcode":"E5 8NR",
    "sg:province":"Greater London",
    "sg:tags":[
        "society",
        "housing"
    ],
    "wof:name":"Refugee Housing Association",
    "wof:placetype":"venue"
},
  "geometry": {"coordinates":[-0.05717,51.555092],"type":"Point"}
}