{
  "type": "Feature",
  "properties": {
    "addr:full":"46 Knighton Heath Road, Bear Cross Bournemouth Dorset BH11 9PW",
    "addr:housenumber":"46",
    "addr:postcode":"bh11 9pw",
    "addr:street":"Knighton Heath Road Bear Cross",
    "iso:country":"GB",
    "sg:address":"46 Knighton Heath Road, Bear Cross",
    "sg:city":"Bournemouth",
    "sg:classifiers":[
        {
            "category":"Professional",
            "subcategory":"Management & Consulting",
            "type":"Services"
        }
    ],
    "sg:phone":"+44 1202 573965",
    "sg:postcode":"BH11 9PW",
    "sg:province":"Dorset",
    "sg:tags":[
        "consultant",
        "business"
    ],
    "wof:name":"Cunupia Consultancy Ltd.",
    "wof:placetype":"venue"
},
  "geometry": {"coordinates":[-1.9255490303,50.7643852234],"type":"Point"}
}