{
  "type": "Feature",
  "properties": {
    "addr:full":"163 Wellington Street, Long Eaton Nottingham Derbyshire NG10 4JQ",
    "addr:housenumber":"163",
    "addr:postcode":"ng10 4jq",
    "addr:street":"Wellington Street",
    "iso:country":"GB",
    "sg:address":"163 Wellington Street, Long Eaton",
    "sg:city":"Nottingham",
    "sg:classifiers":[
        {
            "category":"Retail",
            "subcategory":"Auto Repair",
            "type":"Services"
        }
    ],
    "sg:postcode":"NG10 4JQ",
    "sg:province":"Derbyshire",
    "sg:tags":[
        "modification",
        "garage"
    ],
    "wof:name":"James G Havercroft",
    "wof:placetype":"venue"
},
  "geometry": {"coordinates":[-1.2836639881,52.9087295532],"type":"Point"}
}