{
  "type": "Feature",
  "properties": {
    "addr:full":"30 Balmoral Rd Morecambe Lancashire LA4 4JW",
    "addr:housenumber":"30",
    "addr:postcode":"la4 4jw",
    "addr:street":"Balmoral Rd",
    "iso:country":"GB",
    "sg:address":"30 Balmoral Rd",
    "sg:city":"Morecambe",
    "sg:classifiers":[
        {
            "category":"Professional",
            "subcategory":"Accounting & Tax Preparation",
            "type":"Services"
        }
    ],
    "sg:phone":"+44 1524 412969",
    "sg:postcode":"LA4 4JW",
    "sg:province":"Lancashire",
    "sg:tags":[
        "accountant"
    ],
    "wof:name":"David A. Sutton",
    "wof:placetype":"venue"
},
  "geometry": {"coordinates":[-2.8723759651,54.0668640137],"type":"Point"}
}