{
  "type": "Feature",
  "properties": {
    "iso:country":"GB",
    "sg:address":"51 Waveney Road",
    "sg:city":"Ipswich",
    "sg:classifiers":[
        {
            "category":"Professional",
            "subcategory":"Computer Services",
            "type":"Services"
        }
    ],
    "sg:phone":"+44 1473 740101",
    "sg:postcode":"IP1 5DF",
    "sg:province":"Suffolk",
    "sg:tags":[
        "development",
        "system",
        "software"
    ],
    "wof:name":"Directdual Ltd.",
    "wof:placetype":"venue"
},
  "geometry": {"coordinates":[1.1231700182,52.0689086914],"type":"Point"}
}