{
  "type": "Feature",
  "properties": {
    "iso:country":"GB",
    "sg:address":"313 Marton Road",
    "sg:city":"Middlesbrough",
    "sg:classifiers":[
        {
            "category":"Health Services",
            "subcategory":"Nursing And Care Facility",
            "type":"Services"
        }
    ],
    "sg:phone":"+44 1642 250013",
    "sg:postcode":"TS4 2HG",
    "sg:province":"North Yorkshire",
    "sg:tags":[
        "home"
    ],
    "wof:name":"Tamaris Care Properties Ltd.",
    "wof:placetype":"venue"
},
  "geometry": {"coordinates":[-1.2246359587,54.5645179749],"type":"Point"}
}