{
  "type": "Feature",
  "properties": {
    "addr:full":"53 Merthyr Road, Tongwynlais Cardiff Caerphilly CF15 7LG",
    "addr:housenumber":"53",
    "addr:postcode":"cf15 7lg",
    "addr:street":"Merthyr Road",
    "iso:country":"GB",
    "sg:address":"53 Merthyr Road, Tongwynlais",
    "sg:city":"Cardiff",
    "sg:classifiers":[
        {
            "category":"Arena",
            "subcategory":"Sports Club",
            "type":"Entertainment"
        }
    ],
    "sg:phone":"+44 29 2081 3082",
    "sg:postcode":"CF15 7LG",
    "sg:province":"Caerphilly",
    "wof:name":"R F C Tongwynlais",
    "wof:placetype":"venue"
},
  "geometry": {"coordinates":[-3.25235,51.53212],"type":"Point"}
}