{
  "type": "Feature",
  "properties": {
    "iso:country":"GB",
    "sg:address":"29 Flash Lane",
    "sg:city":"Mirfield",
    "sg:classifiers":[
        {
            "category":"Building & Trades",
            "subcategory":"Equipment Rental",
            "type":"Services"
        }
    ],
    "sg:postcode":"WF14 0PJ",
    "sg:province":"West Yorkshire",
    "sg:tags":[
        "hire",
        "catering"
    ],
    "wof:name":"1st Class Catering Equipment Hire",
    "wof:placetype":"venue"
},
  "geometry": {"coordinates":[-1.6841390133,53.683265686],"type":"Point"}
}