{
  "type": "Feature",
  "properties": {
    "iso:country":"GB",
    "sg:address":"232 Merton High St",
    "sg:city":"Wimbledon",
    "sg:classifiers":[
        {
            "category":"Taxi",
            "type":"Transportation"
        }
    ],
    "sg:phone":"+44 20 8540 4444",
    "sg:postcode":"SW19 1AU",
    "sg:province":"Greater London",
    "sg:tags":[
        "mini",
        "cab"
    ],
    "wof:name":"Southwest Cars",
    "wof:placetype":"venue"
},
  "geometry": {"coordinates":[-0.192255,51.416447],"type":"Point"}
}