{
  "type": "Feature",
  "properties": {
    "iso:country":"GB",
    "sg:address":"35 Mariner Street",
    "sg:city":"Swansea",
    "sg:classifiers":[
        {
            "category":"Sports & Exercise",
            "subcategory":"Gym",
            "type":"Entertainment"
        }
    ],
    "sg:phone":"+44 1792 459282",
    "sg:postcode":"SA1 5BA",
    "sg:province":"Neath Port Talbot",
    "sg:tags":[
        "fitness",
        "health",
        "centre"
    ],
    "wof:name":"Jads Gymnasium Ltd.",
    "wof:placetype":"venue"
},
  "geometry": {"coordinates":[-3.942568,51.625473],"type":"Point"}
}