{
  "type": "Feature",
  "properties": {
    "addr:full":"36 Elgar Drive Shefford Bedfordshire SG17 5RZ",
    "addr:housenumber":"36",
    "addr:postcode":"sg17 5rz",
    "addr:street":"Elgar Drive",
    "iso:country":"GB",
    "sg:address":"36 Elgar Drive",
    "sg:city":"Shefford",
    "sg:classifiers":[
        {
            "category":"Professional",
            "subcategory":"Detective & Security Services",
            "type":"Services"
        }
    ],
    "sg:postcode":"SG17 5RZ",
    "sg:province":"Bedfordshire",
    "sg:tags":[
        "video",
        "cctv"
    ],
    "wof:name":"E C S Technical Services",
    "wof:placetype":"venue"
},
  "geometry": {"coordinates":[-0.32628,52.038357],"type":"Point"}
}