{
  "type": "Feature",
  "properties": {
    "iso:country":"GB",
    "sg:address":"54 High Street, Portishead",
    "sg:city":"Bristol",
    "sg:classifiers":[
        {
            "category":"Shopping",
            "subcategory":"Pets & Pet Supplies",
            "type":"Retail Goods"
        }
    ],
    "sg:phone":"+44 1275 842265",
    "sg:postcode":"BS20 6EL",
    "sg:province":"Somerset",
    "wof:name":"Portishead Pet & Garden Centre",
    "wof:placetype":"venue"
},
  "geometry": {"coordinates":[-2.768923,51.48373],"type":"Point"}
}