{
  "type": "Feature",
  "properties": {
    "addr:full":"Care Of Debenhams, Royal Parade Plymouth Devon PL1 1SA",
    "addr:postcode":"pl1 1sa",
    "addr:street":"Royal Parade",
    "iso:country":"GB",
    "sg:address":"Care Of Debenhams, Royal Parade",
    "sg:city":"Plymouth",
    "sg:classifiers":[
        {
            "category":"Personal",
            "subcategory":"Beauty Salon",
            "type":"Services"
        }
    ],
    "sg:phone":"+44 1752 229070",
    "sg:postcode":"PL1 1SA",
    "sg:province":"Devon",
    "sg:tags":[
        "unisex",
        "hairdresser"
    ],
    "wof:name":"Regis Hair & Beauty Salon",
    "wof:placetype":"venue"
},
  "geometry": {"coordinates":[-4.14041,50.370979],"type":"Point"}
}