{
  "type": "Feature",
  "properties": {
    "addr:full":"Unit M27, New Market Hall, Common Garden St Lancaster Lancashire LA1 1XD",
    "addr:postcode":"la1 1xd",
    "addr:street":"St",
    "iso:country":"GB",
    "sg:address":"Unit M27, New Market Hall, Common Garden St",
    "sg:city":"Lancaster",
    "sg:classifiers":[
        {
            "category":"Shopping",
            "subcategory":"Clothing, Apparel, & Fashions",
            "type":"Retail Goods"
        }
    ],
    "sg:postcode":"LA1 1XD",
    "sg:province":"Lancashire",
    "sg:tags":[
        "shop"
    ],
    "wof:name":"Sareen,K,",
    "wof:placetype":"venue"
},
  "geometry": {"coordinates":[-2.799029,54.044537],"type":"Point"}
}