{
  "type": "Feature",
  "properties": {
    "addr:full":"78 Manchester Road, Hapton Burnley Lancashire BB12 7LF",
    "addr:housenumber":"78",
    "addr:postcode":"bb12 7lf",
    "addr:street":"Manchester Road",
    "iso:country":"GB",
    "sg:address":"78 Manchester Road, Hapton",
    "sg:city":"Burnley",
    "sg:classifiers":[
        {
            "category":"Freight",
            "type":"Transportation"
        }
    ],
    "sg:phone":"+44 1282 778747",
    "sg:postcode":"BB12 7LF",
    "sg:province":"Lancashire",
    "sg:tags":[
        "haulage",
        "road"
    ],
    "wof:name":"Cowie Transport",
    "wof:placetype":"venue"
},
  "geometry": {"coordinates":[-2.3163158894,53.7820549011],"type":"Point"}
}