{
  "type": "Feature",
  "properties": {
    "iso:country":"GB",
    "sg:address":"50 Dale St",
    "sg:city":"Liverpool",
    "sg:classifiers":[
        {
            "category":"Food & Beverages",
            "subcategory":"Fruits & Vegetables",
            "type":"Retail Goods"
        }
    ],
    "sg:postcode":"L2 5ST",
    "sg:province":"Merseyside",
    "sg:tags":[
        "greengrocer"
    ],
    "wof:name":"Baron,Ray,",
    "wof:placetype":"venue"
},
  "geometry": {"coordinates":[-2.988027,53.408176],"type":"Point"}
}