{
  "type": "Feature",
  "properties": {
    "addr:full":"190 Kingston Road Epsom Surrey KT19 0SF",
    "addr:housenumber":"190",
    "addr:postcode":"kt19 0sf",
    "addr:street":"Kingston Road",
    "iso:country":"GB",
    "sg:address":"190 Kingston Road",
    "sg:city":"Epsom",
    "sg:classifiers":[
        {
            "category":"Personal",
            "subcategory":"Beauty Salon",
            "type":"Services"
        },
        {
            "category":"Personal",
            "subcategory":"Barber",
            "type":"Services"
        }
    ],
    "sg:phone":"+44 20 8393 2229",
    "sg:postcode":"KT19 0SF",
    "sg:province":"Surrey",
    "sg:tags":[
        "unisex",
        "hairdresser"
    ],
    "wof:name":"Geneva Reeves Unisex Hair Salon",
    "wof:placetype":"venue"
},
  "geometry": {"coordinates":[-0.253353,51.361263],"type":"Point"}
}