{
  "type": "Feature",
  "properties": {
    "addr:full":"4 Common Close, North Leigh Witney Oxfordshire OX8 6RG",
    "addr:housenumber":"4",
    "addr:postcode":"ox8 6rg",
    "addr:street":"Common Close North Leigh",
    "iso:country":"GB",
    "sg:address":"4 Common Close, North Leigh",
    "sg:city":"Witney",
    "sg:classifiers":[
        {
            "category":"Building & Trades",
            "subcategory":"Construction",
            "type":"Services"
        }
    ],
    "sg:phone":"+44 1993 883308",
    "sg:postcode":"OX8 6RG",
    "sg:province":"Oxfordshire",
    "sg:tags":[
        "flooring"
    ],
    "wof:name":"The Floor Covering Co",
    "wof:placetype":"venue"
},
  "geometry": {"coordinates":[-1.44183,51.815128],"type":"Point"}
}