{
  "type": "Feature",
  "properties": {
    "iso:country":"GB",
    "sg:address":"177 Cowick Street",
    "sg:city":"Exeter",
    "sg:classifiers":[
        {
            "category":"Shopping",
            "subcategory":"Shoes",
            "type":"Retail Goods"
        }
    ],
    "sg:phone":"+44 1392 273758",
    "sg:postcode":"EX4 1AA",
    "sg:province":"Devon",
    "wof:name":"Minit (U K) Plc",
    "wof:placetype":"venue"
},
  "geometry": {"coordinates":[-3.538689,50.717838],"type":"Point"}
}