{
  "type": "Feature",
  "properties": {
    "iso:country":"GB",
    "sg:address":"5 Melrose Road",
    "sg:city":"Norwich",
    "sg:classifiers":[
        {
            "category":"Retail",
            "subcategory":"Auto Repair",
            "type":"Services"
        }
    ],
    "sg:phone":"+44 1603 452534",
    "sg:postcode":"NR4 7PN",
    "sg:province":"Norfolk",
    "sg:tags":[
        "modification",
        "garage",
        "related"
    ],
    "wof:name":"Melrose Garage",
    "wof:placetype":"venue"
},
  "geometry": {"coordinates":[1.270131,52.618137],"type":"Point"}
}