{
  "type": "Feature",
  "properties": {
    "iso:country":"GB",
    "sg:address":"28a Frodsham Street",
    "sg:city":"Chester",
    "sg:classifiers":[
        {
            "category":"Manufacturing",
            "subcategory":"Jewelry",
            "type":"Manufacturing & Wholesale Goods"
        }
    ],
    "sg:phone":"+44 1244 312483",
    "sg:postcode":"CH1 3JL",
    "sg:province":"Cheshire",
    "sg:tags":[
        "manufacture",
        "repair",
        "jewellery"
    ],
    "wof:name":"J P Williams",
    "wof:placetype":"venue"
},
  "geometry": {"coordinates":[-2.8882489204,53.1919937134],"type":"Point"}
}