{
  "type": "Feature",
  "properties": {
    "iso:country":"GB",
    "sg:address":"35 Abbey Road",
    "sg:city":"Dalkeith",
    "sg:classifiers":[
        {
            "category":"Sports & Exercise",
            "subcategory":"Golf",
            "type":"Entertainment"
        }
    ],
    "sg:phone":"+44 131 663 2123",
    "sg:postcode":"EH22 3AD",
    "sg:province":"City of Edinburgh",
    "sg:tags":[
        "club",
        "course"
    ],
    "wof:name":"Newbattle Golf Club Ltd",
    "wof:placetype":"venue"
},
  "geometry": {"coordinates":[-3.071982,55.888367],"type":"Point"}
}