{
  "type": "Feature",
  "properties": {
    "iso:country":"GB",
    "sg:address":"Knoll Lodge, Knoll La",
    "sg:city":"Wimborne",
    "sg:classifiers":[
        {
            "category":"Building & Trades",
            "subcategory":"Construction",
            "type":"Services"
        }
    ],
    "sg:postcode":"BH21 3RF",
    "sg:province":"Dorset",
    "sg:tags":[
        "builder"
    ],
    "wof:name":"Habgood,R C,(Builder),",
    "wof:placetype":"venue"
},
  "geometry": {"coordinates":[-1.988709,50.802235],"type":"Point"}
}