{
  "type": "Feature",
  "properties": {
    "addr:full":"35 New Chapel Street Blackburn Lancashire BB2 4DT",
    "addr:housenumber":"35",
    "addr:postcode":"bb2 4dt",
    "addr:street":"New Chapel Street",
    "iso:country":"GB",
    "sg:address":"35 New Chapel Street",
    "sg:city":"Blackburn",
    "sg:classifiers":[
        {
            "category":"Shopping",
            "subcategory":"News",
            "type":"Retail Goods"
        }
    ],
    "sg:phone":"+44 1254 57479",
    "sg:postcode":"BB2 4DT",
    "sg:province":"Lancashire",
    "sg:tags":[
        "newsagent"
    ],
    "wof:name":"S H & S Bennett",
    "wof:placetype":"venue"
},
  "geometry": {"coordinates":[-2.502343,53.733238],"type":"Point"}
}