{
  "type": "Feature",
  "properties": {
    "iso:country":"GB",
    "sg:address":"5 Winchester Street, Overton",
    "sg:city":"Basingstoke",
    "sg:classifiers":[
        {
            "category":"Real Estate",
            "subcategory":"Real Estate Agent",
            "type":"Services"
        }
    ],
    "sg:phone":"+44 1256 770836",
    "sg:postcode":"RG25 3HR",
    "sg:province":"Hampshire",
    "wof:name":"Parnell Jordy & Harvey",
    "wof:placetype":"venue"
},
  "geometry": {"coordinates":[-1.2628699541,51.243724823],"type":"Point"}
}