{
  "type": "Feature",
  "properties": {
    "addr:full":"12 Sedgley Gro Birmingham West Midlands B20 1JE",
    "addr:housenumber":"12",
    "addr:postcode":"b20 1je",
    "addr:street":"Sedgley Gro",
    "iso:country":"GB",
    "sg:address":"12 Sedgley Gro",
    "sg:city":"Birmingham",
    "sg:classifiers":[
        {
            "category":"Communications",
            "type":"Services"
        }
    ],
    "sg:postcode":"B20 1JE",
    "sg:province":"West Midlands",
    "sg:tags":[
        "data",
        "network"
    ],
    "wof:name":"Acton,Desiree,",
    "wof:placetype":"venue"
},
  "geometry": {"coordinates":[-1.9378099442,52.5250358582],"type":"Point"}
}