{
  "type": "Feature",
  "properties": {
    "iso:country":"GB",
    "sg:address":"Woodside Farm, Appleton Road, Acaster Malbis",
    "sg:city":"York",
    "sg:classifiers":[
        {
            "category":"Food & Beverages",
            "subcategory":"Farmers Market",
            "type":"Retail Goods"
        }
    ],
    "sg:postcode":"YO23 2XA",
    "sg:province":"North Yorkshire",
    "sg:tags":[
        "farm",
        "shop",
        "pyo"
    ],
    "wof:name":"Kevin D Voakes",
    "wof:placetype":"venue"
},
  "geometry": {"coordinates":[-1.106099,53.904945],"type":"Point"}
}