{
  "type": "Feature",
  "properties": {
    "iso:country":"GB",
    "sg:address":"4 The Knoll, Ellington",
    "sg:city":"Morpeth",
    "sg:classifiers":[
        {
            "category":"Professional",
            "subcategory":"Art Services",
            "type":"Services"
        },
        {
            "category":"Building & Trades",
            "subcategory":"Construction",
            "type":"Services"
        }
    ],
    "sg:phone":"+44 1670 860911",
    "sg:postcode":"NE61 5LQ",
    "sg:province":"Northumberland",
    "sg:tags":[
        "decorator",
        "painter"
    ],
    "wof:name":"R H Armstrong",
    "wof:placetype":"venue"
},
  "geometry": {"coordinates":[-1.577114,55.231937],"type":"Point"}
}