{
  "type": "Feature",
  "properties": {
    "addr:full":"Unit 14a Union Mill St Wolverhampton West Midlands WV1 3DW",
    "addr:housenumber":"unit 14a",
    "addr:postcode":"wv1 3dw",
    "addr:street":"Union Mill St",
    "iso:country":"GB",
    "sg:address":"Unit 14a Union Mill St",
    "sg:city":"Wolverhampton",
    "sg:classifiers":[
        {
            "category":"Retail",
            "subcategory":"Auto Repair",
            "type":"Services"
        }
    ],
    "sg:phone":"+44 1902 455841",
    "sg:postcode":"WV1 3DW",
    "sg:province":"West Midlands",
    "sg:tags":[
        "modification",
        "garage"
    ],
    "wof:name":"Mr Mini",
    "wof:placetype":"venue"
},
  "geometry": {"coordinates":[-2.1165850163,52.5854721069],"type":"Point"}
}