{
  "type": "Feature",
  "properties": {
    "addr:full":"15 Newport Road Stafford Staffordshire ST16 2EX",
    "addr:housenumber":"15",
    "addr:postcode":"st16 2ex",
    "addr:street":"Newport Road",
    "iso:country":"GB",
    "sg:address":"15 Newport Road",
    "sg:city":"Stafford",
    "sg:classifiers":[
        {
            "category":"Bars & Pubs",
            "type":"Food & Drink"
        }
    ],
    "sg:postcode":"ST16 2EX",
    "sg:province":"Staffordshire",
    "sg:tags":[
        "pubs",
        "inn"
    ],
    "wof:name":"The Eagle Inn",
    "wof:placetype":"venue"
},
  "geometry": {"coordinates":[-2.116379,52.80368],"type":"Point"}
}