{
  "type": "Feature",
  "properties": {
    "addr:full":"Vault 37, London Silver Vaults London Greater London WC2A 1AF",
    "addr:housenumber":"37",
    "addr:postcode":"wc2a 1af",
    "addr:street":"London Silver Vaults",
    "iso:country":"GB",
    "sg:address":"Vault 37, London Silver Vaults",
    "sg:city":"London",
    "sg:classifiers":[
        {
            "category":"Shopping",
            "subcategory":"Antiques",
            "type":"Retail Goods"
        }
    ],
    "sg:phone":"+44 20 7242 3221",
    "sg:postcode":"WC2A 1AF",
    "sg:province":"Greater London",
    "wof:name":"Jack Simons (Antiques) Ltd.",
    "wof:placetype":"venue"
},
  "geometry": {"coordinates":[-0.1134499982,51.5178489685],"type":"Point"}
}