{
  "type": "Feature",
  "properties": {
    "iso:country":"GB",
    "sg:address":"169 Eastern Esplanade",
    "sg:city":"Canvey Island",
    "sg:classifiers":[
        {
            "category":"Building & Trades",
            "subcategory":"Cleaning & Sanitation",
            "type":"Services"
        }
    ],
    "sg:phone":"+44 1268 510964",
    "sg:postcode":"SS8 7HY",
    "sg:province":"Essex",
    "sg:tags":[
        "industrial",
        "business",
        "removal"
    ],
    "wof:name":"P.H.D Services",
    "wof:placetype":"venue"
},
  "geometry": {"coordinates":[0.604568,51.513397],"type":"Point"}
}