{
  "type": "Feature",
  "properties": {
    "addr:full":"Heronsgate Centre, Whinchat Road London Greater London SE28 0DW",
    "addr:postcode":"se28 0dw",
    "addr:street":"Heronsgate;Whinchat Road",
    "iso:country":"GB",
    "sg:address":"Heronsgate Centre, Whinchat Road",
    "sg:city":"London",
    "sg:classifiers":[
        {
            "category":"Community Center",
            "subcategory":"Youth",
            "type":"Public Place"
        }
    ],
    "sg:phone":"+44 20 8317 1724",
    "sg:postcode":"SE28 0DW",
    "sg:province":"Greater London",
    "sg:tags":[
        "organisation",
        "centre"
    ],
    "wof:name":"Greenwich Youth Aid",
    "wof:placetype":"venue"
},
  "geometry": {"coordinates":[0.0836,51.494991],"type":"Point"}
}