{
  "type": "Feature",
  "properties": {
    "addr:full":"55 Derby Street Colne Lancashire BB8 9AF",
    "addr:housenumber":"55",
    "addr:postcode":"bb8 9af",
    "addr:street":"Derby Street",
    "iso:country":"GB",
    "sg:address":"55 Derby Street",
    "sg:city":"Colne",
    "sg:classifiers":[
        {
            "category":"Food & Beverages",
            "subcategory":"Liquor & Beverages",
            "type":"Retail Goods"
        }
    ],
    "sg:phone":"+44 1282 863227",
    "sg:postcode":"BB8 9AF",
    "sg:province":"Lancashire",
    "sg:tags":[
        "beer",
        "wine",
        "spirit",
        "wines"
    ],
    "wof:name":"M & R Quinn",
    "wof:placetype":"venue"
},
  "geometry": {"coordinates":[-2.1740329266,53.8576927185],"type":"Point"}
}