{
  "type": "Feature",
  "properties": {
    "addr:full":"4 Millbank, Westminster London Greater London SW1P 3GP",
    "addr:housenumber":"4",
    "addr:postcode":"sw1p 3gp",
    "addr:street":"Millbank",
    "iso:country":"GB",
    "sg:address":"4 Millbank, Westminster",
    "sg:city":"London",
    "sg:classifiers":[
        {
            "category":"Organizations",
            "subcategory":"Community Association",
            "type":"Services"
        }
    ],
    "sg:postcode":"SW1P 3GP",
    "sg:province":"Greater London",
    "sg:tags":[
        "relation",
        "public"
    ],
    "wof:name":"Government Policy Consultants",
    "wof:placetype":"venue"
},
  "geometry": {"coordinates":[-0.1257160008,51.496509552],"type":"Point"}
}