{
  "type": "Feature",
  "properties": {
    "addr:full":"Lindisfarne Road, Eye Peterborough Cambridgeshire PE6 7XH",
    "addr:postcode":"pe6 7xh",
    "addr:street":"Lindisfarne Road",
    "iso:country":"GB",
    "sg:address":"Lindisfarne Road, Eye",
    "sg:city":"Peterborough",
    "sg:classifiers":[
        {
            "category":"Arena",
            "subcategory":"Sports Club",
            "type":"Entertainment"
        }
    ],
    "sg:phone":"+44 1733 222094",
    "sg:postcode":"PE6 7XH",
    "sg:province":"Cambridgeshire",
    "wof:name":"Eye United Football Club",
    "wof:placetype":"venue"
},
  "geometry": {"coordinates":[-0.189844,52.605869],"type":"Point"}
}