{
  "type": "Feature",
  "properties": {
    "addr:full":"The Coach House, The Green Broadway Gloucestershire WR12 7AA",
    "addr:postcode":"wr12 7aa",
    "addr:street":"The Green Broadway",
    "iso:country":"GB",
    "sg:address":"The Coach House, The Green",
    "sg:city":"Broadway",
    "sg:classifiers":[
        {
            "category":"Restaurant",
            "type":"Food & Drink"
        }
    ],
    "sg:phone":"+44 1386 858137",
    "sg:postcode":"WR12 7AA",
    "sg:province":"Gloucestershire",
    "sg:tags":[
        "indian"
    ],
    "wof:name":"Sheikh",
    "wof:placetype":"venue"
},
  "geometry": {"coordinates":[-1.863114,52.036781],"type":"Point"}
}