{
  "type": "Feature",
  "properties": {
    "addr:full":"14 St Cross Street London Greater London EC1N 8UN",
    "addr:housenumber":"14",
    "addr:postcode":"ec1n 8un",
    "addr:street":"St Cross Street",
    "iso:country":"GB",
    "sg:address":"14 St Cross Street",
    "sg:city":"London",
    "sg:classifiers":[
        {
            "category":"Shopping",
            "subcategory":"Comic Books",
            "type":"Retail Goods"
        }
    ],
    "sg:phone":"+44 20 7242 8086",
    "sg:postcode":"EC1N 8UN",
    "sg:province":"Greater London",
    "sg:tags":[
        "jeweller"
    ],
    "wof:name":"Lambert Zacks",
    "wof:placetype":"venue"
},
  "geometry": {"coordinates":[-0.107769,51.520866],"type":"Point"}
}