{
  "type": "Feature",
  "properties": {
    "iso:country":"GB",
    "sg:address":"Tresmeer",
    "sg:city":"Launceston",
    "sg:classifiers":[
        {
            "category":"Community Center",
            "type":"Public Place"
        }
    ],
    "sg:phone":"+44 1566 781506",
    "sg:postcode":"PL15 8QX",
    "sg:province":"Cornwall",
    "sg:tags":[
        "nursery",
        "centre"
    ],
    "wof:name":"Camro Nurseries",
    "wof:placetype":"venue"
},
  "geometry": {"coordinates":[-4.446217,50.653408],"type":"Point"}
}