{
  "type": "Feature",
  "properties": {
    "iso:country":"GB",
    "sg:address":"524 Hagley Rd West, Quinton",
    "sg:city":"Birmingham",
    "sg:classifiers":[
        {
            "category":"Home & Garden",
            "subcategory":"Home Furnishings",
            "type":"Retail Goods"
        }
    ],
    "sg:postcode":"B68 0BZ",
    "sg:province":"West Midlands",
    "sg:tags":[
        "soft"
    ],
    "wof:name":"Waterside Manufacturing Ltd",
    "wof:placetype":"venue"
},
  "geometry": {"coordinates":[-1.99839,52.463322],"type":"Point"}
}