{
  "type": "Feature",
  "properties": {
    "addr:full":"Leaside, Aycliffe Industrial Estate Newton Aycliffe Durham DL5 6DE",
    "addr:postcode":"dl5 6de",
    "addr:street":"Industrial Estate;Aycliffe",
    "iso:country":"GB",
    "sg:address":"Leaside, Aycliffe Industrial Estate",
    "sg:city":"Newton Aycliffe",
    "sg:classifiers":[
        {
            "category":"Autos & Motor Vehicles",
            "subcategory":"Auto Supplies",
            "type":"Retail Goods"
        }
    ],
    "sg:phone":"+44 1325 321622",
    "sg:postcode":"DL5 6DE",
    "sg:province":"Durham",
    "sg:tags":[
        "tyre"
    ],
    "wof:name":"Ats",
    "wof:placetype":"venue"
},
  "geometry": {"coordinates":[-1.563024044,54.5962715149],"type":"Point"}
}