{
  "type": "Feature",
  "properties": {
    "addr:full":"Longhouse Lodge, Ermyn Way Leatherhead Surrey KT22 8TN",
    "addr:postcode":"kt22 8tn",
    "addr:street":"Ermyn Way",
    "iso:country":"GB",
    "sg:address":"Longhouse Lodge, Ermyn Way",
    "sg:city":"Leatherhead",
    "sg:classifiers":[
        {
            "category":"Health Services",
            "subcategory":"Health Practitioner",
            "type":"Services"
        }
    ],
    "sg:phone":"+44 1372 274920",
    "sg:postcode":"KT22 8TN",
    "sg:province":"Surrey",
    "sg:tags":[
        "hypnotherapists"
    ],
    "wof:name":"Veraschonberg",
    "wof:placetype":"venue"
},
  "geometry": {"coordinates":[-0.329419,51.29636],"type":"Point"}
}