{
  "type": "Feature",
  "properties": {
    "iso:country":"GB",
    "sg:address":"1st Floor 16 Grosvenor Av",
    "sg:city":"Newquay",
    "sg:classifiers":[
        {
            "category":"Professional",
            "subcategory":"Accounting & Tax Preparation",
            "type":"Services"
        }
    ],
    "sg:phone":"+44 1637 850590",
    "sg:postcode":"TR7 1BQ",
    "sg:province":"Cornwall",
    "sg:tags":[
        "accountant"
    ],
    "wof:name":"Hunt & Co",
    "wof:placetype":"venue"
},
  "geometry": {"coordinates":[-5.0800728798,50.4138183594],"type":"Point"}
}