{
  "type": "Feature",
  "properties": {
    "iso:country":"GB",
    "sg:address":"Church Farm, Main St, Huggate",
    "sg:city":"York",
    "sg:classifiers":[
        {
            "category":"Farming",
            "subcategory":"Livestock Farm",
            "type":"Manufacturing & Wholesale Goods"
        }
    ],
    "sg:phone":"+44 1377 288228",
    "sg:postcode":"YO42 1YF",
    "sg:province":"East Riding of Yorkshire",
    "sg:tags":[
        "others"
    ],
    "wof:name":"E Suddaby",
    "wof:placetype":"venue"
},
  "geometry": {"coordinates":[-0.659121,53.984268],"type":"Point"}
}