{
  "type": "Feature",
  "properties": {
    "iso:country":"GB",
    "sg:address":"89 Market Street",
    "sg:city":"Stalybridge",
    "sg:classifiers":[
        {
            "category":"Education",
            "subcategory":"Library",
            "type":"Public Place"
        }
    ],
    "sg:phone":"+44 161 338 3835",
    "sg:postcode":"SK15 2AA",
    "sg:province":"Greater Manchester",
    "sg:tags":[
        "reproduction",
        "furniture"
    ],
    "wof:name":"Stalybridge Reproduction",
    "wof:placetype":"venue"
},
  "geometry": {"coordinates":[-2.057235,53.483784],"type":"Point"}
}