{
  "type": "Feature",
  "properties": {
    "addr:full":"Lode Road, Bottisham Cambridge Cambridgeshire CB5 9DL",
    "addr:postcode":"cb5 9dl",
    "addr:street":"Lode Road",
    "iso:country":"GB",
    "sg:address":"Lode Road, Bottisham",
    "sg:city":"Cambridge",
    "sg:classifiers":[
        {
            "category":"Education",
            "subcategory":"Library",
            "type":"Public Place"
        },
        {
            "category":"Government",
            "subcategory":"Office",
            "type":"Public Place"
        }
    ],
    "sg:phone":"+44 1223 811372",
    "sg:postcode":"CB5 9DL",
    "sg:province":"Cambridgeshire",
    "sg:tags":[
        "agency",
        "book",
        "authority"
    ],
    "wof:name":"Bottisham Village College Community Education",
    "wof:placetype":"venue"
},
  "geometry": {"coordinates":[0.2586950064,52.222858429],"type":"Point"}
}