{
  "type": "Feature",
  "properties": {
    "iso:country":"GB",
    "sg:address":"Sedgefield Community Hospital, Sedgefield",
    "sg:city":"Stockton-on-tees",
    "sg:classifiers":[
        {
            "category":"Health Services",
            "subcategory":"Hospital",
            "type":"Services"
        }
    ],
    "sg:phone":"+44 1740 626600",
    "sg:postcode":"TS21 3EH",
    "sg:province":"Durham",
    "wof:name":"County Durham & Darlington Priority Services N H S Trust",
    "wof:placetype":"venue"
},
  "geometry": {"coordinates":[-1.4500739574,54.6536064148],"type":"Point"}
}