{
  "type": "Feature",
  "properties": {
    "iso:country":"GB",
    "sg:address":"Tourist Information Centre, Fort Augustus Car Park",
    "sg:city":"Fort Augustus",
    "sg:classifiers":[
        {
            "category":"Landmark",
            "subcategory":"Tourist Information",
            "type":"Public Place"
        }
    ],
    "sg:phone":"+44 1320 366367",
    "sg:postcode":"PH32 4DD",
    "sg:province":"Highland",
    "wof:name":"The Highlands of Scotland Tourist Board",
    "wof:placetype":"venue"
},
  "geometry": {"coordinates":[-4.680657,57.145103],"type":"Point"}
}