{
  "type": "Feature",
  "properties": {
    "addr:full":"10 West Harbour Rd Edinburgh City of Edinburgh EH5 1PH",
    "addr:housenumber":"10",
    "addr:postcode":"eh5 1ph",
    "addr:street":"West Harbour Rd",
    "iso:country":"GB",
    "sg:address":"10 West Harbour Rd",
    "sg:city":"Edinburgh",
    "sg:classifiers":[
        {
            "category":"Shopping",
            "subcategory":"Computers & Home Electronics",
            "type":"Retail Goods"
        }
    ],
    "sg:phone":"+44 131 552 7255",
    "sg:postcode":"EH5 1PH",
    "sg:province":"City of Edinburgh",
    "sg:tags":[
        "electrical"
    ],
    "wof:name":"Maclean's Electrical",
    "wof:placetype":"venue"
},
  "geometry": {"coordinates":[-3.2311439514,55.9780731201],"type":"Point"}
}