{
  "type": "Feature",
  "properties": {
    "iso:country":"GB",
    "sg:address":"15 The Close, New Longton",
    "sg:city":"Preston",
    "sg:classifiers":[
        {
            "category":"Building & Trades",
            "subcategory":"Construction",
            "type":"Services"
        }
    ],
    "sg:postcode":"PR4 4YP",
    "sg:province":"Lancashire",
    "sg:tags":[
        "dry",
        "lining",
        "plasterers",
        "screeders"
    ],
    "wof:name":"Artex Design",
    "wof:placetype":"venue"
},
  "geometry": {"coordinates":[-2.742553,53.721821],"type":"Point"}
}