{
  "type": "Feature",
  "properties": {
    "iso:country":"GB",
    "sg:address":"2 Bryans Close Rd",
    "sg:city":"Calne",
    "sg:classifiers":[
        {
            "category":"Shopping",
            "subcategory":"Computers & Home Electronics",
            "type":"Retail Goods"
        }
    ],
    "sg:phone":"+44 1249 813424",
    "sg:postcode":"SN11 9AA",
    "sg:province":"Wiltshire",
    "sg:tags":[
        "aerial",
        "television",
        "radio"
    ],
    "wof:name":"M Gainey",
    "wof:placetype":"venue"
},
  "geometry": {"coordinates":[-2.005186,51.441311],"type":"Point"}
}