{
  "type": "Feature",
  "properties": {
    "addr:full":"38 Mayton Street London Greater London N7 6QR",
    "addr:housenumber":"38",
    "addr:postcode":"n7 6qr",
    "addr:street":"Mayton Street",
    "iso:country":"GB",
    "sg:address":"38 Mayton Street",
    "sg:city":"London",
    "sg:classifiers":[
        {
            "category":"Farming",
            "subcategory":"Nursery",
            "type":"Manufacturing & Wholesale Goods"
        }
    ],
    "sg:phone":"+44 20 7607 6860",
    "sg:postcode":"N7 6QR",
    "sg:province":"Greater London",
    "sg:tags":[
        "creche"
    ],
    "wof:name":"Holloway Neighbourhood Group Nursery (The)",
    "wof:placetype":"venue"
},
  "geometry": {"coordinates":[-0.116217,51.559078],"type":"Point"}
}