{
  "type": "Feature",
  "properties": {
    "addr:full":"346 Harrow Road London Greater London W9 2HP",
    "addr:housenumber":"346",
    "addr:postcode":"w9 2hp",
    "addr:street":"Harrow Road",
    "iso:country":"GB",
    "sg:address":"346 Harrow Road",
    "sg:city":"London",
    "sg:classifiers":[
        {
            "category":"Organizations",
            "subcategory":"Membership Organization",
            "type":"Services"
        }
    ],
    "sg:postcode":"W9 2HP",
    "sg:province":"Greater London",
    "sg:tags":[
        "club"
    ],
    "wof:name":"Careful Management Ltd",
    "wof:placetype":"venue"
},
  "geometry": {"coordinates":[-0.194609,51.522949],"type":"Point"}
}