{
  "type": "Feature",
  "properties": {
    "addr:full":"25 Pembroke Gardens London Greater London W8 6HU",
    "addr:housenumber":"25",
    "addr:postcode":"w8 6hu",
    "addr:street":"Pembroke Gardens",
    "iso:country":"GB",
    "sg:address":"25 Pembroke Gardens",
    "sg:city":"London",
    "sg:classifiers":[
        {
            "category":"Banks & Credit Unions",
            "subcategory":"Financial Services",
            "type":"Services"
        }
    ],
    "sg:postcode":"W8 6HU",
    "sg:province":"Greater London",
    "sg:tags":[
        "consultant"
    ],
    "wof:name":"Trident Partners Ltd.",
    "wof:placetype":"venue"
},
  "geometry": {"coordinates":[-0.201324,51.495934],"type":"Point"}
}