{
  "type": "Feature",
  "properties": {
    "addr:full":"54 New North Road Exeter Devon EX4 4EP",
    "addr:housenumber":"54",
    "addr:postcode":"ex4 4ep",
    "addr:street":"New North Road",
    "iso:country":"GB",
    "sg:address":"54 New North Road",
    "sg:city":"Exeter",
    "sg:classifiers":[
        {
            "category":"Real Estate",
            "subcategory":"Real Estate Agent",
            "type":"Services"
        }
    ],
    "sg:phone":"+44 1392 499699",
    "sg:postcode":"EX4 4EP",
    "sg:province":"Devon",
    "wof:name":"Hugh McKenzie Village & Country Property",
    "wof:placetype":"venue"
},
  "geometry": {"coordinates":[-3.527476,50.72617],"type":"Point"}
}