{
  "type": "Feature",
  "properties": {
    "addr:full":"119 Days Lane Sidcup Kent DA15 8JT",
    "addr:housenumber":"119",
    "addr:postcode":"da15 8jt",
    "addr:street":"Days Lane",
    "iso:country":"GB",
    "sg:address":"119 Days Lane",
    "sg:city":"Sidcup",
    "sg:classifiers":[
        {
            "category":"Building & Trades",
            "subcategory":"Construction",
            "type":"Services"
        }
    ],
    "sg:phone":"+44 20 8302 8336",
    "sg:postcode":"DA15 8JT",
    "sg:province":"Kent",
    "sg:tags":[
        "builder"
    ],
    "wof:name":"Shannon Building Services",
    "wof:placetype":"venue"
},
  "geometry": {"coordinates":[0.0914589986,51.4447135925],"type":"Point"}
}