{
  "type": "Feature",
  "properties": {
    "iso:country":"GB",
    "sg:address":"Nancy Road, Grimethorpe",
    "sg:city":"Barnsley",
    "sg:classifiers":[
        {
            "category":"Education",
            "subcategory":"School",
            "type":"Public Place"
        }
    ],
    "sg:phone":"+44 1226 711488",
    "sg:postcode":"S72 7JX",
    "sg:province":"South Yorkshire",
    "sg:tags":[
        "local",
        "authority"
    ],
    "wof:name":"Ladywood Primary School",
    "wof:placetype":"venue"
},
  "geometry": {"coordinates":[-1.3805240393,53.5815658569],"type":"Point"}
}