{
  "type": "Feature",
  "properties": {
    "addr:full":"Unit 1, Youngs Indstl Est, Paices Hill, Aldermaston Reading Berkshire RG7 4PW",
    "addr:housenumber":"unit 1",
    "addr:postcode":"rg7 4pw",
    "addr:street":"Youngs Indstl Est Paices Hill",
    "iso:country":"GB",
    "sg:address":"Unit 1, Youngs Indstl Est, Paices Hill, Aldermaston",
    "sg:city":"Reading",
    "sg:classifiers":[
        {
            "category":"Military Area",
            "subcategory":"Air Force Base",
            "type":"Public Place"
        }
    ],
    "sg:postcode":"RG7 4PW",
    "sg:province":"Berkshire",
    "sg:tags":[
        "plate",
        "number"
    ],
    "wof:name":"Modern Plates",
    "wof:placetype":"venue"
},
  "geometry": {"coordinates":[-1.1525789499,51.3829345703],"type":"Point"}
}