{
  "type": "Feature",
  "properties": {
    "addr:full":"37 High Street, Grimethorpe Barnsley South Yorkshire S72 7LR",
    "addr:housenumber":"37",
    "addr:postcode":"s72 7lr",
    "addr:street":"High Street;Yorkshire",
    "iso:country":"GB",
    "sg:address":"37 High Street, Grimethorpe",
    "sg:city":"Barnsley",
    "sg:classifiers":[
        {
            "category":"Military Area",
            "subcategory":"Air Force Base",
            "type":"Public Place"
        }
    ],
    "sg:phone":"+44 1226 714153",
    "sg:postcode":"S72 7LR",
    "sg:province":"South Yorkshire",
    "sg:tags":[
        "taxi",
        "hire",
        "private"
    ],
    "wof:name":"Banners Private Hire",
    "wof:placetype":"venue"
},
  "geometry": {"coordinates":[-1.380352,53.575268],"type":"Point"}
}