{
  "type": "Feature",
  "properties": {
    "iso:country":"GB",
    "sg:address":"51 Norwood Road, Effingham",
    "sg:city":"Leatherhead",
    "sg:classifiers":[
        {
            "category":"Professional",
            "subcategory":"Art Services",
            "type":"Services"
        },
        {
            "category":"Building & Trades",
            "subcategory":"Construction",
            "type":"Services"
        }
    ],
    "sg:phone":"+44 1372 459396",
    "sg:postcode":"KT24 5NU",
    "sg:province":"Surrey",
    "sg:tags":[
        "decorator",
        "painter"
    ],
    "wof:name":"Dade & Renny",
    "wof:placetype":"venue"
},
  "geometry": {"coordinates":[-0.3909209967,51.2664337158],"type":"Point"}
}