{
  "type": "Feature",
  "properties": {
    "addr:full":"Queen Elizabeth House Billericay Essex CM12 0DG",
    "addr:postcode":"cm12 0dg",
    "iso:country":"GB",
    "sg:address":"Queen Elizabeth House",
    "sg:city":"Billericay",
    "sg:classifiers":[
        {
            "category":"Wholesale",
            "subcategory":"Office Equipment",
            "type":"Manufacturing & Wholesale Goods"
        },
        {
            "category":"Shopping",
            "subcategory":"Stationery & Office Supplies",
            "type":"Retail Goods"
        }
    ],
    "sg:phone":"+44 1277 630300",
    "sg:postcode":"CM12 0DG",
    "sg:province":"Essex",
    "sg:tags":[
        "supplier",
        "furniture"
    ],
    "sg:website":"http://www.bridon.co.uk",
    "wof:name":"Bridon Office Systems Ltd.",
    "wof:placetype":"venue"
},
  "geometry": {"coordinates":[0.416855,51.624748],"type":"Point"}
}