{
  "type": "Feature",
  "properties": {
    "addr:full":"Howgill Lane Sedbergh Cumbria LA10 5DE",
    "addr:postcode":"la10 5de",
    "addr:street":"Howgill Lane",
    "iso:country":"GB",
    "sg:address":"Howgill Lane",
    "sg:city":"Sedbergh",
    "sg:classifiers":[
        {
            "category":"Manufacturing",
            "subcategory":"Pottery",
            "type":"Manufacturing & Wholesale Goods"
        }
    ],
    "sg:phone":"+44 15396 21586",
    "sg:postcode":"LA10 5DE",
    "sg:province":"Cumbria",
    "sg:tags":[
        "supplier"
    ],
    "wof:name":"G Ceramics Glynn",
    "wof:placetype":"venue"
},
  "geometry": {"coordinates":[-2.529641,54.323803],"type":"Point"}
}