{
  "type": "Feature",
  "properties": {
    "addr:full":"1 Rutherford Way Indust Est Crawley Surrey RH10 2LN",
    "addr:housenumber":"1",
    "addr:postcode":"rh10 2ln",
    "addr:street":"Rutherford Way",
    "iso:country":"GB",
    "sg:address":"1 Rutherford Way Indust Est",
    "sg:city":"Crawley",
    "sg:classifiers":[
        {
            "category":"Home & Garden",
            "subcategory":"Household Appliances",
            "type":"Retail Goods"
        }
    ],
    "sg:phone":"+44 1293 532734",
    "sg:postcode":"RH10 2LN",
    "sg:province":"Surrey",
    "sg:tags":[
        "refrigeration",
        "air conditioning"
    ],
    "wof:name":"Raven Refrigeration",
    "wof:placetype":"venue"
},
  "geometry": {"coordinates":[-0.166605,51.137211],"type":"Point"}
}