{
  "type": "Feature",
  "properties": {
    "addr:full":"4 Quay Street Haverfordwest Pembrokeshire SA61 1BG",
    "addr:housenumber":"4",
    "addr:postcode":"sa61 1bg",
    "addr:street":"Quay Street",
    "iso:country":"GB",
    "sg:address":"4 Quay Street",
    "sg:city":"Haverfordwest",
    "sg:classifiers":[
        {
            "category":"Professional",
            "subcategory":"Computer Services",
            "type":"Services"
        }
    ],
    "sg:postcode":"SA61 1BG",
    "sg:province":"Pembrokeshire",
    "sg:tags":[
        "system",
        "software"
    ],
    "wof:name":"Galaxy Computers",
    "wof:placetype":"venue"
},
  "geometry": {"coordinates":[-4.967822,51.801514],"type":"Point"}
}