{
  "type": "Feature",
  "properties": {
    "iso:country":"GB",
    "sg:address":"75 Green Lane",
    "sg:city":"Scarborough",
    "sg:classifiers":[
        {
            "category":"Building & Trades",
            "subcategory":"Landscaping Services",
            "type":"Services"
        }
    ],
    "sg:phone":"+44 1723 370971",
    "sg:postcode":"YO12 6HT",
    "sg:province":"North Yorkshire",
    "sg:tags":[
        "gardening"
    ],
    "wof:name":"Todds Gardening Contractors",
    "wof:placetype":"venue"
},
  "geometry": {"coordinates":[-0.4308289886,54.2932510376],"type":"Point"}
}