{
  "type": "Feature",
  "properties": {
    "addr:full":", Marshwood Bridport Dorset DT6 5QJ",
    "addr:postcode":"dt6 5qj",
    "iso:country":"GB",
    "sg:address":", Marshwood",
    "sg:city":"Bridport",
    "sg:classifiers":[
        {
            "category":"Bars & Pubs",
            "type":"Food & Drink"
        }
    ],
    "sg:phone":"+44 1297 678254",
    "sg:postcode":"DT6 5QJ",
    "sg:province":"Dorset",
    "sg:tags":[
        "pubs",
        "inn"
    ],
    "wof:name":"The Bottle Inn",
    "wof:placetype":"venue"
},
  "geometry": {"coordinates":[-2.8780488968,50.7931404114],"type":"Point"}
}