{
  "type": "Feature",
  "properties": {
    "addr:full":"2 Napier Place Thetford Norfolk IP24 3RL",
    "addr:housenumber":"2",
    "addr:postcode":"ip24 3rl",
    "addr:street":"Napier Place",
    "iso:country":"GB",
    "sg:address":"2 Napier Place",
    "sg:city":"Thetford",
    "sg:classifiers":[
        {
            "category":"Organizations",
            "subcategory":"Non-profit Organization",
            "type":"Services"
        }
    ],
    "sg:phone":"+44 1842 753029",
    "sg:postcode":"IP24 3RL",
    "sg:province":"Norfolk",
    "sg:tags":[
        "charitable",
        "organisation",
        "voluntary",
        "charity"
    ],
    "wof:name":"Kilverstone Mobility Assessment Centre Ltd",
    "wof:placetype":"venue"
},
  "geometry": {"coordinates":[0.731964,52.404678],"type":"Point"}
}