{
  "type": "Feature",
  "properties": {
    "addr:full":"2-3 Long Causeway Wakefield West Yorkshire WF1 3SE",
    "addr:housenumber":"2-3",
    "addr:postcode":"wf1 3se",
    "addr:street":"Long Causeway",
    "iso:country":"GB",
    "sg:address":"2-3 Long Causeway",
    "sg:city":"Wakefield",
    "sg:classifiers":[
        {
            "category":"Travel",
            "subcategory":"Hotels & Motels",
            "type":"Entertainment"
        }
    ],
    "sg:phone":"+44 1924 373312",
    "sg:postcode":"WF1 3SE",
    "sg:province":"West Yorkshire",
    "sg:tags":[
        "house",
        "guest"
    ],
    "wof:name":"Eastview Guest House",
    "wof:placetype":"venue"
},
  "geometry": {"coordinates":[-1.493526,53.690216],"type":"Point"}
}