{
  "type": "Feature",
  "properties": {
    "addr:full":"Rectory Lane, Fowlmere Royston Bedfordshire SG8 7TJ",
    "addr:postcode":"sg8 7tj",
    "addr:street":"Rectory Lane",
    "iso:country":"GB",
    "sg:address":"Rectory Lane, Fowlmere",
    "sg:city":"Royston",
    "sg:classifiers":[
        {
            "category":"Manufacturing",
            "subcategory":"Tools & Machinery",
            "type":"Manufacturing & Wholesale Goods"
        }
    ],
    "sg:phone":"+44 1763 208789",
    "sg:postcode":"SG8 7TJ",
    "sg:province":"Bedfordshire",
    "sg:tags":[
        "design",
        "maker"
    ],
    "wof:name":"Curtis Starr Ltd.",
    "wof:placetype":"venue"
},
  "geometry": {"coordinates":[-0.021984,52.04821],"type":"Point"}
}