{
  "type": "Feature",
  "properties": {
    "iso:country":"GB",
    "sg:address":"27 St Werburgh Street",
    "sg:city":"Chester",
    "sg:classifiers":[
        {
            "category":"Insurance",
            "subcategory":"Insurance Agent",
            "type":"Services"
        }
    ],
    "sg:postcode":"CH1 2DY",
    "sg:province":"Cheshire",
    "wof:name":"Swinton",
    "wof:placetype":"venue"
},
  "geometry": {"coordinates":[-2.890352,53.191273],"type":"Point"}
}