{
  "type": "Feature",
  "properties": {
    "addr:full":"The Croft, Whiteley Rd Wallingford Oxfordshire OX10 9RG",
    "addr:postcode":"ox10 9rg",
    "addr:street":"Whiteley Rd",
    "iso:country":"GB",
    "sg:address":"The Croft, Whiteley Rd",
    "sg:city":"Wallingford",
    "sg:classifiers":[
        {
            "category":"Food & Beverages",
            "subcategory":"Groceries & Convenience Stores",
            "type":"Retail Goods"
        }
    ],
    "sg:phone":"+44 1491 832891",
    "sg:postcode":"OX10 9RG",
    "sg:province":"Oxfordshire",
    "sg:tags":[
        "frozen",
        "ice"
    ],
    "wof:name":"Ice Productions",
    "wof:placetype":"venue"
},
  "geometry": {"coordinates":[-1.1256229877,51.6009101868],"type":"Point"}
}