{
  "type": "Feature",
  "properties": {
    "iso:country":"GB",
    "sg:address":"29 Britton St",
    "sg:city":"Clerkenwell",
    "sg:classifiers":[
        {
            "category":"Shopping",
            "subcategory":"Antiques",
            "type":"Retail Goods"
        }
    ],
    "sg:phone":"+44 20 7251 2110",
    "sg:postcode":"EC1M 5NQ",
    "sg:province":"Greater London",
    "wof:name":"Galbraith William Ltd",
    "wof:placetype":"venue"
},
  "geometry": {"coordinates":[-0.104,51.521389],"type":"Point"}
}