{
  "type": "Feature",
  "properties": {
    "iso:country":"GB",
    "sg:address":"158 Blackley New Road",
    "sg:city":"Manchester",
    "sg:classifiers":[
        {
            "category":"Autos & Motor Vehicles",
            "subcategory":"Auto Supplies",
            "type":"Retail Goods"
        }
    ],
    "sg:phone":"+44 161 740 3120",
    "sg:postcode":"M9 3EG",
    "sg:province":"Greater Manchester",
    "sg:tags":[
        "tyre"
    ],
    "wof:name":"National Tyres and Autocare",
    "wof:placetype":"venue"
},
  "geometry": {"coordinates":[-2.21412,53.522308],"type":"Point"}
}