{
  "type": "Feature",
  "properties": {
    "addr:full":"7 The Crescent Selby East Riding of Yorkshire YO8 4PD",
    "addr:housenumber":"7",
    "addr:postcode":"yo8 4pd",
    "addr:street":"The Crescent",
    "iso:country":"GB",
    "sg:address":"7 The Crescent",
    "sg:city":"Selby",
    "sg:classifiers":[
        {
            "category":"Personal",
            "subcategory":"Beauty Salon",
            "type":"Services"
        }
    ],
    "sg:phone":"+44 1757 703229",
    "sg:postcode":"YO8 4PD",
    "sg:province":"East Riding of Yorkshire",
    "sg:tags":[
        "unisex",
        "hairdresser"
    ],
    "wof:name":"Loraine's",
    "wof:placetype":"venue"
},
  "geometry": {"coordinates":[-1.067681,53.783508],"type":"Point"}
}