{
  "type": "Feature",
  "properties": {
    "addr:full":"134 Darwen Street Blackburn Lancashire BB2 2AQ",
    "addr:housenumber":"134",
    "addr:postcode":"bb2 2aq",
    "addr:street":"Darwen Street",
    "iso:country":"GB",
    "sg:address":"134 Darwen Street",
    "sg:city":"Blackburn",
    "sg:classifiers":[
        {
            "category":"Retail",
            "subcategory":"Funeral Services",
            "type":"Services"
        }
    ],
    "sg:phone":"+44 1254 265911",
    "sg:postcode":"BB2 2AQ",
    "sg:province":"Lancashire",
    "wof:name":"Scales Funeral Services",
    "wof:placetype":"venue"
},
  "geometry": {"coordinates":[-2.4825980663,53.7440223694],"type":"Point"}
}