{
  "type": "Feature",
  "properties": {
    "addr:full":"3 Oakham Court Preston Lancashire PR1 3XP",
    "addr:housenumber":"3",
    "addr:postcode":"pr1 3xp",
    "addr:street":"Oakham Court",
    "iso:country":"GB",
    "sg:address":"3 Oakham Court",
    "sg:city":"Preston",
    "sg:classifiers":[
        {
            "category":"Social Services",
            "type":"Services"
        },
        {
            "category":"Organizations",
            "subcategory":"Non-profit Organization",
            "type":"Services"
        }
    ],
    "sg:phone":"+44 1772 822700",
    "sg:postcode":"PR1 3XP",
    "sg:province":"Lancashire",
    "sg:tags":[
        "organisation",
        "disability",
        "voluntary",
        "charity"
    ],
    "sg:website":"http://www.pukar.org.uk",
    "wof:name":"Pukar Disability Resource Centre",
    "wof:placetype":"venue"
},
  "geometry": {"coordinates":[-2.693663,53.757454],"type":"Point"}
}