{
  "type": "Feature",
  "properties": {
    "iso:country":"GB",
    "sg:address":"21 Hall Grn",
    "sg:city":"Skelmersdale",
    "sg:classifiers":[
        {
            "category":"Food & Beverages",
            "subcategory":"Fruits & Vegetables",
            "type":"Retail Goods"
        }
    ],
    "sg:phone":"+44 1695 622369",
    "sg:postcode":"WN8 0PB",
    "sg:province":"Lancashire",
    "sg:tags":[
        "greengrocer"
    ],
    "wof:name":"J&m Edwards",
    "wof:placetype":"venue"
},
  "geometry": {"coordinates":[-2.7275919914,53.5418663025],"type":"Point"}
}