{
  "type": "Feature",
  "properties": {
    "addr:full":"Tirlas Coch, Pinfold Lane, Northop Hall Mold Denbighshire CH7 6HE",
    "addr:postcode":"ch7 6he",
    "addr:street":"Coch Pinfold Lane",
    "iso:country":"GB",
    "sg:address":"Tirlas Coch, Pinfold Lane, Northop Hall",
    "sg:city":"Mold",
    "sg:classifiers":[
        {
            "category":"Farming",
            "subcategory":"Livestock Farm",
            "type":"Manufacturing & Wholesale Goods"
        }
    ],
    "sg:postcode":"CH7 6HE",
    "sg:province":"Denbighshire",
    "sg:tags":[
        "others"
    ],
    "wof:name":"J K Lea & Sons",
    "wof:placetype":"venue"
},
  "geometry": {"coordinates":[-3.097408,53.202393],"type":"Point"}
}