{
  "type": "Feature",
  "properties": {
    "addr:full":"Unit 3 Willen Works, Willen Rd Newport Pagnell Buckinghamshire MK16 0DG",
    "addr:housenumber":"unit 3",
    "addr:postcode":"works;mk16 0dg",
    "addr:street":"Willen Rd",
    "iso:country":"GB",
    "sg:address":"Unit 3 Willen Works, Willen Rd",
    "sg:city":"Newport Pagnell",
    "sg:classifiers":[
        {
            "category":"Autos & Motor Vehicles",
            "subcategory":"Automobile Sales",
            "type":"Retail Goods"
        }
    ],
    "sg:phone":"+44 1908 210352",
    "sg:postcode":"MK16 0DG",
    "sg:province":"Buckinghamshire",
    "sg:tags":[
        "commercial"
    ],
    "wof:name":"M And D Sports Cars",
    "wof:placetype":"venue"
},
  "geometry": {"coordinates":[-0.7230190039,52.0866966248],"type":"Point"}
}