{
  "type": "Feature",
  "properties": {
    "iso:country":"GB",
    "sg:address":"68 Hawkhill Avenue",
    "sg:city":"Ayr",
    "sg:classifiers":[
        {
            "category":"Home & Garden",
            "subcategory":"Building Materials",
            "type":"Retail Goods"
        }
    ],
    "sg:phone":"+44 1292 289942",
    "sg:postcode":"KA8 9JT",
    "sg:province":"South Ayrshire",
    "sg:tags":[
        "insulation",
        "installers"
    ],
    "wof:name":"Patrick Mcardle",
    "wof:placetype":"venue"
},
  "geometry": {"coordinates":[-4.606269,55.477718],"type":"Point"}
}