{
  "type": "Feature",
  "properties": {
    "addr:full":"305 High St West Glossop Derbyshire SK13 8EP",
    "addr:housenumber":"305",
    "addr:postcode":"sk13 8ep",
    "addr:street":"High St West",
    "iso:country":"GB",
    "sg:address":"305 High St West",
    "sg:city":"Glossop",
    "sg:classifiers":[
        {
            "category":"Bars & Pubs",
            "type":"Food & Drink"
        }
    ],
    "sg:phone":"+44 1457 854147",
    "sg:postcode":"SK13 8EP",
    "sg:province":"Derbyshire",
    "sg:tags":[
        "pubs",
        "inn"
    ],
    "wof:name":"Grapes Inn",
    "wof:placetype":"venue"
},
  "geometry": {"coordinates":[-1.9631789923,53.4442062378],"type":"Point"}
}