{
  "type": "Feature",
  "properties": {
    "iso:country":"GB",
    "sg:address":"30 Howardsgate",
    "sg:city":"Welwyn Garden City",
    "sg:classifiers":[
        {
            "category":"Food & Beverages",
            "subcategory":"Liquor & Beverages",
            "type":"Retail Goods"
        }
    ],
    "sg:phone":"+44 1707 372774",
    "sg:postcode":"AL8 6BJ",
    "sg:province":"Hertfordshire",
    "sg:tags":[
        "beer",
        "spirit",
        "wines"
    ],
    "wof:name":"Wine Cellar",
    "wof:placetype":"venue"
},
  "geometry": {"coordinates":[-0.2057289928,51.8014297485],"type":"Point"}
}