{
  "type": "Feature",
  "properties": {
    "addr:full":"25 Willis Grove Bedworth Warwickshire CV12 9BS",
    "addr:housenumber":"25",
    "addr:postcode":"cv12 9bs",
    "addr:street":"Willis Grove",
    "iso:country":"GB",
    "sg:address":"25 Willis Grove",
    "sg:city":"Bedworth",
    "sg:classifiers":[
        {
            "category":"Real Estate",
            "subcategory":"Real Estate Agent",
            "type":"Services"
        }
    ],
    "sg:postcode":"CV12 9BS",
    "sg:province":"Warwickshire",
    "wof:name":"PEARSON PROPERTY MANAGEMENT LTD",
    "wof:placetype":"venue"
},
  "geometry": {"coordinates":[-1.468027,52.483719],"type":"Point"}
}