{
  "type": "Feature",
  "properties": {
    "addr:full":"19 Low Road, Hellesdon Norwich Norfolk NR6 5AE",
    "addr:housenumber":"19",
    "addr:postcode":"nr6 5ae",
    "addr:street":"Low Road",
    "iso:country":"GB",
    "sg:address":"19 Low Road, Hellesdon",
    "sg:city":"Norwich",
    "sg:classifiers":[
        {
            "category":"Building & Trades",
            "subcategory":"Construction",
            "type":"Services"
        }
    ],
    "sg:phone":"+44 1603 425162",
    "sg:postcode":"NR6 5AE",
    "sg:province":"Norfolk",
    "sg:tags":[
        "heating",
        "contractor"
    ],
    "wof:name":"Goldie & Townsend",
    "wof:placetype":"venue"
},
  "geometry": {"coordinates":[1.2507719994,52.6495666504],"type":"Point"}
}