{
  "type": "Feature",
  "properties": {
    "addr:full":"High Street Boston Lincolnshire PE21 8SW",
    "addr:postcode":"pe21 8sw",
    "addr:street":"High Street",
    "iso:country":"GB",
    "sg:address":"High Street",
    "sg:city":"Boston",
    "sg:classifiers":[
        {
            "category":"Professional",
            "subcategory":"Detective & Security Services",
            "type":"Services"
        }
    ],
    "sg:phone":"+44 1205 362166",
    "sg:postcode":"PE21 8SW",
    "sg:province":"Lincolnshire",
    "sg:tags":[
        "locksmith"
    ],
    "wof:name":"W Armes & Co. (Boston) Ltd.",
    "wof:placetype":"venue"
},
  "geometry": {"coordinates":[-0.0246089995,52.9769439697],"type":"Point"}
}