{
  "type": "Feature",
  "properties": {
    "addr:full":"79 Wyke Road, Ilpeton Marsh Trowbridge Wiltshire BA14 7NZ",
    "addr:housenumber":"79",
    "addr:postcode":"ba14 7nz",
    "addr:street":"Wyke Road Ilpeton Marsh Trowbridge",
    "iso:country":"GB",
    "sg:address":"79 Wyke Road, Ilpeton Marsh",
    "sg:city":"Trowbridge",
    "sg:classifiers":[
        {
            "category":"Bars & Pubs",
            "type":"Food & Drink"
        }
    ],
    "sg:phone":"+44 1225 755168",
    "sg:postcode":"BA14 7NZ",
    "sg:province":"Wiltshire",
    "sg:tags":[
        "pubs",
        "inn"
    ],
    "wof:name":"The Kings Arms",
    "wof:placetype":"venue"
},
  "geometry": {"coordinates":[-2.2000420094,51.3403282166],"type":"Point"}
}