{
  "type": "Feature",
  "properties": {
    "addr:full":"45 Queen Street, City Centre Wolverhampton West Midlands WV1 3BJ",
    "addr:housenumber":"45",
    "addr:postcode":"wv1 3bj",
    "addr:street":"Queen Street",
    "iso:country":"GB",
    "sg:address":"45 Queen Street, City Centre",
    "sg:city":"Wolverhampton",
    "sg:classifiers":[
        {
            "category":"Real Estate",
            "subcategory":"Real Estate Agent",
            "type":"Services"
        }
    ],
    "sg:postcode":"WV1 3BJ",
    "sg:province":"West Midlands",
    "wof:name":"Property Finder Ltd.",
    "wof:placetype":"venue"
},
  "geometry": {"coordinates":[-2.1235470772,52.5856971741],"type":"Point"}
}