{
  "type": "Feature",
  "properties": {
    "iso:country":"GB",
    "sg:address":"29 Ashfield Road",
    "sg:city":"Cheadle",
    "sg:classifiers":[
        {
            "category":"Health Services",
            "subcategory":"Nursing And Care Facility",
            "type":"Services"
        },
        {
            "category":"Social Services",
            "subcategory":"Retirement Home",
            "type":"Services"
        }
    ],
    "sg:phone":"+44 161 428 5189",
    "sg:postcode":"SK8 1BB",
    "sg:province":"Cheshire",
    "sg:tags":[
        "residential"
    ],
    "wof:name":"Cheddle Lodge",
    "wof:placetype":"venue"
},
  "geometry": {"coordinates":[-2.213146925,53.3941116333],"type":"Point"}
}