{
  "type": "Feature",
  "properties": {
    "addr:full":"62 Watery Lane Redditch Warwickshire B98 7AN",
    "addr:housenumber":"62",
    "addr:postcode":"b98 7an",
    "addr:street":"Watery Lane",
    "iso:country":"GB",
    "sg:address":"62 Watery Lane",
    "sg:city":"Redditch",
    "sg:classifiers":[
        {
            "category":"Home & Garden",
            "subcategory":"Hardware",
            "type":"Retail Goods"
        }
    ],
    "sg:phone":"+44 1527 515656",
    "sg:postcode":"B98 7AN",
    "sg:province":"Warwickshire",
    "sg:tags":[
        "compressor",
        "air"
    ],
    "wof:name":"Air-vane Compressors",
    "wof:placetype":"venue"
},
  "geometry": {"coordinates":[-1.918415,52.297081],"type":"Point"}
}