{
  "type": "Feature",
  "properties": {
    "addr:full":"102 Boutport Street Barnstaple Devon EX31 1SY",
    "addr:housenumber":"102",
    "addr:postcode":"ex31 1sy",
    "addr:street":"Boutport Street",
    "iso:country":"GB",
    "sg:address":"102 Boutport Street",
    "sg:city":"Barnstaple",
    "sg:classifiers":[
        {
            "category":"Shopping",
            "subcategory":"Shoes",
            "type":"Retail Goods"
        },
        {
            "category":"Shopping",
            "subcategory":"Luggage & Leather Goods",
            "type":"Retail Goods"
        }
    ],
    "sg:postcode":"EX31 1SY",
    "sg:province":"Devon",
    "sg:tags":[
        "shop",
        "leathergoods"
    ],
    "wof:name":"Mark Yendell",
    "wof:placetype":"venue"
},
  "geometry": {"coordinates":[-4.058461,51.080662],"type":"Point"}
}