{
  "type": "Feature",
  "properties": {
    "iso:country":"GB",
    "sg:address":"118 Union Street",
    "sg:city":"Aberdeen",
    "sg:classifiers":[
        {
            "category":"Shopping",
            "subcategory":"Comic Books",
            "type":"Retail Goods"
        }
    ],
    "sg:phone":"+44 1224 646103",
    "sg:postcode":"AB10 1JJ",
    "sg:province":"Aberdeen City",
    "sg:tags":[
        "jeweller"
    ],
    "wof:name":"Beaverbrooks",
    "wof:placetype":"venue"
},
  "geometry": {"coordinates":[-2.100108,57.146347],"type":"Point"}
}