{
  "type": "Feature",
  "properties": {
    "iso:country":"GB",
    "sg:address":"26a High Street",
    "sg:city":"Royston",
    "sg:classifiers":[
        {
            "category":"Personal",
            "subcategory":"Barber",
            "type":"Services"
        }
    ],
    "sg:phone":"+44 1763 248796",
    "sg:postcode":"SG8 9AG",
    "sg:province":"Bedfordshire",
    "sg:tags":[
        "men's",
        "hairdresser"
    ],
    "wof:name":"The Edge",
    "wof:placetype":"venue"
},
  "geometry": {"coordinates":[-0.023504,52.047451],"type":"Point"}
}