{
  "type": "Feature",
  "properties": {
    "addr:full":"61 The Old Village, Huntington York North Yorkshire YO32 9RA",
    "addr:housenumber":"61",
    "addr:postcode":"yo32 9ra",
    "addr:street":"The Old Village",
    "iso:country":"GB",
    "sg:address":"61 The Old Village, Huntington",
    "sg:city":"York",
    "sg:classifiers":[
        {
            "category":"Building & Trades",
            "subcategory":"Construction",
            "type":"Services"
        }
    ],
    "sg:phone":"+44 1904 768624",
    "sg:postcode":"YO32 9RA",
    "sg:province":"North Yorkshire",
    "sg:tags":[
        "joiner",
        "carpenter"
    ],
    "wof:name":"B W Magson",
    "wof:placetype":"venue"
},
  "geometry": {"coordinates":[-1.059545,53.999203],"type":"Point"}
}