{
  "type": "Feature",
  "properties": {
    "iso:country":"GB",
    "sg:address":"Stonehaven, Waverton",
    "sg:city":"Wigton",
    "sg:classifiers":[
        {
            "category":"Professional",
            "subcategory":"Computer Services",
            "type":"Services"
        }
    ],
    "sg:phone":"+44 16973 49365",
    "sg:postcode":"CA7 0AW",
    "sg:province":"Cumbria",
    "sg:tags":[
        "aided",
        "design"
    ],
    "wof:name":"Lance Hetherington Ltd.",
    "wof:placetype":"venue"
},
  "geometry": {"coordinates":[-3.2053899765,54.8169937134],"type":"Point"}
}