{
  "type": "Feature",
  "properties": {
    "addr:full":"64 Griffiths Drive Wolverhampton Staffordshire WV11 2JW",
    "addr:housenumber":"64",
    "addr:postcode":"wv11 2jw",
    "addr:street":"Griffiths Drive",
    "iso:country":"GB",
    "sg:address":"64 Griffiths Drive",
    "sg:city":"Wolverhampton",
    "sg:classifiers":[
        {
            "category":"Shopping",
            "subcategory":"Discount & Variety Stores",
            "type":"Retail Goods"
        }
    ],
    "sg:phone":"+44 1902 721029",
    "sg:postcode":"WV11 2JW",
    "sg:province":"Staffordshire",
    "sg:tags":[
        "centre"
    ],
    "wof:name":"J A C Discount",
    "wof:placetype":"venue"
},
  "geometry": {"coordinates":[-2.061882019,52.613571167],"type":"Point"}
}