{
  "type": "Feature",
  "properties": {
    "iso:country":"GB",
    "sg:address":"23 Ashey Road",
    "sg:city":"Ryde",
    "sg:classifiers":[
        {
            "category":"Building & Trades",
            "subcategory":"Plumbing",
            "type":"Services"
        }
    ],
    "sg:phone":"+44 1983 565364",
    "sg:postcode":"PO33 2UW",
    "sg:province":"Isle of Wight",
    "sg:tags":[
        "plumber",
        "heating"
    ],
    "wof:name":"Kevin Thomas",
    "wof:placetype":"venue"
},
  "geometry": {"coordinates":[-1.167086,50.719902],"type":"Point"}
}