{
  "type": "Feature",
  "properties": {
    "addr:full":"Bell Lane, Hendon London Greater London NW4 2AE",
    "addr:postcode":"nw4 2ae",
    "addr:street":"Bell Lane",
    "iso:country":"GB",
    "sg:address":"Bell Lane, Hendon",
    "sg:city":"London",
    "sg:classifiers":[
        {
            "category":"Travel",
            "subcategory":"Hotels & Motels",
            "type":"Entertainment"
        }
    ],
    "sg:postcode":"NW4 2AE",
    "sg:province":"Greater London",
    "sg:tags":[
        "house",
        "guest"
    ],
    "wof:name":"Hendon Guest House",
    "wof:placetype":"venue"
},
  "geometry": {"coordinates":[-0.213859,51.587021],"type":"Point"}
}