{
  "type": "Feature",
  "properties": {
    "addr:full":"Albert Wks, 24 Thomas St West Stockport Cheshire SK1 3UB",
    "addr:housenumber":"24",
    "addr:postcode":"sk1 3ub",
    "addr:street":"Albert Wks;Thomas St West",
    "iso:country":"GB",
    "sg:address":"Albert Wks, 24 Thomas St West",
    "sg:city":"Stockport",
    "sg:classifiers":[
        {
            "category":"Shopping",
            "subcategory":"Discount & Variety Stores",
            "type":"Retail Goods"
        }
    ],
    "sg:phone":"+44 161 476 6200",
    "sg:postcode":"SK1 3UB",
    "sg:province":"Cheshire",
    "sg:tags":[
        "cleaning",
        "supply"
    ],
    "wof:name":"Hillshaw Ltd",
    "wof:placetype":"venue"
},
  "geometry": {"coordinates":[-2.15717,53.4016],"type":"Point"}
}