{
  "type": "Feature",
  "properties": {
    "iso:country":"GB",
    "sg:address":"1 Lewis Street, Eccles",
    "sg:city":"Manchester",
    "sg:classifiers":[
        {
            "category":"Retail",
            "subcategory":"Auto Repair",
            "type":"Services"
        }
    ],
    "sg:phone":"+44 161 789 5093",
    "sg:postcode":"M30 0PW",
    "sg:province":"Greater Manchester",
    "sg:tags":[
        "body",
        "car"
    ],
    "wof:name":"Eccles Motor House",
    "wof:placetype":"venue"
},
  "geometry": {"coordinates":[-2.3523700237,53.4799461365],"type":"Point"}
}