{
  "type": "Feature",
  "properties": {
    "addr:full":"13 Eagle Street Ipswich Suffolk IP4 1JA",
    "addr:housenumber":"13",
    "addr:postcode":"ip4 1ja",
    "addr:street":"Eagle Street",
    "iso:country":"GB",
    "sg:address":"13 Eagle Street",
    "sg:city":"Ipswich",
    "sg:classifiers":[
        {
            "category":"Sports & Exercise",
            "subcategory":"Sports Center",
            "type":"Entertainment"
        }
    ],
    "sg:phone":"+44 1473 217787",
    "sg:postcode":"IP4 1JA",
    "sg:province":"Suffolk",
    "sg:tags":[
        "shop",
        "good"
    ],
    "wof:name":"M A & M V Curtis",
    "wof:placetype":"venue"
},
  "geometry": {"coordinates":[1.160324,52.055485],"type":"Point"}
}