{
  "type": "Feature",
  "properties": {
    "addr:full":"130 Gloucester Avenue Chelmsford Essex CM2 9LG",
    "addr:housenumber":"130",
    "addr:postcode":"cm2 9lg",
    "addr:street":"Gloucester Avenue",
    "iso:country":"GB",
    "sg:address":"130 Gloucester Avenue",
    "sg:city":"Chelmsford",
    "sg:classifiers":[
        {
            "category":"Food & Beverages",
            "subcategory":"Meat & Fish",
            "type":"Retail Goods"
        }
    ],
    "sg:postcode":"CM2 9LG",
    "sg:province":"Essex",
    "sg:tags":[
        "butcher"
    ],
    "wof:name":"Lee's Butchers",
    "wof:placetype":"venue"
},
  "geometry": {"coordinates":[0.4732919931,51.716129303],"type":"Point"}
}