{
  "type": "Feature",
  "properties": {
    "addr:full":"11 Park Nook Halifax West Yorkshire HX3 9TT",
    "addr:housenumber":"11",
    "addr:postcode":"hx3 9tt",
    "addr:street":"Park Nook",
    "iso:country":"GB",
    "sg:address":"11 Park Nook",
    "sg:city":"Halifax",
    "sg:classifiers":[
        {
            "category":"Building & Trades",
            "subcategory":"Construction",
            "type":"Services"
        }
    ],
    "sg:phone":"+44 1422 368328",
    "sg:postcode":"HX3 9TT",
    "sg:province":"West Yorkshire",
    "sg:tags":[
        "joiner",
        "carpenter"
    ],
    "wof:name":"Ken Rice",
    "wof:placetype":"venue"
},
  "geometry": {"coordinates":[-1.8512500525,53.7001495361],"type":"Point"}
}