{
  "type": "Feature",
  "properties": {
    "iso:country":"GB",
    "sg:address":"Bridge End, Frosterley",
    "sg:city":"Bishop Auckland",
    "sg:classifiers":[
        {
            "category":"Education",
            "subcategory":"School",
            "type":"Public Place"
        },
        {
            "category":"Government",
            "subcategory":"Office",
            "type":"Public Place"
        }
    ],
    "sg:postcode":"DL13 2SN",
    "sg:province":"Durham",
    "sg:tags":[
        "local",
        "authority"
    ],
    "wof:name":"Frosterley Primary School",
    "wof:placetype":"venue"
},
  "geometry": {"coordinates":[-1.9549839497,54.7272644043],"type":"Point"}
}