{
  "type": "Feature",
  "properties": {
    "addr:full":"Letchford Ho, Headstones La Harrow Greater London HA3 6PE",
    "addr:postcode":"ha3 6pe",
    "addr:street":"La Harrow",
    "iso:country":"GB",
    "sg:address":"Letchford Ho, Headstones La",
    "sg:city":"Harrow",
    "sg:classifiers":[
        {
            "category":"Real Estate",
            "subcategory":"Real Estate Agent",
            "type":"Services"
        }
    ],
    "sg:postcode":"HA3 6PE",
    "sg:province":"Greater London",
    "wof:name":"Raymead Property Management Co Ltd",
    "wof:placetype":"venue"
},
  "geometry": {"coordinates":[-0.3402439952,51.6063499451],"type":"Point"}
}