{
  "type": "Feature",
  "properties": {
    "iso:country":"GB",
    "sg:address":"London Road, Hook",
    "sg:city":"Basingstoke",
    "sg:classifiers":[
        {
            "category":"Restaurant",
            "type":"Food & Drink"
        }
    ],
    "sg:phone":"+44 1252 842107",
    "sg:postcode":"RG27 8RT",
    "sg:province":"Berkshire",
    "wof:name":"Stilton Dish Restaurant",
    "wof:placetype":"venue"
},
  "geometry": {"coordinates":[-0.8895900249,51.3139610291],"type":"Point"}
}