{
  "type": "Feature",
  "properties": {
    "addr:full":"Timbold Drive, Kents Hill Park Milton Keynes Buckinghamshire MK7 6HL",
    "addr:postcode":"mk7 6hl",
    "addr:street":"Timbold Drive Kents Hill Park",
    "iso:country":"GB",
    "sg:address":"Timbold Drive, Kents Hill Park",
    "sg:city":"Milton Keynes",
    "sg:classifiers":[
        {
            "category":"Travel",
            "subcategory":"Hotels & Motels",
            "type":"Entertainment"
        }
    ],
    "sg:phone":"+44 1908 694433",
    "sg:postcode":"MK7 6HL",
    "sg:province":"Buckinghamshire",
    "wof:name":"Hilton National Milton Keynes",
    "wof:placetype":"venue"
},
  "geometry": {"coordinates":[-0.7041969895,52.0307579041],"type":"Point"}
}