{
  "type": "Feature",
  "properties": {
    "addr:full":"The Boatyard, Mill Road Fareham Hampshire PO16 0TA",
    "addr:postcode":"po16 0ta",
    "addr:street":"Mill Road",
    "iso:country":"GB",
    "sg:address":"The Boatyard, Mill Road",
    "sg:city":"Fareham",
    "sg:classifiers":[
        {
            "category":"Building & Trades",
            "subcategory":"Construction",
            "type":"Services"
        }
    ],
    "sg:phone":"+44 1329 289625",
    "sg:postcode":"PO16 0TA",
    "sg:province":"Hampshire",
    "sg:tags":[
        "welder"
    ],
    "wof:name":"Roberts Welding & Fabrication",
    "wof:placetype":"venue"
},
  "geometry": {"coordinates":[-1.174099,50.852734],"type":"Point"}
}