{
  "type": "Feature",
  "properties": {
    "addr:full":"56 Northesk Street Plymouth Devon PL2 1EZ",
    "addr:housenumber":"56",
    "addr:postcode":"pl2 1ez",
    "addr:street":"Northesk Street",
    "iso:country":"GB",
    "sg:address":"56 Northesk Street",
    "sg:city":"Plymouth",
    "sg:classifiers":[
        {
            "category":"Home & Garden",
            "subcategory":"Household Appliances",
            "type":"Retail Goods"
        }
    ],
    "sg:postcode":"PL2 1EZ",
    "sg:province":"Devon",
    "sg:tags":[
        "electrical"
    ],
    "wof:name":"Mobile Electrics",
    "wof:placetype":"venue"
},
  "geometry": {"coordinates":[-4.1659011841,50.3829536438],"type":"Point"}
}