{
  "type": "Feature",
  "properties": {
    "addr:full":"16 Old Town, Clapham London Greater London SW4 0JY",
    "addr:housenumber":"16",
    "addr:postcode":"sw4 0jy",
    "addr:street":"Old Town",
    "iso:country":"GB",
    "sg:address":"16 Old Town, Clapham",
    "sg:city":"London",
    "sg:classifiers":[
        {
            "category":"Real Estate",
            "subcategory":"Surveying",
            "type":"Services"
        }
    ],
    "sg:phone":"+44 20 7498 4344",
    "sg:postcode":"SW4 0JY",
    "sg:province":"Greater London",
    "sg:tags":[
        "surveyor",
        "valuer"
    ],
    "wof:name":"Lipinski Forster",
    "wof:placetype":"venue"
},
  "geometry": {"coordinates":[-0.1414660066,51.4646034241],"type":"Point"}
}