{
  "type": "Feature",
  "properties": {
    "iso:country":"GB",
    "sg:address":"3 Parsons St",
    "sg:city":"Dudley",
    "sg:classifiers":[
        {
            "category":"Shopping",
            "subcategory":"Clothing, Apparel, & Fashions",
            "type":"Retail Goods"
        }
    ],
    "sg:phone":"+44 1384 252345",
    "sg:postcode":"DY1 1JJ",
    "sg:province":"West Midlands",
    "sg:tags":[
        "menswear"
    ],
    "wof:name":"Pedley Retail Practices Ltd",
    "wof:placetype":"venue"
},
  "geometry": {"coordinates":[-2.086434,52.511257],"type":"Point"}
}