{
  "type": "Feature",
  "properties": {
    "iso:country":"GB",
    "sg:address":"180 West Regent Street",
    "sg:city":"Glasgow",
    "sg:classifiers":[
        {
            "category":"Professional",
            "subcategory":"Lawyer & Legal Services",
            "type":"Services"
        }
    ],
    "sg:phone":"+44 141 572 1910",
    "sg:postcode":"G2 4RW",
    "sg:province":"Glasgow City",
    "sg:tags":[
        "solicitor"
    ],
    "wof:name":"Grant & Co.",
    "wof:placetype":"venue"
},
  "geometry": {"coordinates":[-4.261743,55.863865],"type":"Point"}
}