{
  "type": "Feature",
  "properties": {
    "iso:country":"GB",
    "sg:address":"2a Ada Street",
    "sg:city":"London",
    "sg:classifiers":[
        {
            "category":"Professional",
            "subcategory":"Computer Services",
            "type":"Services"
        }
    ],
    "sg:phone":"+44 20 7923 2277",
    "sg:postcode":"E8 4QU",
    "sg:province":"Greater London",
    "sg:tags":[
        "system",
        "software"
    ],
    "wof:name":"Vital Office Products Ltd.",
    "wof:placetype":"venue"
},
  "geometry": {"coordinates":[-0.059968,51.535805],"type":"Point"}
}