{
  "type": "Feature",
  "properties": {
    "iso:country":"GB",
    "sg:address":"Ardtalla, New Street, Slamannan",
    "sg:city":"Falkirk",
    "sg:classifiers":[
        {
            "category":"Freight",
            "type":"Transportation"
        }
    ],
    "sg:phone":"+44 1324 851226",
    "sg:postcode":"FK1 3EP",
    "sg:province":"Falkirk",
    "sg:tags":[
        "haulage",
        "road"
    ],
    "wof:name":"Elizabeth Clark",
    "wof:placetype":"venue"
},
  "geometry": {"coordinates":[-3.8334269524,55.9373664856],"type":"Point"}
}