{
  "type": "Feature",
  "properties": {
    "addr:full":"136 Lochee Road Dundee Dundee City DD2 2LB",
    "addr:housenumber":"136",
    "addr:postcode":"dd2 2lb",
    "addr:street":"Lochee Road",
    "iso:country":"GB",
    "sg:address":"136 Lochee Road",
    "sg:city":"Dundee",
    "sg:classifiers":[
        {
            "category":"Shopping",
            "subcategory":"Department Store",
            "type":"Retail Goods"
        },
        {
            "category":"Food & Beverages",
            "subcategory":"Groceries & Convenience Stores",
            "type":"Retail Goods"
        }
    ],
    "sg:phone":"+44 1382 668857",
    "sg:postcode":"DD2 2LB",
    "sg:province":"Dundee City",
    "wof:name":"General Store & Newsagents",
    "wof:placetype":"venue"
},
  "geometry": {"coordinates":[-2.99307,56.46442],"type":"Point"}
}