{
  "type": "Feature",
  "properties": {
    "iso:country":"GB",
    "sg:address":"21 Moor Lane, Crosby",
    "sg:city":"Liverpool",
    "sg:classifiers":[
        {
            "category":"Restaurant",
            "type":"Food & Drink"
        }
    ],
    "sg:phone":"+44 151 924 3334",
    "sg:postcode":"L23 2SE",
    "sg:province":"Merseyside",
    "wof:name":"BLUES BISTRO",
    "wof:placetype":"venue"
},
  "geometry": {"coordinates":[-3.024478,53.493008],"type":"Point"}
}