{
  "type": "Feature",
  "properties": {
    "addr:full":"Green Smithy Lancaster Lancashire LA2 7DH",
    "addr:postcode":"la2 7dh",
    "iso:country":"GB",
    "sg:address":"Green Smithy",
    "sg:city":"Lancaster",
    "sg:classifiers":[
        {
            "category":"Professional",
            "subcategory":"Engineering",
            "type":"Services"
        }
    ],
    "sg:phone":"+44 15242 61353",
    "sg:postcode":"LA2 7DH",
    "sg:province":"Lancashire",
    "wof:name":"Robert Taylor & Sons",
    "wof:placetype":"venue"
},
  "geometry": {"coordinates":[-2.509269,54.11935],"type":"Point"}
}