{
  "type": "Feature",
  "properties": {
    "addr:full":"56 Causewayhead Penzance Cornwall TR18 2SS",
    "addr:housenumber":"56",
    "addr:postcode":"tr18 2ss",
    "addr:street":"Causewayhead",
    "iso:country":"GB",
    "sg:address":"56 Causewayhead",
    "sg:city":"Penzance",
    "sg:classifiers":[
        {
            "category":"Fast Food",
            "type":"Food & Drink"
        }
    ],
    "sg:postcode":"TR18 2SS",
    "sg:province":"Cornwall",
    "sg:tags":[
        "away",
        "take"
    ],
    "wof:name":"Joes Fish & Chip Shops",
    "wof:placetype":"venue"
},
  "geometry": {"coordinates":[-5.538446,50.119835],"type":"Point"}
}