{
  "type": "Feature",
  "properties": {
    "addr:full":"Battledown Service Station, Priors Road Cheltenham Gloucestershire GL52 5AQ",
    "addr:postcode":"gl52 5aq",
    "addr:street":"Priors Road",
    "iso:country":"GB",
    "sg:address":"Battledown Service Station, Priors Road",
    "sg:city":"Cheltenham",
    "sg:classifiers":[
        {
            "category":"Autos & Motor Vehicles",
            "subcategory":"Automobile Sales",
            "type":"Retail Goods"
        },
        {
            "category":"Retail",
            "subcategory":"Auto Repair",
            "type":"Services"
        }
    ],
    "sg:phone":"+44 1242 521761",
    "sg:postcode":"GL52 5AQ",
    "sg:province":"Gloucestershire",
    "sg:tags":[
        "modification",
        "garage",
        "car"
    ],
    "wof:name":"Battledown Service Station",
    "wof:placetype":"venue"
},
  "geometry": {"coordinates":[-2.04542,51.901039],"type":"Point"}
}