{
  "type": "Feature",
  "properties": {
    "iso:country":"GB",
    "sg:address":"87 Commercial Street, Norton",
    "sg:city":"Malton",
    "sg:classifiers":[
        {
            "category":"Bars & Pubs",
            "type":"Food & Drink"
        }
    ],
    "sg:phone":"+44 1653 693456",
    "sg:postcode":"YO17 9HY",
    "sg:province":"North Yorkshire",
    "sg:tags":[
        "pubs",
        "inn"
    ],
    "wof:name":"The Cornucopia",
    "wof:placetype":"venue"
},
  "geometry": {"coordinates":[-0.783645,54.132778],"type":"Point"}
}