{
  "type": "Feature",
  "properties": {
    "addr:full":"38 Potter Street Worksop Nottinghamshire S80 2AQ",
    "addr:housenumber":"38",
    "addr:postcode":"s80 2aq",
    "addr:street":"Potter Street",
    "iso:country":"GB",
    "sg:address":"38 Potter Street",
    "sg:city":"Worksop",
    "sg:classifiers":[
        {
            "category":"Professional",
            "subcategory":"Lawyer & Legal Services",
            "type":"Services"
        }
    ],
    "sg:phone":"+44 1909 480066",
    "sg:postcode":"S80 2AQ",
    "sg:province":"Nottinghamshire",
    "sg:tags":[
        "solicitor"
    ],
    "wof:name":"Jackson Quinn",
    "wof:placetype":"venue"
},
  "geometry": {"coordinates":[-1.1227849722,53.3019866943],"type":"Point"}
}