{
  "type": "Feature",
  "properties": {
    "addr:full":"4 Gorsey Lane Warrington Cheshire WA1 3PU",
    "addr:housenumber":"4",
    "addr:postcode":"wa1 3pu",
    "addr:street":"Gorsey Lane",
    "iso:country":"GB",
    "sg:address":"4 Gorsey Lane",
    "sg:city":"Warrington",
    "sg:classifiers":[
        {
            "category":"Communications",
            "type":"Services"
        }
    ],
    "sg:phone":"+44 1925 636664",
    "sg:postcode":"WA1 3PU",
    "sg:province":"Cheshire",
    "sg:tags":[
        "tv",
        "video",
        "radio"
    ],
    "wof:name":"N J Davenport",
    "wof:placetype":"venue"
},
  "geometry": {"coordinates":[-2.573816061,53.3977241516],"type":"Point"}
}