{
  "type": "Feature",
  "properties": {
    "addr:full":"48 Somersby Avenue Doncaster South Yorkshire DN5 8HB",
    "addr:housenumber":"48",
    "addr:postcode":"dn5 8hb",
    "addr:street":"Somersby Avenue",
    "iso:country":"GB",
    "sg:address":"48 Somersby Avenue",
    "sg:city":"Doncaster",
    "sg:classifiers":[
        {
            "category":"Building & Trades",
            "subcategory":"Plumbing",
            "type":"Services"
        }
    ],
    "sg:phone":"+44 1302 783937",
    "sg:postcode":"DN5 8HB",
    "sg:province":"South Yorkshire",
    "sg:tags":[
        "central",
        "installation",
        "system",
        "servicing",
        "heating"
    ],
    "wof:name":"Kevin Wagstaff",
    "wof:placetype":"venue"
},
  "geometry": {"coordinates":[-1.158965,53.527489],"type":"Point"}
}