{
  "type": "Feature",
  "properties": {
    "iso:country":"GB",
    "sg:address":"17 Temptin Avenue",
    "sg:city":"Canvey Island",
    "sg:classifiers":[
        {
            "category":"Freight",
            "type":"Transportation"
        }
    ],
    "sg:postcode":"SS8 8LE",
    "sg:province":"Essex",
    "sg:tags":[
        "haulage",
        "road"
    ],
    "wof:name":"T H Kelly & Sons",
    "wof:placetype":"venue"
},
  "geometry": {"coordinates":[0.609578,51.520832],"type":"Point"}
}