{
  "type": "Feature",
  "properties": {
    "iso:country":"GB",
    "sg:address":"Municipal Offices, Smith Street",
    "sg:city":"Rochdale",
    "sg:classifiers":[
        {
            "category":"Government",
            "subcategory":"Office",
            "type":"Public Place"
        }
    ],
    "sg:phone":"+44 1706 647474",
    "sg:postcode":"OL16 1XG",
    "sg:province":"Lancashire",
    "sg:tags":[
        "local"
    ],
    "wof:name":"Rochdale Metropolitan Borough Council",
    "wof:placetype":"venue"
},
  "geometry": {"coordinates":[-2.15739,53.61581],"type":"Point"}
}