{
  "type": "Feature",
  "properties": {
    "addr:full":"Unit 12 Heaton Mills, Heaton Street Manchester Greater Manchester M34 3RG",
    "addr:housenumber":"unit 12",
    "addr:postcode":"m34 3rg",
    "addr:street":"Heaton Street",
    "iso:country":"GB",
    "sg:address":"Unit 12 Heaton Mills, Heaton Street",
    "sg:city":"Manchester",
    "sg:classifiers":[
        {
            "category":"Wholesale",
            "subcategory":"Machinery & Supplies",
            "type":"Manufacturing & Wholesale Goods"
        },
        {
            "category":"Arts & Performance",
            "subcategory":"Theater",
            "type":"Entertainment"
        }
    ],
    "sg:phone":"+44 161 320 4345",
    "sg:postcode":"M34 3RG",
    "sg:province":"Greater Manchester",
    "sg:tags":[
        "constume",
        "theatrical",
        "supplier"
    ],
    "wof:name":"The Pantomime Shop",
    "wof:placetype":"venue"
},
  "geometry": {"coordinates":[-2.126661,53.456104],"type":"Point"}
}