{
  "type": "Feature",
  "properties": {
    "addr:full":"2-4 Cockspur Street, Trafalgar Square London Greater London SW1Y 5BQ",
    "addr:housenumber":"2-4",
    "addr:postcode":"sw1y 5bq",
    "addr:street":"Cockspur Street Trafalgar",
    "iso:country":"GB",
    "sg:address":"2-4 Cockspur Street, Trafalgar Square",
    "sg:city":"London",
    "sg:classifiers":[
        {
            "category":"Wholesale",
            "subcategory":"Scrap",
            "type":"Manufacturing & Wholesale Goods"
        }
    ],
    "sg:phone":"+44 20 7269 8400",
    "sg:postcode":"SW1Y 5BQ",
    "sg:province":"Greater London",
    "sg:tags":[
        "waste",
        "metal"
    ],
    "wof:name":"Johnson Matthey Plc",
    "wof:placetype":"venue"
},
  "geometry": {"coordinates":[-0.129291,51.507671],"type":"Point"}
}