{
  "type": "Feature",
  "properties": {
    "iso:country":"GB",
    "sg:address":"130 St Marys Road, Garston",
    "sg:city":"Liverpool",
    "sg:classifiers":[
        {
            "category":"Shopping",
            "subcategory":"Stationery & Office Supplies",
            "type":"Retail Goods"
        },
        {
            "category":"Professional",
            "subcategory":"Printing & Photocopies",
            "type":"Services"
        },
        {
            "category":"Home & Garden",
            "subcategory":"Furniture",
            "type":"Retail Goods"
        }
    ],
    "sg:phone":"+44 151 494 2525",
    "sg:postcode":"L19 2JG",
    "sg:province":"Merseyside",
    "sg:tags":[
        "equipment",
        "mailing",
        "outlet"
    ],
    "wof:name":"The Franking Machine Co. Supplies Ltd.",
    "wof:placetype":"venue"
},
  "geometry": {"coordinates":[-2.902431,53.355766],"type":"Point"}
}