{
  "type": "Feature",
  "properties": {
    "addr:full":"Dairy House Farm, Sutton Waldron Blandford Forum Dorset DT11 8NZ",
    "addr:housenumber":"waldron",
    "addr:postcode":"dt11 8nz",
    "iso:country":"GB",
    "sg:address":"Dairy House Farm, Sutton Waldron",
    "sg:city":"Blandford Forum",
    "sg:classifiers":[
        {
            "category":"Professional",
            "subcategory":"Accounting & Tax Preparation",
            "type":"Services"
        }
    ],
    "sg:postcode":"DT11 8NZ",
    "sg:province":"Dorset",
    "sg:tags":[
        "accountant"
    ],
    "wof:name":"D W Smith",
    "wof:placetype":"venue"
},
  "geometry": {"coordinates":[-2.194778,50.943165],"type":"Point"}
}