{
  "type": "Feature",
  "properties": {
    "addr:full":"7a Bolton Road, Farnworth Bolton Lancashire BL4 7JN",
    "addr:housenumber":"7a",
    "addr:postcode":"bl4 7jn",
    "addr:street":"Bolton Road",
    "iso:country":"GB",
    "sg:address":"7a Bolton Road, Farnworth",
    "sg:city":"Bolton",
    "sg:classifiers":[
        {
            "category":"Shopping",
            "subcategory":"News",
            "type":"Retail Goods"
        }
    ],
    "sg:postcode":"BL4 7JN",
    "sg:province":"Lancashire",
    "sg:tags":[
        "newsagent"
    ],
    "wof:name":"Moses Gate Newsagents",
    "wof:placetype":"venue"
},
  "geometry": {"coordinates":[-2.400383,53.555614],"type":"Point"}
}