{
  "type": "Feature",
  "properties": {
    "addr:full":"Langland House, Langland Road Milton Keynes Buckinghamshire MK6 4JT",
    "addr:postcode":"mk6 4jt",
    "addr:street":"Langland Road",
    "iso:country":"GB",
    "sg:address":"Langland House, Langland Road",
    "sg:city":"Milton Keynes",
    "sg:classifiers":[
        {
            "category":"Organizations",
            "subcategory":"Community Association",
            "type":"Services"
        }
    ],
    "sg:phone":"+44 1908 660774",
    "sg:postcode":"MK6 4JT",
    "sg:province":"Buckinghamshire",
    "sg:tags":[
        "society",
        "housing"
    ],
    "wof:name":"The Hanover Housing Association Charitable Trust",
    "wof:placetype":"venue"
},
  "geometry": {"coordinates":[-0.7264940143,52.0187797546],"type":"Point"}
}