{
  "type": "Feature",
  "properties": {
    "addr:full":"73 The Green, Rawcliffe Goole East Riding of Yorkshire DN14 8QF",
    "addr:housenumber":"73",
    "addr:postcode":"dn14 8qf",
    "addr:street":"The Green",
    "iso:country":"GB",
    "sg:address":"73 The Green, Rawcliffe",
    "sg:city":"Goole",
    "sg:classifiers":[
        {
            "category":"Food & Beverages",
            "subcategory":"Farmers Market",
            "type":"Retail Goods"
        }
    ],
    "sg:phone":"+44 1405 839233",
    "sg:postcode":"DN14 8QF",
    "sg:province":"East Riding of Yorkshire",
    "sg:tags":[
        "gardener"
    ],
    "wof:name":"S Holmes",
    "wof:placetype":"venue"
},
  "geometry": {"coordinates":[-0.965650022,53.6979103088],"type":"Point"}
}