{
  "type": "Feature",
  "properties": {
    "iso:country":"GB",
    "sg:address":"Unit 37, Abergorki Industrial Estate",
    "sg:city":"Treorchy",
    "sg:classifiers":[
        {
            "category":"Military Area",
            "subcategory":"Coast Guard Base",
            "type":"Public Place"
        },
        {
            "category":"Manufacturing",
            "subcategory":"Petroleum Products",
            "type":"Manufacturing & Wholesale Goods"
        }
    ],
    "sg:phone":"+44 1443 777333",
    "sg:postcode":"CF42 6DL",
    "sg:province":"Rhondda, Cynon, Taff",
    "sg:tags":[
        "double",
        "frame",
        "glazing",
        "window",
        "manufacturer"
    ],
    "wof:name":"Griffin Windows Ltd",
    "wof:placetype":"venue"
},
  "geometry": {"coordinates":[-3.505229,51.659664],"type":"Point"}
}