{
  "type": "Feature",
  "properties": {
    "iso:country":"GB",
    "sg:address":"Upper Wick Lane, Rushwick",
    "sg:city":"Worcester",
    "sg:classifiers":[
        {
            "category":"Social Services",
            "subcategory":"Retirement Home",
            "type":"Services"
        }
    ],
    "sg:phone":"+44 1905 425101",
    "sg:postcode":"WR2 5SU",
    "sg:province":"Worcestershire",
    "sg:tags":[
        "residential",
        "care"
    ],
    "wof:name":"Bedwardine House",
    "wof:placetype":"venue"
},
  "geometry": {"coordinates":[-2.2649,52.181557],"type":"Point"}
}