{
  "type": "Feature",
  "properties": {
    "addr:full":"133 Bannings Vale, Saltdean Brighton East Sussex BN2 8DH",
    "addr:housenumber":"133",
    "addr:postcode":"bn2 8dh",
    "addr:street":"Bannings Vale Saltdean",
    "iso:country":"GB",
    "sg:address":"133 Bannings Vale, Saltdean",
    "sg:city":"Brighton",
    "sg:classifiers":[
        {
            "category":"Building & Trades",
            "subcategory":"Construction",
            "type":"Services"
        }
    ],
    "sg:phone":"+44 1273 300839",
    "sg:postcode":"BN2 8DH",
    "sg:province":"East Sussex",
    "sg:tags":[
        "glazier",
        "decorator",
        "painter"
    ],
    "wof:name":"D Skinner",
    "wof:placetype":"venue"
},
  "geometry": {"coordinates":[-0.023365,50.804962],"type":"Point"}
}