{
  "type": "Feature",
  "properties": {
    "iso:country":"GB",
    "sg:address":"87 Chapel Street",
    "sg:city":"Salford",
    "sg:classifiers":[
        {
            "category":"Shopping",
            "subcategory":"Mobile Phones",
            "type":"Retail Goods"
        }
    ],
    "sg:phone":"+44 161 832 1333",
    "sg:postcode":"M3 5DF",
    "sg:province":"Greater Manchester",
    "sg:tags":[
        "supplier"
    ],
    "wof:name":"Livewire",
    "wof:placetype":"venue"
},
  "geometry": {"coordinates":[-2.250391,53.484615],"type":"Point"}
}