{
  "type": "Feature",
  "properties": {
    "iso:country":"GB",
    "sg:address":"Francis Cottage",
    "sg:city":"Penzance",
    "sg:classifiers":[
        {
            "category":"Freight",
            "type":"Transportation"
        }
    ],
    "sg:phone":"+44 1736 740025",
    "sg:postcode":"TR20 8BS",
    "sg:province":"Cornwall",
    "sg:tags":[
        "forwarders"
    ],
    "wof:name":"D L Johnson",
    "wof:placetype":"venue"
},
  "geometry": {"coordinates":[-5.537369,50.123566],"type":"Point"}
}