{
  "type": "Feature",
  "properties": {
    "iso:country":"GB",
    "sg:address":"12a Standish Gallery, The Galleries",
    "sg:city":"Wigan",
    "sg:classifiers":[
        {
            "category":"Retail",
            "subcategory":"Repair Shop",
            "type":"Services"
        }
    ],
    "sg:postcode":"WN1 1AT",
    "sg:province":"Lancashire",
    "sg:tags":[
        "clocks",
        "watch"
    ],
    "wof:name":"Time-Piece Watch Repairs",
    "wof:placetype":"venue"
},
  "geometry": {"coordinates":[-2.6337490082,53.5466918945],"type":"Point"}
}