{
  "type": "Feature",
  "properties": {
    "iso:country":"GB",
    "sg:address":"1261b Stratford Road, Hall Green",
    "sg:city":"Birmingham",
    "sg:classifiers":[
        {
            "category":"Professional",
            "subcategory":"Advertising",
            "type":"Services"
        }
    ],
    "sg:postcode":"B28 9AJ",
    "sg:province":"West Midlands",
    "sg:tags":[
        "directory"
    ],
    "wof:name":"Aaa Marketing Ltd",
    "wof:placetype":"venue"
},
  "geometry": {"coordinates":[-1.8448139429,52.4318161011],"type":"Point"}
}