{
  "type": "Feature",
  "properties": {
    "iso:country":"GB",
    "sg:address":"Unit 1 Rosehill Garage, Winchester Rd, Waltham Chase",
    "sg:city":"Southampton",
    "sg:classifiers":[
        {
            "category":"Sports & Exercise",
            "subcategory":"Tennis Court",
            "type":"Entertainment"
        }
    ],
    "sg:postcode":"SO32 2LX",
    "sg:province":"Hampshire",
    "sg:tags":[
        "breakdown",
        "recovery"
    ],
    "wof:name":"Wilson,David,",
    "wof:placetype":"venue"
},
  "geometry": {"coordinates":[-1.201114,50.932346],"type":"Point"}
}