{
  "type": "Feature",
  "properties": {
    "iso:country":"GB",
    "sg:address":"Heathfield Road",
    "sg:city":"Ayr",
    "sg:classifiers":[
        {
            "category":"Autos & Motor Vehicles",
            "subcategory":"Automobile Sales",
            "type":"Retail Goods"
        }
    ],
    "sg:phone":"+44 1292 282727",
    "sg:postcode":"KA8 9HE",
    "sg:province":"South Ayrshire",
    "sg:tags":[
        "car"
    ],
    "wof:name":"Glen Henderson Ltd.",
    "wof:placetype":"venue"
},
  "geometry": {"coordinates":[-4.615129,55.482609],"type":"Point"}
}