{
  "type": "Feature",
  "properties": {
    "iso:country":"GB",
    "sg:address":"Unit 17 Wng Estate, East Challow",
    "sg:city":"Wantage",
    "sg:classifiers":[
        {
            "category":"Professional",
            "subcategory":"Engineering",
            "type":"Services"
        }
    ],
    "sg:phone":"+44 1235 772161",
    "sg:postcode":"OX12 9TF",
    "sg:province":"Berkshire",
    "wof:name":"Peter Allen Rota Dispensers",
    "wof:placetype":"venue"
},
  "geometry": {"coordinates":[-1.463844,51.597034],"type":"Point"}
}