{
  "type": "Feature",
  "properties": {
    "addr:full":"11 Derwent Dr Preston Lancashire PR3 3FU",
    "addr:housenumber":"11",
    "addr:postcode":"pr3 3fu",
    "addr:street":"Derwent Dr",
    "iso:country":"GB",
    "sg:address":"11 Derwent Dr",
    "sg:city":"Preston",
    "sg:classifiers":[
        {
            "category":"Professional",
            "subcategory":"Engineering",
            "type":"Services"
        }
    ],
    "sg:phone":"+44 1772 785606",
    "sg:postcode":"PR3 3FU",
    "sg:province":"Lancashire",
    "sg:tags":[
        "contractor",
        "electrical",
        "engineer"
    ],
    "wof:name":"Gordon Cronshaw",
    "wof:placetype":"venue"
},
  "geometry": {"coordinates":[-2.61081,53.822102],"type":"Point"}
}