{
  "type": "Feature",
  "properties": {
    "addr:full":"Ward 10 Churchill Hospital, Headington Oxford Oxfordshire OX3 7LH",
    "addr:postcode":"ox3 7lh",
    "addr:street":"Churchill Hospital",
    "iso:country":"GB",
    "sg:address":"Ward 10 Churchill Hospital, Headington",
    "sg:city":"Oxford",
    "sg:classifiers":[
        {
            "category":"Organizations",
            "subcategory":"Non-profit Organization",
            "type":"Services"
        }
    ],
    "sg:phone":"+44 1865 225622",
    "sg:postcode":"OX3 7LH",
    "sg:province":"Oxfordshire",
    "sg:tags":[
        "organisation",
        "voluntary",
        "charity"
    ],
    "wof:name":"British Red Cross",
    "wof:placetype":"venue"
},
  "geometry": {"coordinates":[-1.2123299837,51.7512207031],"type":"Point"}
}