{
  "type": "Feature",
  "properties": {
    "iso:country":"GB",
    "sg:address":"368 Ashton Road",
    "sg:city":"Oldham",
    "sg:classifiers":[
        {
            "category":"Building & Trades",
            "subcategory":"Construction",
            "type":"Services"
        }
    ],
    "sg:phone":"+44 161 620 9699",
    "sg:postcode":"OL8 3HF",
    "sg:province":"Lancashire",
    "sg:tags":[
        "joinery"
    ],
    "wof:name":"Darcy Manufacturing Joiners",
    "wof:placetype":"venue"
},
  "geometry": {"coordinates":[-2.111303,53.525963],"type":"Point"}
}