{
  "type": "Feature",
  "properties": {
    "iso:country":"GB",
    "sg:address":"Hertford House, Hertford Place, Denham Way",
    "sg:city":"Rickmansworth",
    "sg:classifiers":[
        {
            "category":"Professional",
            "subcategory":"Advertising",
            "type":"Services"
        }
    ],
    "sg:postcode":"WD3 9XB",
    "sg:province":"Hertfordshire",
    "sg:tags":[
        "agency"
    ],
    "wof:name":"International Advertising Ltd.",
    "wof:placetype":"venue"
},
  "geometry": {"coordinates":[-0.468275,51.641438],"type":"Point"}
}