{
  "type": "Feature",
  "properties": {
    "addr:full":"Unit 4, 21 Waldo Road Bromley Kent BR1 2QX",
    "addr:housenumber":"unit;21",
    "addr:postcode":"br1 2qx",
    "addr:street":"Waldo Road",
    "iso:country":"GB",
    "sg:address":"Unit 4, 21 Waldo Road",
    "sg:city":"Bromley",
    "sg:classifiers":[
        {
            "category":"Professional",
            "subcategory":"Printing & Photocopies",
            "type":"Services"
        }
    ],
    "sg:phone":"+44 20 8290 0481",
    "sg:postcode":"BR1 2QX",
    "sg:province":"Kent",
    "sg:tags":[
        "printer"
    ],
    "wof:name":"Business Print Services",
    "wof:placetype":"venue"
},
  "geometry": {"coordinates":[0.033567,51.399101],"type":"Point"}
}