{
  "type": "Feature",
  "properties": {
    "addr:full":"Derwent St Middlesbrough North Yorkshire TS1 5QW",
    "addr:postcode":"ts1 5qw",
    "addr:street":"Derwent St",
    "iso:country":"GB",
    "sg:address":"Derwent St",
    "sg:city":"Middlesbrough",
    "sg:classifiers":[
        {
            "category":"Retail",
            "subcategory":"Auto Repair",
            "type":"Services"
        }
    ],
    "sg:phone":"+44 1642 222888",
    "sg:postcode":"TS1 5QW",
    "sg:province":"North Yorkshire",
    "sg:tags":[
        "modification",
        "garage"
    ],
    "wof:name":"D C Hedley Transmissions",
    "wof:placetype":"venue"
},
  "geometry": {"coordinates":[-1.250854,54.572205],"type":"Point"}
}