{
  "type": "Feature",
  "properties": {
    "addr:full":"199-201 High St Northallerton North Yorkshire DL7 8LP",
    "addr:housenumber":"199-201",
    "addr:postcode":"dl7 8lp",
    "addr:street":"High St",
    "iso:country":"GB",
    "sg:address":"199-201 High St",
    "sg:city":"Northallerton",
    "sg:classifiers":[
        {
            "category":"Shopping",
            "subcategory":"Clothing, Apparel, & Fashions",
            "type":"Retail Goods"
        }
    ],
    "sg:phone":"+44 1609 778365",
    "sg:postcode":"DL7 8LP",
    "sg:province":"North Yorkshire",
    "sg:tags":[
        "ladieswear"
    ],
    "wof:name":"Viyella",
    "wof:placetype":"venue"
},
  "geometry": {"coordinates":[-1.434499,54.339874],"type":"Point"}
}