{
  "type": "Feature",
  "properties": {
    "iso:country":"GB",
    "sg:address":"The Shay Stadium",
    "sg:city":"Halifax",
    "sg:classifiers":[
        {
            "category":"Arena",
            "subcategory":"Sports Club",
            "type":"Entertainment"
        }
    ],
    "sg:phone":"+44 1422 366544",
    "sg:postcode":"HX1 2YS",
    "sg:province":"West Yorkshire",
    "wof:name":"The Halifax Town Association Football Club Ltd.",
    "wof:placetype":"venue"
},
  "geometry": {"coordinates":[-1.862224,53.721233],"type":"Point"}
}