{
  "type": "Feature",
  "properties": {
    "iso:country":"GB",
    "sg:address":"Unit 6, Marsh Farm, Nuneaton Rd, Bulkington",
    "sg:city":"Nuneaton",
    "sg:classifiers":[
        {
            "category":"Sports & Exercise",
            "subcategory":"Tennis Court",
            "type":"Entertainment"
        }
    ],
    "sg:postcode":"CV12 9RR",
    "sg:province":"Warwickshire",
    "sg:tags":[
        "breakdown",
        "recovery"
    ],
    "wof:name":"Terry,David,",
    "wof:placetype":"venue"
},
  "geometry": {"coordinates":[-1.422995,52.47628],"type":"Point"}
}