{
  "type": "Feature",
  "properties": {
    "addr:full":"14a West Pier Scarborough North Yorkshire YO11 1PD",
    "addr:housenumber":"14a",
    "addr:postcode":"yo11 1pd",
    "addr:street":"West Pier",
    "iso:country":"GB",
    "sg:address":"14a West Pier",
    "sg:city":"Scarborough",
    "sg:classifiers":[
        {
            "category":"Professional",
            "type":"Services"
        },
        {
            "category":"Building & Trades",
            "subcategory":"Electrical",
            "type":"Services"
        }
    ],
    "sg:phone":"+44 1723 368083",
    "sg:postcode":"YO11 1PD",
    "sg:province":"North Yorkshire",
    "sg:tags":[
        "marine"
    ],
    "wof:name":"A H Parcell & Son",
    "wof:placetype":"venue"
},
  "geometry": {"coordinates":[-0.4069049954,54.280254364],"type":"Point"}
}