{
  "type": "Feature",
  "properties": {
    "iso:country":"GB",
    "sg:address":"3-4 Pond Close, Walkern Road",
    "sg:city":"Stevenage",
    "sg:classifiers":[
        {
            "category":"Professional",
            "subcategory":"Art Services",
            "type":"Services"
        }
    ],
    "sg:phone":"+44 1438 353500",
    "sg:postcode":"SG1 3QP",
    "sg:province":"Hertfordshire",
    "sg:tags":[
        "photographer"
    ],
    "wof:name":"Phil Surbey",
    "wof:placetype":"venue"
},
  "geometry": {"coordinates":[-0.2047059983,51.9090919495],"type":"Point"}
}