{
  "type": "Feature",
  "properties": {
    "addr:full":"133 Blendon Road Bexley Kent DA5 1BT",
    "addr:housenumber":"133",
    "addr:postcode":"da5 1bt",
    "addr:street":"Blendon Road",
    "iso:country":"GB",
    "sg:address":"133 Blendon Road",
    "sg:city":"Bexley",
    "sg:classifiers":[
        {
            "category":"Fast Food",
            "type":"Food & Drink"
        }
    ],
    "sg:phone":"+44 20 8298 1544",
    "sg:postcode":"DA5 1BT",
    "sg:province":"Kent",
    "sg:tags":[
        "away",
        "meal",
        "outlet",
        "take"
    ],
    "wof:name":"THE GOODVIEW GARDENS",
    "wof:placetype":"venue"
},
  "geometry": {"coordinates":[0.1224590018,51.4479484558],"type":"Point"}
}