{
  "type": "Feature",
  "properties": {
    "iso:country":"GB",
    "sg:address":"Lewis Cottage, Jamieson Street, Bowmore",
    "sg:city":"Port Ellen",
    "sg:classifiers":[
        {
            "category":"Health Services",
            "subcategory":"Optometrist",
            "type":"Services"
        },
        {
            "category":"Shopping",
            "subcategory":"Optician",
            "type":"Retail Goods"
        }
    ],
    "sg:phone":"+44 1496 810904",
    "sg:postcode":"PA43 7HL",
    "sg:province":"Argyll and Bute",
    "sg:tags":[
        "ophthalmic"
    ],
    "wof:name":"Norman Holmes",
    "wof:placetype":"venue"
},
  "geometry": {"coordinates":[-6.287072,55.755718],"type":"Point"}
}