{
  "type": "Feature",
  "properties": {
    "iso:country":"GB",
    "sg:address":"36 Albemarle Street",
    "sg:city":"London",
    "sg:classifiers":[
        {
            "category":"Cafe",
            "type":"Food & Drink"
        }
    ],
    "sg:phone":"+44 20 7493 0821",
    "sg:postcode":"W1S 4JE",
    "sg:province":"Greater London",
    "sg:tags":[
        "tea",
        "room"
    ],
    "wof:name":"Nanis of Mayfair",
    "wof:placetype":"venue"
},
  "geometry": {"coordinates":[-0.141878,51.508743],"type":"Point"}
}