{
  "type": "Feature",
  "properties": {
    "iso:country":"GB",
    "sg:address":"1 Fulbrook Road",
    "sg:city":"Dudley",
    "sg:classifiers":[
        {
            "category":"Building & Trades",
            "subcategory":"Construction",
            "type":"Services"
        }
    ],
    "sg:phone":"+44 1384 56619",
    "sg:postcode":"DY1 2BJ",
    "sg:province":"West Midlands",
    "sg:tags":[
        "roofing"
    ],
    "wof:name":"W T  Chambers",
    "wof:placetype":"venue"
},
  "geometry": {"coordinates":[-2.0989980698,52.5099143982],"type":"Point"}
}