{
  "type": "Feature",
  "properties": {
    "addr:full":"The Square, Moreton Hampstead Newton Abbot Devon TQ13 8NF",
    "addr:postcode":"tq13 8nf",
    "addr:street":"The Square",
    "iso:country":"GB",
    "sg:address":"The Square, Moreton Hampstead",
    "sg:city":"Newton Abbot",
    "sg:classifiers":[
        {
            "category":"Museum",
            "subcategory":"Art Museum",
            "type":"Entertainment"
        }
    ],
    "sg:phone":"+44 1647 441007",
    "sg:postcode":"TQ13 8NF",
    "sg:province":"Devon",
    "sg:tags":[
        "gallery"
    ],
    "wof:name":"Lion House Gallery",
    "wof:placetype":"venue"
},
  "geometry": {"coordinates":[-3.8402490616,50.6729202271],"type":"Point"}
}