{
  "type": "Feature",
  "properties": {
    "addr:full":"128 Withington Road Manchester Cheshire M16 8FB",
    "addr:housenumber":"128",
    "addr:postcode":"m16 8fb",
    "addr:street":"Withington Road",
    "iso:country":"GB",
    "sg:address":"128 Withington Road",
    "sg:city":"Manchester",
    "sg:classifiers":[
        {
            "category":"Personal",
            "subcategory":"Beauty Salon",
            "type":"Services"
        },
        {
            "category":"Personal",
            "subcategory":"Barber",
            "type":"Services"
        }
    ],
    "sg:phone":"+44 161 226 1471",
    "sg:postcode":"M16 8FB",
    "sg:province":"Cheshire",
    "sg:tags":[
        "unisex",
        "ladies",
        "lady",
        "hairdresser"
    ],
    "wof:name":"Pamela Jean",
    "wof:placetype":"venue"
},
  "geometry": {"coordinates":[-2.252719,53.450321],"type":"Point"}
}