{
  "type": "Feature",
  "properties": {
    "iso:country":"GB",
    "sg:address":"35 Bondgate Without",
    "sg:city":"Alnwick",
    "sg:classifiers":[
        {
            "category":"Personal",
            "subcategory":"Beauty Salon",
            "type":"Services"
        }
    ],
    "sg:phone":"+44 1665 604326",
    "sg:postcode":"NE66 1PR",
    "sg:province":"Northumberland",
    "wof:name":"The Beauty Salon",
    "wof:placetype":"venue"
},
  "geometry": {"coordinates":[-1.702701,55.412064],"type":"Point"}
}