{
  "type": "Feature",
  "properties": {
    "addr:full":"12 Regent Street Teignmouth Devon TQ14 8SJ",
    "addr:housenumber":"12",
    "addr:postcode":"tq14 8sj",
    "addr:street":"Regent Street",
    "iso:country":"GB",
    "sg:address":"12 Regent Street",
    "sg:city":"Teignmouth",
    "sg:classifiers":[
        {
            "category":"Fast Food",
            "type":"Food & Drink"
        }
    ],
    "sg:phone":"+44 1626 774433",
    "sg:postcode":"TQ14 8SJ",
    "sg:province":"Devon",
    "sg:tags":[
        "away",
        "take"
    ],
    "wof:name":"The Sandwich Shop",
    "wof:placetype":"venue"
},
  "geometry": {"coordinates":[-3.4935889244,50.5468864441],"type":"Point"}
}