{
  "type": "Feature",
  "properties": {
    "iso:country":"GB",
    "sg:address":"52 Middle Street",
    "sg:city":"Deal",
    "sg:classifiers":[
        {
            "category":"Shopping",
            "subcategory":"News",
            "type":"Retail Goods"
        }
    ],
    "sg:phone":"+44 1304 375294",
    "sg:postcode":"CT14 6HT",
    "sg:province":"Kent",
    "sg:tags":[
        "newsagent"
    ],
    "wof:name":"Heath Newsagents",
    "wof:placetype":"venue"
},
  "geometry": {"coordinates":[1.403628,51.224697],"type":"Point"}
}