{
  "type": "Feature",
  "properties": {
    "addr:full":"Portmeadow Farm, Common Road Malmesbury Wiltshire SN16 0HL",
    "addr:postcode":"sn16 0hl",
    "addr:street":"Common Road",
    "iso:country":"GB",
    "sg:address":"Portmeadow Farm, Common Road",
    "sg:city":"Malmesbury",
    "sg:classifiers":[
        {
            "category":"Farming",
            "subcategory":"Livestock Farm",
            "type":"Manufacturing & Wholesale Goods"
        }
    ],
    "sg:phone":"+44 1666 822411",
    "sg:postcode":"SN16 0HL",
    "sg:province":"Wiltshire",
    "sg:tags":[
        "others"
    ],
    "wof:name":"Brian Reeves",
    "wof:placetype":"venue"
},
  "geometry": {"coordinates":[-2.097419,51.582245],"type":"Point"}
}