{
  "type": "Feature",
  "properties": {
    "addr:full":"25 Albany Park, Cabot Lane, Creakmoor Poole Dorset BH17 7BX",
    "addr:housenumber":"25",
    "addr:postcode":"bh17 7bx",
    "addr:street":"Albany;Cabot Lane",
    "iso:country":"GB",
    "sg:address":"25 Albany Park, Cabot Lane, Creakmoor",
    "sg:city":"Poole",
    "sg:classifiers":[
        {
            "category":"Building & Trades",
            "subcategory":"Construction",
            "type":"Services"
        }
    ],
    "sg:phone":"+44 1202 658989",
    "sg:postcode":"BH17 7BX",
    "sg:province":"Dorset",
    "sg:tags":[
        "heating",
        "contractor"
    ],
    "wof:name":"P W B (Industrial Heating) Service Ltd.",
    "wof:placetype":"venue"
},
  "geometry": {"coordinates":[-1.988004,50.743687],"type":"Point"}
}