{
  "type": "Feature",
  "properties": {
    "iso:country":"GB",
    "sg:address":"Satellite House, Sunnybank, Crockenhill Road",
    "sg:city":"Swanley",
    "sg:classifiers":[
        {
            "category":"Professional",
            "subcategory":"Credit Reporting & Collection",
            "type":"Services"
        }
    ],
    "sg:postcode":"BR8 8EP",
    "sg:province":"Kent",
    "sg:tags":[
        "collecting",
        "agency"
    ],
    "wof:name":"Addrecoveries Ltd",
    "wof:placetype":"venue"
},
  "geometry": {"coordinates":[0.139077,51.385731],"type":"Point"}
}