{
  "type": "Feature",
  "properties": {
    "addr:full":"North East Lincolnshire Support Team East, Hereford Av Grimsby Lincolnshire DN34 5BN",
    "addr:postcode":"dn34 5bn",
    "addr:street":"North East;Av Grimsby",
    "iso:country":"GB",
    "sg:address":"North East Lincolnshire Support Team East, Hereford Av",
    "sg:city":"Grimsby",
    "sg:classifiers":[
        {
            "category":"Government",
            "subcategory":"Office",
            "type":"Public Place"
        }
    ],
    "sg:phone":"+44 1472 325435",
    "sg:postcode":"DN34 5BN",
    "sg:province":"Lincolnshire",
    "sg:tags":[
        "local"
    ],
    "wof:name":"North East Lincolnshire Council",
    "wof:placetype":"venue"
},
  "geometry": {"coordinates":[-0.092409,53.560928],"type":"Point"}
}