{
  "type": "Feature",
  "properties": {
    "iso:country":"GB",
    "sg:address":"32 Gravelly Hill North",
    "sg:city":"Birmingham",
    "sg:classifiers":[
        {
            "category":"Education",
            "subcategory":"School",
            "type":"Public Place"
        }
    ],
    "sg:phone":"+44 121 377 6432",
    "sg:postcode":"B23 6BQ",
    "sg:province":"West Midlands",
    "sg:tags":[
        "college",
        "commercial"
    ],
    "wof:name":"New Beavers Office & Technology Skills Centre The",
    "wof:placetype":"venue"
},
  "geometry": {"coordinates":[-1.848256,52.517246],"type":"Point"}
}