{
  "type": "Feature",
  "properties": {
    "addr:full":"Station Rd, Sandycroft Deeside Flintshire CH5 2PT",
    "addr:postcode":"ch5 2pt",
    "addr:street":"Station Rd",
    "iso:country":"GB",
    "sg:address":"Station Rd, Sandycroft",
    "sg:city":"Deeside",
    "sg:classifiers":[
        {
            "category":"Professional",
            "subcategory":"Engineering",
            "type":"Services"
        }
    ],
    "sg:postcode":"CH5 2PT",
    "sg:province":"Flintshire",
    "sg:tags":[
        "civil",
        "engineer"
    ],
    "wof:name":"Spindler,M,",
    "wof:placetype":"venue"
},
  "geometry": {"coordinates":[-3.024987936,53.2024803162],"type":"Point"}
}