{
  "type": "Feature",
  "properties": {
    "iso:country":"GB",
    "sg:address":"2 Station Parade, Ockham Road South, East Horsley",
    "sg:city":"Leatherhead",
    "sg:classifiers":[
        {
            "category":"Food & Beverages",
            "subcategory":"Liquor & Beverages",
            "type":"Retail Goods"
        }
    ],
    "sg:phone":"+44 1483 283280",
    "sg:postcode":"KT24 6QN",
    "sg:province":"Surrey",
    "sg:tags":[
        "beer",
        "spirit",
        "wines"
    ],
    "wof:name":"Wine Rack",
    "wof:placetype":"venue"
},
  "geometry": {"coordinates":[-0.435424,51.27763],"type":"Point"}
}