{
  "type": "Feature",
  "properties": {
    "iso:country":"GB",
    "sg:address":"Guildhall, High St",
    "sg:city":"Kingston Upon Thames",
    "sg:classifiers":[
        {
            "category":"Social Services",
            "type":"Services"
        }
    ],
    "sg:phone":"+44 20 8547 6057",
    "sg:postcode":"KT1 1EU",
    "sg:province":"Greater London",
    "wof:name":"Community Mental Health Team",
    "wof:placetype":"venue"
},
  "geometry": {"coordinates":[-0.3111900091,51.4115409851],"type":"Point"}
}