{
  "type": "Feature",
  "properties": {
    "addr:full":"65 Torridge Way Plymouth Devon PL3 6JG",
    "addr:housenumber":"65",
    "addr:postcode":"pl3 6jg",
    "addr:street":"Torridge Way",
    "iso:country":"GB",
    "sg:address":"65 Torridge Way",
    "sg:city":"Plymouth",
    "sg:classifiers":[
        {
            "category":"Government",
            "subcategory":"Post Office",
            "type":"Public Place"
        }
    ],
    "sg:phone":"+44 1752 773585",
    "sg:postcode":"PL3 6JG",
    "sg:province":"Devon",
    "wof:name":"Torridge Way P.O",
    "wof:placetype":"venue"
},
  "geometry": {"coordinates":[-4.1100888252,50.3889312744],"type":"Point"}
}