{
  "type": "Feature",
  "properties": {
    "iso:country":"GB",
    "sg:address":"16 Lodge Road, Brereton",
    "sg:city":"Rugeley",
    "sg:classifiers":[
        {
            "category":"Freight",
            "type":"Transportation"
        }
    ],
    "sg:phone":"+44 1889 583957",
    "sg:postcode":"WS15 1HG",
    "sg:province":"Staffordshire",
    "sg:tags":[
        "haulage",
        "road"
    ],
    "wof:name":"Glen K Carr",
    "wof:placetype":"venue"
},
  "geometry": {"coordinates":[-1.9221199751,52.7467842102],"type":"Point"}
}