{
  "type": "Feature",
  "properties": {
    "addr:full":"Manor Farm Stud, Bells Yew Grn Tunbridge Wells East Sussex TN3 9BH",
    "addr:housenumber":"stud bells",
    "addr:postcode":"tn3 9bh",
    "addr:street":"Manor;Yew Grn;Wells",
    "iso:country":"GB",
    "sg:address":"Manor Farm Stud, Bells Yew Grn",
    "sg:city":"Tunbridge Wells",
    "sg:classifiers":[
        {
            "category":"Sports & Exercise",
            "subcategory":"Stables",
            "type":"Entertainment"
        },
        {
            "category":"Personal",
            "subcategory":"Adult",
            "type":"Services"
        }
    ],
    "sg:phone":"+44 1892 750288",
    "sg:postcode":"TN3 9BH",
    "sg:province":"East Sussex",
    "sg:tags":[
        "education",
        "equestrian"
    ],
    "wof:name":"Jeffrey Peate Livery Stables",
    "wof:placetype":"venue"
},
  "geometry": {"coordinates":[0.2870399952,51.0947914124],"type":"Point"}
}