{
  "type": "Feature",
  "properties": {
    "addr:full":"Unit 5 Silver Court, Watch Mead Welwyn Garden City Hertfordshire AL7 1LT",
    "addr:housenumber":"unit 5",
    "addr:postcode":"al7 1lt",
    "addr:street":"Silver Court Watch Mead",
    "iso:country":"GB",
    "sg:address":"Unit 5 Silver Court, Watch Mead",
    "sg:city":"Welwyn Garden City",
    "sg:classifiers":[
        {
            "category":"Banks & Credit Unions",
            "subcategory":"Financial Services",
            "type":"Services"
        }
    ],
    "sg:phone":"+44 1707 339326",
    "sg:postcode":"AL7 1LT",
    "sg:province":"Hertfordshire",
    "sg:tags":[
        "consultant"
    ],
    "wof:name":"M F I Financial Services Ltd.",
    "wof:placetype":"venue"
},
  "geometry": {"coordinates":[-0.186114,51.80246],"type":"Point"}
}