{
  "type": "Feature",
  "properties": {
    "addr:full":"33 Berwick St London Greater London W1F 8TQ",
    "addr:housenumber":"33",
    "addr:postcode":"w1f 8tq",
    "addr:street":"Berwick St",
    "iso:country":"GB",
    "sg:address":"33 Berwick St",
    "sg:city":"London",
    "sg:classifiers":[
        {
            "category":"Building & Trades",
            "subcategory":"Construction",
            "type":"Services"
        }
    ],
    "sg:phone":"+44 20 7287 5330",
    "sg:postcode":"W1F 8TQ",
    "sg:province":"Greater London",
    "sg:tags":[
        "builder"
    ],
    "wof:name":"West One Building Maintenance Ltd",
    "wof:placetype":"venue"
},
  "geometry": {"coordinates":[-0.135447,51.5145],"type":"Point"}
}