{
  "type": "Feature",
  "properties": {
    "addr:full":"30 Bankside, Station Fields Kidlington Buckinghamshire OX5 1JE",
    "addr:housenumber":"30",
    "addr:postcode":"ox5 1je",
    "addr:street":"Bankside Station Fields",
    "iso:country":"GB",
    "sg:address":"30 Bankside, Station Fields",
    "sg:city":"Kidlington",
    "sg:classifiers":[
        {
            "category":"Organizations",
            "subcategory":"Membership Organization",
            "type":"Services"
        }
    ],
    "sg:postcode":"OX5 1JE",
    "sg:province":"Buckinghamshire",
    "sg:tags":[
        "club"
    ],
    "wof:name":"Bell Lodge Management Services Limited",
    "wof:placetype":"venue"
},
  "geometry": {"coordinates":[-1.3018,51.830261],"type":"Point"}
}