{
  "type": "Feature",
  "properties": {
    "addr:full":"Unit 5, Enterprise Way, Whitewalls Industrial Estate Colne Lancashire BB8 8LY",
    "addr:housenumber":"unit 5",
    "addr:postcode":"bb8 8ly",
    "addr:street":"Enterprise Way Whitewalls Industrial",
    "iso:country":"GB",
    "sg:address":"Unit 5, Enterprise Way, Whitewalls Industrial Estate",
    "sg:city":"Colne",
    "sg:classifiers":[
        {
            "category":"Wholesale",
            "subcategory":"Machinery & Supplies",
            "type":"Manufacturing & Wholesale Goods"
        }
    ],
    "sg:phone":"+44 1282 870870",
    "sg:postcode":"BB8 8LY",
    "sg:province":"Lancashire",
    "sg:tags":[
        "hydraulic"
    ],
    "wof:name":"Nike Hydraulics Ltd.",
    "wof:placetype":"venue"
},
  "geometry": {"coordinates":[-2.199189,53.849911],"type":"Point"}
}