{
  "type": "Feature",
  "properties": {
    "iso:country":"GB",
    "sg:address":"17 North Street",
    "sg:city":"Dunmow",
    "sg:classifiers":[
        {
            "category":"Real Estate",
            "subcategory":"Surveying",
            "type":"Services"
        }
    ],
    "sg:phone":"+44 1371 878244",
    "sg:postcode":"CM6 1AZ",
    "sg:province":"Essex",
    "sg:tags":[
        "surveyor",
        "quantity"
    ],
    "wof:name":"Curtis Taunton Partnership",
    "wof:placetype":"venue"
},
  "geometry": {"coordinates":[0.36246,51.875034],"type":"Point"}
}