{
  "type": "Feature",
  "properties": {
    "addr:full":"23 Kenyon Street Ipswich Suffolk IP2 8DJ",
    "addr:housenumber":"23",
    "addr:postcode":"ip2 8dj",
    "addr:street":"Kenyon Street",
    "iso:country":"GB",
    "sg:address":"23 Kenyon Street",
    "sg:city":"Ipswich",
    "sg:classifiers":[
        {
            "category":"Shopping",
            "subcategory":"Department Store",
            "type":"Retail Goods"
        }
    ],
    "sg:postcode":"IP2 8DJ",
    "sg:province":"Suffolk",
    "wof:name":"The Corner Store",
    "wof:placetype":"venue"
},
  "geometry": {"coordinates":[1.153855,52.047794],"type":"Point"}
}