{
  "type": "Feature",
  "properties": {
    "addr:full":"Joiner Farm Cottage, Nosely Market Harborough Leicestershire LE7 9EH",
    "addr:postcode":"le7 9eh",
    "addr:street":"Nosely",
    "iso:country":"GB",
    "sg:address":"Joiner Farm Cottage, Nosely",
    "sg:city":"Market Harborough",
    "sg:classifiers":[
        {
            "category":"Building & Trades",
            "subcategory":"Construction",
            "type":"Services"
        }
    ],
    "sg:postcode":"LE7 9EH",
    "sg:province":"Leicestershire",
    "sg:tags":[
        "decorator",
        "painter"
    ],
    "wof:name":"Devereux Decorators Ltd.",
    "wof:placetype":"venue"
},
  "geometry": {"coordinates":[-0.9117500186,52.5793800354],"type":"Point"}
}