{
  "type": "Feature",
  "properties": {
    "addr:full":"Wyvern House, Friary Park, Mills Road Aylesford Kent ME20 7PP",
    "addr:postcode":"me20 7pp",
    "addr:street":"Friary Park Mills Road",
    "iso:country":"GB",
    "sg:address":"Wyvern House, Friary Park, Mills Road",
    "sg:city":"Aylesford",
    "sg:classifiers":[
        {
            "category":"Shopping",
            "subcategory":"Stationery & Office Supplies",
            "type":"Retail Goods"
        }
    ],
    "sg:phone":"+44 1622 882433",
    "sg:postcode":"ME20 7PP",
    "sg:province":"Kent",
    "sg:tags":[
        "printers'",
        "printer"
    ],
    "wof:name":"United Graphics Ltd",
    "wof:placetype":"venue"
},
  "geometry": {"coordinates":[0.4803699851,51.3036308289],"type":"Point"}
}