{
  "type": "Feature",
  "properties": {
    "iso:country":"GB",
    "sg:address":"16 Bells Hill Grn, Stoke Poges",
    "sg:city":"Slough",
    "sg:classifiers":[
        {
            "category":"Fast Food",
            "type":"Food & Drink"
        }
    ],
    "sg:phone":"+44 1753 642561",
    "sg:postcode":"SL2 4BY",
    "sg:province":"Berkshire",
    "sg:tags":[
        "away",
        "take"
    ],
    "wof:name":"Kam's Chinese Take Away",
    "wof:placetype":"venue"
},
  "geometry": {"coordinates":[-0.585224,51.547337],"type":"Point"}
}