{
  "type": "Feature",
  "properties": {
    "addr:full":"Towyn Road, Towyn Abergele Conwy LL22 9HU",
    "addr:postcode":"ll22 9hu",
    "addr:street":"Towyn Road",
    "iso:country":"GB",
    "sg:address":"Towyn Road, Towyn",
    "sg:city":"Abergele",
    "sg:classifiers":[
        {
            "category":"Autos & Motor Vehicles",
            "subcategory":"Fuel & Gas Station",
            "type":"Retail Goods"
        }
    ],
    "sg:postcode":"LL22 9HU",
    "sg:province":"Conwy",
    "sg:tags":[
        "petrol",
        "filling"
    ],
    "wof:name":"Elf Service Station",
    "wof:placetype":"venue"
},
  "geometry": {"coordinates":[-3.541184,53.301846],"type":"Point"}
}