{
  "type": "Feature",
  "properties": {
    "addr:full":"Ashby House, Middleton Street Llandrindod Wells Powys LD1 5ET",
    "addr:postcode":"ld1 5et",
    "addr:street":"Middleton Street",
    "iso:country":"GB",
    "sg:address":"Ashby House, Middleton Street",
    "sg:city":"Llandrindod Wells",
    "sg:classifiers":[
        {
            "category":"Professional",
            "subcategory":"Engineering",
            "type":"Services"
        }
    ],
    "sg:phone":"+44 1597 825788",
    "sg:postcode":"LD1 5ET",
    "sg:province":"Powys",
    "sg:tags":[
        "consultant",
        "structural"
    ],
    "wof:name":"R V W Consulting",
    "wof:placetype":"venue"
},
  "geometry": {"coordinates":[-3.379399,52.240181],"type":"Point"}
}