{
  "type": "Feature",
  "properties": {
    "iso:country":"GB",
    "sg:address":"Baileys Close Farm, Breachwood Grn",
    "sg:city":"Hitchin",
    "sg:classifiers":[
        {
            "category":"Retail",
            "subcategory":"Auto Repair",
            "type":"Services"
        }
    ],
    "sg:postcode":"SG4 8NY",
    "sg:province":"Hertfordshire",
    "sg:tags":[
        "body",
        "car"
    ],
    "wof:name":"Shannon,Gerry,",
    "wof:placetype":"venue"
},
  "geometry": {"coordinates":[-0.32518,51.88065],"type":"Point"}
}