{
  "type": "Feature",
  "properties": {
    "iso:country":"GB",
    "sg:address":"The Green, Kirklington",
    "sg:city":"Bedale",
    "sg:classifiers":[
        {
            "category":"Government",
            "subcategory":"Post Office",
            "type":"Public Place"
        }
    ],
    "sg:postcode":"DL8 2ND",
    "sg:province":"North Yorkshire",
    "wof:name":"Kirklington Post Office",
    "wof:placetype":"venue"
},
  "geometry": {"coordinates":[-1.5120830536,54.2241210938],"type":"Point"}
}