{
  "type": "Feature",
  "properties": {
    "iso:country":"GB",
    "sg:address":"3 Bridge Rd",
    "sg:city":"Felixstowe",
    "sg:classifiers":[
        {
            "category":"Shopping",
            "subcategory":"Stationery & Office Supplies",
            "type":"Retail Goods"
        }
    ],
    "sg:phone":"+44 1394 275033",
    "sg:postcode":"IP11 7SL",
    "sg:province":"Suffolk",
    "sg:tags":[
        "printers'"
    ],
    "wof:name":"Eurotone",
    "wof:placetype":"venue"
},
  "geometry": {"coordinates":[1.346862,51.966591],"type":"Point"}
}