{
  "type": "Feature",
  "properties": {
    "iso:country":"GB",
    "sg:address":"The Hollies, 16 Trelispen Park",
    "sg:city":"St Austell",
    "sg:classifiers":[
        {
            "category":"Shopping",
            "subcategory":"Pets & Pet Supplies",
            "type":"Retail Goods"
        }
    ],
    "sg:postcode":"PL26 6HT",
    "sg:province":"Cornwall",
    "sg:tags":[
        "food"
    ],
    "wof:name":"Oscar Pet Foods",
    "wof:placetype":"venue"
},
  "geometry": {"coordinates":[-4.80075,50.242088],"type":"Point"}
}