{
  "type": "Feature",
  "properties": {
    "addr:full":"112 Acre La London Greater London SW2 5RA",
    "addr:housenumber":"112",
    "addr:postcode":"sw2 5ra",
    "addr:street":"Acre La",
    "iso:country":"GB",
    "sg:address":"112 Acre La",
    "sg:city":"London",
    "sg:classifiers":[
        {
            "category":"Food & Beverages",
            "subcategory":"Fruits & Vegetables",
            "type":"Retail Goods"
        }
    ],
    "sg:postcode":"SW2 5RA",
    "sg:province":"Greater London",
    "sg:tags":[
        "greengrocer"
    ],
    "wof:name":"Sharif,M,",
    "wof:placetype":"venue"
},
  "geometry": {"coordinates":[-0.123573,51.45974],"type":"Point"}
}