{
  "type": "Feature",
  "properties": {
    "addr:full":"15 Barrland Street Glasgow Glasgow City G41 1QH",
    "addr:housenumber":"15",
    "addr:postcode":"g41 1qh",
    "addr:street":"Barrland Street",
    "iso:country":"GB",
    "sg:address":"15 Barrland Street",
    "sg:city":"Glasgow",
    "sg:classifiers":[
        {
            "category":"Organizations",
            "subcategory":"Non-profit Organization",
            "type":"Services"
        }
    ],
    "sg:phone":"+44 141 423 1222",
    "sg:postcode":"G41 1QH",
    "sg:province":"Glasgow City",
    "sg:tags":[
        "charitable",
        "organisation",
        "voluntary",
        "charity"
    ],
    "sg:website":"http://www.banthebomb.org",
    "wof:name":"Scottish C N D",
    "wof:placetype":"venue"
},
  "geometry": {"coordinates":[-4.2640938759,55.8427124023],"type":"Point"}
}