{
  "type": "Feature",
  "properties": {
    "iso:country":"GB",
    "sg:address":"Wroxham Barns, Tunstead Road",
    "sg:city":"Norwich",
    "sg:classifiers":[
        {
            "category":"Manufacturing",
            "subcategory":"Glass & Minerals",
            "type":"Manufacturing & Wholesale Goods"
        }
    ],
    "sg:phone":"+44 1603 784825",
    "sg:postcode":"NR12 8QU",
    "sg:province":"Norfolk",
    "sg:tags":[
        "stained"
    ],
    "wof:name":"Coastal Stained Glass",
    "wof:placetype":"venue"
},
  "geometry": {"coordinates":[1.40069,52.748604],"type":"Point"}
}