{
  "type": "Feature",
  "properties": {
    "addr:full":"Church Street, Hampstead Norreys Thatcham Berkshire RG18 0TB",
    "addr:postcode":"rg18 0tb",
    "addr:street":"Church Street",
    "iso:country":"GB",
    "sg:address":"Church Street, Hampstead Norreys",
    "sg:city":"Thatcham",
    "sg:classifiers":[
        {
            "category":"Government",
            "subcategory":"Post Office",
            "type":"Public Place"
        }
    ],
    "sg:postcode":"RG18 0TB",
    "sg:province":"Berkshire",
    "wof:name":"Hampstead Norreys Post Office",
    "wof:placetype":"venue"
},
  "geometry": {"coordinates":[-1.204007,51.466198],"type":"Point"}
}