{
  "type": "Feature",
  "properties": {
    "addr:full":"Unit 8, Riding Court, Buckingham Road Industrial Estat Brackley Buckinghamshire NN13 7BH",
    "addr:housenumber":"unit 8",
    "addr:postcode":"nn13 7bh",
    "addr:street":"Riding Court Buckingham Road Industrial Estat",
    "iso:country":"GB",
    "sg:address":"Unit 8, Riding Court, Buckingham Road Industrial Estat",
    "sg:city":"Brackley",
    "sg:classifiers":[
        {
            "category":"Shopping",
            "subcategory":"Bicycles & Sporting Goods",
            "type":"Retail Goods"
        },
        {
            "category":"Shopping",
            "subcategory":"Pets & Pet Supplies",
            "type":"Retail Goods"
        }
    ],
    "sg:phone":"+44 1280 702224",
    "sg:postcode":"NN13 7BH",
    "sg:province":"Buckinghamshire",
    "sg:tags":[
        "riding",
        "saddlery",
        "equestrian",
        "wear"
    ],
    "wof:name":"O Shepherd & Son Ltd.",
    "wof:placetype":"venue"
},
  "geometry": {"coordinates":[-1.146082,52.02903],"type":"Point"}
}