{
  "type": "Feature",
  "properties": {
    "addr:full":"9 Florence Street Liverpool Merseyside L4 4JS",
    "addr:housenumber":"9",
    "addr:postcode":"l4 4js",
    "addr:street":"Florence Street",
    "iso:country":"GB",
    "sg:address":"9 Florence Street",
    "sg:city":"Liverpool",
    "sg:classifiers":[
        {
            "category":"Building & Trades",
            "subcategory":"Plumbing",
            "type":"Services"
        }
    ],
    "sg:phone":"+44 151 207 0116",
    "sg:postcode":"L4 4JS",
    "sg:province":"Merseyside",
    "sg:tags":[
        "heating"
    ],
    "wof:name":"Parkes",
    "wof:placetype":"venue"
},
  "geometry": {"coordinates":[-2.970235,53.434982],"type":"Point"}
}