{
  "type": "Feature",
  "properties": {
    "iso:country":"GB",
    "sg:address":"Hill Farm, Dolly La",
    "sg:city":"Stockport",
    "sg:classifiers":[
        {
            "category":"Farming",
            "subcategory":"Livestock Farm",
            "type":"Manufacturing & Wholesale Goods"
        }
    ],
    "sg:phone":"+44 1663 750378",
    "sg:postcode":"SK12 7QG",
    "sg:province":"Cheshire",
    "sg:tags":[
        "others"
    ],
    "wof:name":"A Cooper",
    "wof:placetype":"venue"
},
  "geometry": {"coordinates":[-2.07896,53.34705],"type":"Point"}
}