{
  "type": "Feature",
  "properties": {
    "addr:full":"Ruthin, Prince Of Wales Avenue, Penymaes Holywell Denbighshire CH8 7BJ",
    "addr:postcode":"ch8 7bj",
    "addr:street":"Prince;Wales Avenue Penymaes",
    "iso:country":"GB",
    "sg:address":"Ruthin, Prince Of Wales Avenue, Penymaes",
    "sg:city":"Holywell",
    "sg:classifiers":[
        {
            "category":"Building & Trades",
            "subcategory":"Construction",
            "type":"Services"
        }
    ],
    "sg:postcode":"CH8 7BJ",
    "sg:province":"Denbighshire",
    "sg:tags":[
        "decorator",
        "painter"
    ],
    "wof:name":"Bernard  Dykes",
    "wof:placetype":"venue"
},
  "geometry": {"coordinates":[-3.225194931,53.2745475769],"type":"Point"}
}