{
  "type": "Feature",
  "properties": {
    "iso:country":"GB",
    "sg:address":"1 Glebe Street",
    "sg:city":"Campbeltown",
    "sg:classifiers":[
        {
            "category":"Personal",
            "subcategory":"Beauty Salon",
            "type":"Services"
        }
    ],
    "sg:postcode":"PA28 6JJ",
    "sg:province":"Argyll and Bute",
    "sg:tags":[
        "unisex",
        "hairdresser"
    ],
    "wof:name":"Hi-Lites",
    "wof:placetype":"venue"
},
  "geometry": {"coordinates":[-5.607647,55.423775],"type":"Point"}
}