{
  "type": "Feature",
  "properties": {
    "iso:country":"GB",
    "sg:address":"Picksley Crescent, Holton-le-clay",
    "sg:city":"Grimsby",
    "sg:classifiers":[
        {
            "category":"Education",
            "subcategory":"School",
            "type":"Public Place"
        },
        {
            "category":"Government",
            "subcategory":"Office",
            "type":"Public Place"
        }
    ],
    "sg:phone":"+44 1472 826432",
    "sg:postcode":"DN36 5DR",
    "sg:province":"Lincolnshire",
    "sg:tags":[
        "local",
        "authority"
    ],
    "wof:name":"Holton-le-Clay Junior School",
    "wof:placetype":"venue"
},
  "geometry": {"coordinates":[-0.0585189983,53.5055007935],"type":"Point"}
}