{
  "type": "Feature",
  "properties": {
    "addr:full":"62 Wantage Road Didcot Oxfordshire OX11 0BY",
    "addr:housenumber":"62",
    "addr:postcode":"ox11 0by",
    "addr:street":"Wantage Road",
    "iso:country":"GB",
    "sg:address":"62 Wantage Road",
    "sg:city":"Didcot",
    "sg:classifiers":[
        {
            "category":"Food & Beverages",
            "subcategory":"Groceries & Convenience Stores",
            "type":"Retail Goods"
        }
    ],
    "sg:phone":"+44 1235 811222",
    "sg:postcode":"OX11 0BY",
    "sg:province":"Oxfordshire",
    "wof:name":"Alldays Stores Ltd.",
    "wof:placetype":"venue"
},
  "geometry": {"coordinates":[-1.256649971,51.605381012],"type":"Point"}
}