{
  "type": "Feature",
  "properties": {
    "iso:country":"GB",
    "sg:address":"598 Staniforth Road",
    "sg:city":"Sheffield",
    "sg:classifiers":[
        {
            "category":"Food & Beverages",
            "subcategory":"Fruits & Vegetables",
            "type":"Retail Goods"
        },
        {
            "category":"Food & Beverages",
            "subcategory":"Groceries & Convenience Stores",
            "type":"Retail Goods"
        }
    ],
    "sg:phone":"+44 114 242 1280",
    "sg:postcode":"S9 4LN",
    "sg:province":"South Yorkshire",
    "sg:tags":[
        "grocer",
        "greengrocer"
    ],
    "wof:name":"Darnall Continental Grocer",
    "wof:placetype":"venue"
},
  "geometry": {"coordinates":[-1.414124,53.38657],"type":"Point"}
}