{
  "type": "Feature",
  "properties": {
    "addr:full":"5-7 Leake St York North Yorkshire YO1 3BR",
    "addr:housenumber":"5-7",
    "addr:postcode":"yo1 3br",
    "addr:street":"Leake St York",
    "iso:country":"GB",
    "sg:address":"5-7 Leake St",
    "sg:city":"York",
    "sg:classifiers":[
        {
            "category":"Professional",
            "subcategory":"Engineering",
            "type":"Services"
        }
    ],
    "sg:phone":"+44 1904 655769",
    "sg:postcode":"YO1 3BR",
    "sg:province":"North Yorkshire",
    "sg:tags":[
        "contractor",
        "electrical",
        "engineer"
    ],
    "wof:name":"Dennis King",
    "wof:placetype":"venue"
},
  "geometry": {"coordinates":[-1.0689330101,53.9551429749],"type":"Point"}
}