{
  "type": "Feature",
  "properties": {
    "addr:full":"Whiteholme, Ribchester Rd Blackburn Lancashire BB1 9EY",
    "addr:postcode":"bb1 9ey",
    "addr:street":"Ribchester Rd",
    "iso:country":"GB",
    "sg:address":"Whiteholme, Ribchester Rd",
    "sg:city":"Blackburn",
    "sg:classifiers":[
        {
            "category":"Professional",
            "subcategory":"Lawyer & Legal Services",
            "type":"Services"
        }
    ],
    "sg:phone":"+44 1254 246876",
    "sg:postcode":"BB1 9EY",
    "sg:province":"Lancashire",
    "wof:name":"B Frankland",
    "wof:placetype":"venue"
},
  "geometry": {"coordinates":[-2.514184,53.807835],"type":"Point"}
}