{
  "type": "Feature",
  "properties": {
    "addr:full":"50 Morven Road Sutton Coldfield West Midlands B73 6ND",
    "addr:housenumber":"50",
    "addr:postcode":"b73 6nd",
    "addr:street":"Morven Road",
    "iso:country":"GB",
    "sg:address":"50 Morven Road",
    "sg:city":"Sutton Coldfield",
    "sg:classifiers":[
        {
            "category":"Manufacturing",
            "subcategory":"Tools & Machinery",
            "type":"Manufacturing & Wholesale Goods"
        }
    ],
    "sg:postcode":"B73 6ND",
    "sg:province":"West Midlands",
    "sg:tags":[
        "society",
        "friendly"
    ],
    "wof:name":"Marian Podraza",
    "wof:placetype":"venue"
},
  "geometry": {"coordinates":[-1.8379720449,52.5528106689],"type":"Point"}
}