{
  "type": "Feature",
  "properties": {
    "addr:full":"45 Woodlane Falmouth Cornwall TR11 4RB",
    "addr:housenumber":"45",
    "addr:postcode":"tr11 4rb",
    "addr:street":"Woodlane",
    "iso:country":"GB",
    "sg:address":"45 Woodlane",
    "sg:city":"Falmouth",
    "sg:classifiers":[
        {
            "category":"Food & Beverages",
            "subcategory":"Bakery",
            "type":"Retail Goods"
        }
    ],
    "sg:phone":"+44 1326 312494",
    "sg:postcode":"TR11 4RB",
    "sg:province":"Cornwall",
    "sg:tags":[
        "baker"
    ],
    "wof:name":"Falmouth Pasty Co. Ltd.",
    "wof:placetype":"venue"
},
  "geometry": {"coordinates":[-5.0733218193,50.1483764648],"type":"Point"}
}