{
  "type": "Feature",
  "properties": {
    "iso:country":"GB",
    "sg:address":"Unit 40 London Road Indust Est",
    "sg:city":"Baldock",
    "sg:classifiers":[
        {
            "category":"Building & Trades",
            "subcategory":"Construction",
            "type":"Services"
        }
    ],
    "sg:phone":"+44 1462 893482",
    "sg:postcode":"SG7 6NA",
    "sg:province":"Bedfordshire",
    "sg:tags":[
        "glazier"
    ],
    "wof:name":"Lune Ward Ltd",
    "wof:placetype":"venue"
},
  "geometry": {"coordinates":[-0.1845970005,51.9829521179],"type":"Point"}
}