{
  "type": "Feature",
  "properties": {
    "iso:country":"GB",
    "sg:address":"Post Office Road, Seisdon",
    "sg:city":"Wolverhampton",
    "sg:classifiers":[
        {
            "category":"Personal",
            "subcategory":"Adult",
            "type":"Services"
        }
    ],
    "sg:postcode":"WV5 7HA",
    "sg:province":"Shropshire",
    "sg:tags":[
        "equestrian"
    ],
    "wof:name":"Robins Nest Stables",
    "wof:placetype":"venue"
},
  "geometry": {"coordinates":[-2.244746,52.551552],"type":"Point"}
}