{
  "type": "Feature",
  "properties": {
    "addr:full":"5 Risborough Road, Stoke Mandeville Aylesbury Buckinghamshire HP22 5UP",
    "addr:housenumber":"5",
    "addr:postcode":"hp22 5up",
    "addr:street":"Risborough Road",
    "iso:country":"GB",
    "sg:address":"5 Risborough Road, Stoke Mandeville",
    "sg:city":"Aylesbury",
    "sg:classifiers":[
        {
            "category":"Bars & Pubs",
            "type":"Food & Drink"
        },
        {
            "category":"Community Center",
            "subcategory":"Social",
            "type":"Public Place"
        }
    ],
    "sg:phone":"+44 1296 613632",
    "sg:postcode":"HP22 5UP",
    "sg:province":"Buckinghamshire",
    "sg:tags":[
        "pubs",
        "house",
        "inn",
        "activity"
    ],
    "wof:name":"The Bull",
    "wof:placetype":"venue"
},
  "geometry": {"coordinates":[-0.7910040021,51.7858009338],"type":"Point"}
}