{
  "type": "Feature",
  "properties": {
    "addr:full":"69 Wortley Road Croydon Surrey CR0 3EB",
    "addr:housenumber":"69",
    "addr:postcode":"cr0 3eb",
    "addr:street":"Wortley Road",
    "iso:country":"GB",
    "sg:address":"69 Wortley Road",
    "sg:city":"Croydon",
    "sg:classifiers":[
        {
            "category":"Retail",
            "subcategory":"Auto Repair",
            "type":"Services"
        }
    ],
    "sg:postcode":"CR0 3EB",
    "sg:province":"Surrey",
    "sg:tags":[
        "modification",
        "garage"
    ],
    "wof:name":"South London Taxi",
    "wof:placetype":"venue"
},
  "geometry": {"coordinates":[-0.1174840033,51.3875274658],"type":"Point"}
}