{
  "type": "Feature",
  "properties": {
    "addr:full":"Bernard Sunley House, 21 South Island Place London Greater London SW9 0DY",
    "addr:housenumber":"21",
    "addr:postcode":"sw9 0dy",
    "addr:street":"South Island Place",
    "iso:country":"GB",
    "sg:address":"Bernard Sunley House, 21 South Island Place",
    "sg:city":"London",
    "sg:classifiers":[
        {
            "category":"Organizations",
            "subcategory":"Community Association",
            "type":"Services"
        }
    ],
    "sg:phone":"+44 20 7582 3184",
    "sg:postcode":"SW9 0DY",
    "sg:province":"Greater London",
    "sg:tags":[
        "society",
        "housing"
    ],
    "wof:name":"Anchor Trust Co. Ltd.",
    "wof:placetype":"venue"
},
  "geometry": {"coordinates":[-0.113278,51.478233],"type":"Point"}
}