{
  "type": "Feature",
  "properties": {
    "addr:full":"Grange Hill Farm, Grange Old Road Wirral Merseyside CH48 4ET",
    "addr:postcode":"ch48 4et",
    "addr:street":"Grange Hill Farm Grange Old Road",
    "iso:country":"GB",
    "sg:address":"Grange Hill Farm, Grange Old Road",
    "sg:city":"Wirral",
    "sg:classifiers":[
        {
            "category":"Wholesale",
            "subcategory":"Fruits & Vegetables",
            "type":"Manufacturing & Wholesale Goods"
        },
        {
            "category":"Sports & Exercise",
            "subcategory":"Skate Park",
            "type":"Entertainment"
        }
    ],
    "sg:phone":"+44 151 625 1548",
    "sg:postcode":"CH48 4ET",
    "sg:province":"Merseyside",
    "sg:tags":[
        "grower",
        "mushroom"
    ],
    "wof:name":"S & B Little Mushrooms",
    "wof:placetype":"venue"
},
  "geometry": {"coordinates":[-3.1771199703,53.373840332],"type":"Point"}
}