{
  "type": "Feature",
  "properties": {
    "iso:country":"GB",
    "sg:address":"Kings Ride Court, Kings Ride",
    "sg:city":"Ascot",
    "sg:classifiers":[
        {
            "category":"Professional",
            "subcategory":"Computer Services",
            "type":"Services"
        }
    ],
    "sg:phone":"+44 1344 624949",
    "sg:postcode":"SL5 7JR",
    "sg:province":"Berkshire",
    "sg:tags":[
        "system",
        "software"
    ],
    "wof:name":"Haht Software",
    "wof:placetype":"venue"
},
  "geometry": {"coordinates":[-0.673794,51.410675],"type":"Point"}
}