{
  "type": "Feature",
  "properties": {
    "addr:full":"11 Forfar Avenue Glasgow Glasgow City G52 3JQ",
    "addr:housenumber":"11",
    "addr:postcode":"g52 3jq",
    "addr:street":"Forfar Avenue",
    "iso:country":"GB",
    "sg:address":"11 Forfar Avenue",
    "sg:city":"Glasgow",
    "sg:classifiers":[
        {
            "category":"Shopping",
            "subcategory":"Florist",
            "type":"Retail Goods"
        }
    ],
    "sg:phone":"+44 141 882 3135",
    "sg:postcode":"G52 3JQ",
    "sg:province":"Glasgow City",
    "wof:name":"Wallace's for Flowers",
    "wof:placetype":"venue"
},
  "geometry": {"coordinates":[-4.354452,55.845573],"type":"Point"}
}