{
  "type": "Feature",
  "properties": {
    "iso:country":"GB",
    "sg:address":"22a High Street, Cleobury Mortimer",
    "sg:city":"Kidderminster",
    "sg:classifiers":[
        {
            "category":"Personal",
            "subcategory":"Beauty Salon",
            "type":"Services"
        },
        {
            "category":"Personal",
            "subcategory":"Barber",
            "type":"Services"
        }
    ],
    "sg:phone":"+44 1299 270309",
    "sg:postcode":"DY14 8DG",
    "sg:province":"Shropshire",
    "sg:tags":[
        "unisex",
        "hairdresser"
    ],
    "wof:name":"Shirley's Hairdressers",
    "wof:placetype":"venue"
},
  "geometry": {"coordinates":[-2.482507,52.378391],"type":"Point"}
}