{
  "type": "Feature",
  "properties": {
    "addr:full":"Pottermount, Potterhill Ayr East Ayrshire KA6 5JS",
    "addr:postcode":"ka6 5js",
    "addr:street":"East",
    "iso:country":"GB",
    "sg:address":"Pottermount, Potterhill",
    "sg:city":"Ayr",
    "sg:classifiers":[
        {
            "category":"Recreation",
            "subcategory":"Dog Park",
            "type":"Entertainment"
        }
    ],
    "sg:phone":"+44 1292 570313",
    "sg:postcode":"KA6 5JS",
    "sg:province":"East Ayrshire",
    "wof:name":"Animal Crackers Pet Grooming",
    "wof:placetype":"venue"
},
  "geometry": {"coordinates":[-4.5452699661,55.4560585022],"type":"Point"}
}