{
  "type": "Feature",
  "properties": {
    "iso:country":"GB",
    "sg:address":"169 The Bdwy",
    "sg:city":"Broadstone",
    "sg:classifiers":[
        {
            "category":"Shopping",
            "type":"Retail Goods"
        }
    ],
    "sg:phone":"+44 1202 690769",
    "sg:postcode":"BH18 8DH",
    "sg:province":"Dorset",
    "sg:tags":[
        "part",
        "accessory"
    ],
    "wof:name":"Motorists Discount Centres",
    "wof:placetype":"venue"
},
  "geometry": {"coordinates":[-1.9968789816,50.7625198364],"type":"Point"}
}