{
  "type": "Feature",
  "properties": {
    "iso:country":"GB",
    "sg:address":"6 Woodies Close, Binfield",
    "sg:city":"Bracknell",
    "sg:classifiers":[
        {
            "category":"Building & Trades",
            "subcategory":"Construction",
            "type":"Services"
        }
    ],
    "sg:phone":"+44 1344 426680",
    "sg:postcode":"RG42 4EH",
    "sg:province":"Berkshire",
    "sg:tags":[
        "glazier",
        "decorator",
        "painter"
    ],
    "wof:name":"Marshall's Decorating",
    "wof:placetype":"venue"
},
  "geometry": {"coordinates":[-0.787259,51.4254],"type":"Point"}
}