{
  "type": "Feature",
  "properties": {
    "iso:country":"GB",
    "sg:address":"7 Capricorn Ho Straight Bit, Flackwell Heath",
    "sg:city":"High Wycombe",
    "sg:classifiers":[
        {
            "category":"Building & Trades",
            "subcategory":"Construction",
            "type":"Services"
        }
    ],
    "sg:postcode":"HP10 9NN",
    "sg:province":"Buckinghamshire",
    "sg:tags":[
        "joiner",
        "carpenter"
    ],
    "wof:name":"Holland,Steve,",
    "wof:placetype":"venue"
},
  "geometry": {"coordinates":[-0.7017049789,51.5935173035],"type":"Point"}
}