{
  "type": "Feature",
  "properties": {
    "addr:full":"45 Hampton Park Road Hereford Herefordshire HR1 1TJ",
    "addr:housenumber":"45",
    "addr:postcode":"hr1 1tj",
    "addr:street":"Hampton Park Road",
    "iso:country":"GB",
    "sg:address":"45 Hampton Park Road",
    "sg:city":"Hereford",
    "sg:classifiers":[
        {
            "category":"Health Services",
            "subcategory":"Nursing And Care Facility",
            "type":"Services"
        }
    ],
    "sg:phone":"+44 1432 267996",
    "sg:postcode":"HR1 1TJ",
    "sg:province":"Herefordshire",
    "sg:tags":[
        "home"
    ],
    "wof:name":"Aston House Residential Home",
    "wof:placetype":"venue"
},
  "geometry": {"coordinates":[-2.688278,52.049381],"type":"Point"}
}