{
  "type": "Feature",
  "properties": {
    "addr:full":"4 Lords Walk Earlsfield Shopping, Centre, Eriswell Brandon Norfolk IP27 9BU",
    "addr:housenumber":"4;eriswell",
    "addr:postcode":"ip27 9bu",
    "addr:street":"Lords Walk;Shopping;Brandon Norfolk",
    "iso:country":"GB",
    "sg:address":"4 Lords Walk Earlsfield Shopping, Centre, Eriswell",
    "sg:city":"Brandon",
    "sg:classifiers":[
        {
            "category":"Personal",
            "subcategory":"Beauty Salon",
            "type":"Services"
        }
    ],
    "sg:phone":"+44 1638 532971",
    "sg:postcode":"IP27 9BU",
    "sg:province":"Norfolk",
    "sg:tags":[
        "unisex",
        "hairdresser"
    ],
    "wof:name":"Just Jon Hairstylists",
    "wof:placetype":"venue"
},
  "geometry": {"coordinates":[0.54019,52.389961],"type":"Point"}
}