{
  "type": "Feature",
  "properties": {
    "iso:country":"GB",
    "sg:address":"172 High Street",
    "sg:city":"Irvine",
    "sg:classifiers":[
        {
            "category":"Utilities",
            "type":"Services"
        }
    ],
    "sg:postcode":"KA12 8AN",
    "sg:province":"North Ayrshire",
    "sg:tags":[
        "internet"
    ],
    "wof:name":"Netvine",
    "wof:placetype":"venue"
},
  "geometry": {"coordinates":[-4.6679811478,55.6161727905],"type":"Point"}
}