{
  "type": "Feature",
  "properties": {
    "addr:full":"The Old Station House, Gills Grn Cranbrook East Sussex TN18 5ER",
    "addr:postcode":"tn18 5er",
    "addr:street":"Gills Grn",
    "iso:country":"GB",
    "sg:address":"The Old Station House, Gills Grn",
    "sg:city":"Cranbrook",
    "sg:classifiers":[
        {
            "category":"Bus Charters",
            "type":"Transportation"
        }
    ],
    "sg:phone":"+44 1580 754010",
    "sg:postcode":"TN18 5ER",
    "sg:province":"East Sussex",
    "sg:tags":[
        "mini",
        "hire",
        "leasing"
    ],
    "wof:name":"Valley Travel Mini Bus Hire",
    "wof:placetype":"venue"
},
  "geometry": {"coordinates":[0.5059099793,51.0625],"type":"Point"}
}