{
  "type": "Feature",
  "properties": {
    "addr:full":"Westbourne Ct, Lockwood Ave Poulton-le-fylde Lancashire FY6 7AB",
    "addr:postcode":"fy6 7ab",
    "addr:street":"Westbourne Ct;Ave",
    "iso:country":"GB",
    "sg:address":"Westbourne Ct, Lockwood Ave",
    "sg:city":"Poulton-le-fylde",
    "sg:classifiers":[
        {
            "category":"Health Services",
            "subcategory":"Doctor",
            "type":"Services"
        },
        {
            "category":"Health Services",
            "subcategory":"Clinic",
            "type":"Services"
        }
    ],
    "sg:phone":"+44 1253 886878",
    "sg:postcode":"FY6 7AB",
    "sg:province":"Lancashire",
    "sg:tags":[
        "nh",
        "practitioners"
    ],
    "wof:name":"South Lancashire Health Authority",
    "wof:placetype":"venue"
},
  "geometry": {"coordinates":[-2.994659,53.84808],"type":"Point"}
}