{
  "type": "Feature",
  "properties": {
    "addr:full":"Brunel St Cardiff Cardiff CF1 8ES",
    "addr:postcode":"cf1 8es",
    "addr:street":"Brunel St",
    "iso:country":"GB",
    "sg:address":"Brunel St",
    "sg:city":"Cardiff",
    "sg:classifiers":[
        {
            "category":"Organizations",
            "subcategory":"Non-profit Organization",
            "type":"Services"
        }
    ],
    "sg:phone":"+44 29 2022 6128",
    "sg:postcode":"CF1 8ES",
    "sg:province":"Cardiff",
    "sg:tags":[
        "organisation",
        "voluntary",
        "charity"
    ],
    "wof:name":"CARES",
    "wof:placetype":"venue"
},
  "geometry": {"coordinates":[-3.19098,51.477371],"type":"Point"}
}