{
  "type": "Feature",
  "properties": {
    "addr:full":"15 William Street, South West Lane Edinburgh City of Edinburgh EH3 7LL",
    "addr:housenumber":"15",
    "addr:postcode":"eh3 7ll",
    "addr:street":"William Street South West Lane",
    "iso:country":"GB",
    "sg:address":"15 William Street, South West Lane",
    "sg:city":"Edinburgh",
    "sg:classifiers":[
        {
            "category":"Professional",
            "subcategory":"Printing & Photocopies",
            "type":"Services"
        }
    ],
    "sg:phone":"+44 131 225 0900",
    "sg:postcode":"EH3 7LL",
    "sg:province":"City of Edinburgh",
    "sg:tags":[
        "printer"
    ],
    "wof:name":"Hyway Printing Services Ltd.",
    "wof:placetype":"venue"
},
  "geometry": {"coordinates":[-3.2120249271,55.9496765137],"type":"Point"}
}