{
  "type": "Feature",
  "properties": {
    "addr:full":"12 Weelkes Close Stanford-le-hope Essex SS17 8RE",
    "addr:housenumber":"12",
    "addr:postcode":"ss17 8re",
    "addr:street":"Weelkes Close",
    "iso:country":"GB",
    "sg:address":"12 Weelkes Close",
    "sg:city":"Stanford-le-hope",
    "sg:classifiers":[
        {
            "category":"Home & Garden",
            "subcategory":"Hardware",
            "type":"Retail Goods"
        }
    ],
    "sg:phone":"+44 1375 360366",
    "sg:postcode":"SS17 8RE",
    "sg:province":"Essex",
    "sg:tags":[
        "tarpaulin"
    ],
    "wof:name":"Curtainmaster",
    "wof:placetype":"venue"
},
  "geometry": {"coordinates":[0.4257360101,51.5225601196],"type":"Point"}
}