{
  "type": "Feature",
  "properties": {
    "addr:full":"Cambridge House, 27 Cambridge Park London Greater London E11 2PU",
    "addr:housenumber":"27",
    "addr:postcode":"e11 2pu",
    "addr:street":"Cambridge Park",
    "iso:country":"GB",
    "sg:address":"Cambridge House, 27 Cambridge Park",
    "sg:city":"London",
    "sg:classifiers":[
        {
            "category":"Real Estate",
            "subcategory":"Real Estate Agent",
            "type":"Services"
        }
    ],
    "sg:postcode":"E11 2PU",
    "sg:province":"Greater London",
    "wof:name":"Hare Property Company Limited",
    "wof:placetype":"venue"
},
  "geometry": {"coordinates":[0.025978,51.575005],"type":"Point"}
}