{
  "type": "Feature",
  "properties": {
    "iso:country":"GB",
    "sg:address":"Greenhead Farm",
    "sg:city":"Alva",
    "sg:classifiers":[
        {
            "category":"Building & Trades",
            "subcategory":"Construction",
            "type":"Services"
        }
    ],
    "sg:phone":"+44 1259 760432",
    "sg:postcode":"FK12 5BQ",
    "sg:province":"Clackmannanshire",
    "sg:tags":[
        "builder"
    ],
    "wof:name":"Kelso Logan",
    "wof:placetype":"venue"
},
  "geometry": {"coordinates":[-3.799564,56.153049],"type":"Point"}
}