{
  "type": "Feature",
  "properties": {
    "addr:full":"1 Market Street Ashton-under-lyne Greater Manchester OL6 6BP",
    "addr:housenumber":"1",
    "addr:postcode":"ol6 6bp",
    "addr:street":"Market Street",
    "iso:country":"GB",
    "sg:address":"1 Market Street",
    "sg:city":"Ashton-under-lyne",
    "sg:classifiers":[
        {
            "category":"Shopping",
            "subcategory":"Comic Books",
            "type":"Retail Goods"
        }
    ],
    "sg:phone":"+44 161 339 5100",
    "sg:postcode":"OL6 6BP",
    "sg:province":"Greater Manchester",
    "sg:tags":[
        "jeweller"
    ],
    "wof:name":"Harrington & Hallworth",
    "wof:placetype":"venue"
},
  "geometry": {"coordinates":[-2.0922689438,53.4890556335],"type":"Point"}
}