{
  "type": "Feature",
  "properties": {
    "iso:country":"GB",
    "sg:address":"Lion Depot, Lion Lane, Needham Market",
    "sg:city":"Ipswich",
    "sg:classifiers":[
        {
            "category":"Autos & Motor Vehicles",
            "subcategory":"Automobile Sales",
            "type":"Retail Goods"
        }
    ],
    "sg:phone":"+44 1449 722088",
    "sg:postcode":"IP6 8NT",
    "sg:province":"Suffolk",
    "sg:tags":[
        "commercial"
    ],
    "wof:name":"Lion Cars",
    "wof:placetype":"venue"
},
  "geometry": {"coordinates":[1.05922,52.149281],"type":"Point"}
}