{
  "type": "Feature",
  "properties": {
    "iso:country":"GB",
    "sg:address":"The Meadows, Nursery Road, Nazeing",
    "sg:city":"Waltham Abbey",
    "sg:classifiers":[
        {
            "category":"Building & Trades",
            "subcategory":"Construction",
            "type":"Services"
        }
    ],
    "sg:phone":"+44 1992 465255",
    "sg:postcode":"EN9 2JF",
    "sg:province":"Essex",
    "sg:tags":[
        "roofing"
    ],
    "wof:name":"Alpha Roofing Specialists",
    "wof:placetype":"venue"
},
  "geometry": {"coordinates":[0.048448,51.738914],"type":"Point"}
}