{
  "type": "Feature",
  "properties": {
    "addr:full":"Liberty 2, Mercury Gardens Romford Essex RM1 3EE",
    "addr:housenumber":"2",
    "addr:postcode":"rm1 3ee",
    "addr:street":"Mercury Gardens",
    "iso:country":"GB",
    "sg:address":"Liberty 2, Mercury Gardens",
    "sg:city":"Romford",
    "sg:classifiers":[
        {
            "category":"Recreation",
            "subcategory":"Dance Hall",
            "type":"Entertainment"
        }
    ],
    "sg:phone":"+44 1708 729020",
    "sg:postcode":"RM1 3EE",
    "sg:province":"Essex",
    "sg:tags":[
        "bingo"
    ],
    "wof:name":"Mecca Bingo Ltd.",
    "wof:placetype":"venue"
},
  "geometry": {"coordinates":[0.1863150001,51.5813903809],"type":"Point"}
}