{
  "type": "Feature",
  "properties": {
    "addr:full":"4 Lloyd Av Southampton Hampshire SO40 4WY",
    "addr:housenumber":"4",
    "addr:postcode":"so40 4wy",
    "addr:street":"Lloyd Av",
    "iso:country":"GB",
    "sg:address":"4 Lloyd Av",
    "sg:city":"Southampton",
    "sg:classifiers":[
        {
            "category":"Building & Trades",
            "subcategory":"Construction",
            "type":"Services"
        }
    ],
    "sg:phone":"+44 23 8086 7654",
    "sg:postcode":"SO40 4WY",
    "sg:province":"Hampshire",
    "sg:tags":[
        "contractor",
        "paving",
        "driveway"
    ],
    "wof:name":"Keith Broomfield",
    "wof:placetype":"venue"
},
  "geometry": {"coordinates":[-1.459153,50.889458],"type":"Point"}
}