{
  "type": "Feature",
  "properties": {
    "addr:full":"9 Portland Road Birmingham West Midlands B16 9HN",
    "addr:housenumber":"9",
    "addr:postcode":"b16 9hn",
    "addr:street":"Portland Road",
    "iso:country":"GB",
    "sg:address":"9 Portland Road",
    "sg:city":"Birmingham",
    "sg:classifiers":[
        {
            "category":"Banks & Credit Unions",
            "subcategory":"Financial Services",
            "type":"Services"
        }
    ],
    "sg:phone":"+44 121 455 7373",
    "sg:postcode":"B16 9HN",
    "sg:province":"West Midlands",
    "sg:tags":[
        "adviser"
    ],
    "wof:name":"Provest Financial Planning",
    "wof:placetype":"venue"
},
  "geometry": {"coordinates":[-1.9367,52.472401],"type":"Point"}
}