{
  "type": "Feature",
  "properties": {
    "addr:full":"Happy Land Farm, Dringhoe Driffield East Riding of Yorkshire YO25 8AG",
    "addr:postcode":"yo25 8ag",
    "addr:street":"Land;Dringhoe",
    "iso:country":"GB",
    "sg:address":"Happy Land Farm, Dringhoe",
    "sg:city":"Driffield",
    "sg:classifiers":[
        {
            "category":"Farming",
            "subcategory":"Farm",
            "type":"Manufacturing & Wholesale Goods"
        }
    ],
    "sg:phone":"+44 1262 468303",
    "sg:postcode":"YO25 8AG",
    "sg:province":"East Riding of Yorkshire",
    "sg:tags":[
        "mixed",
        "crop"
    ],
    "wof:name":"Nigel D & Philippa Jane Robinson",
    "wof:placetype":"venue"
},
  "geometry": {"coordinates":[-0.245134,53.976154],"type":"Point"}
}