{
  "type": "Feature",
  "properties": {
    "addr:full":"Speedwell Avenue Chatham Kent ME5 0QG",
    "addr:postcode":"me5 0qg",
    "addr:street":"Speedwell Avenue",
    "iso:country":"GB",
    "sg:address":"Speedwell Avenue",
    "sg:city":"Chatham",
    "sg:classifiers":[
        {
            "category":"Retail",
            "subcategory":"Auto Repair",
            "type":"Services"
        }
    ],
    "sg:postcode":"ME5 0QG",
    "sg:province":"Kent",
    "sg:tags":[
        "modification",
        "garage"
    ],
    "wof:name":"Medway Auto (Mobile)",
    "wof:placetype":"venue"
},
  "geometry": {"coordinates":[0.5173699856,51.3453598022],"type":"Point"}
}