{
  "type": "Feature",
  "properties": {
    "addr:full":"83 London Road Hailsham East Sussex BN27 3DD",
    "addr:housenumber":"83",
    "addr:postcode":"bn27 3dd",
    "addr:street":"London Road",
    "iso:country":"GB",
    "sg:address":"83 London Road",
    "sg:city":"Hailsham",
    "sg:classifiers":[
        {
            "category":"Building & Trades",
            "subcategory":"Construction",
            "type":"Services"
        },
        {
            "category":"Manufacturing",
            "subcategory":"Paper Products",
            "type":"Manufacturing & Wholesale Goods"
        }
    ],
    "sg:postcode":"BN27 3DD",
    "sg:province":"East Sussex",
    "sg:tags":[
        "cardboard",
        "decorator",
        "painter"
    ],
    "wof:name":"Reginald Drewry",
    "wof:placetype":"venue"
},
  "geometry": {"coordinates":[0.25045,50.869686],"type":"Point"}
}