{
  "type": "Feature",
  "properties": {
    "addr:full":"Old Forge Garage, White Apron Street, South Kirkby Pontefract West Yorkshire WF9 3HQ",
    "addr:postcode":"wf9 3hq",
    "addr:street":"Apron Street South;West",
    "iso:country":"GB",
    "sg:address":"Old Forge Garage, White Apron Street, South Kirkby",
    "sg:city":"Pontefract",
    "sg:classifiers":[
        {
            "category":"Bus Charters",
            "type":"Transportation"
        }
    ],
    "sg:phone":"+44 1977 644777",
    "sg:postcode":"WF9 3HQ",
    "sg:province":"West Yorkshire",
    "sg:tags":[
        "hire",
        "coach"
    ],
    "wof:name":"Brown's Coaches (South Kirkby) Ltd.",
    "wof:placetype":"venue"
},
  "geometry": {"coordinates":[-1.312568,53.594608],"type":"Point"}
}