{
  "type": "Feature",
  "properties": {
    "iso:country":"GB",
    "sg:address":"Crayford Close, Beckton",
    "sg:city":"East Ham",
    "sg:classifiers":[
        {
            "category":"Professional",
            "subcategory":"Management & Consulting",
            "type":"Services"
        }
    ],
    "sg:phone":"+44 20 7474 0262",
    "sg:postcode":"E6 5SS",
    "sg:province":"Greater London",
    "sg:tags":[
        "consultant",
        "specialist"
    ],
    "wof:name":"Basic Beauty",
    "wof:placetype":"venue"
},
  "geometry": {"coordinates":[0.045245,51.514599],"type":"Point"}
}