{
  "type": "Feature",
  "properties": {
    "addr:full":"Second Floor, Ormiston House Nottingham Nottinghamshire NG1 2EG",
    "addr:housenumber":"second",
    "addr:postcode":"ng1 2eg",
    "iso:country":"GB",
    "sg:address":"Second Floor, Ormiston House",
    "sg:city":"Nottingham",
    "sg:classifiers":[
        {
            "category":"Organizations",
            "subcategory":"Non-profit Organization",
            "type":"Services"
        }
    ],
    "sg:phone":"+44 115 911 1662",
    "sg:postcode":"NG1 2EG",
    "sg:province":"Nottinghamshire",
    "sg:tags":[
        "organisation",
        "voluntary",
        "charity"
    ],
    "wof:name":"Self Help Nottingham",
    "wof:placetype":"venue"
},
  "geometry": {"coordinates":[-1.143924,52.949226],"type":"Point"}
}