{
  "type": "Feature",
  "properties": {
    "iso:country":"GB",
    "sg:address":"Richmoorhill Farm, Richmoor Hill",
    "sg:city":"Stoke-on-trent",
    "sg:classifiers":[
        {
            "category":"Retail",
            "subcategory":"Auto Repair",
            "type":"Services"
        }
    ],
    "sg:phone":"+44 1782 550070",
    "sg:postcode":"ST10 2PR",
    "sg:province":"Staffordshire",
    "sg:tags":[
        "modification",
        "garage"
    ],
    "wof:name":"Bagnall Motors",
    "wof:placetype":"venue"
},
  "geometry": {"coordinates":[-2.1750690937,53.0293693542],"type":"Point"}
}