{
  "type": "Feature",
  "properties": {
    "addr:full":"Dobies Business Park, Lillyhall Industrial Estate, Lillyhall Workington Cumbria CA14 4HX",
    "addr:postcode":"ca14 4hx",
    "addr:street":"Business Park Lillyhall Industrial Estate",
    "iso:country":"GB",
    "sg:address":"Dobies Business Park, Lillyhall Industrial Estate, Lillyhall",
    "sg:city":"Workington",
    "sg:classifiers":[
        {
            "category":"Autos & Motor Vehicles",
            "subcategory":"Automobile Sales",
            "type":"Retail Goods"
        }
    ],
    "sg:phone":"+44 1900 871234",
    "sg:postcode":"CA14 4HX",
    "sg:province":"Cumbria",
    "sg:tags":[
        "car"
    ],
    "wof:name":"Dobies Peugeot",
    "wof:placetype":"venue"
},
  "geometry": {"coordinates":[-3.526602,54.609421],"type":"Point"}
}