{
  "type": "Feature",
  "properties": {
    "addr:full":"203 Kings Road London Greater London SW3 5ED",
    "addr:housenumber":"203",
    "addr:postcode":"sw3 5ed",
    "addr:street":"Kings Road",
    "iso:country":"GB",
    "sg:address":"203 Kings Road",
    "sg:city":"London",
    "sg:classifiers":[
        {
            "category":"Real Estate",
            "subcategory":"Real Estate Agent",
            "type":"Services"
        }
    ],
    "sg:phone":"+44 20 8398 8550",
    "sg:postcode":"SW3 5ED",
    "sg:province":"Greater London",
    "wof:name":"Waterview (Waterside Property)",
    "wof:placetype":"venue"
},
  "geometry": {"coordinates":[-0.1695860028,51.4869804382],"type":"Point"}
}