{
  "type": "Feature",
  "properties": {
    "addr:full":"85 Walmgate York North Yorkshire YO1 2UA",
    "addr:housenumber":"85",
    "addr:postcode":"yo1 2ua",
    "addr:street":"Walmgate York",
    "iso:country":"GB",
    "sg:address":"85 Walmgate",
    "sg:city":"York",
    "sg:classifiers":[
        {
            "category":"Food & Beverages",
            "subcategory":"Groceries & Convenience Stores",
            "type":"Retail Goods"
        }
    ],
    "sg:phone":"+44 1904 651482",
    "sg:postcode":"YO1 2UA",
    "sg:province":"North Yorkshire",
    "wof:name":"Dillons",
    "wof:placetype":"venue"
},
  "geometry": {"coordinates":[-1.073217,53.956017],"type":"Point"}
}