{
  "type": "Feature",
  "properties": {
    "addr:full":"71 Sutton Road, Terrington St Clement King's Lynn Lincolnshire PE34 4PJ",
    "addr:housenumber":"71",
    "addr:postcode":"pe34 4pj",
    "addr:street":"Sutton Road",
    "iso:country":"GB",
    "sg:address":"71 Sutton Road, Terrington St Clement",
    "sg:city":"King's Lynn",
    "sg:classifiers":[
        {
            "category":"Personal",
            "subcategory":"Beauty Salon",
            "type":"Services"
        }
    ],
    "sg:phone":"+44 1553 828252",
    "sg:postcode":"PE34 4PJ",
    "sg:province":"Lincolnshire",
    "sg:tags":[
        "unisex",
        "hairdresser"
    ],
    "wof:name":"Country Stylers",
    "wof:placetype":"venue"
},
  "geometry": {"coordinates":[0.2871200144,52.7542381287],"type":"Point"}
}