{
  "type": "Feature",
  "properties": {
    "addr:full":"47 Ayr Street Troon South Ayrshire KA10 6EB",
    "addr:housenumber":"47",
    "addr:postcode":"ka10 6eb",
    "addr:street":"Ayr Street",
    "iso:country":"GB",
    "sg:address":"47 Ayr Street",
    "sg:city":"Troon",
    "sg:classifiers":[
        {
            "category":"Shopping",
            "subcategory":"Antiques",
            "type":"Retail Goods"
        }
    ],
    "sg:postcode":"KA10 6EB",
    "sg:province":"South Ayrshire",
    "wof:name":"Commission Antiques & Gallery",
    "wof:placetype":"venue"
},
  "geometry": {"coordinates":[-4.662765,55.543243],"type":"Point"}
}