{
  "type": "Feature",
  "properties": {
    "addr:full":"39 High St Cardigan Ceredigion SA43 1HE",
    "addr:housenumber":"39",
    "addr:postcode":"sa43 1he",
    "addr:street":"High St",
    "iso:country":"GB",
    "sg:address":"39 High St",
    "sg:city":"Cardigan",
    "sg:classifiers":[
        {
            "category":"Travel",
            "subcategory":"Travel Agent",
            "type":"Entertainment"
        }
    ],
    "sg:phone":"+44 1239 621621",
    "sg:postcode":"SA43 1HE",
    "sg:province":"Ceredigion",
    "wof:name":"Global Travel",
    "wof:placetype":"venue"
},
  "geometry": {"coordinates":[-4.6611680984,52.0818901062],"type":"Point"}
}