{
  "type": "Feature",
  "properties": {
    "addr:full":"99 Magdalen Way, Gorleston Great Yarmouth Norfolk NR31 7AA",
    "addr:housenumber":"99",
    "addr:postcode":"nr31 7aa",
    "addr:street":"Magdalen Way",
    "iso:country":"GB",
    "sg:address":"99 Magdalen Way, Gorleston",
    "sg:city":"Great Yarmouth",
    "sg:classifiers":[
        {
            "category":"Food & Beverages",
            "subcategory":"Bakery",
            "type":"Retail Goods"
        }
    ],
    "sg:phone":"+44 1493 663817",
    "sg:postcode":"NR31 7AA",
    "sg:province":"Norfolk",
    "sg:tags":[
        "shop",
        "baker"
    ],
    "wof:name":"Bushell's Bakery",
    "wof:placetype":"venue"
},
  "geometry": {"coordinates":[1.714563,52.573357],"type":"Point"}
}