{
  "type": "Feature",
  "properties": {
    "iso:country":"GB",
    "sg:address":"Brickbarns Farm, Evesham Road, Egdon",
    "sg:city":"Worcester",
    "sg:classifiers":[
        {
            "category":"Building & Trades",
            "subcategory":"Cleaning & Sanitation",
            "type":"Services"
        }
    ],
    "sg:phone":"+44 1905 345821",
    "sg:postcode":"WR7 4QR",
    "sg:province":"Worcestershire",
    "sg:tags":[
        "toilet",
        "portable"
    ],
    "wof:name":"Andy Loos Ltd.",
    "wof:placetype":"venue"
},
  "geometry": {"coordinates":[-2.1222670078,52.1606483459],"type":"Point"}
}