{
  "type": "Feature",
  "properties": {
    "iso:country":"GB",
    "sg:address":"26-40 English Street",
    "sg:city":"Carlisle",
    "sg:classifiers":[
        {
            "category":"Shopping",
            "subcategory":"Shoes",
            "type":"Retail Goods"
        }
    ],
    "sg:phone":"+44 1228 810512",
    "sg:postcode":"CA3 8HU",
    "sg:province":"Cumbria",
    "sg:tags":[
        "shop"
    ],
    "wof:name":"Shoe Studio",
    "wof:placetype":"venue"
},
  "geometry": {"coordinates":[-2.935622,54.894058],"type":"Point"}
}