{
  "type": "Feature",
  "properties": {
    "addr:full":"10 New Causeway, Woodhatch Reigate Surrey RH2 7NX",
    "addr:housenumber":"10",
    "addr:postcode":"rh2 7nx",
    "addr:street":"New Causeway Woodhatch",
    "iso:country":"GB",
    "sg:address":"10 New Causeway, Woodhatch",
    "sg:city":"Reigate",
    "sg:classifiers":[
        {
            "category":"Building & Trades",
            "subcategory":"Construction",
            "type":"Services"
        }
    ],
    "sg:phone":"+44 1737 242381",
    "sg:postcode":"RH2 7NX",
    "sg:province":"Surrey",
    "sg:tags":[
        "decorator",
        "painter"
    ],
    "wof:name":"Kenneth Bellinger",
    "wof:placetype":"venue"
},
  "geometry": {"coordinates":[-0.1978210062,51.2227058411],"type":"Point"}
}