{
  "type": "Feature",
  "properties": {
    "addr:full":"227a Stanley Road Bootle Merseyside L20 3DY",
    "addr:housenumber":"227a",
    "addr:postcode":"l20 3dy",
    "addr:street":"Stanley Road",
    "iso:country":"GB",
    "sg:address":"227a Stanley Road",
    "sg:city":"Bootle",
    "sg:classifiers":[
        {
            "category":"Education",
            "subcategory":"Special Training",
            "type":"Public Place"
        }
    ],
    "sg:phone":"+44 151 922 9222",
    "sg:postcode":"L20 3DY",
    "sg:province":"Merseyside",
    "sg:tags":[
        "product",
        "centre"
    ],
    "wof:name":"Dhp",
    "wof:placetype":"venue"
},
  "geometry": {"coordinates":[-2.990407,53.449894],"type":"Point"}
}