{
  "type": "Feature",
  "properties": {
    "addr:full":"Flat 14 Westminster House, Hallam Close Watford Hertfordshire WD1 1AW",
    "addr:housenumber":"flat 14",
    "addr:postcode":"wd1 1aw",
    "addr:street":"Westminster;Hallam Close",
    "iso:country":"GB",
    "sg:address":"Flat 14 Westminster House, Hallam Close",
    "sg:city":"Watford",
    "sg:classifiers":[
        {
            "category":"Professional",
            "subcategory":"Computer Services",
            "type":"Services"
        }
    ],
    "sg:postcode":"WD1 1AW",
    "sg:province":"Hertfordshire",
    "sg:tags":[
        "system",
        "software"
    ],
    "wof:name":"Shumputing Ltd",
    "wof:placetype":"venue"
},
  "geometry": {"coordinates":[-0.39072,51.652119],"type":"Point"}
}