{
  "type": "Feature",
  "properties": {
    "addr:full":"1 Creffield Road London Greater London W5 3HP",
    "addr:housenumber":"1",
    "addr:postcode":"w5 3hp",
    "addr:street":"Creffield Road",
    "iso:country":"GB",
    "sg:address":"1 Creffield Road",
    "sg:city":"London",
    "sg:classifiers":[
        {
            "category":"Professional",
            "subcategory":"Business Services",
            "type":"Services"
        }
    ],
    "sg:phone":"+44 20 8992 0609",
    "sg:postcode":"W5 3HP",
    "sg:province":"Greater London",
    "sg:tags":[
        "import",
        "export",
        "agent"
    ],
    "wof:name":"Cengreen International Ltd.",
    "wof:placetype":"venue"
},
  "geometry": {"coordinates":[-0.2912839949,51.511882782],"type":"Point"}
}