{
  "type": "Feature",
  "properties": {
    "iso:country":"GB",
    "sg:address":"12 York Gate",
    "sg:city":"London",
    "sg:classifiers":[
        {
            "category":"Shopping",
            "subcategory":"Clothing, Apparel, & Fashions",
            "type":"Retail Goods"
        }
    ],
    "sg:postcode":"NW1 4QS",
    "sg:province":"Greater London",
    "sg:tags":[
        "clothing"
    ],
    "wof:name":"Interlanche Ltd",
    "wof:placetype":"venue"
},
  "geometry": {"coordinates":[-0.15284,51.523335],"type":"Point"}
}