{
  "type": "Feature",
  "properties": {
    "iso:country":"GB",
    "sg:address":"100 Turton Road",
    "sg:city":"Bolton",
    "sg:classifiers":[
        {
            "category":"Personal",
            "subcategory":"Beauty Salon",
            "type":"Services"
        }
    ],
    "sg:postcode":"BL2 3DY",
    "sg:province":"Lancashire",
    "sg:tags":[
        "unisex",
        "hairdresser"
    ],
    "wof:name":"Lock 'N' Roll",
    "wof:placetype":"venue"
},
  "geometry": {"coordinates":[-2.4071700573,53.6059799194],"type":"Point"}
}