{
  "type": "Feature",
  "properties": {
    "iso:country":"GB",
    "sg:address":"38 Hawthorn Road",
    "sg:city":"Kettering",
    "sg:classifiers":[
        {
            "category":"Personal",
            "subcategory":"Beauty Salon",
            "type":"Services"
        }
    ],
    "sg:postcode":"NN15 7HS",
    "sg:province":"Northamptonshire",
    "sg:tags":[
        "unisex",
        "hairdresser"
    ],
    "wof:name":"Joe's Unisex Salon",
    "wof:placetype":"venue"
},
  "geometry": {"coordinates":[-0.723021,52.392082],"type":"Point"}
}