{
  "type": "Feature",
  "properties": {
    "addr:full":"3-5 Cavendish Rd Leeds West Yorkshire LS1 3EN",
    "addr:housenumber":"3-5",
    "addr:postcode":"ls1 3en",
    "addr:street":"Cavendish Rd",
    "iso:country":"GB",
    "sg:address":"3-5 Cavendish Rd",
    "sg:city":"Leeds",
    "sg:classifiers":[
        {
            "category":"Health Services",
            "subcategory":"Clinic",
            "type":"Services"
        }
    ],
    "sg:phone":"+44 113 246 9911",
    "sg:postcode":"LS1 3EN",
    "sg:province":"West Yorkshire",
    "sg:tags":[
        "nh"
    ],
    "wof:name":"Leeds Student Medical Practice",
    "wof:placetype":"venue"
},
  "geometry": {"coordinates":[-1.552732,53.80632],"type":"Point"}
}