{
  "type": "Feature",
  "properties": {
    "addr:full":"28 Western Road Lewes East Sussex BN7 1RP",
    "addr:housenumber":"28",
    "addr:postcode":"bn7 1rp",
    "addr:street":"Western Road",
    "iso:country":"GB",
    "sg:address":"28 Western Road",
    "sg:city":"Lewes",
    "sg:classifiers":[
        {
            "category":"Personal",
            "subcategory":"Barber",
            "type":"Services"
        }
    ],
    "sg:postcode":"BN7 1RP",
    "sg:province":"East Sussex",
    "sg:tags":[
        "men's",
        "hairdresser"
    ],
    "wof:name":"Short & Curlies",
    "wof:placetype":"venue"
},
  "geometry": {"coordinates":[-0.000031,50.872826],"type":"Point"}
}