{
  "type": "Feature",
  "properties": {
    "iso:country":"GB",
    "sg:address":"Douglas Road Industrial Park, Douglas Road",
    "sg:city":"Bristol",
    "sg:classifiers":[
        {
            "category":"Professional",
            "subcategory":"Printing & Photocopies",
            "type":"Services"
        }
    ],
    "sg:phone":"+44 117 377 6216",
    "sg:postcode":"BS15 8PD",
    "sg:province":"City of Bristol",
    "sg:tags":[
        "printer"
    ],
    "wof:name":"Docuplus Document Solutions Ltd.",
    "wof:placetype":"venue"
},
  "geometry": {"coordinates":[-2.509944,51.457825],"type":"Point"}
}