{
  "type": "Feature",
  "properties": {
    "iso:country":"GB",
    "sg:address":"134-138 Twyford Rd",
    "sg:city":"Eastleigh",
    "sg:classifiers":[
        {
            "category":"Autos & Motor Vehicles",
            "subcategory":"Fuel & Gas Station",
            "type":"Retail Goods"
        }
    ],
    "sg:postcode":"SO504HP",
    "sg:province":"Devon",
    "sg:tags":[
        "petrol",
        "filling"
    ],
    "wof:name":"Eastleigh Express",
    "wof:placetype":"venue"
},
  "geometry": {"coordinates":[-1.349323,50.979073],"type":"Point"}
}