{
  "type": "Feature",
  "properties": {
    "iso:country":"GB",
    "sg:address":"107 Moat Street",
    "sg:city":"Wigston",
    "sg:classifiers":[
        {
            "category":"Social Services",
            "subcategory":"Child Care",
            "type":"Services"
        }
    ],
    "sg:phone":"+44 116 288 9709",
    "sg:postcode":"LE18 2GE",
    "sg:province":"Leicestershire",
    "sg:tags":[
        "children's",
        "home"
    ],
    "wof:name":"Littlehill House Children's Home",
    "wof:placetype":"venue"
},
  "geometry": {"coordinates":[-1.103577,52.581421],"type":"Point"}
}