{
  "type": "Feature",
  "properties": {
    "iso:country":"GB",
    "sg:address":"104 Duke St",
    "sg:city":"Whitehaven",
    "sg:classifiers":[
        {
            "category":"Bars & Pubs",
            "type":"Food & Drink"
        }
    ],
    "sg:phone":"+44 1946 692796",
    "sg:postcode":"CA28 7EL",
    "sg:province":"Cumbria",
    "sg:tags":[
        "pubs",
        "inn"
    ],
    "wof:name":"Brown,Matthew (Brewey)",
    "wof:placetype":"venue"
},
  "geometry": {"coordinates":[-3.588305,54.549568],"type":"Point"}
}