{
  "type": "Feature",
  "properties": {
    "addr:full":"89 Poole Road, Westbourne Bournemouth Dorset BH4 9BB",
    "addr:housenumber":"89",
    "addr:postcode":"bh4 9bb",
    "addr:street":"Poole Road",
    "iso:country":"GB",
    "sg:address":"89 Poole Road, Westbourne",
    "sg:city":"Bournemouth",
    "sg:classifiers":[
        {
            "category":"Shopping",
            "subcategory":"Optician",
            "type":"Retail Goods"
        }
    ],
    "sg:phone":"+44 1202 764545",
    "sg:postcode":"BH4 9BB",
    "sg:province":"Dorset",
    "wof:name":"Melson Wingate",
    "wof:placetype":"venue"
},
  "geometry": {"coordinates":[-1.903763,50.723064],"type":"Point"}
}