{
  "type": "Feature",
  "properties": {
    "addr:full":"Moat Farm, Alcaston Church Stretton Shropshire SY6 6RP",
    "addr:housenumber":"alcaston",
    "addr:postcode":"sy6 6rp",
    "addr:street":"Moat",
    "iso:country":"GB",
    "sg:address":"Moat Farm, Alcaston",
    "sg:city":"Church Stretton",
    "sg:classifiers":[
        {
            "category":"Farming",
            "subcategory":"Farm",
            "type":"Manufacturing & Wholesale Goods"
        }
    ],
    "sg:phone":"+44 1694 781252",
    "sg:postcode":"SY6 6RP",
    "sg:province":"Shropshire",
    "sg:tags":[
        "mixed",
        "crop"
    ],
    "wof:name":"Peter Sagar",
    "wof:placetype":"venue"
},
  "geometry": {"coordinates":[-2.8007800579,52.479347229],"type":"Point"}
}