{
  "type": "Feature",
  "properties": {
    "iso:country":"GB",
    "sg:address":"Unit 1-2 Myrtlefield, Grampian Road",
    "sg:city":"Aviemore",
    "sg:classifiers":[
        {
            "category":"Retail",
            "subcategory":"Laundry & Dry Cleaning",
            "type":"Services"
        }
    ],
    "sg:phone":"+44 1479 810462",
    "sg:postcode":"PH22 1PT",
    "sg:province":"Highland",
    "sg:tags":[
        "launderette"
    ],
    "wof:name":"Aviemore Laundry & Dry Cleaning",
    "wof:placetype":"venue"
},
  "geometry": {"coordinates":[-3.8284380436,57.1931343079],"type":"Point"}
}