{
  "type": "Feature",
  "properties": {
    "iso:country":"GB",
    "sg:address":"32 St Johns Road",
    "sg:city":"Tunbridge Wells",
    "sg:classifiers":[
        {
            "category":"Professional",
            "subcategory":"Accounting & Tax Preparation",
            "type":"Services"
        }
    ],
    "sg:postcode":"TN4 9NT",
    "sg:province":"Kent",
    "sg:tags":[
        "accountant"
    ],
    "wof:name":"Perrys",
    "wof:placetype":"venue"
},
  "geometry": {"coordinates":[0.261665,51.138317],"type":"Point"}
}