{
  "type": "Feature",
  "properties": {
    "addr:full":"263 Wickersley Rd Rotherham South Yorkshire S60 4JS",
    "addr:housenumber":"263",
    "addr:postcode":"s60 4js",
    "addr:street":"Wickersley Rd",
    "iso:country":"GB",
    "sg:address":"263 Wickersley Rd",
    "sg:city":"Rotherham",
    "sg:classifiers":[
        {
            "category":"Personal",
            "subcategory":"Beauty Salon",
            "type":"Services"
        }
    ],
    "sg:postcode":"S60 4JS",
    "sg:province":"South Yorkshire",
    "sg:tags":[
        "unisex",
        "hairdresser"
    ],
    "wof:name":"Rogers,Debbie,",
    "wof:placetype":"venue"
},
  "geometry": {"coordinates":[-1.3098260164,53.4194068909],"type":"Point"}
}