{
  "type": "Feature",
  "properties": {
    "iso:country":"GB",
    "sg:address":"39 Jones Road, Goffs Oak",
    "sg:city":"Waltham Cross",
    "sg:classifiers":[
        {
            "category":"Professional",
            "subcategory":"Engineering",
            "type":"Services"
        }
    ],
    "sg:postcode":"EN7 5JT",
    "sg:province":"Greater London",
    "sg:tags":[
        "contractor",
        "electrical",
        "engineer"
    ],
    "wof:name":"Clermont Electrical Engineers & Contractors",
    "wof:placetype":"venue"
},
  "geometry": {"coordinates":[-0.092264,51.707123],"type":"Point"}
}