{
  "type": "Feature",
  "properties": {
    "addr:full":"Memorial Hall, Dittons Rd, Stone Cross Pevensey East Sussex BN24 5EL",
    "addr:postcode":"bn24 5el",
    "addr:street":"Dittons Rd",
    "iso:country":"GB",
    "sg:address":"Memorial Hall, Dittons Rd, Stone Cross",
    "sg:city":"Pevensey",
    "sg:classifiers":[
        {
            "category":"Education",
            "subcategory":"Preschool",
            "type":"Public Place"
        }
    ],
    "sg:phone":"+44 1323 740149",
    "sg:postcode":"BN24 5EL",
    "sg:province":"East Sussex",
    "sg:tags":[
        "pre-school",
        "playgroups"
    ],
    "wof:name":"Stone Cross Independent Pre-school",
    "wof:placetype":"venue"
},
  "geometry": {"coordinates":[0.3407459855,50.8211021423],"type":"Point"}
}