{
  "type": "Feature",
  "properties": {
    "addr:full":"69-71 Bondway London Greater London SW8 1SQ",
    "addr:housenumber":"69-71",
    "addr:postcode":"sw8 1sq",
    "addr:street":"Bondway",
    "iso:country":"GB",
    "sg:address":"69-71 Bondway",
    "sg:city":"London",
    "sg:classifiers":[
        {
            "category":"Professional",
            "subcategory":"Accounting & Tax Preparation",
            "type":"Services"
        },
        {
            "category":"Conference Center",
            "type":"Public Place"
        }
    ],
    "sg:phone":"+44 20 7735 6665",
    "sg:postcode":"SW8 1SQ",
    "sg:province":"Greater London",
    "sg:tags":[
        "accountant"
    ],
    "wof:name":"Spurrier & Co",
    "wof:placetype":"venue"
},
  "geometry": {"coordinates":[-0.12507,51.48362],"type":"Point"}
}