{
  "type": "Feature",
  "properties": {
    "addr:full":"621 Chesterfield Road Sheffield Derbyshire S8 0RX",
    "addr:housenumber":"621",
    "addr:postcode":"s8 0rx",
    "addr:street":"Chesterfield Road",
    "iso:country":"GB",
    "sg:address":"621 Chesterfield Road",
    "sg:city":"Sheffield",
    "sg:classifiers":[
        {
            "category":"Manufacturing",
            "subcategory":"Tools & Machinery",
            "type":"Manufacturing & Wholesale Goods"
        }
    ],
    "sg:phone":"+44 114 281 3035",
    "sg:postcode":"S8 0RX",
    "sg:province":"Derbyshire",
    "sg:tags":[
        "equipment",
        "builder"
    ],
    "wof:name":"Hallam Networks Ltd.",
    "wof:placetype":"venue"
},
  "geometry": {"coordinates":[-1.4786969423,53.3464393616],"type":"Point"}
}