{
  "type": "Feature",
  "properties": {
    "addr:full":"Scalm Park, Wistow Common Selby East Riding of Yorkshire YO8 3RD",
    "addr:postcode":"yo8 3rd",
    "addr:street":"Wistow Common Selby",
    "iso:country":"GB",
    "sg:address":"Scalm Park, Wistow Common",
    "sg:city":"Selby",
    "sg:classifiers":[
        {
            "category":"Farming",
            "subcategory":"Farm",
            "type":"Manufacturing & Wholesale Goods"
        }
    ],
    "sg:postcode":"YO8 3RD",
    "sg:province":"East Riding of Yorkshire",
    "sg:tags":[
        "mixed",
        "crop"
    ],
    "wof:name":"J C Lamb",
    "wof:placetype":"venue"
},
  "geometry": {"coordinates":[-1.135544,53.794487],"type":"Point"}
}