{
  "type": "Feature",
  "properties": {
    "addr:full":"Ladycross Business Pk, Hollow La, Dormansland Lingfield Surrey RH7 6PB",
    "addr:postcode":"rh7 6pb",
    "addr:street":"Pk Hollow La Dormansland",
    "iso:country":"GB",
    "sg:address":"Ladycross Business Pk, Hollow La, Dormansland",
    "sg:city":"Lingfield",
    "sg:classifiers":[
        {
            "category":"Retail",
            "subcategory":"Auto Repair",
            "type":"Services"
        }
    ],
    "sg:postcode":"RH7 6PB",
    "sg:province":"Surrey",
    "sg:tags":[
        "modification",
        "garage"
    ],
    "wof:name":"Slade,John,",
    "wof:placetype":"venue"
},
  "geometry": {"coordinates":[-0.019686,51.17482],"type":"Point"}
}