{
  "type": "Feature",
  "properties": {
    "addr:full":"24 Old Mill Square, Storrington Pulborough West Sussex RH20 4NQ",
    "addr:housenumber":"24",
    "addr:postcode":"rh20 4nq",
    "addr:street":"Old Mill Square Storrington",
    "iso:country":"GB",
    "sg:address":"24 Old Mill Square, Storrington",
    "sg:city":"Pulborough",
    "sg:classifiers":[
        {
            "category":"Health Services",
            "subcategory":"Doctor",
            "type":"Services"
        },
        {
            "category":"Health Services",
            "subcategory":"Hospital",
            "type":"Services"
        },
        {
            "category":"Health Services",
            "subcategory":"Clinic",
            "type":"Services"
        }
    ],
    "sg:phone":"+44 1903 741414",
    "sg:postcode":"RH20 4NQ",
    "sg:province":"West Sussex",
    "sg:tags":[
        "nh",
        "practitioners"
    ],
    "wof:name":"Old Mill Square Chanctonbury Community Mental Health Team",
    "wof:placetype":"venue"
},
  "geometry": {"coordinates":[-0.4525220096,50.9181365967],"type":"Point"}
}