{
  "type": "Feature",
  "properties": {
    "iso:country":"GB",
    "sg:address":"Oakfield House, 35 Perrymount Road",
    "sg:city":"Haywards Heath",
    "sg:classifiers":[
        {
            "category":"Professional",
            "subcategory":"Management & Consulting",
            "type":"Services"
        }
    ],
    "sg:phone":"+44 1444 450911",
    "sg:postcode":"RH16 3BW",
    "sg:province":"East Sussex",
    "sg:tags":[
        "marketing",
        "consultant"
    ],
    "wof:name":"Affinity Solutions Ltd.",
    "wof:placetype":"venue"
},
  "geometry": {"coordinates":[-0.104672,51.002045],"type":"Point"}
}