{
  "type": "Feature",
  "properties": {
    "addr:full":"37 York Street Sidmouth Devon EX10 8BY",
    "addr:housenumber":"37",
    "addr:postcode":"ex10 8by",
    "addr:street":"York Street",
    "iso:country":"GB",
    "sg:address":"37 York Street",
    "sg:city":"Sidmouth",
    "sg:classifiers":[
        {
            "category":"Bars & Pubs",
            "type":"Food & Drink"
        }
    ],
    "sg:postcode":"EX10 8BY",
    "sg:province":"Devon",
    "sg:tags":[
        "pubs",
        "inn"
    ],
    "wof:name":"The Swan Inn",
    "wof:placetype":"venue"
},
  "geometry": {"coordinates":[-3.236205101,50.6805038452],"type":"Point"}
}