{
  "type": "Feature",
  "properties": {
    "iso:country":"GB",
    "sg:address":"Hanover Works, Scotland St",
    "sg:city":"Sheffield",
    "sg:classifiers":[
        {
            "category":"Professional",
            "subcategory":"Management & Consulting",
            "type":"Services"
        }
    ],
    "sg:phone":"+44 114 249 3895",
    "sg:postcode":"S3 7DA",
    "sg:province":"South Yorkshire",
    "sg:tags":[
        "consultant",
        "promotion",
        "sale"
    ],
    "wof:name":"Advanzco Ltd",
    "wof:placetype":"venue"
},
  "geometry": {"coordinates":[-1.484209,53.380798],"type":"Point"}
}