{
  "type": "Feature",
  "properties": {
    "addr:full":"Walton House, 80 Chancery Lane, Off Great Moor Street Bolton Lancashire BL1 1NN",
    "addr:housenumber":"80",
    "addr:postcode":"bl1 1nn",
    "addr:street":"Chancery Lane Off Great Moor Street",
    "iso:country":"GB",
    "sg:address":"Walton House, 80 Chancery Lane, Off Great Moor Street",
    "sg:city":"Bolton",
    "sg:classifiers":[
        {
            "category":"Travel",
            "subcategory":"Travel Agent",
            "type":"Entertainment"
        }
    ],
    "sg:phone":"+44 1204 364747",
    "sg:postcode":"BL1 1NN",
    "sg:province":"Lancashire",
    "wof:name":"Paul A Lever",
    "wof:placetype":"venue"
},
  "geometry": {"coordinates":[-2.4277529716,53.5772094727],"type":"Point"}
}