{
  "type": "Feature",
  "properties": {
    "addr:full":"112 Grahams Road Falkirk Falkirk FK2 7BZ",
    "addr:housenumber":"112",
    "addr:postcode":"fk2 7bz",
    "addr:street":"Grahams Road",
    "iso:country":"GB",
    "sg:address":"112 Grahams Road",
    "sg:city":"Falkirk",
    "sg:classifiers":[
        {
            "category":"Professional",
            "subcategory":"Business Services",
            "type":"Services"
        }
    ],
    "sg:phone":"+44 1324 621354",
    "sg:postcode":"FK2 7BZ",
    "sg:province":"Falkirk",
    "sg:tags":[
        "hospitality",
        "corporate"
    ],
    "wof:name":"Hogg Robinson (Travel) Ltd.",
    "wof:placetype":"venue"
},
  "geometry": {"coordinates":[-3.784638,56.006516],"type":"Point"}
}