{
  "type": "Feature",
  "properties": {
    "addr:full":"4 North Mess Business Park, Lerwick Shetland Shetland Islands ZE1 0LZ",
    "addr:housenumber":"4",
    "addr:postcode":"ze1 0lz",
    "addr:street":"North Mess Business Park",
    "iso:country":"GB",
    "sg:address":"4 North Mess Business Park, Lerwick",
    "sg:city":"Shetland",
    "sg:classifiers":[
        {
            "category":"Real Estate",
            "subcategory":"Architect",
            "type":"Services"
        }
    ],
    "sg:phone":"+44 1595 694880",
    "sg:postcode":"ZE1 0LZ",
    "sg:province":"Shetland Islands",
    "sg:tags":[
        "architectural"
    ],
    "wof:name":"PETER JOHNSON PARTNERSHIP",
    "wof:placetype":"venue"
},
  "geometry": {"coordinates":[-1.1461319923,60.1590766907],"type":"Point"}
}