{
  "type": "Feature",
  "properties": {
    "iso:country":"GB",
    "sg:address":"Frenchmoor, West Tytherley",
    "sg:city":"Salisbury",
    "sg:classifiers":[
        {
            "category":"Manufacturing",
            "subcategory":"Buildings",
            "type":"Manufacturing & Wholesale Goods"
        }
    ],
    "sg:postcode":"SP5 1NU",
    "sg:province":"Dorset",
    "sg:tags":[
        "shed",
        "greenhouse"
    ],
    "wof:name":"Frenchmoor Garden Buildings",
    "wof:placetype":"venue"
},
  "geometry": {"coordinates":[-1.609949,51.066887],"type":"Point"}
}