{
  "type": "Feature",
  "properties": {
    "iso:country":"GB",
    "sg:address":"12 Princess Drive",
    "sg:city":"Colwyn Bay",
    "sg:classifiers":[
        {
            "category":"Shopping",
            "subcategory":"Department Store",
            "type":"Retail Goods"
        }
    ],
    "sg:postcode":"LL29 8LA",
    "sg:province":"Conwy",
    "wof:name":"T J's Discount",
    "wof:placetype":"venue"
},
  "geometry": {"coordinates":[-3.726953,53.296528],"type":"Point"}
}