{
  "type": "Feature",
  "properties": {
    "iso:country":"GB",
    "sg:address":"Bodmin Airfield, Cardinham",
    "sg:city":"Bodmin",
    "sg:classifiers":[
        {
            "category":"Education",
            "subcategory":"Special Training",
            "type":"Public Place"
        }
    ],
    "sg:phone":"+44 1208 821419",
    "sg:postcode":"PL30 4BU",
    "sg:province":"Cornwall",
    "sg:tags":[
        "school",
        "flying"
    ],
    "wof:name":"Cornwall Flying Club Ltd",
    "wof:placetype":"venue"
},
  "geometry": {"coordinates":[-4.647909,50.488785],"type":"Point"}
}