{
  "type": "Feature",
  "properties": {
    "addr:full":"2 Roydon Road Diss Norfolk IP22 4LN",
    "addr:housenumber":"2",
    "addr:postcode":"ip22 4ln",
    "addr:street":"Roydon Road",
    "iso:country":"GB",
    "sg:address":"2 Roydon Road",
    "sg:city":"Diss",
    "sg:classifiers":[
        {
            "category":"Professional",
            "subcategory":"Lawyer & Legal Services",
            "type":"Services"
        }
    ],
    "sg:phone":"+44 1379 643464",
    "sg:postcode":"IP22 4LN",
    "sg:province":"Norfolk",
    "sg:tags":[
        "solicitor"
    ],
    "wof:name":"Lloyd & Co.",
    "wof:placetype":"venue"
},
  "geometry": {"coordinates":[1.106134057,52.3778038025],"type":"Point"}
}