{
  "type": "Feature",
  "properties": {
    "iso:country":"GB",
    "sg:address":"39 Rake End, Uttoxeter Road",
    "sg:city":"Rugeley",
    "sg:classifiers":[
        {
            "category":"Wholesale",
            "subcategory":"Non-durable Goods",
            "type":"Manufacturing & Wholesale Goods"
        }
    ],
    "sg:postcode":"WS15 3RG",
    "sg:province":"Staffordshire",
    "sg:tags":[
        "carry",
        "cash"
    ],
    "wof:name":"Hodgerose Ltd.",
    "wof:placetype":"venue"
},
  "geometry": {"coordinates":[-1.8869290352,52.7632255554],"type":"Point"}
}