{
  "type": "Feature",
  "properties": {
    "addr:full":"Owl Wood Ascot Berkshire SL5 8PF",
    "addr:postcode":"sl5 8pf",
    "addr:street":"Owl Wood",
    "iso:country":"GB",
    "sg:address":"Owl Wood",
    "sg:city":"Ascot",
    "sg:classifiers":[
        {
            "category":"Banks & Credit Unions",
            "subcategory":"Financial Services",
            "type":"Services"
        }
    ],
    "sg:phone":"+44 1344 626167",
    "sg:postcode":"SL5 8PF",
    "sg:province":"Berkshire",
    "sg:tags":[
        "consultant",
        "pension"
    ],
    "wof:name":"Pearson Financial Services",
    "wof:placetype":"venue"
},
  "geometry": {"coordinates":[-0.686438,51.428268],"type":"Point"}
}