{
  "type": "Feature",
  "properties": {
    "addr:full":"252 Kirkdale Sydenham Greater London SE26 4NL",
    "addr:housenumber":"252",
    "addr:postcode":"se26 4nl",
    "addr:street":"Kirkdale Sydenham",
    "iso:country":"GB",
    "sg:address":"252 Kirkdale",
    "sg:city":"Sydenham",
    "sg:classifiers":[
        {
            "category":"Food & Beverages",
            "subcategory":"Fruits & Vegetables",
            "type":"Retail Goods"
        }
    ],
    "sg:phone":"+44 20 8778 3440",
    "sg:postcode":"SE26 4NL",
    "sg:province":"Greater London",
    "sg:tags":[
        "greengrocer"
    ],
    "wof:name":"Alhaja's Cabin",
    "wof:placetype":"venue"
},
  "geometry": {"coordinates":[-0.056596,51.427437],"type":"Point"}
}