{
  "type": "Feature",
  "properties": {
    "addr:full":"Dean Row Day Centre, Dean Row Rd Wilmslow Cheshire SK9 2HA",
    "addr:postcode":"sk9 2ha",
    "addr:street":"Dean Row;Dean Row Rd",
    "iso:country":"GB",
    "sg:address":"Dean Row Day Centre, Dean Row Rd",
    "sg:city":"Wilmslow",
    "sg:classifiers":[
        {
            "category":"Social Services",
            "subcategory":"Adult Care",
            "type":"Services"
        },
        {
            "category":"Organizations",
            "subcategory":"Community Association",
            "type":"Services"
        },
        {
            "category":"Government",
            "subcategory":"Office",
            "type":"Public Place"
        }
    ],
    "sg:phone":"+44 1625 539018",
    "sg:postcode":"SK9 2HA",
    "sg:province":"Cheshire",
    "sg:tags":[
        "associations",
        "centre",
        "housing",
        "co-operatives",
        "trust",
        "local",
        "day",
        "societies"
    ],
    "wof:name":"CHESHIRE COUNTY COUNCIL",
    "wof:placetype":"venue"
},
  "geometry": {"coordinates":[-2.2203249931,53.3388710022],"type":"Point"}
}