{
  "type": "Feature",
  "properties": {
    "iso:country":"GB",
    "sg:address":"15 Castle Street",
    "sg:city":"Tredegar",
    "sg:classifiers":[
        {
            "category":"Home & Garden",
            "subcategory":"Household Appliances",
            "type":"Retail Goods"
        }
    ],
    "sg:phone":"+44 1495 725891",
    "sg:postcode":"NP22 3DF",
    "sg:province":"Blaenau Gwent",
    "sg:tags":[
        "electrical"
    ],
    "wof:name":"Castle Retail & Repair",
    "wof:placetype":"venue"
},
  "geometry": {"coordinates":[-3.246445,51.772182],"type":"Point"}
}