{
  "type": "Feature",
  "properties": {
    "addr:full":"1 Hampton Court Pde, Hampton Ct East Molesey Greater London KT8 9HB",
    "addr:housenumber":"1",
    "addr:postcode":"kt8 9hb",
    "addr:street":"Hampton Court;Hampton Ct",
    "iso:country":"GB",
    "sg:address":"1 Hampton Court Pde, Hampton Ct",
    "sg:city":"East Molesey",
    "sg:classifiers":[
        {
            "category":"Cafe",
            "type":"Food & Drink"
        }
    ],
    "sg:phone":"+44 20 8941 7030",
    "sg:postcode":"KT8 9HB",
    "sg:province":"Greater London",
    "sg:tags":[
        "tea",
        "room"
    ],
    "wof:name":"Al-Wady Ltd",
    "wof:placetype":"venue"
},
  "geometry": {"coordinates":[-0.341735,51.405144],"type":"Point"}
}