{
  "type": "Feature",
  "properties": {
    "addr:full":"Seed Research Station Downham Market Cambridgeshire PE38 0AR",
    "addr:postcode":"pe38 0ar",
    "addr:street":"Downham Market",
    "iso:country":"GB",
    "sg:address":"Seed Research Station",
    "sg:city":"Downham Market",
    "sg:classifiers":[
        {
            "category":"Professional",
            "subcategory":"Business Services",
            "type":"Services"
        }
    ],
    "sg:phone":"+44 1366 383845",
    "sg:postcode":"PE38 0AR",
    "sg:province":"Cambridgeshire",
    "wof:name":"Downham Market Commercial Services",
    "wof:placetype":"venue"
},
  "geometry": {"coordinates":[0.31292,52.603531],"type":"Point"}
}