{
  "type": "Feature",
  "properties": {
    "iso:country":"GB",
    "sg:address":"Quantum House, 34 Tentercroft Street",
    "sg:city":"Lincoln",
    "sg:classifiers":[
        {
            "category":"Shopping",
            "subcategory":"Musical Instruments",
            "type":"Retail Goods"
        }
    ],
    "sg:phone":"+44 1522 528623",
    "sg:postcode":"LN5 7DB",
    "sg:province":"Lincolnshire",
    "sg:tags":[
        "music",
        "sheet"
    ],
    "wof:name":"Note Ability School of Music",
    "wof:placetype":"venue"
},
  "geometry": {"coordinates":[-0.540406,53.224934],"type":"Point"}
}