{
  "type": "Feature",
  "properties": {
    "addr:full":"64 Rider Close Sidcup Kent DA15 8TL",
    "addr:housenumber":"64",
    "addr:postcode":"da15 8tl",
    "addr:street":"Rider Close",
    "iso:country":"GB",
    "sg:address":"64 Rider Close",
    "sg:city":"Sidcup",
    "sg:classifiers":[
        {
            "category":"Organizations",
            "subcategory":"Community Association",
            "type":"Services"
        },
        {
            "category":"Organizations",
            "subcategory":"Membership Organization",
            "type":"Services"
        }
    ],
    "sg:phone":"+44 20 8859 7630",
    "sg:postcode":"DA15 8TL",
    "sg:province":"Kent",
    "sg:tags":[
        "club",
        "social"
    ],
    "wof:name":"Clifton Amateur Radio Society The",
    "wof:placetype":"venue"
},
  "geometry": {"coordinates":[0.0887380019,51.4501991272],"type":"Point"}
}