{
  "type": "Feature",
  "properties": {
    "iso:country":"GB",
    "sg:address":"Lodge Farm, Kineton",
    "sg:city":"Warwick",
    "sg:classifiers":[
        {
            "category":"Home & Garden",
            "subcategory":"Kitchen Supply",
            "type":"Retail Goods"
        }
    ],
    "sg:phone":"+44 1926 641224",
    "sg:postcode":"CV35 0JH",
    "sg:province":"Warwickshire",
    "sg:tags":[
        "measuring",
        "scale"
    ],
    "wof:name":"Tachograph Bureaux Ltd.",
    "wof:placetype":"venue"
},
  "geometry": {"coordinates":[-1.5106090307,52.1565742493],"type":"Point"}
}