{
  "type": "Feature",
  "properties": {
    "iso:country":"GB",
    "sg:address":"28 Millrise Rd, Milton",
    "sg:city":"Stoke On Trent",
    "sg:classifiers":[
        {
            "category":"Insurance",
            "subcategory":"Insurance Agent",
            "type":"Services"
        }
    ],
    "sg:phone":"+44 1782 545800",
    "sg:postcode":"ST2 7BW",
    "sg:province":"Staffordshire",
    "wof:name":"Speedy Insurance",
    "wof:placetype":"venue"
},
  "geometry": {"coordinates":[-2.141322,53.04974],"type":"Point"}
}