{
  "type": "Feature",
  "properties": {
    "addr:full":"68 Leighton Road, Southville Bristol City of Bristol BS3 1NU",
    "addr:housenumber":"68",
    "addr:postcode":"bs3 1nu",
    "addr:street":"Leighton Road",
    "iso:country":"GB",
    "sg:address":"68 Leighton Road, Southville",
    "sg:city":"Bristol",
    "sg:classifiers":[
        {
            "category":"Home & Garden",
            "subcategory":"Carpets & Floor Coverings",
            "type":"Retail Goods"
        }
    ],
    "sg:phone":"+44 1275 877017",
    "sg:postcode":"BS3 1NU",
    "sg:province":"City of Bristol",
    "sg:tags":[
        "cleaner",
        "upholstery"
    ],
    "wof:name":"Chem Dry Winterbourne",
    "wof:placetype":"venue"
},
  "geometry": {"coordinates":[-2.6070280075,51.4434661865],"type":"Point"}
}