{
  "type": "Feature",
  "properties": {
    "addr:full":"122 Park View Whitley Bay Northumberland NE26 3QN",
    "addr:housenumber":"122",
    "addr:postcode":"ne26 3qn",
    "addr:street":"Park View",
    "iso:country":"GB",
    "sg:address":"122 Park View",
    "sg:city":"Whitley Bay",
    "sg:classifiers":[
        {
            "category":"Personal",
            "subcategory":"Barber",
            "type":"Services"
        }
    ],
    "sg:phone":"+44 191 253 4743",
    "sg:postcode":"NE26 3QN",
    "sg:province":"Northumberland",
    "sg:tags":[
        "men's",
        "hairdresser"
    ],
    "wof:name":"Kutz Barbers Shop",
    "wof:placetype":"venue"
},
  "geometry": {"coordinates":[-1.450622,55.043011],"type":"Point"}
}