{
  "type": "Feature",
  "properties": {
    "addr:full":"Merevale House, Old Watling Street, Holly Lane Industrial Estate Atherstone Leicestershire CV9 2PA",
    "addr:postcode":"cv9 2pa",
    "addr:street":"Old Watling Street Holly Lane Industrial Estate",
    "iso:country":"GB",
    "sg:address":"Merevale House, Old Watling Street, Holly Lane Industrial Estate",
    "sg:city":"Atherstone",
    "sg:classifiers":[
        {
            "category":"Social Services",
            "subcategory":"Retirement Home",
            "type":"Services"
        }
    ],
    "sg:phone":"+44 1827 715537",
    "sg:postcode":"CV9 2PA",
    "sg:province":"Leicestershire",
    "sg:tags":[
        "care"
    ],
    "wof:name":"Mobile Care Services",
    "wof:placetype":"venue"
},
  "geometry": {"coordinates":[-1.555577,52.585381],"type":"Point"}
}