{
  "type": "Feature",
  "properties": {
    "iso:country":"GB",
    "sg:address":"2 Ross Street",
    "sg:city":"Tain",
    "sg:classifiers":[
        {
            "category":"Health Services",
            "subcategory":"Health Practitioner",
            "type":"Services"
        }
    ],
    "sg:postcode":"IV19 1BA",
    "sg:province":"Highland",
    "sg:tags":[
        "osteopath"
    ],
    "wof:name":"Tain Osteopathic Clinic",
    "wof:placetype":"venue"
},
  "geometry": {"coordinates":[-4.0526390076,57.8109703064],"type":"Point"}
}