{
  "type": "Feature",
  "properties": {
    "addr:full":"16 Bonnygate Cupar Fife KY15 4LE",
    "addr:housenumber":"16",
    "addr:postcode":"ky15 4le",
    "addr:street":"Bonnygate Cupar",
    "iso:country":"GB",
    "sg:address":"16 Bonnygate",
    "sg:city":"Cupar",
    "sg:classifiers":[
        {
            "category":"Food & Beverages",
            "subcategory":"Bakery",
            "type":"Retail Goods"
        }
    ],
    "sg:phone":"+44 1334 655714",
    "sg:postcode":"KY15 4LE",
    "sg:province":"Fife",
    "sg:tags":[
        "baker"
    ],
    "wof:name":"Strathdee City Bakeries",
    "wof:placetype":"venue"
},
  "geometry": {"coordinates":[-3.0121619701,56.3194694519],"type":"Point"}
}