{
  "type": "Feature",
  "properties": {
    "addr:full":"131-141 Northwalls Stafford Staffordshire ST16 3AD",
    "addr:housenumber":"131-141",
    "addr:postcode":"st16 3ad",
    "addr:street":"Northwalls",
    "iso:country":"GB",
    "sg:address":"131-141 Northwalls",
    "sg:city":"Stafford",
    "sg:classifiers":[
        {
            "category":"Organizations",
            "subcategory":"Non-profit Organization",
            "type":"Services"
        }
    ],
    "sg:phone":"+44 1785 606676",
    "sg:postcode":"ST16 3AD",
    "sg:province":"Staffordshire",
    "sg:tags":[
        "organisation",
        "voluntary",
        "charity"
    ],
    "wof:name":"Carers' National Association",
    "wof:placetype":"venue"
},
  "geometry": {"coordinates":[-2.112616,52.806911],"type":"Point"}
}