{
  "type": "Feature",
  "properties": {
    "addr:full":"6-8 High Street, Harlesden London Greater London NW10 4LX",
    "addr:housenumber":"6-8",
    "addr:postcode":"nw10 4lx",
    "addr:street":"High Street",
    "iso:country":"GB",
    "sg:address":"6-8 High Street, Harlesden",
    "sg:city":"London",
    "sg:classifiers":[
        {
            "category":"Fast Food",
            "type":"Food & Drink"
        }
    ],
    "sg:phone":"+44 20 8965 3785",
    "sg:postcode":"NW10 4LX",
    "sg:province":"Greater London",
    "sg:tags":[
        "away",
        "take"
    ],
    "wof:name":"McDonalds Restaurants Ltd.",
    "wof:placetype":"venue"
},
  "geometry": {"coordinates":[-0.2490179986,51.5372276306],"type":"Point"}
}