{
  "type": "Feature",
  "properties": {
    "addr:full":"3 Market Place Penzance Cornwall TR18 2JA",
    "addr:housenumber":"3",
    "addr:postcode":"tr18 2ja",
    "addr:street":"Market Place",
    "iso:country":"GB",
    "sg:address":"3 Market Place",
    "sg:city":"Penzance",
    "sg:classifiers":[
        {
            "category":"Food & Beverages",
            "subcategory":"Specialty",
            "type":"Retail Goods"
        }
    ],
    "sg:phone":"+44 1736 331855",
    "sg:postcode":"TR18 2JA",
    "sg:province":"Cornwall",
    "sg:tags":[
        "product",
        "health"
    ],
    "wof:name":"Holland & Barrett",
    "wof:placetype":"venue"
},
  "geometry": {"coordinates":[-5.5368189812,50.1189422607],"type":"Point"}
}