{
  "type": "Feature",
  "properties": {
    "iso:country":"GB",
    "sg:address":"10 Spindle Court, Chairborough Road",
    "sg:city":"High Wycombe",
    "sg:classifiers":[
        {
            "category":"Social Services",
            "subcategory":"Job Training",
            "type":"Services"
        }
    ],
    "sg:phone":"+44 1494 522525",
    "sg:postcode":"HP12 3EY",
    "sg:province":"Buckinghamshire",
    "sg:tags":[
        "translator",
        "interpreter"
    ],
    "wof:name":"Compusolute Languages",
    "wof:placetype":"venue"
},
  "geometry": {"coordinates":[-0.772112,51.631641],"type":"Point"}
}