{
  "type": "Feature",
  "properties": {
    "iso:country":"GB",
    "sg:address":"2 Wentworth Way",
    "sg:city":"Towcester",
    "sg:classifiers":[
        {
            "category":"Building & Trades",
            "subcategory":"Construction",
            "type":"Services"
        }
    ],
    "sg:postcode":"NN12 7SA",
    "sg:province":"Buckinghamshire",
    "sg:tags":[
        "builder"
    ],
    "wof:name":"John Chambers",
    "wof:placetype":"venue"
},
  "geometry": {"coordinates":[-0.920897,52.142799],"type":"Point"}
}