{
  "type": "Feature",
  "properties": {
    "addr:full":"Hurworth Moor Darlington Durham DL2 1QL",
    "addr:postcode":"dl2 1ql",
    "addr:street":"Hurworth Moor",
    "iso:country":"GB",
    "sg:address":"Hurworth Moor",
    "sg:city":"Darlington",
    "sg:classifiers":[
        {
            "category":"Retail",
            "subcategory":"Auto Repair",
            "type":"Services"
        }
    ],
    "sg:phone":"+44 1325 720498",
    "sg:postcode":"DL2 1QL",
    "sg:province":"Durham",
    "sg:tags":[
        "modification",
        "garage"
    ],
    "wof:name":"Skipbridge Garage",
    "wof:placetype":"venue"
},
  "geometry": {"coordinates":[-1.51747,54.495571],"type":"Point"}
}