{
  "type": "Feature",
  "properties": {
    "addr:full":"The Grange, Housley Park, Chapeltown Sheffield South Yorkshire S35 2UE",
    "addr:postcode":"s35 2ue",
    "addr:street":"Chapeltown",
    "iso:country":"GB",
    "sg:address":"The Grange, Housley Park, Chapeltown",
    "sg:city":"Sheffield",
    "sg:classifiers":[
        {
            "category":"Professional",
            "type":"Services"
        }
    ],
    "sg:phone":"+44 114 245 7434",
    "sg:postcode":"S35 2UE",
    "sg:province":"South Yorkshire",
    "sg:tags":[
        "caterer"
    ],
    "wof:name":"Nearnet Ltd",
    "wof:placetype":"venue"
},
  "geometry": {"coordinates":[-1.47046,53.46468],"type":"Point"}
}