{
  "type": "Feature",
  "properties": {
    "addr:full":"126-141 Westmoor Street London Greater London SE7 8NH",
    "addr:housenumber":"126-141",
    "addr:postcode":"se7 8nh",
    "addr:street":"Westmoor Street",
    "iso:country":"GB",
    "sg:address":"126-141 Westmoor Street",
    "sg:city":"London",
    "sg:classifiers":[
        {
            "category":"Home & Garden",
            "subcategory":"Furniture",
            "type":"Retail Goods"
        }
    ],
    "sg:phone":"+44 20 8853 4186",
    "sg:postcode":"SE7 8NH",
    "sg:province":"Greater London",
    "wof:name":"Altered Images",
    "wof:placetype":"venue"
},
  "geometry": {"coordinates":[0.037746001,51.4931564331],"type":"Point"}
}