{
  "type": "Feature",
  "properties": {
    "iso:country":"GB",
    "sg:address":"30 Dale Street, Milnrow",
    "sg:city":"Rochdale",
    "sg:classifiers":[
        {
            "category":"Professional",
            "subcategory":"Engineering",
            "type":"Services"
        },
        {
            "category":"Building & Trades",
            "subcategory":"Electrical",
            "type":"Services"
        }
    ],
    "sg:phone":"+44 1706 641341",
    "sg:postcode":"OL16 4HS",
    "sg:province":"Lancashire",
    "sg:tags":[
        "engineer",
        "electrician",
        "contractor"
    ],
    "wof:name":"GERRARD & THORNLEY LTD",
    "wof:placetype":"venue"
},
  "geometry": {"coordinates":[-2.111622,53.610451],"type":"Point"}
}