{
  "type": "Feature",
  "properties": {
    "addr:full":"Chester Court, 1677a High Street, Knowle Solihull Warwickshire B93 0LL",
    "addr:housenumber":"1677a",
    "addr:postcode":"b93 0ll",
    "addr:street":"High Street",
    "iso:country":"GB",
    "sg:address":"Chester Court, 1677a High Street, Knowle",
    "sg:city":"Solihull",
    "sg:classifiers":[
        {
            "category":"Real Estate",
            "subcategory":"Developer",
            "type":"Services"
        }
    ],
    "sg:phone":"+44 1564 771445",
    "sg:postcode":"B93 0LL",
    "sg:province":"Warwickshire",
    "sg:tags":[
        "property"
    ],
    "wof:name":"Chesterhouse Properties (2002) Ltd.",
    "wof:placetype":"venue"
},
  "geometry": {"coordinates":[-1.7347899675,52.3891830444],"type":"Point"}
}