{
  "type": "Feature",
  "properties": {
    "addr:full":"Suite 2 Quintana Gate, Bartholomew St East Exeter Devon EX4 3BH",
    "addr:housenumber":"suite 2",
    "addr:postcode":"ex4 3bh",
    "addr:street":"Quintana Gate Bartholomew St",
    "iso:country":"GB",
    "sg:address":"Suite 2 Quintana Gate, Bartholomew St East",
    "sg:city":"Exeter",
    "sg:classifiers":[
        {
            "category":"Professional",
            "subcategory":"Computer Services",
            "type":"Services"
        }
    ],
    "sg:phone":"+44 1392 432988",
    "sg:postcode":"EX4 3BH",
    "sg:province":"Devon",
    "sg:tags":[
        "information"
    ],
    "wof:name":"Exeter & District Community Health Council",
    "wof:placetype":"venue"
},
  "geometry": {"coordinates":[-3.535904,50.72271],"type":"Point"}
}