{
  "type": "Feature",
  "properties": {
    "addr:full":"Garrison St Marys Cornwall TR21 0JA",
    "addr:postcode":"tr21 0ja",
    "addr:street":"Garrison St",
    "iso:country":"GB",
    "sg:address":"Garrison",
    "sg:city":"St Marys",
    "sg:classifiers":[
        {
            "category":"Travel",
            "subcategory":"Hotels & Motels",
            "type":"Entertainment"
        }
    ],
    "sg:phone":"+44 1720 422317",
    "sg:postcode":"TR21 0JA",
    "sg:province":"Cornwall",
    "wof:name":"Star Castle Hotel",
    "wof:placetype":"venue"
},
  "geometry": {"coordinates":[-6.317941,49.9146],"type":"Point"}
}