{
  "type": "Feature",
  "properties": {
    "addr:full":"1 Alexandra Road, Six Bells Abertillery Blaenau Gwent NP13 2LG",
    "addr:housenumber":"1",
    "addr:postcode":"np13 2lg",
    "addr:street":"Alexandra Road;Gwent",
    "iso:country":"GB",
    "sg:address":"1 Alexandra Road, Six Bells",
    "sg:city":"Abertillery",
    "sg:classifiers":[
        {
            "category":"Food & Beverages",
            "subcategory":"Meat & Fish",
            "type":"Retail Goods"
        }
    ],
    "sg:postcode":"NP13 2LG",
    "sg:province":"Blaenau Gwent",
    "sg:tags":[
        "chip"
    ],
    "wof:name":"P A T",
    "wof:placetype":"venue"
},
  "geometry": {"coordinates":[-3.128225,51.721401],"type":"Point"}
}