{
  "type": "Feature",
  "properties": {
    "addr:full":"30 Sheppard Street Pontypridd Caerphilly CF37 1HT",
    "addr:housenumber":"30",
    "addr:postcode":"cf37 1ht",
    "addr:street":"Sheppard Street",
    "iso:country":"GB",
    "sg:address":"30 Sheppard Street",
    "sg:city":"Pontypridd",
    "sg:classifiers":[
        {
            "category":"Building & Trades",
            "subcategory":"Plumbing",
            "type":"Services"
        }
    ],
    "sg:phone":"+44 1443 491873",
    "sg:postcode":"CF37 1HT",
    "sg:province":"Caerphilly",
    "sg:tags":[
        "plumber",
        "heating"
    ],
    "wof:name":"D A Wescombe",
    "wof:placetype":"venue"
},
  "geometry": {"coordinates":[-3.3513669968,51.6037597656],"type":"Point"}
}