{
  "type": "Feature",
  "properties": {
    "iso:country":"GB",
    "sg:address":"18 Letchmore Rd",
    "sg:city":"Radlett",
    "sg:classifiers":[
        {
            "category":"Professional",
            "subcategory":"Lawyer & Legal Services",
            "type":"Services"
        }
    ],
    "sg:phone":"+44 1923 853358",
    "sg:postcode":"WD7 8HT",
    "sg:province":"Hertfordshire",
    "sg:tags":[
        "advice",
        "counselling"
    ],
    "wof:name":"Louise Amswych",
    "wof:placetype":"venue"
},
  "geometry": {"coordinates":[-0.321024,51.681362],"type":"Point"}
}