{
  "type": "Feature",
  "properties": {
    "addr:full":"30 London Road Edinburgh City of Edinburgh EH7 5BD",
    "addr:housenumber":"30",
    "addr:postcode":"eh7 5bd",
    "addr:street":"London Road",
    "iso:country":"GB",
    "sg:address":"30 London Road",
    "sg:city":"Edinburgh",
    "sg:classifiers":[
        {
            "category":"Banks & Credit Unions",
            "subcategory":"Bank",
            "type":"Services"
        }
    ],
    "sg:phone":"+44 131 661 8186",
    "sg:postcode":"EH7 5BD",
    "sg:province":"City of Edinburgh",
    "wof:name":"Lloyds T S B Bank Plc",
    "wof:placetype":"venue"
},
  "geometry": {"coordinates":[-3.169753,55.957436],"type":"Point"}
}