{
  "type": "Feature",
  "properties": {
    "addr:full":"Unit 2, Dodnor Lane, Dodnor Industrial Estate Newport Isle of Wight PO30 5QA",
    "addr:housenumber":"unit 2",
    "addr:postcode":"po30 5qa",
    "addr:street":"Dodnor Lane Dodnor Industrial Estate",
    "iso:country":"GB",
    "sg:address":"Unit 2, Dodnor Lane, Dodnor Industrial Estate",
    "sg:city":"Newport",
    "sg:classifiers":[
        {
            "category":"Shopping",
            "subcategory":"Party Supplies",
            "type":"Retail Goods"
        }
    ],
    "sg:postcode":"PO30 5QA",
    "sg:province":"Isle of Wight",
    "sg:tags":[
        "equipment",
        "disco"
    ],
    "wof:name":"Happy Daze",
    "wof:placetype":"venue"
},
  "geometry": {"coordinates":[-1.2979439497,50.7102050781],"type":"Point"}
}