{
  "type": "Feature",
  "properties": {
    "addr:full":"Unit 3 Felthambrook Way Feltham Greater London TW13 7DU",
    "addr:housenumber":"unit 3",
    "addr:postcode":"tw13 7du",
    "addr:street":"Felthambrook Way",
    "iso:country":"GB",
    "sg:address":"Unit 3 Felthambrook Way",
    "sg:city":"Feltham",
    "sg:classifiers":[
        {
            "category":"Freight",
            "type":"Transportation"
        }
    ],
    "sg:phone":"+44 20 8751 3176",
    "sg:postcode":"TW13 7DU",
    "sg:province":"Greater London",
    "sg:tags":[
        "overseas",
        "shipping",
        "removal"
    ],
    "wof:name":"Jag-Ocean & Freight Ltd.",
    "wof:placetype":"venue"
},
  "geometry": {"coordinates":[-0.405051,51.438339],"type":"Point"}
}