{
  "type": "Feature",
  "properties": {
    "addr:full":"Vicarage Road, Swinton Manchester Greater Manchester M27 0WA",
    "addr:postcode":"m27 0wa",
    "addr:street":"Vicarage Road",
    "iso:country":"GB",
    "sg:address":"Vicarage Road, Swinton",
    "sg:city":"Manchester",
    "sg:classifiers":[
        {
            "category":"Education",
            "subcategory":"School",
            "type":"Public Place"
        }
    ],
    "sg:phone":"+44 161 794 2616",
    "sg:postcode":"M27 0WA",
    "sg:province":"Greater Manchester",
    "sg:tags":[
        "local",
        "authority"
    ],
    "wof:name":"St Peters C of E Primary School",
    "wof:placetype":"venue"
},
  "geometry": {"coordinates":[-2.3422970772,53.5114517212],"type":"Point"}
}