{
  "type": "Feature",
  "properties": {
    "iso:country":"GB",
    "sg:address":"St Andrew House, 46-48 St Andrew Street",
    "sg:city":"Hertford",
    "sg:classifiers":[
        {
            "category":"Real Estate",
            "subcategory":"Architect",
            "type":"Services"
        }
    ],
    "sg:phone":"+44 1992 505588",
    "sg:postcode":"SG14 1JA",
    "sg:province":"Hertfordshire",
    "wof:name":"M K Scarborough-taylor",
    "wof:placetype":"venue"
},
  "geometry": {"coordinates":[-0.08286,51.796371],"type":"Point"}
}