{
  "type": "Feature",
  "properties": {
    "iso:country":"GB",
    "sg:address":"2 Condurrow Road, Beacon",
    "sg:city":"Camborne",
    "sg:classifiers":[
        {
            "category":"Personal",
            "subcategory":"Beauty Salon",
            "type":"Services"
        }
    ],
    "sg:phone":"+44 1209 718223",
    "sg:postcode":"TR14 7SW",
    "sg:province":"Cornwall",
    "sg:tags":[
        "unisex",
        "hairdresser"
    ],
    "wof:name":"Beacon Hair Salon",
    "wof:placetype":"venue"
},
  "geometry": {"coordinates":[-5.285396,50.206589],"type":"Point"}
}