{
  "type": "Feature",
  "properties": {
    "addr:full":"62-64 Yorkshire Street Burnley Lancashire BB11 3BT",
    "addr:housenumber":"62-64",
    "addr:postcode":"bb11 3bt",
    "addr:street":"Yorkshire Street",
    "iso:country":"GB",
    "sg:address":"62-64 Yorkshire Street",
    "sg:city":"Burnley",
    "sg:classifiers":[
        {
            "category":"Professional",
            "subcategory":"Engineering",
            "type":"Services"
        }
    ],
    "sg:phone":"+44 1282 430433",
    "sg:postcode":"BB11 3BT",
    "sg:province":"Lancashire",
    "sg:tags":[
        "consulting",
        "engineer"
    ],
    "wof:name":"Groundwork East Lancashire",
    "wof:placetype":"venue"
},
  "geometry": {"coordinates":[-2.235429,53.789158],"type":"Point"}
}