{
  "type": "Feature",
  "properties": {
    "iso:country":"GB",
    "sg:address":"Braikly Road",
    "sg:city":"Ellon",
    "sg:classifiers":[
        {
            "category":"Wholesale",
            "subcategory":"Meat",
            "type":"Manufacturing & Wholesale Goods"
        }
    ],
    "sg:phone":"+44 1651 852003",
    "sg:postcode":"AB41 0JX",
    "sg:province":"Aberdeenshire",
    "sg:tags":[
        "-"
    ],
    "wof:name":"Aberdeen Scotch Meat Ltd.",
    "wof:placetype":"venue"
},
  "geometry": {"coordinates":[-2.0728139877,57.3641357422],"type":"Point"}
}