{
  "type": "Feature",
  "properties": {
    "iso:country":"GB",
    "sg:address":"Gff 6 Brayburne Avenue",
    "sg:city":"London",
    "sg:classifiers":[
        {
            "category":"Organizations",
            "subcategory":"Membership Organization",
            "type":"Services"
        }
    ],
    "sg:postcode":"SW4 6AA",
    "sg:province":"Greater London",
    "sg:tags":[
        "club"
    ],
    "wof:name":"Nda Management Ltd",
    "wof:placetype":"venue"
},
  "geometry": {"coordinates":[-0.13801,51.468281],"type":"Point"}
}