{
  "type": "Feature",
  "properties": {
    "addr:full":"66 Connaught Avenue Frinton-on-sea Essex CO13 9PT",
    "addr:housenumber":"66",
    "addr:postcode":"co13 9pt",
    "addr:street":"Connaught Avenue",
    "iso:country":"GB",
    "sg:address":"66 Connaught Avenue",
    "sg:city":"Frinton-on-sea",
    "sg:classifiers":[
        {
            "category":"Shopping",
            "subcategory":"Shoes",
            "type":"Retail Goods"
        }
    ],
    "sg:phone":"+44 1255 850028",
    "sg:postcode":"CO13 9PT",
    "sg:province":"Essex",
    "sg:tags":[
        "shop",
        "retailer",
        "footwear"
    ],
    "wof:name":"Clarksons",
    "wof:placetype":"venue"
},
  "geometry": {"coordinates":[1.2454359531,51.8327827454],"type":"Point"}
}