{
  "type": "Feature",
  "properties": {
    "addr:full":"St Michaels Lodge Church Road, Partridge Green Horsham West Sussex RH13 8JS",
    "addr:postcode":"rh13 8js",
    "addr:street":"Church Road",
    "iso:country":"GB",
    "sg:address":"St Michaels Lodge Church Road, Partridge Green",
    "sg:city":"Horsham",
    "sg:classifiers":[
        {
            "category":"Shopping",
            "subcategory":"Bicycles & Sporting Goods",
            "type":"Retail Goods"
        }
    ],
    "sg:phone":"+44 1403 711502",
    "sg:postcode":"RH13 8JS",
    "sg:province":"West Sussex",
    "sg:tags":[
        "water",
        "cooler"
    ],
    "wof:name":"Kula Products Ltd.",
    "wof:placetype":"venue"
},
  "geometry": {"coordinates":[-0.3059389889,50.9594192505],"type":"Point"}
}