{
  "type": "Feature",
  "properties": {
    "iso:country":"GB",
    "sg:address":"25 Vale Road",
    "sg:city":"Tunbridge Wells",
    "sg:classifiers":[
        {
            "category":"Retail",
            "subcategory":"Laundry & Dry Cleaning",
            "type":"Services"
        }
    ],
    "sg:phone":"+44 1892 524434",
    "sg:postcode":"TN1 1BS",
    "sg:province":"Kent",
    "sg:tags":[
        "alteration"
    ],
    "wof:name":"Mitre Cleaners",
    "wof:placetype":"venue"
},
  "geometry": {"coordinates":[0.261948,51.129192],"type":"Point"}
}