{
  "type": "Feature",
  "properties": {
    "iso:country":"GB",
    "sg:address":"42 St. Marys St",
    "sg:city":"Stamford",
    "sg:classifiers":[
        {
            "category":"Home & Garden",
            "subcategory":"Hardware",
            "type":"Retail Goods"
        }
    ],
    "sg:postcode":"PE9 2DS",
    "sg:province":"Cambridgeshire",
    "sg:tags":[
        "retailer",
        "lighting"
    ],
    "wof:name":"Stamford Decorating Centre",
    "wof:placetype":"venue"
},
  "geometry": {"coordinates":[-0.479762,52.651192],"type":"Point"}
}