{
  "type": "Feature",
  "properties": {
    "addr:full":"12 Butchers Row Barnstaple Devon EX31 1BW",
    "addr:housenumber":"12",
    "addr:postcode":"ex31 1bw",
    "addr:street":"Butchers Row",
    "iso:country":"GB",
    "sg:address":"12 Butchers Row",
    "sg:city":"Barnstaple",
    "sg:classifiers":[
        {
            "category":"Food & Beverages",
            "subcategory":"Meat & Fish",
            "type":"Retail Goods"
        }
    ],
    "sg:phone":"+44 1271 343094",
    "sg:postcode":"EX31 1BW",
    "sg:province":"Devon",
    "sg:tags":[
        "butcher"
    ],
    "wof:name":"Withecombe Robert Butchers",
    "wof:placetype":"venue"
},
  "geometry": {"coordinates":[-4.058866024,51.0803375244],"type":"Point"}
}