{
  "type": "Feature",
  "properties": {
    "addr:full":"Forest Hill Delivery Office, Forest Hill Industrial Estate, Perry Vale London Greater London SE23 2LZ",
    "addr:postcode":"se23 2lz",
    "addr:street":"Estate Perry Vale",
    "iso:country":"GB",
    "sg:address":"Forest Hill Delivery Office, Forest Hill Industrial Estate, Perry Vale",
    "sg:city":"London",
    "sg:classifiers":[
        {
            "category":"Personal",
            "type":"Services"
        }
    ],
    "sg:phone":"+44 20 8291 5441",
    "sg:postcode":"SE23 2LZ",
    "sg:province":"Greater London",
    "sg:tags":[
        "delivery"
    ],
    "wof:name":"Royal Mail",
    "wof:placetype":"venue"
},
  "geometry": {"coordinates":[-0.0531,51.43639],"type":"Point"}
}