{
  "type": "Feature",
  "properties": {
    "addr:full":"Unit 4/5 Llys Penlan Pwllheli Gwynedd LL53 5DE",
    "addr:housenumber":"unit 4 / 5",
    "addr:postcode":"ll53 5de",
    "addr:street":"Llys Penlan",
    "iso:country":"GB",
    "sg:address":"Unit 4/5 Llys Penlan",
    "sg:city":"Pwllheli",
    "sg:classifiers":[
        {
            "category":"Home & Garden",
            "subcategory":"Kitchen Supply",
            "type":"Retail Goods"
        }
    ],
    "sg:phone":"+44 1758 701154",
    "sg:postcode":"LL53 5DE",
    "sg:province":"Gwynedd",
    "sg:tags":[
        "glassware",
        "china"
    ],
    "wof:name":"The Regency",
    "wof:placetype":"venue"
},
  "geometry": {"coordinates":[-4.414314,52.889847],"type":"Point"}
}