{
  "type": "Feature",
  "properties": {
    "addr:full":"12 Hanley Workshops, Hanley Swan Worcester Gloucestershire WR8 0DX",
    "addr:housenumber":"12",
    "addr:postcode":"wr8 0dx",
    "addr:street":"Hanley Workshops Hanley",
    "iso:country":"GB",
    "sg:address":"12 Hanley Workshops, Hanley Swan",
    "sg:city":"Worcester",
    "sg:classifiers":[
        {
            "category":"Manufacturing",
            "subcategory":"Rubber & Plastics",
            "type":"Manufacturing & Wholesale Goods"
        }
    ],
    "sg:phone":"+44 1684 311159",
    "sg:postcode":"WR8 0DX",
    "sg:province":"Gloucestershire",
    "sg:tags":[
        "mould"
    ],
    "wof:name":"Hanley Tooling Ltd.",
    "wof:placetype":"venue"
},
  "geometry": {"coordinates":[-2.220322,52.064026],"type":"Point"}
}