{
  "type": "Feature",
  "properties": {
    "addr:full":"10-12 Burnbank Road, Peacock Cross Hamilton South Lanarkshire ML3 9AA",
    "addr:housenumber":"10-12",
    "addr:postcode":"ml3 9aa",
    "addr:street":"Burnbank Road Peacock Cross",
    "iso:country":"GB",
    "sg:address":"10-12 Burnbank Road, Peacock Cross",
    "sg:city":"Hamilton",
    "sg:classifiers":[
        {
            "category":"Shopping",
            "subcategory":"News",
            "type":"Retail Goods"
        }
    ],
    "sg:phone":"+44 1698 283906",
    "sg:postcode":"ML3 9AA",
    "sg:province":"South Lanarkshire",
    "sg:tags":[
        "newsagent"
    ],
    "wof:name":"Peacock Cross Newsagents",
    "wof:placetype":"venue"
},
  "geometry": {"coordinates":[-4.0546112061,55.7782211304],"type":"Point"}
}