{
  "type": "Feature",
  "properties": {
    "iso:country":"GB",
    "sg:address":"12 Lexden Road",
    "sg:city":"Colchester",
    "sg:classifiers":[
        {
            "category":"Professional",
            "type":"Services"
        }
    ],
    "sg:phone":"+44 1206 541051",
    "sg:postcode":"CO3 3NF",
    "sg:province":"Essex",
    "sg:tags":[
        "archaeologist"
    ],
    "wof:name":"Colchester Archaeological Trust Ltd.",
    "wof:placetype":"venue"
},
  "geometry": {"coordinates":[0.8858399987,51.8874359131],"type":"Point"}
}