{
  "type": "Feature",
  "properties": {
    "addr:full":"759 Cannock Road Wolverhampton Staffordshire WV10 8PN",
    "addr:housenumber":"759",
    "addr:postcode":"wv10 8pn",
    "addr:street":"Cannock Road",
    "iso:country":"GB",
    "sg:address":"759 Cannock Road",
    "sg:city":"Wolverhampton",
    "sg:classifiers":[
        {
            "category":"Shopping",
            "subcategory":"Baby Store",
            "type":"Retail Goods"
        }
    ],
    "sg:phone":"+44 1902 865220",
    "sg:postcode":"WV10 8PN",
    "sg:province":"Staffordshire",
    "sg:tags":[
        "babywear",
        "childrens"
    ],
    "wof:name":"Kiddywinks",
    "wof:placetype":"venue"
},
  "geometry": {"coordinates":[-2.099818,52.612484],"type":"Point"}
}