{
  "type": "Feature",
  "properties": {
    "addr:full":"55 King William Street London Greater London EC4R 9AD",
    "addr:housenumber":"55",
    "addr:postcode":"ec4r 9ad",
    "addr:street":"King William Street",
    "iso:country":"GB",
    "sg:address":"55 King William Street",
    "sg:city":"London",
    "sg:classifiers":[
        {
            "category":"Professional",
            "subcategory":"Lawyer & Legal Services",
            "type":"Services"
        }
    ],
    "sg:phone":"+44 20 7648 0400",
    "sg:postcode":"EC4R 9AD",
    "sg:province":"Greater London",
    "sg:tags":[
        "solicitor"
    ],
    "wof:name":"Vandoorne",
    "wof:placetype":"venue"
},
  "geometry": {"coordinates":[-0.08617,51.510578],"type":"Point"}
}