{
  "type": "Feature",
  "properties": {
    "iso:country":"GB",
    "sg:address":"27 Kenton Road, Earley",
    "sg:city":"Reading",
    "sg:classifiers":[
        {
            "category":"Building & Trades",
            "subcategory":"Plumbing",
            "type":"Services"
        }
    ],
    "sg:phone":"+44 118 961 7702",
    "sg:postcode":"RG6 7LQ",
    "sg:province":"Berkshire",
    "sg:tags":[
        "plumber",
        "heating"
    ],
    "wof:name":"Lee Marshall",
    "wof:placetype":"venue"
},
  "geometry": {"coordinates":[-0.918257,51.436977],"type":"Point"}
}