{
  "type": "Feature",
  "properties": {
    "iso:country":"GB",
    "sg:address":"25 Beatrice St",
    "sg:city":"Oswestry",
    "sg:classifiers":[
        {
            "category":"Food & Beverages",
            "subcategory":"Meat & Fish",
            "type":"Retail Goods"
        }
    ],
    "sg:postcode":"SY11 1QE",
    "sg:province":"Shropshire",
    "sg:tags":[
        "butcher"
    ],
    "wof:name":"H A Hartshorn",
    "wof:placetype":"venue"
},
  "geometry": {"coordinates":[-3.052936,52.861282],"type":"Point"}
}