{
  "type": "Feature",
  "properties": {
    "iso:country":"GB",
    "sg:address":"381 Ashley Rd",
    "sg:city":"Poole",
    "sg:classifiers":[
        {
            "category":"Restaurant",
            "type":"Food & Drink"
        }
    ],
    "sg:phone":"+44 1202 717284",
    "sg:postcode":"BH14 0AT",
    "sg:province":"Dorset",
    "sg:tags":[
        "indian"
    ],
    "wof:name":"Himachol Restaurant The",
    "wof:placetype":"venue"
},
  "geometry": {"coordinates":[-1.942314,50.72887],"type":"Point"}
}