{
  "type": "Feature",
  "properties": {
    "addr:full":"Raven Clo, Bridgend Indust Est Bridgend Bridgend CF31 3RF",
    "addr:postcode":"cf31 3rf",
    "addr:street":"Bridgend Indust Est",
    "iso:country":"GB",
    "sg:address":"Raven Clo, Bridgend Indust Est",
    "sg:city":"Bridgend",
    "sg:classifiers":[
        {
            "category":"Manufacturing",
            "subcategory":"Petroleum Products",
            "type":"Manufacturing & Wholesale Goods"
        }
    ],
    "sg:phone":"+44 1656 657618",
    "sg:postcode":"CF31 3RF",
    "sg:province":"Bridgend",
    "sg:tags":[
        "double",
        "glazing"
    ],
    "wof:name":"Bridgend Budget Windows",
    "wof:placetype":"venue"
},
  "geometry": {"coordinates":[-3.562359,51.501041],"type":"Point"}
}