{
  "type": "Feature",
  "properties": {
    "addr:full":"3 Westport St London Greater London E1 0RA",
    "addr:housenumber":"3",
    "addr:postcode":"e1 0ra",
    "addr:street":"Westport St",
    "iso:country":"GB",
    "sg:address":"3 Westport St",
    "sg:city":"London",
    "sg:classifiers":[
        {
            "category":"Home & Garden",
            "subcategory":"Carpets & Floor Coverings",
            "type":"Retail Goods"
        }
    ],
    "sg:postcode":"E1 0RA",
    "sg:province":"Greater London",
    "sg:tags":[
        "carpets",
        "rug",
        "matting"
    ],
    "wof:name":"McGauley,N,",
    "wof:placetype":"venue"
},
  "geometry": {"coordinates":[-0.043599,51.513649],"type":"Point"}
}