{
  "type": "Feature",
  "properties": {
    "addr:full":"The Old School House, Chandlers Lane, All Cannings Devizes Wiltshire SN10 3PG",
    "addr:postcode":"sn10 3pg",
    "addr:street":"Chandlers Lane",
    "iso:country":"GB",
    "sg:address":"The Old School House, Chandlers Lane, All Cannings",
    "sg:city":"Devizes",
    "sg:classifiers":[
        {
            "category":"Education",
            "subcategory":"School",
            "type":"Public Place"
        },
        {
            "category":"Government",
            "subcategory":"Office",
            "type":"Public Place"
        }
    ],
    "sg:phone":"+44 1380 860676",
    "sg:postcode":"SN10 3PG",
    "sg:province":"Wiltshire",
    "sg:tags":[
        "local",
        "authority"
    ],
    "wof:name":"All Cannings C of E Primary School",
    "wof:placetype":"venue"
},
  "geometry": {"coordinates":[-1.8992099762,51.3539733887],"type":"Point"}
}