{
  "type": "Feature",
  "properties": {
    "addr:full":"Tremabyn, Trematon Saltash Cornwall PL12 4UR",
    "addr:postcode":"pl12 4ur",
    "iso:country":"GB",
    "sg:address":"Tremabyn, Trematon",
    "sg:city":"Saltash",
    "sg:classifiers":[
        {
            "category":"Food & Beverages",
            "subcategory":"Groceries & Convenience Stores",
            "type":"Retail Goods"
        }
    ],
    "sg:phone":"+44 1752 842319",
    "sg:postcode":"PL12 4UR",
    "sg:province":"Cornwall",
    "sg:tags":[
        "merchant",
        "potato"
    ],
    "wof:name":"D Ruby & Son",
    "wof:placetype":"venue"
},
  "geometry": {"coordinates":[-4.262019,50.41531],"type":"Point"}
}