{
  "type": "Feature",
  "properties": {
    "addr:full":"Unit 6 Greenwood Court, Ramridge Road Luton Bedfordshire LU2 0TN",
    "addr:housenumber":"unit 6",
    "addr:postcode":"lu2 0tn",
    "addr:street":"Greenwood Court Ramridge Road",
    "iso:country":"GB",
    "sg:address":"Unit 6 Greenwood Court, Ramridge Road",
    "sg:city":"Luton",
    "sg:classifiers":[
        {
            "category":"Retail",
            "subcategory":"Auto Repair",
            "type":"Services"
        }
    ],
    "sg:phone":"+44 1582 401475",
    "sg:postcode":"LU2 0TN",
    "sg:province":"Bedfordshire",
    "sg:tags":[
        "caravan",
        "servicing"
    ],
    "wof:name":"Hytheland Ltd.",
    "wof:placetype":"venue"
},
  "geometry": {"coordinates":[-0.400774,51.892361],"type":"Point"}
}