{
  "type": "Feature",
  "properties": {
    "addr:full":"Back Lane, Deeping St James Peterborough Cambridgeshire PE6 8RJ",
    "addr:postcode":"pe6 8rj",
    "addr:street":"Back Lane Deeping St James Peterborough",
    "iso:country":"GB",
    "sg:address":"Back Lane, Deeping St James",
    "sg:city":"Peterborough",
    "sg:classifiers":[
        {
            "category":"Community Center",
            "type":"Public Place"
        }
    ],
    "sg:phone":"+44 1778 348444",
    "sg:postcode":"PE6 8RJ",
    "sg:province":"Cambridgeshire",
    "sg:tags":[
        "nursery",
        "centre"
    ],
    "wof:name":"Lanes's Nursery",
    "wof:placetype":"venue"
},
  "geometry": {"coordinates":[-0.282365,52.670704],"type":"Point"}
}