{
  "type": "Feature",
  "properties": {
    "addr:full":"Highcroft House, Station Road, Woolaston Lydney Gloucestershire GL15 6PN",
    "addr:postcode":"gl15 6pn",
    "addr:street":"Station Road",
    "iso:country":"GB",
    "sg:address":"Highcroft House, Station Road, Woolaston",
    "sg:city":"Lydney",
    "sg:classifiers":[
        {
            "category":"Retail",
            "subcategory":"Funeral Services",
            "type":"Services"
        }
    ],
    "sg:phone":"+44 1594 529345",
    "sg:postcode":"GL15 6PN",
    "sg:province":"Gloucestershire",
    "sg:tags":[
        "director"
    ],
    "wof:name":"PHILIP BLATCHLY & SON (MONUMENTAL MASONS) LTD",
    "wof:placetype":"venue"
},
  "geometry": {"coordinates":[-2.5826001167,51.6910018921],"type":"Point"}
}