{
  "type": "Feature",
  "properties": {
    "addr:full":"58 Langdon Road, South Down Park Bath Somerset BA2 1LT",
    "addr:housenumber":"58",
    "addr:postcode":"ba2 1lt",
    "addr:street":"Langdon Road South Down Park",
    "iso:country":"GB",
    "sg:address":"58 Langdon Road, South Down Park",
    "sg:city":"Bath",
    "sg:classifiers":[
        {
            "category":"Professional",
            "subcategory":"Computer Services",
            "type":"Services"
        }
    ],
    "sg:phone":"+44 7941 280086",
    "sg:postcode":"BA2 1LT",
    "sg:province":"Somerset",
    "sg:tags":[
        "system",
        "software"
    ],
    "wof:name":"Ems Plus Ltd.",
    "wof:placetype":"venue"
},
  "geometry": {"coordinates":[-2.3932430744,51.3740272522],"type":"Point"}
}