{
  "type": "Feature",
  "properties": {
    "addr:full":"42 Church Street, Padiham Burnley Lancashire BB12 8JQ",
    "addr:housenumber":"42",
    "addr:postcode":"bb12 8jq",
    "addr:street":"Church Street",
    "iso:country":"GB",
    "sg:address":"42 Church Street, Padiham",
    "sg:city":"Burnley",
    "sg:classifiers":[
        {
            "category":"Food & Beverages",
            "subcategory":"Meat & Fish",
            "type":"Retail Goods"
        }
    ],
    "sg:phone":"+44 1282 772465",
    "sg:postcode":"BB12 8JQ",
    "sg:province":"Lancashire",
    "sg:tags":[
        "butcher"
    ],
    "wof:name":"A C Speak & Son",
    "wof:placetype":"venue"
},
  "geometry": {"coordinates":[-2.31881,53.801514],"type":"Point"}
}