{
  "type": "Feature",
  "properties": {
    "addr:full":"140 Harley Street London Greater London W1G 7JZ",
    "addr:housenumber":"140",
    "addr:postcode":"w1g 7jz",
    "addr:street":"Harley Street",
    "iso:country":"GB",
    "sg:address":"140 Harley Street",
    "sg:city":"London",
    "sg:classifiers":[
        {
            "category":"Shopping",
            "subcategory":"Pharmacy",
            "type":"Retail Goods"
        }
    ],
    "sg:phone":"+44 20 7224 2393",
    "sg:postcode":"W1G 7JZ",
    "sg:province":"Greater London",
    "sg:tags":[
        "medicine",
        "therapy"
    ],
    "wof:name":"Self Centre",
    "wof:placetype":"venue"
},
  "geometry": {"coordinates":[-0.1484729946,51.5228385925],"type":"Point"}
}