{
  "type": "Feature",
  "properties": {
    "addr:full":"Church Road, Roch Haverfordwest Pembrokeshire SA62 6BG",
    "addr:postcode":"sa62 6bg",
    "addr:street":"Church Road",
    "iso:country":"GB",
    "sg:address":"Church Road, Roch",
    "sg:city":"Haverfordwest",
    "sg:classifiers":[
        {
            "category":"Food & Beverages",
            "subcategory":"Supermarket",
            "type":"Retail Goods"
        }
    ],
    "sg:postcode":"SA62 6BG",
    "sg:province":"Pembrokeshire",
    "wof:name":"Marks & Julies",
    "wof:placetype":"venue"
},
  "geometry": {"coordinates":[-5.0889830589,51.8480606079],"type":"Point"}
}