{
  "type": "Feature",
  "properties": {
    "iso:country":"GB",
    "sg:address":"5 Cheapside",
    "sg:city":"Lancaster",
    "sg:classifiers":[
        {
            "category":"Shopping",
            "subcategory":"Music",
            "type":"Retail Goods"
        }
    ],
    "sg:postcode":"LA1 1LY",
    "sg:province":"Lancashire",
    "sg:tags":[
        "record",
        "tape",
        "cd"
    ],
    "wof:name":"Time Computers Ltd",
    "wof:placetype":"venue"
},
  "geometry": {"coordinates":[-2.799668,54.049244],"type":"Point"}
}