{
  "type": "Feature",
  "properties": {
    "iso:country":"GB",
    "sg:address":"14 South Entrance",
    "sg:city":"Saxmundham",
    "sg:classifiers":[
        {
            "category":"Retail",
            "subcategory":"Auto Repair",
            "type":"Services"
        }
    ],
    "sg:phone":"+44 1728 603060",
    "sg:postcode":"IP17 1DQ",
    "sg:province":"Suffolk",
    "sg:tags":[
        "car",
        "specialist",
        "customizing"
    ],
    "wof:name":"TREADS Tyres",
    "wof:placetype":"venue"
},
  "geometry": {"coordinates":[1.491123,52.212757],"type":"Point"}
}