{
  "type": "Feature",
  "properties": {
    "iso:country":"GB",
    "sg:address":"Northumberland Avenue",
    "sg:city":"Welling",
    "sg:classifiers":[
        {
            "category":"Education",
            "subcategory":"School",
            "type":"Public Place"
        }
    ],
    "sg:phone":"+44 20 8303 4461",
    "sg:postcode":"DA16 2QE",
    "sg:province":"Kent",
    "sg:tags":[
        "local",
        "authority"
    ],
    "wof:name":"Westwood Primary",
    "wof:placetype":"venue"
},
  "geometry": {"coordinates":[0.095562,51.462532],"type":"Point"}
}