{
  "type": "Feature",
  "properties": {
    "addr:full":"2 Standard Street Crickhowell Monmouthshire NP8 1BP",
    "addr:housenumber":"2",
    "addr:postcode":"np8 1bp",
    "addr:street":"Standard Street",
    "iso:country":"GB",
    "sg:address":"2 Standard Street",
    "sg:city":"Crickhowell",
    "sg:classifiers":[
        {
            "category":"Home & Garden",
            "subcategory":"Carpets & Floor Coverings",
            "type":"Retail Goods"
        }
    ],
    "sg:phone":"+44 1873 811135",
    "sg:postcode":"NP8 1BP",
    "sg:province":"Monmouthshire",
    "sg:tags":[
        "carpets",
        "rug",
        "matting"
    ],
    "wof:name":"F P Harris",
    "wof:placetype":"venue"
},
  "geometry": {"coordinates":[-3.1364469528,51.8589096069],"type":"Point"}
}