{
  "type": "Feature",
  "properties": {
    "addr:full":"27 Brogden Gro, Brooklands Sale Cheshire M33 7UG",
    "addr:housenumber":"27",
    "addr:postcode":"m33 7ug",
    "addr:street":"Brogden Gro",
    "iso:country":"GB",
    "sg:address":"27 Brogden Gro, Brooklands",
    "sg:city":"Sale",
    "sg:classifiers":[
        {
            "category":"Home & Garden",
            "subcategory":"Home Furnishings",
            "type":"Retail Goods"
        }
    ],
    "sg:phone":"+44 161 962 4530",
    "sg:postcode":"M33 7UG",
    "sg:province":"Cheshire",
    "sg:tags":[
        "blind",
        "curtain",
        "fitting"
    ],
    "wof:name":"Annette's Curtains & Blinds",
    "wof:placetype":"venue"
},
  "geometry": {"coordinates":[-2.3304989338,53.4192581177],"type":"Point"}
}