{
  "type": "Feature",
  "properties": {
    "addr:full":"East District Youth Justice Centre, 2 Mill Bank Liverpool Merseyside L13 0BW",
    "addr:housenumber":"2",
    "addr:postcode":"l13 0bw",
    "addr:street":"East;Mill Bank",
    "iso:country":"GB",
    "sg:address":"East District Youth Justice Centre, 2 Mill Bank",
    "sg:city":"Liverpool",
    "sg:classifiers":[
        {
            "category":"Government",
            "subcategory":"Office",
            "type":"Public Place"
        }
    ],
    "sg:phone":"+44 151 228 6541",
    "sg:postcode":"L13 0BW",
    "sg:province":"Merseyside",
    "sg:tags":[
        "local"
    ],
    "wof:name":"Liverpool City Council",
    "wof:placetype":"venue"
},
  "geometry": {"coordinates":[-2.9784810543,53.4097747803],"type":"Point"}
}