{
  "type": "Feature",
  "properties": {
    "addr:full":"195 Rochdale Road, Milnrow Rochdale Lancashire OL16 3BD",
    "addr:housenumber":"195",
    "addr:postcode":"ol16 3bd",
    "addr:street":"Rochdale Road;Rochdale",
    "iso:country":"GB",
    "sg:address":"195 Rochdale Road, Milnrow",
    "sg:city":"Rochdale",
    "sg:classifiers":[
        {
            "category":"Retail",
            "subcategory":"Funeral Services",
            "type":"Services"
        }
    ],
    "sg:phone":"+44 1706 641344",
    "sg:postcode":"OL16 3BD",
    "sg:province":"Lancashire",
    "sg:tags":[
        "director"
    ],
    "wof:name":"Frank A Brierley",
    "wof:placetype":"venue"
},
  "geometry": {"coordinates":[-2.125358,53.61591],"type":"Point"}
}