{
  "type": "Feature",
  "properties": {
    "addr:full":"183 Lewisham Way Brockley Greater London SE4 1UY",
    "addr:housenumber":"183",
    "addr:postcode":"se4 1uy",
    "addr:street":"Lewisham Way",
    "iso:country":"GB",
    "sg:address":"183 Lewisham Way",
    "sg:city":"Brockley",
    "sg:classifiers":[
        {
            "category":"Professional",
            "subcategory":"Printing & Photocopies",
            "type":"Services"
        }
    ],
    "sg:phone":"+44 20 8694 1128",
    "sg:postcode":"SE4 1UY",
    "sg:province":"Greater London",
    "sg:tags":[
        "process",
        "screen",
        "printer"
    ],
    "wof:name":"Poster & Signs",
    "wof:placetype":"venue"
},
  "geometry": {"coordinates":[-0.0293949991,51.4709739685],"type":"Point"}
}