{
  "type": "Feature",
  "properties": {
    "addr:full":"1-5 Vyner Street London Greater London E2 9DG",
    "addr:housenumber":"1-5",
    "addr:postcode":"e2 9dg",
    "addr:street":"Vyner Street",
    "iso:country":"GB",
    "sg:address":"1-5 Vyner Street",
    "sg:city":"London",
    "sg:classifiers":[
        {
            "category":"Professional",
            "subcategory":"Engineering",
            "type":"Services"
        }
    ],
    "sg:phone":"+44 20 8980 4092",
    "sg:postcode":"E2 9DG",
    "sg:province":"Greater London",
    "wof:name":"Howell Darling Industries Ltd.",
    "wof:placetype":"venue"
},
  "geometry": {"coordinates":[-0.0573190004,51.5342407227],"type":"Point"}
}