{
  "type": "Feature",
  "properties": {
    "addr:full":"P O Box 89 Stockport Cheshire SK4 3JF",
    "addr:housenumber":"box 89",
    "addr:postcode":"sk4 3jf",
    "addr:street":"P O",
    "iso:country":"GB",
    "sg:address":"P O Box 89",
    "sg:city":"Stockport",
    "sg:classifiers":[
        {
            "category":"Professional",
            "subcategory":"Employment Agencies",
            "type":"Services"
        }
    ],
    "sg:postcode":"SK4 3JF",
    "sg:province":"Cheshire",
    "sg:tags":[
        "consultant"
    ],
    "wof:name":"The Interface Partnership Ltd.",
    "wof:placetype":"venue"
},
  "geometry": {"coordinates":[-2.200292,53.413235],"type":"Point"}
}