{
  "type": "Feature",
  "properties": {
    "addr:full":"Unit B4 Meridian Industrial, Newton Road Peacehaven East Sussex BN10 8JQ",
    "addr:postcode":"bn10 8jq",
    "addr:street":"Meridian Industrial Newton Road Peacehaven",
    "iso:country":"GB",
    "sg:address":"Unit B4 Meridian Industrial, Newton Road",
    "sg:city":"Peacehaven",
    "sg:classifiers":[
        {
            "category":"Building & Trades",
            "subcategory":"Plumbing",
            "type":"Services"
        }
    ],
    "sg:phone":"+44 1273 587626",
    "sg:postcode":"BN10 8JQ",
    "sg:province":"East Sussex",
    "sg:tags":[
        "joint",
        "seal"
    ],
    "wof:name":"Sealed Units (Uk) Ltd.",
    "wof:placetype":"venue"
},
  "geometry": {"coordinates":[-0.003642,50.7918167114],"type":"Point"}
}