{
  "type": "Feature",
  "properties": {
    "iso:country":"GB",
    "sg:address":"Carlton Lane, Rothwell",
    "sg:city":"Leeds",
    "sg:classifiers":[
        {
            "category":"Retail",
            "subcategory":"Auto Repair",
            "type":"Services"
        }
    ],
    "sg:phone":"+44 113 282 2095",
    "sg:postcode":"LS26 0SX",
    "sg:province":"West Yorkshire",
    "sg:tags":[
        "modification",
        "garage"
    ],
    "wof:name":"Carlton Lane (Garage) Ltd.",
    "wof:placetype":"venue"
},
  "geometry": {"coordinates":[-1.4798589945,53.7466888428],"type":"Point"}
}