{
  "type": "Feature",
  "properties": {
    "addr:full":"Radnor House Stanner Kington Herefordshire HR5 3NW",
    "addr:postcode":"hr5 3nw",
    "addr:street":"Stanner",
    "iso:country":"GB",
    "sg:address":"Radnor House Stanner",
    "sg:city":"Kington",
    "sg:classifiers":[
        {
            "category":"Freight",
            "type":"Transportation"
        }
    ],
    "sg:postcode":"HR5 3NW",
    "sg:province":"Herefordshire",
    "sg:tags":[
        "haulage",
        "road"
    ],
    "wof:name":"Ken's Tipper Hire Ltd.",
    "wof:placetype":"venue"
},
  "geometry": {"coordinates":[-3.0294780731,52.20362854],"type":"Point"}
}