{
  "type": "Feature",
  "properties": {
    "iso:country":"GB",
    "sg:address":"Cemetery Road, Ogmore Vale",
    "sg:city":"Bridgend",
    "sg:classifiers":[
        {
            "category":"Retail",
            "subcategory":"Auto Repair",
            "type":"Services"
        }
    ],
    "sg:phone":"+44 1656 840454",
    "sg:postcode":"CF32 7HR",
    "sg:province":"Bridgend",
    "sg:tags":[
        "modification",
        "garage"
    ],
    "wof:name":"Crossing Service Station Ltd.",
    "wof:placetype":"venue"
},
  "geometry": {"coordinates":[-3.541698,51.600864],"type":"Point"}
}