{
  "type": "Feature",
  "properties": {
    "addr:full":"The Old Convent, Llanbadarn Road Aberystwyth Ceredigion SY23 1WX",
    "addr:postcode":"sy23 1wx",
    "addr:street":"Llanbadarn Road",
    "iso:country":"GB",
    "sg:address":"The Old Convent, Llanbadarn Road",
    "sg:city":"Aberystwyth",
    "sg:classifiers":[
        {
            "category":"Professional",
            "subcategory":"Management & Consulting",
            "type":"Services"
        }
    ],
    "sg:postcode":"SY23 1WX",
    "sg:province":"Ceredigion",
    "sg:tags":[
        "consultant",
        "business"
    ],
    "wof:name":"Glas Consultancy Ltd",
    "wof:placetype":"venue"
},
  "geometry": {"coordinates":[-4.0801,52.40863],"type":"Point"}
}