{
  "type": "Feature",
  "properties": {
    "addr:full":"Dillingsford Av, Cheylesmore Coventry Warwickshire CV3 5EA",
    "addr:postcode":"cv3 5ea",
    "addr:street":"Av Cheylesmore",
    "iso:country":"GB",
    "sg:address":"Dillingsford Av, Cheylesmore",
    "sg:city":"Coventry",
    "sg:classifiers":[
        {
            "category":"Manufacturing",
            "subcategory":"Metals",
            "type":"Manufacturing & Wholesale Goods"
        }
    ],
    "sg:postcode":"CV3 5EA",
    "sg:province":"Warwickshire",
    "sg:tags":[
        "steel",
        "stockholder"
    ],
    "wof:name":"F G Metals",
    "wof:placetype":"venue"
},
  "geometry": {"coordinates":[-1.50626,52.387272],"type":"Point"}
}