{
  "type": "Feature",
  "properties": {
    "addr:full":"North Terrace Seaham Durham SR7 7EU",
    "addr:postcode":"sr7 7eu",
    "addr:street":"North Terrace",
    "iso:country":"GB",
    "sg:address":"North Terrace",
    "sg:city":"Seaham",
    "sg:classifiers":[
        {
            "category":"Organizations",
            "subcategory":"Membership Organization",
            "type":"Services"
        }
    ],
    "sg:phone":"+44 191 581 2797",
    "sg:postcode":"SR7 7EU",
    "sg:province":"Durham",
    "sg:tags":[
        "club"
    ],
    "wof:name":"Seaham Ex Royal Naval Association Club",
    "wof:placetype":"venue"
},
  "geometry": {"coordinates":[-1.331904,54.838974],"type":"Point"}
}