{
  "type": "Feature",
  "properties": {
    "iso:country":"GB",
    "sg:address":"40 Sayesbury Road",
    "sg:city":"Sawbridgeworth",
    "sg:classifiers":[
        {
            "category":"Building & Trades",
            "subcategory":"Landscaping Services",
            "type":"Services"
        }
    ],
    "sg:phone":"+44 1279 725336",
    "sg:postcode":"CM21 0EB",
    "sg:province":"Essex",
    "sg:tags":[
        "gardening"
    ],
    "wof:name":"R G Landscapes",
    "wof:placetype":"venue"
},
  "geometry": {"coordinates":[0.145801,51.813034],"type":"Point"}
}