{
  "type": "Feature",
  "properties": {
    "iso:country":"GB",
    "sg:address":"Ground, Floor Suite, The Crescent, King St",
    "sg:city":"Leicester",
    "sg:classifiers":[
        {
            "category":"Health Services",
            "subcategory":"Health Practitioner",
            "type":"Services"
        }
    ],
    "sg:phone":"+44 116 255 4383",
    "sg:postcode":"LE1 6RX",
    "sg:province":"Leicestershire",
    "sg:tags":[
        "therapist",
        "speech"
    ],
    "wof:name":"Merewood Therapy Centre",
    "wof:placetype":"venue"
},
  "geometry": {"coordinates":[-1.1403650045,52.6378860474],"type":"Point"}
}