{
  "type": "Feature",
  "properties": {
    "addr:full":"Unit 1/4 Ongar Hall Farm Estate, Brentwood Road, Orsett Grays Essex RM16 3HU",
    "addr:housenumber":"unit 1 / 4;estate",
    "addr:postcode":"rm16 3hu",
    "addr:street":"Ongar Hall;Brentwood Road",
    "iso:country":"GB",
    "sg:address":"Unit 1/4 Ongar Hall Farm Estate, Brentwood Road, Orsett",
    "sg:city":"Grays",
    "sg:classifiers":[
        {
            "category":"Manufacturing",
            "subcategory":"Wood Products",
            "type":"Manufacturing & Wholesale Goods"
        }
    ],
    "sg:phone":"+44 1375 892938",
    "sg:postcode":"RM16 3HU",
    "sg:province":"Essex",
    "sg:tags":[
        "maker",
        "cabinet"
    ],
    "wof:name":"Camdenwood Ltd.",
    "wof:placetype":"venue"
},
  "geometry": {"coordinates":[0.3667750061,51.5123214722],"type":"Point"}
}