{
  "type": "Feature",
  "properties": {
    "iso:country":"GB",
    "sg:address":"Six Ways House, 15 Sutton New Road",
    "sg:city":"Birmingham",
    "sg:classifiers":[
        {
            "category":"Professional",
            "subcategory":"Employment Agencies",
            "type":"Services"
        }
    ],
    "sg:phone":"+44 121 386 1355",
    "sg:postcode":"B23 6TJ",
    "sg:province":"West Midlands",
    "sg:tags":[
        "consultant"
    ],
    "wof:name":"Central Cover Employment Agency & Training Centre",
    "wof:placetype":"venue"
},
  "geometry": {"coordinates":[-1.84331,52.522816],"type":"Point"}
}