{
  "type": "Feature",
  "properties": {
    "addr:full":"Empire Works, Brewery Lane, Thornhill Lees Dewsbury West Yorkshire WF12 9HQ",
    "addr:postcode":"wf12 9hq",
    "addr:street":"Brewery Lane;Lees",
    "iso:country":"GB",
    "sg:address":"Empire Works, Brewery Lane, Thornhill Lees",
    "sg:city":"Dewsbury",
    "sg:classifiers":[
        {
            "category":"Wholesale",
            "subcategory":"Machinery & Supplies",
            "type":"Manufacturing & Wholesale Goods"
        }
    ],
    "sg:phone":"+44 1924 455717",
    "sg:postcode":"WF12 9HQ",
    "sg:province":"West Yorkshire",
    "sg:tags":[
        "industrial",
        "commercial"
    ],
    "wof:name":"Brightside Industries Ltd.",
    "wof:placetype":"venue"
},
  "geometry": {"coordinates":[-1.63764,53.672981],"type":"Point"}
}