{
  "type": "Feature",
  "properties": {
    "addr:full":"236 Northolt Road Harrow Greater London HA2 8DU",
    "addr:housenumber":"236",
    "addr:postcode":"ha2 8du",
    "addr:street":"Northolt Road",
    "iso:country":"GB",
    "sg:address":"236 Northolt Road",
    "sg:city":"Harrow",
    "sg:classifiers":[
        {
            "category":"Home & Garden",
            "subcategory":"Household Appliances",
            "type":"Retail Goods"
        }
    ],
    "sg:postcode":"HA2 8DU",
    "sg:province":"Greater London",
    "sg:tags":[
        "domestic",
        "centre"
    ],
    "wof:name":"Kenray Domestic Appliances",
    "wof:placetype":"venue"
},
  "geometry": {"coordinates":[-0.35384,51.564507],"type":"Point"}
}