{
  "type": "Feature",
  "properties": {
    "addr:full":"93 Throne Road Oldbury West Midlands B65 9JX",
    "addr:housenumber":"93",
    "addr:postcode":"b65 9jx",
    "addr:street":"Throne Road",
    "iso:country":"GB",
    "sg:address":"93 Throne Road",
    "sg:city":"Oldbury",
    "sg:classifiers":[
        {
            "category":"Shopping",
            "subcategory":"News",
            "type":"Retail Goods"
        }
    ],
    "sg:phone":"+44 121 559 2977",
    "sg:postcode":"B65 9JX",
    "sg:province":"West Midlands",
    "sg:tags":[
        "newsagent"
    ],
    "wof:name":"Throne News",
    "wof:placetype":"venue"
},
  "geometry": {"coordinates":[-2.035859108,52.4893417358],"type":"Point"}
}