{
  "type": "Feature",
  "properties": {
    "addr:full":"1st Floor, 47 Upper Basinghall Street Leeds West Yorkshire LS1 5HR",
    "addr:housenumber":"47",
    "addr:postcode":"ls1 5hr",
    "addr:street":"Upper Basinghall Street",
    "iso:country":"GB",
    "sg:address":"1st Floor, 47 Upper Basinghall Street",
    "sg:city":"Leeds",
    "sg:classifiers":[
        {
            "category":"Shopping",
            "subcategory":"Computers & Home Electronics",
            "type":"Retail Goods"
        }
    ],
    "sg:phone":"+44 113 245 6276",
    "sg:postcode":"LS1 5HR",
    "sg:province":"West Yorkshire",
    "wof:name":"Interchange Technology Ltd.",
    "wof:placetype":"venue"
},
  "geometry": {"coordinates":[-1.5465019941,53.7982444763],"type":"Point"}
}