{
  "type": "Feature",
  "properties": {
    "iso:country":"GB",
    "sg:address":"Barr Street",
    "sg:city":"Glasgow",
    "sg:classifiers":[
        {
            "category":"Health Services",
            "subcategory":"Doctor",
            "type":"Services"
        }
    ],
    "sg:phone":"+44 141 531 9585",
    "sg:postcode":"G20 7LR",
    "sg:province":"Glasgow City",
    "sg:tags":[
        "practitioners"
    ],
    "wof:name":"Woodside Health Centre",
    "wof:placetype":"venue"
},
  "geometry": {"coordinates":[-4.2645540237,55.875831604],"type":"Point"}
}