{
  "type": "Feature",
  "properties": {
    "addr:full":"3 Victoria Arcade, Mander Centre Wolverhampton West Midlands WV1 3PX",
    "addr:housenumber":"3",
    "addr:postcode":"wv1 3px",
    "addr:street":"Victoria Arcade Mander",
    "iso:country":"GB",
    "sg:address":"3 Victoria Arcade, Mander Centre",
    "sg:city":"Wolverhampton",
    "sg:classifiers":[
        {
            "category":"Communications",
            "type":"Services"
        }
    ],
    "sg:phone":"+44 1902 714415",
    "sg:postcode":"WV1 3PX",
    "sg:province":"West Midlands",
    "sg:tags":[
        "tv",
        "video",
        "radio"
    ],
    "wof:name":"Deep Audio Visuals",
    "wof:placetype":"venue"
},
  "geometry": {"coordinates":[-2.1290450096,52.5855445862],"type":"Point"}
}