{
  "type": "Feature",
  "properties": {
    "addr:full":"Westergate Street Chichester West Sussex PO20 3QZ",
    "addr:postcode":"po20 3qz",
    "addr:street":"Westergate Street",
    "iso:country":"GB",
    "sg:address":"Westergate Street",
    "sg:city":"Chichester",
    "sg:classifiers":[
        {
            "category":"Professional",
            "subcategory":"Employment Agencies",
            "type":"Services"
        }
    ],
    "sg:phone":"+44 800 731 0642",
    "sg:postcode":"PO20 3QZ",
    "sg:province":"West Sussex",
    "sg:tags":[
        "agricultural",
        "advice"
    ],
    "wof:name":"Agriking Ltd.",
    "wof:placetype":"venue"
},
  "geometry": {"coordinates":[-0.6685140133,50.8395614624],"type":"Point"}
}