{
  "type": "Feature",
  "properties": {
    "addr:full":"4 Glebe Road Cheltenham Gloucestershire GL52 3DG",
    "addr:housenumber":"4",
    "addr:postcode":"gl52 3dg",
    "addr:street":"Glebe Road",
    "iso:country":"GB",
    "sg:address":"4 Glebe Road",
    "sg:city":"Cheltenham",
    "sg:classifiers":[
        {
            "category":"Building & Trades",
            "subcategory":"Plumbing",
            "type":"Services"
        }
    ],
    "sg:postcode":"GL52 3DG",
    "sg:province":"Gloucestershire",
    "sg:tags":[
        "central",
        "heating"
    ],
    "wof:name":"H J Warren (Heating)",
    "wof:placetype":"venue"
},
  "geometry": {"coordinates":[-2.047485,51.911751],"type":"Point"}
}