{
  "type": "Feature",
  "properties": {
    "addr:full":"10 Sycamore Close Attleborough Norfolk NR17 2EU",
    "addr:housenumber":"10",
    "addr:postcode":"nr17 2eu",
    "addr:street":"Sycamore Close",
    "iso:country":"GB",
    "sg:address":"10 Sycamore Close",
    "sg:city":"Attleborough",
    "sg:classifiers":[
        {
            "category":"Arts & Performance",
            "subcategory":"Music",
            "type":"Entertainment"
        }
    ],
    "sg:postcode":"NR17 2EU",
    "sg:province":"Norfolk",
    "sg:tags":[
        "mobile",
        "disco"
    ],
    "wof:name":"Amythyst Mobile Disco",
    "wof:placetype":"venue"
},
  "geometry": {"coordinates":[1.0094380379,52.5134010315],"type":"Point"}
}