{
  "type": "Feature",
  "properties": {
    "iso:country":"GB",
    "sg:address":"Gilmora House, 57-61 Mortimer Street",
    "sg:city":"London",
    "sg:classifiers":[
        {
            "category":"Conference Center",
            "type":"Public Place"
        }
    ],
    "sg:postcode":"W1N 8JX",
    "sg:province":"Greater London",
    "wof:name":"I B C Technical Services Ltd.",
    "wof:placetype":"venue"
},
  "geometry": {"coordinates":[-0.1398849934,51.5177764893],"type":"Point"}
}