{
  "type": "Feature",
  "properties": {
    "iso:country":"GB",
    "sg:address":"Unit 13, Woodlands Business Park",
    "sg:city":"Maidenhead",
    "sg:classifiers":[
        {
            "category":"Professional",
            "subcategory":"Management & Consulting",
            "type":"Services"
        }
    ],
    "sg:postcode":"SL6 3UA",
    "sg:province":"Berkshire",
    "sg:tags":[
        "fire",
        "consultant",
        "protection"
    ],
    "wof:name":"Universal Fire Ltd.",
    "wof:placetype":"venue"
},
  "geometry": {"coordinates":[-0.758576,51.501209],"type":"Point"}
}