{
  "type": "Feature",
  "properties": {
    "addr:full":"101 Netherhall Road Leicester Leicestershire LE5 1DR",
    "addr:housenumber":"101",
    "addr:postcode":"le5 1dr",
    "addr:street":"Netherhall Road",
    "iso:country":"GB",
    "sg:address":"101 Netherhall Road",
    "sg:city":"Leicester",
    "sg:classifiers":[
        {
            "category":"Health Services",
            "subcategory":"Doctor",
            "type":"Services"
        },
        {
            "category":"Health Services",
            "subcategory":"Clinic",
            "type":"Services"
        }
    ],
    "sg:phone":"+44 116 243 2532",
    "sg:postcode":"LE5 1DR",
    "sg:province":"Leicestershire",
    "sg:tags":[
        "nh",
        "practitioners"
    ],
    "wof:name":"The Surgery",
    "wof:placetype":"venue"
},
  "geometry": {"coordinates":[-1.0576820374,52.649143219],"type":"Point"}
}