{
  "type": "Feature",
  "properties": {
    "addr:full":"Arndale Centre Manchester Greater Manchester M4 3AB",
    "addr:postcode":"m4 3ab",
    "iso:country":"GB",
    "sg:address":"Arndale Centre",
    "sg:city":"Manchester",
    "sg:classifiers":[
        {
            "category":"Fast Food",
            "type":"Food & Drink"
        }
    ],
    "sg:phone":"+44 161 839 1182",
    "sg:postcode":"M4 3AB",
    "sg:province":"Greater Manchester",
    "sg:tags":[
        "away",
        "take"
    ],
    "wof:name":"Monglace",
    "wof:placetype":"venue"
},
  "geometry": {"coordinates":[-2.2417,53.483452],"type":"Point"}
}