{
  "type": "Feature",
  "properties": {
    "addr:full":"2 Market Place Ingatestone Essex CM4 0BY",
    "addr:housenumber":"2",
    "addr:postcode":"cm4 0by",
    "addr:street":"Market Place",
    "iso:country":"GB",
    "sg:address":"2 Market Place",
    "sg:city":"Ingatestone",
    "sg:classifiers":[
        {
            "category":"Banks & Credit Unions",
            "subcategory":"Financial Services",
            "type":"Services"
        }
    ],
    "sg:phone":"+44 1277 352727",
    "sg:postcode":"CM4 0BY",
    "sg:province":"Essex",
    "sg:tags":[
        "consultant"
    ],
    "wof:name":"Countrywide Estate Agents Fs Ltd.",
    "wof:placetype":"venue"
},
  "geometry": {"coordinates":[0.3836849928,51.6710166931],"type":"Point"}
}