{
  "type": "Feature",
  "properties": {
    "addr:full":"137 Halesowen Road, Netherton Dudley West Midlands DY2 9PY",
    "addr:housenumber":"137",
    "addr:postcode":"dy2 9py",
    "addr:street":"Halesowen Road",
    "iso:country":"GB",
    "sg:address":"137 Halesowen Road, Netherton",
    "sg:city":"Dudley",
    "sg:classifiers":[
        {
            "category":"Shopping",
            "subcategory":"Pharmacy",
            "type":"Retail Goods"
        }
    ],
    "sg:phone":"+44 1384 254171",
    "sg:postcode":"DY2 9PY",
    "sg:province":"West Midlands",
    "sg:tags":[
        "dispensing",
        "store",
        "pharmacist",
        "chemist",
        "drug"
    ],
    "wof:name":"Milan Chemist",
    "wof:placetype":"venue"
},
  "geometry": {"coordinates":[-2.0816130638,52.4894866943],"type":"Point"}
}