{
  "type": "Feature",
  "properties": {
    "addr:full":"P O Box 1442 London Greater London N16 7HZ",
    "addr:housenumber":"p o;1442",
    "addr:postcode":"n16 7hz",
    "iso:country":"GB",
    "sg:address":"P O Box 1442",
    "sg:city":"London",
    "sg:classifiers":[
        {
            "category":"Coffee & Tea",
            "type":"Food & Drink"
        }
    ],
    "sg:phone":"+44 20 7254 3999",
    "sg:postcode":"N16 7HZ",
    "sg:province":"Greater London",
    "wof:name":"Robertsons Distribution",
    "wof:placetype":"venue"
},
  "geometry": {"coordinates":[-0.07012,51.559078],"type":"Point"}
}