{
  "type": "Feature",
  "properties": {
    "addr:full":"Northfield Rd Ilfracombe Devon EX34 8AL",
    "addr:postcode":"ex34 8al",
    "addr:street":"Northfield Rd",
    "iso:country":"GB",
    "sg:address":"Northfield Rd",
    "sg:city":"Ilfracombe",
    "sg:classifiers":[
        {
            "category":"Home & Garden",
            "subcategory":"Kitchen Supply",
            "type":"Retail Goods"
        }
    ],
    "sg:phone":"+44 1271 862474",
    "sg:postcode":"EX34 8AL",
    "sg:province":"Devon",
    "sg:tags":[
        "catering"
    ],
    "wof:name":"Peeled Potato Service",
    "wof:placetype":"venue"
},
  "geometry": {"coordinates":[-4.1259288788,51.2083625793],"type":"Point"}
}