{
  "type": "Feature",
  "properties": {
    "iso:country":"GB",
    "sg:address":"Morningthorpe",
    "sg:city":"Norwich",
    "sg:classifiers":[
        {
            "category":"Home & Garden",
            "subcategory":"Garden Supply",
            "type":"Retail Goods"
        }
    ],
    "sg:phone":"+44 1508 498263",
    "sg:postcode":"NR15 2LJ",
    "sg:province":"Norfolk",
    "sg:tags":[
        "nursery",
        "centre"
    ],
    "wof:name":"Foundry Nurseries",
    "wof:placetype":"venue"
},
  "geometry": {"coordinates":[1.2654730082,52.4886512756],"type":"Point"}
}