{
  "type": "Feature",
  "properties": {
    "iso:country":"GB",
    "sg:address":"Owl Cottage, High Street, Netheravon",
    "sg:city":"Salisbury",
    "sg:classifiers":[
        {
            "category":"Manufacturing",
            "subcategory":"Wood Products",
            "type":"Manufacturing & Wholesale Goods"
        }
    ],
    "sg:phone":"+44 1980 670396",
    "sg:postcode":"SP4 9PJ",
    "sg:province":"Hampshire",
    "sg:tags":[
        "maker",
        "cabinet"
    ],
    "wof:name":"Alan Englefield",
    "wof:placetype":"venue"
},
  "geometry": {"coordinates":[-1.793908,51.239063],"type":"Point"}
}