{
  "type": "Feature",
  "properties": {
    "addr:full":"2 Sunnyside Cotts, Litlington Polegate East Sussex BN26 5RD",
    "addr:housenumber":"2;cotts litlington",
    "addr:postcode":"bn26 5rd",
    "addr:street":"Sunnyside;Polegate",
    "iso:country":"GB",
    "sg:address":"2 Sunnyside Cotts, Litlington",
    "sg:city":"Polegate",
    "sg:classifiers":[
        {
            "category":"Professional",
            "subcategory":"Engineering",
            "type":"Services"
        }
    ],
    "sg:phone":"+44 1323 870138",
    "sg:postcode":"BN26 5RD",
    "sg:province":"East Sussex",
    "sg:tags":[
        "contractor",
        "electrical",
        "engineer"
    ],
    "wof:name":"J D Patching",
    "wof:placetype":"venue"
},
  "geometry": {"coordinates":[0.1594199985,50.7943496704],"type":"Point"}
}