{
  "type": "Feature",
  "properties": {
    "addr:full":"69 Harrowes Meade Edgware Greater London HA8 8RS",
    "addr:housenumber":"69",
    "addr:postcode":"ha8 8rs",
    "addr:street":"Harrowes Meade",
    "iso:country":"GB",
    "sg:address":"69 Harrowes Meade",
    "sg:city":"Edgware",
    "sg:classifiers":[
        {
            "category":"Shopping",
            "subcategory":"Shoes",
            "type":"Retail Goods"
        }
    ],
    "sg:phone":"+44 20 8958 4023",
    "sg:postcode":"HA8 8RS",
    "sg:province":"Greater London",
    "sg:tags":[
        "footwear"
    ],
    "wof:name":"Courtesy Shoes",
    "wof:placetype":"venue"
},
  "geometry": {"coordinates":[-0.2758899927,51.6269416809],"type":"Point"}
}