{
  "type": "Feature",
  "properties": {
    "iso:country":"GB",
    "sg:address":"191 Hornington Street",
    "sg:city":"Burton-on-trent",
    "sg:classifiers":[
        {
            "category":"Professional",
            "subcategory":"Printing & Photocopies",
            "type":"Services"
        }
    ],
    "sg:postcode":"DE14 1NY",
    "sg:province":"Derbyshire",
    "sg:tags":[
        "printer"
    ],
    "wof:name":"Burton Printers Ltd.",
    "wof:placetype":"venue"
},
  "geometry": {"coordinates":[-1.627574,52.814541],"type":"Point"}
}