{
  "type": "Feature",
  "properties": {
    "addr:full":"15 Market Street, Oakengates Telford Shropshire TF2 6EL",
    "addr:housenumber":"15",
    "addr:postcode":"tf2 6el",
    "addr:street":"Market Street",
    "iso:country":"GB",
    "sg:address":"15 Market Street, Oakengates",
    "sg:city":"Telford",
    "sg:classifiers":[
        {
            "category":"Shopping",
            "subcategory":"Thrift Store",
            "type":"Retail Goods"
        }
    ],
    "sg:phone":"+44 1952 240200",
    "sg:postcode":"TF2 6EL",
    "sg:province":"Shropshire",
    "sg:tags":[
        "shop",
        "charity"
    ],
    "wof:name":"Wear Next Community Shop",
    "wof:placetype":"venue"
},
  "geometry": {"coordinates":[-2.4520349503,52.6949462891],"type":"Point"}
}