{
  "type": "Feature",
  "properties": {
    "iso:country":"GB",
    "sg:address":"21 Boston Road, Kirton",
    "sg:city":"Boston",
    "sg:classifiers":[
        {
            "category":"Home & Garden",
            "subcategory":"Home Furnishings",
            "type":"Retail Goods"
        },
        {
            "category":"Retail",
            "subcategory":"Event Space",
            "type":"Services"
        }
    ],
    "sg:phone":"+44 1205 722694",
    "sg:postcode":"PE20 1DT",
    "sg:province":"Lincolnshire",
    "sg:tags":[
        "product",
        "planner",
        "sales",
        "furnishers",
        "electrical",
        "kitchen"
    ],
    "wof:name":"D MANNING",
    "wof:placetype":"venue"
},
  "geometry": {"coordinates":[-0.057955,52.93079],"type":"Point"}
}