{
  "type": "Feature",
  "properties": {
    "addr:full":"Church House, Church Street Ormskirk Lancashire L39 3AG",
    "addr:postcode":"l39 3ag",
    "addr:street":"Church Street",
    "iso:country":"GB",
    "sg:address":"Church House, Church Street",
    "sg:city":"Ormskirk",
    "sg:classifiers":[
        {
            "category":"Professional",
            "subcategory":"Business Services",
            "type":"Services"
        }
    ],
    "sg:phone":"+44 1695 579669",
    "sg:postcode":"L39 3AG",
    "sg:province":"Lancashire",
    "sg:tags":[
        "hospitality",
        "corporate"
    ],
    "wof:name":"Connections (Corporate Hospitality) Ltd.",
    "wof:placetype":"venue"
},
  "geometry": {"coordinates":[-2.8873291016,53.5688591003],"type":"Point"}
}