{
  "type": "Feature",
  "properties": {
    "addr:full":"Victoria House, Victoria Street Taunton Somerset TA1 3JD",
    "addr:postcode":"ta1 3jd",
    "addr:street":"Victoria Street",
    "iso:country":"GB",
    "sg:address":"Victoria House, Victoria Street",
    "sg:city":"Taunton",
    "sg:classifiers":[
        {
            "category":"Health Services",
            "subcategory":"Nursing And Care Facility",
            "type":"Services"
        }
    ],
    "sg:phone":"+44 1823 350150",
    "sg:postcode":"TA1 3JD",
    "sg:province":"Somerset",
    "sg:tags":[
        "agency"
    ],
    "wof:name":"Contact Care Agency Ltd.",
    "wof:placetype":"venue"
},
  "geometry": {"coordinates":[-3.090784,51.015549],"type":"Point"}
}