{
  "type": "Feature",
  "properties": {
    "iso:country":"GB",
    "sg:address":"36 Linthorpe Rd",
    "sg:city":"Middlesbrough",
    "sg:classifiers":[
        {
            "category":"Home & Garden",
            "subcategory":"Home Furnishings",
            "type":"Retail Goods"
        }
    ],
    "sg:phone":"+44 1642 243944",
    "sg:postcode":"TS1 1RD",
    "sg:province":"North Yorkshire",
    "sg:tags":[
        "beds",
        "bedding",
        "blanket"
    ],
    "wof:name":"Knightingales",
    "wof:placetype":"venue"
},
  "geometry": {"coordinates":[-1.2361630201,54.5774765015],"type":"Point"}
}