{
  "type": "Feature",
  "properties": {
    "iso:country":"GB",
    "sg:address":"18 Callis Court Road",
    "sg:city":"Broadstairs",
    "sg:classifiers":[
        {
            "category":"Education",
            "subcategory":"Dance Studio",
            "type":"Public Place"
        }
    ],
    "sg:phone":"+44 1843 868478",
    "sg:postcode":"CT10 3AE",
    "sg:province":"Kent",
    "sg:tags":[
        "school",
        "dancing"
    ],
    "wof:name":"Page Mason Schools of Dance",
    "wof:placetype":"venue"
},
  "geometry": {"coordinates":[1.431352,51.367741],"type":"Point"}
}