{
  "type": "Feature",
  "properties": {
    "addr:full":"33 Liverpool Road Southport Lancashire PR8 4AG",
    "addr:housenumber":"33",
    "addr:postcode":"pr8 4ag",
    "addr:street":"Liverpool Road",
    "iso:country":"GB",
    "sg:address":"33 Liverpool Road",
    "sg:city":"Southport",
    "sg:classifiers":[
        {
            "category":"Retail",
            "subcategory":"Funeral Services",
            "type":"Services"
        }
    ],
    "sg:phone":"+44 1704 550055",
    "sg:postcode":"PR8 4AG",
    "sg:province":"Lancashire",
    "sg:tags":[
        "director"
    ],
    "wof:name":"Broadbents & Seddons",
    "wof:placetype":"venue"
},
  "geometry": {"coordinates":[-3.012703,53.633736],"type":"Point"}
}