{
  "type": "Feature",
  "properties": {
    "addr:full":"Woodfarm Road, Malvern Wells Malvern Herefordshire WR14 4PP",
    "addr:postcode":"wr14 4pp",
    "addr:street":"Woodfarm Road",
    "iso:country":"GB",
    "sg:address":"Woodfarm Road, Malvern Wells",
    "sg:city":"Malvern",
    "sg:classifiers":[
        {
            "category":"Sports & Exercise",
            "subcategory":"Golf",
            "type":"Entertainment"
        }
    ],
    "sg:phone":"+44 1684 564428",
    "sg:postcode":"WR14 4PP",
    "sg:province":"Herefordshire",
    "sg:tags":[
        "equipment"
    ],
    "wof:name":"Richard Lewis",
    "wof:placetype":"venue"
},
  "geometry": {"coordinates":[-2.326618,52.082493],"type":"Point"}
}