{
  "type": "Feature",
  "properties": {
    "iso:country":"GB",
    "sg:address":"Close Hill",
    "sg:city":"Redruth",
    "sg:classifiers":[
        {
            "category":"Government",
            "subcategory":"Post Office",
            "type":"Public Place"
        }
    ],
    "sg:phone":"+44 1209 313461",
    "sg:postcode":"TR15 1EP",
    "sg:province":"Cornwall",
    "wof:name":"Close Hill P.O",
    "wof:placetype":"venue"
},
  "geometry": {"coordinates":[-5.2328739166,50.2417755127],"type":"Point"}
}