{
  "type": "Feature",
  "properties": {
    "addr:full":"Unit 1 Dronfield Derbyshire S18 2GG",
    "addr:housenumber":"unit 1",
    "addr:postcode":"s18 2gg",
    "iso:country":"GB",
    "sg:address":"Unit 1",
    "sg:city":"Dronfield",
    "sg:classifiers":[
        {
            "category":"Retail",
            "subcategory":"Auto Repair",
            "type":"Services"
        }
    ],
    "sg:phone":"+44 1246 411951",
    "sg:postcode":"S18 2GG",
    "sg:province":"Derbyshire",
    "sg:tags":[
        "modification",
        "garage"
    ],
    "wof:name":"Auto Service & Repairs by M A T",
    "wof:placetype":"venue"
},
  "geometry": {"coordinates":[-1.464699,53.304932],"type":"Point"}
}