{
  "type": "Feature",
  "properties": {
    "addr:full":"Station Rd, Bishops Waltham Southampton Hampshire SO32 1DH",
    "addr:postcode":"so32 1dh",
    "addr:street":"Station Rd",
    "iso:country":"GB",
    "sg:address":"Station Rd, Bishops Waltham",
    "sg:city":"Southampton",
    "sg:classifiers":[
        {
            "category":"Communications",
            "type":"Services"
        }
    ],
    "sg:postcode":"SO32 1DH",
    "sg:province":"Hampshire",
    "sg:tags":[
        "data",
        "network"
    ],
    "wof:name":"Warn,Stephen,",
    "wof:placetype":"venue"
},
  "geometry": {"coordinates":[-1.2157039642,50.9539260864],"type":"Point"}
}