{
  "type": "Feature",
  "properties": {
    "iso:country":"GB",
    "sg:address":"40 Maylea Dr",
    "sg:city":"Otley",
    "sg:classifiers":[
        {
            "category":"Autos & Motor Vehicles",
            "subcategory":"Automobile Sales",
            "type":"Retail Goods"
        }
    ],
    "sg:phone":"+44 1943 850239",
    "sg:postcode":"LS21 3ND",
    "sg:province":"North Yorkshire",
    "sg:tags":[
        "car"
    ],
    "wof:name":"Otley Auto Sales",
    "wof:placetype":"venue"
},
  "geometry": {"coordinates":[-1.717938,53.898739],"type":"Point"}
}