{
  "type": "Feature",
  "properties": {
    "iso:country":"GB",
    "sg:address":"7 Mill Clo",
    "sg:city":"Daventry",
    "sg:classifiers":[
        {
            "category":"Travel",
            "subcategory":"Bed & Breakfast",
            "type":"Entertainment"
        }
    ],
    "sg:phone":"+44 1788 890611",
    "sg:postcode":"NN11 7HY",
    "sg:province":"Northamptonshire",
    "sg:tags":[
        "ladder"
    ],
    "wof:name":"Scott Marketing",
    "wof:placetype":"venue"
},
  "geometry": {"coordinates":[-1.213495,52.292255],"type":"Point"}
}