{
  "type": "Feature",
  "properties": {
    "addr:full":"Unit B Sherriff St Worcester Worcestershire WR4 9AB",
    "addr:postcode":"wr4 9ab",
    "addr:street":"Sherriff St",
    "iso:country":"GB",
    "sg:address":"Unit B Sherriff St",
    "sg:city":"Worcester",
    "sg:classifiers":[
        {
            "category":"Professional",
            "type":"Services"
        }
    ],
    "sg:phone":"+44 1905 619599",
    "sg:postcode":"WR4 9AB",
    "sg:province":"Worcestershire",
    "sg:tags":[
        "control",
        "system"
    ],
    "wof:name":"A G R Automation Supplies Ltd",
    "wof:placetype":"venue"
},
  "geometry": {"coordinates":[-2.206969,52.195171],"type":"Point"}
}