{
  "type": "Feature",
  "properties": {
    "addr:full":"9 Lees Close Maidenhead Berkshire SL6 4NU",
    "addr:housenumber":"9",
    "addr:postcode":"sl6 4nu",
    "addr:street":"Lees Close",
    "iso:country":"GB",
    "sg:address":"9 Lees Close",
    "sg:city":"Maidenhead",
    "sg:classifiers":[
        {
            "category":"Taxi",
            "type":"Transportation"
        }
    ],
    "sg:phone":"+44 1628 683000",
    "sg:postcode":"SL6 4NU",
    "sg:province":"Berkshire",
    "sg:tags":[
        "mini",
        "cab"
    ],
    "wof:name":"Aabacus Taxis",
    "wof:placetype":"venue"
},
  "geometry": {"coordinates":[-0.7544119954,51.5126457214],"type":"Point"}
}