{
  "type": "Feature",
  "properties": {
    "iso:country":"GB",
    "sg:address":"Cleaver Ho, 295 Kennington Rd",
    "sg:city":"Lambeth",
    "sg:classifiers":[
        {
            "category":"Professional",
            "subcategory":"Business Services",
            "type":"Services"
        }
    ],
    "sg:phone":"+44 20 7582 3222",
    "sg:postcode":"SE11 4QE",
    "sg:province":"Greater London",
    "sg:tags":[
        "bookmaker"
    ],
    "wof:name":"Buckley A Credit Bookmakers Ltd",
    "wof:placetype":"venue"
},
  "geometry": {"coordinates":[-0.11122,51.48769],"type":"Point"}
}