{
  "type": "Feature",
  "properties": {
    "iso:country":"GB",
    "sg:address":"59 Bridport Clo",
    "sg:city":"Reading",
    "sg:classifiers":[
        {
            "category":"Home & Garden",
            "subcategory":"Household Appliances",
            "type":"Retail Goods"
        }
    ],
    "sg:phone":"+44 118 966 5325",
    "sg:postcode":"RG6 3DG",
    "sg:province":"Berkshire",
    "sg:tags":[
        "electrical"
    ],
    "wof:name":"A S L Domestic Appliance Repair & Installation",
    "wof:placetype":"venue"
},
  "geometry": {"coordinates":[-0.912085,51.431053],"type":"Point"}
}