{
  "type": "Feature",
  "properties": {
    "iso:country":"GB",
    "sg:address":"Orchard End, Northcote Road, West Horsley",
    "sg:city":"Leatherhead",
    "sg:classifiers":[
        {
            "category":"Health Services",
            "subcategory":"Health Practitioner",
            "type":"Services"
        }
    ],
    "sg:phone":"+44 1483 282130",
    "sg:postcode":"KT24 6LS",
    "sg:province":"Surrey",
    "sg:tags":[
        "therapist",
        "speech"
    ],
    "wof:name":"Speech & Language Therapy Services",
    "wof:placetype":"venue"
},
  "geometry": {"coordinates":[-0.4530999959,51.2605857849],"type":"Point"}
}