{
  "type": "Feature",
  "properties": {
    "iso:country":"GB",
    "sg:address":"36 Thornhill Road, Ickenham",
    "sg:city":"Uxbridge",
    "sg:classifiers":[
        {
            "category":"Professional",
            "subcategory":"Computer Services",
            "type":"Services"
        }
    ],
    "sg:postcode":"UB10 8SG",
    "sg:province":"Greater London",
    "sg:tags":[
        "system",
        "software"
    ],
    "wof:name":"David Ltd",
    "wof:placetype":"venue"
},
  "geometry": {"coordinates":[-0.45637,51.562546],"type":"Point"}
}