{
  "type": "Feature",
  "properties": {
    "iso:country":"GB",
    "sg:address":"Barley Mow Centre, 12 Barley Mow Passage",
    "sg:city":"Chiswick",
    "sg:classifiers":[
        {
            "category":"Shopping",
            "subcategory":"Stationery & Office Supplies",
            "type":"Retail Goods"
        }
    ],
    "sg:phone":"+44 20 8995 9900",
    "sg:postcode":"W4 4PH",
    "sg:province":"Greater London",
    "sg:tags":[
        "item",
        "promotional"
    ],
    "wof:name":"Activate Promotional Products",
    "wof:placetype":"venue"
},
  "geometry": {"coordinates":[-0.2619389892,51.489440918],"type":"Point"}
}