{
  "type": "Feature",
  "properties": {
    "addr:full":"Brook Avenue, Walrush Southampton Hampshire SO31 9HN",
    "addr:postcode":"so31 9hn",
    "addr:street":"Brook Avenue Walrush",
    "iso:country":"GB",
    "sg:address":"Brook Avenue, Walrush",
    "sg:city":"Southampton",
    "sg:classifiers":[
        {
            "category":"Manufacturing",
            "subcategory":"Building Materials",
            "type":"Manufacturing & Wholesale Goods"
        }
    ],
    "sg:phone":"+44 1489 572406",
    "sg:postcode":"SO31 9HN",
    "sg:province":"Hampshire",
    "sg:tags":[
        "concrete",
        "product"
    ],
    "wof:name":"Smith Bros",
    "wof:placetype":"venue"
},
  "geometry": {"coordinates":[-1.294028,50.862427],"type":"Point"}
}