{
  "type": "Feature",
  "properties": {
    "addr:full":"15 Siskin Road, Offerton Stockport Cheshire SK2 5JX",
    "addr:housenumber":"15",
    "addr:postcode":"sk2 5jx",
    "addr:street":"Siskin Road",
    "iso:country":"GB",
    "sg:address":"15 Siskin Road, Offerton",
    "sg:city":"Stockport",
    "sg:classifiers":[
        {
            "category":"Building & Trades",
            "subcategory":"Landscaping Services",
            "type":"Services"
        }
    ],
    "sg:phone":"+44 161 487 1041",
    "sg:postcode":"SK2 5JX",
    "sg:province":"Cheshire",
    "sg:tags":[
        "landscape",
        "contractor"
    ],
    "wof:name":"Three Trees Builder",
    "wof:placetype":"venue"
},
  "geometry": {"coordinates":[-2.1104290485,53.3900756836],"type":"Point"}
}