{
  "type": "Feature",
  "properties": {
    "addr:full":"79 Rosemount Viaduct Aberdeen Aberdeen City AB25 1NS",
    "addr:housenumber":"79",
    "addr:postcode":"ab25 1ns",
    "addr:street":"Rosemount Viaduct",
    "iso:country":"GB",
    "sg:address":"79 Rosemount Viaduct",
    "sg:city":"Aberdeen",
    "sg:classifiers":[
        {
            "category":"Shopping",
            "subcategory":"Thrift Store",
            "type":"Retail Goods"
        }
    ],
    "sg:phone":"+44 1224 644421",
    "sg:postcode":"AB25 1NS",
    "sg:province":"Aberdeen City",
    "sg:tags":[
        "shop",
        "charity"
    ],
    "wof:name":"Blythswood Care",
    "wof:placetype":"venue"
},
  "geometry": {"coordinates":[-2.1094810963,57.1483802795],"type":"Point"}
}