{
  "type": "Feature",
  "properties": {
    "addr:full":"230a Southcaost Road Peacehaven East Sussex BN10 8JR",
    "addr:housenumber":"230a",
    "addr:postcode":"bn10 8jr",
    "addr:street":"Southcaost Road Peacehaven",
    "iso:country":"GB",
    "sg:address":"230a Southcaost Road",
    "sg:city":"Peacehaven",
    "sg:classifiers":[
        {
            "category":"Military Area",
            "subcategory":"Air Force Base",
            "type":"Public Place"
        }
    ],
    "sg:postcode":"BN10 8JR",
    "sg:province":"East Sussex",
    "sg:tags":[
        "taxi",
        "hire",
        "private"
    ],
    "wof:name":"Cab 4 U",
    "wof:placetype":"venue"
},
  "geometry": {"coordinates":[-0.001606,50.7913703918],"type":"Point"}
}