{
  "type": "Feature",
  "properties": {
    "addr:full":"Unit 502 Rolfe Street Smethwick West Midlands B66 2AR",
    "addr:housenumber":"502",
    "addr:postcode":"b66 2ar",
    "addr:street":"Rolfe Street",
    "iso:country":"GB",
    "sg:address":"Unit 502 Rolfe Street",
    "sg:city":"Smethwick",
    "sg:classifiers":[
        {
            "category":"Retail",
            "subcategory":"Auto Repair",
            "type":"Services"
        }
    ],
    "sg:phone":"+44 121 565 4091",
    "sg:postcode":"B66 2AR",
    "sg:province":"West Midlands",
    "sg:tags":[
        "car",
        "upholsterer"
    ],
    "wof:name":"Star Trimmers & Upholsterers",
    "wof:placetype":"venue"
},
  "geometry": {"coordinates":[-1.962718,52.497639],"type":"Point"}
}