{
  "type": "Feature",
  "properties": {
    "iso:country":"GB",
    "sg:address":"6 Hawthorne Vale",
    "sg:city":"Edinburgh",
    "sg:classifiers":[
        {
            "category":"Building & Trades",
            "subcategory":"Construction",
            "type":"Services"
        }
    ],
    "sg:postcode":"EH6 5JT",
    "sg:province":"City of Edinburgh",
    "sg:tags":[
        "builder"
    ],
    "wof:name":"Portland Construction",
    "wof:placetype":"venue"
},
  "geometry": {"coordinates":[-3.1795799732,55.9714317322],"type":"Point"}
}