{
  "type": "Feature",
  "properties": {
    "addr:full":"Rounce Farm, Rounce Lane, West End Woking Surrey GU24 9NP",
    "addr:postcode":"gu24 9np",
    "addr:street":"Rounce Lane",
    "iso:country":"GB",
    "sg:address":"Rounce Farm, Rounce Lane, West End",
    "sg:city":"Woking",
    "sg:classifiers":[
        {
            "category":"Fast Food",
            "type":"Food & Drink"
        },
        {
            "category":"Building & Trades",
            "subcategory":"Equipment Rental",
            "type":"Services"
        }
    ],
    "sg:phone":"+44 1483 473729",
    "sg:postcode":"GU24 9NP",
    "sg:province":"Surrey",
    "sg:tags":[
        "hire",
        "catering",
        "take",
        "away"
    ],
    "wof:name":"Abacus Hire",
    "wof:placetype":"venue"
},
  "geometry": {"coordinates":[-0.6537899971,51.3367385864],"type":"Point"}
}