{
  "type": "Feature",
  "properties": {
    "addr:full":"Lanow, St Kew Bodmin Cornwall PL30 3ES",
    "addr:postcode":"pl30 3es",
    "addr:street":"St",
    "iso:country":"GB",
    "sg:address":"Lanow, St Kew",
    "sg:city":"Bodmin",
    "sg:classifiers":[
        {
            "category":"Farming",
            "subcategory":"Farm",
            "type":"Manufacturing & Wholesale Goods"
        }
    ],
    "sg:phone":"+44 1208 841205",
    "sg:postcode":"PL30 3ES",
    "sg:province":"Cornwall",
    "sg:tags":[
        "mixed",
        "crop"
    ],
    "wof:name":"B J Hawken & Son",
    "wof:placetype":"venue"
},
  "geometry": {"coordinates":[-4.78939,50.562111],"type":"Point"}
}