{
  "type": "Feature",
  "properties": {
    "iso:country":"GB",
    "sg:address":"14 Leytonstone Road",
    "sg:city":"London",
    "sg:classifiers":[
        {
            "category":"Home & Garden",
            "subcategory":"Carpets & Floor Coverings",
            "type":"Retail Goods"
        }
    ],
    "sg:phone":"+44 20 8519 2534",
    "sg:postcode":"E15 1SE",
    "sg:province":"Greater London",
    "sg:tags":[
        "carpets",
        "rug",
        "matting"
    ],
    "wof:name":"Marcon & Co",
    "wof:placetype":"venue"
},
  "geometry": {"coordinates":[0.006211,51.547348],"type":"Point"}
}