{
  "type": "Feature",
  "properties": {
    "addr:full":"The Old Maltings, Station Road, Helpringham Sleaford Lincolnshire NG34 0RB",
    "addr:postcode":"ng34 0rb",
    "addr:street":"Station Road",
    "iso:country":"GB",
    "sg:address":"The Old Maltings, Station Road, Helpringham",
    "sg:city":"Sleaford",
    "sg:classifiers":[
        {
            "category":"Professional",
            "subcategory":"Printing & Photocopies",
            "type":"Services"
        }
    ],
    "sg:postcode":"NG34 0RB",
    "sg:province":"Lincolnshire",
    "sg:tags":[
        "process",
        "screen",
        "printer"
    ],
    "wof:name":"Peter Morson",
    "wof:placetype":"venue"
},
  "geometry": {"coordinates":[-0.304989,52.95224],"type":"Point"}
}