{
  "type": "Feature",
  "properties": {
    "addr:full":"231 Wilton Road Carluke South Lanarkshire ML8 4LW",
    "addr:housenumber":"231",
    "addr:postcode":"ml8 4lw",
    "addr:street":"Wilton Road",
    "iso:country":"GB",
    "sg:address":"231 Wilton Road",
    "sg:city":"Carluke",
    "sg:classifiers":[
        {
            "category":"Retail",
            "subcategory":"Auto Repair",
            "type":"Services"
        }
    ],
    "sg:phone":"+44 1555 771051",
    "sg:postcode":"ML8 4LW",
    "sg:province":"South Lanarkshire",
    "sg:tags":[
        "rebuilding",
        "retreading",
        "tyre"
    ],
    "wof:name":"Stewart On Site",
    "wof:placetype":"venue"
},
  "geometry": {"coordinates":[-3.8168010712,55.7314414978],"type":"Point"}
}