{
  "type": "Feature",
  "properties": {
    "addr:full":"Kincraig Kingussie Highland PH21 1NX",
    "addr:postcode":"ph21 1nx",
    "iso:country":"GB",
    "sg:address":"Kincraig",
    "sg:city":"Kingussie",
    "sg:classifiers":[
        {
            "category":"Farming",
            "subcategory":"Livestock Farm",
            "type":"Manufacturing & Wholesale Goods"
        }
    ],
    "sg:postcode":"PH21 1NX",
    "sg:province":"Highland",
    "sg:tags":[
        "others"
    ],
    "wof:name":"Jane Williamson",
    "wof:placetype":"venue"
},
  "geometry": {"coordinates":[-4.010119915,57.0910377502],"type":"Point"}
}