{
  "type": "Feature",
  "properties": {
    "addr:full":"4 Burke Road Totnes Devon TQ9 5XL",
    "addr:housenumber":"4",
    "addr:postcode":"tq9 5xl",
    "addr:street":"Burke Road",
    "iso:country":"GB",
    "sg:address":"4 Burke Road",
    "sg:city":"Totnes",
    "sg:classifiers":[
        {
            "category":"Retail",
            "subcategory":"Auto Repair",
            "type":"Services"
        }
    ],
    "sg:phone":"+44 1803 863123",
    "sg:postcode":"TQ9 5XL",
    "sg:province":"Devon",
    "sg:tags":[
        "car",
        "servicing",
        "radiator"
    ],
    "wof:name":"Totnes Radiators",
    "wof:placetype":"venue"
},
  "geometry": {"coordinates":[-3.6825330257,50.4347114563],"type":"Point"}
}