{
  "type": "Feature",
  "properties": {
    "iso:country":"GB",
    "sg:address":"82 Brookley Road",
    "sg:city":"Brockenhurst",
    "sg:classifiers":[
        {
            "category":"Shopping",
            "subcategory":"Comic Books",
            "type":"Retail Goods"
        }
    ],
    "sg:phone":"+44 1749 830673",
    "sg:postcode":"SO42 7RA",
    "sg:province":"Hampshire",
    "sg:tags":[
        "jeweller",
        "sale",
        "jewellery"
    ],
    "wof:name":"Anthony French",
    "wof:placetype":"venue"
},
  "geometry": {"coordinates":[-1.579519,50.819466],"type":"Point"}
}