{
  "type": "Feature",
  "properties": {
    "iso:country":"GB",
    "sg:address":"Unit 3, Chase Street",
    "sg:city":"Luton",
    "sg:classifiers":[
        {
            "category":"Manufacturing",
            "subcategory":"Tools & Machinery",
            "type":"Manufacturing & Wholesale Goods"
        }
    ],
    "sg:phone":"+44 1582 725591",
    "sg:postcode":"LU1 3QZ",
    "sg:province":"Bedfordshire",
    "sg:tags":[
        "design",
        "maker"
    ],
    "wof:name":"The Luton Jig & Tool Co. Ltd.",
    "wof:placetype":"venue"
},
  "geometry": {"coordinates":[-0.412639,51.872463],"type":"Point"}
}