{
  "type": "Feature",
  "properties": {
    "iso:country":"GB",
    "sg:address":"3 Lifeboat Avenue",
    "sg:city":"Skegness",
    "sg:classifiers":[
        {
            "category":"Building & Trades",
            "subcategory":"Plumbing",
            "type":"Services"
        }
    ],
    "sg:phone":"+44 1754 769229",
    "sg:postcode":"PE25 3EW",
    "sg:province":"Lincolnshire",
    "sg:tags":[
        "heating"
    ],
    "wof:name":"M Claydon",
    "wof:placetype":"venue"
},
  "geometry": {"coordinates":[0.3421260118,53.1359901428],"type":"Point"}
}