{
  "type": "Feature",
  "properties": {
    "iso:country":"GB",
    "sg:address":"Unit 4, Harcroft Mill, Off Campbell St, Rivelton",
    "sg:city":"Preston",
    "sg:classifiers":[
        {
            "category":"Shopping",
            "subcategory":"Clothing, Apparel, & Fashions",
            "type":"Retail Goods"
        }
    ],
    "sg:postcode":"PR1 5LX",
    "sg:province":"Lancashire",
    "sg:tags":[
        "clothing",
        "fabric"
    ],
    "wof:name":"Exclusive Jeans Co",
    "wof:placetype":"venue"
},
  "geometry": {"coordinates":[-2.68636,53.762211],"type":"Point"}
}