{
  "type": "Feature",
  "properties": {
    "iso:country":"GB",
    "sg:address":"Jackson Ct",
    "sg:city":"High Wycombe",
    "sg:classifiers":[
        {
            "category":"Real Estate",
            "subcategory":"Architect",
            "type":"Services"
        }
    ],
    "sg:phone":"+44 1494 813206",
    "sg:postcode":"HP15 7TZ",
    "sg:province":"Buckinghamshire",
    "wof:name":"Large O'Connor Associates",
    "wof:placetype":"venue"
},
  "geometry": {"coordinates":[-0.7100510001,51.6482276917],"type":"Point"}
}