{
  "type": "Feature",
  "properties": {
    "iso:country":"GB",
    "sg:address":"Suite 202, Coventry Chambers, 1 Coventry Road",
    "sg:city":"Ilford",
    "sg:classifiers":[
        {
            "category":"Wholesale",
            "subcategory":"Books, Periodicals, & Newspapers",
            "type":"Manufacturing & Wholesale Goods"
        }
    ],
    "sg:phone":"+44 20 8262 9000",
    "sg:postcode":"IG1 4QR",
    "sg:province":"Essex",
    "sg:tags":[
        "publishing"
    ],
    "wof:name":"Prime London Properties",
    "wof:placetype":"venue"
},
  "geometry": {"coordinates":[0.0671150014,51.5637512207],"type":"Point"}
}