{
  "type": "Feature",
  "properties": {
    "iso:country":"GB",
    "sg:address":"180 Tuckton Road",
    "sg:city":"Bournemouth",
    "sg:classifiers":[
        {
            "category":"Shopping",
            "subcategory":"Clothing, Apparel, & Fashions",
            "type":"Retail Goods"
        }
    ],
    "sg:phone":"+44 1202 417646",
    "sg:postcode":"BH6 3AA",
    "sg:province":"Dorset",
    "sg:tags":[
        "shop"
    ],
    "wof:name":"Flamingo",
    "wof:placetype":"venue"
},
  "geometry": {"coordinates":[-1.791677,50.728367],"type":"Point"}
}