{
  "type": "Feature",
  "properties": {
    "iso:country":"GB",
    "sg:address":"Windrush Ho, The Business Centre, Little Green, Saxte",
    "sg:city":"Woodbridge",
    "sg:classifiers":[
        {
            "category":"Professional",
            "subcategory":"Research",
            "type":"Services"
        }
    ],
    "sg:postcode":"IP13 9QY",
    "sg:province":"Suffolk",
    "sg:tags":[
        "market"
    ],
    "wof:name":"Future Intelligence Ltd",
    "wof:placetype":"venue"
},
  "geometry": {"coordinates":[1.2952500582,52.2463111877],"type":"Point"}
}