{
  "type": "Feature",
  "properties": {
    "addr:full":"246 Kingston Rd New Malden Surrey KT3 3RN",
    "addr:housenumber":"246",
    "addr:postcode":"kt3 3rn",
    "addr:street":"Kingston Rd",
    "iso:country":"GB",
    "sg:address":"246 Kingston Rd",
    "sg:city":"New Malden",
    "sg:classifiers":[
        {
            "category":"Home & Garden",
            "subcategory":"Home Furnishings",
            "type":"Retail Goods"
        }
    ],
    "sg:postcode":"KT3 3RN",
    "sg:province":"Surrey",
    "sg:tags":[
        "mantelpiece",
        "fireplace"
    ],
    "wof:name":"Homefires",
    "wof:placetype":"venue"
},
  "geometry": {"coordinates":[-0.274538,51.403305],"type":"Point"}
}