{
  "type": "Feature",
  "properties": {
    "addr:full":"2 Laburnum Close, Kinver Stourbridge Shropshire DY7 6BJ",
    "addr:housenumber":"2",
    "addr:postcode":"dy7 6bj",
    "addr:street":"Laburnum Close",
    "iso:country":"GB",
    "sg:address":"2 Laburnum Close, Kinver",
    "sg:city":"Stourbridge",
    "sg:classifiers":[
        {
            "category":"Real Estate",
            "subcategory":"Architect",
            "type":"Services"
        }
    ],
    "sg:postcode":"DY7 6BJ",
    "sg:province":"Shropshire",
    "wof:name":"Idealchoice Ltd.",
    "wof:placetype":"venue"
},
  "geometry": {"coordinates":[-2.236892,52.456573],"type":"Point"}
}