{
  "type": "Feature",
  "properties": {
    "addr:full":"Third Floor Kimberley Ho, 47 Vaughan Way Leicester Leicestershire LE1 4SG",
    "addr:housenumber":"third;47",
    "addr:postcode":"le1 4sg",
    "addr:street":"Vaughan Way",
    "iso:country":"GB",
    "sg:address":"Third Floor Kimberley Ho, 47 Vaughan Way",
    "sg:city":"Leicester",
    "sg:classifiers":[
        {
            "category":"Travel",
            "subcategory":"Travel Agent",
            "type":"Entertainment"
        }
    ],
    "sg:phone":"+44 116 253 8999",
    "sg:postcode":"LE1 4SG",
    "sg:province":"Leicestershire",
    "wof:name":"American Express Business Travel Centre",
    "wof:placetype":"venue"
},
  "geometry": {"coordinates":[-1.1403650045,52.6378860474],"type":"Point"}
}