{
  "type": "Feature",
  "properties": {
    "addr:full":"16 Oak Road, Great Cornard Sudbury Essex CO10 0EY",
    "addr:housenumber":"16",
    "addr:postcode":"co10 0ey",
    "addr:street":"Oak Road",
    "iso:country":"GB",
    "sg:address":"16 Oak Road, Great Cornard",
    "sg:city":"Sudbury",
    "sg:classifiers":[
        {
            "category":"Home & Garden",
            "subcategory":"Building Materials",
            "type":"Retail Goods"
        },
        {
            "category":"Building & Trades",
            "subcategory":"Construction",
            "type":"Services"
        }
    ],
    "sg:phone":"+44 1787 373120",
    "sg:postcode":"CO10 0EY",
    "sg:province":"Essex",
    "sg:tags":[
        "dry",
        "plasterers",
        "installers",
        "lining",
        "insulation",
        "screeders"
    ],
    "wof:name":"Geoffrey Swain",
    "wof:placetype":"venue"
},
  "geometry": {"coordinates":[0.7528719902,52.0321044922],"type":"Point"}
}