{
  "type": "Feature",
  "properties": {
    "iso:country":"GB",
    "sg:address":"98 Pembroke Avenue",
    "sg:city":"Enfield",
    "sg:classifiers":[
        {
            "category":"Social Services",
            "subcategory":"Retirement Home",
            "type":"Services"
        }
    ],
    "sg:postcode":"EN1 4EY",
    "sg:province":"Greater London",
    "sg:tags":[
        "residential",
        "care"
    ],
    "wof:name":"Redhill Care",
    "wof:placetype":"venue"
},
  "geometry": {"coordinates":[-0.053786,51.664726],"type":"Point"}
}