{
  "type": "Feature",
  "properties": {
    "addr:full":"37 Bull Street Holt Norfolk NR25 6HP",
    "addr:housenumber":"37",
    "addr:postcode":"nr25 6hp",
    "addr:street":"Bull Street",
    "iso:country":"GB",
    "sg:address":"37 Bull Street",
    "sg:city":"Holt",
    "sg:classifiers":[
        {
            "category":"Food & Beverages",
            "subcategory":"Bakery",
            "type":"Retail Goods"
        },
        {
            "category":"Food & Beverages",
            "subcategory":"Groceries & Convenience Stores",
            "type":"Retail Goods"
        }
    ],
    "sg:phone":"+44 1263 712229",
    "sg:postcode":"NR25 6HP",
    "sg:province":"Norfolk",
    "sg:tags":[
        "baker"
    ],
    "wof:name":"A & P Setchfield",
    "wof:placetype":"venue"
},
  "geometry": {"coordinates":[1.0901559591,52.9065704346],"type":"Point"}
}