{
  "type": "Feature",
  "properties": {
    "addr:full":"339 West End Lane London Greater London NW6 1RS",
    "addr:housenumber":"339",
    "addr:postcode":"nw6 1rs",
    "addr:street":"West End Lane",
    "iso:country":"GB",
    "sg:address":"339 West End Lane",
    "sg:city":"London",
    "sg:classifiers":[
        {
            "category":"Fast Food",
            "type":"Food & Drink"
        }
    ],
    "sg:postcode":"NW6 1RS",
    "sg:province":"Greater London",
    "sg:tags":[
        "away",
        "take"
    ],
    "wof:name":"Chicken Express Corporation Ltd.",
    "wof:placetype":"venue"
},
  "geometry": {"coordinates":[-0.193041,51.552052],"type":"Point"}
}