{
  "type": "Feature",
  "properties": {
    "addr:full":"Oystermouth Rd Swansea Neath Port Talbot SA1 3UL",
    "addr:postcode":"sa1 3ul",
    "addr:street":"Oystermouth Rd",
    "iso:country":"GB",
    "sg:address":"Oystermouth Rd",
    "sg:city":"Swansea",
    "sg:classifiers":[
        {
            "category":"Autos & Motor Vehicles",
            "subcategory":"Fuel & Gas Station",
            "type":"Retail Goods"
        }
    ],
    "sg:phone":"+44 1792 456939",
    "sg:postcode":"SA1 3UL",
    "sg:province":"Neath Port Talbot",
    "sg:tags":[
        "petrol",
        "filling"
    ],
    "wof:name":"Sandfields Service Station",
    "wof:placetype":"venue"
},
  "geometry": {"coordinates":[-3.9489049911,51.6147270203],"type":"Point"}
}