{
  "type": "Feature",
  "properties": {
    "addr:full":"26 St Johns Road, The Gables Bedlington Northumberland NE22 7DU",
    "addr:housenumber":"26",
    "addr:postcode":"ne22 7du",
    "addr:street":"St Johns Road",
    "iso:country":"GB",
    "sg:address":"26 St Johns Road, The Gables",
    "sg:city":"Bedlington",
    "sg:classifiers":[
        {
            "category":"Health Services",
            "subcategory":"Doctor",
            "type":"Services"
        },
        {
            "category":"Health Services",
            "subcategory":"Clinic",
            "type":"Services"
        }
    ],
    "sg:phone":"+44 1670 829889",
    "sg:postcode":"NE22 7DU",
    "sg:province":"Northumberland",
    "sg:tags":[
        "nh",
        "practitioners"
    ],
    "wof:name":"The Gables Medical Group",
    "wof:placetype":"venue"
},
  "geometry": {"coordinates":[-1.5648590326,55.1406097412],"type":"Point"}
}