{
  "type": "Feature",
  "properties": {
    "iso:country":"GB",
    "sg:address":"The Harbour, Fishmart",
    "sg:city":"Wick",
    "sg:classifiers":[
        {
            "category":"Sports & Exercise",
            "subcategory":"Swimming Pool",
            "type":"Entertainment"
        }
    ],
    "sg:phone":"+44 1955 605956",
    "sg:postcode":"KW1 5HA",
    "sg:province":"Highland",
    "sg:tags":[
        "diver"
    ],
    "wof:name":"Fathoms Ltd.",
    "wof:placetype":"venue"
},
  "geometry": {"coordinates":[-3.085494,58.439243],"type":"Point"}
}