{
  "type": "Feature",
  "properties": {
    "addr:full":"4 Freeman Road Dukinfield Greater Manchester SK16 5AH",
    "addr:housenumber":"4",
    "addr:postcode":"sk16 5ah",
    "addr:street":"Freeman Road",
    "iso:country":"GB",
    "sg:address":"4 Freeman Road",
    "sg:city":"Dukinfield",
    "sg:classifiers":[
        {
            "category":"Building & Trades",
            "subcategory":"Construction",
            "type":"Services"
        }
    ],
    "sg:phone":"+44 161 344 0282",
    "sg:postcode":"SK16 5AH",
    "sg:province":"Greater Manchester",
    "sg:tags":[
        "tiling",
        "contractor"
    ],
    "wof:name":"D Longworth Tilemasters",
    "wof:placetype":"venue"
},
  "geometry": {"coordinates":[-2.086966,53.469391],"type":"Point"}
}