{
  "type": "Feature",
  "properties": {
    "addr:full":"Grange Drive Spalding Lincolnshire PE11 2DX",
    "addr:postcode":"pe11 2dx",
    "addr:street":"Grange Drive",
    "iso:country":"GB",
    "sg:address":"Grange Drive",
    "sg:city":"Spalding",
    "sg:classifiers":[
        {
            "category":"Health Services",
            "subcategory":"Nursing And Care Facility",
            "type":"Services"
        },
        {
            "category":"Social Services",
            "subcategory":"Retirement Home",
            "type":"Services"
        },
        {
            "category":"Government",
            "subcategory":"Office",
            "type":"Public Place"
        }
    ],
    "sg:phone":"+44 1775 723251",
    "sg:postcode":"PE11 2DX",
    "sg:province":"Lincolnshire",
    "sg:tags":[
        "residential",
        "local",
        "rest"
    ],
    "wof:name":"Halmer Grange Home for the Elderly",
    "wof:placetype":"venue"
},
  "geometry": {"coordinates":[-0.1425909996,52.786365509],"type":"Point"}
}