{
  "type": "Feature",
  "properties": {
    "iso:country":"GB",
    "sg:address":"Pwllhai",
    "sg:city":"Cardigan",
    "sg:classifiers":[
        {
            "category":"Shopping",
            "subcategory":"Bicycles & Sporting Goods",
            "type":"Retail Goods"
        }
    ],
    "sg:phone":"+44 1239 621275",
    "sg:postcode":"SA43 1DB",
    "sg:province":"Ceredigion",
    "sg:tags":[
        "cycle",
        "accessory"
    ],
    "wof:name":"New Image Bicycles",
    "wof:placetype":"venue"
},
  "geometry": {"coordinates":[-4.659929,52.083229],"type":"Point"}
}