{
  "type": "Feature",
  "properties": {
    "addr:full":"Windmill Villa, Church Lane Whitchurch Cheshire SY13 2NA",
    "addr:postcode":"sy13 2na",
    "addr:street":"Church Lane",
    "iso:country":"GB",
    "sg:address":"Windmill Villa, Church Lane",
    "sg:city":"Whitchurch",
    "sg:classifiers":[
        {
            "category":"Building & Trades",
            "subcategory":"Construction",
            "type":"Services"
        }
    ],
    "sg:postcode":"SY13 2NA",
    "sg:province":"Cheshire",
    "sg:tags":[
        "joiner",
        "carpenter"
    ],
    "wof:name":"F T Mottram",
    "wof:placetype":"venue"
},
  "geometry": {"coordinates":[-2.685209,52.970558],"type":"Point"}
}