{
  "type": "Feature",
  "properties": {
    "addr:full":"552 Crewe Rd Sandbach Cheshire CW11 3RY",
    "addr:housenumber":"552",
    "addr:postcode":"cw11 3ry",
    "addr:street":"Crewe Rd",
    "iso:country":"GB",
    "sg:address":"552 Crewe Rd",
    "sg:city":"Sandbach",
    "sg:classifiers":[
        {
            "category":"Utilities",
            "subcategory":"Natural Gas",
            "type":"Services"
        }
    ],
    "sg:phone":"+44 1270 764806",
    "sg:postcode":"CW11 3RY",
    "sg:province":"Cheshire",
    "sg:tags":[
        "control",
        "energy",
        "management",
        "system"
    ],
    "wof:name":"G.H.& D Goode",
    "wof:placetype":"venue"
},
  "geometry": {"coordinates":[-2.366079092,53.143989563],"type":"Point"}
}