{
  "type": "Feature",
  "properties": {
    "addr:full":"1 Ackworth Road Pontefract North Yorkshire WF8 3PA",
    "addr:housenumber":"1",
    "addr:postcode":"wf8 3pa",
    "addr:street":"Ackworth Road",
    "iso:country":"GB",
    "sg:address":"1 Ackworth Road",
    "sg:city":"Pontefract",
    "sg:classifiers":[
        {
            "category":"Organizations",
            "subcategory":"Membership Organization",
            "type":"Services"
        }
    ],
    "sg:phone":"+44 1977 703610",
    "sg:postcode":"WF8 3PA",
    "sg:province":"North Yorkshire",
    "sg:tags":[
        "club",
        "social"
    ],
    "wof:name":"Pontefract Masonic Hall Co Ltd",
    "wof:placetype":"venue"
},
  "geometry": {"coordinates":[-1.3172030449,53.6762161255],"type":"Point"}
}