{
  "type": "Feature",
  "properties": {
    "addr:full":"17 Court, Ord Rd, Rottingdean Brighton East Sussex BN2 7FD",
    "addr:housenumber":"17",
    "addr:postcode":"bn2 7fd",
    "addr:street":"Court Ord Rd",
    "iso:country":"GB",
    "sg:address":"17 Court, Ord Rd, Rottingdean",
    "sg:city":"Brighton",
    "sg:classifiers":[
        {
            "category":"Health Services",
            "subcategory":"Podiatrist",
            "type":"Services"
        }
    ],
    "sg:phone":"+44 1273 307020",
    "sg:postcode":"BN2 7FD",
    "sg:province":"East Sussex",
    "sg:tags":[
        "podiatrists",
        "chiropodist"
    ],
    "wof:name":"Barry Wright M.S.S.Ch M.B.Ch.A",
    "wof:placetype":"venue"
},
  "geometry": {"coordinates":[-0.0624409989,50.8127059937],"type":"Point"}
}