{
  "type": "Feature",
  "properties": {
    "addr:full":"Manor, Coach House, Bristol Rd, Keynsham Bristol City of Bristol BS31 2BB",
    "addr:postcode":"bs31 2bb",
    "addr:street":"Bristol Rd",
    "iso:country":"GB",
    "sg:address":"Manor, Coach House, Bristol Rd, Keynsham",
    "sg:city":"Bristol",
    "sg:classifiers":[
        {
            "category":"Building & Trades",
            "subcategory":"Construction",
            "type":"Services"
        }
    ],
    "sg:phone":"+44 117 986 5164",
    "sg:postcode":"BS31 2BB",
    "sg:province":"City of Bristol",
    "sg:tags":[
        "builder"
    ],
    "wof:name":"D.R Miles",
    "wof:placetype":"venue"
},
  "geometry": {"coordinates":[-2.5072538853,51.4184112549],"type":"Point"}
}