{
  "type": "Feature",
  "properties": {
    "addr:full":"Northend, Luckington Chippenham Gloucestershire SN14 6PN",
    "addr:postcode":"sn14 6pn",
    "iso:country":"GB",
    "sg:address":"Northend, Luckington",
    "sg:city":"Chippenham",
    "sg:classifiers":[
        {
            "category":"Building & Trades",
            "subcategory":"Construction",
            "type":"Services"
        }
    ],
    "sg:phone":"+44 1666 840836",
    "sg:postcode":"SN14 6PN",
    "sg:province":"Gloucestershire",
    "sg:tags":[
        "builder"
    ],
    "wof:name":"David Palmer Building Contractors Ltd.",
    "wof:placetype":"venue"
},
  "geometry": {"coordinates":[-2.2426660061,51.5536308289],"type":"Point"}
}