{
  "type": "Feature",
  "properties": {
    "iso:country":"GB",
    "sg:address":"Grove Farm, Grovesend",
    "sg:city":"Swansea",
    "sg:classifiers":[
        {
            "category":"Farming",
            "subcategory":"Livestock Farm",
            "type":"Manufacturing & Wholesale Goods"
        }
    ],
    "sg:phone":"+44 1792 898990",
    "sg:postcode":"SA4 1DB",
    "sg:province":"Carmarthenshire",
    "sg:tags":[
        "others"
    ],
    "wof:name":"S.L Williams & Son",
    "wof:placetype":"venue"
},
  "geometry": {"coordinates":[-4.03923,51.68792],"type":"Point"}
}