{
  "type": "Feature",
  "properties": {
    "addr:full":"96-98 Ramsgate Road Margate Kent CT9 5RY",
    "addr:housenumber":"96-98",
    "addr:postcode":"ct9 5ry",
    "addr:street":"Ramsgate Road",
    "iso:country":"GB",
    "sg:address":"96-98 Ramsgate Road",
    "sg:city":"Margate",
    "sg:classifiers":[
        {
            "category":"Fast Food",
            "type":"Food & Drink"
        }
    ],
    "sg:phone":"+44 1843 226556",
    "sg:postcode":"CT9 5RY",
    "sg:province":"Kent",
    "sg:tags":[
        "away",
        "meal",
        "outlet",
        "take"
    ],
    "wof:name":"Baba Kebab House",
    "wof:placetype":"venue"
},
  "geometry": {"coordinates":[1.383768,51.37899],"type":"Point"}
}