{
  "type": "Feature",
  "properties": {
    "addr:full":"76 The Bridges Sunderland Tyne and Wear SR1 3LE",
    "addr:housenumber":"76;bridges",
    "addr:postcode":"sr1 3le",
    "addr:street":"The",
    "iso:country":"GB",
    "sg:address":"76 The Bridges",
    "sg:city":"Sunderland",
    "sg:classifiers":[
        {
            "category":"Shopping",
            "subcategory":"Baby Store",
            "type":"Retail Goods"
        }
    ],
    "sg:phone":"+44 191 514 4237",
    "sg:postcode":"SR1 3LE",
    "sg:province":"Tyne and Wear",
    "sg:tags":[
        "babywear",
        "childrens"
    ],
    "wof:name":"Adams Childrenswear Ltd.",
    "wof:placetype":"venue"
},
  "geometry": {"coordinates":[-1.38629,54.90229],"type":"Point"}
}