{
  "type": "Feature",
  "properties": {
    "addr:full":"Blade House, Battersea Road Stockport Cheshire SK4 3EA",
    "addr:postcode":"sk4 3ea",
    "addr:street":"Battersea Road",
    "iso:country":"GB",
    "sg:address":"Blade House, Battersea Road",
    "sg:city":"Stockport",
    "sg:classifiers":[
        {
            "category":"Professional",
            "subcategory":"Computer Services",
            "type":"Services"
        }
    ],
    "sg:phone":"+44 161 442 2603",
    "sg:postcode":"SK4 3EA",
    "sg:province":"Cheshire",
    "sg:tags":[
        "system",
        "software"
    ],
    "wof:name":"A P H Computers Ltd.",
    "wof:placetype":"venue"
},
  "geometry": {"coordinates":[-2.202249,53.40834],"type":"Point"}
}