{
  "type": "Feature",
  "properties": {
    "addr:full":"Staff House, Adeyfield Lodge, Adeyfield Road Hemel Hempstead Hertfordshire HP2 5JU",
    "addr:postcode":"hp2 5ju",
    "addr:street":"Adeyfield Road",
    "iso:country":"GB",
    "sg:address":"Staff House, Adeyfield Lodge, Adeyfield Road",
    "sg:city":"Hemel Hempstead",
    "sg:classifiers":[
        {
            "category":"Government",
            "subcategory":"Office",
            "type":"Public Place"
        }
    ],
    "sg:phone":"+44 1442 247464",
    "sg:postcode":"HP2 5JU",
    "sg:province":"Hertfordshire",
    "sg:tags":[
        "education",
        "agency",
        "authority"
    ],
    "wof:name":"Leonard Cheshire Foundation (dacorum Care At Home",
    "wof:placetype":"venue"
},
  "geometry": {"coordinates":[-0.4675459862,51.7569732666],"type":"Point"}
}