{
  "type": "Feature",
  "properties": {
    "addr:full":"Scotts Farm, Peakirk Road, Glinton Peterborough Cambridgeshire PE6 7LT",
    "addr:postcode":"pe6 7lt",
    "addr:street":"Scotts;Peakirk Road",
    "iso:country":"GB",
    "sg:address":"Scotts Farm, Peakirk Road, Glinton",
    "sg:city":"Peterborough",
    "sg:classifiers":[
        {
            "category":"Farming",
            "subcategory":"Farm",
            "type":"Manufacturing & Wholesale Goods"
        }
    ],
    "sg:phone":"+44 1733 252007",
    "sg:postcode":"PE6 7LT",
    "sg:province":"Cambridgeshire",
    "sg:tags":[
        "mixed",
        "crop"
    ],
    "wof:name":"W Neaverson & Son",
    "wof:placetype":"venue"
},
  "geometry": {"coordinates":[-0.296139,52.638981],"type":"Point"}
}