{
  "type": "Feature",
  "properties": {
    "addr:full":"Main Street, Bridge Of Earn Perth Perth and Kinross PH2 9PL",
    "addr:postcode":"ph2 9pl",
    "addr:street":"Main Street",
    "iso:country":"GB",
    "sg:address":"Main Street, Bridge Of Earn",
    "sg:city":"Perth",
    "sg:classifiers":[
        {
            "category":"Food & Beverages",
            "subcategory":"Groceries & Convenience Stores",
            "type":"Retail Goods"
        }
    ],
    "sg:postcode":"PH2 9PL",
    "sg:province":"Perth and Kinross",
    "wof:name":"Spar Store",
    "wof:placetype":"venue"
},
  "geometry": {"coordinates":[-3.404575,56.346127],"type":"Point"}
}