{
  "type": "Feature",
  "properties": {
    "addr:full":"9 Powke La Rowley Regis West Midlands B65 0AA",
    "addr:housenumber":"9",
    "addr:postcode":"b65 0aa",
    "addr:street":"Powke La Rowley",
    "iso:country":"GB",
    "sg:address":"9 Powke La",
    "sg:city":"Rowley Regis",
    "sg:classifiers":[
        {
            "category":"Professional",
            "subcategory":"Secretarial Services",
            "type":"Services"
        }
    ],
    "sg:phone":"+44 121 561 2033",
    "sg:postcode":"B65 0AA",
    "sg:province":"West Midlands",
    "wof:name":"C A Dowling",
    "wof:placetype":"venue"
},
  "geometry": {"coordinates":[-2.047601,52.475853],"type":"Point"}
}