{
  "type": "Feature",
  "properties": {
    "addr:full":"Thoroughfare Lane, Winthorpe Newark Nottinghamshire NG24 2NN",
    "addr:postcode":"ng24 2nn",
    "addr:street":"Thoroughfare Lane",
    "iso:country":"GB",
    "sg:address":"Thoroughfare Lane, Winthorpe",
    "sg:city":"Newark",
    "sg:classifiers":[
        {
            "category":"Education",
            "subcategory":"School",
            "type":"Public Place"
        }
    ],
    "sg:phone":"+44 1636 680060",
    "sg:postcode":"NG24 2NN",
    "sg:province":"Nottinghamshire",
    "sg:tags":[
        "local",
        "authority"
    ],
    "wof:name":"Winthorpe Primary School",
    "wof:placetype":"venue"
},
  "geometry": {"coordinates":[-0.7766669989,53.104057312],"type":"Point"}
}