{
  "type": "Feature",
  "properties": {
    "iso:country":"GB",
    "sg:address":"2 Banning Street",
    "sg:city":"London",
    "sg:classifiers":[
        {
            "category":"Shopping",
            "subcategory":"Catalog Store",
            "type":"Retail Goods"
        }
    ],
    "sg:phone":"+44 20 8853 1935",
    "sg:postcode":"SE10 9PH",
    "sg:province":"Greater London",
    "sg:tags":[
        "mail",
        "order",
        "house"
    ],
    "wof:name":"Supreme Sports",
    "wof:placetype":"venue"
},
  "geometry": {"coordinates":[0.000886,51.4855537415],"type":"Point"}
}