{
  "type": "Feature",
  "properties": {
    "addr:full":"Farnborough Station, Farnborough Rd Farnborough Hampshire GU14 7NL",
    "addr:postcode":"gu14 7nl",
    "addr:street":"Farnborough Rd",
    "iso:country":"GB",
    "sg:address":"Farnborough Station, Farnborough Rd",
    "sg:city":"Farnborough",
    "sg:classifiers":[
        {
            "category":"Shopping",
            "subcategory":"News",
            "type":"Retail Goods"
        }
    ],
    "sg:phone":"+44 1252 544717",
    "sg:postcode":"GU14 7NL",
    "sg:province":"Hampshire",
    "sg:tags":[
        "newsagent"
    ],
    "wof:name":"A Spaven",
    "wof:placetype":"venue"
},
  "geometry": {"coordinates":[-0.7555689812,51.2937240601],"type":"Point"}
}