{
  "type": "Feature",
  "properties": {
    "addr:full":"9 Cwrt Elusendy Llanelli Carmarthenshire SA15 1LD",
    "addr:housenumber":"9",
    "addr:postcode":"sa15 1ld",
    "addr:street":"Cwrt Elusendy;Carmarthenshire",
    "iso:country":"GB",
    "sg:address":"9 Cwrt Elusendy",
    "sg:city":"Llanelli",
    "sg:classifiers":[
        {
            "category":"Organizations",
            "subcategory":"Religious Organization",
            "type":"Services"
        }
    ],
    "sg:phone":"+44 1554 772045",
    "sg:postcode":"SA15 1LD",
    "sg:province":"Carmarthenshire",
    "sg:tags":[
        "organisation"
    ],
    "wof:name":"Convent Little Sisters of Assumption",
    "wof:placetype":"venue"
},
  "geometry": {"coordinates":[-4.155084,51.68055],"type":"Point"}
}