{
  "type": "Feature",
  "properties": {
    "addr:full":"13 Market Hill St Ives Cambridgeshire PE27 5AL",
    "addr:housenumber":"13",
    "addr:postcode":"pe27 5al",
    "addr:street":"Market Hill",
    "iso:country":"GB",
    "sg:address":"13 Market Hill",
    "sg:city":"St Ives",
    "sg:classifiers":[
        {
            "category":"Shopping",
            "subcategory":"Gifts & Souvenirs",
            "type":"Retail Goods"
        }
    ],
    "sg:postcode":"PE27 5AL",
    "sg:province":"Cambridgeshire",
    "sg:tags":[
        "shop"
    ],
    "wof:name":"Karen Whittaker",
    "wof:placetype":"venue"
},
  "geometry": {"coordinates":[-0.0730059966,52.3231697083],"type":"Point"}
}