{
  "type": "Feature",
  "properties": {
    "addr:full":"2 The Leas, Chestfield Whitstable Kent CT5 3QQ",
    "addr:housenumber":"2",
    "addr:postcode":"ct5 3qq",
    "addr:street":"The Leas;Whitstable",
    "iso:country":"GB",
    "sg:address":"2 The Leas, Chestfield",
    "sg:city":"Whitstable",
    "sg:classifiers":[
        {
            "category":"Retail",
            "subcategory":"Driving School",
            "type":"Services"
        }
    ],
    "sg:postcode":"CT5 3QQ",
    "sg:province":"Kent",
    "wof:name":"Colin Reed School of Motoring",
    "wof:placetype":"venue"
},
  "geometry": {"coordinates":[1.064282,51.354702],"type":"Point"}
}