{
  "type": "Feature",
  "properties": {
    "addr:full":"522 Victoria Rd, Queenspark Glasgow Glasgow City G42 8BG",
    "addr:housenumber":"522",
    "addr:postcode":"g42 8bg",
    "addr:street":"Victoria Rd",
    "iso:country":"GB",
    "sg:address":"522 Victoria Rd, Queenspark",
    "sg:city":"Glasgow",
    "sg:classifiers":[
        {
            "category":"Banks & Credit Unions",
            "subcategory":"Financial Services",
            "type":"Services"
        }
    ],
    "sg:postcode":"G42 8BG",
    "sg:province":"Glasgow City",
    "sg:tags":[
        "consultant"
    ],
    "wof:name":"Mortgage & Property Ltd",
    "wof:placetype":"venue"
},
  "geometry": {"coordinates":[-4.265966,55.834259],"type":"Point"}
}