{
  "type": "Feature",
  "properties": {
    "iso:country":"GB",
    "sg:address":"Albion Street",
    "sg:city":"Broadstairs",
    "sg:classifiers":[
        {
            "category":"Travel",
            "subcategory":"Hotels & Motels",
            "type":"Entertainment"
        }
    ],
    "sg:phone":"+44 1843 868071",
    "sg:postcode":"CT10 1AN",
    "sg:province":"Kent",
    "wof:name":"Royal Albion Hotel (Broadstairs) Ltd.",
    "wof:placetype":"venue"
},
  "geometry": {"coordinates":[1.443365,51.360062],"type":"Point"}
}