{
  "type": "Feature",
  "properties": {
    "iso:country":"GB",
    "sg:address":"9 Bellgreen Avenue",
    "sg:city":"Newcastle-upon-tyne",
    "sg:classifiers":[
        {
            "category":"Professional",
            "subcategory":"Management & Consulting",
            "type":"Services"
        }
    ],
    "sg:phone":"+44 191 236 4261",
    "sg:postcode":"NE3 5QR",
    "sg:province":"Tyne and Wear",
    "sg:tags":[
        "consultant",
        "business"
    ],
    "wof:name":"Forster Barham Consultants Ltd.",
    "wof:placetype":"venue"
},
  "geometry": {"coordinates":[-1.615201,55.024513],"type":"Point"}
}