{
  "type": "Feature",
  "properties": {
    "iso:country":"GB",
    "sg:address":"21 St Teilos Road",
    "sg:city":"Abergavenny",
    "sg:classifiers":[
        {
            "category":"Taxi",
            "type":"Transportation"
        },
        {
            "category":"Military Area",
            "subcategory":"Air Force Base",
            "type":"Public Place"
        }
    ],
    "sg:phone":"+44 1873 857233",
    "sg:postcode":"NP7 6HA",
    "sg:province":"Herefordshire",
    "sg:tags":[
        "mini",
        "hire",
        "private",
        "cab"
    ],
    "wof:name":"Station Cars",
    "wof:placetype":"venue"
},
  "geometry": {"coordinates":[-3.009557,51.832085],"type":"Point"}
}