{
  "type": "Feature",
  "properties": {
    "iso:country":"GB",
    "sg:address":"Andersons Yard, Stow Road",
    "sg:city":"Bury St Edmunds",
    "sg:classifiers":[
        {
            "category":"Autos & Motor Vehicles",
            "subcategory":"Automobile Sales",
            "type":"Retail Goods"
        }
    ],
    "sg:phone":"+44 1359 232354",
    "sg:postcode":"IP31 2HZ",
    "sg:province":"Suffolk",
    "sg:tags":[
        "car"
    ],
    "wof:name":"G L Car Sales",
    "wof:placetype":"venue"
},
  "geometry": {"coordinates":[0.832679987,52.2959098816],"type":"Point"}
}