{
  "type": "Feature",
  "properties": {
    "iso:country":"GB",
    "sg:address":"8 Souterhouse Rd",
    "sg:city":"Coatbridge",
    "sg:classifiers":[
        {
            "category":"Government",
            "subcategory":"Post Office",
            "type":"Public Place"
        }
    ],
    "sg:phone":"+44 1236 710555",
    "sg:postcode":"ML5 4AA",
    "sg:province":"North Lanarkshire",
    "sg:tags":[
        "messenger",
        "courier"
    ],
    "wof:name":"On Time Transport 97 Ltd",
    "wof:placetype":"venue"
},
  "geometry": {"coordinates":[-4.033914,55.85437],"type":"Point"}
}