{
  "type": "Feature",
  "properties": {
    "addr:full":"Temple St, Fenton Stoke-on-trent Staffordshire ST4 4NR",
    "addr:postcode":"staffordshire st4 4nr",
    "addr:street":"Temple St",
    "iso:country":"GB",
    "sg:address":"Temple St, Fenton",
    "sg:city":"Stoke-on-trent",
    "sg:classifiers":[
        {
            "category":"Social Services",
            "subcategory":"Adult Care",
            "type":"Services"
        },
        {
            "category":"Government",
            "subcategory":"Office",
            "type":"Public Place"
        }
    ],
    "sg:postcode":"ST4 4NR",
    "sg:province":"Staffordshire",
    "sg:tags":[
        "housing",
        "local",
        "sheltered"
    ],
    "wof:name":"Stoke-on-Trent City Council",
    "wof:placetype":"venue"
},
  "geometry": {"coordinates":[-2.1683690548,52.9994697571],"type":"Point"}
}