{
  "type": "Feature",
  "properties": {
    "addr:full":"18 Union Road London Greater London SW4 6JP",
    "addr:housenumber":"18",
    "addr:postcode":"sw4 6jp",
    "addr:street":"Union Road",
    "iso:country":"GB",
    "sg:address":"18 Union Road",
    "sg:city":"London",
    "sg:classifiers":[
        {
            "category":"Professional",
            "subcategory":"Computer Services",
            "type":"Services"
        }
    ],
    "sg:phone":"+44 20 7787 1130",
    "sg:postcode":"SW4 6JP",
    "sg:province":"Greater London",
    "sg:tags":[
        "system",
        "software"
    ],
    "wof:name":"P M Systems",
    "wof:placetype":"venue"
},
  "geometry": {"coordinates":[-0.1277289987,51.4692306519],"type":"Point"}
}