{
  "type": "Feature",
  "properties": {
    "addr:full":"Priory Court, 145 High Street West Bromwich West Midlands B70 6NY",
    "addr:housenumber":"145",
    "addr:postcode":"b70 6ny",
    "addr:street":"Priory;High Street",
    "iso:country":"GB",
    "sg:address":"Priory Court, 145 High Street",
    "sg:city":"West Bromwich",
    "sg:classifiers":[
        {
            "category":"Restaurant",
            "type":"Food & Drink"
        }
    ],
    "sg:phone":"+44 121 553 1319",
    "sg:postcode":"B70 6NY",
    "sg:province":"West Midlands",
    "sg:tags":[
        "indian",
        "-"
    ],
    "wof:name":"Shalimar Restaurant",
    "wof:placetype":"venue"
},
  "geometry": {"coordinates":[-1.989959,52.516312],"type":"Point"}
}