{
  "type": "Feature",
  "properties": {
    "addr:full":"17 High Street Turriff Aberdeenshire AB53 7ED",
    "addr:housenumber":"17",
    "addr:postcode":"ab53 7ed",
    "addr:street":"High Street",
    "iso:country":"GB",
    "sg:address":"17 High Street",
    "sg:city":"Turriff",
    "sg:classifiers":[
        {
            "category":"Banks & Credit Unions",
            "subcategory":"Financial Services",
            "type":"Services"
        }
    ],
    "sg:phone":"+44 1888 563557",
    "sg:postcode":"AB53 7ED",
    "sg:province":"Aberdeenshire",
    "sg:tags":[
        "building",
        "society"
    ],
    "wof:name":"Alliance & Leicester Plc",
    "wof:placetype":"venue"
},
  "geometry": {"coordinates":[-2.4614470005,57.5375518799],"type":"Point"}
}