{
  "type": "Feature",
  "properties": {
    "iso:country":"GB",
    "sg:address":"29 Baring Road",
    "sg:city":"Cowes",
    "sg:classifiers":[
        {
            "category":"Travel",
            "subcategory":"Hotels & Motels",
            "type":"Entertainment"
        }
    ],
    "sg:phone":"+44 1983 295178",
    "sg:postcode":"PO31 8DF",
    "sg:province":"Isle of Wight",
    "sg:website":"http://www.villa-rothsay.co.uk",
    "wof:name":"Villa Rothsay",
    "wof:placetype":"venue"
},
  "geometry": {"coordinates":[-1.303550005,50.765586853],"type":"Point"}
}