{
  "type": "Feature",
  "properties": {
    "addr:full":"96 Long Lane Rickmansworth Hertfordshire WD3 2YG",
    "addr:housenumber":"96",
    "addr:postcode":"wd3 2yg",
    "addr:street":"Long Lane",
    "iso:country":"GB",
    "sg:address":"96 Long Lane",
    "sg:city":"Rickmansworth",
    "sg:classifiers":[
        {
            "category":"Professional",
            "subcategory":"Computer Services",
            "type":"Services"
        }
    ],
    "sg:phone":"+44 1582 794864",
    "sg:postcode":"WD3 2YG",
    "sg:province":"Hertfordshire",
    "sg:tags":[
        "system",
        "software"
    ],
    "wof:name":"Quantum Learning Ltd.",
    "wof:placetype":"venue"
},
  "geometry": {"coordinates":[-0.507382,51.6366],"type":"Point"}
}