{
  "type": "Feature",
  "properties": {
    "addr:full":"65 Goldington Rd Bedford Bedfordshire MK40 3NB",
    "addr:housenumber":"65",
    "addr:postcode":"mk40 3nb",
    "addr:street":"Goldington Rd",
    "iso:country":"GB",
    "sg:address":"65 Goldington Rd",
    "sg:city":"Bedford",
    "sg:classifiers":[
        {
            "category":"Organizations",
            "subcategory":"Membership Organization",
            "type":"Services"
        }
    ],
    "sg:postcode":"MK40 3NB",
    "sg:province":"Bedfordshire",
    "sg:tags":[
        "club"
    ],
    "wof:name":"Doonsville Management Ltd",
    "wof:placetype":"venue"
},
  "geometry": {"coordinates":[-0.4565080106,52.1397247314],"type":"Point"}
}