{
  "type": "Feature",
  "properties": {
    "addr:full":"331 Euston Road London Greater London NW1 3AD",
    "addr:housenumber":"331",
    "addr:postcode":"nw1 3ad",
    "addr:street":"Euston Road",
    "iso:country":"GB",
    "sg:address":"331 Euston Road",
    "sg:city":"London",
    "sg:classifiers":[
        {
            "category":"Travel",
            "subcategory":"Travel Agent",
            "type":"Entertainment"
        }
    ],
    "sg:phone":"+44 20 7383 5151",
    "sg:postcode":"NW1 3AD",
    "sg:province":"Greater London",
    "wof:name":"Gifto Travels Ltd.",
    "wof:placetype":"venue"
},
  "geometry": {"coordinates":[-0.1399679929,51.5242843628],"type":"Point"}
}