{
  "type": "Feature",
  "properties": {
    "addr:full":"Upper Aston, Claverley Wolverhampton Shropshire WV5 7EE",
    "addr:postcode":"wv5 7ee",
    "addr:street":"Upper Aston",
    "iso:country":"GB",
    "sg:address":"Upper Aston, Claverley",
    "sg:city":"Wolverhampton",
    "sg:classifiers":[
        {
            "category":"Retail",
            "subcategory":"Repair Shop",
            "type":"Services"
        }
    ],
    "sg:phone":"+44 1746 710237",
    "sg:postcode":"WV5 7EE",
    "sg:province":"Shropshire",
    "sg:tags":[
        "upholsterer"
    ],
    "wof:name":"Exclusive Design",
    "wof:placetype":"venue"
},
  "geometry": {"coordinates":[-2.303123,52.537304],"type":"Point"}
}