{
  "type": "Feature",
  "properties": {
    "addr:full":"62 Church Street Enfield Greater London EN2 6AN",
    "addr:housenumber":"62",
    "addr:postcode":"en2 6an",
    "addr:street":"Church Street",
    "iso:country":"GB",
    "sg:address":"62 Church Street",
    "sg:city":"Enfield",
    "sg:classifiers":[
        {
            "category":"Personal",
            "subcategory":"Beauty Salon",
            "type":"Services"
        }
    ],
    "sg:phone":"+44 20 8366 2200",
    "sg:postcode":"EN2 6AN",
    "sg:province":"Greater London",
    "sg:tags":[
        "unisex",
        "hairdresser"
    ],
    "wof:name":"Actworth Ltd.",
    "wof:placetype":"venue"
},
  "geometry": {"coordinates":[-0.0855659992,51.6521530151],"type":"Point"}
}