{
  "type": "Feature",
  "properties": {
    "iso:country":"GB",
    "sg:address":"7 School Lane, Quedgeley",
    "sg:city":"Gloucester",
    "sg:classifiers":[
        {
            "category":"Personal",
            "subcategory":"Beauty Salon",
            "type":"Services"
        }
    ],
    "sg:postcode":"GL2 6PJ",
    "sg:province":"Gloucestershire",
    "sg:tags":[
        "unisex",
        "hairdresser"
    ],
    "wof:name":"Level 1 Hair Design",
    "wof:placetype":"venue"
},
  "geometry": {"coordinates":[-2.27917,51.8186],"type":"Point"}
}