{
  "type": "Feature",
  "properties": {
    "iso:country":"GB",
    "sg:address":"52 Upton Lane",
    "sg:city":"London",
    "sg:classifiers":[
        {
            "category":"Professional",
            "subcategory":"Lawyer & Legal Services",
            "type":"Services"
        }
    ],
    "sg:phone":"+44 20 8552 4850",
    "sg:postcode":"E7 9LN",
    "sg:province":"Greater London",
    "sg:tags":[
        "solicitor"
    ],
    "wof:name":"Khan & Co",
    "wof:placetype":"venue"
},
  "geometry": {"coordinates":[0.025888,51.544819],"type":"Point"}
}