{
  "type": "Feature",
  "properties": {
    "iso:country":"GB",
    "sg:address":"Holderness House, Market Place, South Cave",
    "sg:city":"Brough",
    "sg:classifiers":[
        {
            "category":"Shopping",
            "subcategory":"Pharmacy",
            "type":"Retail Goods"
        }
    ],
    "sg:phone":"+44 1430 424200",
    "sg:postcode":"HU15 2AT",
    "sg:province":"East Riding of Yorkshire",
    "sg:tags":[
        "toiletry"
    ],
    "wof:name":"The Fun Workshop Ltd.",
    "wof:placetype":"venue"
},
  "geometry": {"coordinates":[-0.600922,53.770111],"type":"Point"}
}