{
  "type": "Feature",
  "properties": {
    "addr:full":"5 The Green, Drayton Abingdon Oxfordshire OX14 4JA",
    "addr:housenumber":"5",
    "addr:postcode":"ox14 4ja",
    "addr:street":"The Green",
    "iso:country":"GB",
    "sg:address":"5 The Green, Drayton",
    "sg:city":"Abingdon",
    "sg:classifiers":[
        {
            "category":"Home & Garden",
            "subcategory":"Hardware",
            "type":"Retail Goods"
        }
    ],
    "sg:phone":"+44 1235 531497",
    "sg:postcode":"OX14 4JA",
    "sg:province":"Oxfordshire",
    "sg:tags":[
        "merchant",
        "ironmonger"
    ],
    "wof:name":"A L Vickery & Son",
    "wof:placetype":"venue"
},
  "geometry": {"coordinates":[-1.3125040531,51.6438903809],"type":"Point"}
}