{
  "type": "Feature",
  "properties": {
    "addr:full":"8 Lower Sloane Street London Greater London SW1W 8BL",
    "addr:housenumber":"8",
    "addr:postcode":"sw1w 8bl",
    "addr:street":"Lower Sloane Street",
    "iso:country":"GB",
    "sg:address":"8 Lower Sloane Street",
    "sg:city":"London",
    "sg:classifiers":[
        {
            "category":"Health Services",
            "subcategory":"Dentist",
            "type":"Services"
        }
    ],
    "sg:phone":"+44 20 7730 2500",
    "sg:postcode":"SW1W 8BL",
    "sg:province":"Greater London",
    "wof:name":"The Number 8 Partnership",
    "wof:placetype":"venue"
},
  "geometry": {"coordinates":[-0.1576700062,51.4919395447],"type":"Point"}
}