{
  "type": "Feature",
  "properties": {
    "addr:full":"153 Handsworth New Road Birmingham West Midlands B18 4PU",
    "addr:housenumber":"153",
    "addr:postcode":"b18 4pu",
    "addr:street":"Handsworth New Road",
    "iso:country":"GB",
    "sg:address":"153 Handsworth New Road",
    "sg:city":"Birmingham",
    "sg:classifiers":[
        {
            "category":"Shopping",
            "subcategory":"News",
            "type":"Retail Goods"
        }
    ],
    "sg:phone":"+44 121 554 0162",
    "sg:postcode":"B18 4PU",
    "sg:province":"West Midlands",
    "sg:tags":[
        "newsagent"
    ],
    "wof:name":"Waj's News",
    "wof:placetype":"venue"
},
  "geometry": {"coordinates":[-1.939387,52.496197],"type":"Point"}
}