{
  "type": "Feature",
  "properties": {
    "addr:full":"127 Shard End Crescent, Castle Bromwich Birmingham West Midlands B34 7AG",
    "addr:housenumber":"127",
    "addr:postcode":"7ag",
    "addr:street":"Shard End Crescent",
    "iso:country":"GB",
    "sg:address":"127 Shard End Crescent, Castle Bromwich",
    "sg:city":"Birmingham",
    "sg:classifiers":[
        {
            "category":"Shopping",
            "subcategory":"News",
            "type":"Retail Goods"
        }
    ],
    "sg:phone":"+44 121 748 7591",
    "sg:postcode":"B34 7AG",
    "sg:province":"West Midlands",
    "sg:tags":[
        "newsagent"
    ],
    "wof:name":"Dillons Newsagents Ltd.",
    "wof:placetype":"venue"
},
  "geometry": {"coordinates":[-1.7770979404,52.4953231812],"type":"Point"}
}