{
  "type": "Feature",
  "properties": {
    "iso:country":"GB",
    "sg:address":"14 Manor Park",
    "sg:city":"London",
    "sg:classifiers":[
        {
            "category":"Education",
            "subcategory":"Library",
            "type":"Public Place"
        }
    ],
    "sg:postcode":"SE13 5RN",
    "sg:province":"Greater London",
    "sg:tags":[
        "book"
    ],
    "wof:name":"Manor Park (Lee) Management Ltd.",
    "wof:placetype":"venue"
},
  "geometry": {"coordinates":[-0.002165,51.458057],"type":"Point"}
}