{
  "type": "Feature",
  "properties": {
    "iso:country":"GB",
    "sg:address":"Red Roofs, Farley Way",
    "sg:city":"Hastings",
    "sg:classifiers":[
        {
            "category":"Real Estate",
            "subcategory":"Surveying",
            "type":"Services"
        }
    ],
    "sg:postcode":"TN35 4AS",
    "sg:province":"East Sussex",
    "sg:tags":[
        "surveyor",
        "land"
    ],
    "wof:name":"Boundary Surveys",
    "wof:placetype":"venue"
},
  "geometry": {"coordinates":[0.66005,50.878841],"type":"Point"}
}