{
  "type": "Feature",
  "properties": {
    "addr:full":"Rock House, Blazefield Harrogate North Yorkshire HG3 5DP",
    "addr:postcode":"hg3 5dp",
    "addr:street":"Blazefield",
    "iso:country":"GB",
    "sg:address":"Rock House, Blazefield",
    "sg:city":"Harrogate",
    "sg:classifiers":[
        {
            "category":"Farming",
            "subcategory":"Livestock Farm",
            "type":"Manufacturing & Wholesale Goods"
        },
        {
            "category":"Retail",
            "subcategory":"Auto Repair",
            "type":"Services"
        }
    ],
    "sg:phone":"+44 1423 712148",
    "sg:postcode":"HG3 5DP",
    "sg:province":"North Yorkshire",
    "sg:tags":[
        "car",
        "vehicle",
        "commercial",
        "others"
    ],
    "wof:name":"Glasshouses Trout Farm Ltd",
    "wof:placetype":"venue"
},
  "geometry": {"coordinates":[-1.7288819551,54.082359314],"type":"Point"}
}