{
  "type": "Feature",
  "properties": {
    "iso:country":"GB",
    "sg:address":"633 Garratt Lane",
    "sg:city":"London",
    "sg:classifiers":[
        {
            "category":"Shopping",
            "subcategory":"Shoes",
            "type":"Retail Goods"
        }
    ],
    "sg:phone":"+44 20 8946 2187",
    "sg:postcode":"SW18 4SX",
    "sg:province":"Greater London",
    "wof:name":"S Bruce",
    "wof:placetype":"venue"
},
  "geometry": {"coordinates":[-0.186664,51.437988],"type":"Point"}
}