{
  "type": "Feature",
  "properties": {
    "addr:full":"Horsefair Studios, 5 Horsefair Mews Romsey Hampshire SO51 8JG",
    "addr:housenumber":"5",
    "addr:postcode":"so51 8jg",
    "addr:street":"Horsefair Mews",
    "iso:country":"GB",
    "sg:address":"Horsefair Studios, 5 Horsefair Mews",
    "sg:city":"Romsey",
    "sg:classifiers":[
        {
            "category":"Utilities",
            "type":"Services"
        }
    ],
    "sg:phone":"+44 870 744 7799",
    "sg:postcode":"SO51 8JG",
    "sg:province":"Hampshire",
    "sg:tags":[
        "connection",
        "provider",
        "internet"
    ],
    "wof:name":"4TH Wave Technologies Ltd",
    "wof:placetype":"venue"
},
  "geometry": {"coordinates":[-1.495391,50.988583],"type":"Point"}
}