{
  "type": "Feature",
  "properties": {
    "addr:full":"29a Wadeson Road, Ardwick Manchester Greater Manchester M13 9UG",
    "addr:housenumber":"29a",
    "addr:postcode":"m13 9ug",
    "addr:street":"Wadeson Road",
    "iso:country":"GB",
    "sg:address":"29a Wadeson Road, Ardwick",
    "sg:city":"Manchester",
    "sg:classifiers":[
        {
            "category":"Organizations",
            "subcategory":"Labor Organization",
            "type":"Services"
        },
        {
            "category":"Professional",
            "subcategory":"Business Services",
            "type":"Services"
        }
    ],
    "sg:phone":"+44 161 272 7070",
    "sg:postcode":"M13 9UG",
    "sg:province":"Greater Manchester",
    "sg:tags":[
        "import",
        "export",
        "agent"
    ],
    "sg:website":"http://www.sunhigh.co.uk",
    "wof:name":"Sunhigh Ltd",
    "wof:placetype":"venue"
},
  "geometry": {"coordinates":[-2.228323,53.471424],"type":"Point"}
}