{
  "type": "Feature",
  "properties": {
    "iso:country":"GB",
    "sg:address":"907 Harrogate Road, Greengates",
    "sg:city":"Bradford",
    "sg:classifiers":[
        {
            "category":"Shopping",
            "subcategory":"Florist",
            "type":"Retail Goods"
        }
    ],
    "sg:phone":"+44 1274 621764",
    "sg:postcode":"BD10 0QY",
    "sg:province":"West Yorkshire",
    "wof:name":"Flower Pots",
    "wof:placetype":"venue"
},
  "geometry": {"coordinates":[-1.712869,53.830727],"type":"Point"}
}