{
  "type": "Feature",
  "properties": {
    "addr:full":"70 Links Way Beckenham Kent BR3 3DQ",
    "addr:housenumber":"70",
    "addr:postcode":"br3 3dq",
    "addr:street":"Links Way",
    "iso:country":"GB",
    "sg:address":"70 Links Way",
    "sg:city":"Beckenham",
    "sg:classifiers":[
        {
            "category":"Arts & Performance",
            "subcategory":"Music",
            "type":"Entertainment"
        },
        {
            "category":"Building & Trades",
            "subcategory":"Construction",
            "type":"Services"
        }
    ],
    "sg:postcode":"BR3 3DQ",
    "sg:province":"Kent",
    "sg:tags":[
        "mobile",
        "glazier",
        "disco"
    ],
    "wof:name":"Able Glazing Services & Contractors",
    "wof:placetype":"venue"
},
  "geometry": {"coordinates":[-0.024824,51.387306],"type":"Point"}
}