{
  "type": "Feature",
  "properties": {
    "iso:country":"GB",
    "sg:address":"43 Drumhead Road, Chorley North Industrial Park",
    "sg:city":"Chorley",
    "sg:classifiers":[
        {
            "category":"Manufacturing",
            "subcategory":"Metals",
            "type":"Manufacturing & Wholesale Goods"
        },
        {
            "category":"Manufacturing",
            "subcategory":"Tools & Machinery",
            "type":"Manufacturing & Wholesale Goods"
        }
    ],
    "sg:phone":"+44 1257 261755",
    "sg:postcode":"PR6 7BX",
    "sg:province":"Lancashire",
    "sg:tags":[
        "machine",
        "equipment",
        "welding",
        "manufacturer"
    ],
    "sg:website":"http://www.thermadyne.com",
    "wof:name":"Thermadyne Industries Ltd",
    "wof:placetype":"venue"
},
  "geometry": {"coordinates":[-2.626447,53.669258],"type":"Point"}
}