{
  "type": "Feature",
  "properties": {
    "addr:full":"7a Whitby Street Hartlepool Durham TS24 7AD",
    "addr:housenumber":"7a",
    "addr:postcode":"ts24 7ad",
    "addr:street":"Whitby Street",
    "iso:country":"GB",
    "sg:address":"7a Whitby Street",
    "sg:city":"Hartlepool",
    "sg:classifiers":[
        {
            "category":"Home & Garden",
            "subcategory":"Hardware",
            "type":"Retail Goods"
        }
    ],
    "sg:phone":"+44 1429 232865",
    "sg:postcode":"TS24 7AD",
    "sg:province":"Durham",
    "sg:tags":[
        "retailer",
        "lighting"
    ],
    "wof:name":"Storm Electrical",
    "wof:placetype":"venue"
},
  "geometry": {"coordinates":[-1.2071939707,54.6856422424],"type":"Point"}
}