{
  "type": "Feature",
  "properties": {
    "iso:country":"GB",
    "sg:address":"Great Orme",
    "sg:city":"Llandudno",
    "sg:classifiers":[
        {
            "category":"Government",
            "subcategory":"Office",
            "type":"Public Place"
        },
        {
            "category":"Landmark",
            "subcategory":"Tourist Attraction",
            "type":"Public Place"
        }
    ],
    "sg:phone":"+44 1492 874151",
    "sg:postcode":"LL30 2XF",
    "sg:province":"Conwy",
    "sg:tags":[
        "local",
        "interest"
    ],
    "wof:name":"Great Orme Country Park",
    "wof:placetype":"venue"
},
  "geometry": {"coordinates":[-3.8444290161,53.3216362],"type":"Point"}
}