{
  "type": "Feature",
  "properties": {
    "iso:country":"GB",
    "sg:address":"8a Fore Street",
    "sg:city":"Torrington",
    "sg:classifiers":[
        {
            "category":"Farming",
            "subcategory":"Livestock Farm",
            "type":"Manufacturing & Wholesale Goods"
        }
    ],
    "sg:phone":"+44 1805 622670",
    "sg:postcode":"EX38 8HQ",
    "sg:province":"Devon",
    "sg:tags":[
        "breeder"
    ],
    "wof:name":"Garden Craft",
    "wof:placetype":"venue"
},
  "geometry": {"coordinates":[-4.142823,50.952202],"type":"Point"}
}