{
  "type": "Feature",
  "properties": {
    "addr:full":"Regent Road Liverpool Merseyside L20 8DF",
    "addr:postcode":"l20 8df",
    "addr:street":"Regent Road",
    "iso:country":"GB",
    "sg:address":"Regent Road",
    "sg:city":"Liverpool",
    "sg:classifiers":[
        {
            "category":"Fast Food",
            "type":"Food & Drink"
        }
    ],
    "sg:phone":"+44 151 944 1660",
    "sg:postcode":"L20 8DF",
    "sg:province":"Merseyside",
    "sg:tags":[
        "away",
        "take"
    ],
    "wof:name":"Tracey's Kiosk",
    "wof:placetype":"venue"
},
  "geometry": {"coordinates":[-2.9980740547,53.4314651489],"type":"Point"}
}