{
  "type": "Feature",
  "properties": {
    "iso:country":"GB",
    "sg:address":"17 High St",
    "sg:city":"Southminster",
    "sg:classifiers":[
        {
            "category":"Professional",
            "subcategory":"Printing & Photocopies",
            "type":"Services"
        }
    ],
    "sg:phone":"+44 1621 774244",
    "sg:postcode":"CM0 7AA",
    "sg:province":"Essex",
    "sg:tags":[
        "printer"
    ],
    "wof:name":"H E C Innovations",
    "wof:placetype":"venue"
},
  "geometry": {"coordinates":[0.8280410171,51.6624755859],"type":"Point"}
}