{
  "type": "Feature",
  "properties": {
    "addr:full":"36-37 Kingfisher Shopping Centre, Kingfisher Walk Redditch Warwickshire B97 4EY",
    "addr:housenumber":"36-37",
    "addr:postcode":"b97 4ey",
    "addr:street":"Kingfisher Shopping;Kingfisher Walk",
    "iso:country":"GB",
    "sg:address":"36-37 Kingfisher Shopping Centre, Kingfisher Walk",
    "sg:city":"Redditch",
    "sg:classifiers":[
        {
            "category":"Shopping",
            "subcategory":"Shoes",
            "type":"Retail Goods"
        }
    ],
    "sg:phone":"+44 1527 596675",
    "sg:postcode":"B97 4EY",
    "sg:province":"Warwickshire",
    "sg:tags":[
        "shop",
        "retailer",
        "footwear"
    ],
    "wof:name":"Bacon's Shoes",
    "wof:placetype":"venue"
},
  "geometry": {"coordinates":[-1.9412670135,52.30727005],"type":"Point"}
}