{
  "type": "Feature",
  "properties": {
    "addr:full":"Bristol Road Birmingham West Midlands B5 7SW",
    "addr:postcode":"b5 7sw",
    "addr:street":"Bristol Road",
    "iso:country":"GB",
    "sg:address":"Bristol Road",
    "sg:city":"Birmingham",
    "sg:classifiers":[
        {
            "category":"Restaurant",
            "type":"Food & Drink"
        }
    ],
    "sg:phone":"+44 121 471 2672",
    "sg:postcode":"B5 7SW",
    "sg:province":"West Midlands",
    "wof:name":"Gun Barrels",
    "wof:placetype":"venue"
},
  "geometry": {"coordinates":[-1.9044790268,52.4622039795],"type":"Point"}
}