{
  "type": "Feature",
  "properties": {
    "addr:full":"17 Duckworth Street Darwen Lancashire BB3 1AR",
    "addr:housenumber":"17",
    "addr:postcode":"bb3 1ar",
    "addr:street":"Duckworth Street",
    "iso:country":"GB",
    "sg:address":"17 Duckworth Street",
    "sg:city":"Darwen",
    "sg:classifiers":[
        {
            "category":"Home & Garden",
            "subcategory":"Hardware",
            "type":"Retail Goods"
        }
    ],
    "sg:postcode":"BB3 1AR",
    "sg:province":"Lancashire",
    "sg:tags":[
        "retailer",
        "diy"
    ],
    "wof:name":"Dove D I Y",
    "wof:placetype":"venue"
},
  "geometry": {"coordinates":[-2.4742860794,53.7016868591],"type":"Point"}
}