{
  "type": "Feature",
  "properties": {
    "iso:country":"GB",
    "sg:address":"Unit 3, 115 Spencer Road",
    "sg:city":"Bradford",
    "sg:classifiers":[
        {
            "category":"Shopping",
            "type":"Retail Goods"
        }
    ],
    "sg:phone":"+44 1274 502000",
    "sg:postcode":"BD7 2LF",
    "sg:province":"West Yorkshire",
    "sg:tags":[
        "part",
        "accessory"
    ],
    "wof:name":"Supreme Auto Salvage",
    "wof:placetype":"venue"
},
  "geometry": {"coordinates":[-1.7918659449,53.7843132019],"type":"Point"}
}