{
  "type": "Feature",
  "properties": {
    "addr:full":"2 Castle Close, Cheylesmore Coventry Warwickshire CV3 5JA",
    "addr:housenumber":"2",
    "addr:postcode":"cv3 5ja",
    "addr:street":"Castle Close",
    "iso:country":"GB",
    "sg:address":"2 Castle Close, Cheylesmore",
    "sg:city":"Coventry",
    "sg:classifiers":[
        {
            "category":"Retail",
            "subcategory":"Laundry & Dry Cleaning",
            "type":"Services"
        }
    ],
    "sg:phone":"+44 24 7650 1751",
    "sg:postcode":"CV3 5JA",
    "sg:province":"Warwickshire",
    "sg:tags":[
        "alteration"
    ],
    "wof:name":"Daphnes",
    "wof:placetype":"venue"
},
  "geometry": {"coordinates":[-1.502146,52.38979],"type":"Point"}
}