{
  "type": "Feature",
  "properties": {
    "iso:country":"GB",
    "sg:address":"125 London Road, Cowplain",
    "sg:city":"Waterlooville",
    "sg:classifiers":[
        {
            "category":"Shopping",
            "subcategory":"News",
            "type":"Retail Goods"
        }
    ],
    "sg:phone":"+44 23 9226 2096",
    "sg:postcode":"PO8 8XJ",
    "sg:province":"Hampshire",
    "sg:tags":[
        "newsagent"
    ],
    "wof:name":"S & K News",
    "wof:placetype":"venue"
},
  "geometry": {"coordinates":[-1.01688,50.896904],"type":"Point"}
}