{
  "type": "Feature",
  "properties": {
    "addr:full":"94 Clements Road Birmingham West Midlands B25 8TT",
    "addr:housenumber":"94",
    "addr:postcode":"b25 8tt",
    "addr:street":"Clements Road",
    "iso:country":"GB",
    "sg:address":"94 Clements Road",
    "sg:city":"Birmingham",
    "sg:classifiers":[
        {
            "category":"Shopping",
            "subcategory":"News",
            "type":"Retail Goods"
        }
    ],
    "sg:postcode":"B25 8TT",
    "sg:province":"West Midlands",
    "sg:tags":[
        "newsagent"
    ],
    "wof:name":"Clements News",
    "wof:placetype":"venue"
},
  "geometry": {"coordinates":[-1.813439,52.470772],"type":"Point"}
}