{
  "type": "Feature",
  "properties": {
    "iso:country":"GB",
    "sg:address":"119 Mitcham Lane",
    "sg:city":"London",
    "sg:classifiers":[
        {
            "category":"Shopping",
            "subcategory":"Pharmacy",
            "type":"Retail Goods"
        }
    ],
    "sg:postcode":"SW16 6LY",
    "sg:province":"Greater London",
    "sg:tags":[
        "pharmacist",
        "chemist"
    ],
    "wof:name":"Markrise Ltd.",
    "wof:placetype":"venue"
},
  "geometry": {"coordinates":[-0.141888,51.423801],"type":"Point"}
}