{
  "type": "Feature",
  "properties": {
    "addr:full":"8 West Pilton Gardens Edinburgh City of Edinburgh EH4 4DP",
    "addr:housenumber":"8",
    "addr:postcode":"eh4 4dp",
    "addr:street":"West Pilton Gardens",
    "iso:country":"GB",
    "sg:address":"8 West Pilton Gardens",
    "sg:city":"Edinburgh",
    "sg:classifiers":[
        {
            "category":"Social Services",
            "type":"Services"
        }
    ],
    "sg:phone":"+44 131 529 5400",
    "sg:postcode":"EH4 4DP",
    "sg:province":"City of Edinburgh",
    "sg:tags":[
        "ds"
    ],
    "wof:name":"West Pilton Gardens Social Work Centre",
    "wof:placetype":"venue"
},
  "geometry": {"coordinates":[-3.248245,55.970127],"type":"Point"}
}