{
  "type": "Feature",
  "properties": {
    "iso:country":"GB",
    "sg:address":"142 Gloucester Avenue",
    "sg:city":"London",
    "sg:classifiers":[
        {
            "category":"Professional",
            "subcategory":"Lawyer & Legal Services",
            "type":"Services"
        }
    ],
    "sg:phone":"+44 20 7483 0282",
    "sg:postcode":"NW1 8JA",
    "sg:province":"Greater London",
    "sg:tags":[
        "solicitor"
    ],
    "wof:name":"Crumplins",
    "wof:placetype":"venue"
},
  "geometry": {"coordinates":[-0.154819,51.542213],"type":"Point"}
}