{
  "type": "Feature",
  "properties": {
    "iso:country":"GB",
    "sg:address":"Aberdour Road",
    "sg:city":"Dunfermline",
    "sg:classifiers":[
        {
            "category":"Travel",
            "subcategory":"Hotels & Motels",
            "type":"Entertainment"
        }
    ],
    "sg:phone":"+44 1383 722282",
    "sg:postcode":"KY11 4PB",
    "sg:province":"Fife",
    "wof:name":"Samuel Solley (Hotels) Ltd.",
    "wof:placetype":"venue"
},
  "geometry": {"coordinates":[-3.437894,56.061649],"type":"Point"}
}