{
  "type": "Feature",
  "properties": {
    "addr:full":"Castle Works, Fen Street, Canning Town London Greater London E16 1JS",
    "addr:postcode":"e16 1js",
    "addr:street":"Fen Street",
    "iso:country":"GB",
    "sg:address":"Castle Works, Fen Street, Canning Town",
    "sg:city":"London",
    "sg:classifiers":[
        {
            "category":"Retail",
            "subcategory":"Auto Repair",
            "type":"Services"
        }
    ],
    "sg:phone":"+44 20 7474 3630",
    "sg:postcode":"E16 1JS",
    "sg:province":"Greater London",
    "sg:tags":[
        "modification",
        "garage",
        "related"
    ],
    "wof:name":"Rosslyn Motors",
    "wof:placetype":"venue"
},
  "geometry": {"coordinates":[0.0132299997,51.5102081299],"type":"Point"}
}