{
  "type": "Feature",
  "properties": {
    "addr:full":"25 Church La, Tilbrook Huntingdon Bedfordshire PE28 0JS",
    "addr:housenumber":"25",
    "addr:postcode":"pe28 0js",
    "addr:street":"Church La Tilbrook",
    "iso:country":"GB",
    "sg:address":"25 Church La, Tilbrook",
    "sg:city":"Huntingdon",
    "sg:classifiers":[
        {
            "category":"Building & Trades",
            "subcategory":"Cleaning & Sanitation",
            "type":"Services"
        }
    ],
    "sg:postcode":"PE28 0JS",
    "sg:province":"Bedfordshire",
    "sg:tags":[
        "blast"
    ],
    "wof:name":"Blasting & Lining Services Ltd",
    "wof:placetype":"venue"
},
  "geometry": {"coordinates":[-0.403642,52.347645],"type":"Point"}
}