{
  "type": "Feature",
  "properties": {
    "addr:full":"80a Daw La Wakefield West Yorkshire WF4 3HB",
    "addr:housenumber":"80a",
    "addr:postcode":"wf4 3hb",
    "addr:street":"Daw La Wakefield West",
    "iso:country":"GB",
    "sg:address":"80a Daw La",
    "sg:city":"Wakefield",
    "sg:classifiers":[
        {
            "category":"Building & Trades",
            "subcategory":"Construction",
            "type":"Services"
        }
    ],
    "sg:phone":"+44 1924 256237",
    "sg:postcode":"WF4 3HB",
    "sg:province":"West Yorkshire",
    "sg:tags":[
        "joiner",
        "carpenter"
    ],
    "wof:name":"J M Bateman",
    "wof:placetype":"venue"
},
  "geometry": {"coordinates":[-1.5347399712,53.6355895996],"type":"Point"}
}