{
  "type": "Feature",
  "properties": {
    "iso:country":"GB",
    "sg:address":"28 St Audreys Close, Histon",
    "sg:city":"Cambridge",
    "sg:classifiers":[
        {
            "category":"Autos & Motor Vehicles",
            "subcategory":"Motorcycle Sales",
            "type":"Retail Goods"
        }
    ],
    "sg:phone":"+44 1223 237395",
    "sg:postcode":"CB4 9JX",
    "sg:province":"Cambridgeshire",
    "sg:tags":[
        "chauffeur",
        "driven",
        "car"
    ],
    "wof:name":"Cambridge Omnibus & Carriage Hire",
    "wof:placetype":"venue"
},
  "geometry": {"coordinates":[0.096592,52.252308],"type":"Point"}
}