{
  "type": "Feature",
  "properties": {
    "iso:country":"GB",
    "sg:address":"13 Thornfield Mount, Birstall",
    "sg:city":"Batley",
    "sg:classifiers":[
        {
            "category":"Professional",
            "type":"Services"
        }
    ],
    "sg:phone":"+44 1924 442085",
    "sg:postcode":"WF17 0NY",
    "sg:province":"West Yorkshire",
    "sg:tags":[
        "entertainer"
    ],
    "wof:name":"Megans Rainbow Funtime",
    "wof:placetype":"venue"
},
  "geometry": {"coordinates":[-1.648869,53.733955],"type":"Point"}
}