{
  "type": "Feature",
  "properties": {
    "addr:full":"192 Hollyfield Harlow Essex CM19 4NG",
    "addr:housenumber":"192",
    "addr:postcode":"cm19 4ng",
    "addr:street":"Hollyfield",
    "iso:country":"GB",
    "sg:address":"192 Hollyfield",
    "sg:city":"Harlow",
    "sg:classifiers":[
        {
            "category":"Professional",
            "subcategory":"Engineering",
            "type":"Services"
        },
        {
            "category":"Building & Trades",
            "subcategory":"Electrical",
            "type":"Services"
        }
    ],
    "sg:phone":"+44 1279 437752",
    "sg:postcode":"CM19 4NG",
    "sg:province":"Essex",
    "sg:tags":[
        "engineer",
        "electrician",
        "contractor"
    ],
    "wof:name":"G Harris",
    "wof:placetype":"venue"
},
  "geometry": {"coordinates":[0.0855500028,51.7553482056],"type":"Point"}
}