{
  "type": "Feature",
  "properties": {
    "addr:full":"Jelbert Way Penzance Cornwall TR18 3AS",
    "addr:postcode":"tr18 3as",
    "addr:street":"Jelbert Way",
    "iso:country":"GB",
    "sg:address":"Jelbert Way",
    "sg:city":"Penzance",
    "sg:classifiers":[
        {
            "category":"Manufacturing",
            "subcategory":"Petroleum Products",
            "type":"Manufacturing & Wholesale Goods"
        }
    ],
    "sg:phone":"+44 1736 332244",
    "sg:postcode":"TR18 3AS",
    "sg:province":"Cornwall",
    "sg:tags":[
        "double",
        "glazing"
    ],
    "wof:name":"Pro-Line Window Co",
    "wof:placetype":"venue"
},
  "geometry": {"coordinates":[-5.524224,50.127235],"type":"Point"}
}