{
  "type": "Feature",
  "properties": {
    "addr:full":"134 Sturry Road Canterbury Kent CT1 1DR",
    "addr:housenumber":"134",
    "addr:postcode":"ct1 1dr",
    "addr:street":"Sturry Road",
    "iso:country":"GB",
    "sg:address":"134 Sturry Road",
    "sg:city":"Canterbury",
    "sg:classifiers":[
        {
            "category":"Autos & Motor Vehicles",
            "subcategory":"Automobile Sales",
            "type":"Retail Goods"
        },
        {
            "category":"Retail",
            "subcategory":"Auto Rental",
            "type":"Services"
        }
    ],
    "sg:phone":"+44 1227 456777",
    "sg:postcode":"CT1 1DR",
    "sg:province":"Kent",
    "sg:tags":[
        "car",
        "hire",
        "van",
        "truck"
    ],
    "wof:name":"Budget Rent A Van",
    "wof:placetype":"venue"
},
  "geometry": {"coordinates":[1.0968650579,51.2887191772],"type":"Point"}
}