{
  "type": "Feature",
  "properties": {
    "iso:country":"GB",
    "sg:address":"9 First Avenue",
    "sg:city":"Teignmouth",
    "sg:classifiers":[
        {
            "category":"Building & Trades",
            "subcategory":"Plumbing",
            "type":"Services"
        }
    ],
    "sg:postcode":"TQ14 9DJ",
    "sg:province":"Devon",
    "sg:tags":[
        "heating"
    ],
    "wof:name":"Dave Northcott",
    "wof:placetype":"venue"
},
  "geometry": {"coordinates":[-3.507903,50.548443],"type":"Point"}
}