{
  "type": "Feature",
  "properties": {
    "addr:full":"Unit 1 London Greater London E2 6QF",
    "addr:housenumber":"unit 1",
    "addr:postcode":"e2 6qf",
    "iso:country":"GB",
    "sg:address":"Unit 1",
    "sg:city":"London",
    "sg:classifiers":[
        {
            "category":"Manufacturing",
            "subcategory":"Signs",
            "type":"Manufacturing & Wholesale Goods"
        }
    ],
    "sg:phone":"+44 20 7729 5959",
    "sg:postcode":"E2 6QF",
    "sg:province":"Greater London",
    "sg:tags":[
        "nameplate"
    ],
    "wof:name":"Sign Makers",
    "wof:placetype":"venue"
},
  "geometry": {"coordinates":[-0.0688640028,51.5306739807],"type":"Point"}
}