{
  "type": "Feature",
  "properties": {
    "iso:country":"GB",
    "sg:address":"42 Station Road",
    "sg:city":"Ossett",
    "sg:classifiers":[
        {
            "category":"Food & Beverages",
            "subcategory":"Specialty",
            "type":"Retail Goods"
        }
    ],
    "sg:phone":"+44 1924 273255",
    "sg:postcode":"WF5 8AY",
    "sg:province":"West Yorkshire",
    "sg:tags":[
        "retailer",
        "product",
        "health"
    ],
    "wof:name":"Funny Foods",
    "wof:placetype":"venue"
},
  "geometry": {"coordinates":[-1.5774220228,53.677734375],"type":"Point"}
}