{
  "type": "Feature",
  "properties": {
    "addr:full":"7 Lambarde Close, Halling Rochester Kent ME2 1DE",
    "addr:housenumber":"7",
    "addr:postcode":"me2 1de",
    "addr:street":"Lambarde Close",
    "iso:country":"GB",
    "sg:address":"7 Lambarde Close, Halling",
    "sg:city":"Rochester",
    "sg:classifiers":[
        {
            "category":"Home & Garden",
            "subcategory":"Household Appliances",
            "type":"Retail Goods"
        }
    ],
    "sg:phone":"+44 1634 246298",
    "sg:postcode":"ME2 1DE",
    "sg:province":"Kent",
    "sg:tags":[
        "electrical"
    ],
    "wof:name":"D Peirce",
    "wof:placetype":"venue"
},
  "geometry": {"coordinates":[0.4460580051,51.3480949402],"type":"Point"}
}