{
  "type": "Feature",
  "properties": {
    "addr:full":"87 Hillingdon Hill, Hillingdon Village Uxbridge Greater London UB10 0JQ",
    "addr:housenumber":"87",
    "addr:postcode":"ub10 0jq",
    "addr:street":"Hillingdon Hill",
    "iso:country":"GB",
    "sg:address":"87 Hillingdon Hill, Hillingdon Village",
    "sg:city":"Uxbridge",
    "sg:classifiers":[
        {
            "category":"Professional",
            "type":"Services"
        }
    ],
    "sg:phone":"+44 1895 810399",
    "sg:postcode":"UB10 0JQ",
    "sg:province":"Greater London",
    "sg:tags":[
        "interior",
        "furnishers",
        "designer"
    ],
    "wof:name":"Distinctive Designs",
    "wof:placetype":"venue"
},
  "geometry": {"coordinates":[-0.462996,51.535416],"type":"Point"}
}