{
  "type": "Feature",
  "properties": {
    "addr:full":"6-8 Rabans Close, Rabans Lane Industrial Area Aylesbury Buckinghamshire HP19 8RS",
    "addr:housenumber":"6-8",
    "addr:postcode":"hp19 8rs",
    "addr:street":"Rabans Close Rabans Lane",
    "iso:country":"GB",
    "sg:address":"6-8 Rabans Close, Rabans Lane Industrial Area",
    "sg:city":"Aylesbury",
    "sg:classifiers":[
        {
            "category":"Building & Trades",
            "subcategory":"Construction",
            "type":"Services"
        }
    ],
    "sg:phone":"+44 1296 393144",
    "sg:postcode":"HP19 8RS",
    "sg:province":"Buckinghamshire",
    "sg:tags":[
        "flooring"
    ],
    "wof:name":"Alexis Flooring",
    "wof:placetype":"venue"
},
  "geometry": {"coordinates":[-0.850303,51.824127],"type":"Point"}
}