{
  "type": "Feature",
  "properties": {
    "addr:full":"Brannel Farm, Coombe St Austell Cornwall PL26 7LG",
    "addr:postcode":"pl26 7lg",
    "addr:street":"Coombe",
    "iso:country":"GB",
    "sg:address":"Brannel Farm, Coombe",
    "sg:city":"St Austell",
    "sg:classifiers":[
        {
            "category":"Farming",
            "subcategory":"Nursery",
            "type":"Manufacturing & Wholesale Goods"
        }
    ],
    "sg:postcode":"PL26 7LG",
    "sg:province":"Cornwall",
    "sg:tags":[
        "creche"
    ],
    "wof:name":"Ward,Mandy,",
    "wof:placetype":"venue"
},
  "geometry": {"coordinates":[-4.8781690598,50.3286514282],"type":"Point"}
}