{
  "type": "Feature",
  "properties": {
    "addr:full":"662 Fishponds Road, Fishponds Bristol City of Bristol BS16 3HJ",
    "addr:housenumber":"662",
    "addr:postcode":"bs16 3hj",
    "addr:street":"Fishponds Road",
    "iso:country":"GB",
    "sg:address":"662 Fishponds Road, Fishponds",
    "sg:city":"Bristol",
    "sg:classifiers":[
        {
            "category":"Cafe",
            "type":"Food & Drink"
        }
    ],
    "sg:phone":"+44 117 939 7112",
    "sg:postcode":"BS16 3HJ",
    "sg:province":"City of Bristol",
    "sg:tags":[
        "tea",
        "room"
    ],
    "wof:name":"Stewpots Sandwich Bar",
    "wof:placetype":"venue"
},
  "geometry": {"coordinates":[-2.5363559723,51.4773330688],"type":"Point"}
}