{
  "type": "Feature",
  "properties": {
    "addr:full":"169 Colman Road Norwich Norfolk NR4 7HG",
    "addr:housenumber":"169",
    "addr:postcode":"nr4 7hg",
    "addr:street":"Colman Road Norwich Norfolk",
    "iso:country":"GB",
    "sg:address":"169 Colman Road",
    "sg:city":"Norwich",
    "sg:classifiers":[
        {
            "category":"Health Services",
            "subcategory":"Clinic",
            "type":"Services"
        },
        {
            "category":"Health Services",
            "subcategory":"Dentist",
            "type":"Services"
        }
    ],
    "sg:phone":"+44 1603 503827",
    "sg:postcode":"NR4 7HG",
    "sg:province":"Norfolk",
    "sg:tags":[
        "nh"
    ],
    "wof:name":"Coleman Road Health Centre",
    "wof:placetype":"venue"
},
  "geometry": {"coordinates":[1.2602159977,52.6259155273],"type":"Point"}
}