{
  "type": "Feature",
  "properties": {
    "addr:full":"100 Chrisp St Poplar Greater London E14 6PG",
    "addr:housenumber":"100",
    "addr:postcode":"e14 6pg",
    "addr:street":"Chrisp St",
    "iso:country":"GB",
    "sg:address":"100 Chrisp St",
    "sg:city":"Poplar",
    "sg:classifiers":[
        {
            "category":"Health Services",
            "subcategory":"Doctor",
            "type":"Services"
        }
    ],
    "sg:phone":"+44 20 7515 4860",
    "sg:postcode":"E14 6PG",
    "sg:province":"Greater London",
    "sg:tags":[
        "practitioners"
    ],
    "wof:name":"Robson, J",
    "wof:placetype":"venue"
},
  "geometry": {"coordinates":[-0.0143210003,51.5140991211],"type":"Point"}
}