{
  "type": "Feature",
  "properties": {
    "addr:full":"Culzean Castle Maybole East Ayrshire KA19 8LE",
    "addr:postcode":"ka19 8le",
    "addr:street":"East",
    "iso:country":"GB",
    "sg:address":"Culzean Castle",
    "sg:city":"Maybole",
    "sg:classifiers":[
        {
            "category":"Landmark",
            "subcategory":"Tourist Attraction",
            "type":"Public Place"
        }
    ],
    "sg:phone":"+44 1655 760240",
    "sg:postcode":"KA19 8LE",
    "sg:province":"East Ayrshire",
    "sg:tags":[
        "interest"
    ],
    "wof:name":"The National Trust",
    "wof:placetype":"venue"
},
  "geometry": {"coordinates":[-4.7769699097,55.3479385376],"type":"Point"}
}