{
  "type": "Feature",
  "properties": {
    "addr:full":"Alton Golf Club, Old Odiham Road Alton Hampshire GU34 4BU",
    "addr:postcode":"gu34 4bu",
    "addr:street":"Old Odiham Road",
    "iso:country":"GB",
    "sg:address":"Alton Golf Club, Old Odiham Road",
    "sg:city":"Alton",
    "sg:classifiers":[
        {
            "category":"Sports & Exercise",
            "subcategory":"Golf",
            "type":"Entertainment"
        }
    ],
    "sg:phone":"+44 1420 86518",
    "sg:postcode":"GU34 4BU",
    "sg:province":"Hampshire",
    "sg:tags":[
        "equipment"
    ],
    "wof:name":"Richard Keeling Professional Shop",
    "wof:placetype":"venue"
},
  "geometry": {"coordinates":[-0.9743289948,51.1475601196],"type":"Point"}
}