{
  "type": "Feature",
  "properties": {
    "addr:full":"35 Pentland Road Dronfield Derbyshire S18 8ZX",
    "addr:housenumber":"35",
    "addr:postcode":"s18 8zx",
    "addr:street":"Pentland Road",
    "iso:country":"GB",
    "sg:address":"35 Pentland Road",
    "sg:city":"Dronfield",
    "sg:classifiers":[
        {
            "category":"Food & Beverages",
            "subcategory":"Fruits & Vegetables",
            "type":"Retail Goods"
        }
    ],
    "sg:postcode":"S18 8ZX",
    "sg:province":"Derbyshire",
    "sg:tags":[
        "greengrocer"
    ],
    "wof:name":"Hardwicks Self Selection",
    "wof:placetype":"venue"
},
  "geometry": {"coordinates":[-1.495078,53.301029],"type":"Point"}
}