{
  "type": "Feature",
  "properties": {
    "iso:country":"GB",
    "sg:address":"119 Cleveden Road",
    "sg:city":"Glasgow",
    "sg:classifiers":[
        {
            "category":"Shopping",
            "subcategory":"Pharmacy",
            "type":"Retail Goods"
        }
    ],
    "sg:phone":"+44 141 339 5258",
    "sg:postcode":"G12 0JU",
    "sg:province":"Glasgow City",
    "sg:tags":[
        "pharmacist",
        "chemist"
    ],
    "wof:name":"J B Pharmacy",
    "wof:placetype":"venue"
},
  "geometry": {"coordinates":[-4.3069272041,55.8884162903],"type":"Point"}
}