{
  "type": "Feature",
  "properties": {
    "addr:full":"4 Brackley Road London Greater London W4 2HN",
    "addr:housenumber":"4",
    "addr:postcode":"w4 2hn",
    "addr:street":"Brackley Road",
    "iso:country":"GB",
    "sg:address":"4 Brackley Road",
    "sg:city":"London",
    "sg:classifiers":[
        {
            "category":"Shopping",
            "subcategory":"Clothing, Apparel, & Fashions",
            "type":"Retail Goods"
        }
    ],
    "sg:phone":"+44 20 8995 9446",
    "sg:postcode":"W4 2HN",
    "sg:province":"Greater London",
    "sg:tags":[
        "staff",
        "wear",
        "uniform"
    ],
    "wof:name":"Gryphon Design Associates",
    "wof:placetype":"venue"
},
  "geometry": {"coordinates":[-0.2545950115,51.4924278259],"type":"Point"}
}