{
  "type": "Feature",
  "properties": {
    "addr:full":"34-36 Hookstone Road Harrogate North Yorkshire HG2 8BW",
    "addr:housenumber":"34-36",
    "addr:postcode":"hg2 8bw",
    "addr:street":"Hookstone Road",
    "iso:country":"GB",
    "sg:address":"34-36 Hookstone Road",
    "sg:city":"Harrogate",
    "sg:classifiers":[
        {
            "category":"Shopping",
            "subcategory":"Stationery & Office Supplies",
            "type":"Retail Goods"
        },
        {
            "category":"Personal",
            "type":"Services"
        },
        {
            "category":"Retail",
            "subcategory":"Photofinishing",
            "type":"Services"
        }
    ],
    "sg:phone":"+44 1423 873767",
    "sg:postcode":"HG2 8BW",
    "sg:province":"North Yorkshire",
    "sg:tags":[
        "photographic",
        "processor",
        "wedding"
    ],
    "wof:name":"M T Designs",
    "wof:placetype":"venue"
},
  "geometry": {"coordinates":[-1.5297809839,53.9789619446],"type":"Point"}
}