{
  "type": "Feature",
  "properties": {
    "iso:country":"GB",
    "sg:address":"The Balk, Walton",
    "sg:city":"Wakefield",
    "sg:classifiers":[
        {
            "category":"Recreation",
            "subcategory":"Fishing",
            "type":"Entertainment"
        },
        {
            "category":"Train Station",
            "subcategory":"Rail",
            "type":"Transportation"
        }
    ],
    "sg:phone":"+44 1924 242990",
    "sg:postcode":"WF2 6PW",
    "sg:province":"West Yorkshire",
    "sg:tags":[
        "angling"
    ],
    "sg:website":"http://www.waltonhalltroutlake.co.uk",
    "wof:name":"Walton Hall Trout Fishery",
    "wof:placetype":"venue"
},
  "geometry": {"coordinates":[-1.463949,53.64893],"type":"Point"}
}