{
  "type": "Feature",
  "properties": {
    "addr:full":"165 Manor Road Chigwell Essex IG7 5QA",
    "addr:housenumber":"165",
    "addr:postcode":"ig7 5qa",
    "addr:street":"Manor Road",
    "iso:country":"GB",
    "sg:address":"165 Manor Road",
    "sg:city":"Chigwell",
    "sg:classifiers":[
        {
            "category":"Retail",
            "subcategory":"Laundry & Dry Cleaning",
            "type":"Services"
        }
    ],
    "sg:phone":"+44 20 8501 3786",
    "sg:postcode":"IG7 5QA",
    "sg:province":"Essex",
    "sg:tags":[
        "cleaner",
        "alteration"
    ],
    "wof:name":"The Dry Cleaning Centre",
    "wof:placetype":"venue"
},
  "geometry": {"coordinates":[0.090416,51.612942],"type":"Point"}
}