{
  "type": "Feature",
  "properties": {
    "iso:country":"GB",
    "sg:address":"Castle Cottage, Boreland Wood, Gatehouse Of Fleet",
    "sg:city":"Castle Douglas",
    "sg:classifiers":[
        {
            "category":"Landmark",
            "subcategory":"Historic",
            "type":"Public Place"
        },
        {
            "category":"Landmark",
            "subcategory":"Tourist Attraction",
            "type":"Public Place"
        }
    ],
    "sg:phone":"+44 1557 814427",
    "sg:postcode":"DG7 2EH",
    "sg:province":"Dumfries and Galloway",
    "sg:tags":[
        "house",
        "garden",
        "interest"
    ],
    "wof:name":"Cardoness Castle",
    "wof:placetype":"venue"
},
  "geometry": {"coordinates":[-4.186934,54.880909],"type":"Point"}
}