{
  "type": "Feature",
  "properties": {
    "addr:full":"46 Stanford Way, Broadbridge Heath Horsham West Sussex RH12 3LH",
    "addr:housenumber":"46",
    "addr:postcode":"rh12 3lh",
    "addr:street":"Stanford Way",
    "iso:country":"GB",
    "sg:address":"46 Stanford Way, Broadbridge Heath",
    "sg:city":"Horsham",
    "sg:classifiers":[
        {
            "category":"Professional",
            "subcategory":"Business Services",
            "type":"Services"
        },
        {
            "category":"Recreation",
            "subcategory":"Gun Range",
            "type":"Entertainment"
        }
    ],
    "sg:phone":"+44 1372 458133",
    "sg:postcode":"RH12 3LH",
    "sg:province":"West Sussex",
    "sg:tags":[
        "operator",
        "hospitality",
        "tour",
        "corporate"
    ],
    "wof:name":"Bowood Leisure Ltd",
    "wof:placetype":"venue"
},
  "geometry": {"coordinates":[-0.364820987,51.0699272156],"type":"Point"}
}