{
  "type": "Feature",
  "properties": {
    "addr:full":"Harley Dene Vine Rd Torquay Devon TQ2 5BG",
    "addr:postcode":"tq2 5bg",
    "addr:street":"Vine Rd",
    "iso:country":"GB",
    "sg:address":"Harley Dene Vine Rd",
    "sg:city":"Torquay",
    "sg:classifiers":[
        {
            "category":"Building & Trades",
            "subcategory":"Construction",
            "type":"Services"
        }
    ],
    "sg:phone":"+44 1803 211810",
    "sg:postcode":"TQ2 5BG",
    "sg:province":"Devon",
    "sg:tags":[
        "builder"
    ],
    "wof:name":"D Hughes",
    "wof:placetype":"venue"
},
  "geometry": {"coordinates":[-3.5434639454,50.4671936035],"type":"Point"}
}