{
  "type": "Feature",
  "properties": {
    "iso:country":"GB",
    "sg:address":"Vickers Street",
    "sg:city":"Motherwell",
    "sg:classifiers":[
        {
            "category":"Education",
            "subcategory":"School",
            "type":"Public Place"
        }
    ],
    "sg:phone":"+44 1698 264350",
    "sg:postcode":"ML1 3RE",
    "sg:province":"North Lanarkshire",
    "sg:tags":[
        "local",
        "authority"
    ],
    "wof:name":"St Bernadette's Primary School",
    "wof:placetype":"venue"
},
  "geometry": {"coordinates":[-4.011534,55.797958],"type":"Point"}
}