{
  "type": "Feature",
  "properties": {
    "iso:country":"GB",
    "sg:address":"Watling St",
    "sg:city":"Hinckley",
    "sg:classifiers":[
        {
            "category":"Restaurant",
            "type":"Food & Drink"
        }
    ],
    "sg:phone":"+44 1455 615408",
    "sg:postcode":"LE10 2JQ",
    "sg:province":"Leicestershire",
    "wof:name":"Three Pots Harvester The",
    "wof:placetype":"venue"
},
  "geometry": {"coordinates":[-1.3694250584,52.5181541443],"type":"Point"}
}