{
  "type": "Feature",
  "properties": {
    "addr:full":"Oak Mills, Colliery Approach, Potovens Lane, Lofthouse Wakefield West Yorkshire WF3 3JG",
    "addr:postcode":"wf3 3jg",
    "addr:street":"Colliery Approach Potovens Lane;West",
    "iso:country":"GB",
    "sg:address":"Oak Mills, Colliery Approach, Potovens Lane, Lofthouse",
    "sg:city":"Wakefield",
    "sg:classifiers":[
        {
            "category":"Manufacturing",
            "subcategory":"Furniture",
            "type":"Manufacturing & Wholesale Goods"
        }
    ],
    "sg:phone":"+44 1924 835999",
    "sg:postcode":"WF3 3JG",
    "sg:province":"West Yorkshire",
    "sg:tags":[
        "mnfr",
        "upholsterer"
    ],
    "wof:name":"Marcus Kenyon",
    "wof:placetype":"venue"
},
  "geometry": {"coordinates":[-1.497074008,53.7302589417],"type":"Point"}
}