{
  "type": "Feature",
  "properties": {
    "iso:country":"GB",
    "sg:address":"16 Newlands Road",
    "sg:city":"Darlington",
    "sg:classifiers":[
        {
            "category":"Shopping",
            "subcategory":"Clothing, Apparel, & Fashions",
            "type":"Retail Goods"
        }
    ],
    "sg:postcode":"DL3 9JL",
    "sg:province":"Durham",
    "sg:tags":[
        "shop"
    ],
    "wof:name":"Toggs",
    "wof:placetype":"venue"
},
  "geometry": {"coordinates":[-1.576226,54.535122],"type":"Point"}
}