{
  "type": "Feature",
  "properties": {
    "iso:country":"GB",
    "sg:address":"19 Slimbridge Rd, Tuffley",
    "sg:city":"Gloucester",
    "sg:classifiers":[
        {
            "category":"Professional",
            "subcategory":"Management & Consulting",
            "type":"Services"
        }
    ],
    "sg:phone":"+44 1452 503237",
    "sg:postcode":"GL4 0NA",
    "sg:province":"Gloucestershire",
    "sg:tags":[
        "consultant",
        "business"
    ],
    "wof:name":"Breakthrough",
    "wof:placetype":"venue"
},
  "geometry": {"coordinates":[-2.251016,51.836433],"type":"Point"}
}