{
  "type": "Feature",
  "properties": {
    "iso:country":"GB",
    "sg:address":"108-110 Deedes Street",
    "sg:city":"Airdrie",
    "sg:classifiers":[
        {
            "category":"Shopping",
            "subcategory":"Pharmacy",
            "type":"Retail Goods"
        }
    ],
    "sg:phone":"+44 1236 753252",
    "sg:postcode":"ML6 9AF",
    "sg:province":"North Lanarkshire",
    "sg:tags":[
        "pharmacist",
        "chemist"
    ],
    "wof:name":"Danatec Ltd.",
    "wof:placetype":"venue"
},
  "geometry": {"coordinates":[-4.002055,55.86166],"type":"Point"}
}