{
  "type": "Feature",
  "properties": {
    "addr:full":"104 Westgate Rotherham South Yorkshire S60 1BD",
    "addr:housenumber":"104",
    "addr:postcode":"s60 1bd",
    "addr:street":"Westgate",
    "iso:country":"GB",
    "sg:address":"104 Westgate",
    "sg:city":"Rotherham",
    "sg:classifiers":[
        {
            "category":"Professional",
            "subcategory":"Detective & Security Services",
            "type":"Services"
        }
    ],
    "sg:postcode":"S60 1BD",
    "sg:province":"South Yorkshire",
    "sg:tags":[
        "alarm",
        "burglar",
        "system"
    ],
    "wof:name":"Torry,S,",
    "wof:placetype":"venue"
},
  "geometry": {"coordinates":[-1.358092,53.426563],"type":"Point"}
}