{
  "type": "Feature",
  "properties": {
    "addr:full":"29 Manor Road Taunton Somerset TA1 5BG",
    "addr:housenumber":"29",
    "addr:postcode":"ta1 5bg",
    "addr:street":"Manor Road",
    "iso:country":"GB",
    "sg:address":"29 Manor Road",
    "sg:city":"Taunton",
    "sg:classifiers":[
        {
            "category":"Retail",
            "subcategory":"Driving School",
            "type":"Services"
        }
    ],
    "sg:postcode":"TA1 5BG",
    "sg:province":"Somerset",
    "wof:name":"Lennox Driving School",
    "wof:placetype":"venue"
},
  "geometry": {"coordinates":[-3.1149470806,51.0133323669],"type":"Point"}
}