{
  "type": "Feature",
  "properties": {
    "addr:full":"Bernard Close, High Kelling Holt Norfolk NR25 6QY",
    "addr:postcode":"nr25 6qy",
    "addr:street":"Bernard Close",
    "iso:country":"GB",
    "sg:address":"Bernard Close, High Kelling",
    "sg:city":"Holt",
    "sg:classifiers":[
        {
            "category":"Education",
            "subcategory":"School",
            "type":"Public Place"
        },
        {
            "category":"Education",
            "subcategory":"University",
            "type":"Public Place"
        }
    ],
    "sg:phone":"+44 1263 713578",
    "sg:postcode":"NR25 6QY",
    "sg:province":"Norfolk",
    "sg:tags":[
        "private",
        "tuition"
    ],
    "wof:name":"Norfolk Tutors",
    "wof:placetype":"venue"
},
  "geometry": {"coordinates":[1.1249940395,52.9148368835],"type":"Point"}
}