{
  "type": "Feature",
  "properties": {
    "addr:full":"Astley House, 33 Notting Hill Gate London Greater London W11 3JQ",
    "addr:housenumber":"33",
    "addr:postcode":"w11 3jq",
    "addr:street":"Notting Hill Gate",
    "iso:country":"GB",
    "sg:address":"Astley House, 33 Notting Hill Gate",
    "sg:city":"London",
    "sg:classifiers":[
        {
            "category":"Communications",
            "subcategory":"Newspaper",
            "type":"Services"
        }
    ],
    "sg:phone":"+44 20 7792 2626",
    "sg:postcode":"W11 3JQ",
    "sg:province":"Greater London",
    "sg:tags":[
        "magazine"
    ],
    "wof:name":"Highbury Local Publications Ltd.",
    "wof:placetype":"venue"
},
  "geometry": {"coordinates":[-0.220874,51.553772],"type":"Point"}
}