{
  "type": "Feature",
  "properties": {
    "iso:country":"GB",
    "sg:address":"West End, Rothbury",
    "sg:city":"Morpeth",
    "sg:classifiers":[
        {
            "category":"Organizations",
            "subcategory":"Non-profit Organization",
            "type":"Services"
        }
    ],
    "sg:phone":"+44 1669 620235",
    "sg:postcode":"NE65 7TU",
    "sg:province":"Northumberland",
    "sg:tags":[
        "organisation",
        "voluntary",
        "charity"
    ],
    "wof:name":"Royal Air Force Association",
    "wof:placetype":"venue"
},
  "geometry": {"coordinates":[-1.9139939547,55.3092536926],"type":"Point"}
}