{
  "type": "Feature",
  "properties": {
    "iso:country":"GB",
    "sg:address":"22 Turkdean Road",
    "sg:city":"Cheltenham",
    "sg:classifiers":[
        {
            "category":"Military Area",
            "subcategory":"Air Force Base",
            "type":"Public Place"
        }
    ],
    "sg:phone":"+44 1789 778177",
    "sg:postcode":"GL51 6AL",
    "sg:province":"Gloucestershire",
    "sg:tags":[
        "water",
        "treatment"
    ],
    "wof:name":"Spa Water Softeners",
    "wof:placetype":"venue"
},
  "geometry": {"coordinates":[-2.114604,51.895821],"type":"Point"}
}