{
  "type": "Feature",
  "properties": {
    "addr:full":"Chestnut House, Stonegate Spalding Cambridgeshire PE12 6HR",
    "addr:postcode":"pe12 6hr",
    "addr:street":"Stonegate Spalding",
    "iso:country":"GB",
    "sg:address":"Chestnut House, Stonegate",
    "sg:city":"Spalding",
    "sg:classifiers":[
        {
            "category":"Communications",
            "type":"Services"
        }
    ],
    "sg:postcode":"PE12 6HR",
    "sg:province":"Cambridgeshire",
    "sg:tags":[
        "telecommunication"
    ],
    "wof:name":"Logan Rock Ltd.",
    "wof:placetype":"venue"
},
  "geometry": {"coordinates":[-0.096364,52.821178],"type":"Point"}
}