{
  "type": "Feature",
  "properties": {
    "addr:full":"Russell Road, Rock Ferry Wirral Merseyside CH42 1LU",
    "addr:postcode":"ch42 1lu",
    "addr:street":"Russell Road Rock",
    "iso:country":"GB",
    "sg:address":"Russell Road, Rock Ferry",
    "sg:city":"Wirral",
    "sg:classifiers":[
        {
            "category":"Government",
            "subcategory":"Department Of Motor Vehicles",
            "type":"Public Place"
        }
    ],
    "sg:phone":"+44 151 643 1066",
    "sg:postcode":"CH42 1LU",
    "sg:province":"Merseyside",
    "sg:tags":[
        "inspection"
    ],
    "wof:name":"Olympic Autos Ltd.",
    "wof:placetype":"venue"
},
  "geometry": {"coordinates":[-3.00847,53.376209],"type":"Point"}
}