{
  "type": "Feature",
  "properties": {
    "iso:country":"GB",
    "sg:address":"225 Charminster Road",
    "sg:city":"Bournemouth",
    "sg:classifiers":[
        {
            "category":"Professional",
            "subcategory":"Lawyer & Legal Services",
            "type":"Services"
        }
    ],
    "sg:phone":"+44 1202 510167",
    "sg:postcode":"BH8 9QL",
    "sg:province":"Dorset",
    "sg:tags":[
        "solicitor"
    ],
    "wof:name":"Insley & Partners",
    "wof:placetype":"venue"
},
  "geometry": {"coordinates":[-1.863937974,50.7388877869],"type":"Point"}
}