{
  "type": "Feature",
  "properties": {
    "iso:country":"GB",
    "sg:address":"Unit 3 Hollybrook Way",
    "sg:city":"Derby",
    "sg:classifiers":[
        {
            "category":"Cinema",
            "subcategory":"Movie Rental",
            "type":"Entertainment"
        }
    ],
    "sg:phone":"+44 1332 516143",
    "sg:postcode":"DE23 3TY",
    "sg:province":"Derbyshire",
    "sg:tags":[
        "video",
        "library"
    ],
    "wof:name":"Choices Video",
    "wof:placetype":"venue"
},
  "geometry": {"coordinates":[-1.5268089771,52.891960144],"type":"Point"}
}