{
  "type": "Feature",
  "properties": {
    "addr:full":"10a High Street Ilfracombe Devon EX34 9DF",
    "addr:housenumber":"10a",
    "addr:postcode":"ex34 9df",
    "addr:street":"High Street",
    "iso:country":"GB",
    "sg:address":"10a High Street",
    "sg:city":"Ilfracombe",
    "sg:classifiers":[
        {
            "category":"Sports & Exercise",
            "subcategory":"Sports Center",
            "type":"Entertainment"
        }
    ],
    "sg:phone":"+44 1271 864498",
    "sg:postcode":"EX34 9DF",
    "sg:province":"Devon",
    "sg:tags":[
        "shop",
        "good"
    ],
    "wof:name":"Terrys",
    "wof:placetype":"venue"
},
  "geometry": {"coordinates":[-4.1215291023,51.2088928223],"type":"Point"}
}