{
  "type": "Feature",
  "properties": {
    "iso:country":"GB",
    "sg:address":"22-24 East Park Drive",
    "sg:city":"Leeds",
    "sg:classifiers":[
        {
            "category":"Food & Beverages",
            "subcategory":"Groceries & Convenience Stores",
            "type":"Retail Goods"
        }
    ],
    "sg:phone":"+44 113 225 0440",
    "sg:postcode":"LS9 9JH",
    "sg:province":"West Yorkshire",
    "wof:name":"G V Stores",
    "wof:placetype":"venue"
},
  "geometry": {"coordinates":[-1.515112,53.79406],"type":"Point"}
}