{
  "type": "Feature",
  "properties": {
    "iso:country":"GB",
    "sg:address":"Rosedale Ho, Rosedale Rd",
    "sg:city":"Richmond",
    "sg:classifiers":[
        {
            "category":"Professional",
            "subcategory":"Computer Services",
            "type":"Services"
        }
    ],
    "sg:phone":"+44 20 8948 7170",
    "sg:postcode":"TW9 2SZ",
    "sg:province":"Greater London",
    "sg:tags":[
        "system",
        "software"
    ],
    "wof:name":"Source Incorporated",
    "wof:placetype":"venue"
},
  "geometry": {"coordinates":[-0.300273,51.465714],"type":"Point"}
}