{
  "type": "Feature",
  "properties": {
    "iso:country":"GB",
    "sg:address":"Kennett Road",
    "sg:city":"Slough",
    "sg:classifiers":[
        {
            "category":"Education",
            "subcategory":"School",
            "type":"Public Place"
        }
    ],
    "sg:phone":"+44 1753 542269",
    "sg:postcode":"SL3 8EQ",
    "sg:province":"Berkshire",
    "sg:tags":[
        "local",
        "authority"
    ],
    "wof:name":"Parlaunt Park Primary School",
    "wof:placetype":"venue"
},
  "geometry": {"coordinates":[-0.534964025,51.5039100647],"type":"Point"}
}