{
  "type": "Feature",
  "properties": {
    "iso:country":"GB",
    "sg:address":"9 Clayfield Close, Moulton Park Industrial Estate",
    "sg:city":"Northampton",
    "sg:classifiers":[
        {
            "category":"Home & Garden",
            "subcategory":"Hardware",
            "type":"Retail Goods"
        }
    ],
    "sg:phone":"+44 1604 648484",
    "sg:postcode":"NN3 6QF",
    "sg:province":"Northamptonshire",
    "sg:tags":[
        "sealant",
        "glue",
        "adhesives"
    ],
    "wof:name":"Excel",
    "wof:placetype":"venue"
},
  "geometry": {"coordinates":[-0.86006,52.275719],"type":"Point"}
}