{
  "type": "Feature",
  "properties": {
    "addr:full":"172 Hall Street Stockport Cheshire SK1 4JG",
    "addr:housenumber":"172",
    "addr:postcode":"sk1 4jg",
    "addr:street":"Hall Street",
    "iso:country":"GB",
    "sg:address":"172 Hall Street",
    "sg:city":"Stockport",
    "sg:classifiers":[
        {
            "category":"Shopping",
            "subcategory":"News",
            "type":"Retail Goods"
        }
    ],
    "sg:phone":"+44 161 480 5391",
    "sg:postcode":"SK1 4JG",
    "sg:province":"Cheshire",
    "sg:tags":[
        "newsagent"
    ],
    "wof:name":"Haddrell & Moore",
    "wof:placetype":"venue"
},
  "geometry": {"coordinates":[-2.1397199631,53.4052429199],"type":"Point"}
}