{
  "type": "Feature",
  "properties": {
    "addr:full":"East Voe, Scalloway Shetland Shetland Islands ZE1 0UR",
    "addr:postcode":"ze1 0ur",
    "addr:street":"East Voe Scalloway;Shetland",
    "iso:country":"GB",
    "sg:address":"East Voe, Scalloway",
    "sg:city":"Shetland",
    "sg:classifiers":[
        {
            "category":"Manufacturing",
            "subcategory":"Glass & Minerals",
            "type":"Manufacturing & Wholesale Goods"
        },
        {
            "category":"Government",
            "subcategory":"Office",
            "type":"Public Place"
        }
    ],
    "sg:phone":"+44 1595 880227",
    "sg:postcode":"ZE1 0UR",
    "sg:province":"Shetland Islands",
    "sg:tags":[
        "chalk",
        "stone",
        "local",
        "slate"
    ],
    "wof:name":"Scord Quarry",
    "wof:placetype":"venue"
},
  "geometry": {"coordinates":[-1.279884,60.137489],"type":"Point"}
}