{
  "type": "Feature",
  "properties": {
    "addr:full":"31 Main Street Prestwick South Ayrshire KA9 1AD",
    "addr:housenumber":"31",
    "addr:postcode":"ka9 1ad",
    "addr:street":"Main Street",
    "iso:country":"GB",
    "sg:address":"31 Main Street",
    "sg:city":"Prestwick",
    "sg:classifiers":[
        {
            "category":"Professional",
            "subcategory":"Lawyer & Legal Services",
            "type":"Services"
        }
    ],
    "sg:postcode":"KA9 1AD",
    "sg:province":"South Ayrshire",
    "sg:tags":[
        "solicitor"
    ],
    "wof:name":"Coyle & Welsh",
    "wof:placetype":"venue"
},
  "geometry": {"coordinates":[-4.610807,55.500965],"type":"Point"}
}