{
  "type": "Feature",
  "properties": {
    "iso:country":"GB",
    "sg:address":"3 The Haymarket, Pendeford",
    "sg:city":"Wolverhampton",
    "sg:classifiers":[
        {
            "category":"Professional",
            "subcategory":"Business Services",
            "type":"Services"
        }
    ],
    "sg:postcode":"WV8 1XE",
    "sg:province":"Shropshire",
    "sg:tags":[
        "bookmaker"
    ],
    "wof:name":"Nunn,Christopher,",
    "wof:placetype":"venue"
},
  "geometry": {"coordinates":[-2.156684,52.617111],"type":"Point"}
}