{
  "type": "Feature",
  "properties": {
    "iso:country":"GB",
    "sg:address":"A 106, New Covent Garden Market",
    "sg:city":"London",
    "sg:classifiers":[
        {
            "category":"Professional",
            "subcategory":"Business Services",
            "type":"Services"
        }
    ],
    "sg:phone":"+44 20 7381 8222",
    "sg:postcode":"SW8 5LL",
    "sg:province":"Greater London",
    "sg:tags":[
        "import",
        "export",
        "agent"
    ],
    "wof:name":"Luis Navarro Ltd.",
    "wof:placetype":"venue"
},
  "geometry": {"coordinates":[-0.1228,51.5115890503],"type":"Point"}
}