{
  "type": "Feature",
  "properties": {
    "addr:full":"652 Lordswood Lane Chatham Kent ME5 8RB",
    "addr:housenumber":"652",
    "addr:postcode":"me5 8rb",
    "addr:street":"Lordswood Lane",
    "iso:country":"GB",
    "sg:address":"652 Lordswood Lane",
    "sg:city":"Chatham",
    "sg:classifiers":[
        {
            "category":"Recreation",
            "subcategory":"Dog Park",
            "type":"Entertainment"
        },
        {
            "category":"Education",
            "subcategory":"School",
            "type":"Public Place"
        }
    ],
    "sg:phone":"+44 1634 863476",
    "sg:postcode":"ME5 8RB",
    "sg:province":"Kent",
    "sg:tags":[
        "local",
        "authority"
    ],
    "wof:name":"R J Security Dog Training Services Ltd.",
    "wof:placetype":"venue"
},
  "geometry": {"coordinates":[0.5367059708,51.336391449],"type":"Point"}
}