{
  "type": "Feature",
  "properties": {
    "iso:country":"GB",
    "sg:address":"Unit 33 Britannia Mill, Stoneholme La",
    "sg:city":"Rossendale",
    "sg:classifiers":[
        {
            "category":"Manufacturing",
            "subcategory":"Petroleum Products",
            "type":"Manufacturing & Wholesale Goods"
        }
    ],
    "sg:phone":"+44 1706 830266",
    "sg:postcode":"BB4 8BA",
    "sg:province":"Lancashire",
    "sg:tags":[
        "double",
        "glazing"
    ],
    "wof:name":"Rossendale Windows",
    "wof:placetype":"venue"
},
  "geometry": {"coordinates":[-2.274823904,53.7089614868],"type":"Point"}
}