{
  "type": "Feature",
  "properties": {
    "iso:country":"GB",
    "sg:address":"5 King Street",
    "sg:city":"Wrexham",
    "sg:classifiers":[
        {
            "category":"Professional",
            "subcategory":"Lawyer & Legal Services",
            "type":"Services"
        }
    ],
    "sg:phone":"+44 1978 315100",
    "sg:postcode":"LL11 1HF",
    "sg:province":"Wrexham",
    "sg:tags":[
        "solicitor"
    ],
    "wof:name":"J Hopley Pierce & Bird",
    "wof:placetype":"venue"
},
  "geometry": {"coordinates":[-2.997541,53.04752],"type":"Point"}
}