{
  "type": "Feature",
  "properties": {
    "addr:full":"1 Wharf Street Dukinfield Greater Manchester SK16 4JF",
    "addr:housenumber":"1",
    "addr:postcode":"sk16 4jf",
    "addr:street":"Wharf Street",
    "iso:country":"GB",
    "sg:address":"1 Wharf Street",
    "sg:city":"Dukinfield",
    "sg:classifiers":[
        {
            "category":"Farming",
            "subcategory":"Fish & Marine Products",
            "type":"Manufacturing & Wholesale Goods"
        }
    ],
    "sg:phone":"+44 161 865 2842",
    "sg:postcode":"SK16 4JF",
    "sg:province":"Greater Manchester",
    "sg:tags":[
        "fishmonger"
    ],
    "wof:name":"N & I Wrigley",
    "wof:placetype":"venue"
},
  "geometry": {"coordinates":[-2.0911500454,53.4823150635],"type":"Point"}
}