{
  "type": "Feature",
  "properties": {
    "addr:full":"11 Broad Street Launceston Cornwall PL15 8AJ",
    "addr:housenumber":"11",
    "addr:postcode":"pl15 8aj",
    "addr:street":"Broad Street",
    "iso:country":"GB",
    "sg:address":"11 Broad Street",
    "sg:city":"Launceston",
    "sg:classifiers":[
        {
            "category":"Home & Garden",
            "subcategory":"Carpets & Floor Coverings",
            "type":"Retail Goods"
        }
    ],
    "sg:phone":"+44 1566 773129",
    "sg:postcode":"PL15 8AJ",
    "sg:province":"Cornwall",
    "sg:tags":[
        "carpets",
        "rug",
        "matting"
    ],
    "wof:name":"Hicks & Son",
    "wof:placetype":"venue"
},
  "geometry": {"coordinates":[-4.3601541519,50.6368637085],"type":"Point"}
}