{
  "type": "Feature",
  "properties": {
    "iso:country":"GB",
    "sg:address":"62-65 Trafalgar Square",
    "sg:city":"London",
    "sg:classifiers":[
        {
            "category":"Professional",
            "subcategory":"Computer Services",
            "type":"Services"
        }
    ],
    "sg:phone":"+44 870 071 0110",
    "sg:postcode":"WC2N 5NJ",
    "sg:province":"Greater London",
    "sg:tags":[
        "system",
        "software"
    ],
    "wof:name":"110 Ltd.",
    "wof:placetype":"venue"
},
  "geometry": {"coordinates":[-0.1283169985,51.5075378418],"type":"Point"}
}