{
  "type": "Feature",
  "properties": {
    "addr:full":"Brook House Farm, Hemingby Horncastle Lincolnshire LN9 5QF",
    "addr:housenumber":"hemingby",
    "addr:postcode":"ln9 5qf",
    "addr:street":"Horncastle",
    "iso:country":"GB",
    "sg:address":"Brook House Farm, Hemingby",
    "sg:city":"Horncastle",
    "sg:classifiers":[
        {
            "category":"Farming",
            "subcategory":"Farm",
            "type":"Manufacturing & Wholesale Goods"
        }
    ],
    "sg:postcode":"LN9 5QF",
    "sg:province":"Lincolnshire",
    "sg:tags":[
        "mixed",
        "crop"
    ],
    "wof:name":"F E Read & Sons",
    "wof:placetype":"venue"
},
  "geometry": {"coordinates":[-0.1147650033,53.2085227966],"type":"Point"}
}