{
  "type": "Feature",
  "properties": {
    "addr:full":"7 High Street Marlborough Berkshire SN8 3NU",
    "addr:housenumber":"7",
    "addr:postcode":"sn8 3nu",
    "addr:street":"High Street",
    "iso:country":"GB",
    "sg:address":"7 High Street",
    "sg:city":"Marlborough",
    "sg:classifiers":[
        {
            "category":"Professional",
            "subcategory":"Engineering",
            "type":"Services"
        }
    ],
    "sg:postcode":"SN8 3NU",
    "sg:province":"Berkshire",
    "sg:tags":[
        "contractor",
        "electrical",
        "engineer"
    ],
    "wof:name":"Guy Nicholas",
    "wof:placetype":"venue"
},
  "geometry": {"coordinates":[-1.671561,51.358551],"type":"Point"}
}