{
  "type": "Feature",
  "properties": {
    "addr:full":"9 Arena Parade Letchworth Hertfordshire SG6 3BY",
    "addr:housenumber":"9",
    "addr:postcode":"sg6 3by",
    "addr:street":"Arena Parade Letchworth",
    "iso:country":"GB",
    "sg:address":"9 Arena Parade",
    "sg:city":"Letchworth",
    "sg:classifiers":[
        {
            "category":"Building & Trades",
            "subcategory":"Equipment Rental",
            "type":"Services"
        }
    ],
    "sg:phone":"+44 1462 672120",
    "sg:postcode":"SG6 3BY",
    "sg:province":"Hertfordshire",
    "sg:tags":[
        "hire",
        "centre"
    ],
    "wof:name":"Kilday Tools",
    "wof:placetype":"venue"
},
  "geometry": {"coordinates":[-0.2222429961,51.9725494385],"type":"Point"}
}