{
  "type": "Feature",
  "properties": {
    "iso:country":"GB",
    "sg:address":"Hillside, Hamlet Hill, Roydon",
    "sg:city":"Harlow",
    "sg:classifiers":[
        {
            "category":"Wholesale",
            "subcategory":"Fruits & Vegetables",
            "type":"Manufacturing & Wholesale Goods"
        }
    ],
    "sg:postcode":"CM19 5JU",
    "sg:province":"Essex",
    "wof:name":"B Iameo & Son",
    "wof:placetype":"venue"
},
  "geometry": {"coordinates":[0.038872,51.769241],"type":"Point"}
}