{
  "type": "Feature",
  "properties": {
    "addr:full":"5 Horsdon Terrace Tiverton Devon EX16 4DD",
    "addr:housenumber":"5",
    "addr:postcode":"ex16 4dd",
    "addr:street":"Horsdon Terrace",
    "iso:country":"GB",
    "sg:address":"5 Horsdon Terrace",
    "sg:city":"Tiverton",
    "sg:classifiers":[
        {
            "category":"Professional",
            "subcategory":"Accounting & Tax Preparation",
            "type":"Services"
        }
    ],
    "sg:phone":"+44 1884 252348",
    "sg:postcode":"EX16 4DD",
    "sg:province":"Devon",
    "sg:tags":[
        "accountant"
    ],
    "wof:name":"Rose Beresford",
    "wof:placetype":"venue"
},
  "geometry": {"coordinates":[-3.471621,50.905182],"type":"Point"}
}