{
  "type": "Feature",
  "properties": {
    "addr:full":"18a London Rd Crewe Cheshire CW4 7AJ",
    "addr:housenumber":"18a",
    "addr:postcode":"cw4 7aj",
    "addr:street":"London Rd",
    "iso:country":"GB",
    "sg:address":"18a London Rd",
    "sg:city":"Crewe",
    "sg:classifiers":[
        {
            "category":"Communications",
            "subcategory":"Film & Video Production",
            "type":"Services"
        }
    ],
    "sg:phone":"+44 1477 535392",
    "sg:postcode":"CW4 7AJ",
    "sg:province":"Cheshire",
    "sg:tags":[
        "tv"
    ],
    "wof:name":"Village Videos",
    "wof:placetype":"venue"
},
  "geometry": {"coordinates":[-2.357938,53.202343],"type":"Point"}
}