{
  "type": "Feature",
  "properties": {
    "addr:full":"Warden, Bincombe Court, Hamilton Close Weymouth Dorset DT3 6RG",
    "addr:housenumber":"warden",
    "addr:postcode":"dt3 6rg",
    "addr:street":"Bincombe Court Hamilton Close",
    "iso:country":"GB",
    "sg:address":"Warden, Bincombe Court, Hamilton Close",
    "sg:city":"Weymouth",
    "sg:classifiers":[
        {
            "category":"Government",
            "subcategory":"Office",
            "type":"Public Place"
        },
        {
            "category":"Social Services",
            "subcategory":"Adult Care",
            "type":"Services"
        },
        {
            "category":"Social Services",
            "subcategory":"Retirement Home",
            "type":"Services"
        }
    ],
    "sg:phone":"+44 1305 833760",
    "sg:postcode":"DT3 6RG",
    "sg:province":"Dorset",
    "sg:tags":[
        "housing",
        "local",
        "accommodation",
        "sheltered"
    ],
    "wof:name":"Bincombe Court Sheltered Housing",
    "wof:placetype":"venue"
},
  "geometry": {"coordinates":[-2.449399,50.644596],"type":"Point"}
}