{
  "type": "Feature",
  "properties": {
    "iso:country":"GB",
    "sg:address":"294 Lymington Road, Highcliffe",
    "sg:city":"Christchurch",
    "sg:classifiers":[
        {
            "category":"Real Estate",
            "subcategory":"Real Estate Agent",
            "type":"Services"
        }
    ],
    "sg:phone":"+44 1425 272301",
    "sg:postcode":"BH23 5ET",
    "sg:province":"Dorset",
    "wof:name":"Austin & Wyatt",
    "wof:placetype":"venue"
},
  "geometry": {"coordinates":[-1.701107,50.741322],"type":"Point"}
}