{
  "type": "Feature",
  "properties": {
    "iso:country":"GB",
    "sg:address":"Cammell Laird Shipyard, Campeltown Rd",
    "sg:city":"Birkenhead",
    "sg:classifiers":[
        {
            "category":"Real Estate",
            "subcategory":"Architect",
            "type":"Services"
        }
    ],
    "sg:postcode":"CH41 9BP",
    "sg:province":"Merseyside",
    "sg:tags":[
        "naval"
    ],
    "wof:name":"Cammell Laird Technical Services Ltd",
    "wof:placetype":"venue"
},
  "geometry": {"coordinates":[-3.025489,53.392567],"type":"Point"}
}