{
  "type": "Feature",
  "properties": {
    "addr:full":"293 Uttoxeter Road Stoke-on-trent Staffordshire ST3 5LQ",
    "addr:housenumber":"293",
    "addr:postcode":"st3 5lq",
    "addr:street":"Uttoxeter Road",
    "iso:country":"GB",
    "sg:address":"293 Uttoxeter Road",
    "sg:city":"Stoke-on-trent",
    "sg:classifiers":[
        {
            "category":"Recreation",
            "subcategory":"Fishing",
            "type":"Entertainment"
        }
    ],
    "sg:postcode":"ST3 5LQ",
    "sg:province":"Staffordshire",
    "sg:tags":[
        "angling"
    ],
    "wof:name":"John Birks Sports",
    "wof:placetype":"venue"
},
  "geometry": {"coordinates":[-2.120378,52.982708],"type":"Point"}
}