{
  "type": "Feature",
  "properties": {
    "iso:country":"GB",
    "sg:address":"16 High Street",
    "sg:city":"Brechin",
    "sg:classifiers":[
        {
            "category":"Fast Food",
            "type":"Food & Drink"
        }
    ],
    "sg:phone":"+44 1356 622806",
    "sg:postcode":"DD9 6ER",
    "sg:province":"Aberdeenshire",
    "sg:tags":[
        "away",
        "take"
    ],
    "wof:name":"The Diamond Carry Out",
    "wof:placetype":"venue"
},
  "geometry": {"coordinates":[-2.660425,56.731846],"type":"Point"}
}