{
  "type": "Feature",
  "properties": {
    "addr:full":"25 Barstow Square Wakefield West Yorkshire WF1 2SF",
    "addr:housenumber":"25",
    "addr:postcode":"wf1 2sf",
    "addr:street":"Barstow Square",
    "iso:country":"GB",
    "sg:address":"25 Barstow Square",
    "sg:city":"Wakefield",
    "sg:classifiers":[
        {
            "category":"Personal",
            "subcategory":"Beauty Salon",
            "type":"Services"
        }
    ],
    "sg:phone":"+44 1924 373795",
    "sg:postcode":"WF1 2SF",
    "sg:province":"West Yorkshire",
    "sg:tags":[
        "ladies",
        "lady",
        "hairdresser"
    ],
    "wof:name":"Regency Hairdressing Salon",
    "wof:placetype":"venue"
},
  "geometry": {"coordinates":[-1.501183033,53.6830444336],"type":"Point"}
}