{
  "type": "Feature",
  "properties": {
    "addr:full":"12 Pillory Street Nantwich Cheshire CW5 5BE",
    "addr:housenumber":"12",
    "addr:postcode":"cw5 5be",
    "addr:street":"Pillory Street",
    "iso:country":"GB",
    "sg:address":"12 Pillory Street",
    "sg:city":"Nantwich",
    "sg:classifiers":[
        {
            "category":"Banks & Credit Unions",
            "subcategory":"Bank",
            "type":"Services"
        }
    ],
    "sg:phone":"+44 1270 627081",
    "sg:postcode":"CW5 5BE",
    "sg:province":"Cheshire",
    "sg:tags":[
        "financial",
        "institution"
    ],
    "wof:name":"The Royal Bank of Scotland Plc",
    "wof:placetype":"venue"
},
  "geometry": {"coordinates":[-2.522136,53.06617],"type":"Point"}
}