{
  "type": "Feature",
  "properties": {
    "addr:full":"9c South Gyle Crescent Edinburgh City of Edinburgh EH12 9EB",
    "addr:housenumber":"9c",
    "addr:postcode":"eh12 9eb",
    "addr:street":"South Gyle Crescent",
    "iso:country":"GB",
    "sg:address":"9c South Gyle Crescent",
    "sg:city":"Edinburgh",
    "sg:classifiers":[
        {
            "category":"Professional",
            "subcategory":"Printing & Photocopies",
            "type":"Services"
        }
    ],
    "sg:phone":"+44 131 316 1800",
    "sg:postcode":"EH12 9EB",
    "sg:province":"City of Edinburgh",
    "sg:tags":[
        "printer"
    ],
    "wof:name":"Castle Graphics Ltd.",
    "wof:placetype":"venue"
},
  "geometry": {"coordinates":[-3.2959899902,55.9301719666],"type":"Point"}
}