{
  "type": "Feature",
  "properties": {
    "iso:country":"GB",
    "sg:address":"8 Manchester Road",
    "sg:city":"Nelson",
    "sg:classifiers":[
        {
            "category":"Professional",
            "subcategory":"Lawyer & Legal Services",
            "type":"Services"
        }
    ],
    "sg:postcode":"BB9 7EG",
    "sg:province":"Lancashire",
    "sg:tags":[
        "solicitor"
    ],
    "wof:name":"STERRATT & CO SOLICITORS",
    "wof:placetype":"venue"
},
  "geometry": {"coordinates":[-2.215381,53.836277],"type":"Point"}
}