{
  "type": "Feature",
  "properties": {
    "iso:country":"GB",
    "sg:address":"Caverswall Farm, Lower Loxley",
    "sg:city":"Uttoxeter",
    "sg:classifiers":[
        {
            "category":"Farming",
            "subcategory":"Farm",
            "type":"Manufacturing & Wholesale Goods"
        }
    ],
    "sg:postcode":"ST14 8RZ",
    "sg:province":"Derbyshire",
    "sg:tags":[
        "mixed",
        "crop"
    ],
    "wof:name":"W E F & G Meakin",
    "wof:placetype":"venue"
},
  "geometry": {"coordinates":[-1.916765,52.885002],"type":"Point"}
}