{
  "type": "Feature",
  "properties": {
    "iso:country":"GB",
    "sg:address":"Park St",
    "sg:city":"Barnsley",
    "sg:classifiers":[
        {
            "category":"Autos & Motor Vehicles",
            "subcategory":"Fuel & Gas Station",
            "type":"Retail Goods"
        }
    ],
    "sg:phone":"+44 1226 752990",
    "sg:postcode":"S73 0AS",
    "sg:province":"South Yorkshire",
    "sg:tags":[
        "petrol",
        "filling"
    ],
    "wof:name":"Murco Service Station 91",
    "wof:placetype":"venue"
},
  "geometry": {"coordinates":[-1.3964929581,53.5212745667],"type":"Point"}
}