{
  "type": "Feature",
  "properties": {
    "addr:full":"64 Victoria Road Scarborough North Yorkshire YO11 1SF",
    "addr:housenumber":"64",
    "addr:postcode":"yo11 1sf",
    "addr:street":"Victoria Road",
    "iso:country":"GB",
    "sg:address":"64 Victoria Road",
    "sg:city":"Scarborough",
    "sg:classifiers":[
        {
            "category":"Retail",
            "subcategory":"Laundry & Dry Cleaning",
            "type":"Services"
        }
    ],
    "sg:phone":"+44 1723 366373",
    "sg:postcode":"YO11 1SF",
    "sg:province":"North Yorkshire",
    "sg:tags":[
        "alteration"
    ],
    "wof:name":"Concorde Cleaners",
    "wof:placetype":"venue"
},
  "geometry": {"coordinates":[-0.405796,54.282063],"type":"Point"}
}