{
  "type": "Feature",
  "properties": {
    "iso:country":"GB",
    "sg:address":"12-14 Church Street",
    "sg:city":"Cardiff",
    "sg:classifiers":[
        {
            "category":"Bars & Pubs",
            "type":"Food & Drink"
        }
    ],
    "sg:postcode":"CF10 1BG",
    "sg:province":"Cardiff",
    "sg:tags":[
        "pubs",
        "inn"
    ],
    "wof:name":"Old Arcade Hotel",
    "wof:placetype":"venue"
},
  "geometry": {"coordinates":[-3.179203,51.48027],"type":"Point"}
}