{
  "type": "Feature",
  "properties": {
    "addr:full":"10 King George Avenue Gateshead Tyne and Wear NE11 9UP",
    "addr:housenumber":"10",
    "addr:postcode":"ne11 9up",
    "addr:street":"King George Avenue",
    "iso:country":"GB",
    "sg:address":"10 King George Avenue",
    "sg:city":"Gateshead",
    "sg:classifiers":[
        {
            "category":"Personal",
            "subcategory":"Beauty Salon",
            "type":"Services"
        }
    ],
    "sg:phone":"+44 191 460 4189",
    "sg:postcode":"NE11 9UP",
    "sg:province":"Tyne and Wear",
    "sg:tags":[
        "ladies",
        "lady",
        "hairdresser"
    ],
    "wof:name":"H T Hair Design",
    "wof:placetype":"venue"
},
  "geometry": {"coordinates":[-1.6432900429,54.9537658691],"type":"Point"}
}