{
  "type": "Feature",
  "properties": {
    "iso:country":"GB",
    "sg:address":"Perth Area Office, Gowans Terrace",
    "sg:city":"Perth",
    "sg:classifiers":[
        {
            "category":"Utilities",
            "subcategory":"Water",
            "type":"Services"
        }
    ],
    "sg:phone":"+44 1738 627211",
    "sg:postcode":"PH1 5AY",
    "sg:province":"Perth and Kinross",
    "sg:tags":[
        "authority"
    ],
    "wof:name":"Scottish Water",
    "wof:placetype":"venue"
},
  "geometry": {"coordinates":[-3.44831,56.41],"type":"Point"}
}