{
  "type": "Feature",
  "properties": {
    "iso:country":"GB",
    "sg:address":"School Road, Ringsfield",
    "sg:city":"Beccles",
    "sg:classifiers":[
        {
            "category":"Education",
            "subcategory":"School",
            "type":"Public Place"
        },
        {
            "category":"Government",
            "subcategory":"Office",
            "type":"Public Place"
        }
    ],
    "sg:phone":"+44 1502 713030",
    "sg:postcode":"NR34 8NZ",
    "sg:province":"Norfolk",
    "sg:tags":[
        "local",
        "authority"
    ],
    "wof:name":"Ringsfield C Of E VC Primary School",
    "wof:placetype":"venue"
},
  "geometry": {"coordinates":[1.534522,52.441414],"type":"Point"}
}