{
  "type": "Feature",
  "properties": {
    "addr:full":"Business Station Warrington Cheshire WA1 1QD",
    "addr:postcode":"wa1 1qd",
    "addr:street":"Warrington Cheshire",
    "iso:country":"GB",
    "sg:address":"Business Station",
    "sg:city":"Warrington",
    "sg:classifiers":[
        {
            "category":"Shopping",
            "subcategory":"News",
            "type":"Retail Goods"
        }
    ],
    "sg:phone":"+44 1925 652198",
    "sg:postcode":"WA1 1QD",
    "sg:province":"Cheshire",
    "sg:tags":[
        "newsagent"
    ],
    "wof:name":"Paper Stop",
    "wof:placetype":"venue"
},
  "geometry": {"coordinates":[-2.595979929,53.3903007507],"type":"Point"}
}