{
  "type": "Feature",
  "properties": {
    "iso:country":"GB",
    "sg:address":"19 Parkhurst Rd",
    "sg:city":"Torquay",
    "sg:classifiers":[
        {
            "category":"Building & Trades",
            "subcategory":"Construction",
            "type":"Services"
        }
    ],
    "sg:phone":"+44 1803 315335",
    "sg:postcode":"TQ1 4EW",
    "sg:province":"Devon",
    "sg:tags":[
        "joiner",
        "carpenter"
    ],
    "wof:name":"S & S Carpenters Ltd",
    "wof:placetype":"venue"
},
  "geometry": {"coordinates":[-3.542302,50.476246],"type":"Point"}
}