{
  "type": "Feature",
  "properties": {
    "iso:country":"GB",
    "sg:address":"Manor Farm, Moor La",
    "sg:city":"Otley",
    "sg:classifiers":[
        {
            "category":"Farming",
            "subcategory":"Farm",
            "type":"Manufacturing & Wholesale Goods"
        }
    ],
    "sg:phone":"+44 1943 462285",
    "sg:postcode":"LS21 2HS",
    "sg:province":"North Yorkshire",
    "sg:tags":[
        "mixed",
        "crop"
    ],
    "wof:name":"F Hill",
    "wof:placetype":"venue"
},
  "geometry": {"coordinates":[-1.694953,53.90572],"type":"Point"}
}