{
  "type": "Feature",
  "properties": {
    "addr:full":"108 Taplow Ho, Thurlow St London Greater London SE17 2UJ",
    "addr:housenumber":"108",
    "addr:postcode":"se17 2uj",
    "addr:street":"Taplow Ho Thurlow St",
    "iso:country":"GB",
    "sg:address":"108 Taplow Ho, Thurlow St",
    "sg:city":"London",
    "sg:classifiers":[
        {
            "category":"Professional",
            "subcategory":"Detective & Security Services",
            "type":"Services"
        }
    ],
    "sg:phone":"+44 20 7703 6155",
    "sg:postcode":"SE17 2UJ",
    "sg:province":"Greater London",
    "wof:name":"Delta Security Uk Ltd",
    "wof:placetype":"venue"
},
  "geometry": {"coordinates":[-0.08663,51.4883],"type":"Point"}
}