{
  "type": "Feature",
  "properties": {
    "iso:country":"GB",
    "sg:address":"20 Highbeech Lane",
    "sg:city":"Chepstow",
    "sg:classifiers":[
        {
            "category":"Professional",
            "subcategory":"Lawyer & Legal Services",
            "type":"Services"
        }
    ],
    "sg:phone":"+44 1291 621638",
    "sg:postcode":"NP16 5BQ",
    "sg:province":"Gloucestershire",
    "sg:tags":[
        "solicitor"
    ],
    "wof:name":"Marie Dark Solicitors",
    "wof:placetype":"venue"
},
  "geometry": {"coordinates":[-2.682458,51.633739],"type":"Point"}
}