{
  "type": "Feature",
  "properties": {
    "addr:full":"Sunkyong House, Springfield Road Hayes Greater London UB4 0TY",
    "addr:postcode":"ub4 0ty",
    "addr:street":"Springfield Road",
    "iso:country":"GB",
    "sg:address":"Sunkyong House, Springfield Road",
    "sg:city":"Hayes",
    "sg:classifiers":[
        {
            "category":"Shopping",
            "subcategory":"Computers & Home Electronics",
            "type":"Retail Goods"
        }
    ],
    "sg:phone":"+44 20 8573 0909",
    "sg:postcode":"UB4 0TY",
    "sg:province":"Greater London",
    "sg:tags":[
        "equipment",
        "audio-visual"
    ],
    "wof:name":"S K M Europe Ltd.",
    "wof:placetype":"venue"
},
  "geometry": {"coordinates":[-0.397549,51.51231],"type":"Point"}
}