{
  "type": "Feature",
  "properties": {
    "iso:country":"GB",
    "sg:address":"Woodley Health Centre, Hyde Rd",
    "sg:city":"Stockport",
    "sg:classifiers":[
        {
            "category":"Health Services",
            "subcategory":"Doctor",
            "type":"Services"
        }
    ],
    "sg:phone":"+44 161 430 4166",
    "sg:postcode":"SK6 1NB",
    "sg:province":"Cheshire",
    "sg:tags":[
        "practitioners"
    ],
    "wof:name":"Rahu, C S",
    "wof:placetype":"venue"
},
  "geometry": {"coordinates":[-2.097542,53.426571],"type":"Point"}
}