{
  "type": "Feature",
  "properties": {
    "iso:country":"GB",
    "sg:address":"7a Main Road",
    "sg:city":"Nottingham",
    "sg:classifiers":[
        {
            "category":"Cafe",
            "type":"Food & Drink"
        }
    ],
    "sg:phone":"+44 115 933 3638",
    "sg:postcode":"NG12 2FD",
    "sg:province":"Nottinghamshire",
    "sg:tags":[
        "tea",
        "room"
    ],
    "wof:name":"The Poplars Coffee Shop",
    "wof:placetype":"venue"
},
  "geometry": {"coordinates":[-1.039075017,52.9468269348],"type":"Point"}
}