{
  "type": "Feature",
  "properties": {
    "iso:country":"GB",
    "sg:address":"18 Farmeloan Road, Rutherglen",
    "sg:city":"Glasgow",
    "sg:classifiers":[
        {
            "category":"Organizations",
            "subcategory":"Community Association",
            "type":"Services"
        }
    ],
    "sg:phone":"+44 141 647 4917",
    "sg:postcode":"G73 1DL",
    "sg:province":"Glasgow City",
    "sg:tags":[
        "society",
        "housing"
    ],
    "wof:name":"Rutherglen Housing Association Ltd.",
    "wof:placetype":"venue"
},
  "geometry": {"coordinates":[-4.210319,55.82909],"type":"Point"}
}