{
  "type": "Feature",
  "properties": {
    "iso:country":"GB",
    "sg:address":"27 Prospect Vale",
    "sg:city":"Liverpool",
    "sg:classifiers":[
        {
            "category":"Real Estate",
            "subcategory":"Surveying",
            "type":"Services"
        }
    ],
    "sg:phone":"+44 151 280 2021",
    "sg:postcode":"L6 8PE",
    "sg:province":"Merseyside",
    "sg:tags":[
        "surveyor",
        "land"
    ],
    "wof:name":"Mike Wynne Land Surveys",
    "wof:placetype":"venue"
},
  "geometry": {"coordinates":[-2.937943,53.415134],"type":"Point"}
}