{
  "type": "Feature",
  "properties": {
    "addr:full":"167 Evington Road Leicester Leicestershire LE2 1QL",
    "addr:housenumber":"167",
    "addr:postcode":"le2 1ql",
    "addr:street":"Evington Road",
    "iso:country":"GB",
    "sg:address":"167 Evington Road",
    "sg:city":"Leicester",
    "sg:classifiers":[
        {
            "category":"Food & Beverages",
            "subcategory":"Meat & Fish",
            "type":"Retail Goods"
        }
    ],
    "sg:postcode":"LE2 1QL",
    "sg:province":"Leicestershire",
    "sg:tags":[
        "chip"
    ],
    "wof:name":"Ivo's Fish Bar",
    "wof:placetype":"venue"
},
  "geometry": {"coordinates":[-1.107908,52.625271],"type":"Point"}
}