{
  "type": "Feature",
  "properties": {
    "iso:country":"GB",
    "sg:address":"Trafford Plaza, Old Trafford",
    "sg:city":"Manchester",
    "sg:classifiers":[
        {
            "category":"Professional",
            "subcategory":"Art Services",
            "type":"Services"
        }
    ],
    "sg:phone":"+44 161 874 3403",
    "sg:postcode":"M16 0LD",
    "sg:province":"Cheshire",
    "sg:tags":[
        "graphic",
        "designer"
    ],
    "wof:name":"J F B Advertising Ltd.",
    "wof:placetype":"venue"
},
  "geometry": {"coordinates":[-2.283087,53.464184],"type":"Point"}
}