{
  "type": "Feature",
  "properties": {
    "iso:country":"GB",
    "sg:address":"Livestock Auction Mart, Whitefordhill",
    "sg:city":"Ayr",
    "sg:classifiers":[
        {
            "category":"Professional",
            "type":"Services"
        },
        {
            "category":"Food & Beverages",
            "subcategory":"Farmers Market",
            "type":"Retail Goods"
        },
        {
            "category":"Farming",
            "subcategory":"Livestock Farm",
            "type":"Manufacturing & Wholesale Goods"
        }
    ],
    "sg:phone":"+44 1292 262241",
    "sg:postcode":"KA6 5JW",
    "sg:province":"East Ayrshire",
    "sg:tags":[
        "others",
        "auctioneer"
    ],
    "wof:name":"JAMES CRAIG LTD",
    "wof:placetype":"venue"
},
  "geometry": {"coordinates":[-4.5677,55.452641],"type":"Point"}
}