{
  "type": "Feature",
  "properties": {
    "iso:country":"GB",
    "sg:address":"29 Botanic Road, Churchtown",
    "sg:city":"Southport",
    "sg:classifiers":[
        {
            "category":"Wholesale",
            "subcategory":"Construction Materials",
            "type":"Manufacturing & Wholesale Goods"
        }
    ],
    "sg:phone":"+44 1704 225402",
    "sg:postcode":"PR9 7NG",
    "sg:province":"Lancashire",
    "sg:tags":[
        "merchant",
        "glass"
    ],
    "wof:name":"Churchtown Glass",
    "wof:placetype":"venue"
},
  "geometry": {"coordinates":[-2.964869976,53.6584472656],"type":"Point"}
}