{
  "type": "Feature",
  "properties": {
    "addr:full":"Eastfield Farm Rd Penicuik Midlothian EH26 8EZ",
    "addr:postcode":"eh26 8ez",
    "addr:street":"Eastfield Farm Rd",
    "iso:country":"GB",
    "sg:address":"Eastfield Farm Rd",
    "sg:city":"Penicuik",
    "sg:classifiers":[
        {
            "category":"Food & Beverages",
            "subcategory":"Liquor & Beverages",
            "type":"Retail Goods"
        }
    ],
    "sg:phone":"+44 1968 679676",
    "sg:postcode":"EH26 8EZ",
    "sg:province":"Midlothian",
    "sg:tags":[
        "drink",
        "soft"
    ],
    "wof:name":"Edinburgh Soft Drinks",
    "wof:placetype":"venue"
},
  "geometry": {"coordinates":[-3.2199039459,55.8363952637],"type":"Point"}
}