{
  "type": "Feature",
  "properties": {
    "addr:full":"68 Market Street Wigan Lancashire WN1 1HX",
    "addr:housenumber":"68",
    "addr:postcode":"wn1 1hx",
    "addr:street":"Market Street",
    "iso:country":"GB",
    "sg:address":"68 Market Street",
    "sg:city":"Wigan",
    "sg:classifiers":[
        {
            "category":"Organizations",
            "subcategory":"Non-profit Organization",
            "type":"Services"
        }
    ],
    "sg:phone":"+44 1942 241972",
    "sg:postcode":"WN1 1HX",
    "sg:province":"Lancashire",
    "sg:tags":[
        "organisation",
        "voluntary",
        "charity"
    ],
    "wof:name":"Age Concern Wigan Borough Enterprises Ltd.",
    "wof:placetype":"venue"
},
  "geometry": {"coordinates":[-2.633632,53.547981],"type":"Point"}
}