{
  "type": "Feature",
  "properties": {
    "iso:country":"GB",
    "sg:address":"Redvers Farm, Uppingham Road, Houghton On The Hill",
    "sg:city":"Leicester",
    "sg:classifiers":[
        {
            "category":"Farming",
            "subcategory":"Livestock Farm",
            "type":"Manufacturing & Wholesale Goods"
        }
    ],
    "sg:postcode":"LE7 9HG",
    "sg:province":"Leicestershire",
    "sg:tags":[
        "others"
    ],
    "wof:name":"B A Harris",
    "wof:placetype":"venue"
},
  "geometry": {"coordinates":[-0.998536,52.627869],"type":"Point"}
}