{
  "type": "Feature",
  "properties": {
    "iso:country":"GB",
    "sg:address":"Northfield Industrial Estate, Market Deeping",
    "sg:city":"Peterborough",
    "sg:classifiers":[
        {
            "category":"Professional",
            "subcategory":"Engineering",
            "type":"Services"
        }
    ],
    "sg:phone":"+44 1778 344733",
    "sg:postcode":"PE6 8LA",
    "sg:province":"Cambridgeshire",
    "sg:tags":[
        "precision",
        "engineer"
    ],
    "wof:name":"Gemweld Fabrications & Engineering Co. Ltd.",
    "wof:placetype":"venue"
},
  "geometry": {"coordinates":[-0.314699,52.687248],"type":"Point"}
}