{
  "type": "Feature",
  "properties": {
    "addr:full":"83-85 Kirkstall Road Leeds West Yorkshire LS3 1HS",
    "addr:housenumber":"83-85",
    "addr:postcode":"ls3 1hs",
    "addr:street":"Kirkstall Road",
    "iso:country":"GB",
    "sg:address":"83-85 Kirkstall Road",
    "sg:city":"Leeds",
    "sg:classifiers":[
        {
            "category":"Autos & Motor Vehicles",
            "subcategory":"Auto Supplies",
            "type":"Retail Goods"
        }
    ],
    "sg:phone":"+44 113 243 2266",
    "sg:postcode":"LS3 1HS",
    "sg:province":"West Yorkshire",
    "sg:tags":[
        "tyre"
    ],
    "wof:name":"Rapid Fit",
    "wof:placetype":"venue"
},
  "geometry": {"coordinates":[-1.568031,53.800735],"type":"Point"}
}