{
  "type": "Feature",
  "properties": {
    "iso:country":"GB",
    "sg:address":"Crosby Terrace, Port Clarence",
    "sg:city":"Middlesbrough",
    "sg:classifiers":[
        {
            "category":"Bars & Pubs",
            "type":"Food & Drink"
        }
    ],
    "sg:phone":"+44 1642 546552",
    "sg:postcode":"TS2 1SE",
    "sg:province":"Durham",
    "sg:tags":[
        "pubs",
        "inn"
    ],
    "wof:name":"The Station Hotel",
    "wof:placetype":"venue"
},
  "geometry": {"coordinates":[-1.225494,54.586563],"type":"Point"}
}