{
  "type": "Feature",
  "properties": {
    "iso:country":"GB",
    "sg:address":"15 Buttermarket St",
    "sg:city":"Warrington",
    "sg:classifiers":[
        {
            "category":"Shopping",
            "subcategory":"Beauty & Cosmetics",
            "type":"Retail Goods"
        }
    ],
    "sg:phone":"+44 1925 574717",
    "sg:postcode":"WA1 2LY",
    "sg:province":"Cheshire",
    "sg:tags":[
        "product"
    ],
    "wof:name":"Peels Pound Shop",
    "wof:placetype":"venue"
},
  "geometry": {"coordinates":[-2.592577,53.389568],"type":"Point"}
}