{
  "type": "Feature",
  "properties": {
    "addr:full":"Lee Road Lynton Devon EX35 6HW",
    "addr:postcode":"ex35 6hw",
    "addr:street":"Lee Road",
    "iso:country":"GB",
    "sg:address":"Lee Road",
    "sg:city":"Lynton",
    "sg:classifiers":[
        {
            "category":"Travel",
            "subcategory":"Hotels & Motels",
            "type":"Entertainment"
        }
    ],
    "sg:phone":"+44 1598 752279",
    "sg:postcode":"EX35 6HW",
    "sg:province":"Devon",
    "wof:name":"Rockvale Hotel",
    "wof:placetype":"venue"
},
  "geometry": {"coordinates":[-3.8353660107,51.2301979065],"type":"Point"}
}