{
  "type": "Feature",
  "properties": {
    "iso:country":"GB",
    "sg:address":"Park Garage, Hermet Rd",
    "sg:city":"London",
    "sg:classifiers":[
        {
            "category":"Professional",
            "subcategory":"Testing Lab",
            "type":"Services"
        }
    ],
    "sg:postcode":"E16 4LD",
    "sg:province":"Greater London",
    "sg:tags":[
        "mot"
    ],
    "wof:name":"Bhachoo,K S,",
    "wof:placetype":"venue"
},
  "geometry": {"coordinates":[0.01302,51.51844],"type":"Point"}
}