{
  "type": "Feature",
  "properties": {
    "addr:full":"Unit 1, Coed Y Parc Industrial Estate, Coed Y Parc Bangor Gwynedd LL57 4YY",
    "addr:housenumber":"unit 1",
    "addr:postcode":"ll57 4yy",
    "addr:street":"Coed Y Parc Industrial;Coed Y Parc",
    "iso:country":"GB",
    "sg:address":"Unit 1, Coed Y Parc Industrial Estate, Coed Y Parc",
    "sg:city":"Bangor",
    "sg:classifiers":[
        {
            "category":"Manufacturing",
            "subcategory":"Wood Products",
            "type":"Manufacturing & Wholesale Goods"
        }
    ],
    "sg:phone":"+44 1248 602654",
    "sg:postcode":"LL57 4YY",
    "sg:province":"Gwynedd",
    "sg:tags":[
        "maker",
        "cabinet"
    ],
    "wof:name":"David Fishbein",
    "wof:placetype":"venue"
},
  "geometry": {"coordinates":[-4.0775718689,53.1728630066],"type":"Point"}
}