{
  "type": "Feature",
  "properties": {
    "iso:country":"GB",
    "sg:address":"Westoning Road, Harlington",
    "sg:city":"Dunstable",
    "sg:classifiers":[
        {
            "category":"Home & Garden",
            "subcategory":"Garden Supply",
            "type":"Retail Goods"
        }
    ],
    "sg:phone":"+44 1525 873070",
    "sg:postcode":"LU5 6PA",
    "sg:province":"Bedfordshire",
    "sg:tags":[
        "nursery",
        "centre"
    ],
    "wof:name":"Bridgeside Nurseries & Garden Centre",
    "wof:placetype":"venue"
},
  "geometry": {"coordinates":[-0.494785,51.962418],"type":"Point"}
}