{
  "type": "Feature",
  "properties": {
    "addr:full":"34 Main Road Worcester Worcestershire WR5 3NA",
    "addr:housenumber":"34",
    "addr:postcode":"wr5 3na",
    "addr:street":"Main Road",
    "iso:country":"GB",
    "sg:address":"34 Main Road",
    "sg:city":"Worcester",
    "sg:classifiers":[
        {
            "category":"Bars & Pubs",
            "type":"Food & Drink"
        }
    ],
    "sg:postcode":"WR5 3NA",
    "sg:province":"Worcestershire",
    "sg:tags":[
        "pubs",
        "inn"
    ],
    "wof:name":"Walter de Cantelupe Inn",
    "wof:placetype":"venue"
},
  "geometry": {"coordinates":[-2.216608,52.138428],"type":"Point"}
}