{
  "type": "Feature",
  "properties": {
    "addr:full":"657 Willenhall Road Willenhall West Midlands WV13 3LH",
    "addr:housenumber":"657",
    "addr:postcode":"wv13 3lh",
    "addr:street":"Willenhall Road",
    "iso:country":"GB",
    "sg:address":"657 Willenhall Road",
    "sg:city":"Willenhall",
    "sg:classifiers":[
        {
            "category":"Restaurant",
            "type":"Food & Drink"
        }
    ],
    "sg:phone":"+44 1902 633622",
    "sg:postcode":"WV13 3LH",
    "sg:province":"West Midlands",
    "sg:tags":[
        "indian"
    ],
    "wof:name":"Balti Nite",
    "wof:placetype":"venue"
},
  "geometry": {"coordinates":[-2.0719799995,52.5836257935],"type":"Point"}
}