{
  "type": "Feature",
  "properties": {
    "iso:country":"GB",
    "sg:address":"69a Wynn Rd",
    "sg:city":"Wolverhampton",
    "sg:classifiers":[
        {
            "category":"Personal",
            "subcategory":"Beauty Salon",
            "type":"Services"
        }
    ],
    "sg:phone":"+44 1902 334560",
    "sg:postcode":"WV4 4AJ",
    "sg:province":"Staffordshire",
    "sg:tags":[
        "lady",
        "hairdresser"
    ],
    "wof:name":"Tina Wilbrey Hair Design",
    "wof:placetype":"venue"
},
  "geometry": {"coordinates":[-2.1518371105,52.5661277771],"type":"Point"}
}