{
  "type": "Feature",
  "properties": {
    "addr:full":"5 Lexham Ct, High St Maidenhead Berkshire SL6 1QN",
    "addr:housenumber":"5",
    "addr:postcode":"sl6 1qn",
    "addr:street":"Lexham Ct High St",
    "iso:country":"GB",
    "sg:address":"5 Lexham Ct, High St",
    "sg:city":"Maidenhead",
    "sg:classifiers":[
        {
            "category":"Health Services",
            "subcategory":"Dentist",
            "type":"Services"
        }
    ],
    "sg:phone":"+44 1628 637243",
    "sg:postcode":"SL6 1QN",
    "sg:province":"Berkshire",
    "wof:name":"N D John",
    "wof:placetype":"venue"
},
  "geometry": {"coordinates":[-0.7272570133,51.5223731995],"type":"Point"}
}