{
  "type": "Feature",
  "properties": {
    "iso:country":"GB",
    "sg:address":"Radway Place",
    "sg:city":"Sidmouth",
    "sg:classifiers":[
        {
            "category":"Home & Garden",
            "subcategory":"Household Appliances",
            "type":"Retail Goods"
        }
    ],
    "sg:phone":"+44 1395 579479",
    "sg:postcode":"EX10 8TL",
    "sg:province":"Devon",
    "sg:tags":[
        "electrical",
        "domestic"
    ],
    "wof:name":"C & C Electrical",
    "wof:placetype":"venue"
},
  "geometry": {"coordinates":[-3.239309,50.683083],"type":"Point"}
}