{
  "type": "Feature",
  "properties": {
    "addr:full":"182 Bath Street Glasgow Glasgow City G2 4HG",
    "addr:housenumber":"182",
    "addr:postcode":"g2 4hg",
    "addr:street":"Bath Street",
    "iso:country":"GB",
    "sg:address":"182 Bath Street",
    "sg:city":"Glasgow",
    "sg:classifiers":[
        {
            "category":"Organizations",
            "subcategory":"Non-profit Organization",
            "type":"Services"
        }
    ],
    "sg:phone":"+44 141 332 0476",
    "sg:postcode":"G2 4HG",
    "sg:province":"Glasgow City",
    "sg:tags":[
        "organisation",
        "voluntary",
        "charity"
    ],
    "wof:name":"Renfield Street Trust",
    "wof:placetype":"venue"
},
  "geometry": {"coordinates":[-4.2621598244,55.8645973206],"type":"Point"}
}