{
  "type": "Feature",
  "properties": {
    "addr:full":"136 Duckpool Rd Newport Newport NP19 8FL",
    "addr:housenumber":"136",
    "addr:postcode":"np19 8fl",
    "addr:street":"Duckpool Rd",
    "iso:country":"GB",
    "sg:address":"136 Duckpool Rd",
    "sg:city":"Newport",
    "sg:classifiers":[
        {
            "category":"Communications",
            "type":"Services"
        }
    ],
    "sg:postcode":"NP19 8FL",
    "sg:province":"Newport",
    "sg:tags":[
        "tv",
        "video",
        "radio"
    ],
    "wof:name":"Megavision",
    "wof:placetype":"venue"
},
  "geometry": {"coordinates":[-2.9805839062,51.5924797058],"type":"Point"}
}