{
  "type": "Feature",
  "properties": {
    "addr:full":"137 St Georges Road Glasgow Glasgow City G3 6JB",
    "addr:housenumber":"137",
    "addr:postcode":"g3 6jb",
    "addr:street":"St Georges Road",
    "iso:country":"GB",
    "sg:address":"137 St Georges Road",
    "sg:city":"Glasgow",
    "sg:classifiers":[
        {
            "category":"Health Services",
            "subcategory":"Doctor",
            "type":"Services"
        }
    ],
    "sg:phone":"+44 141 332 5553",
    "sg:postcode":"G3 6JB",
    "sg:province":"Glasgow City",
    "sg:tags":[
        "practitioners"
    ],
    "wof:name":"St Georges Medical Centre",
    "wof:placetype":"venue"
},
  "geometry": {"coordinates":[-4.2646479607,55.8737831116],"type":"Point"}
}