{
  "type": "Feature",
  "properties": {
    "iso:country":"GB",
    "sg:address":"172 London Road, Hazel Gro",
    "sg:city":"Stockport",
    "sg:classifiers":[
        {
            "category":"Shopping",
            "subcategory":"News",
            "type":"Retail Goods"
        }
    ],
    "sg:phone":"+44 161 483 2963",
    "sg:postcode":"SK7 4DJ",
    "sg:province":"Cheshire",
    "sg:tags":[
        "newsagent"
    ],
    "wof:name":"Grove Stationers",
    "wof:placetype":"venue"
},
  "geometry": {"coordinates":[-2.122744,53.380424],"type":"Point"}
}