{
  "type": "Feature",
  "properties": {
    "addr:full":"Unit 5, Abbotts Close Ivybridge Devon PL21 9PE",
    "addr:housenumber":"unit 5",
    "addr:postcode":"pl21 9pe",
    "addr:street":"Abbotts Close",
    "iso:country":"GB",
    "sg:address":"Unit 5, Abbotts Close",
    "sg:city":"Ivybridge",
    "sg:classifiers":[
        {
            "category":"Government",
            "subcategory":"Post Office",
            "type":"Public Place"
        }
    ],
    "sg:postcode":"PL21 9PE",
    "sg:province":"Devon",
    "sg:tags":[
        "messenger",
        "courier"
    ],
    "wof:name":"Driving Force",
    "wof:placetype":"venue"
},
  "geometry": {"coordinates":[-3.9505639076,50.3862113953],"type":"Point"}
}