{
  "type": "Feature",
  "properties": {
    "iso:country":"GB",
    "sg:address":"Woodland Road",
    "sg:city":"Windermere",
    "sg:classifiers":[
        {
            "category":"Personal",
            "subcategory":"Beauty Salon",
            "type":"Services"
        }
    ],
    "sg:phone":"+44 15394 42703",
    "sg:postcode":"LA23 3BJ",
    "sg:province":"Cumbria",
    "sg:tags":[
        "lady",
        "hairdresser"
    ],
    "wof:name":"John Elbourne",
    "wof:placetype":"venue"
},
  "geometry": {"coordinates":[-2.903194,54.376083],"type":"Point"}
}