{
  "type": "Feature",
  "properties": {
    "addr:full":"10 Boscastle Rd, Dartmouth Park Kentish Town Greater London NW5 1EG",
    "addr:housenumber":"10",
    "addr:postcode":"nw5 1eg",
    "addr:street":"Boscastle Rd;Park",
    "iso:country":"GB",
    "sg:address":"10 Boscastle Rd, Dartmouth Park",
    "sg:city":"Kentish Town",
    "sg:classifiers":[
        {
            "category":"Health Services",
            "subcategory":"Health Practitioner",
            "type":"Services"
        }
    ],
    "sg:phone":"+44 20 7267 1519",
    "sg:postcode":"NW5 1EG",
    "sg:province":"Greater London",
    "sg:tags":[
        "technique",
        "alexander"
    ],
    "wof:name":"Susanne Hall M.Stat",
    "wof:placetype":"venue"
},
  "geometry": {"coordinates":[-0.1462779939,51.5590248108],"type":"Point"}
}