{
  "type": "Feature",
  "properties": {
    "iso:country":"GB",
    "sg:address":"155-159 Salters Rd",
    "sg:city":"Newcastle Upon Tyne",
    "sg:classifiers":[
        {
            "category":"Food & Beverages",
            "subcategory":"Liquor & Beverages",
            "type":"Retail Goods"
        }
    ],
    "sg:phone":"+44 191 285 2289",
    "sg:postcode":"NE3 4HJ",
    "sg:province":"Tyne and Wear",
    "sg:tags":[
        "beer",
        "spirit",
        "wines"
    ],
    "wof:name":"Berkeley Wines",
    "wof:placetype":"venue"
},
  "geometry": {"coordinates":[-1.626562,55.005913],"type":"Point"}
}