{
  "type": "Feature",
  "properties": {
    "iso:country":"GB",
    "sg:address":"298 Meadowhead",
    "sg:city":"Sheffield",
    "sg:classifiers":[
        {
            "category":"Shopping",
            "type":"Retail Goods"
        }
    ],
    "sg:phone":"+44 114 274 7712",
    "sg:postcode":"S8 7UH",
    "sg:province":"Derbyshire",
    "sg:tags":[
        "part",
        "accessory"
    ],
    "wof:name":"Motormania",
    "wof:placetype":"venue"
},
  "geometry": {"coordinates":[-1.481629,53.337791],"type":"Point"}
}