{
  "type": "Feature",
  "properties": {
    "addr:full":"2 & 12 Tylney Road Bromley Kent BR1 2RB",
    "addr:housenumber":"2 & 12",
    "addr:postcode":"br1 2rb",
    "addr:street":"Tylney Road",
    "iso:country":"GB",
    "sg:address":"2 & 12 Tylney Road",
    "sg:city":"Bromley",
    "sg:classifiers":[
        {
            "category":"Autos & Motor Vehicles",
            "subcategory":"Automobile Sales",
            "type":"Retail Goods"
        }
    ],
    "sg:phone":"+44 20 8464 7070",
    "sg:postcode":"BR1 2RB",
    "sg:province":"Kent",
    "sg:tags":[
        "car"
    ],
    "wof:name":"S G Smith (Motors) Bromley Ltd.",
    "wof:placetype":"venue"
},
  "geometry": {"coordinates":[0.034917,51.404591],"type":"Point"}
}