{
  "type": "Feature",
  "properties": {
    "addr:full":"7 Easrt Reach Taunton Somerset TA1 3EN",
    "addr:housenumber":"7",
    "addr:postcode":"ta1 3en",
    "addr:street":"Easrt Reach",
    "iso:country":"GB",
    "sg:address":"7 Easrt Reach",
    "sg:city":"Taunton",
    "sg:classifiers":[
        {
            "category":"Home & Garden",
            "subcategory":"Carpets & Floor Coverings",
            "type":"Retail Goods"
        }
    ],
    "sg:phone":"+44 1823 323602",
    "sg:postcode":"TA1 3EN",
    "sg:province":"Somerset",
    "sg:tags":[
        "carpets",
        "retailer",
        "rug",
        "matting"
    ],
    "wof:name":"Carpets 'R' Us",
    "wof:placetype":"venue"
},
  "geometry": {"coordinates":[-3.0961689949,51.0151672363],"type":"Point"}
}