{
  "type": "Feature",
  "properties": {
    "addr:full":"Blacksmiths Workshop, Wharton Court Leominster Herefordshire HR6 0NX",
    "addr:postcode":"hr6 0nx",
    "addr:street":"Wharton Court",
    "iso:country":"GB",
    "sg:address":"Blacksmiths Workshop, Wharton Court",
    "sg:city":"Leominster",
    "sg:classifiers":[
        {
            "category":"Home & Garden",
            "subcategory":"Building Materials",
            "type":"Retail Goods"
        }
    ],
    "sg:postcode":"HR6 0NX",
    "sg:province":"Herefordshire",
    "sg:tags":[
        "ironwork",
        "diy",
        "wrought"
    ],
    "wof:name":"Peter King",
    "wof:placetype":"venue"
},
  "geometry": {"coordinates":[-2.7123188972,52.2772293091],"type":"Point"}
}