{
  "type": "Feature",
  "properties": {
    "addr:full":"Gibbons Street, Dunkirk Nottingham Nottinghamshire NG7 2SB",
    "addr:postcode":"ng7 2sb",
    "addr:street":"Gibbons Street",
    "iso:country":"GB",
    "sg:address":"Gibbons Street, Dunkirk",
    "sg:city":"Nottingham",
    "sg:classifiers":[
        {
            "category":"Banks & Credit Unions",
            "subcategory":"Bureau De Change",
            "type":"Services"
        }
    ],
    "sg:phone":"+44 115 978 7633",
    "sg:postcode":"NG7 2SB",
    "sg:province":"Nottinghamshire",
    "sg:tags":[
        "encapsulation",
        "lamination"
    ],
    "wof:name":"Permabond Laminates Ltd.",
    "wof:placetype":"venue"
},
  "geometry": {"coordinates":[-1.1794019938,52.9363098145],"type":"Point"}
}