{
  "type": "Feature",
  "properties": {
    "addr:full":"56 Stewarts Road, Finedon Road Industrial Estate Wellingborough Northamptonshire NN8 4RJ",
    "addr:housenumber":"56",
    "addr:postcode":"nn8 4rj",
    "addr:street":"Stewarts Road Finedon Road Industrial Estate",
    "iso:country":"GB",
    "sg:address":"56 Stewarts Road, Finedon Road Industrial Estate",
    "sg:city":"Wellingborough",
    "sg:classifiers":[
        {
            "category":"Home & Garden",
            "subcategory":"Building Materials",
            "type":"Retail Goods"
        }
    ],
    "sg:postcode":"NN8 4RJ",
    "sg:province":"Northamptonshire",
    "sg:tags":[
        "wire",
        "cable"
    ],
    "wof:name":"Obo Bettermann Ltd.",
    "wof:placetype":"venue"
},
  "geometry": {"coordinates":[-0.6881110072,52.3199501038],"type":"Point"}
}