{
  "type": "Feature",
  "properties": {
    "iso:country":"GB",
    "sg:address":"Polwarth Gardens Surgery, 72 Polwarth Gardens",
    "sg:city":"Edinburgh",
    "sg:classifiers":[
        {
            "category":"Health Services",
            "subcategory":"Doctor",
            "type":"Services"
        }
    ],
    "sg:phone":"+44 131 229 5914",
    "sg:postcode":"EH11 1LL",
    "sg:province":"City of Edinburgh",
    "sg:tags":[
        "practitioners"
    ],
    "wof:name":"Alec Millar",
    "wof:placetype":"venue"
},
  "geometry": {"coordinates":[-3.216408968,55.9411239624],"type":"Point"}
}