{
  "type": "Feature",
  "properties": {
    "iso:country":"GB",
    "sg:address":"112 Regents Park Road, Finchley",
    "sg:city":"London",
    "sg:classifiers":[
        {
            "category":"Food & Beverages",
            "subcategory":"Meat & Fish",
            "type":"Retail Goods"
        }
    ],
    "sg:phone":"+44 20 8346 3598",
    "sg:postcode":"N3 3JG",
    "sg:province":"Greater London",
    "sg:tags":[
        "butcher"
    ],
    "wof:name":"H Schlagman & Sons Ltd.",
    "wof:placetype":"venue"
},
  "geometry": {"coordinates":[-0.199209,51.592381],"type":"Point"}
}