{
  "type": "Feature",
  "properties": {
    "addr:full":"195 Park Road Loughborough Leicestershire LE11 2HE",
    "addr:housenumber":"195",
    "addr:postcode":"le11 2he",
    "addr:street":"Park Road",
    "iso:country":"GB",
    "sg:address":"195 Park Road",
    "sg:city":"Loughborough",
    "sg:classifiers":[
        {
            "category":"Manufacturing",
            "subcategory":"Pottery",
            "type":"Manufacturing & Wholesale Goods"
        }
    ],
    "sg:phone":"+44 1509 268960",
    "sg:postcode":"LE11 2HE",
    "sg:province":"Leicestershire",
    "wof:name":"Mrs Beetons Pottery",
    "wof:placetype":"venue"
},
  "geometry": {"coordinates":[-1.2071789503,52.7587280273],"type":"Point"}
}