{
  "type": "Feature",
  "properties": {
    "addr:full":"17 Town Street, Thaxted Dunmow Essex CM6 2LD",
    "addr:housenumber":"17",
    "addr:postcode":"cm6 2ld",
    "addr:street":"Town Street",
    "iso:country":"GB",
    "sg:address":"17 Town Street, Thaxted",
    "sg:city":"Dunmow",
    "sg:classifiers":[
        {
            "category":"Restaurant",
            "type":"Food & Drink"
        }
    ],
    "sg:postcode":"CM6 2LD",
    "sg:province":"Essex",
    "wof:name":"Recorders House Restaurant",
    "wof:placetype":"venue"
},
  "geometry": {"coordinates":[0.3439599872,51.953414917],"type":"Point"}
}