{
  "type": "Feature",
  "properties": {
    "iso:country":"GB",
    "sg:address":"Pennine House, 4 Osborne Terrace, Jesmond",
    "sg:city":"Newcastle-upon-tyne",
    "sg:classifiers":[
        {
            "category":"Manufacturing",
            "subcategory":"Lumber",
            "type":"Manufacturing & Wholesale Goods"
        }
    ],
    "sg:phone":"+44 191 281 2153",
    "sg:postcode":"NE2 1NE",
    "sg:province":"Tyne and Wear",
    "sg:tags":[
        "importer",
        "merchants",
        "agent",
        "timber"
    ],
    "wof:name":"Eastern Forest Products Ltd.",
    "wof:placetype":"venue"
},
  "geometry": {"coordinates":[-1.604061,54.982136],"type":"Point"}
}