{
  "type": "Feature",
  "properties": {
    "addr:full":"Bron Trefor Talsarnau Gwynedd LL47 6TA",
    "addr:postcode":"ll47 6ta",
    "iso:country":"GB",
    "sg:address":"Bron Trefor",
    "sg:city":"Talsarnau",
    "sg:classifiers":[
        {
            "category":"Bars & Pubs",
            "type":"Food & Drink"
        }
    ],
    "sg:phone":"+44 1766 770957",
    "sg:postcode":"LL47 6TA",
    "sg:province":"Gwynedd",
    "sg:tags":[
        "pubs",
        "inn"
    ],
    "wof:name":"Terence W & Olive Howard",
    "wof:placetype":"venue"
},
  "geometry": {"coordinates":[-4.0636978149,52.9040184021],"type":"Point"}
}