{
  "type": "Feature",
  "properties": {
    "addr:full":"63 High Street, Lees Oldham Lancashire OL4 3BN",
    "addr:housenumber":"63",
    "addr:postcode":"ol4 3bn",
    "addr:street":"High Street",
    "iso:country":"GB",
    "sg:address":"63 High Street, Lees",
    "sg:city":"Oldham",
    "sg:classifiers":[
        {
            "category":"Shopping",
            "subcategory":"Florist",
            "type":"Retail Goods"
        }
    ],
    "sg:phone":"+44 161 624 2414",
    "sg:postcode":"OL4 3BN",
    "sg:province":"Lancashire",
    "wof:name":"Village Flowers",
    "wof:placetype":"venue"
},
  "geometry": {"coordinates":[-2.073955,53.538151],"type":"Point"}
}