{
  "type": "Feature",
  "properties": {
    "iso:country":"GB",
    "sg:address":"106 Devonshire Street",
    "sg:city":"Sheffield",
    "sg:classifiers":[
        {
            "category":"Personal",
            "subcategory":"Beauty Salon",
            "type":"Services"
        },
        {
            "category":"Personal",
            "subcategory":"Barber",
            "type":"Services"
        }
    ],
    "sg:phone":"+44 114 272 9799",
    "sg:postcode":"S3 7SF",
    "sg:province":"South Yorkshire",
    "sg:tags":[
        "unisex",
        "hairdresser"
    ],
    "wof:name":"Halo's Hair Salon",
    "wof:placetype":"venue"
},
  "geometry": {"coordinates":[-1.477965,53.379555],"type":"Point"}
}