{
  "type": "Feature",
  "properties": {
    "iso:country":"GB",
    "sg:address":"167 West Road",
    "sg:city":"Newcastle-upon-tyne",
    "sg:classifiers":[
        {
            "category":"Personal",
            "subcategory":"Beauty Salon",
            "type":"Services"
        }
    ],
    "sg:phone":"+44 191 226 0530",
    "sg:postcode":"NE15 7NL",
    "sg:province":"Northumberland",
    "sg:tags":[
        "unisex",
        "hairdresser"
    ],
    "wof:name":"Cute & Curly",
    "wof:placetype":"venue"
},
  "geometry": {"coordinates":[-1.670839,54.979118],"type":"Point"}
}