{
  "type": "Feature",
  "properties": {
    "addr:full":"7 Stacey Rd Tonbridge Kent TN10 3AP",
    "addr:housenumber":"7",
    "addr:postcode":"tn10 3ap",
    "addr:street":"Stacey Rd",
    "iso:country":"GB",
    "sg:address":"7 Stacey Rd",
    "sg:city":"Tonbridge",
    "sg:classifiers":[
        {
            "category":"Professional",
            "subcategory":"Management & Consulting",
            "type":"Services"
        }
    ],
    "sg:phone":"+44 1732 352955",
    "sg:postcode":"TN10 3AP",
    "sg:province":"Kent",
    "sg:tags":[
        "fire",
        "consultant",
        "protection"
    ],
    "wof:name":"E J P Fire Protection",
    "wof:placetype":"venue"
},
  "geometry": {"coordinates":[0.262845,51.20509],"type":"Point"}
}