{
  "type": "Feature",
  "properties": {
    "addr:full":"Unit 4 The Courtyard, Darcy Business Park, Llandarcy Neath Neath Port Talbot SA10 6EJ",
    "addr:housenumber":"unit 4",
    "addr:postcode":"sa10 6ej",
    "addr:street":"The Courtyard",
    "iso:country":"GB",
    "sg:address":"Unit 4 The Courtyard, Darcy Business Park, Llandarcy",
    "sg:city":"Neath",
    "sg:classifiers":[
        {
            "category":"Building & Trades",
            "subcategory":"Construction",
            "type":"Services"
        }
    ],
    "sg:phone":"+44 1792 817708",
    "sg:postcode":"SA10 6EJ",
    "sg:province":"Neath Port Talbot",
    "sg:tags":[
        "valve"
    ],
    "wof:name":"Valvetech Services Ltd.",
    "wof:placetype":"venue"
},
  "geometry": {"coordinates":[-3.856599,51.641495],"type":"Point"}
}