{
  "type": "Feature",
  "properties": {
    "addr:full":"314 Long Riding Basildon Essex SS14 1RD",
    "addr:housenumber":"314",
    "addr:postcode":"ss14 1rd",
    "addr:street":"Long Riding",
    "iso:country":"GB",
    "sg:address":"314 Long Riding",
    "sg:city":"Basildon",
    "sg:classifiers":[
        {
            "category":"Professional",
            "subcategory":"Management & Consulting",
            "type":"Services"
        }
    ],
    "sg:phone":"+44 1268 289812",
    "sg:postcode":"SS14 1RD",
    "sg:province":"Essex",
    "sg:tags":[
        "consultant",
        "specialist"
    ],
    "wof:name":"Karen Earnshaw Mobile",
    "wof:placetype":"venue"
},
  "geometry": {"coordinates":[0.4751490057,51.5721969604],"type":"Point"}
}