{
  "type": "Feature",
  "properties": {
    "addr:full":"Newstead Lane, Newstead Stamford Cambridgeshire PE9 4SA",
    "addr:postcode":"pe9 4sa",
    "addr:street":"Newstead Lane",
    "iso:country":"GB",
    "sg:address":"Newstead Lane, Newstead",
    "sg:city":"Stamford",
    "sg:classifiers":[
        {
            "category":"Transit Center",
            "subcategory":"Passenger",
            "type":"Transportation"
        }
    ],
    "sg:phone":"+44 1780 481087",
    "sg:postcode":"PE9 4SA",
    "sg:province":"Cambridgeshire",
    "sg:tags":[
        "boarding",
        "kennel",
        "catteries"
    ],
    "wof:name":"Newstead Cattery",
    "wof:placetype":"venue"
},
  "geometry": {"coordinates":[-0.452771,52.658337],"type":"Point"}
}