{
  "type": "Feature",
  "properties": {
    "addr:full":"Ps21 The New Market Carmarthen Carmarthenshire SA31 1QY",
    "addr:postcode":"sa31 1qy",
    "iso:country":"GB",
    "sg:address":"Ps21 The New Market",
    "sg:city":"Carmarthen",
    "sg:classifiers":[
        {
            "category":"Farming",
            "subcategory":"Livestock Farm",
            "type":"Manufacturing & Wholesale Goods"
        },
        {
            "category":"Shopping",
            "subcategory":"Florist",
            "type":"Retail Goods"
        }
    ],
    "sg:phone":"+44 1267 236831",
    "sg:postcode":"SA31 1QY",
    "sg:province":"Carmarthenshire",
    "sg:tags":[
        "breeder"
    ],
    "wof:name":"R Davies & Sons",
    "wof:placetype":"venue"
},
  "geometry": {"coordinates":[-4.2994041443,51.8602752686],"type":"Point"}
}