{
  "type": "Feature",
  "properties": {
    "addr:full":"Captain St Bolton Lancashire BL6 7PS",
    "addr:postcode":"bl6 7ps",
    "addr:street":"Captain St",
    "iso:country":"GB",
    "sg:address":"Captain St",
    "sg:city":"Bolton",
    "sg:classifiers":[
        {
            "category":"Home & Garden",
            "subcategory":"Furniture",
            "type":"Retail Goods"
        }
    ],
    "sg:postcode":"BL6 7PS",
    "sg:province":"Lancashire",
    "wof:name":"Second Chance",
    "wof:placetype":"venue"
},
  "geometry": {"coordinates":[-2.547347,53.600231],"type":"Point"}
}