{
  "type": "Feature",
  "properties": {
    "addr:full":"1 Clair Rd Haywards Heath East Sussex RH16 3DP",
    "addr:housenumber":"1",
    "addr:postcode":"rh16 3dp",
    "addr:street":"Clair Rd",
    "iso:country":"GB",
    "sg:address":"1 Clair Rd",
    "sg:city":"Haywards Heath",
    "sg:classifiers":[
        {
            "category":"Social Services",
            "subcategory":"Retirement Home",
            "type":"Services"
        }
    ],
    "sg:phone":"+44 1444 410400",
    "sg:postcode":"RH16 3DP",
    "sg:province":"East Sussex",
    "sg:tags":[
        "care"
    ],
    "wof:name":"Primrose Care Ltd",
    "wof:placetype":"venue"
},
  "geometry": {"coordinates":[-0.1036500037,51.0043716431],"type":"Point"}
}