{
  "type": "Feature",
  "properties": {
    "addr:full":"Po Box 232 Plymouth Devon PL2 1YP",
    "addr:housenumber":"po",
    "addr:postcode":"pl2 1yp",
    "addr:street":"Box 232",
    "iso:country":"GB",
    "sg:address":"Po Box 232",
    "sg:city":"Plymouth",
    "sg:classifiers":[
        {
            "category":"Manufacturing",
            "subcategory":"Apparel",
            "type":"Manufacturing & Wholesale Goods"
        }
    ],
    "sg:postcode":"PL2 1YP",
    "sg:province":"Devon",
    "sg:tags":[
        "garment",
        "designer"
    ],
    "wof:name":"Gitta & Co.",
    "wof:placetype":"venue"
},
  "geometry": {"coordinates":[-4.1742191315,50.3826408386],"type":"Point"}
}