{
  "type": "Feature",
  "properties": {
    "addr:full":"8 West Shaw, Oxenhope Keighley North Yorkshire BD22 9QR",
    "addr:housenumber":"8",
    "addr:postcode":"bd22 9qr",
    "addr:street":"West Shaw",
    "iso:country":"GB",
    "sg:address":"8 West Shaw, Oxenhope",
    "sg:city":"Keighley",
    "sg:classifiers":[
        {
            "category":"Autos & Motor Vehicles",
            "subcategory":"Auto Supplies",
            "type":"Retail Goods"
        },
        {
            "category":"Taxi",
            "type":"Transportation"
        },
        {
            "category":"Bus Stop",
            "subcategory":"None",
            "type":"Transportation"
        }
    ],
    "sg:phone":"+44 1535 642913",
    "sg:postcode":"BD22 9QR",
    "sg:province":"North Yorkshire",
    "sg:tags":[
        "mini",
        "hire",
        "eqpt",
        "towing",
        "cab",
        "trailer"
    ],
    "wof:name":"Hodgsons Minibus & Private Hire",
    "wof:placetype":"venue"
},
  "geometry": {"coordinates":[-1.952568,53.811687],"type":"Point"}
}