{
  "type": "Feature",
  "properties": {
    "addr:full":"1 High St High Wycombe Buckinghamshire HP14 3JF",
    "addr:housenumber":"1",
    "addr:postcode":"hp14 3jf",
    "addr:street":"High St",
    "iso:country":"GB",
    "sg:address":"1 High St",
    "sg:city":"High Wycombe",
    "sg:classifiers":[
        {
            "category":"Professional",
            "subcategory":"Engineering",
            "type":"Services"
        }
    ],
    "sg:phone":"+44 1494 882935",
    "sg:postcode":"HP14 3JF",
    "sg:province":"Buckinghamshire",
    "sg:tags":[
        "consulting",
        "engineer"
    ],
    "wof:name":"Stephen Cooke Associates",
    "wof:placetype":"venue"
},
  "geometry": {"coordinates":[-0.8344119787,51.618812561],"type":"Point"}
}