{
  "type": "Feature",
  "properties": {
    "addr:full":"15 Hallcraig Street Airdrie North Lanarkshire ML6 6AH",
    "addr:housenumber":"15",
    "addr:postcode":"ml6 6ah",
    "addr:street":"Hallcraig Street",
    "iso:country":"GB",
    "sg:address":"15 Hallcraig Street",
    "sg:city":"Airdrie",
    "sg:classifiers":[
        {
            "category":"Organizations",
            "subcategory":"Non-profit Organization",
            "type":"Services"
        }
    ],
    "sg:phone":"+44 1236 769258",
    "sg:postcode":"ML6 6AH",
    "sg:province":"North Lanarkshire",
    "sg:tags":[
        "organisation",
        "voluntary",
        "charity"
    ],
    "wof:name":"Ymca",
    "wof:placetype":"venue"
},
  "geometry": {"coordinates":[-3.980314,55.866993],"type":"Point"}
}