{
  "type": "Feature",
  "properties": {
    "addr:full":"294 Mossy Lea Road Wigan Lancashire WN6 9RN",
    "addr:housenumber":"294",
    "addr:postcode":"wn6 9rn",
    "addr:street":"Mossy Lea Road",
    "iso:country":"GB",
    "sg:address":"294 Mossy Lea Road",
    "sg:city":"Wigan",
    "sg:classifiers":[
        {
            "category":"Shopping",
            "type":"Retail Goods"
        }
    ],
    "sg:phone":"+44 1257 473473",
    "sg:postcode":"WN6 9RN",
    "sg:province":"Lancashire",
    "sg:tags":[
        "part",
        "accessory"
    ],
    "wof:name":"Mini Spares Centre",
    "wof:placetype":"venue"
},
  "geometry": {"coordinates":[-2.702383,53.608555],"type":"Point"}
}