{
  "type": "Feature",
  "properties": {
    "addr:full":"11 Manor Powes Stirling Clackmannanshire FK9 5QH",
    "addr:housenumber":"11",
    "addr:postcode":"fk9 5qh",
    "addr:street":"Manor Powes",
    "iso:country":"GB",
    "sg:address":"11 Manor Powes",
    "sg:city":"Stirling",
    "sg:classifiers":[
        {
            "category":"Building & Trades",
            "subcategory":"Plumbing",
            "type":"Services"
        }
    ],
    "sg:postcode":"FK9 5QH",
    "sg:province":"Clackmannanshire",
    "sg:tags":[
        "central",
        "heating"
    ],
    "wof:name":"Aiston,I,",
    "wof:placetype":"venue"
},
  "geometry": {"coordinates":[-3.923759,56.13839],"type":"Point"}
}