{
  "type": "Feature",
  "properties": {
    "iso:country":"GB",
    "sg:address":"167a High St",
    "sg:city":"Elgin",
    "sg:classifiers":[
        {
            "category":"Banks & Credit Unions",
            "subcategory":"Financial Services",
            "type":"Services"
        }
    ],
    "sg:phone":"+44 1343 542121",
    "sg:postcode":"IV30 1DW",
    "sg:province":"Moray",
    "sg:tags":[
        "consultant"
    ],
    "wof:name":"Moray Independant Financial Services",
    "wof:placetype":"venue"
},
  "geometry": {"coordinates":[-3.3171811104,57.6485366821],"type":"Point"}
}