{
  "type": "Feature",
  "properties": {
    "addr:full":"National Agricultural Centre, Stoneleigh Kenilworth Warwickshire CV8 2LZ",
    "addr:postcode":"cv8 2lz",
    "iso:country":"GB",
    "sg:address":"National Agricultural Centre, Stoneleigh",
    "sg:city":"Kenilworth",
    "sg:classifiers":[
        {
            "category":"Professional",
            "subcategory":"Employment Agencies",
            "type":"Services"
        }
    ],
    "sg:postcode":"CV8 2LZ",
    "sg:province":"Warwickshire",
    "sg:tags":[
        "agricultural",
        "advice"
    ],
    "wof:name":"Leaf Linking Environment & Farming",
    "wof:placetype":"venue"
},
  "geometry": {"coordinates":[-1.5794409513,52.3429374695],"type":"Point"}
}