{
  "type": "Feature",
  "properties": {
    "iso:country":"GB",
    "sg:address":"5 Wallingford Road",
    "sg:city":"Manchester",
    "sg:classifiers":[
        {
            "category":"Home & Garden",
            "subcategory":"Hardware",
            "type":"Retail Goods"
        }
    ],
    "sg:postcode":"M41 0QN",
    "sg:province":"Cheshire",
    "sg:tags":[
        "battery"
    ],
    "wof:name":"Industrial Charger Services Ltd.",
    "wof:placetype":"venue"
},
  "geometry": {"coordinates":[-2.342078,53.454712],"type":"Point"}
}