{
  "type": "Feature",
  "properties": {
    "addr:full":"202 Westbourne Pic Rd Notting Hill Greater London W11 1EP",
    "addr:housenumber":"202",
    "addr:postcode":"w11 1ep",
    "addr:street":"Westbourne Pic Rd",
    "iso:country":"GB",
    "sg:address":"202 Westbourne Pic Rd",
    "sg:city":"Notting Hill",
    "sg:classifiers":[
        {
            "category":"Building & Trades",
            "subcategory":"Cleaning & Sanitation",
            "type":"Services"
        }
    ],
    "sg:phone":"+44 20 7229 5322",
    "sg:postcode":"W11 1EP",
    "sg:province":"Greater London",
    "sg:tags":[
        "cleaner",
        "window"
    ],
    "wof:name":"Geraldo Benedito Wnidow Cleaning",
    "wof:placetype":"venue"
},
  "geometry": {"coordinates":[-0.202153,51.517769],"type":"Point"}
}