{
  "type": "Feature",
  "properties": {
    "addr:full":"5a Highgate Kendal Cumbria LA9 4DA",
    "addr:housenumber":"5a",
    "addr:postcode":"la9 4da",
    "addr:street":"Highgate",
    "iso:country":"GB",
    "sg:address":"5a Highgate",
    "sg:city":"Kendal",
    "sg:classifiers":[
        {
            "category":"Travel",
            "subcategory":"Travel Agent",
            "type":"Entertainment"
        }
    ],
    "sg:phone":"+44 1539 733525",
    "sg:postcode":"LA9 4DA",
    "sg:province":"Cumbria",
    "wof:name":"Lunn Poly Ltd.",
    "wof:placetype":"venue"
},
  "geometry": {"coordinates":[-2.747529,54.326309],"type":"Point"}
}