{
  "type": "Feature",
  "properties": {
    "addr:full":"256 London Road, Hadleigh Benfleet Essex SS7 2DE",
    "addr:housenumber":"256",
    "addr:postcode":"ss7 2de",
    "addr:street":"London Road",
    "iso:country":"GB",
    "sg:address":"256 London Road, Hadleigh",
    "sg:city":"Benfleet",
    "sg:classifiers":[
        {
            "category":"Home & Garden",
            "subcategory":"Home Furnishings",
            "type":"Retail Goods"
        }
    ],
    "sg:phone":"+44 1702 557972",
    "sg:postcode":"SS7 2DE",
    "sg:province":"Essex",
    "sg:tags":[
        "beds",
        "bedding",
        "blanket"
    ],
    "wof:name":"Essex Bedding Centre",
    "wof:placetype":"venue"
},
  "geometry": {"coordinates":[0.610845,51.552662],"type":"Point"}
}