{
  "type": "Feature",
  "properties": {
    "addr:full":"159a Warwick Rd Banbury Oxfordshire OX16 2AR",
    "addr:housenumber":"159a",
    "addr:postcode":"ox16 2ar",
    "addr:street":"Warwick Rd",
    "iso:country":"GB",
    "sg:address":"159a Warwick Rd",
    "sg:city":"Banbury",
    "sg:classifiers":[
        {
            "category":"Building & Trades",
            "subcategory":"Cleaning & Sanitation",
            "type":"Services"
        }
    ],
    "sg:postcode":"OX16 2AR",
    "sg:province":"Oxfordshire",
    "sg:tags":[
        "commercial"
    ],
    "wof:name":"Salmons,J,",
    "wof:placetype":"venue"
},
  "geometry": {"coordinates":[-1.3492670059,52.0656700134],"type":"Point"}
}