{
  "type": "Feature",
  "properties": {
    "iso:country":"GB",
    "sg:address":"36 Gertrude Road, West Bridgford",
    "sg:city":"Nottingham",
    "sg:classifiers":[
        {
            "category":"Shopping",
            "subcategory":"Antiques",
            "type":"Retail Goods"
        }
    ],
    "sg:postcode":"NG2 5BY",
    "sg:province":"Nottinghamshire",
    "wof:name":"Piers Keating",
    "wof:placetype":"venue"
},
  "geometry": {"coordinates":[-1.1165590286,52.9389953613],"type":"Point"}
}