{
  "type": "Feature",
  "properties": {
    "addr:full":"Ditherington Road Shrewsbury Shropshire SY1 4BG",
    "addr:postcode":"sy1 4bg",
    "addr:street":"Ditherington Road",
    "iso:country":"GB",
    "sg:address":"Ditherington Road",
    "sg:city":"Shrewsbury",
    "sg:classifiers":[
        {
            "category":"Military Area",
            "subcategory":"Air Force Base",
            "type":"Public Place"
        }
    ],
    "sg:postcode":"SY1 4BG",
    "sg:province":"Shropshire",
    "sg:tags":[
        "taxi",
        "hire",
        "private"
    ],
    "wof:name":"A-Z Cars",
    "wof:placetype":"venue"
},
  "geometry": {"coordinates":[-2.738139,52.724594],"type":"Point"}
}