{
  "type": "Feature",
  "properties": {
    "addr:full":"43 Cwmrhydyceirw Road Swansea Swansea SA6 6LJ",
    "addr:housenumber":"43",
    "addr:postcode":"sa6 6lj",
    "addr:street":"Cwmrhydyceirw Road",
    "iso:country":"GB",
    "sg:address":"43 Cwmrhydyceirw Road",
    "sg:city":"Swansea",
    "sg:classifiers":[
        {
            "category":"Home & Garden",
            "subcategory":"Garden Supply",
            "type":"Retail Goods"
        }
    ],
    "sg:phone":"+44 1792 772602",
    "sg:postcode":"SA6 6LJ",
    "sg:province":"Swansea",
    "sg:tags":[
        "nursery",
        "centre"
    ],
    "wof:name":"Rose Villa Nursery & Garden Centre",
    "wof:placetype":"venue"
},
  "geometry": {"coordinates":[-3.9287669659,51.6763458252],"type":"Point"}
}