{
  "type": "Feature",
  "properties": {
    "addr:full":"38 Station Way Buckhurst Hill Essex IG9 6LN",
    "addr:housenumber":"38",
    "addr:postcode":"ig9 6ln",
    "addr:street":"Station Way",
    "iso:country":"GB",
    "sg:address":"38 Station Way",
    "sg:city":"Buckhurst Hill",
    "sg:classifiers":[
        {
            "category":"Food & Beverages",
            "subcategory":"Groceries & Convenience Stores",
            "type":"Retail Goods"
        }
    ],
    "sg:phone":"+44 20 8504 5201",
    "sg:postcode":"IG9 6LN",
    "sg:province":"Essex",
    "wof:name":"Valley Food & Wine Stores",
    "wof:placetype":"venue"
},
  "geometry": {"coordinates":[0.0444580019,51.6175537109],"type":"Point"}
}