{
  "type": "Feature",
  "properties": {
    "addr:full":"279 Banbury Rd Oxford Oxfordshire OX2 7JF",
    "addr:housenumber":"279",
    "addr:postcode":"ox2 7jf",
    "addr:street":"Banbury Rd",
    "iso:country":"GB",
    "sg:address":"279 Banbury Rd",
    "sg:city":"Oxford",
    "sg:classifiers":[
        {
            "category":"Health Services",
            "subcategory":"Dentist",
            "type":"Services"
        }
    ],
    "sg:phone":"+44 1865 558822",
    "sg:postcode":"OX2 7JF",
    "sg:province":"Oxfordshire",
    "wof:name":"Roz Tritton",
    "wof:placetype":"venue"
},
  "geometry": {"coordinates":[-1.26615,51.780178],"type":"Point"}
}