{
  "type": "Feature",
  "properties": {
    "addr:full":"Penrhiw Fach, Llanpumsaint Carmarthen Carmarthenshire SA33 6LX",
    "addr:postcode":"sa33 6lx",
    "addr:street":"Penrhiw;Llanpumsaint;Carmarthenshire",
    "iso:country":"GB",
    "sg:address":"Penrhiw Fach, Llanpumsaint",
    "sg:city":"Carmarthen",
    "sg:classifiers":[
        {
            "category":"Banks & Credit Unions",
            "subcategory":"Investment Brokerage",
            "type":"Services"
        }
    ],
    "sg:phone":"+44 1267 253668",
    "sg:postcode":"SA33 6LX",
    "sg:province":"Carmarthenshire",
    "sg:tags":[
        "contractor"
    ],
    "wof:name":"Michael Powling",
    "wof:placetype":"venue"
},
  "geometry": {"coordinates":[-4.3013281822,51.9382476807],"type":"Point"}
}