{
  "type": "Feature",
  "properties": {
    "iso:country":"GB",
    "sg:address":"Isombridge Farm",
    "sg:city":"Telford",
    "sg:classifiers":[
        {
            "category":"Farming",
            "subcategory":"Livestock Farm",
            "type":"Manufacturing & Wholesale Goods"
        }
    ],
    "sg:phone":"+44 1952 770256",
    "sg:postcode":"TF6 6NF",
    "sg:province":"Shropshire",
    "sg:tags":[
        "others"
    ],
    "wof:name":"M & M B Evans",
    "wof:placetype":"venue"
},
  "geometry": {"coordinates":[-2.57895,52.720398],"type":"Point"}
}