{
  "type": "Feature",
  "properties": {
    "addr:full":"1-4 College Yard Worcester Worcestershire WR1 2LB",
    "addr:housenumber":"1-4",
    "addr:postcode":"wr1 2lb",
    "addr:street":"College Yard",
    "iso:country":"GB",
    "sg:address":"1-4 College Yard",
    "sg:city":"Worcester",
    "sg:classifiers":[
        {
            "category":"Professional",
            "subcategory":"Accounting & Tax Preparation",
            "type":"Services"
        }
    ],
    "sg:phone":"+44 1905 732100",
    "sg:postcode":"WR1 2LB",
    "sg:province":"Worcestershire",
    "sg:tags":[
        "accountant"
    ],
    "wof:name":"Rabjohns",
    "wof:placetype":"venue"
},
  "geometry": {"coordinates":[-2.220484972,52.1893997192],"type":"Point"}
}