{
  "type": "Feature",
  "properties": {
    "iso:country":"GB",
    "sg:address":"75 Marylebone High St",
    "sg:city":"London",
    "sg:classifiers":[
        {
            "category":"Shopping",
            "subcategory":"News",
            "type":"Retail Goods"
        }
    ],
    "sg:postcode":"W1U 5JW",
    "sg:province":"Greater London",
    "sg:tags":[
        "newsagent"
    ],
    "wof:name":"Beal,Jennifer,",
    "wof:placetype":"venue"
},
  "geometry": {"coordinates":[-0.152162,51.521149],"type":"Point"}
}