{
  "type": "Feature",
  "properties": {
    "addr:full":"The Avenue, Rubery, Rednal Birmingham West Midlands B45 9AP",
    "addr:postcode":"b45 9ap",
    "addr:street":"Avenue Rubery Rednal",
    "iso:country":"GB",
    "sg:address":"The Avenue, Rubery, Rednal",
    "sg:city":"Birmingham",
    "sg:classifiers":[
        {
            "category":"Social Services",
            "type":"Services"
        }
    ],
    "sg:phone":"+44 1656 664321",
    "sg:postcode":"B45 9AP",
    "sg:province":"West Midlands",
    "sg:tags":[
        "disability"
    ],
    "wof:name":"Bencraft Ltd.",
    "wof:placetype":"venue"
},
  "geometry": {"coordinates":[-2.0240991116,52.393901825],"type":"Point"}
}