{
  "type": "Feature",
  "properties": {
    "iso:country":"GB",
    "sg:address":"61-63 Westgate Street",
    "sg:city":"London",
    "sg:classifiers":[
        {
            "category":"Food & Beverages",
            "subcategory":"Supermarket",
            "type":"Retail Goods"
        },
        {
            "category":"Food & Beverages",
            "subcategory":"Groceries & Convenience Stores",
            "type":"Retail Goods"
        }
    ],
    "sg:phone":"+44 20 7249 3379",
    "sg:postcode":"E8 3RL",
    "sg:province":"Greater London",
    "wof:name":"TODAY CONVENIENCE STORE",
    "wof:placetype":"venue"
},
  "geometry": {"coordinates":[-0.060329,51.537415],"type":"Point"}
}