{
  "type": "Feature",
  "properties": {
    "addr:full":"The Galleria, 166a George Lane South Woodford Greater London E18 1AY",
    "addr:housenumber":"166a",
    "addr:postcode":"e18 1ay",
    "addr:street":"George Lane",
    "iso:country":"GB",
    "sg:address":"The Galleria, 166a George Lane",
    "sg:city":"South Woodford",
    "sg:classifiers":[
        {
            "category":"Shopping",
            "subcategory":"Antiques",
            "type":"Retail Goods"
        }
    ],
    "sg:phone":"+44 20 8989 1002",
    "sg:postcode":"E18 1AY",
    "sg:province":"Greater London",
    "wof:name":"Victoria Antiques",
    "wof:placetype":"venue"
},
  "geometry": {"coordinates":[0.024583,51.593914],"type":"Point"}
}