{
  "type": "Feature",
  "properties": {
    "addr:full":"13 Winkfield Clo Luton Bedfordshire LU4 0BY",
    "addr:housenumber":"13",
    "addr:postcode":"lu4 0by",
    "addr:street":"Winkfield Clo",
    "iso:country":"GB",
    "sg:address":"13 Winkfield Clo",
    "sg:city":"Luton",
    "sg:classifiers":[
        {
            "category":"Autos & Motor Vehicles",
            "subcategory":"Motorcycle Sales",
            "type":"Retail Goods"
        }
    ],
    "sg:phone":"+44 1582 595844",
    "sg:postcode":"LU4 0BY",
    "sg:province":"Bedfordshire",
    "sg:tags":[
        "chauffeur",
        "driven",
        "car"
    ],
    "wof:name":"Aarons Wedding Car Hire",
    "wof:placetype":"venue"
},
  "geometry": {"coordinates":[-0.4776650071,51.8900375366],"type":"Point"}
}