{
  "type": "Feature",
  "properties": {
    "addr:full":"1230 Arlington Business Park, Theale Reading Berkshire RG7 4TX",
    "addr:housenumber":"1230",
    "addr:postcode":"rg7 4tx",
    "addr:street":"Arlington Business Park",
    "iso:country":"GB",
    "sg:address":"1230 Arlington Business Park, Theale",
    "sg:city":"Reading",
    "sg:classifiers":[
        {
            "category":"Professional",
            "subcategory":"Printing & Photocopies",
            "type":"Services"
        }
    ],
    "sg:phone":"+44 118 903 2000",
    "sg:postcode":"RG7 4TX",
    "sg:province":"Berkshire",
    "sg:tags":[
        "photocopier",
        "copying",
        "duplicating"
    ],
    "wof:name":"Danka (U K) Plc",
    "wof:placetype":"venue"
},
  "geometry": {"coordinates":[-1.0655,51.43718],"type":"Point"}
}