{
  "type": "Feature",
  "properties": {
    "addr:full":"2b Star Street Ware Hertfordshire SG12 7AA",
    "addr:housenumber":"2b",
    "addr:postcode":"sg12 7aa",
    "addr:street":"Star Street Ware",
    "iso:country":"GB",
    "sg:address":"2b Star Street",
    "sg:city":"Ware",
    "sg:classifiers":[
        {
            "category":"Home & Garden",
            "subcategory":"Furniture",
            "type":"Retail Goods"
        }
    ],
    "sg:phone":"+44 1920 487757",
    "sg:postcode":"SG12 7AA",
    "sg:province":"Hertfordshire",
    "wof:name":"Deans Furnishers Ltd.",
    "wof:placetype":"venue"
},
  "geometry": {"coordinates":[-0.0274679996,51.8097648621],"type":"Point"}
}