{
  "type": "Feature",
  "properties": {
    "addr:full":"Bowers Hall Dunfermline Fife KY11 3HU",
    "addr:postcode":"ky11 3hu",
    "addr:street":"Dunfermline",
    "iso:country":"GB",
    "sg:address":"Bowers Hall",
    "sg:city":"Dunfermline",
    "sg:classifiers":[
        {
            "category":"Military Area",
            "subcategory":"Air Force Base",
            "type":"Public Place"
        }
    ],
    "sg:postcode":"KY11 3HU",
    "sg:province":"Fife",
    "sg:tags":[
        "taxi",
        "hire",
        "private"
    ],
    "wof:name":"Carnegie Radio Taxis",
    "wof:placetype":"venue"
},
  "geometry": {"coordinates":[-3.4808499813,56.0330505371],"type":"Point"}
}