{
  "type": "Feature",
  "properties": {
    "addr:full":"Unity Yard, St Huberts Street, Great Harwood Blackburn Lancashire BB6 7BE",
    "addr:postcode":"bb6 7be",
    "addr:street":"St Huberts Street",
    "iso:country":"GB",
    "sg:address":"Unity Yard, St Huberts Street, Great Harwood",
    "sg:city":"Blackburn",
    "sg:classifiers":[
        {
            "category":"Freight",
            "type":"Transportation"
        }
    ],
    "sg:phone":"+44 1254 883340",
    "sg:postcode":"BB6 7BE",
    "sg:province":"Lancashire",
    "sg:tags":[
        "haulage",
        "road"
    ],
    "wof:name":"R Baron Plant Transport",
    "wof:placetype":"venue"
},
  "geometry": {"coordinates":[-2.4076440334,53.7870140076],"type":"Point"}
}