{
  "type": "Feature",
  "properties": {
    "addr:full":"Unit 5 Pavilion Industrial Estate, Pontnewynydd Pontypool Monmouthshire NP4 6NF",
    "addr:housenumber":"unit 5",
    "addr:postcode":"np4 6nf",
    "addr:street":"Pavilion Industrial",
    "iso:country":"GB",
    "sg:address":"Unit 5 Pavilion Industrial Estate, Pontnewynydd",
    "sg:city":"Pontypool",
    "sg:classifiers":[
        {
            "category":"Professional",
            "subcategory":"Art Services",
            "type":"Services"
        }
    ],
    "sg:phone":"+44 1495 751125",
    "sg:postcode":"NP4 6NF",
    "sg:province":"Monmouthshire",
    "sg:tags":[
        "photographer"
    ],
    "wof:name":"Rod Fawkes Photography",
    "wof:placetype":"venue"
},
  "geometry": {"coordinates":[-3.0504128933,51.7100410461],"type":"Point"}
}