{
  "type": "Feature",
  "properties": {
    "addr:full":"21 Avenue B, 19 Market Square Nottingham Nottinghamshire NG1 1DU",
    "addr:housenumber":"21;19",
    "addr:postcode":"ng1 1du",
    "addr:street":"Avenue B;Market Square",
    "iso:country":"GB",
    "sg:address":"21 Avenue B, 19 Market Square",
    "sg:city":"Nottingham",
    "sg:classifiers":[
        {
            "category":"Professional",
            "subcategory":"Art Services",
            "type":"Services"
        }
    ],
    "sg:postcode":"NG1 1DU",
    "sg:province":"Nottinghamshire",
    "sg:tags":[
        "photographer"
    ],
    "wof:name":"Alec Keeper Photography",
    "wof:placetype":"venue"
},
  "geometry": {"coordinates":[-1.143924,52.949226],"type":"Point"}
}