{
  "type": "Feature",
  "properties": {
    "iso:country":"GB",
    "sg:address":"33 Greyhound Road",
    "sg:city":"London",
    "sg:classifiers":[
        {
            "category":"Sports & Exercise",
            "subcategory":"Bowling",
            "type":"Entertainment"
        }
    ],
    "sg:phone":"+44 20 7386 9060",
    "sg:postcode":"W6 8NH",
    "sg:province":"Greater London",
    "sg:tags":[
        "photography"
    ],
    "wof:name":"Link India",
    "wof:placetype":"venue"
},
  "geometry": {"coordinates":[-0.2187130004,51.4852027893],"type":"Point"}
}