{
  "type": "Feature",
  "properties": {
    "addr:full":"112-116 Bramford Road Ipswich Suffolk IP1 2LL",
    "addr:postcode":"112-116;ip1 2ll",
    "addr:street":"Bramford Road",
    "iso:country":"GB",
    "sg:address":"112-116 Bramford Road",
    "sg:city":"Ipswich",
    "sg:classifiers":[
        {
            "category":"Retail",
            "subcategory":"Auto Rental",
            "type":"Services"
        }
    ],
    "sg:phone":"+44 1473 213344",
    "sg:postcode":"IP1 2LL",
    "sg:province":"Suffolk",
    "sg:tags":[
        "car",
        "vehicle"
    ],
    "sg:website":"http://www.arriva.co.uk",
    "wof:name":"Willhire Group Ltd",
    "wof:placetype":"venue"
},
  "geometry": {"coordinates":[1.138008,52.063175],"type":"Point"}
}