{
  "type": "Feature",
  "properties": {
    "iso:country":"GB",
    "sg:address":"86 Chessington Road",
    "sg:city":"Epsom",
    "sg:classifiers":[
        {
            "category":"Fast Food",
            "type":"Food & Drink"
        }
    ],
    "sg:phone":"+44 20 8393 0888",
    "sg:postcode":"KT19 9UR",
    "sg:province":"Surrey",
    "sg:tags":[
        "away",
        "take"
    ],
    "wof:name":"P J Champion",
    "wof:placetype":"venue"
},
  "geometry": {"coordinates":[-0.260223,51.349754],"type":"Point"}
}