{
  "type": "Feature",
  "properties": {
    "iso:country":"GB",
    "sg:address":"157 Councillor Lane",
    "sg:city":"Cheadle",
    "sg:classifiers":[
        {
            "category":"Food & Beverages",
            "subcategory":"Bakery",
            "type":"Retail Goods"
        }
    ],
    "sg:phone":"+44 161 428 1474",
    "sg:postcode":"SK8 2JE",
    "sg:province":"Cheshire",
    "sg:tags":[
        "baker"
    ],
    "wof:name":"Bread & Butties",
    "wof:placetype":"venue"
},
  "geometry": {"coordinates":[-2.1941559315,53.3910255432],"type":"Point"}
}