{
  "type": "Feature",
  "properties": {
    "addr:full":"4 North Vennel, Bourtreehill South Irvine Irvine East Ayrshire KA11 1NE",
    "addr:housenumber":"4",
    "addr:postcode":"ka11 1ne",
    "addr:street":"North Vennel Bourtreehill South Irvine",
    "iso:country":"GB",
    "sg:address":"4 North Vennel, Bourtreehill South Irvine",
    "sg:city":"Irvine",
    "sg:classifiers":[
        {
            "category":"Banks & Credit Unions",
            "subcategory":"Bank",
            "type":"Services"
        }
    ],
    "sg:phone":"+44 1294 223983",
    "sg:postcode":"KA11 1NE",
    "sg:province":"East Ayrshire",
    "wof:name":"Broomlands & Bourtreehill Credit Union",
    "wof:placetype":"venue"
},
  "geometry": {"coordinates":[-4.633605,55.619896],"type":"Point"}
}