{
  "type": "Feature",
  "properties": {
    "addr:full":"128 London Rd Coalville Leicestershire LE67 3JD",
    "addr:housenumber":"128",
    "addr:postcode":"le67 3jd",
    "addr:street":"London Rd",
    "iso:country":"GB",
    "sg:address":"128 London Rd",
    "sg:city":"Coalville",
    "sg:classifiers":[
        {
            "category":"Retail",
            "subcategory":"Funeral Services",
            "type":"Services"
        }
    ],
    "sg:phone":"+44 1530 836703",
    "sg:postcode":"LE67 3JD",
    "sg:province":"Leicestershire",
    "wof:name":"Coalville Co-Operative Society Ltd",
    "wof:placetype":"venue"
},
  "geometry": {"coordinates":[-1.3681639433,52.7235488892],"type":"Point"}
}