{
  "type": "Feature",
  "properties": {
    "addr:full":"17 Foxcroft Close Burntwood Staffordshire WS7 8ST",
    "addr:housenumber":"17",
    "addr:postcode":"ws7 8st",
    "addr:street":"Foxcroft Close",
    "iso:country":"GB",
    "sg:address":"17 Foxcroft Close",
    "sg:city":"Burntwood",
    "sg:classifiers":[
        {
            "category":"Autos & Motor Vehicles",
            "subcategory":"Motorcycle Sales",
            "type":"Retail Goods"
        }
    ],
    "sg:phone":"+44 1543 677222",
    "sg:postcode":"WS7 8ST",
    "sg:province":"Staffordshire",
    "sg:tags":[
        "chauffeur",
        "driven",
        "car"
    ],
    "wof:name":"W;& Allen C Ravenscroft",
    "wof:placetype":"venue"
},
  "geometry": {"coordinates":[-1.9203560352,52.6701812744],"type":"Point"}
}