{
  "type": "Feature",
  "properties": {
    "iso:country":"GB",
    "sg:address":"9 Granby Road",
    "sg:city":"Buxton",
    "sg:classifiers":[
        {
            "category":"Building & Trades",
            "subcategory":"Construction",
            "type":"Services"
        }
    ],
    "sg:phone":"+44 1298 25085",
    "sg:postcode":"SK17 7TW",
    "sg:province":"Derbyshire",
    "sg:tags":[
        "joiner",
        "carpenter"
    ],
    "wof:name":"J N Cocker Joiners",
    "wof:placetype":"venue"
},
  "geometry": {"coordinates":[-1.902317,53.25761],"type":"Point"}
}