{
  "type": "Feature",
  "properties": {
    "addr:full":"Park Street, Bollington Macclesfield Cheshire SK10 5PQ",
    "addr:postcode":"sk10 5pq",
    "addr:street":"Park Street",
    "iso:country":"GB",
    "sg:address":"Park Street, Bollington",
    "sg:city":"Macclesfield",
    "sg:classifiers":[
        {
            "category":"Building & Trades",
            "subcategory":"Construction",
            "type":"Services"
        }
    ],
    "sg:phone":"+44 1625 573233",
    "sg:postcode":"SK10 5PQ",
    "sg:province":"Cheshire",
    "sg:tags":[
        "builder"
    ],
    "wof:name":"H Cumberbirch & Son Ltd.",
    "wof:placetype":"venue"
},
  "geometry": {"coordinates":[-2.1103689671,53.2933883667],"type":"Point"}
}