{
  "type": "Feature",
  "properties": {
    "addr:full":"Ryeford Rd North, Ryeford Stonehouse Gloucestershire GL10 2LA",
    "addr:postcode":"gl10 2la",
    "addr:street":"Ryeford Rd",
    "iso:country":"GB",
    "sg:address":"Ryeford Rd North, Ryeford",
    "sg:city":"Stonehouse",
    "sg:classifiers":[
        {
            "category":"Retail",
            "subcategory":"Auto Repair",
            "type":"Services"
        }
    ],
    "sg:phone":"+44 1453 791348",
    "sg:postcode":"GL10 2LA",
    "sg:province":"Gloucestershire",
    "sg:tags":[
        "modification",
        "garage"
    ],
    "wof:name":"Scrivin,Paul A,Ltd",
    "wof:placetype":"venue"
},
  "geometry": {"coordinates":[-2.271661,51.740307],"type":"Point"}
}