{
  "type": "Feature",
  "properties": {
    "addr:full":"15-16 Merlin Centre, County Oak Way Crawley West Sussex RH11 7XA",
    "addr:housenumber":"15-16",
    "addr:postcode":"rh11 7xa",
    "addr:street":"Merlin;Way",
    "iso:country":"GB",
    "sg:address":"15-16 Merlin Centre, County Oak Way",
    "sg:city":"Crawley",
    "sg:classifiers":[
        {
            "category":"Professional",
            "type":"Services"
        }
    ],
    "sg:phone":"+44 1293 560666",
    "sg:postcode":"RH11 7XA",
    "sg:province":"West Sussex",
    "sg:tags":[
        "aircraft",
        "maintenance"
    ],
    "wof:name":"Trade Air (U K) Ltd.",
    "wof:placetype":"venue"
},
  "geometry": {"coordinates":[-0.1919099987,51.1360397339],"type":"Point"}
}