{
  "type": "Feature",
  "properties": {
    "iso:country":"GB",
    "sg:address":"3 Crystal Road",
    "sg:city":"Thornton-cleveleys",
    "sg:classifiers":[
        {
            "category":"Building & Trades",
            "subcategory":"Landscaping Services",
            "type":"Services"
        }
    ],
    "sg:phone":"+44 1253 859118",
    "sg:postcode":"FY5 4JL",
    "sg:province":"Lancashire",
    "sg:tags":[
        "landscape",
        "contractor"
    ],
    "wof:name":"Cleveleys Landscapes",
    "wof:placetype":"venue"
},
  "geometry": {"coordinates":[-3.010221,53.887707],"type":"Point"}
}