{
  "type": "Feature",
  "properties": {
    "addr:full":"138 Sydenham Road London Greater London SE26 5JZ",
    "addr:housenumber":"138",
    "addr:postcode":"se26 5jz",
    "addr:street":"Sydenham Road",
    "iso:country":"GB",
    "sg:address":"138 Sydenham Road",
    "sg:city":"London",
    "sg:classifiers":[
        {
            "category":"Manufacturing",
            "subcategory":"Signs",
            "type":"Manufacturing & Wholesale Goods"
        }
    ],
    "sg:phone":"+44 20 8659 7875",
    "sg:postcode":"SE26 5JZ",
    "sg:province":"Greater London",
    "sg:tags":[
        "writer"
    ],
    "wof:name":"Spectrum Signs",
    "wof:placetype":"venue"
},
  "geometry": {"coordinates":[-0.0456909984,51.4255867004],"type":"Point"}
}