{
  "type": "Feature",
  "properties": {
    "addr:full":"Baptist Church, Capel St Folkestone Kent CT18 7LY",
    "addr:postcode":"ct18 7ly",
    "addr:street":"Capel St",
    "iso:country":"GB",
    "sg:address":"Baptist Church, Capel St",
    "sg:city":"Folkestone",
    "sg:classifiers":[
        {
            "category":"Health Services",
            "subcategory":"Doctor",
            "type":"Services"
        }
    ],
    "sg:phone":"+44 1303 220668",
    "sg:postcode":"CT18 7LY",
    "sg:province":"Kent",
    "sg:tags":[
        "practitioners"
    ],
    "wof:name":"Patel, M R",
    "wof:placetype":"venue"
},
  "geometry": {"coordinates":[1.2110500336,51.104839325],"type":"Point"}
}