{
  "type": "Feature",
  "properties": {
    "addr:full":"17 Teawell Close, The Rock Telford Shropshire TF3 5BL",
    "addr:housenumber":"17",
    "addr:postcode":"tf3 5bl",
    "addr:street":"Teawell Close",
    "iso:country":"GB",
    "sg:address":"17 Teawell Close, The Rock",
    "sg:city":"Telford",
    "sg:classifiers":[
        {
            "category":"Professional",
            "subcategory":"Art Services",
            "type":"Services"
        }
    ],
    "sg:phone":"+44 1952 507070",
    "sg:postcode":"TF3 5BL",
    "sg:province":"Shropshire",
    "sg:tags":[
        "photographer"
    ],
    "wof:name":"Images UK",
    "wof:placetype":"venue"
},
  "geometry": {"coordinates":[-2.4714939594,52.6788101196],"type":"Point"}
}