{
  "type": "Feature",
  "properties": {
    "iso:country":"GB",
    "sg:address":"Unit 9-11 Wedgewood Road",
    "sg:city":"Bicester",
    "sg:classifiers":[
        {
            "category":"Manufacturing",
            "subcategory":"Building Materials",
            "type":"Manufacturing & Wholesale Goods"
        }
    ],
    "sg:phone":"+44 1869 248214",
    "sg:postcode":"OX26 4UL",
    "sg:province":"Oxfordshire",
    "sg:tags":[
        "tube",
        "manipulator",
        "bender"
    ],
    "wof:name":"Parallel Motion Consultants",
    "wof:placetype":"venue"
},
  "geometry": {"coordinates":[-1.138399,51.904392],"type":"Point"}
}