{
  "type": "Feature",
  "properties": {
    "iso:country":"GB",
    "sg:address":"25 Victoria St, Irthlingborough",
    "sg:city":"Wellingborough",
    "sg:classifiers":[
        {
            "category":"Autos & Motor Vehicles",
            "subcategory":"Motorcycle Sales",
            "type":"Retail Goods"
        }
    ],
    "sg:phone":"+44 1933 652155",
    "sg:postcode":"NN9 5RG",
    "sg:province":"Northamptonshire",
    "wof:name":"Northants Classic Bike Centre",
    "wof:placetype":"venue"
},
  "geometry": {"coordinates":[-0.6176990271,52.3247718811],"type":"Point"}
}