{
  "type": "Feature",
  "properties": {
    "iso:country":"GB",
    "sg:address":"25 Queen Street",
    "sg:city":"Bridlington",
    "sg:classifiers":[
        {
            "category":"Restaurant",
            "type":"Food & Drink"
        }
    ],
    "sg:phone":"+44 1262 671533",
    "sg:postcode":"YO15 2SN",
    "sg:province":"East Riding of Yorkshire",
    "sg:tags":[
        "seafood",
        "-"
    ],
    "wof:name":"Baynham's Fish Restaurant",
    "wof:placetype":"venue"
},
  "geometry": {"coordinates":[-0.1907780021,54.0817070007],"type":"Point"}
}