{
  "type": "Feature",
  "properties": {
    "addr:full":"Unit 5 Strangeways Cash And Carry Centre, 153 Great Ducie St Manchester Greater Manchester M3 1FB",
    "addr:housenumber":"unit 5;153",
    "addr:postcode":"m3 1fb",
    "addr:street":"Great Ducie St",
    "iso:country":"GB",
    "sg:address":"Unit 5 Strangeways Cash And Carry Centre, 153 Great Ducie St",
    "sg:city":"Manchester",
    "sg:classifiers":[
        {
            "category":"Home & Garden",
            "subcategory":"Home Furnishings",
            "type":"Retail Goods"
        }
    ],
    "sg:phone":"+44 161 819 5300",
    "sg:postcode":"M3 1FB",
    "sg:province":"Greater Manchester",
    "sg:tags":[
        "furnishers",
        "planner",
        "kitchen"
    ],
    "wof:name":"Kitchen Factory Clearance",
    "wof:placetype":"venue"
},
  "geometry": {"coordinates":[-2.248809,53.479622],"type":"Point"}
}