{
  "type": "Feature",
  "properties": {
    "addr:full":"St Lukes Church Hall, Glasshouse La Exeter Devon EX2 7BT",
    "addr:postcode":"ex2 7bt",
    "addr:street":"Glasshouse La Exeter",
    "iso:country":"GB",
    "sg:address":"St Lukes Church Hall, Glasshouse La",
    "sg:city":"Exeter",
    "sg:classifiers":[
        {
            "category":"Health Services",
            "subcategory":"Clinic",
            "type":"Services"
        }
    ],
    "sg:phone":"+44 1392 873500",
    "sg:postcode":"EX2 7BT",
    "sg:province":"Devon",
    "sg:tags":[
        "nh"
    ],
    "wof:name":"Glasshouse Medical Centre",
    "wof:placetype":"venue"
},
  "geometry": {"coordinates":[-3.4909698963,50.6961784363],"type":"Point"}
}