{
  "type": "Feature",
  "properties": {
    "addr:full":"Unit 9, Hertford Street Industrial Estate, Hertford Street Ashton-under-lyne Greater Manchester OL7 0TB",
    "addr:housenumber":"unit 9;estate",
    "addr:postcode":"ol7 0tb",
    "addr:street":"Hertford Street Industrial;Hertford Street",
    "iso:country":"GB",
    "sg:address":"Unit 9, Hertford Street Industrial Estate, Hertford Street",
    "sg:city":"Ashton-under-lyne",
    "sg:classifiers":[
        {
            "category":"Professional",
            "subcategory":"Engineering",
            "type":"Services"
        }
    ],
    "sg:postcode":"OL7 0TB",
    "sg:province":"Greater Manchester",
    "sg:tags":[
        "precision",
        "engineer"
    ],
    "wof:name":"A P C Tools",
    "wof:placetype":"venue"
},
  "geometry": {"coordinates":[-2.1030840874,53.4816741943],"type":"Point"}
}