{
  "type": "Feature",
  "properties": {
    "addr:full":"Unit 32 Glasgow South Lanarkshire G72 7TS",
    "addr:housenumber":"unit 32",
    "addr:postcode":"g72 7ts",
    "iso:country":"GB",
    "sg:address":"Unit 32",
    "sg:city":"Glasgow",
    "sg:classifiers":[
        {
            "category":"Autos & Motor Vehicles",
            "subcategory":"Automobile Sales",
            "type":"Retail Goods"
        }
    ],
    "sg:phone":"+44 141 613 3007",
    "sg:postcode":"G72 7TS",
    "sg:province":"South Lanarkshire",
    "sg:tags":[
        "car"
    ],
    "wof:name":"Richmond Park Car Sales",
    "wof:placetype":"venue"
},
  "geometry": {"coordinates":[-4.19499,55.82785],"type":"Point"}
}