{
  "type": "Feature",
  "properties": {
    "iso:country":"GB",
    "sg:address":"46 Station Road, Addlestone",
    "sg:city":"Weybridge",
    "sg:classifiers":[
        {
            "category":"Retail",
            "subcategory":"Photofinishing",
            "type":"Services"
        }
    ],
    "sg:phone":"+44 1932 820808",
    "sg:postcode":"KT15 2AL",
    "sg:province":"Surrey",
    "sg:tags":[
        "photographic",
        "processor"
    ],
    "wof:name":"1 Stop Photo Shop",
    "wof:placetype":"venue"
},
  "geometry": {"coordinates":[-0.491459,51.370975],"type":"Point"}
}