{
  "type": "Feature",
  "properties": {
    "iso:country":"GB",
    "sg:address":"Lombard Centre, Link Road, Huyton",
    "sg:city":"Liverpool",
    "sg:classifiers":[
        {
            "category":"Organizations",
            "subcategory":"Labor Organization",
            "type":"Services"
        },
        {
            "category":"Professional",
            "subcategory":"Business Services",
            "type":"Services"
        }
    ],
    "sg:phone":"+44 151 449 3535",
    "sg:postcode":"L36 6AP",
    "sg:province":"Merseyside",
    "sg:tags":[
        "import",
        "export",
        "agent"
    ],
    "wof:name":"Lombard Shipping & Forwarding Ltd.",
    "wof:placetype":"venue"
},
  "geometry": {"coordinates":[-2.82051,53.405918],"type":"Point"}
}