{
  "type": "Feature",
  "properties": {
    "addr:full":"17 Oswald Road Scunthorpe Lincolnshire DN15 7PU",
    "addr:housenumber":"17",
    "addr:postcode":"dn15 7pu",
    "addr:street":"Oswald Road",
    "iso:country":"GB",
    "sg:address":"17 Oswald Road",
    "sg:city":"Scunthorpe",
    "sg:classifiers":[
        {
            "category":"Real Estate",
            "subcategory":"Real Estate Agent",
            "type":"Services"
        }
    ],
    "sg:phone":"+44 1724 864411",
    "sg:postcode":"DN15 7PU",
    "sg:province":"Lincolnshire",
    "wof:name":"REVESBY COURT MANAGEMENT LTD",
    "wof:placetype":"venue"
},
  "geometry": {"coordinates":[-0.654304,53.590523],"type":"Point"}
}