{
  "type": "Feature",
  "properties": {
    "iso:country":"GB",
    "sg:address":"31 Cranley Road",
    "sg:city":"Guildford",
    "sg:classifiers":[
        {
            "category":"Professional",
            "subcategory":"Management & Consulting",
            "type":"Services"
        }
    ],
    "sg:postcode":"GU1 2JE",
    "sg:province":"Surrey",
    "sg:tags":[
        "consultant",
        "business"
    ],
    "wof:name":"Sharrah Associates",
    "wof:placetype":"venue"
},
  "geometry": {"coordinates":[-0.554547,51.242912],"type":"Point"}
}