{
  "type": "Feature",
  "properties": {
    "addr:full":"43 Chaucer Road Wellingborough Northamptonshire NN8 3NL",
    "addr:housenumber":"43",
    "addr:postcode":"nn8 3nl",
    "addr:street":"Chaucer Road",
    "iso:country":"GB",
    "sg:address":"43 Chaucer Road",
    "sg:city":"Wellingborough",
    "sg:classifiers":[
        {
            "category":"Building & Trades",
            "subcategory":"Construction",
            "type":"Services"
        }
    ],
    "sg:phone":"+44 1933 677796",
    "sg:postcode":"NN8 3NL",
    "sg:province":"Northamptonshire",
    "sg:tags":[
        "builder"
    ],
    "wof:name":"Williams & Miles",
    "wof:placetype":"venue"
},
  "geometry": {"coordinates":[-0.7189030051,52.2994728088],"type":"Point"}
}