{
  "type": "Feature",
  "properties": {
    "iso:country":"GB",
    "sg:address":"119 Heanor Road, Smalley",
    "sg:city":"Ilkeston",
    "sg:classifiers":[
        {
            "category":"Farming",
            "subcategory":"Livestock Farm",
            "type":"Manufacturing & Wholesale Goods"
        }
    ],
    "sg:phone":"+44 1773 711540",
    "sg:postcode":"DE7 6DY",
    "sg:province":"Derbyshire",
    "sg:tags":[
        "others"
    ],
    "wof:name":"D A H & S H Archer",
    "wof:placetype":"venue"
},
  "geometry": {"coordinates":[-1.379867,53.007088],"type":"Point"}
}