{
  "type": "Feature",
  "properties": {
    "addr:full":"Whitstone Depot, Whitstone Holsworthy Cornwall EX22 6TU",
    "addr:postcode":"ex22 6tu",
    "addr:street":"Whitstone",
    "iso:country":"GB",
    "sg:address":"Whitstone Depot, Whitstone",
    "sg:city":"Holsworthy",
    "sg:classifiers":[
        {
            "category":"Shopping",
            "type":"Retail Goods"
        }
    ],
    "sg:phone":"+44 1288 341540",
    "sg:postcode":"EX22 6TU",
    "sg:province":"Cornwall",
    "sg:tags":[
        "merchant"
    ],
    "wof:name":"D I Bridgman & Sons Ltd.",
    "wof:placetype":"venue"
},
  "geometry": {"coordinates":[-4.3527340889,50.8100128174],"type":"Point"}
}