{
  "type": "Feature",
  "properties": {
    "iso:country":"GB",
    "sg:address":"System House",
    "sg:city":"London",
    "sg:classifiers":[
        {
            "category":"Professional",
            "type":"Services"
        }
    ],
    "sg:phone":"+44 20 8534 9955",
    "sg:postcode":"E15 4LT",
    "sg:province":"Greater London",
    "sg:tags":[
        "exhibition"
    ],
    "wof:name":"Corporate Crew Co",
    "wof:placetype":"venue"
},
  "geometry": {"coordinates":[0.003444,51.540291],"type":"Point"}
}