{
  "type": "Feature",
  "properties": {
    "addr:full":"Eastgate House, Moreton Rd, Longborough Moreton In Marsh Gloucestershire GL56 0QJ",
    "addr:postcode":"gl56 0qj",
    "addr:street":"Eastgate;Moreton Rd",
    "iso:country":"GB",
    "sg:address":"Eastgate House, Moreton Rd, Longborough",
    "sg:city":"Moreton In Marsh",
    "sg:classifiers":[
        {
            "category":"Manufacturing",
            "subcategory":"Textiles",
            "type":"Manufacturing & Wholesale Goods"
        }
    ],
    "sg:phone":"+44 1451 830700",
    "sg:postcode":"GL56 0QJ",
    "sg:province":"Gloucestershire",
    "sg:tags":[
        "printer"
    ],
    "wof:name":"PRINT PRESENTATION",
    "wof:placetype":"venue"
},
  "geometry": {"coordinates":[-1.703281,51.989727],"type":"Point"}
}