{
  "type": "Feature",
  "properties": {
    "iso:country":"GB",
    "sg:address":"6a St Mary's Street",
    "sg:city":"Newport",
    "sg:classifiers":[
        {
            "category":"Deli",
            "type":"Food & Drink"
        }
    ],
    "sg:phone":"+44 1952 272163",
    "sg:postcode":"TF10 7AB",
    "sg:province":"Shropshire",
    "sg:tags":[
        "delivery",
        "sandwich"
    ],
    "wof:name":"Laurel & Hardy",
    "wof:placetype":"venue"
},
  "geometry": {"coordinates":[-2.37856,52.769669],"type":"Point"}
}