{
  "type": "Feature",
  "properties": {
    "addr:full":"88 King's Tamerton Road, St Budeaux Plymouth Devon PL5 2BW",
    "addr:housenumber":"88",
    "addr:postcode":"pl5 2bw",
    "addr:street":"King'S Tamerton Road",
    "iso:country":"GB",
    "sg:address":"88 King's Tamerton Road, St Budeaux",
    "sg:city":"Plymouth",
    "sg:classifiers":[
        {
            "category":"Bus Charters",
            "type":"Transportation"
        }
    ],
    "sg:phone":"+44 1752 369000",
    "sg:postcode":"PL5 2BW",
    "sg:province":"Devon",
    "sg:tags":[
        "hire",
        "coach"
    ],
    "wof:name":"Ray's Coaches",
    "wof:placetype":"venue"
},
  "geometry": {"coordinates":[-4.17301,50.405861],"type":"Point"}
}