{
  "type": "Feature",
  "properties": {
    "addr:full":"21 Western Road Ivybridge Devon PL21 9AN",
    "addr:housenumber":"21",
    "addr:postcode":"pl21 9an",
    "addr:street":"Western Road",
    "iso:country":"GB",
    "sg:address":"21 Western Road",
    "sg:city":"Ivybridge",
    "sg:classifiers":[
        {
            "category":"Recreation",
            "subcategory":"Arcade",
            "type":"Entertainment"
        }
    ],
    "sg:phone":"+44 1752 698220",
    "sg:postcode":"PL21 9AN",
    "sg:province":"Devon",
    "sg:tags":[
        "machine",
        "amusement"
    ],
    "wof:name":"Leisure Engineering",
    "wof:placetype":"venue"
},
  "geometry": {"coordinates":[-3.9242610931,50.3879013062],"type":"Point"}
}