{
  "type": "Feature",
  "properties": {
    "addr:full":"40 Portsmouth Rd Southampton Hampshire SO19 9AD",
    "addr:housenumber":"40",
    "addr:postcode":"so19 9ad",
    "addr:street":"Portsmouth Rd",
    "iso:country":"GB",
    "sg:address":"40 Portsmouth Rd",
    "sg:city":"Southampton",
    "sg:classifiers":[
        {
            "category":"Shopping",
            "subcategory":"Computers & Home Electronics",
            "type":"Retail Goods"
        }
    ],
    "sg:phone":"+44 23 8042 2905",
    "sg:postcode":"SO19 9AD",
    "sg:province":"Hampshire",
    "wof:name":"Future Computer Services",
    "wof:placetype":"venue"
},
  "geometry": {"coordinates":[-1.376883,50.897816],"type":"Point"}
}