{
  "type": "Feature",
  "properties": {
    "iso:country":"GB",
    "sg:address":"The Mill Trad Est, Peacock Cross, Burnbank Rd",
    "sg:city":"Hamilton",
    "sg:classifiers":[
        {
            "category":"Professional",
            "subcategory":"Employment Agencies",
            "type":"Services"
        }
    ],
    "sg:postcode":"ML3 9AY",
    "sg:province":"South Lanarkshire",
    "sg:tags":[
        "consultant"
    ],
    "wof:name":"Comtech Recruitment Ltd",
    "wof:placetype":"venue"
},
  "geometry": {"coordinates":[-4.0528907776,55.7773208618],"type":"Point"}
}