{
  "type": "Feature",
  "properties": {
    "addr:full":"Unit 2 Hawkshead Road, Croft Business Park Wirral Cheshire CH62 3RJ",
    "addr:housenumber":"unit 2",
    "addr:postcode":"ch62 3rj",
    "addr:street":"Hawkshead Road Croft Business Park",
    "iso:country":"GB",
    "sg:address":"Unit 2 Hawkshead Road, Croft Business Park",
    "sg:city":"Wirral",
    "sg:classifiers":[
        {
            "category":"Shopping",
            "subcategory":"Stationery & Office Supplies",
            "type":"Retail Goods"
        }
    ],
    "sg:phone":"+44 151 346 1083",
    "sg:postcode":"CH62 3RJ",
    "sg:province":"Cheshire",
    "sg:tags":[
        "printers'"
    ],
    "wof:name":"Boice Cascade",
    "wof:placetype":"venue"
},
  "geometry": {"coordinates":[-2.9706931114,53.3351020813],"type":"Point"}
}