{
  "type": "Feature",
  "properties": {
    "addr:full":"28 Ellacombe Road, Longwell Grn Bristol Gloucestershire BS30 9BA",
    "addr:housenumber":"28",
    "addr:postcode":"bs30 9ba",
    "addr:street":"Ellacombe Road Longwell Grn",
    "iso:country":"GB",
    "sg:address":"28 Ellacombe Road, Longwell Grn",
    "sg:city":"Bristol",
    "sg:classifiers":[
        {
            "category":"Professional",
            "subcategory":"Engineering",
            "type":"Services"
        }
    ],
    "sg:phone":"+44 117 907 0060",
    "sg:postcode":"BS30 9BA",
    "sg:province":"Gloucestershire",
    "sg:tags":[
        "contractor",
        "electrical",
        "engineer"
    ],
    "wof:name":"Thruput Direct Ltd.",
    "wof:placetype":"venue"
},
  "geometry": {"coordinates":[-2.494902,51.436344],"type":"Point"}
}