{
  "type": "Feature",
  "properties": {
    "iso:country":"GB",
    "sg:address":"133-135 The Broadway",
    "sg:city":"Southall",
    "sg:classifiers":[
        {
            "category":"Wholesale",
            "subcategory":"Non-durable Goods",
            "type":"Manufacturing & Wholesale Goods"
        },
        {
            "category":"Food & Beverages",
            "subcategory":"Supermarket",
            "type":"Retail Goods"
        }
    ],
    "sg:phone":"+44 20 8574 1647",
    "sg:postcode":"UB1 1LW",
    "sg:province":"Greater London",
    "sg:tags":[
        "carry",
        "cash"
    ],
    "wof:name":"Dokal & Sons",
    "wof:placetype":"venue"
},
  "geometry": {"coordinates":[-0.390344,51.51318],"type":"Point"}
}