{
  "type": "Feature",
  "properties": {
    "iso:country":"GB",
    "sg:address":"124 Berryknowes Rd",
    "sg:city":"Glasgow",
    "sg:classifiers":[
        {
            "category":"Organizations",
            "subcategory":"Religious Organization",
            "type":"Services"
        }
    ],
    "sg:phone":"+44 141 883 6139",
    "sg:postcode":"G52 2TT",
    "sg:province":"Glasgow City",
    "sg:tags":[
        "organisation"
    ],
    "wof:name":"Comboni Sisters",
    "wof:placetype":"venue"
},
  "geometry": {"coordinates":[-4.3429198265,55.8486595154],"type":"Point"}
}