{
  "type": "Feature",
  "properties": {
    "addr:full":"The Green Man Inn, Fownhope Hereford Herefordshire HR1 4PE",
    "addr:housenumber":"fownhope",
    "addr:postcode":"hr1 4pe",
    "iso:country":"GB",
    "sg:address":"The Green Man Inn, Fownhope",
    "sg:city":"Hereford",
    "sg:classifiers":[
        {
            "category":"Travel",
            "subcategory":"Hotels & Motels",
            "type":"Entertainment"
        }
    ],
    "sg:postcode":"HR1 4PE",
    "sg:province":"Herefordshire",
    "wof:name":"The Green Man Inn Ltd.",
    "wof:placetype":"venue"
},
  "geometry": {"coordinates":[-2.6153929234,52.007270813],"type":"Point"}
}