{
  "type": "Feature",
  "properties": {
    "addr:full":"Hill Farm, Barnhorn Road Bexhill-on-sea East Sussex TN39 4QR",
    "addr:postcode":"tn39 4qr",
    "addr:street":"Hill;Barnhorn Road",
    "iso:country":"GB",
    "sg:address":"Hill Farm, Barnhorn Road",
    "sg:city":"Bexhill-on-sea",
    "sg:classifiers":[
        {
            "category":"Farming",
            "subcategory":"Farm",
            "type":"Manufacturing & Wholesale Goods"
        }
    ],
    "sg:phone":"+44 1424 844132",
    "sg:postcode":"TN39 4QR",
    "sg:province":"East Sussex",
    "sg:tags":[
        "mixed",
        "crop"
    ],
    "wof:name":"H R Morris & Partners",
    "wof:placetype":"venue"
},
  "geometry": {"coordinates":[0.40127,50.844559],"type":"Point"}
}