{
  "type": "Feature",
  "properties": {
    "addr:full":"16 Magdalene Street Glastonbury Somerset BA6 9EH",
    "addr:housenumber":"16",
    "addr:postcode":"ba6 9eh",
    "addr:street":"Magdalene Street",
    "iso:country":"GB",
    "sg:address":"16 Magdalene Street",
    "sg:city":"Glastonbury",
    "sg:classifiers":[
        {
            "category":"Cafe",
            "type":"Food & Drink"
        }
    ],
    "sg:phone":"+44 1458 832852",
    "sg:postcode":"BA6 9EH",
    "sg:province":"Somerset",
    "sg:tags":[
        "tea",
        "snack",
        "bar",
        "room"
    ],
    "wof:name":"Abbey Tea Rooms & Liscensed Restaurant",
    "wof:placetype":"venue"
},
  "geometry": {"coordinates":[-2.717868,51.145729],"type":"Point"}
}