{
  "type": "Feature",
  "properties": {
    "addr:full":"Norfolk House, 57-59 Charles St Cardiff Cardiff CF10 2GD",
    "addr:housenumber":"57-59",
    "addr:postcode":"cf10 2gd",
    "addr:street":"Charles St",
    "iso:country":"GB",
    "sg:address":"Norfolk House, 57-59 Charles St",
    "sg:city":"Cardiff",
    "sg:classifiers":[
        {
            "category":"Communications",
            "type":"Services"
        }
    ],
    "sg:phone":"+44 29 2022 3337",
    "sg:postcode":"CF10 2GD",
    "sg:province":"Cardiff",
    "sg:tags":[
        "audio-visual"
    ],
    "wof:name":"Zenana",
    "wof:placetype":"venue"
},
  "geometry": {"coordinates":[-3.174589,51.482109],"type":"Point"}
}