{
  "type": "Feature",
  "properties": {
    "addr:full":"1 Stroud Close Wimborne Dorset BH21 2NX",
    "addr:housenumber":"1",
    "addr:postcode":"bh21 2nx",
    "addr:street":"Stroud Close",
    "iso:country":"GB",
    "sg:address":"1 Stroud Close",
    "sg:city":"Wimborne",
    "sg:classifiers":[
        {
            "category":"Home & Garden",
            "subcategory":"Home Furnishings",
            "type":"Retail Goods"
        }
    ],
    "sg:phone":"+44 1202 887065",
    "sg:postcode":"BH21 2NX",
    "sg:province":"Dorset",
    "sg:tags":[
        "blind",
        "curtain",
        "fitting"
    ],
    "wof:name":"Brenda Field Interior Designs",
    "wof:placetype":"venue"
},
  "geometry": {"coordinates":[-1.954991,50.808277],"type":"Point"}
}