{
  "type": "Feature",
  "properties": {
    "addr:full":"138-140 Old Road Clacton-on-sea Essex CO15 3AZ",
    "addr:housenumber":"138-140",
    "addr:postcode":"co15 3az",
    "addr:street":"Old Road",
    "iso:country":"GB",
    "sg:address":"138-140 Old Road",
    "sg:city":"Clacton-on-sea",
    "sg:classifiers":[
        {
            "category":"Shopping",
            "subcategory":"News",
            "type":"Retail Goods"
        }
    ],
    "sg:postcode":"CO15 3AZ",
    "sg:province":"Essex",
    "sg:tags":[
        "newsagent"
    ],
    "wof:name":"Ferguson K Clark",
    "wof:placetype":"venue"
},
  "geometry": {"coordinates":[1.1483919621,51.7942390442],"type":"Point"}
}