{
  "type": "Feature",
  "properties": {
    "addr:full":"3 High Street Woodstock Oxfordshire OX20 1TE",
    "addr:housenumber":"3",
    "addr:postcode":"ox20 1te",
    "addr:street":"High Street",
    "iso:country":"GB",
    "sg:address":"3 High Street",
    "sg:city":"Woodstock",
    "sg:classifiers":[
        {
            "category":"Shopping",
            "subcategory":"Clothing, Apparel, & Fashions",
            "type":"Retail Goods"
        }
    ],
    "sg:phone":"+44 1993 813661",
    "sg:postcode":"OX20 1TE",
    "sg:province":"Oxfordshire",
    "sg:tags":[
        "shop"
    ],
    "wof:name":"Sacs",
    "wof:placetype":"venue"
},
  "geometry": {"coordinates":[-1.3559629917,51.8475494385],"type":"Point"}
}