{
  "type": "Feature",
  "properties": {
    "iso:country":"GB",
    "sg:address":"54 Load Street",
    "sg:city":"Bewdley",
    "sg:classifiers":[
        {
            "category":"Shopping",
            "subcategory":"Clothing, Apparel, & Fashions",
            "type":"Retail Goods"
        },
        {
            "category":"Home & Garden",
            "subcategory":"Building Materials",
            "type":"Retail Goods"
        }
    ],
    "sg:phone":"+44 1299 404825",
    "sg:postcode":"DY12 2AP",
    "sg:province":"Shropshire",
    "sg:tags":[
        "shop",
        "polythene",
        "plastic"
    ],
    "wof:name":"B & B Wholesale",
    "wof:placetype":"venue"
},
  "geometry": {"coordinates":[-2.3160610199,52.3756942749],"type":"Point"}
}