{
  "type": "Feature",
  "properties": {
    "iso:country":"GB",
    "sg:address":"59 Belmont Rd",
    "sg:city":"Uxbridge",
    "sg:classifiers":[
        {
            "category":"Personal",
            "subcategory":"Beauty Salon",
            "type":"Services"
        }
    ],
    "sg:phone":"+44 1895 233616",
    "sg:postcode":"UB8 1QT",
    "sg:province":"Buckinghamshire",
    "sg:tags":[
        "unisex",
        "hairdresser"
    ],
    "wof:name":"Studio Hair & Beauty The",
    "wof:placetype":"venue"
},
  "geometry": {"coordinates":[-0.477955,51.548321],"type":"Point"}
}