{
  "type": "Feature",
  "properties": {
    "iso:country":"GB",
    "sg:address":"I C G House, Station Approach",
    "sg:city":"Greenford",
    "sg:classifiers":[
        {
            "category":"Home & Garden",
            "subcategory":"Building Materials",
            "type":"Retail Goods"
        }
    ],
    "sg:phone":"+44 20 8813 1252",
    "sg:postcode":"UB6 0AL",
    "sg:province":"Greater London",
    "sg:tags":[
        "access",
        "equipment"
    ],
    "wof:name":"Precision Abseiling Ltd.",
    "wof:placetype":"venue"
},
  "geometry": {"coordinates":[-0.349049,51.543697],"type":"Point"}
}