{
  "type": "Feature",
  "properties": {
    "iso:country":"GB",
    "sg:address":"25 West St",
    "sg:city":"Wareham",
    "sg:classifiers":[
        {
            "category":"Health Services",
            "subcategory":"Optometrist",
            "type":"Services"
        }
    ],
    "sg:phone":"+44 1929 553928",
    "sg:postcode":"BH20 4JS",
    "sg:province":"Dorset",
    "sg:tags":[
        "optician"
    ],
    "wof:name":"Shayler Opticians & Colour Consultants",
    "wof:placetype":"venue"
},
  "geometry": {"coordinates":[-2.111213,50.685486],"type":"Point"}
}