{
  "type": "Feature",
  "properties": {
    "addr:full":"63 Coram Street London Greater London WC1N 1HB",
    "addr:housenumber":"63",
    "addr:postcode":"wc1n 1hb",
    "addr:street":"Coram Street",
    "iso:country":"GB",
    "sg:address":"63 Coram Street",
    "sg:city":"London",
    "sg:classifiers":[
        {
            "category":"Professional",
            "subcategory":"Printing & Photocopies",
            "type":"Services"
        }
    ],
    "sg:phone":"+44 20 7833 3005",
    "sg:postcode":"WC1N 1HB",
    "sg:province":"Greater London",
    "sg:tags":[
        "printer"
    ],
    "wof:name":"Prontaprint",
    "wof:placetype":"venue"
},
  "geometry": {"coordinates":[-0.126786,51.52401],"type":"Point"}
}