{
  "type": "Feature",
  "properties": {
    "addr:full":"53 Broomfield Rd Beckenham Kent BR3 3QB",
    "addr:housenumber":"53",
    "addr:postcode":"br3 3qb",
    "addr:street":"Broomfield Rd",
    "iso:country":"GB",
    "sg:address":"53 Broomfield Rd",
    "sg:city":"Beckenham",
    "sg:classifiers":[
        {
            "category":"Building & Trades",
            "subcategory":"Landscaping Services",
            "type":"Services"
        }
    ],
    "sg:phone":"+44 20 8650 3412",
    "sg:postcode":"BR3 3QB",
    "sg:province":"Kent",
    "sg:tags":[
        "gardening"
    ],
    "wof:name":"Grant Clark & Son",
    "wof:placetype":"venue"
},
  "geometry": {"coordinates":[-0.038704,51.399643],"type":"Point"}
}