{
  "type": "Feature",
  "properties": {
    "iso:country":"GB",
    "sg:address":"70 Merton Rd",
    "sg:city":"Bootle",
    "sg:classifiers":[
        {
            "category":"Place Of Worship",
            "type":"Public Place"
        }
    ],
    "sg:phone":"+44 151 922 1315",
    "sg:postcode":"L20 7AT",
    "sg:province":"Merseyside",
    "wof:name":"St. Mary with St. Pauls Church",
    "wof:placetype":"venue"
},
  "geometry": {"coordinates":[-2.994214,53.448601],"type":"Point"}
}