{
  "type": "Feature",
  "properties": {
    "iso:country":"GB",
    "sg:address":"19 St. Helens Avenue",
    "sg:city":"Lincoln",
    "sg:classifiers":[
        {
            "category":"Building & Trades",
            "subcategory":"Construction",
            "type":"Services"
        }
    ],
    "sg:phone":"+44 1522 878629",
    "sg:postcode":"LN6 7RA",
    "sg:province":"Lincolnshire",
    "sg:tags":[
        "joiner",
        "carpenter"
    ],
    "wof:name":"Chris Stow Joinery",
    "wof:placetype":"venue"
},
  "geometry": {"coordinates":[-0.566791,53.212025],"type":"Point"}
}