{
  "type": "Feature",
  "properties": {
    "addr:full":"Unit 1m Vallance By-ways, Gatwick Lowfield, Heath Road Horley Surrey RH6 0BT",
    "addr:housenumber":"1m",
    "addr:postcode":"rh6 0bt",
    "addr:street":"Heath Road",
    "iso:country":"GB",
    "sg:address":"Unit 1m Vallance By-ways, Gatwick Lowfield, Heath Road",
    "sg:city":"Horley",
    "sg:classifiers":[
        {
            "category":"Manufacturing",
            "subcategory":"Petroleum Products",
            "type":"Manufacturing & Wholesale Goods"
        }
    ],
    "sg:postcode":"RH6 0BT",
    "sg:province":"Surrey",
    "sg:tags":[
        "double",
        "glazing"
    ],
    "wof:name":"Gatwick Window Manufacturing Co",
    "wof:placetype":"venue"
},
  "geometry": {"coordinates":[-0.1692889929,51.175365448],"type":"Point"}
}