{
  "type": "Feature",
  "properties": {
    "addr:full":"306 Trelawney Avenue, Langley Slough Berkshire SL3 7UB",
    "addr:housenumber":"306",
    "addr:postcode":"sl3 7ub",
    "addr:street":"Trelawney Avenue",
    "iso:country":"GB",
    "sg:address":"306 Trelawney Avenue, Langley",
    "sg:city":"Slough",
    "sg:classifiers":[
        {
            "category":"Shopping",
            "subcategory":"Pharmacy",
            "type":"Retail Goods"
        }
    ],
    "sg:phone":"+44 1753 541939",
    "sg:postcode":"SL3 7UB",
    "sg:province":"Berkshire",
    "sg:tags":[
        "pharmacist",
        "chemist"
    ],
    "wof:name":"H A McParland (Chemists) Ltd.",
    "wof:placetype":"venue"
},
  "geometry": {"coordinates":[-0.5560250282,51.502407074],"type":"Point"}
}