{
  "type": "Feature",
  "properties": {
    "addr:full":"Unit 7 Laundry Lane, Milford On Sea Lymington Hampshire SO41 0WJ",
    "addr:housenumber":"unit 7",
    "addr:postcode":"so41 0wj",
    "addr:street":"Laundry Lane",
    "iso:country":"GB",
    "sg:address":"Unit 7 Laundry Lane, Milford On Sea",
    "sg:city":"Lymington",
    "sg:classifiers":[
        {
            "category":"Recreation",
            "subcategory":"Fishing",
            "type":"Entertainment"
        }
    ],
    "sg:phone":"+44 1590 643528",
    "sg:postcode":"SO41 0WJ",
    "sg:province":"Hampshire",
    "sg:tags":[
        "angling"
    ],
    "wof:name":"Witlock Products",
    "wof:placetype":"venue"
},
  "geometry": {"coordinates":[-1.585282,50.72414],"type":"Point"}
}