{
  "type": "Feature",
  "properties": {
    "iso:country":"GB",
    "sg:address":"41 Bank Lane",
    "sg:city":"Salford",
    "sg:classifiers":[
        {
            "category":"Food & Beverages",
            "subcategory":"Meat & Fish",
            "type":"Retail Goods"
        }
    ],
    "sg:phone":"+44 161 736 4988",
    "sg:postcode":"M6 7LH",
    "sg:province":"Greater Manchester",
    "sg:tags":[
        "chip"
    ],
    "wof:name":"Norma's Chippy",
    "wof:placetype":"venue"
},
  "geometry": {"coordinates":[-2.304345,53.502773],"type":"Point"}
}