{
  "type": "Feature",
  "properties": {
    "addr:full":"83 High Street, Clowne Chesterfield Derbyshire S43 4JX",
    "addr:housenumber":"83",
    "addr:postcode":"s43 4jx",
    "addr:street":"High Street",
    "iso:country":"GB",
    "sg:address":"83 High Street, Clowne",
    "sg:city":"Chesterfield",
    "sg:classifiers":[
        {
            "category":"Shopping",
            "subcategory":"Bicycles & Sporting Goods",
            "type":"Retail Goods"
        }
    ],
    "sg:phone":"+44 1246 812878",
    "sg:postcode":"S43 4JX",
    "sg:province":"Derbyshire",
    "sg:tags":[
        "cycle",
        "accessory"
    ],
    "wof:name":"Eddison Cycles",
    "wof:placetype":"venue"
},
  "geometry": {"coordinates":[-1.268684,53.272625],"type":"Point"}
}