{
  "type": "Feature",
  "properties": {
    "addr:full":"9 Castle Meadows, Downton Salisbury Dorset SP5 3JY",
    "addr:housenumber":"9",
    "addr:postcode":"sp5 3jy",
    "addr:street":"Castle Meadows",
    "iso:country":"GB",
    "sg:address":"9 Castle Meadows, Downton",
    "sg:city":"Salisbury",
    "sg:classifiers":[
        {
            "category":"Social Services",
            "subcategory":"Adult Care",
            "type":"Services"
        }
    ],
    "sg:phone":"+44 1725 510590",
    "sg:postcode":"SP5 3JY",
    "sg:province":"Dorset",
    "sg:tags":[
        "housing",
        "sheltered"
    ],
    "wof:name":"Castle Meadow",
    "wof:placetype":"venue"
},
  "geometry": {"coordinates":[-1.740665,50.992794],"type":"Point"}
}