{
  "type": "Feature",
  "properties": {
    "iso:country":"GB",
    "sg:address":"9 High Street, Markinch",
    "sg:city":"Glenrothes",
    "sg:classifiers":[
        {
            "category":"Military Area",
            "subcategory":"Air Force Base",
            "type":"Public Place"
        }
    ],
    "sg:phone":"+44 1592 752327",
    "sg:postcode":"KY7 6DQ",
    "sg:province":"Fife",
    "sg:tags":[
        "taxi",
        "hire",
        "private"
    ],
    "wof:name":"United Radio Cabs",
    "wof:placetype":"venue"
},
  "geometry": {"coordinates":[-3.13204,56.201942],"type":"Point"}
}