{
  "type": "Feature",
  "properties": {
    "addr:full":"The Wine Vaults, 22 Abbeygate St Bury St Edmunds Suffolk IP33 1UN",
    "addr:housenumber":"22",
    "addr:postcode":"ip33 1un",
    "addr:street":"Abbeygate St",
    "iso:country":"GB",
    "sg:address":"The Wine Vaults, 22 Abbeygate St",
    "sg:city":"Bury St Edmunds",
    "sg:classifiers":[
        {
            "category":"Fast Food",
            "type":"Food & Drink"
        }
    ],
    "sg:postcode":"IP33 1UN",
    "sg:province":"Suffolk",
    "sg:tags":[
        "away",
        "take"
    ],
    "wof:name":"Butlers Cellar (The)",
    "wof:placetype":"venue"
},
  "geometry": {"coordinates":[0.70932,52.249905],"type":"Point"}
}