{
  "type": "Feature",
  "properties": {
    "iso:country":"GB",
    "sg:address":"46 Kings Court",
    "sg:city":"Bishops Stortford",
    "sg:classifiers":[
        {
            "category":"Home & Garden",
            "subcategory":"Home Furnishings",
            "type":"Retail Goods"
        },
        {
            "category":"Home & Garden",
            "subcategory":"Carpets & Floor Coverings",
            "type":"Retail Goods"
        }
    ],
    "sg:phone":"+44 1279 651833",
    "sg:postcode":"CM23 2AB",
    "sg:province":"Essex",
    "sg:tags":[
        "fitting",
        "rug",
        "matting",
        "carpets"
    ],
    "wof:name":"J A Spalding",
    "wof:placetype":"venue"
},
  "geometry": {"coordinates":[0.166565,51.872917],"type":"Point"}
}