{
  "type": "Feature",
  "properties": {
    "iso:country":"GB",
    "sg:address":"44 Warstones Road",
    "sg:city":"Wolverhampton",
    "sg:classifiers":[
        {
            "category":"Home & Garden",
            "subcategory":"Household Appliances",
            "type":"Retail Goods"
        }
    ],
    "sg:phone":"+44 1902 331600",
    "sg:postcode":"WV4 4LP",
    "sg:province":"Staffordshire",
    "sg:tags":[
        "domestic",
        "centre"
    ],
    "wof:name":"Penn Domestic Appliances",
    "wof:placetype":"venue"
},
  "geometry": {"coordinates":[-2.173226,52.568024],"type":"Point"}
}