{
  "type": "Feature",
  "properties": {
    "addr:full":"Mill Place, Off Erskinefauld Road, Linwood Paisley Renfrewshire PA3 3PR",
    "addr:postcode":"pa3 3pr",
    "addr:street":"Mill Place Off Erskinefauld Road",
    "iso:country":"GB",
    "sg:address":"Mill Place, Off Erskinefauld Road, Linwood",
    "sg:city":"Paisley",
    "sg:classifiers":[
        {
            "category":"Farming",
            "subcategory":"Nursery",
            "type":"Manufacturing & Wholesale Goods"
        },
        {
            "category":"Government",
            "subcategory":"Office",
            "type":"Public Place"
        }
    ],
    "sg:phone":"+44 1505 326005",
    "sg:postcode":"PA3 3PR",
    "sg:province":"Renfrewshire",
    "sg:tags":[
        "local",
        "creche"
    ],
    "wof:name":"The Morton Nursery School",
    "wof:placetype":"venue"
},
  "geometry": {"coordinates":[-4.5014381409,55.8491477966],"type":"Point"}
}