{
  "type": "Feature",
  "properties": {
    "addr:full":"North End Saw Mills, Eastgate North Driffield East Riding of Yorkshire YO25 6DZ",
    "addr:postcode":"yo25 6dz",
    "addr:street":"End;Eastgate North",
    "iso:country":"GB",
    "sg:address":"North End Saw Mills, Eastgate North",
    "sg:city":"Driffield",
    "sg:classifiers":[
        {
            "category":"Manufacturing",
            "subcategory":"Lumber",
            "type":"Manufacturing & Wholesale Goods"
        }
    ],
    "sg:phone":"+44 1377 253338",
    "sg:postcode":"YO25 6DZ",
    "sg:province":"East Riding of Yorkshire",
    "sg:tags":[
        "importer",
        "merchants",
        "agent",
        "timber"
    ],
    "wof:name":"Henry Naylor & Sons Ltd.",
    "wof:placetype":"venue"
},
  "geometry": {"coordinates":[-0.441794008,54.010181427],"type":"Point"}
}