{
  "type": "Feature",
  "properties": {
    "addr:full":"Orlando House, Manchester Road Bolton Lancashire BL2 1ES",
    "addr:postcode":"bl2 1es",
    "addr:street":"Manchester Road",
    "iso:country":"GB",
    "sg:address":"Orlando House, Manchester Road",
    "sg:city":"Bolton",
    "sg:classifiers":[
        {
            "category":"Professional",
            "subcategory":"Art Services",
            "type":"Services"
        }
    ],
    "sg:phone":"+44 1204 382772",
    "sg:postcode":"BL2 1ES",
    "sg:province":"Lancashire",
    "sg:tags":[
        "consultant",
        "design"
    ],
    "wof:name":"S Beech Design",
    "wof:placetype":"venue"
},
  "geometry": {"coordinates":[-2.4225440025,53.5729103088],"type":"Point"}
}