{
  "type": "Feature",
  "properties": {
    "addr:full":"Rear Of 135 Epsom Rd Sutton Surrey SM3 9EY",
    "addr:housenumber":"135",
    "addr:postcode":"sm3 9ey",
    "addr:street":"Epsom Rd",
    "iso:country":"GB",
    "sg:address":"Rear Of 135 Epsom Rd",
    "sg:city":"Sutton",
    "sg:classifiers":[
        {
            "category":"Retail",
            "subcategory":"Auto Repair",
            "type":"Services"
        }
    ],
    "sg:phone":"+44 20 8644 1054",
    "sg:postcode":"SM3 9EY",
    "sg:province":"Surrey",
    "sg:tags":[
        "modification",
        "garage"
    ],
    "wof:name":"R.W. Motors",
    "wof:placetype":"venue"
},
  "geometry": {"coordinates":[-0.2104,51.38649],"type":"Point"}
}