{
  "type": "Feature",
  "properties": {
    "iso:country":"GB",
    "sg:address":"Burnhead Street, Uddingston",
    "sg:city":"Glasgow",
    "sg:classifiers":[
        {
            "category":"Community Center",
            "type":"Public Place"
        }
    ],
    "sg:phone":"+44 1698 815919",
    "sg:postcode":"G71 5AT",
    "sg:province":"Glasgow City",
    "sg:tags":[
        "centre"
    ],
    "wof:name":"Burnhead Community Centre",
    "wof:placetype":"venue"
},
  "geometry": {"coordinates":[-4.065299,55.830025],"type":"Point"}
}