{
  "type": "Feature",
  "properties": {
    "addr:full":"P O Box 100 Southampton Hampshire SO32 2LT",
    "addr:housenumber":"100",
    "addr:postcode":"so32 2lt",
    "addr:street":"P O Box",
    "iso:country":"GB",
    "sg:address":"P O Box 100",
    "sg:city":"Southampton",
    "sg:classifiers":[
        {
            "category":"Manufacturing",
            "subcategory":"Glass & Minerals",
            "type":"Manufacturing & Wholesale Goods"
        }
    ],
    "sg:phone":"+44 1782 292292",
    "sg:postcode":"SO32 2LT",
    "sg:province":"Hampshire",
    "sg:tags":[
        "mnfr",
        "glassware",
        "china"
    ],
    "wof:name":"Royal Doulton Overseas Holdings Ltd.",
    "wof:placetype":"venue"
},
  "geometry": {"coordinates":[-1.205526,50.939251],"type":"Point"}
}