{
  "type": "Feature",
  "properties": {
    "iso:country":"GB",
    "sg:address":"48 Station Road, Burley In Wharfedale",
    "sg:city":"Ilkley",
    "sg:classifiers":[
        {
            "category":"Farming",
            "subcategory":"Nursery",
            "type":"Manufacturing & Wholesale Goods"
        },
        {
            "category":"Education",
            "subcategory":"Preschool",
            "type":"Public Place"
        }
    ],
    "sg:phone":"+44 1943 864909",
    "sg:postcode":"LS29 7NE",
    "sg:province":"North Yorkshire",
    "sg:tags":[
        "school",
        "creche"
    ],
    "wof:name":"Burley Nursery School & Childcare Centre",
    "wof:placetype":"venue"
},
  "geometry": {"coordinates":[-1.751279,53.912292],"type":"Point"}
}