{
  "type": "Feature",
  "properties": {
    "iso:country":"GB",
    "sg:address":"Abercromby Court, 20c Seafield Road East",
    "sg:city":"Edinburgh",
    "sg:classifiers":[
        {
            "category":"Autos & Motor Vehicles",
            "subcategory":"Automobile Sales",
            "type":"Retail Goods"
        }
    ],
    "sg:phone":"+44 131 657 4343",
    "sg:postcode":"EH15 1ED",
    "sg:province":"City of Edinburgh",
    "sg:tags":[
        "car"
    ],
    "wof:name":"Abercromby Toyota",
    "wof:placetype":"venue"
},
  "geometry": {"coordinates":[-3.128684,55.962925],"type":"Point"}
}