{
  "type": "Feature",
  "properties": {
    "iso:country":"GB",
    "sg:address":"24 Steventon, Sandymoor",
    "sg:city":"Runcorn",
    "sg:classifiers":[
        {
            "category":"Building & Trades",
            "subcategory":"Construction",
            "type":"Services"
        }
    ],
    "sg:phone":"+44 1928 579958",
    "sg:postcode":"WA7 1UB",
    "sg:province":"Cheshire",
    "sg:tags":[
        "decorator",
        "painter"
    ],
    "wof:name":"Decor-craft",
    "wof:placetype":"venue"
},
  "geometry": {"coordinates":[-2.660354,53.347702],"type":"Point"}
}