{
  "type": "Feature",
  "properties": {
    "addr:full":"34 New North Road Reigate Surrey RH2 8NA",
    "addr:housenumber":"34",
    "addr:postcode":"rh2 8na",
    "addr:street":"New North Road",
    "iso:country":"GB",
    "sg:address":"34 New North Road",
    "sg:city":"Reigate",
    "sg:classifiers":[
        {
            "category":"Building & Trades",
            "subcategory":"Plumbing",
            "type":"Services"
        }
    ],
    "sg:postcode":"RH2 8NA",
    "sg:province":"Surrey",
    "sg:tags":[
        "heating"
    ],
    "wof:name":"Thorogoods of Dorking",
    "wof:placetype":"venue"
},
  "geometry": {"coordinates":[-0.2151519954,51.2253227234],"type":"Point"}
}