{
  "type": "Feature",
  "properties": {
    "addr:full":"2a Station Rd, Bletchingdon Kidlington Buckinghamshire OX5 3DB",
    "addr:housenumber":"2a",
    "addr:postcode":"ox5 3db",
    "addr:street":"Station Rd",
    "iso:country":"GB",
    "sg:address":"2a Station Rd, Bletchingdon",
    "sg:city":"Kidlington",
    "sg:classifiers":[
        {
            "category":"Retail",
            "subcategory":"Driving School",
            "type":"Services"
        }
    ],
    "sg:phone":"+44 1869 350007",
    "sg:postcode":"OX5 3DB",
    "sg:province":"Buckinghamshire",
    "wof:name":"Elle Driving Academy For Ladies",
    "wof:placetype":"venue"
},
  "geometry": {"coordinates":[-1.273721,51.855671],"type":"Point"}
}