{
  "type": "Feature",
  "properties": {
    "iso:country":"GB",
    "sg:address":"3/4 Little Portland Street",
    "sg:city":"London",
    "sg:classifiers":[
        {
            "category":"Shopping",
            "subcategory":"Crafts & Fabrics",
            "type":"Retail Goods"
        }
    ],
    "sg:phone":"+44 20 7272 2102",
    "sg:postcode":"W1W 7JB",
    "sg:province":"Greater London",
    "sg:tags":[
        "knitwear",
        "yarn"
    ],
    "wof:name":"Vega (London) Ltd.",
    "wof:placetype":"venue"
},
  "geometry": {"coordinates":[-0.140603,51.517422],"type":"Point"}
}