{
  "type": "Feature",
  "properties": {
    "addr:full":"Imperial Works, Wednesfield Road Willenhall West Midlands WV13 1AL",
    "addr:postcode":"wv13 1al",
    "addr:street":"Wednesfield Road",
    "iso:country":"GB",
    "sg:address":"Imperial Works, Wednesfield Road",
    "sg:city":"Willenhall",
    "sg:classifiers":[
        {
            "category":"Professional",
            "subcategory":"Detective & Security Services",
            "type":"Services"
        }
    ],
    "sg:phone":"+44 1902 635964",
    "sg:postcode":"WV13 1AL",
    "sg:province":"West Midlands",
    "sg:tags":[
        "locksmith"
    ],
    "wof:name":"Guardian Lock & Engineering Co. Ltd.",
    "wof:placetype":"venue"
},
  "geometry": {"coordinates":[-2.057104,52.58427],"type":"Point"}
}