{
  "type": "Feature",
  "properties": {
    "addr:full":"33 Cowl St Evesham Gloucestershire WR11 4PL",
    "addr:housenumber":"33",
    "addr:postcode":"wr11 4pl",
    "addr:street":"Cowl St",
    "iso:country":"GB",
    "sg:address":"33 Cowl St",
    "sg:city":"Evesham",
    "sg:classifiers":[
        {
            "category":"Shopping",
            "subcategory":"Crafts & Fabrics",
            "type":"Retail Goods"
        }
    ],
    "sg:postcode":"WR11 4PL",
    "sg:province":"Gloucestershire",
    "sg:tags":[
        "material",
        "art"
    ],
    "wof:name":"Jones,Peter,",
    "wof:placetype":"venue"
},
  "geometry": {"coordinates":[-1.945358,52.092163],"type":"Point"}
}