{
  "type": "Feature",
  "properties": {
    "addr:full":"Unit 13, Aqueduct Mill, Aqueduct Street Preston Lancashire PR1 7JN",
    "addr:housenumber":"unit 13",
    "addr:postcode":"pr1 7jn",
    "addr:street":"Aqueduct Street",
    "iso:country":"GB",
    "sg:address":"Unit 13, Aqueduct Mill, Aqueduct Street",
    "sg:city":"Preston",
    "sg:classifiers":[
        {
            "category":"Manufacturing",
            "subcategory":"Metals",
            "type":"Manufacturing & Wholesale Goods"
        },
        {
            "category":"Professional",
            "type":"Services"
        }
    ],
    "sg:phone":"+44 1772 884801",
    "sg:postcode":"PR1 7JN",
    "sg:province":"Lancashire",
    "sg:tags":[
        "polishing",
        "finishing"
    ],
    "wof:name":"Aqua Plating",
    "wof:placetype":"venue"
},
  "geometry": {"coordinates":[-2.7081589699,53.7686233521],"type":"Point"}
}