{
  "type": "Feature",
  "properties": {
    "addr:full":"132 High St Southampton Hampshire SO14 2BR",
    "addr:housenumber":"132",
    "addr:postcode":"so14 2br",
    "addr:street":"High St",
    "iso:country":"GB",
    "sg:address":"132 High St",
    "sg:city":"Southampton",
    "sg:classifiers":[
        {
            "category":"Shopping",
            "subcategory":"Luggage & Leather Goods",
            "type":"Retail Goods"
        }
    ],
    "sg:postcode":"SO14 2BR",
    "sg:province":"Hampshire",
    "sg:tags":[
        "shop",
        "leathergoods"
    ],
    "wof:name":"Freemantle,J,& Son Ltd",
    "wof:placetype":"venue"
},
  "geometry": {"coordinates":[-1.4039180279,50.8995666504],"type":"Point"}
}