{
  "type": "Feature",
  "properties": {
    "iso:country":"GB",
    "sg:address":"55 East Rd",
    "sg:city":"Islington",
    "sg:classifiers":[
        {
            "category":"Professional",
            "subcategory":"Business Services",
            "type":"Services"
        }
    ],
    "sg:phone":"+44 20 7251 6700",
    "sg:postcode":"N1 6AH",
    "sg:province":"Greater London",
    "sg:tags":[
        "trade"
    ],
    "wof:name":"Association Of Computer System Managers The",
    "wof:placetype":"venue"
},
  "geometry": {"coordinates":[-0.086399,51.53022],"type":"Point"}
}