{
  "type": "Feature",
  "properties": {
    "addr:full":"10 Thames St Business Complex, Thames Street Louth Lincolnshire LN11 7AD",
    "addr:housenumber":"10",
    "addr:postcode":"ln11 7ad",
    "addr:street":"Thames St;Thames Street Louth",
    "iso:country":"GB",
    "sg:address":"10 Thames St Business Complex, Thames Street",
    "sg:city":"Louth",
    "sg:classifiers":[
        {
            "category":"Food & Beverages",
            "subcategory":"Meat & Fish",
            "type":"Retail Goods"
        }
    ],
    "sg:phone":"+44 1507 608388",
    "sg:postcode":"LN11 7AD",
    "sg:province":"Lincolnshire",
    "sg:tags":[
        "butcher"
    ],
    "wof:name":"Viking Foods Ltd.",
    "wof:placetype":"venue"
},
  "geometry": {"coordinates":[0.0099320002,53.3715858459],"type":"Point"}
}