{
  "type": "Feature",
  "properties": {
    "iso:country":"GB",
    "sg:address":"28 Abbots Road",
    "sg:city":"Selby",
    "sg:classifiers":[
        {
            "category":"Building & Trades",
            "subcategory":"Landscaping Services",
            "type":"Services"
        }
    ],
    "sg:phone":"+44 1757 704091",
    "sg:postcode":"YO8 8AU",
    "sg:province":"East Riding of Yorkshire",
    "sg:tags":[
        "landscape",
        "contractor"
    ],
    "wof:name":"Go-Grow",
    "wof:placetype":"venue"
},
  "geometry": {"coordinates":[-1.0534030199,53.7775001526],"type":"Point"}
}