{
  "type": "Feature",
  "properties": {
    "iso:country":"GB",
    "sg:address":"2 Boyn Valley Road",
    "sg:city":"Maidenhead",
    "sg:classifiers":[
        {
            "category":"Health Services",
            "subcategory":"Health Practitioner",
            "type":"Services"
        }
    ],
    "sg:postcode":"SL6 4ED",
    "sg:province":"Berkshire",
    "sg:tags":[
        "osteopath"
    ],
    "wof:name":"Francis Dashwood-Evans",
    "wof:placetype":"venue"
},
  "geometry": {"coordinates":[-0.741247,51.514648],"type":"Point"}
}