{
  "type": "Feature",
  "properties": {
    "addr:full":"Ragwood Farm, Clewer Wedmore Somerset BS28 4JG",
    "addr:postcode":"bs28 4jg",
    "iso:country":"GB",
    "sg:address":"Ragwood Farm, Clewer",
    "sg:city":"Wedmore",
    "sg:classifiers":[
        {
            "category":"Recreation",
            "subcategory":"Campground",
            "type":"Entertainment"
        }
    ],
    "sg:postcode":"BS28 4JG",
    "sg:province":"Somerset",
    "sg:tags":[
        "site",
        "camping"
    ],
    "wof:name":"Stuart Lloyd Morgan",
    "wof:placetype":"venue"
},
  "geometry": {"coordinates":[-2.81016,51.227631],"type":"Point"}
}