{
  "type": "Feature",
  "properties": {
    "addr:full":"George Street Morpeth Northumberland NE65 0DW",
    "addr:postcode":"ne65 0dw",
    "addr:street":"George Street",
    "iso:country":"GB",
    "sg:address":"George Street",
    "sg:city":"Morpeth",
    "sg:classifiers":[
        {
            "category":"Food & Beverages",
            "subcategory":"Groceries & Convenience Stores",
            "type":"Retail Goods"
        }
    ],
    "sg:phone":"+44 1665 710317",
    "sg:postcode":"NE65 0DW",
    "sg:province":"Northumberland",
    "wof:name":"Associated Co-operative Creameries",
    "wof:placetype":"venue"
},
  "geometry": {"coordinates":[-1.5814930201,55.3343505859],"type":"Point"}
}