{
  "type": "Feature",
  "properties": {
    "addr:full":"The Health Centre Corwen Conwy LL21 0DN",
    "addr:postcode":"ll21 0dn",
    "addr:street":"Corwen",
    "iso:country":"GB",
    "sg:address":"The Health Centre",
    "sg:city":"Corwen",
    "sg:classifiers":[
        {
            "category":"Health Services",
            "subcategory":"Doctor",
            "type":"Services"
        }
    ],
    "sg:phone":"+44 1490 412362",
    "sg:postcode":"LL21 0DN",
    "sg:province":"Conwy",
    "sg:tags":[
        "practitioners"
    ],
    "wof:name":"Gibbs & Park Dr S",
    "wof:placetype":"venue"
},
  "geometry": {"coordinates":[-3.373668,52.980648],"type":"Point"}
}