{
  "type": "Feature",
  "properties": {
    "addr:full":"Station Lane, Old Whittington Chesterfield Derbyshire S41 9QX",
    "addr:postcode":"s41 9qx",
    "addr:street":"Station Lane",
    "iso:country":"GB",
    "sg:address":"Station Lane, Old Whittington",
    "sg:city":"Chesterfield",
    "sg:classifiers":[
        {
            "category":"Wholesale",
            "subcategory":"Machinery & Supplies",
            "type":"Manufacturing & Wholesale Goods"
        }
    ],
    "sg:phone":"+44 1246 454536",
    "sg:postcode":"S41 9QX",
    "sg:province":"Derbyshire",
    "sg:tags":[
        "industrial",
        "commercial"
    ],
    "wof:name":"Advanced Cutting Systems",
    "wof:placetype":"venue"
},
  "geometry": {"coordinates":[-1.4254390001,53.2690200806],"type":"Point"}
}