{
  "type": "Feature",
  "properties": {
    "addr:full":"64 Staunton Avenue Hayling Island Hampshire PO11 0EW",
    "addr:housenumber":"64",
    "addr:postcode":"po11 0ew",
    "addr:street":"Staunton Avenue",
    "iso:country":"GB",
    "sg:address":"64 Staunton Avenue",
    "sg:city":"Hayling Island",
    "sg:classifiers":[
        {
            "category":"Professional",
            "subcategory":"Management & Consulting",
            "type":"Services"
        },
        {
            "category":"Professional",
            "subcategory":"Engineering",
            "type":"Services"
        }
    ],
    "sg:phone":"+44 23 9246 4903",
    "sg:postcode":"PO11 0EW",
    "sg:province":"Hampshire",
    "sg:tags":[
        "fire",
        "consultant",
        "protection",
        "engineer"
    ],
    "wof:name":"Fire Protection Services Hayling",
    "wof:placetype":"venue"
},
  "geometry": {"coordinates":[-0.996332,50.787266],"type":"Point"}
}