{
  "type": "Feature",
  "properties": {
    "addr:full":"Upper House Farm Hereford Herefordshire HR2 8EL",
    "addr:postcode":"hr2 8el",
    "iso:country":"GB",
    "sg:address":"Upper House Farm",
    "sg:city":"Hereford",
    "sg:classifiers":[
        {
            "category":"Farming",
            "subcategory":"Livestock Farm",
            "type":"Manufacturing & Wholesale Goods"
        }
    ],
    "sg:phone":"+44 1981 540289",
    "sg:postcode":"HR2 8EL",
    "sg:province":"Herefordshire",
    "sg:tags":[
        "others"
    ],
    "wof:name":"F J Price & Son",
    "wof:placetype":"venue"
},
  "geometry": {"coordinates":[-2.737449,51.953972],"type":"Point"}
}