{
  "type": "Feature",
  "properties": {
    "addr:full":"Gobions Farm House, Collier Row Road Romford Essex RM5 2BH",
    "addr:postcode":"rm5 2bh",
    "addr:street":"Collier Row Road",
    "iso:country":"GB",
    "sg:address":"Gobions Farm House, Collier Row Road",
    "sg:city":"Romford",
    "sg:classifiers":[
        {
            "category":"Farming",
            "subcategory":"Livestock Farm",
            "type":"Manufacturing & Wholesale Goods"
        }
    ],
    "sg:phone":"+44 1708 740123",
    "sg:postcode":"RM5 2BH",
    "sg:province":"Essex",
    "sg:tags":[
        "others"
    ],
    "wof:name":"Andrew F Fowler",
    "wof:placetype":"venue"
},
  "geometry": {"coordinates":[0.160365,51.598598],"type":"Point"}
}