{
  "type": "Feature",
  "properties": {
    "addr:full":"Wigman Rd Nottingham Nottinghamshire NG8 4AB",
    "addr:postcode":"ng8 4ab",
    "addr:street":"Wigman Rd",
    "iso:country":"GB",
    "sg:address":"Wigman Rd",
    "sg:city":"Nottingham",
    "sg:classifiers":[
        {
            "category":"Organizations",
            "subcategory":"Membership Organization",
            "type":"Services"
        }
    ],
    "sg:phone":"+44 115 904 7080",
    "sg:postcode":"NG8 4AB",
    "sg:province":"Nottinghamshire",
    "sg:tags":[
        "club"
    ],
    "wof:name":"Nova Club The",
    "wof:placetype":"venue"
},
  "geometry": {"coordinates":[-1.229879,52.972309],"type":"Point"}
}