{
  "type": "Feature",
  "properties": {
    "iso:country":"GB",
    "sg:address":"8 Dale Lane, Appleton",
    "sg:city":"Warrington",
    "sg:classifiers":[
        {
            "category":"Professional",
            "subcategory":"Management & Consulting",
            "type":"Services"
        }
    ],
    "sg:postcode":"WA4 3DX",
    "sg:province":"Cheshire",
    "sg:tags":[
        "fire",
        "consultant",
        "protection"
    ],
    "wof:name":"F S Consulting",
    "wof:placetype":"venue"
},
  "geometry": {"coordinates":[-2.5681819916,53.3670120239],"type":"Point"}
}