{
  "type": "Feature",
  "properties": {
    "addr:full":"45 Cardy Road Hemel Hempstead Hertfordshire HP1 1SQ",
    "addr:housenumber":"45",
    "addr:postcode":"hp1 1sq",
    "addr:street":"Cardy Road",
    "iso:country":"GB",
    "sg:address":"45 Cardy Road",
    "sg:city":"Hemel Hempstead",
    "sg:classifiers":[
        {
            "category":"Professional",
            "subcategory":"Engineering",
            "type":"Services"
        }
    ],
    "sg:phone":"+44 1442 212167",
    "sg:postcode":"HP1 1SQ",
    "sg:province":"Hertfordshire",
    "sg:tags":[
        "hydraulic",
        "engineer"
    ],
    "wof:name":"Matthews & Son Jack Repairs Ltd",
    "wof:placetype":"venue"
},
  "geometry": {"coordinates":[-0.48616,51.753098],"type":"Point"}
}