{
  "type": "Feature",
  "properties": {
    "iso:country":"GB",
    "sg:address":"150 Lochee Rd",
    "sg:city":"Dundee",
    "sg:classifiers":[
        {
            "category":"Building & Trades",
            "subcategory":"Construction",
            "type":"Services"
        }
    ],
    "sg:postcode":"DD2 2LD",
    "sg:province":"Dundee City",
    "sg:tags":[
        "decorator",
        "painter"
    ],
    "wof:name":"Dow,E,",
    "wof:placetype":"venue"
},
  "geometry": {"coordinates":[-2.9936139584,56.4647445679],"type":"Point"}
}