{
  "type": "Feature",
  "properties": {
    "addr:full":"Alan James And Company, Shepperton Marina, Felix La Shepperton Surrey TW17 8NJ",
    "addr:postcode":"tw17 8nj",
    "addr:street":"Alan;Felix La Shepperton",
    "iso:country":"GB",
    "sg:address":"Alan James And Company, Shepperton Marina, Felix La",
    "sg:city":"Shepperton",
    "sg:classifiers":[
        {
            "category":"Professional",
            "subcategory":"Management & Consulting",
            "type":"Services"
        }
    ],
    "sg:postcode":"TW17 8NJ",
    "sg:province":"Surrey",
    "sg:tags":[
        "consultant",
        "business"
    ],
    "wof:name":"Aspen Management Consultants Ltd",
    "wof:placetype":"venue"
},
  "geometry": {"coordinates":[-0.424789995,51.3905601501],"type":"Point"}
}