{
  "type": "Feature",
  "properties": {
    "iso:country":"GB",
    "sg:address":"13a The Broadway, Kingston Road",
    "sg:city":"Staines",
    "sg:classifiers":[
        {
            "category":"Professional",
            "subcategory":"Detective & Security Services",
            "type":"Services"
        }
    ],
    "sg:phone":"+44 1784 469938",
    "sg:postcode":"TW18 1AT",
    "sg:province":"Berkshire",
    "sg:tags":[
        "alarm",
        "burglar",
        "system"
    ],
    "wof:name":"Burton Security Service",
    "wof:placetype":"venue"
},
  "geometry": {"coordinates":[-0.48612,51.411076],"type":"Point"}
}