{
  "type": "Feature",
  "properties": {
    "iso:country":"GB",
    "sg:address":"North Bradley House, Church Lane, North Bradley",
    "sg:city":"Trowbridge",
    "sg:classifiers":[
        {
            "category":"Professional",
            "subcategory":"Computer Services",
            "type":"Services"
        }
    ],
    "sg:postcode":"BA14 0TA",
    "sg:province":"Wiltshire",
    "sg:tags":[
        "system",
        "software"
    ],
    "wof:name":"Mike Taylor",
    "wof:placetype":"venue"
},
  "geometry": {"coordinates":[-2.229079,51.306465],"type":"Point"}
}