{
  "type": "Feature",
  "properties": {
    "iso:country":"GB",
    "sg:address":"1-2 Stokers Buildings, Front St",
    "sg:city":"Bedlington",
    "sg:classifiers":[
        {
            "category":"Professional",
            "subcategory":"Engineering",
            "type":"Services"
        }
    ],
    "sg:phone":"+44 1670 828222",
    "sg:postcode":"NE22 5DS",
    "sg:province":"Northumberland",
    "sg:tags":[
        "contractor",
        "electrical",
        "engineer"
    ],
    "wof:name":"Atkins Bros",
    "wof:placetype":"venue"
},
  "geometry": {"coordinates":[-1.592434,55.130371],"type":"Point"}
}