{
  "type": "Feature",
  "properties": {
    "iso:country":"GB",
    "sg:address":"Beech House, 35a Hinton Road, Fulbourn",
    "sg:city":"Cambridge",
    "sg:classifiers":[
        {
            "category":"Professional",
            "subcategory":"Art Services",
            "type":"Services"
        }
    ],
    "sg:postcode":"CB1 5DZ",
    "sg:province":"Cambridgeshire",
    "sg:tags":[
        "graphic",
        "designer"
    ],
    "wof:name":"Carrods Design & Communication",
    "wof:placetype":"venue"
},
  "geometry": {"coordinates":[0.2081310004,52.1846847534],"type":"Point"}
}