{
  "type": "Feature",
  "properties": {
    "addr:full":"Commercial Road Alford Lincolnshire LN13 9EY",
    "addr:postcode":"ln13 9ey",
    "addr:street":"Commercial Road",
    "iso:country":"GB",
    "sg:address":"Commercial Road",
    "sg:city":"Alford",
    "sg:classifiers":[
        {
            "category":"Building & Trades",
            "subcategory":"Construction",
            "type":"Services"
        }
    ],
    "sg:phone":"+44 1507 462465",
    "sg:postcode":"LN13 9EY",
    "sg:province":"Lincolnshire",
    "sg:tags":[
        "builder"
    ],
    "wof:name":"Arthur Wood & Sons",
    "wof:placetype":"venue"
},
  "geometry": {"coordinates":[0.17446,53.261181],"type":"Point"}
}