{
  "type": "Feature",
  "properties": {
    "addr:full":"45 Westgate Otley North Yorkshire LS21 3AT",
    "addr:housenumber":"45",
    "addr:postcode":"ls21 3at",
    "addr:street":"Westgate",
    "iso:country":"GB",
    "sg:address":"45 Westgate",
    "sg:city":"Otley",
    "sg:classifiers":[
        {
            "category":"Professional",
            "subcategory":"Advertising",
            "type":"Services"
        }
    ],
    "sg:postcode":"LS21 3AT",
    "sg:province":"North Yorkshire",
    "sg:tags":[
        "agency"
    ],
    "wof:name":"Carey-Campbell,Carole,",
    "wof:placetype":"venue"
},
  "geometry": {"coordinates":[-1.6971329451,53.9047660828],"type":"Point"}
}