{
  "type": "Feature",
  "properties": {
    "addr:full":"194-196 Brook Hill Sheffield South Yorkshire S3 7HE",
    "addr:housenumber":"194-196",
    "addr:postcode":"s3 7he",
    "addr:street":"Brook",
    "iso:country":"GB",
    "sg:address":"194-196 Brook Hill",
    "sg:city":"Sheffield",
    "sg:classifiers":[
        {
            "category":"Fast Food",
            "type":"Food & Drink"
        }
    ],
    "sg:phone":"+44 114 276 2326",
    "sg:postcode":"S3 7HE",
    "sg:province":"South Yorkshire",
    "sg:tags":[
        "away",
        "take"
    ],
    "wof:name":"Southern Fried Chicken",
    "wof:placetype":"venue"
},
  "geometry": {"coordinates":[-1.4823989868,53.3821411133],"type":"Point"}
}