{
  "type": "Feature",
  "properties": {
    "addr:full":"Chapmanslade Westbury Wiltshire BA13 4AQ",
    "addr:housenumber":"chapmanslade",
    "addr:postcode":"ba13 4aq",
    "addr:street":"Westbury",
    "iso:country":"GB",
    "sg:address":"Chapmanslade",
    "sg:city":"Westbury",
    "sg:classifiers":[
        {
            "category":"Sports & Exercise",
            "subcategory":"Golf",
            "type":"Entertainment"
        }
    ],
    "sg:phone":"+44 1373 832825",
    "sg:postcode":"BA13 4AQ",
    "sg:province":"Wiltshire",
    "sg:tags":[
        "club",
        "course"
    ],
    "wof:name":"Tee Jay Leisure Ltd",
    "wof:placetype":"venue"
},
  "geometry": {"coordinates":[-2.2322399616,51.2312507629],"type":"Point"}
}