{
  "type": "Feature",
  "properties": {
    "addr:full":"2 Royal Parade Plymouth Devon PL1 1DS",
    "addr:housenumber":"2",
    "addr:postcode":"pl1 1ds",
    "addr:street":"Royal Parade",
    "iso:country":"GB",
    "sg:address":"2 Royal Parade",
    "sg:city":"Plymouth",
    "sg:classifiers":[
        {
            "category":"Shopping",
            "subcategory":"Comic Books",
            "type":"Retail Goods"
        }
    ],
    "sg:phone":"+44 1752 266107",
    "sg:postcode":"PL1 1DS",
    "sg:province":"Devon",
    "sg:tags":[
        "jeweller"
    ],
    "wof:name":"H Samuel",
    "wof:placetype":"venue"
},
  "geometry": {"coordinates":[-4.139527,50.370537],"type":"Point"}
}