{
  "type": "Feature",
  "properties": {
    "iso:country":"GB",
    "sg:address":"3 Millington Gate, Willen",
    "sg:city":"Milton Keynes",
    "sg:classifiers":[
        {
            "category":"Professional",
            "subcategory":"Computer Services",
            "type":"Services"
        }
    ],
    "sg:postcode":"MK15 9HT",
    "sg:province":"Buckinghamshire",
    "sg:tags":[
        "system",
        "software"
    ],
    "wof:name":"Binary Solutions Ltd.",
    "wof:placetype":"venue"
},
  "geometry": {"coordinates":[-0.72356,52.065117],"type":"Point"}
}