{
  "type": "Feature",
  "properties": {
    "addr:full":"Unit G1, Avonside Enterprise Park Melksham Wiltshire SN12 8BT",
    "addr:postcode":"sn12 8bt",
    "addr:street":"Melksham",
    "iso:country":"GB",
    "sg:address":"Unit G1, Avonside Enterprise Park",
    "sg:city":"Melksham",
    "sg:classifiers":[
        {
            "category":"Shopping",
            "subcategory":"Florist",
            "type":"Retail Goods"
        }
    ],
    "sg:phone":"+44 1225 700018",
    "sg:postcode":"SN12 8BT",
    "sg:province":"Wiltshire",
    "wof:name":"Sheila's",
    "wof:placetype":"venue"
},
  "geometry": {"coordinates":[-2.13560009,51.3740653992],"type":"Point"}
}