{
  "type": "Feature",
  "properties": {
    "addr:full":"75 Port Street Evesham Gloucestershire WR11 3LF",
    "addr:housenumber":"75",
    "addr:postcode":"wr11 3lf",
    "addr:street":"Port Street",
    "iso:country":"GB",
    "sg:address":"75 Port Street",
    "sg:city":"Evesham",
    "sg:classifiers":[
        {
            "category":"Shopping",
            "subcategory":"Florist",
            "type":"Retail Goods"
        }
    ],
    "sg:phone":"+44 1386 442020",
    "sg:postcode":"WR11 3LF",
    "sg:province":"Gloucestershire",
    "wof:name":"The Flower Basket",
    "wof:placetype":"venue"
},
  "geometry": {"coordinates":[-1.9376649857,52.090473175],"type":"Point"}
}