{
  "type": "Feature",
  "properties": {
    "iso:country":"GB",
    "sg:address":"Newark Street",
    "sg:city":"Bath",
    "sg:classifiers":[
        {
            "category":"Parking",
            "type":"Transportation"
        },
        {
            "category":"Government",
            "subcategory":"Office",
            "type":"Public Place"
        }
    ],
    "sg:phone":"+44 1225 461716",
    "sg:postcode":"BA1 5AW",
    "sg:province":"Bath and North East Somerset",
    "sg:tags":[
        "park",
        "car",
        "local"
    ],
    "wof:name":"Ham Gardens Car Park",
    "wof:placetype":"venue"
},
  "geometry": {"coordinates":[-2.358479023,51.3786849976],"type":"Point"}
}