{
  "type": "Feature",
  "properties": {
    "addr:full":"1a New Street Penzance Cornwall TR18 2LZ",
    "addr:housenumber":"1a",
    "addr:postcode":"tr18 2lz",
    "addr:street":"New Street",
    "iso:country":"GB",
    "sg:address":"1a New Street",
    "sg:city":"Penzance",
    "sg:classifiers":[
        {
            "category":"Personal",
            "subcategory":"Barber",
            "type":"Services"
        }
    ],
    "sg:postcode":"TR18 2LZ",
    "sg:province":"Cornwall",
    "sg:tags":[
        "men's",
        "hairdresser"
    ],
    "wof:name":"Marita Hair & Beauty",
    "wof:placetype":"venue"
},
  "geometry": {"coordinates":[-5.5358800888,50.1186294556],"type":"Point"}
}