{
  "type": "Feature",
  "properties": {
    "iso:country":"GB",
    "sg:address":"1 Ellesmere Drive",
    "sg:city":"Bewdley",
    "sg:classifiers":[
        {
            "category":"Farming",
            "subcategory":"Dairy Farm",
            "type":"Manufacturing & Wholesale Goods"
        }
    ],
    "sg:phone":"+44 1299 400216",
    "sg:postcode":"DY12 2PT",
    "sg:province":"Shropshire",
    "wof:name":"R Grazier",
    "wof:placetype":"venue"
},
  "geometry": {"coordinates":[-2.330413,52.376438],"type":"Point"}
}