{
  "type": "Feature",
  "properties": {
    "addr:full":"Coronation Street Cambridge Cambridgeshire CB2 1HJ",
    "addr:postcode":"cb2 1hj",
    "addr:street":"Coronation Street",
    "iso:country":"GB",
    "sg:address":"Coronation Street",
    "sg:city":"Cambridge",
    "sg:classifiers":[
        {
            "category":"Education",
            "subcategory":"School",
            "type":"Public Place"
        }
    ],
    "sg:phone":"+44 1223 568840",
    "sg:postcode":"CB2 1HJ",
    "sg:province":"Cambridgeshire",
    "sg:tags":[
        "local",
        "authority"
    ],
    "wof:name":"St Paul's C of E Primary School",
    "wof:placetype":"venue"
},
  "geometry": {"coordinates":[0.127503,52.196945],"type":"Point"}
}