{
  "type": "Feature",
  "properties": {
    "addr:full":"Heanley Lane, Hurley Atherstone Leicestershire CV9 2HY",
    "addr:postcode":"cv9 2hy",
    "addr:street":"Heanley Lane",
    "iso:country":"GB",
    "sg:address":"Heanley Lane, Hurley",
    "sg:city":"Atherstone",
    "sg:classifiers":[
        {
            "category":"Education",
            "subcategory":"School",
            "type":"Public Place"
        }
    ],
    "sg:phone":"+44 1827 872207",
    "sg:postcode":"CV9 2HY",
    "sg:province":"Leicestershire",
    "sg:tags":[
        "local",
        "authority"
    ],
    "wof:name":"Hurley Primary School",
    "wof:placetype":"venue"
},
  "geometry": {"coordinates":[-1.635619,52.571308],"type":"Point"}
}