{
  "type": "Feature",
  "properties": {
    "iso:country":"GB",
    "sg:address":"Ovenden Park",
    "sg:city":"Halifax",
    "sg:classifiers":[
        {
            "category":"Retail",
            "subcategory":"Auto Repair",
            "type":"Services"
        }
    ],
    "sg:phone":"+44 1422 353840",
    "sg:postcode":"HX2 8AR",
    "sg:province":"West Yorkshire",
    "sg:tags":[
        "modification",
        "garage"
    ],
    "wof:name":"Moorside Garage",
    "wof:placetype":"venue"
},
  "geometry": {"coordinates":[-1.8666169643,53.7280654907],"type":"Point"}
}