{
  "type": "Feature",
  "properties": {
    "iso:country":"GB",
    "sg:address":"Elderberry Cottage, 15 Two Mile Lane, Highnam",
    "sg:city":"Gloucester",
    "sg:classifiers":[
        {
            "category":"Building & Trades",
            "subcategory":"Landscaping Services",
            "type":"Services"
        }
    ],
    "sg:phone":"+44 1452 386662",
    "sg:postcode":"GL2 8DW",
    "sg:province":"Gloucestershire",
    "sg:tags":[
        "forestry",
        "tree"
    ],
    "wof:name":"Anthony Raymond Bethell",
    "wof:placetype":"venue"
},
  "geometry": {"coordinates":[-2.2981541157,51.8770866394],"type":"Point"}
}