{
  "type": "Feature",
  "properties": {
    "addr:full":"33 Middlemarch Road Dereham Norfolk NR19 1EQ",
    "addr:housenumber":"33",
    "addr:postcode":"nr19 1eq",
    "addr:street":"Middlemarch Road",
    "iso:country":"GB",
    "sg:address":"33 Middlemarch Road",
    "sg:city":"Dereham",
    "sg:classifiers":[
        {
            "category":"Building & Trades",
            "subcategory":"Construction",
            "type":"Services"
        }
    ],
    "sg:phone":"+44 1362 692814",
    "sg:postcode":"NR19 1EQ",
    "sg:province":"Norfolk",
    "sg:tags":[
        "joinery",
        "joiner",
        "carpenter",
        "carpentry"
    ],
    "wof:name":"B T Green",
    "wof:placetype":"venue"
},
  "geometry": {"coordinates":[0.93973,52.669025],"type":"Point"}
}