{
  "type": "Feature",
  "properties": {
    "iso:country":"GB",
    "sg:address":"Acre House, 69-76 Long Acre",
    "sg:city":"Holborn",
    "sg:classifiers":[
        {
            "category":"Real Estate",
            "subcategory":"Real Estate Agent",
            "type":"Services"
        }
    ],
    "sg:phone":"+44 20 7240 6199",
    "sg:postcode":"WC2E 9JH",
    "sg:province":"Greater London",
    "wof:name":"Quickplan",
    "wof:placetype":"venue"
},
  "geometry": {"coordinates":[-0.122649,51.513992],"type":"Point"}
}