{
  "type": "Feature",
  "properties": {
    "addr:full":"Mounthope Service Station, Closeburn Thornhill Dumfries and Galloway DG3 5HS",
    "addr:postcode":"dg3 5hs",
    "addr:street":"Closeburn",
    "iso:country":"GB",
    "sg:address":"Mounthope Service Station, Closeburn",
    "sg:city":"Thornhill",
    "sg:classifiers":[
        {
            "category":"Autos & Motor Vehicles",
            "subcategory":"Automobile Sales",
            "type":"Retail Goods"
        }
    ],
    "sg:phone":"+44 1848 331267",
    "sg:postcode":"DG3 5HS",
    "sg:province":"Dumfries and Galloway",
    "sg:tags":[
        "car"
    ],
    "wof:name":"E Martin & Son Ltd.",
    "wof:placetype":"venue"
},
  "geometry": {"coordinates":[-3.7659139633,55.2415046692],"type":"Point"}
}