{
  "type": "Feature",
  "properties": {
    "addr:full":"12a Motcomb Street London Greater London SW1X 8LB",
    "addr:housenumber":"12a",
    "addr:postcode":"sw1x 8lb",
    "addr:street":"Motcomb Street",
    "iso:country":"GB",
    "sg:address":"12a Motcomb Street",
    "sg:city":"London",
    "sg:classifiers":[
        {
            "category":"Wholesale",
            "subcategory":"Motor Vehicles",
            "type":"Manufacturing & Wholesale Goods"
        }
    ],
    "sg:phone":"+44 20 7235 7371",
    "sg:postcode":"SW1X 8LB",
    "sg:province":"Greater London",
    "sg:tags":[
        "container"
    ],
    "wof:name":"Lite Flite Services Ltd.",
    "wof:placetype":"venue"
},
  "geometry": {"coordinates":[-0.1566209942,51.4994812012],"type":"Point"}
}