{
  "type": "Feature",
  "properties": {
    "iso:country":"GB",
    "sg:address":"Haugh La",
    "sg:city":"Hexham",
    "sg:classifiers":[
        {
            "category":"Professional",
            "subcategory":"Lawyer & Legal Services",
            "type":"Services"
        }
    ],
    "sg:phone":"+44 1434 600900",
    "sg:postcode":"NE46 3PU",
    "sg:province":"Northumberland",
    "sg:tags":[
        "advice",
        "counselling"
    ],
    "wof:name":"Womens Driving Initiative Ltd",
    "wof:placetype":"venue"
},
  "geometry": {"coordinates":[-2.102468,54.973099],"type":"Point"}
}