{
  "type": "Feature",
  "properties": {
    "addr:full":"10 Stonedale Crescent Darlington Durham DL3 7BG",
    "addr:housenumber":"10",
    "addr:postcode":"dl3 7bg",
    "addr:street":"Stonedale Crescent",
    "iso:country":"GB",
    "sg:address":"10 Stonedale Crescent",
    "sg:city":"Darlington",
    "sg:classifiers":[
        {
            "category":"Professional",
            "subcategory":"Detective & Security Services",
            "type":"Services"
        }
    ],
    "sg:phone":"+44 1325 252020",
    "sg:postcode":"DL3 7BG",
    "sg:province":"Durham",
    "wof:name":"Chevron Security Systems Co Durham",
    "wof:placetype":"venue"
},
  "geometry": {"coordinates":[-1.568934,54.527679],"type":"Point"}
}