{
  "type": "Feature",
  "properties": {
    "addr:full":"3 Session Street Dundee Dundee City DD1 5DN",
    "addr:housenumber":"3",
    "addr:postcode":"dd1 5dn",
    "addr:street":"Session Street",
    "iso:country":"GB",
    "sg:address":"3 Session Street",
    "sg:city":"Dundee",
    "sg:classifiers":[
        {
            "category":"Bars & Pubs",
            "subcategory":"Nightclub",
            "type":"Food & Drink"
        }
    ],
    "sg:phone":"+44 1382 204284",
    "sg:postcode":"DD1 5DN",
    "sg:province":"Dundee City",
    "sg:tags":[
        "club",
        "night"
    ],
    "wof:name":"The Epic Group (Scotland) Ltd.",
    "wof:placetype":"venue"
},
  "geometry": {"coordinates":[-2.980152,56.460804],"type":"Point"}
}