{
  "type": "Feature",
  "properties": {
    "addr:full":"Richard Hayes, Dalwood Axminster Devon EX13 7DY",
    "addr:postcode":"ex13 7dy",
    "iso:country":"GB",
    "sg:address":"Richard Hayes, Dalwood",
    "sg:city":"Axminster",
    "sg:classifiers":[
        {
            "category":"Manufacturing",
            "subcategory":"Building Materials",
            "type":"Manufacturing & Wholesale Goods"
        }
    ],
    "sg:phone":"+44 1404 831225",
    "sg:postcode":"EX13 7DY",
    "sg:province":"Devon",
    "sg:tags":[
        "tarmac",
        "asphalt"
    ],
    "wof:name":"R B Lawrence (Dalwood) Ltd.",
    "wof:placetype":"venue"
},
  "geometry": {"coordinates":[-3.0687689781,50.7985649109],"type":"Point"}
}