{
  "type": "Feature",
  "properties": {
    "iso:country":"GB",
    "sg:address":"19 Header Park Dr",
    "sg:city":"Wembley",
    "sg:classifiers":[
        {
            "category":"Communications",
            "type":"Services"
        }
    ],
    "sg:postcode":"HA0 1FF",
    "sg:province":"Greater London",
    "sg:tags":[
        "telecommunication"
    ],
    "wof:name":"Starline Communications Ltd",
    "wof:placetype":"venue"
},
  "geometry": {"coordinates":[-0.2817449868,51.543170929],"type":"Point"}
}