{
  "type": "Feature",
  "properties": {
    "iso:country":"GB",
    "sg:address":"68 Villette Road",
    "sg:city":"Sunderland",
    "sg:classifiers":[
        {
            "category":"Shopping",
            "subcategory":"Pharmacy",
            "type":"Retail Goods"
        }
    ],
    "sg:phone":"+44 191 567 5028",
    "sg:postcode":"SR2 8RW",
    "sg:province":"Tyne and Wear",
    "sg:tags":[
        "pharmacist",
        "chemist"
    ],
    "wof:name":"Medichem",
    "wof:placetype":"venue"
},
  "geometry": {"coordinates":[-1.3729939461,54.8948364258],"type":"Point"}
}