{
  "type": "Feature",
  "properties": {
    "addr:full":"Burchetts Green Road, Burchetts Grn Maidenhead Berkshire SL6 6QS",
    "addr:postcode":"sl6 6qs",
    "addr:street":"Green Road Burchetts Grn",
    "iso:country":"GB",
    "sg:address":"Burchetts Green Road, Burchetts Grn",
    "sg:city":"Maidenhead",
    "sg:classifiers":[
        {
            "category":"Transit Center",
            "subcategory":"Passenger",
            "type":"Transportation"
        }
    ],
    "sg:postcode":"SL6 6QS",
    "sg:province":"Berkshire",
    "sg:tags":[
        "boarding",
        "kennel",
        "catteries"
    ],
    "wof:name":"Linden Boarding Kennels",
    "wof:placetype":"venue"
},
  "geometry": {"coordinates":[-0.7920240164,51.5246047974],"type":"Point"}
}