{
  "type": "Feature",
  "properties": {
    "addr:full":"24-26 South Street Wellington Devon TA21 8NS",
    "addr:housenumber":"24-26",
    "addr:postcode":"ta21 8ns",
    "addr:street":"South Street",
    "iso:country":"GB",
    "sg:address":"24-26 South Street",
    "sg:city":"Wellington",
    "sg:classifiers":[
        {
            "category":"Restaurant",
            "type":"Food & Drink"
        }
    ],
    "sg:postcode":"TA21 8NS",
    "sg:province":"Devon",
    "sg:tags":[
        "american"
    ],
    "wof:name":"Yankee Doodle Fast Food Restaurant",
    "wof:placetype":"venue"
},
  "geometry": {"coordinates":[-3.2268149853,50.9773712158],"type":"Point"}
}