{
  "type": "Feature",
  "properties": {
    "addr:full":"Hainton Ho, Hainton Sq Grimsby Lincolnshire DN32 9AQ",
    "addr:postcode":"dn32 9aq",
    "addr:street":"Hainton;Hainton Sq",
    "iso:country":"GB",
    "sg:address":"Hainton Ho, Hainton Sq",
    "sg:city":"Grimsby",
    "sg:classifiers":[
        {
            "category":"Professional",
            "subcategory":"Employment Agencies",
            "type":"Services"
        }
    ],
    "sg:phone":"+44 1472 353525",
    "sg:postcode":"DN32 9AQ",
    "sg:province":"Lincolnshire",
    "sg:tags":[
        "consultant"
    ],
    "wof:name":"Taskmaster Ridings Ltd",
    "wof:placetype":"venue"
},
  "geometry": {"coordinates":[-0.0750939995,53.5660057068],"type":"Point"}
}