{
  "type": "Feature",
  "properties": {
    "addr:full":"Interchange House, 27 Stafford Road Croydon Surrey CR0 4NG",
    "addr:housenumber":"27",
    "addr:postcode":"cr0 4ng",
    "addr:street":"Stafford Road",
    "iso:country":"GB",
    "sg:address":"Interchange House, 27 Stafford Road",
    "sg:city":"Croydon",
    "sg:classifiers":[
        {
            "category":"Travel",
            "subcategory":"Travel Agent",
            "type":"Entertainment"
        }
    ],
    "sg:phone":"+44 20 8681 3612",
    "sg:postcode":"CR0 4NG",
    "sg:province":"Surrey",
    "sg:tags":[
        "agency",
        "activity"
    ],
    "wof:name":"Interchange",
    "wof:placetype":"venue"
},
  "geometry": {"coordinates":[-0.1160899997,51.367061615],"type":"Point"}
}