{
  "type": "Feature",
  "properties": {
    "addr:full":"Court Leys Farm Grantham Leicestershire NG32 2AY",
    "addr:postcode":"ng32 2ay",
    "addr:street":"Court Leys Farm",
    "iso:country":"GB",
    "sg:address":"Court Leys Farm",
    "sg:city":"Grantham",
    "sg:classifiers":[
        {
            "category":"Home & Garden",
            "subcategory":"Furniture",
            "type":"Retail Goods"
        }
    ],
    "sg:phone":"+44 1636 626235",
    "sg:postcode":"NG32 2AY",
    "sg:province":"Leicestershire",
    "wof:name":"Coulpers Pine",
    "wof:placetype":"venue"
},
  "geometry": {"coordinates":[-0.6520799994,53.0327301025],"type":"Point"}
}