{
  "type": "Feature",
  "properties": {
    "addr:full":"37-39 Northgate Street Gloucester Gloucestershire GL1 2AN",
    "addr:housenumber":"37-39",
    "addr:postcode":"gl1 2an",
    "addr:street":"Northgate Street",
    "iso:country":"GB",
    "sg:address":"37-39 Northgate Street",
    "sg:city":"Gloucester",
    "sg:classifiers":[
        {
            "category":"Shopping",
            "subcategory":"Clothing, Apparel, & Fashions",
            "type":"Retail Goods"
        },
        {
            "category":"Shopping",
            "subcategory":"Baby Store",
            "type":"Retail Goods"
        }
    ],
    "sg:phone":"+44 1452 310755",
    "sg:postcode":"GL1 2AN",
    "sg:province":"Gloucestershire",
    "sg:tags":[
        "child",
        "childrens",
        "babywear"
    ],
    "wof:name":"Adams Childrenswear Ltd.",
    "wof:placetype":"venue"
},
  "geometry": {"coordinates":[-2.244239,51.866508],"type":"Point"}
}