{
  "type": "Feature",
  "properties": {
    "addr:full":"34 Crossway, Rogiet Caldicot Monmouthshire NP26 3SJ",
    "addr:housenumber":"34;rogiet",
    "addr:postcode":"np26 3sj",
    "addr:street":"Crossway",
    "iso:country":"GB",
    "sg:address":"34 Crossway, Rogiet",
    "sg:city":"Caldicot",
    "sg:classifiers":[
        {
            "category":"Wholesale",
            "subcategory":"Machinery & Supplies",
            "type":"Manufacturing & Wholesale Goods"
        }
    ],
    "sg:postcode":"NP26 3SJ",
    "sg:province":"Monmouthshire",
    "sg:tags":[
        "theatrical"
    ],
    "wof:name":"Bessant Barry Lighting & Fibre Optic Special Effec",
    "wof:placetype":"venue"
},
  "geometry": {"coordinates":[-2.748045,51.585957],"type":"Point"}
}