{
  "type": "Feature",
  "properties": {
    "iso:country":"GB",
    "sg:address":"55 Victoria Rd",
    "sg:city":"Colne",
    "sg:classifiers":[
        {
            "category":"Personal",
            "subcategory":"Beauty Salon",
            "type":"Services"
        }
    ],
    "sg:phone":"+44 1282 843606",
    "sg:postcode":"BB8 6UN",
    "sg:province":"Lancashire",
    "sg:tags":[
        "lady",
        "hairdresser"
    ],
    "wof:name":"Clip & Curl",
    "wof:placetype":"venue"
},
  "geometry": {"coordinates":[-2.1448390484,53.9158096313],"type":"Point"}
}