{
  "type": "Feature",
  "properties": {
    "addr:full":"The Den Teignmouth Devon TQ14 8BD",
    "addr:postcode":"tq14 8bd",
    "iso:country":"GB",
    "sg:address":"The Den",
    "sg:city":"Teignmouth",
    "sg:classifiers":[
        {
            "category":"Sports & Exercise",
            "subcategory":"Bowling",
            "type":"Entertainment"
        }
    ],
    "sg:phone":"+44 1626 774407",
    "sg:postcode":"TQ14 8BD",
    "sg:province":"Devon",
    "wof:name":"Teignmouth (the den) Bowling Club",
    "wof:placetype":"venue"
},
  "geometry": {"coordinates":[-3.4906589985,50.5545158386],"type":"Point"}
}