{
  "type": "Feature",
  "properties": {
    "addr:full":"40 Euclid Street Swindon Wiltshire SN1 2JW",
    "addr:housenumber":"40",
    "addr:postcode":"sn1 2jw",
    "addr:street":"Euclid Street",
    "iso:country":"GB",
    "sg:address":"40 Euclid Street",
    "sg:city":"Swindon",
    "sg:classifiers":[
        {
            "category":"Shopping",
            "subcategory":"News",
            "type":"Retail Goods"
        }
    ],
    "sg:phone":"+44 1793 534535",
    "sg:postcode":"SN1 2JW",
    "sg:province":"Wiltshire",
    "sg:tags":[
        "newsagent"
    ],
    "wof:name":"Shorts Newsagents",
    "wof:placetype":"venue"
},
  "geometry": {"coordinates":[-1.7755880356,51.5598487854],"type":"Point"}
}