{
  "type": "Feature",
  "properties": {
    "addr:full":"4a One Stop Shopping Centre, Walsall Road, Perry Barr Birmingham West Midlands B42 1AA",
    "addr:housenumber":"4a",
    "addr:postcode":"b42 1aa",
    "addr:street":"Walsall Road",
    "iso:country":"GB",
    "sg:address":"4a One Stop Shopping Centre, Walsall Road, Perry Barr",
    "sg:city":"Birmingham",
    "sg:classifiers":[
        {
            "category":"Shopping",
            "subcategory":"Bicycles & Sporting Goods",
            "type":"Retail Goods"
        },
        {
            "category":"Sports & Exercise",
            "subcategory":"Sports Center",
            "type":"Entertainment"
        }
    ],
    "sg:phone":"+44 121 356 3585",
    "sg:postcode":"B42 1AA",
    "sg:province":"West Midlands",
    "sg:tags":[
        "shop",
        "sale"
    ],
    "wof:name":"SPORTS DIVISION LTD",
    "wof:placetype":"venue"
},
  "geometry": {"coordinates":[-1.9048589468,52.522518158],"type":"Point"}
}