{
  "type": "Feature",
  "properties": {
    "addr:full":"11a Frances St Truro Cornwall TR1 3DN",
    "addr:housenumber":"11a",
    "addr:postcode":"tr1 3dn",
    "addr:street":"Frances St",
    "iso:country":"GB",
    "sg:address":"11a Frances St",
    "sg:city":"Truro",
    "sg:classifiers":[
        {
            "category":"Sports & Exercise",
            "subcategory":"Sports Center",
            "type":"Entertainment"
        }
    ],
    "sg:phone":"+44 1872 261248",
    "sg:postcode":"TR1 3DN",
    "sg:province":"Cornwall",
    "sg:tags":[
        "shop",
        "good"
    ],
    "wof:name":"Ricochet Martial Arts",
    "wof:placetype":"venue"
},
  "geometry": {"coordinates":[-5.0565199852,50.2635917664],"type":"Point"}
}