{
  "type": "Feature",
  "properties": {
    "iso:country":"GB",
    "sg:address":"20 Salop Road",
    "sg:city":"Oswestry",
    "sg:classifiers":[
        {
            "category":"Real Estate",
            "subcategory":"Real Estate Agent",
            "type":"Services"
        }
    ],
    "sg:phone":"+44 1691 655334",
    "sg:postcode":"SY11 2NU",
    "sg:province":"Shropshire",
    "wof:name":"Dalton & Co",
    "wof:placetype":"venue"
},
  "geometry": {"coordinates":[-3.052325,52.858574],"type":"Point"}
}