{
  "type": "Feature",
  "properties": {
    "iso:country":"GB",
    "sg:address":"61 Rossall Road",
    "sg:city":"Thornton-cleveleys",
    "sg:classifiers":[
        {
            "category":"Fast Food",
            "type":"Food & Drink"
        },
        {
            "category":"Cafe",
            "type":"Food & Drink"
        }
    ],
    "sg:postcode":"FY5 1HG",
    "sg:province":"Lancashire",
    "sg:tags":[
        "snack",
        "bar",
        "room",
        "tea",
        "away",
        "take"
    ],
    "wof:name":"KATHLEEN WARREN",
    "wof:placetype":"venue"
},
  "geometry": {"coordinates":[-3.040027,53.883465],"type":"Point"}
}