{
  "type": "Feature",
  "properties": {
    "iso:country":"GB",
    "sg:address":"Unit 4 Builders Sq, Ct Hill Littlebourne",
    "sg:city":"Canterbury",
    "sg:classifiers":[
        {
            "category":"Shopping",
            "subcategory":"Stationery & Office Supplies",
            "type":"Retail Goods"
        }
    ],
    "sg:postcode":"CT3 1XU",
    "sg:province":"Kent",
    "sg:tags":[
        "drawing"
    ],
    "wof:name":"Farrow McCarthey",
    "wof:placetype":"venue"
},
  "geometry": {"coordinates":[1.1651849747,51.2733268738],"type":"Point"}
}