{
  "type": "Feature",
  "properties": {
    "addr:full":"Unit B Cannon Pk Clo Middlesbrough North Yorkshire TS1 5JX",
    "addr:postcode":"ts1 5jx",
    "addr:street":"Cannon",
    "iso:country":"GB",
    "sg:address":"Unit B Cannon Pk Clo",
    "sg:city":"Middlesbrough",
    "sg:classifiers":[
        {
            "category":"Home & Garden",
            "subcategory":"Furniture",
            "type":"Retail Goods"
        }
    ],
    "sg:postcode":"TS1 5JX",
    "sg:province":"North Yorkshire",
    "wof:name":"Conroy,Michael,",
    "wof:placetype":"venue"
},
  "geometry": {"coordinates":[-1.247794,54.574894],"type":"Point"}
}