{
  "type": "Feature",
  "properties": {
    "iso:country":"GB",
    "sg:address":"21 Dunyeats Rd",
    "sg:city":"Broadstone",
    "sg:classifiers":[
        {
            "category":"Community Center",
            "type":"Public Place"
        }
    ],
    "sg:phone":"+44 1202 658664",
    "sg:postcode":"BH18 8AB",
    "sg:province":"Dorset",
    "sg:tags":[
        "centre"
    ],
    "wof:name":"Broadstone Community & Arts Centre",
    "wof:placetype":"venue"
},
  "geometry": {"coordinates":[-1.9930759668,50.7625617981],"type":"Point"}
}