{
  "type": "Feature",
  "properties": {
    "addr:full":"25 Rockingham Avenue Hornchurch Essex RM11 1HH",
    "addr:housenumber":"25",
    "addr:postcode":"rm11 1hh",
    "addr:street":"Rockingham Avenue",
    "iso:country":"GB",
    "sg:address":"25 Rockingham Avenue",
    "sg:city":"Hornchurch",
    "sg:classifiers":[
        {
            "category":"Organizations",
            "subcategory":"Non-profit Organization",
            "type":"Services"
        }
    ],
    "sg:phone":"+44 1708 442844",
    "sg:postcode":"RM11 1HH",
    "sg:province":"Essex",
    "sg:tags":[
        "organisation",
        "voluntary",
        "charity"
    ],
    "wof:name":"Essex Association for Spina Bifida & Hydrocephalus",
    "wof:placetype":"venue"
},
  "geometry": {"coordinates":[0.204358995,51.5702629089],"type":"Point"}
}