{
  "type": "Feature",
  "properties": {
    "addr:full":"Hanbury Gardens, Pontnewynydd Pontypool Monmouthshire NP4 6JA",
    "addr:postcode":"np4 6ja",
    "addr:street":"Hanbury Gardens",
    "iso:country":"GB",
    "sg:address":"Hanbury Gardens, Pontnewynydd",
    "sg:city":"Pontypool",
    "sg:classifiers":[
        {
            "category":"Building & Trades",
            "subcategory":"Construction",
            "type":"Services"
        }
    ],
    "sg:phone":"+44 1495 759600",
    "sg:postcode":"NP4 6JA",
    "sg:province":"Monmouthshire",
    "sg:tags":[
        "builder"
    ],
    "wof:name":"D Lucas & Sons Ltd.",
    "wof:placetype":"venue"
},
  "geometry": {"coordinates":[-3.04319,51.703087],"type":"Point"}
}