{
  "type": "Feature",
  "properties": {
    "addr:full":"10 Ball Grove Drive Colne Lancashire BB8 7HY",
    "addr:housenumber":"10",
    "addr:postcode":"bb8 7hy",
    "addr:street":"Ball Grove Drive",
    "iso:country":"GB",
    "sg:address":"10 Ball Grove Drive",
    "sg:city":"Colne",
    "sg:classifiers":[
        {
            "category":"Professional",
            "subcategory":"Art Services",
            "type":"Services"
        },
        {
            "category":"Building & Trades",
            "subcategory":"Construction",
            "type":"Services"
        }
    ],
    "sg:phone":"+44 1282 865556",
    "sg:postcode":"BB8 7HY",
    "sg:province":"Lancashire",
    "sg:tags":[
        "decorator",
        "painter"
    ],
    "wof:name":"Peter French",
    "wof:placetype":"venue"
},
  "geometry": {"coordinates":[-2.14249897,53.8594512939],"type":"Point"}
}