{
  "type": "Feature",
  "properties": {
    "addr:full":"Lowood, Summerhill Newton Abbot Devon TQ12 6HD",
    "addr:postcode":"tq12 6hd",
    "addr:street":"Lowood",
    "iso:country":"GB",
    "sg:address":"Lowood, Summerhill",
    "sg:city":"Newton Abbot",
    "sg:classifiers":[
        {
            "category":"Building & Trades",
            "subcategory":"Pest Control",
            "type":"Services"
        }
    ],
    "sg:phone":"+44 1626 821396",
    "sg:postcode":"TQ12 6HD",
    "sg:province":"Devon",
    "sg:tags":[
        "vermin"
    ],
    "wof:name":"Antipest",
    "wof:placetype":"venue"
},
  "geometry": {"coordinates":[-3.6705989838,50.5607032776],"type":"Point"}
}