{
  "type": "Feature",
  "properties": {
    "iso:country":"GB",
    "sg:address":"Green Road, Upper Stratton",
    "sg:city":"Swindon",
    "sg:classifiers":[
        {
            "category":"Place Of Worship",
            "type":"Public Place"
        }
    ],
    "sg:phone":"+44 1793 831535",
    "sg:postcode":"SN2 7JA",
    "sg:province":"Wiltshire",
    "wof:name":"Upper Stratton baptist Church",
    "wof:placetype":"venue"
},
  "geometry": {"coordinates":[-1.766508,51.584045],"type":"Point"}
}