{
  "type": "Feature",
  "properties": {
    "addr:full":"Flash Lane, Bramley Rotherham South Yorkshire S66 0TY",
    "addr:postcode":"s66 0ty",
    "addr:street":"Flash Lane",
    "iso:country":"GB",
    "sg:address":"Flash Lane, Bramley",
    "sg:city":"Rotherham",
    "sg:classifiers":[
        {
            "category":"Government",
            "subcategory":"Office",
            "type":"Public Place"
        }
    ],
    "sg:phone":"+44 1709 546845",
    "sg:postcode":"S66 0TY",
    "sg:province":"South Yorkshire",
    "sg:tags":[
        "local"
    ],
    "wof:name":"The Lings Sheltered Housing",
    "wof:placetype":"venue"
},
  "geometry": {"coordinates":[-1.26698,53.437519],"type":"Point"}
}