{
  "type": "Feature",
  "properties": {
    "addr:full":"Newmarket Avenue Northolt Greater London UB5 4HB",
    "addr:postcode":"ub5 4hb",
    "addr:street":"Newmarket Avenue",
    "iso:country":"GB",
    "sg:address":"Newmarket Avenue",
    "sg:city":"Northolt",
    "sg:classifiers":[
        {
            "category":"Education",
            "subcategory":"School",
            "type":"Public Place"
        },
        {
            "category":"Government",
            "subcategory":"Office",
            "type":"Public Place"
        }
    ],
    "sg:phone":"+44 20 8422 4095",
    "sg:postcode":"UB5 4HB",
    "sg:province":"Greater London",
    "sg:tags":[
        "local",
        "authority"
    ],
    "wof:name":"Northolt Park Infant School",
    "wof:placetype":"venue"
},
  "geometry": {"coordinates":[-0.3636290133,51.5539855957],"type":"Point"}
}