{
  "type": "Feature",
  "properties": {
    "addr:full":"3 Lower Lane, Chinley High Peak Cheshire SK23 6BE",
    "addr:housenumber":"3",
    "addr:postcode":"sk23 6be",
    "addr:street":"Lower Lane",
    "iso:country":"GB",
    "sg:address":"3 Lower Lane, Chinley",
    "sg:city":"High Peak",
    "sg:classifiers":[
        {
            "category":"Social Services",
            "subcategory":"Retirement Home",
            "type":"Services"
        }
    ],
    "sg:phone":"+44 1663 750753",
    "sg:postcode":"SK23 6BE",
    "sg:province":"Cheshire",
    "sg:tags":[
        "care"
    ],
    "wof:name":"Alders Home Care",
    "wof:placetype":"venue"
},
  "geometry": {"coordinates":[-1.9405100346,53.3393783569],"type":"Point"}
}