{
  "type": "Feature",
  "properties": {
    "iso:country":"GB",
    "sg:address":"Sunrise House, Sherburn Road",
    "sg:city":"Durham",
    "sg:classifiers":[
        {
            "category":"Fast Food",
            "type":"Food & Drink"
        }
    ],
    "sg:phone":"+44 191 386 2337",
    "sg:postcode":"DH1 2ER",
    "sg:province":"Durham",
    "sg:tags":[
        "away",
        "meal",
        "outlet",
        "take"
    ],
    "wof:name":"Mr Cheng",
    "wof:placetype":"venue"
},
  "geometry": {"coordinates":[-1.555647,54.779015],"type":"Point"}
}