{
  "type": "Feature",
  "properties": {
    "addr:full":"25-27 Thanet Road Margate Kent CT9 1UA",
    "addr:housenumber":"25-27",
    "addr:postcode":"ct9 1ua",
    "addr:street":"Thanet Road",
    "iso:country":"GB",
    "sg:address":"25-27 Thanet Road",
    "sg:city":"Margate",
    "sg:classifiers":[
        {
            "category":"Farming",
            "subcategory":"Nursery",
            "type":"Manufacturing & Wholesale Goods"
        }
    ],
    "sg:phone":"+44 1843 294256",
    "sg:postcode":"CT9 1UA",
    "sg:province":"Kent",
    "sg:tags":[
        "creche"
    ],
    "wof:name":"First Step Nurseries",
    "wof:placetype":"venue"
},
  "geometry": {"coordinates":[1.388915,51.386417],"type":"Point"}
}