{
  "type": "Feature",
  "properties": {
    "addr:full":"Rose Cottage, Albury View Thame Buckinghamshire OX9 2NB",
    "addr:postcode":"ox9 2nb",
    "addr:street":"Albury View",
    "iso:country":"GB",
    "sg:address":"Rose Cottage, Albury View",
    "sg:city":"Thame",
    "sg:classifiers":[
        {
            "category":"Professional",
            "subcategory":"Art Services",
            "type":"Services"
        }
    ],
    "sg:postcode":"OX9 2NB",
    "sg:province":"Buckinghamshire",
    "sg:tags":[
        "photographer"
    ],
    "wof:name":"David Bryer Photography",
    "wof:placetype":"venue"
},
  "geometry": {"coordinates":[-1.0538439751,51.7425308228],"type":"Point"}
}