{
  "type": "Feature",
  "properties": {
    "iso:country":"GB",
    "sg:address":"Ellis Ashton Street",
    "sg:city":"Liverpool",
    "sg:classifiers":[
        {
            "category":"Utilities",
            "subcategory":"Refuse",
            "type":"Services"
        }
    ],
    "sg:phone":"+44 151 480 8100",
    "sg:postcode":"L36 6BN",
    "sg:province":"Merseyside",
    "sg:tags":[
        "disposal",
        "waste"
    ],
    "wof:name":"Mersey Waste Holdings Ltd.",
    "wof:placetype":"venue"
},
  "geometry": {"coordinates":[-2.825801,53.409492],"type":"Point"}
}