{
  "type": "Feature",
  "properties": {
    "addr:full":"Lundynant Caravan Site, St Minver Wadebridge Cornwall PL27 6QX",
    "addr:postcode":"pl27 6qx",
    "iso:country":"GB",
    "sg:address":"Lundynant Caravan Site, St Minver",
    "sg:city":"Wadebridge",
    "sg:classifiers":[
        {
            "category":"Recreation",
            "subcategory":"Campground",
            "type":"Entertainment"
        }
    ],
    "sg:phone":"+44 1208 862268",
    "sg:postcode":"PL27 6QX",
    "sg:province":"Cornwall",
    "sg:tags":[
        "caravan",
        "park"
    ],
    "wof:name":"Lundy Caravan Site",
    "wof:placetype":"venue"
},
  "geometry": {"coordinates":[-4.90541,50.577129],"type":"Point"}
}