{
  "type": "Feature",
  "properties": {
    "iso:country":"GB",
    "sg:address":"23 The Tanneries, Brockhampton Lane",
    "sg:city":"Havant",
    "sg:classifiers":[
        {
            "category":"Manufacturing",
            "subcategory":"Rubber & Plastics",
            "type":"Manufacturing & Wholesale Goods"
        }
    ],
    "sg:phone":"+44 23 9249 2907",
    "sg:postcode":"PO9 1JB",
    "sg:province":"Hampshire",
    "sg:tags":[
        "injection",
        "moulding"
    ],
    "wof:name":"Selsmore (Marketing) Ltd.",
    "wof:placetype":"venue"
},
  "geometry": {"coordinates":[-0.9884409904,50.850692749],"type":"Point"}
}