{
  "type": "Feature",
  "properties": {
    "iso:country":"GB",
    "sg:address":"Tayfen Rd",
    "sg:city":"Bury St Edmunds",
    "sg:classifiers":[
        {
            "category":"Autos & Motor Vehicles",
            "subcategory":"Fuel & Gas Station",
            "type":"Retail Goods"
        }
    ],
    "sg:phone":"+44 1284 750006",
    "sg:postcode":"IP33 1TB",
    "sg:province":"Suffolk",
    "sg:tags":[
        "petrol",
        "filling"
    ],
    "wof:name":"Tayfen Autopoint",
    "wof:placetype":"venue"
},
  "geometry": {"coordinates":[0.710725,52.250336],"type":"Point"}
}