{
  "type": "Feature",
  "properties": {
    "iso:country":"GB",
    "sg:address":"109 Westdale La",
    "sg:city":"Nottingham",
    "sg:classifiers":[
        {
            "category":"Manufacturing",
            "subcategory":"Glass & Minerals",
            "type":"Manufacturing & Wholesale Goods"
        }
    ],
    "sg:phone":"+44 115 952 6044",
    "sg:postcode":"NG4 3NX",
    "sg:province":"Nottinghamshire",
    "sg:tags":[
        "stained"
    ],
    "wof:name":"Westdale Studios",
    "wof:placetype":"venue"
},
  "geometry": {"coordinates":[-1.0878590345,52.9718513489],"type":"Point"}
}