{
  "type": "Feature",
  "properties": {
    "iso:country":"GB",
    "sg:address":"22 Greenway Close",
    "sg:city":"Liverpool",
    "sg:classifiers":[
        {
            "category":"Autos & Motor Vehicles",
            "subcategory":"Auto Supplies",
            "type":"Retail Goods"
        }
    ],
    "sg:phone":"+44 151 449 1565",
    "sg:postcode":"L36 2ND",
    "sg:province":"Merseyside",
    "sg:tags":[
        "windscreen"
    ],
    "wof:name":"Dial Relay Windscreens",
    "wof:placetype":"venue"
},
  "geometry": {"coordinates":[-2.861212,53.419189],"type":"Point"}
}