{
  "type": "Feature",
  "properties": {
    "iso:country":"GB",
    "sg:address":"39 Howden Hall Road",
    "sg:city":"Edinburgh",
    "sg:classifiers":[
        {
            "category":"Social Services",
            "type":"Services"
        }
    ],
    "sg:phone":"+44 131 664 8488",
    "sg:postcode":"EH16 6PG",
    "sg:province":"City of Edinburgh",
    "wof:name":"Howden Hall Children's Unit",
    "wof:placetype":"venue"
},
  "geometry": {"coordinates":[-3.175952,55.904182],"type":"Point"}
}