{
  "type": "Feature",
  "properties": {
    "addr:full":"27 Grove Park Terrace Bristol City of Bristol BS16 2BL",
    "addr:housenumber":"27",
    "addr:postcode":"bs16 2bl",
    "addr:street":"Grove Park Terrace",
    "iso:country":"GB",
    "sg:address":"27 Grove Park Terrace",
    "sg:city":"Bristol",
    "sg:classifiers":[
        {
            "category":"Retail",
            "subcategory":"Auto Repair",
            "type":"Services"
        }
    ],
    "sg:phone":"+44 117 965 2014",
    "sg:postcode":"BS16 2BL",
    "sg:province":"City of Bristol",
    "sg:tags":[
        "modification",
        "garage"
    ],
    "wof:name":"P G Autos",
    "wof:placetype":"venue"
},
  "geometry": {"coordinates":[-2.537949,51.478611],"type":"Point"}
}