{
  "type": "Feature",
  "properties": {
    "addr:full":"17 Melbourn Street Royston Bedfordshire SG8 7BP",
    "addr:housenumber":"17",
    "addr:postcode":"sg8 7bp",
    "addr:street":"Melbourn Street",
    "iso:country":"GB",
    "sg:address":"17 Melbourn Street",
    "sg:city":"Royston",
    "sg:classifiers":[
        {
            "category":"Real Estate",
            "subcategory":"Real Estate Operator",
            "type":"Services"
        }
    ],
    "sg:postcode":"SG8 7BP",
    "sg:province":"Bedfordshire",
    "sg:tags":[
        "letting",
        "agent"
    ],
    "wof:name":"Warners Letting Agency Ltd.",
    "wof:placetype":"venue"
},
  "geometry": {"coordinates":[-0.019039,52.050804],"type":"Point"}
}