{
  "type": "Feature",
  "properties": {
    "iso:country":"GB",
    "sg:address":"115 Oxford Road, Waterloo",
    "sg:city":"Liverpool",
    "sg:classifiers":[
        {
            "category":"Retail",
            "subcategory":"Repair Shop",
            "type":"Services"
        }
    ],
    "sg:postcode":"L22 7RE",
    "sg:province":"Merseyside",
    "sg:tags":[
        "radio",
        "television",
        "video"
    ],
    "wof:name":"Bensons Tv",
    "wof:placetype":"venue"
},
  "geometry": {"coordinates":[-3.0363490582,53.4800338745],"type":"Point"}
}