{
  "type": "Feature",
  "properties": {
    "addr:full":"31 Lime Street Bolton Lancashire BL4 8AF",
    "addr:housenumber":"31",
    "addr:postcode":"bl4 8af",
    "addr:street":"Lime Street",
    "iso:country":"GB",
    "sg:address":"31 Lime Street",
    "sg:city":"Bolton",
    "sg:classifiers":[
        {
            "category":"Building & Trades",
            "subcategory":"Plumbing",
            "type":"Services"
        }
    ],
    "sg:phone":"+44 1204 792693",
    "sg:postcode":"BL4 8AF",
    "sg:province":"Lancashire",
    "sg:tags":[
        "central",
        "heating"
    ],
    "wof:name":"P K Heating Services",
    "wof:placetype":"venue"
},
  "geometry": {"coordinates":[-2.3899049759,53.5490875244],"type":"Point"}
}