{
  "type": "Feature",
  "properties": {
    "addr:full":"166 New Road Brixham Devon TQ5 8DA",
    "addr:housenumber":"166",
    "addr:postcode":"tq5 8da",
    "addr:street":"New Road",
    "iso:country":"GB",
    "sg:address":"166 New Road",
    "sg:city":"Brixham",
    "sg:classifiers":[
        {
            "category":"Travel",
            "subcategory":"Hotels & Motels",
            "type":"Entertainment"
        }
    ],
    "sg:postcode":"TQ5 8DA",
    "sg:province":"Devon",
    "sg:tags":[
        "house",
        "guest"
    ],
    "wof:name":"Fairwinds",
    "wof:placetype":"venue"
},
  "geometry": {"coordinates":[-3.5271410942,50.3894920349],"type":"Point"}
}