{
  "type": "Feature",
  "properties": {
    "addr:full":"4 Far Bank, Shelley Huddersfield South Yorkshire HD8 8LA",
    "addr:housenumber":"4",
    "addr:postcode":"hd8 8la",
    "addr:street":"Far Bank",
    "iso:country":"GB",
    "sg:address":"4 Far Bank, Shelley",
    "sg:city":"Huddersfield",
    "sg:classifiers":[
        {
            "category":"Professional",
            "subcategory":"Printing & Photocopies",
            "type":"Services"
        }
    ],
    "sg:postcode":"HD8 8LA",
    "sg:province":"South Yorkshire",
    "sg:tags":[
        "trophy"
    ],
    "wof:name":"Astin's",
    "wof:placetype":"venue"
},
  "geometry": {"coordinates":[-1.6946129799,53.5973434448],"type":"Point"}
}