{
  "type": "Feature",
  "properties": {
    "addr:full":"30 Meadow Lane Loughborough Leicestershire LE11 1JY",
    "addr:housenumber":"30",
    "addr:postcode":"le11 1jy",
    "addr:street":"Meadow Lane",
    "iso:country":"GB",
    "sg:address":"30 Meadow Lane",
    "sg:city":"Loughborough",
    "sg:classifiers":[
        {
            "category":"Professional",
            "subcategory":"Art Services",
            "type":"Services"
        }
    ],
    "sg:postcode":"LE11 1JY",
    "sg:province":"Leicestershire",
    "sg:tags":[
        "photographer"
    ],
    "wof:name":"Jon Arnold Photographics",
    "wof:placetype":"venue"
},
  "geometry": {"coordinates":[-1.2025790215,52.7758178711],"type":"Point"}
}