{
  "type": "Feature",
  "properties": {
    "addr:full":"The Clock Tower, Compton Acres, West Bridgford Nottingham Nottinghamshire NG2 7PA",
    "addr:postcode":"ng2 7pa",
    "addr:street":"Compton Acres",
    "iso:country":"GB",
    "sg:address":"The Clock Tower, Compton Acres, West Bridgford",
    "sg:city":"Nottingham",
    "sg:classifiers":[
        {
            "category":"Farming",
            "subcategory":"Nursery",
            "type":"Manufacturing & Wholesale Goods"
        }
    ],
    "sg:phone":"+44 115 981 1801",
    "sg:postcode":"NG2 7PA",
    "sg:province":"Nottinghamshire",
    "sg:tags":[
        "creche"
    ],
    "wof:name":"Paper Moon Day Nursery",
    "wof:placetype":"venue"
},
  "geometry": {"coordinates":[-1.15398,52.92329],"type":"Point"}
}