{
  "type": "Feature",
  "properties": {
    "iso:country":"GB",
    "sg:address":"54-58 Clarence Street",
    "sg:city":"Cheltenham",
    "sg:classifiers":[
        {
            "category":"Sports & Exercise",
            "subcategory":"Gym",
            "type":"Entertainment"
        }
    ],
    "sg:phone":"+44 1242 578884",
    "sg:postcode":"GL50 3JL",
    "sg:province":"Gloucestershire",
    "sg:tags":[
        "fitness",
        "health",
        "centre"
    ],
    "wof:name":"Cloud 9 Ladies Health Club",
    "wof:placetype":"venue"
},
  "geometry": {"coordinates":[-2.079219,51.901482],"type":"Point"}
}