{
  "type": "Feature",
  "properties": {
    "addr:full":"12 Market Square, Aylesham Canterbury Kent CT3 3AA",
    "addr:housenumber":"12",
    "addr:postcode":"ct3 3aa",
    "addr:street":"Market Square",
    "iso:country":"GB",
    "sg:address":"12 Market Square, Aylesham",
    "sg:city":"Canterbury",
    "sg:classifiers":[
        {
            "category":"Shopping",
            "subcategory":"Pharmacy",
            "type":"Retail Goods"
        }
    ],
    "sg:phone":"+44 1304 840435",
    "sg:postcode":"CT3 3AA",
    "sg:province":"Kent",
    "sg:tags":[
        "pharmacist",
        "chemist"
    ],
    "wof:name":"E Moss Chemists",
    "wof:placetype":"venue"
},
  "geometry": {"coordinates":[1.2020590305,51.2251243591],"type":"Point"}
}