{
  "type": "Feature",
  "properties": {
    "iso:country":"GB",
    "sg:address":"14 Bevis Marks",
    "sg:city":"London",
    "sg:classifiers":[
        {
            "category":"Insurance",
            "subcategory":"Insurance Agent",
            "type":"Services"
        }
    ],
    "sg:phone":"+44 20 7556 7032",
    "sg:postcode":"EC3A 7NT",
    "sg:province":"Greater London",
    "sg:tags":[
        "broker"
    ],
    "wof:name":"Wbn Ltd.",
    "wof:placetype":"venue"
},
  "geometry": {"coordinates":[-0.078755,51.514553],"type":"Point"}
}