{
  "type": "Feature",
  "properties": {
    "addr:full":"18-30 Lakedale Road London Greater London SE18 1PP",
    "addr:housenumber":"18-30",
    "addr:postcode":"se18 1pp",
    "addr:street":"Lakedale Road",
    "iso:country":"GB",
    "sg:address":"18-30 Lakedale Road",
    "sg:city":"London",
    "sg:classifiers":[
        {
            "category":"Food & Beverages",
            "subcategory":"Groceries & Convenience Stores",
            "type":"Retail Goods"
        }
    ],
    "sg:phone":"+44 20 8854 0143",
    "sg:postcode":"SE18 1PP",
    "sg:province":"Greater London",
    "wof:name":"South East Co-Op",
    "wof:placetype":"venue"
},
  "geometry": {"coordinates":[0.091287002,51.4871101379],"type":"Point"}
}