{
  "type": "Feature",
  "properties": {
    "iso:country":"GB",
    "sg:address":"74 Warren Drive",
    "sg:city":"Hornchurch",
    "sg:classifiers":[
        {
            "category":"Retail",
            "subcategory":"Auto Repair",
            "type":"Services"
        }
    ],
    "sg:phone":"+44 1708 450614",
    "sg:postcode":"RM12 4QX",
    "sg:province":"Essex",
    "sg:tags":[
        "modification",
        "garage"
    ],
    "wof:name":"Eric J Heath & Son",
    "wof:placetype":"venue"
},
  "geometry": {"coordinates":[0.2021840066,51.5549659729],"type":"Point"}
}