{
  "type": "Feature",
  "properties": {
    "addr:full":"75 Leather Lane London Greater London EC1N 7TJ",
    "addr:housenumber":"75",
    "addr:postcode":"ec1n 7tj",
    "addr:street":"Leather Lane",
    "iso:country":"GB",
    "sg:address":"75 Leather Lane",
    "sg:city":"London",
    "sg:classifiers":[
        {
            "category":"Professional",
            "subcategory":"Art Services",
            "type":"Services"
        }
    ],
    "sg:postcode":"EC1N 7TJ",
    "sg:province":"Greater London",
    "sg:tags":[
        "framing"
    ],
    "wof:name":"The London Picture Centre",
    "wof:placetype":"venue"
},
  "geometry": {"coordinates":[-0.1095720008,51.5210723877],"type":"Point"}
}