{
  "type": "Feature",
  "properties": {
    "iso:country":"GB",
    "sg:address":"Hope Street",
    "sg:city":"Leigh",
    "sg:classifiers":[
        {
            "category":"Professional",
            "subcategory":"Printing & Photocopies",
            "type":"Services"
        }
    ],
    "sg:phone":"+44 1942 673166",
    "sg:postcode":"WN7 1AJ",
    "sg:province":"Lancashire",
    "sg:tags":[
        "printer"
    ],
    "wof:name":"Collins & Darwell Ltd.",
    "wof:placetype":"venue"
},
  "geometry": {"coordinates":[-2.5164589882,53.5050163269],"type":"Point"}
}