{
  "type": "Feature",
  "properties": {
    "iso:country":"GB",
    "sg:address":"Chapel Street, Oswaldtwistle",
    "sg:city":"Accrington",
    "sg:classifiers":[
        {
            "category":"Place Of Worship",
            "type":"Public Place"
        }
    ],
    "sg:phone":"+44 1254 233843",
    "sg:postcode":"BB5 3EP",
    "sg:province":"Lancashire",
    "wof:name":"Rhyddings Methodist Church",
    "wof:placetype":"venue"
},
  "geometry": {"coordinates":[-2.3941979408,53.744392395],"type":"Point"}
}