{
  "type": "Feature",
  "properties": {
    "addr:full":"Wimpory Street, Openshaw Manchester Greater Manchester M11 2NU",
    "addr:postcode":"m11 2nu",
    "addr:street":"Wimpory Street",
    "iso:country":"GB",
    "sg:address":"Wimpory Street, Openshaw",
    "sg:city":"Manchester",
    "sg:classifiers":[
        {
            "category":"Wholesale",
            "subcategory":"Chemicals & Plastics",
            "type":"Manufacturing & Wholesale Goods"
        }
    ],
    "sg:phone":"+44 161 223 9299",
    "sg:postcode":"M11 2NU",
    "sg:province":"Greater Manchester",
    "sg:tags":[
        "product",
        "allied"
    ],
    "wof:name":"Milchem Ltd.",
    "wof:placetype":"venue"
},
  "geometry": {"coordinates":[-2.1721639633,53.4715309143],"type":"Point"}
}