{
  "type": "Feature",
  "properties": {
    "iso:country":"GB",
    "sg:address":"7 Sandys Row",
    "sg:city":"London",
    "sg:classifiers":[
        {
            "category":"Professional",
            "subcategory":"Accounting & Tax Preparation",
            "type":"Services"
        },
        {
            "category":"Professional",
            "subcategory":"Lawyer & Legal Services",
            "type":"Services"
        }
    ],
    "sg:postcode":"E1 7HW",
    "sg:province":"Greater London",
    "sg:tags":[
        "accountant",
        "solicitor"
    ],
    "wof:name":"Key Legal Accounting Services Ltd.",
    "wof:placetype":"venue"
},
  "geometry": {"coordinates":[-0.077522,51.518009],"type":"Point"}
}