{
  "type": "Feature",
  "properties": {
    "addr:full":"Lindon House, West Grange Dunfermline Fife KY12 8EL",
    "addr:postcode":"ky12 8el",
    "addr:street":"West Grange Dunfermline",
    "iso:country":"GB",
    "sg:address":"Lindon House, West Grange",
    "sg:city":"Dunfermline",
    "sg:classifiers":[
        {
            "category":"Building & Trades",
            "subcategory":"Construction",
            "type":"Services"
        }
    ],
    "sg:phone":"+44 1383 851174",
    "sg:postcode":"KY12 8EL",
    "sg:province":"Fife",
    "sg:tags":[
        "window",
        "replacement"
    ],
    "wof:name":"Scottish Window Repair & Home Improvement Services",
    "wof:placetype":"venue"
},
  "geometry": {"coordinates":[-3.6318120956,56.0555801392],"type":"Point"}
}