{
  "type": "Feature",
  "properties": {
    "addr:full":"Byde Farm Devizes Wiltshire SN10 3HS",
    "addr:postcode":"sn10 3hs",
    "iso:country":"GB",
    "sg:address":"Byde Farm",
    "sg:city":"Devizes",
    "sg:classifiers":[
        {
            "category":"Military Area",
            "subcategory":"Army Base",
            "type":"Public Place"
        }
    ],
    "sg:postcode":"SN10 3HS",
    "sg:province":"Wiltshire",
    "sg:tags":[
        "joinery",
        "centre"
    ],
    "wof:name":"The Byde Farm Joinery Co.",
    "wof:placetype":"venue"
},
  "geometry": {"coordinates":[-1.9781130552,51.352432251],"type":"Point"}
}