{
  "type": "Feature",
  "properties": {
    "addr:full":"2nd Floor, 25 Micklegate York North Yorkshire YO1 6JH",
    "addr:housenumber":"2nd floor 25",
    "addr:postcode":"yo1 6jh",
    "addr:street":"Micklegate",
    "iso:country":"GB",
    "sg:address":"2nd Floor, 25 Micklegate",
    "sg:city":"York",
    "sg:classifiers":[
        {
            "category":"Professional",
            "subcategory":"Lawyer & Legal Services",
            "type":"Services"
        }
    ],
    "sg:phone":"+44 1904 644916",
    "sg:postcode":"YO1 6JH",
    "sg:province":"North Yorkshire",
    "sg:tags":[
        "advice",
        "counselling"
    ],
    "wof:name":"Relate",
    "wof:placetype":"venue"
},
  "geometry": {"coordinates":[-1.0860780478,53.9571723938],"type":"Point"}
}