{
  "type": "Feature",
  "properties": {
    "iso:country":"GB",
    "sg:address":"92 Bath Street",
    "sg:city":"Birmingham",
    "sg:classifiers":[
        {
            "category":"Bars & Pubs",
            "type":"Food & Drink"
        },
        {
            "category":"Community Center",
            "subcategory":"Social",
            "type":"Public Place"
        }
    ],
    "sg:phone":"+44 121 236 1201",
    "sg:postcode":"B4 6HG",
    "sg:province":"West Midlands",
    "sg:tags":[
        "pubs",
        "house",
        "inn",
        "activity"
    ],
    "wof:name":"The Gunmakers Arms",
    "wof:placetype":"venue"
},
  "geometry": {"coordinates":[-1.896369,52.486549],"type":"Point"}
}