{
  "type": "Feature",
  "properties": {
    "iso:country":"GB",
    "sg:address":"292 Walton Rd",
    "sg:city":"West Molesey",
    "sg:classifiers":[
        {
            "category":"Autos & Motor Vehicles",
            "subcategory":"Automobile Sales",
            "type":"Retail Goods"
        }
    ],
    "sg:phone":"+44 20 8979 3322",
    "sg:postcode":"KT8 2JG",
    "sg:province":"Greater London",
    "sg:tags":[
        "car"
    ],
    "wof:name":"Hampton Court Suzuki",
    "wof:placetype":"venue"
},
  "geometry": {"coordinates":[-0.3617770076,51.4013366699],"type":"Point"}
}