{
  "type": "Feature",
  "properties": {
    "addr:full":"Kings Saltern Road Lymington Hampshire SO41 3QD",
    "addr:postcode":"so41 3qd",
    "addr:street":"Saltern Road",
    "iso:country":"GB",
    "sg:address":"Kings Saltern Road",
    "sg:city":"Lymington",
    "sg:classifiers":[
        {
            "category":"Travel",
            "subcategory":"Hotels & Motels",
            "type":"Entertainment"
        }
    ],
    "sg:phone":"+44 1590 672160",
    "sg:postcode":"SO41 3QD",
    "sg:province":"Hampshire",
    "sg:tags":[
        "house",
        "guest"
    ],
    "wof:name":"The Mayflower Hotel",
    "wof:placetype":"venue"
},
  "geometry": {"coordinates":[-1.530159,50.753929],"type":"Point"}
}