{
  "type": "Feature",
  "properties": {
    "iso:country":"GB",
    "sg:address":"The Broadway, Minster On Sea",
    "sg:city":"Sheerness",
    "sg:classifiers":[
        {
            "category":"Travel",
            "subcategory":"Hotels & Motels",
            "type":"Entertainment"
        }
    ],
    "sg:postcode":"ME12 2DA",
    "sg:province":"Kent",
    "wof:name":"The Abbey Hotel",
    "wof:placetype":"venue"
},
  "geometry": {"coordinates":[0.764665,51.43885],"type":"Point"}
}