{
  "type": "Feature",
  "properties": {
    "iso:country":"GB",
    "sg:address":"36 Swan Lane",
    "sg:city":"Evesham",
    "sg:classifiers":[
        {
            "category":"Farming",
            "subcategory":"Nursery",
            "type":"Manufacturing & Wholesale Goods"
        }
    ],
    "sg:phone":"+44 1386 765446",
    "sg:postcode":"WR11 4PA",
    "sg:province":"Gloucestershire",
    "sg:tags":[
        "creche"
    ],
    "wof:name":"Cygnets Day Nursery",
    "wof:placetype":"venue"
},
  "geometry": {"coordinates":[-1.952314,52.092735],"type":"Point"}
}