{
  "type": "Feature",
  "properties": {
    "addr:full":"2 Heyrod Street, Ancoats Manchester Greater Manchester M1 2WW",
    "addr:housenumber":"2",
    "addr:postcode":"m1 2ww",
    "addr:street":"Heyrod Street",
    "iso:country":"GB",
    "sg:address":"2 Heyrod Street, Ancoats",
    "sg:city":"Manchester",
    "sg:classifiers":[
        {
            "category":"Professional",
            "subcategory":"Advertising",
            "type":"Services"
        },
        {
            "category":"Professional",
            "subcategory":"Printing & Photocopies",
            "type":"Services"
        }
    ],
    "sg:phone":"+44 161 273 5562",
    "sg:postcode":"M1 2WW",
    "sg:province":"Greater Manchester",
    "sg:tags":[
        "screen",
        "printer"
    ],
    "sg:website":"http://www.gbm.co.uk",
    "wof:name":"G B M Group Plc",
    "wof:placetype":"venue"
},
  "geometry": {"coordinates":[-2.2238938808,53.4785118103],"type":"Point"}
}