{
  "type": "Feature",
  "properties": {
    "addr:full":"Felin, Penrhyncoch Aberystwyth Ceredigion SY23 3EW",
    "addr:postcode":"sy23 3ew",
    "addr:street":"Felin",
    "iso:country":"GB",
    "sg:address":"Felin, Penrhyncoch",
    "sg:city":"Aberystwyth",
    "sg:classifiers":[
        {
            "category":"Building & Trades",
            "subcategory":"Construction",
            "type":"Services"
        }
    ],
    "sg:phone":"+44 1970 828405",
    "sg:postcode":"SY23 3EW",
    "sg:province":"Ceredigion",
    "sg:tags":[
        "builder"
    ],
    "wof:name":"Thomas Bros",
    "wof:placetype":"venue"
},
  "geometry": {"coordinates":[-3.996181,52.437813],"type":"Point"}
}