{
  "type": "Feature",
  "properties": {
    "iso:country":"GB",
    "sg:address":"2a Stamford Rd",
    "sg:city":"Birmingham",
    "sg:classifiers":[
        {
            "category":"Building & Trades",
            "subcategory":"Construction",
            "type":"Services"
        }
    ],
    "sg:phone":"+44 121 554 3198",
    "sg:postcode":"B20 3PJ",
    "sg:province":"West Midlands",
    "sg:tags":[
        "builder"
    ],
    "wof:name":"G.W Hughes",
    "wof:placetype":"venue"
},
  "geometry": {"coordinates":[-1.9086669683,52.5081253052],"type":"Point"}
}