{
  "type": "Feature",
  "properties": {
    "iso:country":"GB",
    "sg:address":"38 South Street",
    "sg:city":"Exeter",
    "sg:classifiers":[
        {
            "category":"Shopping",
            "subcategory":"Pharmacy",
            "type":"Retail Goods"
        }
    ],
    "sg:postcode":"EX1 1ED",
    "sg:province":"Devon",
    "sg:tags":[
        "medicine",
        "therapy"
    ],
    "wof:name":"School of Complementary Therapies",
    "wof:placetype":"venue"
},
  "geometry": {"coordinates":[-3.5296869278,50.7203292847],"type":"Point"}
}