{
  "type": "Feature",
  "properties": {
    "iso:country":"GB",
    "sg:address":"Abbey Walk",
    "sg:city":"Cambridge",
    "sg:classifiers":[
        {
            "category":"Wholesale",
            "subcategory":"Non-durable Goods",
            "type":"Manufacturing & Wholesale Goods"
        }
    ],
    "sg:phone":"+44 1223 566386",
    "sg:postcode":"CB1 2QJ",
    "sg:province":"Cambridgeshire",
    "sg:tags":[
        "carry",
        "cash"
    ],
    "wof:name":"Packets Wholesale",
    "wof:placetype":"venue"
},
  "geometry": {"coordinates":[0.1401479989,52.2060241699],"type":"Point"}
}