{
  "type": "Feature",
  "properties": {
    "addr:full":"7 Woodlands Green Harrogate North Yorkshire HG2 8QD",
    "addr:housenumber":"7",
    "addr:postcode":"hg2 8qd",
    "addr:street":"Woodlands Green",
    "iso:country":"GB",
    "sg:address":"7 Woodlands Green",
    "sg:city":"Harrogate",
    "sg:classifiers":[
        {
            "category":"Building & Trades",
            "subcategory":"Construction",
            "type":"Services"
        }
    ],
    "sg:phone":"+44 1423 884266",
    "sg:postcode":"HG2 8QD",
    "sg:province":"North Yorkshire",
    "sg:tags":[
        "equipment"
    ],
    "wof:name":"Atlam International Cranes",
    "wof:placetype":"venue"
},
  "geometry": {"coordinates":[-1.5086610317,53.9861488342],"type":"Point"}
}