{
  "type": "Feature",
  "properties": {
    "addr:full":"1 Charlotte Street Blackburn Lancashire BB1 7LE",
    "addr:housenumber":"1",
    "addr:postcode":"bb1 7le",
    "addr:street":"Charlotte Street",
    "iso:country":"GB",
    "sg:address":"1 Charlotte Street",
    "sg:city":"Blackburn",
    "sg:classifiers":[
        {
            "category":"Fast Food",
            "type":"Food & Drink"
        },
        {
            "category":"Food & Beverages",
            "subcategory":"Bakery",
            "type":"Retail Goods"
        },
        {
            "category":"Wholesale",
            "subcategory":"Groceries",
            "type":"Manufacturing & Wholesale Goods"
        }
    ],
    "sg:phone":"+44 1254 689494",
    "sg:postcode":"BB1 7LE",
    "sg:province":"Lancashire",
    "sg:tags":[
        "supplier",
        "away",
        "take",
        "pizza"
    ],
    "wof:name":"Pizza Island",
    "wof:placetype":"venue"
},
  "geometry": {"coordinates":[-2.483039,53.753471],"type":"Point"}
}