{
  "type": "Feature",
  "properties": {
    "addr:full":"11 Beech Avenue Upminster Essex RM14 2HW",
    "addr:housenumber":"11",
    "addr:postcode":"rm14 2hw",
    "addr:street":"Beech Avenue",
    "iso:country":"GB",
    "sg:address":"11 Beech Avenue",
    "sg:city":"Upminster",
    "sg:classifiers":[
        {
            "category":"Parking",
            "type":"Transportation"
        }
    ],
    "sg:phone":"+44 1708 226023",
    "sg:postcode":"RM14 2HW",
    "sg:province":"Essex",
    "sg:tags":[
        "car",
        "valet"
    ],
    "wof:name":"Ultra Valet",
    "wof:placetype":"venue"
},
  "geometry": {"coordinates":[0.2441640049,51.5515174866],"type":"Point"}
}