{
  "type": "Feature",
  "properties": {
    "iso:country":"GB",
    "sg:address":"22 The Park, Rottingdean",
    "sg:city":"Brighton",
    "sg:classifiers":[
        {
            "category":"Building & Trades",
            "subcategory":"Construction",
            "type":"Services"
        }
    ],
    "sg:postcode":"BN2 7GQ",
    "sg:province":"East Sussex",
    "sg:tags":[
        "roofing"
    ],
    "wof:name":"Graham Buxton Building Maintenance",
    "wof:placetype":"venue"
},
  "geometry": {"coordinates":[-0.049902,50.803299],"type":"Point"}
}