{
  "type": "Feature",
  "properties": {
    "iso:country":"GB",
    "sg:address":"14 Woodley Precinct",
    "sg:city":"Stockport",
    "sg:classifiers":[
        {
            "category":"Home & Garden",
            "subcategory":"Hardware",
            "type":"Retail Goods"
        }
    ],
    "sg:phone":"+44 161 494 8124",
    "sg:postcode":"SK6 1RJ",
    "sg:province":"Cheshire",
    "wof:name":"Woodley Hardware",
    "wof:placetype":"venue"
},
  "geometry": {"coordinates":[-2.102465,53.425884],"type":"Point"}
}