{
  "type": "Feature",
  "properties": {
    "addr:full":"17 The Street, Rayne Braintree Essex CM77 6RW",
    "addr:housenumber":"17",
    "addr:postcode":"cm77 6rw",
    "addr:street":"The Street",
    "iso:country":"GB",
    "sg:address":"17 The Street, Rayne",
    "sg:city":"Braintree",
    "sg:classifiers":[
        {
            "category":"Restaurant",
            "type":"Food & Drink"
        }
    ],
    "sg:phone":"+44 1376 322290",
    "sg:postcode":"CM77 6RW",
    "sg:province":"Essex",
    "sg:tags":[
        "indian"
    ],
    "wof:name":"Tandoori Cottage",
    "wof:placetype":"venue"
},
  "geometry": {"coordinates":[0.510009,51.875626],"type":"Point"}
}