{
  "type": "Feature",
  "properties": {
    "iso:country":"GB",
    "sg:address":"Unit 9, Headlands Business Park, Salisbury Road, Blashford",
    "sg:city":"Ringwood",
    "sg:classifiers":[
        {
            "category":"Professional",
            "subcategory":"Management & Consulting",
            "type":"Services"
        },
        {
            "category":"Shopping",
            "subcategory":"Books",
            "type":"Retail Goods"
        }
    ],
    "sg:phone":"+44 1425 471160",
    "sg:postcode":"BH24 3PB",
    "sg:province":"Dorset",
    "sg:tags":[
        "consultant",
        "retailer",
        "business"
    ],
    "wof:name":"Coutts Library Services U K",
    "wof:placetype":"venue"
},
  "geometry": {"coordinates":[-1.7929890156,50.8463287354],"type":"Point"}
}