{
  "type": "Feature",
  "properties": {
    "addr:full":"10 Fuschia Close, Priorslee Telford Shropshire TF2 9PG",
    "addr:housenumber":"10",
    "addr:postcode":"tf2 9pg",
    "addr:street":"Fuschia Close",
    "iso:country":"GB",
    "sg:address":"10 Fuschia Close, Priorslee",
    "sg:city":"Telford",
    "sg:classifiers":[
        {
            "category":"Building & Trades",
            "subcategory":"Construction",
            "type":"Services"
        }
    ],
    "sg:phone":"+44 1952 293939",
    "sg:postcode":"TF2 9PG",
    "sg:province":"Shropshire",
    "sg:tags":[
        "builder"
    ],
    "wof:name":"R & R Services",
    "wof:placetype":"venue"
},
  "geometry": {"coordinates":[-2.421151,52.68782],"type":"Point"}
}