{
  "type": "Feature",
  "properties": {
    "iso:country":"GB",
    "sg:address":"2-3 Victoria Street",
    "sg:city":"Luton",
    "sg:classifiers":[
        {
            "category":"Utilities",
            "subcategory":"Mobile Phone",
            "type":"Services"
        },
        {
            "category":"Professional",
            "subcategory":"Business Services",
            "type":"Services"
        }
    ],
    "sg:phone":"+44 1582 434000",
    "sg:postcode":"LU1 2UA",
    "sg:province":"Bedfordshire",
    "sg:tags":[
        "answering",
        "telephone"
    ],
    "wof:name":"Nestor Primecare Services Ltd.",
    "wof:placetype":"venue"
},
  "geometry": {"coordinates":[-0.416264,51.876534],"type":"Point"}
}