{
  "type": "Feature",
  "properties": {
    "addr:full":"13-15 Railway Street Chatham Kent ME4 4HX",
    "addr:housenumber":"13-15",
    "addr:postcode":"me4 4hx",
    "addr:street":"Railway Street",
    "iso:country":"GB",
    "sg:address":"13-15 Railway Street",
    "sg:city":"Chatham",
    "sg:classifiers":[
        {
            "category":"Banks & Credit Unions",
            "subcategory":"Financial Services",
            "type":"Services"
        }
    ],
    "sg:phone":"+44 1634 819897",
    "sg:postcode":"ME4 4HX",
    "sg:province":"Kent",
    "sg:tags":[
        "consultant"
    ],
    "wof:name":"Avco Trust",
    "wof:placetype":"venue"
},
  "geometry": {"coordinates":[0.52303,51.382118],"type":"Point"}
}