{
  "type": "Feature",
  "properties": {
    "iso:country":"GB",
    "sg:address":"Portsmouth Road",
    "sg:city":"Camberley",
    "sg:classifiers":[
        {
            "category":"Health Services",
            "subcategory":"Nursing And Care Facility",
            "type":"Services"
        }
    ],
    "sg:phone":"+44 1276 670700",
    "sg:postcode":"GU15 1LD",
    "sg:province":"Berkshire",
    "sg:tags":[
        "home"
    ],
    "wof:name":"Collingwood Grange",
    "wof:placetype":"venue"
},
  "geometry": {"coordinates":[-0.716799,51.345421],"type":"Point"}
}