{
  "type": "Feature",
  "properties": {
    "addr:full":"1 Coldstream Place Bideford Devon EX39 3BP",
    "addr:housenumber":"1",
    "addr:postcode":"ex39 3bp",
    "addr:street":"Coldstream Place",
    "iso:country":"GB",
    "sg:address":"1 Coldstream Place",
    "sg:city":"Bideford",
    "sg:classifiers":[
        {
            "category":"Shopping",
            "subcategory":"Department Store",
            "type":"Retail Goods"
        },
        {
            "category":"Food & Beverages",
            "subcategory":"Groceries & Convenience Stores",
            "type":"Retail Goods"
        }
    ],
    "sg:phone":"+44 1237 472316",
    "sg:postcode":"EX39 3BP",
    "sg:province":"Devon",
    "wof:name":"Coldstream Stores",
    "wof:placetype":"venue"
},
  "geometry": {"coordinates":[-4.2042589188,51.0192489624],"type":"Point"}
}