{
  "type": "Feature",
  "properties": {
    "iso:country":"GB",
    "sg:address":"30 Bishop Road",
    "sg:city":"Bristol",
    "sg:classifiers":[
        {
            "category":"Health Services",
            "subcategory":"Health Practitioner",
            "type":"Services"
        }
    ],
    "sg:phone":"+44 117 942 6810",
    "sg:postcode":"BS7 8LT",
    "sg:province":"City of Bristol",
    "sg:tags":[
        "homoeopathic"
    ],
    "wof:name":"Gordon Dsh Adam Rs Hom",
    "wof:placetype":"venue"
},
  "geometry": {"coordinates":[-2.593168,51.479305],"type":"Point"}
}