{
  "type": "Feature",
  "properties": {
    "addr:full":"67 Kenneth Street Inverness Highland IV3 5QF",
    "addr:housenumber":"67",
    "addr:postcode":"iv3 5qf",
    "addr:street":"Kenneth Street",
    "iso:country":"GB",
    "sg:address":"67 Kenneth Street",
    "sg:city":"Inverness",
    "sg:classifiers":[
        {
            "category":"Communications",
            "type":"Services"
        }
    ],
    "sg:phone":"+44 1463 224788",
    "sg:postcode":"IV3 5QF",
    "sg:province":"Highland",
    "sg:tags":[
        "audio-visual"
    ],
    "wof:name":"H C V F (Inverness) Ltd.",
    "wof:placetype":"venue"
},
  "geometry": {"coordinates":[-4.2356410027,57.4788360596],"type":"Point"}
}