{
  "type": "Feature",
  "properties": {
    "addr:full":"Po Box 1017 Cooks Lane, Kingshurst Birmingham West Midlands B37 6NZ",
    "addr:housenumber":"po",
    "addr:postcode":"b37 6nz",
    "addr:street":"Box 1017 Cooks Lane",
    "iso:country":"GB",
    "sg:address":"Po Box 1017 Cooks Lane, Kingshurst",
    "sg:city":"Birmingham",
    "sg:classifiers":[
        {
            "category":"Education",
            "subcategory":"College",
            "type":"Public Place"
        }
    ],
    "sg:postcode":"B37 6NZ",
    "sg:province":"West Midlands",
    "sg:tags":[
        "technical",
        "agricultural"
    ],
    "wof:name":"The City Technology College Kingshurst",
    "wof:placetype":"venue"
},
  "geometry": {"coordinates":[-1.752429,52.485275],"type":"Point"}
}