{
  "type": "Feature",
  "properties": {
    "addr:full":"11 St Thomas Street Lymington Hampshire SO41 9NA",
    "addr:housenumber":"11",
    "addr:postcode":"so41 9na",
    "addr:street":"St Thomas Street",
    "iso:country":"GB",
    "sg:address":"11 St Thomas Street",
    "sg:city":"Lymington",
    "sg:classifiers":[
        {
            "category":"Shopping",
            "subcategory":"Books",
            "type":"Retail Goods"
        }
    ],
    "sg:phone":"+44 1590 679710",
    "sg:postcode":"SO41 9NA",
    "sg:province":"Hampshire",
    "sg:tags":[
        "bookseller"
    ],
    "wof:name":"Archway Christian Book & Coffee Shop (The)",
    "wof:placetype":"venue"
},
  "geometry": {"coordinates":[-1.5480999947,50.7576942444],"type":"Point"}
}