{
  "type": "Feature",
  "properties": {
    "addr:full":"43 Highwood Rd, Roselands Est Hoddesdon Essex EN11 9AP",
    "addr:housenumber":"43",
    "addr:postcode":"en11 9ap",
    "addr:street":"Highwood Rd",
    "iso:country":"GB",
    "sg:address":"43 Highwood Rd, Roselands Est",
    "sg:city":"Hoddesdon",
    "sg:classifiers":[
        {
            "category":"Social Services",
            "subcategory":"Adult Care",
            "type":"Services"
        }
    ],
    "sg:phone":"+44 1992 302247",
    "sg:postcode":"EN11 9AP",
    "sg:province":"Essex",
    "sg:tags":[
        "domestic",
        "cleaning"
    ],
    "wof:name":"Loyal Cleaning Services Ltd",
    "wof:placetype":"venue"
},
  "geometry": {"coordinates":[-0.019081,51.773289],"type":"Point"}
}