{
  "type": "Feature",
  "properties": {
    "iso:country":"GB",
    "sg:address":"Packers House",
    "sg:city":"Hereford",
    "sg:classifiers":[
        {
            "category":"Insurance",
            "subcategory":"Insurance Agent",
            "type":"Services"
        }
    ],
    "sg:phone":"+44 1432 276060",
    "sg:postcode":"HR4 0BX",
    "sg:province":"Herefordshire",
    "sg:tags":[
        "broker"
    ],
    "wof:name":"W J Bond (Hereford) Ltd.",
    "wof:placetype":"venue"
},
  "geometry": {"coordinates":[-2.731761,52.059204],"type":"Point"}
}