{
  "type": "Feature",
  "properties": {
    "iso:country":"GB",
    "sg:address":"272b Manchester Road, Isle Of Dogs",
    "sg:city":"London",
    "sg:classifiers":[
        {
            "category":"Communications",
            "subcategory":"Film & Video Production",
            "type":"Services"
        },
        {
            "category":"Communications",
            "type":"Services"
        }
    ],
    "sg:phone":"+44 20 7538 1732",
    "sg:postcode":"E14 3HW",
    "sg:province":"Greater London",
    "sg:tags":[
        "audio/visual",
        "audio-visual"
    ],
    "wof:name":"Group Artists",
    "wof:placetype":"venue"
},
  "geometry": {"coordinates":[-0.008041,51.494133],"type":"Point"}
}