{
  "type": "Feature",
  "properties": {
    "iso:country":"GB",
    "sg:address":"Brunel House, Farfield Park, Manvers",
    "sg:city":"Rotherham",
    "sg:classifiers":[
        {
            "category":"Ferry Terminal",
            "type":"Transportation"
        }
    ],
    "sg:phone":"+44 1709 763500",
    "sg:postcode":"S63 5DB",
    "sg:province":"South Yorkshire",
    "sg:tags":[
        "freezer",
        "refrigerator"
    ],
    "wof:name":"Delfield Technologies Ltd.",
    "wof:placetype":"venue"
},
  "geometry": {"coordinates":[-1.32476,53.503769],"type":"Point"}
}