{
  "type": "Feature",
  "properties": {
    "addr:full":"11 Southwood Dr, Caistor St Edmund Norwich Norfolk NR14 8RA",
    "addr:housenumber":"11",
    "addr:postcode":"nr14 8ra",
    "addr:street":"Southwood Dr Caistor St;Norwich",
    "iso:country":"GB",
    "sg:address":"11 Southwood Dr, Caistor St Edmund",
    "sg:city":"Norwich",
    "sg:classifiers":[
        {
            "category":"Organizations",
            "subcategory":"Political Organization",
            "type":"Services"
        }
    ],
    "sg:phone":"+44 1508 494152",
    "sg:postcode":"NR14 8RA",
    "sg:province":"Norfolk",
    "sg:tags":[
        "party"
    ],
    "wof:name":"Liberal Democrats",
    "wof:placetype":"venue"
},
  "geometry": {"coordinates":[1.3252999783,52.5809440613],"type":"Point"}
}