{
  "type": "Feature",
  "properties": {
    "iso:country":"GB",
    "sg:address":"2 Compstall Road, Romiley",
    "sg:city":"Stockport",
    "sg:classifiers":[
        {
            "category":"Professional",
            "subcategory":"Employment Agencies",
            "type":"Services"
        }
    ],
    "sg:phone":"+44 161 406 6868",
    "sg:postcode":"SK6 4DS",
    "sg:province":"Cheshire",
    "sg:tags":[
        "consultant"
    ],
    "wof:name":"Page & Sambrook Technical Services Ltd.",
    "wof:placetype":"venue"
},
  "geometry": {"coordinates":[-2.0880539417,53.4138183594],"type":"Point"}
}