{
  "type": "Feature",
  "properties": {
    "iso:country":"GB",
    "sg:address":"44 High Street",
    "sg:city":"Runcorn",
    "sg:classifiers":[
        {
            "category":"Restaurant",
            "type":"Food & Drink"
        }
    ],
    "sg:postcode":"WA7 1AW",
    "sg:province":"Cheshire",
    "sg:tags":[
        "indian"
    ],
    "wof:name":"Myers Balti House Restaurant",
    "wof:placetype":"venue"
},
  "geometry": {"coordinates":[-2.734361,53.341232],"type":"Point"}
}