{
  "type": "Feature",
  "properties": {
    "addr:full":"Ashbourne House, 23 Ashbourne Road Derby Derbyshire DE22 3FQ",
    "addr:housenumber":"23",
    "addr:postcode":"de22 3fq",
    "addr:street":"Ashbourne Road",
    "iso:country":"GB",
    "sg:address":"Ashbourne House, 23 Ashbourne Road",
    "sg:city":"Derby",
    "sg:classifiers":[
        {
            "category":"Organizations",
            "subcategory":"Political Organization",
            "type":"Services"
        }
    ],
    "sg:phone":"+44 1332 344856",
    "sg:postcode":"DE22 3FQ",
    "sg:province":"Derbyshire",
    "sg:tags":[
        "party"
    ],
    "wof:name":"Derby North Conservative Association",
    "wof:placetype":"venue"
},
  "geometry": {"coordinates":[-1.492159,52.92551],"type":"Point"}
}