{
  "type": "Feature",
  "properties": {
    "addr:full":"4 Wrenmere Clo Sandbach Cheshire CW11 1XS",
    "addr:housenumber":"4",
    "addr:postcode":"cw11 1xs",
    "addr:street":"Wrenmere Clo",
    "iso:country":"GB",
    "sg:address":"4 Wrenmere Clo",
    "sg:city":"Sandbach",
    "sg:classifiers":[
        {
            "category":"Professional",
            "subcategory":"Management & Consulting",
            "type":"Services"
        }
    ],
    "sg:phone":"+44 1270 765358",
    "sg:postcode":"CW11 1XS",
    "sg:province":"Cheshire",
    "sg:tags":[
        "consultant",
        "business"
    ],
    "wof:name":"Financial Management Associates",
    "wof:placetype":"venue"
},
  "geometry": {"coordinates":[-2.384155,53.151413],"type":"Point"}
}