{
  "type": "Feature",
  "properties": {
    "addr:full":"138 The Cornfields, Hatch Warren Basingstoke Hampshire RG22 4QD",
    "addr:housenumber":"138",
    "addr:postcode":"rg22 4qd",
    "addr:street":"The Cornfields",
    "iso:country":"GB",
    "sg:address":"138 The Cornfields, Hatch Warren",
    "sg:city":"Basingstoke",
    "sg:classifiers":[
        {
            "category":"Education",
            "subcategory":"Special Training",
            "type":"Public Place"
        }
    ],
    "sg:phone":"+44 1273 616919",
    "sg:postcode":"RG22 4QD",
    "sg:province":"Hampshire",
    "sg:tags":[
        "product",
        "centre"
    ],
    "wof:name":"R T W Training Services",
    "wof:placetype":"venue"
},
  "geometry": {"coordinates":[-1.131999,51.233913],"type":"Point"}
}