{
  "type": "Feature",
  "properties": {
    "addr:full":"104 Neasham Road Darlington Durham DL1 4AQ",
    "addr:housenumber":"104",
    "addr:postcode":"dl1 4aq",
    "addr:street":"Neasham Road",
    "iso:country":"GB",
    "sg:address":"104 Neasham Road",
    "sg:city":"Darlington",
    "sg:classifiers":[
        {
            "category":"Professional",
            "subcategory":"Detective & Security Services",
            "type":"Services"
        }
    ],
    "sg:phone":"+44 1325 486147",
    "sg:postcode":"DL1 4AQ",
    "sg:province":"Durham",
    "sg:tags":[
        "alarm",
        "burglar",
        "system"
    ],
    "wof:name":"Chieftain Intruder Alarms",
    "wof:placetype":"venue"
},
  "geometry": {"coordinates":[-1.542915,54.51931],"type":"Point"}
}