{
  "type": "Feature",
  "properties": {
    "addr:full":"64 Bank Parade Burnley Lancashire BB11 1TS",
    "addr:housenumber":"64",
    "addr:postcode":"bb11 1ts",
    "addr:street":"Bank Parade",
    "iso:country":"GB",
    "sg:address":"64 Bank Parade",
    "sg:city":"Burnley",
    "sg:classifiers":[
        {
            "category":"Personal",
            "type":"Services"
        },
        {
            "category":"Professional",
            "subcategory":"Lawyer & Legal Services",
            "type":"Services"
        }
    ],
    "sg:phone":"+44 1282 416596",
    "sg:postcode":"BB11 1TS",
    "sg:province":"Lancashire",
    "sg:tags":[
        "advice",
        "counselling"
    ],
    "wof:name":"Brook Advisory Centre North East Lancs",
    "wof:placetype":"venue"
},
  "geometry": {"coordinates":[-2.2412340641,53.7921524048],"type":"Point"}
}