{
  "type": "Feature",
  "properties": {
    "iso:country":"GB",
    "sg:address":"782 Mansfield Road",
    "sg:city":"Nottingham",
    "sg:classifiers":[
        {
            "category":"Retail",
            "subcategory":"Auto Rental",
            "type":"Services"
        }
    ],
    "sg:phone":"+44 115 926 5000",
    "sg:postcode":"NG5 3GG",
    "sg:province":"Nottinghamshire",
    "sg:tags":[
        "car",
        "vehicle"
    ],
    "sg:website":"http://www.earc.com",
    "wof:name":"Enterprise Rent-A-Car UK Ltd",
    "wof:placetype":"venue"
},
  "geometry": {"coordinates":[-1.138662,52.993832],"type":"Point"}
}