{
  "type": "Feature",
  "properties": {
    "iso:country":"GB",
    "sg:address":"Commerce Way",
    "sg:city":"Edenbridge",
    "sg:classifiers":[
        {
            "category":"Wholesale",
            "subcategory":"Groceries",
            "type":"Manufacturing & Wholesale Goods"
        }
    ],
    "sg:phone":"+44 1732 864344",
    "sg:postcode":"TN8 6ED",
    "sg:province":"East Sussex",
    "sg:tags":[
        "food",
        "supplier",
        "drink"
    ],
    "wof:name":"Booker Foodservice",
    "wof:placetype":"venue"
},
  "geometry": {"coordinates":[0.063313,51.205166],"type":"Point"}
}