{
  "type": "Feature",
  "properties": {
    "iso:country":"GB",
    "sg:address":"81 Cheap St",
    "sg:city":"Sherborne",
    "sg:classifiers":[
        {
            "category":"Food & Beverages",
            "subcategory":"Liquor & Beverages",
            "type":"Retail Goods"
        }
    ],
    "sg:phone":"+44 1935 814406",
    "sg:postcode":"DT9 3BA",
    "sg:province":"Dorset",
    "sg:tags":[
        "beer",
        "spirit",
        "wines"
    ],
    "wof:name":"Victoria Wine",
    "wof:placetype":"venue"
},
  "geometry": {"coordinates":[-2.515928,50.947922],"type":"Point"}
}