{
  "type": "Feature",
  "properties": {
    "iso:country":"GB",
    "sg:address":"Off Darlington Road",
    "sg:city":"Richmond",
    "sg:classifiers":[
        {
            "category":"Sports & Exercise",
            "subcategory":"Gym",
            "type":"Entertainment"
        }
    ],
    "sg:phone":"+44 1748 850236",
    "sg:postcode":"DL10 7AW",
    "sg:province":"North Yorkshire",
    "sg:tags":[
        "fitness",
        "health",
        "centre"
    ],
    "wof:name":"The Power & Body Health & Fitness Club )",
    "wof:placetype":"venue"
},
  "geometry": {"coordinates":[-1.7223399878,54.4087524414],"type":"Point"}
}