{
  "type": "Feature",
  "properties": {
    "addr:full":"32 St Mary's Butts Reading Berkshire RG1 2LS",
    "addr:housenumber":"32",
    "addr:postcode":"rg1 2ls",
    "addr:street":"St Mary'S Butts",
    "iso:country":"GB",
    "sg:address":"32 St Mary's Butts",
    "sg:city":"Reading",
    "sg:classifiers":[
        {
            "category":"Professional",
            "subcategory":"Art Services",
            "type":"Services"
        }
    ],
    "sg:phone":"+44 118 939 1451",
    "sg:postcode":"RG1 2LS",
    "sg:province":"Berkshire",
    "sg:tags":[
        "graphic",
        "designer"
    ],
    "wof:name":"L'Image Design Ltd.",
    "wof:placetype":"venue"
},
  "geometry": {"coordinates":[-0.9743800163,51.4540100098],"type":"Point"}
}