{
  "type": "Feature",
  "properties": {
    "addr:full":"37 Radburn Close Harlow Essex CM18 7ED",
    "addr:housenumber":"37",
    "addr:postcode":"cm18 7ed",
    "addr:street":"Radburn Close",
    "iso:country":"GB",
    "sg:address":"37 Radburn Close",
    "sg:city":"Harlow",
    "sg:classifiers":[
        {
            "category":"Shopping",
            "subcategory":"Music",
            "type":"Retail Goods"
        }
    ],
    "sg:postcode":"CM18 7ED",
    "sg:province":"Essex",
    "sg:tags":[
        "shop"
    ],
    "wof:name":"K B Music",
    "wof:placetype":"venue"
},
  "geometry": {"coordinates":[0.114275001,51.7516899109],"type":"Point"}
}