{
  "type": "Feature",
  "properties": {
    "iso:country":"GB",
    "sg:address":"The Landbase, Frating Road, Ardleigh",
    "sg:city":"Colchester",
    "sg:classifiers":[
        {
            "category":"Building & Trades",
            "subcategory":"Landscaping Services",
            "type":"Services"
        }
    ],
    "sg:phone":"+44 1206 230323",
    "sg:postcode":"CO7 7SU",
    "sg:province":"Essex",
    "sg:tags":[
        "landscape",
        "contractor"
    ],
    "wof:name":"E L S Ltd.",
    "wof:placetype":"venue"
},
  "geometry": {"coordinates":[0.983797,51.925888],"type":"Point"}
}