{
  "type": "Feature",
  "properties": {
    "addr:full":"100 Mount Street London Greater London W1K 2TG",
    "addr:housenumber":"100",
    "addr:postcode":"w1k 2tg",
    "addr:street":"Mount Street",
    "iso:country":"GB",
    "sg:address":"100 Mount Street",
    "sg:city":"London",
    "sg:classifiers":[
        {
            "category":"Health Services",
            "subcategory":"Optometrist",
            "type":"Services"
        }
    ],
    "sg:phone":"+44 20 7409 2559",
    "sg:postcode":"W1K 2TG",
    "sg:province":"Greater London",
    "sg:tags":[
        "optician"
    ],
    "wof:name":"Jani Viren",
    "wof:placetype":"venue"
},
  "geometry": {"coordinates":[-0.150603,51.509651],"type":"Point"}
}