{
  "type": "Feature",
  "properties": {
    "addr:full":"North Road Minehead Somerset TA24 5QW",
    "addr:postcode":"ta24 5qw",
    "addr:street":"North Road",
    "iso:country":"GB",
    "sg:address":"North Road",
    "sg:city":"Minehead",
    "sg:classifiers":[
        {
            "category":"Organizations",
            "subcategory":"Community Association",
            "type":"Services"
        },
        {
            "category":"Organizations",
            "subcategory":"Membership Organization",
            "type":"Services"
        }
    ],
    "sg:phone":"+44 1643 702306",
    "sg:postcode":"TA24 5QW",
    "sg:province":"Somerset",
    "sg:tags":[
        "club",
        "social"
    ],
    "wof:name":"Minehead & District Social Club",
    "wof:placetype":"venue"
},
  "geometry": {"coordinates":[-3.4734869003,51.2082290649],"type":"Point"}
}