{
  "type": "Feature",
  "properties": {
    "addr:full":"Norton Canes Business Park, 2 Bettys Lane Cannock Staffordshire WS11 9UH",
    "addr:housenumber":"2",
    "addr:postcode":"ws11 9uh",
    "addr:street":"Park;Bettys Lane",
    "iso:country":"GB",
    "sg:address":"Norton Canes Business Park, 2 Bettys Lane",
    "sg:city":"Cannock",
    "sg:classifiers":[
        {
            "category":"Autos & Motor Vehicles",
            "subcategory":"Motorcycle Sales",
            "type":"Retail Goods"
        }
    ],
    "sg:phone":"+44 1543 450150",
    "sg:postcode":"WS11 9UH",
    "sg:province":"Staffordshire",
    "wof:name":"Edmondson Racing",
    "wof:placetype":"venue"
},
  "geometry": {"coordinates":[-2.033145,52.690952],"type":"Point"}
}