{
  "type": "Feature",
  "properties": {
    "addr:full":"Newtonhill, Kirkinner Newton Stewart Dumfries and Galloway DG8 9AU",
    "addr:postcode":"dg8 9au",
    "addr:street":"Stewart",
    "iso:country":"GB",
    "sg:address":"Newtonhill, Kirkinner",
    "sg:city":"Newton Stewart",
    "sg:classifiers":[
        {
            "category":"Farming",
            "subcategory":"Farm",
            "type":"Manufacturing & Wholesale Goods"
        }
    ],
    "sg:postcode":"DG8 9AU",
    "sg:province":"Dumfries and Galloway",
    "sg:tags":[
        "mixed",
        "crop"
    ],
    "wof:name":"Ian McCreath",
    "wof:placetype":"venue"
},
  "geometry": {"coordinates":[-4.457845211,54.8329658508],"type":"Point"}
}