{
  "type": "Feature",
  "properties": {
    "addr:full":"20 Cranbourn St Holborn Greater London WC2H 7AA",
    "addr:housenumber":"20",
    "addr:postcode":"wc2h 7aa",
    "addr:street":"Cranbourn St",
    "iso:country":"GB",
    "sg:address":"20 Cranbourn St",
    "sg:city":"Holborn",
    "sg:classifiers":[
        {
            "category":"Train Station",
            "subcategory":"Rail",
            "type":"Transportation"
        }
    ],
    "sg:phone":"+44 20 7918 2700",
    "sg:postcode":"WC2H 7AA",
    "sg:province":"Greater London",
    "sg:tags":[
        "railway"
    ],
    "wof:name":"North Line",
    "wof:placetype":"venue"
},
  "geometry": {"coordinates":[-0.1283539981,51.5114440918],"type":"Point"}
}