{
  "type": "Feature",
  "properties": {
    "addr:full":"28 Wansbeck Road South, Gosforth Newcastle-upon-tyne Tyne and Wear NE3 3HQ",
    "addr:housenumber":"28",
    "addr:postcode":"ne3 3hq",
    "addr:street":"Wansbeck Road",
    "iso:country":"GB",
    "sg:address":"28 Wansbeck Road South, Gosforth",
    "sg:city":"Newcastle-upon-tyne",
    "sg:classifiers":[
        {
            "category":"Food & Beverages",
            "subcategory":"Bakery",
            "type":"Retail Goods"
        }
    ],
    "sg:phone":"+44 191 285 1322",
    "sg:postcode":"NE3 3HQ",
    "sg:province":"Tyne and Wear",
    "sg:tags":[
        "shop",
        "baker"
    ],
    "wof:name":"Milligans Bakery Ltd",
    "wof:placetype":"venue"
},
  "geometry": {"coordinates":[-1.635062,55.013184],"type":"Point"}
}