{
  "type": "Feature",
  "properties": {
    "addr:full":"Balcony Shop, B5 Market Hall Derby Derbyshire DE1 9XN",
    "addr:housenumber":"b5",
    "addr:postcode":"de1 9xn",
    "addr:street":"Market Hall",
    "iso:country":"GB",
    "sg:address":"Balcony Shop, B5 Market Hall",
    "sg:city":"Derby",
    "sg:classifiers":[
        {
            "category":"Professional",
            "subcategory":"Lawyer & Legal Services",
            "type":"Services"
        }
    ],
    "sg:phone":"+44 1332 344557",
    "sg:postcode":"DE1 9XN",
    "sg:province":"Derbyshire",
    "wof:name":"Derby Law Centre",
    "wof:placetype":"venue"
},
  "geometry": {"coordinates":[-1.4836839437,52.9251708984],"type":"Point"}
}