{
  "type": "Feature",
  "properties": {
    "addr:full":"2 Bascombe Clo Brixham Devon TQ5 0JR",
    "addr:housenumber":"2",
    "addr:postcode":"tq5 0jr",
    "addr:street":"Bascombe Clo",
    "iso:country":"GB",
    "sg:address":"2 Bascombe Clo",
    "sg:city":"Brixham",
    "sg:classifiers":[
        {
            "category":"Building & Trades",
            "subcategory":"Landscaping Services",
            "type":"Services"
        }
    ],
    "sg:phone":"+44 1803 844210",
    "sg:postcode":"TQ5 0JR",
    "sg:province":"Devon",
    "sg:tags":[
        "preservation",
        "timber"
    ],
    "wof:name":"1st Choice Sure-Cure (S.W.)",
    "wof:placetype":"venue"
},
  "geometry": {"coordinates":[-3.554972887,50.3989219666],"type":"Point"}
}