{
  "type": "Feature",
  "properties": {
    "addr:full":"Barton Stadium, Kingsway Winsford Cheshire CW7 3AE",
    "addr:postcode":"cw7 3ae",
    "addr:street":"Kingsway",
    "iso:country":"GB",
    "sg:address":"Barton Stadium, Kingsway",
    "sg:city":"Winsford",
    "sg:classifiers":[
        {
            "category":"Arena",
            "subcategory":"Sports Club",
            "type":"Entertainment"
        }
    ],
    "sg:phone":"+44 1606 593021",
    "sg:postcode":"CW7 3AE",
    "sg:province":"Cheshire",
    "wof:name":"Winsford United Football Club Ltd",
    "wof:placetype":"venue"
},
  "geometry": {"coordinates":[-2.514418,53.192673],"type":"Point"}
}