{
  "type": "Feature",
  "properties": {
    "addr:full":"7 West Bank Stoke-on-trent Staffordshire ST4 5DE",
    "addr:housenumber":"7",
    "addr:postcode":"st4 5de",
    "addr:street":"West Bank",
    "iso:country":"GB",
    "sg:address":"7 West Bank",
    "sg:city":"Stoke-on-trent",
    "sg:classifiers":[
        {
            "category":"Farming",
            "subcategory":"Nursery",
            "type":"Manufacturing & Wholesale Goods"
        }
    ],
    "sg:postcode":"ST4 5DE",
    "sg:province":"Staffordshire",
    "sg:tags":[
        "creche"
    ],
    "wof:name":"Hall,Diane,",
    "wof:placetype":"venue"
},
  "geometry": {"coordinates":[-2.191273,53.001099],"type":"Point"}
}