{
  "type": "Feature",
  "properties": {
    "addr:full":"Lochvale House, Georgetown Rd Dumfries Dumfries and Galloway DG1 4DF",
    "addr:postcode":"dg1 4df",
    "addr:street":"Georgetown Rd",
    "iso:country":"GB",
    "sg:address":"Lochvale House, Georgetown Rd",
    "sg:city":"Dumfries",
    "sg:classifiers":[
        {
            "category":"Education",
            "subcategory":"Special Training",
            "type":"Public Place"
        }
    ],
    "sg:phone":"+44 1387 247333",
    "sg:postcode":"DG1 4DF",
    "sg:province":"Dumfries and Galloway",
    "sg:tags":[
        "product",
        "centre"
    ],
    "wof:name":"G B T Training",
    "wof:placetype":"venue"
},
  "geometry": {"coordinates":[-3.576099,55.057796],"type":"Point"}
}