{
  "type": "Feature",
  "properties": {
    "addr:full":"12 The Lings, Armthorpe Doncaster South Yorkshire DN3 3RH",
    "addr:housenumber":"12",
    "addr:postcode":"dn3 3rh",
    "addr:street":"The Lings",
    "iso:country":"GB",
    "sg:address":"12 The Lings, Armthorpe",
    "sg:city":"Doncaster",
    "sg:classifiers":[
        {
            "category":"Retail",
            "subcategory":"Driving School",
            "type":"Services"
        }
    ],
    "sg:postcode":"DN3 3RH",
    "sg:province":"South Yorkshire",
    "wof:name":"S Rynn",
    "wof:placetype":"venue"
},
  "geometry": {"coordinates":[-1.0429500341,53.5312347412],"type":"Point"}
}