{
  "type": "Feature",
  "properties": {
    "addr:full":"Princess Beatrice House, 192 Finborough Road London Greater London SW10 9BA",
    "addr:housenumber":"192",
    "addr:postcode":"sw10 9ba",
    "addr:street":"Princess;Finborough Road",
    "iso:country":"GB",
    "sg:address":"Princess Beatrice House, 192 Finborough Road",
    "sg:city":"London",
    "sg:classifiers":[
        {
            "category":"Organizations",
            "subcategory":"Community Association",
            "type":"Services"
        }
    ],
    "sg:phone":"+44 20 7370 0755",
    "sg:postcode":"SW10 9BA",
    "sg:province":"Greater London",
    "sg:tags":[
        "co-operatives",
        "society",
        "housing",
        "trust"
    ],
    "sg:website":"http://www.lookahead.org.uk",
    "wof:name":"Princess Beatrice House",
    "wof:placetype":"venue"
},
  "geometry": {"coordinates":[-0.1924089938,51.4883460999],"type":"Point"}
}