{
  "type": "Feature",
  "properties": {
    "addr:full":"2 Wollaston Rd Dorchester Dorset DT1 1EQ",
    "addr:housenumber":"2",
    "addr:postcode":"dt1 1eq",
    "addr:street":"Wollaston Rd",
    "iso:country":"GB",
    "sg:address":"2 Wollaston Rd",
    "sg:city":"Dorchester",
    "sg:classifiers":[
        {
            "category":"Arts & Performance",
            "subcategory":"Music",
            "type":"Entertainment"
        }
    ],
    "sg:phone":"+44 1305 257595",
    "sg:postcode":"DT1 1EQ",
    "sg:province":"Dorset",
    "sg:tags":[
        "musician",
        "composer"
    ],
    "wof:name":"Opera Singers R Us",
    "wof:placetype":"venue"
},
  "geometry": {"coordinates":[-2.433267,50.71357],"type":"Point"}
}