{
  "type": "Feature",
  "properties": {
    "iso:country":"GB",
    "sg:address":"2 Romford Street, Hindley",
    "sg:city":"Wigan",
    "sg:classifiers":[
        {
            "category":"Organizations",
            "subcategory":"Membership Organization",
            "type":"Services"
        }
    ],
    "sg:phone":"+44 1942 510200",
    "sg:postcode":"WN2 3LW",
    "sg:province":"Lancashire",
    "sg:tags":[
        "club"
    ],
    "wof:name":"Hindley Labour Club",
    "wof:placetype":"venue"
},
  "geometry": {"coordinates":[-2.5808238983,53.5336112976],"type":"Point"}
}