{
  "type": "Feature",
  "properties": {
    "iso:country":"GB",
    "sg:address":"Unit 4, Littletowns Industrial Estate",
    "sg:city":"Blandford Forum",
    "sg:classifiers":[
        {
            "category":"Retail",
            "subcategory":"Auto Repair",
            "type":"Services"
        }
    ],
    "sg:postcode":"DT11 7UR",
    "sg:province":"Dorset",
    "sg:tags":[
        "modification",
        "garage"
    ],
    "wof:name":"Alan W Sims",
    "wof:placetype":"venue"
},
  "geometry": {"coordinates":[-2.157956,50.86665],"type":"Point"}
}