{
  "type": "Feature",
  "properties": {
    "iso:country":"GB",
    "sg:address":"Sutherland Way",
    "sg:city":"Stamford",
    "sg:classifiers":[
        {
            "category":"Shopping",
            "subcategory":"News",
            "type":"Retail Goods"
        }
    ],
    "sg:phone":"+44 1780 755055",
    "sg:postcode":"PE9 2TB",
    "sg:province":"Cambridgeshire",
    "sg:tags":[
        "newsagent"
    ],
    "wof:name":"Sutherland Way Newsagents",
    "wof:placetype":"venue"
},
  "geometry": {"coordinates":[-0.498804,52.657139],"type":"Point"}
}