{
  "type": "Feature",
  "properties": {
    "iso:country":"GB",
    "sg:address":"76 High Street, Wainfleet",
    "sg:city":"Skegness",
    "sg:classifiers":[
        {
            "category":"Building & Trades",
            "subcategory":"Construction",
            "type":"Services"
        }
    ],
    "sg:phone":"+44 1754 880314",
    "sg:postcode":"PE24 4BH",
    "sg:province":"Lincolnshire",
    "sg:tags":[
        "builder"
    ],
    "wof:name":"J T Turner & Sons",
    "wof:placetype":"venue"
},
  "geometry": {"coordinates":[0.236577,53.107609],"type":"Point"}
}