{
  "type": "Feature",
  "properties": {
    "addr:full":"105 Wager St Bow Greater London E3 4JR",
    "addr:housenumber":"105",
    "addr:postcode":"e3 4jr",
    "addr:street":"Wager St",
    "iso:country":"GB",
    "sg:address":"105 Wager St",
    "sg:city":"Bow",
    "sg:classifiers":[
        {
            "category":"Wholesale",
            "subcategory":"Groceries",
            "type":"Manufacturing & Wholesale Goods"
        }
    ],
    "sg:phone":"+44 20 8980 3838",
    "sg:postcode":"E3 4JR",
    "sg:province":"Greater London",
    "sg:tags":[
        "food",
        "supplier",
        "drink"
    ],
    "wof:name":"H Norman",
    "wof:placetype":"venue"
},
  "geometry": {"coordinates":[-0.03071,51.519718],"type":"Point"}
}