{
  "type": "Feature",
  "properties": {
    "addr:full":"Unit D Croydon Surrey CR0 3QS",
    "addr:housenumber":"unit d",
    "addr:postcode":"cr0 3qs",
    "iso:country":"GB",
    "sg:address":"Unit D",
    "sg:city":"Croydon",
    "sg:classifiers":[
        {
            "category":"Recreation",
            "subcategory":"Amusement Park",
            "type":"Entertainment"
        },
        {
            "category":"Autos & Motor Vehicles",
            "subcategory":"Boat Sales",
            "type":"Retail Goods"
        }
    ],
    "sg:phone":"+44 20 8664 8660",
    "sg:postcode":"CR0 3QS",
    "sg:province":"Surrey",
    "sg:tags":[
        "machine",
        "gaming",
        "arcade"
    ],
    "wof:name":"Itza Pleasure Ltd",
    "wof:placetype":"venue"
},
  "geometry": {"coordinates":[-0.11456,51.388008],"type":"Point"}
}