{
  "type": "Feature",
  "properties": {
    "addr:full":"280a St Vincent Street Glasgow Glasgow City G2 5RL",
    "addr:housenumber":"280a",
    "addr:postcode":"g2 5rl",
    "addr:street":"St Vincent Street",
    "iso:country":"GB",
    "sg:address":"280a St Vincent Street",
    "sg:city":"Glasgow",
    "sg:classifiers":[
        {
            "category":"Professional",
            "subcategory":"Advertising",
            "type":"Services"
        }
    ],
    "sg:phone":"+44 141 204 1955",
    "sg:postcode":"G2 5RL",
    "sg:province":"Glasgow City",
    "sg:tags":[
        "agency"
    ],
    "wof:name":"The Glasgow Agency",
    "wof:placetype":"venue"
},
  "geometry": {"coordinates":[-4.265529,55.862602],"type":"Point"}
}