{
  "type": "Feature",
  "properties": {
    "addr:full":"Exchange Ho, Midsummer Blvd Milton Keynes Buckinghamshire MK9 2EA",
    "addr:postcode":"mk9 2ea",
    "addr:street":"Ho Midsummer Blvd",
    "iso:country":"GB",
    "sg:address":"Exchange Ho, Midsummer Blvd",
    "sg:city":"Milton Keynes",
    "sg:classifiers":[
        {
            "category":"Autos & Motor Vehicles",
            "subcategory":"Motorcycle Sales",
            "type":"Retail Goods"
        },
        {
            "category":"Travel",
            "subcategory":"Travel Agent",
            "type":"Entertainment"
        }
    ],
    "sg:postcode":"MK9 2EA",
    "sg:province":"Buckinghamshire",
    "sg:tags":[
        "chauffeur",
        "driven",
        "car"
    ],
    "wof:name":"Orchard Travel",
    "wof:placetype":"venue"
},
  "geometry": {"coordinates":[-0.76098,52.039169],"type":"Point"}
}