{
  "type": "Feature",
  "properties": {
    "iso:country":"GB",
    "sg:address":"84 Weald Lane",
    "sg:city":"Harrow",
    "sg:classifiers":[
        {
            "category":"Autos & Motor Vehicles",
            "subcategory":"Automobile Sales",
            "type":"Retail Goods"
        }
    ],
    "sg:postcode":"HA2 6BZ",
    "sg:province":"Greater London",
    "sg:tags":[
        "car"
    ],
    "wof:name":"Manor Sports Cars Ltd",
    "wof:placetype":"venue"
},
  "geometry": {"coordinates":[-0.3617500067,51.5910415649],"type":"Point"}
}