{
  "type": "Feature",
  "properties": {
    "addr:full":"21a St Donatt's Road, New Cross London Greater London SE14 6NU",
    "addr:housenumber":"21a",
    "addr:postcode":"se14 6nu",
    "addr:street":"St Donatt'S Road",
    "iso:country":"GB",
    "sg:address":"21a St Donatt's Road, New Cross",
    "sg:city":"London",
    "sg:classifiers":[
        {
            "category":"Professional",
            "subcategory":"Lawyer & Legal Services",
            "type":"Services"
        }
    ],
    "sg:postcode":"SE14 6NU",
    "sg:province":"Greater London",
    "sg:tags":[
        "solicitor"
    ],
    "wof:name":"Akhursts Solicitors",
    "wof:placetype":"venue"
},
  "geometry": {"coordinates":[-0.047911,51.437466],"type":"Point"}
}