{
  "type": "Feature",
  "properties": {
    "addr:full":"Harbour Street Folkestone Kent CT20 1QN",
    "addr:postcode":"ct20 1qn",
    "addr:street":"Harbour Street",
    "iso:country":"GB",
    "sg:address":"Harbour Street",
    "sg:city":"Folkestone",
    "sg:classifiers":[
        {
            "category":"Cafe",
            "type":"Food & Drink"
        }
    ],
    "sg:postcode":"CT20 1QN",
    "sg:province":"Kent",
    "sg:tags":[
        "tea",
        "room"
    ],
    "wof:name":"Gigi's Tea Chalet",
    "wof:placetype":"venue"
},
  "geometry": {"coordinates":[1.185695,51.079815],"type":"Point"}
}