{
  "type": "Feature",
  "properties": {
    "addr:full":"60 Humber Street Hull East Riding of Yorkshire HU1 1TT",
    "addr:housenumber":"60",
    "addr:postcode":"hu1 1tt",
    "addr:street":"Humber Street",
    "iso:country":"GB",
    "sg:address":"60 Humber Street",
    "sg:city":"Hull",
    "sg:classifiers":[
        {
            "category":"Shopping",
            "type":"Retail Goods"
        }
    ],
    "sg:phone":"+44 1482 215434",
    "sg:postcode":"HU1 1TT",
    "sg:province":"East Riding of Yorkshire",
    "sg:tags":[
        "merchant"
    ],
    "wof:name":"G B Flowers",
    "wof:placetype":"venue"
},
  "geometry": {"coordinates":[-0.334167,53.739281],"type":"Point"}
}