{
  "type": "Feature",
  "properties": {
    "addr:full":"7-8 Service Bays, The Stow Harlow Essex CM20 3AB",
    "addr:housenumber":"7-8",
    "addr:postcode":"cm20 3ab",
    "addr:street":"Service Bays",
    "iso:country":"GB",
    "sg:address":"7-8 Service Bays, The Stow",
    "sg:city":"Harlow",
    "sg:classifiers":[
        {
            "category":"Autos & Motor Vehicles",
            "subcategory":"Auto Supplies",
            "type":"Retail Goods"
        },
        {
            "category":"Home & Garden",
            "subcategory":"Hardware",
            "type":"Retail Goods"
        }
    ],
    "sg:phone":"+44 1279 306189",
    "sg:postcode":"CM20 3AB",
    "sg:province":"Essex",
    "sg:tags":[
        "lawnmowers",
        "machinery",
        "tyre"
    ],
    "wof:name":"Budget Tyres",
    "wof:placetype":"venue"
},
  "geometry": {"coordinates":[0.1147200018,51.7725296021],"type":"Point"}
}