{
  "type": "Feature",
  "properties": {
    "iso:country":"GB",
    "sg:address":"11 Lovat Lane",
    "sg:city":"Monument",
    "sg:classifiers":[
        {
            "category":"Manufacturing",
            "subcategory":"Tools & Machinery",
            "type":"Manufacturing & Wholesale Goods"
        }
    ],
    "sg:phone":"+44 20 7378 8609",
    "sg:postcode":"EC3R 8DT",
    "sg:province":"Greater London",
    "sg:tags":[
        "society",
        "friendly"
    ],
    "wof:name":"Crawford THG",
    "wof:placetype":"venue"
},
  "geometry": {"coordinates":[-0.084415,51.509792],"type":"Point"}
}