{
  "type": "Feature",
  "properties": {
    "addr:full":"Unit 2 Inkerman Street Luton Bedfordshire LU1 1RJ",
    "addr:housenumber":"unit 2",
    "addr:postcode":"lu1 1rj",
    "addr:street":"Inkerman Street",
    "iso:country":"GB",
    "sg:address":"Unit 2 Inkerman Street",
    "sg:city":"Luton",
    "sg:classifiers":[
        {
            "category":"Real Estate",
            "subcategory":"Architect",
            "type":"Services"
        }
    ],
    "sg:phone":"+44 1582 412626",
    "sg:postcode":"LU1 1RJ",
    "sg:province":"Bedfordshire",
    "sg:tags":[
        "architectural"
    ],
    "wof:name":"Jon Moulding Architectural",
    "wof:placetype":"venue"
},
  "geometry": {"coordinates":[-0.4199590087,51.8809814453],"type":"Point"}
}