{
  "type": "Feature",
  "properties": {
    "addr:full":"Trent Rd Chelmsford Essex CM1 2LQ",
    "addr:postcode":"cm1 2lq",
    "addr:street":"Trent Rd",
    "iso:country":"GB",
    "sg:address":"Trent Rd",
    "sg:city":"Chelmsford",
    "sg:classifiers":[
        {
            "category":"Place Of Worship",
            "type":"Public Place"
        }
    ],
    "sg:phone":"+44 1245 354458",
    "sg:postcode":"CM1 2LQ",
    "sg:province":"Essex",
    "wof:name":"Trent Road United Reformed Church",
    "wof:placetype":"venue"
},
  "geometry": {"coordinates":[0.44209,51.747398],"type":"Point"}
}