{
  "type": "Feature",
  "properties": {
    "addr:full":"Derwent Farm, Aughton York East Riding of Yorkshire YO42 4PG",
    "addr:postcode":"yo42 4pg",
    "iso:country":"GB",
    "sg:address":"Derwent Farm, Aughton",
    "sg:city":"York",
    "sg:classifiers":[
        {
            "category":"Farming",
            "subcategory":"Farm",
            "type":"Manufacturing & Wholesale Goods"
        }
    ],
    "sg:phone":"+44 1757 288226",
    "sg:postcode":"YO42 4PG",
    "sg:province":"East Riding of Yorkshire",
    "sg:tags":[
        "mixed",
        "crop"
    ],
    "wof:name":"E R Nutt & Sons",
    "wof:placetype":"venue"
},
  "geometry": {"coordinates":[-0.9310340285,53.839515686],"type":"Point"}
}