{
  "type": "Feature",
  "properties": {
    "addr:full":"18 Greenacre Drive, Wyke Bradford West Yorkshire BD12 9DH",
    "addr:housenumber":"18",
    "addr:postcode":"bd12 9dh",
    "addr:street":"Greenacre Drive",
    "iso:country":"GB",
    "sg:address":"18 Greenacre Drive, Wyke",
    "sg:city":"Bradford",
    "sg:classifiers":[
        {
            "category":"Professional",
            "subcategory":"Detective & Security Services",
            "type":"Services"
        }
    ],
    "sg:postcode":"BD12 9DH",
    "sg:province":"West Yorkshire",
    "sg:tags":[
        "alarm",
        "burglar",
        "system"
    ],
    "wof:name":"Firth's Security",
    "wof:placetype":"venue"
},
  "geometry": {"coordinates":[-1.7595089674,53.7363014221],"type":"Point"}
}