{
  "type": "Feature",
  "properties": {
    "addr:full":"34 Gladstone Road Croydon Surrey CR0 2BQ",
    "addr:housenumber":"34",
    "addr:postcode":"cr0 2bq",
    "addr:street":"Gladstone Road",
    "iso:country":"GB",
    "sg:address":"34 Gladstone Road",
    "sg:city":"Croydon",
    "sg:classifiers":[
        {
            "category":"Professional",
            "subcategory":"Engineering",
            "type":"Services"
        }
    ],
    "sg:phone":"+44 20 8665 6570",
    "sg:postcode":"CR0 2BQ",
    "sg:province":"Surrey",
    "sg:tags":[
        "precision",
        "engineer"
    ],
    "wof:name":"G & K PRECISION ENGINEERING CO",
    "wof:placetype":"venue"
},
  "geometry": {"coordinates":[-0.0910390019,51.3840637207],"type":"Point"}
}