{
  "type": "Feature",
  "properties": {
    "addr:full":"1st Unit Ben Turner Industrial Estate, Oving Road Chichester West Sussex PO19 7ET",
    "addr:housenumber":"unit",
    "addr:postcode":"po19 7et",
    "addr:street":"Ben Turner Industrial Estate Oving Road",
    "iso:country":"GB",
    "sg:address":"1st Unit Ben Turner Industrial Estate, Oving Road",
    "sg:city":"Chichester",
    "sg:classifiers":[
        {
            "category":"Wholesale",
            "subcategory":"Construction Materials",
            "type":"Manufacturing & Wholesale Goods"
        }
    ],
    "sg:phone":"+44 1243 782855",
    "sg:postcode":"PO19 7ET",
    "sg:province":"West Sussex",
    "sg:tags":[
        "merchant",
        "glass"
    ],
    "wof:name":"C Brewer & Sons Ltd.",
    "wof:placetype":"venue"
},
  "geometry": {"coordinates":[-0.7754290104,50.8361663818],"type":"Point"}
}