{
  "type": "Feature",
  "properties": {
    "iso:country":"GB",
    "sg:address":"12 Larkswood Road, Corringham",
    "sg:city":"Stanford-le-hope",
    "sg:classifiers":[
        {
            "category":"Professional",
            "subcategory":"Accounting & Tax Preparation",
            "type":"Services"
        }
    ],
    "sg:postcode":"SS17 9DF",
    "sg:province":"Essex",
    "sg:tags":[
        "accountant"
    ],
    "wof:name":"B M R Book-Keeping Service",
    "wof:placetype":"venue"
},
  "geometry": {"coordinates":[0.460865,51.528767],"type":"Point"}
}