{
  "type": "Feature",
  "properties": {
    "iso:country":"GB",
    "sg:address":"82 Otley Old Road, Cookridge",
    "sg:city":"Leeds",
    "sg:classifiers":[
        {
            "category":"Retail",
            "subcategory":"Auto Repair",
            "type":"Services"
        }
    ],
    "sg:phone":"+44 113 267 1652",
    "sg:postcode":"LS16 6LQ",
    "sg:province":"West Yorkshire",
    "sg:tags":[
        "modification",
        "garage"
    ],
    "wof:name":"The Garage Ltd.",
    "wof:placetype":"venue"
},
  "geometry": {"coordinates":[-1.604634,53.849197],"type":"Point"}
}