{
  "type": "Feature",
  "properties": {
    "iso:country":"GB",
    "sg:address":"13 New Street",
    "sg:city":"Stourport-on-severn",
    "sg:classifiers":[
        {
            "category":"Professional",
            "subcategory":"Accounting & Tax Preparation",
            "type":"Services"
        }
    ],
    "sg:phone":"+44 1299 826133",
    "sg:postcode":"DY13 8UW",
    "sg:province":"Worcestershire",
    "sg:tags":[
        "accountant"
    ],
    "wof:name":"Connolly & Co",
    "wof:placetype":"venue"
},
  "geometry": {"coordinates":[-2.2813830376,52.339630127],"type":"Point"}
}