{
  "type": "Feature",
  "properties": {
    "addr:full":"9 Davygate York North Yorkshire YO1 8QR",
    "addr:housenumber":"9",
    "addr:postcode":"yo1 8qr",
    "addr:street":"Davygate York",
    "iso:country":"GB",
    "sg:address":"9 Davygate",
    "sg:city":"York",
    "sg:classifiers":[
        {
            "category":"Banks & Credit Unions",
            "subcategory":"Financial Services",
            "type":"Services"
        }
    ],
    "sg:phone":"+44 1904 656888",
    "sg:postcode":"YO1 8QR",
    "sg:province":"North Yorkshire",
    "sg:tags":[
        "building",
        "society"
    ],
    "wof:name":"Newcastle Building Society",
    "wof:placetype":"venue"
},
  "geometry": {"coordinates":[-1.082944,53.959831],"type":"Point"}
}