{
  "type": "Feature",
  "properties": {
    "addr:full":"Rear Of 87 Upper Clapton Rd Clapton Greater London E5 9BU",
    "addr:housenumber":"rear of 87",
    "addr:postcode":"e5 9bu",
    "addr:street":"Upper Clapton Rd",
    "iso:country":"GB",
    "sg:address":"Rear Of 87 Upper Clapton Rd",
    "sg:city":"Clapton",
    "sg:classifiers":[
        {
            "category":"Building & Trades",
            "subcategory":"Construction",
            "type":"Services"
        }
    ],
    "sg:phone":"+44 20 8806 4788",
    "sg:postcode":"E5 9BU",
    "sg:province":"Greater London",
    "sg:tags":[
        "welder",
        "mechanical"
    ],
    "wof:name":"T Tum",
    "wof:placetype":"venue"
},
  "geometry": {"coordinates":[-0.0539060012,51.5587921143],"type":"Point"}
}