{
  "type": "Feature",
  "properties": {
    "iso:country":"GB",
    "sg:address":"Hayes Rd",
    "sg:city":"Penarth",
    "sg:classifiers":[
        {
            "category":"Utilities",
            "subcategory":"Refuse",
            "type":"Services"
        }
    ],
    "sg:phone":"+44 29 2053 1218",
    "sg:postcode":"CF64 5SG",
    "sg:province":"The Vale of Glamorgan",
    "sg:tags":[
        "disposal",
        "waste"
    ],
    "wof:name":"3C'S Waste",
    "wof:placetype":"venue"
},
  "geometry": {"coordinates":[-3.2413029671,51.4023246765],"type":"Point"}
}