{
  "type": "Feature",
  "properties": {
    "iso:country":"GB",
    "sg:address":"97 Queens Cres",
    "sg:city":"Bodmin",
    "sg:classifiers":[
        {
            "category":"Retail",
            "subcategory":"Driving School",
            "type":"Services"
        }
    ],
    "sg:phone":"+44 1208 79337",
    "sg:postcode":"PL31 1QR",
    "sg:province":"Cornwall",
    "wof:name":"Megadrive",
    "wof:placetype":"venue"
},
  "geometry": {"coordinates":[-4.73794,50.463734],"type":"Point"}
}