{
  "type": "Feature",
  "properties": {
    "addr:full":"60 Bentinck Road Newcastle-upon-tyne Tyne and Wear NE4 6UY",
    "addr:housenumber":"60",
    "addr:postcode":"ne4 6uy",
    "addr:street":"Bentinck Road",
    "iso:country":"GB",
    "sg:address":"60 Bentinck Road",
    "sg:city":"Newcastle-upon-tyne",
    "sg:classifiers":[
        {
            "category":"Professional",
            "subcategory":"Secretarial Services",
            "type":"Services"
        },
        {
            "category":"Professional",
            "subcategory":"Advertising",
            "type":"Services"
        }
    ],
    "sg:phone":"+44 191 272 0111",
    "sg:postcode":"NE4 6UY",
    "sg:province":"Tyne and Wear",
    "sg:tags":[
        "mail",
        "direct"
    ],
    "wof:name":"Tynesoft Business Services",
    "wof:placetype":"venue"
},
  "geometry": {"coordinates":[-1.6456459761,54.9694786072],"type":"Point"}
}