{
  "type": "Feature",
  "properties": {
    "addr:full":"5 Montpellier Avenue Cheltenham Gloucestershire GL50 1SA",
    "addr:housenumber":"5",
    "addr:postcode":"gl50 1sa",
    "addr:street":"Montpellier Avenue",
    "iso:country":"GB",
    "sg:address":"5 Montpellier Avenue",
    "sg:city":"Cheltenham",
    "sg:classifiers":[
        {
            "category":"Food & Beverages",
            "subcategory":"Liquor & Beverages",
            "type":"Retail Goods"
        }
    ],
    "sg:phone":"+44 1242 243993",
    "sg:postcode":"GL50 1SA",
    "sg:province":"Gloucestershire",
    "sg:tags":[
        "beer",
        "wine",
        "spirit",
        "wines"
    ],
    "wof:name":"Montpellier Wines",
    "wof:placetype":"venue"
},
  "geometry": {"coordinates":[-2.0782580376,51.8943443298],"type":"Point"}
}