{
  "type": "Feature",
  "properties": {
    "addr:full":"170 Harold Road London Greater London E13 0SE",
    "addr:housenumber":"170",
    "addr:postcode":"e13 0se",
    "addr:street":"Harold Road",
    "iso:country":"GB",
    "sg:address":"170 Harold Road",
    "sg:city":"London",
    "sg:classifiers":[
        {
            "category":"Organizations",
            "subcategory":"Non-profit Organization",
            "type":"Services"
        }
    ],
    "sg:phone":"+44 20 8552 0645",
    "sg:postcode":"E13 0SE",
    "sg:province":"Greater London",
    "sg:tags":[
        "charitable",
        "organisation",
        "voluntary",
        "charity"
    ],
    "wof:name":"NEWHAM NIGHT SHELTER",
    "wof:placetype":"venue"
},
  "geometry": {"coordinates":[0.027196,51.534065],"type":"Point"}
}