{
  "type": "Feature",
  "properties": {
    "addr:full":"9 Winterburn Road Worcester Worcestershire WR2 6DW",
    "addr:housenumber":"9",
    "addr:postcode":"wr2 6dw",
    "addr:street":"Winterburn Road",
    "iso:country":"GB",
    "sg:address":"9 Winterburn Road",
    "sg:city":"Worcester",
    "sg:classifiers":[
        {
            "category":"Real Estate",
            "subcategory":"Surveying",
            "type":"Services"
        }
    ],
    "sg:postcode":"WR2 6DW",
    "sg:province":"Worcestershire",
    "sg:tags":[
        "surveyor",
        "land"
    ],
    "wof:name":"Derek H Longdon",
    "wof:placetype":"venue"
},
  "geometry": {"coordinates":[-2.246133,52.210106],"type":"Point"}
}