{
  "type": "Feature",
  "properties": {
    "addr:full":"5 Boundary Way Croydon Surrey CR0 5AU",
    "addr:housenumber":"5",
    "addr:postcode":"cr0 5au",
    "addr:street":"Boundary Way",
    "iso:country":"GB",
    "sg:address":"5 Boundary Way",
    "sg:city":"Croydon",
    "sg:classifiers":[
        {
            "category":"Professional",
            "subcategory":"Engineering",
            "type":"Services"
        }
    ],
    "sg:phone":"+44 1689 843694",
    "sg:postcode":"CR0 5AU",
    "sg:province":"Surrey",
    "sg:tags":[
        "contractor",
        "electrical",
        "engineer"
    ],
    "wof:name":"Netelec",
    "wof:placetype":"venue"
},
  "geometry": {"coordinates":[-0.030327,51.359348],"type":"Point"}
}