{
  "type": "Feature",
  "properties": {
    "iso:country":"GB",
    "sg:address":"62-64 Chancellors Road",
    "sg:city":"London",
    "sg:classifiers":[
        {
            "category":"Education",
            "subcategory":"Special Training",
            "type":"Public Place"
        },
        {
            "category":"Recreation",
            "subcategory":"Gun Range",
            "type":"Entertainment"
        }
    ],
    "sg:phone":"+44 20 8563 7878",
    "sg:postcode":"W6 9RS",
    "sg:province":"Greater London",
    "sg:tags":[
        "operator",
        "school",
        "tour",
        "language"
    ],
    "wof:name":"J A C Travel Ltd.",
    "wof:placetype":"venue"
},
  "geometry": {"coordinates":[-0.2260040045,51.4881744385],"type":"Point"}
}