{
  "type": "Feature",
  "properties": {
    "iso:country":"GB",
    "sg:address":"Chelsea Cloisters Garage, Sloane Av",
    "sg:city":"Chelsea",
    "sg:classifiers":[
        {
            "category":"Restaurant",
            "type":"Food & Drink"
        }
    ],
    "sg:phone":"+44 20 7581 8344",
    "sg:postcode":"SW3 3EL",
    "sg:province":"Greater London",
    "wof:name":"Rowleys (German Street) Ltd",
    "wof:placetype":"venue"
},
  "geometry": {"coordinates":[-0.1675039977,51.4922599792],"type":"Point"}
}