{
  "type": "Feature",
  "properties": {
    "addr:full":"7 Dawpool Drive, Bromborough Wirral Cheshire CH62 6DE",
    "addr:housenumber":"7",
    "addr:postcode":"ch62 6de",
    "addr:street":"Dawpool Drive",
    "iso:country":"GB",
    "sg:address":"7 Dawpool Drive, Bromborough",
    "sg:city":"Wirral",
    "sg:classifiers":[
        {
            "category":"Cinema",
            "subcategory":"Movie Rental",
            "type":"Entertainment"
        }
    ],
    "sg:phone":"+44 151 334 4035",
    "sg:postcode":"CH62 6DE",
    "sg:province":"Cheshire",
    "sg:tags":[
        "video",
        "library"
    ],
    "wof:name":"Video Time",
    "wof:placetype":"venue"
},
  "geometry": {"coordinates":[-2.9849219322,53.3258934021],"type":"Point"}
}