{
  "type": "Feature",
  "properties": {
    "addr:full":"88 Wood Street London Greater London EC2V 7QR",
    "addr:housenumber":"88",
    "addr:postcode":"ec2v 7qr",
    "addr:street":"Wood Street",
    "iso:country":"GB",
    "sg:address":"88 Wood Street",
    "sg:city":"London",
    "sg:classifiers":[
        {
            "category":"Banks & Credit Unions",
            "subcategory":"Investment Brokerage",
            "type":"Services"
        }
    ],
    "sg:phone":"+44 20 7523 8500",
    "sg:postcode":"EC2V 7QR",
    "sg:province":"Greater London",
    "sg:tags":[
        "stockbroker"
    ],
    "wof:name":"Collins Stewart Ltd.",
    "wof:placetype":"venue"
},
  "geometry": {"coordinates":[-0.0949200019,51.5153083801],"type":"Point"}
}