{
  "type": "Feature",
  "properties": {
    "addr:full":"474 Ilford Lane Ilford Essex IG1 2NF",
    "addr:housenumber":"474",
    "addr:postcode":"ig1 2nf",
    "addr:street":"Ilford Lane",
    "iso:country":"GB",
    "sg:address":"474 Ilford Lane",
    "sg:city":"Ilford",
    "sg:classifiers":[
        {
            "category":"Shopping",
            "subcategory":"News",
            "type":"Retail Goods"
        }
    ],
    "sg:phone":"+44 20 8478 2635",
    "sg:postcode":"IG1 2NF",
    "sg:province":"Essex",
    "sg:tags":[
        "newsagent"
    ],
    "wof:name":"Kilburn Stores",
    "wof:placetype":"venue"
},
  "geometry": {"coordinates":[0.0769580007,51.5453681946],"type":"Point"}
}