{
  "type": "Feature",
  "properties": {
    "addr:full":"34 Seafield Road, Longman Industrial Estate Inverness Highland IV1 1SG",
    "addr:housenumber":"34",
    "addr:postcode":"iv1 1sg",
    "addr:street":"Seafield Road;Industrial Estate",
    "iso:country":"GB",
    "sg:address":"34 Seafield Road, Longman Industrial Estate",
    "sg:city":"Inverness",
    "sg:classifiers":[
        {
            "category":"Shopping",
            "subcategory":"Clothing, Apparel, & Fashions",
            "type":"Retail Goods"
        }
    ],
    "sg:phone":"+44 1463 717099",
    "sg:postcode":"IV1 1SG",
    "sg:province":"Highland",
    "sg:tags":[
        "clothing",
        "fabric"
    ],
    "wof:name":"Stuart Higgs",
    "wof:placetype":"venue"
},
  "geometry": {"coordinates":[-4.215782,57.487118],"type":"Point"}
}