{
  "type": "Feature",
  "properties": {
    "addr:full":"Porthkerry Road Methodist Church, Annex Rommily Road Barry The Vale of Glamorgan CF62 7ER",
    "addr:postcode":"cf62 7er",
    "addr:street":"Porthkerry;Rommily Road;Vale",
    "iso:country":"GB",
    "sg:address":"Porthkerry Road Methodist Church, Annex Rommily Road",
    "sg:city":"Barry",
    "sg:classifiers":[
        {
            "category":"Professional",
            "subcategory":"Lawyer & Legal Services",
            "type":"Services"
        }
    ],
    "sg:phone":"+44 1446 732449",
    "sg:postcode":"CF62 7ER",
    "sg:province":"The Vale of Glamorgan",
    "sg:tags":[
        "advice",
        "counselling"
    ],
    "wof:name":"Barry & Vale Counselling Service",
    "wof:placetype":"venue"
},
  "geometry": {"coordinates":[-3.2832510471,51.4018974304],"type":"Point"}
}