{
  "type": "Feature",
  "properties": {
    "iso:country":"GB",
    "sg:address":"30 Dean Street",
    "sg:city":"Aberdare",
    "sg:classifiers":[
        {
            "category":"Personal",
            "subcategory":"Beauty Salon",
            "type":"Services"
        },
        {
            "category":"Personal",
            "subcategory":"Barber",
            "type":"Services"
        }
    ],
    "sg:phone":"+44 1685 881117",
    "sg:postcode":"CF44 7BN",
    "sg:province":"Neath Port Talbot",
    "sg:tags":[
        "unisex",
        "hairdresser"
    ],
    "wof:name":"Heidi's Hair Fashion",
    "wof:placetype":"venue"
},
  "geometry": {"coordinates":[-3.446864,51.714096],"type":"Point"}
}