{
  "type": "Feature",
  "properties": {
    "addr:full":"808 Stratford Road, Sparkhill Birmingham West Midlands B11 4BS",
    "addr:housenumber":"808",
    "addr:postcode":"b11 4bs",
    "addr:street":"Stratford Road",
    "iso:country":"GB",
    "sg:address":"808 Stratford Road, Sparkhill",
    "sg:city":"Birmingham",
    "sg:classifiers":[
        {
            "category":"Food & Beverages",
            "subcategory":"Bakery",
            "type":"Retail Goods"
        }
    ],
    "sg:phone":"+44 121 778 3934",
    "sg:postcode":"B11 4BS",
    "sg:province":"West Midlands",
    "sg:tags":[
        "baker"
    ],
    "wof:name":"Three Cooks Ltd.",
    "wof:placetype":"venue"
},
  "geometry": {"coordinates":[-1.8593100309,52.4455184937],"type":"Point"}
}