{
  "type": "Feature",
  "properties": {
    "addr:full":"131 Denton Road, Audenshaw Manchester Greater Manchester M34 5BE",
    "addr:housenumber":"131",
    "addr:postcode":"m34 5be",
    "addr:street":"Denton Road",
    "iso:country":"GB",
    "sg:address":"131 Denton Road, Audenshaw",
    "sg:city":"Manchester",
    "sg:classifiers":[
        {
            "category":"Personal",
            "subcategory":"Tanning Parlor",
            "type":"Services"
        },
        {
            "category":"Health Services",
            "subcategory":"Health Practitioner",
            "type":"Services"
        }
    ],
    "sg:phone":"+44 161 320 4409",
    "sg:postcode":"M34 5BE",
    "sg:province":"Greater Manchester",
    "sg:tags":[
        "physiotherapist",
        "sunbeds"
    ],
    "wof:name":"Westernlea Clinic",
    "wof:placetype":"venue"
},
  "geometry": {"coordinates":[-2.117083,53.464012],"type":"Point"}
}