{
  "type": "Feature",
  "properties": {
    "addr:full":"30 Exmouth Market Clerkenwell Greater London EC1R 4QE",
    "addr:housenumber":"30",
    "addr:postcode":"ec1r 4qe",
    "addr:street":"Exmouth Market",
    "iso:country":"GB",
    "sg:address":"30 Exmouth Market",
    "sg:city":"Clerkenwell",
    "sg:classifiers":[
        {
            "category":"Shopping",
            "subcategory":"Gifts & Souvenirs",
            "type":"Retail Goods"
        }
    ],
    "sg:phone":"+44 20 7837 2632",
    "sg:postcode":"EC1R 4QE",
    "sg:province":"Greater London",
    "sg:tags":[
        "poster",
        "card"
    ],
    "wof:name":"Applied",
    "wof:placetype":"venue"
},
  "geometry": {"coordinates":[-0.109395,51.525723],"type":"Point"}
}