{
  "type": "Feature",
  "properties": {
    "addr:full":"55 Ebury St Westminster Greater London SW1W 0PB",
    "addr:housenumber":"55",
    "addr:postcode":"sw1w 0pb",
    "addr:street":"Ebury St",
    "iso:country":"GB",
    "sg:address":"55 Ebury St",
    "sg:city":"Westminster",
    "sg:classifiers":[
        {
            "category":"Health Services",
            "subcategory":"Clinic",
            "type":"Services"
        }
    ],
    "sg:phone":"+44 20 7823 4486",
    "sg:postcode":"SW1W 0PB",
    "sg:province":"Greater London",
    "sg:tags":[
        "medical"
    ],
    "wof:name":"Ashcott Ltd",
    "wof:placetype":"venue"
},
  "geometry": {"coordinates":[-0.1478299946,51.495300293],"type":"Point"}
}