{
  "type": "Feature",
  "properties": {
    "addr:full":"345 Bilston Road Wolverhampton West Midlands WV2 2NH",
    "addr:housenumber":"345",
    "addr:postcode":"wv2 2nh",
    "addr:street":"Bilston Road",
    "iso:country":"GB",
    "sg:address":"345 Bilston Road",
    "sg:city":"Wolverhampton",
    "sg:classifiers":[
        {
            "category":"Autos & Motor Vehicles",
            "subcategory":"Auto Supplies",
            "type":"Retail Goods"
        }
    ],
    "sg:postcode":"WV2 2NH",
    "sg:province":"West Midlands",
    "sg:tags":[
        "component"
    ],
    "wof:name":"A1 Wheel Renovations",
    "wof:placetype":"venue"
},
  "geometry": {"coordinates":[-2.10077,52.57431],"type":"Point"}
}