{
  "type": "Feature",
  "properties": {
    "addr:full":"7 Bonville Road Altrincham Cheshire WA14 4QR",
    "addr:housenumber":"7",
    "addr:postcode":"wa14 4qr",
    "addr:street":"Bonville Road",
    "iso:country":"GB",
    "sg:address":"7 Bonville Road",
    "sg:city":"Altrincham",
    "sg:classifiers":[
        {
            "category":"Building & Trades",
            "subcategory":"Plumbing",
            "type":"Services"
        }
    ],
    "sg:postcode":"WA14 4QR",
    "sg:province":"Cheshire",
    "sg:tags":[
        "heating"
    ],
    "wof:name":"Alan Gibbons",
    "wof:placetype":"venue"
},
  "geometry": {"coordinates":[-2.369969,53.389366],"type":"Point"}
}