{
  "type": "Feature",
  "properties": {
    "addr:full":"62 Dark Lane Batley West Yorkshire WF17 5RN",
    "addr:housenumber":"62",
    "addr:postcode":"wf17 5rn",
    "addr:street":"Dark Lane",
    "iso:country":"GB",
    "sg:address":"62 Dark Lane",
    "sg:city":"Batley",
    "sg:classifiers":[
        {
            "category":"Professional",
            "subcategory":"Business Services",
            "type":"Services"
        }
    ],
    "sg:postcode":"WF17 5RN",
    "sg:province":"West Yorkshire",
    "sg:tags":[
        "tile",
        "stockist"
    ],
    "wof:name":"Mayets's D I Y Store",
    "wof:placetype":"venue"
},
  "geometry": {"coordinates":[-1.640649,53.711166],"type":"Point"}
}