{
  "type": "Feature",
  "properties": {
    "addr:full":"200 Ilford La Ilford Essex IG1 2LW",
    "addr:housenumber":"200",
    "addr:postcode":"ig1 2lw",
    "addr:street":"Ilford La Ilford",
    "iso:country":"GB",
    "sg:address":"200 Ilford La",
    "sg:city":"Ilford",
    "sg:classifiers":[
        {
            "category":"Autos & Motor Vehicles",
            "subcategory":"Fuel & Gas Station",
            "type":"Retail Goods"
        }
    ],
    "sg:phone":"+44 20 8477 7900",
    "sg:postcode":"IG1 2LW",
    "sg:province":"Essex",
    "sg:tags":[
        "hr",
        "petrol"
    ],
    "wof:name":"Shell Ilford Lane",
    "wof:placetype":"venue"
},
  "geometry": {"coordinates":[0.0741809979,51.5512657166],"type":"Point"}
}