{
  "type": "Feature",
  "properties": {
    "addr:full":"Unit 1 Dunkirk Indust Estate, Dunkirk Chester Cheshire CH1 6LZ",
    "addr:housenumber":"unit 1",
    "addr:postcode":"ch1 6lz",
    "addr:street":"Indust Estate",
    "iso:country":"GB",
    "sg:address":"Unit 1 Dunkirk Indust Estate, Dunkirk",
    "sg:city":"Chester",
    "sg:classifiers":[
        {
            "category":"Retail",
            "subcategory":"Storage",
            "type":"Services"
        }
    ],
    "sg:phone":"+44 1244 851733",
    "sg:postcode":"CH1 6LZ",
    "sg:province":"Cheshire",
    "sg:tags":[
        "household",
        "removal"
    ],
    "wof:name":"Renee Richards",
    "wof:placetype":"venue"
},
  "geometry": {"coordinates":[-2.9320790768,53.2485275269],"type":"Point"}
}