{
  "type": "Feature",
  "properties": {
    "addr:full":"18 Princes Street Leamington Spa Warwickshire CV32 4TY",
    "addr:housenumber":"18",
    "addr:postcode":"cv32 4ty",
    "addr:street":"Princes Street",
    "iso:country":"GB",
    "sg:address":"18 Princes Street",
    "sg:city":"Leamington Spa",
    "sg:classifiers":[
        {
            "category":"Bars & Pubs",
            "type":"Food & Drink"
        }
    ],
    "sg:phone":"+44 1926 425169",
    "sg:postcode":"CV32 4TY",
    "sg:province":"Warwickshire",
    "sg:tags":[
        "pubs",
        "inn"
    ],
    "wof:name":"The Black Horse",
    "wof:placetype":"venue"
},
  "geometry": {"coordinates":[-1.524628,52.293812],"type":"Point"}
}