{
  "type": "Feature",
  "properties": {
    "iso:country":"GB",
    "sg:address":"Royals Court, 15-17 Alexandra Street",
    "sg:city":"Southend On Sea",
    "sg:classifiers":[
        {
            "category":"Professional",
            "subcategory":"Art Services",
            "type":"Services"
        }
    ],
    "sg:phone":"+44 1702 391070",
    "sg:postcode":"SS1 1BX",
    "sg:province":"Essex",
    "sg:tags":[
        "photographer"
    ],
    "wof:name":"Paul Melvyn Shuttleworth",
    "wof:placetype":"venue"
},
  "geometry": {"coordinates":[0.713455,51.535137],"type":"Point"}
}