{
  "type": "Feature",
  "properties": {
    "addr:full":"Armley Ridge Rd Leeds West Yorkshire LS12 3NP",
    "addr:postcode":"ls12 3np",
    "addr:street":"Ridge Rd",
    "iso:country":"GB",
    "sg:address":"Armley Ridge Rd",
    "sg:city":"Leeds",
    "sg:classifiers":[
        {
            "category":"Place Of Worship",
            "type":"Public Place"
        }
    ],
    "sg:phone":"+44 113 263 8788",
    "sg:postcode":"LS12 3NP",
    "sg:province":"West Yorkshire",
    "wof:name":"Christ C Of E Church",
    "wof:placetype":"venue"
},
  "geometry": {"coordinates":[-1.6019450426,53.8014678955],"type":"Point"}
}