{
  "type": "Feature",
  "properties": {
    "addr:full":"20 Forge Road Port Talbot Neath Port Talbot SA13 1NU",
    "addr:housenumber":"20",
    "addr:postcode":"sa13 1nu",
    "addr:street":"Forge Road",
    "iso:country":"GB",
    "sg:address":"20 Forge Road",
    "sg:city":"Port Talbot",
    "sg:classifiers":[
        {
            "category":"Restaurant",
            "type":"Food & Drink"
        }
    ],
    "sg:phone":"+44 1639 887390",
    "sg:postcode":"SA13 1NU",
    "sg:province":"Neath Port Talbot",
    "wof:name":"Flamingo Bistro",
    "wof:placetype":"venue"
},
  "geometry": {"coordinates":[-3.782063961,51.5959892273],"type":"Point"}
}