{
  "type": "Feature",
  "properties": {
    "iso:country":"GB",
    "sg:address":"General Enquiries, Minerva House, Spaniel Row",
    "sg:city":"Nottingham",
    "sg:classifiers":[
        {
            "category":"Manufacturing",
            "subcategory":"Food",
            "type":"Manufacturing & Wholesale Goods"
        }
    ],
    "sg:phone":"+44 115 950 6207",
    "sg:postcode":"NG1 6EP",
    "sg:province":"Nottinghamshire",
    "sg:tags":[
        "mnfr",
        "drink",
        "soft"
    ],
    "wof:name":"Coco-Cola & Schweppes Beverages",
    "wof:placetype":"venue"
},
  "geometry": {"coordinates":[-1.15165,52.951786],"type":"Point"}
}