{
  "type": "Feature",
  "properties": {
    "iso:country":"GB",
    "sg:address":"109 Portland St",
    "sg:city":"Manchester",
    "sg:classifiers":[
        {
            "category":"Professional",
            "subcategory":"Engineering",
            "type":"Services"
        }
    ],
    "sg:phone":"+44 161 236 6602",
    "sg:postcode":"M1 6DN",
    "sg:province":"Greater Manchester",
    "sg:tags":[
        "consulting",
        "engineer"
    ],
    "wof:name":"C S L Building Services Ltd",
    "wof:placetype":"venue"
},
  "geometry": {"coordinates":[-2.240446,53.477196],"type":"Point"}
}