{
  "type": "Feature",
  "properties": {
    "addr:full":"The Vicarage, Vicarage Hill Solihull Warwickshire B94 5EB",
    "addr:postcode":"b94 5eb",
    "addr:street":"Vicarage Hill",
    "iso:country":"GB",
    "sg:address":"The Vicarage, Vicarage Hill",
    "sg:city":"Solihull",
    "sg:classifiers":[
        {
            "category":"Place Of Worship",
            "type":"Public Place"
        }
    ],
    "sg:phone":"+44 1564 742565",
    "sg:postcode":"B94 5EB",
    "sg:province":"Warwickshire",
    "wof:name":"St Mary Magdalene C Of E Church",
    "wof:placetype":"venue"
},
  "geometry": {"coordinates":[-1.848467,52.339966],"type":"Point"}
}