{
  "type": "Feature",
  "properties": {
    "addr:full":"5 Mursley Road Milton Keynes Bedfordshire MK17 0SH",
    "addr:housenumber":"5",
    "addr:postcode":"mk17 0sh",
    "addr:street":"Mursley Road",
    "iso:country":"GB",
    "sg:address":"5 Mursley Road",
    "sg:city":"Milton Keynes",
    "sg:classifiers":[
        {
            "category":"Shopping",
            "subcategory":"Department Store",
            "type":"Retail Goods"
        }
    ],
    "sg:postcode":"MK17 0SH",
    "sg:province":"Bedfordshire",
    "wof:name":"Swanbourne Post Office Stores",
    "wof:placetype":"venue"
},
  "geometry": {"coordinates":[-0.834427,51.938347],"type":"Point"}
}