{
  "type": "Feature",
  "properties": {
    "addr:full":"101 Commercial Road Leven Fife KY8 4LE",
    "addr:housenumber":"101",
    "addr:postcode":"ky8 4le",
    "addr:street":"Commercial Road",
    "iso:country":"GB",
    "sg:address":"101 Commercial Road",
    "sg:city":"Leven",
    "sg:classifiers":[
        {
            "category":"Bars & Pubs",
            "type":"Food & Drink"
        }
    ],
    "sg:phone":"+44 1333 424650",
    "sg:postcode":"KY8 4LE",
    "sg:province":"Fife",
    "sg:tags":[
        "pubs",
        "inn"
    ],
    "wof:name":"Blazers",
    "wof:placetype":"venue"
},
  "geometry": {"coordinates":[-2.997519,56.19611],"type":"Point"}
}