{
  "type": "Feature",
  "properties": {
    "addr:full":"Cairnton House, Pitcairngreen Perth Perth and Kinross PH1 3LR",
    "addr:postcode":"ph1 3lr",
    "addr:street":"Pitcairngreen",
    "iso:country":"GB",
    "sg:address":"Cairnton House, Pitcairngreen",
    "sg:city":"Perth",
    "sg:classifiers":[
        {
            "category":"Professional",
            "subcategory":"Accounting & Tax Preparation",
            "type":"Services"
        }
    ],
    "sg:postcode":"PH1 3LR",
    "sg:province":"Perth and Kinross",
    "sg:tags":[
        "accountant"
    ],
    "wof:name":"Longhorn & Co",
    "wof:placetype":"venue"
},
  "geometry": {"coordinates":[-3.517849,56.427151],"type":"Point"}
}