{
  "type": "Feature",
  "properties": {
    "iso:country":"GB",
    "sg:address":"Thorpe Bay Gardens",
    "sg:city":"Southend-on-sea",
    "sg:classifiers":[
        {
            "category":"Arena",
            "subcategory":"Sports Club",
            "type":"Entertainment"
        }
    ],
    "sg:phone":"+44 1702 585245",
    "sg:postcode":"SS1 3HL",
    "sg:province":"Essex",
    "wof:name":"Thorpe Bay Lawn Tennis Club",
    "wof:placetype":"venue"
},
  "geometry": {"coordinates":[0.7545099854,51.5298843384],"type":"Point"}
}