{
  "type": "Feature",
  "properties": {
    "iso:country":"GB",
    "sg:address":"209 Derby Rd",
    "sg:city":"Ripley",
    "sg:classifiers":[
        {
            "category":"Manufacturing",
            "subcategory":"Rubber & Plastics",
            "type":"Manufacturing & Wholesale Goods"
        }
    ],
    "sg:phone":"+44 1773 746067",
    "sg:postcode":"DE5 8HX",
    "sg:province":"Derbyshire",
    "sg:tags":[
        "product"
    ],
    "wof:name":"Apollo Plastic Extruders",
    "wof:placetype":"venue"
},
  "geometry": {"coordinates":[-1.43161,53.015755],"type":"Point"}
}