{
  "type": "Feature",
  "properties": {
    "iso:country":"GB",
    "sg:address":"Stream Road",
    "sg:city":"Stourbridge",
    "sg:classifiers":[
        {
            "category":"Health Services",
            "subcategory":"Hospital",
            "type":"Services"
        }
    ],
    "sg:phone":"+44 1384 244585",
    "sg:postcode":"DY8 5QX",
    "sg:province":"Staffordshire",
    "wof:name":"Wordsley Hospital",
    "wof:placetype":"venue"
},
  "geometry": {"coordinates":[-2.161904,52.484138],"type":"Point"}
}