{
  "type": "Feature",
  "properties": {
    "addr:full":"11 Clamp Grn, Colden Common Winchester Hampshire SO21 1UA",
    "addr:housenumber":"11",
    "addr:postcode":"so21 1ua",
    "addr:street":"Clamp Grn",
    "iso:country":"GB",
    "sg:address":"11 Clamp Grn, Colden Common",
    "sg:city":"Winchester",
    "sg:classifiers":[
        {
            "category":"Professional",
            "subcategory":"Engineering",
            "type":"Services"
        }
    ],
    "sg:postcode":"SO21 1UA",
    "sg:province":"Hampshire",
    "sg:tags":[
        "electronic",
        "engineer"
    ],
    "wof:name":"International Electronics (Europe)",
    "wof:placetype":"venue"
},
  "geometry": {"coordinates":[-1.31842,50.99416],"type":"Point"}
}