{
  "type": "Feature",
  "properties": {
    "addr:full":"3d Cockhedge Way Warrington Cheshire WA1 2QQ",
    "addr:postcode":"wa1 2qq",
    "addr:street":"Cockhedge Way",
    "iso:country":"GB",
    "sg:address":"3d Cockhedge Way",
    "sg:city":"Warrington",
    "sg:classifiers":[
        {
            "category":"Personal",
            "subcategory":"Beauty Salon",
            "type":"Services"
        }
    ],
    "sg:phone":"+44 1925 418448",
    "sg:postcode":"WA1 2QQ",
    "sg:province":"Cheshire",
    "wof:name":"Beverley Hills Nail Co",
    "wof:placetype":"venue"
},
  "geometry": {"coordinates":[-2.587472,53.390865],"type":"Point"}
}