{
  "type": "Feature",
  "properties": {
    "addr:full":"2 Cable St Whitechapel Greater London E1 8JG",
    "addr:housenumber":"2",
    "addr:postcode":"e1 8jg",
    "addr:street":"Cable St",
    "iso:country":"GB",
    "sg:address":"2 Cable St",
    "sg:city":"Whitechapel",
    "sg:classifiers":[
        {
            "category":"Taxi",
            "type":"Transportation"
        }
    ],
    "sg:phone":"+44 20 7488 4223",
    "sg:postcode":"E1 8JG",
    "sg:province":"Greater London",
    "sg:tags":[
        "mini",
        "cab"
    ],
    "wof:name":"City Car Services",
    "wof:placetype":"venue"
},
  "geometry": {"coordinates":[-0.0684420019,51.5107803345],"type":"Point"}
}