{
  "type": "Feature",
  "properties": {
    "addr:full":"59-61 Hatton Garden London Greater London EC1N 8LS",
    "addr:housenumber":"59-61",
    "addr:postcode":"ec1n 8ls",
    "addr:street":"Hatton Garden",
    "iso:country":"GB",
    "sg:address":"59-61 Hatton Garden",
    "sg:city":"London",
    "sg:classifiers":[
        {
            "category":"Professional",
            "subcategory":"Employment Agencies",
            "type":"Services"
        }
    ],
    "sg:postcode":"EC1N 8LS",
    "sg:province":"Greater London",
    "sg:tags":[
        "consultant"
    ],
    "wof:name":"Xtra It Resources Ltd",
    "wof:placetype":"venue"
},
  "geometry": {"coordinates":[-0.1089330018,51.5213050842],"type":"Point"}
}