{
  "type": "Feature",
  "properties": {
    "addr:full":"3 Wimbushes, Finchampstead Wokingham Berkshire RG40 4XG",
    "addr:housenumber":"3",
    "addr:postcode":"rg40 4xg",
    "addr:street":"Wimbushes Finchampstead",
    "iso:country":"GB",
    "sg:address":"3 Wimbushes, Finchampstead",
    "sg:city":"Wokingham",
    "sg:classifiers":[
        {
            "category":"Professional",
            "subcategory":"Management & Consulting",
            "type":"Services"
        },
        {
            "category":"Social Services",
            "subcategory":"Job Training",
            "type":"Services"
        }
    ],
    "sg:phone":"+44 118 973 3417",
    "sg:postcode":"RG40 4XG",
    "sg:province":"Berkshire",
    "sg:tags":[
        "consultant"
    ],
    "wof:name":"J H Training Services",
    "wof:placetype":"venue"
},
  "geometry": {"coordinates":[-0.869111,51.377605],"type":"Point"}
}