{
  "type": "Feature",
  "properties": {
    "addr:full":"11 Church Road Kington Herefordshire HR5 3AG",
    "addr:housenumber":"11",
    "addr:postcode":"hr5 3ag",
    "addr:street":"Church Road",
    "iso:country":"GB",
    "sg:address":"11 Church Road",
    "sg:city":"Kington",
    "sg:classifiers":[
        {
            "category":"Food & Beverages",
            "subcategory":"Liquor & Beverages",
            "type":"Retail Goods"
        }
    ],
    "sg:phone":"+44 1544 230534",
    "sg:postcode":"HR5 3AG",
    "sg:province":"Herefordshire",
    "sg:tags":[
        "beer",
        "spirit",
        "wines"
    ],
    "wof:name":"Andrew Darwin Fine Wines",
    "wof:placetype":"venue"
},
  "geometry": {"coordinates":[-3.0370109081,52.2042961121],"type":"Point"}
}