{
  "type": "Feature",
  "properties": {
    "iso:country":"GB",
    "sg:address":"101 Battle Road",
    "sg:city":"St Leonards-on-sea",
    "sg:classifiers":[
        {
            "category":"Food & Beverages",
            "subcategory":"Meat & Fish",
            "type":"Retail Goods"
        }
    ],
    "sg:phone":"+44 1424 430492",
    "sg:postcode":"TN37 7AD",
    "sg:province":"East Sussex",
    "sg:tags":[
        "chip"
    ],
    "wof:name":"Golden Fry",
    "wof:placetype":"venue"
},
  "geometry": {"coordinates":[0.554487,50.871426],"type":"Point"}
}