{
  "type": "Feature",
  "properties": {
    "addr:full":"7 Town Lane, Pampisford Cambridge Cambridgeshire CB2 4ER",
    "addr:housenumber":"7",
    "addr:postcode":"cb2 4er",
    "addr:street":"Town Lane",
    "iso:country":"GB",
    "sg:address":"7 Town Lane, Pampisford",
    "sg:city":"Cambridge",
    "sg:classifiers":[
        {
            "category":"Professional",
            "subcategory":"Art Services",
            "type":"Services"
        }
    ],
    "sg:phone":"+44 1223 837371",
    "sg:postcode":"CB2 4ER",
    "sg:province":"Cambridgeshire",
    "sg:tags":[
        "photographer"
    ],
    "wof:name":"Andrew Martin Photography",
    "wof:placetype":"venue"
},
  "geometry": {"coordinates":[0.185616,52.110512],"type":"Point"}
}