{
  "type": "Feature",
  "properties": {
    "addr:full":"1 Roberts Walk Darlington Durham DL1 1HF",
    "addr:housenumber":"1",
    "addr:postcode":"dl1 1hf",
    "addr:street":"Roberts Walk",
    "iso:country":"GB",
    "sg:address":"1 Roberts Walk",
    "sg:city":"Darlington",
    "sg:classifiers":[
        {
            "category":"Personal",
            "type":"Services"
        }
    ],
    "sg:phone":"+44 1325 482428",
    "sg:postcode":"DL1 1HF",
    "sg:province":"Durham",
    "sg:tags":[
        "delivery"
    ],
    "wof:name":"Compass Couriers",
    "wof:placetype":"venue"
},
  "geometry": {"coordinates":[-1.5384739637,54.5240592957],"type":"Point"}
}