{
  "type": "Feature",
  "properties": {
    "addr:full":"26 Park St Woodstock Oxfordshire OX20 1RW",
    "addr:housenumber":"26",
    "addr:postcode":"ox20 1rw",
    "addr:street":"Park St",
    "iso:country":"GB",
    "sg:address":"26 Park St",
    "sg:city":"Woodstock",
    "sg:classifiers":[
        {
            "category":"Shopping",
            "subcategory":"Antiques",
            "type":"Retail Goods"
        }
    ],
    "sg:phone":"+44 1993 812817",
    "sg:postcode":"OX20 1RW",
    "sg:province":"Oxfordshire",
    "wof:name":"Park House Antiques",
    "wof:placetype":"venue"
},
  "geometry": {"coordinates":[-1.3583019972,51.8477478027],"type":"Point"}
}