{
  "type": "Feature",
  "properties": {
    "addr:full":"29 Grange Road Alresford Hampshire SO24 9HB",
    "addr:housenumber":"29",
    "addr:postcode":"so24 9hb",
    "addr:street":"Grange Road",
    "iso:country":"GB",
    "sg:address":"29 Grange Road",
    "sg:city":"Alresford",
    "sg:classifiers":[
        {
            "category":"Military Area",
            "subcategory":"Air Force Base",
            "type":"Public Place"
        }
    ],
    "sg:phone":"+44 1962 772255",
    "sg:postcode":"SO24 9HB",
    "sg:province":"Hampshire",
    "sg:tags":[
        "water",
        "treatment"
    ],
    "wof:name":"Hydrotech Services Ltd.",
    "wof:placetype":"venue"
},
  "geometry": {"coordinates":[-1.1673810482,51.0868377686],"type":"Point"}
}