{
  "type": "Feature",
  "properties": {
    "iso:country":"GB",
    "sg:address":"42 Queens Road",
    "sg:city":"Aberdeen",
    "sg:classifiers":[
        {
            "category":"Professional",
            "subcategory":"Employment Agencies",
            "type":"Services"
        }
    ],
    "sg:phone":"+44 1224 209222",
    "sg:postcode":"AB15 4YE",
    "sg:province":"Aberdeen City",
    "sg:tags":[
        "consultant"
    ],
    "wof:name":"Beyglen Ltd.",
    "wof:placetype":"venue"
},
  "geometry": {"coordinates":[-2.13508,57.141537],"type":"Point"}
}