{
  "type": "Feature",
  "properties": {
    "addr:full":"Unit B, Ashmere Terrace Reading Berkshire RG30 1DZ",
    "addr:postcode":"rg30 1dz",
    "addr:street":"Ashmere Terrace",
    "iso:country":"GB",
    "sg:address":"Unit B, Ashmere Terrace",
    "sg:city":"Reading",
    "sg:classifiers":[
        {
            "category":"Building & Trades",
            "subcategory":"Construction",
            "type":"Services"
        }
    ],
    "sg:phone":"+44 118 950 8929",
    "sg:postcode":"RG30 1DZ",
    "sg:province":"Berkshire",
    "sg:tags":[
        "supplier",
        "installers",
        "cladding"
    ],
    "wof:name":"Willmotts Plastic Building Products Ltd.",
    "wof:placetype":"venue"
},
  "geometry": {"coordinates":[-0.9929640293,51.4603805542],"type":"Point"}
}