{
  "type": "Feature",
  "properties": {
    "addr:full":"Wholesome Farm, Long Moss Lane, New Longton Preston Lancashire PR4 4SP",
    "addr:postcode":"pr4 4sp",
    "addr:street":"Long Moss Lane",
    "iso:country":"GB",
    "sg:address":"Wholesome Farm, Long Moss Lane, New Longton",
    "sg:city":"Preston",
    "sg:classifiers":[
        {
            "category":"Building & Trades",
            "subcategory":"Landscaping Services",
            "type":"Services"
        },
        {
            "category":"Home & Garden",
            "subcategory":"Garden Supply",
            "type":"Retail Goods"
        }
    ],
    "sg:phone":"+44 1772 612297",
    "sg:postcode":"PR4 4SP",
    "sg:province":"Lancashire",
    "sg:tags":[
        "bulb",
        "surgeon",
        "tree",
        "grower"
    ],
    "wof:name":"H J & S J Hosker",
    "wof:placetype":"venue"
},
  "geometry": {"coordinates":[-2.7464299202,53.7269325256],"type":"Point"}
}