{
  "type": "Feature",
  "properties": {
    "addr:full":"1 Leafield Way, Leafield Indstl Est Corsham Wiltshire SN13 9SU",
    "addr:housenumber":"1",
    "addr:postcode":"sn13 9su",
    "addr:street":"Leafield Way;Indstl Est",
    "iso:country":"GB",
    "sg:address":"1 Leafield Way, Leafield Indstl Est",
    "sg:city":"Corsham",
    "sg:classifiers":[
        {
            "category":"Autos & Motor Vehicles",
            "subcategory":"Auto Supplies",
            "type":"Retail Goods"
        },
        {
            "category":"Retail",
            "subcategory":"Repair Shop",
            "type":"Services"
        }
    ],
    "sg:phone":"+44 1225 811592",
    "sg:postcode":"SN13 9SU",
    "sg:province":"Wiltshire",
    "sg:tags":[
        "component",
        "maintenance"
    ],
    "wof:name":"Barnes Group (U K ) Ltd.",
    "wof:placetype":"venue"
},
  "geometry": {"coordinates":[-2.199009,51.422005],"type":"Point"}
}