{
  "type": "Feature",
  "properties": {
    "addr:full":"George Street Berkhamsted Bedfordshire HP4 2EG",
    "addr:postcode":"hp4 2eg",
    "addr:street":"George Street",
    "iso:country":"GB",
    "sg:address":"George Street",
    "sg:city":"Berkhamsted",
    "sg:classifiers":[
        {
            "category":"Bars & Pubs",
            "type":"Food & Drink"
        },
        {
            "category":"Community Center",
            "subcategory":"Social",
            "type":"Public Place"
        }
    ],
    "sg:phone":"+44 1442 864913",
    "sg:postcode":"HP4 2EG",
    "sg:province":"Bedfordshire",
    "sg:tags":[
        "pubs",
        "house",
        "inn",
        "activity"
    ],
    "wof:name":"The Rising Sun",
    "wof:placetype":"venue"
},
  "geometry": {"coordinates":[-0.5561280251,51.7597885132],"type":"Point"}
}