{
  "type": "Feature",
  "properties": {
    "iso:country":"GB",
    "sg:address":"63 Fore St",
    "sg:city":"Torpoint",
    "sg:classifiers":[
        {
            "category":"Food & Beverages",
            "subcategory":"Fruits & Vegetables",
            "type":"Retail Goods"
        }
    ],
    "sg:postcode":"PL11 2AB",
    "sg:province":"Cornwall",
    "sg:tags":[
        "greengrocer"
    ],
    "wof:name":"Cardew,P J,",
    "wof:placetype":"venue"
},
  "geometry": {"coordinates":[-4.195922,50.375969],"type":"Point"}
}