{
  "type": "Feature",
  "properties": {
    "iso:country":"GB",
    "sg:address":"3 Ardsheal Road",
    "sg:city":"Worthing",
    "sg:classifiers":[
        {
            "category":"Personal",
            "subcategory":"Beauty Salon",
            "type":"Services"
        }
    ],
    "sg:postcode":"BN14 7RN",
    "sg:province":"West Sussex",
    "sg:tags":[
        "unisex",
        "hairdresser"
    ],
    "wof:name":"Pzazz Hairdressing Co",
    "wof:placetype":"venue"
},
  "geometry": {"coordinates":[-0.3768329918,50.8293609619],"type":"Point"}
}