{
  "type": "Feature",
  "properties": {
    "iso:country":"GB",
    "sg:address":"67 Dalry Road",
    "sg:city":"Kilbirnie",
    "sg:classifiers":[
        {
            "category":"Building & Trades",
            "subcategory":"Construction",
            "type":"Services"
        }
    ],
    "sg:phone":"+44 1505 682534",
    "sg:postcode":"KA25 6JA",
    "sg:province":"North Ayrshire",
    "sg:tags":[
        "decorator",
        "painter"
    ],
    "wof:name":"John's Painters & Decorators",
    "wof:placetype":"venue"
},
  "geometry": {"coordinates":[-4.68947,55.745255],"type":"Point"}
}