{
  "type": "Feature",
  "properties": {
    "addr:full":"2 St. Johns La Milton Keynes Buckinghamshire MK19 6BP",
    "addr:housenumber":"2",
    "addr:postcode":"mk19 6bp",
    "addr:street":"St. Johns La",
    "iso:country":"GB",
    "sg:address":"2 St. Johns La",
    "sg:city":"Milton Keynes",
    "sg:classifiers":[
        {
            "category":"Shopping",
            "subcategory":"Computers & Home Electronics",
            "type":"Retail Goods"
        },
        {
            "category":"Building & Trades",
            "subcategory":"Construction",
            "type":"Services"
        }
    ],
    "sg:phone":"+44 1908 565899",
    "sg:postcode":"MK19 6BP",
    "sg:province":"Buckinghamshire",
    "sg:tags":[
        "supplier",
        "radio",
        "television",
        "erectors",
        "aerial"
    ],
    "wof:name":"Stony Stratford Aerials",
    "wof:placetype":"venue"
},
  "geometry": {"coordinates":[-0.911035,52.04834],"type":"Point"}
}