{
  "type": "Feature",
  "properties": {
    "iso:country":"GB",
    "sg:address":"59 Gladstone Road, Farnworth",
    "sg:city":"Bolton",
    "sg:classifiers":[
        {
            "category":"Personal",
            "subcategory":"Beauty Salon",
            "type":"Services"
        }
    ],
    "sg:phone":"+44 1204 791903",
    "sg:postcode":"BL4 7EL",
    "sg:province":"Lancashire",
    "sg:tags":[
        "unisex",
        "hairdresser"
    ],
    "wof:name":"Jane Micheals",
    "wof:placetype":"venue"
},
  "geometry": {"coordinates":[-2.402776,53.550919],"type":"Point"}
}