{
  "type": "Feature",
  "properties": {
    "addr:full":"3a Stafford Road, Oakengates Telford Shropshire TF2 6JH",
    "addr:housenumber":"3a",
    "addr:postcode":"tf2 6jh",
    "addr:street":"Stafford Road",
    "iso:country":"GB",
    "sg:address":"3a Stafford Road, Oakengates",
    "sg:city":"Telford",
    "sg:classifiers":[
        {
            "category":"Manufacturing",
            "subcategory":"Signs",
            "type":"Manufacturing & Wholesale Goods"
        }
    ],
    "sg:postcode":"TF2 6JH",
    "sg:province":"Shropshire",
    "sg:tags":[
        "nameplate"
    ],
    "wof:name":"Western Signs",
    "wof:placetype":"venue"
},
  "geometry": {"coordinates":[-2.4500439167,52.6961097717],"type":"Point"}
}