{
  "type": "Feature",
  "properties": {
    "iso:country":"GB",
    "sg:address":"Sabhal Mor Ostaig",
    "sg:city":"Isle Of Skye",
    "sg:classifiers":[
        {
            "category":"Arts & Performance",
            "subcategory":"Theater",
            "type":"Entertainment"
        }
    ],
    "sg:phone":"+44 1471 844443",
    "sg:postcode":"IV44 8RQ",
    "sg:province":"Highland",
    "sg:tags":[
        "hall",
        "theatre",
        "concert"
    ],
    "wof:name":"Tosg Gaelic Theatre Co.",
    "wof:placetype":"venue"
},
  "geometry": {"coordinates":[-5.87992,57.086269],"type":"Point"}
}