{
  "type": "Feature",
  "properties": {
    "iso:country":"GB",
    "sg:address":"Spring Valley Mills, Stanningley",
    "sg:city":"Pudsey",
    "sg:classifiers":[
        {
            "category":"Manufacturing",
            "subcategory":"Textiles",
            "type":"Manufacturing & Wholesale Goods"
        }
    ],
    "sg:phone":"+44 113 257 0391",
    "sg:postcode":"LS28 6DW",
    "sg:province":"West Yorkshire",
    "sg:tags":[
        "knitwear"
    ],
    "wof:name":"John Hainsworth & Sons Ltd.",
    "wof:placetype":"venue"
},
  "geometry": {"coordinates":[-1.659892,53.807858],"type":"Point"}
}