{
  "type": "Feature",
  "properties": {
    "addr:full":"Green Tree Warehousing, Tudworth Road Doncaster South Yorkshire DN7 6HD",
    "addr:postcode":"dn7 6hd",
    "addr:street":"Tudworth Road",
    "iso:country":"GB",
    "sg:address":"Green Tree Warehousing, Tudworth Road",
    "sg:city":"Doncaster",
    "sg:classifiers":[
        {
            "category":"Government",
            "subcategory":"Post Office",
            "type":"Public Place"
        }
    ],
    "sg:phone":"+44 1302 840000",
    "sg:postcode":"DN7 6HD",
    "sg:province":"South Yorkshire",
    "sg:tags":[
        "messenger",
        "courier"
    ],
    "wof:name":"Don Despatch International",
    "wof:placetype":"venue"
},
  "geometry": {"coordinates":[-0.9688199759,53.5809288025],"type":"Point"}
}