{
  "type": "Feature",
  "properties": {
    "addr:full":"21-23 Station Rd Henley On Thames Berkshire RG9 1AT",
    "addr:housenumber":"21-23",
    "addr:postcode":"rg9 1at",
    "addr:street":"Station Rd",
    "iso:country":"GB",
    "sg:address":"21-23 Station Rd",
    "sg:city":"Henley On Thames",
    "sg:classifiers":[
        {
            "category":"Banks & Credit Unions",
            "subcategory":"Financial Services",
            "type":"Services"
        }
    ],
    "sg:phone":"+44 1491 412192",
    "sg:postcode":"RG9 1AT",
    "sg:province":"Berkshire",
    "sg:tags":[
        "consultant"
    ],
    "wof:name":"Charles Hamer",
    "wof:placetype":"venue"
},
  "geometry": {"coordinates":[-0.9015840292,51.5345649719],"type":"Point"}
}