{
  "type": "Feature",
  "properties": {
    "iso:country":"GB",
    "sg:address":"27 Sherwell Valley Road",
    "sg:city":"Torquay",
    "sg:classifiers":[
        {
            "category":"Retail",
            "subcategory":"Auto Repair",
            "type":"Services"
        }
    ],
    "sg:phone":"+44 1803 690440",
    "sg:postcode":"TQ2 6EJ",
    "sg:province":"Devon",
    "sg:tags":[
        "modification",
        "garage"
    ],
    "wof:name":"Sherwell Valley Cars",
    "wof:placetype":"venue"
},
  "geometry": {"coordinates":[-3.551579,50.469437],"type":"Point"}
}