{
  "type": "Feature",
  "properties": {
    "iso:country":"GB",
    "sg:address":"214 Liverpool Road, Haydock",
    "sg:city":"St Helens",
    "sg:classifiers":[
        {
            "category":"Building & Trades",
            "subcategory":"Plumbing",
            "type":"Services"
        }
    ],
    "sg:postcode":"WA11 9SB",
    "sg:province":"Lancashire",
    "sg:tags":[
        "heating"
    ],
    "wof:name":"J C S Plumbing & Heating",
    "wof:placetype":"venue"
},
  "geometry": {"coordinates":[-2.675731,53.478767],"type":"Point"}
}