{
  "type": "Feature",
  "properties": {
    "addr:full":"Sandport Sawmill, Tayside Kinross Clackmannanshire KY13 8DN",
    "addr:postcode":"ky13 8dn",
    "iso:country":"GB",
    "sg:address":"Sandport Sawmill, Tayside",
    "sg:city":"Kinross",
    "sg:classifiers":[
        {
            "category":"Manufacturing",
            "subcategory":"Wood Products",
            "type":"Manufacturing & Wholesale Goods"
        }
    ],
    "sg:postcode":"KY13 8DN",
    "sg:province":"Clackmannanshire",
    "sg:tags":[
        "packaging",
        "crate",
        "pallets"
    ],
    "wof:name":"Castle Wightman (Pallets) Ltd.",
    "wof:placetype":"venue"
},
  "geometry": {"coordinates":[-3.4255139828,56.2113265991],"type":"Point"}
}