{
  "type": "Feature",
  "properties": {
    "addr:full":"154 Oxford St West, Guide Bridge Ashton-under-lyne Greater Manchester OL7 0NB",
    "addr:housenumber":"154",
    "addr:postcode":"ol7 0nb",
    "addr:street":"Oxford St;Bridge",
    "iso:country":"GB",
    "sg:address":"154 Oxford St West, Guide Bridge",
    "sg:city":"Ashton-under-lyne",
    "sg:classifiers":[
        {
            "category":"Building & Trades",
            "subcategory":"Construction",
            "type":"Services"
        }
    ],
    "sg:phone":"+44 161 343 4377",
    "sg:postcode":"OL7 0NB",
    "sg:province":"Greater Manchester",
    "sg:tags":[
        "door",
        "replacement"
    ],
    "wof:name":"A6 Roller Shutters Ltd.",
    "wof:placetype":"venue"
},
  "geometry": {"coordinates":[-2.1092329025,53.4771995544],"type":"Point"}
}