{
  "type": "Feature",
  "properties": {
    "iso:country":"GB",
    "sg:address":"11 Foreland Rd",
    "sg:city":"Bembridge",
    "sg:classifiers":[
        {
            "category":"Food & Beverages",
            "subcategory":"Meat & Fish",
            "type":"Retail Goods"
        }
    ],
    "sg:phone":"+44 1983 873334",
    "sg:postcode":"PO35 5XN",
    "sg:province":"Isle of Wight",
    "sg:tags":[
        "chip"
    ],
    "wof:name":"Captain Cooks",
    "wof:placetype":"venue"
},
  "geometry": {"coordinates":[-1.08832,50.690063],"type":"Point"}
}