{
  "type": "Feature",
  "properties": {
    "iso:country":"GB",
    "sg:address":"Willow Ho, Newhouse Rd",
    "sg:city":"Grangemouth",
    "sg:classifiers":[
        {
            "category":"Freight",
            "type":"Transportation"
        }
    ],
    "sg:postcode":"FK3 8LL",
    "sg:province":"Falkirk",
    "sg:tags":[
        "haulage",
        "road"
    ],
    "wof:name":"Stag European Express Ltd",
    "wof:placetype":"venue"
},
  "geometry": {"coordinates":[-3.7238938808,56.0093307495],"type":"Point"}
}