{
  "type": "Feature",
  "properties": {
    "addr:full":"272 Kingston Road Leatherhead Surrey KT22 7QA",
    "addr:housenumber":"272",
    "addr:postcode":"kt22 7qa",
    "addr:street":"Kingston Road",
    "iso:country":"GB",
    "sg:address":"272 Kingston Road",
    "sg:city":"Leatherhead",
    "sg:classifiers":[
        {
            "category":"Personal",
            "type":"Services"
        }
    ],
    "sg:postcode":"KT22 7QA",
    "sg:province":"Surrey",
    "sg:tags":[
        "wedding"
    ],
    "wof:name":"Buckland Carriage Co.",
    "wof:placetype":"venue"
},
  "geometry": {"coordinates":[-0.3332799971,51.3110923767],"type":"Point"}
}