{
  "type": "Feature",
  "properties": {
    "iso:country":"GB",
    "sg:address":"C/o Westmoor Consultancy, Westmoor Main Street Ulley",
    "sg:city":"Sheffield",
    "sg:classifiers":[
        {
            "category":"Professional",
            "subcategory":"Art Services",
            "type":"Services"
        }
    ],
    "sg:postcode":"S26 3YD",
    "sg:province":"South Yorkshire",
    "sg:tags":[
        "photographer"
    ],
    "wof:name":"Tony Holmes (Photography) Ltd.",
    "wof:placetype":"venue"
},
  "geometry": {"coordinates":[-1.304895,53.382084],"type":"Point"}
}