{
  "type": "Feature",
  "properties": {
    "addr:full":"16 Myrtle Walk Bingley West Yorkshire BD16 1AW",
    "addr:housenumber":"16",
    "addr:postcode":"bd16 1aw",
    "addr:street":"Myrtle Walk",
    "iso:country":"GB",
    "sg:address":"16 Myrtle Walk",
    "sg:city":"Bingley",
    "sg:classifiers":[
        {
            "category":"Home & Garden",
            "subcategory":"Household Appliances",
            "type":"Retail Goods"
        },
        {
            "category":"Communications",
            "type":"Services"
        }
    ],
    "sg:phone":"+44 1274 561892",
    "sg:postcode":"BD16 1AW",
    "sg:province":"West Yorkshire",
    "sg:tags":[
        "tv",
        "video",
        "electrical",
        "domestic",
        "radio"
    ],
    "wof:name":"Sameday Electric",
    "wof:placetype":"venue"
},
  "geometry": {"coordinates":[-1.8357330561,53.8438529968],"type":"Point"}
}