{
  "type": "Feature",
  "properties": {
    "addr:full":"36 Tower Centre Hoddesdon Essex EN11 8UD",
    "addr:housenumber":"36",
    "addr:postcode":"en11 8ud",
    "addr:street":"Tower Centre Hoddesdon",
    "iso:country":"GB",
    "sg:address":"36 Tower Centre",
    "sg:city":"Hoddesdon",
    "sg:classifiers":[
        {
            "category":"Shopping",
            "subcategory":"Pets & Pet Supplies",
            "type":"Retail Goods"
        }
    ],
    "sg:phone":"+44 1992 479074",
    "sg:postcode":"EN11 8UD",
    "sg:province":"Essex",
    "wof:name":"Allie's Pet Store",
    "wof:placetype":"venue"
},
  "geometry": {"coordinates":[-0.0132550001,51.7678413391],"type":"Point"}
}