{
  "type": "Feature",
  "properties": {
    "addr:full":"Kingsley Ho, Church La Cheltenham Gloucestershire GL51 5TQ",
    "addr:postcode":"gl51 5tq",
    "addr:street":"La",
    "iso:country":"GB",
    "sg:address":"Kingsley Ho, Church La",
    "sg:city":"Cheltenham",
    "sg:classifiers":[
        {
            "category":"Organizations",
            "subcategory":"Non-profit Organization",
            "type":"Services"
        }
    ],
    "sg:phone":"+44 1242 862994",
    "sg:postcode":"GL51 5TQ",
    "sg:province":"Gloucestershire",
    "sg:tags":[
        "organisation",
        "animal",
        "welfare"
    ],
    "wof:name":"British Small Animal Veterinary Association",
    "wof:placetype":"venue"
},
  "geometry": {"coordinates":[-2.07846,51.898048],"type":"Point"}
}