{
  "type": "Feature",
  "properties": {
    "addr:full":"6 Chapel Road Strathaven South Lanarkshire ML10 6NA",
    "addr:housenumber":"6",
    "addr:postcode":"ml10 6na",
    "addr:street":"Chapel Road",
    "iso:country":"GB",
    "sg:address":"6 Chapel Road",
    "sg:city":"Strathaven",
    "sg:classifiers":[
        {
            "category":"Communications",
            "subcategory":"Newspaper",
            "type":"Services"
        }
    ],
    "sg:postcode":"ML10 6NA",
    "sg:province":"South Lanarkshire",
    "sg:tags":[
        "magazine"
    ],
    "wof:name":"Echo's Newspaper",
    "wof:placetype":"venue"
},
  "geometry": {"coordinates":[-4.06711483,55.679309845],"type":"Point"}
}