{
  "type": "Feature",
  "properties": {
    "iso:country":"GB",
    "sg:address":"35 Wellington St",
    "sg:city":"Aldershot",
    "sg:classifiers":[
        {
            "category":"Banks & Credit Unions",
            "subcategory":"Financial Services",
            "type":"Services"
        }
    ],
    "sg:phone":"+44 1252 338811",
    "sg:postcode":"GU11 1DX",
    "sg:province":"Hampshire",
    "sg:tags":[
        "cashing",
        "cheque"
    ],
    "wof:name":"Cashwise",
    "wof:placetype":"venue"
},
  "geometry": {"coordinates":[-0.764239,51.249664],"type":"Point"}
}