{
  "type": "Feature",
  "properties": {
    "iso:country":"GB",
    "sg:address":"Unit 3 Apple Walk, Kembrey Park",
    "sg:city":"Swindon",
    "sg:classifiers":[
        {
            "category":"Communications",
            "type":"Services"
        }
    ],
    "sg:phone":"+44 1793 546120",
    "sg:postcode":"SN2 6BL",
    "sg:province":"Wiltshire",
    "sg:tags":[
        "telecommunication"
    ],
    "wof:name":"Ford Cellular Operations Ltd",
    "wof:placetype":"venue"
},
  "geometry": {"coordinates":[-1.77059,51.577461],"type":"Point"}
}