{
  "type": "Feature",
  "properties": {
    "iso:country":"GB",
    "sg:address":"24 Highbury Crescent",
    "sg:city":"London",
    "sg:classifiers":[
        {
            "category":"Organizations",
            "subcategory":"Non-profit Organization",
            "type":"Services"
        }
    ],
    "sg:phone":"+44 20 7704 5200",
    "sg:postcode":"N5 1RX",
    "sg:province":"Greater London",
    "sg:tags":[
        "organisation",
        "voluntary",
        "charity"
    ],
    "wof:name":"Research Institute for Consumer Affairs",
    "wof:placetype":"venue"
},
  "geometry": {"coordinates":[-0.102866,51.550327],"type":"Point"}
}