{
  "type": "Feature",
  "properties": {
    "iso:country":"GB",
    "sg:address":"Strode Road",
    "sg:city":"Wellingborough",
    "sg:classifiers":[
        {
            "category":"Retail",
            "subcategory":"Funeral Services",
            "type":"Services"
        }
    ],
    "sg:phone":"+44 1933 227147",
    "sg:postcode":"NN8 1JE",
    "sg:province":"Northamptonshire",
    "wof:name":"Co-Operative Funeral Services",
    "wof:placetype":"venue"
},
  "geometry": {"coordinates":[-0.68764,52.30407],"type":"Point"}
}