{
  "type": "Feature",
  "properties": {
    "iso:country":"GB",
    "sg:address":"6 Dock Road",
    "sg:city":"Lytham St Annes",
    "sg:classifiers":[
        {
            "category":"Autos & Motor Vehicles",
            "subcategory":"Auto Supplies",
            "type":"Retail Goods"
        }
    ],
    "sg:phone":"+44 1253 794671",
    "sg:postcode":"FY8 5HG",
    "sg:province":"Lancashire",
    "sg:tags":[
        "tyre"
    ],
    "wof:name":"Lytham Tyres & Exhausts",
    "wof:placetype":"venue"
},
  "geometry": {"coordinates":[-2.944048,53.740841],"type":"Point"}
}