{
  "type": "Feature",
  "properties": {
    "iso:country":"GB",
    "sg:address":"2 Rosenau Cotts, Aldenham Road, Elstree",
    "sg:city":"Borehamwood",
    "sg:classifiers":[
        {
            "category":"Building & Trades",
            "subcategory":"Construction",
            "type":"Services"
        }
    ],
    "sg:postcode":"WD6 3BD",
    "sg:province":"Hertfordshire",
    "sg:tags":[
        "roofing"
    ],
    "wof:name":"Aldenham Roofing",
    "wof:placetype":"venue"
},
  "geometry": {"coordinates":[-0.298679,51.644112],"type":"Point"}
}