{
  "type": "Feature",
  "properties": {
    "iso:country":"GB",
    "sg:address":"20 Avon Road, Astley",
    "sg:city":"Manchester",
    "sg:classifiers":[
        {
            "category":"Home & Garden",
            "subcategory":"Household Appliances",
            "type":"Retail Goods"
        },
        {
            "category":"Professional",
            "subcategory":"Detective & Security Services",
            "type":"Services"
        }
    ],
    "sg:phone":"+44 1942 879502",
    "sg:postcode":"M29 7HN",
    "sg:province":"Greater Manchester",
    "sg:tags":[
        "burglar",
        "alarm",
        "system",
        "refrigeration",
        "air conditioning"
    ],
    "wof:name":"K & S Services",
    "wof:placetype":"venue"
},
  "geometry": {"coordinates":[-2.452321,53.506138],"type":"Point"}
}