{
  "type": "Feature",
  "properties": {
    "addr:full":"99 Simpkin St Wigan Lancashire WN2 5PS",
    "addr:housenumber":"99",
    "addr:postcode":"wn2 5ps",
    "addr:street":"Simpkin St",
    "iso:country":"GB",
    "sg:address":"99 Simpkin St",
    "sg:city":"Wigan",
    "sg:classifiers":[
        {
            "category":"Retail",
            "subcategory":"Driving School",
            "type":"Services"
        }
    ],
    "sg:phone":"+44 1942 861903",
    "sg:postcode":"WN2 5PS",
    "sg:province":"Lancashire",
    "wof:name":"Paul Aldred",
    "wof:placetype":"venue"
},
  "geometry": {"coordinates":[-2.5893759727,53.5157470703],"type":"Point"}
}