{
  "type": "Feature",
  "properties": {
    "addr:full":"Ferintosh Business Centre, Station Road Dingwall Highland IV15 9JE",
    "addr:postcode":"iv15 9je",
    "addr:street":"Station Road",
    "iso:country":"GB",
    "sg:address":"Ferintosh Business Centre, Station Road",
    "sg:city":"Dingwall",
    "sg:classifiers":[
        {
            "category":"Professional",
            "subcategory":"Management & Consulting",
            "type":"Services"
        }
    ],
    "sg:phone":"+44 1349 865777",
    "sg:postcode":"IV15 9JE",
    "sg:province":"Highland",
    "sg:tags":[
        "consultant",
        "training",
        "business"
    ],
    "wof:name":"Access Training",
    "wof:placetype":"venue"
},
  "geometry": {"coordinates":[-4.4314479828,57.5961799622],"type":"Point"}
}