{
  "type": "Feature",
  "properties": {
    "addr:full":"Scala House, Holloway Circus Birmingham West Midlands B1 1EQ",
    "addr:postcode":"b1 1eq",
    "addr:street":"Holloway Circus",
    "iso:country":"GB",
    "sg:address":"Scala House, Holloway Circus",
    "sg:city":"Birmingham",
    "sg:classifiers":[
        {
            "category":"Professional",
            "subcategory":"Business Services",
            "type":"Services"
        }
    ],
    "sg:phone":"+44 121 643 9269",
    "sg:postcode":"B1 1EQ",
    "sg:province":"West Midlands",
    "sg:tags":[
        "trade"
    ],
    "wof:name":"British Rubber Manufacturing Association",
    "wof:placetype":"venue"
},
  "geometry": {"coordinates":[-1.9018340111,52.474281311],"type":"Point"}
}