{
  "type": "Feature",
  "properties": {
    "addr:full":"Cluden Road, Northam Bideford Devon EX39 3QF",
    "addr:postcode":"ex39 3qf",
    "addr:street":"Cluden Road",
    "iso:country":"GB",
    "sg:address":"Cluden Road, Northam",
    "sg:city":"Bideford",
    "sg:classifiers":[
        {
            "category":"Health Services",
            "subcategory":"Nursing And Care Facility",
            "type":"Services"
        }
    ],
    "sg:phone":"+44 1237 476932",
    "sg:postcode":"EX39 3QF",
    "sg:province":"Devon",
    "sg:tags":[
        "home"
    ],
    "wof:name":"The Warren Nursing Home",
    "wof:placetype":"venue"
},
  "geometry": {"coordinates":[-4.2169761658,51.0370941162],"type":"Point"}
}