{
  "type": "Feature",
  "properties": {
    "addr:full":"14a Musters Rd, West Bridgford Nottingham Nottinghamshire NG2 7PL",
    "addr:housenumber":"14a",
    "addr:postcode":"ng2 7pl",
    "addr:street":"Musters Rd",
    "iso:country":"GB",
    "sg:address":"14a Musters Rd, West Bridgford",
    "sg:city":"Nottingham",
    "sg:classifiers":[
        {
            "category":"Taxi",
            "type":"Transportation"
        }
    ],
    "sg:phone":"+44 115 914 5145",
    "sg:postcode":"NG2 7PL",
    "sg:province":"Nottinghamshire",
    "sg:tags":[
        "mini",
        "cab"
    ],
    "wof:name":"Sky Cars",
    "wof:placetype":"venue"
},
  "geometry": {"coordinates":[-1.133235,52.935635],"type":"Point"}
}