{
  "type": "Feature",
  "properties": {
    "iso:country":"GB",
    "sg:address":"Longport",
    "sg:city":"Canterbury",
    "sg:classifiers":[
        {
            "category":"Education",
            "subcategory":"School",
            "type":"Public Place"
        }
    ],
    "sg:phone":"+44 1227 464600",
    "sg:postcode":"CT1 1PH",
    "sg:province":"Kent",
    "sg:tags":[
        "college"
    ],
    "wof:name":"Barton Court Grammar School",
    "wof:placetype":"venue"
},
  "geometry": {"coordinates":[1.09121,51.276741],"type":"Point"}
}