{
  "type": "Feature",
  "properties": {
    "addr:full":"2a Wornington Road London Greater London W10 5QW",
    "addr:housenumber":"2a",
    "addr:postcode":"w10 5qw",
    "addr:street":"Wornington Road",
    "iso:country":"GB",
    "sg:address":"2a Wornington Road",
    "sg:city":"London",
    "sg:classifiers":[
        {
            "category":"Community Center",
            "subcategory":"Youth",
            "type":"Public Place"
        },
        {
            "category":"Government",
            "subcategory":"Office",
            "type":"Public Place"
        }
    ],
    "sg:phone":"+44 20 8960 6238",
    "sg:postcode":"W10 5QW",
    "sg:province":"Greater London",
    "sg:tags":[
        "organisation",
        "local",
        "centre"
    ],
    "wof:name":"Golborne Youth Development Unit",
    "wof:placetype":"venue"
},
  "geometry": {"coordinates":[-0.205229,51.52092],"type":"Point"}
}