{
  "type": "Feature",
  "properties": {
    "addr:full":"Duke Street Doncaster South Yorkshire DN1 3EA",
    "addr:postcode":"dn1 3ea",
    "addr:street":"Duke Street",
    "iso:country":"GB",
    "sg:address":"Duke Street",
    "sg:city":"Doncaster",
    "sg:classifiers":[
        {
            "category":"Bars & Pubs",
            "subcategory":"Nightclub",
            "type":"Food & Drink"
        }
    ],
    "sg:phone":"+44 1302 367061",
    "sg:postcode":"DN1 3EA",
    "sg:province":"South Yorkshire",
    "sg:tags":[
        "club",
        "night"
    ],
    "wof:name":"Karisma",
    "wof:placetype":"venue"
},
  "geometry": {"coordinates":[-1.1353939772,53.5214500427],"type":"Point"}
}