{
  "type": "Feature",
  "properties": {
    "addr:full":"27 Dunveth Rd Wadebridge Cornwall PL27 7XD",
    "addr:housenumber":"27",
    "addr:postcode":"pl27 7xd",
    "addr:street":"Dunveth Rd",
    "iso:country":"GB",
    "sg:address":"27 Dunveth Rd",
    "sg:city":"Wadebridge",
    "sg:classifiers":[
        {
            "category":"Professional",
            "subcategory":"Detective & Security Services",
            "type":"Services"
        }
    ],
    "sg:phone":"+44 1208 815739",
    "sg:postcode":"PL27 7XD",
    "sg:province":"Cornwall",
    "wof:name":"Acacia Security",
    "wof:placetype":"venue"
},
  "geometry": {"coordinates":[-4.843229,50.515881],"type":"Point"}
}