{
  "type": "Feature",
  "properties": {
    "iso:country":"GB",
    "sg:address":"8 Exchange Quay",
    "sg:city":"Salford",
    "sg:classifiers":[
        {
            "category":"Real Estate",
            "subcategory":"Developer",
            "type":"Services"
        }
    ],
    "sg:phone":"+44 161 872 9000",
    "sg:postcode":"M5 3EJ",
    "sg:province":"Greater Manchester",
    "sg:tags":[
        "property"
    ],
    "wof:name":"Esterre Property Management",
    "wof:placetype":"venue"
},
  "geometry": {"coordinates":[-2.2819569111,53.4656867981],"type":"Point"}
}