{
  "type": "Feature",
  "properties": {
    "addr:full":"Unit 39, St Enoch Centre, St Enoch Square Glasgow Glasgow City G1 4BW",
    "addr:housenumber":"unit 39",
    "addr:postcode":"g1 4bw",
    "addr:street":"St Enoch Centre St Enoch Square",
    "iso:country":"GB",
    "sg:address":"Unit 39, St Enoch Centre, St Enoch Square",
    "sg:city":"Glasgow",
    "sg:classifiers":[
        {
            "category":"Shopping",
            "subcategory":"Shoes",
            "type":"Retail Goods"
        }
    ],
    "sg:phone":"+44 141 204 2923",
    "sg:postcode":"G1 4BW",
    "sg:province":"Glasgow City",
    "sg:tags":[
        "shop"
    ],
    "wof:name":"K Shoes",
    "wof:placetype":"venue"
},
  "geometry": {"coordinates":[-4.254979,55.857254],"type":"Point"}
}