{
  "type": "Feature",
  "properties": {
    "addr:full":"268 High Street Slough Berkshire SL1 1NB",
    "addr:housenumber":"268",
    "addr:postcode":"sl1 1nb",
    "addr:street":"High Street",
    "iso:country":"GB",
    "sg:address":"268 High Street",
    "sg:city":"Slough",
    "sg:classifiers":[
        {
            "category":"Insurance",
            "subcategory":"Insurance Agent",
            "type":"Services"
        }
    ],
    "sg:phone":"+44 1753 516299",
    "sg:postcode":"SL1 1NB",
    "sg:province":"Berkshire",
    "wof:name":"Endsleigh Insurance Services Ltd.",
    "wof:placetype":"venue"
},
  "geometry": {"coordinates":[-0.586811,51.507393],"type":"Point"}
}