{
  "type": "Feature",
  "properties": {
    "addr:full":"25 Featherstone Road Southall Greater London UB2 5AB",
    "addr:housenumber":"25",
    "addr:postcode":"ub2 5ab",
    "addr:street":"Featherstone Road",
    "iso:country":"GB",
    "sg:address":"25 Featherstone Road",
    "sg:city":"Southall",
    "sg:classifiers":[
        {
            "category":"Shopping",
            "type":"Retail Goods"
        }
    ],
    "sg:postcode":"UB2 5AB",
    "sg:province":"Greater London",
    "sg:tags":[
        "part",
        "accessory"
    ],
    "wof:name":"Lyall Motors",
    "wof:placetype":"venue"
},
  "geometry": {"coordinates":[-0.3839510083,51.5021629333],"type":"Point"}
}