{
  "type": "Feature",
  "properties": {
    "addr:full":"Margery Flatt Farm, Newbiggen Lane, Lanchester Durham Durham DH7 0RS",
    "addr:postcode":"dh7 0rs",
    "addr:street":"Margery Flatt Farm Newbiggen Lane",
    "iso:country":"GB",
    "sg:address":"Margery Flatt Farm, Newbiggen Lane, Lanchester",
    "sg:city":"Durham",
    "sg:classifiers":[
        {
            "category":"Professional",
            "subcategory":"Engineering",
            "type":"Services"
        }
    ],
    "sg:phone":"+44 1207 529540",
    "sg:postcode":"DH7 0RS",
    "sg:province":"Durham",
    "sg:tags":[
        "electronic",
        "engineer"
    ],
    "wof:name":"Calltronics",
    "wof:placetype":"venue"
},
  "geometry": {"coordinates":[-1.743283987,54.8209991455],"type":"Point"}
}