{
  "type": "Feature",
  "properties": {
    "addr:full":"Digby Street Ilkeston Derbyshire DE7 5TS",
    "addr:postcode":"de7 5ts",
    "addr:street":"Digby Street",
    "iso:country":"GB",
    "sg:address":"Digby Street",
    "sg:city":"Ilkeston",
    "sg:classifiers":[
        {
            "category":"Manufacturing",
            "subcategory":"Wood Products",
            "type":"Manufacturing & Wholesale Goods"
        }
    ],
    "sg:phone":"+44 115 932 4391",
    "sg:postcode":"DE7 5TS",
    "sg:province":"Derbyshire",
    "sg:tags":[
        "packaging",
        "crate",
        "pallets"
    ],
    "wof:name":"Sidlaw Packaging Uk",
    "wof:placetype":"venue"
},
  "geometry": {"coordinates":[-1.2959040403,52.977016449],"type":"Point"}
}