{
  "type": "Feature",
  "properties": {
    "addr:full":"Orchard Street Preston Lancashire PR25 3SH",
    "addr:postcode":"pr25 3sh",
    "addr:street":"Orchard Street",
    "iso:country":"GB",
    "sg:address":"Orchard Street",
    "sg:city":"Preston",
    "sg:classifiers":[
        {
            "category":"Farming",
            "subcategory":"Nursery",
            "type":"Manufacturing & Wholesale Goods"
        },
        {
            "category":"Education",
            "subcategory":"Preschool",
            "type":"Public Place"
        }
    ],
    "sg:phone":"+44 1772 459199",
    "sg:postcode":"PR25 3SH",
    "sg:province":"Lancashire",
    "sg:tags":[
        "school",
        "creche"
    ],
    "wof:name":"Orchard House Nursery School",
    "wof:placetype":"venue"
},
  "geometry": {"coordinates":[-2.700894,53.76012],"type":"Point"}
}