{
  "type": "Feature",
  "properties": {
    "addr:full":"Redhills Business Park, Redhills Penrith Cumbria CA11 0DT",
    "addr:postcode":"ca11 0dt",
    "addr:street":"Redhills",
    "iso:country":"GB",
    "sg:address":"Redhills Business Park, Redhills",
    "sg:city":"Penrith",
    "sg:classifiers":[
        {
            "category":"Professional",
            "subcategory":"Art Services",
            "type":"Services"
        }
    ],
    "sg:phone":"+44 1768 864171",
    "sg:postcode":"CA11 0DT",
    "sg:province":"Cumbria",
    "sg:tags":[
        "graphic",
        "designer"
    ],
    "wof:name":"Corporate Visual Communications Ltd.",
    "wof:placetype":"venue"
},
  "geometry": {"coordinates":[-2.7698469162,54.6497383118],"type":"Point"}
}