{
  "type": "Feature",
  "properties": {
    "iso:country":"GB",
    "sg:address":"58 Fulwood Road, Little Sutton",
    "sg:city":"Ellesmere Port",
    "sg:classifiers":[
        {
            "category":"Building & Trades",
            "subcategory":"Plumbing",
            "type":"Services"
        }
    ],
    "sg:phone":"+44 151 339 7916",
    "sg:postcode":"CH66 3RT",
    "sg:province":"Cheshire",
    "sg:tags":[
        "heating"
    ],
    "wof:name":"Philip John Jones",
    "wof:placetype":"venue"
},
  "geometry": {"coordinates":[-2.9399271011,53.2809486389],"type":"Point"}
}