{
  "type": "Feature",
  "properties": {
    "iso:country":"GB",
    "sg:address":"Hammond House, 65b Croydon Road",
    "sg:city":"Caterham",
    "sg:classifiers":[
        {
            "category":"Utilities",
            "subcategory":"Natural Gas",
            "type":"Services"
        }
    ],
    "sg:phone":"+44 1883 341028",
    "sg:postcode":"CR3 6PB",
    "sg:province":"Surrey",
    "sg:tags":[
        "consultant",
        "air conditioning"
    ],
    "wof:name":"M R B S Ltd.",
    "wof:placetype":"venue"
},
  "geometry": {"coordinates":[-0.078593,51.283566],"type":"Point"}
}