{
  "type": "Feature",
  "properties": {
    "iso:country":"GB",
    "sg:address":"4 Oak Grove Road, Penge",
    "sg:city":"London",
    "sg:classifiers":[
        {
            "category":"Retail",
            "subcategory":"Auto Repair",
            "type":"Services"
        }
    ],
    "sg:phone":"+44 20 8659 7618",
    "sg:postcode":"SE20 7RQ",
    "sg:province":"Greater London",
    "sg:tags":[
        "modification",
        "garage"
    ],
    "wof:name":"Parsons Autos",
    "wof:placetype":"venue"
},
  "geometry": {"coordinates":[-0.058412,51.408943],"type":"Point"}
}