{
  "type": "Feature",
  "properties": {
    "addr:full":"Unit 14 Westcliff-on-sea Essex SS0 7PD",
    "addr:housenumber":"unit 14",
    "addr:postcode":"ss0 7pd",
    "iso:country":"GB",
    "sg:address":"Unit 14",
    "sg:city":"Westcliff-on-sea",
    "sg:classifiers":[
        {
            "category":"Shopping",
            "subcategory":"Books",
            "type":"Retail Goods"
        }
    ],
    "sg:postcode":"SS0 7PD",
    "sg:province":"Essex",
    "wof:name":"Desert Island Books Ltd.",
    "wof:placetype":"venue"
},
  "geometry": {"coordinates":[0.698585,51.536034],"type":"Point"}
}