{
  "type": "Feature",
  "properties": {
    "addr:full":"8 Capitol Park, Pearce Way Gloucester Gloucestershire GL2 5YD",
    "addr:housenumber":"8",
    "addr:postcode":"gl2 5yd",
    "addr:street":"Capitol;Pearce Way",
    "iso:country":"GB",
    "sg:address":"8 Capitol Park, Pearce Way",
    "sg:city":"Gloucester",
    "sg:classifiers":[
        {
            "category":"Autos & Motor Vehicles",
            "subcategory":"Auto Supplies",
            "type":"Retail Goods"
        },
        {
            "category":"Shopping",
            "type":"Retail Goods"
        }
    ],
    "sg:phone":"+44 1452 526406",
    "sg:postcode":"GL2 5YD",
    "sg:province":"Gloucestershire",
    "sg:tags":[
        "car",
        "part",
        "accessory"
    ],
    "wof:name":"Foreign Auto Parts",
    "wof:placetype":"venue"
},
  "geometry": {"coordinates":[-2.2653200626,51.8389511108],"type":"Point"}
}