{
  "type": "Feature",
  "properties": {
    "iso:country":"GB",
    "sg:address":"Euston Road",
    "sg:city":"Bangor",
    "sg:classifiers":[
        {
            "category":"Organizations",
            "subcategory":"Membership Organization",
            "type":"Services"
        }
    ],
    "sg:phone":"+44 1248 353666",
    "sg:postcode":"LL57 2YP",
    "sg:province":"Gwynedd",
    "sg:tags":[
        "club",
        "social"
    ],
    "wof:name":"Bangor Railway Institute & Club",
    "wof:placetype":"venue"
},
  "geometry": {"coordinates":[-4.138909,53.2229],"type":"Point"}
}