{
  "type": "Feature",
  "properties": {
    "iso:country":"GB",
    "sg:address":"132 Compton Road",
    "sg:city":"Wolverhampton",
    "sg:classifiers":[
        {
            "category":"Real Estate",
            "subcategory":"Architect",
            "type":"Services"
        }
    ],
    "sg:phone":"+44 1902 427067",
    "sg:postcode":"WV3 9QB",
    "sg:province":"Staffordshire",
    "wof:name":"Building Design Practice Ltd.",
    "wof:placetype":"venue"
},
  "geometry": {"coordinates":[-2.148936,52.586254],"type":"Point"}
}