{
  "type": "Feature",
  "properties": {
    "iso:country":"GB",
    "sg:address":"106 Heath Road",
    "sg:city":"Twickenham",
    "sg:classifiers":[
        {
            "category":"Cafe",
            "type":"Food & Drink"
        },
        {
            "category":"Food & Beverages",
            "subcategory":"Groceries & Convenience Stores",
            "type":"Retail Goods"
        }
    ],
    "sg:postcode":"TW1 4BW",
    "sg:province":"Greater London",
    "sg:tags":[
        "shop",
        "tea",
        "fish",
        "room",
        "chip"
    ],
    "wof:name":"G Zarcilla",
    "wof:placetype":"venue"
},
  "geometry": {"coordinates":[-0.335105,51.445492],"type":"Point"}
}