{
  "type": "Feature",
  "properties": {
    "iso:country":"GB",
    "sg:address":"1 Feathers Lane",
    "sg:city":"Basingstoke",
    "sg:classifiers":[
        {
            "category":"Home & Garden",
            "subcategory":"Furniture",
            "type":"Retail Goods"
        },
        {
            "category":"Shopping",
            "subcategory":"Used Merchandise",
            "type":"Retail Goods"
        }
    ],
    "sg:phone":"+44 1256 332266",
    "sg:postcode":"RG21 7AS",
    "sg:province":"Hampshire",
    "sg:tags":[
        "shop",
        "second-hand",
        "outlet"
    ],
    "wof:name":"Foley's Furniture",
    "wof:placetype":"venue"
},
  "geometry": {"coordinates":[-1.086409,51.263119],"type":"Point"}
}