{
  "type": "Feature",
  "properties": {
    "addr:full":"Overland, Ash Canterbury Kent CT3 2LD",
    "addr:postcode":"ct3 2ld",
    "addr:street":"Overland Ash",
    "iso:country":"GB",
    "sg:address":"Overland, Ash",
    "sg:city":"Canterbury",
    "sg:classifiers":[
        {
            "category":"Professional",
            "type":"Services"
        },
        {
            "category":"Food & Beverages",
            "subcategory":"Farmers Market",
            "type":"Retail Goods"
        }
    ],
    "sg:phone":"+44 1304 812283",
    "sg:postcode":"CT3 2LD",
    "sg:province":"Kent",
    "sg:tags":[
        "farm",
        "agricultural",
        "gardener",
        "contractor"
    ],
    "wof:name":"PETER ROWCROFT",
    "wof:placetype":"venue"
},
  "geometry": {"coordinates":[1.2595260143,51.2916297913],"type":"Point"}
}