{
  "type": "Feature",
  "properties": {
    "addr:full":"31 Birches Barn Road, Bradmore Wolverhampton Staffordshire WV3 7BL",
    "addr:housenumber":"31",
    "addr:postcode":"wv3 7bl",
    "addr:street":"Birches Barn Road",
    "iso:country":"GB",
    "sg:address":"31 Birches Barn Road, Bradmore",
    "sg:city":"Wolverhampton",
    "sg:classifiers":[
        {
            "category":"Professional",
            "type":"Services"
        },
        {
            "category":"Home & Garden",
            "subcategory":"Household Appliances",
            "type":"Retail Goods"
        }
    ],
    "sg:phone":"+44 1902 338320",
    "sg:postcode":"WV3 7BL",
    "sg:province":"Staffordshire",
    "sg:tags":[
        "entertainer",
        "electrical"
    ],
    "wof:name":"Penn Electrical Services",
    "wof:placetype":"venue"
},
  "geometry": {"coordinates":[-2.153158,52.575169],"type":"Point"}
}