{
  "type": "Feature",
  "properties": {
    "addr:full":"Unit 9 West Point, Enterprise Park, Clarence Avenue Manchester Cheshire M17 1QS",
    "addr:housenumber":"unit 9",
    "addr:postcode":"m17 1qs",
    "addr:street":"Clarence Avenue",
    "iso:country":"GB",
    "sg:address":"Unit 9 West Point, Enterprise Park, Clarence Avenue",
    "sg:city":"Manchester",
    "sg:classifiers":[
        {
            "category":"Freight",
            "type":"Transportation"
        }
    ],
    "sg:phone":"+44 161 872 4971",
    "sg:postcode":"M17 1QS",
    "sg:province":"Cheshire",
    "sg:tags":[
        "forwarders"
    ],
    "wof:name":"J Heebink (Manchester) Ltd.",
    "wof:placetype":"venue"
},
  "geometry": {"coordinates":[-2.3330440521,53.4721755981],"type":"Point"}
}