{
  "type": "Feature",
  "properties": {
    "addr:full":"Manchester Road, Mossley Ashton Under Lyne Greater Manchester OL5 9BB",
    "addr:postcode":"ol5 9bb",
    "addr:street":"Manchester Road;Under Lyne",
    "iso:country":"GB",
    "sg:address":"Manchester Road, Mossley",
    "sg:city":"Ashton Under Lyne",
    "sg:classifiers":[
        {
            "category":"Retail",
            "subcategory":"Auto Repair",
            "type":"Services"
        }
    ],
    "sg:phone":"+44 1457 834400",
    "sg:postcode":"OL5 9BB",
    "sg:province":"Greater Manchester",
    "sg:tags":[
        "car",
        "upholsterer"
    ],
    "wof:name":"Sovereign Motor Vehicle Upholsters",
    "wof:placetype":"venue"
},
  "geometry": {"coordinates":[-2.0255858898,53.5295639038],"type":"Point"}
}