{
  "type": "Feature",
  "properties": {
    "addr:full":"46 Church La York East Riding of Yorkshire YO2 1QG",
    "addr:housenumber":"46",
    "addr:postcode":"yo2 1qg",
    "addr:street":"Church La York",
    "iso:country":"GB",
    "sg:address":"46 Church La",
    "sg:city":"York",
    "sg:classifiers":[
        {
            "category":"Health Services",
            "subcategory":"Doctor",
            "type":"Services"
        }
    ],
    "sg:phone":"+44 1904 706917",
    "sg:postcode":"YO2 1QG",
    "sg:province":"East Riding of Yorkshire",
    "sg:tags":[
        "practitioners"
    ],
    "wof:name":"Iredale Dr J L",
    "wof:placetype":"venue"
},
  "geometry": {"coordinates":[-1.09644,53.922863],"type":"Point"}
}