{
  "type": "Feature",
  "properties": {
    "iso:country":"GB",
    "sg:address":"Gothic House, Church Street",
    "sg:city":"Welwyn",
    "sg:classifiers":[
        {
            "category":"Building & Trades",
            "subcategory":"Construction",
            "type":"Services"
        }
    ],
    "sg:postcode":"AL6 9LW",
    "sg:province":"Hertfordshire",
    "sg:tags":[
        "restoration",
        "refurbishment"
    ],
    "wof:name":"Huguenot Interiors",
    "wof:placetype":"venue"
},
  "geometry": {"coordinates":[-0.2133679986,51.8315887451],"type":"Point"}
}