{
  "type": "Feature",
  "properties": {
    "addr:full":"Unit 9 Offerton Precinct Stockport Cheshire SK2 5RR",
    "addr:housenumber":"unit 9",
    "addr:postcode":"sk2 5rr",
    "addr:street":"Precinct",
    "iso:country":"GB",
    "sg:address":"Unit 9 Offerton Precinct",
    "sg:city":"Stockport",
    "sg:classifiers":[
        {
            "category":"Food & Beverages",
            "subcategory":"Bakery",
            "type":"Retail Goods"
        }
    ],
    "sg:postcode":"SK2 5RR",
    "sg:province":"Cheshire",
    "sg:tags":[
        "baker"
    ],
    "wof:name":"The Golden Harvest",
    "wof:placetype":"venue"
},
  "geometry": {"coordinates":[-2.1073770523,53.395740509],"type":"Point"}
}