{
  "type": "Feature",
  "properties": {
    "addr:full":"114 Freeman Street Grimsby Lincolnshire DN32 7AJ",
    "addr:housenumber":"114",
    "addr:postcode":"dn32 7aj",
    "addr:street":"Freeman Street",
    "iso:country":"GB",
    "sg:address":"114 Freeman Street",
    "sg:city":"Grimsby",
    "sg:classifiers":[
        {
            "category":"Home & Garden",
            "subcategory":"Home Furnishings",
            "type":"Retail Goods"
        },
        {
            "category":"Building & Trades",
            "subcategory":"Construction",
            "type":"Services"
        }
    ],
    "sg:phone":"+44 1472 345780",
    "sg:postcode":"DN32 7AJ",
    "sg:province":"Lincolnshire",
    "sg:tags":[
        "mantelpiece",
        "fireplace"
    ],
    "wof:name":"Period Design Centre Grimsby Ltd",
    "wof:placetype":"venue"
},
  "geometry": {"coordinates":[-0.073823,53.571213],"type":"Point"}
}