{
  "type": "Feature",
  "properties": {
    "addr:full":"28-32 Princes Drive Colwyn Bay Conwy LL29 8LA",
    "addr:housenumber":"28-32",
    "addr:postcode":"ll29 8la",
    "addr:street":"Princes Drive",
    "iso:country":"GB",
    "sg:address":"28-32 Princes Drive",
    "sg:city":"Colwyn Bay",
    "sg:classifiers":[
        {
            "category":"Shopping",
            "subcategory":"Optician",
            "type":"Retail Goods"
        },
        {
            "category":"Health Services",
            "subcategory":"Optometrist",
            "type":"Services"
        }
    ],
    "sg:phone":"+44 1492 530122",
    "sg:postcode":"LL29 8LA",
    "sg:province":"Conwy",
    "sg:tags":[
        "dispensing"
    ],
    "wof:name":"Saunders Opticians",
    "wof:placetype":"venue"
},
  "geometry": {"coordinates":[-3.72797,53.296925],"type":"Point"}
}