{
  "type": "Feature",
  "properties": {
    "iso:country":"GB",
    "sg:address":"6 Kimberley Rd",
    "sg:city":"Croydon",
    "sg:classifiers":[
        {
            "category":"Building & Trades",
            "subcategory":"Construction",
            "type":"Services"
        }
    ],
    "sg:phone":"+44 20 8684 0342",
    "sg:postcode":"CR0 2PU",
    "sg:province":"Surrey",
    "sg:tags":[
        "dry",
        "lining",
        "plasterers",
        "screeders"
    ],
    "wof:name":"Adrian Parsons",
    "wof:placetype":"venue"
},
  "geometry": {"coordinates":[-0.1055760011,51.3901481628],"type":"Point"}
}