{
  "type": "Feature",
  "properties": {
    "iso:country":"GB",
    "sg:address":"Suite 6, 8 Broomburn Drive",
    "sg:city":"Glasgow",
    "sg:classifiers":[
        {
            "category":"Professional",
            "subcategory":"Computer Services",
            "type":"Services"
        }
    ],
    "sg:phone":"+44 141 577 7644",
    "sg:postcode":"G77 5JL",
    "sg:province":"East Ayrshire",
    "sg:tags":[
        "system",
        "software"
    ],
    "wof:name":"The Fridge",
    "wof:placetype":"venue"
},
  "geometry": {"coordinates":[-4.314247,55.774483],"type":"Point"}
}