{
  "type": "Feature",
  "properties": {
    "iso:country":"GB",
    "sg:address":"81 East St, Bedminster",
    "sg:city":"Bristol",
    "sg:classifiers":[
        {
            "category":"Food & Beverages",
            "subcategory":"Supermarket",
            "type":"Retail Goods"
        }
    ],
    "sg:postcode":"BS3 4EX",
    "sg:province":"City of Bristol",
    "wof:name":"Boon,Rod,",
    "wof:placetype":"venue"
},
  "geometry": {"coordinates":[-2.597386,51.441738],"type":"Point"}
}