{
  "type": "Feature",
  "properties": {
    "iso:country":"GB",
    "sg:address":"Holme Lea Residential Care Home, 2 Alton Road",
    "sg:city":"Ross-on-wye",
    "sg:classifiers":[
        {
            "category":"Health Services",
            "subcategory":"Nursing And Care Facility",
            "type":"Services"
        },
        {
            "category":"Social Services",
            "subcategory":"Retirement Home",
            "type":"Services"
        }
    ],
    "sg:phone":"+44 1989 565317",
    "sg:postcode":"HR9 5ND",
    "sg:province":"Gloucestershire",
    "sg:tags":[
        "residential"
    ],
    "wof:name":"Holme Lea Residential Care Home",
    "wof:placetype":"venue"
},
  "geometry": {"coordinates":[-2.5749080181,51.9115943909],"type":"Point"}
}