{
  "type": "Feature",
  "properties": {
    "iso:country":"GB",
    "sg:address":"Unit 5 Riverside Industrial Estate, Cefn-y-bedd",
    "sg:city":"Wrexham",
    "sg:classifiers":[
        {
            "category":"Food & Beverages",
            "subcategory":"Groceries & Convenience Stores",
            "type":"Retail Goods"
        }
    ],
    "sg:phone":"+44 1978 762866",
    "sg:postcode":"LL12 9YG",
    "sg:province":"Wrexham",
    "sg:tags":[
        "merchant",
        "potato"
    ],
    "wof:name":"Quality Potatoes",
    "wof:placetype":"venue"
},
  "geometry": {"coordinates":[-3.0310690403,53.0979194641],"type":"Point"}
}