{
  "type": "Feature",
  "properties": {
    "addr:full":"14 Wangey Rd Romford Essex RM6 4BW",
    "addr:housenumber":"14",
    "addr:postcode":"rm6 4bw",
    "addr:street":"Wangey Rd",
    "iso:country":"GB",
    "sg:address":"14 Wangey Rd",
    "sg:city":"Romford",
    "sg:classifiers":[
        {
            "category":"Government",
            "subcategory":"Police Station",
            "type":"Public Place"
        }
    ],
    "sg:phone":"+44 20 8597 0025",
    "sg:postcode":"RM6 4BW",
    "sg:province":"Essex",
    "sg:tags":[
        "support"
    ],
    "wof:name":"Metropolitan Police Service",
    "wof:placetype":"venue"
},
  "geometry": {"coordinates":[0.129155,51.569908],"type":"Point"}
}