{
  "type": "Feature",
  "properties": {
    "iso:country":"GB",
    "sg:address":"12 Silk Street",
    "sg:city":"Paisley",
    "sg:classifiers":[
        {
            "category":"Shopping",
            "subcategory":"Hobbies, Toys, & Games",
            "type":"Retail Goods"
        }
    ],
    "sg:postcode":"PA1 1HG",
    "sg:province":"Renfrewshire",
    "sg:tags":[
        "shop",
        "toy"
    ],
    "wof:name":"Sharon O'Donnell",
    "wof:placetype":"venue"
},
  "geometry": {"coordinates":[-4.419318,55.846848],"type":"Point"}
}