{
  "type": "Feature",
  "properties": {
    "iso:country":"GB",
    "sg:address":"113 Mungo Park Rd",
    "sg:city":"Rainham",
    "sg:classifiers":[
        {
            "category":"Government",
            "subcategory":"Post Office",
            "type":"Public Place"
        }
    ],
    "sg:phone":"+44 1708 630843",
    "sg:postcode":"RM13 7PP",
    "sg:province":"Essex",
    "wof:name":"Mungo Park Sub PO",
    "wof:placetype":"venue"
},
  "geometry": {"coordinates":[0.19258,51.540531],"type":"Point"}
}