{
  "type": "Feature",
  "properties": {
    "addr:full":"Low Meadows, Latimer Chesham Buckinghamshire HP5 1TY",
    "addr:postcode":"hp5 1ty",
    "addr:street":"Low Meadows",
    "iso:country":"GB",
    "sg:address":"Low Meadows, Latimer",
    "sg:city":"Chesham",
    "sg:classifiers":[
        {
            "category":"Professional",
            "type":"Services"
        }
    ],
    "sg:phone":"+44 1494 766140",
    "sg:postcode":"HP5 1TY",
    "sg:province":"Buckinghamshire",
    "sg:tags":[
        "relocation"
    ],
    "sg:website":"http://www.wefindhouses.co.uk",
    "wof:name":"The County Homesearch Co",
    "wof:placetype":"venue"
},
  "geometry": {"coordinates":[-0.609333,51.710537],"type":"Point"}
}