{
  "type": "Feature",
  "properties": {
    "iso:country":"GB",
    "sg:address":"Roughtown Road, Mossley",
    "sg:city":"Ashton-under-lyne",
    "sg:classifiers":[
        {
            "category":"Community Center",
            "subcategory":"Youth",
            "type":"Public Place"
        }
    ],
    "sg:phone":"+44 1457 832361",
    "sg:postcode":"OL5 0SG",
    "sg:province":"Greater Manchester",
    "sg:tags":[
        "organisation",
        "centre"
    ],
    "wof:name":"Mossley Youth & Community Centre",
    "wof:placetype":"venue"
},
  "geometry": {"coordinates":[-2.0380940437,53.5228996277],"type":"Point"}
}