{
  "type": "Feature",
  "properties": {
    "addr:full":"13 Coopers Row London Greater London EC3N 2BQ",
    "addr:housenumber":"13",
    "addr:postcode":"ec3n 2bq",
    "addr:street":"Coopers Row",
    "iso:country":"GB",
    "sg:address":"13 Coopers Row",
    "sg:city":"London",
    "sg:classifiers":[
        {
            "category":"Real Estate",
            "subcategory":"Architect",
            "type":"Services"
        }
    ],
    "sg:postcode":"EC3N 2BQ",
    "sg:province":"Greater London",
    "wof:name":"Globestream Engineering Ltd",
    "wof:placetype":"venue"
},
  "geometry": {"coordinates":[-0.051517,51.522106],"type":"Point"}
}