{
  "type": "Feature",
  "properties": {
    "addr:full":"63 Tartar Road Cobham Surrey KT11 2AS",
    "addr:housenumber":"63",
    "addr:postcode":"kt11 2as",
    "addr:street":"Tartar Road",
    "iso:country":"GB",
    "sg:address":"63 Tartar Road",
    "sg:city":"Cobham",
    "sg:classifiers":[
        {
            "category":"Building & Trades",
            "subcategory":"Construction",
            "type":"Services"
        }
    ],
    "sg:postcode":"KT11 2AS",
    "sg:province":"Surrey",
    "sg:tags":[
        "roofing"
    ],
    "wof:name":"Enleigh Ltd",
    "wof:placetype":"venue"
},
  "geometry": {"coordinates":[-0.4075179994,51.33360672],"type":"Point"}
}