{
  "type": "Feature",
  "properties": {
    "iso:country":"GB",
    "sg:address":"179b High Street, Hampton Hill",
    "sg:city":"Hampton",
    "sg:classifiers":[
        {
            "category":"Fast Food",
            "type":"Food & Drink"
        },
        {
            "category":"Deli",
            "type":"Food & Drink"
        }
    ],
    "sg:phone":"+44 20 8941 8668",
    "sg:postcode":"TW12 1NL",
    "sg:province":"Greater London",
    "sg:tags":[
        "delivery",
        "snack",
        "sandwich"
    ],
    "wof:name":"Daisy Chain",
    "wof:placetype":"venue"
},
  "geometry": {"coordinates":[-0.3548049927,51.4284248352],"type":"Point"}
}