{
  "type": "Feature",
  "properties": {
    "addr:full":"West View, Gainsborough Rd, Willingham-by-stow Gainsborough Lincolnshire DN21 5JX",
    "addr:postcode":"dn21 5jx",
    "addr:street":"Gainsborough Rd",
    "iso:country":"GB",
    "sg:address":"West View, Gainsborough Rd, Willingham-by-stow",
    "sg:city":"Gainsborough",
    "sg:classifiers":[
        {
            "category":"Building & Trades",
            "subcategory":"Equipment Rental",
            "type":"Services"
        }
    ],
    "sg:postcode":"DN21 5JX",
    "sg:province":"Lincolnshire",
    "sg:tags":[
        "plant",
        "machinery"
    ],
    "wof:name":"Flynn,P & J,",
    "wof:placetype":"venue"
},
  "geometry": {"coordinates":[-0.6865860224,53.3492355347],"type":"Point"}
}