{
  "type": "Feature",
  "properties": {
    "iso:country":"GB",
    "sg:address":"41 Crichton Av",
    "sg:city":"York",
    "sg:classifiers":[
        {
            "category":"Fast Food",
            "type":"Food & Drink"
        }
    ],
    "sg:phone":"+44 1904 655025",
    "sg:postcode":"YO3 6EF",
    "sg:province":"East Riding of Yorkshire",
    "sg:tags":[
        "away",
        "take"
    ],
    "wof:name":"Crichton Chinese Takeaway",
    "wof:placetype":"venue"
},
  "geometry": {"coordinates":[-1.08937,53.975994],"type":"Point"}
}