{
  "type": "Feature",
  "properties": {
    "addr:full":"2-3 Dorchester Pde Stockport Cheshire SK7 5HA",
    "addr:housenumber":"2-3",
    "addr:postcode":"sk7 5ha",
    "addr:street":"Dorchester Pde",
    "iso:country":"GB",
    "sg:address":"2-3 Dorchester Pde",
    "sg:city":"Stockport",
    "sg:classifiers":[
        {
            "category":"Restaurant",
            "type":"Food & Drink"
        }
    ],
    "sg:phone":"+44 161 439 1041",
    "sg:postcode":"SK7 5HA",
    "sg:province":"Cheshire",
    "sg:tags":[
        "indian"
    ],
    "wof:name":"Bengal Brasserie",
    "wof:placetype":"venue"
},
  "geometry": {"coordinates":[-2.140280962,53.3731079102],"type":"Point"}
}