{
  "type": "Feature",
  "properties": {
    "iso:country":"GB",
    "sg:address":"The Waterside, 1430 Centre Park, Park Blvd",
    "sg:city":"Warrington",
    "sg:classifiers":[
        {
            "category":"Restaurant",
            "type":"Food & Drink"
        }
    ],
    "sg:phone":"+44 1925 242692",
    "sg:postcode":"WA1 1PR",
    "sg:province":"Cheshire",
    "wof:name":"Waterside Beefeater Restaurant",
    "wof:placetype":"venue"
},
  "geometry": {"coordinates":[-2.593930006,53.3843917847],"type":"Point"}
}