{
  "type": "Feature",
  "properties": {
    "addr:full":"1 Houston Pl Glasgow Glasgow City G5 8SG",
    "addr:housenumber":"1",
    "addr:postcode":"g5 8sg",
    "addr:street":"Houston Pl",
    "iso:country":"GB",
    "sg:address":"1 Houston Pl",
    "sg:city":"Glasgow",
    "sg:classifiers":[
        {
            "category":"Wholesale",
            "subcategory":"Machinery & Supplies",
            "type":"Manufacturing & Wholesale Goods"
        }
    ],
    "sg:phone":"+44 141 418 0081",
    "sg:postcode":"G5 8SG",
    "sg:province":"Glasgow City",
    "sg:tags":[
        "hydraulic"
    ],
    "wof:name":"H T C (Engineering) Ltd",
    "wof:placetype":"venue"
},
  "geometry": {"coordinates":[-4.274184227,55.8526115417],"type":"Point"}
}