{
  "type": "Feature",
  "properties": {
    "iso:country":"GB",
    "sg:address":", Box",
    "sg:city":"Stroud",
    "sg:classifiers":[
        {
            "category":"Bars & Pubs",
            "type":"Food & Drink"
        }
    ],
    "sg:phone":"+44 1453 832631",
    "sg:postcode":"GL6 9AE",
    "sg:province":"Gloucestershire",
    "sg:tags":[
        "pubs",
        "inn"
    ],
    "wof:name":"The Halfway Inn",
    "wof:placetype":"venue"
},
  "geometry": {"coordinates":[-2.197043,51.700626],"type":"Point"}
}