{
  "type": "Feature",
  "properties": {
    "iso:country":"GB",
    "sg:address":"1 Elm Way, Hackleton",
    "sg:city":"Northampton",
    "sg:classifiers":[
        {
            "category":"Professional",
            "subcategory":"Management & Consulting",
            "type":"Services"
        }
    ],
    "sg:phone":"+44 1604 870129",
    "sg:postcode":"NN7 2BT",
    "sg:province":"Buckinghamshire",
    "sg:tags":[
        "consultant",
        "business"
    ],
    "wof:name":"Eurogistics Ltd.",
    "wof:placetype":"venue"
},
  "geometry": {"coordinates":[-0.8166369796,52.1888046265],"type":"Point"}
}