{
  "type": "Feature",
  "properties": {
    "addr:full":"17 Railway Enterprise Centre, Shelton New Road Stoke-on-trent Staffordshire ST4 7SH",
    "addr:housenumber":"17",
    "addr:postcode":"st4 7sh",
    "addr:street":"Railway Enterprise Centre;New Road",
    "iso:country":"GB",
    "sg:address":"17 Railway Enterprise Centre, Shelton New Road",
    "sg:city":"Stoke-on-trent",
    "sg:classifiers":[
        {
            "category":"Manufacturing",
            "subcategory":"Wood Products",
            "type":"Manufacturing & Wholesale Goods"
        }
    ],
    "sg:phone":"+44 1782 284403",
    "sg:postcode":"ST4 7SH",
    "sg:province":"Staffordshire",
    "sg:tags":[
        "encapsulation",
        "lamination"
    ],
    "wof:name":"Stephen Futter",
    "wof:placetype":"venue"
},
  "geometry": {"coordinates":[-2.19351,53.013519],"type":"Point"}
}