{
  "type": "Feature",
  "properties": {
    "addr:full":"48 Buena Vista Drive, Glenholt Plymouth Devon PL6 7JF",
    "addr:housenumber":"48",
    "addr:postcode":"pl6 7jf",
    "addr:street":"Buena Vista Drive",
    "iso:country":"GB",
    "sg:address":"48 Buena Vista Drive, Glenholt",
    "sg:city":"Plymouth",
    "sg:classifiers":[
        {
            "category":"Building & Trades",
            "subcategory":"Construction",
            "type":"Services"
        }
    ],
    "sg:postcode":"PL6 7JF",
    "sg:province":"Devon",
    "sg:tags":[
        "roofing"
    ],
    "wof:name":"D R Hewins",
    "wof:placetype":"venue"
},
  "geometry": {"coordinates":[-4.1085700989,50.4294891357],"type":"Point"}
}