{
  "type": "Feature",
  "properties": {
    "addr:full":"Sydnope Hall Farm, Sydnope Hill, Darley Moor Matlock Derbyshire DE4 5LN",
    "addr:postcode":"de4 5ln",
    "addr:street":"Sydnope Hill;Moor",
    "iso:country":"GB",
    "sg:address":"Sydnope Hall Farm, Sydnope Hill, Darley Moor",
    "sg:city":"Matlock",
    "sg:classifiers":[
        {
            "category":"Organizations",
            "subcategory":"Non-profit Organization",
            "type":"Services"
        }
    ],
    "sg:phone":"+44 1629 735500",
    "sg:postcode":"DE4 5LN",
    "sg:province":"Derbyshire",
    "sg:tags":[
        "organisation",
        "voluntary",
        "charity"
    ],
    "wof:name":"National Council of Young Men's Christian Associations (Incorporatedp",
    "wof:placetype":"venue"
},
  "geometry": {"coordinates":[-1.5485889912,53.1814041138],"type":"Point"}
}