{
  "type": "Feature",
  "properties": {
    "addr:full":"Rear Of Church, 37-41 Cowbridge Rd West, Ely Cardiff Cardiff CF5 5BQ",
    "addr:housenumber":"rear of;37-41",
    "addr:postcode":"cf5 5bq",
    "addr:street":"Cowbridge Rd West",
    "iso:country":"GB",
    "sg:address":"Rear Of Church, 37-41 Cowbridge Rd West, Ely",
    "sg:city":"Cardiff",
    "sg:classifiers":[
        {
            "category":"Arts & Performance",
            "subcategory":"Arts Center",
            "type":"Entertainment"
        }
    ],
    "sg:phone":"+44 29 2057 6102",
    "sg:postcode":"CF5 5BQ",
    "sg:province":"Cardiff",
    "sg:tags":[
        "centre"
    ],
    "wof:name":"The Pioneers Ltd",
    "wof:placetype":"venue"
},
  "geometry": {"coordinates":[-3.23605,51.481571],"type":"Point"}
}