{
  "type": "Feature",
  "properties": {
    "iso:country":"GB",
    "sg:address":"Unit 4a, Marley Lane",
    "sg:city":"Battle",
    "sg:classifiers":[
        {
            "category":"Freight",
            "type":"Transportation"
        }
    ],
    "sg:phone":"+44 1424 775097",
    "sg:postcode":"TN33 0RD",
    "sg:province":"East Sussex",
    "sg:tags":[
        "haulage",
        "road"
    ],
    "wof:name":"Eurocouriers",
    "wof:placetype":"venue"
},
  "geometry": {"coordinates":[0.510557,50.920376],"type":"Point"}
}