{
  "type": "Feature",
  "properties": {
    "iso:country":"GB",
    "sg:address":"Emley Moor Business Park, Leys Lane, Emley",
    "sg:city":"Huddersfield",
    "sg:classifiers":[
        {
            "category":"Autos & Motor Vehicles",
            "subcategory":"Motorcycle Sales",
            "type":"Retail Goods"
        }
    ],
    "sg:phone":"+44 1924 849190",
    "sg:postcode":"HD8 9QY",
    "sg:province":"South Yorkshire",
    "wof:name":"Devils Paint Jobs",
    "wof:placetype":"venue"
},
  "geometry": {"coordinates":[-1.633754015,53.6136207581],"type":"Point"}
}