{
  "type": "Feature",
  "properties": {
    "addr:full":"38 Elizabeth St, Widdrington Morpeth Northumberland NE61 5NW",
    "addr:housenumber":"38",
    "addr:postcode":"ne61 5nw",
    "addr:street":"Elizabeth St",
    "iso:country":"GB",
    "sg:address":"38 Elizabeth St, Widdrington",
    "sg:city":"Morpeth",
    "sg:classifiers":[
        {
            "category":"Taxi",
            "type":"Transportation"
        }
    ],
    "sg:phone":"+44 1670 790904",
    "sg:postcode":"NE61 5NW",
    "sg:province":"Northumberland",
    "sg:tags":[
        "mini",
        "cab"
    ],
    "wof:name":"A.W Taxis",
    "wof:placetype":"venue"
},
  "geometry": {"coordinates":[-1.616999,55.241501],"type":"Point"}
}