{
  "type": "Feature",
  "properties": {
    "addr:full":"213 Dunstable Road Luton Bedfordshire LU4 8BN",
    "addr:housenumber":"213",
    "addr:postcode":"lu4 8bn",
    "addr:street":"Dunstable Road",
    "iso:country":"GB",
    "sg:address":"213 Dunstable Road",
    "sg:city":"Luton",
    "sg:classifiers":[
        {
            "category":"Shopping",
            "subcategory":"Pharmacy",
            "type":"Retail Goods"
        }
    ],
    "sg:phone":"+44 1582 423755",
    "sg:postcode":"LU4 8BN",
    "sg:province":"Bedfordshire",
    "sg:tags":[
        "pharmacist",
        "chemist"
    ],
    "wof:name":"S S D Tejani",
    "wof:placetype":"venue"
},
  "geometry": {"coordinates":[-0.42961,51.886036],"type":"Point"}
}