{
  "type": "Feature",
  "properties": {
    "addr:full":"Salisbury Avenue Cheltenham Gloucestershire GL51 3BY",
    "addr:postcode":"gl51 3by",
    "addr:street":"Salisbury Avenue",
    "iso:country":"GB",
    "sg:address":"Salisbury Avenue",
    "sg:city":"Cheltenham",
    "sg:classifiers":[
        {
            "category":"Place Of Worship",
            "type":"Public Place"
        }
    ],
    "sg:phone":"+44 1242 575086",
    "sg:postcode":"GL51 3BY",
    "sg:province":"Gloucestershire",
    "wof:name":"United Reformed Church in Cheltenham",
    "wof:placetype":"venue"
},
  "geometry": {"coordinates":[-2.103229,51.883331],"type":"Point"}
}