{
  "type": "Feature",
  "properties": {
    "iso:country":"GB",
    "sg:address":"High Street, Grateley",
    "sg:city":"Andover",
    "sg:classifiers":[
        {
            "category":"Education",
            "subcategory":"School",
            "type":"Public Place"
        }
    ],
    "sg:phone":"+44 1264 889207",
    "sg:postcode":"SP11 8JT",
    "sg:province":"Hampshire",
    "sg:tags":[
        "local",
        "authority"
    ],
    "wof:name":"Grateley Post Office Services & Stores",
    "wof:placetype":"venue"
},
  "geometry": {"coordinates":[-1.6045160294,51.1755065918],"type":"Point"}
}