{
  "type": "Feature",
  "properties": {
    "addr:full":"3 Saltburn Road Invergordon Highland IV18 0HH",
    "addr:housenumber":"3",
    "addr:postcode":"iv18 0hh",
    "addr:street":"Saltburn Road",
    "iso:country":"GB",
    "sg:address":"3 Saltburn Road",
    "sg:city":"Invergordon",
    "sg:classifiers":[
        {
            "category":"Building & Trades",
            "subcategory":"Plumbing",
            "type":"Services"
        }
    ],
    "sg:phone":"+44 1349 852860",
    "sg:postcode":"IV18 0HH",
    "sg:province":"Highland",
    "sg:tags":[
        "plumber",
        "heating"
    ],
    "wof:name":"H Dunn Plumbing & Heating",
    "wof:placetype":"venue"
},
  "geometry": {"coordinates":[-4.158195,57.689999],"type":"Point"}
}