{
  "type": "Feature",
  "properties": {
    "addr:full":"Old Sawmill, Longtown Carlisle Cumbria CA6 5TS",
    "addr:postcode":"ca6 5ts",
    "iso:country":"GB",
    "sg:address":"Old Sawmill, Longtown",
    "sg:city":"Carlisle",
    "sg:classifiers":[
        {
            "category":"Professional",
            "subcategory":"Engineering",
            "type":"Services"
        }
    ],
    "sg:postcode":"CA6 5TS",
    "sg:province":"Cumbria",
    "sg:tags":[
        "contractor",
        "electrical",
        "engineer"
    ],
    "wof:name":"T E Gallimore & Sons",
    "wof:placetype":"venue"
},
  "geometry": {"coordinates":[-2.9694559574,55.0072631836],"type":"Point"}
}