{
  "type": "Feature",
  "properties": {
    "addr:full":"53 Roman Road, Linthorpe Middlesbrough North Yorkshire TS5 5PH",
    "addr:housenumber":"53",
    "addr:postcode":"ts5 5ph",
    "addr:street":"Roman Road",
    "iso:country":"GB",
    "sg:address":"53 Roman Road, Linthorpe",
    "sg:city":"Middlesbrough",
    "sg:classifiers":[
        {
            "category":"Home & Garden",
            "subcategory":"Carpets & Floor Coverings",
            "type":"Retail Goods"
        }
    ],
    "sg:phone":"+44 1642 815407",
    "sg:postcode":"TS5 5PH",
    "sg:province":"North Yorkshire",
    "sg:tags":[
        "carpets",
        "retailer",
        "rug",
        "matting"
    ],
    "wof:name":"M C S Contracts Ltd",
    "wof:placetype":"venue"
},
  "geometry": {"coordinates":[-1.247359,54.556889],"type":"Point"}
}