{
  "type": "Feature",
  "properties": {
    "addr:full":"7 Greenfield Rd, Harborne Birmingham West Midlands B17 0ED",
    "addr:housenumber":"7",
    "addr:postcode":"b17 0ed",
    "addr:street":"Greenfield Rd",
    "iso:country":"GB",
    "sg:address":"7 Greenfield Rd, Harborne",
    "sg:city":"Birmingham",
    "sg:classifiers":[
        {
            "category":"Manufacturing",
            "subcategory":"Apparel",
            "type":"Manufacturing & Wholesale Goods"
        }
    ],
    "sg:postcode":"B17 0ED",
    "sg:province":"West Midlands",
    "sg:tags":[
        "garment",
        "designer"
    ],
    "wof:name":"Faulkner, Barbara,",
    "wof:placetype":"venue"
},
  "geometry": {"coordinates":[-1.9474649429,52.457572937],"type":"Point"}
}