{
  "type": "Feature",
  "properties": {
    "iso:country":"GB",
    "sg:address":"22 Friezland Road",
    "sg:city":"Tunbridge Wells",
    "sg:classifiers":[
        {
            "category":"Building & Trades",
            "subcategory":"Plumbing",
            "type":"Services"
        }
    ],
    "sg:postcode":"TN4 8LJ",
    "sg:province":"Kent",
    "sg:tags":[
        "heating"
    ],
    "wof:name":"Keith F G Tadd",
    "wof:placetype":"venue"
},
  "geometry": {"coordinates":[0.2398059964,51.1218299866],"type":"Point"}
}