{
  "type": "Feature",
  "properties": {
    "addr:full":"6-8 Sea Front Hayling Island Hampshire PO11 9HL",
    "addr:housenumber":"6-8",
    "addr:postcode":"po11 9hl",
    "addr:street":"Sea Front",
    "iso:country":"GB",
    "sg:address":"6-8 Sea Front",
    "sg:city":"Hayling Island",
    "sg:classifiers":[
        {
            "category":"Shopping",
            "subcategory":"Gifts & Souvenirs",
            "type":"Retail Goods"
        }
    ],
    "sg:phone":"+44 23 9246 7305",
    "sg:postcode":"PO11 9HL",
    "sg:province":"Hampshire",
    "sg:tags":[
        "shop"
    ],
    "wof:name":"Roy's Bazaar",
    "wof:placetype":"venue"
},
  "geometry": {"coordinates":[-0.9656810164,50.7815971375],"type":"Point"}
}