{
  "type": "Feature",
  "properties": {
    "iso:country":"GB",
    "sg:address":"2 Spring Cottage, Moor La",
    "sg:city":"Lewes",
    "sg:classifiers":[
        {
            "category":"Retail",
            "subcategory":"Storage",
            "type":"Services"
        }
    ],
    "sg:phone":"+44 1273 814367",
    "sg:postcode":"BN8 5UP",
    "sg:province":"East Sussex",
    "sg:tags":[
        "household",
        "removal"
    ],
    "wof:name":"Redwing Transport",
    "wof:placetype":"venue"
},
  "geometry": {"coordinates":[0.057977,50.889374],"type":"Point"}
}