{
  "type": "Feature",
  "properties": {
    "iso:country":"GB",
    "sg:address":"4 Eversfield Close",
    "sg:city":"Andover",
    "sg:classifiers":[
        {
            "category":"Professional",
            "subcategory":"Management & Consulting",
            "type":"Services"
        }
    ],
    "sg:phone":"+44 1264 395544",
    "sg:postcode":"SP10 3EN",
    "sg:province":"Hampshire",
    "sg:tags":[
        "consultant"
    ],
    "wof:name":"Lambda Telecoms Consulting",
    "wof:placetype":"venue"
},
  "geometry": {"coordinates":[-1.492571,51.20903],"type":"Point"}
}