{
  "type": "Feature",
  "properties": {
    "addr:full":"2 Spawd Bone Lane Knottingley North Yorkshire WF11 0HY",
    "addr:housenumber":"2",
    "addr:postcode":"wf11 0hy",
    "addr:street":"Spawd Bone Lane",
    "iso:country":"GB",
    "sg:address":"2 Spawd Bone Lane",
    "sg:city":"Knottingley",
    "sg:classifiers":[
        {
            "category":"Fast Food",
            "type":"Food & Drink"
        }
    ],
    "sg:phone":"+44 1977 678249",
    "sg:postcode":"WF11 0HY",
    "sg:province":"North Yorkshire",
    "sg:tags":[
        "away",
        "meal",
        "outlet",
        "take"
    ],
    "wof:name":"Golden Sunrise",
    "wof:placetype":"venue"
},
  "geometry": {"coordinates":[-1.2470309734,53.7060813904],"type":"Point"}
}