{
  "type": "Feature",
  "properties": {
    "addr:full":"Gregory St Stoke On Trent Staffordshire ST3 2LU",
    "addr:postcode":"st3 2lu",
    "addr:street":"Gregory St",
    "iso:country":"GB",
    "sg:address":"Gregory St",
    "sg:city":"Stoke On Trent",
    "sg:classifiers":[
        {
            "category":"Shopping",
            "subcategory":"Discount & Variety Stores",
            "type":"Retail Goods"
        }
    ],
    "sg:phone":"+44 1782 333555",
    "sg:postcode":"ST3 2LU",
    "sg:province":"Staffordshire",
    "sg:tags":[
        "cleaning",
        "supply"
    ],
    "wof:name":"Ceramic Industry Supply Co",
    "wof:placetype":"venue"
},
  "geometry": {"coordinates":[-2.1414289474,52.988319397],"type":"Point"}
}