{
  "type": "Feature",
  "properties": {
    "iso:country":"GB",
    "sg:address":"Unit 5 Fishergate Point, Lower Parliament Street",
    "sg:city":"Nottingham",
    "sg:classifiers":[
        {
            "category":"Autos & Motor Vehicles",
            "subcategory":"Auto Supplies",
            "type":"Retail Goods"
        }
    ],
    "sg:phone":"+44 115 924 2425",
    "sg:postcode":"NG1 1GD",
    "sg:province":"Nottinghamshire",
    "sg:tags":[
        "windscreen"
    ],
    "wof:name":"Silver Shield Automotive Glazing",
    "wof:placetype":"venue"
},
  "geometry": {"coordinates":[-1.141678,52.955013],"type":"Point"}
}