{
  "type": "Feature",
  "properties": {
    "addr:full":"13 Stowe Gardens Plymouth Devon PL5 3PS",
    "addr:housenumber":"13",
    "addr:postcode":"pl5 3ps",
    "addr:street":"Stowe Gardens",
    "iso:country":"GB",
    "sg:address":"13 Stowe Gardens",
    "sg:city":"Plymouth",
    "sg:classifiers":[
        {
            "category":"Organizations",
            "subcategory":"Non-profit Organization",
            "type":"Services"
        }
    ],
    "sg:phone":"+44 1752 770975",
    "sg:postcode":"PL5 3PS",
    "sg:province":"Devon",
    "sg:tags":[
        "organisation",
        "animal",
        "welfare"
    ],
    "wof:name":"The Prickles Hedgehog Unit",
    "wof:placetype":"venue"
},
  "geometry": {"coordinates":[-4.1592040062,50.4085273743],"type":"Point"}
}