{
  "type": "Feature",
  "properties": {
    "addr:full":"Unit 4, Cherrywood Ind Est, Raleigh Rd Birmingham West Midlands B9 4TL",
    "addr:housenumber":"unit 4",
    "addr:postcode":"b9 4tl",
    "addr:street":"Raleigh Rd",
    "iso:country":"GB",
    "sg:address":"Unit 4, Cherrywood Ind Est, Raleigh Rd",
    "sg:city":"Birmingham",
    "sg:classifiers":[
        {
            "category":"Wholesale",
            "subcategory":"Scrap",
            "type":"Manufacturing & Wholesale Goods"
        }
    ],
    "sg:phone":"+44 121 766 8934",
    "sg:postcode":"B9 4TL",
    "sg:province":"West Midlands",
    "sg:tags":[
        "waste",
        "metal"
    ],
    "wof:name":"B.W Astley",
    "wof:placetype":"venue"
},
  "geometry": {"coordinates":[-1.856717,52.48074],"type":"Point"}
}