{
  "type": "Feature",
  "properties": {
    "iso:country":"GB",
    "sg:address":"125a Templehill",
    "sg:city":"Troon",
    "sg:classifiers":[
        {
            "category":"Retail",
            "subcategory":"Auto Repair",
            "type":"Services"
        }
    ],
    "sg:phone":"+44 1292 311755",
    "sg:postcode":"KA10 6BQ",
    "sg:province":"South Ayrshire",
    "sg:tags":[
        "modification",
        "garage",
        "related"
    ],
    "wof:name":"Templetons",
    "wof:placetype":"venue"
},
  "geometry": {"coordinates":[-4.668824,55.54422],"type":"Point"}
}