{
  "type": "Feature",
  "properties": {
    "addr:full":"20 Bramblewood, Pinewood Ipswich Suffolk IP8 3RS",
    "addr:housenumber":"20",
    "addr:postcode":"ip8 3rs",
    "addr:street":"Bramblewood Pinewood",
    "iso:country":"GB",
    "sg:address":"20 Bramblewood, Pinewood",
    "sg:city":"Ipswich",
    "sg:classifiers":[
        {
            "category":"Professional",
            "subcategory":"Computer Services",
            "type":"Services"
        }
    ],
    "sg:phone":"+44 1473 407377",
    "sg:postcode":"IP8 3RS",
    "sg:province":"Suffolk",
    "sg:tags":[
        "system",
        "software"
    ],
    "wof:name":"Excel Computer Centre Ltd.",
    "wof:placetype":"venue"
},
  "geometry": {"coordinates":[1.1071020365,52.0436325073],"type":"Point"}
}