{
  "type": "Feature",
  "properties": {
    "iso:country":"GB",
    "sg:address":"Royal Court, 6 Tatton St",
    "sg:city":"Knutsford",
    "sg:classifiers":[
        {
            "category":"Professional",
            "subcategory":"Computer Services",
            "type":"Services"
        }
    ],
    "sg:phone":"+44 1565 752300",
    "sg:postcode":"WA16 6EN",
    "sg:province":"Cheshire",
    "sg:tags":[
        "system",
        "software"
    ],
    "wof:name":"P W A Personnel Systems Ltd",
    "wof:placetype":"venue"
},
  "geometry": {"coordinates":[-2.3748259544,53.3063278198],"type":"Point"}
}