{
  "type": "Feature",
  "properties": {
    "iso:country":"GB",
    "sg:address":"Oak House, Oak Tree Close",
    "sg:city":"Ammanford",
    "sg:classifiers":[
        {
            "category":"Retail",
            "subcategory":"Repair Shop",
            "type":"Services"
        }
    ],
    "sg:postcode":"SA18 2GX",
    "sg:province":"Carmarthenshire",
    "sg:tags":[
        "maintenance"
    ],
    "wof:name":"Gerald Reginald M Bartlett",
    "wof:placetype":"venue"
},
  "geometry": {"coordinates":[-3.9889450073,51.7923965454],"type":"Point"}
}