{
  "type": "Feature",
  "properties": {
    "addr:full":"Unit 7, Plough Estate, Blandford Heights Blandford Forum Dorset DT11 7UG",
    "addr:housenumber":"unit 7",
    "addr:postcode":"heights;dorset dt11 7ug",
    "addr:street":"Plough Estate",
    "iso:country":"GB",
    "sg:address":"Unit 7, Plough Estate, Blandford Heights",
    "sg:city":"Blandford Forum",
    "sg:classifiers":[
        {
            "category":"Building & Trades",
            "subcategory":"Construction",
            "type":"Services"
        }
    ],
    "sg:postcode":"DT11 7UG",
    "sg:province":"Dorset",
    "sg:tags":[
        "glazier"
    ],
    "wof:name":"C J Glass",
    "wof:placetype":"venue"
},
  "geometry": {"coordinates":[-2.158609,50.871059],"type":"Point"}
}