{
  "type": "Feature",
  "properties": {
    "addr:full":"Darling House, 60 - 62 Kings Road Reading Berkshire RG1 3AA",
    "addr:housenumber":"60 62",
    "addr:postcode":"rg1 3aa",
    "addr:street":"Kings Road",
    "iso:country":"GB",
    "sg:address":"Darling House, 60 - 62 Kings Road",
    "sg:city":"Reading",
    "sg:classifiers":[
        {
            "category":"Professional",
            "subcategory":"Employment Agencies",
            "type":"Services"
        }
    ],
    "sg:phone":"+44 118 951 1333",
    "sg:postcode":"RG1 3AA",
    "sg:province":"Berkshire",
    "sg:tags":[
        "consultant"
    ],
    "wof:name":"Mitchell Rawlings Ltd.",
    "wof:placetype":"venue"
},
  "geometry": {"coordinates":[-0.9665930271,51.45470047],"type":"Point"}
}