{
  "type": "Feature",
  "properties": {
    "addr:full":"64 Clarendon Street Leamington Spa Warwickshire CV32 4PE",
    "addr:housenumber":"64",
    "addr:postcode":"cv32 4pe",
    "addr:street":"Clarendon Street",
    "iso:country":"GB",
    "sg:address":"64 Clarendon Street",
    "sg:city":"Leamington Spa",
    "sg:classifiers":[
        {
            "category":"Health Services",
            "subcategory":"Podiatrist",
            "type":"Services"
        }
    ],
    "sg:phone":"+44 1926 314839",
    "sg:postcode":"CV32 4PE",
    "sg:province":"Warwickshire",
    "sg:tags":[
        "podiatrists",
        "chiropodist"
    ],
    "wof:name":"Paul Smallwood",
    "wof:placetype":"venue"
},
  "geometry": {"coordinates":[-1.531637,52.29171],"type":"Point"}
}