{
  "type": "Feature",
  "properties": {
    "addr:full":"68 Worcester Street Stourbridge Staffordshire DY8 1AY",
    "addr:housenumber":"68",
    "addr:postcode":"dy8 1ay",
    "addr:street":"Worcester Street",
    "iso:country":"GB",
    "sg:address":"68 Worcester Street",
    "sg:city":"Stourbridge",
    "sg:classifiers":[
        {
            "category":"Health Services",
            "subcategory":"Health Practitioner",
            "type":"Services"
        }
    ],
    "sg:phone":"+44 1384 390044",
    "sg:postcode":"DY8 1AY",
    "sg:province":"Staffordshire",
    "sg:tags":[
        "psychologist"
    ],
    "wof:name":"E Conduit",
    "wof:placetype":"venue"
},
  "geometry": {"coordinates":[-2.148318,52.451839],"type":"Point"}
}