{
  "type": "Feature",
  "properties": {
    "addr:full":"Suite 13q Queensway House, Business Centre, Queensway Middlesbrough North Yorkshire TS3 8TF",
    "addr:housenumber":"suite 13q",
    "addr:postcode":"ts3 8tf",
    "addr:street":"Queensway House;Queensway",
    "iso:country":"GB",
    "sg:address":"Suite 13q Queensway House, Business Centre, Queensway",
    "sg:city":"Middlesbrough",
    "sg:classifiers":[
        {
            "category":"Shopping",
            "subcategory":"Bicycles & Sporting Goods",
            "type":"Retail Goods"
        }
    ],
    "sg:phone":"+44 1642 254200",
    "sg:postcode":"TS3 8TF",
    "sg:province":"North Yorkshire",
    "sg:tags":[
        "equipment",
        "marine",
        "supply"
    ],
    "wof:name":"Huttons International Ltd.",
    "wof:placetype":"venue"
},
  "geometry": {"coordinates":[-1.19526,54.572441],"type":"Point"}
}