{
  "type": "Feature",
  "properties": {
    "iso:country":"GB",
    "sg:address":"Unit 2/3 Cardiff Business Park, Lambourne Crescent, Llanishen",
    "sg:city":"Cardiff",
    "sg:classifiers":[
        {
            "category":"Manufacturing",
            "subcategory":"Textiles",
            "type":"Manufacturing & Wholesale Goods"
        }
    ],
    "sg:phone":"+44 870 873 6800",
    "sg:postcode":"CF14 5GF",
    "sg:province":"Cardiff",
    "sg:tags":[
        "printer"
    ],
    "wof:name":"Max Imaging Systems Ltd.",
    "wof:placetype":"venue"
},
  "geometry": {"coordinates":[-3.195525,51.528248],"type":"Point"}
}