{
  "type": "Feature",
  "properties": {
    "iso:country":"GB",
    "sg:address":"49 Forlease Rd",
    "sg:city":"Maidenhead",
    "sg:classifiers":[
        {
            "category":"Retail",
            "subcategory":"Repair Shop",
            "type":"Services"
        }
    ],
    "sg:postcode":"SL6 1RX",
    "sg:province":"Berkshire",
    "sg:tags":[
        "equipment",
        "catering"
    ],
    "wof:name":"Bhogal,Amarjit,",
    "wof:placetype":"venue"
},
  "geometry": {"coordinates":[-0.714746,51.521927],"type":"Point"}
}