{
  "type": "Feature",
  "properties": {
    "addr:full":"30-31 Princess Street Shrewsbury Shropshire SY1 1LW",
    "addr:housenumber":"30-31",
    "addr:postcode":"sy1 1lw",
    "addr:street":"Princess Street",
    "iso:country":"GB",
    "sg:address":"30-31 Princess Street",
    "sg:city":"Shrewsbury",
    "sg:classifiers":[
        {
            "category":"Shopping",
            "subcategory":"Clothing, Apparel, & Fashions",
            "type":"Retail Goods"
        }
    ],
    "sg:postcode":"SY1 1LW",
    "sg:province":"Shropshire",
    "sg:tags":[
        "ladieswear"
    ],
    "wof:name":"Jane of Shrewsbury",
    "wof:placetype":"venue"
},
  "geometry": {"coordinates":[-2.7543540001,52.7070350647],"type":"Point"}
}