{
  "type": "Feature",
  "properties": {
    "iso:country":"GB",
    "sg:address":"10a Oakland Road",
    "sg:city":"Leicester",
    "sg:classifiers":[
        {
            "category":"Manufacturing",
            "subcategory":"Wood Products",
            "type":"Manufacturing & Wholesale Goods"
        }
    ],
    "sg:postcode":"LE2 6AN",
    "sg:province":"Leicestershire",
    "sg:tags":[
        "packaging",
        "crate",
        "pallets"
    ],
    "wof:name":"East Midland Packaging Supplies (Leicester) Ltd.",
    "wof:placetype":"venue"
},
  "geometry": {"coordinates":[-1.124949,52.614498],"type":"Point"}
}