{
  "type": "Feature",
  "properties": {
    "iso:country":"GB",
    "sg:address":"Lower Norton Lane, Kewstoke",
    "sg:city":"Weston-super-mare",
    "sg:classifiers":[
        {
            "category":"Home & Garden",
            "subcategory":"Garden Supply",
            "type":"Retail Goods"
        }
    ],
    "sg:postcode":"BS22 9YT",
    "sg:province":"Somerset",
    "sg:tags":[
        "nursery",
        "centre"
    ],
    "wof:name":"R J & E A Hill",
    "wof:placetype":"venue"
},
  "geometry": {"coordinates":[-2.9404110909,51.3698387146],"type":"Point"}
}