{
  "type": "Feature",
  "properties": {
    "addr:full":"66 Woodcote Road Wallington Surrey SM6 0LY",
    "addr:housenumber":"66",
    "addr:postcode":"sm6 0ly",
    "addr:street":"Woodcote Road",
    "iso:country":"GB",
    "sg:address":"66 Woodcote Road",
    "sg:city":"Wallington",
    "sg:classifiers":[
        {
            "category":"Food & Beverages",
            "subcategory":"Liquor & Beverages",
            "type":"Retail Goods"
        },
        {
            "category":"Food & Beverages",
            "subcategory":"Groceries & Convenience Stores",
            "type":"Retail Goods"
        }
    ],
    "sg:phone":"+44 845 662 1560",
    "sg:postcode":"SM6 0LY",
    "sg:province":"Surrey",
    "sg:tags":[
        "beer",
        "spirit",
        "wine"
    ],
    "wof:name":"Roots Food & Wine",
    "wof:placetype":"venue"
},
  "geometry": {"coordinates":[-0.1498669982,51.358833313],"type":"Point"}
}