{
  "type": "Feature",
  "properties": {
    "iso:country":"GB",
    "sg:address":"21-23 Whiffler Rd",
    "sg:city":"Norwich",
    "sg:classifiers":[
        {
            "category":"Retail",
            "subcategory":"Auto Repair",
            "type":"Services"
        }
    ],
    "sg:postcode":"NR3 2AG",
    "sg:province":"Norfolk",
    "sg:tags":[
        "modification",
        "garage"
    ],
    "wof:name":"A M Motor Services",
    "wof:placetype":"venue"
},
  "geometry": {"coordinates":[1.2667900324,52.6500892639],"type":"Point"}
}