{
  "type": "Feature",
  "properties": {
    "addr:full":"130b North Lane Aldershot Hampshire GU12 4QN",
    "addr:housenumber":"130b",
    "addr:postcode":"gu12 4qn",
    "addr:street":"North Lane",
    "iso:country":"GB",
    "sg:address":"130b North Lane",
    "sg:city":"Aldershot",
    "sg:classifiers":[
        {
            "category":"Professional",
            "type":"Services"
        },
        {
            "category":"Professional",
            "subcategory":"Computer Services",
            "type":"Services"
        }
    ],
    "sg:phone":"+44 1252 325608",
    "sg:postcode":"GU12 4QN",
    "sg:province":"Hampshire",
    "sg:tags":[
        "repair",
        "tech",
        "maintenance"
    ],
    "wof:name":"A.N. ELECTRONIC & COMPUTER SERVICES LTD",
    "wof:placetype":"venue"
},
  "geometry": {"coordinates":[-0.741106987,51.2464027405],"type":"Point"}
}