{
  "type": "Feature",
  "properties": {
    "iso:country":"GB",
    "sg:address":"Reedham Lane, Coningsby",
    "sg:city":"Lincoln",
    "sg:classifiers":[
        {
            "category":"Building & Trades",
            "subcategory":"Landscaping Services",
            "type":"Services"
        },
        {
            "category":"Home & Garden",
            "subcategory":"Garden Supply",
            "type":"Retail Goods"
        },
        {
            "category":"Farming",
            "subcategory":"Farm & Veterinary Services",
            "type":"Manufacturing & Wholesale Goods"
        },
        {
            "category":"Farming",
            "subcategory":"Farm",
            "type":"Manufacturing & Wholesale Goods"
        }
    ],
    "sg:phone":"+44 1526 342546",
    "sg:postcode":"LN4 4RX",
    "sg:province":"Lincolnshire",
    "sg:tags":[
        "gardening",
        "crop",
        "contractor",
        "agricultural",
        "mixed",
        "bulb",
        "grower"
    ],
    "wof:name":"W A & A A Appleyard",
    "wof:placetype":"venue"
},
  "geometry": {"coordinates":[-0.171925,53.106804],"type":"Point"}
}