{
  "type": "Feature",
  "properties": {
    "iso:country":"GB",
    "sg:address":"St Johns Rd Dental Surgery, 18 St Johns Rd",
    "sg:city":"Ryde",
    "sg:classifiers":[
        {
            "category":"Health Services",
            "subcategory":"Dentist",
            "type":"Services"
        }
    ],
    "sg:phone":"+44 1983 810050",
    "sg:postcode":"PO33 2RN",
    "sg:province":"Isle of Wight",
    "wof:name":"Dental Surgeries",
    "wof:placetype":"venue"
},
  "geometry": {"coordinates":[-1.168666,50.727566],"type":"Point"}
}