{
  "type": "Feature",
  "properties": {
    "addr:full":"70 Western Road Hove East Sussex BN3 2JQ",
    "addr:housenumber":"70",
    "addr:postcode":"bn3 2jq",
    "addr:street":"Western Road",
    "iso:country":"GB",
    "sg:address":"70 Western Road",
    "sg:city":"Hove",
    "sg:classifiers":[
        {
            "category":"Shopping",
            "subcategory":"Florist",
            "type":"Retail Goods"
        }
    ],
    "sg:phone":"+44 1273 738050",
    "sg:postcode":"BN3 2JQ",
    "sg:province":"East Sussex",
    "wof:name":"Floral Design",
    "wof:placetype":"venue"
},
  "geometry": {"coordinates":[-0.162684,50.826275],"type":"Point"}
}