{
  "type": "Feature",
  "properties": {
    "iso:country":"GB",
    "sg:address":"39 South Bar Street",
    "sg:city":"Banbury",
    "sg:classifiers":[
        {
            "category":"Professional",
            "subcategory":"Lawyer & Legal Services",
            "type":"Services"
        }
    ],
    "sg:phone":"+44 1295 265566",
    "sg:postcode":"OX16 9AE",
    "sg:province":"Oxfordshire",
    "sg:tags":[
        "solicitor"
    ],
    "wof:name":"Bower & Bailey",
    "wof:placetype":"venue"
},
  "geometry": {"coordinates":[-1.3404920101,52.0582542419],"type":"Point"}
}