{
  "type": "Feature",
  "properties": {
    "iso:country":"GB",
    "sg:address":"21 North Park Road",
    "sg:city":"Harrogate",
    "sg:classifiers":[
        {
            "category":"Professional",
            "subcategory":"Management & Consulting",
            "type":"Services"
        }
    ],
    "sg:postcode":"HG1 5PD",
    "sg:province":"North Yorkshire",
    "sg:tags":[
        "consultant",
        "business"
    ],
    "wof:name":"Westview Business Development Ltd",
    "wof:placetype":"venue"
},
  "geometry": {"coordinates":[-1.533848,53.992287],"type":"Point"}
}