{
  "type": "Feature",
  "properties": {
    "addr:full":"High Street, Otford Sevenoaks Kent TN14 5PQ",
    "addr:postcode":"tn14 5pq",
    "addr:street":"High Street",
    "iso:country":"GB",
    "sg:address":"High Street, Otford",
    "sg:city":"Sevenoaks",
    "sg:classifiers":[
        {
            "category":"Bars & Pubs",
            "type":"Food & Drink"
        }
    ],
    "sg:phone":"+44 1959 522195",
    "sg:postcode":"TN14 5PQ",
    "sg:province":"Kent",
    "sg:tags":[
        "pubs",
        "inn"
    ],
    "wof:name":"The Woodman Public House",
    "wof:placetype":"venue"
},
  "geometry": {"coordinates":[0.189895004,51.3101501465],"type":"Point"}
}