{
  "type": "Feature",
  "properties": {
    "addr:full":"43 Princes Street Edinburgh City of Edinburgh EH2 2BY",
    "addr:housenumber":"43",
    "addr:postcode":"eh2 2by",
    "addr:street":"Princes Street",
    "iso:country":"GB",
    "sg:address":"43 Princes Street",
    "sg:city":"Edinburgh",
    "sg:classifiers":[
        {
            "category":"Travel",
            "subcategory":"Hotels & Motels",
            "type":"Entertainment"
        }
    ],
    "sg:phone":"+44 131 556 4648",
    "sg:postcode":"EH2 2BY",
    "sg:province":"City of Edinburgh",
    "wof:name":"See The Old Waverley Hotel",
    "wof:placetype":"venue"
},
  "geometry": {"coordinates":[-3.1931109428,55.9528083801],"type":"Point"}
}