{
  "type": "Feature",
  "properties": {
    "iso:country":"GB",
    "sg:address":"Unit 3, Calver Mill, Calver Bridge, Calver",
    "sg:city":"Chesterfield",
    "sg:classifiers":[
        {
            "category":"Professional",
            "type":"Services"
        }
    ],
    "sg:phone":"+44 1246 264600",
    "sg:postcode":"S41 9RN",
    "sg:province":"Derbyshire",
    "sg:tags":[
        "interior",
        "furnishers",
        "designer"
    ],
    "wof:name":"Nova Interiors",
    "wof:placetype":"venue"
},
  "geometry": {"coordinates":[-1.43699,53.265141],"type":"Point"}
}