{
  "type": "Feature",
  "properties": {
    "iso:country":"GB",
    "sg:address":"Endeavour House, Colmet Courseventh Avenue, Team Valley",
    "sg:city":"Gateshead",
    "sg:classifiers":[
        {
            "category":"Building & Trades",
            "subcategory":"Construction",
            "type":"Services"
        }
    ],
    "sg:phone":"+44 191 491 4914",
    "sg:postcode":"NE11 0JW",
    "sg:province":"Tyne and Wear",
    "sg:tags":[
        "builder"
    ],
    "wof:name":"Ballast Plc",
    "wof:placetype":"venue"
},
  "geometry": {"coordinates":[-1.61598,54.930168],"type":"Point"}
}