{
  "type": "Feature",
  "properties": {
    "iso:country":"GB",
    "sg:address":"11 Riverside Pla, St James Street",
    "sg:city":"Taunton",
    "sg:classifiers":[
        {
            "category":"Professional",
            "type":"Services"
        }
    ],
    "sg:phone":"+44 1823 271125",
    "sg:postcode":"TA1 1JH",
    "sg:province":"Somerset",
    "sg:tags":[
        "interior",
        "furnishers",
        "designer"
    ],
    "wof:name":"Limited Additions",
    "wof:placetype":"venue"
},
  "geometry": {"coordinates":[-3.1106989384,51.0104904175],"type":"Point"}
}