{
  "type": "Feature",
  "properties": {
    "addr:full":"31 Westbury Court, Hedge End Southampton Hampshire SO30 0HN",
    "addr:housenumber":"31",
    "addr:postcode":"so30 0hn",
    "addr:street":"Westbury Court",
    "iso:country":"GB",
    "sg:address":"31 Westbury Court, Hedge End",
    "sg:city":"Southampton",
    "sg:classifiers":[
        {
            "category":"Professional",
            "subcategory":"Detective & Security Services",
            "type":"Services"
        }
    ],
    "sg:phone":"+44 1329 339739",
    "sg:postcode":"SO30 0HN",
    "sg:province":"Hampshire",
    "sg:tags":[
        "locksmith"
    ],
    "wof:name":"Amtec Security",
    "wof:placetype":"venue"
},
  "geometry": {"coordinates":[-1.3037110567,50.9105873108],"type":"Point"}
}