{
  "type": "Feature",
  "properties": {
    "iso:country":"GB",
    "sg:address":"241 Harehills Lane",
    "sg:city":"Leeds",
    "sg:classifiers":[
        {
            "category":"Autos & Motor Vehicles",
            "subcategory":"Automobile Sales",
            "type":"Retail Goods"
        }
    ],
    "sg:phone":"+44 113 240 6483",
    "sg:postcode":"LS8 3RG",
    "sg:province":"West Yorkshire",
    "sg:tags":[
        "car",
        "truck"
    ],
    "wof:name":"Aadil Parvez",
    "wof:placetype":"venue"
},
  "geometry": {"coordinates":[-1.5118639469,53.8116569519],"type":"Point"}
}