{
  "type": "Feature",
  "properties": {
    "addr:full":"3 Pikes End, Old Eastcote Village Pinner Greater London HA5 2EX",
    "addr:housenumber":"3",
    "addr:postcode":"ha5 2ex",
    "addr:street":"Pikes End Old Eastcote Village",
    "iso:country":"GB",
    "sg:address":"3 Pikes End, Old Eastcote Village",
    "sg:city":"Pinner",
    "sg:classifiers":[
        {
            "category":"Personal",
            "type":"Services"
        }
    ],
    "sg:phone":"+44 20 8866 0506",
    "sg:postcode":"HA5 2EX",
    "sg:province":"Greater London",
    "sg:tags":[
        "wedding"
    ],
    "wof:name":"Heart To Heart",
    "wof:placetype":"venue"
},
  "geometry": {"coordinates":[-0.402931,51.589397],"type":"Point"}
}