{
  "type": "Feature",
  "properties": {
    "addr:full":"10 College Road Harrow Greater London HA1 1BE",
    "addr:housenumber":"10",
    "addr:postcode":"ha1 1be",
    "addr:street":"College Road",
    "iso:country":"GB",
    "sg:address":"10 College Road",
    "sg:city":"Harrow",
    "sg:classifiers":[
        {
            "category":"Professional",
            "subcategory":"Business Services",
            "type":"Services"
        }
    ],
    "sg:postcode":"HA1 1BE",
    "sg:province":"Greater London",
    "sg:tags":[
        "holding"
    ],
    "wof:name":"Galley Holdings Ltd",
    "wof:placetype":"venue"
},
  "geometry": {"coordinates":[-0.3380460143,51.5802383423],"type":"Point"}
}