{
  "type": "Feature",
  "properties": {
    "iso:country":"GB",
    "sg:address":"11-13 Roebuck Road",
    "sg:city":"Ilford",
    "sg:classifiers":[
        {
            "category":"Cafe",
            "type":"Food & Drink"
        }
    ],
    "sg:postcode":"IG6 3UE",
    "sg:province":"Essex",
    "sg:tags":[
        "tea",
        "room"
    ],
    "wof:name":"Joanne Carpel",
    "wof:placetype":"venue"
},
  "geometry": {"coordinates":[0.121171,51.60564],"type":"Point"}
}