{
  "type": "Feature",
  "properties": {
    "addr:full":"6 Moss Street Paisley Renfrewshire PA1 1LB",
    "addr:housenumber":"6",
    "addr:postcode":"pa1 1lb",
    "addr:street":"Moss Street",
    "iso:country":"GB",
    "sg:address":"6 Moss Street",
    "sg:city":"Paisley",
    "sg:classifiers":[
        {
            "category":"Professional",
            "subcategory":"Lawyer & Legal Services",
            "type":"Services"
        }
    ],
    "sg:phone":"+44 141 887 8961",
    "sg:postcode":"PA1 1LB",
    "sg:province":"Renfrewshire",
    "sg:tags":[
        "solicitor"
    ],
    "wof:name":"Alexander McAllister & McKechnie",
    "wof:placetype":"venue"
},
  "geometry": {"coordinates":[-4.424348,55.845821],"type":"Point"}
}