{
  "type": "Feature",
  "properties": {
    "iso:country":"GB",
    "sg:address":"14a High Rd",
    "sg:city":"East Finchley",
    "sg:classifiers":[
        {
            "category":"Autos & Motor Vehicles",
            "subcategory":"Auto Supplies",
            "type":"Retail Goods"
        }
    ],
    "sg:phone":"+44 20 8883 0570",
    "sg:postcode":"N2 9PJ",
    "sg:province":"Greater London",
    "sg:tags":[
        "component"
    ],
    "wof:name":"Franco's Mobile Services",
    "wof:placetype":"venue"
},
  "geometry": {"coordinates":[-0.1642390043,51.5872917175],"type":"Point"}
}