{
  "type": "Feature",
  "properties": {
    "addr:full":"16 Wayside, Fieldway, New Addington Croydon Surrey CR0 9DX",
    "addr:housenumber":"16",
    "addr:postcode":"cr0 9dx",
    "addr:street":"Wayside Fieldway",
    "iso:country":"GB",
    "sg:address":"16 Wayside, Fieldway, New Addington",
    "sg:city":"Croydon",
    "sg:classifiers":[
        {
            "category":"Health Services",
            "subcategory":"Dentist",
            "type":"Services"
        }
    ],
    "sg:phone":"+44 1689 847990",
    "sg:postcode":"CR0 9DX",
    "sg:province":"Surrey",
    "wof:name":"Croydon Health Authority",
    "wof:placetype":"venue"
},
  "geometry": {"coordinates":[-0.0215990003,51.3563270569],"type":"Point"}
}