{
  "type": "Feature",
  "properties": {
    "iso:country":"GB",
    "sg:address":"414-416 Ashley Road",
    "sg:city":"Poole",
    "sg:classifiers":[
        {
            "category":"Retail",
            "subcategory":"Auto Repair",
            "type":"Services"
        }
    ],
    "sg:phone":"+44 1202 740680",
    "sg:postcode":"BH14 0AA",
    "sg:province":"Dorset",
    "sg:tags":[
        "modification",
        "garage",
        "related"
    ],
    "wof:name":"R & H Autos",
    "wof:placetype":"venue"
},
  "geometry": {"coordinates":[-1.940923,50.729061],"type":"Point"}
}