{
  "type": "Feature",
  "properties": {
    "iso:country":"GB",
    "sg:address":"Star Garage, Wakefield Road, Copley",
    "sg:city":"Halifax",
    "sg:classifiers":[
        {
            "category":"Freight",
            "type":"Transportation"
        },
        {
            "category":"Professional",
            "subcategory":"Business Services",
            "type":"Services"
        }
    ],
    "sg:phone":"+44 1422 340821",
    "sg:postcode":"HX3 0TP",
    "sg:province":"West Yorkshire",
    "sg:tags":[
        "haulage",
        "distribution",
        "road"
    ],
    "wof:name":"H R Goodale (Northern) Ltd.",
    "wof:placetype":"venue"
},
  "geometry": {"coordinates":[-1.8694579601,53.6995048523],"type":"Point"}
}