{
  "type": "Feature",
  "properties": {
    "iso:country":"GB",
    "sg:address":"21 West St Helen Street",
    "sg:city":"Abingdon",
    "sg:classifiers":[
        {
            "category":"Shopping",
            "subcategory":"Thrift Store",
            "type":"Retail Goods"
        }
    ],
    "sg:postcode":"OX14 5BL",
    "sg:province":"Oxfordshire",
    "sg:tags":[
        "shop",
        "charity"
    ],
    "wof:name":"Animal Sanctuary Shop",
    "wof:placetype":"venue"
},
  "geometry": {"coordinates":[-1.283039,51.669899],"type":"Point"}
}