{
  "type": "Feature",
  "properties": {
    "addr:full":"614 Wakefield Road, Waterloo Huddersfield West Yorkshire HD5 8PZ",
    "addr:housenumber":"614",
    "addr:postcode":"hd5 8pz",
    "addr:street":"Wakefield Road",
    "iso:country":"GB",
    "sg:address":"614 Wakefield Road, Waterloo",
    "sg:city":"Huddersfield",
    "sg:classifiers":[
        {
            "category":"Shopping",
            "subcategory":"Clothing, Apparel, & Fashions",
            "type":"Retail Goods"
        },
        {
            "category":"Home & Garden",
            "subcategory":"Furniture",
            "type":"Retail Goods"
        }
    ],
    "sg:phone":"+44 1484 450066",
    "sg:postcode":"HD5 8PZ",
    "sg:province":"West Yorkshire",
    "sg:tags":[
        "clothing"
    ],
    "wof:name":"Leather Connections Ltd.",
    "wof:placetype":"venue"
},
  "geometry": {"coordinates":[-1.7390780449,53.6447486877],"type":"Point"}
}