{
  "type": "Feature",
  "properties": {
    "iso:country":"GB",
    "sg:address":"1 Sykes Lane, Balderton",
    "sg:city":"Newark",
    "sg:classifiers":[
        {
            "category":"Communications",
            "subcategory":"Film & Video Production",
            "type":"Services"
        },
        {
            "category":"Communications",
            "type":"Services"
        }
    ],
    "sg:phone":"+44 1636 702403",
    "sg:postcode":"NG24 3LT",
    "sg:province":"Nottinghamshire",
    "sg:tags":[
        "tv",
        "studio",
        "radio"
    ],
    "wof:name":"Bruce & Chambers Ltd.",
    "wof:placetype":"venue"
},
  "geometry": {"coordinates":[-0.780722,53.05497],"type":"Point"}
}