{
  "type": "Feature",
  "properties": {
    "addr:full":"400 Dallow Road Luton Bedfordshire LU1 1UR",
    "addr:housenumber":"400",
    "addr:postcode":"lu1 1ur",
    "addr:street":"Dallow Road",
    "iso:country":"GB",
    "sg:address":"400 Dallow Road",
    "sg:city":"Luton",
    "sg:classifiers":[
        {
            "category":"Professional",
            "subcategory":"Management & Consulting",
            "type":"Services"
        },
        {
            "category":"Government",
            "subcategory":"Fire Station",
            "type":"Public Place"
        }
    ],
    "sg:phone":"+44 1582 747317",
    "sg:postcode":"LU1 1UR",
    "sg:province":"Bedfordshire",
    "sg:tags":[
        "consultant",
        "security",
        "protection"
    ],
    "wof:name":"Autronica Industrial Ltd.",
    "wof:placetype":"venue"
},
  "geometry": {"coordinates":[-0.453822,51.884598],"type":"Point"}
}