{
  "type": "Feature",
  "properties": {
    "iso:country":"GB",
    "sg:address":"14 Lewis Road",
    "sg:city":"Northampton",
    "sg:classifiers":[
        {
            "category":"Recreation",
            "subcategory":"Dance Hall",
            "type":"Entertainment"
        }
    ],
    "sg:postcode":"NN5 7BJ",
    "sg:province":"Northamptonshire",
    "sg:tags":[
        "disco"
    ],
    "wof:name":"Disco Star",
    "wof:placetype":"venue"
},
  "geometry": {"coordinates":[-0.918194,52.245514],"type":"Point"}
}