{
  "type": "Feature",
  "properties": {
    "iso:country":"GB",
    "sg:address":"52 North Road",
    "sg:city":"St Helens",
    "sg:classifiers":[
        {
            "category":"Banks & Credit Unions",
            "subcategory":"Financial Services",
            "type":"Services"
        }
    ],
    "sg:phone":"+44 1744 754499",
    "sg:postcode":"WA10 2TR",
    "sg:province":"Merseyside",
    "sg:tags":[
        "consultant"
    ],
    "wof:name":"Shopacheck Financial Services Ltd.",
    "wof:placetype":"venue"
},
  "geometry": {"coordinates":[-2.739367,53.457397],"type":"Point"}
}