{
  "type": "Feature",
  "properties": {
    "iso:country":"GB",
    "sg:address":"Revells Cottage, Bilden End, Chrishall",
    "sg:city":"Royston",
    "sg:classifiers":[
        {
            "category":"Professional",
            "subcategory":"Art Services",
            "type":"Services"
        }
    ],
    "sg:postcode":"SG8 8RG",
    "sg:province":"Bedfordshire",
    "sg:tags":[
        "photographer"
    ],
    "wof:name":"Gordon Brown Photography",
    "wof:placetype":"venue"
},
  "geometry": {"coordinates":[0.1090840027,52.0293121338],"type":"Point"}
}