{
  "type": "Feature",
  "properties": {
    "iso:country":"GB",
    "sg:address":"23 Patrick Street",
    "sg:city":"Greenock",
    "sg:classifiers":[
        {
            "category":"Real Estate",
            "subcategory":"Real Estate Services",
            "type":"Services"
        },
        {
            "category":"Real Estate",
            "subcategory":"Real Estate Agent",
            "type":"Services"
        }
    ],
    "sg:phone":"+44 1475 784111",
    "sg:postcode":"PA16 8NB",
    "sg:province":"Inverclyde",
    "sg:tags":[
        "management"
    ],
    "wof:name":"Morison Walker Property Management Ltd.",
    "wof:placetype":"venue"
},
  "geometry": {"coordinates":[-4.7666158676,55.9520721436],"type":"Point"}
}