{
  "type": "Feature",
  "properties": {
    "addr:full":"Gilsthwaite Lane, Kirk Hammerton York North Yorkshire YO26 8DS",
    "addr:postcode":"yo26 8ds",
    "addr:street":"Gilsthwaite Lane",
    "iso:country":"GB",
    "sg:address":"Gilsthwaite Lane, Kirk Hammerton",
    "sg:city":"York",
    "sg:classifiers":[
        {
            "category":"Health Services",
            "subcategory":"Nursing And Care Facility",
            "type":"Services"
        },
        {
            "category":"Social Services",
            "subcategory":"Retirement Home",
            "type":"Services"
        }
    ],
    "sg:phone":"+44 1423 330609",
    "sg:postcode":"YO26 8DS",
    "sg:province":"North Yorkshire",
    "sg:tags":[
        "residential"
    ],
    "wof:name":"Oaklands Country Rest Home",
    "wof:placetype":"venue"
},
  "geometry": {"coordinates":[-1.279404,53.999191],"type":"Point"}
}