{
  "type": "Feature",
  "properties": {
    "addr:full":"56 Market Street Galashiels Scottish Borders TD1 3AN",
    "addr:housenumber":"56",
    "addr:postcode":"td1 3an",
    "addr:street":"Market Street",
    "iso:country":"GB",
    "sg:address":"56 Market Street",
    "sg:city":"Galashiels",
    "sg:classifiers":[
        {
            "category":"Travel",
            "subcategory":"Hotels & Motels",
            "type":"Entertainment"
        }
    ],
    "sg:postcode":"TD1 3AN",
    "sg:province":"Scottish Borders",
    "wof:name":"Kings Hotel",
    "wof:placetype":"venue"
},
  "geometry": {"coordinates":[-2.805464983,55.616153717],"type":"Point"}
}