{
  "type": "Feature",
  "properties": {
    "addr:full":"16 Cooks Road, Gosberton Spalding Lincolnshire PE11 4PD",
    "addr:housenumber":"16",
    "addr:postcode":"pe11 4pd",
    "addr:street":"Cooks Road;Spalding",
    "iso:country":"GB",
    "sg:address":"16 Cooks Road, Gosberton",
    "sg:city":"Spalding",
    "sg:classifiers":[
        {
            "category":"Farming",
            "subcategory":"Crops",
            "type":"Manufacturing & Wholesale Goods"
        },
        {
            "category":"Farming",
            "subcategory":"Farm",
            "type":"Manufacturing & Wholesale Goods"
        }
    ],
    "sg:phone":"+44 1775 840504",
    "sg:postcode":"PE11 4PD",
    "sg:province":"Lincolnshire",
    "sg:tags":[
        "mixed",
        "arable"
    ],
    "wof:name":"G A Twigg",
    "wof:placetype":"venue"
},
  "geometry": {"coordinates":[-0.127507,52.877399],"type":"Point"}
}