{
  "type": "Feature",
  "properties": {
    "iso:country":"GB",
    "sg:address":"20 Vicarage Road",
    "sg:city":"Birmingham",
    "sg:classifiers":[
        {
            "category":"Professional",
            "subcategory":"Management & Consulting",
            "type":"Services"
        }
    ],
    "sg:phone":"+44 121 441 5964",
    "sg:postcode":"B14 7RA",
    "sg:province":"West Midlands",
    "sg:tags":[
        "consultant",
        "business"
    ],
    "wof:name":"Michael Carey",
    "wof:placetype":"venue"
},
  "geometry": {"coordinates":[-1.89503,52.432159],"type":"Point"}
}