{
  "type": "Feature",
  "properties": {
    "iso:country":"GB",
    "sg:address":"226 High S East",
    "sg:city":"Wallsend",
    "sg:classifiers":[
        {
            "category":"Manufacturing",
            "subcategory":"Signs",
            "type":"Manufacturing & Wholesale Goods"
        }
    ],
    "sg:postcode":"NE28 7RX",
    "sg:province":"Tyne and Wear",
    "sg:tags":[
        "commercial",
        "maker"
    ],
    "wof:name":"Gemini Signs",
    "wof:placetype":"venue"
},
  "geometry": {"coordinates":[-1.521307,54.99284],"type":"Point"}
}