{
  "type": "Feature",
  "properties": {
    "iso:country":"GB",
    "sg:address":"Unit 7 Northwest Business Park, Servia Hill",
    "sg:city":"Leeds",
    "sg:classifiers":[
        {
            "category":"Real Estate",
            "subcategory":"Architect",
            "type":"Services"
        }
    ],
    "sg:phone":"+44 113 242 8996",
    "sg:postcode":"LS6 2QH",
    "sg:province":"West Yorkshire",
    "wof:name":"Herbert & Partners",
    "wof:placetype":"venue"
},
  "geometry": {"coordinates":[-1.54782,53.811031],"type":"Point"}
}