{
  "type": "Feature",
  "properties": {
    "addr:full":"Bells Close Yard, Bells Clo Newcastle Upon Tyne Northumberland NE15 6XA",
    "addr:postcode":"ne15 6xa",
    "addr:street":"Bells Close Yard Bells Clo",
    "iso:country":"GB",
    "sg:address":"Bells Close Yard, Bells Clo",
    "sg:city":"Newcastle Upon Tyne",
    "sg:classifiers":[
        {
            "category":"Wholesale",
            "subcategory":"Scrap",
            "type":"Manufacturing & Wholesale Goods"
        }
    ],
    "sg:phone":"+44 191 267 4774",
    "sg:postcode":"NE15 6XA",
    "sg:province":"Northumberland",
    "sg:tags":[
        "breaker",
        "dismantlers"
    ],
    "wof:name":"J Pringle Auto Salvage",
    "wof:placetype":"venue"
},
  "geometry": {"coordinates":[-1.6927200556,54.9690208435],"type":"Point"}
}