{
  "type": "Feature",
  "properties": {
    "addr:full":"Keycol Hill, Newington Sittingbourne Kent ME9 7LG",
    "addr:postcode":"me9 7lg",
    "addr:street":"Keycol Hill",
    "iso:country":"GB",
    "sg:address":"Keycol Hill, Newington",
    "sg:city":"Sittingbourne",
    "sg:classifiers":[
        {
            "category":"Health Services",
            "subcategory":"Nursing And Care Facility",
            "type":"Services"
        }
    ],
    "sg:phone":"+44 1795 843033",
    "sg:postcode":"ME9 7LG",
    "sg:province":"Kent",
    "sg:tags":[
        "home"
    ],
    "wof:name":"Keycol Nursing Home",
    "wof:placetype":"venue"
},
  "geometry": {"coordinates":[0.6837099791,51.3490715027],"type":"Point"}
}