{
  "type": "Feature",
  "properties": {
    "addr:full":"Upper Dicconson St Wigan Lancashire WN1 2AT",
    "addr:postcode":"wn1 2at",
    "addr:street":"Upper Dicconson St",
    "iso:country":"GB",
    "sg:address":"Upper Dicconson St",
    "sg:city":"Wigan",
    "sg:classifiers":[
        {
            "category":"Real Estate",
            "subcategory":"Real Estate Agent",
            "type":"Services"
        }
    ],
    "sg:phone":"+44 1942 243246",
    "sg:postcode":"WN1 2AT",
    "sg:province":"Lancashire",
    "wof:name":"M Lowe & Sons",
    "wof:placetype":"venue"
},
  "geometry": {"coordinates":[-2.629234,53.552067],"type":"Point"}
}