{
  "type": "Feature",
  "properties": {
    "iso:country":"GB",
    "sg:address":"Woolford House, Buckland Newton",
    "sg:city":"Dorchester",
    "sg:classifiers":[
        {
            "category":"Building & Trades",
            "subcategory":"Plumbing",
            "type":"Services"
        }
    ],
    "sg:postcode":"DT2 7DP",
    "sg:province":"Dorset",
    "sg:tags":[
        "heating"
    ],
    "wof:name":"Watkin Plumbing Heating & Electrical Services",
    "wof:placetype":"venue"
},
  "geometry": {"coordinates":[-2.43708,50.848179],"type":"Point"}
}