{
  "type": "Feature",
  "properties": {
    "addr:full":"42 Camden Rd Tunbridge Wells Kent TN1 2QD",
    "addr:housenumber":"42",
    "addr:postcode":"tn1 2qd",
    "addr:street":"Camden Rd",
    "iso:country":"GB",
    "sg:address":"42 Camden Rd",
    "sg:city":"Tunbridge Wells",
    "sg:classifiers":[
        {
            "category":"Professional",
            "subcategory":"Management & Consulting",
            "type":"Services"
        }
    ],
    "sg:postcode":"TN1 2QD",
    "sg:province":"Kent",
    "sg:tags":[
        "marketing",
        "consultant"
    ],
    "wof:name":"Howard Rock Marketing",
    "wof:placetype":"venue"
},
  "geometry": {"coordinates":[0.268068,51.135124],"type":"Point"}
}