{
  "type": "Feature",
  "properties": {
    "iso:country":"GB",
    "sg:address":"395a Limpsfield Road",
    "sg:city":"Warlingham",
    "sg:classifiers":[
        {
            "category":"Shopping",
            "subcategory":"Comic Books",
            "type":"Retail Goods"
        }
    ],
    "sg:postcode":"CR6 9HA",
    "sg:province":"Kent",
    "sg:tags":[
        "jeweller"
    ],
    "wof:name":"Carter Jewellers",
    "wof:placetype":"venue"
},
  "geometry": {"coordinates":[-0.055275,51.30983],"type":"Point"}
}