{
  "type": "Feature",
  "properties": {
    "addr:full":"18 Bewick Road Gateshead Tyne and Wear NE8 4DP",
    "addr:housenumber":"18",
    "addr:postcode":"ne8 4dp",
    "addr:street":"Bewick Road",
    "iso:country":"GB",
    "sg:address":"18 Bewick Road",
    "sg:city":"Gateshead",
    "sg:classifiers":[
        {
            "category":"Real Estate",
            "subcategory":"Architect",
            "type":"Services"
        }
    ],
    "sg:phone":"+44 191 478 7470",
    "sg:postcode":"NE8 4DP",
    "sg:province":"Tyne and Wear",
    "sg:tags":[
        "architectural"
    ],
    "wof:name":"Chipchase Associates Ltd",
    "wof:placetype":"venue"
},
  "geometry": {"coordinates":[-1.602543,54.956169],"type":"Point"}
}