{
  "type": "Feature",
  "properties": {
    "addr:full":"24 Carnforth Road, Heaton Chapel Stockport Cheshire SK4 5LE",
    "addr:housenumber":"24",
    "addr:postcode":"sk4 5le",
    "addr:street":"Carnforth Road",
    "iso:country":"GB",
    "sg:address":"24 Carnforth Road, Heaton Chapel",
    "sg:city":"Stockport",
    "sg:classifiers":[
        {
            "category":"Building & Trades",
            "subcategory":"Construction",
            "type":"Services"
        }
    ],
    "sg:phone":"+44 161 432 8825",
    "sg:postcode":"SK4 5LE",
    "sg:province":"Cheshire",
    "sg:tags":[
        "heating",
        "contractor"
    ],
    "wof:name":"Heatrite Industrial & Commercial Heating Engineers",
    "wof:placetype":"venue"
},
  "geometry": {"coordinates":[-2.1728858948,53.4332199097],"type":"Point"}
}