{
  "type": "Feature",
  "properties": {
    "addr:full":"73 Penrhyn Road Kingston-upon-thames Greater London KT1 2EQ",
    "addr:housenumber":"73",
    "addr:postcode":"kt1 2eq",
    "addr:street":"Penrhyn Road",
    "iso:country":"GB",
    "sg:address":"73 Penrhyn Road",
    "sg:city":"Kingston-upon-thames",
    "sg:classifiers":[
        {
            "category":"Building & Trades",
            "subcategory":"Construction",
            "type":"Services"
        }
    ],
    "sg:phone":"+44 20 8974 8676",
    "sg:postcode":"KT1 2EQ",
    "sg:province":"Greater London",
    "sg:tags":[
        "builder"
    ],
    "wof:name":"Amey Building Ltd.",
    "wof:placetype":"venue"
},
  "geometry": {"coordinates":[-0.3042109907,51.4025535583],"type":"Point"}
}