{
  "type": "Feature",
  "properties": {
    "iso:country":"GB",
    "sg:address":"40-41 Commercial Road",
    "sg:city":"Swindon",
    "sg:classifiers":[
        {
            "category":"Banks & Credit Unions",
            "subcategory":"Financial Services",
            "type":"Services"
        }
    ],
    "sg:phone":"+44 1793 613355",
    "sg:postcode":"SN1 5NX",
    "sg:province":"Wiltshire",
    "sg:tags":[
        "consultant",
        "finance"
    ],
    "wof:name":"CITIFINANCIAL EUROPE PLC",
    "wof:placetype":"venue"
},
  "geometry": {"coordinates":[-1.785368,51.558781],"type":"Point"}
}