{
  "type": "Feature",
  "properties": {
    "iso:country":"GB",
    "sg:address":"302 Chigwell Road",
    "sg:city":"Woodford Green",
    "sg:classifiers":[
        {
            "category":"Retail",
            "subcategory":"Auto Repair",
            "type":"Services"
        }
    ],
    "sg:phone":"+44 20 8504 3182",
    "sg:postcode":"IG8 8PN",
    "sg:province":"Essex",
    "sg:tags":[
        "modification",
        "garage",
        "related"
    ],
    "wof:name":"Manford Motors",
    "wof:placetype":"venue"
},
  "geometry": {"coordinates":[0.040454,51.59861],"type":"Point"}
}