{
  "type": "Feature",
  "properties": {
    "addr:full":"34 George Iv Bridge Edinburgh City of Edinburgh EH1 1EN",
    "addr:housenumber":"34",
    "addr:postcode":"eh1 1en",
    "addr:street":"George Iv Bridge Edinburgh",
    "iso:country":"GB",
    "sg:address":"34 George Iv Bridge",
    "sg:city":"Edinburgh",
    "sg:classifiers":[
        {
            "category":"Fast Food",
            "type":"Food & Drink"
        },
        {
            "category":"Cafe",
            "type":"Food & Drink"
        }
    ],
    "sg:phone":"+44 131 226 6706",
    "sg:postcode":"EH1 1EN",
    "sg:province":"City of Edinburgh",
    "sg:tags":[
        "tea",
        "away",
        "room",
        "take"
    ],
    "wof:name":"Pizza Paradise",
    "wof:placetype":"venue"
},
  "geometry": {"coordinates":[-3.1914050579,55.9471664429],"type":"Point"}
}