{
  "type": "Feature",
  "properties": {
    "iso:country":"GB",
    "sg:address":"170 London Rd",
    "sg:city":"High Wycombe",
    "sg:classifiers":[
        {
            "category":"Building & Trades",
            "subcategory":"Equipment Rental",
            "type":"Services"
        }
    ],
    "sg:phone":"+44 1494 443214",
    "sg:postcode":"HP11 1DQ",
    "sg:province":"Buckinghamshire",
    "sg:tags":[
        "hire",
        "centre"
    ],
    "wof:name":"Eveready Equipment Hire Ltd",
    "wof:placetype":"venue"
},
  "geometry": {"coordinates":[-0.735859,51.62532],"type":"Point"}
}