{
  "type": "Feature",
  "properties": {
    "iso:country":"GB",
    "sg:address":"P O Box 68",
    "sg:city":"High Wycombe",
    "sg:classifiers":[
        {
            "category":"Shopping",
            "subcategory":"Comic Books",
            "type":"Retail Goods"
        }
    ],
    "sg:phone":"+44 1494 524124",
    "sg:postcode":"HP13 5WN",
    "sg:province":"Buckinghamshire",
    "sg:tags":[
        "jeweller"
    ],
    "wof:name":"Worth Design Ltd.",
    "wof:placetype":"venue"
},
  "geometry": {"coordinates":[-0.7760570049,51.6499176025],"type":"Point"}
}