{
  "type": "Feature",
  "properties": {
    "addr:full":"80 Cowley Rd Oxford Oxfordshire OX4 1JB",
    "addr:housenumber":"80",
    "addr:postcode":"ox4 1jb",
    "addr:street":"Cowley Rd",
    "iso:country":"GB",
    "sg:address":"80 Cowley Rd",
    "sg:city":"Oxford",
    "sg:classifiers":[
        {
            "category":"Bars & Pubs",
            "type":"Food & Drink"
        }
    ],
    "sg:phone":"+44 1865 243069",
    "sg:postcode":"OX4 1JB",
    "sg:province":"Oxfordshire",
    "sg:tags":[
        "pubs",
        "inn"
    ],
    "wof:name":"The Prince Of Wales",
    "wof:placetype":"venue"
},
  "geometry": {"coordinates":[-1.2404470444,51.7487487793],"type":"Point"}
}