{
  "type": "Feature",
  "properties": {
    "iso:country":"GB",
    "sg:address":"134 Elton Rd",
    "sg:city":"Derby",
    "sg:classifiers":[
        {
            "category":"Fast Food",
            "type":"Food & Drink"
        }
    ],
    "sg:postcode":"DE24 8EG",
    "sg:province":"Derbyshire",
    "sg:tags":[
        "away",
        "take"
    ],
    "wof:name":"Gidda,Surdit Singh,",
    "wof:placetype":"venue"
},
  "geometry": {"coordinates":[-1.469009,52.898388],"type":"Point"}
}