{
  "type": "Feature",
  "properties": {
    "addr:full":"Manor Farm House, Chapel Lane, Enstone Chipping Norton Gloucestershire OX7 4LT",
    "addr:housenumber":"norton",
    "addr:postcode":"ox7 4lt",
    "addr:street":"Manor;Chapel Lane",
    "iso:country":"GB",
    "sg:address":"Manor Farm House, Chapel Lane, Enstone",
    "sg:city":"Chipping Norton",
    "sg:classifiers":[
        {
            "category":"Personal",
            "subcategory":"Beauty Salon",
            "type":"Services"
        }
    ],
    "sg:phone":"+44 1608 678722",
    "sg:postcode":"OX7 4LT",
    "sg:province":"Gloucestershire",
    "sg:tags":[
        "lady",
        "hairdresser"
    ],
    "wof:name":"Stephanie's",
    "wof:placetype":"venue"
},
  "geometry": {"coordinates":[-1.452305,51.916367],"type":"Point"}
}