{
  "type": "Feature",
  "properties": {
    "addr:full":"76 Hatherley Road Sidcup Kent DA14 4AJ",
    "addr:housenumber":"76",
    "addr:postcode":"da14 4aj",
    "addr:street":"Hatherley Road",
    "iso:country":"GB",
    "sg:address":"76 Hatherley Road",
    "sg:city":"Sidcup",
    "sg:classifiers":[
        {
            "category":"Professional",
            "type":"Services"
        }
    ],
    "sg:phone":"+44 20 8309 6164",
    "sg:postcode":"DA14 4AJ",
    "sg:province":"Kent",
    "sg:tags":[
        "shopfitters"
    ],
    "wof:name":"Fenner Nash Projects Ltd.",
    "wof:placetype":"venue"
},
  "geometry": {"coordinates":[0.104489997,51.4317741394],"type":"Point"}
}