{
  "type": "Feature",
  "properties": {
    "addr:full":"52 Allison Street, Digbeth Birmingham West Midlands B5 5TH",
    "addr:housenumber":"52;b5",
    "addr:postcode":"5th",
    "addr:street":"Allison Street",
    "iso:country":"GB",
    "sg:address":"52 Allison Street, Digbeth",
    "sg:city":"Birmingham",
    "sg:classifiers":[
        {
            "category":"Travel",
            "subcategory":"Hotels & Motels",
            "type":"Entertainment"
        }
    ],
    "sg:phone":"+44 121 643 5094",
    "sg:postcode":"B5 5TH",
    "sg:province":"West Midlands",
    "sg:tags":[
        "house",
        "guest"
    ],
    "wof:name":"Allison House",
    "wof:placetype":"venue"
},
  "geometry": {"coordinates":[-1.889463,52.478577],"type":"Point"}
}