{
  "type": "Feature",
  "properties": {
    "addr:full":"306 Havant Road, Drayton Portsmouth Hampshire PO6 1PF",
    "addr:housenumber":"306",
    "addr:postcode":"hampshire po6 1pf",
    "addr:street":"Havant Road",
    "iso:country":"GB",
    "sg:address":"306 Havant Road, Drayton",
    "sg:city":"Portsmouth",
    "sg:classifiers":[
        {
            "category":"Banks & Credit Unions",
            "subcategory":"Financial Services",
            "type":"Services"
        }
    ],
    "sg:phone":"+44 23 9238 4272",
    "sg:postcode":"PO6 1PF",
    "sg:province":"Hampshire",
    "sg:tags":[
        "adviser"
    ],
    "wof:name":"Forrest Peter",
    "wof:placetype":"venue"
},
  "geometry": {"coordinates":[-1.0418269634,50.8463363647],"type":"Point"}
}