{
  "type": "Feature",
  "properties": {
    "addr:full":"13 Bayencourt South Bexhill On Sea East Sussex TN40 2AH",
    "addr:housenumber":"13",
    "addr:postcode":"tn40 2ah",
    "addr:street":"Bayencourt South",
    "iso:country":"GB",
    "sg:address":"13 Bayencourt South",
    "sg:city":"Bexhill On Sea",
    "sg:classifiers":[
        {
            "category":"Retail",
            "subcategory":"Storage",
            "type":"Services"
        }
    ],
    "sg:phone":"+44 1424 733444",
    "sg:postcode":"TN40 2AH",
    "sg:province":"East Sussex",
    "sg:tags":[
        "household",
        "removal"
    ],
    "wof:name":"Economove",
    "wof:placetype":"venue"
},
  "geometry": {"coordinates":[0.4702149928,50.847038269],"type":"Point"}
}