{
  "type": "Feature",
  "properties": {
    "addr:full":"Globos House, Unit A2, Commerce Way Colchester Essex CO2 8HH",
    "addr:housenumber":"unit a2",
    "addr:postcode":"co2 8hh",
    "addr:street":"Commerce Way",
    "iso:country":"GB",
    "sg:address":"Globos House, Unit A2, Commerce Way",
    "sg:city":"Colchester",
    "sg:classifiers":[
        {
            "category":"Wholesale",
            "subcategory":"Toys & Hobbies",
            "type":"Manufacturing & Wholesale Goods"
        }
    ],
    "sg:phone":"+44 1621 819041",
    "sg:postcode":"CO2 8HH",
    "sg:province":"Essex",
    "sg:tags":[
        "balloon",
        "novelty"
    ],
    "wof:name":"I T I Ltd",
    "wof:placetype":"venue"
},
  "geometry": {"coordinates":[0.93282,51.874641],"type":"Point"}
}