{
  "type": "Feature",
  "properties": {
    "iso:country":"GB",
    "sg:address":"175 Alphington Rd",
    "sg:city":"Exeter",
    "sg:classifiers":[
        {
            "category":"Shopping",
            "type":"Retail Goods"
        }
    ],
    "sg:phone":"+44 1392 413144",
    "sg:postcode":"EX2 8NA",
    "sg:province":"Devon",
    "sg:tags":[
        "part",
        "accessory"
    ],
    "wof:name":"Prozone (UK) Ltd",
    "wof:placetype":"venue"
},
  "geometry": {"coordinates":[-3.5373129845,50.7082748413],"type":"Point"}
}