{
  "type": "Feature",
  "properties": {
    "addr:full":"15 Home Street Edinburgh City of Edinburgh EH3 9JR",
    "addr:housenumber":"15",
    "addr:postcode":"eh3 9jr",
    "addr:street":"Home Street",
    "iso:country":"GB",
    "sg:address":"15 Home Street",
    "sg:city":"Edinburgh",
    "sg:classifiers":[
        {
            "category":"Banks & Credit Unions",
            "subcategory":"Financial Services",
            "type":"Services"
        }
    ],
    "sg:phone":"+44 131 221 1177",
    "sg:postcode":"EH3 9JR",
    "sg:province":"City of Edinburgh",
    "sg:tags":[
        "cashing",
        "operation",
        "cheque"
    ],
    "wof:name":"CLEARACHEQUE LTD",
    "wof:placetype":"venue"
},
  "geometry": {"coordinates":[-3.2039449215,55.9434318542],"type":"Point"}
}