{
  "type": "Feature",
  "properties": {
    "addr:full":"10 Wainsford Close Lymington Hampshire SO41 8BR",
    "addr:housenumber":"10",
    "addr:postcode":"so41 8br",
    "addr:street":"Wainsford Close",
    "iso:country":"GB",
    "sg:address":"10 Wainsford Close",
    "sg:city":"Lymington",
    "sg:classifiers":[
        {
            "category":"Building & Trades",
            "subcategory":"Construction",
            "type":"Services"
        }
    ],
    "sg:postcode":"SO41 8BR",
    "sg:province":"Hampshire",
    "sg:tags":[
        "dry",
        "lining",
        "plasterers",
        "screeders"
    ],
    "wof:name":"S J Haley",
    "wof:placetype":"venue"
},
  "geometry": {"coordinates":[-1.5672609806,50.7537460327],"type":"Point"}
}