{
  "type": "Feature",
  "properties": {
    "iso:country":"GB",
    "sg:address":"1 Breton Close, Kilby",
    "sg:city":"Leicester",
    "sg:classifiers":[
        {
            "category":"Manufacturing",
            "subcategory":"Textiles",
            "type":"Manufacturing & Wholesale Goods"
        }
    ],
    "sg:phone":"+44 116 240 3670",
    "sg:postcode":"LE18 3TL",
    "sg:province":"Leicestershire",
    "sg:tags":[
        "merchant",
        "agent"
    ],
    "wof:name":"John Winslow Quality Service",
    "wof:placetype":"venue"
},
  "geometry": {"coordinates":[-1.0865800381,52.5531005859],"type":"Point"}
}