{
  "type": "Feature",
  "properties": {
    "addr:full":"Old Wells Road Fakenham Norfolk NR21 9AF",
    "addr:postcode":"nr21 9af",
    "addr:street":"Old Wells Road",
    "iso:country":"GB",
    "sg:address":"Old Wells Road",
    "sg:city":"Fakenham",
    "sg:classifiers":[
        {
            "category":"Arena",
            "subcategory":"Sports Club",
            "type":"Entertainment"
        }
    ],
    "sg:phone":"+44 1328 851007",
    "sg:postcode":"NR21 9AF",
    "sg:province":"Norfolk",
    "wof:name":"Fakenham Rugby Club",
    "wof:placetype":"venue"
},
  "geometry": {"coordinates":[0.845089972,52.8342247009],"type":"Point"}
}