{
  "type": "Feature",
  "properties": {
    "addr:full":"Hallco House, North Bridge Road Berkhamsted Bedfordshire HP4 1EH",
    "addr:postcode":"hp4 1eh",
    "addr:street":"North Bridge Road",
    "iso:country":"GB",
    "sg:address":"Hallco House, North Bridge Road",
    "sg:city":"Berkhamsted",
    "sg:classifiers":[
        {
            "category":"Home & Garden",
            "subcategory":"Household Appliances",
            "type":"Retail Goods"
        }
    ],
    "sg:phone":"+44 1442 875578",
    "sg:postcode":"HP4 1EH",
    "sg:province":"Bedfordshire",
    "sg:tags":[
        "domestic",
        "oven",
        "microwave"
    ],
    "wof:name":"R H Hall (Microwave) Ltd.",
    "wof:placetype":"venue"
},
  "geometry": {"coordinates":[-0.580807,51.767838],"type":"Point"}
}