{
  "type": "Feature",
  "properties": {
    "iso:country":"GB",
    "sg:address":"Crossend Farm, Moccas",
    "sg:city":"Hereford",
    "sg:classifiers":[
        {
            "category":"Farming",
            "subcategory":"Livestock Farm",
            "type":"Manufacturing & Wholesale Goods"
        }
    ],
    "sg:postcode":"HR2 9LE",
    "sg:province":"Herefordshire",
    "sg:tags":[
        "others"
    ],
    "wof:name":"P M Chester-Master",
    "wof:placetype":"venue"
},
  "geometry": {"coordinates":[-2.9391589165,52.0792198181],"type":"Point"}
}