{
  "type": "Feature",
  "properties": {
    "addr:full":"Old Abbey Road North Berwick East Lothian EH39 4BP",
    "addr:postcode":"eh39 4bp",
    "addr:street":"Old Abbey Road",
    "iso:country":"GB",
    "sg:address":"Old Abbey Road",
    "sg:city":"North Berwick",
    "sg:classifiers":[
        {
            "category":"Government",
            "subcategory":"Office",
            "type":"Public Place"
        }
    ],
    "sg:phone":"+44 1620 892875",
    "sg:postcode":"EH39 4BP",
    "sg:province":"East Lothian",
    "sg:tags":[
        "central"
    ],
    "wof:name":"The Abbey Residential Care",
    "wof:placetype":"venue"
},
  "geometry": {"coordinates":[-2.730972,56.055759],"type":"Point"}
}