{
  "type": "Feature",
  "properties": {
    "addr:full":"1st Floor, 87-89 High Street Hoddesdon Essex EN11 8TL",
    "addr:housenumber":"87-89",
    "addr:postcode":"en11 8tl",
    "addr:street":"High Street",
    "iso:country":"GB",
    "sg:address":"1st Floor, 87-89 High Street",
    "sg:city":"Hoddesdon",
    "sg:classifiers":[
        {
            "category":"Professional",
            "subcategory":"Accounting & Tax Preparation",
            "type":"Services"
        }
    ],
    "sg:phone":"+44 1992 440633",
    "sg:postcode":"EN11 8TL",
    "sg:province":"Essex",
    "sg:tags":[
        "accountant"
    ],
    "wof:name":"A Infantino & Co",
    "wof:placetype":"venue"
},
  "geometry": {"coordinates":[-0.0119240005,51.7605285645],"type":"Point"}
}