{
  "type": "Feature",
  "properties": {
    "addr:full":"Common Leys Farm, Hailey Witney Oxfordshire OX29 9UY",
    "addr:postcode":"ox29 9uy",
    "addr:street":"Common",
    "iso:country":"GB",
    "sg:address":"Common Leys Farm, Hailey",
    "sg:city":"Witney",
    "sg:classifiers":[
        {
            "category":"Education",
            "subcategory":"Special Training",
            "type":"Public Place"
        }
    ],
    "sg:phone":"+44 1993 868076",
    "sg:postcode":"OX29 9UY",
    "sg:province":"Oxfordshire",
    "sg:tags":[
        "product",
        "centre"
    ],
    "wof:name":"Common Leys Farm",
    "wof:placetype":"venue"
},
  "geometry": {"coordinates":[-1.4774,51.82019],"type":"Point"}
}