{
  "type": "Feature",
  "properties": {
    "iso:country":"GB",
    "sg:address":"44 Ashgrove",
    "sg:city":"Buckingham",
    "sg:classifiers":[
        {
            "category":"Home & Garden",
            "subcategory":"Household Appliances",
            "type":"Retail Goods"
        }
    ],
    "sg:phone":"+44 1296 738106",
    "sg:postcode":"MK18 2NW",
    "sg:province":"Buckinghamshire",
    "sg:tags":[
        "electrical"
    ],
    "wof:name":"Cliff Dalton",
    "wof:placetype":"venue"
},
  "geometry": {"coordinates":[-0.987488,51.936451],"type":"Point"}
}