{
  "type": "Feature",
  "properties": {
    "addr:full":"Ewenny Road Maesteg Bridgend CF34 9PT",
    "addr:postcode":"cf34 9pt",
    "addr:street":"Ewenny Road",
    "iso:country":"GB",
    "sg:address":"Ewenny Road",
    "sg:city":"Maesteg",
    "sg:classifiers":[
        {
            "category":"Shopping",
            "type":"Retail Goods"
        },
        {
            "category":"Home & Garden",
            "subcategory":"Carpets & Floor Coverings",
            "type":"Retail Goods"
        }
    ],
    "sg:phone":"+44 1656 812800",
    "sg:postcode":"CF34 9PT",
    "sg:province":"Bridgend",
    "sg:tags":[
        "rubber",
        "plastic",
        "part",
        "accessory"
    ],
    "wof:name":"Cooper Standard Automotive",
    "wof:placetype":"venue"
},
  "geometry": {"coordinates":[-3.6465089321,51.6058235168],"type":"Point"}
}