{
  "type": "Feature",
  "properties": {
    "addr:full":"4-5 Albany Business Centre, Wickham Road Fareham Hampshire PO17 5BD",
    "addr:housenumber":"4-5",
    "addr:postcode":"po17 5bd",
    "addr:street":"Albany Business Centre Wickham Road",
    "iso:country":"GB",
    "sg:address":"4-5 Albany Business Centre, Wickham Road",
    "sg:city":"Fareham",
    "sg:classifiers":[
        {
            "category":"Home & Garden",
            "subcategory":"Furniture",
            "type":"Retail Goods"
        }
    ],
    "sg:phone":"+44 1329 828844",
    "sg:postcode":"PO17 5BD",
    "sg:province":"Hampshire",
    "wof:name":"Kerrian Furniture",
    "wof:placetype":"venue"
},
  "geometry": {"coordinates":[-1.189109,50.899818],"type":"Point"}
}