{
  "type": "Feature",
  "properties": {
    "iso:country":"GB",
    "sg:address":"26 Millwood Road",
    "sg:city":"Ellon",
    "sg:classifiers":[
        {
            "category":"Shopping",
            "subcategory":"Pets & Pet Supplies",
            "type":"Retail Goods"
        }
    ],
    "sg:phone":"+44 1358 723013",
    "sg:postcode":"AB41 9FA",
    "sg:province":"Aberdeenshire",
    "wof:name":"F W W Consulting Ltd.",
    "wof:placetype":"venue"
},
  "geometry": {"coordinates":[-2.092261076,57.3697395325],"type":"Point"}
}