{
  "type": "Feature",
  "properties": {
    "addr:full":"30 Hamilton St Saltcoats North Ayrshire KA21 5DS",
    "addr:housenumber":"30",
    "addr:postcode":"ka21 5ds",
    "addr:street":"Hamilton St",
    "iso:country":"GB",
    "sg:address":"30 Hamilton St",
    "sg:city":"Saltcoats",
    "sg:classifiers":[
        {
            "category":"Professional",
            "subcategory":"Art Services",
            "type":"Services"
        }
    ],
    "sg:postcode":"KA21 5DS",
    "sg:province":"North Ayrshire",
    "sg:tags":[
        "framing"
    ],
    "wof:name":"Paignton,Alison,",
    "wof:placetype":"venue"
},
  "geometry": {"coordinates":[-4.7906770706,55.6343269348],"type":"Point"}
}