{
  "type": "Feature",
  "properties": {
    "iso:country":"GB",
    "sg:address":"30 Hamilton St",
    "sg:city":"Saltcoats",
    "sg:classifiers":[
        {
            "category":"Professional",
            "subcategory":"Art Services",
            "type":"Services"
        }
    ],
    "sg:postcode":"KA21 5DS",
    "sg:province":"North Ayrshire",
    "sg:tags":[
        "framing"
    ],
    "wof:name":"Paignton,Alison,",
    "wof:placetype":"venue"
},
  "geometry": {"coordinates":[-4.7906770706,55.6343269348],"type":"Point"}
}