{
  "type": "Feature",
  "properties": {
    "iso:country":"GB",
    "sg:address":"Park House, London Road",
    "sg:city":"High Wycombe",
    "sg:classifiers":[
        {
            "category":"Professional",
            "subcategory":"Lawyer & Legal Services",
            "type":"Services"
        }
    ],
    "sg:phone":"+44 1494 450171",
    "sg:postcode":"HP11 1BZ",
    "sg:province":"Buckinghamshire",
    "sg:tags":[
        "solicitor"
    ],
    "wof:name":"Blaser Mills Solicitors",
    "wof:placetype":"venue"
},
  "geometry": {"coordinates":[-0.743035,51.626888],"type":"Point"}
}