{
  "type": "Feature",
  "properties": {
    "iso:country":"GB",
    "sg:address":"12 Castle Terr",
    "sg:city":"Edinburgh",
    "sg:classifiers":[
        {
            "category":"Professional",
            "subcategory":"Lawyer & Legal Services",
            "type":"Services"
        }
    ],
    "sg:phone":"+44 131 228 2992",
    "sg:postcode":"EH1 2DP",
    "sg:province":"City of Edinburgh",
    "sg:tags":[
        "patent",
        "agent"
    ],
    "wof:name":"Cruikshank & Fairweather",
    "wof:placetype":"venue"
},
  "geometry": {"coordinates":[-3.204879,55.948139],"type":"Point"}
}