{
  "type": "Feature",
  "properties": {
    "addr:full":"Unit Ii, 11 Dongan Road Warwick Warwickshire CV34 4JW",
    "addr:housenumber":"11",
    "addr:postcode":"cv34 4jw",
    "addr:street":"Dongan Road",
    "iso:country":"GB",
    "sg:address":"Unit Ii, 11 Dongan Road",
    "sg:city":"Warwick",
    "sg:classifiers":[
        {
            "category":"Freight",
            "type":"Transportation"
        }
    ],
    "sg:postcode":"CV34 4JW",
    "sg:province":"Warwickshire",
    "sg:tags":[
        "forwarders"
    ],
    "wof:name":"Warwick Freight Logistics",
    "wof:placetype":"venue"
},
  "geometry": {"coordinates":[-1.5910340548,52.28175354],"type":"Point"}
}