{
  "type": "Feature",
  "properties": {
    "iso:country":"GB",
    "sg:address":"Imot 4 Parrs Corner, Marsh La",
    "sg:city":"Bootle",
    "sg:classifiers":[
        {
            "category":"Cafe",
            "type":"Food & Drink"
        }
    ],
    "sg:postcode":"L20 4JG",
    "sg:province":"Merseyside",
    "sg:tags":[
        "tea",
        "room"
    ],
    "wof:name":"Parrs Corner Cafe",
    "wof:placetype":"venue"
},
  "geometry": {"coordinates":[-2.986464,53.455811],"type":"Point"}
}