{
  "type": "Feature",
  "properties": {
    "addr:full":"Imot 4 Parrs Corner, Marsh La Bootle Merseyside L20 4JG",
    "addr:housenumber":"4",
    "addr:postcode":"l20 4jg",
    "addr:street":"Imot;Corner Marsh La Bootle",
    "iso:country":"GB",
    "sg:address":"Imot 4 Parrs Corner, Marsh La",
    "sg:city":"Bootle",
    "sg:classifiers":[
        {
            "category":"Cafe",
            "type":"Food & Drink"
        }
    ],
    "sg:postcode":"L20 4JG",
    "sg:province":"Merseyside",
    "sg:tags":[
        "tea",
        "room"
    ],
    "wof:name":"Parrs Corner Cafe",
    "wof:placetype":"venue"
},
  "geometry": {"coordinates":[-2.986464,53.455811],"type":"Point"}
}