{
  "type": "Feature",
  "properties": {
    "addr:full":"P O Box 1737 Yeovil Somerset BA20 1NF",
    "addr:housenumber":"p o;1737",
    "addr:postcode":"ba20 1nf",
    "iso:country":"GB",
    "sg:address":"P O Box 1737",
    "sg:city":"Yeovil",
    "sg:classifiers":[
        {
            "category":"Manufacturing",
            "subcategory":"Jewelry",
            "type":"Manufacturing & Wholesale Goods"
        },
        {
            "category":"Building & Trades",
            "subcategory":"Equipment Rental",
            "type":"Services"
        }
    ],
    "sg:postcode":"BA20 1NF",
    "sg:province":"Somerset",
    "sg:tags":[
        "repair",
        "jewellery",
        "supply"
    ],
    "wof:name":"Jonathan Lynne Ltd.",
    "wof:placetype":"venue"
},
  "geometry": {"coordinates":[-2.6243999004,50.9416389465],"type":"Point"}
}