{
  "type": "Feature",
  "properties": {
    "iso:country":"GB",
    "sg:address":"26 Northumberland Square",
    "sg:city":"North Shields",
    "sg:classifiers":[
        {
            "category":"Utilities",
            "subcategory":"Electric",
            "type":"Services"
        },
        {
            "category":"Utilities",
            "subcategory":"Natural Gas",
            "type":"Services"
        }
    ],
    "sg:phone":"+44 191 296 2999",
    "sg:postcode":"NE30 1PW",
    "sg:province":"Tyne and Wear",
    "sg:tags":[
        "consultant",
        "system",
        "air conditioning"
    ],
    "sg:website":"http://www.sutton.co.uk",
    "wof:name":"Sutton Services International Ltd",
    "wof:placetype":"venue"
},
  "geometry": {"coordinates":[-1.4459120035,55.0105171204],"type":"Point"}
}