{
  "type": "Feature",
  "properties": {
    "iso:country":"GB",
    "sg:address":"The Grange, Errol",
    "sg:city":"Perth",
    "sg:classifiers":[
        {
            "category":"Home & Garden",
            "subcategory":"Building Materials",
            "type":"Retail Goods"
        }
    ],
    "sg:postcode":"PH2 7TB",
    "sg:province":"Perth and Kinross",
    "sg:tags":[
        "insulation",
        "installers"
    ],
    "wof:name":"A M Insulations & Acoustic Services",
    "wof:placetype":"venue"
},
  "geometry": {"coordinates":[-3.2097530365,56.3933792114],"type":"Point"}
}