{
  "type": "Feature",
  "properties": {
    "addr:full":"21 Princes Drive Kenilworth Warwickshire CV8 2SD",
    "addr:housenumber":"21",
    "addr:postcode":"cv8 2sd",
    "addr:street":"Princes Drive",
    "iso:country":"GB",
    "sg:address":"21 Princes Drive",
    "sg:city":"Kenilworth",
    "sg:classifiers":[
        {
            "category":"Building & Trades",
            "subcategory":"Construction",
            "type":"Services"
        }
    ],
    "sg:phone":"+44 1926 511316",
    "sg:postcode":"CV8 2SD",
    "sg:province":"Warwickshire",
    "sg:tags":[
        "pipework",
        "contractor"
    ],
    "wof:name":"Pipeline Services Ltd.",
    "wof:placetype":"venue"
},
  "geometry": {"coordinates":[-1.567931,52.357346],"type":"Point"}
}