{
  "type": "Feature",
  "properties": {
    "addr:full":"154-160 High Street Edinburgh City of Edinburgh EH1 1QS",
    "addr:housenumber":"154-160",
    "addr:postcode":"eh1 1qs",
    "addr:street":"High Street",
    "iso:country":"GB",
    "sg:address":"154-160 High Street",
    "sg:city":"Edinburgh",
    "sg:classifiers":[
        {
            "category":"Bars & Pubs",
            "type":"Food & Drink"
        }
    ],
    "sg:phone":"+44 131 225 7064",
    "sg:postcode":"EH1 1QS",
    "sg:province":"City of Edinburgh",
    "sg:tags":[
        "pubs",
        "inn"
    ],
    "wof:name":"Valentine's Saloon Bar",
    "wof:placetype":"venue"
},
  "geometry": {"coordinates":[-3.189324,55.949905],"type":"Point"}
}