{
  "type": "Feature",
  "properties": {
    "addr:full":"29 High Road, Ashton Keynes Swindon Gloucestershire SN6 6NX",
    "addr:housenumber":"29",
    "addr:postcode":"sn6 6nx",
    "addr:street":"High Road",
    "iso:country":"GB",
    "sg:address":"29 High Road, Ashton Keynes",
    "sg:city":"Swindon",
    "sg:classifiers":[
        {
            "category":"Autos & Motor Vehicles",
            "subcategory":"Automobile Sales",
            "type":"Retail Goods"
        }
    ],
    "sg:phone":"+44 1285 861010",
    "sg:postcode":"SN6 6NX",
    "sg:province":"Gloucestershire",
    "sg:tags":[
        "car"
    ],
    "wof:name":"Keyneswell Motor Co",
    "wof:placetype":"venue"
},
  "geometry": {"coordinates":[-1.9351730347,51.6447486877],"type":"Point"}
}