{
  "type": "Feature",
  "properties": {
    "addr:full":"10 Strand Swansea Neath Port Talbot SA1 2AE",
    "addr:housenumber":"10",
    "addr:postcode":"sa1 2ae",
    "addr:street":"Strand",
    "iso:country":"GB",
    "sg:address":"10 Strand",
    "sg:city":"Swansea",
    "sg:classifiers":[
        {
            "category":"Bars & Pubs",
            "type":"Food & Drink"
        }
    ],
    "sg:phone":"+44 1792 645345",
    "sg:postcode":"SA1 2AE",
    "sg:province":"Neath Port Talbot",
    "sg:tags":[
        "pubs",
        "inn"
    ],
    "wof:name":"O'Briens Exchange Bar & Restaurant",
    "wof:placetype":"venue"
},
  "geometry": {"coordinates":[-3.9403820038,51.620098114],"type":"Point"}
}