{
  "type": "Feature",
  "properties": {
    "addr:full":"Brookfield Centre, Brookfield Lane, Cheshunt Waltham Cross Essex EN8 0QH",
    "addr:postcode":"en8 0qh",
    "addr:street":"Brookfield Lane;Cross",
    "iso:country":"GB",
    "sg:address":"Brookfield Centre, Brookfield Lane, Cheshunt",
    "sg:city":"Waltham Cross",
    "sg:classifiers":[
        {
            "category":"Autos & Motor Vehicles",
            "subcategory":"Fuel & Gas Station",
            "type":"Retail Goods"
        },
        {
            "category":"Food & Beverages",
            "subcategory":"Supermarket",
            "type":"Retail Goods"
        },
        {
            "category":"Shopping",
            "subcategory":"Pharmacy",
            "type":"Retail Goods"
        }
    ],
    "sg:phone":"+44 1992 637234",
    "sg:postcode":"EN8 0QH",
    "sg:province":"Essex",
    "sg:tags":[
        "petrol",
        "filling",
        "pharmacist",
        "chemist"
    ],
    "wof:name":"Tesco Petrol Filling Stations",
    "wof:placetype":"venue"
},
  "geometry": {"coordinates":[-0.0374500006,51.7187423706],"type":"Point"}
}