{
  "type": "Feature",
  "properties": {
    "addr:full":"Grove Lane, Wishaw Sutton Coldfield Warwickshire B76 9PQ",
    "addr:postcode":"b76 9pq",
    "addr:street":"Grove Lane",
    "iso:country":"GB",
    "sg:address":"Grove Lane, Wishaw",
    "sg:city":"Sutton Coldfield",
    "sg:classifiers":[
        {
            "category":"Professional",
            "subcategory":"Business Services",
            "type":"Services"
        }
    ],
    "sg:postcode":"B76 9PQ",
    "sg:province":"Warwickshire",
    "sg:tags":[
        "hospitality",
        "corporate"
    ],
    "wof:name":"D & A Mitchell",
    "wof:placetype":"venue"
},
  "geometry": {"coordinates":[-1.755149,52.552963],"type":"Point"}
}