{
  "type": "Feature",
  "properties": {
    "addr:full":"4/5 Knightsbridge Business Centr Cheltenham Gloucestershire GL51 9TA",
    "addr:housenumber":"4 / 5",
    "addr:postcode":"gl51 9ta",
    "addr:street":"Knightsbridge Business Centr",
    "iso:country":"GB",
    "sg:address":"4/5 Knightsbridge Business Centr",
    "sg:city":"Cheltenham",
    "sg:classifiers":[
        {
            "category":"Shopping",
            "subcategory":"Bicycles & Sporting Goods",
            "type":"Retail Goods"
        }
    ],
    "sg:postcode":"GL51 9TA",
    "sg:province":"Gloucestershire",
    "sg:tags":[
        "equipment",
        "leisure"
    ],
    "wof:name":"Dive 90 Ltd.",
    "wof:placetype":"venue"
},
  "geometry": {"coordinates":[-2.1566,51.94043],"type":"Point"}
}