{
  "type": "Feature",
  "properties": {
    "addr:full":"96 High Street Marlow Berkshire SL7 1AQ",
    "addr:housenumber":"96",
    "addr:postcode":"sl7 1aq",
    "addr:street":"High Street",
    "iso:country":"GB",
    "sg:address":"96 High Street",
    "sg:city":"Marlow",
    "sg:classifiers":[
        {
            "category":"Communications",
            "subcategory":"Film & Video Production",
            "type":"Services"
        },
        {
            "category":"Communications",
            "type":"Services"
        }
    ],
    "sg:phone":"+44 1628 477006",
    "sg:postcode":"SL7 1AQ",
    "sg:province":"Berkshire",
    "sg:tags":[
        "tv",
        "broadcasting",
        "studio"
    ],
    "wof:name":"Visionsport International Ltd.",
    "wof:placetype":"venue"
},
  "geometry": {"coordinates":[-0.774699986,51.5694656372],"type":"Point"}
}