{
  "type": "Feature",
  "properties": {
    "iso:country":"GB",
    "sg:address":"Portrack Grange Rd",
    "sg:city":"Stockton On Tees",
    "sg:classifiers":[
        {
            "category":"Wholesale",
            "subcategory":"Home Furnishings",
            "type":"Manufacturing & Wholesale Goods"
        }
    ],
    "sg:phone":"+44 1642 605292",
    "sg:postcode":"TS18 2PF",
    "sg:province":"Durham",
    "sg:tags":[
        "wsale",
        "rug",
        "carpet"
    ],
    "wof:name":"B & G Wholesale Carpets",
    "wof:placetype":"venue"
},
  "geometry": {"coordinates":[-1.2846289873,54.5734291077],"type":"Point"}
}