{
  "type": "Feature",
  "properties": {
    "iso:country":"GB",
    "sg:address":"Lowfield Farm, Oaksey",
    "sg:city":"Malmesbury",
    "sg:classifiers":[
        {
            "category":"Bars & Pubs",
            "subcategory":"Hookah Bar",
            "type":"Food & Drink"
        },
        {
            "category":"Sports & Exercise",
            "subcategory":"Golf",
            "type":"Entertainment"
        }
    ],
    "sg:phone":"+44 1666 577995",
    "sg:postcode":"SN16 9SB",
    "sg:province":"Wiltshire",
    "sg:tags":[
        "club",
        "course",
        "self",
        "holiday",
        "catering"
    ],
    "wof:name":"Oaksey Park Golf & Leisure Ltd.",
    "wof:placetype":"venue"
},
  "geometry": {"coordinates":[-2.097419,51.582245],"type":"Point"}
}