{
  "type": "Feature",
  "properties": {
    "addr:full":"24 Slitting Mill Road Rugeley Staffordshire WS15 2UN",
    "addr:housenumber":"24",
    "addr:postcode":"ws15 2un",
    "addr:street":"Slitting Mill Road",
    "iso:country":"GB",
    "sg:address":"24 Slitting Mill Road",
    "sg:city":"Rugeley",
    "sg:classifiers":[
        {
            "category":"Wholesale",
            "subcategory":"Office Equipment",
            "type":"Manufacturing & Wholesale Goods"
        },
        {
            "category":"Building & Trades",
            "subcategory":"Landscaping Services",
            "type":"Services"
        }
    ],
    "sg:phone":"+44 1889 576633",
    "sg:postcode":"WS15 2UN",
    "sg:province":"Staffordshire",
    "sg:tags":[
        "horticultural",
        "consultant",
        "register",
        "cash",
        "accessory"
    ],
    "wof:name":"Lees Cash Registers",
    "wof:placetype":"venue"
},
  "geometry": {"coordinates":[-1.958558,52.753349],"type":"Point"}
}