{
  "type": "Feature",
  "properties": {
    "addr:full":"111 High Street, Clay Cross Chesterfield Derbyshire S45 9DZ",
    "addr:housenumber":"111",
    "addr:postcode":"s45 9dz",
    "addr:street":"High Street",
    "iso:country":"GB",
    "sg:address":"111 High Street, Clay Cross",
    "sg:city":"Chesterfield",
    "sg:classifiers":[
        {
            "category":"Wholesale",
            "subcategory":"Toys & Hobbies",
            "type":"Manufacturing & Wholesale Goods"
        },
        {
            "category":"Shopping",
            "subcategory":"Florist",
            "type":"Retail Goods"
        }
    ],
    "sg:phone":"+44 1246 861494",
    "sg:postcode":"S45 9DZ",
    "sg:province":"Derbyshire",
    "sg:tags":[
        "balloon",
        "novelty"
    ],
    "wof:name":"Bluebells & Balloons",
    "wof:placetype":"venue"
},
  "geometry": {"coordinates":[-1.4159280062,53.1657104492],"type":"Point"}
}