{
  "type": "Feature",
  "properties": {
    "addr:full":"Jackson Chambers, Jackson Road Clacton-on-sea Essex CO15 1JA",
    "addr:postcode":"co15 1ja",
    "addr:street":"Jackson Road",
    "iso:country":"GB",
    "sg:address":"Jackson Chambers, Jackson Road",
    "sg:city":"Clacton-on-sea",
    "sg:classifiers":[
        {
            "category":"Health Services",
            "subcategory":"Dentist",
            "type":"Services"
        }
    ],
    "sg:postcode":"CO15 1JA",
    "sg:province":"Essex",
    "sg:tags":[
        "technician",
        "dental"
    ],
    "wof:name":"S M Thomas",
    "wof:placetype":"venue"
},
  "geometry": {"coordinates":[1.1532700062,51.8018264771],"type":"Point"}
}