{
  "type": "Feature",
  "properties": {
    "addr:full":"9 The Walk Rochdale Lancashire OL16 1EP",
    "addr:housenumber":"9",
    "addr:postcode":"ol16 1ep",
    "addr:street":"The Walk",
    "iso:country":"GB",
    "sg:address":"9 The Walk",
    "sg:city":"Rochdale",
    "sg:classifiers":[
        {
            "category":"Organizations",
            "subcategory":"Non-profit Organization",
            "type":"Services"
        }
    ],
    "sg:phone":"+44 1706 354001",
    "sg:postcode":"OL16 1EP",
    "sg:province":"Lancashire",
    "sg:tags":[
        "charitable",
        "organisation",
        "voluntary",
        "charity"
    ],
    "wof:name":"British Heart Foundation",
    "wof:placetype":"venue"
},
  "geometry": {"coordinates":[-2.1577169895,53.6171875],"type":"Point"}
}