{
  "type": "Feature",
  "properties": {
    "iso:country":"GB",
    "sg:address":"9 Hatford Road",
    "sg:city":"Reading",
    "sg:classifiers":[
        {
            "category":"Building & Trades",
            "subcategory":"Plumbing",
            "type":"Services"
        }
    ],
    "sg:phone":"+44 118 959 9322",
    "sg:postcode":"RG30 3JA",
    "sg:province":"Berkshire",
    "sg:tags":[
        "heating"
    ],
    "wof:name":"Abra Plumbing",
    "wof:placetype":"venue"
},
  "geometry": {"coordinates":[-1.015354,51.440155],"type":"Point"}
}