{
  "type": "Feature",
  "properties": {
    "iso:country":"GB",
    "sg:address":"Room 112 Hulme Adult Education, Cntr, Stretford Road",
    "sg:city":"Manchester",
    "sg:classifiers":[
        {
            "category":"Shopping",
            "subcategory":"Books",
            "type":"Retail Goods"
        }
    ],
    "sg:phone":"+44 161 226 7152",
    "sg:postcode":"M15 5FQ",
    "sg:province":"Cheshire",
    "wof:name":"Gatehouse Books Ltd.",
    "wof:placetype":"venue"
},
  "geometry": {"coordinates":[-2.25066,53.466942],"type":"Point"}
}