{
  "type": "Feature",
  "properties": {
    "addr:full":"Snowdrop Lane Haverfordwest Pembrokeshire SA61 1JB",
    "addr:postcode":"sa61 1jb",
    "addr:street":"Snowdrop Lane",
    "iso:country":"GB",
    "sg:address":"Snowdrop Lane",
    "sg:city":"Haverfordwest",
    "sg:classifiers":[
        {
            "category":"Manufacturing",
            "subcategory":"Furniture",
            "type":"Manufacturing & Wholesale Goods"
        },
        {
            "category":"Government",
            "subcategory":"Office",
            "type":"Public Place"
        }
    ],
    "sg:phone":"+44 1437 763650",
    "sg:postcode":"SA61 1JB",
    "sg:province":"Pembrokeshire",
    "sg:tags":[
        "mnfr",
        "local",
        "garden",
        "patio"
    ],
    "wof:name":"Norman Industries",
    "wof:placetype":"venue"
},
  "geometry": {"coordinates":[-4.9858589172,51.7981147766],"type":"Point"}
}