{
  "type": "Feature",
  "properties": {
    "addr:full":"Aberdeen Business Centre, Willowbank Road Aberdeen Aberdeen City AB11 6YG",
    "addr:postcode":"ab11 6yg",
    "addr:street":"Willowbank Road",
    "iso:country":"GB",
    "sg:address":"Aberdeen Business Centre, Willowbank Road",
    "sg:city":"Aberdeen",
    "sg:classifiers":[
        {
            "category":"Shopping",
            "subcategory":"Stationery & Office Supplies",
            "type":"Retail Goods"
        },
        {
            "category":"Professional",
            "subcategory":"Research",
            "type":"Services"
        }
    ],
    "sg:postcode":"AB11 6YG",
    "sg:province":"Aberdeen City",
    "sg:tags":[
        "item",
        "organisation",
        "market",
        "promotional"
    ],
    "wof:name":"3 G PROMOTIONS",
    "wof:placetype":"venue"
},
  "geometry": {"coordinates":[-2.1094799042,57.139919281],"type":"Point"}
}