{
  "type": "Feature",
  "properties": {
    "addr:full":"Unit 12 Airside Business Park, Kirkhill Indust Est Aberdeen Aberdeen City AB21 0ES",
    "addr:housenumber":"unit 12",
    "addr:postcode":"ab21 0es",
    "addr:street":"Airside Business Park;Indust",
    "iso:country":"GB",
    "sg:address":"Unit 12 Airside Business Park, Kirkhill Indust Est",
    "sg:city":"Aberdeen",
    "sg:classifiers":[
        {
            "category":"Parking",
            "type":"Transportation"
        }
    ],
    "sg:phone":"+44 1224 775887",
    "sg:postcode":"AB21 0ES",
    "sg:province":"Aberdeen City",
    "sg:tags":[
        "car",
        "valet"
    ],
    "wof:name":"Aberdeen Steam Clean",
    "wof:placetype":"venue"
},
  "geometry": {"coordinates":[-2.2500491142,57.2231216431],"type":"Point"}
}