{
  "type": "Feature",
  "properties": {
    "addr:full":"Ivy Cottage, 300 Southwell Road East Mansfield Nottinghamshire NG21 0AA",
    "addr:housenumber":"300",
    "addr:postcode":"ng21 0aa",
    "addr:street":"Southwell Road East",
    "iso:country":"GB",
    "sg:address":"Ivy Cottage, 300 Southwell Road East",
    "sg:city":"Mansfield",
    "sg:classifiers":[
        {
            "category":"Shopping",
            "subcategory":"Pharmacy",
            "type":"Retail Goods"
        }
    ],
    "sg:phone":"+44 1623 795250",
    "sg:postcode":"NG21 0AA",
    "sg:province":"Nottinghamshire",
    "sg:tags":[
        "pharmacist",
        "chemist"
    ],
    "wof:name":"Co-op Pharmacy",
    "wof:placetype":"venue"
},
  "geometry": {"coordinates":[-1.12729,53.122261],"type":"Point"}
}