{
  "type": "Feature",
  "properties": {
    "iso:country":"GB",
    "sg:address":"130 Sandwell St",
    "sg:city":"Walsall",
    "sg:classifiers":[
        {
            "category":"Health Services",
            "subcategory":"Doctor",
            "type":"Services"
        }
    ],
    "sg:phone":"+44 1922 634598",
    "sg:postcode":"WS1 3EG",
    "sg:province":"West Midlands",
    "sg:tags":[
        "practitioners"
    ],
    "wof:name":"Thawait, S L",
    "wof:placetype":"venue"
},
  "geometry": {"coordinates":[-1.978187,52.576416],"type":"Point"}
}