{
  "type": "Feature",
  "properties": {
    "addr:full":"4 Lucius Street Torquay Devon TQ2 5UN",
    "addr:housenumber":"4",
    "addr:postcode":"tq2 5un",
    "addr:street":"Lucius Street",
    "iso:country":"GB",
    "sg:address":"4 Lucius Street",
    "sg:city":"Torquay",
    "sg:classifiers":[
        {
            "category":"Cafe",
            "type":"Food & Drink"
        }
    ],
    "sg:postcode":"TQ2 5UN",
    "sg:province":"Devon",
    "sg:tags":[
        "tea",
        "room"
    ],
    "wof:name":"Mortimor,Barbara,",
    "wof:placetype":"venue"
},
  "geometry": {"coordinates":[-3.5377149582,50.4677963257],"type":"Point"}
}