{
  "type": "Feature",
  "properties": {
    "iso:country":"GB",
    "sg:address":"Park Road, Earlsheaton",
    "sg:city":"Dewsbury",
    "sg:classifiers":[
        {
            "category":"Farming",
            "subcategory":"Nursery",
            "type":"Manufacturing & Wholesale Goods"
        }
    ],
    "sg:phone":"+44 1924 457177",
    "sg:postcode":"WF12 8BE",
    "sg:province":"West Yorkshire",
    "sg:tags":[
        "creche"
    ],
    "wof:name":"Kiddicare Private Day Nursery",
    "wof:placetype":"venue"
},
  "geometry": {"coordinates":[-1.614853,53.68644],"type":"Point"}
}