{
  "type": "Feature",
  "properties": {
    "iso:country":"GB",
    "sg:address":"309 Greenford Avenue, Hanwell",
    "sg:city":"London",
    "sg:classifiers":[
        {
            "category":"Shopping",
            "subcategory":"Gifts & Souvenirs",
            "type":"Retail Goods"
        }
    ],
    "sg:postcode":"W7 1JH",
    "sg:province":"Greater London",
    "sg:tags":[
        "poster",
        "card"
    ],
    "wof:name":"The Card Shop",
    "wof:placetype":"venue"
},
  "geometry": {"coordinates":[-0.339779,51.522133],"type":"Point"}
}