{
  "type": "Feature",
  "properties": {
    "addr:full":"8a-10a Kilburn Bridge London Greater London NW6 6HT",
    "addr:housenumber":"8a-10a",
    "addr:postcode":"nw6 6ht",
    "addr:street":"Kilburn Bridge",
    "iso:country":"GB",
    "sg:address":"8a-10a Kilburn Bridge",
    "sg:city":"London",
    "sg:classifiers":[
        {
            "category":"Professional",
            "subcategory":"Lawyer & Legal Services",
            "type":"Services"
        }
    ],
    "sg:phone":"+44 20 7372 7529",
    "sg:postcode":"NW6 6HT",
    "sg:province":"Greater London",
    "sg:tags":[
        "solicitor"
    ],
    "wof:name":"Karina Leapman & Co",
    "wof:placetype":"venue"
},
  "geometry": {"coordinates":[-0.192652,51.537151],"type":"Point"}
}