{
  "type": "Feature",
  "properties": {
    "addr:full":"18 Southgate Bath Bath and North East Somerset BA1 1TD",
    "addr:housenumber":"18",
    "addr:postcode":"ba1 1td",
    "addr:street":"Southgate Bath",
    "iso:country":"GB",
    "sg:address":"18 Southgate",
    "sg:city":"Bath",
    "sg:classifiers":[
        {
            "category":"Shopping",
            "subcategory":"Bicycles & Sporting Goods",
            "type":"Retail Goods"
        },
        {
            "category":"Sports & Exercise",
            "subcategory":"Sports Center",
            "type":"Entertainment"
        }
    ],
    "sg:phone":"+44 1225 316491",
    "sg:postcode":"BA1 1TD",
    "sg:province":"Bath and North East Somerset",
    "sg:tags":[
        "shop",
        "sale"
    ],
    "wof:name":"Michael J W Ashley",
    "wof:placetype":"venue"
},
  "geometry": {"coordinates":[-2.3597989082,51.3783187866],"type":"Point"}
}