{
  "type": "Feature",
  "properties": {
    "addr:full":"Manthorpe Hall, Low Road, Manthorpe Grantham Lincolnshire NG31 8NQ",
    "addr:postcode":"ng31 8nq",
    "addr:street":"Low Road",
    "iso:country":"GB",
    "sg:address":"Manthorpe Hall, Low Road, Manthorpe",
    "sg:city":"Grantham",
    "sg:classifiers":[
        {
            "category":"Education",
            "subcategory":"Preschool",
            "type":"Public Place"
        }
    ],
    "sg:phone":"+44 1476 573893",
    "sg:postcode":"NG31 8NQ",
    "sg:province":"Lincolnshire",
    "sg:tags":[
        "pre-school",
        "playgroups"
    ],
    "wof:name":"Manthorpe Play Group",
    "wof:placetype":"venue"
},
  "geometry": {"coordinates":[-0.6324750185,52.9295845032],"type":"Point"}
}