{
  "type": "Feature",
  "properties": {
    "iso:country":"GB",
    "sg:address":"73 Lower Road",
    "sg:city":"Ashford",
    "sg:classifiers":[
        {
            "category":"Building & Trades",
            "subcategory":"Construction",
            "type":"Services"
        }
    ],
    "sg:phone":"+44 1233 860533",
    "sg:postcode":"TN26 3SG",
    "sg:province":"Kent",
    "sg:tags":[
        "builder"
    ],
    "wof:name":"D Blake",
    "wof:placetype":"venue"
},
  "geometry": {"coordinates":[0.7767090201,51.0748710632],"type":"Point"}
}