{
  "type": "Feature",
  "properties": {
    "addr:full":"200 Glasgow Road, Whins Of Milton Stirling Falkirk FK7 0LE",
    "addr:housenumber":"200",
    "addr:postcode":"fk7 0le",
    "addr:street":"Glasgow Road",
    "iso:country":"GB",
    "sg:address":"200 Glasgow Road, Whins Of Milton",
    "sg:city":"Stirling",
    "sg:classifiers":[
        {
            "category":"Real Estate",
            "subcategory":"Developer",
            "type":"Services"
        }
    ],
    "sg:phone":"+44 1786 811811",
    "sg:postcode":"FK7 0LE",
    "sg:province":"Falkirk",
    "sg:tags":[
        "property"
    ],
    "wof:name":"Ogilivie Homes Ltd.",
    "wof:placetype":"venue"
},
  "geometry": {"coordinates":[-3.9310998917,56.0886917114],"type":"Point"}
}