{
  "type": "Feature",
  "properties": {
    "iso:country":"GB",
    "sg:address":"14 Back Knowl Road",
    "sg:city":"Mirfield",
    "sg:classifiers":[
        {
            "category":"Autos & Motor Vehicles",
            "subcategory":"Auto Supplies",
            "type":"Retail Goods"
        },
        {
            "category":"Shopping",
            "type":"Retail Goods"
        }
    ],
    "sg:phone":"+44 1924 497664",
    "sg:postcode":"WF14 9SA",
    "sg:province":"West Yorkshire",
    "sg:tags":[
        "car",
        "part",
        "accessory"
    ],
    "wof:name":"C Barnes",
    "wof:placetype":"venue"
},
  "geometry": {"coordinates":[-1.699886,53.681229],"type":"Point"}
}