{
  "type": "Feature",
  "properties": {
    "iso:country":"GB",
    "sg:address":"38 Dongola Road",
    "sg:city":"Rochester",
    "sg:classifiers":[
        {
            "category":"Bakery",
            "type":"Food & Drink"
        }
    ],
    "sg:postcode":"ME2 3AX",
    "sg:province":"Kent",
    "sg:tags":[
        "cake",
        "maker"
    ],
    "wof:name":"Icing on the Cake",
    "wof:placetype":"venue"
},
  "geometry": {"coordinates":[0.4933089912,51.4028701782],"type":"Point"}
}