{
  "type": "Feature",
  "properties": {
    "addr:full":"Wood La, North Wheatley Retford Nottinghamshire DN22 9BG",
    "addr:postcode":"dn22 9bg",
    "addr:street":"Wood La North",
    "iso:country":"GB",
    "sg:address":"Wood La, North Wheatley",
    "sg:city":"Retford",
    "sg:classifiers":[
        {
            "category":"Shopping",
            "subcategory":"Department Store",
            "type":"Retail Goods"
        },
        {
            "category":"Home & Garden",
            "subcategory":"Garden Supply",
            "type":"Retail Goods"
        }
    ],
    "sg:postcode":"DN22 9BG",
    "sg:province":"Nottinghamshire",
    "sg:tags":[
        "nursery",
        "centre"
    ],
    "wof:name":"Burnett,A,",
    "wof:placetype":"venue"
},
  "geometry": {"coordinates":[-0.859159,53.371616],"type":"Point"}
}