{
  "type": "Feature",
  "properties": {
    "iso:country":"GB",
    "sg:address":"The Whitehouse 51 Marlowes",
    "sg:city":"Hemel Hempstead",
    "sg:classifiers":[
        {
            "category":"Social Services",
            "subcategory":"Retirement Home",
            "type":"Services"
        }
    ],
    "sg:phone":"+44 1442 219696",
    "sg:postcode":"HP1 1LD",
    "sg:province":"Hertfordshire",
    "sg:tags":[
        "care"
    ],
    "wof:name":"Primrose Care Ltd",
    "wof:placetype":"venue"
},
  "geometry": {"coordinates":[-0.475084,51.749001],"type":"Point"}
}