{
  "type": "Feature",
  "properties": {
    "iso:country":"GB",
    "sg:address":"612 Beverley Drive, Bentilee",
    "sg:city":"Stoke-on-trent",
    "sg:classifiers":[
        {
            "category":"Retail",
            "subcategory":"Driving School",
            "type":"Services"
        }
    ],
    "sg:phone":"+44 1782 317816",
    "sg:postcode":"ST2 0RE",
    "sg:province":"Staffordshire",
    "wof:name":"Ace Driving School",
    "wof:placetype":"venue"
},
  "geometry": {"coordinates":[-2.119768,53.006859],"type":"Point"}
}