{
  "type": "Feature",
  "properties": {
    "iso:country":"GB",
    "sg:address":"3 Slade Hill, Hampton Magna",
    "sg:city":"Warwick",
    "sg:classifiers":[
        {
            "category":"Shopping",
            "subcategory":"Florist",
            "type":"Retail Goods"
        }
    ],
    "sg:postcode":"CV35 8SA",
    "sg:province":"Warwickshire",
    "wof:name":"Smith,Elaine,",
    "wof:placetype":"venue"
},
  "geometry": {"coordinates":[-1.62272,52.28326],"type":"Point"}
}