{
  "type": "Feature",
  "properties": {
    "addr:full":"288 Brook Street, Broughty Ferry Dundee Angus DD5 2AP",
    "addr:housenumber":"288",
    "addr:postcode":"dd5 2ap",
    "addr:street":"Brook Street",
    "iso:country":"GB",
    "sg:address":"288 Brook Street, Broughty Ferry",
    "sg:city":"Dundee",
    "sg:classifiers":[
        {
            "category":"Banks & Credit Unions",
            "subcategory":"Bank",
            "type":"Services"
        }
    ],
    "sg:phone":"+44 1382 739466",
    "sg:postcode":"DD5 2AP",
    "sg:province":"Angus",
    "sg:tags":[
        "financial",
        "institution"
    ],
    "wof:name":"The Royal Bank of Scotland plc",
    "wof:placetype":"venue"
},
  "geometry": {"coordinates":[-2.87226,56.466782],"type":"Point"}
}