{
  "type": "Feature",
  "properties": {
    "addr:full":"Rowson St Wallasey Merseyside L45 5AR",
    "addr:postcode":"l45 5ar",
    "addr:street":"St",
    "iso:country":"GB",
    "sg:address":"Rowson St",
    "sg:city":"Wallasey",
    "sg:classifiers":[
        {
            "category":"Bars & Pubs",
            "type":"Food & Drink"
        }
    ],
    "sg:phone":"+44 151 691 1204",
    "sg:postcode":"L45 5AR",
    "sg:province":"Merseyside",
    "sg:tags":[
        "pubs",
        "inn"
    ],
    "wof:name":"Travellers Rest The",
    "wof:placetype":"venue"
},
  "geometry": {"coordinates":[-3.044209,53.438854],"type":"Point"}
}