{
  "type": "Feature",
  "properties": {
    "addr:full":"Tayside Service Area, Smeaton Road Dundee Dundee City DD2 4UT",
    "addr:postcode":"dd2 4ut",
    "addr:street":"Smeaton Road",
    "iso:country":"GB",
    "sg:address":"Tayside Service Area, Smeaton Road",
    "sg:city":"Dundee",
    "sg:classifiers":[
        {
            "category":"Freight",
            "type":"Transportation"
        },
        {
            "category":"Restaurant",
            "type":"Food & Drink"
        }
    ],
    "sg:phone":"+44 1382 621941",
    "sg:postcode":"DD2 4UT",
    "sg:province":"Dundee City",
    "sg:tags":[
        "haulage",
        "-",
        "road",
        "english"
    ],
    "wof:name":"Tayside Truck Stop",
    "wof:placetype":"venue"
},
  "geometry": {"coordinates":[-3.045320034,56.4779281616],"type":"Point"}
}