{
  "type": "Feature",
  "properties": {
    "iso:country":"GB",
    "sg:address":"The Old Station, Charfield",
    "sg:city":"Wotton-under-edge",
    "sg:classifiers":[
        {
            "category":"Autos & Motor Vehicles",
            "subcategory":"Automobile Sales",
            "type":"Retail Goods"
        }
    ],
    "sg:phone":"+44 1453 844131",
    "sg:postcode":"GL12 8SR",
    "sg:province":"Gloucestershire",
    "sg:tags":[
        "car"
    ],
    "wof:name":"M J Fews Ltd.",
    "wof:placetype":"venue"
},
  "geometry": {"coordinates":[-2.39805,51.62949],"type":"Point"}
}