{
  "type": "Feature",
  "properties": {
    "addr:full":"Milngavie Business Centre, 17 Station Rd, Milngavie Glasgow East Dunbartonshire G62 8PG",
    "addr:housenumber":"17",
    "addr:postcode":"g62 8pg",
    "addr:street":"Station Rd",
    "iso:country":"GB",
    "sg:address":"Milngavie Business Centre, 17 Station Rd, Milngavie",
    "sg:city":"Glasgow",
    "sg:classifiers":[
        {
            "category":"Banks & Credit Unions",
            "subcategory":"Bureau De Change",
            "type":"Services"
        }
    ],
    "sg:postcode":"G62 8PG",
    "sg:province":"East Dunbartonshire",
    "sg:tags":[
        "town",
        "consultant",
        "planning"
    ],
    "wof:name":"Kennedy,Gwyn,",
    "wof:placetype":"venue"
},
  "geometry": {"coordinates":[-4.31655,55.941959],"type":"Point"}
}