{
  "type": "Feature",
  "properties": {
    "iso:country":"GB",
    "sg:address":"244 Nuneaton Road, Bulkington",
    "sg:city":"Bedworth",
    "sg:classifiers":[
        {
            "category":"Military Area",
            "subcategory":"Air Force Base",
            "type":"Public Place"
        }
    ],
    "sg:postcode":"CV12 9RZ",
    "sg:province":"Warwickshire",
    "sg:tags":[
        "taxi",
        "hire",
        "private"
    ],
    "wof:name":"Kens Taxis",
    "wof:placetype":"venue"
},
  "geometry": {"coordinates":[-1.44672,52.49268],"type":"Point"}
}