{
  "type": "Feature",
  "properties": {
    "addr:full":"1 Saxon Place Cheddar Somerset BS27 3AF",
    "addr:housenumber":"1",
    "addr:postcode":"bs27 3af",
    "addr:street":"Saxon Place",
    "iso:country":"GB",
    "sg:address":"1 Saxon Place",
    "sg:city":"Cheddar",
    "sg:classifiers":[
        {
            "category":"Home & Garden",
            "subcategory":"Hardware",
            "type":"Retail Goods"
        }
    ],
    "sg:phone":"+44 1934 742326",
    "sg:postcode":"BS27 3AF",
    "sg:province":"Somerset",
    "wof:name":"E E Lane & Sons Ltd.",
    "wof:placetype":"venue"
},
  "geometry": {"coordinates":[-2.7773189545,51.2695732117],"type":"Point"}
}