{
  "type": "Feature",
  "properties": {
    "addr:full":"110 High Street South London Greater London E6 3RL",
    "addr:housenumber":"110",
    "addr:postcode":"e6 3rl",
    "addr:street":"High Street South",
    "iso:country":"GB",
    "sg:address":"110 High Street South",
    "sg:city":"London",
    "sg:classifiers":[
        {
            "category":"Shopping",
            "subcategory":"Department Store",
            "type":"Retail Goods"
        }
    ],
    "sg:postcode":"E6 3RL",
    "sg:province":"Greater London",
    "wof:name":"Euro Food Store",
    "wof:placetype":"venue"
},
  "geometry": {"coordinates":[0.0561559983,51.5267677307],"type":"Point"}
}