{
  "type": "Feature",
  "properties": {
    "iso:country":"GB",
    "sg:address":"Aylesford Rd, Handsworth",
    "sg:city":"Birmingham",
    "sg:classifiers":[
        {
            "category":"Place Of Worship",
            "type":"Public Place"
        },
        {
            "category":"Organizations",
            "subcategory":"Non-profit Organization",
            "type":"Services"
        }
    ],
    "sg:phone":"+44 121 554 0555",
    "sg:postcode":"B21 8DG",
    "sg:province":"West Midlands",
    "sg:tags":[
        "charitable",
        "organisation",
        "charity"
    ],
    "wof:name":"World Vision for Christ Church",
    "wof:placetype":"venue"
},
  "geometry": {"coordinates":[-1.9431289434,52.5121803284],"type":"Point"}
}