{
  "type": "Feature",
  "properties": {
    "addr:full":"21 Midland Road Derby Derbyshire DE1 2SL",
    "addr:housenumber":"21",
    "addr:postcode":"de1 2sl",
    "addr:street":"Midland Road",
    "iso:country":"GB",
    "sg:address":"21 Midland Road",
    "sg:city":"Derby",
    "sg:classifiers":[
        {
            "category":"Restaurant",
            "type":"Food & Drink"
        }
    ],
    "sg:phone":"+44 1332 201700",
    "sg:postcode":"DE1 2SL",
    "sg:province":"Derbyshire",
    "sg:tags":[
        "-",
        "italian"
    ],
    "sg:website":"http://www.antibo.co.uk",
    "wof:name":"Antibo Restaurant",
    "wof:placetype":"venue"
},
  "geometry": {"coordinates":[-1.4648890495,52.9157028198],"type":"Point"}
}