{
  "type": "Feature",
  "properties": {
    "iso:country":"GB",
    "sg:address":"9 Chestnut Rise, Bushey",
    "sg:city":"Watford",
    "sg:classifiers":[
        {
            "category":"Professional",
            "subcategory":"Computer Services",
            "type":"Services"
        }
    ],
    "sg:postcode":"WD2 1AB",
    "sg:province":"Hertfordshire",
    "sg:tags":[
        "system",
        "software"
    ],
    "wof:name":"Soft Options (Europe) Ltd",
    "wof:placetype":"venue"
},
  "geometry": {"coordinates":[-0.3630700111,51.6443405151],"type":"Point"}
}