{
  "type": "Feature",
  "properties": {
    "addr:full":"28 Larkswood Court, The Avenue Chingford Greater London E4 9SF",
    "addr:housenumber":"28",
    "addr:postcode":"e4 9sf",
    "addr:street":"Larkswood Court The Avenue",
    "iso:country":"GB",
    "sg:address":"28 Larkswood Court, The Avenue",
    "sg:city":"Chingford",
    "sg:classifiers":[
        {
            "category":"Banks & Credit Unions",
            "subcategory":"Bank",
            "type":"Services"
        }
    ],
    "sg:phone":"+44 20 8925 4459",
    "sg:postcode":"E4 9SF",
    "sg:province":"Greater London",
    "sg:tags":[
        "broker",
        "mortgage"
    ],
    "wof:name":"G.D.R Consultants",
    "wof:placetype":"venue"
},
  "geometry": {"coordinates":[-0.0157019999,51.6149024963],"type":"Point"}
}