{
  "type": "Feature",
  "properties": {
    "addr:full":"174 Chestnut Gro Mitcham Greater London CR4 1QD",
    "addr:housenumber":"174",
    "addr:postcode":"cr4 1qd",
    "addr:street":"Chestnut Gro",
    "iso:country":"GB",
    "sg:address":"174 Chestnut Gro",
    "sg:city":"Mitcham",
    "sg:classifiers":[
        {
            "category":"Food & Beverages",
            "subcategory":"Fruits & Vegetables",
            "type":"Retail Goods"
        }
    ],
    "sg:phone":"+44 20 8764 6002",
    "sg:postcode":"CR4 1QD",
    "sg:province":"Greater London",
    "sg:tags":[
        "greengrocer"
    ],
    "wof:name":"Professionals Greengrocers",
    "wof:placetype":"venue"
},
  "geometry": {"coordinates":[-0.133203,51.399925],"type":"Point"}
}