{
  "type": "Feature",
  "properties": {
    "iso:country":"GB",
    "sg:address":"97-99 Kings Road",
    "sg:city":"London",
    "sg:classifiers":[
        {
            "category":"Shopping",
            "subcategory":"Clothing, Apparel, & Fashions",
            "type":"Retail Goods"
        }
    ],
    "sg:phone":"+44 20 7823 3014",
    "sg:postcode":"SW3 4PA",
    "sg:province":"Greater London",
    "sg:tags":[
        "menswear"
    ],
    "wof:name":"Woodhouse",
    "wof:placetype":"venue"
},
  "geometry": {"coordinates":[-0.165108,51.488789],"type":"Point"}
}