{
  "type": "Feature",
  "properties": {
    "addr:full":"150 Cookham Road Maidenhead Berkshire SL6 7HR",
    "addr:housenumber":"150",
    "addr:postcode":"sl6 7hr",
    "addr:street":"Cookham Road",
    "iso:country":"GB",
    "sg:address":"150 Cookham Road",
    "sg:city":"Maidenhead",
    "sg:classifiers":[
        {
            "category":"Food & Beverages",
            "subcategory":"Liquor & Beverages",
            "type":"Retail Goods"
        }
    ],
    "sg:phone":"+44 1628 620379",
    "sg:postcode":"SL6 7HR",
    "sg:province":"Berkshire",
    "sg:tags":[
        "beer",
        "spirit",
        "wines"
    ],
    "wof:name":"Thresher Wine Shop",
    "wof:placetype":"venue"
},
  "geometry": {"coordinates":[-0.7250429988,51.5328865051],"type":"Point"}
}