{
  "type": "Feature",
  "properties": {
    "iso:country":"GB",
    "sg:address":"140-143 Milton Road",
    "sg:city":"Gravesend",
    "sg:classifiers":[
        {
            "category":"Home & Garden",
            "subcategory":"Furniture",
            "type":"Retail Goods"
        }
    ],
    "sg:phone":"+44 1474 569076",
    "sg:postcode":"DA12 2RH",
    "sg:province":"Kent",
    "wof:name":"Courts Plc",
    "wof:placetype":"venue"
},
  "geometry": {"coordinates":[0.373974,51.441357],"type":"Point"}
}