{
  "type": "Feature",
  "properties": {
    "addr:full":"Cwm Cyrnach Uchaf Farm, Glais Swansea Neath Port Talbot SA7 9HR",
    "addr:postcode":"sa7 9hr",
    "addr:street":"Glais",
    "iso:country":"GB",
    "sg:address":"Cwm Cyrnach Uchaf Farm, Glais",
    "sg:city":"Swansea",
    "sg:classifiers":[
        {
            "category":"Farming",
            "subcategory":"Livestock Farm",
            "type":"Manufacturing & Wholesale Goods"
        }
    ],
    "sg:phone":"+44 1792 844637",
    "sg:postcode":"SA7 9HR",
    "sg:province":"Neath Port Talbot",
    "sg:tags":[
        "others"
    ],
    "wof:name":"G Irranca",
    "wof:placetype":"venue"
},
  "geometry": {"coordinates":[-3.8773589134,51.6888237],"type":"Point"}
}