{
  "type": "Feature",
  "properties": {
    "iso:country":"GB",
    "sg:address":"8 Kestrel Close, Lake",
    "sg:city":"Sandown",
    "sg:classifiers":[
        {
            "category":"Bus Charters",
            "type":"Transportation"
        }
    ],
    "sg:phone":"+44 1983 405145",
    "sg:postcode":"PO36 9QL",
    "sg:province":"Isle of Wight",
    "sg:tags":[
        "hire",
        "coach"
    ],
    "wof:name":"Wightways Coaches Ltd.",
    "wof:placetype":"venue"
},
  "geometry": {"coordinates":[-1.1764199734,50.6435928345],"type":"Point"}
}