{
  "type": "Feature",
  "properties": {
    "addr:full":"Pine Gro Finsbury Park Greater London N4 3LL",
    "addr:postcode":"n4 3ll",
    "addr:street":"Gro Finsbury Park",
    "iso:country":"GB",
    "sg:address":"Pine Gro",
    "sg:city":"Finsbury Park",
    "sg:classifiers":[
        {
            "category":"Place Of Worship",
            "type":"Public Place"
        }
    ],
    "sg:phone":"+44 20 8348 0445",
    "sg:postcode":"N4 3LL",
    "sg:province":"Greater London",
    "wof:name":"Tollington Park Baptist Church",
    "wof:placetype":"venue"
},
  "geometry": {"coordinates":[-0.1186740026,51.5645942688],"type":"Point"}
}