{
  "type": "Feature",
  "properties": {
    "addr:full":"Church Street, Llandybie Ammanford Carmarthenshire SA18 3HZ",
    "addr:postcode":"sa18 3hz",
    "addr:street":"Church Street",
    "iso:country":"GB",
    "sg:address":"Church Street, Llandybie",
    "sg:city":"Ammanford",
    "sg:classifiers":[
        {
            "category":"Bars & Pubs",
            "type":"Food & Drink"
        }
    ],
    "sg:phone":"+44 1269 850272",
    "sg:postcode":"SA18 3HZ",
    "sg:province":"Carmarthenshire",
    "sg:tags":[
        "pubs",
        "inn"
    ],
    "wof:name":"The Ivy Bush Inn",
    "wof:placetype":"venue"
},
  "geometry": {"coordinates":[-3.988945,51.792397],"type":"Point"}
}