{
  "type": "Feature",
  "properties": {
    "iso:country":"GB",
    "sg:address":"63-64 Railway Road",
    "sg:city":"King's Lynn",
    "sg:classifiers":[
        {
            "category":"Personal",
            "subcategory":"Beauty Salon",
            "type":"Services"
        }
    ],
    "sg:phone":"+44 1553 760901",
    "sg:postcode":"PE30 1NE",
    "sg:province":"Norfolk",
    "wof:name":"Everybody",
    "wof:placetype":"venue"
},
  "geometry": {"coordinates":[0.40055,52.75531],"type":"Point"}
}