{
  "type": "Feature",
  "properties": {
    "iso:country":"GB",
    "sg:address":"127-133 Balham Street",
    "sg:city":"London",
    "sg:classifiers":[
        {
            "category":"Home & Garden",
            "subcategory":"Hardware",
            "type":"Retail Goods"
        }
    ],
    "sg:postcode":"E13 8AF",
    "sg:province":"Greater London",
    "sg:tags":[
        "retailer",
        "diy"
    ],
    "wof:name":"Balaam Suppliers",
    "wof:placetype":"venue"
},
  "geometry": {"coordinates":[0.02392,51.526642],"type":"Point"}
}