{
  "type": "Feature",
  "properties": {
    "addr:full":"1 Barnmeadow Crescent, Rishton Blackburn Lancashire BB1 4PF",
    "addr:housenumber":"1",
    "addr:postcode":"bb1 4pf",
    "addr:street":"Barnmeadow Crescent",
    "iso:country":"GB",
    "sg:address":"1 Barnmeadow Crescent, Rishton",
    "sg:city":"Blackburn",
    "sg:classifiers":[
        {
            "category":"Building & Trades",
            "subcategory":"Construction",
            "type":"Services"
        }
    ],
    "sg:phone":"+44 1254 876604",
    "sg:postcode":"BB1 4PF",
    "sg:province":"Lancashire",
    "sg:tags":[
        "joiner",
        "carpenter"
    ],
    "wof:name":"J D Joinery & Building Contractors",
    "wof:placetype":"venue"
},
  "geometry": {"coordinates":[-2.408049,53.768776],"type":"Point"}
}