{
  "type": "Feature",
  "properties": {
    "iso:country":"GB",
    "sg:address":"13 The Square, Halebarns",
    "sg:city":"Altrincham",
    "sg:classifiers":[
        {
            "category":"Banks & Credit Unions",
            "subcategory":"Bank",
            "type":"Services"
        }
    ],
    "sg:postcode":"WA15 8ST",
    "sg:province":"Cheshire",
    "wof:name":"Barclays Bank Plc",
    "wof:placetype":"venue"
},
  "geometry": {"coordinates":[-2.31461,53.36956],"type":"Point"}
}