{
  "type": "Feature",
  "properties": {
    "addr:full":"25 Borough Market Halifax West Yorkshire HX1 1DZ",
    "addr:housenumber":"25",
    "addr:postcode":"hx1 1dz",
    "addr:street":"Borough Market",
    "iso:country":"GB",
    "sg:address":"25 Borough Market",
    "sg:city":"Halifax",
    "sg:classifiers":[
        {
            "category":"Food & Beverages",
            "subcategory":"Meat & Fish",
            "type":"Retail Goods"
        }
    ],
    "sg:postcode":"HX1 1DZ",
    "sg:province":"West Yorkshire",
    "sg:tags":[
        "butcher"
    ],
    "wof:name":"Whitakers",
    "wof:placetype":"venue"
},
  "geometry": {"coordinates":[-1.8598680496,53.72240448],"type":"Point"}
}