{
  "type": "Feature",
  "properties": {
    "addr:full":"8 Golf Place St Andrews Fife KY16 9JA",
    "addr:housenumber":"8",
    "addr:postcode":"ky16 9ja",
    "addr:street":"Golf Place",
    "iso:country":"GB",
    "sg:address":"8 Golf Place",
    "sg:city":"St Andrews",
    "sg:classifiers":[
        {
            "category":"Shopping",
            "subcategory":"Books",
            "type":"Retail Goods"
        },
        {
            "category":"Shopping",
            "subcategory":"News",
            "type":"Retail Goods"
        }
    ],
    "sg:postcode":"KY16 9JA",
    "sg:province":"Fife",
    "sg:tags":[
        "bookseller",
        "newsagent"
    ],
    "wof:name":"Quarto Book Shop",
    "wof:placetype":"venue"
},
  "geometry": {"coordinates":[-2.802567,56.342529],"type":"Point"}
}