{
  "type": "Feature",
  "properties": {
    "iso:country":"GB",
    "sg:address":"Carol House Farm",
    "sg:city":"Swaffham",
    "sg:classifiers":[
        {
            "category":"Farming",
            "subcategory":"Livestock Farm",
            "type":"Manufacturing & Wholesale Goods"
        }
    ],
    "sg:phone":"+44 1760 721450",
    "sg:postcode":"PE37 8DA",
    "sg:province":"Norfolk",
    "sg:tags":[
        "others"
    ],
    "wof:name":"W J Pick & Sons",
    "wof:placetype":"venue"
},
  "geometry": {"coordinates":[0.772255,52.650555],"type":"Point"}
}