{
  "type": "Feature",
  "properties": {
    "addr:full":"The Old Barn, Black Robins Farm Grants La Edenbridge East Sussex TN8 6QP",
    "addr:housenumber":"grants",
    "addr:postcode":"tn8 6qp",
    "addr:street":"Black;La Edenbridge",
    "iso:country":"GB",
    "sg:address":"The Old Barn, Black Robins Farm Grants La",
    "sg:city":"Edenbridge",
    "sg:classifiers":[
        {
            "category":"Professional",
            "subcategory":"Art Services",
            "type":"Services"
        }
    ],
    "sg:postcode":"TN8 6QP",
    "sg:province":"East Sussex",
    "sg:tags":[
        "photographer"
    ],
    "wof:name":"McMillan Studios Ltd",
    "wof:placetype":"venue"
},
  "geometry": {"coordinates":[0.0647469983,51.1973876953],"type":"Point"}
}