{
  "type": "Feature",
  "properties": {
    "iso:country":"GB",
    "sg:address":"11 Landguard Road",
    "sg:city":"Southampton",
    "sg:classifiers":[
        {
            "category":"Travel",
            "subcategory":"Hotels & Motels",
            "type":"Entertainment"
        }
    ],
    "sg:postcode":"SO15 5DL",
    "sg:province":"Hampshire",
    "sg:tags":[
        "house",
        "guest"
    ],
    "wof:name":"Mayfair Guest House",
    "wof:placetype":"venue"
},
  "geometry": {"coordinates":[-1.416684,50.912228],"type":"Point"}
}