{
  "type": "Feature",
  "properties": {
    "iso:country":"GB",
    "sg:address":"473 Beake Avenue",
    "sg:city":"Coventry",
    "sg:classifiers":[
        {
            "category":"Sports & Exercise",
            "subcategory":"Sports Center",
            "type":"Entertainment"
        }
    ],
    "sg:phone":"+44 24 7633 3569",
    "sg:postcode":"CV6 2HT",
    "sg:province":"Warwickshire",
    "sg:tags":[
        "shop",
        "good"
    ],
    "wof:name":"Ernie Over Bowls",
    "wof:placetype":"venue"
},
  "geometry": {"coordinates":[-1.5223519802,52.4426727295],"type":"Point"}
}