{
  "type": "Feature",
  "properties": {
    "addr:full":"15 Auchterderran Road Lochgelly Fife KY5 9DQ",
    "addr:housenumber":"15",
    "addr:postcode":"ky5 9dq",
    "addr:street":"Auchterderran Road",
    "iso:country":"GB",
    "sg:address":"15 Auchterderran Road",
    "sg:city":"Lochgelly",
    "sg:classifiers":[
        {
            "category":"Personal",
            "subcategory":"Beauty Salon",
            "type":"Services"
        },
        {
            "category":"Personal",
            "subcategory":"Barber",
            "type":"Services"
        }
    ],
    "sg:phone":"+44 1592 780386",
    "sg:postcode":"KY5 9DQ",
    "sg:province":"Fife",
    "sg:tags":[
        "unisex",
        "hairdresser"
    ],
    "wof:name":"Shades",
    "wof:placetype":"venue"
},
  "geometry": {"coordinates":[-3.309617,56.129704],"type":"Point"}
}