{
  "type": "Feature",
  "properties": {
    "addr:full":"49 Frodsham Street Chester Cheshire CH1 3JJ",
    "addr:housenumber":"49",
    "addr:postcode":"ch1 3jj",
    "addr:street":"Frodsham Street",
    "iso:country":"GB",
    "sg:address":"49 Frodsham Street",
    "sg:city":"Chester",
    "sg:classifiers":[
        {
            "category":"Health Services",
            "subcategory":"Optometrist",
            "type":"Services"
        }
    ],
    "sg:phone":"+44 1244 311417",
    "sg:postcode":"CH1 3JJ",
    "sg:province":"Cheshire",
    "sg:tags":[
        "optician"
    ],
    "wof:name":"Crown Eye Glass",
    "wof:placetype":"venue"
},
  "geometry": {"coordinates":[-2.8888370991,53.1926307678],"type":"Point"}
}