{
  "type": "Feature",
  "properties": {
    "addr:full":"99 Southfield Road Middlesbrough North Yorkshire TS1 3EZ",
    "addr:housenumber":"99",
    "addr:postcode":"ts1 3ez",
    "addr:street":"Southfield Road",
    "iso:country":"GB",
    "sg:address":"99 Southfield Road",
    "sg:city":"Middlesbrough",
    "sg:classifiers":[
        {
            "category":"Organizations",
            "subcategory":"Membership Organization",
            "type":"Services"
        }
    ],
    "sg:phone":"+44 1642 242164",
    "sg:postcode":"TS1 3EZ",
    "sg:province":"North Yorkshire",
    "sg:tags":[
        "club"
    ],
    "wof:name":"Westgarths Social & Athletic Club",
    "wof:placetype":"venue"
},
  "geometry": {"coordinates":[-1.232722044,54.5703163147],"type":"Point"}
}