{
  "type": "Feature",
  "properties": {
    "addr:full":"The Old Smithy, Tabley Lane, Cottam Preston Lancashire PR4 0LH",
    "addr:postcode":"pr4 0lh",
    "addr:street":"Tabley Lane",
    "iso:country":"GB",
    "sg:address":"The Old Smithy, Tabley Lane, Cottam",
    "sg:city":"Preston",
    "sg:classifiers":[
        {
            "category":"Personal",
            "subcategory":"Hair Removal",
            "type":"Services"
        }
    ],
    "sg:phone":"+44 1772 734187",
    "sg:postcode":"PR4 0LH",
    "sg:province":"Lancashire",
    "sg:tags":[
        "electrolysis"
    ],
    "wof:name":"Cottam Electrical",
    "wof:placetype":"venue"
},
  "geometry": {"coordinates":[-2.7602739334,53.7865753174],"type":"Point"}
}