{
  "type": "Feature",
  "properties": {
    "iso:country":"GB",
    "sg:address":"15 Oakhurst Drive",
    "sg:city":"Wickford",
    "sg:classifiers":[
        {
            "category":"Professional",
            "subcategory":"Engineering",
            "type":"Services"
        }
    ],
    "sg:postcode":"SS12 0NN",
    "sg:province":"Essex",
    "sg:tags":[
        "contractor",
        "electrical",
        "engineer"
    ],
    "wof:name":"E W Turrell",
    "wof:placetype":"venue"
},
  "geometry": {"coordinates":[0.5141019821,51.604385376],"type":"Point"}
}