{
  "type": "Feature",
  "properties": {
    "iso:country":"GB",
    "sg:address":"6 Cameron Street",
    "sg:city":"Stonehaven",
    "sg:classifiers":[
        {
            "category":"Personal",
            "subcategory":"Beauty Salon",
            "type":"Services"
        }
    ],
    "sg:postcode":"AB39 2BL",
    "sg:province":"Aberdeenshire",
    "sg:tags":[
        "unisex",
        "hairdresser"
    ],
    "wof:name":"Chique",
    "wof:placetype":"venue"
},
  "geometry": {"coordinates":[-2.20948,56.963104],"type":"Point"}
}