{
  "type": "Feature",
  "properties": {
    "iso:country":"GB",
    "sg:address":"Unit 8c Daimler Drive, Cowpen Industrial Estate",
    "sg:city":"Billingham",
    "sg:classifiers":[
        {
            "category":"Shopping",
            "subcategory":"Gifts & Souvenirs",
            "type":"Retail Goods"
        }
    ],
    "sg:phone":"+44 1642 560005",
    "sg:postcode":"TS23 4JD",
    "sg:province":"Durham",
    "sg:tags":[
        "diy"
    ],
    "wof:name":"Colton Home Improvement Products",
    "wof:placetype":"venue"
},
  "geometry": {"coordinates":[-1.2604739666,54.6105041504],"type":"Point"}
}