{
  "type": "Feature",
  "properties": {
    "iso:country":"GB",
    "sg:address":"Tumblefield Road, Stansted",
    "sg:city":"Sevenoaks",
    "sg:classifiers":[
        {
            "category":"Bars & Pubs",
            "type":"Food & Drink"
        }
    ],
    "sg:phone":"+44 1732 822355",
    "sg:postcode":"TN15 7PR",
    "sg:province":"Kent",
    "sg:tags":[
        "pubs",
        "inn"
    ],
    "wof:name":"The Black Horse",
    "wof:placetype":"venue"
},
  "geometry": {"coordinates":[0.302486,51.320797],"type":"Point"}
}