{
  "type": "Feature",
  "properties": {
    "iso:country":"GB",
    "sg:address":"144 Ashton Road",
    "sg:city":"Oldham",
    "sg:classifiers":[
        {
            "category":"Food & Beverages",
            "subcategory":"Meat & Fish",
            "type":"Retail Goods"
        }
    ],
    "sg:phone":"+44 161 626 8089",
    "sg:postcode":"OL8 1QT",
    "sg:province":"Lancashire",
    "sg:tags":[
        "chip"
    ],
    "wof:name":"Golden Bowl",
    "wof:placetype":"venue"
},
  "geometry": {"coordinates":[-2.113873,53.531441],"type":"Point"}
}