{
  "type": "Feature",
  "properties": {
    "iso:country":"GB",
    "sg:address":"1 Crabtree Lane",
    "sg:city":"Harpenden",
    "sg:classifiers":[
        {
            "category":"Professional",
            "type":"Services"
        }
    ],
    "sg:postcode":"AL5 5TA",
    "sg:province":"Hertfordshire",
    "sg:tags":[
        "reflexologists"
    ],
    "wof:name":"Lis Horwich",
    "wof:placetype":"venue"
},
  "geometry": {"coordinates":[-0.348609,51.810059],"type":"Point"}
}