{
  "type": "Feature",
  "properties": {
    "addr:full":"1c Court Road Malvern Herefordshire WR14 3BS",
    "addr:housenumber":"1c",
    "addr:postcode":"wr14 3bs",
    "addr:street":"Court Road",
    "iso:country":"GB",
    "sg:address":"1c Court Road",
    "sg:city":"Malvern",
    "sg:classifiers":[
        {
            "category":"Shopping",
            "subcategory":"Photographic Equipment",
            "type":"Retail Goods"
        }
    ],
    "sg:postcode":"WR14 3BS",
    "sg:province":"Herefordshire",
    "sg:tags":[
        "supply"
    ],
    "wof:name":"E P Photographic",
    "wof:placetype":"venue"
},
  "geometry": {"coordinates":[-2.3123619556,52.1082000732],"type":"Point"}
}