{
  "type": "Feature",
  "properties": {
    "iso:country":"GB",
    "sg:address":"P O Box 115",
    "sg:city":"Northwood",
    "sg:classifiers":[
        {
            "category":"Shopping",
            "subcategory":"Clothing, Apparel, & Fashions",
            "type":"Retail Goods"
        },
        {
            "category":"Professional",
            "subcategory":"Business Services",
            "type":"Services"
        }
    ],
    "sg:phone":"+44 1923 824406",
    "sg:postcode":"HA6 3RG",
    "sg:province":"Greater London",
    "sg:tags":[
        "shop",
        "import",
        "export",
        "agent"
    ],
    "wof:name":"SOUSTIEL (U K) LTD",
    "wof:placetype":"venue"
},
  "geometry": {"coordinates":[-0.4129190147,51.6172714233],"type":"Point"}
}