{
  "type": "Feature",
  "properties": {
    "iso:country":"GB",
    "sg:address":"1 Dovecote Close, Barton Seagrave",
    "sg:city":"Kettering",
    "sg:classifiers":[
        {
            "category":"Professional",
            "subcategory":"Business Services",
            "type":"Services"
        }
    ],
    "sg:phone":"+44 1536 513009",
    "sg:postcode":"NN15 6GT",
    "sg:province":"Northamptonshire",
    "sg:tags":[
        "assessment",
        "quality"
    ],
    "wof:name":"Global Certification Ltd.",
    "wof:placetype":"venue"
},
  "geometry": {"coordinates":[-0.722504,52.378204],"type":"Point"}
}