{
  "type": "Feature",
  "properties": {
    "iso:country":"GB",
    "sg:address":"Globe House, Warwick Technology Park",
    "sg:city":"Warwick",
    "sg:classifiers":[
        {
            "category":"Professional",
            "type":"Services"
        }
    ],
    "sg:phone":"+44 1926 475499",
    "sg:postcode":"CV34 6NZ",
    "sg:province":"Warwickshire",
    "sg:tags":[
        "repair",
        "tech",
        "maintenance"
    ],
    "wof:name":"McKesson Hboc",
    "wof:placetype":"venue"
},
  "geometry": {"coordinates":[-1.5660740137,52.2727851868],"type":"Point"}
}