{
  "type": "Feature",
  "properties": {
    "iso:country":"GB",
    "sg:address":"Abbeyfield Ho, Bridgewater Ro",
    "sg:city":"Manchester",
    "sg:classifiers":[
        {
            "category":"Organizations",
            "subcategory":"Community Association",
            "type":"Services"
        }
    ],
    "sg:postcode":"M28 3JE",
    "sg:province":"Greater Manchester",
    "sg:tags":[
        "society",
        "housing"
    ],
    "wof:name":"Abbeyfield Worsley Society Limited (The)",
    "wof:placetype":"venue"
},
  "geometry": {"coordinates":[-2.39912,53.522999],"type":"Point"}
}