{
  "type": "Feature",
  "properties": {
    "iso:country":"GB",
    "sg:address":"Kirklands Road",
    "sg:city":"Carlisle",
    "sg:classifiers":[
        {
            "category":"Farming",
            "subcategory":"Nursery",
            "type":"Manufacturing & Wholesale Goods"
        },
        {
            "category":"Education",
            "subcategory":"School",
            "type":"Public Place"
        }
    ],
    "sg:phone":"+44 1228 607540",
    "sg:postcode":"CA2 4JD",
    "sg:province":"Cumbria",
    "sg:tags":[
        "local",
        "creche",
        "authority"
    ],
    "wof:name":"St Margaret Mary R C School",
    "wof:placetype":"venue"
},
  "geometry": {"coordinates":[-2.925119,54.876656],"type":"Point"}
}