{
  "type": "Feature",
  "properties": {
    "addr:full":"173 Princess Road Manchester Greater Manchester M14 4RL",
    "addr:housenumber":"173",
    "addr:postcode":"m14 4rl",
    "addr:street":"Princess Road",
    "iso:country":"GB",
    "sg:address":"173 Princess Road",
    "sg:city":"Manchester",
    "sg:classifiers":[
        {
            "category":"Health Services",
            "subcategory":"Optometrist",
            "type":"Services"
        },
        {
            "category":"Shopping",
            "subcategory":"Optician",
            "type":"Retail Goods"
        }
    ],
    "sg:phone":"+44 161 226 1031",
    "sg:postcode":"M14 4RL",
    "sg:province":"Greater Manchester",
    "sg:tags":[
        "ophthalmic"
    ],
    "wof:name":"Murray & Haggerty",
    "wof:placetype":"venue"
},
  "geometry": {"coordinates":[-2.244808,53.453873],"type":"Point"}
}