{
  "type": "Feature",
  "properties": {
    "addr:full":"Walton Street Colne Lancashire BB8 0EA",
    "addr:postcode":"bb8 0ea",
    "addr:street":"Walton Street",
    "iso:country":"GB",
    "sg:address":"Walton Street",
    "sg:city":"Colne",
    "sg:classifiers":[
        {
            "category":"Shopping",
            "subcategory":"Clothing, Apparel, & Fashions",
            "type":"Retail Goods"
        }
    ],
    "sg:phone":"+44 1282 860077",
    "sg:postcode":"BB8 0EA",
    "sg:province":"Lancashire",
    "sg:tags":[
        "sportswear"
    ],
    "wof:name":"B G Sports International Ltd.",
    "wof:placetype":"venue"
},
  "geometry": {"coordinates":[-2.169774,53.854897],"type":"Point"}
}