{
  "type": "Feature",
  "properties": {
    "addr:full":"85 Queen Street Morecambe Lancashire LA4 5EN",
    "addr:housenumber":"85",
    "addr:postcode":"la4 5en",
    "addr:street":"Queen Street",
    "iso:country":"GB",
    "sg:address":"85 Queen Street",
    "sg:city":"Morecambe",
    "sg:classifiers":[
        {
            "category":"Retail",
            "subcategory":"Repair Shop",
            "type":"Services"
        }
    ],
    "sg:phone":"+44 1524 423544",
    "sg:postcode":"LA4 5EN",
    "sg:province":"Lancashire",
    "sg:tags":[
        "upholstering",
        "upholsterer"
    ],
    "wof:name":"Alan Cranswick",
    "wof:placetype":"venue"
},
  "geometry": {"coordinates":[-2.862534,54.071922],"type":"Point"}
}