{
  "type": "Feature",
  "properties": {
    "addr:full":"Unit 8/9, County Workshops Dewsbury West Yorkshire WF13 1QU",
    "addr:housenumber":"unit 8 / 9 county",
    "addr:postcode":"wf13 1qu",
    "addr:street":"Dewsbury West",
    "iso:country":"GB",
    "sg:address":"Unit 8/9, County Workshops",
    "sg:city":"Dewsbury",
    "sg:classifiers":[
        {
            "category":"Shopping",
            "subcategory":"Clothing, Apparel, & Fashions",
            "type":"Retail Goods"
        }
    ],
    "sg:phone":"+44 1924 840370",
    "sg:postcode":"WF13 1QU",
    "sg:province":"West Yorkshire",
    "sg:tags":[
        "clothing",
        "fabric"
    ],
    "wof:name":"Coversafe Clothing Ltd.",
    "wof:placetype":"venue"
},
  "geometry": {"coordinates":[-1.6274889708,53.6927185059],"type":"Point"}
}