{
  "type": "Feature",
  "properties": {
    "iso:country":"GB",
    "sg:address":"36 English St",
    "sg:city":"Dumfries",
    "sg:classifiers":[
        {
            "category":"Wholesale",
            "subcategory":"Chemicals & Plastics",
            "type":"Manufacturing & Wholesale Goods"
        }
    ],
    "sg:phone":"+44 1387 264279",
    "sg:postcode":"DG1 2BY",
    "sg:province":"Dumfries and Galloway",
    "sg:tags":[
        "supplier",
        "w'sale",
        "perfume"
    ],
    "wof:name":"Coultharts Collection",
    "wof:placetype":"venue"
},
  "geometry": {"coordinates":[-3.608883,55.068523],"type":"Point"}
}