{
  "type": "Feature",
  "properties": {
    "addr:full":"Roseacre Gardens Welwyn Garden City Hertfordshire AL7 2RH",
    "addr:postcode":"al7 2rh",
    "addr:street":"Roseacre Gardens",
    "iso:country":"GB",
    "sg:address":"Roseacre Gardens",
    "sg:city":"Welwyn Garden City",
    "sg:classifiers":[
        {
            "category":"Organizations",
            "subcategory":"Community Association",
            "type":"Services"
        }
    ],
    "sg:phone":"+44 1707 372857",
    "sg:postcode":"AL7 2RH",
    "sg:province":"Hertfordshire",
    "sg:tags":[
        "society",
        "housing"
    ],
    "wof:name":"Roseacre Gardens",
    "wof:placetype":"venue"
},
  "geometry": {"coordinates":[-0.166625,51.797428],"type":"Point"}
}