{
  "type": "Feature",
  "properties": {
    "addr:full":"45 Soulbury Road, Linslade Leighton Buzzard Bedfordshire LU7 2RW",
    "addr:housenumber":"45",
    "addr:postcode":"lu7 2rw",
    "addr:street":"Soulbury Road",
    "iso:country":"GB",
    "sg:address":"45 Soulbury Road, Linslade",
    "sg:city":"Leighton Buzzard",
    "sg:classifiers":[
        {
            "category":"Shopping",
            "subcategory":"Musical Instruments",
            "type":"Retail Goods"
        }
    ],
    "sg:phone":"+44 1525 376208",
    "sg:postcode":"LU7 2RW",
    "sg:province":"Bedfordshire",
    "wof:name":"Mr Wright M.P.T.A.",
    "wof:placetype":"venue"
},
  "geometry": {"coordinates":[-0.67977,51.919693],"type":"Point"}
}