{
  "type": "Feature",
  "properties": {
    "addr:full":"133 Brierbush Road Macmerry, Tranent Tranent East Lothian EH33 1PX",
    "addr:housenumber":"133",
    "addr:postcode":"eh33 1px",
    "addr:street":"Brierbush Road",
    "iso:country":"GB",
    "sg:address":"133 Brierbush Road Macmerry, Tranent",
    "sg:city":"Tranent",
    "sg:classifiers":[
        {
            "category":"Professional",
            "subcategory":"Printing & Photocopies",
            "type":"Services"
        }
    ],
    "sg:postcode":"EH33 1PX",
    "sg:province":"East Lothian",
    "sg:tags":[
        "printer"
    ],
    "wof:name":"Thomas Johnstone",
    "wof:placetype":"venue"
},
  "geometry": {"coordinates":[-2.9021399021,55.9405708313],"type":"Point"}
}