{
  "type": "Feature",
  "properties": {
    "addr:full":"42 Temperley Road London Greater London SW12 8QF",
    "addr:housenumber":"42",
    "addr:postcode":"sw12 8qf",
    "addr:street":"Temperley Road",
    "iso:country":"GB",
    "sg:address":"42 Temperley Road",
    "sg:city":"London",
    "sg:classifiers":[
        {
            "category":"Professional",
            "subcategory":"Management & Consulting",
            "type":"Services"
        }
    ],
    "sg:phone":"+44 20 8675 9355",
    "sg:postcode":"SW12 8QF",
    "sg:province":"Greater London",
    "sg:tags":[
        "marketing",
        "consultant"
    ],
    "wof:name":"John F S Akerman & Associates",
    "wof:placetype":"venue"
},
  "geometry": {"coordinates":[-0.1526129991,51.4491882324],"type":"Point"}
}