{
  "type": "Feature",
  "properties": {
    "addr:full":"6 Park Industrial Estate, Frogmore St Albans Hertfordshire AL2 2DR",
    "addr:housenumber":"6",
    "addr:postcode":"al2 2dr",
    "addr:street":"Park Industrial;Frogmore",
    "iso:country":"GB",
    "sg:address":"6 Park Industrial Estate, Frogmore",
    "sg:city":"St Albans",
    "sg:classifiers":[
        {
            "category":"Professional",
            "type":"Services"
        }
    ],
    "sg:postcode":"AL2 2DR",
    "sg:province":"Hertfordshire",
    "sg:tags":[
        "aircraft",
        "maintenance"
    ],
    "wof:name":"Avionics Mobile Services Ltd.",
    "wof:placetype":"venue"
},
  "geometry": {"coordinates":[-0.335496,51.719238],"type":"Point"}
}