{
  "type": "Feature",
  "properties": {
    "addr:full":"Northenden Rd Sale Cheshire M33 2RB",
    "addr:postcode":"m33 2rb",
    "addr:street":"Northenden Rd",
    "iso:country":"GB",
    "sg:address":"Northenden Rd",
    "sg:city":"Sale",
    "sg:classifiers":[
        {
            "category":"Bars & Pubs",
            "type":"Food & Drink"
        }
    ],
    "sg:postcode":"M33 2RB",
    "sg:province":"Cheshire",
    "sg:tags":[
        "pubs",
        "inn"
    ],
    "wof:name":"Wolverhampton & Dudley Breweries Plc (Th",
    "wof:placetype":"venue"
},
  "geometry": {"coordinates":[-2.318174,53.424412],"type":"Point"}
}