{
  "type": "Feature",
  "properties": {
    "iso:country":"GB",
    "sg:address":"66 Askern Rd",
    "sg:city":"Doncaster",
    "sg:classifiers":[
        {
            "category":"Retail",
            "subcategory":"Auto Repair",
            "type":"Services"
        }
    ],
    "sg:postcode":"DN5 0EW",
    "sg:province":"South Yorkshire",
    "sg:tags":[
        "modification",
        "garage"
    ],
    "wof:name":"Park Garage Bentley",
    "wof:placetype":"venue"
},
  "geometry": {"coordinates":[-1.1473350525,53.5496368408],"type":"Point"}
}