{
  "type": "Feature",
  "properties": {
    "addr:full":"12 Cheapside Spennymoor Durham DL16 6DJ",
    "addr:housenumber":"12",
    "addr:postcode":"dl16 6dj",
    "addr:street":"Cheapside",
    "iso:country":"GB",
    "sg:address":"12 Cheapside",
    "sg:city":"Spennymoor",
    "sg:classifiers":[
        {
            "category":"Shopping",
            "subcategory":"News",
            "type":"Retail Goods"
        }
    ],
    "sg:phone":"+44 1388 814443",
    "sg:postcode":"DL16 6DJ",
    "sg:province":"Durham",
    "sg:tags":[
        "newsagent"
    ],
    "wof:name":"R Taylor & Sons Ltd.",
    "wof:placetype":"venue"
},
  "geometry": {"coordinates":[-1.6000150442,54.6999473572],"type":"Point"}
}