{
  "type": "Feature",
  "properties": {
    "addr:full":"83 Clerkenwell Road London Greater London EC1R 5AR",
    "addr:housenumber":"83",
    "addr:postcode":"ec1r 5ar",
    "addr:street":"Clerkenwell Road",
    "iso:country":"GB",
    "sg:address":"83 Clerkenwell Road",
    "sg:city":"London",
    "sg:classifiers":[
        {
            "category":"Manufacturing",
            "subcategory":"Textiles",
            "type":"Manufacturing & Wholesale Goods"
        }
    ],
    "sg:phone":"+44 20 7813 3443",
    "sg:postcode":"EC1R 5AR",
    "sg:province":"Greater London",
    "sg:tags":[
        "knitwear"
    ],
    "wof:name":"Alison Collis Knitwear Design",
    "wof:placetype":"venue"
},
  "geometry": {"coordinates":[-0.110113,51.521957],"type":"Point"}
}