{
  "type": "Feature",
  "properties": {
    "addr:full":"21 Kingfisher Court, Greenhill Herne Bay Kent CT6 7PL",
    "addr:housenumber":"21",
    "addr:postcode":"ct6 7pl",
    "addr:street":"Kingfisher Court;Bay",
    "iso:country":"GB",
    "sg:address":"21 Kingfisher Court, Greenhill",
    "sg:city":"Herne Bay",
    "sg:classifiers":[
        {
            "category":"Personal",
            "subcategory":"Tanning Parlor",
            "type":"Services"
        }
    ],
    "sg:postcode":"CT6 7PL",
    "sg:province":"Kent",
    "sg:tags":[
        "sunbeds"
    ],
    "wof:name":"Just Sunbeds",
    "wof:placetype":"venue"
},
  "geometry": {"coordinates":[1.1136319637,51.3624382019],"type":"Point"}
}