{
  "type": "Feature",
  "properties": {
    "addr:full":"32 Tregonissey Road St Austell Cornwall PL25 4DQ",
    "addr:housenumber":"32",
    "addr:postcode":"pl25 4dq",
    "addr:street":"Tregonissey Road",
    "iso:country":"GB",
    "sg:address":"32 Tregonissey Road",
    "sg:city":"St Austell",
    "sg:classifiers":[
        {
            "category":"Organizations",
            "subcategory":"Non-profit Organization",
            "type":"Services"
        }
    ],
    "sg:postcode":"PL25 4DQ",
    "sg:province":"Cornwall",
    "sg:tags":[
        "organisation",
        "voluntary",
        "charity"
    ],
    "wof:name":"The Cancer Research Campaign",
    "wof:placetype":"venue"
},
  "geometry": {"coordinates":[-4.7848520279,50.3444252014],"type":"Point"}
}