{
  "type": "Feature",
  "properties": {
    "iso:country":"GB",
    "sg:address":"Westridge House, Jennings Wood Lane, Heightington",
    "sg:city":"Bewdley",
    "sg:classifiers":[
        {
            "category":"Autos & Motor Vehicles",
            "subcategory":"Automobile Sales",
            "type":"Retail Goods"
        },
        {
            "category":"Manufacturing",
            "subcategory":"Motor Vehicles & Parts",
            "type":"Manufacturing & Wholesale Goods"
        }
    ],
    "sg:phone":"+44 1299 822862",
    "sg:postcode":"DY12 2YJ",
    "sg:province":"Shropshire",
    "sg:tags":[
        "car",
        "manufacturer"
    ],
    "wof:name":"Grinnall Specialist Cars",
    "wof:placetype":"venue"
},
  "geometry": {"coordinates":[-2.3147790432,52.3760185242],"type":"Point"}
}