{
  "type": "Feature",
  "properties": {
    "iso:country":"GB",
    "sg:address":"Unit 23 Brockhall Village",
    "sg:city":"Blackburn",
    "sg:classifiers":[
        {
            "category":"Building & Trades",
            "subcategory":"Construction",
            "type":"Services"
        }
    ],
    "sg:phone":"+44 1254 246660",
    "sg:postcode":"BB6 8AY",
    "sg:province":"Lancashire",
    "sg:tags":[
        "tiling",
        "contractor"
    ],
    "wof:name":"C B Tiling Contractors Ltd",
    "wof:placetype":"venue"
},
  "geometry": {"coordinates":[-2.446049,53.80941],"type":"Point"}
}