{
  "type": "Feature",
  "properties": {
    "iso:country":"GB",
    "sg:address":"Bus Terminus, Baslow Road",
    "sg:city":"Sheffield",
    "sg:classifiers":[
        {
            "category":"Retail",
            "subcategory":"Auto Repair",
            "type":"Services"
        }
    ],
    "sg:phone":"+44 114 235 1480",
    "sg:postcode":"S17 4AE",
    "sg:province":"Derbyshire",
    "sg:tags":[
        "body",
        "car"
    ],
    "wof:name":"Europa Body Shop",
    "wof:placetype":"venue"
},
  "geometry": {"coordinates":[-1.464544,53.38311],"type":"Point"}
}