{
  "type": "Feature",
  "properties": {
    "addr:full":"Unit A5, Hollywells Rd Ipswich Suffolk IP3 0DL",
    "addr:postcode":"ip3 0dl",
    "addr:street":"Hollywells Rd",
    "iso:country":"GB",
    "sg:address":"Unit A5, Hollywells Rd",
    "sg:city":"Ipswich",
    "sg:classifiers":[
        {
            "category":"Home & Garden",
            "subcategory":"Furniture",
            "type":"Retail Goods"
        }
    ],
    "sg:postcode":"IP3 0DL",
    "sg:province":"Suffolk",
    "wof:name":"Cranwell Pine",
    "wof:placetype":"venue"
},
  "geometry": {"coordinates":[1.166569,52.046951],"type":"Point"}
}