{
  "type": "Feature",
  "properties": {
    "iso:country":"GB",
    "sg:address":"24 Red Lion Street",
    "sg:city":"Chesham",
    "sg:classifiers":[
        {
            "category":"Home & Garden",
            "subcategory":"Home Furnishings",
            "type":"Retail Goods"
        },
        {
            "category":"Retail",
            "subcategory":"Repair Shop",
            "type":"Services"
        }
    ],
    "sg:postcode":"HP5 1EZ",
    "sg:province":"Buckinghamshire",
    "sg:tags":[
        "loose",
        "cover",
        "upholsterer"
    ],
    "wof:name":"Graham Blake Soft Furnishings Ltd.",
    "wof:placetype":"venue"
},
  "geometry": {"coordinates":[-0.612012,51.702847],"type":"Point"}
}