{
  "type": "Feature",
  "properties": {
    "iso:country":"GB",
    "sg:address":"30 Railway Road, Idle",
    "sg:city":"Bradford",
    "sg:classifiers":[
        {
            "category":"Retail",
            "subcategory":"Auto Repair",
            "type":"Services"
        }
    ],
    "sg:postcode":"BD10 9RJ",
    "sg:province":"West Yorkshire",
    "sg:tags":[
        "body",
        "car"
    ],
    "wof:name":"Rawdon Restorations",
    "wof:placetype":"venue"
},
  "geometry": {"coordinates":[-1.72999,53.836575],"type":"Point"}
}