{
  "type": "Feature",
  "properties": {
    "addr:full":"38 Sheffield Road, Hoyland Common Barnsley South Yorkshire S74 0DQ",
    "addr:housenumber":"38",
    "addr:postcode":"s74 0dq",
    "addr:street":"Sheffield Road;Yorkshire",
    "iso:country":"GB",
    "sg:address":"38 Sheffield Road, Hoyland Common",
    "sg:city":"Barnsley",
    "sg:classifiers":[
        {
            "category":"Professional",
            "subcategory":"Printing & Photocopies",
            "type":"Services"
        }
    ],
    "sg:phone":"+44 1226 743561",
    "sg:postcode":"S74 0DQ",
    "sg:province":"South Yorkshire",
    "sg:tags":[
        "engraving"
    ],
    "wof:name":"Rockingham Trophies",
    "wof:placetype":"venue"
},
  "geometry": {"coordinates":[-1.4666260481,53.4978027344],"type":"Point"}
}