{
  "type": "Feature",
  "properties": {
    "iso:country":"GB",
    "sg:address":"9 Coombe Rd",
    "sg:city":"Southminster",
    "sg:classifiers":[
        {
            "category":"Building & Trades",
            "subcategory":"Landscaping Services",
            "type":"Services"
        }
    ],
    "sg:phone":"+44 1621 774132",
    "sg:postcode":"CM0 7AH",
    "sg:province":"Essex",
    "sg:tags":[
        "gardening"
    ],
    "wof:name":"J R H Gardening Contractors",
    "wof:placetype":"venue"
},
  "geometry": {"coordinates":[0.827661,51.664261],"type":"Point"}
}