{
  "type": "Feature",
  "properties": {
    "addr:full":"First Floor 44 Market Jew Street Penzance Cornwall TR18 2HY",
    "addr:housenumber":"44",
    "addr:postcode":"cornwall tr18 2hy",
    "addr:street":"Market Jew Street",
    "iso:country":"GB",
    "sg:address":"First Floor 44 Market Jew Street",
    "sg:city":"Penzance",
    "sg:classifiers":[
        {
            "category":"Professional",
            "subcategory":"Computer Services",
            "type":"Services"
        }
    ],
    "sg:postcode":"TR18 2HY",
    "sg:province":"Cornwall",
    "sg:tags":[
        "consultant"
    ],
    "wof:name":"Computer Support Line Ltd",
    "wof:placetype":"venue"
},
  "geometry": {"coordinates":[-5.5340490341,50.1211471558],"type":"Point"}
}