{
  "type": "Feature",
  "properties": {
    "addr:full":"Torphin Quarry Harbour West Calder South Lanarkshire EH55 8RT",
    "addr:postcode":"eh55 8rt",
    "addr:street":"Torphin Quarry Harbour",
    "iso:country":"GB",
    "sg:address":"Torphin Quarry Harbour",
    "sg:city":"West Calder",
    "sg:classifiers":[
        {
            "category":"Utilities",
            "subcategory":"Refuse",
            "type":"Services"
        }
    ],
    "sg:postcode":"EH55 8RT",
    "sg:province":"South Lanarkshire",
    "sg:tags":[
        "disposal",
        "waste"
    ],
    "wof:name":"Drum Environmental Ltd.",
    "wof:placetype":"venue"
},
  "geometry": {"coordinates":[-3.572372,55.851124],"type":"Point"}
}