{
  "type": "Feature",
  "properties": {
    "iso:country":"GB",
    "sg:address":"London Road, Reed",
    "sg:city":"Royston",
    "sg:classifiers":[
        {
            "category":"Retail",
            "subcategory":"Auto Repair",
            "type":"Services"
        }
    ],
    "sg:postcode":"SG8 8BD",
    "sg:province":"Bedfordshire",
    "sg:tags":[
        "body",
        "car"
    ],
    "wof:name":"S & S Commercial (Europe) Ltd.",
    "wof:placetype":"venue"
},
  "geometry": {"coordinates":[-0.024611,52.0071144104],"type":"Point"}
}