{
  "type": "Feature",
  "properties": {
    "iso:country":"GB",
    "sg:address":"Mowbray Drive",
    "sg:city":"Blackpool",
    "sg:classifiers":[
        {
            "category":"Professional",
            "subcategory":"Art Services",
            "type":"Services"
        },
        {
            "category":"Home & Garden",
            "subcategory":"Building Materials",
            "type":"Retail Goods"
        }
    ],
    "sg:phone":"+44 1253 302527",
    "sg:postcode":"FY3 7UN",
    "sg:province":"Lancashire",
    "sg:tags":[
        "merchant",
        "supplier",
        "decorating",
        "painting"
    ],
    "wof:name":"John Stone's Manders Paints",
    "wof:placetype":"venue"
},
  "geometry": {"coordinates":[-3.022155,53.837612],"type":"Point"}
}