{
  "type": "Feature",
  "properties": {
    "addr:full":"17 The Warren Tadley Berkshire RG26 4XY",
    "addr:housenumber":"17",
    "addr:postcode":"rg26 4xy",
    "addr:street":"The Warren",
    "iso:country":"GB",
    "sg:address":"17 The Warren",
    "sg:city":"Tadley",
    "sg:classifiers":[
        {
            "category":"Farming",
            "subcategory":"Nursery",
            "type":"Manufacturing & Wholesale Goods"
        }
    ],
    "sg:phone":"+44 118 981 3888",
    "sg:postcode":"RG26 4XY",
    "sg:province":"Berkshire",
    "sg:tags":[
        "creche"
    ],
    "wof:name":"Tadley & Baughurst Montessori Nursery School",
    "wof:placetype":"venue"
},
  "geometry": {"coordinates":[-1.1483069658,51.349029541],"type":"Point"}
}