{
  "type": "Feature",
  "properties": {
    "addr:full":"69 Dartmouth Middleway Birmingham West Midlands B7 4UA",
    "addr:housenumber":"69",
    "addr:postcode":"b7 4ua",
    "addr:street":"Dartmouth Middleway",
    "iso:country":"GB",
    "sg:address":"69 Dartmouth Middleway",
    "sg:city":"Birmingham",
    "sg:classifiers":[
        {
            "category":"Professional",
            "type":"Services"
        },
        {
            "category":"Shopping",
            "subcategory":"Computers & Home Electronics",
            "type":"Retail Goods"
        }
    ],
    "sg:postcode":"B7 4UA",
    "sg:province":"West Midlands",
    "sg:tags":[
        "equipment",
        "exhibition",
        "audio-visual"
    ],
    "wof:name":"Ghl Realisations Ltd.",
    "wof:placetype":"venue"
},
  "geometry": {"coordinates":[-1.8855040073,52.4888534546],"type":"Point"}
}