{
  "type": "Feature",
  "properties": {
    "addr:full":"Cheapside Farmhouse, Sandridgebury La St Albans Hertfordshire AL3 6JF",
    "addr:postcode":"al3 6jf",
    "addr:street":"Sandridgebury La",
    "iso:country":"GB",
    "sg:address":"Cheapside Farmhouse, Sandridgebury La",
    "sg:city":"St Albans",
    "sg:classifiers":[
        {
            "category":"Health Services",
            "subcategory":"Health Practitioner",
            "type":"Services"
        }
    ],
    "sg:phone":"+44 1727 857714",
    "sg:postcode":"AL3 6JF",
    "sg:province":"Hertfordshire",
    "sg:tags":[
        "osteopath"
    ],
    "wof:name":"Terry G Moule",
    "wof:placetype":"venue"
},
  "geometry": {"coordinates":[-0.32972,51.781849],"type":"Point"}
}