{
  "type": "Feature",
  "properties": {
    "iso:country":"GB",
    "sg:address":"7 Trowbridge Rd",
    "sg:city":"Westbury",
    "sg:classifiers":[
        {
            "category":"Manufacturing",
            "subcategory":"Metals",
            "type":"Manufacturing & Wholesale Goods"
        }
    ],
    "sg:phone":"+44 1373 822644",
    "sg:postcode":"BA13 3DS",
    "sg:province":"Wiltshire",
    "sg:tags":[
        "die-casting"
    ],
    "wof:name":"R Matthew & Son",
    "wof:placetype":"venue"
},
  "geometry": {"coordinates":[-2.179159,51.269047],"type":"Point"}
}