{
  "type": "Feature",
  "properties": {
    "iso:country":"GB",
    "sg:address":"Forge House",
    "sg:city":"Leeds",
    "sg:classifiers":[
        {
            "category":"Professional",
            "subcategory":"Detective & Security Services",
            "type":"Services"
        }
    ],
    "sg:phone":"+44 113 245 9559",
    "sg:postcode":"LS3 1JX",
    "sg:province":"West Yorkshire",
    "sg:tags":[
        "locksmith"
    ],
    "wof:name":"M B Locking Logistics Group Ltd.",
    "wof:placetype":"venue"
},
  "geometry": {"coordinates":[-1.56623,53.803009],"type":"Point"}
}