{
  "type": "Feature",
  "properties": {
    "iso:country":"GB",
    "sg:address":"59 Harpur St",
    "sg:city":"Bedford",
    "sg:classifiers":[
        {
            "category":"Shopping",
            "subcategory":"Clothing, Apparel, & Fashions",
            "type":"Retail Goods"
        }
    ],
    "sg:postcode":"MK40 2SR",
    "sg:province":"Bedfordshire",
    "sg:tags":[
        "shop",
        "dress",
        "fancy"
    ],
    "wof:name":"Fantasia",
    "wof:placetype":"venue"
},
  "geometry": {"coordinates":[-0.4685139954,52.1392707825],"type":"Point"}
}