{
  "type": "Feature",
  "properties": {
    "addr:full":"5 Portpool La Clerkenwell Greater London EC1N 7UU",
    "addr:housenumber":"5",
    "addr:postcode":"ec1n 7uu",
    "addr:street":"Portpool La Clerkenwell",
    "iso:country":"GB",
    "sg:address":"5 Portpool La",
    "sg:city":"Clerkenwell",
    "sg:classifiers":[
        {
            "category":"Professional",
            "subcategory":"Business Services",
            "type":"Services"
        }
    ],
    "sg:phone":"+44 20 7831 2800",
    "sg:postcode":"EC1N 7UU",
    "sg:province":"Greater London",
    "sg:tags":[
        "planning",
        "design"
    ],
    "wof:name":"Addison Marc",
    "wof:placetype":"venue"
},
  "geometry": {"coordinates":[-0.112451,51.520638],"type":"Point"}
}