{
  "type": "Feature",
  "properties": {
    "iso:country":"GB",
    "sg:address":"4 Church Street, Paulton",
    "sg:city":"Bristol",
    "sg:classifiers":[
        {
            "category":"Personal",
            "subcategory":"Beauty Salon",
            "type":"Services"
        }
    ],
    "sg:phone":"+44 1761 417552",
    "sg:postcode":"BS39 7LG",
    "sg:province":"Somerset",
    "sg:tags":[
        "unisex",
        "hairdresser"
    ],
    "wof:name":"Partners 2",
    "wof:placetype":"venue"
},
  "geometry": {"coordinates":[-2.50365,51.307438],"type":"Point"}
}