{
  "type": "Feature",
  "properties": {
    "iso:country":"GB",
    "sg:address":"Sunset View Garage, 646 Preston Road",
    "sg:city":"Chorley",
    "sg:classifiers":[
        {
            "category":"Autos & Motor Vehicles",
            "subcategory":"Automobile Sales",
            "type":"Retail Goods"
        }
    ],
    "sg:postcode":"PR6 7EH",
    "sg:province":"Lancashire",
    "sg:tags":[
        "car"
    ],
    "wof:name":"J Heys",
    "wof:placetype":"venue"
},
  "geometry": {"coordinates":[-2.6409,53.70961],"type":"Point"}
}