{
  "type": "Feature",
  "properties": {
    "addr:full":"River View Cottage, Bishops Wood Ross-on-wye Gloucestershire HR9 5QX",
    "addr:postcode":"hr9 5qx",
    "iso:country":"GB",
    "sg:address":"River View Cottage, Bishops Wood",
    "sg:city":"Ross-on-wye",
    "sg:classifiers":[
        {
            "category":"Freight",
            "type":"Transportation"
        }
    ],
    "sg:phone":"+44 1600 890979",
    "sg:postcode":"HR9 5QX",
    "sg:province":"Gloucestershire",
    "sg:tags":[
        "haulage",
        "road"
    ],
    "wof:name":"E & C Haulage",
    "wof:placetype":"venue"
},
  "geometry": {"coordinates":[-2.5817329884,51.9164810181],"type":"Point"}
}