{
  "type": "Feature",
  "properties": {
    "addr:full":"Robbs Department Store, 48 Fore Street Hexham Northumberland NE46 1NA",
    "addr:housenumber":"48",
    "addr:postcode":"ne46 1na",
    "addr:street":"Fore Street",
    "iso:country":"GB",
    "sg:address":"Robbs Department Store, 48 Fore Street",
    "sg:city":"Hexham",
    "sg:classifiers":[
        {
            "category":"Health Services",
            "subcategory":"Optometrist",
            "type":"Services"
        }
    ],
    "sg:phone":"+44 1434 600376",
    "sg:postcode":"NE46 1NA",
    "sg:province":"Northumberland",
    "sg:tags":[
        "optician"
    ],
    "wof:name":"Penningtons Opticians",
    "wof:placetype":"venue"
},
  "geometry": {"coordinates":[-2.1012940407,54.970035553],"type":"Point"}
}