{
  "type": "Feature",
  "properties": {
    "addr:full":"Boundary Cottage, London Rd, Flimwell Wadhurst East Sussex TN5 7PL",
    "addr:postcode":"tn5 7pl",
    "addr:street":"London Rd",
    "iso:country":"GB",
    "sg:address":"Boundary Cottage, London Rd, Flimwell",
    "sg:city":"Wadhurst",
    "sg:classifiers":[
        {
            "category":"Building & Trades",
            "subcategory":"Construction",
            "type":"Services"
        }
    ],
    "sg:phone":"+44 1580 879313",
    "sg:postcode":"TN5 7PL",
    "sg:province":"East Sussex",
    "sg:tags":[
        "ceiling",
        "contractor"
    ],
    "wof:name":"A J Latter",
    "wof:placetype":"venue"
},
  "geometry": {"coordinates":[0.4448300004,51.0546951294],"type":"Point"}
}