{
  "type": "Feature",
  "properties": {
    "addr:full":"148 Old St London Greater London EC1V 9HQ",
    "addr:housenumber":"148",
    "addr:postcode":"ec1v 9hq",
    "addr:street":"Old St",
    "iso:country":"GB",
    "sg:address":"148 Old St",
    "sg:city":"London",
    "sg:classifiers":[
        {
            "category":"Personal",
            "type":"Services"
        },
        {
            "category":"Government",
            "subcategory":"Post Office",
            "type":"Public Place"
        }
    ],
    "sg:postcode":"EC1V 9HQ",
    "sg:province":"Greater London",
    "sg:tags":[
        "delivery"
    ],
    "wof:name":"Royal Mail Ltd",
    "wof:placetype":"venue"
},
  "geometry": {"coordinates":[-0.0909899995,51.5248298645],"type":"Point"}
}