{
  "type": "Feature",
  "properties": {
    "addr:full":"41 St Marys Gardens London Greater London SE11 4UF",
    "addr:housenumber":"41",
    "addr:postcode":"se11 4uf",
    "addr:street":"St Marys Gardens",
    "iso:country":"GB",
    "sg:address":"41 St Marys Gardens",
    "sg:city":"London",
    "sg:classifiers":[
        {
            "category":"Building & Trades",
            "subcategory":"Construction",
            "type":"Services"
        }
    ],
    "sg:postcode":"SE11 4UF",
    "sg:province":"Greater London",
    "sg:tags":[
        "builder"
    ],
    "wof:name":"P R Construction",
    "wof:placetype":"venue"
},
  "geometry": {"coordinates":[-0.1091199964,51.4929504395],"type":"Point"}
}