{
  "type": "Feature",
  "properties": {
    "iso:country":"GB",
    "sg:address":"205 Eaton Rd, West Derby",
    "sg:city":"Liverpool",
    "sg:classifiers":[
        {
            "category":"Professional",
            "subcategory":"Lawyer & Legal Services",
            "type":"Services"
        }
    ],
    "sg:postcode":"L12 2AG",
    "sg:province":"Merseyside",
    "wof:name":"Fagan,Jean,",
    "wof:placetype":"venue"
},
  "geometry": {"coordinates":[-2.9029951096,53.4259414673],"type":"Point"}
}