{
  "type": "Feature",
  "properties": {
    "iso:country":"GB",
    "sg:address":"113 Manor Avenue South",
    "sg:city":"Kidderminster",
    "sg:classifiers":[
        {
            "category":"Building & Trades",
            "subcategory":"Construction",
            "type":"Services"
        }
    ],
    "sg:phone":"+44 1562 740676",
    "sg:postcode":"DY11 6DG",
    "sg:province":"Staffordshire",
    "sg:tags":[
        "decorator",
        "painter"
    ],
    "wof:name":"Carl Jones",
    "wof:placetype":"venue"
},
  "geometry": {"coordinates":[-2.278863,52.391384],"type":"Point"}
}