{
  "type": "Feature",
  "properties": {
    "iso:country":"GB",
    "sg:address":"Unit 7, Mossy Lea Rd",
    "sg:city":"Wigan",
    "sg:classifiers":[
        {
            "category":"Home & Garden",
            "subcategory":"Hardware",
            "type":"Retail Goods"
        }
    ],
    "sg:phone":"+44 1257 472721",
    "sg:postcode":"WN6 9RS",
    "sg:province":"Lancashire",
    "sg:tags":[
        "equipment",
        "bathroom",
        "fitting"
    ],
    "wof:name":"The Bathroom Showroom",
    "wof:placetype":"venue"
},
  "geometry": {"coordinates":[-2.696904,53.590416],"type":"Point"}
}