{
  "type": "Feature",
  "properties": {
    "iso:country":"GB",
    "sg:address":"29 Crown Lane, Benson",
    "sg:city":"Wallingford",
    "sg:classifiers":[
        {
            "category":"Building & Trades",
            "subcategory":"Construction",
            "type":"Services"
        }
    ],
    "sg:phone":"+44 1491 834828",
    "sg:postcode":"OX10 6LP",
    "sg:province":"Oxfordshire",
    "sg:tags":[
        "roofing",
        "contracting"
    ],
    "wof:name":"Skyline Roofing Specialists",
    "wof:placetype":"venue"
},
  "geometry": {"coordinates":[-1.1074659824,51.6227493286],"type":"Point"}
}