{
  "type": "Feature",
  "properties": {
    "addr:full":"31 The Moor Sheffield South Yorkshire S1 4PF",
    "addr:housenumber":"31",
    "addr:postcode":"s1 4pf",
    "addr:street":"The Moor",
    "iso:country":"GB",
    "sg:address":"31 The Moor",
    "sg:city":"Sheffield",
    "sg:classifiers":[
        {
            "category":"Shopping",
            "subcategory":"Optician",
            "type":"Retail Goods"
        }
    ],
    "sg:phone":"+44 114 278 0838",
    "sg:postcode":"S1 4PF",
    "sg:province":"South Yorkshire",
    "sg:tags":[
        "dispensing"
    ],
    "wof:name":"Vision Express (UK) Ltd",
    "wof:placetype":"venue"
},
  "geometry": {"coordinates":[-1.472752,53.376774],"type":"Point"}
}