{
  "type": "Feature",
  "properties": {
    "addr:full":"Abbey Road, Wrexham Industrial Estate Wrexham Wrexham LL13 9RF",
    "addr:postcode":"ll13 9rf",
    "addr:street":"Abbey Road;Industrial Estate",
    "iso:country":"GB",
    "sg:address":"Abbey Road, Wrexham Industrial Estate",
    "sg:city":"Wrexham",
    "sg:classifiers":[
        {
            "category":"Wholesale",
            "subcategory":"Scrap",
            "type":"Manufacturing & Wholesale Goods"
        }
    ],
    "sg:phone":"+44 161 777 4300",
    "sg:postcode":"LL13 9RF",
    "sg:province":"Wrexham",
    "sg:tags":[
        "waste",
        "metal"
    ],
    "wof:name":"Uk Waste Recycling Services",
    "wof:placetype":"venue"
},
  "geometry": {"coordinates":[-2.9166789055,53.0419464111],"type":"Point"}
}