{
  "type": "Feature",
  "properties": {
    "addr:full":"Unit 10b Micleton Road, Riverside Park Industrial Estate Middlesbrough Durham TS2 1LQ",
    "addr:housenumber":"unit 10b",
    "addr:postcode":"ts2 1lq",
    "addr:street":"Micleton Road;Park Industrial",
    "iso:country":"GB",
    "sg:address":"Unit 10b Micleton Road, Riverside Park Industrial Estate",
    "sg:city":"Middlesbrough",
    "sg:classifiers":[
        {
            "category":"Shopping",
            "subcategory":"Stationery & Office Supplies",
            "type":"Retail Goods"
        }
    ],
    "sg:phone":"+44 1642 230736",
    "sg:postcode":"TS2 1LQ",
    "sg:province":"Durham",
    "wof:name":"J A Magson Ltd.",
    "wof:placetype":"venue"
},
  "geometry": {"coordinates":[-1.2330960035,54.5813598633],"type":"Point"}
}