{
  "type": "Feature",
  "properties": {
    "addr:full":"28 Saxon Sq Christchurch Dorset BH23 1QB",
    "addr:housenumber":"28",
    "addr:postcode":"bh23 1qb",
    "addr:street":"Saxon Sq",
    "iso:country":"GB",
    "sg:address":"28 Saxon Sq",
    "sg:city":"Christchurch",
    "sg:classifiers":[
        {
            "category":"Shopping",
            "subcategory":"Comic Books",
            "type":"Retail Goods"
        }
    ],
    "sg:phone":"+44 1202 470075",
    "sg:postcode":"BH23 1QB",
    "sg:province":"Dorset",
    "sg:tags":[
        "jeweller"
    ],
    "wof:name":"Goldman Jewellers",
    "wof:placetype":"venue"
},
  "geometry": {"coordinates":[-1.777609,50.735001],"type":"Point"}
}