{
  "type": "Feature",
  "properties": {
    "iso:country":"GB",
    "sg:address":"22 Crockerton Road, Tooting B E C",
    "sg:city":"London",
    "sg:classifiers":[
        {
            "category":"Education",
            "subcategory":"Music School",
            "type":"Public Place"
        }
    ],
    "sg:phone":"+44 20 8767 1293",
    "sg:postcode":"SW17 7HG",
    "sg:province":"Greater London",
    "sg:tags":[
        "teacher"
    ],
    "wof:name":"Angela's Piano Tuition",
    "wof:placetype":"venue"
},
  "geometry": {"coordinates":[-0.165065,51.438408],"type":"Point"}
}