{
  "type": "Feature",
  "properties": {
    "iso:country":"GB",
    "sg:address":"Congregational Church Hall, High Street",
    "sg:city":"Cranbrook",
    "sg:classifiers":[
        {
            "category":"Farming",
            "subcategory":"Nursery",
            "type":"Manufacturing & Wholesale Goods"
        },
        {
            "category":"Education",
            "subcategory":"Preschool",
            "type":"Public Place"
        }
    ],
    "sg:phone":"+44 1580 715570",
    "sg:postcode":"TN17 3DT",
    "sg:province":"Kent",
    "sg:tags":[
        "school",
        "creche"
    ],
    "wof:name":"Rainbow Pre-School",
    "wof:placetype":"venue"
},
  "geometry": {"coordinates":[0.535245,51.0965],"type":"Point"}
}