{
  "type": "Feature",
  "properties": {
    "iso:country":"GB",
    "sg:address":"Hinckley Rd, Burbage",
    "sg:city":"Hinckley",
    "sg:classifiers":[
        {
            "category":"Bars & Pubs",
            "type":"Food & Drink"
        }
    ],
    "sg:phone":"+44 1455 239443",
    "sg:postcode":"LE10 2AF",
    "sg:province":"Leicestershire",
    "sg:tags":[
        "pubs",
        "inn"
    ],
    "wof:name":"The Cross Keys",
    "wof:placetype":"venue"
},
  "geometry": {"coordinates":[-1.348572,52.530193],"type":"Point"}
}