{
  "type": "Feature",
  "properties": {
    "addr:full":"6 Summerskill Grn, Inkersall Chesterfield Derbyshire S43 3SR",
    "addr:housenumber":"6",
    "addr:postcode":"s43 3sr",
    "addr:street":"Summerskill Grn Inkersall",
    "iso:country":"GB",
    "sg:address":"6 Summerskill Grn, Inkersall",
    "sg:city":"Chesterfield",
    "sg:classifiers":[
        {
            "category":"Shopping",
            "subcategory":"Pharmacy",
            "type":"Retail Goods"
        }
    ],
    "sg:postcode":"S43 3SR",
    "sg:province":"Derbyshire",
    "sg:tags":[
        "pharmacist",
        "chemist"
    ],
    "wof:name":"Inkersall Pharmacy",
    "wof:placetype":"venue"
},
  "geometry": {"coordinates":[-1.370227,53.255501],"type":"Point"}
}