{
  "type": "Feature",
  "properties": {
    "addr:full":"41 Walton Road Watford Hertfordshire WD23 2JD",
    "addr:housenumber":"41",
    "addr:postcode":"wd23 2jd",
    "addr:street":"Walton Road",
    "iso:country":"GB",
    "sg:address":"41 Walton Road",
    "sg:city":"Watford",
    "sg:classifiers":[
        {
            "category":"Professional",
            "subcategory":"Research",
            "type":"Services"
        }
    ],
    "sg:phone":"+44 1923 237160",
    "sg:postcode":"WD23 2JD",
    "sg:province":"Hertfordshire",
    "sg:tags":[
        "market"
    ],
    "wof:name":"Edwin G Fisher Associates",
    "wof:placetype":"venue"
},
  "geometry": {"coordinates":[-0.381949991,51.6556282043],"type":"Point"}
}