{
  "type": "Feature",
  "properties": {
    "iso:country":"GB",
    "sg:address":"23 Diane Road, Ashton-in-makerfielddiane",
    "sg:city":"Wigan",
    "sg:classifiers":[
        {
            "category":"Professional",
            "subcategory":"Secretarial Services",
            "type":"Services"
        }
    ],
    "sg:phone":"+44 1942 208315",
    "sg:postcode":"WN4 8SY",
    "sg:province":"Lancashire",
    "wof:name":"Foster Design Services Ltd.",
    "wof:placetype":"venue"
},
  "geometry": {"coordinates":[-2.619326,53.496197],"type":"Point"}
}