{
  "type": "Feature",
  "properties": {
    "iso:country":"GB",
    "sg:address":"18 Bewick Road",
    "sg:city":"Gateshead",
    "sg:classifiers":[
        {
            "category":"Professional",
            "subcategory":"Engineering",
            "type":"Services"
        }
    ],
    "sg:postcode":"NE8 4DP",
    "sg:province":"Tyne and Wear",
    "sg:tags":[
        "consulting",
        "engineer"
    ],
    "wof:name":"K.F. Shadbolt & Partners Llp",
    "wof:placetype":"venue"
},
  "geometry": {"coordinates":[-1.607438,54.948257],"type":"Point"}
}