{
  "type": "Feature",
  "properties": {
    "addr:full":"296 Wragby Road Lincoln Lincolnshire LN2 4QZ",
    "addr:housenumber":"296",
    "addr:postcode":"ln2 4qz",
    "addr:street":"Wragby Road",
    "iso:country":"GB",
    "sg:address":"296 Wragby Road",
    "sg:city":"Lincoln",
    "sg:classifiers":[
        {
            "category":"Retail",
            "subcategory":"Auto Repair",
            "type":"Services"
        }
    ],
    "sg:phone":"+44 1526 320514",
    "sg:postcode":"LN2 4QZ",
    "sg:province":"Lincolnshire",
    "sg:tags":[
        "modification",
        "garage"
    ],
    "wof:name":"Spencers of Lincoln Ltd.",
    "wof:placetype":"venue"
},
  "geometry": {"coordinates":[-0.512149,53.241871],"type":"Point"}
}