{
  "type": "Feature",
  "properties": {
    "addr:full":"37 Hawthorne Road, Castle Bromwich Birmingham West Midlands B36 0HJ",
    "addr:housenumber":"37",
    "addr:postcode":"b36 0hj",
    "addr:street":"Hawthorne Road",
    "iso:country":"GB",
    "sg:address":"37 Hawthorne Road, Castle Bromwich",
    "sg:city":"Birmingham",
    "sg:classifiers":[
        {
            "category":"Building & Trades",
            "subcategory":"Construction",
            "type":"Services"
        },
        {
            "category":"Building & Trades",
            "subcategory":"Electrical",
            "type":"Services"
        }
    ],
    "sg:postcode":"B36 0HJ",
    "sg:province":"West Midlands",
    "sg:tags":[
        "roofing",
        "electrician",
        "contractor"
    ],
    "wof:name":"NTECH ELECTRICAL LTD",
    "wof:placetype":"venue"
},
  "geometry": {"coordinates":[-1.756865,52.501488],"type":"Point"}
}