{
  "type": "Feature",
  "properties": {
    "addr:full":"Brunswick House Southampton Hampshire SO15 2AP",
    "addr:postcode":"hampshire so15 2ap",
    "iso:country":"GB",
    "sg:address":"Brunswick House",
    "sg:city":"Southampton",
    "sg:classifiers":[
        {
            "category":"Manufacturing",
            "subcategory":"Tools & Machinery",
            "type":"Manufacturing & Wholesale Goods"
        }
    ],
    "sg:phone":"+44 23 8063 5966",
    "sg:postcode":"SO15 2AP",
    "sg:province":"Hampshire",
    "sg:tags":[
        "society",
        "friendly"
    ],
    "wof:name":"Stride Ltd.",
    "wof:placetype":"venue"
},
  "geometry": {"coordinates":[-1.4073189497,50.9099388123],"type":"Point"}
}