{
  "type": "Feature",
  "properties": {
    "iso:country":"GB",
    "sg:address":"452 Tile Hill Lane",
    "sg:city":"Coventry",
    "sg:classifiers":[
        {
            "category":"Retail",
            "subcategory":"Driving School",
            "type":"Services"
        },
        {
            "category":"Education",
            "subcategory":"University",
            "type":"Public Place"
        }
    ],
    "sg:phone":"+44 24 7646 9282",
    "sg:postcode":"CV4 9DY",
    "sg:province":"Warwickshire",
    "sg:tags":[
        "higher"
    ],
    "wof:name":"A C T Driving School",
    "wof:placetype":"venue"
},
  "geometry": {"coordinates":[-1.57484,52.402088],"type":"Point"}
}