{
  "type": "Feature",
  "properties": {
    "addr:full":"36 Westgate Wakefield West Yorkshire WF1 1JY",
    "addr:housenumber":"36",
    "addr:postcode":"wf1 1jy",
    "addr:street":"Westgate Wakefield West",
    "iso:country":"GB",
    "sg:address":"36 Westgate",
    "sg:city":"Wakefield",
    "sg:classifiers":[
        {
            "category":"Cafe",
            "type":"Food & Drink"
        }
    ],
    "sg:phone":"+44 1924 372942",
    "sg:postcode":"WF1 1JY",
    "sg:province":"West Yorkshire",
    "sg:tags":[
        "tea",
        "snack",
        "bar",
        "room"
    ],
    "wof:name":"The Conservatory",
    "wof:placetype":"venue"
},
  "geometry": {"coordinates":[-1.5001200438,53.6824455261],"type":"Point"}
}