{
  "type": "Feature",
  "properties": {
    "addr:full":"37 Aldgate Drive Brierley Hill West Midlands DY5 3NT",
    "addr:housenumber":"37",
    "addr:postcode":"dy5 3nt",
    "addr:street":"Aldgate Drive Brierley Hill",
    "iso:country":"GB",
    "sg:address":"37 Aldgate Drive",
    "sg:city":"Brierley Hill",
    "sg:classifiers":[
        {
            "category":"Building & Trades",
            "subcategory":"Construction",
            "type":"Services"
        }
    ],
    "sg:phone":"+44 1384 897848",
    "sg:postcode":"DY5 3NT",
    "sg:province":"West Midlands",
    "sg:tags":[
        "builder"
    ],
    "wof:name":"W B Parsons",
    "wof:placetype":"venue"
},
  "geometry": {"coordinates":[-2.1322999001,52.4661026001],"type":"Point"}
}