{
  "type": "Feature",
  "properties": {
    "iso:country":"GB",
    "sg:address":"Lane End House, Hatt Common, East Woodhay",
    "sg:city":"Newbury",
    "sg:classifiers":[
        {
            "category":"Building & Trades",
            "subcategory":"Landscaping Services",
            "type":"Services"
        }
    ],
    "sg:postcode":"RG20 0NG",
    "sg:province":"Berkshire",
    "sg:tags":[
        "forestry",
        "tree"
    ],
    "wof:name":"G A Butler & Sons",
    "wof:placetype":"venue"
},
  "geometry": {"coordinates":[-1.38775,51.367458],"type":"Point"}
}