{
  "type": "Feature",
  "properties": {
    "addr:full":"67 High Street Tarporley Cheshire CW6 0DP",
    "addr:housenumber":"67",
    "addr:postcode":"cw6 0dp",
    "addr:street":"High Street",
    "iso:country":"GB",
    "sg:address":"67 High Street",
    "sg:city":"Tarporley",
    "sg:classifiers":[
        {
            "category":"Organizations",
            "subcategory":"Non-profit Organization",
            "type":"Services"
        }
    ],
    "sg:phone":"+44 1829 732115",
    "sg:postcode":"CW6 0DP",
    "sg:province":"Cheshire",
    "sg:tags":[
        "organisation",
        "voluntary",
        "charity"
    ],
    "wof:name":"R N I B Transcription Centre North West",
    "wof:placetype":"venue"
},
  "geometry": {"coordinates":[-2.668506,53.159313],"type":"Point"}
}