{
  "type": "Feature",
  "properties": {
    "iso:country":"GB",
    "sg:address":"225 Brockles Mead",
    "sg:city":"Harlow",
    "sg:classifiers":[
        {
            "category":"Building & Trades",
            "subcategory":"Construction",
            "type":"Services"
        }
    ],
    "sg:phone":"+44 1279 454168",
    "sg:postcode":"CM19 4QA",
    "sg:province":"Essex",
    "sg:tags":[
        "glass",
        "replacement"
    ],
    "wof:name":"A.C. Emergency Glazing",
    "wof:placetype":"venue"
},
  "geometry": {"coordinates":[0.0848850012,51.7511787415],"type":"Point"}
}