{
  "type": "Feature",
  "properties": {
    "iso:country":"GB",
    "sg:address":"Unit 15-16 Henwood Business Centre, Henwoodindust Estate",
    "sg:city":"Ashford",
    "sg:classifiers":[
        {
            "category":"Home & Garden",
            "subcategory":"Home Furnishings",
            "type":"Retail Goods"
        }
    ],
    "sg:phone":"+44 1233 622323",
    "sg:postcode":"TN24 8DH",
    "sg:province":"Kent",
    "sg:tags":[
        "merchant",
        "diy",
        "decorators'"
    ],
    "wof:name":"C Brewer & Sons",
    "wof:placetype":"venue"
},
  "geometry": {"coordinates":[0.88453,51.150551],"type":"Point"}
}