{
  "type": "Feature",
  "properties": {
    "iso:country":"GB",
    "sg:address":"531 Tong Road",
    "sg:city":"Leeds",
    "sg:classifiers":[
        {
            "category":"Shopping",
            "subcategory":"Pharmacy",
            "type":"Retail Goods"
        }
    ],
    "sg:phone":"+44 113 263 7023",
    "sg:postcode":"LS12 5AT",
    "sg:province":"West Yorkshire",
    "sg:tags":[
        "pharmacist",
        "chemist"
    ],
    "wof:name":"Lloyds Chemist",
    "wof:placetype":"venue"
},
  "geometry": {"coordinates":[-1.6181950569,53.7923622131],"type":"Point"}
}