{
  "type": "Feature",
  "properties": {
    "iso:country":"GB",
    "sg:address":"Moss Lane",
    "sg:city":"Northwich",
    "sg:classifiers":[
        {
            "category":"Government",
            "subcategory":"Office",
            "type":"Public Place"
        },
        {
            "category":"Sports & Exercise",
            "subcategory":"Swimming Pool",
            "type":"Entertainment"
        }
    ],
    "sg:phone":"+44 1606 783835",
    "sg:postcode":"CW8 4BG",
    "sg:province":"Cheshire",
    "sg:tags":[
        "local"
    ],
    "wof:name":"Northwich Swimming Pool",
    "wof:placetype":"venue"
},
  "geometry": {"coordinates":[-2.527881,53.255939],"type":"Point"}
}