{
  "type": "Feature",
  "properties": {
    "iso:country":"GB",
    "sg:address":"St Ives, Coopers Lane, Bramley",
    "sg:city":"Tadley",
    "sg:classifiers":[
        {
            "category":"Professional",
            "type":"Services"
        }
    ],
    "sg:phone":"+44 1256 881411",
    "sg:postcode":"RG26 5DA",
    "sg:province":"Berkshire",
    "sg:tags":[
        "entertainer"
    ],
    "wof:name":"Shobiz U K",
    "wof:placetype":"venue"
},
  "geometry": {"coordinates":[-1.0608240366,51.3305244446],"type":"Point"}
}