{
  "type": "Feature",
  "properties": {
    "iso:country":"GB",
    "sg:address":"Unit 7 Brookside Business Centre, Church Road, Swallowfield",
    "sg:city":"Reading",
    "sg:classifiers":[
        {
            "category":"Professional",
            "subcategory":"Printing & Photocopies",
            "type":"Services"
        }
    ],
    "sg:phone":"+44 118 988 5064",
    "sg:postcode":"RG7 1TH",
    "sg:province":"Berkshire",
    "sg:tags":[
        "printer"
    ],
    "wof:name":"Swallowfield Press",
    "wof:placetype":"venue"
},
  "geometry": {"coordinates":[-0.966979,51.375095],"type":"Point"}
}