{
  "type": "Feature",
  "properties": {
    "iso:country":"GB",
    "sg:address":"1a Castle Street",
    "sg:city":"Rugby",
    "sg:classifiers":[
        {
            "category":"Shopping",
            "subcategory":"Clothing, Apparel, & Fashions",
            "type":"Retail Goods"
        }
    ],
    "sg:postcode":"CV21 2TP",
    "sg:province":"Warwickshire",
    "sg:tags":[
        "shop"
    ],
    "wof:name":"Routine",
    "wof:placetype":"venue"
},
  "geometry": {"coordinates":[-1.259878993,52.3731117249],"type":"Point"}
}