{
  "type": "Feature",
  "properties": {
    "iso:country":"GB",
    "sg:address":"9 Perrywood Business Park, Salfords",
    "sg:city":"Redhill",
    "sg:classifiers":[
        {
            "category":"Professional",
            "subcategory":"Computer Services",
            "type":"Services"
        }
    ],
    "sg:phone":"+44 1737 768644",
    "sg:postcode":"RH1 5DZ",
    "sg:province":"Surrey",
    "sg:tags":[
        "system",
        "software"
    ],
    "wof:name":"International Publishing Associates Ltd.",
    "wof:placetype":"venue"
},
  "geometry": {"coordinates":[-0.165758,51.19825],"type":"Point"}
}