{
  "type": "Feature",
  "properties": {
    "iso:country":"GB",
    "sg:address":"441 Hornsey Road",
    "sg:city":"London",
    "sg:classifiers":[
        {
            "category":"Building & Trades",
            "subcategory":"Plumbing",
            "type":"Services"
        }
    ],
    "sg:postcode":"N19 4DX",
    "sg:province":"Greater London",
    "sg:tags":[
        "heating"
    ],
    "wof:name":"Probe",
    "wof:placetype":"venue"
},
  "geometry": {"coordinates":[-0.122424,51.567284],"type":"Point"}
}