{
  "type": "Feature",
  "properties": {
    "iso:country":"GB",
    "sg:address":"1-63 John Roll Way, Bermondsey",
    "sg:city":"London",
    "sg:classifiers":[
        {
            "category":"Social Services",
            "subcategory":"Adult Care",
            "type":"Services"
        },
        {
            "category":"Government",
            "subcategory":"Office",
            "type":"Public Place"
        }
    ],
    "sg:phone":"+44 20 7231 7370",
    "sg:postcode":"SE16 4SP",
    "sg:province":"Greater London",
    "sg:tags":[
        "housing",
        "local",
        "sheltered"
    ],
    "wof:name":"Keetons Sheltered Housing",
    "wof:placetype":"venue"
},
  "geometry": {"coordinates":[-0.063491,51.49752],"type":"Point"}
}