{
  "type": "Feature",
  "properties": {
    "addr:full":"Thames Boat Houses, Mill Lane, Hurley Maidenhead Berkshire SL6 5ND",
    "addr:postcode":"sl6 5nd",
    "addr:street":"Mill Lane",
    "iso:country":"GB",
    "sg:address":"Thames Boat Houses, Mill Lane, Hurley",
    "sg:city":"Maidenhead",
    "sg:classifiers":[
        {
            "category":"Autos & Motor Vehicles",
            "subcategory":"Boat Sales",
            "type":"Retail Goods"
        }
    ],
    "sg:phone":"+44 1628 824382",
    "sg:postcode":"SL6 5ND",
    "sg:province":"Berkshire",
    "sg:tags":[
        "repair",
        "builder"
    ],
    "wof:name":"Peter Freebody & Co",
    "wof:placetype":"venue"
},
  "geometry": {"coordinates":[-0.8103219867,51.5408287048],"type":"Point"}
}