{
  "type": "Feature",
  "properties": {
    "addr:full":"Red Shute Mill, Hermitage Newbury Berkshire RG18 9QU",
    "addr:postcode":"rg18 9qu",
    "addr:street":"Newbury",
    "iso:country":"GB",
    "sg:address":"Red Shute Mill, Hermitage",
    "sg:city":"Newbury",
    "sg:classifiers":[
        {
            "category":"Farming",
            "subcategory":"Farm",
            "type":"Manufacturing & Wholesale Goods"
        }
    ],
    "sg:phone":"+44 1962 777687",
    "sg:postcode":"RG18 9QU",
    "sg:province":"Berkshire",
    "sg:tags":[
        "mixed",
        "crop"
    ],
    "wof:name":"S O Y L Ltd",
    "wof:placetype":"venue"
},
  "geometry": {"coordinates":[-1.271127,51.454067],"type":"Point"}
}