{
  "type": "Feature",
  "properties": {
    "addr:full":"424 Well Hall Road London Greater London SE9 6UD",
    "addr:housenumber":"424",
    "addr:postcode":"se9 6ud",
    "addr:street":"Well Hall Road",
    "iso:country":"GB",
    "sg:address":"424 Well Hall Road",
    "sg:city":"London",
    "sg:classifiers":[
        {
            "category":"Fast Food",
            "type":"Food & Drink"
        }
    ],
    "sg:phone":"+44 20 8856 3636",
    "sg:postcode":"SE9 6UD",
    "sg:province":"Greater London",
    "sg:tags":[
        "away",
        "meal",
        "outlet",
        "take"
    ],
    "wof:name":"The Bamboo Garden",
    "wof:placetype":"venue"
},
  "geometry": {"coordinates":[0.0529199988,51.4670791626],"type":"Point"}
}