{
  "type": "Feature",
  "properties": {
    "addr:full":"81 Yorkshire St Oldham Lancashire OL1 3ST",
    "addr:housenumber":"81",
    "addr:postcode":"ol1 3st",
    "addr:street":"Yorkshire St",
    "iso:country":"GB",
    "sg:address":"81 Yorkshire St",
    "sg:city":"Oldham",
    "sg:classifiers":[
        {
            "category":"Retail",
            "subcategory":"Driving School",
            "type":"Services"
        }
    ],
    "sg:postcode":"OL1 3ST",
    "sg:province":"Lancashire",
    "wof:name":"British School of Motoring Ltd (The)",
    "wof:placetype":"venue"
},
  "geometry": {"coordinates":[-2.1078219414,53.5423851013],"type":"Point"}
}