{
  "type": "Feature",
  "properties": {
    "iso:country":"GB",
    "sg:address":"68 Bensham Manor Road",
    "sg:city":"Thornton Heath",
    "sg:classifiers":[
        {
            "category":"Building & Trades",
            "subcategory":"Cleaning & Sanitation",
            "type":"Services"
        }
    ],
    "sg:phone":"+44 20 8683 0606",
    "sg:postcode":"CR7 7AB",
    "sg:province":"Surrey",
    "sg:tags":[
        "cleaner",
        "upholstery",
        "commercial",
        "carpet"
    ],
    "wof:name":"Academy Cleaning Services",
    "wof:placetype":"venue"
},
  "geometry": {"coordinates":[-0.0968319997,51.3957366943],"type":"Point"}
}