{
  "type": "Feature",
  "properties": {
    "iso:country":"GB",
    "sg:address":"12 Moor View",
    "sg:city":"Torpoint",
    "sg:classifiers":[
        {
            "category":"Building & Trades",
            "subcategory":"Construction",
            "type":"Services"
        }
    ],
    "sg:postcode":"PL11 2LH",
    "sg:province":"Cornwall",
    "sg:tags":[
        "builder"
    ],
    "wof:name":"Paul J Kinsman",
    "wof:placetype":"venue"
},
  "geometry": {"coordinates":[-4.199224,50.376022],"type":"Point"}
}