{
  "type": "Feature",
  "properties": {
    "iso:country":"GB",
    "sg:address":"2 High Street",
    "sg:city":"East Grinstead",
    "sg:classifiers":[
        {
            "category":"Manufacturing",
            "subcategory":"Aerospace",
            "type":"Manufacturing & Wholesale Goods"
        }
    ],
    "sg:phone":"+44 1342 305000",
    "sg:postcode":"RH19 3AW",
    "sg:province":"East Sussex",
    "sg:tags":[
        "aircraft",
        "furnishing",
        "fitting"
    ],
    "wof:name":"Michian Ltd.",
    "wof:placetype":"venue"
},
  "geometry": {"coordinates":[-0.008078,51.123962],"type":"Point"}
}