{
  "type": "Feature",
  "properties": {
    "addr:full":"Ashford Lodge, Sudbury Road Halstead Essex CO9 2RR",
    "addr:postcode":"co9 2rr",
    "addr:street":"Sudbury Road",
    "iso:country":"GB",
    "sg:address":"Ashford Lodge, Sudbury Road",
    "sg:city":"Halstead",
    "sg:classifiers":[
        {
            "category":"Professional",
            "subcategory":"Business Services",
            "type":"Services"
        }
    ],
    "sg:phone":"+44 1787 479200",
    "sg:postcode":"CO9 2RR",
    "sg:province":"Essex",
    "sg:tags":[
        "trade"
    ],
    "wof:name":"Essex Agricultural Society",
    "wof:placetype":"venue"
},
  "geometry": {"coordinates":[0.6358249784,51.9439964294],"type":"Point"}
}