{
  "type": "Feature",
  "properties": {
    "iso:country":"GB",
    "sg:address":"Unit 16 Penmaen Industrial Estate, Pontllanfraith",
    "sg:city":"Blackwood",
    "sg:classifiers":[
        {
            "category":"Cafe",
            "type":"Food & Drink"
        }
    ],
    "sg:postcode":"NP12 2DQ",
    "sg:province":"Caerphilly",
    "sg:tags":[
        "tea",
        "room"
    ],
    "wof:name":"Penmaen Cafe",
    "wof:placetype":"venue"
},
  "geometry": {"coordinates":[-3.185114,51.658642],"type":"Point"}
}