{
  "type": "Feature",
  "properties": {
    "addr:full":"Landford Common Farm, New Road Salisbury Dorset SP5 2AZ",
    "addr:postcode":"sp5 2az",
    "addr:street":"Landford;New Road",
    "iso:country":"GB",
    "sg:address":"Landford Common Farm, New Road",
    "sg:city":"Salisbury",
    "sg:classifiers":[
        {
            "category":"Wholesale",
            "subcategory":"Metals & Minerals",
            "type":"Manufacturing & Wholesale Goods"
        }
    ],
    "sg:phone":"+44 1794 324323",
    "sg:postcode":"SP5 2AZ",
    "sg:province":"Dorset",
    "sg:tags":[
        "aluminium",
        "stockholder"
    ],
    "wof:name":"Wyatt Metal Services Ltd.",
    "wof:placetype":"venue"
},
  "geometry": {"coordinates":[-1.7176309824,50.9928588867],"type":"Point"}
}