{
  "type": "Feature",
  "properties": {
    "iso:country":"GB",
    "sg:address":"360 Manford Way",
    "sg:city":"Chigwell",
    "sg:classifiers":[
        {
            "category":"Food & Beverages",
            "subcategory":"Supermarket",
            "type":"Retail Goods"
        }
    ],
    "sg:phone":"+44 20 8500 7921",
    "sg:postcode":"IG7 4AJ",
    "sg:province":"Essex",
    "wof:name":"Supermarket",
    "wof:placetype":"venue"
},
  "geometry": {"coordinates":[0.114801,51.612473],"type":"Point"}
}