{
  "type": "Feature",
  "properties": {
    "addr:full":"37 Kellaway Avenue Bristol City of Bristol BS6 7XS",
    "addr:housenumber":"37",
    "addr:postcode":"bs6 7xs",
    "addr:street":"Kellaway Avenue",
    "iso:country":"GB",
    "sg:address":"37 Kellaway Avenue",
    "sg:city":"Bristol",
    "sg:classifiers":[
        {
            "category":"Health Services",
            "subcategory":"Dentist",
            "type":"Services"
        }
    ],
    "sg:phone":"+44 117 942 3098",
    "sg:postcode":"BS6 7XS",
    "sg:province":"City of Bristol",
    "wof:name":"A J Collier",
    "wof:placetype":"venue"
},
  "geometry": {"coordinates":[-2.6028029919,51.4821014404],"type":"Point"}
}