{
  "type": "Feature",
  "properties": {
    "addr:full":"Redlam Blackburn Lancashire BB2 1UW",
    "addr:postcode":"bb2 1uw",
    "addr:street":"Redlam",
    "iso:country":"GB",
    "sg:address":"Redlam",
    "sg:city":"Blackburn",
    "sg:classifiers":[
        {
            "category":"Government",
            "subcategory":"Post Office",
            "type":"Public Place"
        }
    ],
    "sg:phone":"+44 1254 580553",
    "sg:postcode":"BB2 1UW",
    "sg:province":"Lancashire",
    "wof:name":"Witton Post Office",
    "wof:placetype":"venue"
},
  "geometry": {"coordinates":[-2.503801,53.742462],"type":"Point"}
}