{
  "type": "Feature",
  "properties": {
    "addr:full":"Severn Bank Farm, Elmore Back, Elmore Gloucester Gloucestershire GL2 3ST",
    "addr:housenumber":"elmore",
    "addr:postcode":"gl2 3st",
    "addr:street":"Back Elmore",
    "iso:country":"GB",
    "sg:address":"Severn Bank Farm, Elmore Back, Elmore",
    "sg:city":"Gloucester",
    "sg:classifiers":[
        {
            "category":"Farming",
            "subcategory":"Farm",
            "type":"Manufacturing & Wholesale Goods"
        }
    ],
    "sg:phone":"+44 1452 750233",
    "sg:postcode":"GL2 3ST",
    "sg:province":"Gloucestershire",
    "sg:tags":[
        "mixed",
        "crop"
    ],
    "wof:name":"Graham Lovell",
    "wof:placetype":"venue"
},
  "geometry": {"coordinates":[-2.311565,51.834454],"type":"Point"}
}