{
  "type": "Feature",
  "properties": {
    "addr:full":"Charlton House, Chester Road, Old Trafford Manchester Cheshire M16 0GW",
    "addr:postcode":"m16 0gw",
    "addr:street":"Chester Road",
    "iso:country":"GB",
    "sg:address":"Charlton House, Chester Road, Old Trafford",
    "sg:city":"Manchester",
    "sg:classifiers":[
        {
            "category":"Professional",
            "subcategory":"Business Services",
            "type":"Services"
        }
    ],
    "sg:phone":"+44 161 873 7161",
    "sg:postcode":"M16 0GW",
    "sg:province":"Cheshire",
    "sg:tags":[
        "accomodation"
    ],
    "wof:name":"Business Base",
    "wof:placetype":"venue"
},
  "geometry": {"coordinates":[-2.2874488831,53.4613952637],"type":"Point"}
}