{
  "type": "Feature",
  "properties": {
    "addr:full":"77-87 London Road Dunstable Bedfordshire LU6 3DT",
    "addr:housenumber":"77-87",
    "addr:postcode":"lu6 3dt",
    "addr:street":"London Road",
    "iso:country":"GB",
    "sg:address":"77-87 London Road",
    "sg:city":"Dunstable",
    "sg:classifiers":[
        {
            "category":"Autos & Motor Vehicles",
            "subcategory":"Automobile Sales",
            "type":"Retail Goods"
        }
    ],
    "sg:phone":"+44 870 904 9370",
    "sg:postcode":"LU6 3DT",
    "sg:province":"Bedfordshire",
    "sg:tags":[
        "car"
    ],
    "wof:name":"Trimoco Dunstuble",
    "wof:placetype":"venue"
},
  "geometry": {"coordinates":[-0.508237,51.877556],"type":"Point"}
}