{
  "type": "Feature",
  "properties": {
    "addr:full":"27 Hollow Street, Great Somerford Chippenham Wiltshire SN15 5JD",
    "addr:housenumber":"27",
    "addr:postcode":"sn15 5jd",
    "addr:street":"Hollow Street",
    "iso:country":"GB",
    "sg:address":"27 Hollow Street, Great Somerford",
    "sg:city":"Chippenham",
    "sg:classifiers":[
        {
            "category":"Autos & Motor Vehicles",
            "subcategory":"Motorcycle Sales",
            "type":"Retail Goods"
        }
    ],
    "sg:postcode":"SN15 5JD",
    "sg:province":"Wiltshire",
    "sg:tags":[
        "chauffeur",
        "driven",
        "car"
    ],
    "wof:name":"Elite Chauffering",
    "wof:placetype":"venue"
},
  "geometry": {"coordinates":[-2.059192,51.544708],"type":"Point"}
}