{
  "type": "Feature",
  "properties": {
    "addr:full":"Oak Cottage, Coombe Lane Wadhurst East Sussex TN5 6NU",
    "addr:postcode":"tn5 6nu",
    "addr:street":"Coombe Lane",
    "iso:country":"GB",
    "sg:address":"Oak Cottage, Coombe Lane",
    "sg:city":"Wadhurst",
    "sg:classifiers":[
        {
            "category":"Building & Trades",
            "subcategory":"Construction",
            "type":"Services"
        }
    ],
    "sg:phone":"+44 1892 783633",
    "sg:postcode":"TN5 6NU",
    "sg:province":"East Sussex",
    "sg:tags":[
        "demolition",
        "contractor"
    ],
    "wof:name":"Highoaks",
    "wof:placetype":"venue"
},
  "geometry": {"coordinates":[0.339718014,51.0620079041],"type":"Point"}
}