{
  "type": "Feature",
  "properties": {
    "iso:country":"GB",
    "sg:address":"Station Yard, Station Road, Bluntisham",
    "sg:city":"Huntingdon",
    "sg:classifiers":[
        {
            "category":"Professional",
            "subcategory":"Engineering",
            "type":"Services"
        }
    ],
    "sg:phone":"+44 1487 843031",
    "sg:postcode":"PE28 3PA",
    "sg:province":"Bedfordshire",
    "sg:tags":[
        "agricultural",
        "engineer"
    ],
    "wof:name":"Woodfield",
    "wof:placetype":"venue"
},
  "geometry": {"coordinates":[0.005885,52.350574],"type":"Point"}
}