{
  "type": "Feature",
  "properties": {
    "iso:country":"GB",
    "sg:address":"29g The Grove",
    "sg:city":"Westerham",
    "sg:classifiers":[
        {
            "category":"Building & Trades",
            "subcategory":"Construction",
            "type":"Services"
        }
    ],
    "sg:phone":"+44 1959 575125",
    "sg:postcode":"TN16 3TA",
    "sg:province":"Kent",
    "sg:tags":[
        "decorator",
        "painter"
    ],
    "wof:name":"R Moss",
    "wof:placetype":"venue"
},
  "geometry": {"coordinates":[0.0350550003,51.3073348999],"type":"Point"}
}