{
  "type": "Feature",
  "properties": {
    "addr:full":"Units 4-5 Ingley Wks 13 River Rd Barking Essex IG11 0HE",
    "addr:housenumber":"units 4-5;13",
    "addr:postcode":"ig11 0he",
    "addr:street":"Ingley Wks;River Rd",
    "iso:country":"GB",
    "sg:address":"Units 4-5 Ingley Wks 13 River Rd",
    "sg:city":"Barking",
    "sg:classifiers":[
        {
            "category":"Manufacturing",
            "subcategory":"Building Materials",
            "type":"Manufacturing & Wholesale Goods"
        }
    ],
    "sg:phone":"+44 181 594 9400",
    "sg:postcode":"IG11 0HE",
    "sg:province":"Essex",
    "sg:tags":[
        "shutter",
        "supp",
        "door"
    ],
    "wof:name":"Advanced Concept Services Ltd",
    "wof:placetype":"venue"
},
  "geometry": {"coordinates":[0.0811149999,51.539100647],"type":"Point"}
}