{
  "type": "Feature",
  "properties": {
    "addr:full":"Blunts Wall Farm, Blunts Wall Road Billericay Essex CM12 9SA",
    "addr:postcode":"cm12 9sa",
    "addr:street":"Blunts Wall;Blunts Wall Road",
    "iso:country":"GB",
    "sg:address":"Blunts Wall Farm, Blunts Wall Road",
    "sg:city":"Billericay",
    "sg:classifiers":[
        {
            "category":"Manufacturing",
            "subcategory":"Metals",
            "type":"Manufacturing & Wholesale Goods"
        }
    ],
    "sg:postcode":"CM12 9SA",
    "sg:province":"Essex",
    "sg:tags":[
        "steel",
        "fabricator",
        "erectors"
    ],
    "wof:name":"J Oliver Engineering",
    "wof:placetype":"venue"
},
  "geometry": {"coordinates":[0.416855,51.624748],"type":"Point"}
}