{
  "type": "Feature",
  "properties": {
    "addr:full":"20 Stepney Street Llanelli Carmarthenshire SA15 3UR",
    "addr:housenumber":"20",
    "addr:postcode":"sa15 3ur",
    "addr:street":"Stepney Street",
    "iso:country":"GB",
    "sg:address":"20 Stepney Street",
    "sg:city":"Llanelli",
    "sg:classifiers":[
        {
            "category":"Banks & Credit Unions",
            "subcategory":"Bank",
            "type":"Services"
        }
    ],
    "sg:phone":"+44 845 765 4321",
    "sg:postcode":"SA15 3UR",
    "sg:province":"Carmarthenshire",
    "wof:name":"Abbey National Plc",
    "wof:placetype":"venue"
},
  "geometry": {"coordinates":[-4.163073,51.681194],"type":"Point"}
}