{
  "type": "Feature",
  "properties": {
    "addr:full":"1 Manitoba Place Elgin Moray IV30 6TB",
    "addr:housenumber":"1",
    "addr:postcode":"iv30 6tb",
    "addr:street":"Manitoba Place",
    "iso:country":"GB",
    "sg:address":"1 Manitoba Place",
    "sg:city":"Elgin",
    "sg:classifiers":[
        {
            "category":"Professional",
            "type":"Services"
        },
        {
            "category":"Manufacturing",
            "subcategory":"Electronics",
            "type":"Manufacturing & Wholesale Goods"
        }
    ],
    "sg:phone":"+44 1343 542872",
    "sg:postcode":"IV30 6TB",
    "sg:province":"Moray",
    "sg:tags":[
        "control",
        "manufacture",
        "system",
        "panel"
    ],
    "wof:name":"C S Control Systems Ltd.",
    "wof:placetype":"venue"
},
  "geometry": {"coordinates":[-3.29038,57.64006],"type":"Point"}
}