{
  "type": "Feature",
  "properties": {
    "addr:full":"96 Manorfield Ashford Kent TN23 5YP",
    "addr:housenumber":"96",
    "addr:postcode":"tn23 5yp",
    "addr:street":"Manorfield",
    "iso:country":"GB",
    "sg:address":"96 Manorfield",
    "sg:city":"Ashford",
    "sg:classifiers":[
        {
            "category":"Professional",
            "subcategory":"Employment Agencies",
            "type":"Services"
        }
    ],
    "sg:phone":"+44 1233 335107",
    "sg:postcode":"TN23 5YP",
    "sg:province":"Kent",
    "sg:tags":[
        "cv"
    ],
    "wof:name":"C V Service",
    "wof:placetype":"venue"
},
  "geometry": {"coordinates":[0.84666,51.139488],"type":"Point"}
}