{
  "type": "Feature",
  "properties": {
    "addr:full":"23 Green Lane London Greater London SE20 7JX",
    "addr:housenumber":"23",
    "addr:postcode":"se20 7jx",
    "addr:street":"Green Lane",
    "iso:country":"GB",
    "sg:address":"23 Green Lane",
    "sg:city":"London",
    "sg:classifiers":[
        {
            "category":"Wholesale",
            "subcategory":"Scrap",
            "type":"Manufacturing & Wholesale Goods"
        }
    ],
    "sg:phone":"+44 20 8659 0361",
    "sg:postcode":"SE20 7JX",
    "sg:province":"Greater London",
    "sg:tags":[
        "waste",
        "metal"
    ],
    "wof:name":"G H Metal Co",
    "wof:placetype":"venue"
},
  "geometry": {"coordinates":[-0.049976,51.41452],"type":"Point"}
}