{
  "type": "Feature",
  "properties": {
    "iso:country":"GB",
    "sg:address":"4 Will Hall Close",
    "sg:city":"Alton",
    "sg:classifiers":[
        {
            "category":"Professional",
            "type":"Services"
        }
    ],
    "sg:phone":"+44 1420 83613",
    "sg:postcode":"GU34 1QP",
    "sg:province":"Hampshire",
    "sg:tags":[
        "entertainer"
    ],
    "wof:name":"Peter Robinson",
    "wof:placetype":"venue"
},
  "geometry": {"coordinates":[-0.991743,51.146381],"type":"Point"}
}