{
  "type": "Feature",
  "properties": {
    "iso:country":"GB",
    "sg:address":"103 Manor Road",
    "sg:city":"Fleetwood",
    "sg:classifiers":[
        {
            "category":"Personal",
            "subcategory":"Barber",
            "type":"Services"
        }
    ],
    "sg:postcode":"FY7 7HY",
    "sg:province":"Lancashire",
    "sg:tags":[
        "men's",
        "hairdresser"
    ],
    "wof:name":"Guy Dellacorte",
    "wof:placetype":"venue"
},
  "geometry": {"coordinates":[-3.031519,53.922485],"type":"Point"}
}