{
  "type": "Feature",
  "properties": {
    "iso:country":"GB",
    "sg:address":"Unit 3 Peacocks Est, Providence St",
    "sg:city":"Cradley Heath",
    "sg:classifiers":[
        {
            "category":"Building & Trades",
            "subcategory":"Cleaning & Sanitation",
            "type":"Services"
        }
    ],
    "sg:phone":"+44 1384 561542",
    "sg:postcode":"B64 5DG",
    "sg:province":"West Midlands",
    "sg:tags":[
        "commercial"
    ],
    "wof:name":"First Choice Cleaning Services",
    "wof:placetype":"venue"
},
  "geometry": {"coordinates":[-2.081574,52.472416],"type":"Point"}
}