{
  "type": "Feature",
  "properties": {
    "iso:country":"GB",
    "sg:address":"90 St Vincent Street",
    "sg:city":"Glasgow",
    "sg:classifiers":[
        {
            "category":"Professional",
            "subcategory":"Accounting & Tax Preparation",
            "type":"Services"
        }
    ],
    "sg:postcode":"G2 5UB",
    "sg:province":"Glasgow City",
    "sg:tags":[
        "accountant"
    ],
    "wof:name":"Neville Russell",
    "wof:placetype":"venue"
},
  "geometry": {"coordinates":[-4.256659,55.861481],"type":"Point"}
}