{
  "type": "Feature",
  "properties": {
    "addr:full":"130 Main Street, Baillieston Glasgow East Dunbartonshire G69 6AE",
    "addr:housenumber":"130",
    "addr:postcode":"g69 6ae",
    "addr:street":"Main Street",
    "iso:country":"GB",
    "sg:address":"130 Main Street, Baillieston",
    "sg:city":"Glasgow",
    "sg:classifiers":[
        {
            "category":"Shopping",
            "subcategory":"News",
            "type":"Retail Goods"
        }
    ],
    "sg:phone":"+44 141 771 0765",
    "sg:postcode":"G69 6AE",
    "sg:province":"East Dunbartonshire",
    "sg:tags":[
        "newsagent"
    ],
    "wof:name":"Ahmeds Newsagent",
    "wof:placetype":"venue"
},
  "geometry": {"coordinates":[-4.109307766,55.8506660461],"type":"Point"}
}