{
  "type": "Feature",
  "properties": {
    "addr:full":"162 Abbeydale Road South Sheffield South Yorkshire S7 2QS",
    "addr:housenumber":"162",
    "addr:postcode":"s7 2qs",
    "addr:street":"Abbeydale Road South",
    "iso:country":"GB",
    "sg:address":"162 Abbeydale Road South",
    "sg:city":"Sheffield",
    "sg:classifiers":[
        {
            "category":"Home & Garden",
            "subcategory":"Furniture",
            "type":"Retail Goods"
        }
    ],
    "sg:phone":"+44 114 235 1645",
    "sg:postcode":"S7 2QS",
    "sg:province":"South Yorkshire",
    "wof:name":"Deb-E-Tone",
    "wof:placetype":"venue"
},
  "geometry": {"coordinates":[-1.5102039576,53.3364486694],"type":"Point"}
}