{
  "type": "Feature",
  "properties": {
    "addr:full":"8 Commercial Street Camborne Cornwall TR14 8JY",
    "addr:housenumber":"8",
    "addr:postcode":"tr14 8jy",
    "addr:street":"Commercial Street",
    "iso:country":"GB",
    "sg:address":"8 Commercial Street",
    "sg:city":"Camborne",
    "sg:classifiers":[
        {
            "category":"Professional",
            "subcategory":"Accounting & Tax Preparation",
            "type":"Services"
        }
    ],
    "sg:postcode":"TR14 8JY",
    "sg:province":"Cornwall",
    "sg:tags":[
        "accountant"
    ],
    "wof:name":"Briants Chartered Accountants",
    "wof:placetype":"venue"
},
  "geometry": {"coordinates":[-5.300714016,50.2130203247],"type":"Point"}
}