{
  "type": "Feature",
  "properties": {
    "iso:country":"GB",
    "sg:address":"332 High Road, Newton",
    "sg:city":"Wisbech",
    "sg:classifiers":[
        {
            "category":"Government",
            "subcategory":"Post Office",
            "type":"Public Place"
        }
    ],
    "sg:phone":"+44 1945 870201",
    "sg:postcode":"PE13 5HR",
    "sg:province":"Cambridgeshire",
    "wof:name":"Newton Sub Post Office",
    "wof:placetype":"venue"
},
  "geometry": {"coordinates":[0.128304,52.71254],"type":"Point"}
}