{
  "type": "Feature",
  "properties": {
    "iso:country":"GB",
    "sg:address":"17 Commercial Road",
    "sg:city":"Newport",
    "sg:classifiers":[
        {
            "category":"Shopping",
            "subcategory":"Used Merchandise",
            "type":"Retail Goods"
        }
    ],
    "sg:phone":"+44 1633 243788",
    "sg:postcode":"NP20 2PA",
    "sg:province":"Newport",
    "sg:tags":[
        "shop",
        "second-hand"
    ],
    "wof:name":"Kc's",
    "wof:placetype":"venue"
},
  "geometry": {"coordinates":[-2.991523,51.581425],"type":"Point"}
}