{
  "type": "Feature",
  "properties": {
    "addr:full":"Kingsdown Road, St Margarets At Cliffe Dover Kent CT15 6AZ",
    "addr:postcode":"ct15 6az",
    "addr:street":"Kingsdown Road",
    "iso:country":"GB",
    "sg:address":"Kingsdown Road, St Margarets At Cliffe",
    "sg:city":"Dover",
    "sg:classifiers":[
        {
            "category":"Education",
            "subcategory":"Library",
            "type":"Public Place"
        }
    ],
    "sg:phone":"+44 1304 852865",
    "sg:postcode":"CT15 6AZ",
    "sg:province":"Kent",
    "sg:tags":[
        "book"
    ],
    "wof:name":"St Margarets At Cliffe Library",
    "wof:placetype":"venue"
},
  "geometry": {"coordinates":[1.3773679733,51.158996582],"type":"Point"}
}