{
  "type": "Feature",
  "properties": {
    "addr:full":"5 Chester Rd, Anfield Liverpool Merseyside L6 4DY",
    "addr:housenumber":"5",
    "addr:postcode":"l6 4dy",
    "addr:street":"Chester Rd",
    "iso:country":"GB",
    "sg:address":"5 Chester Rd, Anfield",
    "sg:city":"Liverpool",
    "sg:classifiers":[
        {
            "category":"Retail",
            "subcategory":"Auto Repair",
            "type":"Services"
        }
    ],
    "sg:postcode":"L6 4DY",
    "sg:province":"Merseyside",
    "sg:tags":[
        "modification",
        "garage"
    ],
    "wof:name":"Allman,Jim,",
    "wof:placetype":"venue"
},
  "geometry": {"coordinates":[-2.936392,53.424145],"type":"Point"}
}