{
  "type": "Feature",
  "properties": {
    "addr:full":"The Former Rectory, Oundle Road, Woodston Peterborough Cambridgeshire PE2 9PJ",
    "addr:postcode":"pe2 9pj",
    "addr:street":"Oundle Road",
    "iso:country":"GB",
    "sg:address":"The Former Rectory, Oundle Road, Woodston",
    "sg:city":"Peterborough",
    "sg:classifiers":[
        {
            "category":"Farming",
            "subcategory":"Nursery",
            "type":"Manufacturing & Wholesale Goods"
        },
        {
            "category":"Building & Trades",
            "subcategory":"Construction",
            "type":"Services"
        }
    ],
    "sg:phone":"+44 1733 347883",
    "sg:postcode":"PE2 9PJ",
    "sg:province":"Cambridgeshire",
    "sg:tags":[
        "joiner",
        "creche",
        "carpenter"
    ],
    "wof:name":"Bundles of Fun Ltd.",
    "wof:placetype":"venue"
},
  "geometry": {"coordinates":[-0.2515639961,52.5606040955],"type":"Point"}
}