{
  "type": "Feature",
  "properties": {
    "addr:full":"Sandy Ways Farm, Hoscar Moss Road, Lathom Ormskirk Lancashire L40 4BG",
    "addr:postcode":"l40 4bg",
    "addr:street":"Hoscar Moss Road",
    "iso:country":"GB",
    "sg:address":"Sandy Ways Farm, Hoscar Moss Road, Lathom",
    "sg:city":"Ormskirk",
    "sg:classifiers":[
        {
            "category":"Farming",
            "subcategory":"Livestock Farm",
            "type":"Manufacturing & Wholesale Goods"
        }
    ],
    "sg:postcode":"L40 4BG",
    "sg:province":"Lancashire",
    "sg:tags":[
        "others"
    ],
    "wof:name":"R J Gorst",
    "wof:placetype":"venue"
},
  "geometry": {"coordinates":[-2.80666,53.597439],"type":"Point"}
}