{
  "type": "Feature",
  "properties": {
    "addr:full":"28 Kirkgate Bradford West Yorkshire BD1 1QL",
    "addr:housenumber":"28",
    "addr:postcode":"bd1 1ql",
    "addr:street":"Kirkgate Bradford West",
    "iso:country":"GB",
    "sg:address":"28 Kirkgate",
    "sg:city":"Bradford",
    "sg:classifiers":[
        {
            "category":"Bars & Pubs",
            "type":"Food & Drink"
        }
    ],
    "sg:postcode":"BD1 1QL",
    "sg:province":"West Yorkshire",
    "sg:tags":[
        "pubs",
        "inn"
    ],
    "wof:name":"The Shoulder of Mutton",
    "wof:placetype":"venue"
},
  "geometry": {"coordinates":[-1.752452,53.795135],"type":"Point"}
}