{
  "type": "Feature",
  "properties": {
    "addr:full":"203 The Chandlery, 50 Westminster Bridge Rd Southwark Greater London SE1 7QY",
    "addr:housenumber":"203;50",
    "addr:postcode":"se1 7qy",
    "addr:street":"The Chandlery;Westminster Bridge Rd",
    "iso:country":"GB",
    "sg:address":"203 The Chandlery, 50 Westminster Bridge Rd",
    "sg:city":"Southwark",
    "sg:classifiers":[
        {
            "category":"Professional",
            "subcategory":"Art Services",
            "type":"Services"
        }
    ],
    "sg:phone":"+44 20 7721 7419",
    "sg:postcode":"SE1 7QY",
    "sg:province":"Greater London",
    "sg:tags":[
        "consultant",
        "design"
    ],
    "wof:name":"Glenn Hilling",
    "wof:placetype":"venue"
},
  "geometry": {"coordinates":[-0.10865,51.498501],"type":"Point"}
}