{
  "type": "Feature",
  "properties": {
    "addr:full":"8 Premier Avenue Grays Essex RM16 2SD",
    "addr:housenumber":"8",
    "addr:postcode":"rm16 2sd",
    "addr:street":"Premier Avenue",
    "iso:country":"GB",
    "sg:address":"8 Premier Avenue",
    "sg:city":"Grays",
    "sg:classifiers":[
        {
            "category":"Building & Trades",
            "subcategory":"Landscaping Services",
            "type":"Services"
        }
    ],
    "sg:postcode":"RM16 2SD",
    "sg:province":"Essex",
    "sg:tags":[
        "forestry",
        "tree"
    ],
    "wof:name":"A J K Maintenance",
    "wof:placetype":"venue"
},
  "geometry": {"coordinates":[0.339158,51.489693],"type":"Point"}
}