{
  "type": "Feature",
  "properties": {
    "iso:country":"GB",
    "sg:address":"549 Lea Bridge Road, Bakers Arms",
    "sg:city":"London",
    "sg:classifiers":[
        {
            "category":"Home & Garden",
            "subcategory":"Furniture",
            "type":"Retail Goods"
        }
    ],
    "sg:phone":"+44 20 8558 0010",
    "sg:postcode":"E10 7EB",
    "sg:province":"Greater London",
    "wof:name":"The Furniture Depot",
    "wof:placetype":"venue"
},
  "geometry": {"coordinates":[-0.016536,51.572922],"type":"Point"}
}