{
  "type": "Feature",
  "properties": {
    "iso:country":"GB",
    "sg:address":"Whitworth Industrial Estate, Tilton Rd",
    "sg:city":"Birmingham",
    "sg:classifiers":[
        {
            "category":"Communications",
            "subcategory":"Film & Video Production",
            "type":"Services"
        }
    ],
    "sg:phone":"+44 121 771 3138",
    "sg:postcode":"B9 4PP",
    "sg:province":"West Midlands",
    "sg:tags":[
        "mnfr",
        "coating",
        "powder"
    ],
    "wof:name":"Deritend Powder Coatings",
    "wof:placetype":"venue"
},
  "geometry": {"coordinates":[-1.8567169905,52.4807395935],"type":"Point"}
}