{
  "type": "Feature",
  "properties": {
    "iso:country":"GB",
    "sg:address":"16 The Mount",
    "sg:city":"Guildford",
    "sg:classifiers":[
        {
            "category":"Professional",
            "subcategory":"Accounting & Tax Preparation",
            "type":"Services"
        }
    ],
    "sg:phone":"+44 1483 573113",
    "sg:postcode":"GU2 4HS",
    "sg:province":"Surrey",
    "sg:tags":[
        "accountant"
    ],
    "wof:name":"Pridie Brewster",
    "wof:placetype":"venue"
},
  "geometry": {"coordinates":[-0.579304,51.234516],"type":"Point"}
}