{
  "type": "Feature",
  "properties": {
    "iso:country":"GB",
    "sg:address":"41 Bridgford Road, West Bridgford",
    "sg:city":"Nottingham",
    "sg:classifiers":[
        {
            "category":"Farming",
            "subcategory":"Nursery",
            "type":"Manufacturing & Wholesale Goods"
        }
    ],
    "sg:phone":"+44 115 981 0119",
    "sg:postcode":"NG2 6AU",
    "sg:province":"Nottinghamshire",
    "sg:tags":[
        "creche"
    ],
    "wof:name":"White House Day Nursery",
    "wof:placetype":"venue"
},
  "geometry": {"coordinates":[-1.1277879477,52.9319648743],"type":"Point"}
}