{
  "type": "Feature",
  "properties": {
    "iso:country":"GB",
    "sg:address":"43 The Square, Spencers Wood",
    "sg:city":"Reading",
    "sg:classifiers":[
        {
            "category":"Professional",
            "subcategory":"Business Services",
            "type":"Services"
        },
        {
            "category":"Professional",
            "subcategory":"Art Services",
            "type":"Services"
        }
    ],
    "sg:phone":"+44 118 988 6866",
    "sg:postcode":"RG7 1BS",
    "sg:province":"Berkshire",
    "sg:tags":[
        "consultant",
        "planning",
        "design"
    ],
    "wof:name":"THE HARMSEN GROUP LTD",
    "wof:placetype":"venue"
},
  "geometry": {"coordinates":[-0.971539,51.394829],"type":"Point"}
}