{
  "type": "Feature",
  "properties": {
    "addr:full":"135 Cheswick Drive Newcastle-upon-tyne Tyne and Wear NE3 5DS",
    "addr:housenumber":"135",
    "addr:postcode":"ne3 5ds",
    "addr:street":"Cheswick Drive",
    "iso:country":"GB",
    "sg:address":"135 Cheswick Drive",
    "sg:city":"Newcastle-upon-tyne",
    "sg:classifiers":[
        {
            "category":"Building & Trades",
            "subcategory":"Construction",
            "type":"Services"
        }
    ],
    "sg:phone":"+44 191 284 1262",
    "sg:postcode":"NE3 5DS",
    "sg:province":"Tyne and Wear",
    "sg:tags":[
        "roofing",
        "contracting"
    ],
    "wof:name":"Dougall Roofing Contractors Ltd.",
    "wof:placetype":"venue"
},
  "geometry": {"coordinates":[-1.610348,55.012333],"type":"Point"}
}