{
  "type": "Feature",
  "properties": {
    "iso:country":"GB",
    "sg:address":"2 Riverton Road, Puriton",
    "sg:city":"Bridgwater",
    "sg:classifiers":[
        {
            "category":"Food & Beverages",
            "subcategory":"Groceries & Convenience Stores",
            "type":"Retail Goods"
        }
    ],
    "sg:phone":"+44 1278 683218",
    "sg:postcode":"TA7 8BW",
    "sg:province":"Somerset",
    "wof:name":"Corner Stores",
    "wof:placetype":"venue"
},
  "geometry": {"coordinates":[-2.9734170437,51.1692733765],"type":"Point"}
}