{
  "type": "Feature",
  "properties": {
    "addr:full":"769 Whalley New Road Blackburn Lancashire BB1 9BE",
    "addr:housenumber":"769",
    "addr:postcode":"bb1 9be",
    "addr:street":"Whalley New Road",
    "iso:country":"GB",
    "sg:address":"769 Whalley New Road",
    "sg:city":"Blackburn",
    "sg:classifiers":[
        {
            "category":"Personal",
            "subcategory":"Beauty Salon",
            "type":"Services"
        }
    ],
    "sg:phone":"+44 1254 247662",
    "sg:postcode":"BB1 9BE",
    "sg:province":"Lancashire",
    "sg:tags":[
        "unisex",
        "hairdresser"
    ],
    "wof:name":"Enigma",
    "wof:placetype":"venue"
},
  "geometry": {"coordinates":[-2.477933,53.778465],"type":"Point"}
}