{
  "type": "Feature",
  "properties": {
    "addr:full":"41 Bisley Rd Stroud Gloucestershire GL5 1HF",
    "addr:housenumber":"41",
    "addr:postcode":"gl5 1hf",
    "addr:street":"Bisley Rd",
    "iso:country":"GB",
    "sg:address":"41 Bisley Rd",
    "sg:city":"Stroud",
    "sg:classifiers":[
        {
            "category":"Professional",
            "subcategory":"Advertising",
            "type":"Services"
        }
    ],
    "sg:phone":"+44 1453 768555",
    "sg:postcode":"GL5 1HF",
    "sg:province":"Gloucestershire",
    "sg:tags":[
        "agency"
    ],
    "wof:name":"Future Ideas",
    "wof:placetype":"venue"
},
  "geometry": {"coordinates":[-2.205370903,51.7436752319],"type":"Point"}
}