{
  "type": "Feature",
  "properties": {
    "iso:country":"GB",
    "sg:address":"64 Alma Rd, Clifton",
    "sg:city":"Bristol",
    "sg:classifiers":[
        {
            "category":"Building & Trades",
            "subcategory":"Construction",
            "type":"Services"
        }
    ],
    "sg:phone":"+44 117 946 7312",
    "sg:postcode":"BS8 2DJ",
    "sg:province":"City of Bristol",
    "sg:tags":[
        "builder"
    ],
    "wof:name":"Powerplus Building Services Ltd",
    "wof:placetype":"venue"
},
  "geometry": {"coordinates":[-2.610603,51.462933],"type":"Point"}
}