{
  "type": "Feature",
  "properties": {
    "iso:country":"GB",
    "sg:address":"51 High St",
    "sg:city":"Billericay",
    "sg:classifiers":[
        {
            "category":"Building & Trades",
            "subcategory":"Construction",
            "type":"Services"
        }
    ],
    "sg:postcode":"CM12 9AX",
    "sg:province":"Essex",
    "sg:tags":[
        "heating",
        "contractor"
    ],
    "wof:name":"Southgate Heating Contractors",
    "wof:placetype":"venue"
},
  "geometry": {"coordinates":[0.4182550013,51.6265602112],"type":"Point"}
}