{
  "type": "Feature",
  "properties": {
    "iso:country":"GB",
    "sg:address":"8 St Michaels Square",
    "sg:city":"Southampton",
    "sg:classifiers":[
        {
            "category":"Shopping",
            "subcategory":"Bicycles & Sporting Goods",
            "type":"Retail Goods"
        }
    ],
    "sg:phone":"+44 23 8022 4667",
    "sg:postcode":"SO14 2LD",
    "sg:province":"Hampshire",
    "sg:tags":[
        "equipment",
        "marine",
        "supply"
    ],
    "wof:name":"Montague Smith Ltd.",
    "wof:placetype":"venue"
},
  "geometry": {"coordinates":[-1.404502,50.899647],"type":"Point"}
}