{
  "type": "Feature",
  "properties": {
    "addr:full":"38/39 Havelock Street Swindon Wiltshire SN1 1SD",
    "addr:housenumber":"38 / 39",
    "addr:postcode":"sn1 1sd",
    "addr:street":"Havelock Street",
    "iso:country":"GB",
    "sg:address":"38/39 Havelock Street",
    "sg:city":"Swindon",
    "sg:classifiers":[
        {
            "category":"Shopping",
            "subcategory":"Hobbies, Toys, & Games",
            "type":"Retail Goods"
        },
        {
            "category":"Professional",
            "subcategory":"Computer Services",
            "type":"Services"
        }
    ],
    "sg:postcode":"SN1 1SD",
    "sg:province":"Wiltshire",
    "sg:tags":[
        "system",
        "software"
    ],
    "wof:name":"Next Generation Computers",
    "wof:placetype":"venue"
},
  "geometry": {"coordinates":[-1.7853989601,51.559135437],"type":"Point"}
}