{
  "type": "Feature",
  "properties": {
    "iso:country":"GB",
    "sg:address":"Unit 18 Jarvis St",
    "sg:city":"Leicester",
    "sg:classifiers":[
        {
            "category":"Building & Trades",
            "subcategory":"Construction",
            "type":"Services"
        }
    ],
    "sg:phone":"+44 116 253 2666",
    "sg:postcode":"LE3 5BN",
    "sg:province":"Leicestershire",
    "sg:tags":[
        "contractor",
        "paving",
        "driveway"
    ],
    "wof:name":"Countywide Paving",
    "wof:placetype":"venue"
},
  "geometry": {"coordinates":[-1.1425620317,52.6383552551],"type":"Point"}
}