{
  "type": "Feature",
  "properties": {
    "iso:country":"GB",
    "sg:address":"6 Enterprise Way",
    "sg:city":"Whitby",
    "sg:classifiers":[
        {
            "category":"Shopping",
            "subcategory":"Crafts & Fabrics",
            "type":"Retail Goods"
        }
    ],
    "sg:postcode":"YO22 4NH",
    "sg:province":"North Yorkshire",
    "sg:tags":[
        "material",
        "art"
    ],
    "wof:name":"B W H Design",
    "wof:placetype":"venue"
},
  "geometry": {"coordinates":[-0.594859,54.469021],"type":"Point"}
}