{
  "type": "Feature",
  "properties": {
    "addr:full":"11-13 Ebury Bridge Road London Greater London SW1W 8QX",
    "addr:housenumber":"11-13",
    "addr:postcode":"sw1w 8qx",
    "addr:street":"Ebury Bridge Road",
    "iso:country":"GB",
    "sg:address":"11-13 Ebury Bridge Road",
    "sg:city":"London",
    "sg:classifiers":[
        {
            "category":"Cafe",
            "type":"Food & Drink"
        }
    ],
    "sg:phone":"+44 20 7730 3741",
    "sg:postcode":"SW1W 8QX",
    "sg:province":"Greater London",
    "sg:tags":[
        "tea",
        "room"
    ],
    "wof:name":"Ideal Cafe",
    "wof:placetype":"venue"
},
  "geometry": {"coordinates":[-0.1499529928,51.4904670715],"type":"Point"}
}