{
  "type": "Feature",
  "properties": {
    "iso:country":"GB",
    "sg:address":"Square & Compass Filling Station, Mathley",
    "sg:city":"Haverfordwest",
    "sg:classifiers":[
        {
            "category":"Autos & Motor Vehicles",
            "subcategory":"Fuel & Gas Station",
            "type":"Retail Goods"
        }
    ],
    "sg:postcode":"SA62 5JJ",
    "sg:province":"Pembrokeshire",
    "sg:tags":[
        "petrol",
        "filling"
    ],
    "wof:name":"The Autohouse",
    "wof:placetype":"venue"
},
  "geometry": {"coordinates":[-5.12737,51.938351],"type":"Point"}
}