{
  "type": "Feature",
  "properties": {
    "iso:country":"GB",
    "sg:address":"Southbank Farm",
    "sg:city":"Westhill",
    "sg:classifiers":[
        {
            "category":"Professional",
            "subcategory":"Printing & Photocopies",
            "type":"Services"
        }
    ],
    "sg:phone":"+44 1224 743253",
    "sg:postcode":"AB32 6YL",
    "sg:province":"Aberdeen City",
    "sg:tags":[
        "plate",
        "lithographic",
        "maker"
    ],
    "wof:name":"Farmhouse Printers",
    "wof:placetype":"venue"
},
  "geometry": {"coordinates":[-2.2926840782,57.1494445801],"type":"Point"}
}