{
  "type": "Feature",
  "properties": {
    "iso:country":"GB",
    "sg:address":"Fir Gro",
    "sg:city":"Macclesfield",
    "sg:classifiers":[
        {
            "category":"Education",
            "subcategory":"School",
            "type":"Public Place"
        },
        {
            "category":"Government",
            "subcategory":"Office",
            "type":"Public Place"
        }
    ],
    "sg:phone":"+44 1625 427371",
    "sg:postcode":"SK11 7SF",
    "sg:province":"Cheshire",
    "sg:tags":[
        "local",
        "authority"
    ],
    "wof:name":"Cheshire County Council",
    "wof:placetype":"venue"
},
  "geometry": {"coordinates":[-2.128759,53.247639],"type":"Point"}
}