{
  "type": "Feature",
  "properties": {
    "addr:full":"Oakcliffe House, Woodcroft Chepstow Gloucestershire NP16 7HY",
    "addr:postcode":"np16 7hy",
    "addr:street":"Woodcroft",
    "iso:country":"GB",
    "sg:address":"Oakcliffe House, Woodcroft",
    "sg:city":"Chepstow",
    "sg:classifiers":[
        {
            "category":"Building & Trades",
            "subcategory":"Landscaping Services",
            "type":"Services"
        }
    ],
    "sg:postcode":"NP16 7HY",
    "sg:province":"Gloucestershire",
    "sg:tags":[
        "landscape",
        "contractor"
    ],
    "wof:name":"R J Allbutt & Son",
    "wof:placetype":"venue"
},
  "geometry": {"coordinates":[-2.661929,51.658684],"type":"Point"}
}