{
  "type": "Feature",
  "properties": {
    "addr:full":"Parkey Farm, Cross Lanes Wrexham Wrexham LL13 0UA",
    "addr:postcode":"ll13 0ua",
    "addr:street":"Lanes",
    "iso:country":"GB",
    "sg:address":"Parkey Farm, Cross Lanes",
    "sg:city":"Wrexham",
    "sg:classifiers":[
        {
            "category":"Farming",
            "subcategory":"Livestock Farm",
            "type":"Manufacturing & Wholesale Goods"
        }
    ],
    "sg:phone":"+44 1978 780263",
    "sg:postcode":"LL13 0UA",
    "sg:province":"Wrexham",
    "sg:tags":[
        "others"
    ],
    "wof:name":"G N Jones",
    "wof:placetype":"venue"
},
  "geometry": {"coordinates":[-2.9315650463,53.0164680481],"type":"Point"}
}