{
  "type": "Feature",
  "properties": {
    "iso:country":"GB",
    "sg:address":"90 High St",
    "sg:city":"Reading",
    "sg:classifiers":[
        {
            "category":"Home & Garden",
            "subcategory":"Home Furnishings",
            "type":"Retail Goods"
        }
    ],
    "sg:phone":"+44 118 940 1266",
    "sg:postcode":"RG10 8DE",
    "sg:province":"Berkshire",
    "sg:tags":[
        "furnishers",
        "planner",
        "kitchen"
    ],
    "wof:name":"Important Kitchens",
    "wof:placetype":"venue"
},
  "geometry": {"coordinates":[-0.870437,51.500042],"type":"Point"}
}