{
  "type": "Feature",
  "properties": {
    "addr:full":"38 Craigens Road Cumnock East Ayrshire KA18 3AW",
    "addr:housenumber":"38",
    "addr:postcode":"ka18 3aw",
    "addr:street":"Craigens Road",
    "iso:country":"GB",
    "sg:address":"38 Craigens Road",
    "sg:city":"Cumnock",
    "sg:classifiers":[
        {
            "category":"Shopping",
            "subcategory":"Department Store",
            "type":"Retail Goods"
        }
    ],
    "sg:phone":"+44 1290 420303",
    "sg:postcode":"KA18 3AW",
    "sg:province":"East Ayrshire",
    "wof:name":"Netherthird Bargain Store",
    "wof:placetype":"venue"
},
  "geometry": {"coordinates":[-4.2504558563,55.4414710999],"type":"Point"}
}