{
  "type": "Feature",
  "properties": {
    "addr:full":"60 Picksley Cres Grimsby Lincolnshire DN36 5YE",
    "addr:housenumber":"60",
    "addr:postcode":"dn36 5ye",
    "addr:street":"Picksley Cres",
    "iso:country":"GB",
    "sg:address":"60 Picksley Cres",
    "sg:city":"Grimsby",
    "sg:classifiers":[
        {
            "category":"Building & Trades",
            "subcategory":"Construction",
            "type":"Services"
        }
    ],
    "sg:phone":"+44 1472 827138",
    "sg:postcode":"DN36 5YE",
    "sg:province":"Lincolnshire",
    "sg:tags":[
        "builder"
    ],
    "wof:name":"J Gates",
    "wof:placetype":"venue"
},
  "geometry": {"coordinates":[-0.057909,53.502174],"type":"Point"}
}