{
  "type": "Feature",
  "properties": {
    "addr:full":"Jacksons Holdings, Church Lane Leyburn North Yorkshire DL8 5NA",
    "addr:postcode":"dl8 5na",
    "addr:street":"Church Lane",
    "iso:country":"GB",
    "sg:address":"Jacksons Holdings, Church Lane",
    "sg:city":"Leyburn",
    "sg:classifiers":[
        {
            "category":"Freight",
            "type":"Transportation"
        }
    ],
    "sg:phone":"+44 1677 450411",
    "sg:postcode":"DL8 5NA",
    "sg:province":"North Yorkshire",
    "sg:tags":[
        "haulage",
        "road"
    ],
    "wof:name":"Ian Weatherhill",
    "wof:placetype":"venue"
},
  "geometry": {"coordinates":[-1.830434,54.310139],"type":"Point"}
}