{
  "type": "Feature",
  "properties": {
    "addr:full":"19 Rathbone Market London Greater London E16 1EH",
    "addr:housenumber":"19",
    "addr:postcode":"e16 1eh",
    "addr:street":"Rathbone Market",
    "iso:country":"GB",
    "sg:address":"19 Rathbone Market",
    "sg:city":"London",
    "sg:classifiers":[
        {
            "category":"Shopping",
            "subcategory":"Florist",
            "type":"Retail Goods"
        }
    ],
    "sg:phone":"+44 20 7511 0002",
    "sg:postcode":"E16 1EH",
    "sg:province":"Greater London",
    "wof:name":"Rathbone Florists",
    "wof:placetype":"venue"
},
  "geometry": {"coordinates":[0.01139,51.515388],"type":"Point"}
}