{
  "type": "Feature",
  "properties": {
    "addr:full":"Aemaford Yard, Mill Street East Dewsbury West Yorkshire WF12 9AQ",
    "addr:postcode":"wf12 9aq",
    "addr:street":"Mill Street East",
    "iso:country":"GB",
    "sg:address":"Aemaford Yard, Mill Street East",
    "sg:city":"Dewsbury",
    "sg:classifiers":[
        {
            "category":"Shopping",
            "subcategory":"Computers & Home Electronics",
            "type":"Retail Goods"
        }
    ],
    "sg:phone":"+44 1924 437773",
    "sg:postcode":"WF12 9AQ",
    "sg:province":"West Yorkshire",
    "wof:name":"Europa Pine",
    "wof:placetype":"venue"
},
  "geometry": {"coordinates":[-1.6346440315,53.6893997192],"type":"Point"}
}