{
  "type": "Feature",
  "properties": {
    "iso:country":"GB",
    "sg:address":"Roman Court, Leverington",
    "sg:city":"Wisbech",
    "sg:classifiers":[
        {
            "category":"Health Services",
            "subcategory":"Nursing And Care Facility",
            "type":"Services"
        },
        {
            "category":"Social Services",
            "subcategory":"Adult Care",
            "type":"Services"
        },
        {
            "category":"Social Services",
            "subcategory":"Retirement Home",
            "type":"Services"
        }
    ],
    "sg:phone":"+44 1945 582686",
    "sg:postcode":"PE13 5BZ",
    "sg:province":"Cambridgeshire",
    "sg:tags":[
        "housing",
        "accommodation",
        "sheltered"
    ],
    "wof:name":"Sheltered Housing Scheme",
    "wof:placetype":"venue"
},
  "geometry": {"coordinates":[0.128665,52.674759],"type":"Point"}
}