{
  "type": "Feature",
  "properties": {
    "iso:country":"GB",
    "sg:address":"The Orchard Surgery, Cope Rd",
    "sg:city":"Banbury",
    "sg:classifiers":[
        {
            "category":"Health Services",
            "subcategory":"Doctor",
            "type":"Services"
        }
    ],
    "sg:phone":"+44 1295 256201",
    "sg:postcode":"OX16 7EZ",
    "sg:province":"Oxfordshire",
    "sg:tags":[
        "practitioners"
    ],
    "wof:name":"Allison, N",
    "wof:placetype":"venue"
},
  "geometry": {"coordinates":[-1.340028,52.061111],"type":"Point"}
}