{
  "type": "Feature",
  "properties": {
    "addr:full":"Swansea Road Merthyr Tydfil Caerphilly CF48 1ES",
    "addr:postcode":"cf48 1es",
    "addr:street":"Swansea Road",
    "iso:country":"GB",
    "sg:address":"Swansea Road",
    "sg:city":"Merthyr Tydfil",
    "sg:classifiers":[
        {
            "category":"Organizations",
            "subcategory":"Membership Organization",
            "type":"Services"
        }
    ],
    "sg:phone":"+44 1685 723885",
    "sg:postcode":"CF48 1ES",
    "sg:province":"Caerphilly",
    "sg:tags":[
        "club"
    ],
    "wof:name":"Gellideg Social & Working Mens Club Ltd",
    "wof:placetype":"venue"
},
  "geometry": {"coordinates":[-3.402587,51.751366],"type":"Point"}
}