{
  "type": "Feature",
  "properties": {
    "addr:full":"Rutledge House, 78 Clarkehouse Road Sheffield South Yorkshire S10 2LJ",
    "addr:housenumber":"78",
    "addr:postcode":"s10 2lj",
    "addr:street":"Clarkehouse Road",
    "iso:country":"GB",
    "sg:address":"Rutledge House, 78 Clarkehouse Road",
    "sg:city":"Sheffield",
    "sg:classifiers":[
        {
            "category":"Professional",
            "subcategory":"Computer Services",
            "type":"Services"
        }
    ],
    "sg:phone":"+44 114 266 8404",
    "sg:postcode":"S10 2LJ",
    "sg:province":"South Yorkshire",
    "sg:tags":[
        "system",
        "software"
    ],
    "wof:name":"Lightwork Design Ltd.",
    "wof:placetype":"venue"
},
  "geometry": {"coordinates":[-1.4989689589,53.3729782104],"type":"Point"}
}