{
  "type": "Feature",
  "properties": {
    "addr:full":"Upper Bank Garage, Bonymaen Swansea Neath Port Talbot SA1 7DB",
    "addr:postcode":"sa1 7db",
    "addr:street":"Upper",
    "iso:country":"GB",
    "sg:address":"Upper Bank Garage, Bonymaen",
    "sg:city":"Swansea",
    "sg:classifiers":[
        {
            "category":"Retail",
            "subcategory":"Auto Repair",
            "type":"Services"
        }
    ],
    "sg:phone":"+44 1792 641298",
    "sg:postcode":"SA1 7DB",
    "sg:province":"Neath Port Talbot",
    "sg:tags":[
        "modification",
        "garage"
    ],
    "wof:name":"Morris Bros of Swansea",
    "wof:placetype":"venue"
},
  "geometry": {"coordinates":[-3.911167,51.642887],"type":"Point"}
}