{
  "type": "Feature",
  "properties": {
    "iso:country":"GB",
    "sg:address":"86 Canal Street",
    "sg:city":"Perth",
    "sg:classifiers":[
        {
            "category":"Personal",
            "type":"Services"
        }
    ],
    "sg:phone":"+44 1738 638089",
    "sg:postcode":"PH2 8HX",
    "sg:province":"Perth and Kinross",
    "sg:tags":[
        "tailor"
    ],
    "wof:name":"Gilbert Ferguson",
    "wof:placetype":"venue"
},
  "geometry": {"coordinates":[-3.432744,56.394344],"type":"Point"}
}