{
  "type": "Feature",
  "properties": {
    "iso:country":"GB",
    "sg:address":"107 Waterloo Road",
    "sg:city":"Uxbridge",
    "sg:classifiers":[
        {
            "category":"Professional",
            "subcategory":"Engineering",
            "type":"Services"
        }
    ],
    "sg:postcode":"UB8 2QY",
    "sg:province":"Buckinghamshire",
    "sg:tags":[
        "contractor",
        "electrical",
        "engineer"
    ],
    "wof:name":"King Electrical",
    "wof:placetype":"venue"
},
  "geometry": {"coordinates":[-0.48645,51.538982],"type":"Point"}
}