{
  "type": "Feature",
  "properties": {
    "addr:full":"343 Muswell Hill Broadway London Greater London N10 1BX",
    "addr:housenumber":"343",
    "addr:postcode":"n10 1bx",
    "addr:street":"Muswell Hill Broadway",
    "iso:country":"GB",
    "sg:address":"343 Muswell Hill Broadway",
    "sg:city":"London",
    "sg:classifiers":[
        {
            "category":"Health Services",
            "subcategory":"Optometrist",
            "type":"Services"
        },
        {
            "category":"Shopping",
            "subcategory":"Optician",
            "type":"Retail Goods"
        }
    ],
    "sg:phone":"+44 20 8883 2183",
    "sg:postcode":"N10 1BX",
    "sg:province":"Greater London",
    "sg:tags":[
        "ophthalmic"
    ],
    "wof:name":"H R Breakspear",
    "wof:placetype":"venue"
},
  "geometry": {"coordinates":[-0.1436190009,51.5926818848],"type":"Point"}
}