{
  "type": "Feature",
  "properties": {
    "addr:full":"Portland Business Centre, Portland Road Irvine North Ayrshire KA12 8JE",
    "addr:postcode":"ka12 8je",
    "addr:street":"Portland Road",
    "iso:country":"GB",
    "sg:address":"Portland Business Centre, Portland Road",
    "sg:city":"Irvine",
    "sg:classifiers":[
        {
            "category":"Real Estate",
            "subcategory":"Architect",
            "type":"Services"
        }
    ],
    "sg:postcode":"KA12 8JE",
    "sg:province":"North Ayrshire",
    "wof:name":"A G M Architects",
    "wof:placetype":"venue"
},
  "geometry": {"coordinates":[-4.673259,55.601974],"type":"Point"}
}