{
  "type": "Feature",
  "properties": {
    "addr:full":"Bangor Road, Benllech Tyn-y-gongl Isle of Anglesey LL74 8TF",
    "addr:postcode":"ll74 8tf",
    "addr:street":"Bangor Road;Tyn-Y-Gongl",
    "iso:country":"GB",
    "sg:address":"Bangor Road, Benllech",
    "sg:city":"Tyn-y-gongl",
    "sg:classifiers":[
        {
            "category":"Health Services",
            "subcategory":"Doctor",
            "type":"Services"
        }
    ],
    "sg:phone":"+44 1248 852122",
    "sg:postcode":"LL74 8TF",
    "sg:province":"Isle of Anglesey",
    "sg:tags":[
        "practitioners"
    ],
    "wof:name":"Gerafon Surgery",
    "wof:placetype":"venue"
},
  "geometry": {"coordinates":[-4.2334518433,53.3216133118],"type":"Point"}
}