{
  "type": "Feature",
  "properties": {
    "addr:full":"210 Park Road Loughborough Leicestershire LE11 2HJ",
    "addr:housenumber":"210",
    "addr:postcode":"le11 2hj",
    "addr:street":"Park Road",
    "iso:country":"GB",
    "sg:address":"210 Park Road",
    "sg:city":"Loughborough",
    "sg:classifiers":[
        {
            "category":"Farming",
            "subcategory":"Fish & Marine Products",
            "type":"Manufacturing & Wholesale Goods"
        },
        {
            "category":"Food & Beverages",
            "subcategory":"Meat & Fish",
            "type":"Retail Goods"
        }
    ],
    "sg:phone":"+44 1509 212369",
    "sg:postcode":"LE11 2HJ",
    "sg:province":"Leicestershire",
    "sg:tags":[
        "fishmonger",
        "butcher"
    ],
    "wof:name":"Eric Oakland",
    "wof:placetype":"venue"
},
  "geometry": {"coordinates":[-1.2070070505,52.7584037781],"type":"Point"}
}