{
  "type": "Feature",
  "properties": {
    "iso:country":"GB",
    "sg:address":"Station Road, Pontnewydd",
    "sg:city":"Cwmbran",
    "sg:classifiers":[
        {
            "category":"Autos & Motor Vehicles",
            "subcategory":"Auto Supplies",
            "type":"Retail Goods"
        }
    ],
    "sg:phone":"+44 1633 484964",
    "sg:postcode":"NP44 1YA",
    "sg:province":"Monmouthshire",
    "sg:tags":[
        "tyre"
    ],
    "wof:name":"Ats L",
    "wof:placetype":"venue"
},
  "geometry": {"coordinates":[-3.025864,51.657467],"type":"Point"}
}