{
  "type": "Feature",
  "properties": {
    "addr:full":"Longman Court, Sketty Close Northampton Northamptonshire NN4 7PL",
    "addr:postcode":"nn4 7pl",
    "addr:street":"Longman Court Sketty Close",
    "iso:country":"GB",
    "sg:address":"Longman Court, Sketty Close",
    "sg:city":"Northampton",
    "sg:classifiers":[
        {
            "category":"Home & Garden",
            "subcategory":"Building Materials",
            "type":"Retail Goods"
        }
    ],
    "sg:postcode":"NN4 7PL",
    "sg:province":"Northamptonshire",
    "sg:tags":[
        "ventilator",
        "ventilation",
        "system"
    ],
    "wof:name":"Fans & Grilles Ltd.",
    "wof:placetype":"venue"
},
  "geometry": {"coordinates":[-0.85867,52.217758],"type":"Point"}
}