{
  "type": "Feature",
  "properties": {
    "addr:full":"Bishopton Road West Stockton-on-tees Durham TS19 0QD",
    "addr:postcode":"ts19 0qd",
    "addr:street":"Bishopton Road West",
    "iso:country":"GB",
    "sg:address":"Bishopton Road West",
    "sg:city":"Stockton-on-tees",
    "sg:classifiers":[
        {
            "category":"Education",
            "subcategory":"School",
            "type":"Public Place"
        }
    ],
    "sg:postcode":"TS19 0QD",
    "sg:province":"Durham",
    "sg:tags":[
        "independent",
        "preparatory"
    ],
    "wof:name":"Stockton Sixth Form College",
    "wof:placetype":"venue"
},
  "geometry": {"coordinates":[-1.340674,54.57148],"type":"Point"}
}