{
  "type": "Feature",
  "properties": {
    "addr:full":"14 George Street Warminster Somerset BA12 8QA",
    "addr:housenumber":"14",
    "addr:postcode":"ba12 8qa",
    "addr:street":"George Street",
    "iso:country":"GB",
    "sg:address":"14 George Street",
    "sg:city":"Warminster",
    "sg:classifiers":[
        {
            "category":"Retail",
            "subcategory":"Portrait Studio",
            "type":"Services"
        },
        {
            "category":"Professional",
            "subcategory":"Art Services",
            "type":"Services"
        }
    ],
    "sg:phone":"+44 1985 213376",
    "sg:postcode":"BA12 8QA",
    "sg:province":"Somerset",
    "sg:tags":[
        "photographer",
        "commercial"
    ],
    "wof:name":"David Wiltshire Photography",
    "wof:placetype":"venue"
},
  "geometry": {"coordinates":[-2.185049057,51.2052688599],"type":"Point"}
}