{
  "type": "Feature",
  "properties": {
    "addr:full":"46 High Street Grantham Lincolnshire NG31 6NE",
    "addr:housenumber":"46",
    "addr:postcode":"ng31 6ne",
    "addr:street":"High Street",
    "iso:country":"GB",
    "sg:address":"46 High Street",
    "sg:city":"Grantham",
    "sg:classifiers":[
        {
            "category":"Communications",
            "subcategory":"Newspaper",
            "type":"Services"
        },
        {
            "category":"Wholesale",
            "subcategory":"Books, Periodicals, & Newspapers",
            "type":"Manufacturing & Wholesale Goods"
        }
    ],
    "sg:phone":"+44 1476 562291",
    "sg:postcode":"NG31 6NE",
    "sg:province":"Lincolnshire",
    "sg:tags":[
        "magazine",
        "publishing"
    ],
    "wof:name":"EAST MIDLANDS BUSINESS NEWS LTD",
    "wof:placetype":"venue"
},
  "geometry": {"coordinates":[-0.6420999765,52.9115829468],"type":"Point"}
}