{
  "type": "Feature",
  "properties": {
    "addr:full":"Buttercrambe Road, Stamford Bridge York East Riding of Yorkshire YO41 1AP",
    "addr:postcode":"yo41 1ap",
    "addr:street":"Buttercrambe Road",
    "iso:country":"GB",
    "sg:address":"Buttercrambe Road, Stamford Bridge",
    "sg:city":"York",
    "sg:classifiers":[
        {
            "category":"Retail",
            "subcategory":"Animal Services",
            "type":"Services"
        }
    ],
    "sg:postcode":"YO41 1AP",
    "sg:province":"East Riding of Yorkshire",
    "sg:tags":[
        "box",
        "horse",
        "transporting"
    ],
    "wof:name":"Woodend Horse Transport",
    "wof:placetype":"venue"
},
  "geometry": {"coordinates":[-0.915788,53.992474],"type":"Point"}
}