{
  "type": "Feature",
  "properties": {
    "addr:full":"Unit 1, 5 Neil Street Renfrew Renfrewshire PA4 8TA",
    "addr:housenumber":"unit;5",
    "addr:postcode":"pa4 8ta",
    "addr:street":"Neil Street",
    "iso:country":"GB",
    "sg:address":"Unit 1, 5 Neil Street",
    "sg:city":"Renfrew",
    "sg:classifiers":[
        {
            "category":"Professional",
            "subcategory":"Printing & Photocopies",
            "type":"Services"
        }
    ],
    "sg:phone":"+44 141 886 2258",
    "sg:postcode":"PA4 8TA",
    "sg:province":"Renfrewshire",
    "sg:tags":[
        "printer"
    ],
    "wof:name":"Gardner Gibson (Print) Ltd.",
    "wof:placetype":"venue"
},
  "geometry": {"coordinates":[-4.388212204,55.8859100342],"type":"Point"}
}