{
  "type": "Feature",
  "properties": {
    "addr:full":"38 High Street Southwold Suffolk IP18 6AE",
    "addr:housenumber":"38",
    "addr:postcode":"ip18 6ae",
    "addr:street":"High Street",
    "iso:country":"GB",
    "sg:address":"38 High Street",
    "sg:city":"Southwold",
    "sg:classifiers":[
        {
            "category":"Farming",
            "subcategory":"Fish & Marine Products",
            "type":"Manufacturing & Wholesale Goods"
        }
    ],
    "sg:postcode":"IP18 6AE",
    "sg:province":"Suffolk",
    "sg:tags":[
        "fishmonger"
    ],
    "wof:name":"Fish & Fayre",
    "wof:placetype":"venue"
},
  "geometry": {"coordinates":[1.676676,52.327782],"type":"Point"}
}