{
  "type": "Feature",
  "properties": {
    "iso:country":"GB",
    "sg:address":"Block 5, Unit 1, Lower Glencairn Street",
    "sg:city":"Kilmarnock",
    "sg:classifiers":[
        {
            "category":"Home & Garden",
            "subcategory":"Home Furnishings",
            "type":"Retail Goods"
        }
    ],
    "sg:phone":"+44 1563 570020",
    "sg:postcode":"KA1 4BD",
    "sg:province":"East Ayrshire",
    "sg:tags":[
        "awning",
        "canopy",
        "blinds"
    ],
    "wof:name":"Allshades",
    "wof:placetype":"venue"
},
  "geometry": {"coordinates":[-4.50973,55.608894],"type":"Point"}
}