{
  "type": "Feature",
  "properties": {
    "addr:full":"17 Greenhill Street Stratford-upon-avon Warwickshire CV37 6LF",
    "addr:housenumber":"17",
    "addr:postcode":"cv37 6lf",
    "addr:street":"Greenhill Street",
    "iso:country":"GB",
    "sg:address":"17 Greenhill Street",
    "sg:city":"Stratford-upon-avon",
    "sg:classifiers":[
        {
            "category":"Professional",
            "subcategory":"Accounting & Tax Preparation",
            "type":"Services"
        }
    ],
    "sg:phone":"+44 1789 269157",
    "sg:postcode":"CV37 6LF",
    "sg:province":"Warwickshire",
    "sg:tags":[
        "accountant"
    ],
    "wof:name":"H P Fisher",
    "wof:placetype":"venue"
},
  "geometry": {"coordinates":[-1.710813,52.193188],"type":"Point"}
}