{
  "type": "Feature",
  "properties": {
    "iso:country":"GB",
    "sg:address":"7a & 7b Bemisters Lane",
    "sg:city":"Gosport",
    "sg:classifiers":[
        {
            "category":"Professional",
            "subcategory":"Computer Services",
            "type":"Services"
        }
    ],
    "sg:phone":"+44 23 9252 1582",
    "sg:postcode":"PO12 1HB",
    "sg:province":"Hampshire",
    "sg:tags":[
        "stationery",
        "system",
        "software"
    ],
    "sg:website":"http://www.gosportcomputerstore.co.uk",
    "wof:name":"Gosport Computer Store",
    "wof:placetype":"venue"
},
  "geometry": {"coordinates":[-1.1206300259,50.7946510315],"type":"Point"}
}