{
  "type": "Feature",
  "properties": {
    "iso:country":"GB",
    "sg:address":"51 Vicarage Rd",
    "sg:city":"Buntingford",
    "sg:classifiers":[
        {
            "category":"Building & Trades",
            "subcategory":"Construction",
            "type":"Services"
        }
    ],
    "sg:phone":"+44 1763 274092",
    "sg:postcode":"SG9 9BB",
    "sg:province":"Hertfordshire",
    "sg:tags":[
        "decorator",
        "painter"
    ],
    "wof:name":"Ms",
    "wof:placetype":"venue"
},
  "geometry": {"coordinates":[-0.018971,51.951546],"type":"Point"}
}