{
  "type": "Feature",
  "properties": {
    "iso:country":"GB",
    "sg:address":"Little Queen Oak, Bourton",
    "sg:city":"Gillingham",
    "sg:classifiers":[
        {
            "category":"Education",
            "subcategory":"University",
            "type":"Public Place"
        }
    ],
    "sg:postcode":"SP8 5AL",
    "sg:province":"Dorset",
    "sg:tags":[
        "higher"
    ],
    "wof:name":"Duo (u K ) Ltd",
    "wof:placetype":"venue"
},
  "geometry": {"coordinates":[-2.3224880695,51.0753898621],"type":"Point"}
}