{
  "type": "Feature",
  "properties": {
    "addr:full":"3 Wordsworth Clo Lichfield Staffordshire WS14 9BY",
    "addr:housenumber":"3",
    "addr:postcode":"ws14 9by",
    "addr:street":"Staffordshire",
    "iso:country":"GB",
    "sg:address":"3 Wordsworth Clo",
    "sg:city":"Lichfield",
    "sg:classifiers":[
        {
            "category":"Retail",
            "subcategory":"Driving School",
            "type":"Services"
        }
    ],
    "sg:phone":"+44 1543 263828",
    "sg:postcode":"WS14 9BY",
    "sg:province":"Staffordshire",
    "wof:name":"Baker School Of Motoring",
    "wof:placetype":"venue"
},
  "geometry": {"coordinates":[-1.8271909952,52.6715164185],"type":"Point"}
}