{
  "type": "Feature",
  "properties": {
    "addr:full":"26 High Street, Linton Cambridge Cambridgeshire CB1 6HS",
    "addr:housenumber":"26",
    "addr:postcode":"cb1 6hs",
    "addr:street":"High Street",
    "iso:country":"GB",
    "sg:address":"26 High Street, Linton",
    "sg:city":"Cambridge",
    "sg:classifiers":[
        {
            "category":"Building & Trades",
            "subcategory":"Landscaping Services",
            "type":"Services"
        }
    ],
    "sg:phone":"+44 1223 890263",
    "sg:postcode":"CB1 6HS",
    "sg:province":"Cambridgeshire",
    "sg:tags":[
        "landscape",
        "contractor"
    ],
    "wof:name":"Alpha Landscapes",
    "wof:placetype":"venue"
},
  "geometry": {"coordinates":[0.316738,52.131924],"type":"Point"}
}