{
  "type": "Feature",
  "properties": {
    "addr:full":"Unit 8, Heaton Street Preston Lancashire PR25 2ZH",
    "addr:housenumber":"unit 8",
    "addr:postcode":"pr25 2zh",
    "addr:street":"Heaton Street",
    "iso:country":"GB",
    "sg:address":"Unit 8, Heaton Street",
    "sg:city":"Preston",
    "sg:classifiers":[
        {
            "category":"Building & Trades",
            "subcategory":"Construction",
            "type":"Services"
        }
    ],
    "sg:phone":"+44 1772 451853",
    "sg:postcode":"PR25 2ZH",
    "sg:province":"Lancashire",
    "sg:tags":[
        "roofing"
    ],
    "wof:name":"New City Roofing",
    "wof:placetype":"venue"
},
  "geometry": {"coordinates":[-2.665675,53.765968],"type":"Point"}
}