{
  "type": "Feature",
  "properties": {
    "addr:full":"159 London Rd Worcester Worcestershire WR5 2EE",
    "addr:housenumber":"159",
    "addr:postcode":"wr5 2ee",
    "addr:street":"London Rd",
    "iso:country":"GB",
    "sg:address":"159 London Rd",
    "sg:city":"Worcester",
    "sg:classifiers":[
        {
            "category":"Shopping",
            "subcategory":"Department Store",
            "type":"Retail Goods"
        }
    ],
    "sg:phone":"+44 1905 360458",
    "sg:postcode":"WR5 2EE",
    "sg:province":"Worcestershire",
    "wof:name":"Pause For Thought",
    "wof:placetype":"venue"
},
  "geometry": {"coordinates":[-2.2045819759,52.1847000122],"type":"Point"}
}