{
  "type": "Feature",
  "properties": {
    "iso:country":"GB",
    "sg:address":"4 Milton Rd",
    "sg:city":"Wimborne",
    "sg:classifiers":[
        {
            "category":"Shopping",
            "subcategory":"Party Supplies",
            "type":"Retail Goods"
        }
    ],
    "sg:phone":"+44 1202 840194",
    "sg:postcode":"BH21 1NY",
    "sg:province":"Dorset",
    "sg:tags":[
        "inflatables",
        "bouncy",
        "castle"
    ],
    "wof:name":"Krazee Kastles",
    "wof:placetype":"venue"
},
  "geometry": {"coordinates":[-1.986236,50.806507],"type":"Point"}
}