{
  "type": "Feature",
  "properties": {
    "addr:full":"202a Devizes Road, Hilperton Trowbridge Wiltshire BA14 7QR",
    "addr:housenumber":"202a",
    "addr:postcode":"ba14 7qr",
    "addr:street":"Devizes Road",
    "iso:country":"GB",
    "sg:address":"202a Devizes Road, Hilperton",
    "sg:city":"Trowbridge",
    "sg:classifiers":[
        {
            "category":"Home & Garden",
            "subcategory":"Home Furnishings",
            "type":"Retail Goods"
        }
    ],
    "sg:phone":"+44 1225 766766",
    "sg:postcode":"BA14 7QR",
    "sg:province":"Wiltshire",
    "sg:tags":[
        "furnishers",
        "planner",
        "kitchen"
    ],
    "wof:name":"Delta Kitchens & Bathrooms Ltd.",
    "wof:placetype":"venue"
},
  "geometry": {"coordinates":[-2.181804,51.330235],"type":"Point"}
}