{
  "type": "Feature",
  "properties": {
    "iso:country":"GB",
    "sg:address":"Lower Menadue Farm",
    "sg:city":"Tintagel",
    "sg:classifiers":[
        {
            "category":"Farming",
            "subcategory":"Livestock Farm",
            "type":"Manufacturing & Wholesale Goods"
        }
    ],
    "sg:phone":"+44 1840 770884",
    "sg:postcode":"PL34 0HR",
    "sg:province":"Cornwall",
    "sg:tags":[
        "others"
    ],
    "wof:name":"R E Bowles",
    "wof:placetype":"venue"
},
  "geometry": {"coordinates":[-4.744604,50.662922],"type":"Point"}
}