{
  "type": "Feature",
  "properties": {
    "iso:country":"GB",
    "sg:address":"Tongue Lane",
    "sg:city":"Leeds",
    "sg:classifiers":[
        {
            "category":"Farming",
            "subcategory":"Nursery",
            "type":"Manufacturing & Wholesale Goods"
        }
    ],
    "sg:phone":"+44 113 295 7677",
    "sg:postcode":"LS6 4QD",
    "sg:province":"West Yorkshire",
    "sg:tags":[
        "creche"
    ],
    "wof:name":"Milestones Private Day Nursery",
    "wof:placetype":"venue"
},
  "geometry": {"coordinates":[-1.560624,53.840115],"type":"Point"}
}