{
  "type": "Feature",
  "properties": {
    "addr:full":"562 Burnley Road Rossendale Lancashire BB4 8NE",
    "addr:housenumber":"562",
    "addr:postcode":"bb4 8ne",
    "addr:street":"Burnley Road",
    "iso:country":"GB",
    "sg:address":"562 Burnley Road",
    "sg:city":"Rossendale",
    "sg:classifiers":[
        {
            "category":"Personal",
            "subcategory":"Beauty Salon",
            "type":"Services"
        }
    ],
    "sg:phone":"+44 1706 226443",
    "sg:postcode":"BB4 8NE",
    "sg:province":"Lancashire",
    "wof:name":"Top to Toe",
    "wof:placetype":"venue"
},
  "geometry": {"coordinates":[-2.287977,53.722866],"type":"Point"}
}