{
  "type": "Feature",
  "properties": {
    "iso:country":"GB",
    "sg:address":"2 Oak Rd",
    "sg:city":"Oldham",
    "sg:classifiers":[
        {
            "category":"Organizations",
            "subcategory":"Non-profit Organization",
            "type":"Services"
        }
    ],
    "sg:phone":"+44 161 684 7475",
    "sg:postcode":"OL8 3UN",
    "sg:province":"Lancashire",
    "sg:tags":[
        "organisation",
        "voluntary",
        "charity"
    ],
    "wof:name":"Tree Of Life Foundation The",
    "wof:placetype":"venue"
},
  "geometry": {"coordinates":[-2.131157,53.520756],"type":"Point"}
}