{
  "type": "Feature",
  "properties": {
    "iso:country":"GB",
    "sg:address":"Alexander Works, Oldbury Road",
    "sg:city":"Smethwick",
    "sg:classifiers":[
        {
            "category":"Professional",
            "subcategory":"Printing & Photocopies",
            "type":"Services"
        }
    ],
    "sg:postcode":"B66 1NH",
    "sg:province":"West Midlands",
    "sg:tags":[
        "embroiderer"
    ],
    "wof:name":"Caterpillar Trading Ltd.",
    "wof:placetype":"venue"
},
  "geometry": {"coordinates":[-1.971184,52.495926],"type":"Point"}
}