{
  "type": "Feature",
  "properties": {
    "addr:full":"Great Southern Road Aberdeen Aberdeen City AB12 5XA",
    "addr:postcode":"ab12 5xa",
    "addr:street":"Great Southern Road",
    "iso:country":"GB",
    "sg:address":"Great Southern Road",
    "sg:city":"Aberdeen",
    "sg:classifiers":[
        {
            "category":"Restaurant",
            "type":"Food & Drink"
        }
    ],
    "sg:phone":"+44 1224 249924",
    "sg:postcode":"AB12 5XA",
    "sg:province":"Aberdeen City",
    "wof:name":"Ghillies Lair Beefeater",
    "wof:placetype":"venue"
},
  "geometry": {"coordinates":[-2.1130290031,57.1247291565],"type":"Point"}
}