{
  "type": "Feature",
  "properties": {
    "addr:full":"32 Thirlstane Terrace Selkirk Scottish Borders TD7 4HX",
    "addr:postcode":"td7 4hx",
    "addr:street":"Thirlstane Terrace",
    "iso:country":"GB",
    "sg:address":"32 Thirlstane Terrace",
    "sg:city":"Selkirk",
    "sg:classifiers":[
        {
            "category":"Arts & Performance",
            "subcategory":"Music",
            "type":"Entertainment"
        }
    ],
    "sg:phone":"+44 1750 22595",
    "sg:postcode":"TD7 4HX",
    "sg:province":"Scottish Borders",
    "sg:tags":[
        "mobile",
        "disco"
    ],
    "wof:name":"Rhythms Disco Hire",
    "wof:placetype":"venue"
},
  "geometry": {"coordinates":[-2.8271210194,55.5333824158],"type":"Point"}
}