{
  "type": "Feature",
  "properties": {
    "addr:full":"Connaught Rd, Brookwood Woking Surrey GU24 0EH",
    "addr:postcode":"gu24 0eh",
    "addr:street":"Connaught Rd",
    "iso:country":"GB",
    "sg:address":"Connaught Rd, Brookwood",
    "sg:city":"Woking",
    "sg:classifiers":[
        {
            "category":"Retail",
            "subcategory":"Car Wash",
            "type":"Services"
        }
    ],
    "sg:postcode":"GU24 0EH",
    "sg:province":"Surrey",
    "sg:tags":[
        "polishing",
        "washing"
    ],
    "wof:name":"Dermott,Max,",
    "wof:placetype":"venue"
},
  "geometry": {"coordinates":[-0.6267020106,51.3052902222],"type":"Point"}
}