{
  "type": "Feature",
  "properties": {
    "iso:country":"GB",
    "sg:address":"Honeysuckle Cottage",
    "sg:city":"Cirencester",
    "sg:classifiers":[
        {
            "category":"Professional",
            "type":"Services"
        }
    ],
    "sg:postcode":"GL7 7AR",
    "sg:province":"Gloucestershire",
    "sg:tags":[
        "caterer"
    ],
    "wof:name":"J J Whitaker",
    "wof:placetype":"venue"
},
  "geometry": {"coordinates":[-1.953541,51.718548],"type":"Point"}
}