{
  "type": "Feature",
  "properties": {
    "addr:full":"Boscean Pottery, St Just Penzance Cornwall TR19 7QP",
    "addr:postcode":"tr19 7qp",
    "iso:country":"GB",
    "sg:address":"Boscean Pottery, St Just",
    "sg:city":"Penzance",
    "sg:classifiers":[
        {
            "category":"Manufacturing",
            "subcategory":"Pottery",
            "type":"Manufacturing & Wholesale Goods"
        }
    ],
    "sg:phone":"+44 1736 787093",
    "sg:postcode":"TR19 7QP",
    "sg:province":"Cornwall",
    "wof:name":"Boscean Pottery",
    "wof:placetype":"venue"
},
  "geometry": {"coordinates":[-5.6908,50.130569],"type":"Point"}
}