{
  "type": "Feature",
  "properties": {
    "addr:full":"53 Brasenose Road Bootle Merseyside L20 8HE",
    "addr:housenumber":"53",
    "addr:postcode":"l20 8he",
    "addr:street":"Brasenose Road",
    "iso:country":"GB",
    "sg:address":"53 Brasenose Road",
    "sg:city":"Bootle",
    "sg:classifiers":[
        {
            "category":"Manufacturing",
            "subcategory":"Metals",
            "type":"Manufacturing & Wholesale Goods"
        },
        {
            "category":"Wholesale",
            "subcategory":"Metals & Minerals",
            "type":"Manufacturing & Wholesale Goods"
        }
    ],
    "sg:phone":"+44 151 933 8370",
    "sg:postcode":"L20 8HE",
    "sg:province":"Merseyside",
    "sg:tags":[
        "fabricator",
        "work",
        "sheet"
    ],
    "wof:name":"Cetax Engineering Ltd.",
    "wof:placetype":"venue"
},
  "geometry": {"coordinates":[-2.995448,53.442726],"type":"Point"}
}