{
  "type": "Feature",
  "properties": {
    "iso:country":"GB",
    "sg:address":"9 High Street",
    "sg:city":"Southampton",
    "sg:classifiers":[
        {
            "category":"Professional",
            "subcategory":"Employment Agencies",
            "type":"Services"
        }
    ],
    "sg:phone":"+44 23 8023 4346",
    "sg:postcode":"SO14 2DH",
    "sg:province":"Hampshire",
    "sg:tags":[
        "consultant"
    ],
    "wof:name":"Reed Insurance",
    "wof:placetype":"venue"
},
  "geometry": {"coordinates":[-1.4039390087,50.9019775391],"type":"Point"}
}