{
  "type": "Feature",
  "properties": {
    "iso:country":"GB",
    "sg:address":"1-7 Denmark Street",
    "sg:city":"Wokingham",
    "sg:classifiers":[
        {
            "category":"Home & Garden",
            "subcategory":"Home Furnishings",
            "type":"Retail Goods"
        },
        {
            "category":"Home & Garden",
            "subcategory":"Building Materials",
            "type":"Retail Goods"
        }
    ],
    "sg:phone":"+44 118 978 3393",
    "sg:postcode":"RG40 2AY",
    "sg:province":"Berkshire",
    "sg:tags":[
        "installers",
        "planner",
        "kitchen",
        "furnishers"
    ],
    "wof:name":"Designs For Living",
    "wof:placetype":"venue"
},
  "geometry": {"coordinates":[-0.836779,51.407768],"type":"Point"}
}