{
  "type": "Feature",
  "properties": {
    "addr:full":"Mews Workshop, Montpellier Retreat Cheltenham Gloucestershire GL50 2XG",
    "addr:postcode":"gl50 2xg",
    "iso:country":"GB",
    "sg:address":"Mews Workshop, Montpellier Retreat",
    "sg:city":"Cheltenham",
    "sg:classifiers":[
        {
            "category":"Retail",
            "subcategory":"Repair Shop",
            "type":"Services"
        }
    ],
    "sg:phone":"+44 1242 230320",
    "sg:postcode":"GL50 2XG",
    "sg:province":"Gloucestershire",
    "sg:tags":[
        "antique",
        "restoration",
        "furniture"
    ],
    "wof:name":"K Bawden",
    "wof:placetype":"venue"
},
  "geometry": {"coordinates":[-2.079823,51.892082],"type":"Point"}
}