{
  "type": "Feature",
  "properties": {
    "addr:full":"Bracken Lodge, Old Bury Hill, Westcott Dorking Surrey RH4 3JU",
    "addr:postcode":"rh4 3ju",
    "addr:street":"Old Bury Hill",
    "iso:country":"GB",
    "sg:address":"Bracken Lodge, Old Bury Hill, Westcott",
    "sg:city":"Dorking",
    "sg:classifiers":[
        {
            "category":"Professional",
            "subcategory":"Accounting & Tax Preparation",
            "type":"Services"
        }
    ],
    "sg:phone":"+44 1306 884674",
    "sg:postcode":"RH4 3JU",
    "sg:province":"Surrey",
    "sg:tags":[
        "accountant"
    ],
    "wof:name":"Derek J Rose",
    "wof:placetype":"venue"
},
  "geometry": {"coordinates":[-0.366299,51.225433],"type":"Point"}
}