{
  "type": "Feature",
  "properties": {
    "addr:full":"26 Church St Bilston West Midlands WV14 0AH",
    "addr:housenumber":"26",
    "addr:postcode":"wv14 0ah",
    "addr:street":"Church St",
    "iso:country":"GB",
    "sg:address":"26 Church St",
    "sg:city":"Bilston",
    "sg:classifiers":[
        {
            "category":"Home & Garden",
            "subcategory":"Household Appliances",
            "type":"Retail Goods"
        }
    ],
    "sg:phone":"+44 1902 403770",
    "sg:postcode":"WV14 0AH",
    "sg:province":"West Midlands",
    "sg:tags":[
        "domestic",
        "centre"
    ],
    "wof:name":"Past & Present",
    "wof:placetype":"venue"
},
  "geometry": {"coordinates":[-2.0742239952,52.5660858154],"type":"Point"}
}