{
  "type": "Feature",
  "properties": {
    "addr:full":"Halebank Rd Widnes Cheshire WA8 8NB",
    "addr:postcode":"wa8 8nb",
    "addr:street":"Halebank Rd",
    "iso:country":"GB",
    "sg:address":"Halebank Rd",
    "sg:city":"Widnes",
    "sg:classifiers":[
        {
            "category":"Manufacturing",
            "subcategory":"Metals",
            "type":"Manufacturing & Wholesale Goods"
        }
    ],
    "sg:phone":"+44 151 424 0000",
    "sg:postcode":"WA8 8NB",
    "sg:province":"Cheshire",
    "sg:tags":[
        "steel",
        "stockholder"
    ],
    "wof:name":"Spray Stainless Enginerring",
    "wof:placetype":"venue"
},
  "geometry": {"coordinates":[-2.7976438999,53.3544845581],"type":"Point"}
}