{
  "type": "Feature",
  "properties": {
    "addr:full":"Olde Springfield Spring Street, Wool Wareham Dorset BH20 6DB",
    "addr:postcode":"bh20 6db",
    "addr:street":"Olde Springfield Spring Street",
    "iso:country":"GB",
    "sg:address":"Olde Springfield Spring Street, Wool",
    "sg:city":"Wareham",
    "sg:classifiers":[
        {
            "category":"Building & Trades",
            "subcategory":"Construction",
            "type":"Services"
        }
    ],
    "sg:postcode":"BH20 6DB",
    "sg:province":"Dorset",
    "sg:tags":[
        "builder"
    ],
    "wof:name":"A R  Voyce (Builders) Ltd.",
    "wof:placetype":"venue"
},
  "geometry": {"coordinates":[-2.228854,50.678699],"type":"Point"}
}