{
  "type": "Feature",
  "properties": {
    "addr:full":", Trotton Petersfield Hampshire GU31 5ER",
    "addr:postcode":"gu31 5er",
    "addr:street":"Petersfield",
    "iso:country":"GB",
    "sg:address":", Trotton",
    "sg:city":"Petersfield",
    "sg:classifiers":[
        {
            "category":"Bars & Pubs",
            "type":"Food & Drink"
        }
    ],
    "sg:phone":"+44 1730 813724",
    "sg:postcode":"GU31 5ER",
    "sg:province":"Hampshire",
    "sg:tags":[
        "pubs",
        "inn"
    ],
    "wof:name":"The Keepers Arms",
    "wof:placetype":"venue"
},
  "geometry": {"coordinates":[-0.818125,50.984573],"type":"Point"}
}