{
  "type": "Feature",
  "properties": {
    "addr:full":"Tarnside House, Silloth Wigton Cumbria CA7 4NQ",
    "addr:postcode":"ca7 4nq",
    "addr:street":"Silloth",
    "iso:country":"GB",
    "sg:address":"Tarnside House, Silloth",
    "sg:city":"Wigton",
    "sg:classifiers":[
        {
            "category":"Recreation",
            "subcategory":"Campground",
            "type":"Entertainment"
        }
    ],
    "sg:phone":"+44 16973 31377",
    "sg:postcode":"CA7 4NQ",
    "sg:province":"Cumbria",
    "sg:tags":[
        "caravan",
        "park",
        "site",
        "camping"
    ],
    "wof:name":"W W & B C Wise",
    "wof:placetype":"venue"
},
  "geometry": {"coordinates":[-3.3557488918,54.8533782959],"type":"Point"}
}