{
  "type": "Feature",
  "properties": {
    "iso:country":"GB",
    "sg:address":"Greatford",
    "sg:city":"Stamford",
    "sg:classifiers":[
        {
            "category":"Bars & Pubs",
            "type":"Food & Drink"
        }
    ],
    "sg:postcode":"PE9 4QA",
    "sg:province":"Cambridgeshire",
    "sg:tags":[
        "pubs",
        "inn"
    ],
    "wof:name":"The Hare & Hounds",
    "wof:placetype":"venue"
},
  "geometry": {"coordinates":[-0.3894000053,52.6942100525],"type":"Point"}
}