{
  "type": "Feature",
  "properties": {
    "addr:full":"157 Derlwyn, Dunvant Swansea Swansea SA2 7PN",
    "addr:housenumber":"157",
    "addr:postcode":"sa2 7pn",
    "addr:street":"Derlwyn Dunvant",
    "iso:country":"GB",
    "sg:address":"157 Derlwyn, Dunvant",
    "sg:city":"Swansea",
    "sg:classifiers":[
        {
            "category":"Shopping",
            "subcategory":"Computers & Home Electronics",
            "type":"Retail Goods"
        }
    ],
    "sg:phone":"+44 1792 298796",
    "sg:postcode":"SA2 7PN",
    "sg:province":"Swansea",
    "sg:tags":[
        "aerial",
        "television",
        "radio"
    ],
    "wof:name":"Margaret& Roy Matthews",
    "wof:placetype":"venue"
},
  "geometry": {"coordinates":[-4.0233368874,51.6250839233],"type":"Point"}
}