{
  "type": "Feature",
  "properties": {
    "iso:country":"GB",
    "sg:address":"Horseshoe Corner, Hindmans Way, Off Chequers Lane",
    "sg:city":"Dagenham",
    "sg:classifiers":[
        {
            "category":"Freight",
            "type":"Transportation"
        }
    ],
    "sg:phone":"+44 20 8517 5755",
    "sg:postcode":"RM9 6LB",
    "sg:province":"Essex",
    "sg:tags":[
        "haulage",
        "road"
    ],
    "wof:name":"Rickabin Rentals Ltd.",
    "wof:placetype":"venue"
},
  "geometry": {"coordinates":[0.14232,51.521629],"type":"Point"}
}