{
  "type": "Feature",
  "properties": {
    "iso:country":"GB",
    "sg:address":"13 Birch Close, Wrecclesham",
    "sg:city":"Farnham",
    "sg:classifiers":[
        {
            "category":"Building & Trades",
            "subcategory":"Construction",
            "type":"Services"
        }
    ],
    "sg:phone":"+44 1252 795265",
    "sg:postcode":"GU10 4TJ",
    "sg:province":"Hampshire",
    "sg:tags":[
        "builder"
    ],
    "wof:name":"Goodford (Farnham) Ltd.",
    "wof:placetype":"venue"
},
  "geometry": {"coordinates":[-0.80736,51.188648],"type":"Point"}
}