{
  "type": "Feature",
  "properties": {
    "addr:full":"Unit 9 Kilton Industrial Park Worksop Nottinghamshire S80 2ED",
    "addr:housenumber":"unit 9",
    "addr:postcode":"s80 2ed",
    "addr:street":"Kilton Industrial Park",
    "iso:country":"GB",
    "sg:address":"Unit 9 Kilton Industrial Park",
    "sg:city":"Worksop",
    "sg:classifiers":[
        {
            "category":"Professional",
            "subcategory":"Management & Consulting",
            "type":"Services"
        }
    ],
    "sg:phone":"+44 1909 531315",
    "sg:postcode":"S80 2ED",
    "sg:province":"Nottinghamshire",
    "sg:tags":[
        "consultant",
        "promotion",
        "direct",
        "sale"
    ],
    "wof:name":"Universal Marketing Services Ltd.",
    "wof:placetype":"venue"
},
  "geometry": {"coordinates":[-1.123189,53.30661],"type":"Point"}
}