{
  "type": "Feature",
  "properties": {
    "addr:full":"London Road Faversham Kent ME13 8RZ",
    "addr:postcode":"me13 8rz",
    "addr:street":"London Road",
    "iso:country":"GB",
    "sg:address":"London Road",
    "sg:city":"Faversham",
    "sg:classifiers":[
        {
            "category":"Farming",
            "subcategory":"Nursery",
            "type":"Manufacturing & Wholesale Goods"
        },
        {
            "category":"Education",
            "subcategory":"School",
            "type":"Public Place"
        }
    ],
    "sg:phone":"+44 1795 532633",
    "sg:postcode":"ME13 8RZ",
    "sg:province":"Kent",
    "sg:tags":[
        "creche",
        "local",
        "authority"
    ],
    "wof:name":"The Abbey School",
    "wof:placetype":"venue"
},
  "geometry": {"coordinates":[0.8766080141,51.3109550476],"type":"Point"}
}