{
  "type": "Feature",
  "properties": {
    "iso:country":"GB",
    "sg:address":"80 Arbury Road, Stockingford",
    "sg:city":"Nuneaton",
    "sg:classifiers":[
        {
            "category":"Shopping",
            "subcategory":"Department Store",
            "type":"Retail Goods"
        },
        {
            "category":"Food & Beverages",
            "subcategory":"Groceries & Convenience Stores",
            "type":"Retail Goods"
        }
    ],
    "sg:phone":"+44 24 7638 3172",
    "sg:postcode":"CV10 7NB",
    "sg:province":"Leicestershire",
    "wof:name":"S & K Supermarkets",
    "wof:placetype":"venue"
},
  "geometry": {"coordinates":[-1.498961,52.51532],"type":"Point"}
}