{
  "type": "Feature",
  "properties": {
    "addr:full":"The Ski Shop, 66 Commissioner Street Crieff Perth and Kinross PH7 3AY",
    "addr:housenumber":"66",
    "addr:postcode":"ph7 3ay",
    "addr:street":"Commissioner Street",
    "iso:country":"GB",
    "sg:address":"The Ski Shop, 66 Commissioner Street",
    "sg:city":"Crieff",
    "sg:classifiers":[
        {
            "category":"Sports & Exercise",
            "subcategory":"Winter Sports",
            "type":"Entertainment"
        }
    ],
    "sg:postcode":"PH7 3AY",
    "sg:province":"Perth and Kinross",
    "sg:tags":[
        "skiing"
    ],
    "wof:name":"Crieff Ski Shop",
    "wof:placetype":"venue"
},
  "geometry": {"coordinates":[-3.839511,56.372738],"type":"Point"}
}