{
  "type": "Feature",
  "properties": {
    "iso:country":"GB",
    "sg:address":"Thornbrough Farm",
    "sg:city":"Corbridge",
    "sg:classifiers":[
        {
            "category":"Professional",
            "type":"Services"
        },
        {
            "category":"Banks & Credit Unions",
            "subcategory":"Investment Brokerage",
            "type":"Services"
        }
    ],
    "sg:phone":"+44 1434 633866",
    "sg:postcode":"NE45 5LX",
    "sg:province":"Northumberland",
    "sg:tags":[
        "farm",
        "agricultural",
        "contractor"
    ],
    "wof:name":"MARTIN BELL",
    "wof:placetype":"venue"
},
  "geometry": {"coordinates":[-2.013204,54.975937],"type":"Point"}
}