{
  "type": "Feature",
  "properties": {
    "iso:country":"GB",
    "sg:address":"75 High Street",
    "sg:city":"Yarm",
    "sg:classifiers":[
        {
            "category":"Shopping",
            "subcategory":"News",
            "type":"Retail Goods"
        }
    ],
    "sg:phone":"+44 1642 784500",
    "sg:postcode":"TS15 9BG",
    "sg:province":"North Yorkshire",
    "sg:tags":[
        "newsagent"
    ],
    "wof:name":"Country News",
    "wof:placetype":"venue"
},
  "geometry": {"coordinates":[-1.3545860052,54.5092811584],"type":"Point"}
}