{
  "type": "Feature",
  "properties": {
    "addr:full":"11 Moira Terrace Cardiff Cardiff CF24 0EJ",
    "addr:housenumber":"11",
    "addr:postcode":"cf24 0ej",
    "addr:street":"Moira Terrace",
    "iso:country":"GB",
    "sg:address":"11 Moira Terrace",
    "sg:city":"Cardiff",
    "sg:classifiers":[
        {
            "category":"Professional",
            "subcategory":"Lawyer & Legal Services",
            "type":"Services"
        }
    ],
    "sg:postcode":"CF24 0EJ",
    "sg:province":"Cardiff",
    "sg:tags":[
        "solicitor"
    ],
    "wof:name":"Savery & Pennington",
    "wof:placetype":"venue"
},
  "geometry": {"coordinates":[-3.1628479958,51.4817352295],"type":"Point"}
}