{
  "type": "Feature",
  "properties": {
    "addr:full":"2 Old Taunton Rd Bridgwater Somerset TA6 3NY",
    "addr:housenumber":"2",
    "addr:postcode":"ta6 3ny",
    "addr:street":"Old Taunton Rd",
    "iso:country":"GB",
    "sg:address":"2 Old Taunton Rd",
    "sg:city":"Bridgwater",
    "sg:classifiers":[
        {
            "category":"Bus Charters",
            "type":"Transportation"
        }
    ],
    "sg:phone":"+44 1278 444038",
    "sg:postcode":"TA6 3NY",
    "sg:province":"Somerset",
    "sg:tags":[
        "coach"
    ],
    "wof:name":"Time Away Travel Services",
    "wof:placetype":"venue"
},
  "geometry": {"coordinates":[-3.0021491051,51.1264915466],"type":"Point"}
}