{
  "type": "Feature",
  "properties": {
    "addr:full":"Unit 6 Ladfordfields Industrial Park, Woodseaves Road Stafford Staffordshire ST18 9QE",
    "addr:housenumber":"unit 6",
    "addr:postcode":"st18 9qe",
    "addr:street":"Ladfordfields Industrial Park Woodseaves Road",
    "iso:country":"GB",
    "sg:address":"Unit 6 Ladfordfields Industrial Park, Woodseaves Road",
    "sg:city":"Stafford",
    "sg:classifiers":[
        {
            "category":"Professional",
            "subcategory":"Printing & Photocopies",
            "type":"Services"
        }
    ],
    "sg:phone":"+44 1785 282055",
    "sg:postcode":"ST18 9QE",
    "sg:province":"Staffordshire",
    "sg:tags":[
        "printer"
    ],
    "wof:name":"Penkridge Printers",
    "wof:placetype":"venue"
},
  "geometry": {"coordinates":[-2.205835,52.833069],"type":"Point"}
}