{
  "type": "Feature",
  "properties": {
    "iso:country":"GB",
    "sg:address":"P O Box 125",
    "sg:city":"Shrewsbury",
    "sg:classifiers":[
        {
            "category":"Personal",
            "type":"Services"
        }
    ],
    "sg:postcode":"SY1 3WR",
    "sg:province":"Shropshire",
    "sg:tags":[
        "dating",
        "friendship",
        "agency"
    ],
    "wof:name":"Two for Tea",
    "wof:placetype":"venue"
},
  "geometry": {"coordinates":[-2.751283884,52.7065658569],"type":"Point"}
}