{
  "type": "Feature",
  "properties": {
    "iso:country":"GB",
    "sg:address":"9 Gilliams House, Junction Road",
    "sg:city":"Dorking",
    "sg:classifiers":[
        {
            "category":"Communications",
            "type":"Services"
        }
    ],
    "sg:postcode":"RH4 3HB",
    "sg:province":"Surrey",
    "sg:tags":[
        "data",
        "network"
    ],
    "wof:name":"Deltrex Data Services Ltd",
    "wof:placetype":"venue"
},
  "geometry": {"coordinates":[-0.328814,51.233341],"type":"Point"}
}