{
  "type": "Feature",
  "properties": {
    "iso:country":"GB",
    "sg:address":"17 Hatters Row, Horsemarket Street",
    "sg:city":"Warrington",
    "sg:classifiers":[
        {
            "category":"Coffee & Tea",
            "type":"Food & Drink"
        },
        {
            "category":"Cafe",
            "type":"Food & Drink"
        }
    ],
    "sg:phone":"+44 1925 445716",
    "sg:postcode":"WA1 1XP",
    "sg:province":"Cheshire",
    "sg:tags":[
        "shop",
        "room"
    ],
    "wof:name":"Hatters Coffee Shop",
    "wof:placetype":"venue"
},
  "geometry": {"coordinates":[-2.593472,53.390488],"type":"Point"}
}