{
  "type": "Feature",
  "properties": {
    "addr:full":"49 Torridge Way Plymouth Devon PL3 6JG",
    "addr:housenumber":"49",
    "addr:postcode":"pl3 6jg",
    "addr:street":"Torridge Way",
    "iso:country":"GB",
    "sg:address":"49 Torridge Way",
    "sg:city":"Plymouth",
    "sg:classifiers":[
        {
            "category":"Fast Food",
            "type":"Food & Drink"
        }
    ],
    "sg:phone":"+44 1752 767070",
    "sg:postcode":"PL3 6JG",
    "sg:province":"Devon",
    "sg:tags":[
        "away",
        "take"
    ],
    "wof:name":"Efford Fish Bar & Chinese Takeaway",
    "wof:placetype":"venue"
},
  "geometry": {"coordinates":[-4.110155,50.388725],"type":"Point"}
}