{
  "type": "Feature",
  "properties": {
    "iso:country":"GB",
    "sg:address":"71 Lichfield Rd",
    "sg:city":"Sutton Coldfield",
    "sg:classifiers":[
        {
            "category":"Health Services",
            "subcategory":"Nursing And Care Facility",
            "type":"Services"
        }
    ],
    "sg:phone":"+44 121 354 5133",
    "sg:postcode":"B74 2NU",
    "sg:province":"Staffordshire",
    "sg:tags":[
        "home"
    ],
    "wof:name":"Brynhaf",
    "wof:placetype":"venue"
},
  "geometry": {"coordinates":[-1.822948,52.570179],"type":"Point"}
}