{
  "type": "Feature",
  "properties": {
    "iso:country":"GB",
    "sg:address":"32 Kingsland High Street",
    "sg:city":"London",
    "sg:classifiers":[
        {
            "category":"Shopping",
            "subcategory":"Party Supplies",
            "type":"Retail Goods"
        }
    ],
    "sg:phone":"+44 20 7923 4149",
    "sg:postcode":"E8 2JP",
    "sg:province":"Greater London",
    "sg:tags":[
        "novelty"
    ],
    "wof:name":"Party Party",
    "wof:placetype":"venue"
},
  "geometry": {"coordinates":[-0.075427,51.547092],"type":"Point"}
}