{
  "type": "Feature",
  "properties": {
    "addr:full":"4th Floor Moreau House, 116 Brompton Road London Greater London SW3 1JJ",
    "addr:housenumber":"4th;116",
    "addr:postcode":"sw3 1jj",
    "addr:street":"Floor Moreau;Brompton Road",
    "iso:country":"GB",
    "sg:address":"4th Floor Moreau House, 116 Brompton Road",
    "sg:city":"London",
    "sg:classifiers":[
        {
            "category":"Professional",
            "subcategory":"Employment Agencies",
            "type":"Services"
        }
    ],
    "sg:phone":"+44 20 7581 5544",
    "sg:postcode":"SW3 1JJ",
    "sg:province":"Greater London",
    "sg:tags":[
        "consultant"
    ],
    "wof:name":"Gama International Ltd.",
    "wof:placetype":"venue"
},
  "geometry": {"coordinates":[-0.164479,51.499161],"type":"Point"}
}