{
  "type": "Feature",
  "properties": {
    "iso:country":"GB",
    "sg:address":"303 Market Street, Whitworth",
    "sg:city":"Rochdale",
    "sg:classifiers":[
        {
            "category":"Retail",
            "subcategory":"Repair Shop",
            "type":"Services"
        }
    ],
    "sg:postcode":"OL12 8PW",
    "sg:province":"Lancashire",
    "sg:tags":[
        "radio",
        "television",
        "video"
    ],
    "wof:name":"Ken Taylor T V & Video",
    "wof:placetype":"venue"
},
  "geometry": {"coordinates":[-2.1654651165,53.6796264648],"type":"Point"}
}