{
  "type": "Feature",
  "properties": {
    "iso:country":"GB",
    "sg:address":"Unit 8",
    "sg:city":"Dolgellau",
    "sg:classifiers":[
        {
            "category":"Food & Beverages",
            "subcategory":"Specialty",
            "type":"Retail Goods"
        },
        {
            "category":"Shopping",
            "subcategory":"Crafts & Fabrics",
            "type":"Retail Goods"
        }
    ],
    "sg:phone":"+44 1341 422562",
    "sg:postcode":"LL40 1UU",
    "sg:province":"Gwynedd",
    "sg:tags":[
        "retailer",
        "health",
        "material",
        "art"
    ],
    "wof:name":"THE MILLIPUT CO",
    "wof:placetype":"venue"
},
  "geometry": {"coordinates":[-3.9539890289,52.7230110168],"type":"Point"}
}