{
  "type": "Feature",
  "properties": {
    "addr:full":"69 Titchfield Street Galston East Ayrshire KA4 8AT",
    "addr:housenumber":"69",
    "addr:postcode":"ka4 8at",
    "addr:street":"Titchfield Street",
    "iso:country":"GB",
    "sg:address":"69 Titchfield Street",
    "sg:city":"Galston",
    "sg:classifiers":[
        {
            "category":"Sports & Exercise",
            "subcategory":"Gym",
            "type":"Entertainment"
        }
    ],
    "sg:postcode":"KA4 8AT",
    "sg:province":"East Ayrshire",
    "sg:tags":[
        "fitness",
        "health",
        "centre"
    ],
    "wof:name":"The Power House Gym",
    "wof:placetype":"venue"
},
  "geometry": {"coordinates":[-4.386516,55.602539],"type":"Point"}
}