{
  "type": "Feature",
  "properties": {
    "addr:full":"39 Station App Bromley Kent BR2 7EB",
    "addr:housenumber":"39",
    "addr:postcode":"br2 7eb",
    "iso:country":"GB",
    "sg:address":"39 Station App",
    "sg:city":"Bromley",
    "sg:classifiers":[
        {
            "category":"Food & Beverages",
            "subcategory":"Meat & Fish",
            "type":"Retail Goods"
        }
    ],
    "sg:phone":"+44 20 8462 0712",
    "sg:postcode":"BR2 7EB",
    "sg:province":"Kent",
    "sg:tags":[
        "butcher"
    ],
    "wof:name":"The Crown Roast",
    "wof:placetype":"venue"
},
  "geometry": {"coordinates":[0.011387,51.376255],"type":"Point"}
}