{
  "type": "Feature",
  "properties": {
    "addr:full":"44 Kennington Rd Southwark Greater London SE1 7BL",
    "addr:housenumber":"44",
    "addr:postcode":"se1 7bl",
    "addr:street":"Kennington Rd",
    "iso:country":"GB",
    "sg:address":"44 Kennington Rd",
    "sg:city":"Southwark",
    "sg:classifiers":[
        {
            "category":"Shopping",
            "subcategory":"Pharmacy",
            "type":"Retail Goods"
        }
    ],
    "sg:phone":"+44 20 7401 8088",
    "sg:postcode":"SE1 7BL",
    "sg:province":"Greater London",
    "sg:tags":[
        "pharmaceutical"
    ],
    "wof:name":"Carrycam Ltd",
    "wof:placetype":"venue"
},
  "geometry": {"coordinates":[-0.1120110005,51.4972381592],"type":"Point"}
}