{
  "type": "Feature",
  "properties": {
    "iso:country":"GB",
    "sg:address":"Echo Ho, Pennywell Indstl Est",
    "sg:city":"Sunderland",
    "sg:classifiers":[
        {
            "category":"Communications",
            "type":"Services"
        }
    ],
    "sg:postcode":"SR4 9ER",
    "sg:province":"Tyne and Wear",
    "sg:tags":[
        "broadcasting"
    ],
    "wof:name":"Sun City 103.4 Fm",
    "wof:placetype":"venue"
},
  "geometry": {"coordinates":[-1.4547100067,54.8932113647],"type":"Point"}
}