{
  "type": "Feature",
  "properties": {
    "addr:full":"Haggs Hall Farm, Ramsgreave Blackburn Lancashire BB1 9DS",
    "addr:postcode":"bb1 9ds",
    "addr:street":"Ramsgreave",
    "iso:country":"GB",
    "sg:address":"Haggs Hall Farm, Ramsgreave",
    "sg:city":"Blackburn",
    "sg:classifiers":[
        {
            "category":"Farming",
            "subcategory":"Livestock Farm",
            "type":"Manufacturing & Wholesale Goods"
        }
    ],
    "sg:phone":"+44 1254 247160",
    "sg:postcode":"BB1 9DS",
    "sg:province":"Lancashire",
    "sg:tags":[
        "others"
    ],
    "wof:name":"D & P Harlow",
    "wof:placetype":"venue"
},
  "geometry": {"coordinates":[-2.505397,53.774555],"type":"Point"}
}