{
  "type": "Feature",
  "properties": {
    "iso:country":"GB",
    "sg:address":"Brook Villa, Askham",
    "sg:city":"Penrith",
    "sg:classifiers":[
        {
            "category":"Home & Garden",
            "subcategory":"Building Materials",
            "type":"Retail Goods"
        },
        {
            "category":"Building & Trades",
            "subcategory":"Construction",
            "type":"Services"
        }
    ],
    "sg:phone":"+44 1931 712364",
    "sg:postcode":"CA10 2PG",
    "sg:province":"Cumbria",
    "sg:tags":[
        "dry",
        "plasterers",
        "installers",
        "lining",
        "insulation",
        "screeders"
    ],
    "wof:name":"D Harkness",
    "wof:placetype":"venue"
},
  "geometry": {"coordinates":[-2.754211,54.605949],"type":"Point"}
}