{
  "type": "Feature",
  "properties": {
    "iso:country":"GB",
    "sg:address":"The Piggery, Crowcombe",
    "sg:city":"Taunton",
    "sg:classifiers":[
        {
            "category":"Food & Beverages",
            "subcategory":"Liquor & Beverages",
            "type":"Retail Goods"
        },
        {
            "category":"Military Area",
            "subcategory":"Air Force Base",
            "type":"Public Place"
        }
    ],
    "sg:phone":"+44 1984 618370",
    "sg:postcode":"TA4 4AQ",
    "sg:province":"Devon",
    "sg:tags":[
        "wholesale",
        "beer",
        "wine",
        "spirit",
        "wines"
    ],
    "wof:name":"Quantock Abbey Wine Sellers",
    "wof:placetype":"venue"
},
  "geometry": {"coordinates":[-3.229351,51.121918],"type":"Point"}
}