{
  "type": "Feature",
  "properties": {
    "addr:full":"8-9 Station Street Spalding Lincolnshire PE11 1EF",
    "addr:housenumber":"8-9",
    "addr:postcode":"pe11 1ef",
    "addr:street":"Station Street",
    "iso:country":"GB",
    "sg:address":"8-9 Station Street",
    "sg:city":"Spalding",
    "sg:classifiers":[
        {
            "category":"Fast Food",
            "type":"Food & Drink"
        }
    ],
    "sg:phone":"+44 1775 725181",
    "sg:postcode":"PE11 1EF",
    "sg:province":"Lincolnshire",
    "sg:tags":[
        "away",
        "meal",
        "outlet",
        "take"
    ],
    "wof:name":"RUBY CHINESE TAKEAWAY",
    "wof:placetype":"venue"
},
  "geometry": {"coordinates":[-0.1547150016,52.7874946594],"type":"Point"}
}