{
  "type": "Feature",
  "properties": {
    "addr:full":"132-134 Balcarres Road Leyland Lancashire PR25 3ED",
    "addr:postcode":"132-134;pr25 3ed",
    "addr:street":"Balcarres Road",
    "iso:country":"GB",
    "sg:address":"132-134 Balcarres Road",
    "sg:city":"Leyland",
    "sg:classifiers":[
        {
            "category":"Shopping",
            "subcategory":"Stationery & Office Supplies",
            "type":"Retail Goods"
        }
    ],
    "sg:postcode":"PR25 3ED",
    "sg:province":"Lancashire",
    "sg:tags":[
        "machine",
        "facsimile"
    ],
    "wof:name":"Linear Uk",
    "wof:placetype":"venue"
},
  "geometry": {"coordinates":[-2.6895239353,53.6950798035],"type":"Point"}
}