{
  "type": "Feature",
  "properties": {
    "addr:full":"9 Riverside, Hendon Hendon Greater London NW4 3TU",
    "addr:housenumber":"9;hendon",
    "addr:postcode":"nw4 3tu",
    "addr:street":"Riverside",
    "iso:country":"GB",
    "sg:address":"9 Riverside, Hendon",
    "sg:city":"Hendon",
    "sg:classifiers":[
        {
            "category":"Travel",
            "subcategory":"Travel Agent",
            "type":"Entertainment"
        }
    ],
    "sg:phone":"+44 20 8202 9229",
    "sg:postcode":"NW4 3TU",
    "sg:province":"Greater London",
    "wof:name":"Bonanza Travel",
    "wof:placetype":"venue"
},
  "geometry": {"coordinates":[-0.2314990014,51.5755462646],"type":"Point"}
}