{
  "type": "Feature",
  "properties": {
    "iso:country":"GB",
    "sg:address":"12 Bromley St",
    "sg:city":"Birmingham",
    "sg:classifiers":[
        {
            "category":"Building & Trades",
            "subcategory":"Cleaning & Sanitation",
            "type":"Services"
        }
    ],
    "sg:phone":"+44 121 772 3328",
    "sg:postcode":"B9 4AN",
    "sg:province":"West Midlands",
    "sg:tags":[
        "contracting",
        "commercial"
    ],
    "wof:name":"Premier Cleaning Services",
    "wof:placetype":"venue"
},
  "geometry": {"coordinates":[-1.881531,52.475925],"type":"Point"}
}