{
  "type": "Feature",
  "properties": {
    "addr:full":"3 Whiteleys Parade, Uxbridge Road, Hillingdon Uxbridge Greater London UB10 0PD",
    "addr:housenumber":"3",
    "addr:postcode":"ub10 0pd",
    "addr:street":"Whiteleys Parade Uxbridge Road",
    "iso:country":"GB",
    "sg:address":"3 Whiteleys Parade, Uxbridge Road, Hillingdon",
    "sg:city":"Uxbridge",
    "sg:classifiers":[
        {
            "category":"Shopping",
            "subcategory":"Bicycles & Sporting Goods",
            "type":"Retail Goods"
        }
    ],
    "sg:phone":"+44 1895 811214",
    "sg:postcode":"UB10 0PD",
    "sg:province":"Greater London",
    "sg:tags":[
        "shop",
        "cycle",
        "accessory"
    ],
    "wof:name":"The Wheely Good Bike Shop",
    "wof:placetype":"venue"
},
  "geometry": {"coordinates":[-0.4469659925,51.5297470093],"type":"Point"}
}