{
  "type": "Feature",
  "properties": {
    "iso:country":"GB",
    "sg:address":"146 Holland Park Avenue",
    "sg:city":"London",
    "sg:classifiers":[
        {
            "category":"Health Services",
            "subcategory":"Dentist",
            "type":"Services"
        }
    ],
    "sg:phone":"+44 20 7727 5810",
    "sg:postcode":"W11 4UE",
    "sg:province":"Greater London",
    "wof:name":"Aron Balkin",
    "wof:placetype":"venue"
},
  "geometry": {"coordinates":[-0.2087,51.506439],"type":"Point"}
}