{
  "type": "Feature",
  "properties": {
    "addr:full":"59 Burgate Canterbury Kent CT1 2HJ",
    "addr:housenumber":"59",
    "addr:postcode":"ct1 2hj",
    "addr:street":"Burgate Canterbury",
    "iso:country":"GB",
    "sg:address":"59 Burgate",
    "sg:city":"Canterbury",
    "sg:classifiers":[
        {
            "category":"Place Of Worship",
            "type":"Public Place"
        }
    ],
    "sg:phone":"+44 1227 462896",
    "sg:postcode":"CT1 2HJ",
    "sg:province":"Kent",
    "wof:name":"St. Thomas R C Church",
    "wof:placetype":"venue"
},
  "geometry": {"coordinates":[1.083116,51.278336],"type":"Point"}
}