{
  "type": "Feature",
  "properties": {
    "addr:full":"Mote Cottage, Howland Rd, Marden Tonbridge Kent TN12 9LB",
    "addr:postcode":"tn12 9lb",
    "addr:street":"Howland Rd",
    "iso:country":"GB",
    "sg:address":"Mote Cottage, Howland Rd, Marden",
    "sg:city":"Tonbridge",
    "sg:classifiers":[
        {
            "category":"Recreation",
            "subcategory":"Dog Park",
            "type":"Entertainment"
        }
    ],
    "sg:phone":"+44 1622 833023",
    "sg:postcode":"TN12 9LB",
    "sg:province":"Kent",
    "wof:name":"Debonair Dogs & Cool Cats",
    "wof:placetype":"venue"
},
  "geometry": {"coordinates":[0.489726007,51.176322937],"type":"Point"}
}