{
  "type": "Feature",
  "properties": {
    "iso:country":"GB",
    "sg:address":"1 Clarence Street",
    "sg:city":"York",
    "sg:classifiers":[
        {
            "category":"Communications",
            "type":"Services"
        }
    ],
    "sg:postcode":"YO31 7EL",
    "sg:province":"North Yorkshire",
    "sg:tags":[
        "telecommunication"
    ],
    "wof:name":"Totally in Touch",
    "wof:placetype":"venue"
},
  "geometry": {"coordinates":[-1.083407,53.965546],"type":"Point"}
}