{
  "type": "Feature",
  "properties": {
    "iso:country":"GB",
    "sg:address":"The Cold Store, Gate Lane",
    "sg:city":"Wells",
    "sg:classifiers":[
        {
            "category":"Personal",
            "subcategory":"Beauty Salon",
            "type":"Services"
        },
        {
            "category":"Personal",
            "subcategory":"Barber",
            "type":"Services"
        }
    ],
    "sg:phone":"+44 1749 670673",
    "sg:postcode":"BA5 1UA",
    "sg:province":"Somerset",
    "sg:tags":[
        "unisex",
        "hairdresser"
    ],
    "wof:name":"Tete A Tete",
    "wof:placetype":"venue"
},
  "geometry": {"coordinates":[-2.6459538937,51.2113494873],"type":"Point"}
}