{
  "type": "Feature",
  "properties": {
    "iso:country":"GB",
    "sg:address":"3 Frankholmes Drive, Shirley",
    "sg:city":"Solihull",
    "sg:classifiers":[
        {
            "category":"Home & Garden",
            "subcategory":"Carpets & Floor Coverings",
            "type":"Retail Goods"
        }
    ],
    "sg:phone":"+44 121 733 2490",
    "sg:postcode":"B90 4XF",
    "sg:province":"West Midlands",
    "sg:tags":[
        "cleaner",
        "upholstery"
    ],
    "wof:name":"Gordon Williams",
    "wof:placetype":"venue"
},
  "geometry": {"coordinates":[-1.796254,52.387455],"type":"Point"}
}