{
  "type": "Feature",
  "properties": {
    "addr:full":"42a Main Street, Broughton Astley Leicester Leicestershire LE9 6RE",
    "addr:housenumber":"42a",
    "addr:postcode":"le9 6re",
    "addr:street":"Main Street",
    "iso:country":"GB",
    "sg:address":"42a Main Street, Broughton Astley",
    "sg:city":"Leicester",
    "sg:classifiers":[
        {
            "category":"Personal",
            "subcategory":"Beauty Salon",
            "type":"Services"
        }
    ],
    "sg:phone":"+44 1455 282387",
    "sg:postcode":"LE9 6RE",
    "sg:province":"Leicestershire",
    "sg:tags":[
        "unisex",
        "hairdresser"
    ],
    "wof:name":"Options for Hair",
    "wof:placetype":"venue"
},
  "geometry": {"coordinates":[-1.228517,52.532974],"type":"Point"}
}