{
  "type": "Feature",
  "properties": {
    "iso:country":"GB",
    "sg:address":"665 Finchley Road",
    "sg:city":"London",
    "sg:classifiers":[
        {
            "category":"Shopping",
            "subcategory":"Shoes",
            "type":"Retail Goods"
        }
    ],
    "sg:phone":"+44 20 8450 2617",
    "sg:postcode":"NW2 3HN",
    "sg:province":"Greater London",
    "sg:tags":[
        "shop"
    ],
    "wof:name":"Fairill Ltd.",
    "wof:placetype":"venue"
},
  "geometry": {"coordinates":[-0.197157,51.561035],"type":"Point"}
}