{
  "type": "Feature",
  "properties": {
    "addr:full":"Unit 3, Jackson St Industrial Estate St Helens Cheshire WA9 3AT",
    "addr:housenumber":"unit 3",
    "addr:postcode":"wa9 3at",
    "addr:street":"Jackson St Industrial Estate",
    "iso:country":"GB",
    "sg:address":"Unit 3, Jackson St Industrial Estate",
    "sg:city":"St Helens",
    "sg:classifiers":[
        {
            "category":"Building & Trades",
            "subcategory":"Cleaning & Sanitation",
            "type":"Services"
        }
    ],
    "sg:phone":"+44 1744 26526",
    "sg:postcode":"WA9 3AT",
    "sg:province":"Cheshire",
    "sg:tags":[
        "blast"
    ],
    "wof:name":"N L Williams Group Ltd.",
    "wof:placetype":"venue"
},
  "geometry": {"coordinates":[-2.719029,53.445259],"type":"Point"}
}