{
  "type": "Feature",
  "properties": {
    "addr:full":"32 Walton Clo Waterlooville Hampshire PO7 7DJ",
    "addr:housenumber":"32",
    "addr:postcode":"po7 7dj",
    "addr:street":"Walton Clo",
    "iso:country":"GB",
    "sg:address":"32 Walton Clo",
    "sg:city":"Waterlooville",
    "sg:classifiers":[
        {
            "category":"Building & Trades",
            "subcategory":"Construction",
            "type":"Services"
        }
    ],
    "sg:phone":"+44 23 9225 6577",
    "sg:postcode":"PO7 7DJ",
    "sg:province":"Hampshire",
    "sg:tags":[
        "dry",
        "lining",
        "plasterers",
        "screeders"
    ],
    "wof:name":"J P S Plastering",
    "wof:placetype":"venue"
},
  "geometry": {"coordinates":[-1.0299320221,50.8717651367],"type":"Point"}
}