{
  "type": "Feature",
  "properties": {
    "addr:full":"286a Great North Road, Woodlands Doncaster North Yorkshire DN6 7HN",
    "addr:housenumber":"286a",
    "addr:postcode":"dn6 7hn",
    "addr:street":"Great North Road",
    "iso:country":"GB",
    "sg:address":"286a Great North Road, Woodlands",
    "sg:city":"Doncaster",
    "sg:classifiers":[
        {
            "category":"Personal",
            "subcategory":"Beauty Salon",
            "type":"Services"
        }
    ],
    "sg:phone":"+44 1302 338001",
    "sg:postcode":"DN6 7HN",
    "sg:province":"North Yorkshire",
    "sg:tags":[
        "unisex",
        "hairdresser"
    ],
    "wof:name":"Vanessa 4 Hair",
    "wof:placetype":"venue"
},
  "geometry": {"coordinates":[-1.1875040531,53.5609359741],"type":"Point"}
}