{
  "type": "Feature",
  "properties": {
    "addr:full":"8 Talbot Road London Greater London N15 4DH",
    "addr:housenumber":"8",
    "addr:postcode":"n15 4dh",
    "addr:street":"Talbot Road",
    "iso:country":"GB",
    "sg:address":"8 Talbot Road",
    "sg:city":"London",
    "sg:classifiers":[
        {
            "category":"Social Services",
            "type":"Services"
        },
        {
            "category":"Travel",
            "subcategory":"Hostel",
            "type":"Entertainment"
        }
    ],
    "sg:phone":"+44 20 8808 8758",
    "sg:postcode":"N15 4DH",
    "sg:province":"Greater London",
    "sg:tags":[
        "disability"
    ],
    "wof:name":"Talbot Road Hostel",
    "wof:placetype":"venue"
},
  "geometry": {"coordinates":[-0.0696810037,51.5846481323],"type":"Point"}
}