{
  "type": "Feature",
  "properties": {
    "iso:country":"GB",
    "sg:address":"1-3 Rivington Street",
    "sg:city":"Moorgate",
    "sg:classifiers":[
        {
            "category":"Banks & Credit Unions",
            "subcategory":"Financial Services",
            "type":"Services"
        }
    ],
    "sg:postcode":"EC2A 3DT",
    "sg:province":"Greater London",
    "sg:tags":[
        "consultant"
    ],
    "wof:name":"Jubilee 2000 Coalition Charitable Trust",
    "wof:placetype":"venue"
},
  "geometry": {"coordinates":[-0.083239,51.526207],"type":"Point"}
}