{
  "type": "Feature",
  "properties": {
    "iso:country":"GB",
    "sg:address":"Mackie's Mill Farm, Elderslie",
    "sg:city":"Johnstone",
    "sg:classifiers":[
        {
            "category":"Farming",
            "subcategory":"Livestock Farm",
            "type":"Manufacturing & Wholesale Goods"
        }
    ],
    "sg:phone":"+44 1505 322534",
    "sg:postcode":"PA5 9UW",
    "sg:province":"Renfrewshire",
    "sg:tags":[
        "others"
    ],
    "wof:name":"Thomas Gatherer",
    "wof:placetype":"venue"
},
  "geometry": {"coordinates":[-4.48391,55.822689],"type":"Point"}
}