{
  "type": "Feature",
  "properties": {
    "addr:full":"169 Queen Victoria Street London Greater London EC4V 4DD",
    "addr:housenumber":"169",
    "addr:postcode":"ec4v 4dd",
    "addr:street":"Queen Victoria Street",
    "iso:country":"GB",
    "sg:address":"169 Queen Victoria Street",
    "sg:city":"London",
    "sg:classifiers":[
        {
            "category":"Cafe",
            "type":"Food & Drink"
        }
    ],
    "sg:phone":"+44 20 7248 4021",
    "sg:postcode":"EC4V 4DD",
    "sg:province":"Greater London",
    "sg:tags":[
        "tea",
        "room"
    ],
    "wof:name":"Cafe D'Arte",
    "wof:placetype":"venue"
},
  "geometry": {"coordinates":[-0.1037999988,51.5117530823],"type":"Point"}
}