{
  "type": "Feature",
  "properties": {
    "addr:full":"27 High Street London Greater London W3 6ND",
    "addr:housenumber":"27",
    "addr:postcode":"w3 6nd",
    "addr:street":"High Street",
    "iso:country":"GB",
    "sg:address":"27 High Street",
    "sg:city":"London",
    "sg:classifiers":[
        {
            "category":"Personal",
            "subcategory":"Barber",
            "type":"Services"
        }
    ],
    "sg:phone":"+44 20 8992 0760",
    "sg:postcode":"W3 6ND",
    "sg:province":"Greater London",
    "sg:tags":[
        "men's",
        "hairdresser"
    ],
    "wof:name":"Danny's",
    "wof:placetype":"venue"
},
  "geometry": {"coordinates":[-0.2655700147,51.5064811707],"type":"Point"}
}