{
  "type": "Feature",
  "properties": {
    "addr:full":"11 Downemead Telford Shropshire TF3 2EW",
    "addr:housenumber":"11",
    "addr:postcode":"tf3 2ew",
    "addr:street":"Downemead",
    "iso:country":"GB",
    "sg:address":"11 Downemead",
    "sg:city":"Telford",
    "sg:classifiers":[
        {
            "category":"Food & Beverages",
            "subcategory":"Groceries & Convenience Stores",
            "type":"Retail Goods"
        }
    ],
    "sg:phone":"+44 1952 200068",
    "sg:postcode":"TF3 2EW",
    "sg:province":"Shropshire",
    "wof:name":"Spar Shop",
    "wof:placetype":"venue"
},
  "geometry": {"coordinates":[-2.4372270107,52.6736335754],"type":"Point"}
}