{
  "type": "Feature",
  "properties": {
    "addr:full":"16 Gayfere St London Greater London SW1P 3HP",
    "addr:housenumber":"16",
    "addr:postcode":"sw1p 3hp",
    "addr:street":"Gayfere St",
    "iso:country":"GB",
    "sg:address":"16 Gayfere St",
    "sg:city":"London",
    "sg:classifiers":[
        {
            "category":"Professional",
            "subcategory":"Management & Consulting",
            "type":"Services"
        }
    ],
    "sg:postcode":"SW1P 3HP",
    "sg:province":"Greater London",
    "sg:tags":[
        "conservation"
    ],
    "wof:name":"Fountain Society (The)",
    "wof:placetype":"venue"
},
  "geometry": {"coordinates":[-0.1274479926,51.4963607788],"type":"Point"}
}