{
  "type": "Feature",
  "properties": {
    "addr:full":"Birchwood Farm, Ripley Harrogate North Yorkshire HG3 3AX",
    "addr:housenumber":"ripley",
    "addr:postcode":"hg3 3ax",
    "iso:country":"GB",
    "sg:address":"Birchwood Farm, Ripley",
    "sg:city":"Harrogate",
    "sg:classifiers":[
        {
            "category":"Farming",
            "subcategory":"Livestock Farm",
            "type":"Manufacturing & Wholesale Goods"
        }
    ],
    "sg:phone":"+44 1423 770137",
    "sg:postcode":"HG3 3AX",
    "sg:province":"North Yorkshire",
    "sg:tags":[
        "others"
    ],
    "wof:name":"K Smith",
    "wof:placetype":"venue"
},
  "geometry": {"coordinates":[-1.567788,54.039467],"type":"Point"}
}