{
  "type": "Feature",
  "properties": {
    "iso:country":"GB",
    "sg:address":"Manchester Road",
    "sg:city":"Ashton-under-lyne",
    "sg:classifiers":[
        {
            "category":"Wholesale",
            "subcategory":"Construction Materials",
            "type":"Manufacturing & Wholesale Goods"
        }
    ],
    "sg:phone":"+44 161 339 0845",
    "sg:postcode":"OL7 0DA",
    "sg:province":"Greater Manchester",
    "sg:tags":[
        "lift"
    ],
    "wof:name":"H S S Lift & Shift",
    "wof:placetype":"venue"
},
  "geometry": {"coordinates":[-2.105373,53.484455],"type":"Point"}
}