{
  "type": "Feature",
  "properties": {
    "addr:full":"31 Old Hill Cres, Christchurch Newport Monmouthshire NP18 1JL",
    "addr:housenumber":"31",
    "addr:postcode":"np18 1jl",
    "addr:street":"Old;Cres",
    "iso:country":"GB",
    "sg:address":"31 Old Hill Cres, Christchurch",
    "sg:city":"Newport",
    "sg:classifiers":[
        {
            "category":"Building & Trades",
            "subcategory":"Construction",
            "type":"Services"
        }
    ],
    "sg:postcode":"NP18 1JL",
    "sg:province":"Monmouthshire",
    "sg:tags":[
        "builder",
        "repairer",
        "chimney"
    ],
    "wof:name":"Celtic Chimney Lining",
    "wof:placetype":"venue"
},
  "geometry": {"coordinates":[-2.946966,51.602303],"type":"Point"}
}