{
  "type": "Feature",
  "properties": {
    "addr:full":"277 Walsgrave Road Coventry Warwickshire CV2 4BA",
    "addr:housenumber":"277",
    "addr:postcode":"cv2 4ba",
    "addr:street":"Walsgrave Road",
    "iso:country":"GB",
    "sg:address":"277 Walsgrave Road",
    "sg:city":"Coventry",
    "sg:classifiers":[
        {
            "category":"Restaurant",
            "type":"Food & Drink"
        }
    ],
    "sg:phone":"+44 24 7644 5697",
    "sg:postcode":"CV2 4BA",
    "sg:province":"Warwickshire",
    "sg:tags":[
        "indian",
        "-"
    ],
    "wof:name":"Bombay Joes",
    "wof:placetype":"venue"
},
  "geometry": {"coordinates":[-1.480807,52.41148],"type":"Point"}
}