{
  "type": "Feature",
  "properties": {
    "addr:full":"Hatt Common, Bore Hill Newbury Berkshire RG20 0NQ",
    "addr:postcode":"rg20 0nq",
    "addr:street":"Hatt Common Bore Hill",
    "iso:country":"GB",
    "sg:address":"Hatt Common, Bore Hill",
    "sg:city":"Newbury",
    "sg:classifiers":[
        {
            "category":"Farming",
            "subcategory":"Nursery",
            "type":"Manufacturing & Wholesale Goods"
        }
    ],
    "sg:postcode":"RG20 0NQ",
    "sg:province":"Berkshire",
    "sg:tags":[
        "creche"
    ],
    "wof:name":"The Apples Nursery School",
    "wof:placetype":"venue"
},
  "geometry": {"coordinates":[-1.39238,51.365921],"type":"Point"}
}