{
  "type": "Feature",
  "properties": {
    "iso:country":"GB",
    "sg:address":"5 Thornefield Pde, Holders Hill Rd",
    "sg:city":"Mill Hill",
    "sg:classifiers":[
        {
            "category":"Government",
            "subcategory":"Post Office",
            "type":"Public Place"
        }
    ],
    "sg:phone":"+44 20 8346 4260",
    "sg:postcode":"NW7 1LU",
    "sg:province":"Greater London",
    "wof:name":"Holders Hill Post Office",
    "wof:placetype":"venue"
},
  "geometry": {"coordinates":[-0.2082300037,51.6022987366],"type":"Point"}
}