{
  "type": "Feature",
  "properties": {
    "iso:country":"GB",
    "sg:address":"29 Princes Avenue, Mayland",
    "sg:city":"Chelmsford",
    "sg:classifiers":[
        {
            "category":"Building & Trades",
            "subcategory":"Plumbing",
            "type":"Services"
        }
    ],
    "sg:phone":"+44 1621 744767",
    "sg:postcode":"CM3 6BA",
    "sg:province":"Essex",
    "sg:tags":[
        "central",
        "heating"
    ],
    "wof:name":"Pralet Maintenance",
    "wof:placetype":"venue"
},
  "geometry": {"coordinates":[0.764174,51.683262],"type":"Point"}
}