{
  "type": "Feature",
  "properties": {
    "iso:country":"GB",
    "sg:address":"The London Underwriting Centre, 3 Minster Ct, Mincing La",
    "sg:city":"London",
    "sg:classifiers":[
        {
            "category":"Insurance",
            "subcategory":"Insurance Agent",
            "type":"Services"
        }
    ],
    "sg:phone":"+44 20 7617 4900",
    "sg:postcode":"EC3R 7DD",
    "sg:province":"Greater London",
    "wof:name":"Sirius International Insurance Corporati",
    "wof:placetype":"venue"
},
  "geometry": {"coordinates":[-0.207955,51.551254],"type":"Point"}
}