{
  "type": "Feature",
  "properties": {
    "addr:full":"1-5 Holden Fold Darwen Lancashire BB3 0EL",
    "addr:housenumber":"1-5",
    "addr:postcode":"bb3 0el",
    "addr:street":"Holden Fold",
    "iso:country":"GB",
    "sg:address":"1-5 Holden Fold",
    "sg:city":"Darwen",
    "sg:classifiers":[
        {
            "category":"Shopping",
            "subcategory":"Clothing, Apparel, & Fashions",
            "type":"Retail Goods"
        }
    ],
    "sg:phone":"+44 1254 701156",
    "sg:postcode":"BB3 0EL",
    "sg:province":"Lancashire",
    "sg:tags":[
        "clothing",
        "fabric"
    ],
    "wof:name":"Edward Taylor (Textiles) Ltd.",
    "wof:placetype":"venue"
},
  "geometry": {"coordinates":[-2.461497,53.703789],"type":"Point"}
}