{
  "type": "Feature",
  "properties": {
    "iso:country":"GB",
    "sg:address":"19 Hyde Park Corner",
    "sg:city":"Leeds",
    "sg:classifiers":[
        {
            "category":"Shopping",
            "subcategory":"News",
            "type":"Retail Goods"
        }
    ],
    "sg:postcode":"LS6 1AF",
    "sg:province":"West Yorkshire",
    "sg:tags":[
        "newsagent"
    ],
    "wof:name":"Theti Newsagents",
    "wof:placetype":"venue"
},
  "geometry": {"coordinates":[-1.566403985,53.8083114624],"type":"Point"}
}