{
  "type": "Feature",
  "properties": {
    "iso:country":"GB",
    "sg:address":"66 Rochester Road",
    "sg:city":"Aylesford",
    "sg:classifiers":[
        {
            "category":"Professional",
            "subcategory":"Secretarial Services",
            "type":"Services"
        }
    ],
    "sg:postcode":"ME20 7BJ",
    "sg:province":"Kent",
    "wof:name":"Doorne Documents",
    "wof:placetype":"venue"
},
  "geometry": {"coordinates":[0.4843289852,51.305141449],"type":"Point"}
}