{
  "type": "Feature",
  "properties": {
    "addr:full":"International House, Dover Place Ashford Kent TN23 1HU",
    "addr:postcode":"tn23 1hu",
    "addr:street":"Dover Place",
    "iso:country":"GB",
    "sg:address":"International House, Dover Place",
    "sg:city":"Ashford",
    "sg:classifiers":[
        {
            "category":"Government",
            "subcategory":"Police Station",
            "type":"Public Place"
        }
    ],
    "sg:phone":"+44 1233 617315",
    "sg:postcode":"TN23 1HU",
    "sg:province":"Kent",
    "sg:tags":[
        "support",
        "force"
    ],
    "wof:name":"British Transport Police",
    "wof:placetype":"venue"
},
  "geometry": {"coordinates":[0.8744500279,51.1452903748],"type":"Point"}
}