{
  "type": "Feature",
  "properties": {
    "iso:country":"GB",
    "sg:address":"Green Pastures, Brettenham Road",
    "sg:city":"Stowmarket",
    "sg:classifiers":[
        {
            "category":"Professional",
            "subcategory":"Secretarial Services",
            "type":"Services"
        }
    ],
    "sg:phone":"+44 1449 736628",
    "sg:postcode":"IP14 3DX",
    "sg:province":"Suffolk",
    "wof:name":"Buxhall Secretarial",
    "wof:placetype":"venue"
},
  "geometry": {"coordinates":[0.996769,52.188625],"type":"Point"}
}