{
  "type": "Feature",
  "properties": {
    "iso:country":"GB",
    "sg:address":"524 Stoney Stanton Rd",
    "sg:city":"Coventry",
    "sg:classifiers":[
        {
            "category":"Manufacturing",
            "subcategory":"Metals",
            "type":"Manufacturing & Wholesale Goods"
        }
    ],
    "sg:phone":"+44 24 7668 7907",
    "sg:postcode":"CV6 5FS",
    "sg:province":"Warwickshire",
    "sg:tags":[
        "steel",
        "mnfrs"
    ],
    "wof:name":"Coventry Wheel Base",
    "wof:placetype":"venue"
},
  "geometry": {"coordinates":[-1.491926,52.427036],"type":"Point"}
}