{
  "type": "Feature",
  "properties": {
    "iso:country":"GB",
    "sg:address":"107 Shipfield, Sprowston",
    "sg:city":"Norwich",
    "sg:classifiers":[
        {
            "category":"Fast Food",
            "type":"Food & Drink"
        }
    ],
    "sg:phone":"+44 1603 429460",
    "sg:postcode":"NR3 4DT",
    "sg:province":"Norfolk",
    "sg:tags":[
        "away",
        "take"
    ],
    "wof:name":"Kam Hon",
    "wof:placetype":"venue"
},
  "geometry": {"coordinates":[1.307639,52.651306],"type":"Point"}
}