{
  "type": "Feature",
  "properties": {
    "addr:full":"The Furrows, Llanfallteg Whitland Carmarthenshire SA34 0UP",
    "addr:postcode":"sa34 0up",
    "addr:street":"Llanfallteg;Carmarthenshire",
    "iso:country":"GB",
    "sg:address":"The Furrows, Llanfallteg",
    "sg:city":"Whitland",
    "sg:classifiers":[
        {
            "category":"Building & Trades",
            "subcategory":"Construction",
            "type":"Services"
        }
    ],
    "sg:phone":"+44 1437 563584",
    "sg:postcode":"SA34 0UP",
    "sg:province":"Carmarthenshire",
    "sg:tags":[
        "builder",
        "contractor"
    ],
    "wof:name":"Gethin C John & Sons",
    "wof:placetype":"venue"
},
  "geometry": {"coordinates":[-4.612054,51.819256],"type":"Point"}
}