{
  "type": "Feature",
  "properties": {
    "iso:country":"GB",
    "sg:address":"Park Farm",
    "sg:city":"Clacton On Sea",
    "sg:classifiers":[
        {
            "category":"Farming",
            "subcategory":"Livestock Farm",
            "type":"Manufacturing & Wholesale Goods"
        }
    ],
    "sg:phone":"+44 1255 820230",
    "sg:postcode":"CO16 8HG",
    "sg:province":"Essex",
    "sg:tags":[
        "others"
    ],
    "wof:name":"F J Ford",
    "wof:placetype":"venue"
},
  "geometry": {"coordinates":[1.0527169704,51.7957954407],"type":"Point"}
}