{
  "type": "Feature",
  "properties": {
    "addr:full":"Second Avenue, Millwey Rise Axminster Devon EX13 5HH",
    "addr:postcode":"ex13 5hh",
    "addr:street":"Second Avenue Millwey Rise",
    "iso:country":"GB",
    "sg:address":"Second Avenue, Millwey Rise",
    "sg:city":"Axminster",
    "sg:classifiers":[
        {
            "category":"Manufacturing",
            "subcategory":"Furniture",
            "type":"Manufacturing & Wholesale Goods"
        }
    ],
    "sg:phone":"+44 1297 35735",
    "sg:postcode":"EX13 5HH",
    "sg:province":"Devon",
    "sg:tags":[
        "mnfr",
        "garden",
        "patio"
    ],
    "wof:name":"Country Style",
    "wof:placetype":"venue"
},
  "geometry": {"coordinates":[-3.000562,50.781277],"type":"Point"}
}