{
  "type": "Feature",
  "properties": {
    "addr:full":"100 Church Road Teddington Greater London TW11 8QE",
    "addr:housenumber":"100",
    "addr:postcode":"tw11 8qe",
    "addr:street":"Church Road",
    "iso:country":"GB",
    "sg:address":"100 Church Road",
    "sg:city":"Teddington",
    "sg:classifiers":[
        {
            "category":"Organizations",
            "subcategory":"Non-profit Organization",
            "type":"Services"
        }
    ],
    "sg:phone":"+44 20 8977 9144",
    "sg:postcode":"TW11 8QE",
    "sg:province":"Greater London",
    "sg:tags":[
        "charitable",
        "organisation",
        "voluntary",
        "charity"
    ],
    "wof:name":"Tearfund",
    "wof:placetype":"venue"
},
  "geometry": {"coordinates":[-0.3383249938,51.4287948608],"type":"Point"}
}