{
  "type": "Feature",
  "properties": {
    "iso:country":"GB",
    "sg:address":"70 High Street",
    "sg:city":"Tring",
    "sg:classifiers":[
        {
            "category":"Organizations",
            "subcategory":"Community Association",
            "type":"Services"
        },
        {
            "category":"Organizations",
            "subcategory":"Membership Organization",
            "type":"Services"
        }
    ],
    "sg:phone":"+44 1442 823118",
    "sg:postcode":"HP23 4AF",
    "sg:province":"Buckinghamshire",
    "sg:tags":[
        "club",
        "social"
    ],
    "wof:name":"Tring Conservative Club",
    "wof:placetype":"venue"
},
  "geometry": {"coordinates":[-0.663158,51.793591],"type":"Point"}
}