{
  "type": "Feature",
  "properties": {
    "addr:full":"Old Gasworks, Station Road Newton Abbot Devon TQ13 8SA",
    "addr:postcode":"tq13 8sa",
    "addr:street":"Old;Station Road",
    "iso:country":"GB",
    "sg:address":"Old Gasworks, Station Road",
    "sg:city":"Newton Abbot",
    "sg:classifiers":[
        {
            "category":"Home & Garden",
            "subcategory":"Hardware",
            "type":"Retail Goods"
        }
    ],
    "sg:phone":"+44 1647 440115",
    "sg:postcode":"TQ13 8SA",
    "sg:province":"Devon",
    "sg:tags":[
        "lawnmowers",
        "machinery"
    ],
    "wof:name":"J J Machinery",
    "wof:placetype":"venue"
},
  "geometry": {"coordinates":[-3.7588899136,50.6581192017],"type":"Point"}
}