{
  "type": "Feature",
  "properties": {
    "addr:full":"Harrop Street Mill Stalybridge Greater Manchester SK15 2AP",
    "addr:postcode":"sk15 2ap",
    "addr:street":"Harrop Street",
    "iso:country":"GB",
    "sg:address":"Harrop Street Mill",
    "sg:city":"Stalybridge",
    "sg:classifiers":[
        {
            "category":"Manufacturing",
            "subcategory":"Metals",
            "type":"Manufacturing & Wholesale Goods"
        }
    ],
    "sg:phone":"+44 161 338 6999",
    "sg:postcode":"SK15 2AP",
    "sg:province":"Greater Manchester",
    "sg:tags":[
        "work",
        "sheet"
    ],
    "wof:name":"J G Brown (Sheet Metal Workers) Ltd.",
    "wof:placetype":"venue"
},
  "geometry": {"coordinates":[-2.061449,53.48431],"type":"Point"}
}