{
  "type": "Feature",
  "properties": {
    "iso:country":"GB",
    "sg:address":"Portnellan House",
    "sg:city":"Crianlarich",
    "sg:classifiers":[
        {
            "category":"Travel",
            "subcategory":"Hotels & Motels",
            "type":"Entertainment"
        }
    ],
    "sg:phone":"+44 1838 300284",
    "sg:postcode":"FK20 8QS",
    "sg:province":"Argyll and Bute",
    "sg:tags":[
        "self",
        "catering"
    ],
    "wof:name":"Portnellan Lodge Estate",
    "wof:placetype":"venue"
},
  "geometry": {"coordinates":[-4.6189618111,56.3928947449],"type":"Point"}
}