{
  "type": "Feature",
  "properties": {
    "iso:country":"GB",
    "sg:address":"5 Gardeners Place, West Gillibrands",
    "sg:city":"Skelmersdale",
    "sg:classifiers":[
        {
            "category":"Manufacturing",
            "subcategory":"Metals",
            "type":"Manufacturing & Wholesale Goods"
        }
    ],
    "sg:phone":"+44 1695 727011",
    "sg:postcode":"WN8 9SP",
    "sg:province":"Lancashire",
    "sg:tags":[
        "steel",
        "fabricator",
        "erectors"
    ],
    "wof:name":"Lsf Realisations Ltd.",
    "wof:placetype":"venue"
},
  "geometry": {"coordinates":[-2.796729,53.545334],"type":"Point"}
}