{
  "type": "Feature",
  "properties": {
    "iso:country":"GB",
    "sg:address":"Unit 1 Graphic House",
    "sg:city":"Uxbridge",
    "sg:classifiers":[
        {
            "category":"Building & Trades",
            "subcategory":"Construction",
            "type":"Services"
        }
    ],
    "sg:phone":"+44 1895 613605",
    "sg:postcode":"UB10 8LE",
    "sg:province":"Greater London",
    "sg:tags":[
        "pipework",
        "contractor"
    ],
    "wof:name":"Central Pipework Services",
    "wof:placetype":"venue"
},
  "geometry": {"coordinates":[-0.449289,51.562481],"type":"Point"}
}