{
  "type": "Feature",
  "properties": {
    "iso:country":"GB",
    "sg:address":"61 Green Street, Milton Malsor",
    "sg:city":"Northampton",
    "sg:classifiers":[
        {
            "category":"Bars & Pubs",
            "type":"Food & Drink"
        }
    ],
    "sg:phone":"+44 1604 858365",
    "sg:postcode":"NN7 3AT",
    "sg:province":"Buckinghamshire",
    "sg:tags":[
        "pubs",
        "inn"
    ],
    "wof:name":"The Compass",
    "wof:placetype":"venue"
},
  "geometry": {"coordinates":[-0.9275289774,52.1931800842],"type":"Point"}
}