{
  "type": "Feature",
  "properties": {
    "iso:country":"GB",
    "sg:address":"Brackenrigg, Cardurnock",
    "sg:city":"Carlisle",
    "sg:classifiers":[
        {
            "category":"Communications",
            "subcategory":"Newspaper",
            "type":"Services"
        }
    ],
    "sg:phone":"+44 16973 52163",
    "sg:postcode":"CA5 5AQ",
    "sg:province":"Cumbria",
    "sg:tags":[
        "magazine"
    ],
    "wof:name":"Modern Astronomer The",
    "wof:placetype":"venue"
},
  "geometry": {"coordinates":[-3.1860690117,54.9476242065],"type":"Point"}
}