{
  "type": "Feature",
  "properties": {
    "addr:full":"25 Holbein Clo Basingstoke Hampshire RG21 3EX",
    "addr:postcode":"rg21 3ex",
    "iso:country":"GB",
    "sg:address":"25 Holbein Clo",
    "sg:city":"Basingstoke",
    "sg:classifiers":[
        {
            "category":"Home & Garden",
            "subcategory":"Building Materials",
            "type":"Retail Goods"
        }
    ],
    "sg:postcode":"RG21 3EX",
    "sg:province":"Hampshire",
    "sg:tags":[
        "garage",
        "door"
    ],
    "wof:name":"Esrun",
    "wof:placetype":"venue"
},
  "geometry": {"coordinates":[-1.0733239651,51.2574272156],"type":"Point"}
}