{
  "type": "Feature",
  "properties": {
    "iso:country":"GB",
    "sg:address":"Bournemouth Airport",
    "sg:city":"Christchurch",
    "sg:classifiers":[
        {
            "category":"Airline",
            "type":"Transportation"
        }
    ],
    "sg:phone":"+44 1202 364000",
    "sg:postcode":"BH23 6SE",
    "sg:province":"Dorset",
    "sg:tags":[
        "airport"
    ],
    "wof:name":"Bournemouth International Airport Ltd",
    "wof:placetype":"venue"
},
  "geometry": {"coordinates":[-1.8321199417,50.7791900635],"type":"Point"}
}