{
  "type": "Feature",
  "properties": {
    "iso:country":"GB",
    "sg:address":"7 Hughes Road",
    "sg:city":"Wokingham",
    "sg:classifiers":[
        {
            "category":"Professional",
            "subcategory":"Employment Agencies",
            "type":"Services"
        }
    ],
    "sg:phone":"+44 118 961 9249",
    "sg:postcode":"RG40 1UL",
    "sg:province":"Berkshire",
    "sg:tags":[
        "consultant"
    ],
    "wof:name":"M & L Manhire",
    "wof:placetype":"venue"
},
  "geometry": {"coordinates":[-0.821182,51.416233],"type":"Point"}
}