{
  "type": "Feature",
  "properties": {
    "addr:full":"Wootton Hill Farm, Gorse Lane, Wootton Wawen Solihull Warwickshire B95 6BL",
    "addr:postcode":"b95 6bl",
    "addr:street":"Wootton Hill;Gorse Lane",
    "iso:country":"GB",
    "sg:address":"Wootton Hill Farm, Gorse Lane, Wootton Wawen",
    "sg:city":"Solihull",
    "sg:classifiers":[
        {
            "category":"Farming",
            "subcategory":"Crops",
            "type":"Manufacturing & Wholesale Goods"
        },
        {
            "category":"Farming",
            "subcategory":"Farm",
            "type":"Manufacturing & Wholesale Goods"
        }
    ],
    "sg:phone":"+44 1564 792164",
    "sg:postcode":"B95 6BL",
    "sg:province":"Warwickshire",
    "sg:tags":[
        "mixed",
        "arable"
    ],
    "wof:name":"G J Hollands",
    "wof:placetype":"venue"
},
  "geometry": {"coordinates":[-1.7837690115,52.2669143677],"type":"Point"}
}