{
  "type": "Feature",
  "properties": {
    "addr:full":"2 Gloucester Close Chippenham Gloucestershire SN14 0NS",
    "addr:housenumber":"2",
    "addr:postcode":"sn14 0ns",
    "addr:street":"Gloucester Close",
    "iso:country":"GB",
    "sg:address":"2 Gloucester Close",
    "sg:city":"Chippenham",
    "sg:classifiers":[
        {
            "category":"Professional",
            "subcategory":"Business Services",
            "type":"Services"
        }
    ],
    "sg:phone":"+44 1249 464104",
    "sg:postcode":"SN14 0NS",
    "sg:province":"Gloucestershire",
    "sg:tags":[
        "import",
        "export",
        "agent"
    ],
    "wof:name":"Allied Trade Links Ltd.",
    "wof:placetype":"venue"
},
  "geometry": {"coordinates":[-2.143631,51.452438],"type":"Point"}
}