{
  "type": "Feature",
  "properties": {
    "addr:full":"Baltic Chambers Glasgow Glasgow City G2 6HJ",
    "addr:postcode":"g2 6hj",
    "iso:country":"GB",
    "sg:address":"Baltic Chambers",
    "sg:city":"Glasgow",
    "sg:classifiers":[
        {
            "category":"Professional",
            "subcategory":"Accounting & Tax Preparation",
            "type":"Services"
        }
    ],
    "sg:phone":"+44 141 221 9922",
    "sg:postcode":"G2 6HJ",
    "sg:province":"Glasgow City",
    "sg:tags":[
        "accountant"
    ],
    "wof:name":"Steel Robertson & Co.",
    "wof:placetype":"venue"
},
  "geometry": {"coordinates":[-4.26076,55.85918],"type":"Point"}
}