{
  "type": "Feature",
  "properties": {
    "addr:full":"58 Avenue Road Bexleyheath Kent DA7 4EG",
    "addr:housenumber":"58",
    "addr:postcode":"da7 4eg",
    "addr:street":"Avenue Road",
    "iso:country":"GB",
    "sg:address":"58 Avenue Road",
    "sg:city":"Bexleyheath",
    "sg:classifiers":[
        {
            "category":"Autos & Motor Vehicles",
            "subcategory":"Automobile Sales",
            "type":"Retail Goods"
        }
    ],
    "sg:postcode":"DA7 4EG",
    "sg:province":"Kent",
    "sg:tags":[
        "car"
    ],
    "wof:name":"Coast to Coast Mpvs",
    "wof:placetype":"venue"
},
  "geometry": {"coordinates":[0.132523,51.462784],"type":"Point"}
}