{
  "type": "Feature",
  "properties": {
    "iso:country":"GB",
    "sg:address":"199 Bradley Road",
    "sg:city":"Huddersfield",
    "sg:classifiers":[
        {
            "category":"Bars & Pubs",
            "type":"Food & Drink"
        }
    ],
    "sg:phone":"+44 1484 421432",
    "sg:postcode":"HD2 1QE",
    "sg:province":"West Yorkshire",
    "sg:tags":[
        "pubs",
        "inn"
    ],
    "wof:name":"The Badger Hotel",
    "wof:placetype":"venue"
},
  "geometry": {"coordinates":[-1.753149,53.68261],"type":"Point"}
}