{
  "type": "Feature",
  "properties": {
    "addr:full":"Church Road, Brean Burnham-on-sea Somerset TA8 2SF",
    "addr:postcode":"ta8 2sf",
    "addr:street":"Church Road",
    "iso:country":"GB",
    "sg:address":"Church Road, Brean",
    "sg:city":"Burnham-on-sea",
    "sg:classifiers":[
        {
            "category":"Travel",
            "subcategory":"Hotels & Motels",
            "type":"Entertainment"
        }
    ],
    "sg:phone":"+44 1278 751392",
    "sg:postcode":"TA8 2SF",
    "sg:province":"Somerset",
    "sg:tags":[
        "self",
        "catering"
    ],
    "wof:name":"Richmond Shirley & Peter",
    "wof:placetype":"venue"
},
  "geometry": {"coordinates":[-3.0106320381,51.2938652039],"type":"Point"}
}