{
  "type": "Feature",
  "properties": {
    "addr:full":"124 High Street Winsford Cheshire CW7 2AP",
    "addr:housenumber":"124",
    "addr:postcode":"cw7 2ap",
    "addr:street":"High Street",
    "iso:country":"GB",
    "sg:address":"124 High Street",
    "sg:city":"Winsford",
    "sg:classifiers":[
        {
            "category":"Shopping",
            "subcategory":"Crafts & Fabrics",
            "type":"Retail Goods"
        }
    ],
    "sg:phone":"+44 1606 593554",
    "sg:postcode":"CW7 2AP",
    "sg:province":"Cheshire",
    "sg:tags":[
        "machine",
        "sewing",
        "knitting"
    ],
    "wof:name":"Allan A Sheen",
    "wof:placetype":"venue"
},
  "geometry": {"coordinates":[-2.523753,53.192635],"type":"Point"}
}