{
  "type": "Feature",
  "properties": {
    "iso:country":"GB",
    "sg:address":"179 Corporation Street",
    "sg:city":"Birmingham",
    "sg:classifiers":[
        {
            "category":"Personal",
            "subcategory":"Beauty Salon",
            "type":"Services"
        }
    ],
    "sg:postcode":"B4 6RG",
    "sg:province":"West Midlands",
    "sg:tags":[
        "unisex",
        "hairdresser"
    ],
    "wof:name":"Cirrus",
    "wof:placetype":"venue"
},
  "geometry": {"coordinates":[-1.8929829597,52.4837760925],"type":"Point"}
}