{
  "type": "Feature",
  "properties": {
    "addr:full":"Unit 8, 207 Torrington Avenue Coventry Warwickshire CV4 9AP",
    "addr:housenumber":"unit 8 207",
    "addr:postcode":"cv4 9ap",
    "addr:street":"Torrington Avenue",
    "iso:country":"GB",
    "sg:address":"Unit 8, 207 Torrington Avenue",
    "sg:city":"Coventry",
    "sg:classifiers":[
        {
            "category":"Manufacturing",
            "subcategory":"Wood Products",
            "type":"Manufacturing & Wholesale Goods"
        },
        {
            "category":"Building & Trades",
            "subcategory":"Construction",
            "type":"Services"
        }
    ],
    "sg:phone":"+44 24 7647 4116",
    "sg:postcode":"CV4 9AP",
    "sg:province":"Warwickshire",
    "sg:tags":[
        "joinery",
        "manufacturer"
    ],
    "wof:name":"Norman Joinery Coventry Ltd",
    "wof:placetype":"venue"
},
  "geometry": {"coordinates":[-1.5669980049,52.3986701965],"type":"Point"}
}