{
  "type": "Feature",
  "properties": {
    "addr:full":"38 Brook Street Chester Cheshire CH1 3DZ",
    "addr:housenumber":"38",
    "addr:postcode":"ch1 3dz",
    "addr:street":"Brook Street",
    "iso:country":"GB",
    "sg:address":"38 Brook Street",
    "sg:city":"Chester",
    "sg:classifiers":[
        {
            "category":"Shopping",
            "subcategory":"Clothing, Apparel, & Fashions",
            "type":"Retail Goods"
        }
    ],
    "sg:phone":"+44 1244 316230",
    "sg:postcode":"CH1 3DZ",
    "sg:province":"Cheshire",
    "sg:tags":[
        "dresswear"
    ],
    "wof:name":"Classic",
    "wof:placetype":"venue"
},
  "geometry": {"coordinates":[-2.8862919807,53.194683075],"type":"Point"}
}