{
  "type": "Feature",
  "properties": {
    "iso:country":"GB",
    "sg:address":"Golf Road, Abersoch",
    "sg:city":"Pwllheli",
    "sg:classifiers":[
        {
            "category":"Social Services",
            "subcategory":"Retirement Home",
            "type":"Services"
        }
    ],
    "sg:phone":"+44 1758 712178",
    "sg:postcode":"LL53 7EF",
    "sg:province":"Gwynedd",
    "sg:tags":[
        "residential",
        "care"
    ],
    "wof:name":"Trofa Residential Home",
    "wof:placetype":"venue"
},
  "geometry": {"coordinates":[-4.505129,52.827404],"type":"Point"}
}