{
  "type": "Feature",
  "properties": {
    "iso:country":"GB",
    "sg:address":"32a Hanover Buildings",
    "sg:city":"Southampton",
    "sg:classifiers":[
        {
            "category":"Shopping",
            "subcategory":"Comic Books",
            "type":"Retail Goods"
        }
    ],
    "sg:phone":"+44 23 8033 2448",
    "sg:postcode":"SO14 1JU",
    "sg:province":"Hampshire",
    "sg:tags":[
        "jeweller"
    ],
    "wof:name":"Eclipse",
    "wof:placetype":"venue"
},
  "geometry": {"coordinates":[-1.404339,50.902882],"type":"Point"}
}