{
  "type": "Feature",
  "properties": {
    "addr:full":"Monks Hill, Westbourne Emsworth Hampshire PO10 8SX",
    "addr:postcode":"po10 8sx",
    "addr:street":"Monks;Westbourne",
    "iso:country":"GB",
    "sg:address":"Monks Hill, Westbourne",
    "sg:city":"Emsworth",
    "sg:classifiers":[
        {
            "category":"Sports & Exercise",
            "subcategory":"Stables",
            "type":"Entertainment"
        }
    ],
    "sg:postcode":"PO10 8SX",
    "sg:province":"Hampshire",
    "sg:tags":[
        "education",
        "equestrian"
    ],
    "wof:name":"Valley Farm Livery Stables",
    "wof:placetype":"venue"
},
  "geometry": {"coordinates":[-0.9246900082,50.8617019653],"type":"Point"}
}