{
  "type": "Feature",
  "properties": {
    "addr:full":"12-13 Little Newport Street London Greater London WC2H 7JJ",
    "addr:housenumber":"12-13",
    "addr:postcode":"wc2h 7jj",
    "addr:street":"Little Newport Street",
    "iso:country":"GB",
    "sg:address":"12-13 Little Newport Street",
    "sg:city":"London",
    "sg:classifiers":[
        {
            "category":"Recreation",
            "subcategory":"Gun Range",
            "type":"Entertainment"
        }
    ],
    "sg:phone":"+44 20 7287 0237",
    "sg:postcode":"WC2H 7JJ",
    "sg:province":"Greater London",
    "sg:tags":[
        "operator",
        "tour"
    ],
    "wof:name":"Network Europa Travel Pte Ltd.",
    "wof:placetype":"venue"
},
  "geometry": {"coordinates":[-0.128799,51.511856],"type":"Point"}
}