{
  "type": "Feature",
  "properties": {
    "iso:country":"GB",
    "sg:address":"Market Street",
    "sg:city":"Ely",
    "sg:classifiers":[
        {
            "category":"Shopping",
            "subcategory":"Clothing, Apparel, & Fashions",
            "type":"Retail Goods"
        }
    ],
    "sg:phone":"+44 1353 650347",
    "sg:postcode":"CB7 4PB",
    "sg:province":"Cambridgeshire",
    "sg:tags":[
        "ladieswear"
    ],
    "wof:name":"Mackays",
    "wof:placetype":"venue"
},
  "geometry": {"coordinates":[0.2633849978,52.4003257751],"type":"Point"}
}