{
  "type": "Feature",
  "properties": {
    "addr:full":"Unit 17-18 Greenholme Mills, Iron Row Ilkley North Yorkshire LS29 7DB",
    "addr:housenumber":"unit 17-18",
    "addr:postcode":"ls29 7db",
    "addr:street":"Greenholme Mills Iron Row",
    "iso:country":"GB",
    "sg:address":"Unit 17-18 Greenholme Mills, Iron Row",
    "sg:city":"Ilkley",
    "sg:classifiers":[
        {
            "category":"Home & Garden",
            "subcategory":"Building Materials",
            "type":"Retail Goods"
        }
    ],
    "sg:phone":"+44 1943 864999",
    "sg:postcode":"LS29 7DB",
    "sg:province":"North Yorkshire",
    "sg:tags":[
        "furnishers",
        "bathroom",
        "planner"
    ],
    "wof:name":"Wharfedale",
    "wof:placetype":"venue"
},
  "geometry": {"coordinates":[-1.821754,53.924461],"type":"Point"}
}