{
  "type": "Feature",
  "properties": {
    "addr:full":"3 Summerfield Terrace, Inverallochy Fraserburgh Aberdeenshire AB43 8WB",
    "addr:housenumber":"3",
    "addr:postcode":"ab43 8wb",
    "addr:street":"Summerfield Terrace",
    "iso:country":"GB",
    "sg:address":"3 Summerfield Terrace, Inverallochy",
    "sg:city":"Fraserburgh",
    "sg:classifiers":[
        {
            "category":"Building & Trades",
            "subcategory":"Cleaning & Sanitation",
            "type":"Services"
        }
    ],
    "sg:phone":"+44 1346 582741",
    "sg:postcode":"AB43 8WB",
    "sg:province":"Aberdeenshire",
    "sg:tags":[
        "sweep",
        "chimney"
    ],
    "wof:name":"Alistair Cruickshank",
    "wof:placetype":"venue"
},
  "geometry": {"coordinates":[-1.9322930574,57.6738052368],"type":"Point"}
}