{
  "type": "Feature",
  "properties": {
    "addr:full":"21 Glencaple Avenue, Castledykes Dumfries Dumfries and Galloway DG1 4SH",
    "addr:housenumber":"21",
    "addr:postcode":"dg1 4sh",
    "addr:street":"Glencaple Avenue Castledykes",
    "iso:country":"GB",
    "sg:address":"21 Glencaple Avenue, Castledykes",
    "sg:city":"Dumfries",
    "sg:classifiers":[
        {
            "category":"Freight",
            "type":"Transportation"
        }
    ],
    "sg:phone":"+44 1387 253508",
    "sg:postcode":"DG1 4SH",
    "sg:province":"Dumfries and Galloway",
    "sg:tags":[
        "haulage",
        "road"
    ],
    "wof:name":"James B Kerr Haulage",
    "wof:placetype":"venue"
},
  "geometry": {"coordinates":[-3.602339,55.054565],"type":"Point"}
}