{
  "type": "Feature",
  "properties": {
    "addr:full":"12 Stapleford End Wickford Essex SS11 8XT",
    "addr:housenumber":"12",
    "addr:postcode":"ss11 8xt",
    "addr:street":"Stapleford End",
    "iso:country":"GB",
    "sg:address":"12 Stapleford End",
    "sg:city":"Wickford",
    "sg:classifiers":[
        {
            "category":"Professional",
            "subcategory":"Printing & Photocopies",
            "type":"Services"
        }
    ],
    "sg:phone":"+44 1268 747470",
    "sg:postcode":"SS11 8XT",
    "sg:province":"Essex",
    "sg:tags":[
        "duplicating",
        "copying"
    ],
    "wof:name":"Crystal Copiers Ltd",
    "wof:placetype":"venue"
},
  "geometry": {"coordinates":[0.548834,51.603374],"type":"Point"}
}