{
  "type": "Feature",
  "properties": {
    "iso:country":"GB",
    "sg:address":"Colum Road",
    "sg:city":"Cardiff",
    "sg:classifiers":[
        {
            "category":"Social Services",
            "subcategory":"Retirement Home",
            "type":"Services"
        }
    ],
    "sg:phone":"+44 29 2022 0943",
    "sg:postcode":"CF10 3UN",
    "sg:province":"Cardiff",
    "sg:tags":[
        "residential",
        "care"
    ],
    "wof:name":"Nazareth House",
    "wof:placetype":"venue"
},
  "geometry": {"coordinates":[-3.188657,51.492718],"type":"Point"}
}