{
  "type": "Feature",
  "properties": {
    "addr:full":"Fairway Bristol City of Bristol BS4 5DF",
    "addr:postcode":"bs4 5df",
    "addr:street":"Fairway",
    "iso:country":"GB",
    "sg:address":"Fairway",
    "sg:city":"Bristol",
    "sg:classifiers":[
        {
            "category":"Sports & Exercise",
            "subcategory":"Golf",
            "type":"Entertainment"
        }
    ],
    "sg:phone":"+44 117 977 9193",
    "sg:postcode":"BS4 5DF",
    "sg:province":"City of Bristol",
    "sg:tags":[
        "equipment"
    ],
    "wof:name":"R Haywood Professional Shop",
    "wof:placetype":"venue"
},
  "geometry": {"coordinates":[-2.5496439934,51.4275016785],"type":"Point"}
}