{
  "type": "Feature",
  "properties": {
    "iso:country":"GB",
    "sg:address":"51 Totnes Rd",
    "sg:city":"Paignton",
    "sg:classifiers":[
        {
            "category":"Social Services",
            "subcategory":"Adult Care",
            "type":"Services"
        }
    ],
    "sg:phone":"+44 1803 557801",
    "sg:postcode":"TQ4 5LE",
    "sg:province":"Devon",
    "sg:tags":[
        "day",
        "centre"
    ],
    "wof:name":"Day Break Club",
    "wof:placetype":"venue"
},
  "geometry": {"coordinates":[-3.5722720623,50.4327735901],"type":"Point"}
}