{
  "type": "Feature",
  "properties": {
    "addr:full":"133 High Street, Wootton Bassett Swindon Wiltshire SN4 7AY",
    "addr:housenumber":"133",
    "addr:postcode":"sn4 7ay",
    "addr:street":"High Street",
    "iso:country":"GB",
    "sg:address":"133 High Street, Wootton Bassett",
    "sg:city":"Swindon",
    "sg:classifiers":[
        {
            "category":"Shopping",
            "subcategory":"Pharmacy",
            "type":"Retail Goods"
        }
    ],
    "sg:phone":"+44 1793 852364",
    "sg:postcode":"SN4 7AY",
    "sg:province":"Wiltshire",
    "sg:tags":[
        "pharmacist",
        "chemist"
    ],
    "wof:name":"Boots the Chemist",
    "wof:placetype":"venue"
},
  "geometry": {"coordinates":[-1.903758049,51.5421447754],"type":"Point"}
}