{
  "type": "Feature",
  "properties": {
    "iso:country":"GB",
    "sg:address":"Walker Clo",
    "sg:city":"Newark",
    "sg:classifiers":[
        {
            "category":"Social Services",
            "subcategory":"Retirement Home",
            "type":"Services"
        }
    ],
    "sg:phone":"+44 1636 673548",
    "sg:postcode":"NG24 4BP",
    "sg:province":"Nottinghamshire",
    "sg:tags":[
        "residential",
        "care"
    ],
    "wof:name":"Woods Court",
    "wof:placetype":"venue"
},
  "geometry": {"coordinates":[-0.8039219975,53.0705108643],"type":"Point"}
}