{
  "type": "Feature",
  "properties": {
    "iso:country":"GB",
    "sg:address":"34 Stoneyhurst, Briar Hill",
    "sg:city":"Northampton",
    "sg:classifiers":[
        {
            "category":"Home & Garden",
            "subcategory":"Home Furnishings",
            "type":"Retail Goods"
        }
    ],
    "sg:phone":"+44 1604 705074",
    "sg:postcode":"NN4 8SY",
    "sg:province":"Northamptonshire",
    "sg:tags":[
        "furnishers",
        "planner",
        "bedroom"
    ],
    "wof:name":"M K Smith",
    "wof:placetype":"venue"
},
  "geometry": {"coordinates":[-0.918328,52.225304],"type":"Point"}
}