{
  "type": "Feature",
  "properties": {
    "addr:full":"86 Long La Uxbridge Greater London UB10 8SX",
    "addr:housenumber":"86",
    "addr:postcode":"ub10 8sx",
    "addr:street":"Long La Uxbridge",
    "iso:country":"GB",
    "sg:address":"86 Long La",
    "sg:city":"Uxbridge",
    "sg:classifiers":[
        {
            "category":"Education",
            "subcategory":"School",
            "type":"Public Place"
        }
    ],
    "sg:phone":"+44 1895 676788",
    "sg:postcode":"UB10 8SX",
    "sg:province":"Greater London",
    "sg:tags":[
        "college"
    ],
    "wof:name":"Douay Martyrs Lower School",
    "wof:placetype":"venue"
},
  "geometry": {"coordinates":[-0.445786,51.55759],"type":"Point"}
}