{
  "type": "Feature",
  "properties": {
    "addr:full":"Carters Cottage, Fir Toll Rd Mayfield East Sussex TN20 6NG",
    "addr:postcode":"tn20 6ng",
    "addr:street":"Fir Toll Rd",
    "iso:country":"GB",
    "sg:address":"Carters Cottage, Fir Toll Rd",
    "sg:city":"Mayfield",
    "sg:classifiers":[
        {
            "category":"Professional",
            "subcategory":"Art Services",
            "type":"Services"
        }
    ],
    "sg:phone":"+44 1435 873833",
    "sg:postcode":"TN20 6NG",
    "sg:province":"East Sussex",
    "sg:tags":[
        "consultant",
        "design"
    ],
    "wof:name":"D P A Design Ltd",
    "wof:placetype":"venue"
},
  "geometry": {"coordinates":[0.2587350011,51.0200042725],"type":"Point"}
}