{
  "type": "Feature",
  "properties": {
    "iso:country":"GB",
    "sg:address":"917 Finchley Road, Golders Green",
    "sg:city":"London",
    "sg:classifiers":[
        {
            "category":"Retail",
            "subcategory":"Auto Repair",
            "type":"Services"
        }
    ],
    "sg:phone":"+44 20 8731 6033",
    "sg:postcode":"NW11 8DL",
    "sg:province":"Greater London",
    "sg:tags":[
        "modification",
        "garage"
    ],
    "wof:name":"Mario Auto Repairs Ltd.",
    "wof:placetype":"venue"
},
  "geometry": {"coordinates":[-0.1955190003,51.571849823],"type":"Point"}
}