{
  "type": "Feature",
  "properties": {
    "iso:country":"GB",
    "sg:address":"Cromwell Road",
    "sg:city":"Preston",
    "sg:classifiers":[
        {
            "category":"Retail",
            "subcategory":"Storage",
            "type":"Services"
        }
    ],
    "sg:phone":"+44 1772 796117",
    "sg:postcode":"PR2 6YD",
    "sg:province":"Lancashire",
    "sg:tags":[
        "cold"
    ],
    "wof:name":"Preston Cold Store Ltd.",
    "wof:placetype":"venue"
},
  "geometry": {"coordinates":[-2.674459,53.780704],"type":"Point"}
}