{
  "type": "Feature",
  "properties": {
    "addr:full":"371 Bath Rd, Arnos Vale Bristol City of Bristol BS4 3EU",
    "addr:housenumber":"371",
    "addr:postcode":"bs4 3eu",
    "addr:street":"Bath Rd",
    "iso:country":"GB",
    "sg:address":"371 Bath Rd, Arnos Vale",
    "sg:city":"Bristol",
    "sg:phone":"+44 117 977 6060",
    "sg:postcode":"BS4 3EU",
    "sg:province":"City of Bristol",
    "wof:name":"L & D Motors",
    "wof:placetype":"venue"
},
  "geometry": {"coordinates":[-2.563667,51.442333],"type":"Point"}
}