{
  "type": "Feature",
  "properties": {
    "iso:country":"GB",
    "sg:address":"The Yard, Kelston Road Lane",
    "sg:city":"Cardiff",
    "sg:classifiers":[
        {
            "category":"Building & Trades",
            "subcategory":"Construction",
            "type":"Services"
        }
    ],
    "sg:phone":"+44 29 2048 0011",
    "sg:postcode":"CF14 3BQ",
    "sg:province":"Cardiff",
    "sg:tags":[
        "guttering"
    ],
    "wof:name":"Eros Felt Roofing Services Ltd.",
    "wof:placetype":"venue"
},
  "geometry": {"coordinates":[-3.1958899498,51.5033988953],"type":"Point"}
}