{
  "type": "Feature",
  "properties": {
    "addr:full":"Bradford Ho, High St Pwllheli Gwynedd LL53 6HD",
    "addr:postcode":"ll53 6hd",
    "addr:street":"High St",
    "iso:country":"GB",
    "sg:address":"Bradford Ho, High St",
    "sg:city":"Pwllheli",
    "sg:classifiers":[
        {
            "category":"Building & Trades",
            "subcategory":"Construction",
            "type":"Services"
        }
    ],
    "sg:phone":"+44 1758 721357",
    "sg:postcode":"LL53 6HD",
    "sg:province":"Gwynedd",
    "sg:tags":[
        "joinery"
    ],
    "wof:name":"T Jones",
    "wof:placetype":"venue"
},
  "geometry": {"coordinates":[-4.4143137932,52.8898468018],"type":"Point"}
}