{
  "type": "Feature",
  "properties": {
    "iso:country":"GB",
    "sg:address":"234 Lockwood Road",
    "sg:city":"Huddersfield",
    "sg:classifiers":[
        {
            "category":"Professional",
            "subcategory":"Testing Lab",
            "type":"Services"
        }
    ],
    "sg:phone":"+44 1484 516610",
    "sg:postcode":"HD1 3TG",
    "sg:province":"West Yorkshire",
    "sg:tags":[
        "mot"
    ],
    "wof:name":"Lockwood Road Motorcycles",
    "wof:placetype":"venue"
},
  "geometry": {"coordinates":[-1.794597,53.633808],"type":"Point"}
}