{
  "type": "Feature",
  "properties": {
    "iso:country":"GB",
    "sg:address":"Boyn Hill Ave",
    "sg:city":"Maidenhead",
    "sg:classifiers":[
        {
            "category":"Social Services",
            "subcategory":"Adult Care",
            "type":"Services"
        }
    ],
    "sg:postcode":"SL6 4ES",
    "sg:province":"Berkshire",
    "sg:tags":[
        "housing",
        "sheltered"
    ],
    "wof:name":"Maidenhead & District Housing Associatio",
    "wof:placetype":"venue"
},
  "geometry": {"coordinates":[-0.731294,51.521187],"type":"Point"}
}