{
  "type": "Feature",
  "properties": {
    "iso:country":"GB",
    "sg:address":"Old Lane, Holbrook Industrial Estate, Halfway",
    "sg:city":"Sheffield",
    "sg:classifiers":[
        {
            "category":"Professional",
            "subcategory":"Business Services",
            "type":"Services"
        }
    ],
    "sg:phone":"+44 114 251 1133",
    "sg:postcode":"S20 3GZ",
    "sg:province":"South Yorkshire",
    "sg:tags":[
        "holding"
    ],
    "wof:name":"W M T Holdings Plc",
    "wof:placetype":"venue"
},
  "geometry": {"coordinates":[-1.3403539658,53.3267784119],"type":"Point"}
}