{
  "type": "Feature",
  "properties": {
    "iso:country":"GB",
    "sg:address":"High Street, Brading",
    "sg:city":"Sandown",
    "sg:classifiers":[
        {
            "category":"Museum",
            "subcategory":"Art Museum",
            "type":"Entertainment"
        }
    ],
    "sg:postcode":"PO36 0DJ",
    "sg:province":"Isle of Wight",
    "sg:tags":[
        "gallery"
    ],
    "wof:name":"Lilliput Dolls & Toy Museum",
    "wof:placetype":"venue"
},
  "geometry": {"coordinates":[-1.1432939768,50.6819496155],"type":"Point"}
}