{
  "type": "Feature",
  "properties": {
    "addr:full":"Willow Corner, 7 Ackrells Mead Sandhurst Berkshire GU47 8JJ",
    "addr:housenumber":"7",
    "addr:postcode":"gu47 8jj",
    "addr:street":"Ackrells Mead",
    "iso:country":"GB",
    "sg:address":"Willow Corner, 7 Ackrells Mead",
    "sg:city":"Sandhurst",
    "sg:classifiers":[
        {
            "category":"Professional",
            "subcategory":"Computer Services",
            "type":"Services"
        }
    ],
    "sg:postcode":"GU47 8JJ",
    "sg:province":"Berkshire",
    "sg:tags":[
        "system",
        "software"
    ],
    "wof:name":"Late Summer Ltd",
    "wof:placetype":"venue"
},
  "geometry": {"coordinates":[-0.807099,51.354084],"type":"Point"}
}