{
  "type": "Feature",
  "properties": {
    "addr:full":"61 Queens Rd Weybridge Surrey KT13 9UQ",
    "addr:housenumber":"61",
    "addr:postcode":"kt13 9uq",
    "addr:street":"Queens Rd",
    "iso:country":"GB",
    "sg:address":"61 Queens Rd",
    "sg:city":"Weybridge",
    "sg:classifiers":[
        {
            "category":"Food & Beverages",
            "subcategory":"Liquor & Beverages",
            "type":"Retail Goods"
        }
    ],
    "sg:phone":"+44 1932 821284",
    "sg:postcode":"KT13 9UQ",
    "sg:province":"Surrey",
    "sg:tags":[
        "beer",
        "spirit",
        "wines"
    ],
    "wof:name":"Wine Heritage",
    "wof:placetype":"venue"
},
  "geometry": {"coordinates":[-0.445549,51.368042],"type":"Point"}
}