{
  "type": "Feature",
  "properties": {
    "addr:full":"54 Kenilworth Road Coventry Warwickshire CV7 7EX",
    "addr:housenumber":"54",
    "addr:postcode":"cv7 7ex",
    "addr:street":"Kenilworth Road",
    "iso:country":"GB",
    "sg:address":"54 Kenilworth Road",
    "sg:city":"Coventry",
    "sg:classifiers":[
        {
            "category":"Autos & Motor Vehicles",
            "subcategory":"Automobile Sales",
            "type":"Retail Goods"
        }
    ],
    "sg:phone":"+44 1676 534089",
    "sg:postcode":"CV7 7EX",
    "sg:province":"Warwickshire",
    "sg:tags":[
        "car"
    ],
    "wof:name":"Mastercar",
    "wof:placetype":"venue"
},
  "geometry": {"coordinates":[-1.657061,52.401119],"type":"Point"}
}