{
  "type": "Feature",
  "properties": {
    "iso:country":"GB",
    "sg:address":"Tweedale",
    "sg:city":"Fort William",
    "sg:classifiers":[
        {
            "category":"Health Services",
            "subcategory":"Doctor",
            "type":"Services"
        }
    ],
    "sg:postcode":"PH33 6EU",
    "sg:province":"Highland",
    "sg:tags":[
        "practitioners"
    ],
    "wof:name":"J Munro",
    "wof:placetype":"venue"
},
  "geometry": {"coordinates":[-5.1084589958,56.8184318542],"type":"Point"}
}