{
  "type": "Feature",
  "properties": {
    "addr:full":"627 Southleigh Road Emsworth Hampshire PO10 7TE",
    "addr:housenumber":"627",
    "addr:postcode":"po10 7te",
    "addr:street":"Southleigh Road",
    "iso:country":"GB",
    "sg:address":"627 Southleigh Road",
    "sg:city":"Emsworth",
    "sg:classifiers":[
        {
            "category":"Retail",
            "subcategory":"Repair Shop",
            "type":"Services"
        }
    ],
    "sg:postcode":"PO10 7TE",
    "sg:province":"Hampshire",
    "sg:tags":[
        "upholsterer"
    ],
    "wof:name":"Bognor Bedding & Reupholstery",
    "wof:placetype":"venue"
},
  "geometry": {"coordinates":[-0.93544,50.861397],"type":"Point"}
}