{
  "type": "Feature",
  "properties": {
    "addr:full":"29 Obelisk Way Camberley Berkshire GU15 3SG",
    "addr:housenumber":"29",
    "addr:postcode":"gu15 3sg",
    "addr:street":"Obelisk Way",
    "iso:country":"GB",
    "sg:address":"29 Obelisk Way",
    "sg:city":"Camberley",
    "sg:classifiers":[
        {
            "category":"Shopping",
            "subcategory":"Baby Store",
            "type":"Retail Goods"
        }
    ],
    "sg:phone":"+44 1276 64015",
    "sg:postcode":"GU15 3SG",
    "sg:province":"Berkshire",
    "sg:tags":[
        "babywear",
        "childrens"
    ],
    "wof:name":"Adams Childrenswear Ltd.",
    "wof:placetype":"venue"
},
  "geometry": {"coordinates":[-0.7450090051,51.3390197754],"type":"Point"}
}