{
  "type": "Feature",
  "properties": {
    "iso:country":"GB",
    "sg:address":"7 Ness Way",
    "sg:city":"Fortrose",
    "sg:classifiers":[
        {
            "category":"Social Services",
            "subcategory":"Job Training",
            "type":"Services"
        },
        {
            "category":"Education",
            "subcategory":"Special Training",
            "type":"Public Place"
        }
    ],
    "sg:phone":"+44 1381 621064",
    "sg:postcode":"IV10 8SS",
    "sg:province":"Highland",
    "sg:tags":[
        "product",
        "centre"
    ],
    "wof:name":"M H Training",
    "wof:placetype":"venue"
},
  "geometry": {"coordinates":[-4.111656,57.580284],"type":"Point"}
}