{
  "type": "Feature",
  "properties": {
    "addr:full":"213 Perry Wood Road, Great Barr Birmingham West Midlands B42 2BL",
    "addr:housenumber":"213",
    "addr:postcode":"b42 2bl",
    "addr:street":"Perry Wood Road",
    "iso:country":"GB",
    "sg:address":"213 Perry Wood Road, Great Barr",
    "sg:city":"Birmingham",
    "sg:classifiers":[
        {
            "category":"Professional",
            "subcategory":"Management & Consulting",
            "type":"Services"
        }
    ],
    "sg:postcode":"B42 2BL",
    "sg:province":"West Midlands",
    "sg:tags":[
        "consultant",
        "business"
    ],
    "wof:name":"Boomslang Defence Consultancy Ltd",
    "wof:placetype":"venue"
},
  "geometry": {"coordinates":[-1.926064,52.543499],"type":"Point"}
}