{
  "type": "Feature",
  "properties": {
    "addr:full":"Castle St Clitheroe Lancashire BB7 2BT",
    "addr:postcode":"bb7 2bt",
    "addr:street":"Castle St",
    "iso:country":"GB",
    "sg:address":"Castle St",
    "sg:city":"Clitheroe",
    "sg:classifiers":[
        {
            "category":"Travel",
            "subcategory":"Hotels & Motels",
            "type":"Entertainment"
        }
    ],
    "sg:postcode":"BB7 2BT",
    "sg:province":"Lancashire",
    "wof:name":"Starkie Arms (The)",
    "wof:placetype":"venue"
},
  "geometry": {"coordinates":[-2.39209795,53.8717575073],"type":"Point"}
}