{
  "type": "Feature",
  "properties": {
    "iso:country":"GB",
    "sg:address":"31 Colindale Avenue",
    "sg:city":"London",
    "sg:classifiers":[
        {
            "category":"Bars & Pubs",
            "type":"Food & Drink"
        }
    ],
    "sg:phone":"+44 20 8205 6854",
    "sg:postcode":"NW9 5DS",
    "sg:province":"Greater London",
    "sg:tags":[
        "pubs",
        "inn"
    ],
    "wof:name":"Punch Retail Ltd.",
    "wof:placetype":"venue"
},
  "geometry": {"coordinates":[-0.25522,51.593204],"type":"Point"}
}