{
  "type": "Feature",
  "properties": {
    "addr:full":"15 Greenway Lane Bath Somerset BA2 4LJ",
    "addr:housenumber":"15",
    "addr:postcode":"ba2 4lj",
    "addr:street":"Greenway Lane",
    "iso:country":"GB",
    "sg:address":"15 Greenway Lane",
    "sg:city":"Bath",
    "sg:classifiers":[
        {
            "category":"Professional",
            "subcategory":"Lawyer & Legal Services",
            "type":"Services"
        }
    ],
    "sg:postcode":"BA2 4LJ",
    "sg:province":"Somerset",
    "wof:name":"Hunts Consulting Forensic Engineers",
    "wof:placetype":"venue"
},
  "geometry": {"coordinates":[-2.3614559174,51.3704338074],"type":"Point"}
}