{
  "type": "Feature",
  "properties": {
    "iso:country":"GB",
    "sg:address":"Glencraigs Farm, Glencraigs",
    "sg:city":"Campbeltown",
    "sg:classifiers":[
        {
            "category":"Farming",
            "subcategory":"Dairy Farm",
            "type":"Manufacturing & Wholesale Goods"
        }
    ],
    "sg:phone":"+44 1586 552684",
    "sg:postcode":"PA28 6NS",
    "sg:province":"Argyll and Bute",
    "sg:tags":[
        "farmer"
    ],
    "wof:name":"Thomas Young & Sons",
    "wof:placetype":"venue"
},
  "geometry": {"coordinates":[-5.608384,55.426605],"type":"Point"}
}