{
  "type": "Feature",
  "properties": {
    "addr:full":"172 Empire Rd Greenford Greater London UB6 7EF",
    "addr:housenumber":"172",
    "addr:postcode":"ub6 7ef",
    "addr:street":"Empire Rd",
    "iso:country":"GB",
    "sg:address":"172 Empire Rd",
    "sg:city":"Greenford",
    "sg:classifiers":[
        {
            "category":"Arts & Performance",
            "subcategory":"Music",
            "type":"Entertainment"
        }
    ],
    "sg:phone":"+44 20 8991 1476",
    "sg:postcode":"UB6 7EF",
    "sg:province":"Greater London",
    "sg:tags":[
        "musician",
        "composer"
    ],
    "wof:name":"The Shakers Live Music",
    "wof:placetype":"venue"
},
  "geometry": {"coordinates":[-0.311834,51.5443],"type":"Point"}
}