{
  "type": "Feature",
  "properties": {
    "addr:full":"4a Station Road Heathfield East Sussex TN21 8LG",
    "addr:housenumber":"4a",
    "addr:postcode":"tn21 8lg",
    "addr:street":"Station Road",
    "iso:country":"GB",
    "sg:address":"4a Station Road",
    "sg:city":"Heathfield",
    "sg:classifiers":[
        {
            "category":"Shopping",
            "subcategory":"News",
            "type":"Retail Goods"
        }
    ],
    "sg:postcode":"TN21 8LG",
    "sg:province":"East Sussex",
    "sg:tags":[
        "newsagent"
    ],
    "wof:name":"Goodies Newsagents",
    "wof:placetype":"venue"
},
  "geometry": {"coordinates":[0.249942,50.969769],"type":"Point"}
}