{
  "type": "Feature",
  "properties": {
    "addr:full":"626 Liverpool Road, Eccles Manchester Greater Manchester M30 7NA",
    "addr:housenumber":"626",
    "addr:postcode":"m30 7na",
    "addr:street":"Liverpool Road",
    "iso:country":"GB",
    "sg:address":"626 Liverpool Road, Eccles",
    "sg:city":"Manchester",
    "sg:classifiers":[
        {
            "category":"Personal",
            "subcategory":"Beauty Salon",
            "type":"Services"
        }
    ],
    "sg:phone":"+44 161 789 7825",
    "sg:postcode":"M30 7NA",
    "sg:province":"Greater Manchester",
    "sg:tags":[
        "unisex",
        "hairdresser"
    ],
    "wof:name":"Talking Heads",
    "wof:placetype":"venue"
},
  "geometry": {"coordinates":[-2.3690710068,53.4771728516],"type":"Point"}
}