{
  "type": "Feature",
  "properties": {
    "iso:country":"GB",
    "sg:address":"323 Leeds Road",
    "sg:city":"Nelson",
    "sg:classifiers":[
        {
            "category":"Personal",
            "subcategory":"Beauty Salon",
            "type":"Services"
        }
    ],
    "sg:phone":"+44 1282 612213",
    "sg:postcode":"BB9 8RW",
    "sg:province":"Lancashire",
    "sg:tags":[
        "lady",
        "hairdresser"
    ],
    "wof:name":"Aileen Mason Hair Stylist",
    "wof:placetype":"venue"
},
  "geometry": {"coordinates":[-2.200469,53.843983],"type":"Point"}
}