{
  "type": "Feature",
  "properties": {
    "iso:country":"GB",
    "sg:address":"Verandah House, 29 Ipswich Rd",
    "sg:city":"Stowmarket",
    "sg:classifiers":[
        {
            "category":"Professional",
            "subcategory":"Advertising",
            "type":"Services"
        }
    ],
    "sg:phone":"+44 1449 616125",
    "sg:postcode":"IP14 1BD",
    "sg:province":"Suffolk",
    "sg:tags":[
        "agency"
    ],
    "wof:name":"Power Star Marketing Ltd",
    "wof:placetype":"venue"
},
  "geometry": {"coordinates":[0.99968,52.184299],"type":"Point"}
}