{
  "type": "Feature",
  "properties": {
    "iso:country":"GB",
    "sg:address":"12 Pilcher Gate",
    "sg:city":"Nottingham",
    "sg:classifiers":[
        {
            "category":"Organizations",
            "subcategory":"Non-profit Organization",
            "type":"Services"
        }
    ],
    "sg:phone":"+44 115 911 6666",
    "sg:postcode":"NG1 1QE",
    "sg:province":"Nottinghamshire",
    "sg:tags":[
        "organisation",
        "voluntary",
        "charity"
    ],
    "wof:name":"Business in the Community",
    "wof:placetype":"venue"
},
  "geometry": {"coordinates":[-1.1449689865,52.9521713257],"type":"Point"}
}