{
  "type": "Feature",
  "properties": {
    "addr:full":"Shields Rd Sunderland Tyne and Wear SR6 7PZ",
    "addr:postcode":"sr6 7pz",
    "addr:street":"Shields Rd",
    "iso:country":"GB",
    "sg:address":"Shields Rd",
    "sg:city":"Sunderland",
    "sg:classifiers":[
        {
            "category":"Autos & Motor Vehicles",
            "subcategory":"Fuel & Gas Station",
            "type":"Retail Goods"
        }
    ],
    "sg:phone":"+44 191 519 3911",
    "sg:postcode":"SR6 7PZ",
    "sg:province":"Tyne and Wear",
    "sg:tags":[
        "petrol",
        "filling"
    ],
    "wof:name":"T C S Total",
    "wof:placetype":"venue"
},
  "geometry": {"coordinates":[-1.4038200378,54.9586181641],"type":"Point"}
}