{
  "type": "Feature",
  "properties": {
    "iso:country":"GB",
    "sg:address":"Magdalen Road",
    "sg:city":"St Leonards-on-sea",
    "sg:classifiers":[
        {
            "category":"Education",
            "subcategory":"School",
            "type":"Public Place"
        }
    ],
    "sg:phone":"+44 1424 427801",
    "sg:postcode":"TN37 6EU",
    "sg:province":"East Sussex",
    "sg:tags":[
        "local",
        "authority"
    ],
    "wof:name":"St Mary-Star-of-the-Sea R C School",
    "wof:placetype":"venue"
},
  "geometry": {"coordinates":[0.5657200217,50.8579788208],"type":"Point"}
}