{
  "type": "Feature",
  "properties": {
    "addr:full":"23 Albemarle Avenue, Cheshunt Waltham Cross Essex EN8 0EY",
    "addr:housenumber":"23",
    "addr:postcode":"en8 0ey",
    "addr:street":"Albemarle Avenue;Cross",
    "iso:country":"GB",
    "sg:address":"23 Albemarle Avenue, Cheshunt",
    "sg:city":"Waltham Cross",
    "sg:classifiers":[
        {
            "category":"Building & Trades",
            "subcategory":"Construction",
            "type":"Services"
        }
    ],
    "sg:postcode":"EN8 0EY",
    "sg:province":"Essex",
    "sg:tags":[
        "roofing"
    ],
    "wof:name":"Albemarles",
    "wof:placetype":"venue"
},
  "geometry": {"coordinates":[-0.044787,51.71278],"type":"Point"}
}