{
  "type": "Feature",
  "properties": {
    "addr:full":"67 Rock Lane West Birkenhead Merseyside CH42 1RE",
    "addr:housenumber":"67",
    "addr:postcode":"ch42 1re",
    "addr:street":"Rock Lane West",
    "iso:country":"GB",
    "sg:address":"67 Rock Lane West",
    "sg:city":"Birkenhead",
    "sg:classifiers":[
        {
            "category":"Building & Trades",
            "subcategory":"Equipment Rental",
            "type":"Services"
        }
    ],
    "sg:phone":"+44 151 644 8314",
    "sg:postcode":"CH42 1RE",
    "sg:province":"Merseyside",
    "sg:tags":[
        "plant",
        "tool",
        "hire",
        "centre"
    ],
    "wof:name":"Wirral Hire Ltd",
    "wof:placetype":"venue"
},
  "geometry": {"coordinates":[-3.007542,53.367916],"type":"Point"}
}