{
  "type": "Feature",
  "properties": {
    "addr:full":"Hobson Golf Course, Burnopfield Newcastle-upon-tyne Durham NE16 6BZ",
    "addr:postcode":"ne16 6bz",
    "addr:street":"Burnopfield",
    "iso:country":"GB",
    "sg:address":"Hobson Golf Course, Burnopfield",
    "sg:city":"Newcastle-upon-tyne",
    "sg:classifiers":[
        {
            "category":"Bars & Pubs",
            "type":"Food & Drink"
        }
    ],
    "sg:phone":"+44 1207 270941",
    "sg:postcode":"NE16 6BZ",
    "sg:province":"Durham",
    "sg:tags":[
        "pubs",
        "inn"
    ],
    "wof:name":"Fairways",
    "wof:placetype":"venue"
},
  "geometry": {"coordinates":[-1.727454,54.906704],"type":"Point"}
}