{
  "type": "Feature",
  "properties": {
    "addr:full":"Unit 3 Henshaw St Yard Port Talbot Neath Port Talbot SA12 6NH",
    "addr:housenumber":"unit 3",
    "addr:postcode":"sa12 6nh",
    "addr:street":"St Yard",
    "iso:country":"GB",
    "sg:address":"Unit 3 Henshaw St Yard",
    "sg:city":"Port Talbot",
    "sg:classifiers":[
        {
            "category":"Military Area",
            "subcategory":"Air Force Base",
            "type":"Public Place"
        }
    ],
    "sg:phone":"+44 1639 882600",
    "sg:postcode":"SA12 6NH",
    "sg:province":"Neath Port Talbot",
    "sg:tags":[
        "taxi",
        "hire",
        "private"
    ],
    "wof:name":"Eagle Cabs (Port Talbot)",
    "wof:placetype":"venue"
},
  "geometry": {"coordinates":[-3.795964,51.593803],"type":"Point"}
}