{
  "type": "Feature",
  "properties": {
    "iso:country":"GB",
    "sg:address":"486 Warwick Road, Tyseley",
    "sg:city":"Birmingham",
    "sg:classifiers":[
        {
            "category":"Education",
            "subcategory":"Music School",
            "type":"Public Place"
        }
    ],
    "sg:phone":"+44 121 706 0102",
    "sg:postcode":"B11 2HP",
    "sg:province":"West Midlands",
    "sg:tags":[
        "conservatory"
    ],
    "wof:name":"Traditional Conservatories Ltd.",
    "wof:placetype":"venue"
},
  "geometry": {"coordinates":[-1.853095,52.453045],"type":"Point"}
}