{
  "type": "Feature",
  "properties": {
    "addr:full":"66 George St Croydon Surrey CR0 1PD",
    "addr:housenumber":"66",
    "addr:postcode":"cr0 1pd",
    "addr:street":"George St",
    "iso:country":"GB",
    "sg:address":"66 George St",
    "sg:city":"Croydon",
    "sg:classifiers":[
        {
            "category":"Professional",
            "subcategory":"Business Services",
            "type":"Services"
        }
    ],
    "sg:postcode":"CR0 1PD",
    "sg:province":"Surrey",
    "sg:tags":[
        "holding"
    ],
    "wof:name":"Ellwall Holdings Ltd",
    "wof:placetype":"venue"
},
  "geometry": {"coordinates":[-0.0973659977,51.3739624023],"type":"Point"}
}