{
  "type": "Feature",
  "properties": {
    "addr:full":"1 Penfilia Rd Swansea Swansea SA5 9HX",
    "addr:housenumber":"1",
    "addr:postcode":"sa5 9hx",
    "addr:street":"Penfilia Rd",
    "iso:country":"GB",
    "sg:address":"1 Penfilia Rd",
    "sg:city":"Swansea",
    "sg:classifiers":[
        {
            "category":"Bars & Pubs",
            "type":"Food & Drink"
        }
    ],
    "sg:phone":"+44 1792 630901",
    "sg:postcode":"SA5 9HX",
    "sg:province":"Swansea",
    "sg:tags":[
        "pubs",
        "inn"
    ],
    "wof:name":"Manselton Hotel",
    "wof:placetype":"venue"
},
  "geometry": {"coordinates":[-3.9524691105,51.6428604126],"type":"Point"}
}