{
  "type": "Feature",
  "properties": {
    "iso:country":"GB",
    "sg:address":"Brooklyn Kennels, Blackbush Lane, Horndon-on-the-hill",
    "sg:city":"Stanford-le-hope",
    "sg:classifiers":[
        {
            "category":"Recreation",
            "subcategory":"Dog Park",
            "type":"Entertainment"
        },
        {
            "category":"Retail",
            "subcategory":"Pet Boarding",
            "type":"Services"
        }
    ],
    "sg:phone":"+44 1375 891614",
    "sg:postcode":"SS17 8PT",
    "sg:province":"Essex",
    "sg:tags":[
        "kennel"
    ],
    "wof:name":"Brooklyn Kennels Greyhound Racing",
    "wof:placetype":"venue"
},
  "geometry": {"coordinates":[0.4020099938,51.5262794495],"type":"Point"}
}