{
  "type": "Feature",
  "properties": {
    "addr:full":"19 Morgan Arcade Cardiff Cardiff CF10 1AF",
    "addr:housenumber":"19;arcade",
    "addr:postcode":"cf10 1af",
    "addr:street":"Morgan",
    "iso:country":"GB",
    "sg:address":"19 Morgan Arcade",
    "sg:city":"Cardiff",
    "sg:classifiers":[
        {
            "category":"Cafe",
            "type":"Food & Drink"
        }
    ],
    "sg:phone":"+44 29 2038 8391",
    "sg:postcode":"CF10 1AF",
    "sg:province":"Cardiff",
    "sg:tags":[
        "tea",
        "room"
    ],
    "wof:name":"Lonnvist",
    "wof:placetype":"venue"
},
  "geometry": {"coordinates":[-3.177089,51.47879],"type":"Point"}
}