{
  "type": "Feature",
  "properties": {
    "addr:full":"West Midlands Region, 8th Floor Edmond House, Newhall Street Birmingham West Midlands B3 3NL",
    "addr:housenumber":"8th floor",
    "addr:postcode":"b3 3nl",
    "addr:street":"Edmond House Newhall Street",
    "iso:country":"GB",
    "sg:address":"West Midlands Region, 8th Floor Edmond House, Newhall Street",
    "sg:city":"Birmingham",
    "sg:classifiers":[
        {
            "category":"Organizations",
            "subcategory":"Non-profit Organization",
            "type":"Services"
        }
    ],
    "sg:phone":"+44 121 200 3500",
    "sg:postcode":"B3 3NL",
    "sg:province":"West Midlands",
    "sg:tags":[
        "organisation",
        "voluntary",
        "charity"
    ],
    "wof:name":"The Big Lottery Fund",
    "wof:placetype":"venue"
},
  "geometry": {"coordinates":[-1.9020800591,52.4812011719],"type":"Point"}
}