{
  "type": "Feature",
  "properties": {
    "addr:full":"525 Llangyfelach Rd Swansea Swansea SA5 9HE",
    "addr:housenumber":"525",
    "addr:postcode":"sa5 9he",
    "addr:street":"Llangyfelach Rd",
    "iso:country":"GB",
    "sg:address":"525 Llangyfelach Rd",
    "sg:city":"Swansea",
    "sg:classifiers":[
        {
            "category":"Building & Trades",
            "subcategory":"Construction",
            "type":"Services"
        }
    ],
    "sg:phone":"+44 1792 795068",
    "sg:postcode":"SA5 9HE",
    "sg:province":"Swansea",
    "sg:tags":[
        "decorator",
        "painter"
    ],
    "wof:name":"Ron Lawson",
    "wof:placetype":"venue"
},
  "geometry": {"coordinates":[-3.9462270737,51.6461677551],"type":"Point"}
}