{
  "type": "Feature",
  "properties": {
    "iso:country":"GB",
    "sg:address":"120 Hilldene Avenue",
    "sg:city":"Romford",
    "sg:classifiers":[
        {
            "category":"Food & Beverages",
            "subcategory":"Supermarket",
            "type":"Retail Goods"
        }
    ],
    "sg:postcode":"RM3 8DT",
    "sg:province":"Essex",
    "wof:name":"Kingstone Trading Ltd.",
    "wof:placetype":"venue"
},
  "geometry": {"coordinates":[0.2169480026,51.6068572998],"type":"Point"}
}