{
  "type": "Feature",
  "properties": {
    "addr:full":"101 Field Rd Feltham Greater London TW14 0BE",
    "addr:housenumber":"101",
    "addr:postcode":"tw14 0be",
    "addr:street":"Field Rd",
    "iso:country":"GB",
    "sg:address":"101 Field Rd",
    "sg:city":"Feltham",
    "sg:classifiers":[
        {
            "category":"Freight",
            "type":"Transportation"
        }
    ],
    "sg:phone":"+44 20 8890 2882",
    "sg:postcode":"TW14 0BE",
    "sg:province":"Greater London",
    "sg:tags":[
        "haulage",
        "road"
    ],
    "wof:name":"Tommy Owen & Son",
    "wof:placetype":"venue"
},
  "geometry": {"coordinates":[-0.405196,51.455322],"type":"Point"}
}