{
  "type": "Feature",
  "properties": {
    "iso:country":"GB",
    "sg:address":"101 Field Rd",
    "sg:city":"Feltham",
    "sg:classifiers":[
        {
            "category":"Freight",
            "type":"Transportation"
        }
    ],
    "sg:phone":"+44 20 8890 2882",
    "sg:postcode":"TW14 0BE",
    "sg:province":"Greater London",
    "sg:tags":[
        "haulage",
        "road"
    ],
    "wof:name":"Tommy Owen & Son",
    "wof:placetype":"venue"
},
  "geometry": {"coordinates":[-0.405196,51.455322],"type":"Point"}
}