{
  "type": "Feature",
  "properties": {
    "addr:full":"Lower Bushey Dairy, Rempstone Wareham Dorset BH20 4SD",
    "addr:postcode":"bh20 4sd",
    "addr:street":"Lower",
    "iso:country":"GB",
    "sg:address":"Lower Bushey Dairy, Rempstone",
    "sg:city":"Wareham",
    "sg:classifiers":[
        {
            "category":"Farming",
            "subcategory":"Livestock Farm",
            "type":"Manufacturing & Wholesale Goods"
        }
    ],
    "sg:postcode":"BH20 4SD",
    "sg:province":"Dorset",
    "sg:tags":[
        "others"
    ],
    "wof:name":"Rempstone Farms",
    "wof:placetype":"venue"
},
  "geometry": {"coordinates":[-2.112607,50.689888],"type":"Point"}
}