{
  "type": "Feature",
  "properties": {
    "iso:country":"GB",
    "sg:address":"56a High Street",
    "sg:city":"Shaftesbury",
    "sg:classifiers":[
        {
            "category":"Shopping",
            "subcategory":"Gifts & Souvenirs",
            "type":"Retail Goods"
        }
    ],
    "sg:phone":"+44 1747 853341",
    "sg:postcode":"SP7 8AA",
    "sg:province":"Dorset",
    "sg:tags":[
        "shop"
    ],
    "wof:name":"Serendipity",
    "wof:placetype":"venue"
},
  "geometry": {"coordinates":[-2.194323,51.006454],"type":"Point"}
}