{
  "type": "Feature",
  "properties": {
    "addr:full":"146 Hutton Road, Shenfield Brentwood Essex CM15 8NL",
    "addr:housenumber":"146",
    "addr:postcode":"cm15 8nl",
    "addr:street":"Hutton Road",
    "iso:country":"GB",
    "sg:address":"146 Hutton Road, Shenfield",
    "sg:city":"Brentwood",
    "sg:classifiers":[
        {
            "category":"Home & Garden",
            "subcategory":"Home Furnishings",
            "type":"Retail Goods"
        }
    ],
    "sg:phone":"+44 1277 217486",
    "sg:postcode":"CM15 8NL",
    "sg:province":"Essex",
    "sg:tags":[
        "wall",
        "wallpaper",
        "covering"
    ],
    "wof:name":"Peter Martin Interiors Ltd.",
    "wof:placetype":"venue"
},
  "geometry": {"coordinates":[0.327108,51.63023],"type":"Point"}
}