{
  "type": "Feature",
  "properties": {
    "addr:full":"123 High Street, Penge London Greater London SE20 7DS",
    "addr:housenumber":"123",
    "addr:postcode":"se20 7ds",
    "addr:street":"High Street",
    "iso:country":"GB",
    "sg:address":"123 High Street, Penge",
    "sg:city":"London",
    "sg:classifiers":[
        {
            "category":"Food & Beverages",
            "subcategory":"Bakery",
            "type":"Retail Goods"
        }
    ],
    "sg:phone":"+44 20 8776 8518",
    "sg:postcode":"SE20 7DS",
    "sg:province":"Greater London",
    "sg:tags":[
        "baker"
    ],
    "wof:name":"Slatters Bakery Ltd.",
    "wof:placetype":"venue"
},
  "geometry": {"coordinates":[-0.052678,51.415237],"type":"Point"}
}