{
  "type": "Feature",
  "properties": {
    "addr:full":"501 Great Horton Road Bradford West Yorkshire BD7 4EG",
    "addr:housenumber":"501",
    "addr:postcode":"bd7 4eg",
    "addr:street":"Great Horton Road",
    "iso:country":"GB",
    "sg:address":"501 Great Horton Road",
    "sg:city":"Bradford",
    "sg:classifiers":[
        {
            "category":"Real Estate",
            "subcategory":"Real Estate Agent",
            "type":"Services"
        }
    ],
    "sg:postcode":"BD7 4EG",
    "sg:province":"West Yorkshire",
    "wof:name":"Robert Watts Estate Agents",
    "wof:placetype":"venue"
},
  "geometry": {"coordinates":[-1.785447,53.780243],"type":"Point"}
}