{
  "type": "Feature",
  "properties": {
    "addr:full":"49 Church Street Weybridge Surrey KT13 8DG",
    "addr:housenumber":"49",
    "addr:postcode":"kt13 8dg",
    "addr:street":"Church Street",
    "iso:country":"GB",
    "sg:address":"49 Church Street",
    "sg:city":"Weybridge",
    "sg:classifiers":[
        {
            "category":"Retail",
            "subcategory":"Repair Shop",
            "type":"Services"
        }
    ],
    "sg:phone":"+44 1932 846782",
    "sg:postcode":"KT13 8DG",
    "sg:province":"Surrey",
    "sg:tags":[
        "upholsterer"
    ],
    "wof:name":"E Weycroft Interiors",
    "wof:placetype":"venue"
},
  "geometry": {"coordinates":[-0.4617649913,51.3718833923],"type":"Point"}
}