{
  "type": "Feature",
  "properties": {
    "addr:full":"St Johns Parish Hall, 374 North End Rd Fulham Greater London SW6 1LY",
    "addr:housenumber":"374",
    "addr:postcode":"sw6 1ly",
    "addr:street":"North End Rd",
    "iso:country":"GB",
    "sg:address":"St Johns Parish Hall, 374 North End Rd",
    "sg:city":"Fulham",
    "sg:classifiers":[
        {
            "category":"Restaurant",
            "type":"Food & Drink"
        }
    ],
    "sg:phone":"+44 20 7610 3457",
    "sg:postcode":"SW6 1LY",
    "sg:province":"Greater London",
    "wof:name":"M Bar",
    "wof:placetype":"venue"
},
  "geometry": {"coordinates":[-0.199291,51.480839],"type":"Point"}
}