{
  "type": "Feature",
  "properties": {
    "addr:full":"1 The Tussocks, Marchwood Southampton Hampshire SO40 4YE",
    "addr:housenumber":"1",
    "addr:postcode":"so40 4ye",
    "addr:street":"The Tussocks",
    "iso:country":"GB",
    "sg:address":"1 The Tussocks, Marchwood",
    "sg:city":"Southampton",
    "sg:classifiers":[
        {
            "category":"Home & Garden",
            "subcategory":"Home Furnishings",
            "type":"Retail Goods"
        }
    ],
    "sg:postcode":"SO40 4YE",
    "sg:province":"Hampshire",
    "sg:tags":[
        "furnishers",
        "planner",
        "kitchen"
    ],
    "wof:name":"Premier Designs",
    "wof:placetype":"venue"
},
  "geometry": {"coordinates":[-1.4542989731,50.8926506042],"type":"Point"}
}