{
  "type": "Feature",
  "properties": {
    "addr:full":"Lower Hurdley Farm Montgomery Shropshire SY15 6DY",
    "addr:postcode":"sy15 6dy",
    "addr:street":"Montgomery",
    "iso:country":"GB",
    "sg:address":"Lower Hurdley Farm",
    "sg:city":"Montgomery",
    "sg:classifiers":[
        {
            "category":"Professional",
            "subcategory":"Engineering",
            "type":"Services"
        }
    ],
    "sg:phone":"+44 1588 620266",
    "sg:postcode":"SY15 6DY",
    "sg:province":"Shropshire",
    "wof:name":"Trevor Hamer",
    "wof:placetype":"venue"
},
  "geometry": {"coordinates":[-3.146479,52.563564],"type":"Point"}
}