{
  "type": "Feature",
  "properties": {
    "iso:country":"GB",
    "sg:address":"Sandylands Caravan Park",
    "sg:city":"Saltcoats",
    "sg:classifiers":[
        {
            "category":"Recreation",
            "subcategory":"Campground",
            "type":"Entertainment"
        }
    ],
    "sg:phone":"+44 1294 469411",
    "sg:postcode":"KA21 5JN",
    "sg:province":"North Ayrshire",
    "sg:tags":[
        "site",
        "camping"
    ],
    "wof:name":"P J Shops",
    "wof:placetype":"venue"
},
  "geometry": {"coordinates":[-4.787579,55.64344],"type":"Point"}
}