{
  "type": "Feature",
  "properties": {
    "addr:full":"Stall 40 Eagle Centre Market Derby Derbyshire DE1 2AZ",
    "addr:housenumber":"40",
    "addr:postcode":"de1 2az",
    "addr:street":"Stall;Eagle Centre Market",
    "iso:country":"GB",
    "sg:address":"Stall 40 Eagle Centre Market",
    "sg:city":"Derby",
    "sg:classifiers":[
        {
            "category":"Food & Beverages",
            "subcategory":"Fruits & Vegetables",
            "type":"Retail Goods"
        }
    ],
    "sg:phone":"+44 1332 205180",
    "sg:postcode":"DE1 2AZ",
    "sg:province":"Derbyshire",
    "sg:tags":[
        "greengrocer"
    ],
    "wof:name":"Martins Fruit & Veg",
    "wof:placetype":"venue"
},
  "geometry": {"coordinates":[-1.483684,52.925171],"type":"Point"}
}