{
  "type": "Feature",
  "properties": {
    "iso:country":"GB",
    "sg:address":"Unit 3, Drury Way Industrial Estate, Laxcon Close",
    "sg:city":"London",
    "sg:classifiers":[
        {
            "category":"Shopping",
            "subcategory":"Stationery & Office Supplies",
            "type":"Retail Goods"
        }
    ],
    "sg:postcode":"NW10 0TG",
    "sg:province":"Greater London",
    "sg:tags":[
        "item",
        "promotional"
    ],
    "wof:name":"Chartdesign Ltd.",
    "wof:placetype":"venue"
},
  "geometry": {"coordinates":[-0.261624,51.554436],"type":"Point"}
}