{
  "type": "Feature",
  "properties": {
    "addr:full":"129 London Road Knebworth Hertfordshire SG3 6EX",
    "addr:housenumber":"129",
    "addr:postcode":"sg3 6ex",
    "addr:street":"London Road",
    "iso:country":"GB",
    "sg:address":"129 London Road",
    "sg:city":"Knebworth",
    "sg:classifiers":[
        {
            "category":"Restaurant",
            "type":"Food & Drink"
        }
    ],
    "sg:phone":"+44 1438 813321",
    "sg:postcode":"SG3 6EX",
    "sg:province":"Hertfordshire",
    "sg:tags":[
        "indian"
    ],
    "wof:name":"Raja Tandoori Cuisine",
    "wof:placetype":"venue"
},
  "geometry": {"coordinates":[-0.183338,51.866165],"type":"Point"}
}