{
  "type": "Feature",
  "properties": {
    "iso:country":"GB",
    "sg:address":"96 Collingwood Street, Coundon",
    "sg:city":"Bishop Auckland",
    "sg:classifiers":[
        {
            "category":"Retail",
            "subcategory":"Driving School",
            "type":"Services"
        }
    ],
    "sg:phone":"+44 1388 601082",
    "sg:postcode":"DL14 8LH",
    "sg:province":"Durham",
    "wof:name":"Georgies School of Motoring",
    "wof:placetype":"venue"
},
  "geometry": {"coordinates":[-1.628698,54.660637],"type":"Point"}
}