{
  "type": "Feature",
  "properties": {
    "iso:country":"GB",
    "sg:address":"13 Bradenham Place",
    "sg:city":"Penarth",
    "sg:classifiers":[
        {
            "category":"Health Services",
            "subcategory":"Health Practitioner",
            "type":"Services"
        }
    ],
    "sg:phone":"+44 29 2070 8350",
    "sg:postcode":"CF64 2AG",
    "sg:province":"The Vale of Glamorgan",
    "sg:tags":[
        "osteopath"
    ],
    "wof:name":"C B HANCOCK",
    "wof:placetype":"venue"
},
  "geometry": {"coordinates":[-3.1739490032,51.4386100769],"type":"Point"}
}