{
  "type": "Feature",
  "properties": {
    "iso:country":"GB",
    "sg:address":"Beneknowle Farm, Diptford",
    "sg:city":"Totnes",
    "sg:classifiers":[
        {
            "category":"Farming",
            "subcategory":"Livestock Farm",
            "type":"Manufacturing & Wholesale Goods"
        }
    ],
    "sg:phone":"+44 1364 73153",
    "sg:postcode":"TQ9 7LU",
    "sg:province":"Devon",
    "sg:tags":[
        "others"
    ],
    "wof:name":"L J H & J Barons",
    "wof:placetype":"venue"
},
  "geometry": {"coordinates":[-3.7892839909,50.3975448608],"type":"Point"}
}