{
  "type": "Feature",
  "properties": {
    "addr:full":"Unit 1/2 Skein Enterprise Park, Hodsoll Street Sevenoaks Kent TN15 7LB",
    "addr:housenumber":"unit 1 / 2 skein",
    "addr:postcode":"tn15 7lb",
    "addr:street":"Enterprise Park Hodsoll Street",
    "iso:country":"GB",
    "sg:address":"Unit 1/2 Skein Enterprise Park, Hodsoll Street",
    "sg:city":"Sevenoaks",
    "sg:classifiers":[
        {
            "category":"Autos & Motor Vehicles",
            "subcategory":"Auto Supplies",
            "type":"Retail Goods"
        }
    ],
    "sg:phone":"+44 1732 824618",
    "sg:postcode":"TN15 7LB",
    "sg:province":"Kent",
    "sg:tags":[
        "gearbox"
    ],
    "wof:name":"Kent Transmissions Centre",
    "wof:placetype":"venue"
},
  "geometry": {"coordinates":[0.3370200098,51.3385696411],"type":"Point"}
}