{
  "type": "Feature",
  "properties": {
    "iso:country":"GB",
    "sg:address":"15 Dalhousie Road, Eskbank",
    "sg:city":"Dalkeith",
    "sg:classifiers":[
        {
            "category":"Autos & Motor Vehicles",
            "subcategory":"Automobile Sales",
            "type":"Retail Goods"
        }
    ],
    "sg:phone":"+44 131 654 0055",
    "sg:postcode":"EH22 3AT",
    "sg:province":"City of Edinburgh",
    "sg:tags":[
        "car"
    ],
    "wof:name":"Cutprice Cars",
    "wof:placetype":"venue"
},
  "geometry": {"coordinates":[-3.080291,55.888081],"type":"Point"}
}