{
  "type": "Feature",
  "properties": {
    "iso:country":"GB",
    "sg:address":"746 Ecclesall Rd",
    "sg:city":"Sheffield",
    "sg:classifiers":[
        {
            "category":"Shopping",
            "subcategory":"Clothing, Apparel, & Fashions",
            "type":"Retail Goods"
        }
    ],
    "sg:phone":"+44 114 266 2179",
    "sg:postcode":"S11 8TB",
    "sg:province":"Derbyshire",
    "sg:tags":[
        "shop"
    ],
    "wof:name":"Francesca",
    "wof:placetype":"venue"
},
  "geometry": {"coordinates":[-1.5071690083,53.3662490845],"type":"Point"}
}