{
  "type": "Feature",
  "properties": {
    "iso:country":"GB",
    "sg:address":"Linstene, Little Broughton",
    "sg:city":"Cockermouth",
    "sg:classifiers":[
        {
            "category":"Building & Trades",
            "subcategory":"Plumbing",
            "type":"Services"
        }
    ],
    "sg:phone":"+44 1900 824446",
    "sg:postcode":"CA13 0YG",
    "sg:province":"Cumbria",
    "sg:tags":[
        "plumber",
        "heating"
    ],
    "wof:name":"A VARTY",
    "wof:placetype":"venue"
},
  "geometry": {"coordinates":[-3.432495,54.673355],"type":"Point"}
}