{
  "type": "Feature",
  "properties": {
    "addr:full":"Prospect House, Aykley Heads Durham Durham DH1 5TS",
    "addr:postcode":"dh1 5ts",
    "addr:street":"Aykley",
    "iso:country":"GB",
    "sg:address":"Prospect House, Aykley Heads",
    "sg:city":"Durham",
    "sg:classifiers":[
        {
            "category":"Utilities",
            "subcategory":"Refuse",
            "type":"Services"
        }
    ],
    "sg:phone":"+44 191 384 4000",
    "sg:postcode":"DH1 5TS",
    "sg:province":"Durham",
    "sg:tags":[
        "disposal",
        "waste"
    ],
    "wof:name":"Premier Waste Management Ltd.",
    "wof:placetype":"venue"
},
  "geometry": {"coordinates":[-1.588687,54.790085],"type":"Point"}
}