{
  "type": "Feature",
  "properties": {
    "iso:country":"GB",
    "sg:address":"Unit 2, Little Lane",
    "sg:city":"Willenhall",
    "sg:classifiers":[
        {
            "category":"Retail",
            "subcategory":"Auto Repair",
            "type":"Services"
        }
    ],
    "sg:postcode":"WV12 5PU",
    "sg:province":"West Midlands",
    "sg:tags":[
        "modification",
        "garage"
    ],
    "wof:name":"Anthony Lloyd",
    "wof:placetype":"venue"
},
  "geometry": {"coordinates":[-2.033294,52.606815],"type":"Point"}
}