{
  "type": "Feature",
  "properties": {
    "addr:full":"Unit 303, Hartlebury Trading Estate, Hartlebury Kidderminster Staffordshire DY10 4JB",
    "addr:housenumber":"303",
    "addr:postcode":"dy10 4jb",
    "addr:street":"Hartlebury Trading Estate",
    "iso:country":"GB",
    "sg:address":"Unit 303, Hartlebury Trading Estate, Hartlebury",
    "sg:city":"Kidderminster",
    "sg:classifiers":[
        {
            "category":"Professional",
            "subcategory":"Business Services",
            "type":"Services"
        }
    ],
    "sg:phone":"+44 1299 251033",
    "sg:postcode":"DY10 4JB",
    "sg:province":"Staffordshire",
    "sg:tags":[
        "distribution"
    ],
    "wof:name":"Earlybird Furniture Ltd.",
    "wof:placetype":"venue"
},
  "geometry": {"coordinates":[-2.211575985,52.3237495422],"type":"Point"}
}