{
  "type": "Feature",
  "properties": {
    "addr:full":"64 Croydon Rd Caterham Surrey CR3 6QB",
    "addr:housenumber":"64",
    "addr:postcode":"cr3 6qb",
    "addr:street":"Croydon Rd",
    "iso:country":"GB",
    "sg:address":"64 Croydon Rd",
    "sg:city":"Caterham",
    "sg:classifiers":[
        {
            "category":"Shopping",
            "subcategory":"Musical Instruments",
            "type":"Retail Goods"
        }
    ],
    "sg:postcode":"CR3 6QB",
    "sg:province":"Surrey",
    "wof:name":"Nova Guitar Centre",
    "wof:placetype":"venue"
},
  "geometry": {"coordinates":[-0.078753,51.284176],"type":"Point"}
}