{
  "type": "Feature",
  "properties": {
    "addr:full":"Tyrrells Ct Leominster Herefordshire HR6 9DQ",
    "addr:postcode":"hr6 9dq",
    "addr:street":"Tyrrells Ct",
    "iso:country":"GB",
    "sg:address":"Tyrrells Ct",
    "sg:city":"Leominster",
    "sg:classifiers":[
        {
            "category":"Food & Beverages",
            "subcategory":"Groceries & Convenience Stores",
            "type":"Retail Goods"
        }
    ],
    "sg:phone":"+44 1568 720244",
    "sg:postcode":"HR6 9DQ",
    "sg:province":"Herefordshire",
    "sg:tags":[
        "merchant",
        "potato"
    ],
    "wof:name":"Tyrrell's Court Potato Co",
    "wof:placetype":"venue"
},
  "geometry": {"coordinates":[-2.743553,52.227077],"type":"Point"}
}