{
  "type": "Feature",
  "properties": {
    "addr:full":"Hill Cot Road, Sharples Bolton Lancashire BL1 8RN",
    "addr:postcode":"bl1 8rn",
    "addr:street":"Cot Road",
    "iso:country":"GB",
    "sg:address":"Hill Cot Road, Sharples",
    "sg:city":"Bolton",
    "sg:classifiers":[
        {
            "category":"Government",
            "subcategory":"Office",
            "type":"Public Place"
        },
        {
            "category":"Sports & Exercise",
            "subcategory":"Swimming Pool",
            "type":"Entertainment"
        }
    ],
    "sg:phone":"+44 1204 301444",
    "sg:postcode":"BL1 8RN",
    "sg:province":"Lancashire",
    "sg:tags":[
        "local"
    ],
    "wof:name":"Sharples Swimming Pool",
    "wof:placetype":"venue"
},
  "geometry": {"coordinates":[-2.4263489246,53.606010437],"type":"Point"}
}