{
  "type": "Feature",
  "properties": {
    "addr:full":"Cheque Station Unit 7, Romford Railway Station, South Romford Essex RM1 1SX",
    "addr:housenumber":"unit 7",
    "addr:postcode":"rm1 1sx",
    "addr:street":"Railway;South",
    "iso:country":"GB",
    "sg:address":"Cheque Station Unit 7, Romford Railway Station, South",
    "sg:city":"Romford",
    "sg:classifiers":[
        {
            "category":"Banks & Credit Unions",
            "subcategory":"Financial Services",
            "type":"Services"
        }
    ],
    "sg:postcode":"RM1 1SX",
    "sg:province":"Essex",
    "sg:tags":[
        "cashing",
        "cheque"
    ],
    "wof:name":"Cheque Station Ltd",
    "wof:placetype":"venue"
},
  "geometry": {"coordinates":[0.1863150001,51.5813903809],"type":"Point"}
}