{
  "type": "Feature",
  "properties": {
    "iso:country":"GB",
    "sg:address":"14 Langdale Drive",
    "sg:city":"Cannock",
    "sg:classifiers":[
        {
            "category":"Home & Garden",
            "subcategory":"Household Appliances",
            "type":"Retail Goods"
        }
    ],
    "sg:phone":"+44 1543 579180",
    "sg:postcode":"WS11 1QW",
    "sg:province":"Staffordshire",
    "sg:tags":[
        "electrical",
        "domestic"
    ],
    "wof:name":"H.A Birch & Co",
    "wof:placetype":"venue"
},
  "geometry": {"coordinates":[-2.041099,52.683613],"type":"Point"}
}