{
  "type": "Feature",
  "properties": {
    "addr:full":"69 Whurley Way Maidenhead Berkshire SL6 7SY",
    "addr:housenumber":"69",
    "addr:postcode":"sl6 7sy",
    "addr:street":"Whurley Way",
    "iso:country":"GB",
    "sg:address":"69 Whurley Way",
    "sg:city":"Maidenhead",
    "sg:classifiers":[
        {
            "category":"Taxi",
            "type":"Transportation"
        }
    ],
    "sg:phone":"+44 1628 411422",
    "sg:postcode":"SL6 7SY",
    "sg:province":"Berkshire",
    "sg:tags":[
        "mini",
        "cab"
    ],
    "wof:name":"A Hussain",
    "wof:placetype":"venue"
},
  "geometry": {"coordinates":[-0.731274,51.536655],"type":"Point"}
}