{
  "type": "Feature",
  "properties": {
    "addr:full":"Glan-yr-afon Industrial Estate, Llanbadarn Fawr Aberystwyth Ceredigion SY23 3JQ",
    "addr:postcode":"sy23 3jq",
    "addr:street":"Estate",
    "iso:country":"GB",
    "sg:address":"Glan-yr-afon Industrial Estate, Llanbadarn Fawr",
    "sg:city":"Aberystwyth",
    "sg:classifiers":[
        {
            "category":"Autos & Motor Vehicles",
            "subcategory":"Auto Supplies",
            "type":"Retail Goods"
        }
    ],
    "sg:phone":"+44 1970 611166",
    "sg:postcode":"SY23 3JQ",
    "sg:province":"Ceredigion",
    "sg:tags":[
        "tyre"
    ],
    "wof:name":"A T S",
    "wof:placetype":"venue"
},
  "geometry": {"coordinates":[-4.077869,52.41605],"type":"Point"}
}