{
  "type": "Feature",
  "properties": {
    "iso:country":"GB",
    "sg:address":"The Old Mint, Lawford Close, Nechells",
    "sg:city":"Birmingham",
    "sg:classifiers":[
        {
            "category":"Manufacturing",
            "subcategory":"Rubber & Plastics",
            "type":"Manufacturing & Wholesale Goods"
        }
    ],
    "sg:phone":"+44 121 359 4500",
    "sg:postcode":"B7 4HJ",
    "sg:province":"West Midlands",
    "sg:tags":[
        "product",
        "foam"
    ],
    "wof:name":"Protofoam Packaging Ltd.",
    "wof:placetype":"venue"
},
  "geometry": {"coordinates":[-1.87848,52.48315],"type":"Point"}
}