{
  "type": "Feature",
  "properties": {
    "iso:country":"GB",
    "sg:address":"568 Commercial Rd",
    "sg:city":"Poplar",
    "sg:classifiers":[
        {
            "category":"Shopping",
            "subcategory":"News",
            "type":"Retail Goods"
        }
    ],
    "sg:phone":"+44 20 7791 1958",
    "sg:postcode":"E14 7JD",
    "sg:province":"Greater London",
    "sg:tags":[
        "newsagent"
    ],
    "wof:name":"Days Newsagents",
    "wof:placetype":"venue"
},
  "geometry": {"coordinates":[-0.040469,51.512676],"type":"Point"}
}