{
  "type": "Feature",
  "properties": {
    "iso:country":"GB",
    "sg:address":"Southwood House, Regent Rd",
    "sg:city":"Salford",
    "sg:classifiers":[
        {
            "category":"Professional",
            "type":"Services"
        }
    ],
    "sg:phone":"+44 161 872 4394",
    "sg:postcode":"M5 4QH",
    "sg:province":"Greater Manchester",
    "sg:tags":[
        "repair",
        "tech",
        "maintenance"
    ],
    "wof:name":"Systemhouse plc",
    "wof:placetype":"venue"
},
  "geometry": {"coordinates":[-2.2670650482,53.4763374329],"type":"Point"}
}