{
  "type": "Feature",
  "properties": {
    "iso:country":"GB",
    "sg:address":"21 New Rd",
    "sg:city":"Ilford",
    "sg:classifiers":[
        {
            "category":"Building & Trades",
            "subcategory":"Plumbing",
            "type":"Services"
        }
    ],
    "sg:postcode":"IG3 8AU",
    "sg:province":"Essex",
    "sg:tags":[
        "heating"
    ],
    "wof:name":"Allingham,Steven G,",
    "wof:placetype":"venue"
},
  "geometry": {"coordinates":[0.0959250033,51.561164856],"type":"Point"}
}