{
  "type": "Feature",
  "properties": {
    "addr:full":"12 Wordsworth Street, Cwmaman Aberdare Neath Port Talbot CF44 6HL",
    "addr:housenumber":"12",
    "addr:postcode":"cf44 6hl",
    "addr:street":"Wordsworth Street",
    "iso:country":"GB",
    "sg:address":"12 Wordsworth Street, Cwmaman",
    "sg:city":"Aberdare",
    "sg:classifiers":[
        {
            "category":"Military Area",
            "subcategory":"Air Force Base",
            "type":"Public Place"
        }
    ],
    "sg:postcode":"CF44 6HL",
    "sg:province":"Neath Port Talbot",
    "sg:tags":[
        "taxi",
        "hire",
        "private"
    ],
    "wof:name":"Cwm Cabs",
    "wof:placetype":"venue"
},
  "geometry": {"coordinates":[-3.4428040981,51.687664032],"type":"Point"}
}