{
  "type": "Feature",
  "properties": {
    "iso:country":"GB",
    "sg:address":"236 Chester Road",
    "sg:city":"Flint",
    "sg:classifiers":[
        {
            "category":"Professional",
            "type":"Services"
        }
    ],
    "sg:phone":"+44 1352 733193",
    "sg:postcode":"CH6 5SD",
    "sg:province":"Flintshire",
    "sg:tags":[
        "exhibition"
    ],
    "wof:name":"Clwyd Shop Fitters & Exhibition Services",
    "wof:placetype":"venue"
},
  "geometry": {"coordinates":[-3.116571,53.240524],"type":"Point"}
}