{
  "type": "Feature",
  "properties": {
    "addr:full":"82 High Street Annan Dumfries and Galloway DG12 6DW",
    "addr:housenumber":"82",
    "addr:postcode":"dg12 6dw",
    "addr:street":"High Street",
    "iso:country":"GB",
    "sg:address":"82 High Street",
    "sg:city":"Annan",
    "sg:classifiers":[
        {
            "category":"Cafe",
            "type":"Food & Drink"
        }
    ],
    "sg:postcode":"DG12 6DW",
    "sg:province":"Dumfries and Galloway",
    "sg:tags":[
        "tea",
        "room"
    ],
    "wof:name":"Lairds Kitchen",
    "wof:placetype":"venue"
},
  "geometry": {"coordinates":[-3.2615311146,54.9874420166],"type":"Point"}
}