{
  "type": "Feature",
  "properties": {
    "addr:full":"St Johns House, 30 East Street Leicester Leicestershire LE1 6NN",
    "addr:housenumber":"30",
    "addr:postcode":"le1 6nn",
    "addr:street":"East Street",
    "iso:country":"GB",
    "sg:address":"St Johns House, 30 East Street",
    "sg:city":"Leicester",
    "sg:classifiers":[
        {
            "category":"Insurance",
            "subcategory":"Insurance Agent",
            "type":"Services"
        }
    ],
    "sg:phone":"+44 116 254 2321",
    "sg:postcode":"LE1 6NN",
    "sg:province":"Leicestershire",
    "sg:tags":[
        "broker"
    ],
    "wof:name":"Sedgwick (Uk) Risk Services",
    "wof:placetype":"venue"
},
  "geometry": {"coordinates":[-1.126921,52.63131],"type":"Point"}
}