{
  "type": "Feature",
  "properties": {
    "addr:full":"59 Church Street Kingsbridge Devon TQ7 1BY",
    "addr:housenumber":"59",
    "addr:postcode":"tq7 1by",
    "addr:street":"Church Street",
    "iso:country":"GB",
    "sg:address":"59 Church Street",
    "sg:city":"Kingsbridge",
    "sg:classifiers":[
        {
            "category":"Health Services",
            "subcategory":"Dentist",
            "type":"Services"
        }
    ],
    "sg:phone":"+44 1548 854330",
    "sg:postcode":"TQ7 1BY",
    "sg:province":"Devon",
    "sg:tags":[
        "technician",
        "dental"
    ],
    "wof:name":"Ceramet Ltd.",
    "wof:placetype":"venue"
},
  "geometry": {"coordinates":[-3.7745840549,50.2864532471],"type":"Point"}
}