{
  "type": "Feature",
  "properties": {
    "iso:country":"GB",
    "sg:address":"Unit4, Fountain Court, Gordon Road, West Bridgford",
    "sg:city":"Nottingham",
    "sg:classifiers":[
        {
            "category":"Sports & Exercise",
            "subcategory":"Gym",
            "type":"Entertainment"
        }
    ],
    "sg:phone":"+44 115 914 4130",
    "sg:postcode":"NG2 5LN",
    "sg:province":"Nottinghamshire",
    "sg:tags":[
        "club",
        "fitness",
        "health",
        "centre"
    ],
    "wof:name":"The Fountain Ladies Health Studio",
    "wof:placetype":"venue"
},
  "geometry": {"coordinates":[-1.125374,52.930611],"type":"Point"}
}