{
  "type": "Feature",
  "properties": {
    "addr:full":"29 Lane Green Avenue, Codsall Wolverhampton Shropshire WV8 2JT",
    "addr:housenumber":"29",
    "addr:postcode":"wv8 2jt",
    "addr:street":"Lane Green Avenue",
    "iso:country":"GB",
    "sg:address":"29 Lane Green Avenue, Codsall",
    "sg:city":"Wolverhampton",
    "sg:classifiers":[
        {
            "category":"Transit Center",
            "subcategory":"Passenger",
            "type":"Transportation"
        }
    ],
    "sg:phone":"+44 1902 847373",
    "sg:postcode":"WV8 2JT",
    "sg:province":"Shropshire",
    "sg:tags":[
        "boarding",
        "kennel",
        "catteries"
    ],
    "wof:name":"Lane Green Cattery",
    "wof:placetype":"venue"
},
  "geometry": {"coordinates":[-2.173677,52.618652],"type":"Point"}
}