{
  "type": "Feature",
  "properties": {
    "addr:full":"George Row Northampton Northamptonshire NN1 1DF",
    "addr:postcode":"nn1 1df",
    "addr:street":"George Row",
    "iso:country":"GB",
    "sg:address":"George Row",
    "sg:city":"Northampton",
    "sg:classifiers":[
        {
            "category":"Organizations",
            "subcategory":"Membership Organization",
            "type":"Services"
        }
    ],
    "sg:phone":"+44 1604 632962",
    "sg:postcode":"NN1 1DF",
    "sg:province":"Northamptonshire",
    "sg:tags":[
        "club"
    ],
    "wof:name":"Northampton & County Club",
    "wof:placetype":"venue"
},
  "geometry": {"coordinates":[-0.896182,52.236923],"type":"Point"}
}