{
  "type": "Feature",
  "properties": {
    "iso:country":"GB",
    "sg:address":"3 St Georges Pla",
    "sg:city":"Twickenham",
    "sg:classifiers":[
        {
            "category":"Professional",
            "subcategory":"Advertising",
            "type":"Services"
        }
    ],
    "sg:phone":"+44 20 8744 2630",
    "sg:postcode":"TW1 3NE",
    "sg:province":"Greater London",
    "sg:tags":[
        "agency"
    ],
    "wof:name":"Golley Slater & Partners Ltd.",
    "wof:placetype":"venue"
},
  "geometry": {"coordinates":[-0.328229,51.446636],"type":"Point"}
}