{
  "type": "Feature",
  "properties": {
    "addr:full":"Unit 16 Cardigan Ceredigion SA43 3AG",
    "addr:housenumber":"unit 16",
    "addr:postcode":"sa43 3ag",
    "iso:country":"GB",
    "sg:address":"Unit 16",
    "sg:city":"Cardigan",
    "sg:classifiers":[
        {
            "category":"Professional",
            "subcategory":"Printing & Photocopies",
            "type":"Services"
        }
    ],
    "sg:phone":"+44 1239 614548",
    "sg:postcode":"SA43 3AG",
    "sg:province":"Ceredigion",
    "sg:tags":[
        "trophy"
    ],
    "wof:name":"Trebela Products Ltd.",
    "wof:placetype":"venue"
},
  "geometry": {"coordinates":[-4.684379,52.080261],"type":"Point"}
}