{
  "type": "Feature",
  "properties": {
    "iso:country":"GB",
    "sg:address":"Suite 3 Lewes Business Centre, North Street",
    "sg:city":"Lewes",
    "sg:classifiers":[
        {
            "category":"Health Services",
            "subcategory":"Dentist",
            "type":"Services"
        }
    ],
    "sg:phone":"+44 1273 487573",
    "sg:postcode":"BN7 2PE",
    "sg:province":"East Sussex",
    "sg:tags":[
        "technician",
        "dental"
    ],
    "wof:name":"S & K Dental Ceramics",
    "wof:placetype":"venue"
},
  "geometry": {"coordinates":[0.01062,50.873203],"type":"Point"}
}