{
  "type": "Feature",
  "properties": {
    "addr:full":"Unit 14, Palmeston Business Park, Newgate Lane Fareham Hampshire PO14 1DJ",
    "addr:housenumber":"unit 14",
    "addr:postcode":"po14 1dj",
    "addr:street":"Palmeston Business Park Newgate Lane",
    "iso:country":"GB",
    "sg:address":"Unit 14, Palmeston Business Park, Newgate Lane",
    "sg:city":"Fareham",
    "sg:classifiers":[
        {
            "category":"Shopping",
            "subcategory":"Computers & Home Electronics",
            "type":"Retail Goods"
        }
    ],
    "sg:postcode":"PO14 1DJ",
    "sg:province":"Hampshire",
    "sg:tags":[
        "household",
        "canvas"
    ],
    "wof:name":"Covercare",
    "wof:placetype":"venue"
},
  "geometry": {"coordinates":[-1.18582,50.842461],"type":"Point"}
}