{
  "type": "Feature",
  "properties": {
    "addr:full":"44 Raleigh Crescent, Goring By Sea Worthing West Sussex BN12 6EE",
    "addr:housenumber":"44",
    "addr:postcode":"bn12 6ee",
    "addr:street":"Raleigh Crescent",
    "iso:country":"GB",
    "sg:address":"44 Raleigh Crescent, Goring By Sea",
    "sg:city":"Worthing",
    "sg:classifiers":[
        {
            "category":"Health Services",
            "subcategory":"Health Practitioner",
            "type":"Services"
        }
    ],
    "sg:phone":"+44 1903 240743",
    "sg:postcode":"BN12 6EE",
    "sg:province":"West Sussex",
    "sg:tags":[
        "osteopath"
    ],
    "wof:name":"J.R Thompson",
    "wof:placetype":"venue"
},
  "geometry": {"coordinates":[-0.4160070121,50.8201828003],"type":"Point"}
}