{
  "type": "Feature",
  "properties": {
    "iso:country":"GB",
    "sg:address":"29 Horsemarket St",
    "sg:city":"Warrington",
    "sg:classifiers":[
        {
            "category":"Shopping",
            "subcategory":"Clothing, Apparel, & Fashions",
            "type":"Retail Goods"
        }
    ],
    "sg:postcode":"WA1 1TS",
    "sg:province":"Cheshire",
    "sg:tags":[
        "ladieswear"
    ],
    "wof:name":"Niche",
    "wof:placetype":"venue"
},
  "geometry": {"coordinates":[-2.593545,53.390106],"type":"Point"}
}