{
  "type": "Feature",
  "properties": {
    "addr:full":"29 High Street Marlow Berkshire SL7 1AU",
    "addr:housenumber":"29",
    "addr:postcode":"sl7 1au",
    "addr:street":"High Street",
    "iso:country":"GB",
    "sg:address":"29 High Street",
    "sg:city":"Marlow",
    "sg:classifiers":[
        {
            "category":"Organizations",
            "subcategory":"Community Association",
            "type":"Services"
        }
    ],
    "sg:phone":"+44 1628 890505",
    "sg:postcode":"SL7 1AU",
    "sg:province":"Berkshire",
    "sg:tags":[
        "relation",
        "public"
    ],
    "wof:name":"Gordon Bruce Associates",
    "wof:placetype":"venue"
},
  "geometry": {"coordinates":[-0.7760459781,51.5712928772],"type":"Point"}
}