{
  "type": "Feature",
  "properties": {
    "addr:full":"St James Road Kingston-upon-thames Greater London KT1 2AD",
    "addr:postcode":"kt1 2ad",
    "addr:street":"St James Road",
    "iso:country":"GB",
    "sg:address":"St James Road",
    "sg:city":"Kingston-upon-thames",
    "sg:classifiers":[
        {
            "category":"Government",
            "subcategory":"Court House",
            "type":"Public Place"
        }
    ],
    "sg:phone":"+44 20 8972 8700",
    "sg:postcode":"KT1 2AD",
    "sg:province":"Greater London",
    "wof:name":"Kingston Upon Thames County Court",
    "wof:placetype":"venue"
},
  "geometry": {"coordinates":[-0.3048090041,51.4080238342],"type":"Point"}
}