{
  "type": "Feature",
  "properties": {
    "addr:full":"18 Richmond Terrace Blackburn Lancashire BB1 7BL",
    "addr:housenumber":"18",
    "addr:postcode":"bb1 7bl",
    "addr:street":"Richmond Terrace",
    "iso:country":"GB",
    "sg:address":"18 Richmond Terrace",
    "sg:city":"Blackburn",
    "sg:classifiers":[
        {
            "category":"Real Estate",
            "subcategory":"Surveying",
            "type":"Services"
        }
    ],
    "sg:phone":"+44 1254 681133",
    "sg:postcode":"BB1 7BL",
    "sg:province":"Lancashire",
    "sg:tags":[
        "surveyor",
        "valuer"
    ],
    "wof:name":"Trevor Dawson & Co.",
    "wof:placetype":"venue"
},
  "geometry": {"coordinates":[-2.4842290878,53.7507324219],"type":"Point"}
}