{
  "type": "Feature",
  "properties": {
    "iso:country":"GB",
    "sg:address":"Willowbank",
    "sg:city":"Dunoon",
    "sg:classifiers":[
        {
            "category":"Building & Trades",
            "subcategory":"Construction",
            "type":"Services"
        }
    ],
    "sg:phone":"+44 1369 703335",
    "sg:postcode":"PA23 8LL",
    "sg:province":"Argyll and Bute",
    "sg:tags":[
        "joiner",
        "carpenter"
    ],
    "wof:name":"McLeod & Laver",
    "wof:placetype":"venue"
},
  "geometry": {"coordinates":[-4.921698,55.952366],"type":"Point"}
}