{
  "type": "Feature",
  "properties": {
    "addr:full":"5 Church Place Swindon Wiltshire SN1 5EH",
    "addr:housenumber":"5",
    "addr:postcode":"sn1 5eh",
    "addr:street":"Church Place",
    "iso:country":"GB",
    "sg:address":"5 Church Place",
    "sg:city":"Swindon",
    "sg:classifiers":[
        {
            "category":"Shopping",
            "subcategory":"Thrift Store",
            "type":"Retail Goods"
        }
    ],
    "sg:phone":"+44 1793 420385",
    "sg:postcode":"SN1 5EH",
    "sg:province":"Wiltshire",
    "sg:tags":[
        "shop",
        "charity"
    ],
    "wof:name":"Prospect Foundation Ltd.",
    "wof:placetype":"venue"
},
  "geometry": {"coordinates":[-1.793501,51.560982],"type":"Point"}
}