{
  "type": "Feature",
  "properties": {
    "addr:full":"211a Radstock Way, Merstham Redhill Surrey RH1 3NT",
    "addr:housenumber":"211a",
    "addr:postcode":"rh1 3nt",
    "addr:street":"Radstock Way;Redhill",
    "iso:country":"GB",
    "sg:address":"211a Radstock Way, Merstham",
    "sg:city":"Redhill",
    "sg:classifiers":[
        {
            "category":"Community Center",
            "subcategory":"Youth",
            "type":"Public Place"
        },
        {
            "category":"Government",
            "subcategory":"Office",
            "type":"Public Place"
        }
    ],
    "sg:phone":"+44 1737 642019",
    "sg:postcode":"RH1 3NT",
    "sg:province":"Surrey",
    "sg:tags":[
        "organisation",
        "local",
        "centre"
    ],
    "wof:name":"Merstham Youth & Community Centre",
    "wof:placetype":"venue"
},
  "geometry": {"coordinates":[-0.144049,51.263699],"type":"Point"}
}