{
  "type": "Feature",
  "properties": {
    "addr:full":"Browns Drove, Swineshead Boston Lincolnshire PE20 3PX",
    "addr:postcode":"pe20 3px",
    "addr:street":"Browns Drove",
    "iso:country":"GB",
    "sg:address":"Browns Drove, Swineshead",
    "sg:city":"Boston",
    "sg:classifiers":[
        {
            "category":"Farming",
            "subcategory":"Livestock Farm",
            "type":"Manufacturing & Wholesale Goods"
        }
    ],
    "sg:phone":"+44 1205 820213",
    "sg:postcode":"PE20 3PX",
    "sg:province":"Lincolnshire",
    "sg:tags":[
        "others"
    ],
    "wof:name":"T Greetham",
    "wof:placetype":"venue"
},
  "geometry": {"coordinates":[-0.187225,52.976437],"type":"Point"}
}