{
  "type": "Feature",
  "properties": {
    "iso:country":"GB",
    "sg:address":"Bath Road, Taplow",
    "sg:city":"Maidenhead",
    "sg:classifiers":[
        {
            "category":"Travel",
            "subcategory":"Hotels & Motels",
            "type":"Entertainment"
        }
    ],
    "sg:postcode":"SL6 0AR",
    "sg:province":"Berkshire",
    "sg:tags":[
        "house",
        "guest"
    ],
    "wof:name":"Bridge Cottage Guest House",
    "wof:placetype":"venue"
},
  "geometry": {"coordinates":[-0.687149,51.532169],"type":"Point"}
}