{
  "type": "Feature",
  "properties": {
    "iso:country":"GB",
    "sg:address":"127 High Street",
    "sg:city":"Deal",
    "sg:classifiers":[
        {
            "category":"Professional",
            "subcategory":"Lawyer & Legal Services",
            "type":"Services"
        }
    ],
    "sg:phone":"+44 1304 362146",
    "sg:postcode":"CT14 6BD",
    "sg:province":"Kent",
    "sg:tags":[
        "solicitor"
    ],
    "wof:name":"Emmerson Brown & Brown",
    "wof:placetype":"venue"
},
  "geometry": {"coordinates":[1.4024020433,51.2264060974],"type":"Point"}
}