{
  "type": "Feature",
  "properties": {
    "iso:country":"GB",
    "sg:address":"10 Broadway",
    "sg:city":"Sheerness",
    "sg:classifiers":[
        {
            "category":"Real Estate",
            "subcategory":"Real Estate Agent",
            "type":"Services"
        }
    ],
    "sg:phone":"+44 1795 664651",
    "sg:postcode":"ME12 1AF",
    "sg:province":"Kent",
    "wof:name":"Ward & Partners",
    "wof:placetype":"venue"
},
  "geometry": {"coordinates":[0.7626019716,51.4398117065],"type":"Point"}
}