{
  "type": "Feature",
  "properties": {
    "addr:full":"70 Church Road Liverpool Merseyside L26 6LA",
    "addr:housenumber":"70",
    "addr:postcode":"l26 6la",
    "addr:street":"Church Road",
    "iso:country":"GB",
    "sg:address":"70 Church Road",
    "sg:city":"Liverpool",
    "sg:classifiers":[
        {
            "category":"Place Of Worship",
            "type":"Public Place"
        }
    ],
    "sg:phone":"+44 151 498 4186",
    "sg:postcode":"L26 6LA",
    "sg:province":"Merseyside",
    "wof:name":"St. Nicholas Centre",
    "wof:placetype":"venue"
},
  "geometry": {"coordinates":[-2.8286650181,53.3697128296],"type":"Point"}
}