{
  "type": "Feature",
  "properties": {
    "iso:country":"GB",
    "sg:address":"47 Regent Road, Harborne",
    "sg:city":"Birmingham",
    "sg:classifiers":[
        {
            "category":"Organizations",
            "subcategory":"Community Association",
            "type":"Services"
        }
    ],
    "sg:phone":"+44 121 428 4777",
    "sg:postcode":"B17 9JU",
    "sg:province":"West Midlands",
    "sg:tags":[
        "relation",
        "public"
    ],
    "wof:name":"I M C International Media Contacts",
    "wof:placetype":"venue"
},
  "geometry": {"coordinates":[-1.95007,52.459492],"type":"Point"}
}