{
  "type": "Feature",
  "properties": {
    "addr:full":"8 North Mersey Business Centre, Woodward Road Liverpool Lancashire L33 7UZ",
    "addr:housenumber":"8",
    "addr:postcode":"l33 7uz",
    "addr:street":"North Mersey;Woodward Road",
    "iso:country":"GB",
    "sg:address":"8 North Mersey Business Centre, Woodward Road",
    "sg:city":"Liverpool",
    "sg:classifiers":[
        {
            "category":"Shopping",
            "subcategory":"Stationery & Office Supplies",
            "type":"Retail Goods"
        }
    ],
    "sg:phone":"+44 151 546 7161",
    "sg:postcode":"L33 7UZ",
    "sg:province":"Lancashire",
    "sg:tags":[
        "recording",
        "machine",
        "time"
    ],
    "wof:name":"Auto Time Systems Northen",
    "wof:placetype":"venue"
},
  "geometry": {"coordinates":[-2.85515,53.489498],"type":"Point"}
}