{
  "type": "Feature",
  "properties": {
    "addr:full":"1 Peel Grove London Greater London E2 9LR",
    "addr:housenumber":"1",
    "addr:postcode":"e2 9lr",
    "addr:street":"Peel Grove",
    "iso:country":"GB",
    "sg:address":"1 Peel Grove",
    "sg:city":"London",
    "sg:classifiers":[
        {
            "category":"Professional",
            "subcategory":"Engineering",
            "type":"Services"
        }
    ],
    "sg:phone":"+44 20 8983 1616",
    "sg:postcode":"E2 9LR",
    "sg:province":"Greater London",
    "sg:tags":[
        "consultant",
        "consulting",
        "engineer",
        "structural"
    ],
    "wof:name":"Lewis Hodgson Associates Ltd.",
    "wof:placetype":"venue"
},
  "geometry": {"coordinates":[-0.0541599989,51.5303001404],"type":"Point"}
}