{
  "type": "Feature",
  "properties": {
    "addr:full":"2 Burley Lodge Road Leeds West Yorkshire LS6 1QP",
    "addr:housenumber":"2",
    "addr:postcode":"ls6 1qp",
    "addr:street":"Burley Lodge Road",
    "iso:country":"GB",
    "sg:address":"2 Burley Lodge Road",
    "sg:city":"Leeds",
    "sg:classifiers":[
        {
            "category":"Personal",
            "subcategory":"Barber",
            "type":"Services"
        }
    ],
    "sg:phone":"+44 113 294 4545",
    "sg:postcode":"LS6 1QP",
    "sg:province":"West Yorkshire",
    "sg:tags":[
        "men's",
        "gents",
        "hairdresser"
    ],
    "wof:name":"John's Hairdressing",
    "wof:placetype":"venue"
},
  "geometry": {"coordinates":[-1.5690619946,53.8057174683],"type":"Point"}
}