{
  "type": "Feature",
  "properties": {
    "addr:full":"9 Lower John Street London Greater London W1F 9EB",
    "addr:housenumber":"9",
    "addr:postcode":"w1f 9eb",
    "addr:street":"Lower John Street",
    "iso:country":"GB",
    "sg:address":"9 Lower John Street",
    "sg:city":"London",
    "sg:classifiers":[
        {
            "category":"Professional",
            "subcategory":"Advertising",
            "type":"Services"
        }
    ],
    "sg:phone":"+44 20 7437 4224",
    "sg:postcode":"W1F 9EB",
    "sg:province":"Greater London",
    "sg:tags":[
        "agency"
    ],
    "wof:name":"Cdp-Travissully Ltd.",
    "wof:placetype":"venue"
},
  "geometry": {"coordinates":[-0.13721,51.510929],"type":"Point"}
}