{
  "type": "Feature",
  "properties": {
    "iso:country":"GB",
    "sg:address":"6 Ashley Rd",
    "sg:city":"Market Harborough",
    "sg:classifiers":[
        {
            "category":"Professional",
            "subcategory":"Computer Services",
            "type":"Services"
        }
    ],
    "sg:phone":"+44 1858 565797",
    "sg:postcode":"LE16 8HR",
    "sg:province":"Leicestershire",
    "sg:tags":[
        "system",
        "software"
    ],
    "wof:name":"Penman Ltd",
    "wof:placetype":"venue"
},
  "geometry": {"coordinates":[-0.844174,52.513008],"type":"Point"}
}