{
  "type": "Feature",
  "properties": {
    "iso:country":"GB",
    "sg:address":"50 Albert Road",
    "sg:city":"Middlesbrough",
    "sg:classifiers":[
        {
            "category":"Professional",
            "subcategory":"Lawyer & Legal Services",
            "type":"Services"
        }
    ],
    "sg:phone":"+44 1642 247633",
    "sg:postcode":"TS1 1PF",
    "sg:province":"North Yorkshire",
    "sg:tags":[
        "solicitor"
    ],
    "wof:name":"Outhwaite Sutcliffe & Howard",
    "wof:placetype":"venue"
},
  "geometry": {"coordinates":[-1.2342569828,54.5767326355],"type":"Point"}
}