{
  "type": "Feature",
  "properties": {
    "iso:country":"GB",
    "sg:address":"1 Belvoir Rd",
    "sg:city":"Coalville",
    "sg:classifiers":[
        {
            "category":"Shopping",
            "subcategory":"Florist",
            "type":"Retail Goods"
        }
    ],
    "sg:postcode":"LE67 3PD",
    "sg:province":"Leicestershire",
    "wof:name":"Thompsons Florist",
    "wof:placetype":"venue"
},
  "geometry": {"coordinates":[-1.374514,52.724922],"type":"Point"}
}