{
  "type": "Feature",
  "properties": {
    "iso:country":"GB",
    "sg:address":"93 Bedford Avenue",
    "sg:city":"Hayes",
    "sg:classifiers":[
        {
            "category":"Freight",
            "type":"Transportation"
        }
    ],
    "sg:phone":"+44 7710 453606",
    "sg:postcode":"UB4 0DS",
    "sg:province":"Greater London",
    "sg:tags":[
        "haulage",
        "road"
    ],
    "wof:name":"G & L Logistics Consultancy Ltd.",
    "wof:placetype":"venue"
},
  "geometry": {"coordinates":[-0.4037550092,51.5223464966],"type":"Point"}
}