{
  "type": "Feature",
  "properties": {
    "iso:country":"GB",
    "sg:address":"Meinciau Road",
    "sg:city":"Llanelli",
    "sg:classifiers":[
        {
            "category":"Bars & Pubs",
            "type":"Food & Drink"
        }
    ],
    "sg:postcode":"SA15 5RT",
    "sg:province":"Carmarthenshire",
    "sg:tags":[
        "pubs",
        "inn"
    ],
    "wof:name":"The Square & Compass",
    "wof:placetype":"venue"
},
  "geometry": {"coordinates":[-4.226409,51.766956],"type":"Point"}
}