{
  "type": "Feature",
  "properties": {
    "addr:full":"40 Oxford Road London Greater London SW15 2LQ",
    "addr:housenumber":"40",
    "addr:postcode":"sw15 2lq",
    "addr:street":"Oxford Road",
    "iso:country":"GB",
    "sg:address":"40 Oxford Road",
    "sg:city":"London",
    "sg:classifiers":[
        {
            "category":"Social Services",
            "subcategory":"Retirement Home",
            "type":"Services"
        }
    ],
    "sg:postcode":"SW15 2LQ",
    "sg:province":"Greater London",
    "sg:tags":[
        "residential",
        "care"
    ],
    "wof:name":"The Paxtons Management Co. Ltd.",
    "wof:placetype":"venue"
},
  "geometry": {"coordinates":[-0.212211,51.461586],"type":"Point"}
}