{
  "type": "Feature",
  "properties": {
    "addr:full":"2-6 Park Rd Wellingborough Northamptonshire NN8 4PG",
    "addr:housenumber":"2-6",
    "addr:postcode":"nn8 4pg",
    "addr:street":"Park Rd",
    "iso:country":"GB",
    "sg:address":"2-6 Park Rd",
    "sg:city":"Wellingborough",
    "sg:classifiers":[
        {
            "category":"Community Center",
            "type":"Public Place"
        }
    ],
    "sg:phone":"+44 1933 275541",
    "sg:postcode":"NN8 4PG",
    "sg:province":"Northamptonshire",
    "sg:tags":[
        "centre"
    ],
    "wof:name":"Wellingborough Mosque & Community Centre",
    "wof:placetype":"venue"
},
  "geometry": {"coordinates":[-0.6919609904,52.303401947],"type":"Point"}
}