{
  "type": "Feature",
  "properties": {
    "iso:country":"GB",
    "sg:address":"14 Scott Lane, Riddlesden",
    "sg:city":"Keighley",
    "sg:classifiers":[
        {
            "category":"Travel",
            "subcategory":"Hotels & Motels",
            "type":"Entertainment"
        }
    ],
    "sg:phone":"+44 1535 607705",
    "sg:postcode":"BD20 5BT",
    "sg:province":"North Yorkshire",
    "sg:tags":[
        "house",
        "guest"
    ],
    "wof:name":"Rouselyn Guest House",
    "wof:placetype":"venue"
},
  "geometry": {"coordinates":[-1.888992,53.880093],"type":"Point"}
}