{
  "type": "Feature",
  "properties": {
    "iso:country":"GB",
    "sg:address":"47 Ffordd Ffynnon, Rhuddlan",
    "sg:city":"Rhyl",
    "sg:classifiers":[
        {
            "category":"Banks & Credit Unions",
            "subcategory":"Bank",
            "type":"Services"
        }
    ],
    "sg:postcode":"LL18 2SP",
    "sg:province":"Conwy",
    "sg:tags":[
        "broker",
        "mortgage"
    ],
    "wof:name":"White,A,",
    "wof:placetype":"venue"
},
  "geometry": {"coordinates":[-3.475319,53.307911],"type":"Point"}
}