{
  "type": "Feature",
  "properties": {
    "iso:country":"GB",
    "sg:address":"Palladium Buildings",
    "sg:city":"Middlesbrough",
    "sg:classifiers":[
        {
            "category":"Autos & Motor Vehicles",
            "subcategory":"Automobile Sales",
            "type":"Retail Goods"
        }
    ],
    "sg:phone":"+44 1642 270060",
    "sg:postcode":"TS4 2TZ",
    "sg:province":"North Yorkshire",
    "sg:tags":[
        "car"
    ],
    "wof:name":"Westminster Car Sales",
    "wof:placetype":"venue"
},
  "geometry": {"coordinates":[-1.23314,54.556938],"type":"Point"}
}