{
  "type": "Feature",
  "properties": {
    "addr:full":"3 Blackall Industrial Estate, Hamberts Road Chelmsford Essex CM3 5UW",
    "addr:housenumber":"3",
    "addr:postcode":"cm3 5uw",
    "addr:street":"Blackall Industrial Estate Hamberts Road",
    "iso:country":"GB",
    "sg:address":"3 Blackall Industrial Estate, Hamberts Road",
    "sg:city":"Chelmsford",
    "sg:classifiers":[
        {
            "category":"Manufacturing",
            "subcategory":"Metals",
            "type":"Manufacturing & Wholesale Goods"
        }
    ],
    "sg:phone":"+44 1245 322028",
    "sg:postcode":"CM3 5UW",
    "sg:province":"Essex",
    "sg:tags":[
        "work",
        "sheet"
    ],
    "wof:name":"Goldway Networks Ltd.",
    "wof:placetype":"venue"
},
  "geometry": {"coordinates":[0.6224409938,51.6514053345],"type":"Point"}
}