{
  "type": "Feature",
  "properties": {
    "iso:country":"GB",
    "sg:address":"29 Wimpole Street",
    "sg:city":"Ashton-under-lyne",
    "sg:classifiers":[
        {
            "category":"Real Estate",
            "subcategory":"Architect",
            "type":"Services"
        }
    ],
    "sg:postcode":"OL6 6EG",
    "sg:province":"Greater Manchester",
    "wof:name":"Pikeplace Limited",
    "wof:placetype":"venue"
},
  "geometry": {"coordinates":[-2.090354,53.490292],"type":"Point"}
}