{
  "type": "Feature",
  "properties": {
    "iso:country":"GB",
    "sg:address":"52a Commercial Street",
    "sg:city":"Hereford",
    "sg:classifiers":[
        {
            "category":"Retail",
            "subcategory":"Photofinishing",
            "type":"Services"
        }
    ],
    "sg:phone":"+44 870 750 5625",
    "sg:postcode":"HR1 2DJ",
    "sg:province":"Herefordshire",
    "sg:tags":[
        "processing",
        "photographic",
        "processor"
    ],
    "wof:name":"Klick Photo Point",
    "wof:placetype":"venue"
},
  "geometry": {"coordinates":[-2.710567,52.058285],"type":"Point"}
}