{
  "type": "Feature",
  "properties": {
    "addr:full":"Union Marine Bldg(s), 11 Dale Street Liverpool Merseyside L2 2SH",
    "addr:housenumber":"11",
    "addr:postcode":"l2 2sh",
    "addr:street":"Dale Street",
    "iso:country":"GB",
    "sg:address":"Union Marine Bldg(s), 11 Dale Street",
    "sg:city":"Liverpool",
    "sg:classifiers":[
        {
            "category":"Professional",
            "subcategory":"Lawyer & Legal Services",
            "type":"Services"
        }
    ],
    "sg:phone":"+44 151 236 2011",
    "sg:postcode":"L2 2SH",
    "sg:province":"Merseyside",
    "sg:tags":[
        "solicitor"
    ],
    "wof:name":"Connell Associates",
    "wof:placetype":"venue"
},
  "geometry": {"coordinates":[-2.99027,53.407478],"type":"Point"}
}