{
  "type": "Feature",
  "properties": {
    "addr:full":"362 Walworth Road London Greater London SE17 2NF",
    "addr:housenumber":"362",
    "addr:postcode":"se17 2nf",
    "addr:street":"Walworth Road",
    "iso:country":"GB",
    "sg:address":"362 Walworth Road",
    "sg:city":"London",
    "sg:classifiers":[
        {
            "category":"Retail",
            "subcategory":"Funeral Services",
            "type":"Services"
        }
    ],
    "sg:phone":"+44 20 7703 2803",
    "sg:postcode":"SE17 2NF",
    "sg:province":"Greater London",
    "wof:name":"Co-Operative Funeral Services",
    "wof:placetype":"venue"
},
  "geometry": {"coordinates":[-0.094237,51.485584],"type":"Point"}
}