{
  "type": "Feature",
  "properties": {
    "iso:country":"GB",
    "sg:address":"East Kerse Mains, Grangemouth Road",
    "sg:city":"Bo'ness",
    "sg:classifiers":[
        {
            "category":"Farming",
            "subcategory":"Livestock Farm",
            "type":"Manufacturing & Wholesale Goods"
        }
    ],
    "sg:phone":"+44 1506 822307",
    "sg:postcode":"EH51 0PY",
    "sg:province":"Falkirk",
    "sg:tags":[
        "others"
    ],
    "wof:name":"B Kirk",
    "wof:placetype":"venue"
},
  "geometry": {"coordinates":[-3.6696999073,56.0111885071],"type":"Point"}
}