{
  "type": "Feature",
  "properties": {
    "iso:country":"GB",
    "sg:address":"Wishaw Road, Waterloo",
    "sg:city":"Wishaw",
    "sg:classifiers":[
        {
            "category":"Train Station",
            "subcategory":"Rail",
            "type":"Transportation"
        }
    ],
    "sg:postcode":"ML2 8ES",
    "sg:province":"North Lanarkshire",
    "sg:tags":[
        "caravan"
    ],
    "wof:name":"Duncan Caravans",
    "wof:placetype":"venue"
},
  "geometry": {"coordinates":[-3.9057440758,55.7660942078],"type":"Point"}
}