{
  "type": "Feature",
  "properties": {
    "iso:country":"GB",
    "sg:address":"Woodland Cottage",
    "sg:city":"Ashtead",
    "sg:classifiers":[
        {
            "category":"Banks & Credit Unions",
            "subcategory":"Bank",
            "type":"Services"
        },
        {
            "category":"Professional",
            "subcategory":"Business Services",
            "type":"Services"
        }
    ],
    "sg:phone":"+44 1372 274363",
    "sg:postcode":"KT21 1LR",
    "sg:province":"Surrey",
    "sg:tags":[
        "financial",
        "institution",
        "holding"
    ],
    "wof:name":"Euro-Asia Group Ltd.",
    "wof:placetype":"venue"
},
  "geometry": {"coordinates":[-0.286797,51.317993],"type":"Point"}
}