{
  "type": "Feature",
  "properties": {
    "addr:full":"Rawlings House, Exchange Street Blackburn Lancashire BB1 7JN",
    "addr:postcode":"bb1 7jn",
    "addr:street":"Exchange Street",
    "iso:country":"GB",
    "sg:address":"Rawlings House, Exchange Street",
    "sg:city":"Blackburn",
    "sg:classifiers":[
        {
            "category":"Professional",
            "subcategory":"Lawyer & Legal Services",
            "type":"Services"
        }
    ],
    "sg:phone":"+44 1254 582330",
    "sg:postcode":"BB1 7JN",
    "sg:province":"Lancashire",
    "sg:tags":[
        "patent",
        "agent"
    ],
    "wof:name":"Urquhart-Dykes & Lord",
    "wof:placetype":"venue"
},
  "geometry": {"coordinates":[-2.484015,53.750099],"type":"Point"}
}