{
  "type": "Feature",
  "properties": {
    "addr:full":"28 Badger Way, Hazlemere High Wycombe Buckinghamshire HP15 7LJ",
    "addr:housenumber":"28",
    "addr:postcode":"hp15 7lj",
    "addr:street":"Badger Way",
    "iso:country":"GB",
    "sg:address":"28 Badger Way, Hazlemere",
    "sg:city":"High Wycombe",
    "sg:classifiers":[
        {
            "category":"Professional",
            "subcategory":"Management & Consulting",
            "type":"Services"
        }
    ],
    "sg:phone":"+44 1494 717283",
    "sg:postcode":"HP15 7LJ",
    "sg:province":"Buckinghamshire",
    "sg:tags":[
        "consultant",
        "business"
    ],
    "wof:name":"Icons Ltd.",
    "wof:placetype":"venue"
},
  "geometry": {"coordinates":[-0.702729,51.657207],"type":"Point"}
}