{
  "type": "Feature",
  "properties": {
    "addr:full":"Port Gaverne Hotel, Port Gaverne Port Isaac Cornwall PL29 3SQ",
    "addr:postcode":"pl29 3sq",
    "iso:country":"GB",
    "sg:address":"Port Gaverne Hotel, Port Gaverne",
    "sg:city":"Port Isaac",
    "sg:classifiers":[
        {
            "category":"Travel",
            "subcategory":"Hotels & Motels",
            "type":"Entertainment"
        }
    ],
    "sg:phone":"+44 1208 880151",
    "sg:postcode":"PL29 3SQ",
    "sg:province":"Cornwall",
    "wof:name":"Port Gaverne Hotel",
    "wof:placetype":"venue"
},
  "geometry": {"coordinates":[-4.828199,50.592339],"type":"Point"}
}