{
  "type": "Feature",
  "properties": {
    "iso:country":"GB",
    "sg:address":"32 Buxton Road",
    "sg:city":"Stockport",
    "sg:classifiers":[
        {
            "category":"Home & Garden",
            "subcategory":"Hardware",
            "type":"Retail Goods"
        }
    ],
    "sg:phone":"+44 1457 863311",
    "sg:postcode":"SK12 2EY",
    "sg:province":"Cheshire",
    "sg:tags":[
        "lawnmowers",
        "machinery"
    ],
    "wof:name":"Quick Sharp",
    "wof:placetype":"venue"
},
  "geometry": {"coordinates":[-2.021509,53.35796],"type":"Point"}
}