{
  "type": "Feature",
  "properties": {
    "addr:full":"5 Grange Mt Birkenhead Merseyside L43 4XN",
    "addr:housenumber":"5",
    "addr:postcode":"l43 4xn",
    "addr:street":"Grange Mt",
    "iso:country":"GB",
    "sg:address":"5 Grange Mt",
    "sg:city":"Birkenhead",
    "sg:classifiers":[
        {
            "category":"Food & Beverages",
            "subcategory":"Fruits & Vegetables",
            "type":"Retail Goods"
        }
    ],
    "sg:phone":"+44 151 652 5962",
    "sg:postcode":"L43 4XN",
    "sg:province":"Merseyside",
    "sg:tags":[
        "greengrocer"
    ],
    "wof:name":"Ainslies",
    "wof:placetype":"venue"
},
  "geometry": {"coordinates":[-3.035681963,53.3886451721],"type":"Point"}
}