{
  "type": "Feature",
  "properties": {
    "addr:full":"187 Woodrow Road Melksham Wiltshire SN12 7AY",
    "addr:housenumber":"187",
    "addr:postcode":"sn12 7ay",
    "addr:street":"Woodrow Road",
    "iso:country":"GB",
    "sg:address":"187 Woodrow Road",
    "sg:city":"Melksham",
    "sg:classifiers":[
        {
            "category":"Restaurant",
            "type":"Food & Drink"
        }
    ],
    "sg:phone":"+44 1225 702129",
    "sg:postcode":"SN12 7AY",
    "sg:province":"Wiltshire",
    "wof:name":"Toxique Restaurant",
    "wof:placetype":"venue"
},
  "geometry": {"coordinates":[-2.1246089935,51.3853988647],"type":"Point"}
}