{
  "type": "Feature",
  "properties": {
    "iso:country":"GB",
    "sg:address":"42 King St",
    "sg:city":"Burton On Trent",
    "sg:classifiers":[
        {
            "category":"Freight",
            "type":"Transportation"
        }
    ],
    "sg:phone":"+44 1283 565615",
    "sg:postcode":"DE14 3AF",
    "sg:province":"Derbyshire",
    "sg:tags":[
        "haulage",
        "road"
    ],
    "wof:name":"Jacqueline Transport",
    "wof:placetype":"venue"
},
  "geometry": {"coordinates":[-1.6406489611,52.7960929871],"type":"Point"}
}