{
  "type": "Feature",
  "properties": {
    "addr:full":"8 Cook Lane Keighley West Yorkshire BD21 3PF",
    "addr:housenumber":"8",
    "addr:postcode":"bd21 3pf",
    "addr:street":"Cook Lane",
    "iso:country":"GB",
    "sg:address":"8 Cook Lane",
    "sg:city":"Keighley",
    "sg:classifiers":[
        {
            "category":"Shopping",
            "subcategory":"Clothing, Apparel, & Fashions",
            "type":"Retail Goods"
        },
        {
            "category":"Shopping",
            "subcategory":"Baby Store",
            "type":"Retail Goods"
        }
    ],
    "sg:phone":"+44 1535 611500",
    "sg:postcode":"BD21 3PF",
    "sg:province":"West Yorkshire",
    "sg:tags":[
        "child",
        "childrens",
        "babywear"
    ],
    "wof:name":"Kids Connection",
    "wof:placetype":"venue"
},
  "geometry": {"coordinates":[-1.9083900452,53.867767334],"type":"Point"}
}