{
  "type": "Feature",
  "properties": {
    "addr:full":"7 Bolton Road, Worsley Manchester Greater Manchester M28 3AX",
    "addr:housenumber":"7",
    "addr:postcode":"m28 3ax",
    "addr:street":"Bolton Road",
    "iso:country":"GB",
    "sg:address":"7 Bolton Road, Worsley",
    "sg:city":"Manchester",
    "sg:classifiers":[
        {
            "category":"Personal",
            "subcategory":"Beauty Salon",
            "type":"Services"
        }
    ],
    "sg:phone":"+44 161 790 5451",
    "sg:postcode":"M28 3AX",
    "sg:province":"Greater Manchester",
    "sg:tags":[
        "unisex",
        "hairdresser"
    ],
    "wof:name":"The Clip Joint",
    "wof:placetype":"venue"
},
  "geometry": {"coordinates":[-2.3991,53.524197],"type":"Point"}
}