{
  "type": "Feature",
  "properties": {
    "addr:full":"Fairfield Hospital Grounds, Broadoak Terrace Bury Lancashire BL9 7TD",
    "addr:postcode":"bl9 7td",
    "addr:street":"Broadoak Terrace",
    "iso:country":"GB",
    "sg:address":"Fairfield Hospital Grounds, Broadoak Terrace",
    "sg:city":"Bury",
    "sg:classifiers":[
        {
            "category":"Farming",
            "subcategory":"Nursery",
            "type":"Manufacturing & Wholesale Goods"
        }
    ],
    "sg:phone":"+44 161 705 3613",
    "sg:postcode":"BL9 7TD",
    "sg:province":"Lancashire",
    "sg:tags":[
        "creche"
    ],
    "wof:name":"Fairfield Private Day Nursery",
    "wof:placetype":"venue"
},
  "geometry": {"coordinates":[-2.3010540009,53.5897331238],"type":"Point"}
}