{
  "type": "Feature",
  "properties": {
    "addr:full":"2 Hythe Cres Seaford East Sussex BN25 3TU",
    "addr:housenumber":"2",
    "addr:postcode":"bn25 3tu",
    "addr:street":"Hythe Cres",
    "iso:country":"GB",
    "sg:address":"2 Hythe Cres",
    "sg:city":"Seaford",
    "sg:classifiers":[
        {
            "category":"Building & Trades",
            "subcategory":"Construction",
            "type":"Services"
        }
    ],
    "sg:postcode":"BN25 3TU",
    "sg:province":"East Sussex",
    "sg:tags":[
        "builder"
    ],
    "wof:name":"Maintec",
    "wof:placetype":"venue"
},
  "geometry": {"coordinates":[0.1307329983,50.7805595398],"type":"Point"}
}