{
  "type": "Feature",
  "properties": {
    "iso:country":"GB",
    "sg:address":"57 Market Street, Atherton",
    "sg:city":"Manchester",
    "sg:classifiers":[
        {
            "category":"Shopping",
            "subcategory":"Discount & Variety Stores",
            "type":"Retail Goods"
        },
        {
            "category":"Shopping",
            "subcategory":"Pharmacy",
            "type":"Retail Goods"
        }
    ],
    "sg:phone":"+44 1942 873869",
    "sg:postcode":"M46 0DA",
    "sg:province":"Greater Manchester",
    "sg:tags":[
        "drug",
        "centre"
    ],
    "wof:name":"Quality Save",
    "wof:placetype":"venue"
},
  "geometry": {"coordinates":[-2.493098,53.523861],"type":"Point"}
}