{
  "type": "Feature",
  "properties": {
    "addr:full":"Avon House, 29 New Broad Street Stratford-upon-avon Warwickshire CV37 6NY",
    "addr:housenumber":"29",
    "addr:postcode":"cv37 6ny",
    "addr:street":"New Broad Street",
    "iso:country":"GB",
    "sg:address":"Avon House, 29 New Broad Street",
    "sg:city":"Stratford-upon-avon",
    "sg:classifiers":[
        {
            "category":"Shopping",
            "subcategory":"Pharmacy",
            "type":"Retail Goods"
        }
    ],
    "sg:phone":"+44 1789 267888",
    "sg:postcode":"CV37 6NY",
    "sg:province":"Warwickshire",
    "sg:tags":[
        "medicine",
        "therapy"
    ],
    "wof:name":"Avon House Natural Health Centre",
    "wof:placetype":"venue"
},
  "geometry": {"coordinates":[-1.7128269672,52.188041687],"type":"Point"}
}