{
  "type": "Feature",
  "properties": {
    "addr:full":"Calais Street, Boxford Sudbury Essex CO10 5JA",
    "addr:postcode":"co10 5ja",
    "addr:street":"Calais Street",
    "iso:country":"GB",
    "sg:address":"Calais Street, Boxford",
    "sg:city":"Sudbury",
    "sg:classifiers":[
        {
            "category":"Professional",
            "subcategory":"Printing & Photocopies",
            "type":"Services"
        }
    ],
    "sg:postcode":"CO10 5JA",
    "sg:province":"Essex",
    "sg:tags":[
        "printer"
    ],
    "wof:name":"Box Valley Printing",
    "wof:placetype":"venue"
},
  "geometry": {"coordinates":[0.8590679765,52.0260276794],"type":"Point"}
}