{
  "type": "Feature",
  "properties": {
    "addr:full":"13a Museum Street York North Yorkshire YO1 7DT",
    "addr:housenumber":"13a",
    "addr:postcode":"yo1 7dt",
    "addr:street":"Museum Street",
    "iso:country":"GB",
    "sg:address":"13a Museum Street",
    "sg:city":"York",
    "sg:classifiers":[
        {
            "category":"Food & Beverages",
            "subcategory":"Liquor & Beverages",
            "type":"Retail Goods"
        }
    ],
    "sg:phone":"+44 1904 641030",
    "sg:postcode":"YO1 7DT",
    "sg:province":"North Yorkshire",
    "sg:tags":[
        "beer",
        "wine",
        "spirit",
        "wines"
    ],
    "sg:website":"http://www.thresher.co.uk",
    "wof:name":"Threshers",
    "wof:placetype":"venue"
},
  "geometry": {"coordinates":[-1.0860699415,53.9608039856],"type":"Point"}
}