{
  "type": "Feature",
  "properties": {
    "addr:full":"Eridge Rest Home, 12 Richmond Road Bexhill-on-sea East Sussex TN39 3DN",
    "addr:housenumber":"12",
    "addr:postcode":"tn39 3dn",
    "addr:street":"Richmond Road",
    "iso:country":"GB",
    "sg:address":"Eridge Rest Home, 12 Richmond Road",
    "sg:city":"Bexhill-on-sea",
    "sg:classifiers":[
        {
            "category":"Health Services",
            "subcategory":"Nursing And Care Facility",
            "type":"Services"
        },
        {
            "category":"Social Services",
            "subcategory":"Retirement Home",
            "type":"Services"
        }
    ],
    "sg:phone":"+44 1424 214500",
    "sg:postcode":"TN39 3DN",
    "sg:province":"East Sussex",
    "sg:tags":[
        "residential"
    ],
    "wof:name":"Eridge Rest Home",
    "wof:placetype":"venue"
},
  "geometry": {"coordinates":[0.458205,50.837387],"type":"Point"}
}