{
  "type": "Feature",
  "properties": {
    "iso:country":"GB",
    "sg:address":"Garsett Ho, St Andrews Hall Plain",
    "sg:city":"Norwich",
    "sg:classifiers":[
        {
            "category":"Professional",
            "type":"Services"
        },
        {
            "category":"Government",
            "subcategory":"Office",
            "type":"Public Place"
        }
    ],
    "sg:phone":"+44 1603 633564",
    "sg:postcode":"NR3 1AU",
    "sg:province":"Norfolk",
    "sg:tags":[
        "archaeologist",
        "local"
    ],
    "wof:name":"Norfolk County Council",
    "wof:placetype":"venue"
},
  "geometry": {"coordinates":[1.29638,52.630619],"type":"Point"}
}