{
  "type": "Feature",
  "properties": {
    "addr:full":", Otterham Camelford Cornwall PL32 9SW",
    "addr:postcode":"pl32 9sw",
    "addr:street":"Otterham",
    "iso:country":"GB",
    "sg:address":", Otterham",
    "sg:city":"Camelford",
    "sg:classifiers":[
        {
            "category":"Retail",
            "subcategory":"Auto Repair",
            "type":"Services"
        }
    ],
    "sg:phone":"+44 1840 261230",
    "sg:postcode":"PL32 9SW",
    "sg:province":"Cornwall",
    "sg:tags":[
        "modification",
        "garage"
    ],
    "wof:name":"Otterham Garage",
    "wof:placetype":"venue"
},
  "geometry": {"coordinates":[-4.650909,50.641472],"type":"Point"}
}