{
  "type": "Feature",
  "properties": {
    "iso:country":"GB",
    "sg:address":"7 Leamington House, 23 Stone Gro",
    "sg:city":"Edgware",
    "sg:classifiers":[
        {
            "category":"Food & Beverages",
            "subcategory":"Liquor & Beverages",
            "type":"Retail Goods"
        }
    ],
    "sg:phone":"+44 20 8958 9372",
    "sg:postcode":"HA8 7TN",
    "sg:province":"Greater London",
    "sg:tags":[
        "beer",
        "spirit",
        "wines"
    ],
    "wof:name":"Hilton of London",
    "wof:placetype":"venue"
},
  "geometry": {"coordinates":[-0.277564,51.612083],"type":"Point"}
}