{
  "type": "Feature",
  "properties": {
    "addr:full":"3 Earl Grey Street Mauchline East Ayrshire KA5 5AB",
    "addr:housenumber":"3",
    "addr:postcode":"ka5 5ab",
    "addr:street":"Earl Grey Street",
    "iso:country":"GB",
    "sg:address":"3 Earl Grey Street",
    "sg:city":"Mauchline",
    "sg:classifiers":[
        {
            "category":"Personal",
            "subcategory":"Beauty Salon",
            "type":"Services"
        }
    ],
    "sg:phone":"+44 1290 550523",
    "sg:postcode":"KA5 5AB",
    "sg:province":"East Ayrshire",
    "sg:tags":[
        "unisex",
        "hairdresser"
    ],
    "wof:name":"New Image",
    "wof:placetype":"venue"
},
  "geometry": {"coordinates":[-4.378866,55.515888],"type":"Point"}
}