{
  "type": "Feature",
  "properties": {
    "addr:full":"2 Chats Wood Fold Bradford West Yorkshire BD12 7HG",
    "addr:housenumber":"2;bradford",
    "addr:postcode":"bd12 7hg",
    "addr:street":"Chats Wood Fold",
    "iso:country":"GB",
    "sg:address":"2 Chats Wood Fold",
    "sg:city":"Bradford",
    "sg:classifiers":[
        {
            "category":"Building & Trades",
            "subcategory":"Plumbing",
            "type":"Services"
        }
    ],
    "sg:postcode":"BD12 7HG",
    "sg:province":"West Yorkshire",
    "sg:tags":[
        "central",
        "heating"
    ],
    "wof:name":"Philips Plumbing & Heating Services",
    "wof:placetype":"venue"
},
  "geometry": {"coordinates":[-1.733304,53.749645],"type":"Point"}
}