{
  "type": "Feature",
  "properties": {
    "iso:country":"GB",
    "sg:address":"72 Victoria Street",
    "sg:city":"Perth",
    "sg:classifiers":[
        {
            "category":"Professional",
            "subcategory":"Business Services",
            "type":"Services"
        }
    ],
    "sg:phone":"+44 1738 442443",
    "sg:postcode":"PH2 8JS",
    "sg:province":"Perth and Kinross",
    "sg:tags":[
        "import",
        "export",
        "agent"
    ],
    "wof:name":"Ultramake Ltd.",
    "wof:placetype":"venue"
},
  "geometry": {"coordinates":[-3.4331960678,56.3933868408],"type":"Point"}
}