{
  "type": "Feature",
  "properties": {
    "addr:full":"191 Delaval Road Newcastle-upon-tyne Northumberland NE15 6TR",
    "addr:housenumber":"191",
    "addr:postcode":"ne15 6tr",
    "addr:street":"Delaval Road",
    "iso:country":"GB",
    "sg:address":"191 Delaval Road",
    "sg:city":"Newcastle-upon-tyne",
    "sg:classifiers":[
        {
            "category":"Government",
            "subcategory":"Post Office",
            "type":"Public Place"
        }
    ],
    "sg:phone":"+44 191 274 4990",
    "sg:postcode":"NE15 6TR",
    "sg:province":"Northumberland",
    "wof:name":"West Benwell Post Office",
    "wof:placetype":"venue"
},
  "geometry": {"coordinates":[-1.6736880541,54.9735031128],"type":"Point"}
}