{
  "type": "Feature",
  "properties": {
    "addr:full":"5a Market St Wotton-under-edge Gloucestershire GL12 7AE",
    "addr:housenumber":"5a",
    "addr:postcode":"gl12 7ae",
    "addr:street":"Market St",
    "iso:country":"GB",
    "sg:address":"5a Market St",
    "sg:city":"Wotton-under-edge",
    "sg:classifiers":[
        {
            "category":"Building & Trades",
            "subcategory":"Plumbing",
            "type":"Services"
        }
    ],
    "sg:postcode":"GL12 7AE",
    "sg:province":"Gloucestershire",
    "sg:tags":[
        "heating"
    ],
    "wof:name":"Contract Technical Services Partnership",
    "wof:placetype":"venue"
},
  "geometry": {"coordinates":[-2.35412,51.637573],"type":"Point"}
}