{
  "type": "Feature",
  "properties": {
    "addr:full":"19a Canon Street Newport Newport NP19 7FE",
    "addr:housenumber":"19a",
    "addr:postcode":"np19 7fe",
    "addr:street":"Canon Street",
    "iso:country":"GB",
    "sg:address":"19a Canon Street",
    "sg:city":"Newport",
    "sg:classifiers":[
        {
            "category":"Building & Trades",
            "subcategory":"Construction",
            "type":"Services"
        }
    ],
    "sg:postcode":"NP19 7FE",
    "sg:province":"Newport",
    "sg:tags":[
        "builder"
    ],
    "wof:name":"Mike Otton Professional Building Services",
    "wof:placetype":"venue"
},
  "geometry": {"coordinates":[-2.9836409092,51.5942764282],"type":"Point"}
}