{
  "type": "Feature",
  "properties": {
    "addr:full":"19 Faringdon Rd Swindon Wiltshire SN1 5AR",
    "addr:housenumber":"19",
    "addr:postcode":"sn1 5ar",
    "addr:street":"Faringdon Rd",
    "iso:country":"GB",
    "sg:address":"19 Faringdon Rd",
    "sg:city":"Swindon",
    "sg:classifiers":[
        {
            "category":"Professional",
            "subcategory":"Employment Agencies",
            "type":"Services"
        }
    ],
    "sg:phone":"+44 1793 523251",
    "sg:postcode":"SN1 5AR",
    "sg:province":"Wiltshire",
    "sg:tags":[
        "career",
        "guidance"
    ],
    "wof:name":"Army Careers Information Office",
    "wof:placetype":"venue"
},
  "geometry": {"coordinates":[-1.788832,51.561581],"type":"Point"}
}