{
  "type": "Feature",
  "properties": {
    "iso:country":"GB",
    "sg:address":"Upper Mitton Farm, Mitton, Penkridge",
    "sg:city":"Stafford",
    "sg:classifiers":[
        {
            "category":"Farming",
            "subcategory":"Livestock Farm",
            "type":"Manufacturing & Wholesale Goods"
        }
    ],
    "sg:phone":"+44 1785 780254",
    "sg:postcode":"ST19 5QW",
    "sg:province":"Shropshire",
    "sg:tags":[
        "others"
    ],
    "wof:name":"Norman W Kent",
    "wof:placetype":"venue"
},
  "geometry": {"coordinates":[-2.11634,52.722607],"type":"Point"}
}