{
  "type": "Feature",
  "properties": {
    "addr:full":"60 Pengam St Blackwood Caerphilly NP12 3XJ",
    "addr:housenumber":"60",
    "addr:postcode":"np12 3xj",
    "addr:street":"Pengam St",
    "iso:country":"GB",
    "sg:address":"60 Pengam St",
    "sg:city":"Blackwood",
    "sg:classifiers":[
        {
            "category":"Building & Trades",
            "subcategory":"Construction",
            "type":"Services"
        }
    ],
    "sg:phone":"+44 1443 820640",
    "sg:postcode":"NP12 3XJ",
    "sg:province":"Caerphilly",
    "sg:tags":[
        "platform",
        "work",
        "scaffolding"
    ],
    "wof:name":"All Around Scaffolding",
    "wof:placetype":"venue"
},
  "geometry": {"coordinates":[-3.2301430702,51.6690254211],"type":"Point"}
}