{
  "type": "Feature",
  "properties": {
    "addr:full":"Riversdale Mills, Mansfield Sq Hawick Cumbria TD9 8AH",
    "addr:postcode":"td9 8ah",
    "addr:street":"Riversdale;Mansfield Sq Hawick",
    "iso:country":"GB",
    "sg:address":"Riversdale Mills, Mansfield Sq",
    "sg:city":"Hawick",
    "sg:classifiers":[
        {
            "category":"Shopping",
            "subcategory":"Crafts & Fabrics",
            "type":"Retail Goods"
        }
    ],
    "sg:phone":"+44 1450 372383",
    "sg:postcode":"TD9 8AH",
    "sg:province":"Cumbria",
    "sg:tags":[
        "knitting"
    ],
    "wof:name":"Woodcock Scotland Ltd",
    "wof:placetype":"venue"
},
  "geometry": {"coordinates":[-2.78065,55.42984],"type":"Point"}
}