{
  "type": "Feature",
  "properties": {
    "addr:full":"Barncroft, Windhill Shipley West Yorkshire BD18 2JG",
    "addr:postcode":"bd18 2jg",
    "addr:street":"Barncroft;West",
    "iso:country":"GB",
    "sg:address":"Barncroft, Windhill",
    "sg:city":"Shipley",
    "sg:classifiers":[
        {
            "category":"Social Services",
            "type":"Services"
        }
    ],
    "sg:phone":"+44 1274 530877",
    "sg:postcode":"BD18 2JG",
    "sg:province":"West Yorkshire",
    "sg:tags":[
        "ds"
    ],
    "wof:name":"Owlett Family Centre",
    "wof:placetype":"venue"
},
  "geometry": {"coordinates":[-1.765135,53.830803],"type":"Point"}
}