{
  "type": "Feature",
  "properties": {
    "addr:full":"Briar Cottage, Bunbury Commons, Bunbury Tarporley Cheshire CW6 9QD",
    "addr:postcode":"cw6 9qd",
    "addr:street":"Bunbury;Tarporley",
    "iso:country":"GB",
    "sg:address":"Briar Cottage, Bunbury Commons, Bunbury",
    "sg:city":"Tarporley",
    "sg:classifiers":[
        {
            "category":"Real Estate",
            "subcategory":"Architect",
            "type":"Services"
        }
    ],
    "sg:postcode":"CW6 9QD",
    "sg:province":"Cheshire",
    "wof:name":"John E Edwards",
    "wof:placetype":"venue"
},
  "geometry": {"coordinates":[-2.661644,53.121246],"type":"Point"}
}