{
  "type": "Feature",
  "properties": {
    "iso:country":"GB",
    "sg:address":"6 Adams Way",
    "sg:city":"Croydon",
    "sg:classifiers":[
        {
            "category":"Health Services",
            "subcategory":"Health Practitioner",
            "type":"Services"
        }
    ],
    "sg:postcode":"CR0 6JT",
    "sg:province":"Surrey",
    "sg:tags":[
        "homoeopathic"
    ],
    "wof:name":"J Dabrowski",
    "wof:placetype":"venue"
},
  "geometry": {"coordinates":[-0.076441,51.387775],"type":"Point"}
}