{
  "type": "Feature",
  "properties": {
    "iso:country":"GB",
    "sg:address":"7 High Street West, Uppingham",
    "sg:city":"Oakham",
    "sg:classifiers":[
        {
            "category":"Shopping",
            "subcategory":"Books",
            "type":"Retail Goods"
        },
        {
            "category":"Shopping",
            "subcategory":"Used Merchandise",
            "type":"Retail Goods"
        }
    ],
    "sg:phone":"+44 1572 821173",
    "sg:postcode":"LE15 9QB",
    "sg:province":"Leicestershire",
    "sg:tags":[
        "second-hand",
        "secondhand"
    ],
    "wof:name":"Forest Books",
    "wof:placetype":"venue"
},
  "geometry": {"coordinates":[-0.638565,52.596779],"type":"Point"}
}