{
  "type": "Feature",
  "properties": {
    "addr:full":"Lancaster Way Braintree Essex CM7 5UL",
    "addr:postcode":"cm7 5ul",
    "addr:street":"Lancaster Way",
    "iso:country":"GB",
    "sg:address":"Lancaster Way",
    "sg:city":"Braintree",
    "sg:classifiers":[
        {
            "category":"Education",
            "subcategory":"School",
            "type":"Public Place"
        }
    ],
    "sg:phone":"+44 1376 320272",
    "sg:postcode":"CM7 5UL",
    "sg:province":"Essex",
    "sg:tags":[
        "local",
        "authority"
    ],
    "wof:name":"John Bunjon Community Junior School",
    "wof:placetype":"venue"
},
  "geometry": {"coordinates":[0.5460199714,51.8856544495],"type":"Point"}
}