{
  "type": "Feature",
  "properties": {
    "iso:country":"GB",
    "sg:address":"37a Regent Road",
    "sg:city":"Morecambe",
    "sg:classifiers":[
        {
            "category":"Manufacturing",
            "subcategory":"Tools & Machinery",
            "type":"Manufacturing & Wholesale Goods"
        }
    ],
    "sg:phone":"+44 1524 400271",
    "sg:postcode":"LA3 1QQ",
    "sg:province":"Lancashire",
    "sg:tags":[
        "society",
        "friendly"
    ],
    "wof:name":"Select Insurance",
    "wof:placetype":"venue"
},
  "geometry": {"coordinates":[-2.879367,54.065289],"type":"Point"}
}