{
  "type": "Feature",
  "properties": {
    "iso:country":"GB",
    "sg:address":"Well Cottage, New Pond Hill, Cross In Hand",
    "sg:city":"Heathfield",
    "sg:classifiers":[
        {
            "category":"Airline",
            "type":"Transportation"
        }
    ],
    "sg:phone":"+44 1435 863593",
    "sg:postcode":"TN21 0LY",
    "sg:province":"East Sussex",
    "sg:tags":[
        "aircraft",
        "charter"
    ],
    "wof:name":"Skyline Aviation Ltd.",
    "wof:placetype":"venue"
},
  "geometry": {"coordinates":[0.225756,50.973572],"type":"Point"}
}