{
  "type": "Feature",
  "properties": {
    "addr:full":"Po Box 51 Virginia Water Surrey GU25 4FP",
    "addr:housenumber":"po box 51",
    "addr:postcode":"gu25 4fp",
    "addr:street":"Virginia Water",
    "iso:country":"GB",
    "sg:address":"Po Box 51",
    "sg:city":"Virginia Water",
    "sg:classifiers":[
        {
            "category":"Communications",
            "type":"Services"
        }
    ],
    "sg:phone":"+44 1344 849349",
    "sg:postcode":"GU25 4FP",
    "sg:province":"Surrey",
    "sg:tags":[
        "data",
        "network"
    ],
    "wof:name":"Nexus Connections Ltd.",
    "wof:placetype":"venue"
},
  "geometry": {"coordinates":[-0.565059,51.404171],"type":"Point"}
}