{
  "type": "Feature",
  "properties": {
    "iso:country":"GB",
    "sg:address":"24 Wyle Cop",
    "sg:city":"Shrewsbury",
    "sg:classifiers":[
        {
            "category":"Personal",
            "subcategory":"Beauty Salon",
            "type":"Services"
        }
    ],
    "sg:phone":"+44 1743 247194",
    "sg:postcode":"SY1 1XB",
    "sg:province":"Shropshire",
    "sg:tags":[
        "unisex",
        "hairdresser"
    ],
    "wof:name":"Sheer Elegance",
    "wof:placetype":"venue"
},
  "geometry": {"coordinates":[-2.7509810925,52.7062606812],"type":"Point"}
}