{
  "type": "Feature",
  "properties": {
    "addr:full":"19 North Pole Road London Greater London W10 6QH",
    "addr:housenumber":"19",
    "addr:postcode":"w10 6qh",
    "addr:street":"North Pole Road",
    "iso:country":"GB",
    "sg:address":"19 North Pole Road",
    "sg:city":"London",
    "sg:classifiers":[
        {
            "category":"Personal",
            "subcategory":"Beauty Salon",
            "type":"Services"
        }
    ],
    "sg:phone":"+44 20 8969 0400",
    "sg:postcode":"W10 6QH",
    "sg:province":"Greater London",
    "sg:tags":[
        "ladies",
        "lady",
        "hairdresser"
    ],
    "wof:name":"Marions Hairdressers",
    "wof:placetype":"venue"
},
  "geometry": {"coordinates":[-0.226109,51.519772],"type":"Point"}
}