{
  "type": "Feature",
  "properties": {
    "addr:full":"Opas House, Market Street Sutton-in-ashfield Nottinghamshire NG17 1AH",
    "addr:postcode":"ng17 1ah",
    "addr:street":"Market Street",
    "iso:country":"GB",
    "sg:address":"Opas House, Market Street",
    "sg:city":"Sutton-in-ashfield",
    "sg:classifiers":[
        {
            "category":"Professional",
            "type":"Services"
        }
    ],
    "sg:phone":"+44 1623 451145",
    "sg:postcode":"NG17 1AH",
    "sg:province":"Nottinghamshire",
    "sg:tags":[
        "notary",
        "public"
    ],
    "wof:name":"A T Slade",
    "wof:placetype":"venue"
},
  "geometry": {"coordinates":[-1.2642339468,53.1251296997],"type":"Point"}
}