{
  "type": "Feature",
  "properties": {
    "iso:country":"GB",
    "sg:address":"177 Goldthorn Hill",
    "sg:city":"Wolverhampton",
    "sg:classifiers":[
        {
            "category":"Retail",
            "subcategory":"Driving School",
            "type":"Services"
        }
    ],
    "sg:phone":"+44 1902 337884",
    "sg:postcode":"WV2 4QB",
    "sg:province":"West Midlands",
    "wof:name":"Goldthorn School of Motoring",
    "wof:placetype":"venue"
},
  "geometry": {"coordinates":[-2.1416199207,52.5685043335],"type":"Point"}
}