{
  "type": "Feature",
  "properties": {
    "addr:full":"71 Gaynor Avenue Loanhead Midlothian EH20 9LU",
    "addr:housenumber":"71",
    "addr:postcode":"eh20 9lu",
    "addr:street":"Gaynor Avenue",
    "iso:country":"GB",
    "sg:address":"71 Gaynor Avenue",
    "sg:city":"Loanhead",
    "sg:classifiers":[
        {
            "category":"Building & Trades",
            "subcategory":"Construction",
            "type":"Services"
        }
    ],
    "sg:phone":"+44 131 448 2203",
    "sg:postcode":"EH20 9LU",
    "sg:province":"Midlothian",
    "sg:tags":[
        "roofing"
    ],
    "wof:name":"SABS",
    "wof:placetype":"venue"
},
  "geometry": {"coordinates":[-3.154689,55.880932],"type":"Point"}
}