{
  "type": "Feature",
  "properties": {
    "addr:full":"66 Preston St Brighton East Sussex BN1 2HE",
    "addr:housenumber":"66",
    "addr:postcode":"bn1 2he",
    "addr:street":"Preston St",
    "iso:country":"GB",
    "sg:address":"66 Preston St",
    "sg:city":"Brighton",
    "sg:classifiers":[
        {
            "category":"Bars & Pubs",
            "type":"Food & Drink"
        }
    ],
    "sg:phone":"+44 1273 323289",
    "sg:postcode":"BN1 2HE",
    "sg:province":"East Sussex",
    "sg:tags":[
        "pubs",
        "inn"
    ],
    "wof:name":"The Royal Sovereign",
    "wof:placetype":"venue"
},
  "geometry": {"coordinates":[-0.150859,50.823639],"type":"Point"}
}