{
  "type": "Feature",
  "properties": {
    "addr:full":"11 Skylines Village, Limeharbour Poplar Greater London E14 9TS",
    "addr:housenumber":"11",
    "addr:postcode":"e14 9ts",
    "addr:street":"Skylines Village Limeharbour",
    "iso:country":"GB",
    "sg:address":"11 Skylines Village, Limeharbour",
    "sg:city":"Poplar",
    "sg:classifiers":[
        {
            "category":"Communications",
            "subcategory":"Newspaper",
            "type":"Services"
        }
    ],
    "sg:phone":"+44 20 7536 9060",
    "sg:postcode":"E14 9TS",
    "sg:province":"Greater London",
    "sg:tags":[
        "magazine"
    ],
    "wof:name":"Gateway Publishing & Events Ltd",
    "wof:placetype":"venue"
},
  "geometry": {"coordinates":[-0.0128300004,51.4991416931],"type":"Point"}
}