{
  "type": "Feature",
  "properties": {
    "iso:country":"GB",
    "sg:address":"Victory, Main Road, Kirton Holme",
    "sg:city":"Boston",
    "sg:classifiers":[
        {
            "category":"Freight",
            "type":"Transportation"
        }
    ],
    "sg:postcode":"PE20 1TT",
    "sg:province":"Lincolnshire",
    "sg:tags":[
        "haulage",
        "road"
    ],
    "wof:name":"Smedley Artic Trailer Services",
    "wof:placetype":"venue"
},
  "geometry": {"coordinates":[-0.057138,52.928047],"type":"Point"}
}