{
  "type": "Feature",
  "properties": {
    "iso:country":"GB",
    "sg:address":"Unit 12/16, Corringham Road Indstrl Estate, Corringham Road",
    "sg:city":"Gainsborough",
    "sg:classifiers":[
        {
            "category":"Manufacturing",
            "subcategory":"Wood Products",
            "type":"Manufacturing & Wholesale Goods"
        }
    ],
    "sg:phone":"+44 1427 612007",
    "sg:postcode":"DN21 1QB",
    "sg:province":"Lincolnshire",
    "sg:tags":[
        "packaging",
        "crate",
        "pallets"
    ],
    "wof:name":"Kirkston Packaging & Insulation (E Midlands) Ltd.",
    "wof:placetype":"venue"
},
  "geometry": {"coordinates":[-0.747154,53.405338],"type":"Point"}
}