{
  "type": "Feature",
  "properties": {
    "addr:full":"Cyrus St Manchester Greater Manchester M40 7FG",
    "addr:postcode":"m40 7fg",
    "addr:street":"Cyrus St",
    "iso:country":"GB",
    "sg:address":"Cyrus St",
    "sg:city":"Manchester",
    "sg:classifiers":[
        {
            "category":"Professional",
            "subcategory":"Engineering",
            "type":"Services"
        }
    ],
    "sg:phone":"+44 161 273 2327",
    "sg:postcode":"M40 7FG",
    "sg:province":"Greater Manchester",
    "sg:tags":[
        "precision",
        "engineer"
    ],
    "wof:name":"Project Set Ltd",
    "wof:placetype":"venue"
},
  "geometry": {"coordinates":[-2.212154,53.483967],"type":"Point"}
}