{
  "type": "Feature",
  "properties": {
    "addr:full":"Gellihir Farm Treharris Caerphilly CF46 6PL",
    "addr:postcode":"cf46 6pl",
    "iso:country":"GB",
    "sg:address":"Gellihir Farm",
    "sg:city":"Treharris",
    "sg:classifiers":[
        {
            "category":"Farming",
            "subcategory":"Livestock Farm",
            "type":"Manufacturing & Wholesale Goods"
        }
    ],
    "sg:phone":"+44 1443 450452",
    "sg:postcode":"CF46 6PL",
    "sg:province":"Caerphilly",
    "sg:tags":[
        "others"
    ],
    "wof:name":"E V Thomas",
    "wof:placetype":"venue"
},
  "geometry": {"coordinates":[-3.2970159054,51.6672515869],"type":"Point"}
}