{
  "type": "Feature",
  "properties": {
    "addr:full":"Howards Lane, Orrell Wigan Lancashire WN5 8PY",
    "addr:postcode":"wn5 8py",
    "addr:street":"Howards Lane",
    "iso:country":"GB",
    "sg:address":"Howards Lane, Orrell",
    "sg:city":"Wigan",
    "sg:classifiers":[
        {
            "category":"Social Services",
            "subcategory":"Adult Care",
            "type":"Services"
        }
    ],
    "sg:phone":"+44 1942 215251",
    "sg:postcode":"WN5 8PY",
    "sg:province":"Lancashire",
    "sg:tags":[
        "housing",
        "sheltered"
    ],
    "wof:name":"Mountfield Court",
    "wof:placetype":"venue"
},
  "geometry": {"coordinates":[-2.7016539574,53.5401992798],"type":"Point"}
}