{
  "type": "Feature",
  "properties": {
    "addr:full":"12a York Road Northampton Northamptonshire NN1 5QG",
    "addr:housenumber":"12a",
    "addr:postcode":"nn1 5qg",
    "addr:street":"York Road",
    "iso:country":"GB",
    "sg:address":"12a York Road",
    "sg:city":"Northampton",
    "sg:classifiers":[
        {
            "category":"Health Services",
            "subcategory":"Health Practitioner",
            "type":"Services"
        }
    ],
    "sg:phone":"+44 1604 632129",
    "sg:postcode":"NN1 5QG",
    "sg:province":"Northamptonshire",
    "sg:tags":[
        "acupuncture"
    ],
    "wof:name":"Acupuncture Clinic",
    "wof:placetype":"venue"
},
  "geometry": {"coordinates":[-0.888314,52.238369],"type":"Point"}
}