{
  "type": "Feature",
  "properties": {
    "addr:full":"7a Church St Kingsbridge Devon TQ7 1BT",
    "addr:housenumber":"7a",
    "addr:postcode":"tq7 1bt",
    "addr:street":"Church St",
    "iso:country":"GB",
    "sg:address":"7a Church St",
    "sg:city":"Kingsbridge",
    "sg:classifiers":[
        {
            "category":"Fast Food",
            "type":"Food & Drink"
        }
    ],
    "sg:phone":"+44 1548 856699",
    "sg:postcode":"TQ7 1BT",
    "sg:province":"Devon",
    "sg:tags":[
        "away",
        "take"
    ],
    "wof:name":"Lunch Box The",
    "wof:placetype":"venue"
},
  "geometry": {"coordinates":[-3.7762339115,50.2844810486],"type":"Point"}
}