{
  "type": "Feature",
  "properties": {
    "addr:full":"24a Alens Road, Hamworthy Poole Dorset BH16 5BU",
    "addr:housenumber":"24a",
    "addr:postcode":"bh16 5bu",
    "addr:street":"Alens Road",
    "iso:country":"GB",
    "sg:address":"24a Alens Road, Hamworthy",
    "sg:city":"Poole",
    "sg:classifiers":[
        {
            "category":"Home & Garden",
            "subcategory":"Hardware",
            "type":"Retail Goods"
        }
    ],
    "sg:postcode":"BH16 5BU",
    "sg:province":"Dorset",
    "sg:tags":[
        "equipment",
        "heating"
    ],
    "wof:name":"Industrial Combustion Gas & Oil",
    "wof:placetype":"venue"
},
  "geometry": {"coordinates":[-2.0221819878,50.7331085205],"type":"Point"}
}