{
  "type": "Feature",
  "properties": {
    "iso:country":"GB",
    "sg:address":"904 High Road",
    "sg:city":"London",
    "sg:classifiers":[
        {
            "category":"Manufacturing",
            "subcategory":"Tools & Machinery",
            "type":"Manufacturing & Wholesale Goods"
        },
        {
            "category":"Insurance",
            "subcategory":"Insurance Agent",
            "type":"Services"
        }
    ],
    "sg:phone":"+44 20 8445 8878",
    "sg:postcode":"N12 9RW",
    "sg:province":"Greater London",
    "sg:tags":[
        "society",
        "friendly"
    ],
    "wof:name":"ANCIENT ORDER OF FORESTERS",
    "wof:placetype":"venue"
},
  "geometry": {"coordinates":[-0.1764699966,51.6202507019],"type":"Point"}
}