{
  "type": "Feature",
  "properties": {
    "iso:country":"GB",
    "sg:address":"Gemini House, Hargreaves Road",
    "sg:city":"Swindon",
    "sg:classifiers":[
        {
            "category":"Professional",
            "subcategory":"Management & Consulting",
            "type":"Services"
        }
    ],
    "sg:phone":"+44 1793 725766",
    "sg:postcode":"SN25 5AL",
    "sg:province":"Wiltshire",
    "sg:tags":[
        "environmental",
        "consultant"
    ],
    "wof:name":"Fugro Global Environmental & Ocean Sciences Ltd.",
    "wof:placetype":"venue"
},
  "geometry": {"coordinates":[-1.7739739418,51.5967483521],"type":"Point"}
}