{
  "type": "Feature",
  "properties": {
    "addr:full":"16 Market Street Hebden Bridge West Yorkshire HX7 6AA",
    "addr:housenumber":"16",
    "addr:postcode":"hx7 6aa",
    "addr:street":"Market Street",
    "iso:country":"GB",
    "sg:address":"16 Market Street",
    "sg:city":"Hebden Bridge",
    "sg:classifiers":[
        {
            "category":"Shopping",
            "subcategory":"Hobbies, Toys, & Games",
            "type":"Retail Goods"
        }
    ],
    "sg:phone":"+44 1422 844600",
    "sg:postcode":"HX7 6AA",
    "sg:province":"West Yorkshire",
    "sg:tags":[
        "collectors'",
        "item"
    ],
    "wof:name":"Books & Collectors Centre",
    "wof:placetype":"venue"
},
  "geometry": {"coordinates":[-2.016089,53.741474],"type":"Point"}
}