{
  "type": "Feature",
  "properties": {
    "addr:full":"Cadley Road, Collingbourne Ducis Marlborough Berkshire SN8 3EB",
    "addr:postcode":"sn8 3eb",
    "addr:street":"Cadley Road",
    "iso:country":"GB",
    "sg:address":"Cadley Road, Collingbourne Ducis",
    "sg:city":"Marlborough",
    "sg:classifiers":[
        {
            "category":"Bars & Pubs",
            "type":"Food & Drink"
        },
        {
            "category":"Travel",
            "subcategory":"Hotels & Motels",
            "type":"Entertainment"
        }
    ],
    "sg:phone":"+44 1264 850304",
    "sg:postcode":"SN8 3EB",
    "sg:province":"Berkshire",
    "sg:tags":[
        "pubs",
        "inn"
    ],
    "wof:name":"THE SHEARS INN & COUNTRY HOTEL",
    "wof:placetype":"venue"
},
  "geometry": {"coordinates":[-1.6521749496,51.2836990356],"type":"Point"}
}