{
  "type": "Feature",
  "properties": {
    "iso:country":"GB",
    "sg:address":"181 Winston Rise, Four Marks",
    "sg:city":"Alton",
    "sg:classifiers":[
        {
            "category":"Health Services",
            "subcategory":"Nursing And Care Facility",
            "type":"Services"
        },
        {
            "category":"Professional",
            "subcategory":"Computer Services",
            "type":"Services"
        }
    ],
    "sg:phone":"+44 1420 564463",
    "sg:postcode":"GU34 5HP",
    "sg:province":"Hampshire",
    "sg:tags":[
        "information",
        "agency"
    ],
    "wof:name":"PATIENT SUPPORT CENTRE LTD",
    "wof:placetype":"venue"
},
  "geometry": {"coordinates":[-1.052089,51.11021],"type":"Point"}
}