{
  "type": "Feature",
  "properties": {
    "addr:full":"1 Thistle Crt Edinburgh City of Edinburgh EH2 1DD",
    "addr:housenumber":"1",
    "addr:postcode":"eh2 1dd",
    "addr:street":"Thistle Crt Edinburgh",
    "iso:country":"GB",
    "sg:address":"1 Thistle Crt",
    "sg:city":"Edinburgh",
    "sg:classifiers":[
        {
            "category":"Banks & Credit Unions",
            "subcategory":"Financial Services",
            "type":"Services"
        }
    ],
    "sg:postcode":"EH2 1DD",
    "sg:province":"City of Edinburgh",
    "sg:tags":[
        "adviser"
    ],
    "wof:name":"M D H Hughes Ltd.",
    "wof:placetype":"venue"
},
  "geometry": {"coordinates":[-3.195119,55.954681],"type":"Point"}
}