{
  "type": "Feature",
  "properties": {
    "addr:full":"Merrylaws East Linton East Lothian EH40 3DX",
    "addr:postcode":"eh40 3dx",
    "iso:country":"GB",
    "sg:address":"Merrylaws",
    "sg:city":"East Linton",
    "sg:classifiers":[
        {
            "category":"Utilities",
            "subcategory":"Natural Gas",
            "type":"Services"
        }
    ],
    "sg:phone":"+44 1620 870216",
    "sg:postcode":"EH40 3DX",
    "sg:province":"East Lothian",
    "sg:tags":[
        "blacksmith"
    ],
    "wof:name":"Alec A Anderson",
    "wof:placetype":"venue"
},
  "geometry": {"coordinates":[-2.655973,55.986298],"type":"Point"}
}