{
  "type": "Feature",
  "properties": {
    "iso:country":"GB",
    "sg:address":"Navestock Hall, Navestock",
    "sg:city":"Romford",
    "sg:classifiers":[
        {
            "category":"Communications",
            "subcategory":"Newspaper",
            "type":"Services"
        }
    ],
    "sg:phone":"+44 1277 366134",
    "sg:postcode":"RM4 1HA",
    "sg:province":"Essex",
    "sg:tags":[
        "magazine"
    ],
    "wof:name":"Homeview Publications Ltd.",
    "wof:placetype":"venue"
},
  "geometry": {"coordinates":[0.219708,51.652874],"type":"Point"}
}