{
  "type": "Feature",
  "properties": {
    "iso:country":"GB",
    "sg:address":"20 The Detillens Lane, Limpfield",
    "sg:city":"Oxted",
    "sg:classifiers":[
        {
            "category":"Utilities",
            "subcategory":"Telephone",
            "type":"Services"
        }
    ],
    "sg:phone":"+44 1883 723725",
    "sg:postcode":"RH8 0DJ",
    "sg:province":"Surrey",
    "sg:tags":[
        "telecommunication"
    ],
    "wof:name":"Peaceline Communications",
    "wof:placetype":"venue"
},
  "geometry": {"coordinates":[0.0090100002,51.2578430176],"type":"Point"}
}