{
  "type": "Feature",
  "properties": {
    "addr:full":"Barkby Av Prestatyn Denbighshire LL19 7LA",
    "addr:postcode":"ll19 7la",
    "addr:street":"Barkby Av Prestatyn",
    "iso:country":"GB",
    "sg:address":"Barkby Av",
    "sg:city":"Prestatyn",
    "sg:classifiers":[
        {
            "category":"Recreation",
            "subcategory":"Campground",
            "type":"Entertainment"
        }
    ],
    "sg:phone":"+44 1745 855681",
    "sg:postcode":"LL19 7LA",
    "sg:province":"Denbighshire",
    "sg:tags":[
        "holiday",
        "centre",
        "camp"
    ],
    "wof:name":"BLMS Ltd",
    "wof:placetype":"venue"
},
  "geometry": {"coordinates":[-3.4006710052,53.3431549072],"type":"Point"}
}