{
  "type": "Feature",
  "properties": {
    "iso:country":"GB",
    "sg:address":"58 Kenilworth Drive, Oadby Industrial",
    "sg:city":"Leicester",
    "sg:classifiers":[
        {
            "category":"Professional",
            "subcategory":"Printing & Photocopies",
            "type":"Services"
        }
    ],
    "sg:postcode":"LE2 5LG",
    "sg:province":"Leicestershire",
    "sg:tags":[
        "duplicating",
        "copying"
    ],
    "wof:name":"Transcopy (Southern) Ltd.",
    "wof:placetype":"venue"
},
  "geometry": {"coordinates":[-1.0907930136,52.5977401733],"type":"Point"}
}