{
  "type": "Feature",
  "properties": {
    "addr:full":"10 East Murrayfield, Bannockburn Stirling Falkirk FK7 8HS",
    "addr:housenumber":"10",
    "addr:postcode":"fk7 8hs",
    "addr:street":"East",
    "iso:country":"GB",
    "sg:address":"10 East Murrayfield, Bannockburn",
    "sg:city":"Stirling",
    "sg:classifiers":[
        {
            "category":"Professional",
            "subcategory":"Engineering",
            "type":"Services"
        }
    ],
    "sg:phone":"+44 1786 812678",
    "sg:postcode":"FK7 8HS",
    "sg:province":"Falkirk",
    "sg:tags":[
        "civil",
        "engineer"
    ],
    "wof:name":"P J Griffin & Sons Ltd.",
    "wof:placetype":"venue"
},
  "geometry": {"coordinates":[-3.9051349163,56.0805778503],"type":"Point"}
}