{
  "type": "Feature",
  "properties": {
    "addr:full":"Southmead Industrial Park Didcot Oxfordshire OX11 7PH",
    "addr:postcode":"ox11 7ph",
    "iso:country":"GB",
    "sg:address":"Southmead Industrial Park",
    "sg:city":"Didcot",
    "sg:classifiers":[
        {
            "category":"Professional",
            "subcategory":"Business Services",
            "type":"Services"
        }
    ],
    "sg:phone":"+44 1235 510904",
    "sg:postcode":"OX11 7PH",
    "sg:province":"Oxfordshire",
    "sg:tags":[
        "accomodation"
    ],
    "wof:name":"Didcot Enterprise Centre",
    "wof:placetype":"venue"
},
  "geometry": {"coordinates":[-1.232115,51.602383],"type":"Point"}
}