{
  "type": "Feature",
  "properties": {
    "addr:full":"Unit 9, Seaton Delaval Trading Estate, New Hartley Whitley Bay Northumberland NE25 0SG",
    "addr:housenumber":"unit 9",
    "addr:postcode":"ne25 0sg",
    "addr:street":"Trading",
    "iso:country":"GB",
    "sg:address":"Unit 9, Seaton Delaval Trading Estate, New Hartley",
    "sg:city":"Whitley Bay",
    "sg:classifiers":[
        {
            "category":"Building & Trades",
            "subcategory":"Construction",
            "type":"Services"
        }
    ],
    "sg:phone":"+44 191 237 5017",
    "sg:postcode":"NE25 0SG",
    "sg:province":"Northumberland",
    "sg:tags":[
        "builder"
    ],
    "wof:name":"George Pearson & Son",
    "wof:placetype":"venue"
},
  "geometry": {"coordinates":[-1.51902,55.085609],"type":"Point"}
}