{
  "type": "Feature",
  "properties": {
    "iso:country":"GB",
    "sg:address":"14 Oaklea Gdns, Bramley, Tadley",
    "sg:city":"Basingstoke",
    "sg:classifiers":[
        {
            "category":"Conference Center",
            "type":"Public Place"
        }
    ],
    "sg:postcode":"RG26 5QY",
    "sg:province":"Berkshire",
    "wof:name":"Nigel March Production Services",
    "wof:placetype":"venue"
},
  "geometry": {"coordinates":[-1.044198,51.323479],"type":"Point"}
}