{
  "type": "Feature",
  "properties": {
    "addr:full":"163 Newgate Lane Mansfield Nottinghamshire NG18 2QD",
    "addr:housenumber":"163",
    "addr:postcode":"ng18 2qd",
    "addr:street":"Newgate Lane",
    "iso:country":"GB",
    "sg:address":"163 Newgate Lane",
    "sg:city":"Mansfield",
    "sg:classifiers":[
        {
            "category":"Personal",
            "subcategory":"Beauty Salon",
            "type":"Services"
        }
    ],
    "sg:phone":"+44 1623 635534",
    "sg:postcode":"NG18 2QD",
    "sg:province":"Nottinghamshire",
    "wof:name":"Compliments Beauty Salon",
    "wof:placetype":"venue"
},
  "geometry": {"coordinates":[-1.182594,53.144173],"type":"Point"}
}