{
  "type": "Feature",
  "properties": {
    "iso:country":"GB",
    "sg:address":"Safeway Centre, Caernarvon Road",
    "sg:city":"Cheltenham",
    "sg:classifiers":[
        {
            "category":"Education",
            "subcategory":"Library",
            "type":"Public Place"
        },
        {
            "category":"Government",
            "subcategory":"Office",
            "type":"Public Place"
        }
    ],
    "sg:phone":"+44 1242 863010",
    "sg:postcode":"GL51 3BW",
    "sg:province":"Gloucestershire",
    "sg:tags":[
        "book",
        "local"
    ],
    "wof:name":"Up Hatherley Library",
    "wof:placetype":"venue"
},
  "geometry": {"coordinates":[-2.1181,51.886871],"type":"Point"}
}