{
  "type": "Feature",
  "properties": {
    "addr:full":"The Mill, Mill Street Aberystwyth Ceredigion SY23 1JB",
    "addr:postcode":"sy23 1jb",
    "addr:street":"Mill Street",
    "iso:country":"GB",
    "sg:address":"The Mill, Mill Street",
    "sg:city":"Aberystwyth",
    "sg:classifiers":[
        {
            "category":"Professional",
            "subcategory":"Computer Services",
            "type":"Services"
        }
    ],
    "sg:phone":"+44 1970 612040",
    "sg:postcode":"SY23 1JB",
    "sg:province":"Ceredigion",
    "sg:tags":[
        "system",
        "software"
    ],
    "wof:name":"Firstearth Ltd.",
    "wof:placetype":"venue"
},
  "geometry": {"coordinates":[-4.0778689384,52.4160499573],"type":"Point"}
}