{
  "type": "Feature",
  "properties": {
    "addr:full":"63 Orchard Rd Malton North Yorkshire YO17 7BH",
    "addr:housenumber":"63",
    "addr:postcode":"yo17 7bh",
    "addr:street":"Orchard Rd",
    "iso:country":"GB",
    "sg:address":"63 Orchard Rd",
    "sg:city":"Malton",
    "sg:classifiers":[
        {
            "category":"Farming",
            "subcategory":"Farm",
            "type":"Manufacturing & Wholesale Goods"
        }
    ],
    "sg:postcode":"YO17 7BH",
    "sg:province":"North Yorkshire",
    "sg:tags":[
        "mixed",
        "crop"
    ],
    "wof:name":"Butterworth,P D,",
    "wof:placetype":"venue"
},
  "geometry": {"coordinates":[-0.8083559871,54.1358261108],"type":"Point"}
}