{
  "type": "Feature",
  "properties": {
    "addr:full":"123 Church Hill Road, Thurmaston Leicester Leicestershire LE4 8DG",
    "addr:housenumber":"123",
    "addr:postcode":"le4 8dg",
    "addr:street":"Church Hill Road",
    "iso:country":"GB",
    "sg:address":"123 Church Hill Road, Thurmaston",
    "sg:city":"Leicester",
    "sg:classifiers":[
        {
            "category":"Building & Trades",
            "subcategory":"Construction",
            "type":"Services"
        }
    ],
    "sg:phone":"+44 116 260 6440",
    "sg:postcode":"LE4 8DG",
    "sg:province":"Leicestershire",
    "sg:tags":[
        "builder"
    ],
    "wof:name":"Arbee Construction Ltd.",
    "wof:placetype":"venue"
},
  "geometry": {"coordinates":[-1.088199,52.676235],"type":"Point"}
}