{
  "type": "Feature",
  "properties": {
    "addr:full":"48a Bridge Street Evesham Gloucestershire WR11 4RY",
    "addr:housenumber":"48a",
    "addr:postcode":"wr11 4ry",
    "addr:street":"Bridge Street",
    "iso:country":"GB",
    "sg:address":"48a Bridge Street",
    "sg:city":"Evesham",
    "sg:classifiers":[
        {
            "category":"Building & Trades",
            "subcategory":"Construction",
            "type":"Services"
        }
    ],
    "sg:phone":"+44 1386 49364",
    "sg:postcode":"WR11 4RY",
    "sg:province":"Gloucestershire",
    "sg:tags":[
        "resurfacing",
        "laying",
        "floor"
    ],
    "wof:name":"R M Young & Co. Ltd.",
    "wof:placetype":"venue"
},
  "geometry": {"coordinates":[-1.945527,52.092037],"type":"Point"}
}