{
  "type": "Feature",
  "properties": {
    "iso:country":"GB",
    "sg:address":"Parsonage Barn, Compton Street, Compton",
    "sg:city":"Winchester",
    "sg:classifiers":[
        {
            "category":"Health Services",
            "subcategory":"Clinic",
            "type":"Services"
        }
    ],
    "sg:postcode":"SO21 2AS",
    "sg:province":"Hampshire",
    "sg:tags":[
        "medical"
    ],
    "wof:name":"McCue Plc",
    "wof:placetype":"venue"
},
  "geometry": {"coordinates":[-1.343804,51.021023],"type":"Point"}
}