{
  "type": "Feature",
  "properties": {
    "addr:full":"New Leys, Pickhill Thirsk North Yorkshire YO7 4JN",
    "addr:postcode":"yo7 4jn",
    "addr:street":"New Leys",
    "iso:country":"GB",
    "sg:address":"New Leys, Pickhill",
    "sg:city":"Thirsk",
    "sg:classifiers":[
        {
            "category":"Farming",
            "subcategory":"Livestock Farm",
            "type":"Manufacturing & Wholesale Goods"
        }
    ],
    "sg:postcode":"YO7 4JN",
    "sg:province":"North Yorkshire",
    "sg:tags":[
        "others"
    ],
    "wof:name":"Alan D Thornton",
    "wof:placetype":"venue"
},
  "geometry": {"coordinates":[-1.4705959558,54.2475166321],"type":"Point"}
}