{
  "type": "Feature",
  "properties": {
    "addr:full":"The Old School, Ipsden Wallingford Oxfordshire OX10 6AJ",
    "addr:postcode":"ox10 6aj",
    "iso:country":"GB",
    "sg:address":"The Old School, Ipsden",
    "sg:city":"Wallingford",
    "sg:classifiers":[
        {
            "category":"Farming",
            "subcategory":"Nursery",
            "type":"Manufacturing & Wholesale Goods"
        }
    ],
    "sg:postcode":"OX10 6AJ",
    "sg:province":"Oxfordshire",
    "sg:tags":[
        "creche"
    ],
    "wof:name":"Freeman Nicola",
    "wof:placetype":"venue"
},
  "geometry": {"coordinates":[-1.083779,51.563278],"type":"Point"}
}