{
  "type": "Feature",
  "properties": {
    "addr:full":"Brunswick House, Brunswick Street Nelson Lancashire BB9 0HQ",
    "addr:postcode":"bb9 0hq",
    "addr:street":"Brunswick Street",
    "iso:country":"GB",
    "sg:address":"Brunswick House, Brunswick Street",
    "sg:city":"Nelson",
    "sg:classifiers":[
        {
            "category":"Professional",
            "subcategory":"Art Services",
            "type":"Services"
        },
        {
            "category":"Professional",
            "subcategory":"Computer Services",
            "type":"Services"
        }
    ],
    "sg:phone":"+44 1282 440000",
    "sg:postcode":"BB9 0HQ",
    "sg:province":"Lancashire",
    "sg:tags":[
        "graphic",
        "system",
        "designer",
        "software"
    ],
    "wof:name":"Hartley & Hartley Ltd.",
    "wof:placetype":"venue"
},
  "geometry": {"coordinates":[-2.210584,53.833187],"type":"Point"}
}