{
  "type": "Feature",
  "properties": {
    "addr:full":"West Road Brechin Aberdeenshire DD9 6RJ",
    "addr:postcode":"dd9 6rj",
    "addr:street":"West Road",
    "iso:country":"GB",
    "sg:address":"West Road",
    "sg:city":"Brechin",
    "sg:classifiers":[
        {
            "category":"Autos & Motor Vehicles",
            "subcategory":"Auto Supplies",
            "type":"Retail Goods"
        },
        {
            "category":"Train Station",
            "subcategory":"Rail",
            "type":"Transportation"
        }
    ],
    "sg:phone":"+44 1356 624600",
    "sg:postcode":"DD9 6RJ",
    "sg:province":"Aberdeenshire",
    "sg:tags":[
        "caravan",
        "towing",
        "eqpt",
        "trailer"
    ],
    "wof:name":"Duncan McIntosh Engineering",
    "wof:placetype":"venue"
},
  "geometry": {"coordinates":[-2.6644189358,56.7314758301],"type":"Point"}
}