{
  "type": "Feature",
  "properties": {
    "addr:full":"24a Oxford Street Harrogate North Yorkshire HG1 1PU",
    "addr:housenumber":"24a",
    "addr:postcode":"hg1 1pu",
    "addr:street":"Oxford Street",
    "iso:country":"GB",
    "sg:address":"24a Oxford Street",
    "sg:city":"Harrogate",
    "sg:classifiers":[
        {
            "category":"Shopping",
            "subcategory":"Thrift Store",
            "type":"Retail Goods"
        }
    ],
    "sg:phone":"+44 1423 526449",
    "sg:postcode":"HG1 1PU",
    "sg:province":"North Yorkshire",
    "sg:tags":[
        "shop",
        "charity"
    ],
    "wof:name":"Imperial Cancer Research Fund",
    "wof:placetype":"venue"
},
  "geometry": {"coordinates":[-1.54106,53.994034],"type":"Point"}
}