{
  "type": "Feature",
  "properties": {
    "addr:full":"79 Court Road, Kingswood Bristol City of Bristol BS15 9QN",
    "addr:housenumber":"79",
    "addr:postcode":"bs15 9qn",
    "addr:street":"Court Road",
    "iso:country":"GB",
    "sg:address":"79 Court Road, Kingswood",
    "sg:city":"Bristol",
    "sg:classifiers":[
        {
            "category":"Retail",
            "subcategory":"Auto Repair",
            "type":"Services"
        }
    ],
    "sg:phone":"+44 117 960 9512",
    "sg:postcode":"BS15 9QN",
    "sg:province":"City of Bristol",
    "sg:tags":[
        "modification",
        "garage"
    ],
    "wof:name":"M A Hughes",
    "wof:placetype":"venue"
},
  "geometry": {"coordinates":[-2.5914289951,51.453666687],"type":"Point"}
}