{
  "type": "Feature",
  "properties": {
    "addr:full":"Highcroft, Brook House Lane, Lower Whitley Warrington Cheshire WA4 4EP",
    "addr:postcode":"wa4 4ep",
    "addr:street":"Lane",
    "iso:country":"GB",
    "sg:address":"Highcroft, Brook House Lane, Lower Whitley",
    "sg:city":"Warrington",
    "sg:classifiers":[
        {
            "category":"Organizations",
            "subcategory":"Community Association",
            "type":"Services"
        }
    ],
    "sg:phone":"+44 1925 730053",
    "sg:postcode":"WA4 4EP",
    "sg:province":"Cheshire",
    "sg:tags":[
        "relation",
        "public"
    ],
    "wof:name":"Westgate International Marketing",
    "wof:placetype":"venue"
},
  "geometry": {"coordinates":[-2.581939,53.309742],"type":"Point"}
}