{
  "type": "Feature",
  "properties": {
    "iso:country":"GB",
    "sg:address":"81 Eileen Gardens, Kingshurst",
    "sg:city":"Birmingham",
    "sg:classifiers":[
        {
            "category":"Building & Trades",
            "subcategory":"Construction",
            "type":"Services"
        }
    ],
    "sg:postcode":"B37 6NJ",
    "sg:province":"West Midlands",
    "sg:tags":[
        "roofing"
    ],
    "wof:name":"G Bates Roofing",
    "wof:placetype":"venue"
},
  "geometry": {"coordinates":[-1.751335,52.48761],"type":"Point"}
}