{
  "type": "Feature",
  "properties": {
    "addr:full":"10 Bridge Clo Brentwood Essex CM13 2AH",
    "addr:housenumber":"10",
    "addr:postcode":"cm13 2ah",
    "addr:street":"Bridge Clo",
    "iso:country":"GB",
    "sg:address":"10 Bridge Clo",
    "sg:city":"Brentwood",
    "sg:classifiers":[
        {
            "category":"Education",
            "subcategory":"Music School",
            "type":"Public Place"
        }
    ],
    "sg:phone":"+44 1277 200469",
    "sg:postcode":"CM13 2AH",
    "sg:province":"Essex",
    "sg:tags":[
        "teacher"
    ],
    "wof:name":"Jill Bone Music Unlimited",
    "wof:placetype":"venue"
},
  "geometry": {"coordinates":[0.317308,51.613708],"type":"Point"}
}