{
  "type": "Feature",
  "properties": {
    "addr:full":"Cobden Road Worthing West Sussex BN11 4BD",
    "addr:postcode":"bn11 4bd",
    "addr:street":"Cobden Road",
    "iso:country":"GB",
    "sg:address":"Cobden Road",
    "sg:city":"Worthing",
    "sg:classifiers":[
        {
            "category":"Education",
            "subcategory":"School",
            "type":"Public Place"
        }
    ],
    "sg:phone":"+44 1903 234115",
    "sg:postcode":"BN11 4BD",
    "sg:province":"West Sussex",
    "sg:tags":[
        "local",
        "authority"
    ],
    "wof:name":"St Mary's Catholic Primary School",
    "wof:placetype":"venue"
},
  "geometry": {"coordinates":[-0.379162,50.814964],"type":"Point"}
}