{
  "type": "Feature",
  "properties": {
    "addr:full":"4 Coleridge Street Halifax West Yorkshire HX1 2JF",
    "addr:housenumber":"4",
    "addr:postcode":"hx1 2jf",
    "addr:street":"Coleridge Street",
    "iso:country":"GB",
    "sg:address":"4 Coleridge Street",
    "sg:city":"Halifax",
    "sg:classifiers":[
        {
            "category":"Travel",
            "subcategory":"Travel Agent",
            "type":"Entertainment"
        }
    ],
    "sg:phone":"+44 1422 320220",
    "sg:postcode":"HX1 2JF",
    "sg:province":"West Yorkshire",
    "sg:tags":[
        "agency",
        "activity"
    ],
    "sg:website":"http://www.fairway-travel.co.uk",
    "wof:name":"Fairway International Travel Ltd.",
    "wof:placetype":"venue"
},
  "geometry": {"coordinates":[-1.860228,53.719952],"type":"Point"}
}