{
  "type": "Feature",
  "properties": {
    "addr:full":"95 Sunnydale Shildon Durham DL4 2ET",
    "addr:housenumber":"95",
    "addr:postcode":"dl4 2et",
    "addr:street":"Sunnydale",
    "iso:country":"GB",
    "sg:address":"95 Sunnydale",
    "sg:city":"Shildon",
    "sg:classifiers":[
        {
            "category":"Personal",
            "subcategory":"Tanning Parlor",
            "type":"Services"
        }
    ],
    "sg:phone":"+44 1388 775256",
    "sg:postcode":"DL4 2ET",
    "sg:province":"Durham",
    "sg:tags":[
        "sunbeds"
    ],
    "wof:name":"Mediterranean Sunbeds",
    "wof:placetype":"venue"
},
  "geometry": {"coordinates":[-1.6391019821,54.6352005005],"type":"Point"}
}