{
  "type": "Feature",
  "properties": {
    "addr:full":"Hopley Farm Hopton, Hodnet Market Drayton Shropshire TF9 3LE",
    "addr:housenumber":"hopley;hopton hodnet",
    "addr:postcode":"tf9 3le",
    "iso:country":"GB",
    "sg:address":"Hopley Farm Hopton, Hodnet",
    "sg:city":"Market Drayton",
    "sg:classifiers":[
        {
            "category":"Farming",
            "subcategory":"Crops",
            "type":"Manufacturing & Wholesale Goods"
        },
        {
            "category":"Farming",
            "subcategory":"Farm",
            "type":"Manufacturing & Wholesale Goods"
        }
    ],
    "sg:phone":"+44 1630 685309",
    "sg:postcode":"TF9 3LE",
    "sg:province":"Shropshire",
    "sg:tags":[
        "mixed",
        "arable"
    ],
    "wof:name":"G E  Ryley",
    "wof:placetype":"venue"
},
  "geometry": {"coordinates":[-2.486172,52.904091],"type":"Point"}
}