{
  "type": "Feature",
  "properties": {
    "addr:full":"3 Friday Street Minehead Somerset TA24 5UB",
    "addr:housenumber":"3",
    "addr:postcode":"ta24 5ub",
    "addr:street":"Friday Street",
    "iso:country":"GB",
    "sg:address":"3 Friday Street",
    "sg:city":"Minehead",
    "sg:classifiers":[
        {
            "category":"Real Estate",
            "subcategory":"Real Estate Agent",
            "type":"Services"
        }
    ],
    "sg:phone":"+44 1643 706927",
    "sg:postcode":"TA24 5UB",
    "sg:province":"Somerset",
    "wof:name":"Langdons Estate Agents",
    "wof:placetype":"venue"
},
  "geometry": {"coordinates":[-3.4786999226,51.2054710388],"type":"Point"}
}