{
  "type": "Feature",
  "properties": {
    "addr:full":"24 Argyle Street St Andrews Fife KY16 9BU",
    "addr:housenumber":"24",
    "addr:postcode":"ky16 9bu",
    "addr:street":"Argyle Street",
    "iso:country":"GB",
    "sg:address":"24 Argyle Street",
    "sg:city":"St Andrews",
    "sg:classifiers":[
        {
            "category":"Shopping",
            "subcategory":"Music",
            "type":"Retail Goods"
        }
    ],
    "sg:phone":"+44 1334 472564",
    "sg:postcode":"KY16 9BU",
    "sg:province":"Fife",
    "sg:tags":[
        "shop"
    ],
    "wof:name":"Eclipse Music",
    "wof:placetype":"venue"
},
  "geometry": {"coordinates":[-2.8026609421,56.3384857178],"type":"Point"}
}