{
  "type": "Feature",
  "properties": {
    "addr:full":"Netherhall Rd Leicester Leicestershire LE5 1DT",
    "addr:postcode":"le5 1dt",
    "addr:street":"Netherhall Rd",
    "iso:country":"GB",
    "sg:address":"Netherhall Rd",
    "sg:city":"Leicester",
    "sg:classifiers":[
        {
            "category":"Education",
            "subcategory":"School",
            "type":"Public Place"
        }
    ],
    "sg:phone":"+44 116 241 7258",
    "sg:postcode":"LE5 1DT",
    "sg:province":"Leicestershire",
    "sg:tags":[
        "local",
        "authority"
    ],
    "wof:name":"Netherhall School",
    "wof:placetype":"venue"
},
  "geometry": {"coordinates":[-1.0675840378,52.647895813],"type":"Point"}
}