{
  "type": "Feature",
  "properties": {
    "addr:full":"9e Tadema Rd West Brompton Greater London SW10 0NU",
    "addr:postcode":"sw10 0nu",
    "addr:street":"9E Tadema Rd",
    "iso:country":"GB",
    "sg:address":"9e Tadema Rd",
    "sg:city":"West Brompton",
    "sg:classifiers":[
        {
            "category":"Utilities",
            "subcategory":"Refuse",
            "type":"Services"
        }
    ],
    "sg:phone":"+44 20 7351 0182",
    "sg:postcode":"SW10 0NU",
    "sg:province":"Greater London",
    "sg:tags":[
        "skip",
        "hire"
    ],
    "wof:name":"Worlds End Waste",
    "wof:placetype":"venue"
},
  "geometry": {"coordinates":[-0.181427,51.47863],"type":"Point"}
}