{
  "type": "Feature",
  "properties": {
    "addr:full":"13 Malmesbury Business Park, Beuttell Way Malmesbury Wiltshire SN16 9JU",
    "addr:housenumber":"13",
    "addr:postcode":"sn16 9ju",
    "addr:street":"Malmesbury Business Park Beuttell Way",
    "iso:country":"GB",
    "sg:address":"13 Malmesbury Business Park, Beuttell Way",
    "sg:city":"Malmesbury",
    "sg:classifiers":[
        {
            "category":"Building & Trades",
            "subcategory":"Plumbing",
            "type":"Services"
        },
        {
            "category":"Wholesale",
            "subcategory":"Electrical",
            "type":"Manufacturing & Wholesale Goods"
        }
    ],
    "sg:phone":"+44 1666 822200",
    "sg:postcode":"SN16 9JU",
    "sg:province":"Wiltshire",
    "sg:tags":[
        "equipment",
        "plumber",
        "refrigeration"
    ],
    "wof:name":"CASPIAN CLIMATIC LTD",
    "wof:placetype":"venue"
},
  "geometry": {"coordinates":[-2.0974190235,51.582244873],"type":"Point"}
}