{
  "type": "Feature",
  "properties": {
    "iso:country":"GB",
    "sg:address":"Manor Road",
    "sg:city":"Hayling Island",
    "sg:classifiers":[
        {
            "category":"Place Of Worship",
            "type":"Public Place"
        },
        {
            "category":"Organizations",
            "subcategory":"Non-profit Organization",
            "type":"Services"
        }
    ],
    "sg:phone":"+44 23 9246 3854",
    "sg:postcode":"PO11 0QU",
    "sg:province":"Hampshire",
    "sg:tags":[
        "charitable",
        "organisation",
        "charity"
    ],
    "wof:name":"St Patrick'S Roman Catholic Church",
    "wof:placetype":"venue"
},
  "geometry": {"coordinates":[-0.985454,50.796612],"type":"Point"}
}