{
  "type": "Feature",
  "properties": {
    "addr:full":"74 High Street Sittingbourne Kent ME10 4PB",
    "addr:housenumber":"74",
    "addr:postcode":"me10 4pb",
    "addr:street":"High Street",
    "iso:country":"GB",
    "sg:address":"74 High Street",
    "sg:city":"Sittingbourne",
    "sg:classifiers":[
        {
            "category":"Shopping",
            "subcategory":"Shoes",
            "type":"Retail Goods"
        }
    ],
    "sg:phone":"+44 1795 474411",
    "sg:postcode":"ME10 4PB",
    "sg:province":"Kent",
    "wof:name":"Shoe Mendas",
    "wof:placetype":"venue"
},
  "geometry": {"coordinates":[0.736109972,51.3401374817],"type":"Point"}
}