{
  "type": "Feature",
  "properties": {
    "iso:country":"GB",
    "sg:address":"The Limes, Southminster Road",
    "sg:city":"Burnham-on-crouch",
    "sg:classifiers":[
        {
            "category":"Food & Beverages",
            "subcategory":"Farmers Market",
            "type":"Retail Goods"
        }
    ],
    "sg:phone":"+44 1621 785865",
    "sg:postcode":"CM0 8QB",
    "sg:province":"Essex",
    "sg:tags":[
        "farm",
        "shop",
        "pyo"
    ],
    "wof:name":"J & A Sadler",
    "wof:placetype":"venue"
},
  "geometry": {"coordinates":[0.813176,51.646873],"type":"Point"}
}