{
  "type": "Feature",
  "properties": {
    "addr:full":"4 Orchard Drive, Mayland Chelmsford Essex CM3 6EP",
    "addr:housenumber":"4",
    "addr:postcode":"cm3 6ep",
    "addr:street":"Orchard Drive Mayland",
    "iso:country":"GB",
    "sg:address":"4 Orchard Drive, Mayland",
    "sg:city":"Chelmsford",
    "sg:classifiers":[
        {
            "category":"Retail",
            "subcategory":"Driving School",
            "type":"Services"
        }
    ],
    "sg:phone":"+44 1621 741450",
    "sg:postcode":"CM3 6EP",
    "sg:province":"Essex",
    "wof:name":"Orchard School of Motoring",
    "wof:placetype":"venue"
},
  "geometry": {"coordinates":[0.765163,51.686142],"type":"Point"}
}