{
  "type": "Feature",
  "properties": {
    "iso:country":"GB",
    "sg:address":"16 Hillside Close",
    "sg:city":"Chalfont St Giles",
    "sg:classifiers":[
        {
            "category":"Building & Trades",
            "subcategory":"Construction",
            "type":"Services"
        }
    ],
    "sg:phone":"+44 1494 525925",
    "sg:postcode":"HP8 4JN",
    "sg:province":"Buckinghamshire",
    "sg:tags":[
        "joinery",
        "joiner",
        "carpenter",
        "carpentry"
    ],
    "wof:name":"Mark C Elbourn",
    "wof:placetype":"venue"
},
  "geometry": {"coordinates":[-0.574713,51.629906],"type":"Point"}
}