{
  "type": "Feature",
  "properties": {
    "addr:full":"656 Dumbarton Road, Partick Glasgow Glasgow City G11 6RA",
    "addr:housenumber":"656",
    "addr:postcode":"g11 6ra",
    "addr:street":"Dumbarton Road",
    "iso:country":"GB",
    "sg:address":"656 Dumbarton Road, Partick",
    "sg:city":"Glasgow",
    "sg:classifiers":[
        {
            "category":"Professional",
            "subcategory":"Detective & Security Services",
            "type":"Services"
        }
    ],
    "sg:phone":"+44 141 334 9216",
    "sg:postcode":"G11 6RA",
    "sg:province":"Glasgow City",
    "sg:tags":[
        "locksmith"
    ],
    "wof:name":"Kelvin Lock & Safe Ltd.",
    "wof:placetype":"venue"
},
  "geometry": {"coordinates":[-4.3189787865,55.8707695007],"type":"Point"}
}