{
  "type": "Feature",
  "properties": {
    "iso:country":"GB",
    "sg:address":"253 Kingsacre Road, Rutherglen",
    "sg:city":"Glasgow",
    "sg:classifiers":[
        {
            "category":"Communications",
            "type":"Services"
        }
    ],
    "sg:phone":"+44 141 569 3968",
    "sg:postcode":"G73 2EN",
    "sg:province":"Glasgow City",
    "sg:tags":[
        "broadcasting"
    ],
    "wof:name":"Soundsmove Ltd",
    "wof:placetype":"venue"
},
  "geometry": {"coordinates":[-4.232574,55.821964],"type":"Point"}
}