{
  "type": "Feature",
  "properties": {
    "iso:country":"GB",
    "sg:address":"1-2 The Deacon Estate, Cabinet Way",
    "sg:city":"London",
    "sg:classifiers":[
        {
            "category":"Shopping",
            "subcategory":"Stationery & Office Supplies",
            "type":"Retail Goods"
        }
    ],
    "sg:phone":"+44 20 8523 2051",
    "sg:postcode":"E4 8QF",
    "sg:province":"Greater London",
    "sg:tags":[
        "printers'"
    ],
    "wof:name":"David Richards (Printers & Distributors) Ltd.",
    "wof:placetype":"venue"
},
  "geometry": {"coordinates":[-0.02936,51.609058],"type":"Point"}
}