{
  "type": "Feature",
  "properties": {
    "iso:country":"GB",
    "sg:address":"21 Montague Street, Rothesay",
    "sg:city":"Rothesay",
    "sg:classifiers":[
        {
            "category":"Shopping",
            "subcategory":"Thrift Store",
            "type":"Retail Goods"
        }
    ],
    "sg:phone":"+44 1700 502135",
    "sg:postcode":"PA20 9DA",
    "sg:province":"Argyll and Bute",
    "sg:tags":[
        "shop",
        "charity"
    ],
    "sg:website":"http://www.oxfam.org.uk",
    "wof:name":"Oxfam",
    "wof:placetype":"venue"
},
  "geometry": {"coordinates":[-5.040469,55.826584],"type":"Point"}
}