{
  "type": "Feature",
  "properties": {
    "iso:country":"GB",
    "sg:address":"102 High Street",
    "sg:city":"Street",
    "sg:classifiers":[
        {
            "category":"Food & Beverages",
            "subcategory":"Meat & Fish",
            "type":"Retail Goods"
        }
    ],
    "sg:phone":"+44 1458 442453",
    "sg:postcode":"BA16 0EW",
    "sg:province":"Somerset",
    "sg:tags":[
        "butcher"
    ],
    "wof:name":"F Griffiths",
    "wof:placetype":"venue"
},
  "geometry": {"coordinates":[-2.741311,51.12619],"type":"Point"}
}