{
  "type": "Feature",
  "properties": {
    "addr:full":"157 Blackfriars Rd Southwark Greater London SE1 8EU",
    "addr:housenumber":"157",
    "addr:postcode":"se1 8eu",
    "addr:street":"Blackfriars Rd",
    "iso:country":"GB",
    "sg:address":"157 Blackfriars Rd",
    "sg:city":"Southwark",
    "sg:classifiers":[
        {
            "category":"Professional",
            "subcategory":"Employment Agencies",
            "type":"Services"
        }
    ],
    "sg:phone":"+44 20 7922 1161",
    "sg:postcode":"SE1 8EU",
    "sg:province":"Greater London",
    "sg:tags":[
        "consultant"
    ],
    "wof:name":"Masterlock Recruitment Ltd",
    "wof:placetype":"venue"
},
  "geometry": {"coordinates":[-0.1046060026,51.5018997192],"type":"Point"}
}