{
  "type": "Feature",
  "properties": {
    "addr:full":"The Verne Portland Dorset DT5 1EQ",
    "addr:postcode":"dt5 1eq",
    "iso:country":"GB",
    "sg:address":"The Verne",
    "sg:city":"Portland",
    "sg:classifiers":[
        {
            "category":"Government",
            "subcategory":"Prison",
            "type":"Public Place"
        }
    ],
    "sg:phone":"+44 1305 820124",
    "sg:postcode":"DT5 1EQ",
    "sg:province":"Dorset",
    "wof:name":"The Verne Prison",
    "wof:placetype":"venue"
},
  "geometry": {"coordinates":[-2.4359691143,50.5469017029],"type":"Point"}
}