{
  "type": "Feature",
  "properties": {
    "iso:country":"GB",
    "sg:address":"54 High Street",
    "sg:city":"Carnoustie",
    "sg:classifiers":[
        {
            "category":"Shopping",
            "subcategory":"News",
            "type":"Retail Goods"
        }
    ],
    "sg:phone":"+44 1241 853292",
    "sg:postcode":"DD7 6AH",
    "sg:province":"Angus",
    "sg:tags":[
        "newsagent"
    ],
    "wof:name":"B & D Keiller",
    "wof:placetype":"venue"
},
  "geometry": {"coordinates":[-2.709949,56.501419],"type":"Point"}
}