{
  "type": "Feature",
  "properties": {
    "addr:full":"Unit 10 Atlas Industrial Estate, Foundry Street Glasgow East Dunbartonshire G21 4PR",
    "addr:housenumber":"unit 10;estate",
    "addr:postcode":"g21 4pr",
    "addr:street":"Atlas Industrial;Foundry Street",
    "iso:country":"GB",
    "sg:address":"Unit 10 Atlas Industrial Estate, Foundry Street",
    "sg:city":"Glasgow",
    "sg:classifiers":[
        {
            "category":"Education",
            "subcategory":"Special Training",
            "type":"Public Place"
        }
    ],
    "sg:phone":"+44 141 558 6945",
    "sg:postcode":"G21 4PR",
    "sg:province":"East Dunbartonshire",
    "sg:tags":[
        "product",
        "centre"
    ],
    "wof:name":"Heatwise Ltd.",
    "wof:placetype":"venue"
},
  "geometry": {"coordinates":[-4.23282,55.880138],"type":"Point"}
}