{
  "type": "Feature",
  "properties": {
    "iso:country":"GB",
    "sg:address":"15 Woodside Av",
    "sg:city":"Stoke On Trent",
    "sg:classifiers":[
        {
            "category":"Building & Trades",
            "subcategory":"Construction",
            "type":"Services"
        }
    ],
    "sg:phone":"+44 1782 504983",
    "sg:postcode":"ST6 8RX",
    "sg:province":"Staffordshire",
    "sg:tags":[
        "builder"
    ],
    "wof:name":"Central Building & Roofing Services",
    "wof:placetype":"venue"
},
  "geometry": {"coordinates":[-2.1402080059,53.0725898743],"type":"Point"}
}