{
  "type": "Feature",
  "properties": {
    "iso:country":"GB",
    "sg:address":"19 Madoc Street",
    "sg:city":"Llandudno",
    "sg:classifiers":[
        {
            "category":"Shopping",
            "subcategory":"Used Merchandise",
            "type":"Retail Goods"
        }
    ],
    "sg:phone":"+44 1492 878486",
    "sg:postcode":"LL30 2TL",
    "sg:province":"Conwy",
    "sg:tags":[
        "shop",
        "second-hand"
    ],
    "wof:name":"Brookes Furniture",
    "wof:placetype":"venue"
},
  "geometry": {"coordinates":[-3.8307220936,53.3231468201],"type":"Point"}
}