{
  "type": "Feature",
  "properties": {
    "addr:full":"Hayes Bridge Retail Park, Uxbridge Road Hayes Greater London UB4 0RH",
    "addr:postcode":"ub4 0rh",
    "addr:street":"Hayes Bridge Retail Park Uxbridge Road",
    "iso:country":"GB",
    "sg:address":"Hayes Bridge Retail Park, Uxbridge Road",
    "sg:city":"Hayes",
    "sg:classifiers":[
        {
            "category":"Home & Garden",
            "subcategory":"Furniture",
            "type":"Retail Goods"
        }
    ],
    "sg:phone":"+44 208756760",
    "sg:postcode":"UB4 0RH",
    "sg:province":"Greater London",
    "wof:name":"Courts Furnishers Superstore",
    "wof:placetype":"venue"
},
  "geometry": {"coordinates":[-0.39246,51.513401],"type":"Point"}
}