{
  "type": "Feature",
  "properties": {
    "iso:country":"GB",
    "sg:address":"Pingle Mill, Pingle Lane, Delph",
    "sg:city":"Oldham",
    "sg:classifiers":[
        {
            "category":"Wholesale",
            "subcategory":"Sporting Goods",
            "type":"Manufacturing & Wholesale Goods"
        },
        {
            "category":"Shopping",
            "subcategory":"Crafts & Fabrics",
            "type":"Retail Goods"
        }
    ],
    "sg:phone":"+44 1457 874651",
    "sg:postcode":"OL3 5EX",
    "sg:province":"Lancashire",
    "sg:tags":[
        "yarn",
        "supply"
    ],
    "wof:name":"R Gledhill Ltd",
    "wof:placetype":"venue"
},
  "geometry": {"coordinates":[-2.02309,53.566956],"type":"Point"}
}