{
  "type": "Feature",
  "properties": {
    "addr:full":"250 Leith Walk Edinburgh City of Edinburgh EH6 5EL",
    "addr:housenumber":"250",
    "addr:postcode":"eh6 5el",
    "addr:street":"Leith Walk",
    "iso:country":"GB",
    "sg:address":"250 Leith Walk",
    "sg:city":"Edinburgh",
    "sg:classifiers":[
        {
            "category":"Professional",
            "type":"Services"
        }
    ],
    "sg:phone":"+44 131 554 6407",
    "sg:postcode":"EH6 5EL",
    "sg:province":"City of Edinburgh",
    "sg:tags":[
        "valuer",
        "auctioneer"
    ],
    "wof:name":"Crawfords Auction Rooms",
    "wof:placetype":"venue"
},
  "geometry": {"coordinates":[-3.1755690575,55.9666061401],"type":"Point"}
}