{
  "type": "Feature",
  "properties": {
    "addr:full":"71 Green Lane Rd Leicester Leicestershire LE5 3TP",
    "addr:housenumber":"71",
    "addr:postcode":"le5 3tp",
    "addr:street":"Green Lane Rd",
    "iso:country":"GB",
    "sg:address":"71 Green Lane Rd",
    "sg:city":"Leicester",
    "sg:classifiers":[
        {
            "category":"Shopping",
            "subcategory":"Department Store",
            "type":"Retail Goods"
        },
        {
            "category":"Food & Beverages",
            "subcategory":"Groceries & Convenience Stores",
            "type":"Retail Goods"
        }
    ],
    "sg:phone":"+44 116 262 9405",
    "sg:postcode":"LE5 3TP",
    "sg:province":"Leicestershire",
    "wof:name":"Asha Stores",
    "wof:placetype":"venue"
},
  "geometry": {"coordinates":[-1.104583,52.6395],"type":"Point"}
}