{
  "type": "Feature",
  "properties": {
    "iso:country":"GB",
    "sg:address":"Barnsley Road, South Kirkby",
    "sg:city":"Pontefract",
    "sg:classifiers":[
        {
            "category":"Bars & Pubs",
            "type":"Food & Drink"
        }
    ],
    "sg:phone":"+44 1977 642776",
    "sg:postcode":"WF9 3LA",
    "sg:province":"West Yorkshire",
    "sg:tags":[
        "pubs",
        "inn"
    ],
    "wof:name":"Church House",
    "wof:placetype":"venue"
},
  "geometry": {"coordinates":[-1.308179,53.594711],"type":"Point"}
}