{
  "type": "Feature",
  "properties": {
    "addr:full":"9 Saltoun Square Fraserburgh Aberdeenshire AB43 9DA",
    "addr:housenumber":"9",
    "addr:postcode":"ab43 9da",
    "addr:street":"Saltoun Square",
    "iso:country":"GB",
    "sg:address":"9 Saltoun Square",
    "sg:city":"Fraserburgh",
    "sg:classifiers":[
        {
            "category":"Travel",
            "subcategory":"Travel Agent",
            "type":"Entertainment"
        }
    ],
    "sg:phone":"+44 1346 518955",
    "sg:postcode":"AB43 9DA",
    "sg:province":"Aberdeenshire",
    "wof:name":"Duncan's Travel",
    "wof:placetype":"venue"
},
  "geometry": {"coordinates":[-2.0069708824,57.6909675598],"type":"Point"}
}