{
  "type": "Feature",
  "properties": {
    "addr:full":"76 Cavendish Rd Balham Greater London SW12 0DF",
    "addr:housenumber":"76",
    "addr:postcode":"sw12 0df",
    "addr:street":"Cavendish Rd",
    "iso:country":"GB",
    "sg:address":"76 Cavendish Rd",
    "sg:city":"Balham",
    "sg:classifiers":[
        {
            "category":"Government",
            "subcategory":"Post Office",
            "type":"Public Place"
        }
    ],
    "sg:phone":"+44 20 8673 5345",
    "sg:postcode":"SW12 0DF",
    "sg:province":"Greater London",
    "sg:tags":[
        "messenger",
        "courier"
    ],
    "wof:name":"A.J.M Couriers",
    "wof:placetype":"venue"
},
  "geometry": {"coordinates":[-0.1429339945,51.4527511597],"type":"Point"}
}