{
  "type": "Feature",
  "properties": {
    "addr:full":"30 Burlington Road Ipswich Suffolk IP1 2HS",
    "addr:housenumber":"30",
    "addr:postcode":"ip1 2hs",
    "addr:street":"Burlington Road",
    "iso:country":"GB",
    "sg:address":"30 Burlington Road",
    "sg:city":"Ipswich",
    "sg:classifiers":[
        {
            "category":"Travel",
            "subcategory":"Hotels & Motels",
            "type":"Entertainment"
        }
    ],
    "sg:postcode":"IP1 2HS",
    "sg:province":"Suffolk",
    "sg:tags":[
        "house",
        "guest"
    ],
    "wof:name":"Burlington Lodge",
    "wof:placetype":"venue"
},
  "geometry": {"coordinates":[1.142804,52.058533],"type":"Point"}
}