{
  "type": "Feature",
  "properties": {
    "addr:full":"7 Caraway Hieghts, The Hill Poplar Greater London E14 0BG",
    "addr:housenumber":"7;hieghts",
    "addr:postcode":"e14 0bg",
    "addr:street":"Caraway;The Hill",
    "iso:country":"GB",
    "sg:address":"7 Caraway Hieghts, The Hill",
    "sg:city":"Poplar",
    "sg:classifiers":[
        {
            "category":"Professional",
            "subcategory":"Management & Consulting",
            "type":"Services"
        }
    ],
    "sg:phone":"+44 1580 715765",
    "sg:postcode":"E14 0BG",
    "sg:province":"Greater London",
    "sg:tags":[
        "consultant",
        "business"
    ],
    "wof:name":"Fox Consulting",
    "wof:placetype":"venue"
},
  "geometry": {"coordinates":[-0.016559,51.508942],"type":"Point"}
}