{
  "type": "Feature",
  "properties": {
    "iso:country":"GB",
    "sg:address":"86 Charminster Ave",
    "sg:city":"Bournemouth",
    "sg:classifiers":[
        {
            "category":"Shopping",
            "subcategory":"Crafts & Fabrics",
            "type":"Retail Goods"
        }
    ],
    "sg:postcode":"BH9 1SE",
    "sg:province":"Dorset",
    "sg:tags":[
        "shop",
        "needlecraft",
        "wool"
    ],
    "wof:name":"Horn,Joan A,",
    "wof:placetype":"venue"
},
  "geometry": {"coordinates":[-1.865579,50.748508],"type":"Point"}
}