{
  "type": "Feature",
  "properties": {
    "addr:full":"32 Houndiscombe Road, Mutley Plymouth Devon PL4 6HQ",
    "addr:housenumber":"32",
    "addr:postcode":"pl4 6hq",
    "addr:street":"Houndiscombe Road",
    "iso:country":"GB",
    "sg:address":"32 Houndiscombe Road, Mutley",
    "sg:city":"Plymouth",
    "sg:classifiers":[
        {
            "category":"Travel",
            "subcategory":"Hotels & Motels",
            "type":"Entertainment"
        }
    ],
    "sg:phone":"+44 1752 664749",
    "sg:postcode":"PL4 6HQ",
    "sg:province":"Devon",
    "wof:name":"Rosaland Hotel",
    "wof:placetype":"venue"
},
  "geometry": {"coordinates":[-4.136966,50.379833],"type":"Point"}
}