{
  "type": "Feature",
  "properties": {
    "iso:country":"GB",
    "sg:address":"14 Cornwall Gro, Bletchley",
    "sg:city":"Milton Keynes",
    "sg:classifiers":[
        {
            "category":"Professional",
            "subcategory":"Art Services",
            "type":"Services"
        }
    ],
    "sg:phone":"+44 1908 368081",
    "sg:postcode":"MK3 7HU",
    "sg:province":"Buckinghamshire",
    "sg:tags":[
        "photographer"
    ],
    "wof:name":"Colours Photographics",
    "wof:placetype":"venue"
},
  "geometry": {"coordinates":[-0.7542960048,52.000087738],"type":"Point"}
}