{
  "type": "Feature",
  "properties": {
    "addr:full":"12a King Street, Aspatria Wigton Cumbria CA7 3ES",
    "addr:housenumber":"12a",
    "addr:postcode":"ca7 3es",
    "addr:street":"King Street",
    "iso:country":"GB",
    "sg:address":"12a King Street, Aspatria",
    "sg:city":"Wigton",
    "sg:classifiers":[
        {
            "category":"Manufacturing",
            "subcategory":"Tools & Machinery",
            "type":"Manufacturing & Wholesale Goods"
        },
        {
            "category":"Insurance",
            "subcategory":"Insurance Agent",
            "type":"Services"
        }
    ],
    "sg:phone":"+44 16973 21776",
    "sg:postcode":"CA7 3ES",
    "sg:province":"Cumbria",
    "sg:tags":[
        "society",
        "friendly"
    ],
    "wof:name":"Castle Insurance Services",
    "wof:placetype":"venue"
},
  "geometry": {"coordinates":[-3.3301479816,54.7639389038],"type":"Point"}
}