{
  "type": "Feature",
  "properties": {
    "iso:country":"GB",
    "sg:address":"Greenhill Street",
    "sg:city":"Swansea",
    "sg:classifiers":[
        {
            "category":"Health Services",
            "subcategory":"Doctor",
            "type":"Services"
        }
    ],
    "sg:phone":"+44 1792 412412",
    "sg:postcode":"SA1 1QW",
    "sg:province":"Neath Port Talbot",
    "sg:tags":[
        "practitioners"
    ],
    "wof:name":"The Greenhill Medical Centre",
    "wof:placetype":"venue"
},
  "geometry": {"coordinates":[-3.941869,51.62925],"type":"Point"}
}