{
  "type": "Feature",
  "properties": {
    "addr:full":"2 Cherry Sq Wallasey Merseyside L44 5XU",
    "addr:housenumber":"2",
    "addr:postcode":"l44 5xu",
    "addr:street":"Cherry Sq",
    "iso:country":"GB",
    "sg:address":"2 Cherry Sq",
    "sg:city":"Wallasey",
    "sg:classifiers":[
        {
            "category":"Food & Beverages",
            "subcategory":"Meat & Fish",
            "type":"Retail Goods"
        }
    ],
    "sg:phone":"+44 151 637 1194",
    "sg:postcode":"L44 5XU",
    "sg:province":"Merseyside",
    "sg:tags":[
        "butcher"
    ],
    "wof:name":"Bremicks",
    "wof:placetype":"venue"
},
  "geometry": {"coordinates":[-3.04994,53.41959],"type":"Point"}
}