{
  "type": "Feature",
  "properties": {
    "iso:country":"GB",
    "sg:address":"26 Hayes Lane",
    "sg:city":"Stourbridge",
    "sg:classifiers":[
        {
            "category":"Home & Garden",
            "subcategory":"Building Materials",
            "type":"Retail Goods"
        },
        {
            "category":"Building & Trades",
            "subcategory":"Construction",
            "type":"Services"
        }
    ],
    "sg:phone":"+44 1384 895274",
    "sg:postcode":"DY9 8RD",
    "sg:province":"West Midlands",
    "sg:tags":[
        "fencing",
        "contractor"
    ],
    "wof:name":"Premier Lye Fencing",
    "wof:placetype":"venue"
},
  "geometry": {"coordinates":[-2.1027019024,52.4597816467],"type":"Point"}
}