{
  "type": "Feature",
  "properties": {
    "iso:country":"GB",
    "sg:address":"Bank Street",
    "sg:city":"Lochgelly",
    "sg:classifiers":[
        {
            "category":"Community Center",
            "type":"Public Place"
        },
        {
            "category":"Government",
            "subcategory":"Office",
            "type":"Public Place"
        }
    ],
    "sg:phone":"+44 1592 782342",
    "sg:postcode":"KY5 9RD",
    "sg:province":"Fife",
    "sg:tags":[
        "recreation",
        "local",
        "leisure",
        "centre"
    ],
    "sg:website":"http://www.lauder.ac.uk",
    "wof:name":"Lochgelly Centre",
    "wof:placetype":"venue"
},
  "geometry": {"coordinates":[-3.309844,56.12904],"type":"Point"}
}