{
  "type": "Feature",
  "properties": {
    "addr:full":"201 Seabourne Road Bournemouth Dorset BH5 2HJ",
    "addr:housenumber":"201",
    "addr:postcode":"bh5 2hj",
    "addr:street":"Seabourne Road",
    "iso:country":"GB",
    "sg:address":"201 Seabourne Road",
    "sg:city":"Bournemouth",
    "sg:classifiers":[
        {
            "category":"Deli",
            "type":"Food & Drink"
        }
    ],
    "sg:phone":"+44 1202 429429",
    "sg:postcode":"BH5 2HJ",
    "sg:province":"Dorset",
    "sg:tags":[
        "delicatessen"
    ],
    "wof:name":"Good Food Co. (Southbourne) Ltd.",
    "wof:placetype":"venue"
},
  "geometry": {"coordinates":[-1.818828,50.726997],"type":"Point"}
}