{
  "type": "Feature",
  "properties": {
    "addr:full":"Hillview, Gotherington Lane Cheltenham Gloucestershire GL52 8EN",
    "addr:postcode":"gl52 8en",
    "addr:street":"Gotherington Lane",
    "iso:country":"GB",
    "sg:address":"Hillview, Gotherington Lane",
    "sg:city":"Cheltenham",
    "sg:classifiers":[
        {
            "category":"Shopping",
            "subcategory":"Photographic Equipment",
            "type":"Retail Goods"
        }
    ],
    "sg:postcode":"GL52 8EN",
    "sg:province":"Gloucestershire",
    "sg:tags":[
        "supply"
    ],
    "wof:name":"Great Western Cars",
    "wof:placetype":"venue"
},
  "geometry": {"coordinates":[-2.056264,51.951199],"type":"Point"}
}