{
  "type": "Feature",
  "properties": {
    "iso:country":"GB",
    "sg:address":"1 Queen Street",
    "sg:city":"Ayr",
    "sg:classifiers":[
        {
            "category":"Manufacturing",
            "subcategory":"Metals",
            "type":"Manufacturing & Wholesale Goods"
        },
        {
            "category":"Autos & Motor Vehicles",
            "subcategory":"Fuel & Gas Station",
            "type":"Retail Goods"
        }
    ],
    "sg:phone":"+44 1292 260888",
    "sg:postcode":"KA8 0DW",
    "sg:province":"South Ayrshire",
    "sg:tags":[
        "steel",
        "fence",
        "erectors",
        "gate",
        "supplier",
        "fabricator"
    ],
    "wof:name":"Robert O'Neill",
    "wof:placetype":"venue"
},
  "geometry": {"coordinates":[-4.622097,55.466648],"type":"Point"}
}