{
  "type": "Feature",
  "properties": {
    "addr:full":"163 High Street Potters Bar Greater London EN6 5BB",
    "addr:housenumber":"163",
    "addr:postcode":"en6 5bb",
    "addr:street":"High Street",
    "iso:country":"GB",
    "sg:address":"163 High Street",
    "sg:city":"Potters Bar",
    "sg:classifiers":[
        {
            "category":"Bars & Pubs",
            "type":"Food & Drink"
        }
    ],
    "sg:phone":"+44 1707 661745",
    "sg:postcode":"EN6 5BB",
    "sg:province":"Greater London",
    "sg:tags":[
        "pubs",
        "inn"
    ],
    "wof:name":"Canning's Free House",
    "wof:placetype":"venue"
},
  "geometry": {"coordinates":[-0.1748970002,51.6974067688],"type":"Point"}
}