{
  "type": "Feature",
  "properties": {
    "iso:country":"GB",
    "sg:address":"14 Van Alloys Business Park, Busgrove Lane, Stoke Row",
    "sg:city":"Henley On Thames",
    "sg:classifiers":[
        {
            "category":"Home & Garden",
            "subcategory":"Hardware",
            "type":"Retail Goods"
        }
    ],
    "sg:phone":"+44 1491 680155",
    "sg:postcode":"RG9 5QB",
    "sg:province":"Berkshire",
    "sg:tags":[
        "device",
        "fixing",
        "fastener"
    ],
    "wof:name":"Aerosmith Ltd",
    "wof:placetype":"venue"
},
  "geometry": {"coordinates":[-1.015119,51.55069],"type":"Point"}
}