{
  "type": "Feature",
  "properties": {
    "addr:full":"Witherley House, Hazell Way Nuneaton Leicestershire CV10 7QG",
    "addr:housenumber":"witherley",
    "addr:postcode":"cv10 7qg",
    "addr:street":"Hazell Way",
    "iso:country":"GB",
    "sg:address":"Witherley House, Hazell Way",
    "sg:city":"Nuneaton",
    "sg:classifiers":[
        {
            "category":"Building & Trades",
            "subcategory":"Equipment Rental",
            "type":"Services"
        },
        {
            "category":"Manufacturing",
            "subcategory":"Building Materials",
            "type":"Manufacturing & Wholesale Goods"
        }
    ],
    "sg:phone":"+44 24 7635 1188",
    "sg:postcode":"CV10 7QG",
    "sg:province":"Leicestershire",
    "sg:tags":[
        "merchant",
        "plant",
        "builder",
        "machinery"
    ],
    "wof:name":"Witherley Services Western Ltd.",
    "wof:placetype":"venue"
},
  "geometry": {"coordinates":[-1.4846390486,52.5085601807],"type":"Point"}
}