{
  "type": "Feature",
  "properties": {
    "iso:country":"GB",
    "sg:address":"61 College Road, Handsworth Wood",
    "sg:city":"Birmingham",
    "sg:classifiers":[
        {
            "category":"Building & Trades",
            "subcategory":"Construction",
            "type":"Services"
        }
    ],
    "sg:postcode":"B20 2JH",
    "sg:province":"West Midlands",
    "sg:tags":[
        "builder"
    ],
    "wof:name":"David R Timms Building Contractor",
    "wof:placetype":"venue"
},
  "geometry": {"coordinates":[-1.9366739988,52.5157814026],"type":"Point"}
}