{
  "type": "Feature",
  "properties": {
    "iso:country":"GB",
    "sg:address":"Halfway House, Main Road",
    "sg:city":"Spalding",
    "sg:classifiers":[
        {
            "category":"Food & Beverages",
            "subcategory":"Fruits & Vegetables",
            "type":"Retail Goods"
        }
    ],
    "sg:phone":"+44 1775 630309",
    "sg:postcode":"PE11 3DH",
    "sg:province":"Lincolnshire",
    "sg:tags":[
        "greengrocer"
    ],
    "wof:name":"Alan T Varley",
    "wof:placetype":"venue"
},
  "geometry": {"coordinates":[-0.180834,52.761017],"type":"Point"}
}