{
  "type": "Feature",
  "properties": {
    "iso:country":"GB",
    "sg:address":"79 Drummond Rd",
    "sg:city":"Skegness",
    "sg:classifiers":[
        {
            "category":"Travel",
            "subcategory":"Hotels & Motels",
            "type":"Entertainment"
        }
    ],
    "sg:phone":"+44 1754 763893",
    "sg:postcode":"PE25 3EH",
    "sg:province":"Lincolnshire",
    "wof:name":"The Peveril Hotel",
    "wof:placetype":"venue"
},
  "geometry": {"coordinates":[0.3423709869,53.1373291016],"type":"Point"}
}