{
  "type": "Feature",
  "properties": {
    "iso:country":"GB",
    "sg:address":"71 Drumlanrig Street",
    "sg:city":"Thornhill",
    "sg:classifiers":[
        {
            "category":"Retail",
            "subcategory":"Auto Repair",
            "type":"Services"
        }
    ],
    "sg:phone":"+44 1848 330118",
    "sg:postcode":"DG3 5LY",
    "sg:province":"Dumfries and Galloway",
    "sg:tags":[
        "body",
        "car"
    ],
    "wof:name":"John Black Car Body Shop",
    "wof:placetype":"venue"
},
  "geometry": {"coordinates":[-3.763466,55.239796],"type":"Point"}
}