{
  "type": "Feature",
  "properties": {
    "addr:full":"53 Piccadilly Manchester Greater Manchester M1 2AL",
    "addr:housenumber":"53",
    "addr:postcode":"m1 2al",
    "addr:street":"Piccadilly",
    "iso:country":"GB",
    "sg:address":"53 Piccadilly",
    "sg:city":"Manchester",
    "sg:classifiers":[
        {
            "category":"Travel",
            "subcategory":"Travel Agent",
            "type":"Entertainment"
        }
    ],
    "sg:phone":"+44 161 251 7272",
    "sg:postcode":"M1 2AL",
    "sg:province":"Greater Manchester",
    "wof:name":"Thomas Cook Travel",
    "wof:placetype":"venue"
},
  "geometry": {"coordinates":[-2.234799,53.480862],"type":"Point"}
}