{
  "type": "Feature",
  "properties": {
    "iso:country":"GB",
    "sg:address":"Thornton House, 16 Parkstone Rd",
    "sg:city":"Poole",
    "sg:classifiers":[
        {
            "category":"Professional",
            "subcategory":"Art Services",
            "type":"Services"
        }
    ],
    "sg:phone":"+44 1202 257373",
    "sg:postcode":"BH15 2PG",
    "sg:province":"Dorset",
    "sg:tags":[
        "graphic",
        "designer"
    ],
    "wof:name":"M & A Design",
    "wof:placetype":"venue"
},
  "geometry": {"coordinates":[-1.978203,50.71954],"type":"Point"}
}