{
  "type": "Feature",
  "properties": {
    "addr:full":"6 Woodland Crescent Golspie Highland KW10 6TZ",
    "addr:housenumber":"6",
    "addr:postcode":"kw10 6tz",
    "addr:street":"Woodland Crescent",
    "iso:country":"GB",
    "sg:address":"6 Woodland Crescent",
    "sg:city":"Golspie",
    "sg:classifiers":[
        {
            "category":"Organizations",
            "subcategory":"Community Association",
            "type":"Services"
        }
    ],
    "sg:phone":"+44 1408 633866",
    "sg:postcode":"KW10 6TZ",
    "sg:province":"Highland",
    "sg:tags":[
        "co-operatives",
        "society",
        "housing",
        "trust"
    ],
    "sg:website":"http://www.keyhousing.org",
    "wof:name":"Key Housing Association Ltd",
    "wof:placetype":"venue"
},
  "geometry": {"coordinates":[-3.974389,57.977451],"type":"Point"}
}