{
  "type": "Feature",
  "properties": {
    "iso:country":"GB",
    "sg:address":"Care Of Tourist Information Centre, Bridgefoot",
    "sg:city":"Stratford Upon Avon",
    "sg:classifiers":[
        {
            "category":"Banks & Credit Unions",
            "subcategory":"Bureau De Change",
            "type":"Services"
        }
    ],
    "sg:phone":"+44 1789 415856",
    "sg:postcode":"CV37 6GW",
    "sg:province":"Warwickshire",
    "wof:name":"American Express",
    "wof:placetype":"venue"
},
  "geometry": {"coordinates":[-1.7072689533,52.1941337585],"type":"Point"}
}