{
  "type": "Feature",
  "properties": {
    "addr:full":"139 Sunderland Rd Forest Hill Greater London SE23 2PX",
    "addr:housenumber":"139",
    "addr:postcode":"se23 2px",
    "addr:street":"Sunderland Rd",
    "iso:country":"GB",
    "sg:address":"139 Sunderland Rd",
    "sg:city":"Forest Hill",
    "sg:classifiers":[
        {
            "category":"Retail",
            "subcategory":"Storage",
            "type":"Services"
        }
    ],
    "sg:phone":"+44 20 8355 1303",
    "sg:postcode":"SE23 2PX",
    "sg:province":"Greater London",
    "sg:tags":[
        "household",
        "removal"
    ],
    "wof:name":"Removal Service",
    "wof:placetype":"venue"
},
  "geometry": {"coordinates":[-0.0468619987,51.4356002808],"type":"Point"}
}