{
  "type": "Feature",
  "properties": {
    "iso:country":"GB",
    "sg:address":"26 Glen Road",
    "sg:city":"Sheffield",
    "sg:classifiers":[
        {
            "category":"Health Services",
            "subcategory":"Clinic",
            "type":"Services"
        },
        {
            "category":"Health Services",
            "subcategory":"Dentist",
            "type":"Services"
        }
    ],
    "sg:phone":"+44 114 258 9716",
    "sg:postcode":"S7 1RA",
    "sg:province":"South Yorkshire",
    "sg:tags":[
        "private"
    ],
    "wof:name":"Sheffield Fertility Centre",
    "wof:placetype":"venue"
},
  "geometry": {"coordinates":[-1.4859030247,53.3583297729],"type":"Point"}
}