{
  "type": "Feature",
  "properties": {
    "iso:country":"GB",
    "sg:address":"London Rd",
    "sg:city":"Chalfont St Giles",
    "sg:classifiers":[
        {
            "category":"Home & Garden",
            "subcategory":"Home Furnishings",
            "type":"Retail Goods"
        }
    ],
    "sg:phone":"+44 70 0056 0125",
    "sg:postcode":"HP8 4NN",
    "sg:province":"Buckinghamshire",
    "sg:tags":[
        "blind",
        "curtain",
        "fitting"
    ],
    "wof:name":"Barbara Rouse Curtain Designs",
    "wof:placetype":"venue"
},
  "geometry": {"coordinates":[-0.5658450127,51.6327667236],"type":"Point"}
}