{
  "type": "Feature",
  "properties": {
    "iso:country":"GB",
    "sg:address":"13 High Street",
    "sg:city":"Berkhamsted",
    "sg:classifiers":[
        {
            "category":"Government",
            "subcategory":"Post Office",
            "type":"Public Place"
        }
    ],
    "sg:postcode":"HP4 2BY",
    "sg:province":"Bedfordshire",
    "wof:name":"Berkhamsted Sub Post Office",
    "wof:placetype":"venue"
},
  "geometry": {"coordinates":[-0.5571359992,51.7579612732],"type":"Point"}
}