{
  "type": "Feature",
  "properties": {
    "addr:full":"29 Deer Park Road London Greater London SW19 3UG",
    "addr:housenumber":"29",
    "addr:postcode":"sw19 3ug",
    "addr:street":"Deer Park Road",
    "iso:country":"GB",
    "sg:address":"29 Deer Park Road",
    "sg:city":"London",
    "sg:classifiers":[
        {
            "category":"Retail",
            "subcategory":"Photofinishing",
            "type":"Services"
        }
    ],
    "sg:phone":"+44 20 8542 2435",
    "sg:postcode":"SW19 3UG",
    "sg:province":"Greater London",
    "sg:tags":[
        "photographic",
        "processor"
    ],
    "wof:name":"Kodak Processing Companies Ltd.",
    "wof:placetype":"venue"
},
  "geometry": {"coordinates":[-0.192127,51.408424],"type":"Point"}
}