{
  "type": "Feature",
  "properties": {
    "iso:country":"GB",
    "sg:address":"126 Church Street, Langford",
    "sg:city":"Biggleswade",
    "sg:classifiers":[
        {
            "category":"Bars & Pubs",
            "type":"Food & Drink"
        }
    ],
    "sg:phone":"+44 1462 628899",
    "sg:postcode":"SG18 9NX",
    "sg:province":"Bedfordshire",
    "sg:tags":[
        "pubs",
        "inn"
    ],
    "wof:name":"The Wrestlers",
    "wof:placetype":"venue"
},
  "geometry": {"coordinates":[-0.2720910013,52.0550498962],"type":"Point"}
}