{
  "type": "Feature",
  "properties": {
    "addr:full":"42 New Road, Ditton Aylesford Kent ME20 6AD",
    "addr:housenumber":"42",
    "addr:postcode":"me20 6ad",
    "addr:street":"New Road;Aylesford",
    "iso:country":"GB",
    "sg:address":"42 New Road, Ditton",
    "sg:city":"Aylesford",
    "sg:classifiers":[
        {
            "category":"Organizations",
            "subcategory":"Community Association",
            "type":"Services"
        },
        {
            "category":"Organizations",
            "subcategory":"Membership Organization",
            "type":"Services"
        }
    ],
    "sg:phone":"+44 1732 844959",
    "sg:postcode":"ME20 6AD",
    "sg:province":"Kent",
    "sg:tags":[
        "club",
        "social"
    ],
    "wof:name":"DITTON CLUB",
    "wof:placetype":"venue"
},
  "geometry": {"coordinates":[0.453866,51.297737],"type":"Point"}
}