{
  "type": "Feature",
  "properties": {
    "addr:full":"46 Midship Point, Malabar Street, Isle Of Dogs Poplar Greater London E14 8SP",
    "addr:housenumber":"46",
    "addr:postcode":"e14 8sp",
    "addr:street":"Midship Point Malabar Street",
    "iso:country":"GB",
    "sg:address":"46 Midship Point, Malabar Street, Isle Of Dogs",
    "sg:city":"Poplar",
    "sg:classifiers":[
        {
            "category":"Building & Trades",
            "subcategory":"Construction",
            "type":"Services"
        }
    ],
    "sg:phone":"+44 20 7515 4820",
    "sg:postcode":"E14 8SP",
    "sg:province":"Greater London",
    "sg:tags":[
        "tiling",
        "contractor"
    ],
    "wof:name":"I O D Tiling",
    "wof:placetype":"venue"
},
  "geometry": {"coordinates":[-0.02454,51.498692],"type":"Point"}
}