{
  "type": "Feature",
  "properties": {
    "iso:country":"GB",
    "sg:address":"104 Coillesdene Avenue",
    "sg:city":"Edinburgh",
    "sg:classifiers":[
        {
            "category":"Building & Trades",
            "subcategory":"Landscaping Services",
            "type":"Services"
        }
    ],
    "sg:phone":"+44 131 657 5509",
    "sg:postcode":"EH15 2LG",
    "sg:province":"City of Edinburgh",
    "sg:tags":[
        "gardening"
    ],
    "wof:name":"Bill Aitken",
    "wof:placetype":"venue"
},
  "geometry": {"coordinates":[-3.080885,55.946964],"type":"Point"}
}