{
  "type": "Feature",
  "properties": {
    "addr:full":"Unit 3, Marsh Lane Crediton Devon EX17 1ES",
    "addr:housenumber":"unit 3",
    "addr:postcode":"ex17 1es",
    "addr:street":"Marsh Lane",
    "iso:country":"GB",
    "sg:address":"Unit 3, Marsh Lane",
    "sg:city":"Crediton",
    "sg:classifiers":[
        {
            "category":"Home & Garden",
            "subcategory":"Home Furnishings",
            "type":"Retail Goods"
        },
        {
            "category":"Home & Garden",
            "subcategory":"Building Materials",
            "type":"Retail Goods"
        }
    ],
    "sg:phone":"+44 1363 773533",
    "sg:postcode":"EX17 1ES",
    "sg:province":"Devon",
    "sg:tags":[
        "installers",
        "planner",
        "kitchen",
        "furnishers"
    ],
    "wof:name":"Ashgrove Kitchens Ltd.",
    "wof:placetype":"venue"
},
  "geometry": {"coordinates":[-3.644358,50.790417],"type":"Point"}
}