{
  "type": "Feature",
  "properties": {
    "addr:full":"25 St Martins Walk Dorking Surrey RH4 1UT",
    "addr:housenumber":"25",
    "addr:postcode":"rh4 1ut",
    "addr:street":"St Martins Walk",
    "iso:country":"GB",
    "sg:address":"25 St Martins Walk",
    "sg:city":"Dorking",
    "sg:classifiers":[
        {
            "category":"Shopping",
            "subcategory":"Clothing, Apparel, & Fashions",
            "type":"Retail Goods"
        }
    ],
    "sg:phone":"+44 1306 743617",
    "sg:postcode":"RH4 1UT",
    "sg:province":"Surrey",
    "sg:tags":[
        "shop"
    ],
    "wof:name":"Nightingales",
    "wof:placetype":"venue"
},
  "geometry": {"coordinates":[-0.328814,51.233341],"type":"Point"}
}