{
  "type": "Feature",
  "properties": {
    "addr:full":"68 Gloucester Street Barrow-in-furness Cumbria LA13 9RX",
    "addr:housenumber":"68",
    "addr:postcode":"la13 9rx",
    "addr:street":"Gloucester Street",
    "iso:country":"GB",
    "sg:address":"68 Gloucester Street",
    "sg:city":"Barrow-in-furness",
    "sg:classifiers":[
        {
            "category":"Home & Garden",
            "subcategory":"Hardware",
            "type":"Retail Goods"
        }
    ],
    "sg:phone":"+44 1229 822544",
    "sg:postcode":"LA13 9RX",
    "sg:province":"Cumbria",
    "sg:tags":[
        "retailer",
        "diy"
    ],
    "wof:name":"Delph & Son",
    "wof:placetype":"venue"
},
  "geometry": {"coordinates":[-3.2081310749,54.1122627258],"type":"Point"}
}