{
  "type": "Feature",
  "properties": {
    "addr:full":"431 Hagley Road West, Quinton Birmingham West Midlands B32 2AD",
    "addr:housenumber":"431",
    "addr:postcode":"b32 2ad",
    "addr:street":"Hagley Road West",
    "iso:country":"GB",
    "sg:address":"431 Hagley Road West, Quinton",
    "sg:city":"Birmingham",
    "sg:classifiers":[
        {
            "category":"Insurance",
            "subcategory":"Insurance Agent",
            "type":"Services"
        }
    ],
    "sg:phone":"+44 121 423 4040",
    "sg:postcode":"B32 2AD",
    "sg:province":"West Midlands",
    "wof:name":"Zet Insurance Services Ltd.",
    "wof:placetype":"venue"
},
  "geometry": {"coordinates":[-1.989562,52.464706],"type":"Point"}
}