{
  "type": "Feature",
  "properties": {
    "addr:full":"187 West End La Kilburn Greater London NW6 2LJ",
    "addr:housenumber":"187",
    "addr:postcode":"nw6 2lj",
    "addr:street":"West",
    "iso:country":"GB",
    "sg:address":"187 West End La",
    "sg:city":"Kilburn",
    "sg:classifiers":[
        {
            "category":"Retail",
            "subcategory":"Auto Repair",
            "type":"Services"
        }
    ],
    "sg:phone":"+44 20 7328 8081",
    "sg:postcode":"NW6 2LJ",
    "sg:province":"Greater London",
    "sg:tags":[
        "modification",
        "garage"
    ],
    "wof:name":"S S Auto Repairs",
    "wof:placetype":"venue"
},
  "geometry": {"coordinates":[-0.1911190003,51.54637146],"type":"Point"}
}