{
  "type": "Feature",
  "properties": {
    "iso:country":"GB",
    "sg:address":"5 Bader Close",
    "sg:city":"Kenley",
    "sg:classifiers":[
        {
            "category":"Building & Trades",
            "subcategory":"Cleaning & Sanitation",
            "type":"Services"
        }
    ],
    "sg:phone":"+44 20 8407 5952",
    "sg:postcode":"CR8 5DQ",
    "sg:province":"Surrey",
    "sg:tags":[
        "cleaner",
        "window"
    ],
    "wof:name":"A.V.A Cleaning Services",
    "wof:placetype":"venue"
},
  "geometry": {"coordinates":[-0.096439,51.322327],"type":"Point"}
}