{
  "type": "Feature",
  "properties": {
    "addr:full":"Chapel Hill, Sticker St Austell Cornwall PL26 7HG",
    "addr:postcode":"pl26 7hg",
    "addr:street":"Hill Sticker",
    "iso:country":"GB",
    "sg:address":"Chapel Hill, Sticker",
    "sg:city":"St Austell",
    "sg:classifiers":[
        {
            "category":"Professional",
            "subcategory":"Engineering",
            "type":"Services"
        },
        {
            "category":"Building & Trades",
            "subcategory":"Electrical",
            "type":"Services"
        }
    ],
    "sg:phone":"+44 1726 65635",
    "sg:postcode":"PL26 7HG",
    "sg:province":"Cornwall",
    "sg:tags":[
        "engineer",
        "electrician",
        "contractor"
    ],
    "wof:name":"Waldon Electrical Contractors Ltd",
    "wof:placetype":"venue"
},
  "geometry": {"coordinates":[-4.8184437752,50.3203163147],"type":"Point"}
}