{
  "type": "Feature",
  "properties": {
    "addr:full":"P O Box 30 Wisbech Cambridgeshire PE14 7NE",
    "addr:housenumber":"box 30",
    "addr:postcode":"pe14 7ne",
    "addr:street":"P O",
    "iso:country":"GB",
    "sg:address":"P O Box 30",
    "sg:city":"Wisbech",
    "sg:classifiers":[
        {
            "category":"Home & Garden",
            "subcategory":"Building Materials",
            "type":"Retail Goods"
        }
    ],
    "sg:phone":"+44 1945 780999",
    "sg:postcode":"PE14 7NE",
    "sg:province":"Cambridgeshire",
    "sg:tags":[
        "shutter",
        "door"
    ],
    "wof:name":"Chillerstrip 24 Hour Blinds",
    "wof:placetype":"venue"
},
  "geometry": {"coordinates":[0.2266300023,52.6975212097],"type":"Point"}
}