{
  "type": "Feature",
  "properties": {
    "addr:full":"Brewery Yard, 6 Landseer Road Ipswich Suffolk IP3 0AZ",
    "addr:housenumber":"6",
    "addr:postcode":"ip3 0az",
    "addr:street":"Landseer Road",
    "iso:country":"GB",
    "sg:address":"Brewery Yard, 6 Landseer Road",
    "sg:city":"Ipswich",
    "sg:classifiers":[
        {
            "category":"Freight",
            "type":"Transportation"
        }
    ],
    "sg:phone":"+44 1473 254717",
    "sg:postcode":"IP3 0AZ",
    "sg:province":"Suffolk",
    "sg:tags":[
        "haulage",
        "transport",
        "road"
    ],
    "wof:name":"Waller Transport Services Ltd",
    "wof:placetype":"venue"
},
  "geometry": {"coordinates":[1.16557,52.044708],"type":"Point"}
}