{
  "type": "Feature",
  "properties": {
    "iso:country":"GB",
    "sg:address":"Locks Lane, Sparsholt",
    "sg:city":"Winchester",
    "sg:classifiers":[
        {
            "category":"Arena",
            "subcategory":"Sports Club",
            "type":"Entertainment"
        }
    ],
    "sg:phone":"+44 1962 776575",
    "sg:postcode":"SO21 2LU",
    "sg:province":"Hampshire",
    "wof:name":"Sparsholt Cricket Club",
    "wof:placetype":"venue"
},
  "geometry": {"coordinates":[-1.378382,51.079079],"type":"Point"}
}