{
  "type": "Feature",
  "properties": {
    "iso:country":"GB",
    "sg:address":"20 Kevington Drive",
    "sg:city":"Lowestoft",
    "sg:classifiers":[
        {
            "category":"Cinema",
            "subcategory":"Movie Rental",
            "type":"Entertainment"
        }
    ],
    "sg:postcode":"NR32 3JL",
    "sg:province":"Suffolk",
    "sg:tags":[
        "video",
        "library"
    ],
    "wof:name":"Micks Mobile",
    "wof:placetype":"venue"
},
  "geometry": {"coordinates":[1.7018810511,52.4827613831],"type":"Point"}
}