{
  "type": "Feature",
  "properties": {
    "addr:full":"652 Ashton New Road Manchester Greater Manchester M11 4SQ",
    "addr:housenumber":"652",
    "addr:postcode":"m11 4sq",
    "addr:street":"Ashton New Road",
    "iso:country":"GB",
    "sg:address":"652 Ashton New Road",
    "sg:city":"Manchester",
    "sg:classifiers":[
        {
            "category":"Bars & Pubs",
            "type":"Food & Drink"
        }
    ],
    "sg:phone":"+44 161 223 8242",
    "sg:postcode":"M11 4SQ",
    "sg:province":"Greater Manchester",
    "sg:tags":[
        "pubs",
        "inn"
    ],
    "wof:name":"The Grove Inn",
    "wof:placetype":"venue"
},
  "geometry": {"coordinates":[-2.183484,53.483196],"type":"Point"}
}