{
  "type": "Feature",
  "properties": {
    "addr:full":"Brant Broughton Lincoln Lincolnshire LN5 0SA",
    "addr:postcode":"ln5 0sa",
    "addr:street":"Brant Broughton",
    "iso:country":"GB",
    "sg:address":"Brant Broughton",
    "sg:city":"Lincoln",
    "sg:classifiers":[
        {
            "category":"Farming",
            "subcategory":"Livestock Farm",
            "type":"Manufacturing & Wholesale Goods"
        }
    ],
    "sg:phone":"+44 1400 272256",
    "sg:postcode":"LN5 0SA",
    "sg:province":"Lincolnshire",
    "sg:tags":[
        "others"
    ],
    "wof:name":"J T Hollis (Farms) Ltd.",
    "wof:placetype":"venue"
},
  "geometry": {"coordinates":[-0.6325290203,53.0777168274],"type":"Point"}
}