{
  "type": "Feature",
  "properties": {
    "iso:country":"GB",
    "sg:address":"Trafalgar House, 11waterloo Place",
    "sg:city":"West End",
    "sg:classifiers":[
        {
            "category":"Professional",
            "subcategory":"Management & Consulting",
            "type":"Services"
        }
    ],
    "sg:postcode":"SW1Y 4AU",
    "sg:province":"Greater London",
    "sg:tags":[
        "consultant",
        "business"
    ],
    "wof:name":"Bullus & Co",
    "wof:placetype":"venue"
},
  "geometry": {"coordinates":[-0.13323,51.507809],"type":"Point"}
}