{
  "type": "Feature",
  "properties": {
    "addr:full":"35-40 Charlotte Road London Greater London EC2A 3PB",
    "addr:housenumber":"35-40",
    "addr:postcode":"ec2a 3pb",
    "addr:street":"Charlotte Road",
    "iso:country":"GB",
    "sg:address":"35-40 Charlotte Road",
    "sg:city":"London",
    "sg:classifiers":[
        {
            "category":"Communications",
            "subcategory":"Film & Video Production",
            "type":"Services"
        }
    ],
    "sg:phone":"+44 20 7613 4663",
    "sg:postcode":"EC2A 3PB",
    "sg:province":"Greater London",
    "sg:tags":[
        "illustrator",
        "artist"
    ],
    "wof:name":"Sally Haworth",
    "wof:placetype":"venue"
},
  "geometry": {"coordinates":[-0.081029,51.524921],"type":"Point"}
}