{
  "type": "Feature",
  "properties": {
    "addr:full":"5-6 St Austin Street Shrewsbury Shropshire SY1 1SA",
    "addr:housenumber":"5-6",
    "addr:postcode":"sy1 1sa",
    "addr:street":"St Austin Street",
    "iso:country":"GB",
    "sg:address":"5-6 St Austin Street",
    "sg:city":"Shrewsbury",
    "sg:classifiers":[
        {
            "category":"Restaurant",
            "type":"Food & Drink"
        }
    ],
    "sg:phone":"+44 1743 236599",
    "sg:postcode":"SY1 1SA",
    "sg:province":"Shropshire",
    "sg:tags":[
        "-",
        "chinese"
    ],
    "wof:name":"China Rose",
    "wof:placetype":"venue"
},
  "geometry": {"coordinates":[-2.7516610622,52.7081298828],"type":"Point"}
}