{
  "type": "Feature",
  "properties": {
    "iso:country":"GB",
    "sg:address":"Laburnum Road, Maltby",
    "sg:city":"Rotherham",
    "sg:classifiers":[
        {
            "category":"Social Services",
            "subcategory":"Adult Care",
            "type":"Services"
        },
        {
            "category":"Government",
            "subcategory":"Office",
            "type":"Public Place"
        }
    ],
    "sg:phone":"+44 1709 817067",
    "sg:postcode":"S66 8DR",
    "sg:province":"South Yorkshire",
    "sg:tags":[
        "housing",
        "local",
        "sheltered"
    ],
    "wof:name":"Laburnum Road Sheltered Housing",
    "wof:placetype":"venue"
},
  "geometry": {"coordinates":[-1.2237069607,53.4243354797],"type":"Point"}
}