{
  "type": "Feature",
  "properties": {
    "addr:full":"David Lloyd Leisure Centre, Ipswich Rd Cardiff Caerphilly CF3 7AQ",
    "addr:postcode":"cf3 7aq",
    "addr:street":"Ipswich Rd",
    "iso:country":"GB",
    "sg:address":"David Lloyd Leisure Centre, Ipswich Rd",
    "sg:city":"Cardiff",
    "sg:classifiers":[
        {
            "category":"Personal",
            "subcategory":"Beauty Salon",
            "type":"Services"
        }
    ],
    "sg:phone":"+44 29 2048 6000",
    "sg:postcode":"CF3 7AQ",
    "sg:province":"Caerphilly",
    "wof:name":"Skin Care Salon The",
    "wof:placetype":"venue"
},
  "geometry": {"coordinates":[-3.09191,51.533051],"type":"Point"}
}