{
  "type": "Feature",
  "properties": {
    "addr:full":"4th Floor, Janus House, St Andrews Street Cambridge Cambridgeshire CB2 3AH",
    "addr:housenumber":"4th floor janus house",
    "addr:postcode":"cb2 3ah",
    "addr:street":"St Andrews Street",
    "iso:country":"GB",
    "sg:address":"4th Floor, Janus House, St Andrews Street",
    "sg:city":"Cambridge",
    "sg:classifiers":[
        {
            "category":"Shopping",
            "subcategory":"Thrift Store",
            "type":"Retail Goods"
        }
    ],
    "sg:phone":"+44 1223 301317",
    "sg:postcode":"CB2 3AH",
    "sg:province":"Cambridgeshire",
    "sg:tags":[
        "shop",
        "charity"
    ],
    "wof:name":"Oxfam",
    "wof:placetype":"venue"
},
  "geometry": {"coordinates":[0.1230550036,52.2040901184],"type":"Point"}
}