{
  "type": "Feature",
  "properties": {
    "addr:full":"Charlton Mead Lane Hoddesdon Essex EN11 0DJ",
    "addr:postcode":"en11 0dj",
    "addr:street":"Charlton Mead Lane",
    "iso:country":"GB",
    "sg:address":"Charlton Mead Lane",
    "sg:city":"Hoddesdon",
    "sg:classifiers":[
        {
            "category":"Home & Garden",
            "subcategory":"Garden Supply",
            "type":"Retail Goods"
        }
    ],
    "sg:phone":"+44 1992 470318",
    "sg:postcode":"EN11 0DJ",
    "sg:province":"Essex",
    "sg:tags":[
        "sand",
        "gravel"
    ],
    "wof:name":"Prepack Hoddesdon",
    "wof:placetype":"venue"
},
  "geometry": {"coordinates":[0.0066149998,51.7576217651],"type":"Point"}
}