{
  "type": "Feature",
  "properties": {
    "addr:full":"Norfolk Fire Station, Friars La Great Yarmouth Norfolk NR30 2RP",
    "addr:postcode":"nr30 2rp",
    "addr:street":"Friars La Great Yarmouth",
    "iso:country":"GB",
    "sg:address":"Norfolk Fire Station, Friars La",
    "sg:city":"Great Yarmouth",
    "sg:classifiers":[
        {
            "category":"Government",
            "subcategory":"Office",
            "type":"Public Place"
        }
    ],
    "sg:phone":"+44 1493 843212",
    "sg:postcode":"NR30 2RP",
    "sg:province":"Norfolk",
    "sg:tags":[
        "local"
    ],
    "wof:name":"Norfolk County Council",
    "wof:placetype":"venue"
},
  "geometry": {"coordinates":[1.72399,52.612415],"type":"Point"}
}