{
  "type": "Feature",
  "properties": {
    "iso:country":"GB",
    "sg:address":"669 Liverpool Rd, Irlam",
    "sg:city":"Manchester",
    "sg:classifiers":[
        {
            "category":"Professional",
            "subcategory":"Printing & Photocopies",
            "type":"Services"
        }
    ],
    "sg:postcode":"M44 5BQ",
    "sg:province":"Greater Manchester",
    "sg:tags":[
        "printer"
    ],
    "wof:name":"Barlow,Keith,Publicity",
    "wof:placetype":"venue"
},
  "geometry": {"coordinates":[-2.432654,53.432381],"type":"Point"}
}