{
  "type": "Feature",
  "properties": {
    "addr:full":"Premier Works, Providence Street Cradley Heath West Midlands B64 5DR",
    "addr:postcode":"b64 5dr",
    "addr:street":"Providence Street",
    "iso:country":"GB",
    "sg:address":"Premier Works, Providence Street",
    "sg:city":"Cradley Heath",
    "sg:classifiers":[
        {
            "category":"Manufacturing",
            "subcategory":"Metals",
            "type":"Manufacturing & Wholesale Goods"
        },
        {
            "category":"Home & Garden",
            "subcategory":"Hardware",
            "type":"Retail Goods"
        }
    ],
    "sg:phone":"+44 1384 562551",
    "sg:postcode":"B64 5DR",
    "sg:province":"West Midlands",
    "sg:tags":[
        "steel",
        "equipment",
        "erectors",
        "welding",
        "fabricator"
    ],
    "wof:name":"Grand Engineering",
    "wof:placetype":"venue"
},
  "geometry": {"coordinates":[-2.081574,52.472416],"type":"Point"}
}