{
  "type": "Feature",
  "properties": {
    "iso:country":"GB",
    "sg:address":"1c St James's Street",
    "sg:city":"Brighton",
    "sg:classifiers":[
        {
            "category":"Shopping",
            "subcategory":"News",
            "type":"Retail Goods"
        }
    ],
    "sg:phone":"+44 1273 605366",
    "sg:postcode":"BN2 1RE",
    "sg:province":"East Sussex",
    "sg:tags":[
        "newsagent"
    ],
    "wof:name":"P R News",
    "wof:placetype":"venue"
},
  "geometry": {"coordinates":[-0.124216,50.823078],"type":"Point"}
}