{
  "type": "Feature",
  "properties": {
    "iso:country":"GB",
    "sg:address":"11 Dorchester Waye",
    "sg:city":"Hayes",
    "sg:classifiers":[
        {
            "category":"Building & Trades",
            "subcategory":"Construction",
            "type":"Services"
        }
    ],
    "sg:phone":"+44 20 8561 2839",
    "sg:postcode":"UB4 0HU",
    "sg:province":"Greater London",
    "sg:tags":[
        "heating",
        "contractor"
    ],
    "wof:name":"Burnbright Services",
    "wof:placetype":"venue"
},
  "geometry": {"coordinates":[-0.4022209942,51.5194091797],"type":"Point"}
}