{
  "type": "Feature",
  "properties": {
    "iso:country":"GB",
    "sg:address":"Pro Myrddin Scholl",
    "sg:city":"Carmarthen",
    "sg:classifiers":[
        {
            "category":"Education",
            "subcategory":"School",
            "type":"Public Place"
        }
    ],
    "sg:phone":"+44 1267 234829",
    "sg:postcode":"SA32 8DN",
    "sg:province":"Carmarthenshire",
    "sg:tags":[
        "local",
        "authority"
    ],
    "wof:name":"Ysgol Gyfun Bro Myrddin",
    "wof:placetype":"venue"
},
  "geometry": {"coordinates":[-4.31102,51.835758],"type":"Point"}
}