{
  "type": "Feature",
  "properties": {
    "addr:full":"20 Old Harpenden Road St Albans Hertfordshire AL3 6AX",
    "addr:housenumber":"20",
    "addr:postcode":"al3 6ax",
    "addr:street":"Old Harpenden Road",
    "iso:country":"GB",
    "sg:address":"20 Old Harpenden Road",
    "sg:city":"St Albans",
    "sg:classifiers":[
        {
            "category":"Health Services",
            "subcategory":"Health Practitioner",
            "type":"Services"
        }
    ],
    "sg:phone":"+44 1727 858588",
    "sg:postcode":"AL3 6AX",
    "sg:province":"Hertfordshire",
    "sg:tags":[
        "physiotherapist"
    ],
    "wof:name":"R A B Arnott",
    "wof:placetype":"venue"
},
  "geometry": {"coordinates":[-0.3339569867,51.7680778503],"type":"Point"}
}