{
  "type": "Feature",
  "properties": {
    "addr:full":"29 & 30 Morgan Way, Bowthorpe Industrial Estate Norwich Norfolk NR5 9HH",
    "addr:housenumber":"29 & 30",
    "addr:postcode":"nr5 9hh",
    "addr:street":"Morgan Way;Industrial Estate Norwich Norfolk",
    "iso:country":"GB",
    "sg:address":"29 & 30 Morgan Way, Bowthorpe Industrial Estate",
    "sg:city":"Norwich",
    "sg:classifiers":[
        {
            "category":"Professional",
            "subcategory":"Management & Consulting",
            "type":"Services"
        },
        {
            "category":"Shopping",
            "subcategory":"Books",
            "type":"Retail Goods"
        }
    ],
    "sg:phone":"+44 1603 740400",
    "sg:postcode":"NR5 9HH",
    "sg:province":"Norfolk",
    "sg:tags":[
        "bookseller",
        "holding",
        "activity"
    ],
    "wof:name":"GROLIER LTD",
    "wof:placetype":"venue"
},
  "geometry": {"coordinates":[1.21402,52.644531],"type":"Point"}
}