{
  "type": "Feature",
  "properties": {
    "iso:country":"GB",
    "sg:address":"Crondal Road, Exhall",
    "sg:city":"Coventry",
    "sg:classifiers":[
        {
            "category":"Professional",
            "subcategory":"Business Services",
            "type":"Services"
        }
    ],
    "sg:phone":"+44 24 7664 5404",
    "sg:postcode":"CV7 9NH",
    "sg:province":"Warwickshire",
    "sg:tags":[
        "distribution"
    ],
    "wof:name":"Comag",
    "wof:placetype":"venue"
},
  "geometry": {"coordinates":[-1.4761879444,52.4659156799],"type":"Point"}
}