{
  "type": "Feature",
  "properties": {
    "addr:full":"27 Caithness Pl Kirkcaldy Fife KY1 3ED",
    "addr:housenumber":"27",
    "addr:postcode":"ky1 3ed",
    "addr:street":"Caithness Pl",
    "iso:country":"GB",
    "sg:address":"27 Caithness Pl",
    "sg:city":"Kirkcaldy",
    "sg:classifiers":[
        {
            "category":"Social Services",
            "subcategory":"Adult Care",
            "type":"Services"
        }
    ],
    "sg:phone":"+44 1592 652513",
    "sg:postcode":"KY1 3ED",
    "sg:province":"Fife",
    "sg:tags":[
        "housing",
        "sheltered"
    ],
    "wof:name":"Caithness Place Sheltered Housing",
    "wof:placetype":"venue"
},
  "geometry": {"coordinates":[-3.136245,56.128128],"type":"Point"}
}