{
  "type": "Feature",
  "properties": {
    "addr:full":"11-15 High Street Marlow Berkshire SL7 1AU",
    "addr:housenumber":"11-15",
    "addr:postcode":"sl7 1au",
    "addr:street":"High Street",
    "iso:country":"GB",
    "sg:address":"11-15 High Street",
    "sg:city":"Marlow",
    "sg:classifiers":[
        {
            "category":"Professional",
            "subcategory":"Employment Agencies",
            "type":"Services"
        }
    ],
    "sg:phone":"+44 1628 474474",
    "sg:postcode":"SL7 1AU",
    "sg:province":"Berkshire",
    "sg:tags":[
        "consultant"
    ],
    "wof:name":"Southern Staff Services",
    "wof:placetype":"venue"
},
  "geometry": {"coordinates":[-0.7763770223,51.5716171265],"type":"Point"}
}