{
  "type": "Feature",
  "properties": {
    "iso:country":"GB",
    "sg:address":"26 Hyde Ave",
    "sg:city":"Hitchin",
    "sg:classifiers":[
        {
            "category":"Building & Trades",
            "subcategory":"Construction",
            "type":"Services"
        }
    ],
    "sg:postcode":"SG5 4JD",
    "sg:province":"Bedfordshire",
    "sg:tags":[
        "builder"
    ],
    "wof:name":"Whatmough & Eales Building Contractors",
    "wof:placetype":"venue"
},
  "geometry": {"coordinates":[-0.2361869961,52.0094032288],"type":"Point"}
}