{
  "type": "Feature",
  "properties": {
    "addr:full":"21 Carter Lane Mansfield Nottinghamshire NG18 3DE",
    "addr:housenumber":"21",
    "addr:postcode":"ng18 3de",
    "addr:street":"Carter Lane",
    "iso:country":"GB",
    "sg:address":"21 Carter Lane",
    "sg:city":"Mansfield",
    "sg:classifiers":[
        {
            "category":"Shopping",
            "subcategory":"Gifts & Souvenirs",
            "type":"Retail Goods"
        },
        {
            "category":"Education",
            "subcategory":"School",
            "type":"Public Place"
        },
        {
            "category":"Food & Beverages",
            "subcategory":"Groceries & Convenience Stores",
            "type":"Retail Goods"
        }
    ],
    "sg:phone":"+44 1623 469889",
    "sg:postcode":"NG18 3DE",
    "sg:province":"Nottinghamshire",
    "sg:tags":[
        "poster",
        "local",
        "card",
        "authority"
    ],
    "wof:name":"Carter Lane Stores",
    "wof:placetype":"venue"
},
  "geometry": {"coordinates":[-1.1775130033,53.1424407959],"type":"Point"}
}