{
  "type": "Feature",
  "properties": {
    "iso:country":"GB",
    "sg:address":"Westfields, London Road",
    "sg:city":"High Wycombe",
    "sg:classifiers":[
        {
            "category":"Professional",
            "subcategory":"Management & Consulting",
            "type":"Services"
        }
    ],
    "sg:phone":"+44 1494 442330",
    "sg:postcode":"HP11 1HL",
    "sg:province":"Buckinghamshire",
    "sg:tags":[
        "consultant",
        "training"
    ],
    "wof:name":"Rangepath Ltd.",
    "wof:placetype":"venue"
},
  "geometry": {"coordinates":[-0.723269999,51.6216392517],"type":"Point"}
}