{
  "type": "Feature",
  "properties": {
    "addr:full":"1108 Stratford Road, Hall Grn Birmingham West Midlands B28 8AE",
    "addr:housenumber":"1108",
    "addr:postcode":"b28 8ae",
    "addr:street":"Stratford Road Hall Grn",
    "iso:country":"GB",
    "sg:address":"1108 Stratford Road, Hall Grn",
    "sg:city":"Birmingham",
    "sg:classifiers":[
        {
            "category":"Retail",
            "subcategory":"Laundry & Dry Cleaning",
            "type":"Services"
        }
    ],
    "sg:phone":"+44 121 777 7295",
    "sg:postcode":"B28 8AE",
    "sg:province":"West Midlands",
    "sg:tags":[
        "launderette"
    ],
    "wof:name":"Hillcrest Launderette",
    "wof:placetype":"venue"
},
  "geometry": {"coordinates":[-1.8481440544,52.439491272],"type":"Point"}
}