{
  "type": "Feature",
  "properties": {
    "addr:full":"6 Woodsend Road, Flixton Manchester Cheshire M41 8QT",
    "addr:housenumber":"6",
    "addr:postcode":"m41 8qt",
    "addr:street":"Woodsend Road",
    "iso:country":"GB",
    "sg:address":"6 Woodsend Road, Flixton",
    "sg:city":"Manchester",
    "sg:classifiers":[
        {
            "category":"Personal",
            "subcategory":"Beauty Salon",
            "type":"Services"
        },
        {
            "category":"Personal",
            "subcategory":"Barber",
            "type":"Services"
        }
    ],
    "sg:phone":"+44 161 748 7701",
    "sg:postcode":"M41 8QT",
    "sg:province":"Cheshire",
    "sg:tags":[
        "unisex",
        "hairdresser"
    ],
    "wof:name":"New Dimensions",
    "wof:placetype":"venue"
},
  "geometry": {"coordinates":[-2.391438,53.44923],"type":"Point"}
}