{
  "type": "Feature",
  "properties": {
    "iso:country":"GB",
    "sg:address":"Unit 5 Wahdden Business Park, Wahdden",
    "sg:city":"Salisbury",
    "sg:classifiers":[
        {
            "category":"Professional",
            "subcategory":"Printing & Photocopies",
            "type":"Services"
        }
    ],
    "sg:phone":"+44 1794 341511",
    "sg:postcode":"SP5 3HF",
    "sg:province":"Dorset",
    "sg:tags":[
        "plate",
        "lithographic",
        "maker"
    ],
    "wof:name":"Crown Press",
    "wof:placetype":"venue"
},
  "geometry": {"coordinates":[-1.71945,51.034679],"type":"Point"}
}