{
  "type": "Feature",
  "properties": {
    "addr:full":"Office Secretary, 43 Hunslet La Leeds West Yorkshire LS10 1JW",
    "addr:housenumber":"43",
    "addr:postcode":"ls10 1jw",
    "addr:street":"Secretary;La Leeds West",
    "iso:country":"GB",
    "sg:address":"Office Secretary, 43 Hunslet La",
    "sg:city":"Leeds",
    "sg:classifiers":[
        {
            "category":"Place Of Worship",
            "type":"Public Place"
        }
    ],
    "sg:phone":"+44 113 245 1267",
    "sg:postcode":"LS10 1JW",
    "sg:province":"West Yorkshire",
    "wof:name":"Mr C Mundy",
    "wof:placetype":"venue"
},
  "geometry": {"coordinates":[-1.5276399851,53.7816925049],"type":"Point"}
}