{
  "type": "Feature",
  "properties": {
    "iso:country":"GB",
    "sg:address":"Brooklands, Hardings Elms Road, Crays Hill",
    "sg:city":"Billericay",
    "sg:classifiers":[
        {
            "category":"Personal",
            "type":"Services"
        }
    ],
    "sg:postcode":"CM11 2UH",
    "sg:province":"Essex",
    "sg:tags":[
        "wedding"
    ],
    "wof:name":"Aristocars",
    "wof:placetype":"venue"
},
  "geometry": {"coordinates":[0.473225,51.603241],"type":"Point"}
}