{
  "type": "Feature",
  "properties": {
    "addr:full":"228 Barnett Wood Lane Ashtead Surrey KT21 2DB",
    "addr:housenumber":"228",
    "addr:postcode":"kt21 2db",
    "addr:street":"Barnett Wood Lane",
    "iso:country":"GB",
    "sg:address":"228 Barnett Wood Lane",
    "sg:city":"Ashtead",
    "sg:classifiers":[
        {
            "category":"Home & Garden",
            "subcategory":"Home Furnishings",
            "type":"Retail Goods"
        },
        {
            "category":"Home & Garden",
            "subcategory":"Furniture",
            "type":"Retail Goods"
        }
    ],
    "sg:phone":"+44 1372 273210",
    "sg:postcode":"KT21 2DB",
    "sg:province":"Surrey",
    "sg:tags":[
        "soft",
        "sale"
    ],
    "wof:name":"K & C Decor",
    "wof:placetype":"venue"
},
  "geometry": {"coordinates":[-0.3100019991,51.3137283325],"type":"Point"}
}