{
  "type": "Feature",
  "properties": {
    "addr:full":"4 Grants Cres Seaham Durham SR7 7TR",
    "addr:housenumber":"4",
    "addr:postcode":"sr7 7tr",
    "addr:street":"Grants Cres",
    "iso:country":"GB",
    "sg:address":"4 Grants Cres",
    "sg:city":"Seaham",
    "sg:classifiers":[
        {
            "category":"Professional",
            "subcategory":"Accounting & Tax Preparation",
            "type":"Services"
        }
    ],
    "sg:phone":"+44 191 581 8007",
    "sg:postcode":"SR7 7TR",
    "sg:province":"Durham",
    "sg:tags":[
        "accountant"
    ],
    "wof:name":"J G A Accountancy Services",
    "wof:placetype":"venue"
},
  "geometry": {"coordinates":[-1.3406800032,54.8359451294],"type":"Point"}
}