{
  "type": "Feature",
  "properties": {
    "iso:country":"GB",
    "sg:address":"47 Buxton Road",
    "sg:city":"Macclesfield",
    "sg:classifiers":[
        {
            "category":"Food & Beverages",
            "subcategory":"Liquor & Beverages",
            "type":"Retail Goods"
        }
    ],
    "sg:postcode":"SK10 1JX",
    "sg:province":"Cheshire",
    "sg:tags":[
        "beer",
        "spirit",
        "wines"
    ],
    "wof:name":"Bargain Booze Ltd.",
    "wof:placetype":"venue"
},
  "geometry": {"coordinates":[-2.119897,53.260036],"type":"Point"}
}