{
  "type": "Feature",
  "properties": {
    "iso:country":"GB",
    "sg:address":"65 Orchard Road",
    "sg:city":"South Croydon",
    "sg:classifiers":[
        {
            "category":"Building & Trades",
            "subcategory":"Construction",
            "type":"Services"
        }
    ],
    "sg:phone":"+44 20 8651 6299",
    "sg:postcode":"CR2 9LZ",
    "sg:province":"Surrey",
    "sg:tags":[
        "flooring"
    ],
    "wof:name":"Orchard Flooring & Carpet Company",
    "wof:placetype":"venue"
},
  "geometry": {"coordinates":[-0.068315,51.326344],"type":"Point"}
}