{
  "type": "Feature",
  "properties": {
    "addr:full":"Station Road, Woodside Aberdeen Aberdeen City AB24 2UL",
    "addr:postcode":"ab24 2ul",
    "addr:street":"Station Road",
    "iso:country":"GB",
    "sg:address":"Station Road, Woodside",
    "sg:city":"Aberdeen",
    "sg:classifiers":[
        {
            "category":"Health Services",
            "subcategory":"Nursing And Care Facility",
            "type":"Services"
        }
    ],
    "sg:phone":"+44 1224 492323",
    "sg:postcode":"AB24 2UL",
    "sg:province":"Aberdeen City",
    "sg:tags":[
        "home"
    ],
    "wof:name":"Laurels Lodge Nursing Home",
    "wof:placetype":"venue"
},
  "geometry": {"coordinates":[-2.130875,57.172226],"type":"Point"}
}