{
  "type": "Feature",
  "properties": {
    "iso:country":"GB",
    "sg:address":"29-30 Logan Street, Langley Park",
    "sg:city":"Durham",
    "sg:classifiers":[
        {
            "category":"Professional",
            "subcategory":"Art Services",
            "type":"Services"
        }
    ],
    "sg:postcode":"DH7 9YN",
    "sg:province":"Durham",
    "sg:tags":[
        "photographer"
    ],
    "wof:name":"Northlight Photographic",
    "wof:placetype":"venue"
},
  "geometry": {"coordinates":[-1.6718529463,54.8004074097],"type":"Point"}
}