{
  "type": "Feature",
  "properties": {
    "addr:full":"Balmoral Place Dundee Dundee City DD4 8SJ",
    "addr:postcode":"dd4 8sj",
    "addr:street":"Balmoral Place",
    "iso:country":"GB",
    "sg:address":"Balmoral Place",
    "sg:city":"Dundee",
    "sg:classifiers":[
        {
            "category":"Education",
            "subcategory":"School",
            "type":"Public Place"
        }
    ],
    "sg:phone":"+44 1382 436870",
    "sg:postcode":"DD4 8SJ",
    "sg:province":"Dundee City",
    "sg:tags":[
        "local",
        "authority"
    ],
    "wof:name":"Douglas Primary School",
    "wof:placetype":"venue"
},
  "geometry": {"coordinates":[-2.9053640366,56.4799385071],"type":"Point"}
}