{
  "type": "Feature",
  "properties": {
    "iso:country":"GB",
    "sg:address":"61 Connaught St",
    "sg:city":"Bayswater",
    "sg:classifiers":[
        {
            "category":"Retail",
            "subcategory":"Veterinary Services",
            "type":"Services"
        }
    ],
    "sg:phone":"+44 20 7723 0453",
    "sg:postcode":"W2 2AE",
    "sg:province":"Greater London",
    "sg:tags":[
        "surgeon"
    ],
    "wof:name":"Hyde Park Veterinary Centre",
    "wof:placetype":"venue"
},
  "geometry": {"coordinates":[-0.166999,51.51432],"type":"Point"}
}