{
  "type": "Feature",
  "properties": {
    "addr:full":"44 West Don Street Sheffield South Yorkshire S6 3BH",
    "addr:housenumber":"44",
    "addr:postcode":"s6 3bh",
    "addr:street":"West Don Street",
    "iso:country":"GB",
    "sg:address":"44 West Don Street",
    "sg:city":"Sheffield",
    "sg:classifiers":[
        {
            "category":"Manufacturing",
            "subcategory":"Metals",
            "type":"Manufacturing & Wholesale Goods"
        }
    ],
    "sg:phone":"+44 114 285 3699",
    "sg:postcode":"S6 3BH",
    "sg:province":"South Yorkshire",
    "sg:tags":[
        "work",
        "sheet"
    ],
    "wof:name":"G W Metalwork",
    "wof:placetype":"venue"
},
  "geometry": {"coordinates":[-1.4855389595,53.3927955627],"type":"Point"}
}