{
  "type": "Feature",
  "properties": {
    "iso:country":"GB",
    "sg:address":"4 Marine Walk Street",
    "sg:city":"Hythe",
    "sg:classifiers":[
        {
            "category":"Restaurant",
            "type":"Food & Drink"
        }
    ],
    "sg:phone":"+44 1303 260828",
    "sg:postcode":"CT21 5NW",
    "sg:province":"Kent",
    "wof:name":"Studio Restaurant",
    "wof:placetype":"venue"
},
  "geometry": {"coordinates":[1.084596,51.071186],"type":"Point"}
}