{
  "type": "Feature",
  "properties": {
    "iso:country":"GB",
    "sg:address":"1 Scotch Fir Cottages",
    "sg:city":"Gloucester",
    "sg:classifiers":[
        {
            "category":"Building & Trades",
            "subcategory":"Cleaning & Sanitation",
            "type":"Services"
        }
    ],
    "sg:phone":"+44 1452 723509",
    "sg:postcode":"GL2 6SW",
    "sg:province":"Gloucestershire",
    "sg:tags":[
        "dry",
        "control",
        "damp",
        "rot"
    ],
    "wof:name":"Kent Building Services Damp Proofing & Timber Treatment",
    "wof:placetype":"venue"
},
  "geometry": {"coordinates":[-2.30256,51.8256],"type":"Point"}
}