{
  "type": "Feature",
  "properties": {
    "iso:country":"GB",
    "sg:address":"13a Westexe South",
    "sg:city":"Tiverton",
    "sg:classifiers":[
        {
            "category":"Personal",
            "type":"Services"
        }
    ],
    "sg:postcode":"EX16 5DQ",
    "sg:province":"Devon",
    "sg:tags":[
        "wedding"
    ],
    "wof:name":"Scotties Videos",
    "wof:placetype":"venue"
},
  "geometry": {"coordinates":[-3.4961190224,50.9043502808],"type":"Point"}
}