{
  "type": "Feature",
  "properties": {
    "iso:country":"GB",
    "sg:address":"Wath Stones, Newby Wiske",
    "sg:city":"Northallerton",
    "sg:classifiers":[
        {
            "category":"Farming",
            "subcategory":"Livestock Farm",
            "type":"Manufacturing & Wholesale Goods"
        }
    ],
    "sg:phone":"+44 1609 772415",
    "sg:postcode":"DL7 9ER",
    "sg:province":"North Yorkshire",
    "sg:tags":[
        "others"
    ],
    "wof:name":"B W & R A Shaw & Sons",
    "wof:placetype":"venue"
},
  "geometry": {"coordinates":[-1.437415,54.284306],"type":"Point"}
}