{
  "type": "Feature",
  "properties": {
    "iso:country":"GB",
    "sg:address":"1 Childwall Park Avenue",
    "sg:city":"Liverpool",
    "sg:classifiers":[
        {
            "category":"Health Services",
            "subcategory":"Doctor",
            "type":"Services"
        }
    ],
    "sg:phone":"+44 151 722 2280",
    "sg:postcode":"L16 0JE",
    "sg:province":"Merseyside",
    "sg:tags":[
        "practitioners"
    ],
    "wof:name":"Drs Taylor-robinson Butler Allen",
    "wof:placetype":"venue"
},
  "geometry": {"coordinates":[-2.8895170689,53.3945007324],"type":"Point"}
}