{
  "type": "Feature",
  "properties": {
    "addr:full":"P O Box 20 Crowborough East Sussex TN6 1WG",
    "addr:housenumber":"box 20",
    "addr:postcode":"tn6 1wg",
    "addr:street":"P O",
    "iso:country":"GB",
    "sg:address":"P O Box 20",
    "sg:city":"Crowborough",
    "sg:classifiers":[
        {
            "category":"Professional",
            "subcategory":"Computer Services",
            "type":"Services"
        }
    ],
    "sg:phone":"+44 1892 660251",
    "sg:postcode":"TN6 1WG",
    "sg:province":"East Sussex",
    "sg:tags":[
        "system",
        "software"
    ],
    "wof:name":"Kidger Optics Ltd.",
    "wof:placetype":"venue"
},
  "geometry": {"coordinates":[0.171893,51.053196],"type":"Point"}
}