{
  "type": "Feature",
  "properties": {
    "addr:full":"Pendle, Birch Grove Rd, Horsted Keynes Haywards Heath East Sussex RH17 7AP",
    "addr:postcode":"rh17 7ap",
    "addr:street":"Pendle Birch Grove Rd",
    "iso:country":"GB",
    "sg:address":"Pendle, Birch Grove Rd, Horsted Keynes",
    "sg:city":"Haywards Heath",
    "sg:classifiers":[
        {
            "category":"Building & Trades",
            "subcategory":"Construction",
            "type":"Services"
        }
    ],
    "sg:phone":"+44 1825 790998",
    "sg:postcode":"RH17 7AP",
    "sg:province":"East Sussex",
    "sg:tags":[
        "joiner",
        "carpenter"
    ],
    "wof:name":"J.A & W.D Brown",
    "wof:placetype":"venue"
},
  "geometry": {"coordinates":[-0.028284,51.036671],"type":"Point"}
}