{
  "type": "Feature",
  "properties": {
    "addr:full":"8 Suffolk Street Bridgend Bridgend CF31 3AL",
    "addr:housenumber":"8",
    "addr:postcode":"cf31 3al",
    "addr:street":"Suffolk Street",
    "iso:country":"GB",
    "sg:address":"8 Suffolk Street",
    "sg:city":"Bridgend",
    "sg:classifiers":[
        {
            "category":"Building & Trades",
            "subcategory":"Construction",
            "type":"Services"
        }
    ],
    "sg:phone":"+44 1656 653106",
    "sg:postcode":"CF31 3AL",
    "sg:province":"Bridgend",
    "sg:tags":[
        "builder"
    ],
    "wof:name":"Pioneer Builders & Garden Contractors",
    "wof:placetype":"venue"
},
  "geometry": {"coordinates":[-3.5749940872,51.5022621155],"type":"Point"}
}