{
  "type": "Feature",
  "properties": {
    "addr:full":"Kinclaven Farm, Stanley Perth Perth and Kinross PH1 4QN",
    "addr:postcode":"ph1 4qn",
    "addr:street":"Stanley",
    "iso:country":"GB",
    "sg:address":"Kinclaven Farm, Stanley",
    "sg:city":"Perth",
    "sg:classifiers":[
        {
            "category":"Farming",
            "subcategory":"Farm",
            "type":"Manufacturing & Wholesale Goods"
        }
    ],
    "sg:postcode":"PH1 4QN",
    "sg:province":"Perth and Kinross",
    "sg:tags":[
        "mixed",
        "crop"
    ],
    "wof:name":"Allan W Nicholson & Sons",
    "wof:placetype":"venue"
},
  "geometry": {"coordinates":[-3.4510340691,56.4826889038],"type":"Point"}
}