{
  "type": "Feature",
  "properties": {
    "iso:country":"GB",
    "sg:address":"Midlands Office, Holloway St West, Lower Gornal",
    "sg:city":"Dudley",
    "sg:classifiers":[
        {
            "category":"Organizations",
            "subcategory":"Non-profit Organization",
            "type":"Services"
        }
    ],
    "sg:phone":"+44 1902 661865",
    "sg:postcode":"DY3 2DZ",
    "sg:province":"Staffordshire",
    "sg:tags":[
        "organisation",
        "voluntary",
        "charity"
    ],
    "wof:name":"Tearfund",
    "wof:placetype":"venue"
},
  "geometry": {"coordinates":[-2.120666,52.519909],"type":"Point"}
}