{
  "type": "Feature",
  "properties": {
    "iso:country":"GB",
    "sg:address":"51 Gerard St, Ashton In Makerfield",
    "sg:city":"Wigan",
    "sg:classifiers":[
        {
            "category":"Banks & Credit Unions",
            "subcategory":"Financial Services",
            "type":"Services"
        }
    ],
    "sg:postcode":"WN4 9AG",
    "sg:province":"Lancashire",
    "sg:tags":[
        "building",
        "society"
    ],
    "wof:name":"Nationwide Building Society",
    "wof:placetype":"venue"
},
  "geometry": {"coordinates":[-2.637634,53.486481],"type":"Point"}
}