{
  "type": "Feature",
  "properties": {
    "addr:full":"Millers Yard, Long Lane London Greater London N3 2QG",
    "addr:postcode":"n3 2qg",
    "addr:street":"Long Lane",
    "iso:country":"GB",
    "sg:address":"Millers Yard, Long Lane",
    "sg:city":"London",
    "sg:classifiers":[
        {
            "category":"Retail",
            "subcategory":"Auto Repair",
            "type":"Services"
        }
    ],
    "sg:phone":"+44 20 8346 1412",
    "sg:postcode":"N3 2QG",
    "sg:province":"Greater London",
    "sg:tags":[
        "engine",
        "car",
        "specialist"
    ],
    "wof:name":"G Roberts",
    "wof:placetype":"venue"
},
  "geometry": {"coordinates":[-0.188209,51.603813],"type":"Point"}
}