{
  "type": "Feature",
  "properties": {
    "addr:full":"Park House, 117 Park Road Peterborough Cambridgeshire PE1 2TS",
    "addr:housenumber":"117",
    "addr:postcode":"pe1 2ts",
    "addr:street":"Park Road",
    "iso:country":"GB",
    "sg:address":"Park House, 117 Park Road",
    "sg:city":"Peterborough",
    "sg:classifiers":[
        {
            "category":"Professional",
            "subcategory":"Business Services",
            "type":"Services"
        }
    ],
    "sg:phone":"+44 1733 555161",
    "sg:postcode":"PE1 2TS",
    "sg:province":"Cambridgeshire",
    "sg:tags":[
        "distribution"
    ],
    "wof:name":"Frontline Ltd.",
    "wof:placetype":"venue"
},
  "geometry": {"coordinates":[-0.240122,52.57954],"type":"Point"}
}