{
  "type": "Feature",
  "properties": {
    "iso:country":"GB",
    "sg:address":"134 Thatto Heath Road",
    "sg:city":"St Helens",
    "sg:classifiers":[
        {
            "category":"Personal",
            "type":"Services"
        }
    ],
    "sg:phone":"+44 1744 812118",
    "sg:postcode":"WA9 5PE",
    "sg:province":"Cheshire",
    "sg:tags":[
        "tailor"
    ],
    "wof:name":"K Cameron",
    "wof:placetype":"venue"
},
  "geometry": {"coordinates":[-2.759077,53.436806],"type":"Point"}
}