{
  "type": "Feature",
  "properties": {
    "addr:full":"9 Esthers Lane, Weaverham Northwich Cheshire CW8 3JR",
    "addr:housenumber":"9",
    "addr:postcode":"cw8 3jr",
    "addr:street":"Esthers Lane",
    "iso:country":"GB",
    "sg:address":"9 Esthers Lane, Weaverham",
    "sg:city":"Northwich",
    "sg:classifiers":[
        {
            "category":"Building & Trades",
            "subcategory":"Construction",
            "type":"Services"
        }
    ],
    "sg:postcode":"CW8 3JR",
    "sg:province":"Cheshire",
    "sg:tags":[
        "roofing"
    ],
    "wof:name":"Heritage Roofing & Building Maintenance",
    "wof:placetype":"venue"
},
  "geometry": {"coordinates":[-2.573759079,53.2610435486],"type":"Point"}
}