{
  "type": "Feature",
  "properties": {
    "addr:full":"Doncaster Rd, Langold Worksop Nottinghamshire S81 9RU",
    "addr:postcode":"s81 9ru",
    "addr:street":"Doncaster Rd",
    "iso:country":"GB",
    "sg:address":"Doncaster Rd, Langold",
    "sg:city":"Worksop",
    "sg:classifiers":[
        {
            "category":"Travel",
            "subcategory":"Hotels & Motels",
            "type":"Entertainment"
        }
    ],
    "sg:phone":"+44 1909 730301",
    "sg:postcode":"S81 9RU",
    "sg:province":"Nottinghamshire",
    "wof:name":"Langold Hotel",
    "wof:placetype":"venue"
},
  "geometry": {"coordinates":[-1.1130189896,53.357673645],"type":"Point"}
}