{
  "type": "Feature",
  "properties": {
    "iso:country":"GB",
    "sg:address":"Unit, 8, Woodlands",
    "sg:city":"Southampton",
    "sg:classifiers":[
        {
            "category":"Building & Trades",
            "subcategory":"Construction",
            "type":"Services"
        }
    ],
    "sg:phone":"+44 23 8042 8412",
    "sg:postcode":"SO40 7GY",
    "sg:province":"Hampshire",
    "sg:tags":[
        "builder"
    ],
    "wof:name":"J Ward Building Services",
    "wof:placetype":"venue"
},
  "geometry": {"coordinates":[-1.5321700573,50.8941345215],"type":"Point"}
}