{
  "type": "Feature",
  "properties": {
    "iso:country":"GB",
    "sg:address":"Lawnside, Olinda Street",
    "sg:city":"Rhyl",
    "sg:classifiers":[
        {
            "category":"Health Services",
            "subcategory":"Clinic",
            "type":"Services"
        }
    ],
    "sg:phone":"+44 1745 330881",
    "sg:postcode":"LL18 3EP",
    "sg:province":"Conwy",
    "sg:tags":[
        "private"
    ],
    "wof:name":"Child & Adolescent Mental Health Service",
    "wof:placetype":"venue"
},
  "geometry": {"coordinates":[-3.472384,53.311581],"type":"Point"}
}