{
  "type": "Feature",
  "properties": {
    "iso:country":"GB",
    "sg:address":"33 Sunnyside",
    "sg:city":"Bristol",
    "sg:classifiers":[
        {
            "category":"Building & Trades",
            "subcategory":"Equipment Rental",
            "type":"Services"
        }
    ],
    "sg:phone":"+44 1454 775289",
    "sg:postcode":"BS36 2EH",
    "sg:province":"Gloucestershire",
    "sg:tags":[
        "hire",
        "centre"
    ],
    "wof:name":"Andy Hire Services",
    "wof:placetype":"venue"
},
  "geometry": {"coordinates":[-2.478577,51.531456],"type":"Point"}
}