{
  "type": "Feature",
  "properties": {
    "addr:full":"4-6 Market Street Lancaster Lancashire LA1 1HT",
    "addr:housenumber":"4-6",
    "addr:postcode":"la1 1ht",
    "addr:street":"Market Street",
    "iso:country":"GB",
    "sg:address":"4-6 Market Street",
    "sg:city":"Lancaster",
    "sg:classifiers":[
        {
            "category":"Shopping",
            "subcategory":"Beauty & Cosmetics",
            "type":"Retail Goods"
        }
    ],
    "sg:phone":"+44 1524 846420",
    "sg:postcode":"LA1 1HT",
    "sg:province":"Lancashire",
    "sg:tags":[
        "product"
    ],
    "wof:name":"The Body Shop",
    "wof:placetype":"venue"
},
  "geometry": {"coordinates":[-2.800276,54.048988],"type":"Point"}
}