{
  "type": "Feature",
  "properties": {
    "iso:country":"GB",
    "sg:address":"30/32 North St",
    "sg:city":"Hailsham",
    "sg:classifiers":[
        {
            "category":"Professional",
            "subcategory":"Management & Consulting",
            "type":"Services"
        }
    ],
    "sg:postcode":"BN27 1DW",
    "sg:province":"East Sussex",
    "sg:tags":[
        "consultant",
        "business"
    ],
    "wof:name":"Hamblyn Project Management Ltd",
    "wof:placetype":"venue"
},
  "geometry": {"coordinates":[0.257623,50.863495],"type":"Point"}
}