{
  "type": "Feature",
  "properties": {
    "iso:country":"GB",
    "sg:address":"8 Malling Road",
    "sg:city":"Snodland",
    "sg:classifiers":[
        {
            "category":"Retail",
            "subcategory":"Storage",
            "type":"Services"
        }
    ],
    "sg:phone":"+44 1634 240182",
    "sg:postcode":"ME6 5NA",
    "sg:province":"Kent",
    "sg:tags":[
        "household",
        "removal"
    ],
    "wof:name":"McMillan & Son Removals",
    "wof:placetype":"venue"
},
  "geometry": {"coordinates":[0.442159,51.329849],"type":"Point"}
}