{
  "type": "Feature",
  "properties": {
    "addr:full":"10 Argall Av Leyton Greater London E10 7QE",
    "addr:housenumber":"10",
    "addr:postcode":"e10 7qe",
    "addr:street":"Argall Av Leyton",
    "iso:country":"GB",
    "sg:address":"10 Argall Av",
    "sg:city":"Leyton",
    "sg:classifiers":[
        {
            "category":"Home & Garden",
            "subcategory":"Building Materials",
            "type":"Retail Goods"
        }
    ],
    "sg:phone":"+44 20 8539 3550",
    "sg:postcode":"E10 7QE",
    "sg:province":"Greater London",
    "sg:tags":[
        "veneer"
    ],
    "wof:name":"S P Veneers",
    "wof:placetype":"venue"
},
  "geometry": {"coordinates":[-0.039839,51.569786],"type":"Point"}
}