{
  "type": "Feature",
  "properties": {
    "addr:full":"Unit 1 Lhanbryde Indstl Est Elgin Moray IV30 3PD",
    "addr:housenumber":"unit 1",
    "addr:postcode":"iv30 3pd",
    "addr:street":"Lhanbryde Indstl Est",
    "iso:country":"GB",
    "sg:address":"Unit 1 Lhanbryde Indstl Est",
    "sg:city":"Elgin",
    "sg:classifiers":[
        {
            "category":"Shopping",
            "subcategory":"Hobbies, Toys, & Games",
            "type":"Retail Goods"
        }
    ],
    "sg:postcode":"IV30 3PD",
    "sg:province":"Moray",
    "wof:name":"Bain,John C,& Son",
    "wof:placetype":"venue"
},
  "geometry": {"coordinates":[-3.317868948,57.6493682861],"type":"Point"}
}