{
  "type": "Feature",
  "properties": {
    "addr:full":"222 Stratford Road, Shirley Solihull West Midlands B90 3AG",
    "addr:housenumber":"222",
    "addr:postcode":"b90 3ag",
    "addr:street":"Stratford Road",
    "iso:country":"GB",
    "sg:address":"222 Stratford Road, Shirley",
    "sg:city":"Solihull",
    "sg:classifiers":[
        {
            "category":"Food & Beverages",
            "subcategory":"Meat & Fish",
            "type":"Retail Goods"
        }
    ],
    "sg:postcode":"B90 3AG",
    "sg:province":"West Midlands",
    "sg:tags":[
        "butcher"
    ],
    "wof:name":"David-John (Butchers) Ltd.",
    "wof:placetype":"venue"
},
  "geometry": {"coordinates":[-1.827194,52.411289],"type":"Point"}
}