{
  "type": "Feature",
  "properties": {
    "iso:country":"GB",
    "sg:address":"1 Berrycroft, Willingham",
    "sg:city":"Cambridge",
    "sg:classifiers":[
        {
            "category":"Professional",
            "subcategory":"Lawyer & Legal Services",
            "type":"Services"
        }
    ],
    "sg:phone":"+44 1954 261444",
    "sg:postcode":"CB4 5JX",
    "sg:province":"Cambridgeshire",
    "sg:tags":[
        "solicitor"
    ],
    "wof:name":"Wilcox & Lewis",
    "wof:placetype":"venue"
},
  "geometry": {"coordinates":[0.0562190004,52.3102340698],"type":"Point"}
}