{
  "type": "Feature",
  "properties": {
    "addr:full":"3 Holmfirth Road, Meltham Huddersfield West Yorkshire HD7 3AA",
    "addr:housenumber":"3",
    "addr:postcode":"hd7 3aa",
    "addr:street":"Holmfirth Road;West",
    "iso:country":"GB",
    "sg:address":"3 Holmfirth Road, Meltham",
    "sg:city":"Huddersfield",
    "sg:classifiers":[
        {
            "category":"Food & Beverages",
            "subcategory":"Bakery",
            "type":"Retail Goods"
        }
    ],
    "sg:phone":"+44 1484 851645",
    "sg:postcode":"HD7 3AA",
    "sg:province":"West Yorkshire",
    "sg:tags":[
        "confectionery"
    ],
    "wof:name":"Meltham Patisserie",
    "wof:placetype":"venue"
},
  "geometry": {"coordinates":[-1.7826800346,53.6469497681],"type":"Point"}
}