{
  "type": "Feature",
  "properties": {
    "iso:country":"GB",
    "sg:address":"21 Pinfold Road, Thurmaston",
    "sg:city":"Leicester",
    "sg:classifiers":[
        {
            "category":"Professional",
            "subcategory":"Engineering",
            "type":"Services"
        }
    ],
    "sg:phone":"+44 116 269 5999",
    "sg:postcode":"LE4 8AS",
    "sg:province":"Leicestershire",
    "sg:tags":[
        "engineer"
    ],
    "wof:name":"Glendower Cutting Tools Ltd",
    "wof:placetype":"venue"
},
  "geometry": {"coordinates":[-1.105515,52.673862],"type":"Point"}
}