{
  "type": "Feature",
  "properties": {
    "iso:country":"GB",
    "sg:address":"23 Shaw Brow, Whittle-le-woods",
    "sg:city":"Chorley",
    "sg:classifiers":[
        {
            "category":"Government",
            "subcategory":"Post Office",
            "type":"Public Place"
        }
    ],
    "sg:phone":"+44 1257 262019",
    "sg:postcode":"PR6 7LE",
    "sg:province":"Lancashire",
    "wof:name":"Whittle-le-Woods Post Office",
    "wof:placetype":"venue"
},
  "geometry": {"coordinates":[-2.6382639408,53.6852111816],"type":"Point"}
}