{
  "type": "Feature",
  "properties": {
    "addr:full":"Crossgill Washington Tyne and Wear NE37 1UA",
    "addr:postcode":"ne37 1ua",
    "iso:country":"GB",
    "sg:address":"Crossgill",
    "sg:city":"Washington",
    "sg:classifiers":[
        {
            "category":"Education",
            "subcategory":"School",
            "type":"Public Place"
        },
        {
            "category":"Government",
            "subcategory":"Office",
            "type":"Public Place"
        }
    ],
    "sg:phone":"+44 191 219 3650",
    "sg:postcode":"NE37 1UA",
    "sg:province":"Tyne and Wear",
    "sg:tags":[
        "local",
        "authority"
    ],
    "wof:name":"Albany Primary School",
    "wof:placetype":"venue"
},
  "geometry": {"coordinates":[-1.5350060463,54.909198761],"type":"Point"}
}