{
  "type": "Feature",
  "properties": {
    "addr:full":"136 Oxford Street, Bilston Wolverhampton West Midlands WV14 7DP",
    "addr:housenumber":"136",
    "addr:postcode":"wv14 7dp",
    "addr:street":"Oxford Street",
    "iso:country":"GB",
    "sg:address":"136 Oxford Street, Bilston",
    "sg:city":"Wolverhampton",
    "sg:classifiers":[
        {
            "category":"Home & Garden",
            "subcategory":"Home Furnishings",
            "type":"Retail Goods"
        }
    ],
    "sg:phone":"+44 1902 354466",
    "sg:postcode":"WV14 7DP",
    "sg:province":"West Midlands",
    "sg:tags":[
        "blind",
        "curtain",
        "fitting"
    ],
    "wof:name":"Ferndale Designs",
    "wof:placetype":"venue"
},
  "geometry": {"coordinates":[-2.066233,52.562702],"type":"Point"}
}