{
  "type": "Feature",
  "properties": {
    "iso:country":"GB",
    "sg:address":"Grange Road, Tiptree",
    "sg:city":"Colchester",
    "sg:classifiers":[
        {
            "category":"Shopping",
            "type":"Retail Goods"
        }
    ],
    "sg:postcode":"CO5 0QQ",
    "sg:province":"Essex",
    "sg:tags":[
        "part",
        "accessory"
    ],
    "wof:name":"Audiline",
    "wof:placetype":"venue"
},
  "geometry": {"coordinates":[0.7453340292,51.8164634705],"type":"Point"}
}