{
  "type": "Feature",
  "properties": {
    "iso:country":"GB",
    "sg:address":"87 Aldershot Rd",
    "sg:city":"Fleet",
    "sg:classifiers":[
        {
            "category":"Professional",
            "subcategory":"Lawyer & Legal Services",
            "type":"Services"
        }
    ],
    "sg:phone":"+44 1252 812707",
    "sg:postcode":"GU13 0JY",
    "sg:province":"Dorset",
    "wof:name":"Legal Systems Thames Valley",
    "wof:placetype":"venue"
},
  "geometry": {"coordinates":[-0.838344,51.260189],"type":"Point"}
}