{
  "type": "Feature",
  "properties": {
    "addr:full":"55 Belle Vue Road, Easton Bristol City of Bristol BS5 6DR",
    "addr:housenumber":"55",
    "addr:postcode":"bs5 6dr",
    "addr:street":"Belle Vue Road",
    "iso:country":"GB",
    "sg:address":"55 Belle Vue Road, Easton",
    "sg:city":"Bristol",
    "sg:classifiers":[
        {
            "category":"Government",
            "subcategory":"Post Office",
            "type":"Public Place"
        }
    ],
    "sg:phone":"+44 117 951 0888",
    "sg:postcode":"BS5 6DR",
    "sg:province":"City of Bristol",
    "wof:name":"Lwr Easton Post Office",
    "wof:placetype":"venue"
},
  "geometry": {"coordinates":[-2.691005,51.478325],"type":"Point"}
}