{
  "type": "Feature",
  "properties": {
    "iso:country":"GB",
    "sg:address":"Elm House, 17-19 Claygate Lane",
    "sg:city":"Thames Ditton",
    "sg:classifiers":[
        {
            "category":"Building & Trades",
            "subcategory":"Pest Control",
            "type":"Services"
        }
    ],
    "sg:phone":"+44 20 8398 8441",
    "sg:postcode":"KT7 0DL",
    "sg:province":"Surrey",
    "sg:tags":[
        "woodworm"
    ],
    "wof:name":"Guaranteed Wood & Damp Treatment",
    "wof:placetype":"venue"
},
  "geometry": {"coordinates":[-0.3332409859,51.3827781677],"type":"Point"}
}