{
  "type": "Feature",
  "properties": {
    "iso:country":"GB",
    "sg:address":"83 High Street",
    "sg:city":"Gillingham",
    "sg:classifiers":[
        {
            "category":"Home & Garden",
            "subcategory":"Home Furnishings",
            "type":"Retail Goods"
        }
    ],
    "sg:phone":"+44 1634 578969",
    "sg:postcode":"ME7 1BL",
    "sg:province":"Kent",
    "sg:tags":[
        "blind",
        "curtain",
        "fitting"
    ],
    "wof:name":"Curtain World",
    "wof:placetype":"venue"
},
  "geometry": {"coordinates":[0.54333,51.388618],"type":"Point"}
}