{
  "type": "Feature",
  "properties": {
    "addr:full":"Halifax House, Dale Rd North, Darley Dale Matlock Derbyshire DE4 2FT",
    "addr:postcode":"de4 2ft",
    "addr:street":"Dale Rd North Darley Dale",
    "iso:country":"GB",
    "sg:address":"Halifax House, Dale Rd North, Darley Dale",
    "sg:city":"Matlock",
    "sg:classifiers":[
        {
            "category":"Taxi",
            "type":"Transportation"
        }
    ],
    "sg:phone":"+44 1629 735000",
    "sg:postcode":"DE4 2FT",
    "sg:province":"Derbyshire",
    "sg:tags":[
        "mini",
        "cab"
    ],
    "wof:name":"J B Taxis",
    "wof:placetype":"venue"
},
  "geometry": {"coordinates":[-1.599496007,53.1669921875],"type":"Point"}
}