{
  "type": "Feature",
  "properties": {
    "addr:full":"Dovecote House, 38 Wollaton Rd, Beeston Nottingham Nottinghamshire NG9 2NR",
    "addr:housenumber":"38",
    "addr:postcode":"ng9 2nr",
    "addr:street":"Wollaton Rd",
    "iso:country":"GB",
    "sg:address":"Dovecote House, 38 Wollaton Rd, Beeston",
    "sg:city":"Nottingham",
    "sg:classifiers":[
        {
            "category":"Health Services",
            "subcategory":"Clinic",
            "type":"Services"
        }
    ],
    "sg:phone":"+44 115 925 4281",
    "sg:postcode":"NG9 2NR",
    "sg:province":"Nottinghamshire",
    "sg:tags":[
        "nh"
    ],
    "wof:name":"Beeston Clinic",
    "wof:placetype":"venue"
},
  "geometry": {"coordinates":[-1.2162330151,52.9277076721],"type":"Point"}
}