{
  "type": "Feature",
  "properties": {
    "addr:full":"Little Gambia Padstow Cornwall PL28 8LB",
    "addr:postcode":"pl28 8lb",
    "iso:country":"GB",
    "sg:address":"Little Gambia",
    "sg:city":"Padstow",
    "sg:classifiers":[
        {
            "category":"Organizations",
            "subcategory":"Non-profit Organization",
            "type":"Services"
        }
    ],
    "sg:phone":"+44 1841 533059",
    "sg:postcode":"PL28 8LB",
    "sg:province":"Cornwall",
    "sg:tags":[
        "organisation",
        "voluntary",
        "charity"
    ],
    "wof:name":"Royal National Lifeboat Institution",
    "wof:placetype":"venue"
},
  "geometry": {"coordinates":[-4.9418392181,50.5373649597],"type":"Point"}
}