{
  "type": "Feature",
  "properties": {
    "iso:country":"GB",
    "sg:address":"99 Norfolk Street",
    "sg:city":"Glasgow",
    "sg:classifiers":[
        {
            "category":"Education",
            "subcategory":"School",
            "type":"Public Place"
        }
    ],
    "sg:phone":"+44 141 429 6017",
    "sg:postcode":"G5 9LQ",
    "sg:province":"Glasgow City",
    "sg:tags":[
        "local",
        "authority"
    ],
    "wof:name":"ST JOHN'S R C PRIMARY SCHOOL",
    "wof:placetype":"venue"
},
  "geometry": {"coordinates":[-4.256526,55.852283],"type":"Point"}
}