{
  "type": "Feature",
  "properties": {
    "addr:full":"Nuttaberry Works Bideford Devon EX39 4DU",
    "addr:postcode":"ex39 4du",
    "iso:country":"GB",
    "sg:address":"Nuttaberry Works",
    "sg:city":"Bideford",
    "sg:classifiers":[
        {
            "category":"Manufacturing",
            "subcategory":"Building Materials",
            "type":"Manufacturing & Wholesale Goods"
        }
    ],
    "sg:phone":"+44 1237 473421",
    "sg:postcode":"EX39 4DU",
    "sg:province":"Devon",
    "sg:tags":[
        "merchant",
        "builder"
    ],
    "wof:name":"Jewson Ltd.",
    "wof:placetype":"venue"
},
  "geometry": {"coordinates":[-4.2020630836,51.0092086792],"type":"Point"}
}