{
  "type": "Feature",
  "properties": {
    "addr:full":"84 Walton Street Oxford Oxfordshire OX2 6EA",
    "addr:housenumber":"84",
    "addr:postcode":"ox2 6ea",
    "addr:street":"Walton Street",
    "iso:country":"GB",
    "sg:address":"84 Walton Street",
    "sg:city":"Oxford",
    "sg:classifiers":[
        {
            "category":"Fast Food",
            "type":"Food & Drink"
        }
    ],
    "sg:postcode":"OX2 6EA",
    "sg:province":"Oxfordshire",
    "sg:tags":[
        "away",
        "take"
    ],
    "wof:name":"Foodprep Ltd.",
    "wof:placetype":"venue"
},
  "geometry": {"coordinates":[-1.268247962,51.7615890503],"type":"Point"}
}