{
  "type": "Feature",
  "properties": {
    "iso:country":"GB",
    "sg:address":"Newland",
    "sg:city":"Ulverston",
    "sg:classifiers":[
        {
            "category":"Professional",
            "subcategory":"Business Services",
            "type":"Services"
        }
    ],
    "sg:postcode":"LA12 7QG",
    "sg:province":"Cumbria",
    "sg:tags":[
        "distribution"
    ],
    "wof:name":"Future Prospects",
    "wof:placetype":"venue"
},
  "geometry": {"coordinates":[-3.0755400658,54.2084007263],"type":"Point"}
}