{
  "type": "Feature",
  "properties": {
    "iso:country":"GB",
    "sg:address":"Royal Albert House, Sheet Street",
    "sg:city":"Windsor",
    "sg:classifiers":[
        {
            "category":"Organizations",
            "subcategory":"Community Association",
            "type":"Services"
        }
    ],
    "sg:phone":"+44 1753 831311",
    "sg:postcode":"SL4 1BE",
    "sg:province":"Berkshire",
    "sg:tags":[
        "relation",
        "public"
    ],
    "wof:name":"Devonshire Marketing",
    "wof:placetype":"venue"
},
  "geometry": {"coordinates":[-0.606069,51.47963],"type":"Point"}
}