{
  "type": "Feature",
  "properties": {
    "addr:full":"20 Richmond Terrace Blackburn Lancashire BB1 7BL",
    "addr:housenumber":"20",
    "addr:postcode":"bb1 7bl",
    "addr:street":"Richmond Terrace",
    "iso:country":"GB",
    "sg:address":"20 Richmond Terrace",
    "sg:city":"Blackburn",
    "sg:classifiers":[
        {
            "category":"Shopping",
            "subcategory":"Optician",
            "type":"Retail Goods"
        },
        {
            "category":"Health Services",
            "subcategory":"Optometrist",
            "type":"Services"
        }
    ],
    "sg:phone":"+44 1254 59443",
    "sg:postcode":"BB1 7BL",
    "sg:province":"Lancashire",
    "sg:tags":[
        "opthalmic",
        "ophthalmic"
    ],
    "wof:name":"Alan J Spurrett",
    "wof:placetype":"venue"
},
  "geometry": {"coordinates":[-2.4840610027,53.7507362366],"type":"Point"}
}