{
  "type": "Feature",
  "properties": {
    "addr:full":"26 Kingswood Rise, Four Marks Alton Hampshire GU34 5BD",
    "addr:housenumber":"26",
    "addr:postcode":"gu34 5bd",
    "addr:street":"Kingswood Rise",
    "iso:country":"GB",
    "sg:address":"26 Kingswood Rise, Four Marks",
    "sg:city":"Alton",
    "sg:classifiers":[
        {
            "category":"Professional",
            "subcategory":"Computer Services",
            "type":"Services"
        }
    ],
    "sg:phone":"+44 7802 677553",
    "sg:postcode":"GU34 5BD",
    "sg:province":"Hampshire",
    "sg:tags":[
        "system",
        "software"
    ],
    "wof:name":"Camdaw Ltd",
    "wof:placetype":"venue"
},
  "geometry": {"coordinates":[-1.058217,51.10759],"type":"Point"}
}