{
  "type": "Feature",
  "properties": {
    "iso:country":"GB",
    "sg:address":"215 Ley Street",
    "sg:city":"Ilford",
    "sg:classifiers":[
        {
            "category":"Building & Trades",
            "subcategory":"Plumbing",
            "type":"Services"
        }
    ],
    "sg:postcode":"IG1 4BL",
    "sg:province":"Essex",
    "sg:tags":[
        "merchant",
        "plumbers'"
    ],
    "wof:name":"Lovitt's Ltd",
    "wof:placetype":"venue"
},
  "geometry": {"coordinates":[0.0786029994,51.5626716614],"type":"Point"}
}