{
  "type": "Feature",
  "properties": {
    "addr:full":"39 Grove Street Wilmslow Cheshire SK9 1DT",
    "addr:housenumber":"39",
    "addr:postcode":"sk9 1dt",
    "addr:street":"Grove Street",
    "iso:country":"GB",
    "sg:address":"39 Grove Street",
    "sg:city":"Wilmslow",
    "sg:classifiers":[
        {
            "category":"Banks & Credit Unions",
            "subcategory":"Bank",
            "type":"Services"
        }
    ],
    "sg:phone":"+44 845 765 4321",
    "sg:postcode":"SK9 1DT",
    "sg:province":"Cheshire",
    "wof:name":"Abbey National Plc",
    "wof:placetype":"venue"
},
  "geometry": {"coordinates":[-2.231863,53.326389],"type":"Point"}
}