{
  "type": "Feature",
  "properties": {
    "iso:country":"GB",
    "sg:address":"8a Ratcliffe Drive, Stoke Gifford",
    "sg:city":"Bristol",
    "sg:classifiers":[
        {
            "category":"Professional",
            "subcategory":"Printing & Photocopies",
            "type":"Services"
        }
    ],
    "sg:phone":"+44 117 931 1110",
    "sg:postcode":"BS34 8UE",
    "sg:province":"Gloucestershire",
    "sg:tags":[
        "photocopier"
    ],
    "wof:name":"DCH Reprotech",
    "wof:placetype":"venue"
},
  "geometry": {"coordinates":[-2.5465209484,51.517829895],"type":"Point"}
}