{
  "type": "Feature",
  "properties": {
    "addr:full":"60 Deepdene Avenue Rayleigh Essex SS6 9LG",
    "addr:housenumber":"60",
    "addr:postcode":"ss6 9lg",
    "addr:street":"Deepdene Avenue",
    "iso:country":"GB",
    "sg:address":"60 Deepdene Avenue",
    "sg:city":"Rayleigh",
    "sg:classifiers":[
        {
            "category":"Professional",
            "subcategory":"Art Services",
            "type":"Services"
        }
    ],
    "sg:postcode":"SS6 9LG",
    "sg:province":"Essex",
    "sg:tags":[
        "photographer"
    ],
    "wof:name":"Jeff Goodman Photography",
    "wof:placetype":"venue"
},
  "geometry": {"coordinates":[0.603663981,51.5978240967],"type":"Point"}
}