{
  "type": "Feature",
  "properties": {
    "iso:country":"GB",
    "sg:address":"42 Dale Street, Milnrow",
    "sg:city":"Rochdale",
    "sg:classifiers":[
        {
            "category":"Travel",
            "subcategory":"Travel Agent",
            "type":"Entertainment"
        }
    ],
    "sg:phone":"+44 1706 523399",
    "sg:postcode":"OL16 4HS",
    "sg:province":"Lancashire",
    "wof:name":"Travel Trend",
    "wof:placetype":"venue"
},
  "geometry": {"coordinates":[-2.111249,53.610355],"type":"Point"}
}