{
  "type": "Feature",
  "properties": {
    "addr:full":"5-6 North Street Isleworth Greater London TW7 6BT",
    "addr:housenumber":"5-6",
    "addr:postcode":"tw7 6bt",
    "addr:street":"North Street",
    "iso:country":"GB",
    "sg:address":"5-6 North Street",
    "sg:city":"Isleworth",
    "sg:classifiers":[
        {
            "category":"Organizations",
            "subcategory":"Community Association",
            "type":"Services"
        },
        {
            "category":"Organizations",
            "subcategory":"Membership Organization",
            "type":"Services"
        }
    ],
    "sg:phone":"+44 20 8560 6282",
    "sg:postcode":"TW7 6BT",
    "sg:province":"Greater London",
    "sg:tags":[
        "club",
        "social"
    ],
    "wof:name":"The Royal British Legion",
    "wof:placetype":"venue"
},
  "geometry": {"coordinates":[-0.3241,51.469772],"type":"Point"}
}