{
  "type": "Feature",
  "properties": {
    "addr:full":"Catherine Street Aberdeen Aberdeen City AB1 1EU",
    "addr:postcode":"ab1 1eu",
    "addr:street":"Catherine Street",
    "iso:country":"GB",
    "sg:address":"Catherine Street",
    "sg:city":"Aberdeen",
    "sg:classifiers":[
        {
            "category":"Community Center",
            "type":"Public Place"
        },
        {
            "category":"Government",
            "subcategory":"Office",
            "type":"Public Place"
        }
    ],
    "sg:phone":"+44 1224 640853",
    "sg:postcode":"AB1 1EU",
    "sg:province":"Aberdeen City",
    "sg:tags":[
        "local",
        "centre"
    ],
    "wof:name":"Catherine Street Community Centre",
    "wof:placetype":"venue"
},
  "geometry": {"coordinates":[-2.1040620804,57.1535873413],"type":"Point"}
}