{
  "type": "Feature",
  "properties": {
    "addr:full":"2a Winchester Road Andover Hampshire SP10 2EG",
    "addr:housenumber":"2a",
    "addr:postcode":"sp10 2eg",
    "addr:street":"Winchester Road",
    "iso:country":"GB",
    "sg:address":"2a Winchester Road",
    "sg:city":"Andover",
    "sg:classifiers":[
        {
            "category":"Health Services",
            "subcategory":"Dentist",
            "type":"Services"
        }
    ],
    "sg:phone":"+44 1264 352683",
    "sg:postcode":"SP10 2EG",
    "sg:province":"Hampshire",
    "sg:tags":[
        "technician",
        "dental"
    ],
    "wof:name":"Andover Dental Laboratory",
    "wof:placetype":"venue"
},
  "geometry": {"coordinates":[-1.478658,51.203979],"type":"Point"}
}