{
  "type": "Feature",
  "properties": {
    "addr:full":"Castlefield House, 29 Elesmere Street Manchester Cheshire M15 4LZ",
    "addr:housenumber":"29",
    "addr:postcode":"m15 4lz",
    "addr:street":"Elesmere Street",
    "iso:country":"GB",
    "sg:address":"Castlefield House, 29 Elesmere Street",
    "sg:city":"Manchester",
    "sg:classifiers":[
        {
            "category":"Professional",
            "subcategory":"Engineering",
            "type":"Services"
        }
    ],
    "sg:phone":"+44 161 832 7802",
    "sg:postcode":"M15 4LZ",
    "sg:province":"Cheshire",
    "sg:tags":[
        "consultant",
        "structural"
    ],
    "wof:name":"Shepherd Gilmour Environment Ltd.",
    "wof:placetype":"venue"
},
  "geometry": {"coordinates":[-2.2640750408,53.4707145691],"type":"Point"}
}