{
  "type": "Feature",
  "properties": {
    "addr:full":"101 Henllys Porth Bridgend CF39 9PJ",
    "addr:housenumber":"101",
    "addr:postcode":"cf39 9pj",
    "addr:street":"Henllys Porth",
    "iso:country":"GB",
    "sg:address":"101 Henllys",
    "sg:city":"Porth",
    "sg:classifiers":[
        {
            "category":"Taxi",
            "type":"Transportation"
        },
        {
            "category":"Military Area",
            "subcategory":"Air Force Base",
            "type":"Public Place"
        }
    ],
    "sg:phone":"+44 1443 681510",
    "sg:postcode":"CF39 9PJ",
    "sg:province":"Bridgend",
    "sg:tags":[
        "mini",
        "hire",
        "private",
        "cab"
    ],
    "wof:name":"P & I TAXIS",
    "wof:placetype":"venue"
},
  "geometry": {"coordinates":[-3.4175050259,51.5990333557],"type":"Point"}
}