{
  "type": "Feature",
  "properties": {
    "addr:full":"81 Gunnersbury Lane, Acton Town Acton Greater London W3 8HQ",
    "addr:housenumber":"81",
    "addr:postcode":"w3 8hq",
    "addr:street":"Gunnersbury Lane",
    "iso:country":"GB",
    "sg:address":"81 Gunnersbury Lane, Acton Town",
    "sg:city":"Acton",
    "sg:classifiers":[
        {
            "category":"Professional",
            "subcategory":"Accounting & Tax Preparation",
            "type":"Services"
        }
    ],
    "sg:phone":"+44 20 8993 3132",
    "sg:postcode":"W3 8HQ",
    "sg:province":"Greater London",
    "sg:tags":[
        "consultant"
    ],
    "wof:name":"Travellers Tax Consultants",
    "wof:placetype":"venue"
},
  "geometry": {"coordinates":[-0.2793579996,51.5043487549],"type":"Point"}
}