{
  "type": "Feature",
  "properties": {
    "addr:full":"Link Farm, Wiggonholt Pulborough West Sussex RH20 2EL",
    "addr:postcode":"rh20 2el",
    "addr:street":"Wiggonholt",
    "iso:country":"GB",
    "sg:address":"Link Farm, Wiggonholt",
    "sg:city":"Pulborough",
    "sg:classifiers":[
        {
            "category":"Professional",
            "subcategory":"Computer Services",
            "type":"Services"
        }
    ],
    "sg:phone":"+44 7990 597960",
    "sg:postcode":"RH20 2EL",
    "sg:province":"West Sussex",
    "sg:tags":[
        "system",
        "software"
    ],
    "wof:name":"Xylopace Ltd",
    "wof:placetype":"venue"
},
  "geometry": {"coordinates":[-0.511879,50.957077],"type":"Point"}
}