{
  "type": "Feature",
  "properties": {
    "addr:full":"Rookwood Cott, Frithill Great Missenden Buckinghamshire HP16 0QS",
    "addr:postcode":"hp16 0qs",
    "iso:country":"GB",
    "sg:address":"Rookwood Cott, Frithill",
    "sg:city":"Great Missenden",
    "sg:classifiers":[
        {
            "category":"Autos & Motor Vehicles",
            "subcategory":"Automobile Sales",
            "type":"Retail Goods"
        }
    ],
    "sg:postcode":"HP16 0QS",
    "sg:province":"Buckinghamshire",
    "sg:tags":[
        "car"
    ],
    "wof:name":"O'Shea,J,",
    "wof:placetype":"venue"
},
  "geometry": {"coordinates":[-0.700268,51.693611],"type":"Point"}
}