{
  "type": "Feature",
  "properties": {
    "addr:full":"7 Hillside, Orwell Royston Bedfordshire SG8 5QZ",
    "addr:housenumber":"7",
    "addr:postcode":"sg8 5qz",
    "addr:street":"Hillside",
    "iso:country":"GB",
    "sg:address":"7 Hillside, Orwell",
    "sg:city":"Royston",
    "sg:classifiers":[
        {
            "category":"Communications",
            "subcategory":"News Services",
            "type":"Services"
        }
    ],
    "sg:postcode":"SG8 5QZ",
    "sg:province":"Bedfordshire",
    "sg:tags":[
        "journalist"
    ],
    "wof:name":"Phillip J Hastings",
    "wof:placetype":"venue"
},
  "geometry": {"coordinates":[-0.030069,52.0825],"type":"Point"}
}