{
  "type": "Feature",
  "properties": {
    "iso:country":"GB",
    "sg:address":"Wardalls Gro, Avonley Rd, New Cross",
    "sg:city":"New Cross",
    "sg:classifiers":[
        {
            "category":"Health Services",
            "subcategory":"Clinic",
            "type":"Services"
        }
    ],
    "sg:phone":"+44 20 7639 9646",
    "sg:postcode":"SE14 5ER",
    "sg:province":"Greater London",
    "sg:tags":[
        "nh"
    ],
    "wof:name":"New Cross Family Planning Clinic",
    "wof:placetype":"venue"
},
  "geometry": {"coordinates":[-0.040459,51.47496],"type":"Point"}
}