{
  "type": "Feature",
  "properties": {
    "addr:full":"82 High St Tranent East Lothian EH33 1HH",
    "addr:housenumber":"82",
    "addr:postcode":"eh33 1hh",
    "addr:street":"High St",
    "iso:country":"GB",
    "sg:address":"82 High St",
    "sg:city":"Tranent",
    "sg:classifiers":[
        {
            "category":"Organizations",
            "subcategory":"Non-profit Organization",
            "type":"Services"
        }
    ],
    "sg:phone":"+44 1875 616400",
    "sg:postcode":"EH33 1HH",
    "sg:province":"East Lothian",
    "sg:tags":[
        "organisation",
        "voluntary",
        "charity"
    ],
    "wof:name":"Volunteeer Development (East Lothian)",
    "wof:placetype":"venue"
},
  "geometry": {"coordinates":[-2.9329080582,55.9436187744],"type":"Point"}
}