{
  "type": "Feature",
  "properties": {
    "iso:country":"GB",
    "sg:address":"158 Elliott Street",
    "sg:city":"Manchester",
    "sg:classifiers":[
        {
            "category":"Fast Food",
            "type":"Food & Drink"
        }
    ],
    "sg:phone":"+44 1942 883485",
    "sg:postcode":"M29 8DS",
    "sg:province":"Greater Manchester",
    "sg:tags":[
        "away",
        "take"
    ],
    "wof:name":"Dineaway",
    "wof:placetype":"venue"
},
  "geometry": {"coordinates":[-2.463979,53.513279],"type":"Point"}
}