{
  "type": "Feature",
  "properties": {
    "iso:country":"GB",
    "sg:address":"33 Belmont Rd",
    "sg:city":"Uxbridge",
    "sg:classifiers":[
        {
            "category":"Cinema",
            "subcategory":"Movie Rental",
            "type":"Entertainment"
        }
    ],
    "sg:phone":"+44 1895 274600",
    "sg:postcode":"UB8 1QT",
    "sg:province":"Buckinghamshire",
    "sg:tags":[
        "video",
        "library"
    ],
    "wof:name":"Blockbuster",
    "wof:placetype":"venue"
},
  "geometry": {"coordinates":[-0.478708,51.547882],"type":"Point"}
}