{
  "type": "Feature",
  "properties": {
    "iso:country":"GB",
    "sg:address":"Edderston Farm House",
    "sg:city":"Peebles",
    "sg:classifiers":[
        {
            "category":"Manufacturing",
            "subcategory":"Glass & Minerals",
            "type":"Manufacturing & Wholesale Goods"
        }
    ],
    "sg:phone":"+44 1721 720716",
    "sg:postcode":"EH45 9JE",
    "sg:province":"Scottish Borders",
    "sg:tags":[
        "chalk",
        "stone",
        "slate"
    ],
    "wof:name":"Brague Ltd",
    "wof:placetype":"venue"
},
  "geometry": {"coordinates":[-3.110477,55.640285],"type":"Point"}
}