{
  "type": "Feature",
  "properties": {
    "addr:full":"Middlebridge Street Romsey Hampshire SO51 8QL",
    "addr:postcode":"so51 8ql",
    "addr:street":"Middlebridge Street",
    "iso:country":"GB",
    "sg:address":"Middlebridge Street",
    "sg:city":"Romsey",
    "sg:classifiers":[
        {
            "category":"Social Services",
            "subcategory":"Adult Care",
            "type":"Services"
        }
    ],
    "sg:phone":"+44 1794 517230",
    "sg:postcode":"SO51 8QL",
    "sg:province":"Hampshire",
    "sg:tags":[
        "housing",
        "sheltered"
    ],
    "wof:name":"Homemead House",
    "wof:placetype":"venue"
},
  "geometry": {"coordinates":[-1.501162,50.985725],"type":"Point"}
}