{
  "type": "Feature",
  "properties": {
    "addr:full":"19 Wood Street Kingston-upon-thames Greater London KT1 1TY",
    "addr:housenumber":"19",
    "addr:postcode":"kt1 1ty",
    "addr:street":"Wood Street",
    "iso:country":"GB",
    "sg:address":"19 Wood Street",
    "sg:city":"Kingston-upon-thames",
    "sg:classifiers":[
        {
            "category":"Bars & Pubs",
            "type":"Food & Drink"
        }
    ],
    "sg:phone":"+44 20 8549 3712",
    "sg:postcode":"KT1 1TY",
    "sg:province":"Greater London",
    "sg:tags":[
        "pubs",
        "inn"
    ],
    "wof:name":"Corporate Catering Co. Ltd.",
    "wof:placetype":"venue"
},
  "geometry": {"coordinates":[-0.3056130111,51.41248703],"type":"Point"}
}