{
  "type": "Feature",
  "properties": {
    "iso:country":"GB",
    "sg:address":"5 Ilkeston Rd",
    "sg:city":"Nottingham",
    "sg:classifiers":[
        {
            "category":"Shopping",
            "subcategory":"Clothing, Apparel, & Fashions",
            "type":"Retail Goods"
        }
    ],
    "sg:phone":"+44 115 978 8001",
    "sg:postcode":"NG7 3GD",
    "sg:province":"Nottinghamshire",
    "sg:tags":[
        "clothing",
        "fabric"
    ],
    "wof:name":"Daniel A Hanson",
    "wof:placetype":"venue"
},
  "geometry": {"coordinates":[-1.162158,52.955753],"type":"Point"}
}