{
  "type": "Feature",
  "properties": {
    "iso:country":"GB",
    "sg:address":"54 Victoria Street",
    "sg:city":"Littleborough",
    "sg:classifiers":[
        {
            "category":"Manufacturing",
            "subcategory":"Textiles",
            "type":"Manufacturing & Wholesale Goods"
        }
    ],
    "sg:postcode":"OL15 9DB",
    "sg:province":"Lancashire",
    "sg:tags":[
        "made-up"
    ],
    "wof:name":"Clark & Fielden Jacyln Danny",
    "wof:placetype":"venue"
},
  "geometry": {"coordinates":[-2.095791,53.644295],"type":"Point"}
}