{
  "type": "Feature",
  "properties": {
    "addr:full":"601 Attercliffe Road Sheffield South Yorkshire S9 3RD",
    "addr:housenumber":"601",
    "addr:postcode":"s9 3rd",
    "addr:street":"Attercliffe Road",
    "iso:country":"GB",
    "sg:address":"601 Attercliffe Road",
    "sg:city":"Sheffield",
    "sg:classifiers":[
        {
            "category":"Restaurant",
            "type":"Food & Drink"
        }
    ],
    "sg:postcode":"S9 3RD",
    "sg:province":"South Yorkshire",
    "wof:name":"Attercliffe Bakery",
    "wof:placetype":"venue"
},
  "geometry": {"coordinates":[-1.433379,53.393017],"type":"Point"}
}