{
  "type": "Feature",
  "properties": {
    "iso:country":"GB",
    "sg:address":"299 Lichfield Rd, Four Oaks",
    "sg:city":"Sutton Coldfield",
    "sg:classifiers":[
        {
            "category":"Health Services",
            "subcategory":"Dentist",
            "type":"Services"
        }
    ],
    "sg:phone":"+44 121 308 6075",
    "sg:postcode":"B74 4BZ",
    "sg:province":"Staffordshire",
    "wof:name":"David J Armstrong",
    "wof:placetype":"venue"
},
  "geometry": {"coordinates":[-1.830886,52.588215],"type":"Point"}
}