{
  "type": "Feature",
  "properties": {
    "addr:full":"Woodstock Farm, Astley Road, Irlam Manchester Greater Manchester M44 5LQ",
    "addr:postcode":"m44 5lq",
    "addr:street":"Astley Road",
    "iso:country":"GB",
    "sg:address":"Woodstock Farm, Astley Road, Irlam",
    "sg:city":"Manchester",
    "sg:classifiers":[
        {
            "category":"Farming",
            "subcategory":"Livestock Farm",
            "type":"Manufacturing & Wholesale Goods"
        }
    ],
    "sg:phone":"+44 161 775 2347",
    "sg:postcode":"M44 5LQ",
    "sg:province":"Greater Manchester",
    "sg:tags":[
        "others"
    ],
    "wof:name":"H Upton & Son",
    "wof:placetype":"venue"
},
  "geometry": {"coordinates":[-2.44142,53.449261],"type":"Point"}
}