{
  "type": "Feature",
  "properties": {
    "iso:country":"GB",
    "sg:address":"50 Cavendish Street",
    "sg:city":"Sheffield",
    "sg:classifiers":[
        {
            "category":"Government",
            "subcategory":"Office",
            "type":"Public Place"
        }
    ],
    "sg:phone":"+44 114 278 7020",
    "sg:postcode":"S3 7RZ",
    "sg:province":"South Yorkshire",
    "sg:tags":[
        "education",
        "agency",
        "authority"
    ],
    "wof:name":"Wilson Carlisle College of Evangelism",
    "wof:placetype":"venue"
},
  "geometry": {"coordinates":[-1.480417,53.37867],"type":"Point"}
}