{
  "type": "Feature",
  "properties": {
    "addr:full":"121 Victoria Rd Scarborough North Yorkshire YO11 1SP",
    "addr:housenumber":"121",
    "addr:postcode":"yo11 1sp",
    "addr:street":"Victoria Rd",
    "iso:country":"GB",
    "sg:address":"121 Victoria Rd",
    "sg:city":"Scarborough",
    "sg:classifiers":[
        {
            "category":"Organizations",
            "subcategory":"Non-profit Organization",
            "type":"Services"
        }
    ],
    "sg:phone":"+44 1723 500576",
    "sg:postcode":"YO11 1SP",
    "sg:province":"North Yorkshire",
    "sg:tags":[
        "organisation",
        "voluntary",
        "charity"
    ],
    "wof:name":"Scarborough Mind Self Harm Service",
    "wof:placetype":"venue"
},
  "geometry": {"coordinates":[-0.40812,54.280186],"type":"Point"}
}