{
  "type": "Feature",
  "properties": {
    "addr:full":"90-91 Sidwell Street Exeter Devon EX4 6PH",
    "addr:housenumber":"90-91",
    "addr:postcode":"ex4 6ph",
    "addr:street":"Sidwell Street",
    "iso:country":"GB",
    "sg:address":"90-91 Sidwell Street",
    "sg:city":"Exeter",
    "sg:classifiers":[
        {
            "category":"Shopping",
            "subcategory":"Computers & Home Electronics",
            "type":"Retail Goods"
        }
    ],
    "sg:postcode":"EX4 6PH",
    "sg:province":"Devon",
    "sg:tags":[
        "hi-fi",
        "centre"
    ],
    "wof:name":"Howards (Exeter) Ltd.",
    "wof:placetype":"venue"
},
  "geometry": {"coordinates":[-3.5214579105,50.728767395],"type":"Point"}
}