{
  "type": "Feature",
  "properties": {
    "iso:country":"GB",
    "sg:address":"Unit 5a Falmouth Business Park",
    "sg:city":"Falmouth",
    "sg:classifiers":[
        {
            "category":"Professional",
            "subcategory":"Printing & Photocopies",
            "type":"Services"
        }
    ],
    "sg:phone":"+44 1326 312619",
    "sg:postcode":"TR11 4SZ",
    "sg:province":"Cornwall",
    "sg:tags":[
        "printer"
    ],
    "wof:name":"Scantec Repro Dtp Bureau",
    "wof:placetype":"venue"
},
  "geometry": {"coordinates":[-5.0938310623,50.1484565735],"type":"Point"}
}