{
  "type": "Feature",
  "properties": {
    "addr:full":"Unit 10 Boundary Bsns Park, Wheatley Road Oxford Oxfordshire OX44 9DY",
    "addr:housenumber":"unit 10",
    "addr:postcode":"ox44 9dy",
    "addr:street":"Boundary Bsns Park Wheatley Road",
    "iso:country":"GB",
    "sg:address":"Unit 10 Boundary Bsns Park, Wheatley Road",
    "sg:city":"Oxford",
    "sg:classifiers":[
        {
            "category":"Professional",
            "subcategory":"Accounting & Tax Preparation",
            "type":"Services"
        }
    ],
    "sg:phone":"+44 1865 361457",
    "sg:postcode":"OX44 9DY",
    "sg:province":"Oxfordshire",
    "sg:tags":[
        "accountant"
    ],
    "wof:name":"Aries & Co",
    "wof:placetype":"venue"
},
  "geometry": {"coordinates":[-1.1530989408,51.7268981934],"type":"Point"}
}