{
  "type": "Feature",
  "properties": {
    "iso:country":"GB",
    "sg:address":"Unit C, Chandlers Row",
    "sg:city":"Colchester",
    "sg:classifiers":[
        {
            "category":"Wholesale",
            "subcategory":"Metals & Minerals",
            "type":"Manufacturing & Wholesale Goods"
        }
    ],
    "sg:phone":"+44 1206 797698",
    "sg:postcode":"CO1 2HG",
    "sg:province":"Essex",
    "sg:tags":[
        "aluminium",
        "stockholder"
    ],
    "wof:name":"Eastern Aluminium Co. Ltd.",
    "wof:placetype":"venue"
},
  "geometry": {"coordinates":[0.9213600159,51.8806724548],"type":"Point"}
}