{
  "type": "Feature",
  "properties": {
    "iso:country":"GB",
    "sg:address":"49 Congleton Road, Biddulph",
    "sg:city":"Stoke-on-trent",
    "sg:classifiers":[
        {
            "category":"Personal",
            "subcategory":"Barber",
            "type":"Services"
        }
    ],
    "sg:phone":"+44 1782 517600",
    "sg:postcode":"ST8 6DY",
    "sg:province":"Staffordshire",
    "sg:tags":[
        "men's",
        "hairdresser"
    ],
    "wof:name":"Biddle Barbers",
    "wof:placetype":"venue"
},
  "geometry": {"coordinates":[-2.1723880768,53.1190223694],"type":"Point"}
}