{
  "type": "Feature",
  "properties": {
    "addr:full":"17 Margaret Street Beaumaris Isle of Anglesey LL58 8DN",
    "addr:housenumber":"17",
    "addr:postcode":"ll58 8dn",
    "addr:street":"Margaret Street",
    "iso:country":"GB",
    "sg:address":"17 Margaret Street",
    "sg:city":"Beaumaris",
    "sg:classifiers":[
        {
            "category":"Home & Garden",
            "subcategory":"Home Furnishings",
            "type":"Retail Goods"
        },
        {
            "category":"Home & Garden",
            "subcategory":"Furniture",
            "type":"Retail Goods"
        }
    ],
    "sg:phone":"+44 1248 811287",
    "sg:postcode":"LL58 8DN",
    "sg:province":"Isle of Anglesey",
    "sg:tags":[
        "soft",
        "sale"
    ],
    "wof:name":"Nan's Place",
    "wof:placetype":"venue"
},
  "geometry": {"coordinates":[-4.093834,53.263016],"type":"Point"}
}