{
  "type": "Feature",
  "properties": {
    "iso:country":"GB",
    "sg:address":"Racecourse Lane",
    "sg:city":"Much Wenlock",
    "sg:classifiers":[
        {
            "category":"Education",
            "subcategory":"School",
            "type":"Public Place"
        }
    ],
    "sg:phone":"+44 1952 727634",
    "sg:postcode":"TF13 6JG",
    "sg:province":"Shropshire",
    "sg:tags":[
        "local",
        "authority"
    ],
    "wof:name":"Much Wenlock County Primary School",
    "wof:placetype":"venue"
},
  "geometry": {"coordinates":[-2.556708,52.594105],"type":"Point"}
}