{
  "type": "Feature",
  "properties": {
    "iso:country":"GB",
    "sg:address":"31 Armstrong Road, Manor Trading Estate",
    "sg:city":"Benfleet",
    "sg:classifiers":[
        {
            "category":"Retail",
            "subcategory":"Auto Repair",
            "type":"Services"
        }
    ],
    "sg:phone":"+44 1268 794545",
    "sg:postcode":"SS7 4PW",
    "sg:province":"Essex",
    "sg:tags":[
        "modification",
        "garage"
    ],
    "wof:name":"Vail Motors Ltd.",
    "wof:placetype":"venue"
},
  "geometry": {"coordinates":[0.562605,51.573505],"type":"Point"}
}