{
  "type": "Feature",
  "properties": {
    "iso:country":"GB",
    "sg:address":"Burnbank Gardens",
    "sg:city":"Glasgow",
    "sg:classifiers":[
        {
            "category":"Social Services",
            "subcategory":"Retirement Home",
            "type":"Services"
        }
    ],
    "sg:phone":"+44 141 332 0952",
    "sg:postcode":"G20 6HD",
    "sg:province":"Glasgow City",
    "sg:tags":[
        "residential",
        "care"
    ],
    "wof:name":"Burnbank House",
    "wof:placetype":"venue"
},
  "geometry": {"coordinates":[-4.272567,55.873775],"type":"Point"}
}