{
  "type": "Feature",
  "properties": {
    "addr:full":"158 Hartford Rd Huntingdon Cambridgeshire PE18 7XQ",
    "addr:housenumber":"158",
    "addr:postcode":"pe18 7xq",
    "addr:street":"Hartford Rd",
    "iso:country":"GB",
    "sg:address":"158 Hartford Rd",
    "sg:city":"Huntingdon",
    "sg:classifiers":[
        {
            "category":"Home & Garden",
            "subcategory":"Hardware",
            "type":"Retail Goods"
        }
    ],
    "sg:phone":"+44 1480 451949",
    "sg:postcode":"PE18 7XQ",
    "sg:province":"Cambridgeshire",
    "sg:tags":[
        "equipment",
        "wire",
        "cable"
    ],
    "wof:name":"P.E.L",
    "wof:placetype":"venue"
},
  "geometry": {"coordinates":[-0.166693002,52.3346366882],"type":"Point"}
}