{
  "type": "Feature",
  "properties": {
    "addr:full":"45 Shore Street Inverness Highland IV1 1NT",
    "addr:housenumber":"45",
    "addr:postcode":"iv1 1nt",
    "addr:street":"Shore Street",
    "iso:country":"GB",
    "sg:address":"45 Shore Street",
    "sg:city":"Inverness",
    "sg:classifiers":[
        {
            "category":"Professional",
            "subcategory":"Detective & Security Services",
            "type":"Services"
        }
    ],
    "sg:postcode":"IV1 1NT",
    "sg:province":"Highland",
    "sg:tags":[
        "locksmith"
    ],
    "wof:name":"Highland Locksmiths & Security Systems Ltd.",
    "wof:placetype":"venue"
},
  "geometry": {"coordinates":[-4.229683,57.483898],"type":"Point"}
}