{
  "type": "Feature",
  "properties": {
    "addr:full":"Kincarrathie House, Pitcullen Crescent Perth Perth and Kinross PH2 7HX",
    "addr:postcode":"ph2 7hx",
    "addr:street":"Pitcullen Crescent",
    "iso:country":"GB",
    "sg:address":"Kincarrathie House, Pitcullen Crescent",
    "sg:city":"Perth",
    "sg:classifiers":[
        {
            "category":"Social Services",
            "subcategory":"Retirement Home",
            "type":"Services"
        }
    ],
    "sg:phone":"+44 1738 621828",
    "sg:postcode":"PH2 7HX",
    "sg:province":"Perth and Kinross",
    "sg:tags":[
        "residential",
        "care"
    ],
    "wof:name":"Kincarrathie Trust",
    "wof:placetype":"venue"
},
  "geometry": {"coordinates":[-3.416739,56.407318],"type":"Point"}
}