{
  "type": "Feature",
  "properties": {
    "iso:country":"GB",
    "sg:address":"85 Stroud Grn Road",
    "sg:city":"London",
    "sg:classifiers":[
        {
            "category":"Banks & Credit Unions",
            "subcategory":"Financial Services",
            "type":"Services"
        }
    ],
    "sg:phone":"+44 20 7281 0789",
    "sg:postcode":"N4 3EG",
    "sg:province":"Greater London",
    "sg:tags":[
        "adviser"
    ],
    "wof:name":"Regent Cavendish (I F A) Ltd.",
    "wof:placetype":"venue"
},
  "geometry": {"coordinates":[-0.110677,51.568493],"type":"Point"}
}