{
  "type": "Feature",
  "properties": {
    "addr:full":"2 Green Walk Dartford Kent DA1 4JL",
    "addr:housenumber":"2",
    "addr:postcode":"da1 4jl",
    "addr:street":"Green Walk",
    "iso:country":"GB",
    "sg:address":"2 Green Walk",
    "sg:city":"Dartford",
    "sg:classifiers":[
        {
            "category":"Health Services",
            "subcategory":"Dentist",
            "type":"Services"
        }
    ],
    "sg:phone":"+44 1322 554800",
    "sg:postcode":"DA1 4JL",
    "sg:province":"Kent",
    "sg:tags":[
        "technician",
        "dental"
    ],
    "wof:name":"Crayford Denture Service",
    "wof:placetype":"venue"
},
  "geometry": {"coordinates":[0.179352,51.453251],"type":"Point"}
}