{
  "type": "Feature",
  "properties": {
    "iso:country":"GB",
    "sg:address":"Westcote House, Radway",
    "sg:city":"Warwick",
    "sg:classifiers":[
        {
            "category":"Manufacturing",
            "subcategory":"Food",
            "type":"Manufacturing & Wholesale Goods"
        }
    ],
    "sg:phone":"+44 1295 670561",
    "sg:postcode":"CV35 0UQ",
    "sg:province":"Warwickshire",
    "sg:tags":[
        "additive",
        "colourings",
        "flavouring"
    ],
    "wof:name":"Bruckner-werke",
    "wof:placetype":"venue"
},
  "geometry": {"coordinates":[-1.458852,52.131725],"type":"Point"}
}