{
  "type": "Feature",
  "properties": {
    "addr:full":"Freer Street Walsall West Midlands WS1 1QF",
    "addr:postcode":"ws1 1qf",
    "addr:street":"Freer Street",
    "iso:country":"GB",
    "sg:address":"Freer Street",
    "sg:city":"Walsall",
    "sg:classifiers":[
        {
            "category":"Parking",
            "type":"Transportation"
        }
    ],
    "sg:phone":"+44 20 7499 7050",
    "sg:postcode":"WS1 1QF",
    "sg:province":"West Midlands",
    "sg:tags":[
        "car",
        "park"
    ],
    "wof:name":"Ncp",
    "wof:placetype":"venue"
},
  "geometry": {"coordinates":[-1.9789580107,52.5843772888],"type":"Point"}
}