{
  "type": "Feature",
  "properties": {
    "iso:country":"GB",
    "sg:address":"Slack St",
    "sg:city":"Macclesfield",
    "sg:classifiers":[
        {
            "category":"Wholesale",
            "subcategory":"Fruits & Vegetables",
            "type":"Manufacturing & Wholesale Goods"
        }
    ],
    "sg:phone":"+44 1625 427226",
    "sg:postcode":"SK11 7JP",
    "sg:province":"Cheshire",
    "wof:name":"H Franklin & Son",
    "wof:placetype":"venue"
},
  "geometry": {"coordinates":[-2.119539,53.24971],"type":"Point"}
}