{
  "type": "Feature",
  "properties": {
    "iso:country":"GB",
    "sg:address":"1 Springhill Road",
    "sg:city":"Scarborough",
    "sg:classifiers":[
        {
            "category":"Manufacturing",
            "subcategory":"Signs",
            "type":"Manufacturing & Wholesale Goods"
        }
    ],
    "sg:phone":"+44 1723 500864",
    "sg:postcode":"YO12 4AE",
    "sg:province":"North Yorkshire",
    "sg:tags":[
        "writer"
    ],
    "wof:name":"Sign Design",
    "wof:placetype":"venue"
},
  "geometry": {"coordinates":[-0.416551,54.274143],"type":"Point"}
}