{
  "type": "Feature",
  "properties": {
    "iso:country":"GB",
    "sg:address":"St Peter's Avenue",
    "sg:city":"Sowerby Bridge",
    "sg:classifiers":[
        {
            "category":"Education",
            "subcategory":"School",
            "type":"Public Place"
        },
        {
            "category":"Government",
            "subcategory":"Office",
            "type":"Public Place"
        }
    ],
    "sg:phone":"+44 1422 831360",
    "sg:postcode":"HX6 1BL",
    "sg:province":"West Yorkshire",
    "sg:tags":[
        "local",
        "authority"
    ],
    "wof:name":"Sacred Heart Catholic Primary School",
    "wof:placetype":"venue"
},
  "geometry": {"coordinates":[-1.92347,53.705399],"type":"Point"}
}