{
  "type": "Feature",
  "properties": {
    "addr:full":"7 Lanark Square London Greater London E14 9RE",
    "addr:housenumber":"7",
    "addr:postcode":"e14 9re",
    "addr:street":"Lanark Square",
    "iso:country":"GB",
    "sg:address":"7 Lanark Square",
    "sg:city":"London",
    "sg:classifiers":[
        {
            "category":"Professional",
            "subcategory":"Management & Consulting",
            "type":"Services"
        }
    ],
    "sg:phone":"+44 20 7537 1222",
    "sg:postcode":"E14 9RE",
    "sg:province":"Greater London",
    "sg:tags":[
        "consultant",
        "business"
    ],
    "wof:name":"Icofin (U K) Ltd.",
    "wof:placetype":"venue"
},
  "geometry": {"coordinates":[-0.015389,51.495564],"type":"Point"}
}