{
  "type": "Feature",
  "properties": {
    "iso:country":"GB",
    "sg:address":"2 Slape Moor Cottages, Croford",
    "sg:city":"Taunton",
    "sg:classifiers":[
        {
            "category":"Retail",
            "subcategory":"Funeral Services",
            "type":"Services"
        }
    ],
    "sg:postcode":"TA4 2TR",
    "sg:province":"Devon",
    "wof:name":"Philip R Seddon & Sons",
    "wof:placetype":"venue"
},
  "geometry": {"coordinates":[-3.28295,51.039532],"type":"Point"}
}