{
  "type": "Feature",
  "properties": {
    "addr:full":"Market St, Church Accrington Lancashire BB5 0DN",
    "addr:postcode":"bb5 0dn",
    "addr:street":"Market St;Accrington",
    "iso:country":"GB",
    "sg:address":"Market St, Church",
    "sg:city":"Accrington",
    "sg:classifiers":[
        {
            "category":"Autos & Motor Vehicles",
            "subcategory":"Automobile Sales",
            "type":"Retail Goods"
        }
    ],
    "sg:phone":"+44 1254 231431",
    "sg:postcode":"BB5 0DN",
    "sg:province":"Lancashire",
    "sg:tags":[
        "commercial"
    ],
    "wof:name":"Lancashire Leyland Daf Ltd",
    "wof:placetype":"venue"
},
  "geometry": {"coordinates":[-2.391669035,53.7497940063],"type":"Point"}
}