{
  "type": "Feature",
  "properties": {
    "iso:country":"GB",
    "sg:address":"Unit 3 Marlborough Centre, Marlborough Square",
    "sg:city":"Coalville",
    "sg:classifiers":[
        {
            "category":"Insurance",
            "subcategory":"Insurance Agent",
            "type":"Services"
        }
    ],
    "sg:postcode":"LE67 3WD",
    "sg:province":"Leicestershire",
    "wof:name":"Swinton",
    "wof:placetype":"venue"
},
  "geometry": {"coordinates":[-1.3723059893,52.7187843323],"type":"Point"}
}