{
  "type": "Feature",
  "properties": {
    "addr:full":"34 Bach Mill Dr Birmingham West Midlands B28 0XN",
    "addr:housenumber":"34",
    "addr:postcode":"b28 0xn",
    "addr:street":"Bach Mill Dr",
    "iso:country":"GB",
    "sg:address":"34 Bach Mill Dr",
    "sg:city":"Birmingham",
    "sg:classifiers":[
        {
            "category":"Home & Garden",
            "subcategory":"Household Appliances",
            "type":"Retail Goods"
        }
    ],
    "sg:phone":"+44 7956 485324",
    "sg:postcode":"B28 0XN",
    "sg:province":"West Midlands",
    "sg:tags":[
        "cleaner",
        "domestic",
        "vacuum"
    ],
    "wof:name":"David's Spares",
    "wof:placetype":"venue"
},
  "geometry": {"coordinates":[-1.856038,52.409634],"type":"Point"}
}