{
  "type": "Feature",
  "properties": {
    "iso:country":"GB",
    "sg:address":"Chesterfield Road",
    "sg:city":"Sheffield",
    "sg:classifiers":[
        {
            "category":"Autos & Motor Vehicles",
            "subcategory":"Fuel & Gas Station",
            "type":"Retail Goods"
        }
    ],
    "sg:phone":"+44 114 258 3120",
    "sg:postcode":"S8 0RS",
    "sg:province":"Derbyshire",
    "sg:tags":[
        "hr",
        "petrol"
    ],
    "wof:name":"Woodbank Service Stn",
    "wof:placetype":"venue"
},
  "geometry": {"coordinates":[-1.4759789705,53.3577461243],"type":"Point"}
}