{
  "type": "Feature",
  "properties": {
    "iso:country":"GB",
    "sg:address":"10 Six Acres",
    "sg:city":"Shrewsbury",
    "sg:classifiers":[
        {
            "category":"Real Estate",
            "subcategory":"Architect",
            "type":"Services"
        }
    ],
    "sg:postcode":"SY3 6AF",
    "sg:province":"Shropshire",
    "wof:name":"Beeches Design",
    "wof:placetype":"venue"
},
  "geometry": {"coordinates":[-2.772372,52.69614],"type":"Point"}
}