{
  "type": "Feature",
  "properties": {
    "iso:country":"GB",
    "sg:address":"Beer Hackett",
    "sg:city":"Sherborne",
    "sg:classifiers":[
        {
            "category":"Building & Trades",
            "subcategory":"Construction",
            "type":"Services"
        }
    ],
    "sg:phone":"+44 1935 872428",
    "sg:postcode":"DT9 6QP",
    "sg:province":"Dorset",
    "sg:tags":[
        "builder"
    ],
    "wof:name":"D R Hornsby",
    "wof:placetype":"venue"
},
  "geometry": {"coordinates":[-2.5583291054,50.9202613831],"type":"Point"}
}