{
  "type": "Feature",
  "properties": {
    "addr:full":"291 Rugby Road, Binley Woods Coventry Warwickshire CV3 2BE",
    "addr:housenumber":"291",
    "addr:postcode":"cv3 2be",
    "addr:street":"Rugby Road",
    "iso:country":"GB",
    "sg:address":"291 Rugby Road, Binley Woods",
    "sg:city":"Coventry",
    "sg:classifiers":[
        {
            "category":"Professional",
            "subcategory":"Engineering",
            "type":"Services"
        }
    ],
    "sg:phone":"+44 24 7654 4833",
    "sg:postcode":"CV3 2BE",
    "sg:province":"Warwickshire",
    "sg:tags":[
        "contractor",
        "electrical",
        "engineer"
    ],
    "wof:name":"M H Electrical Installations Ltd.",
    "wof:placetype":"venue"
},
  "geometry": {"coordinates":[-1.416178,52.393852],"type":"Point"}
}