{
  "type": "Feature",
  "properties": {
    "iso:country":"GB",
    "sg:address":"14 Green Bank",
    "sg:city":"Bolton",
    "sg:classifiers":[
        {
            "category":"Shopping",
            "subcategory":"Musical Instruments",
            "type":"Retail Goods"
        }
    ],
    "sg:phone":"+44 1204 528996",
    "sg:postcode":"BL2 3NG",
    "sg:province":"Lancashire",
    "sg:tags":[
        "organ",
        "accessory"
    ],
    "wof:name":"Barmby Music Service",
    "wof:placetype":"venue"
},
  "geometry": {"coordinates":[-2.3882360458,53.5976715088],"type":"Point"}
}