{
  "type": "Feature",
  "properties": {
    "addr:full":"232 London Road, Charlton Kings Cheltenham Gloucestershire GL52 6HW",
    "addr:housenumber":"232",
    "addr:postcode":"gl52 6hw",
    "addr:street":"London Road",
    "iso:country":"GB",
    "sg:address":"232 London Road, Charlton Kings",
    "sg:city":"Cheltenham",
    "sg:classifiers":[
        {
            "category":"Health Services",
            "subcategory":"Dentist",
            "type":"Services"
        }
    ],
    "sg:phone":"+44 1242 512444",
    "sg:postcode":"GL52 6HW",
    "sg:province":"Gloucestershire",
    "wof:name":"Arden House Dental Practice",
    "wof:placetype":"venue"
},
  "geometry": {"coordinates":[-2.056787,51.889862],"type":"Point"}
}