{
  "type": "Feature",
  "properties": {
    "addr:full":"3 Halton Drive, Timperley Altrincham Cheshire WA15 6AU",
    "addr:housenumber":"3",
    "addr:postcode":"wa15 6au",
    "addr:street":"Halton Drive",
    "iso:country":"GB",
    "sg:address":"3 Halton Drive, Timperley",
    "sg:city":"Altrincham",
    "sg:classifiers":[
        {
            "category":"Building & Trades",
            "subcategory":"Construction",
            "type":"Services"
        }
    ],
    "sg:phone":"+44 161 962 9808",
    "sg:postcode":"WA15 6AU",
    "sg:province":"Cheshire",
    "sg:tags":[
        "door",
        "replacement"
    ],
    "wof:name":"A & D Door Systems Ltd.",
    "wof:placetype":"venue"
},
  "geometry": {"coordinates":[-2.3214299679,53.4073486328],"type":"Point"}
}