{
  "type": "Feature",
  "properties": {
    "addr:full":"Kerlyn House, Churchstanton Taunton Devon TA3 7QD",
    "addr:postcode":"ta3 7qd",
    "addr:street":"Churchstanton;Devon",
    "iso:country":"GB",
    "sg:address":"Kerlyn House, Churchstanton",
    "sg:city":"Taunton",
    "sg:classifiers":[
        {
            "category":"Insurance",
            "subcategory":"Insurance Agent",
            "type":"Services"
        }
    ],
    "sg:postcode":"TA3 7QD",
    "sg:province":"Devon",
    "sg:tags":[
        "broker"
    ],
    "wof:name":"Kerlyn Financial Services",
    "wof:placetype":"venue"
},
  "geometry": {"coordinates":[-3.145879,50.924259],"type":"Point"}
}