{
  "type": "Feature",
  "properties": {
    "addr:full":"17 North Street Wareham Dorset BH20 4AB",
    "addr:housenumber":"17",
    "addr:postcode":"bh20 4ab",
    "addr:street":"North Street",
    "iso:country":"GB",
    "sg:address":"17 North Street",
    "sg:city":"Wareham",
    "sg:classifiers":[
        {
            "category":"Restaurant",
            "type":"Food & Drink"
        }
    ],
    "sg:postcode":"BH20 4AB",
    "sg:province":"Dorset",
    "wof:name":"Anglebury House",
    "wof:placetype":"venue"
},
  "geometry": {"coordinates":[-2.1104679108,50.686882019],"type":"Point"}
}