{
  "type": "Feature",
  "properties": {
    "addr:full":"48 Woodlands Rd Glasgow Glasgow City G3 6UR",
    "addr:housenumber":"48",
    "addr:postcode":"g3 6ur",
    "addr:street":"Woodlands Rd",
    "iso:country":"GB",
    "sg:address":"48 Woodlands Rd",
    "sg:city":"Glasgow",
    "sg:classifiers":[
        {
            "category":"Food & Beverages",
            "subcategory":"Specialty",
            "type":"Retail Goods"
        }
    ],
    "sg:phone":"+44 141 353 3278",
    "sg:postcode":"G3 6UR",
    "sg:province":"Glasgow City",
    "sg:tags":[
        "product",
        "health"
    ],
    "wof:name":"West End Wholefoods Limited",
    "wof:placetype":"venue"
},
  "geometry": {"coordinates":[-4.2723960876,55.8684272766],"type":"Point"}
}