{
  "type": "Feature",
  "properties": {
    "addr:full":"Unit 1, Midleton Indstl Est Guildford Surrey GU2 8XW",
    "addr:housenumber":"unit 1",
    "addr:postcode":"gu2 8xw",
    "addr:street":"Indstl Est",
    "iso:country":"GB",
    "sg:address":"Unit 1, Midleton Indstl Est",
    "sg:city":"Guildford",
    "sg:classifiers":[
        {
            "category":"Building & Trades",
            "subcategory":"Landscaping Services",
            "type":"Services"
        }
    ],
    "sg:postcode":"GU2 8XW",
    "sg:province":"Surrey",
    "sg:tags":[
        "landscape",
        "contractor"
    ],
    "wof:name":"Errington,Christopher,",
    "wof:placetype":"venue"
},
  "geometry": {"coordinates":[-0.5843399763,51.2462692261],"type":"Point"}
}