{
  "type": "Feature",
  "properties": {
    "addr:full":"106 Spinney Lane, Aspley Guise Milton Keynes Bedfordshire MK17 8JL",
    "addr:housenumber":"106",
    "addr:postcode":"mk17 8jl",
    "addr:street":"Spinney Lane;Guise",
    "iso:country":"GB",
    "sg:address":"106 Spinney Lane, Aspley Guise",
    "sg:city":"Milton Keynes",
    "sg:classifiers":[
        {
            "category":"Health Services",
            "subcategory":"Health Practitioner",
            "type":"Services"
        }
    ],
    "sg:phone":"+44 1908 281412",
    "sg:postcode":"MK17 8JL",
    "sg:province":"Bedfordshire",
    "sg:tags":[
        "homoeopathic"
    ],
    "wof:name":"Steven Erlic DIHom MA",
    "wof:placetype":"venue"
},
  "geometry": {"coordinates":[-0.6454610229,52.0093955994],"type":"Point"}
}