{
  "type": "Feature",
  "properties": {
    "addr:full":"9 St Peters Garden Yateley Hampshire GU46 6JY",
    "addr:housenumber":"9",
    "addr:postcode":"gu46 6jy",
    "addr:street":"St Peters",
    "iso:country":"GB",
    "sg:address":"9 St Peters Garden",
    "sg:city":"Yateley",
    "sg:classifiers":[
        {
            "category":"Home & Garden",
            "subcategory":"Carpets & Floor Coverings",
            "type":"Retail Goods"
        }
    ],
    "sg:postcode":"GU46 6JY",
    "sg:province":"Hampshire",
    "sg:tags":[
        "cleaner",
        "upholstery"
    ],
    "wof:name":"D & H Cleaning Services",
    "wof:placetype":"venue"
},
  "geometry": {"coordinates":[-0.8272439837,51.339466095],"type":"Point"}
}