{
  "type": "Feature",
  "properties": {
    "addr:full":"81 High Street Dalkeith City of Edinburgh EH22 1JA",
    "addr:housenumber":"81",
    "addr:postcode":"eh22 1ja",
    "addr:street":"High Street",
    "iso:country":"GB",
    "sg:address":"81 High Street",
    "sg:city":"Dalkeith",
    "sg:classifiers":[
        {
            "category":"Recreation",
            "subcategory":"Amusement Park",
            "type":"Entertainment"
        }
    ],
    "sg:phone":"+44 131 660 1224",
    "sg:postcode":"EH22 1JA",
    "sg:province":"City of Edinburgh",
    "sg:tags":[
        "arcade",
        "activity"
    ],
    "wof:name":"Gold Rush Amusements",
    "wof:placetype":"venue"
},
  "geometry": {"coordinates":[-3.0700600147,55.8945732117],"type":"Point"}
}