{
  "type": "Feature",
  "properties": {
    "iso:country":"GB",
    "sg:address":"Wellesley Road, Tharston",
    "sg:city":"Norwich",
    "sg:classifiers":[
        {
            "category":"Retail",
            "subcategory":"Auto Repair",
            "type":"Services"
        }
    ],
    "sg:postcode":"NR15 2PD",
    "sg:province":"Norfolk",
    "sg:tags":[
        "modification",
        "garage"
    ],
    "wof:name":"Stratton Motoring",
    "wof:placetype":"venue"
},
  "geometry": {"coordinates":[1.221765,52.485989],"type":"Point"}
}