{
  "type": "Feature",
  "properties": {
    "addr:full":"8 Rother Court, Parkgate Rotherham South Yorkshire S62 6DR",
    "addr:housenumber":"8",
    "addr:postcode":"s62 6dr",
    "addr:street":"Rother Court Parkgate",
    "iso:country":"GB",
    "sg:address":"8 Rother Court, Parkgate",
    "sg:city":"Rotherham",
    "sg:classifiers":[
        {
            "category":"Cafe",
            "type":"Food & Drink"
        }
    ],
    "sg:phone":"+44 1709 522254",
    "sg:postcode":"S62 6DR",
    "sg:province":"South Yorkshire",
    "sg:tags":[
        "tea",
        "snack",
        "bar",
        "room"
    ],
    "wof:name":"Oasis Cafe",
    "wof:placetype":"venue"
},
  "geometry": {"coordinates":[-1.348035,53.449711],"type":"Point"}
}