{
  "type": "Feature",
  "properties": {
    "addr:full":"970 Harrow Road Wembley Greater London HA0 2QE",
    "addr:housenumber":"970",
    "addr:postcode":"ha0 2qe",
    "addr:street":"Harrow Road",
    "iso:country":"GB",
    "sg:address":"970 Harrow Road",
    "sg:city":"Wembley",
    "sg:classifiers":[
        {
            "category":"Place Of Worship",
            "type":"Public Place"
        },
        {
            "category":"Organizations",
            "subcategory":"Non-profit Organization",
            "type":"Services"
        }
    ],
    "sg:phone":"+44 20 8904 2552",
    "sg:postcode":"HA0 2QE",
    "sg:province":"Greater London",
    "sg:tags":[
        "charitable",
        "organisation",
        "charity"
    ],
    "wof:name":"ST.GEORGE'S CHURCH",
    "wof:placetype":"venue"
},
  "geometry": {"coordinates":[-0.3257099986,51.5587425232],"type":"Point"}
}