{
  "type": "Feature",
  "properties": {
    "addr:full":"Crown Garage, Gravesend Road, Shorne Gravesend Kent DA12 3JL",
    "addr:postcode":"da12 3jl",
    "addr:street":"Gravesend Road",
    "iso:country":"GB",
    "sg:address":"Crown Garage, Gravesend Road, Shorne",
    "sg:city":"Gravesend",
    "sg:classifiers":[
        {
            "category":"Professional",
            "subcategory":"Business Services",
            "type":"Services"
        },
        {
            "category":"Real Estate",
            "subcategory":"Real Estate Agent",
            "type":"Services"
        }
    ],
    "sg:phone":"+44 1474 824362",
    "sg:postcode":"DA12 3JL",
    "sg:province":"Kent",
    "sg:tags":[
        "accomodation"
    ],
    "wof:name":"Clifford Earl Ltd.",
    "wof:placetype":"venue"
},
  "geometry": {"coordinates":[0.4306530058,51.4146003723],"type":"Point"}
}