{
  "type": "Feature",
  "properties": {
    "addr:full":"288 Castle Lane West Bournemouth Dorset BH8 9TU",
    "addr:housenumber":"288",
    "addr:postcode":"bh8 9tu",
    "addr:street":"Castle Lane West",
    "iso:country":"GB",
    "sg:address":"288 Castle Lane West",
    "sg:city":"Bournemouth",
    "sg:classifiers":[
        {
            "category":"Health Services",
            "subcategory":"Dentist",
            "type":"Services"
        }
    ],
    "sg:phone":"+44 1202 513292",
    "sg:postcode":"BH8 9TU",
    "sg:province":"Dorset",
    "wof:name":"T Westerlund",
    "wof:placetype":"venue"
},
  "geometry": {"coordinates":[-1.853621006,50.7523994446],"type":"Point"}
}