{
  "type": "Feature",
  "properties": {
    "addr:full":"Orchard Nell, Greystones Avenue, Killinghall Harrogate North Yorkshire HG3 2BJ",
    "addr:postcode":"hg3 2bj",
    "addr:street":"Avenue",
    "iso:country":"GB",
    "sg:address":"Orchard Nell, Greystones Avenue, Killinghall",
    "sg:city":"Harrogate",
    "sg:classifiers":[
        {
            "category":"Building & Trades",
            "subcategory":"Construction",
            "type":"Services"
        }
    ],
    "sg:postcode":"HG3 2BJ",
    "sg:province":"North Yorkshire",
    "sg:tags":[
        "builder"
    ],
    "wof:name":"N P Hawe Craftsman Builder",
    "wof:placetype":"venue"
},
  "geometry": {"coordinates":[-1.564256,54.024055],"type":"Point"}
}