{
  "type": "Feature",
  "properties": {
    "iso:country":"GB",
    "sg:address":"17 High Street",
    "sg:city":"Ramsgate",
    "sg:classifiers":[
        {
            "category":"Wholesale",
            "subcategory":"Meat",
            "type":"Manufacturing & Wholesale Goods"
        }
    ],
    "sg:phone":"+44 1843 570002",
    "sg:postcode":"CT11 9AG",
    "sg:province":"Kent",
    "sg:tags":[
        "-"
    ],
    "wof:name":"Gilhams (Butchers) Ltd.",
    "wof:placetype":"venue"
},
  "geometry": {"coordinates":[1.4192409515,51.3341064453],"type":"Point"}
}