{
  "type": "Feature",
  "properties": {
    "iso:country":"GB",
    "sg:address":"548 Scott Hall Road",
    "sg:city":"Leeds",
    "sg:classifiers":[
        {
            "category":"Shopping",
            "subcategory":"Gifts & Souvenirs",
            "type":"Retail Goods"
        },
        {
            "category":"Government",
            "subcategory":"Post Office",
            "type":"Public Place"
        }
    ],
    "sg:postcode":"LS7 3RA",
    "sg:province":"West Yorkshire",
    "sg:tags":[
        "poster",
        "card"
    ],
    "wof:name":"Miles Hill Sub Post Office",
    "wof:placetype":"venue"
},
  "geometry": {"coordinates":[-1.546704,53.82827],"type":"Point"}
}