{
  "type": "Feature",
  "properties": {
    "iso:country":"GB",
    "sg:address":"77-85 Fulham Palace Rd",
    "sg:city":"New Malden",
    "sg:classifiers":[
        {
            "category":"Wholesale",
            "subcategory":"Books, Periodicals, & Newspapers",
            "type":"Manufacturing & Wholesale Goods"
        }
    ],
    "sg:phone":"+44 20 8324 5300",
    "sg:postcode":"KT3 4QS",
    "sg:province":"Surrey",
    "sg:tags":[
        "maps",
        "globe",
        "chart",
        "pub"
    ],
    "wof:name":"Etak The Digital Map Co Ltd",
    "wof:placetype":"venue"
},
  "geometry": {"coordinates":[-0.2561939955,51.4017715454],"type":"Point"}
}