{
  "type": "Feature",
  "properties": {
    "iso:country":"GB",
    "sg:address":"46-50 Elswick Road",
    "sg:city":"Newcastle-upon-tyne",
    "sg:classifiers":[
        {
            "category":"Home & Garden",
            "subcategory":"Carpets & Floor Coverings",
            "type":"Retail Goods"
        }
    ],
    "sg:phone":"+44 191 273 7277",
    "sg:postcode":"NE4 6JT",
    "sg:province":"Tyne and Wear",
    "sg:tags":[
        "carpets",
        "rug",
        "matting"
    ],
    "wof:name":"Newcastle Carpets & Furniture Centre",
    "wof:placetype":"venue"
},
  "geometry": {"coordinates":[-1.6320489645,54.9706993103],"type":"Point"}
}