{
  "type": "Feature",
  "properties": {
    "addr:full":"350 Brook Street, Broughty Ferry Dundee Angus DD5 2AN",
    "addr:housenumber":"350",
    "addr:postcode":"dd5 2an",
    "addr:street":"Brook Street",
    "iso:country":"GB",
    "sg:address":"350 Brook Street, Broughty Ferry",
    "sg:city":"Dundee",
    "sg:classifiers":[
        {
            "category":"Health Services",
            "subcategory":"Health Practitioner",
            "type":"Services"
        }
    ],
    "sg:postcode":"DD5 2AN",
    "sg:province":"Angus",
    "sg:tags":[
        "physiotherapist"
    ],
    "wof:name":"Eric Ferguson",
    "wof:placetype":"venue"
},
  "geometry": {"coordinates":[-2.870561,56.466541],"type":"Point"}
}