{
  "type": "Feature",
  "properties": {
    "iso:country":"GB",
    "sg:address":"63-64 Charles La",
    "sg:city":"London",
    "sg:classifiers":[
        {
            "category":"Real Estate",
            "subcategory":"Real Estate Agent",
            "type":"Services"
        }
    ],
    "sg:postcode":"NW8 7SB",
    "sg:province":"Greater London",
    "wof:name":"Careline Properties Ltd",
    "wof:placetype":"venue"
},
  "geometry": {"coordinates":[-0.168844,51.534676],"type":"Point"}
}