{
  "type": "Feature",
  "properties": {
    "iso:country":"GB",
    "sg:address":"24 Allonby Close, Lower Earley",
    "sg:city":"Reading",
    "sg:classifiers":[
        {
            "category":"Professional",
            "subcategory":"Management & Consulting",
            "type":"Services"
        }
    ],
    "sg:phone":"+44 118 966 0268",
    "sg:postcode":"RG6 3BY",
    "sg:province":"Berkshire",
    "sg:tags":[
        "consultant",
        "specialist"
    ],
    "wof:name":"Lynn Williams Beauty Clinic",
    "wof:placetype":"venue"
},
  "geometry": {"coordinates":[-0.912440002,51.4320030212],"type":"Point"}
}