{
  "type": "Feature",
  "properties": {
    "addr:full":"Aston Science Park, Love La Birmingham West Midlands B7 4BJ",
    "addr:postcode":"b7 4bj",
    "iso:country":"GB",
    "sg:address":"Aston Science Park, Love La",
    "sg:city":"Birmingham",
    "sg:classifiers":[
        {
            "category":"Utilities",
            "type":"Services"
        }
    ],
    "sg:phone":"+44 121 248 8787",
    "sg:postcode":"B7 4BJ",
    "sg:province":"West Midlands",
    "sg:tags":[
        "connection",
        "provider",
        "internet"
    ],
    "wof:name":"VBC Net UK Ltd",
    "wof:placetype":"venue"
},
  "geometry": {"coordinates":[-1.8856589794,52.4889907837],"type":"Point"}
}