{
  "type": "Feature",
  "properties": {
    "iso:country":"GB",
    "sg:address":"Back O Hill Industrial Estate",
    "sg:city":"Stirling",
    "sg:classifiers":[
        {
            "category":"Professional",
            "subcategory":"Engineering",
            "type":"Services"
        }
    ],
    "sg:phone":"+44 1786 479997",
    "sg:postcode":"FK8 1SH",
    "sg:province":"Stirling",
    "sg:tags":[
        "contractor",
        "electrical",
        "engineer"
    ],
    "wof:name":"Balfour Kilpatrick Ltd.",
    "wof:placetype":"venue"
},
  "geometry": {"coordinates":[-3.949089,56.127296],"type":"Point"}
}