{
  "type": "Feature",
  "properties": {
    "iso:country":"GB",
    "sg:address":"Llwyn Yr Eos Felindre, Dryslwyn",
    "sg:city":"Carmarthen",
    "sg:classifiers":[
        {
            "category":"Shopping",
            "subcategory":"Gifts & Souvenirs",
            "type":"Retail Goods"
        }
    ],
    "sg:phone":"+44 1558 668900",
    "sg:postcode":"SA32 8RJ",
    "sg:province":"Carmarthenshire",
    "sg:tags":[
        "diy"
    ],
    "wof:name":"Hansells",
    "wof:placetype":"venue"
},
  "geometry": {"coordinates":[-4.1029849052,51.8638381958],"type":"Point"}
}