{
  "type": "Feature",
  "properties": {
    "iso:country":"GB",
    "sg:address":"181 Norwich Rd",
    "sg:city":"Norwich",
    "sg:classifiers":[
        {
            "category":"Building & Trades",
            "subcategory":"Landscaping Services",
            "type":"Services"
        }
    ],
    "sg:phone":"+44 1603 783778",
    "sg:postcode":"NR12 8RZ",
    "sg:province":"Norfolk",
    "sg:tags":[
        "gardening"
    ],
    "wof:name":"A D Bartlett",
    "wof:placetype":"venue"
},
  "geometry": {"coordinates":[1.401545,52.705151],"type":"Point"}
}