{
  "type": "Feature",
  "properties": {
    "addr:full":"9 Meldrum Rd Nuneaton Leicestershire CV10 8HS",
    "addr:housenumber":"9",
    "addr:postcode":"cv10 8hs",
    "addr:street":"Meldrum Rd",
    "iso:country":"GB",
    "sg:address":"9 Meldrum Rd",
    "sg:city":"Nuneaton",
    "sg:classifiers":[
        {
            "category":"Home & Garden",
            "subcategory":"Carpets & Floor Coverings",
            "type":"Retail Goods"
        }
    ],
    "sg:postcode":"CV10 8HS",
    "sg:province":"Leicestershire",
    "sg:tags":[
        "carpets",
        "rug",
        "matting"
    ],
    "wof:name":"Randle,Neil,",
    "wof:placetype":"venue"
},
  "geometry": {"coordinates":[-1.502978,52.520344],"type":"Point"}
}