{
  "type": "Feature",
  "properties": {
    "addr:full":"3 Powmill Road Prestwick South Ayrshire KA9 2NX",
    "addr:housenumber":"3",
    "addr:postcode":"ka9 2nx",
    "addr:street":"Powmill Road Prestwick",
    "iso:country":"GB",
    "sg:address":"3 Powmill Road",
    "sg:city":"Prestwick",
    "sg:classifiers":[
        {
            "category":"Building & Trades",
            "subcategory":"Cleaning & Sanitation",
            "type":"Services"
        },
        {
            "category":"Professional",
            "subcategory":"Art Services",
            "type":"Services"
        },
        {
            "category":"Building & Trades",
            "subcategory":"Construction",
            "type":"Services"
        }
    ],
    "sg:postcode":"KA9 2NX",
    "sg:province":"South Ayrshire",
    "sg:tags":[
        "stone",
        "restoration",
        "builder",
        "exterior"
    ],
    "wof:name":"JOHN S COUGHTRIE",
    "wof:placetype":"venue"
},
  "geometry": {"coordinates":[-4.6036810875,55.5067138672],"type":"Point"}
}