{
  "type": "Feature",
  "properties": {
    "addr:full":"159 Tuckers Rd Loughborough Leicestershire LE11 2PH",
    "addr:housenumber":"159",
    "addr:postcode":"le11 2ph",
    "addr:street":"Tuckers Rd",
    "iso:country":"GB",
    "sg:address":"159 Tuckers Rd",
    "sg:city":"Loughborough",
    "sg:classifiers":[
        {
            "category":"Autos & Motor Vehicles",
            "subcategory":"Automobile Sales",
            "type":"Retail Goods"
        }
    ],
    "sg:phone":"+44 1509 219316",
    "sg:postcode":"LE11 2PH",
    "sg:province":"Leicestershire",
    "sg:tags":[
        "commercial"
    ],
    "wof:name":"B & S Auto's",
    "wof:placetype":"venue"
},
  "geometry": {"coordinates":[-1.191603,52.762905],"type":"Point"}
}