{
  "type": "Feature",
  "properties": {
    "iso:country":"GB",
    "sg:address":"9 Stonehaven, Arnold",
    "sg:city":"Nottingham",
    "sg:classifiers":[
        {
            "category":"Home & Garden",
            "subcategory":"Household Appliances",
            "type":"Retail Goods"
        }
    ],
    "sg:postcode":"NG5 7JG",
    "sg:province":"Nottinghamshire",
    "sg:tags":[
        "electrical"
    ],
    "wof:name":"S Powell Domestics",
    "wof:placetype":"venue"
},
  "geometry": {"coordinates":[-1.122859,53.00243],"type":"Point"}
}