{
  "type": "Feature",
  "properties": {
    "addr:full":"12a Eton Grove London Greater London SE13 5BY",
    "addr:housenumber":"12a",
    "addr:postcode":"se13 5by",
    "addr:street":"Eton Grove",
    "iso:country":"GB",
    "sg:address":"12a Eton Grove",
    "sg:city":"London",
    "sg:classifiers":[
        {
            "category":"Manufacturing",
            "subcategory":"Wood Products",
            "type":"Manufacturing & Wholesale Goods"
        }
    ],
    "sg:phone":"+44 20 8318 2111",
    "sg:postcode":"SE13 5BY",
    "sg:province":"Greater London",
    "sg:tags":[
        "cork"
    ],
    "wof:name":"Alan J White Ltd.",
    "wof:placetype":"venue"
},
  "geometry": {"coordinates":[0.00295,51.462067],"type":"Point"}
}