{
  "type": "Feature",
  "properties": {
    "addr:full":"Unit 1 Junction 7 Business Park, Blackburn Road, Clayton Le Moors Accrington Lancashire BB5 5JW",
    "addr:housenumber":"unit 1;7",
    "addr:postcode":"bb5 5jw",
    "addr:street":"Junction;Business Park Blackburn Road",
    "iso:country":"GB",
    "sg:address":"Unit 1 Junction 7 Business Park, Blackburn Road, Clayton Le Moors",
    "sg:city":"Accrington",
    "sg:classifiers":[
        {
            "category":"Professional",
            "subcategory":"Management & Consulting",
            "type":"Services"
        }
    ],
    "sg:phone":"+44 1254 871766",
    "sg:postcode":"BB5 5JW",
    "sg:province":"Lancashire",
    "sg:tags":[
        "consultant",
        "transport"
    ],
    "wof:name":"Anagraph",
    "wof:placetype":"venue"
},
  "geometry": {"coordinates":[-2.383838892,53.7781066895],"type":"Point"}
}