{
  "type": "Feature",
  "properties": {
    "addr:full":"Warnford Court, 29 Throgmorton Street London Greater London EC2N 2AT",
    "addr:housenumber":"29",
    "addr:postcode":"ec2n 2at",
    "addr:street":"Warnford;Throgmorton Street",
    "iso:country":"GB",
    "sg:address":"Warnford Court, 29 Throgmorton Street",
    "sg:city":"London",
    "sg:classifiers":[
        {
            "category":"Banks & Credit Unions",
            "subcategory":"Investment Brokerage",
            "type":"Services"
        }
    ],
    "sg:phone":"+44 20 7628 5560",
    "sg:postcode":"EC2N 2AT",
    "sg:province":"Greater London",
    "wof:name":"Warnford Investments Ltd.",
    "wof:placetype":"venue"
},
  "geometry": {"coordinates":[-0.086917,51.5149],"type":"Point"}
}