{
  "type": "Feature",
  "properties": {
    "addr:full":"Field House, Eyebury Road Peterborough Cambridgeshire PE6 7TD",
    "addr:postcode":"pe6 7td",
    "addr:street":"Eyebury Road",
    "iso:country":"GB",
    "sg:address":"Field House, Eyebury Road",
    "sg:city":"Peterborough",
    "sg:classifiers":[
        {
            "category":"Social Services",
            "subcategory":"Retirement Home",
            "type":"Services"
        }
    ],
    "sg:phone":"+44 1733 222417",
    "sg:postcode":"PE6 7TD",
    "sg:province":"Cambridgeshire",
    "sg:tags":[
        "residential",
        "care"
    ],
    "wof:name":"Field House (Eye) Ltd.",
    "wof:placetype":"venue"
},
  "geometry": {"coordinates":[-0.186243996,52.6094284058],"type":"Point"}
}