{
  "type": "Feature",
  "properties": {
    "addr:full":"165 Sunderland Rd South Shields Tyne and Wear NE34 6AE",
    "addr:housenumber":"165",
    "addr:postcode":"ne34 6ae",
    "addr:street":"Sunderland Rd",
    "iso:country":"GB",
    "sg:address":"165 Sunderland Rd",
    "sg:city":"South Shields",
    "sg:classifiers":[
        {
            "category":"Bars & Pubs",
            "type":"Food & Drink"
        }
    ],
    "sg:phone":"+44 191 456 1633",
    "sg:postcode":"NE34 6AE",
    "sg:province":"Tyne and Wear",
    "sg:tags":[
        "pubs",
        "inn"
    ],
    "wof:name":"Vigilant Inn The",
    "wof:placetype":"venue"
},
  "geometry": {"coordinates":[-1.4133930206,54.9779052734],"type":"Point"}
}