{
  "type": "Feature",
  "properties": {
    "iso:country":"GB",
    "sg:address":"Great Western Rd",
    "sg:city":"Notting Hill",
    "sg:classifiers":[
        {
            "category":"Manufacturing",
            "subcategory":"Apparel",
            "type":"Manufacturing & Wholesale Goods"
        }
    ],
    "sg:phone":"+44 20 7289 4117",
    "sg:postcode":"W11 1AB",
    "sg:province":"Greater London",
    "sg:tags":[
        "garment",
        "designer"
    ],
    "wof:name":"C A Davis",
    "wof:placetype":"venue"
},
  "geometry": {"coordinates":[-0.198624,51.5187835693],"type":"Point"}
}