{
  "type": "Feature",
  "properties": {
    "addr:full":"Braeside Cottage, Carsegour Kinross Clackmannanshire KY13 0LG",
    "addr:postcode":"ky13 0lg",
    "addr:street":"Carsegour",
    "iso:country":"GB",
    "sg:address":"Braeside Cottage, Carsegour",
    "sg:city":"Kinross",
    "sg:classifiers":[
        {
            "category":"Professional",
            "subcategory":"Computer Services",
            "type":"Services"
        }
    ],
    "sg:phone":"+44 1577 850222",
    "sg:postcode":"KY13 0LG",
    "sg:province":"Clackmannanshire",
    "sg:tags":[
        "consultant"
    ],
    "wof:name":"Coates Consulting Ltd.",
    "wof:placetype":"venue"
},
  "geometry": {"coordinates":[-3.4255139828,56.2113265991],"type":"Point"}
}