{
  "type": "Feature",
  "properties": {
    "addr:full":"Nant-y-cywarch Farm, Glan Conwy Colwyn Bay Conwy LL28 5PP",
    "addr:postcode":"ll28 5pp",
    "addr:street":"Glan",
    "iso:country":"GB",
    "sg:address":"Nant-y-cywarch Farm, Glan Conwy",
    "sg:city":"Colwyn Bay",
    "sg:classifiers":[
        {
            "category":"Farming",
            "subcategory":"Livestock Farm",
            "type":"Manufacturing & Wholesale Goods"
        }
    ],
    "sg:phone":"+44 1492 580379",
    "sg:postcode":"LL28 5PP",
    "sg:province":"Conwy",
    "sg:tags":[
        "others"
    ],
    "wof:name":"J T Hughes",
    "wof:placetype":"venue"
},
  "geometry": {"coordinates":[-3.792182,53.268005],"type":"Point"}
}