{
  "type": "Feature",
  "properties": {
    "iso:country":"GB",
    "sg:address":"Y Maes",
    "sg:city":"Pwllheli",
    "sg:classifiers":[
        {
            "category":"Shopping",
            "subcategory":"Pharmacy",
            "type":"Retail Goods"
        }
    ],
    "sg:postcode":"LL53 5HA",
    "sg:province":"Gwynedd",
    "sg:tags":[
        "dispensing",
        "store",
        "pharmacist",
        "chemist",
        "drug"
    ],
    "wof:name":"D G Evans",
    "wof:placetype":"venue"
},
  "geometry": {"coordinates":[-4.4143137932,52.8898468018],"type":"Point"}
}