{
  "type": "Feature",
  "properties": {
    "iso:country":"GB",
    "sg:address":"3 Mill Lane",
    "sg:city":"Arundel",
    "sg:classifiers":[
        {
            "category":"Restaurant",
            "type":"Food & Drink"
        }
    ],
    "sg:phone":"+44 1903 882140",
    "sg:postcode":"BN18 9AH",
    "sg:province":"West Sussex",
    "sg:tags":[
        "indian"
    ],
    "wof:name":"The New Castle Tandoori of Arundel",
    "wof:placetype":"venue"
},
  "geometry": {"coordinates":[-0.553364,50.854309],"type":"Point"}
}