{
  "type": "Feature",
  "properties": {
    "iso:country":"GB",
    "sg:address":"10th Floor Impact House, 2 Edridge Road",
    "sg:city":"Croydon",
    "sg:classifiers":[
        {
            "category":"Professional",
            "subcategory":"Engineering",
            "type":"Services"
        }
    ],
    "sg:phone":"+44 20 8681 9777",
    "sg:postcode":"CR9 1PJ",
    "sg:province":"Surrey",
    "sg:tags":[
        "design",
        "engineer"
    ],
    "wof:name":"National Design Consultancy",
    "wof:placetype":"venue"
},
  "geometry": {"coordinates":[-0.098136,51.369133],"type":"Point"}
}