{
  "type": "Feature",
  "properties": {
    "addr:full":"Carding Fields Farm Malpas Cheshire SY14 7EL",
    "addr:postcode":"sy14 7el",
    "addr:street":"Carding Fields",
    "iso:country":"GB",
    "sg:address":"Carding Fields Farm",
    "sg:city":"Malpas",
    "sg:classifiers":[
        {
            "category":"Farming",
            "subcategory":"Poultry Farm",
            "type":"Manufacturing & Wholesale Goods"
        }
    ],
    "sg:phone":"+44 1948 860273",
    "sg:postcode":"SY14 7EL",
    "sg:province":"Cheshire",
    "sg:tags":[
        "game"
    ],
    "wof:name":"Cheshire Poultry Breeders",
    "wof:placetype":"venue"
},
  "geometry": {"coordinates":[-2.766259,53.020981],"type":"Point"}
}