{
  "type": "Feature",
  "properties": {
    "addr:full":"120 Kingston Road London Greater London SW19 1LY",
    "addr:housenumber":"120",
    "addr:postcode":"sw19 1ly",
    "addr:street":"Kingston Road",
    "iso:country":"GB",
    "sg:address":"120 Kingston Road",
    "sg:city":"London",
    "sg:classifiers":[
        {
            "category":"Social Services",
            "subcategory":"Retirement Home",
            "type":"Services"
        }
    ],
    "sg:phone":"+44 20 8543 3727",
    "sg:postcode":"SW19 1LY",
    "sg:province":"Greater London",
    "sg:tags":[
        "care"
    ],
    "wof:name":"Community Home Care Provider",
    "wof:placetype":"venue"
},
  "geometry": {"coordinates":[-0.1988849938,51.4151878357],"type":"Point"}
}