{
  "type": "Feature",
  "properties": {
    "addr:full":"37 Beech Road, Cleveleys Thornton-cleveleys Lancashire FY5 1EG",
    "addr:housenumber":"37",
    "addr:postcode":"fy5 1eg",
    "addr:street":"Beech Road",
    "iso:country":"GB",
    "sg:address":"37 Beech Road, Cleveleys",
    "sg:city":"Thornton-cleveleys",
    "sg:classifiers":[
        {
            "category":"Shopping",
            "subcategory":"Clothing, Apparel, & Fashions",
            "type":"Retail Goods"
        }
    ],
    "sg:phone":"+44 1253 867048",
    "sg:postcode":"FY5 1EG",
    "sg:province":"Lancashire",
    "sg:tags":[
        "shop"
    ],
    "wof:name":"Marilyn Jean Fashions",
    "wof:placetype":"venue"
},
  "geometry": {"coordinates":[-3.0414800644,53.8813972473],"type":"Point"}
}