{
  "type": "Feature",
  "properties": {
    "iso:country":"GB",
    "sg:address":"334 Romford Road",
    "sg:city":"London",
    "sg:classifiers":[
        {
            "category":"Autos & Motor Vehicles",
            "subcategory":"Fuel & Gas Station",
            "type":"Retail Goods"
        }
    ],
    "sg:phone":"+44 20 8534 8162",
    "sg:postcode":"E7 8BS",
    "sg:province":"Greater London",
    "sg:tags":[
        "hr",
        "petrol"
    ],
    "wof:name":"Stratford Petroleum",
    "wof:placetype":"venue"
},
  "geometry": {"coordinates":[0.029065,51.546616],"type":"Point"}
}