{
  "type": "Feature",
  "properties": {
    "addr:full":"Old Baldragon, Strathmartine Dundee Dundee City DD3 0PL",
    "addr:postcode":"dd3 0pl",
    "addr:street":"Strathmartine",
    "iso:country":"GB",
    "sg:address":"Old Baldragon, Strathmartine",
    "sg:city":"Dundee",
    "sg:classifiers":[
        {
            "category":"Real Estate",
            "subcategory":"Real Estate Services",
            "type":"Services"
        },
        {
            "category":"Building & Trades",
            "subcategory":"Equipment Rental",
            "type":"Services"
        }
    ],
    "sg:phone":"+44 1382 817242",
    "sg:postcode":"DD3 0PL",
    "sg:province":"Dundee City",
    "sg:tags":[
        "hire",
        "leasing",
        "plant",
        "machinery"
    ],
    "wof:name":"P & G Plant Hire Contractors",
    "wof:placetype":"venue"
},
  "geometry": {"coordinates":[-3.022201,56.514446],"type":"Point"}
}