{
  "type": "Feature",
  "properties": {
    "iso:country":"GB",
    "sg:address":"1 Wood End Avenue",
    "sg:city":"Harrow",
    "sg:classifiers":[
        {
            "category":"Building & Trades",
            "subcategory":"Construction",
            "type":"Services"
        }
    ],
    "sg:phone":"+44 20 8422 9990",
    "sg:postcode":"HA2 8NU",
    "sg:province":"Greater London",
    "sg:tags":[
        "roofing"
    ],
    "wof:name":"F Mummery",
    "wof:placetype":"venue"
},
  "geometry": {"coordinates":[-0.35824,51.560104],"type":"Point"}
}