{
  "type": "Feature",
  "properties": {
    "addr:full":"School Road, Newburgh Ellon Aberdeenshire AB41 6BT",
    "addr:postcode":"ab41 6bt",
    "addr:street":"School Road",
    "iso:country":"GB",
    "sg:address":"School Road, Newburgh",
    "sg:city":"Ellon",
    "sg:classifiers":[
        {
            "category":"Shopping",
            "subcategory":"Gifts & Souvenirs",
            "type":"Retail Goods"
        }
    ],
    "sg:postcode":"AB41 6BT",
    "sg:province":"Aberdeenshire",
    "sg:tags":[
        "shop"
    ],
    "wof:name":"Abbeyside Gallery",
    "wof:placetype":"venue"
},
  "geometry": {"coordinates":[-2.0044391155,57.3170890808],"type":"Point"}
}