{
  "type": "Feature",
  "properties": {
    "iso:country":"GB",
    "sg:address":"Sydnope Hall Farm, Darley Moor",
    "sg:city":"Matlock",
    "sg:classifiers":[
        {
            "category":"Recreation",
            "subcategory":"Fishing",
            "type":"Entertainment"
        }
    ],
    "sg:phone":"+44 1629 732641",
    "sg:postcode":"DE4 5LN",
    "sg:province":"Derbyshire",
    "sg:tags":[
        "angling"
    ],
    "wof:name":"Sydnope Fisheries",
    "wof:placetype":"venue"
},
  "geometry": {"coordinates":[-1.5612460375,53.1749649048],"type":"Point"}
}