{
  "type": "Feature",
  "properties": {
    "addr:full":"1489 Melton Road, Queniborough Leicester Leicestershire LE7 3FP",
    "addr:housenumber":"1489",
    "addr:postcode":"le7 3fp",
    "addr:street":"Melton Road",
    "iso:country":"GB",
    "sg:address":"1489 Melton Road, Queniborough",
    "sg:city":"Leicester",
    "sg:classifiers":[
        {
            "category":"Professional",
            "type":"Services"
        }
    ],
    "sg:phone":"+44 116 260 6005",
    "sg:postcode":"LE7 3FP",
    "sg:province":"Leicestershire",
    "sg:tags":[
        "shopfitters"
    ],
    "wof:name":"T E J Ltd.",
    "wof:placetype":"venue"
},
  "geometry": {"coordinates":[-1.0616589785,52.7041091919],"type":"Point"}
}