{
  "type": "Feature",
  "properties": {
    "iso:country":"GB",
    "sg:address":"Higher Duckworth Hill, Farm Duckworth Hill Lane, Oswaldtwistle",
    "sg:city":"Accrington",
    "sg:classifiers":[
        {
            "category":"Social Services",
            "subcategory":"Child Care",
            "type":"Services"
        },
        {
            "category":"Shopping",
            "subcategory":"Antiques",
            "type":"Retail Goods"
        }
    ],
    "sg:phone":"+44 1254 871832",
    "sg:postcode":"BB5 3RN",
    "sg:province":"Lancashire",
    "sg:tags":[
        "creche"
    ],
    "wof:name":"Bicentennia Ltd.",
    "wof:placetype":"venue"
},
  "geometry": {"coordinates":[-2.397315,53.742584],"type":"Point"}
}