{
  "type": "Feature",
  "properties": {
    "iso:country":"GB",
    "sg:address":"7 Plantation Road",
    "sg:city":"Leighton Buzzard",
    "sg:classifiers":[
        {
            "category":"Retail",
            "subcategory":"Auto Repair",
            "type":"Services"
        }
    ],
    "sg:phone":"+44 1525 382953",
    "sg:postcode":"LU7 3HJ",
    "sg:province":"Bedfordshire",
    "sg:tags":[
        "modification",
        "garage"
    ],
    "wof:name":"Beechgrove Engineering (U K) Ltd.",
    "wof:placetype":"venue"
},
  "geometry": {"coordinates":[-0.6606119871,51.923210144],"type":"Point"}
}