{
  "type": "Feature",
  "properties": {
    "addr:full":"4 Duke St Galston East Ayrshire KA4 8JD",
    "addr:housenumber":"4",
    "addr:postcode":"ka4 8jd",
    "addr:street":"Duke St",
    "iso:country":"GB",
    "sg:address":"4 Duke St",
    "sg:city":"Galston",
    "sg:classifiers":[
        {
            "category":"Home & Garden",
            "subcategory":"Building Materials",
            "type":"Retail Goods"
        }
    ],
    "sg:postcode":"KA4 8JD",
    "sg:province":"East Ayrshire",
    "sg:tags":[
        "roofing",
        "rafter",
        "beams"
    ],
    "wof:name":"Azbraitis,Dennis,",
    "wof:placetype":"venue"
},
  "geometry": {"coordinates":[-4.3782992363,55.5988731384],"type":"Point"}
}