{
  "type": "Feature",
  "properties": {
    "iso:country":"GB",
    "sg:address":"Summertown Pavilion, 18-24 Middle Way",
    "sg:city":"Oxford",
    "sg:classifiers":[
        {
            "category":"Conference Center",
            "type":"Public Place"
        }
    ],
    "sg:phone":"+44 1865 511550",
    "sg:postcode":"OX2 7LG",
    "sg:province":"Oxfordshire",
    "wof:name":"Oxford International Marketing Services Ltd.",
    "wof:placetype":"venue"
},
  "geometry": {"coordinates":[-1.26829,51.77924],"type":"Point"}
}