{
  "type": "Feature",
  "properties": {
    "iso:country":"GB",
    "sg:address":"9 Brockdale Gardens, Keyworth",
    "sg:city":"Nottingham",
    "sg:classifiers":[
        {
            "category":"Retail",
            "subcategory":"Driving School",
            "type":"Services"
        }
    ],
    "sg:phone":"+44 115 937 5300",
    "sg:postcode":"NG12 5HR",
    "sg:province":"Nottinghamshire",
    "wof:name":"Graham School of Motoring",
    "wof:placetype":"venue"
},
  "geometry": {"coordinates":[-1.087529,52.88076],"type":"Point"}
}