{
  "type": "Feature",
  "properties": {
    "addr:full":"Minns Industrial Estate, 7 West Way Oxford Oxfordshire OX2 0JB",
    "addr:housenumber":"7",
    "addr:postcode":"ox2 0jb",
    "addr:street":"Estate;West Way",
    "iso:country":"GB",
    "sg:address":"Minns Industrial Estate, 7 West Way",
    "sg:city":"Oxford",
    "sg:classifiers":[
        {
            "category":"Shopping",
            "subcategory":"Computers & Home Electronics",
            "type":"Retail Goods"
        }
    ],
    "sg:phone":"+44 1865 724716",
    "sg:postcode":"OX2 0JB",
    "sg:province":"Oxfordshire",
    "sg:tags":[
        "electrical"
    ],
    "wof:name":"Gfe Electrical Wholesale",
    "wof:placetype":"venue"
},
  "geometry": {"coordinates":[-1.2911800146,51.7531890869],"type":"Point"}
}