{
  "type": "Feature",
  "properties": {
    "addr:full":"Phoenix Ho, Bartholomew St Newbury Berkshire RG14 5QA",
    "addr:postcode":"rg14 5qa",
    "addr:street":"Bartholomew St",
    "iso:country":"GB",
    "sg:address":"Phoenix Ho, Bartholomew St",
    "sg:city":"Newbury",
    "sg:classifiers":[
        {
            "category":"Professional",
            "subcategory":"Business Services",
            "type":"Services"
        }
    ],
    "sg:postcode":"RG14 5QA",
    "sg:province":"Berkshire",
    "sg:tags":[
        "accomodation"
    ],
    "wof:name":"Advertdealer Ltd",
    "wof:placetype":"venue"
},
  "geometry": {"coordinates":[-1.3256440163,51.3992881775],"type":"Point"}
}