{
  "type": "Feature",
  "properties": {
    "addr:full":"22 Hexham Gardens Milton Keynes Buckinghamshire MK3 5EY",
    "addr:housenumber":"22",
    "addr:postcode":"mk3 5ey",
    "addr:street":"Hexham Gardens",
    "iso:country":"GB",
    "sg:address":"22 Hexham Gardens",
    "sg:city":"Milton Keynes",
    "sg:classifiers":[
        {
            "category":"Building & Trades",
            "subcategory":"Landscaping Services",
            "type":"Services"
        }
    ],
    "sg:phone":"+44 1908 648135",
    "sg:postcode":"MK3 5EY",
    "sg:province":"Buckinghamshire",
    "sg:tags":[
        "landscape",
        "contractor"
    ],
    "wof:name":"B & I Horticulture",
    "wof:placetype":"venue"
},
  "geometry": {"coordinates":[-0.767226994,51.9866104126],"type":"Point"}
}