{
  "type": "Feature",
  "properties": {
    "iso:country":"GB",
    "sg:address":"Headingley Station Building, Kirkstall Lane",
    "sg:city":"Leeds",
    "sg:classifiers":[
        {
            "category":"Professional",
            "subcategory":"Art Services",
            "type":"Services"
        }
    ],
    "sg:phone":"+44 113 274 5735",
    "sg:postcode":"LS5 3LD",
    "sg:province":"West Yorkshire",
    "sg:tags":[
        "graphic",
        "designer"
    ],
    "wof:name":"Forman Doyle",
    "wof:placetype":"venue"
},
  "geometry": {"coordinates":[-1.5972490311,53.8169021606],"type":"Point"}
}