{
  "type": "Feature",
  "properties": {
    "iso:country":"GB",
    "sg:address":", Libanus",
    "sg:city":"Brecon",
    "sg:classifiers":[
        {
            "category":"Health Services",
            "subcategory":"Nursing And Care Facility",
            "type":"Services"
        }
    ],
    "sg:phone":"+44 1874 624242",
    "sg:postcode":"LD3 8EN",
    "sg:province":"Powys",
    "sg:tags":[
        "home"
    ],
    "wof:name":"Mountains Nursing Home",
    "wof:placetype":"venue"
},
  "geometry": {"coordinates":[-3.5317189693,51.9429893494],"type":"Point"}
}