{
  "type": "Feature",
  "properties": {
    "addr:full":"2 Orchard Clo Sheringham Norfolk NR26 8SX",
    "addr:housenumber":"2",
    "addr:postcode":"nr26 8sx",
    "addr:street":"Orchard Clo",
    "iso:country":"GB",
    "sg:address":"2 Orchard Clo",
    "sg:city":"Sheringham",
    "sg:classifiers":[
        {
            "category":"Organizations",
            "subcategory":"Religious Organization",
            "type":"Services"
        }
    ],
    "sg:phone":"+44 1263 821143",
    "sg:postcode":"NR26 8SX",
    "sg:province":"Norfolk",
    "sg:tags":[
        "organisation"
    ],
    "wof:name":"Gideons International",
    "wof:placetype":"venue"
},
  "geometry": {"coordinates":[1.2008399963,52.9402732849],"type":"Point"}
}