{
  "type": "Feature",
  "properties": {
    "addr:full":"1d Shopping Centre Aviemore Highland PH22 1PT",
    "addr:postcode":"ph22 1pt",
    "addr:street":"Aviemore",
    "iso:country":"GB",
    "sg:address":"1d Shopping Centre",
    "sg:city":"Aviemore",
    "sg:classifiers":[
        {
            "category":"Transit Center",
            "subcategory":"Freight",
            "type":"Transportation"
        }
    ],
    "sg:phone":"+44 1479 811164",
    "sg:postcode":"PH22 1PT",
    "sg:province":"Highland",
    "sg:tags":[
        "shop",
        "craft",
        "centre"
    ],
    "wof:name":"Country Crafts",
    "wof:placetype":"venue"
},
  "geometry": {"coordinates":[-3.8287789822,57.1986694336],"type":"Point"}
}