{
  "type": "Feature",
  "properties": {
    "iso:country":"GB",
    "sg:address":"Units 1 7 4 Butts Clo, Red Marsh Indust Est",
    "sg:city":"Thornton Cleveleys",
    "sg:classifiers":[
        {
            "category":"Autos & Motor Vehicles",
            "subcategory":"Automobile Sales",
            "type":"Retail Goods"
        }
    ],
    "sg:phone":"+44 1253 820500",
    "sg:postcode":"FY5 4HT",
    "sg:province":"Lancashire",
    "sg:tags":[
        "commercial"
    ],
    "wof:name":"CSM Minibuses",
    "wof:placetype":"venue"
},
  "geometry": {"coordinates":[-3.001364,53.870968],"type":"Point"}
}