{
  "type": "Feature",
  "properties": {
    "addr:full":"Todd Lane South, Lostock Hall Preston Lancashire PR5 5XE",
    "addr:postcode":"pr5 5xe",
    "addr:street":"Todd Lane South",
    "iso:country":"GB",
    "sg:address":"Todd Lane South, Lostock Hall",
    "sg:city":"Preston",
    "sg:classifiers":[
        {
            "category":"Social Services",
            "subcategory":"Retirement Home",
            "type":"Services"
        }
    ],
    "sg:postcode":"PR5 5XE",
    "sg:province":"Lancashire",
    "sg:tags":[
        "rest"
    ],
    "wof:name":"Chestnut Grove Rest Home",
    "wof:placetype":"venue"
},
  "geometry": {"coordinates":[-2.681909,53.72718],"type":"Point"}
}