{
  "type": "Feature",
  "properties": {
    "iso:country":"GB",
    "sg:address":"250 St Albans Road",
    "sg:city":"Watford",
    "sg:classifiers":[
        {
            "category":"Shopping",
            "subcategory":"Antiques",
            "type":"Retail Goods"
        }
    ],
    "sg:postcode":"WD24 4AX",
    "sg:province":"Hertfordshire",
    "wof:name":"Bygone Years",
    "wof:placetype":"venue"
},
  "geometry": {"coordinates":[-0.3961240053,51.6716842651],"type":"Point"}
}