{
  "type": "Feature",
  "properties": {
    "addr:full":"15 Boundary Way, Shepshed Loughborough Leicestershire LE12 9TZ",
    "addr:housenumber":"15",
    "addr:postcode":"le12 9tz",
    "addr:street":"Boundary Way",
    "iso:country":"GB",
    "sg:address":"15 Boundary Way, Shepshed",
    "sg:city":"Loughborough",
    "sg:classifiers":[
        {
            "category":"Shopping",
            "subcategory":"Photographic Equipment",
            "type":"Retail Goods"
        }
    ],
    "sg:postcode":"LE12 9TZ",
    "sg:province":"Leicestershire",
    "wof:name":"Arcadia Studios",
    "wof:placetype":"venue"
},
  "geometry": {"coordinates":[-1.286237,52.778316],"type":"Point"}
}