{
  "type": "Feature",
  "properties": {
    "addr:full":"1185 Argyle St Glasgow Glasgow City G3 8TQ",
    "addr:housenumber":"1185",
    "addr:postcode":"g3 8tq",
    "addr:street":"Argyle St",
    "iso:country":"GB",
    "sg:address":"1185 Argyle St",
    "sg:city":"Glasgow",
    "sg:classifiers":[
        {
            "category":"Building & Trades",
            "subcategory":"Cleaning & Sanitation",
            "type":"Services"
        }
    ],
    "sg:phone":"+44 141 221 7323",
    "sg:postcode":"G3 8TQ",
    "sg:province":"Glasgow City",
    "sg:tags":[
        "commercial"
    ],
    "wof:name":"Kleen All",
    "wof:placetype":"venue"
},
  "geometry": {"coordinates":[-4.285669,55.86525],"type":"Point"}
}