{
  "type": "Feature",
  "properties": {
    "addr:full":"49 Grange Road Darlington Durham DL1 5NB",
    "addr:housenumber":"49",
    "addr:postcode":"dl1 5nb",
    "addr:street":"Grange Road",
    "iso:country":"GB",
    "sg:address":"49 Grange Road",
    "sg:city":"Darlington",
    "sg:classifiers":[
        {
            "category":"Travel",
            "subcategory":"Travel Agent",
            "type":"Entertainment"
        }
    ],
    "sg:phone":"+44 800 279 1700",
    "sg:postcode":"DL1 5NB",
    "sg:province":"Durham",
    "wof:name":"Topaz Travel",
    "wof:placetype":"venue"
},
  "geometry": {"coordinates":[-1.5581840277,54.5224914551],"type":"Point"}
}