{
  "type": "Feature",
  "properties": {
    "iso:country":"GB",
    "sg:address":"Crescent House, Yonge Close",
    "sg:city":"Eastleigh",
    "sg:classifiers":[
        {
            "category":"Professional",
            "subcategory":"Engineering",
            "type":"Services"
        }
    ],
    "sg:phone":"+44 23 8061 1969",
    "sg:postcode":"SO50 9SX",
    "sg:province":"Hampshire",
    "sg:tags":[
        "consulting",
        "engineer"
    ],
    "wof:name":"Thorburn Colquhoun Ltd",
    "wof:placetype":"venue"
},
  "geometry": {"coordinates":[-1.35178,50.972073],"type":"Point"}
}