{
  "type": "Feature",
  "properties": {
    "iso:country":"GB",
    "sg:address":"Waterside, The St",
    "sg:city":"Maidstone",
    "sg:classifiers":[
        {
            "category":"Building & Trades",
            "subcategory":"Construction",
            "type":"Services"
        }
    ],
    "sg:phone":"+44 1622 844790",
    "sg:postcode":"ME17 1DU",
    "sg:province":"Kent",
    "sg:tags":[
        "builder"
    ],
    "wof:name":"Dave Deakins",
    "wof:placetype":"venue"
},
  "geometry": {"coordinates":[0.64432,51.210049],"type":"Point"}
}