{
  "type": "Feature",
  "properties": {
    "iso:country":"GB",
    "sg:address":"21 Burton End, West Wickham",
    "sg:city":"Cambridge",
    "sg:classifiers":[
        {
            "category":"Professional",
            "subcategory":"Business Services",
            "type":"Services"
        }
    ],
    "sg:phone":"+44 1763 209231",
    "sg:postcode":"CB1 6SD",
    "sg:province":"Cambridgeshire",
    "sg:tags":[
        "hospitality",
        "corporate"
    ],
    "wof:name":"Barrie Hawkins Leisure Services",
    "wof:placetype":"venue"
},
  "geometry": {"coordinates":[0.368063,52.122036],"type":"Point"}
}