{
  "type": "Feature",
  "properties": {
    "addr:full":"140 London Wall London Greater London EC2Y 5DN",
    "addr:housenumber":"140",
    "addr:postcode":"ec2y 5dn",
    "addr:street":"London Wall",
    "iso:country":"GB",
    "sg:address":"140 London Wall",
    "sg:city":"London",
    "sg:classifiers":[
        {
            "category":"Professional",
            "subcategory":"Business Services",
            "type":"Services"
        }
    ],
    "sg:phone":"+44 20 7776 2750",
    "sg:postcode":"EC2Y 5DN",
    "sg:province":"Greater London",
    "sg:tags":[
        "broker",
        "commodity"
    ],
    "wof:name":"Toyota Tsusho (U K) Ltd.",
    "wof:placetype":"venue"
},
  "geometry": {"coordinates":[-0.09601,51.517818],"type":"Point"}
}