{
  "type": "Feature",
  "properties": {
    "iso:country":"GB",
    "sg:address":"Westbourne Road",
    "sg:city":"Hartlepool",
    "sg:classifiers":[
        {
            "category":"Organizations",
            "subcategory":"Community Association",
            "type":"Services"
        },
        {
            "category":"Organizations",
            "subcategory":"Membership Organization",
            "type":"Services"
        }
    ],
    "sg:phone":"+44 1429 272044",
    "sg:postcode":"TS25 5RB",
    "sg:province":"Durham",
    "sg:tags":[
        "club",
        "social"
    ],
    "wof:name":"South Durham Social Club",
    "wof:placetype":"venue"
},
  "geometry": {"coordinates":[-1.218524,54.676544],"type":"Point"}
}