{
  "type": "Feature",
  "properties": {
    "addr:full":"Cheapside Farm House, Sandridge Berry Lane St Albans Hertfordshire AL4 9DD",
    "addr:postcode":"al4 9dd",
    "addr:street":"Cheapside;Berry Lane",
    "iso:country":"GB",
    "sg:address":"Cheapside Farm House, Sandridge Berry Lane",
    "sg:city":"St Albans",
    "sg:classifiers":[
        {
            "category":"Health Services",
            "subcategory":"Health Practitioner",
            "type":"Services"
        }
    ],
    "sg:phone":"+44 1727 832266",
    "sg:postcode":"AL4 9DD",
    "sg:province":"Hertfordshire",
    "sg:tags":[
        "osteopath"
    ],
    "wof:name":"Alban Health Ltd.",
    "wof:placetype":"venue"
},
  "geometry": {"coordinates":[-0.3051809967,51.7812538147],"type":"Point"}
}