{
  "type": "Feature",
  "properties": {
    "addr:full":"Llynfi Lane, Off Talbot Street Maesteg Bridgend CF34 9DE",
    "addr:postcode":"cf34 9de",
    "addr:street":"Llynfi Lane Off Talbot Street",
    "iso:country":"GB",
    "sg:address":"Llynfi Lane, Off Talbot Street",
    "sg:city":"Maesteg",
    "sg:classifiers":[
        {
            "category":"Retail",
            "subcategory":"Auto Rental",
            "type":"Services"
        }
    ],
    "sg:phone":"+44 1656 734062",
    "sg:postcode":"CF34 9DE",
    "sg:province":"Bridgend",
    "sg:tags":[
        "truck",
        "hire",
        "van"
    ],
    "wof:name":"Agate Services Ltd.",
    "wof:placetype":"venue"
},
  "geometry": {"coordinates":[-3.6587939262,51.6083068848],"type":"Point"}
}