{
  "type": "Feature",
  "properties": {
    "addr:full":"2 Old Market Av Spilsby Lincolnshire PE23 5HX",
    "addr:housenumber":"2",
    "addr:postcode":"pe23 5hx",
    "addr:street":"Old Market Av Spilsby",
    "iso:country":"GB",
    "sg:address":"2 Old Market Av",
    "sg:city":"Spilsby",
    "sg:classifiers":[
        {
            "category":"Military Area",
            "subcategory":"Air Force Base",
            "type":"Public Place"
        }
    ],
    "sg:phone":"+44 1790 754008",
    "sg:postcode":"PE23 5HX",
    "sg:province":"Lincolnshire",
    "sg:tags":[
        "taxi",
        "hire",
        "private"
    ],
    "wof:name":"Harry's Executive Private Hire",
    "wof:placetype":"venue"
},
  "geometry": {"coordinates":[0.092574,53.172901],"type":"Point"}
}