{
  "type": "Feature",
  "properties": {
    "addr:full":"5 The Mall, Ealing Ealing Greater London W5 2PJ",
    "addr:housenumber":"5",
    "addr:postcode":"w5 2pj",
    "addr:street":"The Mall",
    "iso:country":"GB",
    "sg:address":"5 The Mall, Ealing",
    "sg:city":"Ealing",
    "sg:classifiers":[
        {
            "category":"Professional",
            "subcategory":"Management & Consulting",
            "type":"Services"
        }
    ],
    "sg:phone":"+44 20 8579 8008",
    "sg:postcode":"W5 2PJ",
    "sg:province":"Greater London",
    "sg:tags":[
        "marketing",
        "consultant"
    ],
    "wof:name":"M1 Marketing",
    "wof:placetype":"venue"
},
  "geometry": {"coordinates":[-0.29897,51.513939],"type":"Point"}
}