{
  "type": "Feature",
  "properties": {
    "iso:country":"GB",
    "sg:address":"Tralee, Bishops Sutton Road",
    "sg:city":"Alresford",
    "sg:classifiers":[
        {
            "category":"Building & Trades",
            "subcategory":"Plumbing",
            "type":"Services"
        }
    ],
    "sg:phone":"+44 1962 733526",
    "sg:postcode":"SO24 9EJ",
    "sg:province":"Hampshire",
    "sg:tags":[
        "heating"
    ],
    "wof:name":"D & P Humber",
    "wof:placetype":"venue"
},
  "geometry": {"coordinates":[-1.1617239714,51.090511322],"type":"Point"}
}