{
  "type": "Feature",
  "properties": {
    "addr:full":"Godsey Lane Peterborough Cambridgeshire PE6 8HY",
    "addr:postcode":"pe6 8hy",
    "addr:street":"Godsey Lane",
    "iso:country":"GB",
    "sg:address":"Godsey Lane",
    "sg:city":"Peterborough",
    "sg:classifiers":[
        {
            "category":"Food & Beverages",
            "subcategory":"Groceries & Convenience Stores",
            "type":"Retail Goods"
        }
    ],
    "sg:phone":"+44 1778 343822",
    "sg:postcode":"PE6 8HY",
    "sg:province":"Cambridgeshire",
    "wof:name":"Spar Stores",
    "wof:placetype":"venue"
},
  "geometry": {"coordinates":[-0.3172490001,52.6835365295],"type":"Point"}
}