{
  "type": "Feature",
  "properties": {
    "iso:country":"GB",
    "sg:address":"18 Fisher Street",
    "sg:city":"Carlisle",
    "sg:classifiers":[
        {
            "category":"Health Services",
            "subcategory":"Podiatrist",
            "type":"Services"
        }
    ],
    "sg:postcode":"CA3 8RH",
    "sg:province":"Cumbria",
    "sg:tags":[
        "podiatrists",
        "chiropodist"
    ],
    "wof:name":"Beattie Podiatry",
    "wof:placetype":"venue"
},
  "geometry": {"coordinates":[-2.937979,54.895897],"type":"Point"}
}