{
  "type": "Feature",
  "properties": {
    "addr:full":"Ashmead Business Centre, Ashmead Road, Keynsham Bristol City of Bristol BS31 1SX",
    "addr:postcode":"bs31 1sx",
    "addr:street":"Ashmead Road",
    "iso:country":"GB",
    "sg:address":"Ashmead Business Centre, Ashmead Road, Keynsham",
    "sg:city":"Bristol",
    "sg:classifiers":[
        {
            "category":"Shopping",
            "subcategory":"Computers & Home Electronics",
            "type":"Retail Goods"
        }
    ],
    "sg:phone":"+44 117 986 6668",
    "sg:postcode":"BS31 1SX",
    "sg:province":"City of Bristol",
    "sg:tags":[
        "electrical"
    ],
    "wof:name":"City Electrical Factors Ltd.",
    "wof:placetype":"venue"
},
  "geometry": {"coordinates":[-2.4964289665,51.4144706726],"type":"Point"}
}