{
  "type": "Feature",
  "properties": {
    "iso:country":"GB",
    "sg:address":"Inverboyndie Industrial Estate",
    "sg:city":"Banff",
    "sg:classifiers":[
        {
            "category":"Utilities",
            "subcategory":"Fuel Oil & Lpg",
            "type":"Services"
        }
    ],
    "sg:phone":"+44 1261 818493",
    "sg:postcode":"AB45 2JJ",
    "sg:province":"Aberdeenshire",
    "wof:name":"C & J Hepburn",
    "wof:placetype":"venue"
},
  "geometry": {"coordinates":[-2.5656039715,57.6678352356],"type":"Point"}
}