{
  "type": "Feature",
  "properties": {
    "addr:full":"Claverton Road, Wythenshawe, Roundthorn Industrial Estate Manchester Cheshire M23 9FT",
    "addr:postcode":"m23 9ft",
    "addr:street":"Claverton Road;Roundthorn Industrial Estate",
    "iso:country":"GB",
    "sg:address":"Claverton Road, Wythenshawe, Roundthorn Industrial Estate",
    "sg:city":"Manchester",
    "sg:classifiers":[
        {
            "category":"Shopping",
            "subcategory":"Stationery & Office Supplies",
            "type":"Retail Goods"
        }
    ],
    "sg:phone":"+44 161 998 9726",
    "sg:postcode":"M23 9FT",
    "sg:province":"Cheshire",
    "sg:tags":[
        "equipment",
        "educational",
        "school"
    ],
    "wof:name":"Klick Technology Ltd.",
    "wof:placetype":"venue"
},
  "geometry": {"coordinates":[-2.298059,53.389256],"type":"Point"}
}