{
  "type": "Feature",
  "properties": {
    "addr:full":"79 Beaconsfield St, Acomb York North Yorkshire YO24 4NB",
    "addr:housenumber":"79",
    "addr:postcode":"yo24 4nb",
    "addr:street":"Beaconsfield St",
    "iso:country":"GB",
    "sg:address":"79 Beaconsfield St, Acomb",
    "sg:city":"York",
    "sg:classifiers":[
        {
            "category":"Shopping",
            "subcategory":"Bicycles & Sporting Goods",
            "type":"Retail Goods"
        }
    ],
    "sg:phone":"+44 1904 799368",
    "sg:postcode":"YO24 4NB",
    "sg:province":"North Yorkshire",
    "sg:tags":[
        "cycle",
        "accessory"
    ],
    "wof:name":"Brian Shannon Cycles",
    "wof:placetype":"venue"
},
  "geometry": {"coordinates":[-1.1245620251,53.954662323],"type":"Point"}
}