{
  "type": "Feature",
  "properties": {
    "addr:full":"19 St Anselms Road Worthing West Sussex BN14 7EW",
    "addr:housenumber":"19",
    "addr:postcode":"bn14 7ew",
    "addr:street":"St Anselms Road",
    "iso:country":"GB",
    "sg:address":"19 St Anselms Road",
    "sg:city":"Worthing",
    "sg:classifiers":[
        {
            "category":"Professional",
            "type":"Services"
        }
    ],
    "sg:postcode":"BN14 7EW",
    "sg:province":"West Sussex",
    "sg:tags":[
        "reflexologists"
    ],
    "wof:name":"Glenda Foggett",
    "wof:placetype":"venue"
},
  "geometry": {"coordinates":[-0.3871819973,50.8196296692],"type":"Point"}
}