{
  "type": "Feature",
  "properties": {
    "addr:full":"788-790 Finchley Rd London Greater London NW11 7UR",
    "addr:housenumber":"788-790",
    "addr:postcode":"nw11 7ur",
    "addr:street":"Finchley Rd",
    "iso:country":"GB",
    "sg:address":"788-790 Finchley Rd",
    "sg:city":"London",
    "sg:classifiers":[
        {
            "category":"Building & Trades",
            "subcategory":"Construction",
            "type":"Services"
        }
    ],
    "sg:postcode":"NW11 7UR",
    "sg:province":"Greater London",
    "sg:tags":[
        "builder"
    ],
    "wof:name":"Everfirst Associates Ltd",
    "wof:placetype":"venue"
},
  "geometry": {"coordinates":[-0.196479,51.575459],"type":"Point"}
}