{
  "type": "Feature",
  "properties": {
    "addr:full":"11 Belmont Road Chislehurst Kent BR7 6HR",
    "addr:housenumber":"11",
    "addr:postcode":"br7 6hr",
    "addr:street":"Belmont Road",
    "iso:country":"GB",
    "sg:address":"11 Belmont Road",
    "sg:city":"Chislehurst",
    "sg:classifiers":[
        {
            "category":"Coffee & Tea",
            "type":"Food & Drink"
        }
    ],
    "sg:phone":"+44 20 8295 5599",
    "sg:postcode":"BR7 6HR",
    "sg:province":"Kent",
    "wof:name":"City Coffee Co.",
    "wof:placetype":"venue"
},
  "geometry": {"coordinates":[0.067015,51.421322],"type":"Point"}
}