{
  "type": "Feature",
  "properties": {
    "addr:full":"Highgate House Farm, Goldthorpe Rotherham South Yorkshire S63 9BJ",
    "addr:postcode":"s63 9bj",
    "addr:street":"Highgate;Rotherham South",
    "iso:country":"GB",
    "sg:address":"Highgate House Farm, Goldthorpe",
    "sg:city":"Rotherham",
    "sg:classifiers":[
        {
            "category":"Farming",
            "subcategory":"Livestock Farm",
            "type":"Manufacturing & Wholesale Goods"
        }
    ],
    "sg:postcode":"S63 9BJ",
    "sg:province":"South Yorkshire",
    "sg:tags":[
        "others"
    ],
    "wof:name":"R Seels & Son",
    "wof:placetype":"venue"
},
  "geometry": {"coordinates":[-1.304249,53.532574],"type":"Point"}
}