{
  "type": "Feature",
  "properties": {
    "addr:full":"Littlehampton Road, Ferring Worthing West Sussex BN12 6PW",
    "addr:postcode":"bn12 6pw",
    "addr:street":"Littlehampton Road",
    "iso:country":"GB",
    "sg:address":"Littlehampton Road, Ferring",
    "sg:city":"Worthing",
    "sg:classifiers":[
        {
            "category":"Cafe",
            "type":"Food & Drink"
        }
    ],
    "sg:postcode":"BN12 6PW",
    "sg:province":"West Sussex",
    "sg:tags":[
        "tea",
        "room"
    ],
    "wof:name":"Chris's Coffee Shop",
    "wof:placetype":"venue"
},
  "geometry": {"coordinates":[-0.442164,50.821636],"type":"Point"}
}