{
  "type": "Feature",
  "properties": {
    "addr:full":"Calderwood Square, East Kilbride Glasgow South Lanarkshire G74 3RF",
    "addr:postcode":"g74 3rf",
    "addr:street":"Calderwood Square",
    "iso:country":"GB",
    "sg:address":"Calderwood Square, East Kilbride",
    "sg:city":"Glasgow",
    "sg:classifiers":[
        {
            "category":"Bus Charters",
            "type":"Transportation"
        }
    ],
    "sg:postcode":"G74 3RF",
    "sg:province":"South Lanarkshire",
    "sg:tags":[
        "coach"
    ],
    "wof:name":"Ferguson Mini Coach Hire",
    "wof:placetype":"venue"
},
  "geometry": {"coordinates":[-4.1620659828,55.7753448486],"type":"Point"}
}