{
  "type": "Feature",
  "properties": {
    "addr:full":"Wyvenhoe Road Harrow Greater London HA2 8LS",
    "addr:postcode":"ha2 8ls",
    "addr:street":"Wyvenhoe Road",
    "iso:country":"GB",
    "sg:address":"Wyvenhoe Road",
    "sg:city":"Harrow",
    "sg:classifiers":[
        {
            "category":"Education",
            "subcategory":"School",
            "type":"Public Place"
        },
        {
            "category":"Government",
            "subcategory":"Office",
            "type":"Public Place"
        }
    ],
    "sg:phone":"+44 20 8422 4304",
    "sg:postcode":"HA2 8LS",
    "sg:province":"Greater London",
    "sg:tags":[
        "local",
        "authority"
    ],
    "wof:name":"Welldon Park Middle School",
    "wof:placetype":"venue"
},
  "geometry": {"coordinates":[-0.355614,51.561161],"type":"Point"}
}