{
  "type": "Feature",
  "properties": {
    "addr:full":"412 Clipsley Lane, Haydock St Helens Lancashire WA11 0SX",
    "addr:housenumber":"412",
    "addr:postcode":"wa11 0sx",
    "addr:street":"Clipsley Lane Haydock",
    "iso:country":"GB",
    "sg:address":"412 Clipsley Lane, Haydock",
    "sg:city":"St Helens",
    "sg:classifiers":[
        {
            "category":"Personal",
            "subcategory":"Tanning Parlor",
            "type":"Services"
        }
    ],
    "sg:phone":"+44 1744 611600",
    "sg:postcode":"WA11 0SX",
    "sg:province":"Lancashire",
    "sg:tags":[
        "sunbeds"
    ],
    "wof:name":"The Tanning Studio",
    "wof:placetype":"venue"
},
  "geometry": {"coordinates":[-2.669778,53.465801],"type":"Point"}
}