{
  "type": "Feature",
  "properties": {
    "iso:country":"GB",
    "sg:address":"34 Oldminster Road, Sharpness",
    "sg:city":"Berkeley",
    "sg:classifiers":[
        {
            "category":"Travel",
            "subcategory":"Hotels & Motels",
            "type":"Entertainment"
        }
    ],
    "sg:phone":"+44 1453 811255",
    "sg:postcode":"GL13 9NA",
    "sg:province":"Gloucestershire",
    "wof:name":"Pier View Hotel",
    "wof:placetype":"venue"
},
  "geometry": {"coordinates":[-2.4725170135,51.7172775269],"type":"Point"}
}