{
  "type": "Feature",
  "properties": {
    "iso:country":"GB",
    "sg:address":"98 Scudamore Road",
    "sg:city":"Leicester",
    "sg:classifiers":[
        {
            "category":"Shopping",
            "subcategory":"Photographic Equipment",
            "type":"Retail Goods"
        }
    ],
    "sg:phone":"+44 116 232 6091",
    "sg:postcode":"LE3 1UQ",
    "sg:province":"Leicestershire",
    "sg:tags":[
        "supply"
    ],
    "wof:name":"Shrewsbury Camera Exchange Ltd.",
    "wof:placetype":"venue"
},
  "geometry": {"coordinates":[-1.200792,52.634003],"type":"Point"}
}