{
  "type": "Feature",
  "properties": {
    "addr:full":"Unit 2 Smiths Buildings, Stephenson Way Crawley Surrey RH10 1TN",
    "addr:housenumber":"unit 2",
    "addr:postcode":"rh10 1tn",
    "addr:street":"Smiths Buildings Stephenson Way",
    "iso:country":"GB",
    "sg:address":"Unit 2 Smiths Buildings, Stephenson Way",
    "sg:city":"Crawley",
    "sg:classifiers":[
        {
            "category":"Retail",
            "subcategory":"Auto Repair",
            "type":"Services"
        }
    ],
    "sg:phone":"+44 1293 863444",
    "sg:postcode":"RH10 1TN",
    "sg:province":"Surrey",
    "sg:tags":[
        "modification",
        "garage"
    ],
    "wof:name":"Country Car The",
    "wof:placetype":"venue"
},
  "geometry": {"coordinates":[-0.184753,51.118458],"type":"Point"}
}