{
  "type": "Feature",
  "properties": {
    "iso:country":"GB",
    "sg:address":"Post Office Chambers, King Street",
    "sg:city":"Knutsford",
    "sg:classifiers":[
        {
            "category":"Organizations",
            "subcategory":"Membership Organization",
            "type":"Services"
        }
    ],
    "sg:postcode":"WA16 6EH",
    "sg:province":"Cheshire",
    "sg:tags":[
        "club"
    ],
    "wof:name":"Tatton Garden Society",
    "wof:placetype":"venue"
},
  "geometry": {"coordinates":[-2.376240015,53.3042030334],"type":"Point"}
}