{
  "type": "Feature",
  "properties": {
    "addr:full":"Cwmbach Road Aberdare Neath Port Talbot CF44 0NF",
    "addr:postcode":"cf44 0nf",
    "addr:street":"Cwmbach Road",
    "iso:country":"GB",
    "sg:address":"Cwmbach Road",
    "sg:city":"Aberdare",
    "sg:classifiers":[
        {
            "category":"Education",
            "subcategory":"School",
            "type":"Public Place"
        }
    ],
    "sg:phone":"+44 1685 872460",
    "sg:postcode":"CF44 0NF",
    "sg:province":"Neath Port Talbot",
    "sg:tags":[
        "local",
        "college",
        "authority"
    ],
    "wof:name":"Aberdare Girls Upper Comprehensive School",
    "wof:placetype":"venue"
},
  "geometry": {"coordinates":[-3.440684,51.714714],"type":"Point"}
}