{
  "type": "Feature",
  "properties": {
    "iso:country":"GB",
    "sg:address":"10 Bowling Road",
    "sg:city":"Ware",
    "sg:classifiers":[
        {
            "category":"Professional",
            "subcategory":"Printing & Photocopies",
            "type":"Services"
        }
    ],
    "sg:postcode":"SG12 7EE",
    "sg:province":"Hertfordshire",
    "sg:tags":[
        "printer"
    ],
    "wof:name":"Marketshot Ltd.",
    "wof:placetype":"venue"
},
  "geometry": {"coordinates":[-0.02674,51.810848],"type":"Point"}
}