{
  "type": "Feature",
  "properties": {
    "iso:country":"GB",
    "sg:address":"Nicol Rd, Chalfont St. Peter",
    "sg:city":"Gerrards Cross",
    "sg:classifiers":[
        {
            "category":"Utilities",
            "subcategory":"Recycling",
            "type":"Services"
        }
    ],
    "sg:phone":"+44 1753 882368",
    "sg:postcode":"SL9 9LY",
    "sg:province":"Buckinghamshire",
    "sg:tags":[
        "centre"
    ],
    "wof:name":"Dodds Bibko",
    "wof:placetype":"venue"
},
  "geometry": {"coordinates":[-0.570399,51.607555],"type":"Point"}
}