{
  "type": "Feature",
  "properties": {
    "iso:country":"GB",
    "sg:address":"34 George Street",
    "sg:city":"Perth",
    "sg:classifiers":[
        {
            "category":"Home & Garden",
            "subcategory":"Furniture",
            "type":"Retail Goods"
        }
    ],
    "sg:phone":"+44 1738 632211",
    "sg:postcode":"PH1 5JP",
    "sg:province":"Perth and Kinross",
    "wof:name":"Scandinavian Interiors",
    "wof:placetype":"venue"
},
  "geometry": {"coordinates":[-3.4276940823,56.3974189758],"type":"Point"}
}