{
  "type": "Feature",
  "properties": {
    "addr:full":"44-45 Marine Terrace Aberystwyth Ceredigion SY23 2BX",
    "addr:housenumber":"44-45",
    "addr:postcode":"sy23 2bx",
    "addr:street":"Marine Terrace",
    "iso:country":"GB",
    "sg:address":"44-45 Marine Terrace",
    "sg:city":"Aberystwyth",
    "sg:classifiers":[
        {
            "category":"Travel",
            "subcategory":"Hotels & Motels",
            "type":"Entertainment"
        }
    ],
    "sg:phone":"+44 1970 612201",
    "sg:postcode":"SY23 2BX",
    "sg:province":"Ceredigion",
    "wof:name":"Richmond Hotel",
    "wof:placetype":"venue"
},
  "geometry": {"coordinates":[-4.083989,52.418037],"type":"Point"}
}