{
  "type": "Feature",
  "properties": {
    "addr:full":"65 Park St Camberley Berkshire GU15 3PE",
    "addr:housenumber":"65",
    "addr:postcode":"gu15 3pe",
    "addr:street":"Park St",
    "iso:country":"GB",
    "sg:address":"65 Park St",
    "sg:city":"Camberley",
    "sg:classifiers":[
        {
            "category":"Communications",
            "type":"Services"
        }
    ],
    "sg:postcode":"GU15 3PE",
    "sg:province":"Berkshire",
    "sg:tags":[
        "data",
        "network"
    ],
    "wof:name":"Defacto Distribution Ltd",
    "wof:placetype":"venue"
},
  "geometry": {"coordinates":[-0.7474089861,51.3366241455],"type":"Point"}
}