{
  "type": "Feature",
  "properties": {
    "addr:full":"108 Shenley Road Borehamwood Hertfordshire WD6 1EB",
    "addr:housenumber":"108",
    "addr:postcode":"wd6 1eb",
    "addr:street":"Shenley Road",
    "iso:country":"GB",
    "sg:address":"108 Shenley Road",
    "sg:city":"Borehamwood",
    "sg:classifiers":[
        {
            "category":"Restaurant",
            "type":"Food & Drink"
        }
    ],
    "sg:phone":"+44 20 8953 9141",
    "sg:postcode":"WD6 1EB",
    "sg:province":"Hertfordshire",
    "wof:name":"Greenfields Restaurant",
    "wof:placetype":"venue"
},
  "geometry": {"coordinates":[-0.2742170095,51.6562843323],"type":"Point"}
}