{
  "type": "Feature",
  "properties": {
    "addr:full":"66 Bedford Place Southampton Hampshire SO15 2DS",
    "addr:housenumber":"66",
    "addr:postcode":"so15 2ds",
    "addr:street":"Bedford Place",
    "iso:country":"GB",
    "sg:address":"66 Bedford Place",
    "sg:city":"Southampton",
    "sg:classifiers":[
        {
            "category":"Cafe",
            "type":"Food & Drink"
        }
    ],
    "sg:phone":"+44 23 9922 2299",
    "sg:postcode":"SO15 2DS",
    "sg:province":"Hampshire",
    "sg:tags":[
        "tea",
        "snack",
        "bar",
        "room"
    ],
    "wof:name":"Millies Tea Room",
    "wof:placetype":"venue"
},
  "geometry": {"coordinates":[-1.406665,50.913239],"type":"Point"}
}