{
  "type": "Feature",
  "properties": {
    "iso:country":"GB",
    "sg:address":"14 Castlebay, Vatersay",
    "sg:city":"Castlebay",
    "sg:classifiers":[
        {
            "category":"Government",
            "subcategory":"Post Office",
            "type":"Public Place"
        }
    ],
    "sg:phone":"+44 1871 810371",
    "sg:postcode":"HS9 5YW",
    "sg:province":"Eilean Siar",
    "wof:name":"Vatersay Post Office",
    "wof:placetype":"venue"
},
  "geometry": {"coordinates":[-7.4770708084,56.9590072632],"type":"Point"}
}