{
  "type": "Feature",
  "properties": {
    "iso:country":"GB",
    "sg:address":"Tanner House, 54-58 Tanner Street",
    "sg:city":"London",
    "sg:classifiers":[
        {
            "category":"Sports & Exercise",
            "subcategory":"Bowling",
            "type":"Entertainment"
        }
    ],
    "sg:postcode":"SE1 3PH",
    "sg:province":"Greater London",
    "sg:tags":[
        "photography"
    ],
    "wof:name":"Action Plus Photographic",
    "wof:placetype":"venue"
},
  "geometry": {"coordinates":[-0.0774839967,51.4997406006],"type":"Point"}
}