{
  "type": "Feature",
  "properties": {
    "iso:country":"GB",
    "sg:address":"1a Albion Road West",
    "sg:city":"North Shields",
    "sg:classifiers":[
        {
            "category":"Personal",
            "subcategory":"Beauty Salon",
            "type":"Services"
        },
        {
            "category":"Personal",
            "subcategory":"Barber",
            "type":"Services"
        }
    ],
    "sg:phone":"+44 191 296 1241",
    "sg:postcode":"NE29 0JA",
    "sg:province":"Tyne and Wear",
    "sg:tags":[
        "unisex",
        "hairdresser"
    ],
    "wof:name":"Rumours",
    "wof:placetype":"venue"
},
  "geometry": {"coordinates":[-1.4533799887,55.0090827942],"type":"Point"}
}