{
  "type": "Feature",
  "properties": {
    "iso:country":"GB",
    "sg:address":"51 Cranmer Ave",
    "sg:city":"Hove",
    "sg:classifiers":[
        {
            "category":"Building & Trades",
            "subcategory":"Plumbing",
            "type":"Services"
        }
    ],
    "sg:postcode":"BN3 7JP",
    "sg:province":"East Sussex",
    "sg:tags":[
        "central",
        "heating"
    ],
    "wof:name":"Taylor,John,",
    "wof:placetype":"venue"
},
  "geometry": {"coordinates":[-0.186775,50.839901],"type":"Point"}
}