{
  "type": "Feature",
  "properties": {
    "addr:full":"40 Ivanhoe Close Doncaster South Yorkshire DN5 8DY",
    "addr:housenumber":"40",
    "addr:postcode":"dn5 8dy",
    "addr:street":"Ivanhoe Close",
    "iso:country":"GB",
    "sg:address":"40 Ivanhoe Close",
    "sg:city":"Doncaster",
    "sg:classifiers":[
        {
            "category":"Home & Garden",
            "subcategory":"Household Appliances",
            "type":"Retail Goods"
        },
        {
            "category":"Retail",
            "subcategory":"Repair Shop",
            "type":"Services"
        }
    ],
    "sg:phone":"+44 1302 785919",
    "sg:postcode":"DN5 8DY",
    "sg:province":"South Yorkshire",
    "sg:tags":[
        "machine",
        "electrical",
        "washing"
    ],
    "wof:name":"Barry Heaton",
    "wof:placetype":"venue"
},
  "geometry": {"coordinates":[-1.15734303,53.529335022],"type":"Point"}
}