{
  "type": "Feature",
  "properties": {
    "iso:country":"GB",
    "sg:address":"Tanner Pl, 54-58 Tanner St",
    "sg:city":"Southwark",
    "sg:classifiers":[
        {
            "category":"Food & Beverages",
            "subcategory":"Liquor & Beverages",
            "type":"Retail Goods"
        }
    ],
    "sg:phone":"+44 20 7787 0111",
    "sg:postcode":"SE1 3PH",
    "sg:province":"Greater London",
    "sg:tags":[
        "beer",
        "spirit",
        "wines"
    ],
    "wof:name":"European Wholesale Wines & Spirits",
    "wof:placetype":"venue"
},
  "geometry": {"coordinates":[-0.0782200024,51.4997787476],"type":"Point"}
}