{
  "type": "Feature",
  "properties": {
    "addr:full":"Charlton Kings Industrial Estate, Cirencester Road Cheltenham Gloucestershire GL53 8DZ",
    "addr:postcode":"gl53 8dz",
    "addr:street":"Industrial Estate Cirencester Road",
    "iso:country":"GB",
    "sg:address":"Charlton Kings Industrial Estate, Cirencester Road",
    "sg:city":"Cheltenham",
    "sg:classifiers":[
        {
            "category":"Manufacturing",
            "subcategory":"Metals",
            "type":"Manufacturing & Wholesale Goods"
        }
    ],
    "sg:postcode":"GL53 8DZ",
    "sg:province":"Gloucestershire",
    "sg:tags":[
        "work",
        "sheet"
    ],
    "wof:name":"Charlton Kings Engineering Ltd.",
    "wof:placetype":"venue"
},
  "geometry": {"coordinates":[-2.05417,51.875961],"type":"Point"}
}