{
  "type": "Feature",
  "properties": {
    "addr:full":"14 Kings Haven Close, Charfleets Industrial Estate Canvey Island Essex SS8 0PW",
    "addr:housenumber":"14",
    "addr:postcode":"ss8 0pw",
    "addr:street":"Kings Haven Close;Industrial Estate",
    "iso:country":"GB",
    "sg:address":"14 Kings Haven Close, Charfleets Industrial Estate",
    "sg:city":"Canvey Island",
    "sg:classifiers":[
        {
            "category":"Shopping",
            "subcategory":"Stationery & Office Supplies",
            "type":"Retail Goods"
        }
    ],
    "sg:phone":"+44 1268 684636",
    "sg:postcode":"SS8 0PW",
    "sg:province":"Essex",
    "sg:tags":[
        "printers'"
    ],
    "wof:name":"L P Finishing & Packaging",
    "wof:placetype":"venue"
},
  "geometry": {"coordinates":[0.5911200047,51.5203742981],"type":"Point"}
}