{
  "type": "Feature",
  "properties": {
    "addr:full":"Market Place Barton-upon-humber Lincolnshire DN18 5DA",
    "addr:postcode":"dn18 5da",
    "addr:street":"Market Place",
    "iso:country":"GB",
    "sg:address":"Market Place",
    "sg:city":"Barton-upon-humber",
    "sg:classifiers":[
        {
            "category":"Organizations",
            "subcategory":"Community Association",
            "type":"Services"
        },
        {
            "category":"Organizations",
            "subcategory":"Membership Organization",
            "type":"Services"
        }
    ],
    "sg:phone":"+44 1652 632104",
    "sg:postcode":"DN18 5DA",
    "sg:province":"Lincolnshire",
    "sg:tags":[
        "club",
        "social"
    ],
    "wof:name":"CONSTITUTIONAL CLUB",
    "wof:placetype":"venue"
},
  "geometry": {"coordinates":[-0.4379940033,53.6824951172],"type":"Point"}
}