{
  "type": "Feature",
  "properties": {
    "iso:country":"GB",
    "sg:address":"8 Boulton Cotts, Heybridge",
    "sg:city":"Maldon",
    "sg:classifiers":[
        {
            "category":"Building & Trades",
            "subcategory":"Landscaping Services",
            "type":"Services"
        }
    ],
    "sg:postcode":"CM9 4AD",
    "sg:province":"Essex",
    "sg:tags":[
        "landscape",
        "contractor"
    ],
    "wof:name":"Fitz,Tony,",
    "wof:placetype":"venue"
},
  "geometry": {"coordinates":[0.692628,51.740593],"type":"Point"}
}