{
  "type": "Feature",
  "properties": {
    "iso:country":"GB",
    "sg:address":"80 The Bdwy",
    "sg:city":"Greenford",
    "sg:classifiers":[
        {
            "category":"Real Estate",
            "subcategory":"Real Estate Agent",
            "type":"Services"
        }
    ],
    "sg:phone":"+44 20 8575 1144",
    "sg:postcode":"UB6 9QA",
    "sg:province":"Greater London",
    "wof:name":"Rolfe East & Co.",
    "wof:placetype":"venue"
},
  "geometry": {"coordinates":[-0.3530989885,51.5276794434],"type":"Point"}
}