{
  "type": "Feature",
  "properties": {
    "iso:country":"GB",
    "sg:address":"45 Bath Road",
    "sg:city":"Swindon",
    "sg:classifiers":[
        {
            "category":"Health Services",
            "subcategory":"Dentist",
            "type":"Services"
        }
    ],
    "sg:phone":"+44 1793 522120",
    "sg:postcode":"SN1 4AU",
    "sg:province":"Wiltshire",
    "wof:name":"Eurodental",
    "wof:placetype":"venue"
},
  "geometry": {"coordinates":[-1.779639,51.552502],"type":"Point"}
}