{
  "type": "Feature",
  "properties": {
    "addr:full":"Broughton Road, Durton Lane Preston Lancashire PR1 5LD",
    "addr:postcode":"pr1 5ld",
    "addr:street":"Broughton Road Durton Lane",
    "iso:country":"GB",
    "sg:address":"Broughton Road, Durton Lane",
    "sg:city":"Preston",
    "sg:classifiers":[
        {
            "category":"Health Services",
            "subcategory":"Hospital",
            "type":"Services"
        }
    ],
    "sg:phone":"+44 1772 861133",
    "sg:postcode":"PR1 5LD",
    "sg:province":"Lancashire",
    "wof:name":"Northern Clinic of Cosmetic Surgery Ltd.",
    "wof:placetype":"venue"
},
  "geometry": {"coordinates":[-2.705729,53.757961],"type":"Point"}
}