{
  "type": "Feature",
  "properties": {
    "iso:country":"GB",
    "sg:address":"Beaumont Ho, Lambton Rd, Raynes Park",
    "sg:city":"Raynes Park",
    "sg:classifiers":[
        {
            "category":"Professional",
            "subcategory":"Accounting & Tax Preparation",
            "type":"Services"
        }
    ],
    "sg:phone":"+44 20 8255 8008",
    "sg:postcode":"SW20 0LW",
    "sg:province":"Greater London",
    "sg:tags":[
        "accountant"
    ],
    "wof:name":"Castles",
    "wof:placetype":"venue"
},
  "geometry": {"coordinates":[-0.226519,51.411095],"type":"Point"}
}