{
  "type": "Feature",
  "properties": {
    "iso:country":"GB",
    "sg:address":"Ivy Cottage, West End Road, Norton",
    "sg:city":"Doncaster",
    "sg:classifiers":[
        {
            "category":"Building & Trades",
            "subcategory":"Construction",
            "type":"Services"
        }
    ],
    "sg:phone":"+44 1302 701335",
    "sg:postcode":"DN6 9EF",
    "sg:province":"North Yorkshire",
    "sg:tags":[
        "roofing"
    ],
    "wof:name":"K Humphries & Sons",
    "wof:placetype":"venue"
},
  "geometry": {"coordinates":[-1.1705240011,53.632434845],"type":"Point"}
}