{
  "type": "Feature",
  "properties": {
    "addr:full":"37 New Street, Three Bridges Crawley Surrey RH10 1LP",
    "addr:housenumber":"37",
    "addr:postcode":"rh10 1lp",
    "addr:street":"New Street",
    "iso:country":"GB",
    "sg:address":"37 New Street, Three Bridges",
    "sg:city":"Crawley",
    "sg:classifiers":[
        {
            "category":"Professional",
            "subcategory":"Printing & Photocopies",
            "type":"Services"
        }
    ],
    "sg:phone":"+44 1293 528455",
    "sg:postcode":"RH10 1LP",
    "sg:province":"Surrey",
    "sg:tags":[
        "printer"
    ],
    "wof:name":"The Woodcote Press Ltd.",
    "wof:placetype":"venue"
},
  "geometry": {"coordinates":[-0.1654620022,51.1183586121],"type":"Point"}
}