{
  "type": "Feature",
  "properties": {
    "iso:country":"GB",
    "sg:address":"Maes-y-fynnon, Penrhosgarnedd",
    "sg:city":"Bangor",
    "sg:classifiers":[
        {
            "category":"Utilities",
            "subcategory":"Water",
            "type":"Services"
        }
    ],
    "sg:phone":"+44 800 052 0130",
    "sg:postcode":"LL57 2DN",
    "sg:province":"Gwynedd",
    "wof:name":"Welsh Water International Ltd",
    "wof:placetype":"venue"
},
  "geometry": {"coordinates":[-4.126064,53.229595],"type":"Point"}
}