{
  "type": "Feature",
  "properties": {
    "iso:country":"GB",
    "sg:address":"The Country Gardens, Bath Road",
    "sg:city":"Hungerford",
    "sg:classifiers":[
        {
            "category":"Education",
            "subcategory":"Music School",
            "type":"Public Place"
        },
        {
            "category":"Home & Garden",
            "subcategory":"Hardware",
            "type":"Retail Goods"
        }
    ],
    "sg:phone":"+44 1488 685487",
    "sg:postcode":"RG17 0HE",
    "sg:province":"Berkshire",
    "sg:tags":[
        "conservatory",
        "improvement",
        "centre"
    ],
    "wof:name":"Ridgeway Home Improvement Ltd.",
    "wof:placetype":"venue"
},
  "geometry": {"coordinates":[-1.516156,51.413197],"type":"Point"}
}