{
  "type": "Feature",
  "properties": {
    "addr:full":"42 Dymoke Road Hornchurch Essex RM11 1AA",
    "addr:housenumber":"42",
    "addr:postcode":"rm11 1aa",
    "addr:street":"Dymoke Road",
    "iso:country":"GB",
    "sg:address":"42 Dymoke Road",
    "sg:city":"Hornchurch",
    "sg:classifiers":[
        {
            "category":"Sports & Exercise",
            "subcategory":"Skate Park",
            "type":"Entertainment"
        }
    ],
    "sg:phone":"+44 1708 720727",
    "sg:postcode":"RM11 1AA",
    "sg:province":"Essex",
    "sg:tags":[
        "mnfrs",
        "brake",
        "clutch"
    ],
    "wof:name":"Industrial & Commerical Linings Ltd.",
    "wof:placetype":"venue"
},
  "geometry": {"coordinates":[0.1892630011,51.5704269409],"type":"Point"}
}