{
  "type": "Feature",
  "properties": {
    "addr:full":"Priory Lane, Little Wymondley Hitchin Hertfordshire SG4 7HE",
    "addr:postcode":"sg4 7he",
    "addr:street":"Priory Lane",
    "iso:country":"GB",
    "sg:address":"Priory Lane, Little Wymondley",
    "sg:city":"Hitchin",
    "sg:classifiers":[
        {
            "category":"Shopping",
            "subcategory":"Antiques",
            "type":"Retail Goods"
        }
    ],
    "sg:phone":"+44 1438 315386",
    "sg:postcode":"SG4 7HE",
    "sg:province":"Hertfordshire",
    "wof:name":"Wymondley Antiques",
    "wof:placetype":"venue"
},
  "geometry": {"coordinates":[-0.233809,51.93272],"type":"Point"}
}