{
  "type": "Feature",
  "properties": {
    "iso:country":"GB",
    "sg:address":"35 Thingwall Road",
    "sg:city":"Wirral",
    "sg:classifiers":[
        {
            "category":"Health Services",
            "subcategory":"Dentist",
            "type":"Services"
        }
    ],
    "sg:phone":"+44 151 648 1974",
    "sg:postcode":"CH61 3UE",
    "sg:province":"Merseyside",
    "wof:name":"D Harrison",
    "wof:placetype":"venue"
},
  "geometry": {"coordinates":[-3.097268,53.354713],"type":"Point"}
}