{
  "type": "Feature",
  "properties": {
    "addr:full":"37a Stockport Road, Woodley Stockport Cheshire SK6 1AL",
    "addr:housenumber":"37a",
    "addr:postcode":"sk6 1al",
    "addr:street":"Stockport Road",
    "iso:country":"GB",
    "sg:address":"37a Stockport Road, Woodley",
    "sg:city":"Stockport",
    "sg:classifiers":[
        {
            "category":"Personal",
            "subcategory":"Beauty Salon",
            "type":"Services"
        }
    ],
    "sg:postcode":"SK6 1AL",
    "sg:province":"Cheshire",
    "sg:tags":[
        "unisex",
        "hairdresser"
    ],
    "wof:name":"Christian Leonard",
    "wof:placetype":"venue"
},
  "geometry": {"coordinates":[-2.107451,53.424049],"type":"Point"}
}