{
  "type": "Feature",
  "properties": {
    "addr:full":"Gosford Road Ottery St Mary Devon EX11 1LZ",
    "addr:postcode":"ex11 1lz",
    "addr:street":"Gosford Road",
    "iso:country":"GB",
    "sg:address":"Gosford Road",
    "sg:city":"Ottery St Mary",
    "sg:classifiers":[
        {
            "category":"Home & Garden",
            "subcategory":"Garden Supply",
            "type":"Retail Goods"
        },
        {
            "category":"Shopping",
            "subcategory":"Florist",
            "type":"Retail Goods"
        }
    ],
    "sg:phone":"+44 1404 815815",
    "sg:postcode":"EX11 1LZ",
    "sg:province":"Devon",
    "sg:tags":[
        "nursery",
        "centre"
    ],
    "wof:name":"Otter Nurseries (Torbay) Ltd.",
    "wof:placetype":"venue"
},
  "geometry": {"coordinates":[-3.2728970051,50.7625427246],"type":"Point"}
}