{
  "type": "Feature",
  "properties": {
    "iso:country":"GB",
    "sg:address":"44 Royal Parade Mews",
    "sg:city":"London",
    "sg:classifiers":[
        {
            "category":"Home & Garden",
            "subcategory":"Building Materials",
            "type":"Retail Goods"
        }
    ],
    "sg:postcode":"SE3 0TN",
    "sg:province":"Greater London",
    "sg:tags":[
        "system",
        "staircase"
    ],
    "wof:name":"H A Chibrall Engineering",
    "wof:placetype":"venue"
},
  "geometry": {"coordinates":[0.007516,51.4670562744],"type":"Point"}
}