{
  "type": "Feature",
  "properties": {
    "addr:full":"6 Southey Road Worthing West Sussex BN11 3HT",
    "addr:housenumber":"6",
    "addr:postcode":"bn11 3ht",
    "addr:street":"Southey Road",
    "iso:country":"GB",
    "sg:address":"6 Southey Road",
    "sg:city":"Worthing",
    "sg:classifiers":[
        {
            "category":"Health Services",
            "subcategory":"Clinic",
            "type":"Services"
        }
    ],
    "sg:postcode":"BN11 3HT",
    "sg:province":"West Sussex",
    "sg:tags":[
        "nh"
    ],
    "wof:name":"Child & Family Consultation Service",
    "wof:placetype":"venue"
},
  "geometry": {"coordinates":[-0.382288,50.81044],"type":"Point"}
}