{
  "type": "Feature",
  "properties": {
    "iso:country":"GB",
    "sg:address":"22 Church Lane",
    "sg:city":"Oxted",
    "sg:classifiers":[
        {
            "category":"Professional",
            "subcategory":"Printing & Photocopies",
            "type":"Services"
        }
    ],
    "sg:phone":"+44 1883 714020",
    "sg:postcode":"RH8 9LB",
    "sg:province":"Surrey",
    "sg:tags":[
        "printer"
    ],
    "wof:name":"Foot Print",
    "wof:placetype":"venue"
},
  "geometry": {"coordinates":[-0.010484,51.254742],"type":"Point"}
}