{
  "type": "Feature",
  "properties": {
    "addr:full":"2 Rowcroft Stroud Gloucestershire GL5 3BB",
    "addr:housenumber":"2",
    "addr:postcode":"gl5 3bb",
    "addr:street":"Rowcroft",
    "iso:country":"GB",
    "sg:address":"2 Rowcroft",
    "sg:city":"Stroud",
    "sg:classifiers":[
        {
            "category":"Professional",
            "subcategory":"Lawyer & Legal Services",
            "type":"Services"
        }
    ],
    "sg:phone":"+44 1453 763433",
    "sg:postcode":"GL5 3BB",
    "sg:province":"Gloucestershire",
    "sg:tags":[
        "solicitor"
    ],
    "wof:name":"Goldinghams",
    "wof:placetype":"venue"
},
  "geometry": {"coordinates":[-2.219844,51.745037],"type":"Point"}
}