{
  "type": "Feature",
  "properties": {
    "addr:full":"18 Churchfield Road, Walton Peterborough Cambridgeshire PE4 6HD",
    "addr:housenumber":"18",
    "addr:postcode":"pe4 6hd",
    "addr:street":"Churchfield Road",
    "iso:country":"GB",
    "sg:address":"18 Churchfield Road, Walton",
    "sg:city":"Peterborough",
    "sg:classifiers":[
        {
            "category":"Retail",
            "subcategory":"Auto Repair",
            "type":"Services"
        }
    ],
    "sg:phone":"+44 1733 577090",
    "sg:postcode":"PE4 6HD",
    "sg:province":"Cambridgeshire",
    "sg:tags":[
        "body",
        "car",
        "repairer"
    ],
    "wof:name":"Threeways Crash Repair Centre Ltd",
    "wof:placetype":"venue"
},
  "geometry": {"coordinates":[-0.2624289989,52.6022224426],"type":"Point"}
}