{
  "type": "Feature",
  "properties": {
    "addr:full":"Unit 9 Salcombe Road, Meadow Lane Industrial Estate Alfreton Derbyshire DE55 7RG",
    "addr:housenumber":"unit 9;estate",
    "addr:postcode":"de55 7rg",
    "addr:street":"Salcombe Road Meadow Lane Industrial",
    "iso:country":"GB",
    "sg:address":"Unit 9 Salcombe Road, Meadow Lane Industrial Estate",
    "sg:city":"Alfreton",
    "sg:classifiers":[
        {
            "category":"Mining & Drilling",
            "type":"Manufacturing & Wholesale Goods"
        }
    ],
    "sg:phone":"+44 1773 521382",
    "sg:postcode":"DE55 7RG",
    "sg:province":"Derbyshire",
    "sg:tags":[
        "contractor"
    ],
    "wof:name":"Rig Services Ltd.",
    "wof:placetype":"venue"
},
  "geometry": {"coordinates":[-1.3751289845,53.1016387939],"type":"Point"}
}