{
  "type": "Feature",
  "properties": {
    "addr:full":"Meliden Road Prestatyn Denbighshire LL19 8NR",
    "addr:postcode":"ll19 8nr",
    "addr:street":"Meliden Road",
    "iso:country":"GB",
    "sg:address":"Meliden Road",
    "sg:city":"Prestatyn",
    "sg:classifiers":[
        {
            "category":"Retail",
            "subcategory":"Auto Repair",
            "type":"Services"
        }
    ],
    "sg:phone":"+44 1745 887313",
    "sg:postcode":"LL19 8NR",
    "sg:province":"Denbighshire",
    "sg:tags":[
        "modification",
        "garage"
    ],
    "wof:name":"Meliden Motor Repairs",
    "wof:placetype":"venue"
},
  "geometry": {"coordinates":[-3.404294,53.326969],"type":"Point"}
}