{
  "type": "Feature",
  "properties": {
    "iso:country":"GB",
    "sg:address":"1 Great Cumberland Place",
    "sg:city":"London",
    "sg:classifiers":[
        {
            "category":"Arts & Performance",
            "subcategory":"Theater",
            "type":"Entertainment"
        }
    ],
    "sg:postcode":"W1H 7LW",
    "sg:province":"Greater London",
    "sg:tags":[
        "theatre"
    ],
    "wof:name":"Effective Theatrical Productions Ltd",
    "wof:placetype":"venue"
},
  "geometry": {"coordinates":[-0.159327,51.513794],"type":"Point"}
}