{
  "type": "Feature",
  "properties": {
    "addr:full":"Hanover House Liverpool Merseyside L1 3DZ",
    "addr:postcode":"l1 3dz",
    "iso:country":"GB",
    "sg:address":"Hanover House",
    "sg:city":"Liverpool",
    "sg:classifiers":[
        {
            "category":"Health Services",
            "subcategory":"Clinic",
            "type":"Services"
        }
    ],
    "sg:phone":"+44 870 990 9702",
    "sg:postcode":"L1 3DZ",
    "sg:province":"Merseyside",
    "sg:tags":[
        "abuse",
        "drug"
    ],
    "wof:name":"Hit",
    "wof:placetype":"venue"
},
  "geometry": {"coordinates":[-2.978481,53.409775],"type":"Point"}
}