{
  "type": "Feature",
  "properties": {
    "addr:full":"24 Balls Pond Road London Greater London N1 4AU",
    "addr:housenumber":"24",
    "addr:postcode":"n1 4au",
    "addr:street":"Balls Pond Road",
    "iso:country":"GB",
    "sg:address":"24 Balls Pond Road",
    "sg:city":"London",
    "sg:classifiers":[
        {
            "category":"Shopping",
            "subcategory":"Gifts & Souvenirs",
            "type":"Retail Goods"
        }
    ],
    "sg:postcode":"N1 4AU",
    "sg:province":"Greater London",
    "sg:tags":[
        "shop"
    ],
    "wof:name":"Sally Tonyin",
    "wof:placetype":"venue"
},
  "geometry": {"coordinates":[-0.07717,51.546211],"type":"Point"}
}