{
  "type": "Feature",
  "properties": {
    "addr:full":"78 Langley Road, Chedgrave Norwich Norfolk NR14 6HE",
    "addr:housenumber":"78",
    "addr:postcode":"nr14 6he",
    "addr:street":"Langley Road",
    "iso:country":"GB",
    "sg:address":"78 Langley Road, Chedgrave",
    "sg:city":"Norwich",
    "sg:classifiers":[
        {
            "category":"Sports & Exercise",
            "subcategory":"Gym",
            "type":"Entertainment"
        }
    ],
    "sg:postcode":"NR14 6HE",
    "sg:province":"Norfolk",
    "sg:tags":[
        "fitness",
        "health",
        "centre"
    ],
    "wof:name":"Shape Up Slimming Club",
    "wof:placetype":"venue"
},
  "geometry": {"coordinates":[1.48162,52.542995],"type":"Point"}
}