{
  "type": "Feature",
  "properties": {
    "addr:full":"13 Hope Carr Road Leigh Lancashire WN7 3ET",
    "addr:housenumber":"13",
    "addr:postcode":"wn7 3et",
    "addr:street":"Hope Carr Road Leigh",
    "iso:country":"GB",
    "sg:address":"13 Hope Carr Road",
    "sg:city":"Leigh",
    "sg:classifiers":[
        {
            "category":"Fast Food",
            "type":"Food & Drink"
        },
        {
            "category":"Food & Beverages",
            "subcategory":"Meat & Fish",
            "type":"Retail Goods"
        }
    ],
    "sg:postcode":"WN7 3ET",
    "sg:province":"Lancashire",
    "sg:tags":[
        "chip",
        "away",
        "take"
    ],
    "wof:name":"Leslie & Hilary Ann Prescott",
    "wof:placetype":"venue"
},
  "geometry": {"coordinates":[-2.511571,53.490547],"type":"Point"}
}