{
  "type": "Feature",
  "properties": {
    "iso:country":"GB",
    "sg:address":"Tudor Cottage, Headcorn Road",
    "sg:city":"Maidstone",
    "sg:classifiers":[
        {
            "category":"Building & Trades",
            "subcategory":"Plumbing",
            "type":"Services"
        }
    ],
    "sg:postcode":"ME17 2AP",
    "sg:province":"Kent",
    "sg:tags":[
        "heating"
    ],
    "wof:name":"Barry Wheble",
    "wof:placetype":"venue"
},
  "geometry": {"coordinates":[0.677940011,51.2065887451],"type":"Point"}
}