{
  "type": "Feature",
  "properties": {
    "iso:country":"GB",
    "sg:address":"14 Clifford Close",
    "sg:city":"Droitwich",
    "sg:classifiers":[
        {
            "category":"Shopping",
            "type":"Retail Goods"
        }
    ],
    "sg:postcode":"WR9 8UT",
    "sg:province":"Worcestershire",
    "sg:tags":[
        "part",
        "accessory"
    ],
    "wof:name":"Precision Parts International",
    "wof:placetype":"venue"
},
  "geometry": {"coordinates":[-2.162047,52.251148],"type":"Point"}
}