{
  "type": "Feature",
  "properties": {
    "addr:full":"6 Hammet Street Taunton Somerset TA1 1RZ",
    "addr:housenumber":"6",
    "addr:postcode":"ta1 1rz",
    "addr:street":"Hammet Street",
    "iso:country":"GB",
    "sg:address":"6 Hammet Street",
    "sg:city":"Taunton",
    "sg:classifiers":[
        {
            "category":"Professional",
            "subcategory":"Lawyer & Legal Services",
            "type":"Services"
        }
    ],
    "sg:phone":"+44 808 032 3123",
    "sg:postcode":"TA1 1RZ",
    "sg:province":"Somerset",
    "sg:tags":[
        "solicitor"
    ],
    "wof:name":"Harris Fowler",
    "wof:placetype":"venue"
},
  "geometry": {"coordinates":[-3.1020419598,51.015411377],"type":"Point"}
}