{
  "type": "Feature",
  "properties": {
    "addr:full":"Unit 7 Foundry La Leicester Leicestershire LE1 3WU",
    "addr:housenumber":"unit 7",
    "addr:postcode":"le1 3wu",
    "addr:street":"Foundry La Leicester",
    "iso:country":"GB",
    "sg:address":"Unit 7 Foundry La",
    "sg:city":"Leicester",
    "sg:classifiers":[
        {
            "category":"Home & Garden",
            "subcategory":"Carpets & Floor Coverings",
            "type":"Retail Goods"
        }
    ],
    "sg:postcode":"LE1 3WU",
    "sg:province":"Leicestershire",
    "sg:tags":[
        "trimming",
        "trimmer"
    ],
    "wof:name":"Arena Trims",
    "wof:placetype":"venue"
},
  "geometry": {"coordinates":[-1.128973,52.64291],"type":"Point"}
}