{
  "type": "Feature",
  "properties": {
    "addr:full":"32 Cyprus Avenue, Elderslie Johnstone Renfrewshire PA5 9NB",
    "addr:housenumber":"32",
    "addr:postcode":"pa5 9nb",
    "addr:street":"Cyprus Avenue Elderslie",
    "iso:country":"GB",
    "sg:address":"32 Cyprus Avenue, Elderslie",
    "sg:city":"Johnstone",
    "sg:classifiers":[
        {
            "category":"Home & Garden",
            "subcategory":"Home Furnishings",
            "type":"Retail Goods"
        }
    ],
    "sg:phone":"+44 1505 344660",
    "sg:postcode":"PA5 9NB",
    "sg:province":"Renfrewshire",
    "sg:tags":[
        "blind",
        "curtain",
        "fitting"
    ],
    "wof:name":"Blind Cleaning Co",
    "wof:placetype":"venue"
},
  "geometry": {"coordinates":[-4.4955368042,55.8301200867],"type":"Point"}
}