{
  "type": "Feature",
  "properties": {
    "iso:country":"GB",
    "sg:address":"M62 Trad Est, Larsen Rd",
    "sg:city":"Goole",
    "sg:classifiers":[
        {
            "category":"Manufacturing",
            "subcategory":"Buildings",
            "type":"Manufacturing & Wholesale Goods"
        }
    ],
    "sg:postcode":"DN14 6XF",
    "sg:province":"East Riding of Yorkshire",
    "sg:tags":[
        "portable"
    ],
    "wof:name":"Universal Hire Ltd",
    "wof:placetype":"venue"
},
  "geometry": {"coordinates":[-0.874499,53.704514],"type":"Point"}
}