{
  "type": "Feature",
  "properties": {
    "addr:full":"Up Corner Cottage, Silver Hill Chalfont St. Giles Buckinghamshire HP8 4PS",
    "addr:postcode":"st. giles;hp8 4ps",
    "addr:street":"Silver Hill Chalfont",
    "iso:country":"GB",
    "sg:address":"Up Corner Cottage, Silver Hill",
    "sg:city":"Chalfont St. Giles",
    "sg:classifiers":[
        {
            "category":"Professional",
            "subcategory":"Business Services",
            "type":"Services"
        }
    ],
    "sg:phone":"+44 1494 873303",
    "sg:postcode":"HP8 4PS",
    "sg:province":"Buckinghamshire",
    "sg:tags":[
        "import",
        "export",
        "agent"
    ],
    "wof:name":"Norton Megaw-uK Representative",
    "wof:placetype":"venue"
},
  "geometry": {"coordinates":[-0.576628983,51.6299247742],"type":"Point"}
}