{
  "type": "Feature",
  "properties": {
    "addr:full":"Church Lane, Thurlaston Rugby Northamptonshire CV23 9JY",
    "addr:postcode":"cv23 9jy",
    "addr:street":"Church Lane",
    "iso:country":"GB",
    "sg:address":"Church Lane, Thurlaston",
    "sg:city":"Rugby",
    "sg:classifiers":[
        {
            "category":"Personal",
            "type":"Services"
        }
    ],
    "sg:phone":"+44 1788 817343",
    "sg:postcode":"CV23 9JY",
    "sg:province":"Northamptonshire",
    "sg:tags":[
        "wedding"
    ],
    "wof:name":"Church Video Productions",
    "wof:placetype":"venue"
},
  "geometry": {"coordinates":[-1.3165149689,52.3328666687],"type":"Point"}
}