{
  "type": "Feature",
  "properties": {
    "iso:country":"GB",
    "sg:address":"1a Smith Avenue",
    "sg:city":"Irvine",
    "sg:classifiers":[
        {
            "category":"Personal",
            "subcategory":"Beauty Salon",
            "type":"Services"
        },
        {
            "category":"Personal",
            "subcategory":"Barber",
            "type":"Services"
        }
    ],
    "sg:phone":"+44 1294 275966",
    "sg:postcode":"KA12 9JP",
    "sg:province":"North Ayrshire",
    "sg:tags":[
        "unisex",
        "hairdresser"
    ],
    "wof:name":"Looking Good Hair Studio",
    "wof:placetype":"venue"
},
  "geometry": {"coordinates":[-4.655444,55.62466],"type":"Point"}
}