{
  "type": "Feature",
  "properties": {
    "iso:country":"GB",
    "sg:address":"5 Caxton Park, Caxton Road",
    "sg:city":"Bedford",
    "sg:classifiers":[
        {
            "category":"Professional",
            "subcategory":"Computer Services",
            "type":"Services"
        }
    ],
    "sg:phone":"+44 1234 268880",
    "sg:postcode":"MK41 0TY",
    "sg:province":"Bedfordshire",
    "sg:tags":[
        "system",
        "software"
    ],
    "wof:name":"X B Data Spares Ltd.",
    "wof:placetype":"venue"
},
  "geometry": {"coordinates":[-0.417142,52.147503],"type":"Point"}
}