{
  "type": "Feature",
  "properties": {
    "addr:full":"323 Dudley Rd Birmingham West Midlands B18 4HB",
    "addr:housenumber":"323",
    "addr:postcode":"b18 4hb",
    "addr:street":"Dudley Rd",
    "iso:country":"GB",
    "sg:address":"323 Dudley Rd",
    "sg:city":"Birmingham",
    "sg:classifiers":[
        {
            "category":"Shopping",
            "subcategory":"Clothing, Apparel, & Fashions",
            "type":"Retail Goods"
        }
    ],
    "sg:phone":"+44 121 312 1212",
    "sg:postcode":"B18 4HB",
    "sg:province":"West Midlands",
    "sg:tags":[
        "shop"
    ],
    "wof:name":"Sahib Collections",
    "wof:placetype":"venue"
},
  "geometry": {"coordinates":[-1.9424510002,52.4866409302],"type":"Point"}
}