{
  "type": "Feature",
  "properties": {
    "addr:full":"61 Northfield Av, West Ealing West Ealing Greater London W13 9QP",
    "addr:housenumber":"61",
    "addr:postcode":"w13 9qp",
    "addr:street":"Northfield Av",
    "iso:country":"GB",
    "sg:address":"61 Northfield Av, West Ealing",
    "sg:city":"West Ealing",
    "sg:classifiers":[
        {
            "category":"Health Services",
            "subcategory":"Doctor",
            "type":"Services"
        }
    ],
    "sg:phone":"+44 20 8567 1612",
    "sg:postcode":"W13 9QP",
    "sg:province":"Greater London",
    "sg:tags":[
        "practitioners"
    ],
    "wof:name":"Butler, C M",
    "wof:placetype":"venue"
},
  "geometry": {"coordinates":[-0.3186860085,51.5045661926],"type":"Point"}
}