{
  "type": "Feature",
  "properties": {
    "addr:full":"The Paisley Centre, 2 High Street Paisley Renfrewshire PA1 2AF",
    "addr:housenumber":"2",
    "addr:postcode":"pa1 2af",
    "addr:street":"High Street",
    "iso:country":"GB",
    "sg:address":"The Paisley Centre, 2 High Street",
    "sg:city":"Paisley",
    "sg:classifiers":[
        {
            "category":"Shopping",
            "subcategory":"Clothing, Apparel, & Fashions",
            "type":"Retail Goods"
        }
    ],
    "sg:phone":"+44 141 889 5414",
    "sg:postcode":"PA1 2AF",
    "sg:province":"Renfrewshire",
    "sg:tags":[
        "shop"
    ],
    "wof:name":"Quiz",
    "wof:placetype":"venue"
},
  "geometry": {"coordinates":[-4.426129818,55.8451194763],"type":"Point"}
}