{
  "type": "Feature",
  "properties": {
    "addr:full":"Holker Farm, Cark In Cartmel Grange-over-sands Cumbria LA11 7PS",
    "addr:postcode":"la11 7ps",
    "iso:country":"GB",
    "sg:address":"Holker Farm, Cark In Cartmel",
    "sg:city":"Grange-over-sands",
    "sg:classifiers":[
        {
            "category":"Organizations",
            "subcategory":"Community Association",
            "type":"Services"
        }
    ],
    "sg:postcode":"LA11 7PS",
    "sg:province":"Cumbria",
    "sg:tags":[
        "relation",
        "public"
    ],
    "wof:name":"J Olstead",
    "wof:placetype":"venue"
},
  "geometry": {"coordinates":[-2.9216399193,54.1841583252],"type":"Point"}
}