{
  "type": "Feature",
  "properties": {
    "iso:country":"GB",
    "sg:address":"3 Penny Drive, Wood St Village",
    "sg:city":"Guildford",
    "sg:classifiers":[
        {
            "category":"Building & Trades",
            "subcategory":"Construction",
            "type":"Services"
        }
    ],
    "sg:phone":"+44 1483 715002",
    "sg:postcode":"GU3 3DJ",
    "sg:province":"Surrey",
    "sg:tags":[
        "decorator",
        "painter"
    ],
    "wof:name":"R Sherlock & Sons",
    "wof:placetype":"venue"
},
  "geometry": {"coordinates":[-0.627148,51.248856],"type":"Point"}
}