{
  "type": "Feature",
  "properties": {
    "iso:country":"GB",
    "sg:address":"Newfield Farm, Lottings Lane, Barmby Moor",
    "sg:city":"York",
    "sg:classifiers":[
        {
            "category":"Farming",
            "subcategory":"Livestock Farm",
            "type":"Manufacturing & Wholesale Goods"
        }
    ],
    "sg:phone":"+44 1759 302202",
    "sg:postcode":"YO42 4DF",
    "sg:province":"East Riding of Yorkshire",
    "sg:tags":[
        "others"
    ],
    "wof:name":"C A Potter",
    "wof:placetype":"venue"
},
  "geometry": {"coordinates":[-0.8144900203,53.932056427],"type":"Point"}
}