{
  "type": "Feature",
  "properties": {
    "addr:full":"Parts, Alfred Rd Wallasey Merseyside L44 7HY",
    "addr:postcode":"l44 7hy",
    "addr:street":"Alfred Rd",
    "iso:country":"GB",
    "sg:address":"Parts, Alfred Rd",
    "sg:city":"Wallasey",
    "sg:classifiers":[
        {
            "category":"Retail",
            "subcategory":"Auto Repair",
            "type":"Services"
        }
    ],
    "sg:phone":"+44 151 638 3200",
    "sg:postcode":"L44 7HY",
    "sg:province":"Merseyside",
    "sg:tags":[
        "modification",
        "garage"
    ],
    "wof:name":"Wallasey Car Centre",
    "wof:placetype":"venue"
},
  "geometry": {"coordinates":[-3.04994,53.41959],"type":"Point"}
}