{
  "type": "Feature",
  "properties": {
    "addr:full":"182 The Luton, Arndale Centre Luton Bedfordshire LU1 2TJ",
    "addr:housenumber":"182",
    "addr:postcode":"lu1 2tj",
    "addr:street":"The",
    "iso:country":"GB",
    "sg:address":"182 The Luton, Arndale Centre",
    "sg:city":"Luton",
    "sg:classifiers":[
        {
            "category":"Shopping",
            "subcategory":"Shoes",
            "type":"Retail Goods"
        }
    ],
    "sg:phone":"+44 1582 391300",
    "sg:postcode":"LU1 2TJ",
    "sg:province":"Bedfordshire",
    "wof:name":"Timpson Ltd.",
    "wof:placetype":"venue"
},
  "geometry": {"coordinates":[-0.4156149924,51.8813362122],"type":"Point"}
}