{
  "type": "Feature",
  "properties": {
    "iso:country":"GB",
    "sg:address":"Bog Hall Farm, Kirkheaton",
    "sg:city":"Newcastle-upon-tyne",
    "sg:classifiers":[
        {
            "category":"Farming",
            "subcategory":"Dairy Farm",
            "type":"Manufacturing & Wholesale Goods"
        }
    ],
    "sg:phone":"+44 1830 530274",
    "sg:postcode":"NE19 2DL",
    "sg:province":"Northumberland",
    "sg:tags":[
        "farmer"
    ],
    "wof:name":"N A Robinson & Sons",
    "wof:placetype":"venue"
},
  "geometry": {"coordinates":[-1.971254,55.091499],"type":"Point"}
}