{
  "type": "Feature",
  "properties": {
    "addr:full":"4 Sea Front Court, The Quay Looe Cornwall PL13 1AL",
    "addr:housenumber":"4",
    "addr:postcode":"pl13 1al",
    "addr:street":"Sea Front Court The Quay",
    "iso:country":"GB",
    "sg:address":"4 Sea Front Court, The Quay",
    "sg:city":"Looe",
    "sg:classifiers":[
        {
            "category":"Shopping",
            "subcategory":"Gifts & Souvenirs",
            "type":"Retail Goods"
        }
    ],
    "sg:postcode":"PL13 1AL",
    "sg:province":"Cornwall",
    "sg:tags":[
        "shop"
    ],
    "wof:name":"Banjo Beach Shop",
    "wof:placetype":"venue"
},
  "geometry": {"coordinates":[-4.4551510811,50.3570518494],"type":"Point"}
}