{
  "type": "Feature",
  "properties": {
    "addr:full":"71a Borough Rd Wallasey Merseyside L44 6NB",
    "addr:housenumber":"71a",
    "addr:postcode":"l44 6nb",
    "addr:street":"Borough Rd",
    "iso:country":"GB",
    "sg:address":"71a Borough Rd",
    "sg:city":"Wallasey",
    "sg:classifiers":[
        {
            "category":"Arts & Performance",
            "subcategory":"Music",
            "type":"Entertainment"
        }
    ],
    "sg:phone":"+44 151 630 3456",
    "sg:postcode":"L44 6NB",
    "sg:province":"Merseyside",
    "sg:tags":[
        "mobile",
        "disco"
    ],
    "wof:name":"Sounds Alternative Disco's",
    "wof:placetype":"venue"
},
  "geometry": {"coordinates":[-3.021574,53.411358],"type":"Point"}
}