{
  "type": "Feature",
  "properties": {
    "addr:full":"182 Darkes Lane Potters Bar Greater London EN6 1AF",
    "addr:housenumber":"182",
    "addr:postcode":"en6 1af",
    "addr:street":"Darkes Lane",
    "iso:country":"GB",
    "sg:address":"182 Darkes Lane",
    "sg:city":"Potters Bar",
    "sg:classifiers":[
        {
            "category":"Home & Garden",
            "subcategory":"Carpets & Floor Coverings",
            "type":"Retail Goods"
        }
    ],
    "sg:phone":"+44 1707 643180",
    "sg:postcode":"EN6 1AF",
    "sg:province":"Greater London",
    "sg:tags":[
        "carpets",
        "rug",
        "matting"
    ],
    "wof:name":"Potters Bar Carpet & Bedding Centre",
    "wof:placetype":"venue"
},
  "geometry": {"coordinates":[-0.190347001,51.6992645264],"type":"Point"}
}