{
  "type": "Feature",
  "properties": {
    "addr:full":"6 Kildare Terrace, Bayswater London Greater London W2 5LX",
    "addr:housenumber":"6",
    "addr:postcode":"w2 5lx",
    "addr:street":"Kildare Terrace",
    "iso:country":"GB",
    "sg:address":"6 Kildare Terrace, Bayswater",
    "sg:city":"London",
    "sg:classifiers":[
        {
            "category":"Travel",
            "subcategory":"Hotels & Motels",
            "type":"Entertainment"
        }
    ],
    "sg:phone":"+44 20 7243 1904",
    "sg:postcode":"W2 5LX",
    "sg:province":"Greater London",
    "sg:tags":[
        "self",
        "catering"
    ],
    "wof:name":"C B Ward Ltd.",
    "wof:placetype":"venue"
},
  "geometry": {"coordinates":[-0.193495,51.517616],"type":"Point"}
}