{
  "type": "Feature",
  "properties": {
    "addr:full":"Raymond Buildings, 3 Grays Inn London Greater London WC1R 5BH",
    "addr:housenumber":"3",
    "addr:postcode":"wc1r 5bh",
    "addr:street":"Grays Inn",
    "iso:country":"GB",
    "sg:address":"Raymond Buildings, 3 Grays Inn",
    "sg:city":"London",
    "sg:classifiers":[
        {
            "category":"Professional",
            "subcategory":"Lawyer & Legal Services",
            "type":"Services"
        }
    ],
    "sg:phone":"+44 20 7831 3833",
    "sg:postcode":"WC1R 5BH",
    "sg:province":"Greater London",
    "sg:tags":[
        "barrister"
    ],
    "wof:name":"Helen Malcolm",
    "wof:placetype":"venue"
},
  "geometry": {"coordinates":[-0.11525,51.52066],"type":"Point"}
}