{
  "type": "Feature",
  "properties": {
    "addr:full":"Thames Waugh London Greater London SE7 8NJ",
    "addr:postcode":"se7 8nj",
    "iso:country":"GB",
    "sg:address":"Thames Waugh",
    "sg:city":"London",
    "sg:classifiers":[
        {
            "category":"Freight",
            "type":"Transportation"
        }
    ],
    "sg:phone":"+44 20 8305 2403",
    "sg:postcode":"SE7 8NJ",
    "sg:province":"Greater London",
    "sg:tags":[
        "haulage",
        "road"
    ],
    "wof:name":"Heyland Haulage Ltd.",
    "wof:placetype":"venue"
},
  "geometry": {"coordinates":[0.0356200002,51.4940795898],"type":"Point"}
}