{
  "type": "Feature",
  "properties": {
    "addr:full":"2nd Floor, 767 High Rd, North Finchley North Finchley Greater London N12 8LB",
    "addr:housenumber":"2nd floor 767",
    "addr:postcode":"n12 8lb",
    "addr:street":"High Rd",
    "iso:country":"GB",
    "sg:address":"2nd Floor, 767 High Rd, North Finchley",
    "sg:city":"North Finchley",
    "sg:classifiers":[
        {
            "category":"Professional",
            "subcategory":"Art Services",
            "type":"Services"
        }
    ],
    "sg:phone":"+44 20 8445 0347",
    "sg:postcode":"N12 8LB",
    "sg:province":"Greater London",
    "sg:tags":[
        "consultant",
        "design"
    ],
    "wof:name":"Shuna Le Moine",
    "wof:placetype":"venue"
},
  "geometry": {"coordinates":[-0.177414,51.6216888428],"type":"Point"}
}