{
  "type": "Feature",
  "properties": {
    "addr:full":"Spire House, Picketts Hill, Headley Bordon Hampshire GU35 8TD",
    "addr:postcode":"gu35 8td",
    "addr:street":"Picketts Hill",
    "iso:country":"GB",
    "sg:address":"Spire House, Picketts Hill, Headley",
    "sg:city":"Bordon",
    "sg:classifiers":[
        {
            "category":"Professional",
            "subcategory":"Employment Agencies",
            "type":"Services"
        }
    ],
    "sg:phone":"+44 1428 714814",
    "sg:postcode":"GU35 8TD",
    "sg:province":"Hampshire",
    "sg:tags":[
        "pair",
        "au"
    ],
    "wof:name":"East-West Au Pairs Ltd.",
    "wof:placetype":"venue"
},
  "geometry": {"coordinates":[-0.8427850008,51.1392860413],"type":"Point"}
}