{
  "type": "Feature",
  "properties": {
    "addr:full":"28 Main Street, Papplewick Nottingham Nottinghamshire NG15 8FD",
    "addr:housenumber":"28",
    "addr:postcode":"ng15 8fd",
    "addr:street":"Main Street",
    "iso:country":"GB",
    "sg:address":"28 Main Street, Papplewick",
    "sg:city":"Nottingham",
    "sg:classifiers":[
        {
            "category":"Autos & Motor Vehicles",
            "subcategory":"Motorcycle Sales",
            "type":"Retail Goods"
        }
    ],
    "sg:postcode":"NG15 8FD",
    "sg:province":"Nottinghamshire",
    "sg:tags":[
        "chauffeur",
        "driven",
        "car"
    ],
    "wof:name":"Luxury Chauffeured Cars",
    "wof:placetype":"venue"
},
  "geometry": {"coordinates":[-1.2035109997,53.0537948608],"type":"Point"}
}