{
  "type": "Feature",
  "properties": {
    "addr:full":"Steeton Health Centre, Chapel Rd Keighley North Yorkshire BD20 6NU",
    "addr:postcode":"bd20 6nu",
    "addr:street":"Chapel Rd",
    "iso:country":"GB",
    "sg:address":"Steeton Health Centre, Chapel Rd",
    "sg:city":"Keighley",
    "sg:classifiers":[
        {
            "category":"Health Services",
            "subcategory":"Doctor",
            "type":"Services"
        }
    ],
    "sg:phone":"+44 1535 652448",
    "sg:postcode":"BD20 6NU",
    "sg:province":"North Yorkshire",
    "sg:tags":[
        "practitioners"
    ],
    "wof:name":"Smith, N",
    "wof:placetype":"venue"
},
  "geometry": {"coordinates":[-1.948458,53.897301],"type":"Point"}
}