{
  "type": "Feature",
  "properties": {
    "addr:full":"1a Silver Street, Stainforth Doncaster South Yorkshire DN7 5AH",
    "addr:housenumber":"1a",
    "addr:postcode":"dn7 5ah",
    "addr:street":"Silver Street",
    "iso:country":"GB",
    "sg:address":"1a Silver Street, Stainforth",
    "sg:city":"Doncaster",
    "sg:classifiers":[
        {
            "category":"Professional",
            "subcategory":"Business Services",
            "type":"Services"
        },
        {
            "category":"Casinos & Gambling",
            "type":"Entertainment"
        }
    ],
    "sg:phone":"+44 1302 841245",
    "sg:postcode":"DN7 5AH",
    "sg:province":"South Yorkshire",
    "sg:tags":[
        "turf",
        "accountant",
        "bookmaker"
    ],
    "wof:name":"Central Racing",
    "wof:placetype":"venue"
},
  "geometry": {"coordinates":[-1.0303989649,53.5950737],"type":"Point"}
}