{
  "type": "Feature",
  "properties": {
    "addr:full":"Tamarim Farm, Littleworth, Norton Lindsay Warwick Warwickshire CV35 8HD",
    "addr:housenumber":"littleworth norton",
    "addr:postcode":"cv35 8hd",
    "addr:street":"Lindsay",
    "iso:country":"GB",
    "sg:address":"Tamarim Farm, Littleworth, Norton Lindsay",
    "sg:city":"Warwick",
    "sg:classifiers":[
        {
            "category":"Personal",
            "subcategory":"Adult",
            "type":"Services"
        }
    ],
    "sg:phone":"+44 1926 499421",
    "sg:postcode":"CV35 8HD",
    "sg:province":"Warwickshire",
    "sg:tags":[
        "equestrian"
    ],
    "wof:name":"J Tickle",
    "wof:placetype":"venue"
},
  "geometry": {"coordinates":[-1.654186964,52.2686080933],"type":"Point"}
}