{
  "type": "Feature",
  "properties": {
    "addr:full":"9 Hannah Street Porth Bridgend CF39 9PU",
    "addr:housenumber":"9",
    "addr:postcode":"cf39 9pu",
    "addr:street":"Hannah Street",
    "iso:country":"GB",
    "sg:address":"9 Hannah Street",
    "sg:city":"Porth",
    "sg:classifiers":[
        {
            "category":"Shopping",
            "subcategory":"Gifts & Souvenirs",
            "type":"Retail Goods"
        }
    ],
    "sg:phone":"+44 1443 686011",
    "sg:postcode":"CF39 9PU",
    "sg:province":"Bridgend",
    "sg:tags":[
        "shop",
        "poster",
        "card"
    ],
    "wof:name":"Top Cards",
    "wof:placetype":"venue"
},
  "geometry": {"coordinates":[-3.4074959755,51.611831665],"type":"Point"}
}