{
  "type": "Feature",
  "properties": {
    "iso:country":"GB",
    "sg:address":"9 Kilmahew Avenue, Cardross",
    "sg:city":"Dumbarton",
    "sg:classifiers":[
        {
            "category":"Autos & Motor Vehicles",
            "subcategory":"Motorcycle Sales",
            "type":"Retail Goods"
        },
        {
            "category":"Bus Charters",
            "type":"Transportation"
        }
    ],
    "sg:phone":"+44 1389 842111",
    "sg:postcode":"G82 5NG",
    "sg:province":"Argyll and Bute",
    "sg:tags":[
        "chauffeur",
        "driven",
        "coach",
        "car"
    ],
    "wof:name":"Chauffeurs of Scotland",
    "wof:placetype":"venue"
},
  "geometry": {"coordinates":[-4.653647,55.968216],"type":"Point"}
}