{
  "type": "Feature",
  "properties": {
    "addr:full":"74 Heath Road Twickenham Greater London TW1 4BW",
    "addr:housenumber":"74",
    "addr:postcode":"tw1 4bw",
    "addr:street":"Heath Road",
    "iso:country":"GB",
    "sg:address":"74 Heath Road",
    "sg:city":"Twickenham",
    "sg:classifiers":[
        {
            "category":"Real Estate",
            "subcategory":"Real Estate Agent",
            "type":"Services"
        }
    ],
    "sg:postcode":"TW1 4BW",
    "sg:province":"Greater London",
    "wof:name":"Camerons Residential",
    "wof:placetype":"venue"
},
  "geometry": {"coordinates":[-0.334379,51.445419],"type":"Point"}
}