{
  "type": "Feature",
  "properties": {
    "iso:country":"GB",
    "sg:address":"Jubilee Ho, Scott Green, Gildersome",
    "sg:city":"Leeds",
    "sg:classifiers":[
        {
            "category":"Social Services",
            "subcategory":"Retirement Home",
            "type":"Services"
        }
    ],
    "sg:phone":"+44 113 204 9544",
    "sg:postcode":"LS27 7AP",
    "sg:province":"West Yorkshire",
    "sg:tags":[
        "care"
    ],
    "wof:name":"J C Care Management",
    "wof:placetype":"venue"
},
  "geometry": {"coordinates":[-1.63317,53.759445],"type":"Point"}
}