{
  "type": "Feature",
  "properties": {
    "addr:full":"818 Manchester Road Rochdale Lancashire OL11 3AW",
    "addr:housenumber":"818",
    "addr:postcode":"ol11 3aw",
    "addr:street":"Manchester Road",
    "iso:country":"GB",
    "sg:address":"818 Manchester Road",
    "sg:city":"Rochdale",
    "sg:classifiers":[
        {
            "category":"Bars & Pubs",
            "type":"Food & Drink"
        }
    ],
    "sg:phone":"+44 1706 656322",
    "sg:postcode":"OL11 3AW",
    "sg:province":"Lancashire",
    "sg:tags":[
        "pubs",
        "inn"
    ],
    "wof:name":"The New Inn",
    "wof:placetype":"venue"
},
  "geometry": {"coordinates":[-2.1794509888,53.5920715332],"type":"Point"}
}