{
  "type": "Feature",
  "properties": {
    "addr:full":"Penralltgwin, Beulah Newcastle Emlyn Carmarthenshire SA38 9QH",
    "addr:postcode":"sa38 9qh",
    "addr:street":"Beulah",
    "iso:country":"GB",
    "sg:address":"Penralltgwin, Beulah",
    "sg:city":"Newcastle Emlyn",
    "sg:classifiers":[
        {
            "category":"Farming",
            "subcategory":"Farm",
            "type":"Manufacturing & Wholesale Goods"
        }
    ],
    "sg:phone":"+44 1239 851364",
    "sg:postcode":"SA38 9QH",
    "sg:province":"Carmarthenshire",
    "sg:tags":[
        "mixed",
        "crop"
    ],
    "wof:name":"M J Evans & Sons",
    "wof:placetype":"venue"
},
  "geometry": {"coordinates":[-4.467984,52.035919],"type":"Point"}
}