{
  "type": "Feature",
  "properties": {
    "iso:country":"GB",
    "sg:address":"16 Midland Close",
    "sg:city":"Colchester",
    "sg:classifiers":[
        {
            "category":"Retail",
            "subcategory":"Repair Shop",
            "type":"Services"
        }
    ],
    "sg:phone":"+44 1206 530591",
    "sg:postcode":"CO2 7RS",
    "sg:province":"Essex",
    "sg:tags":[
        "appliance",
        "electrical"
    ],
    "wof:name":"Alan Mills",
    "wof:placetype":"venue"
},
  "geometry": {"coordinates":[0.903548,51.877724],"type":"Point"}
}