{
  "type": "Feature",
  "properties": {
    "addr:full":"Church-in-the-wood Lane St Leonards-on-sea East Sussex TN38 9PB",
    "addr:postcode":"tn38 9pb",
    "addr:street":"Church-In-The-Wood Lane",
    "iso:country":"GB",
    "sg:address":"Church-in-the-wood Lane",
    "sg:city":"St Leonards-on-sea",
    "sg:classifiers":[
        {
            "category":"Education",
            "subcategory":"School",
            "type":"Public Place"
        }
    ],
    "sg:phone":"+44 1424 852326",
    "sg:postcode":"TN38 9PB",
    "sg:province":"East Sussex",
    "sg:tags":[
        "local",
        "authority"
    ],
    "wof:name":"Churchwood Primary School",
    "wof:placetype":"venue"
},
  "geometry": {"coordinates":[0.538258,50.874962],"type":"Point"}
}