{
  "type": "Feature",
  "properties": {
    "iso:country":"GB",
    "sg:address":"4 Fore Hill",
    "sg:city":"Ely",
    "sg:classifiers":[
        {
            "category":"Retail",
            "subcategory":"Photofinishing",
            "type":"Services"
        }
    ],
    "sg:phone":"+44 1353 665562",
    "sg:postcode":"CB7 4AF",
    "sg:province":"Cambridgeshire",
    "sg:tags":[
        "photographic",
        "processor"
    ],
    "wof:name":"Klick Photopoint",
    "wof:placetype":"venue"
},
  "geometry": {"coordinates":[0.266612,52.398754],"type":"Point"}
}