{
  "type": "Feature",
  "properties": {
    "addr:full":"16 Abbey Churchyard Bath Bath and North East Somerset BA1 1LY",
    "addr:housenumber":"16",
    "addr:postcode":"ba1 1ly",
    "addr:street":"Abbey",
    "iso:country":"GB",
    "sg:address":"16 Abbey Churchyard",
    "sg:city":"Bath",
    "sg:classifiers":[
        {
            "category":"Professional",
            "subcategory":"Accounting & Tax Preparation",
            "type":"Services"
        }
    ],
    "sg:phone":"+44 1225 465238",
    "sg:postcode":"BA1 1LY",
    "sg:province":"Bath and North East Somerset",
    "sg:tags":[
        "accountant",
        "activity"
    ],
    "wof:name":"Jane Baber",
    "wof:placetype":"venue"
},
  "geometry": {"coordinates":[-2.35874,51.380562],"type":"Point"}
}