{
  "type": "Feature",
  "properties": {
    "addr:full":"Mill Street, Cradley Halesowen West Midlands B63 2UB",
    "addr:postcode":"b63 2ub",
    "addr:street":"Mill Street",
    "iso:country":"GB",
    "sg:address":"Mill Street, Cradley",
    "sg:city":"Halesowen",
    "sg:classifiers":[
        {
            "category":"Professional",
            "subcategory":"Engineering",
            "type":"Services"
        }
    ],
    "sg:postcode":"B63 2UB",
    "sg:province":"West Midlands",
    "wof:name":"Cradley Property Developments Ltd.",
    "wof:placetype":"venue"
},
  "geometry": {"coordinates":[-2.0865840912,52.4664955139],"type":"Point"}
}