{
  "type": "Feature",
  "properties": {
    "addr:full":"126 Cornwall Road London Greater London SE1 8TQ",
    "addr:housenumber":"126",
    "addr:postcode":"se1 8tq",
    "addr:street":"Cornwall Road",
    "iso:country":"GB",
    "sg:address":"126 Cornwall Road",
    "sg:city":"London",
    "sg:classifiers":[
        {
            "category":"Shopping",
            "subcategory":"Books",
            "type":"Retail Goods"
        }
    ],
    "sg:phone":"+44 20 7633 0599",
    "sg:postcode":"SE1 8TQ",
    "sg:province":"Greater London",
    "wof:name":"Calder Publications",
    "wof:placetype":"venue"
},
  "geometry": {"coordinates":[-0.110168,51.503315],"type":"Point"}
}