{
  "type": "Feature",
  "properties": {
    "addr:full":"61 Elmstone Drive, Tilehurst Reading Berkshire RG31 5NS",
    "addr:housenumber":"61",
    "addr:postcode":"rg31 5ns",
    "addr:street":"Elmstone Drive",
    "iso:country":"GB",
    "sg:address":"61 Elmstone Drive, Tilehurst",
    "sg:city":"Reading",
    "sg:classifiers":[
        {
            "category":"Wholesale",
            "subcategory":"Meat",
            "type":"Manufacturing & Wholesale Goods"
        }
    ],
    "sg:phone":"+44 118 942 6621",
    "sg:postcode":"RG31 5NS",
    "sg:province":"Berkshire",
    "sg:tags":[
        "-"
    ],
    "wof:name":"Rafique Wholesale Butchers",
    "wof:placetype":"venue"
},
  "geometry": {"coordinates":[-1.045758,51.461109],"type":"Point"}
}