{
  "type": "Feature",
  "properties": {
    "iso:country":"GB",
    "sg:address":"68a Reading Road, Yateley",
    "sg:city":"Camberley",
    "sg:classifiers":[
        {
            "category":"Professional",
            "subcategory":"Lawyer & Legal Services",
            "type":"Services"
        }
    ],
    "sg:phone":"+44 1252 872617",
    "sg:postcode":"GU46 7UJ",
    "sg:province":"Hampshire",
    "sg:tags":[
        "solicitor"
    ],
    "sg:website":"http://www.hart.gov.uk",
    "wof:name":"Davies Blunden & Evans",
    "wof:placetype":"venue"
},
  "geometry": {"coordinates":[-0.8206089735,51.3415184021],"type":"Point"}
}