{
  "type": "Feature",
  "properties": {
    "iso:country":"GB",
    "sg:address":"57 Albion Road",
    "sg:city":"Edinburgh",
    "sg:classifiers":[
        {
            "category":"Organizations",
            "subcategory":"Non-profit Organization",
            "type":"Services"
        }
    ],
    "sg:postcode":"EH7 5QY",
    "sg:province":"City of Edinburgh",
    "sg:tags":[
        "organisation",
        "voluntary",
        "charity"
    ],
    "wof:name":"The Action Group",
    "wof:placetype":"venue"
},
  "geometry": {"coordinates":[-3.166962,55.961388],"type":"Point"}
}