{
  "type": "Feature",
  "properties": {
    "iso:country":"GB",
    "sg:address":"Stickley Lane, Lower Gornal",
    "sg:city":"Dudley",
    "sg:classifiers":[
        {
            "category":"Education",
            "subcategory":"School",
            "type":"Public Place"
        }
    ],
    "sg:phone":"+44 1902 825025",
    "sg:postcode":"DY3 2JH",
    "sg:province":"Staffordshire",
    "sg:tags":[
        "college"
    ],
    "wof:name":"Ellowes Hall School",
    "wof:placetype":"venue"
},
  "geometry": {"coordinates":[-2.120666,52.519909],"type":"Point"}
}