{
  "type": "Feature",
  "properties": {
    "iso:country":"GB",
    "sg:address":"Selwell House, Hough Road, Caythorpe",
    "sg:city":"Grantham",
    "sg:classifiers":[
        {
            "category":"Professional",
            "subcategory":"Computer Services",
            "type":"Services"
        }
    ],
    "sg:phone":"+44 1400 273311",
    "sg:postcode":"NG32 3DA",
    "sg:province":"Leicestershire",
    "sg:tags":[
        "system",
        "software"
    ],
    "wof:name":"Selwell Computers (Software) Ltd.",
    "wof:placetype":"venue"
},
  "geometry": {"coordinates":[-0.600198,53.017441],"type":"Point"}
}