{
  "type": "Feature",
  "properties": {
    "addr:full":"1 Spring Villa, High Road, Turnford Broxbourne Essex EN10 6AA",
    "addr:housenumber":"1",
    "addr:postcode":"en10 6aa",
    "addr:street":"Spring Villa High Road Turnford",
    "iso:country":"GB",
    "sg:address":"1 Spring Villa, High Road, Turnford",
    "sg:city":"Broxbourne",
    "sg:classifiers":[
        {
            "category":"Building & Trades",
            "subcategory":"Construction",
            "type":"Services"
        }
    ],
    "sg:postcode":"EN10 6AA",
    "sg:province":"Essex",
    "sg:tags":[
        "builder"
    ],
    "wof:name":"A & G Roofing & Building Contractors",
    "wof:placetype":"venue"
},
  "geometry": {"coordinates":[-0.0251650009,51.721321106],"type":"Point"}
}