{
  "type": "Feature",
  "properties": {
    "addr:full":"76 George Street Luton Bedfordshire LU1 2BD",
    "addr:housenumber":"76",
    "addr:postcode":"lu1 2bd",
    "addr:street":"George Street",
    "iso:country":"GB",
    "sg:address":"76 George Street",
    "sg:city":"Luton",
    "sg:classifiers":[
        {
            "category":"Shopping",
            "subcategory":"Discount & Variety Stores",
            "type":"Retail Goods"
        }
    ],
    "sg:phone":"+44 1582 729681",
    "sg:postcode":"LU1 2BD",
    "sg:province":"Bedfordshire",
    "sg:tags":[
        "centre"
    ],
    "sg:website":"http://www.poundstretcher.co.uk",
    "wof:name":"Poundstretcher Ltd.",
    "wof:placetype":"venue"
},
  "geometry": {"coordinates":[-0.41659,51.879288],"type":"Point"}
}