{
  "type": "Feature",
  "properties": {
    "addr:full":"53 High Street, Kinver Stourbridge Shropshire DY7 6HE",
    "addr:housenumber":"53",
    "addr:postcode":"dy7 6he",
    "addr:street":"High Street",
    "iso:country":"GB",
    "sg:address":"53 High Street, Kinver",
    "sg:city":"Stourbridge",
    "sg:classifiers":[
        {
            "category":"Food & Beverages",
            "subcategory":"Meat & Fish",
            "type":"Retail Goods"
        }
    ],
    "sg:phone":"+44 1384 872841",
    "sg:postcode":"DY7 6HE",
    "sg:province":"Shropshire",
    "sg:tags":[
        "butcher"
    ],
    "wof:name":"Kay's Butchers",
    "wof:placetype":"venue"
},
  "geometry": {"coordinates":[-2.229061,52.449066],"type":"Point"}
}