{
  "type": "Feature",
  "properties": {
    "iso:country":"GB",
    "sg:address":"Foster House, Maxwell Road",
    "sg:city":"Borehamwood",
    "sg:classifiers":[
        {
            "category":"Professional",
            "subcategory":"Engineering",
            "type":"Services"
        }
    ],
    "sg:postcode":"WD6 1JB",
    "sg:province":"Hertfordshire",
    "sg:tags":[
        "consultant",
        "structural"
    ],
    "wof:name":"Aleck Associates",
    "wof:placetype":"venue"
},
  "geometry": {"coordinates":[-0.266863,51.658474],"type":"Point"}
}