{
  "type": "Feature",
  "properties": {
    "addr:full":"Thornton Road, Thornton Bradford West Yorkshire BD13 3LN",
    "addr:postcode":"bd13 3ln",
    "addr:street":"Thornton Road",
    "iso:country":"GB",
    "sg:address":"Thornton Road, Thornton",
    "sg:city":"Bradford",
    "sg:classifiers":[
        {
            "category":"Home & Garden",
            "subcategory":"Garden Supply",
            "type":"Retail Goods"
        }
    ],
    "sg:phone":"+44 1274 835416",
    "sg:postcode":"BD13 3LN",
    "sg:province":"West Yorkshire",
    "sg:tags":[
        "nursery",
        "centre"
    ],
    "wof:name":"Ashfield Horticultural Resource Centre",
    "wof:placetype":"venue"
},
  "geometry": {"coordinates":[-1.8494340181,53.7902336121],"type":"Point"}
}