{
  "type": "Feature",
  "properties": {
    "iso:country":"GB",
    "sg:address":"6 Windsor Square",
    "sg:city":"Rotherham",
    "sg:classifiers":[
        {
            "category":"Military Area",
            "subcategory":"Air Force Base",
            "type":"Public Place"
        }
    ],
    "sg:postcode":"S63 0HE",
    "sg:province":"South Yorkshire",
    "sg:tags":[
        "taxi",
        "hire",
        "private"
    ],
    "wof:name":"Barry Tansley",
    "wof:placetype":"venue"
},
  "geometry": {"coordinates":[-1.305073,53.548],"type":"Point"}
}