{
  "type": "Feature",
  "properties": {
    "iso:country":"GB",
    "sg:address":"Hill House Farm",
    "sg:city":"Stockport",
    "sg:classifiers":[
        {
            "category":"Farming",
            "subcategory":"Livestock Farm",
            "type":"Manufacturing & Wholesale Goods"
        }
    ],
    "sg:phone":"+44 1663 743737",
    "sg:postcode":"SK12 5LJ",
    "sg:province":"Cheshire",
    "sg:tags":[
        "others"
    ],
    "wof:name":"H Hodgson",
    "wof:placetype":"venue"
},
  "geometry": {"coordinates":[-2.058187,53.358795],"type":"Point"}
}