{
  "type": "Feature",
  "properties": {
    "addr:full":"P O Box 27, Yarm Road Darlington Durham DL1 4DE",
    "addr:housenumber":"box 27",
    "addr:postcode":"dl1 4de",
    "addr:street":"P O;Yarm Road",
    "iso:country":"GB",
    "sg:address":"P O Box 27, Yarm Road",
    "sg:city":"Darlington",
    "sg:classifiers":[
        {
            "category":"Professional",
            "subcategory":"Engineering",
            "type":"Services"
        }
    ],
    "sg:phone":"+44 1325 381188",
    "sg:postcode":"DL1 4DE",
    "sg:province":"Durham",
    "sg:tags":[
        "civil",
        "engineer"
    ],
    "wof:name":"Cleveland Bridge & Engineering Co. Ltd.",
    "wof:placetype":"venue"
},
  "geometry": {"coordinates":[-1.5488940477,54.5245018005],"type":"Point"}
}