{
  "type": "Feature",
  "properties": {
    "iso:country":"GB",
    "sg:address":"582-600 Ringwood Road",
    "sg:city":"Poole",
    "sg:classifiers":[
        {
            "category":"Retail",
            "subcategory":"Auto Repair",
            "type":"Services"
        }
    ],
    "sg:phone":"+44 1202 733866",
    "sg:postcode":"BH12 4LW",
    "sg:province":"Dorset",
    "sg:tags":[
        "body",
        "car"
    ],
    "wof:name":"Paul Motors Accident Repair",
    "wof:placetype":"venue"
},
  "geometry": {"coordinates":[-1.944347,50.745079],"type":"Point"}
}