{
  "type": "Feature",
  "properties": {
    "iso:country":"GB",
    "sg:address":"2 Penarwyn Woods",
    "sg:city":"Par",
    "sg:classifiers":[
        {
            "category":"Shopping",
            "subcategory":"Photographic Equipment",
            "type":"Retail Goods"
        }
    ],
    "sg:phone":"+44 1726 814449",
    "sg:postcode":"PL24 2DG",
    "sg:province":"Cornwall",
    "wof:name":"Glitterglog",
    "wof:placetype":"venue"
},
  "geometry": {"coordinates":[-4.718766,50.351059],"type":"Point"}
}