{
  "type": "Feature",
  "properties": {
    "iso:country":"GB",
    "sg:address":"81 Kilby Road, Fleckney",
    "sg:city":"Leicester",
    "sg:classifiers":[
        {
            "category":"Government",
            "subcategory":"Office",
            "type":"Public Place"
        }
    ],
    "sg:phone":"+44 116 240 2971",
    "sg:postcode":"LE8 8BP",
    "sg:province":"Leicestershire",
    "sg:tags":[
        "education",
        "agency",
        "authority"
    ],
    "wof:name":"Pebbles",
    "wof:placetype":"venue"
},
  "geometry": {"coordinates":[-1.051946,52.537216],"type":"Point"}
}