{
  "type": "Feature",
  "properties": {
    "addr:full":"The Furze, Long Row, Tibenham Norwich Norfolk NR16 1PA",
    "addr:postcode":"nr16 1pa",
    "addr:street":"Long Row",
    "iso:country":"GB",
    "sg:address":"The Furze, Long Row, Tibenham",
    "sg:city":"Norwich",
    "sg:classifiers":[
        {
            "category":"Building & Trades",
            "subcategory":"Construction",
            "type":"Services"
        }
    ],
    "sg:phone":"+44 1379 677804",
    "sg:postcode":"NR16 1PA",
    "sg:province":"Norfolk",
    "sg:tags":[
        "builder"
    ],
    "wof:name":"P.M.J Bryant",
    "wof:placetype":"venue"
},
  "geometry": {"coordinates":[1.1444499493,52.4632873535],"type":"Point"}
}