{
  "type": "Feature",
  "properties": {
    "addr:full":"260 Wallasey Village Wallasey Merseyside L45 3HB",
    "addr:housenumber":"260",
    "addr:postcode":"l45 3hb",
    "addr:street":"Wallasey Village",
    "iso:country":"GB",
    "sg:address":"260 Wallasey Village",
    "sg:city":"Wallasey",
    "sg:classifiers":[
        {
            "category":"Government",
            "subcategory":"Post Office",
            "type":"Public Place"
        }
    ],
    "sg:phone":"+44 151 639 1814",
    "sg:postcode":"L45 3HB",
    "sg:province":"Merseyside",
    "wof:name":"Wallasey Grove Road Sub Post Office",
    "wof:placetype":"venue"
},
  "geometry": {"coordinates":[-3.0677819252,53.4281311035],"type":"Point"}
}