{
  "type": "Feature",
  "properties": {
    "addr:full":"Bradford Old Rd Bingley West Yorkshire BD16 1SA",
    "addr:postcode":"bd16 1sa",
    "addr:street":"Old Rd",
    "iso:country":"GB",
    "sg:address":"Bradford Old Rd",
    "sg:city":"Bingley",
    "sg:classifiers":[
        {
            "category":"Bars & Pubs",
            "type":"Food & Drink"
        }
    ],
    "sg:phone":"+44 1274 550981",
    "sg:postcode":"BD16 1SA",
    "sg:province":"West Yorkshire",
    "sg:tags":[
        "pubs",
        "inn"
    ],
    "wof:name":"Sun Inn",
    "wof:placetype":"venue"
},
  "geometry": {"coordinates":[-1.8218040466,53.8321647644],"type":"Point"}
}