{
  "type": "Feature",
  "properties": {
    "iso:country":"GB",
    "sg:address":"137 Kettering Rd",
    "sg:city":"Northampton",
    "sg:classifiers":[
        {
            "category":"Food & Beverages",
            "subcategory":"Fruits & Vegetables",
            "type":"Retail Goods"
        }
    ],
    "sg:phone":"+44 1604 460022",
    "sg:postcode":"NN1 4BS",
    "sg:province":"Northamptonshire",
    "sg:tags":[
        "greengrocer"
    ],
    "wof:name":"Hallal",
    "wof:placetype":"venue"
},
  "geometry": {"coordinates":[-0.883678,52.244564],"type":"Point"}
}