{
  "type": "Feature",
  "properties": {
    "addr:full":"16 Tenterhill Lane, Sheepbridge Huddersfield West Yorkshire HD2 1EJ",
    "addr:housenumber":"16",
    "addr:postcode":"hd2 1ej",
    "addr:street":"Tenterhill Lane;West",
    "iso:country":"GB",
    "sg:address":"16 Tenterhill Lane, Sheepbridge",
    "sg:city":"Huddersfield",
    "sg:classifiers":[
        {
            "category":"Building & Trades",
            "subcategory":"Plumbing",
            "type":"Services"
        }
    ],
    "sg:phone":"+44 1484 531736",
    "sg:postcode":"HD2 1EJ",
    "sg:province":"West Yorkshire",
    "sg:tags":[
        "heating"
    ],
    "wof:name":"S Maude & Co.",
    "wof:placetype":"venue"
},
  "geometry": {"coordinates":[-1.762526989,53.6732902527],"type":"Point"}
}