{
  "type": "Feature",
  "properties": {
    "addr:full":"12 Warren Walk, Royston Barnsley South Yorkshire S71 4QB",
    "addr:housenumber":"12",
    "addr:postcode":"s71 4qb",
    "addr:street":"Warren Walk;Yorkshire",
    "iso:country":"GB",
    "sg:address":"12 Warren Walk, Royston",
    "sg:city":"Barnsley",
    "sg:classifiers":[
        {
            "category":"Farming",
            "subcategory":"Livestock Farm",
            "type":"Manufacturing & Wholesale Goods"
        }
    ],
    "sg:phone":"+44 1226 722887",
    "sg:postcode":"S71 4QB",
    "sg:province":"South Yorkshire",
    "sg:tags":[
        "others"
    ],
    "wof:name":"Woods Ltd",
    "wof:placetype":"venue"
},
  "geometry": {"coordinates":[-1.4459240437,53.6035346985],"type":"Point"}
}