{
  "type": "Feature",
  "properties": {
    "iso:country":"GB",
    "sg:address":"Wonnacott Farm, Lewdown",
    "sg:city":"Okehampton",
    "sg:classifiers":[
        {
            "category":"Farming",
            "subcategory":"Farm",
            "type":"Manufacturing & Wholesale Goods"
        }
    ],
    "sg:phone":"+44 1837 871238",
    "sg:postcode":"EX20 4QU",
    "sg:province":"Devon",
    "sg:tags":[
        "mixed",
        "crop"
    ],
    "wof:name":"P W Yells",
    "wof:placetype":"venue"
},
  "geometry": {"coordinates":[-4.1965141296,50.6587867737],"type":"Point"}
}