{
  "type": "Feature",
  "properties": {
    "addr:full":"272 Highbury Road Nottingham Nottinghamshire NG6 9FE",
    "addr:housenumber":"272",
    "addr:postcode":"ng6 9fe",
    "addr:street":"Highbury Road",
    "iso:country":"GB",
    "sg:address":"272 Highbury Road",
    "sg:city":"Nottingham",
    "sg:classifiers":[
        {
            "category":"Shopping",
            "subcategory":"Computers & Home Electronics",
            "type":"Retail Goods"
        },
        {
            "category":"Communications",
            "type":"Services"
        }
    ],
    "sg:phone":"+44 115 977 1066",
    "sg:postcode":"NG6 9FE",
    "sg:province":"Nottinghamshire",
    "sg:tags":[
        "telephone",
        "telecommunication"
    ],
    "wof:name":"Cellular Phoneworld",
    "wof:placetype":"venue"
},
  "geometry": {"coordinates":[-1.1933180094,52.9978561401],"type":"Point"}
}