{
  "type": "Feature",
  "properties": {
    "iso:country":"GB",
    "sg:address":"333-337 Sheffield Rd",
    "sg:city":"Chesterfield",
    "sg:classifiers":[
        {
            "category":"Building & Trades",
            "subcategory":"Construction",
            "type":"Services"
        }
    ],
    "sg:phone":"+44 1246 200022",
    "sg:postcode":"S41 8LQ",
    "sg:province":"Derbyshire",
    "sg:tags":[
        "ventilation",
        "contractor"
    ],
    "wof:name":"U.K Damp Protection",
    "wof:placetype":"venue"
},
  "geometry": {"coordinates":[-1.427246,53.255306],"type":"Point"}
}