{
  "type": "Feature",
  "properties": {
    "addr:full":"35 Grasmere Road Cheltenham Gloucestershire GL51 3PQ",
    "addr:housenumber":"35",
    "addr:postcode":"gl51 3pq",
    "addr:street":"Grasmere Road",
    "iso:country":"GB",
    "sg:address":"35 Grasmere Road",
    "sg:city":"Cheltenham",
    "sg:classifiers":[
        {
            "category":"Health Services",
            "subcategory":"Dentist",
            "type":"Services"
        }
    ],
    "sg:phone":"+44 1242 515621",
    "sg:postcode":"GL51 3PQ",
    "sg:province":"Gloucestershire",
    "wof:name":"A J Pusar",
    "wof:placetype":"venue"
},
  "geometry": {"coordinates":[-2.1100580692,51.8879966736],"type":"Point"}
}