{
  "type": "Feature",
  "properties": {
    "addr:full":"34 Dixons Green Road Dudley West Midlands DY2 7DH",
    "addr:housenumber":"34",
    "addr:postcode":"dy2 7dh",
    "addr:street":"Dixons Green Road",
    "iso:country":"GB",
    "sg:address":"34 Dixons Green Road",
    "sg:city":"Dudley",
    "sg:classifiers":[
        {
            "category":"Social Services",
            "subcategory":"Retirement Home",
            "type":"Services"
        },
        {
            "category":"Government",
            "subcategory":"Office",
            "type":"Public Place"
        }
    ],
    "sg:phone":"+44 1384 813500",
    "sg:postcode":"DY2 7DH",
    "sg:province":"West Midlands",
    "sg:tags":[
        "residential",
        "local",
        "care"
    ],
    "wof:name":"The Woodlands",
    "wof:placetype":"venue"
},
  "geometry": {"coordinates":[-2.074717,52.506786],"type":"Point"}
}