{
  "type": "Feature",
  "properties": {
    "addr:full":"6 Haigh Hall Bradford West Yorkshire BD10 9BB",
    "addr:housenumber":"6",
    "addr:postcode":"bd10 9bb",
    "addr:street":"Haigh Hall Bradford West",
    "iso:country":"GB",
    "sg:address":"6 Haigh Hall",
    "sg:city":"Bradford",
    "sg:classifiers":[
        {
            "category":"Building & Trades",
            "subcategory":"Construction",
            "type":"Services"
        }
    ],
    "sg:postcode":"BD10 9BB",
    "sg:province":"West Yorkshire",
    "sg:tags":[
        "builder"
    ],
    "wof:name":"Dexter,Paul,",
    "wof:placetype":"venue"
},
  "geometry": {"coordinates":[-1.7146810293,53.8315544128],"type":"Point"}
}