{
  "type": "Feature",
  "properties": {
    "addr:full":"Bellingham Way, New Hythe, Larkfield Aylesford Kent ME20 6XS",
    "addr:postcode":"me20 6xs",
    "addr:street":"Bellingham Way",
    "iso:country":"GB",
    "sg:address":"Bellingham Way, New Hythe, Larkfield",
    "sg:city":"Aylesford",
    "sg:classifiers":[
        {
            "category":"Wholesale",
            "subcategory":"Machinery & Supplies",
            "type":"Manufacturing & Wholesale Goods"
        }
    ],
    "sg:phone":"+44 1622 716816",
    "sg:postcode":"ME20 6XS",
    "sg:province":"Kent",
    "sg:tags":[
        "pump"
    ],
    "wof:name":"Rietschle (U K) Ltd.",
    "wof:placetype":"venue"
},
  "geometry": {"coordinates":[0.447722,51.308285],"type":"Point"}
}