{
  "type": "Feature",
  "properties": {
    "addr:full":"Bowling Bank Wrexham Wrexham LL13 9RT",
    "addr:postcode":"ll13 9rt",
    "iso:country":"GB",
    "sg:address":"Bowling Bank",
    "sg:city":"Wrexham",
    "sg:classifiers":[
        {
            "category":"Farming",
            "subcategory":"Livestock Farm",
            "type":"Manufacturing & Wholesale Goods"
        }
    ],
    "sg:phone":"+44 1978 661445",
    "sg:postcode":"LL13 9RT",
    "sg:province":"Wrexham",
    "sg:tags":[
        "others"
    ],
    "wof:name":"Thomas Eric Done",
    "wof:placetype":"venue"
},
  "geometry": {"coordinates":[-2.915790081,53.0391082764],"type":"Point"}
}