{
  "type": "Feature",
  "properties": {
    "iso:country":"GB",
    "sg:address":"92 Breck Rd",
    "sg:city":"Wallasey",
    "sg:classifiers":[
        {
            "category":"Building & Trades",
            "subcategory":"Construction",
            "type":"Services"
        }
    ],
    "sg:phone":"+44 151 639 4352",
    "sg:postcode":"L44 3BE",
    "sg:province":"Merseyside",
    "sg:tags":[
        "joinery"
    ],
    "wof:name":"S & B Builders",
    "wof:placetype":"venue"
},
  "geometry": {"coordinates":[-3.056663,53.415131],"type":"Point"}
}