{
  "type": "Feature",
  "properties": {
    "iso:country":"GB",
    "sg:address":"138 Dunstable Road",
    "sg:city":"Luton",
    "sg:classifiers":[
        {
            "category":"Travel",
            "subcategory":"Travel Agent",
            "type":"Entertainment"
        }
    ],
    "sg:postcode":"LU1 1EW",
    "sg:province":"Bedfordshire",
    "wof:name":"Royal International Travel & Currency Exchange",
    "wof:placetype":"venue"
},
  "geometry": {"coordinates":[-0.428425014,51.8856124878],"type":"Point"}
}