{
  "type": "Feature",
  "properties": {
    "addr:full":"Seamer Road Scarborough North Yorkshire YO12 4HF",
    "addr:postcode":"yo12 4hf",
    "addr:street":"Seamer Road",
    "iso:country":"GB",
    "sg:address":"Seamer Road",
    "sg:city":"Scarborough",
    "sg:classifiers":[
        {
            "category":"Education",
            "subcategory":"School",
            "type":"Public Place"
        },
        {
            "category":"Government",
            "subcategory":"Office",
            "type":"Public Place"
        }
    ],
    "sg:phone":"+44 1723 373110",
    "sg:postcode":"YO12 4HF",
    "sg:province":"North Yorkshire",
    "sg:tags":[
        "local",
        "authority"
    ],
    "wof:name":"Hinderwell Community Primary School",
    "wof:placetype":"venue"
},
  "geometry": {"coordinates":[-0.416144,54.275265],"type":"Point"}
}