{
  "type": "Feature",
  "properties": {
    "iso:country":"GB",
    "sg:address":"Crickhowell Rd",
    "sg:city":"Cardiff",
    "sg:classifiers":[
        {
            "category":"Shopping",
            "subcategory":"Pharmacy",
            "type":"Retail Goods"
        }
    ],
    "sg:phone":"+44 29 2079 7300",
    "sg:postcode":"CF3 0EF",
    "sg:province":"Caerphilly",
    "sg:tags":[
        "pharmacist",
        "chemist"
    ],
    "wof:name":"Lloyds Chemist",
    "wof:placetype":"venue"
},
  "geometry": {"coordinates":[-3.101534,51.52475],"type":"Point"}
}