{
  "type": "Feature",
  "properties": {
    "iso:country":"GB",
    "sg:address":"Perry Road",
    "sg:city":"Witham",
    "sg:classifiers":[
        {
            "category":"Professional",
            "subcategory":"Printing & Photocopies",
            "type":"Services"
        }
    ],
    "sg:phone":"+44 1376 513377",
    "sg:postcode":"CM8 3UY",
    "sg:province":"Essex",
    "sg:tags":[
        "print",
        "finisher"
    ],
    "wof:name":"The Finishing Touch",
    "wof:placetype":"venue"
},
  "geometry": {"coordinates":[0.64667,51.794643],"type":"Point"}
}