{
  "type": "Feature",
  "properties": {
    "iso:country":"GB",
    "sg:address":"113 Market St, Atherton",
    "sg:city":"Manchester",
    "sg:classifiers":[
        {
            "category":"Shopping",
            "subcategory":"Gifts & Souvenirs",
            "type":"Retail Goods"
        }
    ],
    "sg:phone":"+44 1942 878845",
    "sg:postcode":"M46 0DF",
    "sg:province":"Greater Manchester",
    "sg:tags":[
        "shop"
    ],
    "wof:name":"M & M Store",
    "wof:placetype":"venue"
},
  "geometry": {"coordinates":[-2.495659,53.523705],"type":"Point"}
}