{
  "type": "Feature",
  "properties": {
    "addr:full":"10 Tay Street Perth Perth and Kinross PH1 5LQ",
    "addr:housenumber":"10",
    "addr:postcode":"ph1 5lq",
    "addr:street":"Tay Street",
    "iso:country":"GB",
    "sg:address":"10 Tay Street",
    "sg:city":"Perth",
    "sg:classifiers":[
        {
            "category":"Organizations",
            "subcategory":"Community Association",
            "type":"Services"
        },
        {
            "category":"Organizations",
            "subcategory":"Membership Organization",
            "type":"Services"
        }
    ],
    "sg:phone":"+44 1738 625100",
    "sg:postcode":"PH1 5LQ",
    "sg:province":"Perth and Kinross",
    "sg:tags":[
        "club",
        "social"
    ],
    "wof:name":"THE NEW CLUB",
    "wof:placetype":"venue"
},
  "geometry": {"coordinates":[-3.426429987,56.3975906372],"type":"Point"}
}