{
  "type": "Feature",
  "properties": {
    "addr:full":"38 Russell Square Brighton East Sussex BN1 2EF",
    "addr:housenumber":"38",
    "addr:postcode":"bn1 2ef",
    "addr:street":"Russell Square",
    "iso:country":"GB",
    "sg:address":"38 Russell Square",
    "sg:city":"Brighton",
    "sg:classifiers":[
        {
            "category":"Travel",
            "subcategory":"Hotels & Motels",
            "type":"Entertainment"
        }
    ],
    "sg:phone":"+44 1273 700800",
    "sg:postcode":"BN1 2EF",
    "sg:province":"East Sussex",
    "wof:name":"Valentine House Hotel",
    "wof:placetype":"venue"
},
  "geometry": {"coordinates":[-0.14812,50.822754],"type":"Point"}
}