{
  "type": "Feature",
  "properties": {
    "addr:full":"2a Woodlands Rd Liverpool Merseyside L17 0AW",
    "addr:housenumber":"2a",
    "addr:postcode":"l17 0aw",
    "addr:street":"Woodlands Rd",
    "iso:country":"GB",
    "sg:address":"2a Woodlands Rd",
    "sg:city":"Liverpool",
    "sg:classifiers":[
        {
            "category":"Building & Trades",
            "subcategory":"Construction",
            "type":"Services"
        }
    ],
    "sg:postcode":"L17 0AW",
    "sg:province":"Merseyside",
    "sg:tags":[
        "builder"
    ],
    "wof:name":"Coote,Paul,",
    "wof:placetype":"venue"
},
  "geometry": {"coordinates":[-2.932641,53.371342],"type":"Point"}
}