{
  "type": "Feature",
  "properties": {
    "addr:full":"62 High Street, Weedon Northampton Buckinghamshire NN7 4QD",
    "addr:housenumber":"62",
    "addr:postcode":"nn7 4qd",
    "addr:street":"High Street",
    "iso:country":"GB",
    "sg:address":"62 High Street, Weedon",
    "sg:city":"Northampton",
    "sg:classifiers":[
        {
            "category":"Sports & Exercise",
            "subcategory":"Gym",
            "type":"Entertainment"
        }
    ],
    "sg:postcode":"NN7 4QD",
    "sg:province":"Buckinghamshire",
    "sg:tags":[
        "fitness",
        "health",
        "centre"
    ],
    "wof:name":"Bodybitz",
    "wof:placetype":"venue"
},
  "geometry": {"coordinates":[-1.0533659458,52.2373580933],"type":"Point"}
}