{
  "type": "Feature",
  "properties": {
    "addr:full":"8 Northlands Avenue Haywards Heath East Sussex RH16 3RT",
    "addr:housenumber":"8",
    "addr:postcode":"rh16 3rt",
    "addr:street":"Northlands Avenue",
    "iso:country":"GB",
    "sg:address":"8 Northlands Avenue",
    "sg:city":"Haywards Heath",
    "sg:classifiers":[
        {
            "category":"Professional",
            "subcategory":"Accounting & Tax Preparation",
            "type":"Services"
        }
    ],
    "sg:phone":"+44 1444 450280",
    "sg:postcode":"RH16 3RT",
    "sg:province":"East Sussex",
    "sg:tags":[
        "accountant"
    ],
    "wof:name":"Mid Sussex Office Services",
    "wof:placetype":"venue"
},
  "geometry": {"coordinates":[-0.084043,50.99498],"type":"Point"}
}