{
  "type": "Feature",
  "properties": {
    "iso:country":"GB",
    "sg:address":"57 Cavendish Road, Edgbaston",
    "sg:city":"Birmingham",
    "sg:classifiers":[
        {
            "category":"Government",
            "subcategory":"Post Office",
            "type":"Public Place"
        }
    ],
    "sg:phone":"+44 121 247 5648",
    "sg:postcode":"B16 0HT",
    "sg:province":"West Midlands",
    "sg:tags":[
        "messenger",
        "courier"
    ],
    "wof:name":"Milennium Express Couriers",
    "wof:placetype":"venue"
},
  "geometry": {"coordinates":[-1.945945,52.48513],"type":"Point"}
}