{
  "type": "Feature",
  "properties": {
    "addr:full":"220-228 Northdown Road, Cliftonville Margate Kent CT9 2RP",
    "addr:housenumber":"220-228",
    "addr:postcode":"ct9 2rp",
    "addr:street":"Northdown Road;Margate",
    "iso:country":"GB",
    "sg:address":"220-228 Northdown Road, Cliftonville",
    "sg:city":"Margate",
    "sg:classifiers":[
        {
            "category":"Government",
            "subcategory":"Post Office",
            "type":"Public Place"
        }
    ],
    "sg:postcode":"CT9 2RP",
    "sg:province":"Kent",
    "sg:tags":[
        "print",
        "typesetter"
    ],
    "wof:name":"Trutape Setting Systems Ltd.",
    "wof:placetype":"venue"
},
  "geometry": {"coordinates":[1.39641,51.387959],"type":"Point"}
}