{
  "type": "Feature",
  "properties": {
    "addr:full":"13 Bedford Close Maidenhead Berkshire SL6 3UP",
    "addr:housenumber":"13",
    "addr:postcode":"sl6 3up",
    "addr:street":"Bedford Close",
    "iso:country":"GB",
    "sg:address":"13 Bedford Close",
    "sg:city":"Maidenhead",
    "sg:classifiers":[
        {
            "category":"Professional",
            "subcategory":"Computer Services",
            "type":"Services"
        }
    ],
    "sg:postcode":"SL6 3UP",
    "sg:province":"Berkshire",
    "sg:tags":[
        "system",
        "software"
    ],
    "wof:name":"Bga (uk) Ltd",
    "wof:placetype":"venue"
},
  "geometry": {"coordinates":[-0.755382,51.506237],"type":"Point"}
}