{
  "type": "Feature",
  "properties": {
    "addr:full":"164-166 Sidwell St Exeter Devon EX4 6RH",
    "addr:housenumber":"164-166",
    "addr:postcode":"ex4 6rh",
    "addr:street":"Sidwell St",
    "iso:country":"GB",
    "sg:address":"164-166 Sidwell St",
    "sg:city":"Exeter",
    "sg:classifiers":[
        {
            "category":"Shopping",
            "subcategory":"Used Merchandise",
            "type":"Retail Goods"
        }
    ],
    "sg:phone":"+44 1392 491221",
    "sg:postcode":"EX4 6RH",
    "sg:province":"Devon",
    "sg:tags":[
        "shop",
        "second-hand"
    ],
    "wof:name":"Cash Converters Exeter",
    "wof:placetype":"venue"
},
  "geometry": {"coordinates":[-3.5248439312,50.7264480591],"type":"Point"}
}