{
  "type": "Feature",
  "properties": {
    "addr:full":"Longhayne Farm, Chevithorne Tiverton Devon EX16 7QN",
    "addr:postcode":"ex16 7qn",
    "addr:street":"Chevithorne",
    "iso:country":"GB",
    "sg:address":"Longhayne Farm, Chevithorne",
    "sg:city":"Tiverton",
    "sg:classifiers":[
        {
            "category":"Farming",
            "subcategory":"Farm",
            "type":"Manufacturing & Wholesale Goods"
        }
    ],
    "sg:phone":"+44 1398 331433",
    "sg:postcode":"EX16 7QN",
    "sg:province":"Devon",
    "sg:tags":[
        "mixed",
        "crop"
    ],
    "wof:name":"D A & C R Heard",
    "wof:placetype":"venue"
},
  "geometry": {"coordinates":[-3.4579739571,50.9294281006],"type":"Point"}
}