{
  "type": "Feature",
  "properties": {
    "iso:country":"GB",
    "sg:address":"140 Ochiltree",
    "sg:city":"Dunblane",
    "sg:classifiers":[
        {
            "category":"Mining & Drilling",
            "type":"Manufacturing & Wholesale Goods"
        }
    ],
    "sg:phone":"+44 1786 824867",
    "sg:postcode":"FK15 0PB",
    "sg:province":"Perth and Kinross",
    "sg:tags":[
        "oil",
        "petroleum"
    ],
    "wof:name":"J Sloan",
    "wof:placetype":"venue"
},
  "geometry": {"coordinates":[-3.952475,56.197021],"type":"Point"}
}