{
  "type": "Feature",
  "properties": {
    "addr:full":"Kelvin Campus, Maryhill Road Glasgow Glasgow City G20 0SP",
    "addr:postcode":"g20 0sp",
    "addr:street":"Maryhill Road",
    "iso:country":"GB",
    "sg:address":"Kelvin Campus, Maryhill Road",
    "sg:city":"Glasgow",
    "sg:classifiers":[
        {
            "category":"Health Services",
            "subcategory":"Hospital",
            "type":"Services"
        }
    ],
    "sg:postcode":"G20 0SP",
    "sg:province":"Glasgow City",
    "sg:tags":[
        "surgical"
    ],
    "wof:name":"Semple Campbell",
    "wof:placetype":"venue"
},
  "geometry": {"coordinates":[-4.3133201599,55.9012908936],"type":"Point"}
}