{
  "type": "Feature",
  "properties": {
    "iso:country":"GB",
    "sg:address":"6 Clifton Square",
    "sg:city":"Lytham St Annes",
    "sg:classifiers":[
        {
            "category":"Banks & Credit Unions",
            "subcategory":"Bank",
            "type":"Services"
        }
    ],
    "sg:phone":"+44 1253 613909",
    "sg:postcode":"FY8 5JU",
    "sg:province":"Lancashire",
    "sg:tags":[
        "financial",
        "institution"
    ],
    "wof:name":"HSBC Bank plc",
    "wof:placetype":"venue"
},
  "geometry": {"coordinates":[-2.9635241032,53.7369499207],"type":"Point"}
}