{
  "type": "Feature",
  "properties": {
    "addr:full":"Unit 14, Elder Way Slough Berkshire SL3 6EP",
    "addr:housenumber":"unit 14",
    "addr:postcode":"sl3 6ep",
    "addr:street":"Elder Way",
    "iso:country":"GB",
    "sg:address":"Unit 14, Elder Way",
    "sg:city":"Slough",
    "sg:classifiers":[
        {
            "category":"Shopping",
            "subcategory":"Stationery & Office Supplies",
            "type":"Retail Goods"
        }
    ],
    "sg:phone":"+44 1753 212380",
    "sg:postcode":"SL3 6EP",
    "sg:province":"Berkshire",
    "sg:tags":[
        "printers'"
    ],
    "wof:name":"Bits 'N' P C's Ltd.",
    "wof:placetype":"venue"
},
  "geometry": {"coordinates":[-0.547686,51.508369],"type":"Point"}
}