{
  "type": "Feature",
  "properties": {
    "addr:full":"3 Market Way Northwich Cheshire CW9 5AZ",
    "addr:housenumber":"3",
    "addr:postcode":"cw9 5az",
    "addr:street":"Market Way",
    "iso:country":"GB",
    "sg:address":"3 Market Way",
    "sg:city":"Northwich",
    "sg:classifiers":[
        {
            "category":"Travel",
            "subcategory":"Travel Agent",
            "type":"Entertainment"
        }
    ],
    "sg:postcode":"CW9 5AZ",
    "sg:province":"Cheshire",
    "wof:name":"J L & D A Gray Ltd.",
    "wof:placetype":"venue"
},
  "geometry": {"coordinates":[-2.514692,53.261066],"type":"Point"}
}