{
  "type": "Feature",
  "properties": {
    "addr:full":"Rosewood Mill, Wilshaw Rd Huddersfield West Yorkshire HD7 2US",
    "addr:postcode":"hd7 2us",
    "addr:street":"Rosewood;Wilshaw Rd",
    "iso:country":"GB",
    "sg:address":"Rosewood Mill, Wilshaw Rd",
    "sg:city":"Huddersfield",
    "sg:classifiers":[
        {
            "category":"Shopping",
            "subcategory":"Stationery & Office Supplies",
            "type":"Retail Goods"
        }
    ],
    "sg:phone":"+44 1484 681618",
    "sg:postcode":"HD7 2US",
    "sg:province":"West Yorkshire",
    "wof:name":"Idaho Stationery",
    "wof:placetype":"venue"
},
  "geometry": {"coordinates":[-1.78268,53.64695],"type":"Point"}
}