{
  "type": "Feature",
  "properties": {
    "iso:country":"GB",
    "sg:address":"Lane Niche",
    "sg:city":"South Petherton",
    "sg:classifiers":[
        {
            "category":"Professional",
            "subcategory":"Engineering",
            "type":"Services"
        },
        {
            "category":"Real Estate",
            "subcategory":"Architect",
            "type":"Services"
        }
    ],
    "sg:phone":"+44 1460 240808",
    "sg:postcode":"TA13 5AG",
    "sg:province":"Somerset",
    "sg:tags":[
        "consulting",
        "engineer"
    ],
    "wof:name":"Incast Consultancy Ltd",
    "wof:placetype":"venue"
},
  "geometry": {"coordinates":[-2.805539,50.949532],"type":"Point"}
}