{
  "type": "Feature",
  "properties": {
    "iso:country":"GB",
    "sg:address":"37 Sherbourne Road",
    "sg:city":"Blackpool",
    "sg:classifiers":[
        {
            "category":"Military Area",
            "subcategory":"Air Force Base",
            "type":"Public Place"
        },
        {
            "category":"Wholesale",
            "subcategory":"Toys & Hobbies",
            "type":"Manufacturing & Wholesale Goods"
        }
    ],
    "sg:phone":"+44 1253 295040",
    "sg:postcode":"FY1 2PN",
    "sg:province":"Lancashire",
    "sg:tags":[
        "balloon",
        "novelty"
    ],
    "wof:name":"Balloonatics",
    "wof:placetype":"venue"
},
  "geometry": {"coordinates":[-3.049179,53.828415],"type":"Point"}
}