{
  "type": "Feature",
  "properties": {
    "addr:full":"Rainbow Centre, Clarence Street Morecambe Lancashire LA4 5EX",
    "addr:postcode":"la4 5ex",
    "addr:street":"Clarence Street",
    "iso:country":"GB",
    "sg:address":"Rainbow Centre, Clarence Street",
    "sg:city":"Morecambe",
    "sg:classifiers":[
        {
            "category":"Organizations",
            "subcategory":"Non-profit Organization",
            "type":"Services"
        }
    ],
    "sg:phone":"+44 1524 411364",
    "sg:postcode":"LA4 5EX",
    "sg:province":"Lancashire",
    "sg:tags":[
        "organisation",
        "voluntary",
        "charity"
    ],
    "wof:name":"W R V S",
    "wof:placetype":"venue"
},
  "geometry": {"coordinates":[-2.854494,54.070129],"type":"Point"}
}