{
  "type": "Feature",
  "properties": {
    "addr:full":"16 High Street, Seal Sevenoaks Kent TN15 0AJ",
    "addr:housenumber":"16",
    "addr:postcode":"tn15 0aj",
    "addr:street":"High Street",
    "iso:country":"GB",
    "sg:address":"16 High Street, Seal",
    "sg:city":"Sevenoaks",
    "sg:classifiers":[
        {
            "category":"Bars & Pubs",
            "type":"Food & Drink"
        }
    ],
    "sg:phone":"+44 1732 761023",
    "sg:postcode":"TN15 0AJ",
    "sg:province":"Kent",
    "sg:tags":[
        "pubs",
        "inn"
    ],
    "wof:name":"The Crown Inn Seal",
    "wof:placetype":"venue"
},
  "geometry": {"coordinates":[0.2215860039,51.2883453369],"type":"Point"}
}