{
  "type": "Feature",
  "properties": {
    "iso:country":"GB",
    "sg:address":"Unit 60, Anne Road",
    "sg:city":"Smethwick",
    "sg:classifiers":[
        {
            "category":"Wholesale",
            "subcategory":"Scrap",
            "type":"Manufacturing & Wholesale Goods"
        },
        {
            "category":"Manufacturing",
            "subcategory":"Building Materials",
            "type":"Manufacturing & Wholesale Goods"
        }
    ],
    "sg:phone":"+44 121 555 5476",
    "sg:postcode":"B66 2NZ",
    "sg:province":"West Midlands",
    "sg:tags":[
        "merchant",
        "builder",
        "waste",
        "metal"
    ],
    "wof:name":"ALL METAL RECOVERY LTD",
    "wof:placetype":"venue"
},
  "geometry": {"coordinates":[-1.94816,52.500179],"type":"Point"}
}