{
  "type": "Feature",
  "properties": {
    "iso:country":"GB",
    "sg:address":"Bowling Green Street",
    "sg:city":"Warwick",
    "sg:classifiers":[
        {
            "category":"Education",
            "subcategory":"Preschool",
            "type":"Public Place"
        },
        {
            "category":"Education",
            "subcategory":"School",
            "type":"Public Place"
        }
    ],
    "sg:phone":"+44 1926 492015",
    "sg:postcode":"CV34 4DD",
    "sg:province":"Warwickshire",
    "sg:tags":[
        "playgroups",
        "pre-school",
        "local",
        "authority"
    ],
    "wof:name":"Westgate Primary School",
    "wof:placetype":"venue"
},
  "geometry": {"coordinates":[-1.590919,52.279625],"type":"Point"}
}