{
  "type": "Feature",
  "properties": {
    "addr:full":"13a Marefair Northampton Northamptonshire NN1 1SR",
    "addr:housenumber":"13a",
    "addr:postcode":"nn1 1sr",
    "addr:street":"Marefair Northampton",
    "iso:country":"GB",
    "sg:address":"13a Marefair",
    "sg:city":"Northampton",
    "sg:classifiers":[
        {
            "category":"Shopping",
            "subcategory":"Music",
            "type":"Retail Goods"
        }
    ],
    "sg:postcode":"NN1 1SR",
    "sg:province":"Northamptonshire",
    "sg:tags":[
        "record",
        "tape",
        "cd"
    ],
    "wof:name":"Essential Vinyl & Clothing",
    "wof:placetype":"venue"
},
  "geometry": {"coordinates":[-0.904072,52.23679],"type":"Point"}
}