{
  "type": "Feature",
  "properties": {
    "iso:country":"GB",
    "sg:address":"3 Castle Market",
    "sg:city":"Sheffield",
    "sg:classifiers":[
        {
            "category":"Farming",
            "subcategory":"Fish & Marine Products",
            "type":"Manufacturing & Wholesale Goods"
        }
    ],
    "sg:phone":"+44 114 272 4837",
    "sg:postcode":"S1 2AJ",
    "sg:province":"South Yorkshire",
    "sg:tags":[
        "fishmonger"
    ],
    "wof:name":"A & S Foods",
    "wof:placetype":"venue"
},
  "geometry": {"coordinates":[-1.465195,53.384571],"type":"Point"}
}