{
  "type": "Feature",
  "properties": {
    "addr:full":"Gillfoot, Dundrennan Kirkcudbright Dumfries and Galloway DG6 4QH",
    "addr:postcode":"dg6 4qh",
    "addr:street":"Dundrennan",
    "iso:country":"GB",
    "sg:address":"Gillfoot, Dundrennan",
    "sg:city":"Kirkcudbright",
    "sg:classifiers":[
        {
            "category":"Organizations",
            "subcategory":"Non-profit Organization",
            "type":"Services"
        }
    ],
    "sg:phone":"+44 1557 500242",
    "sg:postcode":"DG6 4QH",
    "sg:province":"Dumfries and Galloway",
    "sg:tags":[
        "organisation",
        "animal",
        "welfare"
    ],
    "wof:name":"Cats Protection",
    "wof:placetype":"venue"
},
  "geometry": {"coordinates":[-4.047639,54.836971],"type":"Point"}
}