{
  "type": "Feature",
  "properties": {
    "iso:country":"GB",
    "sg:address":"Carole Ho, Pinnox St",
    "sg:city":"Stoke On Trent",
    "sg:classifiers":[
        {
            "category":"Organizations",
            "subcategory":"Non-profit Organization",
            "type":"Services"
        }
    ],
    "sg:phone":"+44 1782 575723",
    "sg:postcode":"ST6 6AH",
    "sg:province":"Staffordshire",
    "sg:tags":[
        "organisation",
        "voluntary",
        "charity"
    ],
    "wof:name":"NSPCC",
    "wof:placetype":"venue"
},
  "geometry": {"coordinates":[-2.20938,53.054859],"type":"Point"}
}