{
  "type": "Feature",
  "properties": {
    "addr:full":"2 Chandlers Court, Picow Farm Road Runcorn Cheshire WA7 4UH",
    "addr:housenumber":"2",
    "addr:postcode":"wa7 4uh",
    "addr:street":"Chandlers Court Picow Farm Road",
    "iso:country":"GB",
    "sg:address":"2 Chandlers Court, Picow Farm Road",
    "sg:city":"Runcorn",
    "sg:classifiers":[
        {
            "category":"Government",
            "subcategory":"Post Office",
            "type":"Public Place"
        }
    ],
    "sg:phone":"+44 1928 561018",
    "sg:postcode":"WA7 4UH",
    "sg:province":"Cheshire",
    "sg:tags":[
        "messenger",
        "courier"
    ],
    "wof:name":"Rosier Services",
    "wof:placetype":"venue"
},
  "geometry": {"coordinates":[-2.7090189457,53.3304214478],"type":"Point"}
}