{
  "type": "Feature",
  "properties": {
    "addr:full":"310 Eastcote Lane Harrow Greater London HA2 8RU",
    "addr:housenumber":"310",
    "addr:postcode":"ha2 8ru",
    "addr:street":"Eastcote Lane",
    "iso:country":"GB",
    "sg:address":"310 Eastcote Lane",
    "sg:city":"Harrow",
    "sg:classifiers":[
        {
            "category":"Food & Beverages",
            "subcategory":"Fruits & Vegetables",
            "type":"Retail Goods"
        }
    ],
    "sg:postcode":"HA2 8RU",
    "sg:province":"Greater London",
    "sg:tags":[
        "greengrocer"
    ],
    "wof:name":"Santa Rajh",
    "wof:placetype":"venue"
},
  "geometry": {"coordinates":[-0.3714300096,51.5623054504],"type":"Point"}
}