{
  "type": "Feature",
  "properties": {
    "iso:country":"GB",
    "sg:address":"97 Mortimer Road, Filton",
    "sg:city":"Bristol",
    "sg:classifiers":[
        {
            "category":"Real Estate",
            "subcategory":"Architect",
            "type":"Services"
        }
    ],
    "sg:phone":"+44 117 969 1294",
    "sg:postcode":"BS34 7LH",
    "sg:province":"Gloucestershire",
    "sg:tags":[
        "architectural"
    ],
    "wof:name":"K P Bayliss",
    "wof:placetype":"venue"
},
  "geometry": {"coordinates":[-2.564771,51.506046],"type":"Point"}
}