{
  "type": "Feature",
  "properties": {
    "addr:full":"2 Boxer Place, Moss Side, Leyland Preston Lancashire PR5 3QL",
    "addr:housenumber":"2",
    "addr:postcode":"pr5 3ql",
    "addr:street":"Boxer Place",
    "iso:country":"GB",
    "sg:address":"2 Boxer Place, Moss Side, Leyland",
    "sg:city":"Preston",
    "sg:classifiers":[
        {
            "category":"Retail",
            "subcategory":"Auto Repair",
            "type":"Services"
        }
    ],
    "sg:phone":"+44 1772 421773",
    "sg:postcode":"PR5 3QL",
    "sg:province":"Lancashire",
    "sg:tags":[
        "modification",
        "garage"
    ],
    "wof:name":"Naylors Motor Sales",
    "wof:placetype":"venue"
},
  "geometry": {"coordinates":[-2.7340099812,53.6929512024],"type":"Point"}
}