{
  "type": "Feature",
  "properties": {
    "addr:full":"Unit 14, The Shires Industrial Estate, Birmingham Road Lichfield Staffordshire WS14 9BW",
    "addr:housenumber":"unit 14",
    "addr:postcode":"ws14 9bw",
    "addr:street":"The Shires Industrial Estate Birmingham Road",
    "iso:country":"GB",
    "sg:address":"Unit 14, The Shires Industrial Estate, Birmingham Road",
    "sg:city":"Lichfield",
    "sg:classifiers":[
        {
            "category":"Manufacturing",
            "subcategory":"Metals",
            "type":"Manufacturing & Wholesale Goods"
        }
    ],
    "sg:postcode":"WS14 9BW",
    "sg:province":"Staffordshire",
    "sg:tags":[
        "work",
        "sheet"
    ],
    "wof:name":"Lichfield Sheet Metal Craft",
    "wof:placetype":"venue"
},
  "geometry": {"coordinates":[-1.8325079679,52.673374176],"type":"Point"}
}