{
  "type": "Feature",
  "properties": {
    "addr:full":"48 Milton Street Ipswich Suffolk IP4 4PR",
    "addr:housenumber":"48",
    "addr:postcode":"ip4 4pr",
    "addr:street":"Milton Street",
    "iso:country":"GB",
    "sg:address":"48 Milton Street",
    "sg:city":"Ipswich",
    "sg:classifiers":[
        {
            "category":"Building & Trades",
            "subcategory":"Construction",
            "type":"Services"
        }
    ],
    "sg:phone":"+44 1473 716559",
    "sg:postcode":"IP4 4PR",
    "sg:province":"Suffolk",
    "sg:tags":[
        "roofing"
    ],
    "wof:name":"S P F",
    "wof:placetype":"venue"
},
  "geometry": {"coordinates":[1.186393,52.060566],"type":"Point"}
}