{
  "type": "Feature",
  "properties": {
    "iso:country":"GB",
    "sg:address":"11 The Green",
    "sg:city":"Sutton In Ashfield",
    "sg:classifiers":[
        {
            "category":"Retail",
            "subcategory":"Driving School",
            "type":"Services"
        }
    ],
    "sg:phone":"+44 1623 554927",
    "sg:postcode":"NG17 2RP",
    "sg:province":"Nottinghamshire",
    "wof:name":"Moore School Of Motoring",
    "wof:placetype":"venue"
},
  "geometry": {"coordinates":[-1.3011339903,53.1211967468],"type":"Point"}
}