{
  "type": "Feature",
  "properties": {
    "iso:country":"GB",
    "sg:address":"Po Box 845",
    "sg:city":"Halifax",
    "sg:classifiers":[
        {
            "category":"Shopping",
            "subcategory":"Computers & Home Electronics",
            "type":"Retail Goods"
        }
    ],
    "sg:phone":"+44 800 042 4646",
    "sg:postcode":"HX3 6YR",
    "sg:province":"West Yorkshire",
    "sg:tags":[
        "consumables"
    ],
    "wof:name":"Bingo Office Supplies Ltd.",
    "wof:placetype":"venue"
},
  "geometry": {"coordinates":[-1.864769,53.73494],"type":"Point"}
}