{
  "type": "Feature",
  "properties": {
    "addr:full":"561 Trentham Road Stoke-on-trent Staffordshire ST3 3BN",
    "addr:housenumber":"561",
    "addr:postcode":"st3 3bn",
    "addr:street":"Trentham Road",
    "iso:country":"GB",
    "sg:address":"561 Trentham Road",
    "sg:city":"Stoke-on-trent",
    "sg:classifiers":[
        {
            "category":"Health Services",
            "subcategory":"Health Practitioner",
            "type":"Services"
        }
    ],
    "sg:phone":"+44 1782 331807",
    "sg:postcode":"ST3 3BN",
    "sg:province":"Staffordshire",
    "sg:tags":[
        "hypnotherapists"
    ],
    "wof:name":"Hypnosis & Parapsychology",
    "wof:placetype":"venue"
},
  "geometry": {"coordinates":[-2.1527979374,52.970539093],"type":"Point"}
}