{
  "type": "Feature",
  "properties": {
    "iso:country":"GB",
    "sg:address":"7 Barrow Road, Sileby",
    "sg:city":"Loughborough",
    "sg:classifiers":[
        {
            "category":"Restaurant",
            "type":"Food & Drink"
        }
    ],
    "sg:postcode":"LE12 7LW",
    "sg:province":"Leicestershire",
    "wof:name":"The Old School Restaurant",
    "wof:placetype":"venue"
},
  "geometry": {"coordinates":[-1.1123,52.731483],"type":"Point"}
}