{
  "type": "Feature",
  "properties": {
    "addr:full":"Church Lane, Ravenstone Coalville Leicestershire LE67 2AE",
    "addr:postcode":"le67 2ae",
    "addr:street":"Church Lane",
    "iso:country":"GB",
    "sg:address":"Church Lane, Ravenstone",
    "sg:city":"Coalville",
    "sg:classifiers":[
        {
            "category":"Education",
            "subcategory":"School",
            "type":"Public Place"
        }
    ],
    "sg:phone":"+44 1530 832431",
    "sg:postcode":"LE67 2AE",
    "sg:province":"Leicestershire",
    "sg:tags":[
        "local",
        "authority"
    ],
    "wof:name":"Ravenstone County Primary",
    "wof:placetype":"venue"
},
  "geometry": {"coordinates":[-1.3984470367,52.7180366516],"type":"Point"}
}