{
  "type": "Feature",
  "properties": {
    "iso:country":"GB",
    "sg:address":"20 Lavender Avenue",
    "sg:city":"Worcester Park",
    "sg:classifiers":[
        {
            "category":"Wholesale",
            "subcategory":"Books, Periodicals, & Newspapers",
            "type":"Manufacturing & Wholesale Goods"
        }
    ],
    "sg:phone":"+44 20 8286 8889",
    "sg:postcode":"KT4 8RR",
    "sg:province":"Surrey",
    "sg:tags":[
        "publishing"
    ],
    "wof:name":"Transmission & Distribution",
    "wof:placetype":"venue"
},
  "geometry": {"coordinates":[-0.227986,51.372585],"type":"Point"}
}