{
  "type": "Feature",
  "properties": {
    "addr:full":"25 St James Street London Greater London E17 7PJ",
    "addr:housenumber":"25",
    "addr:postcode":"e17 7pj",
    "addr:street":"St James Street",
    "iso:country":"GB",
    "sg:address":"25 St James Street",
    "sg:city":"London",
    "sg:classifiers":[
        {
            "category":"Retail",
            "subcategory":"Auto Repair",
            "type":"Services"
        }
    ],
    "sg:phone":"+44 20 8521 8333",
    "sg:postcode":"E17 7PJ",
    "sg:province":"Greater London",
    "sg:tags":[
        "body",
        "car",
        "repairer"
    ],
    "wof:name":"P & P Body Shop",
    "wof:placetype":"venue"
},
  "geometry": {"coordinates":[-0.03266,51.58025],"type":"Point"}
}