{
  "type": "Feature",
  "properties": {
    "addr:full":"19 Market Pl Alfreton Derbyshire DE55 2BN",
    "addr:housenumber":"19",
    "addr:postcode":"de55 2bn",
    "addr:street":"Market Pl",
    "iso:country":"GB",
    "sg:address":"19 Market Pl",
    "sg:city":"Alfreton",
    "sg:classifiers":[
        {
            "category":"Professional",
            "subcategory":"Accounting & Tax Preparation",
            "type":"Services"
        }
    ],
    "sg:phone":"+44 1773 813952",
    "sg:postcode":"DE55 2BN",
    "sg:province":"Derbyshire",
    "sg:tags":[
        "consultant"
    ],
    "wof:name":"T J Marshall & Co",
    "wof:placetype":"venue"
},
  "geometry": {"coordinates":[-1.343914032,53.101436615],"type":"Point"}
}