{
  "type": "Feature",
  "properties": {
    "addr:full":"19a Chapel Street Blackpool Lancashire FY1 5AW",
    "addr:housenumber":"19a",
    "addr:postcode":"fy1 5aw",
    "addr:street":"Chapel Street",
    "iso:country":"GB",
    "sg:address":"19a Chapel Street",
    "sg:city":"Blackpool",
    "sg:classifiers":[
        {
            "category":"Food & Beverages",
            "subcategory":"Candy",
            "type":"Retail Goods"
        }
    ],
    "sg:phone":"+44 1253 751136",
    "sg:postcode":"FY1 5AW",
    "sg:province":"Lancashire",
    "sg:tags":[
        "confectioner"
    ],
    "wof:name":"Ruth Patton",
    "wof:placetype":"venue"
},
  "geometry": {"coordinates":[-3.053591,53.81123],"type":"Point"}
}