{
  "type": "Feature",
  "properties": {
    "iso:country":"GB",
    "sg:address":"Unit 4 Larkhill",
    "sg:city":"Kidderminster",
    "sg:classifiers":[
        {
            "category":"Shopping",
            "subcategory":"Stationery & Office Supplies",
            "type":"Retail Goods"
        }
    ],
    "sg:phone":"+44 1562 745202",
    "sg:postcode":"DY10 2NW",
    "sg:province":"Staffordshire",
    "sg:tags":[
        "adhesive",
        "tape",
        "domestic"
    ],
    "wof:name":"Stokvis Tapes (Uk)",
    "wof:placetype":"venue"
},
  "geometry": {"coordinates":[-2.245518,52.394604],"type":"Point"}
}