{
  "type": "Feature",
  "properties": {
    "iso:country":"GB",
    "sg:address":"21 Deansgate, Radcliffe",
    "sg:city":"Manchester",
    "sg:classifiers":[
        {
            "category":"Insurance",
            "subcategory":"Insurance Agent",
            "type":"Services"
        }
    ],
    "sg:phone":"+44 161 725 9390",
    "sg:postcode":"M26 2SH",
    "sg:province":"Greater Manchester",
    "wof:name":"Deansgate Insurance Services Ltd.",
    "wof:placetype":"venue"
},
  "geometry": {"coordinates":[-2.324774,53.559502],"type":"Point"}
}