{
  "type": "Feature",
  "properties": {
    "addr:full":"67 Halsall Road Southport Lancashire PR8 3DB",
    "addr:housenumber":"67",
    "addr:postcode":"pr8 3db",
    "addr:street":"Halsall Road",
    "iso:country":"GB",
    "sg:address":"67 Halsall Road",
    "sg:city":"Southport",
    "sg:classifiers":[
        {
            "category":"Shopping",
            "subcategory":"Pharmacy",
            "type":"Retail Goods"
        }
    ],
    "sg:postcode":"PR8 3DB",
    "sg:province":"Lancashire",
    "sg:tags":[
        "medicine",
        "therapy"
    ],
    "wof:name":"Peter Bimpson",
    "wof:placetype":"venue"
},
  "geometry": {"coordinates":[-3.011601,53.616127],"type":"Point"}
}