{
  "type": "Feature",
  "properties": {
    "iso:country":"GB",
    "sg:address":"Southwoods Farm, Lodge Road, Woodham Mortimer",
    "sg:city":"Maldon",
    "sg:classifiers":[
        {
            "category":"Farming",
            "subcategory":"Poultry Farm",
            "type":"Manufacturing & Wholesale Goods"
        }
    ],
    "sg:phone":"+44 1621 828148",
    "sg:postcode":"CM9 6SJ",
    "sg:province":"Essex",
    "sg:tags":[
        "game"
    ],
    "wof:name":"Firth Partnership",
    "wof:placetype":"venue"
},
  "geometry": {"coordinates":[0.62384,51.711643],"type":"Point"}
}