{
  "type": "Feature",
  "properties": {
    "iso:country":"GB",
    "sg:address":"21 Redmans Road",
    "sg:city":"London",
    "sg:classifiers":[
        {
            "category":"Insurance",
            "subcategory":"Insurance Agent",
            "type":"Services"
        }
    ],
    "sg:phone":"+44 20 7790 2460",
    "sg:postcode":"E1 3AQ",
    "sg:province":"Greater London",
    "sg:tags":[
        "broker"
    ],
    "wof:name":"Risk Management & Insurance Services",
    "wof:placetype":"venue"
},
  "geometry": {"coordinates":[-0.051063,51.519264],"type":"Point"}
}