{
  "type": "Feature",
  "properties": {
    "addr:full":"Stannergate Road Dundee Dundee City DD1 3NA",
    "addr:postcode":"dd1 3na",
    "addr:street":"Stannergate Road",
    "iso:country":"GB",
    "sg:address":"Stannergate Road",
    "sg:city":"Dundee",
    "sg:classifiers":[
        {
            "category":"Cafe",
            "type":"Food & Drink"
        }
    ],
    "sg:phone":"+44 1382 450816",
    "sg:postcode":"DD1 3NA",
    "sg:province":"Dundee City",
    "sg:tags":[
        "tea",
        "room"
    ],
    "wof:name":"The Tay Cafe",
    "wof:placetype":"venue"
},
  "geometry": {"coordinates":[-2.923736,56.467979],"type":"Point"}
}