{
  "type": "Feature",
  "properties": {
    "iso:country":"GB",
    "sg:address":"Po Box 22",
    "sg:city":"Rotherham",
    "sg:classifiers":[
        {
            "category":"Manufacturing",
            "subcategory":"Metals",
            "type":"Manufacturing & Wholesale Goods"
        },
        {
            "category":"Professional",
            "subcategory":"Engineering",
            "type":"Services"
        }
    ],
    "sg:phone":"+44 1709 388888",
    "sg:postcode":"S60 1AD",
    "sg:province":"South Yorkshire",
    "sg:tags":[
        "steel",
        "mnfrs"
    ],
    "wof:name":"Firth Rixson Rings Ltd.",
    "wof:placetype":"venue"
},
  "geometry": {"coordinates":[-1.354243,53.429874],"type":"Point"}
}