{
  "type": "Feature",
  "properties": {
    "addr:full":"Unit J5, Middlesex Business, Centre, Bridge Road, Southall Greater London UB2 4AB",
    "addr:housenumber":"unit j5",
    "addr:postcode":"ub2 4ab",
    "addr:street":"Middlesex Business Centre Bridge Road",
    "iso:country":"GB",
    "sg:address":"Unit J5, Middlesex Business, Centre, Bridge Road,",
    "sg:city":"Southall",
    "sg:classifiers":[
        {
            "category":"Home & Garden",
            "subcategory":"Home Furnishings",
            "type":"Retail Goods"
        }
    ],
    "sg:phone":"+44 20 8843 2233",
    "sg:postcode":"UB2 4AB",
    "sg:province":"Greater London",
    "sg:tags":[
        "household",
        "furniture"
    ],
    "wof:name":"Camel (UK) Limited",
    "wof:placetype":"venue"
},
  "geometry": {"coordinates":[-0.3756990135,51.5039367676],"type":"Point"}
}