{
  "type": "Feature",
  "properties": {
    "addr:full":"Higher Quoit Animal Centre, Quoit St Columb Cornwall TR9 6JS",
    "addr:postcode":"tr9 6js",
    "addr:street":"St",
    "iso:country":"GB",
    "sg:address":"Higher Quoit Animal Centre, Quoit",
    "sg:city":"St Columb",
    "sg:classifiers":[
        {
            "category":"Organizations",
            "subcategory":"Non-profit Organization",
            "type":"Services"
        }
    ],
    "sg:phone":"+44 1637 881455",
    "sg:postcode":"TR9 6JS",
    "sg:province":"Cornwall",
    "sg:tags":[
        "organisation",
        "care",
        "animal",
        "welfare"
    ],
    "wof:name":"Rspca",
    "wof:placetype":"venue"
},
  "geometry": {"coordinates":[-4.936884,50.43256],"type":"Point"}
}