{
  "type": "Feature",
  "properties": {
    "addr:full":"Buckland House, 29 Dingwall Rd Croydon Surrey CR0 2NB",
    "addr:housenumber":"29",
    "addr:postcode":"cr0 2nb",
    "addr:street":"Dingwall Rd",
    "iso:country":"GB",
    "sg:address":"Buckland House, 29 Dingwall Rd",
    "sg:city":"Croydon",
    "sg:classifiers":[
        {
            "category":"Insurance",
            "subcategory":"Insurance Agent",
            "type":"Services"
        }
    ],
    "sg:phone":"+44 20 8686 1708",
    "sg:postcode":"CR0 2NB",
    "sg:province":"Surrey",
    "sg:tags":[
        "broker"
    ],
    "wof:name":"Grout & Judge",
    "wof:placetype":"venue"
},
  "geometry": {"coordinates":[-0.0953150019,51.3785743713],"type":"Point"}
}