{
  "type": "Feature",
  "properties": {
    "addr:full":"102 Fernbank Road Ascot Berkshire SL5 8JN",
    "addr:housenumber":"102",
    "addr:postcode":"sl5 8jn",
    "addr:street":"Fernbank Road",
    "iso:country":"GB",
    "sg:address":"102 Fernbank Road",
    "sg:city":"Ascot",
    "sg:classifiers":[
        {
            "category":"Bars & Pubs",
            "type":"Food & Drink"
        }
    ],
    "sg:phone":"+44 1344 882498",
    "sg:postcode":"SL5 8JN",
    "sg:province":"Berkshire",
    "sg:tags":[
        "pubs",
        "inn"
    ],
    "wof:name":"The Gold Cup",
    "wof:placetype":"venue"
},
  "geometry": {"coordinates":[-0.695295,51.41795],"type":"Point"}
}