{
  "type": "Feature",
  "properties": {
    "addr:full":"Poltair Road St Austell Cornwall PL25 4LR",
    "addr:postcode":"pl25 4lr",
    "addr:street":"Poltair Road",
    "iso:country":"GB",
    "sg:address":"Poltair Road",
    "sg:city":"St Austell",
    "sg:classifiers":[
        {
            "category":"Arena",
            "subcategory":"Sports Club",
            "type":"Entertainment"
        }
    ],
    "sg:phone":"+44 1726 69629",
    "sg:postcode":"PL25 4LR",
    "sg:province":"Cornwall",
    "wof:name":"St.Austell Rifle & Pistol Club",
    "wof:placetype":"venue"
},
  "geometry": {"coordinates":[-4.785211,50.342251],"type":"Point"}
}