{
  "type": "Feature",
  "properties": {
    "iso:country":"GB",
    "sg:address":"Butlers Green Road",
    "sg:city":"Haywards Heath",
    "sg:classifiers":[
        {
            "category":"Professional",
            "subcategory":"Computer Services",
            "type":"Services"
        }
    ],
    "sg:phone":"+44 1444 417286",
    "sg:postcode":"RH16 4BB",
    "sg:province":"East Sussex",
    "sg:tags":[
        "information"
    ],
    "wof:name":"Mid Downs Advocacy Service",
    "wof:placetype":"venue"
},
  "geometry": {"coordinates":[-0.113219,50.99955],"type":"Point"}
}