{
  "type": "Feature",
  "properties": {
    "addr:full":"Bannerigg Farm, Kendal Road Windermere Cumbria LA23 1JL",
    "addr:postcode":"la23 1jl",
    "addr:street":"Kendal Road",
    "iso:country":"GB",
    "sg:address":"Bannerigg Farm, Kendal Road",
    "sg:city":"Windermere",
    "sg:classifiers":[
        {
            "category":"Farming",
            "subcategory":"Farm",
            "type":"Manufacturing & Wholesale Goods"
        }
    ],
    "sg:postcode":"LA23 1JL",
    "sg:province":"Cumbria",
    "sg:tags":[
        "mixed",
        "crop"
    ],
    "wof:name":"F W Park",
    "wof:placetype":"venue"
},
  "geometry": {"coordinates":[-2.906404,54.379665],"type":"Point"}
}