{
  "type": "Feature",
  "properties": {
    "iso:country":"GB",
    "sg:address":"99 Brighton Road",
    "sg:city":"Surbiton",
    "sg:classifiers":[
        {
            "category":"Home & Garden",
            "subcategory":"Home Furnishings",
            "type":"Retail Goods"
        }
    ],
    "sg:phone":"+44 20 8390 7197",
    "sg:postcode":"KT6 5NF",
    "sg:province":"Surrey",
    "sg:tags":[
        "furnishers",
        "planner",
        "kitchen"
    ],
    "wof:name":"Kitchencraft of Surbiton",
    "wof:placetype":"venue"
},
  "geometry": {"coordinates":[-0.3123930097,51.3924331665],"type":"Point"}
}