{
  "type": "Feature",
  "properties": {
    "iso:country":"GB",
    "sg:address":"2 Lings Local Centre",
    "sg:city":"Northampton",
    "sg:classifiers":[
        {
            "category":"Shopping",
            "subcategory":"News",
            "type":"Retail Goods"
        },
        {
            "category":"Government",
            "subcategory":"Post Office",
            "type":"Public Place"
        }
    ],
    "sg:phone":"+44 1604 408849",
    "sg:postcode":"NN3 8NQ",
    "sg:province":"Northamptonshire",
    "sg:tags":[
        "newsagent"
    ],
    "wof:name":"Lumbertubs Post Office",
    "wof:placetype":"venue"
},
  "geometry": {"coordinates":[-0.83486,52.263618],"type":"Point"}
}