{
  "type": "Feature",
  "properties": {
    "addr:full":"141 Front Street Chester-le-street Durham DH3 3AU",
    "addr:housenumber":"141",
    "addr:postcode":"dh3 3au",
    "addr:street":"Front Street",
    "iso:country":"GB",
    "sg:address":"141 Front Street",
    "sg:city":"Chester-le-street",
    "sg:classifiers":[
        {
            "category":"Home & Garden",
            "subcategory":"Home Furnishings",
            "type":"Retail Goods"
        }
    ],
    "sg:phone":"+44 191 389 2791",
    "sg:postcode":"DH3 3AU",
    "sg:province":"Durham",
    "sg:tags":[
        "mantelpiece",
        "fireplace"
    ],
    "wof:name":"Marble Arts",
    "wof:placetype":"venue"
},
  "geometry": {"coordinates":[-1.5737309456,54.8538246155],"type":"Point"}
}