{
  "type": "Feature",
  "properties": {
    "addr:full":"26 Wroxham Road, Coltishall Norwich Norfolk NR12 7EA",
    "addr:housenumber":"26",
    "addr:postcode":"nr12 7ea",
    "addr:street":"Wroxham Road;Norwich",
    "iso:country":"GB",
    "sg:address":"26 Wroxham Road, Coltishall",
    "sg:city":"Norwich",
    "sg:classifiers":[
        {
            "category":"Bars & Pubs",
            "type":"Food & Drink"
        }
    ],
    "sg:phone":"+44 1603 737426",
    "sg:postcode":"NR12 7EA",
    "sg:province":"Norfolk",
    "sg:tags":[
        "pubs",
        "inn"
    ],
    "wof:name":"The Kings Head",
    "wof:placetype":"venue"
},
  "geometry": {"coordinates":[1.370607,52.728203],"type":"Point"}
}