{
  "type": "Feature",
  "properties": {
    "iso:country":"GB",
    "sg:address":"Llandeilo Road, Gorslas",
    "sg:city":"Llanelli",
    "sg:classifiers":[
        {
            "category":"Building & Trades",
            "subcategory":"Equipment Rental",
            "type":"Services"
        }
    ],
    "sg:phone":"+44 1269 851512",
    "sg:postcode":"SA14 7LW",
    "sg:province":"Carmarthenshire",
    "sg:tags":[
        "plant",
        "machinery"
    ],
    "wof:name":"G Winter Plant Hire",
    "wof:placetype":"venue"
},
  "geometry": {"coordinates":[-4.075134,51.804161],"type":"Point"}
}