{
  "type": "Feature",
  "properties": {
    "iso:country":"GB",
    "sg:address":"40 Coronation Rd",
    "sg:city":"Nottingham",
    "sg:classifiers":[
        {
            "category":"Building & Trades",
            "subcategory":"Plumbing",
            "type":"Services"
        }
    ],
    "sg:phone":"+44 115 963 2597",
    "sg:postcode":"NG15 7EJ",
    "sg:province":"Nottinghamshire",
    "sg:tags":[
        "heating"
    ],
    "wof:name":"Wighay Plumbing Co",
    "wof:placetype":"venue"
},
  "geometry": {"coordinates":[-1.2106679678,53.0448951721],"type":"Point"}
}