{
  "type": "Feature",
  "properties": {
    "addr:full":"58 Charlotte Road London Greater London EC2A 3QT",
    "addr:housenumber":"58",
    "addr:postcode":"ec2a 3qt",
    "addr:street":"Charlotte Road",
    "iso:country":"GB",
    "sg:address":"58 Charlotte Road",
    "sg:city":"London",
    "sg:classifiers":[
        {
            "category":"Professional",
            "type":"Services"
        }
    ],
    "sg:postcode":"EC2A 3QT",
    "sg:province":"Greater London",
    "sg:tags":[
        "exhibition"
    ],
    "wof:name":"Work",
    "wof:placetype":"venue"
},
  "geometry": {"coordinates":[-0.080982,51.525928],"type":"Point"}
}