{
  "type": "Feature",
  "properties": {
    "addr:full":"Bibbear Farm, Frithelstock Torrington Devon EX38 8LF",
    "addr:housenumber":"frithelstock",
    "addr:postcode":"ex38 8lf",
    "iso:country":"GB",
    "sg:address":"Bibbear Farm, Frithelstock",
    "sg:city":"Torrington",
    "sg:classifiers":[
        {
            "category":"Farming",
            "subcategory":"Livestock Farm",
            "type":"Manufacturing & Wholesale Goods"
        }
    ],
    "sg:phone":"+44 1805 601223",
    "sg:postcode":"EX38 8LF",
    "sg:province":"Devon",
    "sg:tags":[
        "others"
    ],
    "wof:name":"C J & C Ley",
    "wof:placetype":"venue"
},
  "geometry": {"coordinates":[-4.142255,50.953152],"type":"Point"}
}