{
  "type": "Feature",
  "properties": {
    "iso:country":"GB",
    "sg:address":"199 Abbey Street",
    "sg:city":"Derby",
    "sg:classifiers":[
        {
            "category":"Shopping",
            "subcategory":"Bicycles & Sporting Goods",
            "type":"Retail Goods"
        },
        {
            "category":"Autos & Motor Vehicles",
            "subcategory":"Auto Supplies",
            "type":"Retail Goods"
        }
    ],
    "sg:phone":"+44 1332 348630",
    "sg:postcode":"DE22 3ST",
    "sg:province":"Derbyshire",
    "sg:tags":[
        "eqpt",
        "equipment",
        "towing",
        "fishing",
        "angling",
        "trailer"
    ],
    "wof:name":"ABBEY TRAILERS LTD",
    "wof:placetype":"venue"
},
  "geometry": {"coordinates":[-1.483079,52.917248],"type":"Point"}
}