{
  "type": "Feature",
  "properties": {
    "iso:country":"GB",
    "sg:address":"21 Lowther Road",
    "sg:city":"Fleetwood",
    "sg:classifiers":[
        {
            "category":"Professional",
            "subcategory":"Art Services",
            "type":"Services"
        },
        {
            "category":"Building & Trades",
            "subcategory":"Construction",
            "type":"Services"
        },
        {
            "category":"Manufacturing",
            "subcategory":"Paper Products",
            "type":"Manufacturing & Wholesale Goods"
        }
    ],
    "sg:phone":"+44 1253 876342",
    "sg:postcode":"FY7 7AS",
    "sg:province":"Lancashire",
    "sg:tags":[
        "cardboard",
        "decorator",
        "painter"
    ],
    "wof:name":"J Grundy & Son",
    "wof:placetype":"venue"
},
  "geometry": {"coordinates":[-3.0228760242,53.9211196899],"type":"Point"}
}