{
  "type": "Feature",
  "properties": {
    "addr:full":"Unit 4 Campbell Street Preston Lancashire PR1 5LX",
    "addr:housenumber":"unit 4",
    "addr:postcode":"pr1 5lx",
    "addr:street":"Campbell Street",
    "iso:country":"GB",
    "sg:address":"Unit 4 Campbell Street",
    "sg:city":"Preston",
    "sg:classifiers":[
        {
            "category":"Shopping",
            "subcategory":"Clothing, Apparel, & Fashions",
            "type":"Retail Goods"
        }
    ],
    "sg:phone":"+44 1772 653523",
    "sg:postcode":"PR1 5LX",
    "sg:province":"Lancashire",
    "sg:tags":[
        "clothing",
        "fabric"
    ],
    "wof:name":"Patrol Jeanswear Ltd.",
    "wof:placetype":"venue"
},
  "geometry": {"coordinates":[-2.685764,53.762505],"type":"Point"}
}