{
  "type": "Feature",
  "properties": {
    "iso:country":"GB",
    "sg:address":"17 Woodview Rise",
    "sg:city":"Rochester",
    "sg:classifiers":[
        {
            "category":"Professional",
            "subcategory":"Management & Consulting",
            "type":"Services"
        },
        {
            "category":"Professional",
            "subcategory":"Computer Services",
            "type":"Services"
        }
    ],
    "sg:postcode":"ME2 3RP",
    "sg:province":"Kent",
    "sg:tags":[
        "consultant",
        "business"
    ],
    "wof:name":"Dallas Consultants Ltd.",
    "wof:placetype":"venue"
},
  "geometry": {"coordinates":[0.483856,51.404079],"type":"Point"}
}