{
  "type": "Feature",
  "properties": {
    "addr:full":"11 Fernlea Road Mitcham Greater London CR4 2HF",
    "addr:housenumber":"11",
    "addr:postcode":"cr4 2hf",
    "addr:street":"Fernlea Road",
    "iso:country":"GB",
    "sg:address":"11 Fernlea Road",
    "sg:city":"Mitcham",
    "sg:classifiers":[
        {
            "category":"Professional",
            "subcategory":"Secretarial Services",
            "type":"Services"
        }
    ],
    "sg:phone":"+44 20 8648 8947",
    "sg:postcode":"CR4 2HF",
    "sg:province":"Greater London",
    "wof:name":"Abracadabra Typing",
    "wof:placetype":"venue"
},
  "geometry": {"coordinates":[-0.1558459997,51.4106292725],"type":"Point"}
}