{
  "type": "Feature",
  "properties": {
    "addr:full":"St Nicholas Close, Rattlesden Bury St Edmunds Suffolk IP30 0RL",
    "addr:postcode":"ip30 0rl",
    "addr:street":"St Nicholas Close",
    "iso:country":"GB",
    "sg:address":"St Nicholas Close, Rattlesden",
    "sg:city":"Bury St Edmunds",
    "sg:classifiers":[
        {
            "category":"Government",
            "subcategory":"Post Office",
            "type":"Public Place"
        }
    ],
    "sg:phone":"+44 1449 736197",
    "sg:postcode":"IP30 0RL",
    "sg:province":"Suffolk",
    "wof:name":"Rattlesden Sub Post Office",
    "wof:placetype":"venue"
},
  "geometry": {"coordinates":[0.8909559846,52.1924209595],"type":"Point"}
}