{
  "type": "Feature",
  "properties": {
    "addr:full":"200 Wells Road Bristol City of Bristol BS4 2AX",
    "addr:housenumber":"200",
    "addr:postcode":"bs4 2ax",
    "addr:street":"Wells Road",
    "iso:country":"GB",
    "sg:address":"200 Wells Road",
    "sg:city":"Bristol",
    "sg:classifiers":[
        {
            "category":"Food & Beverages",
            "subcategory":"Meat & Fish",
            "type":"Retail Goods"
        }
    ],
    "sg:phone":"+44 117 977 6973",
    "sg:postcode":"BS4 2AX",
    "sg:province":"City of Bristol",
    "sg:tags":[
        "chip"
    ],
    "wof:name":"Wangs Fish Bar",
    "wof:placetype":"venue"
},
  "geometry": {"coordinates":[-2.572369,51.438751],"type":"Point"}
}