{
  "type": "Feature",
  "properties": {
    "addr:full":"45 Boodle Street Ashton-under-lyne Greater Manchester OL6 8NF",
    "addr:housenumber":"45",
    "addr:postcode":"ol6 8nf",
    "addr:street":"Boodle Street",
    "iso:country":"GB",
    "sg:address":"45 Boodle Street",
    "sg:city":"Ashton-under-lyne",
    "sg:classifiers":[
        {
            "category":"Retail",
            "subcategory":"Auto Repair",
            "type":"Services"
        }
    ],
    "sg:phone":"+44 161 343 2487",
    "sg:postcode":"OL6 8NF",
    "sg:province":"Greater Manchester",
    "sg:tags":[
        "modification",
        "garage"
    ],
    "wof:name":"Thameside Volkswagen Aldi",
    "wof:placetype":"venue"
},
  "geometry": {"coordinates":[-2.095635,53.492325],"type":"Point"}
}