{
  "type": "Feature",
  "properties": {
    "iso:country":"GB",
    "sg:address":"Account Direct Limited, Elsinore House, Buckingham Street",
    "sg:city":"Aylesbury",
    "sg:classifiers":[
        {
            "category":"Professional",
            "subcategory":"Management & Consulting",
            "type":"Services"
        }
    ],
    "sg:postcode":"HP20 2NQ",
    "sg:province":"Buckinghamshire",
    "sg:tags":[
        "consultant",
        "business"
    ],
    "wof:name":"Four Lakes Consulting Ltd",
    "wof:placetype":"venue"
},
  "geometry": {"coordinates":[-0.815438,51.819672],"type":"Point"}
}