{
  "type": "Feature",
  "properties": {
    "addr:full":"53 Red Leasowes Road Halesowen West Midlands B63 4SE",
    "addr:housenumber":"53",
    "addr:postcode":"b63 4se",
    "addr:street":"Red Leasowes Road",
    "iso:country":"GB",
    "sg:address":"53 Red Leasowes Road",
    "sg:city":"Halesowen",
    "sg:classifiers":[
        {
            "category":"Retail",
            "subcategory":"Repair Shop",
            "type":"Services"
        }
    ],
    "sg:phone":"+44 121 550 0019",
    "sg:postcode":"B63 4SE",
    "sg:province":"West Midlands",
    "sg:tags":[
        "radio",
        "television",
        "video"
    ],
    "wof:name":"Vintage Radio Repairs",
    "wof:placetype":"venue"
},
  "geometry": {"coordinates":[-2.0579519272,52.4453544617],"type":"Point"}
}