{
  "type": "Feature",
  "properties": {
    "iso:country":"GB",
    "sg:address":"Sandymount, Merrow Lane",
    "sg:city":"Guildford",
    "sg:classifiers":[
        {
            "category":"Professional",
            "subcategory":"Computer Services",
            "type":"Services"
        }
    ],
    "sg:phone":"+44 1483 827371",
    "sg:postcode":"GU4 7LQ",
    "sg:province":"Surrey",
    "sg:tags":[
        "system",
        "software"
    ],
    "wof:name":"Kennedy Software Products",
    "wof:placetype":"venue"
},
  "geometry": {"coordinates":[-0.5363900065,51.265460968],"type":"Point"}
}