{
  "type": "Feature",
  "properties": {
    "iso:country":"GB",
    "sg:address":"11 Castle Street",
    "sg:city":"Aberdeen",
    "sg:classifiers":[
        {
            "category":"Shopping",
            "subcategory":"Crafts & Fabrics",
            "type":"Retail Goods"
        }
    ],
    "sg:postcode":"AB11 5BQ",
    "sg:province":"Aberdeen City",
    "sg:tags":[
        "material",
        "art"
    ],
    "wof:name":"The Artists Pad",
    "wof:placetype":"venue"
},
  "geometry": {"coordinates":[-2.086923,57.148697],"type":"Point"}
}