{
  "type": "Feature",
  "properties": {
    "addr:full":"Lee Samuel House, 2/23 Nealden St Brixton Greater London SW9 9RA",
    "addr:housenumber":"2 / 23",
    "addr:postcode":"sw9 9ra",
    "addr:street":"Nealden St",
    "iso:country":"GB",
    "sg:address":"Lee Samuel House, 2/23 Nealden St",
    "sg:city":"Brixton",
    "sg:classifiers":[
        {
            "category":"Health Services",
            "subcategory":"Nursing And Care Facility",
            "type":"Services"
        }
    ],
    "sg:phone":"+44 20 7738 3785",
    "sg:postcode":"SW9 9RA",
    "sg:province":"Greater London",
    "sg:tags":[
        "home"
    ],
    "wof:name":"Carib Housing Association Ltd",
    "wof:placetype":"venue"
},
  "geometry": {"coordinates":[-0.1210749969,51.4662322998],"type":"Point"}
}