{
  "type": "Feature",
  "properties": {
    "addr:full":"3 Station Street Cockermouth Cumbria CA13 9QW",
    "addr:housenumber":"3",
    "addr:postcode":"ca13 9qw",
    "addr:street":"Station Street",
    "iso:country":"GB",
    "sg:address":"3 Station Street",
    "sg:city":"Cockermouth",
    "sg:classifiers":[
        {
            "category":"Real Estate",
            "subcategory":"Real Estate Agent",
            "type":"Services"
        }
    ],
    "sg:phone":"+44 1900 825114",
    "sg:postcode":"CA13 9QW",
    "sg:province":"Cumbria",
    "wof:name":"Reeds Rains Ltd.",
    "wof:placetype":"venue"
},
  "geometry": {"coordinates":[-3.364231,54.663528],"type":"Point"}
}