{
  "type": "Feature",
  "properties": {
    "iso:country":"GB",
    "sg:address":"45 High Street North",
    "sg:city":"Dunstable",
    "sg:classifiers":[
        {
            "category":"Professional",
            "subcategory":"Art Services",
            "type":"Services"
        }
    ],
    "sg:phone":"+44 1582 475828",
    "sg:postcode":"LU6 1JE",
    "sg:province":"Bedfordshire",
    "sg:tags":[
        "picture",
        "framing"
    ],
    "wof:name":"Allframe Ltd.",
    "wof:placetype":"venue"
},
  "geometry": {"coordinates":[-0.5229420066,51.8872756958],"type":"Point"}
}