{
  "type": "Feature",
  "properties": {
    "addr:full":"54 Lowther Street Carlisle Cumbria CA3 8DP",
    "addr:housenumber":"54",
    "addr:postcode":"ca3 8dp",
    "addr:street":"Lowther Street",
    "iso:country":"GB",
    "sg:address":"54 Lowther Street",
    "sg:city":"Carlisle",
    "sg:classifiers":[
        {
            "category":"Insurance",
            "subcategory":"Insurance Agent",
            "type":"Services"
        }
    ],
    "sg:phone":"+44 1228 549430",
    "sg:postcode":"CA3 8DP",
    "sg:province":"Cumbria",
    "sg:tags":[
        "broker"
    ],
    "wof:name":"Beacon Insurance Brokers Ltd.",
    "wof:placetype":"venue"
},
  "geometry": {"coordinates":[-2.9335160255,54.894947052],"type":"Point"}
}