{
  "type": "Feature",
  "properties": {
    "iso:country":"GB",
    "sg:address":"53 High Street",
    "sg:city":"Stourport-on-severn",
    "sg:classifiers":[
        {
            "category":"Retail",
            "subcategory":"Photofinishing",
            "type":"Services"
        }
    ],
    "sg:phone":"+44 1299 827813",
    "sg:postcode":"DY13 8BX",
    "sg:province":"Worcestershire",
    "sg:tags":[
        "processing",
        "photographic",
        "processor"
    ],
    "wof:name":"Stourport Photo Centre",
    "wof:placetype":"venue"
},
  "geometry": {"coordinates":[-2.278652,52.340439],"type":"Point"}
}