{
  "type": "Feature",
  "properties": {
    "addr:full":"West Point Shopping Centre, By-pass Road Nottingham Nottinghamshire NG9 6NX",
    "addr:postcode":"ng9 6nx",
    "addr:street":"Shopping Centre By-Pass Road",
    "iso:country":"GB",
    "sg:address":"West Point Shopping Centre, By-pass Road",
    "sg:city":"Nottingham",
    "sg:classifiers":[
        {
            "category":"Cinema",
            "subcategory":"Movie Rental",
            "type":"Entertainment"
        }
    ],
    "sg:phone":"+44 115 946 8268",
    "sg:postcode":"NG9 6NX",
    "sg:province":"Nottinghamshire",
    "sg:tags":[
        "video",
        "library"
    ],
    "wof:name":"Hollywood Movie Store",
    "wof:placetype":"venue"
},
  "geometry": {"coordinates":[-1.23967,52.908298],"type":"Point"}
}