{
  "type": "Feature",
  "properties": {
    "addr:full":"Unit 3a, Red Hills Est, Redhills Penrith Cumbria CA11 0DT",
    "addr:housenumber":"unit 3a",
    "addr:postcode":"ca11 0dt",
    "addr:street":"Hills Est Redhills",
    "iso:country":"GB",
    "sg:address":"Unit 3a, Red Hills Est, Redhills",
    "sg:city":"Penrith",
    "sg:classifiers":[
        {
            "category":"Wholesale",
            "subcategory":"Non-durable Goods",
            "type":"Manufacturing & Wholesale Goods"
        }
    ],
    "sg:phone":"+44 1768 864864",
    "sg:postcode":"CA11 0DT",
    "sg:province":"Cumbria",
    "sg:tags":[
        "animal",
        "by-product"
    ],
    "wof:name":"Williams Foods Contracts Ltd",
    "wof:placetype":"venue"
},
  "geometry": {"coordinates":[-2.7698469162,54.6497383118],"type":"Point"}
}