{
  "type": "Feature",
  "properties": {
    "iso:country":"GB",
    "sg:address":"35 Swan Rd, Kingsholm",
    "sg:city":"Gloucester",
    "sg:classifiers":[
        {
            "category":"Building & Trades",
            "subcategory":"Construction",
            "type":"Services"
        }
    ],
    "sg:phone":"+44 1452 545958",
    "sg:postcode":"GL1 3BJ",
    "sg:province":"Gloucestershire",
    "sg:tags":[
        "builder"
    ],
    "wof:name":"Top Class Property Maintenance",
    "wof:placetype":"venue"
},
  "geometry": {"coordinates":[-2.240734,51.871498],"type":"Point"}
}