{
  "type": "Feature",
  "properties": {
    "addr:full":"Moorside Lane, Addingham Ilkley North Yorkshire LS29 9JX",
    "addr:postcode":"ls29 9jx",
    "addr:street":"Moorside Lane",
    "iso:country":"GB",
    "sg:address":"Moorside Lane, Addingham",
    "sg:city":"Ilkley",
    "sg:classifiers":[
        {
            "category":"Farming",
            "subcategory":"Farm",
            "type":"Manufacturing & Wholesale Goods"
        }
    ],
    "sg:phone":"+44 1943 830370",
    "sg:postcode":"LS29 9JX",
    "sg:province":"North Yorkshire",
    "sg:tags":[
        "mixed",
        "crop"
    ],
    "wof:name":"J S Flesher & Son",
    "wof:placetype":"venue"
},
  "geometry": {"coordinates":[-1.891517,53.926861],"type":"Point"}
}