{
  "type": "Feature",
  "properties": {
    "addr:full":"1348 London Road Leigh-on-sea Essex SS9 2UH",
    "addr:housenumber":"1348",
    "addr:postcode":"ss9 2uh",
    "addr:street":"London Road",
    "iso:country":"GB",
    "sg:address":"1348 London Road",
    "sg:city":"Leigh-on-sea",
    "sg:classifiers":[
        {
            "category":"Real Estate",
            "subcategory":"Developer",
            "type":"Services"
        }
    ],
    "sg:postcode":"SS9 2UH",
    "sg:province":"Essex",
    "sg:tags":[
        "property"
    ],
    "wof:name":"Town & Country Developments (Essex) Ltd.",
    "wof:placetype":"venue"
},
  "geometry": {"coordinates":[0.638767004,51.5477218628],"type":"Point"}
}