{
  "type": "Feature",
  "properties": {
    "iso:country":"GB",
    "sg:address":"25 Main Street, Lyddington",
    "sg:city":"Oakham",
    "sg:classifiers":[
        {
            "category":"Real Estate",
            "subcategory":"Surveying",
            "type":"Services"
        }
    ],
    "sg:phone":"+44 1572 823825",
    "sg:postcode":"LE15 9LR",
    "sg:province":"Leicestershire",
    "sg:tags":[
        "surveyor",
        "valuer"
    ],
    "wof:name":"Hives Associates Ltd",
    "wof:placetype":"venue"
},
  "geometry": {"coordinates":[-0.794505,52.602764],"type":"Point"}
}