{
  "type": "Feature",
  "properties": {
    "iso:country":"GB",
    "sg:address":"No 1 Kingfisher Parade, East Wittering",
    "sg:city":"Chichester",
    "sg:classifiers":[
        {
            "category":"Professional",
            "subcategory":"Lawyer & Legal Services",
            "type":"Services"
        }
    ],
    "sg:phone":"+44 1243 671782",
    "sg:postcode":"PO20 8BJ",
    "sg:province":"West Sussex",
    "sg:tags":[
        "solicitor"
    ],
    "wof:name":"Paul Hills & Co",
    "wof:placetype":"venue"
},
  "geometry": {"coordinates":[-0.871509,50.769089],"type":"Point"}
}