{
  "type": "Feature",
  "properties": {
    "iso:country":"GB",
    "sg:address":"2343 Glasgow Rd",
    "sg:city":"Glasgow",
    "sg:classifiers":[
        {
            "category":"Food & Beverages",
            "subcategory":"Meat & Fish",
            "type":"Retail Goods"
        }
    ],
    "sg:phone":"+44 1698 825291",
    "sg:postcode":"G72 7DW",
    "sg:province":"South Lanarkshire",
    "sg:tags":[
        "butcher"
    ],
    "wof:name":"Co-Operative Wholesale Society (Scotland",
    "wof:placetype":"venue"
},
  "geometry": {"coordinates":[-4.181166172,55.8232917786],"type":"Point"}
}