{
  "type": "Feature",
  "properties": {
    "iso:country":"GB",
    "sg:address":"3 St James Close, Clanfield",
    "sg:city":"Waterlooville",
    "sg:classifiers":[
        {
            "category":"Professional",
            "subcategory":"Management & Consulting",
            "type":"Services"
        }
    ],
    "sg:postcode":"PO8 0JY",
    "sg:province":"Hampshire",
    "sg:tags":[
        "consultant",
        "business"
    ],
    "wof:name":"Butser Ancient Farm Consultancy Ltd.",
    "wof:placetype":"venue"
},
  "geometry": {"coordinates":[-0.998621,50.938179],"type":"Point"}
}