{
  "type": "Feature",
  "properties": {
    "addr:full":"Cwm Bedw, Rhydlewis Llandysul Carmarthenshire SA44 5PR",
    "addr:postcode":"sa44 5pr",
    "iso:country":"GB",
    "sg:address":"Cwm Bedw, Rhydlewis",
    "sg:city":"Llandysul",
    "sg:classifiers":[
        {
            "category":"Building & Trades",
            "subcategory":"Construction",
            "type":"Services"
        }
    ],
    "sg:phone":"+44 1239 851844",
    "sg:postcode":"SA44 5PR",
    "sg:province":"Carmarthenshire",
    "sg:tags":[
        "joiner",
        "carpenter"
    ],
    "wof:name":"S Arden",
    "wof:placetype":"venue"
},
  "geometry": {"coordinates":[-4.4141321182,52.0991439819],"type":"Point"}
}