{
  "type": "Feature",
  "properties": {
    "addr:full":"55-57 Streatham High Road London Greater London SW16 1PJ",
    "addr:housenumber":"55-57",
    "addr:postcode":"sw16 1pj",
    "addr:street":"Streatham High Road",
    "iso:country":"GB",
    "sg:address":"55-57 Streatham High Road",
    "sg:city":"London",
    "sg:classifiers":[
        {
            "category":"Banks & Credit Unions",
            "subcategory":"Bank",
            "type":"Services"
        }
    ],
    "sg:phone":"+44 845 765 4321",
    "sg:postcode":"SW16 1PJ",
    "sg:province":"Greater London",
    "wof:name":"Abbey National Plc",
    "wof:placetype":"venue"
},
  "geometry": {"coordinates":[-0.1291549951,51.4319763184],"type":"Point"}
}