{
  "type": "Feature",
  "properties": {
    "iso:country":"GB",
    "sg:address":"Copse Rd",
    "sg:city":"Fleetwood",
    "sg:classifiers":[
        {
            "category":"Autos & Motor Vehicles",
            "subcategory":"Auto Supplies",
            "type":"Retail Goods"
        }
    ],
    "sg:phone":"+44 1253 777715",
    "sg:postcode":"FY7 6RP",
    "sg:province":"Lancashire",
    "sg:tags":[
        "towing",
        "eqpt",
        "trailer"
    ],
    "wof:name":"Blackpool Trucking Co Ltd",
    "wof:placetype":"venue"
},
  "geometry": {"coordinates":[-3.019939,53.916897],"type":"Point"}
}