{
  "type": "Feature",
  "properties": {
    "addr:full":"93 High St Nairn Highland IV12 4DB",
    "addr:housenumber":"93",
    "addr:postcode":"iv12 4db",
    "addr:street":"High St",
    "iso:country":"GB",
    "sg:address":"93 High St",
    "sg:city":"Nairn",
    "sg:classifiers":[
        {
            "category":"Personal",
            "type":"Services"
        }
    ],
    "sg:phone":"+44 1667 451154",
    "sg:postcode":"IV12 4DB",
    "sg:province":"Highland",
    "sg:tags":[
        "dressmaker"
    ],
    "wof:name":"Fitz2",
    "wof:placetype":"venue"
},
  "geometry": {"coordinates":[-3.8667709827,57.5856246948],"type":"Point"}
}