{
  "type": "Feature",
  "properties": {
    "iso:country":"GB",
    "sg:address":"P O Box 5, Spondon",
    "sg:city":"Derby",
    "sg:classifiers":[
        {
            "category":"Building & Trades",
            "subcategory":"Equipment Rental",
            "type":"Services"
        }
    ],
    "sg:phone":"+44 1332 668576",
    "sg:postcode":"DE21 7BP",
    "sg:province":"Derbyshire",
    "sg:tags":[
        "drain",
        "clearance"
    ],
    "wof:name":"Dennis Brown",
    "wof:placetype":"venue"
},
  "geometry": {"coordinates":[-1.38138,52.906448],"type":"Point"}
}