{
  "type": "Feature",
  "properties": {
    "addr:full":"50 Sheriffs Highway Gateshead Tyne and Wear NE9 5UE",
    "addr:housenumber":"50",
    "addr:postcode":"ne9 5ue",
    "addr:street":"Sheriffs Highway",
    "iso:country":"GB",
    "sg:address":"50 Sheriffs Highway",
    "sg:city":"Gateshead",
    "sg:classifiers":[
        {
            "category":"Food & Beverages",
            "subcategory":"Fruits & Vegetables",
            "type":"Retail Goods"
        }
    ],
    "sg:postcode":"NE9 5UE",
    "sg:province":"Tyne and Wear",
    "sg:tags":[
        "greengrocer"
    ],
    "wof:name":"Posthewaite,Margaret,",
    "wof:placetype":"venue"
},
  "geometry": {"coordinates":[-1.5889899731,54.9417800903],"type":"Point"}
}