{
  "type": "Feature",
  "properties": {
    "iso:country":"GB",
    "sg:address":"68 Otley Rd",
    "sg:city":"Leeds",
    "sg:classifiers":[
        {
            "category":"Bars & Pubs",
            "type":"Food & Drink"
        }
    ],
    "sg:phone":"+44 113 275 5035",
    "sg:postcode":"LS6 4BA",
    "sg:province":"West Yorkshire",
    "sg:tags":[
        "pubs",
        "inn"
    ],
    "wof:name":"O'Hagans New Inn",
    "wof:placetype":"venue"
},
  "geometry": {"coordinates":[-1.581794,53.826538],"type":"Point"}
}