{
  "type": "Feature",
  "properties": {
    "addr:full":"56 Albert Rd, South Woodford London Greater London E18 1LE",
    "addr:housenumber":"56",
    "addr:postcode":"e18 1le",
    "addr:street":"Albert Rd",
    "iso:country":"GB",
    "sg:address":"56 Albert Rd, South Woodford",
    "sg:city":"London",
    "sg:classifiers":[
        {
            "category":"Professional",
            "subcategory":"Detective & Security Services",
            "type":"Services"
        }
    ],
    "sg:phone":"+44 20 8989 5459",
    "sg:postcode":"E18 1LE",
    "sg:province":"Greater London",
    "sg:tags":[
        "car"
    ],
    "wof:name":"Cartech Sound & Security Ltd",
    "wof:placetype":"venue"
},
  "geometry": {"coordinates":[0.0339969993,51.5910491943],"type":"Point"}
}