{
  "type": "Feature",
  "properties": {
    "addr:full":"Unit C, Ripon Way Harrogate North Yorkshire HG1 2AU",
    "addr:housenumber":"unit c",
    "addr:postcode":"hg1 2au",
    "addr:street":"Ripon Way",
    "iso:country":"GB",
    "sg:address":"Unit C, Ripon Way",
    "sg:city":"Harrogate",
    "sg:classifiers":[
        {
            "category":"Wholesale",
            "subcategory":"Fruits & Vegetables",
            "type":"Manufacturing & Wholesale Goods"
        }
    ],
    "sg:postcode":"HG1 2AU",
    "sg:province":"North Yorkshire",
    "wof:name":"IMPERIAL FRUITERERS",
    "wof:placetype":"venue"
},
  "geometry": {"coordinates":[-1.544524,53.99469],"type":"Point"}
}