{
  "type": "Feature",
  "properties": {
    "addr:full":"32 Felin Fach, Whitchurch Cardiff Cardiff CF14 1NZ",
    "addr:housenumber":"32",
    "addr:postcode":"cf14 1nz",
    "addr:street":"Felin",
    "iso:country":"GB",
    "sg:address":"32 Felin Fach, Whitchurch",
    "sg:city":"Cardiff",
    "sg:classifiers":[
        {
            "category":"Banks & Credit Unions",
            "subcategory":"Financial Services",
            "type":"Services"
        }
    ],
    "sg:phone":"+44 29 2061 1038",
    "sg:postcode":"CF14 1NZ",
    "sg:province":"Cardiff",
    "sg:tags":[
        "consultant"
    ],
    "wof:name":"Guardsman Finance",
    "wof:placetype":"venue"
},
  "geometry": {"coordinates":[-3.217967,51.507011],"type":"Point"}
}