{
  "type": "Feature",
  "properties": {
    "iso:country":"GB",
    "sg:address":"63 Effra Rd",
    "sg:city":"Brixton",
    "sg:classifiers":[
        {
            "category":"Place Of Worship",
            "type":"Public Place"
        }
    ],
    "sg:phone":"+44 20 8852 8897",
    "sg:postcode":"SW2 1BZ",
    "sg:province":"Greater London",
    "wof:name":"Living Waters Apostolic Bibleway Church",
    "wof:placetype":"venue"
},
  "geometry": {"coordinates":[-0.117424,51.458584],"type":"Point"}
}