{
  "type": "Feature",
  "properties": {
    "addr:full":"86 Commercial Street, Rothwell Leeds West Yorkshire LS26 0AX",
    "addr:housenumber":"86",
    "addr:postcode":"ls26 0ax",
    "addr:street":"Commercial Street",
    "iso:country":"GB",
    "sg:address":"86 Commercial Street, Rothwell",
    "sg:city":"Leeds",
    "sg:classifiers":[
        {
            "category":"Community Center",
            "subcategory":"Social",
            "type":"Public Place"
        }
    ],
    "sg:phone":"+44 113 282 7444",
    "sg:postcode":"LS26 0AX",
    "sg:province":"West Yorkshire",
    "sg:tags":[
        "frozen",
        "food",
        "freezer",
        "centre"
    ],
    "wof:name":"Jack Fulton",
    "wof:placetype":"venue"
},
  "geometry": {"coordinates":[-1.478678,53.748596],"type":"Point"}
}