{
  "type": "Feature",
  "properties": {
    "iso:country":"GB",
    "sg:address":"14 Auster Rd",
    "sg:city":"York",
    "sg:classifiers":[
        {
            "category":"Retail",
            "subcategory":"Auto Repair",
            "type":"Services"
        }
    ],
    "sg:phone":"+44 1904 691311",
    "sg:postcode":"YO3 4XA",
    "sg:province":"East Riding of Yorkshire",
    "sg:tags":[
        "modification",
        "garage"
    ],
    "wof:name":"Mini Car Centre",
    "wof:placetype":"venue"
},
  "geometry": {"coordinates":[-1.091982,53.988998],"type":"Point"}
}