{
  "type": "Feature",
  "properties": {
    "iso:country":"GB",
    "sg:address":"Crest Ho, Kings Rd",
    "sg:city":"Wolverhampton",
    "sg:classifiers":[
        {
            "category":"Building & Trades",
            "subcategory":"Construction",
            "type":"Services"
        }
    ],
    "sg:phone":"+44 1902 790661",
    "sg:postcode":"WV10 7DU",
    "sg:province":"Staffordshire",
    "sg:tags":[
        "window",
        "replacement"
    ],
    "wof:name":"County Windows",
    "wof:placetype":"venue"
},
  "geometry": {"coordinates":[-2.121669054,52.5886497498],"type":"Point"}
}