{
  "type": "Feature",
  "properties": {
    "iso:country":"GB",
    "sg:address":"1 Wharf Rd",
    "sg:city":"Newton Abbot",
    "sg:classifiers":[
        {
            "category":"Building & Trades",
            "subcategory":"Cleaning & Sanitation",
            "type":"Services"
        }
    ],
    "sg:phone":"+44 1626 202011",
    "sg:postcode":"TQ12 2DA",
    "sg:province":"Devon",
    "sg:tags":[
        "blast"
    ],
    "wof:name":"Alloys South West",
    "wof:placetype":"venue"
},
  "geometry": {"coordinates":[-3.6020278931,50.534122467],"type":"Point"}
}