{
  "type": "Feature",
  "properties": {
    "addr:full":"88 Punch Croft, New Ash Green Longfield Kent DA3 8HR",
    "addr:housenumber":"88",
    "addr:postcode":"da3 8hr",
    "addr:street":"Punch Croft",
    "iso:country":"GB",
    "sg:address":"88 Punch Croft, New Ash Green",
    "sg:city":"Longfield",
    "sg:classifiers":[
        {
            "category":"Real Estate",
            "subcategory":"Architect",
            "type":"Services"
        }
    ],
    "sg:phone":"+44 1474 872519",
    "sg:postcode":"DA3 8HR",
    "sg:province":"Kent",
    "wof:name":"Spanners Ltd.",
    "wof:placetype":"venue"
},
  "geometry": {"coordinates":[0.301591,51.36298],"type":"Point"}
}