{
  "type": "Feature",
  "properties": {
    "addr:full":"The Clock 12-13 Westgate Grantham Lincolnshire NG31 6LT",
    "addr:housenumber":"12-13",
    "addr:postcode":"ng31 6lt",
    "addr:street":"Westgate Grantham",
    "iso:country":"GB",
    "sg:address":"The Clock 12-13 Westgate",
    "sg:city":"Grantham",
    "sg:classifiers":[
        {
            "category":"Personal",
            "type":"Services"
        }
    ],
    "sg:phone":"+44 1476 563027",
    "sg:postcode":"NG31 6LT",
    "sg:province":"Lincolnshire",
    "sg:tags":[
        "tailor"
    ],
    "wof:name":"H H Cox (Tailors) Ltd.",
    "wof:placetype":"venue"
},
  "geometry": {"coordinates":[-0.6399289966,52.9095497131],"type":"Point"}
}