{
  "type": "Feature",
  "properties": {
    "addr:full":"36 Oakdale Ave Northwood Greater London HA6 1PG",
    "addr:housenumber":"36",
    "addr:postcode":"ha6 1pg",
    "addr:street":"Oakdale Ave",
    "iso:country":"GB",
    "sg:address":"36 Oakdale Ave",
    "sg:city":"Northwood",
    "sg:classifiers":[
        {
            "category":"Autos & Motor Vehicles",
            "subcategory":"Automobile Sales",
            "type":"Retail Goods"
        }
    ],
    "sg:postcode":"HA6 1PG",
    "sg:province":"Greater London",
    "sg:tags":[
        "car"
    ],
    "wof:name":"Kenton Car Centre",
    "wof:placetype":"venue"
},
  "geometry": {"coordinates":[-0.4088340104,51.6017532349],"type":"Point"}
}