{
  "type": "Feature",
  "properties": {
    "addr:full":"Box House, Dummer Basingstoke Hampshire RG25 2AJ",
    "addr:postcode":"rg25 2aj",
    "iso:country":"GB",
    "sg:address":"Box House, Dummer",
    "sg:city":"Basingstoke",
    "sg:classifiers":[
        {
            "category":"Professional",
            "subcategory":"Management & Consulting",
            "type":"Services"
        },
        {
            "category":"Organizations",
            "subcategory":"Community Association",
            "type":"Services"
        }
    ],
    "sg:phone":"+44 1256 397465",
    "sg:postcode":"RG25 2AJ",
    "sg:province":"Hampshire",
    "sg:tags":[
        "club",
        "consultant",
        "training",
        "social"
    ],
    "wof:name":"JEFFREY NORTHAM",
    "wof:placetype":"venue"
},
  "geometry": {"coordinates":[-1.160154,51.210186],"type":"Point"}
}