{
  "type": "Feature",
  "properties": {
    "iso:country":"GB",
    "sg:address":"9 Dudley Street",
    "sg:city":"Dudley",
    "sg:classifiers":[
        {
            "category":"Shopping",
            "subcategory":"Shoes",
            "type":"Retail Goods"
        }
    ],
    "sg:phone":"+44 1902 880301",
    "sg:postcode":"DY3 1SA",
    "sg:province":"Staffordshire",
    "sg:tags":[
        "shop"
    ],
    "wof:name":"R & S Brookes",
    "wof:placetype":"venue"
},
  "geometry": {"coordinates":[-2.121589,52.540997],"type":"Point"}
}