{
  "type": "Feature",
  "properties": {
    "addr:full":"North Street, Winchcombe Cheltenham Gloucestershire GL54 5LH",
    "addr:postcode":"gl54 5lh",
    "addr:street":"North Street",
    "iso:country":"GB",
    "sg:address":"North Street, Winchcombe",
    "sg:city":"Cheltenham",
    "sg:classifiers":[
        {
            "category":"Bars & Pubs",
            "type":"Food & Drink"
        }
    ],
    "sg:phone":"+44 1242 602256",
    "sg:postcode":"GL54 5LH",
    "sg:province":"Gloucestershire",
    "sg:tags":[
        "pubs",
        "inn"
    ],
    "wof:name":"The Sun Inn",
    "wof:placetype":"venue"
},
  "geometry": {"coordinates":[-1.964353,51.953388],"type":"Point"}
}