{
  "type": "Feature",
  "properties": {
    "addr:full":"66 Priory Grn, Highworth Swindon Gloucestershire SN6 7NU",
    "addr:housenumber":"66",
    "addr:postcode":"sn6 7nu",
    "addr:street":"Priory Grn",
    "iso:country":"GB",
    "sg:address":"66 Priory Grn, Highworth",
    "sg:city":"Swindon",
    "sg:classifiers":[
        {
            "category":"Education",
            "subcategory":"Special Training",
            "type":"Public Place"
        }
    ],
    "sg:postcode":"SN6 7NU",
    "sg:province":"Gloucestershire",
    "sg:tags":[
        "school",
        "language"
    ],
    "wof:name":"Marlborough Language Service",
    "wof:placetype":"venue"
},
  "geometry": {"coordinates":[-1.705033,51.632423],"type":"Point"}
}