{
  "type": "Feature",
  "properties": {
    "iso:country":"GB",
    "sg:address":"2 Kings Square",
    "sg:city":"York",
    "sg:classifiers":[
        {
            "category":"Cafe",
            "type":"Food & Drink"
        }
    ],
    "sg:phone":"+44 1904 630631",
    "sg:postcode":"YO1 8BH",
    "sg:province":"North Yorkshire",
    "sg:tags":[
        "tea",
        "snack",
        "bar",
        "room"
    ],
    "wof:name":"Harlequin Coffee & Tea House",
    "wof:placetype":"venue"
},
  "geometry": {"coordinates":[-1.080537,53.959705],"type":"Point"}
}