{
  "type": "Feature",
  "properties": {
    "addr:full":"84-86 Bromley Road, Catford London Greater London SE6 2UR",
    "addr:housenumber":"84-86",
    "addr:postcode":"se6 2ur",
    "addr:street":"Bromley Road",
    "iso:country":"GB",
    "sg:address":"84-86 Bromley Road, Catford",
    "sg:city":"London",
    "sg:classifiers":[
        {
            "category":"Health Services",
            "subcategory":"Nursing And Care Facility",
            "type":"Services"
        },
        {
            "category":"Professional",
            "subcategory":"Lawyer & Legal Services",
            "type":"Services"
        }
    ],
    "sg:phone":"+44 20 8748 9898",
    "sg:postcode":"SE6 2UR",
    "sg:province":"Greater London",
    "sg:tags":[
        "home",
        "solicitor"
    ],
    "wof:name":"U K Medi-Care Associates Ltd.",
    "wof:placetype":"venue"
},
  "geometry": {"coordinates":[-0.018704,51.437214],"type":"Point"}
}