{
  "type": "Feature",
  "properties": {
    "addr:full":"Northmuir Primary School, Roods Kirriemuir Angus DD8 4HA",
    "addr:postcode":"dd8 4ha",
    "addr:street":"Roods",
    "iso:country":"GB",
    "sg:address":"Northmuir Primary School, Roods",
    "sg:city":"Kirriemuir",
    "sg:classifiers":[
        {
            "category":"Organizations",
            "subcategory":"Membership Organization",
            "type":"Services"
        }
    ],
    "sg:phone":"+44 1575 575393",
    "sg:postcode":"DD8 4HA",
    "sg:province":"Angus",
    "sg:tags":[
        "club"
    ],
    "wof:name":"Kirriemuir Out of School Care Club",
    "wof:placetype":"venue"
},
  "geometry": {"coordinates":[-2.998349,56.675529],"type":"Point"}
}