{
  "type": "Feature",
  "properties": {
    "addr:full":"Hallmark Company Services Ltd, 140 Tabernacle St London Greater London EC2A 4SD",
    "addr:housenumber":"140",
    "addr:postcode":"ec2a 4sd",
    "addr:street":"Tabernacle St",
    "iso:country":"GB",
    "sg:address":"Hallmark Company Services Ltd, 140 Tabernacle St",
    "sg:city":"London",
    "sg:classifiers":[
        {
            "category":"Education",
            "subcategory":"School",
            "type":"Public Place"
        }
    ],
    "sg:postcode":"EC2A 4SD",
    "sg:province":"Greater London",
    "sg:tags":[
        "local",
        "authority"
    ],
    "wof:name":"London Languages (International) Ltd",
    "wof:placetype":"venue"
},
  "geometry": {"coordinates":[-0.08433,51.5255584717],"type":"Point"}
}