{
  "type": "Feature",
  "properties": {
    "addr:full":"1 Main Street, Hilton Derby Derbyshire DE65 5FF",
    "addr:housenumber":"1",
    "addr:postcode":"de65 5ff",
    "addr:street":"Main Street",
    "iso:country":"GB",
    "sg:address":"1 Main Street, Hilton",
    "sg:city":"Derby",
    "sg:classifiers":[
        {
            "category":"Bars & Pubs",
            "type":"Food & Drink"
        }
    ],
    "sg:phone":"+44 1283 733728",
    "sg:postcode":"DE65 5FF",
    "sg:province":"Derbyshire",
    "sg:tags":[
        "pubs",
        "inn"
    ],
    "wof:name":"The Old Talbot",
    "wof:placetype":"venue"
},
  "geometry": {"coordinates":[-1.635745,52.873116],"type":"Point"}
}