{
  "type": "Feature",
  "properties": {
    "addr:full":"Chatterton Lane, Stubbins, Ramsbottom Bury Lancashire BL0 0PQ",
    "addr:postcode":"bl0 0pq",
    "addr:street":"Chatterton Lane",
    "iso:country":"GB",
    "sg:address":"Chatterton Lane, Stubbins, Ramsbottom",
    "sg:city":"Bury",
    "sg:classifiers":[
        {
            "category":"Shopping",
            "subcategory":"Crafts & Fabrics",
            "type":"Retail Goods"
        }
    ],
    "sg:postcode":"BL0 0PQ",
    "sg:province":"Lancashire",
    "sg:tags":[
        "felt"
    ],
    "wof:name":"Tunstead Needlefelt Co. Ltd.",
    "wof:placetype":"venue"
},
  "geometry": {"coordinates":[-2.314271,53.661018],"type":"Point"}
}