{
  "type": "Feature",
  "properties": {
    "addr:full":"7 Vicarage Lane, Ruddington Nottingham Nottinghamshire NG11 6HB",
    "addr:housenumber":"7",
    "addr:postcode":"ng11 6hb",
    "addr:street":"Vicarage Lane",
    "iso:country":"GB",
    "sg:address":"7 Vicarage Lane, Ruddington",
    "sg:city":"Nottingham",
    "sg:classifiers":[
        {
            "category":"Manufacturing",
            "subcategory":"Building Materials",
            "type":"Manufacturing & Wholesale Goods"
        }
    ],
    "sg:postcode":"NG11 6HB",
    "sg:province":"Nottinghamshire",
    "sg:tags":[
        "stonemason"
    ],
    "wof:name":"G Dickman",
    "wof:placetype":"venue"
},
  "geometry": {"coordinates":[-1.1530549526,52.892074585],"type":"Point"}
}