{
  "type": "Feature",
  "properties": {
    "iso:country":"GB",
    "sg:address":"9 Elm Gro, Killingworth",
    "sg:city":"Newcastle-upon-tyne",
    "sg:classifiers":[
        {
            "category":"Professional",
            "subcategory":"Engineering",
            "type":"Services"
        }
    ],
    "sg:postcode":"NE12 7AN",
    "sg:province":"Tyne and Wear",
    "sg:tags":[
        "contractor",
        "electrical",
        "engineer"
    ],
    "wof:name":"B S Electrics",
    "wof:placetype":"venue"
},
  "geometry": {"coordinates":[-1.5586049557,55.0275802612],"type":"Point"}
}