{
  "type": "Feature",
  "properties": {
    "addr:full":"Eastwater Farm, Priddy Wells Somerset BA5 3AX",
    "addr:housenumber":"priddy;somerset",
    "addr:postcode":"ba5 3ax",
    "iso:country":"GB",
    "sg:address":"Eastwater Farm, Priddy",
    "sg:city":"Wells",
    "sg:classifiers":[
        {
            "category":"Farming",
            "subcategory":"Livestock Farm",
            "type":"Manufacturing & Wholesale Goods"
        },
        {
            "category":"Farming",
            "subcategory":"Farm",
            "type":"Manufacturing & Wholesale Goods"
        }
    ],
    "sg:phone":"+44 1749 676283",
    "sg:postcode":"BA5 3AX",
    "sg:province":"Somerset",
    "sg:tags":[
        "mixed",
        "crop",
        "others"
    ],
    "wof:name":"Ivor Robert Gibbons",
    "wof:placetype":"venue"
},
  "geometry": {"coordinates":[-2.679572,51.258656],"type":"Point"}
}