{
  "type": "Feature",
  "properties": {
    "addr:full":"10 Portland Business Centre, Manor House Lane, Datchet Slough Berkshire SL3 9BD",
    "addr:housenumber":"10",
    "addr:postcode":"sl3 9bd",
    "addr:street":"Portland Business Centre Manor House Lane",
    "iso:country":"GB",
    "sg:address":"10 Portland Business Centre, Manor House Lane, Datchet",
    "sg:city":"Slough",
    "sg:classifiers":[
        {
            "category":"Shopping",
            "subcategory":"Pets & Pet Supplies",
            "type":"Retail Goods"
        }
    ],
    "sg:postcode":"SL3 9BD",
    "sg:province":"Berkshire",
    "wof:name":"Pet Subjects Ltd.",
    "wof:placetype":"venue"
},
  "geometry": {"coordinates":[-0.5804880261,51.4840736389],"type":"Point"}
}