{
  "type": "Feature",
  "properties": {
    "iso:country":"GB",
    "sg:address":"Care Of Community Centre, Shackleton Rd",
    "sg:city":"Crawley",
    "sg:classifiers":[
        {
            "category":"Education",
            "subcategory":"Preschool",
            "type":"Public Place"
        }
    ],
    "sg:postcode":"RH10 5DF",
    "sg:province":"Surrey",
    "sg:tags":[
        "pre-school",
        "playgroups"
    ],
    "wof:name":"Tilgate Childrens Playgroup",
    "wof:placetype":"venue"
},
  "geometry": {"coordinates":[-0.184753,51.118458],"type":"Point"}
}