{
  "type": "Feature",
  "properties": {
    "iso:country":"GB",
    "sg:address":"Judges Close",
    "sg:city":"East Grinstead",
    "sg:classifiers":[
        {
            "category":"Shopping",
            "subcategory":"Pharmacy",
            "type":"Retail Goods"
        }
    ],
    "sg:phone":"+44 1342 301085",
    "sg:postcode":"RH19 3AA",
    "sg:province":"East Sussex",
    "sg:tags":[
        "medicine",
        "therapy"
    ],
    "wof:name":"Cornmill Complementary Health Centre",
    "wof:placetype":"venue"
},
  "geometry": {"coordinates":[-0.008319,51.123989],"type":"Point"}
}