{
  "type": "Feature",
  "properties": {
    "addr:full":"Unit 5 279 Bristol Rd Gloucester Gloucestershire GL2 5DF",
    "addr:housenumber":"unit 5 279",
    "addr:postcode":"gl2 5df",
    "addr:street":"Bristol Rd",
    "iso:country":"GB",
    "sg:address":"Unit 5 279 Bristol Rd",
    "sg:city":"Gloucester",
    "sg:classifiers":[
        {
            "category":"Retail",
            "subcategory":"Auto Repair",
            "type":"Services"
        }
    ],
    "sg:phone":"+44 1452 414448",
    "sg:postcode":"GL2 5DF",
    "sg:province":"Gloucestershire",
    "sg:tags":[
        "car",
        "servicing",
        "radiator"
    ],
    "wof:name":"Serck Marston",
    "wof:placetype":"venue"
},
  "geometry": {"coordinates":[-2.266816,51.84169],"type":"Point"}
}