{
  "type": "Feature",
  "properties": {
    "addr:full":"106 Woodthorpe Road Ashford Greater London TW15 3JY",
    "addr:housenumber":"106",
    "addr:postcode":"tw15 3jy",
    "addr:street":"Woodthorpe Road",
    "iso:country":"GB",
    "sg:address":"106 Woodthorpe Road",
    "sg:city":"Ashford",
    "sg:classifiers":[
        {
            "category":"Professional",
            "subcategory":"Management & Consulting",
            "type":"Services"
        }
    ],
    "sg:phone":"+44 1784 244110",
    "sg:postcode":"TW15 3JY",
    "sg:province":"Greater London",
    "sg:tags":[
        "music"
    ],
    "wof:name":"Kickstart Management Ltd.",
    "wof:placetype":"venue"
},
  "geometry": {"coordinates":[-0.477248013,51.4337615967],"type":"Point"}
}