{
  "type": "Feature",
  "properties": {
    "addr:full":"Unit 7b Brookefield Farm, Gravel Pit La, Prestbury Cheltenham Gloucestershire GL52 3NQ",
    "addr:housenumber":"unit 7b brookefield farm gravel",
    "addr:postcode":"cheltenham;gl52 3nq",
    "addr:street":"La Prestbury",
    "iso:country":"GB",
    "sg:address":"Unit 7b Brookefield Farm, Gravel Pit La, Prestbury",
    "sg:city":"Cheltenham",
    "sg:classifiers":[
        {
            "category":"Manufacturing",
            "subcategory":"Metals",
            "type":"Manufacturing & Wholesale Goods"
        }
    ],
    "sg:postcode":"GL52 3NQ",
    "sg:province":"Gloucestershire",
    "sg:tags":[
        "work",
        "sheet"
    ],
    "wof:name":"Fish,Ian,",
    "wof:placetype":"venue"
},
  "geometry": {"coordinates":[-2.035477,51.914501],"type":"Point"}
}