{
  "type": "Feature",
  "properties": {
    "addr:full":"16a Oxford Rd Dewsbury West Yorkshire WF13 4JT",
    "addr:housenumber":"16a",
    "addr:postcode":"wf13 4jt",
    "addr:street":"Oxford Rd",
    "iso:country":"GB",
    "sg:address":"16a Oxford Rd",
    "sg:city":"Dewsbury",
    "sg:classifiers":[
        {
            "category":"Place Of Worship",
            "type":"Public Place"
        }
    ],
    "sg:phone":"+44 1924 465491",
    "sg:postcode":"WF13 4JT",
    "sg:province":"West Yorkshire",
    "wof:name":"St Marks C of E Church",
    "wof:placetype":"venue"
},
  "geometry": {"coordinates":[-1.6441129446,53.6955184937],"type":"Point"}
}