{
  "type": "Feature",
  "properties": {
    "addr:full":"36 Rowlett Road Corby Northamptonshire NN17 2BW",
    "addr:housenumber":"36",
    "addr:postcode":"nn17 2bw",
    "addr:street":"Rowlett Road",
    "iso:country":"GB",
    "sg:address":"36 Rowlett Road",
    "sg:city":"Corby",
    "sg:classifiers":[
        {
            "category":"Shopping",
            "subcategory":"Computers & Home Electronics",
            "type":"Retail Goods"
        }
    ],
    "sg:postcode":"NN17 2BW",
    "sg:province":"Northamptonshire",
    "sg:tags":[
        "aerial",
        "television",
        "radio"
    ],
    "wof:name":"Xtra Visions",
    "wof:placetype":"venue"
},
  "geometry": {"coordinates":[-0.699806,52.501472],"type":"Point"}
}