{
  "type": "Feature",
  "properties": {
    "iso:country":"GB",
    "sg:address":"49 Carr St",
    "sg:city":"Ipswich",
    "sg:classifiers":[
        {
            "category":"Food & Beverages",
            "subcategory":"Liquor & Beverages",
            "type":"Retail Goods"
        }
    ],
    "sg:phone":"+44 1473 230429",
    "sg:postcode":"IP4 1HB",
    "sg:province":"Suffolk",
    "sg:tags":[
        "beer",
        "spirit",
        "wines"
    ],
    "wof:name":"Victoria Wine",
    "wof:placetype":"venue"
},
  "geometry": {"coordinates":[1.158379,52.057495],"type":"Point"}
}