{
  "type": "Feature",
  "properties": {
    "iso:country":"GB",
    "sg:address":"5 Cavendish Court, Newland Dale",
    "sg:city":"Chesterfield",
    "sg:classifiers":[
        {
            "category":"Personal",
            "subcategory":"Nail Salon",
            "type":"Services"
        }
    ],
    "sg:postcode":"S41 7QG",
    "sg:province":"Derbyshire",
    "sg:tags":[
        "technician"
    ],
    "wof:name":"Top Talons",
    "wof:placetype":"venue"
},
  "geometry": {"coordinates":[-1.435319,53.242882],"type":"Point"}
}