{
  "type": "Feature",
  "properties": {
    "addr:full":"46 Pencoed Road Burry Port Carmarthenshire SA16 0PW",
    "addr:housenumber":"46",
    "addr:postcode":"sa16 0pw",
    "addr:street":"Pencoed Road",
    "iso:country":"GB",
    "sg:address":"46 Pencoed Road",
    "sg:city":"Burry Port",
    "sg:classifiers":[
        {
            "category":"Building & Trades",
            "subcategory":"Construction",
            "type":"Services"
        }
    ],
    "sg:postcode":"SA16 0PW",
    "sg:province":"Carmarthenshire",
    "sg:tags":[
        "conversion",
        "loft"
    ],
    "wof:name":"Haven Loft Conversion",
    "wof:placetype":"venue"
},
  "geometry": {"coordinates":[-4.2468299866,51.6871376038],"type":"Point"}
}