{
  "type": "Feature",
  "properties": {
    "addr:full":"Sutton Court Farm, Sutton Lane Slough Berkshire SL3 8AR",
    "addr:postcode":"sl3 8ar",
    "addr:street":"Sutton;Sutton Lane",
    "iso:country":"GB",
    "sg:address":"Sutton Court Farm, Sutton Lane",
    "sg:city":"Slough",
    "sg:classifiers":[
        {
            "category":"Building & Trades",
            "subcategory":"Landscaping Services",
            "type":"Services"
        },
        {
            "category":"Shopping",
            "subcategory":"Pets & Pet Supplies",
            "type":"Retail Goods"
        }
    ],
    "sg:phone":"+44 1753 540777",
    "sg:postcode":"SL3 8AR",
    "sg:province":"Berkshire",
    "sg:tags":[
        "horticultural",
        "consultant"
    ],
    "wof:name":"Ashvale",
    "wof:placetype":"venue"
},
  "geometry": {"coordinates":[-0.5357630253,51.4898757935],"type":"Point"}
}