{
  "type": "Feature",
  "properties": {
    "addr:full":"Colwell Rd Leicester Leicestershire LE3 9AX",
    "addr:postcode":"le3 9ax",
    "addr:street":"Colwell Rd",
    "iso:country":"GB",
    "sg:address":"Colwell Rd",
    "sg:city":"Leicester",
    "sg:classifiers":[
        {
            "category":"Health Services",
            "subcategory":"Doctor",
            "type":"Services"
        }
    ],
    "sg:phone":"+44 116 262 1579",
    "sg:postcode":"LE3 9AX",
    "sg:province":"Leicestershire",
    "sg:tags":[
        "practitioners"
    ],
    "wof:name":"Taylor, M",
    "wof:placetype":"venue"
},
  "geometry": {"coordinates":[-1.1480289698,52.6472740173],"type":"Point"}
}