{
  "type": "Feature",
  "properties": {
    "addr:full":"1a Inglis Road Croydon Surrey CR0 6QW",
    "addr:housenumber":"1a",
    "addr:postcode":"cr0 6qw",
    "addr:street":"Inglis Road",
    "iso:country":"GB",
    "sg:address":"1a Inglis Road",
    "sg:city":"Croydon",
    "sg:classifiers":[
        {
            "category":"Utilities",
            "subcategory":"Refuse",
            "type":"Services"
        }
    ],
    "sg:postcode":"CR0 6QW",
    "sg:province":"Surrey",
    "sg:tags":[
        "skip",
        "hire"
    ],
    "wof:name":"Express Skips",
    "wof:placetype":"venue"
},
  "geometry": {"coordinates":[-0.075573,51.379387],"type":"Point"}
}