{
  "type": "Feature",
  "properties": {
    "iso:country":"GB",
    "sg:address":"Crown Avenue, Dukestown",
    "sg:city":"Tredegar",
    "sg:classifiers":[
        {
            "category":"Retail",
            "subcategory":"Auto Repair",
            "type":"Services"
        }
    ],
    "sg:phone":"+44 1495 717585",
    "sg:postcode":"NP22 4EE",
    "sg:province":"Blaenau Gwent",
    "sg:tags":[
        "modification",
        "garage"
    ],
    "wof:name":"Steve's Auto Repairs",
    "wof:placetype":"venue"
},
  "geometry": {"coordinates":[-3.2505021095,51.7873268127],"type":"Point"}
}