{
  "type": "Feature",
  "properties": {
    "addr:full":"Unit 8 Kingswood Clo Coventry Warwickshire CV6 4AZ",
    "addr:housenumber":"unit 8",
    "addr:postcode":"cv6 4az",
    "iso:country":"GB",
    "sg:address":"Unit 8 Kingswood Clo",
    "sg:city":"Coventry",
    "sg:classifiers":[
        {
            "category":"Wholesale",
            "subcategory":"Machinery & Supplies",
            "type":"Manufacturing & Wholesale Goods"
        }
    ],
    "sg:phone":"+44 24 7668 2700",
    "sg:postcode":"CV6 4AZ",
    "sg:province":"Warwickshire",
    "sg:tags":[
        "hydraulic"
    ],
    "wof:name":"G M Hydraulics Ltd",
    "wof:placetype":"venue"
},
  "geometry": {"coordinates":[-1.505704,52.435459],"type":"Point"}
}