{
  "type": "Feature",
  "properties": {
    "addr:full":"34 Chaytor Road Tamworth Staffordshire B78 1JP",
    "addr:housenumber":"34",
    "addr:postcode":"b78 1jp",
    "addr:street":"Chaytor Road",
    "iso:country":"GB",
    "sg:address":"34 Chaytor Road",
    "sg:city":"Tamworth",
    "sg:classifiers":[
        {
            "category":"Building & Trades",
            "subcategory":"Plumbing",
            "type":"Services"
        }
    ],
    "sg:postcode":"B78 1JP",
    "sg:province":"Staffordshire",
    "sg:tags":[
        "central",
        "heating"
    ],
    "wof:name":"William Thomas Newey",
    "wof:placetype":"venue"
},
  "geometry": {"coordinates":[-1.614785,52.614239],"type":"Point"}
}