{
  "type": "Feature",
  "properties": {
    "iso:country":"GB",
    "sg:address":"52 Mucklow Hill",
    "sg:city":"Halesowen",
    "sg:classifiers":[
        {
            "category":"Professional",
            "subcategory":"Business Services",
            "type":"Services"
        }
    ],
    "sg:phone":"+44 121 422 9248",
    "sg:postcode":"B62 8BL",
    "sg:province":"West Midlands",
    "sg:tags":[
        "registrar"
    ],
    "wof:name":"Smallwood Co Services",
    "wof:placetype":"venue"
},
  "geometry": {"coordinates":[-2.032181,52.461082],"type":"Point"}
}