{
  "type": "Feature",
  "properties": {
    "iso:country":"GB",
    "sg:address":"Bawtry Rd, Bramley",
    "sg:city":"Rotherham",
    "sg:classifiers":[
        {
            "category":"Bars & Pubs",
            "type":"Food & Drink"
        }
    ],
    "sg:phone":"+44 1709 704341",
    "sg:postcode":"S66 2TS",
    "sg:province":"South Yorkshire",
    "sg:tags":[
        "pubs",
        "inn"
    ],
    "wof:name":"Travellers Inn",
    "wof:placetype":"venue"
},
  "geometry": {"coordinates":[-1.258009,53.424278],"type":"Point"}
}