{
  "type": "Feature",
  "properties": {
    "addr:full":"65 Blackfriars Road Salford Greater Manchester M3 7DB",
    "addr:housenumber":"65",
    "addr:postcode":"m3 7db",
    "addr:street":"Blackfriars Road",
    "iso:country":"GB",
    "sg:address":"65 Blackfriars Road",
    "sg:city":"Salford",
    "sg:classifiers":[
        {
            "category":"Manufacturing",
            "subcategory":"Furniture",
            "type":"Manufacturing & Wholesale Goods"
        }
    ],
    "sg:phone":"+44 161 834 4342",
    "sg:postcode":"M3 7DB",
    "sg:province":"Greater Manchester",
    "sg:tags":[
        "polishing",
        "french"
    ],
    "wof:name":"A & B Polishers",
    "wof:placetype":"venue"
},
  "geometry": {"coordinates":[-2.255206,53.487541],"type":"Point"}
}