{
  "type": "Feature",
  "properties": {
    "addr:full":"77 Westleigh La Leigh Lancashire WN7 5JE",
    "addr:housenumber":"77",
    "addr:postcode":"wn7 5je",
    "addr:street":"Westleigh La Leigh",
    "iso:country":"GB",
    "sg:address":"77 Westleigh La",
    "sg:city":"Leigh",
    "sg:classifiers":[
        {
            "category":"Bars & Pubs",
            "type":"Food & Drink"
        }
    ],
    "sg:phone":"+44 1942 709416",
    "sg:postcode":"WN7 5JE",
    "sg:province":"Lancashire",
    "sg:tags":[
        "pubs",
        "inn"
    ],
    "wof:name":"Punch Retail Ltd",
    "wof:placetype":"venue"
},
  "geometry": {"coordinates":[-2.526859,53.51178],"type":"Point"}
}