{
  "type": "Feature",
  "properties": {
    "iso:country":"GB",
    "sg:address":"Horsleys Fields, Hardwick Road",
    "sg:city":"King's Lynn",
    "sg:classifiers":[
        {
            "category":"Wholesale",
            "subcategory":"Fruits & Vegetables",
            "type":"Manufacturing & Wholesale Goods"
        }
    ],
    "sg:phone":"+44 1553 775115",
    "sg:postcode":"PE30 5DD",
    "sg:province":"Norfolk",
    "wof:name":"G F Cheney (Produce) Ltd.",
    "wof:placetype":"venue"
},
  "geometry": {"coordinates":[0.41414,52.748619],"type":"Point"}
}