{
  "type": "Feature",
  "properties": {
    "iso:country":"GB",
    "sg:address":"12 Ashdown Court, 5 Idmiston Road",
    "sg:city":"Worcester Park",
    "sg:classifiers":[
        {
            "category":"Home & Garden",
            "subcategory":"Furniture",
            "type":"Retail Goods"
        }
    ],
    "sg:phone":"+44 20 8286 3000",
    "sg:postcode":"KT4 7SE",
    "sg:province":"Surrey",
    "wof:name":"Ideal Sofas Ltd.",
    "wof:placetype":"venue"
},
  "geometry": {"coordinates":[-0.2349340022,51.3750648499],"type":"Point"}
}