{
  "type": "Feature",
  "properties": {
    "addr:full":"74 Newport Rd Barnstaple Devon EX32 9BG",
    "addr:housenumber":"74",
    "addr:postcode":"ex32 9bg",
    "addr:street":"Newport Rd",
    "iso:country":"GB",
    "sg:address":"74 Newport Rd",
    "sg:city":"Barnstaple",
    "sg:classifiers":[
        {
            "category":"Wholesale",
            "subcategory":"Scrap",
            "type":"Manufacturing & Wholesale Goods"
        }
    ],
    "sg:phone":"+44 1271 329641",
    "sg:postcode":"EX32 9BG",
    "sg:province":"Devon",
    "sg:tags":[
        "waste",
        "metal"
    ],
    "wof:name":"Barnstaple Architectural Salvage",
    "wof:placetype":"venue"
},
  "geometry": {"coordinates":[-4.0485582352,51.072101593],"type":"Point"}
}