{
  "type": "Feature",
  "properties": {
    "iso:country":"GB",
    "sg:address":"The Corner House, Tuttington Road, Aylsham",
    "sg:city":"Norwich",
    "sg:classifiers":[
        {
            "category":"Real Estate",
            "subcategory":"Surveying",
            "type":"Services"
        }
    ],
    "sg:phone":"+44 1263 734403",
    "sg:postcode":"NR11 6TA",
    "sg:province":"Norfolk",
    "sg:tags":[
        "surveyor",
        "valuer"
    ],
    "wof:name":"John Bell Surveyors & Valuers Ltd.",
    "wof:placetype":"venue"
},
  "geometry": {"coordinates":[1.28067,52.801945],"type":"Point"}
}