{
  "type": "Feature",
  "properties": {
    "iso:country":"GB",
    "sg:address":"61b High Street",
    "sg:city":"Ascot",
    "sg:classifiers":[
        {
            "category":"Banks & Credit Unions",
            "subcategory":"Financial Services",
            "type":"Services"
        }
    ],
    "sg:postcode":"SL5 7HP",
    "sg:province":"Berkshire",
    "sg:tags":[
        "consultant"
    ],
    "wof:name":"K D R Financial Services",
    "wof:placetype":"venue"
},
  "geometry": {"coordinates":[-0.671338,51.410606],"type":"Point"}
}