{
  "type": "Feature",
  "properties": {
    "iso:country":"GB",
    "sg:address":"95 Newington Road",
    "sg:city":"Edinburgh",
    "sg:classifiers":[
        {
            "category":"Retail",
            "subcategory":"Laundry & Dry Cleaning",
            "type":"Services"
        }
    ],
    "sg:postcode":"EH9 1QW",
    "sg:province":"City of Edinburgh",
    "sg:tags":[
        "alteration"
    ],
    "wof:name":"A Kennedy",
    "wof:placetype":"venue"
},
  "geometry": {"coordinates":[-3.1779921055,55.937702179],"type":"Point"}
}