{
  "type": "Feature",
  "properties": {
    "addr:full":"2 Charter Rd Newcastle Staffordshire ST5 9HJ",
    "addr:housenumber":"2",
    "addr:postcode":"st5 9hj",
    "addr:street":"Charter Rd",
    "iso:country":"GB",
    "sg:address":"2 Charter Rd",
    "sg:city":"Newcastle",
    "sg:classifiers":[
        {
            "category":"Food & Beverages",
            "subcategory":"Fruits & Vegetables",
            "type":"Retail Goods"
        }
    ],
    "sg:phone":"+44 1782 863451",
    "sg:postcode":"ST5 9HJ",
    "sg:province":"Staffordshire",
    "sg:tags":[
        "greengrocer"
    ],
    "wof:name":"MacS Corner",
    "wof:placetype":"venue"
},
  "geometry": {"coordinates":[-2.2351250648,53.0222358704],"type":"Point"}
}