{
  "type": "Feature",
  "properties": {
    "addr:full":"New Park Farm, Lodge Lane, Kirk Langley Derby Derbyshire DE6 4NX",
    "addr:postcode":"de6 4nx",
    "addr:street":"Park;Lodge Lane",
    "iso:country":"GB",
    "sg:address":"New Park Farm, Lodge Lane, Kirk Langley",
    "sg:city":"Derby",
    "sg:classifiers":[
        {
            "category":"Farming",
            "subcategory":"Crops",
            "type":"Manufacturing & Wholesale Goods"
        },
        {
            "category":"Farming",
            "subcategory":"Farm",
            "type":"Manufacturing & Wholesale Goods"
        }
    ],
    "sg:phone":"+44 1332 824262",
    "sg:postcode":"DE6 4NX",
    "sg:province":"Derbyshire",
    "sg:tags":[
        "mixed",
        "arable"
    ],
    "wof:name":"J H Buxton",
    "wof:placetype":"venue"
},
  "geometry": {"coordinates":[-1.5725280046,52.9467277527],"type":"Point"}
}