{
  "type": "Feature",
  "properties": {
    "iso:country":"GB",
    "sg:address":"Weymeadows, Chertsey Road",
    "sg:city":"Shepperton",
    "sg:classifiers":[
        {
            "category":"Parking",
            "type":"Transportation"
        }
    ],
    "sg:postcode":"TW17 9NS",
    "sg:province":"Surrey",
    "sg:tags":[
        "car",
        "valet"
    ],
    "wof:name":"Chauffeur Assured",
    "wof:placetype":"venue"
},
  "geometry": {"coordinates":[-0.4485470057,51.3943214417],"type":"Point"}
}