{
  "type": "Feature",
  "properties": {
    "addr:full":"White Hart Stables, Bank St Southampton Hampshire SO32 1AN",
    "addr:postcode":"so32 1an",
    "addr:street":"Bank St",
    "iso:country":"GB",
    "sg:address":"White Hart Stables, Bank St",
    "sg:city":"Southampton",
    "sg:classifiers":[
        {
            "category":"Professional",
            "subcategory":"Lawyer & Legal Services",
            "type":"Services"
        }
    ],
    "sg:phone":"+44 1489 896656",
    "sg:postcode":"SO32 1AN",
    "sg:province":"Hampshire",
    "wof:name":"Personal Injury Claims Services",
    "wof:placetype":"venue"
},
  "geometry": {"coordinates":[-1.2096999884,50.9544487],"type":"Point"}
}