{
  "type": "Feature",
  "properties": {
    "iso:country":"GB",
    "sg:address":"14 Allhallows",
    "sg:city":"Bedford",
    "sg:classifiers":[
        {
            "category":"Shopping",
            "subcategory":"Books",
            "type":"Retail Goods"
        }
    ],
    "sg:postcode":"MK40 1LJ",
    "sg:province":"Bedfordshire",
    "sg:tags":[
        "bookseller"
    ],
    "wof:name":"K K Books",
    "wof:placetype":"venue"
},
  "geometry": {"coordinates":[-0.470508,52.137356],"type":"Point"}
}