{
  "type": "Feature",
  "properties": {
    "iso:country":"GB",
    "sg:address":"Coombe Butler, Calverleigh",
    "sg:city":"Tiverton",
    "sg:classifiers":[
        {
            "category":"Home & Garden",
            "subcategory":"Garden Supply",
            "type":"Retail Goods"
        },
        {
            "category":"Farming",
            "subcategory":"Farm",
            "type":"Manufacturing & Wholesale Goods"
        }
    ],
    "sg:phone":"+44 1884 252947",
    "sg:postcode":"EX16 8BA",
    "sg:province":"Devon",
    "sg:tags":[
        "mixed",
        "bulb",
        "crop",
        "grower"
    ],
    "wof:name":"M W Slade",
    "wof:placetype":"venue"
},
  "geometry": {"coordinates":[-3.524194,50.9189],"type":"Point"}
}