{
  "type": "Feature",
  "properties": {
    "iso:country":"GB",
    "sg:address":"Block Farm, Bradfield Combust",
    "sg:city":"Bury St Edmunds",
    "sg:classifiers":[
        {
            "category":"Farming",
            "subcategory":"Livestock Farm",
            "type":"Manufacturing & Wholesale Goods"
        }
    ],
    "sg:postcode":"IP30 0LW",
    "sg:province":"Suffolk",
    "sg:tags":[
        "others"
    ],
    "wof:name":"T Waspe & Son",
    "wof:placetype":"venue"
},
  "geometry": {"coordinates":[0.76568,52.179321],"type":"Point"}
}