{
  "type": "Feature",
  "properties": {
    "iso:country":"GB",
    "sg:address":"100 Harvey Road, Willesborough",
    "sg:city":"Ashford",
    "sg:classifiers":[
        {
            "category":"Building & Trades",
            "subcategory":"Construction",
            "type":"Services"
        }
    ],
    "sg:phone":"+44 1233 631767",
    "sg:postcode":"TN24 0AW",
    "sg:province":"Kent",
    "sg:tags":[
        "joiner",
        "carpenter"
    ],
    "wof:name":"W D Carter",
    "wof:placetype":"venue"
},
  "geometry": {"coordinates":[0.901041,51.143932],"type":"Point"}
}