{
  "type": "Feature",
  "properties": {
    "addr:full":"Unit 2 Brunts Business Centre Mansfield Nottinghamshire NG18 2AH",
    "addr:housenumber":"unit 2",
    "addr:postcode":"ng18 2ah",
    "addr:street":"Brunts Business Centre",
    "iso:country":"GB",
    "sg:address":"Unit 2 Brunts Business Centre",
    "sg:city":"Mansfield",
    "sg:classifiers":[
        {
            "category":"Insurance",
            "subcategory":"Hazard Insurance",
            "type":"Services"
        }
    ],
    "sg:phone":"+44 1623 628462",
    "sg:postcode":"NG18 2AH",
    "sg:province":"Nottinghamshire",
    "sg:tags":[
        "travel"
    ],
    "wof:name":"Management Co (London) Ltd (The)",
    "wof:placetype":"venue"
},
  "geometry": {"coordinates":[-1.1934570074,53.1490821838],"type":"Point"}
}