{
  "type": "Feature",
  "properties": {
    "iso:country":"GB",
    "sg:address":"22 Westfield Avenue",
    "sg:city":"Hayling Island",
    "sg:classifiers":[
        {
            "category":"Health Services",
            "subcategory":"Nursing And Care Facility",
            "type":"Services"
        }
    ],
    "sg:phone":"+44 23 9246 8811",
    "sg:postcode":"PO11 9AG",
    "sg:province":"Hampshire",
    "sg:tags":[
        "home"
    ],
    "wof:name":"Oakmore Nursing Home",
    "wof:placetype":"venue"
},
  "geometry": {"coordinates":[-0.986161,50.786514],"type":"Point"}
}