{
  "type": "Feature",
  "properties": {
    "addr:full":"90 Station Road Sidcup Kent DA15 7DU",
    "addr:housenumber":"90",
    "addr:postcode":"da15 7du",
    "addr:street":"Station Road",
    "iso:country":"GB",
    "sg:address":"90 Station Road",
    "sg:city":"Sidcup",
    "sg:classifiers":[
        {
            "category":"Personal",
            "subcategory":"Barber",
            "type":"Services"
        }
    ],
    "sg:phone":"+44 20 8302 5991",
    "sg:postcode":"DA15 7DU",
    "sg:province":"Kent",
    "sg:tags":[
        "men's",
        "hairdresser"
    ],
    "wof:name":"Station Road Barbers",
    "wof:placetype":"venue"
},
  "geometry": {"coordinates":[0.1024520025,51.4317512512],"type":"Point"}
}