{
  "type": "Feature",
  "properties": {
    "addr:full":"312a Cowbridge Road East, Canton Cardiff Cardiff CF5 1HW",
    "addr:housenumber":"312a",
    "addr:postcode":"cf5 1hw",
    "addr:street":"Cowbridge Road East",
    "iso:country":"GB",
    "sg:address":"312a Cowbridge Road East, Canton",
    "sg:city":"Cardiff",
    "sg:classifiers":[
        {
            "category":"Shopping",
            "subcategory":"Bicycles & Sporting Goods",
            "type":"Retail Goods"
        }
    ],
    "sg:postcode":"CF5 1HW",
    "sg:province":"Cardiff",
    "sg:tags":[
        "cycle",
        "accessory"
    ],
    "wof:name":"Dennis & Linda Griffiths",
    "wof:placetype":"venue"
},
  "geometry": {"coordinates":[-3.2109079361,51.4826164246],"type":"Point"}
}