{
  "type": "Feature",
  "properties": {
    "addr:full":"21 Station Road Swanley Kent BR8 8ES",
    "addr:housenumber":"21",
    "addr:postcode":"br8 8es",
    "addr:street":"Station Road",
    "iso:country":"GB",
    "sg:address":"21 Station Road",
    "sg:city":"Swanley",
    "sg:classifiers":[
        {
            "category":"Personal",
            "subcategory":"Beauty Salon",
            "type":"Services"
        }
    ],
    "sg:postcode":"BR8 8ES",
    "sg:province":"Kent",
    "sg:tags":[
        "lady",
        "hairdresser"
    ],
    "wof:name":"Barry's",
    "wof:placetype":"venue"
},
  "geometry": {"coordinates":[0.175925,51.394917],"type":"Point"}
}