{
  "type": "Feature",
  "properties": {
    "addr:full":"19 East Street Petworth West Sussex GU28 0AB",
    "addr:housenumber":"19",
    "addr:postcode":"gu28 0ab",
    "addr:street":"East Street",
    "iso:country":"GB",
    "sg:address":"19 East Street",
    "sg:city":"Petworth",
    "sg:classifiers":[
        {
            "category":"Shopping",
            "subcategory":"Antiques",
            "type":"Retail Goods"
        }
    ],
    "sg:postcode":"GU28 0AB",
    "sg:province":"West Sussex",
    "wof:name":"De Brett's",
    "wof:placetype":"venue"
},
  "geometry": {"coordinates":[-0.608529,50.986931],"type":"Point"}
}