{
  "type": "Feature",
  "properties": {
    "iso:country":"GB",
    "sg:address":"Paradise Mill, John St",
    "sg:city":"Bury",
    "sg:classifiers":[
        {
            "category":"Professional",
            "subcategory":"Accounting & Tax Preparation",
            "type":"Services"
        }
    ],
    "sg:phone":"+44 161 761 2061",
    "sg:postcode":"BL9 0NH",
    "sg:province":"Lancashire",
    "sg:tags":[
        "accountant"
    ],
    "wof:name":"David Stringfellow & Co",
    "wof:placetype":"venue"
},
  "geometry": {"coordinates":[-2.301054,53.589733],"type":"Point"}
}