{
  "type": "Feature",
  "properties": {
    "iso:country":"GB",
    "sg:address":"Burgh Chambers, Church Street, Portknockie",
    "sg:city":"Buckie",
    "sg:classifiers":[
        {
            "category":"Education",
            "subcategory":"Preschool",
            "type":"Public Place"
        }
    ],
    "sg:postcode":"AB56 2LN",
    "sg:province":"Moray",
    "sg:tags":[
        "pre-school",
        "playgroups"
    ],
    "wof:name":"Portknockie Playgroup",
    "wof:placetype":"venue"
},
  "geometry": {"coordinates":[-2.965224,57.676701],"type":"Point"}
}