{
  "type": "Feature",
  "properties": {
    "iso:country":"GB",
    "sg:address":"Station House, Gresford Hill, Gresford",
    "sg:city":"Wrexham",
    "sg:classifiers":[
        {
            "category":"Real Estate",
            "subcategory":"Developer",
            "type":"Services"
        },
        {
            "category":"Building & Trades",
            "subcategory":"Construction",
            "type":"Services"
        }
    ],
    "sg:phone":"+44 1978 853338",
    "sg:postcode":"LL12 8RH",
    "sg:province":"Wrexham",
    "sg:tags":[
        "residential",
        "builder",
        "property"
    ],
    "wof:name":"Griffin Homes Ltd.",
    "wof:placetype":"venue"
},
  "geometry": {"coordinates":[-2.977964,53.087158],"type":"Point"}
}