{
  "type": "Feature",
  "properties": {
    "iso:country":"GB",
    "sg:address":"20 Brunswick Street East",
    "sg:city":"Hove",
    "sg:classifiers":[
        {
            "category":"Shopping",
            "subcategory":"Antiques",
            "type":"Retail Goods"
        }
    ],
    "sg:phone":"+44 1273 778816",
    "sg:postcode":"BN3 1AU",
    "sg:province":"East Sussex",
    "wof:name":"Iain Mackinnon",
    "wof:placetype":"venue"
},
  "geometry": {"coordinates":[-0.157504,50.823326],"type":"Point"}
}