{
  "type": "Feature",
  "properties": {
    "addr:full":"315 Hertford Road London Greater London N9 7ET",
    "addr:housenumber":"315",
    "addr:postcode":"n9 7et",
    "addr:street":"Hertford Road",
    "iso:country":"GB",
    "sg:address":"315 Hertford Road",
    "sg:city":"London",
    "sg:classifiers":[
        {
            "category":"Home & Garden",
            "subcategory":"Home Furnishings",
            "type":"Retail Goods"
        },
        {
            "category":"Home & Garden",
            "subcategory":"Building Materials",
            "type":"Retail Goods"
        }
    ],
    "sg:postcode":"N9 7ET",
    "sg:province":"Greater London",
    "sg:tags":[
        "installers",
        "planner",
        "kitchen",
        "furnishers"
    ],
    "wof:name":"LEEDAL KITCHEN SYSTEMS",
    "wof:placetype":"venue"
},
  "geometry": {"coordinates":[-0.0539789982,51.6331291199],"type":"Point"}
}