{
  "type": "Feature",
  "properties": {
    "addr:full":"Tamarisk, Puddington Tiverton Devon EX16 8LW",
    "addr:postcode":"ex16 8lw",
    "addr:street":"Puddington",
    "iso:country":"GB",
    "sg:address":"Tamarisk, Puddington",
    "sg:city":"Tiverton",
    "sg:classifiers":[
        {
            "category":"Farming",
            "subcategory":"Livestock Farm",
            "type":"Manufacturing & Wholesale Goods"
        }
    ],
    "sg:phone":"+44 1884 860691",
    "sg:postcode":"EX16 8LW",
    "sg:province":"Devon",
    "sg:tags":[
        "others"
    ],
    "wof:name":"Frederick G Berry",
    "wof:placetype":"venue"
},
  "geometry": {"coordinates":[-3.6586489677,50.8828392029],"type":"Point"}
}