{
  "type": "Feature",
  "properties": {
    "iso:country":"GB",
    "sg:address":"30 Aylestone Lane",
    "sg:city":"Wigston",
    "sg:classifiers":[
        {
            "category":"Personal",
            "subcategory":"Beauty Salon",
            "type":"Services"
        },
        {
            "category":"Personal",
            "subcategory":"Barber",
            "type":"Services"
        }
    ],
    "sg:phone":"+44 116 288 2580",
    "sg:postcode":"LE18 1AA",
    "sg:province":"Leicestershire",
    "sg:tags":[
        "unisex",
        "lady",
        "hairdresser"
    ],
    "wof:name":"Willow Hair Styles",
    "wof:placetype":"venue"
},
  "geometry": {"coordinates":[-1.108062,52.586334],"type":"Point"}
}