{
  "type": "Feature",
  "properties": {
    "addr:full":"19 West Street Sevenoaks Kent TN15 7AR",
    "addr:housenumber":"19",
    "addr:postcode":"tn15 7ar",
    "addr:street":"West Street",
    "iso:country":"GB",
    "sg:address":"19 West Street",
    "sg:city":"Sevenoaks",
    "sg:classifiers":[
        {
            "category":"Building & Trades",
            "subcategory":"Plumbing",
            "type":"Services"
        }
    ],
    "sg:phone":"+44 1732 884375",
    "sg:postcode":"TN15 7AR",
    "sg:province":"Kent",
    "sg:tags":[
        "heating"
    ],
    "wof:name":"Alan Summers",
    "wof:placetype":"venue"
},
  "geometry": {"coordinates":[0.308648,51.308926],"type":"Point"}
}