{
  "type": "Feature",
  "properties": {
    "iso:country":"GB",
    "sg:address":"Unit 16, The Business Centre, Ross Road, Weedon Road Industrial Estate",
    "sg:city":"Northampton",
    "sg:classifiers":[
        {
            "category":"Building & Trades",
            "subcategory":"Construction",
            "type":"Services"
        }
    ],
    "sg:phone":"+44 1604 588909",
    "sg:postcode":"NN5 5AX",
    "sg:province":"Northamptonshire",
    "sg:tags":[
        "flooring"
    ],
    "wof:name":"Crown Flooring Consultants",
    "wof:placetype":"venue"
},
  "geometry": {"coordinates":[-0.91427,52.233681],"type":"Point"}
}