{
  "type": "Feature",
  "properties": {
    "addr:full":"Craigview House, 50 Main Street, Strathkinness St. Andrews Fife KY16 9SA",
    "addr:housenumber":"50",
    "addr:postcode":"ky16 9sa",
    "addr:street":"Main Street Strathkinness",
    "iso:country":"GB",
    "sg:address":"Craigview House, 50 Main Street, Strathkinness",
    "sg:city":"St. Andrews",
    "sg:classifiers":[
        {
            "category":"Bus Charters",
            "type":"Transportation"
        }
    ],
    "sg:phone":"+44 1334 850255",
    "sg:postcode":"KY16 9SA",
    "sg:province":"Fife",
    "sg:tags":[
        "coach"
    ],
    "wof:name":"Gordon Donaldson",
    "wof:placetype":"venue"
},
  "geometry": {"coordinates":[-2.877023,56.33374],"type":"Point"}
}