{
  "type": "Feature",
  "properties": {
    "iso:country":"GB",
    "sg:address":"Care Of Royal Masonic Hospital, Ravenscourt Park",
    "sg:city":"London",
    "sg:classifiers":[
        {
            "category":"Health Services",
            "subcategory":"Hospital",
            "type":"Services"
        }
    ],
    "sg:phone":"+44 20 8563 3898",
    "sg:postcode":"W6 0TN",
    "sg:province":"Greater London",
    "wof:name":"Spring Medical",
    "wof:placetype":"venue"
},
  "geometry": {"coordinates":[-0.24144,51.496349],"type":"Point"}
}