{
  "type": "Feature",
  "properties": {
    "iso:country":"GB",
    "sg:address":"9 Hillingdon",
    "sg:city":"Bridport",
    "sg:classifiers":[
        {
            "category":"Building & Trades",
            "subcategory":"Landscaping Services",
            "type":"Services"
        }
    ],
    "sg:phone":"+44 1308 422527",
    "sg:postcode":"DT6 3DH",
    "sg:province":"Dorset",
    "sg:tags":[
        "gardening"
    ],
    "wof:name":"Horwoods Landscape Gardeners",
    "wof:placetype":"venue"
},
  "geometry": {"coordinates":[-2.7458760738,50.7419433594],"type":"Point"}
}