{
  "type": "Feature",
  "properties": {
    "addr:full":"8 South Common, Redbourn St Albans Hertfordshire AL3 7LU",
    "addr:housenumber":"8",
    "addr:postcode":"al3 7lu",
    "addr:street":"South Common Redbourn",
    "iso:country":"GB",
    "sg:address":"8 South Common, Redbourn",
    "sg:city":"St Albans",
    "sg:classifiers":[
        {
            "category":"Building & Trades",
            "subcategory":"Cleaning & Sanitation",
            "type":"Services"
        },
        {
            "category":"Shopping",
            "subcategory":"Pharmacy",
            "type":"Retail Goods"
        }
    ],
    "sg:phone":"+44 1582 793076",
    "sg:postcode":"AL3 7LU",
    "sg:province":"Hertfordshire",
    "sg:tags":[
        "medicine",
        "cleaner",
        "window",
        "therapy"
    ],
    "wof:name":"MEL FURLONG",
    "wof:placetype":"venue"
},
  "geometry": {"coordinates":[-0.396754,51.796535],"type":"Point"}
}