{
  "type": "Feature",
  "properties": {
    "addr:full":"Suffolk House, Trade Street Cardiff Cardiff CF10 5DQ",
    "addr:postcode":"cf10 5dq",
    "addr:street":"Trade Street",
    "iso:country":"GB",
    "sg:address":"Suffolk House, Trade Street",
    "sg:city":"Cardiff",
    "sg:classifiers":[
        {
            "category":"Professional",
            "subcategory":"Business Services",
            "type":"Services"
        }
    ],
    "sg:phone":"+44 29 2034 4150",
    "sg:postcode":"CF10 5DQ",
    "sg:province":"Cardiff",
    "sg:tags":[
        "holding"
    ],
    "wof:name":"Penta Holdings Ltd.",
    "wof:placetype":"venue"
},
  "geometry": {"coordinates":[-3.178169,51.472244],"type":"Point"}
}