{
  "type": "Feature",
  "properties": {
    "iso:country":"GB",
    "sg:address":"50 West Street",
    "sg:city":"Farnham",
    "sg:classifiers":[
        {
            "category":"Health Services",
            "subcategory":"Doctor",
            "type":"Services"
        }
    ],
    "sg:phone":"+44 1278 794010",
    "sg:postcode":"GU9 7DX",
    "sg:province":"Surrey",
    "sg:tags":[
        "practitioners"
    ],
    "wof:name":"Columbia Enterprises Uk Ltd.",
    "wof:placetype":"venue"
},
  "geometry": {"coordinates":[-0.806525,51.212624],"type":"Point"}
}