{
  "type": "Feature",
  "properties": {
    "iso:country":"GB",
    "sg:address":"Unit 7 Kings Business Park, Kings Park Av",
    "sg:city":"Bristol",
    "sg:classifiers":[
        {
            "category":"Building & Trades",
            "subcategory":"Construction",
            "type":"Services"
        }
    ],
    "sg:phone":"+44 117 977 4999",
    "sg:postcode":"BS2 0TZ",
    "sg:province":"City of Bristol",
    "sg:tags":[
        "builder"
    ],
    "wof:name":"Taymech Maintenance",
    "wof:placetype":"venue"
},
  "geometry": {"coordinates":[-2.56038,51.450748],"type":"Point"}
}