{
  "type": "Feature",
  "properties": {
    "addr:full":"34 Manchester Rd, Chorlton Cum Hardy Manchester Cheshire M21 9PH",
    "addr:housenumber":"34",
    "addr:postcode":"m21 9ph",
    "addr:street":"Manchester Rd",
    "iso:country":"GB",
    "sg:address":"34 Manchester Rd, Chorlton Cum Hardy",
    "sg:city":"Manchester",
    "sg:classifiers":[
        {
            "category":"Professional",
            "subcategory":"Art Services",
            "type":"Services"
        }
    ],
    "sg:phone":"+44 161 861 0440",
    "sg:postcode":"M21 9PH",
    "sg:province":"Cheshire",
    "sg:tags":[
        "graphic",
        "designer"
    ],
    "wof:name":"Printworld Design Group Ltd (The)",
    "wof:placetype":"venue"
},
  "geometry": {"coordinates":[-2.278167963,53.4441642761],"type":"Point"}
}