{
  "type": "Feature",
  "properties": {
    "iso:country":"GB",
    "sg:address":"20 Howard St South",
    "sg:city":"Great Yarmouth",
    "sg:classifiers":[
        {
            "category":"Shopping",
            "subcategory":"Florist",
            "type":"Retail Goods"
        }
    ],
    "sg:phone":"+44 1493 844122",
    "sg:postcode":"NR30 1LL",
    "sg:province":"Norfolk",
    "wof:name":"Garlands",
    "wof:placetype":"venue"
},
  "geometry": {"coordinates":[1.725647,52.606987],"type":"Point"}
}