{
  "type": "Feature",
  "properties": {
    "addr:full":"66 Cranmore Lane Aldershot Hampshire GU11 3BB",
    "addr:housenumber":"66",
    "addr:postcode":"gu11 3bb",
    "addr:street":"Cranmore Lane",
    "iso:country":"GB",
    "sg:address":"66 Cranmore Lane",
    "sg:city":"Aldershot",
    "sg:classifiers":[
        {
            "category":"Personal",
            "subcategory":"Tanning Parlor",
            "type":"Services"
        }
    ],
    "sg:postcode":"GU11 3BB",
    "sg:province":"Hampshire",
    "sg:tags":[
        "sunbeds"
    ],
    "wof:name":"Rocket Tan",
    "wof:placetype":"venue"
},
  "geometry": {"coordinates":[-0.780235,51.243401],"type":"Point"}
}