{
  "type": "Feature",
  "properties": {
    "addr:full":"Bank House, Stoke Bliss Tenbury Wells Herefordshire WR15 8QH",
    "addr:housenumber":"bliss",
    "addr:postcode":"wr15 8qh",
    "iso:country":"GB",
    "sg:address":"Bank House, Stoke Bliss",
    "sg:city":"Tenbury Wells",
    "sg:classifiers":[
        {
            "category":"Recreation",
            "subcategory":"Campground",
            "type":"Entertainment"
        }
    ],
    "sg:postcode":"WR15 8QH",
    "sg:province":"Herefordshire",
    "sg:tags":[
        "caravan",
        "park"
    ],
    "wof:name":"Healing Hands Network",
    "wof:placetype":"venue"
},
  "geometry": {"coordinates":[-2.594178915,52.3125839233],"type":"Point"}
}