{
  "type": "Feature",
  "properties": {
    "addr:full":"29 Station Lane, Featherstone Pontefract West Yorkshire WF7 5BE",
    "addr:housenumber":"29",
    "addr:postcode":"wf7 5be",
    "addr:street":"Station Lane;West",
    "iso:country":"GB",
    "sg:address":"29 Station Lane, Featherstone",
    "sg:city":"Pontefract",
    "sg:classifiers":[
        {
            "category":"Personal",
            "subcategory":"Beauty Salon",
            "type":"Services"
        },
        {
            "category":"Personal",
            "subcategory":"Barber",
            "type":"Services"
        }
    ],
    "sg:phone":"+44 1977 799042",
    "sg:postcode":"WF7 5BE",
    "sg:province":"West Yorkshire",
    "sg:tags":[
        "unisex",
        "hairdresser"
    ],
    "wof:name":"Kay 4 Kuts",
    "wof:placetype":"venue"
},
  "geometry": {"coordinates":[-1.359072,53.675465],"type":"Point"}
}