{
  "type": "Feature",
  "properties": {
    "iso:country":"GB",
    "sg:address":"41 Walton Cres",
    "sg:city":"Oxford",
    "sg:classifiers":[
        {
            "category":"Health Services",
            "subcategory":"Health Practitioner",
            "type":"Services"
        }
    ],
    "sg:postcode":"OX1 2JQ",
    "sg:province":"Oxfordshire",
    "sg:tags":[
        "acupuncture"
    ],
    "wof:name":"Acupuncture Centre",
    "wof:placetype":"venue"
},
  "geometry": {"coordinates":[-1.265474,51.757641],"type":"Point"}
}