{
  "type": "Feature",
  "properties": {
    "iso:country":"GB",
    "sg:address":"164a South Coast Road",
    "sg:city":"Peacehaven",
    "sg:classifiers":[
        {
            "category":"Personal",
            "subcategory":"Beauty Salon",
            "type":"Services"
        }
    ],
    "sg:postcode":"BN10 7BY",
    "sg:province":"East Sussex",
    "sg:tags":[
        "unisex",
        "hairdresser"
    ],
    "wof:name":"Nail & Beauty Studio",
    "wof:placetype":"venue"
},
  "geometry": {"coordinates":[-0.002729,50.79158],"type":"Point"}
}