{
  "type": "Feature",
  "properties": {
    "addr:full":"20 Camberidge Drive St Ives Cambridgeshire PE27 3AB",
    "addr:housenumber":"20",
    "addr:postcode":"pe27 3ab",
    "addr:street":"Camberidge Drive",
    "iso:country":"GB",
    "sg:address":"20 Camberidge Drive",
    "sg:city":"St Ives",
    "sg:classifiers":[
        {
            "category":"Building & Trades",
            "subcategory":"Cleaning & Sanitation",
            "type":"Services"
        }
    ],
    "sg:phone":"+44 1480 462651",
    "sg:postcode":"PE27 3AB",
    "sg:province":"Cambridgeshire",
    "sg:tags":[
        "commercial"
    ],
    "wof:name":"Tt Services",
    "wof:placetype":"venue"
},
  "geometry": {"coordinates":[-0.0794729963,52.3437576294],"type":"Point"}
}