{
  "type": "Feature",
  "properties": {
    "addr:full":"Great Spenders Basildon Essex SS14 2PJ",
    "addr:postcode":"ss14 2pj",
    "iso:country":"GB",
    "sg:address":"Great Spenders",
    "sg:city":"Basildon",
    "sg:classifiers":[
        {
            "category":"Health Services",
            "subcategory":"Nursing And Care Facility",
            "type":"Services"
        }
    ],
    "sg:phone":"+44 1268 533678",
    "sg:postcode":"SS14 2PJ",
    "sg:province":"Essex",
    "sg:tags":[
        "home"
    ],
    "wof:name":"Southwood Court",
    "wof:placetype":"venue"
},
  "geometry": {"coordinates":[0.4786159992,51.5823402405],"type":"Point"}
}