{
  "type": "Feature",
  "properties": {
    "addr:full":"23 Stanley Park Avenue South Liverpool Merseyside L4 7XB",
    "addr:housenumber":"23",
    "addr:postcode":"l4 7xb",
    "addr:street":"Stanley Park Avenue South",
    "iso:country":"GB",
    "sg:address":"23 Stanley Park Avenue South",
    "sg:city":"Liverpool",
    "sg:classifiers":[
        {
            "category":"Shopping",
            "subcategory":"Florist",
            "type":"Retail Goods"
        }
    ],
    "sg:phone":"+44 151 264 7151",
    "sg:postcode":"L4 7XB",
    "sg:province":"Merseyside",
    "wof:name":"Anne Marie",
    "wof:placetype":"venue"
},
  "geometry": {"coordinates":[-2.9518580437,53.4349632263],"type":"Point"}
}