{
  "type": "Feature",
  "properties": {
    "iso:country":"GB",
    "sg:address":"Chapel Rd",
    "sg:city":"Oldham",
    "sg:classifiers":[
        {
            "category":"Place Of Worship",
            "type":"Public Place"
        }
    ],
    "sg:phone":"+44 161 681 4541",
    "sg:postcode":"OL8 4QQ",
    "sg:province":"Lancashire",
    "wof:name":"St Margaret C of E Church",
    "wof:placetype":"venue"
},
  "geometry": {"coordinates":[-2.1365110874,53.5244407654],"type":"Point"}
}