{
  "type": "Feature",
  "properties": {
    "iso:country":"GB",
    "sg:address":"Hellesveor Farm",
    "sg:city":"St Ives",
    "sg:classifiers":[
        {
            "category":"Farming",
            "subcategory":"Livestock Farm",
            "type":"Manufacturing & Wholesale Goods"
        }
    ],
    "sg:phone":"+44 1736 795738",
    "sg:postcode":"TR26 3AD",
    "sg:province":"Cornwall",
    "sg:tags":[
        "others"
    ],
    "wof:name":"G & H Rogers",
    "wof:placetype":"venue"
},
  "geometry": {"coordinates":[-5.501724,50.206215],"type":"Point"}
}