{
  "type": "Feature",
  "properties": {
    "iso:country":"GB",
    "sg:address":"8 Dunyeats Rd",
    "sg:city":"Broadstone",
    "sg:classifiers":[
        {
            "category":"Professional",
            "subcategory":"Management & Consulting",
            "type":"Services"
        }
    ],
    "sg:postcode":"BH18 8AG",
    "sg:province":"Dorset",
    "sg:tags":[
        "consultant",
        "energy",
        "conservation"
    ],
    "wof:name":"Energy 2000",
    "wof:placetype":"venue"
},
  "geometry": {"coordinates":[-1.9951629639,50.762046814],"type":"Point"}
}