{
  "type": "Feature",
  "properties": {
    "addr:full":"473 Aylestone Road Leicester Leicestershire LE2 8TB",
    "addr:housenumber":"473",
    "addr:postcode":"le2 8tb",
    "addr:street":"Aylestone Road",
    "iso:country":"GB",
    "sg:address":"473 Aylestone Road",
    "sg:city":"Leicester",
    "sg:classifiers":[
        {
            "category":"Professional",
            "subcategory":"Business Services",
            "type":"Services"
        }
    ],
    "sg:phone":"+44 116 244 0101",
    "sg:postcode":"LE2 8TB",
    "sg:province":"Leicestershire",
    "sg:tags":[
        "tile",
        "stockist"
    ],
    "wof:name":"Designer Tiles",
    "wof:placetype":"venue"
},
  "geometry": {"coordinates":[-1.1454819441,52.609954834],"type":"Point"}
}