{
  "type": "Feature",
  "properties": {
    "addr:full":"541 Pentregethin Road, Ravenhill Swansea Swansea SA5 8AB",
    "addr:housenumber":"541",
    "addr:postcode":"sa5 8ab",
    "addr:street":"Pentregethin Road",
    "iso:country":"GB",
    "sg:address":"541 Pentregethin Road, Ravenhill",
    "sg:city":"Swansea",
    "sg:classifiers":[
        {
            "category":"Home & Garden",
            "subcategory":"Home Furnishings",
            "type":"Retail Goods"
        }
    ],
    "sg:postcode":"SA5 8AB",
    "sg:province":"Swansea",
    "sg:tags":[
        "blind",
        "curtain",
        "fitting"
    ],
    "wof:name":"Evans Curtains & Blinds",
    "wof:placetype":"venue"
},
  "geometry": {"coordinates":[-3.970801,51.64558],"type":"Point"}
}