{
  "type": "Feature",
  "properties": {
    "addr:full":"58-60 High Rd East Finchley Greater London N2 9PN",
    "addr:housenumber":"58-60",
    "addr:postcode":"n2 9pn",
    "addr:street":"High Rd",
    "iso:country":"GB",
    "sg:address":"58-60 High Rd",
    "sg:city":"East Finchley",
    "sg:classifiers":[
        {
            "category":"Shopping",
            "subcategory":"Florist",
            "type":"Retail Goods"
        }
    ],
    "sg:phone":"+44 20 8883 3598",
    "sg:postcode":"N2 9PN",
    "sg:province":"Greater London",
    "wof:name":"Flowers By Josephines",
    "wof:placetype":"venue"
},
  "geometry": {"coordinates":[-0.1641989946,51.5878791809],"type":"Point"}
}