{
  "type": "Feature",
  "properties": {
    "iso:country":"GB",
    "sg:address":"Unit 1b, The Sidings Industrial Estate",
    "sg:city":"Settle",
    "sg:classifiers":[
        {
            "category":"Autos & Motor Vehicles",
            "subcategory":"Auto Supplies",
            "type":"Retail Goods"
        }
    ],
    "sg:phone":"+44 1729 825237",
    "sg:postcode":"BD24 9RP",
    "sg:province":"North Yorkshire",
    "sg:tags":[
        "rubber",
        "tyre"
    ],
    "wof:name":"Best Tyres",
    "wof:placetype":"venue"
},
  "geometry": {"coordinates":[-2.281249,54.065403],"type":"Point"}
}