{
  "type": "Feature",
  "properties": {
    "addr:full":"51 Burnside Crescent, Blantyre Glasgow South Lanarkshire G72 0LB",
    "addr:housenumber":"51",
    "addr:postcode":"g72 0lb",
    "addr:street":"Burnside Crescent",
    "iso:country":"GB",
    "sg:address":"51 Burnside Crescent, Blantyre",
    "sg:city":"Glasgow",
    "sg:classifiers":[
        {
            "category":"Shopping",
            "subcategory":"Discount & Variety Stores",
            "type":"Retail Goods"
        }
    ],
    "sg:phone":"+44 1698 712433",
    "sg:postcode":"G72 0LB",
    "sg:province":"South Lanarkshire",
    "sg:tags":[
        "cleaning",
        "supply"
    ],
    "wof:name":"Thistle Hygiene Co",
    "wof:placetype":"venue"
},
  "geometry": {"coordinates":[-4.0803279877,55.7874145508],"type":"Point"}
}