{
  "type": "Feature",
  "properties": {
    "addr:full":"D-e, Unit, Vallis Mills Trading Estate Frome Somerset BA11 3DT",
    "addr:postcode":"ba11 3dt",
    "iso:country":"GB",
    "sg:address":"D-e, Unit, Vallis Mills Trading Estate",
    "sg:city":"Frome",
    "sg:classifiers":[
        {
            "category":"Manufacturing",
            "subcategory":"Building Materials",
            "type":"Manufacturing & Wholesale Goods"
        }
    ],
    "sg:phone":"+44 1373 451600",
    "sg:postcode":"BA11 3DT",
    "sg:province":"Somerset",
    "sg:tags":[
        "merchant",
        "builder"
    ],
    "wof:name":"Tipadel Ltd.",
    "wof:placetype":"venue"
},
  "geometry": {"coordinates":[-2.333292,51.233795],"type":"Point"}
}