{
  "type": "Feature",
  "properties": {
    "iso:country":"GB",
    "sg:address":"Anglo Dutch, 1 Mentmore View",
    "sg:city":"Tring",
    "sg:classifiers":[
        {
            "category":"Shopping",
            "subcategory":"Department Store",
            "type":"Retail Goods"
        }
    ],
    "sg:postcode":"HP23 4HR",
    "sg:province":"Buckinghamshire",
    "wof:name":"Stoney Ground Ltd",
    "wof:placetype":"venue"
},
  "geometry": {"coordinates":[-0.66398,51.79327],"type":"Point"}
}