{
  "type": "Feature",
  "properties": {
    "addr:full":"11 Lansdowne Way Liverpool Merseyside L36 9YB",
    "addr:housenumber":"11",
    "addr:postcode":"l36 9yb",
    "addr:street":"Lansdowne Way",
    "iso:country":"GB",
    "sg:address":"11 Lansdowne Way",
    "sg:city":"Liverpool",
    "sg:classifiers":[
        {
            "category":"Shopping",
            "subcategory":"Baby Store",
            "type":"Retail Goods"
        }
    ],
    "sg:postcode":"L36 9YB",
    "sg:province":"Merseyside",
    "sg:tags":[
        "babywear",
        "childrens"
    ],
    "wof:name":"Phillips,P,",
    "wof:placetype":"venue"
},
  "geometry": {"coordinates":[-2.8386399746,53.4112586975],"type":"Point"}
}