{
  "type": "Feature",
  "properties": {
    "addr:full":"Nelson Wharf, Victoria Rd Lowestoft Suffolk NR33 9LP",
    "addr:postcode":"nr33 9lp",
    "addr:street":"Nelson;Victoria Rd",
    "iso:country":"GB",
    "sg:address":"Nelson Wharf, Victoria Rd",
    "sg:city":"Lowestoft",
    "sg:classifiers":[
        {
            "category":"Manufacturing",
            "subcategory":"Paper Products",
            "type":"Manufacturing & Wholesale Goods"
        }
    ],
    "sg:phone":"+44 1502 561811",
    "sg:postcode":"NR33 9LP",
    "sg:province":"Suffolk",
    "sg:tags":[
        "merchant",
        "waste"
    ],
    "wof:name":"SCA Recycling UK",
    "wof:placetype":"venue"
},
  "geometry": {"coordinates":[1.718455,52.47134],"type":"Point"}
}