{
  "type": "Feature",
  "properties": {
    "addr:full":"4 Glebelands, Johnston Haverfordwest Pembrokeshire SA62 3PN",
    "addr:housenumber":"4",
    "addr:postcode":"sa62 3pn",
    "addr:street":"Glebelands Johnston",
    "iso:country":"GB",
    "sg:address":"4 Glebelands, Johnston",
    "sg:city":"Haverfordwest",
    "sg:classifiers":[
        {
            "category":"Food & Beverages",
            "subcategory":"Groceries & Convenience Stores",
            "type":"Retail Goods"
        }
    ],
    "sg:phone":"+44 1437 891663",
    "sg:postcode":"SA62 3PN",
    "sg:province":"Pembrokeshire",
    "wof:name":"The Late Shop",
    "wof:placetype":"venue"
},
  "geometry": {"coordinates":[-4.997662,51.755421],"type":"Point"}
}