{
  "type": "Feature",
  "properties": {
    "addr:full":"23 North End Bedale North Yorkshire DL8 1AF",
    "addr:housenumber":"23",
    "addr:postcode":"dl8 1af",
    "addr:street":"North End",
    "iso:country":"GB",
    "sg:address":"23 North End",
    "sg:city":"Bedale",
    "sg:classifiers":[
        {
            "category":"Shopping",
            "subcategory":"Clothing, Apparel, & Fashions",
            "type":"Retail Goods"
        }
    ],
    "sg:phone":"+44 1677 422583",
    "sg:postcode":"DL8 1AF",
    "sg:province":"North Yorkshire",
    "sg:tags":[
        "ladieswear"
    ],
    "wof:name":"Plumage Too",
    "wof:placetype":"venue"
},
  "geometry": {"coordinates":[-1.593236,54.290146],"type":"Point"}
}