{
  "type": "Feature",
  "properties": {
    "addr:full":"Unit 10, Morley Road Shopping Centre Walsall Staffordshire WS7 9AZ",
    "addr:housenumber":"unit 10",
    "addr:postcode":"ws7 9az",
    "addr:street":"Morley Road",
    "iso:country":"GB",
    "sg:address":"Unit 10, Morley Road Shopping Centre",
    "sg:city":"Walsall",
    "sg:classifiers":[
        {
            "category":"Shopping",
            "subcategory":"Pharmacy",
            "type":"Retail Goods"
        }
    ],
    "sg:phone":"+44 1543 676302",
    "sg:postcode":"WS7 9AZ",
    "sg:province":"Staffordshire",
    "sg:tags":[
        "pharmacist",
        "chemist"
    ],
    "wof:name":"N & J's Chemist",
    "wof:placetype":"venue"
},
  "geometry": {"coordinates":[-1.92119,52.680092],"type":"Point"}
}