{
  "type": "Feature",
  "properties": {
    "addr:full":"Dunedin Road Rainham Essex RM13 8SP",
    "addr:postcode":"rm13 8sp",
    "addr:street":"Dunedin Road",
    "iso:country":"GB",
    "sg:address":"Dunedin Road",
    "sg:city":"Rainham",
    "sg:classifiers":[
        {
            "category":"Education",
            "subcategory":"School",
            "type":"Public Place"
        }
    ],
    "sg:phone":"+44 1708 555554",
    "sg:postcode":"RM13 8SP",
    "sg:province":"Essex",
    "sg:tags":[
        "local",
        "authority"
    ],
    "wof:name":"La Salette R C Primary School",
    "wof:placetype":"venue"
},
  "geometry": {"coordinates":[0.1824299991,51.5233802795],"type":"Point"}
}