{
  "type": "Feature",
  "properties": {
    "iso:country":"GB",
    "sg:address":"27 Ley Lane, Mansfield Woodhouse",
    "sg:city":"Mansfield",
    "sg:classifiers":[
        {
            "category":"Retail",
            "subcategory":"Auto Repair",
            "type":"Services"
        }
    ],
    "sg:postcode":"NG19 8LD",
    "sg:province":"Derbyshire",
    "sg:tags":[
        "modification",
        "garage"
    ],
    "wof:name":"High Street Garage",
    "wof:placetype":"venue"
},
  "geometry": {"coordinates":[-1.1875859499,53.1669960022],"type":"Point"}
}