{
  "type": "Feature",
  "properties": {
    "iso:country":"GB",
    "sg:address":"Unit 8 Indust Est, Victoria Rd",
    "sg:city":"Stanford Le Hope",
    "sg:classifiers":[
        {
            "category":"Wholesale",
            "subcategory":"Furniture",
            "type":"Manufacturing & Wholesale Goods"
        }
    ],
    "sg:phone":"+44 1375 675858",
    "sg:postcode":"SS17 0JE",
    "sg:province":"Essex",
    "sg:tags":[
        "shop",
        "fitting"
    ],
    "wof:name":"Newric Sheet Metal Co",
    "wof:placetype":"venue"
},
  "geometry": {"coordinates":[0.4147500098,51.5136451721],"type":"Point"}
}