{
  "type": "Feature",
  "properties": {
    "addr:full":"20a Moreton Terr London Greater London SW1V 2NX",
    "addr:housenumber":"20a",
    "addr:postcode":"sw1v 2nx",
    "addr:street":"Moreton Terr",
    "iso:country":"GB",
    "sg:address":"20a Moreton Terr",
    "sg:city":"London",
    "sg:classifiers":[
        {
            "category":"Professional",
            "subcategory":"Management & Consulting",
            "type":"Services"
        }
    ],
    "sg:postcode":"SW1V 2NX",
    "sg:province":"Greater London",
    "sg:tags":[
        "consultant",
        "business"
    ],
    "wof:name":"Peet Bennett Associates",
    "wof:placetype":"venue"
},
  "geometry": {"coordinates":[-0.1376609951,51.4892807007],"type":"Point"}
}