{
  "type": "Feature",
  "properties": {
    "addr:full":"Unit 2a Barbican Rise Industrial Estate, Barbican Road Looe Cornwall PL13 1NT",
    "addr:housenumber":"unit 2a;estate",
    "addr:postcode":"pl13 1nt",
    "addr:street":"Barbican Rise Industrial;Barbican Road",
    "iso:country":"GB",
    "sg:address":"Unit 2a Barbican Rise Industrial Estate, Barbican Road",
    "sg:city":"Looe",
    "sg:classifiers":[
        {
            "category":"Manufacturing",
            "subcategory":"Retail Goods",
            "type":"Manufacturing & Wholesale Goods"
        }
    ],
    "sg:phone":"+44 1503 264118",
    "sg:postcode":"PL13 1NT",
    "sg:province":"Cornwall",
    "sg:tags":[
        "chandler"
    ],
    "wof:name":"Fishing Co-Op Uk",
    "wof:placetype":"venue"
},
  "geometry": {"coordinates":[-4.455151,50.357052],"type":"Point"}
}