{
  "type": "Feature",
  "properties": {
    "addr:full":"46-47 Bloomsbury Sq London Greater London WC1A 2RU",
    "addr:housenumber":"46-47",
    "addr:postcode":"wc1a 2ru",
    "addr:street":"Bloomsbury Sq",
    "iso:country":"GB",
    "sg:address":"46-47 Bloomsbury Sq",
    "sg:city":"London",
    "sg:classifiers":[
        {
            "category":"Real Estate",
            "subcategory":"Real Estate Agent",
            "type":"Services"
        }
    ],
    "sg:postcode":"WC1A 2RU",
    "sg:province":"Greater London",
    "wof:name":"Dewmont Properties Management (U K) Ltd",
    "wof:placetype":"venue"
},
  "geometry": {"coordinates":[-0.122002,51.518433],"type":"Point"}
}