{
  "type": "Feature",
  "properties": {
    "addr:full":"Unit 51-53, Concourse House, Dewsbury Road Leeds West Yorkshire LS11 7DF",
    "addr:housenumber":"unit 51-53",
    "addr:postcode":"ls11 7df",
    "addr:street":"Concourse House Dewsbury Road",
    "iso:country":"GB",
    "sg:address":"Unit 51-53, Concourse House, Dewsbury Road",
    "sg:city":"Leeds",
    "sg:classifiers":[
        {
            "category":"Shopping",
            "subcategory":"Stationery & Office Supplies",
            "type":"Retail Goods"
        }
    ],
    "sg:phone":"+44 113 270 5161",
    "sg:postcode":"LS11 7DF",
    "sg:province":"West Yorkshire",
    "sg:tags":[
        "printers'"
    ],
    "wof:name":"The Colour Co. Ltd.",
    "wof:placetype":"venue"
},
  "geometry": {"coordinates":[-1.546587,53.794495],"type":"Point"}
}