{
  "type": "Feature",
  "properties": {
    "addr:full":"27 Croydon Rd, Erdington Birmingham West Midlands B24 8HT",
    "addr:housenumber":"27",
    "addr:postcode":"b24 8ht",
    "addr:street":"Croydon Rd",
    "iso:country":"GB",
    "sg:address":"27 Croydon Rd, Erdington",
    "sg:city":"Birmingham",
    "sg:classifiers":[
        {
            "category":"Professional",
            "subcategory":"Engineering",
            "type":"Services"
        }
    ],
    "sg:phone":"+44 121 240 8133",
    "sg:postcode":"B24 8HT",
    "sg:province":"West Midlands",
    "sg:tags":[
        "contractor",
        "electrical",
        "engineer"
    ],
    "wof:name":"Romac Electrical Services",
    "wof:placetype":"venue"
},
  "geometry": {"coordinates":[-1.839349,52.510513],"type":"Point"}
}