{
  "type": "Feature",
  "properties": {
    "iso:country":"GB",
    "sg:address":"44 New Conduit Street",
    "sg:city":"King's Lynn",
    "sg:classifiers":[
        {
            "category":"Health Services",
            "subcategory":"Optometrist",
            "type":"Services"
        },
        {
            "category":"Shopping",
            "subcategory":"Optical Goods",
            "type":"Retail Goods"
        }
    ],
    "sg:phone":"+44 1553 773610",
    "sg:postcode":"PE30 1DL",
    "sg:province":"Norfolk",
    "sg:tags":[
        "optician"
    ],
    "wof:name":"C B Cartwright Ltd.",
    "wof:placetype":"venue"
},
  "geometry": {"coordinates":[0.395587,52.753696],"type":"Point"}
}