{
  "type": "Feature",
  "properties": {
    "addr:full":"Sackville Place, 44-48 Magdalen St Norwich Norfolk NR3 1JU",
    "addr:housenumber":"44-48",
    "addr:postcode":"nr3 1ju",
    "addr:street":"Sackville;Magdalen St",
    "iso:country":"GB",
    "sg:address":"Sackville Place, 44-48 Magdalen St",
    "sg:city":"Norwich",
    "sg:classifiers":[
        {
            "category":"Real Estate",
            "subcategory":"Real Estate Agent",
            "type":"Services"
        }
    ],
    "sg:phone":"+44 1603 631000",
    "sg:postcode":"NR3 1JU",
    "sg:province":"Norfolk",
    "wof:name":"Anglian Property Management",
    "wof:placetype":"venue"
},
  "geometry": {"coordinates":[1.29408,52.63879],"type":"Point"}
}