{
  "type": "Feature",
  "properties": {
    "iso:country":"GB",
    "sg:address":"5 High Street, Sutton On Sea",
    "sg:city":"Mablethorpe",
    "sg:classifiers":[
        {
            "category":"Home & Garden",
            "subcategory":"Furniture",
            "type":"Retail Goods"
        },
        {
            "category":"Home & Garden",
            "subcategory":"Carpets & Floor Coverings",
            "type":"Retail Goods"
        }
    ],
    "sg:phone":"+44 1507 441005",
    "sg:postcode":"LN12 2ET",
    "sg:province":"Lincolnshire",
    "sg:tags":[
        "retailer",
        "rug"
    ],
    "sg:website":"http://www.squires.info",
    "wof:name":"Squire Furnishings",
    "wof:placetype":"venue"
},
  "geometry": {"coordinates":[0.2828209996,53.3140907288],"type":"Point"}
}