{
  "type": "Feature",
  "properties": {
    "addr:full":"78 Mauchline, East Kilbride Glasgow South Lanarkshire G74 3RZ",
    "addr:housenumber":"78",
    "addr:postcode":"g74 3rz",
    "addr:street":"Mauchline East",
    "iso:country":"GB",
    "sg:address":"78 Mauchline, East Kilbride",
    "sg:city":"Glasgow",
    "sg:classifiers":[
        {
            "category":"Travel",
            "subcategory":"Travel Agent",
            "type":"Entertainment"
        }
    ],
    "sg:phone":"+44 1355 908062",
    "sg:postcode":"G74 3RZ",
    "sg:province":"South Lanarkshire",
    "wof:name":"Bonanza Travel",
    "wof:placetype":"venue"
},
  "geometry": {"coordinates":[-4.1376171112,55.7739868164],"type":"Point"}
}