{
  "type": "Feature",
  "properties": {
    "addr:full":"Widney Close, Bentley Heath Solihull Warwickshire B93 9AS",
    "addr:postcode":"b93 9as",
    "addr:street":"Widney Close",
    "iso:country":"GB",
    "sg:address":"Widney Close, Bentley Heath",
    "sg:city":"Solihull",
    "sg:classifiers":[
        {
            "category":"Education",
            "subcategory":"School",
            "type":"Public Place"
        },
        {
            "category":"Government",
            "subcategory":"Office",
            "type":"Public Place"
        }
    ],
    "sg:phone":"+44 1564 772132",
    "sg:postcode":"B93 9AS",
    "sg:province":"Warwickshire",
    "sg:tags":[
        "local",
        "authority"
    ],
    "wof:name":"Bentley Heath C of E Primary School",
    "wof:placetype":"venue"
},
  "geometry": {"coordinates":[-1.7581529617,52.3852920532],"type":"Point"}
}