{
  "type": "Feature",
  "properties": {
    "addr:full":"Woodborough Road Nottingham Nottinghamshire NG3 1AX",
    "addr:postcode":"ng3 1ax",
    "addr:street":"Woodborough Road",
    "iso:country":"GB",
    "sg:address":"Woodborough Road",
    "sg:city":"Nottingham",
    "sg:classifiers":[
        {
            "category":"Shopping",
            "subcategory":"Bicycles & Sporting Goods",
            "type":"Retail Goods"
        }
    ],
    "sg:phone":"+44 115 958 5900",
    "sg:postcode":"NG3 1AX",
    "sg:province":"Nottinghamshire",
    "sg:tags":[
        "cycle",
        "accessory"
    ],
    "wof:name":"Hawk Factory Cycle Stores Ltd.",
    "wof:placetype":"venue"
},
  "geometry": {"coordinates":[-1.147986,52.960312],"type":"Point"}
}