{
  "type": "Feature",
  "properties": {
    "addr:full":"7-14 Green Park Business Centre, Sutton On The Forest York North Yorkshire YO61 1ET",
    "addr:housenumber":"7-14",
    "addr:postcode":"yo61 1et",
    "addr:street":"Green Park",
    "iso:country":"GB",
    "sg:address":"7-14 Green Park Business Centre, Sutton On The Forest",
    "sg:city":"York",
    "sg:classifiers":[
        {
            "category":"Communications",
            "type":"Services"
        }
    ],
    "sg:phone":"+44 1347 811111",
    "sg:postcode":"YO61 1ET",
    "sg:province":"North Yorkshire",
    "sg:tags":[
        "broadcasting"
    ],
    "wof:name":"Hi-Q Broadcast Ltd.",
    "wof:placetype":"venue"
},
  "geometry": {"coordinates":[-1.107176,54.074821],"type":"Point"}
}