{
  "type": "Feature",
  "properties": {
    "addr:full":"Kingsford Manor, Kentisbeare Cullompton Devon EX15 2AU",
    "addr:postcode":"ex15 2au",
    "addr:street":"Kingsford",
    "iso:country":"GB",
    "sg:address":"Kingsford Manor, Kentisbeare",
    "sg:city":"Cullompton",
    "sg:classifiers":[
        {
            "category":"Farming",
            "subcategory":"Livestock Farm",
            "type":"Manufacturing & Wholesale Goods"
        },
        {
            "category":"Farming",
            "subcategory":"Farm",
            "type":"Manufacturing & Wholesale Goods"
        }
    ],
    "sg:phone":"+44 1884 266223",
    "sg:postcode":"EX15 2AU",
    "sg:province":"Devon",
    "sg:tags":[
        "mixed",
        "others"
    ],
    "wof:name":"S & H Frost",
    "wof:placetype":"venue"
},
  "geometry": {"coordinates":[-3.328136,50.865486],"type":"Point"}
}