{
  "type": "Feature",
  "properties": {
    "addr:full":"121 High Street Musselburgh City of Edinburgh EH21 7DA",
    "addr:housenumber":"121",
    "addr:postcode":"eh21 7da",
    "addr:street":"High Street",
    "iso:country":"GB",
    "sg:address":"121 High Street",
    "sg:city":"Musselburgh",
    "sg:classifiers":[
        {
            "category":"Shopping",
            "subcategory":"Pharmacy",
            "type":"Retail Goods"
        }
    ],
    "sg:phone":"+44 131 653 2577",
    "sg:postcode":"EH21 7DA",
    "sg:province":"City of Edinburgh",
    "sg:tags":[
        "pharmacist",
        "chemist"
    ],
    "wof:name":"Lindsay & Gilmour",
    "wof:placetype":"venue"
},
  "geometry": {"coordinates":[-3.0508069992,55.9427375793],"type":"Point"}
}