{
  "type": "Feature",
  "properties": {
    "iso:country":"GB",
    "sg:address":"Treffgarne Hall Treffgarne",
    "sg:city":"Haverfordwest",
    "sg:classifiers":[
        {
            "category":"Shopping",
            "type":"Retail Goods"
        }
    ],
    "sg:phone":"+44 1437 741777",
    "sg:postcode":"SA62 5PJ",
    "sg:province":"Pembrokeshire",
    "sg:tags":[
        "part",
        "accessory"
    ],
    "wof:name":"Kartray Enterprises",
    "wof:placetype":"venue"
},
  "geometry": {"coordinates":[-4.969418,51.873726],"type":"Point"}
}