{
  "type": "Feature",
  "properties": {
    "iso:country":"GB",
    "sg:address":"Long Meadow Works, Ringwood Road, Three Legged Cross",
    "sg:city":"Wimborne",
    "sg:classifiers":[
        {
            "category":"Building & Trades",
            "subcategory":"Equipment Rental",
            "type":"Services"
        }
    ],
    "sg:phone":"+44 1202 823213",
    "sg:postcode":"BH21 6RD",
    "sg:province":"Dorset",
    "sg:tags":[
        "plant",
        "machinery"
    ],
    "wof:name":"Eddie Moors Plant Hire Ltd.",
    "wof:placetype":"venue"
},
  "geometry": {"coordinates":[-1.884271,50.850346],"type":"Point"}
}