{
  "type": "Feature",
  "properties": {
    "iso:country":"GB",
    "sg:address":"128 Street La, Gildersome",
    "sg:city":"Leeds",
    "sg:classifiers":[
        {
            "category":"Cinema",
            "subcategory":"Movie Rental",
            "type":"Entertainment"
        }
    ],
    "sg:phone":"+44 113 252 0969",
    "sg:postcode":"LS27 7JB",
    "sg:province":"West Yorkshire",
    "sg:tags":[
        "video",
        "library"
    ],
    "wof:name":"Square Eyes Gildi Video",
    "wof:placetype":"venue"
},
  "geometry": {"coordinates":[-1.6330690384,53.7571487427],"type":"Point"}
}