{
  "type": "Feature",
  "properties": {
    "addr:full":"Harmondsworth Road West Drayton Greater London UB7 9JS",
    "addr:postcode":"ub7 9js",
    "addr:street":"Harmondsworth Road",
    "iso:country":"GB",
    "sg:address":"Harmondsworth Road",
    "sg:city":"West Drayton",
    "sg:classifiers":[
        {
            "category":"Home & Garden",
            "subcategory":"Garden Supply",
            "type":"Retail Goods"
        }
    ],
    "sg:phone":"+44 20 8759 3010",
    "sg:postcode":"UB7 9JS",
    "sg:province":"Greater London",
    "sg:tags":[
        "nursery",
        "centre"
    ],
    "wof:name":"John Train Plants",
    "wof:placetype":"venue"
},
  "geometry": {"coordinates":[-0.466987,51.50251],"type":"Point"}
}