{
  "type": "Feature",
  "properties": {
    "addr:full":"Crabtree Farm, 3a Stratford Road, Bidford-on-avon Alcester Warwickshire B50 4LL",
    "addr:housenumber":"3a",
    "addr:postcode":"b50 4ll",
    "addr:street":"Stratford Road",
    "iso:country":"GB",
    "sg:address":"Crabtree Farm, 3a Stratford Road, Bidford-on-avon",
    "sg:city":"Alcester",
    "sg:classifiers":[
        {
            "category":"Shopping",
            "subcategory":"Department Store",
            "type":"Retail Goods"
        },
        {
            "category":"Home & Garden",
            "subcategory":"Garden Supply",
            "type":"Retail Goods"
        },
        {
            "category":"Food & Beverages",
            "subcategory":"Farmers Market",
            "type":"Retail Goods"
        }
    ],
    "sg:phone":"+44 1789 773497",
    "sg:postcode":"B50 4LL",
    "sg:province":"Warwickshire",
    "sg:tags":[
        "shop",
        "farm",
        "nursery",
        "pyo",
        "centre"
    ],
    "wof:name":"P R Morris & Co.",
    "wof:placetype":"venue"
},
  "geometry": {"coordinates":[-1.860054,52.164616],"type":"Point"}
}