{
  "type": "Feature",
  "properties": {
    "addr:full":"220 Moulsham St Chelmsford Essex CM2 0LS",
    "addr:housenumber":"220",
    "addr:postcode":"cm2 0ls",
    "addr:street":"Moulsham St",
    "iso:country":"GB",
    "sg:address":"220 Moulsham St",
    "sg:city":"Chelmsford",
    "sg:classifiers":[
        {
            "category":"Travel",
            "subcategory":"Travel Agent",
            "type":"Entertainment"
        }
    ],
    "sg:phone":"+44 1245 490290",
    "sg:postcode":"CM2 0LS",
    "sg:province":"Essex",
    "wof:name":"Co-Op Travel Centre",
    "wof:placetype":"venue"
},
  "geometry": {"coordinates":[0.473789,51.730984],"type":"Point"}
}