{
  "type": "Feature",
  "properties": {
    "iso:country":"GB",
    "sg:address":"16 New Chapel Street",
    "sg:city":"Blackburn",
    "sg:classifiers":[
        {
            "category":"Professional",
            "type":"Services"
        }
    ],
    "sg:phone":"+44 1254 661297",
    "sg:postcode":"BB2 2RD",
    "sg:province":"Lancashire",
    "sg:tags":[
        "entertainer"
    ],
    "wof:name":"Whodeano the Magician",
    "wof:placetype":"venue"
},
  "geometry": {"coordinates":[-2.503292,53.735901],"type":"Point"}
}