{
  "type": "Feature",
  "properties": {
    "iso:country":"GB",
    "sg:address":"190 Pilton Vale, Malpas",
    "sg:city":"Newport",
    "sg:classifiers":[
        {
            "category":"Manufacturing",
            "subcategory":"Petroleum Products",
            "type":"Manufacturing & Wholesale Goods"
        }
    ],
    "sg:phone":"+44 1633 859921",
    "sg:postcode":"NP20 6LN",
    "sg:province":"Newport",
    "sg:tags":[
        "double",
        "glazing"
    ],
    "wof:name":"C Crawley",
    "wof:placetype":"venue"
},
  "geometry": {"coordinates":[-2.9993340969,51.6153450012],"type":"Point"}
}