{
  "type": "Feature",
  "properties": {
    "addr:full":"453 Great Western Road Glasgow Glasgow City G12 8HH",
    "addr:housenumber":"453",
    "addr:postcode":"g12 8hh",
    "addr:street":"Great Western Road",
    "iso:country":"GB",
    "sg:address":"453 Great Western Road",
    "sg:city":"Glasgow",
    "sg:classifiers":[
        {
            "category":"Home & Garden",
            "subcategory":"Building Materials",
            "type":"Retail Goods"
        }
    ],
    "sg:phone":"+44 141 334 3300",
    "sg:postcode":"G12 8HH",
    "sg:province":"Glasgow City",
    "sg:tags":[
        "hinge"
    ],
    "wof:name":"G L R Stores",
    "wof:placetype":"venue"
},
  "geometry": {"coordinates":[-4.28127,55.875107],"type":"Point"}
}