{
  "type": "Feature",
  "properties": {
    "addr:full":"16 London Road Stanford-le-hope Essex SS17 0LD",
    "addr:housenumber":"16",
    "addr:postcode":"ss17 0ld",
    "addr:street":"London Road",
    "iso:country":"GB",
    "sg:address":"16 London Road",
    "sg:city":"Stanford-le-hope",
    "sg:classifiers":[
        {
            "category":"Autos & Motor Vehicles",
            "subcategory":"Automobile Sales",
            "type":"Retail Goods"
        }
    ],
    "sg:phone":"+44 1375 644405",
    "sg:postcode":"SS17 0LD",
    "sg:province":"Essex",
    "sg:tags":[
        "car"
    ],
    "wof:name":"Barry Ottley Motor Co",
    "wof:placetype":"venue"
},
  "geometry": {"coordinates":[0.420655,51.51424],"type":"Point"}
}