{
  "type": "Feature",
  "properties": {
    "iso:country":"GB",
    "sg:address":"15 St Mary Street",
    "sg:city":"Kirkcudbright",
    "sg:classifiers":[
        {
            "category":"Personal",
            "subcategory":"Beauty Salon",
            "type":"Services"
        },
        {
            "category":"Personal",
            "subcategory":"Barber",
            "type":"Services"
        }
    ],
    "sg:phone":"+44 1557 330982",
    "sg:postcode":"DG6 4AA",
    "sg:province":"Dumfries and Galloway",
    "sg:tags":[
        "unisex",
        "hairdresser"
    ],
    "wof:name":"Maurice Halliday Hair & Beauty Salons",
    "wof:placetype":"venue"
},
  "geometry": {"coordinates":[-4.044148922,54.8412361145],"type":"Point"}
}