{
  "type": "Feature",
  "properties": {
    "iso:country":"GB",
    "sg:address":"3-5 Commercial Gate",
    "sg:city":"Mansfield",
    "sg:classifiers":[
        {
            "category":"Professional",
            "subcategory":"Accounting & Tax Preparation",
            "type":"Services"
        }
    ],
    "sg:phone":"+44 1623 623248",
    "sg:postcode":"NG18 1EJ",
    "sg:province":"Nottinghamshire",
    "sg:tags":[
        "accountant",
        "activity"
    ],
    "wof:name":"Wall & Partners",
    "wof:placetype":"venue"
},
  "geometry": {"coordinates":[-1.196275,53.140766],"type":"Point"}
}