{
  "type": "Feature",
  "properties": {
    "addr:full":"51 Park Avenue Flint Flintshire CH6 5DW",
    "addr:housenumber":"51",
    "addr:postcode":"ch6 5dw",
    "addr:street":"Park Avenue",
    "iso:country":"GB",
    "sg:address":"51 Park Avenue",
    "sg:city":"Flint",
    "sg:classifiers":[
        {
            "category":"Home & Garden",
            "subcategory":"Household Appliances",
            "type":"Retail Goods"
        }
    ],
    "sg:postcode":"CH6 5DW",
    "sg:province":"Flintshire",
    "sg:tags":[
        "electrical"
    ],
    "wof:name":"B S Refrigeration",
    "wof:placetype":"venue"
},
  "geometry": {"coordinates":[-3.132633,53.246426],"type":"Point"}
}