{
  "type": "Feature",
  "properties": {
    "addr:full":"1 Launceston Ho, Launceston Rd Wigston Leicestershire LE18 2GL",
    "addr:housenumber":"1",
    "addr:postcode":"le18 2gl",
    "addr:street":"Launceston Ho Launceston Rd",
    "iso:country":"GB",
    "sg:address":"1 Launceston Ho, Launceston Rd",
    "sg:city":"Wigston",
    "sg:classifiers":[
        {
            "category":"Food & Beverages",
            "subcategory":"Meat & Fish",
            "type":"Retail Goods"
        }
    ],
    "sg:postcode":"LE18 2GL",
    "sg:province":"Leicestershire",
    "sg:tags":[
        "chip"
    ],
    "wof:name":"Chu,K S & S T,",
    "wof:placetype":"venue"
},
  "geometry": {"coordinates":[-1.111689,52.583035],"type":"Point"}
}