{
  "type": "Feature",
  "properties": {
    "addr:full":"275 Arbury Road Nuneaton Leicestershire CV10 7NQ",
    "addr:housenumber":"275",
    "addr:postcode":"cv10 7nq",
    "addr:street":"Arbury Road",
    "iso:country":"GB",
    "sg:address":"275 Arbury Road",
    "sg:city":"Nuneaton",
    "sg:classifiers":[
        {
            "category":"Autos & Motor Vehicles",
            "subcategory":"Fuel & Gas Station",
            "type":"Retail Goods"
        }
    ],
    "sg:postcode":"CV10 7NQ",
    "sg:province":"Leicestershire",
    "sg:tags":[
        "petrol",
        "filling"
    ],
    "wof:name":"P M Service Stations",
    "wof:placetype":"venue"
},
  "geometry": {"coordinates":[-1.505183,52.51569],"type":"Point"}
}