{
  "type": "Feature",
  "properties": {
    "addr:full":"97 Southcote Rd Reading Berkshire RG30 2AA",
    "addr:housenumber":"97",
    "addr:postcode":"rg30 2aa",
    "addr:street":"Southcote Rd",
    "iso:country":"GB",
    "sg:address":"97 Southcote Rd",
    "sg:city":"Reading",
    "sg:classifiers":[
        {
            "category":"Recreation",
            "subcategory":"Fishing",
            "type":"Entertainment"
        }
    ],
    "sg:phone":"+44 118 950 2585",
    "sg:postcode":"RG30 2AA",
    "sg:province":"Berkshire",
    "sg:tags":[
        "angling"
    ],
    "wof:name":"Frank J Wallace",
    "wof:placetype":"venue"
},
  "geometry": {"coordinates":[-0.9948509932,51.4515571594],"type":"Point"}
}