{
  "type": "Feature",
  "properties": {
    "iso:country":"GB",
    "sg:address":"108 Rowan Rd",
    "sg:city":"London",
    "sg:classifiers":[
        {
            "category":"Professional",
            "subcategory":"Management & Consulting",
            "type":"Services"
        }
    ],
    "sg:postcode":"SW16 5JQ",
    "sg:province":"Greater London",
    "sg:tags":[
        "consultant",
        "business"
    ],
    "wof:name":"Jilanda Ltd",
    "wof:placetype":"venue"
},
  "geometry": {"coordinates":[-0.140862,51.407108],"type":"Point"}
}