{
  "type": "Feature",
  "properties": {
    "addr:full":"Flowerdale, Bow St Langport Somerset TA10 9PG",
    "addr:postcode":"ta10 9pg",
    "addr:street":"Flowerdale Bow St",
    "iso:country":"GB",
    "sg:address":"Flowerdale, Bow St",
    "sg:city":"Langport",
    "sg:classifiers":[
        {
            "category":"Shopping",
            "subcategory":"Clothing, Apparel, & Fashions",
            "type":"Retail Goods"
        }
    ],
    "sg:phone":"+44 1458 253987",
    "sg:postcode":"TA10 9PG",
    "sg:province":"Somerset",
    "sg:tags":[
        "shop",
        "hat"
    ],
    "wof:name":"Dat Hat",
    "wof:placetype":"venue"
},
  "geometry": {"coordinates":[-2.824284,51.042049],"type":"Point"}
}