{
  "type": "Feature",
  "properties": {
    "addr:full":"Forest Trading Estate, 1 Priestley Way London Greater London E17 6AL",
    "addr:housenumber":"1",
    "addr:postcode":"e17 6al",
    "addr:street":"Priestley Way",
    "iso:country":"GB",
    "sg:address":"Forest Trading Estate, 1 Priestley Way",
    "sg:city":"London",
    "sg:classifiers":[
        {
            "category":"Food & Beverages",
            "subcategory":"Liquor & Beverages",
            "type":"Retail Goods"
        }
    ],
    "sg:phone":"+44 20 8527 7660",
    "sg:postcode":"E17 6AL",
    "sg:province":"Greater London",
    "sg:tags":[
        "drink",
        "soft"
    ],
    "wof:name":"Barr Soft Drinks",
    "wof:placetype":"venue"
},
  "geometry": {"coordinates":[-0.0319599994,51.5931510925],"type":"Point"}
}