{
  "type": "Feature",
  "properties": {
    "iso:country":"GB",
    "sg:address":"Gatenby Grange, Gatenby",
    "sg:city":"Northallerton",
    "sg:classifiers":[
        {
            "category":"Farming",
            "subcategory":"Farm",
            "type":"Manufacturing & Wholesale Goods"
        }
    ],
    "sg:postcode":"DL7 9NG",
    "sg:province":"North Yorkshire",
    "sg:tags":[
        "mixed",
        "crop"
    ],
    "wof:name":"H Harrison & Son",
    "wof:placetype":"venue"
},
  "geometry": {"coordinates":[-1.507428,54.287033],"type":"Point"}
}