{
  "type": "Feature",
  "properties": {
    "iso:country":"GB",
    "sg:address":"22 St Margarets Drive, Sibsey",
    "sg:city":"Boston",
    "sg:classifiers":[
        {
            "category":"Personal",
            "type":"Services"
        }
    ],
    "sg:postcode":"PE22 0ST",
    "sg:province":"Lincolnshire",
    "sg:tags":[
        "tailor"
    ],
    "wof:name":"Smalley's Tailoring Services",
    "wof:placetype":"venue"
},
  "geometry": {"coordinates":[0.0097629996,53.0392684937],"type":"Point"}
}