{
  "type": "Feature",
  "properties": {
    "iso:country":"GB",
    "sg:address":"93 Bryanston Road",
    "sg:city":"Solihull",
    "sg:classifiers":[
        {
            "category":"Shopping",
            "type":"Retail Goods"
        }
    ],
    "sg:postcode":"B91 1BS",
    "sg:province":"West Midlands",
    "sg:tags":[
        "part",
        "accessory"
    ],
    "wof:name":"Essential Car Parts",
    "wof:placetype":"venue"
},
  "geometry": {"coordinates":[-1.800987,52.425659],"type":"Point"}
}