{
  "type": "Feature",
  "properties": {
    "addr:full":"17 Hoppet La Manchester Greater Manchester M43 7GN",
    "addr:housenumber":"17",
    "addr:postcode":"m43 7gn",
    "addr:street":"Hoppet La Manchester",
    "iso:country":"GB",
    "sg:address":"17 Hoppet La",
    "sg:city":"Manchester",
    "sg:classifiers":[
        {
            "category":"Professional",
            "subcategory":"Accounting & Tax Preparation",
            "type":"Services"
        }
    ],
    "sg:phone":"+44 161 301 5387",
    "sg:postcode":"M43 7GN",
    "sg:province":"Greater Manchester",
    "sg:tags":[
        "accountant"
    ],
    "wof:name":"A E Spratling",
    "wof:placetype":"venue"
},
  "geometry": {"coordinates":[-2.1333520412,53.4866447449],"type":"Point"}
}