{
  "type": "Feature",
  "properties": {
    "addr:full":"25 Market Place Westbury Wiltshire BA13 3DQ",
    "addr:housenumber":"25",
    "addr:postcode":"ba13 3dq",
    "addr:street":"Market Place",
    "iso:country":"GB",
    "sg:address":"25 Market Place",
    "sg:city":"Westbury",
    "sg:classifiers":[
        {
            "category":"Fast Food",
            "type":"Food & Drink"
        }
    ],
    "sg:phone":"+44 1373 822857",
    "sg:postcode":"BA13 3DQ",
    "sg:province":"Wiltshire",
    "sg:tags":[
        "away",
        "meal",
        "outlet",
        "take"
    ],
    "wof:name":"Olympia Takeaway",
    "wof:placetype":"venue"
},
  "geometry": {"coordinates":[-2.182199,51.262844],"type":"Point"}
}