{
  "type": "Feature",
  "properties": {
    "addr:full":"1 Fore Street Hexham Northumberland NE46 1ND",
    "addr:housenumber":"1",
    "addr:postcode":"ne46 1nd",
    "addr:street":"Fore Street",
    "iso:country":"GB",
    "sg:address":"1 Fore Street",
    "sg:city":"Hexham",
    "sg:classifiers":[
        {
            "category":"Professional",
            "subcategory":"Engineering",
            "type":"Services"
        }
    ],
    "sg:postcode":"NE46 1ND",
    "sg:province":"Northumberland",
    "sg:tags":[
        "design",
        "engineer"
    ],
    "wof:name":"B T Bell Associates Ltd.",
    "wof:placetype":"venue"
},
  "geometry": {"coordinates":[-2.1012439728,54.9715805054],"type":"Point"}
}