{
  "type": "Feature",
  "properties": {
    "addr:full":"Gemini House, Bartholomew Walk Ely Cambridgeshire CB7 4EA",
    "addr:postcode":"cb7 4ea",
    "addr:street":"Bartholomew Walk",
    "iso:country":"GB",
    "sg:address":"Gemini House, Bartholomew Walk",
    "sg:city":"Ely",
    "sg:classifiers":[
        {
            "category":"Shopping",
            "subcategory":"Pharmacy",
            "type":"Retail Goods"
        },
        {
            "category":"Government",
            "subcategory":"Post Office",
            "type":"Public Place"
        }
    ],
    "sg:postcode":"CB7 4EA",
    "sg:province":"Cambridgeshire",
    "sg:tags":[
        "pharmaceutical",
        "organisation",
        "soc",
        "research"
    ],
    "wof:name":"Elan Transdermal Technologies (Uk) Ltd",
    "wof:placetype":"venue"
},
  "geometry": {"coordinates":[0.2621450126,52.3900146484],"type":"Point"}
}