{
  "type": "Feature",
  "properties": {
    "addr:full":"Pheasants Nest Farm, Smorrall La  Bedworth Nuneaton Warwickshire CV12 0NL",
    "addr:housenumber":"pheasants nest farm",
    "addr:postcode":"cv12 0nl",
    "addr:street":"Smorrall La Bedworth",
    "iso:country":"GB",
    "sg:address":"Pheasants Nest Farm, Smorrall La  Bedworth",
    "sg:city":"Nuneaton",
    "sg:classifiers":[
        {
            "category":"Farming",
            "subcategory":"Farm",
            "type":"Manufacturing & Wholesale Goods"
        }
    ],
    "sg:postcode":"CV12 0NL",
    "sg:province":"Warwickshire",
    "sg:tags":[
        "mixed",
        "crop"
    ],
    "wof:name":"Kay,William,",
    "wof:placetype":"venue"
},
  "geometry": {"coordinates":[-1.506442,52.47419],"type":"Point"}
}