{
  "type": "Feature",
  "properties": {
    "addr:full":"154 Market Street, Hindley Wigan Lancashire WN2 3AY",
    "addr:housenumber":"154",
    "addr:postcode":"wn2 3ay",
    "addr:street":"Market Street",
    "iso:country":"GB",
    "sg:address":"154 Market Street, Hindley",
    "sg:city":"Wigan",
    "sg:classifiers":[
        {
            "category":"Building & Trades",
            "subcategory":"Construction",
            "type":"Services"
        },
        {
            "category":"Home & Garden",
            "subcategory":"Carpets & Floor Coverings",
            "type":"Retail Goods"
        }
    ],
    "sg:phone":"+44 1942 253910",
    "sg:postcode":"WN2 3AY",
    "sg:province":"Lancashire",
    "sg:tags":[
        "textile",
        "flooring",
        "floorcoverings"
    ],
    "wof:name":"T P & J A Culshaw",
    "wof:placetype":"venue"
},
  "geometry": {"coordinates":[-2.58058,53.534138],"type":"Point"}
}