{
  "type": "Feature",
  "properties": {
    "iso:country":"GB",
    "sg:address":"Anchor Buildings, Westgate",
    "sg:city":"Morecambe",
    "sg:classifiers":[
        {
            "category":"Manufacturing",
            "subcategory":"Retail Goods",
            "type":"Manufacturing & Wholesale Goods"
        }
    ],
    "sg:phone":"+44 1524 862010",
    "sg:postcode":"LA3 3DH",
    "sg:province":"Lancashire",
    "sg:tags":[
        "chandler"
    ],
    "wof:name":"Mrs J C Altham & Sons (Lancaster) Ltd.",
    "wof:placetype":"venue"
},
  "geometry": {"coordinates":[-2.84805,54.061798],"type":"Point"}
}