{
  "type": "Feature",
  "properties": {
    "iso:country":"GB",
    "sg:address":"Marshall House, Wymans Lane, Swindon Village",
    "sg:city":"Cheltenham",
    "sg:classifiers":[
        {
            "category":"Home & Garden",
            "subcategory":"Household Appliances",
            "type":"Retail Goods"
        }
    ],
    "sg:postcode":"GL51 9QF",
    "sg:province":"Gloucestershire",
    "sg:tags":[
        "electrical"
    ],
    "wof:name":"Classic Services",
    "wof:placetype":"venue"
},
  "geometry": {"coordinates":[-2.095149,51.925465],"type":"Point"}
}