{
  "type": "Feature",
  "properties": {
    "addr:full":"40 Carlton Place Glasgow Glasgow City G5 9TW",
    "addr:housenumber":"40",
    "addr:postcode":"g5 9tw",
    "addr:street":"Carlton Place",
    "iso:country":"GB",
    "sg:address":"40 Carlton Place",
    "sg:city":"Glasgow",
    "sg:classifiers":[
        {
            "category":"Professional",
            "subcategory":"Detective & Security Services",
            "type":"Services"
        }
    ],
    "sg:phone":"+44 141 429 4716",
    "sg:postcode":"G5 9TW",
    "sg:province":"Glasgow City",
    "sg:tags":[
        "agency"
    ],
    "wof:name":"J.W Trace Investigations",
    "wof:placetype":"venue"
},
  "geometry": {"coordinates":[-4.2545051575,55.8537406921],"type":"Point"}
}