{
  "type": "Feature",
  "properties": {
    "addr:full":"Chapel St Inverness Highland IV1 1NA",
    "addr:postcode":"iv1 1na",
    "addr:street":"Chapel St",
    "iso:country":"GB",
    "sg:address":"Chapel St",
    "sg:city":"Inverness",
    "sg:classifiers":[
        {
            "category":"Autos & Motor Vehicles",
            "subcategory":"Fuel & Gas Station",
            "type":"Retail Goods"
        }
    ],
    "sg:phone":"+44 1463 220011",
    "sg:postcode":"IV1 1NA",
    "sg:province":"Highland",
    "sg:tags":[
        "hr",
        "petrol"
    ],
    "wof:name":"Cromwells Tower Filling Station",
    "wof:placetype":"venue"
},
  "geometry": {"coordinates":[-4.229365,57.481392],"type":"Point"}
}