{
  "type": "Feature",
  "properties": {
    "iso:country":"GB",
    "sg:address":"4 Empiress Court",
    "sg:city":"Greenock",
    "sg:classifiers":[
        {
            "category":"Real Estate",
            "subcategory":"Real Estate Operator",
            "type":"Services"
        },
        {
            "category":"Building & Trades",
            "subcategory":"Cleaning & Sanitation",
            "type":"Services"
        }
    ],
    "sg:phone":"+44 1475 730202",
    "sg:postcode":"PA15 4RW",
    "sg:province":"Inverclyde",
    "sg:tags":[
        "letting",
        "commercial",
        "agent"
    ],
    "wof:name":"Patrick Bryceland Ltd.",
    "wof:placetype":"venue"
},
  "geometry": {"coordinates":[-4.746419,55.943802],"type":"Point"}
}