{
  "type": "Feature",
  "properties": {
    "addr:full":"Penhyddwaelod Farm, Bryn Port Talbot Neath Port Talbot SA13 2RB",
    "addr:postcode":"sa13 2rb",
    "addr:street":"Bryn;Talbot",
    "iso:country":"GB",
    "sg:address":"Penhyddwaelod Farm, Bryn",
    "sg:city":"Port Talbot",
    "sg:classifiers":[
        {
            "category":"Farming",
            "subcategory":"Livestock Farm",
            "type":"Manufacturing & Wholesale Goods"
        }
    ],
    "sg:phone":"+44 1639 896485",
    "sg:postcode":"SA13 2RB",
    "sg:province":"Neath Port Talbot",
    "sg:tags":[
        "others"
    ],
    "wof:name":"E J Allen",
    "wof:placetype":"venue"
},
  "geometry": {"coordinates":[-3.715499,51.616058],"type":"Point"}
}