{
  "type": "Feature",
  "properties": {
    "iso:country":"GB",
    "sg:address":"Albion Road",
    "sg:city":"Rochdale",
    "sg:classifiers":[
        {
            "category":"Professional",
            "subcategory":"Engineering",
            "type":"Services"
        }
    ],
    "sg:phone":"+44 1706 641484",
    "sg:postcode":"OL11 4HQ",
    "sg:province":"Lancashire",
    "sg:tags":[
        "civil",
        "engineer"
    ],
    "wof:name":"J  Cooney Ltd.",
    "wof:placetype":"venue"
},
  "geometry": {"coordinates":[-2.169664,53.612213],"type":"Point"}
}