{
  "type": "Feature",
  "properties": {
    "iso:country":"GB",
    "sg:address":"2nd Floor, India House, 45 Curlew Street",
    "sg:city":"London",
    "sg:classifiers":[
        {
            "category":"Organizations",
            "subcategory":"Community Association",
            "type":"Services"
        }
    ],
    "sg:phone":"+44 20 7403 7500",
    "sg:postcode":"SE1 2ND",
    "sg:province":"Greater London",
    "sg:tags":[
        "relation",
        "public"
    ],
    "wof:name":"V L P Ltd.",
    "wof:placetype":"venue"
},
  "geometry": {"coordinates":[-0.074287,51.502453],"type":"Point"}
}