{
  "type": "Feature",
  "properties": {
    "addr:full":"1 Mill Lane Chesterfield Derbyshire S42 5AA",
    "addr:housenumber":"1",
    "addr:postcode":"s42 5aa",
    "addr:street":"Mill Lane",
    "iso:country":"GB",
    "sg:address":"1 Mill Lane",
    "sg:city":"Chesterfield",
    "sg:classifiers":[
        {
            "category":"Shopping",
            "subcategory":"Department Store",
            "type":"Retail Goods"
        }
    ],
    "sg:phone":"+44 1246 850496",
    "sg:postcode":"S42 5AA",
    "sg:province":"Derbyshire",
    "wof:name":"Del & Sue's",
    "wof:placetype":"venue"
},
  "geometry": {"coordinates":[-1.3967260122,53.1985931396],"type":"Point"}
}