{
  "type": "Feature",
  "properties": {
    "addr:full":"Sighthill Health Centre, 380 Calder Rd Edinburgh City of Edinburgh EH11 4AU",
    "addr:housenumber":"380",
    "addr:postcode":"eh11 4au",
    "addr:street":"Calder Rd",
    "iso:country":"GB",
    "sg:address":"Sighthill Health Centre, 380 Calder Rd",
    "sg:city":"Edinburgh",
    "sg:classifiers":[
        {
            "category":"Health Services",
            "subcategory":"Doctor",
            "type":"Services"
        }
    ],
    "sg:phone":"+44 131 537 7090",
    "sg:postcode":"EH11 4AU",
    "sg:province":"City of Edinburgh",
    "sg:tags":[
        "practitioners"
    ],
    "wof:name":"Gordon Scott",
    "wof:placetype":"venue"
},
  "geometry": {"coordinates":[-3.292299,55.924416],"type":"Point"}
}