{
  "type": "Feature",
  "properties": {
    "addr:full":"Latheronwheel Latheron Highland KW5 6DW",
    "addr:postcode":"kw5 6dw",
    "addr:street":"Highland",
    "iso:country":"GB",
    "sg:address":"Latheronwheel",
    "sg:city":"Latheron",
    "sg:classifiers":[
        {
            "category":"Shopping",
            "subcategory":"Florist",
            "type":"Retail Goods"
        }
    ],
    "sg:phone":"+44 1593 741345",
    "sg:postcode":"KW5 6DW",
    "sg:province":"Highland",
    "wof:name":"Petals",
    "wof:placetype":"venue"
},
  "geometry": {"coordinates":[-3.3675808907,58.2837524414],"type":"Point"}
}