{
  "type": "Feature",
  "properties": {
    "addr:full":"New Factory Woods La, Cradley Heath Cradley Heath West Midlands B64 7AA",
    "addr:postcode":"b64 7aa",
    "addr:street":"Woods La Cradley",
    "iso:country":"GB",
    "sg:address":"New Factory Woods La, Cradley Heath",
    "sg:city":"Cradley Heath",
    "sg:classifiers":[
        {
            "category":"Manufacturing",
            "subcategory":"Metals",
            "type":"Manufacturing & Wholesale Goods"
        }
    ],
    "sg:phone":"+44 1384 634111",
    "sg:postcode":"B64 7AA",
    "sg:province":"West Midlands",
    "wof:name":"Bronze & Chrome Ltd",
    "wof:placetype":"venue"
},
  "geometry": {"coordinates":[-2.0815739632,52.4724159241],"type":"Point"}
}