{
  "type": "Feature",
  "properties": {
    "iso:country":"GB",
    "sg:address":"20 Sidmouth Avenue",
    "sg:city":"Isleworth",
    "sg:classifiers":[
        {
            "category":"Building & Trades",
            "subcategory":"Construction",
            "type":"Services"
        }
    ],
    "sg:phone":"+44 20 8560 5411",
    "sg:postcode":"TW7 4DW",
    "sg:province":"Greater London",
    "sg:tags":[
        "builder"
    ],
    "wof:name":"Ted Kopcinski",
    "wof:placetype":"venue"
},
  "geometry": {"coordinates":[-0.34073,51.473831],"type":"Point"}
}