{
  "type": "Feature",
  "properties": {
    "addr:full":"17-19 Military Rd Chatham Kent ME4 4JG",
    "addr:housenumber":"17-19",
    "addr:postcode":"me4 4jg",
    "addr:street":"Military Rd",
    "iso:country":"GB",
    "sg:address":"17-19 Military Rd",
    "sg:city":"Chatham",
    "sg:classifiers":[
        {
            "category":"Professional",
            "subcategory":"Lawyer & Legal Services",
            "type":"Services"
        }
    ],
    "sg:phone":"+44 1634 405349",
    "sg:postcode":"ME4 4JG",
    "sg:province":"Kent",
    "sg:tags":[
        "advice",
        "counselling"
    ],
    "wof:name":"Medway Housing Link",
    "wof:placetype":"venue"
},
  "geometry": {"coordinates":[0.524139,51.384075],"type":"Point"}
}