{
  "type": "Feature",
  "properties": {
    "iso:country":"GB",
    "sg:address":"Norton Way South",
    "sg:city":"Letchworth",
    "sg:classifiers":[
        {
            "category":"Organizations",
            "subcategory":"Membership Organization",
            "type":"Services"
        }
    ],
    "sg:phone":"+44 1462 682524",
    "sg:postcode":"SG6 1SU",
    "sg:province":"Hertfordshire",
    "sg:tags":[
        "club"
    ],
    "wof:name":"Howard Garden Social & Day Care Centre",
    "wof:placetype":"venue"
},
  "geometry": {"coordinates":[-0.223927,51.979744],"type":"Point"}
}