{
  "type": "Feature",
  "properties": {
    "iso:country":"GB",
    "sg:address":"Jubilee House, Victoria Road",
    "sg:city":"Emsworth",
    "sg:classifiers":[
        {
            "category":"Social Services",
            "subcategory":"Adult Care",
            "type":"Services"
        }
    ],
    "sg:phone":"+44 1243 373014",
    "sg:postcode":"PO10 7LY",
    "sg:province":"Hampshire",
    "sg:tags":[
        "housing",
        "sheltered"
    ],
    "wof:name":"Hermitage Housing Association Ltd",
    "wof:placetype":"venue"
},
  "geometry": {"coordinates":[-0.9510229826,50.8518676758],"type":"Point"}
}