{
  "type": "Feature",
  "properties": {
    "addr:full":"3 Seaview Heights, The Parade Birchington Kent CT7 9QQ",
    "addr:housenumber":"3",
    "addr:postcode":"ct7 9qq",
    "addr:street":"Seaview Heights The Parade",
    "iso:country":"GB",
    "sg:address":"3 Seaview Heights, The Parade",
    "sg:city":"Birchington",
    "sg:classifiers":[
        {
            "category":"Social Services",
            "subcategory":"Child Care",
            "type":"Services"
        }
    ],
    "sg:postcode":"CT7 9QQ",
    "sg:province":"Kent",
    "sg:tags":[
        "agency",
        "nanny"
    ],
    "wof:name":"Capital U K Nannies",
    "wof:placetype":"venue"
},
  "geometry": {"coordinates":[1.2913500071,51.381187439],"type":"Point"}
}