{
  "type": "Feature",
  "properties": {
    "addr:full":"42 Malting Lane, Donington Spalding Lincolnshire PE11 4XA",
    "addr:housenumber":"42",
    "addr:postcode":"pe11 4xa",
    "addr:street":"Malting Lane",
    "iso:country":"GB",
    "sg:address":"42 Malting Lane, Donington",
    "sg:city":"Spalding",
    "sg:classifiers":[
        {
            "category":"Professional",
            "subcategory":"Lawyer & Legal Services",
            "type":"Services"
        }
    ],
    "sg:postcode":"PE11 4XA",
    "sg:province":"Lincolnshire",
    "wof:name":"Law-Direct",
    "wof:placetype":"venue"
},
  "geometry": {"coordinates":[-0.209999,52.90089],"type":"Point"}
}