{
  "type": "Feature",
  "properties": {
    "addr:full":"164 Tachbrook St Westminster Greater London SW1V 2NE",
    "addr:housenumber":"164",
    "addr:postcode":"sw1v 2ne",
    "addr:street":"Tachbrook St",
    "iso:country":"GB",
    "sg:address":"164 Tachbrook St",
    "sg:city":"Westminster",
    "sg:classifiers":[
        {
            "category":"Building & Trades",
            "subcategory":"Construction",
            "type":"Services"
        }
    ],
    "sg:phone":"+44 20 7820 1234",
    "sg:postcode":"SW1V 2NE",
    "sg:province":"Greater London",
    "sg:tags":[
        "builder"
    ],
    "wof:name":"Ormond Associates",
    "wof:placetype":"venue"
},
  "geometry": {"coordinates":[-0.1348080039,51.4892654419],"type":"Point"}
}