{
  "type": "Feature",
  "properties": {
    "iso:country":"GB",
    "sg:address":"Chorleywood Clo",
    "sg:city":"Rickmansworth",
    "sg:classifiers":[
        {
            "category":"Organizations",
            "subcategory":"Non-profit Organization",
            "type":"Services"
        }
    ],
    "sg:phone":"+44 1923 775856",
    "sg:postcode":"WD3 4EG",
    "sg:province":"Hertfordshire",
    "sg:tags":[
        "organisation",
        "voluntary",
        "charity"
    ],
    "wof:name":"Methodist Local Preachers Mutual Aid Association",
    "wof:placetype":"venue"
},
  "geometry": {"coordinates":[-0.474059,51.642281],"type":"Point"}
}