{
  "type": "Feature",
  "properties": {
    "addr:full":"41-43 Regent Street, Kingswood Bristol City of Bristol BS15 8LA",
    "addr:housenumber":"41-43",
    "addr:postcode":"bs15 8la",
    "addr:street":"Regent Street",
    "iso:country":"GB",
    "sg:address":"41-43 Regent Street, Kingswood",
    "sg:city":"Bristol",
    "sg:classifiers":[
        {
            "category":"Community Center",
            "subcategory":"Social",
            "type":"Public Place"
        }
    ],
    "sg:phone":"+44 117 961 1643",
    "sg:postcode":"BS15 8LA",
    "sg:province":"City of Bristol",
    "sg:tags":[
        "frozen",
        "food",
        "freezer",
        "centre"
    ],
    "wof:name":"Iceland Foods Plc",
    "wof:placetype":"venue"
},
  "geometry": {"coordinates":[-2.5096011162,51.4628448486],"type":"Point"}
}