{
  "type": "Feature",
  "properties": {
    "addr:full":"2 - 4 Fair Road Bradford West Yorkshire BD6 1QN",
    "addr:housenumber":"4",
    "addr:postcode":"bd6 1qn",
    "addr:street":"Fair Road",
    "iso:country":"GB",
    "sg:address":"2 - 4 Fair Road",
    "sg:city":"Bradford",
    "sg:classifiers":[
        {
            "category":"Personal",
            "subcategory":"Beauty Salon",
            "type":"Services"
        }
    ],
    "sg:phone":"+44 1274 670410",
    "sg:postcode":"BD6 1QN",
    "sg:province":"West Yorkshire",
    "sg:tags":[
        "unisex",
        "hairdresser"
    ],
    "wof:name":"Hair Effects",
    "wof:placetype":"venue"
},
  "geometry": {"coordinates":[-1.7757129669,53.7667045593],"type":"Point"}
}