{
  "type": "Feature",
  "properties": {
    "addr:full":"95 Queens Road Leicester Leicestershire LE2 1TT",
    "addr:housenumber":"95",
    "addr:postcode":"le2 1tt",
    "addr:street":"Queens Road",
    "iso:country":"GB",
    "sg:address":"95 Queens Road",
    "sg:city":"Leicester",
    "sg:classifiers":[
        {
            "category":"Shopping",
            "subcategory":"Florist",
            "type":"Retail Goods"
        }
    ],
    "sg:phone":"+44 116 270 7874",
    "sg:postcode":"LE2 1TT",
    "sg:province":"Leicestershire",
    "wof:name":"The Flower Corner",
    "wof:placetype":"venue"
},
  "geometry": {"coordinates":[-1.117462,52.617779],"type":"Point"}
}