{
  "type": "Feature",
  "properties": {
    "addr:full":"14 Sheephouse Road Hemel Hempstead Hertfordshire HP3 9LW",
    "addr:housenumber":"14",
    "addr:postcode":"hp3 9lw",
    "addr:street":"Sheephouse Road",
    "iso:country":"GB",
    "sg:address":"14 Sheephouse Road",
    "sg:city":"Hemel Hempstead",
    "sg:classifiers":[
        {
            "category":"Building & Trades",
            "subcategory":"Cleaning & Sanitation",
            "type":"Services"
        }
    ],
    "sg:postcode":"HP3 9LW",
    "sg:province":"Hertfordshire",
    "sg:tags":[
        "commercial"
    ],
    "wof:name":"S & B Building Cleaning",
    "wof:placetype":"venue"
},
  "geometry": {"coordinates":[-0.455145,51.745422],"type":"Point"}
}