{
  "type": "Feature",
  "properties": {
    "iso:country":"GB",
    "sg:address":"122 Dartmouth Park Hill",
    "sg:city":"London",
    "sg:classifiers":[
        {
            "category":"Manufacturing",
            "subcategory":"Glass & Minerals",
            "type":"Manufacturing & Wholesale Goods"
        },
        {
            "category":"Manufacturing",
            "subcategory":"Pottery",
            "type":"Manufacturing & Wholesale Goods"
        }
    ],
    "sg:phone":"+44 20 7263 3398",
    "sg:postcode":"N19 5HT",
    "sg:province":"Greater London",
    "sg:tags":[
        "shop",
        "china",
        "crystalware"
    ],
    "wof:name":"Dartmouth Park Pottery",
    "wof:placetype":"venue"
},
  "geometry": {"coordinates":[-0.140533,51.564442],"type":"Point"}
}