{
  "type": "Feature",
  "properties": {
    "addr:full":"40 Greek St West End Greater London W1D 4EB",
    "addr:housenumber":"40",
    "addr:postcode":"w1d 4eb",
    "addr:street":"Greek St",
    "iso:country":"GB",
    "sg:address":"40 Greek St",
    "sg:city":"West End",
    "sg:classifiers":[
        {
            "category":"Organizations",
            "subcategory":"Membership Organization",
            "type":"Services"
        }
    ],
    "sg:phone":"+44 20 7734 5188",
    "sg:postcode":"W1D 4EB",
    "sg:province":"Greater London",
    "sg:tags":[
        "club"
    ],
    "wof:name":"Soho House",
    "wof:placetype":"venue"
},
  "geometry": {"coordinates":[-0.1305570006,51.5132751465],"type":"Point"}
}