{
  "type": "Feature",
  "properties": {
    "iso:country":"GB",
    "sg:address":"135d London Road",
    "sg:city":"Knebworth",
    "sg:classifiers":[
        {
            "category":"Home & Garden",
            "subcategory":"Furniture",
            "type":"Retail Goods"
        }
    ],
    "sg:phone":"+44 1438 811811",
    "sg:postcode":"SG3 6EX",
    "sg:province":"Hertfordshire",
    "wof:name":"Gower House Soft Furnishings",
    "wof:placetype":"venue"
},
  "geometry": {"coordinates":[-0.183535,51.866302],"type":"Point"}
}