{
  "type": "Feature",
  "properties": {
    "iso:country":"GB",
    "sg:address":"12 Upper Berkeley St",
    "sg:city":"West End",
    "sg:classifiers":[
        {
            "category":"Real Estate",
            "subcategory":"Developer",
            "type":"Services"
        }
    ],
    "sg:phone":"+44 20 7724 7303",
    "sg:postcode":"W1H 7PE",
    "sg:province":"Greater London",
    "sg:tags":[
        "property"
    ],
    "wof:name":"B P L",
    "wof:placetype":"venue"
},
  "geometry": {"coordinates":[-0.1600099951,51.5155601501],"type":"Point"}
}