{
  "type": "Feature",
  "properties": {
    "iso:country":"GB",
    "sg:address":"96 Queens Road",
    "sg:city":"Buckhurst Hill",
    "sg:classifiers":[
        {
            "category":"Health Services",
            "subcategory":"Podiatrist",
            "type":"Services"
        }
    ],
    "sg:postcode":"IG9 5BS",
    "sg:province":"Essex",
    "sg:tags":[
        "podiatrists",
        "chiropodist"
    ],
    "wof:name":"R L A Carr",
    "wof:placetype":"venue"
},
  "geometry": {"coordinates":[0.041386,51.625427],"type":"Point"}
}