{
  "type": "Feature",
  "properties": {
    "addr:full":"Units 61-62, Southampton House Hounslow Greater London TW6 3LJ",
    "addr:housenumber":"units 61-62",
    "addr:postcode":"tw6 3lj",
    "addr:street":"Southampton House",
    "iso:country":"GB",
    "sg:address":"Units 61-62, Southampton House",
    "sg:city":"Hounslow",
    "sg:classifiers":[
        {
            "category":"Autos & Motor Vehicles",
            "subcategory":"Motorcycle Sales",
            "type":"Retail Goods"
        }
    ],
    "sg:postcode":"TW6 3LJ",
    "sg:province":"Greater London",
    "sg:tags":[
        "chauffeur",
        "driven",
        "car"
    ],
    "wof:name":"Jays Carriages",
    "wof:placetype":"venue"
},
  "geometry": {"coordinates":[-0.4552699924,51.4601707458],"type":"Point"}
}