{
  "type": "Feature",
  "properties": {
    "addr:full":"Office, 6-7 162 Dock St Fleetwood Lancashire FY7 6JB",
    "addr:housenumber":"6-7 162",
    "addr:postcode":"fy7 6jb",
    "addr:street":"Dock St",
    "iso:country":"GB",
    "sg:address":"Office, 6-7 162 Dock St",
    "sg:city":"Fleetwood",
    "sg:classifiers":[
        {
            "category":"Health Services",
            "subcategory":"Nursing And Care Facility",
            "type":"Services"
        }
    ],
    "sg:phone":"+44 1253 874056",
    "sg:postcode":"FY7 6JB",
    "sg:province":"Lancashire",
    "sg:tags":[
        "home"
    ],
    "wof:name":"TLC",
    "wof:placetype":"venue"
},
  "geometry": {"coordinates":[-3.0053989887,53.9238815308],"type":"Point"}
}