{
  "type": "Feature",
  "properties": {
    "addr:full":"25 Cross Street Abergavenny Herefordshire NP7 5EW",
    "addr:housenumber":"25",
    "addr:postcode":"np7 5ew",
    "addr:street":"Cross Street",
    "iso:country":"GB",
    "sg:address":"25 Cross Street",
    "sg:city":"Abergavenny",
    "sg:classifiers":[
        {
            "category":"Home & Garden",
            "subcategory":"Household Appliances",
            "type":"Retail Goods"
        },
        {
            "category":"Wholesale",
            "subcategory":"Electrical",
            "type":"Manufacturing & Wholesale Goods"
        }
    ],
    "sg:phone":"+44 1873 854729",
    "sg:postcode":"NP7 5EW",
    "sg:province":"Herefordshire",
    "sg:tags":[
        "wholesaler",
        "television",
        "domestic"
    ],
    "wof:name":"A F Thomas",
    "wof:placetype":"venue"
},
  "geometry": {"coordinates":[-3.0167150497,51.8205032349],"type":"Point"}
}