{
  "type": "Feature",
  "properties": {
    "addr:full":"Ladymead La Bristol City of Bristol BS19 5NH",
    "addr:postcode":"bs19 5nh",
    "addr:street":"Ladymead La",
    "iso:country":"GB",
    "sg:address":"Ladymead La",
    "sg:city":"Bristol",
    "sg:classifiers":[
        {
            "category":"Education",
            "subcategory":"School",
            "type":"Public Place"
        }
    ],
    "sg:phone":"+44 1934 852446",
    "sg:postcode":"BS19 5NH",
    "sg:province":"City of Bristol",
    "sg:tags":[
        "local",
        "authority"
    ],
    "wof:name":"Churchill Controlled Primary School",
    "wof:placetype":"venue"
},
  "geometry": {"coordinates":[-2.7907850742,51.3421592712],"type":"Point"}
}