{
  "type": "Feature",
  "properties": {
    "addr:full":"A34 Northbound, Weston On The Green Bicester Oxfordshire OX25 3QQ",
    "addr:postcode":"ox25 3qq",
    "addr:street":"Green",
    "iso:country":"GB",
    "sg:address":"A34 Northbound, Weston On The Green",
    "sg:city":"Bicester",
    "sg:classifiers":[
        {
            "category":"Restaurant",
            "type":"Food & Drink"
        }
    ],
    "sg:phone":"+44 1869 351169",
    "sg:postcode":"OX25 3QQ",
    "sg:province":"Oxfordshire",
    "wof:name":"Little Chef",
    "wof:placetype":"venue"
},
  "geometry": {"coordinates":[-1.217257,51.857037],"type":"Point"}
}