{
  "type": "Feature",
  "properties": {
    "iso:country":"GB",
    "sg:address":"4 Gurneys Lane",
    "sg:city":"Droitwich",
    "sg:classifiers":[
        {
            "category":"Shopping",
            "subcategory":"Thrift Store",
            "type":"Retail Goods"
        }
    ],
    "sg:phone":"+44 1905 794790",
    "sg:postcode":"WR9 8EL",
    "sg:province":"Worcestershire",
    "sg:tags":[
        "shop",
        "charity"
    ],
    "wof:name":"St. Richards Hospice",
    "wof:placetype":"venue"
},
  "geometry": {"coordinates":[-2.1475889683,52.2684898376],"type":"Point"}
}