{
  "type": "Feature",
  "properties": {
    "addr:full":"Oldbury Road Tewkesbury Gloucestershire GL20 5LR",
    "addr:postcode":"gl20 5lr",
    "addr:street":"Oldbury Road",
    "iso:country":"GB",
    "sg:address":"Oldbury Road",
    "sg:city":"Tewkesbury",
    "sg:classifiers":[
        {
            "category":"Bars & Pubs",
            "type":"Food & Drink"
        }
    ],
    "sg:phone":"+44 1684 293147",
    "sg:postcode":"GL20 5LR",
    "sg:province":"Gloucestershire",
    "sg:tags":[
        "pubs",
        "inn"
    ],
    "wof:name":"The Albion Inn",
    "wof:placetype":"venue"
},
  "geometry": {"coordinates":[-2.1540789604,51.996963501],"type":"Point"}
}