{
  "type": "Feature",
  "properties": {
    "addr:full":"7a Bow Street Rugeley Staffordshire WS15 2BT",
    "addr:housenumber":"7a",
    "addr:postcode":"ws15 2bt",
    "addr:street":"Bow Street",
    "iso:country":"GB",
    "sg:address":"7a Bow Street",
    "sg:city":"Rugeley",
    "sg:classifiers":[
        {
            "category":"Building & Trades",
            "subcategory":"Construction",
            "type":"Services"
        }
    ],
    "sg:postcode":"WS15 2BT",
    "sg:province":"Staffordshire",
    "sg:tags":[
        "window",
        "replacement"
    ],
    "wof:name":"Mark Thomas",
    "wof:placetype":"venue"
},
  "geometry": {"coordinates":[-1.937144,52.76054],"type":"Point"}
}