{
  "type": "Feature",
  "properties": {
    "iso:country":"GB",
    "sg:address":"48 Oakleigh Park South",
    "sg:city":"London",
    "sg:classifiers":[
        {
            "category":"Professional",
            "subcategory":"Management & Consulting",
            "type":"Services"
        },
        {
            "category":"Shopping",
            "subcategory":"Adult",
            "type":"Retail Goods"
        }
    ],
    "sg:phone":"+44 20 8445 9203",
    "sg:postcode":"N20 9JN",
    "sg:province":"Greater London",
    "sg:tags":[
        "consultant",
        "graphologist",
        "business"
    ],
    "wof:name":"Graph-o-Logica Ltd.",
    "wof:placetype":"venue"
},
  "geometry": {"coordinates":[-0.165411,51.634666],"type":"Point"}
}