{
  "type": "Feature",
  "properties": {
    "addr:full":"8 Elmsway, High Lane Stockport Cheshire SK6 8BT",
    "addr:housenumber":"8",
    "addr:postcode":"sk6 8bt",
    "addr:street":"Elmsway High Lane",
    "iso:country":"GB",
    "sg:address":"8 Elmsway, High Lane",
    "sg:city":"Stockport",
    "sg:classifiers":[
        {
            "category":"Retail",
            "subcategory":"Repair Shop",
            "type":"Services"
        },
        {
            "category":"Building & Trades",
            "subcategory":"Construction",
            "type":"Services"
        }
    ],
    "sg:phone":"+44 1663 762803",
    "sg:postcode":"SK6 8BT",
    "sg:province":"Cheshire",
    "sg:tags":[
        "installers",
        "gas",
        "maintenance"
    ],
    "wof:name":"Andrew S M Skuszka",
    "wof:placetype":"venue"
},
  "geometry": {"coordinates":[-2.073259,53.361279],"type":"Point"}
}