{
  "type": "Feature",
  "properties": {
    "addr:full":"3 Raglan Road Birmingham West Midlands B5 7RA",
    "addr:housenumber":"3",
    "addr:postcode":"b5 7ra",
    "addr:street":"Raglan Road",
    "iso:country":"GB",
    "sg:address":"3 Raglan Road",
    "sg:city":"Birmingham",
    "sg:classifiers":[
        {
            "category":"Professional",
            "subcategory":"Accounting & Tax Preparation",
            "type":"Services"
        }
    ],
    "sg:phone":"+44 121 440 8508",
    "sg:postcode":"B5 7RA",
    "sg:province":"West Midlands",
    "sg:tags":[
        "accountant"
    ],
    "wof:name":"J E Johnson Ltd.",
    "wof:placetype":"venue"
},
  "geometry": {"coordinates":[-1.903785,52.458828],"type":"Point"}
}