{
  "type": "Feature",
  "properties": {
    "addr:full":"34-36 High Street, Barkingside Ilford Essex IG6 2DQ",
    "addr:housenumber":"34-36",
    "addr:postcode":"ig6 2dq",
    "addr:street":"High Street",
    "iso:country":"GB",
    "sg:address":"34-36 High Street, Barkingside",
    "sg:city":"Ilford",
    "sg:classifiers":[
        {
            "category":"Insurance",
            "subcategory":"Insurance Agent",
            "type":"Services"
        }
    ],
    "sg:phone":"+44 20 8551 3232",
    "sg:postcode":"IG6 2DQ",
    "sg:province":"Essex",
    "sg:tags":[
        "broker"
    ],
    "wof:name":"MOTORWATCH DIRECT",
    "wof:placetype":"venue"
},
  "geometry": {"coordinates":[0.08173,51.589405],"type":"Point"}
}