{
  "type": "Feature",
  "properties": {
    "iso:country":"GB",
    "sg:address":"Low Creoch, Gatehouse Of Fleet",
    "sg:city":"Castle Douglas",
    "sg:classifiers":[
        {
            "category":"Farming",
            "subcategory":"Livestock Farm",
            "type":"Manufacturing & Wholesale Goods"
        }
    ],
    "sg:postcode":"DG7 2BH",
    "sg:province":"Dumfries and Galloway",
    "sg:tags":[
        "others"
    ],
    "wof:name":"T D & T Veitch",
    "wof:placetype":"venue"
},
  "geometry": {"coordinates":[-4.1869339943,54.8809089661],"type":"Point"}
}