{
  "type": "Feature",
  "properties": {
    "addr:full":"2 Palm Bay Avenue, Cliftonville Margate Kent CT9 3DH",
    "addr:housenumber":"2",
    "addr:postcode":"ct9 3dh",
    "addr:street":"Palm Bay Avenue;Margate",
    "iso:country":"GB",
    "sg:address":"2 Palm Bay Avenue, Cliftonville",
    "sg:city":"Margate",
    "sg:classifiers":[
        {
            "category":"Utilities",
            "type":"Services"
        }
    ],
    "sg:phone":"+44 1843 290652",
    "sg:postcode":"CT9 3DH",
    "sg:province":"Kent",
    "sg:tags":[
        "internet"
    ],
    "wof:name":"Independent Consultant City 2000 plc",
    "wof:placetype":"venue"
},
  "geometry": {"coordinates":[1.406102,51.391342],"type":"Point"}
}