{
  "type": "Feature",
  "properties": {
    "iso:country":"GB",
    "sg:address":"6 Market Street",
    "sg:city":"Barnstaple",
    "sg:classifiers":[
        {
            "category":"Shopping",
            "subcategory":"Clothing, Apparel, & Fashions",
            "type":"Retail Goods"
        }
    ],
    "sg:phone":"+44 1271 345088",
    "sg:postcode":"EX31 1BX",
    "sg:province":"Devon",
    "sg:tags":[
        "menswear"
    ],
    "wof:name":"Robert Miller Menswear",
    "wof:placetype":"venue"
},
  "geometry": {"coordinates":[-4.059293,51.08073],"type":"Point"}
}