{
  "type": "Feature",
  "properties": {
    "iso:country":"GB",
    "sg:address":"Scott Lidgett Road, Longport",
    "sg:city":"Stoke-on-trent",
    "sg:classifiers":[
        {
            "category":"Professional",
            "subcategory":"Engineering",
            "type":"Services"
        }
    ],
    "sg:phone":"+44 1782 825555",
    "sg:postcode":"ST6 4NQ",
    "sg:province":"Staffordshire",
    "wof:name":"Jackmark Engineering Ltd.",
    "wof:placetype":"venue"
},
  "geometry": {"coordinates":[-2.213124,53.042328],"type":"Point"}
}