{
  "type": "Feature",
  "properties": {
    "addr:full":"1 Cattybrook Terr Port Talbot Neath Port Talbot SA12 9EE",
    "addr:housenumber":"1",
    "addr:postcode":"sa12 9ee",
    "addr:street":"Cattybrook Terr",
    "iso:country":"GB",
    "sg:address":"1 Cattybrook Terr",
    "sg:city":"Port Talbot",
    "sg:classifiers":[
        {
            "category":"Shopping",
            "subcategory":"Shoes",
            "type":"Retail Goods"
        }
    ],
    "sg:phone":"+44 1639 896285",
    "sg:postcode":"SA12 9EE",
    "sg:province":"Neath Port Talbot",
    "sg:tags":[
        "shop"
    ],
    "wof:name":"Shoes & Fashions",
    "wof:placetype":"venue"
},
  "geometry": {"coordinates":[-3.8023691177,51.5913848877],"type":"Point"}
}