{
  "type": "Feature",
  "properties": {
    "iso:country":"GB",
    "sg:address":"8 Dragonfly Green",
    "sg:city":"Worcester",
    "sg:classifiers":[
        {
            "category":"Manufacturing",
            "subcategory":"Petroleum Products",
            "type":"Manufacturing & Wholesale Goods"
        }
    ],
    "sg:phone":"+44 1905 359299",
    "sg:postcode":"WR5 3TU",
    "sg:province":"Worcestershire",
    "sg:tags":[
        "double",
        "glazing"
    ],
    "wof:name":"Nu-life Windows & Conservatories",
    "wof:placetype":"venue"
},
  "geometry": {"coordinates":[-2.197863102,52.1706390381],"type":"Point"}
}