{
  "type": "Feature",
  "properties": {
    "iso:country":"GB",
    "sg:address":"Church Street",
    "sg:city":"Bridgwater",
    "sg:classifiers":[
        {
            "category":"Insurance",
            "subcategory":"Hazard Insurance",
            "type":"Services"
        }
    ],
    "sg:phone":"+44 1278 420802",
    "sg:postcode":"TA6 5AT",
    "sg:province":"Somerset",
    "sg:tags":[
        "fire",
        "water",
        "damage"
    ],
    "wof:name":"Action React",
    "wof:placetype":"venue"
},
  "geometry": {"coordinates":[-2.9979100227,51.1312904358],"type":"Point"}
}