{
  "type": "Feature",
  "properties": {
    "addr:full":"Northport Wareham Dorset BH20 4AS",
    "addr:postcode":"bh20 4as",
    "iso:country":"GB",
    "sg:address":"Northport",
    "sg:city":"Wareham",
    "sg:classifiers":[
        {
            "category":"Autos & Motor Vehicles",
            "subcategory":"Automobile Sales",
            "type":"Retail Goods"
        }
    ],
    "sg:phone":"+44 1929 552458",
    "sg:postcode":"BH20 4AS",
    "sg:province":"Dorset",
    "sg:tags":[
        "car"
    ],
    "wof:name":"Station Garage",
    "wof:placetype":"venue"
},
  "geometry": {"coordinates":[-2.1126070023,50.6898880005],"type":"Point"}
}