{
  "type": "Feature",
  "properties": {
    "addr:full":"21-25 Yorkshire Street Blackpool Lancashire FY1 5BG",
    "addr:housenumber":"21-25",
    "addr:postcode":"fy1 5bg",
    "addr:street":"Yorkshire Street",
    "iso:country":"GB",
    "sg:address":"21-25 Yorkshire Street",
    "sg:city":"Blackpool",
    "sg:classifiers":[
        {
            "category":"Travel",
            "subcategory":"Hotels & Motels",
            "type":"Entertainment"
        }
    ],
    "sg:phone":"+44 1253 296866",
    "sg:postcode":"FY1 5BG",
    "sg:province":"Lancashire",
    "wof:name":"Manvers Hotel",
    "wof:placetype":"venue"
},
  "geometry": {"coordinates":[-3.0538959503,53.8097114563],"type":"Point"}
}