{
  "type": "Feature",
  "properties": {
    "addr:full":"68 Chigwell Road South, Woodford London Greater London E18 1NN",
    "addr:housenumber":"68",
    "addr:postcode":"e18 1nn",
    "addr:street":"Chigwell Road",
    "iso:country":"GB",
    "sg:address":"68 Chigwell Road South, Woodford",
    "sg:city":"London",
    "sg:classifiers":[
        {
            "category":"Shopping",
            "subcategory":"Used Merchandise",
            "type":"Retail Goods"
        }
    ],
    "sg:postcode":"E18 1NN",
    "sg:province":"Greater London",
    "sg:tags":[
        "shop",
        "second-hand"
    ],
    "wof:name":"Dennis William King",
    "wof:placetype":"venue"
},
  "geometry": {"coordinates":[0.0353519991,51.5918121338],"type":"Point"}
}