{
  "type": "Feature",
  "properties": {
    "addr:full":"Bethania Row Bridgend Bridgend CF32 7AB",
    "addr:postcode":"cf32 7ab",
    "addr:street":"Bethania Row",
    "iso:country":"GB",
    "sg:address":"Bethania Row",
    "sg:city":"Bridgend",
    "sg:classifiers":[
        {
            "category":"Organizations",
            "subcategory":"Membership Organization",
            "type":"Services"
        }
    ],
    "sg:postcode":"CF32 7AB",
    "sg:province":"Bridgend",
    "sg:tags":[
        "club"
    ],
    "wof:name":"Ogmore & Garw Ex-Servicemens Club",
    "wof:placetype":"venue"
},
  "geometry": {"coordinates":[-3.5411109924,51.6020011902],"type":"Point"}
}