{
  "type": "Feature",
  "properties": {
    "addr:full":"10 London Mews London Greater London W2 1HY",
    "addr:housenumber":"10",
    "addr:postcode":"w2 1hy",
    "addr:street":"London Mews",
    "iso:country":"GB",
    "sg:address":"10 London Mews",
    "sg:city":"London",
    "sg:classifiers":[
        {
            "category":"Health Services",
            "subcategory":"Optometrist",
            "type":"Services"
        }
    ],
    "sg:postcode":"W2 1HY",
    "sg:province":"Greater London",
    "sg:tags":[
        "optician"
    ],
    "wof:name":"Melissa Conway Ltd",
    "wof:placetype":"venue"
},
  "geometry": {"coordinates":[-0.173866,51.516335],"type":"Point"}
}