{
  "type": "Feature",
  "properties": {
    "iso:country":"GB",
    "sg:address":"473 Wandsworth Road",
    "sg:city":"London",
    "sg:classifiers":[
        {
            "category":"Food & Beverages",
            "subcategory":"Supermarket",
            "type":"Retail Goods"
        }
    ],
    "sg:phone":"+44 20 7498 5442",
    "sg:postcode":"SW8 4NX",
    "sg:province":"Greater London",
    "wof:name":"Quickstop",
    "wof:placetype":"venue"
},
  "geometry": {"coordinates":[-0.136489,51.471371],"type":"Point"}
}