{
  "type": "Feature",
  "properties": {
    "addr:full":"181 Spring Grove Road Hounslow Greater London TW7 4BE",
    "addr:housenumber":"181",
    "addr:postcode":"tw7 4be",
    "addr:street":"Spring Grove Road",
    "iso:country":"GB",
    "sg:address":"181 Spring Grove Road",
    "sg:city":"Hounslow",
    "sg:classifiers":[
        {
            "category":"Professional",
            "subcategory":"Printing & Photocopies",
            "type":"Services"
        }
    ],
    "sg:phone":"+44 20 8569 9473",
    "sg:postcode":"TW7 4BE",
    "sg:province":"Greater London",
    "sg:tags":[
        "printer"
    ],
    "wof:name":"Collingwood Print Ltd.",
    "wof:placetype":"venue"
},
  "geometry": {"coordinates":[-0.3496589959,51.4760017395],"type":"Point"}
}