{
  "type": "Feature",
  "properties": {
    "iso:country":"GB",
    "sg:address":"293-299 Kentish Town Road",
    "sg:city":"London",
    "sg:classifiers":[
        {
            "category":"Professional",
            "subcategory":"Lawyer & Legal Services",
            "type":"Services"
        }
    ],
    "sg:phone":"+44 20 7485 8450",
    "sg:postcode":"NW5 2TJ",
    "sg:province":"Greater London",
    "sg:tags":[
        "solicitor"
    ],
    "wof:name":"Adrian & Co.",
    "wof:placetype":"venue"
},
  "geometry": {"coordinates":[-0.141080007,51.5493049622],"type":"Point"}
}