{
  "type": "Feature",
  "properties": {
    "addr:full":"Griegsland, Johnstonebridge Lockerbie Dumfries and Galloway DG11 1HF",
    "addr:postcode":"dg11 1hf",
    "iso:country":"GB",
    "sg:address":"Griegsland, Johnstonebridge",
    "sg:city":"Lockerbie",
    "sg:classifiers":[
        {
            "category":"Farming",
            "subcategory":"Dairy Farm",
            "type":"Manufacturing & Wholesale Goods"
        }
    ],
    "sg:postcode":"DG11 1HF",
    "sg:province":"Dumfries and Galloway",
    "wof:name":"A & A Paul & Son",
    "wof:placetype":"venue"
},
  "geometry": {"coordinates":[-3.4159240723,55.2182044983],"type":"Point"}
}