{
  "type": "Feature",
  "properties": {
    "iso:country":"GB",
    "sg:address":"89 Holburn Street",
    "sg:city":"Aberdeen",
    "sg:classifiers":[
        {
            "category":"Shopping",
            "subcategory":"Hobbies, Toys, & Games",
            "type":"Retail Goods"
        },
        {
            "category":"Communications",
            "type":"Services"
        }
    ],
    "sg:phone":"+44 1224 212721",
    "sg:postcode":"AB10 6BQ",
    "sg:province":"Aberdeen City",
    "sg:tags":[
        "tv",
        "video",
        "computer",
        "radio"
    ],
    "wof:name":"Solid Gold Games Centre",
    "wof:placetype":"venue"
},
  "geometry": {"coordinates":[-2.113319,57.140541],"type":"Point"}
}