{
  "type": "Feature",
  "properties": {
    "iso:country":"GB",
    "sg:address":"Lansdowne House, City Forum 250 City Road",
    "sg:city":"London",
    "sg:classifiers":[
        {
            "category":"Professional",
            "subcategory":"Accounting & Tax Preparation",
            "type":"Services"
        }
    ],
    "sg:postcode":"EC1V 2QZ",
    "sg:province":"Greater London",
    "sg:tags":[
        "accountant"
    ],
    "wof:name":"Just Accounting Services Ltd",
    "wof:placetype":"venue"
},
  "geometry": {"coordinates":[-0.09633,51.529099],"type":"Point"}
}