{
  "type": "Feature",
  "properties": {
    "addr:full":"Sauchie House, 64 Baker Street Stirling Stirling FK8 1DB",
    "addr:housenumber":"64",
    "addr:postcode":"fk8 1db",
    "addr:street":"Baker Street",
    "iso:country":"GB",
    "sg:address":"Sauchie House, 64 Baker Street",
    "sg:city":"Stirling",
    "sg:classifiers":[
        {
            "category":"Organizations",
            "subcategory":"Non-profit Organization",
            "type":"Services"
        }
    ],
    "sg:phone":"+44 1786 472718",
    "sg:postcode":"FK8 1DB",
    "sg:province":"Stirling",
    "sg:tags":[
        "organisation",
        "voluntary",
        "charity"
    ],
    "wof:name":"Women's Royal Voluntary Service",
    "wof:placetype":"venue"
},
  "geometry": {"coordinates":[-3.940789,56.119961],"type":"Point"}
}