{
  "type": "Feature",
  "properties": {
    "addr:full":"M V Lea, Leigh Creek, Leigh Marshes Leigh-on-sea Essex SS9 1JP",
    "addr:postcode":"ss9 1jp",
    "addr:street":"Lea Leigh Creek Leigh",
    "iso:country":"GB",
    "sg:address":"M V Lea, Leigh Creek, Leigh Marshes",
    "sg:city":"Leigh-on-sea",
    "sg:classifiers":[
        {
            "category":"Organizations",
            "subcategory":"Membership Organization",
            "type":"Services"
        }
    ],
    "sg:phone":"+44 1702 714858",
    "sg:postcode":"SS9 1JP",
    "sg:province":"Essex",
    "sg:tags":[
        "club"
    ],
    "wof:name":"Leigh Motor Boat Club",
    "wof:placetype":"venue"
},
  "geometry": {"coordinates":[0.6711400151,51.5438690186],"type":"Point"}
}