{
  "type": "Feature",
  "properties": {
    "iso:country":"GB",
    "sg:address":"Oak Tree Farm, Station Road, Topcliffe",
    "sg:city":"Thirsk",
    "sg:classifiers":[
        {
            "category":"Shopping",
            "type":"Retail Goods"
        }
    ],
    "sg:phone":"+44 1845 577028",
    "sg:postcode":"YO7 3SD",
    "sg:province":"North Yorkshire",
    "sg:tags":[
        "merchant"
    ],
    "wof:name":"Fishers Seeds & Grains Ltd.",
    "wof:placetype":"venue"
},
  "geometry": {"coordinates":[-1.385269,54.178375],"type":"Point"}
}