{
  "type": "Feature",
  "properties": {
    "addr:full":"5 Dale House Lane Kenilworth Warwickshire CV8 2HW",
    "addr:housenumber":"5",
    "addr:postcode":"cv8 2hw",
    "addr:street":"Dale House Lane",
    "iso:country":"GB",
    "sg:address":"5 Dale House Lane",
    "sg:city":"Kenilworth",
    "sg:classifiers":[
        {
            "category":"Shopping",
            "subcategory":"Pharmacy",
            "type":"Retail Goods"
        }
    ],
    "sg:postcode":"CV8 2HW",
    "sg:province":"Warwickshire",
    "sg:tags":[
        "medicine",
        "therapy"
    ],
    "wof:name":"Natures Sunshine Distributor",
    "wof:placetype":"venue"
},
  "geometry": {"coordinates":[-1.56493,52.352417],"type":"Point"}
}