{
  "type": "Feature",
  "properties": {
    "iso:country":"GB",
    "sg:address":"Unit 7 Town Lane, Denton",
    "sg:city":"Manchester",
    "sg:classifiers":[
        {
            "category":"Manufacturing",
            "subcategory":"Metals",
            "type":"Manufacturing & Wholesale Goods"
        }
    ],
    "sg:phone":"+44 161 335 0828",
    "sg:postcode":"M34 6LE",
    "sg:province":"Greater Manchester",
    "sg:tags":[
        "fabricator",
        "aluminium",
        "mnfrs"
    ],
    "wof:name":"Alpha Windows",
    "wof:placetype":"venue"
},
  "geometry": {"coordinates":[-2.112254,53.451916],"type":"Point"}
}