{
  "type": "Feature",
  "properties": {
    "iso:country":"GB",
    "sg:address":"145 Upper Tooting Road",
    "sg:city":"London",
    "sg:classifiers":[
        {
            "category":"Place Of Worship",
            "type":"Public Place"
        }
    ],
    "sg:phone":"+44 20 8767 2344",
    "sg:postcode":"SW17 7TJ",
    "sg:province":"Greater London",
    "wof:name":"Tooting Islamic Centre",
    "wof:placetype":"venue"
},
  "geometry": {"coordinates":[-0.163811,51.432129],"type":"Point"}
}