{
  "type": "Feature",
  "properties": {
    "addr:full":"96 Westgate Grantham Lincolnshire NG31 6LE",
    "addr:housenumber":"96",
    "addr:postcode":"ng31 6le",
    "addr:street":"Westgate Grantham",
    "iso:country":"GB",
    "sg:address":"96 Westgate",
    "sg:city":"Grantham",
    "sg:classifiers":[
        {
            "category":"Shopping",
            "subcategory":"Hobbies, Toys, & Games",
            "type":"Retail Goods"
        }
    ],
    "sg:phone":"+44 1476 400014",
    "sg:postcode":"NG31 6LE",
    "sg:province":"Lincolnshire",
    "sg:tags":[
        "shop",
        "toy",
        "sale"
    ],
    "wof:name":"Arbon & Watts Ltd.",
    "wof:placetype":"venue"
},
  "geometry": {"coordinates":[-0.644035995,52.9126739502],"type":"Point"}
}