{
  "type": "Feature",
  "properties": {
    "iso:country":"GB",
    "sg:address":"55 Narborough Road",
    "sg:city":"Leicester",
    "sg:classifiers":[
        {
            "category":"Wholesale",
            "subcategory":"Apparel",
            "type":"Manufacturing & Wholesale Goods"
        }
    ],
    "sg:phone":"+44 116 272 1112",
    "sg:postcode":"LE3 0LE",
    "sg:province":"Leicestershire",
    "sg:tags":[
        "w'sale",
        "ladieswear"
    ],
    "wof:name":"Euro Designs",
    "wof:placetype":"venue"
},
  "geometry": {"coordinates":[-1.148858,52.629414],"type":"Point"}
}