{
  "type": "Feature",
  "properties": {
    "addr:full":"14 Silver Street Leicester Leicestershire LE1 5ET",
    "addr:housenumber":"14",
    "addr:postcode":"le1 5et",
    "addr:street":"Silver Street",
    "iso:country":"GB",
    "sg:address":"14 Silver Street",
    "sg:city":"Leicester",
    "sg:classifiers":[
        {
            "category":"Shopping",
            "subcategory":"Gifts & Souvenirs",
            "type":"Retail Goods"
        }
    ],
    "sg:phone":"+44 116 262 5408",
    "sg:postcode":"LE1 5ET",
    "sg:province":"Leicestershire",
    "sg:tags":[
        "poster",
        "card"
    ],
    "wof:name":"Cut Cost Cards",
    "wof:placetype":"venue"
},
  "geometry": {"coordinates":[-1.1346240044,52.6354446411],"type":"Point"}
}