{
  "type": "Feature",
  "properties": {
    "addr:full":"8 Ebor Terrace Leeds West Yorkshire LS10 2EQ",
    "addr:housenumber":"8",
    "addr:postcode":"ls10 2eq",
    "addr:street":"Ebor Terrace",
    "iso:country":"GB",
    "sg:address":"8 Ebor Terrace",
    "sg:city":"Leeds",
    "sg:classifiers":[
        {
            "category":"Professional",
            "subcategory":"Engineering",
            "type":"Services"
        },
        {
            "category":"Building & Trades",
            "subcategory":"Electrical",
            "type":"Services"
        }
    ],
    "sg:phone":"+44 113 277 7432",
    "sg:postcode":"LS10 2EQ",
    "sg:province":"West Yorkshire",
    "sg:tags":[
        "engineer",
        "electrician",
        "contractor"
    ],
    "wof:name":"Rothwell Electrical Services",
    "wof:placetype":"venue"
},
  "geometry": {"coordinates":[-1.5256329775,53.7707939148],"type":"Point"}
}