{
  "type": "Feature",
  "properties": {
    "addr:full":"27 The Street, Appledore Ashford Kent TN26 2BU",
    "addr:housenumber":"27",
    "addr:postcode":"tn26 2bu",
    "addr:street":"The Street",
    "iso:country":"GB",
    "sg:address":"27 The Street, Appledore",
    "sg:city":"Ashford",
    "sg:classifiers":[
        {
            "category":"Travel",
            "subcategory":"Hotels & Motels",
            "type":"Entertainment"
        }
    ],
    "sg:phone":"+44 1233 758000",
    "sg:postcode":"TN26 2BU",
    "sg:province":"Kent",
    "wof:name":"The Swan Hotel",
    "wof:placetype":"venue"
},
  "geometry": {"coordinates":[0.788796,51.031216],"type":"Point"}
}