{
  "type": "Feature",
  "properties": {
    "addr:full":"24 Central Road Stroud Gloucestershire GL5 4HQ",
    "addr:housenumber":"24",
    "addr:postcode":"gl5 4hq",
    "addr:street":"Central Road",
    "iso:country":"GB",
    "sg:address":"24 Central Road",
    "sg:city":"Stroud",
    "sg:classifiers":[
        {
            "category":"Insurance",
            "subcategory":"Insurance Agent",
            "type":"Services"
        }
    ],
    "sg:phone":"+44 1453 755774",
    "sg:postcode":"GL5 4HQ",
    "sg:province":"Gloucestershire",
    "sg:tags":[
        "broker"
    ],
    "wof:name":"Pearson Insurance Services",
    "wof:placetype":"venue"
},
  "geometry": {"coordinates":[-2.2346990108,51.7475776672],"type":"Point"}
}