{
  "type": "Feature",
  "properties": {
    "addr:full":"158 Oxford Road Reading Berkshire RG1 7PJ",
    "addr:housenumber":"158",
    "addr:postcode":"rg1 7pj",
    "addr:street":"Oxford Road",
    "iso:country":"GB",
    "sg:address":"158 Oxford Road",
    "sg:city":"Reading",
    "sg:classifiers":[
        {
            "category":"Fast Food",
            "type":"Food & Drink"
        },
        {
            "category":"Restaurant",
            "type":"Food & Drink"
        }
    ],
    "sg:phone":"+44 118 958 2616",
    "sg:postcode":"RG1 7PJ",
    "sg:province":"Berkshire",
    "sg:tags":[
        "away",
        "-",
        "american",
        "outlet",
        "meal",
        "take"
    ],
    "wof:name":"Perfect Fried Chicken Ltd",
    "wof:placetype":"venue"
},
  "geometry": {"coordinates":[-0.987878,51.455711],"type":"Point"}
}