{
  "type": "Feature",
  "properties": {
    "iso:country":"GB",
    "sg:address":"Crewkerne Area Community Office, Town Hall, Market Square",
    "sg:city":"Crewkerne",
    "sg:classifiers":[
        {
            "category":"Landmark",
            "subcategory":"Tourist Information",
            "type":"Public Place"
        }
    ],
    "sg:phone":"+44 1460 73441",
    "sg:postcode":"TA18 7LN",
    "sg:province":"Dorset",
    "wof:name":"Crewkerne Tourist Office",
    "wof:placetype":"venue"
},
  "geometry": {"coordinates":[-2.796014,50.884327],"type":"Point"}
}