{
  "type": "Feature",
  "properties": {
    "addr:full":"Cyfie Farm, Llanfihangel Llanfyllin Shropshire SY22 5JE",
    "addr:postcode":"sy22 5je",
    "addr:street":"Llanfyllin Shropshire",
    "iso:country":"GB",
    "sg:address":"Cyfie Farm, Llanfihangel",
    "sg:city":"Llanfyllin",
    "sg:classifiers":[
        {
            "category":"Farming",
            "subcategory":"Farm",
            "type":"Manufacturing & Wholesale Goods"
        }
    ],
    "sg:postcode":"SY22 5JE",
    "sg:province":"Shropshire",
    "sg:tags":[
        "mixed",
        "crop"
    ],
    "wof:name":"George Edward Jenkins",
    "wof:placetype":"venue"
},
  "geometry": {"coordinates":[-3.269958,52.764301],"type":"Point"}
}