{
  "type": "Feature",
  "properties": {
    "iso:country":"GB",
    "sg:address":"Whitmore Ho",
    "sg:city":"Bromyard",
    "sg:classifiers":[
        {
            "category":"Professional",
            "subcategory":"Engineering",
            "type":"Services"
        }
    ],
    "sg:phone":"+44 1432 761104",
    "sg:postcode":"HR7 4RP",
    "sg:province":"Herefordshire",
    "sg:tags":[
        "contractor",
        "electrical",
        "engineer"
    ],
    "wof:name":"J T Benjamin",
    "wof:placetype":"venue"
},
  "geometry": {"coordinates":[-2.510399,52.189098],"type":"Point"}
}