{
  "type": "Feature",
  "properties": {
    "addr:full":"Unit 3 The Orchard Trading Estate, Beverley Road York East Riding of Yorkshire YO43 4SQ",
    "addr:housenumber":"unit 3",
    "addr:postcode":"yo43 4sq",
    "addr:street":"The;Trading Estate Beverley Road",
    "iso:country":"GB",
    "sg:address":"Unit 3 The Orchard Trading Estate, Beverley Road",
    "sg:city":"York",
    "sg:classifiers":[
        {
            "category":"Autos & Motor Vehicles",
            "subcategory":"Motorcycle Sales",
            "type":"Retail Goods"
        }
    ],
    "sg:postcode":"YO43 4SQ",
    "sg:province":"East Riding of Yorkshire",
    "sg:tags":[
        "outboard"
    ],
    "wof:name":"Newbald Marine Engineering Services",
    "wof:placetype":"venue"
},
  "geometry": {"coordinates":[-0.6103600264,53.8220100403],"type":"Point"}
}