{
  "type": "Feature",
  "properties": {
    "addr:full":"65 Newgate St Morpeth Northumberland NE61 1AY",
    "addr:housenumber":"65",
    "addr:postcode":"ne61 1ay",
    "addr:street":"Newgate St",
    "iso:country":"GB",
    "sg:address":"65 Newgate St",
    "sg:city":"Morpeth",
    "sg:classifiers":[
        {
            "category":"Health Services",
            "subcategory":"Podiatrist",
            "type":"Services"
        }
    ],
    "sg:phone":"+44 1670 514244",
    "sg:postcode":"NE61 1AY",
    "sg:province":"Northumberland",
    "sg:tags":[
        "podiatrists",
        "chiropodist"
    ],
    "wof:name":"Elizabeth Ayres",
    "wof:placetype":"venue"
},
  "geometry": {"coordinates":[-1.692135,55.169659],"type":"Point"}
}