{
  "type": "Feature",
  "properties": {
    "addr:full":"303 Leeds Road Nelson Lancashire BB9 8EJ",
    "addr:housenumber":"303",
    "addr:postcode":"bb9 8ej",
    "addr:street":"Leeds Road",
    "iso:country":"GB",
    "sg:address":"303 Leeds Road",
    "sg:city":"Nelson",
    "sg:classifiers":[
        {
            "category":"Professional",
            "type":"Services"
        },
        {
            "category":"Building & Trades",
            "subcategory":"Cleaning & Sanitation",
            "type":"Services"
        }
    ],
    "sg:phone":"+44 1282 693184",
    "sg:postcode":"BB9 8EJ",
    "sg:province":"Lancashire",
    "sg:tags":[
        "dry",
        "control",
        "damp",
        "rot",
        "preservation"
    ],
    "wof:name":"Stone Oak Ltd",
    "wof:placetype":"venue"
},
  "geometry": {"coordinates":[-2.2019739151,53.8434257507],"type":"Point"}
}