{
  "type": "Feature",
  "properties": {
    "addr:full":"Morfa Farm, Morfa Lane Llantwit Major The Vale of Glamorgan CF61 2YT",
    "addr:postcode":"cf61 2yt",
    "addr:street":"Morfa Lane",
    "iso:country":"GB",
    "sg:address":"Morfa Farm, Morfa Lane",
    "sg:city":"Llantwit Major",
    "sg:classifiers":[
        {
            "category":"Farming",
            "subcategory":"Dairy Farm",
            "type":"Manufacturing & Wholesale Goods"
        }
    ],
    "sg:phone":"+44 1446 792320",
    "sg:postcode":"CF61 2YT",
    "sg:province":"The Vale of Glamorgan",
    "sg:tags":[
        "farmer"
    ],
    "wof:name":"J D Llewellyn & Son",
    "wof:placetype":"venue"
},
  "geometry": {"coordinates":[-3.4718389511,51.4141616821],"type":"Point"}
}