{
  "type": "Feature",
  "properties": {
    "addr:full":"3 Newcastle Street Stoke-on-trent Staffordshire ST6 3QB",
    "addr:housenumber":"3",
    "addr:postcode":"st6 3qb",
    "addr:street":"Newcastle Street",
    "iso:country":"GB",
    "sg:address":"3 Newcastle Street",
    "sg:city":"Stoke-on-trent",
    "sg:classifiers":[
        {
            "category":"Personal",
            "subcategory":"Beauty Salon",
            "type":"Services"
        }
    ],
    "sg:phone":"+44 1782 834309",
    "sg:postcode":"ST6 3QB",
    "sg:province":"Staffordshire",
    "sg:tags":[
        "lady",
        "hairdresser"
    ],
    "wof:name":"Patricia's",
    "wof:placetype":"venue"
},
  "geometry": {"coordinates":[-2.19948,53.044891],"type":"Point"}
}