{
  "type": "Feature",
  "properties": {
    "iso:country":"GB",
    "sg:address":"Riverside Avenue West, Lawford",
    "sg:city":"Manningtree",
    "sg:classifiers":[
        {
            "category":"Manufacturing",
            "subcategory":"Rubber & Plastics",
            "type":"Manufacturing & Wholesale Goods"
        }
    ],
    "sg:phone":"+44 1206 391209",
    "sg:postcode":"CO11 1UN",
    "sg:province":"Essex",
    "sg:tags":[
        "forming",
        "injection",
        "moulding",
        "vacuum"
    ],
    "wof:name":"S M H PLASTICS",
    "wof:placetype":"venue"
},
  "geometry": {"coordinates":[1.055852,51.94849],"type":"Point"}
}