{
  "type": "Feature",
  "properties": {
    "iso:country":"GB",
    "sg:address":"17 Alderney Way",
    "sg:city":"Immingham",
    "sg:classifiers":[
        {
            "category":"Military Area",
            "subcategory":"Air Force Base",
            "type":"Public Place"
        }
    ],
    "sg:postcode":"DN40 1RB",
    "sg:province":"Lincolnshire",
    "sg:tags":[
        "taxi",
        "hire",
        "private"
    ],
    "wof:name":"A to B Taxis",
    "wof:placetype":"venue"
},
  "geometry": {"coordinates":[-0.213699,53.608223],"type":"Point"}
}