{
  "type": "Feature",
  "properties": {
    "addr:full":"5 St Margarets Road Bournemouth Dorset BH10 4BD",
    "addr:housenumber":"5",
    "addr:postcode":"bh10 4bd",
    "addr:street":"St Margarets Road",
    "iso:country":"GB",
    "sg:address":"5 St Margarets Road",
    "sg:city":"Bournemouth",
    "sg:classifiers":[
        {
            "category":"Building & Trades",
            "subcategory":"Plumbing",
            "type":"Services"
        }
    ],
    "sg:postcode":"BH10 4BD",
    "sg:province":"Dorset",
    "sg:tags":[
        "plumber",
        "heating"
    ],
    "wof:name":"KARL H LAWRENCE",
    "wof:placetype":"venue"
},
  "geometry": {"coordinates":[-1.9021259546,50.7514381409],"type":"Point"}
}