{
  "type": "Feature",
  "properties": {
    "addr:full":"5 Keats Way, Higham Ferrers Wellingborough Bedfordshire NN10 8DQ",
    "addr:housenumber":"5",
    "addr:postcode":"bedfordshire nn10 8dq",
    "addr:street":"Keats Way",
    "iso:country":"GB",
    "sg:address":"5 Keats Way, Higham Ferrers",
    "sg:city":"Wellingborough",
    "sg:classifiers":[
        {
            "category":"Professional",
            "subcategory":"Art Services",
            "type":"Services"
        },
        {
            "category":"Building & Trades",
            "subcategory":"Construction",
            "type":"Services"
        }
    ],
    "sg:phone":"+44 1933 313991",
    "sg:postcode":"NN10 8DQ",
    "sg:province":"Bedfordshire",
    "sg:tags":[
        "decorator",
        "painter"
    ],
    "wof:name":"Colourwise Decorating Services",
    "wof:placetype":"venue"
},
  "geometry": {"coordinates":[-0.601186,52.303753],"type":"Point"}
}