{
  "type": "Feature",
  "properties": {
    "addr:full":"120a Randall Road London Greater London SE11 5JR",
    "addr:housenumber":"120a",
    "addr:postcode":"se11 5jr",
    "addr:street":"Randall Road",
    "iso:country":"GB",
    "sg:address":"120a Randall Road",
    "sg:city":"London",
    "sg:classifiers":[
        {
            "category":"Retail",
            "subcategory":"Auto Rental",
            "type":"Services"
        },
        {
            "category":"Autos & Motor Vehicles",
            "subcategory":"Motorcycle Sales",
            "type":"Retail Goods"
        }
    ],
    "sg:phone":"+44 20 7735 5515",
    "sg:postcode":"SE11 5JR",
    "sg:province":"Greater London",
    "sg:tags":[
        "chauffeur",
        "driven",
        "hire",
        "car"
    ],
    "wof:name":"Chauffeurs Incorporated Ltd.",
    "wof:placetype":"venue"
},
  "geometry": {"coordinates":[-0.121364,51.490471],"type":"Point"}
}