{
  "type": "Feature",
  "properties": {
    "addr:full":"Breakspear Park, Breakspear Way Hemel Hempstead Hertfordshire HP2 4UL",
    "addr:postcode":"hp2 4ul",
    "addr:street":"Breakspear Way",
    "iso:country":"GB",
    "sg:address":"Breakspear Park, Breakspear Way",
    "sg:city":"Hemel Hempstead",
    "sg:classifiers":[
        {
            "category":"Professional",
            "subcategory":"Computer Services",
            "type":"Services"
        }
    ],
    "sg:phone":"+44 1442 437700",
    "sg:postcode":"HP2 4UL",
    "sg:province":"Hertfordshire",
    "sg:tags":[
        "system",
        "software"
    ],
    "wof:name":"Oracle Corporation U K Ltd.",
    "wof:placetype":"venue"
},
  "geometry": {"coordinates":[-0.4217660129,51.7564086914],"type":"Point"}
}