{
  "type": "Feature",
  "properties": {
    "addr:full":"47 Station Road, West Town Hayling Island Hampshire PO11 0EB",
    "addr:housenumber":"47",
    "addr:postcode":"po11 0eb",
    "addr:street":"Station Road West",
    "iso:country":"GB",
    "sg:address":"47 Station Road, West Town",
    "sg:city":"Hayling Island",
    "sg:classifiers":[
        {
            "category":"Fast Food",
            "type":"Food & Drink"
        },
        {
            "category":"Food & Beverages",
            "subcategory":"Meat & Fish",
            "type":"Retail Goods"
        }
    ],
    "sg:phone":"+44 23 9246 8821",
    "sg:postcode":"PO11 0EB",
    "sg:province":"Hampshire",
    "sg:tags":[
        "shop",
        "chip"
    ],
    "wof:name":"Manor Farm Fish Bar",
    "wof:placetype":"venue"
},
  "geometry": {"coordinates":[-0.990193,50.791279],"type":"Point"}
}