{
  "type": "Feature",
  "properties": {
    "iso:country":"GB",
    "sg:address":"Ponstreath Halfway House",
    "sg:city":"Penryn",
    "sg:classifiers":[
        {
            "category":"Building & Trades",
            "subcategory":"Equipment Rental",
            "type":"Services"
        }
    ],
    "sg:phone":"+44 1326 340475",
    "sg:postcode":"TR10 9EH",
    "sg:province":"Cornwall",
    "sg:tags":[
        "plant",
        "machinery"
    ],
    "wof:name":"W B R Andrew",
    "wof:placetype":"venue"
},
  "geometry": {"coordinates":[-5.124879,50.16428],"type":"Point"}
}