{
  "type": "Feature",
  "properties": {
    "addr:full":"Main Road, Otterbourne Winchester Hampshire SO21 2EQ",
    "addr:postcode":"so21 2eq",
    "addr:street":"Main Road",
    "iso:country":"GB",
    "sg:address":"Main Road, Otterbourne",
    "sg:city":"Winchester",
    "sg:classifiers":[
        {
            "category":"Bars & Pubs",
            "type":"Food & Drink"
        }
    ],
    "sg:phone":"+44 1962 712830",
    "sg:postcode":"SO21 2EQ",
    "sg:province":"Hampshire",
    "sg:tags":[
        "pubs",
        "inn"
    ],
    "wof:name":"White Horse Inn",
    "wof:placetype":"venue"
},
  "geometry": {"coordinates":[-1.3430089951,51.0084152222],"type":"Point"}
}