{
  "type": "Feature",
  "properties": {
    "addr:full":"46 High Street Epping Essex CM16 4AE",
    "addr:housenumber":"46",
    "addr:postcode":"cm16 4ae",
    "addr:street":"High Street",
    "iso:country":"GB",
    "sg:address":"46 High Street",
    "sg:city":"Epping",
    "sg:classifiers":[
        {
            "category":"Shopping",
            "subcategory":"Clothing, Apparel, & Fashions",
            "type":"Retail Goods"
        }
    ],
    "sg:phone":"+44 1992 575454",
    "sg:postcode":"CM16 4AE",
    "sg:province":"Essex",
    "sg:tags":[
        "menswear"
    ],
    "wof:name":"Zanelli",
    "wof:placetype":"venue"
},
  "geometry": {"coordinates":[0.107614,51.69635],"type":"Point"}
}