{
  "type": "Feature",
  "properties": {
    "iso:country":"GB",
    "sg:address":"18 Stirling Road, Edgbaston",
    "sg:city":"Birmingham",
    "sg:classifiers":[
        {
            "category":"Travel",
            "subcategory":"Hotels & Motels",
            "type":"Entertainment"
        }
    ],
    "sg:phone":"+44 121 454 3962",
    "sg:postcode":"B16 9BG",
    "sg:province":"West Midlands",
    "wof:name":"San Roque",
    "wof:placetype":"venue"
},
  "geometry": {"coordinates":[-1.935248,52.473194],"type":"Point"}
}