{
  "type": "Feature",
  "properties": {
    "addr:full":"Dunston Heath Farm, Dunston Stafford Staffordshire ST18 9AQ",
    "addr:postcode":"st18 9aq",
    "iso:country":"GB",
    "sg:address":"Dunston Heath Farm, Dunston",
    "sg:city":"Stafford",
    "sg:classifiers":[
        {
            "category":"Farming",
            "subcategory":"Farm",
            "type":"Manufacturing & Wholesale Goods"
        }
    ],
    "sg:postcode":"ST18 9AQ",
    "sg:province":"Staffordshire",
    "sg:tags":[
        "mixed",
        "crop"
    ],
    "wof:name":"H J & J W Richardson & Sons",
    "wof:placetype":"venue"
},
  "geometry": {"coordinates":[-2.108577013,52.75963974],"type":"Point"}
}