{
  "type": "Feature",
  "properties": {
    "addr:full":"16b Church Street, St Georges Telford Shropshire TF2 9JU",
    "addr:housenumber":"16b",
    "addr:postcode":"tf2 9ju",
    "addr:street":"Church Street",
    "iso:country":"GB",
    "sg:address":"16b Church Street, St Georges",
    "sg:city":"Telford",
    "sg:classifiers":[
        {
            "category":"Shopping",
            "subcategory":"News",
            "type":"Retail Goods"
        }
    ],
    "sg:postcode":"TF2 9JU",
    "sg:province":"Shropshire",
    "sg:tags":[
        "newsagent"
    ],
    "wof:name":"S M Gregory Newsagents",
    "wof:placetype":"venue"
},
  "geometry": {"coordinates":[-2.4350869656,52.6947059631],"type":"Point"}
}