{
  "type": "Feature",
  "properties": {
    "addr:full":"Plock Farm, Liverpool Road, Bretherton Preston Lancashire PR26 9AX",
    "addr:postcode":"pr26 9ax",
    "addr:street":"Liverpool Road",
    "iso:country":"GB",
    "sg:address":"Plock Farm, Liverpool Road, Bretherton",
    "sg:city":"Preston",
    "sg:classifiers":[
        {
            "category":"Farming",
            "subcategory":"Livestock Farm",
            "type":"Manufacturing & Wholesale Goods"
        }
    ],
    "sg:phone":"+44 1772 600382",
    "sg:postcode":"PR26 9AX",
    "sg:province":"Lancashire",
    "sg:tags":[
        "others"
    ],
    "wof:name":"Golden Acres Ltd.",
    "wof:placetype":"venue"
},
  "geometry": {"coordinates":[-2.798654,53.681431],"type":"Point"}
}