{
  "type": "Feature",
  "properties": {
    "iso:country":"GB",
    "sg:address":"Unit 11 Delbaron, Chertsey Road",
    "sg:city":"Shepperton",
    "sg:classifiers":[
        {
            "category":"Shopping",
            "subcategory":"Stationery & Office Supplies",
            "type":"Retail Goods"
        }
    ],
    "sg:phone":"+44 1932 569979",
    "sg:postcode":"TW17 9NU",
    "sg:province":"Surrey",
    "sg:tags":[
        "equipment"
    ],
    "wof:name":"Business Electronics Ltd.",
    "wof:placetype":"venue"
},
  "geometry": {"coordinates":[-0.4570440054,51.3878135681],"type":"Point"}
}