{
  "type": "Feature",
  "properties": {
    "iso:country":"GB",
    "sg:address":"Stirling Road, South Marston",
    "sg:city":"Swindon",
    "sg:classifiers":[
        {
            "category":"Communications",
            "subcategory":"News Services",
            "type":"Services"
        }
    ],
    "sg:phone":"+44 1793 831818",
    "sg:postcode":"SN3 4TQ",
    "sg:province":"Wiltshire",
    "sg:tags":[
        "press"
    ],
    "wof:name":"Wilson Tool International Ltd.",
    "wof:placetype":"venue"
},
  "geometry": {"coordinates":[-1.723333,51.591125],"type":"Point"}
}