{
  "type": "Feature",
  "properties": {
    "addr:full":"2 Thorley Neighbourhood Centre Bishops Stortford Essex CM23 4EG",
    "addr:housenumber":"2",
    "addr:postcode":"cm23 4eg",
    "iso:country":"GB",
    "sg:address":"2 Thorley Neighbourhood Centre",
    "sg:city":"Bishops Stortford",
    "sg:classifiers":[
        {
            "category":"Shopping",
            "subcategory":"Clothing, Apparel, & Fashions",
            "type":"Retail Goods"
        }
    ],
    "sg:postcode":"CM23 4EG",
    "sg:province":"Essex",
    "sg:tags":[
        "shop"
    ],
    "wof:name":"Catalogue Collections",
    "wof:placetype":"venue"
},
  "geometry": {"coordinates":[0.159056,51.853436],"type":"Point"}
}