{
  "type": "Feature",
  "properties": {
    "addr:full":"The Grove London Greater London W5 5DX",
    "addr:postcode":"w5 5dx",
    "addr:street":"The Grove",
    "iso:country":"GB",
    "sg:address":"The Grove",
    "sg:city":"London",
    "sg:classifiers":[
        {
            "category":"Education",
            "subcategory":"School",
            "type":"Public Place"
        }
    ],
    "sg:phone":"+44 20 8758 5001",
    "sg:postcode":"W5 5DX",
    "sg:province":"Greater London",
    "sg:tags":[
        "local",
        "authority"
    ],
    "wof:name":"St Saviours C Of E Infant & Nursery School",
    "wof:placetype":"venue"
},
  "geometry": {"coordinates":[-0.3024300039,51.5108985901],"type":"Point"}
}