{
  "type": "Feature",
  "properties": {
    "iso:country":"GB",
    "sg:address":"Chapel Close Farm, Prescott, Gotherington",
    "sg:city":"Cheltenham",
    "sg:classifiers":[
        {
            "category":"Farming",
            "subcategory":"Livestock Farm",
            "type":"Manufacturing & Wholesale Goods"
        },
        {
            "category":"Farming",
            "subcategory":"Farm",
            "type":"Manufacturing & Wholesale Goods"
        }
    ],
    "sg:phone":"+44 1242 673186",
    "sg:postcode":"GL52 9RE",
    "sg:province":"Gloucestershire",
    "sg:tags":[
        "mixed",
        "crop",
        "others"
    ],
    "wof:name":"J B Adamson",
    "wof:placetype":"venue"
},
  "geometry": {"coordinates":[-2.0561490059,51.9652404785],"type":"Point"}
}