{
  "type": "Feature",
  "properties": {
    "addr:full":"16 Salesbury Dr Billericay Essex CM11 2JH",
    "addr:housenumber":"16",
    "addr:postcode":"cm11 2jh",
    "addr:street":"Salesbury Dr",
    "iso:country":"GB",
    "sg:address":"16 Salesbury Dr",
    "sg:city":"Billericay",
    "sg:classifiers":[
        {
            "category":"Building & Trades",
            "subcategory":"Construction",
            "type":"Services"
        }
    ],
    "sg:phone":"+44 1277 631531",
    "sg:postcode":"CM11 2JH",
    "sg:province":"Essex",
    "sg:tags":[
        "dry",
        "lining",
        "plasterers",
        "screeders"
    ],
    "wof:name":"J C Girdlestone",
    "wof:placetype":"venue"
},
  "geometry": {"coordinates":[0.437985003,51.624584198],"type":"Point"}
}