{
  "type": "Feature",
  "properties": {
    "addr:full":"The Ticket Office, Station Road North Ferriby East Riding of Yorkshire HU14 3DJ",
    "addr:postcode":"hu14 3dj",
    "addr:street":"Station Road",
    "iso:country":"GB",
    "sg:address":"The Ticket Office, Station Road",
    "sg:city":"North Ferriby",
    "sg:classifiers":[
        {
            "category":"Home & Garden",
            "subcategory":"Home Furnishings",
            "type":"Retail Goods"
        }
    ],
    "sg:phone":"+44 1482 631643",
    "sg:postcode":"HU14 3DJ",
    "sg:province":"East Riding of Yorkshire",
    "sg:tags":[
        "furnishers",
        "planner",
        "kitchen"
    ],
    "wof:name":"Websters of Ferriby",
    "wof:placetype":"venue"
},
  "geometry": {"coordinates":[-0.504243,53.722614],"type":"Point"}
}