{
  "type": "Feature",
  "properties": {
    "iso:country":"GB",
    "sg:address":"45 Pickford Lane",
    "sg:city":"Bexleyheath",
    "sg:classifiers":[
        {
            "category":"Retail",
            "subcategory":"Auto Repair",
            "type":"Services"
        }
    ],
    "sg:phone":"+44 20 8303 6258",
    "sg:postcode":"DA7 4QU",
    "sg:province":"Kent",
    "sg:tags":[
        "modification",
        "garage"
    ],
    "wof:name":"Pickford Lane Service Centre",
    "wof:placetype":"venue"
},
  "geometry": {"coordinates":[0.132976,51.465515],"type":"Point"}
}