{
  "type": "Feature",
  "properties": {
    "addr:full":"20 Bracewell Rd Huddersfield West Yorkshire HD7 3JR",
    "addr:housenumber":"20",
    "addr:postcode":"hd7 3jr",
    "addr:street":"Bracewell Rd",
    "iso:country":"GB",
    "sg:address":"20 Bracewell Rd",
    "sg:city":"Huddersfield",
    "sg:classifiers":[
        {
            "category":"Building & Trades",
            "subcategory":"Construction",
            "type":"Services"
        }
    ],
    "sg:phone":"+44 1484 850448",
    "sg:postcode":"HD7 3JR",
    "sg:province":"West Yorkshire",
    "sg:tags":[
        "contractor",
        "paving",
        "driveway"
    ],
    "wof:name":"D. Haigh & Co Tarmacadam Specialists",
    "wof:placetype":"venue"
},
  "geometry": {"coordinates":[-1.78268,53.64695],"type":"Point"}
}