{
  "type": "Feature",
  "properties": {
    "iso:country":"GB",
    "sg:address":"77 Elmfield Road, Gosforth",
    "sg:city":"Newcastle-upon-tyne",
    "sg:classifiers":[
        {
            "category":"Health Services",
            "subcategory":"Dentist",
            "type":"Services"
        }
    ],
    "sg:phone":"+44 191 285 1150",
    "sg:postcode":"NE3 4BY",
    "sg:province":"Tyne and Wear",
    "wof:name":"Kelvin Lodge Dental Surgery",
    "wof:placetype":"venue"
},
  "geometry": {"coordinates":[-1.630484,54.999615],"type":"Point"}
}