{
  "type": "Feature",
  "properties": {
    "iso:country":"GB",
    "sg:address":"47 High Street, Biddulph",
    "sg:city":"Stoke-on-trent",
    "sg:classifiers":[
        {
            "category":"Shopping",
            "subcategory":"Crafts & Fabrics",
            "type":"Retail Goods"
        },
        {
            "category":"Manufacturing",
            "subcategory":"Pottery",
            "type":"Manufacturing & Wholesale Goods"
        }
    ],
    "sg:postcode":"ST8 6AD",
    "sg:province":"Staffordshire",
    "sg:tags":[
        "shop",
        "needlecraft",
        "wool",
        "furnaces"
    ],
    "wof:name":"Potteries Ceramic Services",
    "wof:placetype":"venue"
},
  "geometry": {"coordinates":[-2.175494,53.117004],"type":"Point"}
}