{
  "type": "Feature",
  "properties": {
    "addr:full":"56-58 Front Street Consett Durham DH8 5AL",
    "addr:housenumber":"56-58",
    "addr:postcode":"dh8 5al",
    "addr:street":"Front Street",
    "iso:country":"GB",
    "sg:address":"56-58 Front Street",
    "sg:city":"Consett",
    "sg:classifiers":[
        {
            "category":"Home & Garden",
            "subcategory":"Furniture",
            "type":"Retail Goods"
        }
    ],
    "sg:postcode":"DH8 5AL",
    "sg:province":"Durham",
    "wof:name":"Rendles (House Furnishers)",
    "wof:placetype":"venue"
},
  "geometry": {"coordinates":[-1.8304239511,54.8519134521],"type":"Point"}
}