{
  "type": "Feature",
  "properties": {
    "iso:country":"GB",
    "sg:address":"Goods Depot, Silverthorne Rd",
    "sg:city":"South Lambeth",
    "sg:classifiers":[
        {
            "category":"Professional",
            "subcategory":"Detective & Security Services",
            "type":"Services"
        }
    ],
    "sg:phone":"+44 20 7978 1227",
    "sg:postcode":"SW8 3HH",
    "sg:province":"Greater London",
    "wof:name":"Alacrity Security",
    "wof:placetype":"venue"
},
  "geometry": {"coordinates":[-0.147683993,51.4720535278],"type":"Point"}
}