{
  "type": "Feature",
  "properties": {
    "addr:full":"83 Station Road East Oxted Surrey RH8 0AX",
    "addr:housenumber":"83",
    "addr:postcode":"rh8 0ax",
    "addr:street":"Station Road East",
    "iso:country":"GB",
    "sg:address":"83 Station Road East",
    "sg:city":"Oxted",
    "sg:classifiers":[
        {
            "category":"Professional",
            "subcategory":"Printing & Photocopies",
            "type":"Services"
        }
    ],
    "sg:phone":"+44 1883 722282",
    "sg:postcode":"RH8 0AX",
    "sg:province":"Surrey",
    "sg:tags":[
        "duplicating",
        "copying"
    ],
    "wof:name":"S M S Creative Photography",
    "wof:placetype":"venue"
},
  "geometry": {"coordinates":[-0.002883,51.257648],"type":"Point"}
}