{
  "type": "Feature",
  "properties": {
    "addr:full":"22 Ulster Crescent Edinburgh City of Edinburgh EH8 7LD",
    "addr:housenumber":"22",
    "addr:postcode":"eh8 7ld",
    "addr:street":"Ulster Crescent",
    "iso:country":"GB",
    "sg:address":"22 Ulster Crescent",
    "sg:city":"Edinburgh",
    "sg:classifiers":[
        {
            "category":"Military Area",
            "subcategory":"Army Base",
            "type":"Public Place"
        }
    ],
    "sg:phone":"+44 131 652 9802",
    "sg:postcode":"EH8 7LD",
    "sg:province":"City of Edinburgh",
    "sg:tags":[
        "mnfr",
        "printed",
        "circuit"
    ],
    "wof:name":"Circatron",
    "wof:placetype":"venue"
},
  "geometry": {"coordinates":[-3.1486051083,55.9550514221],"type":"Point"}
}