{
  "type": "Feature",
  "properties": {
    "iso:country":"GB",
    "sg:address":"243 Green Lane",
    "sg:city":"Morden",
    "sg:classifiers":[
        {
            "category":"Place Of Worship",
            "type":"Public Place"
        }
    ],
    "sg:phone":"+44 20 8640 2912",
    "sg:postcode":"SM4 6SQ",
    "sg:province":"Surrey",
    "wof:name":"St Helier Methodist Church",
    "wof:placetype":"venue"
},
  "geometry": {"coordinates":[-0.197458,51.389992],"type":"Point"}
}