{
  "type": "Feature",
  "properties": {
    "addr:full":"Boghead Sawmill Fochabers Moray IV32 7PQ",
    "addr:postcode":"iv32 7pq",
    "iso:country":"GB",
    "sg:address":"Boghead Sawmill",
    "sg:city":"Fochabers",
    "sg:classifiers":[
        {
            "category":"Wholesale",
            "subcategory":"Construction Materials",
            "type":"Manufacturing & Wholesale Goods"
        }
    ],
    "sg:phone":"+44 1343 821140",
    "sg:postcode":"IV32 7PQ",
    "sg:province":"Moray",
    "sg:tags":[
        "sawdust",
        "sawmills",
        "shaving"
    ],
    "wof:name":"Moray Timber Products",
    "wof:placetype":"venue"
},
  "geometry": {"coordinates":[-3.0974979401,57.614238739],"type":"Point"}
}