{
  "type": "Feature",
  "properties": {
    "addr:full":"12 Shepherds Bush Market Shepherd's Bush Greater London W12 8LH",
    "addr:housenumber":"12",
    "addr:postcode":"w12 8lh",
    "addr:street":"Shepherds Bush Market",
    "iso:country":"GB",
    "sg:address":"12 Shepherds Bush Market",
    "sg:city":"Shepherd's Bush",
    "sg:classifiers":[
        {
            "category":"Shopping",
            "subcategory":"Mobile Phones",
            "type":"Retail Goods"
        }
    ],
    "sg:phone":"+44 20 8749 8575",
    "sg:postcode":"W12 8LH",
    "sg:province":"Greater London",
    "wof:name":"Ali International",
    "wof:placetype":"venue"
},
  "geometry": {"coordinates":[-0.22744,51.505619],"type":"Point"}
}