{
  "type": "Feature",
  "properties": {
    "addr:full":"The Old Stables, The St, Shotesham All Saints Norwich Norfolk NR15 1AP",
    "addr:housenumber":"the",
    "addr:postcode":"nr15 1ap",
    "addr:street":"Norwich",
    "iso:country":"GB",
    "sg:address":"The Old Stables, The St, Shotesham All Saints",
    "sg:city":"Norwich",
    "sg:classifiers":[
        {
            "category":"Real Estate",
            "subcategory":"Real Estate Operator",
            "type":"Services"
        }
    ],
    "sg:postcode":"NR15 1AP",
    "sg:province":"Norfolk",
    "sg:tags":[
        "letting",
        "agent"
    ],
    "wof:name":"Barrett-Vane,S,",
    "wof:placetype":"venue"
},
  "geometry": {"coordinates":[1.2948999405,52.6224937439],"type":"Point"}
}