{
  "type": "Feature",
  "properties": {
    "iso:country":"GB",
    "sg:address":"17 Greenbank Road",
    "sg:city":"Watford",
    "sg:classifiers":[
        {
            "category":"Building & Trades",
            "subcategory":"Construction",
            "type":"Services"
        }
    ],
    "sg:phone":"+44 1923 661324",
    "sg:postcode":"WD17 4JJ",
    "sg:province":"Hertfordshire",
    "sg:tags":[
        "builder"
    ],
    "wof:name":"D C Builders",
    "wof:placetype":"venue"
},
  "geometry": {"coordinates":[-0.4249489903,51.6804847717],"type":"Point"}
}