{
  "type": "Feature",
  "properties": {
    "addr:full":"135 Palatine Rd Manchester Greater Manchester M20 9YA",
    "addr:housenumber":"135",
    "addr:postcode":"m20 9ya",
    "addr:street":"Palatine Rd",
    "iso:country":"GB",
    "sg:address":"135 Palatine Rd",
    "sg:city":"Manchester",
    "sg:classifiers":[
        {
            "category":"Health Services",
            "subcategory":"Doctor",
            "type":"Services"
        }
    ],
    "sg:phone":"+44 161 445 0332",
    "sg:postcode":"M20 9YA",
    "sg:province":"Greater Manchester",
    "sg:tags":[
        "surgeon"
    ],
    "wof:name":"M A Sambrook",
    "wof:placetype":"venue"
},
  "geometry": {"coordinates":[-2.2386009693,53.4235191345],"type":"Point"}
}