{
  "type": "Feature",
  "properties": {
    "addr:full":"The Plassey Craft Centre, Eyton Wrexham Wrexham LL13 0SP",
    "addr:postcode":"ll13 0sp",
    "addr:street":"Eyton",
    "iso:country":"GB",
    "sg:address":"The Plassey Craft Centre, Eyton",
    "sg:city":"Wrexham",
    "sg:classifiers":[
        {
            "category":"Shopping",
            "subcategory":"Clothing, Apparel, & Fashions",
            "type":"Retail Goods"
        }
    ],
    "sg:phone":"+44 1978 780601",
    "sg:postcode":"LL13 0SP",
    "sg:province":"Wrexham",
    "sg:tags":[
        "ladieswear"
    ],
    "wof:name":"The Barn Boutique",
    "wof:placetype":"venue"
},
  "geometry": {"coordinates":[-2.9693770409,52.9971961975],"type":"Point"}
}