{
  "type": "Feature",
  "properties": {
    "iso:country":"GB",
    "sg:address":"Faxton Street",
    "sg:city":"Gillingham",
    "sg:classifiers":[
        {
            "category":"Social Services",
            "subcategory":"Adult Care",
            "type":"Services"
        },
        {
            "category":"Social Services",
            "subcategory":"Retirement Home",
            "type":"Services"
        }
    ],
    "sg:phone":"+44 1634 572723",
    "sg:postcode":"ME7 5TW",
    "sg:province":"Kent",
    "sg:tags":[
        "housing",
        "sheltered",
        "accommodation"
    ],
    "wof:name":"St Mark's House",
    "wof:placetype":"venue"
},
  "geometry": {"coordinates":[0.5495430231,51.3864593506],"type":"Point"}
}