{
  "type": "Feature",
  "properties": {
    "iso:country":"GB",
    "sg:address":"P O Box 244",
    "sg:city":"Bristol",
    "sg:classifiers":[
        {
            "category":"Wholesale",
            "subcategory":"Vending Machines",
            "type":"Manufacturing & Wholesale Goods"
        }
    ],
    "sg:phone":"+44 1179 78111",
    "sg:postcode":"BS99 7UJ",
    "sg:province":"City of Bristol",
    "sg:tags":[
        "sale"
    ],
    "wof:name":"Mayfair Vending Ltd.",
    "wof:placetype":"venue"
},
  "geometry": {"coordinates":[-2.594340086,51.4544181824],"type":"Point"}
}