{
  "type": "Feature",
  "properties": {
    "addr:full":"11 Mill Park Avenue Hornchurch Essex RM12 6HA",
    "addr:housenumber":"11",
    "addr:postcode":"rm12 6ha",
    "addr:street":"Mill Park Avenue",
    "iso:country":"GB",
    "sg:address":"11 Mill Park Avenue",
    "sg:city":"Hornchurch",
    "sg:classifiers":[
        {
            "category":"Building & Trades",
            "subcategory":"Construction",
            "type":"Services"
        }
    ],
    "sg:phone":"+44 1708 442265",
    "sg:postcode":"RM12 6HA",
    "sg:province":"Essex",
    "sg:tags":[
        "builder"
    ],
    "wof:name":"Meadway Construction",
    "wof:placetype":"venue"
},
  "geometry": {"coordinates":[0.223044,51.55941],"type":"Point"}
}