{
  "type": "Feature",
  "properties": {
    "iso:country":"GB",
    "sg:address":"66 Berkeley Street",
    "sg:city":"Glasgow",
    "sg:classifiers":[
        {
            "category":"Real Estate",
            "subcategory":"Architect",
            "type":"Services"
        }
    ],
    "sg:phone":"+44 141 204 5003",
    "sg:postcode":"G3 7DS",
    "sg:province":"Glasgow City",
    "wof:name":"Grant Design",
    "wof:placetype":"venue"
},
  "geometry": {"coordinates":[-4.2749919891,55.8654785156],"type":"Point"}
}