{
  "type": "Feature",
  "properties": {
    "iso:country":"GB",
    "sg:address":"Poplar Ho, Jackson St",
    "sg:city":"St Helens",
    "sg:classifiers":[
        {
            "category":"Professional",
            "subcategory":"Printing & Photocopies",
            "type":"Services"
        }
    ],
    "sg:phone":"+44 1744 23363",
    "sg:postcode":"WA9 3AP",
    "sg:province":"Cheshire",
    "sg:tags":[
        "printer"
    ],
    "wof:name":"Poplar Services Ltd",
    "wof:placetype":"venue"
},
  "geometry": {"coordinates":[-2.71982,53.447201],"type":"Point"}
}