{
  "type": "Feature",
  "properties": {
    "addr:full":"40 Kingston Road Staines Berkshire TW18 4NL",
    "addr:housenumber":"40",
    "addr:postcode":"tw18 4nl",
    "addr:street":"Kingston Road",
    "iso:country":"GB",
    "sg:address":"40 Kingston Road",
    "sg:city":"Staines",
    "sg:classifiers":[
        {
            "category":"Real Estate",
            "subcategory":"Real Estate Agent",
            "type":"Services"
        }
    ],
    "sg:phone":"+44 1784 469538",
    "sg:postcode":"TW18 4NL",
    "sg:province":"Berkshire",
    "wof:name":"Gleeson Management Ltd.",
    "wof:placetype":"venue"
},
  "geometry": {"coordinates":[-0.5040599704,51.4338150024],"type":"Point"}
}