{
  "type": "Feature",
  "properties": {
    "iso:country":"GB",
    "sg:address":"352 Kew Rd",
    "sg:city":"Richmond",
    "sg:classifiers":[
        {
            "category":"Education",
            "subcategory":"Special Training",
            "type":"Public Place"
        }
    ],
    "sg:phone":"+44 20 8948 4393",
    "sg:postcode":"TW9 3DU",
    "sg:province":"Greater London",
    "sg:tags":[
        "school",
        "language"
    ],
    "wof:name":"Kew Language Centre",
    "wof:placetype":"venue"
},
  "geometry": {"coordinates":[-0.286918,51.482368],"type":"Point"}
}