{
  "type": "Feature",
  "properties": {
    "addr:full":"275 Court Road London Greater London SE9 4TH",
    "addr:housenumber":"275",
    "addr:postcode":"se9 4th",
    "addr:street":"Court Road",
    "iso:country":"GB",
    "sg:address":"275 Court Road",
    "sg:city":"London",
    "sg:classifiers":[
        {
            "category":"Shopping",
            "subcategory":"Florist",
            "type":"Retail Goods"
        }
    ],
    "sg:phone":"+44 20 8857 6559",
    "sg:postcode":"SE9 4TH",
    "sg:province":"Greater London",
    "wof:name":"The Flower Boutique",
    "wof:placetype":"venue"
},
  "geometry": {"coordinates":[0.0457680002,51.4364089966],"type":"Point"}
}