{
  "type": "Feature",
  "properties": {
    "addr:full":"Dcc Service Suite No 10, 38 New Oxford Street London Greater London WC1A 1EP",
    "addr:housenumber":"suite no;38",
    "addr:postcode":"wc1a 1ep",
    "addr:street":"New Oxford Street",
    "iso:country":"GB",
    "sg:address":"Dcc Service Suite No 10, 38 New Oxford Street",
    "sg:city":"London",
    "sg:classifiers":[
        {
            "category":"Professional",
            "subcategory":"Management & Consulting",
            "type":"Services"
        }
    ],
    "sg:postcode":"WC1A 1EP",
    "sg:province":"Greater London",
    "sg:tags":[
        "consultant",
        "business"
    ],
    "wof:name":"Europe Enterprises Ltd.",
    "wof:placetype":"venue"
},
  "geometry": {"coordinates":[-0.1443900019,51.5149307251],"type":"Point"}
}