{
  "type": "Feature",
  "properties": {
    "addr:full":"163 Lavender Hill Battersea Greater London SW11 5QH",
    "addr:housenumber":"163",
    "addr:postcode":"sw11 5qh",
    "addr:street":"Lavender Hill",
    "iso:country":"GB",
    "sg:address":"163 Lavender Hill",
    "sg:city":"Battersea",
    "sg:classifiers":[
        {
            "category":"Restaurant",
            "type":"Food & Drink"
        }
    ],
    "sg:phone":"+44 20 7223 1046",
    "sg:postcode":"SW11 5QH",
    "sg:province":"Greater London",
    "wof:name":"Fidelio",
    "wof:placetype":"venue"
},
  "geometry": {"coordinates":[-0.1588090062,51.4649047852],"type":"Point"}
}