{
  "type": "Feature",
  "properties": {
    "iso:country":"GB",
    "sg:address":"27 Meadowcroft, Higher Kinnerton",
    "sg:city":"Chester",
    "sg:classifiers":[
        {
            "category":"Building & Trades",
            "subcategory":"Construction",
            "type":"Services"
        }
    ],
    "sg:postcode":"CH4 9AY",
    "sg:province":"Cheshire",
    "sg:tags":[
        "decorator",
        "painter"
    ],
    "wof:name":"David Shone",
    "wof:placetype":"venue"
},
  "geometry": {"coordinates":[-3.001594,53.143883],"type":"Point"}
}