{
  "type": "Feature",
  "properties": {
    "addr:full":"Station Road, Yeoford Crediton Devon EX17 5HU",
    "addr:postcode":"ex17 5hu",
    "addr:street":"Station Road",
    "iso:country":"GB",
    "sg:address":"Station Road, Yeoford",
    "sg:city":"Crediton",
    "sg:classifiers":[
        {
            "category":"Government",
            "subcategory":"Post Office",
            "type":"Public Place"
        }
    ],
    "sg:phone":"+44 1363 85296",
    "sg:postcode":"EX17 5HU",
    "sg:province":"Devon",
    "wof:name":"Yeoford Post Office",
    "wof:placetype":"venue"
},
  "geometry": {"coordinates":[-3.7275791168,50.776725769],"type":"Point"}
}