{
  "type": "Feature",
  "properties": {
    "iso:country":"GB",
    "sg:address":"89 Poplar Rd",
    "sg:city":"Redditch",
    "sg:classifiers":[
        {
            "category":"Retail",
            "subcategory":"Repair Shop",
            "type":"Services"
        },
        {
            "category":"Shopping",
            "subcategory":"Used Merchandise",
            "type":"Retail Goods"
        }
    ],
    "sg:phone":"+44 1527 61290",
    "sg:postcode":"B97 6NY",
    "sg:province":"Warwickshire",
    "sg:tags":[
        "sale",
        "second-hand"
    ],
    "wof:name":"Homestyle",
    "wof:placetype":"venue"
},
  "geometry": {"coordinates":[-1.9669799805,52.3051490784],"type":"Point"}
}