{
  "type": "Feature",
  "properties": {
    "iso:country":"GB",
    "sg:address":"Cranswick Industrial Estate, Beverly Road, Cranswick",
    "sg:city":"Driffield",
    "sg:classifiers":[
        {
            "category":"Autos & Motor Vehicles",
            "subcategory":"Automobile Sales",
            "type":"Retail Goods"
        }
    ],
    "sg:phone":"+44 1377 271383",
    "sg:postcode":"YO25 9PQ",
    "sg:province":"East Riding of Yorkshire",
    "sg:tags":[
        "car"
    ],
    "wof:name":"Frysport Ltd.",
    "wof:placetype":"venue"
},
  "geometry": {"coordinates":[-0.4450699985,53.9575042725],"type":"Point"}
}