{
  "type": "Feature",
  "properties": {
    "addr:full":"34 Abbeville Road London Greater London SW4 9NG",
    "addr:housenumber":"34",
    "addr:postcode":"sw4 9ng",
    "addr:street":"Abbeville Road",
    "iso:country":"GB",
    "sg:address":"34 Abbeville Road",
    "sg:city":"London",
    "sg:classifiers":[
        {
            "category":"Government",
            "subcategory":"Post Office",
            "type":"Public Place"
        }
    ],
    "sg:phone":"+44 20 8673 1749",
    "sg:postcode":"SW4 9NG",
    "sg:province":"Greater London",
    "wof:name":"Abbeville Rd Post Office",
    "wof:placetype":"venue"
},
  "geometry": {"coordinates":[-0.1398739964,51.454158783],"type":"Point"}
}