{
  "type": "Feature",
  "properties": {
    "addr:full":"32 Morten Close London Greater London SW4 8LG",
    "addr:housenumber":"32",
    "addr:postcode":"sw4 8lg",
    "addr:street":"Morten Close",
    "iso:country":"GB",
    "sg:address":"32 Morten Close",
    "sg:city":"London",
    "sg:classifiers":[
        {
            "category":"Building & Trades",
            "subcategory":"Cleaning & Sanitation",
            "type":"Services"
        }
    ],
    "sg:phone":"+44 20 8678 6160",
    "sg:postcode":"SW4 8LG",
    "sg:province":"Greater London",
    "sg:tags":[
        "commercial"
    ],
    "wof:name":"Exhibit General Cleaning Services",
    "wof:placetype":"venue"
},
  "geometry": {"coordinates":[-0.134044,51.451946],"type":"Point"}
}