{
  "type": "Feature",
  "properties": {
    "addr:full":"Russell Square, Madeley Telford Shropshire TF7 5AQ",
    "addr:postcode":"tf7 5aq",
    "addr:street":"Russell Square",
    "iso:country":"GB",
    "sg:address":"Russell Square, Madeley",
    "sg:city":"Telford",
    "sg:classifiers":[
        {
            "category":"Shopping",
            "subcategory":"Florist",
            "type":"Retail Goods"
        }
    ],
    "sg:phone":"+44 1952 586346",
    "sg:postcode":"TF7 5AQ",
    "sg:province":"Shropshire",
    "wof:name":"The Flower Shop",
    "wof:placetype":"venue"
},
  "geometry": {"coordinates":[-2.4559979439,52.6354446411],"type":"Point"}
}