{
  "type": "Feature",
  "properties": {
    "addr:full":"23 Station Square, Petts Wood Orpington Kent BR5 1LY",
    "addr:housenumber":"23",
    "addr:postcode":"br5 1ly",
    "addr:street":"Station Square Petts",
    "iso:country":"GB",
    "sg:address":"23 Station Square, Petts Wood",
    "sg:city":"Orpington",
    "sg:classifiers":[
        {
            "category":"Fast Food",
            "type":"Food & Drink"
        }
    ],
    "sg:phone":"+44 1689 820427",
    "sg:postcode":"BR5 1LY",
    "sg:province":"Kent",
    "sg:tags":[
        "away",
        "take"
    ],
    "wof:name":"Ming",
    "wof:placetype":"venue"
},
  "geometry": {"coordinates":[0.0757440031,51.3892555237],"type":"Point"}
}