{
  "type": "Feature",
  "properties": {
    "iso:country":"GB",
    "sg:address":"132 Northampton Road, Brixworth",
    "sg:city":"Northampton",
    "sg:classifiers":[
        {
            "category":"Professional",
            "subcategory":"Business Services",
            "type":"Services"
        }
    ],
    "sg:postcode":"NN6 9BU",
    "sg:province":"Northamptonshire",
    "sg:tags":[
        "bookmaker"
    ],
    "wof:name":"T Smith",
    "wof:placetype":"venue"
},
  "geometry": {"coordinates":[-0.903234,52.329327],"type":"Point"}
}