{
  "type": "Feature",
  "properties": {
    "iso:country":"GB",
    "sg:address":"Unit F1 Innsworth Technology Park, Innsworth Lane",
    "sg:city":"Gloucester",
    "sg:classifiers":[
        {
            "category":"Fast Food",
            "type":"Food & Drink"
        }
    ],
    "sg:phone":"+44 1452 530159",
    "sg:postcode":"GL3 1DL",
    "sg:province":"Gloucestershire",
    "sg:tags":[
        "away",
        "take"
    ],
    "wof:name":"Balti Park Diner",
    "wof:placetype":"venue"
},
  "geometry": {"coordinates":[-2.202919,51.888386],"type":"Point"}
}