{
  "type": "Feature",
  "properties": {
    "addr:full":"Mongewell Park Farm, Mongewell Wallingford Oxfordshire OX10 8BS",
    "addr:housenumber":"mongewell",
    "addr:postcode":"ox10 8bs",
    "iso:country":"GB",
    "sg:address":"Mongewell Park Farm, Mongewell",
    "sg:city":"Wallingford",
    "sg:classifiers":[
        {
            "category":"Farming",
            "subcategory":"Livestock Farm",
            "type":"Manufacturing & Wholesale Goods"
        }
    ],
    "sg:postcode":"OX10 8BS",
    "sg:province":"Oxfordshire",
    "sg:tags":[
        "others"
    ],
    "wof:name":"Mongewell Park Farm",
    "wof:placetype":"venue"
},
  "geometry": {"coordinates":[-1.1195640564,51.5852432251],"type":"Point"}
}