{
  "type": "Feature",
  "properties": {
    "iso:country":"GB",
    "sg:address":"Alfold Rd",
    "sg:city":"Cranleigh",
    "sg:classifiers":[
        {
            "category":"Farming",
            "subcategory":"Livestock Farm",
            "type":"Manufacturing & Wholesale Goods"
        }
    ],
    "sg:phone":"+44 1483 273344",
    "sg:postcode":"GU6 8JT",
    "sg:province":"Surrey",
    "sg:tags":[
        "others"
    ],
    "wof:name":"Holdhurst Farm",
    "wof:placetype":"venue"
},
  "geometry": {"coordinates":[-0.5066859722,51.1415176392],"type":"Point"}
}