{
  "type": "Feature",
  "properties": {
    "addr:full":"5 Millbrook Court, Magor Caldicot Monmouthshire NP26 3JN",
    "addr:housenumber":"5",
    "addr:postcode":"np26 3jn",
    "addr:street":"Millbrook Court",
    "iso:country":"GB",
    "sg:address":"5 Millbrook Court, Magor",
    "sg:city":"Caldicot",
    "sg:classifiers":[
        {
            "category":"Building & Trades",
            "subcategory":"Construction",
            "type":"Services"
        }
    ],
    "sg:phone":"+44 1633 880455",
    "sg:postcode":"NP26 3JN",
    "sg:province":"Monmouthshire",
    "sg:tags":[
        "erectors",
        "platform",
        "builder",
        "work",
        "scaffold"
    ],
    "wof:name":"J B Scaffolding",
    "wof:placetype":"venue"
},
  "geometry": {"coordinates":[-2.748045,51.585957],"type":"Point"}
}