{
  "type": "Feature",
  "properties": {
    "addr:full":"Cotwall End Nature Centre Dudley Staffordshire DY3 3UE",
    "addr:postcode":"dy3 3ue",
    "iso:country":"GB",
    "sg:address":"Cotwall End Nature Centre",
    "sg:city":"Dudley",
    "sg:classifiers":[
        {
            "category":"Cafe",
            "type":"Food & Drink"
        }
    ],
    "sg:phone":"+44 1902 675417",
    "sg:postcode":"DY3 3UE",
    "sg:province":"Staffordshire",
    "sg:tags":[
        "tea",
        "room"
    ],
    "wof:name":"Ringside Refreshments",
    "wof:placetype":"venue"
},
  "geometry": {"coordinates":[-2.127779007,52.5384597778],"type":"Point"}
}