{
  "type": "Feature",
  "properties": {
    "addr:full":"22 Greenbank Lane Northwich Cheshire CW8 1JQ",
    "addr:housenumber":"22",
    "addr:postcode":"cw8 1jq",
    "addr:street":"Greenbank Lane",
    "iso:country":"GB",
    "sg:address":"22 Greenbank Lane",
    "sg:city":"Northwich",
    "sg:classifiers":[
        {
            "category":"Shopping",
            "subcategory":"Bicycles & Sporting Goods",
            "type":"Retail Goods"
        }
    ],
    "sg:phone":"+44 1606 76170",
    "sg:postcode":"CW8 1JQ",
    "sg:province":"Cheshire",
    "sg:tags":[
        "cycle",
        "accessory"
    ],
    "wof:name":"Hartford Cycles",
    "wof:placetype":"venue"
},
  "geometry": {"coordinates":[-2.5345840454,53.2500267029],"type":"Point"}
}