{
  "type": "Feature",
  "properties": {
    "addr:full":"High Street, Market Lavington Devizes Wiltshire SN10 4AG",
    "addr:postcode":"sn10 4ag",
    "addr:street":"High Street",
    "iso:country":"GB",
    "sg:address":"High Street, Market Lavington",
    "sg:city":"Devizes",
    "sg:classifiers":[
        {
            "category":"Education",
            "subcategory":"Library",
            "type":"Public Place"
        }
    ],
    "sg:phone":"+44 1380 818358",
    "sg:postcode":"SN10 4AG",
    "sg:province":"Wiltshire",
    "sg:tags":[
        "book"
    ],
    "wof:name":"Market Lavington Library",
    "wof:placetype":"venue"
},
  "geometry": {"coordinates":[-1.9705799818,51.2967262268],"type":"Point"}
}