{
  "type": "Feature",
  "properties": {
    "iso:country":"GB",
    "sg:address":"St Marys Road, Dymchurch",
    "sg:city":"Romney Marsh",
    "sg:classifiers":[
        {
            "category":"Farming",
            "subcategory":"Livestock Farm",
            "type":"Manufacturing & Wholesale Goods"
        }
    ],
    "sg:phone":"+44 1303 872103",
    "sg:postcode":"TN29 0PW",
    "sg:province":"Kent",
    "sg:tags":[
        "others"
    ],
    "wof:name":"E & J Piper",
    "wof:placetype":"venue"
},
  "geometry": {"coordinates":[0.990367,51.023941],"type":"Point"}
}