{
  "type": "Feature",
  "properties": {
    "iso:country":"GB",
    "sg:address":"Staples Hill, Kirdford",
    "sg:city":"Billingshurst",
    "sg:classifiers":[
        {
            "category":"Farming",
            "subcategory":"Farm",
            "type":"Manufacturing & Wholesale Goods"
        }
    ],
    "sg:phone":"+44 1403 820287",
    "sg:postcode":"RH14 0JL",
    "sg:province":"West Sussex",
    "sg:tags":[
        "egg",
        "producer"
    ],
    "wof:name":"Foxleigh Farm",
    "wof:placetype":"venue"
},
  "geometry": {"coordinates":[-0.5526239872,51.0324287415],"type":"Point"}
}