{
  "type": "Feature",
  "properties": {
    "addr:full":"Shadwell House, 65 Lower Green Road Rusthall Tunbridge Wells Kent TN4 8TW",
    "addr:housenumber":"65",
    "addr:postcode":"tn4 8tw",
    "addr:street":"Lower Green Road;Wells",
    "iso:country":"GB",
    "sg:address":"Shadwell House, 65 Lower Green Road Rusthall",
    "sg:city":"Tunbridge Wells",
    "sg:classifiers":[
        {
            "category":"Retail",
            "subcategory":"Event Space",
            "type":"Services"
        }
    ],
    "sg:postcode":"TN4 8TW",
    "sg:province":"Kent",
    "sg:tags":[
        "exhibition",
        "organiser"
    ],
    "wof:name":"Revolution Events Ltd",
    "wof:placetype":"venue"
},
  "geometry": {"coordinates":[0.231309,51.139149],"type":"Point"}
}