{
  "type": "Feature",
  "properties": {
    "iso:country":"GB",
    "sg:address":"7-11 Warwick Road",
    "sg:city":"Peterborough",
    "sg:classifiers":[
        {
            "category":"Government",
            "subcategory":"Post Office",
            "type":"Public Place"
        }
    ],
    "sg:phone":"+44 1733 571108",
    "sg:postcode":"PE4 6DE",
    "sg:province":"Cambridgeshire",
    "wof:name":"Walton Post Office",
    "wof:placetype":"venue"
},
  "geometry": {"coordinates":[-0.27103,52.606468],"type":"Point"}
}