{
  "type": "Feature",
  "properties": {
    "addr:full":"Ty-glas Avenue, Llanishen Cardiff Cardiff CF14 5EB",
    "addr:postcode":"cf14 5eb",
    "addr:street":"Avenue",
    "iso:country":"GB",
    "sg:address":"Ty-glas Avenue, Llanishen",
    "sg:city":"Cardiff",
    "sg:classifiers":[
        {
            "category":"Community Center",
            "type":"Public Place"
        },
        {
            "category":"Government",
            "subcategory":"Office",
            "type":"Public Place"
        }
    ],
    "sg:phone":"+44 29 2076 2411",
    "sg:postcode":"CF14 5EB",
    "sg:province":"Cardiff",
    "sg:tags":[
        "recreation",
        "local",
        "leisure",
        "centre"
    ],
    "wof:name":"Llanishen Leisure Centre",
    "wof:placetype":"venue"
},
  "geometry": {"coordinates":[-3.195525,51.528248],"type":"Point"}
}