{
  "type": "Feature",
  "properties": {
    "iso:country":"GB",
    "sg:address":"Head Dyke Lane, Pilling",
    "sg:city":"Preston",
    "sg:classifiers":[
        {
            "category":"Building & Trades",
            "subcategory":"Landscaping Services",
            "type":"Services"
        }
    ],
    "sg:phone":"+44 1253 790327",
    "sg:postcode":"PR3 6SJ",
    "sg:province":"Lancashire",
    "sg:tags":[
        "contractor",
        "drainage"
    ],
    "wof:name":"Curwen Contractors",
    "wof:placetype":"venue"
},
  "geometry": {"coordinates":[-2.9332060814,53.9166221619],"type":"Point"}
}