{
  "type": "Feature",
  "properties": {
    "addr:full":"9 The Hart Centre Fleet Hampshire GU51 3LA",
    "addr:housenumber":"9",
    "addr:postcode":"gu51 3la",
    "addr:street":"The Hart Centre Fleet",
    "iso:country":"GB",
    "sg:address":"9 The Hart Centre",
    "sg:city":"Fleet",
    "sg:classifiers":[
        {
            "category":"Shopping",
            "subcategory":"Books",
            "type":"Retail Goods"
        }
    ],
    "sg:phone":"+44 1252 816852",
    "sg:postcode":"GU51 3LA",
    "sg:province":"Hampshire",
    "sg:tags":[
        "bookseller"
    ],
    "wof:name":"Maher the Bookseller",
    "wof:placetype":"venue"
},
  "geometry": {"coordinates":[-0.830815,51.2775],"type":"Point"}
}