{
  "type": "Feature",
  "properties": {
    "addr:full":"13 Bradford Rd Pudsey West Yorkshire LS28 6AT",
    "addr:housenumber":"13",
    "addr:postcode":"ls28 6at",
    "addr:street":"Bradford Rd",
    "iso:country":"GB",
    "sg:address":"13 Bradford Rd",
    "sg:city":"Pudsey",
    "sg:classifiers":[
        {
            "category":"Retail",
            "subcategory":"Auto Rental",
            "type":"Services"
        }
    ],
    "sg:phone":"+44 113 256 0996",
    "sg:postcode":"LS28 6AT",
    "sg:province":"West Yorkshire",
    "sg:tags":[
        "truck",
        "hire",
        "van"
    ],
    "wof:name":"Practical Car & Van Rental",
    "wof:placetype":"venue"
},
  "geometry": {"coordinates":[-1.6936689615,53.8039283752],"type":"Point"}
}