{
  "type": "Feature",
  "properties": {
    "addr:full":"Unit 14/15 Crewe Cheshire CW1 6FF",
    "addr:housenumber":"unit 14 / 15",
    "addr:postcode":"cw1 6ff",
    "iso:country":"GB",
    "sg:address":"Unit 14/15",
    "sg:city":"Crewe",
    "sg:classifiers":[
        {
            "category":"Manufacturing",
            "subcategory":"Electronics",
            "type":"Manufacturing & Wholesale Goods"
        },
        {
            "category":"Retail",
            "subcategory":"Auto Repair",
            "type":"Services"
        }
    ],
    "sg:phone":"+44 1270 252566",
    "sg:postcode":"CW1 6FF",
    "sg:province":"Cheshire",
    "sg:tags":[
        "control",
        "-",
        "component",
        "related",
        "garage",
        "electronic"
    ],
    "wof:name":"Tru-Form",
    "wof:placetype":"venue"
},
  "geometry": {"coordinates":[-2.4178299904,53.0899505615],"type":"Point"}
}