{
  "type": "Feature",
  "properties": {
    "addr:full":"18 Millard Way Hitchin Hertfordshire SG4 0QE",
    "addr:housenumber":"18",
    "addr:postcode":"sg4 0qe",
    "addr:street":"Millard Way",
    "iso:country":"GB",
    "sg:address":"18 Millard Way",
    "sg:city":"Hitchin",
    "sg:classifiers":[
        {
            "category":"Building & Trades",
            "subcategory":"Construction",
            "type":"Services"
        }
    ],
    "sg:postcode":"SG4 0QE",
    "sg:province":"Hertfordshire",
    "sg:tags":[
        "builder"
    ],
    "wof:name":"Castle Construction Services Ltd.",
    "wof:placetype":"venue"
},
  "geometry": {"coordinates":[-0.253472,51.959927],"type":"Point"}
}