{
  "type": "Feature",
  "properties": {
    "iso:country":"GB",
    "sg:address":"Mount Pleasant Farm",
    "sg:city":"Bishop Auckland",
    "sg:classifiers":[
        {
            "category":"Farming",
            "subcategory":"Livestock Farm",
            "type":"Manufacturing & Wholesale Goods"
        }
    ],
    "sg:phone":"+44 1388 718362",
    "sg:postcode":"DL13 5NG",
    "sg:province":"Durham",
    "sg:tags":[
        "others"
    ],
    "wof:name":"Charlton Kevin",
    "wof:placetype":"venue"
},
  "geometry": {"coordinates":[-1.8889900446,54.6359100342],"type":"Point"}
}