{
  "type": "Feature",
  "properties": {
    "addr:full":"Newsham Farm, Hutton Roof Penrith Cumbria CA11 0XX",
    "addr:housenumber":"roof",
    "addr:postcode":"ca11 0xx",
    "iso:country":"GB",
    "sg:address":"Newsham Farm, Hutton Roof",
    "sg:city":"Penrith",
    "sg:classifiers":[
        {
            "category":"Farming",
            "subcategory":"Livestock Farm",
            "type":"Manufacturing & Wholesale Goods"
        }
    ],
    "sg:phone":"+44 17684 84252",
    "sg:postcode":"CA11 0XX",
    "sg:province":"Cumbria",
    "sg:tags":[
        "others"
    ],
    "wof:name":"J Y Elliott & Son",
    "wof:placetype":"venue"
},
  "geometry": {"coordinates":[-2.975649,54.697861],"type":"Point"}
}