{
  "type": "Feature",
  "properties": {
    "iso:country":"GB",
    "sg:address":"P O Box 18",
    "sg:city":"Eastleigh",
    "sg:classifiers":[
        {
            "category":"Personal",
            "type":"Services"
        }
    ],
    "sg:postcode":"SO50 7ZD",
    "sg:province":"Hampshire",
    "sg:tags":[
        "wedding"
    ],
    "wof:name":"Crownline",
    "wof:placetype":"venue"
},
  "geometry": {"coordinates":[-1.3058160543,50.984413147],"type":"Point"}
}