{
  "type": "Feature",
  "properties": {
    "iso:country":"GB",
    "sg:address":"359 Harehills Lane, Harehills",
    "sg:city":"Leeds",
    "sg:classifiers":[
        {
            "category":"Food & Beverages",
            "subcategory":"Fruits & Vegetables",
            "type":"Retail Goods"
        }
    ],
    "sg:phone":"+44 113 249 6835",
    "sg:postcode":"LS9 6AX",
    "sg:province":"West Yorkshire",
    "sg:tags":[
        "greengrocer"
    ],
    "wof:name":"Turners Fruit Market",
    "wof:placetype":"venue"
},
  "geometry": {"coordinates":[-1.5094109774,53.8095016479],"type":"Point"}
}