{
  "type": "Feature",
  "properties": {
    "addr:full":"7 St Dominic St Penzance Cornwall TR18 2DL",
    "addr:housenumber":"7",
    "addr:postcode":"tr18 2dl",
    "addr:street":"St Dominic St",
    "iso:country":"GB",
    "sg:address":"7 St Dominic St",
    "sg:city":"Penzance",
    "sg:classifiers":[
        {
            "category":"Military Area",
            "subcategory":"Air Force Base",
            "type":"Public Place"
        }
    ],
    "sg:phone":"+44 1736 368787",
    "sg:postcode":"TR18 2DL",
    "sg:province":"Cornwall",
    "sg:tags":[
        "taxi",
        "hire",
        "private"
    ],
    "wof:name":"Colin's Taxis",
    "wof:placetype":"venue"
},
  "geometry": {"coordinates":[-5.536763,50.122608],"type":"Point"}
}