{
  "type": "Feature",
  "properties": {
    "addr:full":"153 Thornbury Road, Osterley Isleworth Greater London TW7 4QG",
    "addr:housenumber":"153",
    "addr:postcode":"tw7 4qg",
    "addr:street":"Thornbury Road",
    "iso:country":"GB",
    "sg:address":"153 Thornbury Road, Osterley",
    "sg:city":"Isleworth",
    "sg:classifiers":[
        {
            "category":"Health Services",
            "subcategory":"Dentist",
            "type":"Services"
        }
    ],
    "sg:phone":"+44 20 8569 7744",
    "sg:postcode":"TW7 4QG",
    "sg:province":"Greater London",
    "wof:name":"Osterley Dentist Practice",
    "wof:placetype":"venue"
},
  "geometry": {"coordinates":[-0.347574,51.482445],"type":"Point"}
}