{
  "type": "Feature",
  "properties": {
    "addr:full":"43-45 North Parade Whitley Bay Northumberland NE26 1NX",
    "addr:housenumber":"43-45",
    "addr:postcode":"ne26 1nx",
    "addr:street":"North Parade",
    "iso:country":"GB",
    "sg:address":"43-45 North Parade",
    "sg:city":"Whitley Bay",
    "sg:classifiers":[
        {
            "category":"Organizations",
            "subcategory":"Community Association",
            "type":"Services"
        },
        {
            "category":"Organizations",
            "subcategory":"Membership Organization",
            "type":"Services"
        }
    ],
    "sg:phone":"+44 191 251 3779",
    "sg:postcode":"NE26 1NX",
    "sg:province":"Northumberland",
    "sg:tags":[
        "club",
        "social"
    ],
    "wof:name":"Promenade Club Ltd",
    "wof:placetype":"venue"
},
  "geometry": {"coordinates":[-1.4431179762,55.0444946289],"type":"Point"}
}