{
  "type": "Feature",
  "properties": {
    "addr:full":"Studio 13 Brockley Cross Business Centre, Endwell Rd Brockley Greater London SE4 2PD",
    "addr:housenumber":"13",
    "addr:postcode":"se4 2pd",
    "addr:street":"Brockley Cross Business Centre Endwell Rd",
    "iso:country":"GB",
    "sg:address":"Studio 13 Brockley Cross Business Centre, Endwell Rd",
    "sg:city":"Brockley",
    "sg:classifiers":[
        {
            "category":"Shopping",
            "subcategory":"Pharmacy",
            "type":"Retail Goods"
        }
    ],
    "sg:phone":"+44 20 7277 6630",
    "sg:postcode":"SE4 2PD",
    "sg:province":"Greater London",
    "sg:tags":[
        "pharmaceutical"
    ],
    "wof:name":"Condomi Ltd",
    "wof:placetype":"venue"
},
  "geometry": {"coordinates":[-0.035469,51.462051],"type":"Point"}
}