{
  "type": "Feature",
  "properties": {
    "addr:full":"The Round House, Sennen Cove Penzance Cornwall TR19 7DF",
    "addr:postcode":"tr19 7df",
    "addr:street":"Sennen Cove",
    "iso:country":"GB",
    "sg:address":"The Round House, Sennen Cove",
    "sg:city":"Penzance",
    "sg:classifiers":[
        {
            "category":"Transit Center",
            "subcategory":"Freight",
            "type":"Transportation"
        }
    ],
    "sg:postcode":"TR19 7DF",
    "sg:province":"Cornwall",
    "sg:tags":[
        "shop",
        "craft",
        "centre"
    ],
    "wof:name":"Round House Gallery",
    "wof:placetype":"venue"
},
  "geometry": {"coordinates":[-5.695374,50.07053],"type":"Point"}
}