{
  "type": "Feature",
  "properties": {
    "iso:country":"GB",
    "sg:address":"The Island, Greatbridge",
    "sg:city":"Romsey",
    "sg:classifiers":[
        {
            "category":"Farming",
            "subcategory":"Farm",
            "type":"Manufacturing & Wholesale Goods"
        }
    ],
    "sg:phone":"+44 1794 512453",
    "sg:postcode":"SO51 0HP",
    "sg:province":"Hampshire",
    "sg:tags":[
        "hatchery"
    ],
    "wof:name":"Test Valley Trout Ltd.",
    "wof:placetype":"venue"
},
  "geometry": {"coordinates":[-1.5720829964,51.034072876],"type":"Point"}
}