{
  "type": "Feature",
  "properties": {
    "addr:full":"33 Murton Lane, Newton Swansea Swansea SA3 4TR",
    "addr:housenumber":"33",
    "addr:postcode":"sa3 4tr",
    "addr:street":"Murton Lane",
    "iso:country":"GB",
    "sg:address":"33 Murton Lane, Newton",
    "sg:city":"Swansea",
    "sg:classifiers":[
        {
            "category":"Professional",
            "subcategory":"Management & Consulting",
            "type":"Services"
        }
    ],
    "sg:phone":"+44 1792 410962",
    "sg:postcode":"SA3 4TR",
    "sg:province":"Swansea",
    "sg:tags":[
        "consultant",
        "business"
    ],
    "wof:name":"Business Advice Ltd.",
    "wof:placetype":"venue"
},
  "geometry": {"coordinates":[-4.0216479301,51.5763282776],"type":"Point"}
}