{
  "type": "Feature",
  "properties": {
    "addr:full":"Potternewton View Leeds West Yorkshire LS7 2DW",
    "addr:postcode":"ls7 2dw",
    "addr:street":"Potternewton View",
    "iso:country":"GB",
    "sg:address":"Potternewton View",
    "sg:city":"Leeds",
    "sg:classifiers":[
        {
            "category":"Education",
            "subcategory":"Special Training",
            "type":"Public Place"
        }
    ],
    "sg:phone":"+44 113 262 6549",
    "sg:postcode":"LS7 2DW",
    "sg:province":"West Yorkshire",
    "sg:tags":[
        "product",
        "centre"
    ],
    "wof:name":"Potternewton Centre",
    "wof:placetype":"venue"
},
  "geometry": {"coordinates":[-1.5474239588,53.8246307373],"type":"Point"}
}