{
  "type": "Feature",
  "properties": {
    "iso:country":"GB",
    "sg:address":"Po Box 151",
    "sg:city":"Wantage",
    "sg:classifiers":[
        {
            "category":"Professional",
            "subcategory":"Accounting & Tax Preparation",
            "type":"Services"
        }
    ],
    "sg:phone":"+44 1235 762449",
    "sg:postcode":"OX12 9ZN",
    "sg:province":"Berkshire",
    "sg:tags":[
        "accountant"
    ],
    "wof:name":"Gould & Mansford",
    "wof:placetype":"venue"
},
  "geometry": {"coordinates":[-1.453465,51.585079],"type":"Point"}
}