{
  "type": "Feature",
  "properties": {
    "iso:country":"GB",
    "sg:address":"16 Belair Road",
    "sg:city":"Plymouth",
    "sg:classifiers":[
        {
            "category":"Building & Trades",
            "subcategory":"Plumbing",
            "type":"Services"
        },
        {
            "category":"Education",
            "subcategory":"School",
            "type":"Public Place"
        }
    ],
    "sg:phone":"+44 1752 777027",
    "sg:postcode":"PL2 3QH",
    "sg:province":"Devon",
    "sg:tags":[
        "heating",
        "private",
        "tuition"
    ],
    "wof:name":"P S B Plumbing",
    "wof:placetype":"venue"
},
  "geometry": {"coordinates":[-4.149891,50.393478],"type":"Point"}
}