{
  "type": "Feature",
  "properties": {
    "addr:full":"2 Cockcrowing Corner, Higher Eype Bridport Dorset DT6 6AS",
    "addr:housenumber":"2;eype",
    "addr:postcode":"dt6 6as",
    "addr:street":"Cockcrowing Corner Higher",
    "iso:country":"GB",
    "sg:address":"2 Cockcrowing Corner, Higher Eype",
    "sg:city":"Bridport",
    "sg:classifiers":[
        {
            "category":"Professional",
            "subcategory":"Art Services",
            "type":"Services"
        }
    ],
    "sg:postcode":"DT6 6AS",
    "sg:province":"Dorset",
    "sg:tags":[
        "graphic",
        "designer"
    ],
    "wof:name":"Modus Operandi",
    "wof:placetype":"venue"
},
  "geometry": {"coordinates":[-2.782238,50.720287],"type":"Point"}
}