{
  "type": "Feature",
  "properties": {
    "addr:full":"62a Bell Street Henley-on-thames Berkshire RG9 2BN",
    "addr:housenumber":"62a",
    "addr:postcode":"rg9 2bn",
    "addr:street":"Bell Street",
    "iso:country":"GB",
    "sg:address":"62a Bell Street",
    "sg:city":"Henley-on-thames",
    "sg:classifiers":[
        {
            "category":"Shopping",
            "subcategory":"Comic Books",
            "type":"Retail Goods"
        }
    ],
    "sg:phone":"+44 1491 577166",
    "sg:postcode":"RG9 2BN",
    "sg:province":"Berkshire",
    "sg:tags":[
        "jeweller"
    ],
    "wof:name":"D A Lendon & J G Cook",
    "wof:placetype":"venue"
},
  "geometry": {"coordinates":[-0.904245019,51.5395240784],"type":"Point"}
}