{
  "type": "Feature",
  "properties": {
    "addr:full":"43 Dunkeld Rd Dagenham Essex RM8 2PS",
    "addr:housenumber":"43",
    "addr:postcode":"rm8 2ps",
    "addr:street":"Dunkeld Rd",
    "iso:country":"GB",
    "sg:address":"43 Dunkeld Rd",
    "sg:city":"Dagenham",
    "sg:classifiers":[
        {
            "category":"Professional",
            "subcategory":"Computer Services",
            "type":"Services"
        }
    ],
    "sg:phone":"+44 20 8270 0281",
    "sg:postcode":"RM8 2PS",
    "sg:province":"Essex",
    "sg:tags":[
        "system",
        "software"
    ],
    "wof:name":"Hakkai",
    "wof:placetype":"venue"
},
  "geometry": {"coordinates":[0.1198270023,51.5612411499],"type":"Point"}
}