{
  "type": "Feature",
  "properties": {
    "iso:country":"GB",
    "sg:address":"Unit 53 Hobbs Indust Est, Eastbourne Rd",
    "sg:city":"Lingfield",
    "sg:classifiers":[
        {
            "category":"Retail",
            "subcategory":"Auto Repair",
            "type":"Services"
        }
    ],
    "sg:phone":"+44 1342 833939",
    "sg:postcode":"RH7 6HL",
    "sg:province":"Surrey",
    "sg:tags":[
        "modification",
        "garage"
    ],
    "wof:name":"Axis",
    "wof:placetype":"venue"
},
  "geometry": {"coordinates":[-0.051229,51.15514],"type":"Point"}
}