{
  "type": "Feature",
  "properties": {
    "addr:full":"Unit 53 Hobbs Indust Est, Eastbourne Rd Lingfield Surrey RH7 6HL",
    "addr:housenumber":"unit 53",
    "addr:postcode":"rh7 6hl",
    "addr:street":"Indust;Eastbourne Rd",
    "iso:country":"GB",
    "sg:address":"Unit 53 Hobbs Indust Est, Eastbourne Rd",
    "sg:city":"Lingfield",
    "sg:classifiers":[
        {
            "category":"Retail",
            "subcategory":"Auto Repair",
            "type":"Services"
        }
    ],
    "sg:phone":"+44 1342 833939",
    "sg:postcode":"RH7 6HL",
    "sg:province":"Surrey",
    "sg:tags":[
        "modification",
        "garage"
    ],
    "wof:name":"Axis",
    "wof:placetype":"venue"
},
  "geometry": {"coordinates":[-0.051229,51.15514],"type":"Point"}
}