{
  "type": "Feature",
  "properties": {
    "addr:full":"5 Grattan Street, Kimberworth Rotherham South Yorkshire S61 2JP",
    "addr:housenumber":"5",
    "addr:postcode":"s61 2jp",
    "addr:street":"Grattan Street",
    "iso:country":"GB",
    "sg:address":"5 Grattan Street, Kimberworth",
    "sg:city":"Rotherham",
    "sg:classifiers":[
        {
            "category":"Building & Trades",
            "subcategory":"Construction",
            "type":"Services"
        }
    ],
    "sg:postcode":"S61 2JP",
    "sg:province":"South Yorkshire",
    "sg:tags":[
        "roofing"
    ],
    "wof:name":"New Roof Services",
    "wof:placetype":"venue"
},
  "geometry": {"coordinates":[-1.396334,53.430622],"type":"Point"}
}