{
  "type": "Feature",
  "properties": {
    "addr:full":"Tradeforce Building, Cornwall Pl Bradford West Yorkshire BD8 7JT",
    "addr:postcode":"bd8 7jt",
    "addr:street":"Cornwall Pl",
    "iso:country":"GB",
    "sg:address":"Tradeforce Building, Cornwall Pl",
    "sg:city":"Bradford",
    "sg:classifiers":[
        {
            "category":"Organizations",
            "subcategory":"Non-profit Organization",
            "type":"Services"
        }
    ],
    "sg:phone":"+44 1274 770159",
    "sg:postcode":"BD8 7JT",
    "sg:province":"West Yorkshire",
    "sg:tags":[
        "organisation",
        "voluntary",
        "charity"
    ],
    "wof:name":"MIND Information Services",
    "wof:placetype":"venue"
},
  "geometry": {"coordinates":[-1.7600799799,53.8024291992],"type":"Point"}
}