{
  "type": "Feature",
  "properties": {
    "iso:country":"GB",
    "sg:address":"6 Prideaux Road",
    "sg:city":"Eastbourne",
    "sg:classifiers":[
        {
            "category":"Real Estate",
            "subcategory":"Architect",
            "type":"Services"
        }
    ],
    "sg:phone":"+44 7976 385814",
    "sg:postcode":"BN21 2ND",
    "sg:province":"East Sussex",
    "wof:name":"Charles E Gallagher & Ian S Gallagher",
    "wof:placetype":"venue"
},
  "geometry": {"coordinates":[0.276820004,50.7791366577],"type":"Point"}
}