{
  "type": "Feature",
  "properties": {
    "addr:full":"18 Compton Crescent, West Moors Ferndown Dorset BH22 0BZ",
    "addr:housenumber":"18",
    "addr:postcode":"bh22 0bz",
    "addr:street":"Compton Crescent West",
    "iso:country":"GB",
    "sg:address":"18 Compton Crescent, West Moors",
    "sg:city":"Ferndown",
    "sg:classifiers":[
        {
            "category":"Professional",
            "subcategory":"Engineering",
            "type":"Services"
        },
        {
            "category":"Professional",
            "subcategory":"Detective & Security Services",
            "type":"Services"
        }
    ],
    "sg:postcode":"BH22 0BZ",
    "sg:province":"Dorset",
    "sg:tags":[
        "burglar",
        "alarm",
        "system",
        "contractor",
        "electrical",
        "engineer"
    ],
    "wof:name":"Household Electrics",
    "wof:placetype":"venue"
},
  "geometry": {"coordinates":[-1.866047,50.819378],"type":"Point"}
}