{
  "type": "Feature",
  "properties": {
    "iso:country":"GB",
    "sg:address":"Unit 5, Featherstall Road South",
    "sg:city":"Oldham",
    "sg:classifiers":[
        {
            "category":"Retail",
            "subcategory":"Event Space",
            "type":"Services"
        }
    ],
    "sg:phone":"+44 161 626 1844",
    "sg:postcode":"OL9 6HS",
    "sg:province":"Lancashire",
    "sg:tags":[
        "product",
        "disposable",
        "dom"
    ],
    "wof:name":"Industrial & Professional Supplies Ltd.",
    "wof:placetype":"venue"
},
  "geometry": {"coordinates":[-2.127094,53.547417],"type":"Point"}
}