{
  "type": "Feature",
  "properties": {
    "addr:full":"33 Westcott Street Hull East Riding of Yorkshire HU8 8LR",
    "addr:housenumber":"33",
    "addr:postcode":"hu8 8lr",
    "addr:street":"Westcott Street",
    "iso:country":"GB",
    "sg:address":"33 Westcott Street",
    "sg:city":"Hull",
    "sg:classifiers":[
        {
            "category":"Building & Trades",
            "subcategory":"Plumbing",
            "type":"Services"
        }
    ],
    "sg:phone":"+44 1482 375076",
    "sg:postcode":"HU8 8LR",
    "sg:province":"East Riding of Yorkshire",
    "sg:tags":[
        "heating"
    ],
    "wof:name":"Mark Paddison Plumbing & Heating",
    "wof:placetype":"venue"
},
  "geometry": {"coordinates":[-0.3072710037,53.7607040405],"type":"Point"}
}