{
  "type": "Feature",
  "properties": {
    "addr:full":"30 Stronend Street Glasgow Glasgow City G22 6AR",
    "addr:housenumber":"30",
    "addr:postcode":"g22 6ar",
    "addr:street":"Stronend Street",
    "iso:country":"GB",
    "sg:address":"30 Stronend Street",
    "sg:city":"Glasgow",
    "sg:classifiers":[
        {
            "category":"Wholesale",
            "subcategory":"Scrap",
            "type":"Manufacturing & Wholesale Goods"
        }
    ],
    "sg:phone":"+44 141 336 3001",
    "sg:postcode":"G22 6AR",
    "sg:province":"Glasgow City",
    "sg:tags":[
        "breaker",
        "dismantlers"
    ],
    "wof:name":"Arcadia Car Breakers",
    "wof:placetype":"venue"
},
  "geometry": {"coordinates":[-4.261957,55.885052],"type":"Point"}
}