{
  "type": "Feature",
  "properties": {
    "addr:full":"356 Pinner Road, North Harrow Harrow Greater London HA2 6DZ",
    "addr:housenumber":"356",
    "addr:postcode":"ha2 6dz",
    "addr:street":"Pinner Road North",
    "iso:country":"GB",
    "sg:address":"356 Pinner Road, North Harrow",
    "sg:city":"Harrow",
    "sg:classifiers":[
        {
            "category":"Food & Beverages",
            "subcategory":"Supermarket",
            "type":"Retail Goods"
        }
    ],
    "sg:phone":"+44 20 8427 5812",
    "sg:postcode":"HA2 6DZ",
    "sg:province":"Greater London",
    "wof:name":"Safeway Stores Ltd.",
    "wof:placetype":"venue"
},
  "geometry": {"coordinates":[-0.3610889912,51.5862045288],"type":"Point"}
}