{
  "type": "Feature",
  "properties": {
    "iso:country":"GB",
    "sg:address":"Summertown Pavilion, Middle Way",
    "sg:city":"Oxford",
    "sg:classifiers":[
        {
            "category":"Organizations",
            "subcategory":"Non-profit Organization",
            "type":"Services"
        }
    ],
    "sg:phone":"+44 1865 311211",
    "sg:postcode":"OX2 7LG",
    "sg:province":"Oxfordshire",
    "sg:tags":[
        "organisation",
        "voluntary",
        "charity"
    ],
    "wof:name":"Summer Town Pavilion Middle Way",
    "wof:placetype":"venue"
},
  "geometry": {"coordinates":[-1.26829,51.77924],"type":"Point"}
}