{
  "type": "Feature",
  "properties": {
    "addr:full":"Unit 10 Leanne Business Centre, Sandford Lane Wareham Dorset BH20 4DY",
    "addr:housenumber":"unit 10",
    "addr:postcode":"bh20 4dy",
    "addr:street":"Leanne Business Centre Sandford Lane",
    "iso:country":"GB",
    "sg:address":"Unit 10 Leanne Business Centre, Sandford Lane",
    "sg:city":"Wareham",
    "sg:classifiers":[
        {
            "category":"Professional",
            "type":"Services"
        }
    ],
    "sg:postcode":"BH20 4DY",
    "sg:province":"Dorset",
    "sg:tags":[
        "control",
        "system"
    ],
    "wof:name":"Charter Tech Ltd.",
    "wof:placetype":"venue"
},
  "geometry": {"coordinates":[-2.1081590652,50.6942367554],"type":"Point"}
}