{
  "type": "Feature",
  "properties": {
    "addr:full":"3 New Inn Road, Hinxworth Baldock Bedfordshire SG7 5HE",
    "addr:housenumber":"3",
    "addr:postcode":"sg7 5he",
    "addr:street":"New Inn Road",
    "iso:country":"GB",
    "sg:address":"3 New Inn Road, Hinxworth",
    "sg:city":"Baldock",
    "sg:classifiers":[
        {
            "category":"Sports & Exercise",
            "subcategory":"Stables",
            "type":"Entertainment"
        }
    ],
    "sg:postcode":"SG7 5HE",
    "sg:province":"Bedfordshire",
    "sg:tags":[
        "education",
        "equestrian"
    ],
    "wof:name":"New Inn Livery",
    "wof:placetype":"venue"
},
  "geometry": {"coordinates":[-0.1998990029,52.0494842529],"type":"Point"}
}