{
  "type": "Feature",
  "properties": {
    "addr:full":"17 Dundee Street Hull East Riding of Yorkshire HU5 3TX",
    "addr:housenumber":"17",
    "addr:postcode":"hu5 3tx",
    "addr:street":"Dundee Street",
    "iso:country":"GB",
    "sg:address":"17 Dundee Street",
    "sg:city":"Hull",
    "sg:classifiers":[
        {
            "category":"Home & Garden",
            "subcategory":"Building Materials",
            "type":"Retail Goods"
        }
    ],
    "sg:postcode":"HU5 3TX",
    "sg:province":"East Riding of Yorkshire",
    "sg:tags":[
        "garage",
        "door"
    ],
    "wof:name":"Swift Fit Garage Door Services",
    "wof:placetype":"venue"
},
  "geometry": {"coordinates":[-0.374224,53.752659],"type":"Point"}
}