{
  "type": "Feature",
  "properties": {
    "addr:full":"1 John Street, Cullercoats North Shields Tyne and Wear NE30 4PL",
    "addr:housenumber":"1",
    "addr:postcode":"ne30 4pl",
    "addr:street":"John Street",
    "iso:country":"GB",
    "sg:address":"1 John Street, Cullercoats",
    "sg:city":"North Shields",
    "sg:classifiers":[
        {
            "category":"Cafe",
            "type":"Food & Drink"
        }
    ],
    "sg:phone":"+44 191 251 3616",
    "sg:postcode":"NE30 4PL",
    "sg:province":"Tyne and Wear",
    "sg:tags":[
        "tea",
        "room"
    ],
    "wof:name":"The Copper Kettle",
    "wof:placetype":"venue"
},
  "geometry": {"coordinates":[-1.4331840277,55.0349121094],"type":"Point"}
}