{
  "type": "Feature",
  "properties": {
    "iso:country":"GB",
    "sg:address":"Unit 2, Greenhill Industrial Estate, Mytholmroyd",
    "sg:city":"Hebden Bridge",
    "sg:classifiers":[
        {
            "category":"Shopping",
            "subcategory":"Clothing, Apparel, & Fashions",
            "type":"Retail Goods"
        }
    ],
    "sg:phone":"+44 1422 882300",
    "sg:postcode":"HX7 5QF",
    "sg:province":"West Yorkshire",
    "sg:tags":[
        "clothing",
        "fabric"
    ],
    "wof:name":"Thos Sutcliffe & Son Ltd.",
    "wof:placetype":"venue"
},
  "geometry": {"coordinates":[-1.9753880501,53.7291526794],"type":"Point"}
}