{
  "type": "Feature",
  "properties": {
    "addr:full":"156 Prescot Road Liverpool Merseyside L7 0JB",
    "addr:housenumber":"156",
    "addr:postcode":"l7 0jb",
    "addr:street":"Prescot Road",
    "iso:country":"GB",
    "sg:address":"156 Prescot Road",
    "sg:city":"Liverpool",
    "sg:classifiers":[
        {
            "category":"Retail",
            "subcategory":"Auto Repair",
            "type":"Services"
        }
    ],
    "sg:phone":"+44 151 228 8988",
    "sg:postcode":"L7 0JB",
    "sg:province":"Merseyside",
    "sg:tags":[
        "modification",
        "garage"
    ],
    "wof:name":"Newsham Auto Centre",
    "wof:placetype":"venue"
},
  "geometry": {"coordinates":[-2.9359440804,53.4137382507],"type":"Point"}
}