{
  "type": "Feature",
  "properties": {
    "addr:full":"Appletree House, Northwick Close Worcester Worcestershire WR3 7EF",
    "addr:postcode":"wr3 7ef",
    "addr:street":"Northwick Close",
    "iso:country":"GB",
    "sg:address":"Appletree House, Northwick Close",
    "sg:city":"Worcester",
    "sg:classifiers":[
        {
            "category":"Professional",
            "subcategory":"Computer Services",
            "type":"Services"
        }
    ],
    "sg:phone":"+44 1905 613447",
    "sg:postcode":"WR3 7EF",
    "sg:province":"Worcestershire",
    "sg:tags":[
        "system",
        "software"
    ],
    "wof:name":"Saxon Computers Ltd.",
    "wof:placetype":"venue"
},
  "geometry": {"coordinates":[-2.2336258888,52.2152023315],"type":"Point"}
}