{
  "type": "Feature",
  "properties": {
    "addr:full":"3 Middle Gate Newark Nottinghamshire NG24 1AQ",
    "addr:housenumber":"3",
    "addr:postcode":"ng24 1aq",
    "addr:street":"Middle Gate",
    "iso:country":"GB",
    "sg:address":"3 Middle Gate",
    "sg:city":"Newark",
    "sg:classifiers":[
        {
            "category":"Banks & Credit Unions",
            "subcategory":"Financial Services",
            "type":"Services"
        }
    ],
    "sg:postcode":"NG24 1AQ",
    "sg:province":"Nottinghamshire",
    "sg:tags":[
        "adviser"
    ],
    "wof:name":"Middlegate Financial Management Ltd.",
    "wof:placetype":"venue"
},
  "geometry": {"coordinates":[-0.809657,53.077415],"type":"Point"}
}