{
  "type": "Feature",
  "properties": {
    "addr:full":"Scarcliffe Grange, Scarcliffe Chesterfield Derbyshire S44 6TJ",
    "addr:postcode":"s44 6tj",
    "iso:country":"GB",
    "sg:address":"Scarcliffe Grange, Scarcliffe",
    "sg:city":"Chesterfield",
    "sg:classifiers":[
        {
            "category":"Farming",
            "subcategory":"Farm",
            "type":"Manufacturing & Wholesale Goods"
        }
    ],
    "sg:phone":"+44 1246 828286",
    "sg:postcode":"S44 6TJ",
    "sg:province":"Derbyshire",
    "sg:tags":[
        "mixed",
        "crop"
    ],
    "wof:name":"Turstee's of J Warrender",
    "wof:placetype":"venue"
},
  "geometry": {"coordinates":[-1.2666679621,53.2154350281],"type":"Point"}
}