{
  "type": "Feature",
  "properties": {
    "iso:country":"GB",
    "sg:address":"Warren Hill, Oakley",
    "sg:city":"Diss",
    "sg:classifiers":[
        {
            "category":"Farming",
            "subcategory":"Farm",
            "type":"Manufacturing & Wholesale Goods"
        }
    ],
    "sg:phone":"+44 1379 740324",
    "sg:postcode":"IP21 4AN",
    "sg:province":"Norfolk",
    "sg:tags":[
        "mixed",
        "crop"
    ],
    "wof:name":"C A West & Son",
    "wof:placetype":"venue"
},
  "geometry": {"coordinates":[1.178695,52.35693],"type":"Point"}
}