{
  "type": "Feature",
  "properties": {
    "iso:country":"GB",
    "sg:address":"2 Walnut Cottage, Alveston",
    "sg:city":"Stratford-upon-avon",
    "sg:classifiers":[
        {
            "category":"Building & Trades",
            "subcategory":"Construction",
            "type":"Services"
        }
    ],
    "sg:postcode":"CV37 7RA",
    "sg:province":"Warwickshire",
    "sg:tags":[
        "builder"
    ],
    "wof:name":"A Barker",
    "wof:placetype":"venue"
},
  "geometry": {"coordinates":[-1.6583759785,52.2028007507],"type":"Point"}
}