{
  "type": "Feature",
  "properties": {
    "addr:full":"76 South Marine Drive Bridlington East Riding of Yorkshire YO15 3NS",
    "addr:housenumber":"76",
    "addr:postcode":"yo15 3ns",
    "addr:street":"South Marine Drive",
    "iso:country":"GB",
    "sg:address":"76 South Marine Drive",
    "sg:city":"Bridlington",
    "sg:classifiers":[
        {
            "category":"Travel",
            "subcategory":"Hotels & Motels",
            "type":"Entertainment"
        }
    ],
    "sg:phone":"+44 1262 400872",
    "sg:postcode":"YO15 3NS",
    "sg:province":"East Riding of Yorkshire",
    "wof:name":"SEA COURT HOTEL",
    "wof:placetype":"venue"
},
  "geometry": {"coordinates":[-0.2013230026,54.0752449036],"type":"Point"}
}