{
  "type": "Feature",
  "properties": {
    "addr:full":"671 Seven Sisters Road London Greater London N15 5LA",
    "addr:housenumber":"671",
    "addr:postcode":"n15 5la",
    "addr:street":"Seven Sisters Road",
    "iso:country":"GB",
    "sg:address":"671 Seven Sisters Road",
    "sg:city":"London",
    "sg:classifiers":[
        {
            "category":"Taxi",
            "type":"Transportation"
        }
    ],
    "sg:phone":"+44 20 8800 8734",
    "sg:postcode":"N15 5LA",
    "sg:province":"Greater London",
    "sg:tags":[
        "mini",
        "cab"
    ],
    "wof:name":"Alans Cars",
    "wof:placetype":"venue"
},
  "geometry": {"coordinates":[-0.0748559982,51.5821075439],"type":"Point"}
}