{
  "type": "Feature",
  "properties": {
    "addr:full":"14 Prescot Road, Fairfield Liverpool Merseyside L7 0LQ",
    "addr:housenumber":"14",
    "addr:postcode":"l7 0lq",
    "addr:street":"Prescot Road",
    "iso:country":"GB",
    "sg:address":"14 Prescot Road, Fairfield",
    "sg:city":"Liverpool",
    "sg:classifiers":[
        {
            "category":"Home & Garden",
            "subcategory":"Household Appliances",
            "type":"Retail Goods"
        }
    ],
    "sg:postcode":"L7 0LQ",
    "sg:province":"Merseyside",
    "sg:tags":[
        "domestic",
        "centre"
    ],
    "wof:name":"Discount Domestic Services",
    "wof:placetype":"venue"
},
  "geometry": {"coordinates":[-2.943046093,53.4124298096],"type":"Point"}
}