{
  "type": "Feature",
  "properties": {
    "iso:country":"GB",
    "sg:address":"2 High Road",
    "sg:city":"Stevenston",
    "sg:classifiers":[
        {
            "category":"Building & Trades",
            "subcategory":"Cleaning & Sanitation",
            "type":"Services"
        },
        {
            "category":"Social Services",
            "subcategory":"Adult Care",
            "type":"Services"
        }
    ],
    "sg:postcode":"KA20 3DN",
    "sg:province":"North Ayrshire",
    "sg:tags":[
        "contracting",
        "commercial",
        "domestic"
    ],
    "wof:name":"CARE CREW",
    "wof:placetype":"venue"
},
  "geometry": {"coordinates":[-4.7584447861,55.641658783],"type":"Point"}
}