{
  "type": "Feature",
  "properties": {
    "addr:full":"17 Moredun Park Gardens Edinburgh City of Edinburgh EH17 7JN",
    "addr:housenumber":"17",
    "addr:postcode":"eh17 7jn",
    "addr:street":"Moredun Park Gardens",
    "iso:country":"GB",
    "sg:address":"17 Moredun Park Gardens",
    "sg:city":"Edinburgh",
    "sg:classifiers":[
        {
            "category":"Building & Trades",
            "subcategory":"Construction",
            "type":"Services"
        }
    ],
    "sg:phone":"+44 131 664 9469",
    "sg:postcode":"EH17 7JN",
    "sg:province":"City of Edinburgh",
    "sg:tags":[
        "joiner",
        "carpenter"
    ],
    "wof:name":"D K L Joinery",
    "wof:placetype":"venue"
},
  "geometry": {"coordinates":[-3.145056963,55.9137840271],"type":"Point"}
}