{
  "type": "Feature",
  "properties": {
    "addr:full":"Bower Farm, Madley Hereford Herefordshire HR2 9PA",
    "addr:housenumber":"madley",
    "addr:postcode":"hr2 9pa",
    "iso:country":"GB",
    "sg:address":"Bower Farm, Madley",
    "sg:city":"Hereford",
    "sg:classifiers":[
        {
            "category":"Farming",
            "subcategory":"Livestock Farm",
            "type":"Manufacturing & Wholesale Goods"
        }
    ],
    "sg:phone":"+44 1981 250208",
    "sg:postcode":"HR2 9PA",
    "sg:province":"Herefordshire",
    "sg:tags":[
        "others"
    ],
    "wof:name":"T E Hobby & Son",
    "wof:placetype":"venue"
},
  "geometry": {"coordinates":[-2.848336935,52.0450782776],"type":"Point"}
}