{
  "type": "Feature",
  "properties": {
    "addr:full":"2 Bedwell Close, Rownhams Southampton Hampshire SO16 8FT",
    "addr:housenumber":"2",
    "addr:postcode":"so16 8ft",
    "addr:street":"Bedwell Close",
    "iso:country":"GB",
    "sg:address":"2 Bedwell Close, Rownhams",
    "sg:city":"Southampton",
    "sg:classifiers":[
        {
            "category":"Retail",
            "subcategory":"Driving School",
            "type":"Services"
        }
    ],
    "sg:phone":"+44 23 8073 4247",
    "sg:postcode":"SO16 8FT",
    "sg:province":"Hampshire",
    "wof:name":"Margaret Lake",
    "wof:placetype":"venue"
},
  "geometry": {"coordinates":[-1.451079,50.946705],"type":"Point"}
}