{
  "type": "Feature",
  "properties": {
    "iso:country":"GB",
    "sg:address":"C/o Kpmg Corporate Recovery",
    "sg:city":"Cardiff",
    "sg:classifiers":[
        {
            "category":"Travel",
            "subcategory":"Hotels & Motels",
            "type":"Entertainment"
        }
    ],
    "sg:postcode":"CF24 0TE",
    "sg:province":"Cardiff",
    "wof:name":"Bells Hotel Ltd.",
    "wof:placetype":"venue"
},
  "geometry": {"coordinates":[-3.1685500145,51.483039856],"type":"Point"}
}