{
  "type": "Feature",
  "properties": {
    "addr:full":"Sherriff Street Worcester Worcestershire WR4 9AB",
    "addr:postcode":"wr4 9ab",
    "addr:street":"Sherriff Street",
    "iso:country":"GB",
    "sg:address":"Sherriff Street",
    "sg:city":"Worcester",
    "sg:classifiers":[
        {
            "category":"Insurance",
            "subcategory":"Insurance Agent",
            "type":"Services"
        }
    ],
    "sg:phone":"+44 1905 726367",
    "sg:postcode":"WR4 9AB",
    "sg:province":"Worcestershire",
    "wof:name":"Britannic Assurance Plc",
    "wof:placetype":"venue"
},
  "geometry": {"coordinates":[-2.206969,52.195171],"type":"Point"}
}