{
  "type": "Feature",
  "properties": {
    "addr:full":"4 Westerlea Court, Bridge Of Allan Stirling Clackmannanshire FK9 4DH",
    "addr:housenumber":"4",
    "addr:postcode":"fk9 4dh",
    "addr:street":"Westerlea Court",
    "iso:country":"GB",
    "sg:address":"4 Westerlea Court, Bridge Of Allan",
    "sg:city":"Stirling",
    "sg:classifiers":[
        {
            "category":"Building & Trades",
            "subcategory":"Plumbing",
            "type":"Services"
        }
    ],
    "sg:phone":"+44 1786 833744",
    "sg:postcode":"FK9 4DH",
    "sg:province":"Clackmannanshire",
    "sg:tags":[
        "plumber",
        "heating"
    ],
    "wof:name":"Robert Paterson",
    "wof:placetype":"venue"
},
  "geometry": {"coordinates":[-3.946186,56.144936],"type":"Point"}
}