{
  "type": "Feature",
  "properties": {
    "addr:full":"56 High Road, Gorleston Great Yarmouth Norfolk NR31 0PE",
    "addr:housenumber":"56",
    "addr:postcode":"nr31 0pe",
    "addr:street":"High Road",
    "iso:country":"GB",
    "sg:address":"56 High Road, Gorleston",
    "sg:city":"Great Yarmouth",
    "sg:classifiers":[
        {
            "category":"Building & Trades",
            "subcategory":"Construction",
            "type":"Services"
        }
    ],
    "sg:phone":"+44 1493 665675",
    "sg:postcode":"NR31 0PE",
    "sg:province":"Norfolk",
    "sg:tags":[
        "joinery",
        "joiner",
        "carpenter",
        "carpentry"
    ],
    "wof:name":"John Symonds",
    "wof:placetype":"venue"
},
  "geometry": {"coordinates":[1.727435,52.587109],"type":"Point"}
}