{
  "type": "Feature",
  "properties": {
    "addr:full":"210 Alum Rock Rd Birmingham West Midlands B8 3DH",
    "addr:housenumber":"210",
    "addr:postcode":"b8 3dh",
    "addr:street":"Alum Rock Rd",
    "iso:country":"GB",
    "sg:address":"210 Alum Rock Rd",
    "sg:city":"Birmingham",
    "sg:classifiers":[
        {
            "category":"Home & Garden",
            "subcategory":"Household Appliances",
            "type":"Retail Goods"
        }
    ],
    "sg:phone":"+44 121 326 8700",
    "sg:postcode":"B8 3DH",
    "sg:province":"West Midlands",
    "sg:tags":[
        "domestic",
        "centre"
    ],
    "wof:name":"Euro Appliance Centre",
    "wof:placetype":"venue"
},
  "geometry": {"coordinates":[-1.8499749899,52.4888877869],"type":"Point"}
}