{
  "type": "Feature",
  "properties": {
    "iso:country":"GB",
    "sg:address":"212 Princes Road",
    "sg:city":"Stoke-on-trent",
    "sg:classifiers":[
        {
            "category":"Retail",
            "subcategory":"Driving School",
            "type":"Services"
        }
    ],
    "sg:postcode":"ST4 7JW",
    "sg:province":"Staffordshire",
    "wof:name":"Linda's School of Motoring",
    "wof:placetype":"venue"
},
  "geometry": {"coordinates":[-2.197361,53.00679],"type":"Point"}
}