{
  "type": "Feature",
  "properties": {
    "addr:full":"16 Hall Drive, Finedon Wellingborough Northamptonshire NN9 5NF",
    "addr:housenumber":"16",
    "addr:postcode":"nn9 5nf",
    "addr:street":"Hall Drive",
    "iso:country":"GB",
    "sg:address":"16 Hall Drive, Finedon",
    "sg:city":"Wellingborough",
    "sg:classifiers":[
        {
            "category":"Bus Charters",
            "type":"Transportation"
        }
    ],
    "sg:phone":"+44 1933 681774",
    "sg:postcode":"NN9 5NF",
    "sg:province":"Northamptonshire",
    "sg:tags":[
        "hire",
        "coach"
    ],
    "wof:name":"Roy's Minibuses",
    "wof:placetype":"venue"
},
  "geometry": {"coordinates":[-0.65951401,52.3350372314],"type":"Point"}
}