{
  "type": "Feature",
  "properties": {
    "addr:full":"38 Half Mile Clo Norwich Norfolk NR3 2LW",
    "addr:housenumber":"38",
    "addr:postcode":"nr3 2lw",
    "addr:street":"Half Mile Clo Norwich Norfolk",
    "iso:country":"GB",
    "sg:address":"38 Half Mile Clo",
    "sg:city":"Norwich",
    "sg:classifiers":[
        {
            "category":"Building & Trades",
            "subcategory":"Construction",
            "type":"Services"
        }
    ],
    "sg:phone":"+44 1603 412773",
    "sg:postcode":"NR3 2LW",
    "sg:province":"Norfolk",
    "sg:tags":[
        "decorator",
        "painter"
    ],
    "wof:name":"D M Riches",
    "wof:placetype":"venue"
},
  "geometry": {"coordinates":[1.279146,52.646755],"type":"Point"}
}