{
  "type": "Feature",
  "properties": {
    "addr:full":"7 Sycamore Street Newcastle Emlyn Carmarthenshire SA38 9AU",
    "addr:housenumber":"7",
    "addr:postcode":"sa38 9au",
    "addr:street":"Sycamore Street",
    "iso:country":"GB",
    "sg:address":"7 Sycamore Street",
    "sg:city":"Newcastle Emlyn",
    "sg:classifiers":[
        {
            "category":"Shopping",
            "subcategory":"Clothing, Apparel, & Fashions",
            "type":"Retail Goods"
        }
    ],
    "sg:phone":"+44 1239 711594",
    "sg:postcode":"SA38 9AU",
    "sg:province":"Carmarthenshire",
    "sg:tags":[
        "shop",
        "dress",
        "fancy"
    ],
    "wof:name":"Something Different",
    "wof:placetype":"venue"
},
  "geometry": {"coordinates":[-4.4682421684,52.0383148193],"type":"Point"}
}