{
  "type": "Feature",
  "properties": {
    "addr:full":"1 Welby Street Grantham Lincolnshire NG31 6DY",
    "addr:housenumber":"1",
    "addr:postcode":"ng31 6dy",
    "addr:street":"Welby Street",
    "iso:country":"GB",
    "sg:address":"1 Welby Street",
    "sg:city":"Grantham",
    "sg:classifiers":[
        {
            "category":"Fast Food",
            "type":"Food & Drink"
        }
    ],
    "sg:phone":"+44 1476 564531",
    "sg:postcode":"NG31 6DY",
    "sg:province":"Lincolnshire",
    "sg:tags":[
        "away",
        "take"
    ],
    "wof:name":"Po Sing",
    "wof:placetype":"venue"
},
  "geometry": {"coordinates":[-0.644316,52.910965],"type":"Point"}
}