{
  "type": "Feature",
  "properties": {
    "iso:country":"GB",
    "sg:address":"Unit 3 7 High St",
    "sg:city":"Portsmouth",
    "sg:classifiers":[
        {
            "category":"Shopping",
            "subcategory":"Gifts & Souvenirs",
            "type":"Retail Goods"
        }
    ],
    "sg:phone":"+44 23 9238 1536",
    "sg:postcode":"PO6 3EJ",
    "sg:province":"Hampshire",
    "sg:tags":[
        "shop"
    ],
    "wof:name":"All In One",
    "wof:placetype":"venue"
},
  "geometry": {"coordinates":[-1.067139,50.8451],"type":"Point"}
}