{
  "type": "Feature",
  "properties": {
    "addr:full":"23 Castlefield Place Cardiff Cardiff CF14 3DU",
    "addr:housenumber":"23",
    "addr:postcode":"cf14 3du",
    "addr:street":"Castlefield Place",
    "iso:country":"GB",
    "sg:address":"23 Castlefield Place",
    "sg:city":"Cardiff",
    "sg:classifiers":[
        {
            "category":"Professional",
            "subcategory":"Engineering",
            "type":"Services"
        }
    ],
    "sg:phone":"+44 29 2062 1049",
    "sg:postcode":"CF14 3DU",
    "sg:province":"Cardiff",
    "sg:tags":[
        "contractor",
        "electrical",
        "engineer"
    ],
    "wof:name":"A L Ball Electrical Engineers & Contractors Ltd.",
    "wof:placetype":"venue"
},
  "geometry": {"coordinates":[-3.1974020004,51.5005645752],"type":"Point"}
}