{
  "type": "Feature",
  "properties": {
    "addr:full":"4 Alltan Place, Culloden Inverness Highland IV2 7TB",
    "addr:housenumber":"4",
    "addr:postcode":"iv2 7tb",
    "addr:street":"Alltan Place Culloden",
    "iso:country":"GB",
    "sg:address":"4 Alltan Place, Culloden",
    "sg:city":"Inverness",
    "sg:classifiers":[
        {
            "category":"Personal",
            "subcategory":"Beauty Salon",
            "type":"Services"
        }
    ],
    "sg:phone":"+44 1463 798121",
    "sg:postcode":"IV2 7TB",
    "sg:province":"Highland",
    "sg:tags":[
        "unisex",
        "hairdresser"
    ],
    "wof:name":"Hairstorm",
    "wof:placetype":"venue"
},
  "geometry": {"coordinates":[-4.143159,57.490704],"type":"Point"}
}