{
  "type": "Feature",
  "properties": {
    "addr:full":"Primrose Court, Orchard Way, Guiseley Leeds West Yorkshire LS20 9EP",
    "addr:postcode":"ls20 9ep",
    "addr:street":"Primrose Court Orchard Way",
    "iso:country":"GB",
    "sg:address":"Primrose Court, Orchard Way, Guiseley",
    "sg:city":"Leeds",
    "sg:classifiers":[
        {
            "category":"Health Services",
            "subcategory":"Nursing And Care Facility",
            "type":"Services"
        },
        {
            "category":"Organizations",
            "subcategory":"Community Association",
            "type":"Services"
        }
    ],
    "sg:phone":"+44 1943 875690",
    "sg:postcode":"LS20 9EP",
    "sg:province":"West Yorkshire",
    "sg:tags":[
        "residential",
        "housing",
        "society"
    ],
    "wof:name":"Anchor Trust",
    "wof:placetype":"venue"
},
  "geometry": {"coordinates":[-1.7082769871,53.8762588501],"type":"Point"}
}