{
  "type": "Feature",
  "properties": {
    "addr:full":"Wide Open Dykes, Blackford Carlisle Cumbria CA6 4EP",
    "addr:postcode":"ca6 4ep",
    "iso:country":"GB",
    "sg:address":"Wide Open Dykes, Blackford",
    "sg:city":"Carlisle",
    "sg:classifiers":[
        {
            "category":"Farming",
            "subcategory":"Farm",
            "type":"Manufacturing & Wholesale Goods"
        }
    ],
    "sg:postcode":"CA6 4EP",
    "sg:province":"Cumbria",
    "sg:tags":[
        "mixed",
        "crop"
    ],
    "wof:name":"E & I Davidson",
    "wof:placetype":"venue"
},
  "geometry": {"coordinates":[-2.9434580803,54.9519195557],"type":"Point"}
}