{
  "type": "Feature",
  "properties": {
    "iso:country":"GB",
    "sg:address":"Chantry Farm, Eyke Road",
    "sg:city":"Woodbridge",
    "sg:classifiers":[
        {
            "category":"Building & Trades",
            "subcategory":"Landscaping Services",
            "type":"Services"
        }
    ],
    "sg:phone":"+44 1728 747113",
    "sg:postcode":"IP13 0PZ",
    "sg:province":"Suffolk",
    "sg:tags":[
        "landscape",
        "contractor"
    ],
    "wof:name":"Tennyson Landscapes",
    "wof:placetype":"venue"
},
  "geometry": {"coordinates":[1.4021500349,52.148639679],"type":"Point"}
}