{
  "type": "Feature",
  "properties": {
    "addr:full":"Room B11 College Business Centre, Uttoexter New Rd Derby Derbyshire DE22 3WZ",
    "addr:housenumber":"b11",
    "addr:postcode":"de22 3wz",
    "addr:street":"New Rd",
    "iso:country":"GB",
    "sg:address":"Room B11 College Business Centre, Uttoexter New Rd",
    "sg:city":"Derby",
    "sg:classifiers":[
        {
            "category":"Education",
            "subcategory":"Special Training",
            "type":"Public Place"
        }
    ],
    "sg:phone":"+44 1332 370560",
    "sg:postcode":"DE22 3WZ",
    "sg:province":"Derbyshire",
    "sg:tags":[
        "product",
        "centre"
    ],
    "wof:name":"Invotex",
    "wof:placetype":"venue"
},
  "geometry": {"coordinates":[-1.4932800531,52.919719696],"type":"Point"}
}