{
  "type": "Feature",
  "properties": {
    "iso:country":"GB",
    "sg:address":"Herriot House, 12 Summerhill Terrace",
    "sg:city":"Newcastle-upon-tyne",
    "sg:classifiers":[
        {
            "category":"Real Estate",
            "subcategory":"Architect",
            "type":"Services"
        }
    ],
    "sg:phone":"+44 191 260 2299",
    "sg:postcode":"NE4 6EB",
    "sg:province":"Tyne and Wear",
    "wof:name":"M W E Architects",
    "wof:placetype":"venue"
},
  "geometry": {"coordinates":[-1.625836,54.96986],"type":"Point"}
}