{
  "type": "Feature",
  "properties": {
    "iso:country":"GB",
    "sg:address":"70 Mill Street, Eynsham",
    "sg:city":"Witney",
    "sg:classifiers":[
        {
            "category":"Fast Food",
            "type":"Food & Drink"
        }
    ],
    "sg:phone":"+44 1865 881432",
    "sg:postcode":"OX29 4JU",
    "sg:province":"Oxfordshire",
    "sg:tags":[
        "away",
        "meal",
        "outlet",
        "take"
    ],
    "wof:name":"Rainbow House",
    "wof:placetype":"venue"
},
  "geometry": {"coordinates":[-1.373119,51.784004],"type":"Point"}
}