{
  "type": "Feature",
  "properties": {
    "addr:full":"Walsall Road Wednesbury West Midlands WS10 9JW",
    "addr:postcode":"ws10 9jw",
    "addr:street":"Walsall Road",
    "iso:country":"GB",
    "sg:address":"Walsall Road",
    "sg:city":"Wednesbury",
    "sg:classifiers":[
        {
            "category":"Health Services",
            "subcategory":"Doctor",
            "type":"Services"
        }
    ],
    "sg:phone":"+44 121 526 2466",
    "sg:postcode":"WS10 9JW",
    "sg:province":"West Midlands",
    "sg:tags":[
        "practitioners"
    ],
    "wof:name":"Darlaston Medical Centre",
    "wof:placetype":"venue"
},
  "geometry": {"coordinates":[-2.0205879211,52.5711669922],"type":"Point"}
}