{
  "type": "Feature",
  "properties": {
    "addr:full":"Kinnaird Hall Penzance Cornwall TR18 4AW",
    "addr:postcode":"tr18 4aw",
    "iso:country":"GB",
    "sg:address":"Kinnaird Hall",
    "sg:city":"Penzance",
    "sg:classifiers":[
        {
            "category":"Organizations",
            "subcategory":"Membership Organization",
            "type":"Services"
        },
        {
            "category":"Organizations",
            "subcategory":"Non-profit Organization",
            "type":"Services"
        }
    ],
    "sg:postcode":"TR18 4AW",
    "sg:province":"Cornwall",
    "sg:tags":[
        "club",
        "organisation",
        "voluntary",
        "charity"
    ],
    "wof:name":"The Royal Air Forces Association",
    "wof:placetype":"venue"
},
  "geometry": {"coordinates":[-5.5349187851,50.119808197],"type":"Point"}
}