{
  "type": "Feature",
  "properties": {
    "addr:full":"Main Street, Feppercairn Laurencekirk Aberdeenshire AB30 1XF",
    "addr:postcode":"ab30 1xf",
    "addr:street":"Main Street",
    "iso:country":"GB",
    "sg:address":"Main Street, Feppercairn",
    "sg:city":"Laurencekirk",
    "sg:classifiers":[
        {
            "category":"Fast Food",
            "type":"Food & Drink"
        }
    ],
    "sg:phone":"+44 1561 340271",
    "sg:postcode":"AB30 1XF",
    "sg:province":"Aberdeenshire",
    "sg:tags":[
        "away",
        "take"
    ],
    "wof:name":"J Mackillon",
    "wof:placetype":"venue"
},
  "geometry": {"coordinates":[-2.4693739414,56.8306617737],"type":"Point"}
}