{
  "type": "Feature",
  "properties": {
    "iso:country":"GB",
    "sg:address":"Leatherhead Court, Woodlands Road",
    "sg:city":"Leatherhead",
    "sg:classifiers":[
        {
            "category":"Shopping",
            "subcategory":"Thrift Store",
            "type":"Retail Goods"
        },
        {
            "category":"Organizations",
            "subcategory":"Non-profit Organization",
            "type":"Services"
        }
    ],
    "sg:phone":"+44 1372 841100",
    "sg:postcode":"KT22 0BN",
    "sg:province":"Surrey",
    "sg:tags":[
        "shop",
        "organisation",
        "voluntary",
        "charity"
    ],
    "wof:name":"Queen Elizabeth's Foundation for Disabled People",
    "wof:placetype":"venue"
},
  "geometry": {"coordinates":[-0.355019,51.313156],"type":"Point"}
}