{
  "type": "Feature",
  "properties": {
    "addr:full":"Littleton Manor Farm, Bicester Road, Waddesdon Aylesbury Buckinghamshire HP18 0JR",
    "addr:postcode":"hp18 0jr",
    "addr:street":"Bicester Road",
    "iso:country":"GB",
    "sg:address":"Littleton Manor Farm, Bicester Road, Waddesdon",
    "sg:city":"Aylesbury",
    "sg:classifiers":[
        {
            "category":"Farming",
            "subcategory":"Dairy Farm",
            "type":"Manufacturing & Wholesale Goods"
        }
    ],
    "sg:phone":"+44 1296 651256",
    "sg:postcode":"HP18 0JR",
    "sg:province":"Buckinghamshire",
    "sg:tags":[
        "farmer"
    ],
    "wof:name":"C F B JENKINS & SON",
    "wof:placetype":"venue"
},
  "geometry": {"coordinates":[-0.919449,51.846096],"type":"Point"}
}