{
  "type": "Feature",
  "properties": {
    "addr:full":"3 Golf Road Gourock Inverclyde PA19 1DG",
    "addr:housenumber":"3",
    "addr:postcode":"pa19 1dg",
    "addr:street":"Golf Road",
    "iso:country":"GB",
    "sg:address":"3 Golf Road",
    "sg:city":"Gourock",
    "sg:classifiers":[
        {
            "category":"Sports & Exercise",
            "subcategory":"Sports Center",
            "type":"Entertainment"
        },
        {
            "category":"Recreation",
            "type":"Entertainment"
        }
    ],
    "sg:phone":"+44 1475 630637",
    "sg:postcode":"PA19 1DG",
    "sg:province":"Inverclyde",
    "sg:tags":[
        "shop",
        "good",
        "outdoor",
        "pursuit"
    ],
    "wof:name":"Footloose Adventure (Scotland) Ltd.",
    "wof:placetype":"venue"
},
  "geometry": {"coordinates":[-4.831219,55.953621],"type":"Point"}
}