{
  "type": "Feature",
  "properties": {
    "iso:country":"GB",
    "sg:address":"134a Kingston Road",
    "sg:city":"Leatherhead",
    "sg:classifiers":[
        {
            "category":"Retail",
            "subcategory":"Auto Repair",
            "type":"Services"
        }
    ],
    "sg:phone":"+44 1372 375908",
    "sg:postcode":"KT22 7PU",
    "sg:province":"Surrey",
    "sg:tags":[
        "body",
        "car",
        "repairer"
    ],
    "wof:name":"Ryebrook Motors Ltd.",
    "wof:placetype":"venue"
},
  "geometry": {"coordinates":[-0.3328279853,51.310218811],"type":"Point"}
}