{
  "type": "Feature",
  "properties": {
    "addr:full":"Unit 2 Lealand Way Boston Lincolnshire PE21 7SW",
    "addr:housenumber":"unit 2",
    "addr:postcode":"pe21 7sw",
    "addr:street":"Lealand Way",
    "iso:country":"GB",
    "sg:address":"Unit 2 Lealand Way",
    "sg:city":"Boston",
    "sg:classifiers":[
        {
            "category":"Shopping",
            "subcategory":"Bicycles & Sporting Goods",
            "type":"Retail Goods"
        }
    ],
    "sg:phone":"+44 1205 359611",
    "sg:postcode":"PE21 7SW",
    "sg:province":"Lincolnshire",
    "sg:tags":[
        "equipment",
        "gym",
        "sport"
    ],
    "wof:name":"Sapphire Fitness",
    "wof:placetype":"venue"
},
  "geometry": {"coordinates":[-0.011703,52.965557],"type":"Point"}
}