{
  "type": "Feature",
  "properties": {
    "iso:country":"GB",
    "sg:address":"Acorn Cotts Bigmore Lane, Cadmore End",
    "sg:city":"High Wycombe",
    "sg:classifiers":[
        {
            "category":"Health Services",
            "subcategory":"Health Practitioner",
            "type":"Services"
        }
    ],
    "sg:postcode":"HP14 3UR",
    "sg:province":"Buckinghamshire",
    "sg:tags":[
        "psychotherapist"
    ],
    "wof:name":"J J Counselling Services",
    "wof:placetype":"venue"
},
  "geometry": {"coordinates":[-0.8631190062,51.6260185242],"type":"Point"}
}