{
  "type": "Feature",
  "properties": {
    "iso:country":"GB",
    "sg:address":"Yeancott Farm, Bathealton",
    "sg:city":"Taunton",
    "sg:classifiers":[
        {
            "category":"Farming",
            "subcategory":"Livestock Farm",
            "type":"Manufacturing & Wholesale Goods"
        }
    ],
    "sg:postcode":"TA4 2AW",
    "sg:province":"Devon",
    "sg:tags":[
        "others"
    ],
    "wof:name":"F J & P M Cottrell & Sons",
    "wof:placetype":"venue"
},
  "geometry": {"coordinates":[-3.314404,51.008938],"type":"Point"}
}