{
  "type": "Feature",
  "properties": {
    "iso:country":"GB",
    "sg:address":"Little Malgraves Hall, Indust Est, Lower Dunton Rd, Bulphan",
    "sg:city":"Upminster",
    "sg:classifiers":[
        {
            "category":"Building & Trades",
            "subcategory":"Construction",
            "type":"Services"
        }
    ],
    "sg:phone":"+44 1268 419234",
    "sg:postcode":"RM14 3XS",
    "sg:province":"Essex",
    "sg:tags":[
        "fork",
        "lift",
        "truck"
    ],
    "wof:name":"Mechanical Handling Hire & Sales Fork Lift Trucks",
    "wof:placetype":"venue"
},
  "geometry": {"coordinates":[0.362449,51.548279],"type":"Point"}
}