{
  "type": "Feature",
  "properties": {
    "iso:country":"GB",
    "sg:address":"11 Wantsume Lees",
    "sg:city":"Sandwich",
    "sg:classifiers":[
        {
            "category":"Taxi",
            "type":"Transportation"
        },
        {
            "category":"Military Area",
            "subcategory":"Air Force Base",
            "type":"Public Place"
        }
    ],
    "sg:phone":"+44 1304 614209",
    "sg:postcode":"CT13 9JF",
    "sg:province":"Kent",
    "sg:tags":[
        "hire",
        "private",
        "vehicle"
    ],
    "wof:name":"A M Cars",
    "wof:placetype":"venue"
},
  "geometry": {"coordinates":[1.331542,51.280273],"type":"Point"}
}