{
  "type": "Feature",
  "properties": {
    "iso:country":"GB",
    "sg:address":"152 Birkrig",
    "sg:city":"Skelmersdale",
    "sg:classifiers":[
        {
            "category":"Professional",
            "subcategory":"Lawyer & Legal Services",
            "type":"Services"
        }
    ],
    "sg:phone":"+44 1695 723601",
    "sg:postcode":"WN8 9HP",
    "sg:province":"Lancashire",
    "sg:tags":[
        "solicitor"
    ],
    "wof:name":"Brighouse Jones & Co.",
    "wof:placetype":"venue"
},
  "geometry": {"coordinates":[-2.758618,53.537132],"type":"Point"}
}