{
  "type": "Feature",
  "properties": {
    "addr:full":"259 Shirland Road London Greater London W9 3JW",
    "addr:housenumber":"259",
    "addr:postcode":"w9 3jw",
    "addr:street":"Shirland Road",
    "iso:country":"GB",
    "sg:address":"259 Shirland Road",
    "sg:city":"London",
    "sg:classifiers":[
        {
            "category":"Communications",
            "type":"Services"
        }
    ],
    "sg:phone":"+44 20 8960 3561",
    "sg:postcode":"W9 3JW",
    "sg:province":"Greater London",
    "sg:tags":[
        "data",
        "network"
    ],
    "wof:name":"Data Strategy Ltd.",
    "wof:placetype":"venue"
},
  "geometry": {"coordinates":[-0.199933,51.528416],"type":"Point"}
}