{
  "type": "Feature",
  "properties": {
    "iso:country":"GB",
    "sg:address":"47 Princess Street, Magnetic Works",
    "sg:city":"Rochdale",
    "sg:classifiers":[
        {
            "category":"Manufacturing",
            "subcategory":"Metals",
            "type":"Manufacturing & Wholesale Goods"
        }
    ],
    "sg:phone":"+44 161 628 2222",
    "sg:postcode":"OL12 0HN",
    "sg:province":"Lancashire",
    "sg:tags":[
        "product",
        "fabricated"
    ],
    "wof:name":"H S Greenwood & Sons Ltd.",
    "wof:placetype":"venue"
},
  "geometry": {"coordinates":[-2.1546230316,53.6228256226],"type":"Point"}
}