{
  "type": "Feature",
  "properties": {
    "iso:country":"GB",
    "sg:address":"10 Meeting House La",
    "sg:city":"Brighton",
    "sg:classifiers":[
        {
            "category":"Health Services",
            "subcategory":"Clinic",
            "type":"Services"
        }
    ],
    "sg:postcode":"BN1 1HB",
    "sg:province":"East Sussex",
    "sg:tags":[
        "aromatherapy"
    ],
    "wof:name":"Creativity Interiors Ltd",
    "wof:placetype":"venue"
},
  "geometry": {"coordinates":[-0.1405790001,50.8227233887],"type":"Point"}
}