{
  "type": "Feature",
  "properties": {
    "addr:full":"8 Poole Rd, Upton Poole Dorset BH16 5JA",
    "addr:housenumber":"8",
    "addr:postcode":"bh16 5ja",
    "addr:street":"Poole Rd",
    "iso:country":"GB",
    "sg:address":"8 Poole Rd, Upton",
    "sg:city":"Poole",
    "sg:classifiers":[
        {
            "category":"Personal",
            "subcategory":"Beauty Salon",
            "type":"Services"
        }
    ],
    "sg:phone":"+44 1202 632908",
    "sg:postcode":"BH16 5JA",
    "sg:province":"Dorset",
    "sg:tags":[
        "unisex",
        "hairdresser"
    ],
    "wof:name":"Layers",
    "wof:placetype":"venue"
},
  "geometry": {"coordinates":[-2.026725,50.738041],"type":"Point"}
}