{
  "type": "Feature",
  "properties": {
    "addr:full":"Knockterra Farm Cumnock East Ayrshire KA18 2QZ",
    "addr:postcode":"ka18 2qz",
    "addr:street":"East",
    "iso:country":"GB",
    "sg:address":"Knockterra Farm",
    "sg:city":"Cumnock",
    "sg:classifiers":[
        {
            "category":"Farming",
            "subcategory":"Livestock Farm",
            "type":"Manufacturing & Wholesale Goods"
        }
    ],
    "sg:phone":"+44 1290 420901",
    "sg:postcode":"KA18 2QZ",
    "sg:province":"East Ayrshire",
    "sg:tags":[
        "others"
    ],
    "wof:name":"KNOCKTERRA CO",
    "wof:placetype":"venue"
},
  "geometry": {"coordinates":[-4.264099,55.453255],"type":"Point"}
}