{
  "type": "Feature",
  "properties": {
    "iso:country":"GB",
    "sg:address":"71a High St",
    "sg:city":"Polegate",
    "sg:classifiers":[
        {
            "category":"Shopping",
            "subcategory":"Crafts & Fabrics",
            "type":"Retail Goods"
        }
    ],
    "sg:phone":"+44 1323 482847",
    "sg:postcode":"BN26 6AH",
    "sg:province":"East Sussex",
    "sg:tags":[
        "material",
        "art"
    ],
    "wof:name":"Clear Dimension",
    "wof:placetype":"venue"
},
  "geometry": {"coordinates":[0.244096,50.822189],"type":"Point"}
}