{
  "type": "Feature",
  "properties": {
    "addr:full":"22 Charter Place Watford Hertfordshire WD1 2RS",
    "addr:housenumber":"22",
    "addr:postcode":"wd1 2rs",
    "addr:street":"Charter Place",
    "iso:country":"GB",
    "sg:address":"22 Charter Place",
    "sg:city":"Watford",
    "sg:classifiers":[
        {
            "category":"Shopping",
            "subcategory":"Clothing, Apparel, & Fashions",
            "type":"Retail Goods"
        }
    ],
    "sg:phone":"+44 1923 248374",
    "sg:postcode":"WD1 2RS",
    "sg:province":"Hertfordshire",
    "sg:tags":[
        "shop"
    ],
    "wof:name":"Top Shop",
    "wof:placetype":"venue"
},
  "geometry": {"coordinates":[-0.396648,51.657326],"type":"Point"}
}