{
  "type": "Feature",
  "properties": {
    "iso:country":"GB",
    "sg:address":"Heyford Park, Camp Rd",
    "sg:city":"Bicester",
    "sg:classifiers":[
        {
            "category":"Home & Garden",
            "subcategory":"Building Materials",
            "type":"Retail Goods"
        }
    ],
    "sg:phone":"+44 1869 233300",
    "sg:postcode":"OX6 3HA",
    "sg:province":"Oxfordshire",
    "sg:tags":[
        "access",
        "equipment"
    ],
    "wof:name":"Terex Aerials Ltd",
    "wof:placetype":"venue"
},
  "geometry": {"coordinates":[-1.15354,51.898022],"type":"Point"}
}