{
  "type": "Feature",
  "properties": {
    "iso:country":"GB",
    "sg:address":"178 Pall Mall",
    "sg:city":"Leigh-on-sea",
    "sg:classifiers":[
        {
            "category":"Health Services",
            "subcategory":"Doctor",
            "type":"Services"
        }
    ],
    "sg:phone":"+44 1702 78338",
    "sg:postcode":"SS9 1RB",
    "sg:province":"Essex",
    "sg:tags":[
        "practitioners"
    ],
    "wof:name":"A Behn",
    "wof:placetype":"venue"
},
  "geometry": {"coordinates":[0.6610530019,51.5435791016],"type":"Point"}
}