{
  "type": "Feature",
  "properties": {
    "addr:full":"East Prior Rigg Farm, Kirklinton Carlisle Cumbria CA6 6EB",
    "addr:postcode":"ca6 6eb",
    "addr:street":"East Prior Rigg",
    "iso:country":"GB",
    "sg:address":"East Prior Rigg Farm, Kirklinton",
    "sg:city":"Carlisle",
    "sg:classifiers":[
        {
            "category":"Shopping",
            "subcategory":"Discount & Variety Stores",
            "type":"Retail Goods"
        }
    ],
    "sg:postcode":"CA6 6EB",
    "sg:province":"Cumbria",
    "sg:tags":[
        "cleaning",
        "supply"
    ],
    "wof:name":"Paul Barber",
    "wof:placetype":"venue"
},
  "geometry": {"coordinates":[-2.886519,54.99432],"type":"Point"}
}