{
  "type": "Feature",
  "properties": {
    "iso:country":"GB",
    "sg:address":"8a Trafford Rd",
    "sg:city":"Salford",
    "sg:classifiers":[
        {
            "category":"Arts & Performance",
            "subcategory":"Theater",
            "type":"Entertainment"
        }
    ],
    "sg:phone":"+44 161 737 5154",
    "sg:postcode":"M5 2TD",
    "sg:province":"Greater Manchester",
    "sg:tags":[
        "theatrical",
        "agency"
    ],
    "wof:name":"Mark Andrews Productions Costume Hire",
    "wof:placetype":"venue"
},
  "geometry": {"coordinates":[-2.283404,53.476616],"type":"Point"}
}