{
  "type": "Feature",
  "properties": {
    "iso:country":"GB",
    "sg:address":"Church Street",
    "sg:city":"Bridgwater",
    "sg:classifiers":[
        {
            "category":"Autos & Motor Vehicles",
            "subcategory":"Automobile Sales",
            "type":"Retail Goods"
        },
        {
            "category":"Retail",
            "subcategory":"Auto Repair",
            "type":"Services"
        }
    ],
    "sg:phone":"+44 1278 422010",
    "sg:postcode":"TA6 5AS",
    "sg:province":"Somerset",
    "sg:tags":[
        "garage",
        "related",
        "car"
    ],
    "wof:name":"Anderson & Wall",
    "wof:placetype":"venue"
},
  "geometry": {"coordinates":[-2.9979100227,51.1312904358],"type":"Point"}
}