{
  "type": "Feature",
  "properties": {
    "addr:full":"503 Garratt Lane London Greater London SW18 4SW",
    "addr:housenumber":"503",
    "addr:postcode":"sw18 4sw",
    "addr:street":"Garratt Lane",
    "iso:country":"GB",
    "sg:address":"503 Garratt Lane",
    "sg:city":"London",
    "sg:classifiers":[
        {
            "category":"Fast Food",
            "type":"Food & Drink"
        }
    ],
    "sg:phone":"+44 20 8874 9846",
    "sg:postcode":"SW18 4SW",
    "sg:province":"Greater London",
    "sg:tags":[
        "away",
        "take"
    ],
    "wof:name":"Majors Fried Chicken",
    "wof:placetype":"venue"
},
  "geometry": {"coordinates":[-0.188085,51.442387],"type":"Point"}
}