{
  "type": "Feature",
  "properties": {
    "iso:country":"GB",
    "sg:address":"16 Park Parade, Roker",
    "sg:city":"Sunderland",
    "sg:classifiers":[
        {
            "category":"Professional",
            "subcategory":"Management & Consulting",
            "type":"Services"
        }
    ],
    "sg:phone":"+44 191 565 0391",
    "sg:postcode":"SR6 9LU",
    "sg:province":"Tyne and Wear",
    "sg:tags":[
        "consultant",
        "business"
    ],
    "wof:name":"Nigel Smith Associates",
    "wof:placetype":"venue"
},
  "geometry": {"coordinates":[-1.3698990345,54.9292755127],"type":"Point"}
}