{
  "type": "Feature",
  "properties": {
    "addr:full":"18b Penton Rd Staines Berkshire TW18 2JY",
    "addr:housenumber":"18b",
    "addr:postcode":"tw18 2jy",
    "addr:street":"Penton Rd",
    "iso:country":"GB",
    "sg:address":"18b Penton Rd",
    "sg:city":"Staines",
    "sg:classifiers":[
        {
            "category":"Home & Garden",
            "subcategory":"Household Appliances",
            "type":"Retail Goods"
        }
    ],
    "sg:phone":"+44 1784 464723",
    "sg:postcode":"TW18 2JY",
    "sg:province":"Berkshire",
    "sg:tags":[
        "electrical"
    ],
    "wof:name":"Ridley R.J.",
    "wof:placetype":"venue"
},
  "geometry": {"coordinates":[-0.507233,51.424732],"type":"Point"}
}