{
  "type": "Feature",
  "properties": {
    "addr:full":"72 Market Street Ely Cambridgeshire CB7 4LS",
    "addr:housenumber":"72",
    "addr:postcode":"cb7 4ls",
    "addr:street":"Market Street",
    "iso:country":"GB",
    "sg:address":"72 Market Street",
    "sg:city":"Ely",
    "sg:classifiers":[
        {
            "category":"Government",
            "subcategory":"Office",
            "type":"Public Place"
        }
    ],
    "sg:phone":"+44 1353 661016",
    "sg:postcode":"CB7 4LS",
    "sg:province":"Cambridgeshire",
    "sg:tags":[
        "local"
    ],
    "wof:name":"Ely Parish Council",
    "wof:placetype":"venue"
},
  "geometry": {"coordinates":[0.2631410062,52.4004974365],"type":"Point"}
}