{
  "type": "Feature",
  "properties": {
    "addr:full":"62 Bristol Rd Ipswich Suffolk IP4 4LP",
    "addr:housenumber":"62",
    "addr:postcode":"ip4 4lp",
    "addr:street":"Bristol Rd",
    "iso:country":"GB",
    "sg:address":"62 Bristol Rd",
    "sg:city":"Ipswich",
    "sg:classifiers":[
        {
            "category":"Building & Trades",
            "subcategory":"Equipment Rental",
            "type":"Services"
        }
    ],
    "sg:phone":"+44 1473 726333",
    "sg:postcode":"IP4 4LP",
    "sg:province":"Suffolk",
    "sg:tags":[
        "plant",
        "machinery"
    ],
    "wof:name":"Ipswich Plant Services",
    "wof:placetype":"venue"
},
  "geometry": {"coordinates":[1.182394,52.062683],"type":"Point"}
}