{
  "type": "Feature",
  "properties": {
    "iso:country":"GB",
    "sg:address":"115 Newport Road",
    "sg:city":"Stafford",
    "sg:classifiers":[
        {
            "category":"Health Services",
            "subcategory":"Clinic",
            "type":"Services"
        }
    ],
    "sg:postcode":"ST16 1DA",
    "sg:province":"Staffordshire",
    "sg:tags":[
        "private"
    ],
    "wof:name":"The Staffordshire Sports Injuries Clinic",
    "wof:placetype":"venue"
},
  "geometry": {"coordinates":[-2.129998,52.80006],"type":"Point"}
}