{
  "type": "Feature",
  "properties": {
    "iso:country":"GB",
    "sg:address":"23 Coney St",
    "sg:city":"York",
    "sg:classifiers":[
        {
            "category":"Shopping",
            "subcategory":"Clothing, Apparel, & Fashions",
            "type":"Retail Goods"
        }
    ],
    "sg:phone":"+44 1904 651169",
    "sg:postcode":"YO1 9QL",
    "sg:province":"North Yorkshire",
    "sg:tags":[
        "ladieswear"
    ],
    "wof:name":"Miss Selfridge",
    "wof:placetype":"venue"
},
  "geometry": {"coordinates":[-1.083982,53.958923],"type":"Point"}
}