{
  "type": "Feature",
  "properties": {
    "addr:full":"Kilknowe House, Strathmilgo Cupar Fife KY14 7SG",
    "addr:postcode":"ky14 7sg",
    "addr:street":"Strathmilgo",
    "iso:country":"GB",
    "sg:address":"Kilknowe House, Strathmilgo",
    "sg:city":"Cupar",
    "sg:classifiers":[
        {
            "category":"Shopping",
            "type":"Retail Goods"
        }
    ],
    "sg:postcode":"KY14 7SG",
    "sg:province":"Fife",
    "sg:tags":[
        "merchant"
    ],
    "wof:name":"Thomas Ford",
    "wof:placetype":"venue"
},
  "geometry": {"coordinates":[-3.2373189926,56.2897148132],"type":"Point"}
}