{
  "type": "Feature",
  "properties": {
    "addr:full":"18-20 King Street Stranraer Dumfries and Galloway DG9 7JU",
    "addr:housenumber":"18-20",
    "addr:postcode":"dg9 7ju",
    "addr:street":"King Street",
    "iso:country":"GB",
    "sg:address":"18-20 King Street",
    "sg:city":"Stranraer",
    "sg:classifiers":[
        {
            "category":"Shopping",
            "subcategory":"Department Store",
            "type":"Retail Goods"
        }
    ],
    "sg:phone":"+44 1776 810235",
    "sg:postcode":"DG9 7JU",
    "sg:province":"Dumfries and Galloway",
    "wof:name":"John Gillespie & Sons Ltd.",
    "wof:placetype":"venue"
},
  "geometry": {"coordinates":[-5.0305662155,54.9050369263],"type":"Point"}
}