{
  "type": "Feature",
  "properties": {
    "addr:full":"The Old Bakery, Pontesbury Shrewsbury Shropshire SY5 0PY",
    "addr:postcode":"sy5 0py",
    "iso:country":"GB",
    "sg:address":"The Old Bakery, Pontesbury",
    "sg:city":"Shrewsbury",
    "sg:classifiers":[
        {
            "category":"Home & Garden",
            "subcategory":"Hardware",
            "type":"Retail Goods"
        },
        {
            "category":"Professional",
            "subcategory":"Printing & Photocopies",
            "type":"Services"
        }
    ],
    "sg:phone":"+44 1743 790650",
    "sg:postcode":"SY5 0PY",
    "sg:province":"Shropshire",
    "sg:tags":[
        "paint",
        "printer",
        "lithographic",
        "maker",
        "plate"
    ],
    "wof:name":"Rea Valley Printers Ltd.",
    "wof:placetype":"venue"
},
  "geometry": {"coordinates":[-2.892414093,52.6500511169],"type":"Point"}
}