{
  "type": "Feature",
  "properties": {
    "addr:full":"High Farm, Rowden Lane, Hampsthwaite Harrogate North Yorkshire HG3 2HR",
    "addr:postcode":"hg3 2hr",
    "addr:street":"High;Rowden Lane",
    "iso:country":"GB",
    "sg:address":"High Farm, Rowden Lane, Hampsthwaite",
    "sg:city":"Harrogate",
    "sg:classifiers":[
        {
            "category":"Transit Center",
            "subcategory":"Passenger",
            "type":"Transportation"
        }
    ],
    "sg:phone":"+44 7971 497630",
    "sg:postcode":"HG3 2HR",
    "sg:province":"North Yorkshire",
    "sg:tags":[
        "boarding",
        "kennel",
        "catteries"
    ],
    "wof:name":"High Farm Boarding Kennels & Cattery",
    "wof:placetype":"venue"
},
  "geometry": {"coordinates":[-1.6044290066,54.0261764526],"type":"Point"}
}