{
  "type": "Feature",
  "properties": {
    "iso:country":"GB",
    "sg:address":"1 Ashley Road",
    "sg:city":"Bournemouth",
    "sg:classifiers":[
        {
            "category":"Home & Garden",
            "subcategory":"Carpets & Floor Coverings",
            "type":"Retail Goods"
        }
    ],
    "sg:phone":"+44 1202 397853",
    "sg:postcode":"BH1 4LE",
    "sg:province":"Dorset",
    "sg:tags":[
        "cleaner",
        "upholstery"
    ],
    "wof:name":"de Parys",
    "wof:placetype":"venue"
},
  "geometry": {"coordinates":[-1.8371579647,50.727432251],"type":"Point"}
}