{
  "type": "Feature",
  "properties": {
    "addr:full":"Hillside Road Bath Somerset BA2 3NX",
    "addr:postcode":"ba2 3nx",
    "addr:street":"Hillside Road",
    "iso:country":"GB",
    "sg:address":"Hillside Road",
    "sg:city":"Bath",
    "sg:classifiers":[
        {
            "category":"Government",
            "subcategory":"City Hall",
            "type":"Public Place"
        }
    ],
    "sg:phone":"+44 1225 482156",
    "sg:postcode":"BA2 3NX",
    "sg:province":"Somerset",
    "wof:name":"Hillside Hall",
    "wof:placetype":"venue"
},
  "geometry": {"coordinates":[-2.3767590523,51.3722038269],"type":"Point"}
}