{
  "type": "Feature",
  "properties": {
    "addr:full":"35 London Road, Kirton Boston Lincolnshire PE20 1JE",
    "addr:housenumber":"35",
    "addr:postcode":"pe20 1je",
    "addr:street":"London Road",
    "iso:country":"GB",
    "sg:address":"35 London Road, Kirton",
    "sg:city":"Boston",
    "sg:classifiers":[
        {
            "category":"Professional",
            "subcategory":"Art Services",
            "type":"Services"
        },
        {
            "category":"Building & Trades",
            "subcategory":"Construction",
            "type":"Services"
        }
    ],
    "sg:postcode":"PE20 1JE",
    "sg:province":"Lincolnshire",
    "sg:tags":[
        "decorator",
        "painter"
    ],
    "wof:name":"Maurice Hardy",
    "wof:placetype":"venue"
},
  "geometry": {"coordinates":[-0.0615790002,52.9268074036],"type":"Point"}
}