{
  "type": "Feature",
  "properties": {
    "iso:country":"GB",
    "sg:address":"204 White Lane",
    "sg:city":"Sheffield",
    "sg:classifiers":[
        {
            "category":"Government",
            "subcategory":"Post Office",
            "type":"Public Place"
        }
    ],
    "sg:phone":"+44 114 239 9909",
    "sg:postcode":"S12 3GL",
    "sg:province":"Derbyshire",
    "wof:name":"Gleadless Sub Post Office",
    "wof:placetype":"venue"
},
  "geometry": {"coordinates":[-1.426511,53.344524],"type":"Point"}
}