{
  "type": "Feature",
  "properties": {
    "iso:country":"GB",
    "sg:address":"21 Stonecliffe Drive, Middlestown",
    "sg:city":"Wakefield",
    "sg:classifiers":[
        {
            "category":"Home & Garden",
            "subcategory":"Household Appliances",
            "type":"Retail Goods"
        },
        {
            "category":"Retail",
            "subcategory":"Repair Shop",
            "type":"Services"
        }
    ],
    "sg:phone":"+44 1924 261516",
    "sg:postcode":"WF4 4QD",
    "sg:province":"West Yorkshire",
    "sg:tags":[
        "machine",
        "electrical",
        "washing"
    ],
    "wof:name":"Armitage Domestic Appliance Repair Service",
    "wof:placetype":"venue"
},
  "geometry": {"coordinates":[-1.5967409611,53.6499671936],"type":"Point"}
}