{
  "type": "Feature",
  "properties": {
    "addr:full":"48 Belfast Road London Greater London N16 6UH",
    "addr:housenumber":"48",
    "addr:postcode":"n16 6uh",
    "addr:street":"Belfast Road",
    "iso:country":"GB",
    "sg:address":"48 Belfast Road",
    "sg:city":"London",
    "sg:classifiers":[
        {
            "category":"Retail",
            "subcategory":"Auto Repair",
            "type":"Services"
        }
    ],
    "sg:phone":"+44 20 8806 1965",
    "sg:postcode":"N16 6UH",
    "sg:province":"Greater London",
    "sg:tags":[
        "modification",
        "garage"
    ],
    "wof:name":"Vee Kay Autos",
    "wof:placetype":"venue"
},
  "geometry": {"coordinates":[-0.0704789981,51.5653495789],"type":"Point"}
}