{
  "type": "Feature",
  "properties": {
    "iso:country":"GB",
    "sg:address":"10b Beeches Walk",
    "sg:city":"Sutton Coldfield",
    "sg:classifiers":[
        {
            "category":"Retail",
            "subcategory":"Laundry & Dry Cleaning",
            "type":"Services"
        },
        {
            "category":"Retail",
            "subcategory":"Repair Shop",
            "type":"Services"
        }
    ],
    "sg:phone":"+44 121 354 2676",
    "sg:postcode":"B73 6HN",
    "sg:province":"West Midlands",
    "sg:tags":[
        "clothing",
        "alteration"
    ],
    "wof:name":"Sew It All",
    "wof:placetype":"venue"
},
  "geometry": {"coordinates":[-1.8280830383,52.5547370911],"type":"Point"}
}