{
  "type": "Feature",
  "properties": {
    "addr:full":"57 Front Street, Cleadon Sunderland Tyne and Wear SR6 7PG",
    "addr:housenumber":"57",
    "addr:postcode":"sr6 7pg",
    "addr:street":"Front Street",
    "iso:country":"GB",
    "sg:address":"57 Front Street, Cleadon",
    "sg:city":"Sunderland",
    "sg:classifiers":[
        {
            "category":"Professional",
            "subcategory":"Management & Consulting",
            "type":"Services"
        }
    ],
    "sg:phone":"+44 191 536 7272",
    "sg:postcode":"SR6 7PG",
    "sg:province":"Tyne and Wear",
    "sg:tags":[
        "consultant",
        "specialist"
    ],
    "wof:name":"Cleadon Beauty Clinic",
    "wof:placetype":"venue"
},
  "geometry": {"coordinates":[-1.4026550055,54.9544143677],"type":"Point"}
}