{
  "type": "Feature",
  "properties": {
    "addr:full":"P O Box 11803 London Greater London N20 0RR",
    "addr:housenumber":"box 11803",
    "addr:postcode":"n20 0rr",
    "iso:country":"GB",
    "sg:address":"P O Box 11803",
    "sg:city":"London",
    "sg:classifiers":[
        {
            "category":"Retail",
            "subcategory":"Driving School",
            "type":"Services"
        }
    ],
    "sg:phone":"+44 20 8264 5000",
    "sg:postcode":"N20 0RR",
    "sg:province":"Greater London",
    "wof:name":"Alpha Beta Driving Academy",
    "wof:placetype":"venue"
},
  "geometry": {"coordinates":[-0.1550299972,51.6248283386],"type":"Point"}
}