{
  "type": "Feature",
  "properties": {
    "addr:full":"Unit 3 Frogmore Estate, Kelvin Road London Greater London N5 2PR",
    "addr:housenumber":"unit 3",
    "addr:postcode":"n5 2pr",
    "addr:street":"Frogmore Estate Kelvin Road",
    "iso:country":"GB",
    "sg:address":"Unit 3 Frogmore Estate, Kelvin Road",
    "sg:city":"London",
    "sg:classifiers":[
        {
            "category":"Professional",
            "subcategory":"Printing & Photocopies",
            "type":"Services"
        }
    ],
    "sg:phone":"+44 20 7226 2607",
    "sg:postcode":"N5 2PR",
    "sg:province":"Greater London",
    "sg:tags":[
        "printer"
    ],
    "wof:name":"Jensen Press (London) Ltd.",
    "wof:placetype":"venue"
},
  "geometry": {"coordinates":[-0.0983000025,51.5531997681],"type":"Point"}
}