{
  "type": "Feature",
  "properties": {
    "iso:country":"GB",
    "sg:address":"Unit 2 Pony Road, Cowley",
    "sg:city":"Oxford",
    "sg:classifiers":[
        {
            "category":"Wholesale",
            "subcategory":"Machinery & Supplies",
            "type":"Manufacturing & Wholesale Goods"
        }
    ],
    "sg:phone":"+44 1865 715757",
    "sg:postcode":"OX4 2RD",
    "sg:province":"Oxfordshire",
    "sg:tags":[
        "hydraulic"
    ],
    "wof:name":"M F Hydraulics Ltd.",
    "wof:placetype":"venue"
},
  "geometry": {"coordinates":[-1.194519,51.737942],"type":"Point"}
}