{
  "type": "Feature",
  "properties": {
    "addr:full":"192 Willingdon Road Eastbourne East Sussex BN21 1TT",
    "addr:housenumber":"192",
    "addr:postcode":"bn21 1tt",
    "addr:street":"Willingdon Road",
    "iso:country":"GB",
    "sg:address":"192 Willingdon Road",
    "sg:city":"Eastbourne",
    "sg:classifiers":[
        {
            "category":"Health Services",
            "subcategory":"Health Practitioner",
            "type":"Services"
        }
    ],
    "sg:postcode":"BN21 1TT",
    "sg:province":"East Sussex",
    "sg:tags":[
        "physiotherapist"
    ],
    "wof:name":"Highmead Physiotherapy & Sport Injury Clinic",
    "wof:placetype":"venue"
},
  "geometry": {"coordinates":[0.2622390091,50.7835426331],"type":"Point"}
}