{
  "type": "Feature",
  "properties": {
    "iso:country":"GB",
    "sg:address":"21 Staffick Close, Kenton",
    "sg:city":"Exeter",
    "sg:classifiers":[
        {
            "category":"Building & Trades",
            "subcategory":"Construction",
            "type":"Services"
        },
        {
            "category":"Sports & Exercise",
            "subcategory":"Playing Field",
            "type":"Entertainment"
        }
    ],
    "sg:phone":"+44 1626 891514",
    "sg:postcode":"EX6 8NS",
    "sg:province":"Devon",
    "sg:tags":[
        "conservation",
        "craft",
        "thatching",
        "related"
    ],
    "wof:name":"Paul Barkwill",
    "wof:placetype":"venue"
},
  "geometry": {"coordinates":[-3.470844,50.639534],"type":"Point"}
}