{
  "type": "Feature",
  "properties": {
    "addr:full":"Unit 6/7, Bar Hill Business Park Cambridge Cambridgeshire CB3 8SL",
    "addr:housenumber":"unit 6 / 7",
    "addr:postcode":"cb3 8sl",
    "addr:street":"Bar Hill Business Park",
    "iso:country":"GB",
    "sg:address":"Unit 6/7, Bar Hill Business Park",
    "sg:city":"Cambridge",
    "sg:classifiers":[
        {
            "category":"Home & Garden",
            "subcategory":"Building Materials",
            "type":"Retail Goods"
        },
        {
            "category":"Communications",
            "type":"Services"
        }
    ],
    "sg:phone":"+44 1954 783600",
    "sg:postcode":"CB3 8SL",
    "sg:province":"Cambridgeshire",
    "sg:tags":[
        "access",
        "equipment",
        "data",
        "network"
    ],
    "wof:name":"Imerge Ltd.",
    "wof:placetype":"venue"
},
  "geometry": {"coordinates":[0.0160700008,52.255355835],"type":"Point"}
}