{
  "type": "Feature",
  "properties": {
    "iso:country":"GB",
    "sg:address":"Plodder Lane",
    "sg:city":"Bolton",
    "sg:classifiers":[
        {
            "category":"Sports & Exercise",
            "subcategory":"Golf",
            "type":"Entertainment"
        }
    ],
    "sg:phone":"+44 1204 656493",
    "sg:postcode":"BL4 0LQ",
    "sg:province":"Lancashire",
    "sg:tags":[
        "club",
        "course"
    ],
    "wof:name":"Great Lever & Farnworth Golf Club",
    "wof:placetype":"venue"
},
  "geometry": {"coordinates":[-2.453585,53.549698],"type":"Point"}
}