{
  "type": "Feature",
  "properties": {
    "iso:country":"GB",
    "sg:address":"4 Faulkner St",
    "sg:city":"Chester",
    "sg:classifiers":[
        {
            "category":"Retail",
            "subcategory":"Photofinishing",
            "type":"Services"
        }
    ],
    "sg:phone":"+44 1244 321040",
    "sg:postcode":"CH2 3BD",
    "sg:province":"Cheshire",
    "sg:tags":[
        "photographic",
        "processor"
    ],
    "wof:name":"Photo Fast",
    "wof:placetype":"venue"
},
  "geometry": {"coordinates":[-2.876658,53.200058],"type":"Point"}
}