{
  "type": "Feature",
  "properties": {
    "addr:full":"Graham St Leicester Leicestershire LE5 3BB",
    "addr:postcode":"le5 3bb",
    "addr:street":"Graham St",
    "iso:country":"GB",
    "sg:address":"Graham St",
    "sg:city":"Leicester",
    "sg:classifiers":[
        {
            "category":"Wholesale",
            "subcategory":"Chemicals & Plastics",
            "type":"Manufacturing & Wholesale Goods"
        }
    ],
    "sg:phone":"+44 116 262 9202",
    "sg:postcode":"LE5 3BB",
    "sg:province":"Leicestershire",
    "sg:tags":[
        "product",
        "allied"
    ],
    "wof:name":"Derma Chemicals Ltd",
    "wof:placetype":"venue"
},
  "geometry": {"coordinates":[-1.118843,52.638924],"type":"Point"}
}