{
  "type": "Feature",
  "properties": {
    "addr:full":"38 George Street Richmond Greater London TW9 1HY",
    "addr:housenumber":"38",
    "addr:postcode":"tw9 1hy",
    "addr:street":"George Street",
    "iso:country":"GB",
    "sg:address":"38 George Street",
    "sg:city":"Richmond",
    "sg:classifiers":[
        {
            "category":"Shopping",
            "subcategory":"Baby Store",
            "type":"Retail Goods"
        }
    ],
    "sg:phone":"+44 20 8332 7080",
    "sg:postcode":"TW9 1HY",
    "sg:province":"Greater London",
    "sg:tags":[
        "babywear",
        "childrens"
    ],
    "wof:name":"Gap Kids",
    "wof:placetype":"venue"
},
  "geometry": {"coordinates":[-0.303619,51.461079],"type":"Point"}
}