{
  "type": "Feature",
  "properties": {
    "addr:full":"Sovereign Court, Bligh Way, Strood Rochester Kent ME2 2NE",
    "addr:postcode":"me2 2ne",
    "addr:street":"Sovereign;Bligh Way",
    "iso:country":"GB",
    "sg:address":"Sovereign Court, Bligh Way, Strood",
    "sg:city":"Rochester",
    "sg:classifiers":[
        {
            "category":"Health Services",
            "subcategory":"Nursing And Care Facility",
            "type":"Services"
        },
        {
            "category":"Organizations",
            "subcategory":"Community Association",
            "type":"Services"
        }
    ],
    "sg:phone":"+44 1634 724909",
    "sg:postcode":"ME2 2NE",
    "sg:province":"Kent",
    "sg:tags":[
        "residential",
        "housing",
        "society"
    ],
    "wof:name":"M H S HOMES LTD",
    "wof:placetype":"venue"
},
  "geometry": {"coordinates":[0.460162,51.393776],"type":"Point"}
}