{
  "type": "Feature",
  "properties": {
    "addr:full":"187-189 London Rd Liverpool Merseyside L3 8JG",
    "addr:housenumber":"187-189",
    "addr:postcode":"l3 8jg",
    "addr:street":"London Rd",
    "iso:country":"GB",
    "sg:address":"187-189 London Rd",
    "sg:city":"Liverpool",
    "sg:classifiers":[
        {
            "category":"Real Estate",
            "subcategory":"Architect",
            "type":"Services"
        }
    ],
    "sg:phone":"+44 151 207 4144",
    "sg:postcode":"L3 8JG",
    "sg:province":"Merseyside",
    "wof:name":"Leighton Associates",
    "wof:placetype":"venue"
},
  "geometry": {"coordinates":[-2.968413,53.410366],"type":"Point"}
}