{
  "type": "Feature",
  "properties": {
    "addr:full":"Somerset House, Tateley Bridge Harrogate North Yorkshire HG3 5NF",
    "addr:postcode":"hg3 5nf",
    "addr:street":"Tateley Bridge",
    "iso:country":"GB",
    "sg:address":"Somerset House, Tateley Bridge",
    "sg:city":"Harrogate",
    "sg:classifiers":[
        {
            "category":"Farming",
            "subcategory":"Farm",
            "type":"Manufacturing & Wholesale Goods"
        }
    ],
    "sg:phone":"+44 1423 711418",
    "sg:postcode":"HG3 5NF",
    "sg:province":"North Yorkshire",
    "sg:tags":[
        "mixed",
        "crop"
    ],
    "wof:name":"G H Wardman & Co",
    "wof:placetype":"venue"
},
  "geometry": {"coordinates":[-1.75146,54.098061],"type":"Point"}
}