{
  "type": "Feature",
  "properties": {
    "iso:country":"GB",
    "sg:address":"Ty Croes Mawr, Llanfaethlu",
    "sg:city":"Holyhead",
    "sg:classifiers":[
        {
            "category":"Recreation",
            "subcategory":"Fishing",
            "type":"Entertainment"
        }
    ],
    "sg:phone":"+44 1407 730877",
    "sg:postcode":"LL65 4PE",
    "sg:province":"Isle of Anglesey",
    "sg:tags":[
        "angling"
    ],
    "wof:name":"Lobstar (Uk) Ltd",
    "wof:placetype":"venue"
},
  "geometry": {"coordinates":[-4.535946,53.352547],"type":"Point"}
}