{
  "type": "Feature",
  "properties": {
    "iso:country":"GB",
    "sg:address":"Suite 1 Oak House, Brunswick St",
    "sg:city":"Macclesfield",
    "sg:classifiers":[
        {
            "category":"Shopping",
            "subcategory":"Pharmacy",
            "type":"Retail Goods"
        }
    ],
    "sg:phone":"+44 1625 433444",
    "sg:postcode":"SK10 1ER",
    "sg:province":"Cheshire",
    "sg:tags":[
        "medicine",
        "therapy"
    ],
    "wof:name":"Optimum Health",
    "wof:placetype":"venue"
},
  "geometry": {"coordinates":[-2.124579,53.261459],"type":"Point"}
}