{
  "type": "Feature",
  "properties": {
    "iso:country":"GB",
    "sg:address":"178 Chorley Road, Adlington",
    "sg:city":"Chorley",
    "sg:classifiers":[
        {
            "category":"Fast Food",
            "type":"Food & Drink"
        }
    ],
    "sg:phone":"+44 1257 474630",
    "sg:postcode":"PR6 9LQ",
    "sg:province":"Lancashire",
    "sg:tags":[
        "away",
        "meal",
        "outlet",
        "take"
    ],
    "wof:name":"Shapla Indian Takeaway",
    "wof:placetype":"venue"
},
  "geometry": {"coordinates":[-2.597922,53.617367],"type":"Point"}
}