{
  "type": "Feature",
  "properties": {
    "addr:full":"Brentford Conservative Club, Boston Park Road Brentford Greater London TW8 9JF",
    "addr:postcode":"tw8 9jf",
    "addr:street":"Boston Park Road",
    "iso:country":"GB",
    "sg:address":"Brentford Conservative Club, Boston Park Road",
    "sg:city":"Brentford",
    "sg:classifiers":[
        {
            "category":"Personal",
            "type":"Services"
        }
    ],
    "sg:postcode":"TW8 9JF",
    "sg:province":"Greater London",
    "sg:tags":[
        "slimming",
        "product"
    ],
    "wof:name":"Slimming World",
    "wof:placetype":"venue"
},
  "geometry": {"coordinates":[-0.306724,51.484135],"type":"Point"}
}