{
  "type": "Feature",
  "properties": {
    "addr:full":"7a Orchard Street Weston-super-mare Somerset BS23 1RG",
    "addr:housenumber":"7a",
    "addr:postcode":"bs23 1rg",
    "addr:street":"Orchard Street",
    "iso:country":"GB",
    "sg:address":"7a Orchard Street",
    "sg:city":"Weston-super-mare",
    "sg:classifiers":[
        {
            "category":"Building & Trades",
            "subcategory":"Cleaning & Sanitation",
            "type":"Services"
        },
        {
            "category":"Building & Trades",
            "subcategory":"Construction",
            "type":"Services"
        }
    ],
    "sg:postcode":"BS23 1RG",
    "sg:province":"Somerset",
    "sg:tags":[
        "dry",
        "control",
        "damp",
        "rot",
        "builder"
    ],
    "wof:name":"Western Preservation",
    "wof:placetype":"venue"
},
  "geometry": {"coordinates":[-2.976252,51.347595],"type":"Point"}
}