{
  "type": "Feature",
  "properties": {
    "addr:full":"15 West Road Feltham Greater London TW14 8JG",
    "addr:housenumber":"15",
    "addr:postcode":"tw14 8jg",
    "addr:street":"West Road",
    "iso:country":"GB",
    "sg:address":"15 West Road",
    "sg:city":"Feltham",
    "sg:classifiers":[
        {
            "category":"Building & Trades",
            "subcategory":"Construction",
            "type":"Services"
        }
    ],
    "sg:phone":"+44 20 8890 7930",
    "sg:postcode":"TW14 8JG",
    "sg:province":"Greater London",
    "sg:tags":[
        "builder"
    ],
    "wof:name":"Kevin McDonagh",
    "wof:placetype":"venue"
},
  "geometry": {"coordinates":[-0.4362519979,51.4528007507],"type":"Point"}
}