{
  "type": "Feature",
  "properties": {
    "addr:full":"21 Nelson St Edinburgh City of Edinburgh EH3 6LJ",
    "addr:housenumber":"21",
    "addr:postcode":"eh3 6lj",
    "addr:street":"Nelson St Edinburgh",
    "iso:country":"GB",
    "sg:address":"21 Nelson St",
    "sg:city":"Edinburgh",
    "sg:classifiers":[
        {
            "category":"Organizations",
            "subcategory":"Non-profit Organization",
            "type":"Services"
        }
    ],
    "sg:phone":"+44 131 467 7083",
    "sg:postcode":"EH3 6LJ",
    "sg:province":"City of Edinburgh",
    "sg:tags":[
        "organisation",
        "voluntary",
        "charity"
    ],
    "wof:name":"Tusk Trust",
    "wof:placetype":"venue"
},
  "geometry": {"coordinates":[-3.1957809925,55.9576034546],"type":"Point"}
}