{
  "type": "Feature",
  "properties": {
    "iso:country":"GB",
    "sg:address":"1b Gardenia Drive, Allesley",
    "sg:city":"Coventry",
    "sg:classifiers":[
        {
            "category":"Food & Beverages",
            "subcategory":"Liquor & Beverages",
            "type":"Retail Goods"
        }
    ],
    "sg:postcode":"CV5 9BN",
    "sg:province":"West Midlands",
    "sg:tags":[
        "beer",
        "spirit",
        "wines"
    ],
    "wof:name":"K Wines & Spirits",
    "wof:placetype":"venue"
},
  "geometry": {"coordinates":[-1.5671390295,52.423538208],"type":"Point"}
}