{
  "type": "Feature",
  "properties": {
    "addr:full":"34 Gore Rd New Milton Hampshire BH25 6RZ",
    "addr:housenumber":"34",
    "addr:postcode":"bh25 6rz",
    "addr:street":"Gore Rd",
    "iso:country":"GB",
    "sg:address":"34 Gore Rd",
    "sg:city":"New Milton",
    "sg:classifiers":[
        {
            "category":"Health Services",
            "subcategory":"Clinic",
            "type":"Services"
        }
    ],
    "sg:phone":"+44 1425 620171",
    "sg:postcode":"BH25 6RZ",
    "sg:province":"Hampshire",
    "sg:tags":[
        "planning",
        "family",
        "centre"
    ],
    "wof:name":"Forest Pregnancy Counselling",
    "wof:placetype":"venue"
},
  "geometry": {"coordinates":[-1.6605889797,50.7523117065],"type":"Point"}
}