{
  "type": "Feature",
  "properties": {
    "iso:country":"GB",
    "sg:address":"4 Meadway, Marton",
    "sg:city":"Blackpool",
    "sg:classifiers":[
        {
            "category":"Home & Garden",
            "subcategory":"Carpets & Floor Coverings",
            "type":"Retail Goods"
        }
    ],
    "sg:phone":"+44 1253 762683",
    "sg:postcode":"FY4 4DL",
    "sg:province":"Lancashire",
    "sg:tags":[
        "carpets",
        "rug",
        "matting"
    ],
    "wof:name":"R.H Parsons",
    "wof:placetype":"venue"
},
  "geometry": {"coordinates":[-3.026113987,53.8008537292],"type":"Point"}
}