{
  "type": "Feature",
  "properties": {
    "addr:full":"160 Hamblett Court Road, Westcliff Southend-on-sea Essex SS0 7LJ",
    "addr:housenumber":"160",
    "addr:postcode":"ss0 7lj",
    "addr:street":"Hamblett Court Road",
    "iso:country":"GB",
    "sg:address":"160 Hamblett Court Road, Westcliff",
    "sg:city":"Southend-on-sea",
    "sg:classifiers":[
        {
            "category":"Food & Beverages",
            "subcategory":"Meat & Fish",
            "type":"Retail Goods"
        }
    ],
    "sg:phone":"+44 1702 347166",
    "sg:postcode":"SS0 7LJ",
    "sg:province":"Essex",
    "sg:tags":[
        "butcher"
    ],
    "wof:name":"Mertens Meats",
    "wof:placetype":"venue"
},
  "geometry": {"coordinates":[0.695748,51.540882],"type":"Point"}
}