{
  "type": "Feature",
  "properties": {
    "addr:full":"The Garage, 73 Boston Road Sleaford Lincolnshire NG34 7HH",
    "addr:housenumber":"73",
    "addr:postcode":"ng34 7hh",
    "addr:street":"Boston Road",
    "iso:country":"GB",
    "sg:address":"The Garage, 73 Boston Road",
    "sg:city":"Sleaford",
    "sg:classifiers":[
        {
            "category":"Autos & Motor Vehicles",
            "subcategory":"Automobile Sales",
            "type":"Retail Goods"
        }
    ],
    "sg:phone":"+44 1529 302518",
    "sg:postcode":"NG34 7HH",
    "sg:province":"Lincolnshire",
    "sg:tags":[
        "car"
    ],
    "wof:name":"J T Lord & Son (Sleaford) Ltd.",
    "wof:placetype":"venue"
},
  "geometry": {"coordinates":[-0.4118689895,52.9945869446],"type":"Point"}
}