{
  "type": "Feature",
  "properties": {
    "addr:full":"304 High Street Dorking Surrey RH4 1QX",
    "addr:housenumber":"304",
    "addr:postcode":"rh4 1qx",
    "addr:street":"High Street",
    "iso:country":"GB",
    "sg:address":"304 High Street",
    "sg:city":"Dorking",
    "sg:classifiers":[
        {
            "category":"Restaurant",
            "type":"Food & Drink"
        }
    ],
    "sg:phone":"+44 1306 889006",
    "sg:postcode":"RH4 1QX",
    "sg:province":"Surrey",
    "sg:tags":[
        "indian"
    ],
    "wof:name":"Khyber Pass",
    "wof:placetype":"venue"
},
  "geometry": {"coordinates":[-0.326711,51.234436],"type":"Point"}
}