{
  "type": "Feature",
  "properties": {
    "addr:full":"31 Salisbury Street Fordingbridge Dorset SP6 1AB",
    "addr:housenumber":"31",
    "addr:postcode":"sp6 1ab",
    "addr:street":"Salisbury Street",
    "iso:country":"GB",
    "sg:address":"31 Salisbury Street",
    "sg:city":"Fordingbridge",
    "sg:classifiers":[
        {
            "category":"Shopping",
            "subcategory":"Crafts & Fabrics",
            "type":"Retail Goods"
        }
    ],
    "sg:postcode":"SP6 1AB",
    "sg:province":"Dorset",
    "sg:tags":[
        "shop",
        "needlecraft",
        "wool"
    ],
    "wof:name":"Applins Wools & Haberdashery",
    "wof:placetype":"venue"
},
  "geometry": {"coordinates":[-1.7891390324,50.9284706116],"type":"Point"}
}