{
  "type": "Feature",
  "properties": {
    "iso:country":"GB",
    "sg:address":"18 Esplanade",
    "sg:city":"Ryde",
    "sg:classifiers":[
        {
            "category":"Travel",
            "subcategory":"Hotels & Motels",
            "type":"Entertainment"
        }
    ],
    "sg:phone":"+44 1983 566521",
    "sg:postcode":"PO33 2DZ",
    "sg:province":"Isle of Wight",
    "sg:tags":[
        "self",
        "catering"
    ],
    "wof:name":"Beachcomber Holiday Flats",
    "wof:placetype":"venue"
},
  "geometry": {"coordinates":[-1.158881,50.732174],"type":"Point"}
}