{
  "type": "Feature",
  "properties": {
    "addr:full":"120 Wakefield Road Halifax West Yorkshire HX3 8TH",
    "addr:housenumber":"120",
    "addr:postcode":"hx3 8th",
    "addr:street":"Wakefield Road",
    "iso:country":"GB",
    "sg:address":"120 Wakefield Road",
    "sg:city":"Halifax",
    "sg:classifiers":[
        {
            "category":"Arts & Performance",
            "subcategory":"Music",
            "type":"Entertainment"
        }
    ],
    "sg:phone":"+44 1422 203871",
    "sg:postcode":"HX3 8TH",
    "sg:province":"West Yorkshire",
    "sg:tags":[
        "mobile",
        "disco"
    ],
    "wof:name":"Past 'N' Present Disco Sounds",
    "wof:placetype":"venue"
},
  "geometry": {"coordinates":[-1.7936450243,53.7249145508],"type":"Point"}
}