{
  "type": "Feature",
  "properties": {
    "addr:full":"102 High Street, Epworth Doncaster Lincolnshire DN9 1JS",
    "addr:housenumber":"102",
    "addr:postcode":"dn9 1js",
    "addr:street":"High Street",
    "iso:country":"GB",
    "sg:address":"102 High Street, Epworth",
    "sg:city":"Doncaster",
    "sg:classifiers":[
        {
            "category":"Home & Garden",
            "subcategory":"Carpets & Floor Coverings",
            "type":"Retail Goods"
        }
    ],
    "sg:postcode":"DN9 1JS",
    "sg:province":"Lincolnshire",
    "sg:tags":[
        "carpets",
        "rug",
        "matting"
    ],
    "wof:name":"B M Brown Carpet Fitter",
    "wof:placetype":"venue"
},
  "geometry": {"coordinates":[-0.824559,53.52647],"type":"Point"}
}