{
  "type": "Feature",
  "properties": {
    "addr:full":"23 Crayford Road, Alvaston Derby Derbyshire DE24 0HL",
    "addr:housenumber":"23",
    "addr:postcode":"de24 0hl",
    "addr:street":"Crayford Road",
    "iso:country":"GB",
    "sg:address":"23 Crayford Road, Alvaston",
    "sg:city":"Derby",
    "sg:classifiers":[
        {
            "category":"Shopping",
            "subcategory":"Department Store",
            "type":"Retail Goods"
        },
        {
            "category":"Food & Beverages",
            "subcategory":"Groceries & Convenience Stores",
            "type":"Retail Goods"
        }
    ],
    "sg:phone":"+44 1332 732466",
    "sg:postcode":"DE24 0HL",
    "sg:province":"Derbyshire",
    "wof:name":"Crayford Stores",
    "wof:placetype":"venue"
},
  "geometry": {"coordinates":[-1.435264,52.88805],"type":"Point"}
}