{
  "type": "Feature",
  "properties": {
    "addr:full":"Chelsea Ho, Chelsea Arc, The Broadway Haywards Heath East Sussex RH16 3AP",
    "addr:postcode":"rh16 3ap",
    "addr:street":"The Broadway",
    "iso:country":"GB",
    "sg:address":"Chelsea Ho, Chelsea Arc, The Broadway",
    "sg:city":"Haywards Heath",
    "sg:classifiers":[
        {
            "category":"Banks & Credit Unions",
            "subcategory":"Financial Services",
            "type":"Services"
        }
    ],
    "sg:phone":"+44 1444 440365",
    "sg:postcode":"RH16 3AP",
    "sg:province":"East Sussex",
    "sg:tags":[
        "consultant"
    ],
    "wof:name":"P L T Ltd",
    "wof:placetype":"venue"
},
  "geometry": {"coordinates":[-0.1020469964,50.9966583252],"type":"Point"}
}