{
  "type": "Feature",
  "properties": {
    "addr:full":"710 Chesterfield Rd, Woodsoats Sheffield Derbyshire S8 0SD",
    "addr:housenumber":"710",
    "addr:postcode":"s8 0sd",
    "addr:street":"Chesterfield Rd",
    "iso:country":"GB",
    "sg:address":"710 Chesterfield Rd, Woodsoats",
    "sg:city":"Sheffield",
    "sg:classifiers":[
        {
            "category":"Shopping",
            "subcategory":"Clothing, Apparel, & Fashions",
            "type":"Retail Goods"
        }
    ],
    "sg:postcode":"S8 0SD",
    "sg:province":"Derbyshire",
    "sg:tags":[
        "dresswear"
    ],
    "wof:name":"Intrique Boutique",
    "wof:placetype":"venue"
},
  "geometry": {"coordinates":[-1.478323,53.343735],"type":"Point"}
}