{
  "type": "Feature",
  "properties": {
    "addr:full":"27 Warley Hill, Warley Brentwood Essex CM14 5HR",
    "addr:housenumber":"27",
    "addr:postcode":"cm14 5hr",
    "addr:street":"Warley Hill",
    "iso:country":"GB",
    "sg:address":"27 Warley Hill, Warley",
    "sg:city":"Brentwood",
    "sg:classifiers":[
        {
            "category":"Wholesale",
            "subcategory":"Construction Materials",
            "type":"Manufacturing & Wholesale Goods"
        },
        {
            "category":"Building & Trades",
            "subcategory":"Construction",
            "type":"Services"
        }
    ],
    "sg:phone":"+44 1277 218721",
    "sg:postcode":"CM14 5HR",
    "sg:province":"Essex",
    "sg:tags":[
        "merchant",
        "glass",
        "glazier"
    ],
    "wof:name":"Brentwood Glass",
    "wof:placetype":"venue"
},
  "geometry": {"coordinates":[0.29868,51.612492],"type":"Point"}
}