{
  "type": "Feature",
  "properties": {
    "addr:full":"Rock Cross, Rock Kidderminster Shropshire DY14 9RH",
    "addr:postcode":"dy14 9rh",
    "addr:street":"Rock Cross Rock",
    "iso:country":"GB",
    "sg:address":"Rock Cross, Rock",
    "sg:city":"Kidderminster",
    "sg:classifiers":[
        {
            "category":"Farming",
            "subcategory":"Livestock Farm",
            "type":"Manufacturing & Wholesale Goods"
        }
    ],
    "sg:phone":"+44 1299 832677",
    "sg:postcode":"DY14 9RH",
    "sg:province":"Shropshire",
    "sg:tags":[
        "others"
    ],
    "wof:name":"Ernest A Fletcher",
    "wof:placetype":"venue"
},
  "geometry": {"coordinates":[-2.3899700642,52.3388175964],"type":"Point"}
}