{
  "type": "Feature",
  "properties": {
    "addr:full":"9 Rose Crescent Cambridge Cambridgeshire CB2 3LL",
    "addr:housenumber":"9",
    "addr:postcode":"cb2 3ll",
    "addr:street":"Rose Crescent",
    "iso:country":"GB",
    "sg:address":"9 Rose Crescent",
    "sg:city":"Cambridge",
    "sg:classifiers":[
        {
            "category":"Fast Food",
            "type":"Food & Drink"
        },
        {
            "category":"Restaurant",
            "type":"Food & Drink"
        }
    ],
    "sg:phone":"+44 1223 303020",
    "sg:postcode":"CB2 3LL",
    "sg:province":"Cambridgeshire",
    "sg:tags":[
        "american",
        "-",
        "away",
        "take"
    ],
    "wof:name":"McDonald's Restaurants Ltd",
    "wof:placetype":"venue"
},
  "geometry": {"coordinates":[0.1189690009,52.2059249878],"type":"Point"}
}