{
  "type": "Feature",
  "properties": {
    "addr:full":"8 Camden Place Preston Lancashire PR1 3JL",
    "addr:housenumber":"8",
    "addr:postcode":"pr1 3jl",
    "addr:street":"Camden Place",
    "iso:country":"GB",
    "sg:address":"8 Camden Place",
    "sg:city":"Preston",
    "sg:classifiers":[
        {
            "category":"Professional",
            "subcategory":"Accounting & Tax Preparation",
            "type":"Services"
        }
    ],
    "sg:phone":"+44 1772 200666",
    "sg:postcode":"PR1 3JL",
    "sg:province":"Lancashire",
    "sg:tags":[
        "accountant"
    ],
    "wof:name":"Bolland Associates",
    "wof:placetype":"venue"
},
  "geometry": {"coordinates":[-2.7009830475,53.7549133301],"type":"Point"}
}