{
  "type": "Feature",
  "properties": {
    "iso:country":"GB",
    "sg:address":"Unit 2 Praed Road, Trafford Park",
    "sg:city":"Manchester",
    "sg:classifiers":[
        {
            "category":"Freight",
            "type":"Transportation"
        }
    ],
    "sg:phone":"+44 161 848 7770",
    "sg:postcode":"M17 1PQ",
    "sg:province":"Cheshire",
    "sg:tags":[
        "haulage",
        "road"
    ],
    "wof:name":"Lever Massey Haulage Ltd.",
    "wof:placetype":"venue"
},
  "geometry": {"coordinates":[-2.315559,53.465065],"type":"Point"}
}