{
  "type": "Feature",
  "properties": {
    "addr:full":"Unit C4 (1) Centre Ct, Moss Indust Est, St Helens Rd Leigh Lancashire WN7 3PT",
    "addr:housenumber":"1",
    "addr:postcode":"wn7 3pt",
    "addr:street":"Centre Ct;St Helens Rd",
    "iso:country":"GB",
    "sg:address":"Unit C4 (1) Centre Ct, Moss Indust Est, St Helens Rd",
    "sg:city":"Leigh",
    "sg:classifiers":[
        {
            "category":"Real Estate",
            "subcategory":"Real Estate Agent",
            "type":"Services"
        }
    ],
    "sg:phone":"+44 1942 671231",
    "sg:postcode":"WN7 3PT",
    "sg:province":"Lancashire",
    "wof:name":"Moss Industrial Estate",
    "wof:placetype":"venue"
},
  "geometry": {"coordinates":[-2.549448967,53.4783210754],"type":"Point"}
}