{
  "type": "Feature",
  "properties": {
    "addr:full":"2 Knights Close, Bozeat Wellingborough Bedfordshire NN29 7LQ",
    "addr:housenumber":"2",
    "addr:postcode":"nn29 7lq",
    "addr:street":"Knights Close",
    "iso:country":"GB",
    "sg:address":"2 Knights Close, Bozeat",
    "sg:city":"Wellingborough",
    "sg:classifiers":[
        {
            "category":"Organizations",
            "subcategory":"Non-profit Organization",
            "type":"Services"
        }
    ],
    "sg:postcode":"NN29 7LQ",
    "sg:province":"Bedfordshire",
    "sg:tags":[
        "charitable",
        "organisation",
        "voluntary",
        "charity"
    ],
    "wof:name":"MULTIPLE SCLEROSIS SOCIETY OF GREAT BRITAIN & NORTHERN IRELAND",
    "wof:placetype":"venue"
},
  "geometry": {"coordinates":[-0.673583,52.219849],"type":"Point"}
}