{
  "type": "Feature",
  "properties": {
    "addr:full":"9 Cranford Way, Hornsey London Greater London N8 9DG",
    "addr:housenumber":"9",
    "addr:postcode":"n8 9dg",
    "addr:street":"Cranford Way",
    "iso:country":"GB",
    "sg:address":"9 Cranford Way, Hornsey",
    "sg:city":"London",
    "sg:classifiers":[
        {
            "category":"Shopping",
            "subcategory":"Clothing, Apparel, & Fashions",
            "type":"Retail Goods"
        }
    ],
    "sg:phone":"+44 20 8341 9700",
    "sg:postcode":"N8 9DG",
    "sg:province":"Greater London",
    "sg:tags":[
        "t-shirt"
    ],
    "wof:name":"The Tradewinds Merchandising Co. Ltd.",
    "wof:placetype":"venue"
},
  "geometry": {"coordinates":[-0.109666,51.580116],"type":"Point"}
}