{
  "type": "Feature",
  "properties": {
    "addr:full":"142 Narborough Road South Leicester Leicestershire LE3 2LA",
    "addr:housenumber":"142",
    "addr:postcode":"le3 2la",
    "addr:street":"Narborough Road South",
    "iso:country":"GB",
    "sg:address":"142 Narborough Road South",
    "sg:city":"Leicester",
    "sg:classifiers":[
        {
            "category":"Retail",
            "subcategory":"Driving School",
            "type":"Services"
        },
        {
            "category":"Education",
            "subcategory":"University",
            "type":"Public Place"
        }
    ],
    "sg:postcode":"LE3 2LA",
    "sg:province":"Leicestershire",
    "sg:tags":[
        "higher"
    ],
    "wof:name":"Ellis School of Motoring",
    "wof:placetype":"venue"
},
  "geometry": {"coordinates":[-1.173797,52.605286],"type":"Point"}
}