{
  "type": "Feature",
  "properties": {
    "addr:full":"A W Nielson Road Goole East Riding of Yorkshire DN14 6XQ",
    "addr:postcode":"dn14 6xq",
    "addr:street":"A W Nielson Road",
    "iso:country":"GB",
    "sg:address":"A W Nielson Road",
    "sg:city":"Goole",
    "sg:classifiers":[
        {
            "category":"Freight",
            "type":"Transportation"
        }
    ],
    "sg:postcode":"DN14 6XQ",
    "sg:province":"East Riding of Yorkshire",
    "sg:tags":[
        "forwarders"
    ],
    "wof:name":"Ciscato Shipping & Forwarding Ltd.",
    "wof:placetype":"venue"
},
  "geometry": {"coordinates":[-0.874499,53.704514],"type":"Point"}
}