{
  "type": "Feature",
  "properties": {
    "addr:full":"Southwater Way, Town Centre Telford Shropshire TF3 4LN",
    "addr:postcode":"tf3 4ln",
    "addr:street":"Southwater Way",
    "iso:country":"GB",
    "sg:address":"Southwater Way, Town Centre",
    "sg:city":"Telford",
    "sg:classifiers":[
        {
            "category":"Shopping",
            "subcategory":"Gifts & Souvenirs",
            "type":"Retail Goods"
        }
    ],
    "sg:phone":"+44 1952 201905",
    "sg:postcode":"TF3 4LN",
    "sg:province":"Shropshire",
    "sg:tags":[
        "poster",
        "card"
    ],
    "wof:name":"John & Marie Byrne",
    "wof:placetype":"venue"
},
  "geometry": {"coordinates":[-2.444159,52.673939],"type":"Point"}
}