{
  "type": "Feature",
  "properties": {
    "addr:full":"54 Gladstone Street Scarborough North Yorkshire YO12 7BN",
    "addr:housenumber":"54",
    "addr:postcode":"yo12 7bn",
    "addr:street":"Gladstone Street",
    "iso:country":"GB",
    "sg:address":"54 Gladstone Street",
    "sg:city":"Scarborough",
    "sg:classifiers":[
        {
            "category":"Retail",
            "subcategory":"Auto Repair",
            "type":"Services"
        }
    ],
    "sg:phone":"+44 1723 500145",
    "sg:postcode":"YO12 7BN",
    "sg:province":"North Yorkshire",
    "sg:tags":[
        "modification",
        "garage"
    ],
    "wof:name":"Billy McSweeney Motors",
    "wof:placetype":"venue"
},
  "geometry": {"coordinates":[-0.412987,54.282032],"type":"Point"}
}