{
  "type": "Feature",
  "properties": {
    "addr:full":"59 Newbiggin Richmond North Yorkshire DL10 4DX",
    "addr:housenumber":"59",
    "addr:postcode":"dl10 4dx",
    "addr:street":"Newbiggin Richmond",
    "iso:country":"GB",
    "sg:address":"59 Newbiggin",
    "sg:city":"Richmond",
    "sg:classifiers":[
        {
            "category":"Social Services",
            "subcategory":"Adult Care",
            "type":"Services"
        },
        {
            "category":"Government",
            "subcategory":"Office",
            "type":"Public Place"
        }
    ],
    "sg:phone":"+44 1748 850031",
    "sg:postcode":"DL10 4DX",
    "sg:province":"North Yorkshire",
    "sg:tags":[
        "local",
        "day",
        "centre"
    ],
    "wof:name":"Ashlands Outreach",
    "wof:placetype":"venue"
},
  "geometry": {"coordinates":[-1.742707,54.403683],"type":"Point"}
}