{
  "type": "Feature",
  "properties": {
    "iso:country":"GB",
    "sg:address":"28 Fifth Avenue, Heworth",
    "sg:city":"York",
    "sg:classifiers":[
        {
            "category":"Health Services",
            "subcategory":"Clinic",
            "type":"Services"
        }
    ],
    "sg:phone":"+44 1904 430652",
    "sg:postcode":"YO31 0XA",
    "sg:province":"North Yorkshire",
    "sg:tags":[
        "aromatherapy"
    ],
    "wof:name":"Tuesday Burlingham",
    "wof:placetype":"venue"
},
  "geometry": {"coordinates":[-1.066571,53.962723],"type":"Point"}
}