{
  "type": "Feature",
  "properties": {
    "iso:country":"GB",
    "sg:address":"15 Homerton Street",
    "sg:city":"Cambridge",
    "sg:classifiers":[
        {
            "category":"Professional",
            "subcategory":"Business Services",
            "type":"Services"
        }
    ],
    "sg:postcode":"CB2 2NZ",
    "sg:province":"Cambridgeshire",
    "sg:tags":[
        "import",
        "export",
        "agent"
    ],
    "wof:name":"Moore Universal Ltd.",
    "wof:placetype":"venue"
},
  "geometry": {"coordinates":[0.13933,52.183842],"type":"Point"}
}