{
  "type": "Feature",
  "properties": {
    "iso:country":"GB",
    "sg:address":"Lyndene, Station Road, Baschurch",
    "sg:city":"Shrewsbury",
    "sg:classifiers":[
        {
            "category":"Education",
            "subcategory":"Special Training",
            "type":"Public Place"
        }
    ],
    "sg:phone":"+44 1939 261005",
    "sg:postcode":"SY4 2BB",
    "sg:province":"Shropshire",
    "sg:tags":[
        "product",
        "centre"
    ],
    "wof:name":"Central Safety Systems",
    "wof:placetype":"venue"
},
  "geometry": {"coordinates":[-2.85266,52.787228],"type":"Point"}
}