{
  "type": "Feature",
  "properties": {
    "addr:full":"Chrystie Recreation Ground, Dorking Road, Great Bookham Leatherhead Surrey KT22 0NP",
    "addr:postcode":"kt22 0np",
    "addr:street":"Dorking Road",
    "iso:country":"GB",
    "sg:address":"Chrystie Recreation Ground, Dorking Road, Great Bookham",
    "sg:city":"Leatherhead",
    "sg:classifiers":[
        {
            "category":"Arena",
            "subcategory":"Sports Club",
            "type":"Entertainment"
        }
    ],
    "sg:phone":"+44 1372 450020",
    "sg:postcode":"KT22 0NP",
    "sg:province":"Surrey",
    "wof:name":"Bookham Bowls Club",
    "wof:placetype":"venue"
},
  "geometry": {"coordinates":[-0.329418987,51.2963600159],"type":"Point"}
}