{
  "type": "Feature",
  "properties": {
    "addr:full":"142 Commercial Street Maesteg Bridgend CF34 9DW",
    "addr:housenumber":"142",
    "addr:postcode":"cf34 9dw",
    "addr:street":"Commercial Street",
    "iso:country":"GB",
    "sg:address":"142 Commercial Street",
    "sg:city":"Maesteg",
    "sg:classifiers":[
        {
            "category":"Shopping",
            "subcategory":"Shoes",
            "type":"Retail Goods"
        }
    ],
    "sg:phone":"+44 1656 733438",
    "sg:postcode":"CF34 9DW",
    "sg:province":"Bridgend",
    "sg:tags":[
        "shop",
        "retailer",
        "footwear"
    ],
    "wof:name":"Shoefayre Ltd",
    "wof:placetype":"venue"
},
  "geometry": {"coordinates":[-3.6601519585,51.608215332],"type":"Point"}
}