{
  "type": "Feature",
  "properties": {
    "iso:country":"GB",
    "sg:address":"30 White Rose Shopping Centre",
    "sg:city":"Leeds",
    "sg:classifiers":[
        {
            "category":"Shopping",
            "subcategory":"Clothing, Apparel, & Fashions",
            "type":"Retail Goods"
        }
    ],
    "sg:phone":"+44 113 277 2112",
    "sg:postcode":"LS11 8LU",
    "sg:province":"West Yorkshire",
    "sg:tags":[
        "menswear"
    ],
    "wof:name":"Ciro Citterio Menswear Plc",
    "wof:placetype":"venue"
},
  "geometry": {"coordinates":[-1.572584,53.761459],"type":"Point"}
}