{
  "type": "Feature",
  "properties": {
    "iso:country":"GB",
    "sg:address":"208 Oakwood Lane, Oakwood",
    "sg:city":"Leeds",
    "sg:classifiers":[
        {
            "category":"Retail",
            "subcategory":"Repair Shop",
            "type":"Services"
        }
    ],
    "sg:phone":"+44 113 240 1402",
    "sg:postcode":"LS8 2PE",
    "sg:province":"West Yorkshire",
    "sg:tags":[
        "upholstering",
        "upholsterer"
    ],
    "wof:name":"Sovereign Upholstery",
    "wof:placetype":"venue"
},
  "geometry": {"coordinates":[-1.4980089664,53.8229293823],"type":"Point"}
}