{
  "type": "Feature",
  "properties": {
    "addr:full":"Suite 2 Geddes Warehouse, Town Quay Southampton Hampshire SO14 2AR",
    "addr:housenumber":"suite 2",
    "addr:postcode":"so14 2ar",
    "iso:country":"GB",
    "sg:address":"Suite 2 Geddes Warehouse, Town Quay",
    "sg:city":"Southampton",
    "sg:classifiers":[
        {
            "category":"Insurance",
            "subcategory":"Insurance Agent",
            "type":"Services"
        }
    ],
    "sg:phone":"+44 23 8033 6800",
    "sg:postcode":"SO14 2AR",
    "sg:province":"Hampshire",
    "sg:tags":[
        "broker"
    ],
    "wof:name":"J T C Insurance Brokers Ltd.",
    "wof:placetype":"venue"
},
  "geometry": {"coordinates":[-1.40511,50.896851],"type":"Point"}
}