{
  "type": "Feature",
  "properties": {
    "addr:full":"51 Stoke Gabriel Road, Galmpton Brixham Devon TQ5 0NH",
    "addr:housenumber":"51",
    "addr:postcode":"tq5 0nh",
    "addr:street":"Stoke Gabriel Road",
    "iso:country":"GB",
    "sg:address":"51 Stoke Gabriel Road, Galmpton",
    "sg:city":"Brixham",
    "sg:classifiers":[
        {
            "category":"Government",
            "subcategory":"Post Office",
            "type":"Public Place"
        }
    ],
    "sg:phone":"+44 1803 842148",
    "sg:postcode":"TQ5 0NH",
    "sg:province":"Devon",
    "wof:name":"Galleon Stores",
    "wof:placetype":"venue"
},
  "geometry": {"coordinates":[-3.5673849583,50.3956031799],"type":"Point"}
}