{
  "type": "Feature",
  "properties": {
    "addr:full":"39 Bridgnorth Road Wolverhampton Shropshire WV6 8AF",
    "addr:housenumber":"39",
    "addr:postcode":"wv6 8af",
    "addr:street":"Bridgnorth Road",
    "iso:country":"GB",
    "sg:address":"39 Bridgnorth Road",
    "sg:city":"Wolverhampton",
    "sg:classifiers":[
        {
            "category":"Professional",
            "subcategory":"Accounting & Tax Preparation",
            "type":"Services"
        },
        {
            "category":"Health Services",
            "subcategory":"Optometrist",
            "type":"Services"
        }
    ],
    "sg:postcode":"WV6 8AF",
    "sg:province":"Shropshire",
    "sg:tags":[
        "accountant",
        "optician"
    ],
    "wof:name":"Taylor Biddle",
    "wof:placetype":"venue"
},
  "geometry": {"coordinates":[-2.1757590771,52.5869102478],"type":"Point"}
}