{
  "type": "Feature",
  "properties": {
    "addr:full":"87 Etnam Street Leominster Herefordshire HR6 8AE",
    "addr:housenumber":"87",
    "addr:postcode":"hr6 8ae",
    "addr:street":"Etnam Street",
    "iso:country":"GB",
    "sg:address":"87 Etnam Street",
    "sg:city":"Leominster",
    "sg:classifiers":[
        {
            "category":"Shopping",
            "subcategory":"Musical Instruments",
            "type":"Retail Goods"
        }
    ],
    "sg:phone":"+44 1568 613611",
    "sg:postcode":"HR6 8AE",
    "sg:province":"Herefordshire",
    "sg:tags":[
        "retailer",
        "sheet",
        "music"
    ],
    "wof:name":"Trevor Davies Music",
    "wof:placetype":"venue"
},
  "geometry": {"coordinates":[-2.734244,52.226456],"type":"Point"}
}