{
  "type": "Feature",
  "properties": {
    "iso:country":"GB",
    "sg:address":"Unit 3 Berryden Business Centre, Berryden Road",
    "sg:city":"Aberdeen",
    "sg:classifiers":[
        {
            "category":"Home & Garden",
            "subcategory":"Carpets & Floor Coverings",
            "type":"Retail Goods"
        }
    ],
    "sg:phone":"+44 1224 658688",
    "sg:postcode":"AB25 3SA",
    "sg:province":"Aberdeen City",
    "sg:tags":[
        "carpets",
        "rug",
        "matting"
    ],
    "wof:name":"Carpet Depot",
    "wof:placetype":"venue"
},
  "geometry": {"coordinates":[-2.1067891121,57.1538200378],"type":"Point"}
}