{
  "type": "Feature",
  "properties": {
    "iso:country":"GB",
    "sg:address":"56-58 High Street",
    "sg:city":"Sutton",
    "sg:classifiers":[
        {
            "category":"Organizations",
            "subcategory":"Labor Organization",
            "type":"Services"
        },
        {
            "category":"Professional",
            "subcategory":"Business Services",
            "type":"Services"
        }
    ],
    "sg:phone":"+44 20 8722 5900",
    "sg:postcode":"SM1 1EZ",
    "sg:province":"Surrey",
    "sg:tags":[
        "import",
        "export",
        "agent"
    ],
    "sg:website":"http://www.marpex.com",
    "wof:name":"Marpex Chemicals Ltd.",
    "wof:placetype":"venue"
},
  "geometry": {"coordinates":[-0.192187,51.361652],"type":"Point"}
}