{
  "type": "Feature",
  "properties": {
    "iso:country":"GB",
    "sg:address":"1 Audley Road",
    "sg:city":"Enfield",
    "sg:classifiers":[
        {
            "category":"Building & Trades",
            "subcategory":"Cleaning & Sanitation",
            "type":"Services"
        }
    ],
    "sg:phone":"+44 20 8216 5965",
    "sg:postcode":"EN2 8PL",
    "sg:province":"Greater London",
    "sg:tags":[
        "blast"
    ],
    "wof:name":"Power Clean Services",
    "wof:placetype":"venue"
},
  "geometry": {"coordinates":[-0.0979510024,51.6590232849],"type":"Point"}
}