{
  "type": "Feature",
  "properties": {
    "addr:full":"11-13 High Street Swanley Kent BR8 8AE",
    "addr:housenumber":"11-13",
    "addr:postcode":"br8 8ae",
    "addr:street":"High Street",
    "iso:country":"GB",
    "sg:address":"11-13 High Street",
    "sg:city":"Swanley",
    "sg:classifiers":[
        {
            "category":"Professional",
            "subcategory":"Accounting & Tax Preparation",
            "type":"Services"
        }
    ],
    "sg:phone":"+44 1322 665732",
    "sg:postcode":"BR8 8AE",
    "sg:province":"Kent",
    "sg:tags":[
        "accountant"
    ],
    "wof:name":"T S Batt",
    "wof:placetype":"venue"
},
  "geometry": {"coordinates":[0.1774670035,51.3954391479],"type":"Point"}
}