{
  "type": "Feature",
  "properties": {
    "addr:full":"Block 5, Unit 4, New Albion Industrial Estate Glasgow Glasgow City G13 4DT",
    "addr:housenumber":"unit 4",
    "addr:postcode":"g13 4dt",
    "addr:street":"New;Industrial Estate",
    "iso:country":"GB",
    "sg:address":"Block 5, Unit 4, New Albion Industrial Estate",
    "sg:city":"Glasgow",
    "sg:classifiers":[
        {
            "category":"Manufacturing",
            "subcategory":"Metals",
            "type":"Manufacturing & Wholesale Goods"
        }
    ],
    "sg:phone":"+44 141 952 3186",
    "sg:postcode":"G13 4DT",
    "sg:province":"Glasgow City",
    "sg:tags":[
        "work",
        "sheet"
    ],
    "wof:name":"Youmac Sheet Metal Ltd.",
    "wof:placetype":"venue"
},
  "geometry": {"coordinates":[-4.2425107956,55.8578071594],"type":"Point"}
}