{
  "type": "Feature",
  "properties": {
    "addr:full":"213 Preston Road Brighton East Sussex BN1 6SA",
    "addr:housenumber":"213",
    "addr:postcode":"bn1 6sa",
    "addr:street":"Preston Road",
    "iso:country":"GB",
    "sg:address":"213 Preston Road",
    "sg:city":"Brighton",
    "sg:classifiers":[
        {
            "category":"Bars & Pubs",
            "type":"Food & Drink"
        }
    ],
    "sg:postcode":"BN1 6SA",
    "sg:province":"East Sussex",
    "sg:tags":[
        "pubs",
        "inn"
    ],
    "wof:name":"Crown & Anchor",
    "wof:placetype":"venue"
},
  "geometry": {"coordinates":[-0.1514730006,50.8431549072],"type":"Point"}
}