{
  "type": "Feature",
  "properties": {
    "iso:country":"GB",
    "sg:address":"1-6 Glengall Road",
    "sg:city":"London",
    "sg:classifiers":[
        {
            "category":"Restaurant",
            "type":"Food & Drink"
        }
    ],
    "sg:postcode":"NW6 7EP",
    "sg:province":"Greater London",
    "sg:tags":[
        "greek"
    ],
    "wof:name":"Aurel Dedi",
    "wof:placetype":"venue"
},
  "geometry": {"coordinates":[-0.1960780025,51.539894104],"type":"Point"}
}