{
  "type": "Feature",
  "properties": {
    "iso:country":"GB",
    "sg:address":"Terminal Buildings, East Midlands Intl Airport, Castle Donington",
    "sg:city":"Derby",
    "sg:classifiers":[
        {
            "category":"Travel",
            "subcategory":"Travel Agent",
            "type":"Entertainment"
        }
    ],
    "sg:phone":"+44 1332 853350",
    "sg:postcode":"DE74 2SA",
    "sg:province":"Leicestershire",
    "wof:name":"Ilkeston Co-Operative Travel Centre",
    "wof:placetype":"venue"
},
  "geometry": {"coordinates":[-1.3373839855,52.8448791504],"type":"Point"}
}