{
  "type": "Feature",
  "properties": {
    "addr:full":"Chichester & Arun Branch Chichester West Sussex PO18 0EH",
    "addr:postcode":"po18 0eh",
    "iso:country":"GB",
    "sg:address":"Chichester & Arun Branch",
    "sg:city":"Chichester",
    "sg:classifiers":[
        {
            "category":"Personal",
            "type":"Services"
        },
        {
            "category":"Professional",
            "subcategory":"Lawyer & Legal Services",
            "type":"Services"
        },
        {
            "category":"Organizations",
            "subcategory":"Membership Organization",
            "type":"Services"
        }
    ],
    "sg:phone":"+44 1243 530202",
    "sg:postcode":"PO18 0EH",
    "sg:province":"West Sussex",
    "sg:tags":[
        "club",
        "advice",
        "counselling",
        "social"
    ],
    "wof:name":"Cruse - Bereavement Care",
    "wof:placetype":"venue"
},
  "geometry": {"coordinates":[-0.7155500054,50.8595581055],"type":"Point"}
}