{
  "type": "Feature",
  "properties": {
    "addr:full":"Suite 401, 302-308 Regent Street London Greater London W1B 3HH",
    "addr:housenumber":"suite 401",
    "addr:postcode":"302-308;w1b 3hh",
    "addr:street":"Regent Street",
    "iso:country":"GB",
    "sg:address":"Suite 401, 302-308 Regent Street",
    "sg:city":"London",
    "sg:classifiers":[
        {
            "category":"Retail",
            "subcategory":"Repair Shop",
            "type":"Services"
        }
    ],
    "sg:phone":"+44 20 7580 4242",
    "sg:postcode":"W1B 3HH",
    "sg:province":"Greater London",
    "sg:tags":[
        "upholsterer"
    ],
    "wof:name":"Prince Regent Upholstery & Soft Furnishings",
    "wof:placetype":"venue"
},
  "geometry": {"coordinates":[-0.142385,51.516544],"type":"Point"}
}