{
  "type": "Feature",
  "properties": {
    "iso:country":"GB",
    "sg:address":"43 Market St",
    "sg:city":"Ashby-de-la-zouch",
    "sg:classifiers":[
        {
            "category":"Personal",
            "subcategory":"Barber",
            "type":"Services"
        }
    ],
    "sg:postcode":"LE65 1AG",
    "sg:province":"Derbyshire",
    "sg:tags":[
        "men's",
        "hairdresser"
    ],
    "wof:name":"Barry,Sarah,",
    "wof:placetype":"venue"
},
  "geometry": {"coordinates":[-1.473344,52.746651],"type":"Point"}
}