{
  "type": "Feature",
  "properties": {
    "addr:full":"41 Main Street, Balmullo St Andrews Fife KY16 0AE",
    "addr:housenumber":"41",
    "addr:postcode":"ky16 0ae",
    "addr:street":"Main Street Balmullo;Andrews",
    "iso:country":"GB",
    "sg:address":"41 Main Street, Balmullo",
    "sg:city":"St Andrews",
    "sg:classifiers":[
        {
            "category":"Personal",
            "subcategory":"Barber",
            "type":"Services"
        },
        {
            "category":"Sports & Exercise",
            "subcategory":"Gym",
            "type":"Entertainment"
        }
    ],
    "sg:phone":"+44 1334 870871",
    "sg:postcode":"KY16 0AE",
    "sg:province":"Fife",
    "sg:tags":[
        "unisex",
        "centre",
        "health",
        "fitness",
        "hairdresser"
    ],
    "wof:name":"The Highlite Tone",
    "wof:placetype":"venue"
},
  "geometry": {"coordinates":[-2.89113307,56.3608627319],"type":"Point"}
}