{
  "type": "Feature",
  "properties": {
    "iso:country":"GB",
    "sg:address":"413 Lainshaw Drive",
    "sg:city":"Glasgow",
    "sg:classifiers":[
        {
            "category":"Retail",
            "subcategory":"Funeral Services",
            "type":"Services"
        }
    ],
    "sg:phone":"+44 141 634 2121",
    "sg:postcode":"G45 9SP",
    "sg:province":"Glasgow City",
    "sg:tags":[
        "cemetery",
        "crematorium"
    ],
    "wof:name":"Linn Crematorium",
    "wof:placetype":"venue"
},
  "geometry": {"coordinates":[-4.246579,55.801723],"type":"Point"}
}