{
  "type": "Feature",
  "properties": {
    "iso:country":"GB",
    "sg:address":"Danford, Claverley",
    "sg:city":"Wolverhampton",
    "sg:classifiers":[
        {
            "category":"Bars & Pubs",
            "type":"Food & Drink"
        }
    ],
    "sg:phone":"+44 1746 710553",
    "sg:postcode":"WV5 7DG",
    "sg:province":"Shropshire",
    "sg:tags":[
        "pubs",
        "inn"
    ],
    "wof:name":"Woodman Inn",
    "wof:placetype":"venue"
},
  "geometry": {"coordinates":[-2.3031229973,52.5373039246],"type":"Point"}
}