{
  "type": "Feature",
  "properties": {
    "iso:country":"GB",
    "sg:address":"69 Monifieth Road, Broughty Ferry",
    "sg:city":"Dundee",
    "sg:classifiers":[
        {
            "category":"Travel",
            "subcategory":"Hotels & Motels",
            "type":"Entertainment"
        }
    ],
    "sg:phone":"+44 1382 737812",
    "sg:postcode":"DD5 2RW",
    "sg:province":"Angus",
    "sg:tags":[
        "house",
        "guest"
    ],
    "wof:name":"STONELEE GUEST HOUSE",
    "wof:placetype":"venue"
},
  "geometry": {"coordinates":[-2.863956,56.468536],"type":"Point"}
}