{
  "type": "Feature",
  "properties": {
    "addr:full":"82 Myddleton Rd Wood Green Greater London N22 8NQ",
    "addr:housenumber":"82",
    "addr:postcode":"n22 8nq",
    "addr:street":"Myddleton Rd",
    "iso:country":"GB",
    "sg:address":"82 Myddleton Rd",
    "sg:city":"Wood Green",
    "sg:classifiers":[
        {
            "category":"Retail",
            "subcategory":"Driving School",
            "type":"Services"
        }
    ],
    "sg:phone":"+44 20 8889 3274",
    "sg:postcode":"N22 8NQ",
    "sg:province":"Greater London",
    "wof:name":"Easy Learning Centre",
    "wof:placetype":"venue"
},
  "geometry": {"coordinates":[-0.1175059974,51.6065635681],"type":"Point"}
}