{
  "type": "Feature",
  "properties": {
    "iso:country":"GB",
    "sg:address":"17 The Triangle",
    "sg:city":"Bournemouth",
    "sg:classifiers":[
        {
            "category":"Organizations",
            "subcategory":"Membership Organization",
            "type":"Services"
        }
    ],
    "sg:postcode":"BH2 5RY",
    "sg:province":"Dorset",
    "sg:tags":[
        "club"
    ],
    "wof:name":"Bournemouth Central Club",
    "wof:placetype":"venue"
},
  "geometry": {"coordinates":[-1.885599,50.720718],"type":"Point"}
}