{
  "type": "Feature",
  "properties": {
    "addr:full":"10 Biggar Road Edinburgh City of Edinburgh EH10 7BQ",
    "addr:housenumber":"10",
    "addr:postcode":"eh10 7bq",
    "addr:street":"Biggar Road",
    "iso:country":"GB",
    "sg:address":"10 Biggar Road",
    "sg:city":"Edinburgh",
    "sg:classifiers":[
        {
            "category":"Health Services",
            "subcategory":"Health Practitioner",
            "type":"Services"
        }
    ],
    "sg:phone":"+44 131 445 2485",
    "sg:postcode":"EH10 7BQ",
    "sg:province":"City of Edinburgh",
    "sg:tags":[
        "hypnotherapists"
    ],
    "wof:name":"Robin W Thorburn",
    "wof:placetype":"venue"
},
  "geometry": {"coordinates":[-3.2045769691,55.9008636475],"type":"Point"}
}