{
  "type": "Feature",
  "properties": {
    "iso:country":"GB",
    "sg:address":"Old Rectory, Hope-under-dinmore",
    "sg:city":"Leominster",
    "sg:classifiers":[
        {
            "category":"Social Services",
            "subcategory":"Child Care",
            "type":"Services"
        }
    ],
    "sg:phone":"+44 1568 616322",
    "sg:postcode":"HR6 0PW",
    "sg:province":"Herefordshire",
    "sg:tags":[
        "children's",
        "home"
    ],
    "wof:name":"Solutions (Ross) Ltd.",
    "wof:placetype":"venue"
},
  "geometry": {"coordinates":[-2.7193489075,52.1684532166],"type":"Point"}
}