{
  "type": "Feature",
  "properties": {
    "addr:full":"2 Holbeck, Astley Manchester Greater Manchester M29 7DU",
    "addr:housenumber":"2",
    "addr:postcode":"m29 7du",
    "addr:street":"Holbeck",
    "iso:country":"GB",
    "sg:address":"2 Holbeck, Astley",
    "sg:city":"Manchester",
    "sg:classifiers":[
        {
            "category":"Health Services",
            "subcategory":"Podiatrist",
            "type":"Services"
        }
    ],
    "sg:postcode":"M29 7DU",
    "sg:province":"Greater Manchester",
    "sg:tags":[
        "podiatrists",
        "chiropodist"
    ],
    "wof:name":"P McDonnell",
    "wof:placetype":"venue"
},
  "geometry": {"coordinates":[-2.4586939812,53.4983901978],"type":"Point"}
}