{
  "type": "Feature",
  "properties": {
    "addr:full":"41a Kingsland Road, West Mersey Colchester Essex CO5 8RA",
    "addr:housenumber":"41a",
    "addr:postcode":"co5 8ra",
    "addr:street":"Kingsland Road West Mersey Colchester",
    "iso:country":"GB",
    "sg:address":"41a Kingsland Road, West Mersey",
    "sg:city":"Colchester",
    "sg:classifiers":[
        {
            "category":"Autos & Motor Vehicles",
            "subcategory":"Fuel & Gas Station",
            "type":"Retail Goods"
        }
    ],
    "sg:phone":"+44 1206 382840",
    "sg:postcode":"CO5 8RA",
    "sg:province":"Essex",
    "sg:tags":[
        "petrol",
        "filling"
    ],
    "wof:name":"B J & M Underwood",
    "wof:placetype":"venue"
},
  "geometry": {"coordinates":[0.9196709991,51.7779846191],"type":"Point"}
}