{
  "type": "Feature",
  "properties": {
    "addr:full":"44 Tower Bridge Rd Southwark Greater London SE1 4TR",
    "addr:housenumber":"44",
    "addr:postcode":"se1 4tr",
    "addr:street":"Tower Bridge Rd",
    "iso:country":"GB",
    "sg:address":"44 Tower Bridge Rd",
    "sg:city":"Southwark",
    "sg:classifiers":[
        {
            "category":"Retail",
            "subcategory":"Laundry & Dry Cleaning",
            "type":"Services"
        }
    ],
    "sg:phone":"+44 20 7231 7583",
    "sg:postcode":"SE1 4TR",
    "sg:province":"Greater London",
    "sg:tags":[
        "launderette"
    ],
    "wof:name":"Launderette",
    "wof:placetype":"venue"
},
  "geometry": {"coordinates":[-0.08296,51.495861],"type":"Point"}
}