{
  "type": "Feature",
  "properties": {
    "addr:full":"8 Ferry Rd Southampton Hampshire SO45 5GD",
    "addr:housenumber":"8",
    "addr:postcode":"so45 5gd",
    "addr:street":"Ferry Rd",
    "iso:country":"GB",
    "sg:address":"8 Ferry Rd",
    "sg:city":"Southampton",
    "sg:classifiers":[
        {
            "category":"Fast Food",
            "type":"Food & Drink"
        }
    ],
    "sg:phone":"+44 23 8084 3482",
    "sg:postcode":"SO45 5GD",
    "sg:province":"Hampshire",
    "sg:tags":[
        "away",
        "meal",
        "outlet",
        "take"
    ],
    "wof:name":"The Modern",
    "wof:placetype":"venue"
},
  "geometry": {"coordinates":[-1.405385,50.865379],"type":"Point"}
}