{
  "type": "Feature",
  "properties": {
    "iso:country":"GB",
    "sg:address":"Newland Rd",
    "sg:city":"Worthing",
    "sg:classifiers":[
        {
            "category":"Farming",
            "subcategory":"Nursery",
            "type":"Manufacturing & Wholesale Goods"
        }
    ],
    "sg:phone":"+44 1903 215789",
    "sg:postcode":"BN11 1LB",
    "sg:province":"West Sussex",
    "sg:tags":[
        "creche"
    ],
    "wof:name":"Ardmore Nursery School",
    "wof:placetype":"venue"
},
  "geometry": {"coordinates":[-0.367268,50.818581],"type":"Point"}
}