{
  "type": "Feature",
  "properties": {
    "iso:country":"GB",
    "sg:address":"820 Bath Road, Cranford",
    "sg:city":"Hounslow",
    "sg:classifiers":[
        {
            "category":"Autos & Motor Vehicles",
            "subcategory":"Motorcycle Sales",
            "type":"Retail Goods"
        }
    ],
    "sg:postcode":"TW5 9UH",
    "sg:province":"Greater London",
    "sg:tags":[
        "chauffeur",
        "driven",
        "car"
    ],
    "wof:name":"Crest Cars",
    "wof:placetype":"venue"
},
  "geometry": {"coordinates":[-0.41307,51.480133],"type":"Point"}
}