{
  "type": "Feature",
  "properties": {
    "iso:country":"GB",
    "sg:address":"70 Hatch La, Old Basing",
    "sg:city":"Basingstoke",
    "sg:classifiers":[
        {
            "category":"Building & Trades",
            "subcategory":"Construction",
            "type":"Services"
        }
    ],
    "sg:postcode":"RG24 7EB",
    "sg:province":"Hampshire",
    "sg:tags":[
        "joiner",
        "carpenter"
    ],
    "wof:name":"Garrod,David,",
    "wof:placetype":"venue"
},
  "geometry": {"coordinates":[-1.039027,51.266579],"type":"Point"}
}