{
  "type": "Feature",
  "properties": {
    "addr:full":"15 St Catherines Road Evesham Gloucestershire WR11 2GE",
    "addr:housenumber":"15",
    "addr:postcode":"wr11 2ge",
    "addr:street":"St Catherines Road",
    "iso:country":"GB",
    "sg:address":"15 St Catherines Road",
    "sg:city":"Evesham",
    "sg:classifiers":[
        {
            "category":"Professional",
            "subcategory":"Engineering",
            "type":"Services"
        }
    ],
    "sg:postcode":"WR11 2GE",
    "sg:province":"Gloucestershire",
    "sg:tags":[
        "contractor",
        "electrical",
        "engineer"
    ],
    "wof:name":"Grinlec Electrical Contractors",
    "wof:placetype":"venue"
},
  "geometry": {"coordinates":[-1.9458990097,52.079082489],"type":"Point"}
}