{
  "type": "Feature",
  "properties": {
    "addr:full":"10 Upminster Road South Rainham Essex RM13 9YX",
    "addr:housenumber":"10",
    "addr:postcode":"rm13 9yx",
    "addr:street":"Upminster Road South",
    "iso:country":"GB",
    "sg:address":"10 Upminster Road South",
    "sg:city":"Rainham",
    "sg:classifiers":[
        {
            "category":"Fast Food",
            "type":"Food & Drink"
        }
    ],
    "sg:phone":"+44 1708 550011",
    "sg:postcode":"RM13 9YX",
    "sg:province":"Essex",
    "sg:tags":[
        "away",
        "take"
    ],
    "wof:name":"Kebab Village House",
    "wof:placetype":"venue"
},
  "geometry": {"coordinates":[0.191136,51.518284],"type":"Point"}
}