{
  "type": "Feature",
  "properties": {
    "addr:full":"145-149 London Road Croydon Surrey CR0 2RG",
    "addr:housenumber":"145-149",
    "addr:postcode":"cr0 2rg",
    "addr:street":"London Road",
    "iso:country":"GB",
    "sg:address":"145-149 London Road",
    "sg:city":"Croydon",
    "sg:classifiers":[
        {
            "category":"Autos & Motor Vehicles",
            "subcategory":"Auto Supplies",
            "type":"Retail Goods"
        }
    ],
    "sg:phone":"+44 20 8686 0721",
    "sg:postcode":"CR0 2RG",
    "sg:province":"Surrey",
    "sg:tags":[
        "tyre"
    ],
    "wof:name":"S M C",
    "wof:placetype":"venue"
},
  "geometry": {"coordinates":[-0.1055940017,51.3811683655],"type":"Point"}
}