{
  "type": "Feature",
  "properties": {
    "addr:full":"Cramond House, Henley Rd Marlow Berkshire SL7 2BZ",
    "addr:postcode":"sl7 2bz",
    "addr:street":"Henley Rd",
    "iso:country":"GB",
    "sg:address":"Cramond House, Henley Rd",
    "sg:city":"Marlow",
    "sg:classifiers":[
        {
            "category":"Professional",
            "subcategory":"Management & Consulting",
            "type":"Services"
        }
    ],
    "sg:phone":"+44 1628 483760",
    "sg:postcode":"SL7 2BZ",
    "sg:province":"Berkshire",
    "sg:tags":[
        "consultant",
        "business"
    ],
    "wof:name":"Archer Mathieson",
    "wof:placetype":"venue"
},
  "geometry": {"coordinates":[-0.786666,51.56802],"type":"Point"}
}