{
  "type": "Feature",
  "properties": {
    "iso:country":"GB",
    "sg:address":"Fourriggs",
    "sg:city":"Darlington",
    "sg:classifiers":[
        {
            "category":"Professional",
            "type":"Services"
        }
    ],
    "sg:postcode":"DL3 6TL",
    "sg:province":"Durham",
    "sg:tags":[
        "auctioneer"
    ],
    "wof:name":"Hunt Bros",
    "wof:placetype":"venue"
},
  "geometry": {"coordinates":[-1.557970047,54.5278015137],"type":"Point"}
}