{
  "type": "Feature",
  "properties": {
    "addr:full":"Brewer St Farm, Brewer Street, Bletchingley Redhill Surrey RH1 4QP",
    "addr:postcode":"rh1 4qp",
    "addr:street":"Brewer St;Brewer Street;Redhill",
    "iso:country":"GB",
    "sg:address":"Brewer St Farm, Brewer Street, Bletchingley",
    "sg:city":"Redhill",
    "sg:classifiers":[
        {
            "category":"Manufacturing",
            "subcategory":"Petroleum Products",
            "type":"Manufacturing & Wholesale Goods"
        },
        {
            "category":"Building & Trades",
            "subcategory":"Construction",
            "type":"Services"
        }
    ],
    "sg:phone":"+44 1883 744149",
    "sg:postcode":"RH1 4QP",
    "sg:province":"Surrey",
    "sg:tags":[
        "double",
        "glazier",
        "glazing"
    ],
    "wof:name":"Pro Glass & Glazing Co",
    "wof:placetype":"venue"
},
  "geometry": {"coordinates":[-0.1046880037,51.2501296997],"type":"Point"}
}