{
  "type": "Feature",
  "properties": {
    "iso:country":"GB",
    "sg:address":"26 Charles Business Park, Cinder Hill Road Bulwell",
    "sg:city":"Nottingham",
    "sg:classifiers":[
        {
            "category":"Shopping",
            "subcategory":"Stationery & Office Supplies",
            "type":"Retail Goods"
        }
    ],
    "sg:phone":"+44 115 927 0280",
    "sg:postcode":"NG6 8RE",
    "sg:province":"Nottinghamshire",
    "sg:tags":[
        "equipment"
    ],
    "wof:name":"Ricoh U K Ltd.",
    "wof:placetype":"venue"
},
  "geometry": {"coordinates":[-1.1981639862,53.0011940002],"type":"Point"}
}