{
  "type": "Feature",
  "properties": {
    "addr:full":"Fff 17 Southern Road, Southbourne Bournemouth Dorset BH6 3SR",
    "addr:housenumber":"17",
    "addr:postcode":"bh6 3sr",
    "addr:street":"Fff;Southern Road",
    "iso:country":"GB",
    "sg:address":"Fff 17 Southern Road, Southbourne",
    "sg:city":"Bournemouth",
    "sg:classifiers":[
        {
            "category":"Professional",
            "subcategory":"Computer Services",
            "type":"Services"
        }
    ],
    "sg:postcode":"BH6 3SR",
    "sg:province":"Dorset",
    "sg:tags":[
        "system",
        "software"
    ],
    "wof:name":"Ledrange Projects Ltd",
    "wof:placetype":"venue"
},
  "geometry": {"coordinates":[-1.8164999485,50.7241592407],"type":"Point"}
}