{
  "type": "Feature",
  "properties": {
    "addr:full":"10 Glebe Close, Burton Upon Stather Scunthorpe Lincolnshire DN15 9BZ",
    "addr:housenumber":"10",
    "addr:postcode":"stather;dn15 9bz",
    "addr:street":"Glebe Close",
    "iso:country":"GB",
    "sg:address":"10 Glebe Close, Burton Upon Stather",
    "sg:city":"Scunthorpe",
    "sg:classifiers":[
        {
            "category":"Organizations",
            "subcategory":"Non-profit Organization",
            "type":"Services"
        }
    ],
    "sg:phone":"+44 1724 720389",
    "sg:postcode":"DN15 9BZ",
    "sg:province":"Lincolnshire",
    "sg:tags":[
        "organisation",
        "voluntary",
        "charity"
    ],
    "wof:name":"S S A F A Forces Help",
    "wof:placetype":"venue"
},
  "geometry": {"coordinates":[-0.6850600243,53.6514282227],"type":"Point"}
}