{
  "type": "Feature",
  "properties": {
    "iso:country":"GB",
    "sg:address":"32 Hawbank Road, College Milton North, East Kilbride",
    "sg:city":"Glasgow",
    "sg:classifiers":[
        {
            "category":"Utilities",
            "subcategory":"Telephone",
            "type":"Services"
        },
        {
            "category":"Communications",
            "type":"Services"
        }
    ],
    "sg:phone":"+44 1355 841000",
    "sg:postcode":"G74 5EX",
    "sg:province":"South Lanarkshire",
    "sg:tags":[
        "telecommunication"
    ],
    "wof:name":"Azzurri Scotland Ltd.",
    "wof:placetype":"venue"
},
  "geometry": {"coordinates":[-4.212384,55.772938],"type":"Point"}
}