{
  "type": "Feature",
  "properties": {
    "addr:full":"83 St Clair Street Kirkcaldy Fife KY1 2NW",
    "addr:housenumber":"83",
    "addr:postcode":"ky1 2nw",
    "addr:street":"St Clair Street",
    "iso:country":"GB",
    "sg:address":"83 St Clair Street",
    "sg:city":"Kirkcaldy",
    "sg:classifiers":[
        {
            "category":"Building & Trades",
            "subcategory":"Cleaning & Sanitation",
            "type":"Services"
        }
    ],
    "sg:postcode":"KY1 2NW",
    "sg:province":"Fife",
    "sg:tags":[
        "cleaner",
        "window"
    ],
    "wof:name":"T Moffat & Sons",
    "wof:placetype":"venue"
},
  "geometry": {"coordinates":[-3.141738,56.124561],"type":"Point"}
}