{
  "type": "Feature",
  "properties": {
    "addr:full":"Rear Of 71a Great Bridge Tipton West Midlands DY4 0HF",
    "addr:housenumber":"rear of 71a",
    "addr:postcode":"dy4 0hf",
    "iso:country":"GB",
    "sg:address":"Rear Of 71a Great Bridge",
    "sg:city":"Tipton",
    "sg:classifiers":[
        {
            "category":"Manufacturing",
            "subcategory":"Buildings",
            "type":"Manufacturing & Wholesale Goods"
        }
    ],
    "sg:phone":"+44 121 520 0009",
    "sg:postcode":"DY4 0HF",
    "sg:province":"West Midlands",
    "sg:tags":[
        "sectional"
    ],
    "wof:name":"Great Bridge Sheds & Fencing",
    "wof:placetype":"venue"
},
  "geometry": {"coordinates":[-2.0706970692,52.528137207],"type":"Point"}
}