{
  "type": "Feature",
  "properties": {
    "addr:full":"49 Croft End Rd, Chipperfield Kings Langley Hertfordshire WD4 9DZ",
    "addr:housenumber":"49",
    "addr:postcode":"wd4 9dz",
    "addr:street":"Croft End Rd",
    "iso:country":"GB",
    "sg:address":"49 Croft End Rd, Chipperfield",
    "sg:city":"Kings Langley",
    "sg:classifiers":[
        {
            "category":"Building & Trades",
            "subcategory":"Construction",
            "type":"Services"
        }
    ],
    "sg:phone":"+44 1923 270574",
    "sg:postcode":"WD4 9DZ",
    "sg:province":"Hertfordshire",
    "sg:tags":[
        "builder"
    ],
    "wof:name":"Atkins Roofing",
    "wof:placetype":"venue"
},
  "geometry": {"coordinates":[-0.4901579916,51.7083244324],"type":"Point"}
}