{
  "type": "Feature",
  "properties": {
    "addr:full":"Park Rd Stroud Gloucestershire GL6 0HY",
    "addr:postcode":"gl6 0hy",
    "addr:street":"Park Rd",
    "iso:country":"GB",
    "sg:address":"Park Rd",
    "sg:city":"Stroud",
    "sg:classifiers":[
        {
            "category":"Social Services",
            "subcategory":"Adult Care",
            "type":"Services"
        },
        {
            "category":"Social Services",
            "subcategory":"Retirement Home",
            "type":"Services"
        }
    ],
    "sg:phone":"+44 1453 832603",
    "sg:postcode":"GL6 0HY",
    "sg:province":"Gloucestershire",
    "sg:tags":[
        "housing",
        "sheltered",
        "accommodation"
    ],
    "wof:name":"Ringfield Close",
    "wof:placetype":"venue"
},
  "geometry": {"coordinates":[-2.215996,51.692497],"type":"Point"}
}