{
  "type": "Feature",
  "properties": {
    "addr:full":"Windsor Way, Kingston Park Newcastle Upon Tyne Tyne and Wear NE3 2SZ",
    "addr:postcode":"ne3 2sz",
    "addr:street":"Windsor Way;Park",
    "iso:country":"GB",
    "sg:address":"Windsor Way, Kingston Park",
    "sg:city":"Newcastle Upon Tyne",
    "sg:classifiers":[
        {
            "category":"Bars & Pubs",
            "type":"Food & Drink"
        }
    ],
    "sg:phone":"+44 191 286 1076",
    "sg:postcode":"NE3 2SZ",
    "sg:province":"Tyne and Wear",
    "sg:tags":[
        "pubs",
        "inn"
    ],
    "wof:name":"The Windsor",
    "wof:placetype":"venue"
},
  "geometry": {"coordinates":[-1.657564044,55.0202293396],"type":"Point"}
}