{
  "type": "Feature",
  "properties": {
    "addr:full":"19 Ribblesdale Avenue Hinckley Leicestershire LE10 1SY",
    "addr:housenumber":"19",
    "addr:postcode":"le10 1sy",
    "addr:street":"Ribblesdale Avenue",
    "iso:country":"GB",
    "sg:address":"19 Ribblesdale Avenue",
    "sg:city":"Hinckley",
    "sg:classifiers":[
        {
            "category":"Education",
            "subcategory":"Dance Studio",
            "type":"Public Place"
        }
    ],
    "sg:phone":"+44 1455 637646",
    "sg:postcode":"LE10 1SY",
    "sg:province":"Leicestershire",
    "sg:tags":[
        "school",
        "dancing"
    ],
    "wof:name":"Leo & Annabelle",
    "wof:placetype":"venue"
},
  "geometry": {"coordinates":[-1.3598250151,52.5525588989],"type":"Point"}
}