{
  "type": "Feature",
  "properties": {
    "iso:country":"GB",
    "sg:address":"19 Church Street",
    "sg:city":"Whitehaven",
    "sg:classifiers":[
        {
            "category":"Personal",
            "type":"Services"
        }
    ],
    "sg:postcode":"CA28 7AY",
    "sg:province":"Cumbria",
    "sg:tags":[
        "tailor"
    ],
    "wof:name":"Risino Bros",
    "wof:placetype":"venue"
},
  "geometry": {"coordinates":[-3.588274,54.548244],"type":"Point"}
}