{
  "type": "Feature",
  "properties": {
    "addr:full":"Pengarth Helston Cornwall TR12 7HB",
    "addr:postcode":"tr12 7hb",
    "addr:street":"Pengarth",
    "iso:country":"GB",
    "sg:address":"Pengarth",
    "sg:city":"Helston",
    "sg:classifiers":[
        {
            "category":"Organizations",
            "subcategory":"Religious Organization",
            "type":"Services"
        }
    ],
    "sg:phone":"+44 1326 240174",
    "sg:postcode":"TR12 7HB",
    "sg:province":"Cornwall",
    "sg:tags":[
        "organisation"
    ],
    "wof:name":"Quakers Religious Society Of Friends",
    "wof:placetype":"venue"
},
  "geometry": {"coordinates":[-5.211989,50.016102],"type":"Point"}
}