{
  "type": "Feature",
  "properties": {
    "addr:full":"133 Station Road Sidcup Kent DA15 7AA",
    "addr:housenumber":"133",
    "addr:postcode":"da15 7aa",
    "addr:street":"Station Road",
    "iso:country":"GB",
    "sg:address":"133 Station Road",
    "sg:city":"Sidcup",
    "sg:classifiers":[
        {
            "category":"Real Estate",
            "subcategory":"Surveying",
            "type":"Services"
        }
    ],
    "sg:phone":"+44 20 8300 1144",
    "sg:postcode":"DA15 7AA",
    "sg:province":"Kent",
    "sg:tags":[
        "surveyor",
        "valuer"
    ],
    "wof:name":"Maitlands Chartered Surveyors",
    "wof:placetype":"venue"
},
  "geometry": {"coordinates":[0.102069,51.434868],"type":"Point"}
}