{
  "type": "Feature",
  "properties": {
    "addr:full":"9 George Square Greenock Inverclyde PA15 1QP",
    "addr:housenumber":"9",
    "addr:postcode":"pa15 1qp",
    "addr:street":"George Square Greenock",
    "iso:country":"GB",
    "sg:address":"9 George Square",
    "sg:city":"Greenock",
    "sg:classifiers":[
        {
            "category":"Professional",
            "subcategory":"Lawyer & Legal Services",
            "type":"Services"
        }
    ],
    "sg:phone":"+44 1475 787888",
    "sg:postcode":"PA15 1QP",
    "sg:province":"Inverclyde",
    "sg:tags":[
        "solicitor"
    ],
    "wof:name":"Lyons Laing & Co.",
    "wof:placetype":"venue"
},
  "geometry": {"coordinates":[-4.75711,55.948437],"type":"Point"}
}