{
  "type": "Feature",
  "properties": {
    "iso:country":"GB",
    "sg:address":"Merridale Primary School, Kitchen, Aspen Way",
    "sg:city":"Wolverhampton",
    "sg:classifiers":[
        {
            "category":"Government",
            "subcategory":"Office",
            "type":"Public Place"
        }
    ],
    "sg:phone":"+44 1902 424675",
    "sg:postcode":"WV3 0UP",
    "sg:province":"Staffordshire",
    "sg:tags":[
        "local"
    ],
    "wof:name":"Wolverhampton Borough Council",
    "wof:placetype":"venue"
},
  "geometry": {"coordinates":[-2.14706,52.581249],"type":"Point"}
}