{
  "type": "Feature",
  "properties": {
    "iso:country":"GB",
    "sg:address":"Broadgate, Broadway Business Park",
    "sg:city":"Oldham",
    "sg:classifiers":[
        {
            "category":"Shopping",
            "subcategory":"Crafts & Fabrics",
            "type":"Retail Goods"
        }
    ],
    "sg:phone":"+44 161 681 9191",
    "sg:postcode":"OL9 9XA",
    "sg:province":"Lancashire",
    "sg:tags":[
        "shop"
    ],
    "wof:name":"S Frankenhuis & Son Ltd.",
    "wof:placetype":"venue"
},
  "geometry": {"coordinates":[-2.1663899422,53.5298576355],"type":"Point"}
}