{
  "type": "Feature",
  "properties": {
    "iso:country":"GB",
    "sg:address":"16 Watson Place, St Judes",
    "sg:city":"Plymouth",
    "sg:classifiers":[
        {
            "category":"Professional",
            "subcategory":"Engineering",
            "type":"Services"
        }
    ],
    "sg:phone":"+44 1752 222133",
    "sg:postcode":"PL4 9QN",
    "sg:province":"Devon",
    "sg:tags":[
        "contractor",
        "electrical",
        "engineer"
    ],
    "wof:name":"Wright & Owen",
    "wof:placetype":"venue"
},
  "geometry": {"coordinates":[-4.1247439384,50.3712921143],"type":"Point"}
}