{
  "type": "Feature",
  "properties": {
    "iso:country":"GB",
    "sg:address":"98 Hornchurch Road",
    "sg:city":"Hornchurch",
    "sg:classifiers":[
        {
            "category":"Professional",
            "subcategory":"Accounting & Tax Preparation",
            "type":"Services"
        }
    ],
    "sg:phone":"+44 1708 457941",
    "sg:postcode":"RM11 1JS",
    "sg:province":"Essex",
    "sg:tags":[
        "accountant"
    ],
    "wof:name":"Farra Wilkins & Gould",
    "wof:placetype":"venue"
},
  "geometry": {"coordinates":[0.2071419954,51.5638313293],"type":"Point"}
}