{
  "type": "Feature",
  "properties": {
    "addr:full":"Unit 3f D'arcy Business Centre, D'arcy B, Llandarcy Neath Neath Port Talbot SA10 6EJ",
    "addr:housenumber":"unit 3f;b llandarcy",
    "addr:postcode":"sa10 6ej",
    "addr:street":"D'Arcy Business Centre D'Arcy",
    "iso:country":"GB",
    "sg:address":"Unit 3f D'arcy Business Centre, D'arcy B, Llandarcy",
    "sg:city":"Neath",
    "sg:classifiers":[
        {
            "category":"Personal",
            "subcategory":"Tanning Parlor",
            "type":"Services"
        }
    ],
    "sg:phone":"+44 1792 321828",
    "sg:postcode":"SA10 6EJ",
    "sg:province":"Neath Port Talbot",
    "sg:tags":[
        "laser"
    ],
    "wof:name":"Millennium Lasers Ltd",
    "wof:placetype":"venue"
},
  "geometry": {"coordinates":[-3.85213,51.647869],"type":"Point"}
}