{
  "type": "Feature",
  "properties": {
    "addr:full":"528 Finchley Rd Golders Green Greater London NW11 8DD",
    "addr:housenumber":"528",
    "addr:postcode":"nw11 8dd",
    "addr:street":"Finchley Rd",
    "iso:country":"GB",
    "sg:address":"528 Finchley Rd",
    "sg:city":"Golders Green",
    "sg:classifiers":[
        {
            "category":"Shopping",
            "subcategory":"Pharmacy",
            "type":"Retail Goods"
        }
    ],
    "sg:phone":"+44 20 8731 8642",
    "sg:postcode":"NW11 8DD",
    "sg:province":"Greater London",
    "sg:tags":[
        "medicine",
        "therapy"
    ],
    "wof:name":"Dr Maureen Gledhill M.B.Ch.B M.R.C.Psych. D.C.H.",
    "wof:placetype":"venue"
},
  "geometry": {"coordinates":[-0.1953089982,51.5667190552],"type":"Point"}
}