{
  "type": "Feature",
  "properties": {
    "addr:full":"Hinkins Close, Melbourn Royston Bedfordshire SG8 6JL",
    "addr:postcode":"sg8 6jl",
    "addr:street":"Hinkins Close",
    "iso:country":"GB",
    "sg:address":"Hinkins Close, Melbourn",
    "sg:city":"Royston",
    "sg:classifiers":[
        {
            "category":"Social Services",
            "subcategory":"Retirement Home",
            "type":"Services"
        }
    ],
    "sg:phone":"+44 1763 262121",
    "sg:postcode":"SG8 6JL",
    "sg:province":"Bedfordshire",
    "sg:tags":[
        "residential",
        "care"
    ],
    "wof:name":"Southwell Court",
    "wof:placetype":"venue"
},
  "geometry": {"coordinates":[0.026469,52.083382],"type":"Point"}
}