{
  "type": "Feature",
  "properties": {
    "iso:country":"GB",
    "sg:address":"216 Marsh Hill",
    "sg:city":"Birmingham",
    "sg:classifiers":[
        {
            "category":"Government",
            "subcategory":"Post Office",
            "type":"Public Place"
        }
    ],
    "sg:phone":"+44 121 373 1829",
    "sg:postcode":"B23 7HE",
    "sg:province":"West Midlands",
    "wof:name":"Marsh Hill Post Office",
    "wof:placetype":"venue"
},
  "geometry": {"coordinates":[-1.8691129684,52.5245094299],"type":"Point"}
}