{
  "type": "Feature",
  "properties": {
    "addr:full":"Wakefield Road, Oulton Leeds West Yorkshire LS26 8EL",
    "addr:postcode":"ls26 8el",
    "addr:street":"Wakefield Road",
    "iso:country":"GB",
    "sg:address":"Wakefield Road, Oulton",
    "sg:city":"Leeds",
    "sg:classifiers":[
        {
            "category":"Community Center",
            "type":"Public Place"
        }
    ],
    "sg:phone":"+44 113 282 4110",
    "sg:postcode":"LS26 8EL",
    "sg:province":"West Yorkshire",
    "sg:tags":[
        "recreation",
        "leisure",
        "centre"
    ],
    "wof:name":"Rothwell Sports Centre",
    "wof:placetype":"venue"
},
  "geometry": {"coordinates":[-1.4530830383,53.7431106567],"type":"Point"}
}