{
  "type": "Feature",
  "properties": {
    "addr:full":"Church Street Cheltenham Gloucestershire GL50 3HA",
    "addr:postcode":"gl50 3ha",
    "addr:street":"Church Street",
    "iso:country":"GB",
    "sg:address":"Church Street",
    "sg:city":"Cheltenham",
    "sg:classifiers":[
        {
            "category":"Bars & Pubs",
            "type":"Food & Drink"
        }
    ],
    "sg:phone":"+44 1242 224844",
    "sg:postcode":"GL50 3HA",
    "sg:province":"Gloucestershire",
    "sg:tags":[
        "pubs",
        "inn"
    ],
    "wof:name":"The Two Pigs",
    "wof:placetype":"venue"
},
  "geometry": {"coordinates":[-2.07611,51.901169],"type":"Point"}
}