{
  "type": "Feature",
  "properties": {
    "addr:full":"Barnes House, 9-15 Camden Road London Greater London NW1 9LQ",
    "addr:housenumber":"9-15",
    "addr:postcode":"nw1 9lq",
    "addr:street":"Barnes;Camden Road",
    "iso:country":"GB",
    "sg:address":"Barnes House, 9-15 Camden Road",
    "sg:city":"London",
    "sg:classifiers":[
        {
            "category":"Professional",
            "subcategory":"Lawyer & Legal Services",
            "type":"Services"
        }
    ],
    "sg:phone":"+44 20 7911 0815",
    "sg:postcode":"NW1 9LQ",
    "sg:province":"Greater London",
    "sg:tags":[
        "advice",
        "counselling"
    ],
    "wof:name":"Melanie Davis Tranquilliser Project",
    "wof:placetype":"venue"
},
  "geometry": {"coordinates":[-0.1415520012,51.5399436951],"type":"Point"}
}