{
  "type": "Feature",
  "properties": {
    "addr:full":"3a St. Helens Rd Swansea Neath Port Talbot SA1 4AN",
    "addr:housenumber":"3a",
    "addr:postcode":"sa1 4an",
    "addr:street":"St. Helens Rd",
    "iso:country":"GB",
    "sg:address":"3a St. Helens Rd",
    "sg:city":"Swansea",
    "sg:classifiers":[
        {
            "category":"Fast Food",
            "type":"Food & Drink"
        }
    ],
    "sg:postcode":"SA1 4AN",
    "sg:province":"Neath Port Talbot",
    "sg:tags":[
        "away",
        "take"
    ],
    "wof:name":"Flannigans Steak House",
    "wof:placetype":"venue"
},
  "geometry": {"coordinates":[-3.950304,51.619114],"type":"Point"}
}