{
  "type": "Feature",
  "properties": {
    "iso:country":"GB",
    "sg:address":"3 Fox Road",
    "sg:city":"Street",
    "sg:classifiers":[
        {
            "category":"Retail",
            "subcategory":"Driving School",
            "type":"Services"
        }
    ],
    "sg:phone":"+44 1458 445003",
    "sg:postcode":"BA16 0PZ",
    "sg:province":"Somerset",
    "wof:name":"Tor School of Motoring",
    "wof:placetype":"venue"
},
  "geometry": {"coordinates":[-2.754068,51.122124],"type":"Point"}
}