{
  "type": "Feature",
  "properties": {
    "iso:country":"GB",
    "sg:address":"28 Dyers Court",
    "sg:city":"Kelso",
    "sg:classifiers":[
        {
            "category":"Communications",
            "subcategory":"News Services",
            "type":"Services"
        }
    ],
    "sg:phone":"+44 1573 224581",
    "sg:postcode":"TD5 7NQ",
    "sg:province":"Scottish Borders",
    "sg:tags":[
        "journalist"
    ],
    "wof:name":"John Dawson",
    "wof:placetype":"venue"
},
  "geometry": {"coordinates":[-2.43677,55.605862],"type":"Point"}
}