{
  "type": "Feature",
  "properties": {
    "addr:full":"397 Staines Road Feltham Greater London TW14 9HA",
    "addr:housenumber":"397",
    "addr:postcode":"tw14 9ha",
    "addr:street":"Staines Road",
    "iso:country":"GB",
    "sg:address":"397 Staines Road",
    "sg:city":"Feltham",
    "sg:classifiers":[
        {
            "category":"Professional",
            "subcategory":"Employment Agencies",
            "type":"Services"
        }
    ],
    "sg:phone":"+44 20 8893 2673",
    "sg:postcode":"TW14 9HA",
    "sg:province":"Greater London",
    "sg:tags":[
        "consultant",
        "recruitment"
    ],
    "wof:name":"Mackenzie Personnel Ltd",
    "wof:placetype":"venue"
},
  "geometry": {"coordinates":[-0.4235570133,51.4547195435],"type":"Point"}
}