{
  "type": "Feature",
  "properties": {
    "iso:country":"GB",
    "sg:address":"5 Spring Vale St, Tottington",
    "sg:city":"Bury",
    "sg:classifiers":[
        {
            "category":"Manufacturing",
            "subcategory":"Petroleum Products",
            "type":"Manufacturing & Wholesale Goods"
        }
    ],
    "sg:phone":"+44 1204 885005",
    "sg:postcode":"BL8 3LR",
    "sg:province":"Lancashire",
    "sg:tags":[
        "double",
        "glazing"
    ],
    "wof:name":"Independent Windows",
    "wof:placetype":"venue"
},
  "geometry": {"coordinates":[-2.340982,53.612225],"type":"Point"}
}