{
  "type": "Feature",
  "properties": {
    "iso:country":"GB",
    "sg:address":"414 Erith Rd",
    "sg:city":"Erith",
    "sg:classifiers":[
        {
            "category":"Building & Trades",
            "subcategory":"Construction",
            "type":"Services"
        }
    ],
    "sg:phone":"+44 1322 330046",
    "sg:postcode":"DA8 3NJ",
    "sg:province":"Kent",
    "sg:tags":[
        "builder"
    ],
    "wof:name":"J P W Building & Installation Ltd",
    "wof:placetype":"venue"
},
  "geometry": {"coordinates":[0.160323,51.470592],"type":"Point"}
}