{
  "type": "Feature",
  "properties": {
    "addr:full":"24 Claycliffe Av Barnsley South Yorkshire S75 1HJ",
    "addr:housenumber":"24",
    "addr:postcode":"s75 1hj",
    "addr:street":"Av Barnsley South",
    "iso:country":"GB",
    "sg:address":"24 Claycliffe Av",
    "sg:city":"Barnsley",
    "sg:classifiers":[
        {
            "category":"Professional",
            "subcategory":"Printing & Photocopies",
            "type":"Services"
        }
    ],
    "sg:phone":"+44 1226 771263",
    "sg:postcode":"S75 1HJ",
    "sg:province":"South Yorkshire",
    "sg:tags":[
        "printer"
    ],
    "wof:name":"Mason Print Services",
    "wof:placetype":"venue"
},
  "geometry": {"coordinates":[-1.5183720589,53.5655975342],"type":"Point"}
}