{
  "type": "Feature",
  "properties": {
    "addr:full":"Station Rd, Welham Grn Hatfield Hertfordshire AL9 7PJ",
    "addr:postcode":"al9 7pj",
    "addr:street":"Station Rd",
    "iso:country":"GB",
    "sg:address":"Station Rd, Welham Grn",
    "sg:city":"Hatfield",
    "sg:classifiers":[
        {
            "category":"Bus Charters",
            "type":"Transportation"
        }
    ],
    "sg:postcode":"AL9 7PJ",
    "sg:province":"Hertfordshire",
    "sg:tags":[
        "coach"
    ],
    "wof:name":"Davies,Alan,",
    "wof:placetype":"venue"
},
  "geometry": {"coordinates":[-0.205447,51.723984],"type":"Point"}
}