{
  "type": "Feature",
  "properties": {
    "addr:full":"23a Banbury Road Kidlington Buckinghamshire OX5 1AQ",
    "addr:housenumber":"23a",
    "addr:postcode":"ox5 1aq",
    "addr:street":"Banbury Road",
    "iso:country":"GB",
    "sg:address":"23a Banbury Road",
    "sg:city":"Kidlington",
    "sg:classifiers":[
        {
            "category":"Personal",
            "type":"Services"
        },
        {
            "category":"Shopping",
            "subcategory":"Bridal",
            "type":"Retail Goods"
        }
    ],
    "sg:postcode":"OX5 1AQ",
    "sg:province":"Buckinghamshire",
    "sg:tags":[
        "shop",
        "gown",
        "wedding"
    ],
    "wof:name":"C WARNER",
    "wof:placetype":"venue"
},
  "geometry": {"coordinates":[-1.292124033,51.8238563538],"type":"Point"}
}