{
  "type": "Feature",
  "properties": {
    "iso:country":"GB",
    "sg:address":"20-22 Bedford Row",
    "sg:city":"Bloomsbury",
    "sg:classifiers":[
        {
            "category":"Professional",
            "type":"Services"
        }
    ],
    "sg:postcode":"WC1R 4JS",
    "sg:province":"Greater London",
    "sg:tags":[
        "caterer"
    ],
    "wof:name":"Cumbia Ltd",
    "wof:placetype":"venue"
},
  "geometry": {"coordinates":[-0.116149,51.520439],"type":"Point"}
}