{
  "type": "Feature",
  "properties": {
    "addr:full":"1 Portways Farm Cottages, Cuckfield La Haywards Heath East Sussex RH17 5SN",
    "addr:housenumber":"1",
    "addr:postcode":"rh17 5sn",
    "addr:street":"Portways Farm Cottages;La Haywards",
    "iso:country":"GB",
    "sg:address":"1 Portways Farm Cottages, Cuckfield La",
    "sg:city":"Haywards Heath",
    "sg:classifiers":[
        {
            "category":"Recreation",
            "subcategory":"Dog Park",
            "type":"Entertainment"
        }
    ],
    "sg:phone":"+44 1444 461480",
    "sg:postcode":"RH17 5SN",
    "sg:province":"East Sussex",
    "wof:name":"Jan Taylor",
    "wof:placetype":"venue"
},
  "geometry": {"coordinates":[-0.1406289935,51.0108146667],"type":"Point"}
}