{
  "type": "Feature",
  "properties": {
    "addr:full":"56 Springfield Terrace, St Boswells Melrose Scottish Borders TD6 0ER",
    "addr:housenumber":"56",
    "addr:postcode":"td6 0er",
    "addr:street":"Springfield Terrace St",
    "iso:country":"GB",
    "sg:address":"56 Springfield Terrace, St Boswells",
    "sg:city":"Melrose",
    "sg:classifiers":[
        {
            "category":"Building & Trades",
            "subcategory":"Construction",
            "type":"Services"
        }
    ],
    "sg:phone":"+44 1835 823285",
    "sg:postcode":"TD6 0ER",
    "sg:province":"Scottish Borders",
    "sg:tags":[
        "joiner",
        "carpenter"
    ],
    "wof:name":"John F McDonald",
    "wof:placetype":"venue"
},
  "geometry": {"coordinates":[-2.6464970112,55.5683822632],"type":"Point"}
}