{
  "type": "Feature",
  "properties": {
    "iso:country":"GB",
    "sg:address":"Carr Wood Rd",
    "sg:city":"Castleford",
    "sg:classifiers":[
        {
            "category":"Home & Garden",
            "subcategory":"Building Materials",
            "type":"Retail Goods"
        }
    ],
    "sg:phone":"+44 1977 603932",
    "sg:postcode":"WF10 4SB",
    "sg:province":"West Yorkshire",
    "sg:tags":[
        "furnishers",
        "bathroom",
        "planner"
    ],
    "wof:name":"Cph Bathroom & Fireplace Centre",
    "wof:placetype":"venue"
},
  "geometry": {"coordinates":[-1.344208,53.721699],"type":"Point"}
}