{
  "type": "Feature",
  "properties": {
    "addr:full":"68 Sharps Lane Ruislip Greater London HA4 7JQ",
    "addr:housenumber":"68",
    "addr:postcode":"ha4 7jq",
    "addr:street":"Sharps Lane",
    "iso:country":"GB",
    "sg:address":"68 Sharps Lane",
    "sg:city":"Ruislip",
    "sg:classifiers":[
        {
            "category":"Retail",
            "subcategory":"Auto Repair",
            "type":"Services"
        }
    ],
    "sg:phone":"+44 1895 632894",
    "sg:postcode":"HA4 7JQ",
    "sg:province":"Greater London",
    "sg:tags":[
        "engine",
        "specialist",
        "garage",
        "modification",
        "car"
    ],
    "wof:name":"Heathway Motor Services",
    "wof:placetype":"venue"
},
  "geometry": {"coordinates":[-0.43294999,51.5763626099],"type":"Point"}
}