{
  "type": "Feature",
  "properties": {
    "addr:full":"Nicholas La Huntingdon Cambridgeshire PE17 4PW",
    "addr:postcode":"pe17 4pw",
    "addr:street":"Huntingdon",
    "iso:country":"GB",
    "sg:address":"Nicholas La",
    "sg:city":"Huntingdon",
    "sg:classifiers":[
        {
            "category":"Professional",
            "subcategory":"Management & Consulting",
            "type":"Services"
        }
    ],
    "sg:phone":"+44 1480 460631",
    "sg:postcode":"PE17 4PW",
    "sg:province":"Cambridgeshire",
    "sg:tags":[
        "sport"
    ],
    "wof:name":"International Allied Sporting Promotion",
    "wof:placetype":"venue"
},
  "geometry": {"coordinates":[-0.1893000007,52.3351402283],"type":"Point"}
}