{
  "type": "Feature",
  "properties": {
    "addr:full":"5 Cundy Road London Greater London E16 3DJ",
    "addr:housenumber":"5",
    "addr:postcode":"e16 3dj",
    "addr:street":"Cundy Road",
    "iso:country":"GB",
    "sg:address":"5 Cundy Road",
    "sg:city":"London",
    "sg:classifiers":[
        {
            "category":"Personal",
            "subcategory":"Beauty Salon",
            "type":"Services"
        }
    ],
    "sg:phone":"+44 20 7476 1987",
    "sg:postcode":"E16 3DJ",
    "sg:province":"Greater London",
    "sg:tags":[
        "ladies",
        "lady",
        "hairdresser"
    ],
    "wof:name":"Regent Hairdressers",
    "wof:placetype":"venue"
},
  "geometry": {"coordinates":[0.0332879983,51.5110740662],"type":"Point"}
}