{
  "type": "Feature",
  "properties": {
    "iso:country":"GB",
    "sg:address":"32 Eastgate, Honley",
    "sg:city":"Huddersfield",
    "sg:classifiers":[
        {
            "category":"Personal",
            "subcategory":"Beauty Salon",
            "type":"Services"
        },
        {
            "category":"Personal",
            "subcategory":"Barber",
            "type":"Services"
        }
    ],
    "sg:phone":"+44 1484 663345",
    "sg:postcode":"HD9 6PA",
    "sg:province":"South Yorkshire",
    "sg:tags":[
        "unisex",
        "hairdresser"
    ],
    "wof:name":"Maxines",
    "wof:placetype":"venue"
},
  "geometry": {"coordinates":[-1.789603,53.604511],"type":"Point"}
}