{
  "type": "Feature",
  "properties": {
    "addr:full":"14 Cranford Crescent, Ross-on-sea Colwyn Bay Conwy LL28 4LN",
    "addr:housenumber":"14",
    "addr:postcode":"ll28 4ln",
    "addr:street":"Cranford Crescent Ross-On-Sea",
    "iso:country":"GB",
    "sg:address":"14 Cranford Crescent, Ross-on-sea",
    "sg:city":"Colwyn Bay",
    "sg:classifiers":[
        {
            "category":"Personal",
            "subcategory":"Beauty Salon",
            "type":"Services"
        },
        {
            "category":"Personal",
            "subcategory":"Barber",
            "type":"Services"
        }
    ],
    "sg:phone":"+44 1492 546812",
    "sg:postcode":"LL28 4LN",
    "sg:province":"Conwy",
    "sg:tags":[
        "unisex",
        "hairdresser"
    ],
    "wof:name":"BERYL DEVEREUX",
    "wof:placetype":"venue"
},
  "geometry": {"coordinates":[-3.7471559048,53.3130607605],"type":"Point"}
}