{
  "type": "Feature",
  "properties": {
    "iso:country":"GB",
    "sg:address":"9 Verdun Crescent, Spotland",
    "sg:city":"Rochdale",
    "sg:classifiers":[
        {
            "category":"Building & Trades",
            "subcategory":"Cleaning & Sanitation",
            "type":"Services"
        }
    ],
    "sg:phone":"+44 1706 642918",
    "sg:postcode":"OL11 5DT",
    "sg:province":"Lancashire",
    "sg:tags":[
        "cleaner",
        "window"
    ],
    "wof:name":"High Access",
    "wof:placetype":"venue"
},
  "geometry": {"coordinates":[-2.180885,53.618347],"type":"Point"}
}