{
  "type": "Feature",
  "properties": {
    "addr:full":"28 Queens Road Reading Berkshire RG1 4AU",
    "addr:housenumber":"28",
    "addr:postcode":"rg1 4au",
    "addr:street":"Queens Road",
    "iso:country":"GB",
    "sg:address":"28 Queens Road",
    "sg:city":"Reading",
    "sg:classifiers":[
        {
            "category":"Communications",
            "type":"Services"
        }
    ],
    "sg:postcode":"RG1 4AU",
    "sg:province":"Berkshire",
    "sg:tags":[
        "data",
        "network"
    ],
    "wof:name":"Olandata Ltd.",
    "wof:placetype":"venue"
},
  "geometry": {"coordinates":[-0.9671630263,51.4533996582],"type":"Point"}
}