{
  "type": "Feature",
  "properties": {
    "iso:country":"GB",
    "sg:address":"9 Princess Street",
    "sg:city":"Wolverhampton",
    "sg:classifiers":[
        {
            "category":"Bars & Pubs",
            "type":"Food & Drink"
        }
    ],
    "sg:phone":"+44 1902 313147",
    "sg:postcode":"WV1 1HW",
    "sg:province":"West Midlands",
    "sg:tags":[
        "pubs",
        "inn"
    ],
    "wof:name":"Punch Retail Ltd",
    "wof:placetype":"venue"
},
  "geometry": {"coordinates":[-2.125496,52.586357],"type":"Point"}
}