{
  "type": "Feature",
  "properties": {
    "addr:full":"Trecader Court, Penmark Barry The Vale of Glamorgan CF62 3BP",
    "addr:postcode":"cf62 3bp",
    "addr:street":"Vale",
    "iso:country":"GB",
    "sg:address":"Trecader Court, Penmark",
    "sg:city":"Barry",
    "sg:classifiers":[
        {
            "category":"Communications",
            "subcategory":"Film & Video Production",
            "type":"Services"
        }
    ],
    "sg:postcode":"CF62 3BP",
    "sg:province":"The Vale of Glamorgan",
    "sg:tags":[
        "tv",
        "radio"
    ],
    "wof:name":"Tacticall Ltd.",
    "wof:placetype":"venue"
},
  "geometry": {"coordinates":[-3.3559479713,51.4106483459],"type":"Point"}
}