{
  "type": "Feature",
  "properties": {
    "addr:full":"Field House, Recreation Road, New Houghton Mansfield Derbyshire NG19 8TL",
    "addr:postcode":"ng19 8tl",
    "addr:street":"Recreation Road New",
    "iso:country":"GB",
    "sg:address":"Field House, Recreation Road, New Houghton",
    "sg:city":"Mansfield",
    "sg:classifiers":[
        {
            "category":"Professional",
            "subcategory":"Computer Services",
            "type":"Services"
        }
    ],
    "sg:phone":"+44 115 840 5075",
    "sg:postcode":"NG19 8TL",
    "sg:province":"Derbyshire",
    "sg:tags":[
        "system",
        "software"
    ],
    "wof:name":"Perkeo Computer Systems Ltd.",
    "wof:placetype":"venue"
},
  "geometry": {"coordinates":[-1.256199,53.184296],"type":"Point"}
}