{
  "type": "Feature",
  "properties": {
    "iso:country":"GB",
    "sg:address":"1st Floor Eastern House, 8/10 Eastern Road",
    "sg:city":"Romford",
    "sg:classifiers":[
        {
            "category":"Education",
            "subcategory":"Special Training",
            "type":"Public Place"
        }
    ],
    "sg:phone":"+44 1708 730459",
    "sg:postcode":"RM1 3PJ",
    "sg:province":"Essex",
    "sg:tags":[
        "product",
        "centre"
    ],
    "wof:name":"Chelmer Training Ltd.",
    "wof:placetype":"venue"
},
  "geometry": {"coordinates":[0.184535,51.575779],"type":"Point"}
}