{
  "type": "Feature",
  "properties": {
    "iso:country":"GB",
    "sg:address":"8 Oxford St",
    "sg:city":"Workington",
    "sg:classifiers":[
        {
            "category":"Banks & Credit Unions",
            "subcategory":"Financial Services",
            "type":"Services"
        }
    ],
    "sg:phone":"+44 1900 602861",
    "sg:postcode":"CA14 2AH",
    "sg:province":"Cumbria",
    "sg:tags":[
        "consultant"
    ],
    "wof:name":"Provident Personal Credit",
    "wof:placetype":"venue"
},
  "geometry": {"coordinates":[-3.5498919487,54.6436576843],"type":"Point"}
}