{
  "type": "Feature",
  "properties": {
    "iso:country":"GB",
    "sg:address":"5a Jubilee Market, St Barnabas Road",
    "sg:city":"Woodford Green",
    "sg:classifiers":[
        {
            "category":"Home & Garden",
            "subcategory":"Carpets & Floor Coverings",
            "type":"Retail Goods"
        }
    ],
    "sg:phone":"+44 20 8559 0002",
    "sg:postcode":"IG8 7BZ",
    "sg:province":"Essex",
    "sg:tags":[
        "carpets",
        "rug",
        "matting"
    ],
    "wof:name":"C M S Carpets",
    "wof:placetype":"venue"
},
  "geometry": {"coordinates":[0.035644,51.60754],"type":"Point"}
}