{
  "type": "Feature",
  "properties": {
    "addr:full":"9 Temple Close, Lees Oldham Lancashire OL4 3PA",
    "addr:housenumber":"9",
    "addr:postcode":"ol4 3pa",
    "addr:street":"Temple Close",
    "iso:country":"GB",
    "sg:address":"9 Temple Close, Lees",
    "sg:city":"Oldham",
    "sg:classifiers":[
        {
            "category":"Building & Trades",
            "subcategory":"Construction",
            "type":"Services"
        }
    ],
    "sg:postcode":"OL4 3PA",
    "sg:province":"Lancashire",
    "sg:tags":[
        "builder"
    ],
    "wof:name":"Birchwood Construction Ltd.",
    "wof:placetype":"venue"
},
  "geometry": {"coordinates":[-2.0699789524,53.5494155884],"type":"Point"}
}