{
  "type": "Feature",
  "properties": {
    "addr:full":"5 Moor Road, Hunslet Leeds West Yorkshire LS10 2JJ",
    "addr:housenumber":"5",
    "addr:postcode":"ls10 2jj",
    "addr:street":"Moor Road",
    "iso:country":"GB",
    "sg:address":"5 Moor Road, Hunslet",
    "sg:city":"Leeds",
    "sg:classifiers":[
        {
            "category":"Health Services",
            "subcategory":"Doctor",
            "type":"Services"
        },
        {
            "category":"Health Services",
            "subcategory":"Clinic",
            "type":"Services"
        }
    ],
    "sg:phone":"+44 844 477 0926",
    "sg:postcode":"LS10 2JJ",
    "sg:province":"West Yorkshire",
    "sg:tags":[
        "nh",
        "practitioners"
    ],
    "wof:name":"Archingcon Medical Centre",
    "wof:placetype":"venue"
},
  "geometry": {"coordinates":[-1.5322450399,53.7722625732],"type":"Point"}
}