{
  "type": "Feature",
  "properties": {
    "addr:full":"Haddon Road Bakewell Derbyshire DE45 1BA",
    "addr:postcode":"de45 1ba",
    "addr:street":"Haddon Road",
    "iso:country":"GB",
    "sg:address":"Haddon Road",
    "sg:city":"Bakewell",
    "sg:classifiers":[
        {
            "category":"Food & Beverages",
            "subcategory":"Supermarket",
            "type":"Retail Goods"
        }
    ],
    "sg:phone":"+44 1629 812845",
    "sg:postcode":"DE45 1BA",
    "sg:province":"Derbyshire",
    "wof:name":"M A Hill",
    "wof:placetype":"venue"
},
  "geometry": {"coordinates":[-1.6697800159,53.2078933716],"type":"Point"}
}