{
  "type": "Feature",
  "properties": {
    "addr:full":"Old Harcroft Wagon Wrks Coalville Leicestershire LE67 3FH",
    "addr:postcode":"le67 3fh",
    "addr:street":"Old Harcroft Wagon Wrks",
    "iso:country":"GB",
    "sg:address":"Old Harcroft Wagon Wrks",
    "sg:city":"Coalville",
    "sg:classifiers":[
        {
            "category":"Retail",
            "subcategory":"Auto Repair",
            "type":"Services"
        }
    ],
    "sg:phone":"+44 1530 815028",
    "sg:postcode":"LE67 3FH",
    "sg:province":"Leicestershire",
    "sg:tags":[
        "bodybuilder",
        "repairer"
    ],
    "wof:name":"Coalville Commercials Ltd.",
    "wof:placetype":"venue"
},
  "geometry": {"coordinates":[-1.3723059893,52.7187843323],"type":"Point"}
}