{
  "type": "Feature",
  "properties": {
    "addr:full":"71b Durham Road Gateshead Tyne and Wear NE8 4AP",
    "addr:housenumber":"71b",
    "addr:postcode":"ne8 4ap",
    "addr:street":"Durham Road",
    "iso:country":"GB",
    "sg:address":"71b Durham Road",
    "sg:city":"Gateshead",
    "sg:classifiers":[
        {
            "category":"Autos & Motor Vehicles",
            "subcategory":"Auto Supplies",
            "type":"Retail Goods"
        }
    ],
    "sg:postcode":"NE8 4AP",
    "sg:province":"Tyne and Wear",
    "sg:tags":[
        "windscreen"
    ],
    "wof:name":"Glasweld Systems",
    "wof:placetype":"venue"
},
  "geometry": {"coordinates":[-1.599338,54.953377],"type":"Point"}
}