{
  "type": "Feature",
  "properties": {
    "addr:full":"447 Perth Avenue, Slough Trading Estate Slough Berkshire SL1 4TS",
    "addr:housenumber":"447",
    "addr:postcode":"sl1 4ts",
    "addr:street":"Perth Avenue;Trading Estate",
    "iso:country":"GB",
    "sg:address":"447 Perth Avenue, Slough Trading Estate",
    "sg:city":"Slough",
    "sg:classifiers":[
        {
            "category":"Retail",
            "subcategory":"Auto Repair",
            "type":"Services"
        }
    ],
    "sg:postcode":"SL1 4TS",
    "sg:province":"Berkshire",
    "sg:tags":[
        "modification",
        "garage"
    ],
    "wof:name":"Auto Technics U K Ltd.",
    "wof:placetype":"venue"
},
  "geometry": {"coordinates":[-0.6172519922,51.5235481262],"type":"Point"}
}