{
  "type": "Feature",
  "properties": {
    "iso:country":"GB",
    "sg:address":"66 High Street, Worle",
    "sg:city":"Weston-super-mare",
    "sg:classifiers":[
        {
            "category":"Social Services",
            "subcategory":"Retirement Home",
            "type":"Services"
        }
    ],
    "sg:postcode":"BS22 6EJ",
    "sg:province":"Somerset",
    "sg:tags":[
        "residential",
        "care"
    ],
    "wof:name":"Nutwell Residential Home",
    "wof:placetype":"venue"
},
  "geometry": {"coordinates":[-2.9319760799,51.3585357666],"type":"Point"}
}