{
  "type": "Feature",
  "properties": {
    "addr:full":"66 High Street, Worle Weston-super-mare Somerset BS22 6EJ",
    "addr:housenumber":"66",
    "addr:postcode":"bs22 6ej",
    "addr:street":"High Street",
    "iso:country":"GB",
    "sg:address":"66 High Street, Worle",
    "sg:city":"Weston-super-mare",
    "sg:classifiers":[
        {
            "category":"Social Services",
            "subcategory":"Retirement Home",
            "type":"Services"
        }
    ],
    "sg:postcode":"BS22 6EJ",
    "sg:province":"Somerset",
    "sg:tags":[
        "residential",
        "care"
    ],
    "wof:name":"Nutwell Residential Home",
    "wof:placetype":"venue"
},
  "geometry": {"coordinates":[-2.9319760799,51.3585357666],"type":"Point"}
}