{
  "type": "Feature",
  "properties": {
    "addr:full":"Wykes House, Buckingham Street Birmingham West Midlands B19 3HS",
    "addr:postcode":"b19 3hs",
    "addr:street":"Buckingham Street",
    "iso:country":"GB",
    "sg:address":"Wykes House, Buckingham Street",
    "sg:city":"Birmingham",
    "sg:classifiers":[
        {
            "category":"Home & Garden",
            "subcategory":"Household Appliances",
            "type":"Retail Goods"
        }
    ],
    "sg:phone":"+44 121 200 2740",
    "sg:postcode":"B19 3HS",
    "sg:province":"West Midlands",
    "sg:tags":[
        "electrical"
    ],
    "wof:name":"Wykes Electrical Repairs Ltd.",
    "wof:placetype":"venue"
},
  "geometry": {"coordinates":[-1.9035140276,52.4891281128],"type":"Point"}
}