{
  "type": "Feature",
  "properties": {
    "iso:country":"GB",
    "sg:address":"Copthorne Road, Poundhill",
    "sg:city":"Crawley",
    "sg:classifiers":[
        {
            "category":"Building & Trades",
            "subcategory":"Landscaping Services",
            "type":"Services"
        },
        {
            "category":"Home & Garden",
            "subcategory":"Garden Supply",
            "type":"Retail Goods"
        }
    ],
    "sg:phone":"+44 1293 886007",
    "sg:postcode":"RH10 3PD",
    "sg:province":"Surrey",
    "sg:tags":[
        "planting",
        "tree",
        "shrub",
        "landscape",
        "contractor"
    ],
    "wof:name":"Windmill Contractors Ltd",
    "wof:placetype":"venue"
},
  "geometry": {"coordinates":[-0.121961,51.133877],"type":"Point"}
}