{
  "type": "Feature",
  "properties": {
    "iso:country":"GB",
    "sg:address":"8 Sun Way",
    "sg:city":"Leicester",
    "sg:classifiers":[
        {
            "category":"Fast Food",
            "type":"Food & Drink"
        }
    ],
    "sg:phone":"+44 116 289 1626",
    "sg:postcode":"LE3 3DS",
    "sg:province":"Leicestershire",
    "sg:tags":[
        "away",
        "meal",
        "outlet",
        "take"
    ],
    "wof:name":"Lees House",
    "wof:placetype":"venue"
},
  "geometry": {"coordinates":[-1.1931680441,52.6237258911],"type":"Point"}
}