{
  "type": "Feature",
  "properties": {
    "iso:country":"GB",
    "sg:address":"Westminster Lane",
    "sg:city":"Newport",
    "sg:classifiers":[
        {
            "category":"Wholesale",
            "subcategory":"Plants",
            "type":"Manufacturing & Wholesale Goods"
        }
    ],
    "sg:phone":"+44 1983 524962",
    "sg:postcode":"PO30 5DP",
    "sg:province":"Isle of Wight",
    "sg:tags":[
        "pot",
        "pourri"
    ],
    "wof:name":"Ashley & Burwood Manufacturing",
    "wof:placetype":"venue"
},
  "geometry": {"coordinates":[-1.3033879995,50.6982383728],"type":"Point"}
}