{
  "type": "Feature",
  "properties": {
    "addr:full":"13 Halifax Rd Todmorden Lancashire OL14 5AG",
    "addr:housenumber":"13",
    "addr:postcode":"ol14 5ag",
    "addr:street":"Halifax Rd",
    "iso:country":"GB",
    "sg:address":"13 Halifax Rd",
    "sg:city":"Todmorden",
    "sg:classifiers":[
        {
            "category":"Shopping",
            "subcategory":"Books",
            "type":"Retail Goods"
        }
    ],
    "sg:phone":"+44 1706 810820",
    "sg:postcode":"OL14 5AG",
    "sg:province":"Lancashire",
    "sg:tags":[
        "bookseller"
    ],
    "wof:name":"Bookworm",
    "wof:placetype":"venue"
},
  "geometry": {"coordinates":[-2.096585,53.713764],"type":"Point"}
}