{
  "type": "Feature",
  "properties": {
    "addr:full":"81 Monkoms Drive Woodford Green Essex IG8 0LD",
    "addr:housenumber":"81",
    "addr:postcode":"ig8 0ld",
    "addr:street":"Monkoms Drive",
    "iso:country":"GB",
    "sg:address":"81 Monkoms Drive",
    "sg:city":"Woodford Green",
    "sg:classifiers":[
        {
            "category":"Professional",
            "subcategory":"Art Services",
            "type":"Services"
        }
    ],
    "sg:postcode":"IG8 0LD",
    "sg:province":"Essex",
    "sg:tags":[
        "graphic",
        "designer"
    ],
    "wof:name":"Mark Carpenter Design Consultants",
    "wof:placetype":"venue"
},
  "geometry": {"coordinates":[0.030793,51.613644],"type":"Point"}
}