{
  "type": "Feature",
  "properties": {
    "addr:full":"174 Tudor Drive Morden Surrey SM4 4PG",
    "addr:housenumber":"174",
    "addr:postcode":"sm4 4pg",
    "addr:street":"Tudor Drive",
    "iso:country":"GB",
    "sg:address":"174 Tudor Drive",
    "sg:city":"Morden",
    "sg:classifiers":[
        {
            "category":"Professional",
            "subcategory":"Art Services",
            "type":"Services"
        },
        {
            "category":"Building & Trades",
            "subcategory":"Construction",
            "type":"Services"
        }
    ],
    "sg:phone":"+44 20 8337 2438",
    "sg:postcode":"SM4 4PG",
    "sg:province":"Surrey",
    "sg:tags":[
        "decorator",
        "painter"
    ],
    "wof:name":"P & M Decorators",
    "wof:placetype":"venue"
},
  "geometry": {"coordinates":[-0.219099,51.389309],"type":"Point"}
}