{
  "type": "Feature",
  "properties": {
    "addr:full":"Po Box 154 Sheffield South Yorkshire S10 4BW",
    "addr:housenumber":"po",
    "addr:postcode":"s10 4bw",
    "addr:street":"Box 154",
    "iso:country":"GB",
    "sg:address":"Po Box 154",
    "sg:city":"Sheffield",
    "sg:classifiers":[
        {
            "category":"Communications",
            "subcategory":"News Services",
            "type":"Services"
        }
    ],
    "sg:phone":"+44 114 230 3093",
    "sg:postcode":"S10 4BW",
    "sg:province":"South Yorkshire",
    "sg:tags":[
        "photo",
        "agency"
    ],
    "wof:name":"Snowdon Sports Editorial",
    "wof:placetype":"venue"
},
  "geometry": {"coordinates":[-1.464544,53.38311],"type":"Point"}
}