{
  "type": "Feature",
  "properties": {
    "addr:full":"22 Bron Y Deri Mountain Ash Rhondda, Cynon, Taff CF45 4LL",
    "addr:housenumber":"22",
    "addr:postcode":"cf45 4ll",
    "addr:street":"Bron Y Deri;Ash;Cynon Taff",
    "iso:country":"GB",
    "sg:address":"22 Bron Y Deri",
    "sg:city":"Mountain Ash",
    "sg:classifiers":[
        {
            "category":"Professional",
            "subcategory":"Engineering",
            "type":"Services"
        }
    ],
    "sg:phone":"+44 1443 476176",
    "sg:postcode":"CF45 4LL",
    "sg:province":"Rhondda, Cynon, Taff",
    "sg:tags":[
        "contractor",
        "electrical",
        "engineer"
    ],
    "wof:name":"Wayne Keepin Electrical Contractors",
    "wof:placetype":"venue"
},
  "geometry": {"coordinates":[-3.373404026,51.6827430725],"type":"Point"}
}