{
  "type": "Feature",
  "properties": {
    "addr:full":"17 Valleyfield Road London Greater London SW16 2HS",
    "addr:housenumber":"17",
    "addr:postcode":"sw16 2hs",
    "addr:street":"Valleyfield Road",
    "iso:country":"GB",
    "sg:address":"17 Valleyfield Road",
    "sg:city":"London",
    "sg:classifiers":[
        {
            "category":"Building & Trades",
            "subcategory":"Plumbing",
            "type":"Services"
        }
    ],
    "sg:postcode":"SW16 2HS",
    "sg:province":"Greater London",
    "sg:tags":[
        "heating"
    ],
    "wof:name":"J T D Plumbing & Heating",
    "wof:placetype":"venue"
},
  "geometry": {"coordinates":[-0.120423,51.426296],"type":"Point"}
}