{
  "type": "Feature",
  "properties": {
    "iso:country":"GB",
    "sg:address":"Rose Farm, Foxholes Lane",
    "sg:city":"Normanton",
    "sg:classifiers":[
        {
            "category":"Farming",
            "subcategory":"Dairy Farm",
            "type":"Manufacturing & Wholesale Goods"
        }
    ],
    "sg:postcode":"WF6 2PE",
    "sg:province":"West Yorkshire",
    "wof:name":"P Swift",
    "wof:placetype":"venue"
},
  "geometry": {"coordinates":[-1.412878,53.698082],"type":"Point"}
}