{
  "type": "Feature",
  "properties": {
    "iso:country":"GB",
    "sg:address":"2 Whitwell Crescent, Stocksbridge",
    "sg:city":"Sheffield",
    "sg:classifiers":[
        {
            "category":"Taxi",
            "type":"Transportation"
        }
    ],
    "sg:phone":"+44 114 288 5909",
    "sg:postcode":"S36 1GD",
    "sg:province":"South Yorkshire",
    "sg:tags":[
        "mini",
        "cab"
    ],
    "wof:name":"L O Taxis",
    "wof:placetype":"venue"
},
  "geometry": {"coordinates":[-1.5978449583,53.4813537598],"type":"Point"}
}