{
  "type": "Feature",
  "properties": {
    "addr:full":"23 Church Gate Leicester Leicestershire LE1 3AL",
    "addr:housenumber":"23",
    "addr:postcode":"le1 3al",
    "addr:street":"Church Gate",
    "iso:country":"GB",
    "sg:address":"23 Church Gate",
    "sg:city":"Leicester",
    "sg:classifiers":[
        {
            "category":"Shopping",
            "subcategory":"Optician",
            "type":"Retail Goods"
        },
        {
            "category":"Health Services",
            "subcategory":"Optometrist",
            "type":"Services"
        }
    ],
    "sg:phone":"+44 116 262 0090",
    "sg:postcode":"LE1 3AL",
    "sg:province":"Leicestershire",
    "sg:tags":[
        "opthalmic"
    ],
    "wof:name":"Lancaster & Thorpe Ltd.",
    "wof:placetype":"venue"
},
  "geometry": {"coordinates":[-1.1337200403,52.6369934082],"type":"Point"}
}