{
  "type": "Feature",
  "properties": {
    "addr:full":"45 Townside, Haddenham Aylesbury Buckinghamshire HP17 8AW",
    "addr:housenumber":"45;haddenham",
    "addr:postcode":"hp17 8aw",
    "addr:street":"Townside",
    "iso:country":"GB",
    "sg:address":"45 Townside, Haddenham",
    "sg:city":"Aylesbury",
    "sg:classifiers":[
        {
            "category":"Food & Beverages",
            "subcategory":"Meat & Fish",
            "type":"Retail Goods"
        }
    ],
    "sg:postcode":"HP17 8AW",
    "sg:province":"Buckinghamshire",
    "sg:tags":[
        "butcher"
    ],
    "wof:name":"A & M Meat Specialists",
    "wof:placetype":"venue"
},
  "geometry": {"coordinates":[-0.897059,51.787472],"type":"Point"}
}