{
  "type": "Feature",
  "properties": {
    "addr:full":"86 Berry Down, Combe Martin Ilfracombe Devon EX34 0NU",
    "addr:housenumber":"86;combe",
    "addr:postcode":"ex34 0nu",
    "addr:street":"Berry Down",
    "iso:country":"GB",
    "sg:address":"86 Berry Down, Combe Martin",
    "sg:city":"Ilfracombe",
    "sg:classifiers":[
        {
            "category":"Banks & Credit Unions",
            "subcategory":"Investment Brokerage",
            "type":"Services"
        }
    ],
    "sg:phone":"+44 1271 883238",
    "sg:postcode":"EX34 0NU",
    "sg:province":"Devon",
    "sg:tags":[
        "contractor"
    ],
    "wof:name":"Dennis J Peddle",
    "wof:placetype":"venue"
},
  "geometry": {"coordinates":[-4.0431408882,51.2058906555],"type":"Point"}
}