{
  "type": "Feature",
  "properties": {
    "addr:full":"63 Southway Newcastle-upon-tyne Northumberland NE15 7RB",
    "addr:housenumber":"63;newcastle-upon-tyne",
    "addr:postcode":"ne15 7rb",
    "addr:street":"Southway",
    "iso:country":"GB",
    "sg:address":"63 Southway",
    "sg:city":"Newcastle-upon-tyne",
    "sg:classifiers":[
        {
            "category":"Building & Trades",
            "subcategory":"Construction",
            "type":"Services"
        }
    ],
    "sg:phone":"+44 191 267 3051",
    "sg:postcode":"NE15 7RB",
    "sg:province":"Northumberland",
    "sg:tags":[
        "builder"
    ],
    "wof:name":"M G Properties",
    "wof:placetype":"venue"
},
  "geometry": {"coordinates":[-1.6976989508,54.9828605652],"type":"Point"}
}