{
  "type": "Feature",
  "properties": {
    "addr:full":"113 Brighton Road Croydon Surrey CR2 6EE",
    "addr:housenumber":"113",
    "addr:postcode":"cr2 6ee",
    "addr:street":"Brighton Road",
    "iso:country":"GB",
    "sg:address":"113 Brighton Road",
    "sg:city":"Croydon",
    "sg:classifiers":[
        {
            "category":"Professional",
            "type":"Services"
        },
        {
            "category":"Retail",
            "subcategory":"Auto Rental",
            "type":"Services"
        }
    ],
    "sg:postcode":"CR2 6EE",
    "sg:province":"Surrey",
    "sg:tags":[
        "car",
        "leasing",
        "vehicle"
    ],
    "wof:name":"Translease Vehicle Management Ltd.",
    "wof:placetype":"venue"
},
  "geometry": {"coordinates":[-0.097549,51.358482],"type":"Point"}
}