{
  "type": "Feature",
  "properties": {
    "addr:full":"10 Obelisk Rise, Kingsthorpe Northampton Northamptonshire NN2 8QT",
    "addr:housenumber":"10",
    "addr:postcode":"nn2 8qt",
    "addr:street":"Obelisk Rise",
    "iso:country":"GB",
    "sg:address":"10 Obelisk Rise, Kingsthorpe",
    "sg:city":"Northampton",
    "sg:classifiers":[
        {
            "category":"Building & Trades",
            "subcategory":"Construction",
            "type":"Services"
        }
    ],
    "sg:phone":"+44 1604 845619",
    "sg:postcode":"NN2 8QT",
    "sg:province":"Northamptonshire",
    "sg:tags":[
        "fork",
        "lift",
        "truck"
    ],
    "wof:name":"Transport & Lift Truck Safety Training Services",
    "wof:placetype":"venue"
},
  "geometry": {"coordinates":[-0.8909590244,52.2777786255],"type":"Point"}
}