{
  "type": "Feature",
  "properties": {
    "addr:full":"121 Shipston Road Stratford-upon-avon Warwickshire CV37 7LW",
    "addr:housenumber":"121",
    "addr:postcode":"cv37 7lw",
    "addr:street":"Shipston Road",
    "iso:country":"GB",
    "sg:address":"121 Shipston Road",
    "sg:city":"Stratford-upon-avon",
    "sg:classifiers":[
        {
            "category":"Travel",
            "subcategory":"Hotels & Motels",
            "type":"Entertainment"
        }
    ],
    "sg:phone":"+44 1789 297542",
    "sg:postcode":"CV37 7LW",
    "sg:province":"Warwickshire",
    "wof:name":"Avon View Hotel",
    "wof:placetype":"venue"
},
  "geometry": {"coordinates":[-1.700687,52.184433],"type":"Point"}
}