{
  "type": "Feature",
  "properties": {
    "iso:country":"GB",
    "sg:address":"111a Houghton Road, Thurnscoe",
    "sg:city":"Rotherham",
    "sg:classifiers":[
        {
            "category":"Health Services",
            "subcategory":"Optometrist",
            "type":"Services"
        },
        {
            "category":"Shopping",
            "subcategory":"Optician",
            "type":"Retail Goods"
        }
    ],
    "sg:phone":"+44 1709 893317",
    "sg:postcode":"S63 0NG",
    "sg:province":"South Yorkshire",
    "sg:tags":[
        "ophthalmic"
    ],
    "wof:name":"Roger H Auckland",
    "wof:placetype":"venue"
},
  "geometry": {"coordinates":[-1.318681,53.546555],"type":"Point"}
}