{
  "type": "Feature",
  "properties": {
    "addr:full":"89 New Bridge Street Newcastle-upon-tyne Tyne and Wear NE1 2SW",
    "addr:housenumber":"89",
    "addr:postcode":"ne1 2sw",
    "addr:street":"New Bridge Street",
    "iso:country":"GB",
    "sg:address":"89 New Bridge Street",
    "sg:city":"Newcastle-upon-tyne",
    "sg:classifiers":[
        {
            "category":"Food & Beverages",
            "subcategory":"Bakery",
            "type":"Retail Goods"
        }
    ],
    "sg:phone":"+44 191 221 0995",
    "sg:postcode":"NE1 2SW",
    "sg:province":"Tyne and Wear",
    "sg:tags":[
        "pizza"
    ],
    "wof:name":"Deep Pan Pizza Co",
    "wof:placetype":"venue"
},
  "geometry": {"coordinates":[-1.6025960445,54.9745521545],"type":"Point"}
}