{
  "type": "Feature",
  "properties": {
    "iso:country":"GB",
    "sg:address":"22 Berry St",
    "sg:city":"Liverpool",
    "sg:classifiers":[
        {
            "category":"Shopping",
            "subcategory":"Department Store",
            "type":"Retail Goods"
        }
    ],
    "sg:postcode":"L1 4JF",
    "sg:province":"Merseyside",
    "wof:name":"Sung,K M,",
    "wof:placetype":"venue"
},
  "geometry": {"coordinates":[-2.976143,53.401386],"type":"Point"}
}