{
  "type": "Feature",
  "properties": {
    "iso:country":"GB",
    "sg:address":"393 Wimborne Road East",
    "sg:city":"Ferndown",
    "sg:classifiers":[
        {
            "category":"Retail",
            "subcategory":"Auto Repair",
            "type":"Services"
        }
    ],
    "sg:phone":"+44 1202 893090",
    "sg:postcode":"BH22 9LZ",
    "sg:province":"Dorset",
    "sg:tags":[
        "modification",
        "garage",
        "related"
    ],
    "wof:name":"Steve Poldens Autos",
    "wof:placetype":"venue"
},
  "geometry": {"coordinates":[-1.9112989902,50.8061599731],"type":"Point"}
}