{
  "type": "Feature",
  "properties": {
    "addr:full":"125 Tilbury Rd Sunderland Tyne and Wear SR3 4LX",
    "addr:housenumber":"125",
    "addr:postcode":"sr3 4lx",
    "addr:street":"Tilbury Rd",
    "iso:country":"GB",
    "sg:address":"125 Tilbury Rd",
    "sg:city":"Sunderland",
    "sg:classifiers":[
        {
            "category":"Retail",
            "subcategory":"Driving School",
            "type":"Services"
        }
    ],
    "sg:phone":"+44 191 520 3170",
    "sg:postcode":"SR3 4LX",
    "sg:province":"Tyne and Wear",
    "wof:name":"Grahams School Of Motoring",
    "wof:placetype":"venue"
},
  "geometry": {"coordinates":[-1.4371579885,54.8773117065],"type":"Point"}
}