{
  "type": "Feature",
  "properties": {
    "iso:country":"GB",
    "sg:address":"Units 7 & 9 Cradge Bank",
    "sg:city":"Spalding",
    "sg:classifiers":[
        {
            "category":"Shopping",
            "subcategory":"Discount & Variety Stores",
            "type":"Retail Goods"
        }
    ],
    "sg:phone":"+44 1775 724301",
    "sg:postcode":"PE11 3AB",
    "sg:province":"Lincolnshire",
    "sg:tags":[
        "cleaning",
        "supply"
    ],
    "wof:name":"Logtek Ltd.",
    "wof:placetype":"venue"
},
  "geometry": {"coordinates":[-0.1627299935,52.7738609314],"type":"Point"}
}