{
  "type": "Feature",
  "properties": {
    "addr:full":"1 Dan Y Lan, Pen Y Fai Road Bridgend Bridgend CF32 9AB",
    "addr:housenumber":"1",
    "addr:postcode":"cf32 9ab",
    "addr:street":"Dan Y Lan Pen Y Fai Road",
    "iso:country":"GB",
    "sg:address":"1 Dan Y Lan, Pen Y Fai Road",
    "sg:city":"Bridgend",
    "sg:classifiers":[
        {
            "category":"Retail",
            "subcategory":"Repair Shop",
            "type":"Services"
        }
    ],
    "sg:phone":"+44 1656 722418",
    "sg:postcode":"CF32 9AB",
    "sg:province":"Bridgend",
    "sg:tags":[
        "radio",
        "television",
        "video"
    ],
    "wof:name":"Highland Electrix",
    "wof:placetype":"venue"
},
  "geometry": {"coordinates":[-3.595872,51.535786],"type":"Point"}
}