{
  "type": "Feature",
  "properties": {
    "addr:full":"Unitc, Tern Place, Denmore Road, Bridge Of Don Aberdeen Aberdeen City AB23 8JX",
    "addr:postcode":"ab23 8jx",
    "addr:street":"Unitc Tern Place Denmore Road",
    "iso:country":"GB",
    "sg:address":"Unitc, Tern Place, Denmore Road, Bridge Of Don",
    "sg:city":"Aberdeen",
    "sg:classifiers":[
        {
            "category":"Professional",
            "subcategory":"Engineering",
            "type":"Services"
        }
    ],
    "sg:phone":"+44 1224 702211",
    "sg:postcode":"AB23 8JX",
    "sg:province":"Aberdeen City",
    "sg:tags":[
        "contractor",
        "electrical",
        "engineer"
    ],
    "wof:name":"Capelrig Ltd",
    "wof:placetype":"venue"
},
  "geometry": {"coordinates":[-2.095714,57.196136],"type":"Point"}
}