{
  "type": "Feature",
  "properties": {
    "iso:country":"GB",
    "sg:address":"1-3 The Cloisters",
    "sg:city":"Wantage",
    "sg:classifiers":[
        {
            "category":"Social Services",
            "subcategory":"Child Care",
            "type":"Services"
        },
        {
            "category":"Social Services",
            "subcategory":"Adult Care",
            "type":"Services"
        }
    ],
    "sg:phone":"+44 1235 760428",
    "sg:postcode":"OX12 8AQ",
    "sg:province":"Berkshire",
    "sg:tags":[
        "day",
        "centre"
    ],
    "wof:name":"The October Club",
    "wof:placetype":"venue"
},
  "geometry": {"coordinates":[-1.4281209707,51.5888633728],"type":"Point"}
}