{
  "type": "Feature",
  "properties": {
    "addr:full":"Maxstoke Priory, Coleshill Birmingham Warwickshire B46 2QW",
    "addr:housenumber":"maxstoke",
    "addr:postcode":"b46 2qw",
    "addr:street":"Priory",
    "iso:country":"GB",
    "sg:address":"Maxstoke Priory, Coleshill",
    "sg:city":"Birmingham",
    "sg:classifiers":[
        {
            "category":"Farming",
            "subcategory":"Livestock Farm",
            "type":"Manufacturing & Wholesale Goods"
        }
    ],
    "sg:postcode":"B46 2QW",
    "sg:province":"Warwickshire",
    "sg:tags":[
        "others"
    ],
    "wof:name":"R J Tyacke",
    "wof:placetype":"venue"
},
  "geometry": {"coordinates":[-1.68445,52.491871],"type":"Point"}
}