{
  "type": "Feature",
  "properties": {
    "addr:full":"Po Box 23 Chertsey Surrey KT16 9WQ",
    "addr:housenumber":"po box 23",
    "addr:postcode":"kt16 9wq",
    "iso:country":"GB",
    "sg:address":"Po Box 23",
    "sg:city":"Chertsey",
    "sg:classifiers":[
        {
            "category":"Recreation",
            "subcategory":"Dog Park",
            "type":"Entertainment"
        }
    ],
    "sg:phone":"+44 1932 566696",
    "sg:postcode":"KT16 9WQ",
    "sg:province":"Surrey",
    "wof:name":"The Co. of Animals Ltd.",
    "wof:placetype":"venue"
},
  "geometry": {"coordinates":[-0.5108789802,51.3891487122],"type":"Point"}
}