{
  "type": "Feature",
  "properties": {
    "addr:full":"7 Martlesham Welwyn Garden City Hertfordshire AL7 2QF",
    "addr:housenumber":"7",
    "addr:postcode":"al7 2qf",
    "iso:country":"GB",
    "sg:address":"7 Martlesham",
    "sg:city":"Welwyn Garden City",
    "sg:classifiers":[
        {
            "category":"Retail",
            "subcategory":"Repair Shop",
            "type":"Services"
        }
    ],
    "sg:phone":"+44 1707 372734",
    "sg:postcode":"AL7 2QF",
    "sg:province":"Hertfordshire",
    "sg:tags":[
        "maintenance"
    ],
    "wof:name":"D Pollard",
    "wof:placetype":"venue"
},
  "geometry": {"coordinates":[-0.1570439935,51.7992019653],"type":"Point"}
}