{
  "type": "Feature",
  "properties": {
    "addr:full":"47 High Street Boston Lincolnshire PE21 8SP",
    "addr:housenumber":"47",
    "addr:postcode":"pe21 8sp",
    "addr:street":"High Street",
    "iso:country":"GB",
    "sg:address":"47 High Street",
    "sg:city":"Boston",
    "sg:classifiers":[
        {
            "category":"Building & Trades",
            "subcategory":"Construction",
            "type":"Services"
        }
    ],
    "sg:postcode":"PE21 8SP",
    "sg:province":"Lincolnshire",
    "sg:tags":[
        "builder"
    ],
    "wof:name":"Poststone Limited",
    "wof:placetype":"venue"
},
  "geometry": {"coordinates":[-0.0247939993,52.9754600525],"type":"Point"}
}