{
  "type": "Feature",
  "properties": {
    "iso:country":"GB",
    "sg:address":"Park Lane, Queensbury",
    "sg:city":"Bradford",
    "sg:classifiers":[
        {
            "category":"Health Services",
            "subcategory":"Nursing And Care Facility",
            "type":"Services"
        }
    ],
    "sg:phone":"+44 1274 817014",
    "sg:postcode":"BD13 1QJ",
    "sg:province":"West Yorkshire",
    "sg:tags":[
        "home"
    ],
    "wof:name":"Park House Private Nursing Home",
    "wof:placetype":"venue"
},
  "geometry": {"coordinates":[-1.835138,53.768215],"type":"Point"}
}