{
  "type": "Feature",
  "properties": {
    "addr:full":"Forest Product Terminal, Royal Portbury Dock, Portbury Bristol Somerset BS20 7XF",
    "addr:postcode":"bs20 7xf",
    "iso:country":"GB",
    "sg:address":"Forest Product Terminal, Royal Portbury Dock, Portbury",
    "sg:city":"Bristol",
    "sg:classifiers":[
        {
            "category":"Freight",
            "type":"Transportation"
        }
    ],
    "sg:phone":"+44 1275 375418",
    "sg:postcode":"BS20 7XF",
    "sg:province":"Somerset",
    "sg:tags":[
        "overseas",
        "shipping",
        "removal"
    ],
    "wof:name":"Wilhelmsen Lines",
    "wof:placetype":"venue"
},
  "geometry": {"coordinates":[-2.7173190117,51.4746360779],"type":"Point"}
}