{
  "type": "Feature",
  "properties": {
    "addr:full":"Unit 1 Swansea Swansea SA2 7QA",
    "addr:housenumber":"unit 1",
    "addr:postcode":"sa2 7qa",
    "iso:country":"GB",
    "sg:address":"Unit 1",
    "sg:city":"Swansea",
    "sg:classifiers":[
        {
            "category":"Communications",
            "subcategory":"Film & Video Production",
            "type":"Services"
        }
    ],
    "sg:phone":"+44 1792 298088",
    "sg:postcode":"SA2 7QA",
    "sg:province":"Swansea",
    "sg:tags":[
        "tv"
    ],
    "wof:name":"Proteus",
    "wof:placetype":"venue"
},
  "geometry": {"coordinates":[-4.0344791412,51.6240615845],"type":"Point"}
}