{
  "type": "Feature",
  "properties": {
    "addr:full":"106 Dundee Rd Perth Perth and Kinross PH2 7BA",
    "addr:housenumber":"106",
    "addr:postcode":"ph2 7ba",
    "addr:street":"Dundee Rd",
    "iso:country":"GB",
    "sg:address":"106 Dundee Rd",
    "sg:city":"Perth",
    "sg:classifiers":[
        {
            "category":"Professional",
            "type":"Services"
        },
        {
            "category":"Banks & Credit Unions",
            "subcategory":"Financial Services",
            "type":"Services"
        }
    ],
    "sg:phone":"+44 1738 451440",
    "sg:postcode":"PH2 7BA",
    "sg:province":"Perth and Kinross",
    "sg:tags":[
        "consultant",
        "leasing"
    ],
    "wof:name":"IHM Asset Finance",
    "wof:placetype":"venue"
},
  "geometry": {"coordinates":[-3.418671,56.389351],"type":"Point"}
}