{
  "type": "Feature",
  "properties": {
    "addr:full":"35 Kelston Rd Bath Bath and North East Somerset BA1 3QH",
    "addr:housenumber":"35",
    "addr:postcode":"ba1 3qh",
    "addr:street":"Kelston Rd",
    "iso:country":"GB",
    "sg:address":"35 Kelston Rd",
    "sg:city":"Bath",
    "sg:classifiers":[
        {
            "category":"Autos & Motor Vehicles",
            "subcategory":"Motorcycle Sales",
            "type":"Retail Goods"
        }
    ],
    "sg:phone":"+44 1225 835680",
    "sg:postcode":"BA1 3QH",
    "sg:province":"Bath and North East Somerset",
    "sg:tags":[
        "chauffeur",
        "driven",
        "car"
    ],
    "wof:name":"Luxury Drive",
    "wof:placetype":"venue"
},
  "geometry": {"coordinates":[-2.402309,51.39109],"type":"Point"}
}