{
  "type": "Feature",
  "properties": {
    "addr:full":"Macswysh, Dorchester On Thames Wallingford Oxfordshire OX10 7HN",
    "addr:postcode":"ox10 7hn",
    "iso:country":"GB",
    "sg:address":"Macswysh, Dorchester On Thames",
    "sg:city":"Wallingford",
    "sg:classifiers":[
        {
            "category":"Home & Garden",
            "subcategory":"Building Materials",
            "type":"Retail Goods"
        }
    ],
    "sg:phone":"+44 1865 340079",
    "sg:postcode":"OX10 7HN",
    "sg:province":"Oxfordshire",
    "sg:tags":[
        "brick"
    ],
    "wof:name":"Dorchester Wood Workers & Carvers",
    "wof:placetype":"venue"
},
  "geometry": {"coordinates":[-1.166757,51.645405],"type":"Point"}
}