{
  "type": "Feature",
  "properties": {
    "addr:full":"Alice Munns House, 44 Gravel Hill Ludlow Herefordshire SY8 1QR",
    "addr:housenumber":"44",
    "addr:postcode":"sy8 1qr",
    "addr:street":"Gravel Hill",
    "iso:country":"GB",
    "sg:address":"Alice Munns House, 44 Gravel Hill",
    "sg:city":"Ludlow",
    "sg:classifiers":[
        {
            "category":"Organizations",
            "subcategory":"Non-profit Organization",
            "type":"Services"
        }
    ],
    "sg:phone":"+44 1584 873126",
    "sg:postcode":"SY8 1QR",
    "sg:province":"Herefordshire",
    "sg:tags":[
        "organisation",
        "voluntary",
        "charity"
    ],
    "wof:name":"W R V S",
    "wof:placetype":"venue"
},
  "geometry": {"coordinates":[-2.713184,52.370949],"type":"Point"}
}