{
  "type": "Feature",
  "properties": {
    "addr:full":"Retreat Farm, Broad Lane Markfield Leicestershire LE67 9TB",
    "addr:postcode":"le67 9tb",
    "addr:street":"Broad Lane",
    "iso:country":"GB",
    "sg:address":"Retreat Farm, Broad Lane",
    "sg:city":"Markfield",
    "sg:classifiers":[
        {
            "category":"Transit Center",
            "subcategory":"Passenger",
            "type":"Transportation"
        }
    ],
    "sg:phone":"+44 1530 243385",
    "sg:postcode":"LE67 9TB",
    "sg:province":"Leicestershire",
    "sg:tags":[
        "boarding",
        "kennel",
        "catteries"
    ],
    "wof:name":"Retreat Farm Boarding Kennels",
    "wof:placetype":"venue"
},
  "geometry": {"coordinates":[-1.276934,52.690189],"type":"Point"}
}