{
  "type": "Feature",
  "properties": {
    "iso:country":"GB",
    "sg:address":"2a Market St",
    "sg:city":"Dewsbury",
    "sg:classifiers":[
        {
            "category":"Sports & Exercise",
            "subcategory":"Gym",
            "type":"Entertainment"
        }
    ],
    "sg:phone":"+44 1924 461483",
    "sg:postcode":"WF13 1DB",
    "sg:province":"West Yorkshire",
    "sg:tags":[
        "fitness",
        "health",
        "centre"
    ],
    "wof:name":"Sunspot Sauna",
    "wof:placetype":"venue"
},
  "geometry": {"coordinates":[-1.628925,53.691895],"type":"Point"}
}