{
  "type": "Feature",
  "properties": {
    "addr:full":"Tonge Moor Road Bolton Lancashire BL2 2DJ",
    "addr:postcode":"bl2 2dj",
    "addr:street":"Tonge Moor Road",
    "iso:country":"GB",
    "sg:address":"Tonge Moor Road",
    "sg:city":"Bolton",
    "sg:classifiers":[
        {
            "category":"Wholesale",
            "subcategory":"Non-durable Goods",
            "type":"Manufacturing & Wholesale Goods"
        }
    ],
    "sg:phone":"+44 1204 383733",
    "sg:postcode":"BL2 2DJ",
    "sg:province":"Lancashire",
    "sg:tags":[
        "carry",
        "cash"
    ],
    "wof:name":"Matalan Discount Club",
    "wof:placetype":"venue"
},
  "geometry": {"coordinates":[-2.4117391109,53.5947914124],"type":"Point"}
}