{
  "type": "Feature",
  "properties": {
    "addr:full":"88 Middlesex Street Glasgow Glasgow City G41 1EE",
    "addr:housenumber":"88",
    "addr:postcode":"g41 1ee",
    "addr:street":"Middlesex Street",
    "iso:country":"GB",
    "sg:address":"88 Middlesex Street",
    "sg:city":"Glasgow",
    "sg:classifiers":[
        {
            "category":"Building & Trades",
            "subcategory":"Construction",
            "type":"Services"
        }
    ],
    "sg:phone":"+44 141 420 3620",
    "sg:postcode":"G41 1EE",
    "sg:province":"Glasgow City",
    "sg:tags":[
        "management"
    ],
    "wof:name":"Mace Ltd.",
    "wof:placetype":"venue"
},
  "geometry": {"coordinates":[-4.282719,55.851685],"type":"Point"}
}