{
  "type": "Feature",
  "properties": {
    "addr:full":"Reynards Cl, Chapel Rd, Rotherwas Indstl Est Hereford Herefordshire HR2 6JH",
    "addr:postcode":"hr2 6jh",
    "addr:street":"Cl Chapel Rd;Indstl Est",
    "iso:country":"GB",
    "sg:address":"Reynards Cl, Chapel Rd, Rotherwas Indstl Est",
    "sg:city":"Hereford",
    "sg:classifiers":[
        {
            "category":"Freight",
            "type":"Transportation"
        }
    ],
    "sg:phone":"+44 1432 357050",
    "sg:postcode":"HR2 6JH",
    "sg:province":"Herefordshire",
    "sg:tags":[
        "haulage",
        "road"
    ],
    "wof:name":"John Bevan (Transport) Ltd",
    "wof:placetype":"venue"
},
  "geometry": {"coordinates":[-2.6782240868,52.0390167236],"type":"Point"}
}