{
  "type": "Feature",
  "properties": {
    "addr:full":"Nine Trees Industrial Estate, Morthern Road, Thurcroft Rotherham South Yorkshire S66 9JE",
    "addr:postcode":"s66 9je",
    "addr:street":"Industrial Estate Morthern Road",
    "iso:country":"GB",
    "sg:address":"Nine Trees Industrial Estate, Morthern Road, Thurcroft",
    "sg:city":"Rotherham",
    "sg:classifiers":[
        {
            "category":"Real Estate",
            "subcategory":"Developer",
            "type":"Services"
        }
    ],
    "sg:postcode":"S66 9JE",
    "sg:province":"South Yorkshire",
    "sg:tags":[
        "property"
    ],
    "wof:name":"Universal Properties (South Yorkshire) Ltd.",
    "wof:placetype":"venue"
},
  "geometry": {"coordinates":[-1.257554,53.394321],"type":"Point"}
}