{
  "type": "Feature",
  "properties": {
    "iso:country":"GB",
    "sg:address":"6 Park Rd, Lwr Gornal",
    "sg:city":"Dudley",
    "sg:classifiers":[
        {
            "category":"Food & Beverages",
            "subcategory":"Meat & Fish",
            "type":"Retail Goods"
        }
    ],
    "sg:postcode":"DY3 2JL",
    "sg:province":"Staffordshire",
    "sg:tags":[
        "chip"
    ],
    "wof:name":"Ellowes Fishbar",
    "wof:placetype":"venue"
},
  "geometry": {"coordinates":[-2.130243,52.524914],"type":"Point"}
}