{
  "type": "Feature",
  "properties": {
    "iso:country":"GB",
    "sg:address":"17 Glen-dale Crescent",
    "sg:city":"St Austell",
    "sg:classifiers":[
        {
            "category":"Professional",
            "subcategory":"Accounting & Tax Preparation",
            "type":"Services"
        }
    ],
    "sg:postcode":"PL25 3DD",
    "sg:province":"Cornwall",
    "sg:tags":[
        "accountant"
    ],
    "wof:name":"M Trahair",
    "wof:placetype":"venue"
},
  "geometry": {"coordinates":[-4.765812,50.344757],"type":"Point"}
}