{
  "type": "Feature",
  "properties": {
    "addr:full":"33 Mabel Grove, West Bridgford Nottingham Nottinghamshire NG2 5GT",
    "addr:housenumber":"33",
    "addr:postcode":"ng2 5gt",
    "addr:street":"Mabel Grove",
    "iso:country":"GB",
    "sg:address":"33 Mabel Grove, West Bridgford",
    "sg:city":"Nottingham",
    "sg:classifiers":[
        {
            "category":"Shopping",
            "subcategory":"Pharmacy",
            "type":"Retail Goods"
        }
    ],
    "sg:postcode":"NG2 5GT",
    "sg:province":"Nottinghamshire",
    "sg:tags":[
        "medicine",
        "therapy"
    ],
    "wof:name":"British School of Shiatsu-Do",
    "wof:placetype":"venue"
},
  "geometry": {"coordinates":[-1.1232759953,52.9343719482],"type":"Point"}
}