{
  "type": "Feature",
  "properties": {
    "addr:full":"10 Stanton Av Manchester Greater Manchester M7 3TS",
    "addr:housenumber":"10",
    "addr:postcode":"m7 3ts",
    "addr:street":"Stanton Av",
    "iso:country":"GB",
    "sg:address":"10 Stanton Av",
    "sg:city":"Manchester",
    "sg:classifiers":[
        {
            "category":"Professional",
            "subcategory":"Computer Services",
            "type":"Services"
        }
    ],
    "sg:phone":"+44 161 445 5888",
    "sg:postcode":"M7 3TS",
    "sg:province":"Greater Manchester",
    "sg:tags":[
        "consultant"
    ],
    "wof:name":"Gradlin Ltd",
    "wof:placetype":"venue"
},
  "geometry": {"coordinates":[-2.250172,53.422134],"type":"Point"}
}