{
  "type": "Feature",
  "properties": {
    "addr:full":"57 Brewer Street London Greater London W1F 9UN",
    "addr:housenumber":"57",
    "addr:postcode":"w1f 9un",
    "addr:street":"Brewer Street",
    "iso:country":"GB",
    "sg:address":"57 Brewer Street",
    "sg:city":"London",
    "sg:classifiers":[
        {
            "category":"Shopping",
            "subcategory":"Gifts & Souvenirs",
            "type":"Retail Goods"
        }
    ],
    "sg:phone":"+44 20 7437 3910",
    "sg:postcode":"W1F 9UN",
    "sg:province":"Greater London",
    "sg:tags":[
        "shop"
    ],
    "wof:name":"Anything Left Handed Ltd.",
    "wof:placetype":"venue"
},
  "geometry": {"coordinates":[-0.1354350001,51.5114173889],"type":"Point"}
}