{
  "type": "Feature",
  "properties": {
    "addr:full":"Glebe Farm, Maidford Road, Farthingstone Towcester Buckinghamshire NN12 8HE",
    "addr:postcode":"nn12 8he",
    "addr:street":"Maidford Road",
    "iso:country":"GB",
    "sg:address":"Glebe Farm, Maidford Road, Farthingstone",
    "sg:city":"Towcester",
    "sg:classifiers":[
        {
            "category":"Farming",
            "subcategory":"Farm",
            "type":"Manufacturing & Wholesale Goods"
        }
    ],
    "sg:postcode":"NN12 8HE",
    "sg:province":"Buckinghamshire",
    "sg:tags":[
        "mixed",
        "crop"
    ],
    "wof:name":"G L & J M Bryce",
    "wof:placetype":"venue"
},
  "geometry": {"coordinates":[-1.1031990051,52.1901168823],"type":"Point"}
}