{
  "type": "Feature",
  "properties": {
    "addr:full":"36 High Street, Cheslyn Hay Walsall Staffordshire WS6 7AD",
    "addr:housenumber":"36",
    "addr:postcode":"ws6 7ad",
    "addr:street":"High Street",
    "iso:country":"GB",
    "sg:address":"36 High Street, Cheslyn Hay",
    "sg:city":"Walsall",
    "sg:classifiers":[
        {
            "category":"Professional",
            "subcategory":"Accounting & Tax Preparation",
            "type":"Services"
        }
    ],
    "sg:phone":"+44 1922 414699",
    "sg:postcode":"WS6 7AD",
    "sg:province":"Staffordshire",
    "sg:tags":[
        "accountant"
    ],
    "wof:name":"Silver & Co.",
    "wof:placetype":"venue"
},
  "geometry": {"coordinates":[-2.0336289406,52.6600418091],"type":"Point"}
}