{
  "type": "Feature",
  "properties": {
    "addr:full":"8 High Street Shepton Mallet Somerset BA4 5AN",
    "addr:housenumber":"8",
    "addr:postcode":"ba4 5an",
    "addr:street":"High Street",
    "iso:country":"GB",
    "sg:address":"8 High Street",
    "sg:city":"Shepton Mallet",
    "sg:classifiers":[
        {
            "category":"Food & Beverages",
            "subcategory":"Meat & Fish",
            "type":"Retail Goods"
        }
    ],
    "sg:phone":"+44 1749 343252",
    "sg:postcode":"BA4 5AN",
    "sg:province":"Somerset",
    "sg:tags":[
        "chip"
    ],
    "wof:name":"Steves Fish & Chips",
    "wof:placetype":"venue"
},
  "geometry": {"coordinates":[-2.547661,51.18956],"type":"Point"}
}