{
  "type": "Feature",
  "properties": {
    "addr:full":"25 Seatoller Court, Shaw Street, Royton Oldham Lancashire OL2 6YU",
    "addr:housenumber":"25",
    "addr:postcode":"ol2 6yu",
    "addr:street":"Seatoller Court Shaw Street",
    "iso:country":"GB",
    "sg:address":"25 Seatoller Court, Shaw Street, Royton",
    "sg:city":"Oldham",
    "sg:classifiers":[
        {
            "category":"Organizations",
            "subcategory":"Community Association",
            "type":"Services"
        }
    ],
    "sg:phone":"+44 161 628 2845",
    "sg:postcode":"OL2 6YU",
    "sg:province":"Lancashire",
    "sg:tags":[
        "co-operatives",
        "society",
        "housing",
        "trust"
    ],
    "wof:name":"Northern Counties Housing Association Ltd",
    "wof:placetype":"venue"
},
  "geometry": {"coordinates":[-2.119744,53.565338],"type":"Point"}
}