{
  "type": "Feature",
  "properties": {
    "iso:country":"GB",
    "sg:address":"3 Earlsfield, Holyport Rd",
    "sg:city":"Maidenhead",
    "sg:classifiers":[
        {
            "category":"Shopping",
            "subcategory":"Stationery & Office Supplies",
            "type":"Retail Goods"
        }
    ],
    "sg:postcode":"SL6 2LZ",
    "sg:province":"Berkshire",
    "sg:tags":[
        "box",
        "carton"
    ],
    "wof:name":"Boxit Packaging Co",
    "wof:placetype":"venue"
},
  "geometry": {"coordinates":[-0.703711,51.498863],"type":"Point"}
}