{
  "type": "Feature",
  "properties": {
    "addr:full":"1 Fleming Road, London Industrial Estate Newbury Berkshire RG13 2DE",
    "addr:housenumber":"1;estate",
    "addr:postcode":"rg13 2de",
    "addr:street":"Fleming Road;Industrial",
    "iso:country":"GB",
    "sg:address":"1 Fleming Road, London Industrial Estate",
    "sg:city":"Newbury",
    "sg:classifiers":[
        {
            "category":"Autos & Motor Vehicles",
            "subcategory":"Auto Supplies",
            "type":"Retail Goods"
        }
    ],
    "sg:phone":"+44 1635 46195",
    "sg:postcode":"RG13 2DE",
    "sg:province":"Berkshire",
    "sg:tags":[
        "component"
    ],
    "wof:name":"Partco Autoparts",
    "wof:placetype":"venue"
},
  "geometry": {"coordinates":[-1.3258700371,51.4058685303],"type":"Point"}
}