{
  "type": "Feature",
  "properties": {
    "addr:full":"Mead Road Chislehurst Kent BR7 6AD",
    "addr:postcode":"br7 6ad",
    "addr:street":"Mead Road",
    "iso:country":"GB",
    "sg:address":"Mead Road",
    "sg:city":"Chislehurst",
    "sg:classifiers":[
        {
            "category":"Education",
            "subcategory":"School",
            "type":"Public Place"
        }
    ],
    "sg:phone":"+44 20 8467 1730",
    "sg:postcode":"BR7 6AD",
    "sg:province":"Kent",
    "sg:tags":[
        "local",
        "authority"
    ],
    "wof:name":"Mead Road Infant School",
    "wof:placetype":"venue"
},
  "geometry": {"coordinates":[0.0707800016,51.418926239],"type":"Point"}
}