{
  "type": "Feature",
  "properties": {
    "addr:full":"51 Waters Road London Greater London SE6 1UF",
    "addr:housenumber":"51",
    "addr:postcode":"se6 1uf",
    "addr:street":"Waters Road",
    "iso:country":"GB",
    "sg:address":"51 Waters Road",
    "sg:city":"London",
    "sg:classifiers":[
        {
            "category":"Home & Garden",
            "subcategory":"Household Appliances",
            "type":"Retail Goods"
        }
    ],
    "sg:postcode":"SE6 1UF",
    "sg:province":"Greater London",
    "sg:tags":[
        "refrigeration",
        "air conditioning"
    ],
    "wof:name":"R T Refrigeration",
    "wof:placetype":"venue"
},
  "geometry": {"coordinates":[0.001823,51.432983],"type":"Point"}
}