{
  "type": "Feature",
  "properties": {
    "iso:country":"GB",
    "sg:address":"1 America Street",
    "sg:city":"London",
    "sg:classifiers":[
        {
            "category":"Organizations",
            "subcategory":"Non-profit Organization",
            "type":"Services"
        }
    ],
    "sg:phone":"+44 20 7902 1060",
    "sg:postcode":"SE1 0NE",
    "sg:province":"Greater London",
    "sg:tags":[
        "organisation",
        "voluntary",
        "charity"
    ],
    "wof:name":"The National Foundation for Youth Music",
    "wof:placetype":"venue"
},
  "geometry": {"coordinates":[-0.0962830037,51.504524231],"type":"Point"}
}