{
  "type": "Feature",
  "properties": {
    "addr:full":"4 Seymour Chase Knutsford Cheshire WA16 9BY",
    "addr:housenumber":"4",
    "addr:postcode":"wa16 9by",
    "addr:street":"Seymour Chase",
    "iso:country":"GB",
    "sg:address":"4 Seymour Chase",
    "sg:city":"Knutsford",
    "sg:classifiers":[
        {
            "category":"Building & Trades",
            "subcategory":"Construction",
            "type":"Services"
        }
    ],
    "sg:phone":"+44 1565 652890",
    "sg:postcode":"WA16 9BY",
    "sg:province":"Cheshire",
    "sg:tags":[
        "roofing"
    ],
    "wof:name":"K J Keogh Roofing",
    "wof:placetype":"venue"
},
  "geometry": {"coordinates":[-2.3690838814,53.2945175171],"type":"Point"}
}