{
  "type": "Feature",
  "properties": {
    "addr:full":"70 Midland Road Swadlincote Derbyshire DE11 0AW",
    "addr:housenumber":"70",
    "addr:postcode":"de11 0aw",
    "addr:street":"Midland Road",
    "iso:country":"GB",
    "sg:address":"70 Midland Road",
    "sg:city":"Swadlincote",
    "sg:classifiers":[
        {
            "category":"Home & Garden",
            "subcategory":"Hardware",
            "type":"Retail Goods"
        }
    ],
    "sg:phone":"+44 1283 217621",
    "sg:postcode":"DE11 0AW",
    "sg:province":"Derbyshire",
    "sg:tags":[
        "lawnmowers",
        "machinery"
    ],
    "wof:name":"J Flintham",
    "wof:placetype":"venue"
},
  "geometry": {"coordinates":[-1.557221,52.778938],"type":"Point"}
}