{
  "type": "Feature",
  "properties": {
    "iso:country":"GB",
    "sg:address":"Somerfields House, Narrow Lane, Belchford",
    "sg:city":"Horncastle",
    "sg:classifiers":[
        {
            "category":"Farming",
            "subcategory":"Poultry Farm",
            "type":"Manufacturing & Wholesale Goods"
        }
    ],
    "sg:phone":"+44 1507 533676",
    "sg:postcode":"LN9 6LE",
    "sg:province":"Lincolnshire",
    "sg:tags":[
        "game"
    ],
    "wof:name":"L J Fairburn & Son",
    "wof:placetype":"venue"
},
  "geometry": {"coordinates":[-0.055695001,53.2593650818],"type":"Point"}
}