{
  "type": "Feature",
  "properties": {
    "iso:country":"GB",
    "sg:address":", Culmhead",
    "sg:city":"Taunton",
    "sg:classifiers":[
        {
            "category":"Bars & Pubs",
            "type":"Food & Drink"
        }
    ],
    "sg:phone":"+44 1823 421432",
    "sg:postcode":"TA3 7EA",
    "sg:province":"Devon",
    "sg:tags":[
        "pubs",
        "inn"
    ],
    "wof:name":"The Holman Clavel Inn",
    "wof:placetype":"venue"
},
  "geometry": {"coordinates":[-3.12671,50.943935],"type":"Point"}
}