{
  "type": "Feature",
  "properties": {
    "iso:country":"GB",
    "sg:address":"1 Haywra Street",
    "sg:city":"Harrogate",
    "sg:classifiers":[
        {
            "category":"Social Services",
            "type":"Services"
        },
        {
            "category":"Government",
            "subcategory":"Office",
            "type":"Public Place"
        }
    ],
    "sg:phone":"+44 1423 505049",
    "sg:postcode":"HG1 5BJ",
    "sg:province":"North Yorkshire",
    "sg:tags":[
        "local"
    ],
    "wof:name":"Children & Families Services",
    "wof:placetype":"venue"
},
  "geometry": {"coordinates":[-1.5366590023,53.9946289062],"type":"Point"}
}