{
  "type": "Feature",
  "properties": {
    "addr:full":"9 Haynes Road Leicester Leicestershire LE5 4AR",
    "addr:housenumber":"9",
    "addr:postcode":"le5 4ar",
    "addr:street":"Haynes Road",
    "iso:country":"GB",
    "sg:address":"9 Haynes Road",
    "sg:city":"Leicester",
    "sg:classifiers":[
        {
            "category":"Retail",
            "subcategory":"Storage",
            "type":"Services"
        }
    ],
    "sg:phone":"+44 116 276 7545",
    "sg:postcode":"LE5 4AR",
    "sg:province":"Leicestershire",
    "sg:tags":[
        "household",
        "removal"
    ],
    "wof:name":"Andrews Bros",
    "wof:placetype":"venue"
},
  "geometry": {"coordinates":[-1.094113946,52.6417961121],"type":"Point"}
}