{
  "type": "Feature",
  "properties": {
    "iso:country":"GB",
    "sg:address":"447 High Rd",
    "sg:city":"North Finchley",
    "sg:classifiers":[
        {
            "category":"Professional",
            "subcategory":"Business Services",
            "type":"Services"
        }
    ],
    "sg:phone":"+44 20 8371 9981",
    "sg:postcode":"N12 0AZ",
    "sg:province":"Greater London",
    "sg:tags":[
        "import",
        "export",
        "agent"
    ],
    "wof:name":"Signet Enterprises Ltd",
    "wof:placetype":"venue"
},
  "geometry": {"coordinates":[-0.1748179942,51.6033935547],"type":"Point"}
}