{
  "type": "Feature",
  "properties": {
    "iso:country":"GB",
    "sg:address":"Little Horton Lane",
    "sg:city":"Bradford",
    "sg:classifiers":[
        {
            "category":"Bars & Pubs",
            "type":"Food & Drink"
        }
    ],
    "sg:phone":"+44 1274 521501",
    "sg:postcode":"BD5 9EJ",
    "sg:province":"West Yorkshire",
    "sg:tags":[
        "pubs",
        "inn"
    ],
    "wof:name":"Black Horse Hotel",
    "wof:placetype":"venue"
},
  "geometry": {"coordinates":[-1.767074,53.778511],"type":"Point"}
}