{
  "type": "Feature",
  "properties": {
    "iso:country":"GB",
    "sg:address":"Unit 17, Beeching Park Industrial Estate, Wainwright Road",
    "sg:city":"Bexhill-on-sea",
    "sg:classifiers":[
        {
            "category":"Wholesale",
            "subcategory":"Electrical",
            "type":"Manufacturing & Wholesale Goods"
        },
        {
            "category":"Shopping",
            "subcategory":"Computers & Home Electronics",
            "type":"Retail Goods"
        }
    ],
    "sg:phone":"+44 1424 225881",
    "sg:postcode":"TN39 3UR",
    "sg:province":"East Sussex",
    "sg:tags":[
        "wholesaler"
    ],
    "wof:name":"L & G Wholesale Electric",
    "wof:placetype":"venue"
},
  "geometry": {"coordinates":[0.4657869935,50.8416786194],"type":"Point"}
}