{
  "type": "Feature",
  "properties": {
    "addr:full":"6 Farnham Business Centre, Dogflud Way Farnham Surrey GU9 7UP",
    "addr:housenumber":"6",
    "addr:postcode":"gu9 7up",
    "addr:street":"Dogflud Way",
    "iso:country":"GB",
    "sg:address":"6 Farnham Business Centre, Dogflud Way",
    "sg:city":"Farnham",
    "sg:classifiers":[
        {
            "category":"Wholesale",
            "subcategory":"Construction Materials",
            "type":"Manufacturing & Wholesale Goods"
        }
    ],
    "sg:phone":"+44 1252 727262",
    "sg:postcode":"GU9 7UP",
    "sg:province":"Surrey",
    "sg:tags":[
        "merchant",
        "glass"
    ],
    "wof:name":"Allways Glazing Works Ltd",
    "wof:placetype":"venue"
},
  "geometry": {"coordinates":[-0.800837,51.214321],"type":"Point"}
}