{
  "type": "Feature",
  "properties": {
    "addr:full":"62 Bucknalls Drive, Bricket Wood St Albans Hertfordshire AL2 3XL",
    "addr:housenumber":"62",
    "addr:postcode":"al2 3xl",
    "addr:street":"Bucknalls Drive Bricket Wood",
    "iso:country":"GB",
    "sg:address":"62 Bucknalls Drive, Bricket Wood",
    "sg:city":"St Albans",
    "sg:classifiers":[
        {
            "category":"Farming",
            "subcategory":"Livestock Farm",
            "type":"Manufacturing & Wholesale Goods"
        }
    ],
    "sg:phone":"+44 1923 677734",
    "sg:postcode":"AL2 3XL",
    "sg:province":"Hertfordshire",
    "sg:tags":[
        "others"
    ],
    "wof:name":"Karobar Koi",
    "wof:placetype":"venue"
},
  "geometry": {"coordinates":[-0.3725480139,51.7022323608],"type":"Point"}
}