{
  "type": "Feature",
  "properties": {
    "addr:full":"High Street, Rothbury Morpeth Northumberland NE65 7UG",
    "addr:postcode":"ne65 7ug",
    "addr:street":"High Street",
    "iso:country":"GB",
    "sg:address":"High Street, Rothbury",
    "sg:city":"Morpeth",
    "sg:classifiers":[
        {
            "category":"Retail",
            "subcategory":"Veterinary Services",
            "type":"Services"
        }
    ],
    "sg:phone":"+44 1669 620638",
    "sg:postcode":"NE65 7UG",
    "sg:province":"Northumberland",
    "sg:tags":[
        "surgeon"
    ],
    "wof:name":"Simonside Veterinary Centre",
    "wof:placetype":"venue"
},
  "geometry": {"coordinates":[-1.9139939547,55.3092536926],"type":"Point"}
}