{
  "type": "Feature",
  "properties": {
    "iso:country":"GB",
    "sg:address":"5a Victoria Road",
    "sg:city":"Tamworth",
    "sg:classifiers":[
        {
            "category":"Professional",
            "subcategory":"Computer Services",
            "type":"Services"
        }
    ],
    "sg:phone":"+44 1827 60464",
    "sg:postcode":"B79 7HL",
    "sg:province":"Staffordshire",
    "sg:tags":[
        "information"
    ],
    "wof:name":"Property Data Services",
    "wof:placetype":"venue"
},
  "geometry": {"coordinates":[-1.689354,52.635361],"type":"Point"}
}