{
  "type": "Feature",
  "properties": {
    "iso:country":"GB",
    "sg:address":"344 Hoe Street",
    "sg:city":"London",
    "sg:classifiers":[
        {
            "category":"Organizations",
            "subcategory":"Non-profit Organization",
            "type":"Services"
        }
    ],
    "sg:phone":"+44 20 8509 0119",
    "sg:postcode":"E17 9PX",
    "sg:province":"Greater London",
    "sg:tags":[
        "organisation",
        "voluntary",
        "charity"
    ],
    "wof:name":"Waltham Forest Family Service Unit",
    "wof:placetype":"venue"
},
  "geometry": {"coordinates":[-0.0186330006,51.580368042],"type":"Point"}
}