{
  "type": "Feature",
  "properties": {
    "addr:full":"27 Wellfield Road Cardiff Cardiff CF24 3NZ",
    "addr:housenumber":"27",
    "addr:postcode":"cf24 3nz",
    "addr:street":"Wellfield Road",
    "iso:country":"GB",
    "sg:address":"27 Wellfield Road",
    "sg:city":"Cardiff",
    "sg:classifiers":[
        {
            "category":"Retail",
            "subcategory":"Photofinishing",
            "type":"Services"
        }
    ],
    "sg:postcode":"CF24 3NZ",
    "sg:province":"Cardiff",
    "sg:tags":[
        "photographic",
        "processor"
    ],
    "wof:name":"Klick Photopoint",
    "wof:placetype":"venue"
},
  "geometry": {"coordinates":[-3.1657099724,51.4952507019],"type":"Point"}
}