{
  "type": "Feature",
  "properties": {
    "addr:full":"The Street, Chilham Canterbury Kent CT4 8BX",
    "addr:postcode":"ct4 8bx",
    "addr:street":"The Street",
    "iso:country":"GB",
    "sg:address":"The Street, Chilham",
    "sg:city":"Canterbury",
    "sg:classifiers":[
        {
            "category":"Government",
            "subcategory":"Post Office",
            "type":"Public Place"
        }
    ],
    "sg:phone":"+44 1227 730261",
    "sg:postcode":"CT4 8BX",
    "sg:province":"Kent",
    "wof:name":"Chilham PO",
    "wof:placetype":"venue"
},
  "geometry": {"coordinates":[0.9637389779,51.2438812256],"type":"Point"}
}