{
  "type": "Feature",
  "properties": {
    "addr:full":"16 Market Pl Banbury Oxfordshire OX16 8LL",
    "addr:housenumber":"16",
    "addr:postcode":"ox16 8ll",
    "addr:street":"Market Pl",
    "iso:country":"GB",
    "sg:address":"16 Market Pl",
    "sg:city":"Banbury",
    "sg:classifiers":[
        {
            "category":"Shopping",
            "subcategory":"Used Merchandise",
            "type":"Retail Goods"
        }
    ],
    "sg:phone":"+44 1295 262421",
    "sg:postcode":"OX16 8LL",
    "sg:province":"Oxfordshire",
    "sg:tags":[
        "shop",
        "second-hand"
    ],
    "wof:name":"Cargo Carpenter's",
    "wof:placetype":"venue"
},
  "geometry": {"coordinates":[-1.33517,52.062309],"type":"Point"}
}