{
  "type": "Feature",
  "properties": {
    "addr:full":"Occupational Health Department, Mountain View, Penrhos Rd Bangor Gwynedd LL57 2NA",
    "addr:postcode":"ll57 2na",
    "addr:street":"Penrhos Rd",
    "iso:country":"GB",
    "sg:address":"Occupational Health Department, Mountain View, Penrhos Rd",
    "sg:city":"Bangor",
    "sg:classifiers":[
        {
            "category":"Health Services",
            "subcategory":"Hospital",
            "type":"Services"
        }
    ],
    "sg:phone":"+44 1248 351127",
    "sg:postcode":"LL57 2NA",
    "sg:province":"Gwynedd",
    "wof:name":"Gwynedd Hospitals NHS Trust",
    "wof:placetype":"venue"
},
  "geometry": {"coordinates":[-4.126064,53.229595],"type":"Point"}
}