{
  "type": "Feature",
  "properties": {
    "iso:country":"GB",
    "sg:address":"51d Garratts Way",
    "sg:city":"High Wycombe",
    "sg:classifiers":[
        {
            "category":"Building & Trades",
            "subcategory":"Cleaning & Sanitation",
            "type":"Services"
        }
    ],
    "sg:phone":"+44 1494 471136",
    "sg:postcode":"HP13 5AH",
    "sg:province":"Buckinghamshire",
    "sg:tags":[
        "commercial"
    ],
    "wof:name":"Accolade Cleaning Services",
    "wof:placetype":"venue"
},
  "geometry": {"coordinates":[-0.7582389712,51.6346740723],"type":"Point"}
}