{
  "type": "Feature",
  "properties": {
    "iso:country":"GB",
    "sg:address":"4 Alice Gardens",
    "sg:city":"Llandudno",
    "sg:classifiers":[
        {
            "category":"Building & Trades",
            "subcategory":"Construction",
            "type":"Services"
        }
    ],
    "sg:phone":"+44 1492 879229",
    "sg:postcode":"LL30 1UF",
    "sg:province":"Conwy",
    "sg:tags":[
        "roofing"
    ],
    "wof:name":"T & M Pritchard",
    "wof:placetype":"venue"
},
  "geometry": {"coordinates":[-3.813419,53.315655],"type":"Point"}
}