{
  "type": "Feature",
  "properties": {
    "iso:country":"GB",
    "sg:address":"Charles Berry House, 45 East Bond Street",
    "sg:city":"Leicester",
    "sg:classifiers":[
        {
            "category":"Insurance",
            "subcategory":"Insurance Agent",
            "type":"Services"
        }
    ],
    "sg:phone":"+44 116 222 8222",
    "sg:postcode":"LE1 4SX",
    "sg:province":"Leicestershire",
    "sg:tags":[
        "broker"
    ],
    "wof:name":"Brett & Randall Marine Insurance Brokers Ltd.",
    "wof:placetype":"venue"
},
  "geometry": {"coordinates":[-1.1361060143,52.6377258301],"type":"Point"}
}