{
  "type": "Feature",
  "properties": {
    "addr:full":"13 Orme Street Blackpool Lancashire FY1 4AL",
    "addr:housenumber":"13",
    "addr:postcode":"fy1 4al",
    "addr:street":"Orme Street",
    "iso:country":"GB",
    "sg:address":"13 Orme Street",
    "sg:city":"Blackpool",
    "sg:classifiers":[
        {
            "category":"Freight",
            "type":"Transportation"
        }
    ],
    "sg:postcode":"FY1 4AL",
    "sg:province":"Lancashire",
    "sg:tags":[
        "haulage",
        "road"
    ],
    "wof:name":"G A Kirk (West Coast Traction)",
    "wof:placetype":"venue"
},
  "geometry": {"coordinates":[-3.043595,53.811066],"type":"Point"}
}