{
  "type": "Feature",
  "properties": {
    "iso:country":"GB",
    "sg:address":"246 Soho Rd",
    "sg:city":"Birmingham",
    "sg:classifiers":[
        {
            "category":"Shopping",
            "subcategory":"Clothing, Apparel, & Fashions",
            "type":"Retail Goods"
        }
    ],
    "sg:phone":"+44 121 554 4113",
    "sg:postcode":"B21 9LR",
    "sg:province":"West Midlands",
    "sg:tags":[
        "clothing"
    ],
    "wof:name":"Branch Bros",
    "wof:placetype":"venue"
},
  "geometry": {"coordinates":[-1.9364689589,52.5038375854],"type":"Point"}
}