{
  "type": "Feature",
  "properties": {
    "addr:full":"Riclyn House, Flitch Industrial Estate, Chelmsford Road Dunmow Essex CM6 1XJ",
    "addr:postcode":"cm6 1xj",
    "addr:street":"Flitch Industrial Estate Chelmsford Road",
    "iso:country":"GB",
    "sg:address":"Riclyn House, Flitch Industrial Estate, Chelmsford Road",
    "sg:city":"Dunmow",
    "sg:classifiers":[
        {
            "category":"Manufacturing",
            "subcategory":"Rubber & Plastics",
            "type":"Manufacturing & Wholesale Goods"
        }
    ],
    "sg:phone":"+44 1371 876681",
    "sg:postcode":"CM6 1XJ",
    "sg:province":"Essex",
    "sg:tags":[
        "injection",
        "moulding"
    ],
    "wof:name":"Precision Moulded Products (Essex) Ltd.",
    "wof:placetype":"venue"
},
  "geometry": {"coordinates":[0.365555,51.86731],"type":"Point"}
}