{
  "type": "Feature",
  "properties": {
    "addr:full":"Pivington Mill, Pluckley Ashford Kent TN27 0PG",
    "addr:postcode":"tn27 0pg",
    "iso:country":"GB",
    "sg:address":"Pivington Mill, Pluckley",
    "sg:city":"Ashford",
    "sg:classifiers":[
        {
            "category":"Utilities",
            "subcategory":"Refuse",
            "type":"Services"
        }
    ],
    "sg:phone":"+44 1233 840624",
    "sg:postcode":"TN27 0PG",
    "sg:province":"Kent",
    "sg:tags":[
        "disposal",
        "waste"
    ],
    "wof:name":"Sucklifts Ltd.",
    "wof:placetype":"venue"
},
  "geometry": {"coordinates":[0.755068,51.176594],"type":"Point"}
}