{
  "type": "Feature",
  "properties": {
    "iso:country":"GB",
    "sg:address":"Thorntrees Service Station, Wigan Road",
    "sg:city":"Preston",
    "sg:classifiers":[
        {
            "category":"Building & Trades",
            "subcategory":"Electrical",
            "type":"Services"
        }
    ],
    "sg:phone":"+44 1772 621888",
    "sg:postcode":"PR5 2SB",
    "sg:province":"Lancashire",
    "sg:tags":[
        "lighting"
    ],
    "wof:name":"Karl Fryer",
    "wof:placetype":"venue"
},
  "geometry": {"coordinates":[-2.63084,53.745762],"type":"Point"}
}