{
  "type": "Feature",
  "properties": {
    "iso:country":"GB",
    "sg:address":"23 St. Johns Rd, Wallasey Village",
    "sg:city":"Wallasey",
    "sg:classifiers":[
        {
            "category":"Shopping",
            "subcategory":"Photographic Equipment",
            "type":"Retail Goods"
        }
    ],
    "sg:phone":"+44 151 639 8490",
    "sg:postcode":"CH45 3LU",
    "sg:province":"Merseyside",
    "wof:name":"Steve Jones Photography",
    "wof:placetype":"venue"
},
  "geometry": {"coordinates":[-3.06367,53.423862],"type":"Point"}
}