{
  "type": "Feature",
  "properties": {
    "addr:full":"8 Moorefide Road, Heaton Moor Stockport Cheshire SK4 4DT",
    "addr:housenumber":"8",
    "addr:postcode":"sk4 4dt",
    "addr:street":"Moorefide Road",
    "iso:country":"GB",
    "sg:address":"8 Moorefide Road, Heaton Moor",
    "sg:city":"Stockport",
    "sg:classifiers":[
        {
            "category":"Food & Beverages",
            "subcategory":"Meat & Fish",
            "type":"Retail Goods"
        }
    ],
    "sg:phone":"+44 161 442 8043",
    "sg:postcode":"SK4 4DT",
    "sg:province":"Cheshire",
    "sg:tags":[
        "chip"
    ],
    "wof:name":"Double Happiness",
    "wof:placetype":"venue"
},
  "geometry": {"coordinates":[-2.1896100044,53.4164810181],"type":"Point"}
}