{
  "type": "Feature",
  "properties": {
    "addr:full":"5-7 Upper Brook Street Rugeley Staffordshire WS15 2DP",
    "addr:housenumber":"5-7",
    "addr:postcode":"ws15 2dp",
    "addr:street":"Upper Brook Street",
    "iso:country":"GB",
    "sg:address":"5-7 Upper Brook Street",
    "sg:city":"Rugeley",
    "sg:classifiers":[
        {
            "category":"Freight",
            "type":"Transportation"
        }
    ],
    "sg:phone":"+44 1889 586148",
    "sg:postcode":"WS15 2DP",
    "sg:province":"Staffordshire",
    "sg:tags":[
        "forwarders"
    ],
    "wof:name":"A Hartrodt U K",
    "wof:placetype":"venue"
},
  "geometry": {"coordinates":[-1.94036,52.754429],"type":"Point"}
}