{
  "type": "Feature",
  "properties": {
    "addr:full":"11 Dorward Road Montrose Aberdeenshire DD10 8SB",
    "addr:housenumber":"11",
    "addr:postcode":"dd10 8sb",
    "addr:street":"Dorward Road",
    "iso:country":"GB",
    "sg:address":"11 Dorward Road",
    "sg:city":"Montrose",
    "sg:classifiers":[
        {
            "category":"Travel",
            "subcategory":"Hotels & Motels",
            "type":"Entertainment"
        }
    ],
    "sg:phone":"+44 1674 672273",
    "sg:postcode":"DD10 8SB",
    "sg:province":"Aberdeenshire",
    "sg:tags":[
        "house",
        "guest"
    ],
    "wof:name":"Linksgate Guest House",
    "wof:placetype":"venue"
},
  "geometry": {"coordinates":[-2.4592239857,56.7159004211],"type":"Point"}
}