{
  "type": "Feature",
  "properties": {
    "addr:full":"9 Chalklands, Sandon Chelmsford Essex CM2 7TH",
    "addr:housenumber":"9",
    "addr:postcode":"cm2 7th",
    "addr:street":"Chalklands Sandon",
    "iso:country":"GB",
    "sg:address":"9 Chalklands, Sandon",
    "sg:city":"Chelmsford",
    "sg:classifiers":[
        {
            "category":"Professional",
            "type":"Services"
        }
    ],
    "sg:phone":"+44 1245 471589",
    "sg:postcode":"CM2 7TH",
    "sg:province":"Essex",
    "sg:tags":[
        "writer"
    ],
    "wof:name":"Electrotech Services",
    "wof:placetype":"venue"
},
  "geometry": {"coordinates":[0.527858,51.699455],"type":"Point"}
}