{
  "type": "Feature",
  "properties": {
    "iso:country":"GB",
    "sg:address":"701 High Rd",
    "sg:city":"Tottenham",
    "sg:classifiers":[
        {
            "category":"Home & Garden",
            "subcategory":"Household Appliances",
            "type":"Retail Goods"
        }
    ],
    "sg:phone":"+44 20 8801 7575",
    "sg:postcode":"N17 8AD",
    "sg:province":"Greater London",
    "sg:tags":[
        "domestic",
        "centre"
    ],
    "wof:name":"Q & B",
    "wof:placetype":"venue"
},
  "geometry": {"coordinates":[-0.068069,51.600891],"type":"Point"}
}