{
  "type": "Feature",
  "properties": {
    "addr:full":"3 Potters Cross, Iver Heath Iver Berkshire SL0 0BS",
    "addr:housenumber":"3",
    "addr:postcode":"sl0 0bs",
    "addr:street":"Potters Cross",
    "iso:country":"GB",
    "sg:address":"3 Potters Cross, Iver Heath",
    "sg:city":"Iver",
    "sg:classifiers":[
        {
            "category":"Freight",
            "type":"Transportation"
        }
    ],
    "sg:phone":"+44 20 8573 0005",
    "sg:postcode":"SL0 0BS",
    "sg:province":"Berkshire",
    "sg:tags":[
        "haulage",
        "road"
    ],
    "wof:name":"Shirlstar Container Transport Ltd.",
    "wof:placetype":"venue"
},
  "geometry": {"coordinates":[-0.515699,51.53587],"type":"Point"}
}