{
  "type": "Feature",
  "properties": {
    "addr:full":"27 Pleshey Road, Fordend Chelmsford Essex CM3 1LF",
    "addr:housenumber":"27",
    "addr:postcode":"cm3 1lf",
    "addr:street":"Pleshey Road Fordend",
    "iso:country":"GB",
    "sg:address":"27 Pleshey Road, Fordend",
    "sg:city":"Chelmsford",
    "sg:classifiers":[
        {
            "category":"Building & Trades",
            "subcategory":"Construction",
            "type":"Services"
        }
    ],
    "sg:phone":"+44 1245 237342",
    "sg:postcode":"CM3 1LF",
    "sg:province":"Essex",
    "sg:tags":[
        "builder"
    ],
    "wof:name":"M & C Rayner Builders",
    "wof:placetype":"venue"
},
  "geometry": {"coordinates":[0.431164,51.824062],"type":"Point"}
}