{
  "type": "Feature",
  "properties": {
    "addr:full":"2 Court Gardens Yeovil Somerset BA21 3LZ",
    "addr:housenumber":"2",
    "addr:postcode":"ba21 3lz",
    "addr:street":"Court Gardens",
    "iso:country":"GB",
    "sg:address":"2 Court Gardens",
    "sg:city":"Yeovil",
    "sg:classifiers":[
        {
            "category":"Professional",
            "subcategory":"Engineering",
            "type":"Services"
        }
    ],
    "sg:phone":"+44 1935 479282",
    "sg:postcode":"BA21 3LZ",
    "sg:province":"Somerset",
    "sg:tags":[
        "civil",
        "engineer"
    ],
    "wof:name":"JOHN G A PRICE",
    "wof:placetype":"venue"
},
  "geometry": {"coordinates":[-2.6542429924,50.9562644958],"type":"Point"}
}