{
  "type": "Feature",
  "properties": {
    "addr:full":"1-2 Hanover Street London Greater London W1S 1YZ",
    "addr:housenumber":"1-2",
    "addr:postcode":"w1s 1yz",
    "addr:street":"Hanover Street",
    "iso:country":"GB",
    "sg:address":"1-2 Hanover Street",
    "sg:city":"London",
    "sg:classifiers":[
        {
            "category":"Recreation",
            "subcategory":"Gun Range",
            "type":"Entertainment"
        }
    ],
    "sg:phone":"+44 20 7629 9777",
    "sg:postcode":"W1S 1YZ",
    "sg:province":"Greater London",
    "sg:tags":[
        "operator",
        "tour"
    ],
    "wof:name":"Motion Europe Ltd.",
    "wof:placetype":"venue"
},
  "geometry": {"coordinates":[-0.141681999,51.5140533447],"type":"Point"}
}