{
  "type": "Feature",
  "properties": {
    "iso:country":"GB",
    "sg:address":"High St",
    "sg:city":"Barmouth",
    "sg:classifiers":[
        {
            "category":"Bars & Pubs",
            "type":"Food & Drink"
        }
    ],
    "sg:phone":"+44 1341 281007",
    "sg:postcode":"LL42 1DP",
    "sg:province":"Gwynedd",
    "sg:tags":[
        "pubs",
        "inn"
    ],
    "wof:name":"Cors Y Gedol Fun Bar",
    "wof:placetype":"venue"
},
  "geometry": {"coordinates":[-4.055159,52.722664],"type":"Point"}
}