{
  "type": "Feature",
  "properties": {
    "iso:country":"GB",
    "sg:address":"23 Verne Drive",
    "sg:city":"Oldham",
    "sg:classifiers":[
        {
            "category":"Professional",
            "subcategory":"Research",
            "type":"Services"
        },
        {
            "category":"Organizations",
            "subcategory":"Non-profit Organization",
            "type":"Services"
        }
    ],
    "sg:phone":"+44 161 678 8281",
    "sg:postcode":"OL1 4RF",
    "sg:province":"Lancashire",
    "sg:tags":[
        "organisation",
        "voluntary",
        "market",
        "charity"
    ],
    "wof:name":"Sholver Tenants Management Organisation Ltd.",
    "wof:placetype":"venue"
},
  "geometry": {"coordinates":[-2.070885,53.569092],"type":"Point"}
}