{
  "type": "Feature",
  "properties": {
    "iso:country":"GB",
    "sg:address":"21 Vineyard Hill Road",
    "sg:city":"London",
    "sg:classifiers":[
        {
            "category":"Government",
            "subcategory":"Office",
            "type":"Public Place"
        }
    ],
    "sg:phone":"+44 20 8946 4433",
    "sg:postcode":"SW19 7JL",
    "sg:province":"Greater London",
    "sg:tags":[
        "education",
        "agency",
        "authority"
    ],
    "wof:name":"Montessori Education (Uk)",
    "wof:placetype":"venue"
},
  "geometry": {"coordinates":[-0.2026370019,51.4301834106],"type":"Point"}
}