{
  "type": "Feature",
  "properties": {
    "addr:full":"4 Station Rd Mansfield Derbyshire NG20 8SY",
    "addr:housenumber":"4",
    "addr:postcode":"ng20 8sy",
    "addr:street":"Station Rd",
    "iso:country":"GB",
    "sg:address":"4 Station Rd",
    "sg:city":"Mansfield",
    "sg:classifiers":[
        {
            "category":"Manufacturing",
            "subcategory":"Signs",
            "type":"Manufacturing & Wholesale Goods"
        }
    ],
    "sg:phone":"+44 1623 748195",
    "sg:postcode":"NG20 8SY",
    "sg:province":"Derbyshire",
    "sg:tags":[
        "nameplate"
    ],
    "wof:name":"Signal Signs",
    "wof:placetype":"venue"
},
  "geometry": {"coordinates":[-1.2155749798,53.2138595581],"type":"Point"}
}