{
  "type": "Feature",
  "properties": {
    "addr:full":"The Little Smithy, Village Road, Childs Ercall Market Drayton Shropshire TF9 2BZ",
    "addr:postcode":"tf9 2bz",
    "addr:street":"Village Road",
    "iso:country":"GB",
    "sg:address":"The Little Smithy, Village Road, Childs Ercall",
    "sg:city":"Market Drayton",
    "sg:classifiers":[
        {
            "category":"Retail",
            "subcategory":"Driving School",
            "type":"Services"
        }
    ],
    "sg:phone":"+44 1952 840304",
    "sg:postcode":"TF9 2BZ",
    "sg:province":"Shropshire",
    "wof:name":"V M Gibbs",
    "wof:placetype":"venue"
},
  "geometry": {"coordinates":[-2.4943039417,52.8222732544],"type":"Point"}
}