{
  "type": "Feature",
  "properties": {
    "addr:full":"Foxwood Drive, Elm Tree Farm Stockton-on-tees Durham TS19 0XT",
    "addr:postcode":"ts19 0xt",
    "addr:street":"Foxwood Drive Elm Tree",
    "iso:country":"GB",
    "sg:address":"Foxwood Drive, Elm Tree Farm",
    "sg:city":"Stockton-on-tees",
    "sg:classifiers":[
        {
            "category":"Social Services",
            "subcategory":"Adult Care",
            "type":"Services"
        }
    ],
    "sg:phone":"+44 1642 671967",
    "sg:postcode":"TS19 0XT",
    "sg:province":"Durham",
    "sg:tags":[
        "housing",
        "sheltered"
    ],
    "wof:name":"Cedar House",
    "wof:placetype":"venue"
},
  "geometry": {"coordinates":[-1.3488160372,54.574634552],"type":"Point"}
}