{
  "type": "Feature",
  "properties": {
    "iso:country":"GB",
    "sg:address":"Workshop Unit 3 Garmouth Road, Lhanbryde",
    "sg:city":"Elgin",
    "sg:classifiers":[
        {
            "category":"Manufacturing",
            "subcategory":"Furniture",
            "type":"Manufacturing & Wholesale Goods"
        }
    ],
    "sg:postcode":"IV30 3PD",
    "sg:province":"Moray",
    "sg:tags":[
        "mnfr",
        "upholsterer"
    ],
    "wof:name":"Raymond McKenzie Upholstery",
    "wof:placetype":"venue"
},
  "geometry": {"coordinates":[-3.2200100422,57.6350402832],"type":"Point"}
}