{
  "type": "Feature",
  "properties": {
    "iso:country":"GB",
    "sg:address":"120 Broadfield Drive",
    "sg:city":"Preston",
    "sg:classifiers":[
        {
            "category":"Building & Trades",
            "subcategory":"Plumbing",
            "type":"Services"
        }
    ],
    "sg:phone":"+44 1772 434885",
    "sg:postcode":"PR25 1QN",
    "sg:province":"Lancashire",
    "sg:tags":[
        "plumber",
        "heating"
    ],
    "wof:name":"Paul Hayes",
    "wof:placetype":"venue"
},
  "geometry": {"coordinates":[-2.717559,53.735699],"type":"Point"}
}