{
  "type": "Feature",
  "properties": {
    "iso:country":"GB",
    "sg:address":"Yarbridge, Brading",
    "sg:city":"Sandown",
    "sg:classifiers":[
        {
            "category":"Bars & Pubs",
            "type":"Food & Drink"
        }
    ],
    "sg:phone":"+44 1983 406212",
    "sg:postcode":"PO36 0AA",
    "sg:province":"Isle of Wight",
    "sg:tags":[
        "pubs",
        "house",
        "inn",
        "public",
        "activity"
    ],
    "wof:name":"Yarbridge Inn",
    "wof:placetype":"venue"
},
  "geometry": {"coordinates":[-1.1432939768,50.6819496155],"type":"Point"}
}