{
  "type": "Feature",
  "properties": {
    "addr:full":"Spitfire Way Leeds North Yorkshire LS25 6NB",
    "addr:postcode":"ls25 6nb",
    "addr:street":"Spitfire Way",
    "iso:country":"GB",
    "sg:address":"Spitfire Way",
    "sg:city":"Leeds",
    "sg:classifiers":[
        {
            "category":"Utilities",
            "subcategory":"Refuse",
            "type":"Services"
        }
    ],
    "sg:postcode":"LS25 6NB",
    "sg:province":"North Yorkshire",
    "sg:tags":[
        "skip",
        "hire"
    ],
    "wof:name":"Aero Waste Disposal Ltd.",
    "wof:placetype":"venue"
},
  "geometry": {"coordinates":[-1.226683,53.792542],"type":"Point"}
}