{
  "type": "Feature",
  "properties": {
    "addr:full":"Mulberry Cottage, 11 Cross Lane, Helmdon Brackley Buckinghamshire NN13 5QL",
    "addr:housenumber":"11",
    "addr:postcode":"nn13 5ql",
    "addr:street":"Cross Lane",
    "iso:country":"GB",
    "sg:address":"Mulberry Cottage, 11 Cross Lane, Helmdon",
    "sg:city":"Brackley",
    "sg:classifiers":[
        {
            "category":"Professional",
            "subcategory":"Employment Agencies",
            "type":"Services"
        }
    ],
    "sg:phone":"+44 1295 760554",
    "sg:postcode":"NN13 5QL",
    "sg:province":"Buckinghamshire",
    "sg:tags":[
        "consultant"
    ],
    "wof:name":"Gillian Derbyshire Executive Search Research Services",
    "wof:placetype":"venue"
},
  "geometry": {"coordinates":[-1.143324,52.087761],"type":"Point"}
}