{
  "type": "Feature",
  "properties": {
    "iso:country":"GB",
    "sg:address":"68-70 Osmaston Road",
    "sg:city":"Derby",
    "sg:classifiers":[
        {
            "category":"Retail",
            "subcategory":"Repair Shop",
            "type":"Services"
        },
        {
            "category":"Communications",
            "type":"Services"
        }
    ],
    "sg:phone":"+44 1332 344016",
    "sg:postcode":"DE1 2HZ",
    "sg:province":"Derbyshire",
    "sg:tags":[
        "tv",
        "radio",
        "television",
        "video"
    ],
    "wof:name":"Domestic Electric",
    "wof:placetype":"venue"
},
  "geometry": {"coordinates":[-1.474504,52.917522],"type":"Point"}
}