{
  "type": "Feature",
  "properties": {
    "addr:full":"Unit B, 23 Seafield Road East Edinburgh City of Edinburgh EH15 1ED",
    "addr:housenumber":"23",
    "addr:postcode":"eh15 1ed",
    "addr:street":"Seafield Road East Edinburgh",
    "iso:country":"GB",
    "sg:address":"Unit B, 23 Seafield Road East",
    "sg:city":"Edinburgh",
    "sg:classifiers":[
        {
            "category":"Freight",
            "type":"Transportation"
        }
    ],
    "sg:phone":"+44 131 669 0099",
    "sg:postcode":"EH15 1ED",
    "sg:province":"City of Edinburgh",
    "sg:tags":[
        "forwarders"
    ],
    "wof:name":"Leith Shipping & Forwarding Services Ltd.",
    "wof:placetype":"venue"
},
  "geometry": {"coordinates":[-3.12931,55.96344],"type":"Point"}
}