{
  "type": "Feature",
  "properties": {
    "iso:country":"GB",
    "sg:address":"Hatherley Mews",
    "sg:city":"London",
    "sg:classifiers":[
        {
            "category":"Health Services",
            "subcategory":"Dentist",
            "type":"Services"
        }
    ],
    "sg:phone":"+44 20 8503 6624",
    "sg:postcode":"E17 4QP",
    "sg:province":"Greater London",
    "sg:tags":[
        "technician",
        "dental"
    ],
    "wof:name":"M & M Dentals",
    "wof:placetype":"venue"
},
  "geometry": {"coordinates":[-0.0208039992,51.5864601135],"type":"Point"}
}