{
  "type": "Feature",
  "properties": {
    "addr:full":"Garage, 121 Wales Road Sheffield South Yorkshire S26 6RA",
    "addr:housenumber":"121",
    "addr:postcode":"s26 6ra",
    "addr:street":"Wales Road",
    "iso:country":"GB",
    "sg:address":"Garage, 121 Wales Road",
    "sg:city":"Sheffield",
    "sg:classifiers":[
        {
            "category":"Food & Beverages",
            "subcategory":"Meat & Fish",
            "type":"Retail Goods"
        }
    ],
    "sg:postcode":"S26 6RA",
    "sg:province":"South Yorkshire",
    "sg:tags":[
        "butcher"
    ],
    "wof:name":"E V Taylor",
    "wof:placetype":"venue"
},
  "geometry": {"coordinates":[-1.2704600096,53.3407287598],"type":"Point"}
}