{
  "type": "Feature",
  "properties": {
    "iso:country":"GB",
    "sg:address":"7 St Edwards Road",
    "sg:city":"Gosport",
    "sg:classifiers":[
        {
            "category":"Retail",
            "subcategory":"Emissions Testing",
            "type":"Services"
        },
        {
            "category":"Professional",
            "subcategory":"Testing Lab",
            "type":"Services"
        }
    ],
    "sg:phone":"+44 23 9279 7491",
    "sg:postcode":"PO12 1PN",
    "sg:province":"Hampshire",
    "sg:tags":[
        "mot"
    ],
    "wof:name":"G F Auto Services",
    "wof:placetype":"venue"
},
  "geometry": {"coordinates":[-1.1371500492,50.7931671143],"type":"Point"}
}