{
  "type": "Feature",
  "properties": {
    "addr:full":"Parkside Residential Care Home, 6-8 Edward Street Oldham Lancashire OL9 7QW",
    "addr:housenumber":"6-8",
    "addr:postcode":"ol9 7qw",
    "addr:street":"Edward Street",
    "iso:country":"GB",
    "sg:address":"Parkside Residential Care Home, 6-8 Edward Street",
    "sg:city":"Oldham",
    "sg:classifiers":[
        {
            "category":"Health Services",
            "subcategory":"Nursing And Care Facility",
            "type":"Services"
        },
        {
            "category":"Social Services",
            "subcategory":"Retirement Home",
            "type":"Services"
        }
    ],
    "sg:phone":"+44 161 624 6113",
    "sg:postcode":"OL9 7QW",
    "sg:province":"Lancashire",
    "sg:tags":[
        "rest"
    ],
    "wof:name":"Parkside Residential Care Home",
    "wof:placetype":"venue"
},
  "geometry": {"coordinates":[-2.131993,53.53614],"type":"Point"}
}