{
  "type": "Feature",
  "properties": {
    "iso:country":"GB",
    "sg:address":"Artech House, 46 Gillingham Street",
    "sg:city":"London",
    "sg:classifiers":[
        {
            "category":"Communications",
            "subcategory":"Newspaper",
            "type":"Services"
        }
    ],
    "sg:phone":"+44 20 7596 8730",
    "sg:postcode":"SW1V 1AH",
    "sg:province":"Greater London",
    "sg:tags":[
        "magazine"
    ],
    "wof:name":"Horizon House Publications Ltd.",
    "wof:placetype":"venue"
},
  "geometry": {"coordinates":[-0.142823,51.493351],"type":"Point"}
}