{
  "type": "Feature",
  "properties": {
    "iso:country":"GB",
    "sg:address":"E C A House, 1 Dronfield Court, Civic Centre",
    "sg:city":"Dronfield",
    "sg:classifiers":[
        {
            "category":"Professional",
            "subcategory":"Management & Consulting",
            "type":"Services"
        }
    ],
    "sg:postcode":"S18 1NQ",
    "sg:province":"Derbyshire",
    "sg:tags":[
        "consultant",
        "business"
    ],
    "wof:name":"Energy Cost Advisors Ltd.",
    "wof:placetype":"venue"
},
  "geometry": {"coordinates":[-1.47446,53.30167],"type":"Point"}
}