{
  "type": "Feature",
  "properties": {
    "iso:country":"GB",
    "sg:address":"21 Holt Dr",
    "sg:city":"Colchester",
    "sg:classifiers":[
        {
            "category":"Professional",
            "subcategory":"Management & Consulting",
            "type":"Services"
        }
    ],
    "sg:phone":"+44 1206 766668",
    "sg:postcode":"CO2 0BH",
    "sg:province":"Essex",
    "sg:tags":[
        "consultant",
        "energy",
        "conservation"
    ],
    "wof:name":"Simms Associates",
    "wof:placetype":"venue"
},
  "geometry": {"coordinates":[0.912142,51.854687],"type":"Point"}
}