{
  "type": "Feature",
  "properties": {
    "addr:full":"79 Stonecot Hill Sutton Surrey SM3 9HJ",
    "addr:housenumber":"79",
    "addr:postcode":"sm3 9hj",
    "addr:street":"Stonecot Hill",
    "iso:country":"GB",
    "sg:address":"79 Stonecot Hill",
    "sg:city":"Sutton",
    "sg:classifiers":[
        {
            "category":"Shopping",
            "subcategory":"Hobbies, Toys, & Games",
            "type":"Retail Goods"
        }
    ],
    "sg:phone":"+44 20 8644 3545",
    "sg:postcode":"SM3 9HJ",
    "sg:province":"Surrey",
    "sg:tags":[
        "computer"
    ],
    "wof:name":"The Stockxchange",
    "wof:placetype":"venue"
},
  "geometry": {"coordinates":[-0.2138759941,51.3834533691],"type":"Point"}
}