{
  "type": "Feature",
  "properties": {
    "iso:country":"GB",
    "sg:address":"Pardise Wild Life Park, White Stubbs Lane",
    "sg:city":"Broxbourne",
    "sg:classifiers":[
        {
            "category":"Community Center",
            "type":"Public Place"
        }
    ],
    "sg:phone":"+44 1992 440494",
    "sg:postcode":"EN10 7QA",
    "sg:province":"Essex",
    "sg:tags":[
        "conference",
        "room",
        "centre"
    ],
    "wof:name":"The Sarfari Suite",
    "wof:placetype":"venue"
},
  "geometry": {"coordinates":[-0.02046,51.743214],"type":"Point"}
}