{
  "type": "Feature",
  "properties": {
    "addr:full":"18 Tawelan Carmarthen Carmarthenshire SA32 7NQ",
    "addr:housenumber":"18",
    "addr:postcode":"sa32 7nq",
    "addr:street":"Tawelan;Carmarthenshire",
    "iso:country":"GB",
    "sg:address":"18 Tawelan",
    "sg:city":"Carmarthen",
    "sg:classifiers":[
        {
            "category":"Freight",
            "type":"Transportation"
        }
    ],
    "sg:phone":"+44 1267 290521",
    "sg:postcode":"SA32 7NQ",
    "sg:province":"Carmarthenshire",
    "sg:tags":[
        "haulage",
        "road"
    ],
    "wof:name":"J W M Davies",
    "wof:placetype":"venue"
},
  "geometry": {"coordinates":[-4.1687269211,51.8738517761],"type":"Point"}
}