{
  "type": "Feature",
  "properties": {
    "addr:full":"54 High Street Inverkeithing Fife KY11 1NN",
    "addr:housenumber":"54",
    "addr:postcode":"ky11 1nn",
    "addr:street":"High Street",
    "iso:country":"GB",
    "sg:address":"54 High Street",
    "sg:city":"Inverkeithing",
    "sg:classifiers":[
        {
            "category":"Home & Garden",
            "subcategory":"Hardware",
            "type":"Retail Goods"
        }
    ],
    "sg:phone":"+44 1383 415723",
    "sg:postcode":"KY11 1NN",
    "sg:province":"Fife",
    "sg:tags":[
        "merchant",
        "ironmonger"
    ],
    "wof:name":"Boyds",
    "wof:placetype":"venue"
},
  "geometry": {"coordinates":[-3.3985719681,56.0300636292],"type":"Point"}
}