{
  "type": "Feature",
  "properties": {
    "addr:full":"46 Craven Walk London Greater London N16 6BU",
    "addr:housenumber":"46",
    "addr:postcode":"n16 6bu",
    "addr:street":"Craven Walk",
    "iso:country":"GB",
    "sg:address":"46 Craven Walk",
    "sg:city":"London",
    "sg:classifiers":[
        {
            "category":"Shopping",
            "subcategory":"Stationery & Office Supplies",
            "type":"Retail Goods"
        },
        {
            "category":"Manufacturing",
            "subcategory":"Printing",
            "type":"Manufacturing & Wholesale Goods"
        }
    ],
    "sg:phone":"+44 20 8880 2359",
    "sg:postcode":"N16 6BU",
    "sg:province":"Greater London",
    "sg:tags":[
        "stamp",
        "promotional",
        "rubber",
        "item",
        "supplier",
        "manufacturer"
    ],
    "wof:name":"Swift Publicity Ltd",
    "wof:placetype":"venue"
},
  "geometry": {"coordinates":[-0.0633,51.574184],"type":"Point"}
}