{
  "type": "Feature",
  "properties": {
    "iso:country":"GB",
    "sg:address":"Little Heath, Parish Hall, Thornton Rd, Little Heath",
    "sg:city":"Potters Bar",
    "sg:classifiers":[
        {
            "category":"Education",
            "subcategory":"Music School",
            "type":"Public Place"
        }
    ],
    "sg:phone":"+44 1707 644276",
    "sg:postcode":"EN6 1JJ",
    "sg:province":"Greater London",
    "wof:name":"Little Heath Theatre Workshop",
    "wof:placetype":"venue"
},
  "geometry": {"coordinates":[-0.178424,51.693012],"type":"Point"}
}