{
  "type": "Feature",
  "properties": {
    "addr:full":"Broadaxe Lane Presteigne Herefordshire LD8 2AY",
    "addr:postcode":"ld8 2ay",
    "addr:street":"Broadaxe Lane",
    "iso:country":"GB",
    "sg:address":"Broadaxe Lane",
    "sg:city":"Presteigne",
    "sg:classifiers":[
        {
            "category":"Education",
            "subcategory":"School",
            "type":"Public Place"
        }
    ],
    "sg:phone":"+44 1544 267259",
    "sg:postcode":"LD8 2AY",
    "sg:province":"Herefordshire",
    "sg:tags":[
        "local",
        "authority"
    ],
    "wof:name":"John Beddoes School",
    "wof:placetype":"venue"
},
  "geometry": {"coordinates":[-3.004454,52.270206],"type":"Point"}
}