{
  "type": "Feature",
  "properties": {
    "iso:country":"GB",
    "sg:address":"Stone House Hospital, Cotton La",
    "sg:city":"Dartford",
    "sg:classifiers":[
        {
            "category":"Organizations",
            "subcategory":"Non-profit Organization",
            "type":"Services"
        }
    ],
    "sg:phone":"+44 1322 622192",
    "sg:postcode":"DA2 6AU",
    "sg:province":"Kent",
    "sg:tags":[
        "organisation",
        "voluntary",
        "charity"
    ],
    "wof:name":"Kaleidoscope",
    "wof:placetype":"venue"
},
  "geometry": {"coordinates":[0.2453500032,51.4447288513],"type":"Point"}
}