{
  "type": "Feature",
  "properties": {
    "addr:full":"275 Bath Road Hounslow Greater London TW3 3DA",
    "addr:housenumber":"275",
    "addr:postcode":"tw3 3da",
    "addr:street":"Bath Road",
    "iso:country":"GB",
    "sg:address":"275 Bath Road",
    "sg:city":"Hounslow",
    "sg:classifiers":[
        {
            "category":"Retail",
            "subcategory":"Laundry & Dry Cleaning",
            "type":"Services"
        }
    ],
    "sg:phone":"+44 20 8572 9551",
    "sg:postcode":"TW3 3DA",
    "sg:province":"Greater London",
    "sg:tags":[
        "launderette",
        "alteration"
    ],
    "wof:name":"Slough Quickwash Ltd.",
    "wof:placetype":"venue"
},
  "geometry": {"coordinates":[-0.381077,51.471207],"type":"Point"}
}