{
  "type": "Feature",
  "properties": {
    "iso:country":"GB",
    "sg:address":"Watling Street, Wedges Mills",
    "sg:city":"Cannock",
    "sg:classifiers":[
        {
            "category":"Freight",
            "type":"Transportation"
        }
    ],
    "sg:phone":"+44 1543 462801",
    "sg:postcode":"WS11 1TE",
    "sg:province":"Staffordshire",
    "sg:tags":[
        "haulage",
        "road"
    ],
    "wof:name":"Bowmur Haulage Co. Ltd.",
    "wof:placetype":"venue"
},
  "geometry": {"coordinates":[-2.050205946,52.674369812],"type":"Point"}
}