{
  "type": "Feature",
  "properties": {
    "addr:full":"Park House, Springfield Park, Overton Wrexham Wrexham LL13 0EX",
    "addr:postcode":"ll13 0ex",
    "addr:street":"Springfield Park",
    "iso:country":"GB",
    "sg:address":"Park House, Springfield Park, Overton",
    "sg:city":"Wrexham",
    "sg:classifiers":[
        {
            "category":"Professional",
            "subcategory":"Business Services",
            "type":"Services"
        },
        {
            "category":"Real Estate",
            "subcategory":"Architect",
            "type":"Services"
        }
    ],
    "sg:postcode":"LL13 0EX",
    "sg:province":"Wrexham",
    "sg:tags":[
        "planning",
        "supervisor"
    ],
    "wof:name":"G B Simms & Associates",
    "wof:placetype":"venue"
},
  "geometry": {"coordinates":[-2.9342889786,52.9685707092],"type":"Point"}
}