{
  "type": "Feature",
  "properties": {
    "iso:country":"GB",
    "sg:address":"Unit 6 Burnbank Centre, Burnbank",
    "sg:city":"Hamilton",
    "sg:classifiers":[
        {
            "category":"Personal",
            "subcategory":"Barber",
            "type":"Services"
        }
    ],
    "sg:phone":"+44 1698 891656",
    "sg:postcode":"ML3 0QG",
    "sg:province":"South Lanarkshire",
    "sg:tags":[
        "men's",
        "hairdresser"
    ],
    "wof:name":"Andy's Barber Shop",
    "wof:placetype":"venue"
},
  "geometry": {"coordinates":[-4.066469,55.780964],"type":"Point"}
}