{
  "type": "Feature",
  "properties": {
    "addr:full":"38 Yorkersgate Malton North Yorkshire YO17 7AB",
    "addr:housenumber":"38",
    "addr:postcode":"yo17 7ab",
    "addr:street":"Yorkersgate",
    "iso:country":"GB",
    "sg:address":"38 Yorkersgate",
    "sg:city":"Malton",
    "sg:classifiers":[
        {
            "category":"Professional",
            "subcategory":"Business Services",
            "type":"Services"
        }
    ],
    "sg:phone":"+44 1653 693898",
    "sg:postcode":"YO17 7AB",
    "sg:province":"North Yorkshire",
    "sg:tags":[
        "bookmaker"
    ],
    "wof:name":"J Dyson",
    "wof:placetype":"venue"
},
  "geometry": {"coordinates":[-0.7991930246,54.1344566345],"type":"Point"}
}