{
  "type": "Feature",
  "properties": {
    "iso:country":"GB",
    "sg:address":"Abbey Foregate",
    "sg:city":"Shrewsbury",
    "sg:classifiers":[
        {
            "category":"Place Of Worship",
            "type":"Public Place"
        }
    ],
    "sg:phone":"+44 1743 232723",
    "sg:postcode":"SY2 6BS",
    "sg:province":"Shropshire",
    "wof:name":"Shrewsbury Abbey",
    "wof:placetype":"venue"
},
  "geometry": {"coordinates":[-2.7451729774,52.7072410583],"type":"Point"}
}