{
  "type": "Feature",
  "properties": {
    "addr:full":"Southmoor Road, Roundthorn Industrial Estate Manchester Cheshire M23 9NR",
    "addr:postcode":"m23 9nr",
    "addr:street":"Southmoor Road Roundthorn Industrial Estate",
    "iso:country":"GB",
    "sg:address":"Southmoor Road, Roundthorn Industrial Estate",
    "sg:city":"Manchester",
    "sg:classifiers":[
        {
            "category":"Shopping",
            "subcategory":"Stationery & Office Supplies",
            "type":"Retail Goods"
        }
    ],
    "sg:phone":"+44 161 946 0645",
    "sg:postcode":"M23 9NR",
    "sg:province":"Cheshire",
    "sg:tags":[
        "equipment"
    ],
    "wof:name":"le-Al (Associates) Ltd.",
    "wof:placetype":"venue"
},
  "geometry": {"coordinates":[-2.294809103,53.4010047913],"type":"Point"}
}