{
  "type": "Feature",
  "properties": {
    "addr:full":"118 Windmill Rd Brentford Greater London TW8 9NA",
    "addr:housenumber":"118",
    "addr:postcode":"tw8 9na",
    "addr:street":"Windmill Rd",
    "iso:country":"GB",
    "sg:address":"118 Windmill Rd",
    "sg:city":"Brentford",
    "sg:classifiers":[
        {
            "category":"Social Services",
            "subcategory":"Retirement Home",
            "type":"Services"
        }
    ],
    "sg:phone":"+44 20 8560 7473",
    "sg:postcode":"TW8 9NA",
    "sg:province":"Greater London",
    "sg:tags":[
        "residential",
        "care"
    ],
    "wof:name":"Windmill Lodge",
    "wof:placetype":"venue"
},
  "geometry": {"coordinates":[-0.3105260134,51.4909591675],"type":"Point"}
}