{
  "type": "Feature",
  "properties": {
    "iso:country":"GB",
    "sg:address":"17a Dundonald Street",
    "sg:city":"Dundee",
    "sg:classifiers":[
        {
            "category":"Shopping",
            "subcategory":"Used Merchandise",
            "type":"Retail Goods"
        }
    ],
    "sg:phone":"+44 1382 461666",
    "sg:postcode":"DD3 7QA",
    "sg:province":"Dundee City",
    "sg:tags":[
        "shop",
        "second-hand"
    ],
    "wof:name":"Household Cleared",
    "wof:placetype":"venue"
},
  "geometry": {"coordinates":[-2.965711,56.471855],"type":"Point"}
}