{
  "type": "Feature",
  "properties": {
    "addr:full":"Rockwood Hospital, Fairwater Rd Cardiff Cardiff CF5 2YN",
    "addr:postcode":"cf5 2yn",
    "addr:street":"Fairwater Rd",
    "iso:country":"GB",
    "sg:address":"Rockwood Hospital, Fairwater Rd",
    "sg:city":"Cardiff",
    "sg:classifiers":[
        {
            "category":"Social Services",
            "type":"Services"
        }
    ],
    "sg:phone":"+44 29 2055 5677",
    "sg:postcode":"CF5 2YN",
    "sg:province":"Cardiff",
    "sg:tags":[
        "disability"
    ],
    "wof:name":"Artificial Limb & Appliance Centre",
    "wof:placetype":"venue"
},
  "geometry": {"coordinates":[-3.22515,51.49437],"type":"Point"}
}