{
  "type": "Feature",
  "properties": {
    "iso:country":"GB",
    "sg:address":"79-81 Princess Road",
    "sg:city":"Poole",
    "sg:classifiers":[
        {
            "category":"Health Services",
            "subcategory":"Nursing And Care Facility",
            "type":"Services"
        }
    ],
    "sg:postcode":"BH12 1BQ",
    "sg:province":"Dorset",
    "sg:tags":[
        "home"
    ],
    "wof:name":"Harry Bhugoo",
    "wof:placetype":"venue"
},
  "geometry": {"coordinates":[-1.909793,50.725456],"type":"Point"}
}