{
  "type": "Feature",
  "properties": {
    "iso:country":"GB",
    "sg:address":"102 Fulbourn Old Drift, Cherry Hinton",
    "sg:city":"Cambridge",
    "sg:classifiers":[
        {
            "category":"Building & Trades",
            "subcategory":"Plumbing",
            "type":"Services"
        }
    ],
    "sg:phone":"+44 1223 246444",
    "sg:postcode":"CB1 9LR",
    "sg:province":"Cambridgeshire",
    "sg:tags":[
        "plumber",
        "heating"
    ],
    "wof:name":"William H Taylor",
    "wof:placetype":"venue"
},
  "geometry": {"coordinates":[0.1733849943,52.186668396],"type":"Point"}
}