{
  "type": "Feature",
  "properties": {
    "addr:full":"Redmoor Road, Kelly Bray Callington Cornwall PL17 8EJ",
    "addr:postcode":"pl17 8ej",
    "addr:street":"Redmoor Road Kelly",
    "iso:country":"GB",
    "sg:address":"Redmoor Road, Kelly Bray",
    "sg:city":"Callington",
    "sg:classifiers":[
        {
            "category":"Wholesale",
            "subcategory":"Machinery & Supplies",
            "type":"Manufacturing & Wholesale Goods"
        },
        {
            "category":"Professional",
            "subcategory":"Business Services",
            "type":"Services"
        },
        {
            "category":"Shopping",
            "type":"Retail Goods"
        }
    ],
    "sg:phone":"+44 1579 382292",
    "sg:postcode":"PL17 8EJ",
    "sg:province":"Cornwall",
    "sg:tags":[
        "merchant",
        "agricultural"
    ],
    "wof:name":"Cornwall Farmers Ltd.",
    "wof:placetype":"venue"
},
  "geometry": {"coordinates":[-4.316074,50.520367],"type":"Point"}
}