{
  "type": "Feature",
  "properties": {
    "addr:full":"657 Bury Road Bolton Lancashire BL2 6HR",
    "addr:housenumber":"657",
    "addr:postcode":"bl2 6hr",
    "addr:street":"Bury Road",
    "iso:country":"GB",
    "sg:address":"657 Bury Road",
    "sg:city":"Bolton",
    "sg:classifiers":[
        {
            "category":"Food & Beverages",
            "subcategory":"Fruits & Vegetables",
            "type":"Retail Goods"
        }
    ],
    "sg:phone":"+44 1204 527911",
    "sg:postcode":"BL2 6HR",
    "sg:province":"Lancashire",
    "sg:tags":[
        "greengrocer"
    ],
    "wof:name":"S Owen",
    "wof:placetype":"venue"
},
  "geometry": {"coordinates":[-2.391082,53.581188],"type":"Point"}
}