{
  "type": "Feature",
  "properties": {
    "addr:full":"Balgreddan Farm Kirkcudbright Dumfries and Galloway DG6 4XR",
    "addr:postcode":"dg6 4xr",
    "iso:country":"GB",
    "sg:address":"Balgreddan Farm",
    "sg:city":"Kirkcudbright",
    "sg:classifiers":[
        {
            "category":"Farming",
            "subcategory":"Livestock Farm",
            "type":"Manufacturing & Wholesale Goods"
        }
    ],
    "sg:phone":"+44 1557 330945",
    "sg:postcode":"DG6 4XR",
    "sg:province":"Dumfries and Galloway",
    "sg:tags":[
        "others"
    ],
    "wof:name":"R E & A Baird",
    "wof:placetype":"venue"
},
  "geometry": {"coordinates":[-4.0476388931,54.836971283],"type":"Point"}
}