{
  "type": "Feature",
  "properties": {
    "iso:country":"GB",
    "sg:address":"Hampsfell Road",
    "sg:city":"Grange-over-sands",
    "sg:classifiers":[
        {
            "category":"Travel",
            "subcategory":"Hotels & Motels",
            "type":"Entertainment"
        }
    ],
    "sg:phone":"+44 15395 32567",
    "sg:postcode":"LA11 6BG",
    "sg:province":"Cumbria",
    "wof:name":"Hampsfell House Hotel",
    "wof:placetype":"venue"
},
  "geometry": {"coordinates":[-2.9087638855,54.1983032227],"type":"Point"}
}