{
  "type": "Feature",
  "properties": {
    "addr:full":"25-27 Market St Birkenhead Merseyside L41 5BS",
    "addr:housenumber":"25-27",
    "addr:postcode":"l41 5bs",
    "addr:street":"Market St",
    "iso:country":"GB",
    "sg:address":"25-27 Market St",
    "sg:city":"Birkenhead",
    "sg:classifiers":[
        {
            "category":"Arts & Performance",
            "subcategory":"Arts Center",
            "type":"Entertainment"
        }
    ],
    "sg:phone":"+44 151 647 6822",
    "sg:postcode":"L41 5BS",
    "sg:province":"Merseyside",
    "sg:tags":[
        "centre"
    ],
    "wof:name":"Artsworks",
    "wof:placetype":"venue"
},
  "geometry": {"coordinates":[-3.016015,53.392143],"type":"Point"}
}