{
  "type": "Feature",
  "properties": {
    "addr:full":"Maesglas Retail Estate Newport Newport NP20 2XF",
    "addr:postcode":"np20 2xf",
    "iso:country":"GB",
    "sg:address":"Maesglas Retail Estate",
    "sg:city":"Newport",
    "sg:classifiers":[
        {
            "category":"Home & Garden",
            "subcategory":"Household Appliances",
            "type":"Retail Goods"
        },
        {
            "category":"Utilities",
            "subcategory":"Natural Gas",
            "type":"Services"
        }
    ],
    "sg:phone":"+44 1633 267979",
    "sg:postcode":"NP20 2XF",
    "sg:province":"Newport",
    "sg:tags":[
        "supplier"
    ],
    "wof:name":"Newport Calor Centre",
    "wof:placetype":"venue"
},
  "geometry": {"coordinates":[-2.9993228912,51.570766449],"type":"Point"}
}