{
  "type": "Feature",
  "properties": {
    "addr:full":"30 Sandpit Rd Bromley Kent BR1 4PE",
    "addr:housenumber":"30",
    "addr:postcode":"br1 4pe",
    "addr:street":"Sandpit Rd",
    "iso:country":"GB",
    "sg:address":"30 Sandpit Rd",
    "sg:city":"Bromley",
    "sg:classifiers":[
        {
            "category":"Shopping",
            "subcategory":"Florist",
            "type":"Retail Goods"
        }
    ],
    "sg:postcode":"BR1 4PE",
    "sg:province":"Kent",
    "wof:name":"Darlings Florist",
    "wof:placetype":"venue"
},
  "geometry": {"coordinates":[-0.000826,51.4220809937],"type":"Point"}
}