{
  "type": "Feature",
  "properties": {
    "iso:country":"GB",
    "sg:address":"Old Court St",
    "sg:city":"Stoke On Trent",
    "sg:classifiers":[
        {
            "category":"Bars & Pubs",
            "type":"Food & Drink"
        }
    ],
    "sg:phone":"+44 1782 836765",
    "sg:postcode":"ST6 5BL",
    "sg:province":"Staffordshire",
    "sg:tags":[
        "pubs",
        "inn"
    ],
    "wof:name":"Coach & Horses",
    "wof:placetype":"venue"
},
  "geometry": {"coordinates":[-2.212414,53.058231],"type":"Point"}
}