{
  "type": "Feature",
  "properties": {
    "iso:country":"GB",
    "sg:address":"South Bridge, Cotton End",
    "sg:city":"Northampton",
    "sg:classifiers":[
        {
            "category":"Manufacturing",
            "subcategory":"Metals",
            "type":"Manufacturing & Wholesale Goods"
        }
    ],
    "sg:phone":"+44 1604 762188",
    "sg:postcode":"NN4 8BS",
    "sg:province":"Northamptonshire",
    "sg:tags":[
        "steel",
        "fabricator",
        "erectors"
    ],
    "wof:name":"J E Matthews & Sons Ltd",
    "wof:placetype":"venue"
},
  "geometry": {"coordinates":[-0.8966100216,52.2299194336],"type":"Point"}
}