{
  "type": "Feature",
  "properties": {
    "addr:full":"84 Victoria Rd Wallasey Merseyside L45 2JF",
    "addr:housenumber":"84",
    "addr:postcode":"l45 2jf",
    "addr:street":"Victoria Rd",
    "iso:country":"GB",
    "sg:address":"84 Victoria Rd",
    "sg:city":"Wallasey",
    "sg:classifiers":[
        {
            "category":"Shopping",
            "subcategory":"Clothing, Apparel, & Fashions",
            "type":"Retail Goods"
        }
    ],
    "sg:phone":"+44 151 637 2111",
    "sg:postcode":"L45 2JF",
    "sg:province":"Merseyside",
    "sg:tags":[
        "shop"
    ],
    "wof:name":"Togs",
    "wof:placetype":"venue"
},
  "geometry": {"coordinates":[-3.0411720276,53.4384841919],"type":"Point"}
}