{
  "type": "Feature",
  "properties": {
    "iso:country":"GB",
    "sg:address":"Highfield Ind Est",
    "sg:city":"Folkestone",
    "sg:classifiers":[
        {
            "category":"Shopping",
            "subcategory":"Mobile Phones",
            "type":"Retail Goods"
        }
    ],
    "sg:phone":"+44 1303 220787",
    "sg:postcode":"CT20 1BW",
    "sg:province":"Kent",
    "wof:name":"Mobiles Direct",
    "wof:placetype":"venue"
},
  "geometry": {"coordinates":[1.177945,51.084431],"type":"Point"}
}