{
  "type": "Feature",
  "properties": {
    "addr:full":"68 Albany Rd Cardiff Cardiff CF2 3RS",
    "addr:housenumber":"68",
    "addr:postcode":"cf2 3rs",
    "addr:street":"Albany Rd",
    "iso:country":"GB",
    "sg:address":"68 Albany Rd",
    "sg:city":"Cardiff",
    "sg:classifiers":[
        {
            "category":"Cafe",
            "type":"Food & Drink"
        }
    ],
    "sg:phone":"+44 29 2045 2332",
    "sg:postcode":"CF2 3RS",
    "sg:province":"Cardiff",
    "sg:tags":[
        "tea",
        "room"
    ],
    "wof:name":"Celtic Connection Cafe The",
    "wof:placetype":"venue"
},
  "geometry": {"coordinates":[-3.167217,51.493607],"type":"Point"}
}