{
  "type": "Feature",
  "properties": {
    "addr:full":"2 Manor House Lane, Datchet Slough Berkshire SL3 9EB",
    "addr:housenumber":"2",
    "addr:postcode":"sl3 9eb",
    "addr:street":"Manor House Lane",
    "iso:country":"GB",
    "sg:address":"2 Manor House Lane, Datchet",
    "sg:city":"Slough",
    "sg:classifiers":[
        {
            "category":"Real Estate",
            "subcategory":"Surveying",
            "type":"Services"
        }
    ],
    "sg:phone":"+44 1753 582500",
    "sg:postcode":"SL3 9EB",
    "sg:province":"Berkshire",
    "sg:tags":[
        "surveyor",
        "valuer"
    ],
    "wof:name":"Boddy & Edwards",
    "wof:placetype":"venue"
},
  "geometry": {"coordinates":[-0.5787389874,51.4825363159],"type":"Point"}
}