{
  "type": "Feature",
  "properties": {
    "addr:full":"Pen Y Green Farm, Pen Y Green Road Llanidloes Powys SY18 6AJ",
    "addr:postcode":"sy18 6aj",
    "addr:street":"Green Road",
    "iso:country":"GB",
    "sg:address":"Pen Y Green Farm, Pen Y Green Road",
    "sg:city":"Llanidloes",
    "sg:classifiers":[
        {
            "category":"Farming",
            "subcategory":"Livestock Farm",
            "type":"Manufacturing & Wholesale Goods"
        }
    ],
    "sg:phone":"+44 1686 412311",
    "sg:postcode":"SY18 6AJ",
    "sg:province":"Powys",
    "sg:tags":[
        "others"
    ],
    "wof:name":"John Vernon Howells",
    "wof:placetype":"venue"
},
  "geometry": {"coordinates":[-3.540166,52.445915],"type":"Point"}
}