{
  "type": "Feature",
  "properties": {
    "iso:country":"GB",
    "sg:address":"Holme Works, Norfolk Street",
    "sg:city":"Carlisle",
    "sg:classifiers":[
        {
            "category":"Professional",
            "subcategory":"Art Services",
            "type":"Services"
        }
    ],
    "sg:postcode":"CA2 5JA",
    "sg:province":"Cumbria",
    "sg:tags":[
        "framing"
    ],
    "wof:name":"Michael's Framing",
    "wof:placetype":"venue"
},
  "geometry": {"coordinates":[-2.939799,54.885849],"type":"Point"}
}