{
  "type": "Feature",
  "properties": {
    "iso:country":"GB",
    "sg:address":"Hatherleigh Rd",
    "sg:city":"Exeter",
    "sg:classifiers":[
        {
            "category":"Community Center",
            "subcategory":"Youth",
            "type":"Public Place"
        }
    ],
    "sg:phone":"+44 1392 435490",
    "sg:postcode":"EX2 9LG",
    "sg:province":"Devon",
    "sg:tags":[
        "organisation",
        "centre"
    ],
    "wof:name":"Air Training Corps",
    "wof:placetype":"venue"
},
  "geometry": {"coordinates":[-3.5388529301,50.7079811096],"type":"Point"}
}