{
  "type": "Feature",
  "properties": {
    "iso:country":"GB",
    "sg:address":"195 High Street",
    "sg:city":"Berkhamsted",
    "sg:classifiers":[
        {
            "category":"Shopping",
            "subcategory":"Clothing, Apparel, & Fashions",
            "type":"Retail Goods"
        }
    ],
    "sg:postcode":"HP4 1AD",
    "sg:province":"Bedfordshire",
    "sg:tags":[
        "menswear"
    ],
    "wof:name":"Birtchnells",
    "wof:placetype":"venue"
},
  "geometry": {"coordinates":[-0.567417,51.761158],"type":"Point"}
}