{
  "type": "Feature",
  "properties": {
    "addr:full":"Woodhall Crescent, Reddish Stockport Cheshire SK5 7QG",
    "addr:postcode":"sk5 7qg",
    "addr:street":"Woodhall Crescent",
    "iso:country":"GB",
    "sg:address":"Woodhall Crescent, Reddish",
    "sg:city":"Stockport",
    "sg:classifiers":[
        {
            "category":"Social Services",
            "subcategory":"Adult Care",
            "type":"Services"
        }
    ],
    "sg:postcode":"SK5 7QG",
    "sg:province":"Cheshire",
    "sg:tags":[
        "day",
        "centre"
    ],
    "wof:name":"Woodhall Crescent Day Centre",
    "wof:placetype":"venue"
},
  "geometry": {"coordinates":[-2.1495490074,53.4243431091],"type":"Point"}
}