{
  "type": "Feature",
  "properties": {
    "iso:country":"GB",
    "sg:address":"Enville Road, Kinver",
    "sg:city":"Stourbridge",
    "sg:classifiers":[
        {
            "category":"Education",
            "subcategory":"School",
            "type":"Public Place"
        }
    ],
    "sg:phone":"+44 1384 872342",
    "sg:postcode":"DY7 6AA",
    "sg:province":"Shropshire",
    "sg:tags":[
        "local",
        "authority"
    ],
    "wof:name":"Staffordshire County Council",
    "wof:placetype":"venue"
},
  "geometry": {"coordinates":[-2.233058,52.452961],"type":"Point"}
}