{
  "type": "Feature",
  "properties": {
    "addr:full":"Fish Farm Aberughill, Comrie Crieff Perth and Kinross PH6 2LD",
    "addr:postcode":"ph6 2ld",
    "addr:street":"Aberughill;Crieff",
    "iso:country":"GB",
    "sg:address":"Fish Farm Aberughill, Comrie",
    "sg:city":"Crieff",
    "sg:classifiers":[
        {
            "category":"Farming",
            "subcategory":"Farm",
            "type":"Manufacturing & Wholesale Goods"
        }
    ],
    "sg:phone":"+44 1764 670500",
    "sg:postcode":"PH6 2LD",
    "sg:province":"Perth and Kinross",
    "sg:tags":[
        "hatchery"
    ],
    "wof:name":"Drummond Estates",
    "wof:placetype":"venue"
},
  "geometry": {"coordinates":[-3.9850640297,56.3709640503],"type":"Point"}
}