{
  "type": "Feature",
  "properties": {
    "addr:full":"82 Church Way South Croydon Surrey CR2 0JR",
    "addr:housenumber":"82",
    "addr:postcode":"cr2 0jr",
    "addr:street":"Church Way",
    "iso:country":"GB",
    "sg:address":"82 Church Way",
    "sg:city":"South Croydon",
    "sg:classifiers":[
        {
            "category":"Professional",
            "subcategory":"Engineering",
            "type":"Services"
        }
    ],
    "sg:phone":"+44 20 8657 0443",
    "sg:postcode":"CR2 0JR",
    "sg:province":"Surrey",
    "sg:tags":[
        "contractor",
        "electrical",
        "engineer"
    ],
    "wof:name":"Richard Wakeman",
    "wof:placetype":"venue"
},
  "geometry": {"coordinates":[-0.0762170032,51.3375053406],"type":"Point"}
}