{
  "type": "Feature",
  "properties": {
    "iso:country":"GB",
    "sg:address":"17 Sheep Street",
    "sg:city":"Bicester",
    "sg:classifiers":[
        {
            "category":"Shopping",
            "subcategory":"Clothing, Apparel, & Fashions",
            "type":"Retail Goods"
        }
    ],
    "sg:phone":"+44 1869 246216",
    "sg:postcode":"OX26 6JF",
    "sg:province":"Oxfordshire",
    "sg:tags":[
        "menswear"
    ],
    "wof:name":"D 2",
    "wof:placetype":"venue"
},
  "geometry": {"coordinates":[-1.1505080462,51.8977203369],"type":"Point"}
}