{
  "type": "Feature",
  "properties": {
    "iso:country":"GB",
    "sg:address":"Church Road, Kearsley",
    "sg:city":"Bolton",
    "sg:classifiers":[
        {
            "category":"Professional",
            "subcategory":"Detective & Security Services",
            "type":"Services"
        }
    ],
    "sg:phone":"+44 1204 575254",
    "sg:postcode":"BL4 8BP",
    "sg:province":"Lancashire",
    "sg:tags":[
        "alarm",
        "burglar",
        "system"
    ],
    "wof:name":"Acorn Alarms",
    "wof:placetype":"venue"
},
  "geometry": {"coordinates":[-2.375309,53.539822],"type":"Point"}
}