{
  "type": "Feature",
  "properties": {
    "addr:full":"Bayswater Middle School, Bayswater Rd Oxford Oxfordshire OX3 9NY",
    "addr:postcode":"ox3 9ny",
    "addr:street":"Bayswater Rd",
    "iso:country":"GB",
    "sg:address":"Bayswater Middle School, Bayswater Rd",
    "sg:city":"Oxford",
    "sg:classifiers":[
        {
            "category":"Government",
            "subcategory":"Office",
            "type":"Public Place"
        }
    ],
    "sg:phone":"+44 1865 763297",
    "sg:postcode":"OX3 9NY",
    "sg:province":"Oxfordshire",
    "sg:tags":[
        "local"
    ],
    "wof:name":"Oxfordshire Council Council",
    "wof:placetype":"venue"
},
  "geometry": {"coordinates":[-1.1930799484,51.7649002075],"type":"Point"}
}