{
  "type": "Feature",
  "properties": {
    "iso:country":"GB",
    "sg:address":"P O Box 3, Wpdo, Glaisdale Drive West",
    "sg:city":"Nottingham",
    "sg:classifiers":[
        {
            "category":"Shopping",
            "subcategory":"Clothing, Apparel, & Fashions",
            "type":"Retail Goods"
        }
    ],
    "sg:phone":"+44 115 928 6411",
    "sg:postcode":"NG8 4GS",
    "sg:province":"Nottinghamshire",
    "sg:tags":[
        "workwear",
        "protective"
    ],
    "wof:name":"Arco Ltd.",
    "wof:placetype":"venue"
},
  "geometry": {"coordinates":[-1.23119,52.963161],"type":"Point"}
}