{
  "type": "Feature",
  "properties": {
    "iso:country":"GB",
    "sg:address":"73 High Street",
    "sg:city":"Fraserburgh",
    "sg:classifiers":[
        {
            "category":"Shopping",
            "subcategory":"Baby Store",
            "type":"Retail Goods"
        }
    ],
    "sg:phone":"+44 1346 516607",
    "sg:postcode":"AB43 9ET",
    "sg:province":"Aberdeenshire",
    "sg:tags":[
        "babywear",
        "childrens"
    ],
    "wof:name":"Aileens",
    "wof:placetype":"venue"
},
  "geometry": {"coordinates":[-2.017819,57.687931],"type":"Point"}
}