{
  "type": "Feature",
  "properties": {
    "iso:country":"GB",
    "sg:address":"19 Burton Av",
    "sg:city":"Altrincham",
    "sg:classifiers":[
        {
            "category":"Shopping",
            "subcategory":"Pharmacy",
            "type":"Retail Goods"
        }
    ],
    "sg:phone":"+44 161 962 6234",
    "sg:postcode":"WA15 6AQ",
    "sg:province":"Cheshire",
    "sg:tags":[
        "medicine",
        "therapy"
    ],
    "wof:name":"M Howarth",
    "wof:placetype":"venue"
},
  "geometry": {"coordinates":[-2.3287520409,53.4072494507],"type":"Point"}
}