{
  "type": "Feature",
  "properties": {
    "iso:country":"GB",
    "sg:address":"Chatham Road, Boxley",
    "sg:city":"Maidstone",
    "sg:classifiers":[
        {
            "category":"Sports & Exercise",
            "subcategory":"Golf",
            "type":"Entertainment"
        }
    ],
    "sg:phone":"+44 1622 753276",
    "sg:postcode":"ME14 3AZ",
    "sg:province":"Kent",
    "sg:tags":[
        "club",
        "course"
    ],
    "wof:name":"Cobtree Manor Park Golf Course",
    "wof:placetype":"venue"
},
  "geometry": {"coordinates":[0.514252,51.306789],"type":"Point"}
}