{
  "type": "Feature",
  "properties": {
    "iso:country":"GB",
    "sg:address":"Stather Road, Flixborough",
    "sg:city":"Scunthorpe",
    "sg:classifiers":[
        {
            "category":"Manufacturing",
            "subcategory":"Rubber & Plastics",
            "type":"Manufacturing & Wholesale Goods"
        }
    ],
    "sg:postcode":"DN15 8RR",
    "sg:province":"Lincolnshire",
    "sg:tags":[
        "product"
    ],
    "wof:name":"Crystal Polymers Ltd.",
    "wof:placetype":"venue"
},
  "geometry": {"coordinates":[-0.683625,53.624676],"type":"Point"}
}