{
  "type": "Feature",
  "properties": {
    "addr:full":"Star Lane Indstl Est, Great Wakering Southend-on-sea Essex SS3 0PJ",
    "addr:postcode":"ss3 0pj",
    "addr:street":"Star Lane Indstl Est",
    "iso:country":"GB",
    "sg:address":"Star Lane Indstl Est, Great Wakering",
    "sg:city":"Southend-on-sea",
    "sg:classifiers":[
        {
            "category":"Retail",
            "subcategory":"Auto Repair",
            "type":"Services"
        }
    ],
    "sg:postcode":"SS3 0PJ",
    "sg:province":"Essex",
    "sg:tags":[
        "body",
        "car"
    ],
    "wof:name":"Bondlet Ltd",
    "wof:placetype":"venue"
},
  "geometry": {"coordinates":[0.7874360085,51.5515708923],"type":"Point"}
}