{
  "type": "Feature",
  "properties": {
    "iso:country":"GB",
    "sg:address":"The Workshop, Johnson Terrace",
    "sg:city":"Stanley",
    "sg:classifiers":[
        {
            "category":"Manufacturing",
            "subcategory":"Wood Products",
            "type":"Manufacturing & Wholesale Goods"
        }
    ],
    "sg:postcode":"DH9 7UR",
    "sg:province":"Durham",
    "sg:tags":[
        "sawmill",
        "shaving"
    ],
    "wof:name":"Johnson's Joinery",
    "wof:placetype":"venue"
},
  "geometry": {"coordinates":[-1.690338,54.872379],"type":"Point"}
}