{
  "type": "Feature",
  "properties": {
    "iso:country":"GB",
    "sg:address":"Fairy Court Hotel, Westhill Rd",
    "sg:city":"Shanklin",
    "sg:classifiers":[
        {
            "category":"Bus Charters",
            "type":"Transportation"
        }
    ],
    "sg:postcode":"PO37 6PZ",
    "sg:province":"Isle of Wight",
    "sg:tags":[
        "coach"
    ],
    "wof:name":"Fairy Wedding Cars",
    "wof:placetype":"venue"
},
  "geometry": {"coordinates":[-1.179239,50.626976],"type":"Point"}
}