{
  "type": "Feature",
  "properties": {
    "addr:full":"13 Woodlands Ossett West Yorkshire WF5 9PY",
    "addr:housenumber":"13",
    "addr:postcode":"wf5 9py",
    "addr:street":"Woodlands Ossett West",
    "iso:country":"GB",
    "sg:address":"13 Woodlands",
    "sg:city":"Ossett",
    "sg:classifiers":[
        {
            "category":"Professional",
            "type":"Services"
        }
    ],
    "sg:phone":"+44 1924 276602",
    "sg:postcode":"WF5 9PY",
    "sg:province":"West Yorkshire",
    "sg:tags":[
        "shopfitters"
    ],
    "wof:name":"Storefitting Services Ltd.",
    "wof:placetype":"venue"
},
  "geometry": {"coordinates":[-1.582144,53.689037],"type":"Point"}
}