{
  "type": "Feature",
  "properties": {
    "addr:full":"302 Middle Park Way Havant Hampshire PO9 4NL",
    "addr:housenumber":"302",
    "addr:postcode":"po9 4nl",
    "addr:street":"Middle Park Way",
    "iso:country":"GB",
    "sg:address":"302 Middle Park Way",
    "sg:city":"Havant",
    "sg:classifiers":[
        {
            "category":"Building & Trades",
            "subcategory":"Landscaping Services",
            "type":"Services"
        }
    ],
    "sg:phone":"+44 23 9247 3065",
    "sg:postcode":"PO9 4NL",
    "sg:province":"Hampshire",
    "sg:tags":[
        "forestry",
        "tree"
    ],
    "wof:name":"A J & P Hawley",
    "wof:placetype":"venue"
},
  "geometry": {"coordinates":[-0.99109,50.872807],"type":"Point"}
}