{
  "type": "Feature",
  "properties": {
    "addr:full":"21 Elsee Rd Rugby Warwickshire CV21 3BA",
    "addr:housenumber":"21",
    "addr:postcode":"cv21 3ba",
    "addr:street":"Elsee Rd",
    "iso:country":"GB",
    "sg:address":"21 Elsee Rd",
    "sg:city":"Rugby",
    "sg:classifiers":[
        {
            "category":"Professional",
            "subcategory":"Computer Services",
            "type":"Services"
        }
    ],
    "sg:postcode":"CV21 3BA",
    "sg:province":"Warwickshire",
    "sg:tags":[
        "system",
        "software"
    ],
    "wof:name":"Sargunar,E,",
    "wof:placetype":"venue"
},
  "geometry": {"coordinates":[-1.2588759661,52.3711547852],"type":"Point"}
}