{
  "type": "Feature",
  "properties": {
    "addr:full":"35 Nevill St Southport Lancashire PR9 0DE",
    "addr:housenumber":"35",
    "addr:postcode":"pr9 0de",
    "addr:street":"Nevill St",
    "iso:country":"GB",
    "sg:address":"35 Nevill St",
    "sg:city":"Southport",
    "sg:classifiers":[
        {
            "category":"Food & Beverages",
            "subcategory":"Candy",
            "type":"Retail Goods"
        }
    ],
    "sg:phone":"+44 1704 540276",
    "sg:postcode":"PR9 0DE",
    "sg:province":"Lancashire",
    "sg:tags":[
        "confectioner"
    ],
    "wof:name":"Southport Rock Co",
    "wof:placetype":"venue"
},
  "geometry": {"coordinates":[-3.006071,53.64957],"type":"Point"}
}