{
  "type": "Feature",
  "properties": {
    "addr:full":"Hurst End Farm Newport Pagnell Buckinghamshire MK16 9HS",
    "addr:postcode":"mk16 9hs",
    "addr:street":"Hurst",
    "iso:country":"GB",
    "sg:address":"Hurst End Farm",
    "sg:city":"Newport Pagnell",
    "sg:classifiers":[
        {
            "category":"Building & Trades",
            "subcategory":"Construction",
            "type":"Services"
        }
    ],
    "sg:postcode":"MK16 9HS",
    "sg:province":"Buckinghamshire",
    "sg:tags":[
        "fork",
        "lift",
        "truck"
    ],
    "wof:name":"Beds & Bucks Forktrucks Ltd.",
    "wof:placetype":"venue"
},
  "geometry": {"coordinates":[-0.6508700252,52.0826911926],"type":"Point"}
}