{
  "type": "Feature",
  "properties": {
    "iso:country":"GB",
    "sg:address":"19 Down Rd",
    "sg:city":"Bexhill On Sea",
    "sg:classifiers":[
        {
            "category":"Professional",
            "subcategory":"Engineering",
            "type":"Services"
        }
    ],
    "sg:phone":"+44 1424 220166",
    "sg:postcode":"TN39 4HD",
    "sg:province":"East Sussex",
    "sg:tags":[
        "contractor",
        "electrical",
        "engineer"
    ],
    "wof:name":"A Z L Electrical",
    "wof:placetype":"venue"
},
  "geometry": {"coordinates":[0.460943,50.849918],"type":"Point"}
}