{
  "type": "Feature",
  "properties": {
    "iso:country":"GB",
    "sg:address":"87 Trent Rd",
    "sg:city":"Oldham",
    "sg:classifiers":[
        {
            "category":"Building & Trades",
            "subcategory":"Plumbing",
            "type":"Services"
        }
    ],
    "sg:postcode":"OL2 7YQ",
    "sg:province":"Lancashire",
    "sg:tags":[
        "heating"
    ],
    "wof:name":"Jones,H,& Co",
    "wof:placetype":"venue"
},
  "geometry": {"coordinates":[-2.102048,53.586021],"type":"Point"}
}