{
  "type": "Feature",
  "properties": {
    "addr:full":"1 Lammermoor Drive, Cumbernauld Glasgow Falkirk G67 4BE",
    "addr:housenumber":"1",
    "addr:postcode":"g67 4be",
    "addr:street":"Lammermoor Drive",
    "iso:country":"GB",
    "sg:address":"1 Lammermoor Drive, Cumbernauld",
    "sg:city":"Glasgow",
    "sg:classifiers":[
        {
            "category":"Manufacturing",
            "subcategory":"Furniture",
            "type":"Manufacturing & Wholesale Goods"
        }
    ],
    "sg:phone":"+44 1236 732310",
    "sg:postcode":"G67 4BE",
    "sg:province":"Falkirk",
    "sg:tags":[
        "mnfr",
        "upholsterer"
    ],
    "wof:name":"E.J Murrin",
    "wof:placetype":"venue"
},
  "geometry": {"coordinates":[-4.0008740425,55.9375038147],"type":"Point"}
}