{
  "type": "Feature",
  "properties": {
    "iso:country":"GB",
    "sg:address":"Llanerch Farm, Llanvihangel",
    "sg:city":"Abergavenny",
    "sg:classifiers":[
        {
            "category":"Farming",
            "subcategory":"Livestock Farm",
            "type":"Manufacturing & Wholesale Goods"
        }
    ],
    "sg:phone":"+44 1873 890432",
    "sg:postcode":"NP7 8EW",
    "sg:province":"Herefordshire",
    "sg:tags":[
        "others"
    ],
    "wof:name":"Roger J Ikin",
    "wof:placetype":"venue"
},
  "geometry": {"coordinates":[-3.0206799507,51.8250083923],"type":"Point"}
}