{
  "type": "Feature",
  "properties": {
    "iso:country":"GB",
    "sg:address":"41 First Avenue",
    "sg:city":"Gillingham",
    "sg:classifiers":[
        {
            "category":"Personal",
            "type":"Services"
        }
    ],
    "sg:phone":"+44 1634 580180",
    "sg:postcode":"ME7 2LH",
    "sg:province":"Kent",
    "sg:tags":[
        "consultant",
        "fitness"
    ],
    "wof:name":"Rosemary Conley Diet & Fitness Club",
    "wof:placetype":"venue"
},
  "geometry": {"coordinates":[0.561255,51.373802],"type":"Point"}
}