{
  "type": "Feature",
  "properties": {
    "iso:country":"GB",
    "sg:address":"Pier St",
    "sg:city":"Poplar",
    "sg:classifiers":[
        {
            "category":"Sports & Exercise",
            "subcategory":"Stables",
            "type":"Entertainment"
        }
    ],
    "sg:phone":"+44 20 7515 0749",
    "sg:postcode":"E14 9HP",
    "sg:province":"Greater London",
    "sg:tags":[
        "education",
        "equestrian"
    ],
    "wof:name":"Mudchute Farm Stables",
    "wof:placetype":"venue"
},
  "geometry": {"coordinates":[-0.01264,51.500408],"type":"Point"}
}