{
  "type": "Feature",
  "properties": {
    "addr:full":"6 Himley Lane, Himley Dudley Staffordshire DY3 4LN",
    "addr:housenumber":"6",
    "addr:postcode":"dy3 4ln",
    "addr:street":"Himley Lane",
    "iso:country":"GB",
    "sg:address":"6 Himley Lane, Himley",
    "sg:city":"Dudley",
    "sg:classifiers":[
        {
            "category":"Building & Trades",
            "subcategory":"Construction",
            "type":"Services"
        }
    ],
    "sg:phone":"+44 1902 892876",
    "sg:postcode":"DY3 4LN",
    "sg:province":"Staffordshire",
    "sg:tags":[
        "glazier",
        "decorator",
        "painter"
    ],
    "wof:name":"Lawrence Malcolm Sneyd",
    "wof:placetype":"venue"
},
  "geometry": {"coordinates":[-2.182973,52.517914],"type":"Point"}
}