{
  "type": "Feature",
  "properties": {
    "addr:full":"104 Station Rd Harrow Greater London HA1 2RX",
    "addr:housenumber":"104",
    "addr:postcode":"ha1 2rx",
    "addr:street":"Station Rd",
    "iso:country":"GB",
    "sg:address":"104 Station Rd",
    "sg:city":"Harrow",
    "sg:classifiers":[
        {
            "category":"Autos & Motor Vehicles",
            "subcategory":"Automobile Sales",
            "type":"Retail Goods"
        }
    ],
    "sg:phone":"+44 20 8863 4433",
    "sg:postcode":"HA1 2RX",
    "sg:province":"Greater London",
    "sg:tags":[
        "car"
    ],
    "wof:name":"Harrow Carmart",
    "wof:placetype":"venue"
},
  "geometry": {"coordinates":[-0.332087,51.586353],"type":"Point"}
}