{
  "type": "Feature",
  "properties": {
    "addr:full":", Horam Heathfield East Sussex TN21 0YD",
    "addr:housenumber":"horam",
    "addr:postcode":"tn21 0yd",
    "addr:street":"Heathfield",
    "iso:country":"GB",
    "sg:address":", Horam",
    "sg:city":"Heathfield",
    "sg:classifiers":[
        {
            "category":"Recreation",
            "subcategory":"Campground",
            "type":"Entertainment"
        }
    ],
    "sg:phone":"+44 1435 813662",
    "sg:postcode":"TN21 0YD",
    "sg:province":"East Sussex",
    "sg:tags":[
        "operator",
        "site",
        "camping"
    ],
    "wof:name":"Horam Manor Touring Park",
    "wof:placetype":"venue"
},
  "geometry": {"coordinates":[0.2429649979,50.93359375],"type":"Point"}
}