{
  "type": "Feature",
  "properties": {
    "addr:full":"17 High Street, St Neots Huntingdon Bedfordshire PE19 1BU",
    "addr:housenumber":"17",
    "addr:postcode":"pe19 1bu",
    "addr:street":"High Street",
    "iso:country":"GB",
    "sg:address":"17 High Street, St Neots",
    "sg:city":"Huntingdon",
    "sg:classifiers":[
        {
            "category":"Food & Beverages",
            "subcategory":"Meat & Fish",
            "type":"Retail Goods"
        }
    ],
    "sg:phone":"+44 1480 477500",
    "sg:postcode":"PE19 1BU",
    "sg:province":"Bedfordshire",
    "sg:tags":[
        "butcher"
    ],
    "wof:name":"Hall Farm Fine Produce",
    "wof:placetype":"venue"
},
  "geometry": {"coordinates":[-0.2682639956,52.2281951904],"type":"Point"}
}