{
  "type": "Feature",
  "properties": {
    "iso:country":"GB",
    "sg:address":"29 Denmark St",
    "sg:city":"Bristol",
    "sg:classifiers":[
        {
            "category":"Food & Beverages",
            "subcategory":"Ethnic Foods",
            "type":"Retail Goods"
        }
    ],
    "sg:postcode":"BS1 5DQ",
    "sg:province":"City of Bristol",
    "sg:tags":[
        "merchant",
        "oil",
        "essential"
    ],
    "wof:name":"Aromatherapy Supply Co",
    "wof:placetype":"venue"
},
  "geometry": {"coordinates":[-2.59805,51.452988],"type":"Point"}
}