{
  "type": "Feature",
  "properties": {
    "addr:full":"Derby City Transport, Ascot Dr Derby Derbyshire DE24 8GW",
    "addr:postcode":"de24 8gw",
    "addr:street":"Ascot Dr",
    "iso:country":"GB",
    "sg:address":"Derby City Transport, Ascot Dr",
    "sg:city":"Derby",
    "sg:classifiers":[
        {
            "category":"Professional",
            "subcategory":"Advertising",
            "type":"Services"
        }
    ],
    "sg:phone":"+44 1332 754457",
    "sg:postcode":"DE24 8GW",
    "sg:province":"Derbyshire",
    "sg:tags":[
        "outdoor"
    ],
    "wof:name":"T D I Advertising Ltd",
    "wof:placetype":"venue"
},
  "geometry": {"coordinates":[-1.4520900249,52.8981513977],"type":"Point"}
}