{
  "type": "Feature",
  "properties": {
    "iso:country":"GB",
    "sg:address":"107 Brook Street",
    "sg:city":"Chester",
    "sg:classifiers":[
        {
            "category":"Personal",
            "subcategory":"Beauty Salon",
            "type":"Services"
        }
    ],
    "sg:postcode":"CH1 3DX",
    "sg:province":"Cheshire",
    "sg:tags":[
        "unisex",
        "hairdresser"
    ],
    "wof:name":"Roger Barri",
    "wof:placetype":"venue"
},
  "geometry": {"coordinates":[-2.885258,53.196037],"type":"Point"}
}