{
  "type": "Feature",
  "properties": {
    "iso:country":"GB",
    "sg:address":"Thompson House, 42-44 Dolben Street",
    "sg:city":"London",
    "sg:classifiers":[
        {
            "category":"Coffee & Tea",
            "type":"Food & Drink"
        }
    ],
    "sg:phone":"+44 20 7620 2304",
    "sg:postcode":"SE1 0UQ",
    "sg:province":"Greater London",
    "wof:name":"Thompson Lloyd & Ewart Ltd.",
    "wof:placetype":"venue"
},
  "geometry": {"coordinates":[-0.101839,51.504848],"type":"Point"}
}