{
  "type": "Feature",
  "properties": {
    "addr:full":"82 Fishergate Preston Lancashire PR1 2NJ",
    "addr:housenumber":"82",
    "addr:postcode":"pr1 2nj",
    "addr:street":"Fishergate Preston",
    "iso:country":"GB",
    "sg:address":"82 Fishergate",
    "sg:city":"Preston",
    "sg:classifiers":[
        {
            "category":"Real Estate",
            "subcategory":"Real Estate Operator",
            "type":"Services"
        }
    ],
    "sg:phone":"+44 1772 880908",
    "sg:postcode":"PR1 2NJ",
    "sg:province":"Lancashire",
    "sg:tags":[
        "letting",
        "agent"
    ],
    "wof:name":"General Accident Property Services",
    "wof:placetype":"venue"
},
  "geometry": {"coordinates":[-2.7055850029,53.7576141357],"type":"Point"}
}