{
  "type": "Feature",
  "properties": {
    "addr:full":"201 Sydenham Road London Greater London SE26 5HF",
    "addr:housenumber":"201",
    "addr:postcode":"se26 5hf",
    "addr:street":"Sydenham Road",
    "iso:country":"GB",
    "sg:address":"201 Sydenham Road",
    "sg:city":"London",
    "sg:classifiers":[
        {
            "category":"Retail",
            "subcategory":"Auto Repair",
            "type":"Services"
        }
    ],
    "sg:phone":"+44 20 8659 2263",
    "sg:postcode":"SE26 5HF",
    "sg:province":"Greater London",
    "sg:tags":[
        "modification",
        "garage"
    ],
    "wof:name":"M & K Citroen",
    "wof:placetype":"venue"
},
  "geometry": {"coordinates":[-0.0453759991,51.4258308411],"type":"Point"}
}