{
  "type": "Feature",
  "properties": {
    "addr:full":"Acrefield, Boundary Road Bishops Stortford Essex CM23 5LE",
    "addr:postcode":"cm23 5le",
    "addr:street":"Acrefield Boundary Road",
    "iso:country":"GB",
    "sg:address":"Acrefield, Boundary Road",
    "sg:city":"Bishops Stortford",
    "sg:classifiers":[
        {
            "category":"Real Estate",
            "subcategory":"Developer",
            "type":"Services"
        },
        {
            "category":"Real Estate",
            "subcategory":"Real Estate Agent",
            "type":"Services"
        }
    ],
    "sg:phone":"+44 1279 465577",
    "sg:postcode":"CM23 5LE",
    "sg:province":"Essex",
    "sg:tags":[
        "property"
    ],
    "wof:name":"Chain Breakers",
    "wof:placetype":"venue"
},
  "geometry": {"coordinates":[0.1619559973,51.8723564148],"type":"Point"}
}