{
  "type": "Feature",
  "properties": {
    "iso:country":"GB",
    "sg:address":"21 Church Street",
    "sg:city":"Cromer",
    "sg:classifiers":[
        {
            "category":"Professional",
            "subcategory":"Business Services",
            "type":"Services"
        },
        {
            "category":"Organizations",
            "subcategory":"Non-profit Organization",
            "type":"Services"
        }
    ],
    "sg:phone":"+44 1263 512818",
    "sg:postcode":"NR27 9ES",
    "sg:province":"Norfolk",
    "sg:tags":[
        "voluntary",
        "organisation",
        "agent",
        "export",
        "import",
        "charity"
    ],
    "wof:name":"The Childrens Society",
    "wof:placetype":"venue"
},
  "geometry": {"coordinates":[1.302387,52.930447],"type":"Point"}
}