{
  "type": "Feature",
  "properties": {
    "addr:full":"58 High Street, Meadowhall Centre Sheffield South Yorkshire S9 1EN",
    "addr:housenumber":"58",
    "addr:postcode":"s9 1en",
    "addr:street":"High Street",
    "iso:country":"GB",
    "sg:address":"58 High Street, Meadowhall Centre",
    "sg:city":"Sheffield",
    "sg:classifiers":[
        {
            "category":"Shopping",
            "subcategory":"Beauty & Cosmetics",
            "type":"Retail Goods"
        }
    ],
    "sg:phone":"+44 114 256 8429",
    "sg:postcode":"S9 1EN",
    "sg:province":"South Yorkshire",
    "sg:tags":[
        "product"
    ],
    "wof:name":"The Body Shop",
    "wof:placetype":"venue"
},
  "geometry": {"coordinates":[-1.391479,53.41275],"type":"Point"}
}