{
  "type": "Feature",
  "properties": {
    "iso:country":"GB",
    "sg:address":"35 Lower Bridge Street",
    "sg:city":"Chester",
    "sg:classifiers":[
        {
            "category":"Shopping",
            "subcategory":"News",
            "type":"Retail Goods"
        }
    ],
    "sg:phone":"+44 1244 316864",
    "sg:postcode":"CH1 1RW",
    "sg:province":"Cheshire",
    "sg:tags":[
        "newsagent"
    ],
    "wof:name":"Bridgegate Stores",
    "wof:placetype":"venue"
},
  "geometry": {"coordinates":[-2.8903310299,53.1878700256],"type":"Point"}
}