{
  "type": "Feature",
  "properties": {
    "iso:country":"GB",
    "sg:address":"26 Anchorsholme Lane East",
    "sg:city":"Thornton-cleveleys",
    "sg:classifiers":[
        {
            "category":"Fast Food",
            "type":"Food & Drink"
        }
    ],
    "sg:phone":"+44 1253 823596",
    "sg:postcode":"FY5 3QL",
    "sg:province":"Lancashire",
    "sg:tags":[
        "away",
        "meal",
        "outlet",
        "take"
    ],
    "wof:name":"Pearl City Chinese Takeaway",
    "wof:placetype":"venue"
},
  "geometry": {"coordinates":[-3.0411920547,53.8721618652],"type":"Point"}
}