{
  "type": "Feature",
  "properties": {
    "addr:full":"11 Ingram Street Huntingdon Cambridgeshire PE29 3QG",
    "addr:housenumber":"11",
    "addr:postcode":"pe29 3qg",
    "addr:street":"Ingram Street",
    "iso:country":"GB",
    "sg:address":"11 Ingram Street",
    "sg:city":"Huntingdon",
    "sg:classifiers":[
        {
            "category":"Building & Trades",
            "subcategory":"Construction",
            "type":"Services"
        }
    ],
    "sg:phone":"+44 1480 453753",
    "sg:postcode":"PE29 3QG",
    "sg:province":"Cambridgeshire",
    "sg:tags":[
        "builder"
    ],
    "wof:name":"Ashley & Foster",
    "wof:placetype":"venue"
},
  "geometry": {"coordinates":[-0.1794780046,52.3294677734],"type":"Point"}
}