{
  "type": "Feature",
  "properties": {
    "addr:full":"Long Walk Cottage, Bdwy, Fairlight Hastings East Sussex TN35 4DA",
    "addr:postcode":"tn35 4da",
    "addr:street":"Long;Bdwy;Hastings",
    "iso:country":"GB",
    "sg:address":"Long Walk Cottage, Bdwy, Fairlight",
    "sg:city":"Hastings",
    "sg:classifiers":[
        {
            "category":"Autos & Motor Vehicles",
            "subcategory":"Motorcycle Sales",
            "type":"Retail Goods"
        }
    ],
    "sg:postcode":"TN35 4DA",
    "sg:province":"East Sussex",
    "sg:tags":[
        "chauffeur",
        "driven",
        "car"
    ],
    "wof:name":"Rye Classics Car Hire",
    "wof:placetype":"venue"
},
  "geometry": {"coordinates":[0.6655399799,50.8778495789],"type":"Point"}
}