{
  "type": "Feature",
  "properties": {
    "iso:country":"GB",
    "sg:address":"37 Lower Cippenham Lane",
    "sg:city":"Slough",
    "sg:classifiers":[
        {
            "category":"Professional",
            "subcategory":"Engineering",
            "type":"Services"
        }
    ],
    "sg:postcode":"SL1 5DG",
    "sg:province":"Berkshire",
    "sg:tags":[
        "contractor",
        "electrical",
        "engineer"
    ],
    "wof:name":"James Eastop",
    "wof:placetype":"venue"
},
  "geometry": {"coordinates":[-0.6299020052,51.5133056641],"type":"Point"}
}