{
  "type": "Feature",
  "properties": {
    "addr:full":"Deepdale Farm, Lutterworth Road, Burbage Hinckley Leicestershire LE10 2DL",
    "addr:postcode":"le10 2dl",
    "addr:street":"Lutterworth Road",
    "iso:country":"GB",
    "sg:address":"Deepdale Farm, Lutterworth Road, Burbage",
    "sg:city":"Hinckley",
    "sg:classifiers":[
        {
            "category":"Freight",
            "type":"Transportation"
        }
    ],
    "sg:phone":"+44 1455 615559",
    "sg:postcode":"LE10 2DL",
    "sg:province":"Leicestershire",
    "sg:tags":[
        "haulage",
        "road"
    ],
    "wof:name":"G Atkinson & Sons Ltd.",
    "wof:placetype":"venue"
},
  "geometry": {"coordinates":[-1.348572,52.530193],"type":"Point"}
}