{
  "type": "Feature",
  "properties": {
    "iso:country":"GB",
    "sg:address":"Waters Edge, The Bridge",
    "sg:city":"Abingdon",
    "sg:classifiers":[
        {
            "category":"Home & Garden",
            "subcategory":"Home Furnishings",
            "type":"Retail Goods"
        }
    ],
    "sg:postcode":"OX14 3HY",
    "sg:province":"Oxfordshire",
    "sg:tags":[
        "blind",
        "curtain",
        "fitting"
    ],
    "wof:name":"Maggie Leonard Soft Furnishings",
    "wof:placetype":"venue"
},
  "geometry": {"coordinates":[-1.210504,51.657696],"type":"Point"}
}