{
  "type": "Feature",
  "properties": {
    "iso:country":"GB",
    "sg:address":"353 South Street",
    "sg:city":"Romford",
    "sg:classifiers":[
        {
            "category":"Social Services",
            "subcategory":"Retirement Home",
            "type":"Services"
        }
    ],
    "sg:postcode":"RM1 2AP",
    "sg:province":"Essex",
    "sg:tags":[
        "residential",
        "care"
    ],
    "wof:name":"Tara Lodge",
    "wof:placetype":"venue"
},
  "geometry": {"coordinates":[0.1867650002,51.5669403076],"type":"Point"}
}