{
  "type": "Feature",
  "properties": {
    "iso:country":"GB",
    "sg:address":"1 St Andrews Road, Bletchley",
    "sg:city":"Milton Keynes",
    "sg:classifiers":[
        {
            "category":"Building & Trades",
            "subcategory":"Construction",
            "type":"Services"
        }
    ],
    "sg:phone":"+44 1908 632278",
    "sg:postcode":"MK3 5DR",
    "sg:province":"Buckinghamshire",
    "sg:tags":[
        "builder"
    ],
    "wof:name":"Bcg",
    "wof:placetype":"venue"
},
  "geometry": {"coordinates":[-0.7592539787,51.989074707],"type":"Point"}
}