{
  "type": "Feature",
  "properties": {
    "addr:full":"Kenton Lane Harrow Greater London HA3 7LH",
    "addr:postcode":"ha3 7lh",
    "addr:street":"Kenton Lane",
    "iso:country":"GB",
    "sg:address":"Kenton Lane",
    "sg:city":"Harrow",
    "sg:classifiers":[
        {
            "category":"Travel",
            "subcategory":"Hostel",
            "type":"Entertainment"
        }
    ],
    "sg:phone":"+44 20 8427 8965",
    "sg:postcode":"HA3 7LH",
    "sg:province":"Greater London",
    "wof:name":"Vernon Lodge",
    "wof:placetype":"venue"
},
  "geometry": {"coordinates":[-0.3272129893,51.6036911011],"type":"Point"}
}