{
  "type": "Feature",
  "properties": {
    "addr:full":"6 Mungle Street West Calder South Lanarkshire EH55 8BX",
    "addr:housenumber":"6",
    "addr:postcode":"eh55 8bx",
    "addr:street":"Mungle Street",
    "iso:country":"GB",
    "sg:address":"6 Mungle Street",
    "sg:city":"West Calder",
    "sg:classifiers":[
        {
            "category":"Communications",
            "type":"Services"
        },
        {
            "category":"Shopping",
            "subcategory":"Luggage & Leather Goods",
            "type":"Retail Goods"
        }
    ],
    "sg:phone":"+44 1506 871365",
    "sg:postcode":"EH55 8BX",
    "sg:province":"South Lanarkshire",
    "sg:tags":[
        "shop",
        "tv",
        "video",
        "radio",
        "leathergoods"
    ],
    "wof:name":"Lothian Electronics",
    "wof:placetype":"venue"
},
  "geometry": {"coordinates":[-3.571789,55.851528],"type":"Point"}
}