{
  "type": "Feature",
  "properties": {
    "iso:country":"GB",
    "sg:address":"Unit 2, Satmar Farm",
    "sg:city":"Folkestone",
    "sg:classifiers":[
        {
            "category":"Building & Trades",
            "subcategory":"Construction",
            "type":"Services"
        }
    ],
    "sg:phone":"+44 1303 240789",
    "sg:postcode":"CT18 7JF",
    "sg:province":"Kent",
    "sg:tags":[
        "joinery"
    ],
    "wof:name":"M M  Macey",
    "wof:placetype":"venue"
},
  "geometry": {"coordinates":[1.219597,51.113209],"type":"Point"}
}