{
  "type": "Feature",
  "properties": {
    "iso:country":"GB",
    "sg:address":"91 Springvale Road",
    "sg:city":"Winchester",
    "sg:classifiers":[
        {
            "category":"Building & Trades",
            "subcategory":"Plumbing",
            "type":"Services"
        }
    ],
    "sg:postcode":"SO23 7RB",
    "sg:province":"Hampshire",
    "sg:tags":[
        "central",
        "heating"
    ],
    "wof:name":"Worthy Heating",
    "wof:placetype":"venue"
},
  "geometry": {"coordinates":[-1.3034950495,51.1007385254],"type":"Point"}
}