{
  "type": "Feature",
  "properties": {
    "addr:full":"14 Red Lion Way High Wycombe Buckinghamshire HP10 0HT",
    "addr:housenumber":"14",
    "addr:postcode":"hp10 0ht",
    "addr:street":"Red Lion Way",
    "iso:country":"GB",
    "sg:address":"14 Red Lion Way",
    "sg:city":"High Wycombe",
    "sg:classifiers":[
        {
            "category":"Building & Trades",
            "subcategory":"Landscaping Services",
            "type":"Services"
        }
    ],
    "sg:phone":"+44 1628 530254",
    "sg:postcode":"HP10 0HT",
    "sg:province":"Buckinghamshire",
    "sg:tags":[
        "landscape",
        "contractor"
    ],
    "wof:name":"Mark Gethin",
    "wof:placetype":"venue"
},
  "geometry": {"coordinates":[-0.6843739748,51.5895195007],"type":"Point"}
}