{
  "type": "Feature",
  "properties": {
    "iso:country":"GB",
    "sg:address":"12 Nyewood Lane",
    "sg:city":"Bognor Regis",
    "sg:classifiers":[
        {
            "category":"Social Services",
            "subcategory":"Retirement Home",
            "type":"Services"
        }
    ],
    "sg:postcode":"PO21 2QB",
    "sg:province":"West Sussex",
    "sg:tags":[
        "rest"
    ],
    "wof:name":"Barham Manor",
    "wof:placetype":"venue"
},
  "geometry": {"coordinates":[-0.687922,50.780483],"type":"Point"}
}