{
  "type": "Feature",
  "properties": {
    "iso:country":"GB",
    "sg:address":"2 West Park Road",
    "sg:city":"St Helens",
    "sg:classifiers":[
        {
            "category":"Real Estate",
            "subcategory":"Architect",
            "type":"Services"
        }
    ],
    "sg:phone":"+44 1744 24263",
    "sg:postcode":"WA10 4LJ",
    "sg:province":"Merseyside",
    "wof:name":"J M Wilson & Son",
    "wof:placetype":"venue"
},
  "geometry": {"coordinates":[-2.757074,53.448524],"type":"Point"}
}