{
  "type": "Feature",
  "properties": {
    "iso:country":"GB",
    "sg:address":"Sefton Place, Warningcamp",
    "sg:city":"Arundel",
    "sg:classifiers":[
        {
            "category":"Travel",
            "subcategory":"Hostel",
            "type":"Entertainment"
        }
    ],
    "sg:phone":"+44 1903 882204",
    "sg:postcode":"BN18 9QY",
    "sg:province":"West Sussex",
    "sg:tags":[
        "youth"
    ],
    "wof:name":"Youth Hostels Association (England & Wales)",
    "wof:placetype":"venue"
},
  "geometry": {"coordinates":[-0.554589,50.854836],"type":"Point"}
}