{
  "type": "Feature",
  "properties": {
    "iso:country":"GB",
    "sg:address":"16 Western St",
    "sg:city":"Brighton",
    "sg:classifiers":[
        {
            "category":"Bars & Pubs",
            "type":"Food & Drink"
        }
    ],
    "sg:phone":"+44 1273 737287",
    "sg:postcode":"BN1 2PG",
    "sg:province":"East Sussex",
    "sg:tags":[
        "pubs",
        "inn"
    ],
    "wof:name":"The Grosvenor Arms",
    "wof:placetype":"venue"
},
  "geometry": {"coordinates":[-0.1555480063,50.8238792419],"type":"Point"}
}