{
  "type": "Feature",
  "properties": {
    "addr:full":"Hawkstone Road Pembroke Dock Pembrokeshire SA72 6HN",
    "addr:postcode":"sa72 6hn",
    "addr:street":"Hawkstone Road",
    "iso:country":"GB",
    "sg:address":"Hawkstone Road",
    "sg:city":"Pembroke Dock",
    "sg:classifiers":[
        {
            "category":"Social Services",
            "subcategory":"Adult Care",
            "type":"Services"
        }
    ],
    "sg:phone":"+44 1646 686221",
    "sg:postcode":"SA72 6HN",
    "sg:province":"Pembrokeshire",
    "sg:tags":[
        "day",
        "centre"
    ],
    "wof:name":"Hawkstone Road Day Centre",
    "wof:placetype":"venue"
},
  "geometry": {"coordinates":[-4.9356389046,51.6931991577],"type":"Point"}
}