{
  "type": "Feature",
  "properties": {
    "iso:country":"GB",
    "sg:address":"Wareing Road",
    "sg:city":"Liverpool",
    "sg:classifiers":[
        {
            "category":"Personal",
            "type":"Services"
        }
    ],
    "sg:phone":"+44 151 523 5858",
    "sg:postcode":"L9 7AU",
    "sg:province":"Merseyside",
    "sg:tags":[
        "delivery"
    ],
    "wof:name":"Securicor Group",
    "wof:placetype":"venue"
},
  "geometry": {"coordinates":[-2.946804,53.461063],"type":"Point"}
}