{
  "type": "Feature",
  "properties": {
    "iso:country":"GB",
    "sg:address":"Unit 1, Meridian Trading Estate",
    "sg:city":"London",
    "sg:classifiers":[
        {
            "category":"Coffee & Tea",
            "type":"Food & Drink"
        }
    ],
    "sg:postcode":"SE7 7SW",
    "sg:province":"Greater London",
    "wof:name":"Rex Trading Ltd.",
    "wof:placetype":"venue"
},
  "geometry": {"coordinates":[0.02569,51.490528],"type":"Point"}
}