{
  "type": "Feature",
  "properties": {
    "iso:country":"GB",
    "sg:address":"2 Rossett Way, Little Acton",
    "sg:city":"Wrexham",
    "sg:classifiers":[
        {
            "category":"Professional",
            "subcategory":"Art Services",
            "type":"Services"
        }
    ],
    "sg:postcode":"LL12 8AT",
    "sg:province":"Wrexham",
    "sg:tags":[
        "photographer"
    ],
    "wof:name":"V Clevely",
    "wof:placetype":"venue"
},
  "geometry": {"coordinates":[-2.9890270233,53.0684204102],"type":"Point"}
}