{
  "type": "Feature",
  "properties": {
    "iso:country":"GB",
    "sg:address":"69 High Street, Earl Shilton",
    "sg:city":"Leicester",
    "sg:classifiers":[
        {
            "category":"Shopping",
            "subcategory":"Antiques",
            "type":"Retail Goods"
        }
    ],
    "sg:phone":"+44 1455 847922",
    "sg:postcode":"LE9 7DH",
    "sg:province":"Leicestershire",
    "wof:name":"Glory Hole Antiques",
    "wof:placetype":"venue"
},
  "geometry": {"coordinates":[-1.3102799654,52.5788345337],"type":"Point"}
}