{
  "type": "Feature",
  "properties": {
    "addr:full":"35 Woodwarde Rd East Dulwich Greater London SE22 8UN",
    "addr:housenumber":"35",
    "addr:postcode":"se22 8un",
    "addr:street":"Woodwarde Rd",
    "iso:country":"GB",
    "sg:address":"35 Woodwarde Rd",
    "sg:city":"East Dulwich",
    "sg:classifiers":[
        {
            "category":"Social Services",
            "subcategory":"Job Training",
            "type":"Services"
        }
    ],
    "sg:phone":"+44 20 8299 3625",
    "sg:postcode":"SE22 8UN",
    "sg:province":"Greater London",
    "sg:tags":[
        "translator",
        "interpreter"
    ],
    "wof:name":"J Jones MITI",
    "wof:placetype":"venue"
},
  "geometry": {"coordinates":[-0.076963,51.449867],"type":"Point"}
}