{
  "type": "Feature",
  "properties": {
    "iso:country":"GB",
    "sg:address":"Office 1 Unit B Silkmoor, New St",
    "sg:city":"Shrewsbury",
    "sg:classifiers":[
        {
            "category":"Health Services",
            "subcategory":"Nursing And Care Facility",
            "type":"Services"
        }
    ],
    "sg:phone":"+44 1743 245848",
    "sg:postcode":"SY3 8LN",
    "sg:province":"Shropshire",
    "sg:tags":[
        "agency"
    ],
    "wof:name":"Rosemary Williams R G N Nursing Services",
    "wof:placetype":"venue"
},
  "geometry": {"coordinates":[-2.76041,52.711029],"type":"Point"}
}