{
  "type": "Feature",
  "properties": {
    "addr:full":"Curtis Ho, 34 Third Av Hove East Sussex BN3 2PD",
    "addr:housenumber":"34",
    "addr:postcode":"bn3 2pd",
    "addr:street":"Third Av Hove",
    "iso:country":"GB",
    "sg:address":"Curtis Ho, 34 Third Av",
    "sg:city":"Hove",
    "sg:classifiers":[
        {
            "category":"Conference Center",
            "type":"Public Place"
        }
    ],
    "sg:phone":"+44 1273 220211",
    "sg:postcode":"BN3 2PD",
    "sg:province":"East Sussex",
    "wof:name":"Inntel",
    "wof:placetype":"venue"
},
  "geometry": {"coordinates":[-0.182449,50.838943],"type":"Point"}
}