{
  "type": "Feature",
  "properties": {
    "iso:country":"GB",
    "sg:address":"4 Roe St",
    "sg:city":"Macclesfield",
    "sg:classifiers":[
        {
            "category":"Shopping",
            "subcategory":"Clothing, Apparel, & Fashions",
            "type":"Retail Goods"
        }
    ],
    "sg:phone":"+44 1625 612505",
    "sg:postcode":"SK11 6UT",
    "sg:province":"Cheshire",
    "sg:tags":[
        "shop"
    ],
    "wof:name":"Worsleywear",
    "wof:placetype":"venue"
},
  "geometry": {"coordinates":[-2.126116,53.258049],"type":"Point"}
}