{
  "type": "Feature",
  "properties": {
    "iso:country":"GB",
    "sg:address":"Manor Farm, Church End, Wood Walton",
    "sg:city":"Huntingdon",
    "sg:classifiers":[
        {
            "category":"Farming",
            "subcategory":"Crops",
            "type":"Manufacturing & Wholesale Goods"
        },
        {
            "category":"Farming",
            "subcategory":"Farm",
            "type":"Manufacturing & Wholesale Goods"
        }
    ],
    "sg:phone":"+44 1487 831843",
    "sg:postcode":"PE28 5YU",
    "sg:province":"Bedfordshire",
    "sg:tags":[
        "mixed",
        "arable"
    ],
    "wof:name":"Agreserves Ltd.",
    "wof:placetype":"venue"
},
  "geometry": {"coordinates":[-0.278784,52.438801],"type":"Point"}
}