{
  "type": "Feature",
  "properties": {
    "iso:country":"GB",
    "sg:address":"Boulton Rd",
    "sg:city":"Solihull",
    "sg:classifiers":[
        {
            "category":"Home & Garden",
            "subcategory":"Home Furnishings",
            "type":"Retail Goods"
        }
    ],
    "sg:phone":"+44 121 704 0488",
    "sg:postcode":"B91 2JU",
    "sg:province":"West Midlands",
    "sg:tags":[
        "furnishers",
        "planner",
        "kitchen"
    ],
    "wof:name":"Little Kitchen & Bedroom Factory",
    "wof:placetype":"venue"
},
  "geometry": {"coordinates":[-1.775639,52.427235],"type":"Point"}
}