{
  "type": "Feature",
  "properties": {
    "iso:country":"GB",
    "sg:address":"Caepant, Bonvilston",
    "sg:city":"Cardiff",
    "sg:classifiers":[
        {
            "category":"Building & Trades",
            "subcategory":"Construction",
            "type":"Services"
        }
    ],
    "sg:phone":"+44 1446 781494",
    "sg:postcode":"CF5 6TS",
    "sg:province":"Cardiff",
    "sg:tags":[
        "builder"
    ],
    "wof:name":"Brian Toutt & Sons",
    "wof:placetype":"venue"
},
  "geometry": {"coordinates":[-3.3435111046,51.4577407837],"type":"Point"}
}