{
  "type": "Feature",
  "properties": {
    "iso:country":"GB",
    "sg:address":"The Old Bakery Main Rd, Langworth",
    "sg:city":"Lincoln",
    "sg:classifiers":[
        {
            "category":"Autos & Motor Vehicles",
            "subcategory":"Automobile Sales",
            "type":"Retail Goods"
        }
    ],
    "sg:phone":"+44 1522 754210",
    "sg:postcode":"LN3 5BJ",
    "sg:province":"Lincolnshire",
    "sg:tags":[
        "commercial"
    ],
    "wof:name":"Nick Wiles",
    "wof:placetype":"venue"
},
  "geometry": {"coordinates":[-0.4082710147,53.2743911743],"type":"Point"}
}