{
  "type": "Feature",
  "properties": {
    "addr:full":"40 Market Hill Woodbridge Suffolk IP12 4LU",
    "addr:housenumber":"40",
    "addr:postcode":"ip12 4lu",
    "addr:street":"Market Hill",
    "iso:country":"GB",
    "sg:address":"40 Market Hill",
    "sg:city":"Woodbridge",
    "sg:classifiers":[
        {
            "category":"Shopping",
            "subcategory":"Clothing, Apparel, & Fashions",
            "type":"Retail Goods"
        }
    ],
    "sg:phone":"+44 1394 383300",
    "sg:postcode":"IP12 4LU",
    "sg:province":"Suffolk",
    "sg:tags":[
        "lady",
        "fashionwear",
        "ladieswear"
    ],
    "wof:name":"LINGWOLD LTD",
    "wof:placetype":"venue"
},
  "geometry": {"coordinates":[1.3130630255,52.094203949],"type":"Point"}
}