{
  "type": "Feature",
  "properties": {
    "addr:full":"60 The Esplanade Fowey Cornwall PL23 1JA",
    "addr:housenumber":"60",
    "addr:postcode":"pl23 1ja",
    "addr:street":"The Esplanade",
    "iso:country":"GB",
    "sg:address":"60 The Esplanade",
    "sg:city":"Fowey",
    "sg:classifiers":[
        {
            "category":"Travel",
            "subcategory":"Hotels & Motels",
            "type":"Entertainment"
        }
    ],
    "sg:phone":"+44 1726 832452",
    "sg:postcode":"PL23 1JA",
    "sg:province":"Cornwall",
    "sg:tags":[
        "house",
        "guest"
    ],
    "wof:name":"The Wheelhouse",
    "wof:placetype":"venue"
},
  "geometry": {"coordinates":[-4.64071,50.33239],"type":"Point"}
}