{
  "type": "Feature",
  "properties": {
    "iso:country":"GB",
    "sg:address":"22 The Borough",
    "sg:city":"Farnham",
    "sg:classifiers":[
        {
            "category":"Banks & Credit Unions",
            "subcategory":"Bank",
            "type":"Services"
        }
    ],
    "sg:phone":"+44 1483 704400",
    "sg:postcode":"GU9 7NH",
    "sg:province":"Surrey",
    "wof:name":"Barclays Bank Plc",
    "wof:placetype":"venue"
},
  "geometry": {"coordinates":[-0.797569,51.215427],"type":"Point"}
}