{
  "type": "Feature",
  "properties": {
    "iso:country":"GB",
    "sg:address":"Boxhall Holiday Park",
    "sg:city":"Great Yarmouth",
    "sg:classifiers":[
        {
            "category":"Shopping",
            "subcategory":"Department Store",
            "type":"Retail Goods"
        }
    ],
    "sg:phone":"+44 1493 858256",
    "sg:postcode":"NR30 1TB",
    "sg:province":"Norfolk",
    "wof:name":"Nick's Kiosk",
    "wof:placetype":"venue"
},
  "geometry": {"coordinates":[1.72399,52.612415],"type":"Point"}
}