{
  "type": "Feature",
  "properties": {
    "iso:country":"GB",
    "sg:address":"16 Cliddesden Road",
    "sg:city":"Basingstoke",
    "sg:classifiers":[
        {
            "category":"Health Services",
            "subcategory":"Nursing And Care Facility",
            "type":"Services"
        },
        {
            "category":"Social Services",
            "subcategory":"Retirement Home",
            "type":"Services"
        }
    ],
    "sg:postcode":"RG21 3DU",
    "sg:province":"Hampshire",
    "sg:tags":[
        "residential"
    ],
    "wof:name":"GREENBANKS",
    "wof:placetype":"venue"
},
  "geometry": {"coordinates":[-1.084924,51.259338],"type":"Point"}
}