{
  "type": "Feature",
  "properties": {
    "addr:full":"74 Stoke Road, Bletchley Milton Keynes Buckinghamshire MK2 3AD",
    "addr:housenumber":"74",
    "addr:postcode":"mk2 3ad",
    "addr:street":"Stoke Road",
    "iso:country":"GB",
    "sg:address":"74 Stoke Road, Bletchley",
    "sg:city":"Milton Keynes",
    "sg:classifiers":[
        {
            "category":"Professional",
            "subcategory":"Art Services",
            "type":"Services"
        }
    ],
    "sg:postcode":"MK2 3AD",
    "sg:province":"Buckinghamshire",
    "sg:tags":[
        "photographer"
    ],
    "wof:name":"Milton Keynes Photo Services",
    "wof:placetype":"venue"
},
  "geometry": {"coordinates":[-0.7202410102,51.9839439392],"type":"Point"}
}