{
  "type": "Feature",
  "properties": {
    "iso:country":"GB",
    "sg:address":"Fen Road",
    "sg:city":"Cambridge",
    "sg:classifiers":[
        {
            "category":"Retail",
            "subcategory":"Auto Repair",
            "type":"Services"
        }
    ],
    "sg:phone":"+44 1223 423700",
    "sg:postcode":"CB1 5LF",
    "sg:province":"Cambridgeshire",
    "sg:tags":[
        "body",
        "car"
    ],
    "wof:name":"Rob Dean",
    "wof:placetype":"venue"
},
  "geometry": {"coordinates":[0.248549,52.204685],"type":"Point"}
}