{
  "type": "Feature",
  "properties": {
    "iso:country":"GB",
    "sg:address":"28-32 Westgate",
    "sg:city":"Rotherham",
    "sg:classifiers":[
        {
            "category":"Restaurant",
            "type":"Food & Drink"
        }
    ],
    "sg:phone":"+44 1709 720900",
    "sg:postcode":"S60 1AX",
    "sg:province":"South Yorkshire",
    "sg:tags":[
        "indian"
    ],
    "wof:name":"Shahjahan Indian Takeaway",
    "wof:placetype":"venue"
},
  "geometry": {"coordinates":[-1.357393,53.428875],"type":"Point"}
}