{
  "type": "Feature",
  "properties": {
    "addr:full":"Sidney Street Sheffield South Yorkshire S1 4RH",
    "addr:postcode":"s1 4rh",
    "addr:street":"Sidney Street",
    "iso:country":"GB",
    "sg:address":"Sidney Street",
    "sg:city":"Sheffield",
    "sg:classifiers":[
        {
            "category":"Parking",
            "type":"Transportation"
        }
    ],
    "sg:phone":"+44 20 7499 7050",
    "sg:postcode":"S1 4RH",
    "sg:province":"South Yorkshire",
    "sg:tags":[
        "car",
        "park"
    ],
    "wof:name":"Ncp",
    "wof:placetype":"venue"
},
  "geometry": {"coordinates":[-1.469324,53.375019],"type":"Point"}
}