{
  "type": "Feature",
  "properties": {
    "iso:country":"GB",
    "sg:address":"26 Highbury Rd, Tilehurst",
    "sg:city":"Reading",
    "sg:classifiers":[
        {
            "category":"Professional",
            "subcategory":"Engineering",
            "type":"Services"
        }
    ],
    "sg:postcode":"RG31 5JL",
    "sg:province":"Berkshire",
    "sg:tags":[
        "design",
        "engineer"
    ],
    "wof:name":"Raven ,Brian,",
    "wof:placetype":"venue"
},
  "geometry": {"coordinates":[-1.059475,51.452976],"type":"Point"}
}