{
  "type": "Feature",
  "properties": {
    "addr:full":"26 Highbury Rd, Tilehurst Reading Berkshire RG31 5JL",
    "addr:housenumber":"26",
    "addr:postcode":"rg31 5jl",
    "addr:street":"Highbury Rd",
    "iso:country":"GB",
    "sg:address":"26 Highbury Rd, Tilehurst",
    "sg:city":"Reading",
    "sg:classifiers":[
        {
            "category":"Professional",
            "subcategory":"Engineering",
            "type":"Services"
        }
    ],
    "sg:postcode":"RG31 5JL",
    "sg:province":"Berkshire",
    "sg:tags":[
        "design",
        "engineer"
    ],
    "wof:name":"Raven ,Brian,",
    "wof:placetype":"venue"
},
  "geometry": {"coordinates":[-1.059475,51.452976],"type":"Point"}
}