{
  "type": "Feature",
  "properties": {
    "iso:country":"GB",
    "sg:address":"400-408 Old Durham Road, Deckham",
    "sg:city":"Gateshead",
    "sg:classifiers":[
        {
            "category":"Autos & Motor Vehicles",
            "subcategory":"Auto Supplies",
            "type":"Retail Goods"
        }
    ],
    "sg:postcode":"NE9 5DQ",
    "sg:province":"Tyne and Wear",
    "sg:tags":[
        "component"
    ],
    "wof:name":"Auto Refinish Supplies Ltd.",
    "wof:placetype":"venue"
},
  "geometry": {"coordinates":[-1.5933970213,54.948841095],"type":"Point"}
}