{
  "type": "Feature",
  "properties": {
    "addr:full":"2 Hill Dale Cottages, South Cave Brough East Riding of Yorkshire HU15 2DY",
    "addr:housenumber":"2",
    "addr:postcode":"hu15 2dy",
    "addr:street":"Hill Dale Cottages",
    "iso:country":"GB",
    "sg:address":"2 Hill Dale Cottages, South Cave",
    "sg:city":"Brough",
    "sg:classifiers":[
        {
            "category":"Building & Trades",
            "subcategory":"Construction",
            "type":"Services"
        }
    ],
    "sg:phone":"+44 1430 423019",
    "sg:postcode":"HU15 2DY",
    "sg:province":"East Riding of Yorkshire",
    "sg:tags":[
        "builder"
    ],
    "wof:name":"K C Robinson Builder",
    "wof:placetype":"venue"
},
  "geometry": {"coordinates":[-0.6003220081,53.7687530518],"type":"Point"}
}