{
  "type": "Feature",
  "properties": {
    "addr:full":"Widemouth Bay Caravan Park Bude Cornwall EX23 0DF",
    "addr:postcode":"ex23 0df",
    "iso:country":"GB",
    "sg:address":"Widemouth Bay Caravan Park",
    "sg:city":"Bude",
    "sg:classifiers":[
        {
            "category":"Recreation",
            "subcategory":"Amusement Park",
            "type":"Entertainment"
        }
    ],
    "sg:phone":"+44 1288 361616",
    "sg:postcode":"EX23 0DF",
    "sg:province":"Cornwall",
    "sg:tags":[
        "arcade"
    ],
    "wof:name":"Westcountry Amusements Ltd",
    "wof:placetype":"venue"
},
  "geometry": {"coordinates":[-4.5444779396,50.8283615112],"type":"Point"}
}