{
  "type": "Feature",
  "properties": {
    "addr:full":"26 Farcroft Av Coventry West Midlands CV5 7DU",
    "addr:housenumber":"26",
    "addr:postcode":"cv5 7du",
    "addr:street":"Farcroft Av Coventry West",
    "iso:country":"GB",
    "sg:address":"26 Farcroft Av",
    "sg:city":"Coventry",
    "sg:classifiers":[
        {
            "category":"Building & Trades",
            "subcategory":"Construction",
            "type":"Services"
        }
    ],
    "sg:phone":"+44 24 7646 9131",
    "sg:postcode":"CV5 7DU",
    "sg:province":"West Midlands",
    "sg:tags":[
        "decorator",
        "painter"
    ],
    "wof:name":"Design Decoration",
    "wof:placetype":"venue"
},
  "geometry": {"coordinates":[-1.592457,52.415211],"type":"Point"}
}