{
  "type": "Feature",
  "properties": {
    "iso:country":"GB",
    "sg:address":"230 Stapleford La",
    "sg:city":"Nottingham",
    "sg:classifiers":[
        {
            "category":"Home & Garden",
            "subcategory":"Household Appliances",
            "type":"Retail Goods"
        }
    ],
    "sg:phone":"+44 115 972 7799",
    "sg:postcode":"NG9 6JE",
    "sg:province":"Nottinghamshire",
    "sg:tags":[
        "electrical"
    ],
    "wof:name":"Dean Laundry Systems",
    "wof:placetype":"venue"
},
  "geometry": {"coordinates":[-1.260943,52.91328],"type":"Point"}
}