{
  "type": "Feature",
  "properties": {
    "iso:country":"GB",
    "sg:address":"Flannagill Farm, Bentham",
    "sg:city":"Lancaster",
    "sg:classifiers":[
        {
            "category":"Retail",
            "subcategory":"Repair Shop",
            "type":"Services"
        }
    ],
    "sg:phone":"+44 15242 62622",
    "sg:postcode":"LA2 7DQ",
    "sg:province":"Lancashire",
    "sg:tags":[
        "plant",
        "machinery"
    ],
    "wof:name":"Plantec",
    "wof:placetype":"venue"
},
  "geometry": {"coordinates":[-2.51425,54.104111],"type":"Point"}
}