{
  "type": "Feature",
  "properties": {
    "addr:full":"69 High Street Ferndale Rhondda, Cynon, Taff CF43 4RP",
    "addr:housenumber":"69",
    "addr:postcode":"cf43 4rp",
    "addr:street":"High Street",
    "iso:country":"GB",
    "sg:address":"69 High Street",
    "sg:city":"Ferndale",
    "sg:classifiers":[
        {
            "category":"Professional",
            "subcategory":"Employment Agencies",
            "type":"Services"
        }
    ],
    "sg:phone":"+44 1443 733032",
    "sg:postcode":"CF43 4RP",
    "sg:province":"Rhondda, Cynon, Taff",
    "sg:tags":[
        "consultant"
    ],
    "wof:name":"The Job Club",
    "wof:placetype":"venue"
},
  "geometry": {"coordinates":[-3.447777,51.661331],"type":"Point"}
}