{
  "type": "Feature",
  "properties": {
    "addr:full":"47 Albert Street Fleet Hampshire GU51 3RL",
    "addr:housenumber":"47",
    "addr:postcode":"gu51 3rl",
    "addr:street":"Albert Street",
    "iso:country":"GB",
    "sg:address":"47 Albert Street",
    "sg:city":"Fleet",
    "sg:classifiers":[
        {
            "category":"Organizations",
            "subcategory":"Community Association",
            "type":"Services"
        },
        {
            "category":"Organizations",
            "subcategory":"Membership Organization",
            "type":"Services"
        }
    ],
    "sg:phone":"+44 1252 614103",
    "sg:postcode":"GU51 3RL",
    "sg:province":"Hampshire",
    "sg:tags":[
        "club",
        "social"
    ],
    "wof:name":"The Albert Social Club",
    "wof:placetype":"venue"
},
  "geometry": {"coordinates":[-0.83848,51.282459],"type":"Point"}
}