{
  "type": "Feature",
  "properties": {
    "iso:country":"GB",
    "sg:address":"21 Smokies Way, Biddulph",
    "sg:city":"Stoke-on-trent",
    "sg:classifiers":[
        {
            "category":"Recreation",
            "subcategory":"Dog Park",
            "type":"Entertainment"
        }
    ],
    "sg:postcode":"ST8 6TZ",
    "sg:province":"Staffordshire",
    "wof:name":"Grooming Dales",
    "wof:placetype":"venue"
},
  "geometry": {"coordinates":[-2.179892,53.120937],"type":"Point"}
}