{
  "type": "Feature",
  "properties": {
    "addr:full":"Westgate Buildings Bath Bath and North East Somerset BA1 1SP",
    "addr:postcode":"ba1 1sp",
    "addr:street":"Westgate Buildings",
    "iso:country":"GB",
    "sg:address":"Westgate Buildings",
    "sg:city":"Bath",
    "sg:classifiers":[
        {
            "category":"Government",
            "subcategory":"City Hall",
            "type":"Public Place"
        }
    ],
    "sg:phone":"+44 1225 462088",
    "sg:postcode":"BA1 1SP",
    "sg:province":"Bath and North East Somerset",
    "wof:name":"Abbey Church House",
    "wof:placetype":"venue"
},
  "geometry": {"coordinates":[-2.3624589443,51.381061554],"type":"Point"}
}