{
  "type": "Feature",
  "properties": {
    "addr:full":"83-91 Woodside Way Glenrothes Fife KY7 5DW",
    "addr:housenumber":"83-91",
    "addr:postcode":"ky7 5dw",
    "addr:street":"Woodside Way",
    "iso:country":"GB",
    "sg:address":"83-91 Woodside Way",
    "sg:city":"Glenrothes",
    "sg:classifiers":[
        {
            "category":"Manufacturing",
            "subcategory":"Tools & Machinery",
            "type":"Manufacturing & Wholesale Goods"
        },
        {
            "category":"Insurance",
            "subcategory":"Insurance Agent",
            "type":"Services"
        },
        {
            "category":"Banks & Credit Unions",
            "subcategory":"Financial Services",
            "type":"Services"
        }
    ],
    "sg:phone":"+44 1592 756711",
    "sg:postcode":"KY7 5DW",
    "sg:province":"Fife",
    "sg:tags":[
        "consultant",
        "friendly",
        "society"
    ],
    "wof:name":"Abbey Spring Hill Ltd",
    "wof:placetype":"venue"
},
  "geometry": {"coordinates":[-3.149326086,56.1893882751],"type":"Point"}
}