{
  "type": "Feature",
  "properties": {
    "iso:country":"GB",
    "sg:address":"Grosvenor Road",
    "sg:city":"Mablethorpe",
    "sg:classifiers":[
        {
            "category":"Health Services",
            "subcategory":"Nursing And Care Facility",
            "type":"Services"
        }
    ],
    "sg:phone":"+44 1507 472203",
    "sg:postcode":"LN12 1EL",
    "sg:province":"Lincolnshire",
    "sg:tags":[
        "home"
    ],
    "wof:name":"Orchard House Nursing Home",
    "wof:placetype":"venue"
},
  "geometry": {"coordinates":[0.25434,53.339947],"type":"Point"}
}