{
  "type": "Feature",
  "properties": {
    "addr:full":"Unit 44b Hartlebury Trading Est Kidderminster Staffordshire DY10 4JB",
    "addr:housenumber":"unit 44b",
    "addr:postcode":"dy10 4jb",
    "iso:country":"GB",
    "sg:address":"Unit 44b Hartlebury Trading Est",
    "sg:city":"Kidderminster",
    "sg:classifiers":[
        {
            "category":"Manufacturing",
            "subcategory":"Glass & Minerals",
            "type":"Manufacturing & Wholesale Goods"
        }
    ],
    "sg:phone":"+44 1299 253122",
    "sg:postcode":"DY10 4JB",
    "sg:province":"Staffordshire",
    "sg:tags":[
        "fibre",
        "moulding"
    ],
    "wof:name":"Glassic Mouldings",
    "wof:placetype":"venue"
},
  "geometry": {"coordinates":[-2.211575985,52.3237495422],"type":"Point"}
}