{
  "type": "Feature",
  "properties": {
    "iso:country":"GB",
    "sg:address":"332 Ampthill Rd",
    "sg:city":"Bedford",
    "sg:classifiers":[
        {
            "category":"Autos & Motor Vehicles",
            "subcategory":"Automobile Sales",
            "type":"Retail Goods"
        }
    ],
    "sg:phone":"+44 1480 461019",
    "sg:postcode":"MK42 9RU",
    "sg:province":"Bedfordshire",
    "sg:tags":[
        "commercial"
    ],
    "wof:name":"Vindis Audi",
    "wof:placetype":"venue"
},
  "geometry": {"coordinates":[-0.477301,52.115784],"type":"Point"}
}