{
  "type": "Feature",
  "properties": {
    "addr:full":"Crossways, Station Road, Elsenham Bishops Stortford Essex CM22 6LA",
    "addr:postcode":"cm22 6la",
    "addr:street":"Station Road",
    "iso:country":"GB",
    "sg:address":"Crossways, Station Road, Elsenham",
    "sg:city":"Bishops Stortford",
    "sg:classifiers":[
        {
            "category":"Building & Trades",
            "subcategory":"Landscaping Services",
            "type":"Services"
        }
    ],
    "sg:phone":"+44 1279 813289",
    "sg:postcode":"CM22 6LA",
    "sg:province":"Essex",
    "sg:tags":[
        "forestry",
        "tree"
    ],
    "wof:name":"Log-A-Heads",
    "wof:placetype":"venue"
},
  "geometry": {"coordinates":[0.2292200029,51.914226532],"type":"Point"}
}