{
  "type": "Feature",
  "properties": {
    "iso:country":"GB",
    "sg:address":"Juro Antiques, Whitbourne",
    "sg:city":"Worcester",
    "sg:classifiers":[
        {
            "category":"Shopping",
            "subcategory":"Antiques",
            "type":"Retail Goods"
        }
    ],
    "sg:phone":"+44 1886 821261",
    "sg:postcode":"WR6 5SG",
    "sg:province":"Herefordshire",
    "wof:name":"Juro Antiques",
    "wof:placetype":"venue"
},
  "geometry": {"coordinates":[-2.411139,52.208172],"type":"Point"}
}