{
  "type": "Feature",
  "properties": {
    "addr:full":"15a Westbriugh Wimborne Dorset BH21 1LT",
    "addr:housenumber":"15a",
    "addr:postcode":"bh21 1lt",
    "addr:street":"Westbriugh",
    "iso:country":"GB",
    "sg:address":"15a Westbriugh",
    "sg:city":"Wimborne",
    "sg:classifiers":[
        {
            "category":"Real Estate",
            "subcategory":"Architect",
            "type":"Services"
        }
    ],
    "sg:phone":"+44 1202 888075",
    "sg:postcode":"BH21 1LT",
    "sg:province":"Dorset",
    "sg:tags":[
        "technologist",
        "architectural"
    ],
    "wof:name":"Bondesign Associates",
    "wof:placetype":"venue"
},
  "geometry": {"coordinates":[-1.988725,50.800884],"type":"Point"}
}