{
  "type": "Feature",
  "properties": {
    "iso:country":"GB",
    "sg:address":"20 Burrough Street, Ash",
    "sg:city":"Martock",
    "sg:classifiers":[
        {
            "category":"Real Estate",
            "subcategory":"Real Estate Services",
            "type":"Services"
        },
        {
            "category":"Retail",
            "subcategory":"Repair Shop",
            "type":"Services"
        }
    ],
    "sg:phone":"+44 1935 824049",
    "sg:postcode":"TA12 6NZ",
    "sg:province":"Somerset",
    "sg:tags":[
        "property",
        "maintenance"
    ],
    "wof:name":"Richard Taylor",
    "wof:placetype":"venue"
},
  "geometry": {"coordinates":[-2.74216,50.983067],"type":"Point"}
}