{
  "type": "Feature",
  "properties": {
    "addr:full":"Greenway Farm, Wiveliscombe Taunton Devon TA4 2UA",
    "addr:housenumber":"wiveliscombe",
    "addr:postcode":"ta4 2ua",
    "addr:street":"Greenway",
    "iso:country":"GB",
    "sg:address":"Greenway Farm, Wiveliscombe",
    "sg:city":"Taunton",
    "sg:classifiers":[
        {
            "category":"Farming",
            "subcategory":"Dairy Farm",
            "type":"Manufacturing & Wholesale Goods"
        },
        {
            "category":"Professional",
            "subcategory":"Computer Services",
            "type":"Services"
        }
    ],
    "sg:postcode":"TA4 2UA",
    "sg:province":"Devon",
    "sg:tags":[
        "consultant"
    ],
    "wof:name":"A E Woollaston & Sons",
    "wof:placetype":"venue"
},
  "geometry": {"coordinates":[-3.3088541031,51.0414581299],"type":"Point"}
}