{
  "type": "Feature",
  "properties": {
    "iso:country":"GB",
    "sg:address":"Lemington",
    "sg:city":"Newcastle-upon-tyne",
    "sg:classifiers":[
        {
            "category":"Building & Trades",
            "subcategory":"Construction",
            "type":"Services"
        }
    ],
    "sg:phone":"+44 191 264 5115",
    "sg:postcode":"NE15 8SW",
    "sg:province":"Northumberland",
    "sg:tags":[
        "equipment"
    ],
    "wof:name":"Reeds Plant Ltd.",
    "wof:placetype":"venue"
},
  "geometry": {"coordinates":[-1.71268,54.975101],"type":"Point"}
}