{
  "type": "Feature",
  "properties": {
    "addr:full":"70-72 St Marks Road Maidenhead Berkshire SL6 6DW",
    "addr:housenumber":"70-72",
    "addr:postcode":"sl6 6dw",
    "addr:street":"St Marks Road",
    "iso:country":"GB",
    "sg:address":"70-72 St Marks Road",
    "sg:city":"Maidenhead",
    "sg:classifiers":[
        {
            "category":"Professional",
            "subcategory":"Management & Consulting",
            "type":"Services"
        }
    ],
    "sg:phone":"+44 1628 671717",
    "sg:postcode":"SL6 6DW",
    "sg:province":"Berkshire",
    "sg:tags":[
        "consultant",
        "energy",
        "conservation"
    ],
    "wof:name":"Energy Logistics International Ltd.",
    "wof:placetype":"venue"
},
  "geometry": {"coordinates":[-0.739042,51.523327],"type":"Point"}
}