{
  "type": "Feature",
  "properties": {
    "addr:full":"Bede Court Sheltered Housing, Bede Court, Little Gaddesden Berkhamsted Bedfordshire HP4 1NY",
    "addr:postcode":"hp4 1ny",
    "addr:street":"Bede Court Sheltered;Bede Court",
    "iso:country":"GB",
    "sg:address":"Bede Court Sheltered Housing, Bede Court, Little Gaddesden",
    "sg:city":"Berkhamsted",
    "sg:classifiers":[
        {
            "category":"Social Services",
            "subcategory":"Adult Care",
            "type":"Services"
        },
        {
            "category":"Government",
            "subcategory":"Office",
            "type":"Public Place"
        }
    ],
    "sg:phone":"+44 1442 842450",
    "sg:postcode":"HP4 1NY",
    "sg:province":"Bedfordshire",
    "sg:tags":[
        "housing",
        "local",
        "sheltered"
    ],
    "wof:name":"Dacorum Borough Council",
    "wof:placetype":"venue"
},
  "geometry": {"coordinates":[-0.562148,51.81213],"type":"Point"}
}