{
  "type": "Feature",
  "properties": {
    "addr:full":"1 Mansfield Road, Papplewick Nottingham Nottinghamshire NG15 8FJ",
    "addr:housenumber":"1",
    "addr:postcode":"ng15 8fj",
    "addr:street":"Mansfield Road",
    "iso:country":"GB",
    "sg:address":"1 Mansfield Road, Papplewick",
    "sg:city":"Nottingham",
    "sg:classifiers":[
        {
            "category":"Restaurant",
            "type":"Food & Drink"
        }
    ],
    "sg:phone":"+44 115 920 4656",
    "sg:postcode":"NG15 8FJ",
    "sg:province":"Nottinghamshire",
    "wof:name":"The Seven Mile House",
    "wof:placetype":"venue"
},
  "geometry": {"coordinates":[-1.152437,53.053707],"type":"Point"}
}