{
  "type": "Feature",
  "properties": {
    "addr:full":"Western Business Centre, Riverside Terrace Cardiff Cardiff CF5 5AS",
    "addr:postcode":"cf5 5as",
    "addr:street":"Riverside Terrace",
    "iso:country":"GB",
    "sg:address":"Western Business Centre, Riverside Terrace",
    "sg:city":"Cardiff",
    "sg:classifiers":[
        {
            "category":"Travel",
            "subcategory":"Travel Agent",
            "type":"Entertainment"
        }
    ],
    "sg:phone":"+44 29 2055 1155",
    "sg:postcode":"CF5 5AS",
    "sg:province":"Cardiff",
    "wof:name":"Travel Club The",
    "wof:placetype":"venue"
},
  "geometry": {"coordinates":[-3.23112,51.483608],"type":"Point"}
}