{
  "type": "Feature",
  "properties": {
    "addr:full":"Preston St Centre, Preston Street Exeter Devon EX1 1DF",
    "addr:postcode":"ex1 1df",
    "addr:street":"Preston St;Preston Street",
    "iso:country":"GB",
    "sg:address":"Preston St Centre, Preston Street",
    "sg:city":"Exeter",
    "sg:classifiers":[
        {
            "category":"Education",
            "subcategory":"University",
            "type":"Public Place"
        }
    ],
    "sg:phone":"+44 1392 383129",
    "sg:postcode":"EX1 1DF",
    "sg:province":"Devon",
    "sg:tags":[
        "higher"
    ],
    "wof:name":"Exeter College",
    "wof:placetype":"venue"
},
  "geometry": {"coordinates":[-3.533209,50.720421],"type":"Point"}
}