{
  "type": "Feature",
  "properties": {
    "iso:country":"GB",
    "sg:address":"Ballam Road",
    "sg:city":"Lytham St Annes",
    "sg:classifiers":[
        {
            "category":"Sports & Exercise",
            "subcategory":"Golf",
            "type":"Entertainment"
        }
    ],
    "sg:phone":"+44 1253 737390",
    "sg:postcode":"FY8 4LE",
    "sg:province":"Lancashire",
    "sg:tags":[
        "club",
        "course"
    ],
    "wof:name":"The Lytham (Greendrive) Golf Club Ltd.",
    "wof:placetype":"venue"
},
  "geometry": {"coordinates":[-2.9608290195,53.7477760315],"type":"Point"}
}