{
  "type": "Feature",
  "properties": {
    "addr:full":"55 Hall End Road, Wootton Bedford Bedfordshire MK43 9HP",
    "addr:housenumber":"55",
    "addr:postcode":"mk43 9hp",
    "addr:street":"Hall End Road",
    "iso:country":"GB",
    "sg:address":"55 Hall End Road, Wootton",
    "sg:city":"Bedford",
    "sg:classifiers":[
        {
            "category":"Health Services",
            "subcategory":"Podiatrist",
            "type":"Services"
        }
    ],
    "sg:phone":"+44 1234 766571",
    "sg:postcode":"MK43 9HP",
    "sg:province":"Bedfordshire",
    "sg:tags":[
        "podiatrists",
        "chiropodist"
    ],
    "wof:name":"A Walker",
    "wof:placetype":"venue"
},
  "geometry": {"coordinates":[-0.5401,52.099949],"type":"Point"}
}