{
  "type": "Feature",
  "properties": {
    "addr:full":"1541 Stratford Road, Hall Green Birmingham West Midlands B28 9JA",
    "addr:housenumber":"1541",
    "addr:postcode":"b28 9ja",
    "addr:street":"Stratford Road",
    "iso:country":"GB",
    "sg:address":"1541 Stratford Road, Hall Green",
    "sg:city":"Birmingham",
    "sg:classifiers":[
        {
            "category":"Shopping",
            "subcategory":"Comic Books",
            "type":"Retail Goods"
        }
    ],
    "sg:phone":"+44 121 745 7911",
    "sg:postcode":"B28 9JA",
    "sg:province":"West Midlands",
    "sg:tags":[
        "jeweller"
    ],
    "wof:name":"The Gem Box",
    "wof:placetype":"venue"
},
  "geometry": {"coordinates":[-1.8362870216,52.4215431213],"type":"Point"}
}