{
  "type": "Feature",
  "properties": {
    "addr:full":"44d Borough St, Castle Donnington Derby Leicestershire DE74 2LB",
    "addr:housenumber":"44d",
    "addr:postcode":"de74 2lb",
    "addr:street":"Borough St",
    "iso:country":"GB",
    "sg:address":"44d Borough St, Castle Donnington",
    "sg:city":"Derby",
    "sg:classifiers":[
        {
            "category":"Professional",
            "subcategory":"Computer Services",
            "type":"Services"
        }
    ],
    "sg:phone":"+44 1332 853113",
    "sg:postcode":"DE74 2LB",
    "sg:province":"Leicestershire",
    "sg:tags":[
        "development",
        "system",
        "software"
    ],
    "wof:name":"Trimalgo Ltd",
    "wof:placetype":"venue"
},
  "geometry": {"coordinates":[-1.277749,52.838188],"type":"Point"}
}