{
  "type": "Feature",
  "properties": {
    "addr:full":"63 Milngavie Road, Bearsden Glasgow East Dunbartonshire G61 2DW",
    "addr:housenumber":"63",
    "addr:postcode":"g61 2dw",
    "addr:street":"Milngavie Road",
    "iso:country":"GB",
    "sg:address":"63 Milngavie Road, Bearsden",
    "sg:city":"Glasgow",
    "sg:classifiers":[
        {
            "category":"Fast Food",
            "type":"Food & Drink"
        }
    ],
    "sg:postcode":"G61 2DW",
    "sg:province":"East Dunbartonshire",
    "sg:tags":[
        "away",
        "take"
    ],
    "wof:name":"Wok This Way",
    "wof:placetype":"venue"
},
  "geometry": {"coordinates":[-4.321575,55.915539],"type":"Point"}
}