{
  "type": "Feature",
  "properties": {
    "iso:country":"GB",
    "sg:address":"Residents, St Mildreds Rd",
    "sg:city":"Ramsgate",
    "sg:classifiers":[
        {
            "category":"Social Services",
            "subcategory":"Adult Care",
            "type":"Services"
        }
    ],
    "sg:phone":"+44 1843 583753",
    "sg:postcode":"CT11 0ER",
    "sg:province":"Kent",
    "sg:tags":[
        "housing",
        "sheltered"
    ],
    "wof:name":"Thanet Community Housing Association",
    "wof:placetype":"venue"
},
  "geometry": {"coordinates":[1.40579,51.331161],"type":"Point"}
}