{
  "type": "Feature",
  "properties": {
    "iso:country":"GB",
    "sg:address":"1a Moor View",
    "sg:city":"Torpoint",
    "sg:classifiers":[
        {
            "category":"Place Of Worship",
            "type":"Public Place"
        }
    ],
    "sg:phone":"+44 1752 812347",
    "sg:postcode":"PL11 2LH",
    "sg:province":"Cornwall",
    "wof:name":"St.Joan of Arc R C Church",
    "wof:placetype":"venue"
},
  "geometry": {"coordinates":[-4.198423,50.375565],"type":"Point"}
}