{
  "type": "Feature",
  "properties": {
    "iso:country":"GB",
    "sg:address":"6 Orchard Street",
    "sg:city":"Gillingham",
    "sg:classifiers":[
        {
            "category":"Building & Trades",
            "subcategory":"Construction",
            "type":"Services"
        }
    ],
    "sg:phone":"+44 1634 388806",
    "sg:postcode":"ME8 9AA",
    "sg:province":"Kent",
    "sg:tags":[
        "supplier",
        "installers",
        "cladding"
    ],
    "wof:name":"Cladding 2000",
    "wof:placetype":"venue"
},
  "geometry": {"coordinates":[0.606663,51.363438],"type":"Point"}
}