{
  "type": "Feature",
  "properties": {
    "addr:full":"Broadway Lane, South Cerney Cirencester Gloucestershire GL7 5UQ",
    "addr:postcode":"gl7 5uq",
    "addr:street":"Broadway Lane",
    "iso:country":"GB",
    "sg:address":"Broadway Lane, South Cerney",
    "sg:city":"Cirencester",
    "sg:classifiers":[
        {
            "category":"Park",
            "subcategory":"Provincial",
            "type":"Public Place"
        },
        {
            "category":"Recreation",
            "subcategory":"Campground",
            "type":"Entertainment"
        }
    ],
    "sg:phone":"+44 1285 860216",
    "sg:postcode":"GL7 5UQ",
    "sg:province":"Gloucestershire",
    "sg:tags":[
        "caravan",
        "camp",
        "holiday",
        "centre"
    ],
    "sg:website":"http://www.hoburne.com",
    "wof:name":"COTSWOLD HOBURNE LTD",
    "wof:placetype":"venue"
},
  "geometry": {"coordinates":[-1.919170022,51.6605682373],"type":"Point"}
}