{
  "type": "Feature",
  "properties": {
    "iso:country":"GB",
    "sg:address":"20 Scarisbrick Street",
    "sg:city":"Southport",
    "sg:classifiers":[
        {
            "category":"Education",
            "subcategory":"Special Training",
            "type":"Public Place"
        }
    ],
    "sg:phone":"+44 1704 531021",
    "sg:postcode":"PR9 0TU",
    "sg:province":"Lancashire",
    "sg:tags":[
        "aid",
        "first"
    ],
    "wof:name":"St. John's Ambulance",
    "wof:placetype":"venue"
},
  "geometry": {"coordinates":[-3.000393,53.647358],"type":"Point"}
}