{
  "type": "Feature",
  "properties": {
    "addr:full":"Regent Road Shopping Arcade Great Yarmouth Norfolk NR30 2AX",
    "addr:postcode":"nr30 2ax",
    "addr:street":"Regent;Great Yarmouth",
    "iso:country":"GB",
    "sg:address":"Regent Road Shopping Arcade",
    "sg:city":"Great Yarmouth",
    "sg:classifiers":[
        {
            "category":"Home & Garden",
            "subcategory":"Kitchen Supply",
            "type":"Retail Goods"
        }
    ],
    "sg:phone":"+44 1493 331272",
    "sg:postcode":"NR30 2AX",
    "sg:province":"Norfolk",
    "sg:tags":[
        "glassware",
        "china"
    ],
    "wof:name":"Carlton China",
    "wof:placetype":"venue"
},
  "geometry": {"coordinates":[1.7366960049,52.608215332],"type":"Point"}
}