{
  "type": "Feature",
  "properties": {
    "addr:full":"15a The Mall, Ealing London Greater London W5 2PJ",
    "addr:housenumber":"15a",
    "addr:postcode":"w5 2pj",
    "addr:street":"The Mall",
    "iso:country":"GB",
    "sg:address":"15a The Mall, Ealing",
    "sg:city":"London",
    "sg:classifiers":[
        {
            "category":"Education",
            "subcategory":"Special Training",
            "type":"Public Place"
        }
    ],
    "sg:phone":"+44 20 8566 5710",
    "sg:postcode":"W5 2PJ",
    "sg:province":"Greater London",
    "sg:tags":[
        "school",
        "language"
    ],
    "wof:name":"Brudenell School of English",
    "wof:placetype":"venue"
},
  "geometry": {"coordinates":[-0.299691,51.514103],"type":"Point"}
}