{
  "type": "Feature",
  "properties": {
    "iso:country":"GB",
    "sg:address":"Swanlow Medical Centre, 60 Swanlow Lane",
    "sg:city":"Winsford",
    "sg:classifiers":[
        {
            "category":"Health Services",
            "subcategory":"Doctor",
            "type":"Services"
        },
        {
            "category":"Health Services",
            "subcategory":"Clinic",
            "type":"Services"
        }
    ],
    "sg:postcode":"CW7 1JF",
    "sg:province":"Cheshire",
    "sg:tags":[
        "nh",
        "practitioners"
    ],
    "wof:name":"Swanlow Medical Centre",
    "wof:placetype":"venue"
},
  "geometry": {"coordinates":[-2.5303459167,53.1918144226],"type":"Point"}
}