{
  "type": "Feature",
  "properties": {
    "iso:country":"GB",
    "sg:address":"Carronbank Crescent",
    "sg:city":"Denny",
    "sg:classifiers":[
        {
            "category":"Retail",
            "subcategory":"Repair Shop",
            "type":"Services"
        }
    ],
    "sg:postcode":"FK6 6DW",
    "sg:province":"Falkirk",
    "sg:tags":[
        "upholsterer"
    ],
    "wof:name":"John McKenna",
    "wof:placetype":"venue"
},
  "geometry": {"coordinates":[-3.910091,56.025665],"type":"Point"}
}