{
  "type": "Feature",
  "properties": {
    "iso:country":"GB",
    "sg:address":"Carlisle Buildings, Carlisle Road",
    "sg:city":"Eastbourne",
    "sg:classifiers":[
        {
            "category":"Shopping",
            "subcategory":"News",
            "type":"Retail Goods"
        }
    ],
    "sg:phone":"+44 1323 720961",
    "sg:postcode":"BN21 4DB",
    "sg:province":"East Sussex",
    "sg:tags":[
        "newsagent"
    ],
    "wof:name":"Carlisle News",
    "wof:placetype":"venue"
},
  "geometry": {"coordinates":[0.2857019901,50.7625808716],"type":"Point"}
}