{
  "type": "Feature",
  "properties": {
    "iso:country":"GB",
    "sg:address":"Unit 3d Goldthorpe Indust Est, Commercial Rd",
    "sg:city":"Rotherham",
    "sg:classifiers":[
        {
            "category":"Manufacturing",
            "subcategory":"Wood Products",
            "type":"Manufacturing & Wholesale Goods"
        }
    ],
    "sg:phone":"+44 1709 889885",
    "sg:postcode":"S63 9BL",
    "sg:province":"South Yorkshire",
    "sg:tags":[
        "packaging",
        "crate",
        "pallets"
    ],
    "wof:name":"Danson Consultants Ltd",
    "wof:placetype":"venue"
},
  "geometry": {"coordinates":[-1.3071,53.529758],"type":"Point"}
}