{
  "type": "Feature",
  "properties": {
    "addr:full":"65 Middle Road, Cywmdu Swansea Swansea SA5 8HQ",
    "addr:housenumber":"65",
    "addr:postcode":"sa5 8hq",
    "addr:street":"Middle Road Cywmdu",
    "iso:country":"GB",
    "sg:address":"65 Middle Road, Cywmdu",
    "sg:city":"Swansea",
    "sg:classifiers":[
        {
            "category":"Home & Garden",
            "subcategory":"Carpets & Floor Coverings",
            "type":"Retail Goods"
        }
    ],
    "sg:phone":"+44 1792 470009",
    "sg:postcode":"SA5 8HQ",
    "sg:province":"Swansea",
    "sg:tags":[
        "carpets",
        "rug",
        "matting"
    ],
    "wof:name":"Select Carpets & Vinyls",
    "wof:placetype":"venue"
},
  "geometry": {"coordinates":[-3.9547550678,51.6354789734],"type":"Point"}
}