{
  "type": "Feature",
  "properties": {
    "addr:full":"232 Oldham Rd, Failsworth Manchester Lancashire M35 0HB",
    "addr:housenumber":"232",
    "addr:postcode":"m35 0hb",
    "addr:street":"Oldham Rd",
    "iso:country":"GB",
    "sg:address":"232 Oldham Rd, Failsworth",
    "sg:city":"Manchester",
    "sg:classifiers":[
        {
            "category":"Shopping",
            "subcategory":"Computers & Home Electronics",
            "type":"Retail Goods"
        }
    ],
    "sg:phone":"+44 161 682 1991",
    "sg:postcode":"M35 0HB",
    "sg:province":"Lancashire",
    "wof:name":"Dal Components",
    "wof:placetype":"venue"
},
  "geometry": {"coordinates":[-2.165844,53.507008],"type":"Point"}
}