{
  "type": "Feature",
  "properties": {
    "iso:country":"GB",
    "sg:address":"47 Eyre Place",
    "sg:city":"Edinburgh",
    "sg:classifiers":[
        {
            "category":"Education",
            "subcategory":"Music School",
            "type":"Public Place"
        }
    ],
    "sg:phone":"+44 131 557 2088",
    "sg:postcode":"EH3 5EY",
    "sg:province":"City of Edinburgh",
    "sg:tags":[
        "teacher"
    ],
    "wof:name":"Drumtask",
    "wof:placetype":"venue"
},
  "geometry": {"coordinates":[-3.197173,55.961567],"type":"Point"}
}