{
  "type": "Feature",
  "properties": {
    "addr:full":"22 The Grn Warlingham Kent CR6 9NA",
    "addr:housenumber":"22",
    "addr:postcode":"cr6 9na",
    "addr:street":"The Grn",
    "iso:country":"GB",
    "sg:address":"22 The Grn",
    "sg:city":"Warlingham",
    "sg:classifiers":[
        {
            "category":"Building & Trades",
            "subcategory":"Construction",
            "type":"Services"
        }
    ],
    "sg:phone":"+44 1883 623862",
    "sg:postcode":"CR6 9NA",
    "sg:province":"Kent",
    "sg:tags":[
        "tiling",
        "contractor"
    ],
    "wof:name":"R A Lambert",
    "wof:placetype":"venue"
},
  "geometry": {"coordinates":[-0.0564350002,51.3095932007],"type":"Point"}
}