{
  "type": "Feature",
  "properties": {
    "iso:country":"GB",
    "sg:address":"643 Melton Rd",
    "sg:city":"Leicester",
    "sg:classifiers":[
        {
            "category":"Professional",
            "subcategory":"Engineering",
            "type":"Services"
        }
    ],
    "sg:phone":"+44 116 264 0927",
    "sg:postcode":"LE4 8EB",
    "sg:province":"Leicestershire",
    "wof:name":"Metoil Engineers",
    "wof:placetype":"venue"
},
  "geometry": {"coordinates":[-1.104809,52.671761],"type":"Point"}
}