{
  "type": "Feature",
  "properties": {
    "addr:full":"Devonshire Rd Blackpool Lancashire FY2 0JR",
    "addr:postcode":"fy2 0jr",
    "addr:street":"Devonshire Rd",
    "iso:country":"GB",
    "sg:address":"Devonshire Rd",
    "sg:city":"Blackpool",
    "sg:classifiers":[
        {
            "category":"Education",
            "subcategory":"Library",
            "type":"Public Place"
        }
    ],
    "sg:phone":"+44 1253 353112",
    "sg:postcode":"FY2 0JR",
    "sg:province":"Lancashire",
    "sg:tags":[
        "book"
    ],
    "wof:name":"Bispham Library",
    "wof:placetype":"venue"
},
  "geometry": {"coordinates":[-3.0402328968,53.8593330383],"type":"Point"}
}