{
  "type": "Feature",
  "properties": {
    "iso:country":"GB",
    "sg:address":"21 Glenn Crescent",
    "sg:city":"Middlesbrough",
    "sg:classifiers":[
        {
            "category":"Professional",
            "subcategory":"Management & Consulting",
            "type":"Services"
        }
    ],
    "sg:phone":"+44 1642 300377",
    "sg:postcode":"TS7 8ED",
    "sg:province":"North Yorkshire",
    "sg:tags":[
        "consultant",
        "business"
    ],
    "wof:name":"Gallagher Business Consultancies",
    "wof:placetype":"venue"
},
  "geometry": {"coordinates":[-1.199094,54.527405],"type":"Point"}
}