{
  "type": "Feature",
  "properties": {
    "addr:full":"57 Rectory Road Blackpool Lancashire FY4 4DU",
    "addr:housenumber":"57",
    "addr:postcode":"fy4 4du",
    "addr:street":"Rectory Road",
    "iso:country":"GB",
    "sg:address":"57 Rectory Road",
    "sg:city":"Blackpool",
    "sg:classifiers":[
        {
            "category":"Building & Trades",
            "subcategory":"Construction",
            "type":"Services"
        }
    ],
    "sg:phone":"+44 1253 403063",
    "sg:postcode":"FY4 4DU",
    "sg:province":"Lancashire",
    "sg:tags":[
        "joiner",
        "carpenter"
    ],
    "wof:name":"Laver Rit and Son",
    "wof:placetype":"venue"
},
  "geometry": {"coordinates":[-3.0291409492,53.8000679016],"type":"Point"}
}