{
  "type": "Feature",
  "properties": {
    "addr:full":"Unit C2-c3 Abbey Road Industrial Estate, Pity Me Durham Durham DH1 5HA",
    "addr:housenumber":"c2-c3",
    "addr:postcode":"dh1 5ha",
    "addr:street":"Abbey Road Industrial Estate",
    "iso:country":"GB",
    "sg:address":"Unit C2-c3 Abbey Road Industrial Estate, Pity Me",
    "sg:city":"Durham",
    "sg:phone":"+44 191 386 7048",
    "sg:postcode":"DH1 5HA",
    "sg:province":"Durham",
    "wof:name":"E J Holt (Precision Engineers) Ltd.",
    "wof:placetype":"venue"
},
  "geometry": {"coordinates":[-1.5923140049,54.8035430908],"type":"Point"}
}