{
  "type": "Feature",
  "properties": {
    "iso:country":"GB",
    "sg:address":"Enderby Road, Blaby",
    "sg:city":"Leicester",
    "sg:classifiers":[
        {
            "category":"Banks & Credit Unions",
            "subcategory":"Bureau De Change",
            "type":"Services"
        }
    ],
    "sg:phone":"+44 116 277 0374",
    "sg:postcode":"LE8 4GD",
    "sg:province":"Leicestershire",
    "wof:name":"EUROCHANGE LTD",
    "wof:placetype":"venue"
},
  "geometry": {"coordinates":[-1.164713,52.573448],"type":"Point"}
}