{
  "type": "Feature",
  "properties": {
    "addr:full":"Challow House Farm, Main Street, East Challow Wantage Berkshire OX12 9SR",
    "addr:postcode":"ox12 9sr",
    "addr:street":"Main Street East",
    "iso:country":"GB",
    "sg:address":"Challow House Farm, Main Street, East Challow",
    "sg:city":"Wantage",
    "sg:classifiers":[
        {
            "category":"Real Estate",
            "subcategory":"Real Estate Services",
            "type":"Services"
        }
    ],
    "sg:phone":"+44 1235 760225",
    "sg:postcode":"OX12 9SR",
    "sg:province":"Berkshire",
    "sg:tags":[
        "management",
        "facility"
    ],
    "wof:name":"Calber Facilities Management Ltd.",
    "wof:placetype":"venue"
},
  "geometry": {"coordinates":[-1.4523789883,51.5912361145],"type":"Point"}
}