{
  "type": "Feature",
  "properties": {
    "addr:full":"834 Dumbarton Road Clydebank East Dunbartonshire G81 4BX",
    "addr:housenumber":"834",
    "addr:postcode":"g81 4bx",
    "addr:street":"Dumbarton Road",
    "iso:country":"GB",
    "sg:address":"834 Dumbarton Road",
    "sg:city":"Clydebank",
    "sg:classifiers":[
        {
            "category":"Autos & Motor Vehicles",
            "subcategory":"Fuel & Gas Station",
            "type":"Retail Goods"
        }
    ],
    "sg:phone":"+44 141 952 0617",
    "sg:postcode":"G81 4BX",
    "sg:province":"East Dunbartonshire",
    "sg:tags":[
        "petrol",
        "filling"
    ],
    "wof:name":"Mountblow Service Station",
    "wof:placetype":"venue"
},
  "geometry": {"coordinates":[-4.4338917732,55.9132118225],"type":"Point"}
}