{
  "type": "Feature",
  "properties": {
    "addr:full":"Ruscote Avenue Banbury Oxfordshire OX16 2NZ",
    "addr:postcode":"ox16 2nz",
    "addr:street":"Avenue",
    "iso:country":"GB",
    "sg:address":"Ruscote Avenue",
    "sg:city":"Banbury",
    "sg:classifiers":[
        {
            "category":"Bars & Pubs",
            "type":"Food & Drink"
        },
        {
            "category":"Community Center",
            "subcategory":"Social",
            "type":"Public Place"
        }
    ],
    "sg:phone":"+44 1295 269296",
    "sg:postcode":"OX16 2NZ",
    "sg:province":"Oxfordshire",
    "sg:tags":[
        "pubs",
        "house",
        "inn",
        "activity"
    ],
    "wof:name":"The Musketeer",
    "wof:placetype":"venue"
},
  "geometry": {"coordinates":[-1.347809,52.069431],"type":"Point"}
}