{
  "type": "Feature",
  "properties": {
    "iso:country":"GB",
    "sg:address":"104 Chaldon Road",
    "sg:city":"Caterham",
    "sg:classifiers":[
        {
            "category":"Banks & Credit Unions",
            "subcategory":"Financial Services",
            "type":"Services"
        }
    ],
    "sg:postcode":"CR3 5PH",
    "sg:province":"Surrey",
    "sg:tags":[
        "adviser"
    ],
    "wof:name":"Independent Money Matters Ltd.",
    "wof:placetype":"venue"
},
  "geometry": {"coordinates":[-0.095511,51.285145],"type":"Point"}
}