{
  "type": "Feature",
  "properties": {
    "iso:country":"GB",
    "sg:address":"Unit 66 Chelmsley Wood Mkt, Greenwood Way",
    "sg:city":"Birmingham",
    "sg:classifiers":[
        {
            "category":"Shopping",
            "subcategory":"Music",
            "type":"Retail Goods"
        }
    ],
    "sg:phone":"+44 121 779 6401",
    "sg:postcode":"B37 5TL",
    "sg:province":"West Midlands",
    "sg:tags":[
        "record",
        "tape",
        "cd"
    ],
    "wof:name":"Marriner,L,",
    "wof:placetype":"venue"
},
  "geometry": {"coordinates":[-1.740049,52.480705],"type":"Point"}
}