{
  "type": "Feature",
  "properties": {
    "addr:full":"21 Dorset Sq Camden Greater London NW1 6QG",
    "addr:housenumber":"21",
    "addr:postcode":"nw1 6qg",
    "addr:street":"Dorset Sq",
    "iso:country":"GB",
    "sg:address":"21 Dorset Sq",
    "sg:city":"Camden",
    "sg:classifiers":[
        {
            "category":"Professional",
            "subcategory":"Computer Services",
            "type":"Services"
        }
    ],
    "sg:phone":"+44 20 7258 0384",
    "sg:postcode":"NW1 6QG",
    "sg:province":"Greater London",
    "sg:tags":[
        "consultant"
    ],
    "wof:name":"Mouncey & Partners",
    "wof:placetype":"venue"
},
  "geometry": {"coordinates":[-0.1618179977,51.5229034424],"type":"Point"}
}