{
  "type": "Feature",
  "properties": {
    "iso:country":"GB",
    "sg:address":"Fawkham Manor Farm, Manor Lane, Fawkham",
    "sg:city":"Longfield",
    "sg:classifiers":[
        {
            "category":"Health Services",
            "subcategory":"Hospital",
            "type":"Services"
        }
    ],
    "sg:phone":"+44 1474 879900",
    "sg:postcode":"DA3 8ND",
    "sg:province":"Kent",
    "wof:name":"Bmi Fawkham Manor Hospital",
    "wof:placetype":"venue"
},
  "geometry": {"coordinates":[0.2766279876,51.3669395447],"type":"Point"}
}