{
  "type": "Feature",
  "properties": {
    "addr:full":"8 Church Street Dover Kent CT16 1LY",
    "addr:housenumber":"8",
    "addr:postcode":"ct16 1ly",
    "addr:street":"Church Street",
    "iso:country":"GB",
    "sg:address":"8 Church Street",
    "sg:city":"Dover",
    "sg:classifiers":[
        {
            "category":"Communications",
            "subcategory":"Newspaper",
            "type":"Services"
        }
    ],
    "sg:phone":"+44 1304 240380",
    "sg:postcode":"CT16 1LY",
    "sg:province":"Kent",
    "sg:tags":[
        "magazine"
    ],
    "wof:name":"Dover Extra",
    "wof:placetype":"venue"
},
  "geometry": {"coordinates":[1.31356,51.125938],"type":"Point"}
}