{
  "type": "Feature",
  "properties": {
    "addr:full":"15 Roche Road, Bugle St Austell Cornwall PL26 8PL",
    "addr:housenumber":"15",
    "addr:postcode":"pl26 8pl",
    "addr:street":"Roche Road Bugle",
    "iso:country":"GB",
    "sg:address":"15 Roche Road, Bugle",
    "sg:city":"St Austell",
    "sg:classifiers":[
        {
            "category":"Professional",
            "subcategory":"Management & Consulting",
            "type":"Services"
        }
    ],
    "sg:postcode":"PL26 8PL",
    "sg:province":"Cornwall",
    "sg:tags":[
        "consultant",
        "training"
    ],
    "wof:name":"Personal Self Defence Services",
    "wof:placetype":"venue"
},
  "geometry": {"coordinates":[-4.794962,50.396748],"type":"Point"}
}