{
  "type": "Feature",
  "properties": {
    "addr:full":"119 Cotmandene Crescent, St Pauls Cray Orpington Kent BR5 2RB",
    "addr:housenumber":"119",
    "addr:postcode":"br5 2rb",
    "addr:street":"Cotmandene Crescent",
    "iso:country":"GB",
    "sg:address":"119 Cotmandene Crescent, St Pauls Cray",
    "sg:city":"Orpington",
    "sg:classifiers":[
        {
            "category":"Retail",
            "subcategory":"Laundry & Dry Cleaning",
            "type":"Services"
        }
    ],
    "sg:phone":"+44 20 8300 4020",
    "sg:postcode":"BR5 2RB",
    "sg:province":"Kent",
    "sg:tags":[
        "alteration"
    ],
    "wof:name":"Gold Star",
    "wof:placetype":"venue"
},
  "geometry": {"coordinates":[0.1066529974,51.4033317566],"type":"Point"}
}