{
  "type": "Feature",
  "properties": {
    "iso:country":"GB",
    "sg:address":"2 Glasgow Road",
    "sg:city":"Edinburgh",
    "sg:classifiers":[
        {
            "category":"Professional",
            "type":"Services"
        }
    ],
    "sg:phone":"+44 131 316 4600",
    "sg:postcode":"EH12 8HL",
    "sg:province":"City of Edinburgh",
    "sg:tags":[
        "repair",
        "tech",
        "maintenance"
    ],
    "wof:name":"Blue Chip Computers Ltd.",
    "wof:placetype":"venue"
},
  "geometry": {"coordinates":[-3.293872,55.942776],"type":"Point"}
}