{
  "type": "Feature",
  "properties": {
    "addr:full":"23 High Street Selkirk Scottish Borders TD7 4BZ",
    "addr:housenumber":"23",
    "addr:postcode":"td7 4bz",
    "addr:street":"High Street",
    "iso:country":"GB",
    "sg:address":"23 High Street",
    "sg:city":"Selkirk",
    "sg:classifiers":[
        {
            "category":"Manufacturing",
            "subcategory":"Electronics",
            "type":"Manufacturing & Wholesale Goods"
        }
    ],
    "sg:postcode":"TD7 4BZ",
    "sg:province":"Scottish Borders",
    "sg:tags":[
        "printed",
        "circuit"
    ],
    "wof:name":"J Muir Services & Supplies",
    "wof:placetype":"venue"
},
  "geometry": {"coordinates":[-2.840954,55.54776],"type":"Point"}
}