{
  "type": "Feature",
  "properties": {
    "iso:country":"GB",
    "sg:address":"Eastern Avenue",
    "sg:city":"Gloucester",
    "sg:classifiers":[
        {
            "category":"Autos & Motor Vehicles",
            "subcategory":"Automobile Sales",
            "type":"Retail Goods"
        }
    ],
    "sg:phone":"+44 1452 529755",
    "sg:postcode":"GL4 3BS",
    "sg:province":"Gloucestershire",
    "sg:tags":[
        "car"
    ],
    "wof:name":"Warners Trust Plc",
    "wof:placetype":"venue"
},
  "geometry": {"coordinates":[-2.2135579586,51.8635597229],"type":"Point"}
}