{
  "type": "Feature",
  "properties": {
    "addr:full":"33 Blackburn Road Darwen Lancashire BB3 1EJ",
    "addr:housenumber":"33",
    "addr:postcode":"bb3 1ej",
    "addr:street":"Blackburn Road",
    "iso:country":"GB",
    "sg:address":"33 Blackburn Road",
    "sg:city":"Darwen",
    "sg:classifiers":[
        {
            "category":"Food & Beverages",
            "subcategory":"Candy",
            "type":"Retail Goods"
        },
        {
            "category":"Cafe",
            "type":"Food & Drink"
        }
    ],
    "sg:phone":"+44 1254 708126",
    "sg:postcode":"BB3 1EJ",
    "sg:province":"Lancashire",
    "sg:tags":[
        "confectioner",
        "snack",
        "bar"
    ],
    "wof:name":"Carole's Butty Box",
    "wof:placetype":"venue"
},
  "geometry": {"coordinates":[-2.4757039547,53.7031211853],"type":"Point"}
}