{
  "type": "Feature",
  "properties": {
    "addr:full":"Units 2/3 Common Lane North Beccles Norfolk NR34 9BL",
    "addr:housenumber":"units 2 / 3",
    "addr:postcode":"nr34 9bl",
    "addr:street":"Common Lane North",
    "iso:country":"GB",
    "sg:address":"Units 2/3 Common Lane North",
    "sg:city":"Beccles",
    "sg:classifiers":[
        {
            "category":"Autos & Motor Vehicles",
            "subcategory":"Auto Supplies",
            "type":"Retail Goods"
        }
    ],
    "sg:phone":"+44 1502 717885",
    "sg:postcode":"NR34 9BL",
    "sg:province":"Norfolk",
    "sg:tags":[
        "tyre"
    ],
    "wof:name":"Wheels & Tyres Direct",
    "wof:placetype":"venue"
},
  "geometry": {"coordinates":[1.567245,52.453667],"type":"Point"}
}