{
  "type": "Feature",
  "properties": {
    "iso:country":"GB",
    "sg:address":"Crossdale Road, Hindley Grn",
    "sg:city":"Wigan",
    "sg:classifiers":[
        {
            "category":"Bars & Pubs",
            "type":"Food & Drink"
        }
    ],
    "sg:phone":"+44 1942 706277",
    "sg:postcode":"WN2 4XA",
    "sg:province":"Lancashire",
    "sg:tags":[
        "pubs",
        "inn"
    ],
    "wof:name":"Dray King Hotel",
    "wof:placetype":"venue"
},
  "geometry": {"coordinates":[-2.560589,53.532269],"type":"Point"}
}