{
  "type": "Feature",
  "properties": {
    "addr:full":"Openshaw Market, Stanley St Manchester Greater Manchester M11 1LE",
    "addr:postcode":"m11 1le",
    "addr:street":"Stanley St",
    "iso:country":"GB",
    "sg:address":"Openshaw Market, Stanley St",
    "sg:city":"Manchester",
    "sg:classifiers":[
        {
            "category":"Cafe",
            "type":"Food & Drink"
        }
    ],
    "sg:phone":"+44 161 292 0787",
    "sg:postcode":"M11 1LE",
    "sg:province":"Greater Manchester",
    "sg:tags":[
        "tea",
        "room"
    ],
    "wof:name":"Harriets Cafe",
    "wof:placetype":"venue"
},
  "geometry": {"coordinates":[-2.2488100529,53.4796218872],"type":"Point"}
}