{
  "type": "Feature",
  "properties": {
    "addr:full":"Hindley Green Business Park, Leigh Road, Hindley Green Wigan Lancashire WN2 4TN",
    "addr:postcode":"wn2 4tn",
    "addr:street":"Hindley Green Business Park Leigh Road",
    "iso:country":"GB",
    "sg:address":"Hindley Green Business Park, Leigh Road, Hindley Green",
    "sg:city":"Wigan",
    "sg:classifiers":[
        {
            "category":"Manufacturing",
            "subcategory":"Petroleum Products",
            "type":"Manufacturing & Wholesale Goods"
        }
    ],
    "sg:phone":"+44 1942 255000",
    "sg:postcode":"WN2 4TN",
    "sg:province":"Lancashire",
    "sg:tags":[
        "double",
        "glazing"
    ],
    "wof:name":"The Welch Glazing Co. Ltd.",
    "wof:placetype":"venue"
},
  "geometry": {"coordinates":[-2.5426490307,53.5309295654],"type":"Point"}
}