{
  "type": "Feature",
  "properties": {
    "addr:full":"1 Jubilee Cotts, Elmbridge Road Cranleigh Surrey GU6 8NN",
    "addr:housenumber":"1;cotts",
    "addr:postcode":"gu6 8nn",
    "addr:street":"Jubilee;Elmbridge Road",
    "iso:country":"GB",
    "sg:address":"1 Jubilee Cotts, Elmbridge Road",
    "sg:city":"Cranleigh",
    "sg:classifiers":[
        {
            "category":"Retail",
            "subcategory":"Repair Shop",
            "type":"Services"
        }
    ],
    "sg:postcode":"GU6 8NN",
    "sg:province":"Surrey",
    "sg:tags":[
        "radio",
        "television",
        "video"
    ],
    "wof:name":"Televideo",
    "wof:placetype":"venue"
},
  "geometry": {"coordinates":[-0.482998997,51.1415405273],"type":"Point"}
}