{
  "type": "Feature",
  "properties": {
    "addr:full":"Mauldeth Ho, Mauldeth Rd West, Chorlton Manchester Cheshire M21 7RL",
    "addr:postcode":"m21 7rl",
    "addr:street":"Mauldeth Rd West",
    "iso:country":"GB",
    "sg:address":"Mauldeth Ho, Mauldeth Rd West, Chorlton",
    "sg:city":"Manchester",
    "sg:classifiers":[
        {
            "category":"Government",
            "subcategory":"Office",
            "type":"Public Place"
        }
    ],
    "sg:postcode":"M21 7RL",
    "sg:province":"Cheshire",
    "sg:tags":[
        "local"
    ],
    "wof:name":"Mancunian Community Health N H S Trust",
    "wof:placetype":"venue"
},
  "geometry": {"coordinates":[-2.246599,53.439842],"type":"Point"}
}