{
  "type": "Feature",
  "properties": {
    "iso:country":"GB",
    "sg:address":"High St",
    "sg:city":"Auchterarder",
    "sg:classifiers":[
        {
            "category":"Government",
            "subcategory":"Police Station",
            "type":"Public Place"
        }
    ],
    "sg:phone":"+44 1764 662212",
    "sg:postcode":"PH3 1DF",
    "sg:province":"Perth and Kinross",
    "sg:tags":[
        "support"
    ],
    "wof:name":"Auchterarder Police Station",
    "wof:placetype":"venue"
},
  "geometry": {"coordinates":[-3.707734,56.298615],"type":"Point"}
}