{
  "type": "Feature",
  "properties": {
    "iso:country":"GB",
    "sg:address":"Waterfield House, High St, Wombourne",
    "sg:city":"Wolverhampton",
    "sg:classifiers":[
        {
            "category":"Government",
            "subcategory":"Office",
            "type":"Public Place"
        }
    ],
    "sg:phone":"+44 1902 898348",
    "sg:postcode":"WV5 9DL",
    "sg:province":"Shropshire",
    "sg:tags":[
        "local"
    ],
    "wof:name":"South Staffordshire Housing Association",
    "wof:placetype":"venue"
},
  "geometry": {"coordinates":[-2.180909,52.536621],"type":"Point"}
}