{
  "type": "Feature",
  "properties": {
    "addr:full":"26 Water Street Rhyl Conwy LL18 1SS",
    "addr:housenumber":"26",
    "addr:postcode":"ll18 1ss",
    "addr:street":"Water Street",
    "iso:country":"GB",
    "sg:address":"26 Water Street",
    "sg:city":"Rhyl",
    "sg:classifiers":[
        {
            "category":"Shopping",
            "subcategory":"Gifts & Souvenirs",
            "type":"Retail Goods"
        },
        {
            "category":"Professional",
            "subcategory":"Business Services",
            "type":"Services"
        },
        {
            "category":"Professional",
            "subcategory":"Printing & Photocopies",
            "type":"Services"
        }
    ],
    "sg:phone":"+44 1745 759466",
    "sg:postcode":"LL18 1SS",
    "sg:province":"Conwy",
    "sg:tags":[
        "trophy",
        "agent",
        "export",
        "supplier",
        "import",
        "medal"
    ],
    "wof:name":"Sovereign Trophies",
    "wof:placetype":"venue"
},
  "geometry": {"coordinates":[-3.494399,53.320995],"type":"Point"}
}