{
  "type": "Feature",
  "properties": {
    "addr:full":"4 Coventry Street Nuneaton Leicestershire CV11 5SZ",
    "addr:housenumber":"4",
    "addr:postcode":"cv11 5sz",
    "addr:street":"Coventry Street",
    "iso:country":"GB",
    "sg:address":"4 Coventry Street",
    "sg:city":"Nuneaton",
    "sg:classifiers":[
        {
            "category":"Professional",
            "subcategory":"Lawyer & Legal Services",
            "type":"Services"
        }
    ],
    "sg:phone":"+44 24 7638 7821",
    "sg:postcode":"CV11 5SZ",
    "sg:province":"Leicestershire",
    "sg:tags":[
        "solicitor"
    ],
    "wof:name":"Willson Letchford & Co.",
    "wof:placetype":"venue"
},
  "geometry": {"coordinates":[-1.467514,52.52269],"type":"Point"}
}