{
  "type": "Feature",
  "properties": {
    "addr:full":"29 Cassio Road Watford Hertfordshire WD18 0QP",
    "addr:housenumber":"29",
    "addr:postcode":"wd18 0qp",
    "addr:street":"Cassio Road",
    "iso:country":"GB",
    "sg:address":"29 Cassio Road",
    "sg:city":"Watford",
    "sg:classifiers":[
        {
            "category":"Building & Trades",
            "subcategory":"Landscaping Services",
            "type":"Services"
        }
    ],
    "sg:phone":"+44 1923 440156",
    "sg:postcode":"WD18 0QP",
    "sg:province":"Hertfordshire",
    "sg:tags":[
        "gardening"
    ],
    "wof:name":"The Green Man Gardening",
    "wof:placetype":"venue"
},
  "geometry": {"coordinates":[-0.4015649855,51.6543998718],"type":"Point"}
}