{
  "type": "Feature",
  "properties": {
    "addr:full":"17 Trevone Gardens Pinner Greater London HA5 5LW",
    "addr:housenumber":"17",
    "addr:postcode":"ha5 5lw",
    "addr:street":"Trevone Gardens",
    "iso:country":"GB",
    "sg:address":"17 Trevone Gardens",
    "sg:city":"Pinner",
    "sg:classifiers":[
        {
            "category":"Professional",
            "subcategory":"Engineering",
            "type":"Services"
        },
        {
            "category":"Building & Trades",
            "subcategory":"Electrical",
            "type":"Services"
        }
    ],
    "sg:phone":"+44 20 8866 9375",
    "sg:postcode":"HA5 5LW",
    "sg:province":"Greater London",
    "sg:tags":[
        "engineer",
        "electrician",
        "contractor"
    ],
    "wof:name":"M & M Electrical",
    "wof:placetype":"venue"
},
  "geometry": {"coordinates":[-0.379803,51.58353],"type":"Point"}
}