{
  "type": "Feature",
  "properties": {
    "iso:country":"GB",
    "sg:address":"P O Box 65",
    "sg:city":"Wisbech",
    "sg:classifiers":[
        {
            "category":"Professional",
            "subcategory":"Business Services",
            "type":"Services"
        }
    ],
    "sg:phone":"+44 1945 781148",
    "sg:postcode":"PE14 7ZZ",
    "sg:province":"Cambridgeshire",
    "sg:tags":[
        "trade"
    ],
    "wof:name":"Nuclear Stock Association Ltd.",
    "wof:placetype":"venue"
},
  "geometry": {"coordinates":[0.22663,52.697521],"type":"Point"}
}