{
  "type": "Feature",
  "properties": {
    "addr:full":"4 Teal Business Park, Dodwells Road Hinckley Leicestershire LE10 3BZ",
    "addr:housenumber":"4",
    "addr:postcode":"le10 3bz",
    "addr:street":"Teal Business Park Dodwells Road",
    "iso:country":"GB",
    "sg:address":"4 Teal Business Park, Dodwells Road",
    "sg:city":"Hinckley",
    "sg:classifiers":[
        {
            "category":"Home & Garden",
            "subcategory":"Hardware",
            "type":"Retail Goods"
        }
    ],
    "sg:phone":"+44 1455 610544",
    "sg:postcode":"LE10 3BZ",
    "sg:province":"Leicestershire",
    "sg:tags":[
        "wheel",
        "castor"
    ],
    "wof:name":"Castor Supply Co. Ltd.",
    "wof:placetype":"venue"
},
  "geometry": {"coordinates":[-1.372754,52.542439],"type":"Point"}
}