{
  "type": "Feature",
  "properties": {
    "iso:country":"GB",
    "sg:address":"48 Fallowfield",
    "sg:city":"Stevenage",
    "sg:classifiers":[
        {
            "category":"Communications",
            "type":"Services"
        }
    ],
    "sg:postcode":"SG2 9PL",
    "sg:province":"Hertfordshire",
    "sg:tags":[
        "telecommunication"
    ],
    "wof:name":"S Kiernan Ltd",
    "wof:placetype":"venue"
},
  "geometry": {"coordinates":[-0.164468,51.894115],"type":"Point"}
}