{
  "type": "Feature",
  "properties": {
    "iso:country":"GB",
    "sg:address":"19 St Matthews Street",
    "sg:city":"Ipswich",
    "sg:classifiers":[
        {
            "category":"Shopping",
            "subcategory":"Thrift Store",
            "type":"Retail Goods"
        }
    ],
    "sg:phone":"+44 1473 217357",
    "sg:postcode":"IP1 3EL",
    "sg:province":"Suffolk",
    "sg:tags":[
        "shop",
        "charity"
    ],
    "wof:name":"M I N D",
    "wof:placetype":"venue"
},
  "geometry": {"coordinates":[1.148363,52.059433],"type":"Point"}
}