{
  "type": "Feature",
  "properties": {
    "addr:full":"Chantry Ho, 2a West St Buckingham Buckinghamshire MK18 1HL",
    "addr:housenumber":"2a",
    "addr:postcode":"mk18 1hl",
    "addr:street":"West St",
    "iso:country":"GB",
    "sg:address":"Chantry Ho, 2a West St",
    "sg:city":"Buckingham",
    "sg:classifiers":[
        {
            "category":"Food & Beverages",
            "subcategory":"Liquor & Beverages",
            "type":"Retail Goods"
        }
    ],
    "sg:phone":"+44 1280 824120",
    "sg:postcode":"MK18 1HL",
    "sg:province":"Buckinghamshire",
    "sg:tags":[
        "beer",
        "spirit",
        "wines"
    ],
    "wof:name":"Winelink International Ltd",
    "wof:placetype":"venue"
},
  "geometry": {"coordinates":[-0.986479,52.000751],"type":"Point"}
}