{
  "type": "Feature",
  "properties": {
    "addr:full":"264 Glasgow Road Glasgow South Lanarkshire G72 0YH",
    "addr:housenumber":"264",
    "addr:postcode":"g72 0yh",
    "addr:street":"Glasgow Road",
    "iso:country":"GB",
    "sg:address":"264 Glasgow Road",
    "sg:city":"Glasgow",
    "sg:classifiers":[
        {
            "category":"Shopping",
            "type":"Retail Goods"
        }
    ],
    "sg:phone":"+44 1698 823609",
    "sg:postcode":"G72 0YH",
    "sg:province":"South Lanarkshire",
    "sg:tags":[
        "part",
        "accessory"
    ],
    "wof:name":"Highway One",
    "wof:placetype":"venue"
},
  "geometry": {"coordinates":[-4.0930871964,55.79429245],"type":"Point"}
}