{
  "type": "Feature",
  "properties": {
    "addr:full":"High St North Dunstable Bedfordshire LU6 1JJ",
    "addr:postcode":"lu6 1jj",
    "addr:street":"High St North",
    "iso:country":"GB",
    "sg:address":"High St North",
    "sg:city":"Dunstable",
    "sg:classifiers":[
        {
            "category":"Freight",
            "type":"Transportation"
        }
    ],
    "sg:phone":"+44 1582 478737",
    "sg:postcode":"LU6 1JJ",
    "sg:province":"Bedfordshire",
    "sg:tags":[
        "forwarders"
    ],
    "wof:name":"C S R Freight Associates",
    "wof:placetype":"venue"
},
  "geometry": {"coordinates":[-0.5317590237,51.8937339783],"type":"Point"}
}