{
  "type": "Feature",
  "properties": {
    "addr:full":"136 Burton Road, Carlton Nottingham Nottinghamshire NG4 3GP",
    "addr:housenumber":"136",
    "addr:postcode":"ng4 3gp",
    "addr:street":"Burton Road",
    "iso:country":"GB",
    "sg:address":"136 Burton Road, Carlton",
    "sg:city":"Nottingham",
    "sg:classifiers":[
        {
            "category":"Autos & Motor Vehicles",
            "subcategory":"Automobile Sales",
            "type":"Retail Goods"
        }
    ],
    "sg:phone":"+44 115 961 5389",
    "sg:postcode":"NG4 3GP",
    "sg:province":"Nottinghamshire",
    "sg:tags":[
        "car"
    ],
    "wof:name":"Carlton Car Centre",
    "wof:placetype":"venue"
},
  "geometry": {"coordinates":[-1.076144,52.970631],"type":"Point"}
}