{
  "type": "Feature",
  "properties": {
    "iso:country":"GB",
    "sg:address":"Old Chapel Road",
    "sg:city":"Inverurie",
    "sg:classifiers":[
        {
            "category":"Wholesale",
            "subcategory":"Petroleum",
            "type":"Manufacturing & Wholesale Goods"
        },
        {
            "category":"Utilities",
            "subcategory":"Fuel Oil & Lpg",
            "type":"Services"
        }
    ],
    "sg:phone":"+44 1467 621418",
    "sg:postcode":"AB51 4QN",
    "sg:province":"Aberdeenshire",
    "sg:tags":[
        "distributor"
    ],
    "wof:name":"James Milne & Sons (Fuels) Ltd.",
    "wof:placetype":"venue"
},
  "geometry": {"coordinates":[-2.398564,57.289989],"type":"Point"}
}