{
  "type": "Feature",
  "properties": {
    "iso:country":"GB",
    "sg:address":"106 The Broadway",
    "sg:city":"Leigh-on-sea",
    "sg:classifiers":[
        {
            "category":"Communications",
            "subcategory":"Newspaper",
            "type":"Services"
        }
    ],
    "sg:phone":"+44 1702 477666",
    "sg:postcode":"SS9 1AB",
    "sg:province":"Essex",
    "sg:tags":[
        "magazine"
    ],
    "wof:name":"Leigh Times Newspaper",
    "wof:placetype":"venue"
},
  "geometry": {"coordinates":[0.6605749726,51.5416069031],"type":"Point"}
}