{
  "type": "Feature",
  "properties": {
    "addr:full":"28 Clarence Street Batley West Yorkshire WF17 5NF",
    "addr:housenumber":"28",
    "addr:postcode":"wf17 5nf",
    "addr:street":"Clarence Street",
    "iso:country":"GB",
    "sg:address":"28 Clarence Street",
    "sg:city":"Batley",
    "sg:classifiers":[
        {
            "category":"Professional",
            "subcategory":"Business Services",
            "type":"Services"
        }
    ],
    "sg:phone":"+44 1924 441197",
    "sg:postcode":"WF17 5NF",
    "sg:province":"West Yorkshire",
    "sg:tags":[
        "distribution"
    ],
    "wof:name":"Richard J Philips",
    "wof:placetype":"venue"
},
  "geometry": {"coordinates":[-1.626826,53.713657],"type":"Point"}
}