{
  "type": "Feature",
  "properties": {
    "addr:full":"The Old Malthouse, Victoria Road Winchester Hampshire SO23 7DU",
    "addr:postcode":"so23 7du",
    "addr:street":"Victoria Road",
    "iso:country":"GB",
    "sg:address":"The Old Malthouse, Victoria Road",
    "sg:city":"Winchester",
    "sg:classifiers":[
        {
            "category":"Shopping",
            "subcategory":"Pharmacy",
            "type":"Retail Goods"
        }
    ],
    "sg:phone":"+44 1962 890890",
    "sg:postcode":"SO23 7DU",
    "sg:province":"Hampshire",
    "sg:tags":[
        "pharmaceutical"
    ],
    "wof:name":"Quedos Ltd.",
    "wof:placetype":"venue"
},
  "geometry": {"coordinates":[-1.3168090582,51.0630683899],"type":"Point"}
}