{
  "type": "Feature",
  "properties": {
    "addr:full":"64 Waterloo St Glasgow Glasgow City G2 7DA",
    "addr:housenumber":"64",
    "addr:postcode":"g2 7da",
    "addr:street":"Waterloo St",
    "iso:country":"GB",
    "sg:address":"64 Waterloo St",
    "sg:city":"Glasgow",
    "sg:classifiers":[
        {
            "category":"Banks & Credit Unions",
            "subcategory":"Financial Services",
            "type":"Services"
        }
    ],
    "sg:phone":"+44 141 225 2004",
    "sg:postcode":"G2 7DA",
    "sg:province":"Glasgow City",
    "sg:tags":[
        "marketing",
        "board"
    ],
    "wof:name":"Scotland The Brand",
    "wof:placetype":"venue"
},
  "geometry": {"coordinates":[-4.263429,55.860641],"type":"Point"}
}