{
  "type": "Feature",
  "properties": {
    "iso:country":"GB",
    "sg:address":"52 High Street",
    "sg:city":"Chatteris",
    "sg:classifiers":[
        {
            "category":"Shopping",
            "subcategory":"Clothing, Apparel, & Fashions",
            "type":"Retail Goods"
        }
    ],
    "sg:postcode":"PE16 6BH",
    "sg:province":"Cambridgeshire",
    "sg:tags":[
        "menswear"
    ],
    "wof:name":"G & E S Ray",
    "wof:placetype":"venue"
},
  "geometry": {"coordinates":[0.0481229983,52.4566993713],"type":"Point"}
}