{
  "type": "Feature",
  "properties": {
    "iso:country":"GB",
    "sg:address":"30 The Square",
    "sg:city":"Birchington",
    "sg:classifiers":[
        {
            "category":"Professional",
            "subcategory":"Accounting & Tax Preparation",
            "type":"Services"
        }
    ],
    "sg:phone":"+44 1843 845141",
    "sg:postcode":"CT7 9AB",
    "sg:province":"Kent",
    "sg:tags":[
        "accountant"
    ],
    "wof:name":"Noel Martin & Co",
    "wof:placetype":"venue"
},
  "geometry": {"coordinates":[1.30714,51.373859],"type":"Point"}
}