{
  "type": "Feature",
  "properties": {
    "addr:full":"28 Somers Road Trading Estate Rugby Warwickshire CV22 7DG",
    "addr:housenumber":"28;estate",
    "addr:postcode":"cv22 7dg",
    "addr:street":"Somers Road Trading",
    "iso:country":"GB",
    "sg:address":"28 Somers Road Trading Estate",
    "sg:city":"Rugby",
    "sg:classifiers":[
        {
            "category":"Professional",
            "type":"Services"
        }
    ],
    "sg:phone":"+44 1788 567508",
    "sg:postcode":"CV22 7DG",
    "sg:province":"Warwickshire",
    "sg:tags":[
        "display",
        "maker"
    ],
    "wof:name":"Mice Group Plc",
    "wof:placetype":"venue"
},
  "geometry": {"coordinates":[-1.287712,52.372696],"type":"Point"}
}