{
  "type": "Feature",
  "properties": {
    "addr:full":"110 Union Lane Cambridge Cambridgeshire CB4 1QB",
    "addr:housenumber":"110",
    "addr:postcode":"cb4 1qb",
    "addr:street":"Union Lane",
    "iso:country":"GB",
    "sg:address":"110 Union Lane",
    "sg:city":"Cambridge",
    "sg:classifiers":[
        {
            "category":"Autos & Motor Vehicles",
            "subcategory":"Motorcycle Sales",
            "type":"Retail Goods"
        }
    ],
    "sg:phone":"+44 1223 519333",
    "sg:postcode":"CB4 1QB",
    "sg:province":"Cambridgeshire",
    "sg:tags":[
        "chauffeur",
        "driven",
        "car"
    ],
    "wof:name":"Beaumont Chauffeur Services",
    "wof:placetype":"venue"
},
  "geometry": {"coordinates":[0.1356510073,52.2200050354],"type":"Point"}
}