{
  "type": "Feature",
  "properties": {
    "addr:full":"17 Gerrard Road Sunderland Tyne and Wear SR4 9QG",
    "addr:housenumber":"17",
    "addr:postcode":"sr4 9qg",
    "addr:street":"Gerrard Road",
    "iso:country":"GB",
    "sg:address":"17 Gerrard Road",
    "sg:city":"Sunderland",
    "sg:classifiers":[
        {
            "category":"Government",
            "subcategory":"Post Office",
            "type":"Public Place"
        }
    ],
    "sg:phone":"+44 191 534 2320",
    "sg:postcode":"SR4 9QG",
    "sg:province":"Tyne and Wear",
    "wof:name":"Gerrard Road Post Office",
    "wof:placetype":"venue"
},
  "geometry": {"coordinates":[-1.446917057,54.889415741],"type":"Point"}
}