{
  "type": "Feature",
  "properties": {
    "addr:full":"80 Chesterfield Rd Bristol City of Bristol BS6 5DR",
    "addr:housenumber":"80",
    "addr:postcode":"bs6 5dr",
    "addr:street":"Chesterfield Rd",
    "iso:country":"GB",
    "sg:address":"80 Chesterfield Rd",
    "sg:city":"Bristol",
    "sg:classifiers":[
        {
            "category":"Manufacturing",
            "subcategory":"Tools & Machinery",
            "type":"Manufacturing & Wholesale Goods"
        }
    ],
    "sg:phone":"+44 117 924 5654",
    "sg:postcode":"BS6 5DR",
    "sg:province":"City of Bristol",
    "sg:tags":[
        "society",
        "friendly"
    ],
    "wof:name":"Thornbury Insurance Services",
    "wof:placetype":"venue"
},
  "geometry": {"coordinates":[-2.5869250298,51.4680137634],"type":"Point"}
}