{
  "type": "Feature",
  "properties": {
    "iso:country":"GB",
    "sg:address":"Lower Gwestydd",
    "sg:city":"Newtown",
    "sg:classifiers":[
        {
            "category":"Travel",
            "subcategory":"Hotels & Motels",
            "type":"Entertainment"
        }
    ],
    "sg:phone":"+44 1686 626718",
    "sg:postcode":"SY16 3AY",
    "sg:province":"Powys",
    "sg:tags":[
        "house",
        "guest"
    ],
    "wof:name":"D E Jarman",
    "wof:placetype":"venue"
},
  "geometry": {"coordinates":[-3.2889039516,52.530960083],"type":"Point"}
}