{
  "type": "Feature",
  "properties": {
    "addr:full":"1 East St Bridge Town Cannock Staffordshire WS11 3LN",
    "addr:housenumber":"1",
    "addr:postcode":"ws11 3ln",
    "addr:street":"East St Bridge",
    "iso:country":"GB",
    "sg:address":"1 East St Bridge Town",
    "sg:city":"Cannock",
    "sg:classifiers":[
        {
            "category":"Retail",
            "subcategory":"Auto Repair",
            "type":"Services"
        }
    ],
    "sg:phone":"+44 1543 577027",
    "sg:postcode":"WS11 3LN",
    "sg:province":"Staffordshire",
    "sg:tags":[
        "body",
        "car"
    ],
    "wof:name":"Gerrard's",
    "wof:placetype":"venue"
},
  "geometry": {"coordinates":[-2.0331449509,52.690952301],"type":"Point"}
}