{
  "type": "Feature",
  "properties": {
    "iso:country":"GB",
    "sg:address":"52 Meadow Road, Earley",
    "sg:city":"Reading",
    "sg:classifiers":[
        {
            "category":"Retail",
            "subcategory":"Driving School",
            "type":"Services"
        }
    ],
    "sg:phone":"+44 118 926 5369",
    "sg:postcode":"RG6 7EX",
    "sg:province":"Berkshire",
    "wof:name":"Earley School Of Motoring",
    "wof:placetype":"venue"
},
  "geometry": {"coordinates":[-0.9091699719,51.4353179932],"type":"Point"}
}