{
  "type": "Feature",
  "properties": {
    "iso:country":"GB",
    "sg:address":"Gothic Cottage, 1 White Lion Street",
    "sg:city":"Stafford",
    "sg:classifiers":[
        {
            "category":"Professional",
            "subcategory":"Accounting & Tax Preparation",
            "type":"Services"
        }
    ],
    "sg:phone":"+44 1785 215044",
    "sg:postcode":"ST17 4BW",
    "sg:province":"Staffordshire",
    "sg:tags":[
        "accountant"
    ],
    "wof:name":"Jackson's",
    "wof:placetype":"venue"
},
  "geometry": {"coordinates":[-2.11368,52.802738],"type":"Point"}
}