{
  "type": "Feature",
  "properties": {
    "addr:full":"Sandy Road Liverpool Merseyside L21 1AF",
    "addr:postcode":"l21 1af",
    "addr:street":"Sandy Road",
    "iso:country":"GB",
    "sg:address":"Sandy Road",
    "sg:city":"Liverpool",
    "sg:classifiers":[
        {
            "category":"Shopping",
            "subcategory":"Clothing, Apparel, & Fashions",
            "type":"Retail Goods"
        }
    ],
    "sg:phone":"+44 151 920 5888",
    "sg:postcode":"L21 1AF",
    "sg:province":"Merseyside",
    "sg:tags":[
        "clothing",
        "fabric"
    ],
    "wof:name":"Bentwood Ltd.",
    "wof:placetype":"venue"
},
  "geometry": {"coordinates":[-3.0136039257,53.4701461792],"type":"Point"}
}