{
  "type": "Feature",
  "properties": {
    "addr:full":"7 Royde Close, St Fagans Cardiff Cardiff CF5 4UP",
    "addr:housenumber":"7",
    "addr:postcode":"cf5 4up",
    "addr:street":"Royde Close",
    "iso:country":"GB",
    "sg:address":"7 Royde Close, St Fagans",
    "sg:city":"Cardiff",
    "sg:classifiers":[
        {
            "category":"Communications",
            "subcategory":"News Services",
            "type":"Services"
        }
    ],
    "sg:postcode":"CF5 4UP",
    "sg:province":"Cardiff",
    "sg:tags":[
        "journalist"
    ],
    "wof:name":"Andrew Shott",
    "wof:placetype":"venue"
},
  "geometry": {"coordinates":[-3.268543005,51.4749069214],"type":"Point"}
}