{
  "type": "Feature",
  "properties": {
    "iso:country":"GB",
    "sg:address":"19a Earsham Street",
    "sg:city":"Bungay",
    "sg:classifiers":[
        {
            "category":"Real Estate",
            "subcategory":"Surveying",
            "type":"Services"
        }
    ],
    "sg:phone":"+44 1986 895895",
    "sg:postcode":"NR35 1AE",
    "sg:province":"Norfolk",
    "sg:tags":[
        "surveyor",
        "quantity"
    ],
    "wof:name":"Brooke Contract Services Ltd.",
    "wof:placetype":"venue"
},
  "geometry": {"coordinates":[1.435875,52.456436],"type":"Point"}
}