{
  "type": "Feature",
  "properties": {
    "addr:full":"Tennyson House, 159-165 Great Portland St West End Hampshire W1N 5FD",
    "addr:housenumber":"159-165",
    "addr:postcode":"5fd",
    "addr:street":"Great Portland St",
    "iso:country":"GB",
    "sg:address":"Tennyson House, 159-165 Great Portland St",
    "sg:city":"West End",
    "sg:classifiers":[
        {
            "category":"Professional",
            "subcategory":"Art Services",
            "type":"Services"
        }
    ],
    "sg:phone":"+44 20 7436 3905",
    "sg:postcode":"W1N 5FD",
    "sg:province":"Hampshire",
    "sg:tags":[
        "consultant",
        "design"
    ],
    "wof:name":"Retail Planning Innovations",
    "wof:placetype":"venue"
},
  "geometry": {"coordinates":[-0.143537,51.521519],"type":"Point"}
}