{
  "type": "Feature",
  "properties": {
    "iso:country":"GB",
    "sg:address":"Blacketts Wood, Lochard Road, Aberfoyle",
    "sg:city":"Stirling",
    "sg:classifiers":[
        {
            "category":"Building & Trades",
            "subcategory":"Construction",
            "type":"Services"
        }
    ],
    "sg:postcode":"FK8 3TD",
    "sg:province":"Stirling",
    "sg:tags":[
        "contractor",
        "paving",
        "driveway"
    ],
    "wof:name":"Distinctive Driveways",
    "wof:placetype":"venue"
},
  "geometry": {"coordinates":[-4.378112793,56.1776771545],"type":"Point"}
}