{
  "type": "Feature",
  "properties": {
    "addr:full":"198 Blackburn Road Accrington Lancashire BB5 0AQ",
    "addr:housenumber":"198",
    "addr:postcode":"bb5 0aq",
    "addr:street":"Blackburn Road",
    "iso:country":"GB",
    "sg:address":"198 Blackburn Road",
    "sg:city":"Accrington",
    "sg:classifiers":[
        {
            "category":"Shopping",
            "subcategory":"Pharmacy",
            "type":"Retail Goods"
        }
    ],
    "sg:phone":"+44 1254 394083",
    "sg:postcode":"BB5 0AQ",
    "sg:province":"Lancashire",
    "sg:tags":[
        "pharmacist",
        "chemist"
    ],
    "wof:name":"Nash Chemists",
    "wof:placetype":"venue"
},
  "geometry": {"coordinates":[-2.375477,53.753109],"type":"Point"}
}