{
  "type": "Feature",
  "properties": {
    "addr:full":"Park Avenue Whitchurch Cheshire SY13 1SH",
    "addr:postcode":"sy13 1sh",
    "addr:street":"Park Avenue",
    "iso:country":"GB",
    "sg:address":"Park Avenue",
    "sg:city":"Whitchurch",
    "sg:classifiers":[
        {
            "category":"Professional",
            "subcategory":"Engineering",
            "type":"Services"
        }
    ],
    "sg:postcode":"SY13 1SH",
    "sg:province":"Cheshire",
    "wof:name":"Gollins Engineering",
    "wof:placetype":"venue"
},
  "geometry": {"coordinates":[-2.685861,52.968021],"type":"Point"}
}