{
  "type": "Feature",
  "properties": {
    "addr:full":"12 Fernville Lane Hemel Hempstead Hertfordshire HP2 4AL",
    "addr:housenumber":"12",
    "addr:postcode":"hp2 4al",
    "addr:street":"Fernville Lane",
    "iso:country":"GB",
    "sg:address":"12 Fernville Lane",
    "sg:city":"Hemel Hempstead",
    "sg:classifiers":[
        {
            "category":"Retail",
            "subcategory":"Photofinishing",
            "type":"Services"
        }
    ],
    "sg:postcode":"HP2 4AL",
    "sg:province":"Hertfordshire",
    "sg:tags":[
        "photographic",
        "processor"
    ],
    "wof:name":"The Dupe Connection",
    "wof:placetype":"venue"
},
  "geometry": {"coordinates":[-0.470899,51.754848],"type":"Point"}
}