{
  "type": "Feature",
  "properties": {
    "addr:full":"14 Beehive Lane Chelmsford Essex CM2 9TQ",
    "addr:housenumber":"14",
    "addr:postcode":"cm2 9tq",
    "addr:street":"Beehive Lane",
    "iso:country":"GB",
    "sg:address":"14 Beehive Lane",
    "sg:city":"Chelmsford",
    "sg:classifiers":[
        {
            "category":"Building & Trades",
            "subcategory":"Plumbing",
            "type":"Services"
        },
        {
            "category":"Home & Garden",
            "subcategory":"Building Materials",
            "type":"Retail Goods"
        }
    ],
    "sg:phone":"+44 1245 356540",
    "sg:postcode":"CM2 9TQ",
    "sg:province":"Essex",
    "sg:tags":[
        "furnishers",
        "bathroom",
        "planner",
        "heating"
    ],
    "wof:name":"Mid Essex Plumbing Services",
    "wof:placetype":"venue"
},
  "geometry": {"coordinates":[0.487,51.718491],"type":"Point"}
}