{
  "type": "Feature",
  "properties": {
    "iso:country":"GB",
    "sg:address":"Yew Tree Farm, Town Street, Lound",
    "sg:city":"Retford",
    "sg:classifiers":[
        {
            "category":"Home & Garden",
            "subcategory":"Garden Supply",
            "type":"Retail Goods"
        },
        {
            "category":"Farming",
            "subcategory":"Farm",
            "type":"Manufacturing & Wholesale Goods"
        }
    ],
    "sg:postcode":"DN22 8SA",
    "sg:province":"Nottinghamshire",
    "sg:tags":[
        "mixed",
        "bulb",
        "crop",
        "grower"
    ],
    "wof:name":"Powell Farms",
    "wof:placetype":"venue"
},
  "geometry": {"coordinates":[-0.962739,53.366295],"type":"Point"}
}