{
  "type": "Feature",
  "properties": {
    "addr:full":"Laser House, 132 Goswell Road London Greater London EC1V 7DY",
    "addr:housenumber":"132",
    "addr:postcode":"ec1v 7dy",
    "addr:street":"Goswell Road",
    "iso:country":"GB",
    "sg:address":"Laser House, 132 Goswell Road",
    "sg:city":"London",
    "sg:classifiers":[
        {
            "category":"Shopping",
            "subcategory":"Computers & Home Electronics",
            "type":"Retail Goods"
        },
        {
            "category":"Professional",
            "subcategory":"Computer Services",
            "type":"Services"
        }
    ],
    "sg:phone":"+44 20 7553 9950",
    "sg:postcode":"EC1V 7DY",
    "sg:province":"Greater London",
    "sg:tags":[
        "system",
        "software"
    ],
    "wof:name":"Jagrule Ltd.",
    "wof:placetype":"venue"
},
  "geometry": {"coordinates":[-0.099173,51.524921],"type":"Point"}
}