{
  "type": "Feature",
  "properties": {
    "addr:full":"37 High Street Herne Bay Kent CT6 5LN",
    "addr:housenumber":"37",
    "addr:postcode":"ct6 5ln",
    "addr:street":"High Street",
    "iso:country":"GB",
    "sg:address":"37 High Street",
    "sg:city":"Herne Bay",
    "sg:classifiers":[
        {
            "category":"Cafe",
            "type":"Food & Drink"
        }
    ],
    "sg:postcode":"CT6 5LN",
    "sg:province":"Kent",
    "sg:tags":[
        "tea",
        "room"
    ],
    "wof:name":"Golden Grill",
    "wof:placetype":"venue"
},
  "geometry": {"coordinates":[1.1236740351,51.371257782],"type":"Point"}
}