{
  "type": "Feature",
  "properties": {
    "addr:full":"11 Jengers Mead Billingshurst West Sussex RH14 9PB",
    "addr:housenumber":"11",
    "addr:postcode":"rh14 9pb",
    "addr:street":"Jengers Mead",
    "iso:country":"GB",
    "sg:address":"11 Jengers Mead",
    "sg:city":"Billingshurst",
    "sg:classifiers":[
        {
            "category":"Shopping",
            "subcategory":"Bicycles & Sporting Goods",
            "type":"Retail Goods"
        }
    ],
    "sg:phone":"+44 1403 782594",
    "sg:postcode":"RH14 9PB",
    "sg:province":"West Sussex",
    "sg:tags":[
        "shop",
        "cycle",
        "accessory"
    ],
    "wof:name":"Two Wheels Plus Cycles",
    "wof:placetype":"venue"
},
  "geometry": {"coordinates":[-0.4507859945,51.0242919922],"type":"Point"}
}