{
  "type": "Feature",
  "properties": {
    "iso:country":"GB",
    "sg:address":"Poplar Tree Farm, Carr Lane, Blyton",
    "sg:city":"Gainsborough",
    "sg:classifiers":[
        {
            "category":"Banks & Credit Unions",
            "subcategory":"Investment Brokerage",
            "type":"Services"
        }
    ],
    "sg:phone":"+44 1427 628817",
    "sg:postcode":"DN21 3LJ",
    "sg:province":"Lincolnshire",
    "sg:tags":[
        "contractor"
    ],
    "wof:name":"Blyth Farm Services Ltd.",
    "wof:placetype":"venue"
},
  "geometry": {"coordinates":[-0.722983,53.441483],"type":"Point"}
}