{
  "type": "Feature",
  "properties": {
    "iso:country":"GB",
    "sg:address":"P O Box 24",
    "sg:city":"Broxbourne",
    "sg:classifiers":[
        {
            "category":"Professional",
            "subcategory":"Lawyer & Legal Services",
            "type":"Services"
        }
    ],
    "sg:phone":"+44 1992 450914",
    "sg:postcode":"EN10 6BG",
    "sg:province":"Essex",
    "sg:tags":[
        "advice",
        "counselling"
    ],
    "wof:name":"Harlow & Broxbourne Womens Aid",
    "wof:placetype":"venue"
},
  "geometry": {"coordinates":[-0.0228530001,51.7297439575],"type":"Point"}
}