{
  "type": "Feature",
  "properties": {
    "addr:full":"25 Phipp Street London Greater London EC2A 4NP",
    "addr:housenumber":"25",
    "addr:postcode":"ec2a 4np",
    "addr:street":"Phipp Street",
    "iso:country":"GB",
    "sg:address":"25 Phipp Street",
    "sg:city":"London",
    "sg:classifiers":[
        {
            "category":"Communications",
            "subcategory":"Film & Video Production",
            "type":"Services"
        }
    ],
    "sg:phone":"+44 20 7613 3081",
    "sg:postcode":"EC2A 4NP",
    "sg:province":"Greater London",
    "sg:tags":[
        "illustrator",
        "artist"
    ],
    "wof:name":"Ian Jackson",
    "wof:placetype":"venue"
},
  "geometry": {"coordinates":[-0.0811270028,51.5246276855],"type":"Point"}
}