{
  "type": "Feature",
  "properties": {
    "addr:full":"44 Courtenay Street Newton Abbot Devon TQ12 2ED",
    "addr:housenumber":"44",
    "addr:postcode":"tq12 2ed",
    "addr:street":"Courtenay Street",
    "iso:country":"GB",
    "sg:address":"44 Courtenay Street",
    "sg:city":"Newton Abbot",
    "sg:classifiers":[
        {
            "category":"Retail",
            "subcategory":"Repair Shop",
            "type":"Services"
        }
    ],
    "sg:phone":"+44 1626 354613",
    "sg:postcode":"TQ12 2ED",
    "sg:province":"Devon",
    "sg:tags":[
        "clocks",
        "watch"
    ],
    "wof:name":"Gerry & Co Jewellers",
    "wof:placetype":"venue"
},
  "geometry": {"coordinates":[-3.6097249985,50.5304832458],"type":"Point"}
}