{
  "type": "Feature",
  "properties": {
    "addr:full":"10 Richard Street, Hetton-le-hole Houghton-le-spring Durham DH5 9HN",
    "addr:housenumber":"10",
    "addr:postcode":"dh5 9hn",
    "addr:street":"Richard Street",
    "iso:country":"GB",
    "sg:address":"10 Richard Street, Hetton-le-hole",
    "sg:city":"Houghton-le-spring",
    "sg:classifiers":[
        {
            "category":"Organizations",
            "subcategory":"Community Association",
            "type":"Services"
        },
        {
            "category":"Organizations",
            "subcategory":"Membership Organization",
            "type":"Services"
        }
    ],
    "sg:phone":"+44 191 526 2132",
    "sg:postcode":"DH5 9HN",
    "sg:province":"Durham",
    "sg:tags":[
        "club",
        "social"
    ],
    "wof:name":"Hetton Victory Club Ltd.",
    "wof:placetype":"venue"
},
  "geometry": {"coordinates":[-1.451343,54.820984],"type":"Point"}
}