{
  "type": "Feature",
  "properties": {
    "addr:full":"59 New Market Hall, Carlton Lane Castleford West Yorkshire WF10 1BE",
    "addr:housenumber":"59",
    "addr:postcode":"wf10 1be",
    "addr:street":"New Market Hall Carlton Lane",
    "iso:country":"GB",
    "sg:address":"59 New Market Hall, Carlton Lane",
    "sg:city":"Castleford",
    "sg:classifiers":[
        {
            "category":"Home & Garden",
            "subcategory":"Household Appliances",
            "type":"Retail Goods"
        }
    ],
    "sg:postcode":"WF10 1BE",
    "sg:province":"West Yorkshire",
    "sg:tags":[
        "electrical",
        "domestic"
    ],
    "wof:name":"Discount Electrics",
    "wof:placetype":"venue"
},
  "geometry": {"coordinates":[-1.3442080021,53.721698761],"type":"Point"}
}