{
  "type": "Feature",
  "properties": {
    "addr:full":"171 Lauderdale Mansions, Lauderdale Rd Maida Vale Greater London W9 1LY",
    "addr:housenumber":"171",
    "addr:postcode":"w9 1ly",
    "addr:street":"Lauderdale Rd",
    "iso:country":"GB",
    "sg:address":"171 Lauderdale Mansions, Lauderdale Rd",
    "sg:city":"Maida Vale",
    "sg:classifiers":[
        {
            "category":"Professional",
            "subcategory":"Secretarial Services",
            "type":"Services"
        }
    ],
    "sg:phone":"+44 20 7286 9839",
    "sg:postcode":"W9 1LY",
    "sg:province":"Greater London",
    "wof:name":"Betty Robinson",
    "wof:placetype":"venue"
},
  "geometry": {"coordinates":[-0.187529996,51.5274085999],"type":"Point"}
}