{
  "type": "Feature",
  "properties": {
    "addr:full":"3 Durngate Street Dorchester Dorset DT1 1JP",
    "addr:housenumber":"3",
    "addr:postcode":"dt1 1jp",
    "addr:street":"Durngate Street",
    "iso:country":"GB",
    "sg:address":"3 Durngate Street",
    "sg:city":"Dorchester",
    "sg:classifiers":[
        {
            "category":"Real Estate",
            "subcategory":"Architect",
            "type":"Services"
        },
        {
            "category":"Arts & Performance",
            "subcategory":"Theater",
            "type":"Entertainment"
        }
    ],
    "sg:postcode":"DT1 1JP",
    "sg:province":"Dorset",
    "sg:tags":[
        "theatre"
    ],
    "wof:name":"Adams Powell Associates",
    "wof:placetype":"venue"
},
  "geometry": {"coordinates":[-2.435296,50.714893],"type":"Point"}
}