{
  "type": "Feature",
  "properties": {
    "iso:country":"GB",
    "sg:address":"47 Rivermead Road",
    "sg:city":"Exeter",
    "sg:classifiers":[
        {
            "category":"Professional",
            "subcategory":"Engineering",
            "type":"Services"
        }
    ],
    "sg:postcode":"EX2 4RH",
    "sg:province":"Devon",
    "sg:tags":[
        "design",
        "engineer"
    ],
    "wof:name":"David Roche Geoconsulting Ltd.",
    "wof:placetype":"venue"
},
  "geometry": {"coordinates":[-3.517424,50.710522],"type":"Point"}
}