{
  "type": "Feature",
  "properties": {
    "addr:full":"11 Pryors Orchard, Melbourn Royston Bedfordshire SG8 6UT",
    "addr:housenumber":"11",
    "addr:postcode":"sg8 6ut",
    "addr:street":"Pryors Orchard",
    "iso:country":"GB",
    "sg:address":"11 Pryors Orchard, Melbourn",
    "sg:city":"Royston",
    "sg:classifiers":[
        {
            "category":"Building & Trades",
            "subcategory":"Construction",
            "type":"Services"
        }
    ],
    "sg:phone":"+44 1763 261700",
    "sg:postcode":"SG8 6UT",
    "sg:province":"Bedfordshire",
    "sg:tags":[
        "decorator",
        "painter"
    ],
    "wof:name":"J Halbert (Cambridge) Ltd.",
    "wof:placetype":"venue"
},
  "geometry": {"coordinates":[0.011957,52.087051],"type":"Point"}
}