{
  "type": "Feature",
  "properties": {
    "iso:country":"GB",
    "sg:address":"13 Leighton Road, Northhall",
    "sg:city":"Dunstable",
    "sg:classifiers":[
        {
            "category":"Building & Trades",
            "subcategory":"Construction",
            "type":"Services"
        }
    ],
    "sg:phone":"+44 1525 220142",
    "sg:postcode":"LU6 2HD",
    "sg:province":"Bedfordshire",
    "sg:tags":[
        "builder"
    ],
    "wof:name":"Dennis Leaver",
    "wof:placetype":"venue"
},
  "geometry": {"coordinates":[-0.598491,51.865238],"type":"Point"}
}