{
  "type": "Feature",
  "properties": {
    "iso:country":"GB",
    "sg:address":"Second Floor Harrington Chambers, 26 North John Street",
    "sg:city":"Liverpool",
    "sg:classifiers":[
        {
            "category":"Professional",
            "subcategory":"Employment Agencies",
            "type":"Services"
        }
    ],
    "sg:phone":"+44 151 227 1050",
    "sg:postcode":"L2 9RU",
    "sg:province":"Merseyside",
    "sg:tags":[
        "consultant"
    ],
    "wof:name":"Elite Recruitment Agency Ltd.",
    "wof:placetype":"venue"
},
  "geometry": {"coordinates":[-2.98846,53.405762],"type":"Point"}
}