{
  "type": "Feature",
  "properties": {
    "addr:full":"Main Road Tamworth Staffordshire B77 2BS",
    "addr:postcode":"b77 2bs",
    "addr:street":"Main Road",
    "iso:country":"GB",
    "sg:address":"Main Road",
    "sg:city":"Tamworth",
    "sg:classifiers":[
        {
            "category":"Ice Cream",
            "type":"Food & Drink"
        }
    ],
    "sg:phone":"+44 1827 54196",
    "sg:postcode":"B77 2BS",
    "sg:province":"Staffordshire",
    "sg:tags":[
        "mnfr"
    ],
    "wof:name":"Suncream Dairies Ltd.",
    "wof:placetype":"venue"
},
  "geometry": {"coordinates":[-1.6918640137,52.6506538391],"type":"Point"}
}