{
  "type": "Feature",
  "properties": {
    "addr:full":"10 Upland Drive Plymouth Devon PL6 6BB",
    "addr:housenumber":"10",
    "addr:postcode":"pl6 6bb",
    "addr:street":"Upland Drive",
    "iso:country":"GB",
    "sg:address":"10 Upland Drive",
    "sg:city":"Plymouth",
    "sg:classifiers":[
        {
            "category":"Professional",
            "type":"Services"
        }
    ],
    "sg:phone":"+44 1752 775058",
    "sg:postcode":"PL6 6BB",
    "sg:province":"Devon",
    "sg:tags":[
        "caterer"
    ],
    "wof:name":"Stedman Catering",
    "wof:placetype":"venue"
},
  "geometry": {"coordinates":[-4.1211829185,50.4247398376],"type":"Point"}
}