{
  "type": "Feature",
  "properties": {
    "iso:country":"GB",
    "sg:address":"76 Willoughby Lane",
    "sg:city":"London",
    "sg:classifiers":[
        {
            "category":"Retail",
            "subcategory":"Auto Repair",
            "type":"Services"
        }
    ],
    "sg:phone":"+44 20 8885 3741",
    "sg:postcode":"N17 0SS",
    "sg:province":"Greater London",
    "sg:tags":[
        "engine",
        "car",
        "specialist"
    ],
    "wof:name":"M & M Autocare Ltd.",
    "wof:placetype":"venue"
},
  "geometry": {"coordinates":[-0.054338,51.607597],"type":"Point"}
}