{
  "type": "Feature",
  "properties": {
    "addr:full":"47 Newhall St Birmingham West Midlands B3 3QU",
    "addr:housenumber":"47",
    "addr:postcode":"b3 3qu",
    "addr:street":"Newhall St",
    "iso:country":"GB",
    "sg:address":"47 Newhall St",
    "sg:city":"Birmingham",
    "sg:classifiers":[
        {
            "category":"Professional",
            "subcategory":"Lawyer & Legal Services",
            "type":"Services"
        }
    ],
    "sg:phone":"+44 121 233 2644",
    "sg:postcode":"B3 3QU",
    "sg:province":"West Midlands",
    "sg:tags":[
        "solicitor"
    ],
    "wof:name":"A Smith Parton & Co",
    "wof:placetype":"venue"
},
  "geometry": {"coordinates":[-1.902812,52.482006],"type":"Point"}
}