{
  "type": "Feature",
  "properties": {
    "addr:full":"113-115 High Street, Uppermill Oldham Lancashire OL3 6BD",
    "addr:housenumber":"113-115",
    "addr:postcode":"ol3 6bd",
    "addr:street":"High Street",
    "iso:country":"GB",
    "sg:address":"113-115 High Street, Uppermill",
    "sg:city":"Oldham",
    "sg:classifiers":[
        {
            "category":"Government",
            "subcategory":"Office",
            "type":"Public Place"
        }
    ],
    "sg:phone":"+44 1457 872427",
    "sg:postcode":"OL3 6BD",
    "sg:province":"Lancashire",
    "sg:tags":[
        "education",
        "agency",
        "authority"
    ],
    "wof:name":"Focus Education",
    "wof:placetype":"venue"
},
  "geometry": {"coordinates":[-2.005474,53.549965],"type":"Point"}
}