{
  "type": "Feature",
  "properties": {
    "addr:full":"Townsend Chambers, Amherst Hill Sevenoaks Kent TN13 2EL",
    "addr:postcode":"tn13 2el",
    "addr:street":"Amherst Hill",
    "iso:country":"GB",
    "sg:address":"Townsend Chambers, Amherst Hill",
    "sg:city":"Sevenoaks",
    "sg:classifiers":[
        {
            "category":"Wholesale",
            "subcategory":"Meat",
            "type":"Manufacturing & Wholesale Goods"
        }
    ],
    "sg:phone":"+44 1732 740741",
    "sg:postcode":"TN13 2EL",
    "sg:province":"Kent",
    "sg:tags":[
        "-"
    ],
    "wof:name":"Meatal Supplies Ltd",
    "wof:placetype":"venue"
},
  "geometry": {"coordinates":[0.1929389983,51.270198822],"type":"Point"}
}