{
  "type": "Feature",
  "properties": {
    "addr:full":"Holt Rd, Greet Birmingham West Midlands B6 6RP",
    "addr:postcode":"b6 6rp",
    "addr:street":"Holt Rd",
    "iso:country":"GB",
    "sg:address":"Holt Rd, Greet",
    "sg:city":"Birmingham",
    "sg:classifiers":[
        {
            "category":"Sports & Exercise",
            "subcategory":"Tennis Court",
            "type":"Entertainment"
        }
    ],
    "sg:phone":"+44 121 766 5825",
    "sg:postcode":"B6 6RP",
    "sg:province":"West Midlands",
    "sg:tags":[
        "breakdown",
        "recovery"
    ],
    "wof:name":"New Style Recovery & Salvage",
    "wof:placetype":"venue"
},
  "geometry": {"coordinates":[-1.882344,52.509094],"type":"Point"}
}