{
  "type": "Feature",
  "properties": {
    "iso:country":"GB",
    "sg:address":"Bod Hyfryd Farm, Maenan Llanrwst",
    "sg:city":"Llanrwst",
    "sg:classifiers":[
        {
            "category":"Farming",
            "subcategory":"Dairy Farm",
            "type":"Manufacturing & Wholesale Goods"
        }
    ],
    "sg:phone":"+44 1492 660201",
    "sg:postcode":"LL26 0YR",
    "sg:province":"Conwy",
    "wof:name":"W J Davies & Co",
    "wof:placetype":"venue"
},
  "geometry": {"coordinates":[-3.7977,53.137661],"type":"Point"}
}