{
  "type": "Feature",
  "properties": {
    "addr:full":"104 Fishergate Preston Lancashire PR1 2AE",
    "addr:housenumber":"104",
    "addr:postcode":"pr1 2ae",
    "addr:street":"Fishergate Preston",
    "iso:country":"GB",
    "sg:address":"104 Fishergate",
    "sg:city":"Preston",
    "sg:classifiers":[
        {
            "category":"Shopping",
            "subcategory":"Shoes",
            "type":"Retail Goods"
        }
    ],
    "sg:phone":"+44 1772 250819",
    "sg:postcode":"PR1 2AE",
    "sg:province":"Lancashire",
    "sg:tags":[
        "shop",
        "retailer",
        "footwear"
    ],
    "sg:website":"http://www.clarks.co.uk",
    "wof:name":"Clarks Shoes Ltd",
    "wof:placetype":"venue"
},
  "geometry": {"coordinates":[-2.701299,53.758144],"type":"Point"}
}