{
  "type": "Feature",
  "properties": {
    "addr:full":"2 Tivoli Crescent Brighton East Sussex BN1 5ND",
    "addr:housenumber":"2",
    "addr:postcode":"bn1 5nd",
    "addr:street":"Tivoli Crescent",
    "iso:country":"GB",
    "sg:address":"2 Tivoli Crescent",
    "sg:city":"Brighton",
    "sg:classifiers":[
        {
            "category":"Autos & Motor Vehicles",
            "subcategory":"Auto Supplies",
            "type":"Retail Goods"
        }
    ],
    "sg:phone":"+44 1273 559797",
    "sg:postcode":"BN1 5ND",
    "sg:province":"East Sussex",
    "sg:tags":[
        "component"
    ],
    "wof:name":"Btr Brakes",
    "wof:placetype":"venue"
},
  "geometry": {"coordinates":[-0.1580249965,50.8422203064],"type":"Point"}
}