{
  "type": "Feature",
  "properties": {
    "addr:full":"125 Sibson Road, Birstall Leicester Leicestershire LE4 4ND",
    "addr:housenumber":"125",
    "addr:postcode":"le4 4nd",
    "addr:street":"Sibson Road",
    "iso:country":"GB",
    "sg:address":"125 Sibson Road, Birstall",
    "sg:city":"Leicester",
    "sg:classifiers":[
        {
            "category":"Home & Garden",
            "subcategory":"Home Furnishings",
            "type":"Retail Goods"
        },
        {
            "category":"Home & Garden",
            "subcategory":"Building Materials",
            "type":"Retail Goods"
        }
    ],
    "sg:phone":"+44 116 267 1231",
    "sg:postcode":"LE4 4ND",
    "sg:province":"Leicestershire",
    "sg:tags":[
        "installers",
        "planner",
        "kitchen",
        "furnishers"
    ],
    "wof:name":"Sapphire Kitchens & Bedrooms",
    "wof:placetype":"venue"
},
  "geometry": {"coordinates":[-1.124442,52.679825],"type":"Point"}
}