{
  "type": "Feature",
  "properties": {
    "addr:full":"Green Nook Farm, Carrs Green Preston Lancashire PR4 0TJ",
    "addr:postcode":"pr4 0tj",
    "addr:street":"Carrs Green",
    "iso:country":"GB",
    "sg:address":"Green Nook Farm, Carrs Green",
    "sg:city":"Preston",
    "sg:classifiers":[
        {
            "category":"Travel",
            "subcategory":"Hotels & Motels",
            "type":"Entertainment"
        }
    ],
    "sg:phone":"+44 1772 690530",
    "sg:postcode":"PR4 0TJ",
    "sg:province":"Lancashire",
    "sg:tags":[
        "house",
        "guest"
    ],
    "wof:name":"M Whitehead",
    "wof:placetype":"venue"
},
  "geometry": {"coordinates":[-2.80845,53.82951],"type":"Point"}
}