{
  "type": "Feature",
  "properties": {
    "addr:full":"R B R House, Central Park Telford Shropshire TF2 9TU",
    "addr:postcode":"tf2 9tu",
    "addr:street":"R B R House",
    "iso:country":"GB",
    "sg:address":"R B R House, Central Park",
    "sg:city":"Telford",
    "sg:classifiers":[
        {
            "category":"Education",
            "subcategory":"Special Training",
            "type":"Public Place"
        }
    ],
    "sg:phone":"+44 1952 201338",
    "sg:postcode":"TF2 9TU",
    "sg:province":"Shropshire",
    "sg:tags":[
        "product",
        "centre"
    ],
    "wof:name":"Specialist Training International Ltd.",
    "wof:placetype":"venue"
},
  "geometry": {"coordinates":[-2.4447820187,52.6783981323],"type":"Point"}
}