{
  "type": "Feature",
  "properties": {
    "iso:country":"GB",
    "sg:address":"195 Split Crow Road, Deckham",
    "sg:city":"Gateshead",
    "sg:classifiers":[
        {
            "category":"Social Services",
            "type":"Services"
        },
        {
            "category":"Government",
            "subcategory":"Office",
            "type":"Public Place"
        }
    ],
    "sg:phone":"+44 191 477 1864",
    "sg:postcode":"NE10 9HL",
    "sg:province":"Tyne and Wear",
    "sg:tags":[
        "local"
    ],
    "wof:name":"Deckham Family Centre",
    "wof:placetype":"venue"
},
  "geometry": {"coordinates":[-1.579771,54.950893],"type":"Point"}
}