{
  "type": "Feature",
  "properties": {
    "iso:country":"GB",
    "sg:address":"2 Pinfold Close",
    "sg:city":"Wetherby",
    "sg:classifiers":[
        {
            "category":"Home & Garden",
            "subcategory":"Building Materials",
            "type":"Retail Goods"
        }
    ],
    "sg:phone":"+44 1423 359842",
    "sg:postcode":"LS22 5JW",
    "sg:province":"North Yorkshire",
    "sg:tags":[
        "fencing"
    ],
    "wof:name":"Fabrication & Fencing Services Ltd.",
    "wof:placetype":"venue"
},
  "geometry": {"coordinates":[-1.312792,53.948574],"type":"Point"}
}