{
  "type": "Feature",
  "properties": {
    "addr:full":"Unit 4 Whitworth Road, Pingreen Industrial Estate Stevenage Hertfordshire SG1 4QS",
    "addr:housenumber":"unit 4",
    "addr:postcode":"sg1 4qs",
    "addr:street":"Whitworth Road Pingreen Industrial Estate",
    "iso:country":"GB",
    "sg:address":"Unit 4 Whitworth Road, Pingreen Industrial Estate",
    "sg:city":"Stevenage",
    "sg:classifiers":[
        {
            "category":"Professional",
            "subcategory":"Computer Services",
            "type":"Services"
        }
    ],
    "sg:phone":"+44 1438 354422",
    "sg:postcode":"SG1 4QS",
    "sg:province":"Hertfordshire",
    "sg:tags":[
        "system",
        "software"
    ],
    "wof:name":"Logicare",
    "wof:placetype":"venue"
},
  "geometry": {"coordinates":[-0.1701100022,51.927532196],"type":"Point"}
}