{
  "type": "Feature",
  "properties": {
    "addr:full":"145 Hales Road Cheltenham Gloucestershire GL52 6TD",
    "addr:housenumber":"145",
    "addr:postcode":"gl52 6td",
    "addr:street":"Hales Road",
    "iso:country":"GB",
    "sg:address":"145 Hales Road",
    "sg:city":"Cheltenham",
    "sg:classifiers":[
        {
            "category":"Social Services",
            "subcategory":"Retirement Home",
            "type":"Services"
        }
    ],
    "sg:postcode":"GL52 6TD",
    "sg:province":"Gloucestershire",
    "sg:tags":[
        "rest"
    ],
    "wof:name":"Thornburns Rest Home",
    "wof:placetype":"venue"
},
  "geometry": {"coordinates":[-2.055497,51.900093],"type":"Point"}
}