{
  "type": "Feature",
  "properties": {
    "addr:full":"2 Glenthorne Road London Greater London N11 3HT",
    "addr:housenumber":"2",
    "addr:postcode":"n11 3ht",
    "addr:street":"Glenthorne Road",
    "iso:country":"GB",
    "sg:address":"2 Glenthorne Road",
    "sg:city":"London",
    "sg:classifiers":[
        {
            "category":"Professional",
            "subcategory":"Printing & Photocopies",
            "type":"Services"
        }
    ],
    "sg:phone":"+44 20 8368 4567",
    "sg:postcode":"N11 3HT",
    "sg:province":"Greater London",
    "sg:tags":[
        "printer"
    ],
    "wof:name":"Market Printing Service",
    "wof:placetype":"venue"
},
  "geometry": {"coordinates":[-0.150948,51.614395],"type":"Point"}
}