{
  "type": "Feature",
  "properties": {
    "addr:full":"5 Bruton Street London Greater London W1X 7AF",
    "addr:housenumber":"5",
    "addr:postcode":"w1x 7af",
    "addr:street":"Bruton Street",
    "iso:country":"GB",
    "sg:address":"5 Bruton Street",
    "sg:city":"London",
    "sg:classifiers":[
        {
            "category":"Bars & Pubs",
            "type":"Food & Drink"
        }
    ],
    "sg:phone":"+44 20 7629 4123",
    "sg:postcode":"W1X 7AF",
    "sg:province":"Greater London",
    "sg:tags":[
        "pubs",
        "inn"
    ],
    "wof:name":"Coach & Horses",
    "wof:placetype":"venue"
},
  "geometry": {"coordinates":[-0.144223,51.511055],"type":"Point"}
}