{
  "type": "Feature",
  "properties": {
    "addr:full":"27-29 Eastcheap London Greater London EC3M 1DE",
    "addr:housenumber":"27-29",
    "addr:postcode":"ec3m 1de",
    "addr:street":"Eastcheap",
    "iso:country":"GB",
    "sg:address":"27-29 Eastcheap",
    "sg:city":"London",
    "sg:classifiers":[
        {
            "category":"Travel",
            "subcategory":"Travel Agent",
            "type":"Entertainment"
        }
    ],
    "sg:phone":"+44 20 7623 3341",
    "sg:postcode":"EC3M 1DE",
    "sg:province":"Greater London",
    "wof:name":"Going Places Leisure Travel",
    "wof:placetype":"venue"
},
  "geometry": {"coordinates":[-0.0841019973,51.5107574463],"type":"Point"}
}