{
  "type": "Feature",
  "properties": {
    "addr:full":"162 Warbreck Moor Liverpool Merseyside L9 0HZ",
    "addr:housenumber":"162",
    "addr:postcode":"l9 0hz",
    "addr:street":"Warbreck Moor",
    "iso:country":"GB",
    "sg:address":"162 Warbreck Moor",
    "sg:city":"Liverpool",
    "sg:classifiers":[
        {
            "category":"Retail",
            "subcategory":"Auto Repair",
            "type":"Services"
        }
    ],
    "sg:postcode":"L9 0HZ",
    "sg:province":"Merseyside",
    "sg:tags":[
        "modification",
        "garage"
    ],
    "wof:name":"J & M Motors",
    "wof:placetype":"venue"
},
  "geometry": {"coordinates":[-2.955563,53.469788],"type":"Point"}
}