{
  "type": "Feature",
  "properties": {
    "addr:full":"Pantdwfn Farm Carmarthen Carmarthenshire SA33 4NF",
    "addr:housenumber":"carmarthen",
    "addr:postcode":"sa33 4nf",
    "addr:street":"Carmarthenshire",
    "iso:country":"GB",
    "sg:address":"Pantdwfn Farm",
    "sg:city":"Carmarthen",
    "sg:classifiers":[
        {
            "category":"Farming",
            "subcategory":"Livestock Farm",
            "type":"Manufacturing & Wholesale Goods"
        }
    ],
    "sg:phone":"+44 1994 231051",
    "sg:postcode":"SA33 4NF",
    "sg:province":"Carmarthenshire",
    "sg:tags":[
        "others"
    ],
    "wof:name":"I Parker",
    "wof:placetype":"venue"
},
  "geometry": {"coordinates":[-4.4707698822,51.8058815002],"type":"Point"}
}