{
  "type": "Feature",
  "properties": {
    "addr:full":"270-274 Ashley Rd Poole Dorset BH14 9BZ",
    "addr:housenumber":"270-274",
    "addr:postcode":"bh14 9bz",
    "addr:street":"Ashley Rd",
    "iso:country":"GB",
    "sg:address":"270-274 Ashley Rd",
    "sg:city":"Poole",
    "sg:classifiers":[
        {
            "category":"Retail",
            "subcategory":"Auto Repair",
            "type":"Services"
        }
    ],
    "sg:phone":"+44 1202 381381",
    "sg:postcode":"BH14 9BZ",
    "sg:province":"Dorset",
    "sg:tags":[
        "engine",
        "car",
        "specialist"
    ],
    "wof:name":"Hughes Motor Co",
    "wof:placetype":"venue"
},
  "geometry": {"coordinates":[-1.9339109659,50.7286567688],"type":"Point"}
}