{
  "type": "Feature",
  "properties": {
    "addr:full":"328a Victoria Road Ruislip Greater London HA4 0DP",
    "addr:housenumber":"328a",
    "addr:postcode":"ha4 0dp",
    "addr:street":"Victoria Road",
    "iso:country":"GB",
    "sg:address":"328a Victoria Road",
    "sg:city":"Ruislip",
    "sg:classifiers":[
        {
            "category":"Building & Trades",
            "subcategory":"Construction",
            "type":"Services"
        }
    ],
    "sg:phone":"+44 1895 638290",
    "sg:postcode":"HA4 0DP",
    "sg:province":"Greater London",
    "sg:tags":[
        "builder"
    ],
    "wof:name":"David Baker",
    "wof:placetype":"venue"
},
  "geometry": {"coordinates":[-0.4052380025,51.5640029907],"type":"Point"}
}