{
  "type": "Feature",
  "properties": {
    "iso:country":"GB",
    "sg:address":"Unit 4-5 Sunnyside Park, Hinckley Fields Industrial Estate",
    "sg:city":"Hinckley",
    "sg:classifiers":[
        {
            "category":"Communications",
            "subcategory":"Film & Video Production",
            "type":"Services"
        }
    ],
    "sg:phone":"+44 24 7639 3888",
    "sg:postcode":"LE10 1PJ",
    "sg:province":"Leicestershire",
    "sg:tags":[
        "mnfr",
        "coating",
        "powder"
    ],
    "wof:name":"Appletec/Epsi U K Ltd.",
    "wof:placetype":"venue"
},
  "geometry": {"coordinates":[-1.366601944,52.5524902344],"type":"Point"}
}