{
  "type": "Feature",
  "properties": {
    "iso:country":"GB",
    "sg:address":"Dockray Hall Mill, Dockray Hall",
    "sg:city":"Kendal",
    "sg:classifiers":[
        {
            "category":"Manufacturing",
            "subcategory":"Building Materials",
            "type":"Manufacturing & Wholesale Goods"
        }
    ],
    "sg:phone":"+44 1539 723600",
    "sg:postcode":"LA9 4RU",
    "sg:province":"Cumbria",
    "sg:tags":[
        "concrete",
        "product"
    ],
    "wof:name":"Cumbria Precast",
    "wof:placetype":"venue"
},
  "geometry": {"coordinates":[-2.7479379177,54.3352508545],"type":"Point"}
}