{
  "type": "Feature",
  "properties": {
    "addr:full":"Jordans Courtyard, 8 Upper High Street Thame Buckinghamshire OX9 3ER",
    "addr:housenumber":"8",
    "addr:postcode":"ox9 3er",
    "addr:street":"Jordans Courtyard;Upper High Street",
    "iso:country":"GB",
    "sg:address":"Jordans Courtyard, 8 Upper High Street",
    "sg:city":"Thame",
    "sg:classifiers":[
        {
            "category":"Education",
            "subcategory":"School",
            "type":"Public Place"
        }
    ],
    "sg:phone":"+44 1844 260270",
    "sg:postcode":"OX9 3ER",
    "sg:province":"Buckinghamshire",
    "sg:tags":[
        "private",
        "tuition"
    ],
    "wof:name":"Pelican Point Learning",
    "wof:placetype":"venue"
},
  "geometry": {"coordinates":[-0.980029,51.74855],"type":"Point"}
}