{
  "type": "Feature",
  "properties": {
    "addr:full":"Grantham Road, Old Somerby Grantham Leicestershire NG33 4AB",
    "addr:postcode":"ng33 4ab",
    "addr:street":"Grantham Road",
    "iso:country":"GB",
    "sg:address":"Grantham Road, Old Somerby",
    "sg:city":"Grantham",
    "sg:classifiers":[
        {
            "category":"Bars & Pubs",
            "type":"Food & Drink"
        }
    ],
    "sg:phone":"+44 1476 564121",
    "sg:postcode":"NG33 4AB",
    "sg:province":"Leicestershire",
    "sg:tags":[
        "pubs",
        "inn"
    ],
    "wof:name":"Fox & Hounds",
    "wof:placetype":"venue"
},
  "geometry": {"coordinates":[-0.574959,52.889854],"type":"Point"}
}