{
  "type": "Feature",
  "properties": {
    "iso:country":"GB",
    "sg:address":"The Manor Lodge, Thornhill Rd, South Marsdon",
    "sg:city":"Swindon",
    "sg:classifiers":[
        {
            "category":"Professional",
            "type":"Services"
        }
    ],
    "sg:phone":"+44 1793 824533",
    "sg:postcode":"SN3 4RY",
    "sg:province":"Wiltshire",
    "sg:tags":[
        "interior",
        "furnishers",
        "designer"
    ],
    "wof:name":"Bridgford Design Solutions",
    "wof:placetype":"venue"
},
  "geometry": {"coordinates":[-1.7246299982,51.58826828],"type":"Point"}
}