{
  "type": "Feature",
  "properties": {
    "addr:full":"Wharf Ho, Stratford Rd Buckingham Buckinghamshire MK18 1TD",
    "addr:postcode":"mk18 1td",
    "addr:street":"Wharf;Stratford Rd",
    "iso:country":"GB",
    "sg:address":"Wharf Ho, Stratford Rd",
    "sg:city":"Buckingham",
    "sg:classifiers":[
        {
            "category":"Banks & Credit Unions",
            "subcategory":"Bank",
            "type":"Services"
        }
    ],
    "sg:phone":"+44 1280 821407",
    "sg:postcode":"MK18 1TD",
    "sg:province":"Buckinghamshire",
    "sg:tags":[
        "broker",
        "mortgage"
    ],
    "wof:name":"D W P Financial",
    "wof:placetype":"venue"
},
  "geometry": {"coordinates":[-0.986479,52.000751],"type":"Point"}
}