{
  "type": "Feature",
  "properties": {
    "iso:country":"GB",
    "sg:address":"Unit 6, Meadow La",
    "sg:city":"Ellesmere Port",
    "sg:classifiers":[
        {
            "category":"Manufacturing",
            "subcategory":"Metals",
            "type":"Manufacturing & Wholesale Goods"
        }
    ],
    "sg:phone":"+44 151 355 5454",
    "sg:postcode":"CH65 4EH",
    "sg:province":"Cheshire",
    "sg:tags":[
        "steel",
        "fabricator",
        "erectors"
    ],
    "wof:name":"'Lenvic' Erection & Pipework Services Lt",
    "wof:placetype":"venue"
},
  "geometry": {"coordinates":[-2.894974,53.283504],"type":"Point"}
}