{
  "type": "Feature",
  "properties": {
    "addr:full":"Dawley Trading Estate Brierley Hill Staffordshire DY6 7BW",
    "addr:postcode":"dy6 7bw",
    "iso:country":"GB",
    "sg:address":"Dawley Trading Estate",
    "sg:city":"Brierley Hill",
    "sg:classifiers":[
        {
            "category":"Home & Garden",
            "subcategory":"Home Furnishings",
            "type":"Retail Goods"
        }
    ],
    "sg:phone":"+44 1384 401299",
    "sg:postcode":"DY6 7BW",
    "sg:province":"Staffordshire",
    "sg:tags":[
        "tube",
        "fitting",
        "stockist"
    ],
    "wof:name":"Blackheath Tube Co. Ltd.",
    "wof:placetype":"venue"
},
  "geometry": {"coordinates":[-2.1656999588,52.504901886],"type":"Point"}
}