{
  "type": "Feature",
  "properties": {
    "addr:full":"Ponteland Road, Prestwick Newcastle-upon-tyne Northumberland NE20 9DB",
    "addr:postcode":"ne20 9db",
    "addr:street":"Ponteland Road",
    "iso:country":"GB",
    "sg:address":"Ponteland Road, Prestwick",
    "sg:city":"Newcastle-upon-tyne",
    "sg:classifiers":[
        {
            "category":"Restaurant",
            "type":"Food & Drink"
        }
    ],
    "sg:phone":"+44 1661 825040",
    "sg:postcode":"NE20 9DB",
    "sg:province":"Northumberland",
    "wof:name":"The Aviator Beefeater Restaurant Pub & Travel Inn",
    "wof:placetype":"venue"
},
  "geometry": {"coordinates":[-1.739671,55.049992],"type":"Point"}
}