{
  "type": "Feature",
  "properties": {
    "iso:country":"GB",
    "sg:address":"6 Langborough Road",
    "sg:city":"Wokingham",
    "sg:classifiers":[
        {
            "category":"Social Services",
            "type":"Services"
        }
    ],
    "sg:phone":"+44 118 979 3008",
    "sg:postcode":"RG40 2BT",
    "sg:province":"Berkshire",
    "wof:name":"Youth Resources Team",
    "wof:placetype":"venue"
},
  "geometry": {"coordinates":[-0.834763,51.407944],"type":"Point"}
}