{
  "type": "Feature",
  "properties": {
    "iso:country":"GB",
    "sg:address":"13 Langton Road",
    "sg:city":"Tunbridge Wells",
    "sg:classifiers":[
        {
            "category":"Manufacturing",
            "subcategory":"Paper Products",
            "type":"Manufacturing & Wholesale Goods"
        }
    ],
    "sg:postcode":"TN4 8XA",
    "sg:province":"Kent",
    "sg:tags":[
        "cardboard"
    ],
    "wof:name":"Easycarton Ltd.",
    "wof:placetype":"venue"
},
  "geometry": {"coordinates":[0.245024994,51.1299514771],"type":"Point"}
}