{
  "type": "Feature",
  "properties": {
    "addr:full":"863 Plymouth Road Slough Berkshire SL1 4LP",
    "addr:housenumber":"863",
    "addr:postcode":"sl1 4lp",
    "addr:street":"Plymouth Road",
    "iso:country":"GB",
    "sg:address":"863 Plymouth Road",
    "sg:city":"Slough",
    "sg:classifiers":[
        {
            "category":"Professional",
            "type":"Services"
        }
    ],
    "sg:phone":"+44 1753 738509",
    "sg:postcode":"SL1 4LP",
    "sg:province":"Berkshire",
    "sg:tags":[
        "control",
        "system"
    ],
    "wof:name":"Relative Technology (U K) Ltd.",
    "wof:placetype":"venue"
},
  "geometry": {"coordinates":[-0.6411929727,51.5255661011],"type":"Point"}
}