{
  "type": "Feature",
  "properties": {
    "addr:full":"128 Ellingham Industrial Estate, Ellingham Way Ashford Kent TN23 6LZ",
    "addr:housenumber":"128;estate",
    "addr:postcode":"tn23 6lz",
    "addr:street":"Ellingham Industrial;Ellingham Way",
    "iso:country":"GB",
    "sg:address":"128 Ellingham Industrial Estate, Ellingham Way",
    "sg:city":"Ashford",
    "sg:classifiers":[
        {
            "category":"Autos & Motor Vehicles",
            "subcategory":"Auto Supplies",
            "type":"Retail Goods"
        }
    ],
    "sg:phone":"+44 1233 638393",
    "sg:postcode":"TN23 6LZ",
    "sg:province":"Kent",
    "sg:tags":[
        "electric"
    ],
    "wof:name":"1st Rewinds",
    "wof:placetype":"venue"
},
  "geometry": {"coordinates":[0.8760370016,51.1466331482],"type":"Point"}
}