{
  "type": "Feature",
  "properties": {
    "addr:full":"Bunhill Row London Greater London EC1Y 8LQ",
    "addr:postcode":"ec1y 8lq",
    "addr:street":"Bunhill Row",
    "iso:country":"GB",
    "sg:address":"Bunhill Row",
    "sg:city":"London",
    "sg:classifiers":[
        {
            "category":"Professional",
            "subcategory":"Employment Agencies",
            "type":"Services"
        }
    ],
    "sg:postcode":"EC1Y 8LQ",
    "sg:province":"Greater London",
    "sg:tags":[
        "career",
        "guidance"
    ],
    "wof:name":"Enterprise Careers Services",
    "wof:placetype":"venue"
},
  "geometry": {"coordinates":[-0.089789,51.52282],"type":"Point"}
}