{
  "type": "Feature",
  "properties": {
    "addr:full":"26 Hatton Gardens London Greater London EC1N 8BR",
    "addr:housenumber":"26",
    "addr:postcode":"ec1n 8br",
    "addr:street":"Hatton Gardens",
    "iso:country":"GB",
    "sg:address":"26 Hatton Gardens",
    "sg:city":"London",
    "sg:classifiers":[
        {
            "category":"Building & Trades",
            "subcategory":"Equipment Rental",
            "type":"Services"
        }
    ],
    "sg:phone":"+44 20 7242 6093",
    "sg:postcode":"EC1N 8BR",
    "sg:province":"Greater London",
    "sg:tags":[
        "supply"
    ],
    "wof:name":"Prizelook Ltd.",
    "wof:placetype":"venue"
},
  "geometry": {"coordinates":[-0.108175002,51.5214805603],"type":"Point"}
}