{
  "type": "Feature",
  "properties": {
    "addr:full":"84 Coombe Road New Malden Surrey KT3 4QS",
    "addr:housenumber":"84",
    "addr:postcode":"kt3 4qs",
    "addr:street":"Coombe Road",
    "iso:country":"GB",
    "sg:address":"84 Coombe Road",
    "sg:city":"New Malden",
    "sg:classifiers":[
        {
            "category":"Shopping",
            "subcategory":"Computers & Home Electronics",
            "type":"Retail Goods"
        },
        {
            "category":"Professional",
            "subcategory":"Computer Services",
            "type":"Services"
        }
    ],
    "sg:phone":"+44 20 8336 8800",
    "sg:postcode":"KT3 4QS",
    "sg:province":"Surrey",
    "sg:tags":[
        "software",
        "sales",
        "system"
    ],
    "wof:name":"Cognition Solutions plc",
    "wof:placetype":"venue"
},
  "geometry": {"coordinates":[-0.2581399977,51.4070739746],"type":"Point"}
}