{
  "type": "Feature",
  "properties": {
    "addr:full":"Blackburn Road, Wheelton Chorley Lancashire PR6 8EY",
    "addr:postcode":"pr6 8ey",
    "addr:street":"Blackburn Road",
    "iso:country":"GB",
    "sg:address":"Blackburn Road, Wheelton",
    "sg:city":"Chorley",
    "sg:classifiers":[
        {
            "category":"Personal",
            "subcategory":"Beauty Salon",
            "type":"Services"
        }
    ],
    "sg:phone":"+44 1254 832308",
    "sg:postcode":"PR6 8EY",
    "sg:province":"Lancashire",
    "sg:tags":[
        "unisex",
        "hairdresser"
    ],
    "wof:name":"The Cutting Corner",
    "wof:placetype":"venue"
},
  "geometry": {"coordinates":[-2.6162331104,53.677696228],"type":"Point"}
}