{
  "type": "Feature",
  "properties": {
    "iso:country":"GB",
    "sg:address":"8 Houndsfield Road",
    "sg:city":"London",
    "sg:classifiers":[
        {
            "category":"Organizations",
            "subcategory":"Non-profit Organization",
            "type":"Services"
        }
    ],
    "sg:phone":"+44 20 8805 0865",
    "sg:postcode":"N9 7RA",
    "sg:province":"Greater London",
    "sg:tags":[
        "organisation",
        "voluntary",
        "charity"
    ],
    "wof:name":"British Red Cross",
    "wof:placetype":"venue"
},
  "geometry": {"coordinates":[-0.055708,51.633438],"type":"Point"}
}