{
  "type": "Feature",
  "properties": {
    "addr:full":"High House, Farm Lane, Colton Norwich Norfolk NR9 5DG",
    "addr:postcode":"nr9 5dg",
    "addr:street":"High House Farm Lane;Norwich Norfolk",
    "iso:country":"GB",
    "sg:address":"High House, Farm Lane, Colton",
    "sg:city":"Norwich",
    "sg:classifiers":[
        {
            "category":"Bars & Pubs",
            "type":"Food & Drink"
        }
    ],
    "sg:postcode":"NR9 5DG",
    "sg:province":"Norfolk",
    "sg:tags":[
        "pubs",
        "inn"
    ],
    "wof:name":"Ugly Bug Inn",
    "wof:placetype":"venue"
},
  "geometry": {"coordinates":[1.1162589788,52.6449127197],"type":"Point"}
}