{
  "type": "Feature",
  "properties": {
    "iso:country":"GB",
    "sg:address":"2-4 Effingham Street",
    "sg:city":"Rotherham",
    "sg:classifiers":[
        {
            "category":"Shopping",
            "subcategory":"Optician",
            "type":"Retail Goods"
        }
    ],
    "sg:phone":"+44 1709 830906",
    "sg:postcode":"S65 1AJ",
    "sg:province":"South Yorkshire",
    "wof:name":"Vision Express (U K) Ltd.",
    "wof:placetype":"venue"
},
  "geometry": {"coordinates":[-1.354069,53.434971],"type":"Point"}
}