{
  "type": "Feature",
  "properties": {
    "addr:full":"27 Lawson Terrace Durham Durham DH1 4EW",
    "addr:housenumber":"27",
    "addr:postcode":"dh1 4ew",
    "addr:street":"Lawson Terrace",
    "iso:country":"GB",
    "sg:address":"27 Lawson Terrace",
    "sg:city":"Durham",
    "sg:classifiers":[
        {
            "category":"Shopping",
            "subcategory":"Musical Instruments",
            "type":"Retail Goods"
        }
    ],
    "sg:postcode":"DH1 4EW",
    "sg:province":"Durham",
    "wof:name":"H E Prested Organ Builder",
    "wof:placetype":"venue"
},
  "geometry": {"coordinates":[-1.5875860453,54.7755622864],"type":"Point"}
}