{
  "type": "Feature",
  "properties": {
    "iso:country":"GB",
    "sg:address":"28 Auchmill Rd",
    "sg:city":"Aberdeen",
    "sg:classifiers":[
        {
            "category":"Fast Food",
            "type":"Food & Drink"
        }
    ],
    "sg:phone":"+44 1224 712710",
    "sg:postcode":"AB21 9LD",
    "sg:province":"Aberdeen City",
    "sg:tags":[
        "delivery"
    ],
    "wof:name":"Dragon Peking",
    "wof:placetype":"venue"
},
  "geometry": {"coordinates":[-2.18595,57.18029],"type":"Point"}
}