{
  "type": "Feature",
  "properties": {
    "iso:country":"GB",
    "sg:address":"Unit 4, Cabinet Way, Eastwood",
    "sg:city":"Leigh-on-sea",
    "sg:classifiers":[
        {
            "category":"Home & Garden",
            "subcategory":"Building Materials",
            "type":"Retail Goods"
        }
    ],
    "sg:postcode":"SS9 5LP",
    "sg:province":"Essex",
    "sg:tags":[
        "veneer"
    ],
    "wof:name":"Griffiths & Hood Ltd.",
    "wof:placetype":"venue"
},
  "geometry": {"coordinates":[0.644421,51.568649],"type":"Point"}
}