{
  "type": "Feature",
  "properties": {
    "addr:full":"21 Hope Street, Hanley Stoke-on-trent Staffordshire ST1 5BT",
    "addr:housenumber":"21",
    "addr:postcode":"staffordshire st1 5bt",
    "addr:street":"Hope Street",
    "iso:country":"GB",
    "sg:address":"21 Hope Street, Hanley",
    "sg:city":"Stoke-on-trent",
    "sg:classifiers":[
        {
            "category":"Shopping",
            "subcategory":"Musical Instruments",
            "type":"Retail Goods"
        }
    ],
    "sg:postcode":"ST1 5BT",
    "sg:province":"Staffordshire",
    "sg:tags":[
        "music",
        "sheet"
    ],
    "wof:name":"R & B Music",
    "wof:placetype":"venue"
},
  "geometry": {"coordinates":[-2.17811203,53.0277671814],"type":"Point"}
}