{
  "type": "Feature",
  "properties": {
    "addr:full":"1 Cumnor Rd Oxford Oxfordshire OX2 9NS",
    "addr:housenumber":"1",
    "addr:postcode":"ox2 9ns",
    "addr:street":"Cumnor Rd",
    "iso:country":"GB",
    "sg:address":"1 Cumnor Rd",
    "sg:city":"Oxford",
    "sg:classifiers":[
        {
            "category":"Shopping",
            "subcategory":"Florist",
            "type":"Retail Goods"
        }
    ],
    "sg:phone":"+44 1865 862735",
    "sg:postcode":"OX2 9NS",
    "sg:province":"Oxfordshire",
    "wof:name":"Eileen M Simmonds",
    "wof:placetype":"venue"
},
  "geometry": {"coordinates":[-1.347704,51.759197],"type":"Point"}
}