{
  "type": "Feature",
  "properties": {
    "addr:full":"Duffield Rd Derby Derbyshire DE22 1AJ",
    "addr:postcode":"de22 1aj",
    "addr:street":"Duffield Rd",
    "iso:country":"GB",
    "sg:address":"Duffield Rd",
    "sg:city":"Derby",
    "sg:classifiers":[
        {
            "category":"Community Center",
            "type":"Public Place"
        }
    ],
    "sg:phone":"+44 1332 331396",
    "sg:postcode":"DE22 1AJ",
    "sg:province":"Derbyshire",
    "sg:tags":[
        "nursery",
        "centre"
    ],
    "wof:name":"Norfolk Gardens",
    "wof:placetype":"venue"
},
  "geometry": {"coordinates":[-1.483831048,52.9376716614],"type":"Point"}
}