{
  "type": "Feature",
  "properties": {
    "iso:country":"GB",
    "sg:address":"Ollershaw Lane, Wincham",
    "sg:city":"Northwich",
    "sg:classifiers":[
        {
            "category":"Building & Trades",
            "subcategory":"Construction",
            "type":"Services"
        }
    ],
    "sg:phone":"+44 1606 45405",
    "sg:postcode":"CW9 6ES",
    "sg:province":"Cheshire",
    "sg:tags":[
        "welder"
    ],
    "wof:name":"Ellis Welding Ltd.",
    "wof:placetype":"venue"
},
  "geometry": {"coordinates":[-2.4929640293,53.2859458923],"type":"Point"}
}