{
  "type": "Feature",
  "properties": {
    "iso:country":"GB",
    "sg:address":"41 High West Street",
    "sg:city":"Dorchester",
    "sg:classifiers":[
        {
            "category":"Real Estate",
            "subcategory":"Surveying",
            "type":"Services"
        }
    ],
    "sg:postcode":"DT1 1UT",
    "sg:province":"Dorset",
    "sg:tags":[
        "surveyor",
        "quantity"
    ],
    "wof:name":"Croot & Partners",
    "wof:placetype":"venue"
},
  "geometry": {"coordinates":[-2.4415,50.714924],"type":"Point"}
}