{
  "type": "Feature",
  "properties": {
    "addr:full":"Ormerod School, Waynslete Road Oxford Oxfordshire OX3 8DD",
    "addr:postcode":"ox3 8dd",
    "addr:street":"Waynslete Road",
    "iso:country":"GB",
    "sg:address":"Ormerod School, Waynslete Road",
    "sg:city":"Oxford",
    "sg:classifiers":[
        {
            "category":"Social Services",
            "type":"Services"
        }
    ],
    "sg:phone":"+44 1865 764952",
    "sg:postcode":"OX3 8DD",
    "sg:province":"Oxfordshire",
    "wof:name":"The Roundabout Centre",
    "wof:placetype":"venue"
},
  "geometry": {"coordinates":[-1.1895099878,51.7630805969],"type":"Point"}
}