{
  "type": "Feature",
  "properties": {
    "addr:full":"72 Brentwood Road Romford Essex RM1 2EP",
    "addr:housenumber":"72",
    "addr:postcode":"rm1 2ep",
    "addr:street":"Brentwood Road",
    "iso:country":"GB",
    "sg:address":"72 Brentwood Road",
    "sg:city":"Romford",
    "sg:classifiers":[
        {
            "category":"Retail",
            "subcategory":"Auto Repair",
            "type":"Services"
        }
    ],
    "sg:postcode":"RM1 2EP",
    "sg:province":"Essex",
    "sg:tags":[
        "modification",
        "garage"
    ],
    "wof:name":"A & S Autos",
    "wof:placetype":"venue"
},
  "geometry": {"coordinates":[0.190248996,51.5719947815],"type":"Point"}
}