{
  "type": "Feature",
  "properties": {
    "addr:full":"5 Cabot Dr, Grange Pk Swindon Wiltshire SN5 6HG",
    "addr:housenumber":"5",
    "addr:postcode":"sn5 6hg",
    "addr:street":"Cabot Dr;Pk Swindon",
    "iso:country":"GB",
    "sg:address":"5 Cabot Dr, Grange Pk",
    "sg:city":"Swindon",
    "sg:classifiers":[
        {
            "category":"Professional",
            "subcategory":"Employment Agencies",
            "type":"Services"
        }
    ],
    "sg:postcode":"SN5 6HG",
    "sg:province":"Wiltshire",
    "sg:tags":[
        "introduction"
    ],
    "wof:name":"Titmus,Mike,",
    "wof:placetype":"venue"
},
  "geometry": {"coordinates":[-1.8446700573,51.5599365234],"type":"Point"}
}