{
  "type": "Feature",
  "properties": {
    "addr:full":"29 Moir Cres Aberdeen Aberdeen City AB16 7DB",
    "addr:housenumber":"29",
    "addr:postcode":"ab16 7db",
    "addr:street":"Moir Cres",
    "iso:country":"GB",
    "sg:address":"29 Moir Cres",
    "sg:city":"Aberdeen",
    "sg:classifiers":[
        {
            "category":"Food & Beverages",
            "subcategory":"Meat & Fish",
            "type":"Retail Goods"
        }
    ],
    "sg:phone":"+44 1224 681095",
    "sg:postcode":"AB16 7DB",
    "sg:province":"Aberdeen City",
    "sg:tags":[
        "butcher"
    ],
    "wof:name":"Spenlin (Catering Supplies) Ltd",
    "wof:placetype":"venue"
},
  "geometry": {"coordinates":[-2.144645,57.164337],"type":"Point"}
}