{
  "type": "Feature",
  "properties": {
    "addr:full":"3 Montrose Place, Dronfield Woodhouse Dronfield Derbyshire S18 8ZZ",
    "addr:housenumber":"3",
    "addr:postcode":"s18 8zz",
    "addr:street":"Montrose Place",
    "iso:country":"GB",
    "sg:address":"3 Montrose Place, Dronfield Woodhouse",
    "sg:city":"Dronfield",
    "sg:classifiers":[
        {
            "category":"Retail",
            "subcategory":"Auto Rental",
            "type":"Services"
        }
    ],
    "sg:phone":"+44 1246 411704",
    "sg:postcode":"S18 8ZZ",
    "sg:province":"Derbyshire",
    "sg:tags":[
        "truck",
        "hire",
        "van"
    ],
    "wof:name":"Apple van Hire",
    "wof:placetype":"venue"
},
  "geometry": {"coordinates":[-1.49294,53.302608],"type":"Point"}
}