{
  "type": "Feature",
  "properties": {
    "addr:full":"508 Coach Road Estate Washington Tyne and Wear NE37 2HN",
    "addr:housenumber":"508",
    "addr:postcode":"ne37 2hn",
    "addr:street":"Coach Road Estate",
    "iso:country":"GB",
    "sg:address":"508 Coach Road Estate",
    "sg:city":"Washington",
    "sg:classifiers":[
        {
            "category":"Building & Trades",
            "subcategory":"Construction",
            "type":"Services"
        }
    ],
    "sg:postcode":"NE37 2HN",
    "sg:province":"Tyne and Wear",
    "sg:tags":[
        "joiner",
        "carpenter"
    ],
    "wof:name":"Jeff's Joinery",
    "wof:placetype":"venue"
},
  "geometry": {"coordinates":[-1.526698947,54.9205665588],"type":"Point"}
}