{
  "type": "Feature",
  "properties": {
    "addr:full":"St Andrews House, 59 St Andrews Street Cambridge Cambridgeshire CB2 3DD",
    "addr:housenumber":"59",
    "addr:postcode":"cb2 3dd",
    "addr:street":"St Andrews Street",
    "iso:country":"GB",
    "sg:address":"St Andrews House, 59 St Andrews Street",
    "sg:city":"Cambridge",
    "sg:classifiers":[
        {
            "category":"Professional",
            "subcategory":"Lawyer & Legal Services",
            "type":"Services"
        }
    ],
    "sg:phone":"+44 1223 365432",
    "sg:postcode":"CB2 3DD",
    "sg:province":"Cambridgeshire",
    "sg:tags":[
        "solicitor"
    ],
    "wof:name":"King & Co. Solicitors",
    "wof:placetype":"venue"
},
  "geometry": {"coordinates":[0.122799,52.204575],"type":"Point"}
}