{
  "type": "Feature",
  "properties": {
    "iso:country":"GB",
    "sg:address":"41 Washington Street",
    "sg:city":"Workington",
    "sg:classifiers":[
        {
            "category":"Building & Trades",
            "subcategory":"Construction",
            "type":"Services"
        }
    ],
    "sg:postcode":"CA14 3AR",
    "sg:province":"Cumbria",
    "sg:tags":[
        "joiner",
        "carpenter"
    ],
    "wof:name":"Millwood Joinery  &  Building Ltd",
    "wof:placetype":"venue"
},
  "geometry": {"coordinates":[-3.543308,54.642151],"type":"Point"}
}