{
  "type": "Feature",
  "properties": {
    "addr:full":"32 Melbourne Place Sunderland Tyne and Wear SR4 8LN",
    "addr:housenumber":"32",
    "addr:postcode":"sr4 8ln",
    "addr:street":"Melbourne Place",
    "iso:country":"GB",
    "sg:address":"32 Melbourne Place",
    "sg:city":"Sunderland",
    "sg:classifiers":[
        {
            "category":"Personal",
            "subcategory":"Beauty Salon",
            "type":"Services"
        }
    ],
    "sg:postcode":"SR4 8LN",
    "sg:province":"Tyne and Wear",
    "sg:tags":[
        "unisex",
        "hairdresser"
    ],
    "wof:name":"Barnes View Hair Fashions",
    "wof:placetype":"venue"
},
  "geometry": {"coordinates":[-1.4240679741,54.8957061768],"type":"Point"}
}