{
  "type": "Feature",
  "properties": {
    "addr:full":"22 Wargrave Road Newton-le-willows Cheshire WA12 9QZ",
    "addr:housenumber":"22",
    "addr:postcode":"wa12 9qz",
    "addr:street":"Wargrave Road",
    "iso:country":"GB",
    "sg:address":"22 Wargrave Road",
    "sg:city":"Newton-le-willows",
    "sg:classifiers":[
        {
            "category":"Professional",
            "subcategory":"Printing & Photocopies",
            "type":"Services"
        }
    ],
    "sg:phone":"+44 1925 221504",
    "sg:postcode":"WA12 9QZ",
    "sg:province":"Cheshire",
    "sg:tags":[
        "printer"
    ],
    "wof:name":"Acorn Print",
    "wof:placetype":"venue"
},
  "geometry": {"coordinates":[-2.6355209351,53.4518623352],"type":"Point"}
}