{
  "type": "Feature",
  "properties": {
    "iso:country":"GB",
    "sg:address":"The Flookery, Hothfield Common",
    "sg:city":"Ashford",
    "sg:classifiers":[
        {
            "category":"Home & Garden",
            "subcategory":"Building Materials",
            "type":"Retail Goods"
        }
    ],
    "sg:postcode":"TN26 1HD",
    "sg:province":"Kent",
    "sg:tags":[
        "fencing"
    ],
    "wof:name":"Roger James Fencing",
    "wof:placetype":"venue"
},
  "geometry": {"coordinates":[0.8182250261,51.1729507446],"type":"Point"}
}