{
  "type": "Feature",
  "properties": {
    "addr:full":"20 Royce Road Works, Eastern Industry Peterborough Cambridgeshire PE1 5YB",
    "addr:housenumber":"20",
    "addr:postcode":"pe1 5yb",
    "addr:street":"Royce Road;Eastern",
    "iso:country":"GB",
    "sg:address":"20 Royce Road Works, Eastern Industry",
    "sg:city":"Peterborough",
    "sg:classifiers":[
        {
            "category":"Manufacturing",
            "subcategory":"Metals",
            "type":"Manufacturing & Wholesale Goods"
        }
    ],
    "sg:phone":"+44 1733 558989",
    "sg:postcode":"PE1 5YB",
    "sg:province":"Cambridgeshire",
    "sg:tags":[
        "steel",
        "fabricator",
        "erectors"
    ],
    "wof:name":"N Class Fabrication & Installation",
    "wof:placetype":"venue"
},
  "geometry": {"coordinates":[-0.2196190059,52.579120636],"type":"Point"}
}