{
  "type": "Feature",
  "properties": {
    "iso:country":"GB",
    "sg:address":"Unit 11, Airlink, Inchinnan Road",
    "sg:city":"Paisley",
    "sg:classifiers":[
        {
            "category":"Freight",
            "type":"Transportation"
        },
        {
            "category":"Real Estate",
            "subcategory":"Real Estate Agent",
            "type":"Services"
        },
        {
            "category":"Government",
            "subcategory":"Post Office",
            "type":"Public Place"
        }
    ],
    "sg:phone":"+44 800 626849",
    "sg:postcode":"PA3 2RS",
    "sg:province":"Renfrewshire",
    "sg:tags":[
        "cargo",
        "ship",
        "handling",
        "messenger",
        "courier"
    ],
    "wof:name":"Ecosse World Express Ltd.",
    "wof:placetype":"venue"
},
  "geometry": {"coordinates":[-4.4300341606,55.8581809998],"type":"Point"}
}