{
  "type": "Feature",
  "properties": {
    "iso:country":"GB",
    "sg:address":"Unit 1 West Line Industrial Estate",
    "sg:city":"Washington",
    "sg:classifiers":[
        {
            "category":"Professional",
            "subcategory":"Engineering",
            "type":"Services"
        },
        {
            "category":"Building & Trades",
            "subcategory":"Construction",
            "type":"Services"
        }
    ],
    "sg:phone":"+44 191 492 2666",
    "sg:postcode":"NE38 8QD",
    "sg:province":"Durham",
    "sg:tags":[
        "fork",
        "lift",
        "truck"
    ],
    "wof:name":"Justproof Ltd.",
    "wof:placetype":"venue"
},
  "geometry": {"coordinates":[-1.506431,54.899311],"type":"Point"}
}