{
  "type": "Feature",
  "properties": {
    "addr:full":"4 Ardern Walk Stockport Cheshire SK1 1PT",
    "addr:housenumber":"4",
    "addr:postcode":"sk1 1pt",
    "addr:street":"Ardern Walk",
    "iso:country":"GB",
    "sg:address":"4 Ardern Walk",
    "sg:city":"Stockport",
    "sg:classifiers":[
        {
            "category":"Food & Beverages",
            "subcategory":"Supermarket",
            "type":"Retail Goods"
        }
    ],
    "sg:phone":"+44 161 480 2912",
    "sg:postcode":"SK1 1PT",
    "sg:province":"Cheshire",
    "wof:name":"Tesco Stores Ltd.",
    "wof:placetype":"venue"
},
  "geometry": {"coordinates":[-2.1618840694,53.4109115601],"type":"Point"}
}