{
  "type": "Feature",
  "properties": {
    "iso:country":"GB",
    "sg:address":"136 Bradford Street",
    "sg:city":"Braintree",
    "sg:classifiers":[
        {
            "category":"Professional",
            "subcategory":"Engineering",
            "type":"Services"
        }
    ],
    "sg:postcode":"CM7 9AU",
    "sg:province":"Essex",
    "sg:tags":[
        "contractor",
        "electrical",
        "engineer"
    ],
    "wof:name":"John Hancock",
    "wof:placetype":"venue"
},
  "geometry": {"coordinates":[0.55652,51.886971],"type":"Point"}
}