{
  "type": "Feature",
  "properties": {
    "iso:country":"GB",
    "sg:address":"16 Terrace Road",
    "sg:city":"Walton-on-thames",
    "sg:classifiers":[
        {
            "category":"Health Services",
            "subcategory":"Podiatrist",
            "type":"Services"
        }
    ],
    "sg:phone":"+44 1932 226749",
    "sg:postcode":"KT12 2SB",
    "sg:province":"Surrey",
    "sg:tags":[
        "podiatrists",
        "chiropodist"
    ],
    "wof:name":"Blampied & St Hill",
    "wof:placetype":"venue"
},
  "geometry": {"coordinates":[-0.4151239991,51.3894958496],"type":"Point"}
}