{
  "type": "Feature",
  "properties": {
    "addr:full":"The Broadway Huntingdon Cambridgeshire PE17 4BB",
    "addr:postcode":"pe17 4bb",
    "addr:street":"The Broadway",
    "iso:country":"GB",
    "sg:address":"The Broadway",
    "sg:city":"Huntingdon",
    "sg:classifiers":[
        {
            "category":"Recreation",
            "type":"Entertainment"
        }
    ],
    "sg:phone":"+44 1480 466199",
    "sg:postcode":"PE17 4BB",
    "sg:province":"Cambridgeshire",
    "sg:tags":[
        "snooker",
        "billiards",
        "pool"
    ],
    "wof:name":"Binz's",
    "wof:placetype":"venue"
},
  "geometry": {"coordinates":[-0.1893,52.33514],"type":"Point"}
}