{
  "type": "Feature",
  "properties": {
    "addr:full":"Alexandra Road Mablethorpe Lincolnshire LN12 1BJ",
    "addr:postcode":"ln12 1bj",
    "addr:street":"Alexandra Road",
    "iso:country":"GB",
    "sg:address":"Alexandra Road",
    "sg:city":"Mablethorpe",
    "sg:classifiers":[
        {
            "category":"Autos & Motor Vehicles",
            "subcategory":"Auto Supplies",
            "type":"Retail Goods"
        }
    ],
    "sg:phone":"+44 1507 477177",
    "sg:postcode":"LN12 1BJ",
    "sg:province":"Lincolnshire",
    "sg:tags":[
        "component"
    ],
    "wof:name":"Keetch Factors (1984) Ltd.",
    "wof:placetype":"venue"
},
  "geometry": {"coordinates":[0.256137,53.341339],"type":"Point"}
}