{
  "type": "Feature",
  "properties": {
    "iso:country":"GB",
    "sg:address":"Stourport Road",
    "sg:city":"Kidderminster",
    "sg:classifiers":[
        {
            "category":"Professional",
            "type":"Services"
        },
        {
            "category":"Retail",
            "subcategory":"Auto Rental",
            "type":"Services"
        },
        {
            "category":"Real Estate",
            "subcategory":"Real Estate Services",
            "type":"Services"
        }
    ],
    "sg:phone":"+44 1562 862626",
    "sg:postcode":"DY11 7QL",
    "sg:province":"Staffordshire",
    "sg:tags":[
        "truck",
        "hire",
        "van",
        "caravan",
        "plant",
        "towing",
        "car",
        "leasing",
        "transport"
    ],
    "wof:name":"FOLEY SELF DRIVE LTD",
    "wof:placetype":"venue"
},
  "geometry": {"coordinates":[-2.262434,52.370884],"type":"Point"}
}