{
  "type": "Feature",
  "properties": {
    "iso:country":"GB",
    "sg:address":"16 Main St",
    "sg:city":"Buckingham",
    "sg:classifiers":[
        {
            "category":"Shopping",
            "subcategory":"Bicycles & Sporting Goods",
            "type":"Retail Goods"
        }
    ],
    "sg:phone":"+44 1280 847209",
    "sg:postcode":"MK18 4NN",
    "sg:province":"Buckinghamshire",
    "sg:tags":[
        "cycle",
        "accessory"
    ],
    "wof:name":"The Bike Inn",
    "wof:placetype":"venue"
},
  "geometry": {"coordinates":[-1.0434969664,51.9905586243],"type":"Point"}
}