{
  "type": "Feature",
  "properties": {
    "addr:full":"Central Ho, Upper Woburn Pl London Greater London WC1H 0QA",
    "addr:postcode":"wc1h 0qa",
    "addr:street":"Upper Woburn Pl",
    "iso:country":"GB",
    "sg:address":"Central Ho, Upper Woburn Pl",
    "sg:city":"London",
    "sg:classifiers":[
        {
            "category":"Banks & Credit Unions",
            "subcategory":"Bank",
            "type":"Services"
        }
    ],
    "sg:postcode":"WC1H 0QA",
    "sg:province":"Greater London",
    "sg:tags":[
        "broker",
        "mortgage"
    ],
    "wof:name":"A & B Associated Lenders Ltd",
    "wof:placetype":"venue"
},
  "geometry": {"coordinates":[-0.1294240057,51.526134491],"type":"Point"}
}