{
  "type": "Feature",
  "properties": {
    "addr:full":"7 Queen Avenue, Dale Street, Castle Street Liverpool Merseyside L2 4TZ",
    "addr:housenumber":"7",
    "addr:postcode":"l2 4tz",
    "addr:street":"Queen Avenue Dale Street Castle Street",
    "iso:country":"GB",
    "sg:address":"7 Queen Avenue, Dale Street, Castle Street",
    "sg:city":"Liverpool",
    "sg:classifiers":[
        {
            "category":"Professional",
            "subcategory":"Lawyer & Legal Services",
            "type":"Services"
        }
    ],
    "sg:phone":"+44 151 227 2555",
    "sg:postcode":"L2 4TZ",
    "sg:province":"Merseyside",
    "sg:tags":[
        "solicitor"
    ],
    "wof:name":"Robinsons",
    "wof:placetype":"venue"
},
  "geometry": {"coordinates":[-2.9901540279,53.4068717957],"type":"Point"}
}