{
  "type": "Feature",
  "properties": {
    "addr:full":"20 Langford Cres Benfleet Essex SS7 3JP",
    "addr:housenumber":"20",
    "addr:postcode":"ss7 3jp",
    "addr:street":"Langford Cres Benfleet",
    "iso:country":"GB",
    "sg:address":"20 Langford Cres",
    "sg:city":"Benfleet",
    "sg:classifiers":[
        {
            "category":"Building & Trades",
            "subcategory":"Construction",
            "type":"Services"
        }
    ],
    "sg:phone":"+44 1268 793614",
    "sg:postcode":"SS7 3JP",
    "sg:province":"Essex",
    "sg:tags":[
        "builder"
    ],
    "wof:name":"A D Selley & Sons",
    "wof:placetype":"venue"
},
  "geometry": {"coordinates":[0.5773169994,51.5709495544],"type":"Point"}
}