{
  "type": "Feature",
  "properties": {
    "addr:full":"3 Madleaze Trading Estate, Bristol Road Gloucester Gloucestershire GL1 5SG",
    "addr:housenumber":"3",
    "addr:postcode":"gl1 5sg",
    "addr:street":"Trading;Bristol Road",
    "iso:country":"GB",
    "sg:address":"3 Madleaze Trading Estate, Bristol Road",
    "sg:city":"Gloucester",
    "sg:classifiers":[
        {
            "category":"Building & Trades",
            "subcategory":"Construction",
            "type":"Services"
        }
    ],
    "sg:phone":"+44 1452 502163",
    "sg:postcode":"GL1 5SG",
    "sg:province":"Gloucestershire",
    "sg:tags":[
        "joinery"
    ],
    "wof:name":"Dale Joinery (Redbourne Division)",
    "wof:placetype":"venue"
},
  "geometry": {"coordinates":[-2.249624,51.863811],"type":"Point"}
}