{
  "type": "Feature",
  "properties": {
    "addr:full":"Bridge Studios, Eastgate Street Gloucester Gloucestershire GL1 1SS",
    "addr:postcode":"gl1 1ss",
    "addr:street":"Eastgate Street",
    "iso:country":"GB",
    "sg:address":"Bridge Studios, Eastgate Street",
    "sg:city":"Gloucester",
    "sg:classifiers":[
        {
            "category":"Communications",
            "subcategory":"Film & Video Production",
            "type":"Services"
        }
    ],
    "sg:phone":"+44 1452 313200",
    "sg:postcode":"GL1 1SS",
    "sg:province":"Gloucestershire",
    "sg:tags":[
        "tv",
        "radio"
    ],
    "wof:name":"Gloucestershire Broadcasting Plc",
    "wof:placetype":"venue"
},
  "geometry": {"coordinates":[-2.2496240139,51.8638114929],"type":"Point"}
}