{
  "type": "Feature",
  "properties": {
    "addr:full":"13 Stratford Place, West 1 West End Hampshire W1N 9AF",
    "addr:housenumber":"13;1",
    "addr:postcode":"w1n 9af",
    "addr:street":"Stratford Place West;West End",
    "iso:country":"GB",
    "sg:address":"13 Stratford Place, West 1",
    "sg:city":"West End",
    "sg:classifiers":[
        {
            "category":"Professional",
            "subcategory":"Lawyer & Legal Services",
            "type":"Services"
        }
    ],
    "sg:phone":"+44 20 7355 4441",
    "sg:postcode":"W1N 9AF",
    "sg:province":"Hampshire",
    "sg:tags":[
        "solicitor"
    ],
    "wof:name":"Matthew Trackman & Co",
    "wof:placetype":"venue"
},
  "geometry": {"coordinates":[-0.13899,51.50758],"type":"Point"}
}