{
  "type": "Feature",
  "properties": {
    "iso:country":"GB",
    "sg:address":"524 King St, Fenton",
    "sg:city":"Stoke On Trent",
    "sg:classifiers":[
        {
            "category":"Shopping",
            "subcategory":"Bicycles & Sporting Goods",
            "type":"Retail Goods"
        }
    ],
    "sg:phone":"+44 1782 596654",
    "sg:postcode":"ST4 2LT",
    "sg:province":"Staffordshire",
    "sg:tags":[
        "riding",
        "saddlery",
        "wear"
    ],
    "wof:name":"Pepstan Saddlery",
    "wof:placetype":"venue"
},
  "geometry": {"coordinates":[-2.16098,52.9981],"type":"Point"}
}