{
  "type": "Feature",
  "properties": {
    "iso:country":"GB",
    "sg:address":"B 6 St Andrew Street",
    "sg:city":"Hertford",
    "sg:classifiers":[
        {
            "category":"Parking",
            "type":"Transportation"
        },
        {
            "category":"Real Estate",
            "subcategory":"Real Estate Services",
            "type":"Services"
        }
    ],
    "sg:phone":"+44 1992 509700",
    "sg:postcode":"SG14 1JA",
    "sg:province":"Hertfordshire",
    "sg:tags":[
        "car",
        "garaging",
        "management",
        "facility"
    ],
    "sg:website":"http://www.townandcityparking.co.uk",
    "wof:name":"Town & City Parking Ltd.",
    "wof:placetype":"venue"
},
  "geometry": {"coordinates":[-0.082699,51.796341],"type":"Point"}
}