{
  "type": "Feature",
  "properties": {
    "addr:full":"20-22 Victoria Rd Dartmouth Devon TQ6 9BE",
    "addr:housenumber":"20-22",
    "addr:postcode":"tq6 9be",
    "addr:street":"Victoria Rd",
    "iso:country":"GB",
    "sg:address":"20-22 Victoria Rd",
    "sg:city":"Dartmouth",
    "sg:classifiers":[
        {
            "category":"Government",
            "subcategory":"Post Office",
            "type":"Public Place"
        }
    ],
    "sg:phone":"+44 1803 832730",
    "sg:postcode":"TQ6 9BE",
    "sg:province":"Devon",
    "wof:name":"Post Office Counters Ltd",
    "wof:placetype":"venue"
},
  "geometry": {"coordinates":[-3.5810439587,50.3511352539],"type":"Point"}
}