{
  "type": "Feature",
  "properties": {
    "addr:full":"122 Station Rd Sidcup Kent DA15 7AB",
    "addr:housenumber":"122",
    "addr:postcode":"da15 7ab",
    "addr:street":"Station Rd",
    "iso:country":"GB",
    "sg:address":"122 Station Rd",
    "sg:city":"Sidcup",
    "sg:classifiers":[
        {
            "category":"Bars & Pubs",
            "type":"Food & Drink"
        }
    ],
    "sg:phone":"+44 20 8300 5540",
    "sg:postcode":"DA15 7AB",
    "sg:province":"Kent",
    "sg:tags":[
        "pubs",
        "inn"
    ],
    "wof:name":"Iron Horse",
    "wof:placetype":"venue"
},
  "geometry": {"coordinates":[0.102579,51.434151],"type":"Point"}
}