{
  "type": "Feature",
  "properties": {
    "addr:full":"Heron Rd, Sowton Indust Est Exeter Devon EX2 7NF",
    "addr:postcode":"ex2 7nf",
    "addr:street":"Heron Rd;Indust Est",
    "iso:country":"GB",
    "sg:address":"Heron Rd, Sowton Indust Est",
    "sg:city":"Exeter",
    "sg:classifiers":[
        {
            "category":"Communications",
            "subcategory":"Newspaper",
            "type":"Services"
        }
    ],
    "sg:phone":"+44 1392 442470",
    "sg:postcode":"EX2 7NF",
    "sg:province":"Devon",
    "sg:tags":[
        "magazine"
    ],
    "wof:name":"T D B",
    "wof:placetype":"venue"
},
  "geometry": {"coordinates":[-3.4736139774,50.722782135],"type":"Point"}
}