{
  "type": "Feature",
  "properties": {
    "addr:full":"104 Wollaton Road Sheffield Derbyshire S17 4LG",
    "addr:housenumber":"104",
    "addr:postcode":"s17 4lg",
    "addr:street":"Wollaton Road",
    "iso:country":"GB",
    "sg:address":"104 Wollaton Road",
    "sg:city":"Sheffield",
    "sg:classifiers":[
        {
            "category":"Professional",
            "subcategory":"Management & Consulting",
            "type":"Services"
        }
    ],
    "sg:phone":"+44 114 236 6434",
    "sg:postcode":"S17 4LG",
    "sg:province":"Derbyshire",
    "sg:tags":[
        "marketing",
        "consultant"
    ],
    "wof:name":"Camus Marketing Consultants Ltd",
    "wof:placetype":"venue"
},
  "geometry": {"coordinates":[-1.5212999582,53.3162536621],"type":"Point"}
}