{
  "type": "Feature",
  "properties": {
    "addr:full":"Caring Lane, Leeds Maidstone Kent ME17 1TJ",
    "addr:postcode":"me17 1tj",
    "addr:street":"Caring Lane",
    "iso:country":"GB",
    "sg:address":"Caring Lane, Leeds",
    "sg:city":"Maidstone",
    "sg:classifiers":[
        {
            "category":"Transit Center",
            "subcategory":"Passenger",
            "type":"Transportation"
        }
    ],
    "sg:phone":"+44 1622 861288",
    "sg:postcode":"ME17 1TJ",
    "sg:province":"Kent",
    "sg:tags":[
        "boarding",
        "kennel",
        "catteries"
    ],
    "wof:name":"Caring for Cats",
    "wof:placetype":"venue"
},
  "geometry": {"coordinates":[0.5928810239,51.2578697205],"type":"Point"}
}