{
  "type": "Feature",
  "properties": {
    "addr:full":"112 Main Rd, Cidcup Sth Bermondsey Greater London SE16 1PR",
    "addr:housenumber":"112",
    "addr:postcode":"se16 1pr",
    "addr:street":"Main Rd;Sth Bermondsey",
    "iso:country":"GB",
    "sg:address":"112 Main Rd, Cidcup",
    "sg:city":"Sth Bermondsey",
    "sg:classifiers":[
        {
            "category":"Professional",
            "subcategory":"Accounting & Tax Preparation",
            "type":"Services"
        }
    ],
    "sg:phone":"+44 20 7252 0653",
    "sg:postcode":"SE16 1PR",
    "sg:province":"Greater London",
    "sg:tags":[
        "accountant"
    ],
    "wof:name":"Dyer & Co",
    "wof:placetype":"venue"
},
  "geometry": {"coordinates":[-0.0532,51.496029],"type":"Point"}
}