{
  "type": "Feature",
  "properties": {
    "iso:country":"GB",
    "sg:address":"110 High Street",
    "sg:city":"Tewkesbury",
    "sg:classifiers":[
        {
            "category":"Shopping",
            "subcategory":"Shoes",
            "type":"Retail Goods"
        }
    ],
    "sg:phone":"+44 1684 292251",
    "sg:postcode":"GL20 5JZ",
    "sg:province":"Gloucestershire",
    "sg:tags":[
        "shop"
    ],
    "wof:name":"Clarkes",
    "wof:placetype":"venue"
},
  "geometry": {"coordinates":[-2.156376,51.994991],"type":"Point"}
}