{
  "type": "Feature",
  "properties": {
    "iso:country":"GB",
    "sg:address":"Unit 33 Riverside Power Station, Road",
    "sg:city":"Rugeley",
    "sg:classifiers":[
        {
            "category":"Building & Trades",
            "subcategory":"Cleaning & Sanitation",
            "type":"Services"
        }
    ],
    "sg:phone":"+44 1889 575618",
    "sg:postcode":"WS15 2YR",
    "sg:province":"Staffordshire",
    "sg:tags":[
        "asbestos",
        "removal"
    ],
    "wof:name":"Pectel Ltd.",
    "wof:placetype":"venue"
},
  "geometry": {"coordinates":[-1.932009,52.765644],"type":"Point"}
}