{
  "type": "Feature",
  "properties": {
    "addr:full":"46a Grahams Rd Falkirk Falkirk FK1 1HR",
    "addr:housenumber":"46a",
    "addr:postcode":"fk1 1hr",
    "addr:street":"Grahams Rd",
    "iso:country":"GB",
    "sg:address":"46a Grahams Rd",
    "sg:city":"Falkirk",
    "sg:classifiers":[
        {
            "category":"Shopping",
            "subcategory":"Florist",
            "type":"Retail Goods"
        }
    ],
    "sg:postcode":"FK1 1HR",
    "sg:province":"Falkirk",
    "wof:name":"Love,David M,",
    "wof:placetype":"venue"
},
  "geometry": {"coordinates":[-3.783905983,56.0038490295],"type":"Point"}
}