{
  "type": "Feature",
  "properties": {
    "iso:country":"GB",
    "sg:address":"Birkdale, Little Common",
    "sg:city":"Bexhill-on-sea",
    "sg:classifiers":[
        {
            "category":"Farming",
            "subcategory":"Nursery",
            "type":"Manufacturing & Wholesale Goods"
        }
    ],
    "sg:phone":"+44 1424 846224",
    "sg:postcode":"TN39 3TY",
    "sg:province":"East Sussex",
    "sg:tags":[
        "creche"
    ],
    "wof:name":"Birkdale Hall Day Nursery",
    "wof:placetype":"venue"
},
  "geometry": {"coordinates":[0.452065,50.846115],"type":"Point"}
}