{
  "type": "Feature",
  "properties": {
    "addr:full":"383 Soundell Road, Kingswood Bristol City of Bristol BS15 1JN",
    "addr:housenumber":"383",
    "addr:postcode":"bs15 1jn",
    "addr:street":"Soundell Road",
    "iso:country":"GB",
    "sg:address":"383 Soundell Road, Kingswood",
    "sg:city":"Bristol",
    "sg:classifiers":[
        {
            "category":"Home & Garden",
            "subcategory":"Household Appliances",
            "type":"Retail Goods"
        }
    ],
    "sg:postcode":"BS15 1JN",
    "sg:province":"City of Bristol",
    "sg:tags":[
        "refrigeration",
        "air conditioning"
    ],
    "wof:name":"Balfour Refrigeration Ltd.",
    "wof:placetype":"venue"
},
  "geometry": {"coordinates":[-2.5131399632,51.4656524658],"type":"Point"}
}