{
  "type": "Feature",
  "properties": {
    "iso:country":"GB",
    "sg:address":"181 Knutsford Road, Grappenhall",
    "sg:city":"Warrington",
    "sg:classifiers":[
        {
            "category":"Organizations",
            "subcategory":"Non-profit Organization",
            "type":"Services"
        }
    ],
    "sg:phone":"+44 1925 600000",
    "sg:postcode":"WA4 2QL",
    "sg:province":"Cheshire",
    "sg:tags":[
        "organisation",
        "animal",
        "welfare"
    ],
    "wof:name":"Eliot's Veterinary Centre",
    "wof:placetype":"venue"
},
  "geometry": {"coordinates":[-2.541933,53.377289],"type":"Point"}
}