{
  "type": "Feature",
  "properties": {
    "addr:full":"157 Boothferry Road Goole East Riding of Yorkshire DN14 6AL",
    "addr:housenumber":"157",
    "addr:postcode":"dn14 6al",
    "addr:street":"Boothferry Road",
    "iso:country":"GB",
    "sg:address":"157 Boothferry Road",
    "sg:city":"Goole",
    "sg:classifiers":[
        {
            "category":"Professional",
            "subcategory":"Lawyer & Legal Services",
            "type":"Services"
        }
    ],
    "sg:phone":"+44 1405 763853",
    "sg:postcode":"DN14 6AL",
    "sg:province":"East Riding of Yorkshire",
    "sg:tags":[
        "solicitor"
    ],
    "wof:name":"Taylor Broomer & Co.",
    "wof:placetype":"venue"
},
  "geometry": {"coordinates":[-0.881718,53.706738],"type":"Point"}
}