{
  "type": "Feature",
  "properties": {
    "addr:full":"Chertsey Road Windlesham Surrey GU20 6HT",
    "addr:postcode":"gu20 6ht",
    "addr:street":"Chertsey Road",
    "iso:country":"GB",
    "sg:address":"Chertsey Road",
    "sg:city":"Windlesham",
    "sg:classifiers":[
        {
            "category":"Restaurant",
            "type":"Food & Drink"
        }
    ],
    "sg:postcode":"GU20 6HT",
    "sg:province":"Surrey",
    "wof:name":"The Brickmakers Arms",
    "wof:placetype":"venue"
},
  "geometry": {"coordinates":[-0.647779,51.368446],"type":"Point"}
}