{
  "type": "Feature",
  "properties": {
    "addr:full":"7 Young Street Doncaster South Yorkshire DN1 3EL",
    "addr:housenumber":"7",
    "addr:postcode":"dn1 3el",
    "addr:street":"Young Street",
    "iso:country":"GB",
    "sg:address":"7 Young Street",
    "sg:city":"Doncaster",
    "sg:classifiers":[
        {
            "category":"Professional",
            "subcategory":"Printing & Photocopies",
            "type":"Services"
        }
    ],
    "sg:postcode":"DN1 3EL",
    "sg:province":"South Yorkshire",
    "sg:tags":[
        "printer"
    ],
    "wof:name":"Kall Kwik Printing",
    "wof:placetype":"venue"
},
  "geometry": {"coordinates":[-1.1328890324,53.5214004517],"type":"Point"}
}