{
  "type": "Feature",
  "properties": {
    "addr:full":"49 Whippendell Way Orpington Kent BR5 3BZ",
    "addr:housenumber":"49",
    "addr:postcode":"br5 3bz",
    "addr:street":"Whippendell Way",
    "iso:country":"GB",
    "sg:address":"49 Whippendell Way",
    "sg:city":"Orpington",
    "sg:classifiers":[
        {
            "category":"Professional",
            "subcategory":"Computer Services",
            "type":"Services"
        }
    ],
    "sg:postcode":"BR5 3BZ",
    "sg:province":"Kent",
    "sg:tags":[
        "system",
        "software"
    ],
    "wof:name":"Versatile It Answers Ltd",
    "wof:placetype":"venue"
},
  "geometry": {"coordinates":[0.106919,51.405575],"type":"Point"}
}