{
  "type": "Feature",
  "properties": {
    "addr:full":"31 Queen Elizabeth Way Woking Surrey GU22 9AG",
    "addr:housenumber":"31",
    "addr:postcode":"gu22 9ag",
    "addr:street":"Queen Elizabeth Way",
    "iso:country":"GB",
    "sg:address":"31 Queen Elizabeth Way",
    "sg:city":"Woking",
    "sg:classifiers":[
        {
            "category":"Professional",
            "subcategory":"Computer Services",
            "type":"Services"
        }
    ],
    "sg:phone":"+44 1483 726990",
    "sg:postcode":"GU22 9AG",
    "sg:province":"Surrey",
    "sg:tags":[
        "system",
        "software"
    ],
    "wof:name":"Trendstore Ltd.",
    "wof:placetype":"venue"
},
  "geometry": {"coordinates":[-0.553524,51.309593],"type":"Point"}
}