{
  "type": "Feature",
  "properties": {
    "addr:full":"Whitton Road Hounslow Greater London TW3 2DB",
    "addr:postcode":"tw3 2db",
    "addr:street":"Whitton Road",
    "iso:country":"GB",
    "sg:address":"Whitton Road",
    "sg:city":"Hounslow",
    "sg:classifiers":[
        {
            "category":"Social Services",
            "subcategory":"Adult Care",
            "type":"Services"
        }
    ],
    "sg:phone":"+44 20 8572 0933",
    "sg:postcode":"TW3 2DB",
    "sg:province":"Greater London",
    "sg:tags":[
        "day",
        "centre"
    ],
    "wof:name":"Hounslow 'London Borough of)",
    "wof:placetype":"venue"
},
  "geometry": {"coordinates":[-0.362704,51.4641],"type":"Point"}
}