{
  "type": "Feature",
  "properties": {
    "iso:country":"GB",
    "sg:address":"Albert Quay",
    "sg:city":"Aberdeen",
    "sg:classifiers":[
        {
            "category":"Utilities",
            "subcategory":"Water",
            "type":"Services"
        }
    ],
    "sg:phone":"+44 1224 592891",
    "sg:postcode":"AB11 5PX",
    "sg:province":"Aberdeen City",
    "sg:tags":[
        "authority"
    ],
    "wof:name":"Shipping Water Depot",
    "wof:placetype":"venue"
},
  "geometry": {"coordinates":[-2.090276,57.142178],"type":"Point"}
}