{
  "type": "Feature",
  "properties": {
    "iso:country":"GB",
    "sg:address":"High Moor Top, Moorside, Cononley",
    "sg:city":"Keighley",
    "sg:classifiers":[
        {
            "category":"Transit Center",
            "subcategory":"Passenger",
            "type":"Transportation"
        },
        {
            "category":"Retail",
            "subcategory":"Pet Boarding",
            "type":"Services"
        }
    ],
    "sg:phone":"+44 1535 633934",
    "sg:postcode":"BD20 8PD",
    "sg:province":"North Yorkshire",
    "sg:tags":[
        "kennel",
        "catteries"
    ],
    "wof:name":"Metadale Kennels & Cattery",
    "wof:placetype":"venue"
},
  "geometry": {"coordinates":[-2.014676,53.918289],"type":"Point"}
}