{
  "type": "Feature",
  "properties": {
    "addr:full":"43 High Street Swanley Kent BR8 8AE",
    "addr:housenumber":"43",
    "addr:postcode":"br8 8ae",
    "addr:street":"High Street",
    "iso:country":"GB",
    "sg:address":"43 High Street",
    "sg:city":"Swanley",
    "sg:classifiers":[
        {
            "category":"Shopping",
            "subcategory":"Clothing, Apparel, & Fashions",
            "type":"Retail Goods"
        }
    ],
    "sg:phone":"+44 1322 613323",
    "sg:postcode":"BR8 8AE",
    "sg:province":"Kent",
    "sg:tags":[
        "shop",
        "dress",
        "fancy"
    ],
    "wof:name":"Cozzies of Swanley",
    "wof:placetype":"venue"
},
  "geometry": {"coordinates":[0.1796109974,51.394367218],"type":"Point"}
}