{
  "type": "Feature",
  "properties": {
    "addr:full":"Dental Surgery, 43 Castle St Banbury Oxfordshire OX16 8NU",
    "addr:housenumber":"43",
    "addr:postcode":"ox16 8nu",
    "addr:street":"Castle St",
    "iso:country":"GB",
    "sg:address":"Dental Surgery, 43 Castle St",
    "sg:city":"Banbury",
    "sg:classifiers":[
        {
            "category":"Health Services",
            "subcategory":"Dentist",
            "type":"Services"
        }
    ],
    "sg:phone":"+44 1295 270792",
    "sg:postcode":"OX16 8NU",
    "sg:province":"Oxfordshire",
    "wof:name":"L J A Black & Associates",
    "wof:placetype":"venue"
},
  "geometry": {"coordinates":[-1.340028,52.061111],"type":"Point"}
}