{
  "type": "Feature",
  "properties": {
    "iso:country":"GB",
    "sg:address":"12 Cedar Road, Thundersley",
    "sg:city":"Benfleet",
    "sg:classifiers":[
        {
            "category":"Building & Trades",
            "subcategory":"Construction",
            "type":"Services"
        }
    ],
    "sg:phone":"+44 1268 735054",
    "sg:postcode":"SS7 3QX",
    "sg:province":"Essex",
    "sg:tags":[
        "roofing"
    ],
    "wof:name":"Leisure Laminates",
    "wof:placetype":"venue"
},
  "geometry": {"coordinates":[0.587105,51.569813],"type":"Point"}
}