{
  "type": "Feature",
  "properties": {
    "iso:country":"GB",
    "sg:address":"Fold Mill, Bradley Lane",
    "sg:city":"Bolton",
    "sg:classifiers":[
        {
            "category":"Recreation",
            "subcategory":"Water Park",
            "type":"Entertainment"
        },
        {
            "category":"Building & Trades",
            "subcategory":"Construction",
            "type":"Services"
        }
    ],
    "sg:phone":"+44 1204 513200",
    "sg:postcode":"BL2 6RR",
    "sg:province":"Lancashire",
    "sg:tags":[
        "shop",
        "mill",
        "upholstery",
        "furniture"
    ],
    "wof:name":"Dorma Sheets Ltd.",
    "wof:placetype":"venue"
},
  "geometry": {"coordinates":[-2.359558,53.573132],"type":"Point"}
}