{
  "type": "Feature",
  "properties": {
    "addr:full":"1 Leylands Road Burgess Hill East Sussex RH15 0QF",
    "addr:housenumber":"1",
    "addr:postcode":"rh15 0qf",
    "addr:street":"Leylands Road",
    "iso:country":"GB",
    "sg:address":"1 Leylands Road",
    "sg:city":"Burgess Hill",
    "sg:classifiers":[
        {
            "category":"Bars & Pubs",
            "type":"Food & Drink"
        }
    ],
    "sg:phone":"+44 1444 235517",
    "sg:postcode":"RH15 0QF",
    "sg:province":"East Sussex",
    "sg:tags":[
        "pubs",
        "house",
        "inn",
        "public",
        "activity"
    ],
    "wof:name":"The Watermill",
    "wof:placetype":"venue"
},
  "geometry": {"coordinates":[-0.1187459975,50.9648666382],"type":"Point"}
}