{
  "type": "Feature",
  "properties": {
    "iso:country":"GB",
    "sg:address":"71-72 Hudson Street",
    "sg:city":"North Shields",
    "sg:classifiers":[
        {
            "category":"Building & Trades",
            "subcategory":"Construction",
            "type":"Services"
        }
    ],
    "sg:phone":"+44 191 257 3330",
    "sg:postcode":"NE30 1DL",
    "sg:province":"Tyne and Wear",
    "sg:tags":[
        "builder"
    ],
    "wof:name":"Robert Amos & Co. Ltd.",
    "wof:placetype":"venue"
},
  "geometry": {"coordinates":[-1.436776,55.010727],"type":"Point"}
}