{
  "type": "Feature",
  "properties": {
    "addr:full":"High Street, Bluntisham Huntingdon Bedfordshire PE28 3LA",
    "addr:postcode":"pe28 3la",
    "addr:street":"High Street",
    "iso:country":"GB",
    "sg:address":"High Street, Bluntisham",
    "sg:city":"Huntingdon",
    "sg:classifiers":[
        {
            "category":"Government",
            "subcategory":"Post Office",
            "type":"Public Place"
        }
    ],
    "sg:postcode":"PE28 3LA",
    "sg:province":"Bedfordshire",
    "wof:name":"D & B Hinstock",
    "wof:placetype":"venue"
},
  "geometry": {"coordinates":[0.0095250001,52.3510818481],"type":"Point"}
}