{
  "type": "Feature",
  "properties": {
    "addr:full":"Unit 5a, High Bank Trading Estate Manchester Greater Manchester M11 2LJ",
    "addr:housenumber":"unit 5a",
    "addr:postcode":"m11 2lj",
    "addr:street":"Trading",
    "iso:country":"GB",
    "sg:address":"Unit 5a, High Bank Trading Estate",
    "sg:city":"Manchester",
    "sg:classifiers":[
        {
            "category":"Building & Trades",
            "subcategory":"Construction",
            "type":"Services"
        }
    ],
    "sg:phone":"+44 161 231 1408",
    "sg:postcode":"M11 2LJ",
    "sg:province":"Greater Manchester",
    "sg:tags":[
        "joinery"
    ],
    "wof:name":"Lomax Joinery Ltd",
    "wof:placetype":"venue"
},
  "geometry": {"coordinates":[-2.2488100529,53.4796218872],"type":"Point"}
}