{
  "type": "Feature",
  "properties": {
    "addr:full":"27pontardawe Rd Swansea Swansea SA6 5NS",
    "addr:postcode":"sa6 5ns",
    "addr:street":"27Pontardawe Rd",
    "iso:country":"GB",
    "sg:address":"27pontardawe Rd",
    "sg:city":"Swansea",
    "sg:classifiers":[
        {
            "category":"Bus Charters",
            "type":"Transportation"
        }
    ],
    "sg:phone":"+44 1792 843301",
    "sg:postcode":"SA6 5NS",
    "sg:province":"Swansea",
    "sg:tags":[
        "hire",
        "coach"
    ],
    "wof:name":"East End Garage",
    "wof:placetype":"venue"
},
  "geometry": {"coordinates":[-3.897249,51.701401],"type":"Point"}
}