{
  "type": "Feature",
  "properties": {
    "addr:full":"Hamilton Ho, 6 Great Cornbow, Halesowen West Midlands DY1 1DB",
    "addr:housenumber":"6",
    "addr:postcode":"dy1 1db",
    "addr:street":"Great Cornbow",
    "iso:country":"GB",
    "sg:address":"Hamilton Ho, 6 Great Cornbow,",
    "sg:city":"Halesowen",
    "sg:classifiers":[
        {
            "category":"Building & Trades",
            "subcategory":"Construction",
            "type":"Services"
        }
    ],
    "sg:postcode":"DY1 1DB",
    "sg:province":"West Midlands",
    "sg:tags":[
        "flooring"
    ],
    "wof:name":"Croft Supplies Ltd",
    "wof:placetype":"venue"
},
  "geometry": {"coordinates":[-2.0853800774,52.5102882385],"type":"Point"}
}