{
  "type": "Feature",
  "properties": {
    "addr:full":"57 Upper Brighton Rd Lancing West Sussex BN15 0JQ",
    "addr:housenumber":"57",
    "addr:postcode":"bn15 0jq",
    "addr:street":"Upper Brighton Rd",
    "iso:country":"GB",
    "sg:address":"57 Upper Brighton Rd",
    "sg:city":"Lancing",
    "sg:classifiers":[
        {
            "category":"Building & Trades",
            "subcategory":"Construction",
            "type":"Services"
        }
    ],
    "sg:phone":"+44 1903 767311",
    "sg:postcode":"BN15 0JQ",
    "sg:province":"West Sussex",
    "sg:tags":[
        "monumental",
        "mason"
    ],
    "wof:name":"Pilgrim Memorials",
    "wof:placetype":"venue"
},
  "geometry": {"coordinates":[-0.334131,50.837193],"type":"Point"}
}