{
  "type": "Feature",
  "properties": {
    "iso:country":"GB",
    "sg:address":"102 Southchurch Road",
    "sg:city":"Southend-on-sea",
    "sg:classifiers":[
        {
            "category":"Personal",
            "subcategory":"Beauty Salon",
            "type":"Services"
        }
    ],
    "sg:phone":"+44 1702 602453",
    "sg:postcode":"SS1 2LX",
    "sg:province":"Essex",
    "sg:tags":[
        "unisex",
        "hairdresser"
    ],
    "wof:name":"Deja Vu Hairdressing",
    "wof:placetype":"venue"
},
  "geometry": {"coordinates":[0.7169809937,51.5402259827],"type":"Point"}
}