{
  "type": "Feature",
  "properties": {
    "addr:full":"Newbattle House, Newbattle Road Dalkeith City of Edinburgh EH22 3LH",
    "addr:postcode":"eh22 3lh",
    "addr:street":"Newbattle Road",
    "iso:country":"GB",
    "sg:address":"Newbattle House, Newbattle Road",
    "sg:city":"Dalkeith",
    "sg:classifiers":[
        {
            "category":"Manufacturing",
            "subcategory":"Petroleum Products",
            "type":"Manufacturing & Wholesale Goods"
        }
    ],
    "sg:phone":"+44 131 454 0054",
    "sg:postcode":"EH22 3LH",
    "sg:province":"City of Edinburgh",
    "sg:tags":[
        "double",
        "glazing"
    ],
    "wof:name":"J & S McFayden",
    "wof:placetype":"venue"
},
  "geometry": {"coordinates":[-3.0793790817,55.8882141113],"type":"Point"}
}