{
  "type": "Feature",
  "properties": {
    "addr:full":"3 Lower Holyhead Road Coventry West Midlands CV1 3AX",
    "addr:housenumber":"3",
    "addr:postcode":"cv1 3ax",
    "addr:street":"Lower Holyhead Road",
    "iso:country":"GB",
    "sg:address":"3 Lower Holyhead Road",
    "sg:city":"Coventry",
    "sg:classifiers":[
        {
            "category":"Personal",
            "subcategory":"Beauty Salon",
            "type":"Services"
        }
    ],
    "sg:phone":"+44 24 7622 2007",
    "sg:postcode":"CV1 3AX",
    "sg:province":"West Midlands",
    "sg:tags":[
        "unisex",
        "hairdresser"
    ],
    "wof:name":"Evolve",
    "wof:placetype":"venue"
},
  "geometry": {"coordinates":[-1.5166009665,52.4084892273],"type":"Point"}
}