{
  "type": "Feature",
  "properties": {
    "iso:country":"GB",
    "sg:address":"7 Knutsford Way, Sealand Ind Est",
    "sg:city":"Chester",
    "sg:classifiers":[
        {
            "category":"Government",
            "subcategory":"Post Office",
            "type":"Public Place"
        }
    ],
    "sg:phone":"+44 1244 398300",
    "sg:postcode":"CH1 4NS",
    "sg:province":"Cheshire",
    "sg:tags":[
        "messenger",
        "courier"
    ],
    "wof:name":"Speed Couriers",
    "wof:placetype":"venue"
},
  "geometry": {"coordinates":[-2.914612,53.19463],"type":"Point"}
}