{
  "type": "Feature",
  "properties": {
    "iso:country":"GB",
    "sg:address":"110/112 Hoxton Street",
    "sg:city":"London",
    "sg:classifiers":[
        {
            "category":"Home & Garden",
            "subcategory":"Household Appliances",
            "type":"Retail Goods"
        }
    ],
    "sg:phone":"+44 20 7613 1123",
    "sg:postcode":"N1 6SH",
    "sg:province":"Greater London",
    "sg:tags":[
        "electrical"
    ],
    "wof:name":"Domestic Appliances",
    "wof:placetype":"venue"
},
  "geometry": {"coordinates":[-0.080095,51.531281],"type":"Point"}
}