{
  "type": "Feature",
  "properties": {
    "iso:country":"GB",
    "sg:address":"Beaufort Cottage",
    "sg:city":"Bristol",
    "sg:classifiers":[
        {
            "category":"Farming",
            "subcategory":"Fish & Marine Products",
            "type":"Manufacturing & Wholesale Goods"
        }
    ],
    "sg:phone":"+44 1202 665531",
    "sg:postcode":"BS8 4AN",
    "sg:province":"City of Bristol",
    "sg:tags":[
        "equipment",
        "electrical"
    ],
    "wof:name":"Ocean Marine Electronics Ltd.",
    "wof:placetype":"venue"
},
  "geometry": {"coordinates":[-2.621353,51.456295],"type":"Point"}
}