{
  "type": "Feature",
  "properties": {
    "addr:full":"2 High Street Thatcham Berkshire RG19 3JD",
    "addr:housenumber":"2",
    "addr:postcode":"rg19 3jd",
    "addr:street":"High Street",
    "iso:country":"GB",
    "sg:address":"2 High Street",
    "sg:city":"Thatcham",
    "sg:classifiers":[
        {
            "category":"Bars & Pubs",
            "type":"Food & Drink"
        },
        {
            "category":"Community Center",
            "subcategory":"Social",
            "type":"Public Place"
        }
    ],
    "sg:phone":"+44 1635 863251",
    "sg:postcode":"RG19 3JD",
    "sg:province":"Berkshire",
    "sg:tags":[
        "pubs",
        "house",
        "inn",
        "activity"
    ],
    "wof:name":"White Heart",
    "wof:placetype":"venue"
},
  "geometry": {"coordinates":[-1.2578569651,51.4031639099],"type":"Point"}
}