{
  "type": "Feature",
  "properties": {
    "iso:country":"GB",
    "sg:address":"34 Great Underbank, Merseyway Precinct",
    "sg:city":"Stockport",
    "sg:classifiers":[
        {
            "category":"Banks & Credit Unions",
            "subcategory":"Bank",
            "type":"Services"
        }
    ],
    "sg:phone":"+44 161 480 0041",
    "sg:postcode":"SK1 1PD",
    "sg:province":"Cheshire",
    "wof:name":"Northern Rock Plc",
    "wof:placetype":"venue"
},
  "geometry": {"coordinates":[-2.1591000557,53.4109268188],"type":"Point"}
}