{
  "type": "Feature",
  "properties": {
    "addr:full":"104 Cherry Hinton Road Cambridge Cambridgeshire CB1 9EN",
    "addr:housenumber":"104",
    "addr:postcode":"cb1 9en",
    "addr:street":"Cherry Hinton Road",
    "iso:country":"GB",
    "sg:address":"104 Cherry Hinton Road",
    "sg:city":"Cambridge",
    "sg:classifiers":[
        {
            "category":"Banks & Credit Unions",
            "subcategory":"Financial Services",
            "type":"Services"
        }
    ],
    "sg:phone":"+44 1223 213290",
    "sg:postcode":"CB1 9EN",
    "sg:province":"Cambridgeshire",
    "sg:tags":[
        "building",
        "society"
    ],
    "wof:name":"Cambridge Building Society",
    "wof:placetype":"venue"
},
  "geometry": {"coordinates":[0.1417080015,52.1883163452],"type":"Point"}
}