{
  "type": "Feature",
  "properties": {
    "addr:full":"14 Edwards Walk Maldon Essex CM9 5PS",
    "addr:housenumber":"14",
    "addr:postcode":"cm9 5ps",
    "addr:street":"Edwards Walk",
    "iso:country":"GB",
    "sg:address":"14 Edwards Walk",
    "sg:city":"Maldon",
    "sg:classifiers":[
        {
            "category":"Personal",
            "subcategory":"Beauty Salon",
            "type":"Services"
        }
    ],
    "sg:phone":"+44 1621 850980",
    "sg:postcode":"CM9 5PS",
    "sg:province":"Essex",
    "wof:name":"Pure Indulgence",
    "wof:placetype":"venue"
},
  "geometry": {"coordinates":[0.6752489805,51.7313766479],"type":"Point"}
}