{
  "type": "Feature",
  "properties": {
    "addr:full":"Shannon Retail Park, Shannons Corner, Burlington Road New Malden Surrey KT3 4RP",
    "addr:postcode":"kt3 4rp",
    "addr:street":"Shannon Retail Park Shannons Corner Burlington Road",
    "iso:country":"GB",
    "sg:address":"Shannon Retail Park, Shannons Corner, Burlington Road",
    "sg:city":"New Malden",
    "sg:classifiers":[
        {
            "category":"Home & Garden",
            "subcategory":"Furniture",
            "type":"Retail Goods"
        }
    ],
    "sg:phone":"+44 20 8949 7066",
    "sg:postcode":"KT3 4RP",
    "sg:province":"Surrey",
    "wof:name":"D F S",
    "wof:placetype":"venue"
},
  "geometry": {"coordinates":[-0.2561939955,51.4017715454],"type":"Point"}
}