{
  "type": "Feature",
  "properties": {
    "iso:country":"GB",
    "sg:address":"57 High Street",
    "sg:city":"Grantham",
    "sg:classifiers":[
        {
            "category":"Bars & Pubs",
            "type":"Food & Drink"
        }
    ],
    "sg:postcode":"NG32 3DR",
    "sg:province":"Leicestershire",
    "sg:tags":[
        "pubs",
        "inn"
    ],
    "wof:name":"The Wagon & Horses",
    "wof:placetype":"venue"
},
  "geometry": {"coordinates":[-0.60302,53.024731],"type":"Point"}
}