{
  "type": "Feature",
  "properties": {
    "addr:full":"1a Treaford Lane Birmingham West Midlands B8 2UF",
    "addr:housenumber":"1a",
    "addr:postcode":"b8 2uf",
    "addr:street":"Treaford Lane",
    "iso:country":"GB",
    "sg:address":"1a Treaford Lane",
    "sg:city":"Birmingham",
    "sg:classifiers":[
        {
            "category":"Autos & Motor Vehicles",
            "subcategory":"Auto Supplies",
            "type":"Retail Goods"
        }
    ],
    "sg:phone":"+44 121 328 2548",
    "sg:postcode":"B8 2UF",
    "sg:province":"West Midlands",
    "sg:tags":[
        "tyre"
    ],
    "wof:name":"Wardend Tyre Service",
    "wof:placetype":"venue"
},
  "geometry": {"coordinates":[-1.8260099888,52.4898796082],"type":"Point"}
}