{
  "type": "Feature",
  "properties": {
    "addr:full":"Cropton Ho, Three Tuns La Liverpool Lancashire L37 4AQ",
    "addr:postcode":"l37 4aq",
    "addr:street":"La Liverpool",
    "iso:country":"GB",
    "sg:address":"Cropton Ho, Three Tuns La",
    "sg:city":"Liverpool",
    "sg:classifiers":[
        {
            "category":"Health Services",
            "subcategory":"Dentist",
            "type":"Services"
        }
    ],
    "sg:phone":"+44 1704 876846",
    "sg:postcode":"L37 4AQ",
    "sg:province":"Lancashire",
    "wof:name":"Powell J A & Tootell.M",
    "wof:placetype":"venue"
},
  "geometry": {"coordinates":[-3.059859,53.556904],"type":"Point"}
}