{
  "type": "Feature",
  "properties": {
    "addr:full":"22 Wensum Street Norwich Norfolk NR3 1HY",
    "addr:housenumber":"22",
    "addr:postcode":"nr3 1hy",
    "addr:street":"Wensum Street",
    "iso:country":"GB",
    "sg:address":"22 Wensum Street",
    "sg:city":"Norwich",
    "sg:classifiers":[
        {
            "category":"Shopping",
            "subcategory":"Photographic Equipment",
            "type":"Retail Goods"
        }
    ],
    "sg:phone":"+44 1603 625261",
    "sg:postcode":"NR3 1HY",
    "sg:province":"Norfolk",
    "sg:tags":[
        "supply"
    ],
    "wof:name":"Phillips Camera's",
    "wof:placetype":"venue"
},
  "geometry": {"coordinates":[1.297285,52.632629],"type":"Point"}
}