{
  "type": "Feature",
  "properties": {
    "iso:country":"GB",
    "sg:address":"111 Davison Road",
    "sg:city":"Darlington",
    "sg:classifiers":[
        {
            "category":"Building & Trades",
            "subcategory":"Plumbing",
            "type":"Services"
        }
    ],
    "sg:phone":"+44 1325 465283",
    "sg:postcode":"DL1 3DS",
    "sg:province":"Durham",
    "sg:tags":[
        "heating"
    ],
    "wof:name":"Raymond W Colling",
    "wof:placetype":"venue"
},
  "geometry": {"coordinates":[-1.541476965,54.5494880676],"type":"Point"}
}