{
  "type": "Feature",
  "properties": {
    "addr:full":"82-88 North Esk Road Montrose Aberdeenshire DD10 8TG",
    "addr:housenumber":"82-88",
    "addr:postcode":"dd10 8tg",
    "addr:street":"North Esk Road",
    "iso:country":"GB",
    "sg:address":"82-88 North Esk Road",
    "sg:city":"Montrose",
    "sg:classifiers":[
        {
            "category":"Bars & Pubs",
            "type":"Food & Drink"
        }
    ],
    "sg:phone":"+44 1674 673109",
    "sg:postcode":"DD10 8TG",
    "sg:province":"Aberdeenshire",
    "sg:tags":[
        "pubs",
        "inn"
    ],
    "wof:name":"David Taylor",
    "wof:placetype":"venue"
},
  "geometry": {"coordinates":[-2.463588953,56.7120780945],"type":"Point"}
}