{
  "type": "Feature",
  "properties": {
    "iso:country":"GB",
    "sg:address":"39 Martin Rd",
    "sg:city":"Barnstaple",
    "sg:classifiers":[
        {
            "category":"Professional",
            "subcategory":"Engineering",
            "type":"Services"
        },
        {
            "category":"Professional",
            "subcategory":"Detective & Security Services",
            "type":"Services"
        }
    ],
    "sg:postcode":"EX32 7EL",
    "sg:province":"Devon",
    "sg:tags":[
        "burglar",
        "alarm",
        "system",
        "contractor",
        "electrical",
        "engineer"
    ],
    "wof:name":"Williamson,Karl,",
    "wof:placetype":"venue"
},
  "geometry": {"coordinates":[-4.045567,51.082058],"type":"Point"}
}