{
  "type": "Feature",
  "properties": {
    "iso:country":"GB",
    "sg:address":"Ampthill Road, Houghton Conquest, Ampthill",
    "sg:city":"Bedford",
    "sg:classifiers":[
        {
            "category":"Bars & Pubs",
            "type":"Food & Drink"
        }
    ],
    "sg:phone":"+44 1525 404853",
    "sg:postcode":"MK45 3JP",
    "sg:province":"Bedfordshire",
    "sg:tags":[
        "pubs",
        "inn"
    ],
    "wof:name":"Sandra K Waldt",
    "wof:placetype":"venue"
},
  "geometry": {"coordinates":[-0.481479,52.111721],"type":"Point"}
}