{
  "type": "Feature",
  "properties": {
    "iso:country":"GB",
    "sg:address":"42 Drummond Rd",
    "sg:city":"Bournemouth",
    "sg:classifiers":[
        {
            "category":"Building & Trades",
            "subcategory":"Construction",
            "type":"Services"
        }
    ],
    "sg:postcode":"BH1 4DT",
    "sg:province":"Dorset",
    "sg:tags":[
        "decorator",
        "painter"
    ],
    "wof:name":"Teather,A,",
    "wof:placetype":"venue"
},
  "geometry": {"coordinates":[-1.847927,50.726265],"type":"Point"}
}