{
  "type": "Feature",
  "properties": {
    "addr:full":"Bosanath Valley, Mawnan Smith Falmouth Cornwall TR11 5LL",
    "addr:postcode":"tr11 5ll",
    "iso:country":"GB",
    "sg:address":"Bosanath Valley, Mawnan Smith",
    "sg:city":"Falmouth",
    "sg:classifiers":[
        {
            "category":"Home & Garden",
            "subcategory":"Hardware",
            "type":"Retail Goods"
        }
    ],
    "sg:postcode":"TR11 5LL",
    "sg:province":"Cornwall",
    "sg:tags":[
        "lawnmowers",
        "machinery"
    ],
    "wof:name":"Hennings Horticultural Ltd.",
    "wof:placetype":"venue"
},
  "geometry": {"coordinates":[-5.110490799,50.1180458069],"type":"Point"}
}