{
  "type": "Feature",
  "properties": {
    "addr:full":"227-229 Bury Old Road, Prestwich Manchester Greater Manchester M25 1JE",
    "addr:housenumber":"227-229",
    "addr:postcode":"m25 1je",
    "addr:street":"Bury Old Road",
    "iso:country":"GB",
    "sg:address":"227-229 Bury Old Road, Prestwich",
    "sg:city":"Manchester",
    "sg:classifiers":[
        {
            "category":"Shopping",
            "subcategory":"Bicycles & Sporting Goods",
            "type":"Retail Goods"
        }
    ],
    "sg:phone":"+44 161 773 4977",
    "sg:postcode":"M25 1JE",
    "sg:province":"Greater Manchester",
    "sg:tags":[
        "shop",
        "cycle",
        "accessory"
    ],
    "wof:name":"Heaton Park Cycles",
    "wof:placetype":"venue"
},
  "geometry": {"coordinates":[-2.266371,53.530785],"type":"Point"}
}