{
  "type": "Feature",
  "properties": {
    "addr:full":"Company Formations Ltd, 7-11 Minerva Road London Greater London NW10 6HJ",
    "addr:housenumber":"7-11",
    "addr:postcode":"nw10 6hj",
    "addr:street":"Minerva Road",
    "iso:country":"GB",
    "sg:address":"Company Formations Ltd, 7-11 Minerva Road",
    "sg:city":"London",
    "sg:classifiers":[
        {
            "category":"Professional",
            "subcategory":"Management & Consulting",
            "type":"Services"
        }
    ],
    "sg:phone":"+44 20 8537 1212",
    "sg:postcode":"NW10 6HJ",
    "sg:province":"Greater London",
    "sg:tags":[
        "consultant",
        "business"
    ],
    "wof:name":"Stoklot Ltd.",
    "wof:placetype":"venue"
},
  "geometry": {"coordinates":[-0.2628200054,51.529510498],"type":"Point"}
}