{
  "type": "Feature",
  "properties": {
    "iso:country":"GB",
    "sg:address":"Dundas Street",
    "sg:city":"Grangemouth",
    "sg:classifiers":[
        {
            "category":"Organizations",
            "subcategory":"Community Association",
            "type":"Services"
        },
        {
            "category":"Organizations",
            "subcategory":"Membership Organization",
            "type":"Services"
        }
    ],
    "sg:phone":"+44 1324 483143",
    "sg:postcode":"FK3 8BX",
    "sg:province":"Falkirk",
    "sg:tags":[
        "club",
        "social"
    ],
    "wof:name":"Grangemouth Dock Workers Social & Recreation Club",
    "wof:placetype":"venue"
},
  "geometry": {"coordinates":[-3.7255890369,56.0176086426],"type":"Point"}
}