{
  "type": "Feature",
  "properties": {
    "iso:country":"GB",
    "sg:address":"Unit B8, Owen Road",
    "sg:city":"Diss",
    "sg:classifiers":[
        {
            "category":"Manufacturing",
            "subcategory":"Petroleum Products",
            "type":"Manufacturing & Wholesale Goods"
        }
    ],
    "sg:phone":"+44 1379 650303",
    "sg:postcode":"IP22 3ER",
    "sg:province":"Norfolk",
    "sg:tags":[
        "double",
        "glazing"
    ],
    "wof:name":"Diss Window & Conservatory Centre",
    "wof:placetype":"venue"
},
  "geometry": {"coordinates":[1.12249,52.375076],"type":"Point"}
}