{
  "type": "Feature",
  "properties": {
    "addr:full":"Unit 12 Alliance Ct, Alliance Rd Acton Greater London W3 0RB",
    "addr:housenumber":"unit 12",
    "addr:postcode":"w3 0rb",
    "addr:street":"Alliance Ct Alliance Rd",
    "iso:country":"GB",
    "sg:address":"Unit 12 Alliance Ct, Alliance Rd",
    "sg:city":"Acton",
    "sg:classifiers":[
        {
            "category":"Communications",
            "type":"Services"
        }
    ],
    "sg:phone":"+44 20 8993 3535",
    "sg:postcode":"W3 0RB",
    "sg:province":"Greater London",
    "sg:tags":[
        "audio-visual"
    ],
    "wof:name":"P T O Ltd",
    "wof:placetype":"venue"
},
  "geometry": {"coordinates":[-0.2758490145,51.524936676],"type":"Point"}
}