{
  "type": "Feature",
  "properties": {
    "addr:full":"Chapel Lane, Emley Huddersfield South Yorkshire HD8 9SP",
    "addr:postcode":"hd8 9sp",
    "addr:street":"Chapel Lane",
    "iso:country":"GB",
    "sg:address":"Chapel Lane, Emley",
    "sg:city":"Huddersfield",
    "sg:classifiers":[
        {
            "category":"Bars & Pubs",
            "type":"Food & Drink"
        },
        {
            "category":"Community Center",
            "subcategory":"Social",
            "type":"Public Place"
        }
    ],
    "sg:phone":"+44 1924 840937",
    "sg:postcode":"HD8 9SP",
    "sg:province":"South Yorkshire",
    "sg:tags":[
        "pubs",
        "house",
        "inn",
        "activity"
    ],
    "wof:name":"THE WHITE HORSE",
    "wof:placetype":"venue"
},
  "geometry": {"coordinates":[-1.637225,53.613899],"type":"Point"}
}