{
  "type": "Feature",
  "properties": {
    "addr:full":"12 Higher Terrace, Ponsanooth Truro Cornwall TR3 7EW",
    "addr:housenumber":"12",
    "addr:postcode":"tr3 7ew",
    "addr:street":"Higher Terrace Ponsanooth",
    "iso:country":"GB",
    "sg:address":"12 Higher Terrace, Ponsanooth",
    "sg:city":"Truro",
    "sg:classifiers":[
        {
            "category":"Manufacturing",
            "subcategory":"Tools & Machinery",
            "type":"Manufacturing & Wholesale Goods"
        }
    ],
    "sg:phone":"+44 1872 864861",
    "sg:postcode":"TR3 7EW",
    "sg:province":"Cornwall",
    "sg:tags":[
        "cleaning"
    ],
    "wof:name":"Pressure Services",
    "wof:placetype":"venue"
},
  "geometry": {"coordinates":[-5.1428689957,50.1957588196],"type":"Point"}
}