{
  "type": "Feature",
  "properties": {
    "addr:full":"17 London Road Southampton Hampshire SO15 2AE",
    "addr:housenumber":"17",
    "addr:postcode":"so15 2ae",
    "addr:street":"London Road",
    "iso:country":"GB",
    "sg:address":"17 London Road",
    "sg:city":"Southampton",
    "sg:classifiers":[
        {
            "category":"Banks & Credit Unions",
            "subcategory":"Investment Brokerage",
            "type":"Services"
        },
        {
            "category":"Banks & Credit Unions",
            "subcategory":"Financial Services",
            "type":"Services"
        }
    ],
    "sg:phone":"+44 23 8023 7800",
    "sg:postcode":"SO15 2AE",
    "sg:province":"Hampshire",
    "sg:tags":[
        "adviser",
        "pension",
        "independent"
    ],
    "wof:name":"CORPORATE FINANCIAL SOLUTIONS",
    "wof:placetype":"venue"
},
  "geometry": {"coordinates":[-1.4048559666,50.9110908508],"type":"Point"}
}