{
  "type": "Feature",
  "properties": {
    "iso:country":"GB",
    "sg:address":"High Street, Brockmoor",
    "sg:city":"Brierley Hill",
    "sg:classifiers":[
        {
            "category":"Bars & Pubs",
            "type":"Food & Drink"
        }
    ],
    "sg:phone":"+44 1384 484453",
    "sg:postcode":"DY5 3HX",
    "sg:province":"West Midlands",
    "sg:tags":[
        "pubs",
        "house",
        "inn",
        "public",
        "activity"
    ],
    "wof:name":"Brockmoor House",
    "wof:placetype":"venue"
},
  "geometry": {"coordinates":[-2.121174,52.483601],"type":"Point"}
}