{
  "type": "Feature",
  "properties": {
    "iso:country":"GB",
    "sg:address":"41 Station Road, Ratho Station",
    "sg:city":"Newbridge",
    "sg:classifiers":[
        {
            "category":"Retail",
            "subcategory":"Driving School",
            "type":"Services"
        }
    ],
    "sg:postcode":"EH28 8PT",
    "sg:province":"City of Edinburgh",
    "wof:name":"Ratho School of Motoring",
    "wof:placetype":"venue"
},
  "geometry": {"coordinates":[-3.391239,55.93745],"type":"Point"}
}