{
  "type": "Feature",
  "properties": {
    "iso:country":"GB",
    "sg:address":"Beech Business Park, Tillington Road",
    "sg:city":"Hereford",
    "sg:classifiers":[
        {
            "category":"Wholesale",
            "subcategory":"Machinery & Supplies",
            "type":"Manufacturing & Wholesale Goods"
        },
        {
            "category":"Home & Garden",
            "subcategory":"Hardware",
            "type":"Retail Goods"
        },
        {
            "category":"Home & Garden",
            "subcategory":"Carpets & Floor Coverings",
            "type":"Retail Goods"
        }
    ],
    "sg:phone":"+44 1432 274775",
    "sg:postcode":"HR4 9QJ",
    "sg:province":"Herefordshire",
    "sg:tags":[
        "lawnmowers",
        "sales"
    ],
    "sg:website":"http://www.lawnmowersandchainsaws.co.uk",
    "wof:name":"Hereford Mower Services",
    "wof:placetype":"venue"
},
  "geometry": {"coordinates":[-2.731761,52.059204],"type":"Point"}
}