{
  "type": "Feature",
  "properties": {
    "iso:country":"GB",
    "sg:address":"Staplehurst Railway Station, Station Approach, Staplehurst",
    "sg:city":"Tonbridge",
    "sg:classifiers":[
        {
            "category":"Taxi",
            "type":"Transportation"
        }
    ],
    "sg:phone":"+44 1580 890077",
    "sg:postcode":"TN12 0QR",
    "sg:province":"Kent",
    "sg:tags":[
        "mini",
        "cab"
    ],
    "wof:name":"Station Cars",
    "wof:placetype":"venue"
},
  "geometry": {"coordinates":[0.5525919795,51.167049408],"type":"Point"}
}