{
  "type": "Feature",
  "properties": {
    "iso:country":"GB",
    "sg:address":"4 Mansfield Road, Clipstone Village",
    "sg:city":"Mansfield",
    "sg:classifiers":[
        {
            "category":"Freight",
            "type":"Transportation"
        }
    ],
    "sg:phone":"+44 1623 642171",
    "sg:postcode":"NG21 9EJ",
    "sg:province":"Nottinghamshire",
    "sg:tags":[
        "haulage",
        "road"
    ],
    "wof:name":"Barry J Austen & Son",
    "wof:placetype":"venue"
},
  "geometry": {"coordinates":[-1.110311985,53.1652946472],"type":"Point"}
}