{
  "type": "Feature",
  "properties": {
    "iso:country":"GB",
    "sg:address":"291 Woodbridge Road",
    "sg:city":"Ipswich",
    "sg:classifiers":[
        {
            "category":"Wholesale",
            "subcategory":"Toys & Hobbies",
            "type":"Manufacturing & Wholesale Goods"
        }
    ],
    "sg:phone":"+44 1473 728870",
    "sg:postcode":"IP4 4AS",
    "sg:province":"Suffolk",
    "sg:tags":[
        "balloon",
        "novelty"
    ],
    "wof:name":"Ace Balloon Art",
    "wof:placetype":"venue"
},
  "geometry": {"coordinates":[1.1747499704,52.0614891052],"type":"Point"}
}