{
  "type": "Feature",
  "properties": {
    "addr:full":"43 Iffley Rd Oxford Oxfordshire OX4 1EA",
    "addr:housenumber":"43",
    "addr:postcode":"ox4 1ea",
    "addr:street":"Iffley Rd",
    "iso:country":"GB",
    "sg:address":"43 Iffley Rd",
    "sg:city":"Oxford",
    "sg:classifiers":[
        {
            "category":"Bars & Pubs",
            "type":"Food & Drink"
        }
    ],
    "sg:phone":"+44 1865 726264",
    "sg:postcode":"OX4 1EA",
    "sg:province":"Oxfordshire",
    "sg:tags":[
        "pubs",
        "inn"
    ],
    "wof:name":"The Cricketers Arms",
    "wof:placetype":"venue"
},
  "geometry": {"coordinates":[-1.242626,51.748508],"type":"Point"}
}