{
  "type": "Feature",
  "properties": {
    "iso:country":"GB",
    "sg:address":"43 Sparrow Hill",
    "sg:city":"Loughborough",
    "sg:classifiers":[
        {
            "category":"Fast Food",
            "type":"Food & Drink"
        }
    ],
    "sg:postcode":"LE11 1BU",
    "sg:province":"Leicestershire",
    "sg:tags":[
        "away",
        "take"
    ],
    "wof:name":"Curry Express",
    "wof:placetype":"venue"
},
  "geometry": {"coordinates":[-1.201504,52.772739],"type":"Point"}
}