{
  "type": "Feature",
  "properties": {
    "addr:full":"26 Pen Nook Close, Deepcar Sheffield South Yorkshire S36 2TY",
    "addr:housenumber":"26",
    "addr:postcode":"s36 2ty",
    "addr:street":"Pen Nook Close",
    "iso:country":"GB",
    "sg:address":"26 Pen Nook Close, Deepcar",
    "sg:city":"Sheffield",
    "sg:classifiers":[
        {
            "category":"Manufacturing",
            "subcategory":"Rubber & Plastics",
            "type":"Manufacturing & Wholesale Goods"
        }
    ],
    "sg:phone":"+44 114 288 8840",
    "sg:postcode":"S36 2TY",
    "sg:province":"South Yorkshire",
    "sg:tags":[
        "product"
    ],
    "wof:name":"Polyurethane Maintenance Systems",
    "wof:placetype":"venue"
},
  "geometry": {"coordinates":[-1.57996,53.472221],"type":"Point"}
}