{
  "type": "Feature",
  "properties": {
    "addr:full":"448 High Rd Tottenham Greater London N17 9JN",
    "addr:housenumber":"448",
    "addr:postcode":"n17 9jn",
    "addr:street":"High Rd",
    "iso:country":"GB",
    "sg:address":"448 High Rd",
    "sg:city":"Tottenham",
    "sg:classifiers":[
        {
            "category":"Place Of Worship",
            "type":"Public Place"
        }
    ],
    "sg:phone":"+44 20 8885 3333",
    "sg:postcode":"N17 9JN",
    "sg:province":"Greater London",
    "wof:name":"Fresh Annointing Christian Centre",
    "wof:placetype":"venue"
},
  "geometry": {"coordinates":[-0.0697370023,51.5923233032],"type":"Point"}
}