{
  "type": "Feature",
  "properties": {
    "addr:full":"All Saints Rd Wolverhampton West Midlands WV2 1EL",
    "addr:postcode":"wv2 1el",
    "addr:street":"All Saints Rd",
    "iso:country":"GB",
    "sg:address":"All Saints Rd",
    "sg:city":"Wolverhampton",
    "sg:classifiers":[
        {
            "category":"Education",
            "subcategory":"School",
            "type":"Public Place"
        }
    ],
    "sg:phone":"+44 1902 556443",
    "sg:postcode":"WV2 1EL",
    "sg:province":"West Midlands",
    "sg:tags":[
        "local",
        "authority"
    ],
    "wof:name":"All Saints C.E Primary School",
    "wof:placetype":"venue"
},
  "geometry": {"coordinates":[-2.1231839657,52.5779495239],"type":"Point"}
}