{
  "type": "Feature",
  "properties": {
    "addr:full":"70 Whitley Road Whitley Bay Northumberland NE26 2NE",
    "addr:housenumber":"70",
    "addr:postcode":"ne26 2ne",
    "addr:street":"Whitley Road",
    "iso:country":"GB",
    "sg:address":"70 Whitley Road",
    "sg:city":"Whitley Bay",
    "sg:classifiers":[
        {
            "category":"Shopping",
            "subcategory":"Florist",
            "type":"Retail Goods"
        }
    ],
    "sg:phone":"+44 191 251 4961",
    "sg:postcode":"NE26 2NE",
    "sg:province":"Northumberland",
    "wof:name":"Eliza",
    "wof:placetype":"venue"
},
  "geometry": {"coordinates":[-1.437479,55.039867],"type":"Point"}
}