{
  "type": "Feature",
  "properties": {
    "addr:full":"33 Windrush Road, Millbrook Southampton Hampshire SO16 9DD",
    "addr:housenumber":"33",
    "addr:postcode":"so16 9dd",
    "addr:street":"Windrush Road",
    "iso:country":"GB",
    "sg:address":"33 Windrush Road, Millbrook",
    "sg:city":"Southampton",
    "sg:classifiers":[
        {
            "category":"Food & Beverages",
            "subcategory":"Groceries & Convenience Stores",
            "type":"Retail Goods"
        }
    ],
    "sg:phone":"+44 23 8077 4099",
    "sg:postcode":"SO16 9DD",
    "sg:province":"Hampshire",
    "wof:name":"Arrow News",
    "wof:placetype":"venue"
},
  "geometry": {"coordinates":[-1.4577950239,50.9248847961],"type":"Point"}
}