{
  "type": "Feature",
  "properties": {
    "addr:full":"151 Forton Rd Gosport Hampshire PO12 3HB",
    "addr:housenumber":"151",
    "addr:postcode":"po12 3hb",
    "addr:street":"Forton Rd",
    "iso:country":"GB",
    "sg:address":"151 Forton Rd",
    "sg:city":"Gosport",
    "sg:classifiers":[
        {
            "category":"Manufacturing",
            "subcategory":"Petroleum Products",
            "type":"Manufacturing & Wholesale Goods"
        }
    ],
    "sg:phone":"+44 23 9252 9811",
    "sg:postcode":"PO12 3HB",
    "sg:province":"Hampshire",
    "sg:tags":[
        "double",
        "glazing"
    ],
    "wof:name":"Choice Windows",
    "wof:placetype":"venue"
},
  "geometry": {"coordinates":[-1.1413320303,50.8004875183],"type":"Point"}
}