{
  "type": "Feature",
  "properties": {
    "iso:country":"GB",
    "sg:address":"Beehive Farm, Rosliston",
    "sg:city":"Burton-on-trent",
    "sg:classifiers":[
        {
            "category":"Professional",
            "type":"Services"
        },
        {
            "category":"Banks & Credit Unions",
            "subcategory":"Investment Brokerage",
            "type":"Services"
        }
    ],
    "sg:phone":"+44 1283 761467",
    "sg:postcode":"DE12 8HZ",
    "sg:province":"Derbyshire",
    "sg:tags":[
        "farm",
        "agricultural",
        "contractor"
    ],
    "wof:name":"CHAPMAN PARTNERS",
    "wof:placetype":"venue"
},
  "geometry": {"coordinates":[-1.642307,52.748905],"type":"Point"}
}