{
  "type": "Feature",
  "properties": {
    "addr:full":"98 Orchard Way Croydon Surrey CR0 7NJ",
    "addr:housenumber":"98",
    "addr:postcode":"cr0 7nj",
    "addr:street":"Orchard Way",
    "iso:country":"GB",
    "sg:address":"98 Orchard Way",
    "sg:city":"Croydon",
    "sg:classifiers":[
        {
            "category":"Banks & Credit Unions",
            "subcategory":"Financial Services",
            "type":"Services"
        }
    ],
    "sg:phone":"+44 20 8777 9577",
    "sg:postcode":"CR0 7NJ",
    "sg:province":"Surrey",
    "sg:tags":[
        "adviser"
    ],
    "wof:name":"Beauchamp Financial Services",
    "wof:placetype":"venue"
},
  "geometry": {"coordinates":[-0.04053,51.384869],"type":"Point"}
}