{
  "type": "Feature",
  "properties": {
    "iso:country":"GB",
    "sg:address":"73 Baycliff Rd",
    "sg:city":"Liverpool",
    "sg:classifiers":[
        {
            "category":"Health Services",
            "subcategory":"Dentist",
            "type":"Services"
        }
    ],
    "sg:phone":"+44 151 228 2200",
    "sg:postcode":"L12 6QT",
    "sg:province":"Merseyside",
    "wof:name":"Baycliff Dental Practice",
    "wof:placetype":"venue"
},
  "geometry": {"coordinates":[-2.88047,53.433609],"type":"Point"}
}