{
  "type": "Feature",
  "properties": {
    "addr:full":"42 New St Bradford West Yorkshire BD10 9RQ",
    "addr:housenumber":"42",
    "addr:postcode":"bd10 9rq",
    "addr:street":"New St",
    "iso:country":"GB",
    "sg:address":"42 New St",
    "sg:city":"Bradford",
    "sg:classifiers":[
        {
            "category":"Government",
            "subcategory":"Post Office",
            "type":"Public Place"
        }
    ],
    "sg:phone":"+44 1274 611442",
    "sg:postcode":"BD10 9RQ",
    "sg:province":"West Yorkshire",
    "sg:tags":[
        "print",
        "typesetter"
    ],
    "wof:name":"Media Unlimited",
    "wof:placetype":"venue"
},
  "geometry": {"coordinates":[-1.729414,53.835873],"type":"Point"}
}