{
  "type": "Feature",
  "properties": {
    "addr:full":"Wickham Road Fareham Hampshire PO16 7HB",
    "addr:postcode":"po16 7hb",
    "addr:street":"Wickham Road",
    "iso:country":"GB",
    "sg:address":"Wickham Road",
    "sg:city":"Fareham",
    "sg:classifiers":[
        {
            "category":"Utilities",
            "subcategory":"Mobile Phone",
            "type":"Services"
        },
        {
            "category":"Autos & Motor Vehicles",
            "subcategory":"Auto Supplies",
            "type":"Retail Goods"
        },
        {
            "category":"Farming",
            "subcategory":"Farm",
            "type":"Manufacturing & Wholesale Goods"
        },
        {
            "category":"Retail",
            "subcategory":"Auto Repair",
            "type":"Services"
        }
    ],
    "sg:phone":"+44 1329 230805",
    "sg:postcode":"PO16 7HB",
    "sg:province":"Hampshire",
    "sg:tags":[
        "specialist",
        "battery",
        "car",
        "accessory",
        "part",
        "tyre",
        "customizing",
        "supplier",
        "agricultural"
    ],
    "sg:website":"http://turnpiketyres.co.uk",
    "wof:name":"Turnpike Batteries & Tyres",
    "wof:placetype":"venue"
},
  "geometry": {"coordinates":[-1.180414,50.862789],"type":"Point"}
}