{
  "type": "Feature",
  "properties": {
    "addr:full":"75 Landguard Road Shanklin Isle of Wight PO37 7JY",
    "addr:housenumber":"75",
    "addr:postcode":"po37 7jy",
    "addr:street":"Landguard Road",
    "iso:country":"GB",
    "sg:address":"75 Landguard Road",
    "sg:city":"Shanklin",
    "sg:classifiers":[
        {
            "category":"Health Services",
            "subcategory":"Dentist",
            "type":"Services"
        }
    ],
    "sg:phone":"+44 1983 866855",
    "sg:postcode":"PO37 7JY",
    "sg:province":"Isle of Wight",
    "wof:name":"Harold Greenway",
    "wof:placetype":"venue"
},
  "geometry": {"coordinates":[-1.179314971,50.6317062378],"type":"Point"}
}