{
  "type": "Feature",
  "properties": {
    "addr:full":"Unit J, Arklow Trading Estate, Arklow Road London Greater London SE14 6EB",
    "addr:postcode":"se14 6eb",
    "addr:street":"Arklow Road",
    "iso:country":"GB",
    "sg:address":"Unit J, Arklow Trading Estate, Arklow Road",
    "sg:city":"London",
    "sg:classifiers":[
        {
            "category":"Home & Garden",
            "subcategory":"Building Materials",
            "type":"Retail Goods"
        }
    ],
    "sg:phone":"+44 20 8691 9544",
    "sg:postcode":"SE14 6EB",
    "sg:province":"Greater London",
    "sg:tags":[
        "ventilator",
        "ventilation",
        "system"
    ],
    "wof:name":"M J S Ductwork",
    "wof:placetype":"venue"
},
  "geometry": {"coordinates":[-0.03417,51.481659],"type":"Point"}
}