{
  "type": "Feature",
  "properties": {
    "addr:full":"13 Market Pavement Basildon Essex SS14 1DD",
    "addr:housenumber":"13",
    "addr:postcode":"ss14 1dd",
    "addr:street":"Market Pavement",
    "iso:country":"GB",
    "sg:address":"13 Market Pavement",
    "sg:city":"Basildon",
    "sg:classifiers":[
        {
            "category":"Community Center",
            "subcategory":"Social",
            "type":"Public Place"
        }
    ],
    "sg:phone":"+44 1268 270686",
    "sg:postcode":"SS14 1DD",
    "sg:province":"Essex",
    "sg:tags":[
        "frozen",
        "food",
        "freezer",
        "centre"
    ],
    "wof:name":"Iceland Foods Plc",
    "wof:placetype":"venue"
},
  "geometry": {"coordinates":[0.456487,51.569152832],"type":"Point"}
}