{
  "type": "Feature",
  "properties": {
    "iso:country":"GB",
    "sg:address":"Unit 2 Albion Mill, London Road",
    "sg:city":"Macclesfield",
    "sg:classifiers":[
        {
            "category":"Retail",
            "subcategory":"Auto Repair",
            "type":"Services"
        }
    ],
    "sg:phone":"+44 1625 425396",
    "sg:postcode":"SK11 7QX",
    "sg:province":"Cheshire",
    "sg:tags":[
        "electrician"
    ],
    "wof:name":"Macclesfield Auto Electrics",
    "wof:placetype":"venue"
},
  "geometry": {"coordinates":[-2.1229689121,53.2464447021],"type":"Point"}
}