{
  "type": "Feature",
  "properties": {
    "addr:full":"Albion Parade, Wall Heath, Kingswinford Brierley Hill Staffordshire DY6 0NP",
    "addr:postcode":"dy6 0np",
    "addr:street":"Albion Parade Wall Heath",
    "iso:country":"GB",
    "sg:address":"Albion Parade, Wall Heath, Kingswinford",
    "sg:city":"Brierley Hill",
    "sg:classifiers":[
        {
            "category":"Education",
            "subcategory":"Library",
            "type":"Public Place"
        },
        {
            "category":"Government",
            "subcategory":"Office",
            "type":"Public Place"
        }
    ],
    "sg:phone":"+44 1384 812735",
    "sg:postcode":"DY6 0NP",
    "sg:province":"Staffordshire",
    "sg:tags":[
        "book",
        "local"
    ],
    "wof:name":"Wall Heath Library",
    "wof:placetype":"venue"
},
  "geometry": {"coordinates":[-2.181096,52.509308],"type":"Point"}
}