{
  "type": "Feature",
  "properties": {
    "addr:full":"20 Stanhope Street, Whitecross Hereford Herefordshire HR4 0HB",
    "addr:housenumber":"20",
    "addr:postcode":"hr4 0hb",
    "addr:street":"Stanhope Street",
    "iso:country":"GB",
    "sg:address":"20 Stanhope Street, Whitecross",
    "sg:city":"Hereford",
    "sg:classifiers":[
        {
            "category":"Retail",
            "subcategory":"Driving School",
            "type":"Services"
        }
    ],
    "sg:phone":"+44 1432 357389",
    "sg:postcode":"HR4 0HB",
    "sg:province":"Herefordshire",
    "wof:name":"Four Seasons School of Motoring",
    "wof:placetype":"venue"
},
  "geometry": {"coordinates":[-2.7302610874,52.0562667847],"type":"Point"}
}