{
  "type": "Feature",
  "properties": {
    "iso:country":"GB",
    "sg:address":"Newton-st-cyres",
    "sg:city":"Exeter",
    "sg:classifiers":[
        {
            "category":"Bars & Pubs",
            "type":"Food & Drink"
        },
        {
            "category":"Community Center",
            "subcategory":"Social",
            "type":"Public Place"
        }
    ],
    "sg:phone":"+44 1392 851278",
    "sg:postcode":"EX5 5DA",
    "sg:province":"Devon",
    "sg:tags":[
        "pubs",
        "house",
        "inn",
        "activity"
    ],
    "wof:name":"The Crown & Sceptre",
    "wof:placetype":"venue"
},
  "geometry": {"coordinates":[-3.58832,50.770599],"type":"Point"}
}