{
  "type": "Feature",
  "properties": {
    "addr:full":"27 High Street, Long Sutton Spalding Cambridgeshire PE12 9DB",
    "addr:housenumber":"27",
    "addr:postcode":"pe12 9db",
    "addr:street":"High Street",
    "iso:country":"GB",
    "sg:address":"27 High Street, Long Sutton",
    "sg:city":"Spalding",
    "sg:classifiers":[
        {
            "category":"Insurance",
            "subcategory":"Insurance Agent",
            "type":"Services"
        }
    ],
    "sg:phone":"+44 1406 362462",
    "sg:postcode":"PE12 9DB",
    "sg:province":"Cambridgeshire",
    "sg:tags":[
        "broker"
    ],
    "wof:name":"Anthony Fidler & Co",
    "wof:placetype":"venue"
},
  "geometry": {"coordinates":[0.123112,52.785221],"type":"Point"}
}