{
  "type": "Feature",
  "properties": {
    "iso:country":"GB",
    "sg:address":"Westwood House, Westwood Road",
    "sg:city":"Coventry",
    "sg:classifiers":[
        {
            "category":"Retail",
            "subcategory":"Repair Shop",
            "type":"Services"
        }
    ],
    "sg:phone":"+44 24 7671 7560",
    "sg:postcode":"CV5 6GE",
    "sg:province":"West Midlands",
    "sg:tags":[
        "furniture"
    ],
    "wof:name":"Allwood Restorations & Paint Stripping Service",
    "wof:placetype":"venue"
},
  "geometry": {"coordinates":[-1.5292719603,52.4020767212],"type":"Point"}
}