{
  "type": "Feature",
  "properties": {
    "iso:country":"GB",
    "sg:address":"The Old Bakery, 14 Reading Road",
    "sg:city":"Henley-on-thames",
    "sg:classifiers":[
        {
            "category":"Professional",
            "type":"Services"
        }
    ],
    "sg:phone":"+44 1491 578682",
    "sg:postcode":"RG9 1AG",
    "sg:province":"Berkshire",
    "sg:tags":[
        "caterer"
    ],
    "wof:name":"Michelle's Catering",
    "wof:placetype":"venue"
},
  "geometry": {"coordinates":[-0.903189,51.535297],"type":"Point"}
}