{
  "type": "Feature",
  "properties": {
    "iso:country":"GB",
    "sg:address":"3 Gulistan Road",
    "sg:city":"Leamington Spa",
    "sg:classifiers":[
        {
            "category":"Building & Trades",
            "subcategory":"Plumbing",
            "type":"Services"
        }
    ],
    "sg:postcode":"CV32 5LU",
    "sg:province":"Warwickshire",
    "sg:tags":[
        "heating"
    ],
    "wof:name":"Frank A  Haynes",
    "wof:placetype":"venue"
},
  "geometry": {"coordinates":[-1.545027,52.292362],"type":"Point"}
}