{
  "type": "Feature",
  "properties": {
    "addr:full":"44 Albert Road West, Heaton Bolton Lancashire BL1 5HG",
    "addr:housenumber":"44",
    "addr:postcode":"bl1 5hg",
    "addr:street":"Albert Road West",
    "iso:country":"GB",
    "sg:address":"44 Albert Road West, Heaton",
    "sg:city":"Bolton",
    "sg:classifiers":[
        {
            "category":"Professional",
            "subcategory":"Employment Agencies",
            "type":"Services"
        }
    ],
    "sg:phone":"+44 1204 495000",
    "sg:postcode":"BL1 5HG",
    "sg:province":"Lancashire",
    "sg:tags":[
        "consultant"
    ],
    "wof:name":"Carole Payne",
    "wof:placetype":"venue"
},
  "geometry": {"coordinates":[-2.461829,53.582298],"type":"Point"}
}