{
  "type": "Feature",
  "properties": {
    "iso:country":"GB",
    "sg:address":"Regional Office, 126a London Road",
    "sg:city":"Portsmouth",
    "sg:classifiers":[
        {
            "category":"Banks & Credit Unions",
            "subcategory":"Financial Services",
            "type":"Services"
        }
    ],
    "sg:phone":"+44 23 9265 4369",
    "sg:postcode":"PO2 9DE",
    "sg:province":"Hampshire",
    "sg:tags":[
        "adviser"
    ],
    "wof:name":"Royal Insurance Property Services (South)",
    "wof:placetype":"venue"
},
  "geometry": {"coordinates":[-1.07924,50.817429],"type":"Point"}
}