{
  "type": "Feature",
  "properties": {
    "addr:full":"173 Rawlinson Street Barrow-in-furness Cumbria LA14 1ED",
    "addr:housenumber":"173",
    "addr:postcode":"la14 1ed",
    "addr:street":"Rawlinson Street",
    "iso:country":"GB",
    "sg:address":"173 Rawlinson Street",
    "sg:city":"Barrow-in-furness",
    "sg:classifiers":[
        {
            "category":"Personal",
            "subcategory":"Beauty Salon",
            "type":"Services"
        }
    ],
    "sg:phone":"+44 1229 821152",
    "sg:postcode":"LA14 1ED",
    "sg:province":"Cumbria",
    "sg:tags":[
        "unisex",
        "hairdresser"
    ],
    "wof:name":"Margaret Anne",
    "wof:placetype":"venue"
},
  "geometry": {"coordinates":[-3.2218990326,54.1135215759],"type":"Point"}
}