{
  "type": "Feature",
  "properties": {
    "iso:country":"GB",
    "sg:address":"Crompton St",
    "sg:city":"Wigan",
    "sg:classifiers":[
        {
            "category":"Social Services",
            "subcategory":"Adult Care",
            "type":"Services"
        }
    ],
    "sg:phone":"+44 1942 243800",
    "sg:postcode":"WN1 3SL",
    "sg:province":"Lancashire",
    "sg:tags":[
        "day",
        "centre"
    ],
    "wof:name":"Crompton Street Day Centre",
    "wof:placetype":"venue"
},
  "geometry": {"coordinates":[-2.628674,53.547482],"type":"Point"}
}