{
  "type": "Feature",
  "properties": {
    "addr:full":"100 Promenade Cheltenham Gloucestershire GL50 1NB",
    "addr:housenumber":"100",
    "addr:postcode":"gl50 1nb",
    "addr:street":"Promenade",
    "iso:country":"GB",
    "sg:address":"100 Promenade",
    "sg:city":"Cheltenham",
    "sg:classifiers":[
        {
            "category":"Shopping",
            "subcategory":"Clothing, Apparel, & Fashions",
            "type":"Retail Goods"
        }
    ],
    "sg:phone":"+44 1242 580770",
    "sg:postcode":"GL50 1NB",
    "sg:province":"Gloucestershire",
    "sg:tags":[
        "shop"
    ],
    "wof:name":"Laura Ashley",
    "wof:placetype":"venue"
},
  "geometry": {"coordinates":[-2.0776019096,51.8985481262],"type":"Point"}
}