{
  "type": "Feature",
  "properties": {
    "iso:country":"GB",
    "sg:address":"4 Plaza Way, Southchurch Road",
    "sg:city":"Southend-on-sea",
    "sg:classifiers":[
        {
            "category":"Fast Food",
            "type":"Food & Drink"
        }
    ],
    "sg:phone":"+44 1702 467908",
    "sg:postcode":"SS1 2PU",
    "sg:province":"Essex",
    "sg:tags":[
        "away",
        "take"
    ],
    "wof:name":"Plaza Pizza",
    "wof:placetype":"venue"
},
  "geometry": {"coordinates":[0.7129520178,51.5399971008],"type":"Point"}
}