{
  "type": "Feature",
  "properties": {
    "addr:full":"Broomhouse Road Edinburgh City of Edinburgh EH12 9AE",
    "addr:postcode":"eh12 9ae",
    "addr:street":"Broomhouse Road",
    "iso:country":"GB",
    "sg:address":"Broomhouse Road",
    "sg:city":"Edinburgh",
    "sg:classifiers":[
        {
            "category":"Arena",
            "subcategory":"Sports Club",
            "type":"Entertainment"
        }
    ],
    "sg:phone":"+44 131 334 6981",
    "sg:postcode":"EH12 9AE",
    "sg:province":"City of Edinburgh",
    "wof:name":"Forrester Rugby Club & Sports Association",
    "wof:placetype":"venue"
},
  "geometry": {"coordinates":[-3.287474,55.93317],"type":"Point"}
}