{
  "type": "Feature",
  "properties": {
    "iso:country":"GB",
    "sg:address":"Victoria Avenue, Ockbrook",
    "sg:city":"Derby",
    "sg:classifiers":[
        {
            "category":"Arena",
            "subcategory":"Sports Club",
            "type":"Entertainment"
        }
    ],
    "sg:phone":"+44 1332 670522",
    "sg:postcode":"DE72 3RL",
    "sg:province":"Derbyshire",
    "wof:name":"Ockbrook & Borrowash Cricket Club",
    "wof:placetype":"venue"
},
  "geometry": {"coordinates":[-1.37211,52.919765],"type":"Point"}
}