{
  "type": "Feature",
  "properties": {
    "addr:full":"P O Box 14, 410 Birchwood Blvd Warrington Cheshire WA3 7GA",
    "addr:housenumber":"box 14 410",
    "addr:postcode":"wa3 7ga",
    "addr:street":"P O;Birchwood Blvd",
    "iso:country":"GB",
    "sg:address":"P O Box 14, 410 Birchwood Blvd",
    "sg:city":"Warrington",
    "sg:classifiers":[
        {
            "category":"Utilities",
            "subcategory":"Water",
            "type":"Services"
        }
    ],
    "sg:phone":"+44 1925 285000",
    "sg:postcode":"WA3 7GA",
    "sg:province":"Cheshire",
    "wof:name":"United Utilities Nominees Ltd",
    "wof:placetype":"venue"
},
  "geometry": {"coordinates":[-2.541079998,53.4271011353],"type":"Point"}
}