{
  "type": "Feature",
  "properties": {
    "iso:country":"GB",
    "sg:address":"4 Church Road",
    "sg:city":"Lytham St Annes",
    "sg:classifiers":[
        {
            "category":"Professional",
            "subcategory":"Lawyer & Legal Services",
            "type":"Services"
        }
    ],
    "sg:phone":"+44 1253 734253",
    "sg:postcode":"FY8 5LH",
    "sg:province":"Lancashire",
    "sg:tags":[
        "solicitor"
    ],
    "wof:name":"Butterfield",
    "wof:placetype":"venue"
},
  "geometry": {"coordinates":[-2.9657599926,53.7372627258],"type":"Point"}
}