{
  "type": "Feature",
  "properties": {
    "iso:country":"GB",
    "sg:address":"27 Longley Avenue West",
    "sg:city":"Sheffield",
    "sg:classifiers":[
        {
            "category":"Food & Beverages",
            "subcategory":"Bakery",
            "type":"Retail Goods"
        }
    ],
    "sg:phone":"+44 114 261 8637",
    "sg:postcode":"S5 8WA",
    "sg:province":"South Yorkshire",
    "sg:tags":[
        "pizza"
    ],
    "wof:name":"Mona Lisa Pizzeria",
    "wof:placetype":"venue"
},
  "geometry": {"coordinates":[-1.470544,53.409187],"type":"Point"}
}