{
  "type": "Feature",
  "properties": {
    "iso:country":"GB",
    "sg:address":"53 High St",
    "sg:city":"Cheltenham",
    "sg:classifiers":[
        {
            "category":"Personal",
            "subcategory":"Beauty Salon",
            "type":"Services"
        }
    ],
    "sg:postcode":"GL50 1DX",
    "sg:province":"Gloucestershire",
    "sg:tags":[
        "unisex",
        "hairdresser"
    ],
    "wof:name":"Pearce,Sarah,",
    "wof:placetype":"venue"
},
  "geometry": {"coordinates":[-2.070935,51.897926],"type":"Point"}
}