{
  "type": "Feature",
  "properties": {
    "addr:full":"Care Of Sprowston Training Centre, Church La Norwich Norfolk NR7 8AY",
    "addr:postcode":"nr7 8ay",
    "addr:street":"La Norwich Norfolk",
    "iso:country":"GB",
    "sg:address":"Care Of Sprowston Training Centre, Church La",
    "sg:city":"Norwich",
    "sg:classifiers":[
        {
            "category":"Health Services",
            "subcategory":"Nursing And Care Facility",
            "type":"Services"
        },
        {
            "category":"Social Services",
            "subcategory":"Retirement Home",
            "type":"Services"
        }
    ],
    "sg:phone":"+44 1603 411855",
    "sg:postcode":"NR7 8AY",
    "sg:province":"Norfolk",
    "sg:tags":[
        "residential"
    ],
    "wof:name":"Span Housing With Support",
    "wof:placetype":"venue"
},
  "geometry": {"coordinates":[1.3215800524,52.651309967],"type":"Point"}
}