{
  "type": "Feature",
  "properties": {
    "addr:full":"The Street, Charmouth Bridport Dorset DT6 6PN",
    "addr:postcode":"dt6 6pn",
    "addr:street":"The Street",
    "iso:country":"GB",
    "sg:address":"The Street, Charmouth",
    "sg:city":"Bridport",
    "sg:classifiers":[
        {
            "category":"Taxi",
            "type":"Transportation"
        },
        {
            "category":"Military Area",
            "subcategory":"Air Force Base",
            "type":"Public Place"
        }
    ],
    "sg:phone":"+44 1297 560733",
    "sg:postcode":"DT6 6PN",
    "sg:province":"Dorset",
    "sg:tags":[
        "hire",
        "private"
    ],
    "wof:name":"Floyds Taxis & Mini Buses",
    "wof:placetype":"venue"
},
  "geometry": {"coordinates":[-2.896855,50.739422],"type":"Point"}
}