{
  "type": "Feature",
  "properties": {
    "addr:full":"8 Langley Road, Spondon Derby Derbyshire DE21 7HY",
    "addr:housenumber":"8",
    "addr:postcode":"de21 7hy",
    "addr:street":"Langley Road",
    "iso:country":"GB",
    "sg:address":"8 Langley Road, Spondon",
    "sg:city":"Derby",
    "sg:classifiers":[
        {
            "category":"Building & Trades",
            "subcategory":"Construction",
            "type":"Services"
        }
    ],
    "sg:postcode":"DE21 7HY",
    "sg:province":"Derbyshire",
    "sg:tags":[
        "glazier",
        "decorator",
        "painter"
    ],
    "wof:name":"Thomas M Earnshaw Decorators",
    "wof:placetype":"venue"
},
  "geometry": {"coordinates":[-1.4014790058,52.9134292603],"type":"Point"}
}