{
  "type": "Feature",
  "properties": {
    "addr:full":"104 Radcliffe Road, West Bridgford Nottingham Nottinghamshire NG2 5HG",
    "addr:housenumber":"104",
    "addr:postcode":"ng2 5hg",
    "addr:street":"Radcliffe Road",
    "iso:country":"GB",
    "sg:address":"104 Radcliffe Road, West Bridgford",
    "sg:city":"Nottingham",
    "sg:classifiers":[
        {
            "category":"Travel",
            "subcategory":"Hotels & Motels",
            "type":"Entertainment"
        }
    ],
    "sg:phone":"+44 115 981 1413",
    "sg:postcode":"NG2 5HG",
    "sg:province":"Nottinghamshire",
    "sg:tags":[
        "house",
        "guest"
    ],
    "wof:name":"Rushcliffe",
    "wof:placetype":"venue"
},
  "geometry": {"coordinates":[-1.123898983,52.9365844727],"type":"Point"}
}