{
  "type": "Feature",
  "properties": {
    "addr:full":"Chellow Grange Quarries, Haworth Road Bradford West Yorkshire BD9 6NL",
    "addr:postcode":"bd9 6nl",
    "addr:street":"Haworth Road",
    "iso:country":"GB",
    "sg:address":"Chellow Grange Quarries, Haworth Road",
    "sg:city":"Bradford",
    "sg:classifiers":[
        {
            "category":"Wholesale",
            "subcategory":"Construction Materials",
            "type":"Manufacturing & Wholesale Goods"
        }
    ],
    "sg:phone":"+44 1274 542439",
    "sg:postcode":"BD9 6NL",
    "sg:province":"West Yorkshire",
    "sg:tags":[
        "merchant",
        "stone"
    ],
    "wof:name":"Harry Parker & Son",
    "wof:placetype":"venue"
},
  "geometry": {"coordinates":[-1.8103289604,53.8063049316],"type":"Point"}
}