{
  "type": "Feature",
  "properties": {
    "addr:full":"22 Sandbeck Park, Sandbeck Lane Wetherby North Yorkshire LS22 4DN",
    "addr:housenumber":"22",
    "addr:postcode":"ls22 4dn",
    "addr:street":"Sandbeck Park Sandbeck Lane",
    "iso:country":"GB",
    "sg:address":"22 Sandbeck Park, Sandbeck Lane",
    "sg:city":"Wetherby",
    "sg:classifiers":[
        {
            "category":"Sports & Exercise",
            "subcategory":"Playing Field",
            "type":"Entertainment"
        }
    ],
    "sg:phone":"+44 1937 588585",
    "sg:postcode":"LS22 4DN",
    "sg:province":"North Yorkshire",
    "sg:tags":[
        "transmission",
        "power"
    ],
    "wof:name":"Yorkshire Engineering Services",
    "wof:placetype":"venue"
},
  "geometry": {"coordinates":[-1.3868039846,53.9279899597],"type":"Point"}
}