{
  "type": "Feature",
  "properties": {
    "iso:country":"GB",
    "sg:address":"Skellingthorpe Road",
    "sg:city":"Lincoln",
    "sg:classifiers":[
        {
            "category":"Landmark",
            "subcategory":"Tourist Attraction",
            "type":"Public Place"
        }
    ],
    "sg:phone":"+44 1522 686264",
    "sg:postcode":"LN6 0EY",
    "sg:province":"Lincolnshire",
    "sg:tags":[
        "interest"
    ],
    "wof:name":"Hartsholme Country Park",
    "wof:placetype":"venue"
},
  "geometry": {"coordinates":[-0.589539,53.220531],"type":"Point"}
}