{
  "type": "Feature",
  "properties": {
    "iso:country":"GB",
    "sg:address":", Blaydon Bank",
    "sg:city":"Blaydon On Tyne",
    "sg:classifiers":[
        {
            "category":"Organizations",
            "subcategory":"Political Organization",
            "type":"Services"
        }
    ],
    "sg:phone":"+44 191 414 2956",
    "sg:postcode":"NE21 4RB",
    "sg:province":"Tyne and Wear",
    "sg:tags":[
        "promoter",
        "pool"
    ],
    "wof:name":"Rex Bingo & Social Clb",
    "wof:placetype":"venue"
},
  "geometry": {"coordinates":[-1.713958,54.964378],"type":"Point"}
}