{
  "type": "Feature",
  "properties": {
    "addr:full":"Maryport Street Usk Monmouthshire NP15 1AB",
    "addr:postcode":"np15 1ab",
    "addr:street":"Maryport Street",
    "iso:country":"GB",
    "sg:address":"Maryport Street",
    "sg:city":"Usk",
    "sg:classifiers":[
        {
            "category":"Health Services",
            "subcategory":"Doctor",
            "type":"Services"
        }
    ],
    "sg:phone":"+44 1291 672753",
    "sg:postcode":"NP15 1AB",
    "sg:province":"Monmouthshire",
    "sg:tags":[
        "practitioners"
    ],
    "wof:name":"Monmouth House Medical Centre",
    "wof:placetype":"venue"
},
  "geometry": {"coordinates":[-2.903329,51.70332],"type":"Point"}
}