{
  "type": "Feature",
  "properties": {
    "addr:full":"137 Greenwich South St Greenwich Greater London SE10 8NX",
    "addr:housenumber":"137",
    "addr:postcode":"se10 8nx",
    "addr:street":"Greenwich South St",
    "iso:country":"GB",
    "sg:address":"137 Greenwich South St",
    "sg:city":"Greenwich",
    "sg:classifiers":[
        {
            "category":"Health Services",
            "subcategory":"Doctor",
            "type":"Services"
        }
    ],
    "sg:phone":"+44 20 8691 8999",
    "sg:postcode":"SE10 8NX",
    "sg:province":"Greater London",
    "sg:tags":[
        "practitioners"
    ],
    "wof:name":"Ratneswaren, N",
    "wof:placetype":"venue"
},
  "geometry": {"coordinates":[-0.0147089995,51.4733695984],"type":"Point"}
}