{
  "type": "Feature",
  "properties": {
    "iso:country":"GB",
    "sg:address":"Park View Garage, Shiney Row",
    "sg:city":"Houghton-le-spring",
    "sg:classifiers":[
        {
            "category":"Retail",
            "subcategory":"Auto Repair",
            "type":"Services"
        }
    ],
    "sg:postcode":"DH4 4QR",
    "sg:province":"Durham",
    "sg:tags":[
        "modification",
        "garage"
    ],
    "wof:name":"Park View Vehicle Services",
    "wof:placetype":"venue"
},
  "geometry": {"coordinates":[-1.493529,54.867294],"type":"Point"}
}