{
  "type": "Feature",
  "properties": {
    "addr:full":"38 Bridge Street Downham Market Cambridgeshire PE38 9DH",
    "addr:housenumber":"38",
    "addr:postcode":"pe38 9dh",
    "addr:street":"Bridge Street",
    "iso:country":"GB",
    "sg:address":"38 Bridge Street",
    "sg:city":"Downham Market",
    "sg:classifiers":[
        {
            "category":"Food & Beverages",
            "subcategory":"Meat & Fish",
            "type":"Retail Goods"
        }
    ],
    "sg:phone":"+44 1366 383029",
    "sg:postcode":"PE38 9DH",
    "sg:province":"Cambridgeshire",
    "sg:tags":[
        "chip"
    ],
    "wof:name":"Downham Fryer",
    "wof:placetype":"venue"
},
  "geometry": {"coordinates":[0.375751,52.602974],"type":"Point"}
}