{
  "type": "Feature",
  "properties": {
    "addr:full":"2 South Embankment Dartmouth Devon TQ6 9BH",
    "addr:housenumber":"2",
    "addr:postcode":"tq6 9bh",
    "addr:street":"South Embankment",
    "iso:country":"GB",
    "sg:address":"2 South Embankment",
    "sg:city":"Dartmouth",
    "sg:classifiers":[
        {
            "category":"Restaurant",
            "type":"Food & Drink"
        }
    ],
    "sg:phone":"+44 1803 832465",
    "sg:postcode":"TQ6 9BH",
    "sg:province":"Devon",
    "wof:name":"The Carved Angel Ltd.",
    "wof:placetype":"venue"
},
  "geometry": {"coordinates":[-3.5776898861,50.3510017395],"type":"Point"}
}