{
  "type": "Feature",
  "properties": {
    "iso:country":"GB",
    "sg:address":"52 Nevill Road, Rottingdean",
    "sg:city":"Brighton",
    "sg:classifiers":[
        {
            "category":"Health Services",
            "subcategory":"Health Practitioner",
            "type":"Services"
        }
    ],
    "sg:postcode":"BN2 7HG",
    "sg:province":"East Sussex",
    "sg:tags":[
        "osteopath"
    ],
    "wof:name":"The Back-to-Work Clinic",
    "wof:placetype":"venue"
},
  "geometry": {"coordinates":[-0.0616640002,50.8045425415],"type":"Point"}
}