{
  "type": "Feature",
  "properties": {
    "addr:full":"The Bungalow, Kelling Rd, Lower Bodham Holt Norfolk NR25 6RT",
    "addr:postcode":"nr25 6rt",
    "addr:street":"Kelling Rd",
    "iso:country":"GB",
    "sg:address":"The Bungalow, Kelling Rd, Lower Bodham",
    "sg:city":"Holt",
    "sg:classifiers":[
        {
            "category":"Professional",
            "subcategory":"Engineering",
            "type":"Services"
        }
    ],
    "sg:phone":"+44 1263 713323",
    "sg:postcode":"NR25 6RT",
    "sg:province":"Norfolk",
    "sg:tags":[
        "agricultural",
        "engineer"
    ],
    "wof:name":"G.R Digby",
    "wof:placetype":"venue"
},
  "geometry": {"coordinates":[1.089946,52.903057],"type":"Point"}
}