{
  "type": "Feature",
  "properties": {
    "addr:full":"468 West Green Road London Greater London N15 3PT",
    "addr:housenumber":"468",
    "addr:postcode":"n15 3pt",
    "addr:street":"West Green Road",
    "iso:country":"GB",
    "sg:address":"468 West Green Road",
    "sg:city":"London",
    "sg:classifiers":[
        {
            "category":"Travel",
            "subcategory":"Travel Agent",
            "type":"Entertainment"
        }
    ],
    "sg:phone":"+44 20 8881 7760",
    "sg:postcode":"N15 3PT",
    "sg:province":"Greater London",
    "wof:name":"Infinity Travel & Tours Ltd.",
    "wof:placetype":"venue"
},
  "geometry": {"coordinates":[-0.098037,51.587357],"type":"Point"}
}