{
  "type": "Feature",
  "properties": {
    "iso:country":"GB",
    "sg:address":"2177 Stratford Road, Hockley Heath",
    "sg:city":"Solihull",
    "sg:classifiers":[
        {
            "category":"Home & Garden",
            "subcategory":"Home Furnishings",
            "type":"Retail Goods"
        },
        {
            "category":"Home & Garden",
            "subcategory":"Furniture",
            "type":"Retail Goods"
        }
    ],
    "sg:postcode":"B94 6EA",
    "sg:province":"Warwickshire",
    "sg:tags":[
        "furnishers",
        "planner",
        "bedroom"
    ],
    "wof:name":"Solihull Bedroooms",
    "wof:placetype":"venue"
},
  "geometry": {"coordinates":[-1.781812,52.364895],"type":"Point"}
}