{
  "type": "Feature",
  "properties": {
    "addr:full":"51 Crowland Street Southport Lancashire PR9 7RX",
    "addr:housenumber":"51",
    "addr:postcode":"pr9 7rx",
    "addr:street":"Crowland Street",
    "iso:country":"GB",
    "sg:address":"51 Crowland Street",
    "sg:city":"Southport",
    "sg:classifiers":[
        {
            "category":"Home & Garden",
            "subcategory":"Kitchen Supply",
            "type":"Retail Goods"
        }
    ],
    "sg:phone":"+44 1704 507330",
    "sg:postcode":"PR9 7RX",
    "sg:province":"Lancashire",
    "sg:tags":[
        "equipment",
        "catering"
    ],
    "wof:name":"Southport Metal Fabrications",
    "wof:placetype":"venue"
},
  "geometry": {"coordinates":[-2.9631690979,53.6422080994],"type":"Point"}
}