{
  "type": "Feature",
  "properties": {
    "addr:full":"Hutchison House, Senhouse Rd, Lingfield Way Darlington Durham DL1 4YG",
    "addr:postcode":"dl1 4yg",
    "addr:street":"Senhouse Rd Lingfield Way",
    "iso:country":"GB",
    "sg:address":"Hutchison House, Senhouse Rd, Lingfield Way",
    "sg:city":"Darlington",
    "sg:classifiers":[
        {
            "category":"Communications",
            "type":"Services"
        }
    ],
    "sg:phone":"+44 1325 393939",
    "sg:postcode":"DL1 4YG",
    "sg:province":"Durham",
    "sg:tags":[
        "telecommunication"
    ],
    "wof:name":"Hutchison Paging",
    "wof:placetype":"venue"
},
  "geometry": {"coordinates":[-1.5094490051,54.5203018188],"type":"Point"}
}