{
  "type": "Feature",
  "properties": {
    "addr:full":"Windmill Lane, Cheshunt Waltham Cross Essex EN8 9AA",
    "addr:postcode":"en8 9aa",
    "addr:street":"Windmill Lane;Cross",
    "iso:country":"GB",
    "sg:address":"Windmill Lane, Cheshunt",
    "sg:city":"Waltham Cross",
    "sg:classifiers":[
        {
            "category":"Government",
            "subcategory":"City Hall",
            "type":"Public Place"
        }
    ],
    "sg:phone":"+44 1992 628567",
    "sg:postcode":"EN8 9AA",
    "sg:province":"Essex",
    "wof:name":"Wolsey Hall",
    "wof:placetype":"venue"
},
  "geometry": {"coordinates":[-0.023139,51.703213],"type":"Point"}
}