{
  "type": "Feature",
  "properties": {
    "addr:full":"16 St James Court, Mapperley Nottingham Nottinghamshire NG3 6GH",
    "addr:housenumber":"16",
    "addr:postcode":"ng3 6gh",
    "addr:street":"St James Court",
    "iso:country":"GB",
    "sg:address":"16 St James Court, Mapperley",
    "sg:city":"Nottingham",
    "sg:classifiers":[
        {
            "category":"Building & Trades",
            "subcategory":"Construction",
            "type":"Services"
        }
    ],
    "sg:postcode":"NG3 6GH",
    "sg:province":"Nottinghamshire",
    "sg:tags":[
        "decorator",
        "painter"
    ],
    "wof:name":"John M Lucas",
    "wof:placetype":"venue"
},
  "geometry": {"coordinates":[-1.10875,52.979359],"type":"Point"}
}