{
  "type": "Feature",
  "properties": {
    "iso:country":"GB",
    "sg:address":"17 Howitt Road",
    "sg:city":"London",
    "sg:classifiers":[
        {
            "category":"Communications",
            "type":"Services"
        }
    ],
    "sg:phone":"+44 20 7722 6464",
    "sg:postcode":"NW3 4LT",
    "sg:province":"Greater London",
    "sg:tags":[
        "audio-visual"
    ],
    "wof:name":"Richmond Films & Television Ltd.",
    "wof:placetype":"venue"
},
  "geometry": {"coordinates":[-0.164726,51.549648],"type":"Point"}
}