{
  "type": "Feature",
  "properties": {
    "addr:full":"5 Bolton Rd, Ashton In Makerfield Wigan Lancashire WN4 8AA",
    "addr:housenumber":"5",
    "addr:postcode":"wn4 8aa",
    "addr:street":"Bolton Rd",
    "iso:country":"GB",
    "sg:address":"5 Bolton Rd, Ashton In Makerfield",
    "sg:city":"Wigan",
    "sg:classifiers":[
        {
            "category":"Wholesale",
            "subcategory":"Office Equipment",
            "type":"Manufacturing & Wholesale Goods"
        }
    ],
    "sg:phone":"+44 1942 270729",
    "sg:postcode":"WN4 8AA",
    "sg:province":"Lancashire",
    "sg:tags":[
        "cleaning"
    ],
    "wof:name":"Anglo Scot Abrasives",
    "wof:placetype":"venue"
},
  "geometry": {"coordinates":[-2.635296,53.488983],"type":"Point"}
}