{
  "type": "Feature",
  "properties": {
    "addr:full":"5 Umberslade Business Centre, Pound Hous, Hockley Heath Solihull Warwickshire B94 5DF",
    "addr:housenumber":"5",
    "addr:postcode":"b94 5df",
    "addr:street":"Umberslade Business Centre",
    "iso:country":"GB",
    "sg:address":"5 Umberslade Business Centre, Pound Hous, Hockley Heath",
    "sg:city":"Solihull",
    "sg:classifiers":[
        {
            "category":"Communications",
            "type":"Services"
        }
    ],
    "sg:postcode":"B94 5DF",
    "sg:province":"Warwickshire",
    "sg:tags":[
        "data",
        "network"
    ],
    "wof:name":"Sterling Network Services Ltd",
    "wof:placetype":"venue"
},
  "geometry": {"coordinates":[-1.803385973,52.3431358337],"type":"Point"}
}