{
  "type": "Feature",
  "properties": {
    "addr:full":"West End Farm, Brompton-by-sawdon Scarborough North Yorkshire YO13 9DQ",
    "addr:postcode":"yo13 9dq",
    "addr:street":"Brompton-By-Sawdon",
    "iso:country":"GB",
    "sg:address":"West End Farm, Brompton-by-sawdon",
    "sg:city":"Scarborough",
    "sg:classifiers":[
        {
            "category":"Professional",
            "subcategory":"Employment Agencies",
            "type":"Services"
        }
    ],
    "sg:postcode":"YO13 9DQ",
    "sg:province":"North Yorkshire",
    "sg:tags":[
        "agricultural",
        "advice"
    ],
    "wof:name":"Koppert",
    "wof:placetype":"venue"
},
  "geometry": {"coordinates":[-0.5529440045,54.227104187],"type":"Point"}
}