{
  "type": "Feature",
  "properties": {
    "iso:country":"GB",
    "sg:address":"22 Dronfield Civic Centre, Farwater Lane",
    "sg:city":"Dronfield",
    "sg:classifiers":[
        {
            "category":"Food & Beverages",
            "subcategory":"Supermarket",
            "type":"Retail Goods"
        }
    ],
    "sg:phone":"+44 1246 412749",
    "sg:postcode":"S18 1PD",
    "sg:province":"Derbyshire",
    "wof:name":"Somerfield",
    "wof:placetype":"venue"
},
  "geometry": {"coordinates":[-1.4750080109,53.3017120361],"type":"Point"}
}