{
  "type": "Feature",
  "properties": {
    "iso:country":"GB",
    "sg:address":"Oakwood, Bethersden",
    "sg:city":"Ashford",
    "sg:classifiers":[
        {
            "category":"Health Services",
            "subcategory":"Health Practitioner",
            "type":"Services"
        }
    ],
    "sg:postcode":"TN26 3ED",
    "sg:province":"Kent",
    "sg:tags":[
        "osteopath"
    ],
    "wof:name":"Mark Hutchin",
    "wof:placetype":"venue"
},
  "geometry": {"coordinates":[0.752973,51.126179],"type":"Point"}
}