{
  "type": "Feature",
  "properties": {
    "iso:country":"GB",
    "sg:address":"Jewry Street",
    "sg:city":"Winchester",
    "sg:classifiers":[
        {
            "category":"Real Estate",
            "subcategory":"Surveying",
            "type":"Services"
        }
    ],
    "sg:phone":"+44 1962 841187",
    "sg:postcode":"SO23 8RY",
    "sg:province":"Hampshire",
    "sg:tags":[
        "surveyor",
        "land"
    ],
    "wof:name":"Countrywide Surveyors",
    "wof:placetype":"venue"
},
  "geometry": {"coordinates":[-1.315899,51.065723],"type":"Point"}
}