{
  "type": "Feature",
  "properties": {
    "addr:full":"115 Clermiston Road Edinburgh City of Edinburgh EH12 6UR",
    "addr:housenumber":"115",
    "addr:postcode":"eh12 6ur",
    "addr:street":"Clermiston Road",
    "iso:country":"GB",
    "sg:address":"115 Clermiston Road",
    "sg:city":"Edinburgh",
    "sg:classifiers":[
        {
            "category":"Building & Trades",
            "subcategory":"Construction",
            "type":"Services"
        }
    ],
    "sg:postcode":"EH12 6UR",
    "sg:province":"City of Edinburgh",
    "sg:tags":[
        "joinery",
        "joiner",
        "carpenter",
        "carpentry"
    ],
    "wof:name":"Alex Davie",
    "wof:placetype":"venue"
},
  "geometry": {"coordinates":[-3.2790699005,55.9504470825],"type":"Point"}
}