{
  "type": "Feature",
  "properties": {
    "iso:country":"GB",
    "sg:address":"10 Church Road, Bitton",
    "sg:city":"Bristol",
    "sg:classifiers":[
        {
            "category":"Building & Trades",
            "subcategory":"Landscaping Services",
            "type":"Services"
        }
    ],
    "sg:phone":"+44 117 932 4991",
    "sg:postcode":"BS30 6HH",
    "sg:province":"Gloucestershire",
    "sg:tags":[
        "gardening"
    ],
    "wof:name":"Avon Patios",
    "wof:placetype":"venue"
},
  "geometry": {"coordinates":[-2.4603760242,51.4239654541],"type":"Point"}
}