{
  "type": "Feature",
  "properties": {
    "addr:full":"55 Knockcushan Street Girvan South Ayrshire KA26 9AG",
    "addr:housenumber":"55",
    "addr:postcode":"ka26 9ag",
    "addr:street":"Knockcushan Street",
    "iso:country":"GB",
    "sg:address":"55 Knockcushan Street",
    "sg:city":"Girvan",
    "sg:classifiers":[
        {
            "category":"Food & Beverages",
            "subcategory":"Candy",
            "type":"Retail Goods"
        }
    ],
    "sg:phone":"+44 1465 712560",
    "sg:postcode":"KA26 9AG",
    "sg:province":"South Ayrshire",
    "sg:tags":[
        "confectioner"
    ],
    "wof:name":"M Funai",
    "wof:placetype":"venue"
},
  "geometry": {"coordinates":[-4.860204,55.243137],"type":"Point"}
}