{
  "type": "Feature",
  "properties": {
    "addr:full":"Dyffryn Business Park, Ystrad Mynach Hengoed Caerphilly CF82 7RJ",
    "addr:postcode":"cf82 7rj",
    "iso:country":"GB",
    "sg:address":"Dyffryn Business Park, Ystrad Mynach",
    "sg:city":"Hengoed",
    "sg:classifiers":[
        {
            "category":"Manufacturing",
            "subcategory":"Chemicals & Compounds",
            "type":"Manufacturing & Wholesale Goods"
        }
    ],
    "sg:phone":"+44 1443 816656",
    "sg:postcode":"CF82 7RJ",
    "sg:province":"Caerphilly",
    "sg:tags":[
        "pesticide"
    ],
    "wof:name":"International Sorbent Technology Ltd.",
    "wof:placetype":"venue"
},
  "geometry": {"coordinates":[-3.231799,51.648319],"type":"Point"}
}