{
  "type": "Feature",
  "properties": {
    "addr:full":"48a High St Pershore Worcestershire WR10 1DP",
    "addr:housenumber":"48a",
    "addr:postcode":"wr10 1dp",
    "addr:street":"High St",
    "iso:country":"GB",
    "sg:address":"48a High St",
    "sg:city":"Pershore",
    "sg:classifiers":[
        {
            "category":"Professional",
            "subcategory":"Art Services",
            "type":"Services"
        }
    ],
    "sg:postcode":"WR10 1DP",
    "sg:province":"Worcestershire",
    "sg:tags":[
        "framing"
    ],
    "wof:name":"Griffiths,Jean,",
    "wof:placetype":"venue"
},
  "geometry": {"coordinates":[-2.075832,52.11145],"type":"Point"}
}