{
  "type": "Feature",
  "properties": {
    "addr:full":"Eastern Green Penzance Cornwall TR18 3AS",
    "addr:postcode":"tr18 3as",
    "iso:country":"GB",
    "sg:address":"Eastern Green",
    "sg:city":"Penzance",
    "sg:classifiers":[
        {
            "category":"Manufacturing",
            "subcategory":"Building Materials",
            "type":"Manufacturing & Wholesale Goods"
        }
    ],
    "sg:phone":"+44 1736 333123",
    "sg:postcode":"TR18 3AS",
    "sg:province":"Cornwall",
    "sg:tags":[
        "merchant",
        "builder"
    ],
    "wof:name":"E G N Services Ltd.",
    "wof:placetype":"venue"
},
  "geometry": {"coordinates":[-5.52255,50.12801],"type":"Point"}
}