{
  "type": "Feature",
  "properties": {
    "addr:full":"15 Sowood Gardens Ossett West Yorkshire WF5 0SP",
    "addr:housenumber":"15",
    "addr:postcode":"wf5 0sp",
    "addr:street":"Sowood Gardens",
    "iso:country":"GB",
    "sg:address":"15 Sowood Gardens",
    "sg:city":"Ossett",
    "sg:classifiers":[
        {
            "category":"Professional",
            "subcategory":"Printing & Photocopies",
            "type":"Services"
        }
    ],
    "sg:phone":"+44 1924 276104",
    "sg:postcode":"WF5 0SP",
    "sg:province":"West Yorkshire",
    "sg:tags":[
        "printer"
    ],
    "wof:name":"Print & Flexible Packaging",
    "wof:placetype":"venue"
},
  "geometry": {"coordinates":[-1.567223,53.670605],"type":"Point"}
}