{
  "type": "Feature",
  "properties": {
    "addr:full":"190 Boleyn Road London Greater London N16 8AS",
    "addr:housenumber":"190",
    "addr:postcode":"n16 8as",
    "addr:street":"Boleyn Road",
    "iso:country":"GB",
    "sg:address":"190 Boleyn Road",
    "sg:city":"London",
    "sg:classifiers":[
        {
            "category":"Bars & Pubs",
            "type":"Food & Drink"
        }
    ],
    "sg:phone":"+44 20 7254 7531",
    "sg:postcode":"N16 8AS",
    "sg:province":"Greater London",
    "sg:tags":[
        "pubs",
        "inn"
    ],
    "wof:name":"The Woodman",
    "wof:placetype":"venue"
},
  "geometry": {"coordinates":[-0.079242,51.551636],"type":"Point"}
}