{
  "type": "Feature",
  "properties": {
    "addr:full":"25 Borough Pavement, Grange Precinct Birkenhead Merseyside L41 2XX",
    "addr:housenumber":"25",
    "addr:postcode":"l41 2xx",
    "addr:street":"Borough Pavement;Precinct",
    "iso:country":"GB",
    "sg:address":"25 Borough Pavement, Grange Precinct",
    "sg:city":"Birkenhead",
    "sg:classifiers":[
        {
            "category":"Shopping",
            "subcategory":"Clothing, Apparel, & Fashions",
            "type":"Retail Goods"
        }
    ],
    "sg:phone":"+44 151 647 9451",
    "sg:postcode":"L41 2XX",
    "sg:province":"Merseyside",
    "sg:tags":[
        "shop"
    ],
    "wof:name":"Jeanster",
    "wof:placetype":"venue"
},
  "geometry": {"coordinates":[-3.02549,53.392559],"type":"Point"}
}