{
  "type": "Feature",
  "properties": {
    "iso:country":"GB",
    "sg:address":"88 Newbridge Hill",
    "sg:city":"Bath",
    "sg:classifiers":[
        {
            "category":"Health Services",
            "subcategory":"Nursing And Care Facility",
            "type":"Services"
        },
        {
            "category":"Social Services",
            "subcategory":"Retirement Home",
            "type":"Services"
        }
    ],
    "sg:phone":"+44 1225 319293",
    "sg:postcode":"BA1 3QA",
    "sg:province":"Bath and North East Somerset",
    "sg:tags":[
        "residential"
    ],
    "wof:name":"St Bethans Residential Home for the Elderly",
    "wof:placetype":"venue"
},
  "geometry": {"coordinates":[-2.3952898979,51.3880691528],"type":"Point"}
}