{
  "type": "Feature",
  "properties": {
    "iso:country":"GB",
    "sg:address":"Moory Meadow, Combe Martin",
    "sg:city":"Ilfracombe",
    "sg:classifiers":[
        {
            "category":"Travel",
            "subcategory":"Hotels & Motels",
            "type":"Entertainment"
        }
    ],
    "sg:postcode":"EX34 0DG",
    "sg:province":"Devon",
    "wof:name":"Blair Lodge Private Hotel",
    "wof:placetype":"venue"
},
  "geometry": {"coordinates":[-4.036413,51.206375],"type":"Point"}
}