{
  "type": "Feature",
  "properties": {
    "iso:country":"GB",
    "sg:address":"The Steps, Church Grn",
    "sg:city":"Redditch",
    "sg:classifiers":[
        {
            "category":"Shopping",
            "subcategory":"Clothing, Apparel, & Fashions",
            "type":"Retail Goods"
        },
        {
            "category":"Personal",
            "subcategory":"Beauty Salon",
            "type":"Services"
        }
    ],
    "sg:phone":"+44 1527 62076",
    "sg:postcode":"B98 8AA",
    "sg:province":"Warwickshire",
    "sg:tags":[
        "shop",
        "unisex",
        "hat",
        "hairdresser"
    ],
    "wof:name":"T J's Hair & Beauty Studio",
    "wof:placetype":"venue"
},
  "geometry": {"coordinates":[-1.94102,52.306702],"type":"Point"}
}