{
  "type": "Feature",
  "properties": {
    "addr:full":"Stanley Road, Stockton Brook Stoke-on-trent Staffordshire ST9 9LJ",
    "addr:postcode":"staffordshire st9 9lj",
    "addr:street":"Stanley Road",
    "iso:country":"GB",
    "sg:address":"Stanley Road, Stockton Brook",
    "sg:city":"Stoke-on-trent",
    "sg:classifiers":[
        {
            "category":"Sports & Exercise",
            "subcategory":"Golf",
            "type":"Entertainment"
        }
    ],
    "sg:phone":"+44 1782 503158",
    "sg:postcode":"ST9 9LJ",
    "sg:province":"Staffordshire",
    "sg:tags":[
        "club",
        "course"
    ],
    "wof:name":"Greenway Hall Golf Club Ltd.",
    "wof:placetype":"venue"
},
  "geometry": {"coordinates":[-2.116296,53.06424],"type":"Point"}
}