{
  "type": "Feature",
  "properties": {
    "iso:country":"GB",
    "sg:address":"5 Chapel Street Court",
    "sg:city":"Poulton-le-fylde",
    "sg:classifiers":[
        {
            "category":"Personal",
            "subcategory":"Barber",
            "type":"Services"
        }
    ],
    "sg:phone":"+44 1253 882344",
    "sg:postcode":"FY6 7BH",
    "sg:province":"Lancashire",
    "sg:tags":[
        "men's",
        "hairdresser"
    ],
    "wof:name":"Peter J's",
    "wof:placetype":"venue"
},
  "geometry": {"coordinates":[-2.990944,53.84721],"type":"Point"}
}