{
  "type": "Feature",
  "properties": {
    "addr:full":"2 Brox Rd, Ottershaw Chertsey Surrey KT16 0HL",
    "addr:housenumber":"2",
    "addr:postcode":"kt16 0hl",
    "addr:street":"Brox Rd",
    "iso:country":"GB",
    "sg:address":"2 Brox Rd, Ottershaw",
    "sg:city":"Chertsey",
    "sg:classifiers":[
        {
            "category":"Health Services",
            "subcategory":"Dentist",
            "type":"Services"
        }
    ],
    "sg:phone":"+44 1932 875000",
    "sg:postcode":"KT16 0HL",
    "sg:province":"Surrey",
    "wof:name":"Ottershaw Dental Practice",
    "wof:placetype":"venue"
},
  "geometry": {"coordinates":[-0.5314459801,51.3651542664],"type":"Point"}
}