{
  "type": "Feature",
  "properties": {
    "addr:full":"17 Sleigh Drive Edinburgh City of Edinburgh EH7 6EB",
    "addr:housenumber":"17",
    "addr:postcode":"eh7 6eb",
    "addr:street":"Sleigh Drive",
    "iso:country":"GB",
    "sg:address":"17 Sleigh Drive",
    "sg:city":"Edinburgh",
    "sg:classifiers":[
        {
            "category":"Professional",
            "subcategory":"Art Services",
            "type":"Services"
        },
        {
            "category":"Building & Trades",
            "subcategory":"Construction",
            "type":"Services"
        }
    ],
    "sg:phone":"+44 70 5005 9932",
    "sg:postcode":"EH7 6EB",
    "sg:province":"City of Edinburgh",
    "sg:tags":[
        "decorator",
        "painter"
    ],
    "wof:name":"Sutherland & Miller",
    "wof:placetype":"venue"
},
  "geometry": {"coordinates":[-3.157166,55.962532],"type":"Point"}
}