{
  "type": "Feature",
  "properties": {
    "iso:country":"GB",
    "sg:address":"2nd Floor, 1-5 Maple Place",
    "sg:city":"London",
    "sg:classifiers":[
        {
            "category":"Communications",
            "subcategory":"Newspaper",
            "type":"Services"
        }
    ],
    "sg:phone":"+44 20 7462 4700",
    "sg:postcode":"W1T 4BB",
    "sg:province":"Greater London",
    "sg:tags":[
        "magazine"
    ],
    "wof:name":"That's Life Magazine",
    "wof:placetype":"venue"
},
  "geometry": {"coordinates":[-0.137673,51.52206],"type":"Point"}
}