{
  "type": "Feature",
  "properties": {
    "addr:full":"22-24 Worple Road, Wimbledon London Greater London SW19 4DD",
    "addr:housenumber":"22-24",
    "addr:postcode":"sw19 4dd",
    "addr:street":"Worple Road",
    "iso:country":"GB",
    "sg:address":"22-24 Worple Road, Wimbledon",
    "sg:city":"London",
    "sg:classifiers":[
        {
            "category":"Organizations",
            "subcategory":"Professional Association",
            "type":"Services"
        }
    ],
    "sg:phone":"+44 20 8947 3131",
    "sg:postcode":"SW19 4DD",
    "sg:province":"Greater London",
    "sg:tags":[
        "union",
        "trade"
    ],
    "wof:name":"G M B - Britains General Union",
    "wof:placetype":"venue"
},
  "geometry": {"coordinates":[-0.2098519951,51.4207496643],"type":"Point"}
}