{
  "type": "Feature",
  "properties": {
    "addr:full":"8 The Bdwy Shopping Centre, Yaxley Peterborough Cambridgeshire PE7 3EF",
    "addr:housenumber":"8",
    "addr:postcode":"pe7 3ef",
    "addr:street":"The Bdwy Shopping;Peterborough",
    "iso:country":"GB",
    "sg:address":"8 The Bdwy Shopping Centre, Yaxley",
    "sg:city":"Peterborough",
    "sg:classifiers":[
        {
            "category":"Fast Food",
            "type":"Food & Drink"
        }
    ],
    "sg:postcode":"PE7 3EF",
    "sg:province":"Cambridgeshire",
    "sg:tags":[
        "away",
        "take"
    ],
    "wof:name":"Golden Gate",
    "wof:placetype":"venue"
},
  "geometry": {"coordinates":[-0.255084008,52.5185890198],"type":"Point"}
}