{
  "type": "Feature",
  "properties": {
    "addr:full":"Falcon Ho, 86-90 East Barnet Rd Barnet Hertfordshire EN4 8RQ",
    "addr:housenumber":"86-90",
    "addr:postcode":"en4 8rq",
    "addr:street":"East Barnet Rd",
    "iso:country":"GB",
    "sg:address":"Falcon Ho, 86-90 East Barnet Rd",
    "sg:city":"Barnet",
    "sg:classifiers":[
        {
            "category":"Professional",
            "subcategory":"Lawyer & Legal Services",
            "type":"Services"
        }
    ],
    "sg:postcode":"EN4 8RQ",
    "sg:province":"Hertfordshire",
    "sg:tags":[
        "solicitor"
    ],
    "wof:name":"Barnett,Peter,",
    "wof:placetype":"venue"
},
  "geometry": {"coordinates":[-0.1617050022,51.6442108154],"type":"Point"}
}