{
  "type": "Feature",
  "properties": {
    "addr:full":"7 Blakenhurst Evesham Gloucestershire WR11 8NB",
    "addr:housenumber":"7",
    "addr:postcode":"wr11 8nb",
    "addr:street":"Blakenhurst Evesham",
    "iso:country":"GB",
    "sg:address":"7 Blakenhurst",
    "sg:city":"Evesham",
    "sg:classifiers":[
        {
            "category":"Professional",
            "subcategory":"Secretarial Services",
            "type":"Services"
        }
    ],
    "sg:phone":"+44 1386 871417",
    "sg:postcode":"WR11 8NB",
    "sg:province":"Gloucestershire",
    "wof:name":"Office Administration Support",
    "wof:placetype":"venue"
},
  "geometry": {"coordinates":[-1.9304330349,52.1449241638],"type":"Point"}
}