{
  "type": "Feature",
  "properties": {
    "iso:country":"GB",
    "sg:address":"The White Cottage, Hawkenbury Road",
    "sg:city":"Tonbridge",
    "sg:classifiers":[
        {
            "category":"Real Estate",
            "subcategory":"Surveying",
            "type":"Services"
        }
    ],
    "sg:postcode":"TN12 0DU",
    "sg:province":"Kent",
    "sg:tags":[
        "building",
        "surveyor"
    ],
    "wof:name":"Tenmar Surveyors & Estimators",
    "wof:placetype":"venue"
},
  "geometry": {"coordinates":[0.583425,51.178108],"type":"Point"}
}