{
  "type": "Feature",
  "properties": {
    "iso:country":"GB",
    "sg:address":"Deken House, Amesbury Road",
    "sg:city":"Salisbury",
    "sg:classifiers":[
        {
            "category":"Building & Trades",
            "subcategory":"Construction",
            "type":"Services"
        }
    ],
    "sg:postcode":"SP3 4HD",
    "sg:province":"Wiltshire",
    "sg:tags":[
        "decorator",
        "painter"
    ],
    "wof:name":"Easton Decorating Services",
    "wof:placetype":"venue"
},
  "geometry": {"coordinates":[-1.9015769958,51.1911506653],"type":"Point"}
}