{
  "type": "Feature",
  "properties": {
    "addr:full":"P O Box 115 Stevenage Hertfordshire SG1 2UH",
    "addr:housenumber":"115",
    "addr:postcode":"sg1 2uh",
    "addr:street":"P O Box",
    "iso:country":"GB",
    "sg:address":"P O Box 115",
    "sg:city":"Stevenage",
    "sg:classifiers":[
        {
            "category":"Insurance",
            "subcategory":"Insurance Agent",
            "type":"Services"
        }
    ],
    "sg:phone":"+44 1438 770011",
    "sg:postcode":"SG1 2UH",
    "sg:province":"Hertfordshire",
    "wof:name":"General Accident Insurance Group",
    "wof:placetype":"venue"
},
  "geometry": {"coordinates":[-0.1886799932,51.9056091309],"type":"Point"}
}