{
  "type": "Feature",
  "properties": {
    "addr:full":"Clubhouse, Fife Airport Glenrothes Fife KY6 2SL",
    "addr:postcode":"ky6 2sl",
    "addr:street":"Glenrothes",
    "iso:country":"GB",
    "sg:address":"Clubhouse, Fife Airport",
    "sg:city":"Glenrothes",
    "sg:classifiers":[
        {
            "category":"Education",
            "subcategory":"Special Training",
            "type":"Public Place"
        }
    ],
    "sg:phone":"+44 1592 753792",
    "sg:postcode":"KY6 2SL",
    "sg:province":"Fife",
    "sg:tags":[
        "school",
        "flying"
    ],
    "wof:name":"R L FRAZER",
    "wof:placetype":"venue"
},
  "geometry": {"coordinates":[-3.21686,56.185291],"type":"Point"}
}