{
  "type": "Feature",
  "properties": {
    "iso:country":"GB",
    "sg:address":"165 Bridge Road",
    "sg:city":"Grays",
    "sg:classifiers":[
        {
            "category":"Organizations",
            "subcategory":"Non-profit Organization",
            "type":"Services"
        }
    ],
    "sg:phone":"+44 1375 377205",
    "sg:postcode":"RM17 6DB",
    "sg:province":"Essex",
    "sg:tags":[
        "organisation",
        "voluntary",
        "charity"
    ],
    "wof:name":"British Red Cross Society",
    "wof:placetype":"venue"
},
  "geometry": {"coordinates":[0.3308430016,51.4804496765],"type":"Point"}
}