{
  "type": "Feature",
  "properties": {
    "iso:country":"GB",
    "sg:address":"15 Church Hill Road",
    "sg:city":"Ormskirk",
    "sg:classifiers":[
        {
            "category":"Building & Trades",
            "subcategory":"Plumbing",
            "type":"Services"
        }
    ],
    "sg:postcode":"L39 3BB",
    "sg:province":"Lancashire",
    "sg:tags":[
        "heating"
    ],
    "wof:name":"J J Rhodes & Son",
    "wof:placetype":"venue"
},
  "geometry": {"coordinates":[-2.894329,53.571346],"type":"Point"}
}