{
  "type": "Feature",
  "properties": {
    "addr:full":"Frankby Road, Frankby Wirral Merseyside CH48 1PF",
    "addr:postcode":"ch48 1pf",
    "addr:street":"Frankby Road",
    "iso:country":"GB",
    "sg:address":"Frankby Road, Frankby",
    "sg:city":"Wirral",
    "sg:classifiers":[
        {
            "category":"Farming",
            "subcategory":"Poultry Farm",
            "type":"Manufacturing & Wholesale Goods"
        }
    ],
    "sg:postcode":"CH48 1PF",
    "sg:province":"Merseyside",
    "sg:tags":[
        "game"
    ],
    "wof:name":"Hillcroft Poultry Farm",
    "wof:placetype":"venue"
},
  "geometry": {"coordinates":[-3.136784,53.371616],"type":"Point"}
}