{
  "type": "Feature",
  "properties": {
    "iso:country":"GB",
    "sg:address":"Unit 7 Constance Industrial Estate, Waterloo Road",
    "sg:city":"Widnes",
    "sg:classifiers":[
        {
            "category":"Retail",
            "subcategory":"Auto Repair",
            "type":"Services"
        }
    ],
    "sg:phone":"+44 151 420 8585",
    "sg:postcode":"WA8 0QR",
    "sg:province":"Cheshire",
    "sg:tags":[
        "electrician"
    ],
    "wof:name":"Widnes Auto Electrical Services",
    "wof:placetype":"venue"
},
  "geometry": {"coordinates":[-2.734285,53.355553],"type":"Point"}
}