{
  "type": "Feature",
  "properties": {
    "addr:full":"South St Bourne Lincolnshire PE10 9LY",
    "addr:postcode":"pe10 9ly",
    "addr:street":"South St",
    "iso:country":"GB",
    "sg:address":"South St",
    "sg:city":"Bourne",
    "sg:classifiers":[
        {
            "category":"Autos & Motor Vehicles",
            "subcategory":"Automobile Sales",
            "type":"Retail Goods"
        }
    ],
    "sg:phone":"+44 1778 424848",
    "sg:postcode":"PE10 9LY",
    "sg:province":"Lincolnshire",
    "sg:tags":[
        "car"
    ],
    "wof:name":"Auto Trading Co",
    "wof:placetype":"venue"
},
  "geometry": {"coordinates":[-0.3754670024,52.7656669617],"type":"Point"}
}