{
  "type": "Feature",
  "properties": {
    "iso:country":"GB",
    "sg:address":"10 Cavendish Road",
    "sg:city":"Redhill",
    "sg:classifiers":[
        {
            "category":"Building & Trades",
            "subcategory":"Plumbing",
            "type":"Services"
        }
    ],
    "sg:phone":"+44 1737 779600",
    "sg:postcode":"RH1 4AE",
    "sg:province":"Surrey",
    "sg:tags":[
        "filtration",
        "system"
    ],
    "wof:name":"Beaumonts International",
    "wof:placetype":"venue"
},
  "geometry": {"coordinates":[-0.1629430056,51.2393951416],"type":"Point"}
}