{
  "type": "Feature",
  "properties": {
    "iso:country":"GB",
    "sg:address":"Park Way",
    "sg:city":"Newbury",
    "sg:classifiers":[
        {
            "category":"Shopping",
            "subcategory":"Beauty & Cosmetics",
            "type":"Retail Goods"
        }
    ],
    "sg:phone":"+44 1635 42040",
    "sg:postcode":"RG14 1EE",
    "sg:province":"Berkshire",
    "sg:tags":[
        "product"
    ],
    "wof:name":"Slenderline",
    "wof:placetype":"venue"
},
  "geometry": {"coordinates":[-1.322596,51.405682],"type":"Point"}
}