{
  "type": "Feature",
  "properties": {
    "iso:country":"GB",
    "sg:address":"1070-1072 Harrow Road",
    "sg:city":"London",
    "sg:classifiers":[
        {
            "category":"Retail",
            "subcategory":"Auto Repair",
            "type":"Services"
        }
    ],
    "sg:phone":"+44 20 8969 0358",
    "sg:postcode":"NW10 5NL",
    "sg:province":"Greater London",
    "sg:tags":[
        "electrical",
        "centre"
    ],
    "wof:name":"R & R Auto Electrics",
    "wof:placetype":"venue"
},
  "geometry": {"coordinates":[-0.231844,51.531715],"type":"Point"}
}