{
  "type": "Feature",
  "properties": {
    "addr:full":"309 Hornchurch Road Hornchurch Essex RM12 4PQ",
    "addr:housenumber":"309",
    "addr:postcode":"rm12 4pq",
    "addr:street":"Hornchurch Road",
    "iso:country":"GB",
    "sg:address":"309 Hornchurch Road",
    "sg:city":"Hornchurch",
    "sg:classifiers":[
        {
            "category":"Personal",
            "subcategory":"Beauty Salon",
            "type":"Services"
        }
    ],
    "sg:phone":"+44 1708 447460",
    "sg:postcode":"RM12 4PQ",
    "sg:province":"Essex",
    "sg:tags":[
        "unisex",
        "hairdresser"
    ],
    "wof:name":"Continental Hairstylists",
    "wof:placetype":"venue"
},
  "geometry": {"coordinates":[0.189713,51.565163],"type":"Point"}
}