{
  "type": "Feature",
  "properties": {
    "iso:country":"GB",
    "sg:address":"108 Bowyer Drive",
    "sg:city":"Slough",
    "sg:classifiers":[
        {
            "category":"Home & Garden",
            "subcategory":"Kitchen Supply",
            "type":"Retail Goods"
        }
    ],
    "sg:phone":"+44 1753 674358",
    "sg:postcode":"SL1 5EQ",
    "sg:province":"Berkshire",
    "sg:tags":[
        "equipment",
        "catering"
    ],
    "wof:name":"Wrimer Catering",
    "wof:placetype":"venue"
},
  "geometry": {"coordinates":[-0.64416,51.515392],"type":"Point"}
}