{
  "type": "Feature",
  "properties": {
    "addr:full":"Trent House, Twisleton Court, Priory Hill Dartford Kent DA1 2EN",
    "addr:postcode":"da1 2en",
    "addr:street":"Twisleton;Priory Hill",
    "iso:country":"GB",
    "sg:address":"Trent House, Twisleton Court, Priory Hill",
    "sg:city":"Dartford",
    "sg:classifiers":[
        {
            "category":"Professional",
            "subcategory":"Engineering",
            "type":"Services"
        },
        {
            "category":"Building & Trades",
            "subcategory":"Construction",
            "type":"Services"
        }
    ],
    "sg:phone":"+44 1322 287733",
    "sg:postcode":"DA1 2EN",
    "sg:province":"Kent",
    "sg:tags":[
        "mechanical",
        "heating",
        "contractor"
    ],
    "wof:name":"C B S Maintenance Services Ltd.",
    "wof:placetype":"venue"
},
  "geometry": {"coordinates":[0.2114939988,51.4478034973],"type":"Point"}
}