{
  "type": "Feature",
  "properties": {
    "iso:country":"GB",
    "sg:address":"16 Old Milton Rd",
    "sg:city":"New Milton",
    "sg:classifiers":[
        {
            "category":"Organizations",
            "subcategory":"Non-profit Organization",
            "type":"Services"
        }
    ],
    "sg:phone":"+44 1425 628750",
    "sg:postcode":"BH25 6DX",
    "sg:province":"Hampshire",
    "sg:tags":[
        "organisation",
        "voluntary",
        "charity"
    ],
    "wof:name":"New Forest Disability Information Service",
    "wof:placetype":"venue"
},
  "geometry": {"coordinates":[-1.658445,50.7523],"type":"Point"}
}