{
  "type": "Feature",
  "properties": {
    "iso:country":"GB",
    "sg:address":"Court Farm, Eastdown, Blackawton",
    "sg:city":"Totnes",
    "sg:classifiers":[
        {
            "category":"Farming",
            "subcategory":"Dairy Farm",
            "type":"Manufacturing & Wholesale Goods"
        }
    ],
    "sg:phone":"+44 1803 712205",
    "sg:postcode":"TQ9 7AP",
    "sg:province":"Devon",
    "wof:name":"M G Jarvis",
    "wof:placetype":"venue"
},
  "geometry": {"coordinates":[-3.681114,50.346016],"type":"Point"}
}