{
  "type": "Feature",
  "properties": {
    "addr:full":"Berth 104 Eastern Docks, Herbert Walker Avenue Southampton Hampshire SO14 3JJ",
    "addr:housenumber":"104",
    "addr:postcode":"so14 3jj",
    "addr:street":"Berth;Herbert Walker Avenue",
    "iso:country":"GB",
    "sg:address":"Berth 104 Eastern Docks, Herbert Walker Avenue",
    "sg:city":"Southampton",
    "sg:classifiers":[
        {
            "category":"Professional",
            "subcategory":"Business Services",
            "type":"Services"
        }
    ],
    "sg:phone":"+44 23 8033 5169",
    "sg:postcode":"SO14 3JJ",
    "sg:province":"Hampshire",
    "sg:tags":[
        "distribution"
    ],
    "wof:name":"Allfruit International Ltd.",
    "wof:placetype":"venue"
},
  "geometry": {"coordinates":[-1.3998500109,50.8926086426],"type":"Point"}
}