{
  "type": "Feature",
  "properties": {
    "addr:full":"27 Syr Davids Avenue, Canton Cardiff Cardiff CF5 1GH",
    "addr:housenumber":"27",
    "addr:postcode":"cf5 1gh",
    "addr:street":"Syr Davids Avenue",
    "iso:country":"GB",
    "sg:address":"27 Syr Davids Avenue, Canton",
    "sg:city":"Cardiff",
    "sg:classifiers":[
        {
            "category":"Recreation",
            "subcategory":"Sailing Club",
            "type":"Entertainment"
        }
    ],
    "sg:phone":"+44 29 2023 6366",
    "sg:postcode":"CF5 1GH",
    "sg:province":"Cardiff",
    "wof:name":"Glyn Lloyd",
    "wof:placetype":"venue"
},
  "geometry": {"coordinates":[-3.210966,51.487473],"type":"Point"}
}