{
  "type": "Feature",
  "properties": {
    "addr:full":"Unit 2/3, Southfields Road Dunstable Bedfordshire LU6 3EJ",
    "addr:housenumber":"unit 2 / 3",
    "addr:postcode":"lu6 3ej",
    "addr:street":"Southfields Road",
    "iso:country":"GB",
    "sg:address":"Unit 2/3, Southfields Road",
    "sg:city":"Dunstable",
    "sg:classifiers":[
        {
            "category":"Manufacturing",
            "subcategory":"Building Materials",
            "type":"Manufacturing & Wholesale Goods"
        }
    ],
    "sg:phone":"+44 1582 475663",
    "sg:postcode":"LU6 3EJ",
    "sg:province":"Bedfordshire",
    "sg:tags":[
        "tube",
        "manipulator",
        "bender"
    ],
    "wof:name":"Silkmead Tubular Ltd.",
    "wof:placetype":"venue"
},
  "geometry": {"coordinates":[-0.507891,51.876732],"type":"Point"}
}