{
  "type": "Feature",
  "properties": {
    "addr:full":"379 Kilbowie Rd Clydebank East Dunbartonshire G81 2TU",
    "addr:housenumber":"379",
    "addr:postcode":"g81 2tu",
    "addr:street":"Kilbowie Rd",
    "iso:country":"GB",
    "sg:address":"379 Kilbowie Rd",
    "sg:city":"Clydebank",
    "sg:classifiers":[
        {
            "category":"Government",
            "subcategory":"Post Office",
            "type":"Public Place"
        }
    ],
    "sg:phone":"+44 141 951 1948",
    "sg:postcode":"G81 2TU",
    "sg:province":"East Dunbartonshire",
    "wof:name":"Radnor Park Post Office",
    "wof:placetype":"venue"
},
  "geometry": {"coordinates":[-4.3972887993,55.9060211182],"type":"Point"}
}