{
  "type": "Feature",
  "properties": {
    "addr:full":"Norton Farm Holsworthy Cornwall EX22 7EL",
    "addr:housenumber":"holsworthy",
    "addr:postcode":"ex22 7el",
    "addr:street":"Norton",
    "iso:country":"GB",
    "sg:address":"Norton Farm",
    "sg:city":"Holsworthy",
    "sg:classifiers":[
        {
            "category":"Farming",
            "subcategory":"Dairy Farm",
            "type":"Manufacturing & Wholesale Goods"
        }
    ],
    "sg:phone":"+44 1288 381470",
    "sg:postcode":"EX22 7EL",
    "sg:province":"Cornwall",
    "sg:tags":[
        "farmer"
    ],
    "wof:name":"R A J Nokes",
    "wof:placetype":"venue"
},
  "geometry": {"coordinates":[-4.334923,50.849064],"type":"Point"}
}