{
  "type": "Feature",
  "properties": {
    "iso:country":"GB",
    "sg:address":"84 Offerton Lane",
    "sg:city":"Stockport",
    "sg:classifiers":[
        {
            "category":"Bars & Pubs",
            "type":"Food & Drink"
        },
        {
            "category":"Community Center",
            "subcategory":"Social",
            "type":"Public Place"
        }
    ],
    "sg:phone":"+44 161 483 1568",
    "sg:postcode":"SK2 5BS",
    "sg:province":"Cheshire",
    "sg:tags":[
        "pubs",
        "house",
        "inn",
        "activity"
    ],
    "wof:name":"The Strawberry Gardens",
    "wof:placetype":"venue"
},
  "geometry": {"coordinates":[-2.1321101189,53.4023132324],"type":"Point"}
}