{
  "type": "Feature",
  "properties": {
    "iso:country":"GB",
    "sg:address":"St Francis, Great Doward",
    "sg:city":"Ross-on-wye",
    "sg:classifiers":[
        {
            "category":"Shopping",
            "subcategory":"Books",
            "type":"Retail Goods"
        }
    ],
    "sg:phone":"+44 1600 890878",
    "sg:postcode":"HR9 6DY",
    "sg:province":"Gloucestershire",
    "sg:tags":[
        "second-hand"
    ],
    "wof:name":"John Bevan Bookseller",
    "wof:placetype":"venue"
},
  "geometry": {"coordinates":[-2.5817329884,51.9164810181],"type":"Point"}
}