{
  "type": "Feature",
  "properties": {
    "addr:full":"384 Garratt Lane London Greater London SW18 4HP",
    "addr:housenumber":"384",
    "addr:postcode":"sw18 4hp",
    "addr:street":"Garratt Lane",
    "iso:country":"GB",
    "sg:address":"384 Garratt Lane",
    "sg:city":"London",
    "sg:classifiers":[
        {
            "category":"Banks & Credit Unions",
            "subcategory":"Financial Services",
            "type":"Services"
        }
    ],
    "sg:postcode":"SW18 4HP",
    "sg:province":"Greater London",
    "sg:tags":[
        "consultant"
    ],
    "wof:name":"Southbound Investments Ltd",
    "wof:placetype":"venue"
},
  "geometry": {"coordinates":[-0.18727,51.441048],"type":"Point"}
}