{
  "type": "Feature",
  "properties": {
    "addr:full":"72 Coniger Road London Greater London SW6 3TA",
    "addr:housenumber":"72",
    "addr:postcode":"sw6 3ta",
    "addr:street":"Coniger Road",
    "iso:country":"GB",
    "sg:address":"72 Coniger Road",
    "sg:city":"London",
    "sg:classifiers":[
        {
            "category":"Real Estate",
            "subcategory":"Real Estate Agent",
            "type":"Services"
        }
    ],
    "sg:phone":"+44 20 7736 3226",
    "sg:postcode":"SW6 3TA",
    "sg:province":"Greater London",
    "wof:name":"Shipley Properties Ltd.",
    "wof:placetype":"venue"
},
  "geometry": {"coordinates":[-0.197844997,51.4711036682],"type":"Point"}
}