{
  "type": "Feature",
  "properties": {
    "iso:country":"GB",
    "sg:address":"16 Richmond Way",
    "sg:city":"Wirral",
    "sg:classifiers":[
        {
            "category":"Professional",
            "subcategory":"Engineering",
            "type":"Services"
        }
    ],
    "sg:phone":"+44 151 342 7158",
    "sg:postcode":"CH61 6XH",
    "sg:province":"Merseyside",
    "sg:tags":[
        "contractor",
        "electrical",
        "engineer"
    ],
    "wof:name":"Richmond Electrical Services",
    "wof:placetype":"venue"
},
  "geometry": {"coordinates":[-3.100376,53.337555],"type":"Point"}
}