{
  "type": "Feature",
  "properties": {
    "addr:full":"Rainbow House, 36 Smith Grove Crewe Cheshire CW1 3NB",
    "addr:housenumber":"36",
    "addr:postcode":"cw1 3nb",
    "addr:street":"Smith Grove",
    "iso:country":"GB",
    "sg:address":"Rainbow House, 36 Smith Grove",
    "sg:city":"Crewe",
    "sg:classifiers":[
        {
            "category":"Organizations",
            "subcategory":"Non-profit Organization",
            "type":"Services"
        }
    ],
    "sg:phone":"+44 1270 588399",
    "sg:postcode":"CW1 3NB",
    "sg:province":"Cheshire",
    "sg:tags":[
        "charitable",
        "organisation",
        "voluntary",
        "charity"
    ],
    "wof:name":"Nspcc",
    "wof:placetype":"venue"
},
  "geometry": {"coordinates":[-2.463712,53.10733],"type":"Point"}
}