{
  "type": "Feature",
  "properties": {
    "addr:full":"Unit A1-2 Monmouth Trading Centre, Monmouth Street Bridgwater Somerset TA6 5EQ",
    "addr:housenumber":"a1-2",
    "addr:postcode":"ta6 5eq",
    "addr:street":"Monmouth Street",
    "iso:country":"GB",
    "sg:address":"Unit A1-2 Monmouth Trading Centre, Monmouth Street",
    "sg:city":"Bridgwater",
    "sg:classifiers":[
        {
            "category":"Retail",
            "subcategory":"Auto Repair",
            "type":"Services"
        }
    ],
    "sg:phone":"+44 1278 429752",
    "sg:postcode":"TA6 5EQ",
    "sg:province":"Somerset",
    "sg:tags":[
        "modification",
        "garage"
    ],
    "wof:name":"G B Auto Repairs",
    "wof:placetype":"venue"
},
  "geometry": {"coordinates":[-3.013824,51.127556],"type":"Point"}
}