{
  "type": "Feature",
  "properties": {
    "iso:country":"GB",
    "sg:address":"8 Dixon Drive",
    "sg:city":"Weybridge",
    "sg:classifiers":[
        {
            "category":"Professional",
            "subcategory":"Computer Services",
            "type":"Services"
        }
    ],
    "sg:postcode":"KT13 0XJ",
    "sg:province":"Surrey",
    "sg:tags":[
        "system",
        "software"
    ],
    "wof:name":"Competitive Stance Ltd",
    "wof:placetype":"venue"
},
  "geometry": {"coordinates":[-0.4663639963,51.3474807739],"type":"Point"}
}