{
  "type": "Feature",
  "properties": {
    "iso:country":"GB",
    "sg:address":"Main Street",
    "sg:city":"Wigan",
    "sg:classifiers":[
        {
            "category":"Bars & Pubs",
            "type":"Food & Drink"
        }
    ],
    "sg:phone":"+44 1744 602600",
    "sg:postcode":"WN5 7PA",
    "sg:province":"Lancashire",
    "sg:tags":[
        "pubs",
        "inn"
    ],
    "wof:name":"Burtonwood Brewery Plc",
    "wof:placetype":"venue"
},
  "geometry": {"coordinates":[-2.704374,53.503105],"type":"Point"}
}