{
  "type": "Feature",
  "properties": {
    "iso:country":"GB",
    "sg:address":"C/o St Bartholomews Hospital, New Road",
    "sg:city":"Rochester",
    "sg:classifiers":[
        {
            "category":"Health Services",
            "subcategory":"Clinic",
            "type":"Services"
        }
    ],
    "sg:postcode":"ME1 1DS",
    "sg:province":"Kent",
    "sg:tags":[
        "nh"
    ],
    "wof:name":"North Kent Healthcare N H S Trust",
    "wof:placetype":"venue"
},
  "geometry": {"coordinates":[0.516225,51.382889],"type":"Point"}
}