{
  "type": "Feature",
  "properties": {
    "iso:country":"GB",
    "sg:address":"27 Craven Ct",
    "sg:city":"Warrington",
    "sg:classifiers":[
        {
            "category":"Home & Garden",
            "subcategory":"Household Appliances",
            "type":"Retail Goods"
        }
    ],
    "sg:phone":"+44 1925 243883",
    "sg:postcode":"WA2 8QU",
    "sg:province":"Cheshire",
    "sg:tags":[
        "electrical"
    ],
    "wof:name":"C T C Refrigeration Services",
    "wof:placetype":"venue"
},
  "geometry": {"coordinates":[-2.607934,53.420422],"type":"Point"}
}