{
  "type": "Feature",
  "properties": {
    "addr:full":"70 High St Burntisland Fife KY3 0SW",
    "addr:housenumber":"70",
    "addr:postcode":"ky3 0sw",
    "addr:street":"High St",
    "iso:country":"GB",
    "sg:address":"70 High St",
    "sg:city":"Burntisland",
    "sg:classifiers":[
        {
            "category":"Professional",
            "subcategory":"Business Services",
            "type":"Services"
        }
    ],
    "sg:phone":"+44 1383 860870",
    "sg:postcode":"KY3 0SW",
    "sg:province":"Fife",
    "sg:tags":[
        "import",
        "export",
        "agent"
    ],
    "wof:name":"Claim Title Ltd",
    "wof:placetype":"venue"
},
  "geometry": {"coordinates":[-3.3032469749,56.0534820557],"type":"Point"}
}