{
  "type": "Feature",
  "properties": {
    "iso:country":"GB",
    "sg:address":"Office One, 40 Oakfield",
    "sg:city":"Sale",
    "sg:classifiers":[
        {
            "category":"Insurance",
            "subcategory":"Insurance Agent",
            "type":"Services"
        }
    ],
    "sg:phone":"+44 20 8597 8100",
    "sg:postcode":"M33 6WD",
    "sg:province":"Cheshire",
    "wof:name":"Bookingdirectory.Com",
    "wof:placetype":"venue"
},
  "geometry": {"coordinates":[-2.320417,53.425949],"type":"Point"}
}