{
  "type": "Feature",
  "properties": {
    "iso:country":"GB",
    "sg:address":"63a High St",
    "sg:city":"Bridgnorth",
    "sg:classifiers":[
        {
            "category":"Home & Garden",
            "subcategory":"Furniture",
            "type":"Retail Goods"
        }
    ],
    "sg:postcode":"WV16 4DX",
    "sg:province":"Shropshire",
    "wof:name":"Mansfield,Alan M J,",
    "wof:placetype":"venue"
},
  "geometry": {"coordinates":[-2.419525,52.535702],"type":"Point"}
}