{
  "type": "Feature",
  "properties": {
    "addr:full":"16 Market Pl Nottingham Derbyshire NG10 1LT",
    "addr:housenumber":"16",
    "addr:postcode":"ng10 1lt",
    "addr:street":"Market Pl",
    "iso:country":"GB",
    "sg:address":"16 Market Pl",
    "sg:city":"Nottingham",
    "sg:classifiers":[
        {
            "category":"Shopping",
            "subcategory":"Shoes",
            "type":"Retail Goods"
        }
    ],
    "sg:postcode":"NG10 1LT",
    "sg:province":"Derbyshire",
    "sg:tags":[
        "shop"
    ],
    "wof:name":"Nella Shoes Ltd",
    "wof:placetype":"venue"
},
  "geometry": {"coordinates":[-1.2707109451,52.89793396],"type":"Point"}
}