{
  "type": "Feature",
  "properties": {
    "addr:full":"Unit 3 Soaphouse Industrial Esta, Te Bristol City of Bristol BS5 7AZ",
    "addr:housenumber":"unit 3",
    "addr:postcode":"bs5 7az",
    "addr:street":"Soaphouse Industrial Esta Te",
    "iso:country":"GB",
    "sg:address":"Unit 3 Soaphouse Industrial Esta, Te",
    "sg:city":"Bristol",
    "sg:classifiers":[
        {
            "category":"Wholesale",
            "subcategory":"Scrap",
            "type":"Manufacturing & Wholesale Goods"
        }
    ],
    "sg:phone":"+44 117 955 6682",
    "sg:postcode":"BS5 7AZ",
    "sg:province":"City of Bristol",
    "sg:tags":[
        "waste",
        "metal"
    ],
    "wof:name":"Waste Compaction Services",
    "wof:placetype":"venue"
},
  "geometry": {"coordinates":[-2.54568,51.463879],"type":"Point"}
}