{
  "type": "Feature",
  "properties": {
    "addr:full":"1/2 Foremans Walk, High Street, Headcorn Ashford Kent TN27 9NE",
    "addr:housenumber":"1 / 2",
    "addr:postcode":"tn27 9ne",
    "addr:street":"Foremans Walk High Street",
    "iso:country":"GB",
    "sg:address":"1/2 Foremans Walk, High Street, Headcorn",
    "sg:city":"Ashford",
    "sg:classifiers":[
        {
            "category":"Professional",
            "subcategory":"Computer Services",
            "type":"Services"
        }
    ],
    "sg:phone":"+44 1622 891584",
    "sg:postcode":"TN27 9NE",
    "sg:province":"Kent",
    "sg:tags":[
        "system",
        "software"
    ],
    "wof:name":"Abbey Computer Services Ltd.",
    "wof:placetype":"venue"
},
  "geometry": {"coordinates":[0.63093,51.166901],"type":"Point"}
}