{
  "type": "Feature",
  "properties": {
    "addr:full":"5 Lichfield Street Stone Staffordshire ST15 8NA",
    "addr:housenumber":"5",
    "addr:postcode":"st15 8na",
    "addr:street":"Lichfield Street",
    "iso:country":"GB",
    "sg:address":"5 Lichfield Street",
    "sg:city":"Stone",
    "sg:classifiers":[
        {
            "category":"Shopping",
            "subcategory":"Thrift Store",
            "type":"Retail Goods"
        }
    ],
    "sg:phone":"+44 1785 818858",
    "sg:postcode":"ST15 8NA",
    "sg:province":"Staffordshire",
    "sg:tags":[
        "shop",
        "charity"
    ],
    "wof:name":"Shelter Shop",
    "wof:placetype":"venue"
},
  "geometry": {"coordinates":[-2.145106,52.901299],"type":"Point"}
}