{
  "type": "Feature",
  "properties": {
    "addr:full":"The Loft 60 George Street, Ringway, Bedworth Nuneaton Warwickshire CV12 8EB",
    "addr:housenumber":"60",
    "addr:postcode":"cv12 8eb",
    "addr:street":"George Street",
    "iso:country":"GB",
    "sg:address":"The Loft 60 George Street, Ringway, Bedworth",
    "sg:city":"Nuneaton",
    "sg:classifiers":[
        {
            "category":"Real Estate",
            "subcategory":"Architect",
            "type":"Services"
        }
    ],
    "sg:phone":"+44 24 7631 1113",
    "sg:postcode":"CV12 8EB",
    "sg:province":"Warwickshire",
    "wof:name":"Keith Corrigan",
    "wof:placetype":"venue"
},
  "geometry": {"coordinates":[-1.4718739986,52.4781494141],"type":"Point"}
}