{
  "type": "Feature",
  "properties": {
    "iso:country":"GB",
    "sg:address":"31 High Street",
    "sg:city":"Leeds",
    "sg:classifiers":[
        {
            "category":"Retail",
            "subcategory":"Auto Repair",
            "type":"Services"
        }
    ],
    "sg:postcode":"LS25 7AF",
    "sg:province":"North Yorkshire",
    "sg:tags":[
        "modification",
        "garage"
    ],
    "wof:name":"Smith & Gummerson",
    "wof:placetype":"venue"
},
  "geometry": {"coordinates":[-1.3688089848,53.7668113708],"type":"Point"}
}