{
  "type": "Feature",
  "properties": {
    "iso:country":"GB",
    "sg:address":"59 High Street, Odiham",
    "sg:city":"Hook",
    "sg:classifiers":[
        {
            "category":"Health Services",
            "subcategory":"Health Practitioner",
            "type":"Services"
        }
    ],
    "sg:postcode":"RG29 1LF",
    "sg:province":"Hampshire",
    "sg:tags":[
        "osteopath"
    ],
    "wof:name":"Christina Hood",
    "wof:placetype":"venue"
},
  "geometry": {"coordinates":[-0.9386979938,51.2540397644],"type":"Point"}
}