{
  "type": "Feature",
  "properties": {
    "iso:country":"GB",
    "sg:address":"Hill Farm, Thurstaston Rd",
    "sg:city":"Wirral",
    "sg:classifiers":[
        {
            "category":"Farming",
            "subcategory":"Livestock Farm",
            "type":"Manufacturing & Wholesale Goods"
        }
    ],
    "sg:phone":"+44 151 648 1350",
    "sg:postcode":"CH61 0HQ",
    "sg:province":"Merseyside",
    "sg:tags":[
        "others"
    ],
    "wof:name":"D R Roberts",
    "wof:placetype":"venue"
},
  "geometry": {"coordinates":[-3.128288,53.354492],"type":"Point"}
}