{
  "type": "Feature",
  "properties": {
    "iso:country":"GB",
    "sg:address":"Cwm Cynon Business Centre",
    "sg:city":"Mountain Ash",
    "sg:classifiers":[
        {
            "category":"Professional",
            "subcategory":"Computer Services",
            "type":"Services"
        }
    ],
    "sg:phone":"+44 1443 477757",
    "sg:postcode":"CF45 4ER",
    "sg:province":"Rhondda, Cynon, Taff",
    "sg:tags":[
        "system",
        "software"
    ],
    "wof:name":"Miracle Information Services Ltd.",
    "wof:placetype":"venue"
},
  "geometry": {"coordinates":[-3.378964,51.684399],"type":"Point"}
}