{
  "type": "Feature",
  "properties": {
    "addr:full":"76 Acacia Avenue Hornchurch Essex RM12 4EN",
    "addr:housenumber":"76",
    "addr:postcode":"rm12 4en",
    "addr:street":"Acacia Avenue",
    "iso:country":"GB",
    "sg:address":"76 Acacia Avenue",
    "sg:city":"Hornchurch",
    "sg:classifiers":[
        {
            "category":"Professional",
            "subcategory":"Computer Services",
            "type":"Services"
        }
    ],
    "sg:postcode":"RM12 4EN",
    "sg:province":"Essex",
    "sg:tags":[
        "consultant"
    ],
    "wof:name":"Kim Com Associates Ltd",
    "wof:placetype":"venue"
},
  "geometry": {"coordinates":[0.1904090047,51.5566596985],"type":"Point"}
}