{
  "type": "Feature",
  "properties": {
    "iso:country":"GB",
    "sg:address":"Unit 3 Bently Park, Blacknest",
    "sg:city":"Alton",
    "sg:classifiers":[
        {
            "category":"Professional",
            "subcategory":"Engineering",
            "type":"Services"
        },
        {
            "category":"Utilities",
            "subcategory":"Natural Gas",
            "type":"Services"
        }
    ],
    "sg:phone":"+44 1420 23256",
    "sg:postcode":"GU34 4PX",
    "sg:province":"Hampshire",
    "sg:tags":[
        "consultant",
        "electrical",
        "contractor",
        "air conditioning",
        "engineer"
    ],
    "wof:name":"D.L Electrical",
    "wof:placetype":"venue"
},
  "geometry": {"coordinates":[-0.8598300219,51.1672706604],"type":"Point"}
}