{
  "type": "Feature",
  "properties": {
    "iso:country":"GB",
    "sg:address":"1 Stoke Road, Aston Fields",
    "sg:city":"Bromsgrove",
    "sg:classifiers":[
        {
            "category":"Shopping",
            "subcategory":"News",
            "type":"Retail Goods"
        },
        {
            "category":"Food & Beverages",
            "subcategory":"Groceries & Convenience Stores",
            "type":"Retail Goods"
        }
    ],
    "sg:phone":"+44 1527 872576",
    "sg:postcode":"B60 3EQ",
    "sg:province":"Worcestershire",
    "sg:tags":[
        "newsagent"
    ],
    "wof:name":"BALFOUR NEWS",
    "wof:placetype":"venue"
},
  "geometry": {"coordinates":[-2.048502,52.323067],"type":"Point"}
}