{
  "type": "Feature",
  "properties": {
    "addr:full":"Elnor Street, Langley Mill Nottingham Derbyshire NG16 4AP",
    "addr:postcode":"ng16 4ap",
    "addr:street":"Elnor Street",
    "iso:country":"GB",
    "sg:address":"Elnor Street, Langley Mill",
    "sg:city":"Nottingham",
    "sg:classifiers":[
        {
            "category":"Professional",
            "subcategory":"Engineering",
            "type":"Services"
        }
    ],
    "sg:phone":"+44 1773 760332",
    "sg:postcode":"NG16 4AP",
    "sg:province":"Derbyshire",
    "sg:tags":[
        "contractor",
        "electrical",
        "engineer"
    ],
    "wof:name":"Slater Electrical Services Ltd.",
    "wof:placetype":"venue"
},
  "geometry": {"coordinates":[-1.3289849758,53.0185165405],"type":"Point"}
}