{
  "type": "Feature",
  "properties": {
    "addr:full":"Tudway Road London Greater London SE3 9YX",
    "addr:postcode":"se3 9yx",
    "addr:street":"Tudway Road",
    "iso:country":"GB",
    "sg:address":"Tudway Road",
    "sg:city":"London",
    "sg:classifiers":[
        {
            "category":"Education",
            "subcategory":"School",
            "type":"Public Place"
        },
        {
            "category":"Government",
            "subcategory":"Office",
            "type":"Public Place"
        }
    ],
    "sg:phone":"+44 20 8856 2708",
    "sg:postcode":"SE3 9YX",
    "sg:province":"Greater London",
    "sg:tags":[
        "local",
        "authority"
    ],
    "wof:name":"Holy Family Rc Primary School",
    "wof:placetype":"venue"
},
  "geometry": {"coordinates":[0.0276350006,51.456905365],"type":"Point"}
}