{
  "type": "Feature",
  "properties": {
    "addr:full":"Unit 4  16 Cross Street Leamington Spa Warwickshire CV32 4PX",
    "addr:housenumber":"unit;16",
    "addr:postcode":"cv32 4px",
    "addr:street":"Cross Street",
    "iso:country":"GB",
    "sg:address":"Unit 4  16 Cross Street",
    "sg:city":"Leamington Spa",
    "sg:classifiers":[
        {
            "category":"Professional",
            "subcategory":"Art Services",
            "type":"Services"
        }
    ],
    "sg:postcode":"CV32 4PX",
    "sg:province":"Warwickshire",
    "sg:tags":[
        "consultant",
        "design"
    ],
    "wof:name":"Perceptions Design & Pr Ltd",
    "wof:placetype":"venue"
},
  "geometry": {"coordinates":[-1.529381,52.291767],"type":"Point"}
}