{
  "type": "Feature",
  "properties": {
    "iso:country":"GB",
    "sg:address":"Tilgate Way",
    "sg:city":"Crawley",
    "sg:classifiers":[
        {
            "category":"Health Services",
            "subcategory":"Doctor",
            "type":"Services"
        }
    ],
    "sg:phone":"+44 1293 525204",
    "sg:postcode":"RH10 5BS",
    "sg:province":"Surrey",
    "sg:tags":[
        "practitioners"
    ],
    "wof:name":"Greengrass, A",
    "wof:placetype":"venue"
},
  "geometry": {"coordinates":[-0.1847140044,51.1042137146],"type":"Point"}
}