{
  "type": "Feature",
  "properties": {
    "addr:full":"48a Kirk Gate Newark Nottinghamshire NG24 1AB",
    "addr:housenumber":"48a",
    "addr:postcode":"ng24 1ab",
    "addr:street":"Kirk Gate",
    "iso:country":"GB",
    "sg:address":"48a Kirk Gate",
    "sg:city":"Newark",
    "sg:classifiers":[
        {
            "category":"Home & Garden",
            "subcategory":"Home Furnishings",
            "type":"Retail Goods"
        }
    ],
    "sg:phone":"+44 1636 700369",
    "sg:postcode":"NG24 1AB",
    "sg:province":"Nottinghamshire",
    "sg:tags":[
        "awning",
        "canopy",
        "blinds"
    ],
    "wof:name":"The Venetian Blind Centre",
    "wof:placetype":"venue"
},
  "geometry": {"coordinates":[-0.8088480234,53.0769577026],"type":"Point"}
}