{
  "type": "Feature",
  "properties": {
    "addr:full":"Unit 13 Northpoint Business Estate, Enterprise Close Rochester Kent ME2 4LX",
    "addr:housenumber":"unit 13",
    "addr:postcode":"me2 4lx",
    "addr:street":"Enterprise Close",
    "iso:country":"GB",
    "sg:address":"Unit 13 Northpoint Business Estate, Enterprise Close",
    "sg:city":"Rochester",
    "sg:classifiers":[
        {
            "category":"Professional",
            "subcategory":"Printing & Photocopies",
            "type":"Services"
        }
    ],
    "sg:phone":"+44 1634 720735",
    "sg:postcode":"ME2 4LX",
    "sg:province":"Kent",
    "sg:tags":[
        "print",
        "finisher"
    ],
    "wof:name":"Triblade Ltd.",
    "wof:placetype":"venue"
},
  "geometry": {"coordinates":[0.4887830019,51.3963699341],"type":"Point"}
}