{
  "type": "Feature",
  "properties": {
    "iso:country":"GB",
    "sg:address":"215 Manningham Lane",
    "sg:city":"Bradford",
    "sg:classifiers":[
        {
            "category":"Retail",
            "subcategory":"Laundry & Dry Cleaning",
            "type":"Services"
        }
    ],
    "sg:phone":"+44 1274 822707",
    "sg:postcode":"BD8 7HH",
    "sg:province":"West Yorkshire",
    "sg:tags":[
        "alteration"
    ],
    "wof:name":"Bellevue Dry Cleaners",
    "wof:placetype":"venue"
},
  "geometry": {"coordinates":[-1.763026,53.80452],"type":"Point"}
}