{
  "type": "Feature",
  "properties": {
    "iso:country":"GB",
    "sg:address":"Kad House, Portsmouth Road",
    "sg:city":"Esher",
    "sg:classifiers":[
        {
            "category":"Professional",
            "subcategory":"Computer Services",
            "type":"Services"
        }
    ],
    "sg:phone":"+44 1374 78478",
    "sg:postcode":"KT10 9AD",
    "sg:province":"Surrey",
    "sg:tags":[
        "system",
        "software"
    ],
    "wof:name":"Baxdata Ltd.",
    "wof:placetype":"venue"
},
  "geometry": {"coordinates":[-0.3488140106,51.3782691956],"type":"Point"}
}