{
  "type": "Feature",
  "properties": {
    "addr:full":"6 Warbreck Dr Blackpool Lancashire FY2 9SZ",
    "addr:housenumber":"6",
    "addr:postcode":"fy2 9sz",
    "addr:street":"Warbreck Dr",
    "iso:country":"GB",
    "sg:address":"6 Warbreck Dr",
    "sg:city":"Blackpool",
    "sg:classifiers":[
        {
            "category":"Building & Trades",
            "subcategory":"Construction",
            "type":"Services"
        }
    ],
    "sg:phone":"+44 1253 594911",
    "sg:postcode":"FY2 9SZ",
    "sg:province":"Lancashire",
    "sg:tags":[
        "flooring"
    ],
    "wof:name":"Secker D",
    "wof:placetype":"venue"
},
  "geometry": {"coordinates":[-3.051073,53.83543],"type":"Point"}
}