{
  "type": "Feature",
  "properties": {
    "iso:country":"GB",
    "sg:address":"Cornfield Terrace",
    "sg:city":"St Leonards-on-sea",
    "sg:classifiers":[
        {
            "category":"Social Services",
            "subcategory":"Retirement Home",
            "type":"Services"
        },
        {
            "category":"Organizations",
            "subcategory":"Non-profit Organization",
            "type":"Services"
        }
    ],
    "sg:phone":"+44 1424 439103",
    "sg:postcode":"TN37 6JD",
    "sg:province":"East Sussex",
    "sg:tags":[
        "residential",
        "organisation",
        "charity",
        "voluntary",
        "care"
    ],
    "wof:name":"Streatfield Ho",
    "wof:placetype":"venue"
},
  "geometry": {"coordinates":[0.5597689748,50.8614196777],"type":"Point"}
}