{
  "type": "Feature",
  "properties": {
    "addr:full":"1 Speed Road, Barnfield Industrial Estate Tipton West Midlands DY4 9DJ",
    "addr:housenumber":"1",
    "addr:postcode":"dy4 9dj",
    "addr:street":"Speed Road Barnfield Industrial Estate Tipton",
    "iso:country":"GB",
    "sg:address":"1 Speed Road, Barnfield Industrial Estate",
    "sg:city":"Tipton",
    "sg:classifiers":[
        {
            "category":"Manufacturing",
            "subcategory":"Glass & Minerals",
            "type":"Manufacturing & Wholesale Goods"
        },
        {
            "category":"Manufacturing",
            "subcategory":"Pottery",
            "type":"Manufacturing & Wholesale Goods"
        }
    ],
    "sg:phone":"+44 121 557 2208",
    "sg:postcode":"DY4 9DJ",
    "sg:province":"West Midlands",
    "sg:tags":[
        "mnfr",
        "glassware",
        "china"
    ],
    "wof:name":"Chatsworth Porcelain",
    "wof:placetype":"venue"
},
  "geometry": {"coordinates":[-2.071334,52.53548],"type":"Point"}
}