{
  "type": "Feature",
  "properties": {
    "addr:full":"Whitelands Cottages, Kington Langley Chippenham Wiltshire SN15 5PD",
    "addr:postcode":"sn15 5pd",
    "iso:country":"GB",
    "sg:address":"Whitelands Cottages, Kington Langley",
    "sg:city":"Chippenham",
    "sg:classifiers":[
        {
            "category":"Building & Trades",
            "subcategory":"Landscaping Services",
            "type":"Services"
        },
        {
            "category":"Professional",
            "subcategory":"Employment Agencies",
            "type":"Services"
        }
    ],
    "sg:phone":"+44 1249 750151",
    "sg:postcode":"SN15 5PD",
    "sg:province":"Wiltshire",
    "sg:tags":[
        "agricultural",
        "advice"
    ],
    "wof:name":"M D & V S Sealy",
    "wof:placetype":"venue"
},
  "geometry": {"coordinates":[-2.114341,51.489937],"type":"Point"}
}