{
  "type": "Feature",
  "properties": {
    "iso:country":"GB",
    "sg:address":"338 Streatham High Road",
    "sg:city":"London",
    "sg:classifiers":[
        {
            "category":"Government",
            "subcategory":"Post Office",
            "type":"Public Place"
        }
    ],
    "sg:phone":"+44 20 8776 8776",
    "sg:postcode":"SW16 6HH",
    "sg:province":"Greater London",
    "sg:tags":[
        "print",
        "typesetter"
    ],
    "wof:name":"338 Computers Ltd.",
    "wof:placetype":"venue"
},
  "geometry": {"coordinates":[-0.13136,51.427021],"type":"Point"}
}