{
  "type": "Feature",
  "properties": {
    "addr:full":"153-155 Albany Road Cardiff Cardiff CF24 3NT",
    "addr:housenumber":"153-155",
    "addr:postcode":"cf24 3nt",
    "addr:street":"Albany Road",
    "iso:country":"GB",
    "sg:address":"153-155 Albany Road",
    "sg:city":"Cardiff",
    "sg:classifiers":[
        {
            "category":"Professional",
            "subcategory":"Engineering",
            "type":"Services"
        }
    ],
    "sg:postcode":"CF24 3NT",
    "sg:province":"Cardiff",
    "sg:tags":[
        "contractor",
        "electrical",
        "engineer"
    ],
    "wof:name":"K H Baynton & Son (Electrical Contractors) Ltd.",
    "wof:placetype":"venue"
},
  "geometry": {"coordinates":[-3.1637599468,51.4942626953],"type":"Point"}
}