{
  "type": "Feature",
  "properties": {
    "addr:full":"92 Green Lane Road Leicester Leicestershire LE5 3TJ",
    "addr:housenumber":"92",
    "addr:postcode":"le5 3tj",
    "addr:street":"Green Lane Road",
    "iso:country":"GB",
    "sg:address":"92 Green Lane Road",
    "sg:city":"Leicester",
    "sg:classifiers":[
        {
            "category":"Shopping",
            "subcategory":"Clothing, Apparel, & Fashions",
            "type":"Retail Goods"
        }
    ],
    "sg:phone":"+44 116 262 3641",
    "sg:postcode":"LE5 3TJ",
    "sg:province":"Leicestershire",
    "sg:tags":[
        "menswear"
    ],
    "wof:name":"SUPEDA MENSWEAR",
    "wof:placetype":"venue"
},
  "geometry": {"coordinates":[-1.103676,52.639301],"type":"Point"}
}