{
  "type": "Feature",
  "properties": {
    "addr:full":"Cheetall Farm, Clitheroe Road, Bashall Eaves Clitheroe Lancashire BB7 3LH",
    "addr:postcode":"bb7 3lh",
    "addr:street":"Clitheroe Road",
    "iso:country":"GB",
    "sg:address":"Cheetall Farm, Clitheroe Road, Bashall Eaves",
    "sg:city":"Clitheroe",
    "sg:classifiers":[
        {
            "category":"Farming",
            "subcategory":"Dairy Farm",
            "type":"Manufacturing & Wholesale Goods"
        }
    ],
    "sg:phone":"+44 1200 422693",
    "sg:postcode":"BB7 3LH",
    "sg:province":"Lancashire",
    "sg:tags":[
        "farmer"
    ],
    "wof:name":"J R Drinkall & Sons",
    "wof:placetype":"venue"
},
  "geometry": {"coordinates":[-2.4640040398,53.8850440979],"type":"Point"}
}