{
  "type": "Feature",
  "properties": {
    "addr:full":"154 Staincliffe Road Dewsbury West Yorkshire WF13 4RH",
    "addr:housenumber":"154",
    "addr:postcode":"wf13 4rh",
    "addr:street":"Staincliffe Road",
    "iso:country":"GB",
    "sg:address":"154 Staincliffe Road",
    "sg:city":"Dewsbury",
    "sg:classifiers":[
        {
            "category":"Food & Beverages",
            "subcategory":"Liquor & Beverages",
            "type":"Retail Goods"
        }
    ],
    "sg:postcode":"WF13 4RH",
    "sg:province":"West Yorkshire",
    "sg:tags":[
        "beer",
        "spirit",
        "wines"
    ],
    "wof:name":"The Wine Cellar",
    "wof:placetype":"venue"
},
  "geometry": {"coordinates":[-1.653327,53.69957],"type":"Point"}
}