{
  "type": "Feature",
  "properties": {
    "iso:country":"GB",
    "sg:address":"57 Falkland Road",
    "sg:city":"Barnet",
    "sg:classifiers":[
        {
            "category":"Retail",
            "subcategory":"Auto Repair",
            "type":"Services"
        }
    ],
    "sg:phone":"+44 20 8447 0799",
    "sg:postcode":"EN5 4LQ",
    "sg:province":"Hertfordshire",
    "sg:tags":[
        "modification",
        "garage"
    ],
    "wof:name":"I B Autos",
    "wof:placetype":"venue"
},
  "geometry": {"coordinates":[-0.206559,51.658558],"type":"Point"}
}