{
  "type": "Feature",
  "properties": {
    "addr:full":"Valley Mills, Park Road Elland West Yorkshire HX5 9HP",
    "addr:postcode":"hx5 9hp",
    "addr:street":"Park Road",
    "iso:country":"GB",
    "sg:address":"Valley Mills, Park Road",
    "sg:city":"Elland",
    "sg:classifiers":[
        {
            "category":"Home & Garden",
            "subcategory":"Hardware",
            "type":"Retail Goods"
        }
    ],
    "sg:postcode":"HX5 9HP",
    "sg:province":"West Yorkshire",
    "sg:tags":[
        "retailer",
        "lighting"
    ],
    "wof:name":"Wilkins & Wilkinson (Elland) Ltd.",
    "wof:placetype":"venue"
},
  "geometry": {"coordinates":[-1.835879,53.686256],"type":"Point"}
}