{
  "type": "Feature",
  "properties": {
    "addr:full":"Lathkill House, Beacon Bottom, Park Gate Southampton Hampshire SO31 7GQ",
    "addr:postcode":"so31 7gq",
    "addr:street":"Bottom;Gate",
    "iso:country":"GB",
    "sg:address":"Lathkill House, Beacon Bottom, Park Gate",
    "sg:city":"Southampton",
    "sg:classifiers":[
        {
            "category":"Professional",
            "subcategory":"Business Services",
            "type":"Services"
        }
    ],
    "sg:phone":"+44 1489 575573",
    "sg:postcode":"SO31 7GQ",
    "sg:province":"Hampshire",
    "sg:tags":[
        "transfer",
        "agent",
        "broking"
    ],
    "wof:name":"Concepts International",
    "wof:placetype":"venue"
},
  "geometry": {"coordinates":[-1.269304,50.874863],"type":"Point"}
}