{
  "type": "Feature",
  "properties": {
    "iso:country":"GB",
    "sg:address":"111-115 Salisbury Road, Burton",
    "sg:city":"Christchurch",
    "sg:classifiers":[
        {
            "category":"Shopping",
            "subcategory":"News",
            "type":"Retail Goods"
        },
        {
            "category":"Government",
            "subcategory":"Post Office",
            "type":"Public Place"
        }
    ],
    "sg:phone":"+44 1202 485139",
    "sg:postcode":"BH23 7JN",
    "sg:province":"Dorset",
    "sg:tags":[
        "newsagent"
    ],
    "wof:name":"Burton News & Stores",
    "wof:placetype":"venue"
},
  "geometry": {"coordinates":[-1.764283,50.751663],"type":"Point"}
}