{
  "type": "Feature",
  "properties": {
    "iso:country":"GB",
    "sg:address":"4 Fore Street",
    "sg:city":"South Brent",
    "sg:classifiers":[
        {
            "category":"Manufacturing",
            "subcategory":"Tools & Machinery",
            "type":"Manufacturing & Wholesale Goods"
        }
    ],
    "sg:phone":"+44 1364 72939",
    "sg:postcode":"TQ10 9BQ",
    "sg:province":"Devon",
    "sg:tags":[
        "society",
        "friendly"
    ],
    "wof:name":"Roger Hind Insurance",
    "wof:placetype":"venue"
},
  "geometry": {"coordinates":[-3.834304,50.42635],"type":"Point"}
}