{
  "type": "Feature",
  "properties": {
    "iso:country":"GB",
    "sg:address":"51 A Street, Marys Road, Bearwood",
    "sg:city":"Birmingham",
    "sg:classifiers":[
        {
            "category":"Education",
            "subcategory":"Music School",
            "type":"Public Place"
        }
    ],
    "sg:postcode":"B67 5DH",
    "sg:province":"West Midlands",
    "wof:name":"The Classical Guitar Centre Ltd.",
    "wof:placetype":"venue"
},
  "geometry": {"coordinates":[-1.9744499922,52.4751205444],"type":"Point"}
}