{
  "type": "Feature",
  "properties": {
    "addr:full":"Unit 1, Parkway Court, Bilborough Nottingham Nottinghamshire NG8 4GN",
    "addr:housenumber":"unit 1",
    "addr:postcode":"ng8 4gn",
    "addr:street":"Parkway Court",
    "iso:country":"GB",
    "sg:address":"Unit 1, Parkway Court, Bilborough",
    "sg:city":"Nottingham",
    "sg:classifiers":[
        {
            "category":"Retail",
            "subcategory":"Laundry & Dry Cleaning",
            "type":"Services"
        }
    ],
    "sg:phone":"+44 115 928 1129",
    "sg:postcode":"NG8 4GN",
    "sg:province":"Nottinghamshire",
    "sg:tags":[
        "launderette"
    ],
    "wof:name":"Mr Clean",
    "wof:placetype":"venue"
},
  "geometry": {"coordinates":[-1.228364,52.958382],"type":"Point"}
}