{
  "type": "Feature",
  "properties": {
    "addr:full":"19-21 North Mall Lower Edmonton Greater London N9 0EQ",
    "addr:housenumber":"19-21",
    "addr:postcode":"n9 0eq",
    "addr:street":"North Mall",
    "iso:country":"GB",
    "sg:address":"19-21 North Mall",
    "sg:city":"Lower Edmonton",
    "sg:classifiers":[
        {
            "category":"Shopping",
            "subcategory":"Shoes",
            "type":"Retail Goods"
        }
    ],
    "sg:phone":"+44 20 8803 6690",
    "sg:postcode":"N9 0EQ",
    "sg:province":"Greater London",
    "sg:tags":[
        "shop"
    ],
    "wof:name":"Shoe Express",
    "wof:placetype":"venue"
},
  "geometry": {"coordinates":[-0.05523,51.625969],"type":"Point"}
}