{
  "type": "Feature",
  "properties": {
    "iso:country":"GB",
    "sg:address":"Somnes Avenue",
    "sg:city":"Canvey Island",
    "sg:classifiers":[
        {
            "category":"Sports & Exercise",
            "subcategory":"Golf",
            "type":"Entertainment"
        }
    ],
    "sg:phone":"+44 1268 510830",
    "sg:postcode":"SS8 9FG",
    "sg:province":"Essex",
    "sg:tags":[
        "range",
        "driving"
    ],
    "wof:name":"Castle Point Golf & Leisure Ltd.",
    "wof:placetype":"venue"
},
  "geometry": {"coordinates":[0.564718008,51.5356369019],"type":"Point"}
}