{
  "type": "Feature",
  "properties": {
    "iso:country":"GB",
    "sg:address":"The Hedges, Wyberton West Road",
    "sg:city":"Boston",
    "sg:classifiers":[
        {
            "category":"Manufacturing",
            "subcategory":"Wood Products",
            "type":"Manufacturing & Wholesale Goods"
        },
        {
            "category":"Building & Trades",
            "subcategory":"Construction",
            "type":"Services"
        }
    ],
    "sg:phone":"+44 1205 363365",
    "sg:postcode":"PE21 7LH",
    "sg:province":"Lincolnshire",
    "sg:tags":[
        "joinery",
        "manufacturer"
    ],
    "wof:name":"T Ford",
    "wof:placetype":"venue"
},
  "geometry": {"coordinates":[-0.0411290005,52.9540977478],"type":"Point"}
}