{
  "type": "Feature",
  "properties": {
    "addr:full":"22 Southern Road Bournemouth Dorset BH6 3SR",
    "addr:housenumber":"22",
    "addr:postcode":"bh6 3sr",
    "addr:street":"Southern Road",
    "iso:country":"GB",
    "sg:address":"22 Southern Road",
    "sg:city":"Bournemouth",
    "sg:classifiers":[
        {
            "category":"Travel",
            "subcategory":"Hotels & Motels",
            "type":"Entertainment"
        }
    ],
    "sg:phone":"+44 1202 428309",
    "sg:postcode":"BH6 3SR",
    "sg:province":"Dorset",
    "wof:name":"Vine Hotel",
    "wof:placetype":"venue"
},
  "geometry": {"coordinates":[-1.8159320354,50.7236099243],"type":"Point"}
}