{
  "type": "Feature",
  "properties": {
    "iso:country":"GB",
    "sg:address":"2 Arndale House, Durham Road, Birtley",
    "sg:city":"Chester Le Street",
    "sg:classifiers":[
        {
            "category":"Personal",
            "type":"Services"
        }
    ],
    "sg:phone":"+44 191 410 3148",
    "sg:postcode":"DH3 2PG",
    "sg:province":"Durham",
    "sg:tags":[
        "dressmaker"
    ],
    "wof:name":"As You Like It",
    "wof:placetype":"venue"
},
  "geometry": {"coordinates":[-1.574964,54.859135],"type":"Point"}
}