{
  "type": "Feature",
  "properties": {
    "addr:full":"Holtham Carrs Farm, Legsby Market Rasen Lincolnshire LN8 3QS",
    "addr:housenumber":"legsby",
    "addr:postcode":"ln8 3qs",
    "addr:street":"Holtham Carrs;Market Rasen",
    "iso:country":"GB",
    "sg:address":"Holtham Carrs Farm, Legsby",
    "sg:city":"Market Rasen",
    "sg:classifiers":[
        {
            "category":"Farming",
            "subcategory":"Farm",
            "type":"Manufacturing & Wholesale Goods"
        }
    ],
    "sg:phone":"+44 1673 842492",
    "sg:postcode":"LN8 3QS",
    "sg:province":"Lincolnshire",
    "sg:tags":[
        "mixed",
        "crop"
    ],
    "wof:name":"Steven Charles & Eric Charles Dixon",
    "wof:placetype":"venue"
},
  "geometry": {"coordinates":[-0.333068,53.386787],"type":"Point"}
}