{
  "type": "Feature",
  "properties": {
    "addr:full":"10-12 Mell Square Solihull West Midlands B91 3AY",
    "addr:housenumber":"10-12",
    "addr:postcode":"b91 3ay",
    "addr:street":"Mell Square",
    "iso:country":"GB",
    "sg:address":"10-12 Mell Square",
    "sg:city":"Solihull",
    "sg:classifiers":[
        {
            "category":"Shopping",
            "subcategory":"Music",
            "type":"Retail Goods"
        }
    ],
    "sg:phone":"+44 121 709 0661",
    "sg:postcode":"B91 3AY",
    "sg:province":"West Midlands",
    "sg:tags":[
        "record",
        "tape",
        "cd"
    ],
    "wof:name":"H M V U K",
    "wof:placetype":"venue"
},
  "geometry": {"coordinates":[-1.7767839432,52.4133758545],"type":"Point"}
}