{
  "type": "Feature",
  "properties": {
    "iso:country":"GB",
    "sg:address":"84 Main Street, Cleland",
    "sg:city":"Motherwell",
    "sg:classifiers":[
        {
            "category":"Building & Trades",
            "subcategory":"Construction",
            "type":"Services"
        }
    ],
    "sg:phone":"+44 1698 860715",
    "sg:postcode":"ML1 5QR",
    "sg:province":"North Lanarkshire",
    "sg:tags":[
        "builder"
    ],
    "wof:name":"John R Phillips & Sons",
    "wof:placetype":"venue"
},
  "geometry": {"coordinates":[-3.918349,55.800209],"type":"Point"}
}