{
  "type": "Feature",
  "properties": {
    "addr:full":"14 Park Avenue Whitley Bay Northumberland NE26 1DG",
    "addr:housenumber":"14",
    "addr:postcode":"ne26 1dg",
    "addr:street":"Park Avenue",
    "iso:country":"GB",
    "sg:address":"14 Park Avenue",
    "sg:city":"Whitley Bay",
    "sg:classifiers":[
        {
            "category":"Food & Beverages",
            "subcategory":"Supermarket",
            "type":"Retail Goods"
        }
    ],
    "sg:phone":"+44 191 252 1690",
    "sg:postcode":"NE26 1DG",
    "sg:province":"Northumberland",
    "wof:name":"Spar",
    "wof:placetype":"venue"
},
  "geometry": {"coordinates":[-1.446277,55.042622],"type":"Point"}
}