{
  "type": "Feature",
  "properties": {
    "addr:full":"Unit 8 London Greater London SW10 0XE",
    "addr:housenumber":"unit 8",
    "addr:postcode":"sw10 0xe",
    "iso:country":"GB",
    "sg:address":"Unit 8",
    "sg:city":"London",
    "sg:classifiers":[
        {
            "category":"Shopping",
            "subcategory":"Clothing, Apparel, & Fashions",
            "type":"Retail Goods"
        },
        {
            "category":"Shopping",
            "subcategory":"Crafts & Fabrics",
            "type":"Retail Goods"
        }
    ],
    "sg:phone":"+44 20 7351 9985",
    "sg:postcode":"SW10 0XE",
    "sg:province":"Greater London",
    "sg:tags":[
        "clothing",
        "retailer"
    ],
    "wof:name":"Abbott & Boyd Ltd.",
    "wof:placetype":"venue"
},
  "geometry": {"coordinates":[-0.1041079983,51.4979934692],"type":"Point"}
}