{
  "type": "Feature",
  "properties": {
    "addr:full":"Hawkwell Ho Oxford Oxfordshire OX4 4BZ",
    "addr:postcode":"ox4 4bz",
    "addr:street":"Hawkwell",
    "iso:country":"GB",
    "sg:address":"Hawkwell Ho",
    "sg:city":"Oxford",
    "sg:classifiers":[
        {
            "category":"Professional",
            "subcategory":"Accounting & Tax Preparation",
            "type":"Services"
        }
    ],
    "sg:phone":"+44 1865 747676",
    "sg:postcode":"OX4 4BZ",
    "sg:province":"Oxfordshire",
    "sg:tags":[
        "accountant"
    ],
    "wof:name":"Terrells Chartered Accountants",
    "wof:placetype":"venue"
},
  "geometry": {"coordinates":[-1.2321200371,51.7373085022],"type":"Point"}
}