{
  "type": "Feature",
  "properties": {
    "addr:full":"10 Bridle Way Herne Bay Kent CT6 7PQ",
    "addr:housenumber":"10",
    "addr:postcode":"ct6 7pq",
    "addr:street":"Bridle Way",
    "iso:country":"GB",
    "sg:address":"10 Bridle Way",
    "sg:city":"Herne Bay",
    "sg:classifiers":[
        {
            "category":"Real Estate",
            "subcategory":"Surveying",
            "type":"Services"
        }
    ],
    "sg:phone":"+44 1227 743363",
    "sg:postcode":"CT6 7PQ",
    "sg:province":"Kent",
    "sg:tags":[
        "surveyor",
        "valuer"
    ],
    "wof:name":"Pearce & Co",
    "wof:placetype":"venue"
},
  "geometry": {"coordinates":[1.1149280071,51.3611221313],"type":"Point"}
}