{
  "type": "Feature",
  "properties": {
    "addr:full":"26 Victoria Pl Bournemouth Dorset BH1 4SA",
    "addr:housenumber":"26",
    "addr:postcode":"bh1 4sa",
    "addr:street":"Victoria Pl",
    "iso:country":"GB",
    "sg:address":"26 Victoria Pl",
    "sg:city":"Bournemouth",
    "sg:classifiers":[
        {
            "category":"Autos & Motor Vehicles",
            "subcategory":"Automobile Sales",
            "type":"Retail Goods"
        }
    ],
    "sg:postcode":"BH1 4SA",
    "sg:province":"Dorset",
    "sg:tags":[
        "car"
    ],
    "wof:name":"Wilkes,Ian,",
    "wof:placetype":"venue"
},
  "geometry": {"coordinates":[-1.852699995,50.7292900085],"type":"Point"}
}