{
  "type": "Feature",
  "properties": {
    "addr:full":"Woodstock Rd Broxbourne Essex EN10 7NX",
    "addr:postcode":"en10 7nx",
    "addr:street":"Woodstock Rd",
    "iso:country":"GB",
    "sg:address":"Woodstock Rd",
    "sg:city":"Broxbourne",
    "sg:classifiers":[
        {
            "category":"Banks & Credit Unions",
            "subcategory":"Bank",
            "type":"Services"
        }
    ],
    "sg:phone":"+44 1992 448006",
    "sg:postcode":"EN10 7NX",
    "sg:province":"Essex",
    "sg:tags":[
        "broker",
        "mortgage"
    ],
    "wof:name":"Enfield Mortgage Services",
    "wof:placetype":"venue"
},
  "geometry": {"coordinates":[-0.0249850005,51.7532501221],"type":"Point"}
}