{
  "type": "Feature",
  "properties": {
    "addr:full":"Hennymoor Ho, 7-9 Manor Row Bradford West Yorkshire BD1 4PB",
    "addr:housenumber":"7-9",
    "addr:postcode":"bd1 4pb",
    "addr:street":"Manor Row Bradford West",
    "iso:country":"GB",
    "sg:address":"Hennymoor Ho, 7-9 Manor Row",
    "sg:city":"Bradford",
    "sg:classifiers":[
        {
            "category":"Professional",
            "subcategory":"Detective & Security Services",
            "type":"Services"
        }
    ],
    "sg:phone":"+44 1274 745554",
    "sg:postcode":"BD1 4PB",
    "sg:province":"West Yorkshire",
    "wof:name":"S E S Ltd",
    "wof:placetype":"venue"
},
  "geometry": {"coordinates":[-1.7583060265,53.7957382202],"type":"Point"}
}