{
  "type": "Feature",
  "properties": {
    "addr:full":"54 Queens Road Leicester Leicestershire LE2 1TU",
    "addr:housenumber":"54",
    "addr:postcode":"le2 1tu",
    "addr:street":"Queens Road",
    "iso:country":"GB",
    "sg:address":"54 Queens Road",
    "sg:city":"Leicester",
    "sg:classifiers":[
        {
            "category":"Restaurant",
            "type":"Food & Drink"
        }
    ],
    "sg:phone":"+44 116 270 8408",
    "sg:postcode":"LE2 1TU",
    "sg:province":"Leicestershire",
    "wof:name":"Barceloneta",
    "wof:placetype":"venue"
},
  "geometry": {"coordinates":[-1.117256,52.618595],"type":"Point"}
}