{
  "type": "Feature",
  "properties": {
    "iso:country":"GB",
    "sg:address":"Lyall Ct, Commerce Way, Maulden Road Indust Est",
    "sg:city":"Bedford",
    "sg:classifiers":[
        {
            "category":"Professional",
            "type":"Services"
        }
    ],
    "sg:phone":"+44 1525 718811",
    "sg:postcode":"MK45 1UY",
    "sg:province":"Bedfordshire",
    "sg:tags":[
        "shopfitters"
    ],
    "wof:name":"Grafton Group The",
    "wof:placetype":"venue"
},
  "geometry": {"coordinates":[-0.493642,52.000111],"type":"Point"}
}