{
  "type": "Feature",
  "properties": {
    "iso:country":"GB",
    "sg:address":"10 High St",
    "sg:city":"Galashiels",
    "sg:classifiers":[
        {
            "category":"Communications",
            "type":"Services"
        }
    ],
    "sg:postcode":"TD1 1SD",
    "sg:province":"Scottish Borders",
    "sg:tags":[
        "tv",
        "video",
        "radio"
    ],
    "wof:name":"Switched on",
    "wof:placetype":"venue"
},
  "geometry": {"coordinates":[-2.8103289604,55.6172676086],"type":"Point"}
}