{
  "type": "Feature",
  "properties": {
    "addr:full":"Unit 13 Freshwharf, Highbridge Rd Barking Essex IG11 7BG",
    "addr:housenumber":"unit 13 freshwharf",
    "addr:postcode":"ig11 7bg",
    "addr:street":"Highbridge Rd",
    "iso:country":"GB",
    "sg:address":"Unit 13 Freshwharf, Highbridge Rd",
    "sg:city":"Barking",
    "sg:classifiers":[
        {
            "category":"Professional",
            "subcategory":"Engineering",
            "type":"Services"
        }
    ],
    "sg:postcode":"IG11 7BG",
    "sg:province":"Essex",
    "sg:tags":[
        "precision",
        "engineer"
    ],
    "wof:name":"Gaur Engineering Co  Ltd",
    "wof:placetype":"venue"
},
  "geometry": {"coordinates":[0.070849,51.53434],"type":"Point"}
}