{
  "type": "Feature",
  "properties": {
    "addr:full":"Inglewood, Bowling Alley Aylesbury Buckinghamshire HP22 4HD",
    "addr:postcode":"hp22 4hd",
    "iso:country":"GB",
    "sg:address":"Inglewood, Bowling Alley",
    "sg:city":"Aylesbury",
    "sg:classifiers":[
        {
            "category":"Professional",
            "subcategory":"Accounting & Tax Preparation",
            "type":"Services"
        }
    ],
    "sg:phone":"+44 1296 641858",
    "sg:postcode":"HP22 4HD",
    "sg:province":"Buckinghamshire",
    "sg:tags":[
        "accountant"
    ],
    "wof:name":"J P Thornton & Co",
    "wof:placetype":"venue"
},
  "geometry": {"coordinates":[-0.8586400151,51.8872909546],"type":"Point"}
}