{
  "type": "Feature",
  "properties": {
    "addr:full":"28 Grove Crescent, Adlington Chorley Lancashire PR6 9RJ",
    "addr:housenumber":"28",
    "addr:postcode":"pr6 9rj",
    "addr:street":"Grove Crescent",
    "iso:country":"GB",
    "sg:address":"28 Grove Crescent, Adlington",
    "sg:city":"Chorley",
    "sg:classifiers":[
        {
            "category":"Professional",
            "subcategory":"Management & Consulting",
            "type":"Services"
        },
        {
            "category":"Professional",
            "subcategory":"Employment Agencies",
            "type":"Services"
        }
    ],
    "sg:phone":"+44 1257 483940",
    "sg:postcode":"PR6 9RJ",
    "sg:province":"Lancashire",
    "sg:tags":[
        "consultant",
        "business",
        "recruitment"
    ],
    "wof:name":"Sharples Davies Ltd.",
    "wof:placetype":"venue"
},
  "geometry": {"coordinates":[-2.6052310467,53.6161613464],"type":"Point"}
}