{
  "type": "Feature",
  "properties": {
    "iso:country":"GB",
    "sg:address":"Renown Close, Chandlers Ford Industrial Estate, Eastleigh",
    "sg:city":"Southampton",
    "sg:classifiers":[
        {
            "category":"Building & Trades",
            "subcategory":"Construction",
            "type":"Services"
        }
    ],
    "sg:phone":"+44 23 8026 7322",
    "sg:postcode":"SO53 4HZ",
    "sg:province":"Hampshire",
    "sg:tags":[
        "flooring"
    ],
    "wof:name":"Nutland Carpet Accessories Ltd.",
    "wof:placetype":"venue"
},
  "geometry": {"coordinates":[-1.393464,50.978954],"type":"Point"}
}