{
  "type": "Feature",
  "properties": {
    "addr:full":"2a Burroughs Parade Hendon Greater London NW4 4BD",
    "addr:housenumber":"2a",
    "addr:postcode":"nw4 4bd",
    "addr:street":"Burroughs Parade",
    "iso:country":"GB",
    "sg:address":"2a Burroughs Parade",
    "sg:city":"Hendon",
    "sg:classifiers":[
        {
            "category":"Restaurant",
            "type":"Food & Drink"
        }
    ],
    "sg:phone":"+44 20 8203 3028",
    "sg:postcode":"NW4 4BD",
    "sg:province":"Greater London",
    "sg:tags":[
        "oriental"
    ],
    "wof:name":"Junction 88",
    "wof:placetype":"venue"
},
  "geometry": {"coordinates":[-0.2302840054,51.5870094299],"type":"Point"}
}