{
  "type": "Feature",
  "properties": {
    "iso:country":"GB",
    "sg:address":"7 Calvert Avenue",
    "sg:city":"London",
    "sg:classifiers":[
        {
            "category":"Shopping",
            "subcategory":"Department Store",
            "type":"Retail Goods"
        }
    ],
    "sg:phone":"+44 20 7739 6505",
    "sg:postcode":"E2 7JP",
    "sg:province":"Greater London",
    "wof:name":"Duven",
    "wof:placetype":"venue"
},
  "geometry": {"coordinates":[-0.076406002,51.5263595581],"type":"Point"}
}