{
  "type": "Feature",
  "properties": {
    "addr:full":"3 Grove Terr, Union Rd Crediton Devon EX17 3AR",
    "addr:housenumber":"3",
    "addr:postcode":"ex17 3ar",
    "addr:street":"Grove Terr Union Rd",
    "iso:country":"GB",
    "sg:address":"3 Grove Terr, Union Rd",
    "sg:city":"Crediton",
    "sg:classifiers":[
        {
            "category":"Building & Trades",
            "subcategory":"Construction",
            "type":"Services"
        }
    ],
    "sg:phone":"+44 1363 772191",
    "sg:postcode":"EX17 3AR",
    "sg:province":"Devon",
    "sg:tags":[
        "decorator",
        "painter"
    ],
    "wof:name":"John Redmond",
    "wof:placetype":"venue"
},
  "geometry": {"coordinates":[-3.6561219692,50.7898902893],"type":"Point"}
}