{
  "type": "Feature",
  "properties": {
    "iso:country":"GB",
    "sg:address":"61 Woolwich New Road",
    "sg:city":"London",
    "sg:classifiers":[
        {
            "category":"Shopping",
            "subcategory":"News",
            "type":"Retail Goods"
        }
    ],
    "sg:phone":"+44 20 8854 0440",
    "sg:postcode":"SE18 6ED",
    "sg:province":"Greater London",
    "sg:tags":[
        "newsagent"
    ],
    "wof:name":"Binas Newsagents",
    "wof:placetype":"venue"
},
  "geometry": {"coordinates":[0.0676269978,51.4892692566],"type":"Point"}
}