{
  "type": "Feature",
  "properties": {
    "addr:full":"47 Princes Square, Buchanan Street Glasgow Glasgow City G1 3JN",
    "addr:housenumber":"47",
    "addr:postcode":"g1 3jn",
    "addr:street":"Princes Square Buchanan Street",
    "iso:country":"GB",
    "sg:address":"47 Princes Square, Buchanan Street",
    "sg:city":"Glasgow",
    "sg:classifiers":[
        {
            "category":"Shopping",
            "subcategory":"Gifts & Souvenirs",
            "type":"Retail Goods"
        }
    ],
    "sg:phone":"+44 141 248 6635",
    "sg:postcode":"G1 3JN",
    "sg:province":"Glasgow City",
    "sg:tags":[
        "shop"
    ],
    "wof:name":"Once A Tree Ltd.",
    "wof:placetype":"venue"
},
  "geometry": {"coordinates":[-4.242511,55.857807],"type":"Point"}
}