{
  "type": "Feature",
  "properties": {
    "addr:full":"Langley Brook Farm, London Road, Middleton Tamworth Staffordshire B78 2BP",
    "addr:postcode":"b78 2bp",
    "addr:street":"Langley Brook Farm London Road",
    "iso:country":"GB",
    "sg:address":"Langley Brook Farm, London Road, Middleton",
    "sg:city":"Tamworth",
    "sg:classifiers":[
        {
            "category":"Food & Beverages",
            "subcategory":"Groceries & Convenience Stores",
            "type":"Retail Goods"
        }
    ],
    "sg:phone":"+44 121 378 4673",
    "sg:postcode":"B78 2BP",
    "sg:province":"Staffordshire",
    "sg:tags":[
        "merchant",
        "potato"
    ],
    "wof:name":"Panda Pre-Packs (Sales) Ltd.",
    "wof:placetype":"venue"
},
  "geometry": {"coordinates":[-1.7393989563,52.5823936462],"type":"Point"}
}