{
  "type": "Feature",
  "properties": {
    "iso:country":"GB",
    "sg:address":"Friary Gardens, Victoria Road",
    "sg:city":"Richmond",
    "sg:classifiers":[
        {
            "category":"Landmark",
            "subcategory":"Tourist Information",
            "type":"Public Place"
        }
    ],
    "sg:phone":"+44 1748 850252",
    "sg:postcode":"DL10 4AJ",
    "sg:province":"North Yorkshire",
    "wof:name":"Richmond Tourist Imformation Centre",
    "wof:placetype":"venue"
},
  "geometry": {"coordinates":[-1.738664031,54.4043388367],"type":"Point"}
}