{
  "type": "Feature",
  "properties": {
    "addr:full":"38 Corse Park Road, Great Farr Birmingham West Midlands B43 5LP",
    "addr:housenumber":"38",
    "addr:postcode":"b43 5lp",
    "addr:street":"Corse Park Road;Farr",
    "iso:country":"GB",
    "sg:address":"38 Corse Park Road, Great Farr",
    "sg:city":"Birmingham",
    "sg:classifiers":[
        {
            "category":"Home & Garden",
            "subcategory":"Carpets & Floor Coverings",
            "type":"Retail Goods"
        }
    ],
    "sg:phone":"+44 121 472 3264",
    "sg:postcode":"B43 5LP",
    "sg:province":"West Midlands",
    "sg:tags":[
        "cleaner",
        "upholstery"
    ],
    "wof:name":"Cleaning & Restoration Services",
    "wof:placetype":"venue"
},
  "geometry": {"coordinates":[-1.9375699759,52.5422401428],"type":"Point"}
}