{
  "type": "Feature",
  "properties": {
    "iso:country":"GB",
    "sg:address":"Rooksfield, Bishops Green",
    "sg:city":"Newbury",
    "sg:classifiers":[
        {
            "category":"Wholesale",
            "subcategory":"Scrap",
            "type":"Manufacturing & Wholesale Goods"
        }
    ],
    "sg:phone":"+44 1635 269692",
    "sg:postcode":"RG20 9JJ",
    "sg:province":"Berkshire",
    "sg:tags":[
        "waste",
        "metal"
    ],
    "wof:name":"Lewis Rawlings",
    "wof:placetype":"venue"
},
  "geometry": {"coordinates":[-1.28251,51.361061],"type":"Point"}
}