{
  "type": "Feature",
  "properties": {
    "iso:country":"GB",
    "sg:address":"1 Carradale Crescent Broadwood, Business Park, Cumbernauld",
    "sg:city":"Glasgow",
    "sg:classifiers":[
        {
            "category":"Wholesale",
            "subcategory":"Machinery & Supplies",
            "type":"Manufacturing & Wholesale Goods"
        }
    ],
    "sg:phone":"+44 1236 781133",
    "sg:postcode":"G68 9LE",
    "sg:province":"East Dunbartonshire",
    "sg:tags":[
        "equipment",
        "pneumatic",
        "system"
    ],
    "wof:name":"Smc Pneumatics (Uk)",
    "wof:placetype":"venue"
},
  "geometry": {"coordinates":[-4.040339,55.939602],"type":"Point"}
}