{
  "type": "Feature",
  "properties": {
    "addr:full":"241 The Broadway, Wimbledon London Greater London SW19 1SD",
    "addr:housenumber":"241",
    "addr:postcode":"sw19 1sd",
    "addr:street":"The Broadway",
    "iso:country":"GB",
    "sg:address":"241 The Broadway, Wimbledon",
    "sg:city":"London",
    "sg:classifiers":[
        {
            "category":"Organizations",
            "subcategory":"Membership Organization",
            "type":"Services"
        }
    ],
    "sg:phone":"+44 20 8542 7513",
    "sg:postcode":"SW19 1SD",
    "sg:province":"Greater London",
    "sg:tags":[
        "club"
    ],
    "wof:name":"Merton Ex-Service Men's Club Ltd.",
    "wof:placetype":"venue"
},
  "geometry": {"coordinates":[-0.195575,51.419266],"type":"Point"}
}