{
  "type": "Feature",
  "properties": {
    "addr:full":"265 Ayr Road, Newton Mearns Glasgow East Ayrshire G77 6AW",
    "addr:housenumber":"265",
    "addr:postcode":"g77 6aw",
    "addr:street":"Ayr Road",
    "iso:country":"GB",
    "sg:address":"265 Ayr Road, Newton Mearns",
    "sg:city":"Glasgow",
    "sg:classifiers":[
        {
            "category":"Professional",
            "subcategory":"Management & Consulting",
            "type":"Services"
        }
    ],
    "sg:postcode":"G77 6AW",
    "sg:province":"East Ayrshire",
    "sg:tags":[
        "consultant",
        "business"
    ],
    "wof:name":"Charter Catering Consultants Ltd.",
    "wof:placetype":"venue"
},
  "geometry": {"coordinates":[-4.3393387794,55.768901825],"type":"Point"}
}