{
  "type": "Feature",
  "properties": {
    "addr:full":"26 Warsash Road, Warsash Southampton Hampshire SO31 9HX",
    "addr:housenumber":"26",
    "addr:postcode":"so31 9hx",
    "addr:street":"Warsash Road",
    "iso:country":"GB",
    "sg:address":"26 Warsash Road, Warsash",
    "sg:city":"Southampton",
    "sg:classifiers":[
        {
            "category":"Shopping",
            "subcategory":"Pharmacy",
            "type":"Retail Goods"
        }
    ],
    "sg:phone":"+44 1489 573001",
    "sg:postcode":"SO31 9HX",
    "sg:province":"Hampshire",
    "sg:tags":[
        "pharmacist",
        "chemist"
    ],
    "wof:name":"H J Everett Chemist",
    "wof:placetype":"venue"
},
  "geometry": {"coordinates":[-1.296493,50.853081],"type":"Point"}
}