{
  "type": "Feature",
  "properties": {
    "iso:country":"GB",
    "sg:address":"Market Pl, 67 High St",
    "sg:city":"Fordingbridge",
    "sg:classifiers":[
        {
            "category":"Food & Beverages",
            "subcategory":"Meat & Fish",
            "type":"Retail Goods"
        }
    ],
    "sg:phone":"+44 1425 652228",
    "sg:postcode":"SP6 1AS",
    "sg:province":"Dorset",
    "sg:tags":[
        "butcher"
    ],
    "wof:name":"Price D J",
    "wof:placetype":"venue"
},
  "geometry": {"coordinates":[-1.7916519642,50.9268188477],"type":"Point"}
}