{
  "type": "Feature",
  "properties": {
    "addr:full":"84 Sylvia Crescent Southampton Hampshire SO40 3LN",
    "addr:housenumber":"84",
    "addr:postcode":"so40 3ln",
    "addr:street":"Sylvia Crescent",
    "iso:country":"GB",
    "sg:address":"84 Sylvia Crescent",
    "sg:city":"Southampton",
    "sg:classifiers":[
        {
            "category":"Building & Trades",
            "subcategory":"Construction",
            "type":"Services"
        }
    ],
    "sg:phone":"+44 23 8086 3485",
    "sg:postcode":"SO40 3LN",
    "sg:province":"Hampshire",
    "sg:tags":[
        "builder"
    ],
    "wof:name":"Barber Homes",
    "wof:placetype":"venue"
},
  "geometry": {"coordinates":[-1.500821,50.925976],"type":"Point"}
}