{
  "type": "Feature",
  "properties": {
    "iso:country":"GB",
    "sg:address":"272 Burlington Road",
    "sg:city":"New Malden",
    "sg:classifiers":[
        {
            "category":"Restaurant",
            "type":"Food & Drink"
        },
        {
            "category":"Food & Beverages",
            "subcategory":"Groceries & Convenience Stores",
            "type":"Retail Goods"
        }
    ],
    "sg:phone":"+44 20 8949 2506",
    "sg:postcode":"KT3 4NL",
    "sg:province":"Surrey",
    "sg:tags":[
        "shop",
        "fish",
        "oriental",
        "chip"
    ],
    "wof:name":"JANG WON",
    "wof:placetype":"venue"
},
  "geometry": {"coordinates":[-0.238903001,51.4000778198],"type":"Point"}
}