{
  "type": "Feature",
  "properties": {
    "iso:country":"GB",
    "sg:address":"10 Howard St",
    "sg:city":"Ipswich",
    "sg:classifiers":[
        {
            "category":"Building & Trades",
            "subcategory":"Landscaping Services",
            "type":"Services"
        }
    ],
    "sg:postcode":"IP4 4PL",
    "sg:province":"Suffolk",
    "sg:tags":[
        "landscape",
        "contractor"
    ],
    "wof:name":"Canham,Steve,",
    "wof:placetype":"venue"
},
  "geometry": {"coordinates":[1.187945,52.060658],"type":"Point"}
}