{
  "type": "Feature",
  "properties": {
    "iso:country":"GB",
    "sg:address":"Annexe 88 Wood Lane, Quorn",
    "sg:city":"Loughborough",
    "sg:classifiers":[
        {
            "category":"Personal",
            "subcategory":"Beauty Salon",
            "type":"Services"
        }
    ],
    "sg:postcode":"LE12 8DB",
    "sg:province":"Leicestershire",
    "sg:tags":[
        "unisex",
        "hairdresser"
    ],
    "wof:name":"Changes Hair & Beauty",
    "wof:placetype":"venue"
},
  "geometry": {"coordinates":[-1.1762789488,52.750202179],"type":"Point"}
}