{
  "type": "Feature",
  "properties": {
    "addr:full":"4 Buckingham Gro Kingswinford Staffordshire DY6 9ED",
    "addr:housenumber":"4",
    "addr:postcode":"dy6 9ed",
    "addr:street":"Buckingham Gro Kingswinford",
    "iso:country":"GB",
    "sg:address":"4 Buckingham Gro",
    "sg:city":"Kingswinford",
    "sg:classifiers":[
        {
            "category":"Shopping",
            "subcategory":"News",
            "type":"Retail Goods"
        }
    ],
    "sg:phone":"+44 1384 821030",
    "sg:postcode":"DY6 9ED",
    "sg:province":"Staffordshire",
    "sg:tags":[
        "newsagent"
    ],
    "wof:name":"S R Lees",
    "wof:placetype":"venue"
},
  "geometry": {"coordinates":[-2.1727149487,52.4972801208],"type":"Point"}
}