{
  "type": "Feature",
  "properties": {
    "addr:full":"Wester Shieldhill Lands Falkirk Falkirk FK1 3AT",
    "addr:postcode":"fk1 3at",
    "addr:street":"Wester Shieldhill Lands",
    "iso:country":"GB",
    "sg:address":"Wester Shieldhill Lands",
    "sg:city":"Falkirk",
    "sg:classifiers":[
        {
            "category":"Building & Trades",
            "subcategory":"Construction",
            "type":"Services"
        }
    ],
    "sg:postcode":"FK1 3AT",
    "sg:province":"Falkirk",
    "sg:tags":[
        "decorator",
        "painter"
    ],
    "wof:name":"Corrosion Treatment Services Ltd",
    "wof:placetype":"venue"
},
  "geometry": {"coordinates":[-3.778592,55.987492],"type":"Point"}
}