{
  "type": "Feature",
  "properties": {
    "iso:country":"GB",
    "sg:address":"Quarry Farm, Springwell La",
    "sg:city":"Rickmansworth",
    "sg:classifiers":[
        {
            "category":"Home & Garden",
            "subcategory":"Garden Supply",
            "type":"Retail Goods"
        }
    ],
    "sg:postcode":"WD3 8UX",
    "sg:province":"Hertfordshire",
    "sg:tags":[
        "sand",
        "gravel"
    ],
    "wof:name":"Sandman Aggregates Ltd",
    "wof:placetype":"venue"
},
  "geometry": {"coordinates":[-0.4963989854,51.6290855408],"type":"Point"}
}