{
  "type": "Feature",
  "properties": {
    "addr:full":"121 Kirby Road Leicester Leicestershire LE3 6BE",
    "addr:housenumber":"121",
    "addr:postcode":"le3 6be",
    "addr:street":"Kirby Road",
    "iso:country":"GB",
    "sg:address":"121 Kirby Road",
    "sg:city":"Leicester",
    "sg:classifiers":[
        {
            "category":"Recreation",
            "subcategory":"Gun Range",
            "type":"Entertainment"
        }
    ],
    "sg:phone":"+44 116 253 2686",
    "sg:postcode":"LE3 6BE",
    "sg:province":"Leicestershire",
    "sg:tags":[
        "operator",
        "tour"
    ],
    "wof:name":"Pearl Destinations Ltd.",
    "wof:placetype":"venue"
},
  "geometry": {"coordinates":[-1.1565899849,52.6334724426],"type":"Point"}
}