{
  "type": "Feature",
  "properties": {
    "addr:full":"15-16 Clifton Rd Exeter Devon EX1 2BR",
    "addr:housenumber":"15-16",
    "addr:postcode":"ex1 2br",
    "addr:street":"Clifton Rd",
    "iso:country":"GB",
    "sg:address":"15-16 Clifton Rd",
    "sg:city":"Exeter",
    "sg:classifiers":[
        {
            "category":"Organizations",
            "subcategory":"Non-profit Organization",
            "type":"Services"
        }
    ],
    "sg:phone":"+44 1392 434466",
    "sg:postcode":"EX1 2BR",
    "sg:province":"Devon",
    "sg:tags":[
        "fundraising",
        "charity"
    ],
    "wof:name":"P D K Enterprises Ltd",
    "wof:placetype":"venue"
},
  "geometry": {"coordinates":[-3.519535,50.726093],"type":"Point"}
}