{
  "type": "Feature",
  "properties": {
    "iso:country":"GB",
    "sg:address":"17 Crabtree Lane",
    "sg:city":"Hemel Hempstead",
    "sg:classifiers":[
        {
            "category":"Building & Trades",
            "subcategory":"Construction",
            "type":"Services"
        },
        {
            "category":"Real Estate",
            "subcategory":"Architect",
            "type":"Services"
        }
    ],
    "sg:phone":"+44 1442 263081",
    "sg:postcode":"HP3 9EG",
    "sg:province":"Hertfordshire",
    "sg:tags":[
        "consultant",
        "advisor"
    ],
    "wof:name":"Wren Designs",
    "wof:placetype":"venue"
},
  "geometry": {"coordinates":[-0.4688470066,51.7433357239],"type":"Point"}
}