{
  "type": "Feature",
  "properties": {
    "addr:full":"Hale Farm, Newnham Lane, Newnham Hook Berkshire RG27 9AQ",
    "addr:postcode":"rg27 9aq",
    "addr:street":"Newnham Lane",
    "iso:country":"GB",
    "sg:address":"Hale Farm, Newnham Lane, Newnham",
    "sg:city":"Hook",
    "sg:classifiers":[
        {
            "category":"Home & Garden",
            "subcategory":"Garden Supply",
            "type":"Retail Goods"
        },
        {
            "category":"Farming",
            "subcategory":"Livestock Farm",
            "type":"Manufacturing & Wholesale Goods"
        }
    ],
    "sg:postcode":"RG27 9AQ",
    "sg:province":"Berkshire",
    "sg:tags":[
        "bulb",
        "grower",
        "others"
    ],
    "wof:name":"Richard A H Fouracre",
    "wof:placetype":"venue"
},
  "geometry": {"coordinates":[-0.9657189846,51.2813606262],"type":"Point"}
}