{
  "type": "Feature",
  "properties": {
    "iso:country":"GB",
    "sg:address":"Varnsdorf Way, Petersburn",
    "sg:city":"Airdrie",
    "sg:classifiers":[
        {
            "category":"Bars & Pubs",
            "type":"Food & Drink"
        }
    ],
    "sg:phone":"+44 1236 606106",
    "sg:postcode":"ML6 8EQ",
    "sg:province":"North Lanarkshire",
    "sg:tags":[
        "pubs",
        "inn"
    ],
    "wof:name":"The Four Isles",
    "wof:placetype":"venue"
},
  "geometry": {"coordinates":[-3.943509,55.860287],"type":"Point"}
}