{
  "type": "Feature",
  "properties": {
    "addr:full":"104 Tollington Park Finsbury Park Greater London N4 3RB",
    "addr:housenumber":"104",
    "addr:postcode":"n4 3rb",
    "addr:street":"Tollington Park;Park",
    "iso:country":"GB",
    "sg:address":"104 Tollington Park",
    "sg:city":"Finsbury Park",
    "sg:classifiers":[
        {
            "category":"Building & Trades",
            "subcategory":"Construction",
            "type":"Services"
        }
    ],
    "sg:phone":"+44 20 7281 0424",
    "sg:postcode":"N4 3RB",
    "sg:province":"Greater London",
    "sg:tags":[
        "builder"
    ],
    "wof:name":"Natis Ltd",
    "wof:placetype":"venue"
},
  "geometry": {"coordinates":[-0.114067,51.566319],"type":"Point"}
}