{
  "type": "Feature",
  "properties": {
    "addr:full":"11 Bernard Street Edinburgh City of Edinburgh EH6 6PW",
    "addr:housenumber":"11",
    "addr:postcode":"eh6 6pw",
    "addr:street":"Bernard Street",
    "iso:country":"GB",
    "sg:address":"11 Bernard Street",
    "sg:city":"Edinburgh",
    "sg:classifiers":[
        {
            "category":"Fast Food",
            "type":"Food & Drink"
        },
        {
            "category":"Food & Beverages",
            "subcategory":"Meat & Fish",
            "type":"Retail Goods"
        }
    ],
    "sg:phone":"+44 131 477 7727",
    "sg:postcode":"EH6 6PW",
    "sg:province":"City of Edinburgh",
    "sg:tags":[
        "outlet",
        "chip",
        "meal",
        "away",
        "take"
    ],
    "wof:name":"Pierino's",
    "wof:placetype":"venue"
},
  "geometry": {"coordinates":[-3.167187,55.975266],"type":"Point"}
}