{
  "type": "Feature",
  "properties": {
    "addr:full":"16 Trembath Crescent Newquay Cornwall TR7 2DX",
    "addr:housenumber":"16",
    "addr:postcode":"tr7 2dx",
    "addr:street":"Trembath Crescent",
    "iso:country":"GB",
    "sg:address":"16 Trembath Crescent",
    "sg:city":"Newquay",
    "sg:classifiers":[
        {
            "category":"Retail",
            "subcategory":"Driving School",
            "type":"Services"
        }
    ],
    "sg:phone":"+44 1637 850817",
    "sg:postcode":"TR7 2DX",
    "sg:province":"Cornwall",
    "wof:name":"Malcolm D Crocker",
    "wof:placetype":"venue"
},
  "geometry": {"coordinates":[-5.0830388069,50.4081230164],"type":"Point"}
}