{
  "type": "Feature",
  "properties": {
    "iso:country":"GB",
    "sg:address":"112 Bernard St",
    "sg:city":"Southampton",
    "sg:classifiers":[
        {
            "category":"Fast Food",
            "type":"Food & Drink"
        }
    ],
    "sg:postcode":"SO14 3EH",
    "sg:province":"Hampshire",
    "sg:tags":[
        "away",
        "take"
    ],
    "wof:name":"McElvenny,Mrs,",
    "wof:placetype":"venue"
},
  "geometry": {"coordinates":[-1.398174,50.899231],"type":"Point"}
}