{
  "type": "Feature",
  "properties": {
    "iso:country":"GB",
    "sg:address":"Estate Office, Freston",
    "sg:city":"Ipswich",
    "sg:classifiers":[
        {
            "category":"Farming",
            "subcategory":"Livestock Farm",
            "type":"Manufacturing & Wholesale Goods"
        }
    ],
    "sg:phone":"+44 1473 690864",
    "sg:postcode":"IP9 1AF",
    "sg:province":"Suffolk",
    "sg:tags":[
        "others"
    ],
    "wof:name":"William Paul & Sons",
    "wof:placetype":"venue"
},
  "geometry": {"coordinates":[1.160965,52.007313],"type":"Point"}
}