{
  "type": "Feature",
  "properties": {
    "addr:full":"1-2 Lincolns Inn Fields Holborn Greater London WC2A 3BA",
    "addr:housenumber":"1-2",
    "addr:postcode":"wc2a 3ba",
    "addr:street":"Lincolns;Fields",
    "iso:country":"GB",
    "sg:address":"1-2 Lincolns Inn Fields",
    "sg:city":"Holborn",
    "sg:classifiers":[
        {
            "category":"Real Estate",
            "subcategory":"Surveying",
            "type":"Services"
        }
    ],
    "sg:phone":"+44 20 7242 8275",
    "sg:postcode":"WC2A 3BA",
    "sg:province":"Greater London",
    "sg:tags":[
        "surveyor",
        "valuer"
    ],
    "wof:name":"Browett Taylor & Co",
    "wof:placetype":"venue"
},
  "geometry": {"coordinates":[-0.1184919998,51.5166473389],"type":"Point"}
}