{
  "type": "Feature",
  "properties": {
    "iso:country":"GB",
    "sg:address":"61 Waterloo Road",
    "sg:city":"Liverpool",
    "sg:classifiers":[
        {
            "category":"Home & Garden",
            "subcategory":"Hardware",
            "type":"Retail Goods"
        }
    ],
    "sg:phone":"+44 151 227 5728",
    "sg:postcode":"L3 7BE",
    "sg:province":"Merseyside",
    "sg:tags":[
        "equipment",
        "welding"
    ],
    "wof:name":"John Davies (Liverpool) Ltd.",
    "wof:placetype":"venue"
},
  "geometry": {"coordinates":[-2.999658,53.416965],"type":"Point"}
}