{
  "type": "Feature",
  "properties": {
    "iso:country":"GB",
    "sg:address":"9 Farnham Way",
    "sg:city":"Bedford",
    "sg:classifiers":[
        {
            "category":"Education",
            "subcategory":"School",
            "type":"Public Place"
        }
    ],
    "sg:phone":"+44 1234 353455",
    "sg:postcode":"MK41 8RE",
    "sg:province":"Bedfordshire",
    "sg:tags":[
        "private",
        "tuition"
    ],
    "wof:name":"Private Tuition",
    "wof:placetype":"venue"
},
  "geometry": {"coordinates":[-0.436545,52.156013],"type":"Point"}
}