{
  "type": "Feature",
  "properties": {
    "iso:country":"GB",
    "sg:address":"Overton, West Monkton",
    "sg:city":"Taunton",
    "sg:classifiers":[
        {
            "category":"Professional",
            "subcategory":"Advertising",
            "type":"Services"
        }
    ],
    "sg:phone":"+44 1823 412345",
    "sg:postcode":"TA2 8LS",
    "sg:province":"Somerset",
    "sg:tags":[
        "cider",
        "maker"
    ],
    "wof:name":"Lane's Cider",
    "wof:placetype":"venue"
},
  "geometry": {"coordinates":[-3.054035,51.05233],"type":"Point"}
}