{
  "type": "Feature",
  "properties": {
    "addr:full":"146 Gravelly Hill North Birmingham West Midlands B23 6BA",
    "addr:housenumber":"146",
    "addr:postcode":"b23 6ba",
    "addr:street":"Gravelly Hill North",
    "iso:country":"GB",
    "sg:address":"146 Gravelly Hill North",
    "sg:city":"Birmingham",
    "sg:classifiers":[
        {
            "category":"Cafe",
            "type":"Food & Drink"
        }
    ],
    "sg:phone":"+44 121 373 3102",
    "sg:postcode":"B23 6BA",
    "sg:province":"West Midlands",
    "sg:tags":[
        "tea",
        "room"
    ],
    "wof:name":"Georges Lunchbox Cafe",
    "wof:placetype":"venue"
},
  "geometry": {"coordinates":[-1.845058,52.521084],"type":"Point"}
}