{
  "type": "Feature",
  "properties": {
    "iso:country":"GB",
    "sg:address":"12 Larch Clo",
    "sg:city":"Wigan",
    "sg:classifiers":[
        {
            "category":"Personal",
            "type":"Services"
        }
    ],
    "sg:phone":"+44 1744 895198",
    "sg:postcode":"WN5 7PX",
    "sg:province":"Lancashire",
    "sg:tags":[
        "wedding"
    ],
    "wof:name":"A & D Print",
    "wof:placetype":"venue"
},
  "geometry": {"coordinates":[-2.711293,53.497868],"type":"Point"}
}