{
  "type": "Feature",
  "properties": {
    "iso:country":"GB",
    "sg:address":"Alma Road, Walsden",
    "sg:city":"Todmorden",
    "sg:classifiers":[
        {
            "category":"Personal",
            "subcategory":"Skin Care",
            "type":"Services"
        }
    ],
    "sg:phone":"+44 1706 812830",
    "sg:postcode":"OL14 6SB",
    "sg:province":"Lancashire",
    "sg:tags":[
        "leather",
        "merchant"
    ],
    "wof:name":"Dugdale Lello & Co. Ltd.",
    "wof:placetype":"venue"
},
  "geometry": {"coordinates":[-2.1004989147,53.694770813],"type":"Point"}
}