{
  "type": "Feature",
  "properties": {
    "addr:full":"6 Church Street Settle North Yorkshire BD24 9JH",
    "addr:housenumber":"6",
    "addr:postcode":"bd24 9jh",
    "addr:street":"Church Street",
    "iso:country":"GB",
    "sg:address":"6 Church Street",
    "sg:city":"Settle",
    "sg:classifiers":[
        {
            "category":"Professional",
            "subcategory":"Art Services",
            "type":"Services"
        }
    ],
    "sg:phone":"+44 1729 823123",
    "sg:postcode":"BD24 9JH",
    "sg:province":"North Yorkshire",
    "sg:tags":[
        "framing"
    ],
    "wof:name":"The Dales Picture Shop",
    "wof:placetype":"venue"
},
  "geometry": {"coordinates":[-2.2798979282,54.0715255737],"type":"Point"}
}