{
  "type": "Feature",
  "properties": {
    "addr:full":"65 Queens Road Buckhurst Hill Essex IG9 5BW",
    "addr:housenumber":"65",
    "addr:postcode":"ig9 5bw",
    "addr:street":"Queens Road",
    "iso:country":"GB",
    "sg:address":"65 Queens Road",
    "sg:city":"Buckhurst Hill",
    "sg:classifiers":[
        {
            "category":"Shopping",
            "subcategory":"Clothing, Apparel, & Fashions",
            "type":"Retail Goods"
        }
    ],
    "sg:phone":"+44 20 8505 9221",
    "sg:postcode":"IG9 5BW",
    "sg:province":"Essex",
    "sg:tags":[
        "menswear"
    ],
    "wof:name":"Zap Clothing Ltd.",
    "wof:placetype":"venue"
},
  "geometry": {"coordinates":[0.042737,51.625565],"type":"Point"}
}