{
  "type": "Feature",
  "properties": {
    "addr:full":"828 Manchester Road Bradford West Yorkshire BD5 8DJ",
    "addr:housenumber":"828",
    "addr:postcode":"bd5 8dj",
    "addr:street":"Manchester Road",
    "iso:country":"GB",
    "sg:address":"828 Manchester Road",
    "sg:city":"Bradford",
    "sg:classifiers":[
        {
            "category":"Professional",
            "subcategory":"Computer Services",
            "type":"Services"
        }
    ],
    "sg:phone":"+44 1274 402244",
    "sg:postcode":"BD5 8DJ",
    "sg:province":"West Yorkshire",
    "sg:tags":[
        "system",
        "software"
    ],
    "wof:name":"Trilogic (U K) Ltd.",
    "wof:placetype":"venue"
},
  "geometry": {"coordinates":[-1.7607170343,53.7745628357],"type":"Point"}
}