{
  "type": "Feature",
  "properties": {
    "addr:full":"43 Stocks Lane, Boughton Chester Cheshire CH3 5TE",
    "addr:housenumber":"43",
    "addr:postcode":"ch3 5te",
    "addr:street":"Stocks Lane",
    "iso:country":"GB",
    "sg:address":"43 Stocks Lane, Boughton",
    "sg:city":"Chester",
    "sg:classifiers":[
        {
            "category":"Professional",
            "subcategory":"Accounting & Tax Preparation",
            "type":"Services"
        }
    ],
    "sg:phone":"+44 1244 327547",
    "sg:postcode":"CH3 5TE",
    "sg:province":"Cheshire",
    "sg:tags":[
        "accountant"
    ],
    "wof:name":"J M Stafford-Smith & Co",
    "wof:placetype":"venue"
},
  "geometry": {"coordinates":[-2.866137,53.188118],"type":"Point"}
}