{
  "type": "Feature",
  "properties": {
    "iso:country":"GB",
    "sg:address":"36-38 Parker Street",
    "sg:city":"Burnley",
    "sg:classifiers":[
        {
            "category":"Retail",
            "subcategory":"Auto Repair",
            "type":"Services"
        }
    ],
    "sg:phone":"+44 1282 838189",
    "sg:postcode":"BB11 1AU",
    "sg:province":"Lancashire",
    "sg:tags":[
        "modification",
        "garage",
        "related"
    ],
    "wof:name":"KWIK-FIT 2003 LTD",
    "wof:placetype":"venue"
},
  "geometry": {"coordinates":[-2.24326,53.791359],"type":"Point"}
}