{
  "type": "Feature",
  "properties": {
    "addr:full":"Intext House 18/22  Burnley Road, Padiham Burnley Lancashire BB12 8BX",
    "addr:housenumber":"18 / 22",
    "addr:postcode":"bb12 8bx",
    "addr:street":"Burnley Road",
    "iso:country":"GB",
    "sg:address":"Intext House 18/22  Burnley Road, Padiham",
    "sg:city":"Burnley",
    "sg:classifiers":[
        {
            "category":"Professional",
            "subcategory":"Employment Agencies",
            "type":"Services"
        }
    ],
    "sg:postcode":"BB12 8BX",
    "sg:province":"Lancashire",
    "sg:tags":[
        "consultant"
    ],
    "wof:name":"Intext Recruitment Services Ltd",
    "wof:placetype":"venue"
},
  "geometry": {"coordinates":[-2.314358,53.801491],"type":"Point"}
}