{
  "type": "Feature",
  "properties": {
    "iso:country":"GB",
    "sg:address":"29-31 The Strait",
    "sg:city":"Lincoln",
    "sg:classifiers":[
        {
            "category":"Shopping",
            "subcategory":"Catalog Store",
            "type":"Retail Goods"
        },
        {
            "category":"Shopping",
            "subcategory":"Discount & Variety Stores",
            "type":"Retail Goods"
        }
    ],
    "sg:phone":"+44 1522 527276",
    "sg:postcode":"LN2 1JD",
    "sg:province":"Lincolnshire",
    "sg:tags":[
        "mail",
        "order",
        "centre"
    ],
    "wof:name":"Catalogue Bargain Shop",
    "wof:placetype":"venue"
},
  "geometry": {"coordinates":[-0.539504,53.231606],"type":"Point"}
}