{
  "type": "Feature",
  "properties": {
    "iso:country":"GB",
    "sg:address":"Kingfisher Court, The Oaks, Clews Road",
    "sg:city":"Redditch",
    "sg:classifiers":[
        {
            "category":"Organizations",
            "subcategory":"Non-profit Organization",
            "type":"Services"
        }
    ],
    "sg:phone":"+44 1527 546000",
    "sg:postcode":"B98 7ST",
    "sg:province":"Warwickshire",
    "sg:tags":[
        "charitable",
        "organisation",
        "voluntary",
        "charity"
    ],
    "wof:name":"Individual Care Services",
    "wof:placetype":"venue"
},
  "geometry": {"coordinates":[-1.9300099611,52.2834510803],"type":"Point"}
}