{
  "type": "Feature",
  "properties": {
    "addr:full":"20 Bond Street Wakefield West Yorkshire WF1 2QP",
    "addr:housenumber":"20",
    "addr:postcode":"wf1 2qp",
    "addr:street":"Bond Street",
    "iso:country":"GB",
    "sg:address":"20 Bond Street",
    "sg:city":"Wakefield",
    "sg:classifiers":[
        {
            "category":"Health Services",
            "subcategory":"Dentist",
            "type":"Services"
        }
    ],
    "sg:phone":"+44 1924 374092",
    "sg:postcode":"WF1 2QP",
    "sg:province":"West Yorkshire",
    "wof:name":"Tovey & Little",
    "wof:placetype":"venue"
},
  "geometry": {"coordinates":[-1.5030109882,53.6857910156],"type":"Point"}
}