{
  "type": "Feature",
  "properties": {
    "iso:country":"GB",
    "sg:address":"6b Water-ma-trout",
    "sg:city":"Helston",
    "sg:classifiers":[
        {
            "category":"Autos & Motor Vehicles",
            "subcategory":"Motorcycle Sales",
            "type":"Retail Goods"
        }
    ],
    "sg:phone":"+44 1326 564486",
    "sg:postcode":"TR13 0LW",
    "sg:province":"Cornwall",
    "sg:tags":[
        "component"
    ],
    "wof:name":"West Coast Racing",
    "wof:placetype":"venue"
},
  "geometry": {"coordinates":[-5.269809,50.113869],"type":"Point"}
}