{
  "type": "Feature",
  "properties": {
    "addr:full":"56 Ennerdale Road, Astley Manchester Greater Manchester M29 7AR",
    "addr:housenumber":"56",
    "addr:postcode":"m29 7ar",
    "addr:street":"Ennerdale Road",
    "iso:country":"GB",
    "sg:address":"56 Ennerdale Road, Astley",
    "sg:city":"Manchester",
    "sg:classifiers":[
        {
            "category":"Professional",
            "subcategory":"Engineering",
            "type":"Services"
        }
    ],
    "sg:postcode":"M29 7AR",
    "sg:province":"Greater Manchester",
    "sg:tags":[
        "precision",
        "engineer"
    ],
    "wof:name":"Dee Bee Engineering Ltd",
    "wof:placetype":"venue"
},
  "geometry": {"coordinates":[-2.4591500759,53.5076637268],"type":"Point"}
}