{
  "type": "Feature",
  "properties": {
    "addr:full":"24 Butcher Walk Swanscombe Kent DA10 0JR",
    "addr:housenumber":"24",
    "addr:postcode":"da10 0jr",
    "addr:street":"Butcher Walk",
    "iso:country":"GB",
    "sg:address":"24 Butcher Walk",
    "sg:city":"Swanscombe",
    "sg:classifiers":[
        {
            "category":"Building & Trades",
            "subcategory":"Cleaning & Sanitation",
            "type":"Services"
        }
    ],
    "sg:phone":"+44 1322 624398",
    "sg:postcode":"DA10 0JR",
    "sg:province":"Kent",
    "sg:tags":[
        "commercial"
    ],
    "wof:name":"Manlite Cleaning",
    "wof:placetype":"venue"
},
  "geometry": {"coordinates":[0.30373,51.44278],"type":"Point"}
}