{
  "type": "Feature",
  "properties": {
    "iso:country":"GB",
    "sg:address":"53 High St",
    "sg:city":"Malmesbury",
    "sg:classifiers":[
        {
            "category":"Building & Trades",
            "subcategory":"Landscaping Services",
            "type":"Services"
        }
    ],
    "sg:phone":"+44 1666 825682",
    "sg:postcode":"SN16 9AG",
    "sg:province":"Wiltshire",
    "sg:tags":[
        "designer",
        "architect",
        "landscape"
    ],
    "wof:name":"Rockscape",
    "wof:placetype":"venue"
},
  "geometry": {"coordinates":[-2.097254,51.581791],"type":"Point"}
}