{
  "type": "Feature",
  "properties": {
    "addr:full":"Wern Farm, Llanarthney Carmarthen Carmarthenshire SA32 8LE",
    "addr:postcode":"sa32 8le",
    "iso:country":"GB",
    "sg:address":"Wern Farm, Llanarthney",
    "sg:city":"Carmarthen",
    "sg:classifiers":[
        {
            "category":"Farming",
            "subcategory":"Dairy Farm",
            "type":"Manufacturing & Wholesale Goods"
        },
        {
            "category":"Farming",
            "subcategory":"Livestock Farm",
            "type":"Manufacturing & Wholesale Goods"
        }
    ],
    "sg:postcode":"SA32 8LE",
    "sg:province":"Carmarthenshire",
    "sg:tags":[
        "others"
    ],
    "wof:name":"Jones Bros",
    "wof:placetype":"venue"
},
  "geometry": {"coordinates":[-4.1298370361,51.8611755371],"type":"Point"}
}