{
  "type": "Feature",
  "properties": {
    "addr:full":"222 Cowbridge Road East Cardiff Cardiff CF5 1GY",
    "addr:housenumber":"222",
    "addr:postcode":"cf5 1gy",
    "addr:street":"Cowbridge Road East",
    "iso:country":"GB",
    "sg:address":"222 Cowbridge Road East",
    "sg:city":"Cardiff",
    "sg:classifiers":[
        {
            "category":"Cafe",
            "type":"Food & Drink"
        }
    ],
    "sg:phone":"+44 29 2022 1426",
    "sg:postcode":"CF5 1GY",
    "sg:province":"Cardiff",
    "sg:tags":[
        "tea",
        "room"
    ],
    "wof:name":"Canton Cafe",
    "wof:placetype":"venue"
},
  "geometry": {"coordinates":[-3.205299,51.482021],"type":"Point"}
}