{
  "type": "Feature",
  "properties": {
    "addr:full":"9 Hall Lane, Wiveton Holt Norfolk NR25 7TG",
    "addr:housenumber":"9",
    "addr:postcode":"nr25 7tg",
    "addr:street":"Hall Lane",
    "iso:country":"GB",
    "sg:address":"9 Hall Lane, Wiveton",
    "sg:city":"Holt",
    "sg:classifiers":[
        {
            "category":"Professional",
            "subcategory":"Computer Services",
            "type":"Services"
        }
    ],
    "sg:phone":"+44 1263 741368",
    "sg:postcode":"NR25 7TG",
    "sg:province":"Norfolk",
    "sg:tags":[
        "development",
        "system",
        "software"
    ],
    "wof:name":"Forcefield Software Ltd",
    "wof:placetype":"venue"
},
  "geometry": {"coordinates":[1.035828,52.949657],"type":"Point"}
}