{
  "type": "Feature",
  "properties": {
    "addr:full":"Warnford Rd Southampton Hampshire SO32 3ND",
    "addr:postcode":"so32 3nd",
    "addr:street":"Warnford Rd",
    "iso:country":"GB",
    "sg:address":"Warnford Rd",
    "sg:city":"Southampton",
    "sg:classifiers":[
        {
            "category":"Shopping",
            "subcategory":"Department Store",
            "type":"Retail Goods"
        }
    ],
    "sg:phone":"+44 1489 877374",
    "sg:postcode":"SO32 3ND",
    "sg:province":"Hampshire",
    "wof:name":"Village Stores & Post Office",
    "wof:placetype":"venue"
},
  "geometry": {"coordinates":[-1.1217390299,50.9868164062],"type":"Point"}
}