{
  "type": "Feature",
  "properties": {
    "addr:full":"Arun Shipyard Littlehampton West Sussex BN17 5DH",
    "addr:postcode":"bn17 5dh",
    "iso:country":"GB",
    "sg:address":"Arun Shipyard",
    "sg:city":"Littlehampton",
    "sg:classifiers":[
        {
            "category":"Autos & Motor Vehicles",
            "subcategory":"Boat Sales",
            "type":"Retail Goods"
        }
    ],
    "sg:phone":"+44 1903 713996",
    "sg:postcode":"BN17 5DH",
    "sg:province":"West Sussex",
    "sg:tags":[
        "repair",
        "builder"
    ],
    "wof:name":"William Osborne Ltd.",
    "wof:placetype":"venue"
},
  "geometry": {"coordinates":[-0.54271698,50.8038902283],"type":"Point"}
}