{
  "type": "Feature",
  "properties": {
    "addr:full":"230 Sharrow Vale Road Sheffield Derbyshire S11 8ZH",
    "addr:housenumber":"230",
    "addr:postcode":"s11 8zh",
    "addr:street":"Sharrow Vale Road",
    "iso:country":"GB",
    "sg:address":"230 Sharrow Vale Road",
    "sg:city":"Sheffield",
    "sg:classifiers":[
        {
            "category":"Autos & Motor Vehicles",
            "subcategory":"Auto Supplies",
            "type":"Retail Goods"
        }
    ],
    "sg:phone":"+44 114 268 5000",
    "sg:postcode":"S11 8ZH",
    "sg:province":"Derbyshire",
    "sg:tags":[
        "tyre",
        "towbars"
    ],
    "wof:name":"Towmaster",
    "wof:placetype":"venue"
},
  "geometry": {"coordinates":[-1.495704,53.367695],"type":"Point"}
}