{
  "type": "Feature",
  "properties": {
    "addr:full":"Melbourne Avenue Chelmsford Essex CM1 2XX",
    "addr:postcode":"cm1 2xx",
    "addr:street":"Melbourne Avenue",
    "iso:country":"GB",
    "sg:address":"Melbourne Avenue",
    "sg:city":"Chelmsford",
    "sg:classifiers":[
        {
            "category":"Social Services",
            "subcategory":"Adult Care",
            "type":"Services"
        },
        {
            "category":"Government",
            "subcategory":"Office",
            "type":"Public Place"
        }
    ],
    "sg:phone":"+44 1245 283424",
    "sg:postcode":"CM1 2XX",
    "sg:province":"Essex",
    "sg:tags":[
        "housing",
        "local",
        "sheltered"
    ],
    "wof:name":"Landers Court Sheltered Housing",
    "wof:placetype":"venue"
},
  "geometry": {"coordinates":[0.455567,51.749271],"type":"Point"}
}