{
  "type": "Feature",
  "properties": {
    "iso:country":"GB",
    "sg:address":"Ladycross Business Park, Hollow Lane, Dormansland",
    "sg:city":"Lingfield",
    "sg:classifiers":[
        {
            "category":"Home & Garden",
            "subcategory":"Building Materials",
            "type":"Retail Goods"
        }
    ],
    "sg:phone":"+44 1342 323822",
    "sg:postcode":"RH7 6PB",
    "sg:province":"Surrey",
    "sg:tags":[
        "gate",
        "door",
        "barrier"
    ],
    "wof:name":"Automated Access Contracts Ltd.",
    "wof:placetype":"venue"
},
  "geometry": {"coordinates":[-0.019686,51.17482],"type":"Point"}
}