{
  "type": "Feature",
  "properties": {
    "addr:full":"8 Railway Terrace, Old Walsall Road, Hamstead Birmingham West Midlands B42 1NR",
    "addr:housenumber":"8",
    "addr:postcode":"b42 1nr",
    "addr:street":"Railway Terrace;Walsall Road",
    "iso:country":"GB",
    "sg:address":"8 Railway Terrace, Old Walsall Road, Hamstead",
    "sg:city":"Birmingham",
    "sg:classifiers":[
        {
            "category":"Banks & Credit Unions",
            "subcategory":"Bank",
            "type":"Services"
        }
    ],
    "sg:postcode":"B42 1NR",
    "sg:province":"West Midlands",
    "sg:tags":[
        "broker",
        "mortgage"
    ],
    "wof:name":"D K & Associates",
    "wof:placetype":"venue"
},
  "geometry": {"coordinates":[-1.92998,52.532589],"type":"Point"}
}