{
  "type": "Feature",
  "properties": {
    "addr:full":"40 Otley Road, Guiseley Leeds West Yorkshire LS20 8AH",
    "addr:housenumber":"40",
    "addr:postcode":"ls20 8ah",
    "addr:street":"Otley Road",
    "iso:country":"GB",
    "sg:address":"40 Otley Road, Guiseley",
    "sg:city":"Leeds",
    "sg:classifiers":[
        {
            "category":"Banks & Credit Unions",
            "subcategory":"Financial Services",
            "type":"Services"
        }
    ],
    "sg:phone":"+44 1943 874890",
    "sg:postcode":"LS20 8AH",
    "sg:province":"West Yorkshire",
    "sg:tags":[
        "building",
        "society"
    ],
    "sg:website":"http://www.skipton.co.uk",
    "wof:name":"Skipton Building Society Plc",
    "wof:placetype":"venue"
},
  "geometry": {"coordinates":[-1.7112829685,53.873462677],"type":"Point"}
}