{
  "type": "Feature",
  "properties": {
    "addr:full":"11-13 Wye Cliff Road Birmingham West Midlands B20 3TA",
    "addr:housenumber":"11-13",
    "addr:postcode":"b20 3ta",
    "addr:street":"Wye Cliff Road",
    "iso:country":"GB",
    "sg:address":"11-13 Wye Cliff Road",
    "sg:city":"Birmingham",
    "sg:classifiers":[
        {
            "category":"Social Services",
            "subcategory":"Retirement Home",
            "type":"Services"
        }
    ],
    "sg:phone":"+44 121 554 1749",
    "sg:postcode":"B20 3TA",
    "sg:province":"West Midlands",
    "sg:tags":[
        "residential",
        "care"
    ],
    "wof:name":"Birmingham Institute for the Deaf",
    "wof:placetype":"venue"
},
  "geometry": {"coordinates":[-1.9178780317,52.5043983459],"type":"Point"}
}