{
  "type": "Feature",
  "properties": {
    "addr:full":"369 Kilburn High Road London Greater London NW6 7QB",
    "addr:housenumber":"369",
    "addr:postcode":"nw6 7qb",
    "addr:street":"Kilburn High Road",
    "iso:country":"GB",
    "sg:address":"369 Kilburn High Road",
    "sg:city":"London",
    "sg:classifiers":[
        {
            "category":"Real Estate",
            "subcategory":"Real Estate Agent",
            "type":"Services"
        }
    ],
    "sg:postcode":"NW6 7QB",
    "sg:province":"Greater London",
    "wof:name":"Michel Pauls Estate Agents",
    "wof:placetype":"venue"
},
  "geometry": {"coordinates":[-0.202495,51.545582],"type":"Point"}
}