{
  "type": "Feature",
  "properties": {
    "addr:full":"7 Ruskin Close Crawley Surrey RH10 3TP",
    "addr:housenumber":"7",
    "addr:postcode":"rh10 3tp",
    "addr:street":"Ruskin Close",
    "iso:country":"GB",
    "sg:address":"7 Ruskin Close",
    "sg:city":"Crawley",
    "sg:classifiers":[
        {
            "category":"Building & Trades",
            "subcategory":"Construction",
            "type":"Services"
        }
    ],
    "sg:phone":"+44 1293 883817",
    "sg:postcode":"RH10 3TP",
    "sg:province":"Surrey",
    "sg:tags":[
        "dry",
        "lining",
        "plasterers",
        "screeders"
    ],
    "wof:name":"C J Plastering",
    "wof:placetype":"venue"
},
  "geometry": {"coordinates":[-0.154353,51.127251],"type":"Point"}
}