{
  "type": "Feature",
  "properties": {
    "addr:full":"Overton Road, Ruabon Wrexham Wrexham LL14 6HN",
    "addr:postcode":"ll14 6hn",
    "addr:street":"Overton Road",
    "iso:country":"GB",
    "sg:address":"Overton Road, Ruabon",
    "sg:city":"Wrexham",
    "sg:classifiers":[
        {
            "category":"Wholesale",
            "subcategory":"Construction Materials",
            "type":"Manufacturing & Wholesale Goods"
        }
    ],
    "sg:phone":"+44 1978 822010",
    "sg:postcode":"LL14 6HN",
    "sg:province":"Wrexham",
    "sg:tags":[
        "sawdust",
        "sawmills",
        "shaving",
        "sawmill",
        "activity"
    ],
    "wof:name":"Wynnstay Sawmills",
    "wof:placetype":"venue"
},
  "geometry": {"coordinates":[-3.0391139984,52.9874382019],"type":"Point"}
}