{
  "type": "Feature",
  "properties": {
    "addr:full":"19 Woodville Road, Leytonstone London Greater London E11 3BH",
    "addr:housenumber":"19",
    "addr:postcode":"e11 3bh",
    "addr:street":"Woodville Road",
    "iso:country":"GB",
    "sg:address":"19 Woodville Road, Leytonstone",
    "sg:city":"London",
    "sg:classifiers":[
        {
            "category":"Building & Trades",
            "subcategory":"Construction",
            "type":"Services"
        }
    ],
    "sg:postcode":"E11 3BH",
    "sg:province":"Greater London",
    "sg:tags":[
        "builder"
    ],
    "wof:name":"Laserbeam Developments Ltd",
    "wof:placetype":"venue"
},
  "geometry": {"coordinates":[0.015385,51.568356],"type":"Point"}
}