{
  "type": "Feature",
  "properties": {
    "iso:country":"GB",
    "sg:address":"Se Ur Beatha, Tarland",
    "sg:city":"Aboyne",
    "sg:classifiers":[
        {
            "category":"Professional",
            "subcategory":"Management & Consulting",
            "type":"Services"
        }
    ],
    "sg:postcode":"AB34 4UD",
    "sg:province":"Aberdeenshire",
    "sg:tags":[
        "consultant",
        "safety"
    ],
    "wof:name":"P M G Safety & Technical Services Ltd.",
    "wof:placetype":"venue"
},
  "geometry": {"coordinates":[-2.8543889523,57.1311264038],"type":"Point"}
}