{
  "type": "Feature",
  "properties": {
    "iso:country":"GB",
    "sg:address":"Red House, 10 Market Square",
    "sg:city":"Amersham",
    "sg:classifiers":[
        {
            "category":"Insurance",
            "subcategory":"Insurance Agent",
            "type":"Services"
        }
    ],
    "sg:phone":"+44 1494 432338",
    "sg:postcode":"HP7 0DQ",
    "sg:province":"Buckinghamshire",
    "sg:tags":[
        "broker"
    ],
    "wof:name":"Knight Lambert & Co. Ltd.",
    "wof:placetype":"venue"
},
  "geometry": {"coordinates":[-0.616855,51.666534],"type":"Point"}
}