{
  "type": "Feature",
  "properties": {
    "iso:country":"GB",
    "sg:address":"266 Glasgow Rd",
    "sg:city":"Glasgow",
    "sg:classifiers":[
        {
            "category":"Place Of Worship",
            "type":"Public Place"
        }
    ],
    "sg:phone":"+44 1698 307744",
    "sg:postcode":"G72 0YH",
    "sg:province":"South Lanarkshire",
    "wof:name":"Word Of Life Church",
    "wof:placetype":"venue"
},
  "geometry": {"coordinates":[-4.0932588577,55.7943267822],"type":"Point"}
}