{
  "type": "Feature",
  "properties": {
    "addr:full":"Riverside House Norwich Norfolk NR1 1SQ",
    "addr:postcode":"nr1 1sq",
    "addr:street":"Norwich Norfolk",
    "iso:country":"GB",
    "sg:address":"Riverside House",
    "sg:city":"Norwich",
    "sg:classifiers":[
        {
            "category":"Banks & Credit Unions",
            "subcategory":"Financial Services",
            "type":"Services"
        }
    ],
    "sg:phone":"+44 1603 767616",
    "sg:postcode":"NR1 1SQ",
    "sg:province":"Norfolk",
    "sg:tags":[
        "consultant"
    ],
    "wof:name":"Norscot Investments Ltd.",
    "wof:placetype":"venue"
},
  "geometry": {"coordinates":[1.2948999405,52.6224937439],"type":"Point"}
}