{
  "type": "Feature",
  "properties": {
    "iso:country":"GB",
    "sg:address":"The Green",
    "sg:city":"Great Yarmouth",
    "sg:classifiers":[
        {
            "category":"Bars & Pubs",
            "type":"Food & Drink"
        }
    ],
    "sg:phone":"+44 1493 751096",
    "sg:postcode":"NR29 3EX",
    "sg:province":"Norfolk",
    "sg:tags":[
        "pubs",
        "inn"
    ],
    "wof:name":"Ferry Inn",
    "wof:placetype":"venue"
},
  "geometry": {"coordinates":[1.638185,52.641014],"type":"Point"}
}