{
  "type": "Feature",
  "properties": {
    "addr:full":"2 High Street Swanley Kent BR8 8BE",
    "addr:housenumber":"2",
    "addr:postcode":"br8 8be",
    "addr:street":"High Street",
    "iso:country":"GB",
    "sg:address":"2 High Street",
    "sg:city":"Swanley",
    "sg:classifiers":[
        {
            "category":"Bars & Pubs",
            "type":"Food & Drink"
        }
    ],
    "sg:phone":"+44 1322 662027",
    "sg:postcode":"BR8 8BE",
    "sg:province":"Kent",
    "sg:tags":[
        "pubs",
        "inn"
    ],
    "wof:name":"Lullingstone Castle",
    "wof:placetype":"venue"
},
  "geometry": {"coordinates":[0.1768489927,51.3954086304],"type":"Point"}
}