{
  "type": "Feature",
  "properties": {
    "addr:full":"35 Seaview Rd Wallasey Merseyside L45 4QN",
    "addr:housenumber":"35",
    "addr:postcode":"l45 4qn",
    "addr:street":"Seaview Rd",
    "iso:country":"GB",
    "sg:address":"35 Seaview Rd",
    "sg:city":"Wallasey",
    "sg:classifiers":[
        {
            "category":"Home & Garden",
            "subcategory":"Home Furnishings",
            "type":"Retail Goods"
        }
    ],
    "sg:phone":"+44 151 638 6238",
    "sg:postcode":"L45 4QN",
    "sg:province":"Merseyside",
    "sg:tags":[
        "loose",
        "cover"
    ],
    "wof:name":"Marielle's",
    "wof:placetype":"venue"
},
  "geometry": {"coordinates":[-3.0460829735,53.4211463928],"type":"Point"}
}