{
  "type": "Feature",
  "properties": {
    "iso:country":"GB",
    "sg:address":"Fitzherbert Road",
    "sg:city":"Portsmouth",
    "sg:classifiers":[
        {
            "category":"Manufacturing",
            "subcategory":"Glass & Minerals",
            "type":"Manufacturing & Wholesale Goods"
        }
    ],
    "sg:phone":"+44 23 9221 4504",
    "sg:postcode":"PO6 1RU",
    "sg:province":"Hampshire",
    "sg:tags":[
        "fibre",
        "material"
    ],
    "wof:name":"Harry Odey",
    "wof:placetype":"venue"
},
  "geometry": {"coordinates":[-1.030622,50.843586],"type":"Point"}
}