{
  "type": "Feature",
  "properties": {
    "iso:country":"GB",
    "sg:address":"Mcdonald Business Centre, 107 Mcdonald Rd",
    "sg:city":"Edinburgh",
    "sg:classifiers":[
        {
            "category":"Organizations",
            "subcategory":"Non-profit Organization",
            "type":"Services"
        }
    ],
    "sg:phone":"+44 131 478 7414",
    "sg:postcode":"EH7 4NW",
    "sg:province":"City of Edinburgh",
    "sg:tags":[
        "organisation",
        "voluntary",
        "charity"
    ],
    "wof:name":"ARC Scotland",
    "wof:placetype":"venue"
},
  "geometry": {"coordinates":[-3.196203,55.968159],"type":"Point"}
}