{
  "type": "Feature",
  "properties": {
    "addr:full":"Arkle Drive Coventry Warwickshire CV2 2EF",
    "addr:postcode":"cv2 2ef",
    "addr:street":"Arkle Drive",
    "iso:country":"GB",
    "sg:address":"Arkle Drive",
    "sg:city":"Coventry",
    "sg:classifiers":[
        {
            "category":"Education",
            "subcategory":"School",
            "type":"Public Place"
        },
        {
            "category":"Government",
            "subcategory":"Office",
            "type":"Public Place"
        }
    ],
    "sg:phone":"+44 24 7661 5665",
    "sg:postcode":"CV2 2EF",
    "sg:province":"Warwickshire",
    "sg:tags":[
        "local",
        "authority"
    ],
    "wof:name":"St Peter and Paul Catholic Primary School",
    "wof:placetype":"venue"
},
  "geometry": {"coordinates":[-1.4455219507,52.4267997742],"type":"Point"}
}