{
  "type": "Feature",
  "properties": {
    "addr:full":"4 Ironmonger Street Stamford Cambridgeshire PE9 1PL",
    "addr:housenumber":"4",
    "addr:postcode":"pe9 1pl",
    "addr:street":"Ironmonger Street",
    "iso:country":"GB",
    "sg:address":"4 Ironmonger Street",
    "sg:city":"Stamford",
    "sg:classifiers":[
        {
            "category":"Real Estate",
            "subcategory":"Real Estate Agent",
            "type":"Services"
        }
    ],
    "sg:phone":"+44 1780 482121",
    "sg:postcode":"PE9 1PL",
    "sg:province":"Cambridgeshire",
    "wof:name":"Paul Johnson Property Consultants",
    "wof:placetype":"venue"
},
  "geometry": {"coordinates":[-0.47814,52.652866],"type":"Point"}
}