{
  "type": "Feature",
  "properties": {
    "addr:full":"1-3 Park Rd Penarth The Vale of Glamorgan CF64 3BD",
    "addr:housenumber":"1-3",
    "addr:postcode":"cf64 3bd",
    "addr:street":"Park Rd;Vale",
    "iso:country":"GB",
    "sg:address":"1-3 Park Rd",
    "sg:city":"Penarth",
    "sg:classifiers":[
        {
            "category":"Social Services",
            "subcategory":"Adult Care",
            "type":"Services"
        },
        {
            "category":"Social Services",
            "subcategory":"Retirement Home",
            "type":"Services"
        }
    ],
    "sg:phone":"+44 29 2071 1099",
    "sg:postcode":"CF64 3BD",
    "sg:province":"The Vale of Glamorgan",
    "sg:tags":[
        "provider"
    ],
    "wof:name":"Total Loving Care",
    "wof:placetype":"venue"
},
  "geometry": {"coordinates":[-3.171012,51.433647],"type":"Point"}
}