{
  "type": "Feature",
  "properties": {
    "iso:country":"GB",
    "sg:address":"Grosvenor Ct",
    "sg:city":"Wolverhampton",
    "sg:classifiers":[
        {
            "category":"Government",
            "subcategory":"Office",
            "type":"Public Place"
        }
    ],
    "sg:phone":"+44 1902 552822",
    "sg:postcode":"WV3 0NU",
    "sg:province":"Staffordshire",
    "sg:tags":[
        "local"
    ],
    "wof:name":"Wolverhampton Borough Council",
    "wof:placetype":"venue"
},
  "geometry": {"coordinates":[-2.1113479137,52.5899810791],"type":"Point"}
}