{
  "type": "Feature",
  "properties": {
    "addr:full":"50 Austhorpe Road Leeds West Yorkshire LS15 8DX",
    "addr:housenumber":"50",
    "addr:postcode":"ls15 8dx",
    "addr:street":"Austhorpe Road",
    "iso:country":"GB",
    "sg:address":"50 Austhorpe Road",
    "sg:city":"Leeds",
    "sg:classifiers":[
        {
            "category":"Professional",
            "subcategory":"Accounting & Tax Preparation",
            "type":"Services"
        }
    ],
    "sg:phone":"+44 113 260 8484",
    "sg:postcode":"LS15 8DX",
    "sg:province":"West Yorkshire",
    "sg:tags":[
        "accountant",
        "chartered"
    ],
    "wof:name":"Morehouses",
    "wof:placetype":"venue"
},
  "geometry": {"coordinates":[-1.449239,53.807297],"type":"Point"}
}