{
  "type": "Feature",
  "properties": {
    "addr:full":"Unit 45-46 Plumstead Road, Covered Market, Woolwich London Greater London SE18 7DB",
    "addr:housenumber":"unit 45-46",
    "addr:postcode":"se18 7db",
    "addr:street":"Plumstead Road",
    "iso:country":"GB",
    "sg:address":"Unit 45-46 Plumstead Road, Covered Market, Woolwich",
    "sg:city":"London",
    "sg:classifiers":[
        {
            "category":"Sports & Exercise",
            "subcategory":"Sports Center",
            "type":"Entertainment"
        }
    ],
    "sg:phone":"+44 20 8854 2282",
    "sg:postcode":"SE18 7DB",
    "sg:province":"Greater London",
    "sg:tags":[
        "shop",
        "good"
    ],
    "wof:name":"Stats Trophies",
    "wof:placetype":"venue"
},
  "geometry": {"coordinates":[0.0743630007,51.4905891418],"type":"Point"}
}