{
  "type": "Feature",
  "properties": {
    "iso:country":"GB",
    "sg:address":"52-54 Main Street, Alrewas",
    "sg:city":"Burton-on-trent",
    "sg:classifiers":[
        {
            "category":"Shopping",
            "subcategory":"Pharmacy",
            "type":"Retail Goods"
        }
    ],
    "sg:phone":"+44 1283 712218",
    "sg:postcode":"DE13 7AA",
    "sg:province":"Derbyshire",
    "sg:tags":[
        "pharmacist",
        "chemist"
    ],
    "wof:name":"Barton Pharmacy",
    "wof:placetype":"venue"
},
  "geometry": {"coordinates":[-1.743112,52.732006],"type":"Point"}
}