{
  "type": "Feature",
  "properties": {
    "iso:country":"GB",
    "sg:address":"Unit 5 Links Ave, Brundall",
    "sg:city":"Norwich",
    "sg:classifiers":[
        {
            "category":"Recreation",
            "subcategory":"Dog Park",
            "type":"Entertainment"
        }
    ],
    "sg:postcode":"NR13 5LL",
    "sg:province":"Norfolk",
    "wof:name":"Merritt,Christine,",
    "wof:placetype":"venue"
},
  "geometry": {"coordinates":[1.433319,52.62516],"type":"Point"}
}