{
  "type": "Feature",
  "properties": {
    "iso:country":"GB",
    "sg:address":"14 Ryton Street",
    "sg:city":"Worksop",
    "sg:classifiers":[
        {
            "category":"Shopping",
            "subcategory":"Comic Books",
            "type":"Retail Goods"
        }
    ],
    "sg:phone":"+44 1909 474585",
    "sg:postcode":"S80 2AU",
    "sg:province":"Nottinghamshire",
    "sg:tags":[
        "jeweller"
    ],
    "wof:name":"Marshalls the Jewellers",
    "wof:placetype":"venue"
},
  "geometry": {"coordinates":[-1.12363,53.30492],"type":"Point"}
}