{
  "type": "Feature",
  "properties": {
    "addr:full":"Hemley Woodbridge Suffolk, Hemley Woodbridge Suffolk IP12 4QF",
    "addr:postcode":"ip12 4qf",
    "iso:country":"GB",
    "sg:address":"Hemley Woodbridge Suffolk, Hemley",
    "sg:city":"Woodbridge",
    "sg:classifiers":[
        {
            "category":"Travel",
            "subcategory":"Travel Agent",
            "type":"Entertainment"
        }
    ],
    "sg:phone":"+44 1473 736265",
    "sg:postcode":"IP12 4QF",
    "sg:province":"Suffolk",
    "wof:name":"Cargo Ship Voyages Ltd.",
    "wof:placetype":"venue"
},
  "geometry": {"coordinates":[1.3312410116,52.0323066711],"type":"Point"}
}