{
  "type": "Feature",
  "properties": {
    "iso:country":"GB",
    "sg:address":"62 High Street, Caterham On The Hill",
    "sg:city":"Caterham",
    "sg:classifiers":[
        {
            "category":"Building & Trades",
            "subcategory":"Cleaning & Sanitation",
            "type":"Services"
        }
    ],
    "sg:phone":"+44 1883 330557",
    "sg:postcode":"CR3 5UB",
    "sg:province":"Surrey",
    "sg:tags":[
        "sweep",
        "chimney"
    ],
    "wof:name":"Milborrow & Sons",
    "wof:placetype":"venue"
},
  "geometry": {"coordinates":[-0.088354,51.285294],"type":"Point"}
}