{
  "type": "Feature",
  "properties": {
    "iso:country":"GB",
    "sg:address":"Copper Cottage, West Netherton, Milnathort",
    "sg:city":"Kinross",
    "sg:classifiers":[
        {
            "category":"Retail",
            "subcategory":"Driving School",
            "type":"Services"
        }
    ],
    "sg:phone":"+44 1577 862266",
    "sg:postcode":"KY13 0SA",
    "sg:province":"Clackmannanshire",
    "wof:name":"Loch Levan Driving School",
    "wof:placetype":"venue"
},
  "geometry": {"coordinates":[-3.4085099697,56.2340202332],"type":"Point"}
}