{
  "type": "Feature",
  "properties": {
    "addr:full":"25 Church Street Calne Wiltshire SN11 0HY",
    "addr:housenumber":"25",
    "addr:postcode":"sn11 0hy",
    "addr:street":"Church Street",
    "iso:country":"GB",
    "sg:address":"25 Church Street",
    "sg:city":"Calne",
    "sg:classifiers":[
        {
            "category":"Home & Garden",
            "subcategory":"Household Appliances",
            "type":"Retail Goods"
        }
    ],
    "sg:phone":"+44 1249 822686",
    "sg:postcode":"SN11 0HY",
    "sg:province":"Wiltshire",
    "sg:tags":[
        "electrical"
    ],
    "wof:name":"Calne Appliances",
    "wof:placetype":"venue"
},
  "geometry": {"coordinates":[-2.003618,51.437084],"type":"Point"}
}