{
  "type": "Feature",
  "properties": {
    "addr:full":"52 Cannon Hill London Greater London N14 6LH",
    "addr:housenumber":"52",
    "addr:postcode":"n14 6lh",
    "addr:street":"Cannon Hill",
    "iso:country":"GB",
    "sg:address":"52 Cannon Hill",
    "sg:city":"London",
    "sg:classifiers":[
        {
            "category":"Shopping",
            "subcategory":"News",
            "type":"Retail Goods"
        }
    ],
    "sg:postcode":"N14 6LH",
    "sg:province":"Greater London",
    "sg:tags":[
        "newsagent"
    ],
    "wof:name":"Salih Mehmet",
    "wof:placetype":"venue"
},
  "geometry": {"coordinates":[-0.123273,51.624279],"type":"Point"}
}