{
  "type": "Feature",
  "properties": {
    "iso:country":"GB",
    "sg:address":"1e Chandos Rd",
    "sg:city":"Bristol",
    "sg:classifiers":[
        {
            "category":"Arts & Performance",
            "subcategory":"Comedy Club",
            "type":"Entertainment"
        }
    ],
    "sg:postcode":"BS6 6PG",
    "sg:province":"City of Bristol",
    "sg:tags":[
        "japanese"
    ],
    "wof:name":"Inoue,Y,",
    "wof:placetype":"venue"
},
  "geometry": {"coordinates":[-2.606969,51.467476],"type":"Point"}
}