{
  "type": "Feature",
  "properties": {
    "iso:country":"GB",
    "sg:address":"Ashey Rd",
    "sg:city":"Ryde",
    "sg:classifiers":[
        {
            "category":"Restaurant",
            "type":"Food & Drink"
        }
    ],
    "sg:phone":"+44 1983 616598",
    "sg:postcode":"PO33 4BB",
    "sg:province":"Isle of Wight",
    "wof:name":"Ponda Rosa",
    "wof:placetype":"venue"
},
  "geometry": {"coordinates":[-1.166903,50.704582],"type":"Point"}
}