{
  "type": "Feature",
  "properties": {
    "iso:country":"GB",
    "sg:address":"13 White Dirt Lane, Catherington",
    "sg:city":"Waterlooville",
    "sg:classifiers":[
        {
            "category":"Professional",
            "subcategory":"Engineering",
            "type":"Services"
        },
        {
            "category":"Building & Trades",
            "subcategory":"Electrical",
            "type":"Services"
        }
    ],
    "sg:phone":"+44 23 9259 8455",
    "sg:postcode":"PO8 0NB",
    "sg:province":"Hampshire",
    "sg:tags":[
        "engineer",
        "electrician",
        "contractor"
    ],
    "wof:name":"Robotham Electrics",
    "wof:placetype":"venue"
},
  "geometry": {"coordinates":[-1.0003290176,50.9346389771],"type":"Point"}
}