{
  "type": "Feature",
  "properties": {
    "addr:full":"87 Bayston Rd Stoke Newington Greater London N16 7NB",
    "addr:housenumber":"87",
    "addr:postcode":"n16 7nb",
    "addr:street":"Bayston Rd",
    "iso:country":"GB",
    "sg:address":"87 Bayston Rd",
    "sg:city":"Stoke Newington",
    "sg:classifiers":[
        {
            "category":"Building & Trades",
            "subcategory":"Landscaping Services",
            "type":"Services"
        }
    ],
    "sg:phone":"+44 20 7241 1677",
    "sg:postcode":"N16 7NB",
    "sg:province":"Greater London",
    "sg:tags":[
        "contractor"
    ],
    "wof:name":"Elsie Josland Garden Design",
    "wof:placetype":"venue"
},
  "geometry": {"coordinates":[-0.072201,51.560127],"type":"Point"}
}