{
  "type": "Feature",
  "properties": {
    "addr:full":"8 Bakers Lane, Chapelfields Coventry West Midlands CV5 8PR",
    "addr:housenumber":"8",
    "addr:postcode":"cv5 8pr",
    "addr:street":"Bakers Lane Chapelfields",
    "iso:country":"GB",
    "sg:address":"8 Bakers Lane, Chapelfields",
    "sg:city":"Coventry",
    "sg:classifiers":[
        {
            "category":"Real Estate",
            "subcategory":"Architect",
            "type":"Services"
        }
    ],
    "sg:postcode":"CV5 8PR",
    "sg:province":"West Midlands",
    "wof:name":"S  H  Architectural Services Ltd.",
    "wof:placetype":"venue"
},
  "geometry": {"coordinates":[-1.5419939756,52.4073791504],"type":"Point"}
}