{
  "type": "Feature",
  "properties": {
    "addr:full":"91 Leigh Road Eastleigh Hampshire SO50 9DQ",
    "addr:housenumber":"91",
    "addr:postcode":"so50 9dq",
    "addr:street":"Leigh Road",
    "iso:country":"GB",
    "sg:address":"91 Leigh Road",
    "sg:city":"Eastleigh",
    "sg:classifiers":[
        {
            "category":"Professional",
            "subcategory":"Lawyer & Legal Services",
            "type":"Services"
        }
    ],
    "sg:phone":"+44 23 8062 9009",
    "sg:postcode":"SO50 9DQ",
    "sg:province":"Hampshire",
    "sg:tags":[
        "solicitor"
    ],
    "wof:name":"Gammon Bell & Co.",
    "wof:placetype":"venue"
},
  "geometry": {"coordinates":[-1.357139,50.969666],"type":"Point"}
}