{
  "type": "Feature",
  "properties": {
    "iso:country":"GB",
    "sg:address":"99 Heaton Park Road",
    "sg:city":"Newcastle-upon-tyne",
    "sg:classifiers":[
        {
            "category":"Professional",
            "subcategory":"Lawyer & Legal Services",
            "type":"Services"
        }
    ],
    "sg:phone":"+44 191 276 4080",
    "sg:postcode":"NE6 5NR",
    "sg:province":"Tyne and Wear",
    "sg:tags":[
        "advice",
        "counselling"
    ],
    "wof:name":"Victim Support",
    "wof:placetype":"venue"
},
  "geometry": {"coordinates":[-1.5861229897,54.9794960022],"type":"Point"}
}