{
  "type": "Feature",
  "properties": {
    "iso:country":"GB",
    "sg:address":"Lower Santon Lane, Preston",
    "sg:city":"Canterbury",
    "sg:classifiers":[
        {
            "category":"Wholesale",
            "subcategory":"Fruits & Vegetables",
            "type":"Manufacturing & Wholesale Goods"
        }
    ],
    "sg:phone":"+44 1227 722543",
    "sg:postcode":"CT3 1JF",
    "sg:province":"Kent",
    "wof:name":"Santon Farms",
    "wof:placetype":"venue"
},
  "geometry": {"coordinates":[1.22767,51.304417],"type":"Point"}
}