{
  "type": "Feature",
  "properties": {
    "addr:full":"Unit 15 Parkfield Industrial Estate, Culvert Place London Greater London SW11 5BA",
    "addr:housenumber":"unit 15",
    "addr:postcode":"sw11 5ba",
    "addr:street":"Parkfield Industrial;Culvert Place",
    "iso:country":"GB",
    "sg:address":"Unit 15 Parkfield Industrial Estate, Culvert Place",
    "sg:city":"London",
    "sg:classifiers":[
        {
            "category":"Autos & Motor Vehicles",
            "subcategory":"Auto Supplies",
            "type":"Retail Goods"
        }
    ],
    "sg:phone":"+44 20 7498 9333",
    "sg:postcode":"SW11 5BA",
    "sg:province":"Greater London",
    "sg:tags":[
        "tyre"
    ],
    "wof:name":"Compass Tyres",
    "wof:placetype":"venue"
},
  "geometry": {"coordinates":[-0.1538300067,51.4710006714],"type":"Point"}
}