{
  "type": "Feature",
  "properties": {
    "iso:country":"GB",
    "sg:address":"Hall More Farm, Hale",
    "sg:city":"Milnthorpe",
    "sg:classifiers":[
        {
            "category":"Sports & Exercise",
            "subcategory":"Stables",
            "type":"Entertainment"
        }
    ],
    "sg:postcode":"LA7 7BP",
    "sg:province":"Cumbria",
    "sg:tags":[
        "education",
        "equestrian"
    ],
    "wof:name":"Trekkers",
    "wof:placetype":"venue"
},
  "geometry": {"coordinates":[-2.772592,54.226864],"type":"Point"}
}