{
  "type": "Feature",
  "properties": {
    "addr:full":"1 Frisby Avenue, Long Eaton Nottingham Derbyshire NG10 1FL",
    "addr:housenumber":"1",
    "addr:postcode":"ng10 1fl",
    "addr:street":"Frisby Avenue",
    "iso:country":"GB",
    "sg:address":"1 Frisby Avenue, Long Eaton",
    "sg:city":"Nottingham",
    "sg:classifiers":[
        {
            "category":"Building & Trades",
            "subcategory":"Cleaning & Sanitation",
            "type":"Services"
        },
        {
            "category":"Social Services",
            "subcategory":"Adult Care",
            "type":"Services"
        }
    ],
    "sg:phone":"+44 115 946 8119",
    "sg:postcode":"NG10 1FL",
    "sg:province":"Derbyshire",
    "sg:tags":[
        "contracting",
        "domestic"
    ],
    "wof:name":"Clean Sweep",
    "wof:placetype":"venue"
},
  "geometry": {"coordinates":[-1.270296,52.891853],"type":"Point"}
}