{
  "type": "Feature",
  "properties": {
    "addr:full":"21 Turton Heights, Bolton Le Sands Carnforth Lancashire BL2 3DU",
    "addr:housenumber":"21",
    "addr:postcode":"bl2 3du",
    "addr:street":"Turton Heights",
    "iso:country":"GB",
    "sg:address":"21 Turton Heights, Bolton Le Sands",
    "sg:city":"Carnforth",
    "sg:classifiers":[
        {
            "category":"Professional",
            "subcategory":"Business Services",
            "type":"Services"
        }
    ],
    "sg:phone":"+44 1204 305762",
    "sg:postcode":"BL2 3DU",
    "sg:province":"Lancashire",
    "sg:tags":[
        "import",
        "export",
        "agent"
    ],
    "wof:name":"West Wind International Ltd.",
    "wof:placetype":"venue"
},
  "geometry": {"coordinates":[-2.4100790024,53.609828949],"type":"Point"}
}