{
  "type": "Feature",
  "properties": {
    "addr:full":"12 George St Glossop Derbyshire SK13 8AY",
    "addr:housenumber":"12",
    "addr:postcode":"sk13 8ay",
    "addr:street":"George St",
    "iso:country":"GB",
    "sg:address":"12 George St",
    "sg:city":"Glossop",
    "sg:classifiers":[
        {
            "category":"Home & Garden",
            "subcategory":"Home Furnishings",
            "type":"Retail Goods"
        }
    ],
    "sg:phone":"+44 1457 862584",
    "sg:postcode":"SK13 8AY",
    "sg:province":"Derbyshire",
    "sg:tags":[
        "blind",
        "curtain",
        "fitting"
    ],
    "wof:name":"Creative Curtains",
    "wof:placetype":"venue"
},
  "geometry": {"coordinates":[-1.9528230429,53.4431686401],"type":"Point"}
}