{
  "type": "Feature",
  "properties": {
    "addr:full":"Blundell Ho, Goodwood Rd New Cross Greater London SE14 6BL",
    "addr:postcode":"se14 6bl",
    "addr:street":"Goodwood Rd New",
    "iso:country":"GB",
    "sg:address":"Blundell Ho, Goodwood Rd",
    "sg:city":"New Cross",
    "sg:classifiers":[
        {
            "category":"Home & Garden",
            "subcategory":"Carpets & Floor Coverings",
            "type":"Retail Goods"
        }
    ],
    "sg:phone":"+44 20 8692 7870",
    "sg:postcode":"SE14 6BL",
    "sg:province":"Greater London",
    "sg:tags":[
        "cleaner",
        "upholstery"
    ],
    "wof:name":"A1 Printz London Wash Ltd",
    "wof:placetype":"venue"
},
  "geometry": {"coordinates":[-0.040459,51.47496],"type":"Point"}
}