{
  "type": "Feature",
  "properties": {
    "iso:country":"GB",
    "sg:address":"57 Primrose Drive, Kingsnorth",
    "sg:city":"Ashford",
    "sg:classifiers":[
        {
            "category":"Building & Trades",
            "subcategory":"Landscaping Services",
            "type":"Services"
        }
    ],
    "sg:phone":"+44 1233 502102",
    "sg:postcode":"TN23 3NP",
    "sg:province":"Kent",
    "sg:tags":[
        "consultant"
    ],
    "wof:name":"Design & Contracting",
    "wof:placetype":"venue"
},
  "geometry": {"coordinates":[0.869198,51.120338],"type":"Point"}
}