{
  "type": "Feature",
  "properties": {
    "iso:country":"GB",
    "sg:address":"6 Little Hivings",
    "sg:city":"Chesham",
    "sg:classifiers":[
        {
            "category":"Building & Trades",
            "subcategory":"Landscaping Services",
            "type":"Services"
        }
    ],
    "sg:phone":"+44 1494 772395",
    "sg:postcode":"HP5 2NA",
    "sg:province":"Buckinghamshire",
    "sg:tags":[
        "landscape",
        "contractor"
    ],
    "wof:name":"Pete Thornhill",
    "wof:placetype":"venue"
},
  "geometry": {"coordinates":[-0.62202,51.725304],"type":"Point"}
}