{
  "type": "Feature",
  "properties": {
    "addr:full":"3 Inkerman St Llanelli Carmarthenshire SA15 1RY",
    "addr:housenumber":"3",
    "addr:postcode":"sa15 1ry",
    "addr:street":"Inkerman St",
    "iso:country":"GB",
    "sg:address":"3 Inkerman St",
    "sg:city":"Llanelli",
    "sg:classifiers":[
        {
            "category":"Health Services",
            "subcategory":"Dentist",
            "type":"Services"
        }
    ],
    "sg:phone":"+44 1554 751248",
    "sg:postcode":"SA15 1RY",
    "sg:province":"Carmarthenshire",
    "wof:name":"Dr Newton D Johnson",
    "wof:placetype":"venue"
},
  "geometry": {"coordinates":[-4.161042,51.680084],"type":"Point"}
}