{
  "type": "Feature",
  "properties": {
    "addr:full":"Walker Cousins Ho, Portsmouth Rd Southampton Hampshire SO31 8ES",
    "addr:postcode":"so31 8es",
    "addr:street":"Portsmouth Rd",
    "iso:country":"GB",
    "sg:address":"Walker Cousins Ho, Portsmouth Rd",
    "sg:city":"Southampton",
    "sg:classifiers":[
        {
            "category":"Home & Garden",
            "subcategory":"Building Materials",
            "type":"Retail Goods"
        }
    ],
    "sg:phone":"+44 23 8040 7303",
    "sg:postcode":"SO31 8ES",
    "sg:province":"Hampshire",
    "sg:tags":[
        "ventilator",
        "ventilation",
        "system"
    ],
    "wof:name":"Southpoint Developments Ltd",
    "wof:placetype":"venue"
},
  "geometry": {"coordinates":[-1.3167500496,50.889629364],"type":"Point"}
}