{
  "type": "Feature",
  "properties": {
    "addr:full":"73 Paxton Cres, Armthorpe Doncaster South Yorkshire DN3 2AW",
    "addr:housenumber":"73",
    "addr:postcode":"dn3 2aw",
    "addr:street":"Paxton Cres",
    "iso:country":"GB",
    "sg:address":"73 Paxton Cres, Armthorpe",
    "sg:city":"Doncaster",
    "sg:classifiers":[
        {
            "category":"Shopping",
            "subcategory":"Department Store",
            "type":"Retail Goods"
        }
    ],
    "sg:postcode":"DN3 2AW",
    "sg:province":"South Yorkshire",
    "wof:name":"Dairies Early Bird",
    "wof:placetype":"venue"
},
  "geometry": {"coordinates":[-1.0723409653,53.5380706787],"type":"Point"}
}