{
  "type": "Feature",
  "properties": {
    "addr:full":"Compston Road Ambleside Cumbria LA22 9AD",
    "addr:postcode":"la22 9ad",
    "addr:street":"Compston Road",
    "iso:country":"GB",
    "sg:address":"Compston Road",
    "sg:city":"Ambleside",
    "sg:classifiers":[
        {
            "category":"Cinema",
            "subcategory":"Movie Theater",
            "type":"Entertainment"
        }
    ],
    "sg:phone":"+44 15394 33845",
    "sg:postcode":"LA22 9AD",
    "sg:province":"Cumbria",
    "wof:name":"Zeffirellis Cinema",
    "wof:placetype":"venue"
},
  "geometry": {"coordinates":[-2.963408947,54.4321594238],"type":"Point"}
}