{
  "type": "Feature",
  "properties": {
    "iso:country":"GB",
    "sg:address":"4 Station Road, Great Sankey",
    "sg:city":"Warrington",
    "sg:classifiers":[
        {
            "category":"Shopping",
            "subcategory":"Pets & Pet Supplies",
            "type":"Retail Goods"
        }
    ],
    "sg:postcode":"WA5 1RQ",
    "sg:province":"Cheshire",
    "wof:name":"Brookfield Pets",
    "wof:placetype":"venue"
},
  "geometry": {"coordinates":[-2.649601,53.391815],"type":"Point"}
}