{
  "type": "Feature",
  "properties": {
    "addr:full":"Unit 2 Kingsdale Industrial Estate, Regina Road Chelmsford Essex CM1 1PE",
    "addr:housenumber":"unit 2",
    "addr:postcode":"cm1 1pe",
    "addr:street":"Kingsdale Industrial Estate Regina Road",
    "iso:country":"GB",
    "sg:address":"Unit 2 Kingsdale Industrial Estate, Regina Road",
    "sg:city":"Chelmsford",
    "sg:classifiers":[
        {
            "category":"Manufacturing",
            "subcategory":"Building Materials",
            "type":"Manufacturing & Wholesale Goods"
        }
    ],
    "sg:phone":"+44 1245 495777",
    "sg:postcode":"CM1 1PE",
    "sg:province":"Essex",
    "sg:tags":[
        "merchant",
        "builder"
    ],
    "wof:name":"P S Building Supplies Ltd",
    "wof:placetype":"venue"
},
  "geometry": {"coordinates":[0.4778999984,51.7380905151],"type":"Point"}
}