{
  "type": "Feature",
  "properties": {
    "iso:country":"GB",
    "sg:address":"The Old Rectory, Tattingstone",
    "sg:city":"Ipswich",
    "sg:classifiers":[
        {
            "category":"Social Services",
            "subcategory":"Retirement Home",
            "type":"Services"
        }
    ],
    "sg:postcode":"IP9 2NE",
    "sg:province":"Suffolk",
    "sg:tags":[
        "residential",
        "care"
    ],
    "wof:name":"Wyman,Richard,",
    "wof:placetype":"venue"
},
  "geometry": {"coordinates":[1.1089990139,51.9918441772],"type":"Point"}
}