{
  "type": "Feature",
  "properties": {
    "addr:full":"2 Southlands Court Bromley Kent BR2 9QU",
    "addr:housenumber":"2",
    "addr:postcode":"br2 9qu",
    "addr:street":"Southlands Court",
    "iso:country":"GB",
    "sg:address":"2 Southlands Court",
    "sg:city":"Bromley",
    "sg:classifiers":[
        {
            "category":"Building & Trades",
            "subcategory":"Construction",
            "type":"Services"
        }
    ],
    "sg:phone":"+44 20 8464 2023",
    "sg:postcode":"BR2 9QU",
    "sg:province":"Kent",
    "sg:tags":[
        "decorator",
        "painter"
    ],
    "wof:name":"L K Decorators",
    "wof:placetype":"venue"
},
  "geometry": {"coordinates":[0.0311409999,51.392780304],"type":"Point"}
}