{
  "type": "Feature",
  "properties": {
    "iso:country":"GB",
    "sg:address":"150 Hayes Chase",
    "sg:city":"West Wickham",
    "sg:classifiers":[
        {
            "category":"Communications",
            "subcategory":"Radio Station",
            "type":"Services"
        }
    ],
    "sg:postcode":"BR4 0JE",
    "sg:province":"Kent",
    "sg:tags":[
        "consultant",
        "medium"
    ],
    "wof:name":"All Media Direct Ltd.",
    "wof:placetype":"venue"
},
  "geometry": {"coordinates":[-0.004538,51.385551],"type":"Point"}
}