{
  "type": "Feature",
  "properties": {
    "addr:full":"6 Gwerthonor Place, Gilfach Bargoed Caerphilly CF81 8JQ",
    "addr:housenumber":"6",
    "addr:postcode":"cf81 8jq",
    "addr:street":"Gwerthonor Place Gilfach",
    "iso:country":"GB",
    "sg:address":"6 Gwerthonor Place, Gilfach",
    "sg:city":"Bargoed",
    "sg:classifiers":[
        {
            "category":"Health Services",
            "subcategory":"Podiatrist",
            "type":"Services"
        }
    ],
    "sg:postcode":"CF81 8JQ",
    "sg:province":"Caerphilly",
    "sg:tags":[
        "podiatrists",
        "chiropodist"
    ],
    "wof:name":"Bargoed Chiropody Clinic",
    "wof:placetype":"venue"
},
  "geometry": {"coordinates":[-3.226443,51.677746],"type":"Point"}
}