{
  "type": "Feature",
  "properties": {
    "addr:full":"13 North Seaton Road Ashington Northumberland NE63 0AF",
    "addr:housenumber":"13",
    "addr:postcode":"ne63 0af",
    "addr:street":"North Seaton Road;Northumberland",
    "iso:country":"GB",
    "sg:address":"13 North Seaton Road",
    "sg:city":"Ashington",
    "sg:classifiers":[
        {
            "category":"Professional",
            "subcategory":"Business Services",
            "type":"Services"
        },
        {
            "category":"Casinos & Gambling",
            "type":"Entertainment"
        }
    ],
    "sg:phone":"+44 1670 813388",
    "sg:postcode":"NE63 0AF",
    "sg:province":"Northumberland",
    "sg:tags":[
        "turf",
        "accountant",
        "bookmaker"
    ],
    "wof:name":"Chisholm Bookmakers Ltd",
    "wof:placetype":"venue"
},
  "geometry": {"coordinates":[-1.568875,55.182625],"type":"Point"}
}