{
  "type": "Feature",
  "properties": {
    "iso:country":"GB",
    "sg:address":"113 Liverpool Road, Crosby",
    "sg:city":"Liverpool",
    "sg:classifiers":[
        {
            "category":"Autos & Motor Vehicles",
            "subcategory":"Automobile Sales",
            "type":"Retail Goods"
        }
    ],
    "sg:phone":"+44 151 924 2274",
    "sg:postcode":"L23 5TD",
    "sg:province":"Merseyside",
    "sg:tags":[
        "car"
    ],
    "wof:name":"Ryders Autoservice",
    "wof:placetype":"venue"
},
  "geometry": {"coordinates":[-3.0237400532,53.4883499146],"type":"Point"}
}