{
  "type": "Feature",
  "properties": {
    "iso:country":"GB",
    "sg:address":"Unit 1 Devonshire Buildings, Works Road, Hollingwood",
    "sg:city":"Chesterfield",
    "sg:classifiers":[
        {
            "category":"Transit Center",
            "subcategory":"Passenger",
            "type":"Transportation"
        }
    ],
    "sg:phone":"+44 1246 477277",
    "sg:postcode":"S43 2PE",
    "sg:province":"Derbyshire",
    "sg:tags":[
        "airport"
    ],
    "wof:name":"Keith's Private Hire",
    "wof:placetype":"venue"
},
  "geometry": {"coordinates":[-1.376959,53.263435],"type":"Point"}
}