{
  "type": "Feature",
  "properties": {
    "addr:full":"Imperial Annex, 48 The Street, Charlwood Horley Surrey RH6 0DF",
    "addr:housenumber":"48",
    "addr:postcode":"rh6 0df",
    "addr:street":"The Street",
    "iso:country":"GB",
    "sg:address":"Imperial Annex, 48 The Street, Charlwood",
    "sg:city":"Horley",
    "sg:classifiers":[
        {
            "category":"Real Estate",
            "subcategory":"Developer",
            "type":"Services"
        }
    ],
    "sg:postcode":"RH6 0DF",
    "sg:province":"Surrey",
    "sg:tags":[
        "property"
    ],
    "wof:name":"Imperial Buildings (Horley) Ltd",
    "wof:placetype":"venue"
},
  "geometry": {"coordinates":[-0.228463,51.156803],"type":"Point"}
}