{
  "type": "Feature",
  "properties": {
    "addr:full":"106 Montgomery Street Irvine North Ayrshire KA12 8PW",
    "addr:housenumber":"106",
    "addr:postcode":"ka12 8pw",
    "addr:street":"Montgomery Street",
    "iso:country":"GB",
    "sg:address":"106 Montgomery Street",
    "sg:city":"Irvine",
    "sg:classifiers":[
        {
            "category":"Professional",
            "subcategory":"Printing & Photocopies",
            "type":"Services"
        }
    ],
    "sg:phone":"+44 1294 279955",
    "sg:postcode":"KA12 8PW",
    "sg:province":"North Ayrshire",
    "sg:tags":[
        "printer"
    ],
    "wof:name":"C S Printers",
    "wof:placetype":"venue"
},
  "geometry": {"coordinates":[-4.677349,55.610584],"type":"Point"}
}