{
  "type": "Feature",
  "properties": {
    "iso:country":"GB",
    "sg:address":"427 Linthorpe Road",
    "sg:city":"Middlesbrough",
    "sg:classifiers":[
        {
            "category":"Recreation",
            "subcategory":"Water Park",
            "type":"Entertainment"
        }
    ],
    "sg:phone":"+44 1642 648050",
    "sg:postcode":"TS5 6HH",
    "sg:province":"North Yorkshire",
    "sg:tags":[
        "supplier",
        "bottled"
    ],
    "wof:name":"Bored Water Services Ltd.",
    "wof:placetype":"venue"
},
  "geometry": {"coordinates":[-1.2427179813,54.5616531372],"type":"Point"}
}