{
  "type": "Feature",
  "properties": {
    "addr:full":"17 Adelaide Gro Stockton-on-tees Durham TS18 5BT",
    "addr:housenumber":"17",
    "addr:postcode":"ts18 5bt",
    "addr:street":"Gro Stockton-On-Tees",
    "iso:country":"GB",
    "sg:address":"17 Adelaide Gro",
    "sg:city":"Stockton-on-tees",
    "sg:classifiers":[
        {
            "category":"Building & Trades",
            "subcategory":"Construction",
            "type":"Services"
        }
    ],
    "sg:phone":"+44 1642 582087",
    "sg:postcode":"TS18 5BT",
    "sg:province":"Durham",
    "sg:tags":[
        "tiling",
        "contractor"
    ],
    "wof:name":"Malcolm Wilkinson",
    "wof:placetype":"venue"
},
  "geometry": {"coordinates":[-1.34108,54.556614],"type":"Point"}
}