{
  "type": "Feature",
  "properties": {
    "addr:full":"2 Kidlington Centre, High Street Kidlington Buckinghamshire OX5 2DL",
    "addr:housenumber":"2",
    "addr:postcode":"ox5 2dl",
    "addr:street":"Kidlington Centre High Street",
    "iso:country":"GB",
    "sg:address":"2 Kidlington Centre, High Street",
    "sg:city":"Kidlington",
    "sg:classifiers":[
        {
            "category":"Food & Beverages",
            "subcategory":"Bakery",
            "type":"Retail Goods"
        }
    ],
    "sg:phone":"+44 1865 376751",
    "sg:postcode":"OX5 2DL",
    "sg:province":"Buckinghamshire",
    "sg:tags":[
        "shop",
        "baker"
    ],
    "wof:name":"la Patisserie",
    "wof:placetype":"venue"
},
  "geometry": {"coordinates":[-1.290104,51.823048],"type":"Point"}
}