{
  "type": "Feature",
  "properties": {
    "addr:full":"Old School House Doncaster South Yorkshire DN5 7BZ",
    "addr:postcode":"dn5 7bz",
    "iso:country":"GB",
    "sg:address":"Old School House",
    "sg:city":"Doncaster",
    "sg:classifiers":[
        {
            "category":"Shopping",
            "subcategory":"Department Store",
            "type":"Retail Goods"
        },
        {
            "category":"Food & Beverages",
            "subcategory":"Groceries & Convenience Stores",
            "type":"Retail Goods"
        }
    ],
    "sg:phone":"+44 1977 642856",
    "sg:postcode":"DN5 7BZ",
    "sg:province":"South Yorkshire",
    "wof:name":"Clayton Post Office",
    "wof:placetype":"venue"
},
  "geometry": {"coordinates":[-1.207219,53.54187],"type":"Point"}
}