{
  "type": "Feature",
  "properties": {
    "addr:full":"King Street Brixham Devon TQ5 9TF",
    "addr:postcode":"tq5 9tf",
    "addr:street":"King Street",
    "iso:country":"GB",
    "sg:address":"King Street",
    "sg:city":"Brixham",
    "sg:classifiers":[
        {
            "category":"Recreation",
            "subcategory":"Amusement Park",
            "type":"Entertainment"
        }
    ],
    "sg:phone":"+44 1803 855658",
    "sg:postcode":"TQ5 9TF",
    "sg:province":"Devon",
    "sg:tags":[
        "arcade"
    ],
    "wof:name":"The Harbour Side Arcade",
    "wof:placetype":"venue"
},
  "geometry": {"coordinates":[-3.509989,50.39677],"type":"Point"}
}