{
  "type": "Feature",
  "properties": {
    "iso:country":"GB",
    "sg:address":"The Red House, 74-76 High Street",
    "sg:city":"Bushey",
    "sg:classifiers":[
        {
            "category":"Banks & Credit Unions",
            "subcategory":"Financial Services",
            "type":"Services"
        }
    ],
    "sg:phone":"+44 20 8950 0047",
    "sg:postcode":"WD23 3HA",
    "sg:province":"Hertfordshire",
    "sg:tags":[
        "consultant"
    ],
    "wof:name":"Pearce Arrow Ltd.",
    "wof:placetype":"venue"
},
  "geometry": {"coordinates":[-0.365439,51.64484],"type":"Point"}
}