{
  "type": "Feature",
  "properties": {
    "addr:full":"Northgate Hartlepool Durham TS24 0LT",
    "addr:postcode":"ts24 0lt",
    "addr:street":"Northgate",
    "iso:country":"GB",
    "sg:address":"Northgate",
    "sg:city":"Hartlepool",
    "sg:classifiers":[
        {
            "category":"Education",
            "subcategory":"Library",
            "type":"Public Place"
        },
        {
            "category":"Government",
            "subcategory":"Office",
            "type":"Public Place"
        }
    ],
    "sg:phone":"+44 1429 268169",
    "sg:postcode":"TS24 0LT",
    "sg:province":"Durham",
    "sg:tags":[
        "book",
        "local"
    ],
    "wof:name":"Northgate Branch Library",
    "wof:placetype":"venue"
},
  "geometry": {"coordinates":[-1.194052,54.701534],"type":"Point"}
}