{
  "type": "Feature",
  "properties": {
    "addr:full":"Odd Fellows Hall, Sutton Road, Terrington St Clement King's Lynn Norfolk PE30 4PJ",
    "addr:postcode":"pe30 4pj",
    "addr:street":"Sutton Road;Lynn",
    "iso:country":"GB",
    "sg:address":"Odd Fellows Hall, Sutton Road, Terrington St Clement",
    "sg:city":"King's Lynn",
    "sg:classifiers":[
        {
            "category":"Farming",
            "subcategory":"Nursery",
            "type":"Manufacturing & Wholesale Goods"
        }
    ],
    "sg:phone":"+44 1553 829813",
    "sg:postcode":"PE30 4PJ",
    "sg:province":"Norfolk",
    "sg:tags":[
        "creche"
    ],
    "wof:name":"Phoenix Montessori Nursery School",
    "wof:placetype":"venue"
},
  "geometry": {"coordinates":[0.4232,52.754051],"type":"Point"}
}