{
  "type": "Feature",
  "properties": {
    "addr:full":"Cannons Meadow, Tewin Welwyn Hertfordshire AL6 0JU",
    "addr:postcode":"al6 0ju",
    "addr:street":"Cannons Meadow Tewin",
    "iso:country":"GB",
    "sg:address":"Cannons Meadow, Tewin",
    "sg:city":"Welwyn",
    "sg:classifiers":[
        {
            "category":"Education",
            "subcategory":"School",
            "type":"Public Place"
        }
    ],
    "sg:phone":"+44 1438 717378",
    "sg:postcode":"AL6 0JU",
    "sg:province":"Hertfordshire",
    "sg:tags":[
        "local",
        "authority"
    ],
    "wof:name":"Tewin Cowper School",
    "wof:placetype":"venue"
},
  "geometry": {"coordinates":[-0.156229,51.818802],"type":"Point"}
}