{
  "type": "Feature",
  "properties": {
    "iso:country":"GB",
    "sg:address":"10 Commercial Road, Kirkstall",
    "sg:city":"Leeds",
    "sg:classifiers":[
        {
            "category":"Shopping",
            "subcategory":"Books",
            "type":"Retail Goods"
        }
    ],
    "sg:postcode":"LS5 3AQ",
    "sg:province":"West Yorkshire",
    "sg:tags":[
        "second-hand"
    ],
    "wof:name":"The Bookshop",
    "wof:placetype":"venue"
},
  "geometry": {"coordinates":[-1.601226,53.814651],"type":"Point"}
}