{
  "type": "Feature",
  "properties": {
    "addr:full":"65 Bishops Avenue Bromley Kent BR1 3ET",
    "addr:housenumber":"65",
    "addr:postcode":"br1 3et",
    "addr:street":"Bishops Avenue",
    "iso:country":"GB",
    "sg:address":"65 Bishops Avenue",
    "sg:city":"Bromley",
    "sg:classifiers":[
        {
            "category":"Building & Trades",
            "subcategory":"Construction",
            "type":"Services"
        }
    ],
    "sg:phone":"+44 20 8460 1621",
    "sg:postcode":"BR1 3ET",
    "sg:province":"Kent",
    "sg:tags":[
        "heating",
        "contractor"
    ],
    "wof:name":"G H Tyce",
    "wof:placetype":"venue"
},
  "geometry": {"coordinates":[0.028509,51.401413],"type":"Point"}
}