{
  "type": "Feature",
  "properties": {
    "addr:full":"2 Overton Farm Cottages, Blairhall Dunfermline Fife KY12 9HA",
    "addr:housenumber":"2",
    "addr:postcode":"ky12 9ha",
    "addr:street":"Overton Farm Cottages",
    "iso:country":"GB",
    "sg:address":"2 Overton Farm Cottages, Blairhall",
    "sg:city":"Dunfermline",
    "sg:classifiers":[
        {
            "category":"Home & Garden",
            "subcategory":"Building Materials",
            "type":"Retail Goods"
        }
    ],
    "sg:phone":"+44 1383 851585",
    "sg:postcode":"KY12 9HA",
    "sg:province":"Fife",
    "sg:tags":[
        "roofing",
        "rafter",
        "beams"
    ],
    "wof:name":"The Willow Works",
    "wof:placetype":"venue"
},
  "geometry": {"coordinates":[-3.6006190777,56.09167099],"type":"Point"}
}