{
  "type": "Feature",
  "properties": {
    "addr:full":"10 Craigleith Road Edinburgh City of Edinburgh EH4 2DP",
    "addr:housenumber":"10",
    "addr:postcode":"eh4 2dp",
    "addr:street":"Craigleith Road",
    "iso:country":"GB",
    "sg:address":"10 Craigleith Road",
    "sg:city":"Edinburgh",
    "sg:classifiers":[
        {
            "category":"Restaurant",
            "type":"Food & Drink"
        }
    ],
    "sg:phone":"+44 131 332 3362",
    "sg:postcode":"EH4 2DP",
    "sg:province":"City of Edinburgh",
    "sg:tags":[
        "indian",
        "-"
    ],
    "wof:name":"The Far Pavilions",
    "wof:placetype":"venue"
},
  "geometry": {"coordinates":[-3.2269260883,55.9583930969],"type":"Point"}
}