{
  "type": "Feature",
  "properties": {
    "iso:country":"GB",
    "sg:address":"11 Leven Avenue",
    "sg:city":"Bournemouth",
    "sg:classifiers":[
        {
            "category":"Social Services",
            "subcategory":"Retirement Home",
            "type":"Services"
        },
        {
            "category":"Government",
            "subcategory":"Office",
            "type":"Public Place"
        }
    ],
    "sg:phone":"+44 1202 764415",
    "sg:postcode":"BH4 9LH",
    "sg:province":"Dorset",
    "sg:tags":[
        "residential",
        "local",
        "care"
    ],
    "wof:name":"Leven House",
    "wof:placetype":"venue"
},
  "geometry": {"coordinates":[-1.891612,50.72644],"type":"Point"}
}