{
  "type": "Feature",
  "properties": {
    "addr:full":"7 Fowey Clo, Lordswood Chatham Kent ME5 8JX",
    "addr:housenumber":"7",
    "addr:postcode":"me5 8jx",
    "addr:street":"Fowey Clo Lordswood",
    "iso:country":"GB",
    "sg:address":"7 Fowey Clo, Lordswood",
    "sg:city":"Chatham",
    "sg:classifiers":[
        {
            "category":"Building & Trades",
            "subcategory":"Landscaping Services",
            "type":"Services"
        }
    ],
    "sg:postcode":"ME5 8JX",
    "sg:province":"Kent",
    "sg:tags":[
        "landscape",
        "contractor"
    ],
    "wof:name":"Orme,David,",
    "wof:placetype":"venue"
},
  "geometry": {"coordinates":[0.5421220064,51.3496894836],"type":"Point"}
}