{
  "type": "Feature",
  "properties": {
    "iso:country":"GB",
    "sg:address":"Lower Kiosk, Wade Lane",
    "sg:city":"Leeds",
    "sg:classifiers":[
        {
            "category":"Shopping",
            "subcategory":"Luggage & Leather Goods",
            "type":"Retail Goods"
        }
    ],
    "sg:postcode":"LS2 8NG",
    "sg:province":"West Yorkshire",
    "sg:tags":[
        "shop",
        "leathergoods"
    ],
    "wof:name":"Skin 2",
    "wof:placetype":"venue"
},
  "geometry": {"coordinates":[-1.54402,53.801579],"type":"Point"}
}