{
  "type": "Feature",
  "properties": {
    "addr:full":"Webb Hill Farm, Heathfield Taunton Devon TA4 1DP",
    "addr:postcode":"ta4 1dp",
    "addr:street":"Webb Hill;Heathfield",
    "iso:country":"GB",
    "sg:address":"Webb Hill Farm, Heathfield",
    "sg:city":"Taunton",
    "sg:classifiers":[
        {
            "category":"Farming",
            "subcategory":"Livestock Farm",
            "type":"Manufacturing & Wholesale Goods"
        }
    ],
    "sg:postcode":"TA4 1DP",
    "sg:province":"Devon",
    "sg:tags":[
        "others"
    ],
    "wof:name":"W J Weatherill",
    "wof:placetype":"venue"
},
  "geometry": {"coordinates":[-3.197327,51.030087],"type":"Point"}
}