{
  "type": "Feature",
  "properties": {
    "addr:full":"221 Cranbrook Road Ilford Essex IG1 4TD",
    "addr:housenumber":"221",
    "addr:postcode":"ig1 4td",
    "addr:street":"Cranbrook Road",
    "iso:country":"GB",
    "sg:address":"221 Cranbrook Road",
    "sg:city":"Ilford",
    "sg:classifiers":[
        {
            "category":"Banks & Credit Unions",
            "subcategory":"Bank",
            "type":"Services"
        },
        {
            "category":"Professional",
            "subcategory":"Business Services",
            "type":"Services"
        }
    ],
    "sg:phone":"+44 20 8554 9665",
    "sg:postcode":"IG1 4TD",
    "sg:province":"Essex",
    "sg:tags":[
        "stocktaking",
        "inventory"
    ],
    "wof:name":"Whittome Clarke & Co Ltd",
    "wof:placetype":"venue"
},
  "geometry": {"coordinates":[0.0674490035,51.5631980896],"type":"Point"}
}