{
  "type": "Feature",
  "properties": {
    "addr:full":"A, 74 Church La Rickmansworth Hertfordshire WD3 2HE",
    "addr:housenumber":"74",
    "addr:postcode":"wd3 2he",
    "addr:street":"A;Church La Rickmansworth",
    "iso:country":"GB",
    "sg:address":"A, 74 Church La",
    "sg:city":"Rickmansworth",
    "sg:classifiers":[
        {
            "category":"Building & Trades",
            "subcategory":"Construction",
            "type":"Services"
        }
    ],
    "sg:phone":"+44 1923 712871",
    "sg:postcode":"WD3 2HE",
    "sg:province":"Hertfordshire",
    "sg:tags":[
        "builder"
    ],
    "wof:name":"Tudor Construction",
    "wof:placetype":"venue"
},
  "geometry": {"coordinates":[-0.4682750106,51.6414375305],"type":"Point"}
}