{
  "type": "Feature",
  "properties": {
    "addr:full":"12 Cannon Street Preston Lancashire PR1 3NR",
    "addr:housenumber":"12",
    "addr:postcode":"pr1 3nr",
    "addr:street":"Cannon Street",
    "iso:country":"GB",
    "sg:address":"12 Cannon Street",
    "sg:city":"Preston",
    "sg:classifiers":[
        {
            "category":"Cafe",
            "type":"Food & Drink"
        }
    ],
    "sg:phone":"+44 1772 887982",
    "sg:postcode":"PR1 3NR",
    "sg:province":"Lancashire",
    "sg:tags":[
        "tea",
        "room"
    ],
    "wof:name":"Carsons",
    "wof:placetype":"venue"
},
  "geometry": {"coordinates":[-2.6993229389,53.7574691772],"type":"Point"}
}