{
  "type": "Feature",
  "properties": {
    "addr:full":"30 Hurst Meadow Rochdale Lancashire OL16 4QP",
    "addr:housenumber":"30",
    "addr:postcode":"ol16 4qp",
    "addr:street":"Hurst Meadow Rochdale",
    "iso:country":"GB",
    "sg:address":"30 Hurst Meadow",
    "sg:city":"Rochdale",
    "sg:classifiers":[
        {
            "category":"Professional",
            "subcategory":"Art Services",
            "type":"Services"
        },
        {
            "category":"Building & Trades",
            "subcategory":"Construction",
            "type":"Services"
        }
    ],
    "sg:phone":"+44 1706 759599",
    "sg:postcode":"OL16 4QP",
    "sg:province":"Lancashire",
    "sg:tags":[
        "decorator",
        "painter"
    ],
    "wof:name":"Fisher Marshall Decorators",
    "wof:placetype":"venue"
},
  "geometry": {"coordinates":[-2.1387090683,53.5951461792],"type":"Point"}
}