{
  "type": "Feature",
  "properties": {
    "iso:country":"GB",
    "sg:address":"151 Derby Road",
    "sg:city":"Loughborough",
    "sg:classifiers":[
        {
            "category":"Shopping",
            "subcategory":"News",
            "type":"Retail Goods"
        }
    ],
    "sg:phone":"+44 1509 214095",
    "sg:postcode":"LE11 5HJ",
    "sg:province":"Leicestershire",
    "sg:tags":[
        "newsagent"
    ],
    "wof:name":"R & V Newsagents",
    "wof:placetype":"venue"
},
  "geometry": {"coordinates":[-1.2168380022,52.7771492004],"type":"Point"}
}