{
  "type": "Feature",
  "properties": {
    "addr:full":"Inshop Unit 1-2 Telegraph Way Liverpool Merseyside L32 2BL",
    "addr:housenumber":"unit 1-2",
    "addr:postcode":"l32 2bl",
    "addr:street":"Telegraph Way",
    "iso:country":"GB",
    "sg:address":"Inshop Unit 1-2 Telegraph Way",
    "sg:city":"Liverpool",
    "sg:classifiers":[
        {
            "category":"Home & Garden",
            "subcategory":"Furniture",
            "type":"Retail Goods"
        }
    ],
    "sg:postcode":"L32 2BL",
    "sg:province":"Merseyside",
    "wof:name":"Norris,P,",
    "wof:placetype":"venue"
},
  "geometry": {"coordinates":[-2.89984,53.491009],"type":"Point"}
}