{
  "type": "Feature",
  "properties": {
    "addr:full":"47 Nash Road Newport Newport NP19 4NH",
    "addr:housenumber":"47",
    "addr:postcode":"np19 4nh",
    "addr:street":"Nash Road",
    "iso:country":"GB",
    "sg:address":"47 Nash Road",
    "sg:city":"Newport",
    "sg:classifiers":[
        {
            "category":"Retail",
            "subcategory":"Funeral Services",
            "type":"Services"
        }
    ],
    "sg:phone":"+44 1633 278329",
    "sg:postcode":"NP19 4NH",
    "sg:province":"Newport",
    "wof:name":"Lyndon Bassett Funeral Directors",
    "wof:placetype":"venue"
},
  "geometry": {"coordinates":[-2.956397,51.578781],"type":"Point"}
}