{
  "type": "Feature",
  "properties": {
    "addr:full":"The Hanger, Station Road, Theale Reading Berkshire RG7 1DP",
    "addr:postcode":"rg7 1dp",
    "addr:street":"Station Road",
    "iso:country":"GB",
    "sg:address":"The Hanger, Station Road, Theale",
    "sg:city":"Reading",
    "sg:classifiers":[
        {
            "category":"Utilities",
            "subcategory":"Refuse",
            "type":"Services"
        }
    ],
    "sg:phone":"+44 118 930 4591",
    "sg:postcode":"RG7 1DP",
    "sg:province":"Berkshire",
    "sg:tags":[
        "skip",
        "hire"
    ],
    "wof:name":"A J Kelly Skip Hire",
    "wof:placetype":"venue"
},
  "geometry": {"coordinates":[-0.96607,51.396381],"type":"Point"}
}