{
  "type": "Feature",
  "properties": {
    "addr:full":"Chalon Way West St. Helens Merseyside WA10 1BF",
    "addr:postcode":"wa10 1bf",
    "addr:street":"Chalon Way West",
    "iso:country":"GB",
    "sg:address":"Chalon Way West",
    "sg:city":"St. Helens",
    "sg:classifiers":[
        {
            "category":"Food & Beverages",
            "subcategory":"Supermarket",
            "type":"Retail Goods"
        }
    ],
    "sg:phone":"+44 1744 451297",
    "sg:postcode":"WA10 1BF",
    "sg:province":"Merseyside",
    "wof:name":"Safeway Creche",
    "wof:placetype":"venue"
},
  "geometry": {"coordinates":[-2.7399890423,53.4511833191],"type":"Point"}
}