{
  "type": "Feature",
  "properties": {
    "iso:country":"GB",
    "sg:address":"Fire Station, Byrom Street",
    "sg:city":"Blackburn",
    "sg:classifiers":[
        {
            "category":"Government",
            "subcategory":"Fire Station",
            "type":"Public Place"
        }
    ],
    "sg:phone":"+44 1254 262721",
    "sg:postcode":"BB2 2LE",
    "sg:province":"Lancashire",
    "wof:name":"Fire Brigade",
    "wof:placetype":"venue"
},
  "geometry": {"coordinates":[-2.488009,53.74485],"type":"Point"}
}