{
  "type": "Feature",
  "properties": {
    "addr:full":"50 William Street Tayport Fife DD6 9HQ",
    "addr:housenumber":"50",
    "addr:postcode":"dd6 9hq",
    "addr:street":"William Street",
    "iso:country":"GB",
    "sg:address":"50 William Street",
    "sg:city":"Tayport",
    "sg:classifiers":[
        {
            "category":"Farming",
            "subcategory":"Nursery",
            "type":"Manufacturing & Wholesale Goods"
        },
        {
            "category":"Education",
            "subcategory":"Preschool",
            "type":"Public Place"
        }
    ],
    "sg:phone":"+44 1382 552670",
    "sg:postcode":"DD6 9HQ",
    "sg:province":"Fife",
    "sg:tags":[
        "school",
        "creche"
    ],
    "wof:name":"Ferryport Nursery School",
    "wof:placetype":"venue"
},
  "geometry": {"coordinates":[-2.882934,56.450241],"type":"Point"}
}