{
  "type": "Feature",
  "properties": {
    "addr:full":"203 St Johns Hill Battersea Greater London SW11 1TH",
    "addr:housenumber":"203",
    "addr:postcode":"sw11 1th",
    "addr:street":"St Johns Hill",
    "iso:country":"GB",
    "sg:address":"203 St Johns Hill",
    "sg:city":"Battersea",
    "sg:classifiers":[
        {
            "category":"Communications",
            "type":"Services"
        }
    ],
    "sg:phone":"+44 20 7223 9494",
    "sg:postcode":"SW11 1TH",
    "sg:province":"Greater London",
    "sg:tags":[
        "broadcasting"
    ],
    "wof:name":"Sho International",
    "wof:placetype":"venue"
},
  "geometry": {"coordinates":[-0.17871,51.45982],"type":"Point"}
}