{
  "type": "Feature",
  "properties": {
    "addr:full":"147 Engineer Road, West Wilts Trading Estate Westbury Wiltshire BA13 4JW",
    "addr:housenumber":"147",
    "addr:postcode":"ba13 4jw",
    "addr:street":"Engineer Road West Wilts Trading Estate",
    "iso:country":"GB",
    "sg:address":"147 Engineer Road, West Wilts Trading Estate",
    "sg:city":"Westbury",
    "sg:classifiers":[
        {
            "category":"Freight",
            "type":"Transportation"
        }
    ],
    "sg:phone":"+44 1373 822214",
    "sg:postcode":"BA13 4JW",
    "sg:province":"Wiltshire",
    "sg:tags":[
        "haulage",
        "road"
    ],
    "wof:name":"Deejay Transport",
    "wof:placetype":"venue"
},
  "geometry": {"coordinates":[-2.210848,51.276218],"type":"Point"}
}