{
  "type": "Feature",
  "properties": {
    "iso:country":"GB",
    "sg:address":"Denbrae Farm Cottage",
    "sg:city":"Cupar",
    "sg:classifiers":[
        {
            "category":"Farming",
            "subcategory":"Farm",
            "type":"Manufacturing & Wholesale Goods"
        }
    ],
    "sg:phone":"+44 1334 652151",
    "sg:postcode":"KY15 4PZ",
    "sg:province":"Fife",
    "sg:tags":[
        "mixed",
        "crop"
    ],
    "wof:name":"R S Bell & Sons",
    "wof:placetype":"venue"
},
  "geometry": {"coordinates":[-3.0117590427,56.3194961548],"type":"Point"}
}