{
  "type": "Feature",
  "properties": {
    "addr:full":"87 King Street Middlewich Cheshire CW10 9EH",
    "addr:housenumber":"87",
    "addr:postcode":"cw10 9eh",
    "addr:street":"King Street",
    "iso:country":"GB",
    "sg:address":"87 King Street",
    "sg:city":"Middlewich",
    "sg:classifiers":[
        {
            "category":"Utilities",
            "subcategory":"Fuel Oil & Lpg",
            "type":"Services"
        }
    ],
    "sg:phone":"+44 1606 832980",
    "sg:postcode":"CW10 9EH",
    "sg:province":"Cheshire",
    "sg:tags":[
        "distributor"
    ],
    "wof:name":"Hayhurst Sons & Co. Ltd.",
    "wof:placetype":"venue"
},
  "geometry": {"coordinates":[-2.445231,53.197475],"type":"Point"}
}