{
  "type": "Feature",
  "properties": {
    "iso:country":"GB",
    "sg:address":"53 The Arches, Alma Road",
    "sg:city":"Windsor",
    "sg:classifiers":[
        {
            "category":"Home & Garden",
            "subcategory":"Hardware",
            "type":"Retail Goods"
        }
    ],
    "sg:phone":"+44 1753 621581",
    "sg:postcode":"SL4 3HY",
    "sg:province":"Berkshire",
    "sg:tags":[
        "shop",
        "lawnmowers",
        "machinery",
        "diy"
    ],
    "wof:name":"Archway Lawnmowers",
    "wof:placetype":"venue"
},
  "geometry": {"coordinates":[-0.624664,51.478806],"type":"Point"}
}