{
  "type": "Feature",
  "properties": {
    "iso:country":"GB",
    "sg:address":"Featherbed Lane",
    "sg:city":"Shrewsbury",
    "sg:classifiers":[
        {
            "category":"Retail",
            "subcategory":"Auto Repair",
            "type":"Services"
        }
    ],
    "sg:phone":"+44 1743 446951",
    "sg:postcode":"SY1 4NL",
    "sg:province":"Shropshire",
    "sg:tags":[
        "modification",
        "garage"
    ],
    "wof:name":"T J Vickers & Sons",
    "wof:placetype":"venue"
},
  "geometry": {"coordinates":[-2.723659,52.736355],"type":"Point"}
}