{
  "type": "Feature",
  "properties": {
    "addr:full":"19 Lever Street Manchester Greater Manchester M1 3LT",
    "addr:housenumber":"19",
    "addr:postcode":"m1 3lt",
    "addr:street":"Lever Street",
    "iso:country":"GB",
    "sg:address":"19 Lever Street",
    "sg:city":"Manchester",
    "sg:classifiers":[
        {
            "category":"Professional",
            "subcategory":"Engineering",
            "type":"Services"
        }
    ],
    "sg:phone":"+44 161 228 6282",
    "sg:postcode":"M1 3LT",
    "sg:province":"Greater Manchester",
    "sg:tags":[
        "design",
        "engineer"
    ],
    "wof:name":"Kennedy & Donkin Systems Control Ltd.",
    "wof:placetype":"venue"
},
  "geometry": {"coordinates":[-2.23542,53.476601],"type":"Point"}
}