{
  "type": "Feature",
  "properties": {
    "iso:country":"GB",
    "sg:address":"Haydock Mews, Pleckgate Road",
    "sg:city":"Blackburn",
    "sg:classifiers":[
        {
            "category":"Real Estate",
            "subcategory":"Developer",
            "type":"Services"
        },
        {
            "category":"Building & Trades",
            "subcategory":"Construction",
            "type":"Services"
        }
    ],
    "sg:phone":"+44 1254 245045",
    "sg:postcode":"BB1 8RP",
    "sg:province":"Lancashire",
    "sg:tags":[
        "residential",
        "builder",
        "property"
    ],
    "wof:name":"Haydock Developments Ltd",
    "wof:placetype":"venue"
},
  "geometry": {"coordinates":[-2.480399,53.748516],"type":"Point"}
}