{
  "type": "Feature",
  "properties": {
    "iso:country":"GB",
    "sg:address":"Unit 3 Britannia Industrial Estate, Hobley Drive",
    "sg:city":"Swindon",
    "sg:classifiers":[
        {
            "category":"Manufacturing",
            "subcategory":"Building Materials",
            "type":"Manufacturing & Wholesale Goods"
        }
    ],
    "sg:phone":"+44 1793 832118",
    "sg:postcode":"SN3 4NS",
    "sg:province":"Wiltshire",
    "sg:tags":[
        "merchant",
        "builder"
    ],
    "wof:name":"W T Burden",
    "wof:placetype":"venue"
},
  "geometry": {"coordinates":[-1.728243947,51.5862808228],"type":"Point"}
}