{
  "type": "Feature",
  "properties": {
    "iso:country":"GB",
    "sg:address":"Studio E2 Boston Industrial Centre, Norfolk Street",
    "sg:city":"Boston",
    "sg:classifiers":[
        {
            "category":"Shopping",
            "subcategory":"Gifts & Souvenirs",
            "type":"Retail Goods"
        }
    ],
    "sg:phone":"+44 1205 311119",
    "sg:postcode":"PE21 9HG",
    "sg:province":"Lincolnshire",
    "sg:tags":[
        "giftware"
    ],
    "wof:name":"Korina International",
    "wof:placetype":"venue"
},
  "geometry": {"coordinates":[-0.029124,52.974697],"type":"Point"}
}