{
  "type": "Feature",
  "properties": {
    "iso:country":"GB",
    "sg:address":"3 Buxton Rd",
    "sg:city":"Bakewell",
    "sg:classifiers":[
        {
            "category":"Professional",
            "type":"Services"
        }
    ],
    "sg:phone":"+44 1629 815010",
    "sg:postcode":"DE45 1DA",
    "sg:province":"Derbyshire",
    "sg:tags":[
        "auctioneer"
    ],
    "wof:name":"Mays Dowse",
    "wof:placetype":"venue"
},
  "geometry": {"coordinates":[-1.67704,53.214474],"type":"Point"}
}