{
  "type": "Feature",
  "properties": {
    "iso:country":"GB",
    "sg:address":"Near Fort William",
    "sg:city":"Glenfinnan",
    "sg:classifiers":[
        {
            "category":"Travel",
            "subcategory":"Hotels & Motels",
            "type":"Entertainment"
        }
    ],
    "sg:phone":"+44 1397 722246",
    "sg:postcode":"PH37 4LT",
    "sg:province":"Highland",
    "wof:name":"Prince's House The",
    "wof:placetype":"venue"
},
  "geometry": {"coordinates":[-5.453159,56.873055],"type":"Point"}
}