{
  "type": "Feature",
  "properties": {
    "iso:country":"GB",
    "sg:address":"Units 5-6 Locks Street, Coatdyke Retail Park",
    "sg:city":"Coatbridge",
    "sg:classifiers":[
        {
            "category":"Building & Trades",
            "subcategory":"Construction",
            "type":"Services"
        }
    ],
    "sg:phone":"+44 1236 710991",
    "sg:postcode":"ML5 3RT",
    "sg:province":"North Lanarkshire",
    "sg:tags":[
        "decorator",
        "painter"
    ],
    "wof:name":"The Untouchables Decorators Ltd.",
    "wof:placetype":"venue"
},
  "geometry": {"coordinates":[-4.035839,55.858753],"type":"Point"}
}