{
  "type": "Feature",
  "properties": {
    "addr:full":"5 Keighley Road Skipton Lancashire BD23 2NS",
    "addr:housenumber":"5",
    "addr:postcode":"bd23 2ns",
    "addr:street":"Keighley Road",
    "iso:country":"GB",
    "sg:address":"5 Keighley Road",
    "sg:city":"Skipton",
    "sg:classifiers":[
        {
            "category":"Shopping",
            "subcategory":"Bicycles & Sporting Goods",
            "type":"Retail Goods"
        }
    ],
    "sg:phone":"+44 1756 797733",
    "sg:postcode":"BD23 2NS",
    "sg:province":"Lancashire",
    "sg:tags":[
        "equipment",
        "camping"
    ],
    "wof:name":"Yeomans Army Stores",
    "wof:placetype":"venue"
},
  "geometry": {"coordinates":[-2.0125041008,53.9390869141],"type":"Point"}
}