{
  "type": "Feature",
  "properties": {
    "addr:full":"Hanbeck Farm, Back Lane, Wilsford Grantham Leicestershire NG32 3PB",
    "addr:postcode":"ng32 3pb",
    "addr:street":"Back Lane",
    "iso:country":"GB",
    "sg:address":"Hanbeck Farm, Back Lane, Wilsford",
    "sg:city":"Grantham",
    "sg:classifiers":[
        {
            "category":"Farming",
            "subcategory":"Livestock Farm",
            "type":"Manufacturing & Wholesale Goods"
        },
        {
            "category":"Farming",
            "subcategory":"Farm",
            "type":"Manufacturing & Wholesale Goods"
        }
    ],
    "sg:phone":"+44 1400 230303",
    "sg:postcode":"NG32 3PB",
    "sg:province":"Leicestershire",
    "sg:tags":[
        "mixed",
        "others"
    ],
    "wof:name":"Lunn & Partner",
    "wof:placetype":"venue"
},
  "geometry": {"coordinates":[-0.5040500164,52.9764595032],"type":"Point"}
}