{
  "type": "Feature",
  "properties": {
    "addr:full":"Birch Park, Ontario Road Scunthorpe Lincolnshire DN17 2TQ",
    "addr:postcode":"dn17 2tq",
    "addr:street":"Park Ontario Road",
    "iso:country":"GB",
    "sg:address":"Birch Park, Ontario Road",
    "sg:city":"Scunthorpe",
    "sg:classifiers":[
        {
            "category":"Arena",
            "subcategory":"Sports Club",
            "type":"Entertainment"
        }
    ],
    "sg:phone":"+44 1724 871883",
    "sg:postcode":"DN17 2TQ",
    "sg:province":"Lincolnshire",
    "wof:name":"Bottesford Town Football Club",
    "wof:placetype":"venue"
},
  "geometry": {"coordinates":[-0.680591,53.556091],"type":"Point"}
}