{
  "type": "Feature",
  "properties": {
    "addr:full":"Unit 4b, Windsor Court Salford Greater Manchester M5 4PT",
    "addr:housenumber":"unit 4b",
    "addr:postcode":"m5 4pt",
    "addr:street":"Windsor Court",
    "iso:country":"GB",
    "sg:address":"Unit 4b, Windsor Court",
    "sg:city":"Salford",
    "sg:classifiers":[
        {
            "category":"Professional",
            "subcategory":"Art Services",
            "type":"Services"
        },
        {
            "category":"Home & Garden",
            "subcategory":"Kitchen Supply",
            "type":"Retail Goods"
        }
    ],
    "sg:phone":"+44 161 848 7007",
    "sg:postcode":"M5 4PT",
    "sg:province":"Greater Manchester",
    "sg:tags":[
        "equipment",
        "graphic",
        "designer",
        "catering"
    ],
    "wof:name":"Lockhart Design Services",
    "wof:placetype":"venue"
},
  "geometry": {"coordinates":[-2.2796928883,53.4787979126],"type":"Point"}
}