{
  "type": "Feature",
  "properties": {
    "iso:country":"GB",
    "sg:address":"34 Hamilton Road",
    "sg:city":"Felixstowe",
    "sg:classifiers":[
        {
            "category":"Travel",
            "subcategory":"Travel Agent",
            "type":"Entertainment"
        }
    ],
    "sg:phone":"+44 1394 672212",
    "sg:postcode":"IP11 7AN",
    "sg:province":"Suffolk",
    "wof:name":"Carlson Worldchoice",
    "wof:placetype":"venue"
},
  "geometry": {"coordinates":[1.351544,51.962135],"type":"Point"}
}