{
  "type": "Feature",
  "properties": {
    "addr:full":"Western Estate Greenford Greater London UB6 8DW",
    "addr:postcode":"ub6 8dw",
    "iso:country":"GB",
    "sg:address":"Western Estate",
    "sg:city":"Greenford",
    "sg:classifiers":[
        {
            "category":"Retail",
            "subcategory":"Storage",
            "type":"Services"
        }
    ],
    "sg:phone":"+44 20 8998 8888",
    "sg:postcode":"UB6 8DW",
    "sg:province":"Greater London",
    "sg:tags":[
        "household",
        "removal"
    ],
    "wof:name":"Vanguard Group Ltd",
    "wof:placetype":"venue"
},
  "geometry": {"coordinates":[-0.3106290102,51.5321540833],"type":"Point"}
}