{
  "type": "Feature",
  "properties": {
    "addr:full":"Station Saw Mills, Wooperton Alnwick Northumberland NE66 4XW",
    "addr:postcode":"ne66 4xw",
    "addr:street":"Saw;Wooperton",
    "iso:country":"GB",
    "sg:address":"Station Saw Mills, Wooperton",
    "sg:city":"Alnwick",
    "sg:classifiers":[
        {
            "category":"Wholesale",
            "subcategory":"Construction Materials",
            "type":"Manufacturing & Wholesale Goods"
        },
        {
            "category":"Manufacturing",
            "subcategory":"Lumber",
            "type":"Manufacturing & Wholesale Goods"
        }
    ],
    "sg:phone":"+44 1668 217288",
    "sg:postcode":"NE66 4XW",
    "sg:province":"Northumberland",
    "sg:tags":[
        "merchants",
        "agent",
        "importer",
        "activity",
        "sawmill",
        "timber"
    ],
    "sg:website":"http://www.ajscott.co.uk",
    "wof:name":"A & J Scott Ltd",
    "wof:placetype":"venue"
},
  "geometry": {"coordinates":[-1.937893033,55.4760894775],"type":"Point"}
}