{
  "type": "Feature",
  "properties": {
    "iso:country":"GB",
    "sg:address":"26 Dingle Walk",
    "sg:city":"Winsford",
    "sg:classifiers":[
        {
            "category":"Retail",
            "subcategory":"Laundry & Dry Cleaning",
            "type":"Services"
        }
    ],
    "sg:phone":"+44 1606 593915",
    "sg:postcode":"CW7 1BA",
    "sg:province":"Cheshire",
    "sg:tags":[
        "alteration"
    ],
    "wof:name":"Johnsons the Cleaners",
    "wof:placetype":"venue"
},
  "geometry": {"coordinates":[-2.525369,53.19112],"type":"Point"}
}