{
  "type": "Feature",
  "properties": {
    "addr:full":"13 Bolingbroke Close, Hook Swindon Wiltshire SN4 8ED",
    "addr:housenumber":"13",
    "addr:postcode":"sn4 8ed",
    "addr:street":"Bolingbroke Close",
    "iso:country":"GB",
    "sg:address":"13 Bolingbroke Close, Hook",
    "sg:city":"Swindon",
    "sg:classifiers":[
        {
            "category":"Manufacturing",
            "subcategory":"Metals",
            "type":"Manufacturing & Wholesale Goods"
        },
        {
            "category":"Utilities",
            "subcategory":"Natural Gas",
            "type":"Services"
        }
    ],
    "sg:postcode":"SN4 8ED",
    "sg:province":"Wiltshire",
    "sg:tags":[
        "supplier",
        "steel",
        "stockholder"
    ],
    "wof:name":"C A W Matthews",
    "wof:placetype":"venue"
},
  "geometry": {"coordinates":[-1.888309,51.561588],"type":"Point"}
}