{
  "type": "Feature",
  "properties": {
    "iso:country":"GB",
    "sg:address":"239b Trysull Rd, Five Ways",
    "sg:city":"Wolverhampton",
    "sg:classifiers":[
        {
            "category":"Health Services",
            "subcategory":"Dentist",
            "type":"Services"
        }
    ],
    "sg:phone":"+44 1902 766388",
    "sg:postcode":"WV3 7LG",
    "sg:province":"Staffordshire",
    "wof:name":"Kimpton A J & Associates",
    "wof:placetype":"venue"
},
  "geometry": {"coordinates":[-2.171243,52.57098],"type":"Point"}
}