{
  "type": "Feature",
  "properties": {
    "iso:country":"GB",
    "sg:address":"62 Kyle St",
    "sg:city":"Ayr",
    "sg:classifiers":[
        {
            "category":"Manufacturing",
            "subcategory":"Petroleum Products",
            "type":"Manufacturing & Wholesale Goods"
        }
    ],
    "sg:phone":"+44 1292 260100",
    "sg:postcode":"KA7 1RZ",
    "sg:province":"South Ayrshire",
    "sg:tags":[
        "double",
        "glazing"
    ],
    "wof:name":"Weatherseal Window Systems",
    "wof:placetype":"venue"
},
  "geometry": {"coordinates":[-4.62775,55.45961],"type":"Point"}
}