{
  "type": "Feature",
  "properties": {
    "addr:full":"Ground Floor, 4 Exchange Quay Salford Greater Manchester M5 3EE",
    "addr:housenumber":"4",
    "addr:postcode":"m5 3ee",
    "addr:street":"Ground Floor;Exchange Quay",
    "iso:country":"GB",
    "sg:address":"Ground Floor, 4 Exchange Quay",
    "sg:city":"Salford",
    "sg:classifiers":[
        {
            "category":"Communications",
            "type":"Services"
        }
    ],
    "sg:phone":"+44 161 848 4600",
    "sg:postcode":"M5 3EE",
    "sg:province":"Greater Manchester",
    "sg:tags":[
        "data",
        "network"
    ],
    "wof:name":"Global One",
    "wof:placetype":"venue"
},
  "geometry": {"coordinates":[-2.2829,53.46611],"type":"Point"}
}