{
  "type": "Feature",
  "properties": {
    "iso:country":"GB",
    "sg:address":"118-120 High St, Gorleston",
    "sg:city":"Great Yarmouth",
    "sg:classifiers":[
        {
            "category":"Shopping",
            "subcategory":"News",
            "type":"Retail Goods"
        }
    ],
    "sg:phone":"+44 1493 442727",
    "sg:postcode":"NR31 6RE",
    "sg:province":"Norfolk",
    "sg:tags":[
        "newsagent"
    ],
    "wof:name":"Martin The Newsagent",
    "wof:placetype":"venue"
},
  "geometry": {"coordinates":[1.727745,52.57843],"type":"Point"}
}