{
  "type": "Feature",
  "properties": {
    "iso:country":"GB",
    "sg:address":"8 Balmachie Road",
    "sg:city":"Carnoustie",
    "sg:classifiers":[
        {
            "category":"Personal",
            "subcategory":"Beauty Salon",
            "type":"Services"
        },
        {
            "category":"Personal",
            "subcategory":"Barber",
            "type":"Services"
        }
    ],
    "sg:phone":"+44 1241 852269",
    "sg:postcode":"DD7 7SR",
    "sg:province":"Angus",
    "sg:tags":[
        "unisex",
        "hairdresser"
    ],
    "wof:name":"Martine's",
    "wof:placetype":"venue"
},
  "geometry": {"coordinates":[-2.720815,56.50499],"type":"Point"}
}