{
  "type": "Feature",
  "properties": {
    "iso:country":"GB",
    "sg:address":"1 Blythwood Road, Tyseley",
    "sg:city":"Birmingham",
    "sg:classifiers":[
        {
            "category":"Building & Trades",
            "subcategory":"Plumbing",
            "type":"Services"
        },
        {
            "category":"Government",
            "subcategory":"Post Office",
            "type":"Public Place"
        }
    ],
    "sg:phone":"+44 121 764 4448",
    "sg:postcode":"B11 2BX",
    "sg:province":"West Midlands",
    "sg:tags":[
        "clearance",
        "drain",
        "sewer",
        "sewar"
    ],
    "wof:name":"Forward Drains Ltd",
    "wof:placetype":"venue"
},
  "geometry": {"coordinates":[-1.836418,52.453732],"type":"Point"}
}