{
  "type": "Feature",
  "properties": {
    "addr:full":"Somerset Place Plymouth Devon PL3 4BD",
    "addr:postcode":"pl3 4bd",
    "addr:street":"Somerset Place",
    "iso:country":"GB",
    "sg:address":"Somerset Place",
    "sg:city":"Plymouth",
    "sg:classifiers":[
        {
            "category":"Education",
            "subcategory":"School",
            "type":"Public Place"
        }
    ],
    "sg:phone":"+44 1752 556065",
    "sg:postcode":"PL3 4BD",
    "sg:province":"Devon",
    "sg:tags":[
        "local",
        "authority"
    ],
    "wof:name":"Stoke Damerel Community College",
    "wof:placetype":"venue"
},
  "geometry": {"coordinates":[-4.1610021591,50.3811912537],"type":"Point"}
}