{
  "type": "Feature",
  "properties": {
    "addr:full":"19 Fore Street Ivybridge Devon PL21 9AB",
    "addr:housenumber":"19",
    "addr:postcode":"pl21 9ab",
    "addr:street":"Fore Street",
    "iso:country":"GB",
    "sg:address":"19 Fore Street",
    "sg:city":"Ivybridge",
    "sg:classifiers":[
        {
            "category":"Shopping",
            "subcategory":"Gifts & Souvenirs",
            "type":"Retail Goods"
        }
    ],
    "sg:postcode":"PL21 9AB",
    "sg:province":"Devon",
    "sg:tags":[
        "poster",
        "card"
    ],
    "wof:name":"Fancy That",
    "wof:placetype":"venue"
},
  "geometry": {"coordinates":[-3.9223279953,50.388759613],"type":"Point"}
}