{
  "type": "Feature",
  "properties": {
    "iso:country":"GB",
    "sg:address":"50 Clement Rise, Dedridge",
    "sg:city":"Livingston",
    "sg:classifiers":[
        {
            "category":"Wholesale",
            "subcategory":"Construction Materials",
            "type":"Manufacturing & Wholesale Goods"
        }
    ],
    "sg:phone":"+44 1506 494273",
    "sg:postcode":"EH54 6JY",
    "sg:province":"West Lothian",
    "sg:tags":[
        "cladding"
    ],
    "wof:name":"Euro Cladd Central",
    "wof:placetype":"venue"
},
  "geometry": {"coordinates":[-3.496539,55.88271],"type":"Point"}
}