{
  "type": "Feature",
  "properties": {
    "addr:full":"2 Melgund Terrace Edinburgh City of Edinburgh EH7 4BU",
    "addr:housenumber":"2",
    "addr:postcode":"eh7 4bu",
    "addr:street":"Melgund Terrace",
    "iso:country":"GB",
    "sg:address":"2 Melgund Terrace",
    "sg:city":"Edinburgh",
    "sg:classifiers":[
        {
            "category":"Retail",
            "subcategory":"Storage",
            "type":"Services"
        }
    ],
    "sg:postcode":"EH7 4BU",
    "sg:province":"City of Edinburgh",
    "sg:tags":[
        "household",
        "removal"
    ],
    "wof:name":"Douglas Turnbull Removals",
    "wof:placetype":"venue"
},
  "geometry": {"coordinates":[-3.1919291019,55.9618835449],"type":"Point"}
}