{
  "type": "Feature",
  "properties": {
    "addr:full":"Unit 3 Brazil Close, Beddington Farm Road Croydon Surrey CR0 4XQ",
    "addr:housenumber":"unit 3",
    "addr:postcode":"cr0 4xq",
    "addr:street":"Brazil Close;Farm Road",
    "iso:country":"GB",
    "sg:address":"Unit 3 Brazil Close, Beddington Farm Road",
    "sg:city":"Croydon",
    "sg:classifiers":[
        {
            "category":"Manufacturing",
            "subcategory":"Paper Products",
            "type":"Manufacturing & Wholesale Goods"
        }
    ],
    "sg:phone":"+44 20 8665 7777",
    "sg:postcode":"CR0 4XQ",
    "sg:province":"Surrey",
    "sg:tags":[
        "cardboard"
    ],
    "wof:name":"SCOPE PACKAGING LTD",
    "wof:placetype":"venue"
},
  "geometry": {"coordinates":[-0.130039,51.383347],"type":"Point"}
}