{
  "type": "Feature",
  "properties": {
    "addr:full":"Charlestown Road Aboyne Aberdeenshire AB34 5EL",
    "addr:postcode":"ab34 5el",
    "addr:street":"Charlestown Road",
    "iso:country":"GB",
    "sg:address":"Charlestown Road",
    "sg:city":"Aboyne",
    "sg:classifiers":[
        {
            "category":"Bars & Pubs",
            "type":"Food & Drink"
        }
    ],
    "sg:phone":"+44 1339 886137",
    "sg:postcode":"AB34 5EL",
    "sg:province":"Aberdeenshire",
    "sg:tags":[
        "pubs",
        "inn"
    ],
    "wof:name":"The Boat Inn",
    "wof:placetype":"venue"
},
  "geometry": {"coordinates":[-2.7804389,57.0758209229],"type":"Point"}
}