{
  "type": "Feature",
  "properties": {
    "addr:full":"31 Minister Crescent Darwen Lancashire BB3 3PY",
    "addr:housenumber":"31",
    "addr:postcode":"bb3 3py",
    "addr:street":"Minister Crescent",
    "iso:country":"GB",
    "sg:address":"31 Minister Crescent",
    "sg:city":"Darwen",
    "sg:classifiers":[
        {
            "category":"Shopping",
            "subcategory":"Stationery & Office Supplies",
            "type":"Retail Goods"
        },
        {
            "category":"Shopping",
            "subcategory":"Crafts & Fabrics",
            "type":"Retail Goods"
        }
    ],
    "sg:phone":"+44 1254 760316",
    "sg:postcode":"BB3 3PY",
    "sg:province":"Lancashire",
    "sg:tags":[
        "services",
        "supplies",
        "ceramic",
        "manufacturer"
    ],
    "wof:name":"G S Ceramics",
    "wof:placetype":"venue"
},
  "geometry": {"coordinates":[-2.449369,53.692665],"type":"Point"}
}