{
  "type": "Feature",
  "properties": {
    "addr:full":"12 High Street Hampton Greater London TW12 2SJ",
    "addr:housenumber":"12",
    "addr:postcode":"tw12 2sj",
    "addr:street":"High Street",
    "iso:country":"GB",
    "sg:address":"12 High Street",
    "sg:city":"Hampton",
    "sg:classifiers":[
        {
            "category":"Shopping",
            "subcategory":"Beauty & Cosmetics",
            "type":"Retail Goods"
        }
    ],
    "sg:phone":"+44 20 8941 4480",
    "sg:postcode":"TW12 2SJ",
    "sg:province":"Greater London",
    "sg:tags":[
        "equipment",
        "supply",
        "hairdressing"
    ],
    "wof:name":"V M L Beauty Products",
    "wof:placetype":"venue"
},
  "geometry": {"coordinates":[-0.362217,51.413521],"type":"Point"}
}