{
  "type": "Feature",
  "properties": {
    "addr:full":"Unit 11, 19 Blairtummock Road Glasgow Glasgow City G33 4AN",
    "addr:housenumber":"unit;19",
    "addr:postcode":"g33 4an",
    "addr:street":"Blairtummock Road",
    "iso:country":"GB",
    "sg:address":"Unit 11, 19 Blairtummock Road",
    "sg:city":"Glasgow",
    "sg:classifiers":[
        {
            "category":"Home & Garden",
            "subcategory":"Building Materials",
            "type":"Retail Goods"
        }
    ],
    "sg:phone":"+44 141 774 0786",
    "sg:postcode":"G33 4AN",
    "sg:province":"Glasgow City",
    "sg:tags":[
        "stairlifts"
    ],
    "wof:name":"Clyde Valley Lifts Ltd.",
    "wof:placetype":"venue"
},
  "geometry": {"coordinates":[-4.153985,55.867443],"type":"Point"}
}