{
  "type": "Feature",
  "properties": {
    "iso:country":"GB",
    "sg:address":"4 Osborne Villas",
    "sg:city":"Newcastle Upon Tyne",
    "sg:classifiers":[
        {
            "category":"Organizations",
            "subcategory":"Religious Organization",
            "type":"Services"
        }
    ],
    "sg:phone":"+44 191 281 7261",
    "sg:postcode":"NE2 1JU",
    "sg:province":"Tyne and Wear",
    "sg:tags":[
        "organisation"
    ],
    "wof:name":"Sisters Of Marie Reparatrice",
    "wof:placetype":"venue"
},
  "geometry": {"coordinates":[-1.60244,54.987499],"type":"Point"}
}