{
  "type": "Feature",
  "properties": {
    "addr:full":"8 Drydon Road Dalkeith Midlothian EH20 9LZ",
    "addr:housenumber":"8",
    "addr:postcode":"eh20 9lz",
    "addr:street":"Drydon Road",
    "iso:country":"GB",
    "sg:address":"8 Drydon Road",
    "sg:city":"Dalkeith",
    "sg:classifiers":[
        {
            "category":"Farming",
            "subcategory":"Dairy Farm",
            "type":"Manufacturing & Wholesale Goods"
        },
        {
            "category":"Food & Beverages",
            "subcategory":"Dairy",
            "type":"Retail Goods"
        }
    ],
    "sg:phone":"+44 131 440 0110",
    "sg:postcode":"EH20 9LZ",
    "sg:province":"Midlothian",
    "sg:tags":[
        "merchant",
        "produce"
    ],
    "wof:name":"Bonaly Farm Dairy",
    "wof:placetype":"venue"
},
  "geometry": {"coordinates":[-3.16821,55.874439],"type":"Point"}
}