{
  "type": "Feature",
  "properties": {
    "addr:full":"58 Northfield Avenue London Greater London W13 9RR",
    "addr:housenumber":"58",
    "addr:postcode":"w13 9rr",
    "addr:street":"Northfield Avenue",
    "iso:country":"GB",
    "sg:address":"58 Northfield Avenue",
    "sg:city":"London",
    "sg:classifiers":[
        {
            "category":"Cafe",
            "type":"Food & Drink"
        }
    ],
    "sg:phone":"+44 20 8579 2113",
    "sg:postcode":"W13 9RR",
    "sg:province":"Greater London",
    "sg:tags":[
        "tea",
        "room"
    ],
    "wof:name":"Anne's Snacks",
    "wof:placetype":"venue"
},
  "geometry": {"coordinates":[-0.318472,51.504028],"type":"Point"}
}