{
  "type": "Feature",
  "properties": {
    "addr:full":"Unit 77, Riverside Estate, Sir Thomas Longley Road Rochester Kent ME2 4BH",
    "addr:housenumber":"unit 77",
    "addr:postcode":"me2 4bh",
    "addr:street":"Riverside Estate Sir Thomas Longley Road Rochester",
    "iso:country":"GB",
    "sg:address":"Unit 77, Riverside Estate, Sir Thomas Longley Road",
    "sg:city":"Rochester",
    "sg:classifiers":[
        {
            "category":"Building & Trades",
            "subcategory":"Construction",
            "type":"Services"
        }
    ],
    "sg:phone":"+44 1634 720555",
    "sg:postcode":"ME2 4BH",
    "sg:province":"Kent",
    "sg:tags":[
        "heating",
        "contractor"
    ],
    "wof:name":"Matrix Mechanical Services Ltd.",
    "wof:placetype":"venue"
},
  "geometry": {"coordinates":[0.516595,51.394852],"type":"Point"}
}