{
  "type": "Feature",
  "properties": {
    "addr:full":"Mil Birnar, Stryt Isa Wrexham Wrexham LL12 9PT",
    "addr:postcode":"ll12 9pt",
    "addr:street":"Stryt",
    "iso:country":"GB",
    "sg:address":"Mil Birnar, Stryt Isa",
    "sg:city":"Wrexham",
    "sg:classifiers":[
        {
            "category":"Professional",
            "subcategory":"Printing & Photocopies",
            "type":"Services"
        }
    ],
    "sg:phone":"+44 1978 762762",
    "sg:postcode":"LL12 9PT",
    "sg:province":"Wrexham",
    "sg:tags":[
        "tag",
        "label"
    ],
    "wof:name":"K D S Label Co. Ltd.",
    "wof:placetype":"venue"
},
  "geometry": {"coordinates":[-3.03635,53.121181],"type":"Point"}
}