{
  "type": "Feature",
  "properties": {
    "iso:country":"GB",
    "sg:address":"Unit 21c Dawkins Business Centre, Dawkins Road",
    "sg:city":"Poole",
    "sg:classifiers":[
        {
            "category":"Home & Garden",
            "subcategory":"Building Materials",
            "type":"Retail Goods"
        }
    ],
    "sg:phone":"+44 1202 686333",
    "sg:postcode":"BH15 4JY",
    "sg:province":"Dorset",
    "sg:tags":[
        "ventilator",
        "ventilation",
        "system"
    ],
    "wof:name":"Air Handling Air Conditioning Boilers & Controls 1",
    "wof:placetype":"venue"
},
  "geometry": {"coordinates":[-1.9867390394,50.7144851685],"type":"Point"}
}