{
  "type": "Feature",
  "properties": {
    "iso:country":"GB",
    "sg:address":"19 West Tower Street",
    "sg:city":"Carlisle",
    "sg:classifiers":[
        {
            "category":"Professional",
            "subcategory":"Art Services",
            "type":"Services"
        }
    ],
    "sg:phone":"+44 1228 531837",
    "sg:postcode":"CA3 8QT",
    "sg:province":"Cumbria",
    "sg:tags":[
        "picture",
        "restoration",
        "framing",
        "cleaning"
    ],
    "wof:name":"Grays Picture Framers Ltd.",
    "wof:placetype":"venue"
},
  "geometry": {"coordinates":[-2.9373679161,54.8966026306],"type":"Point"}
}