{
  "type": "Feature",
  "properties": {
    "addr:full":"Higher Lillesdon Farm, Lillesdon Taunton Devon TA3 6BN",
    "addr:postcode":"ta3 6bn",
    "iso:country":"GB",
    "sg:address":"Higher Lillesdon Farm, Lillesdon",
    "sg:city":"Taunton",
    "sg:classifiers":[
        {
            "category":"Farming",
            "subcategory":"Farm",
            "type":"Manufacturing & Wholesale Goods"
        }
    ],
    "sg:phone":"+44 1823 490285",
    "sg:postcode":"TA3 6BN",
    "sg:province":"Devon",
    "sg:tags":[
        "mixed",
        "crop"
    ],
    "wof:name":"A E Vile & Son",
    "wof:placetype":"venue"
},
  "geometry": {"coordinates":[-2.993208,51.008408],"type":"Point"}
}