{
  "type": "Feature",
  "properties": {
    "iso:country":"GB",
    "sg:address":"Challon's Combe Farm, Aveton Gifford",
    "sg:city":"Kingsbridge",
    "sg:classifiers":[
        {
            "category":"Farming",
            "subcategory":"Dairy Farm",
            "type":"Manufacturing & Wholesale Goods"
        }
    ],
    "sg:postcode":"TQ7 4NQ",
    "sg:province":"Devon",
    "wof:name":"A C F Read",
    "wof:placetype":"venue"
},
  "geometry": {"coordinates":[-3.85645,50.318909],"type":"Point"}
}