{
  "type": "Feature",
  "properties": {
    "addr:full":"31 Greenfarm Rd Cardiff Cardiff CF5 4RG",
    "addr:housenumber":"31",
    "addr:postcode":"cf5 4rg",
    "addr:street":"Greenfarm Rd",
    "iso:country":"GB",
    "sg:address":"31 Greenfarm Rd",
    "sg:city":"Cardiff",
    "sg:classifiers":[
        {
            "category":"Shopping",
            "subcategory":"Department Store",
            "type":"Retail Goods"
        }
    ],
    "sg:phone":"+44 29 2059 1513",
    "sg:postcode":"CF5 4RG",
    "sg:province":"Cardiff",
    "wof:name":"Green Farm Stores",
    "wof:placetype":"venue"
},
  "geometry": {"coordinates":[-3.268844,51.474689],"type":"Point"}
}