{
  "type": "Feature",
  "properties": {
    "addr:full":"345 Rookery Road, Handsworth Birmingham West Midlands B21 9PP",
    "addr:housenumber":"345",
    "addr:postcode":"b21 9pp",
    "addr:street":"Rookery Road",
    "iso:country":"GB",
    "sg:address":"345 Rookery Road, Handsworth",
    "sg:city":"Birmingham",
    "sg:classifiers":[
        {
            "category":"Retail",
            "subcategory":"Repair Shop",
            "type":"Services"
        },
        {
            "category":"Home & Garden",
            "subcategory":"Furniture",
            "type":"Retail Goods"
        }
    ],
    "sg:phone":"+44 121 554 5963",
    "sg:postcode":"B21 9PP",
    "sg:province":"West Midlands",
    "sg:tags":[
        "sale",
        "second-hand"
    ],
    "wof:name":"The Furniture Shop",
    "wof:placetype":"venue"
},
  "geometry": {"coordinates":[-1.939598,52.514221],"type":"Point"}
}