{
  "type": "Feature",
  "properties": {
    "addr:full":"Chesilton Avenue Huddersfield West Yorkshire HD3 4YA",
    "addr:postcode":"hd3 4ya",
    "addr:street":"Chesilton Avenue",
    "iso:country":"GB",
    "sg:address":"Chesilton Avenue",
    "sg:city":"Huddersfield",
    "sg:classifiers":[
        {
            "category":"Health Services",
            "subcategory":"Nursing And Care Facility",
            "type":"Services"
        }
    ],
    "sg:phone":"+44 1484 460968",
    "sg:postcode":"HD3 4YA",
    "sg:province":"West Yorkshire",
    "sg:tags":[
        "home"
    ],
    "wof:name":"Oakes Villa Rehabilitation Unit",
    "wof:placetype":"venue"
},
  "geometry": {"coordinates":[-1.8243819475,53.6519126892],"type":"Point"}
}