{
  "type": "Feature",
  "properties": {
    "addr:full":"1 College Walk Rotherham South Yorkshire S60 1QB",
    "addr:housenumber":"1",
    "addr:postcode":"s60 1qb",
    "addr:street":"College Walk",
    "iso:country":"GB",
    "sg:address":"1 College Walk",
    "sg:city":"Rotherham",
    "sg:classifiers":[
        {
            "category":"Cinema",
            "subcategory":"Movie Rental",
            "type":"Entertainment"
        }
    ],
    "sg:phone":"+44 1709 836104",
    "sg:postcode":"S60 1QB",
    "sg:province":"South Yorkshire",
    "sg:tags":[
        "video",
        "library"
    ],
    "wof:name":"Global Video (Uk) Ltd.",
    "wof:placetype":"venue"
},
  "geometry": {"coordinates":[-1.3655689955,53.431728363],"type":"Point"}
}