{
  "type": "Feature",
  "properties": {
    "addr:full":"114 Lewisham High Street, Lewisham London Greater London SE13 6LF",
    "addr:housenumber":"114",
    "addr:postcode":"se13 6lf",
    "addr:street":"Lewisham High Street",
    "iso:country":"GB",
    "sg:address":"114 Lewisham High Street, Lewisham",
    "sg:city":"London",
    "sg:classifiers":[
        {
            "category":"Shopping",
            "subcategory":"Optician",
            "type":"Retail Goods"
        }
    ],
    "sg:phone":"+44 20 8854 8750",
    "sg:postcode":"SE13 6LF",
    "sg:province":"Greater London",
    "wof:name":"K A Rowland Ltd.",
    "wof:placetype":"venue"
},
  "geometry": {"coordinates":[-0.0103709996,51.4622993469],"type":"Point"}
}