{
  "type": "Feature",
  "properties": {
    "addr:full":"28 Chapel Street Innerleithen Scottish Borders EH44 6HN",
    "addr:housenumber":"28",
    "addr:postcode":"eh44 6hn",
    "addr:street":"Chapel Street",
    "iso:country":"GB",
    "sg:address":"28 Chapel Street",
    "sg:city":"Innerleithen",
    "sg:classifiers":[
        {
            "category":"Professional",
            "subcategory":"Art Services",
            "type":"Services"
        }
    ],
    "sg:phone":"+44 1896 831414",
    "sg:postcode":"EH44 6HN",
    "sg:province":"Scottish Borders",
    "sg:tags":[
        "consultant",
        "design"
    ],
    "wof:name":"H G Design Consultants",
    "wof:placetype":"venue"
},
  "geometry": {"coordinates":[-3.062779,55.620186],"type":"Point"}
}