{
  "type": "Feature",
  "properties": {
    "iso:country":"GB",
    "sg:address":"43 Cotswold Avenue, Wrose",
    "sg:city":"Shipley",
    "sg:classifiers":[
        {
            "category":"Building & Trades",
            "subcategory":"Construction",
            "type":"Services"
        }
    ],
    "sg:phone":"+44 1274 594308",
    "sg:postcode":"BD18 1LS",
    "sg:province":"West Yorkshire",
    "sg:tags":[
        "glazier",
        "decorator",
        "painter"
    ],
    "wof:name":"Terence Strauss Decorator",
    "wof:placetype":"venue"
},
  "geometry": {"coordinates":[-1.752478,53.83173],"type":"Point"}
}