{
  "type": "Feature",
  "properties": {
    "iso:country":"GB",
    "sg:address":"Acre Close Playing Field, Whitnash",
    "sg:city":"Leamington Spa",
    "sg:classifiers":[
        {
            "category":"Community Center",
            "type":"Public Place"
        }
    ],
    "sg:phone":"+44 1926 425219",
    "sg:postcode":"CV31 2ND",
    "sg:province":"Warwickshire",
    "sg:tags":[
        "centre"
    ],
    "wof:name":"Whitnash Community Centre",
    "wof:placetype":"venue"
},
  "geometry": {"coordinates":[-1.528289,52.269264],"type":"Point"}
}