{
  "type": "Feature",
  "properties": {
    "addr:full":"Lhr Cargo Office Building 558, Heathrow Airport Hounslow Greater London TW6 3RN",
    "addr:housenumber":"558",
    "addr:postcode":"tw6 3rn",
    "addr:street":"Heathrow Airport",
    "iso:country":"GB",
    "sg:address":"Lhr Cargo Office Building 558, Heathrow Airport",
    "sg:city":"Hounslow",
    "sg:classifiers":[
        {
            "category":"Airline",
            "type":"Transportation"
        }
    ],
    "sg:phone":"+44 20 8897 7070",
    "sg:postcode":"TW6 3RN",
    "sg:province":"Greater London",
    "wof:name":"Malaysia Airlines",
    "wof:placetype":"venue"
},
  "geometry": {"coordinates":[-0.47068,51.460972],"type":"Point"}
}