{
  "type": "Feature",
  "properties": {
    "addr:full":"25 Fane Drive, Berinsfield Wallingford Oxfordshire OX10 7ND",
    "addr:housenumber":"25",
    "addr:postcode":"ox10 7nd",
    "addr:street":"Fane Drive Berinsfield",
    "iso:country":"GB",
    "sg:address":"25 Fane Drive, Berinsfield",
    "sg:city":"Wallingford",
    "sg:classifiers":[
        {
            "category":"Shopping",
            "subcategory":"News",
            "type":"Retail Goods"
        }
    ],
    "sg:postcode":"OX10 7ND",
    "sg:province":"Oxfordshire",
    "sg:tags":[
        "newsagent"
    ],
    "wof:name":"Berinsfield News",
    "wof:placetype":"venue"
},
  "geometry": {"coordinates":[-1.17758,51.66341],"type":"Point"}
}