{
  "type": "Feature",
  "properties": {
    "iso:country":"GB",
    "sg:address":"Hill House, 2 High Street, Blackboys",
    "sg:city":"Uckfield",
    "sg:classifiers":[
        {
            "category":"Retail",
            "subcategory":"Repair Shop",
            "type":"Services"
        }
    ],
    "sg:postcode":"TN22 5JS",
    "sg:province":"East Sussex",
    "sg:tags":[
        "radio",
        "television",
        "video"
    ],
    "wof:name":"Polegate Television Rentals",
    "wof:placetype":"venue"
},
  "geometry": {"coordinates":[0.173003003,50.9658927917],"type":"Point"}
}