{
  "type": "Feature",
  "properties": {
    "iso:country":"GB",
    "sg:address":"Ashfield, Carleton Road",
    "sg:city":"Skipton",
    "sg:classifiers":[
        {
            "category":"Social Services",
            "subcategory":"Adult Care",
            "type":"Services"
        }
    ],
    "sg:phone":"+44 1756 797956",
    "sg:postcode":"BD23 2BE",
    "sg:province":"Lancashire",
    "sg:tags":[
        "day",
        "centre"
    ],
    "wof:name":"Ashfield Day Centre",
    "wof:placetype":"venue"
},
  "geometry": {"coordinates":[-2.0208449364,53.9553565979],"type":"Point"}
}