{
  "type": "Feature",
  "properties": {
    "addr:full":"Pickering Works, Netherton Road Wishaw North Lanarkshire ML2 0EQ",
    "addr:postcode":"ml2 0eq",
    "addr:street":"Netherton Road",
    "iso:country":"GB",
    "sg:address":"Pickering Works, Netherton Road",
    "sg:city":"Wishaw",
    "sg:classifiers":[
        {
            "category":"Personal",
            "type":"Services"
        }
    ],
    "sg:phone":"+44 1698 356405",
    "sg:postcode":"ML2 0EQ",
    "sg:province":"North Lanarkshire",
    "sg:tags":[
        "delivery"
    ],
    "wof:name":"Amtrak Express Parcels",
    "wof:placetype":"venue"
},
  "geometry": {"coordinates":[-3.920879,55.774391],"type":"Point"}
}