{
  "type": "Feature",
  "properties": {
    "iso:country":"GB",
    "sg:address":"33 London St",
    "sg:city":"Reading",
    "sg:classifiers":[
        {
            "category":"Health Services",
            "subcategory":"Nursing And Care Facility",
            "type":"Services"
        }
    ],
    "sg:phone":"+44 118 957 6656",
    "sg:postcode":"RG1 4PS",
    "sg:province":"Berkshire",
    "sg:tags":[
        "agency"
    ],
    "wof:name":"Carefinders",
    "wof:placetype":"venue"
},
  "geometry": {"coordinates":[-0.968169,51.452923],"type":"Point"}
}