{
  "type": "Feature",
  "properties": {
    "addr:full":"241 Allenby Road Southall Greater London UB1 2HB",
    "addr:housenumber":"241",
    "addr:postcode":"ub1 2hb",
    "addr:street":"Allenby Road",
    "iso:country":"GB",
    "sg:address":"241 Allenby Road",
    "sg:city":"Southall",
    "sg:classifiers":[
        {
            "category":"Manufacturing",
            "subcategory":"Lumber",
            "type":"Manufacturing & Wholesale Goods"
        }
    ],
    "sg:phone":"+44 20 8813 2023",
    "sg:postcode":"UB1 2HB",
    "sg:province":"Greater London",
    "sg:tags":[
        "importer",
        "merchants",
        "agent",
        "timber"
    ],
    "wof:name":"Five Star Timber & Builders Mechants",
    "wof:placetype":"venue"
},
  "geometry": {"coordinates":[-0.3644540012,51.5242424011],"type":"Point"}
}