{
  "type": "Feature",
  "properties": {
    "addr:full":"Stadium Way Benfleet Essex SS7 3NY",
    "addr:postcode":"ss7 3ny",
    "addr:street":"Stadium Way",
    "iso:country":"GB",
    "sg:address":"Stadium Way",
    "sg:city":"Benfleet",
    "sg:classifiers":[
        {
            "category":"Cafe",
            "type":"Food & Drink"
        }
    ],
    "sg:postcode":"SS7 3NY",
    "sg:province":"Essex",
    "sg:tags":[
        "tea",
        "room"
    ],
    "wof:name":"Snak Bar",
    "wof:placetype":"venue"
},
  "geometry": {"coordinates":[0.605636,51.574551],"type":"Point"}
}