{
  "type": "Feature",
  "properties": {
    "addr:full":"6 Bush Hill Parade, Bush Hill Park London Greater London N9 9JS",
    "addr:housenumber":"6",
    "addr:postcode":"n9 9js",
    "addr:street":"Bush Hill Parade Bush Hill Park",
    "iso:country":"GB",
    "sg:address":"6 Bush Hill Parade, Bush Hill Park",
    "sg:city":"London",
    "sg:classifiers":[
        {
            "category":"Retail",
            "subcategory":"Funeral Services",
            "type":"Services"
        }
    ],
    "sg:phone":"+44 1992 713000",
    "sg:postcode":"N9 9JS",
    "sg:province":"Greater London",
    "wof:name":"Abbott & English Funeral Directors",
    "wof:placetype":"venue"
},
  "geometry": {"coordinates":[-0.0822670013,51.6447715759],"type":"Point"}
}