{
  "type": "Feature",
  "properties": {
    "iso:country":"GB",
    "sg:address":"1-2 & 5 Mathew Ct, Milnes, East Wynd",
    "sg:city":"Dundee",
    "sg:classifiers":[
        {
            "category":"Professional",
            "type":"Services"
        }
    ],
    "sg:postcode":"DD1 5BY",
    "sg:province":"Dundee City",
    "sg:tags":[
        "repair",
        "tech",
        "maintenance"
    ],
    "wof:name":"Phillips,John,",
    "wof:placetype":"venue"
},
  "geometry": {"coordinates":[-2.98487,56.462002],"type":"Point"}
}