{
  "type": "Feature",
  "properties": {
    "iso:country":"GB",
    "sg:address":"Alder Rd",
    "sg:city":"Poole",
    "sg:classifiers":[
        {
            "category":"Place Of Worship",
            "type":"Public Place"
        }
    ],
    "sg:phone":"+44 1202 746225",
    "sg:postcode":"BH12 4AA",
    "sg:province":"Dorset",
    "wof:name":"Talbot Community Church",
    "wof:placetype":"venue"
},
  "geometry": {"coordinates":[-1.916594,50.738255],"type":"Point"}
}