{
  "type": "Feature",
  "properties": {
    "addr:full":"36b Stubbington Grn Fareham Hampshire PO14 2LE",
    "addr:housenumber":"36b",
    "addr:postcode":"po14 2le",
    "addr:street":"Stubbington Grn",
    "iso:country":"GB",
    "sg:address":"36b Stubbington Grn",
    "sg:city":"Fareham",
    "sg:classifiers":[
        {
            "category":"Real Estate",
            "subcategory":"Real Estate Agent",
            "type":"Services"
        }
    ],
    "sg:phone":"+44 1329 664213",
    "sg:postcode":"PO14 2LE",
    "sg:province":"Hampshire",
    "wof:name":"B B G Estate Agencies",
    "wof:placetype":"venue"
},
  "geometry": {"coordinates":[-1.2135009766,50.8258514404],"type":"Point"}
}