{
  "type": "Feature",
  "properties": {
    "addr:full":"677 Fulham Road London Greater London SW6 5PZ",
    "addr:housenumber":"677",
    "addr:postcode":"sw6 5pz",
    "addr:street":"Fulham Road",
    "iso:country":"GB",
    "sg:address":"677 Fulham Road",
    "sg:city":"London",
    "sg:classifiers":[
        {
            "category":"Food & Beverages",
            "subcategory":"Bakery",
            "type":"Retail Goods"
        }
    ],
    "sg:phone":"+44 20 7736 0757",
    "sg:postcode":"SW6 5PZ",
    "sg:province":"Greater London",
    "wof:name":"Trolgold Ltd.",
    "wof:placetype":"venue"
},
  "geometry": {"coordinates":[-0.200368,51.478325],"type":"Point"}
}