{
  "type": "Feature",
  "properties": {
    "addr:full":"Quarry Road Cleckheaton West Yorkshire BD19 5HP",
    "addr:postcode":"bd19 5hp",
    "addr:street":"Quarry Road",
    "iso:country":"GB",
    "sg:address":"Quarry Road",
    "sg:city":"Cleckheaton",
    "sg:classifiers":[
        {
            "category":"Professional",
            "subcategory":"Engineering",
            "type":"Services"
        }
    ],
    "sg:phone":"+44 1274 874063",
    "sg:postcode":"BD19 5HP",
    "sg:province":"West Yorkshire",
    "sg:tags":[
        "precision",
        "engineer"
    ],
    "wof:name":"Hopkinson Engineering",
    "wof:placetype":"venue"
},
  "geometry": {"coordinates":[-1.720729,53.722],"type":"Point"}
}