{
  "type": "Feature",
  "properties": {
    "iso:country":"GB",
    "sg:address":"9 Prospect Pl",
    "sg:city":"Weston-super-mare",
    "sg:classifiers":[
        {
            "category":"Professional",
            "subcategory":"Printing & Photocopies",
            "type":"Services"
        }
    ],
    "sg:postcode":"BS23 1RW",
    "sg:province":"Somerset",
    "sg:tags":[
        "duplicating",
        "copying"
    ],
    "wof:name":"O T S Copiers",
    "wof:placetype":"venue"
},
  "geometry": {"coordinates":[-2.9742159843,51.3496513367],"type":"Point"}
}