{
  "type": "Feature",
  "properties": {
    "addr:full":"87 Moor Lane Preston Lancashire PR1 1JQ",
    "addr:housenumber":"87",
    "addr:postcode":"pr1 1jq",
    "addr:street":"Moor Lane",
    "iso:country":"GB",
    "sg:address":"87 Moor Lane",
    "sg:city":"Preston",
    "sg:classifiers":[
        {
            "category":"Fast Food",
            "type":"Food & Drink"
        }
    ],
    "sg:phone":"+44 1772 555164",
    "sg:postcode":"PR1 1JQ",
    "sg:province":"Lancashire",
    "sg:tags":[
        "away",
        "meal",
        "outlet",
        "take"
    ],
    "wof:name":"Moor Lane Takeaway",
    "wof:placetype":"venue"
},
  "geometry": {"coordinates":[-2.7048139572,53.7676124573],"type":"Point"}
}