{
  "type": "Feature",
  "properties": {
    "iso:country":"GB",
    "sg:address":"4 Hillbrow House, Hillbrow Road",
    "sg:city":"Liss",
    "sg:classifiers":[
        {
            "category":"Professional",
            "subcategory":"Computer Services",
            "type":"Services"
        }
    ],
    "sg:phone":"+44 1730 892388",
    "sg:postcode":"GU33 7RJ",
    "sg:province":"Hampshire",
    "sg:tags":[
        "system",
        "software"
    ],
    "wof:name":"Proteus Software",
    "wof:placetype":"venue"
},
  "geometry": {"coordinates":[-0.8926500082,51.0430259705],"type":"Point"}
}