{
  "type": "Feature",
  "properties": {
    "addr:full":"91 Hindes Road Harrow Greater London HA1 1RX",
    "addr:housenumber":"91",
    "addr:postcode":"ha1 1rx",
    "addr:street":"Hindes Road",
    "iso:country":"GB",
    "sg:address":"91 Hindes Road",
    "sg:city":"Harrow",
    "sg:classifiers":[
        {
            "category":"Education",
            "subcategory":"School",
            "type":"Public Place"
        }
    ],
    "sg:phone":"+44 20 8427 1304",
    "sg:postcode":"HA1 1RX",
    "sg:province":"Greater London",
    "sg:tags":[
        "independent",
        "preparatory"
    ],
    "wof:name":"Quainton Hall School",
    "wof:placetype":"venue"
},
  "geometry": {"coordinates":[-0.339146,51.584862],"type":"Point"}
}