{
  "type": "Feature",
  "properties": {
    "iso:country":"GB",
    "sg:address":"Stondon Works Clapgate Estate, Chivers Road Stondon Massey",
    "sg:city":"Brentwood",
    "sg:classifiers":[
        {
            "category":"Farming",
            "subcategory":"Farm",
            "type":"Manufacturing & Wholesale Goods"
        }
    ],
    "sg:phone":"+44 1277 824160",
    "sg:postcode":"CM15 0LH",
    "sg:province":"Essex",
    "sg:tags":[
        "agricultural"
    ],
    "wof:name":"J a D Plant",
    "wof:placetype":"venue"
},
  "geometry": {"coordinates":[0.288167,51.681969],"type":"Point"}
}