{
  "type": "Feature",
  "properties": {
    "addr:full":"Stondon Works Clapgate Estate, Chivers Road Stondon Massey Brentwood Essex CM15 0LH",
    "addr:postcode":"cm15 0lh",
    "addr:street":"Clapgate Estate Chivers Road",
    "iso:country":"GB",
    "sg:address":"Stondon Works Clapgate Estate, Chivers Road Stondon Massey",
    "sg:city":"Brentwood",
    "sg:classifiers":[
        {
            "category":"Farming",
            "subcategory":"Farm",
            "type":"Manufacturing & Wholesale Goods"
        }
    ],
    "sg:phone":"+44 1277 824160",
    "sg:postcode":"CM15 0LH",
    "sg:province":"Essex",
    "sg:tags":[
        "agricultural"
    ],
    "wof:name":"J a D Plant",
    "wof:placetype":"venue"
},
  "geometry": {"coordinates":[0.288167,51.681969],"type":"Point"}
}