{
  "type": "Feature",
  "properties": {
    "addr:full":"Lime Road, Broadmeadows Industrial Estate Dumbarton Argyll and Bute G82 2EL",
    "addr:housenumber":"estate",
    "addr:postcode":"g82 2el",
    "addr:street":"Lime Road;Industrial",
    "iso:country":"GB",
    "sg:address":"Lime Road, Broadmeadows Industrial Estate",
    "sg:city":"Dumbarton",
    "sg:classifiers":[
        {
            "category":"Manufacturing",
            "subcategory":"Metals",
            "type":"Manufacturing & Wholesale Goods"
        }
    ],
    "sg:phone":"+44 1389 734277",
    "sg:postcode":"G82 2EL",
    "sg:province":"Argyll and Bute",
    "sg:tags":[
        "steel",
        "fabricator",
        "erectors"
    ],
    "wof:name":"William P  Whiland & Son Ltd.",
    "wof:placetype":"venue"
},
  "geometry": {"coordinates":[-4.570759,55.948181],"type":"Point"}
}