{
  "type": "Feature",
  "properties": {
    "iso:country":"GB",
    "sg:address":"96 Kirkway, Middleton",
    "sg:city":"Manchester",
    "sg:classifiers":[
        {
            "category":"Food & Beverages",
            "subcategory":"Bakery",
            "type":"Retail Goods"
        }
    ],
    "sg:phone":"+44 161 653 6676",
    "sg:postcode":"M24 1EN",
    "sg:province":"Greater Manchester",
    "sg:tags":[
        "shop",
        "baker"
    ],
    "wof:name":"Martin's Swiss Confectioners",
    "wof:placetype":"venue"
},
  "geometry": {"coordinates":[-2.193959,53.542912],"type":"Point"}
}