{
  "type": "Feature",
  "properties": {
    "addr:full":"D4 Metropolitan Wharf, Wapping Wall London Greater London E1 9SS",
    "addr:postcode":"e1 9ss",
    "addr:street":"Wapping Wall",
    "iso:country":"GB",
    "sg:address":"D4 Metropolitan Wharf, Wapping Wall",
    "sg:city":"London",
    "sg:classifiers":[
        {
            "category":"Professional",
            "subcategory":"Art Services",
            "type":"Services"
        }
    ],
    "sg:phone":"+44 20 7702 9365",
    "sg:postcode":"E1 9SS",
    "sg:province":"Greater London",
    "sg:tags":[
        "graphic",
        "designer"
    ],
    "wof:name":"Big-Active Ltd.",
    "wof:placetype":"venue"
},
  "geometry": {"coordinates":[-0.0573600009,51.5179786682],"type":"Point"}
}