{
  "type": "Feature",
  "properties": {
    "addr:full":"8 Queen Victoria Rd Coventry West Midlands CV1 3JH",
    "addr:housenumber":"8",
    "addr:postcode":"cv1 3jh",
    "addr:street":"Queen Victoria Rd",
    "iso:country":"GB",
    "sg:address":"8 Queen Victoria Rd",
    "sg:city":"Coventry",
    "sg:classifiers":[
        {
            "category":"Real Estate",
            "subcategory":"Real Estate Operator",
            "type":"Services"
        }
    ],
    "sg:phone":"+44 24 7663 0923",
    "sg:postcode":"CV1 3JH",
    "sg:province":"West Midlands",
    "sg:tags":[
        "letting",
        "agent"
    ],
    "wof:name":"Asra Care Ltd",
    "wof:placetype":"venue"
},
  "geometry": {"coordinates":[-1.515867,52.405586],"type":"Point"}
}