{
  "type": "Feature",
  "properties": {
    "addr:full":"Unit 2, Roydsdale Way, Euroway Estate Bradford West Yorkshire BD4 6SE",
    "addr:housenumber":"unit 2",
    "addr:postcode":"bd4 6se",
    "addr:street":"Roydsdale Way Euroway Estate Bradford West",
    "iso:country":"GB",
    "sg:address":"Unit 2, Roydsdale Way, Euroway Estate",
    "sg:city":"Bradford",
    "sg:classifiers":[
        {
            "category":"Shopping",
            "subcategory":"News",
            "type":"Retail Goods"
        }
    ],
    "sg:phone":"+44 1274 680304",
    "sg:postcode":"BD4 6SE",
    "sg:province":"West Yorkshire",
    "sg:tags":[
        "newsagent"
    ],
    "wof:name":"John Menzies",
    "wof:placetype":"venue"
},
  "geometry": {"coordinates":[-1.7389140129,53.7557678223],"type":"Point"}
}