{
  "type": "Feature",
  "properties": {
    "addr:full":"68 Garstang Rd, Bowgreave Preston Lancashire PR3 1YE",
    "addr:housenumber":"68",
    "addr:postcode":"pr3 1ye",
    "addr:street":"Garstang Rd",
    "iso:country":"GB",
    "sg:address":"68 Garstang Rd, Bowgreave",
    "sg:city":"Preston",
    "sg:classifiers":[
        {
            "category":"Social Services",
            "subcategory":"Job Training",
            "type":"Services"
        }
    ],
    "sg:phone":"+44 1995 604225",
    "sg:postcode":"PR3 1YE",
    "sg:province":"Lancashire",
    "sg:tags":[
        "translator",
        "interpreter"
    ],
    "wof:name":"V Smolienko Mil Dip Trans",
    "wof:placetype":"venue"
},
  "geometry": {"coordinates":[-2.766887,53.888275],"type":"Point"}
}