{
  "type": "Feature",
  "properties": {
    "iso:country":"GB",
    "sg:address":"West Stoke Farm, Holne",
    "sg:city":"Newton Abbot",
    "sg:classifiers":[
        {
            "category":"Farming",
            "subcategory":"Livestock Farm",
            "type":"Manufacturing & Wholesale Goods"
        }
    ],
    "sg:postcode":"TQ13 7SS",
    "sg:province":"Devon",
    "sg:tags":[
        "others"
    ],
    "wof:name":"West Stoke Farm",
    "wof:placetype":"venue"
},
  "geometry": {"coordinates":[-3.8264729977,50.5114936829],"type":"Point"}
}