{
  "type": "Feature",
  "properties": {
    "addr:full":"Gotham Road Wirral Merseyside CH63 9NQ",
    "addr:postcode":"ch63 9nq",
    "addr:street":"Gotham Road",
    "iso:country":"GB",
    "sg:address":"Gotham Road",
    "sg:city":"Wirral",
    "sg:classifiers":[
        {
            "category":"Home & Garden",
            "subcategory":"Home Furnishings",
            "type":"Retail Goods"
        }
    ],
    "sg:phone":"+44 151 343 0800",
    "sg:postcode":"CH63 9NQ",
    "sg:province":"Merseyside",
    "sg:tags":[
        "awning",
        "canopy",
        "blinds"
    ],
    "wof:name":"Hillarys Blinds Ltd.",
    "wof:placetype":"venue"
},
  "geometry": {"coordinates":[-2.999469,53.340042],"type":"Point"}
}