{
  "type": "Feature",
  "properties": {
    "addr:full":"53 Market Street Buxton Derbyshire SK17 6LF",
    "addr:housenumber":"53",
    "addr:postcode":"sk17 6lf",
    "addr:street":"Market Street",
    "iso:country":"GB",
    "sg:address":"53 Market Street",
    "sg:city":"Buxton",
    "sg:classifiers":[
        {
            "category":"Personal",
            "subcategory":"Beauty Salon",
            "type":"Services"
        }
    ],
    "sg:phone":"+44 1298 23220",
    "sg:postcode":"SK17 6LF",
    "sg:province":"Derbyshire",
    "sg:tags":[
        "unisex",
        "hairdresser"
    ],
    "wof:name":"Cut & Curl",
    "wof:placetype":"venue"
},
  "geometry": {"coordinates":[-1.912286,53.254337],"type":"Point"}
}