{
  "type": "Feature",
  "properties": {
    "iso:country":"GB",
    "sg:address":"Chester House, 2-6 Mansfield Rd, Eastwood",
    "sg:city":"Nottingham",
    "sg:classifiers":[
        {
            "category":"Wholesale",
            "subcategory":"Medical Equipment & Supplies",
            "type":"Manufacturing & Wholesale Goods"
        }
    ],
    "sg:phone":"+44 1773 719844",
    "sg:postcode":"NG16 3AQ",
    "sg:province":"Derbyshire",
    "sg:tags":[
        "hospital"
    ],
    "wof:name":"Merdean Ltd",
    "wof:placetype":"venue"
},
  "geometry": {"coordinates":[-1.308198,53.018353],"type":"Point"}
}