{
  "type": "Feature",
  "properties": {
    "addr:full":"8 Mennakarne Estate Redruth Cornwall TR16 5RQ",
    "addr:housenumber":"8",
    "addr:postcode":"tr16 5rq",
    "addr:street":"Mennakarne Estate",
    "iso:country":"GB",
    "sg:address":"8 Mennakarne Estate",
    "sg:city":"Redruth",
    "sg:classifiers":[
        {
            "category":"Manufacturing",
            "subcategory":"Building Materials",
            "type":"Manufacturing & Wholesale Goods"
        }
    ],
    "sg:phone":"+44 1209 821726",
    "sg:postcode":"TR16 5RQ",
    "sg:province":"Cornwall",
    "sg:tags":[
        "tarmac",
        "asphalt"
    ],
    "wof:name":"D J Morford",
    "wof:placetype":"venue"
},
  "geometry": {"coordinates":[-5.1816940308,50.2314605713],"type":"Point"}
}