{
  "type": "Feature",
  "properties": {
    "addr:full":"Thistle House, Beechwood Park North Inverness Highland IV2 3ED",
    "addr:postcode":"iv2 3ed",
    "addr:street":"Beechwood Park North Inverness",
    "iso:country":"GB",
    "sg:address":"Thistle House, Beechwood Park North",
    "sg:city":"Inverness",
    "sg:classifiers":[
        {
            "category":"Landmark",
            "subcategory":"Tourist Information",
            "type":"Public Place"
        }
    ],
    "sg:phone":"+44 1463 716996",
    "sg:postcode":"IV2 3ED",
    "sg:province":"Highland",
    "wof:name":"Scottish Tourist Board",
    "wof:placetype":"venue"
},
  "geometry": {"coordinates":[-4.1975169182,57.4791870117],"type":"Point"}
}