{
  "type": "Feature",
  "properties": {
    "iso:country":"GB",
    "sg:address":"171 Lower House Lane",
    "sg:city":"Liverpool",
    "sg:classifiers":[
        {
            "category":"Government",
            "subcategory":"Post Office",
            "type":"Public Place"
        }
    ],
    "sg:phone":"+44 151 546 2149",
    "sg:postcode":"L11 2SF",
    "sg:province":"Merseyside",
    "wof:name":"Dog & Gun Post Office",
    "wof:placetype":"venue"
},
  "geometry": {"coordinates":[-2.910503,53.447826],"type":"Point"}
}