{
  "type": "Feature",
  "properties": {
    "iso:country":"GB",
    "sg:address":"16 Faraday Square",
    "sg:city":"Bedford",
    "sg:classifiers":[
        {
            "category":"Building & Trades",
            "subcategory":"Cleaning & Sanitation",
            "type":"Services"
        }
    ],
    "sg:phone":"+44 1234 262795",
    "sg:postcode":"MK42 9ND",
    "sg:province":"Bedfordshire",
    "sg:tags":[
        "cleaner",
        "window"
    ],
    "wof:name":"Cleaning Services D H",
    "wof:placetype":"venue"
},
  "geometry": {"coordinates":[-0.463057,52.122826],"type":"Point"}
}