{
  "type": "Feature",
  "properties": {
    "addr:full":"Vincents Road, Bumpers Farm Industrial Estate Chippenham Gloucestershire SN14 6QA",
    "addr:housenumber":"industrial",
    "addr:postcode":"sn14 6qa",
    "addr:street":"Vincents Road Bumpers;Estate",
    "iso:country":"GB",
    "sg:address":"Vincents Road, Bumpers Farm Industrial Estate",
    "sg:city":"Chippenham",
    "sg:classifiers":[
        {
            "category":"Bus Charters",
            "type":"Transportation"
        }
    ],
    "sg:phone":"+44 1249 444444",
    "sg:postcode":"SN14 6QA",
    "sg:province":"Gloucestershire",
    "sg:tags":[
        "hire",
        "coach"
    ],
    "wof:name":"Fosseway Coaches",
    "wof:placetype":"venue"
},
  "geometry": {"coordinates":[-2.146249,51.465321],"type":"Point"}
}