{
  "type": "Feature",
  "properties": {
    "addr:full":"Unit, 5 Lytham St. Annes Lancashire FY8 2BL",
    "addr:housenumber":"unit 5",
    "addr:postcode":"fy8 2bl",
    "addr:street":"Annes",
    "iso:country":"GB",
    "sg:address":"Unit, 5",
    "sg:city":"Lytham St. Annes",
    "sg:classifiers":[
        {
            "category":"Retail",
            "subcategory":"Auto Repair",
            "type":"Services"
        }
    ],
    "sg:phone":"+44 1253 714004",
    "sg:postcode":"FY8 2BL",
    "sg:province":"Lancashire",
    "sg:tags":[
        "body",
        "car"
    ],
    "wof:name":"Spectrum Auto Services",
    "wof:placetype":"venue"
},
  "geometry": {"coordinates":[-3.02969,53.75515],"type":"Point"}
}