{
  "type": "Feature",
  "properties": {
    "addr:full":"Kings Ct, Harwood Rd Horsham West Sussex RH13 5UR",
    "addr:postcode":"rh13 5ur",
    "addr:street":"Kings Ct Harwood Rd",
    "iso:country":"GB",
    "sg:address":"Kings Ct, Harwood Rd",
    "sg:city":"Horsham",
    "sg:classifiers":[
        {
            "category":"Bus Charters",
            "type":"Transportation"
        }
    ],
    "sg:phone":"+44 1403 252999",
    "sg:postcode":"RH13 5UR",
    "sg:province":"West Sussex",
    "sg:tags":[
        "hire",
        "coach"
    ],
    "wof:name":"Fleetmaster (PCV Hire)",
    "wof:placetype":"venue"
},
  "geometry": {"coordinates":[-0.309613,51.071384],"type":"Point"}
}