{
  "type": "Feature",
  "properties": {
    "iso:country":"GB",
    "sg:address":"Waunrhyddod, Cwmfelin Mynach",
    "sg:city":"Whitland",
    "sg:classifiers":[
        {
            "category":"Farming",
            "subcategory":"Dairy Farm",
            "type":"Manufacturing & Wholesale Goods"
        }
    ],
    "sg:phone":"+44 1994 448218",
    "sg:postcode":"SA34 0DH",
    "sg:province":"Carmarthenshire",
    "sg:tags":[
        "farmer"
    ],
    "wof:name":"H T Wood & Co",
    "wof:placetype":"venue"
},
  "geometry": {"coordinates":[-4.612054,51.819256],"type":"Point"}
}