{
  "type": "Feature",
  "properties": {
    "iso:country":"GB",
    "sg:address":"66 Eastlace Gate",
    "sg:city":"Doncaster",
    "sg:classifiers":[
        {
            "category":"Insurance",
            "subcategory":"Insurance Agent",
            "type":"Services"
        }
    ],
    "sg:phone":"+44 1302 368255",
    "sg:postcode":"DN1 1JD",
    "sg:province":"South Yorkshire",
    "sg:tags":[
        "broker"
    ],
    "wof:name":"Atkinson Smith",
    "wof:placetype":"venue"
},
  "geometry": {"coordinates":[-1.129748,53.523861],"type":"Point"}
}