{
  "type": "Feature",
  "properties": {
    "addr:full":"66 Fletcher Gardens, Amen Corner Bracknell Berkshire RG42 1FJ",
    "addr:housenumber":"66",
    "addr:postcode":"rg42 1fj",
    "addr:street":"Fletcher Gardens Amen Corner",
    "iso:country":"GB",
    "sg:address":"66 Fletcher Gardens, Amen Corner",
    "sg:city":"Bracknell",
    "sg:classifiers":[
        {
            "category":"Professional",
            "subcategory":"Computer Services",
            "type":"Services"
        }
    ],
    "sg:phone":"+44 1344 301871",
    "sg:postcode":"RG42 1FJ",
    "sg:province":"Berkshire",
    "sg:tags":[
        "system",
        "software"
    ],
    "wof:name":"Tudor Logic Ltd.",
    "wof:placetype":"venue"
},
  "geometry": {"coordinates":[-0.7828140259,51.4189682007],"type":"Point"}
}