{
  "type": "Feature",
  "properties": {
    "iso:country":"GB",
    "sg:address":"3 Plunkett Terr",
    "sg:city":"Chester Le Street",
    "sg:classifiers":[
        {
            "category":"Organizations",
            "subcategory":"Non-profit Organization",
            "type":"Services"
        }
    ],
    "sg:phone":"+44 191 388 7609",
    "sg:postcode":"DH2 2PA",
    "sg:province":"Durham",
    "sg:tags":[
        "fundraising",
        "charity"
    ],
    "wof:name":"House Of Armstrong The",
    "wof:placetype":"venue"
},
  "geometry": {"coordinates":[-1.6134929657,54.8587646484],"type":"Point"}
}