{
  "type": "Feature",
  "properties": {
    "iso:country":"GB",
    "sg:address":"3 Manor House Rd",
    "sg:city":"Rotherham",
    "sg:classifiers":[
        {
            "category":"Building & Trades",
            "subcategory":"Construction",
            "type":"Services"
        }
    ],
    "sg:phone":"+44 1709 558790",
    "sg:postcode":"S61 1NU",
    "sg:province":"South Yorkshire",
    "sg:tags":[
        "joiner",
        "carpenter"
    ],
    "wof:name":"R J Rowbotham",
    "wof:placetype":"venue"
},
  "geometry": {"coordinates":[-1.396198,53.437016],"type":"Point"}
}