{
  "type": "Feature",
  "properties": {
    "iso:country":"GB",
    "sg:address":"49 Moorburn Road",
    "sg:city":"Largs",
    "sg:classifiers":[
        {
            "category":"Retail",
            "subcategory":"Repair Shop",
            "type":"Services"
        },
        {
            "category":"Manufacturing",
            "subcategory":"Furniture",
            "type":"Manufacturing & Wholesale Goods"
        },
        {
            "category":"Building & Trades",
            "subcategory":"Construction",
            "type":"Services"
        }
    ],
    "sg:phone":"+44 1475 674992",
    "sg:postcode":"KA30 9DD",
    "sg:province":"North Ayrshire",
    "sg:tags":[
        "mnfr",
        "builder",
        "upholsterer"
    ],
    "wof:name":"Largs Upholstery",
    "wof:placetype":"venue"
},
  "geometry": {"coordinates":[-4.859873,55.799992],"type":"Point"}
}