{
  "type": "Feature",
  "properties": {
    "iso:country":"GB",
    "sg:address":"Western Road North",
    "sg:city":"Montrose",
    "sg:classifiers":[
        {
            "category":"Building & Trades",
            "subcategory":"Construction",
            "type":"Services"
        }
    ],
    "sg:phone":"+44 1674 672882",
    "sg:postcode":"DD10 8LN",
    "sg:province":"Aberdeenshire",
    "sg:tags":[
        "joiner",
        "carpenter"
    ],
    "wof:name":"Buchan & Coull",
    "wof:placetype":"venue"
},
  "geometry": {"coordinates":[-2.4715790749,56.7162590027],"type":"Point"}
}