{
  "type": "Feature",
  "properties": {
    "iso:country":"GB",
    "sg:address":"2-4 Queen Street",
    "sg:city":"Lymington",
    "sg:classifiers":[
        {
            "category":"Professional",
            "subcategory":"Printing & Photocopies",
            "type":"Services"
        }
    ],
    "sg:postcode":"SO41 9NH",
    "sg:province":"Hampshire",
    "sg:tags":[
        "printer"
    ],
    "wof:name":"Ace Print (Lymington) Ltd.",
    "wof:placetype":"venue"
},
  "geometry": {"coordinates":[-1.5486910343,50.7570228577],"type":"Point"}
}