{
  "type": "Feature",
  "properties": {
    "addr:full":"5 Hambleton Way York East Riding of Yorkshire YO3 9PJ",
    "addr:housenumber":"5",
    "addr:postcode":"yo3 9pj",
    "addr:street":"Hambleton Way",
    "iso:country":"GB",
    "sg:address":"5 Hambleton Way",
    "sg:city":"York",
    "sg:classifiers":[
        {
            "category":"Retail",
            "subcategory":"Driving School",
            "type":"Services"
        }
    ],
    "sg:phone":"+44 1904 760240",
    "sg:postcode":"YO3 9PJ",
    "sg:province":"East Riding of Yorkshire",
    "wof:name":"A1 School Of Motoring",
    "wof:placetype":"venue"
},
  "geometry": {"coordinates":[-1.0775380135,53.9731178284],"type":"Point"}
}