{
  "type": "Feature",
  "properties": {
    "addr:full":"Roanheads Sheltered Housing Comp Peterhead Aberdeenshire AB42 6LL",
    "addr:postcode":"ab42 6ll",
    "iso:country":"GB",
    "sg:address":"Roanheads Sheltered Housing Comp",
    "sg:city":"Peterhead",
    "sg:classifiers":[
        {
            "category":"Social Services",
            "subcategory":"Adult Care",
            "type":"Services"
        },
        {
            "category":"Government",
            "subcategory":"Office",
            "type":"Public Place"
        }
    ],
    "sg:phone":"+44 1779 477601",
    "sg:postcode":"AB42 6LL",
    "sg:province":"Aberdeenshire",
    "sg:tags":[
        "local",
        "day",
        "centre"
    ],
    "wof:name":"Roanheads Day Centre",
    "wof:placetype":"venue"
},
  "geometry": {"coordinates":[-1.797219038,57.5065345764],"type":"Point"}
}