{
  "type": "Feature",
  "properties": {
    "addr:full":"Hilltop Cottage, Brookside Farm Henfield West Sussex BN5 9SH",
    "addr:housenumber":"brookside farm henfield",
    "addr:postcode":"bn5 9sh",
    "iso:country":"GB",
    "sg:address":"Hilltop Cottage, Brookside Farm",
    "sg:city":"Henfield",
    "sg:classifiers":[
        {
            "category":"Building & Trades",
            "subcategory":"Construction",
            "type":"Services"
        }
    ],
    "sg:phone":"+44 1273 494501",
    "sg:postcode":"BN5 9SH",
    "sg:province":"West Sussex",
    "sg:tags":[
        "builder"
    ],
    "wof:name":"Lonsdale & Co",
    "wof:placetype":"venue"
},
  "geometry": {"coordinates":[-0.2722890079,50.9314193726],"type":"Point"}
}