{
  "type": "Feature",
  "properties": {
    "addr:full":"40 Nelson Street Largs North Ayrshire KA30 9AE",
    "addr:housenumber":"40",
    "addr:postcode":"ka30 9ae",
    "addr:street":"Nelson Street",
    "iso:country":"GB",
    "sg:address":"40 Nelson Street",
    "sg:city":"Largs",
    "sg:classifiers":[
        {
            "category":"Food & Beverages",
            "subcategory":"Fruits & Vegetables",
            "type":"Retail Goods"
        }
    ],
    "sg:postcode":"KA30 9AE",
    "sg:province":"North Ayrshire",
    "sg:tags":[
        "greengrocer"
    ],
    "wof:name":"Thomas J H Stevens",
    "wof:placetype":"venue"
},
  "geometry": {"coordinates":[-4.8664112091,55.7964630127],"type":"Point"}
}