{
  "type": "Feature",
  "properties": {
    "iso:country":"GB",
    "sg:address":"New Haven Business Park, Barton Lane, Eccles",
    "sg:city":"Manchester",
    "sg:classifiers":[
        {
            "category":"Retail",
            "subcategory":"Auto Repair",
            "type":"Services"
        }
    ],
    "sg:phone":"+44 161 788 0267",
    "sg:postcode":"M30 0HH",
    "sg:province":"Greater Manchester",
    "sg:tags":[
        "garage"
    ],
    "wof:name":"Celtech U K",
    "wof:placetype":"venue"
},
  "geometry": {"coordinates":[-2.344669,53.479053],"type":"Point"}
}