{
  "type": "Feature",
  "properties": {
    "addr:full":"89 Station Road, Forest Hall Newcastle-upon-tyne Tyne and Wear NE12 8AQ",
    "addr:housenumber":"89",
    "addr:postcode":"ne12 8aq",
    "addr:street":"Station Road",
    "iso:country":"GB",
    "sg:address":"89 Station Road, Forest Hall",
    "sg:city":"Newcastle-upon-tyne",
    "sg:classifiers":[
        {
            "category":"Organizations",
            "subcategory":"Non-profit Organization",
            "type":"Services"
        }
    ],
    "sg:phone":"+44 191 266 7488",
    "sg:postcode":"NE12 8AQ",
    "sg:province":"Tyne and Wear",
    "sg:tags":[
        "organisation",
        "voluntary",
        "charity"
    ],
    "wof:name":"Age Concern Training",
    "wof:placetype":"venue"
},
  "geometry": {"coordinates":[-1.5681179762,55.0195388794],"type":"Point"}
}