{
  "type": "Feature",
  "properties": {
    "addr:full":"58 Ivy Lane Canterbury Kent CT1 1TU",
    "addr:housenumber":"58",
    "addr:postcode":"ct1 1tu",
    "addr:street":"Ivy Lane",
    "iso:country":"GB",
    "sg:address":"58 Ivy Lane",
    "sg:city":"Canterbury",
    "sg:classifiers":[
        {
            "category":"Bars & Pubs",
            "type":"Food & Drink"
        }
    ],
    "sg:phone":"+44 1227 765419",
    "sg:postcode":"CT1 1TU",
    "sg:province":"Kent",
    "sg:tags":[
        "pubs",
        "inn"
    ],
    "wof:name":"The Two Sawyers",
    "wof:placetype":"venue"
},
  "geometry": {"coordinates":[1.085791,51.276875],"type":"Point"}
}