{
  "type": "Feature",
  "properties": {
    "addr:full":"The Sion, Crown Glass Place Bristol Somerset BS48 1RB",
    "addr:postcode":"bs48 1rb",
    "addr:street":"Place",
    "iso:country":"GB",
    "sg:address":"The Sion, Crown Glass Place",
    "sg:city":"Bristol",
    "sg:classifiers":[
        {
            "category":"Banks & Credit Unions",
            "subcategory":"Financial Services",
            "type":"Services"
        }
    ],
    "sg:phone":"+44 117 923 2831",
    "sg:postcode":"BS48 1RB",
    "sg:province":"Somerset",
    "sg:tags":[
        "consultant"
    ],
    "wof:name":"Agency Financial Services",
    "wof:placetype":"venue"
},
  "geometry": {"coordinates":[-2.75902,51.432281],"type":"Point"}
}