{
  "type": "Feature",
  "properties": {
    "iso:country":"GB",
    "sg:address":"Unit 1 London Road Business Park",
    "sg:city":"St Albans",
    "sg:classifiers":[
        {
            "category":"Home & Garden",
            "subcategory":"Hardware",
            "type":"Retail Goods"
        }
    ],
    "sg:phone":"+44 1727 859171",
    "sg:postcode":"AL1 1PN",
    "sg:province":"Hertfordshire",
    "sg:tags":[
        "equipment",
        "welding"
    ],
    "wof:name":"British Federal Ltd.",
    "wof:placetype":"venue"
},
  "geometry": {"coordinates":[-0.339024,51.75071],"type":"Point"}
}