{
  "type": "Feature",
  "properties": {
    "addr:full":"1 St Andrew Street Castle Douglas Dumfries and Galloway DG7 1DE",
    "addr:housenumber":"1",
    "addr:postcode":"dg7 1de",
    "addr:street":"St Andrew Street",
    "iso:country":"GB",
    "sg:address":"1 St Andrew Street",
    "sg:city":"Castle Douglas",
    "sg:classifiers":[
        {
            "category":"Health Services",
            "subcategory":"Dentist",
            "type":"Services"
        }
    ],
    "sg:phone":"+44 1556 503348",
    "sg:postcode":"DG7 1DE",
    "sg:province":"Dumfries and Galloway",
    "wof:name":"D D McConnachie",
    "wof:placetype":"venue"
},
  "geometry": {"coordinates":[-3.9328570366,54.939743042],"type":"Point"}
}