{
  "type": "Feature",
  "properties": {
    "iso:country":"GB",
    "sg:address":"129 Mansfield Road, Clipstone Village",
    "sg:city":"Mansfield",
    "sg:classifiers":[
        {
            "category":"Shopping",
            "subcategory":"Gifts & Souvenirs",
            "type":"Retail Goods"
        }
    ],
    "sg:postcode":"NG21 9AA",
    "sg:province":"Nottinghamshire",
    "sg:tags":[
        "poster",
        "card"
    ],
    "wof:name":"Clipstone Village Post Office",
    "wof:placetype":"venue"
},
  "geometry": {"coordinates":[-1.0753819942,53.1937179565],"type":"Point"}
}