{
  "type": "Feature",
  "properties": {
    "iso:country":"GB",
    "sg:address":"45 Whitecroft Road, Meldreth",
    "sg:city":"Royston",
    "sg:classifiers":[
        {
            "category":"Personal",
            "subcategory":"Beauty Salon",
            "type":"Services"
        }
    ],
    "sg:phone":"+44 1763 262424",
    "sg:postcode":"SG8 6LS",
    "sg:province":"Bedfordshire",
    "wof:name":"Something Different",
    "wof:placetype":"venue"
},
  "geometry": {"coordinates":[0.003488,52.092754],"type":"Point"}
}