{
  "type": "Feature",
  "properties": {
    "addr:full":"102 Fishergate York North Yorkshire YO10 4BB",
    "addr:housenumber":"102",
    "addr:postcode":"yo10 4bb",
    "addr:street":"Fishergate",
    "iso:country":"GB",
    "sg:address":"102 Fishergate",
    "sg:city":"York",
    "sg:classifiers":[
        {
            "category":"Fast Food",
            "type":"Food & Drink"
        }
    ],
    "sg:phone":"+44 1904 646511",
    "sg:postcode":"YO10 4BB",
    "sg:province":"North Yorkshire",
    "sg:tags":[
        "away",
        "take"
    ],
    "wof:name":"Eastern Promise",
    "wof:placetype":"venue"
},
  "geometry": {"coordinates":[-1.075824976,53.9508323669],"type":"Point"}
}