{
  "type": "Feature",
  "properties": {
    "addr:full":"8 Station Avenue Haddington East Lothian EH41 4EG",
    "addr:housenumber":"8",
    "addr:postcode":"eh41 4eg",
    "addr:street":"Station Avenue",
    "iso:country":"GB",
    "sg:address":"8 Station Avenue",
    "sg:city":"Haddington",
    "sg:classifiers":[
        {
            "category":"Real Estate",
            "subcategory":"Architect",
            "type":"Services"
        }
    ],
    "sg:phone":"+44 1620 825504",
    "sg:postcode":"EH41 4EG",
    "sg:province":"East Lothian",
    "sg:tags":[
        "architectural"
    ],
    "wof:name":"Building & Design Services",
    "wof:placetype":"venue"
},
  "geometry": {"coordinates":[-2.788146019,55.9553718567],"type":"Point"}
}