{
  "type": "Feature",
  "properties": {
    "addr:full":"109 Cobbold Road, Willesden Willesden Greater London NW10 9SL",
    "addr:housenumber":"109",
    "addr:postcode":"nw10 9sl",
    "addr:street":"Cobbold Road",
    "iso:country":"GB",
    "sg:address":"109 Cobbold Road, Willesden",
    "sg:city":"Willesden",
    "sg:classifiers":[
        {
            "category":"Manufacturing",
            "subcategory":"Petroleum Products",
            "type":"Manufacturing & Wholesale Goods"
        }
    ],
    "sg:phone":"+44 20 8451 3077",
    "sg:postcode":"NW10 9SL",
    "sg:province":"Greater London",
    "sg:tags":[
        "double",
        "glazing"
    ],
    "wof:name":"Vag Windows",
    "wof:placetype":"venue"
},
  "geometry": {"coordinates":[-0.2458630055,51.5484733582],"type":"Point"}
}