{
  "type": "Feature",
  "properties": {
    "iso:country":"GB",
    "sg:address":"60 Ainsworth Road, Radcliffe",
    "sg:city":"Manchester",
    "sg:classifiers":[
        {
            "category":"Health Services",
            "subcategory":"Medical Lab",
            "type":"Services"
        },
        {
            "category":"Health Services",
            "subcategory":"Dentist",
            "type":"Services"
        }
    ],
    "sg:phone":"+44 161 725 9869",
    "sg:postcode":"M26 4FA",
    "sg:province":"Greater Manchester",
    "sg:tags":[
        "technician",
        "dental"
    ],
    "wof:name":"Crystal Ceramics",
    "wof:placetype":"venue"
},
  "geometry": {"coordinates":[-2.3338000774,53.5653648376],"type":"Point"}
}