{
  "type": "Feature",
  "properties": {
    "iso:country":"GB",
    "sg:address":"Oak St",
    "sg:city":"Stoke On Trent",
    "sg:classifiers":[
        {
            "category":"Organizations",
            "subcategory":"Membership Organization",
            "type":"Services"
        }
    ],
    "sg:phone":"+44 1782 214998",
    "sg:postcode":"ST1 2NB",
    "sg:province":"Staffordshire",
    "sg:tags":[
        "club"
    ],
    "wof:name":"Birches Head & District Gardeners Club & Institute",
    "wof:placetype":"venue"
},
  "geometry": {"coordinates":[-2.165044,53.033829],"type":"Point"}
}