{
  "type": "Feature",
  "properties": {
    "addr:full":"Old Market Street Usk Monmouthshire NP15 1AL",
    "addr:postcode":"np15 1al",
    "addr:street":"Old Market Street",
    "iso:country":"GB",
    "sg:address":"Old Market Street",
    "sg:city":"Usk",
    "sg:classifiers":[
        {
            "category":"Shopping",
            "subcategory":"Antiques",
            "type":"Retail Goods"
        }
    ],
    "sg:postcode":"NP15 1AL",
    "sg:province":"Monmouthshire",
    "wof:name":"Shirley Lockyer",
    "wof:placetype":"venue"
},
  "geometry": {"coordinates":[-2.902624,51.700829],"type":"Point"}
}