{
  "type": "Feature",
  "properties": {
    "addr:full":"Averlea, Polgooth St Austell Cornwall PL26 7BP",
    "addr:postcode":"pl26 7bp",
    "iso:country":"GB",
    "sg:address":"Averlea, Polgooth",
    "sg:city":"St Austell",
    "sg:classifiers":[
        {
            "category":"Social Services",
            "subcategory":"Retirement Home",
            "type":"Services"
        }
    ],
    "sg:phone":"+44 1726 66892",
    "sg:postcode":"PL26 7BP",
    "sg:province":"Cornwall",
    "sg:tags":[
        "rest"
    ],
    "wof:name":"Averlea Rest Home",
    "wof:placetype":"venue"
},
  "geometry": {"coordinates":[-4.820494175,50.3215484619],"type":"Point"}
}