{
  "type": "Feature",
  "properties": {
    "addr:full":"Cross Gates Road Leeds West Yorkshire LS15 7PE",
    "addr:postcode":"ls15 7pe",
    "addr:street":"Cross Gates Road",
    "iso:country":"GB",
    "sg:address":"Cross Gates Road",
    "sg:city":"Leeds",
    "sg:classifiers":[
        {
            "category":"Home & Garden",
            "subcategory":"Home Furnishings",
            "type":"Retail Goods"
        },
        {
            "category":"Home & Garden",
            "subcategory":"Furniture",
            "type":"Retail Goods"
        }
    ],
    "sg:phone":"+44 113 284 0668",
    "sg:postcode":"LS15 7PE",
    "sg:province":"West Yorkshire",
    "sg:tags":[
        "beds",
        "bedding",
        "blanket",
        "outlet"
    ],
    "wof:name":"Chiltern Mills",
    "wof:placetype":"venue"
},
  "geometry": {"coordinates":[-1.4579240084,53.808391571],"type":"Point"}
}