{
  "type": "Feature",
  "properties": {
    "iso:country":"GB",
    "sg:address":"5 Maison Dieu Rd",
    "sg:city":"Dover",
    "sg:classifiers":[
        {
            "category":"Building & Trades",
            "subcategory":"Landscaping Services",
            "type":"Services"
        }
    ],
    "sg:postcode":"CT16 1RW",
    "sg:province":"Kent",
    "sg:tags":[
        "gardening"
    ],
    "wof:name":"Haviland,G B,",
    "wof:placetype":"venue"
},
  "geometry": {"coordinates":[1.315007,51.12756],"type":"Point"}
}