{
  "type": "Feature",
  "properties": {
    "addr:full":"Terminal Building, Edinburgh Airport Edinburgh City of Edinburgh EH12 9DN",
    "addr:postcode":"eh12 9dn",
    "iso:country":"GB",
    "sg:address":"Terminal Building, Edinburgh Airport",
    "sg:city":"Edinburgh",
    "sg:classifiers":[
        {
            "category":"Airline",
            "type":"Transportation"
        }
    ],
    "sg:phone":"+44 131 344 3222",
    "sg:postcode":"EH12 9DN",
    "sg:province":"City of Edinburgh",
    "wof:name":"Sabena",
    "wof:placetype":"venue"
},
  "geometry": {"coordinates":[-3.3615040779,55.944644928],"type":"Point"}
}