{
  "type": "Feature",
  "properties": {
    "addr:full":"Unit 4 Ogmore Crescent, Bridgend Industrial Estate Bridgend Bridgend CF31 3TE",
    "addr:housenumber":"unit 4",
    "addr:postcode":"cf31 3te",
    "addr:street":"Ogmore Crescent;Industrial Estate",
    "iso:country":"GB",
    "sg:address":"Unit 4 Ogmore Crescent, Bridgend Industrial Estate",
    "sg:city":"Bridgend",
    "sg:classifiers":[
        {
            "category":"Building & Trades",
            "subcategory":"Construction",
            "type":"Services"
        }
    ],
    "sg:phone":"+44 1656 661808",
    "sg:postcode":"CF31 3TE",
    "sg:province":"Bridgend",
    "sg:tags":[
        "builder"
    ],
    "wof:name":"Colston",
    "wof:placetype":"venue"
},
  "geometry": {"coordinates":[-3.5648341179,51.501121521],"type":"Point"}
}