{
  "type": "Feature",
  "properties": {
    "addr:full":"11 Clos Y Gof, Bryn Dyffryn Cardiff Cardiff CF5 4QQ",
    "addr:housenumber":"11",
    "addr:postcode":"cf5 4qq",
    "addr:street":"Clos Y Gof Bryn",
    "iso:country":"GB",
    "sg:address":"11 Clos Y Gof, Bryn Dyffryn",
    "sg:city":"Cardiff",
    "sg:classifiers":[
        {
            "category":"Building & Trades",
            "subcategory":"Construction",
            "type":"Services"
        }
    ],
    "sg:postcode":"CF5 4QQ",
    "sg:province":"Cardiff",
    "sg:tags":[
        "builder"
    ],
    "wof:name":"Walsh,Michael,",
    "wof:placetype":"venue"
},
  "geometry": {"coordinates":[-3.2724881172,51.4775924683],"type":"Point"}
}