{
  "type": "Feature",
  "properties": {
    "iso:country":"GB",
    "sg:address":"Unit 2 Crossley Mills, New Mill Road",
    "sg:city":"Huddersfield",
    "sg:classifiers":[
        {
            "category":"Autos & Motor Vehicles",
            "subcategory":"Auto Supplies",
            "type":"Retail Goods"
        }
    ],
    "sg:phone":"+44 1484 660222",
    "sg:postcode":"HD9 6QB",
    "sg:province":"South Yorkshire",
    "sg:tags":[
        "electric",
        "servicing",
        "sales"
    ],
    "wof:name":"Kenworth Products Ltd",
    "wof:placetype":"venue"
},
  "geometry": {"coordinates":[-1.78444,53.602661],"type":"Point"}
}