{
  "type": "Feature",
  "properties": {
    "addr:full":"8 Bloomsberry Ay West End Hampshire W1P 9DG",
    "addr:housenumber":"8;ay",
    "addr:postcode":"w1p 9dg",
    "addr:street":"Bloomsberry;End Hampshire",
    "iso:country":"GB",
    "sg:address":"8 Bloomsberry Ay",
    "sg:city":"West End",
    "sg:classifiers":[
        {
            "category":"Food & Beverages",
            "subcategory":"Specialty",
            "type":"Retail Goods"
        }
    ],
    "sg:phone":"+44 20 7323 0660",
    "sg:postcode":"W1P 9DG",
    "sg:province":"Hampshire",
    "sg:tags":[
        "vegetarian"
    ],
    "wof:name":"Mandeer Vegetarian Restaurant",
    "wof:placetype":"venue"
},
  "geometry": {"coordinates":[-0.1389899999,51.5075798035],"type":"Point"}
}