{
  "type": "Feature",
  "properties": {
    "addr:full":"72/74 Newmarket Road Cambridge Cambridgeshire CB5 8DZ",
    "addr:housenumber":"72 / 74",
    "addr:postcode":"cb5 8dz",
    "addr:street":"Newmarket Road",
    "iso:country":"GB",
    "sg:address":"72/74 Newmarket Road",
    "sg:city":"Cambridge",
    "sg:classifiers":[
        {
            "category":"Professional",
            "subcategory":"Lawyer & Legal Services",
            "type":"Services"
        }
    ],
    "sg:postcode":"CB5 8DZ",
    "sg:province":"Cambridgeshire",
    "sg:tags":[
        "advice",
        "counselling"
    ],
    "wof:name":"Cambridge & District Citizens Advice Bur",
    "wof:placetype":"venue"
},
  "geometry": {"coordinates":[0.1361860037,52.2083625793],"type":"Point"}
}