{
  "type": "Feature",
  "properties": {
    "addr:full":"509 Foleshill Road Coventry Warwickshire CV6 5AU",
    "addr:housenumber":"509",
    "addr:postcode":"cv6 5au",
    "addr:street":"Foleshill Road",
    "iso:country":"GB",
    "sg:address":"509 Foleshill Road",
    "sg:city":"Coventry",
    "sg:classifiers":[
        {
            "category":"Shopping",
            "subcategory":"Clothing, Apparel, & Fashions",
            "type":"Retail Goods"
        }
    ],
    "sg:phone":"+44 24 7663 7423",
    "sg:postcode":"CV6 5AU",
    "sg:province":"Warwickshire",
    "sg:tags":[
        "shop"
    ],
    "wof:name":"Khuman Clothing Store",
    "wof:placetype":"venue"
},
  "geometry": {"coordinates":[-1.499615,52.428432],"type":"Point"}
}