{
  "type": "Feature",
  "properties": {
    "addr:full":"23 Spiller Road Weymouth Dorset DT3 4AX",
    "addr:housenumber":"23",
    "addr:postcode":"dt3 4ax",
    "addr:street":"Spiller Road",
    "iso:country":"GB",
    "sg:address":"23 Spiller Road",
    "sg:city":"Weymouth",
    "sg:classifiers":[
        {
            "category":"Professional",
            "subcategory":"Engineering",
            "type":"Services"
        }
    ],
    "sg:postcode":"DT3 4AX",
    "sg:province":"Dorset",
    "sg:tags":[
        "contractor",
        "electrical",
        "engineer"
    ],
    "wof:name":"Pye Hill Electrical Ltd.",
    "wof:placetype":"venue"
},
  "geometry": {"coordinates":[-2.5010669231,50.6217002869],"type":"Point"}
}