{
  "type": "Feature",
  "properties": {
    "iso:country":"GB",
    "sg:address":"Highview House, Tattenham Crescent",
    "sg:city":"Epsom",
    "sg:classifiers":[
        {
            "category":"Professional",
            "subcategory":"Employment Agencies",
            "type":"Services"
        }
    ],
    "sg:phone":"+44 1708 867575",
    "sg:postcode":"KT18 5QJ",
    "sg:province":"Surrey",
    "sg:tags":[
        "consultant"
    ],
    "wof:name":"Premier Recruitment International Ltd",
    "wof:placetype":"venue"
},
  "geometry": {"coordinates":[-0.241603002,51.3096008301],"type":"Point"}
}