{
  "type": "Feature",
  "properties": {
    "addr:full":"30 Keith Dr Wirral Merseyside CH63 0PB",
    "addr:housenumber":"30",
    "addr:postcode":"ch63 0pb",
    "addr:street":"Keith Dr",
    "iso:country":"GB",
    "sg:address":"30 Keith Dr",
    "sg:city":"Wirral",
    "sg:classifiers":[
        {
            "category":"Retail",
            "subcategory":"Driving School",
            "type":"Services"
        }
    ],
    "sg:phone":"+44 151 334 6639",
    "sg:postcode":"CH63 0PB",
    "sg:province":"Merseyside",
    "wof:name":"Dave Jones",
    "wof:placetype":"venue"
},
  "geometry": {"coordinates":[-2.9843840599,53.3142471313],"type":"Point"}
}