{
  "type": "Feature",
  "properties": {
    "addr:full":"Park Farm, Park Lane, Endon Stoke-on-trent Staffordshire ST9 9JB",
    "addr:postcode":"st9 9jb",
    "addr:street":"Park;Park Lane",
    "iso:country":"GB",
    "sg:address":"Park Farm, Park Lane, Endon",
    "sg:city":"Stoke-on-trent",
    "sg:classifiers":[
        {
            "category":"Freight",
            "type":"Transportation"
        }
    ],
    "sg:phone":"+44 1782 503186",
    "sg:postcode":"ST9 9JB",
    "sg:province":"Staffordshire",
    "sg:tags":[
        "haulage",
        "road"
    ],
    "wof:name":"D W Weaver",
    "wof:placetype":"venue"
},
  "geometry": {"coordinates":[-2.108759,53.078529],"type":"Point"}
}