{
  "type": "Feature",
  "properties": {
    "addr:full":"606 Warwick Rd Solihull West Midlands B91 1AA",
    "addr:housenumber":"606",
    "addr:postcode":"b91 1aa",
    "addr:street":"Warwick Rd",
    "iso:country":"GB",
    "sg:address":"606 Warwick Rd",
    "sg:city":"Solihull",
    "sg:classifiers":[
        {
            "category":"Health Services",
            "subcategory":"Dentist",
            "type":"Services"
        }
    ],
    "sg:phone":"+44 121 705 5925",
    "sg:postcode":"B91 1AA",
    "sg:province":"West Midlands",
    "wof:name":"R.A Bailey",
    "wof:placetype":"venue"
},
  "geometry": {"coordinates":[-1.7823209763,52.4175109863],"type":"Point"}
}