{
  "type": "Feature",
  "properties": {
    "addr:full":"64 London Road St Leonards-on-sea East Sussex TN37 6AS",
    "addr:housenumber":"64",
    "addr:postcode":"leonards-on-sea;tn37 6as",
    "addr:street":"London Road St",
    "iso:country":"GB",
    "sg:address":"64 London Road",
    "sg:city":"St Leonards-on-sea",
    "sg:classifiers":[
        {
            "category":"Social Services",
            "subcategory":"Adult Care",
            "type":"Services"
        },
        {
            "category":"Organizations",
            "subcategory":"Non-profit Organization",
            "type":"Services"
        }
    ],
    "sg:phone":"+44 1424 424813",
    "sg:postcode":"TN37 6AS",
    "sg:province":"East Sussex",
    "sg:tags":[
        "organisation",
        "charity",
        "voluntary",
        "day",
        "centre"
    ],
    "wof:name":"Mencap",
    "wof:placetype":"venue"
},
  "geometry": {"coordinates":[0.558673,50.85619],"type":"Point"}
}