{
  "type": "Feature",
  "properties": {
    "addr:full":"26 Highfield Road Birkenhead Merseyside CH42 2BY",
    "addr:housenumber":"26",
    "addr:postcode":"ch42 2by",
    "addr:street":"Highfield Road",
    "iso:country":"GB",
    "sg:address":"26 Highfield Road",
    "sg:city":"Birkenhead",
    "sg:classifiers":[
        {
            "category":"Organizations",
            "subcategory":"Religious Organization",
            "type":"Services"
        }
    ],
    "sg:phone":"+44 151 645 9482",
    "sg:postcode":"CH42 2BY",
    "sg:province":"Merseyside",
    "sg:tags":[
        "organisation",
        "place",
        "worship"
    ],
    "wof:name":"Holy Family Convent",
    "wof:placetype":"venue"
},
  "geometry": {"coordinates":[-3.0139501095,53.3680686951],"type":"Point"}
}