{
  "type": "Feature",
  "properties": {
    "addr:full":"98 Ossulton Way London Greater London N2 0LD",
    "addr:housenumber":"98",
    "addr:postcode":"n2 0ld",
    "addr:street":"Ossulton Way",
    "iso:country":"GB",
    "sg:address":"98 Ossulton Way",
    "sg:city":"London",
    "sg:classifiers":[
        {
            "category":"Shopping",
            "subcategory":"Clothing, Apparel, & Fashions",
            "type":"Retail Goods"
        }
    ],
    "sg:phone":"+44 20 8444 1121",
    "sg:postcode":"N2 0LD",
    "sg:province":"Greater London",
    "sg:tags":[
        "clothing"
    ],
    "wof:name":"London Team (U K) Ltd.",
    "wof:placetype":"venue"
},
  "geometry": {"coordinates":[-0.1796260029,51.5907974243],"type":"Point"}
}