{
  "type": "Feature",
  "properties": {
    "addr:full":"166 Spring Cottage Road, Overseal Swadlincote Derbyshire DE12 6ND",
    "addr:housenumber":"166",
    "addr:postcode":"de12 6nd",
    "addr:street":"Spring Cottage Road",
    "iso:country":"GB",
    "sg:address":"166 Spring Cottage Road, Overseal",
    "sg:city":"Swadlincote",
    "sg:classifiers":[
        {
            "category":"Bars & Pubs",
            "type":"Food & Drink"
        },
        {
            "category":"Community Center",
            "subcategory":"Social",
            "type":"Public Place"
        }
    ],
    "sg:phone":"+44 1283 760493",
    "sg:postcode":"DE12 6ND",
    "sg:province":"Derbyshire",
    "sg:tags":[
        "pubs",
        "house",
        "inn",
        "activity"
    ],
    "wof:name":"The Navigation Inn",
    "wof:placetype":"venue"
},
  "geometry": {"coordinates":[-1.5431,52.749313],"type":"Point"}
}