{
  "type": "Feature",
  "properties": {
    "addr:full":"208 Coombe Valley Road Dover Kent CT17 0HG",
    "addr:housenumber":"208",
    "addr:postcode":"ct17 0hg",
    "addr:street":"Coombe Valley Road",
    "iso:country":"GB",
    "sg:address":"208 Coombe Valley Road",
    "sg:city":"Dover",
    "sg:classifiers":[
        {
            "category":"Autos & Motor Vehicles",
            "subcategory":"Motorcycle Sales",
            "type":"Retail Goods"
        }
    ],
    "sg:phone":"+44 1304 203343",
    "sg:postcode":"CT17 0HG",
    "sg:province":"Kent",
    "wof:name":"Coombe Valley Motorcycles",
    "wof:placetype":"venue"
},
  "geometry": {"coordinates":[1.288986,51.131248],"type":"Point"}
}