{
  "type": "Feature",
  "properties": {
    "addr:full":"22 Chester Rd, Gresford Wrexham Wrexham LL12 8TN",
    "addr:housenumber":"22",
    "addr:postcode":"ll12 8tn",
    "addr:street":"Chester Rd",
    "iso:country":"GB",
    "sg:address":"22 Chester Rd, Gresford",
    "sg:city":"Wrexham",
    "sg:classifiers":[
        {
            "category":"Building & Trades",
            "subcategory":"Construction",
            "type":"Services"
        }
    ],
    "sg:postcode":"LL12 8TN",
    "sg:province":"Wrexham",
    "sg:tags":[
        "glazier",
        "decorator",
        "painter"
    ],
    "wof:name":"Randles,Malvin,",
    "wof:placetype":"venue"
},
  "geometry": {"coordinates":[-2.973375082,53.0845184326],"type":"Point"}
}