{
  "type": "Feature",
  "properties": {
    "iso:country":"GB",
    "sg:address":"Tynshettin, Llanwddyn",
    "sg:city":"Oswestry",
    "sg:classifiers":[
        {
            "category":"Farming",
            "subcategory":"Livestock Farm",
            "type":"Manufacturing & Wholesale Goods"
        },
        {
            "category":"Farming",
            "subcategory":"Farm",
            "type":"Manufacturing & Wholesale Goods"
        }
    ],
    "sg:postcode":"SY10 0NN",
    "sg:province":"Shropshire",
    "sg:tags":[
        "mixed",
        "crop",
        "others"
    ],
    "wof:name":"Emyr L Owen",
    "wof:placetype":"venue"
},
  "geometry": {"coordinates":[-3.4524440765,52.7612037659],"type":"Point"}
}