{
  "type": "Feature",
  "properties": {
    "iso:country":"GB",
    "sg:address":"243 The Ridgeway",
    "sg:city":"Harrow",
    "sg:classifiers":[
        {
            "category":"Professional",
            "subcategory":"Engineering",
            "type":"Services"
        }
    ],
    "sg:phone":"+44 181 861 6494",
    "sg:postcode":"HA2 7PA",
    "sg:province":"Greater London",
    "sg:tags":[
        "contractor",
        "electrical",
        "engineer"
    ],
    "wof:name":"Wallis,R S,Electrical Services Ltd",
    "wof:placetype":"venue"
},
  "geometry": {"coordinates":[-0.3600620031,51.5776786804],"type":"Point"}
}