{
  "type": "Feature",
  "properties": {
    "iso:country":"GB",
    "sg:address":"32 Manor Park Drive, Finchampstead",
    "sg:city":"Wokingham",
    "sg:classifiers":[
        {
            "category":"Professional",
            "subcategory":"Accounting & Tax Preparation",
            "type":"Services"
        }
    ],
    "sg:postcode":"RG40 4XE",
    "sg:province":"Berkshire",
    "sg:tags":[
        "accountant"
    ],
    "wof:name":"Paul Manning & Associates Ltd.",
    "wof:placetype":"venue"
},
  "geometry": {"coordinates":[-0.865181,51.378082],"type":"Point"}
}