{
  "type": "Feature",
  "properties": {
    "addr:full":"Elite House, 663-675 Princes Road Dartford Kent DA2 6EJ",
    "addr:housenumber":"663-675",
    "addr:postcode":"da2 6ej",
    "addr:street":"Princes Road",
    "iso:country":"GB",
    "sg:address":"Elite House, 663-675 Princes Road",
    "sg:city":"Dartford",
    "sg:classifiers":[
        {
            "category":"Building & Trades",
            "subcategory":"Cleaning & Sanitation",
            "type":"Services"
        }
    ],
    "sg:postcode":"DA2 6EJ",
    "sg:province":"Kent",
    "sg:tags":[
        "repair",
        "lift",
        "-"
    ],
    "wof:name":"Elite Elevators Ltd.",
    "wof:placetype":"venue"
},
  "geometry": {"coordinates":[0.2486719936,51.4381141663],"type":"Point"}
}