{
  "type": "Feature",
  "properties": {
    "addr:full":"Campbell Park, Fernhurst Road, Milland Liphook Hampshire GU30 7LU",
    "addr:postcode":"gu30 7lu",
    "addr:street":"Fernhurst Road",
    "iso:country":"GB",
    "sg:address":"Campbell Park, Fernhurst Road, Milland",
    "sg:city":"Liphook",
    "sg:classifiers":[
        {
            "category":"Professional",
            "subcategory":"Management & Consulting",
            "type":"Services"
        }
    ],
    "sg:phone":"+44 1428 741333",
    "sg:postcode":"GU30 7LU",
    "sg:province":"Hampshire",
    "sg:tags":[
        "sport"
    ],
    "wof:name":"Professional Golf Management Ltd.",
    "wof:placetype":"venue"
},
  "geometry": {"coordinates":[-0.7991999984,51.0776405334],"type":"Point"}
}