{
  "type": "Feature",
  "properties": {
    "iso:country":"GB",
    "sg:address":"81 Lee Lane, Horwich",
    "sg:city":"Bolton",
    "sg:classifiers":[
        {
            "category":"Real Estate",
            "subcategory":"Surveying",
            "type":"Services"
        }
    ],
    "sg:phone":"+44 1204 667766",
    "sg:postcode":"BL6 7AU",
    "sg:province":"Lancashire",
    "sg:tags":[
        "surveyor",
        "quantity"
    ],
    "sg:website":"http://www.pike-qs.demon.co.uk",
    "wof:name":"Ian James & Associates",
    "wof:placetype":"venue"
},
  "geometry": {"coordinates":[-2.546765089,53.6006813049],"type":"Point"}
}