{
  "type": "Feature",
  "properties": {
    "addr:full":"37 Parkside, Wollaton Nottingham Nottinghamshire NG8 2NQ",
    "addr:housenumber":"37",
    "addr:postcode":"ng8 2nq",
    "addr:street":"Parkside",
    "iso:country":"GB",
    "sg:address":"37 Parkside, Wollaton",
    "sg:city":"Nottingham",
    "sg:classifiers":[
        {
            "category":"Manufacturing",
            "subcategory":"Buildings",
            "type":"Manufacturing & Wholesale Goods"
        }
    ],
    "sg:phone":"+44 115 925 4506",
    "sg:postcode":"NG8 2NQ",
    "sg:province":"Nottinghamshire",
    "sg:tags":[
        "portable"
    ],
    "wof:name":"Prisma Products",
    "wof:placetype":"venue"
},
  "geometry": {"coordinates":[-1.220644,52.942528],"type":"Point"}
}