{
  "type": "Feature",
  "properties": {
    "iso:country":"GB",
    "sg:address":"Sunrise Business Park, Higher Shaftesbury Rd",
    "sg:city":"Blandford Forum",
    "sg:classifiers":[
        {
            "category":"Professional",
            "subcategory":"Management & Consulting",
            "type":"Services"
        }
    ],
    "sg:phone":"+44 1258 830808",
    "sg:postcode":"DT11 8ST",
    "sg:province":"Dorset",
    "sg:tags":[
        "consultant",
        "business"
    ],
    "wof:name":"Whiterose Management",
    "wof:placetype":"venue"
},
  "geometry": {"coordinates":[-2.119489,50.869389],"type":"Point"}
}