{
  "type": "Feature",
  "properties": {
    "iso:country":"GB",
    "sg:address":"634 Wilmslow Road",
    "sg:city":"Manchester",
    "sg:classifiers":[
        {
            "category":"Professional",
            "subcategory":"Computer Services",
            "type":"Services"
        }
    ],
    "sg:phone":"+44 161 447 6800",
    "sg:postcode":"M20 3QX",
    "sg:province":"Greater Manchester",
    "sg:tags":[
        "system",
        "software"
    ],
    "wof:name":"Teleca Ltd.",
    "wof:placetype":"venue"
},
  "geometry": {"coordinates":[-2.2278690338,53.4346084595],"type":"Point"}
}