{
  "type": "Feature",
  "properties": {
    "addr:full":"Passwood House, Redmire Leyburn North Yorkshire DL8 4ED",
    "addr:postcode":"dl8 4ed",
    "iso:country":"GB",
    "sg:address":"Passwood House, Redmire",
    "sg:city":"Leyburn",
    "sg:classifiers":[
        {
            "category":"Building & Trades",
            "subcategory":"Plumbing",
            "type":"Services"
        }
    ],
    "sg:phone":"+44 1969 623316",
    "sg:postcode":"DL8 4ED",
    "sg:province":"North Yorkshire",
    "sg:tags":[
        "heating"
    ],
    "wof:name":"Frank Shields & Sons",
    "wof:placetype":"venue"
},
  "geometry": {"coordinates":[-1.830434,54.310139],"type":"Point"}
}