{
  "type": "Feature",
  "properties": {
    "iso:country":"GB",
    "sg:address":"5 Turney Grove",
    "sg:city":"Stafford",
    "sg:classifiers":[
        {
            "category":"Building & Trades",
            "subcategory":"Plumbing",
            "type":"Services"
        }
    ],
    "sg:phone":"+44 1785 258591",
    "sg:postcode":"ST17 9XY",
    "sg:province":"Staffordshire",
    "sg:tags":[
        "heating"
    ],
    "wof:name":"A.R Wiggin",
    "wof:placetype":"venue"
},
  "geometry": {"coordinates":[-2.128667,52.792522],"type":"Point"}
}