{
  "type": "Feature",
  "properties": {
    "addr:full":"50 Edinburgh Gardens Braintree Essex CM7 9LH",
    "addr:housenumber":"50",
    "addr:postcode":"cm7 9lh",
    "addr:street":"Edinburgh Gardens",
    "iso:country":"GB",
    "sg:address":"50 Edinburgh Gardens",
    "sg:city":"Braintree",
    "sg:classifiers":[
        {
            "category":"Building & Trades",
            "subcategory":"Construction",
            "type":"Services"
        }
    ],
    "sg:postcode":"CM7 9LH",
    "sg:province":"Essex",
    "sg:tags":[
        "decorator",
        "painter"
    ],
    "wof:name":"Trevor Gillbanks",
    "wof:placetype":"venue"
},
  "geometry": {"coordinates":[0.5707669854,51.8843917847],"type":"Point"}
}