{
  "type": "Feature",
  "properties": {
    "addr:full":"272 Shobnall Road Burton-on-trent Derbyshire DE14 2BE",
    "addr:housenumber":"272",
    "addr:postcode":"de14 2be",
    "addr:street":"Shobnall Road",
    "iso:country":"GB",
    "sg:address":"272 Shobnall Road",
    "sg:city":"Burton-on-trent",
    "sg:classifiers":[
        {
            "category":"Shopping",
            "subcategory":"Computers & Home Electronics",
            "type":"Retail Goods"
        }
    ],
    "sg:postcode":"DE14 2BE",
    "sg:province":"Derbyshire",
    "sg:tags":[
        "equipment",
        "audio-visual"
    ],
    "wof:name":"G B International",
    "wof:placetype":"venue"
},
  "geometry": {"coordinates":[-1.6612759829,52.8086433411],"type":"Point"}
}