{
  "type": "Feature",
  "properties": {
    "addr:full":"Hartle Lane, Belbroughton Stourbridge West Midlands DY9 9TG",
    "addr:postcode":"dy9 9tg",
    "addr:street":"Hartle Lane",
    "iso:country":"GB",
    "sg:address":"Hartle Lane, Belbroughton",
    "sg:city":"Stourbridge",
    "sg:classifiers":[
        {
            "category":"Bars & Pubs",
            "type":"Food & Drink"
        },
        {
            "category":"Community Center",
            "subcategory":"Social",
            "type":"Public Place"
        }
    ],
    "sg:phone":"+44 1562 730249",
    "sg:postcode":"DY9 9TG",
    "sg:province":"West Midlands",
    "sg:tags":[
        "pubs",
        "house",
        "inn",
        "activity"
    ],
    "wof:name":"The Talbot",
    "wof:placetype":"venue"
},
  "geometry": {"coordinates":[-2.1183879375,52.3916511536],"type":"Point"}
}