{
  "type": "Feature",
  "properties": {
    "iso:country":"GB",
    "sg:address":"Unit 9c Southbrook Rd, Millbrook",
    "sg:city":"Southampton",
    "sg:classifiers":[
        {
            "category":"Shopping",
            "subcategory":"Stationery & Office Supplies",
            "type":"Retail Goods"
        }
    ],
    "sg:postcode":"SO15 1GQ",
    "sg:province":"Hampshire",
    "sg:tags":[
        "printers'"
    ],
    "wof:name":"Right Scan",
    "wof:placetype":"venue"
},
  "geometry": {"coordinates":[-1.415619,50.907845],"type":"Point"}
}