{
  "type": "Feature",
  "properties": {
    "iso:country":"GB",
    "sg:address":"80 Craiglockhart Road",
    "sg:city":"Edinburgh",
    "sg:classifiers":[
        {
            "category":"Personal",
            "type":"Services"
        }
    ],
    "sg:postcode":"EH14 1EP",
    "sg:province":"City of Edinburgh",
    "sg:tags":[
        "wedding"
    ],
    "wof:name":"Wedding List Direct",
    "wof:placetype":"venue"
},
  "geometry": {"coordinates":[-3.2425,55.915756],"type":"Point"}
}