{
  "type": "Feature",
  "properties": {
    "addr:full":"Main Road, Great Haywood Stafford Staffordshire ST18 0RT",
    "addr:postcode":"st18 0rt",
    "addr:street":"Main Road",
    "iso:country":"GB",
    "sg:address":"Main Road, Great Haywood",
    "sg:city":"Stafford",
    "sg:classifiers":[
        {
            "category":"Home & Garden",
            "subcategory":"Garden Supply",
            "type":"Retail Goods"
        }
    ],
    "sg:postcode":"ST18 0RT",
    "sg:province":"Staffordshire",
    "sg:tags":[
        "nursery",
        "centre"
    ],
    "wof:name":"Roseacre Nursery",
    "wof:placetype":"venue"
},
  "geometry": {"coordinates":[-2.0001909733,52.8067855835],"type":"Point"}
}