{
  "type": "Feature",
  "properties": {
    "iso:country":"GB",
    "sg:address":"2 Rylands",
    "sg:city":"Prestwick",
    "sg:classifiers":[
        {
            "category":"Retail",
            "subcategory":"Driving School",
            "type":"Services"
        }
    ],
    "sg:postcode":"KA9 2DX",
    "sg:province":"South Ayrshire",
    "wof:name":"Mark Harford",
    "wof:placetype":"venue"
},
  "geometry": {"coordinates":[-4.6066360474,55.4909095764],"type":"Point"}
}