{
  "type": "Feature",
  "properties": {
    "iso:country":"GB",
    "sg:address":"30 Beveridge Way",
    "sg:city":"Newton Aycliffe",
    "sg:classifiers":[
        {
            "category":"Shopping",
            "subcategory":"Department Store",
            "type":"Retail Goods"
        }
    ],
    "sg:phone":"+44 1325 312936",
    "sg:postcode":"DL5 4DR",
    "sg:province":"Durham",
    "sg:tags":[
        "departmental"
    ],
    "wof:name":"Woolworths Plc",
    "wof:placetype":"venue"
},
  "geometry": {"coordinates":[-1.571474,54.619186],"type":"Point"}
}