{
  "type": "Feature",
  "properties": {
    "iso:country":"GB",
    "sg:address":"G5 Ground Floor Victoria Gardens",
    "sg:city":"Harrogate",
    "sg:classifiers":[
        {
            "category":"Shopping",
            "subcategory":"Clothing, Apparel, & Fashions",
            "type":"Retail Goods"
        }
    ],
    "sg:postcode":"HG1 1AE",
    "sg:province":"North Yorkshire",
    "sg:tags":[
        "accessory"
    ],
    "wof:name":"Miss Attitude (Trading) Ltd.",
    "wof:placetype":"venue"
},
  "geometry": {"coordinates":[-1.544524,53.99469],"type":"Point"}
}