{
  "type": "Feature",
  "properties": {
    "addr:full":"Shenley Church End Local Centre Milton Keynes Buckinghamshire MK5 6JG",
    "addr:housenumber":"local",
    "addr:postcode":"mk5 6jg",
    "addr:street":"Shenley Church End;Centre",
    "iso:country":"GB",
    "sg:address":"Shenley Church End Local Centre",
    "sg:city":"Milton Keynes",
    "sg:classifiers":[
        {
            "category":"Shopping",
            "subcategory":"Pharmacy",
            "type":"Retail Goods"
        }
    ],
    "sg:postcode":"MK5 6JG",
    "sg:province":"Buckinghamshire",
    "sg:tags":[
        "pharmacist",
        "chemist"
    ],
    "wof:name":"Jardines Late Night Chemist",
    "wof:placetype":"venue"
},
  "geometry": {"coordinates":[-0.797313,52.021435],"type":"Point"}
}