{
  "type": "Feature",
  "properties": {
    "iso:country":"GB",
    "sg:address":"27 Halford Street",
    "sg:city":"Leicester",
    "sg:classifiers":[
        {
            "category":"Shopping",
            "subcategory":"Optician",
            "type":"Retail Goods"
        }
    ],
    "sg:phone":"+44 116 253 6727",
    "sg:postcode":"LE1 1JA",
    "sg:province":"Leicestershire",
    "sg:tags":[
        "opthalmic"
    ],
    "wof:name":"Dollond & Aitchison",
    "wof:placetype":"venue"
},
  "geometry": {"coordinates":[-1.129904,52.634674],"type":"Point"}
}