{
  "type": "Feature",
  "properties": {
    "addr:full":"43 Dukes Rd, Lower Weston Totnes Devon TQ9 5YA",
    "addr:housenumber":"43",
    "addr:postcode":"tq9 5ya",
    "addr:street":"Dukes Rd",
    "iso:country":"GB",
    "sg:address":"43 Dukes Rd, Lower Weston",
    "sg:city":"Totnes",
    "sg:classifiers":[
        {
            "category":"Retail",
            "subcategory":"Driving School",
            "type":"Services"
        }
    ],
    "sg:phone":"+44 1803 865337",
    "sg:postcode":"TQ9 5YA",
    "sg:province":"Devon",
    "wof:name":"Joe Beard",
    "wof:placetype":"venue"
},
  "geometry": {"coordinates":[-3.6677598953,50.4285392761],"type":"Point"}
}