{
  "type": "Feature",
  "properties": {
    "addr:full":"8 The Parade Cwmbran Monmouthshire NP44 1PT",
    "addr:housenumber":"8",
    "addr:postcode":"np44 1pt",
    "addr:street":"The Parade",
    "iso:country":"GB",
    "sg:address":"8 The Parade",
    "sg:city":"Cwmbran",
    "sg:classifiers":[
        {
            "category":"Real Estate",
            "subcategory":"Real Estate Agent",
            "type":"Services"
        }
    ],
    "sg:phone":"+44 1633 872717",
    "sg:postcode":"NP44 1PT",
    "sg:province":"Monmouthshire",
    "wof:name":"Halifax Property Services",
    "wof:placetype":"venue"
},
  "geometry": {"coordinates":[-3.037635088,51.6619224548],"type":"Point"}
}