{
  "type": "Feature",
  "properties": {
    "iso:country":"GB",
    "sg:address":"Unit A, The Old Brewery Yard, Middle Street",
    "sg:city":"Taunton",
    "sg:classifiers":[
        {
            "category":"Professional",
            "subcategory":"Detective & Security Services",
            "type":"Services"
        }
    ],
    "sg:phone":"+44 1823 350070",
    "sg:postcode":"TA1 1SH",
    "sg:province":"Somerset",
    "wof:name":"Pro-Guard Southwest Security Ltd.",
    "wof:placetype":"venue"
},
  "geometry": {"coordinates":[-3.1106989384,51.0104904175],"type":"Point"}
}