{
  "type": "Feature",
  "properties": {
    "addr:full":"26 North Street Ashford Kent TN24 8JR",
    "addr:housenumber":"26",
    "addr:postcode":"tn24 8jr",
    "addr:street":"North Street",
    "iso:country":"GB",
    "sg:address":"26 North Street",
    "sg:city":"Ashford",
    "sg:classifiers":[
        {
            "category":"Professional",
            "subcategory":"Lawyer & Legal Services",
            "type":"Services"
        }
    ],
    "sg:phone":"+44 1233 624545",
    "sg:postcode":"TN24 8JR",
    "sg:province":"Kent",
    "sg:tags":[
        "solicitor"
    ],
    "wof:name":"Colin Hayward & Co",
    "wof:placetype":"venue"
},
  "geometry": {"coordinates":[0.8734149933,51.1496276855],"type":"Point"}
}