{
  "type": "Feature",
  "properties": {
    "iso:country":"GB",
    "sg:address":"31 Shifford Path, Perry Vale",
    "sg:city":"Forest Hill",
    "sg:classifiers":[
        {
            "category":"Home & Garden",
            "subcategory":"Hardware",
            "type":"Retail Goods"
        }
    ],
    "sg:phone":"+44 20 8699 1534",
    "sg:postcode":"SE23 2XE",
    "sg:province":"Greater London",
    "sg:tags":[
        "equipment",
        "heating"
    ],
    "wof:name":"C&d Plumbing Heating",
    "wof:placetype":"venue"
},
  "geometry": {"coordinates":[-0.045269,51.433456],"type":"Point"}
}