{
  "type": "Feature",
  "properties": {
    "addr:full":"Stone Acre, School Lane, Ripple Tewkesbury Gloucestershire GL20 6EU",
    "addr:postcode":"gl20 6eu",
    "addr:street":"Stone;School Lane",
    "iso:country":"GB",
    "sg:address":"Stone Acre, School Lane, Ripple",
    "sg:city":"Tewkesbury",
    "sg:classifiers":[
        {
            "category":"Retail",
            "subcategory":"Veterinary Services",
            "type":"Services"
        }
    ],
    "sg:phone":"+44 1684 592333",
    "sg:postcode":"GL20 6EU",
    "sg:province":"Gloucestershire",
    "sg:tags":[
        "surgeon"
    ],
    "wof:name":"Chase Veterinary Clinic",
    "wof:placetype":"venue"
},
  "geometry": {"coordinates":[-2.1857800484,52.0382003784],"type":"Point"}
}