{
  "type": "Feature",
  "properties": {
    "addr:full":"210 Broadway Bexleyheath Kent DA6 7BD",
    "addr:housenumber":"210",
    "addr:postcode":"da6 7bd",
    "addr:street":"Broadway",
    "iso:country":"GB",
    "sg:address":"210 Broadway",
    "sg:city":"Bexleyheath",
    "sg:classifiers":[
        {
            "category":"Banks & Credit Unions",
            "subcategory":"Bank",
            "type":"Services"
        }
    ],
    "sg:phone":"+44 20 8304 0555",
    "sg:postcode":"DA6 7BD",
    "sg:province":"Kent",
    "wof:name":"Cash-A-Cheque (G B) Ltd.",
    "wof:placetype":"venue"
},
  "geometry": {"coordinates":[0.1391550004,51.4575042725],"type":"Point"}
}