{
  "type": "Feature",
  "properties": {
    "iso:country":"GB",
    "sg:address":"Redhouse Industrial Estate, Shieldhill Road",
    "sg:city":"Falkirk",
    "sg:classifiers":[
        {
            "category":"Personal",
            "subcategory":"Beauty Salon",
            "type":"Services"
        }
    ],
    "sg:postcode":"FK2 0DT",
    "sg:province":"Falkirk",
    "sg:tags":[
        "unisex",
        "hairdresser"
    ],
    "wof:name":"Principals",
    "wof:placetype":"venue"
},
  "geometry": {"coordinates":[-3.74174,55.980289],"type":"Point"}
}