{
  "type": "Feature",
  "properties": {
    "addr:full":"Unit 3b-3d Shrub Hill Indstl Est Worcester Worcestershire WR4 9EL",
    "addr:postcode":"wr4 9el",
    "addr:street":"Shrub Hill Indstl Est",
    "iso:country":"GB",
    "sg:address":"Unit 3b-3d Shrub Hill Indstl Est",
    "sg:city":"Worcester",
    "sg:classifiers":[
        {
            "category":"Utilities",
            "subcategory":"Telephone",
            "type":"Services"
        },
        {
            "category":"Professional",
            "subcategory":"Computer Services",
            "type":"Services"
        }
    ],
    "sg:phone":"+44 1905 616239",
    "sg:postcode":"WR4 9EL",
    "sg:province":"Worcestershire",
    "sg:tags":[
        "software",
        "system",
        "telecommunication"
    ],
    "wof:name":"Globelink Systems Ltd",
    "wof:placetype":"venue"
},
  "geometry": {"coordinates":[-2.210565,52.194458],"type":"Point"}
}