{
  "type": "Feature",
  "properties": {
    "addr:full":"42 Northgate Peebles Scottish Borders EH45 8BZ",
    "addr:housenumber":"42",
    "addr:postcode":"eh45 8bz",
    "addr:street":"Northgate",
    "iso:country":"GB",
    "sg:address":"42 Northgate",
    "sg:city":"Peebles",
    "sg:classifiers":[
        {
            "category":"Building & Trades",
            "subcategory":"Construction",
            "type":"Services"
        }
    ],
    "sg:phone":"+44 1721 720724",
    "sg:postcode":"EH45 8BZ",
    "sg:province":"Scottish Borders",
    "sg:tags":[
        "decorator",
        "painter"
    ],
    "wof:name":"J Mackison & Son",
    "wof:placetype":"venue"
},
  "geometry": {"coordinates":[-3.188822,55.653706],"type":"Point"}
}