{
  "type": "Feature",
  "properties": {
    "iso:country":"GB",
    "sg:address":"Ince Clinic & Community Centre, Manchester Road, Ince",
    "sg:city":"Wigan",
    "sg:classifiers":[
        {
            "category":"Health Services",
            "subcategory":"Clinic",
            "type":"Services"
        }
    ],
    "sg:phone":"+44 1942 204735",
    "sg:postcode":"WN2 2DJ",
    "sg:province":"Lancashire",
    "sg:tags":[
        "nh"
    ],
    "wof:name":"Ince Community Resource Centre",
    "wof:placetype":"venue"
},
  "geometry": {"coordinates":[-2.60395,53.543331],"type":"Point"}
}