{
  "type": "Feature",
  "properties": {
    "addr:full":"Tollgate Lane Bury St Edmunds Suffolk IP32 6DG",
    "addr:postcode":"ip32 6dg",
    "addr:street":"Tollgate Lane",
    "iso:country":"GB",
    "sg:address":"Tollgate Lane",
    "sg:city":"Bury St Edmunds",
    "sg:classifiers":[
        {
            "category":"Education",
            "subcategory":"School",
            "type":"Public Place"
        }
    ],
    "sg:postcode":"IP32 6DG",
    "sg:province":"Suffolk",
    "sg:tags":[
        "local",
        "authority"
    ],
    "wof:name":"Tollgate Primary School",
    "wof:placetype":"venue"
},
  "geometry": {"coordinates":[0.7101,52.260365],"type":"Point"}
}