{
  "type": "Feature",
  "properties": {
    "addr:full":"Eastfield, Belmont St Halifax West Yorkshire HX3 6AT",
    "addr:postcode":"hx3 6at",
    "addr:street":"Eastfield Belmont St",
    "iso:country":"GB",
    "sg:address":"Eastfield, Belmont St",
    "sg:city":"Halifax",
    "sg:classifiers":[
        {
            "category":"Autos & Motor Vehicles",
            "subcategory":"Automobile Sales",
            "type":"Retail Goods"
        }
    ],
    "sg:phone":"+44 1422 344166",
    "sg:postcode":"HX3 6AT",
    "sg:province":"West Yorkshire",
    "sg:tags":[
        "car"
    ],
    "wof:name":"Calderdale Accident Repair Centre",
    "wof:placetype":"venue"
},
  "geometry": {"coordinates":[-1.84761,53.728809],"type":"Point"}
}