{
  "type": "Feature",
  "properties": {
    "addr:full":"33 Merthyr Road, Whitchurch Cardiff Cardiff CF14 1DB",
    "addr:housenumber":"33",
    "addr:postcode":"cf14 1db",
    "addr:street":"Merthyr Road",
    "iso:country":"GB",
    "sg:address":"33 Merthyr Road, Whitchurch",
    "sg:city":"Cardiff",
    "sg:classifiers":[
        {
            "category":"Food & Beverages",
            "subcategory":"Meat & Fish",
            "type":"Retail Goods"
        },
        {
            "category":"Food & Beverages",
            "subcategory":"Groceries & Convenience Stores",
            "type":"Retail Goods"
        }
    ],
    "sg:phone":"+44 29 2061 8693",
    "sg:postcode":"CF14 1DB",
    "sg:province":"Cardiff",
    "sg:tags":[
        "shop",
        "chip"
    ],
    "wof:name":"TOP GUN FISH BAR",
    "wof:placetype":"venue"
},
  "geometry": {"coordinates":[-3.2190840244,51.5125579834],"type":"Point"}
}