{
  "type": "Feature",
  "properties": {
    "addr:full":"Riverside Cottage, Millhall Road, Eaglesham Glasgow East Renfrewshire G76 0PD",
    "addr:postcode":"g76 0pd",
    "addr:street":"Millhall Road",
    "iso:country":"GB",
    "sg:address":"Riverside Cottage, Millhall Road, Eaglesham",
    "sg:city":"Glasgow",
    "sg:classifiers":[
        {
            "category":"Professional",
            "subcategory":"Computer Services",
            "type":"Services"
        }
    ],
    "sg:phone":"+44 1355 301050",
    "sg:postcode":"G76 0PD",
    "sg:province":"East Renfrewshire",
    "sg:tags":[
        "system",
        "software"
    ],
    "wof:name":"5 S Ltd.",
    "wof:placetype":"venue"
},
  "geometry": {"coordinates":[-4.276189,55.759369],"type":"Point"}
}