{
  "type": "Feature",
  "properties": {
    "addr:full":"5 Market Place, Kegworth Derby Leicestershire DE74 2EE",
    "addr:housenumber":"5",
    "addr:postcode":"de74 2ee",
    "addr:street":"Market Place",
    "iso:country":"GB",
    "sg:address":"5 Market Place, Kegworth",
    "sg:city":"Derby",
    "sg:classifiers":[
        {
            "category":"Insurance",
            "subcategory":"Insurance Agent",
            "type":"Services"
        }
    ],
    "sg:phone":"+44 1509 673900",
    "sg:postcode":"DE74 2EE",
    "sg:province":"Leicestershire",
    "sg:tags":[
        "broker"
    ],
    "wof:name":"BENSONS",
    "wof:placetype":"venue"
},
  "geometry": {"coordinates":[-1.2781840563,52.8353767395],"type":"Point"}
}