{
  "type": "Feature",
  "properties": {
    "iso:country":"GB",
    "sg:address":"Ravenstruthers Plant",
    "sg:city":"Lanark",
    "sg:classifiers":[
        {
            "category":"Mining & Drilling",
            "type":"Manufacturing & Wholesale Goods"
        }
    ],
    "sg:phone":"+44 1555 870998",
    "sg:postcode":"ML11 8NN",
    "sg:province":"South Lanarkshire",
    "sg:tags":[
        "coal"
    ],
    "wof:name":"The Scottish Coal Co. Ltd.",
    "wof:placetype":"venue"
},
  "geometry": {"coordinates":[-3.631189,55.700539],"type":"Point"}
}