{
  "type": "Feature",
  "properties": {
    "addr:full":"Albany House, 31 Hurst Street Birmingham West Midlands B5 4BD",
    "addr:housenumber":"31",
    "addr:postcode":"b5 4bd",
    "addr:street":"Hurst Street",
    "iso:country":"GB",
    "sg:address":"Albany House, 31 Hurst Street",
    "sg:city":"Birmingham",
    "sg:classifiers":[
        {
            "category":"Building & Trades",
            "subcategory":"Construction",
            "type":"Services"
        }
    ],
    "sg:phone":"+44 121 622 4811",
    "sg:postcode":"B5 4BD",
    "sg:province":"West Midlands",
    "sg:tags":[
        "restoration",
        "refurbishment"
    ],
    "wof:name":"City Office Interiors Ltd.",
    "wof:placetype":"venue"
},
  "geometry": {"coordinates":[-1.8974889517,52.4748001099],"type":"Point"}
}