{
  "type": "Feature",
  "properties": {
    "addr:full":"110 Station Road Accrington Lancashire BB5 6LS",
    "addr:housenumber":"110",
    "addr:postcode":"bb5 6ls",
    "addr:street":"Station Road",
    "iso:country":"GB",
    "sg:address":"110 Station Road",
    "sg:city":"Accrington",
    "sg:classifiers":[
        {
            "category":"Building & Trades",
            "subcategory":"Plumbing",
            "type":"Services"
        }
    ],
    "sg:phone":"+44 1254 871420",
    "sg:postcode":"BB5 6LS",
    "sg:province":"Lancashire",
    "sg:tags":[
        "plumber",
        "heating"
    ],
    "wof:name":"M Alldritt Plumbing and Heating",
    "wof:placetype":"venue"
},
  "geometry": {"coordinates":[-2.3422451019,53.7740859985],"type":"Point"}
}