{
  "type": "Feature",
  "properties": {
    "addr:full":"Kings Pyon House, Kings Pyon Hereford Herefordshire HR4 8PZ",
    "addr:postcode":"hr4 8pz",
    "addr:street":"Kings Pyon",
    "iso:country":"GB",
    "sg:address":"Kings Pyon House, Kings Pyon",
    "sg:city":"Hereford",
    "sg:classifiers":[
        {
            "category":"Professional",
            "subcategory":"Employment Agencies",
            "type":"Services"
        }
    ],
    "sg:phone":"+44 1432 830915",
    "sg:postcode":"HR4 8PZ",
    "sg:province":"Herefordshire",
    "sg:tags":[
        "agricultural",
        "advice"
    ],
    "wof:name":"Powell & Oliver Agricultural Consultants",
    "wof:placetype":"venue"
},
  "geometry": {"coordinates":[-2.8222570419,52.1508331299],"type":"Point"}
}