{
  "type": "Feature",
  "properties": {
    "addr:full":"111 Piccadilly Manchester Greater Manchester M1 2HY",
    "addr:housenumber":"111",
    "addr:postcode":"m1 2hy",
    "addr:street":"Piccadilly",
    "iso:country":"GB",
    "sg:address":"111 Piccadilly",
    "sg:city":"Manchester",
    "sg:classifiers":[
        {
            "category":"Professional",
            "subcategory":"Computer Services",
            "type":"Services"
        }
    ],
    "sg:phone":"+44 161 236 9261",
    "sg:postcode":"M1 2HY",
    "sg:province":"Greater Manchester",
    "sg:tags":[
        "information"
    ],
    "wof:name":"Comites",
    "wof:placetype":"venue"
},
  "geometry": {"coordinates":[-2.232835,53.479408],"type":"Point"}
}