{
  "type": "Feature",
  "properties": {
    "iso:country":"GB",
    "sg:address":"5 St James Place, Threemilldown",
    "sg:city":"Linlithgow",
    "sg:classifiers":[
        {
            "category":"Professional",
            "subcategory":"Engineering",
            "type":"Services"
        }
    ],
    "sg:phone":"+44 1506 834707",
    "sg:postcode":"EH49 6NE",
    "sg:province":"Falkirk",
    "sg:tags":[
        "contractor",
        "electrical",
        "engineer"
    ],
    "wof:name":"Brian Mcneill",
    "wof:placetype":"venue"
},
  "geometry": {"coordinates":[-3.602564,55.97657],"type":"Point"}
}