{
  "type": "Feature",
  "properties": {
    "addr:full":"7 Smith St Stoke On Trent Staffordshire ST3 1DR",
    "addr:housenumber":"7",
    "addr:postcode":"st3 1dr",
    "addr:street":"Smith St",
    "iso:country":"GB",
    "sg:address":"7 Smith St",
    "sg:city":"Stoke On Trent",
    "sg:classifiers":[
        {
            "category":"Professional",
            "subcategory":"Detective & Security Services",
            "type":"Services"
        }
    ],
    "sg:phone":"+44 1782 314314",
    "sg:postcode":"ST3 1DR",
    "sg:province":"Staffordshire",
    "sg:tags":[
        "alarm",
        "burglar",
        "system"
    ],
    "wof:name":"D B Electrics",
    "wof:placetype":"venue"
},
  "geometry": {"coordinates":[-2.1333060265,52.9928970337],"type":"Point"}
}