{
  "type": "Feature",
  "properties": {
    "iso:country":"GB",
    "sg:address":"Wolverhampton Road, Heath Town",
    "sg:city":"Wolverhampton",
    "sg:classifiers":[
        {
            "category":"Retail",
            "subcategory":"Auto Repair",
            "type":"Services"
        }
    ],
    "sg:phone":"+44 1902 863300",
    "sg:postcode":"WV10 0QF",
    "sg:province":"Staffordshire",
    "sg:tags":[
        "modification",
        "garage"
    ],
    "wof:name":"Whitehouse Motor Co.",
    "wof:placetype":"venue"
},
  "geometry": {"coordinates":[-2.102082,52.595856],"type":"Point"}
}