{
  "type": "Feature",
  "properties": {
    "iso:country":"GB",
    "sg:address":"Blakes Lane, Hare Hatch",
    "sg:city":"Reading",
    "sg:classifiers":[
        {
            "category":"Bars & Pubs",
            "type":"Food & Drink"
        },
        {
            "category":"Community Center",
            "subcategory":"Social",
            "type":"Public Place"
        }
    ],
    "sg:phone":"+44 118 940 2477",
    "sg:postcode":"RG10 9TA",
    "sg:province":"Berkshire",
    "sg:tags":[
        "pubs",
        "house",
        "inn",
        "activity"
    ],
    "wof:name":"The Queen Victoria",
    "wof:placetype":"venue"
},
  "geometry": {"coordinates":[-0.8418070078,51.5009841919],"type":"Point"}
}