{
  "type": "Feature",
  "properties": {
    "addr:full":"Holly Gro, Chadderton Oldham Lancashire OL9 0DX",
    "addr:postcode":"ol9 0dx",
    "addr:street":"Gro",
    "iso:country":"GB",
    "sg:address":"Holly Gro, Chadderton",
    "sg:city":"Oldham",
    "sg:classifiers":[
        {
            "category":"Education",
            "subcategory":"School",
            "type":"Public Place"
        }
    ],
    "sg:phone":"+44 161 620 8121",
    "sg:postcode":"OL9 0DX",
    "sg:province":"Lancashire",
    "sg:tags":[
        "local",
        "authority"
    ],
    "wof:name":"Bare Trees Junior School",
    "wof:placetype":"venue"
},
  "geometry": {"coordinates":[-2.1556990147,53.5546340942],"type":"Point"}
}