{
  "type": "Feature",
  "properties": {
    "addr:full":"4a Oxford Street Ripley Derbyshire DE5 3AB",
    "addr:housenumber":"4a",
    "addr:postcode":"de5 3ab",
    "addr:street":"Oxford Street",
    "iso:country":"GB",
    "sg:address":"4a Oxford Street",
    "sg:city":"Ripley",
    "sg:classifiers":[
        {
            "category":"Health Services",
            "subcategory":"Optometrist",
            "type":"Services"
        },
        {
            "category":"Shopping",
            "subcategory":"Optical Goods",
            "type":"Retail Goods"
        },
        {
            "category":"Professional",
            "subcategory":"Business Services",
            "type":"Services"
        }
    ],
    "sg:postcode":"DE5 3AB",
    "sg:province":"Derbyshire",
    "sg:tags":[
        "import",
        "export",
        "optician",
        "agent"
    ],
    "wof:name":"Hurst Opticians",
    "wof:placetype":"venue"
},
  "geometry": {"coordinates":[-1.4067510366,53.0496482849],"type":"Point"}
}