{
  "type": "Feature",
  "properties": {
    "iso:country":"GB",
    "sg:address":"Hayston Park",
    "sg:city":"St. Andrews",
    "sg:classifiers":[
        {
            "category":"Education",
            "subcategory":"School",
            "type":"Public Place"
        }
    ],
    "sg:phone":"+44 1334 870304",
    "sg:postcode":"KY16 0DH",
    "sg:province":"Fife",
    "sg:tags":[
        "local",
        "authority"
    ],
    "wof:name":"Balmullo Primary School",
    "wof:placetype":"venue"
},
  "geometry": {"coordinates":[-2.926377058,56.3791999817],"type":"Point"}
}