{
  "type": "Feature",
  "properties": {
    "addr:full":"Britannia House, 1-11 Glenthorne Road, Hammersmith London Greater London W6 0LH",
    "addr:housenumber":"1-11",
    "addr:postcode":"w6 0lh",
    "addr:street":"Glenthorne Road",
    "iso:country":"GB",
    "sg:address":"Britannia House, 1-11 Glenthorne Road, Hammersmith",
    "sg:city":"London",
    "sg:classifiers":[
        {
            "category":"Professional",
            "subcategory":"Business Services",
            "type":"Services"
        }
    ],
    "sg:phone":"+44 870 244 4422",
    "sg:postcode":"W6 0LH",
    "sg:province":"Greater London",
    "sg:tags":[
        "answering"
    ],
    "wof:name":"Cheers International Ltd.",
    "wof:placetype":"venue"
},
  "geometry": {"coordinates":[-0.22681,51.494331],"type":"Point"}
}