{
  "type": "Feature",
  "properties": {
    "addr:full":"The Old Station, Station Road, Three Cocks Brecon Powys LD3 0SD",
    "addr:postcode":"ld3 0sd",
    "addr:street":"Station Road Three Cocks",
    "iso:country":"GB",
    "sg:address":"The Old Station, Station Road, Three Cocks",
    "sg:city":"Brecon",
    "sg:classifiers":[
        {
            "category":"Retail",
            "subcategory":"Repair Shop",
            "type":"Services"
        },
        {
            "category":"Wholesale",
            "subcategory":"Machinery & Supplies",
            "type":"Manufacturing & Wholesale Goods"
        },
        {
            "category":"Farming",
            "subcategory":"Farm",
            "type":"Manufacturing & Wholesale Goods"
        }
    ],
    "sg:phone":"+44 1497 847623",
    "sg:postcode":"LD3 0SD",
    "sg:province":"Powys",
    "sg:tags":[
        "agricultural",
        "sale"
    ],
    "wof:name":"Rees Agri Equipment",
    "wof:placetype":"venue"
},
  "geometry": {"coordinates":[-3.2732288837,52.0440444946],"type":"Point"}
}