{
  "type": "Feature",
  "properties": {
    "iso:country":"GB",
    "sg:address":"25 Range Road",
    "sg:city":"Manchester",
    "sg:classifiers":[
        {
            "category":"Retail",
            "subcategory":"Funeral Services",
            "type":"Services"
        }
    ],
    "sg:postcode":"M16 8FS",
    "sg:province":"Cheshire",
    "sg:tags":[
        "mnfr",
        "monumental",
        "mason"
    ],
    "wof:name":"Audley Granites",
    "wof:placetype":"venue"
},
  "geometry": {"coordinates":[-2.256424,53.452797],"type":"Point"}
}