{
  "type": "Feature",
  "properties": {
    "addr:full":"Gower Street Bradford West Yorkshire BD5 7JF",
    "addr:postcode":"bd5 7jf",
    "addr:street":"Gower Street",
    "iso:country":"GB",
    "sg:address":"Gower Street",
    "sg:city":"Bradford",
    "sg:classifiers":[
        {
            "category":"Military Area",
            "subcategory":"Coast Guard Base",
            "type":"Public Place"
        }
    ],
    "sg:phone":"+44 1274 390038",
    "sg:postcode":"BD5 7JF",
    "sg:province":"West Yorkshire",
    "sg:tags":[
        "equipment",
        "bar",
        "accessory"
    ],
    "wof:name":"Servaclean Ltd.",
    "wof:placetype":"venue"
},
  "geometry": {"coordinates":[-1.754139,53.78376],"type":"Point"}
}