{
  "type": "Feature",
  "properties": {
    "iso:country":"GB",
    "sg:address":"76 Northolt Road",
    "sg:city":"Harrow",
    "sg:classifiers":[
        {
            "category":"Organizations",
            "subcategory":"Membership Organization",
            "type":"Services"
        }
    ],
    "sg:phone":"+44 20 8422 1222",
    "sg:postcode":"HA2 0DW",
    "sg:province":"Greater London",
    "sg:tags":[
        "club"
    ],
    "wof:name":"South Harrow Royal British Legion",
    "wof:placetype":"venue"
},
  "geometry": {"coordinates":[-0.348546,51.568165],"type":"Point"}
}