{
  "type": "Feature",
  "properties": {
    "addr:full":"Over Lethame Farm Strathaven South Lanarkshire ML10 6RW",
    "addr:postcode":"ml10 6rw",
    "addr:street":"Strathaven",
    "iso:country":"GB",
    "sg:address":"Over Lethame Farm",
    "sg:city":"Strathaven",
    "sg:classifiers":[
        {
            "category":"Banks & Credit Unions",
            "subcategory":"Investment Brokerage",
            "type":"Services"
        }
    ],
    "sg:postcode":"ML10 6RW",
    "sg:province":"South Lanarkshire",
    "sg:tags":[
        "contractor"
    ],
    "wof:name":"Alex S Fleming Agricultural Contractors",
    "wof:placetype":"venue"
},
  "geometry": {"coordinates":[-4.0667939186,55.6769790649],"type":"Point"}
}