{
  "type": "Feature",
  "properties": {
    "addr:full":"The Firs, Bourton Westwood Much Wenlock Shropshire TF13 6QB",
    "addr:postcode":"tf13 6qb",
    "iso:country":"GB",
    "sg:address":"The Firs, Bourton Westwood",
    "sg:city":"Much Wenlock",
    "sg:classifiers":[
        {
            "category":"Farming",
            "subcategory":"Livestock Farm",
            "type":"Manufacturing & Wholesale Goods"
        }
    ],
    "sg:phone":"+44 1952 728299",
    "sg:postcode":"TF13 6QB",
    "sg:province":"Shropshire",
    "sg:tags":[
        "others"
    ],
    "wof:name":"M G Davies",
    "wof:placetype":"venue"
},
  "geometry": {"coordinates":[-2.559925,52.594009],"type":"Point"}
}