{
  "type": "Feature",
  "properties": {
    "iso:country":"GB",
    "sg:address":"120 The Esplanade",
    "sg:city":"Weymouth",
    "sg:classifiers":[
        {
            "category":"Travel",
            "subcategory":"Hotels & Motels",
            "type":"Entertainment"
        }
    ],
    "sg:phone":"+44 1305 785897",
    "sg:postcode":"DT4 7EW",
    "sg:province":"Dorset",
    "sg:tags":[
        "house",
        "guest"
    ],
    "wof:name":"Gresham Hotel",
    "wof:placetype":"venue"
},
  "geometry": {"coordinates":[-2.452486,50.615761],"type":"Point"}
}