{
  "type": "Feature",
  "properties": {
    "addr:full":"117 Cromwell Rd Whitstable Kent CT5 1NJ",
    "addr:housenumber":"117",
    "addr:postcode":"ct5 1nj",
    "addr:street":"Cromwell Rd Whitstable",
    "iso:country":"GB",
    "sg:address":"117 Cromwell Rd",
    "sg:city":"Whitstable",
    "sg:classifiers":[
        {
            "category":"Wholesale",
            "subcategory":"Scrap",
            "type":"Manufacturing & Wholesale Goods"
        }
    ],
    "sg:phone":"+44 1227 275171",
    "sg:postcode":"CT5 1NJ",
    "sg:province":"Kent",
    "sg:tags":[
        "car",
        "breaker",
        "dismantlers"
    ],
    "wof:name":"Japanese Car Spares",
    "wof:placetype":"venue"
},
  "geometry": {"coordinates":[1.029994,51.35714],"type":"Point"}
}