{
  "type": "Feature",
  "properties": {
    "iso:country":"GB",
    "sg:address":"32 South View, Downley",
    "sg:city":"High Wycombe",
    "sg:classifiers":[
        {
            "category":"Community Center",
            "subcategory":"Youth",
            "type":"Public Place"
        }
    ],
    "sg:postcode":"HP13 5UL",
    "sg:province":"Buckinghamshire",
    "sg:tags":[
        "children's",
        "activity"
    ],
    "wof:name":"Tumble Tots",
    "wof:placetype":"venue"
},
  "geometry": {"coordinates":[-0.778495,51.644093],"type":"Point"}
}