{
  "type": "Feature",
  "properties": {
    "iso:country":"GB",
    "sg:address":"28 Market Pl",
    "sg:city":"Wetherby",
    "sg:classifiers":[
        {
            "category":"Shopping",
            "subcategory":"Clothing, Apparel, & Fashions",
            "type":"Retail Goods"
        }
    ],
    "sg:phone":"+44 1937 584567",
    "sg:postcode":"LS22 6NE",
    "sg:province":"North Yorkshire",
    "sg:tags":[
        "menswear"
    ],
    "wof:name":"Mans Wardrobe The",
    "wof:placetype":"venue"
},
  "geometry": {"coordinates":[-1.386696,53.928059],"type":"Point"}
}