{
  "type": "Feature",
  "properties": {
    "iso:country":"GB",
    "sg:address":"Copers Cope Rd",
    "sg:city":"Beckenham",
    "sg:classifiers":[
        {
            "category":"Arena",
            "subcategory":"Sports Club",
            "type":"Entertainment"
        }
    ],
    "sg:postcode":"BR3 1NZ",
    "sg:province":"Kent",
    "sg:tags":[
        "ground"
    ],
    "wof:name":"National Westminster Bank Sports & Recre",
    "wof:placetype":"venue"
},
  "geometry": {"coordinates":[-0.0282039996,51.4216690063],"type":"Point"}
}