{
  "type": "Feature",
  "properties": {
    "addr:full":"139 Yorkshire Street Oldham Lancashire OL1 3TH",
    "addr:housenumber":"139",
    "addr:postcode":"ol1 3th",
    "addr:street":"Yorkshire Street",
    "iso:country":"GB",
    "sg:address":"139 Yorkshire Street",
    "sg:city":"Oldham",
    "sg:classifiers":[
        {
            "category":"Fast Food",
            "type":"Food & Drink"
        },
        {
            "category":"Food & Beverages",
            "subcategory":"Meat & Fish",
            "type":"Retail Goods"
        }
    ],
    "sg:postcode":"OL1 3TH",
    "sg:province":"Lancashire",
    "sg:tags":[
        "outlet",
        "chip",
        "meal",
        "away",
        "take"
    ],
    "wof:name":"WICK'S TAKE AWAY",
    "wof:placetype":"venue"
},
  "geometry": {"coordinates":[-2.1054110527,53.5422744751],"type":"Point"}
}