{
  "type": "Feature",
  "properties": {
    "addr:full":"Cardiff Rd Treharris Caerphilly CF46 5EY",
    "addr:postcode":"cf46 5ey",
    "addr:street":"Cardiff Rd",
    "iso:country":"GB",
    "sg:address":"Cardiff Rd",
    "sg:city":"Treharris",
    "sg:classifiers":[
        {
            "category":"Autos & Motor Vehicles",
            "subcategory":"Fuel & Gas Station",
            "type":"Retail Goods"
        }
    ],
    "sg:phone":"+44 1443 410331",
    "sg:postcode":"CF46 5EY",
    "sg:province":"Caerphilly",
    "sg:tags":[
        "petrol",
        "filling"
    ],
    "wof:name":"Memonoo Ltd",
    "wof:placetype":"venue"
},
  "geometry": {"coordinates":[-3.3118150234,51.6571998596],"type":"Point"}
}