{
  "type": "Feature",
  "properties": {
    "addr:full":"31 Goresbrook Road Dagenham Essex RM9 6UX",
    "addr:housenumber":"31",
    "addr:postcode":"rm9 6ux",
    "addr:street":"Goresbrook Road",
    "iso:country":"GB",
    "sg:address":"31 Goresbrook Road",
    "sg:city":"Dagenham",
    "sg:classifiers":[
        {
            "category":"Fast Food",
            "type":"Food & Drink"
        }
    ],
    "sg:phone":"+44 20 8517 1832",
    "sg:postcode":"RM9 6UX",
    "sg:province":"Essex",
    "sg:tags":[
        "away",
        "meal",
        "outlet",
        "take"
    ],
    "wof:name":"Good Friend",
    "wof:placetype":"venue"
},
  "geometry": {"coordinates":[0.1459089965,51.5324859619],"type":"Point"}
}