{
  "type": "Feature",
  "properties": {
    "addr:full":"Denton Hall, Denton Ilkley North Yorkshire LS29 0HH",
    "addr:postcode":"ls29 0hh",
    "iso:country":"GB",
    "sg:address":"Denton Hall, Denton",
    "sg:city":"Ilkley",
    "sg:classifiers":[
        {
            "category":"Professional",
            "subcategory":"Engineering",
            "type":"Services"
        }
    ],
    "sg:phone":"+44 1943 601933",
    "sg:postcode":"LS29 0HH",
    "sg:province":"North Yorkshire",
    "sg:tags":[
        "contractor",
        "electrical",
        "engineer"
    ],
    "wof:name":"The N G Bailey Organisation Ltd.",
    "wof:placetype":"venue"
},
  "geometry": {"coordinates":[-1.783072,53.936768],"type":"Point"}
}