{
  "type": "Feature",
  "properties": {
    "addr:full":"108 Moseley Road Bilston West Midlands WV14 6JF",
    "addr:housenumber":"108",
    "addr:postcode":"wv14 6jf",
    "addr:street":"Moseley Road",
    "iso:country":"GB",
    "sg:address":"108 Moseley Road",
    "sg:city":"Bilston",
    "sg:classifiers":[
        {
            "category":"Fast Food",
            "type":"Food & Drink"
        }
    ],
    "sg:postcode":"WV14 6JF",
    "sg:province":"West Midlands",
    "sg:tags":[
        "away",
        "take"
    ],
    "wof:name":"Lucky House",
    "wof:placetype":"venue"
},
  "geometry": {"coordinates":[-2.0680069923,52.5761566162],"type":"Point"}
}