{
  "type": "Feature",
  "properties": {
    "iso:country":"GB",
    "sg:address":"8 Bank Street",
    "sg:city":"Cromarty",
    "sg:classifiers":[
        {
            "category":"Government",
            "subcategory":"Post Office",
            "type":"Public Place"
        }
    ],
    "sg:phone":"+44 1381 600201",
    "sg:postcode":"IV11 8UY",
    "sg:province":"Highland",
    "wof:name":"Cromarty Post Office",
    "wof:placetype":"venue"
},
  "geometry": {"coordinates":[-4.0352640152,57.6809997559],"type":"Point"}
}