{
  "type": "Feature",
  "properties": {
    "addr:full":"46 Stepney Street Llanelli Carmarthenshire SA15 3TR",
    "addr:housenumber":"46",
    "addr:postcode":"sa15 3tr",
    "addr:street":"Stepney Street",
    "iso:country":"GB",
    "sg:address":"46 Stepney Street",
    "sg:city":"Llanelli",
    "sg:classifiers":[
        {
            "category":"Personal",
            "subcategory":"Beauty Salon",
            "type":"Services"
        }
    ],
    "sg:phone":"+44 1554 770955",
    "sg:postcode":"SA15 3TR",
    "sg:province":"Carmarthenshire",
    "wof:name":"The Beauty Spot",
    "wof:placetype":"venue"
},
  "geometry": {"coordinates":[-4.163073,51.681194],"type":"Point"}
}