{
  "type": "Feature",
  "properties": {
    "addr:full":"10 Denby Hill, Oakworth Keighley North Yorkshire BD22 7QB",
    "addr:housenumber":"10",
    "addr:postcode":"bd22 7qb",
    "addr:street":"Denby Hill",
    "iso:country":"GB",
    "sg:address":"10 Denby Hill, Oakworth",
    "sg:city":"Keighley",
    "sg:classifiers":[
        {
            "category":"Building & Trades",
            "subcategory":"Landscaping Services",
            "type":"Services"
        },
        {
            "category":"Shopping",
            "subcategory":"Florist",
            "type":"Retail Goods"
        }
    ],
    "sg:phone":"+44 1535 646995",
    "sg:postcode":"BD22 7QB",
    "sg:province":"North Yorkshire",
    "sg:tags":[
        "landscape",
        "contractor"
    ],
    "wof:name":"Bronte Country Flowers",
    "wof:placetype":"venue"
},
  "geometry": {"coordinates":[-1.9588069916,53.8431587219],"type":"Point"}
}