{
  "type": "Feature",
  "properties": {
    "iso:country":"GB",
    "sg:address":"5a Hazelgrove Road",
    "sg:city":"Haywards Heath",
    "sg:classifiers":[
        {
            "category":"Utilities",
            "subcategory":"Telephone",
            "type":"Services"
        }
    ],
    "sg:postcode":"RH16 3PH",
    "sg:province":"East Sussex",
    "sg:tags":[
        "telecommunication"
    ],
    "wof:name":"Grahame Bowring",
    "wof:placetype":"venue"
},
  "geometry": {"coordinates":[-0.100826,50.996334],"type":"Point"}
}