{
  "type": "Feature",
  "properties": {
    "iso:country":"GB",
    "sg:address":"Kings Farm, Pebmarsh",
    "sg:city":"Halstead",
    "sg:classifiers":[
        {
            "category":"Structure",
            "subcategory":"Warehouse",
            "type":"Public Place"
        }
    ],
    "sg:phone":"+44 1787 269990",
    "sg:postcode":"CO9 2NY",
    "sg:province":"Essex",
    "wof:name":"Pebmarsh Farmers Ltd.",
    "wof:placetype":"venue"
},
  "geometry": {"coordinates":[0.635825,51.943996],"type":"Point"}
}