{
  "type": "Feature",
  "properties": {
    "iso:country":"GB",
    "sg:address":"3 Ashby Road, Northchurch",
    "sg:city":"Berkhamsted",
    "sg:classifiers":[
        {
            "category":"Building & Trades",
            "subcategory":"Construction",
            "type":"Services"
        }
    ],
    "sg:phone":"+44 1442 874079",
    "sg:postcode":"HP4 2SJ",
    "sg:province":"Bedfordshire",
    "sg:tags":[
        "builder"
    ],
    "wof:name":"Castle Construction",
    "wof:placetype":"venue"
},
  "geometry": {"coordinates":[-0.564559,51.760414],"type":"Point"}
}