{
  "type": "Feature",
  "properties": {
    "addr:full":"Unit 1, North Drive Rotherham South Yorkshire S60 1QF",
    "addr:housenumber":"unit 1",
    "addr:postcode":"s60 1qf",
    "addr:street":"North Drive",
    "iso:country":"GB",
    "sg:address":"Unit 1, North Drive",
    "sg:city":"Rotherham",
    "sg:classifiers":[
        {
            "category":"Wholesale",
            "subcategory":"Scrap",
            "type":"Manufacturing & Wholesale Goods"
        }
    ],
    "sg:phone":"+44 1709 376844",
    "sg:postcode":"S60 1QF",
    "sg:province":"South Yorkshire",
    "sg:tags":[
        "waste",
        "metal"
    ],
    "wof:name":"Tinico Alloys Ltd.",
    "wof:placetype":"venue"
},
  "geometry": {"coordinates":[-1.3603390455,53.4386940002],"type":"Point"}
}