{
  "type": "Feature",
  "properties": {
    "addr:full":"138 Maida Vale London Greater London W9 1QD",
    "addr:housenumber":"138",
    "addr:postcode":"w9 1qd",
    "addr:street":"Maida Vale",
    "iso:country":"GB",
    "sg:address":"138 Maida Vale",
    "sg:city":"London",
    "sg:classifiers":[
        {
            "category":"Building & Trades",
            "subcategory":"Plumbing",
            "type":"Services"
        }
    ],
    "sg:phone":"+44 20 7372 9400",
    "sg:postcode":"W9 1QD",
    "sg:province":"Greater London",
    "sg:tags":[
        "plumber",
        "heating"
    ],
    "wof:name":"1St Action Maintenance Ltd",
    "wof:placetype":"venue"
},
  "geometry": {"coordinates":[-0.188787,51.53474],"type":"Point"}
}