{
  "type": "Feature",
  "properties": {
    "addr:full":"43 Hospital Street Nantwich Cheshire CW5 5RL",
    "addr:housenumber":"43",
    "addr:postcode":"cw5 5rl",
    "addr:street":"Hospital Street",
    "iso:country":"GB",
    "sg:address":"43 Hospital Street",
    "sg:city":"Nantwich",
    "sg:classifiers":[
        {
            "category":"Manufacturing",
            "subcategory":"Tools & Machinery",
            "type":"Manufacturing & Wholesale Goods"
        },
        {
            "category":"Insurance",
            "subcategory":"Insurance Agent",
            "type":"Services"
        }
    ],
    "sg:phone":"+44 1270 620500",
    "sg:postcode":"CW5 5RL",
    "sg:province":"Cheshire",
    "sg:tags":[
        "society",
        "friendly"
    ],
    "wof:name":"Barnett Jones & Cooke Ltd.",
    "wof:placetype":"venue"
},
  "geometry": {"coordinates":[-2.5194470882,53.0662307739],"type":"Point"}
}