{
  "type": "Feature",
  "properties": {
    "addr:full":"1-4 The Globe Centre, Wellfield Road Cardiff Cardiff CF24 3PE",
    "addr:housenumber":"1-4",
    "addr:postcode":"cf24 3pe",
    "addr:street":"The;Wellfield Road",
    "iso:country":"GB",
    "sg:address":"1-4 The Globe Centre, Wellfield Road",
    "sg:city":"Cardiff",
    "sg:classifiers":[
        {
            "category":"Banks & Credit Unions",
            "subcategory":"Bank",
            "type":"Services"
        }
    ],
    "sg:phone":"+44 29 2049 3496",
    "sg:postcode":"CF24 3PE",
    "sg:province":"Cardiff",
    "wof:name":"Lloyds T S B Bank Plc",
    "wof:placetype":"venue"
},
  "geometry": {"coordinates":[-3.1650700569,51.4960289001],"type":"Point"}
}