{
  "type": "Feature",
  "properties": {
    "addr:full":"Mitchell Charlesworth, Chavasse Court Liverpool Merseyside L2 1TA",
    "addr:postcode":"l2 1ta",
    "addr:street":"Chavasse Court",
    "iso:country":"GB",
    "sg:address":"Mitchell Charlesworth, Chavasse Court",
    "sg:city":"Liverpool",
    "sg:classifiers":[
        {
            "category":"Organizations",
            "subcategory":"Membership Organization",
            "type":"Services"
        }
    ],
    "sg:postcode":"L2 1TA",
    "sg:province":"Merseyside",
    "sg:tags":[
        "club"
    ],
    "wof:name":"Discovery Management Ltd",
    "wof:placetype":"venue"
},
  "geometry": {"coordinates":[-2.98883,53.40506],"type":"Point"}
}