{
  "type": "Feature",
  "properties": {
    "iso:country":"GB",
    "sg:address":"41 The Street, West Hougham",
    "sg:city":"Dover",
    "sg:classifiers":[
        {
            "category":"Social Services",
            "subcategory":"Job Training",
            "type":"Services"
        }
    ],
    "sg:phone":"+44 1304 202677",
    "sg:postcode":"CT15 7AZ",
    "sg:province":"Kent",
    "sg:tags":[
        "draughtsman",
        "drawing"
    ],
    "wof:name":"The Design House",
    "wof:placetype":"venue"
},
  "geometry": {"coordinates":[1.1897549629,51.1464500427],"type":"Point"}
}