{
  "type": "Feature",
  "properties": {
    "addr:full":"Rimington Rd, Wombwell Barnsley South Yorkshire S73 8DQ",
    "addr:postcode":"s73 8dq",
    "addr:street":"Rimington Rd;Yorkshire",
    "iso:country":"GB",
    "sg:address":"Rimington Rd, Wombwell",
    "sg:city":"Barnsley",
    "sg:classifiers":[
        {
            "category":"Retail",
            "subcategory":"Auto Repair",
            "type":"Services"
        }
    ],
    "sg:phone":"+44 1226 754006",
    "sg:postcode":"S73 8DQ",
    "sg:province":"South Yorkshire",
    "sg:tags":[
        "modification",
        "garage"
    ],
    "wof:name":"D.& P. Motors",
    "wof:placetype":"venue"
},
  "geometry": {"coordinates":[-1.4018540382,53.5250816345],"type":"Point"}
}