{
  "type": "Feature",
  "properties": {
    "addr:full":"49-51 Gordon Square London Greater London WC1H 0PQ",
    "addr:housenumber":"49-51",
    "addr:postcode":"wc1h 0pq",
    "addr:street":"Gordon Square",
    "iso:country":"GB",
    "sg:address":"49-51 Gordon Square",
    "sg:city":"London",
    "sg:classifiers":[
        {
            "category":"Professional",
            "subcategory":"Employment Agencies",
            "type":"Services"
        }
    ],
    "sg:phone":"+44 20 7554 4500",
    "sg:postcode":"WC1H 0PQ",
    "sg:province":"Greater London",
    "sg:tags":[
        "career",
        "guidance"
    ],
    "wof:name":"University of London Careers Service",
    "wof:placetype":"venue"
},
  "geometry": {"coordinates":[-0.13004,51.524403],"type":"Point"}
}