{
  "type": "Feature",
  "properties": {
    "addr:full":"19 Market Place Wigan Lancashire WN1 1PE",
    "addr:housenumber":"19",
    "addr:postcode":"wn1 1pe",
    "addr:street":"Market Place",
    "iso:country":"GB",
    "sg:address":"19 Market Place",
    "sg:city":"Wigan",
    "sg:classifiers":[
        {
            "category":"Professional",
            "subcategory":"Art Services",
            "type":"Services"
        }
    ],
    "sg:phone":"+44 1942 821121",
    "sg:postcode":"WN1 1PE",
    "sg:province":"Lancashire",
    "sg:tags":[
        "picture",
        "restoration"
    ],
    "wof:name":"Fastframe",
    "wof:placetype":"venue"
},
  "geometry": {"coordinates":[-2.6314721107,53.5463790894],"type":"Point"}
}