{
  "type": "Feature",
  "properties": {
    "addr:full":"224 Cannock Rd Cannock Staffordshire WS12 5HF",
    "addr:housenumber":"224",
    "addr:postcode":"ws12 5hf",
    "addr:street":"Cannock Rd",
    "iso:country":"GB",
    "sg:address":"224 Cannock Rd",
    "sg:city":"Cannock",
    "sg:classifiers":[
        {
            "category":"Home & Garden",
            "subcategory":"Home Furnishings",
            "type":"Retail Goods"
        }
    ],
    "sg:phone":"+44 1543 275852",
    "sg:postcode":"WS12 5HF",
    "sg:province":"Staffordshire",
    "sg:tags":[
        "blind",
        "curtain",
        "fitting"
    ],
    "wof:name":"Fancy Draws",
    "wof:placetype":"venue"
},
  "geometry": {"coordinates":[-1.9869639874,52.687953949],"type":"Point"}
}