{
  "type": "Feature",
  "properties": {
    "addr:full":"81 Offington Lane Worthing West Sussex BN14 9RJ",
    "addr:housenumber":"81",
    "addr:postcode":"bn14 9rj",
    "addr:street":"Offington Lane",
    "iso:country":"GB",
    "sg:address":"81 Offington Lane",
    "sg:city":"Worthing",
    "sg:classifiers":[
        {
            "category":"Freight",
            "type":"Transportation"
        },
        {
            "category":"Retail",
            "subcategory":"Storage",
            "type":"Services"
        }
    ],
    "sg:postcode":"BN14 9RJ",
    "sg:province":"West Sussex",
    "sg:tags":[
        "haulage",
        "household",
        "road",
        "removal"
    ],
    "wof:name":"Reliable Removals",
    "wof:placetype":"venue"
},
  "geometry": {"coordinates":[-0.3918400109,50.8359985352],"type":"Point"}
}