{
  "type": "Feature",
  "properties": {
    "addr:full":"Marina Village, Prestonbrook Runcorn Cheshire WA7 3DW",
    "addr:postcode":"wa7 3dw",
    "addr:street":"Prestonbrook",
    "iso:country":"GB",
    "sg:address":"Marina Village, Prestonbrook",
    "sg:city":"Runcorn",
    "sg:classifiers":[
        {
            "category":"Autos & Motor Vehicles",
            "subcategory":"Boat Sales",
            "type":"Retail Goods"
        }
    ],
    "sg:phone":"+44 1928 716666",
    "sg:postcode":"WA7 3DW",
    "sg:province":"Cheshire",
    "sg:tags":[
        "equipment",
        "builder",
        "repair"
    ],
    "wof:name":"Pyranha Mouldings Ltd.",
    "wof:placetype":"venue"
},
  "geometry": {"coordinates":[-2.655544,53.324924],"type":"Point"}
}