{
  "type": "Feature",
  "properties": {
    "addr:full":"94 Clayhall Av Ilford Essex IG5 0LF",
    "addr:housenumber":"94",
    "addr:postcode":"ig5 0lf",
    "addr:street":"Clayhall Av Ilford",
    "iso:country":"GB",
    "sg:address":"94 Clayhall Av",
    "sg:city":"Ilford",
    "sg:classifiers":[
        {
            "category":"Professional",
            "subcategory":"Business Services",
            "type":"Services"
        }
    ],
    "sg:phone":"+44 20 8551 1685",
    "sg:postcode":"IG5 0LF",
    "sg:province":"Essex",
    "sg:tags":[
        "shop",
        "cleaning"
    ],
    "wof:name":"European Elite Cleaning Ltd",
    "wof:placetype":"venue"
},
  "geometry": {"coordinates":[0.0546599999,51.5917053223],"type":"Point"}
}