{
  "type": "Feature",
  "properties": {
    "iso:country":"GB",
    "sg:address":"Broadford Area",
    "sg:city":"Isle Of Skye",
    "sg:classifiers":[
        {
            "category":"Landmark",
            "subcategory":"Tourist Information",
            "type":"Public Place"
        },
        {
            "category":"Government",
            "subcategory":"Office",
            "type":"Public Place"
        }
    ],
    "sg:phone":"+44 1471 822361",
    "sg:postcode":"IV49 9AB",
    "sg:province":"Highland",
    "sg:tags":[
        "local"
    ],
    "wof:name":"Highlands of Scotland Tourist Board (The",
    "wof:placetype":"venue"
},
  "geometry": {"coordinates":[-5.91218,57.242214],"type":"Point"}
}