{
  "type": "Feature",
  "properties": {
    "addr:full":"Bennachie Craft Centre, Chapel Of Garioch Inverurie Aberdeenshire AB51 5HE",
    "addr:postcode":"ab51 5he",
    "iso:country":"GB",
    "sg:address":"Bennachie Craft Centre, Chapel Of Garioch",
    "sg:city":"Inverurie",
    "sg:classifiers":[
        {
            "category":"Retail",
            "subcategory":"Repair Shop",
            "type":"Services"
        }
    ],
    "sg:postcode":"AB51 5HE",
    "sg:province":"Aberdeenshire",
    "sg:tags":[
        "clocks",
        "watch"
    ],
    "wof:name":"Christopher Edwards",
    "wof:placetype":"venue"
},
  "geometry": {"coordinates":[-2.4720311165,57.3060188293],"type":"Point"}
}