{
  "type": "Feature",
  "properties": {
    "iso:country":"GB",
    "sg:address":"376 Canterbury Street",
    "sg:city":"Gillingham",
    "sg:classifiers":[
        {
            "category":"Shopping",
            "subcategory":"Used Merchandise",
            "type":"Retail Goods"
        }
    ],
    "sg:phone":"+44 1634 856433",
    "sg:postcode":"ME7 5LD",
    "sg:province":"Kent",
    "sg:tags":[
        "shop",
        "second-hand",
        "furniture"
    ],
    "wof:name":"F J Phillips & Son",
    "wof:placetype":"venue"
},
  "geometry": {"coordinates":[0.5523110032,51.3748168945],"type":"Point"}
}