{
  "type": "Feature",
  "properties": {
    "iso:country":"GB",
    "sg:address":"Heaton Rd, Heaton",
    "sg:city":"Newcastle Upon Tyne",
    "sg:classifiers":[
        {
            "category":"Place Of Worship",
            "type":"Public Place"
        }
    ],
    "sg:phone":"+44 191 240 0114",
    "sg:postcode":"NE6 5HN",
    "sg:province":"Tyne and Wear",
    "wof:name":"Heaton United Reformed Church",
    "wof:placetype":"venue"
},
  "geometry": {"coordinates":[-1.583084,54.990486],"type":"Point"}
}