{
  "type": "Feature",
  "properties": {
    "addr:full":"Carr House, Seamer Middlesbrough North Yorkshire TS9 5LL",
    "addr:postcode":"ts9 5ll",
    "iso:country":"GB",
    "sg:address":"Carr House, Seamer",
    "sg:city":"Middlesbrough",
    "sg:classifiers":[
        {
            "category":"Building & Trades",
            "subcategory":"Landscaping Services",
            "type":"Services"
        }
    ],
    "sg:phone":"+44 1642 713177",
    "sg:postcode":"TS9 5LL",
    "sg:province":"North Yorkshire",
    "sg:tags":[
        "gardening"
    ],
    "wof:name":"Puregrow Natural Products",
    "wof:placetype":"venue"
},
  "geometry": {"coordinates":[-1.230557,54.484856],"type":"Point"}
}