{
  "type": "Feature",
  "properties": {
    "addr:full":", Ruthern Bridge Bodmin Cornwall PL30 5LU",
    "addr:housenumber":"bodmin",
    "addr:postcode":"pl30 5lu",
    "addr:street":"Bridge",
    "iso:country":"GB",
    "sg:address":", Ruthern Bridge",
    "sg:city":"Bodmin",
    "sg:classifiers":[
        {
            "category":"Travel",
            "subcategory":"Hotels & Motels",
            "type":"Entertainment"
        },
        {
            "category":"Travel",
            "subcategory":"Travel Agent",
            "type":"Entertainment"
        }
    ],
    "sg:phone":"+44 1208 831395",
    "sg:postcode":"PL30 5LU",
    "sg:province":"Cornwall",
    "sg:tags":[
        "self",
        "agency",
        "catering",
        "activity"
    ],
    "wof:name":"Ruthern Valley Holidays",
    "wof:placetype":"venue"
},
  "geometry": {"coordinates":[-4.8036999702,50.4589004517],"type":"Point"}
}