{
  "type": "Feature",
  "properties": {
    "addr:full":"43 Bloomsbury Square London Greater London WC1A 2RA",
    "addr:housenumber":"43",
    "addr:postcode":"wc1a 2ra",
    "addr:street":"Bloomsbury",
    "iso:country":"GB",
    "sg:address":"43 Bloomsbury Square",
    "sg:city":"London",
    "sg:classifiers":[
        {
            "category":"Professional",
            "subcategory":"Lawyer & Legal Services",
            "type":"Services"
        }
    ],
    "sg:phone":"+44 20 7242 8692",
    "sg:postcode":"WC1A 2RA",
    "sg:province":"Greater London",
    "sg:tags":[
        "patent",
        "agent"
    ],
    "wof:name":"Carpmaels & Ransford",
    "wof:placetype":"venue"
},
  "geometry": {"coordinates":[-0.1218319982,51.5185661316],"type":"Point"}
}