{
  "type": "Feature",
  "properties": {
    "addr:full":"Shire House, Chester Road, Gatesheath Chester Cheshire CH3 9AH",
    "addr:postcode":"ch3 9ah",
    "addr:street":"Chester Road Gatesheath",
    "iso:country":"GB",
    "sg:address":"Shire House, Chester Road, Gatesheath",
    "sg:city":"Chester",
    "sg:classifiers":[
        {
            "category":"Manufacturing",
            "subcategory":"Tools & Machinery",
            "type":"Manufacturing & Wholesale Goods"
        }
    ],
    "sg:phone":"+44 1829 771133",
    "sg:postcode":"CH3 9AH",
    "sg:province":"Cheshire",
    "sg:tags":[
        "society",
        "friendly"
    ],
    "wof:name":"Nfu Mutual",
    "wof:placetype":"venue"
},
  "geometry": {"coordinates":[-2.799546,53.13855],"type":"Point"}
}