{
  "type": "Feature",
  "properties": {
    "iso:country":"GB",
    "sg:address":"Sherburn Gate, Chapeltown",
    "sg:city":"Sheffield",
    "sg:classifiers":[
        {
            "category":"Education",
            "subcategory":"School",
            "type":"Public Place"
        },
        {
            "category":"Government",
            "subcategory":"Office",
            "type":"Public Place"
        }
    ],
    "sg:phone":"+44 114 246 3412",
    "sg:postcode":"S35 2EU",
    "sg:province":"South Yorkshire",
    "sg:tags":[
        "local",
        "authority"
    ],
    "wof:name":"Lound Infants School",
    "wof:placetype":"venue"
},
  "geometry": {"coordinates":[-1.475945,53.466702],"type":"Point"}
}