{
  "type": "Feature",
  "properties": {
    "iso:country":"GB",
    "sg:address":"The Shambles, Market Place",
    "sg:city":"Thetford",
    "sg:classifiers":[
        {
            "category":"Fast Food",
            "type":"Food & Drink"
        }
    ],
    "sg:phone":"+44 1842 750434",
    "sg:postcode":"IP24 2BA",
    "sg:province":"Norfolk",
    "sg:tags":[
        "away",
        "take"
    ],
    "wof:name":"Thetford Kebab House",
    "wof:placetype":"venue"
},
  "geometry": {"coordinates":[0.7407330275,52.4132919312],"type":"Point"}
}