{
  "type": "Feature",
  "properties": {
    "addr:full":"30-32 Westbourne Grove, Bayswater London Greater London W2 5RH",
    "addr:housenumber":"30-32",
    "addr:postcode":"w2 5rh",
    "addr:street":"Westbourne Grove",
    "iso:country":"GB",
    "sg:address":"30-32 Westbourne Grove, Bayswater",
    "sg:city":"London",
    "sg:classifiers":[
        {
            "category":"Banks & Credit Unions",
            "subcategory":"Bank",
            "type":"Services"
        }
    ],
    "sg:phone":"+44 845 730 9059",
    "sg:postcode":"W2 5RH",
    "sg:province":"Greater London",
    "wof:name":"Lloyds Tsb",
    "wof:placetype":"venue"
},
  "geometry": {"coordinates":[-0.18983,51.51569],"type":"Point"}
}