{
  "type": "Feature",
  "properties": {
    "iso:country":"GB",
    "sg:address":"Wellfield Offices, Garth Road",
    "sg:city":"Bangor",
    "sg:classifiers":[
        {
            "category":"Professional",
            "subcategory":"Lawyer & Legal Services",
            "type":"Services"
        }
    ],
    "sg:postcode":"LL57 1EE",
    "sg:province":"Gwynedd",
    "sg:tags":[
        "solicitor"
    ],
    "wof:name":"Carter Vincent Jones Davis",
    "wof:placetype":"venue"
},
  "geometry": {"coordinates":[-4.1260638237,53.2295951843],"type":"Point"}
}