{
  "type": "Feature",
  "properties": {
    "addr:full":"Lochwinnoch Rd Kilmacolm Inverclyde PA13 4LG",
    "addr:postcode":"pa13 4lg",
    "addr:street":"Lochwinnoch Rd",
    "iso:country":"GB",
    "sg:address":"Lochwinnoch Rd",
    "sg:city":"Kilmacolm",
    "sg:classifiers":[
        {
            "category":"Government",
            "subcategory":"Police Station",
            "type":"Public Place"
        }
    ],
    "sg:phone":"+44 1505 872056",
    "sg:postcode":"PA13 4LG",
    "sg:province":"Inverclyde",
    "sg:tags":[
        "support"
    ],
    "wof:name":"Strathclyde Police",
    "wof:placetype":"venue"
},
  "geometry": {"coordinates":[-4.6301999092,55.8926010132],"type":"Point"}
}