{
  "type": "Feature",
  "properties": {
    "addr:full":"72b High Street, Aveley South Ockendon Essex RM15 4BX",
    "addr:housenumber":"72b",
    "addr:postcode":"rm15 4bx",
    "addr:street":"High Street;Ockendon",
    "iso:country":"GB",
    "sg:address":"72b High Street, Aveley",
    "sg:city":"South Ockendon",
    "sg:classifiers":[
        {
            "category":"Shopping",
            "subcategory":"Florist",
            "type":"Retail Goods"
        }
    ],
    "sg:phone":"+44 1708 866580",
    "sg:postcode":"RM15 4BX",
    "sg:province":"Essex",
    "wof:name":"Village Florists",
    "wof:placetype":"venue"
},
  "geometry": {"coordinates":[0.255221,51.498817],"type":"Point"}
}