{
  "type": "Feature",
  "properties": {
    "iso:country":"GB",
    "sg:address":"87 Povey Cross Rd",
    "sg:city":"Horley",
    "sg:classifiers":[
        {
            "category":"Travel",
            "subcategory":"Hotels & Motels",
            "type":"Entertainment"
        }
    ],
    "sg:phone":"+44 1293 772149",
    "sg:postcode":"RH6 0AE",
    "sg:province":"Surrey",
    "sg:tags":[
        "house",
        "guest"
    ],
    "wof:name":"The Poplars",
    "wof:placetype":"venue"
},
  "geometry": {"coordinates":[-0.181116,51.166634],"type":"Point"}
}