{
  "type": "Feature",
  "properties": {
    "addr:full":"23 Sandpiper Road, Highfield Wigan Lancashire WN3 6AX",
    "addr:housenumber":"23",
    "addr:postcode":"wn3 6ax",
    "addr:street":"Sandpiper Road",
    "iso:country":"GB",
    "sg:address":"23 Sandpiper Road, Highfield",
    "sg:city":"Wigan",
    "sg:classifiers":[
        {
            "category":"Retail",
            "subcategory":"Auto Repair",
            "type":"Services"
        }
    ],
    "sg:phone":"+44 1942 217651",
    "sg:postcode":"WN3 6AX",
    "sg:province":"Lancashire",
    "sg:tags":[
        "engine",
        "car",
        "specialist"
    ],
    "wof:name":"Ian's Mobile Crypton Tuning",
    "wof:placetype":"venue"
},
  "geometry": {"coordinates":[-2.679729,53.528488],"type":"Point"}
}