{
  "type": "Feature",
  "properties": {
    "addr:full":"Greenland Avenue Wymondham Norfolk NR18 0ER",
    "addr:postcode":"nr18 0er",
    "addr:street":"Greenland Avenue",
    "iso:country":"GB",
    "sg:address":"Greenland Avenue",
    "sg:city":"Wymondham",
    "sg:classifiers":[
        {
            "category":"Building & Trades",
            "subcategory":"Construction",
            "type":"Services"
        }
    ],
    "sg:phone":"+44 1953 604312",
    "sg:postcode":"NR18 0ER",
    "sg:province":"Norfolk",
    "sg:tags":[
        "builder"
    ],
    "wof:name":"I J Scott & J K",
    "wof:placetype":"venue"
},
  "geometry": {"coordinates":[1.134425,52.581051],"type":"Point"}
}