{
  "type": "Feature",
  "properties": {
    "addr:full":"Bearwood Shopping Centre, 543 Bearwood Road Smethwick West Midlands B66 4BH",
    "addr:housenumber":"543",
    "addr:postcode":"b66 4bh",
    "addr:street":"Bearwood Road",
    "iso:country":"GB",
    "sg:address":"Bearwood Shopping Centre, 543 Bearwood Road",
    "sg:city":"Smethwick",
    "sg:classifiers":[
        {
            "category":"Shopping",
            "subcategory":"Thrift Store",
            "type":"Retail Goods"
        },
        {
            "category":"Organizations",
            "subcategory":"Non-profit Organization",
            "type":"Services"
        }
    ],
    "sg:phone":"+44 121 429 1954",
    "sg:postcode":"B66 4BH",
    "sg:province":"West Midlands",
    "sg:tags":[
        "shop",
        "organisation",
        "voluntary",
        "charity"
    ],
    "wof:name":"Barnardo's",
    "wof:placetype":"venue"
},
  "geometry": {"coordinates":[-1.9694709778,52.4754524231],"type":"Point"}
}