{
  "type": "Feature",
  "properties": {
    "iso:country":"GB",
    "sg:address":"41 Ridgeway",
    "sg:city":"Plymouth",
    "sg:classifiers":[
        {
            "category":"Food & Beverages",
            "subcategory":"Fruits & Vegetables",
            "type":"Retail Goods"
        }
    ],
    "sg:phone":"+44 1752 346369",
    "sg:postcode":"PL7 2AW",
    "sg:province":"Devon",
    "sg:tags":[
        "greengrocer"
    ],
    "wof:name":"Charlies Top of the Town",
    "wof:placetype":"venue"
},
  "geometry": {"coordinates":[-4.052583,50.388035],"type":"Point"}
}