{
  "type": "Feature",
  "properties": {
    "iso:country":"GB",
    "sg:address":"9 Kings Rd, Prestwich",
    "sg:city":"Manchester",
    "sg:classifiers":[
        {
            "category":"Communications",
            "type":"Services"
        }
    ],
    "sg:phone":"+44 161 773 9100",
    "sg:postcode":"M25 0LE",
    "sg:province":"Greater Manchester",
    "sg:tags":[
        "telecommunication"
    ],
    "wof:name":"Mobiles Direct",
    "wof:placetype":"venue"
},
  "geometry": {"coordinates":[-2.270754,53.519035],"type":"Point"}
}