{
  "type": "Feature",
  "properties": {
    "iso:country":"GB",
    "sg:address":"11 Wellspring Ho, Pinkerton Rd",
    "sg:city":"Basingstoke",
    "sg:classifiers":[
        {
            "category":"Professional",
            "subcategory":"Computer Services",
            "type":"Services"
        }
    ],
    "sg:postcode":"RG22 6RP",
    "sg:province":"Hampshire",
    "sg:tags":[
        "consultant"
    ],
    "wof:name":"Fox Electronic Services Ltd",
    "wof:placetype":"venue"
},
  "geometry": {"coordinates":[-1.1224999428,51.2546005249],"type":"Point"}
}