{
  "type": "Feature",
  "properties": {
    "addr:full":"17 Glenholme Way Sheffield South Yorkshire S13 8PY",
    "addr:housenumber":"17",
    "addr:postcode":"s13 8py",
    "addr:street":"Glenholme Way",
    "iso:country":"GB",
    "sg:address":"17 Glenholme Way",
    "sg:city":"Sheffield",
    "sg:classifiers":[
        {
            "category":"Building & Trades",
            "subcategory":"Construction",
            "type":"Services"
        }
    ],
    "sg:phone":"+44 114 239 4123",
    "sg:postcode":"S13 8PY",
    "sg:province":"South Yorkshire",
    "sg:tags":[
        "dry",
        "lining",
        "plasterers",
        "screeders"
    ],
    "wof:name":"Andy Mellor",
    "wof:placetype":"venue"
},
  "geometry": {"coordinates":[-1.39375,53.364746],"type":"Point"}
}