{
  "type": "Feature",
  "properties": {
    "addr:full":"Brookside Farm, Foston Derby Derbyshire DE65 5PU",
    "addr:postcode":"de65 5pu",
    "iso:country":"GB",
    "sg:address":"Brookside Farm, Foston",
    "sg:city":"Derby",
    "sg:classifiers":[
        {
            "category":"Wholesale",
            "subcategory":"Meat",
            "type":"Manufacturing & Wholesale Goods"
        }
    ],
    "sg:phone":"+44 1283 812242",
    "sg:postcode":"DE65 5PU",
    "sg:province":"Derbyshire",
    "sg:tags":[
        "abattoir"
    ],
    "wof:name":"Messrs Brooks",
    "wof:placetype":"venue"
},
  "geometry": {"coordinates":[-1.7221779823,52.8835983276],"type":"Point"}
}