{
  "type": "Feature",
  "properties": {
    "iso:country":"GB",
    "sg:address":"Unit 5, Brunel Way",
    "sg:city":"Stonehouse",
    "sg:classifiers":[
        {
            "category":"Shopping",
            "type":"Retail Goods"
        }
    ],
    "sg:phone":"+44 1453 825255",
    "sg:postcode":"GL10 3SX",
    "sg:province":"Gloucestershire",
    "sg:tags":[
        "scientific",
        "apparatus"
    ],
    "wof:name":"Greiner Bio-One Ltd.",
    "wof:placetype":"venue"
},
  "geometry": {"coordinates":[-2.29637,51.753071],"type":"Point"}
}