{
  "type": "Feature",
  "properties": {
    "iso:country":"GB",
    "sg:address":"The Castle Practice, 2 Hawthorne Rd",
    "sg:city":"Birmingham",
    "sg:classifiers":[
        {
            "category":"Health Services",
            "subcategory":"Doctor",
            "type":"Services"
        }
    ],
    "sg:phone":"+44 121 748 3622",
    "sg:postcode":"B36 0HH",
    "sg:province":"West Midlands",
    "sg:tags":[
        "practitioners"
    ],
    "wof:name":"Parnaik, V G",
    "wof:placetype":"venue"
},
  "geometry": {"coordinates":[-1.75873,52.50156],"type":"Point"}
}