{
  "type": "Feature",
  "properties": {
    "addr:full":"1 Townley Rd East Dulwich Greater London SE22 8SW",
    "addr:housenumber":"1",
    "addr:postcode":"se22 8sw",
    "addr:street":"Townley Rd",
    "iso:country":"GB",
    "sg:address":"1 Townley Rd",
    "sg:city":"East Dulwich",
    "sg:classifiers":[
        {
            "category":"Health Services",
            "subcategory":"Dentist",
            "type":"Services"
        }
    ],
    "sg:phone":"+44 20 8693 4974",
    "sg:postcode":"SE22 8SW",
    "sg:province":"Greater London",
    "wof:name":"Joe Callanan",
    "wof:placetype":"venue"
},
  "geometry": {"coordinates":[-0.077612,51.453407],"type":"Point"}
}