{
  "type": "Feature",
  "properties": {
    "iso:country":"GB",
    "sg:address":"Unit A, Berkeley Court, Earl Russell Way",
    "sg:city":"Bristol",
    "sg:classifiers":[
        {
            "category":"Manufacturing",
            "subcategory":"Motor Vehicles & Parts",
            "type":"Manufacturing & Wholesale Goods"
        }
    ],
    "sg:phone":"+44 117 935 0422",
    "sg:postcode":"BS5 0BX",
    "sg:province":"City of Bristol",
    "sg:tags":[
        "bearing"
    ],
    "wof:name":"B S L",
    "wof:placetype":"venue"
},
  "geometry": {"coordinates":[-2.5653278828,51.4583206177],"type":"Point"}
}