{
  "type": "Feature",
  "properties": {
    "iso:country":"GB",
    "sg:address":"Unit 4 Grecian Mill",
    "sg:city":"Bolton",
    "sg:classifiers":[
        {
            "category":"Manufacturing",
            "subcategory":"Glass & Minerals",
            "type":"Manufacturing & Wholesale Goods"
        }
    ],
    "sg:postcode":"BL3 6PB",
    "sg:province":"Lancashire",
    "sg:tags":[
        "fibre",
        "moulding"
    ],
    "wof:name":"Gary Armstrong",
    "wof:placetype":"venue"
},
  "geometry": {"coordinates":[-2.4282250404,53.5659217834],"type":"Point"}
}