{
  "type": "Feature",
  "properties": {
    "addr:full":"91 Bedford Rd Hitchin Bedfordshire SG5 2TT",
    "addr:housenumber":"91",
    "addr:postcode":"sg5 2tt",
    "addr:street":"Bedford Rd",
    "iso:country":"GB",
    "sg:address":"91 Bedford Rd",
    "sg:city":"Hitchin",
    "sg:classifiers":[
        {
            "category":"Autos & Motor Vehicles",
            "subcategory":"Auto Supplies",
            "type":"Retail Goods"
        }
    ],
    "sg:phone":"+44 1462 421666",
    "sg:postcode":"SG5 2TT",
    "sg:province":"Bedfordshire",
    "sg:tags":[
        "tyre"
    ],
    "wof:name":"Supertyres Motorists Centre Ltd",
    "wof:placetype":"venue"
},
  "geometry": {"coordinates":[-0.285303,51.954659],"type":"Point"}
}