{
  "type": "Feature",
  "properties": {
    "addr:full":"56 Christchurch Rd Ringwood Dorset BH24 1DW",
    "addr:housenumber":"56",
    "addr:postcode":"bh24 1dw",
    "addr:street":"Christchurch Rd",
    "iso:country":"GB",
    "sg:address":"56 Christchurch Rd",
    "sg:city":"Ringwood",
    "sg:classifiers":[
        {
            "category":"Community Center",
            "subcategory":"Youth",
            "type":"Public Place"
        }
    ],
    "sg:phone":"+44 1425 474397",
    "sg:postcode":"BH24 1DW",
    "sg:province":"Dorset",
    "sg:tags":[
        "organisation",
        "centre"
    ],
    "wof:name":"Hampshire Youth Service",
    "wof:placetype":"venue"
},
  "geometry": {"coordinates":[-1.7885750532,50.8442573547],"type":"Point"}
}