{
  "type": "Feature",
  "properties": {
    "iso:country":"GB",
    "sg:address":"Architect Enquiries, 2nd Floor, 1 Lancaster Circus",
    "sg:city":"Birmingham",
    "sg:classifiers":[
        {
            "category":"Government",
            "subcategory":"Office",
            "type":"Public Place"
        }
    ],
    "sg:phone":"+44 121 303 6719",
    "sg:postcode":"B4 7DG",
    "sg:province":"West Midlands",
    "sg:tags":[
        "local"
    ],
    "wof:name":"Birmingham City Council",
    "wof:placetype":"venue"
},
  "geometry": {"coordinates":[-1.89222,52.481998],"type":"Point"}
}