{
  "type": "Feature",
  "properties": {
    "iso:country":"GB",
    "sg:address":"Ground Floor, 3 Tanner Street",
    "sg:city":"London",
    "sg:classifiers":[
        {
            "category":"Professional",
            "subcategory":"Art Services",
            "type":"Services"
        }
    ],
    "sg:phone":"+44 20 7226 1973",
    "sg:postcode":"N1 8HE",
    "sg:province":"Greater London",
    "sg:tags":[
        "graphic",
        "designer"
    ],
    "wof:name":"Mercury Design",
    "wof:placetype":"venue"
},
  "geometry": {"coordinates":[-0.09904,51.533211],"type":"Point"}
}