{
  "type": "Feature",
  "properties": {
    "addr:full":"Eastern Electricity, P O Box 40 Ipswich Suffolk IP9 2AQ",
    "addr:housenumber":"box 40",
    "addr:postcode":"ip9 2aq",
    "addr:street":"P O",
    "iso:country":"GB",
    "sg:address":"Eastern Electricity, P O Box 40",
    "sg:city":"Ipswich",
    "sg:classifiers":[
        {
            "category":"Utilities",
            "subcategory":"Electric",
            "type":"Services"
        }
    ],
    "sg:phone":"+44 1473 688688",
    "sg:postcode":"IP9 2AQ",
    "sg:province":"Suffolk",
    "sg:tags":[
        "electricity"
    ],
    "wof:name":"Eastern Group PLC",
    "wof:placetype":"venue"
},
  "geometry": {"coordinates":[1.10175,51.99926],"type":"Point"}
}