{
  "type": "Feature",
  "properties": {
    "iso:country":"GB",
    "sg:address":"50 Maple Drive",
    "sg:city":"Johnstone",
    "sg:classifiers":[
        {
            "category":"Taxi",
            "type":"Transportation"
        }
    ],
    "sg:postcode":"PA5 9RY",
    "sg:province":"Renfrewshire",
    "sg:tags":[
        "mini",
        "cab"
    ],
    "wof:name":"Kab Cars Ltd.",
    "wof:placetype":"venue"
},
  "geometry": {"coordinates":[-4.504029,55.824867],"type":"Point"}
}