{
  "type": "Feature",
  "properties": {
    "addr:full":"New Buildings, Victoria Street, Greetland Halifax West Yorkshire HX4 8DF",
    "addr:postcode":"hx4 8df",
    "addr:street":"Victoria Street",
    "iso:country":"GB",
    "sg:address":"New Buildings, Victoria Street, Greetland",
    "sg:city":"Halifax",
    "sg:classifiers":[
        {
            "category":"Health Services",
            "subcategory":"Doctor",
            "type":"Services"
        }
    ],
    "sg:phone":"+44 1422 372355",
    "sg:postcode":"HX4 8DF",
    "sg:province":"West Yorkshire",
    "sg:tags":[
        "practitioners"
    ],
    "wof:name":"West Yorkshire Strategic Health Authority",
    "wof:placetype":"venue"
},
  "geometry": {"coordinates":[-1.8729749918,53.6873893738],"type":"Point"}
}