{
  "type": "Feature",
  "properties": {
    "addr:full":"395 Hanworth Road Hounslow Greater London TW4 5LF",
    "addr:housenumber":"395",
    "addr:postcode":"tw4 5lf",
    "addr:street":"Hanworth Road",
    "iso:country":"GB",
    "sg:address":"395 Hanworth Road",
    "sg:city":"Hounslow",
    "sg:classifiers":[
        {
            "category":"Utilities",
            "type":"Services"
        }
    ],
    "sg:postcode":"TW4 5LF",
    "sg:province":"Greater London",
    "sg:tags":[
        "internet"
    ],
    "wof:name":"Net Benefits Ltd.",
    "wof:placetype":"venue"
},
  "geometry": {"coordinates":[-0.371989,51.457813],"type":"Point"}
}