{
  "type": "Feature",
  "properties": {
    "iso:country":"GB",
    "sg:address":"Manor Cottage, Baverstock, Dinton",
    "sg:city":"Salisbury",
    "sg:classifiers":[
        {
            "category":"Farming",
            "subcategory":"Livestock Farm",
            "type":"Manufacturing & Wholesale Goods"
        }
    ],
    "sg:phone":"+44 1722 716205",
    "sg:postcode":"SP3 5EN",
    "sg:province":"Wiltshire",
    "sg:tags":[
        "others"
    ],
    "wof:name":"S J Combes Farming Co",
    "wof:placetype":"venue"
},
  "geometry": {"coordinates":[-1.979668,51.083214],"type":"Point"}
}