{
  "type": "Feature",
  "properties": {
    "iso:country":"GB",
    "sg:address":"9 Kilburn Bridge",
    "sg:city":"Kilburn",
    "sg:classifiers":[
        {
            "category":"Shopping",
            "subcategory":"Pawn Shop",
            "type":"Retail Goods"
        }
    ],
    "sg:phone":"+44 20 7624 4730",
    "sg:postcode":"NW6 6HT",
    "sg:province":"Greater London",
    "sg:tags":[
        "pawnbroker"
    ],
    "wof:name":"William Kunsler",
    "wof:placetype":"venue"
},
  "geometry": {"coordinates":[-0.192664,51.537186],"type":"Point"}
}