{
  "type": "Feature",
  "properties": {
    "iso:country":"GB",
    "sg:address":"Geraldine Road",
    "sg:city":"Malvern",
    "sg:classifiers":[
        {
            "category":"Education",
            "subcategory":"Special Training",
            "type":"Public Place"
        }
    ],
    "sg:phone":"+44 1684 893961",
    "sg:postcode":"WR14 3NZ",
    "sg:province":"Herefordshire",
    "sg:tags":[
        "school"
    ],
    "wof:name":"S C S I Hearing Repaired Resource Base",
    "wof:placetype":"venue"
},
  "geometry": {"coordinates":[-2.309644,52.107857],"type":"Point"}
}