{
  "type": "Feature",
  "properties": {
    "iso:country":"GB",
    "sg:address":"Unit 10 The Forum",
    "sg:city":"Kirkcaldy",
    "sg:classifiers":[
        {
            "category":"Retail",
            "subcategory":"Laundry & Dry Cleaning",
            "type":"Services"
        }
    ],
    "sg:postcode":"KY1 1NJ",
    "sg:province":"Fife",
    "sg:tags":[
        "alteration"
    ],
    "wof:name":"Forum Alterations",
    "wof:placetype":"venue"
},
  "geometry": {"coordinates":[-3.163029,56.109596],"type":"Point"}
}