{
  "type": "Feature",
  "properties": {
    "iso:country":"GB",
    "sg:address":"Unit 7d, Steel Close, Eaton Soton",
    "sg:city":"Huntingdon",
    "sg:classifiers":[
        {
            "category":"Manufacturing",
            "subcategory":"Metals",
            "type":"Manufacturing & Wholesale Goods"
        }
    ],
    "sg:postcode":"PE19 4TT",
    "sg:province":"Bedfordshire",
    "sg:tags":[
        "steel",
        "fabricator",
        "erectors"
    ],
    "wof:name":"Bripat Engineering",
    "wof:placetype":"venue"
},
  "geometry": {"coordinates":[-0.27204,52.246269],"type":"Point"}
}