{
  "type": "Feature",
  "properties": {
    "iso:country":"GB",
    "sg:address":"2 High Street, Corby Glen",
    "sg:city":"Grantham",
    "sg:classifiers":[
        {
            "category":"Professional",
            "subcategory":"Art Services",
            "type":"Services"
        }
    ],
    "sg:phone":"+44 1476 550502",
    "sg:postcode":"NG33 4LX",
    "sg:province":"Leicestershire",
    "sg:tags":[
        "graphic",
        "designer"
    ],
    "wof:name":"Mackenzie Wilson Ltd.",
    "wof:placetype":"venue"
},
  "geometry": {"coordinates":[-0.5395089984,52.7546043396],"type":"Point"}
}