{
  "type": "Feature",
  "properties": {
    "addr:full":"85 Ross Rd Maidenhead Berkshire SL6 2SR",
    "addr:housenumber":"85",
    "addr:postcode":"sl6 2sr",
    "addr:street":"Ross Rd",
    "iso:country":"GB",
    "sg:address":"85 Ross Rd",
    "sg:city":"Maidenhead",
    "sg:classifiers":[
        {
            "category":"Health Services",
            "subcategory":"Doctor",
            "type":"Services"
        }
    ],
    "sg:phone":"+44 1628 623767",
    "sg:postcode":"SL6 2SR",
    "sg:province":"Berkshire",
    "sg:tags":[
        "practitioners"
    ],
    "wof:name":"Obi, B C",
    "wof:placetype":"venue"
},
  "geometry": {"coordinates":[-0.7324450016,51.5095558167],"type":"Point"}
}