{
  "type": "Feature",
  "properties": {
    "addr:full":"Pemberton Avenue Romford Essex RM2 6EX",
    "addr:postcode":"rm2 6ex",
    "addr:street":"Pemberton Avenue",
    "iso:country":"GB",
    "sg:address":"Pemberton Avenue",
    "sg:city":"Romford",
    "sg:classifiers":[
        {
            "category":"Professional",
            "subcategory":"Secretarial Services",
            "type":"Services"
        }
    ],
    "sg:postcode":"RM2 6EX",
    "sg:province":"Essex",
    "wof:name":"W P Type-Rite Services",
    "wof:placetype":"venue"
},
  "geometry": {"coordinates":[0.20596,51.586361],"type":"Point"}
}