{
  "type": "Feature",
  "properties": {
    "iso:country":"GB",
    "sg:address":"Units 7-8",
    "sg:city":"Huntingdon",
    "sg:classifiers":[
        {
            "category":"Building & Trades",
            "subcategory":"Construction",
            "type":"Services"
        }
    ],
    "sg:phone":"+44 1480 356463",
    "sg:postcode":"PE29 6DY",
    "sg:province":"Cambridgeshire",
    "sg:tags":[
        "joinery"
    ],
    "wof:name":"The Real Wooden Window Co. Ltd.",
    "wof:placetype":"venue"
},
  "geometry": {"coordinates":[-0.1996510029,52.345916748],"type":"Point"}
}