{
  "type": "Feature",
  "properties": {
    "addr:full":"74 Worksop Rd Sheffield South Yorkshire S9 3TN",
    "addr:housenumber":"74",
    "addr:postcode":"s9 3tn",
    "addr:street":"Worksop Rd",
    "iso:country":"GB",
    "sg:address":"74 Worksop Rd",
    "sg:city":"Sheffield",
    "sg:classifiers":[
        {
            "category":"Bars & Pubs",
            "type":"Food & Drink"
        }
    ],
    "sg:phone":"+44 114 244 1161",
    "sg:postcode":"S9 3TN",
    "sg:province":"South Yorkshire",
    "sg:tags":[
        "pubs",
        "inn"
    ],
    "wof:name":"Cutlers Arms",
    "wof:placetype":"venue"
},
  "geometry": {"coordinates":[-1.42773,53.394825],"type":"Point"}
}