{
  "type": "Feature",
  "properties": {
    "iso:country":"GB",
    "sg:address":"72 Hillary Road",
    "sg:city":"Maidstone",
    "sg:classifiers":[
        {
            "category":"Professional",
            "type":"Services"
        },
        {
            "category":"Arts & Performance",
            "subcategory":"Music",
            "type":"Entertainment"
        }
    ],
    "sg:phone":"+44 1227 266885",
    "sg:postcode":"ME14 2JU",
    "sg:province":"Kent",
    "sg:tags":[
        "mobile",
        "entertainer",
        "disco"
    ],
    "wof:name":"Woodpecker Family Disco",
    "wof:placetype":"venue"
},
  "geometry": {"coordinates":[0.5273780227,51.2860641479],"type":"Point"}
}