{
  "type": "Feature",
  "properties": {
    "iso:country":"GB",
    "sg:address":"135 Wellington Street",
    "sg:city":"Glasgow",
    "sg:classifiers":[
        {
            "category":"Professional",
            "subcategory":"Accounting & Tax Preparation",
            "type":"Services"
        }
    ],
    "sg:phone":"+44 141 248 3904",
    "sg:postcode":"G2 2XE",
    "sg:province":"Glasgow City",
    "sg:tags":[
        "accountant"
    ],
    "wof:name":"Wylie & Bisset Financial Services Ltd.",
    "wof:placetype":"venue"
},
  "geometry": {"coordinates":[-4.259268,55.864063],"type":"Point"}
}