{
  "type": "Feature",
  "properties": {
    "iso:country":"GB",
    "sg:address":"50 Shiplake Bottom, Peppard Common",
    "sg:city":"Henley-on-thames",
    "sg:classifiers":[
        {
            "category":"Home & Garden",
            "subcategory":"Building Materials",
            "type":"Retail Goods"
        }
    ],
    "sg:postcode":"RG9 5HN",
    "sg:province":"Berkshire",
    "sg:tags":[
        "fencing"
    ],
    "wof:name":"D R Fisher Contractors",
    "wof:placetype":"venue"
},
  "geometry": {"coordinates":[-0.9848819971,51.5233345032],"type":"Point"}
}