{
  "type": "Feature",
  "properties": {
    "addr:full":"Shepley Bridge Marina, Huddersfield Road Mirfield West Yorkshire WF14 9HR",
    "addr:postcode":"wf14 9hr",
    "addr:street":"Shepley;Huddersfield Road",
    "iso:country":"GB",
    "sg:address":"Shepley Bridge Marina, Huddersfield Road",
    "sg:city":"Mirfield",
    "sg:classifiers":[
        {
            "category":"Autos & Motor Vehicles",
            "subcategory":"Boat Sales",
            "type":"Retail Goods"
        }
    ],
    "sg:phone":"+44 1924 491872",
    "sg:postcode":"WF14 9HR",
    "sg:province":"West Yorkshire",
    "sg:tags":[
        "repair",
        "builder"
    ],
    "wof:name":"Shepley Bridge Marina Ltd.",
    "wof:placetype":"venue"
},
  "geometry": {"coordinates":[-1.6967099905,53.6749382019],"type":"Point"}
}