{
  "type": "Feature",
  "properties": {
    "iso:country":"GB",
    "sg:address":"Bridge Street",
    "sg:city":"Stafford",
    "sg:classifiers":[
        {
            "category":"Restaurant",
            "type":"Food & Drink"
        }
    ],
    "sg:phone":"+44 1785 258199",
    "sg:postcode":"ST16 2HJ",
    "sg:province":"Staffordshire",
    "wof:name":"Wimpy",
    "wof:placetype":"venue"
},
  "geometry": {"coordinates":[-2.1160390377,52.8048210144],"type":"Point"}
}