{
  "type": "Feature",
  "properties": {
    "addr:full":"Dental Surgery, 27 Stockton Road Darlington Durham DL1 2RX",
    "addr:housenumber":"27",
    "addr:postcode":"dl1 2rx",
    "addr:street":"Stockton Road",
    "iso:country":"GB",
    "sg:address":"Dental Surgery, 27 Stockton Road",
    "sg:city":"Darlington",
    "sg:classifiers":[
        {
            "category":"Health Services",
            "subcategory":"Dentist",
            "type":"Services"
        }
    ],
    "sg:phone":"+44 1325 358916",
    "sg:postcode":"DL1 2RX",
    "sg:province":"Durham",
    "wof:name":"G P M Walton",
    "wof:placetype":"venue"
},
  "geometry": {"coordinates":[-1.548894,54.524502],"type":"Point"}
}