{
  "type": "Feature",
  "properties": {
    "iso:country":"GB",
    "sg:address":"79 Walters Road, Llansamlet",
    "sg:city":"Swansea",
    "sg:classifiers":[
        {
            "category":"Health Services",
            "subcategory":"Health Practitioner",
            "type":"Services"
        }
    ],
    "sg:postcode":"SA7 9RW",
    "sg:province":"Neath Port Talbot",
    "sg:tags":[
        "osteopath"
    ],
    "wof:name":"H L Smith",
    "wof:placetype":"venue"
},
  "geometry": {"coordinates":[-3.8957359791,51.6671180725],"type":"Point"}
}