{
  "type": "Feature",
  "properties": {
    "iso:country":"GB",
    "sg:address":"98a Phillip Street",
    "sg:city":"Chester",
    "sg:classifiers":[
        {
            "category":"Professional",
            "subcategory":"Art Services",
            "type":"Services"
        }
    ],
    "sg:phone":"+44 1244 349431",
    "sg:postcode":"CH2 3DA",
    "sg:province":"Cheshire",
    "sg:tags":[
        "picture",
        "framing"
    ],
    "wof:name":"City Framers",
    "wof:placetype":"venue"
},
  "geometry": {"coordinates":[-2.875242,53.197132],"type":"Point"}
}