{
  "type": "Feature",
  "properties": {
    "iso:country":"GB",
    "sg:address":"49 Burncross Road, Chapeltown",
    "sg:city":"Sheffield",
    "sg:classifiers":[
        {
            "category":"Autos & Motor Vehicles",
            "subcategory":"Auto Supplies",
            "type":"Retail Goods"
        }
    ],
    "sg:phone":"+44 114 246 2473",
    "sg:postcode":"S35 1RX",
    "sg:province":"South Yorkshire",
    "sg:tags":[
        "component"
    ],
    "wof:name":"Sinemaster Motor Factors Ltd.",
    "wof:placetype":"venue"
},
  "geometry": {"coordinates":[-1.4681179523,53.4618721008],"type":"Point"}
}