{
  "type": "Feature",
  "properties": {
    "addr:full":"The Office Brocklesby Ox Mobile, Home Park Brigg Lincolnshire DN20 8NL",
    "addr:postcode":"dn20 8nl",
    "addr:street":"Brigg",
    "iso:country":"GB",
    "sg:address":"The Office Brocklesby Ox Mobile, Home Park",
    "sg:city":"Brigg",
    "sg:classifiers":[
        {
            "category":"Building & Trades",
            "subcategory":"Construction",
            "type":"Services"
        }
    ],
    "sg:postcode":"DN20 8NL",
    "sg:province":"Lincolnshire",
    "sg:tags":[
        "excavation",
        "groundwork",
        "contractor"
    ],
    "wof:name":"M A Smith Groundworks Ltd.",
    "wof:placetype":"venue"
},
  "geometry": {"coordinates":[-0.484879,53.552986],"type":"Point"}
}