{
  "type": "Feature",
  "properties": {
    "addr:full":"67 Birchley Road, Billinge Wigan Lancashire WN5 7QN",
    "addr:housenumber":"67",
    "addr:postcode":"wn5 7qn",
    "addr:street":"Birchley Road",
    "iso:country":"GB",
    "sg:address":"67 Birchley Road, Billinge",
    "sg:city":"Wigan",
    "sg:classifiers":[
        {
            "category":"Farming",
            "subcategory":"Livestock Farm",
            "type":"Manufacturing & Wholesale Goods"
        }
    ],
    "sg:phone":"+44 1744 892279",
    "sg:postcode":"WN5 7QN",
    "sg:province":"Lancashire",
    "sg:tags":[
        "others"
    ],
    "wof:name":"H Abbott",
    "wof:placetype":"venue"
},
  "geometry": {"coordinates":[-2.722148,53.489647],"type":"Point"}
}