{
  "type": "Feature",
  "properties": {
    "addr:full":"101 Brent Terrace, Cricklewood London Greater London NW2 1BY",
    "addr:housenumber":"101",
    "addr:postcode":"nw2 1by",
    "addr:street":"Brent Terrace",
    "iso:country":"GB",
    "sg:address":"101 Brent Terrace, Cricklewood",
    "sg:city":"London",
    "sg:classifiers":[
        {
            "category":"Building & Trades",
            "subcategory":"Landscaping Services",
            "type":"Services"
        }
    ],
    "sg:postcode":"NW2 1BY",
    "sg:province":"Greater London",
    "sg:tags":[
        "designer",
        "architect",
        "landscape"
    ],
    "wof:name":"Plant Craft Designs Ltd.",
    "wof:placetype":"venue"
},
  "geometry": {"coordinates":[-0.2227700055,51.5685691833],"type":"Point"}
}