{
  "type": "Feature",
  "properties": {
    "addr:full":"Scotland House, Combe Rd Bristol Somerset BS20 6BJ",
    "addr:postcode":"bs20 6bj",
    "addr:street":"Combe Rd",
    "iso:country":"GB",
    "sg:address":"Scotland House, Combe Rd",
    "sg:city":"Bristol",
    "sg:classifiers":[
        {
            "category":"Social Services",
            "type":"Services"
        }
    ],
    "sg:phone":"+44 1275 845023",
    "sg:postcode":"BS20 6BJ",
    "sg:province":"Somerset",
    "sg:tags":[
        "need",
        "disability",
        "special"
    ],
    "wof:name":"Mencap Family Advisor Service",
    "wof:placetype":"venue"
},
  "geometry": {"coordinates":[-2.769456,51.484295],"type":"Point"}
}