{
  "type": "Feature",
  "properties": {
    "iso:country":"GB",
    "sg:address":"Lanes End",
    "sg:city":"Craven Arms",
    "sg:classifiers":[
        {
            "category":"Home & Garden",
            "subcategory":"Garden Supply",
            "type":"Retail Goods"
        }
    ],
    "sg:postcode":"SY7 8DE",
    "sg:province":"Herefordshire",
    "sg:tags":[
        "ornament"
    ],
    "wof:name":"Connoisseur Sun Dials",
    "wof:placetype":"venue"
},
  "geometry": {"coordinates":[-2.836239,52.439388],"type":"Point"}
}