{
  "type": "Feature",
  "properties": {
    "addr:full":"136 High Street, Nailsea Bristol Somerset BS48 1AP",
    "addr:housenumber":"136",
    "addr:postcode":"bs48 1ap",
    "addr:street":"High Street",
    "iso:country":"GB",
    "sg:address":"136 High Street, Nailsea",
    "sg:city":"Bristol",
    "sg:classifiers":[
        {
            "category":"Shopping",
            "subcategory":"Comic Books",
            "type":"Retail Goods"
        }
    ],
    "sg:postcode":"BS48 1AP",
    "sg:province":"Somerset",
    "sg:tags":[
        "jeweller"
    ],
    "wof:name":"David Christopher Ltd.",
    "wof:placetype":"venue"
},
  "geometry": {"coordinates":[-2.7585310936,51.433380127],"type":"Point"}
}