{
  "type": "Feature",
  "properties": {
    "iso:country":"GB",
    "sg:address":"7a Burnt House Road",
    "sg:city":"Whitley Bay",
    "sg:classifiers":[
        {
            "category":"Personal",
            "subcategory":"Beauty Salon",
            "type":"Services"
        }
    ],
    "sg:postcode":"NE25 9DZ",
    "sg:province":"Northumberland",
    "sg:tags":[
        "unisex",
        "hairdresser"
    ],
    "wof:name":"Hair by Moods",
    "wof:placetype":"venue"
},
  "geometry": {"coordinates":[-1.467118,55.034081],"type":"Point"}
}