{
  "type": "Feature",
  "properties": {
    "addr:full":"25 Cheriton Place Folkestone Kent CT20 2AY",
    "addr:housenumber":"25",
    "addr:postcode":"ct20 2ay",
    "addr:street":"Cheriton Place",
    "iso:country":"GB",
    "sg:address":"25 Cheriton Place",
    "sg:city":"Folkestone",
    "sg:classifiers":[
        {
            "category":"Professional",
            "subcategory":"Lawyer & Legal Services",
            "type":"Services"
        }
    ],
    "sg:phone":"+44 1303 851180",
    "sg:postcode":"CT20 2AY",
    "sg:province":"Kent",
    "sg:tags":[
        "solicitor"
    ],
    "wof:name":"Bushnell & Shortman",
    "wof:placetype":"venue"
},
  "geometry": {"coordinates":[1.1758790016,51.0787582397],"type":"Point"}
}