{
  "type": "Feature",
  "properties": {
    "iso:country":"GB",
    "sg:address":"193 Queens Road",
    "sg:city":"London",
    "sg:classifiers":[
        {
            "category":"Cafe",
            "type":"Food & Drink"
        }
    ],
    "sg:phone":"+44 20 7358 1410",
    "sg:postcode":"SE15 2NG",
    "sg:province":"Greater London",
    "sg:tags":[
        "tea",
        "room"
    ],
    "wof:name":"H's Cafe",
    "wof:placetype":"venue"
},
  "geometry": {"coordinates":[-0.05537,51.473248],"type":"Point"}
}