{
  "type": "Feature",
  "properties": {
    "addr:full":"10 The Crescent York North Yorkshire YO24 1AW",
    "addr:housenumber":"10",
    "addr:postcode":"yo24 1aw",
    "addr:street":"The Crescent",
    "iso:country":"GB",
    "sg:address":"10 The Crescent",
    "sg:city":"York",
    "sg:classifiers":[
        {
            "category":"Banks & Credit Unions",
            "subcategory":"Bureau De Change",
            "type":"Services"
        },
        {
            "category":"Building & Trades",
            "subcategory":"Construction",
            "type":"Services"
        }
    ],
    "sg:phone":"+44 1904 641713",
    "sg:postcode":"YO24 1AW",
    "sg:province":"North Yorkshire",
    "sg:tags":[
        "paint",
        "varnish",
        "decorator",
        "remover",
        "painter"
    ],
    "wof:name":"Yesterday's Furniture",
    "wof:placetype":"venue"
},
  "geometry": {"coordinates":[-1.0937180519,53.9552612305],"type":"Point"}
}