{
  "type": "Feature",
  "properties": {
    "addr:full":"Blackpool Tmc, Faraday Way Blackpool Lancashire FY2 0JW",
    "addr:postcode":"fy2 0jw",
    "addr:street":"Tmc Faraday Way",
    "iso:country":"GB",
    "sg:address":"Blackpool Tmc, Faraday Way",
    "sg:city":"Blackpool",
    "sg:classifiers":[
        {
            "category":"Insurance",
            "subcategory":"Health Insurance",
            "type":"Services"
        }
    ],
    "sg:postcode":"FY2 0JW",
    "sg:province":"Lancashire",
    "sg:tags":[
        "indemnity"
    ],
    "wof:name":"Auto Indemnity Trustees Ltd",
    "wof:placetype":"venue"
},
  "geometry": {"coordinates":[-3.0213398933,53.8526611328],"type":"Point"}
}