{
  "type": "Feature",
  "properties": {
    "addr:full":"113-115 Fonthill Rd Finsbury Park Greater London N4 3HH",
    "addr:housenumber":"113-115",
    "addr:postcode":"n4 3hh",
    "addr:street":"Fonthill Rd",
    "iso:country":"GB",
    "sg:address":"113-115 Fonthill Rd",
    "sg:city":"Finsbury Park",
    "sg:classifiers":[
        {
            "category":"Shopping",
            "subcategory":"Clothing, Apparel, & Fashions",
            "type":"Retail Goods"
        }
    ],
    "sg:phone":"+44 20 7263 7845",
    "sg:postcode":"N4 3HH",
    "sg:province":"Greater London",
    "sg:tags":[
        "clothing",
        "fabric"
    ],
    "wof:name":"Crown Gate Designs Ltd",
    "wof:placetype":"venue"
},
  "geometry": {"coordinates":[-0.1089090034,51.5645217896],"type":"Point"}
}