{
  "type": "Feature",
  "properties": {
    "addr:full":"18 Leather Lane London Greater London EC1N 7SU",
    "addr:housenumber":"18",
    "addr:postcode":"ec1n 7su",
    "addr:street":"Leather Lane",
    "iso:country":"GB",
    "sg:address":"18 Leather Lane",
    "sg:city":"London",
    "sg:classifiers":[
        {
            "category":"Professional",
            "subcategory":"Advertising",
            "type":"Services"
        }
    ],
    "sg:phone":"+44 20 7404 1290",
    "sg:postcode":"EC1N 7SU",
    "sg:province":"Greater London",
    "wof:name":"Visual Aspects Ltd.",
    "wof:placetype":"venue"
},
  "geometry": {"coordinates":[-0.109056,51.519455],"type":"Point"}
}