{
  "type": "Feature",
  "properties": {
    "iso:country":"GB",
    "sg:address":"11 Greenland Road",
    "sg:city":"Barnet",
    "sg:classifiers":[
        {
            "category":"Professional",
            "subcategory":"Secretarial Services",
            "type":"Services"
        }
    ],
    "sg:postcode":"EN5 2AL",
    "sg:province":"Hertfordshire",
    "wof:name":"Business Services Bureau",
    "wof:placetype":"venue"
},
  "geometry": {"coordinates":[-0.219167,51.643955],"type":"Point"}
}