{
  "type": "Feature",
  "properties": {
    "addr:full":"180 South Lambeth Road London Greater London SW8 1QP",
    "addr:housenumber":"180",
    "addr:postcode":"sw8 1qp",
    "addr:street":"South Lambeth Road",
    "iso:country":"GB",
    "sg:address":"180 South Lambeth Road",
    "sg:city":"London",
    "sg:classifiers":[
        {
            "category":"Education",
            "subcategory":"Library",
            "type":"Public Place"
        },
        {
            "category":"Government",
            "subcategory":"Office",
            "type":"Public Place"
        }
    ],
    "sg:phone":"+44 20 7926 0705",
    "sg:postcode":"SW8 1QP",
    "sg:province":"Greater London",
    "sg:tags":[
        "book",
        "local"
    ],
    "wof:name":"South Lambeth Library",
    "wof:placetype":"venue"
},
  "geometry": {"coordinates":[-0.123825,51.479179],"type":"Point"}
}