{
  "type": "Feature",
  "properties": {
    "addr:full":"Railton Road, Woburn Road Industrial Estate, Kempston Bedford Bedfordshire MK42 7PW",
    "addr:postcode":"mk42 7pw",
    "addr:street":"Railton Road Woburn Road Industrial Estate",
    "iso:country":"GB",
    "sg:address":"Railton Road, Woburn Road Industrial Estate, Kempston",
    "sg:city":"Bedford",
    "sg:classifiers":[
        {
            "category":"Wholesale",
            "subcategory":"Books, Periodicals, & Newspapers",
            "type":"Manufacturing & Wholesale Goods"
        }
    ],
    "sg:postcode":"MK42 7PW",
    "sg:province":"Bedfordshire",
    "sg:tags":[
        "publishing"
    ],
    "wof:name":"I F S International Ltd.",
    "wof:placetype":"venue"
},
  "geometry": {"coordinates":[-0.4976809919,52.1057548523],"type":"Point"}
}