{
  "type": "Feature",
  "properties": {
    "addr:full":"26 Murray Street Llanelli Carmarthenshire SA15 1DJ",
    "addr:housenumber":"26",
    "addr:postcode":"sa15 1dj",
    "addr:street":"Murray Street",
    "iso:country":"GB",
    "sg:address":"26 Murray Street",
    "sg:city":"Llanelli",
    "sg:classifiers":[
        {
            "category":"Fast Food",
            "type":"Food & Drink"
        }
    ],
    "sg:phone":"+44 1554 750934",
    "sg:postcode":"SA15 1DJ",
    "sg:province":"Carmarthenshire",
    "sg:tags":[
        "away",
        "take"
    ],
    "wof:name":"Chung San House",
    "wof:placetype":"venue"
},
  "geometry": {"coordinates":[-4.1612319946,51.6804733276],"type":"Point"}
}