{
  "type": "Feature",
  "properties": {
    "addr:full":"3 Crookes Sheffield South Yorkshire S10 1UA",
    "addr:housenumber":"3",
    "addr:postcode":"s10 1ua",
    "addr:street":"Crookes",
    "iso:country":"GB",
    "sg:address":"3 Crookes",
    "sg:city":"Sheffield",
    "sg:classifiers":[
        {
            "category":"Bars & Pubs",
            "type":"Food & Drink"
        }
    ],
    "sg:phone":"+44 114 266 0322",
    "sg:postcode":"S10 1UA",
    "sg:province":"South Yorkshire",
    "sg:tags":[
        "pubs",
        "inn"
    ],
    "wof:name":"Whitbread Hotel Co. Ltd.",
    "wof:placetype":"venue"
},
  "geometry": {"coordinates":[-1.5056530237,53.3813705444],"type":"Point"}
}