{
  "type": "Feature",
  "properties": {
    "addr:full":"9 Nine Mile Ride, Finchampstead Wokingham Berkshire RG40 4QB",
    "addr:housenumber":"9",
    "addr:postcode":"rg40 4qb",
    "addr:street":"Nine Mile Ride",
    "iso:country":"GB",
    "sg:address":"9 Nine Mile Ride, Finchampstead",
    "sg:city":"Wokingham",
    "sg:classifiers":[
        {
            "category":"Autos & Motor Vehicles",
            "subcategory":"Automobile Sales",
            "type":"Retail Goods"
        }
    ],
    "sg:postcode":"RG40 4QB",
    "sg:province":"Berkshire",
    "sg:tags":[
        "car"
    ],
    "wof:name":"Brian McMorrie",
    "wof:placetype":"venue"
},
  "geometry": {"coordinates":[-0.8825830221,51.374671936],"type":"Point"}
}