{
  "type": "Feature",
  "properties": {
    "addr:full":"6 Eastern Industrial Centre, Jackson Close, Drayton Portsmouth Hampshire PO6 1QW",
    "addr:housenumber":"6",
    "addr:postcode":"hampshire po6 1qw",
    "addr:street":"Eastern;Jackson Close",
    "iso:country":"GB",
    "sg:address":"6 Eastern Industrial Centre, Jackson Close, Drayton",
    "sg:city":"Portsmouth",
    "sg:classifiers":[
        {
            "category":"Building & Trades",
            "subcategory":"Plumbing",
            "type":"Services"
        }
    ],
    "sg:phone":"+44 23 9238 8833",
    "sg:postcode":"PO6 1QW",
    "sg:province":"Hampshire",
    "sg:tags":[
        "heating"
    ],
    "wof:name":"Portsmouth Plumbing Supplies Ltd.",
    "wof:placetype":"venue"
},
  "geometry": {"coordinates":[-1.040704,50.846596],"type":"Point"}
}