{
  "type": "Feature",
  "properties": {
    "iso:country":"GB",
    "sg:address":"12 Bridge Street",
    "sg:city":"York",
    "sg:classifiers":[
        {
            "category":"Shopping",
            "subcategory":"Department Store",
            "type":"Retail Goods"
        },
        {
            "category":"Shopping",
            "subcategory":"Clothing, Apparel, & Fashions",
            "type":"Retail Goods"
        }
    ],
    "sg:phone":"+44 1439 770313",
    "sg:postcode":"YO62 5DX",
    "sg:province":"North Yorkshire",
    "sg:tags":[
        "menswear"
    ],
    "wof:name":"D V Townend & Co",
    "wof:placetype":"venue"
},
  "geometry": {"coordinates":[-1.0605479479,54.245475769],"type":"Point"}
}