{
  "type": "Feature",
  "properties": {
    "addr:full":"159 Drummond Street London Greater London NW1 2PB",
    "addr:housenumber":"159",
    "addr:postcode":"nw1 2pb",
    "addr:street":"Drummond Street",
    "iso:country":"GB",
    "sg:address":"159 Drummond Street",
    "sg:city":"London",
    "sg:classifiers":[
        {
            "category":"Restaurant",
            "type":"Food & Drink"
        }
    ],
    "sg:phone":"+44 20 7383 5677",
    "sg:postcode":"NW1 2PB",
    "sg:province":"Greater London",
    "sg:tags":[
        "indian"
    ],
    "wof:name":"Shah Tandoori",
    "wof:placetype":"venue"
},
  "geometry": {"coordinates":[-0.1387940049,51.5263366699],"type":"Point"}
}