{
  "type": "Feature",
  "properties": {
    "addr:full":"Centre Organiser, Gosford Green Centre Coventry Warwickshire CV2 5NA",
    "addr:postcode":"cv2 5na",
    "addr:street":"Gosford Green",
    "iso:country":"GB",
    "sg:address":"Centre Organiser, Gosford Green Centre",
    "sg:city":"Coventry",
    "sg:classifiers":[
        {
            "category":"Organizations",
            "subcategory":"Non-profit Organization",
            "type":"Services"
        }
    ],
    "sg:phone":"+44 24 7645 6477",
    "sg:postcode":"CV2 5NA",
    "sg:province":"Warwickshire",
    "sg:tags":[
        "organisation",
        "voluntary",
        "charity"
    ],
    "wof:name":"British Red Cross",
    "wof:placetype":"venue"
},
  "geometry": {"coordinates":[-1.47041,52.407341],"type":"Point"}
}