{
  "type": "Feature",
  "properties": {
    "addr:full":"Del House, 800 Oxford Avenue Slough Berkshire SL1 4LN",
    "addr:housenumber":"800",
    "addr:postcode":"sl1 4ln",
    "addr:street":"Oxford Avenue",
    "iso:country":"GB",
    "sg:address":"Del House, 800 Oxford Avenue",
    "sg:city":"Slough",
    "sg:classifiers":[
        {
            "category":"Banks & Credit Unions",
            "subcategory":"Investment Brokerage",
            "type":"Services"
        }
    ],
    "sg:postcode":"SL1 4LN",
    "sg:province":"Berkshire",
    "wof:name":"Bearcast Ltd.",
    "wof:placetype":"venue"
},
  "geometry": {"coordinates":[-0.6376199722,51.5261726379],"type":"Point"}
}