{
  "type": "Feature",
  "properties": {
    "addr:full":"Brighton Rd Shoreham By Sea West Sussex BN43 5LD",
    "addr:postcode":"bn43 5ld",
    "addr:street":"Brighton Rd",
    "iso:country":"GB",
    "sg:address":"Brighton Rd",
    "sg:city":"Shoreham By Sea",
    "sg:classifiers":[
        {
            "category":"Bars & Pubs",
            "type":"Food & Drink"
        }
    ],
    "sg:phone":"+44 1273 454077",
    "sg:postcode":"BN43 5LD",
    "sg:province":"West Sussex",
    "sg:tags":[
        "pubs",
        "inn"
    ],
    "wof:name":"Royal Coach The",
    "wof:placetype":"venue"
},
  "geometry": {"coordinates":[-0.2902149856,50.8273849487],"type":"Point"}
}