{
  "type": "Feature",
  "properties": {
    "iso:country":"GB",
    "sg:address":"21 Basford Way",
    "sg:city":"Windsor",
    "sg:classifiers":[
        {
            "category":"Home & Garden",
            "subcategory":"Household Appliances",
            "type":"Retail Goods"
        }
    ],
    "sg:postcode":"SL4 4NF",
    "sg:province":"Berkshire",
    "sg:tags":[
        "cleaner",
        "domestic",
        "vacuum"
    ],
    "wof:name":"Krisons Systems (U K) Ltd",
    "wof:placetype":"venue"
},
  "geometry": {"coordinates":[-0.654158,51.473812],"type":"Point"}
}