{
  "type": "Feature",
  "properties": {
    "addr:full":"Unit 9, Bridge Road Camberley Berkshire GU15 2QR",
    "addr:housenumber":"unit 9",
    "addr:postcode":"gu15 2qr",
    "addr:street":"Bridge Road",
    "iso:country":"GB",
    "sg:address":"Unit 9, Bridge Road",
    "sg:city":"Camberley",
    "sg:classifiers":[
        {
            "category":"Shopping",
            "subcategory":"Computers & Home Electronics",
            "type":"Retail Goods"
        }
    ],
    "sg:phone":"+44 1276 709560",
    "sg:postcode":"GU15 2QR",
    "sg:province":"Berkshire",
    "wof:name":"Off the Wall (Furnishings) Ltd.",
    "wof:placetype":"venue"
},
  "geometry": {"coordinates":[-0.75671,51.327515],"type":"Point"}
}