{
  "type": "Feature",
  "properties": {
    "iso:country":"GB",
    "sg:address":"27a Market Pl",
    "sg:city":"Uttoxeter",
    "sg:classifiers":[
        {
            "category":"Personal",
            "subcategory":"Beauty Salon",
            "type":"Services"
        }
    ],
    "sg:postcode":"ST14 8HL",
    "sg:province":"Derbyshire",
    "sg:tags":[
        "unisex",
        "hairdresser"
    ],
    "wof:name":"Wardman,Carol,",
    "wof:placetype":"venue"
},
  "geometry": {"coordinates":[-1.863808,52.898003],"type":"Point"}
}