{
  "type": "Feature",
  "properties": {
    "iso:country":"GB",
    "sg:address":"The Presbytery, Snow Hill",
    "sg:city":"Wolverhampton",
    "sg:classifiers":[
        {
            "category":"Place Of Worship",
            "type":"Public Place"
        }
    ],
    "sg:phone":"+44 1902 421676",
    "sg:postcode":"WV2 4AD",
    "sg:province":"West Midlands",
    "wof:name":"St Mary's & St John's R C Church",
    "wof:placetype":"venue"
},
  "geometry": {"coordinates":[-2.12581,52.58263],"type":"Point"}
}