{
  "type": "Feature",
  "properties": {
    "iso:country":"GB",
    "sg:address":"Church Balk, Thorne",
    "sg:city":"Doncaster",
    "sg:classifiers":[
        {
            "category":"Social Services",
            "type":"Services"
        },
        {
            "category":"Bus Charters",
            "type":"Transportation"
        }
    ],
    "sg:phone":"+44 1405 741401",
    "sg:postcode":"DN8 5BU",
    "sg:province":"East Riding of Yorkshire",
    "sg:tags":[
        "hire",
        "coach",
        "disability"
    ],
    "wof:name":"Comet Community Transport Ltd.",
    "wof:placetype":"venue"
},
  "geometry": {"coordinates":[-0.961637,53.611591],"type":"Point"}
}