{
  "type": "Feature",
  "properties": {
    "addr:full":"Mains Of Allathan, New Deer Turriff Aberdeenshire AB53 6TL",
    "addr:postcode":"ab53 6tl",
    "iso:country":"GB",
    "sg:address":"Mains Of Allathan, New Deer",
    "sg:city":"Turriff",
    "sg:classifiers":[
        {
            "category":"Farming",
            "subcategory":"Farm",
            "type":"Manufacturing & Wholesale Goods"
        }
    ],
    "sg:postcode":"AB53 6TL",
    "sg:province":"Aberdeenshire",
    "sg:tags":[
        "mixed",
        "crop"
    ],
    "wof:name":"K & A Elphinstone",
    "wof:placetype":"venue"
},
  "geometry": {"coordinates":[-2.193004,57.511147],"type":"Point"}
}