{
  "type": "Feature",
  "properties": {
    "iso:country":"GB",
    "sg:address":"46 Alma Road",
    "sg:city":"Windsor",
    "sg:classifiers":[
        {
            "category":"Building & Trades",
            "subcategory":"Construction",
            "type":"Services"
        }
    ],
    "sg:postcode":"SL4 3HA",
    "sg:province":"Berkshire",
    "sg:tags":[
        "platform",
        "work",
        "scaffolding"
    ],
    "wof:name":"Atom Scaffolding Ltd.",
    "wof:placetype":"venue"
},
  "geometry": {"coordinates":[-0.615996,51.478729],"type":"Point"}
}