{
  "type": "Feature",
  "properties": {
    "addr:full":"13 Mitcham Lane London Greater London SW16 6LQ",
    "addr:housenumber":"13",
    "addr:postcode":"sw16 6lq",
    "addr:street":"Mitcham Lane",
    "iso:country":"GB",
    "sg:address":"13 Mitcham Lane",
    "sg:city":"London",
    "sg:classifiers":[
        {
            "category":"Bars & Pubs",
            "type":"Food & Drink"
        }
    ],
    "sg:phone":"+44 20 8769 3446",
    "sg:postcode":"SW16 6LQ",
    "sg:province":"Greater London",
    "sg:tags":[
        "pubs",
        "inn"
    ],
    "wof:name":"The Manor Arms",
    "wof:placetype":"venue"
},
  "geometry": {"coordinates":[-0.132065,51.428444],"type":"Point"}
}