{
  "type": "Feature",
  "properties": {
    "iso:country":"GB",
    "sg:address":"92 Gardenfield, Skellingthorpe",
    "sg:city":"Lincoln",
    "sg:classifiers":[
        {
            "category":"Personal",
            "subcategory":"Beauty Salon",
            "type":"Services"
        },
        {
            "category":"Personal",
            "subcategory":"Barber",
            "type":"Services"
        }
    ],
    "sg:phone":"+44 1522 687686",
    "sg:postcode":"LN6 5SZ",
    "sg:province":"Lincolnshire",
    "sg:tags":[
        "unisex",
        "hairdresser"
    ],
    "wof:name":"Denise Hair Fashion",
    "wof:placetype":"venue"
},
  "geometry": {"coordinates":[-0.614245,53.228134],"type":"Point"}
}