{
  "type": "Feature",
  "properties": {
    "addr:full":"245 Goldsmith Avenue Southsea Hampshire PO4 0BS",
    "addr:housenumber":"245",
    "addr:postcode":"po4 0bs",
    "addr:street":"Goldsmith Avenue",
    "iso:country":"GB",
    "sg:address":"245 Goldsmith Avenue",
    "sg:city":"Southsea",
    "sg:classifiers":[
        {
            "category":"Building & Trades",
            "subcategory":"Construction",
            "type":"Services"
        }
    ],
    "sg:phone":"+44 23 9279 9251",
    "sg:postcode":"PO4 0BS",
    "sg:province":"Hampshire",
    "sg:tags":[
        "decorator",
        "painter"
    ],
    "wof:name":"The Strip Joint",
    "wof:placetype":"venue"
},
  "geometry": {"coordinates":[-1.075572,50.795868],"type":"Point"}
}