{
  "type": "Feature",
  "properties": {
    "addr:full":"5 Tower Hill, Westwoodside Doncaster Lincolnshire DN9 2DH",
    "addr:housenumber":"5",
    "addr:postcode":"dn9 2dh",
    "addr:street":"Tower Hill Westwoodside",
    "iso:country":"GB",
    "sg:address":"5 Tower Hill, Westwoodside",
    "sg:city":"Doncaster",
    "sg:classifiers":[
        {
            "category":"Professional",
            "subcategory":"Engineering",
            "type":"Services"
        }
    ],
    "sg:postcode":"DN9 2DH",
    "sg:province":"Lincolnshire",
    "sg:tags":[
        "contractor",
        "electrical",
        "engineer"
    ],
    "wof:name":"McCreadie Electrical Ltd",
    "wof:placetype":"venue"
},
  "geometry": {"coordinates":[-0.8560879827,53.4891204834],"type":"Point"}
}