{
  "type": "Feature",
  "properties": {
    "iso:country":"GB",
    "sg:address":"Round House, Gloucester Road",
    "sg:city":"Cheltenham",
    "sg:classifiers":[
        {
            "category":"Shopping",
            "subcategory":"Bicycles & Sporting Goods",
            "type":"Retail Goods"
        },
        {
            "category":"Sports & Exercise",
            "subcategory":"Sports Center",
            "type":"Entertainment"
        }
    ],
    "sg:phone":"+44 1242 256716",
    "sg:postcode":"GL51 8NE",
    "sg:province":"Gloucestershire",
    "sg:tags":[
        "shop",
        "sale"
    ],
    "sg:website":"http://www.jjb.co.uk",
    "wof:name":"J J B Sports Plc",
    "wof:placetype":"venue"
},
  "geometry": {"coordinates":[-2.085408926,51.905620575],"type":"Point"}
}