{
  "type": "Feature",
  "properties": {
    "addr:full":"Flat 2, 19 Percy Circus London Greater London WC1X 9EE",
    "addr:housenumber":"19",
    "addr:postcode":"wc1x 9ee",
    "addr:street":"Percy Circus",
    "iso:country":"GB",
    "sg:address":"Flat 2, 19 Percy Circus",
    "sg:city":"London",
    "sg:classifiers":[
        {
            "category":"Professional",
            "subcategory":"Management & Consulting",
            "type":"Services"
        }
    ],
    "sg:postcode":"WC1X 9EE",
    "sg:province":"Greater London",
    "sg:tags":[
        "consultant",
        "business"
    ],
    "wof:name":"Red Rock London Ltd",
    "wof:placetype":"venue"
},
  "geometry": {"coordinates":[-0.11546,51.530918],"type":"Point"}
}