{
  "type": "Feature",
  "properties": {
    "addr:full":"8 Highfield Rd, Wigginton Tring Buckinghamshire HP23 6EB",
    "addr:housenumber":"8",
    "addr:postcode":"hp23 6eb",
    "addr:street":"Highfield Rd",
    "iso:country":"GB",
    "sg:address":"8 Highfield Rd, Wigginton",
    "sg:city":"Tring",
    "sg:classifiers":[
        {
            "category":"Retail",
            "subcategory":"Repair Shop",
            "type":"Services"
        }
    ],
    "sg:phone":"+44 1442 827546",
    "sg:postcode":"HP23 6EB",
    "sg:province":"Buckinghamshire",
    "sg:tags":[
        "equipment",
        "catering"
    ],
    "wof:name":"Highfield Catering Engineers",
    "wof:placetype":"venue"
},
  "geometry": {"coordinates":[-0.6443349719,51.7832794189],"type":"Point"}
}