{
  "type": "Feature",
  "properties": {
    "iso:country":"GB",
    "sg:address":"52 Topping Street",
    "sg:city":"Blackpool",
    "sg:classifiers":[
        {
            "category":"Real Estate",
            "subcategory":"Real Estate Agent",
            "type":"Services"
        }
    ],
    "sg:phone":"+44 1253 752700",
    "sg:postcode":"FY1 3AQ",
    "sg:province":"Lancashire",
    "wof:name":"K C & J B Allitt",
    "wof:placetype":"venue"
},
  "geometry": {"coordinates":[-3.049806,53.819115],"type":"Point"}
}