{
  "type": "Feature",
  "properties": {
    "addr:full":"6 Fennel Close, Abbeydale Gloucester Gloucestershire GL4 5YB",
    "addr:housenumber":"6",
    "addr:postcode":"gl4 5yb",
    "addr:street":"Fennel Close",
    "iso:country":"GB",
    "sg:address":"6 Fennel Close, Abbeydale",
    "sg:city":"Gloucester",
    "sg:classifiers":[
        {
            "category":"Professional",
            "type":"Services"
        },
        {
            "category":"Social Services",
            "subcategory":"Job Training",
            "type":"Services"
        }
    ],
    "sg:phone":"+44 1452 526170",
    "sg:postcode":"GL4 5YB",
    "sg:province":"Gloucestershire",
    "sg:tags":[
        "translator",
        "interpreter",
        "translation",
        "activity"
    ],
    "wof:name":"Community Translation Service",
    "wof:placetype":"venue"
},
  "geometry": {"coordinates":[-2.211304,51.838646],"type":"Point"}
}