{
  "type": "Feature",
  "properties": {
    "iso:country":"GB",
    "sg:address":"49 Newtown Road",
    "sg:city":"Carlisle",
    "sg:classifiers":[
        {
            "category":"Fast Food",
            "type":"Food & Drink"
        }
    ],
    "sg:phone":"+44 1228 521262",
    "sg:postcode":"CA2 7JA",
    "sg:province":"Cumbria",
    "sg:tags":[
        "away",
        "meal",
        "outlet",
        "take"
    ],
    "wof:name":"Lucky Chop Suey House",
    "wof:placetype":"venue"
},
  "geometry": {"coordinates":[-2.9558200836,54.8941726685],"type":"Point"}
}