{
  "type": "Feature",
  "properties": {
    "addr:full":"27a The Forge, Gallowgate Glasgow Glasgow City G31 4DX",
    "addr:housenumber":"27a",
    "addr:postcode":"g31 4dx",
    "addr:street":"The Forge Gallowgate",
    "iso:country":"GB",
    "sg:address":"27a The Forge, Gallowgate",
    "sg:city":"Glasgow",
    "sg:classifiers":[
        {
            "category":"Travel",
            "subcategory":"Travel Agent",
            "type":"Entertainment"
        }
    ],
    "sg:phone":"+44 141 551 8787",
    "sg:postcode":"G31 4DX",
    "sg:province":"Glasgow City",
    "wof:name":"Lunn Poly",
    "wof:placetype":"venue"
},
  "geometry": {"coordinates":[-4.1986498833,55.8517303467],"type":"Point"}
}