{
  "type": "Feature",
  "properties": {
    "addr:full":"23 Manor View Stevenage Hertfordshire SG2 8PE",
    "addr:housenumber":"23",
    "addr:postcode":"sg2 8pe",
    "addr:street":"Manor View",
    "iso:country":"GB",
    "sg:address":"23 Manor View",
    "sg:city":"Stevenage",
    "sg:classifiers":[
        {
            "category":"Professional",
            "subcategory":"Engineering",
            "type":"Services"
        }
    ],
    "sg:postcode":"SG2 8PE",
    "sg:province":"Hertfordshire",
    "sg:tags":[
        "gas",
        "engineer"
    ],
    "wof:name":"Brightray (Stevenage) Co",
    "wof:placetype":"venue"
},
  "geometry": {"coordinates":[-0.1743430048,51.8863983154],"type":"Point"}
}