{
  "type": "Feature",
  "properties": {
    "addr:full":"Ellenborough Park South Weston Super Mare Somerset BS23 1XW",
    "addr:postcode":"bs23 1xw",
    "iso:country":"GB",
    "sg:address":"Ellenborough Park South",
    "sg:city":"Weston Super Mare",
    "sg:classifiers":[
        {
            "category":"Place Of Worship",
            "type":"Public Place"
        }
    ],
    "sg:phone":"+44 1934 621929",
    "sg:postcode":"BS23 1XW",
    "sg:province":"Somerset",
    "wof:name":"Corpus Christi R C Church",
    "wof:placetype":"venue"
},
  "geometry": {"coordinates":[-2.979239,51.341824],"type":"Point"}
}