{
  "type": "Feature",
  "properties": {
    "iso:country":"GB",
    "sg:address":"87 Hassell Street",
    "sg:city":"Newcastle",
    "sg:classifiers":[
        {
            "category":"Professional",
            "subcategory":"Employment Agencies",
            "type":"Services"
        }
    ],
    "sg:phone":"+44 1782 719900",
    "sg:postcode":"ST5 1AX",
    "sg:province":"Staffordshire",
    "sg:tags":[
        "provider",
        "internet"
    ],
    "wof:name":"Owenstar Ltd.",
    "wof:placetype":"venue"
},
  "geometry": {"coordinates":[-2.220639,53.01162],"type":"Point"}
}