{
  "type": "Feature",
  "properties": {
    "iso:country":"GB",
    "sg:address":"Low Barkhouse",
    "sg:city":"Cockermouth",
    "sg:classifiers":[
        {
            "category":"Farming",
            "subcategory":"Farm",
            "type":"Manufacturing & Wholesale Goods"
        }
    ],
    "sg:postcode":"CA13 9SJ",
    "sg:province":"Cumbria",
    "sg:tags":[
        "mixed",
        "crop"
    ],
    "wof:name":"Thompson,W,& Son",
    "wof:placetype":"venue"
},
  "geometry": {"coordinates":[-3.3659520149,54.663646698],"type":"Point"}
}