{
  "type": "Feature",
  "properties": {
    "addr:full":"Church St Shipston On Stour Warwickshire CV36 4AS",
    "addr:postcode":"cv36 4as",
    "addr:street":"Church St",
    "iso:country":"GB",
    "sg:address":"Church St",
    "sg:city":"Shipston On Stour",
    "sg:classifiers":[
        {
            "category":"Manufacturing",
            "subcategory":"Wood Products",
            "type":"Manufacturing & Wholesale Goods"
        }
    ],
    "sg:phone":"+44 1608 662311",
    "sg:postcode":"CV36 4AS",
    "sg:province":"Warwickshire",
    "sg:tags":[
        "craftsman"
    ],
    "wof:name":"Stour Woodcraft",
    "wof:placetype":"venue"
},
  "geometry": {"coordinates":[-1.624002,52.064877],"type":"Point"}
}