{
  "type": "Feature",
  "properties": {
    "addr:full":"Birchbrook Industrial Park, Lynn Lane Lichfield Staffordshire WS14 0DJ",
    "addr:postcode":"ws14 0dj",
    "addr:street":"Birchbrook Industrial Park Lynn Lane",
    "iso:country":"GB",
    "sg:address":"Birchbrook Industrial Park, Lynn Lane",
    "sg:city":"Lichfield",
    "sg:classifiers":[
        {
            "category":"Shopping",
            "subcategory":"Beauty & Cosmetics",
            "type":"Retail Goods"
        }
    ],
    "sg:phone":"+44 1633 892121",
    "sg:postcode":"WS14 0DJ",
    "sg:province":"Staffordshire",
    "sg:tags":[
        "product"
    ],
    "wof:name":"Sunary Ltd.",
    "wof:placetype":"venue"
},
  "geometry": {"coordinates":[-1.848729,52.639656],"type":"Point"}
}