{
  "type": "Feature",
  "properties": {
    "iso:country":"GB",
    "sg:address":"13 Ashley Rd",
    "sg:city":"Altrincham",
    "sg:classifiers":[
        {
            "category":"Shopping",
            "subcategory":"Books",
            "type":"Retail Goods"
        }
    ],
    "sg:phone":"+44 161 928 0061",
    "sg:postcode":"WA14 2DU",
    "sg:province":"Cheshire",
    "sg:tags":[
        "bookseller"
    ],
    "wof:name":"Lucas Ltd",
    "wof:placetype":"venue"
},
  "geometry": {"coordinates":[-2.3520710468,53.3838882446],"type":"Point"}
}