{
  "type": "Feature",
  "properties": {
    "iso:country":"GB",
    "sg:address":"Airdrie Road",
    "sg:city":"Carluke",
    "sg:classifiers":[
        {
            "category":"Home & Garden",
            "subcategory":"Building Materials",
            "type":"Retail Goods"
        }
    ],
    "sg:phone":"+44 1555 752000",
    "sg:postcode":"ML8 5EW",
    "sg:province":"South Lanarkshire",
    "sg:tags":[
        "window",
        "frame"
    ],
    "wof:name":"J & S McFadyen",
    "wof:placetype":"venue"
},
  "geometry": {"coordinates":[-3.844285,55.743549],"type":"Point"}
}