{
  "type": "Feature",
  "properties": {
    "iso:country":"GB",
    "sg:address":"Unit 22, 33 Hylton Street",
    "sg:city":"Birmingham",
    "sg:classifiers":[
        {
            "category":"Manufacturing",
            "subcategory":"Jewelry",
            "type":"Manufacturing & Wholesale Goods"
        }
    ],
    "sg:phone":"+44 121 554 4422",
    "sg:postcode":"B18 6HJ",
    "sg:province":"West Midlands",
    "sg:tags":[
        "precious",
        "stone",
        "gem"
    ],
    "wof:name":"Levy Gems Co Ltd",
    "wof:placetype":"venue"
},
  "geometry": {"coordinates":[-1.9125560522,52.4910926819],"type":"Point"}
}