{
  "type": "Feature",
  "properties": {
    "addr:full":"1a Felspar Rd, Amington Indust Est Tamworth Staffordshire B77 4DP",
    "addr:housenumber":"1a",
    "addr:postcode":"b77 4dp",
    "addr:street":"Felspar Rd;Indust",
    "iso:country":"GB",
    "sg:address":"1a Felspar Rd, Amington Indust Est",
    "sg:city":"Tamworth",
    "sg:classifiers":[
        {
            "category":"Building & Trades",
            "subcategory":"Electrical",
            "type":"Services"
        }
    ],
    "sg:phone":"+44 1827 63454",
    "sg:postcode":"B77 4DP",
    "sg:province":"Staffordshire",
    "sg:tags":[
        "equipment",
        "purification",
        "air"
    ],
    "wof:name":"Aquamajor",
    "wof:placetype":"venue"
},
  "geometry": {"coordinates":[-1.6539690495,52.6255683899],"type":"Point"}
}