{
  "type": "Feature",
  "properties": {
    "iso:country":"GB",
    "sg:address":"The Point, Town Hall Centre, Leigh Road",
    "sg:city":"Eastleigh",
    "sg:classifiers":[
        {
            "category":"Education",
            "subcategory":"Dance Studio",
            "type":"Public Place"
        }
    ],
    "sg:phone":"+44 23 8065 2333",
    "sg:postcode":"SO50 9DE",
    "sg:province":"Hampshire",
    "sg:tags":[
        "school",
        "dancing"
    ],
    "wof:name":"Eastleigh Dance Project",
    "wof:placetype":"venue"
},
  "geometry": {"coordinates":[-1.350593,50.968323],"type":"Point"}
}