{
  "type": "Feature",
  "properties": {
    "addr:full":"11 Rose Crescent Cambridge Cambridgeshire CB2 3LP",
    "addr:housenumber":"11",
    "addr:postcode":"cb2 3lp",
    "addr:street":"Rose Crescent",
    "iso:country":"GB",
    "sg:address":"11 Rose Crescent",
    "sg:city":"Cambridge",
    "sg:classifiers":[
        {
            "category":"Retail",
            "subcategory":"Repair Shop",
            "type":"Services"
        },
        {
            "category":"Wholesale",
            "subcategory":"Photographic Equipment",
            "type":"Manufacturing & Wholesale Goods"
        }
    ],
    "sg:phone":"+44 1223 364223",
    "sg:postcode":"CB2 3LP",
    "sg:province":"Cambridgeshire",
    "wof:name":"Campkins Camera Centre Ltd.",
    "wof:placetype":"venue"
},
  "geometry": {"coordinates":[0.1192039996,52.2058486938],"type":"Point"}
}