{
  "type": "Feature",
  "properties": {
    "addr:full":"33 Lonon Road, Marks Tey Colchester Essex CO6 1DZ",
    "addr:housenumber":"33",
    "addr:postcode":"co6 1dz",
    "addr:street":"Lonon Road",
    "iso:country":"GB",
    "sg:address":"33 Lonon Road, Marks Tey",
    "sg:city":"Colchester",
    "sg:classifiers":[
        {
            "category":"Wholesale",
            "subcategory":"Machinery & Supplies",
            "type":"Manufacturing & Wholesale Goods"
        }
    ],
    "sg:postcode":"CO6 1DZ",
    "sg:province":"Essex",
    "wof:name":"Master Farm Services (G B) Ltd.",
    "wof:placetype":"venue"
},
  "geometry": {"coordinates":[0.804942,51.880913],"type":"Point"}
}