{
  "type": "Feature",
  "properties": {
    "addr:full":"10-12 John Street Porthcawl Bridgend CF36 3BA",
    "addr:housenumber":"10-12",
    "addr:postcode":"cf36 3ba",
    "addr:street":"John Street",
    "iso:country":"GB",
    "sg:address":"10-12 John Street",
    "sg:city":"Porthcawl",
    "sg:classifiers":[
        {
            "category":"Sports & Exercise",
            "subcategory":"Sports Center",
            "type":"Entertainment"
        }
    ],
    "sg:phone":"+44 1656 782873",
    "sg:postcode":"CF36 3BA",
    "sg:province":"Bridgend",
    "sg:tags":[
        "shop",
        "good"
    ],
    "wof:name":"Bridge's Sports",
    "wof:placetype":"venue"
},
  "geometry": {"coordinates":[-3.704395,51.47654],"type":"Point"}
}