{
  "type": "Feature",
  "properties": {
    "iso:country":"GB",
    "sg:address":"151 North End Rd",
    "sg:city":"Golders Green",
    "sg:classifiers":[
        {
            "category":"Health Services",
            "subcategory":"Dentist",
            "type":"Services"
        }
    ],
    "sg:phone":"+44 20 8731 9020",
    "sg:postcode":"NW11 7HX",
    "sg:province":"Greater London",
    "wof:name":"Dental Practice The",
    "wof:placetype":"venue"
},
  "geometry": {"coordinates":[-0.1859789938,51.5694503784],"type":"Point"}
}