{
  "type": "Feature",
  "properties": {
    "addr:full":"P O Box 142 Wakefield West Yorkshire WF2 0YN",
    "addr:housenumber":"142",
    "addr:postcode":"wf2 0yn",
    "addr:street":"P O Box;West",
    "iso:country":"GB",
    "sg:address":"P O Box 142",
    "sg:city":"Wakefield",
    "sg:classifiers":[
        {
            "category":"Manufacturing",
            "subcategory":"Glass & Minerals",
            "type":"Manufacturing & Wholesale Goods"
        }
    ],
    "sg:phone":"+44 1924 373361",
    "sg:postcode":"WF2 0YN",
    "sg:province":"West Yorkshire",
    "sg:tags":[
        "product"
    ],
    "wof:name":"Wisthoff Gmbh & Co.",
    "wof:placetype":"venue"
},
  "geometry": {"coordinates":[-1.5228480101,53.7099304199],"type":"Point"}
}