{
  "type": "Feature",
  "properties": {
    "iso:country":"GB",
    "sg:address":"14 Tenters Street",
    "sg:city":"Bishop Auckland",
    "sg:classifiers":[
        {
            "category":"Professional",
            "subcategory":"Computer Services",
            "type":"Services"
        }
    ],
    "sg:phone":"+44 1388 605013",
    "sg:postcode":"DL14 7AD",
    "sg:province":"Durham",
    "sg:tags":[
        "information"
    ],
    "wof:name":"South West Durham Community Health Council",
    "wof:placetype":"venue"
},
  "geometry": {"coordinates":[-1.677029,54.663876],"type":"Point"}
}