{
  "type": "Feature",
  "properties": {
    "addr:full":"129 Sheen Lane London Greater London SW14 8AE",
    "addr:housenumber":"129",
    "addr:postcode":"sw14 8ae",
    "addr:street":"Sheen Lane",
    "iso:country":"GB",
    "sg:address":"129 Sheen Lane",
    "sg:city":"London",
    "sg:classifiers":[
        {
            "category":"Home & Garden",
            "subcategory":"Home Furnishings",
            "type":"Retail Goods"
        }
    ],
    "sg:phone":"+44 20 8296 9300",
    "sg:postcode":"SW14 8AE",
    "sg:province":"Greater London",
    "sg:tags":[
        "blind",
        "curtain",
        "fitting"
    ],
    "wof:name":"C J R Soft Furnishings",
    "wof:placetype":"venue"
},
  "geometry": {"coordinates":[-0.2662169933,51.4646339417],"type":"Point"}
}