{
  "type": "Feature",
  "properties": {
    "iso:country":"GB",
    "sg:address":"30 Kingston Road",
    "sg:city":"Portsmouth",
    "sg:classifiers":[
        {
            "category":"Social Services",
            "subcategory":"Child Care",
            "type":"Services"
        }
    ],
    "sg:phone":"+44 23 9235 8841",
    "sg:postcode":"PO1 5RZ",
    "sg:province":"Hampshire",
    "sg:tags":[
        "baby",
        "sitter"
    ],
    "wof:name":"Shamrock Babysitting Service",
    "wof:placetype":"venue"
},
  "geometry": {"coordinates":[-1.077249,50.807468],"type":"Point"}
}