{
  "type": "Feature",
  "properties": {
    "iso:country":"GB",
    "sg:address":"59 New Road",
    "sg:city":"Holt",
    "sg:classifiers":[
        {
            "category":"Building & Trades",
            "subcategory":"Plumbing",
            "type":"Services"
        }
    ],
    "sg:postcode":"NR25 7PA",
    "sg:province":"Norfolk",
    "sg:tags":[
        "heating"
    ],
    "wof:name":"Malcolm H Scargill",
    "wof:placetype":"venue"
},
  "geometry": {"coordinates":[1.0196679831,52.9515380859],"type":"Point"}
}