{
  "type": "Feature",
  "properties": {
    "addr:full":"109 B Hamilton Road Felixstowe Suffolk IP11 7BL",
    "addr:housenumber":"109 b",
    "addr:postcode":"ip11 7bl",
    "addr:street":"Hamilton Road",
    "iso:country":"GB",
    "sg:address":"109 B Hamilton Road",
    "sg:city":"Felixstowe",
    "sg:classifiers":[
        {
            "category":"Freight",
            "type":"Transportation"
        }
    ],
    "sg:phone":"+44 1394 277700",
    "sg:postcode":"IP11 7BL",
    "sg:province":"Suffolk",
    "sg:tags":[
        "forwarders"
    ],
    "wof:name":"Gearing International Ltd.",
    "wof:placetype":"venue"
},
  "geometry": {"coordinates":[1.351853,51.96439],"type":"Point"}
}