{
  "type": "Feature",
  "properties": {
    "iso:country":"GB",
    "sg:address":"26 Vetch Close",
    "sg:city":"Gloucester",
    "sg:classifiers":[
        {
            "category":"Building & Trades",
            "subcategory":"Plumbing",
            "type":"Services"
        }
    ],
    "sg:postcode":"GL4 6YG",
    "sg:province":"Gloucestershire",
    "sg:tags":[
        "central",
        "heating"
    ],
    "wof:name":"D Heating",
    "wof:placetype":"venue"
},
  "geometry": {"coordinates":[-2.226037,51.841496],"type":"Point"}
}