{
  "type": "Feature",
  "properties": {
    "iso:country":"GB",
    "sg:address":"4 Garden Croft, Weston Rhyn",
    "sg:city":"Oswestry",
    "sg:classifiers":[
        {
            "category":"Home & Garden",
            "subcategory":"Carpets & Floor Coverings",
            "type":"Retail Goods"
        }
    ],
    "sg:postcode":"SY10 7SG",
    "sg:province":"Shropshire",
    "sg:tags":[
        "carpets",
        "rug",
        "matting"
    ],
    "wof:name":"Bob Law Carpets",
    "wof:placetype":"venue"
},
  "geometry": {"coordinates":[-3.0615580082,52.9160804749],"type":"Point"}
}