{
  "type": "Feature",
  "properties": {
    "iso:country":"GB",
    "sg:address":"Lansdown Properties Ltd, 11 Alma Vale Road",
    "sg:city":"Bristol",
    "sg:classifiers":[
        {
            "category":"Real Estate",
            "subcategory":"Developer",
            "type":"Services"
        }
    ],
    "sg:postcode":"BS8 2HL",
    "sg:province":"City of Bristol",
    "sg:tags":[
        "property"
    ],
    "wof:name":"Frenchay Manor Park (The Rowans) Ltd",
    "wof:placetype":"venue"
},
  "geometry": {"coordinates":[-2.6143100262,51.4626693726],"type":"Point"}
}