{
  "type": "Feature",
  "properties": {
    "iso:country":"GB",
    "sg:address":"New La",
    "sg:city":"Thornton Cleveleys",
    "sg:classifiers":[
        {
            "category":"Building & Trades",
            "subcategory":"Construction",
            "type":"Services"
        }
    ],
    "sg:phone":"+44 1253 826536",
    "sg:postcode":"FY5 5NN",
    "sg:province":"Lancashire",
    "sg:tags":[
        "window",
        "replacement"
    ],
    "wof:name":"Anglian Home Improvements",
    "wof:placetype":"venue"
},
  "geometry": {"coordinates":[-3.003825,53.862057],"type":"Point"}
}