{
  "type": "Feature",
  "properties": {
    "iso:country":"GB",
    "sg:address":"3 Old Church Road, Bell Grn",
    "sg:city":"Coventry",
    "sg:classifiers":[
        {
            "category":"Community Center",
            "type":"Public Place"
        },
        {
            "category":"Organizations",
            "subcategory":"Community Association",
            "type":"Services"
        }
    ],
    "sg:phone":"+44 24 7668 8086",
    "sg:postcode":"CV6 7BZ",
    "sg:province":"Warwickshire",
    "sg:tags":[
        "associations",
        "centre",
        "housing",
        "co-operatives",
        "trust",
        "societies"
    ],
    "wof:name":"Bell Green Community Centre",
    "wof:placetype":"venue"
},
  "geometry": {"coordinates":[-1.483331,52.439411],"type":"Point"}
}