{
  "type": "Feature",
  "properties": {
    "addr:full":"55-56-66 New Public Mkt, Duke St Barrow-in-furness Cumbria LA14 1RW",
    "addr:housenumber":"55-56-66",
    "addr:postcode":"la14 1rw",
    "addr:street":"Duke St",
    "iso:country":"GB",
    "sg:address":"55-56-66 New Public Mkt, Duke St",
    "sg:city":"Barrow-in-furness",
    "sg:classifiers":[
        {
            "category":"Food & Beverages",
            "subcategory":"Fruits & Vegetables",
            "type":"Retail Goods"
        }
    ],
    "sg:postcode":"LA14 1RW",
    "sg:province":"Cumbria",
    "sg:tags":[
        "greengrocer"
    ],
    "wof:name":"Preston,Stephen,",
    "wof:placetype":"venue"
},
  "geometry": {"coordinates":[-3.225847,54.111088],"type":"Point"}
}