{
  "type": "Feature",
  "properties": {
    "addr:full":"182 High Road Loughton Essex IG10 1DN",
    "addr:housenumber":"182",
    "addr:postcode":"ig10 1dn",
    "addr:street":"High Road",
    "iso:country":"GB",
    "sg:address":"182 High Road",
    "sg:city":"Loughton",
    "sg:classifiers":[
        {
            "category":"Professional",
            "subcategory":"Printing & Photocopies",
            "type":"Services"
        }
    ],
    "sg:phone":"+44 20 8502 1177",
    "sg:postcode":"IG10 1DN",
    "sg:province":"Essex",
    "sg:tags":[
        "duplicating",
        "copying"
    ],
    "wof:name":"Economy Print (Loughton) Ltd.",
    "wof:placetype":"venue"
},
  "geometry": {"coordinates":[0.0538,51.646141],"type":"Point"}
}