{
  "type": "Feature",
  "properties": {
    "iso:country":"GB",
    "sg:address":"Unit 7 Oakland Industrial Estate, Lower Road",
    "sg:city":"Cannock",
    "sg:classifiers":[
        {
            "category":"Manufacturing",
            "subcategory":"Electronics",
            "type":"Manufacturing & Wholesale Goods"
        }
    ],
    "sg:postcode":"WS12 5UZ",
    "sg:province":"Staffordshire",
    "sg:tags":[
        "printed",
        "circuit"
    ],
    "wof:name":"Laser Circuits",
    "wof:placetype":"venue"
},
  "geometry": {"coordinates":[-1.962696,52.710758],"type":"Point"}
}