{
  "type": "Feature",
  "properties": {
    "iso:country":"GB",
    "sg:address":"99d Lord Street",
    "sg:city":"Grimsby",
    "sg:classifiers":[
        {
            "category":"Personal",
            "type":"Services"
        },
        {
            "category":"Retail",
            "subcategory":"Auto Rental",
            "type":"Services"
        }
    ],
    "sg:postcode":"DN31 2NF",
    "sg:province":"Lincolnshire",
    "sg:tags":[
        "car",
        "wedding"
    ],
    "wof:name":"N S White Wedding Cars",
    "wof:placetype":"venue"
},
  "geometry": {"coordinates":[-0.0954369977,53.5682525635],"type":"Point"}
}