{
  "type": "Feature",
  "properties": {
    "addr:full":"16b Heath Road, Great Brickhill Milton Keynes Bedfordshire MK17 9AL",
    "addr:housenumber":"16b",
    "addr:postcode":"mk17 9al",
    "addr:street":"Heath Road",
    "iso:country":"GB",
    "sg:address":"16b Heath Road, Great Brickhill",
    "sg:city":"Milton Keynes",
    "sg:classifiers":[
        {
            "category":"Professional",
            "type":"Services"
        }
    ],
    "sg:phone":"+44 7973 443348",
    "sg:postcode":"MK17 9AL",
    "sg:province":"Bedfordshire",
    "sg:tags":[
        "repair",
        "tech",
        "maintenance"
    ],
    "wof:name":"Market Research Analysis Ltd.",
    "wof:placetype":"venue"
},
  "geometry": {"coordinates":[-0.6800670028,51.9626045227],"type":"Point"}
}