{
  "type": "Feature",
  "properties": {
    "iso:country":"GB",
    "sg:address":"Unit 1 Gateway Park, Newcombe Way Orton Southgate",
    "sg:city":"Peterborough",
    "sg:classifiers":[
        {
            "category":"Professional",
            "subcategory":"Business Services",
            "type":"Services"
        }
    ],
    "sg:phone":"+44 1733 232929",
    "sg:postcode":"PE2 6SF",
    "sg:province":"Cambridgeshire",
    "sg:tags":[
        "import",
        "export",
        "agent"
    ],
    "wof:name":"United Overseas Holdings Ltd.",
    "wof:placetype":"venue"
},
  "geometry": {"coordinates":[-0.319989,52.537899],"type":"Point"}
}