{
  "type": "Feature",
  "properties": {
    "iso:country":"GB",
    "sg:address":"193 Western Rd",
    "sg:city":"Brighton",
    "sg:classifiers":[
        {
            "category":"Shopping",
            "subcategory":"Clothing, Apparel, & Fashions",
            "type":"Retail Goods"
        }
    ],
    "sg:phone":"+44 1273 327770",
    "sg:postcode":"BN1 2BA",
    "sg:province":"East Sussex",
    "sg:tags":[
        "shop"
    ],
    "wof:name":"Tammy Girl",
    "wof:placetype":"venue"
},
  "geometry": {"coordinates":[-0.144965,50.823746],"type":"Point"}
}