{
  "type": "Feature",
  "properties": {
    "addr:full":"Bordesley Hall, The Holloway, Alvechurch Birmingham Worcestershire B48 7QB",
    "addr:postcode":"b48 7qb",
    "addr:street":"The;Alvechurch",
    "iso:country":"GB",
    "sg:address":"Bordesley Hall, The Holloway, Alvechurch",
    "sg:city":"Birmingham",
    "sg:classifiers":[
        {
            "category":"Home & Garden",
            "subcategory":"Household Appliances",
            "type":"Retail Goods"
        }
    ],
    "sg:phone":"+44 1527 63314",
    "sg:postcode":"B48 7QB",
    "sg:province":"Worcestershire",
    "sg:tags":[
        "gas"
    ],
    "wof:name":"Rinnai Corporation European Liason Office",
    "wof:placetype":"venue"
},
  "geometry": {"coordinates":[-1.9616140127,52.3511695862],"type":"Point"}
}