{
  "type": "Feature",
  "properties": {
    "addr:full":"13 The Quadrant, Kilburn Lane London Greater London W10 4AL",
    "addr:housenumber":"13",
    "addr:postcode":"w10 4al",
    "addr:street":"The Quadrant Kilburn Lane",
    "iso:country":"GB",
    "sg:address":"13 The Quadrant, Kilburn Lane",
    "sg:city":"London",
    "sg:classifiers":[
        {
            "category":"Personal",
            "subcategory":"Beauty Salon",
            "type":"Services"
        }
    ],
    "sg:phone":"+44 20 8960 6740",
    "sg:postcode":"W10 4AL",
    "sg:province":"Greater London",
    "sg:tags":[
        "unisex",
        "hairdresser"
    ],
    "wof:name":"Hair by Charles Delores",
    "wof:placetype":"venue"
},
  "geometry": {"coordinates":[-0.2155400068,51.5298500061],"type":"Point"}
}