{
  "type": "Feature",
  "properties": {
    "addr:full":"Mulberry St Liverpool Merseyside L7 7EF",
    "addr:postcode":"l7 7ef",
    "addr:street":"Mulberry St",
    "iso:country":"GB",
    "sg:address":"Mulberry St",
    "sg:city":"Liverpool",
    "sg:classifiers":[
        {
            "category":"Community Center",
            "subcategory":"Youth",
            "type":"Public Place"
        }
    ],
    "sg:phone":"+44 151 709 3855",
    "sg:postcode":"L7 7EF",
    "sg:province":"Merseyside",
    "sg:tags":[
        "organisation",
        "centre"
    ],
    "wof:name":"Rodney Youth Centre Ltd",
    "wof:placetype":"venue"
},
  "geometry": {"coordinates":[-2.967296,53.400711],"type":"Point"}
}