{
  "type": "Feature",
  "properties": {
    "addr:full":"York Road Leeds West Yorkshire LS9 9NT",
    "addr:postcode":"ls9 9nt",
    "addr:street":"York Road",
    "iso:country":"GB",
    "sg:address":"York Road",
    "sg:city":"Leeds",
    "sg:classifiers":[
        {
            "category":"Travel",
            "subcategory":"Travel Agent",
            "type":"Entertainment"
        },
        {
            "category":"Organizations",
            "subcategory":"Membership Organization",
            "type":"Services"
        }
    ],
    "sg:phone":"+44 113 248 0887",
    "sg:postcode":"LS9 9NT",
    "sg:province":"West Yorkshire",
    "sg:tags":[
        "club",
        "social"
    ],
    "wof:name":"The Irish Centre",
    "wof:placetype":"venue"
},
  "geometry": {"coordinates":[-1.497934,53.80135],"type":"Point"}
}