{
  "type": "Feature",
  "properties": {
    "addr:full":"Crookhurst Farm, Rainford Rd Wigan Lancashire WN5 7PS",
    "addr:postcode":"wn5 7ps",
    "addr:street":"Rainford Rd",
    "iso:country":"GB",
    "sg:address":"Crookhurst Farm, Rainford Rd",
    "sg:city":"Wigan",
    "sg:classifiers":[
        {
            "category":"Building & Trades",
            "subcategory":"Construction",
            "type":"Services"
        }
    ],
    "sg:phone":"+44 1744 895997",
    "sg:postcode":"WN5 7PS",
    "sg:province":"Lancashire",
    "sg:tags":[
        "builder"
    ],
    "wof:name":"Robert May",
    "wof:placetype":"venue"
},
  "geometry": {"coordinates":[-2.711024,53.49979],"type":"Point"}
}