{
  "type": "Feature",
  "properties": {
    "addr:full":"175 New Road Ascot Berkshire SL5 8PX",
    "addr:housenumber":"175",
    "addr:postcode":"sl5 8px",
    "addr:street":"New Road",
    "iso:country":"GB",
    "sg:address":"175 New Road",
    "sg:city":"Ascot",
    "sg:classifiers":[
        {
            "category":"Place Of Worship",
            "type":"Public Place"
        },
        {
            "category":"Education",
            "subcategory":"Preschool",
            "type":"Public Place"
        }
    ],
    "sg:phone":"+44 1344 883792",
    "sg:postcode":"SL5 8PX",
    "sg:province":"Berkshire",
    "sg:tags":[
        "pre-school",
        "playgroups"
    ],
    "wof:name":"Ascot baptist Church",
    "wof:placetype":"venue"
},
  "geometry": {"coordinates":[-0.685654,51.42189],"type":"Point"}
}