{
  "type": "Feature",
  "properties": {
    "addr:full":"Unit 6 Hadfield Industrial Estate, Waterside Glossop Derbyshire SK13 1BS",
    "addr:housenumber":"unit 6;estate",
    "addr:postcode":"sk13 1bs",
    "addr:street":"Industrial",
    "iso:country":"GB",
    "sg:address":"Unit 6 Hadfield Industrial Estate, Waterside",
    "sg:city":"Glossop",
    "sg:classifiers":[
        {
            "category":"Retail",
            "subcategory":"Auto Repair",
            "type":"Services"
        }
    ],
    "sg:phone":"+44 1457 863795",
    "sg:postcode":"SK13 1BS",
    "sg:province":"Derbyshire",
    "sg:tags":[
        "modification",
        "garage"
    ],
    "wof:name":"B & B Auto Engineers",
    "wof:placetype":"venue"
},
  "geometry": {"coordinates":[-1.94657,53.443336],"type":"Point"}
}