{
  "type": "Feature",
  "properties": {
    "iso:country":"GB",
    "sg:address":"11b North Claremont St",
    "sg:city":"Glasgow",
    "sg:classifiers":[
        {
            "category":"Health Services",
            "subcategory":"Health Practitioner",
            "type":"Services"
        }
    ],
    "sg:postcode":"G3 7NG",
    "sg:province":"Glasgow City",
    "sg:tags":[
        "acupuncture"
    ],
    "wof:name":"Robinson,M,",
    "wof:placetype":"venue"
},
  "geometry": {"coordinates":[-4.280529,55.866581],"type":"Point"}
}