{
  "type": "Feature",
  "properties": {
    "iso:country":"GB",
    "sg:address":"Unit 1 Crosspost Industrial Esta, Te Cowfold Road, Bolney",
    "sg:city":"Haywards Heath",
    "sg:classifiers":[
        {
            "category":"Manufacturing",
            "subcategory":"Building Materials",
            "type":"Manufacturing & Wholesale Goods"
        }
    ],
    "sg:phone":"+44 1444 882106",
    "sg:postcode":"RH17 5QU",
    "sg:province":"East Sussex",
    "sg:tags":[
        "tile",
        "mnfrs"
    ],
    "wof:name":"Have-A-Go Ltd.",
    "wof:placetype":"venue"
},
  "geometry": {"coordinates":[-0.2044519931,50.9905815125],"type":"Point"}
}