{
  "type": "Feature",
  "properties": {
    "iso:country":"GB",
    "sg:address":"Chritchon House, Edgington Way",
    "sg:city":"Sidcup",
    "sg:classifiers":[
        {
            "category":"Professional",
            "subcategory":"Engineering",
            "type":"Services"
        }
    ],
    "sg:postcode":"DA14 5BH",
    "sg:province":"Kent",
    "sg:tags":[
        "contractor",
        "electrical",
        "engineer"
    ],
    "wof:name":"K H Electrics",
    "wof:placetype":"venue"
},
  "geometry": {"coordinates":[0.1155499965,51.4133453369],"type":"Point"}
}