{
  "type": "Feature",
  "properties": {
    "addr:full":"Roselake Ho, Hudds Vale Rd Bristol City of Bristol BS5 7HY",
    "addr:postcode":"bs5 7hy",
    "addr:street":"Vale Rd",
    "iso:country":"GB",
    "sg:address":"Roselake Ho, Hudds Vale Rd",
    "sg:city":"Bristol",
    "sg:classifiers":[
        {
            "category":"Building & Trades",
            "subcategory":"Landscaping Services",
            "type":"Services"
        }
    ],
    "sg:phone":"+44 117 939 4423",
    "sg:postcode":"BS5 7HY",
    "sg:province":"City of Bristol",
    "sg:tags":[
        "designer",
        "architect",
        "landscape"
    ],
    "wof:name":"Nova Landscapes",
    "wof:placetype":"venue"
},
  "geometry": {"coordinates":[-2.5410590172,51.4626541138],"type":"Point"}
}