{
  "type": "Feature",
  "properties": {
    "addr:full":"Chowley Oak, Chowley Oak Lane, Tattenhall Chester Cheshire CH3 9EX",
    "addr:postcode":"ch3 9ex",
    "addr:street":"Chowley;Chowley Oak Lane",
    "iso:country":"GB",
    "sg:address":"Chowley Oak, Chowley Oak Lane, Tattenhall",
    "sg:city":"Chester",
    "sg:classifiers":[
        {
            "category":"Health Services",
            "subcategory":"Clinic",
            "type":"Services"
        }
    ],
    "sg:phone":"+44 1829 771111",
    "sg:postcode":"CH3 9EX",
    "sg:province":"Cheshire",
    "sg:tags":[
        "medical"
    ],
    "wof:name":"Nucletron U K Ltd.",
    "wof:placetype":"venue"
},
  "geometry": {"coordinates":[-2.7820429802,53.1042861938],"type":"Point"}
}