{
  "type": "Feature",
  "properties": {
    "addr:full":"11a Grange Pl Kilmarnock East Ayrshire KA1 2AB",
    "addr:housenumber":"11a",
    "addr:postcode":"ka1 2ab",
    "addr:street":"Grange Pl",
    "iso:country":"GB",
    "sg:address":"11a Grange Pl",
    "sg:city":"Kilmarnock",
    "sg:classifiers":[
        {
            "category":"Health Services",
            "subcategory":"Clinic",
            "type":"Services"
        }
    ],
    "sg:phone":"+44 1563 525207",
    "sg:postcode":"KA1 2AB",
    "sg:province":"East Ayrshire",
    "sg:tags":[
        "aromatherapy"
    ],
    "wof:name":"Inglis Rhona Aromatherapy",
    "wof:placetype":"venue"
},
  "geometry": {"coordinates":[-4.517379,55.611061],"type":"Point"}
}