{
  "type": "Feature",
  "properties": {
    "iso:country":"GB",
    "sg:address":"Tonbridge & Malling Constituency, Palace Of Westminster",
    "sg:city":"Westminster",
    "sg:classifiers":[
        {
            "category":"Government",
            "subcategory":"Office",
            "type":"Public Place"
        }
    ],
    "sg:phone":"+44 20 7219 3000",
    "sg:postcode":"SW1A 2PW",
    "sg:province":"Greater London",
    "sg:tags":[
        "mp",
        "meps"
    ],
    "wof:name":"Sir John Stanley",
    "wof:placetype":"venue"
},
  "geometry": {"coordinates":[-0.1238939986,51.5279045105],"type":"Point"}
}