{
  "type": "Feature",
  "properties": {
    "addr:full":"100 Gladstone Road Altrincham Cheshire WA14 1NL",
    "addr:housenumber":"100",
    "addr:postcode":"wa14 1nl",
    "addr:street":"Gladstone Road",
    "iso:country":"GB",
    "sg:address":"100 Gladstone Road",
    "sg:city":"Altrincham",
    "sg:classifiers":[
        {
            "category":"Communications",
            "subcategory":"Film & Video Production",
            "type":"Services"
        }
    ],
    "sg:phone":"+44 161 941 3441",
    "sg:postcode":"WA14 1NL",
    "sg:province":"Cheshire",
    "sg:tags":[
        "tv",
        "studio"
    ],
    "wof:name":"T V The & Video Clinic",
    "wof:placetype":"venue"
},
  "geometry": {"coordinates":[-2.344488,53.395569],"type":"Point"}
}