{
  "type": "Feature",
  "properties": {
    "iso:country":"GB",
    "sg:address":"1 Pitlessie Road, Ladybank",
    "sg:city":"Cupar",
    "sg:classifiers":[
        {
            "category":"Home & Garden",
            "subcategory":"Building Materials",
            "type":"Retail Goods"
        }
    ],
    "sg:phone":"+44 1337 831699",
    "sg:postcode":"KY15 7SQ",
    "sg:province":"Fife",
    "sg:tags":[
        "fencing"
    ],
    "wof:name":"Keith Garry Fencing",
    "wof:placetype":"venue"
},
  "geometry": {"coordinates":[-3.125374,56.278324],"type":"Point"}
}