{
  "type": "Feature",
  "properties": {
    "iso:country":"GB",
    "sg:address":"9-11 King Street",
    "sg:city":"Huddersfield",
    "sg:classifiers":[
        {
            "category":"Sports & Exercise",
            "subcategory":"Gym",
            "type":"Entertainment"
        }
    ],
    "sg:phone":"+44 1484 559970",
    "sg:postcode":"HD1 2ER",
    "sg:province":"West Yorkshire",
    "sg:tags":[
        "fitness",
        "health",
        "centre"
    ],
    "wof:name":"Reviva",
    "wof:placetype":"venue"
},
  "geometry": {"coordinates":[-1.782091,53.646004],"type":"Point"}
}