{
  "type": "Feature",
  "properties": {
    "addr:full":"Albert Street Halifax West Yorkshire HX1 5NW",
    "addr:postcode":"hx1 5nw",
    "addr:street":"Albert Street",
    "iso:country":"GB",
    "sg:address":"Albert Street",
    "sg:city":"Halifax",
    "sg:classifiers":[
        {
            "category":"Professional",
            "type":"Services"
        }
    ],
    "sg:phone":"+44 1422 352521",
    "sg:postcode":"HX1 5NW",
    "sg:province":"West Yorkshire",
    "sg:tags":[
        "caterer"
    ],
    "wof:name":"M Qureshi",
    "wof:placetype":"venue"
},
  "geometry": {"coordinates":[-1.871059,53.724144],"type":"Point"}
}