{
  "type": "Feature",
  "properties": {
    "addr:full":"118 Arbury Road Nuneaton Leicestershire CV10 7NB",
    "addr:housenumber":"118",
    "addr:postcode":"cv10 7nb",
    "addr:street":"Arbury Road",
    "iso:country":"GB",
    "sg:address":"118 Arbury Road",
    "sg:city":"Nuneaton",
    "sg:classifiers":[
        {
            "category":"Real Estate",
            "subcategory":"Real Estate Services",
            "type":"Services"
        },
        {
            "category":"Real Estate",
            "subcategory":"Real Estate Agent",
            "type":"Services"
        }
    ],
    "sg:phone":"+44 24 7634 3683",
    "sg:postcode":"CV10 7NB",
    "sg:province":"Leicestershire",
    "sg:tags":[
        "management"
    ],
    "wof:name":"S E Property Services",
    "wof:placetype":"venue"
},
  "geometry": {"coordinates":[-1.500115,52.515324],"type":"Point"}
}