{
  "type": "Feature",
  "properties": {
    "addr:full":"99 Walford Road Birmingham West Midlands B11 1NP",
    "addr:housenumber":"99",
    "addr:postcode":"b11 1np",
    "addr:street":"Walford Road",
    "iso:country":"GB",
    "sg:address":"99 Walford Road",
    "sg:city":"Birmingham",
    "sg:classifiers":[
        {
            "category":"Shopping",
            "subcategory":"Clothing, Apparel, & Fashions",
            "type":"Retail Goods"
        },
        {
            "category":"Personal",
            "subcategory":"Beauty Salon",
            "type":"Services"
        }
    ],
    "sg:phone":"+44 121 773 2122",
    "sg:postcode":"B11 1NP",
    "sg:province":"West Midlands",
    "sg:tags":[
        "shop"
    ],
    "wof:name":"Pearl",
    "wof:placetype":"venue"
},
  "geometry": {"coordinates":[-1.8667360544,52.4592285156],"type":"Point"}
}