{
  "type": "Feature",
  "properties": {
    "iso:country":"GB",
    "sg:address":"Northgate, Pinchbeck",
    "sg:city":"Spalding",
    "sg:classifiers":[
        {
            "category":"Wholesale",
            "subcategory":"Fruits & Vegetables",
            "type":"Manufacturing & Wholesale Goods"
        }
    ],
    "sg:phone":"+44 1775 640210",
    "sg:postcode":"PE11 3TB",
    "sg:province":"Lincolnshire",
    "wof:name":"F Tipler & Sons (Pinchbeck) Ltd.",
    "wof:placetype":"venue"
},
  "geometry": {"coordinates":[-0.1612509936,52.8165283203],"type":"Point"}
}