{
  "type": "Feature",
  "properties": {
    "iso:country":"GB",
    "sg:address":"54 Feckenham Road",
    "sg:city":"Redditch",
    "sg:classifiers":[
        {
            "category":"Building & Trades",
            "subcategory":"Plumbing",
            "type":"Services"
        }
    ],
    "sg:postcode":"B97 5AL",
    "sg:province":"Warwickshire",
    "sg:tags":[
        "heating"
    ],
    "wof:name":"B Evans & Son",
    "wof:placetype":"venue"
},
  "geometry": {"coordinates":[-1.9552710056,52.2934188843],"type":"Point"}
}