{
  "type": "Feature",
  "properties": {
    "addr:full":"Dewberry Lane, Radcliffe-on-trent Nottingham Nottinghamshire NG12 2JH",
    "addr:postcode":"ng12 2jh",
    "addr:street":"Dewberry Lane",
    "iso:country":"GB",
    "sg:address":"Dewberry Lane, Radcliffe-on-trent",
    "sg:city":"Nottingham",
    "sg:classifiers":[
        {
            "category":"Sports & Exercise",
            "subcategory":"Golf",
            "type":"Entertainment"
        }
    ],
    "sg:phone":"+44 115 933 3000",
    "sg:postcode":"NG12 2JH",
    "sg:province":"Nottinghamshire",
    "sg:tags":[
        "club",
        "course"
    ],
    "wof:name":"Radcliffe On Trent Golf Club",
    "wof:placetype":"venue"
},
  "geometry": {"coordinates":[-1.025529,52.941711],"type":"Point"}
}