{
  "type": "Feature",
  "properties": {
    "addr:full":"5 Lathkill Dale Swadlincote Derbyshire DE11 9RL",
    "addr:housenumber":"5",
    "addr:postcode":"de11 9rl",
    "addr:street":"Lathkill Dale",
    "iso:country":"GB",
    "sg:address":"5 Lathkill Dale",
    "sg:city":"Swadlincote",
    "sg:classifiers":[
        {
            "category":"Health Services",
            "subcategory":"Podiatrist",
            "type":"Services"
        }
    ],
    "sg:phone":"+44 1283 552535",
    "sg:postcode":"DE11 9RL",
    "sg:province":"Derbyshire",
    "sg:tags":[
        "podiatrists",
        "chiropodist"
    ],
    "wof:name":"Holford",
    "wof:placetype":"venue"
},
  "geometry": {"coordinates":[-1.576093,52.766781],"type":"Point"}
}