{
  "type": "Feature",
  "properties": {
    "addr:full":"Nine Acres Farm, Water Stratford Road, Stratford Buckingham Buckinghamshire MK18 5DU",
    "addr:postcode":"mk18 5du",
    "addr:street":"Water Stratford Road",
    "iso:country":"GB",
    "sg:address":"Nine Acres Farm, Water Stratford Road, Stratford",
    "sg:city":"Buckingham",
    "sg:classifiers":[
        {
            "category":"Building & Trades",
            "subcategory":"Construction",
            "type":"Services"
        }
    ],
    "sg:postcode":"MK18 5DU",
    "sg:province":"Buckinghamshire",
    "sg:tags":[
        "concrete",
        "contractor"
    ],
    "wof:name":"G & K Paving",
    "wof:placetype":"venue"
},
  "geometry": {"coordinates":[-1.0503690243,52.0060348511],"type":"Point"}
}