{
  "type": "Feature",
  "properties": {
    "addr:full":"Wester Carnie Bungalow Perth Perth and Kinross PH2 0PT",
    "addr:postcode":"ph2 0pt",
    "addr:street":"Wester;Perth",
    "iso:country":"GB",
    "sg:address":"Wester Carnie Bungalow",
    "sg:city":"Perth",
    "sg:classifiers":[
        {
            "category":"Home & Garden",
            "subcategory":"Building Materials",
            "type":"Retail Goods"
        }
    ],
    "sg:phone":"+44 1738 730255",
    "sg:postcode":"PH2 0PT",
    "sg:province":"Perth and Kinross",
    "sg:tags":[
        "fencing"
    ],
    "wof:name":"R D Leadbetter",
    "wof:placetype":"venue"
},
  "geometry": {"coordinates":[-3.4324140549,56.3960533142],"type":"Point"}
}