{
  "type": "Feature",
  "properties": {
    "iso:country":"GB",
    "sg:address":"16 Trevone Avenue, Stapleford",
    "sg:city":"Nottingham",
    "sg:classifiers":[
        {
            "category":"Recreation",
            "subcategory":"Amusement Park",
            "type":"Entertainment"
        },
        {
            "category":"Shopping",
            "subcategory":"Party Supplies",
            "type":"Retail Goods"
        }
    ],
    "sg:postcode":"NG9 7HJ",
    "sg:province":"Nottinghamshire",
    "sg:tags":[
        "inflatables",
        "bouncy",
        "castle",
        "activity"
    ],
    "wof:name":"SANDIACRE LEISURE",
    "wof:placetype":"venue"
},
  "geometry": {"coordinates":[-1.269873,52.927734],"type":"Point"}
}