{
  "type": "Feature",
  "properties": {
    "iso:country":"GB",
    "sg:address":"Bulls Place, Newark Road, Swinderby",
    "sg:city":"Lincoln",
    "sg:classifiers":[
        {
            "category":"Professional",
            "subcategory":"Engineering",
            "type":"Services"
        }
    ],
    "sg:phone":"+44 1522 866060",
    "sg:postcode":"LN6 9HN",
    "sg:province":"Lincolnshire",
    "sg:tags":[
        "civil",
        "engineer"
    ],
    "wof:name":"A C Moore Constructions Ltd",
    "wof:placetype":"venue"
},
  "geometry": {"coordinates":[-0.6233350039,53.1769752502],"type":"Point"}
}