{
  "type": "Feature",
  "properties": {
    "iso:country":"GB",
    "sg:address":"63 Vista Road",
    "sg:city":"Clacton-on-sea",
    "sg:classifiers":[
        {
            "category":"Professional",
            "subcategory":"Art Services",
            "type":"Services"
        }
    ],
    "sg:phone":"+44 1255 222606",
    "sg:postcode":"CO15 6DQ",
    "sg:province":"Essex",
    "sg:tags":[
        "consultant",
        "design"
    ],
    "wof:name":"Brian White Design",
    "wof:placetype":"venue"
},
  "geometry": {"coordinates":[1.158895,51.795151],"type":"Point"}
}