{
  "type": "Feature",
  "properties": {
    "iso:country":"GB",
    "sg:address":"16 Darley, Worsborough Dale",
    "sg:city":"Barnsley",
    "sg:classifiers":[
        {
            "category":"Building & Trades",
            "subcategory":"Cleaning & Sanitation",
            "type":"Services"
        },
        {
            "category":"Home & Garden",
            "subcategory":"Carpets & Floor Coverings",
            "type":"Retail Goods"
        }
    ],
    "sg:phone":"+44 1226 247196",
    "sg:postcode":"S70 4RB",
    "sg:province":"South Yorkshire",
    "sg:tags":[
        "cleaner",
        "upholstery",
        "commercial",
        "contracting"
    ],
    "wof:name":"J & J Cleaning Services",
    "wof:placetype":"venue"
},
  "geometry": {"coordinates":[-1.451551,53.534409],"type":"Point"}
}