{
  "type": "Feature",
  "properties": {
    "addr:full":"14 East Oval Northampton Northamptonshire NN5 7NR",
    "addr:housenumber":"14",
    "addr:postcode":"nn5 7nr",
    "addr:street":"East Oval",
    "iso:country":"GB",
    "sg:address":"14 East Oval",
    "sg:city":"Northampton",
    "sg:classifiers":[
        {
            "category":"Professional",
            "type":"Services"
        }
    ],
    "sg:phone":"+44 1604 582154",
    "sg:postcode":"NN5 7NR",
    "sg:province":"Northamptonshire",
    "sg:tags":[
        "caterer"
    ],
    "wof:name":"The Tuck in Catering Co",
    "wof:placetype":"venue"
},
  "geometry": {"coordinates":[-0.9180719852,52.2579307556],"type":"Point"}
}