{
  "type": "Feature",
  "properties": {
    "iso:country":"GB",
    "sg:address":"20 Meadow Road",
    "sg:city":"Glasgow",
    "sg:classifiers":[
        {
            "category":"Retail",
            "subcategory":"Auto Repair",
            "type":"Services"
        }
    ],
    "sg:phone":"+44 141 334 6261",
    "sg:postcode":"G11 6HX",
    "sg:province":"Glasgow City",
    "sg:tags":[
        "modification",
        "garage",
        "related"
    ],
    "wof:name":"Frema Motor Repairs",
    "wof:placetype":"venue"
},
  "geometry": {"coordinates":[-4.316163,55.869282],"type":"Point"}
}