{
  "type": "Feature",
  "properties": {
    "addr:full":"9-13 Blackburn Rd Darwen Lancashire BB3 1EJ",
    "addr:housenumber":"9-13",
    "addr:postcode":"bb3 1ej",
    "addr:street":"Blackburn Rd",
    "iso:country":"GB",
    "sg:address":"9-13 Blackburn Rd",
    "sg:city":"Darwen",
    "sg:classifiers":[
        {
            "category":"Restaurant",
            "type":"Food & Drink"
        }
    ],
    "sg:phone":"+44 1254 762500",
    "sg:postcode":"BB3 1EJ",
    "sg:province":"Lancashire",
    "sg:tags":[
        "indian"
    ],
    "wof:name":"Taj Mahal",
    "wof:placetype":"venue"
},
  "geometry": {"coordinates":[-2.4752058983,53.7025871277],"type":"Point"}
}