{
  "type": "Feature",
  "properties": {
    "addr:full":"Chevithorne Farm, Chevithorne Tiverton Devon EX16 7PU",
    "addr:postcode":"ex16 7pu",
    "addr:street":"Chevithorne",
    "iso:country":"GB",
    "sg:address":"Chevithorne Farm, Chevithorne",
    "sg:city":"Tiverton",
    "sg:classifiers":[
        {
            "category":"Farming",
            "subcategory":"Livestock Farm",
            "type":"Manufacturing & Wholesale Goods"
        }
    ],
    "sg:phone":"+44 1884 252529",
    "sg:postcode":"EX16 7PU",
    "sg:province":"Devon",
    "sg:tags":[
        "others"
    ],
    "wof:name":"H W Gale & Son",
    "wof:placetype":"venue"
},
  "geometry": {"coordinates":[-3.457974,50.929428],"type":"Point"}
}