{
  "type": "Feature",
  "properties": {
    "addr:full":"40 Market Place Wokingham Berkshire RG11 1AT",
    "addr:housenumber":"40",
    "addr:postcode":"rg11 1at",
    "addr:street":"Market Place",
    "iso:country":"GB",
    "sg:address":"40 Market Place",
    "sg:city":"Wokingham",
    "sg:classifiers":[
        {
            "category":"Shopping",
            "subcategory":"Pharmacy",
            "type":"Retail Goods"
        }
    ],
    "sg:phone":"+44 118 978 4294",
    "sg:postcode":"RG11 1AT",
    "sg:province":"Berkshire",
    "sg:tags":[
        "pharmacist",
        "chemist"
    ],
    "wof:name":"Boots the Chemists",
    "wof:placetype":"venue"
},
  "geometry": {"coordinates":[-0.8334649801,51.4103088379],"type":"Point"}
}