{
  "type": "Feature",
  "properties": {
    "addr:full":"336 Mayplace Road East Bexleyheath Kent DA7 6JT",
    "addr:housenumber":"336",
    "addr:postcode":"da7 6jt",
    "addr:street":"Mayplace Road East",
    "iso:country":"GB",
    "sg:address":"336 Mayplace Road East",
    "sg:city":"Bexleyheath",
    "sg:classifiers":[
        {
            "category":"Building & Trades",
            "subcategory":"Plumbing",
            "type":"Services"
        }
    ],
    "sg:phone":"+44 1322 553920",
    "sg:postcode":"DA7 6JT",
    "sg:province":"Kent",
    "sg:tags":[
        "plumber",
        "heating"
    ],
    "wof:name":"A B R PLUMBING",
    "wof:placetype":"venue"
},
  "geometry": {"coordinates":[0.1579699963,51.4593391418],"type":"Point"}
}