{
  "type": "Feature",
  "properties": {
    "addr:full":"35 Hills Lane Shrewsbury Shropshire SY1 1QU",
    "addr:housenumber":"35",
    "addr:postcode":"sy1 1qu",
    "addr:street":"Hills Lane",
    "iso:country":"GB",
    "sg:address":"35 Hills Lane",
    "sg:city":"Shrewsbury",
    "sg:classifiers":[
        {
            "category":"Professional",
            "subcategory":"Lawyer & Legal Services",
            "type":"Services"
        }
    ],
    "sg:phone":"+44 1743 241429",
    "sg:postcode":"SY1 1QU",
    "sg:province":"Shropshire",
    "sg:tags":[
        "solicitor"
    ],
    "wof:name":"Howells Williams Solicitors",
    "wof:placetype":"venue"
},
  "geometry": {"coordinates":[-2.756498,52.708832],"type":"Point"}
}