{
  "type": "Feature",
  "properties": {
    "iso:country":"GB",
    "sg:address":"436 Whitehorse Rd",
    "sg:city":"Thornton Heath",
    "sg:classifiers":[
        {
            "category":"Personal",
            "type":"Services"
        }
    ],
    "sg:phone":"+44 20 8665 1695",
    "sg:postcode":"CR7 8SB",
    "sg:province":"Surrey",
    "sg:tags":[
        "dressmaker"
    ],
    "wof:name":"First Class Concept Designs",
    "wof:placetype":"venue"
},
  "geometry": {"coordinates":[-0.092492,51.397182],"type":"Point"}
}