{
  "type": "Feature",
  "properties": {
    "addr:full":"1 Cambridge Road, Granby Industrial Estate Weymouth Dorset DT4 9TJ",
    "addr:housenumber":"1;estate",
    "addr:postcode":"dt4 9tj",
    "addr:street":"Cambridge Road;Industrial",
    "iso:country":"GB",
    "sg:address":"1 Cambridge Road, Granby Industrial Estate",
    "sg:city":"Weymouth",
    "sg:classifiers":[
        {
            "category":"Shopping",
            "subcategory":"Tobacco",
            "type":"Retail Goods"
        },
        {
            "category":"Food & Beverages",
            "subcategory":"Bakery",
            "type":"Retail Goods"
        },
        {
            "category":"Wholesale",
            "subcategory":"Vending Machines",
            "type":"Manufacturing & Wholesale Goods"
        }
    ],
    "sg:postcode":"DT4 9TJ",
    "sg:province":"Dorset",
    "sg:tags":[
        "shop",
        "confectioner",
        "baker",
        "tobacconist",
        "sale"
    ],
    "wof:name":"J Cox & Sons",
    "wof:placetype":"venue"
},
  "geometry": {"coordinates":[-2.487497,50.612495],"type":"Point"}
}