{
  "type": "Feature",
  "properties": {
    "iso:country":"GB",
    "sg:address":"45 Broome Avenue, East Goscote",
    "sg:city":"Leicester",
    "sg:classifiers":[
        {
            "category":"Professional",
            "subcategory":"Advertising",
            "type":"Services"
        },
        {
            "category":"Manufacturing",
            "subcategory":"Signs",
            "type":"Manufacturing & Wholesale Goods"
        }
    ],
    "sg:phone":"+44 116 260 6779",
    "sg:postcode":"LE7 3SA",
    "sg:province":"Leicestershire",
    "sg:tags":[
        "writer",
        "signwriters"
    ],
    "wof:name":"J & B S Sargeant",
    "wof:placetype":"venue"
},
  "geometry": {"coordinates":[-1.0496629477,52.7166213989],"type":"Point"}
}