{
  "type": "Feature",
  "properties": {
    "addr:full":"10 Burghley Road London Greater London NW5 1UE",
    "addr:housenumber":"10",
    "addr:postcode":"nw5 1ue",
    "addr:street":"Burghley Road",
    "iso:country":"GB",
    "sg:address":"10 Burghley Road",
    "sg:city":"London",
    "sg:classifiers":[
        {
            "category":"Wholesale",
            "subcategory":"Books, Periodicals, & Newspapers",
            "type":"Manufacturing & Wholesale Goods"
        }
    ],
    "sg:phone":"+44 20 7482 2390",
    "sg:postcode":"NW5 1UE",
    "sg:province":"Greater London",
    "sg:tags":[
        "publishing"
    ],
    "wof:name":"Libris Ltd.",
    "wof:placetype":"venue"
},
  "geometry": {"coordinates":[-0.1418379992,51.553730011],"type":"Point"}
}