{
  "type": "Feature",
  "properties": {
    "iso:country":"GB",
    "sg:address":"103 Denmark Street",
    "sg:city":"Diss",
    "sg:classifiers":[
        {
            "category":"Personal",
            "subcategory":"Beauty Salon",
            "type":"Services"
        },
        {
            "category":"Personal",
            "subcategory":"Barber",
            "type":"Services"
        }
    ],
    "sg:phone":"+44 1379 652511",
    "sg:postcode":"IP22 4LF",
    "sg:province":"Norfolk",
    "sg:tags":[
        "unisex",
        "hairdresser"
    ],
    "wof:name":"Linda Owen Haircutters",
    "wof:placetype":"venue"
},
  "geometry": {"coordinates":[1.106112,52.377129],"type":"Point"}
}