{
  "type": "Feature",
  "properties": {
    "addr:full":"1 Castle Street Canterbury Kent CT1 2QF",
    "addr:housenumber":"1",
    "addr:postcode":"ct1 2qf",
    "addr:street":"Castle Street",
    "iso:country":"GB",
    "sg:address":"1 Castle Street",
    "sg:city":"Canterbury",
    "sg:classifiers":[
        {
            "category":"Real Estate",
            "subcategory":"Surveying",
            "type":"Services"
        },
        {
            "category":"Real Estate",
            "subcategory":"Real Estate Agent",
            "type":"Services"
        }
    ],
    "sg:phone":"+44 1227 453530",
    "sg:postcode":"CT1 2QF",
    "sg:province":"Kent",
    "sg:tags":[
        "surveyor",
        "valuer"
    ],
    "wof:name":"Caxtons Commercial Ltd.",
    "wof:placetype":"venue"
},
  "geometry": {"coordinates":[1.078426,51.277519],"type":"Point"}
}