{
  "type": "Feature",
  "properties": {
    "addr:full":"Shinfield, Poffley End Witney Oxfordshire OX29 9UW",
    "addr:postcode":"ox29 9uw",
    "addr:street":"End",
    "iso:country":"GB",
    "sg:address":"Shinfield, Poffley End",
    "sg:city":"Witney",
    "sg:classifiers":[
        {
            "category":"Shopping",
            "subcategory":"Pets & Pet Supplies",
            "type":"Retail Goods"
        },
        {
            "category":"Shopping",
            "subcategory":"Florist",
            "type":"Retail Goods"
        }
    ],
    "sg:postcode":"OX29 9UW",
    "sg:province":"Oxfordshire",
    "sg:tags":[
        "cemetery",
        "crematorium"
    ],
    "wof:name":"M & J Harris",
    "wof:placetype":"venue"
},
  "geometry": {"coordinates":[-1.4823,51.809872],"type":"Point"}
}