{
  "type": "Feature",
  "properties": {
    "addr:full":"Unit 10 Brownhills Business Park, Canal Lane Stoke-on-trent Staffordshire ST6 4RP",
    "addr:housenumber":"unit 10",
    "addr:postcode":"st6 4rp",
    "addr:street":"Brownhills Business Park Canal Lane",
    "iso:country":"GB",
    "sg:address":"Unit 10 Brownhills Business Park, Canal Lane",
    "sg:city":"Stoke-on-trent",
    "sg:classifiers":[
        {
            "category":"Building & Trades",
            "subcategory":"Construction",
            "type":"Services"
        }
    ],
    "sg:phone":"+44 1782 813414",
    "sg:postcode":"ST6 4RP",
    "sg:province":"Staffordshire",
    "sg:tags":[
        "builder"
    ],
    "wof:name":"J Littleton & Co. Ltd.",
    "wof:placetype":"venue"
},
  "geometry": {"coordinates":[-2.2115740776,53.0526885986],"type":"Point"}
}