{
  "type": "Feature",
  "properties": {
    "iso:country":"GB",
    "sg:address":"22 Bond Street",
    "sg:city":"Wakefield",
    "sg:classifiers":[
        {
            "category":"Building & Trades",
            "subcategory":"Construction",
            "type":"Services"
        }
    ],
    "sg:phone":"+44 1924 374818",
    "sg:postcode":"WF1 2QP",
    "sg:province":"West Yorkshire",
    "sg:tags":[
        "contractor",
        "paving",
        "driveway"
    ],
    "wof:name":"Grass Concrete Ltd.",
    "wof:placetype":"venue"
},
  "geometry": {"coordinates":[-1.5030039549,53.6858177185],"type":"Point"}
}