{
  "type": "Feature",
  "properties": {
    "addr:full":"Unit 5 Upper Mall, Pride Hill Centre Shrewsbury Shropshire SY1 1BU",
    "addr:housenumber":"unit 5",
    "addr:postcode":"sy1 1bu",
    "addr:street":"Upper Mall Pride Hill Centre",
    "iso:country":"GB",
    "sg:address":"Unit 5 Upper Mall, Pride Hill Centre",
    "sg:city":"Shrewsbury",
    "sg:classifiers":[
        {
            "category":"Shopping",
            "subcategory":"Optician",
            "type":"Retail Goods"
        }
    ],
    "sg:phone":"+44 1743 231111",
    "sg:postcode":"SY1 1BU",
    "sg:province":"Shropshire",
    "wof:name":"Vision Express (Uk)",
    "wof:placetype":"venue"
},
  "geometry": {"coordinates":[-2.751284,52.706566],"type":"Point"}
}