{
  "type": "Feature",
  "properties": {
    "addr:full":"15 Northampton Rd Olney Buckinghamshire MK46 4EY",
    "addr:housenumber":"15",
    "addr:postcode":"mk46 4ey",
    "addr:street":"Northampton Rd",
    "iso:country":"GB",
    "sg:address":"15 Northampton Rd",
    "sg:city":"Olney",
    "sg:classifiers":[
        {
            "category":"Building & Trades",
            "subcategory":"Construction",
            "type":"Services"
        }
    ],
    "sg:phone":"+44 1234 712634",
    "sg:postcode":"MK46 4EY",
    "sg:province":"Buckinghamshire",
    "sg:tags":[
        "builder"
    ],
    "wof:name":"R F Lay & Son",
    "wof:placetype":"venue"
},
  "geometry": {"coordinates":[-0.6628950238,52.173664093],"type":"Point"}
}