{
  "type": "Feature",
  "properties": {
    "addr:full":"17 Faulkner St, Hoole Chester Cheshire CH2 3BD",
    "addr:housenumber":"17",
    "addr:postcode":"ch2 3bd",
    "addr:street":"Faulkner St",
    "iso:country":"GB",
    "sg:address":"17 Faulkner St, Hoole",
    "sg:city":"Chester",
    "sg:classifiers":[
        {
            "category":"Real Estate",
            "subcategory":"Surveying",
            "type":"Services"
        }
    ],
    "sg:phone":"+44 1244 340220",
    "sg:postcode":"CH2 3BD",
    "sg:province":"Cheshire",
    "sg:tags":[
        "surveyor",
        "valuer"
    ],
    "wof:name":"Thomas C Adams",
    "wof:placetype":"venue"
},
  "geometry": {"coordinates":[-2.87688,53.19968],"type":"Point"}
}