{
  "type": "Feature",
  "properties": {
    "addr:full":"Frimley Green Youth Centre, Wharfenden Way, Frimley Green Camberley Hampshire GU16 6PJ",
    "addr:postcode":"gu16 6pj",
    "addr:street":"Frimley;Wharfenden Way",
    "iso:country":"GB",
    "sg:address":"Frimley Green Youth Centre, Wharfenden Way, Frimley Green",
    "sg:city":"Camberley",
    "sg:classifiers":[
        {
            "category":"Organizations",
            "subcategory":"Non-profit Organization",
            "type":"Services"
        }
    ],
    "sg:phone":"+44 1252 837978",
    "sg:postcode":"GU16 6PJ",
    "sg:province":"Hampshire",
    "sg:tags":[
        "organisation",
        "voluntary",
        "charity"
    ],
    "wof:name":"Frimley & Camberley Age Concern",
    "wof:placetype":"venue"
},
  "geometry": {"coordinates":[-0.73398,51.3091011047],"type":"Point"}
}