{
  "type": "Feature",
  "properties": {
    "iso:country":"GB",
    "sg:address":"9 Mornington Road",
    "sg:city":"Southport",
    "sg:classifiers":[
        {
            "category":"Sports & Exercise",
            "subcategory":"Gym",
            "type":"Entertainment"
        }
    ],
    "sg:postcode":"PR9 0TS",
    "sg:province":"Lancashire",
    "sg:tags":[
        "fitness",
        "health",
        "centre"
    ],
    "wof:name":"Fitness One Health Centre",
    "wof:placetype":"venue"
},
  "geometry": {"coordinates":[-2.996701,53.647053],"type":"Point"}
}