{
  "type": "Feature",
  "properties": {
    "iso:country":"GB",
    "sg:address":"Colomendy House, 1 Vale Rd",
    "sg:city":"Denbigh",
    "sg:classifiers":[
        {
            "category":"Shopping",
            "subcategory":"Photographic Equipment",
            "type":"Retail Goods"
        }
    ],
    "sg:phone":"+44 1745 815030",
    "sg:postcode":"LL16 3DF",
    "sg:province":"Conwy",
    "wof:name":"The Society Of Wedding & Portrait Photographers",
    "wof:placetype":"venue"
},
  "geometry": {"coordinates":[-3.410379,53.187168],"type":"Point"}
}