{
  "type": "Feature",
  "properties": {
    "addr:full":"Clarendon House, 81 Moseley Street Manchester Greater Manchester M2 3LQ",
    "addr:housenumber":"81",
    "addr:postcode":"m2 3lq",
    "addr:street":"Moseley Street",
    "iso:country":"GB",
    "sg:address":"Clarendon House, 81 Moseley Street",
    "sg:city":"Manchester",
    "sg:classifiers":[
        {
            "category":"Professional",
            "subcategory":"Employment Agencies",
            "type":"Services"
        }
    ],
    "sg:postcode":"M2 3LQ",
    "sg:province":"Greater Manchester",
    "sg:tags":[
        "consultant"
    ],
    "wof:name":"Michael Page Finance",
    "wof:placetype":"venue"
},
  "geometry": {"coordinates":[-2.2425670624,53.4782867432],"type":"Point"}
}