{
  "type": "Feature",
  "properties": {
    "iso:country":"GB",
    "sg:address":"46 Court St",
    "sg:city":"Dundee",
    "sg:classifiers":[
        {
            "category":"Personal",
            "subcategory":"Beauty Salon",
            "type":"Services"
        }
    ],
    "sg:postcode":"DD3 7QT",
    "sg:province":"Dundee City",
    "sg:tags":[
        "unisex",
        "hairdresser"
    ],
    "wof:name":"Robb,C F,",
    "wof:placetype":"venue"
},
  "geometry": {"coordinates":[-2.963558,56.474777],"type":"Point"}
}