{
  "type": "Feature",
  "properties": {
    "addr:full":"539 Queensferry Road Edinburgh City of Edinburgh EH4 7QE",
    "addr:housenumber":"539",
    "addr:postcode":"eh4 7qe",
    "addr:street":"Queensferry Road",
    "iso:country":"GB",
    "sg:address":"539 Queensferry Road",
    "sg:city":"Edinburgh",
    "sg:classifiers":[
        {
            "category":"Retail",
            "subcategory":"Veterinary Services",
            "type":"Services"
        }
    ],
    "sg:phone":"+44 131 539 7539",
    "sg:postcode":"EH4 7QE",
    "sg:province":"City of Edinburgh",
    "sg:tags":[
        "surgeon"
    ],
    "wof:name":"Oak Tree Veterinary Centre",
    "wof:placetype":"venue"
},
  "geometry": {"coordinates":[-3.2980139256,55.9601821899],"type":"Point"}
}