{
  "type": "Feature",
  "properties": {
    "addr:full":"Highfield, Faversham Rd, Lenham Maidstone Kent ME17 2EX",
    "addr:postcode":"me17 2ex",
    "addr:street":"Faversham Rd",
    "iso:country":"GB",
    "sg:address":"Highfield, Faversham Rd, Lenham",
    "sg:city":"Maidstone",
    "sg:classifiers":[
        {
            "category":"Sports & Exercise",
            "subcategory":"Gym",
            "type":"Entertainment"
        }
    ],
    "sg:phone":"+44 1622 858431",
    "sg:postcode":"ME17 2EX",
    "sg:province":"Kent",
    "sg:tags":[
        "fitness",
        "health",
        "centre"
    ],
    "wof:name":"Swami Dev Murti Yoga Centre",
    "wof:placetype":"venue"
},
  "geometry": {"coordinates":[0.710315,51.240082],"type":"Point"}
}