{
  "type": "Feature",
  "properties": {
    "iso:country":"GB",
    "sg:address":"2 Ettrick Pl",
    "sg:city":"Glasgow",
    "sg:classifiers":[
        {
            "category":"Retail",
            "subcategory":"Storage",
            "type":"Services"
        }
    ],
    "sg:phone":"+44 141 636 9494",
    "sg:postcode":"G43 1UB",
    "sg:province":"Glasgow City",
    "sg:tags":[
        "household",
        "removal"
    ],
    "wof:name":"City Removals Glasgow",
    "wof:placetype":"venue"
},
  "geometry": {"coordinates":[-4.287117,55.825558],"type":"Point"}
}