{
  "type": "Feature",
  "properties": {
    "addr:full":"158 Baslow Road Sheffield Derbyshire S17 4DR",
    "addr:housenumber":"158",
    "addr:postcode":"s17 4dr",
    "addr:street":"Baslow Road",
    "iso:country":"GB",
    "sg:address":"158 Baslow Road",
    "sg:city":"Sheffield",
    "sg:classifiers":[
        {
            "category":"Shopping",
            "subcategory":"Clothing, Apparel, & Fashions",
            "type":"Retail Goods"
        }
    ],
    "sg:postcode":"S17 4DR",
    "sg:province":"Derbyshire",
    "sg:tags":[
        "shop",
        "hat"
    ],
    "wof:name":"Felicity Hat Hire",
    "wof:placetype":"venue"
},
  "geometry": {"coordinates":[-1.5308530331,53.316242218],"type":"Point"}
}