{
  "type": "Feature",
  "properties": {
    "iso:country":"GB",
    "sg:address":"22a Congleton Road",
    "sg:city":"Sandbach",
    "sg:classifiers":[
        {
            "category":"Autos & Motor Vehicles",
            "subcategory":"Automobile Sales",
            "type":"Retail Goods"
        },
        {
            "category":"Retail",
            "subcategory":"Auto Repair",
            "type":"Services"
        }
    ],
    "sg:phone":"+44 1270 766700",
    "sg:postcode":"CW11 1HJ",
    "sg:province":"Cheshire",
    "sg:tags":[
        "modification",
        "car",
        "related",
        "garage"
    ],
    "wof:name":"Smithy Garage",
    "wof:placetype":"venue"
},
  "geometry": {"coordinates":[-2.3624269962,53.1454772949],"type":"Point"}
}