{
  "type": "Feature",
  "properties": {
    "addr:full":"Maybush Corner, Romsey Road Southampton Hampshire SO16 9GJ",
    "addr:postcode":"so16 9gj",
    "addr:street":"Romsey Road",
    "iso:country":"GB",
    "sg:address":"Maybush Corner, Romsey Road",
    "sg:city":"Southampton",
    "sg:classifiers":[
        {
            "category":"Food & Beverages",
            "subcategory":"Supermarket",
            "type":"Retail Goods"
        }
    ],
    "sg:phone":"+44 23 8077 2552",
    "sg:postcode":"SO16 9GJ",
    "sg:province":"Hampshire",
    "wof:name":"Co-Op Retail Services",
    "wof:placetype":"venue"
},
  "geometry": {"coordinates":[-1.4481300116,50.9312210083],"type":"Point"}
}