{
  "type": "Feature",
  "properties": {
    "iso:country":"GB",
    "sg:address":"Home Farm Cottage, Oare",
    "sg:city":"Marlborough",
    "sg:classifiers":[
        {
            "category":"Building & Trades",
            "subcategory":"Construction",
            "type":"Services"
        }
    ],
    "sg:phone":"+44 836335175",
    "sg:postcode":"SN8 4JA",
    "sg:province":"Berkshire",
    "sg:tags":[
        "builder"
    ],
    "wof:name":"Knight Builders",
    "wof:placetype":"venue"
},
  "geometry": {"coordinates":[-1.773879,51.367203],"type":"Point"}
}