{
  "type": "Feature",
  "properties": {
    "addr:full":"Fraser Road Havant Hampshire PO9 3EF",
    "addr:postcode":"po9 3ef",
    "addr:street":"Fraser Road",
    "iso:country":"GB",
    "sg:address":"Fraser Road",
    "sg:city":"Havant",
    "sg:classifiers":[
        {
            "category":"Education",
            "subcategory":"School",
            "type":"Public Place"
        }
    ],
    "sg:phone":"+44 23 9248 3336",
    "sg:postcode":"PO9 3EF",
    "sg:province":"Hampshire",
    "sg:tags":[
        "local",
        "authority"
    ],
    "wof:name":"Bidbury Infant School",
    "wof:placetype":"venue"
},
  "geometry": {"coordinates":[-0.992299,50.857044],"type":"Point"}
}