{
  "type": "Feature",
  "properties": {
    "iso:country":"GB",
    "sg:address":"75 Ambleside Drive",
    "sg:city":"Worcester",
    "sg:classifiers":[
        {
            "category":"Cinema",
            "subcategory":"Movie Rental",
            "type":"Entertainment"
        }
    ],
    "sg:phone":"+44 1905 723220",
    "sg:postcode":"WR4 9DA",
    "sg:province":"Worcestershire",
    "sg:tags":[
        "video",
        "library"
    ],
    "wof:name":"Blockbuster Video Express",
    "wof:placetype":"venue"
},
  "geometry": {"coordinates":[-2.190263,52.20311],"type":"Point"}
}