{
  "type": "Feature",
  "properties": {
    "iso:country":"GB",
    "sg:address":"36 Church St",
    "sg:city":"Rugby",
    "sg:classifiers":[
        {
            "category":"Retail",
            "subcategory":"Repair Shop",
            "type":"Services"
        }
    ],
    "sg:phone":"+44 1788 541494",
    "sg:postcode":"CV21 3PU",
    "sg:province":"Warwickshire",
    "sg:tags":[
        "radio",
        "television",
        "video"
    ],
    "wof:name":"Audio Market",
    "wof:placetype":"venue"
},
  "geometry": {"coordinates":[-1.2588750124,52.3725357056],"type":"Point"}
}