{
  "type": "Feature",
  "properties": {
    "addr:full":"356 Crofton Road Orpington Kent BR6 8NN",
    "addr:housenumber":"356",
    "addr:postcode":"br6 8nn",
    "addr:street":"Crofton Road",
    "iso:country":"GB",
    "sg:address":"356 Crofton Road",
    "sg:city":"Orpington",
    "sg:classifiers":[
        {
            "category":"Food & Beverages",
            "subcategory":"Meat & Fish",
            "type":"Retail Goods"
        }
    ],
    "sg:phone":"+44 1689 852418",
    "sg:postcode":"BR6 8NN",
    "sg:province":"Kent",
    "sg:tags":[
        "butcher"
    ],
    "wof:name":"Williamson's",
    "wof:placetype":"venue"
},
  "geometry": {"coordinates":[0.054929,51.367466],"type":"Point"}
}