{
  "type": "Feature",
  "properties": {
    "iso:country":"GB",
    "sg:address":"51 Baymead Lane, North Petherton",
    "sg:city":"Bridgwater",
    "sg:classifiers":[
        {
            "category":"Communications",
            "type":"Services"
        }
    ],
    "sg:phone":"+44 1278 662555",
    "sg:postcode":"TA6 6RN",
    "sg:province":"Somerset",
    "sg:tags":[
        "audio-visual"
    ],
    "wof:name":"Custom Installations",
    "wof:placetype":"venue"
},
  "geometry": {"coordinates":[-3.012698,51.089012],"type":"Point"}
}