{
  "type": "Feature",
  "properties": {
    "addr:full":"8 Knowle Road Mirfield West Yorkshire WF14 8DQ",
    "addr:housenumber":"8",
    "addr:postcode":"wf14 8dq",
    "addr:street":"Knowle Road",
    "iso:country":"GB",
    "sg:address":"8 Knowle Road",
    "sg:city":"Mirfield",
    "sg:classifiers":[
        {
            "category":"Restaurant",
            "type":"Food & Drink"
        }
    ],
    "sg:phone":"+44 1924 491414",
    "sg:postcode":"WF14 8DQ",
    "sg:province":"West Yorkshire",
    "sg:tags":[
        "indian"
    ],
    "wof:name":"Subras Indian Restaurant & Take Away",
    "wof:placetype":"venue"
},
  "geometry": {"coordinates":[-1.690932,53.674812],"type":"Point"}
}