{
  "type": "Feature",
  "properties": {
    "iso:country":"GB",
    "sg:address":"Market Place",
    "sg:city":"Norwich",
    "sg:classifiers":[
        {
            "category":"Food & Beverages",
            "subcategory":"Meat & Fish",
            "type":"Retail Goods"
        }
    ],
    "sg:phone":"+44 1603 621148",
    "sg:postcode":"NR2 1NB",
    "sg:province":"Norfolk",
    "sg:tags":[
        "butcher"
    ],
    "wof:name":"Central Butchers",
    "wof:placetype":"venue"
},
  "geometry": {"coordinates":[1.297775,52.629051],"type":"Point"}
}