{
  "type": "Feature",
  "properties": {
    "addr:full":"Rawcliffe Rd Preston Lancashire PR3 0UD",
    "addr:postcode":"pr3 0ud",
    "addr:street":"Rawcliffe Rd",
    "iso:country":"GB",
    "sg:address":"Rawcliffe Rd",
    "sg:city":"Preston",
    "sg:classifiers":[
        {
            "category":"Government",
            "subcategory":"Post Office",
            "type":"Public Place"
        }
    ],
    "sg:phone":"+44 1995 679225",
    "sg:postcode":"PR3 0UD",
    "sg:province":"Lancashire",
    "wof:name":"St Michaels Post Office",
    "wof:placetype":"venue"
},
  "geometry": {"coordinates":[-2.822349,53.865726],"type":"Point"}
}