{
  "type": "Feature",
  "properties": {
    "addr:full":"Crane Hill, London Rd Ipswich Suffolk IP2 0SS",
    "addr:postcode":"ip2 0ss",
    "addr:street":"Crane Hill London Rd",
    "iso:country":"GB",
    "sg:address":"Crane Hill, London Rd",
    "sg:city":"Ipswich",
    "sg:classifiers":[
        {
            "category":"Travel",
            "subcategory":"Hotels & Motels",
            "type":"Entertainment"
        }
    ],
    "sg:postcode":"IP2 0SS",
    "sg:province":"Suffolk",
    "sg:tags":[
        "house",
        "guest"
    ],
    "wof:name":"Stelvio Guest House",
    "wof:placetype":"venue"
},
  "geometry": {"coordinates":[1.1248500347,52.0530815125],"type":"Point"}
}