{
  "type": "Feature",
  "properties": {
    "addr:full":"10 Brookway, North Cheshire Trading Est Birkenhead Merseyside L43 3DT",
    "addr:housenumber":"10",
    "addr:postcode":"l43 3dt",
    "addr:street":"Brookway North Cheshire;Est",
    "iso:country":"GB",
    "sg:address":"10 Brookway, North Cheshire Trading Est",
    "sg:city":"Birkenhead",
    "sg:classifiers":[
        {
            "category":"Bus Charters",
            "type":"Transportation"
        }
    ],
    "sg:phone":"+44 151 608 8000",
    "sg:postcode":"L43 3DT",
    "sg:province":"Merseyside",
    "sg:tags":[
        "coach"
    ],
    "wof:name":"Avon Coaches",
    "wof:placetype":"venue"
},
  "geometry": {"coordinates":[-3.02549,53.392559],"type":"Point"}
}