{
  "type": "Feature",
  "properties": {
    "iso:country":"GB",
    "sg:address":"Southfield Road",
    "sg:city":"Middlesbrough",
    "sg:classifiers":[
        {
            "category":"Place Of Worship",
            "type":"Public Place"
        }
    ],
    "sg:phone":"+44 1642 241344",
    "sg:postcode":"TS1 3BZ",
    "sg:province":"North Yorkshire",
    "wof:name":"The Salvation Army",
    "wof:placetype":"venue"
},
  "geometry": {"coordinates":[-1.236934,54.570717],"type":"Point"}
}