{
  "type": "Feature",
  "properties": {
    "addr:full":"The Indoor Bowling Centre Hereford Herefordshire HR2 8EQ",
    "addr:postcode":"hr2 8eq",
    "iso:country":"GB",
    "sg:address":"The Indoor Bowling Centre",
    "sg:city":"Hereford",
    "sg:classifiers":[
        {
            "category":"Sports & Exercise",
            "subcategory":"Bowling",
            "type":"Entertainment"
        }
    ],
    "sg:phone":"+44 1981 540801",
    "sg:postcode":"HR2 8EQ",
    "sg:province":"Herefordshire",
    "wof:name":"Martin Edwards Associates Ltd.",
    "wof:placetype":"venue"
},
  "geometry": {"coordinates":[-2.74634,51.967781],"type":"Point"}
}