{
  "type": "Feature",
  "properties": {
    "addr:full":"Phoenix Ho, Phoenix Cres, Strathclyde Business Park Bellshill North Lanarkshire ML4 3NJ",
    "addr:postcode":"ml4 3nj",
    "addr:street":"Cres;Business Park Bellshill",
    "iso:country":"GB",
    "sg:address":"Phoenix Ho, Phoenix Cres, Strathclyde Business Park",
    "sg:city":"Bellshill",
    "sg:classifiers":[
        {
            "category":"Manufacturing",
            "subcategory":"Buildings",
            "type":"Manufacturing & Wholesale Goods"
        }
    ],
    "sg:phone":"+44 1698 501410",
    "sg:postcode":"ML4 3NJ",
    "sg:province":"North Lanarkshire",
    "sg:tags":[
        "system",
        "air conditioning"
    ],
    "wof:name":"Toshiba Air Conditioning",
    "wof:placetype":"venue"
},
  "geometry": {"coordinates":[-4.034526825,55.830493927],"type":"Point"}
}