{
  "type": "Feature",
  "properties": {
    "addr:full":"1 Holdenhurst Rd Bournemouth Dorset BH8 8EH",
    "addr:housenumber":"1",
    "addr:postcode":"bh8 8eh",
    "addr:street":"Holdenhurst Rd",
    "iso:country":"GB",
    "sg:address":"1 Holdenhurst Rd",
    "sg:city":"Bournemouth",
    "sg:classifiers":[
        {
            "category":"Personal",
            "type":"Services"
        }
    ],
    "sg:phone":"+44 1202 314422",
    "sg:postcode":"BH8 8EH",
    "sg:province":"Dorset",
    "sg:tags":[
        "slimming",
        "product"
    ],
    "wof:name":"Natural Way The",
    "wof:placetype":"venue"
},
  "geometry": {"coordinates":[-1.866184,50.722469],"type":"Point"}
}