{
  "type": "Feature",
  "properties": {
    "addr:full":"633 High Road, Seven Kings Ilford Essex IG3 8RA",
    "addr:housenumber":"633",
    "addr:postcode":"ig3 8ra",
    "addr:street":"High Road",
    "iso:country":"GB",
    "sg:address":"633 High Road, Seven Kings",
    "sg:city":"Ilford",
    "sg:classifiers":[
        {
            "category":"Shopping",
            "subcategory":"Thrift Store",
            "type":"Retail Goods"
        }
    ],
    "sg:phone":"+44 20 8597 5834",
    "sg:postcode":"IG3 8RA",
    "sg:province":"Essex",
    "sg:tags":[
        "shop",
        "charity"
    ],
    "wof:name":"The Sue Ryder Foundation",
    "wof:placetype":"venue"
},
  "geometry": {"coordinates":[0.097873,51.564377],"type":"Point"}
}