{
  "type": "Feature",
  "properties": {
    "addr:full":"34 Sandy Road, Sandyford Stoke-on-trent Staffordshire ST6 5LW",
    "addr:housenumber":"34",
    "addr:postcode":"staffordshire st6 5lw",
    "addr:street":"Sandy Road",
    "iso:country":"GB",
    "sg:address":"34 Sandy Road, Sandyford",
    "sg:city":"Stoke-on-trent",
    "sg:classifiers":[
        {
            "category":"Building & Trades",
            "subcategory":"Plumbing",
            "type":"Services"
        }
    ],
    "sg:postcode":"ST6 5LW",
    "sg:province":"Staffordshire",
    "sg:tags":[
        "heating"
    ],
    "wof:name":"P W Reeves",
    "wof:placetype":"venue"
},
  "geometry": {"coordinates":[-2.213821888,53.0737533569],"type":"Point"}
}