{
  "type": "Feature",
  "properties": {
    "iso:country":"GB",
    "sg:address":"Town Green Lane, Aughton",
    "sg:city":"Ormskirk",
    "sg:classifiers":[
        {
            "category":"Education",
            "subcategory":"School",
            "type":"Public Place"
        },
        {
            "category":"Government",
            "subcategory":"Office",
            "type":"Public Place"
        }
    ],
    "sg:phone":"+44 1695 423688",
    "sg:postcode":"L39 6SF",
    "sg:province":"Lancashire",
    "sg:tags":[
        "local",
        "authority"
    ],
    "wof:name":"Aughton Town Green County Primary School",
    "wof:placetype":"venue"
},
  "geometry": {"coordinates":[-2.900505,53.544621],"type":"Point"}
}