{
  "type": "Feature",
  "properties": {
    "addr:full":"Unit 17 Central Trading Estate, Signal Way Swindon Wiltshire SN3 1PD",
    "addr:housenumber":"unit 17",
    "addr:postcode":"sn3 1pd",
    "addr:street":"Central Trading Estate Signal Way",
    "iso:country":"GB",
    "sg:address":"Unit 17 Central Trading Estate, Signal Way",
    "sg:city":"Swindon",
    "sg:classifiers":[
        {
            "category":"Home & Garden",
            "subcategory":"Hardware",
            "type":"Retail Goods"
        }
    ],
    "sg:phone":"+44 1793 523438",
    "sg:postcode":"SN3 1PD",
    "sg:province":"Wiltshire",
    "sg:tags":[
        "compressor",
        "air"
    ],
    "wof:name":"Instant Air",
    "wof:placetype":"venue"
},
  "geometry": {"coordinates":[-1.775317,51.549438],"type":"Point"}
}