{
  "type": "Feature",
  "properties": {
    "addr:full":"Sunnyside, Woodhouse Lane, Heversham Milnthorpe Cumbria LA7 7EW",
    "addr:postcode":"la7 7ew",
    "addr:street":"Woodhouse Lane",
    "iso:country":"GB",
    "sg:address":"Sunnyside, Woodhouse Lane, Heversham",
    "sg:city":"Milnthorpe",
    "sg:classifiers":[
        {
            "category":"Building & Trades",
            "subcategory":"Construction",
            "type":"Services"
        }
    ],
    "sg:phone":"+44 15395 63249",
    "sg:postcode":"LA7 7EW",
    "sg:province":"Cumbria",
    "sg:tags":[
        "joinery",
        "joiner",
        "carpenter",
        "carpentry"
    ],
    "wof:name":"W Gott Joiners & Contractors",
    "wof:placetype":"venue"
},
  "geometry": {"coordinates":[-2.772592,54.226864],"type":"Point"}
}