{
  "type": "Feature",
  "properties": {
    "addr:full":"Off Hungate Car-park Beccles Norfolk NR34 9TT",
    "addr:postcode":"nr34 9tt",
    "addr:street":"Off Hungate",
    "iso:country":"GB",
    "sg:address":"Off Hungate Car-park",
    "sg:city":"Beccles",
    "sg:classifiers":[
        {
            "category":"Personal",
            "subcategory":"Nail Salon",
            "type":"Services"
        }
    ],
    "sg:postcode":"NR34 9TT",
    "sg:province":"Norfolk",
    "sg:tags":[
        "solarium",
        "tanning"
    ],
    "wof:name":"Tanning Studio (The)",
    "wof:placetype":"venue"
},
  "geometry": {"coordinates":[1.5672450066,52.453666687],"type":"Point"}
}