{
  "type": "Feature",
  "properties": {
    "addr:full":"Main Road, Stanton-in-the-peak Matlock Derbyshire DE4 2LX",
    "addr:postcode":"de4 2lx",
    "addr:street":"Main Road Stanton-In-The-Peak",
    "iso:country":"GB",
    "sg:address":"Main Road, Stanton-in-the-peak",
    "sg:city":"Matlock",
    "sg:classifiers":[
        {
            "category":"Professional",
            "subcategory":"Engineering",
            "type":"Services"
        }
    ],
    "sg:postcode":"DE4 2LX",
    "sg:province":"Derbyshire",
    "sg:tags":[
        "precision",
        "engineer"
    ],
    "wof:name":"GOLDCREST ENGINEERING",
    "wof:placetype":"venue"
},
  "geometry": {"coordinates":[-1.597965,53.154808],"type":"Point"}
}