{
  "type": "Feature",
  "properties": {
    "iso:country":"GB",
    "sg:address":"Main Road, Stanton-in-the-peak",
    "sg:city":"Matlock",
    "sg:classifiers":[
        {
            "category":"Professional",
            "subcategory":"Engineering",
            "type":"Services"
        }
    ],
    "sg:postcode":"DE4 2LX",
    "sg:province":"Derbyshire",
    "sg:tags":[
        "precision",
        "engineer"
    ],
    "wof:name":"GOLDCREST ENGINEERING",
    "wof:placetype":"venue"
},
  "geometry": {"coordinates":[-1.597965,53.154808],"type":"Point"}
}