{
  "type": "Feature",
  "properties": {
    "addr:full":"Detection House, Brooklands Appr, North Street Romford Essex RM1 1DX",
    "addr:postcode":"rm1 1dx",
    "addr:street":"Brooklands;North Street",
    "iso:country":"GB",
    "sg:address":"Detection House, Brooklands Appr, North Street",
    "sg:city":"Romford",
    "sg:classifiers":[
        {
            "category":"Professional",
            "subcategory":"Management & Consulting",
            "type":"Services"
        }
    ],
    "sg:postcode":"RM1 1DX",
    "sg:province":"Essex",
    "sg:tags":[
        "fire",
        "consultant",
        "protection"
    ],
    "wof:name":"James Stuart (London) & Co. Ltd.",
    "wof:placetype":"venue"
},
  "geometry": {"coordinates":[0.1742070019,51.5835075378],"type":"Point"}
}