{
  "type": "Feature",
  "properties": {
    "iso:country":"GB",
    "sg:address":"11 Lisker Drive",
    "sg:city":"Otley",
    "sg:classifiers":[
        {
            "category":"Education",
            "subcategory":"Music School",
            "type":"Public Place"
        }
    ],
    "sg:phone":"+44 1943 465322",
    "sg:postcode":"LS21 1DQ",
    "sg:province":"North Yorkshire",
    "sg:tags":[
        "teacher"
    ],
    "wof:name":"Ian Mcteer",
    "wof:placetype":"venue"
},
  "geometry": {"coordinates":[-1.683588,53.902039],"type":"Point"}
}