{
  "type": "Feature",
  "properties": {
    "addr:full":"60 Lyme Grove, Romiley Stockport Cheshire SK6 4DJ",
    "addr:housenumber":"60",
    "addr:postcode":"sk6 4dj",
    "addr:street":"Lyme Grove",
    "iso:country":"GB",
    "sg:address":"60 Lyme Grove, Romiley",
    "sg:city":"Stockport",
    "sg:classifiers":[
        {
            "category":"Professional",
            "subcategory":"Business Services",
            "type":"Services"
        }
    ],
    "sg:phone":"+44 161 406 6335",
    "sg:postcode":"SK6 4DJ",
    "sg:province":"Cheshire",
    "sg:tags":[
        "distributor",
        "film"
    ],
    "wof:name":"Admit One Video Distribution",
    "wof:placetype":"venue"
},
  "geometry": {"coordinates":[-2.082998991,53.4124794006],"type":"Point"}
}