{
  "type": "Feature",
  "properties": {
    "iso:country":"GB",
    "sg:address":"Keward Park",
    "sg:city":"Wells",
    "sg:classifiers":[
        {
            "category":"Retail",
            "subcategory":"Auto Repair",
            "type":"Services"
        }
    ],
    "sg:phone":"+44 1749 678999",
    "sg:postcode":"BA5 1QE",
    "sg:province":"Somerset",
    "sg:tags":[
        "body",
        "car"
    ],
    "wof:name":"Wells Accident Repair Centre",
    "wof:placetype":"venue"
},
  "geometry": {"coordinates":[-2.653894,51.203403],"type":"Point"}
}