{
  "type": "Feature",
  "properties": {
    "addr:full":"1 Trafalgar Road, Portslade Brighton East Sussex BN41 1LD",
    "addr:housenumber":"1",
    "addr:postcode":"bn41 1ld",
    "addr:street":"Trafalgar Road",
    "iso:country":"GB",
    "sg:address":"1 Trafalgar Road, Portslade",
    "sg:city":"Brighton",
    "sg:classifiers":[
        {
            "category":"Professional",
            "subcategory":"Printing & Photocopies",
            "type":"Services"
        }
    ],
    "sg:postcode":"BN41 1LD",
    "sg:province":"East Sussex",
    "sg:tags":[
        "process",
        "screen",
        "printer"
    ],
    "wof:name":"Advance Screen Print Service",
    "wof:placetype":"venue"
},
  "geometry": {"coordinates":[-0.2145790011,50.8344192505],"type":"Point"}
}