{
  "type": "Feature",
  "properties": {
    "iso:country":"GB",
    "sg:address":"Alford Road",
    "sg:city":"Mablethorpe",
    "sg:classifiers":[
        {
            "category":"Health Services",
            "subcategory":"Nursing And Care Facility",
            "type":"Services"
        }
    ],
    "sg:phone":"+44 1507 472240",
    "sg:postcode":"LN12 1PX",
    "sg:province":"Lincolnshire",
    "sg:tags":[
        "home",
        "residential"
    ],
    "wof:name":"Mablethorpe Hall",
    "wof:placetype":"venue"
},
  "geometry": {"coordinates":[0.249465,53.338573],"type":"Point"}
}