{
  "type": "Feature",
  "properties": {
    "addr:full":"38 Norton Green Lane Cannock Staffordshire WS11 3PR",
    "addr:housenumber":"38",
    "addr:postcode":"ws11 3pr",
    "addr:street":"Norton Green Lane",
    "iso:country":"GB",
    "sg:address":"38 Norton Green Lane",
    "sg:city":"Cannock",
    "sg:classifiers":[
        {
            "category":"Building & Trades",
            "subcategory":"Construction",
            "type":"Services"
        },
        {
            "category":"Manufacturing",
            "subcategory":"Building Materials",
            "type":"Manufacturing & Wholesale Goods"
        }
    ],
    "sg:postcode":"WS11 3PR",
    "sg:province":"Staffordshire",
    "sg:tags":[
        "tarmac",
        "road",
        "surfacing",
        "asphalt"
    ],
    "wof:name":"Sutton & Pickerill",
    "wof:placetype":"venue"
},
  "geometry": {"coordinates":[-1.976583,52.668278],"type":"Point"}
}