{
  "type": "Feature",
  "properties": {
    "addr:full":"28 Elmfield Road Bromley Kent BR1 1LR",
    "addr:housenumber":"28",
    "addr:postcode":"br1 1lr",
    "addr:street":"Elmfield Road",
    "iso:country":"GB",
    "sg:address":"28 Elmfield Road",
    "sg:city":"Bromley",
    "sg:classifiers":[
        {
            "category":"Government",
            "subcategory":"Office",
            "type":"Public Place"
        }
    ],
    "sg:phone":"+44 20 8315 2800",
    "sg:postcode":"BR1 1LR",
    "sg:province":"Kent",
    "sg:tags":[
        "local"
    ],
    "wof:name":"Valuation Office",
    "wof:placetype":"venue"
},
  "geometry": {"coordinates":[0.0179399997,51.4003067017],"type":"Point"}
}