{
  "type": "Feature",
  "properties": {
    "iso:country":"GB",
    "sg:address":"7 Cess Road",
    "sg:city":"Great Yarmouth",
    "sg:classifiers":[
        {
            "category":"Building & Trades",
            "subcategory":"Construction",
            "type":"Services"
        }
    ],
    "sg:phone":"+44 1493 740135",
    "sg:postcode":"NR29 4QX",
    "sg:province":"Norfolk",
    "sg:tags":[
        "joinery"
    ],
    "wof:name":"Martham Joinery",
    "wof:placetype":"venue"
},
  "geometry": {"coordinates":[1.6256400347,52.7020568848],"type":"Point"}
}