{
  "type": "Feature",
  "properties": {
    "addr:full":"Mount Edgcumbe Torpoint Cornwall PL10 1HZ",
    "addr:postcode":"pl10 1hz",
    "addr:street":"Torpoint",
    "iso:country":"GB",
    "sg:address":"Mount Edgcumbe",
    "sg:city":"Torpoint",
    "sg:classifiers":[
        {
            "category":"Landmark",
            "subcategory":"Tourist Attraction",
            "type":"Public Place"
        }
    ],
    "sg:phone":"+44 1752 822236",
    "sg:postcode":"PL10 1HZ",
    "sg:province":"Cornwall",
    "sg:tags":[
        "interest"
    ],
    "wof:name":"Mount Edgcumbe House & Country Park",
    "wof:placetype":"venue"
},
  "geometry": {"coordinates":[-4.212720871,50.3406677246],"type":"Point"}
}