{
  "type": "Feature",
  "properties": {
    "iso:country":"GB",
    "sg:address":"9 Court Road",
    "sg:city":"Bridgend",
    "sg:classifiers":[
        {
            "category":"Professional",
            "subcategory":"Accounting & Tax Preparation",
            "type":"Services"
        }
    ],
    "sg:phone":"+44 1656 661253",
    "sg:postcode":"CF31 1BE",
    "sg:province":"Bridgend",
    "sg:tags":[
        "accountant",
        "activity"
    ],
    "wof:name":"Morris & Thomas",
    "wof:placetype":"venue"
},
  "geometry": {"coordinates":[-3.5762929916,51.5069503784],"type":"Point"}
}