{
  "type": "Feature",
  "properties": {
    "addr:full":"Unit 1 Station Road, Stockton Southam Warwickshire CV47 8HA",
    "addr:housenumber":"unit 1",
    "addr:postcode":"cv47 8ha",
    "addr:street":"Station Road",
    "iso:country":"GB",
    "sg:address":"Unit 1 Station Road, Stockton",
    "sg:city":"Southam",
    "sg:classifiers":[
        {
            "category":"Retail",
            "subcategory":"Auto Repair",
            "type":"Services"
        }
    ],
    "sg:phone":"+44 1926 811505",
    "sg:postcode":"CV47 8HA",
    "sg:province":"Warwickshire",
    "sg:tags":[
        "engine",
        "car",
        "specialist"
    ],
    "wof:name":"Peter Johns Racing",
    "wof:placetype":"venue"
},
  "geometry": {"coordinates":[-1.350276947,52.2731056213],"type":"Point"}
}