{
  "type": "Feature",
  "properties": {
    "addr:full":"Culloden Medical Practice, Keppoch Rd Inverness Highland IV1 2LL",
    "addr:postcode":"iv1 2ll",
    "addr:street":"Keppoch Rd",
    "iso:country":"GB",
    "sg:address":"Culloden Medical Practice, Keppoch Rd",
    "sg:city":"Inverness",
    "sg:classifiers":[
        {
            "category":"Health Services",
            "subcategory":"Doctor",
            "type":"Services"
        }
    ],
    "sg:phone":"+44 1463 793400",
    "sg:postcode":"IV1 2LL",
    "sg:province":"Highland",
    "sg:tags":[
        "practitioners"
    ],
    "wof:name":"Campbell, R J",
    "wof:placetype":"venue"
},
  "geometry": {"coordinates":[-4.2684001923,57.5230484009],"type":"Point"}
}