{
  "type": "Feature",
  "properties": {
    "addr:full":"York House, 102-108 Borough Road Middlesbrough North Yorkshire TS1 2HJ",
    "addr:housenumber":"102-108",
    "addr:postcode":"ts1 2hj",
    "addr:street":"Borough Road",
    "iso:country":"GB",
    "sg:address":"York House, 102-108 Borough Road",
    "sg:city":"Middlesbrough",
    "sg:classifiers":[
        {
            "category":"Education",
            "subcategory":"University",
            "type":"Public Place"
        }
    ],
    "sg:postcode":"TS1 2HJ",
    "sg:province":"North Yorkshire",
    "sg:tags":[
        "higher"
    ],
    "wof:name":"The National Distance Learning College Ltd.",
    "wof:placetype":"venue"
},
  "geometry": {"coordinates":[-1.234472,54.572914],"type":"Point"}
}