{
  "type": "Feature",
  "properties": {
    "addr:full":"62 Cresswell Road Chesham Buckinghamshire HP5 1SX",
    "addr:housenumber":"62",
    "addr:postcode":"hp5 1sx",
    "addr:street":"Cresswell Road",
    "iso:country":"GB",
    "sg:address":"62 Cresswell Road",
    "sg:city":"Chesham",
    "sg:classifiers":[
        {
            "category":"Shopping",
            "subcategory":"Antiques",
            "type":"Retail Goods"
        },
        {
            "category":"Government",
            "subcategory":"Customs House",
            "type":"Public Place"
        }
    ],
    "sg:phone":"+44 1494 774599",
    "sg:postcode":"HP5 1SX",
    "sg:province":"Buckinghamshire",
    "sg:tags":[
        "clearance"
    ],
    "wof:name":"GRANNIES ATTIC",
    "wof:placetype":"venue"
},
  "geometry": {"coordinates":[-0.598266,51.691887],"type":"Point"}
}