{
  "type": "Feature",
  "properties": {
    "addr:full":"St Leger Drive, Great Linford Milton Keynes Buckinghamshire MK14 5BL",
    "addr:postcode":"mk14 5bl",
    "addr:street":"St Leger Drive Great",
    "iso:country":"GB",
    "sg:address":"St Leger Drive, Great Linford",
    "sg:city":"Milton Keynes",
    "sg:classifiers":[
        {
            "category":"Education",
            "subcategory":"School",
            "type":"Public Place"
        }
    ],
    "sg:phone":"+44 1908 605027",
    "sg:postcode":"MK14 5BL",
    "sg:province":"Buckinghamshire",
    "sg:tags":[
        "local",
        "authority"
    ],
    "wof:name":"Great Linford Combined School",
    "wof:placetype":"venue"
},
  "geometry": {"coordinates":[-0.764227,52.070679],"type":"Point"}
}