{
  "type": "Feature",
  "properties": {
    "addr:full":"Vicarage Road Chelmsford Essex CM2 0JQ",
    "addr:postcode":"cm2 0jq",
    "addr:street":"Vicarage Road",
    "iso:country":"GB",
    "sg:address":"Vicarage Road",
    "sg:city":"Chelmsford",
    "sg:classifiers":[
        {
            "category":"Community Center",
            "type":"Public Place"
        },
        {
            "category":"Government",
            "subcategory":"Office",
            "type":"Public Place"
        }
    ],
    "sg:phone":"+44 1245 269020",
    "sg:postcode":"CM2 0JQ",
    "sg:province":"Essex",
    "sg:tags":[
        "recreation",
        "local",
        "leisure",
        "centre"
    ],
    "wof:name":"Dovedale Sports Centre",
    "wof:placetype":"venue"
},
  "geometry": {"coordinates":[0.470015,51.72591],"type":"Point"}
}