{
  "type": "Feature",
  "properties": {
    "addr:full":"2491 Dumbarton Road Glasgow Glasgow City G14 0PR",
    "addr:housenumber":"2491",
    "addr:postcode":"g14 0pr",
    "addr:street":"Dumbarton Road",
    "iso:country":"GB",
    "sg:address":"2491 Dumbarton Road",
    "sg:city":"Glasgow",
    "sg:classifiers":[
        {
            "category":"Health Services",
            "subcategory":"Doctor",
            "type":"Services"
        }
    ],
    "sg:phone":"+44 141 952 2873",
    "sg:postcode":"G14 0PR",
    "sg:province":"Glasgow City",
    "sg:tags":[
        "practitioners"
    ],
    "wof:name":"A McCall",
    "wof:placetype":"venue"
},
  "geometry": {"coordinates":[-4.3833389282,55.8902511597],"type":"Point"}
}