{
  "type": "Feature",
  "properties": {
    "addr:full":"85 Edenfield Gardens Worcester Park Surrey KT4 7DX",
    "addr:housenumber":"85",
    "addr:postcode":"kt4 7dx",
    "addr:street":"Edenfield Gardens;Park",
    "iso:country":"GB",
    "sg:address":"85 Edenfield Gardens",
    "sg:city":"Worcester Park",
    "sg:classifiers":[
        {
            "category":"Professional",
            "subcategory":"Accounting & Tax Preparation",
            "type":"Services"
        }
    ],
    "sg:postcode":"KT4 7DX",
    "sg:province":"Surrey",
    "sg:tags":[
        "accountant"
    ],
    "wof:name":"Ashlei Associates",
    "wof:placetype":"venue"
},
  "geometry": {"coordinates":[-0.251762,51.373726],"type":"Point"}
}