{
  "type": "Feature",
  "properties": {
    "addr:full":"Attercliffe Works Sheffield South Yorkshire S9 3QQ",
    "addr:postcode":"s9 3qq",
    "iso:country":"GB",
    "sg:address":"Attercliffe Works",
    "sg:city":"Sheffield",
    "sg:classifiers":[
        {
            "category":"Manufacturing",
            "subcategory":"Metals",
            "type":"Manufacturing & Wholesale Goods"
        }
    ],
    "sg:postcode":"S9 3QQ",
    "sg:province":"South Yorkshire",
    "sg:tags":[
        "product",
        "fabricated"
    ],
    "wof:name":"F 1 Metal Fabrications (Sheffield)",
    "wof:placetype":"venue"
},
  "geometry": {"coordinates":[-1.429104,53.396252],"type":"Point"}
}