{
  "type": "Feature",
  "properties": {
    "addr:full":"Buckingham Ho, 6 Buckingham St Holborn Greater London WC2N 6BU",
    "addr:housenumber":"6",
    "addr:postcode":"wc2n 6bu",
    "addr:street":"Buckingham St",
    "iso:country":"GB",
    "sg:address":"Buckingham Ho, 6 Buckingham St",
    "sg:city":"Holborn",
    "sg:classifiers":[
        {
            "category":"Professional",
            "subcategory":"Employment Agencies",
            "type":"Services"
        }
    ],
    "sg:phone":"+44 20 7930 1010",
    "sg:postcode":"WC2N 6BU",
    "sg:province":"Greater London",
    "sg:tags":[
        "consultant"
    ],
    "wof:name":"Reilly Recruitment",
    "wof:placetype":"venue"
},
  "geometry": {"coordinates":[-0.12385,51.50845],"type":"Point"}
}