{
  "type": "Feature",
  "properties": {
    "addr:full":"29 Croft House Gro, Morley Leeds West Yorkshire LS27 8PA",
    "addr:housenumber":"29",
    "addr:postcode":"ls27 8pa",
    "addr:street":"Croft House Gro",
    "iso:country":"GB",
    "sg:address":"29 Croft House Gro, Morley",
    "sg:city":"Leeds",
    "sg:classifiers":[
        {
            "category":"Professional",
            "type":"Services"
        },
        {
            "category":"Personal",
            "type":"Services"
        }
    ],
    "sg:postcode":"LS27 8PA",
    "sg:province":"West Yorkshire",
    "sg:tags":[
        "entertainer",
        "wedding"
    ],
    "wof:name":"Visual Promotions",
    "wof:placetype":"venue"
},
  "geometry": {"coordinates":[-1.5956549644,53.7520484924],"type":"Point"}
}