{
  "type": "Feature",
  "properties": {
    "addr:full":"92 Tylacelyn Road Tonypandy Rhondda, Cynon, Taff CF40 1JR",
    "addr:housenumber":"92",
    "addr:postcode":"cf40 1jr",
    "addr:street":"Tylacelyn Road;Cynon Taff",
    "iso:country":"GB",
    "sg:address":"92 Tylacelyn Road",
    "sg:city":"Tonypandy",
    "sg:classifiers":[
        {
            "category":"Government",
            "subcategory":"Post Office",
            "type":"Public Place"
        }
    ],
    "sg:phone":"+44 1443 432227",
    "sg:postcode":"CF40 1JR",
    "sg:province":"Rhondda, Cynon, Taff",
    "wof:name":"Penygraig Post Office",
    "wof:placetype":"venue"
},
  "geometry": {"coordinates":[-3.448325,51.615177],"type":"Point"}
}