{
  "type": "Feature",
  "properties": {
    "addr:full":"Marine Ho, Blaikies Quay Aberdeen Aberdeen City AB11 5EZ",
    "addr:postcode":"ab11 5ez",
    "addr:street":"Quay",
    "iso:country":"GB",
    "sg:address":"Marine Ho, Blaikies Quay",
    "sg:city":"Aberdeen",
    "sg:classifiers":[
        {
            "category":"Government",
            "subcategory":"Office",
            "type":"Public Place"
        }
    ],
    "sg:phone":"+44 1224 574122",
    "sg:postcode":"AB11 5EZ",
    "sg:province":"Aberdeen City",
    "sg:tags":[
        "central"
    ],
    "wof:name":"Department Of Transportmarine Safety Agency",
    "wof:placetype":"venue"
},
  "geometry": {"coordinates":[-2.0878500938,57.1444587708],"type":"Point"}
}