{
  "type": "Feature",
  "properties": {
    "addr:full":"Layerthorpe York North Yorkshire YO31 7UN",
    "addr:postcode":"yo31 7un",
    "addr:street":"Layerthorpe",
    "iso:country":"GB",
    "sg:address":"Layerthorpe",
    "sg:city":"York",
    "sg:classifiers":[
        {
            "category":"Autos & Motor Vehicles",
            "subcategory":"Auto Supplies",
            "type":"Retail Goods"
        }
    ],
    "sg:postcode":"YO31 7UN",
    "sg:province":"North Yorkshire",
    "sg:tags":[
        "windscreen"
    ],
    "wof:name":"Auto Glass York Ltd.",
    "wof:placetype":"venue"
},
  "geometry": {"coordinates":[-1.0697439909,53.9636039734],"type":"Point"}
}