{
  "type": "Feature",
  "properties": {
    "iso:country":"GB",
    "sg:address":"14 John Princes St",
    "sg:city":"London",
    "sg:classifiers":[
        {
            "category":"Personal",
            "subcategory":"Beauty Salon",
            "type":"Services"
        }
    ],
    "sg:phone":"+44 20 7499 2300",
    "sg:postcode":"W1G 0JR",
    "sg:province":"Greater London",
    "sg:tags":[
        "unisex",
        "hairdresser"
    ],
    "wof:name":"Burlingtons Hair Salon",
    "wof:placetype":"venue"
},
  "geometry": {"coordinates":[-0.1432439983,51.5161972046],"type":"Point"}
}