{
  "type": "Feature",
  "properties": {
    "iso:country":"GB",
    "sg:address":"Lower Boathouse (the), Chatham Historic Dockyard",
    "sg:city":"Chatham",
    "sg:classifiers":[
        {
            "category":"Autos & Motor Vehicles",
            "subcategory":"Boat Sales",
            "type":"Retail Goods"
        }
    ],
    "sg:phone":"+44 1634 813057",
    "sg:postcode":"ME4 4TE",
    "sg:province":"Kent",
    "sg:tags":[
        "repair",
        "builder"
    ],
    "wof:name":"Victory Boat Builders",
    "wof:placetype":"venue"
},
  "geometry": {"coordinates":[0.52244,51.381889],"type":"Point"}
}