{
  "type": "Feature",
  "properties": {
    "addr:full":"Unitb, Acorn Park, Lenton Lane Industrial Estate Nottingham Nottinghamshire NG7 2TR",
    "addr:postcode":"ng7 2tr",
    "addr:street":"Acorn Park Lenton Lane Industrial Estate",
    "iso:country":"GB",
    "sg:address":"Unitb, Acorn Park, Lenton Lane Industrial Estate",
    "sg:city":"Nottingham",
    "sg:classifiers":[
        {
            "category":"Wholesale",
            "subcategory":"Electrical",
            "type":"Manufacturing & Wholesale Goods"
        },
        {
            "category":"Shopping",
            "subcategory":"Computers & Home Electronics",
            "type":"Retail Goods"
        }
    ],
    "sg:phone":"+44 115 986 5453",
    "sg:postcode":"NG7 2TR",
    "sg:province":"Nottinghamshire",
    "sg:tags":[
        "wholesaler"
    ],
    "wof:name":"Bennett & Fountain Ltd.",
    "wof:placetype":"venue"
},
  "geometry": {"coordinates":[-1.1815890074,52.9337692261],"type":"Point"}
}