{
  "type": "Feature",
  "properties": {
    "iso:country":"GB",
    "sg:address":"81 Sandy Hill Road",
    "sg:city":"London",
    "sg:classifiers":[
        {
            "category":"Bars & Pubs",
            "type":"Food & Drink"
        }
    ],
    "sg:phone":"+44 20 8265 7475",
    "sg:postcode":"SE18 7BB",
    "sg:province":"Greater London",
    "sg:tags":[
        "pubs",
        "inn"
    ],
    "wof:name":"The Melbourne Arms",
    "wof:placetype":"venue"
},
  "geometry": {"coordinates":[0.069348,51.484623],"type":"Point"}
}