{
  "type": "Feature",
  "properties": {
    "iso:country":"GB",
    "sg:address":"103 The Broadway",
    "sg:city":"London",
    "sg:classifiers":[
        {
            "category":"Home & Garden",
            "subcategory":"Furniture",
            "type":"Retail Goods"
        }
    ],
    "sg:phone":"+44 20 8906 9446",
    "sg:postcode":"NW7 3TG",
    "sg:province":"Greater London",
    "wof:name":"Goodwood Pine Ltd.",
    "wof:placetype":"venue"
},
  "geometry": {"coordinates":[-0.2455960065,51.6154937744],"type":"Point"}
}