{
  "type": "Feature",
  "properties": {
    "addr:full":"Sherburn Hill, Front Street Durham Durham DH6 1PA",
    "addr:postcode":"dh6 1pa",
    "addr:street":"Hill Front Street",
    "iso:country":"GB",
    "sg:address":"Sherburn Hill, Front Street",
    "sg:city":"Durham",
    "sg:classifiers":[
        {
            "category":"Social Services",
            "subcategory":"Retirement Home",
            "type":"Services"
        }
    ],
    "sg:phone":"+44 191 372 0642",
    "sg:postcode":"DH6 1PA",
    "sg:province":"Durham",
    "sg:tags":[
        "residential",
        "care"
    ],
    "wof:name":"The Chimneys",
    "wof:placetype":"venue"
},
  "geometry": {"coordinates":[-1.48002,54.772968],"type":"Point"}
}