{
  "type": "Feature",
  "properties": {
    "addr:full":"5-6 Sydney Terrace, The Green, Claygate Esher Surrey KT10 0JJ",
    "addr:housenumber":"5-6",
    "addr:postcode":"kt10 0jj",
    "addr:street":"Sydney Terrace The Green",
    "iso:country":"GB",
    "sg:address":"5-6 Sydney Terrace, The Green, Claygate",
    "sg:city":"Esher",
    "sg:classifiers":[
        {
            "category":"Shopping",
            "subcategory":"Pharmacy",
            "type":"Retail Goods"
        }
    ],
    "sg:phone":"+44 1372 464659",
    "sg:postcode":"KT10 0JJ",
    "sg:province":"Surrey",
    "sg:tags":[
        "medicine",
        "therapy"
    ],
    "wof:name":"Complimentary Health Partnership",
    "wof:placetype":"venue"
},
  "geometry": {"coordinates":[-0.340494,51.360138],"type":"Point"}
}