{
  "type": "Feature",
  "properties": {
    "addr:full":"Cherwell Service Station, Cherwell St Banbury Oxfordshire OX16 8BA",
    "addr:postcode":"ox16 8ba",
    "addr:street":"St",
    "iso:country":"GB",
    "sg:address":"Cherwell Service Station, Cherwell St",
    "sg:city":"Banbury",
    "sg:classifiers":[
        {
            "category":"Retail",
            "subcategory":"Auto Repair",
            "type":"Services"
        }
    ],
    "sg:phone":"+44 1295 275709",
    "sg:postcode":"OX16 8BA",
    "sg:province":"Oxfordshire",
    "sg:tags":[
        "modification",
        "garage"
    ],
    "wof:name":"Fina PLC",
    "wof:placetype":"venue"
},
  "geometry": {"coordinates":[-1.340028,52.061111],"type":"Point"}
}