{
  "type": "Feature",
  "properties": {
    "iso:country":"GB",
    "sg:address":"394 Rayners Lane",
    "sg:city":"Pinner",
    "sg:classifiers":[
        {
            "category":"Health Services",
            "subcategory":"Podiatrist",
            "type":"Services"
        }
    ],
    "sg:phone":"+44 20 8429 1808",
    "sg:postcode":"HA5 5DY",
    "sg:province":"Greater London",
    "sg:tags":[
        "podiatrists",
        "chiropodist"
    ],
    "wof:name":"James P Burnett",
    "wof:placetype":"venue"
},
  "geometry": {"coordinates":[-0.370846,51.576527],"type":"Point"}
}