{
  "type": "Feature",
  "properties": {
    "iso:country":"GB",
    "sg:address":"115 High Street",
    "sg:city":"Enfield",
    "sg:classifiers":[
        {
            "category":"Autos & Motor Vehicles",
            "subcategory":"Automobile Sales",
            "type":"Retail Goods"
        },
        {
            "category":"Retail",
            "subcategory":"Auto Repair",
            "type":"Services"
        },
        {
            "category":"Parking",
            "subcategory":"Bicycle",
            "type":"Transportation"
        }
    ],
    "sg:phone":"+44 20 8804 3930",
    "sg:postcode":"EN3 4ED",
    "sg:province":"Greater London",
    "sg:tags":[
        "car",
        "garaging",
        "commercial"
    ],
    "wof:name":"Sun Motors",
    "wof:placetype":"venue"
},
  "geometry": {"coordinates":[-0.0465020016,51.6499290466],"type":"Point"}
}