{
  "type": "Feature",
  "properties": {
    "addr:full":"Walton Bay House Clevedon Somerset BS21 7AX",
    "addr:housenumber":"clevedon",
    "addr:postcode":"bs21 7ax",
    "addr:street":"Walton",
    "iso:country":"GB",
    "sg:address":"Walton Bay House",
    "sg:city":"Clevedon",
    "sg:classifiers":[
        {
            "category":"Manufacturing",
            "subcategory":"Buildings",
            "type":"Manufacturing & Wholesale Goods"
        }
    ],
    "sg:phone":"+44 1275 871625",
    "sg:postcode":"BS21 7AX",
    "sg:province":"Somerset",
    "sg:tags":[
        "mobile",
        "home"
    ],
    "wof:name":"W G Way Ltd.",
    "wof:placetype":"venue"
},
  "geometry": {"coordinates":[-2.8281140327,51.4641914368],"type":"Point"}
}