{
  "type": "Feature",
  "properties": {
    "addr:full":"Unit 5, Garth Wks Est, Taffs Wells Cardiff Caerphilly CF15 7YF",
    "addr:housenumber":"unit 5",
    "addr:postcode":"cf15 7yf",
    "addr:street":"Garth Wks Est;Wells",
    "iso:country":"GB",
    "sg:address":"Unit 5, Garth Wks Est, Taffs Wells",
    "sg:city":"Cardiff",
    "sg:classifiers":[
        {
            "category":"Shopping",
            "subcategory":"Bicycles & Sporting Goods",
            "type":"Retail Goods"
        }
    ],
    "sg:postcode":"CF15 7YF",
    "sg:province":"Caerphilly",
    "sg:tags":[
        "cycle",
        "accessory"
    ],
    "wof:name":"Bikes Direct",
    "wof:placetype":"venue"
},
  "geometry": {"coordinates":[-3.2617900372,51.5409011841],"type":"Point"}
}