{
  "type": "Feature",
  "properties": {
    "iso:country":"GB",
    "sg:address":"Burford Lane, Broomedge",
    "sg:city":"Lymm",
    "sg:classifiers":[
        {
            "category":"Farming",
            "subcategory":"Livestock Farm",
            "type":"Manufacturing & Wholesale Goods"
        }
    ],
    "sg:phone":"+44 1925 752830",
    "sg:postcode":"WA13 0SE",
    "sg:province":"Cheshire",
    "sg:tags":[
        "others"
    ],
    "wof:name":"Ronald Stanhope",
    "wof:placetype":"venue"
},
  "geometry": {"coordinates":[-2.4875559807,53.379573822],"type":"Point"}
}