{
  "type": "Feature",
  "properties": {
    "iso:country":"GB",
    "sg:address":"Staincliffe Road Garage",
    "sg:city":"Dewsbury",
    "sg:classifiers":[
        {
            "category":"Professional",
            "subcategory":"Testing Lab",
            "type":"Services"
        }
    ],
    "sg:postcode":"WF13 4RB",
    "sg:province":"West Yorkshire",
    "sg:tags":[
        "mot"
    ],
    "wof:name":"H Bailey & Son",
    "wof:placetype":"venue"
},
  "geometry": {"coordinates":[-1.653799,53.7066],"type":"Point"}
}