{
  "type": "Feature",
  "properties": {
    "addr:full":"Derwenthaugh Indstl Est, Derwenthaugh Rd Newcastle-upon-tyne Durham NE16 3BQ",
    "addr:postcode":"ne16 3bq",
    "addr:street":"Derwenthaugh Rd",
    "iso:country":"GB",
    "sg:address":"Derwenthaugh Indstl Est, Derwenthaugh Rd",
    "sg:city":"Newcastle-upon-tyne",
    "sg:classifiers":[
        {
            "category":"Professional",
            "subcategory":"Management & Consulting",
            "type":"Services"
        },
        {
            "category":"Utilities",
            "subcategory":"Telephone",
            "type":"Services"
        }
    ],
    "sg:phone":"+44 191 499 1100",
    "sg:postcode":"NE16 3BQ",
    "sg:province":"Durham",
    "sg:tags":[
        "consultant",
        "telecommunication"
    ],
    "wof:name":"Northern Independent Business Systems Lt",
    "wof:placetype":"venue"
},
  "geometry": {"coordinates":[-1.6924099922,54.9629592896],"type":"Point"}
}