{
  "type": "Feature",
  "properties": {
    "iso:country":"GB",
    "sg:address":", Crudwell",
    "sg:city":"Malmesbury",
    "sg:classifiers":[
        {
            "category":"Education",
            "subcategory":"School",
            "type":"Public Place"
        }
    ],
    "sg:phone":"+44 1666 577357",
    "sg:postcode":"SN16 9ER",
    "sg:province":"Wiltshire",
    "sg:tags":[
        "local",
        "authority"
    ],
    "wof:name":"Crudwell C Of E Primary School",
    "wof:placetype":"venue"
},
  "geometry": {"coordinates":[-2.080943,51.634193],"type":"Point"}
}