{
  "type": "Feature",
  "properties": {
    "addr:full":"120 Commonwealth Way Abbey Wood Greater London SE2 0LB",
    "addr:housenumber":"120",
    "addr:postcode":"se2 0lb",
    "addr:street":"Commonwealth Way",
    "iso:country":"GB",
    "sg:address":"120 Commonwealth Way",
    "sg:city":"Abbey Wood",
    "sg:classifiers":[
        {
            "category":"Building & Trades",
            "subcategory":"Cleaning & Sanitation",
            "type":"Services"
        }
    ],
    "sg:phone":"+44 20 8312 1132",
    "sg:postcode":"SE2 0LB",
    "sg:province":"Greater London",
    "sg:tags":[
        "commercial"
    ],
    "wof:name":"D B Cleaning",
    "wof:placetype":"venue"
},
  "geometry": {"coordinates":[0.1168150008,51.4852218628],"type":"Point"}
}