{
  "type": "Feature",
  "properties": {
    "addr:full":"Spring Cottage, 54 Park Close, Snettisham King's Lynn Norfolk PE31 7RY",
    "addr:housenumber":"54",
    "addr:postcode":"pe31 7ry",
    "addr:street":"Park Close;Lynn",
    "iso:country":"GB",
    "sg:address":"Spring Cottage, 54 Park Close, Snettisham",
    "sg:city":"King's Lynn",
    "sg:classifiers":[
        {
            "category":"Building & Trades",
            "subcategory":"Plumbing",
            "type":"Services"
        }
    ],
    "sg:postcode":"PE31 7RY",
    "sg:province":"Norfolk",
    "sg:tags":[
        "heating"
    ],
    "wof:name":"John Starling Boiler Service",
    "wof:placetype":"venue"
},
  "geometry": {"coordinates":[0.50562,52.874062],"type":"Point"}
}