{
  "type": "Feature",
  "properties": {
    "iso:country":"GB",
    "sg:address":"Castle Annexe",
    "sg:city":"Northwich",
    "sg:classifiers":[
        {
            "category":"Retail",
            "subcategory":"Driving School",
            "type":"Services"
        }
    ],
    "sg:postcode":"CW8 1LE",
    "sg:province":"Cheshire",
    "sg:tags":[
        "instruction",
        "cycling",
        "motor"
    ],
    "wof:name":"Bike School",
    "wof:placetype":"venue"
},
  "geometry": {"coordinates":[-2.519159,53.254799],"type":"Point"}
}