{
  "type": "Feature",
  "properties": {
    "addr:full":"21 South Copse Northampton Northamptonshire NN4 0RY",
    "addr:housenumber":"21",
    "addr:postcode":"nn4 0ry",
    "addr:street":"South Copse",
    "iso:country":"GB",
    "sg:address":"21 South Copse",
    "sg:city":"Northampton",
    "sg:classifiers":[
        {
            "category":"Home & Garden",
            "subcategory":"Carpets & Floor Coverings",
            "type":"Retail Goods"
        }
    ],
    "sg:postcode":"NN4 0RY",
    "sg:province":"Northamptonshire",
    "sg:tags":[
        "cleaner",
        "upholstery"
    ],
    "wof:name":"H C S",
    "wof:placetype":"venue"
},
  "geometry": {"coordinates":[-0.9081680179,52.2066841125],"type":"Point"}
}