{
  "type": "Feature",
  "properties": {
    "iso:country":"GB",
    "sg:address":"Poplar Lane, Winnersh",
    "sg:city":"Wokingham",
    "sg:classifiers":[
        {
            "category":"Sports & Exercise",
            "subcategory":"Tennis Court",
            "type":"Entertainment"
        }
    ],
    "sg:phone":"+44 118 979 1234",
    "sg:postcode":"RG41 5JR",
    "sg:province":"Berkshire",
    "sg:tags":[
        "breakdown",
        "recovery"
    ],
    "wof:name":"Bromley Recovery",
    "wof:placetype":"venue"
},
  "geometry": {"coordinates":[-0.8806459904,51.4302406311],"type":"Point"}
}