{
  "type": "Feature",
  "properties": {
    "iso:country":"GB",
    "sg:address":"Long Lane",
    "sg:city":"Norwich",
    "sg:classifiers":[
        {
            "category":"Sports & Exercise",
            "subcategory":"Golf",
            "type":"Entertainment"
        }
    ],
    "sg:phone":"+44 1603 742323",
    "sg:postcode":"NR9 3LX",
    "sg:province":"Norfolk",
    "sg:tags":[
        "club",
        "course"
    ],
    "wof:name":"Bawburgh Driving Range",
    "wof:placetype":"venue"
},
  "geometry": {"coordinates":[1.185,52.641369],"type":"Point"}
}