{
  "type": "Feature",
  "properties": {
    "addr:full":"26 High Street Delabole Cornwall PL33 9AE",
    "addr:housenumber":"26",
    "addr:postcode":"pl33 9ae",
    "addr:street":"High Street",
    "iso:country":"GB",
    "sg:address":"26 High Street",
    "sg:city":"Delabole",
    "sg:classifiers":[
        {
            "category":"Real Estate",
            "subcategory":"Real Estate Services",
            "type":"Services"
        },
        {
            "category":"Building & Trades",
            "subcategory":"Equipment Rental",
            "type":"Services"
        },
        {
            "category":"Social Services",
            "subcategory":"Retirement Home",
            "type":"Services"
        }
    ],
    "sg:phone":"+44 1840 213566",
    "sg:postcode":"PL33 9AE",
    "sg:province":"Cornwall",
    "sg:tags":[
        "plant",
        "leasing",
        "hire",
        "machinery"
    ],
    "wof:name":"Leslie B Tyson",
    "wof:placetype":"venue"
},
  "geometry": {"coordinates":[-4.728812,50.626434],"type":"Point"}
}