{
  "type": "Feature",
  "properties": {
    "addr:full":"Southampton Road Eastleigh Hampshire SO50 5QT",
    "addr:postcode":"so50 5qt",
    "addr:street":"Southampton Road",
    "iso:country":"GB",
    "sg:address":"Southampton Road",
    "sg:city":"Eastleigh",
    "sg:classifiers":[
        {
            "category":"Home & Garden",
            "subcategory":"Building Materials",
            "type":"Retail Goods"
        }
    ],
    "sg:phone":"+44 23 8061 2028",
    "sg:postcode":"SO50 5QT",
    "sg:province":"Hampshire",
    "sg:tags":[
        "ironwork",
        "diy",
        "wrought"
    ],
    "wof:name":"Scroll Engineering Co.",
    "wof:placetype":"venue"
},
  "geometry": {"coordinates":[-1.3510979414,50.9658126831],"type":"Point"}
}