{
  "type": "Feature",
  "properties": {
    "addr:full":"22 Hopes Hill Drive, Harraby Carlisle Cumbria CA1 3LD",
    "addr:housenumber":"22",
    "addr:postcode":"ca1 3ld",
    "addr:street":"Hopes Hill Drive",
    "iso:country":"GB",
    "sg:address":"22 Hopes Hill Drive, Harraby",
    "sg:city":"Carlisle",
    "sg:classifiers":[
        {
            "category":"Building & Trades",
            "subcategory":"Construction",
            "type":"Services"
        }
    ],
    "sg:postcode":"CA1 3LD",
    "sg:province":"Cumbria",
    "sg:tags":[
        "builder"
    ],
    "wof:name":"Halway Ltd.",
    "wof:placetype":"venue"
},
  "geometry": {"coordinates":[-2.899385,54.875118],"type":"Point"}
}