{
  "type": "Feature",
  "properties": {
    "iso:country":"GB",
    "sg:address":"295 Watling Street",
    "sg:city":"Radlett",
    "sg:classifiers":[
        {
            "category":"Cinema",
            "subcategory":"Movie Rental",
            "type":"Entertainment"
        }
    ],
    "sg:phone":"+44 1923 853644",
    "sg:postcode":"WD7 7LA",
    "sg:province":"Hertfordshire",
    "sg:tags":[
        "video",
        "library"
    ],
    "wof:name":"Apollo Home Entertainment",
    "wof:placetype":"venue"
},
  "geometry": {"coordinates":[-0.317549,51.683929],"type":"Point"}
}