{
  "type": "Feature",
  "properties": {
    "addr:full":"287-289 Whitley Road Whitley Bay Northumberland NE26 2TA",
    "addr:housenumber":"287-289",
    "addr:postcode":"ne26 2ta",
    "addr:street":"Whitley Road",
    "iso:country":"GB",
    "sg:address":"287-289 Whitley Road",
    "sg:city":"Whitley Bay",
    "sg:classifiers":[
        {
            "category":"Food & Beverages",
            "subcategory":"Specialty",
            "type":"Retail Goods"
        }
    ],
    "sg:phone":"+44 191 251 6107",
    "sg:postcode":"NE26 2TA",
    "sg:province":"Northumberland",
    "sg:tags":[
        "product",
        "health"
    ],
    "wof:name":"Holland & Barrett",
    "wof:placetype":"venue"
},
  "geometry": {"coordinates":[-1.4458400011,55.042049408],"type":"Point"}
}