{
  "type": "Feature",
  "properties": {
    "iso:country":"GB",
    "sg:address":"Cumberland House, 80 Scubbs Lane",
    "sg:city":"London",
    "sg:classifiers":[
        {
            "category":"Communications",
            "subcategory":"Newspaper",
            "type":"Services"
        }
    ],
    "sg:phone":"+44 20 8962 6800",
    "sg:postcode":"NW10 6AH",
    "sg:province":"Greater London",
    "sg:tags":[
        "magazine"
    ],
    "wof:name":"North West London Newspapers",
    "wof:placetype":"venue"
},
  "geometry": {"coordinates":[-0.253224,51.527088],"type":"Point"}
}