{
  "type": "Feature",
  "properties": {
    "addr:full":"17 High Street Stonehouse Gloucestershire GL10 2NG",
    "addr:housenumber":"17",
    "addr:postcode":"gl10 2ng",
    "addr:street":"High Street",
    "iso:country":"GB",
    "sg:address":"17 High Street",
    "sg:city":"Stonehouse",
    "sg:classifiers":[
        {
            "category":"Shopping",
            "subcategory":"Optician",
            "type":"Retail Goods"
        },
        {
            "category":"Health Services",
            "subcategory":"Optometrist",
            "type":"Services"
        }
    ],
    "sg:phone":"+44 1453 823399",
    "sg:postcode":"GL10 2NG",
    "sg:province":"Gloucestershire",
    "sg:tags":[
        "opthalmic",
        "ophthalmic"
    ],
    "wof:name":"Michael D Bailey",
    "wof:placetype":"venue"
},
  "geometry": {"coordinates":[-2.28283,51.746746],"type":"Point"}
}