{
  "type": "Feature",
  "properties": {
    "addr:full":"191 Tyburn Road Birmingham West Midlands B24 8NQ",
    "addr:housenumber":"191",
    "addr:postcode":"b24 8nq",
    "addr:street":"Tyburn Road",
    "iso:country":"GB",
    "sg:address":"191 Tyburn Road",
    "sg:city":"Birmingham",
    "sg:classifiers":[
        {
            "category":"Retail",
            "subcategory":"Auto Rental",
            "type":"Services"
        }
    ],
    "sg:phone":"+44 121 327 0026",
    "sg:postcode":"B24 8NQ",
    "sg:province":"West Midlands",
    "sg:tags":[
        "car"
    ],
    "wof:name":"Gravelly Park Service Station",
    "wof:placetype":"venue"
},
  "geometry": {"coordinates":[-1.85108,52.507862],"type":"Point"}
}