{
  "type": "Feature",
  "properties": {
    "addr:full":"135 Levett Gardens Ilford Essex IG3 9BX",
    "addr:housenumber":"135",
    "addr:postcode":"ig3 9bx",
    "addr:street":"Levett Gardens",
    "iso:country":"GB",
    "sg:address":"135 Levett Gardens",
    "sg:city":"Ilford",
    "sg:classifiers":[
        {
            "category":"Professional",
            "subcategory":"Art Services",
            "type":"Services"
        },
        {
            "category":"Building & Trades",
            "subcategory":"Construction",
            "type":"Services"
        }
    ],
    "sg:phone":"+44 20 8590 0891",
    "sg:postcode":"IG3 9BX",
    "sg:province":"Essex",
    "sg:tags":[
        "decorator",
        "painter"
    ],
    "wof:name":"DENNIS LAMEY",
    "wof:placetype":"venue"
},
  "geometry": {"coordinates":[0.1079579964,51.5554542542],"type":"Point"}
}