{
  "type": "Feature",
  "properties": {
    "addr:full":"76 Thirlmere Road, Partington Manchester Cheshire M31 4PT",
    "addr:housenumber":"76",
    "addr:postcode":"m31 4pt",
    "addr:street":"Thirlmere Road",
    "iso:country":"GB",
    "sg:address":"76 Thirlmere Road, Partington",
    "sg:city":"Manchester",
    "sg:classifiers":[
        {
            "category":"Professional",
            "subcategory":"Art Services",
            "type":"Services"
        },
        {
            "category":"Building & Trades",
            "subcategory":"Construction",
            "type":"Services"
        }
    ],
    "sg:phone":"+44 161 775 4172",
    "sg:postcode":"M31 4PT",
    "sg:province":"Cheshire",
    "sg:tags":[
        "decorator",
        "painter"
    ],
    "wof:name":"CHARLES F HALLIGAN",
    "wof:placetype":"venue"
},
  "geometry": {"coordinates":[-2.4315369129,53.421207428],"type":"Point"}
}