{
  "type": "Feature",
  "properties": {
    "iso:country":"GB",
    "sg:address":"Hall Farm, Cockerhouse Road, Eastwood",
    "sg:city":"Nottingham",
    "sg:classifiers":[
        {
            "category":"Farming",
            "subcategory":"Farm",
            "type":"Manufacturing & Wholesale Goods"
        }
    ],
    "sg:phone":"+44 1773 713661",
    "sg:postcode":"NG16 3DX",
    "sg:province":"Derbyshire",
    "sg:tags":[
        "mixed",
        "crop"
    ],
    "wof:name":"Jas Noon",
    "wof:placetype":"venue"
},
  "geometry": {"coordinates":[-1.292701,53.01403],"type":"Point"}
}