{
  "type": "Feature",
  "properties": {
    "addr:full":"Unit 2 Hampton Court Estate, Summer Road Thames Ditton Surrey KT7 0RG",
    "addr:housenumber":"unit 2",
    "addr:postcode":"kt7 0rg",
    "addr:street":"Hampton Court Estate Summer Road",
    "iso:country":"GB",
    "sg:address":"Unit 2 Hampton Court Estate, Summer Road",
    "sg:city":"Thames Ditton",
    "sg:classifiers":[
        {
            "category":"Autos & Motor Vehicles",
            "subcategory":"Motorcycle Sales",
            "type":"Retail Goods"
        }
    ],
    "sg:phone":"+44 20 8398 8304",
    "sg:postcode":"KT7 0RG",
    "sg:province":"Surrey",
    "sg:tags":[
        "chauffeur",
        "driven",
        "car"
    ],
    "wof:name":"Braemar Chauffeur Services",
    "wof:placetype":"venue"
},
  "geometry": {"coordinates":[-0.3390620053,51.3963470459],"type":"Point"}
}