{
  "type": "Feature",
  "properties": {
    "iso:country":"GB",
    "sg:address":"Westfield Complex, Cardenden",
    "sg:city":"Lochgelly",
    "sg:classifiers":[
        {
            "category":"Mining & Drilling",
            "type":"Manufacturing & Wholesale Goods"
        }
    ],
    "sg:phone":"+44 1592 882448",
    "sg:postcode":"KY5 0HN",
    "sg:province":"Fife",
    "sg:tags":[
        "coal"
    ],
    "wof:name":"Scottish Coal Co.Ltd",
    "wof:placetype":"venue"
},
  "geometry": {"coordinates":[-3.263912,56.147362],"type":"Point"}
}