{
  "type": "Feature",
  "properties": {
    "iso:country":"GB",
    "sg:address":"2 South Street",
    "sg:city":"Seahouses",
    "sg:classifiers":[
        {
            "category":"Farming",
            "subcategory":"Fish & Marine Products",
            "type":"Manufacturing & Wholesale Goods"
        }
    ],
    "sg:phone":"+44 1665 721052",
    "sg:postcode":"NE68 7RB",
    "sg:province":"Northumberland",
    "sg:tags":[
        "fishmonger"
    ],
    "wof:name":"Swallow Fish Ltd.",
    "wof:placetype":"venue"
},
  "geometry": {"coordinates":[-1.6485140324,55.5817489624],"type":"Point"}
}