{
  "type": "Feature",
  "properties": {
    "iso:country":"GB",
    "sg:address":"628 Wellsway",
    "sg:city":"Bath",
    "sg:classifiers":[
        {
            "category":"Bars & Pubs",
            "type":"Food & Drink"
        }
    ],
    "sg:phone":"+44 1225 833616",
    "sg:postcode":"BA2 2UE",
    "sg:province":"Somerset",
    "sg:tags":[
        "pubs",
        "inn"
    ],
    "wof:name":"Strydes",
    "wof:placetype":"venue"
},
  "geometry": {"coordinates":[-2.382495,51.354694],"type":"Point"}
}