{
  "type": "Feature",
  "properties": {
    "iso:country":"GB",
    "sg:address":"15 Church Street",
    "sg:city":"Highbridge",
    "sg:classifiers":[
        {
            "category":"Autos & Motor Vehicles",
            "subcategory":"Auto Supplies",
            "type":"Retail Goods"
        },
        {
            "category":"Shopping",
            "type":"Retail Goods"
        }
    ],
    "sg:phone":"+44 1278 784400",
    "sg:postcode":"TA9 3AF",
    "sg:province":"Somerset",
    "sg:tags":[
        "car",
        "part",
        "accessory"
    ],
    "wof:name":"Harry Parkes Motor Spares",
    "wof:placetype":"venue"
},
  "geometry": {"coordinates":[-2.975218,51.221134],"type":"Point"}
}