{
  "type": "Feature",
  "properties": {
    "iso:country":"GB",
    "sg:address":"Unit E3, Copley Hill Trading Estate, Whitehall Road",
    "sg:city":"Leeds",
    "sg:classifiers":[
        {
            "category":"Manufacturing",
            "subcategory":"Building Materials",
            "type":"Manufacturing & Wholesale Goods"
        }
    ],
    "sg:phone":"+44 113 242 4448",
    "sg:postcode":"LS12 1HE",
    "sg:province":"West Yorkshire",
    "sg:tags":[
        "merchant",
        "builder"
    ],
    "wof:name":"TRAVIS PERKINS TRADING CO LTD",
    "wof:placetype":"venue"
},
  "geometry": {"coordinates":[-1.572807,53.789841],"type":"Point"}
}