{
  "type": "Feature",
  "properties": {
    "iso:country":"GB",
    "sg:address":"117 Cumberland Road",
    "sg:city":"Reading",
    "sg:classifiers":[
        {
            "category":"Education",
            "subcategory":"Special Training",
            "type":"Public Place"
        }
    ],
    "sg:phone":"+44 118 926 7758",
    "sg:postcode":"RG1 3JY",
    "sg:province":"Berkshire",
    "sg:tags":[
        "aid",
        "first"
    ],
    "wof:name":"St.John Ambulance",
    "wof:placetype":"venue"
},
  "geometry": {"coordinates":[-0.951168,51.455952],"type":"Point"}
}