{
  "type": "Feature",
  "properties": {
    "iso:country":"GB",
    "sg:address":"12 Collingwood Road",
    "sg:city":"Shanklin",
    "sg:classifiers":[
        {
            "category":"Travel",
            "subcategory":"Hotels & Motels",
            "type":"Entertainment"
        }
    ],
    "sg:postcode":"PO37 7LR",
    "sg:province":"Isle of Wight",
    "wof:name":"The Westboro",
    "wof:placetype":"venue"
},
  "geometry": {"coordinates":[-1.1811989546,50.63123703],"type":"Point"}
}