{
  "type": "Feature",
  "properties": {
    "iso:country":"GB",
    "sg:address":"Ousegate",
    "sg:city":"Selby",
    "sg:classifiers":[
        {
            "category":"Freight",
            "type":"Transportation"
        }
    ],
    "sg:phone":"+44 1757 706168",
    "sg:postcode":"YO8 8BL",
    "sg:province":"East Riding of Yorkshire",
    "sg:tags":[
        "haulage",
        "road"
    ],
    "wof:name":"Fleetbush Ltd.",
    "wof:placetype":"venue"
},
  "geometry": {"coordinates":[-1.060354,53.7831],"type":"Point"}
}