{
  "type": "Feature",
  "properties": {
    "addr:full":"Unit 13, Cadzow Ind Est Hamilton South Lanarkshire ML3 7QU",
    "addr:housenumber":"unit 13",
    "addr:postcode":"ml3 7qu",
    "addr:street":"Cadzow Ind Est",
    "iso:country":"GB",
    "sg:address":"Unit 13, Cadzow Ind Est",
    "sg:city":"Hamilton",
    "sg:classifiers":[
        {
            "category":"Sports & Exercise",
            "subcategory":"Playing Field",
            "type":"Entertainment"
        }
    ],
    "sg:phone":"+44 1698 891171",
    "sg:postcode":"ML3 7QU",
    "sg:province":"South Lanarkshire",
    "sg:tags":[
        "sanitary",
        "hygiene",
        "appliance"
    ],
    "wof:name":"Cadzow Home Improvments",
    "wof:placetype":"venue"
},
  "geometry": {"coordinates":[-4.0320792198,55.7391052246],"type":"Point"}
}