{
  "type": "Feature",
  "properties": {
    "iso:country":"GB",
    "sg:address":"High Gosforth Park",
    "sg:city":"Newcastle-upon-tyne",
    "sg:classifiers":[
        {
            "category":"Personal",
            "subcategory":"Beauty Salon",
            "type":"Services"
        },
        {
            "category":"Personal",
            "subcategory":"Barber",
            "type":"Services"
        }
    ],
    "sg:phone":"+44 191 217 0217",
    "sg:postcode":"NE3 5HN",
    "sg:province":"Tyne and Wear",
    "sg:tags":[
        "unisex",
        "hairdresser"
    ],
    "wof:name":"Gary Hooker Hairdressing",
    "wof:placetype":"venue"
},
  "geometry": {"coordinates":[-1.594745,55.019596],"type":"Point"}
}