{
  "type": "Feature",
  "properties": {
    "addr:full":"Queensway House, Queensway Hatfield Hertfordshire AL10 0LW",
    "addr:postcode":"al10 0lw",
    "addr:street":"Queensway",
    "iso:country":"GB",
    "sg:address":"Queensway House, Queensway",
    "sg:city":"Hatfield",
    "sg:classifiers":[
        {
            "category":"Personal",
            "type":"Services"
        },
        {
            "category":"Professional",
            "subcategory":"Lawyer & Legal Services",
            "type":"Services"
        }
    ],
    "sg:phone":"+44 1707 260934",
    "sg:postcode":"AL10 0LW",
    "sg:province":"Hertfordshire",
    "sg:tags":[
        "advice",
        "counselling"
    ],
    "wof:name":"Welwyn Hatfield Citizens Advice Bureau",
    "wof:placetype":"venue"
},
  "geometry": {"coordinates":[-0.2242,51.763199],"type":"Point"}
}