{
  "type": "Feature",
  "properties": {
    "addr:full":"14 Market Street, Kidsgrove Stoke-on-trent Cheshire ST7 4AB",
    "addr:housenumber":"14",
    "addr:postcode":"st7 4ab",
    "addr:street":"Market Street",
    "iso:country":"GB",
    "sg:address":"14 Market Street, Kidsgrove",
    "sg:city":"Stoke-on-trent",
    "sg:classifiers":[
        {
            "category":"Personal",
            "subcategory":"Beauty Salon",
            "type":"Services"
        }
    ],
    "sg:phone":"+44 1782 782149",
    "sg:postcode":"ST7 4AB",
    "sg:province":"Cheshire",
    "sg:tags":[
        "unisex",
        "hairdresser"
    ],
    "wof:name":"Pop-in",
    "wof:placetype":"venue"
},
  "geometry": {"coordinates":[-2.239384,53.087219],"type":"Point"}
}