{
  "type": "Feature",
  "properties": {
    "iso:country":"GB",
    "sg:address":"New Bungalow, Francis Grn Lane, Penkridge",
    "sg:city":"Stafford",
    "sg:classifiers":[
        {
            "category":"Autos & Motor Vehicles",
            "subcategory":"Automobile Sales",
            "type":"Retail Goods"
        }
    ],
    "sg:postcode":"ST19 5HE",
    "sg:province":"Shropshire",
    "sg:tags":[
        "car"
    ],
    "wof:name":"J A Bond Car Sales",
    "wof:placetype":"venue"
},
  "geometry": {"coordinates":[-2.11634,52.722607],"type":"Point"}
}