{
  "type": "Feature",
  "properties": {
    "addr:full":"28b Mentmore Road, Linslade Leighton Buzzard Bedfordshire LU7 2NZ",
    "addr:housenumber":"28b",
    "addr:postcode":"lu7 2nz",
    "addr:street":"Mentmore Road",
    "iso:country":"GB",
    "sg:address":"28b Mentmore Road, Linslade",
    "sg:city":"Leighton Buzzard",
    "sg:classifiers":[
        {
            "category":"Building & Trades",
            "subcategory":"Construction",
            "type":"Services"
        }
    ],
    "sg:phone":"+44 1525 854979",
    "sg:postcode":"LU7 2NZ",
    "sg:province":"Bedfordshire",
    "sg:tags":[
        "builder"
    ],
    "wof:name":"Rosebury Developments Ltd.",
    "wof:placetype":"venue"
},
  "geometry": {"coordinates":[-0.673083,51.913902],"type":"Point"}
}