{
  "type": "Feature",
  "properties": {
    "addr:full":"Unit 4 Aldermans Grn Industrial Estate, Redland Close Coventry Warwickshire CV2 2NP",
    "addr:housenumber":"unit 4",
    "addr:postcode":"cv2 2np",
    "addr:street":"Aldermans Grn Industrial Estate Redland Close",
    "iso:country":"GB",
    "sg:address":"Unit 4 Aldermans Grn Industrial Estate, Redland Close",
    "sg:city":"Coventry",
    "sg:classifiers":[
        {
            "category":"Manufacturing",
            "subcategory":"Tools & Machinery",
            "type":"Manufacturing & Wholesale Goods"
        }
    ],
    "sg:phone":"+44 24 7660 3500",
    "sg:postcode":"CV2 2NP",
    "sg:province":"Warwickshire",
    "sg:tags":[
        "design",
        "maker"
    ],
    "wof:name":"D B Precision",
    "wof:placetype":"venue"
},
  "geometry": {"coordinates":[-1.437073946,52.4366493225],"type":"Point"}
}