{
  "type": "Feature",
  "properties": {
    "addr:full":"3 Church Street Ross-on-wye Gloucestershire HR9 5HN",
    "addr:housenumber":"3",
    "addr:postcode":"hr9 5hn",
    "addr:street":"Church Street",
    "iso:country":"GB",
    "sg:address":"3 Church Street",
    "sg:city":"Ross-on-wye",
    "sg:classifiers":[
        {
            "category":"Personal",
            "subcategory":"Beauty Salon",
            "type":"Services"
        }
    ],
    "sg:phone":"+44 1989 564579",
    "sg:postcode":"HR9 5HN",
    "sg:province":"Gloucestershire",
    "wof:name":"Ross Health & Beauty Centre",
    "wof:placetype":"venue"
},
  "geometry": {"coordinates":[-2.584717,51.914032],"type":"Point"}
}