{
  "type": "Feature",
  "properties": {
    "addr:full":"Unit 23, Enterprise Workshops, Lower Trostre Road Llanelli Carmarthenshire SA15 2EA",
    "addr:housenumber":"unit 23",
    "addr:postcode":"sa15 2ea",
    "addr:street":"Enterprise Workshops Lower Trostre Road",
    "iso:country":"GB",
    "sg:address":"Unit 23, Enterprise Workshops, Lower Trostre Road",
    "sg:city":"Llanelli",
    "sg:classifiers":[
        {
            "category":"Retail",
            "subcategory":"Auto Repair",
            "type":"Services"
        }
    ],
    "sg:postcode":"SA15 2EA",
    "sg:province":"Carmarthenshire",
    "sg:tags":[
        "modification",
        "garage"
    ],
    "wof:name":"Motormend",
    "wof:placetype":"venue"
},
  "geometry": {"coordinates":[-4.1342988014,51.6826820374],"type":"Point"}
}