{
  "type": "Feature",
  "properties": {
    "addr:full":"Unit 1 Wem Engineering Centre, Church Lane Wem Shrewsbury Shropshire SY4 5HS",
    "addr:housenumber":"unit 1",
    "addr:postcode":"sy4 5hs",
    "addr:street":"Church Lane",
    "iso:country":"GB",
    "sg:address":"Unit 1 Wem Engineering Centre, Church Lane Wem",
    "sg:city":"Shrewsbury",
    "sg:classifiers":[
        {
            "category":"Home & Garden",
            "subcategory":"Hardware",
            "type":"Retail Goods"
        }
    ],
    "sg:phone":"+44 1939 236236",
    "sg:postcode":"SY4 5HS",
    "sg:province":"Shropshire",
    "sg:tags":[
        "device",
        "fixing",
        "fastener"
    ],
    "wof:name":"Excel Metalform Techniques",
    "wof:placetype":"venue"
},
  "geometry": {"coordinates":[-2.70851,52.85783],"type":"Point"}
}