{
  "type": "Feature",
  "properties": {
    "addr:full":"9 Linksview Rd Motherwell North Lanarkshire ML1 4AT",
    "addr:housenumber":"9",
    "addr:postcode":"ml1 4at",
    "addr:street":"Linksview Rd",
    "iso:country":"GB",
    "sg:address":"9 Linksview Rd",
    "sg:city":"Motherwell",
    "sg:classifiers":[
        {
            "category":"Building & Trades",
            "subcategory":"Cleaning & Sanitation",
            "type":"Services"
        }
    ],
    "sg:phone":"+44 1698 275359",
    "sg:postcode":"ML1 4AT",
    "sg:province":"North Lanarkshire",
    "sg:tags":[
        "commercial"
    ],
    "wof:name":"Dublcheck",
    "wof:placetype":"venue"
},
  "geometry": {"coordinates":[-3.9747390747,55.8133201599],"type":"Point"}
}