{
  "type": "Feature",
  "properties": {
    "addr:full":"Llwynfelin, Llanddowror, St Clears Carmarthen Carmarthenshire SA33 4JE",
    "addr:postcode":"sa33 4je",
    "addr:street":"Llanddowror;Clears;Carmarthenshire",
    "iso:country":"GB",
    "sg:address":"Llwynfelin, Llanddowror, St Clears",
    "sg:city":"Carmarthen",
    "sg:classifiers":[
        {
            "category":"Farming",
            "subcategory":"Livestock Farm",
            "type":"Manufacturing & Wholesale Goods"
        }
    ],
    "sg:phone":"+44 1994 240419",
    "sg:postcode":"SA33 4JE",
    "sg:province":"Carmarthenshire",
    "sg:tags":[
        "others"
    ],
    "wof:name":"M C  &G M Powell",
    "wof:placetype":"venue"
},
  "geometry": {"coordinates":[-4.582449913,51.7799606323],"type":"Point"}
}