{
  "type": "Feature",
  "properties": {
    "iso:country":"GB",
    "sg:address":"3 Brattles Grange Cotts, Tibbs Court Lane, Brenchley",
    "sg:city":"Tonbridge",
    "sg:classifiers":[
        {
            "category":"Professional",
            "type":"Services"
        }
    ],
    "sg:phone":"+44 1892 723376",
    "sg:postcode":"TN12 7AJ",
    "sg:province":"Kent",
    "sg:tags":[
        "entertainer"
    ],
    "wof:name":"Barn Dance to Banquet",
    "wof:placetype":"venue"
},
  "geometry": {"coordinates":[0.400162,51.151306],"type":"Point"}
}