{
  "type": "Feature",
  "properties": {
    "addr:full":"Mundles Farm, Mundles Lane East Boldon Tyne and Wear NE36 0AW",
    "addr:postcode":"ne36 0aw",
    "addr:street":"Mundles Lane",
    "iso:country":"GB",
    "sg:address":"Mundles Farm, Mundles Lane",
    "sg:city":"East Boldon",
    "sg:classifiers":[
        {
            "category":"Professional",
            "type":"Services"
        },
        {
            "category":"Banks & Credit Unions",
            "subcategory":"Investment Brokerage",
            "type":"Services"
        }
    ],
    "sg:phone":"+44 191 536 6076",
    "sg:postcode":"NE36 0AW",
    "sg:province":"Tyne and Wear",
    "sg:tags":[
        "farm",
        "agricultural",
        "contractor"
    ],
    "wof:name":"PETER ALDERSLADE",
    "wof:placetype":"venue"
},
  "geometry": {"coordinates":[-1.4319729805,54.9442863464],"type":"Point"}
}