{
  "type": "Feature",
  "properties": {
    "addr:full":"Station Road, Mursley Milton Keynes Bedfordshire MK17 0SA",
    "addr:postcode":"mk17 0sa",
    "addr:street":"Station Road",
    "iso:country":"GB",
    "sg:address":"Station Road, Mursley",
    "sg:city":"Milton Keynes",
    "sg:classifiers":[
        {
            "category":"Retail",
            "subcategory":"Auto Repair",
            "type":"Services"
        }
    ],
    "sg:phone":"+44 1296 720376",
    "sg:postcode":"MK17 0SA",
    "sg:province":"Bedfordshire",
    "sg:tags":[
        "modification",
        "garage"
    ],
    "wof:name":"A & B Garage",
    "wof:placetype":"venue"
},
  "geometry": {"coordinates":[-0.81375,51.943604],"type":"Point"}
}