{
  "type": "Feature",
  "properties": {
    "addr:full":"1 Campsfield Road London Greater London N8 7AL",
    "addr:housenumber":"1",
    "addr:postcode":"n8 7al",
    "addr:street":"Campsfield Road",
    "iso:country":"GB",
    "sg:address":"1 Campsfield Road",
    "sg:city":"London",
    "sg:classifiers":[
        {
            "category":"Parking",
            "type":"Transportation"
        }
    ],
    "sg:phone":"+44 20 8348 7055",
    "sg:postcode":"N8 7AL",
    "sg:province":"Greater London",
    "sg:tags":[
        "car",
        "valet"
    ],
    "wof:name":"CLEAN CLASSY CARS",
    "wof:placetype":"venue"
},
  "geometry": {"coordinates":[-0.1192149967,51.590877533],"type":"Point"}
}