{
  "type": "Feature",
  "properties": {
    "iso:country":"GB",
    "sg:address":"Flax Lane, Glemsford",
    "sg:city":"Sudbury",
    "sg:classifiers":[
        {
            "category":"Home & Garden",
            "subcategory":"Home Furnishings",
            "type":"Retail Goods"
        },
        {
            "category":"Military Area",
            "subcategory":"Air Force Base",
            "type":"Public Place"
        }
    ],
    "sg:postcode":"CO10 7RS",
    "sg:province":"Essex",
    "sg:tags":[
        "decorative",
        "mnfr",
        "mirror",
        "glass"
    ],
    "wof:name":"2 Uk Mirror",
    "wof:placetype":"venue"
},
  "geometry": {"coordinates":[0.668990016,52.0964546204],"type":"Point"}
}