{
  "type": "Feature",
  "properties": {
    "addr:full":"22 Orchard Avenue, Midsomer Norton Bath Somerset BA3 2QZ",
    "addr:housenumber":"22",
    "addr:postcode":"ba3 2qz",
    "addr:street":"Orchard Avenue",
    "iso:country":"GB",
    "sg:address":"22 Orchard Avenue, Midsomer Norton",
    "sg:city":"Bath",
    "sg:classifiers":[
        {
            "category":"Building & Trades",
            "subcategory":"Construction",
            "type":"Services"
        }
    ],
    "sg:phone":"+44 7702 024501",
    "sg:postcode":"BA3 2QZ",
    "sg:province":"Somerset",
    "sg:tags":[
        "builder"
    ],
    "wof:name":"Kemp Building & Maintenance Ltd.",
    "wof:placetype":"venue"
},
  "geometry": {"coordinates":[-2.4936931133,51.2869338989],"type":"Point"}
}