{
  "type": "Feature",
  "properties": {
    "addr:full":"10 Levitt Cottage, Wrythe Lane Carshalton Surrey SM5 2RN",
    "addr:housenumber":"10",
    "addr:postcode":"sm5 2rn",
    "addr:street":"Wrythe Lane",
    "iso:country":"GB",
    "sg:address":"10 Levitt Cottage, Wrythe Lane",
    "sg:city":"Carshalton",
    "sg:classifiers":[
        {
            "category":"Personal",
            "subcategory":"Beauty Salon",
            "type":"Services"
        }
    ],
    "sg:postcode":"SM5 2RN",
    "sg:province":"Surrey",
    "sg:tags":[
        "lady",
        "hairdresser"
    ],
    "wof:name":"Torva Lisa Ladies Hairdressing",
    "wof:placetype":"venue"
},
  "geometry": {"coordinates":[-0.161094,51.365288],"type":"Point"}
}