{
  "type": "Feature",
  "properties": {
    "addr:full":"Longmoor La Liverpool Merseyside L10 1LD",
    "addr:postcode":"l10 1ld",
    "addr:street":"La",
    "iso:country":"GB",
    "sg:address":"Longmoor La",
    "sg:city":"Liverpool",
    "sg:classifiers":[
        {
            "category":"Government",
            "subcategory":"Office",
            "type":"Public Place"
        }
    ],
    "sg:phone":"+44 151 525 8126",
    "sg:postcode":"L10 1LD",
    "sg:province":"Merseyside",
    "sg:tags":[
        "local"
    ],
    "wof:name":"Liverpool City Council",
    "wof:placetype":"venue"
},
  "geometry": {"coordinates":[-2.919489,53.469833],"type":"Point"}
}