{
  "type": "Feature",
  "properties": {
    "iso:country":"GB",
    "sg:address":"19 Kirkland Avenue, Clayhall",
    "sg:city":"Ilford",
    "sg:classifiers":[
        {
            "category":"Banks & Credit Unions",
            "subcategory":"Bank",
            "type":"Services"
        }
    ],
    "sg:phone":"+44 20 8924 0009",
    "sg:postcode":"IG5 0TQ",
    "sg:province":"Essex",
    "sg:tags":[
        "broker",
        "mortgage"
    ],
    "wof:name":"George Associates",
    "wof:placetype":"venue"
},
  "geometry": {"coordinates":[0.065397,51.593288],"type":"Point"}
}