{
  "type": "Feature",
  "properties": {
    "addr:full":"154 Reid Street Glasgow Glasgow City G40 4EN",
    "addr:housenumber":"154",
    "addr:postcode":"g40 4en",
    "addr:street":"Reid Street",
    "iso:country":"GB",
    "sg:address":"154 Reid Street",
    "sg:city":"Glasgow",
    "sg:classifiers":[
        {
            "category":"Autos & Motor Vehicles",
            "subcategory":"Auto Supplies",
            "type":"Retail Goods"
        }
    ],
    "sg:phone":"+44 141 556 6581",
    "sg:postcode":"G40 4EN",
    "sg:province":"Glasgow City",
    "sg:tags":[
        "tyre"
    ],
    "wof:name":"Motorway Tyres & Accessories Ltd",
    "wof:placetype":"venue"
},
  "geometry": {"coordinates":[-4.224873,55.842354],"type":"Point"}
}