{
  "type": "Feature",
  "properties": {
    "iso:country":"GB",
    "sg:address":"1 William Street, Churwell, Morley",
    "sg:city":"Leeds",
    "sg:classifiers":[
        {
            "category":"Shopping",
            "subcategory":"News",
            "type":"Retail Goods"
        }
    ],
    "sg:phone":"+44 113 253 5466",
    "sg:postcode":"LS27 7RE",
    "sg:province":"West Yorkshire",
    "sg:tags":[
        "newsagent"
    ],
    "wof:name":"United News Shops Ltd.",
    "wof:placetype":"venue"
},
  "geometry": {"coordinates":[-1.5879089832,53.7618103027],"type":"Point"}
}