{
  "type": "Feature",
  "properties": {
    "addr:full":"409 Dudley Road, Winson Grn Birmingham West Midlands B18 4HD",
    "addr:housenumber":"409",
    "addr:postcode":"b18 4hd",
    "addr:street":"Dudley Road;Grn",
    "iso:country":"GB",
    "sg:address":"409 Dudley Road, Winson Grn",
    "sg:city":"Birmingham",
    "sg:classifiers":[
        {
            "category":"Shopping",
            "subcategory":"Stationery & Office Supplies",
            "type":"Retail Goods"
        }
    ],
    "sg:phone":"+44 121 565 4950",
    "sg:postcode":"B18 4HD",
    "sg:province":"West Midlands",
    "sg:tags":[
        "equipment"
    ],
    "wof:name":"N & Z Office Supplies",
    "wof:placetype":"venue"
},
  "geometry": {"coordinates":[-1.9460129738,52.4874038696],"type":"Point"}
}