{
  "type": "Feature",
  "properties": {
    "iso:country":"GB",
    "sg:address":"Unit 8 Lonlas Village Workshop, Lonlas Business Park Skewen",
    "sg:city":"Neath",
    "sg:classifiers":[
        {
            "category":"Building & Trades",
            "subcategory":"Construction",
            "type":"Services"
        }
    ],
    "sg:phone":"+44 1792 815561",
    "sg:postcode":"SA10 6RP",
    "sg:province":"Neath Port Talbot",
    "sg:tags":[
        "joiner",
        "carpenter"
    ],
    "wof:name":"Skewen Joinery Services",
    "wof:placetype":"venue"
},
  "geometry": {"coordinates":[-3.860088,51.659138],"type":"Point"}
}