{
  "type": "Feature",
  "properties": {
    "addr:full":"Room G40 Five Ways House, Islington Row, Middleway Birmingham West Midlands B15 1SL",
    "addr:housenumber":"g40 five;house",
    "addr:postcode":"b15 1sl",
    "addr:street":"Islington Row Middleway",
    "iso:country":"GB",
    "sg:address":"Room G40 Five Ways House, Islington Row, Middleway",
    "sg:city":"Birmingham",
    "sg:classifiers":[
        {
            "category":"Real Estate",
            "subcategory":"Surveying",
            "type":"Services"
        }
    ],
    "sg:phone":"+44 121 626 2856",
    "sg:postcode":"B15 1SL",
    "sg:province":"West Midlands",
    "sg:tags":[
        "surveyor",
        "land"
    ],
    "wof:name":"Ordnance Survey",
    "wof:placetype":"venue"
},
  "geometry": {"coordinates":[-1.9152439833,52.4721984863],"type":"Point"}
}