{
  "type": "Feature",
  "properties": {
    "addr:full":"Pebley Hill Farm, Icomb Road, Bledington Chipping Norton Gloucestershire OX7 6XJ",
    "addr:postcode":"norton;ox7 6xj",
    "addr:street":"Pebley Hill;Icomb Road",
    "iso:country":"GB",
    "sg:address":"Pebley Hill Farm, Icomb Road, Bledington",
    "sg:city":"Chipping Norton",
    "sg:classifiers":[
        {
            "category":"Farming",
            "subcategory":"Livestock Farm",
            "type":"Manufacturing & Wholesale Goods"
        }
    ],
    "sg:phone":"+44 1608 658312",
    "sg:postcode":"OX7 6XJ",
    "sg:province":"Gloucestershire",
    "sg:tags":[
        "others"
    ],
    "wof:name":"Robert Prentice",
    "wof:placetype":"venue"
},
  "geometry": {"coordinates":[-1.647899,51.903873],"type":"Point"}
}