{
  "type": "Feature",
  "properties": {
    "iso:country":"GB",
    "sg:address":"Tong Hall, Tong Lane",
    "sg:city":"Bradford",
    "sg:classifiers":[
        {
            "category":"Banks & Credit Unions",
            "subcategory":"Bank",
            "type":"Services"
        },
        {
            "category":"Professional",
            "subcategory":"Credit Reporting & Collection",
            "type":"Services"
        }
    ],
    "sg:phone":"+44 113 287 9123",
    "sg:postcode":"BD4 0RR",
    "sg:province":"West Yorkshire",
    "sg:tags":[
        "collecting",
        "agency",
        "institution",
        "related"
    ],
    "wof:name":"Direct Route Collections Ltd.",
    "wof:placetype":"venue"
},
  "geometry": {"coordinates":[-1.663764,53.772091],"type":"Point"}
}