{
  "type": "Feature",
  "properties": {
    "iso:country":"GB",
    "sg:address":"Speculation Place",
    "sg:city":"Washington",
    "sg:classifiers":[
        {
            "category":"Bars & Pubs",
            "type":"Food & Drink"
        }
    ],
    "sg:phone":"+44 191 416 0284",
    "sg:postcode":"NE37 2AS",
    "sg:province":"Tyne and Wear",
    "sg:tags":[
        "pubs",
        "inn"
    ],
    "wof:name":"Speculation Inn",
    "wof:placetype":"venue"
},
  "geometry": {"coordinates":[-1.519009,54.912563],"type":"Point"}
}