{
  "type": "Feature",
  "properties": {
    "iso:country":"GB",
    "sg:address":"255 Packington Avenue",
    "sg:city":"Birmingham",
    "sg:classifiers":[
        {
            "category":"Professional",
            "subcategory":"Accounting & Tax Preparation",
            "type":"Services"
        }
    ],
    "sg:phone":"+44 121 747 9933",
    "sg:postcode":"B34 7RU",
    "sg:province":"West Midlands",
    "sg:tags":[
        "accountant"
    ],
    "wof:name":"Accounting Service",
    "wof:placetype":"venue"
},
  "geometry": {"coordinates":[-1.76773,52.495918],"type":"Point"}
}