{
  "type": "Feature",
  "properties": {
    "iso:country":"GB",
    "sg:address":"The Level, Dittisham",
    "sg:city":"Dartmouth",
    "sg:classifiers":[
        {
            "category":"Bars & Pubs",
            "type":"Food & Drink"
        }
    ],
    "sg:phone":"+44 1803 722235",
    "sg:postcode":"TQ6 0ES",
    "sg:province":"Devon",
    "sg:tags":[
        "pubs",
        "inn"
    ],
    "wof:name":"The Red Lion Inn",
    "wof:placetype":"venue"
},
  "geometry": {"coordinates":[-3.603538,50.383839],"type":"Point"}
}