{
  "type": "Feature",
  "properties": {
    "addr:full":"Bluebird House, Povey Cross Road Horley Surrey RH6 0AF",
    "addr:postcode":"rh6 0af",
    "addr:street":"Povey Cross Road",
    "iso:country":"GB",
    "sg:address":"Bluebird House, Povey Cross Road",
    "sg:city":"Horley",
    "sg:classifiers":[
        {
            "category":"Manufacturing",
            "subcategory":"Metals",
            "type":"Manufacturing & Wholesale Goods"
        }
    ],
    "sg:phone":"+44 1293 821143",
    "sg:postcode":"RH6 0AF",
    "sg:province":"Surrey",
    "wof:name":"Gentronics",
    "wof:placetype":"venue"
},
  "geometry": {"coordinates":[-0.1789290011,51.1671905518],"type":"Point"}
}