{
  "type": "Feature",
  "properties": {
    "iso:country":"GB",
    "sg:address":"Unit 8, Commerce Way, Lawford",
    "sg:city":"Manningtree",
    "sg:classifiers":[
        {
            "category":"Manufacturing",
            "subcategory":"Metals",
            "type":"Manufacturing & Wholesale Goods"
        }
    ],
    "sg:phone":"+44 1206 396539",
    "sg:postcode":"CO11 1UT",
    "sg:province":"Essex",
    "wof:name":"K M Finishing",
    "wof:placetype":"venue"
},
  "geometry": {"coordinates":[1.057152,51.947971],"type":"Point"}
}