{
  "type": "Feature",
  "properties": {
    "iso:country":"GB",
    "sg:address":"5-10 Crown Works, Temple St",
    "sg:city":"Bethnal Green",
    "sg:classifiers":[
        {
            "category":"Professional",
            "subcategory":"Printing & Photocopies",
            "type":"Services"
        },
        {
            "category":"Shopping",
            "subcategory":"Photographic Equipment",
            "type":"Retail Goods"
        }
    ],
    "sg:phone":"+44 20 7729 9663",
    "sg:postcode":"E2 6QQ",
    "sg:province":"Greater London",
    "sg:tags":[
        "screen",
        "printer"
    ],
    "wof:name":"The Mangle",
    "wof:placetype":"venue"
},
  "geometry": {"coordinates":[-0.06062,51.530548],"type":"Point"}
}