{
  "type": "Feature",
  "properties": {
    "iso:country":"GB",
    "sg:address":"3a Macclesfield Rd, Holmes Chapel",
    "sg:city":"Crewe",
    "sg:classifiers":[
        {
            "category":"Professional",
            "subcategory":"Lawyer & Legal Services",
            "type":"Services"
        }
    ],
    "sg:phone":"+44 1477 534488",
    "sg:postcode":"CW4 7NF",
    "sg:province":"Cheshire",
    "sg:tags":[
        "solicitor"
    ],
    "wof:name":"Poole Alcock & Co",
    "wof:placetype":"venue"
},
  "geometry": {"coordinates":[-2.357178,53.202572],"type":"Point"}
}