{
  "type": "Feature",
  "properties": {
    "iso:country":"GB",
    "sg:address":"52-58 Wordsworth Terr",
    "sg:city":"Chorley",
    "sg:classifiers":[
        {
            "category":"Social Services",
            "type":"Services"
        }
    ],
    "sg:phone":"+44 1257 266081",
    "sg:postcode":"PR6 7AG",
    "sg:province":"Lancashire",
    "wof:name":"Social Services",
    "wof:placetype":"venue"
},
  "geometry": {"coordinates":[-2.623909,53.66375],"type":"Point"}
}