{
  "type": "Feature",
  "properties": {
    "iso:country":"GB",
    "sg:address":"Detection House, 4 Vaughan Way",
    "sg:city":"Leicester",
    "sg:classifiers":[
        {
            "category":"Professional",
            "subcategory":"Detective & Security Services",
            "type":"Services"
        }
    ],
    "sg:phone":"+44 116 265 4200",
    "sg:postcode":"LE1 4ST",
    "sg:province":"Leicestershire",
    "sg:tags":[
        "equipment",
        "alarm",
        "burglar",
        "system"
    ],
    "wof:name":"Abel Alarm Co. Ltd.",
    "wof:placetype":"venue"
},
  "geometry": {"coordinates":[-1.1396080256,52.6366653442],"type":"Point"}
}