{
  "type": "Feature",
  "properties": {
    "addr:full":"305 Great Portland St West End Greater London NW1 2HD",
    "addr:housenumber":"305",
    "addr:postcode":"nw1 2hd",
    "addr:street":"Great Portland St",
    "iso:country":"GB",
    "sg:address":"305 Great Portland St",
    "sg:city":"West End",
    "sg:classifiers":[
        {
            "category":"Real Estate",
            "subcategory":"Real Estate Agent",
            "type":"Services"
        }
    ],
    "sg:phone":"+44 20 7554 5800",
    "sg:postcode":"NW1 2HD",
    "sg:province":"Greater London",
    "wof:name":"Gross Fine",
    "wof:placetype":"venue"
},
  "geometry": {"coordinates":[-0.13537,51.526501],"type":"Point"}
}