{
  "type": "Feature",
  "properties": {
    "addr:full":"Martins Farm Barn, Knowsley Lane, Broadhead Bolton Lancashire BL7 0JH",
    "addr:postcode":"bl7 0jh",
    "addr:street":"Knowsley Lane",
    "iso:country":"GB",
    "sg:address":"Martins Farm Barn, Knowsley Lane, Broadhead",
    "sg:city":"Bolton",
    "sg:classifiers":[
        {
            "category":"Manufacturing",
            "subcategory":"Building Materials",
            "type":"Manufacturing & Wholesale Goods"
        }
    ],
    "sg:phone":"+44 1204 853671",
    "sg:postcode":"BL7 0JH",
    "sg:province":"Lancashire",
    "sg:tags":[
        "stonemason"
    ],
    "wof:name":"Peter Isherwood Stonework",
    "wof:placetype":"venue"
},
  "geometry": {"coordinates":[-2.3959789276,53.6383895874],"type":"Point"}
}