{
  "type": "Feature",
  "properties": {
    "addr:full":"Church Lane, Ellerkey Brough East Riding of Yorkshire HU15 2DN",
    "addr:postcode":"hu15 2dn",
    "addr:street":"Church Lane",
    "iso:country":"GB",
    "sg:address":"Church Lane, Ellerkey",
    "sg:city":"Brough",
    "sg:classifiers":[
        {
            "category":"Restaurant",
            "type":"Food & Drink"
        }
    ],
    "sg:phone":"+44 1430 423270",
    "sg:postcode":"HU15 2DN",
    "sg:province":"East Riding of Yorkshire",
    "wof:name":"The Black Horse",
    "wof:placetype":"venue"
},
  "geometry": {"coordinates":[-0.6033189893,53.7531013489],"type":"Point"}
}