{
  "type": "Feature",
  "properties": {
    "iso:country":"GB",
    "sg:address":"426 Malden Road",
    "sg:city":"Worcester Park",
    "sg:classifiers":[
        {
            "category":"Health Services",
            "subcategory":"Doctor",
            "type":"Services"
        }
    ],
    "sg:phone":"+44 20 8337 8180",
    "sg:postcode":"KT4 7NG",
    "sg:province":"Surrey",
    "sg:tags":[
        "practitioners"
    ],
    "wof:name":"Dr A M Lewis",
    "wof:placetype":"venue"
},
  "geometry": {"coordinates":[-0.246889,51.381691],"type":"Point"}
}