{
  "type": "Feature",
  "properties": {
    "addr:full":"175 Silverdale Road Tunbridge Wells Kent TN4 9HT",
    "addr:housenumber":"175",
    "addr:postcode":"tn4 9ht",
    "addr:street":"Silverdale Road",
    "iso:country":"GB",
    "sg:address":"175 Silverdale Road",
    "sg:city":"Tunbridge Wells",
    "sg:classifiers":[
        {
            "category":"Food & Beverages",
            "subcategory":"Meat & Fish",
            "type":"Retail Goods"
        }
    ],
    "sg:phone":"+44 1892 543179",
    "sg:postcode":"TN4 9HT",
    "sg:province":"Kent",
    "sg:tags":[
        "butcher"
    ],
    "wof:name":"K Jones",
    "wof:placetype":"venue"
},
  "geometry": {"coordinates":[0.2740400136,51.1470108032],"type":"Point"}
}