{
  "type": "Feature",
  "properties": {
    "iso:country":"GB",
    "sg:address":"9 Hatton Street",
    "sg:city":"London",
    "sg:classifiers":[
        {
            "category":"Real Estate",
            "subcategory":"Architect",
            "type":"Services"
        }
    ],
    "sg:phone":"+44 20 7723 3010",
    "sg:postcode":"NW8 8PL",
    "sg:province":"Greater London",
    "wof:name":"Nightingale Associates",
    "wof:placetype":"venue"
},
  "geometry": {"coordinates":[-0.173672,51.523369],"type":"Point"}
}