{
  "type": "Feature",
  "properties": {
    "iso:country":"GB",
    "sg:address":"34 Moor St, Shaw",
    "sg:city":"Oldham",
    "sg:classifiers":[
        {
            "category":"Health Services",
            "subcategory":"Health Practitioner",
            "type":"Services"
        }
    ],
    "sg:phone":"+44 1706 848646",
    "sg:postcode":"OL2 7BD",
    "sg:province":"Lancashire",
    "sg:tags":[
        "physiotherapist"
    ],
    "wof:name":"D.L Tregellas MCSP",
    "wof:placetype":"venue"
},
  "geometry": {"coordinates":[-2.1007940769,53.5738601685],"type":"Point"}
}