{
  "type": "Feature",
  "properties": {
    "addr:full":"11 Revelstoke Road London Greater London SW18 5NJ",
    "addr:housenumber":"11",
    "addr:postcode":"sw18 5nj",
    "addr:street":"Revelstoke Road",
    "iso:country":"GB",
    "sg:address":"11 Revelstoke Road",
    "sg:city":"London",
    "sg:classifiers":[
        {
            "category":"Home & Garden",
            "subcategory":"Home Furnishings",
            "type":"Retail Goods"
        }
    ],
    "sg:phone":"+44 20 8947 6225",
    "sg:postcode":"SW18 5NJ",
    "sg:province":"Greater London",
    "sg:tags":[
        "blind",
        "curtain",
        "fitting"
    ],
    "wof:name":"The Curtain Lady Interiors",
    "wof:placetype":"venue"
},
  "geometry": {"coordinates":[-0.201889,51.4394],"type":"Point"}
}