{
  "type": "Feature",
  "properties": {
    "addr:full":"Tower Rd Sutton Coldfield Staffordshire B75 5EW",
    "addr:postcode":"b75 5ew",
    "addr:street":"Tower Rd",
    "iso:country":"GB",
    "sg:address":"Tower Rd",
    "sg:city":"Sutton Coldfield",
    "sg:classifiers":[
        {
            "category":"Bars & Pubs",
            "type":"Food & Drink"
        }
    ],
    "sg:postcode":"B75 5EW",
    "sg:province":"Staffordshire",
    "sg:tags":[
        "pubs",
        "inn"
    ],
    "wof:name":"Pint Pot (The)",
    "wof:placetype":"venue"
},
  "geometry": {"coordinates":[-1.828484,52.591347],"type":"Point"}
}