{
  "type": "Feature",
  "properties": {
    "iso:country":"GB",
    "sg:address":"22 Hovefields Avenue",
    "sg:city":"Basildon",
    "sg:classifiers":[
        {
            "category":"Building & Trades",
            "subcategory":"Construction",
            "type":"Services"
        }
    ],
    "sg:phone":"+44 1268 725047",
    "sg:postcode":"SS13 1EB",
    "sg:province":"Essex",
    "sg:tags":[
        "roofing"
    ],
    "wof:name":"Buckley Builders",
    "wof:placetype":"venue"
},
  "geometry": {"coordinates":[0.5162150264,51.5771255493],"type":"Point"}
}