{
  "type": "Feature",
  "properties": {
    "addr:full":"Limes Farm, Balterley Crewe Cheshire CW2 5QJ",
    "addr:postcode":"cw2 5qj",
    "iso:country":"GB",
    "sg:address":"Limes Farm, Balterley",
    "sg:city":"Crewe",
    "sg:classifiers":[
        {
            "category":"Farming",
            "subcategory":"Dairy Farm",
            "type":"Manufacturing & Wholesale Goods"
        }
    ],
    "sg:phone":"+44 1270 820273",
    "sg:postcode":"CW2 5QJ",
    "sg:province":"Cheshire",
    "wof:name":"G W & S Barber",
    "wof:placetype":"venue"
},
  "geometry": {"coordinates":[-2.356648922,53.0498504639],"type":"Point"}
}