{
  "type": "Feature",
  "properties": {
    "iso:country":"GB",
    "sg:address":"Ivanhoe St",
    "sg:city":"Dudley",
    "sg:classifiers":[
        {
            "category":"Professional",
            "subcategory":"Computer Services",
            "type":"Services"
        }
    ],
    "sg:phone":"+44 1384 238883",
    "sg:postcode":"DY2 0YB",
    "sg:province":"West Midlands",
    "sg:tags":[
        "system",
        "software"
    ],
    "wof:name":"R.C.S. (Designs) Ltd",
    "wof:placetype":"venue"
},
  "geometry": {"coordinates":[-2.0990490913,52.5039710999],"type":"Point"}
}