{
  "type": "Feature",
  "properties": {
    "iso:country":"GB",
    "sg:address":"62 Carlton Avenue",
    "sg:city":"Worksop",
    "sg:classifiers":[
        {
            "category":"Professional",
            "subcategory":"Engineering",
            "type":"Services"
        }
    ],
    "sg:phone":"+44 1909 473119",
    "sg:postcode":"S81 7JZ",
    "sg:province":"Nottinghamshire",
    "sg:tags":[
        "contractor",
        "electrical",
        "engineer"
    ],
    "wof:name":"H Hughes Son (Worksop) Ltd.",
    "wof:placetype":"venue"
},
  "geometry": {"coordinates":[-1.1257810593,53.3205490112],"type":"Point"}
}