{
  "type": "Feature",
  "properties": {
    "iso:country":"GB",
    "sg:address":"166 Northdown Road",
    "sg:city":"Margate",
    "sg:classifiers":[
        {
            "category":"Real Estate",
            "subcategory":"Developer",
            "type":"Services"
        }
    ],
    "sg:phone":"+44 1843 232704",
    "sg:postcode":"CT9 2QN",
    "sg:province":"Kent",
    "sg:tags":[
        "property"
    ],
    "wof:name":"Woodbarn Properties Ltd.",
    "wof:placetype":"venue"
},
  "geometry": {"coordinates":[1.3949350119,51.3882026672],"type":"Point"}
}