{
  "type": "Feature",
  "properties": {
    "addr:full":"5 Pocket Workshops, Washington Street Bolton Lancashire BL3 5EY",
    "addr:housenumber":"5;workshops",
    "addr:postcode":"bl3 5ey",
    "addr:street":"Washington Street",
    "iso:country":"GB",
    "sg:address":"5 Pocket Workshops, Washington Street",
    "sg:city":"Bolton",
    "sg:classifiers":[
        {
            "category":"Food & Beverages",
            "subcategory":"Bakery",
            "type":"Retail Goods"
        }
    ],
    "sg:phone":"+44 1204 363762",
    "sg:postcode":"BL3 5EY",
    "sg:province":"Lancashire",
    "sg:tags":[
        "baker"
    ],
    "wof:name":"M Dad",
    "wof:placetype":"venue"
},
  "geometry": {"coordinates":[-2.4492399693,53.5738105774],"type":"Point"}
}