{
  "type": "Feature",
  "properties": {
    "addr:full":"11b St James St Newport Isle of Wight PO30 5HE",
    "addr:housenumber":"11b",
    "addr:postcode":"po30 5he",
    "addr:street":"St James St",
    "iso:country":"GB",
    "sg:address":"11b St James St",
    "sg:city":"Newport",
    "sg:classifiers":[
        {
            "category":"Manufacturing",
            "subcategory":"Signs",
            "type":"Manufacturing & Wholesale Goods"
        }
    ],
    "sg:phone":"+44 1983 520047",
    "sg:postcode":"PO30 5HE",
    "sg:province":"Isle of Wight",
    "sg:tags":[
        "nameplate"
    ],
    "wof:name":"The Sign Co Ltd",
    "wof:placetype":"venue"
},
  "geometry": {"coordinates":[-1.297013,50.701981],"type":"Point"}
}