{
  "type": "Feature",
  "properties": {
    "addr:full":"Unit 6 Old Garden House, Bridge Lane London Greater London SW11 3AD",
    "addr:housenumber":"unit 6",
    "addr:postcode":"sw11 3ad",
    "addr:street":"Old Garden;Bridge Lane",
    "iso:country":"GB",
    "sg:address":"Unit 6 Old Garden House, Bridge Lane",
    "sg:city":"London",
    "sg:classifiers":[
        {
            "category":"Organizations",
            "subcategory":"Non-profit Organization",
            "type":"Services"
        }
    ],
    "sg:phone":"+44 20 7924 3553",
    "sg:postcode":"SW11 3AD",
    "sg:province":"Greater London",
    "sg:tags":[
        "charitable",
        "organisation",
        "voluntary",
        "charity"
    ],
    "sg:website":"http://www.bobchampion.org.uk",
    "wof:name":"The Bob Champion Cancer Trust",
    "wof:placetype":"venue"
},
  "geometry": {"coordinates":[-0.167,51.474159],"type":"Point"}
}