{
  "type": "Feature",
  "properties": {
    "addr:full":"18 Arnold St Rugby Warwickshire CV21 3HD",
    "addr:housenumber":"18",
    "addr:postcode":"cv21 3hd",
    "addr:street":"Arnold St",
    "iso:country":"GB",
    "sg:address":"18 Arnold St",
    "sg:city":"Rugby",
    "sg:classifiers":[
        {
            "category":"Building & Trades",
            "subcategory":"Construction",
            "type":"Services"
        }
    ],
    "sg:postcode":"CV21 3HD",
    "sg:province":"Warwickshire",
    "sg:tags":[
        "builder"
    ],
    "wof:name":"Bowen,Peter,",
    "wof:placetype":"venue"
},
  "geometry": {"coordinates":[-1.2549129725,52.373714447],"type":"Point"}
}