{
  "type": "Feature",
  "properties": {
    "iso:country":"GB",
    "sg:address":"77 Brighton Road",
    "sg:city":"Redhill",
    "sg:classifiers":[
        {
            "category":"Manufacturing",
            "subcategory":"Signs",
            "type":"Manufacturing & Wholesale Goods"
        }
    ],
    "sg:phone":"+44 1737 778841",
    "sg:postcode":"RH1 6PS",
    "sg:province":"Surrey",
    "sg:tags":[
        "writer",
        "nameplate"
    ],
    "wof:name":"The Complete Sign Co",
    "wof:placetype":"venue"
},
  "geometry": {"coordinates":[-0.1711159945,51.2345848083],"type":"Point"}
}