{
  "type": "Feature",
  "properties": {
    "addr:full":"26a Trinity Road Weymouth Dorset DT4 8TJ",
    "addr:housenumber":"26a",
    "addr:postcode":"dt4 8tj",
    "addr:street":"Trinity Road",
    "iso:country":"GB",
    "sg:address":"26a Trinity Road",
    "sg:city":"Weymouth",
    "sg:classifiers":[
        {
            "category":"Shopping",
            "subcategory":"Antiques",
            "type":"Retail Goods"
        }
    ],
    "sg:phone":"+44 1305 779313",
    "sg:postcode":"DT4 8TJ",
    "sg:province":"Dorset",
    "wof:name":"NORTH QUAY ANTIQUES",
    "wof:placetype":"venue"
},
  "geometry": {"coordinates":[-2.456001,50.606773],"type":"Point"}
}