{
  "type": "Feature",
  "properties": {
    "iso:country":"GB",
    "sg:address":"Pennsylvania, Llanedeyrn",
    "sg:city":"Cardiff",
    "sg:classifiers":[
        {
            "category":"Education",
            "subcategory":"School",
            "type":"Public Place"
        }
    ],
    "sg:phone":"+44 29 2073 5101",
    "sg:postcode":"CF23 9LS",
    "sg:province":"Cardiff",
    "sg:tags":[
        "local",
        "authority"
    ],
    "sg:website":"http://www.cardiff.gov.uk",
    "wof:name":"Springwood County Primary School",
    "wof:placetype":"venue"
},
  "geometry": {"coordinates":[-3.153818,51.512436],"type":"Point"}
}