{
  "type": "Feature",
  "properties": {
    "addr:full":"28a St James Street Newport Isle of Wight PO30 1HY",
    "addr:housenumber":"28a",
    "addr:postcode":"po30 1hy",
    "addr:street":"St James Street",
    "iso:country":"GB",
    "sg:address":"28a St James Street",
    "sg:city":"Newport",
    "sg:classifiers":[
        {
            "category":"Banks & Credit Unions",
            "subcategory":"Financial Services",
            "type":"Services"
        }
    ],
    "sg:phone":"+44 1983 520678",
    "sg:postcode":"PO30 1HY",
    "sg:province":"Isle of Wight",
    "sg:tags":[
        "adviser",
        "independent"
    ],
    "wof:name":"Select Financial Services",
    "wof:placetype":"venue"
},
  "geometry": {"coordinates":[-1.2950359583,50.6986618042],"type":"Point"}
}