{
  "type": "Feature",
  "properties": {
    "iso:country":"GB",
    "sg:address":"5 Rookery Park, Pensnett",
    "sg:city":"Brierley Hill",
    "sg:classifiers":[
        {
            "category":"Manufacturing",
            "subcategory":"Signs",
            "type":"Manufacturing & Wholesale Goods"
        }
    ],
    "sg:phone":"+44 1384 860544",
    "sg:postcode":"DY5 4LU",
    "sg:province":"West Midlands",
    "sg:tags":[
        "commercial",
        "maker"
    ],
    "wof:name":"Supasigns & Print",
    "wof:placetype":"venue"
},
  "geometry": {"coordinates":[-2.138909,52.493027],"type":"Point"}
}