{
  "type": "Feature",
  "properties": {
    "iso:country":"GB",
    "sg:address":"11 Bridlington Road",
    "sg:city":"Watford",
    "sg:classifiers":[
        {
            "category":"Shopping",
            "subcategory":"Clothing, Apparel, & Fashions",
            "type":"Retail Goods"
        }
    ],
    "sg:postcode":"WD19 7AF",
    "sg:province":"Hertfordshire",
    "sg:tags":[
        "shop"
    ],
    "wof:name":"Ramas Style",
    "wof:placetype":"venue"
},
  "geometry": {"coordinates":[-0.388618,51.62748],"type":"Point"}
}