{
  "type": "Feature",
  "properties": {
    "iso:country":"GB",
    "sg:address":"13-14 Dean Street",
    "sg:city":"London",
    "sg:classifiers":[
        {
            "category":"Professional",
            "subcategory":"Management & Consulting",
            "type":"Services"
        }
    ],
    "sg:phone":"+44 20 7734 6310",
    "sg:postcode":"W1D 3RS",
    "sg:province":"Greater London",
    "sg:tags":[
        "consultant",
        "business"
    ],
    "wof:name":"Frost Rowley",
    "wof:placetype":"venue"
},
  "geometry": {"coordinates":[-0.133615,51.514999],"type":"Point"}
}