{
  "type": "Feature",
  "properties": {
    "iso:country":"GB",
    "sg:address":"Sevenhampton Manor, Sevenhampton",
    "sg:city":"Cheltenham",
    "sg:classifiers":[
        {
            "category":"Communications",
            "type":"Services"
        }
    ],
    "sg:phone":"+44 1242 221250",
    "sg:postcode":"GL54 5SW",
    "sg:province":"Gloucestershire",
    "sg:tags":[
        "audio-visual"
    ],
    "wof:name":"Tower Productions",
    "wof:placetype":"venue"
},
  "geometry": {"coordinates":[-1.955099,51.893951],"type":"Point"}
}