{
  "type": "Feature",
  "properties": {
    "iso:country":"GB",
    "sg:address":"Monkton Hall Hospital, Monkton Village",
    "sg:city":"Jarrow",
    "sg:classifiers":[
        {
            "category":"Health Services",
            "subcategory":"Hospital",
            "type":"Services"
        }
    ],
    "sg:phone":"+44 191 428 0241",
    "sg:postcode":"NE32 5NN",
    "sg:province":"Tyne and Wear",
    "wof:name":"Community Nursing Services",
    "wof:placetype":"venue"
},
  "geometry": {"coordinates":[-1.50128,54.966648],"type":"Point"}
}