{
  "type": "Feature",
  "properties": {
    "iso:country":"GB",
    "sg:address":"27 Prentiss Court, Charlton Lane",
    "sg:city":"London",
    "sg:classifiers":[
        {
            "category":"Real Estate",
            "subcategory":"Architect",
            "type":"Services"
        }
    ],
    "sg:postcode":"SE7 8LD",
    "sg:province":"Greater London",
    "wof:name":"Bnw Engineers Ltd",
    "wof:placetype":"venue"
},
  "geometry": {"coordinates":[0.0393380001,51.4885978699],"type":"Point"}
}