{
  "type": "Feature",
  "properties": {
    "addr:full":"164 Crooked Mile Waltham Abbey Essex EN9 2ES",
    "addr:housenumber":"164",
    "addr:postcode":"en9 2es",
    "addr:street":"Crooked Mile Waltham Abbey",
    "iso:country":"GB",
    "sg:address":"164 Crooked Mile",
    "sg:city":"Waltham Abbey",
    "sg:classifiers":[
        {
            "category":"Retail",
            "subcategory":"Auto Repair",
            "type":"Services"
        }
    ],
    "sg:phone":"+44 1992 788749",
    "sg:postcode":"EN9 2ES",
    "sg:province":"Essex",
    "sg:tags":[
        "modification",
        "garage"
    ],
    "wof:name":"Mile Garage",
    "wof:placetype":"venue"
},
  "geometry": {"coordinates":[0.000852,51.6988258362],"type":"Point"}
}