{
  "type": "Feature",
  "properties": {
    "addr:full":"1 Sighthill Court Edinburgh City of Edinburgh EH11 4BN",
    "addr:housenumber":"1",
    "addr:postcode":"eh11 4bn",
    "addr:street":"Sighthill Court Edinburgh",
    "iso:country":"GB",
    "sg:address":"1 Sighthill Court",
    "sg:city":"Edinburgh",
    "sg:classifiers":[
        {
            "category":"Organizations",
            "subcategory":"Membership Organization",
            "type":"Services"
        }
    ],
    "sg:phone":"+44 131 229 8791",
    "sg:postcode":"EH11 4BN",
    "sg:province":"City of Edinburgh",
    "sg:tags":[
        "club"
    ],
    "wof:name":"Napier Students Association",
    "wof:placetype":"venue"
},
  "geometry": {"coordinates":[-3.287395,55.923847],"type":"Point"}
}