{
  "type": "Feature",
  "properties": {
    "addr:full":"31 Spring St Brighton East Sussex BN1 3EF",
    "addr:housenumber":"31",
    "addr:postcode":"bn1 3ef",
    "addr:street":"Spring St",
    "iso:country":"GB",
    "sg:address":"31 Spring St",
    "sg:city":"Brighton",
    "sg:classifiers":[
        {
            "category":"Professional",
            "subcategory":"Art Services",
            "type":"Services"
        }
    ],
    "sg:postcode":"BN1 3EF",
    "sg:province":"East Sussex",
    "sg:tags":[
        "photographer"
    ],
    "wof:name":"Deverall,Nicki,",
    "wof:placetype":"venue"
},
  "geometry": {"coordinates":[-0.1493930072,50.8246536255],"type":"Point"}
}