{
  "type": "Feature",
  "properties": {
    "addr:full":"Trinity Way Keswick Cumbria CA12 4HZ",
    "addr:postcode":"ca12 4hz",
    "addr:street":"Trinity Way",
    "iso:country":"GB",
    "sg:address":"Trinity Way",
    "sg:city":"Keswick",
    "sg:classifiers":[
        {
            "category":"Education",
            "subcategory":"School",
            "type":"Public Place"
        }
    ],
    "sg:postcode":"CA12 4HZ",
    "sg:province":"Cumbria",
    "sg:tags":[
        "local",
        "authority"
    ],
    "wof:name":"C of E Trinity School",
    "wof:placetype":"venue"
},
  "geometry": {"coordinates":[-3.1222701073,54.6028633118],"type":"Point"}
}