{
  "type": "Feature",
  "properties": {
    "addr:full":"17 Rosebery Avenue London Greater London EC1R 4SP",
    "addr:housenumber":"17",
    "addr:postcode":"ec1r 4sp",
    "addr:street":"Rosebery Avenue",
    "iso:country":"GB",
    "sg:address":"17 Rosebery Avenue",
    "sg:city":"London",
    "sg:classifiers":[
        {
            "category":"Professional",
            "subcategory":"Printing & Photocopies",
            "type":"Services"
        }
    ],
    "sg:phone":"+44 20 7278 9149",
    "sg:postcode":"EC1R 4SP",
    "sg:province":"Greater London",
    "sg:tags":[
        "printer"
    ],
    "wof:name":"Avenue Litho",
    "wof:placetype":"venue"
},
  "geometry": {"coordinates":[-0.110924,51.524426],"type":"Point"}
}