{
  "type": "Feature",
  "properties": {
    "addr:full":"13 Manor Forestal, New Ash Grn Longfield Kent DA3 8JG",
    "addr:housenumber":"13",
    "addr:postcode":"da3 8jg",
    "addr:street":"Manor Forestal New Ash Grn Longfield",
    "iso:country":"GB",
    "sg:address":"13 Manor Forestal, New Ash Grn",
    "sg:city":"Longfield",
    "sg:classifiers":[
        {
            "category":"Home & Garden",
            "subcategory":"Carpets & Floor Coverings",
            "type":"Retail Goods"
        }
    ],
    "sg:phone":"+44 1474 871332",
    "sg:postcode":"DA3 8JG",
    "sg:province":"Kent",
    "sg:tags":[
        "cleaner",
        "upholstery"
    ],
    "wof:name":"M A S Cleaning",
    "wof:placetype":"venue"
},
  "geometry": {"coordinates":[0.309865,51.364178],"type":"Point"}
}