{
  "type": "Feature",
  "properties": {
    "iso:country":"GB",
    "sg:address":"Hall Lane, Brinsley",
    "sg:city":"Nottingham",
    "sg:classifiers":[
        {
            "category":"Banks & Credit Unions",
            "subcategory":"Investment Brokerage",
            "type":"Services"
        },
        {
            "category":"Farming",
            "subcategory":"Dairy Farm",
            "type":"Manufacturing & Wholesale Goods"
        }
    ],
    "sg:phone":"+44 1773 717046",
    "sg:postcode":"NG16 5AP",
    "sg:province":"Derbyshire",
    "sg:tags":[
        "contractor"
    ],
    "wof:name":"T W & R Taylor",
    "wof:placetype":"venue"
},
  "geometry": {"coordinates":[-1.3105390072,53.0405654907],"type":"Point"}
}