{
  "type": "Feature",
  "properties": {
    "iso:country":"GB",
    "sg:address":"Gorsemoor Road",
    "sg:city":"Cannock",
    "sg:classifiers":[
        {
            "category":"Health Services",
            "subcategory":"Doctor",
            "type":"Services"
        }
    ],
    "sg:phone":"+44 1543 277933",
    "sg:postcode":"WS12 5TG",
    "sg:province":"Staffordshire",
    "sg:tags":[
        "practitioners"
    ],
    "wof:name":"Heath Hayes Health Centre",
    "wof:placetype":"venue"
},
  "geometry": {"coordinates":[-1.988204,52.690475],"type":"Point"}
}