{
  "type": "Feature",
  "properties": {
    "iso:country":"GB",
    "sg:address":"48 Addison Close, Feltwell",
    "sg:city":"Thetford",
    "sg:classifiers":[
        {
            "category":"Retail",
            "subcategory":"Driving School",
            "type":"Services"
        }
    ],
    "sg:phone":"+44 1842 828313",
    "sg:postcode":"IP26 4DJ",
    "sg:province":"Norfolk",
    "wof:name":"Feltwell & District School of Motoring",
    "wof:placetype":"venue"
},
  "geometry": {"coordinates":[0.531345,52.489491],"type":"Point"}
}