{
  "type": "Feature",
  "properties": {
    "iso:country":"GB",
    "sg:address":"14/16 North Street",
    "sg:city":"Bishops Stortford",
    "sg:classifiers":[
        {
            "category":"Professional",
            "subcategory":"Printing & Photocopies",
            "type":"Services"
        }
    ],
    "sg:phone":"+44 1279 654033",
    "sg:postcode":"CM23 2LL",
    "sg:province":"Essex",
    "sg:tags":[
        "photocopier"
    ],
    "wof:name":"Boardmans Photocopying Ltd.",
    "wof:placetype":"venue"
},
  "geometry": {"coordinates":[0.158879,51.871761],"type":"Point"}
}