{
  "type": "Feature",
  "properties": {
    "iso:country":"GB",
    "sg:address":"York House, Leicester Road",
    "sg:city":"Lutterworth",
    "sg:classifiers":[
        {
            "category":"Professional",
            "subcategory":"Advertising",
            "type":"Services"
        }
    ],
    "sg:phone":"+44 1455 552246",
    "sg:postcode":"LE17 4HF",
    "sg:province":"Leicestershire",
    "sg:tags":[
        "agency"
    ],
    "wof:name":"Key Parker Ltd",
    "wof:placetype":"venue"
},
  "geometry": {"coordinates":[-1.198149,52.46571],"type":"Point"}
}