{
  "type": "Feature",
  "properties": {
    "iso:country":"GB",
    "sg:address":"Unit 4-5 Harmill Indust Est, Grovebury Rd",
    "sg:city":"Leighton Buzzard",
    "sg:classifiers":[
        {
            "category":"Banks & Credit Unions",
            "subcategory":"Bank",
            "type":"Services"
        }
    ],
    "sg:phone":"+44 1525 371177",
    "sg:postcode":"LU7 8FF",
    "sg:province":"Bedfordshire",
    "sg:tags":[
        "broker",
        "mortgage"
    ],
    "wof:name":"Capital Strategy",
    "wof:placetype":"venue"
},
  "geometry": {"coordinates":[-0.663909,51.917351],"type":"Point"}
}