{
  "type": "Feature",
  "properties": {
    "addr:full":"14 Haven Grn London Greater London W5 2UU",
    "addr:housenumber":"14",
    "addr:postcode":"w5 2uu",
    "addr:street":"Haven Grn",
    "iso:country":"GB",
    "sg:address":"14 Haven Grn",
    "sg:city":"London",
    "sg:classifiers":[
        {
            "category":"Social Services",
            "subcategory":"Job Training",
            "type":"Services"
        },
        {
            "category":"Travel",
            "subcategory":"Hotels & Motels",
            "type":"Entertainment"
        }
    ],
    "sg:phone":"+44 20 8997 3524",
    "sg:postcode":"W5 2UU",
    "sg:province":"Greater London",
    "sg:tags":[
        "translator",
        "interpreter"
    ],
    "wof:name":"Caspian Iranian Arabic Interpreting Services",
    "wof:placetype":"venue"
},
  "geometry": {"coordinates":[-0.3048489988,51.5158882141],"type":"Point"}
}