{
  "type": "Feature",
  "properties": {
    "addr:full":"182 Kensington Church St Kensington Greater London W8 4DP",
    "addr:housenumber":"182",
    "addr:postcode":"w8 4dp",
    "addr:street":"Kensington Church St",
    "iso:country":"GB",
    "sg:address":"182 Kensington Church St",
    "sg:city":"Kensington",
    "sg:classifiers":[
        {
            "category":"Health Services",
            "subcategory":"Health Practitioner",
            "type":"Services"
        }
    ],
    "sg:phone":"+44 20 7262 4507",
    "sg:postcode":"W8 4DP",
    "sg:province":"Greater London",
    "sg:tags":[
        "osteopath"
    ],
    "wof:name":"Andrew C.D. Mullen",
    "wof:placetype":"venue"
},
  "geometry": {"coordinates":[-0.19492,51.508331],"type":"Point"}
}