{
  "type": "Feature",
  "properties": {
    "addr:full":"North Lodge, Fulmer Grange Slough Berkshire SL2 4QS",
    "addr:housenumber":"fulmer",
    "addr:postcode":"sl2 4qs",
    "addr:street":"Grange",
    "iso:country":"GB",
    "sg:address":"North Lodge, Fulmer Grange",
    "sg:city":"Slough",
    "sg:classifiers":[
        {
            "category":"Building & Trades",
            "subcategory":"Construction",
            "type":"Services"
        }
    ],
    "sg:phone":"+44 1753 664141",
    "sg:postcode":"SL2 4QS",
    "sg:province":"Berkshire",
    "sg:tags":[
        "builder"
    ],
    "wof:name":"Such & Lowe Ltd.",
    "wof:placetype":"venue"
},
  "geometry": {"coordinates":[-0.5670599937,51.5508003235],"type":"Point"}
}