{
  "type": "Feature",
  "properties": {
    "iso:country":"GB",
    "sg:address":"22 Keats Close",
    "sg:city":"Hemel Hempstead",
    "sg:classifiers":[
        {
            "category":"Conference Center",
            "type":"Public Place"
        }
    ],
    "sg:phone":"+44 1442 395237",
    "sg:postcode":"HP2 7NL",
    "sg:province":"Hertfordshire",
    "wof:name":"Perfect Venue Ltd",
    "wof:placetype":"venue"
},
  "geometry": {"coordinates":[-0.4409349859,51.7795143127],"type":"Point"}
}