{
  "type": "Feature",
  "properties": {
    "addr:full":"43a Lower Bore Street Bodmin Cornwall PL31 2JU",
    "addr:housenumber":"43a",
    "addr:postcode":"pl31 2ju",
    "addr:street":"Lower Bore Street",
    "iso:country":"GB",
    "sg:address":"43a Lower Bore Street",
    "sg:city":"Bodmin",
    "sg:classifiers":[
        {
            "category":"Home & Garden",
            "subcategory":"Household Appliances",
            "type":"Retail Goods"
        }
    ],
    "sg:phone":"+44 1208 78264",
    "sg:postcode":"PL31 2JU",
    "sg:province":"Cornwall",
    "sg:tags":[
        "electrical"
    ],
    "wof:name":"Jim's Domestic Supplies",
    "wof:placetype":"venue"
},
  "geometry": {"coordinates":[-4.7258110046,50.4715881348],"type":"Point"}
}