{
  "type": "Feature",
  "properties": {
    "iso:country":"GB",
    "sg:address":"100 Cathcart St",
    "sg:city":"Birkenhead",
    "sg:classifiers":[
        {
            "category":"Bars & Pubs",
            "type":"Food & Drink"
        }
    ],
    "sg:phone":"+44 151 647 7288",
    "sg:postcode":"CH41 3JZ",
    "sg:province":"Merseyside",
    "sg:tags":[
        "pubs",
        "inn"
    ],
    "wof:name":"Punch Retail Ltd",
    "wof:placetype":"venue"
},
  "geometry": {"coordinates":[-3.028742075,53.3954353333],"type":"Point"}
}