{
  "type": "Feature",
  "properties": {
    "addr:full":"Bassenthwaite Keswick Cumbria CA12 4QH",
    "addr:postcode":"ca12 4qh",
    "iso:country":"GB",
    "sg:address":"Bassenthwaite",
    "sg:city":"Keswick",
    "sg:classifiers":[
        {
            "category":"Retail",
            "subcategory":"Auto Repair",
            "type":"Services"
        }
    ],
    "sg:phone":"+44 17687 76218",
    "sg:postcode":"CA12 4QH",
    "sg:province":"Cumbria",
    "sg:tags":[
        "modification",
        "garage"
    ],
    "wof:name":"Skiddaw Service Station",
    "wof:placetype":"venue"
},
  "geometry": {"coordinates":[-3.1954579353,54.6790275574],"type":"Point"}
}