{
  "type": "Feature",
  "properties": {
    "iso:country":"GB",
    "sg:address":"13 Bridge St, Lockwood",
    "sg:city":"Huddersfield",
    "sg:classifiers":[
        {
            "category":"Shopping",
            "type":"Retail Goods"
        }
    ],
    "sg:phone":"+44 1484 456454",
    "sg:postcode":"HD4 6EL",
    "sg:province":"West Yorkshire",
    "sg:tags":[
        "equipment",
        "clothing",
        "safety"
    ],
    "wof:name":"Qualsafe Ltd",
    "wof:placetype":"venue"
},
  "geometry": {"coordinates":[-1.795291,53.632702],"type":"Point"}
}