{
  "type": "Feature",
  "properties": {
    "iso:country":"GB",
    "sg:address":"North Street",
    "sg:city":"Scunthorpe",
    "sg:classifiers":[
        {
            "category":"Train Station",
            "subcategory":"Rail",
            "type":"Transportation"
        }
    ],
    "sg:phone":"+44 1724 733114",
    "sg:postcode":"DN15 9QS",
    "sg:province":"Lincolnshire",
    "sg:tags":[
        "caravan"
    ],
    "wof:name":"Armstrong Caravan Sales",
    "wof:placetype":"venue"
},
  "geometry": {"coordinates":[-0.5920240283,53.6598358154],"type":"Point"}
}