{
  "type": "Feature",
  "properties": {
    "addr:full":"63 Broad Street Worcester Worcestershire WR1 3LY",
    "addr:housenumber":"63",
    "addr:postcode":"wr1 3ly",
    "addr:street":"Broad Street",
    "iso:country":"GB",
    "sg:address":"63 Broad Street",
    "sg:city":"Worcester",
    "sg:classifiers":[
        {
            "category":"Personal",
            "subcategory":"Beauty Salon",
            "type":"Services"
        }
    ],
    "sg:postcode":"WR1 3LY",
    "sg:province":"Worcestershire",
    "sg:tags":[
        "lady",
        "hairdresser"
    ],
    "wof:name":"Lisbeth Hair Stylist",
    "wof:placetype":"venue"
},
  "geometry": {"coordinates":[-2.2218151093,52.1927032471],"type":"Point"}
}