{
  "type": "Feature",
  "properties": {
    "addr:full":"6 Old School Close, Ellistown Coalville Leicestershire LE67 1FN",
    "addr:housenumber":"6",
    "addr:postcode":"le67 1fn",
    "addr:street":"Old School Close",
    "iso:country":"GB",
    "sg:address":"6 Old School Close, Ellistown",
    "sg:city":"Coalville",
    "sg:classifiers":[
        {
            "category":"Retail",
            "subcategory":"Auto Repair",
            "type":"Services"
        }
    ],
    "sg:phone":"+44 1530 260879",
    "sg:postcode":"LE67 1FN",
    "sg:province":"Leicestershire",
    "sg:tags":[
        "body",
        "car",
        "repairer"
    ],
    "wof:name":"John Spencer",
    "wof:placetype":"venue"
},
  "geometry": {"coordinates":[-1.3648389578,52.6940536499],"type":"Point"}
}