{
  "type": "Feature",
  "properties": {
    "iso:country":"GB",
    "sg:address":"55 Big Wood Park, Sugworth Lane, Radley",
    "sg:city":"Abingdon",
    "sg:classifiers":[
        {
            "category":"Retail",
            "subcategory":"Driving School",
            "type":"Services"
        }
    ],
    "sg:phone":"+44 1865 326391",
    "sg:postcode":"OX14 2LL",
    "sg:province":"Oxfordshire",
    "wof:name":"Thames School Of Motoring",
    "wof:placetype":"venue"
},
  "geometry": {"coordinates":[-1.285489,51.673325],"type":"Point"}
}