{
  "type": "Feature",
  "properties": {
    "addr:full":"12 Bentley Way Stanmore Greater London HA7 3RP",
    "addr:housenumber":"12",
    "addr:postcode":"ha7 3rp",
    "addr:street":"Bentley Way",
    "iso:country":"GB",
    "sg:address":"12 Bentley Way",
    "sg:city":"Stanmore",
    "sg:classifiers":[
        {
            "category":"Shopping",
            "subcategory":"Pharmacy",
            "type":"Retail Goods"
        }
    ],
    "sg:phone":"+44 20 8954 8515",
    "sg:postcode":"HA7 3RP",
    "sg:province":"Greater London",
    "sg:tags":[
        "toiletry"
    ],
    "wof:name":"House of Bentley",
    "wof:placetype":"venue"
},
  "geometry": {"coordinates":[-0.3238779902,51.6161956787],"type":"Point"}
}