{
  "type": "Feature",
  "properties": {
    "iso:country":"GB",
    "sg:address":"2 Bellerton Lane",
    "sg:city":"Stoke-on-trent",
    "sg:classifiers":[
        {
            "category":"Building & Trades",
            "subcategory":"Construction",
            "type":"Services"
        }
    ],
    "sg:postcode":"ST6 8XP",
    "sg:province":"Staffordshire",
    "sg:tags":[
        "installers",
        "gas"
    ],
    "wof:name":"G C Heating",
    "wof:placetype":"venue"
},
  "geometry": {"coordinates":[-2.155689,53.050499],"type":"Point"}
}