{
  "type": "Feature",
  "properties": {
    "addr:full":"Suite 4, Craven Hall Skipton Lancashire BD23 2PB",
    "addr:housenumber":"suite 4",
    "addr:postcode":"bd23 2pb",
    "addr:street":"Craven Hall",
    "iso:country":"GB",
    "sg:address":"Suite 4, Craven Hall",
    "sg:city":"Skipton",
    "sg:classifiers":[
        {
            "category":"Professional",
            "type":"Services"
        }
    ],
    "sg:phone":"+44 1756 797877",
    "sg:postcode":"BD23 2PB",
    "sg:province":"Lancashire",
    "sg:tags":[
        "exhibition"
    ],
    "wof:name":"Afar Exhibition Services Ltd.",
    "wof:placetype":"venue"
},
  "geometry": {"coordinates":[-2.0207669735,53.9576263428],"type":"Point"}
}