{
  "type": "Feature",
  "properties": {
    "iso:country":"GB",
    "sg:address":"5 Weymouth House, Bolney Street",
    "sg:city":"London",
    "sg:classifiers":[
        {
            "category":"Shopping",
            "subcategory":"Florist",
            "type":"Retail Goods"
        }
    ],
    "sg:postcode":"SW8 1EN",
    "sg:province":"Greater London",
    "wof:name":"Paradise Plants Ltd.",
    "wof:placetype":"venue"
},
  "geometry": {"coordinates":[-0.1216000021,51.4789390564],"type":"Point"}
}