{
  "type": "Feature",
  "properties": {
    "iso:country":"GB",
    "sg:address":"39-43 Bridge Street, Swinton",
    "sg:city":"Mexborough",
    "sg:classifiers":[
        {
            "category":"Home & Garden",
            "subcategory":"Building Materials",
            "type":"Retail Goods"
        }
    ],
    "sg:postcode":"S64 8AP",
    "sg:province":"South Yorkshire",
    "sg:tags":[
        "ventilator",
        "ventilation",
        "system"
    ],
    "wof:name":"Tomac Fabrications Ltd.",
    "wof:placetype":"venue"
},
  "geometry": {"coordinates":[-1.3024580479,53.4883804321],"type":"Point"}
}