{
  "type": "Feature",
  "properties": {
    "addr:full":"Unit 2, East Way Ivybridge Devon PL21 9GE",
    "addr:housenumber":"unit 2",
    "addr:postcode":"pl21 9ge",
    "addr:street":"East Way",
    "iso:country":"GB",
    "sg:address":"Unit 2, East Way",
    "sg:city":"Ivybridge",
    "sg:classifiers":[
        {
            "category":"Manufacturing",
            "subcategory":"Tools & Machinery",
            "type":"Manufacturing & Wholesale Goods"
        },
        {
            "category":"Professional",
            "subcategory":"Engineering",
            "type":"Services"
        }
    ],
    "sg:postcode":"PL21 9GE",
    "sg:province":"Devon",
    "sg:tags":[
        "engineer"
    ],
    "wof:name":"Parkins Industrial Supplies Ltd.",
    "wof:placetype":"venue"
},
  "geometry": {"coordinates":[-3.9493610859,50.3867835999],"type":"Point"}
}