{
  "type": "Feature",
  "properties": {
    "addr:full":"Brownston Cottage, Sleep Street, Charlbury Oxford Gloucestershire OX7 3RR",
    "addr:postcode":"ox7 3rr",
    "addr:street":"Sleep Street",
    "iso:country":"GB",
    "sg:address":"Brownston Cottage, Sleep Street, Charlbury",
    "sg:city":"Oxford",
    "sg:classifiers":[
        {
            "category":"Communications",
            "type":"Services"
        }
    ],
    "sg:phone":"+44 1608 811617",
    "sg:postcode":"OX7 3RR",
    "sg:province":"Gloucestershire",
    "sg:tags":[
        "data",
        "network"
    ],
    "wof:name":"Education Consultancy Services Ltd.",
    "wof:placetype":"venue"
},
  "geometry": {"coordinates":[-1.4756430387,51.8729782104],"type":"Point"}
}