{
  "type": "Feature",
  "properties": {
    "iso:country":"GB",
    "sg:address":"390 Brook Street",
    "sg:city":"Preston",
    "sg:classifiers":[
        {
            "category":"Food & Beverages",
            "subcategory":"Farmers Market",
            "type":"Retail Goods"
        }
    ],
    "sg:postcode":"PR2 3AH",
    "sg:province":"Lancashire",
    "sg:tags":[
        "oil",
        "-",
        "edible"
    ],
    "wof:name":"Preston Oils",
    "wof:placetype":"venue"
},
  "geometry": {"coordinates":[-2.716193,53.774277],"type":"Point"}
}