{
  "type": "Feature",
  "properties": {
    "addr:full":"61 High Road Willenhall West Midlands WV12 4JR",
    "addr:housenumber":"61",
    "addr:postcode":"wv12 4jr",
    "addr:street":"High Road",
    "iso:country":"GB",
    "sg:address":"61 High Road",
    "sg:city":"Willenhall",
    "sg:classifiers":[
        {
            "category":"Government",
            "subcategory":"Post Office",
            "type":"Public Place"
        }
    ],
    "sg:phone":"+44 1902 606420",
    "sg:postcode":"WV12 4JR",
    "sg:province":"West Midlands",
    "wof:name":"Lane Head Post Offfice",
    "wof:placetype":"venue"
},
  "geometry": {"coordinates":[-2.0385370255,52.6007041931],"type":"Point"}
}