{
  "type": "Feature",
  "properties": {
    "addr:full":"145 Bury Road, Radcliffe Manchester Greater Manchester M26 2XA",
    "addr:housenumber":"145",
    "addr:postcode":"m26 2xa",
    "addr:street":"Bury Road",
    "iso:country":"GB",
    "sg:address":"145 Bury Road, Radcliffe",
    "sg:city":"Manchester",
    "sg:classifiers":[
        {
            "category":"Shopping",
            "subcategory":"Computers & Home Electronics",
            "type":"Retail Goods"
        }
    ],
    "sg:phone":"+44 161 723 3726",
    "sg:postcode":"M26 2XA",
    "sg:province":"Greater Manchester",
    "sg:tags":[
        "electrical"
    ],
    "wof:name":"D Howarth Ltd.",
    "wof:placetype":"venue"
},
  "geometry": {"coordinates":[-2.315096,53.569756],"type":"Point"}
}