{
  "type": "Feature",
  "properties": {
    "iso:country":"GB",
    "sg:address":"35 Rowlls Rd",
    "sg:city":"Kingston Upon Thames",
    "sg:classifiers":[
        {
            "category":"Education",
            "subcategory":"Preschool",
            "type":"Public Place"
        }
    ],
    "sg:phone":"+44 20 8549 6483",
    "sg:postcode":"KT1 3ET",
    "sg:province":"Greater London",
    "sg:tags":[
        "pre-school",
        "playgroups"
    ],
    "wof:name":"Ark Nursery Pre-School The",
    "wof:placetype":"venue"
},
  "geometry": {"coordinates":[-0.289876014,51.4071578979],"type":"Point"}
}