{
  "type": "Feature",
  "properties": {
    "addr:full":"Dental Surgery, 7 South Street, Lydd Romney Marsh Kent TN29 9DQ",
    "addr:housenumber":"7",
    "addr:postcode":"tn29 9dq",
    "addr:street":"South Street",
    "iso:country":"GB",
    "sg:address":"Dental Surgery, 7 South Street, Lydd",
    "sg:city":"Romney Marsh",
    "sg:classifiers":[
        {
            "category":"Health Services",
            "subcategory":"Dentist",
            "type":"Services"
        }
    ],
    "sg:phone":"+44 1797 320826",
    "sg:postcode":"TN29 9DQ",
    "sg:province":"Kent",
    "wof:name":"Janice E Robertson",
    "wof:placetype":"venue"
},
  "geometry": {"coordinates":[0.9037529826,50.9503479004],"type":"Point"}
}