{
  "type": "Feature",
  "properties": {
    "iso:country":"GB",
    "sg:address":", South Tawton",
    "sg:city":"Okehampton",
    "sg:classifiers":[
        {
            "category":"Bars & Pubs",
            "type":"Food & Drink"
        }
    ],
    "sg:phone":"+44 1837 840292",
    "sg:postcode":"EX20 2LW",
    "sg:province":"Devon",
    "sg:tags":[
        "pubs",
        "inn"
    ],
    "wof:name":"Seven Stars",
    "wof:placetype":"venue"
},
  "geometry": {"coordinates":[-3.9101541042,50.7335166931],"type":"Point"}
}