{
  "type": "Feature",
  "properties": {
    "iso:country":"GB",
    "sg:address":"16 Burlington Rd",
    "sg:city":"New Malden",
    "sg:classifiers":[
        {
            "category":"Professional",
            "type":"Services"
        }
    ],
    "sg:phone":"+44 7958 721029",
    "sg:postcode":"KT3 4NY",
    "sg:province":"Surrey",
    "sg:tags":[
        "interior",
        "furnishers",
        "designer"
    ],
    "wof:name":"Intuitive Interiors",
    "wof:placetype":"venue"
},
  "geometry": {"coordinates":[-0.25449,51.398602],"type":"Point"}
}