{
  "type": "Feature",
  "properties": {
    "addr:full":"713 Seven Sisters Road London Greater London N15 5JT",
    "addr:housenumber":"713",
    "addr:postcode":"n15 5jt",
    "addr:street":"Seven Sisters Road",
    "iso:country":"GB",
    "sg:address":"713 Seven Sisters Road",
    "sg:city":"London",
    "sg:classifiers":[
        {
            "category":"Professional",
            "subcategory":"Printing & Photocopies",
            "type":"Services"
        }
    ],
    "sg:phone":"+44 20 8800 0070",
    "sg:postcode":"N15 5JT",
    "sg:province":"Greater London",
    "sg:tags":[
        "printer"
    ],
    "wof:name":"The Inkwell Co.",
    "wof:placetype":"venue"
},
  "geometry": {"coordinates":[-0.0804990008,51.5794258118],"type":"Point"}
}