{
  "type": "Feature",
  "properties": {
    "iso:country":"GB",
    "sg:address":"Unit 7, Walton Industrial Estate",
    "sg:city":"Stone",
    "sg:classifiers":[
        {
            "category":"Professional",
            "subcategory":"Printing & Photocopies",
            "type":"Services"
        }
    ],
    "sg:phone":"+44 1785 818860",
    "sg:postcode":"ST15 0NN",
    "sg:province":"Staffordshire",
    "sg:tags":[
        "process",
        "screen",
        "printer"
    ],
    "wof:name":"Harlequin Transfers Ltd.",
    "wof:placetype":"venue"
},
  "geometry": {"coordinates":[-2.150181,52.886574],"type":"Point"}
}