{
  "type": "Feature",
  "properties": {
    "addr:full":"The Old Library, Risley Lane, Breaston Derby Derbyshire DE72 3BP",
    "addr:postcode":"de72 3bp",
    "addr:street":"Risley Lane",
    "iso:country":"GB",
    "sg:address":"The Old Library, Risley Lane, Breaston",
    "sg:city":"Derby",
    "sg:classifiers":[
        {
            "category":"Professional",
            "subcategory":"Business Services",
            "type":"Services"
        }
    ],
    "sg:phone":"+44 115 946 1964",
    "sg:postcode":"DE72 3BP",
    "sg:province":"Derbyshire",
    "wof:name":"Breaston Associates Ltd.",
    "wof:placetype":"venue"
},
  "geometry": {"coordinates":[-1.313864,52.897701],"type":"Point"}
}