{
  "type": "Feature",
  "properties": {
    "iso:country":"GB",
    "sg:address":"36b-36c Swansea Market",
    "sg:city":"Swansea",
    "sg:classifiers":[
        {
            "category":"Food & Beverages",
            "subcategory":"Bakery",
            "type":"Retail Goods"
        }
    ],
    "sg:phone":"+44 1792 641088",
    "sg:postcode":"SA1 3PF",
    "sg:province":"Neath Port Talbot",
    "sg:tags":[
        "shop",
        "baker"
    ],
    "wof:name":"Mavis Davies",
    "wof:placetype":"venue"
},
  "geometry": {"coordinates":[-4.025455,51.658531],"type":"Point"}
}