{
  "type": "Feature",
  "properties": {
    "iso:country":"GB",
    "sg:address":"Ballantyne Rd, Hillington Indust Est",
    "sg:city":"Glasgow",
    "sg:classifiers":[
        {
            "category":"Professional",
            "type":"Services"
        }
    ],
    "sg:phone":"+44 141 882 5358",
    "sg:postcode":"G52 4BP",
    "sg:province":"Glasgow City",
    "sg:tags":[
        "control",
        "system"
    ],
    "wof:name":"Lighthouse Controls",
    "wof:placetype":"venue"
},
  "geometry": {"coordinates":[-4.359809,55.858715],"type":"Point"}
}