{
  "type": "Feature",
  "properties": {
    "iso:country":"GB",
    "sg:address":"Royal London House, 196 Deansgate",
    "sg:city":"Manchester",
    "sg:classifiers":[
        {
            "category":"Professional",
            "subcategory":"Lawyer & Legal Services",
            "type":"Services"
        }
    ],
    "sg:phone":"+44 161 834 7374",
    "sg:postcode":"M3 3WF",
    "sg:province":"Greater Manchester",
    "sg:tags":[
        "solicitor"
    ],
    "wof:name":"Burton Copeland",
    "wof:placetype":"venue"
},
  "geometry": {"coordinates":[-2.2501089573,53.4795684814],"type":"Point"}
}