{
  "type": "Feature",
  "properties": {
    "addr:full":"5 Meadow Avenue Loughborough Leicestershire LE11 1JS",
    "addr:housenumber":"5",
    "addr:postcode":"le11 1js",
    "addr:street":"Meadow Avenue",
    "iso:country":"GB",
    "sg:address":"5 Meadow Avenue",
    "sg:city":"Loughborough",
    "sg:classifiers":[
        {
            "category":"Taxi",
            "type":"Transportation"
        }
    ],
    "sg:phone":"+44 1509 232852",
    "sg:postcode":"LE11 1JS",
    "sg:province":"Leicestershire",
    "sg:tags":[
        "mini",
        "cab"
    ],
    "wof:name":"Keiths Taxis",
    "wof:placetype":"venue"
},
  "geometry": {"coordinates":[-1.2022809982,52.7803916931],"type":"Point"}
}