{
  "type": "Feature",
  "properties": {
    "addr:full":"Chillinghome Road Birmingham West Midlands B36 8QJ",
    "addr:postcode":"b36 8qj",
    "addr:street":"Chillinghome Road",
    "iso:country":"GB",
    "sg:address":"Chillinghome Road",
    "sg:city":"Birmingham",
    "sg:classifiers":[
        {
            "category":"Education",
            "subcategory":"School",
            "type":"Public Place"
        },
        {
            "category":"Government",
            "subcategory":"Office",
            "type":"Public Place"
        }
    ],
    "sg:phone":"+44 121 747 4497",
    "sg:postcode":"B36 8QJ",
    "sg:province":"West Midlands",
    "sg:tags":[
        "local",
        "authority"
    ],
    "wof:name":"Tame Valley Primary School",
    "wof:placetype":"venue"
},
  "geometry": {"coordinates":[-1.811564,52.507534],"type":"Point"}
}