{
  "type": "Feature",
  "properties": {
    "addr:full":"Hart Road, Fallowfield Manchester Greater Manchester M14 7BB",
    "addr:postcode":"m14 7bb",
    "addr:street":"Hart Road",
    "iso:country":"GB",
    "sg:address":"Hart Road, Fallowfield",
    "sg:city":"Manchester",
    "sg:classifiers":[
        {
            "category":"Organizations",
            "subcategory":"Membership Organization",
            "type":"Services"
        }
    ],
    "sg:phone":"+44 161 224 2033",
    "sg:postcode":"M14 7BB",
    "sg:province":"Greater Manchester",
    "sg:tags":[
        "club"
    ],
    "wof:name":"St.Kentigerns Social Club",
    "wof:placetype":"venue"
},
  "geometry": {"coordinates":[-2.239162,53.448353],"type":"Point"}
}