{
  "type": "Feature",
  "properties": {
    "addr:full":"Sutton Road King's Lynn Lincolnshire PE34 4HD",
    "addr:postcode":"pe34 4hd",
    "addr:street":"Sutton Road",
    "iso:country":"GB",
    "sg:address":"Sutton Road",
    "sg:city":"King's Lynn",
    "sg:classifiers":[
        {
            "category":"Manufacturing",
            "subcategory":"Wood Products",
            "type":"Manufacturing & Wholesale Goods"
        }
    ],
    "sg:postcode":"PE34 4HD",
    "sg:province":"Lincolnshire",
    "sg:tags":[
        "packaging",
        "crate",
        "pallets"
    ],
    "wof:name":"A N P Easton",
    "wof:placetype":"venue"
},
  "geometry": {"coordinates":[0.29299,52.75536],"type":"Point"}
}