{
  "type": "Feature",
  "properties": {
    "iso:country":"GB",
    "sg:address":"Globe La Indstl Est",
    "sg:city":"Dukinfield",
    "sg:classifiers":[
        {
            "category":"Home & Garden",
            "subcategory":"Building Materials",
            "type":"Retail Goods"
        }
    ],
    "sg:phone":"+44 161 343 1591",
    "sg:postcode":"SK16 4XP",
    "sg:province":"Greater Manchester",
    "sg:tags":[
        "window",
        "frame"
    ],
    "wof:name":"Thameside Metroborough Council",
    "wof:placetype":"venue"
},
  "geometry": {"coordinates":[-2.092224,53.476139],"type":"Point"}
}