{
  "type": "Feature",
  "properties": {
    "iso:country":"GB",
    "sg:address":"29 Portfield Road",
    "sg:city":"Christchurch",
    "sg:classifiers":[
        {
            "category":"Building & Trades",
            "subcategory":"Construction",
            "type":"Services"
        }
    ],
    "sg:phone":"+44 1202 485272",
    "sg:postcode":"BH23 2AF",
    "sg:province":"Dorset",
    "sg:tags":[
        "builder"
    ],
    "wof:name":"Inside Out Builders",
    "wof:placetype":"venue"
},
  "geometry": {"coordinates":[-1.7880220413,50.7395210266],"type":"Point"}
}