{
  "type": "Feature",
  "properties": {
    "addr:full":"High St, Neyland Milford Haven Pembrokeshire SA73 1SR",
    "addr:postcode":"sa73 1sr",
    "addr:street":"High St",
    "iso:country":"GB",
    "sg:address":"High St, Neyland",
    "sg:city":"Milford Haven",
    "sg:classifiers":[
        {
            "category":"Travel",
            "subcategory":"Hotels & Motels",
            "type":"Entertainment"
        }
    ],
    "sg:postcode":"SA73 1SR",
    "sg:province":"Pembrokeshire",
    "wof:name":"Lawrenny Castle Hotel",
    "wof:placetype":"venue"
},
  "geometry": {"coordinates":[-4.949875,51.709881],"type":"Point"}
}