{
  "type": "Feature",
  "properties": {
    "addr:full":"The Register Office, Memorial Hospital, Sheep Street Cirencester Gloucestershire GL7 1QW",
    "addr:postcode":"gl7 1qw",
    "addr:street":"Sheep Street",
    "iso:country":"GB",
    "sg:address":"The Register Office, Memorial Hospital, Sheep Street",
    "sg:city":"Cirencester",
    "sg:classifiers":[
        {
            "category":"Government",
            "subcategory":"Office",
            "type":"Public Place"
        }
    ],
    "sg:phone":"+44 1285 650455",
    "sg:postcode":"GL7 1QW",
    "sg:province":"Gloucestershire",
    "sg:tags":[
        "marriage",
        "death",
        "births",
        "local"
    ],
    "wof:name":"Registration of Births Deaths & Marriages",
    "wof:placetype":"venue"
},
  "geometry": {"coordinates":[-1.953541,51.718548],"type":"Point"}
}