{
  "type": "Feature",
  "properties": {
    "addr:full":"4 Camp View, Nailsea Bristol Somerset BS48 2AB",
    "addr:housenumber":"4",
    "addr:postcode":"bs48 2ab",
    "addr:street":"Camp View",
    "iso:country":"GB",
    "sg:address":"4 Camp View, Nailsea",
    "sg:city":"Bristol",
    "sg:classifiers":[
        {
            "category":"Retail",
            "subcategory":"Repair Shop",
            "type":"Services"
        },
        {
            "category":"Building & Trades",
            "subcategory":"Construction",
            "type":"Services"
        }
    ],
    "sg:phone":"+44 1275 852738",
    "sg:postcode":"BS48 2AB",
    "sg:province":"Somerset",
    "sg:tags":[
        "builder",
        "maintenance"
    ],
    "wof:name":"Terence Frederick Grandfield",
    "wof:placetype":"venue"
},
  "geometry": {"coordinates":[-2.7603940964,51.4357948303],"type":"Point"}
}