{
  "type": "Feature",
  "properties": {
    "addr:full":"627 Chesterfield Road Sheffield Derbyshire S8 0RX",
    "addr:housenumber":"627",
    "addr:postcode":"s8 0rx",
    "addr:street":"Chesterfield Road",
    "iso:country":"GB",
    "sg:address":"627 Chesterfield Road",
    "sg:city":"Sheffield",
    "sg:classifiers":[
        {
            "category":"Home & Garden",
            "subcategory":"Home Furnishings",
            "type":"Retail Goods"
        }
    ],
    "sg:phone":"+44 114 258 9168",
    "sg:postcode":"S8 0RX",
    "sg:province":"Derbyshire",
    "sg:tags":[
        "awning",
        "canopy",
        "blinds"
    ],
    "wof:name":"Grants",
    "wof:placetype":"venue"
},
  "geometry": {"coordinates":[-1.4786449671,53.3463134766],"type":"Point"}
}