{
  "type": "Feature",
  "properties": {
    "addr:full":"Information Centre, Leighton Hospital, Middlewich Road Crewe Cheshire CW1 4QJ",
    "addr:postcode":"cw1 4qj",
    "addr:street":"Middlewich Road",
    "iso:country":"GB",
    "sg:address":"Information Centre, Leighton Hospital, Middlewich Road",
    "sg:city":"Crewe",
    "sg:classifiers":[
        {
            "category":"Organizations",
            "subcategory":"Non-profit Organization",
            "type":"Services"
        }
    ],
    "sg:phone":"+44 1270 612385",
    "sg:postcode":"CW1 4QJ",
    "sg:province":"Cheshire",
    "sg:tags":[
        "organisation",
        "voluntary",
        "charity"
    ],
    "wof:name":"The Stroke Association",
    "wof:placetype":"venue"
},
  "geometry": {"coordinates":[-2.4698369503,53.1195831299],"type":"Point"}
}