{
  "type": "Feature",
  "properties": {
    "iso:country":"GB",
    "sg:address":"Haley Ho, Whitehall Rd",
    "sg:city":"Cleckheaton",
    "sg:classifiers":[
        {
            "category":"Building & Trades",
            "subcategory":"Construction",
            "type":"Services"
        }
    ],
    "sg:phone":"+44 1274 855219",
    "sg:postcode":"BD19 4DN",
    "sg:province":"West Yorkshire",
    "sg:tags":[
        "contractor",
        "paving",
        "driveway"
    ],
    "wof:name":"Centre Court Designs Ltd",
    "wof:placetype":"venue"
},
  "geometry": {"coordinates":[-1.7060990334,53.7421913147],"type":"Point"}
}