{
  "type": "Feature",
  "properties": {
    "addr:full":"11 Modena Road Hove East Sussex BN3 5QF",
    "addr:housenumber":"11",
    "addr:postcode":"bn3 5qf",
    "addr:street":"Modena Road",
    "iso:country":"GB",
    "sg:address":"11 Modena Road",
    "sg:city":"Hove",
    "sg:classifiers":[
        {
            "category":"Professional",
            "subcategory":"Accounting & Tax Preparation",
            "type":"Services"
        }
    ],
    "sg:phone":"+44 1273 208012",
    "sg:postcode":"BN3 5QF",
    "sg:province":"East Sussex",
    "sg:tags":[
        "consultant"
    ],
    "wof:name":"M L Russell",
    "wof:placetype":"venue"
},
  "geometry": {"coordinates":[-0.1851660013,50.8318252563],"type":"Point"}
}