{
  "type": "Feature",
  "properties": {
    "addr:full":"69 Lincoln Rd Birmingham West Midlands B27 6PA",
    "addr:housenumber":"69",
    "addr:postcode":"b27 6pa",
    "addr:street":"Lincoln Rd",
    "iso:country":"GB",
    "sg:address":"69 Lincoln Rd",
    "sg:city":"Birmingham",
    "sg:classifiers":[
        {
            "category":"Personal",
            "subcategory":"Beauty Salon",
            "type":"Services"
        }
    ],
    "sg:phone":"+44 121 706 0460",
    "sg:postcode":"B27 6PA",
    "sg:province":"West Midlands",
    "sg:tags":[
        "unisex",
        "hairdresser"
    ],
    "wof:name":"Maurice Hairstylists",
    "wof:placetype":"venue"
},
  "geometry": {"coordinates":[-1.810904026,52.4439620972],"type":"Point"}
}