{
  "type": "Feature",
  "properties": {
    "addr:full":"413 George Street Aberdeen Aberdeen City AB25 1ER",
    "addr:housenumber":"413",
    "addr:postcode":"ab25 1er",
    "addr:street":"George Street",
    "iso:country":"GB",
    "sg:address":"413 George Street",
    "sg:city":"Aberdeen",
    "sg:classifiers":[
        {
            "category":"Fast Food",
            "type":"Food & Drink"
        }
    ],
    "sg:phone":"+44 1224 644933",
    "sg:postcode":"AB25 1ER",
    "sg:province":"Aberdeen City",
    "sg:tags":[
        "away",
        "take"
    ],
    "wof:name":"Nanking",
    "wof:placetype":"venue"
},
  "geometry": {"coordinates":[-2.105309,57.153439],"type":"Point"}
}