{
  "type": "Feature",
  "properties": {
    "addr:full":"131 Brownlow Rd, New Southgate London Greater London N11 2BN",
    "addr:housenumber":"131",
    "addr:postcode":"n11 2bn",
    "addr:street":"Brownlow Rd",
    "iso:country":"GB",
    "sg:address":"131 Brownlow Rd, New Southgate",
    "sg:city":"London",
    "sg:classifiers":[
        {
            "category":"Wholesale",
            "subcategory":"Meat",
            "type":"Manufacturing & Wholesale Goods"
        }
    ],
    "sg:postcode":"N11 2BN",
    "sg:province":"Greater London",
    "sg:tags":[
        "-"
    ],
    "wof:name":"M & S Supplies",
    "wof:placetype":"venue"
},
  "geometry": {"coordinates":[-0.122006,51.612198],"type":"Point"}
}