{
  "type": "Feature",
  "properties": {
    "addr:full":"Crest House 138 Main Road Sidcup Kent DA14 6NY",
    "addr:housenumber":"138",
    "addr:postcode":"da14 6ny",
    "addr:street":"Main Road",
    "iso:country":"GB",
    "sg:address":"Crest House 138 Main Road",
    "sg:city":"Sidcup",
    "sg:classifiers":[
        {
            "category":"Professional",
            "subcategory":"Employment Agencies",
            "type":"Services"
        }
    ],
    "sg:phone":"+44 20 8300 7766",
    "sg:postcode":"DA14 6NY",
    "sg:province":"Kent",
    "sg:tags":[
        "consultant"
    ],
    "wof:name":"Hunters Electrical Wholesale Recruitment Ltd.",
    "wof:placetype":"venue"
},
  "geometry": {"coordinates":[0.0960770026,51.4266204834],"type":"Point"}
}