{
  "type": "Feature",
  "properties": {
    "addr:full":"The Green, Tottenham London Greater London N15 5HZ",
    "addr:postcode":"n15 5hz",
    "addr:street":"Green",
    "iso:country":"GB",
    "sg:address":"The Green, Tottenham",
    "sg:city":"London",
    "sg:classifiers":[
        {
            "category":"Farming",
            "subcategory":"Nursery",
            "type":"Manufacturing & Wholesale Goods"
        }
    ],
    "sg:phone":"+44 20 8808 9194",
    "sg:postcode":"N15 5HZ",
    "sg:province":"Greater London",
    "sg:tags":[
        "creche"
    ],
    "wof:name":"Tottenham Green under Five Centre",
    "wof:placetype":"venue"
},
  "geometry": {"coordinates":[-0.0922890007,51.6082229614],"type":"Point"}
}