{
  "type": "Feature",
  "properties": {
    "addr:full":"Newhaven, Farm Road Chichester West Sussex PO20 8JU",
    "addr:postcode":"po20 8ju",
    "addr:street":"Farm Road",
    "iso:country":"GB",
    "sg:address":"Newhaven, Farm Road",
    "sg:city":"Chichester",
    "sg:classifiers":[
        {
            "category":"Social Services",
            "subcategory":"Adult Care",
            "type":"Services"
        }
    ],
    "sg:postcode":"PO20 8JU",
    "sg:province":"West Sussex",
    "sg:tags":[
        "domestic",
        "cleaning"
    ],
    "wof:name":"Shine on",
    "wof:placetype":"venue"
},
  "geometry": {"coordinates":[-0.8574900031,50.7611312866],"type":"Point"}
}