{
  "type": "Feature",
  "properties": {
    "addr:full":"136-138 Marjorie Street, Belgrave Leicester Leicestershire LE4 5GX",
    "addr:housenumber":"136-138",
    "addr:postcode":"le4 5gx",
    "addr:street":"Marjorie Street",
    "iso:country":"GB",
    "sg:address":"136-138 Marjorie Street, Belgrave",
    "sg:city":"Leicester",
    "sg:classifiers":[
        {
            "category":"Shopping",
            "subcategory":"Clothing, Apparel, & Fashions",
            "type":"Retail Goods"
        }
    ],
    "sg:phone":"+44 116 261 0156",
    "sg:postcode":"LE4 5GX",
    "sg:province":"Leicestershire",
    "sg:tags":[
        "clothing",
        "fabric"
    ],
    "wof:name":"Leicester Garments Ltd.",
    "wof:placetype":"venue"
},
  "geometry": {"coordinates":[-1.128991,52.649128],"type":"Point"}
}