{
  "type": "Feature",
  "properties": {
    "addr:full":"Bath Rd West Drayton Greater London UB7 0DB",
    "addr:postcode":"ub7 0db",
    "addr:street":"Bath Rd",
    "iso:country":"GB",
    "sg:address":"Bath Rd",
    "sg:city":"West Drayton",
    "sg:classifiers":[
        {
            "category":"Professional",
            "subcategory":"Business Services",
            "type":"Services"
        }
    ],
    "sg:phone":"+44 20 8564 8080",
    "sg:postcode":"UB7 0DB",
    "sg:province":"Greater London",
    "wof:name":"Heathrow Business Centre",
    "wof:placetype":"venue"
},
  "geometry": {"coordinates":[-0.491084,51.480179],"type":"Point"}
}