{
  "type": "Feature",
  "properties": {
    "addr:full":"1 Ramsay Crescent Aberdeen Aberdeen City AB10 7BL",
    "addr:housenumber":"1",
    "addr:postcode":"ab10 7bl",
    "addr:street":"Ramsay Crescent",
    "iso:country":"GB",
    "sg:address":"1 Ramsay Crescent",
    "sg:city":"Aberdeen",
    "sg:classifiers":[
        {
            "category":"Shopping",
            "subcategory":"News",
            "type":"Retail Goods"
        }
    ],
    "sg:phone":"+44 1224 208964",
    "sg:postcode":"AB10 7BL",
    "sg:province":"Aberdeen City",
    "sg:tags":[
        "newsagent"
    ],
    "wof:name":"R S McColl",
    "wof:placetype":"venue"
},
  "geometry": {"coordinates":[-2.137997,57.12394],"type":"Point"}
}