{
  "type": "Feature",
  "properties": {
    "iso:country":"GB",
    "sg:address":"1a Washington St",
    "sg:city":"Leeds",
    "sg:classifiers":[
        {
            "category":"Autos & Motor Vehicles",
            "subcategory":"Auto Supplies",
            "type":"Retail Goods"
        }
    ],
    "sg:phone":"+44 113 245 1659",
    "sg:postcode":"LS3 1JQ",
    "sg:province":"West Yorkshire",
    "sg:tags":[
        "exhaust",
        "absorber",
        "shock"
    ],
    "wof:name":"Q E D",
    "wof:placetype":"venue"
},
  "geometry": {"coordinates":[-1.571139,53.801353],"type":"Point"}
}