{
  "type": "Feature",
  "properties": {
    "addr:full":"Mayfield Mill, Briercliffe Rd Chorley Lancashire PR6 0DA",
    "addr:postcode":"pr6 0da",
    "addr:street":"Briercliffe Rd",
    "iso:country":"GB",
    "sg:address":"Mayfield Mill, Briercliffe Rd",
    "sg:city":"Chorley",
    "sg:classifiers":[
        {
            "category":"Shopping",
            "subcategory":"Computers & Home Electronics",
            "type":"Retail Goods"
        }
    ],
    "sg:phone":"+44 1257 263085",
    "sg:postcode":"PR6 0DA",
    "sg:province":"Lancashire",
    "wof:name":"Buoyant Upholstery",
    "wof:placetype":"venue"
},
  "geometry": {"coordinates":[-2.6261799335,53.656829834],"type":"Point"}
}