{
  "type": "Feature",
  "properties": {
    "iso:country":"GB",
    "sg:address":"300 Gibbet Street",
    "sg:city":"Halifax",
    "sg:classifiers":[
        {
            "category":"Bars & Pubs",
            "type":"Food & Drink"
        }
    ],
    "sg:phone":"+44 1422 360960",
    "sg:postcode":"HX1 4JX",
    "sg:province":"West Yorkshire",
    "sg:tags":[
        "pubs",
        "inn"
    ],
    "wof:name":"The Granby",
    "wof:placetype":"venue"
},
  "geometry": {"coordinates":[-1.883963,53.722687],"type":"Point"}
}