{
  "type": "Feature",
  "properties": {
    "iso:country":"GB",
    "sg:address":"37 Oxford Street",
    "sg:city":"Weston-super-mare",
    "sg:classifiers":[
        {
            "category":"Retail",
            "subcategory":"Funeral Services",
            "type":"Services"
        }
    ],
    "sg:phone":"+44 1934 419922",
    "sg:postcode":"BS23 1TN",
    "sg:province":"Somerset",
    "wof:name":"Pearce & Weston Funeral Services",
    "wof:placetype":"venue"
},
  "geometry": {"coordinates":[-2.977825,51.346268],"type":"Point"}
}