{
  "type": "Feature",
  "properties": {
    "addr:full":"904a New Chester Road Wirral Cheshire CH62 6AU",
    "addr:housenumber":"904a",
    "addr:postcode":"ch62 6au",
    "addr:street":"New Chester Road",
    "iso:country":"GB",
    "sg:address":"904a New Chester Road",
    "sg:city":"Wirral",
    "sg:classifiers":[
        {
            "category":"Personal",
            "subcategory":"Beauty Salon",
            "type":"Services"
        },
        {
            "category":"Personal",
            "subcategory":"Sauna",
            "type":"Services"
        }
    ],
    "sg:postcode":"CH62 6AU",
    "sg:province":"Cheshire",
    "sg:tags":[
        "unisex",
        "hairdresser"
    ],
    "wof:name":"Viking Sauna",
    "wof:placetype":"venue"
},
  "geometry": {"coordinates":[-2.971637,53.325054],"type":"Point"}
}