{
  "type": "Feature",
  "properties": {
    "addr:full":"17 Broomfield Place, Springburn Glasgow East Dunbartonshire G21 3UP",
    "addr:housenumber":"17",
    "addr:postcode":"g21 3up",
    "addr:street":"Broomfield Place",
    "iso:country":"GB",
    "sg:address":"17 Broomfield Place, Springburn",
    "sg:city":"Glasgow",
    "sg:classifiers":[
        {
            "category":"Organizations",
            "subcategory":"Membership Organization",
            "type":"Services"
        },
        {
            "category":"Arena",
            "subcategory":"Sports Club",
            "type":"Entertainment"
        }
    ],
    "sg:phone":"+44 141 558 2764",
    "sg:postcode":"G21 3UP",
    "sg:province":"East Dunbartonshire",
    "wof:name":"Springburn Private Bowling Club",
    "wof:placetype":"venue"
},
  "geometry": {"coordinates":[-4.2289447784,55.8872146606],"type":"Point"}
}