{
  "type": "Feature",
  "properties": {
    "addr:full":"451-465 Cleethorpe Road Grimsby Lincolnshire DN31 3BZ",
    "addr:postcode":"451-465;dn31 3bz",
    "addr:street":"Cleethorpe Road",
    "iso:country":"GB",
    "sg:address":"451-465 Cleethorpe Road",
    "sg:city":"Grimsby",
    "sg:classifiers":[
        {
            "category":"Government",
            "subcategory":"Post Office",
            "type":"Public Place"
        }
    ],
    "sg:phone":"+44 1472 340534",
    "sg:postcode":"DN31 3BZ",
    "sg:province":"Lincolnshire",
    "wof:name":"Clee Park Post Office",
    "wof:placetype":"venue"
},
  "geometry": {"coordinates":[-0.057847999,53.572177887],"type":"Point"}
}