{
  "type": "Feature",
  "properties": {
    "iso:country":"GB",
    "sg:address":"Aberconwy House, Castle Street",
    "sg:city":"Conwy",
    "sg:classifiers":[
        {
            "category":"Landmark",
            "subcategory":"Tourist Attraction",
            "type":"Public Place"
        }
    ],
    "sg:phone":"+44 1492 592246",
    "sg:postcode":"LL32 8AY",
    "sg:province":"Conwy",
    "sg:tags":[
        "interest"
    ],
    "wof:name":"The National Trust",
    "wof:placetype":"venue"
},
  "geometry": {"coordinates":[-3.827224,53.280849],"type":"Point"}
}