{
  "type": "Feature",
  "properties": {
    "iso:country":"GB",
    "sg:address":"Wellington House, 20-32 Wellington St",
    "sg:city":"Leicester",
    "sg:classifiers":[
        {
            "category":"Banks & Credit Unions",
            "subcategory":"Bank",
            "type":"Services"
        }
    ],
    "sg:phone":"+44 116 280 2241",
    "sg:postcode":"LE1 6HL",
    "sg:province":"Leicestershire",
    "wof:name":"H S B C Trade Services",
    "wof:placetype":"venue"
},
  "geometry": {"coordinates":[-1.13223,52.631927],"type":"Point"}
}