{
  "type": "Feature",
  "properties": {
    "iso:country":"GB",
    "sg:address":"Stockport Road East, Bredbury",
    "sg:city":"Stockport",
    "sg:classifiers":[
        {
            "category":"Manufacturing",
            "subcategory":"Tools & Machinery",
            "type":"Manufacturing & Wholesale Goods"
        }
    ],
    "sg:phone":"+44 161 430 5231",
    "sg:postcode":"SK6 2AT",
    "sg:province":"Cheshire",
    "wof:name":"Ajax Machine Tool Co. Ltd.",
    "wof:placetype":"venue"
},
  "geometry": {"coordinates":[-2.107924,53.424046],"type":"Point"}
}