{
  "type": "Feature",
  "properties": {
    "addr:full":"8 North Street Farm Stoke-sub-hamdon Somerset TA14 6QR",
    "addr:housenumber":"8;stoke-sub-hamdon",
    "addr:postcode":"ta14 6qr",
    "addr:street":"North Street;Somerset",
    "iso:country":"GB",
    "sg:address":"8 North Street Farm",
    "sg:city":"Stoke-sub-hamdon",
    "sg:classifiers":[
        {
            "category":"Professional",
            "subcategory":"Business Services",
            "type":"Services"
        }
    ],
    "sg:phone":"+44 1935 825082",
    "sg:postcode":"TA14 6QR",
    "sg:province":"Somerset",
    "sg:tags":[
        "fashion",
        "agent"
    ],
    "wof:name":"Mark Lovell Ltd.",
    "wof:placetype":"venue"
},
  "geometry": {"coordinates":[-2.7505269051,50.9536094666],"type":"Point"}
}