{
  "type": "Feature",
  "properties": {
    "addr:full":"Hafan, Hardwick Hill La Chepstow Gloucestershire NP6 5PP",
    "addr:postcode":"np6 5pp",
    "addr:street":"Hardwick Hill La Chepstow",
    "iso:country":"GB",
    "sg:address":"Hafan, Hardwick Hill La",
    "sg:city":"Chepstow",
    "sg:classifiers":[
        {
            "category":"Health Services",
            "subcategory":"Health Practitioner",
            "type":"Services"
        }
    ],
    "sg:phone":"+44 1291 623792",
    "sg:postcode":"NP6 5PP",
    "sg:province":"Gloucestershire",
    "sg:tags":[
        "osteopath"
    ],
    "wof:name":"D Edmund Parker",
    "wof:placetype":"venue"
},
  "geometry": {"coordinates":[-2.680182,51.638103],"type":"Point"}
}