{
  "type": "Feature",
  "properties": {
    "iso:country":"GB",
    "sg:address":"Unit 3b Cockersdale Works, Whitehall Road, Drighlington",
    "sg:city":"Bradford",
    "sg:classifiers":[
        {
            "category":"Manufacturing",
            "subcategory":"Metals",
            "type":"Manufacturing & Wholesale Goods"
        }
    ],
    "sg:phone":"+44 113 285 3988",
    "sg:postcode":"BD11 1NQ",
    "sg:province":"West Yorkshire",
    "sg:tags":[
        "product",
        "fabricated"
    ],
    "wof:name":"Stainfree Fabrications Ltd.",
    "wof:placetype":"venue"
},
  "geometry": {"coordinates":[-1.662250042,53.7565917969],"type":"Point"}
}