{
  "type": "Feature",
  "properties": {
    "addr:full":"58 Hexthorpe Road Doncaster South Yorkshire DN4 0BD",
    "addr:housenumber":"58",
    "addr:postcode":"dn4 0bd",
    "addr:street":"Hexthorpe Road",
    "iso:country":"GB",
    "sg:address":"58 Hexthorpe Road",
    "sg:city":"Doncaster",
    "sg:classifiers":[
        {
            "category":"Arts & Performance",
            "subcategory":"Music",
            "type":"Entertainment"
        },
        {
            "category":"Professional",
            "subcategory":"Computer Services",
            "type":"Services"
        }
    ],
    "sg:phone":"+44 1302 342818",
    "sg:postcode":"DN4 0BD",
    "sg:province":"South Yorkshire",
    "sg:tags":[
        "mobile",
        "software",
        "system",
        "disco"
    ],
    "wof:name":"Strobes Disco",
    "wof:placetype":"venue"
},
  "geometry": {"coordinates":[-1.146762,53.51833],"type":"Point"}
}