{
  "type": "Feature",
  "properties": {
    "iso:country":"GB",
    "sg:address":"432 Chickerell Road, Chickerell",
    "sg:city":"Weymouth",
    "sg:classifiers":[
        {
            "category":"Health Services",
            "subcategory":"Nursing And Care Facility",
            "type":"Services"
        }
    ],
    "sg:phone":"+44 1305 773128",
    "sg:postcode":"DT3 4DQ",
    "sg:province":"Dorset",
    "sg:tags":[
        "home"
    ],
    "wof:name":"Montevideo House Nursing Home",
    "wof:placetype":"venue"
},
  "geometry": {"coordinates":[-2.4990470409,50.6148986816],"type":"Point"}
}