{
  "type": "Feature",
  "properties": {
    "iso:country":"GB",
    "sg:address":"55a Oreston Road",
    "sg:city":"Plymouth",
    "sg:classifiers":[
        {
            "category":"Professional",
            "subcategory":"Engineering",
            "type":"Services"
        }
    ],
    "sg:postcode":"PL9 7JU",
    "sg:province":"Devon",
    "wof:name":"Cts Engineering Ltd.",
    "wof:placetype":"venue"
},
  "geometry": {"coordinates":[-4.104028,50.363258],"type":"Point"}
}