{
  "type": "Feature",
  "properties": {
    "iso:country":"GB",
    "sg:address":"Ty Cooke Farm, Mamhilad",
    "sg:city":"Pontypool",
    "sg:classifiers":[
        {
            "category":"Farming",
            "subcategory":"Livestock Farm",
            "type":"Manufacturing & Wholesale Goods"
        }
    ],
    "sg:postcode":"NP4 8QZ",
    "sg:province":"Monmouthshire",
    "sg:tags":[
        "others"
    ],
    "wof:name":"R J Price",
    "wof:placetype":"venue"
},
  "geometry": {"coordinates":[-3.04319,51.703087],"type":"Point"}
}