{
  "type": "Feature",
  "properties": {
    "addr:full":"252 St Saviours Road Leicester Leicestershire LE5 4HF",
    "addr:housenumber":"252",
    "addr:postcode":"le5 4hf",
    "addr:street":"St Saviours Road",
    "iso:country":"GB",
    "sg:address":"252 St Saviours Road",
    "sg:city":"Leicester",
    "sg:classifiers":[
        {
            "category":"Shopping",
            "subcategory":"Clothing, Apparel, & Fashions",
            "type":"Retail Goods"
        }
    ],
    "sg:postcode":"LE5 4HF",
    "sg:province":"Leicestershire",
    "sg:tags":[
        "shop"
    ],
    "wof:name":"Deepa Fashions",
    "wof:placetype":"venue"
},
  "geometry": {"coordinates":[-1.103358984,52.6351699829],"type":"Point"}
}