{
  "type": "Feature",
  "properties": {
    "iso:country":"GB",
    "sg:address":"2 Hurn Road",
    "sg:city":"Dereham",
    "sg:classifiers":[
        {
            "category":"Manufacturing",
            "subcategory":"Petroleum Products",
            "type":"Manufacturing & Wholesale Goods"
        },
        {
            "category":"Building & Trades",
            "subcategory":"Construction",
            "type":"Services"
        }
    ],
    "sg:phone":"+44 1362 692212",
    "sg:postcode":"NR19 1WD",
    "sg:province":"Norfolk",
    "sg:tags":[
        "double",
        "glazing",
        "installers"
    ],
    "wof:name":"Henman Green Ltd.",
    "wof:placetype":"venue"
},
  "geometry": {"coordinates":[0.95705,52.672546],"type":"Point"}
}