{
  "type": "Feature",
  "properties": {
    "addr:full":"Beehive Club Ho, St Marys Field Bridport Dorset DT6 6AN",
    "addr:postcode":"dt6 6an",
    "addr:street":"St;Dorset",
    "iso:country":"GB",
    "sg:address":"Beehive Club Ho, St Marys Field",
    "sg:city":"Bridport",
    "sg:classifiers":[
        {
            "category":"Arena",
            "subcategory":"Sports Club",
            "type":"Entertainment"
        }
    ],
    "sg:phone":"+44 1308 423834",
    "sg:postcode":"DT6 6AN",
    "sg:province":"Dorset",
    "wof:name":"Bridport Football Club",
    "wof:placetype":"venue"
},
  "geometry": {"coordinates":[-2.758019,50.733566],"type":"Point"}
}