{
  "type": "Feature",
  "properties": {
    "addr:full":"Derwent House, Willersley Lane Matlock Derbyshire DE4 5JG",
    "addr:postcode":"de4 5jg",
    "addr:street":"Willersley Lane",
    "iso:country":"GB",
    "sg:address":"Derwent House, Willersley Lane",
    "sg:city":"Matlock",
    "sg:classifiers":[
        {
            "category":"Organizations",
            "subcategory":"Religious Organization",
            "type":"Services"
        }
    ],
    "sg:postcode":"DE4 5JG",
    "sg:province":"Derbyshire",
    "sg:tags":[
        "organisation"
    ],
    "wof:name":"Wesley Guild Holidays (London) Ltd.",
    "wof:placetype":"venue"
},
  "geometry": {"coordinates":[-1.5500710011,53.1157951355],"type":"Point"}
}