{
  "type": "Feature",
  "properties": {
    "addr:full":"16-20 Dereham Place London Greater London EC2A 3HJ",
    "addr:housenumber":"16-20",
    "addr:postcode":"ec2a 3hj",
    "addr:street":"Dereham Place",
    "iso:country":"GB",
    "sg:address":"16-20 Dereham Place",
    "sg:city":"London",
    "sg:classifiers":[
        {
            "category":"Professional",
            "subcategory":"Art Services",
            "type":"Services"
        }
    ],
    "sg:phone":"+44 20 7684 9084",
    "sg:postcode":"EC2A 3HJ",
    "sg:province":"Greater London",
    "sg:tags":[
        "graphic",
        "designer"
    ],
    "wof:name":"K M A Ltd.",
    "wof:placetype":"venue"
},
  "geometry": {"coordinates":[-0.078401,51.525654],"type":"Point"}
}