{
  "type": "Feature",
  "properties": {
    "addr:full":"Elm Road Wisbech Cambridgeshire PE13 2TE",
    "addr:postcode":"pe13 2te",
    "addr:street":"Elm Road",
    "iso:country":"GB",
    "sg:address":"Elm Road",
    "sg:city":"Wisbech",
    "sg:classifiers":[
        {
            "category":"Wholesale",
            "subcategory":"Scrap",
            "type":"Manufacturing & Wholesale Goods"
        }
    ],
    "sg:postcode":"PE13 2TE",
    "sg:province":"Cambridgeshire",
    "sg:tags":[
        "breaker",
        "dismantlers"
    ],
    "wof:name":"Herbie Motors",
    "wof:placetype":"venue"
},
  "geometry": {"coordinates":[0.165205,52.659828],"type":"Point"}
}