{
  "type": "Feature",
  "properties": {
    "addr:full":"7 Mckay Trading Estate, Blackthorne Road, Colnbrook Slough Berkshire SL3 0AH",
    "addr:housenumber":"7",
    "addr:postcode":"sl3 0ah",
    "addr:street":"Mckay Trading Estate Blackthorne Road",
    "iso:country":"GB",
    "sg:address":"7 Mckay Trading Estate, Blackthorne Road, Colnbrook",
    "sg:city":"Slough",
    "sg:classifiers":[
        {
            "category":"Freight",
            "type":"Transportation"
        }
    ],
    "sg:phone":"+44 1753 688188",
    "sg:postcode":"SL3 0AH",
    "sg:province":"Berkshire",
    "sg:tags":[
        "forwarders"
    ],
    "wof:name":"Walsh Freight Services Ltd.",
    "wof:placetype":"venue"
},
  "geometry": {"coordinates":[-0.526976,51.484173],"type":"Point"}
}