{
  "type": "Feature",
  "properties": {
    "addr:full":"43 Bridgnorth Road, Compton Wolverhampton Shropshire WV6 8AF",
    "addr:housenumber":"43",
    "addr:postcode":"wv6 8af",
    "addr:street":"Bridgnorth Road",
    "iso:country":"GB",
    "sg:address":"43 Bridgnorth Road, Compton",
    "sg:city":"Wolverhampton",
    "sg:classifiers":[
        {
            "category":"Shopping",
            "subcategory":"Clothing, Apparel, & Fashions",
            "type":"Retail Goods"
        }
    ],
    "sg:phone":"+44 1902 753193",
    "sg:postcode":"WV6 8AF",
    "sg:province":"Shropshire",
    "sg:tags":[
        "shop"
    ],
    "wof:name":"Cache",
    "wof:placetype":"venue"
},
  "geometry": {"coordinates":[-2.1755371094,52.5869293213],"type":"Point"}
}