{
  "type": "Feature",
  "properties": {
    "iso:country":"GB",
    "sg:address":"Market Place",
    "sg:city":"Ambleside",
    "sg:classifiers":[
        {
            "category":"Government",
            "subcategory":"Post Office",
            "type":"Public Place"
        }
    ],
    "sg:phone":"+44 15394 32267",
    "sg:postcode":"LA22 0AA",
    "sg:province":"Cumbria",
    "wof:name":"Etcetera",
    "wof:placetype":"venue"
},
  "geometry": {"coordinates":[-2.961827,54.431721],"type":"Point"}
}