{
  "type": "Feature",
  "properties": {
    "iso:country":"GB",
    "sg:address":"Ivydene, Whelpley Hill",
    "sg:city":"Chesham",
    "sg:classifiers":[
        {
            "category":"Retail",
            "subcategory":"Auto Repair",
            "type":"Services"
        }
    ],
    "sg:postcode":"HP5 3RN",
    "sg:province":"Buckinghamshire",
    "sg:tags":[
        "modification",
        "garage"
    ],
    "wof:name":"Date A Car",
    "wof:placetype":"venue"
},
  "geometry": {"coordinates":[-0.609333,51.710537],"type":"Point"}
}