{
  "type": "Feature",
  "properties": {
    "addr:full":"High Street North Dunstable Bedfordshire LU6 1UZ",
    "addr:postcode":"lu6 1uz",
    "addr:street":"High Street North",
    "iso:country":"GB",
    "sg:address":"High Street North",
    "sg:city":"Dunstable",
    "sg:classifiers":[
        {
            "category":"Shopping",
            "type":"Retail Goods"
        }
    ],
    "sg:postcode":"LU6 1UZ",
    "sg:province":"Bedfordshire",
    "sg:tags":[
        "part",
        "accessory"
    ],
    "wof:name":"A C D Tridon (Holdings) Ltd.",
    "wof:placetype":"venue"
},
  "geometry": {"coordinates":[-0.5317590237,51.8937339783],"type":"Point"}
}