{
  "type": "Feature",
  "properties": {
    "addr:full":"52 Pages Lane, Great Barr Birmingham West Midlands B43 6LR",
    "addr:housenumber":"52",
    "addr:postcode":"b43 6lr",
    "addr:street":"Pages Lane",
    "iso:country":"GB",
    "sg:address":"52 Pages Lane, Great Barr",
    "sg:city":"Birmingham",
    "sg:classifiers":[
        {
            "category":"Home & Garden",
            "subcategory":"Building Materials",
            "type":"Retail Goods"
        }
    ],
    "sg:phone":"+44 121 358 1101",
    "sg:postcode":"B43 6LR",
    "sg:province":"West Midlands",
    "sg:tags":[
        "plaster",
        "ware"
    ],
    "wof:name":"Regency House Ornate Plaster",
    "wof:placetype":"venue"
},
  "geometry": {"coordinates":[-1.936228,52.549965],"type":"Point"}
}