{
  "type": "Feature",
  "properties": {
    "addr:full":"9 Thingwall Road Wirral Merseyside CH61 3UA",
    "addr:housenumber":"9",
    "addr:postcode":"ch61 3ua",
    "addr:street":"Thingwall Road",
    "iso:country":"GB",
    "sg:address":"9 Thingwall Road",
    "sg:city":"Wirral",
    "sg:classifiers":[
        {
            "category":"Fast Food",
            "type":"Food & Drink"
        }
    ],
    "sg:phone":"+44 151 648 0111",
    "sg:postcode":"CH61 3UA",
    "sg:province":"Merseyside",
    "sg:tags":[
        "away",
        "take"
    ],
    "wof:name":"Dial A Pizza",
    "wof:placetype":"venue"
},
  "geometry": {"coordinates":[-3.097415,53.35603],"type":"Point"}
}