{
  "type": "Feature",
  "properties": {
    "iso:country":"GB",
    "sg:address":"5 Academy Street",
    "sg:city":"Coatbridge",
    "sg:classifiers":[
        {
            "category":"Banks & Credit Unions",
            "subcategory":"Financial Services",
            "type":"Services"
        }
    ],
    "sg:phone":"+44 1236 427949",
    "sg:postcode":"ML5 3AW",
    "sg:province":"North Lanarkshire",
    "sg:tags":[
        "building",
        "society"
    ],
    "wof:name":"Dunfermline Building Society",
    "wof:placetype":"venue"
},
  "geometry": {"coordinates":[-4.028173,55.862816],"type":"Point"}
}