{
  "type": "Feature",
  "properties": {
    "iso:country":"GB",
    "sg:address":"Unit 15, Charles St",
    "sg:city":"West Bromwich",
    "sg:classifiers":[
        {
            "category":"Shopping",
            "subcategory":"Computers & Home Electronics",
            "type":"Retail Goods"
        }
    ],
    "sg:phone":"+44 121 520 8645",
    "sg:postcode":"B70 0AY",
    "sg:province":"West Midlands",
    "sg:tags":[
        "electrical"
    ],
    "wof:name":"Sparky's Electrical Wholesale Ltd",
    "wof:placetype":"venue"
},
  "geometry": {"coordinates":[-2.0269610882,52.5284576416],"type":"Point"}
}