{
  "type": "Feature",
  "properties": {
    "addr:full":"Ilderton Station Alnwick Northumberland NE66 4PH",
    "addr:postcode":"ne66 4ph",
    "addr:street":"Northumberland",
    "iso:country":"GB",
    "sg:address":"Ilderton Station",
    "sg:city":"Alnwick",
    "sg:classifiers":[
        {
            "category":"Manufacturing",
            "subcategory":"Glass & Minerals",
            "type":"Manufacturing & Wholesale Goods"
        }
    ],
    "sg:phone":"+44 1668 217901",
    "sg:postcode":"NE66 4PH",
    "sg:province":"Northumberland",
    "sg:tags":[
        "stained"
    ],
    "wof:name":"I W F Ltd.",
    "wof:placetype":"venue"
},
  "geometry": {"coordinates":[-1.9756339788,55.4911460876],"type":"Point"}
}