{
  "type": "Feature",
  "properties": {
    "iso:country":"GB",
    "sg:address":"50 Haughton Grn",
    "sg:city":"Darlington",
    "sg:classifiers":[
        {
            "category":"Farming",
            "subcategory":"Nursery",
            "type":"Manufacturing & Wholesale Goods"
        }
    ],
    "sg:phone":"+44 1325 464443",
    "sg:postcode":"DL1 2DF",
    "sg:province":"Durham",
    "sg:tags":[
        "creche"
    ],
    "wof:name":"Secret Garden Childrens Nursery",
    "wof:placetype":"venue"
},
  "geometry": {"coordinates":[-1.5209809542,54.5377197266],"type":"Point"}
}