{
  "type": "Feature",
  "properties": {
    "iso:country":"GB",
    "sg:address":"13 Spurgeon Avenue",
    "sg:city":"London",
    "sg:classifiers":[
        {
            "category":"Professional",
            "subcategory":"Art Services",
            "type":"Services"
        }
    ],
    "sg:phone":"+44 20 8768 0908",
    "sg:postcode":"SE19 3UQ",
    "sg:province":"Greater London",
    "sg:tags":[
        "consultant",
        "design"
    ],
    "wof:name":"Palmer Johnson Design",
    "wof:placetype":"venue"
},
  "geometry": {"coordinates":[-0.093709,51.413185],"type":"Point"}
}