{
  "type": "Feature",
  "properties": {
    "iso:country":"GB",
    "sg:address":"4 Birmingham Road",
    "sg:city":"Kidderminster",
    "sg:classifiers":[
        {
            "category":"Professional",
            "subcategory":"Engineering",
            "type":"Services"
        }
    ],
    "sg:phone":"+44 1562 820673",
    "sg:postcode":"DY10 2BX",
    "sg:province":"Staffordshire",
    "sg:tags":[
        "contractor",
        "electrical",
        "engineer"
    ],
    "wof:name":"Arden Electrical Contractors",
    "wof:placetype":"venue"
},
  "geometry": {"coordinates":[-2.239939,52.390472],"type":"Point"}
}