{
  "type": "Feature",
  "properties": {
    "addr:full":"Buccleuch Mills, Green Lane Hawick Cumbria TD9 0HR",
    "addr:postcode":"td9 0hr",
    "addr:street":"Buccleuch Mills Green Lane",
    "iso:country":"GB",
    "sg:address":"Buccleuch Mills, Green Lane",
    "sg:city":"Hawick",
    "sg:classifiers":[
        {
            "category":"Shopping",
            "subcategory":"Crafts & Fabrics",
            "type":"Retail Goods"
        }
    ],
    "sg:phone":"+44 1450 371441",
    "sg:postcode":"TD9 0HR",
    "sg:province":"Cumbria",
    "sg:tags":[
        "knitwear",
        "yarn"
    ],
    "wof:name":"Glenhowe of Scotland Ltd.",
    "wof:placetype":"venue"
},
  "geometry": {"coordinates":[-2.787549,55.422146],"type":"Point"}
}