{
  "type": "Feature",
  "properties": {
    "addr:full":"7 Market Place London Greater London NW11 6LB",
    "addr:housenumber":"7",
    "addr:postcode":"nw11 6lb",
    "addr:street":"Market Place",
    "iso:country":"GB",
    "sg:address":"7 Market Place",
    "sg:city":"London",
    "sg:classifiers":[
        {
            "category":"Home & Garden",
            "subcategory":"Home Furnishings",
            "type":"Retail Goods"
        }
    ],
    "sg:phone":"+44 20 8209 1665",
    "sg:postcode":"NW11 6LB",
    "sg:province":"Greater London",
    "sg:tags":[
        "blind",
        "curtain",
        "fitting"
    ],
    "wof:name":"Curtain Call (Uk) Ltd.",
    "wof:placetype":"venue"
},
  "geometry": {"coordinates":[-0.1834439933,51.5861129761],"type":"Point"}
}