{
  "type": "Feature",
  "properties": {
    "addr:full":"Oak Farm, 276 Fakenham Road Norwich Norfolk NR8 6AD",
    "addr:housenumber":"276",
    "addr:postcode":"nr8 6ad",
    "addr:street":"Oak;Fakenham Road Norwich Norfolk",
    "iso:country":"GB",
    "sg:address":"Oak Farm, 276 Fakenham Road",
    "sg:city":"Norwich",
    "sg:classifiers":[
        {
            "category":"Health Services",
            "subcategory":"Nursing And Care Facility",
            "type":"Services"
        }
    ],
    "sg:phone":"+44 1603 868953",
    "sg:postcode":"NR8 6AD",
    "sg:province":"Norfolk",
    "sg:tags":[
        "home"
    ],
    "wof:name":"Oak Farm Physical Rehabilitaion Unit",
    "wof:placetype":"venue"
},
  "geometry": {"coordinates":[1.1961100101,52.686958313],"type":"Point"}
}