{
  "type": "Feature",
  "properties": {
    "addr:full":"Kinmuck Inverurie Aberdeenshire AB51 0LY",
    "addr:postcode":"ab51 0ly",
    "iso:country":"GB",
    "sg:address":"Kinmuck",
    "sg:city":"Inverurie",
    "sg:classifiers":[
        {
            "category":"Bars & Pubs",
            "type":"Food & Drink"
        }
    ],
    "sg:phone":"+44 1224 791235",
    "sg:postcode":"AB51 0LY",
    "sg:province":"Aberdeenshire",
    "sg:tags":[
        "pubs",
        "inn"
    ],
    "wof:name":"The Boars Head Inn",
    "wof:placetype":"venue"
},
  "geometry": {"coordinates":[-2.303249,57.268696],"type":"Point"}
}