{
  "type": "Feature",
  "properties": {
    "iso:country":"GB",
    "sg:address":"31 Mitcham Road",
    "sg:city":"Camberley",
    "sg:classifiers":[
        {
            "category":"Social Services",
            "subcategory":"Adult Care",
            "type":"Services"
        }
    ],
    "sg:phone":"+44 1276 676757",
    "sg:postcode":"GU15 4AR",
    "sg:province":"Berkshire",
    "sg:tags":[
        "domestic",
        "cleaning"
    ],
    "wof:name":"Squeaky Clean",
    "wof:placetype":"venue"
},
  "geometry": {"coordinates":[-0.7212659717,51.3531799316],"type":"Point"}
}