{
  "type": "Feature",
  "properties": {
    "addr:full":"288 Beaver Rd Ashford Kent TN23 7RP",
    "addr:housenumber":"288",
    "addr:postcode":"tn23 7rp",
    "addr:street":"Beaver Rd",
    "iso:country":"GB",
    "sg:address":"288 Beaver Rd",
    "sg:city":"Ashford",
    "sg:classifiers":[
        {
            "category":"Building & Trades",
            "subcategory":"Plumbing",
            "type":"Services"
        }
    ],
    "sg:phone":"+44 1233 623147",
    "sg:postcode":"TN23 7RP",
    "sg:province":"Kent",
    "sg:tags":[
        "heating"
    ],
    "wof:name":"J Barnard",
    "wof:placetype":"venue"
},
  "geometry": {"coordinates":[0.8665599823,51.1366844177],"type":"Point"}
}