{
  "type": "Feature",
  "properties": {
    "addr:full":"12 Chisholm Avenue Dunblane Perth and Kinross FK15 0BP",
    "addr:housenumber":"12",
    "addr:postcode":"fk15 0bp",
    "addr:street":"Chisholm Avenue",
    "iso:country":"GB",
    "sg:address":"12 Chisholm Avenue",
    "sg:city":"Dunblane",
    "sg:classifiers":[
        {
            "category":"Professional",
            "subcategory":"Art Services",
            "type":"Services"
        }
    ],
    "sg:postcode":"FK15 0BP",
    "sg:province":"Perth and Kinross",
    "sg:tags":[
        "consultant",
        "design"
    ],
    "wof:name":"Stevenson Sharpe Ltd.",
    "wof:placetype":"venue"
},
  "geometry": {"coordinates":[-3.957725,56.194572],"type":"Point"}
}