{
  "type": "Feature",
  "properties": {
    "addr:full":"2 Huby Road, Sutton On Forest York North Yorkshire YO61 1DY",
    "addr:housenumber":"2",
    "addr:postcode":"yo61 1dy",
    "addr:street":"Huby Road",
    "iso:country":"GB",
    "sg:address":"2 Huby Road, Sutton On Forest",
    "sg:city":"York",
    "sg:classifiers":[
        {
            "category":"Shopping",
            "subcategory":"Mobile Phones",
            "type":"Retail Goods"
        }
    ],
    "sg:postcode":"YO61 1DY",
    "sg:province":"North Yorkshire",
    "sg:tags":[
        "answering",
        "telephone"
    ],
    "wof:name":"J Johnson & K Beaumont",
    "wof:placetype":"venue"
},
  "geometry": {"coordinates":[-1.115714,54.074741],"type":"Point"}
}