{
  "type": "Feature",
  "properties": {
    "addr:full":"Grape Lane Whitby North Yorkshire YO22 4BE",
    "addr:postcode":"yo22 4be",
    "addr:street":"Grape Lane",
    "iso:country":"GB",
    "sg:address":"Grape Lane",
    "sg:city":"Whitby",
    "sg:classifiers":[
        {
            "category":"Museum",
            "subcategory":"Art Museum",
            "type":"Entertainment"
        }
    ],
    "sg:phone":"+44 1947 601900",
    "sg:postcode":"YO22 4BE",
    "sg:province":"North Yorkshire",
    "sg:tags":[
        "gallery"
    ],
    "wof:name":"Captain Cook Memorial Museum",
    "wof:placetype":"venue"
},
  "geometry": {"coordinates":[-0.6123610139,54.4870910645],"type":"Point"}
}