{
  "type": "Feature",
  "properties": {
    "iso:country":"GB",
    "sg:address":"Bucklea, Manson Lane",
    "sg:city":"Monmouth",
    "sg:classifiers":[
        {
            "category":"Building & Trades",
            "subcategory":"Pest Control",
            "type":"Services"
        }
    ],
    "sg:phone":"+44 1600 715559",
    "sg:postcode":"NP25 5RB",
    "sg:province":"Gloucestershire",
    "sg:tags":[
        "vermin"
    ],
    "wof:name":"Kiltec Services",
    "wof:placetype":"venue"
},
  "geometry": {"coordinates":[-2.728054,51.836884],"type":"Point"}
}