{
  "type": "Feature",
  "properties": {
    "addr:full":"7 Linacre Crescent Cirencester Gloucestershire GL7 1WB",
    "addr:housenumber":"7",
    "addr:postcode":"gl7 1wb",
    "addr:street":"Linacre Crescent",
    "iso:country":"GB",
    "sg:address":"7 Linacre Crescent",
    "sg:city":"Cirencester",
    "sg:classifiers":[
        {
            "category":"Building & Trades",
            "subcategory":"Construction",
            "type":"Services"
        }
    ],
    "sg:postcode":"GL7 1WB",
    "sg:province":"Gloucestershire",
    "sg:tags":[
        "window",
        "replacement"
    ],
    "wof:name":"Fix-It Windows & Doors",
    "wof:placetype":"venue"
},
  "geometry": {"coordinates":[-1.976764,51.703415],"type":"Point"}
}