{
  "type": "Feature",
  "properties": {
    "addr:full":"2 Vicarage Road, Mickleover Derby Derbyshire DE3 0EA",
    "addr:housenumber":"2",
    "addr:postcode":"de3 0ea",
    "addr:street":"Vicarage Road",
    "iso:country":"GB",
    "sg:address":"2 Vicarage Road, Mickleover",
    "sg:city":"Derby",
    "sg:classifiers":[
        {
            "category":"Shopping",
            "subcategory":"Florist",
            "type":"Retail Goods"
        }
    ],
    "sg:postcode":"DE3 0EA",
    "sg:province":"Derbyshire",
    "wof:name":"Floral Dreams",
    "wof:placetype":"venue"
},
  "geometry": {"coordinates":[-1.546159029,52.9057197571],"type":"Point"}
}