{
  "type": "Feature",
  "properties": {
    "iso:country":"GB",
    "sg:address":"1 Dale Valley Gardens",
    "sg:city":"Southampton",
    "sg:classifiers":[
        {
            "category":"Retail",
            "subcategory":"Driving School",
            "type":"Services"
        }
    ],
    "sg:phone":"+44 23 8077 5987",
    "sg:postcode":"SO16 6QT",
    "sg:province":"Hampshire",
    "wof:name":"Easy-Way School Of Motoring",
    "wof:placetype":"venue"
},
  "geometry": {"coordinates":[-1.4289239645,50.9321937561],"type":"Point"}
}