{
  "type": "Feature",
  "properties": {
    "iso:country":"GB",
    "sg:address":"The Cadcam Centre, The Stable Block",
    "sg:city":"Alresford",
    "sg:classifiers":[
        {
            "category":"Manufacturing",
            "subcategory":"Chemicals & Compounds",
            "type":"Manufacturing & Wholesale Goods"
        }
    ],
    "sg:postcode":"SO24 9RE",
    "sg:province":"Hampshire",
    "wof:name":"Adichem U K Ltd.",
    "wof:placetype":"venue"
},
  "geometry": {"coordinates":[-1.161724,51.090511],"type":"Point"}
}