{
  "type": "Feature",
  "properties": {
    "iso:country":"GB",
    "sg:address":"Fillingate",
    "sg:city":"Leicester",
    "sg:classifiers":[
        {
            "category":"Professional",
            "subcategory":"Engineering",
            "type":"Services"
        }
    ],
    "sg:phone":"+44 116 267 1458",
    "sg:postcode":"LE7 4PF",
    "sg:province":"Leicestershire",
    "sg:tags":[
        "consulting",
        "engineer"
    ],
    "wof:name":"White's Environmental",
    "wof:placetype":"venue"
},
  "geometry": {"coordinates":[-1.116981,52.694523],"type":"Point"}
}