{
  "type": "Feature",
  "properties": {
    "iso:country":"GB",
    "sg:address":"11a New Rd",
    "sg:city":"Chippenham",
    "sg:classifiers":[
        {
            "category":"Manufacturing",
            "subcategory":"Tools & Machinery",
            "type":"Manufacturing & Wholesale Goods"
        }
    ],
    "sg:phone":"+44 1249 651151",
    "sg:postcode":"SN15 1HJ",
    "sg:province":"Wiltshire",
    "sg:tags":[
        "society",
        "friendly"
    ],
    "wof:name":"Motor & General Insurance",
    "wof:placetype":"venue"
},
  "geometry": {"coordinates":[-2.118507,51.461666],"type":"Point"}
}