{
  "type": "Feature",
  "properties": {
    "iso:country":"GB",
    "sg:address":"2 Sycamore Close",
    "sg:city":"Malvern",
    "sg:classifiers":[
        {
            "category":"Building & Trades",
            "subcategory":"Construction",
            "type":"Services"
        }
    ],
    "sg:phone":"+44 7712 527224",
    "sg:postcode":"WR13 5LD",
    "sg:province":"Gloucestershire",
    "sg:tags":[
        "dry",
        "lining",
        "plasterers",
        "screeders"
    ],
    "wof:name":"Semin Distribution",
    "wof:placetype":"venue"
},
  "geometry": {"coordinates":[-2.400155,52.117664],"type":"Point"}
}