{
  "type": "Feature",
  "properties": {
    "iso:country":"GB",
    "sg:address":"Bromford Road",
    "sg:city":"Birmingham",
    "sg:classifiers":[
        {
            "category":"Education",
            "subcategory":"School",
            "type":"Public Place"
        },
        {
            "category":"Government",
            "subcategory":"Office",
            "type":"Public Place"
        }
    ],
    "sg:phone":"+44 121 464 4797",
    "sg:postcode":"B36 8JH",
    "sg:province":"West Midlands",
    "sg:tags":[
        "local",
        "authority"
    ],
    "wof:name":"Bromford Junior School",
    "wof:placetype":"venue"
},
  "geometry": {"coordinates":[-1.827079,52.503021],"type":"Point"}
}