{
  "type": "Feature",
  "properties": {
    "addr:full":"101 Mumbles Road, West Cross Swansea Swansea SA3 5TW",
    "addr:housenumber":"101",
    "addr:postcode":"sa3 5tw",
    "addr:street":"Mumbles Road West Cross",
    "iso:country":"GB",
    "sg:address":"101 Mumbles Road, West Cross",
    "sg:city":"Swansea",
    "sg:classifiers":[
        {
            "category":"Home & Garden",
            "subcategory":"Home Furnishings",
            "type":"Retail Goods"
        }
    ],
    "sg:phone":"+44 1792 404979",
    "sg:postcode":"SA3 5TW",
    "sg:province":"Swansea",
    "sg:tags":[
        "blind",
        "curtain",
        "fitting"
    ],
    "wof:name":"Swags & Tails",
    "wof:placetype":"venue"
},
  "geometry": {"coordinates":[-4.001139164,51.5813140869],"type":"Point"}
}