{
  "type": "Feature",
  "properties": {
    "addr:full":"Oak Road, Bishops Waltham Southampton Hampshire SO32 1EP",
    "addr:postcode":"so32 1ep",
    "addr:street":"Oak Road",
    "iso:country":"GB",
    "sg:address":"Oak Road, Bishops Waltham",
    "sg:city":"Southampton",
    "sg:classifiers":[
        {
            "category":"Education",
            "subcategory":"School",
            "type":"Public Place"
        }
    ],
    "sg:phone":"+44 1489 892368",
    "sg:postcode":"SO32 1EP",
    "sg:province":"Hampshire",
    "sg:tags":[
        "local",
        "authority"
    ],
    "wof:name":"Bishops Waltham Ridgemede County Junior School",
    "wof:placetype":"venue"
},
  "geometry": {"coordinates":[-1.2014299631,50.9554634094],"type":"Point"}
}