{
  "type": "Feature",
  "properties": {
    "iso:country":"GB",
    "sg:address":"64 Clapham Common North Side",
    "sg:city":"London",
    "sg:classifiers":[
        {
            "category":"Conference Center",
            "type":"Public Place"
        }
    ],
    "sg:phone":"+44 20 7978 7050",
    "sg:postcode":"SW4 9SB",
    "sg:province":"Greater London",
    "wof:name":"On Location Conferences",
    "wof:placetype":"venue"
},
  "geometry": {"coordinates":[-0.15245,51.4613],"type":"Point"}
}