{
  "type": "Feature",
  "properties": {
    "iso:country":"GB",
    "sg:address":"147 Albert Road",
    "sg:city":"Middlesbrough",
    "sg:classifiers":[
        {
            "category":"Real Estate",
            "subcategory":"Surveying",
            "type":"Services"
        }
    ],
    "sg:phone":"+44 1642 246246",
    "sg:postcode":"TS1 2PS",
    "sg:province":"North Yorkshire",
    "sg:tags":[
        "surveyor",
        "valuer"
    ],
    "wof:name":"Hudson & Straughan",
    "wof:placetype":"venue"
},
  "geometry": {"coordinates":[-1.235297,54.5737],"type":"Point"}
}