{
  "type": "Feature",
  "properties": {
    "addr:full":"56 Chapel Street Ibstock Leicestershire LE67 6HE",
    "addr:housenumber":"56",
    "addr:postcode":"le67 6he",
    "addr:street":"Chapel Street",
    "iso:country":"GB",
    "sg:address":"56 Chapel Street",
    "sg:city":"Ibstock",
    "sg:classifiers":[
        {
            "category":"Retail",
            "subcategory":"Auto Repair",
            "type":"Services"
        }
    ],
    "sg:phone":"+44 1530 262885",
    "sg:postcode":"LE67 6HE",
    "sg:province":"Leicestershire",
    "sg:tags":[
        "body",
        "car"
    ],
    "wof:name":"Ibstock Car Repairs",
    "wof:placetype":"venue"
},
  "geometry": {"coordinates":[-1.39935,52.691971],"type":"Point"}
}