{
  "type": "Feature",
  "properties": {
    "addr:full":"Westland Sq Leeds West Yorkshire LS11 5SU",
    "addr:postcode":"ls11 5su",
    "addr:street":"Westland Sq",
    "iso:country":"GB",
    "sg:address":"Westland Sq",
    "sg:city":"Leeds",
    "sg:classifiers":[
        {
            "category":"Manufacturing",
            "subcategory":"Metals",
            "type":"Manufacturing & Wholesale Goods"
        }
    ],
    "sg:phone":"+44 113 271 1711",
    "sg:postcode":"LS11 5SU",
    "sg:province":"West Yorkshire",
    "sg:tags":[
        "work",
        "sheet"
    ],
    "wof:name":"Bulman Metal Fabrications Ltd",
    "wof:placetype":"venue"
},
  "geometry": {"coordinates":[-1.548937,53.765064],"type":"Point"}
}