{
  "type": "Feature",
  "properties": {
    "addr:full":"17 Normandale Bexhill-on-sea East Sussex TN39 3LU",
    "addr:housenumber":"17",
    "addr:postcode":"tn39 3lu",
    "addr:street":"Normandale Bexhill-On-Sea",
    "iso:country":"GB",
    "sg:address":"17 Normandale",
    "sg:city":"Bexhill-on-sea",
    "sg:classifiers":[
        {
            "category":"Building & Trades",
            "subcategory":"Construction",
            "type":"Services"
        }
    ],
    "sg:postcode":"TN39 3LU",
    "sg:province":"East Sussex",
    "sg:tags":[
        "builder",
        "repairer",
        "chimney"
    ],
    "wof:name":"Cico Chimney Linings East Sussex",
    "wof:placetype":"venue"
},
  "geometry": {"coordinates":[0.4555639923,50.8403091431],"type":"Point"}
}