{
  "type": "Feature",
  "properties": {
    "addr:full":"46 Hamilton Sq Birkenhead Merseyside L41 5AR",
    "addr:housenumber":"46",
    "addr:postcode":"l41 5ar",
    "addr:street":"Hamilton Sq",
    "iso:country":"GB",
    "sg:address":"46 Hamilton Sq",
    "sg:city":"Birkenhead",
    "sg:classifiers":[
        {
            "category":"Professional",
            "subcategory":"Lawyer & Legal Services",
            "type":"Services"
        }
    ],
    "sg:phone":"+44 151 647 2316",
    "sg:postcode":"L41 5AR",
    "sg:province":"Merseyside",
    "sg:tags":[
        "advice",
        "counselling"
    ],
    "wof:name":"Cruse Bereavement Care",
    "wof:placetype":"venue"
},
  "geometry": {"coordinates":[-3.016208,53.392841],"type":"Point"}
}