{
  "type": "Feature",
  "properties": {
    "addr:full":"63 Kingsland High Street London Greater London E8 2JS",
    "addr:housenumber":"63",
    "addr:postcode":"e8 2js",
    "addr:street":"Kingsland High Street",
    "iso:country":"GB",
    "sg:address":"63 Kingsland High Street",
    "sg:city":"London",
    "sg:classifiers":[
        {
            "category":"Professional",
            "subcategory":"Management & Consulting",
            "type":"Services"
        }
    ],
    "sg:phone":"+44 20 7923 1111",
    "sg:postcode":"E8 2JS",
    "sg:province":"Greater London",
    "sg:tags":[
        "consultant",
        "business"
    ],
    "wof:name":"Tamer & Co.",
    "wof:placetype":"venue"
},
  "geometry": {"coordinates":[-0.075628,51.548294],"type":"Point"}
}