{
  "type": "Feature",
  "properties": {
    "addr:full":"2 Rawson St, Selston Nottingham Derbyshire NG16 6EL",
    "addr:housenumber":"2",
    "addr:postcode":"ng16 6el",
    "addr:street":"Rawson St",
    "iso:country":"GB",
    "sg:address":"2 Rawson St, Selston",
    "sg:city":"Nottingham",
    "sg:classifiers":[
        {
            "category":"Arts & Performance",
            "subcategory":"Music",
            "type":"Entertainment"
        }
    ],
    "sg:phone":"+44 1773 581088",
    "sg:postcode":"NG16 6EL",
    "sg:province":"Derbyshire",
    "sg:tags":[
        "mobile",
        "disco"
    ],
    "wof:name":"Pleasure Sounds Disco & P A Hire",
    "wof:placetype":"venue"
},
  "geometry": {"coordinates":[-1.298938036,53.0709533691],"type":"Point"}
}