{
  "type": "Feature",
  "properties": {
    "addr:full":"11 Green Street Cambridge Cambridgeshire CB2 3JU",
    "addr:housenumber":"11",
    "addr:postcode":"cb2 3ju",
    "addr:street":"Green Street",
    "iso:country":"GB",
    "sg:address":"11 Green Street",
    "sg:city":"Cambridge",
    "sg:classifiers":[
        {
            "category":"Shopping",
            "subcategory":"Bicycles & Sporting Goods",
            "type":"Retail Goods"
        }
    ],
    "sg:postcode":"CB2 3JU",
    "sg:province":"Cambridgeshire",
    "sg:tags":[
        "equipment",
        "camping"
    ],
    "wof:name":"Open Air Cambridge Ltd.",
    "wof:placetype":"venue"
},
  "geometry": {"coordinates":[0.1194590032,52.2069358826],"type":"Point"}
}