{
  "type": "Feature",
  "properties": {
    "iso:country":"GB",
    "sg:address":"Hamilton House, Clinton Avenue",
    "sg:city":"Nottingham",
    "sg:classifiers":[
        {
            "category":"Real Estate",
            "subcategory":"Surveying",
            "type":"Services"
        },
        {
            "category":"Building & Trades",
            "subcategory":"Construction",
            "type":"Services"
        }
    ],
    "sg:phone":"+44 115 962 2511",
    "sg:postcode":"NG5 1AW",
    "sg:province":"Nottinghamshire",
    "sg:tags":[
        "surveyor",
        "management"
    ],
    "wof:name":"C W A Project Management",
    "wof:placetype":"venue"
},
  "geometry": {"coordinates":[-1.154914,52.971748],"type":"Point"}
}