{
  "type": "Feature",
  "properties": {
    "addr:full":"3 Lewis St Pembroke Dock Pembrokeshire SA72 6DD",
    "addr:housenumber":"3",
    "addr:postcode":"sa72 6dd",
    "addr:street":"Lewis St",
    "iso:country":"GB",
    "sg:address":"3 Lewis St",
    "sg:city":"Pembroke Dock",
    "sg:classifiers":[
        {
            "category":"Building & Trades",
            "subcategory":"Cleaning & Sanitation",
            "type":"Services"
        }
    ],
    "sg:phone":"+44 7721 350573",
    "sg:postcode":"SA72 6DD",
    "sg:province":"Pembrokeshire",
    "sg:tags":[
        "dry",
        "control",
        "damp",
        "rot"
    ],
    "wof:name":"Heritage Preservations",
    "wof:placetype":"venue"
},
  "geometry": {"coordinates":[-4.941079,51.693439],"type":"Point"}
}