{
  "type": "Feature",
  "properties": {
    "addr:full":"25 The Martlets Burgess Hill East Sussex RH15 9NN",
    "addr:housenumber":"25",
    "addr:postcode":"rh15 9nn",
    "addr:street":"The Martlets",
    "iso:country":"GB",
    "sg:address":"25 The Martlets",
    "sg:city":"Burgess Hill",
    "sg:classifiers":[
        {
            "category":"Shopping",
            "subcategory":"Baby Store",
            "type":"Retail Goods"
        }
    ],
    "sg:postcode":"RH15 9NN",
    "sg:province":"East Sussex",
    "sg:tags":[
        "nursery",
        "accessory"
    ],
    "wof:name":"Tiny Tribe Ltd",
    "wof:placetype":"venue"
},
  "geometry": {"coordinates":[-0.156618,50.961552],"type":"Point"}
}