{
  "type": "Feature",
  "properties": {
    "addr:full":"Brittania Road Waltham Cross Essex EN8 7NZ",
    "addr:postcode":"en8 7nz",
    "addr:street":"Brittania Road",
    "iso:country":"GB",
    "sg:address":"Brittania Road",
    "sg:city":"Waltham Cross",
    "sg:classifiers":[
        {
            "category":"Autos & Motor Vehicles",
            "subcategory":"Automobile Sales",
            "type":"Retail Goods"
        }
    ],
    "sg:postcode":"EN8 7NZ",
    "sg:province":"Essex",
    "sg:tags":[
        "car"
    ],
    "wof:name":"Douglas Stewart Ltd.",
    "wof:placetype":"venue"
},
  "geometry": {"coordinates":[-0.023654,51.68399],"type":"Point"}
}