{
  "type": "Feature",
  "properties": {
    "addr:full":"Trelan Farm, Trelan Road, Cilcain Mold Denbighshire CH7 5NX",
    "addr:postcode":"ch7 5nx",
    "addr:street":"Trelan Road",
    "iso:country":"GB",
    "sg:address":"Trelan Farm, Trelan Road, Cilcain",
    "sg:city":"Mold",
    "sg:classifiers":[
        {
            "category":"Farming",
            "subcategory":"Livestock Farm",
            "type":"Manufacturing & Wholesale Goods"
        }
    ],
    "sg:postcode":"CH7 5NX",
    "sg:province":"Denbighshire",
    "sg:tags":[
        "others"
    ],
    "wof:name":"J & A J Davies & Son",
    "wof:placetype":"venue"
},
  "geometry": {"coordinates":[-3.231229,53.177673],"type":"Point"}
}