{
  "type": "Feature",
  "properties": {
    "addr:full":"92 Church Street Leatherhead Surrey KT22 8ER",
    "addr:housenumber":"92",
    "addr:postcode":"kt22 8er",
    "addr:street":"Church Street",
    "iso:country":"GB",
    "sg:address":"92 Church Street",
    "sg:city":"Leatherhead",
    "sg:classifiers":[
        {
            "category":"Shopping",
            "subcategory":"Books",
            "type":"Retail Goods"
        }
    ],
    "sg:phone":"+44 1372 378182",
    "sg:postcode":"KT22 8ER",
    "sg:province":"Surrey",
    "wof:name":"Silverdisc Ltd.",
    "wof:placetype":"venue"
},
  "geometry": {"coordinates":[-0.3288600147,51.294052124],"type":"Point"}
}