{
  "type": "Feature",
  "properties": {
    "addr:full":"30 St Albans Road Lytham St Annes Lancashire FY8 1TH",
    "addr:housenumber":"30",
    "addr:postcode":"fy8 1th",
    "addr:street":"St Albans Road",
    "iso:country":"GB",
    "sg:address":"30 St Albans Road",
    "sg:city":"Lytham St Annes",
    "sg:classifiers":[
        {
            "category":"Retail",
            "subcategory":"Repair Shop",
            "type":"Services"
        }
    ],
    "sg:phone":"+44 1253 712436",
    "sg:postcode":"FY8 1TH",
    "sg:province":"Lancashire",
    "sg:tags":[
        "upholsterer"
    ],
    "wof:name":"Talbot Upholstery",
    "wof:placetype":"venue"
},
  "geometry": {"coordinates":[-3.0250930786,53.7531356812],"type":"Point"}
}