{
  "type": "Feature",
  "properties": {
    "addr:full":"Edgeley Park, Hardcastle Road Stockport Cheshire SK3 9DD",
    "addr:postcode":"sk3 9dd",
    "addr:street":"Hardcastle Road",
    "iso:country":"GB",
    "sg:address":"Edgeley Park, Hardcastle Road",
    "sg:city":"Stockport",
    "sg:classifiers":[
        {
            "category":"Arena",
            "subcategory":"Sports Club",
            "type":"Entertainment"
        }
    ],
    "sg:postcode":"SK3 9DD",
    "sg:province":"Cheshire",
    "wof:name":"Stockport County Association Football Club Ltd.",
    "wof:placetype":"venue"
},
  "geometry": {"coordinates":[-2.1714189053,53.400894165],"type":"Point"}
}