{
  "type": "Feature",
  "properties": {
    "iso:country":"GB",
    "sg:address":"10 Court Avenue, Stoke Gifford",
    "sg:city":"Bristol",
    "sg:classifiers":[
        {
            "category":"Manufacturing",
            "subcategory":"Buildings",
            "type":"Manufacturing & Wholesale Goods"
        }
    ],
    "sg:phone":"+44 1454 774456",
    "sg:postcode":"BS34 8PJ",
    "sg:province":"Gloucestershire",
    "sg:tags":[
        "mobile",
        "home"
    ],
    "wof:name":"Mobile Homes Services (Bristol)",
    "wof:placetype":"venue"
},
  "geometry": {"coordinates":[-2.540253,51.520035],"type":"Point"}
}