{
  "type": "Feature",
  "properties": {
    "addr:full":"11 Wordsworth Clo Basingstoke Hampshire RG24 9DE",
    "addr:housenumber":"11",
    "addr:postcode":"rg24 9de",
    "addr:street":"Wordsworth Clo",
    "iso:country":"GB",
    "sg:address":"11 Wordsworth Clo",
    "sg:city":"Basingstoke",
    "sg:classifiers":[
        {
            "category":"Utilities",
            "type":"Services"
        }
    ],
    "sg:phone":"+44 1256 333941",
    "sg:postcode":"RG24 9DE",
    "sg:province":"Hampshire",
    "sg:tags":[
        "connection",
        "provider",
        "internet"
    ],
    "wof:name":"Castle.Net Ltd (ISP)",
    "wof:placetype":"venue"
},
  "geometry": {"coordinates":[-1.080701,51.279797],"type":"Point"}
}