{
  "type": "Feature",
  "properties": {
    "addr:full":"131 Welbourne, Werrington Peterborough Cambridgeshire PE4 6NR",
    "addr:housenumber":"131",
    "addr:postcode":"pe4 6nr",
    "addr:street":"Welbourne",
    "iso:country":"GB",
    "sg:address":"131 Welbourne, Werrington",
    "sg:city":"Peterborough",
    "sg:classifiers":[
        {
            "category":"Building & Trades",
            "subcategory":"Landscaping Services",
            "type":"Services"
        }
    ],
    "sg:postcode":"PE4 6NR",
    "sg:province":"Cambridgeshire",
    "sg:tags":[
        "landscape",
        "contractor"
    ],
    "wof:name":"Absolute Arboriculture Ltd.",
    "wof:placetype":"venue"
},
  "geometry": {"coordinates":[-0.2741490006,52.6085510254],"type":"Point"}
}