{
  "type": "Feature",
  "properties": {
    "addr:full":"94 Albert Road Romford Essex RM1 2PP",
    "addr:housenumber":"94",
    "addr:postcode":"rm1 2pp",
    "addr:street":"Albert Road",
    "iso:country":"GB",
    "sg:address":"94 Albert Road",
    "sg:city":"Romford",
    "sg:classifiers":[
        {
            "category":"Retail",
            "subcategory":"Repair Shop",
            "type":"Services"
        }
    ],
    "sg:phone":"+44 1708 744587",
    "sg:postcode":"RM1 2PP",
    "sg:province":"Essex",
    "sg:tags":[
        "upholsterer"
    ],
    "wof:name":"Collard's Upholstery Co. Ltd.",
    "wof:placetype":"venue"
},
  "geometry": {"coordinates":[0.190444,51.573059],"type":"Point"}
}