{
  "type": "Feature",
  "properties": {
    "addr:full":"3a Hanbury Road Bargoed Caerphilly CF81 8QR",
    "addr:housenumber":"3a",
    "addr:postcode":"cf81 8qr",
    "addr:street":"Hanbury Road",
    "iso:country":"GB",
    "sg:address":"3a Hanbury Road",
    "sg:city":"Bargoed",
    "sg:classifiers":[
        {
            "category":"Fast Food",
            "type":"Food & Drink"
        }
    ],
    "sg:phone":"+44 1443 835473",
    "sg:postcode":"CF81 8QR",
    "sg:province":"Caerphilly",
    "sg:tags":[
        "away",
        "take"
    ],
    "wof:name":"Indian Empire Cuisine",
    "wof:placetype":"venue"
},
  "geometry": {"coordinates":[-3.2287349701,51.6902389526],"type":"Point"}
}