{
  "type": "Feature",
  "properties": {
    "addr:full":"430 Evesham Road Redditch Warwickshire B97 5JB",
    "addr:housenumber":"430",
    "addr:postcode":"b97 5jb",
    "addr:street":"Evesham Road",
    "iso:country":"GB",
    "sg:address":"430 Evesham Road",
    "sg:city":"Redditch",
    "sg:classifiers":[
        {
            "category":"Food & Beverages",
            "subcategory":"Groceries & Convenience Stores",
            "type":"Retail Goods"
        }
    ],
    "sg:phone":"+44 1527 401253",
    "sg:postcode":"B97 5JB",
    "sg:province":"Warwickshire",
    "wof:name":"Alldays Stores Ltd.",
    "wof:placetype":"venue"
},
  "geometry": {"coordinates":[-1.942425,52.282181],"type":"Point"}
}