{
  "type": "Feature",
  "properties": {
    "iso:country":"GB",
    "sg:address":"7 North Street",
    "sg:city":"Wisbech",
    "sg:classifiers":[
        {
            "category":"Fast Food",
            "type":"Food & Drink"
        }
    ],
    "sg:phone":"+44 1945 584648",
    "sg:postcode":"PE13 1NP",
    "sg:province":"Cambridgeshire",
    "sg:tags":[
        "away",
        "take"
    ],
    "wof:name":"Ho-Ho Chinese Take Away",
    "wof:placetype":"venue"
},
  "geometry": {"coordinates":[0.158552,52.666519],"type":"Point"}
}