{
  "type": "Feature",
  "properties": {
    "addr:full":"Olivohairhill Road, Grangewood Estate Chesterfield Derbyshire S40 2JA",
    "addr:postcode":"s40 2ja",
    "addr:street":"Olivohairhill Road Grangewood Estate",
    "iso:country":"GB",
    "sg:address":"Olivohairhill Road, Grangewood Estate",
    "sg:city":"Chesterfield",
    "sg:classifiers":[
        {
            "category":"Building & Trades",
            "subcategory":"Landscaping Services",
            "type":"Services"
        }
    ],
    "sg:phone":"+44 1246 235211",
    "sg:postcode":"S40 2JA",
    "sg:province":"Derbyshire",
    "sg:tags":[
        "forestry",
        "tree"
    ],
    "wof:name":"John Goodman Landscape Gardener",
    "wof:placetype":"venue"
},
  "geometry": {"coordinates":[-1.4346599579,53.217830658],"type":"Point"}
}