{
  "type": "Feature",
  "properties": {
    "iso:country":"GB",
    "sg:address":"56 Long Street",
    "sg:city":"Tetbury",
    "sg:classifiers":[
        {
            "category":"Shopping",
            "subcategory":"Crafts & Fabrics",
            "type":"Retail Goods"
        }
    ],
    "sg:phone":"+44 1666 502706",
    "sg:postcode":"GL8 8AQ",
    "sg:province":"Gloucestershire",
    "sg:tags":[
        "shop",
        "needlecraft",
        "wool",
        "retailer"
    ],
    "wof:name":"Skeins",
    "wof:placetype":"venue"
},
  "geometry": {"coordinates":[-2.161907,51.638634],"type":"Point"}
}