{
  "type": "Feature",
  "properties": {
    "addr:full":"17 Newgate Row, Grosvenor Precinct Chester Cheshire CH1 1ER",
    "addr:housenumber":"17",
    "addr:postcode":"ch1 1er",
    "addr:street":"Newgate Row",
    "iso:country":"GB",
    "sg:address":"17 Newgate Row, Grosvenor Precinct",
    "sg:city":"Chester",
    "sg:classifiers":[
        {
            "category":"Shopping",
            "subcategory":"Clothing, Apparel, & Fashions",
            "type":"Retail Goods"
        }
    ],
    "sg:phone":"+44 1244 343818",
    "sg:postcode":"CH1 1ER",
    "sg:province":"Cheshire",
    "sg:tags":[
        "accessory"
    ],
    "sg:website":"http://www.claires.co.uk",
    "wof:name":"Claire's Accessories UK Ltd",
    "wof:placetype":"venue"
},
  "geometry": {"coordinates":[-2.8885829449,53.1894264221],"type":"Point"}
}