{
  "type": "Feature",
  "properties": {
    "iso:country":"GB",
    "sg:address":"159 Coppins Road",
    "sg:city":"Clacton-on-sea",
    "sg:classifiers":[
        {
            "category":"Building & Trades",
            "subcategory":"Construction",
            "type":"Services"
        }
    ],
    "sg:phone":"+44 1255 476370",
    "sg:postcode":"CO15 3LF",
    "sg:province":"Essex",
    "sg:tags":[
        "glazier",
        "decorator",
        "painter"
    ],
    "wof:name":"Blackwell's Painters & Decorators",
    "wof:placetype":"venue"
},
  "geometry": {"coordinates":[1.137826,51.79678],"type":"Point"}
}