{
  "type": "Feature",
  "properties": {
    "iso:country":"GB",
    "sg:address":"37 Widnes Rd",
    "sg:city":"Widnes",
    "sg:classifiers":[
        {
            "category":"Food & Beverages",
            "subcategory":"Meat & Fish",
            "type":"Retail Goods"
        }
    ],
    "sg:phone":"+44 151 495 1303",
    "sg:postcode":"WA8 6AZ",
    "sg:province":"Cheshire",
    "sg:tags":[
        "butcher"
    ],
    "wof:name":"D F Benyon",
    "wof:placetype":"venue"
},
  "geometry": {"coordinates":[-2.728730917,53.36668396],"type":"Point"}
}