{
  "type": "Feature",
  "properties": {
    "addr:full":"99b Cavendish Place Eastbourne East Sussex BN21 3TY",
    "addr:housenumber":"99b",
    "addr:postcode":"bn21 3ty",
    "addr:street":"Cavendish Place",
    "iso:country":"GB",
    "sg:address":"99b Cavendish Place",
    "sg:city":"Eastbourne",
    "sg:classifiers":[
        {
            "category":"Utilities",
            "type":"Services"
        }
    ],
    "sg:phone":"+44 1323 507030",
    "sg:postcode":"BN21 3TY",
    "sg:province":"East Sussex",
    "sg:tags":[
        "internet"
    ],
    "wof:name":"Tarran Developments Ltd.",
    "wof:placetype":"venue"
},
  "geometry": {"coordinates":[0.288221,50.771851],"type":"Point"}
}