{
  "type": "Feature",
  "properties": {
    "addr:full":"7 Hawley Road Falkirk Falkirk FK1 1SH",
    "addr:housenumber":"7",
    "addr:postcode":"fk1 1sh",
    "addr:street":"Hawley Road",
    "iso:country":"GB",
    "sg:address":"7 Hawley Road",
    "sg:city":"Falkirk",
    "sg:classifiers":[
        {
            "category":"Professional",
            "subcategory":"Art Services",
            "type":"Services"
        },
        {
            "category":"Building & Trades",
            "subcategory":"Construction",
            "type":"Services"
        }
    ],
    "sg:phone":"+44 1324 620050",
    "sg:postcode":"FK1 1SH",
    "sg:province":"Falkirk",
    "sg:tags":[
        "decorator",
        "painter"
    ],
    "wof:name":"John Savoy",
    "wof:placetype":"venue"
},
  "geometry": {"coordinates":[-3.770544,56.000294],"type":"Point"}
}