{
  "type": "Feature",
  "properties": {
    "addr:full":"28 Highburgh Rd Glasgow Glasgow City G12 9DZ",
    "addr:housenumber":"28",
    "addr:postcode":"g12 9dz",
    "addr:street":"Highburgh Rd",
    "iso:country":"GB",
    "sg:address":"28 Highburgh Rd",
    "sg:city":"Glasgow",
    "sg:classifiers":[
        {
            "category":"Professional",
            "subcategory":"Management & Consulting",
            "type":"Services"
        }
    ],
    "sg:postcode":"G12 9DZ",
    "sg:province":"Glasgow City",
    "sg:tags":[
        "consultant",
        "business"
    ],
    "wof:name":"Scott Associates",
    "wof:placetype":"venue"
},
  "geometry": {"coordinates":[-4.2978210449,55.8744926453],"type":"Point"}
}