{
  "type": "Feature",
  "properties": {
    "iso:country":"GB",
    "sg:address":"Manor House, 48 Sutton Road, Terrington St Clements",
    "sg:city":"King's Lynn",
    "sg:classifiers":[
        {
            "category":"Home & Garden",
            "subcategory":"Building Materials",
            "type":"Retail Goods"
        },
        {
            "category":"Building & Trades",
            "subcategory":"Construction",
            "type":"Services"
        }
    ],
    "sg:phone":"+44 1553 828429",
    "sg:postcode":"PE34 4PQ",
    "sg:province":"Lincolnshire",
    "sg:tags":[
        "insulation",
        "installers",
        "ceiling",
        "contractor"
    ],
    "wof:name":"Calcutt Ceilings & Partitions",
    "wof:placetype":"venue"
},
  "geometry": {"coordinates":[0.2931199968,52.75548172],"type":"Point"}
}