{
  "type": "Feature",
  "properties": {
    "addr:full":"Watercress Cottage, Farleigh Hungerford Bath Somerset BA2 7RS",
    "addr:housenumber":"farleigh",
    "addr:postcode":"bath;ba2 7rs",
    "addr:street":"Hungerford",
    "iso:country":"GB",
    "sg:address":"Watercress Cottage, Farleigh Hungerford",
    "sg:city":"Bath",
    "sg:classifiers":[
        {
            "category":"Farming",
            "subcategory":"Farm",
            "type":"Manufacturing & Wholesale Goods"
        }
    ],
    "sg:postcode":"BA2 7RS",
    "sg:province":"Somerset",
    "sg:tags":[
        "hatchery"
    ],
    "wof:name":"Farleigh Natural Springs Trout Farm",
    "wof:placetype":"venue"
},
  "geometry": {"coordinates":[-2.2838900089,51.3173866272],"type":"Point"}
}