{
  "type": "Feature",
  "properties": {
    "addr:full":"95 Morrison St Glasgow Glasgow City G5 8LP",
    "addr:housenumber":"95",
    "addr:postcode":"g5 8lp",
    "addr:street":"Morrison St",
    "iso:country":"GB",
    "sg:address":"95 Morrison St",
    "sg:city":"Glasgow",
    "sg:classifiers":[
        {
            "category":"Organizations",
            "subcategory":"Non-profit Organization",
            "type":"Services"
        }
    ],
    "sg:postcode":"G5 8LP",
    "sg:province":"Glasgow City",
    "sg:tags":[
        "organisation",
        "voluntary",
        "charity"
    ],
    "wof:name":"Woodcraft Folk",
    "wof:placetype":"venue"
},
  "geometry": {"coordinates":[-4.265121,55.853317],"type":"Point"}
}