{
  "type": "Feature",
  "properties": {
    "addr:full":"Lightbowne Road Manchester Greater Manchester M40 5EF",
    "addr:postcode":"m40 5ef",
    "addr:street":"Lightbowne Road",
    "iso:country":"GB",
    "sg:address":"Lightbowne Road",
    "sg:city":"Manchester",
    "sg:classifiers":[
        {
            "category":"Autos & Motor Vehicles",
            "subcategory":"Fuel & Gas Station",
            "type":"Retail Goods"
        }
    ],
    "sg:postcode":"M40 5EF",
    "sg:province":"Greater Manchester",
    "sg:tags":[
        "petrol",
        "filling"
    ],
    "wof:name":"Elf Service Station",
    "wof:placetype":"venue"
},
  "geometry": {"coordinates":[-2.1912128925,53.5096054077],"type":"Point"}
}