{
  "type": "Feature",
  "properties": {
    "iso:country":"GB",
    "sg:address":"Old Parsonage, Huntsham",
    "sg:city":"Tiverton",
    "sg:classifiers":[
        {
            "category":"Professional",
            "subcategory":"Employment Agencies",
            "type":"Services"
        }
    ],
    "sg:phone":"+44 1398 361478",
    "sg:postcode":"EX16 7NQ",
    "sg:province":"Devon",
    "sg:tags":[
        "consultant"
    ],
    "wof:name":"Locator Computer Support Ltd.",
    "wof:placetype":"venue"
},
  "geometry": {"coordinates":[-3.418984,50.9748],"type":"Point"}
}