{
  "type": "Feature",
  "properties": {
    "iso:country":"GB",
    "sg:address":"20 Victoria Terrace",
    "sg:city":"Hove",
    "sg:classifiers":[
        {
            "category":"Food & Beverages",
            "subcategory":"Liquor & Beverages",
            "type":"Retail Goods"
        }
    ],
    "sg:phone":"+44 1273 325331",
    "sg:postcode":"BN3 2WB",
    "sg:province":"East Sussex",
    "sg:tags":[
        "beer",
        "spirit",
        "wines"
    ],
    "wof:name":"Unwins Wine Merchants",
    "wof:placetype":"venue"
},
  "geometry": {"coordinates":[-0.175514,50.825069],"type":"Point"}
}