{
  "type": "Feature",
  "properties": {
    "addr:full":"30 Kylemilne Way Stourport-on-severn Worcestershire DY13 9NA",
    "addr:housenumber":"30",
    "addr:postcode":"dy13 9na",
    "addr:street":"Kylemilne Way",
    "iso:country":"GB",
    "sg:address":"30 Kylemilne Way",
    "sg:city":"Stourport-on-severn",
    "sg:classifiers":[
        {
            "category":"Shopping",
            "subcategory":"Department Store",
            "type":"Retail Goods"
        }
    ],
    "sg:phone":"+44 1299 822230",
    "sg:postcode":"DY13 9NA",
    "sg:province":"Worcestershire",
    "wof:name":"Kylemilne Stores",
    "wof:placetype":"venue"
},
  "geometry": {"coordinates":[-2.262635,52.339535],"type":"Point"}
}