{
  "type": "Feature",
  "properties": {
    "iso:country":"GB",
    "sg:address":"40 The Moors",
    "sg:city":"Kidlington",
    "sg:classifiers":[
        {
            "category":"Social Services",
            "subcategory":"Child Care",
            "type":"Services"
        }
    ],
    "sg:phone":"+44 1865 373153",
    "sg:postcode":"OX5 2AL",
    "sg:province":"Buckinghamshire",
    "sg:tags":[
        "children's",
        "home"
    ],
    "wof:name":"Thornbury House",
    "wof:placetype":"venue"
},
  "geometry": {"coordinates":[-1.2985999584,51.8301925659],"type":"Point"}
}