{
  "type": "Feature",
  "properties": {
    "addr:full":"Mountsorrel Quarry, Wood Lane, Quorn Leicester Leicestershire LE12 8GE",
    "addr:postcode":"le12 8ge",
    "addr:street":"Mountsorrel Quarry Wood Lane",
    "iso:country":"GB",
    "sg:address":"Mountsorrel Quarry, Wood Lane, Quorn",
    "sg:city":"Leicester",
    "sg:classifiers":[
        {
            "category":"Home & Garden",
            "subcategory":"Garden Supply",
            "type":"Retail Goods"
        }
    ],
    "sg:phone":"+44 116 230 3881",
    "sg:postcode":"LE12 8GE",
    "sg:province":"Leicestershire",
    "sg:tags":[
        "sand",
        "gravel"
    ],
    "wof:name":"The Quarry",
    "wof:placetype":"venue"
},
  "geometry": {"coordinates":[-1.1762789488,52.750202179],"type":"Point"}
}