{
  "type": "Feature",
  "properties": {
    "addr:full":"28a Highbury Park London Greater London N5 2AA",
    "addr:housenumber":"28a",
    "addr:postcode":"n5 2aa",
    "addr:street":"Highbury Park",
    "iso:country":"GB",
    "sg:address":"28a Highbury Park",
    "sg:city":"London",
    "sg:classifiers":[
        {
            "category":"Fast Food",
            "type":"Food & Drink"
        }
    ],
    "sg:phone":"+44 20 7359 5374",
    "sg:postcode":"N5 2AA",
    "sg:province":"Greater London",
    "sg:tags":[
        "away",
        "meal",
        "outlet",
        "take"
    ],
    "wof:name":"The Barn Fish Bar",
    "wof:placetype":"venue"
},
  "geometry": {"coordinates":[-0.097981,51.553947],"type":"Point"}
}