{
  "type": "Feature",
  "properties": {
    "iso:country":"GB",
    "sg:address":"Elliot Junction Caravan Site, Elliot",
    "sg:city":"Arbroath",
    "sg:classifiers":[
        {
            "category":"Recreation",
            "subcategory":"Campground",
            "type":"Entertainment"
        }
    ],
    "sg:phone":"+44 1241 873466",
    "sg:postcode":"DD11 2PH",
    "sg:province":"Angus",
    "sg:tags":[
        "caravan",
        "park"
    ],
    "wof:name":"Elliot Caravan Site",
    "wof:placetype":"venue"
},
  "geometry": {"coordinates":[-2.6152610779,56.5476570129],"type":"Point"}
}