{
  "type": "Feature",
  "properties": {
    "addr:full":"Girvan Health Centre, 109a Henrietta St Girvan South Ayrshire KA26 9AN",
    "addr:housenumber":"109a",
    "addr:postcode":"ka26 9an",
    "addr:street":"Henrietta St",
    "iso:country":"GB",
    "sg:address":"Girvan Health Centre, 109a Henrietta St",
    "sg:city":"Girvan",
    "sg:classifiers":[
        {
            "category":"Health Services",
            "subcategory":"Doctor",
            "type":"Services"
        }
    ],
    "sg:phone":"+44 1465 713343",
    "sg:postcode":"KA26 9AN",
    "sg:province":"South Ayrshire",
    "sg:tags":[
        "practitioners"
    ],
    "wof:name":"Moore, C D",
    "wof:placetype":"venue"
},
  "geometry": {"coordinates":[-4.7827692032,55.2605895996],"type":"Point"}
}