{
  "type": "Feature",
  "properties": {
    "addr:full":"International Press Centre, A Floor, 76 Shoe Lane London Greater London EC4A 3JB",
    "addr:housenumber":"76",
    "addr:postcode":"ec4a 3jb",
    "addr:street":"Shoe Lane",
    "iso:country":"GB",
    "sg:address":"International Press Centre, A Floor, 76 Shoe Lane",
    "sg:city":"London",
    "sg:classifiers":[
        {
            "category":"Manufacturing",
            "subcategory":"Metals",
            "type":"Manufacturing & Wholesale Goods"
        }
    ],
    "sg:phone":"+44 20 7583 1133",
    "sg:postcode":"EC4A 3JB",
    "sg:province":"Greater London",
    "sg:tags":[
        "steel",
        "mnfrs"
    ],
    "wof:name":"Kawasaki Steel Corporation",
    "wof:placetype":"venue"
},
  "geometry": {"coordinates":[-0.10666,51.515831],"type":"Point"}
}