{
  "type": "Feature",
  "properties": {
    "iso:country":"GB",
    "sg:address":"16 Halifax Lane, Luddenden",
    "sg:city":"Halifax",
    "sg:classifiers":[
        {
            "category":"Professional",
            "subcategory":"Art Services",
            "type":"Services"
        }
    ],
    "sg:postcode":"HX2 6PN",
    "sg:province":"West Yorkshire",
    "sg:tags":[
        "photographer"
    ],
    "wof:name":"Peter Hollings Photography",
    "wof:placetype":"venue"
},
  "geometry": {"coordinates":[-1.936402,53.730564],"type":"Point"}
}