{
  "type": "Feature",
  "properties": {
    "addr:full":"1st Floor, Bedford House London Greater London WC2E 9HD",
    "addr:postcode":"wc2e 9hd",
    "iso:country":"GB",
    "sg:address":"1st Floor, Bedford House",
    "sg:city":"London",
    "sg:classifiers":[
        {
            "category":"Communications",
            "type":"Services"
        }
    ],
    "sg:phone":"+44 29 2040 5600",
    "sg:postcode":"WC2E 9HD",
    "sg:province":"Greater London",
    "sg:tags":[
        "broadcasting"
    ],
    "wof:name":"S D N Ltd.",
    "wof:placetype":"venue"
},
  "geometry": {"coordinates":[-0.12334,51.509701],"type":"Point"}
}