{
  "type": "Feature",
  "properties": {
    "addr:full":"59-63 Station Road Northwich Cheshire CW9 5LT",
    "addr:housenumber":"59-63",
    "addr:postcode":"cw9 5lt",
    "addr:street":"Station Road",
    "iso:country":"GB",
    "sg:address":"59-63 Station Road",
    "sg:city":"Northwich",
    "sg:classifiers":[
        {
            "category":"Professional",
            "subcategory":"Accounting & Tax Preparation",
            "type":"Services"
        }
    ],
    "sg:postcode":"CW9 5LT",
    "sg:province":"Cheshire",
    "sg:tags":[
        "accountant"
    ],
    "wof:name":"Kay Chartered Accountants",
    "wof:placetype":"venue"
},
  "geometry": {"coordinates":[-2.499761,53.2621],"type":"Point"}
}