{
  "type": "Feature",
  "properties": {
    "addr:full":"19 Manor Road, Catcott Bridgwater Somerset TA7 9HT",
    "addr:housenumber":"19",
    "addr:postcode":"ta7 9ht",
    "addr:street":"Manor Road",
    "iso:country":"GB",
    "sg:address":"19 Manor Road, Catcott",
    "sg:city":"Bridgwater",
    "sg:classifiers":[
        {
            "category":"Social Services",
            "subcategory":"Retirement Home",
            "type":"Services"
        }
    ],
    "sg:phone":"+44 1278 722405",
    "sg:postcode":"TA7 9HT",
    "sg:province":"Somerset",
    "sg:tags":[
        "rest"
    ],
    "wof:name":"Wellfield House",
    "wof:placetype":"venue"
},
  "geometry": {"coordinates":[-2.8659079075,51.1498756409],"type":"Point"}
}