{
  "type": "Feature",
  "properties": {
    "iso:country":"GB",
    "sg:address":"Grange Business Centre, Belasis Avenue",
    "sg:city":"Billingham",
    "sg:classifiers":[
        {
            "category":"Professional",
            "subcategory":"Engineering",
            "type":"Services"
        }
    ],
    "sg:phone":"+44 1642 360490",
    "sg:postcode":"TS23 1LG",
    "sg:province":"Durham",
    "sg:tags":[
        "design",
        "engineer"
    ],
    "wof:name":"John Boyd Associates Ltd.",
    "wof:placetype":"venue"
},
  "geometry": {"coordinates":[-1.293645,54.606857],"type":"Point"}
}