{
  "type": "Feature",
  "properties": {
    "addr:full":"879 London Rd Westcliff On Sea Essex SS0 9SZ",
    "addr:housenumber":"879",
    "addr:postcode":"ss0 9sz",
    "addr:street":"London Rd",
    "iso:country":"GB",
    "sg:address":"879 London Rd",
    "sg:city":"Westcliff On Sea",
    "sg:classifiers":[
        {
            "category":"Food & Beverages",
            "subcategory":"Meat & Fish",
            "type":"Retail Goods"
        }
    ],
    "sg:phone":"+44 1702 482082",
    "sg:postcode":"SS0 9SZ",
    "sg:province":"Essex",
    "sg:tags":[
        "merchant"
    ],
    "wof:name":"Sunshine Seafoods Ltd",
    "wof:placetype":"venue"
},
  "geometry": {"coordinates":[0.6729789972,51.5459365845],"type":"Point"}
}