{
  "type": "Feature",
  "properties": {
    "addr:full":"Third Floor Building 8 Exchange Quay Salford Greater Manchester M5 3EJ",
    "addr:housenumber":"third",
    "addr:postcode":"m5 3ej",
    "addr:street":"Exchange Quay",
    "iso:country":"GB",
    "sg:address":"Third Floor Building 8 Exchange Quay",
    "sg:city":"Salford",
    "sg:classifiers":[
        {
            "category":"Manufacturing",
            "subcategory":"Tools & Machinery",
            "type":"Manufacturing & Wholesale Goods"
        }
    ],
    "sg:phone":"+44 161 876 6565",
    "sg:postcode":"M5 3EJ",
    "sg:province":"Greater Manchester",
    "sg:tags":[
        "society",
        "friendly"
    ],
    "wof:name":"NCM Credit Insurance",
    "wof:placetype":"venue"
},
  "geometry": {"coordinates":[-2.2824289799,53.4662284851],"type":"Point"}
}