{
  "type": "Feature",
  "properties": {
    "iso:country":"GB",
    "sg:address":"73 Rowlands Rd",
    "sg:city":"Worthing",
    "sg:classifiers":[
        {
            "category":"Professional",
            "subcategory":"Printing & Photocopies",
            "type":"Services"
        }
    ],
    "sg:phone":"+44 1903 238401",
    "sg:postcode":"BN11 3JN",
    "sg:province":"West Sussex",
    "sg:tags":[
        "engraving"
    ],
    "wof:name":"Worthing Engraving",
    "wof:placetype":"venue"
},
  "geometry": {"coordinates":[-0.381822,50.809826],"type":"Point"}
}