{
  "type": "Feature",
  "properties": {
    "iso:country":"GB",
    "sg:address":"21a Wilson Patten St",
    "sg:city":"Warrington",
    "sg:classifiers":[
        {
            "category":"Professional",
            "subcategory":"Lawyer & Legal Services",
            "type":"Services"
        }
    ],
    "sg:phone":"+44 1925 630124",
    "sg:postcode":"WA1 1PG",
    "sg:province":"Cheshire",
    "sg:tags":[
        "advice",
        "counselling"
    ],
    "wof:name":"Relate",
    "wof:placetype":"venue"
},
  "geometry": {"coordinates":[-2.596983,53.386192],"type":"Point"}
}