{
  "type": "Feature",
  "properties": {
    "iso:country":"GB",
    "sg:address":"13 Underwood Crescent, Sapcote",
    "sg:city":"Leicester",
    "sg:classifiers":[
        {
            "category":"Professional",
            "type":"Services"
        }
    ],
    "sg:phone":"+44 1455 273482",
    "sg:postcode":"LE9 4FY",
    "sg:province":"Leicestershire",
    "sg:tags":[
        "interior",
        "furnishers",
        "designer"
    ],
    "wof:name":"Stephanie Lee Interiors",
    "wof:placetype":"venue"
},
  "geometry": {"coordinates":[-1.2775349617,52.5392723083],"type":"Point"}
}