{
  "type": "Feature",
  "properties": {
    "addr:full":"Spa Rd Llandrindod Wells Powys LD1 5ER",
    "addr:postcode":"ld1 5er",
    "addr:street":"Spa Rd",
    "iso:country":"GB",
    "sg:address":"Spa Rd",
    "sg:city":"Llandrindod Wells",
    "sg:classifiers":[
        {
            "category":"Travel",
            "subcategory":"Hotels & Motels",
            "type":"Entertainment"
        }
    ],
    "sg:phone":"+44 1597 822288",
    "sg:postcode":"LD1 5ER",
    "sg:province":"Powys",
    "wof:name":"Hotel Commodore",
    "wof:placetype":"venue"
},
  "geometry": {"coordinates":[-3.379347,52.239799],"type":"Point"}
}