{
  "type": "Feature",
  "properties": {
    "addr:full":"79 Northgate Hartlepool Durham TS24 0JX",
    "addr:housenumber":"79",
    "addr:postcode":"ts24 0jx",
    "addr:street":"Northgate",
    "iso:country":"GB",
    "sg:address":"79 Northgate",
    "sg:city":"Hartlepool",
    "sg:classifiers":[
        {
            "category":"Cinema",
            "subcategory":"Movie Rental",
            "type":"Entertainment"
        }
    ],
    "sg:phone":"+44 1429 266868",
    "sg:postcode":"TS24 0JX",
    "sg:province":"Durham",
    "sg:tags":[
        "video",
        "library"
    ],
    "wof:name":"Rewind Video Film Hire",
    "wof:placetype":"venue"
},
  "geometry": {"coordinates":[-1.184312,54.697762],"type":"Point"}
}