{
  "type": "Feature",
  "properties": {
    "addr:full":"2 Lewis Street Aberdare Neath Port Talbot CF44 6PY",
    "addr:housenumber":"2",
    "addr:postcode":"cf44 6py",
    "addr:street":"Lewis Street",
    "iso:country":"GB",
    "sg:address":"2 Lewis Street",
    "sg:city":"Aberdare",
    "sg:classifiers":[
        {
            "category":"Autos & Motor Vehicles",
            "subcategory":"Auto Supplies",
            "type":"Retail Goods"
        },
        {
            "category":"Shopping",
            "type":"Retail Goods"
        }
    ],
    "sg:phone":"+44 1685 872053",
    "sg:postcode":"CF44 6PY",
    "sg:province":"Neath Port Talbot",
    "sg:tags":[
        "car",
        "part",
        "accessory"
    ],
    "wof:name":"Lewis Street Motor Spares",
    "wof:placetype":"venue"
},
  "geometry": {"coordinates":[-3.4296629429,51.7030677795],"type":"Point"}
}