{
  "type": "Feature",
  "properties": {
    "addr:full":"The Clock House, Market St Tenbury Wells Herefordshire WR15 8BQ",
    "addr:postcode":"wr15 8bq",
    "addr:street":"Market St",
    "iso:country":"GB",
    "sg:address":"The Clock House, Market St",
    "sg:city":"Tenbury Wells",
    "sg:classifiers":[
        {
            "category":"Manufacturing",
            "subcategory":"Rubber & Plastics",
            "type":"Manufacturing & Wholesale Goods"
        }
    ],
    "sg:phone":"+44 1584 819988",
    "sg:postcode":"WR15 8BQ",
    "sg:province":"Herefordshire",
    "sg:tags":[
        "tool"
    ],
    "wof:name":"Luen Tai Ltd",
    "wof:placetype":"venue"
},
  "geometry": {"coordinates":[-2.594417,52.310844],"type":"Point"}
}