{
  "type": "Feature",
  "properties": {
    "addr:full":"The Hillocks, Meikle Wartle Inverurie Aberdeenshire AB51 5BL",
    "addr:postcode":"ab51 5bl",
    "addr:street":"Meikle Wartle Inverurie",
    "iso:country":"GB",
    "sg:address":"The Hillocks, Meikle Wartle",
    "sg:city":"Inverurie",
    "sg:classifiers":[
        {
            "category":"Manufacturing",
            "subcategory":"Metals",
            "type":"Manufacturing & Wholesale Goods"
        },
        {
            "category":"Building & Trades",
            "subcategory":"Construction",
            "type":"Services"
        }
    ],
    "sg:phone":"+44 1651 821265",
    "sg:postcode":"AB51 5BL",
    "sg:province":"Aberdeenshire",
    "sg:tags":[
        "fabricator",
        "builder"
    ],
    "wof:name":"James Moir & Sons Ltd",
    "wof:placetype":"venue"
},
  "geometry": {"coordinates":[-2.464914,57.367748],"type":"Point"}
}