{
  "type": "Feature",
  "properties": {
    "iso:country":"GB",
    "sg:address":"53 Broad Street",
    "sg:city":"Chesham",
    "sg:classifiers":[
        {
            "category":"Building & Trades",
            "subcategory":"Construction",
            "type":"Services"
        }
    ],
    "sg:phone":"+44 1494 774659",
    "sg:postcode":"HP5 3EA",
    "sg:province":"Buckinghamshire",
    "sg:tags":[
        "builder"
    ],
    "wof:name":"Lorderwood Ltd.",
    "wof:placetype":"venue"
},
  "geometry": {"coordinates":[-0.610091,51.709103],"type":"Point"}
}