{
  "type": "Feature",
  "properties": {
    "addr:full":"Viewsonic House, Jenner Road Crawley Surrey RH10 9GA",
    "addr:postcode":"rh10 9ga",
    "addr:street":"Jenner Road",
    "iso:country":"GB",
    "sg:address":"Viewsonic House, Jenner Road",
    "sg:city":"Crawley",
    "sg:classifiers":[
        {
            "category":"Shopping",
            "subcategory":"Computers & Home Electronics",
            "type":"Retail Goods"
        }
    ],
    "sg:phone":"+44 1293 643900",
    "sg:postcode":"RH10 9GA",
    "sg:province":"Surrey",
    "wof:name":"Viewsonic Europe Ltd.",
    "wof:placetype":"venue"
},
  "geometry": {"coordinates":[-0.1731539965,51.1360931396],"type":"Point"}
}