{
  "type": "Feature",
  "properties": {
    "iso:country":"GB",
    "sg:address":"15 West Maitland Street",
    "sg:city":"Edinburgh",
    "sg:classifiers":[
        {
            "category":"Organizations",
            "subcategory":"Non-profit Organization",
            "type":"Services"
        }
    ],
    "sg:phone":"+44 131 225 7801",
    "sg:postcode":"EH12 5EA",
    "sg:province":"City of Edinburgh",
    "sg:tags":[
        "organisation",
        "voluntary",
        "charity"
    ],
    "wof:name":"Abbeyfield Society for Scotland",
    "wof:placetype":"venue"
},
  "geometry": {"coordinates":[-3.2162399292,55.9466590881],"type":"Point"}
}