{
  "type": "Feature",
  "properties": {
    "addr:full":"45a Bampton Street Tiverton Devon EX16 6AH",
    "addr:housenumber":"45a",
    "addr:postcode":"ex16 6ah",
    "addr:street":"Bampton Street",
    "iso:country":"GB",
    "sg:address":"45a Bampton Street",
    "sg:city":"Tiverton",
    "sg:classifiers":[
        {
            "category":"Shopping",
            "subcategory":"Optician",
            "type":"Retail Goods"
        },
        {
            "category":"Health Services",
            "subcategory":"Optometrist",
            "type":"Services"
        }
    ],
    "sg:phone":"+44 1884 252034",
    "sg:postcode":"EX16 6AH",
    "sg:province":"Devon",
    "sg:tags":[
        "opthalmic"
    ],
    "wof:name":"Adam J Pilgrim",
    "wof:placetype":"venue"
},
  "geometry": {"coordinates":[-3.486142,50.904778],"type":"Point"}
}