{
  "type": "Feature",
  "properties": {
    "addr:full":"Unit 400 Glenfield Park 1, Philips Road Blackburn Lancashire BB1 5PF",
    "addr:housenumber":"400;1",
    "addr:postcode":"bb1 5pf",
    "addr:street":"Glenfield Park;Philips Road",
    "iso:country":"GB",
    "sg:address":"Unit 400 Glenfield Park 1, Philips Road",
    "sg:city":"Blackburn",
    "sg:classifiers":[
        {
            "category":"Professional",
            "subcategory":"Employment Agencies",
            "type":"Services"
        }
    ],
    "sg:postcode":"BB1 5PF",
    "sg:province":"Lancashire",
    "sg:tags":[
        "recr",
        "hire",
        "driver"
    ],
    "wof:name":"Drivertime Manchester Ltd.",
    "wof:placetype":"venue"
},
  "geometry": {"coordinates":[-2.480399,53.748516],"type":"Point"}
}