{
  "type": "Feature",
  "properties": {
    "iso:country":"GB",
    "sg:address":"97-99 Furtherwick Road",
    "sg:city":"Canvey Island",
    "sg:classifiers":[
        {
            "category":"Shopping",
            "type":"Retail Goods"
        }
    ],
    "sg:phone":"+44 1268 510341",
    "sg:postcode":"SS8 7AY",
    "sg:province":"Essex",
    "sg:tags":[
        "part",
        "accessory"
    ],
    "wof:name":"Auto Care",
    "wof:placetype":"venue"
},
  "geometry": {"coordinates":[0.592863977,51.520526886],"type":"Point"}
}