{
  "type": "Feature",
  "properties": {
    "addr:full":"Unit 5 Moorview Court, Estover Close Plymouth Devon PL6 7PL",
    "addr:housenumber":"unit 5",
    "addr:postcode":"pl6 7pl",
    "addr:street":"Moorview Court Estover Close",
    "iso:country":"GB",
    "sg:address":"Unit 5 Moorview Court, Estover Close",
    "sg:city":"Plymouth",
    "sg:classifiers":[
        {
            "category":"Home & Garden",
            "subcategory":"Home Furnishings",
            "type":"Retail Goods"
        }
    ],
    "sg:phone":"+44 1752 732111",
    "sg:postcode":"PL6 7PL",
    "sg:province":"Devon",
    "sg:tags":[
        "tubing",
        "fitting"
    ],
    "wof:name":"Europower Direct Hoser Services",
    "wof:placetype":"venue"
},
  "geometry": {"coordinates":[-4.090434,50.421261],"type":"Point"}
}