{
  "type": "Feature",
  "properties": {
    "addr:full":"Brooklands Yard, Rope Walk Chatham Kent ME4 4LB",
    "addr:postcode":"me4 4lb",
    "addr:street":"Rope Walk",
    "iso:country":"GB",
    "sg:address":"Brooklands Yard, Rope Walk",
    "sg:city":"Chatham",
    "sg:classifiers":[
        {
            "category":"Retail",
            "subcategory":"Auto Repair",
            "type":"Services"
        }
    ],
    "sg:phone":"+44 1634 831270",
    "sg:postcode":"ME4 4LB",
    "sg:province":"Kent",
    "sg:tags":[
        "modification",
        "garage"
    ],
    "wof:name":"Medway Transmission",
    "wof:placetype":"venue"
},
  "geometry": {"coordinates":[0.5224400163,51.3818893433],"type":"Point"}
}