{
  "type": "Feature",
  "properties": {
    "iso:country":"GB",
    "sg:address":"27 Chapel Street",
    "sg:city":"Leigh",
    "sg:classifiers":[
        {
            "category":"Personal",
            "subcategory":"Beauty Salon",
            "type":"Services"
        }
    ],
    "sg:phone":"+44 1942 510150",
    "sg:postcode":"WN7 2PB",
    "sg:province":"Lancashire",
    "wof:name":"The Works Nail & Beauty Specialists",
    "wof:placetype":"venue"
},
  "geometry": {"coordinates":[-2.511049,53.495369],"type":"Point"}
}