{
  "type": "Feature",
  "properties": {
    "iso:country":"GB",
    "sg:address":"3 Cornmarket",
    "sg:city":"Louth",
    "sg:classifiers":[
        {
            "category":"Restaurant",
            "type":"Food & Drink"
        }
    ],
    "sg:phone":"+44 1507 611110",
    "sg:postcode":"LN11 9PZ",
    "sg:province":"Lincolnshire",
    "wof:name":"Jaydees Family Restaurant",
    "wof:placetype":"venue"
},
  "geometry": {"coordinates":[-0.004858,53.366653],"type":"Point"}
}