{
  "type": "Feature",
  "properties": {
    "iso:country":"GB",
    "sg:address":"86 Old Oak Common Lane",
    "sg:city":"London",
    "sg:classifiers":[
        {
            "category":"Retail",
            "subcategory":"Funeral Services",
            "type":"Services"
        }
    ],
    "sg:phone":"+44 20 8743 3338",
    "sg:postcode":"W3 7DA",
    "sg:province":"Greater London",
    "sg:tags":[
        "director"
    ],
    "wof:name":"H J Bent & Co",
    "wof:placetype":"venue"
},
  "geometry": {"coordinates":[-0.248964,51.514416],"type":"Point"}
}