{
  "type": "Feature",
  "properties": {
    "addr:full":"17-19 West Princes Street Helensburgh Argyll and Bute G84 8TF",
    "addr:housenumber":"17-19",
    "addr:postcode":"g84 8tf",
    "addr:street":"West Princes Street",
    "iso:country":"GB",
    "sg:address":"17-19 West Princes Street",
    "sg:city":"Helensburgh",
    "sg:classifiers":[
        {
            "category":"Shopping",
            "subcategory":"Shoes",
            "type":"Retail Goods"
        }
    ],
    "sg:postcode":"G84 8TF",
    "sg:province":"Argyll and Bute",
    "sg:tags":[
        "shop",
        "retailer",
        "footwear"
    ],
    "wof:name":"HARGANS SHOES",
    "wof:placetype":"venue"
},
  "geometry": {"coordinates":[-4.7342867851,56.0040245056],"type":"Point"}
}