{
  "type": "Feature",
  "properties": {
    "iso:country":"GB",
    "sg:address":"Pencaer, Bryniwan",
    "sg:city":"Carmarthen",
    "sg:classifiers":[
        {
            "category":"Building & Trades",
            "subcategory":"Construction",
            "type":"Services"
        }
    ],
    "sg:phone":"+44 1994 484540",
    "sg:postcode":"SA33 6TE",
    "sg:province":"Carmarthenshire",
    "sg:tags":[
        "joiner",
        "carpenter"
    ],
    "wof:name":"Delmie L James",
    "wof:placetype":"venue"
},
  "geometry": {"coordinates":[-4.45206,51.9557],"type":"Point"}
}