{
  "type": "Feature",
  "properties": {
    "addr:full":"Cannons Farm, Ansells End, Kimpton Hitchin Hertfordshire SG4 8HD",
    "addr:postcode":"sg4 8hd",
    "addr:street":"Cannons;Ansells End",
    "iso:country":"GB",
    "sg:address":"Cannons Farm, Ansells End, Kimpton",
    "sg:city":"Hitchin",
    "sg:classifiers":[
        {
            "category":"Home & Garden",
            "subcategory":"Garden Supply",
            "type":"Retail Goods"
        },
        {
            "category":"Farming",
            "subcategory":"Livestock Farm",
            "type":"Manufacturing & Wholesale Goods"
        }
    ],
    "sg:postcode":"SG4 8HD",
    "sg:province":"Hertfordshire",
    "sg:tags":[
        "bulb",
        "grower",
        "others"
    ],
    "wof:name":"F C & D Manning",
    "wof:placetype":"venue"
},
  "geometry": {"coordinates":[-0.2983390093,51.8511734009],"type":"Point"}
}