{
  "type": "Feature",
  "properties": {
    "addr:full":"7 St Marys Road, Hartley Wintney, Hook Basingstoke Berkshire RG27 8EZ",
    "addr:housenumber":"7",
    "addr:postcode":"rg27 8ez",
    "addr:street":"St Marys Road;Hook",
    "iso:country":"GB",
    "sg:address":"7 St Marys Road, Hartley Wintney, Hook",
    "sg:city":"Basingstoke",
    "sg:classifiers":[
        {
            "category":"Building & Trades",
            "subcategory":"Landscaping Services",
            "type":"Services"
        }
    ],
    "sg:postcode":"RG27 8EZ",
    "sg:province":"Berkshire",
    "sg:tags":[
        "gardening"
    ],
    "wof:name":"R V R Supplies",
    "wof:placetype":"venue"
},
  "geometry": {"coordinates":[-0.9065840244,51.2995071411],"type":"Point"}
}