{
  "type": "Feature",
  "properties": {
    "iso:country":"GB",
    "sg:address":"19-23 Church Street, The Agora",
    "sg:city":"Milton Keynes",
    "sg:classifiers":[
        {
            "category":"Organizations",
            "subcategory":"Professional Association",
            "type":"Services"
        }
    ],
    "sg:phone":"+44 1908 312511",
    "sg:postcode":"MK12 5LG",
    "sg:province":"Buckinghamshire",
    "sg:tags":[
        "institute"
    ],
    "wof:name":"The Institute of Groundsmanship Ltd.",
    "wof:placetype":"venue"
},
  "geometry": {"coordinates":[-0.808598,52.062595],"type":"Point"}
}