{
  "type": "Feature",
  "properties": {
    "iso:country":"GB",
    "sg:address":"P O Box 307",
    "sg:city":"Walton-on-thames",
    "sg:classifiers":[
        {
            "category":"Home & Garden",
            "subcategory":"Household Appliances",
            "type":"Retail Goods"
        }
    ],
    "sg:postcode":"KT12 3WA",
    "sg:province":"Surrey",
    "sg:tags":[
        "electrical"
    ],
    "wof:name":"Grafters",
    "wof:placetype":"venue"
},
  "geometry": {"coordinates":[-0.420704,51.384346],"type":"Point"}
}