{
  "type": "Feature",
  "properties": {
    "iso:country":"GB",
    "sg:address":"101 High Street, Crigglestone",
    "sg:city":"Wakefield",
    "sg:classifiers":[
        {
            "category":"Bars & Pubs",
            "type":"Food & Drink"
        }
    ],
    "sg:phone":"+44 1924 255559",
    "sg:postcode":"WF4 3EF",
    "sg:province":"West Yorkshire",
    "sg:tags":[
        "pubs",
        "inn"
    ],
    "wof:name":"The Gardeners Arms",
    "wof:placetype":"venue"
},
  "geometry": {"coordinates":[-1.528656,53.641609],"type":"Point"}
}