{
  "type": "Feature",
  "properties": {
    "addr:full":"88 Fleet Road Fleet Hampshire GU51 4PA",
    "addr:housenumber":"88",
    "addr:postcode":"gu51 4pa",
    "addr:street":"Fleet Road",
    "iso:country":"GB",
    "sg:address":"88 Fleet Road",
    "sg:city":"Fleet",
    "sg:classifiers":[
        {
            "category":"Shopping",
            "subcategory":"Jewelry",
            "type":"Retail Goods"
        },
        {
            "category":"Manufacturing",
            "subcategory":"Jewelry",
            "type":"Manufacturing & Wholesale Goods"
        }
    ],
    "sg:phone":"+44 1252 812048",
    "sg:postcode":"GU51 4PA",
    "sg:province":"Hampshire",
    "sg:tags":[
        "repair",
        "sale",
        "jewellery"
    ],
    "wof:name":"S E Riordan",
    "wof:placetype":"venue"
},
  "geometry": {"coordinates":[-0.8400629759,51.2831344604],"type":"Point"}
}