{
  "type": "Feature",
  "properties": {
    "addr:full":"Grassland, Lynn Road, Sculthorpe Fakenham Norfolk NR21 9QF",
    "addr:postcode":"nr21 9qf",
    "addr:street":"Grassland Lynn Road",
    "iso:country":"GB",
    "sg:address":"Grassland, Lynn Road, Sculthorpe",
    "sg:city":"Fakenham",
    "sg:classifiers":[
        {
            "category":"Utilities",
            "subcategory":"Fuel Oil & Lpg",
            "type":"Services"
        }
    ],
    "sg:postcode":"NR21 9QF",
    "sg:province":"Norfolk",
    "wof:name":"Chestneys",
    "wof:placetype":"venue"
},
  "geometry": {"coordinates":[0.809607029,52.8423881531],"type":"Point"}
}