{
  "type": "Feature",
  "properties": {
    "iso:country":"GB",
    "sg:address":"9 The Downs, Portishead",
    "sg:city":"Bristol",
    "sg:classifiers":[
        {
            "category":"Shopping",
            "subcategory":"Discount & Variety Stores",
            "type":"Retail Goods"
        }
    ],
    "sg:postcode":"BS20 6ED",
    "sg:province":"Somerset",
    "sg:tags":[
        "cleaning",
        "supply"
    ],
    "wof:name":"Matson Supplies",
    "wof:placetype":"venue"
},
  "geometry": {"coordinates":[-2.769958,51.473667],"type":"Point"}
}