{
  "type": "Feature",
  "properties": {
    "iso:country":"GB",
    "sg:address":"Parkfield Road",
    "sg:city":"Stockton-on-tees",
    "sg:classifiers":[
        {
            "category":"Shopping",
            "subcategory":"Shoes",
            "type":"Retail Goods"
        }
    ],
    "sg:phone":"+44 1642 672525",
    "sg:postcode":"TS18 3DJ",
    "sg:province":"Durham",
    "sg:tags":[
        "shop",
        "retailer",
        "footwear"
    ],
    "wof:name":"Wynsors World of Shoes",
    "wof:placetype":"venue"
},
  "geometry": {"coordinates":[-1.3139020205,54.5586357117],"type":"Point"}
}