{
  "type": "Feature",
  "properties": {
    "iso:country":"GB",
    "sg:address":"Paradise St",
    "sg:city":"Accrington",
    "sg:classifiers":[
        {
            "category":"Community Center",
            "subcategory":"Youth",
            "type":"Public Place"
        }
    ],
    "sg:phone":"+44 1254 237690",
    "sg:postcode":"BB5 1PB",
    "sg:province":"Lancashire",
    "sg:tags":[
        "organisation",
        "centre"
    ],
    "wof:name":"Accrington New Era Youth Centre",
    "wof:placetype":"venue"
},
  "geometry": {"coordinates":[-2.36756,53.751789],"type":"Point"}
}