{
  "type": "Feature",
  "properties": {
    "addr:full":"11b Saville Street North Shields Tyne and Wear NE29 6QW",
    "addr:housenumber":"11b",
    "addr:postcode":"ne29 6qw",
    "addr:street":"Saville Street",
    "iso:country":"GB",
    "sg:address":"11b Saville Street",
    "sg:city":"North Shields",
    "sg:classifiers":[
        {
            "category":"Shopping",
            "subcategory":"Thrift Store",
            "type":"Retail Goods"
        }
    ],
    "sg:postcode":"NE29 6QW",
    "sg:province":"Tyne and Wear",
    "sg:tags":[
        "shop",
        "charity"
    ],
    "wof:name":"Oxfam",
    "wof:placetype":"venue"
},
  "geometry": {"coordinates":[-1.4465869665,55.0073661804],"type":"Point"}
}