{
  "type": "Feature",
  "properties": {
    "iso:country":"GB",
    "sg:address":"Charlton Saw Mill, Charlton",
    "sg:city":"Chichester",
    "sg:classifiers":[
        {
            "category":"Home & Garden",
            "subcategory":"Building Materials",
            "type":"Retail Goods"
        }
    ],
    "sg:postcode":"PO18 0HZ",
    "sg:province":"West Sussex",
    "sg:tags":[
        "fencing"
    ],
    "wof:name":"Downland Fencing",
    "wof:placetype":"venue"
},
  "geometry": {"coordinates":[-0.738943994,50.9102058411],"type":"Point"}
}