{
  "type": "Feature",
  "properties": {
    "iso:country":"GB",
    "sg:address":"38 Main Street Braeburn",
    "sg:city":"Stirling",
    "sg:classifiers":[
        {
            "category":"Shopping",
            "subcategory":"Department Store",
            "type":"Retail Goods"
        }
    ],
    "sg:phone":"+44 1786 812657",
    "sg:postcode":"FK7 8BT",
    "sg:province":"Falkirk",
    "wof:name":"Centre Food Store",
    "wof:placetype":"venue"
},
  "geometry": {"coordinates":[-3.876323,56.065815],"type":"Point"}
}