{
  "type": "Feature",
  "properties": {
    "iso:country":"GB",
    "sg:address":"8 Sandgate",
    "sg:city":"Berwick-upon-tweed",
    "sg:classifiers":[
        {
            "category":"Professional",
            "subcategory":"Art Services",
            "type":"Services"
        }
    ],
    "sg:phone":"+44 1289 330165",
    "sg:postcode":"TD15 1EP",
    "sg:province":"Northumberland",
    "sg:tags":[
        "picture",
        "restoration",
        "framing"
    ],
    "wof:name":"The Studio Keyside",
    "wof:placetype":"venue"
},
  "geometry": {"coordinates":[-2.003532,55.767746],"type":"Point"}
}