{
  "type": "Feature",
  "properties": {
    "iso:country":"GB",
    "sg:address":"St Anne's Rest Home, Grange Lane, Burghwallis",
    "sg:city":"Doncaster",
    "sg:classifiers":[
        {
            "category":"Social Services",
            "subcategory":"Retirement Home",
            "type":"Services"
        }
    ],
    "sg:phone":"+44 1302 700319",
    "sg:postcode":"DN6 9JL",
    "sg:province":"North Yorkshire",
    "sg:tags":[
        "rest"
    ],
    "wof:name":"St Anne's Rest Home",
    "wof:placetype":"venue"
},
  "geometry": {"coordinates":[-1.195068,53.600735],"type":"Point"}
}