{
  "type": "Feature",
  "properties": {
    "iso:country":"GB",
    "sg:address":"Gloucester Place",
    "sg:city":"Wellingborough",
    "sg:classifiers":[
        {
            "category":"Home & Garden",
            "subcategory":"Household Appliances",
            "type":"Retail Goods"
        }
    ],
    "sg:phone":"+44 1933 224445",
    "sg:postcode":"NN8 1AX",
    "sg:province":"Northamptonshire",
    "sg:tags":[
        "electrical"
    ],
    "wof:name":"Housewives Choice Electrical Services",
    "wof:placetype":"venue"
},
  "geometry": {"coordinates":[-0.696296,52.302422],"type":"Point"}
}