{
  "type": "Feature",
  "properties": {
    "addr:full":"48 Firmuir Ave, Closeburn Thornhill Dumfries and Galloway DG3 5HY",
    "addr:housenumber":"48",
    "addr:postcode":"dg3 5hy",
    "addr:street":"Firmuir Ave",
    "iso:country":"GB",
    "sg:address":"48 Firmuir Ave, Closeburn",
    "sg:city":"Thornhill",
    "sg:classifiers":[
        {
            "category":"Building & Trades",
            "subcategory":"Cleaning & Sanitation",
            "type":"Services"
        }
    ],
    "sg:postcode":"DG3 5HY",
    "sg:province":"Dumfries and Galloway",
    "sg:tags":[
        "sweep",
        "chimney"
    ],
    "wof:name":"Williamson,Matthew,",
    "wof:placetype":"venue"
},
  "geometry": {"coordinates":[-3.7380011082,55.2137031555],"type":"Point"}
}