{
  "type": "Feature",
  "properties": {
    "addr:full":"231 St Vincent St Glasgow Glasgow City G2 5QY",
    "addr:housenumber":"231",
    "addr:postcode":"g2 5qy",
    "addr:street":"St Vincent St",
    "iso:country":"GB",
    "sg:address":"231 St Vincent St",
    "sg:city":"Glasgow",
    "sg:classifiers":[
        {
            "category":"Banks & Credit Unions",
            "subcategory":"Financial Services",
            "type":"Services"
        }
    ],
    "sg:phone":"+44 141 243 2468",
    "sg:postcode":"G2 5QY",
    "sg:province":"Glasgow City",
    "sg:tags":[
        "consultant"
    ],
    "wof:name":"Dental Lease Direct Ltd",
    "wof:placetype":"venue"
},
  "geometry": {"coordinates":[-4.2636289597,55.8621368408],"type":"Point"}
}