{
  "type": "Feature",
  "properties": {
    "addr:full":"120 Bolton Road, Atherton Manchester Greater Manchester M46 9YZ",
    "addr:housenumber":"120",
    "addr:postcode":"m46 9yz",
    "addr:street":"Bolton Road",
    "iso:country":"GB",
    "sg:address":"120 Bolton Road, Atherton",
    "sg:city":"Manchester",
    "sg:classifiers":[
        {
            "category":"Professional",
            "subcategory":"Engineering",
            "type":"Services"
        },
        {
            "category":"Wholesale",
            "subcategory":"Construction Materials",
            "type":"Manufacturing & Wholesale Goods"
        }
    ],
    "sg:phone":"+44 1942 896565",
    "sg:postcode":"M46 9YZ",
    "sg:province":"Greater Manchester",
    "sg:tags":[
        "lift",
        "engineer"
    ],
    "wof:name":"L G H Group Plc",
    "wof:placetype":"venue"
},
  "geometry": {"coordinates":[-2.4892408848,53.5231323242],"type":"Point"}
}