{
  "type": "Feature",
  "properties": {
    "iso:country":"GB",
    "sg:address":"4 Oakhurst Close, West Moors",
    "sg:city":"Ferndown",
    "sg:classifiers":[
        {
            "category":"Professional",
            "subcategory":"Engineering",
            "type":"Services"
        }
    ],
    "sg:phone":"+44 1202 875697",
    "sg:postcode":"BH22 0DF",
    "sg:province":"Dorset",
    "sg:tags":[
        "civil",
        "engineer"
    ],
    "wof:name":"D T Smith Contractors (Dorset) Ltd",
    "wof:placetype":"venue"
},
  "geometry": {"coordinates":[-1.879278,50.824635],"type":"Point"}
}