{
  "type": "Feature",
  "properties": {
    "addr:full":"Longstring Farm, Perry Lake Lane, Wookey Wells Somerset BA5 1NZ",
    "addr:postcode":"ba5 1nz",
    "addr:street":"Perry Lake Lane",
    "iso:country":"GB",
    "sg:address":"Longstring Farm, Perry Lake Lane, Wookey",
    "sg:city":"Wells",
    "sg:classifiers":[
        {
            "category":"Farming",
            "subcategory":"Livestock Farm",
            "type":"Manufacturing & Wholesale Goods"
        }
    ],
    "sg:phone":"+44 1749 675533",
    "sg:postcode":"BA5 1NZ",
    "sg:province":"Somerset",
    "sg:tags":[
        "others"
    ],
    "wof:name":"STOTT BROS",
    "wof:placetype":"venue"
},
  "geometry": {"coordinates":[-2.7248990536,51.1988983154],"type":"Point"}
}