{
  "type": "Feature",
  "properties": {
    "addr:full":"Lower Lamphey Road Pembroke Pembrokeshire SA71 4AF",
    "addr:postcode":"sa71 4af",
    "addr:street":"Lamphey Road",
    "iso:country":"GB",
    "sg:address":"Lower Lamphey Road",
    "sg:city":"Pembroke",
    "sg:classifiers":[
        {
            "category":"Building & Trades",
            "subcategory":"Construction",
            "type":"Services"
        }
    ],
    "sg:phone":"+44 1646 683312",
    "sg:postcode":"SA71 4AF",
    "sg:province":"Pembrokeshire",
    "sg:tags":[
        "builder"
    ],
    "wof:name":"Elliott & Nicholas",
    "wof:placetype":"venue"
},
  "geometry": {"coordinates":[-4.9052348137,51.67212677],"type":"Point"}
}