{
  "type": "Feature",
  "properties": {
    "addr:full":"33 Quarry St Hamilton South Lanarkshire ML3 7AH",
    "addr:housenumber":"33",
    "addr:postcode":"ml3 7ah",
    "addr:street":"Quarry St",
    "iso:country":"GB",
    "sg:address":"33 Quarry St",
    "sg:city":"Hamilton",
    "sg:classifiers":[
        {
            "category":"Shopping",
            "subcategory":"Clothing, Apparel, & Fashions",
            "type":"Retail Goods"
        }
    ],
    "sg:phone":"+44 1698 282002",
    "sg:postcode":"ML3 7AH",
    "sg:province":"South Lanarkshire",
    "sg:tags":[
        "menswear"
    ],
    "wof:name":"Burton Menswear",
    "wof:placetype":"venue"
},
  "geometry": {"coordinates":[-4.037019,55.77396],"type":"Point"}
}