{
  "type": "Feature",
  "properties": {
    "addr:full":"King Street Ho, 15 Upper King St Norwich Norfolk NR3 1RB",
    "addr:housenumber":"15",
    "addr:postcode":"nr3 1rb",
    "addr:street":"King Street;Upper King St",
    "iso:country":"GB",
    "sg:address":"King Street Ho, 15 Upper King St",
    "sg:city":"Norwich",
    "sg:classifiers":[
        {
            "category":"Real Estate",
            "subcategory":"Developer",
            "type":"Services"
        }
    ],
    "sg:postcode":"NR3 1RB",
    "sg:province":"Norfolk",
    "sg:tags":[
        "property"
    ],
    "wof:name":"M1 Millennium Uk Ltd",
    "wof:placetype":"venue"
},
  "geometry": {"coordinates":[1.2987999916,52.629650116],"type":"Point"}
}