{
  "type": "Feature",
  "properties": {
    "iso:country":"GB",
    "sg:address":"4 Elm Clo, Rishton",
    "sg:city":"Blackburn",
    "sg:classifiers":[
        {
            "category":"Building & Trades",
            "subcategory":"Construction",
            "type":"Services"
        }
    ],
    "sg:postcode":"BB1 4HN",
    "sg:province":"Lancashire",
    "sg:tags":[
        "decorator",
        "painter"
    ],
    "wof:name":"Hope,Robert,",
    "wof:placetype":"venue"
},
  "geometry": {"coordinates":[-2.416389,53.764446],"type":"Point"}
}