{
  "type": "Feature",
  "properties": {
    "addr:full":"11 Frederick St Sunderland Tyne and Wear SR1 1NL",
    "addr:housenumber":"11",
    "addr:postcode":"sr1 1nl",
    "addr:street":"Frederick St",
    "iso:country":"GB",
    "sg:address":"11 Frederick St",
    "sg:city":"Sunderland",
    "sg:classifiers":[
        {
            "category":"Shopping",
            "subcategory":"Thrift Store",
            "type":"Retail Goods"
        }
    ],
    "sg:phone":"+44 191 567 3233",
    "sg:postcode":"SR1 1NL",
    "sg:province":"Tyne and Wear",
    "sg:tags":[
        "shop",
        "charity"
    ],
    "wof:name":"YWCA",
    "wof:placetype":"venue"
},
  "geometry": {"coordinates":[-1.37943995,54.9058151245],"type":"Point"}
}