{
  "type": "Feature",
  "properties": {
    "addr:full":"10a Broad Street Fraserburgh Aberdeenshire AB43 9AH",
    "addr:housenumber":"10a",
    "addr:postcode":"ab43 9ah",
    "addr:street":"Broad Street",
    "iso:country":"GB",
    "sg:address":"10a Broad Street",
    "sg:city":"Fraserburgh",
    "sg:classifiers":[
        {
            "category":"Bars & Pubs",
            "type":"Food & Drink"
        }
    ],
    "sg:phone":"+44 1346 519525",
    "sg:postcode":"AB43 9AH",
    "sg:province":"Aberdeenshire",
    "sg:tags":[
        "pubs",
        "inn"
    ],
    "wof:name":"Cheers Bar",
    "wof:placetype":"venue"
},
  "geometry": {"coordinates":[-2.004749,57.692726],"type":"Point"}
}