{
  "type": "Feature",
  "properties": {
    "iso:country":"GB",
    "sg:address":"7 Long Street",
    "sg:city":"Tetbury",
    "sg:classifiers":[
        {
            "category":"Food & Beverages",
            "subcategory":"Liquor & Beverages",
            "type":"Retail Goods"
        }
    ],
    "sg:phone":"+44 1666 502714",
    "sg:postcode":"GL8 8AA",
    "sg:province":"Gloucestershire",
    "sg:tags":[
        "beer",
        "spirit",
        "wines"
    ],
    "wof:name":"Victoria Wine",
    "wof:placetype":"venue"
},
  "geometry": {"coordinates":[-2.15992,51.637363],"type":"Point"}
}