{
  "type": "Feature",
  "properties": {
    "addr:full":"Dots & Melon Farm, Marsh Rd, Tillingham Southminster Essex CM0 7SJ",
    "addr:postcode":"cm0 7sj",
    "addr:street":"Marsh Rd",
    "iso:country":"GB",
    "sg:address":"Dots & Melon Farm, Marsh Rd, Tillingham",
    "sg:city":"Southminster",
    "sg:classifiers":[
        {
            "category":"Professional",
            "subcategory":"Art Services",
            "type":"Services"
        }
    ],
    "sg:phone":"+44 1621 779224",
    "sg:postcode":"CM0 7SJ",
    "sg:province":"Essex",
    "sg:tags":[
        "consultant",
        "design"
    ],
    "wof:name":"Project Design International Ltd",
    "wof:placetype":"venue"
},
  "geometry": {"coordinates":[0.9017599821,51.7020301819],"type":"Point"}
}