{
  "type": "Feature",
  "properties": {
    "iso:country":"GB",
    "sg:address":"12 Alloa Road",
    "sg:city":"Alloa",
    "sg:classifiers":[
        {
            "category":"Autos & Motor Vehicles",
            "subcategory":"Fuel & Gas Station",
            "type":"Retail Goods"
        }
    ],
    "sg:postcode":"FK10 4HH",
    "sg:province":"Clackmannanshire",
    "sg:tags":[
        "petrol",
        "filling"
    ],
    "wof:name":"Tower Service Station",
    "wof:placetype":"venue"
},
  "geometry": {"coordinates":[-3.740719,56.10471],"type":"Point"}
}