{
  "type": "Feature",
  "properties": {
    "addr:full":"Unit 14 Station Rd Wallingford Oxfordshire OX10 0HX",
    "addr:housenumber":"unit 14",
    "addr:postcode":"ox10 0hx",
    "addr:street":"Station Rd",
    "iso:country":"GB",
    "sg:address":"Unit 14 Station Rd",
    "sg:city":"Wallingford",
    "sg:classifiers":[
        {
            "category":"Shopping",
            "subcategory":"Florist",
            "type":"Retail Goods"
        }
    ],
    "sg:phone":"+44 1491 838080",
    "sg:postcode":"OX10 0HX",
    "sg:province":"Oxfordshire",
    "wof:name":"Craft Co Ltd The",
    "wof:placetype":"venue"
},
  "geometry": {"coordinates":[-1.135519,51.604069],"type":"Point"}
}