{
  "type": "Feature",
  "properties": {
    "addr:full":"2 Clayton Road Hayes Greater London UB3 1AY",
    "addr:housenumber":"2",
    "addr:postcode":"ub3 1ay",
    "addr:street":"Clayton Road",
    "iso:country":"GB",
    "sg:address":"2 Clayton Road",
    "sg:city":"Hayes",
    "sg:classifiers":[
        {
            "category":"Cafe",
            "type":"Food & Drink"
        }
    ],
    "sg:phone":"+44 20 8573 3326",
    "sg:postcode":"UB3 1AY",
    "sg:province":"Greater London",
    "sg:tags":[
        "tea",
        "room"
    ],
    "wof:name":"Brunchtime",
    "wof:placetype":"venue"
},
  "geometry": {"coordinates":[-0.420231998,51.504119873],"type":"Point"}
}