{
  "type": "Feature",
  "properties": {
    "addr:full":"183 Cobham Road, Fetcham Leatherhead Surrey KT22 9RU",
    "addr:housenumber":"183",
    "addr:postcode":"kt22 9ru",
    "addr:street":"Cobham Road",
    "iso:country":"GB",
    "sg:address":"183 Cobham Road, Fetcham",
    "sg:city":"Leatherhead",
    "sg:classifiers":[
        {
            "category":"Real Estate",
            "subcategory":"Architect",
            "type":"Services"
        }
    ],
    "sg:postcode":"KT22 9RU",
    "sg:province":"Surrey",
    "wof:name":"Pavla Heath Associates",
    "wof:placetype":"venue"
},
  "geometry": {"coordinates":[-0.3577879965,51.2981338501],"type":"Point"}
}