{
  "type": "Feature",
  "properties": {
    "iso:country":"GB",
    "sg:address":"23 Carriage Drive",
    "sg:city":"Kettering",
    "sg:classifiers":[
        {
            "category":"Education",
            "subcategory":"Special Training",
            "type":"Public Place"
        }
    ],
    "sg:phone":"+44 1536 522792",
    "sg:postcode":"NN16 9EN",
    "sg:province":"Northamptonshire",
    "sg:tags":[
        "product",
        "centre"
    ],
    "wof:name":"Priory Training Services",
    "wof:placetype":"venue"
},
  "geometry": {"coordinates":[-0.722497,52.418262],"type":"Point"}
}