{
  "type": "Feature",
  "properties": {
    "addr:full":"Kerswell, Drakelow Lane, Wolverley Kidderminster Staffordshire DY11 5RU",
    "addr:postcode":"dy11 5ru",
    "addr:street":"Drakelow Lane",
    "iso:country":"GB",
    "sg:address":"Kerswell, Drakelow Lane, Wolverley",
    "sg:city":"Kidderminster",
    "sg:classifiers":[
        {
            "category":"Building & Trades",
            "subcategory":"Landscaping Services",
            "type":"Services"
        }
    ],
    "sg:phone":"+44 1562 850066",
    "sg:postcode":"DY11 5RU",
    "sg:province":"Staffordshire",
    "sg:tags":[
        "landscape",
        "contractor"
    ],
    "wof:name":"Complete Weed Control",
    "wof:placetype":"venue"
},
  "geometry": {"coordinates":[-2.269094,52.422531],"type":"Point"}
}