{
  "type": "Feature",
  "properties": {
    "iso:country":"GB",
    "sg:address":"Renown Close, Chandlers Ford Industrial Estate",
    "sg:city":"Eastleigh",
    "sg:classifiers":[
        {
            "category":"Professional",
            "subcategory":"Engineering",
            "type":"Services"
        }
    ],
    "sg:phone":"+44 23 8026 9977",
    "sg:postcode":"SO53 4HZ",
    "sg:province":"Hampshire",
    "sg:tags":[
        "precision",
        "engineer"
    ],
    "wof:name":"Ottaway Engineering Ltd.",
    "wof:placetype":"venue"
},
  "geometry": {"coordinates":[-1.393464,50.978954],"type":"Point"}
}