{
  "type": "Feature",
  "properties": {
    "addr:full":"Shed D, Commerce Road Brentford Greater London TW8 8LA",
    "addr:postcode":"tw8 8la",
    "addr:street":"Commerce Road",
    "iso:country":"GB",
    "sg:address":"Shed D, Commerce Road",
    "sg:city":"Brentford",
    "sg:classifiers":[
        {
            "category":"Manufacturing",
            "subcategory":"Metals",
            "type":"Manufacturing & Wholesale Goods"
        }
    ],
    "sg:phone":"+44 20 8560 9901",
    "sg:postcode":"TW8 8LA",
    "sg:province":"Greater London",
    "sg:tags":[
        "steel",
        "stockholder"
    ],
    "wof:name":"Thames Valley Steels Ltd.",
    "wof:placetype":"venue"
},
  "geometry": {"coordinates":[-0.314836,51.48415],"type":"Point"}
}