{
  "type": "Feature",
  "properties": {
    "addr:full":"57 Fleetwood Close Tadworth Surrey KT20 5QH",
    "addr:housenumber":"57",
    "addr:postcode":"kt20 5qh",
    "addr:street":"Fleetwood Close",
    "iso:country":"GB",
    "sg:address":"57 Fleetwood Close",
    "sg:city":"Tadworth",
    "sg:classifiers":[
        {
            "category":"Building & Trades",
            "subcategory":"Landscaping Services",
            "type":"Services"
        }
    ],
    "sg:postcode":"KT20 5QH",
    "sg:province":"Surrey",
    "sg:tags":[
        "gardening"
    ],
    "wof:name":"Gardens Complete",
    "wof:placetype":"venue"
},
  "geometry": {"coordinates":[-0.229572,51.299103],"type":"Point"}
}