{
  "type": "Feature",
  "properties": {
    "addr:full":"Haven House, 33 Beaumont Fee Lincoln Lincolnshire LN1 1EZ",
    "addr:housenumber":"33",
    "addr:postcode":"ln1 1ez",
    "addr:street":"Fee",
    "iso:country":"GB",
    "sg:address":"Haven House, 33 Beaumont Fee",
    "sg:city":"Lincoln",
    "sg:classifiers":[
        {
            "category":"Banks & Credit Unions",
            "subcategory":"Financial Services",
            "type":"Services"
        }
    ],
    "sg:phone":"+44 1522 512707",
    "sg:postcode":"LN1 1EZ",
    "sg:province":"Lincolnshire",
    "sg:tags":[
        "consultant"
    ],
    "wof:name":"John Calland",
    "wof:placetype":"venue"
},
  "geometry": {"coordinates":[-0.5419809818,53.2319717407],"type":"Point"}
}