{
  "type": "Feature",
  "properties": {
    "addr:full":"100 Bon Accord St Aberdeen Aberdeen City AB11 6UY",
    "addr:housenumber":"100",
    "addr:postcode":"ab11 6uy",
    "addr:street":"Bon Accord St",
    "iso:country":"GB",
    "sg:address":"100 Bon Accord St",
    "sg:city":"Aberdeen",
    "sg:classifiers":[
        {
            "category":"Building & Trades",
            "subcategory":"Construction",
            "type":"Services"
        }
    ],
    "sg:phone":"+44 1224 575647",
    "sg:postcode":"AB11 6UY",
    "sg:province":"Aberdeen City",
    "sg:tags":[
        "joiner",
        "carpenter"
    ],
    "wof:name":"A C Simmers",
    "wof:placetype":"venue"
},
  "geometry": {"coordinates":[-2.1040000916,57.1400794983],"type":"Point"}
}