{
  "type": "Feature",
  "properties": {
    "iso:country":"GB",
    "sg:address":"Verey Rd, Woodside Ind Est",
    "sg:city":"Dunstable",
    "sg:classifiers":[
        {
            "category":"Professional",
            "subcategory":"Business Services",
            "type":"Services"
        }
    ],
    "sg:phone":"+44 1582 676800",
    "sg:postcode":"LU5 4TT",
    "sg:province":"Bedfordshire",
    "sg:tags":[
        "distribution"
    ],
    "wof:name":"Cert plc",
    "wof:placetype":"venue"
},
  "geometry": {"coordinates":[-0.5120900273,51.8956298828],"type":"Point"}
}