{
  "type": "Feature",
  "properties": {
    "addr:full":"6a Beaconsfield Terrace Road London Greater London W14 0PP",
    "addr:housenumber":"6a",
    "addr:postcode":"w14 0pp",
    "addr:street":"Beaconsfield Terrace Road",
    "iso:country":"GB",
    "sg:address":"6a Beaconsfield Terrace Road",
    "sg:city":"London",
    "sg:classifiers":[
        {
            "category":"Restaurant",
            "type":"Food & Drink"
        }
    ],
    "sg:phone":"+44 20 7603 8145",
    "sg:postcode":"W14 0PP",
    "sg:province":"Greater London",
    "sg:tags":[
        "chinese"
    ],
    "wof:name":"Mandarin Chinese Restaurant",
    "wof:placetype":"venue"
},
  "geometry": {"coordinates":[-0.212145,51.497356],"type":"Point"}
}