{
  "type": "Feature",
  "properties": {
    "iso:country":"GB",
    "sg:address":"Estate Agency, 37 Barrow St",
    "sg:city":"St Helens",
    "sg:classifiers":[
        {
            "category":"Real Estate",
            "subcategory":"Real Estate Agent",
            "type":"Services"
        }
    ],
    "sg:phone":"+44 1744 453333",
    "sg:postcode":"WA10 1RX",
    "sg:province":"Merseyside",
    "wof:name":"Jacksons Residential Property Services",
    "wof:placetype":"venue"
},
  "geometry": {"coordinates":[-2.738868,53.451687],"type":"Point"}
}