{
  "type": "Feature",
  "properties": {
    "iso:country":"GB",
    "sg:address":"65 Melbourne Road",
    "sg:city":"Ibstock",
    "sg:classifiers":[
        {
            "category":"Shopping",
            "subcategory":"Department Store",
            "type":"Retail Goods"
        },
        {
            "category":"Food & Beverages",
            "subcategory":"Groceries & Convenience Stores",
            "type":"Retail Goods"
        }
    ],
    "sg:phone":"+44 1530 260521",
    "sg:postcode":"LE67 6NN",
    "sg:province":"Leicestershire",
    "wof:name":"Milestone House General Store",
    "wof:placetype":"venue"
},
  "geometry": {"coordinates":[-1.401909,52.686321],"type":"Point"}
}