{
  "type": "Feature",
  "properties": {
    "addr:full":"8 Hawarden Avenue Morecambe Lancashire LA4 5RG",
    "addr:housenumber":"8",
    "addr:postcode":"la4 5rg",
    "addr:street":"Hawarden Avenue",
    "iso:country":"GB",
    "sg:address":"8 Hawarden Avenue",
    "sg:city":"Morecambe",
    "sg:classifiers":[
        {
            "category":"Professional",
            "subcategory":"Secretarial Services",
            "type":"Services"
        }
    ],
    "sg:phone":"+44 1524 414983",
    "sg:postcode":"LA4 5RG",
    "sg:province":"Lancashire",
    "wof:name":"Jean Cleasby Secretarial Agency",
    "wof:placetype":"venue"
},
  "geometry": {"coordinates":[-2.852799,54.070786],"type":"Point"}
}