{
  "type": "Feature",
  "properties": {
    "iso:country":"GB",
    "sg:address":"61 Charles Street",
    "sg:city":"Stockport",
    "sg:classifiers":[
        {
            "category":"Communications",
            "subcategory":"Newspaper",
            "type":"Services"
        }
    ],
    "sg:postcode":"SK1 3JR",
    "sg:province":"Cheshire",
    "sg:tags":[
        "magazine"
    ],
    "wof:name":"National Ex-Service Association",
    "wof:placetype":"venue"
},
  "geometry": {"coordinates":[-2.1510920525,53.4007835388],"type":"Point"}
}