{
  "type": "Feature",
  "properties": {
    "addr:full":"Water Lane, Stathern Melton Mowbray Leicestershire LE14 4HT",
    "addr:postcode":"le14 4ht",
    "addr:street":"Water Lane",
    "iso:country":"GB",
    "sg:address":"Water Lane, Stathern",
    "sg:city":"Melton Mowbray",
    "sg:classifiers":[
        {
            "category":"Education",
            "subcategory":"School",
            "type":"Public Place"
        }
    ],
    "sg:phone":"+44 1949 860316",
    "sg:postcode":"LE14 4HT",
    "sg:province":"Leicestershire",
    "sg:tags":[
        "local",
        "authority"
    ],
    "wof:name":"Stathern County Primary School",
    "wof:placetype":"venue"
},
  "geometry": {"coordinates":[-0.9142370224,52.8412666321],"type":"Point"}
}