{
  "type": "Feature",
  "properties": {
    "addr:full":"66-68 Kings Road Harrogate North Yorkshire HG1 5JR",
    "addr:housenumber":"66-68",
    "addr:postcode":"hg1 5jr",
    "addr:street":"Kings Road",
    "iso:country":"GB",
    "sg:address":"66-68 Kings Road",
    "sg:city":"Harrogate",
    "sg:classifiers":[
        {
            "category":"Travel",
            "subcategory":"Hotels & Motels",
            "type":"Entertainment"
        }
    ],
    "sg:phone":"+44 1423 504361",
    "sg:postcode":"HG1 5JR",
    "sg:province":"North Yorkshire",
    "wof:name":"Scotia House Hotel",
    "wof:placetype":"venue"
},
  "geometry": {"coordinates":[-1.5403900146,53.9969749451],"type":"Point"}
}