{
  "type": "Feature",
  "properties": {
    "addr:full":"Unit 2 Brymau Four, River Lane Chester Cheshire CH4 8RF",
    "addr:housenumber":"unit 2",
    "addr:postcode":"ch4 8rf",
    "addr:street":"Brymau Four River Lane",
    "iso:country":"GB",
    "sg:address":"Unit 2 Brymau Four, River Lane",
    "sg:city":"Chester",
    "sg:classifiers":[
        {
            "category":"Manufacturing",
            "subcategory":"Textiles",
            "type":"Manufacturing & Wholesale Goods"
        }
    ],
    "sg:phone":"+44 1244 680506",
    "sg:postcode":"CH4 8RF",
    "sg:province":"Cheshire",
    "sg:tags":[
        "mnfr",
        "sewing",
        "thread"
    ],
    "wof:name":"Somac Thread Manufacturing Ltd.",
    "wof:placetype":"venue"
},
  "geometry": {"coordinates":[-2.93335,53.180923],"type":"Point"}
}