{
  "type": "Feature",
  "properties": {
    "addr:full":"33 Saville Road Cheadle Cheshire SK8 4BY",
    "addr:housenumber":"33",
    "addr:postcode":"sk8 4by",
    "addr:street":"Saville Road Cheadle",
    "iso:country":"GB",
    "sg:address":"33 Saville Road",
    "sg:city":"Cheadle",
    "sg:classifiers":[
        {
            "category":"Real Estate",
            "subcategory":"Architect",
            "type":"Services"
        }
    ],
    "sg:postcode":"SK8 4BY",
    "sg:province":"Cheshire",
    "wof:name":"Ludplace Ltd.",
    "wof:placetype":"venue"
},
  "geometry": {"coordinates":[-2.2313940525,53.3971176147],"type":"Point"}
}