{
  "type": "Feature",
  "properties": {
    "iso:country":"GB",
    "sg:address":"Penwern Saron",
    "sg:city":"Llandysul",
    "sg:classifiers":[
        {
            "category":"Sports & Exercise",
            "subcategory":"Golf",
            "type":"Entertainment"
        }
    ],
    "sg:phone":"+44 1559 370705",
    "sg:postcode":"SA44 5EL",
    "sg:province":"Carmarthenshire",
    "sg:tags":[
        "club",
        "course"
    ],
    "wof:name":"Saron Community Golf Course",
    "wof:placetype":"venue"
},
  "geometry": {"coordinates":[-4.369909,52.01709],"type":"Point"}
}