{
  "type": "Feature",
  "properties": {
    "iso:country":"GB",
    "sg:address":"37 Broad Street",
    "sg:city":"Reading",
    "sg:classifiers":[
        {
            "category":"Shopping",
            "subcategory":"Comic Books",
            "type":"Retail Goods"
        }
    ],
    "sg:phone":"+44 118 957 3861",
    "sg:postcode":"RG1 2AA",
    "sg:province":"Berkshire",
    "sg:tags":[
        "jeweller"
    ],
    "wof:name":"Ernest Jones",
    "wof:placetype":"venue"
},
  "geometry": {"coordinates":[-0.9724140167,51.4557609558],"type":"Point"}
}