{
  "type": "Feature",
  "properties": {
    "addr:full":"Unit 16, Stevens Road Doncaster South Yorkshire DN4 0LT",
    "addr:housenumber":"unit 16",
    "addr:postcode":"dn4 0lt",
    "addr:street":"Stevens Road",
    "iso:country":"GB",
    "sg:address":"Unit 16, Stevens Road",
    "sg:city":"Doncaster",
    "sg:classifiers":[
        {
            "category":"Professional",
            "subcategory":"Engineering",
            "type":"Services"
        }
    ],
    "sg:phone":"+44 1302 310822",
    "sg:postcode":"DN4 0LT",
    "sg:province":"South Yorkshire",
    "wof:name":"Sitech Components Ltd.",
    "wof:placetype":"venue"
},
  "geometry": {"coordinates":[-1.148876,53.512058],"type":"Point"}
}