{
  "type": "Feature",
  "properties": {
    "iso:country":"GB",
    "sg:address":"36 St George's Road",
    "sg:city":"Winsford",
    "sg:classifiers":[
        {
            "category":"Building & Trades",
            "subcategory":"Plumbing",
            "type":"Services"
        }
    ],
    "sg:postcode":"CW7 1DA",
    "sg:province":"Cheshire",
    "sg:tags":[
        "heating"
    ],
    "wof:name":"E J Brown Plumbing",
    "wof:placetype":"venue"
},
  "geometry": {"coordinates":[-2.5356640816,53.187374115],"type":"Point"}
}