{
  "type": "Feature",
  "properties": {
    "addr:full":"6a Market St Lichfield Staffordshire WS13 6LH",
    "addr:housenumber":"6a",
    "addr:postcode":"ws13 6lh",
    "addr:street":"Market St",
    "iso:country":"GB",
    "sg:address":"6a Market St",
    "sg:city":"Lichfield",
    "sg:classifiers":[
        {
            "category":"Professional",
            "subcategory":"Accounting & Tax Preparation",
            "type":"Services"
        }
    ],
    "sg:phone":"+44 1543 250888",
    "sg:postcode":"WS13 6LH",
    "sg:province":"Staffordshire",
    "sg:tags":[
        "accountant"
    ],
    "wof:name":"Taxassist Direct",
    "wof:placetype":"venue"
},
  "geometry": {"coordinates":[-1.8292510509,52.6826782227],"type":"Point"}
}