{
  "type": "Feature",
  "properties": {
    "iso:country":"GB",
    "sg:address":"Birtley Lane, Birtley",
    "sg:city":"Chester-le-street",
    "sg:classifiers":[
        {
            "category":"Sports & Exercise",
            "subcategory":"Golf",
            "type":"Entertainment"
        }
    ],
    "sg:phone":"+44 191 410 2207",
    "sg:postcode":"DH3 2LR",
    "sg:province":"Durham",
    "sg:tags":[
        "club",
        "course"
    ],
    "wof:name":"Birtley Golf Club",
    "wof:placetype":"venue"
},
  "geometry": {"coordinates":[-1.5743969679,54.8961906433],"type":"Point"}
}