{
  "type": "Feature",
  "properties": {
    "iso:country":"GB",
    "sg:address":"312 Brownhill Road, Catford",
    "sg:city":"London",
    "sg:classifiers":[
        {
            "category":"Health Services",
            "subcategory":"Podiatrist",
            "type":"Services"
        }
    ],
    "sg:postcode":"SE6 1AX",
    "sg:province":"Greater London",
    "sg:tags":[
        "podiatrists",
        "chiropodist"
    ],
    "wof:name":"C K Y Kudzi",
    "wof:placetype":"venue"
},
  "geometry": {"coordinates":[-0.000752,51.4449806213],"type":"Point"}
}