{
  "type": "Feature",
  "properties": {
    "iso:country":"GB",
    "sg:address":"Units 2-3 Pattenden Lane, Marden",
    "sg:city":"Tonbridge",
    "sg:classifiers":[
        {
            "category":"Professional",
            "subcategory":"Business Services",
            "type":"Services"
        }
    ],
    "sg:phone":"+44 1622 832344",
    "sg:postcode":"TN12 9QS",
    "sg:province":"Kent",
    "sg:tags":[
        "distribution"
    ],
    "wof:name":"Cert",
    "wof:placetype":"venue"
},
  "geometry": {"coordinates":[0.489726007,51.176322937],"type":"Point"}
}