{
  "type": "Feature",
  "properties": {
    "addr:full":"St Thomas Vicarage, Church La Macclesfield Cheshire SK11 9NN",
    "addr:postcode":"sk11 9nn",
    "addr:street":"La Macclesfield",
    "iso:country":"GB",
    "sg:address":"St Thomas Vicarage, Church La",
    "sg:city":"Macclesfield",
    "sg:classifiers":[
        {
            "category":"Place Of Worship",
            "type":"Public Place"
        }
    ],
    "sg:phone":"+44 1625 424113",
    "sg:postcode":"SK11 9NN",
    "sg:province":"Cheshire",
    "wof:name":"St Thomas's C Of E Church",
    "wof:placetype":"venue"
},
  "geometry": {"coordinates":[-2.125756,53.255669],"type":"Point"}
}