{
  "type": "Feature",
  "properties": {
    "iso:country":"GB",
    "sg:address":"Dumfries Station, Lovers Walk",
    "sg:city":"Dumfries",
    "sg:classifiers":[
        {
            "category":"Freight",
            "type":"Transportation"
        }
    ],
    "sg:phone":"+44 1387 256218",
    "sg:postcode":"DG1 1LU",
    "sg:province":"Dumfries and Galloway",
    "sg:tags":[
        "haulage",
        "road"
    ],
    "wof:name":"Red Star Parcels",
    "wof:placetype":"venue"
},
  "geometry": {"coordinates":[-3.600536,55.100868],"type":"Point"}
}