{
  "type": "Feature",
  "properties": {
    "addr:full":"Unit 3, Chartists Way Leeds West Yorkshire LS27 9ET",
    "addr:housenumber":"unit 3",
    "addr:postcode":"ls27 9et",
    "addr:street":"Chartists Way",
    "iso:country":"GB",
    "sg:address":"Unit 3, Chartists Way",
    "sg:city":"Leeds",
    "sg:classifiers":[
        {
            "category":"Professional",
            "type":"Services"
        }
    ],
    "sg:postcode":"LS27 9ET",
    "sg:province":"West Yorkshire",
    "sg:tags":[
        "repair",
        "tech",
        "maintenance"
    ],
    "wof:name":"Pennine Computers Ltd",
    "wof:placetype":"venue"
},
  "geometry": {"coordinates":[-1.6035380363,53.7419700623],"type":"Point"}
}