{
  "type": "Feature",
  "properties": {
    "iso:country":"GB",
    "sg:address":"34 Kent Road",
    "sg:city":"Harrogate",
    "sg:classifiers":[
        {
            "category":"Social Services",
            "subcategory":"Retirement Home",
            "type":"Services"
        }
    ],
    "sg:postcode":"HG1 2LJ",
    "sg:province":"North Yorkshire",
    "sg:tags":[
        "residential",
        "care"
    ],
    "wof:name":"Stoneleigh Court Residential Home",
    "wof:placetype":"venue"
},
  "geometry": {"coordinates":[-1.5529619455,53.9977989197],"type":"Point"}
}