{
  "type": "Feature",
  "properties": {
    "addr:full":"Gynaechologist, 82 Berners St Ipswich Suffolk IP1 3LU",
    "addr:housenumber":"82",
    "addr:postcode":"ip1 3lu",
    "addr:street":"Gynaechologist;Berners St",
    "iso:country":"GB",
    "sg:address":"Gynaechologist, 82 Berners St",
    "sg:city":"Ipswich",
    "sg:classifiers":[
        {
            "category":"Health Services",
            "subcategory":"Doctor",
            "type":"Services"
        }
    ],
    "sg:phone":"+44 1473 257555",
    "sg:postcode":"IP1 3LU",
    "sg:province":"Suffolk",
    "sg:tags":[
        "surgeon"
    ],
    "wof:name":"J A Chalmers",
    "wof:placetype":"venue"
},
  "geometry": {"coordinates":[1.1437879801,52.0577774048],"type":"Point"}
}