{
  "type": "Feature",
  "properties": {
    "addr:full":"1 Benarty Sq Lochgelly Fife KY5 8NR",
    "addr:housenumber":"1",
    "addr:postcode":"ky5 8nr",
    "addr:street":"Benarty Sq Lochgelly",
    "iso:country":"GB",
    "sg:address":"1 Benarty Sq",
    "sg:city":"Lochgelly",
    "sg:classifiers":[
        {
            "category":"Food & Beverages",
            "subcategory":"Supermarket",
            "type":"Retail Goods"
        }
    ],
    "sg:phone":"+44 1592 861522",
    "sg:postcode":"KY5 8NR",
    "sg:province":"Fife",
    "wof:name":"Goodnews",
    "wof:placetype":"venue"
},
  "geometry": {"coordinates":[-3.3084158897,56.1347122192],"type":"Point"}
}