{
  "type": "Feature",
  "properties": {
    "addr:full":"23 Kimbolton Road Bedford Bedfordshire MK40 2NY",
    "addr:housenumber":"23",
    "addr:postcode":"mk40 2ny",
    "addr:street":"Kimbolton Road",
    "iso:country":"GB",
    "sg:address":"23 Kimbolton Road",
    "sg:city":"Bedford",
    "sg:classifiers":[
        {
            "category":"Education",
            "subcategory":"School",
            "type":"Public Place"
        }
    ],
    "sg:postcode":"MK40 2NY",
    "sg:province":"Bedfordshire",
    "sg:tags":[
        "independent",
        "preparatory"
    ],
    "wof:name":"Walmsley House School",
    "wof:placetype":"venue"
},
  "geometry": {"coordinates":[-0.4569880068,52.1454238892],"type":"Point"}
}