{
  "type": "Feature",
  "properties": {
    "iso:country":"GB",
    "sg:address":"3 The Old Forge",
    "sg:city":"Rayleigh",
    "sg:classifiers":[
        {
            "category":"Professional",
            "subcategory":"Management & Consulting",
            "type":"Services"
        }
    ],
    "sg:postcode":"SS6 9HQ",
    "sg:province":"Essex",
    "sg:tags":[
        "consultant",
        "business"
    ],
    "wof:name":"Barry Dimond Communications",
    "wof:placetype":"venue"
},
  "geometry": {"coordinates":[0.6046779752,51.5864448547],"type":"Point"}
}