{
  "type": "Feature",
  "properties": {
    "iso:country":"GB",
    "sg:address":"8 High Holborn",
    "sg:city":"London",
    "sg:classifiers":[
        {
            "category":"Shopping",
            "subcategory":"Gifts & Souvenirs",
            "type":"Retail Goods"
        }
    ],
    "sg:phone":"+44 20 7831 1127",
    "sg:postcode":"WC1V 6DR",
    "sg:province":"Greater London",
    "sg:tags":[
        "poster",
        "card"
    ],
    "wof:name":"Clinton Cards Plc",
    "wof:placetype":"venue"
},
  "geometry": {"coordinates":[-0.0723590031,51.5760498047],"type":"Point"}
}