{
  "type": "Feature",
  "properties": {
    "addr:full":"1 Clark Way Bellshill North Lanarkshire ML4 3NX",
    "addr:housenumber":"1",
    "addr:postcode":"ml4 3nx",
    "addr:street":"Clark Way",
    "iso:country":"GB",
    "sg:address":"1 Clark Way",
    "sg:city":"Bellshill",
    "sg:classifiers":[
        {
            "category":"Retail",
            "subcategory":"Auto Repair",
            "type":"Services"
        }
    ],
    "sg:phone":"+44 1698 339090",
    "sg:postcode":"ML4 3NX",
    "sg:province":"North Lanarkshire",
    "sg:tags":[
        "bodybuilder",
        "repairer"
    ],
    "wof:name":"Trucktec Ltd.",
    "wof:placetype":"venue"
},
  "geometry": {"coordinates":[-4.0352110863,55.826461792],"type":"Point"}
}