{
  "type": "Feature",
  "properties": {
    "addr:full":"Conduit Road, Norton Kane Cannock Staffordshire WS11 3TJ",
    "addr:postcode":"ws11 3tj",
    "addr:street":"Conduit Road",
    "iso:country":"GB",
    "sg:address":"Conduit Road, Norton Kane",
    "sg:city":"Cannock",
    "sg:classifiers":[
        {
            "category":"Manufacturing",
            "subcategory":"Lumber",
            "type":"Manufacturing & Wholesale Goods"
        }
    ],
    "sg:phone":"+44 1543 278777",
    "sg:postcode":"WS11 3TJ",
    "sg:province":"Staffordshire",
    "sg:tags":[
        "importer",
        "merchants",
        "agent",
        "timber"
    ],
    "wof:name":"Avanty Timber Supplies",
    "wof:placetype":"venue"
},
  "geometry": {"coordinates":[-1.971514,52.66861],"type":"Point"}
}