{
  "type": "Feature",
  "properties": {
    "addr:full":", Fortrie Turriff Aberdeenshire AB53 4HY",
    "addr:postcode":"ab53 4hy",
    "iso:country":"GB",
    "sg:address":", Fortrie",
    "sg:city":"Turriff",
    "sg:classifiers":[
        {
            "category":"Education",
            "subcategory":"School",
            "type":"Public Place"
        }
    ],
    "sg:phone":"+44 1466 730206",
    "sg:postcode":"AB53 4HY",
    "sg:province":"Aberdeenshire",
    "sg:tags":[
        "local",
        "authority"
    ],
    "wof:name":"Easterfield Primary School",
    "wof:placetype":"venue"
},
  "geometry": {"coordinates":[-2.455229044,57.5399017334],"type":"Point"}
}