{
  "type": "Feature",
  "properties": {
    "addr:full":"Head Office, 320 Goldhawk Rd Hammersmith Greater London W6 0XF",
    "addr:housenumber":"320",
    "addr:postcode":"w6 0xf",
    "addr:street":"Goldhawk Rd",
    "iso:country":"GB",
    "sg:address":"Head Office, 320 Goldhawk Rd",
    "sg:city":"Hammersmith",
    "sg:classifiers":[
        {
            "category":"Restaurant",
            "type":"Food & Drink"
        }
    ],
    "sg:phone":"+44 20 8846 9797",
    "sg:postcode":"W6 0XF",
    "sg:province":"Greater London",
    "wof:name":"Woodstock Group The",
    "wof:placetype":"venue"
},
  "geometry": {"coordinates":[-0.2294200063,51.4961509705],"type":"Point"}
}