{
  "type": "Feature",
  "properties": {
    "addr:full":"Livesey St Sheffield South Yorkshire S6 2BL",
    "addr:postcode":"s6 2bl",
    "addr:street":"Livesey St",
    "iso:country":"GB",
    "sg:address":"Livesey St",
    "sg:city":"Sheffield",
    "sg:classifiers":[
        {
            "category":"Freight",
            "type":"Transportation"
        }
    ],
    "sg:phone":"+44 114 234 3444",
    "sg:postcode":"S6 2BL",
    "sg:province":"South Yorkshire",
    "sg:tags":[
        "haulage",
        "road"
    ],
    "wof:name":"H Askey Haulage Contractors",
    "wof:placetype":"venue"
},
  "geometry": {"coordinates":[-1.4954550266,53.4048957825],"type":"Point"}
}