{
  "type": "Feature",
  "properties": {
    "iso:country":"GB",
    "sg:address":"75 Hilltot Road, Earley",
    "sg:city":"Reading",
    "sg:classifiers":[
        {
            "category":"Building & Trades",
            "subcategory":"Construction",
            "type":"Services"
        }
    ],
    "sg:phone":"+44 118 935 1769",
    "sg:postcode":"RG6 1DB",
    "sg:province":"Berkshire",
    "sg:tags":[
        "joinery",
        "joiner",
        "carpenter",
        "carpentry"
    ],
    "wof:name":"N Mackinnon",
    "wof:placetype":"venue"
},
  "geometry": {"coordinates":[-0.9257370234,51.45520401],"type":"Point"}
}