{
  "type": "Feature",
  "properties": {
    "addr:full":"1210 Lincoln Road Peterborough Cambridgeshire PE4 6LA",
    "addr:housenumber":"1210",
    "addr:postcode":"pe4 6la",
    "addr:street":"Lincoln Road",
    "iso:country":"GB",
    "sg:address":"1210 Lincoln Road",
    "sg:city":"Peterborough",
    "sg:classifiers":[
        {
            "category":"Professional",
            "subcategory":"Business Services",
            "type":"Services"
        }
    ],
    "sg:phone":"+44 1733 578717",
    "sg:postcode":"PE4 6LA",
    "sg:province":"Cambridgeshire",
    "sg:tags":[
        "retail",
        "premise"
    ],
    "wof:name":"Beecham Enterprises Ltd.",
    "wof:placetype":"venue"
},
  "geometry": {"coordinates":[-0.2755619884,52.6088943481],"type":"Point"}
}