{
  "type": "Feature",
  "properties": {
    "addr:full":"Bowness Clinic 10 Harley St West End Hampshire W1N 1AA",
    "addr:housenumber":"10",
    "addr:postcode":"w1n 1aa",
    "addr:street":"Harley St",
    "iso:country":"GB",
    "sg:address":"Bowness Clinic 10 Harley St",
    "sg:city":"West End",
    "sg:classifiers":[
        {
            "category":"Health Services",
            "subcategory":"Doctor",
            "type":"Services"
        }
    ],
    "sg:phone":"+44 20 7467 8368",
    "sg:postcode":"W1N 1AA",
    "sg:province":"Hampshire",
    "sg:tags":[
        "practitioners"
    ],
    "wof:name":"Sherlock Clive",
    "wof:placetype":"venue"
},
  "geometry": {"coordinates":[-0.145998,51.517368],"type":"Point"}
}