{
  "type": "Feature",
  "properties": {
    "iso:country":"GB",
    "sg:address":"26a High St",
    "sg:city":"Merthyr Tydfil",
    "sg:classifiers":[
        {
            "category":"Government",
            "subcategory":"Police Station",
            "type":"Public Place"
        }
    ],
    "sg:phone":"+44 1685 721848",
    "sg:postcode":"CF47 8DP",
    "sg:province":"Merthyr Tydfil",
    "sg:tags":[
        "support"
    ],
    "wof:name":"The Probation Service",
    "wof:placetype":"venue"
},
  "geometry": {"coordinates":[-3.3778810501,51.7436065674],"type":"Point"}
}