{
  "type": "Feature",
  "properties": {
    "addr:full":"Oakley House, Pinfold Lane Reading Berkshire RG8 8SH",
    "addr:postcode":"rg8 8sh",
    "addr:street":"Pinfold Lane",
    "iso:country":"GB",
    "sg:address":"Oakley House, Pinfold Lane",
    "sg:city":"Reading",
    "sg:classifiers":[
        {
            "category":"Shopping",
            "subcategory":"Stationery & Office Supplies",
            "type":"Retail Goods"
        },
        {
            "category":"Professional",
            "subcategory":"Computer Services",
            "type":"Services"
        }
    ],
    "sg:phone":"+44 1635 579059",
    "sg:postcode":"RG8 8SH",
    "sg:province":"Berkshire",
    "sg:tags":[
        "machine",
        "facsimile",
        "system",
        "software"
    ],
    "wof:name":"Delta Point Computers Ltd",
    "wof:placetype":"venue"
},
  "geometry": {"coordinates":[-1.1881079674,51.4869728088],"type":"Point"}
}