{
  "type": "Feature",
  "properties": {
    "addr:full":"15 Main Drive, East Lane Wembley Greater London HA9 7FF",
    "addr:housenumber":"15",
    "addr:postcode":"ha9 7ff",
    "addr:street":"Main Drive East Lane",
    "iso:country":"GB",
    "sg:address":"15 Main Drive, East Lane",
    "sg:city":"Wembley",
    "sg:classifiers":[
        {
            "category":"Professional",
            "subcategory":"Business Services",
            "type":"Services"
        }
    ],
    "sg:phone":"+44 20 8385 4455",
    "sg:postcode":"HA9 7FF",
    "sg:province":"Greater London",
    "sg:tags":[
        "distributor",
        "film"
    ],
    "wof:name":"IMPERIAL ENTERTAINMENT UK LTD",
    "wof:placetype":"venue"
},
  "geometry": {"coordinates":[-0.2955389917,51.5529632568],"type":"Point"}
}