{
  "type": "Feature",
  "properties": {
    "addr:full":"10 Bruntcliffe Rd Leeds West Yorkshire LS27 0LX",
    "addr:housenumber":"10",
    "addr:postcode":"ls27 0lx",
    "addr:street":"Bruntcliffe Rd",
    "iso:country":"GB",
    "sg:address":"10 Bruntcliffe Rd",
    "sg:city":"Leeds",
    "sg:classifiers":[
        {
            "category":"Retail",
            "subcategory":"Repair Shop",
            "type":"Services"
        }
    ],
    "sg:phone":"+44 113 219 4261",
    "sg:postcode":"LS27 0LX",
    "sg:province":"West Yorkshire",
    "sg:tags":[
        "maintenance"
    ],
    "wof:name":"P3 Pointing-Patience-Pride",
    "wof:placetype":"venue"
},
  "geometry": {"coordinates":[-1.6211889982,53.7457809448],"type":"Point"}
}