{
  "type": "Feature",
  "properties": {
    "addr:full":"School Rd Ashford Greater London TW15 2BW",
    "addr:postcode":"tw15 2bw",
    "addr:street":"School Rd",
    "iso:country":"GB",
    "sg:address":"School Rd",
    "sg:city":"Ashford",
    "sg:classifiers":[
        {
            "category":"Education",
            "subcategory":"School",
            "type":"Public Place"
        }
    ],
    "sg:phone":"+44 1784 253310",
    "sg:postcode":"TW15 2BW",
    "sg:province":"Greater London",
    "sg:tags":[
        "local",
        "authority"
    ],
    "wof:name":"Ashford C Of E Primary School",
    "wof:placetype":"venue"
},
  "geometry": {"coordinates":[-0.451244,51.426109],"type":"Point"}
}