{
  "type": "Feature",
  "properties": {
    "addr:full":"71 Basingstoke Road Reading Berkshire RG2 0ER",
    "addr:housenumber":"71",
    "addr:postcode":"rg2 0er",
    "addr:street":"Basingstoke Road",
    "iso:country":"GB",
    "sg:address":"71 Basingstoke Road",
    "sg:city":"Reading",
    "sg:classifiers":[
        {
            "category":"Shopping",
            "subcategory":"Pharmacy",
            "type":"Retail Goods"
        }
    ],
    "sg:phone":"+44 118 987 5712",
    "sg:postcode":"RG2 0ER",
    "sg:province":"Berkshire",
    "sg:tags":[
        "pharmacist",
        "chemist"
    ],
    "wof:name":"R C Jogia & Co. Ltd.",
    "wof:placetype":"venue"
},
  "geometry": {"coordinates":[-0.967179,51.439636],"type":"Point"}
}