{
  "type": "Feature",
  "properties": {
    "addr:full":"38-40 Wheelergate Nottingham Nottinghamshire NG1 2ND",
    "addr:housenumber":"38-40",
    "addr:postcode":"ng1 2nd",
    "addr:street":"Wheelergate",
    "iso:country":"GB",
    "sg:address":"38-40 Wheelergate",
    "sg:city":"Nottingham",
    "sg:classifiers":[
        {
            "category":"Professional",
            "subcategory":"Employment Agencies",
            "type":"Services"
        }
    ],
    "sg:phone":"+44 115 948 4850",
    "sg:postcode":"NG1 2ND",
    "sg:province":"Nottinghamshire",
    "sg:tags":[
        "consultant"
    ],
    "wof:name":"Hays Accountancy Personnel",
    "wof:placetype":"venue"
},
  "geometry": {"coordinates":[-1.1439239979,52.9492263794],"type":"Point"}
}