{
  "type": "Feature",
  "properties": {
    "addr:full":"2a Gloucester Road London Greater London N17 6DH",
    "addr:housenumber":"2a",
    "addr:postcode":"n17 6dh",
    "addr:street":"Gloucester Road",
    "iso:country":"GB",
    "sg:address":"2a Gloucester Road",
    "sg:city":"London",
    "sg:classifiers":[
        {
            "category":"Shopping",
            "subcategory":"Stationery & Office Supplies",
            "type":"Retail Goods"
        }
    ],
    "sg:phone":"+44 20 8801 7514",
    "sg:postcode":"N17 6DH",
    "sg:province":"Greater London",
    "wof:name":"Dailiprint Ltd.",
    "wof:placetype":"venue"
},
  "geometry": {"coordinates":[-0.081381,51.588917],"type":"Point"}
}