{
  "type": "Feature",
  "properties": {
    "addr:full":"Langer Lane, Wingerworth Chesterfield Derbyshire S42 6TY",
    "addr:postcode":"s42 6ty",
    "addr:street":"Langer Lane",
    "iso:country":"GB",
    "sg:address":"Langer Lane, Wingerworth",
    "sg:city":"Chesterfield",
    "sg:classifiers":[
        {
            "category":"Retail",
            "subcategory":"Funeral Services",
            "type":"Services"
        }
    ],
    "sg:postcode":"S42 6TY",
    "sg:province":"Derbyshire",
    "wof:name":"J E Nicholson Funeral Director",
    "wof:placetype":"venue"
},
  "geometry": {"coordinates":[-1.4215910435,53.2055282593],"type":"Point"}
}