{
  "type": "Feature",
  "properties": {
    "addr:full":"7 Grange Road, Houston Industrial Estate Livingston West Lothian EH54 5DE",
    "addr:housenumber":"7",
    "addr:postcode":"eh54 5de",
    "addr:street":"Grange Road;Industrial Estate",
    "iso:country":"GB",
    "sg:address":"7 Grange Road, Houston Industrial Estate",
    "sg:city":"Livingston",
    "sg:classifiers":[
        {
            "category":"Professional",
            "subcategory":"Computer Services",
            "type":"Services"
        }
    ],
    "sg:phone":"+44 1506 434811",
    "sg:postcode":"EH54 5DE",
    "sg:province":"West Lothian",
    "sg:tags":[
        "support",
        "system",
        "software"
    ],
    "wof:name":"Computer Links Ltd",
    "wof:placetype":"venue"
},
  "geometry": {"coordinates":[-3.4997279644,55.9034996033],"type":"Point"}
}