{
  "type": "Feature",
  "properties": {
    "addr:full":"Odiham Rd, Upper Hale Farnham Hampshire GU10 5AB",
    "addr:postcode":"gu10 5ab",
    "addr:street":"Odiham Rd;Hale",
    "iso:country":"GB",
    "sg:address":"Odiham Rd, Upper Hale",
    "sg:city":"Farnham",
    "sg:classifiers":[
        {
            "category":"Autos & Motor Vehicles",
            "subcategory":"Fuel & Gas Station",
            "type":"Retail Goods"
        }
    ],
    "sg:phone":"+44 1252 739900",
    "sg:postcode":"GU10 5AB",
    "sg:province":"Hampshire",
    "sg:tags":[
        "petrol",
        "filling"
    ],
    "wof:name":"Total Convenience Stores",
    "wof:placetype":"venue"
},
  "geometry": {"coordinates":[-0.8263959885,51.2364997864],"type":"Point"}
}