{
  "type": "Feature",
  "properties": {
    "iso:country":"GB",
    "sg:address":"Suite 15, 6-8 York Place",
    "sg:city":"Leeds",
    "sg:classifiers":[
        {
            "category":"Banks & Credit Unions",
            "subcategory":"Investment Brokerage",
            "type":"Services"
        }
    ],
    "sg:postcode":"LS1 2DS",
    "sg:province":"West Yorkshire",
    "sg:tags":[
        "stockbroker"
    ],
    "wof:name":"Fyshe Horton Finney Ltd.",
    "wof:placetype":"venue"
},
  "geometry": {"coordinates":[-1.551193,53.79678],"type":"Point"}
}