{
  "type": "Feature",
  "properties": {
    "addr:full":"5 Applehaigh Gro Barnsley South Yorkshire S71 4ER",
    "addr:housenumber":"5",
    "addr:postcode":"s71 4er",
    "addr:street":"Applehaigh Gro;Yorkshire",
    "iso:country":"GB",
    "sg:address":"5 Applehaigh Gro",
    "sg:city":"Barnsley",
    "sg:classifiers":[
        {
            "category":"Professional",
            "subcategory":"Engineering",
            "type":"Services"
        }
    ],
    "sg:phone":"+44 1226 727128",
    "sg:postcode":"S71 4ER",
    "sg:province":"South Yorkshire",
    "sg:tags":[
        "contractor",
        "electrical",
        "engineer"
    ],
    "wof:name":"M G Electrical Services",
    "wof:placetype":"venue"
},
  "geometry": {"coordinates":[-1.471285,53.599209],"type":"Point"}
}