{
  "type": "Feature",
  "properties": {
    "addr:full":"Lypiatt Lodge, Lypiatt Road Cheltenham Gloucestershire GL50 2SY",
    "addr:postcode":"gl50 2sy",
    "addr:street":"Lypiatt Road",
    "iso:country":"GB",
    "sg:address":"Lypiatt Lodge, Lypiatt Road",
    "sg:city":"Cheltenham",
    "sg:classifiers":[
        {
            "category":"Social Services",
            "subcategory":"Retirement Home",
            "type":"Services"
        }
    ],
    "sg:phone":"+44 1242 526218",
    "sg:postcode":"GL50 2SY",
    "sg:province":"Gloucestershire",
    "sg:tags":[
        "care"
    ],
    "wof:name":"Astley Care Home",
    "wof:placetype":"venue"
},
  "geometry": {"coordinates":[-2.0784590244,51.8980484009],"type":"Point"}
}