{
  "type": "Feature",
  "properties": {
    "iso:country":"GB",
    "sg:address":"9 Westgate",
    "sg:city":"Huddersfield",
    "sg:classifiers":[
        {
            "category":"Personal",
            "subcategory":"Beauty Salon",
            "type":"Services"
        },
        {
            "category":"Personal",
            "subcategory":"Barber",
            "type":"Services"
        }
    ],
    "sg:phone":"+44 1484 432111",
    "sg:postcode":"HD1 1NP",
    "sg:province":"West Yorkshire",
    "sg:tags":[
        "unisex",
        "hairdresser"
    ],
    "wof:name":"Rubens Hair & Beauty Ltd",
    "wof:placetype":"venue"
},
  "geometry": {"coordinates":[-1.783197999,53.6468963623],"type":"Point"}
}