{
  "type": "Feature",
  "properties": {
    "addr:full":"5a Regent Street, Pocklington York East Riding of Yorkshire YO42 2QN",
    "addr:housenumber":"5a",
    "addr:postcode":"yo42 2qn",
    "addr:street":"Regent Street",
    "iso:country":"GB",
    "sg:address":"5a Regent Street, Pocklington",
    "sg:city":"York",
    "sg:classifiers":[
        {
            "category":"Personal",
            "subcategory":"Barber",
            "type":"Services"
        }
    ],
    "sg:postcode":"YO42 2QN",
    "sg:province":"East Riding of Yorkshire",
    "sg:tags":[
        "men's",
        "hairdresser"
    ],
    "wof:name":"Sam's Hairdressers",
    "wof:placetype":"venue"
},
  "geometry": {"coordinates":[-0.7787389755,53.9304504395],"type":"Point"}
}