{
  "type": "Feature",
  "properties": {
    "addr:full":"923 Queslett Road, Great Barr Birmingham West Midlands B43 7DT",
    "addr:housenumber":"923",
    "addr:postcode":"b43 7dt",
    "addr:street":"Queslett Road",
    "iso:country":"GB",
    "sg:address":"923 Queslett Road, Great Barr",
    "sg:city":"Birmingham",
    "sg:classifiers":[
        {
            "category":"Shopping",
            "subcategory":"News",
            "type":"Retail Goods"
        }
    ],
    "sg:phone":"+44 121 360 3704",
    "sg:postcode":"B43 7DT",
    "sg:province":"West Midlands",
    "sg:tags":[
        "newsagent"
    ],
    "wof:name":"Dillons Newsagents Ltd.",
    "wof:placetype":"venue"
},
  "geometry": {"coordinates":[-1.898899,52.55534],"type":"Point"}
}