{
  "type": "Feature",
  "properties": {
    "iso:country":"GB",
    "sg:address":"104 The Street",
    "sg:city":"Ashtead",
    "sg:classifiers":[
        {
            "category":"Organizations",
            "subcategory":"Membership Organization",
            "type":"Services"
        }
    ],
    "sg:phone":"+44 1372 272927",
    "sg:postcode":"KT21 1AW",
    "sg:province":"Surrey",
    "sg:tags":[
        "club"
    ],
    "wof:name":"Ashtead Village Club",
    "wof:placetype":"venue"
},
  "geometry": {"coordinates":[-0.297975,51.310032],"type":"Point"}
}