{
  "type": "Feature",
  "properties": {
    "addr:full":"Wood Edge, Apperley Lane Bradford West Yorkshire BD10 0PH",
    "addr:postcode":"bd10 0ph",
    "addr:street":"Apperley Lane",
    "iso:country":"GB",
    "sg:address":"Wood Edge, Apperley Lane",
    "sg:city":"Bradford",
    "sg:classifiers":[
        {
            "category":"Retail",
            "subcategory":"Laundry & Dry Cleaning",
            "type":"Services"
        }
    ],
    "sg:phone":"+44 113 250 2441",
    "sg:postcode":"BD10 0PH",
    "sg:province":"West Yorkshire",
    "sg:tags":[
        "launderette"
    ],
    "wof:name":"Harry King",
    "wof:placetype":"venue"
},
  "geometry": {"coordinates":[-1.7583060265,53.7957382202],"type":"Point"}
}