{
  "type": "Feature",
  "properties": {
    "iso:country":"GB",
    "sg:address":"23 Jameson Rd",
    "sg:city":"Hull",
    "sg:classifiers":[
        {
            "category":"Professional",
            "subcategory":"Business Services",
            "type":"Services"
        }
    ],
    "sg:postcode":"HU1 3HR",
    "sg:province":"East Riding of Yorkshire",
    "sg:tags":[
        "import",
        "export",
        "agent"
    ],
    "wof:name":"Azar",
    "wof:placetype":"venue"
},
  "geometry": {"coordinates":[-0.340105,53.744923],"type":"Point"}
}