{
  "type": "Feature",
  "properties": {
    "addr:full":"G E C Indust Estate, Clayton Park, Blackburn Road, Clayton Le Moors Accrington Lancashire BB5 5JW",
    "addr:postcode":"bb5 5jw",
    "addr:street":"Indust Estate Clayton Park Blackburn Road",
    "iso:country":"GB",
    "sg:address":"G E C Indust Estate, Clayton Park, Blackburn Road, Clayton Le Moors",
    "sg:city":"Accrington",
    "sg:classifiers":[
        {
            "category":"Building & Trades",
            "subcategory":"Cleaning & Sanitation",
            "type":"Services"
        }
    ],
    "sg:phone":"+44 1254 399704",
    "sg:postcode":"BB5 5JW",
    "sg:province":"Lancashire",
    "sg:tags":[
        "blast"
    ],
    "wof:name":"Ross Valley Sand Blasting",
    "wof:placetype":"venue"
},
  "geometry": {"coordinates":[-2.383838892,53.7781066895],"type":"Point"}
}