{
  "type": "Feature",
  "properties": {
    "iso:country":"GB",
    "sg:address":"The Quay",
    "sg:city":"Sandwich",
    "sg:classifiers":[
        {
            "category":"Travel",
            "subcategory":"Hotels & Motels",
            "type":"Entertainment"
        }
    ],
    "sg:phone":"+44 1304 613388",
    "sg:postcode":"CT13 9EF",
    "sg:province":"Kent",
    "wof:name":"The Bell Hotel",
    "wof:placetype":"venue"
},
  "geometry": {"coordinates":[1.34205,51.275726],"type":"Point"}
}