{
  "type": "Feature",
  "properties": {
    "iso:country":"GB",
    "sg:address":"55 Braidley Road",
    "sg:city":"Bournemouth",
    "sg:classifiers":[
        {
            "category":"Banks & Credit Unions",
            "subcategory":"Financial Services",
            "type":"Services"
        }
    ],
    "sg:phone":"+44 1202 311331",
    "sg:postcode":"BH2 6JY",
    "sg:province":"Dorset",
    "sg:tags":[
        "adviser",
        "independent"
    ],
    "wof:name":"Independence Assured",
    "wof:placetype":"venue"
},
  "geometry": {"coordinates":[-1.8773260117,50.7265014648],"type":"Point"}
}