{
  "type": "Feature",
  "properties": {
    "iso:country":"GB",
    "sg:address":"4 Winifred Avenue, Earlsdon",
    "sg:city":"Coventry",
    "sg:classifiers":[
        {
            "category":"Personal",
            "subcategory":"Tanning Parlor",
            "type":"Services"
        }
    ],
    "sg:postcode":"CV5 6JS",
    "sg:province":"West Midlands",
    "sg:tags":[
        "sunbeds"
    ],
    "wof:name":"Oasis Sunbeds",
    "wof:placetype":"venue"
},
  "geometry": {"coordinates":[-1.525965,52.396191],"type":"Point"}
}