{
  "type": "Feature",
  "properties": {
    "addr:full":"62-64 Victoria Road East, Thornton Cleveleys Blackpool Lancashire FY5 5HQ",
    "addr:housenumber":"62-64",
    "addr:postcode":"fy5 5hq",
    "addr:street":"Victoria Road East",
    "iso:country":"GB",
    "sg:address":"62-64 Victoria Road East, Thornton Cleveleys",
    "sg:city":"Blackpool",
    "sg:classifiers":[
        {
            "category":"Home & Garden",
            "subcategory":"Hardware",
            "type":"Retail Goods"
        }
    ],
    "sg:phone":"+44 1253 868331",
    "sg:postcode":"FY5 5HQ",
    "sg:province":"Lancashire",
    "sg:tags":[
        "retailer",
        "diy"
    ],
    "wof:name":"Workshop",
    "wof:placetype":"venue"
},
  "geometry": {"coordinates":[-3.002879,53.870556],"type":"Point"}
}