{
  "type": "Feature",
  "properties": {
    "addr:full":"Red House Buntingford Hertfordshire SG9 9AJ",
    "addr:postcode":"sg9 9aj",
    "iso:country":"GB",
    "sg:address":"Red House",
    "sg:city":"Buntingford",
    "sg:classifiers":[
        {
            "category":"Professional",
            "type":"Services"
        }
    ],
    "sg:postcode":"SG9 9AJ",
    "sg:province":"Hertfordshire",
    "sg:tags":[
        "marine"
    ],
    "wof:name":"Chiltern Maritime Ltd.",
    "wof:placetype":"venue"
},
  "geometry": {"coordinates":[-0.0186349992,51.9463005066],"type":"Point"}
}