{
  "type": "Feature",
  "properties": {
    "iso:country":"GB",
    "sg:address":"3 Pembroke Parade, Pembroke Road",
    "sg:city":"Erith",
    "sg:classifiers":[
        {
            "category":"Taxi",
            "type":"Transportation"
        }
    ],
    "sg:phone":"+44 1322 431313",
    "sg:postcode":"DA8 1DB",
    "sg:province":"Kent",
    "sg:tags":[
        "mini",
        "cab"
    ],
    "wof:name":"Car Nation",
    "wof:placetype":"venue"
},
  "geometry": {"coordinates":[0.168451,51.486782],"type":"Point"}
}