{
  "type": "Feature",
  "properties": {
    "addr:full":"613 Romford Road, Manor Park London Greater London E12 5AD",
    "addr:housenumber":"613",
    "addr:postcode":"e12 5ad",
    "addr:street":"Romford Road Manor",
    "iso:country":"GB",
    "sg:address":"613 Romford Road, Manor Park",
    "sg:city":"London",
    "sg:classifiers":[
        {
            "category":"Food & Beverages",
            "subcategory":"Bakery",
            "type":"Retail Goods"
        }
    ],
    "sg:phone":"+44 20 8514 6040",
    "sg:postcode":"E12 5AD",
    "sg:province":"Greater London",
    "sg:tags":[
        "pizza"
    ],
    "wof:name":"Pizza Grove",
    "wof:placetype":"venue"
},
  "geometry": {"coordinates":[0.04266,51.549137],"type":"Point"}
}