{
  "type": "Feature",
  "properties": {
    "addr:full":"6d Canaan Lane Edinburgh City of Edinburgh EH10 4SY",
    "addr:housenumber":"6d",
    "addr:postcode":"eh10 4sy",
    "addr:street":"Canaan Lane",
    "iso:country":"GB",
    "sg:address":"6d Canaan Lane",
    "sg:city":"Edinburgh",
    "sg:classifiers":[
        {
            "category":"Real Estate",
            "subcategory":"Architect",
            "type":"Services"
        }
    ],
    "sg:postcode":"EH10 4SY",
    "sg:province":"City of Edinburgh",
    "wof:name":"Lee Boyd Ltd.",
    "wof:placetype":"venue"
},
  "geometry": {"coordinates":[-3.2083439827,55.9277114868],"type":"Point"}
}