{
  "type": "Feature",
  "properties": {
    "iso:country":"GB",
    "sg:address":"Burns Cottage, Cornhill",
    "sg:city":"Banff",
    "sg:classifiers":[
        {
            "category":"Building & Trades",
            "subcategory":"Construction",
            "type":"Services"
        }
    ],
    "sg:phone":"+44 1466 751671",
    "sg:postcode":"AB45 2DL",
    "sg:province":"Aberdeenshire",
    "sg:tags":[
        "builder"
    ],
    "wof:name":"Murray & Co",
    "wof:placetype":"venue"
},
  "geometry": {"coordinates":[-2.696909,57.611614],"type":"Point"}
}