{
  "type": "Feature",
  "properties": {
    "addr:full":"35 Linnet Close Exeter Devon EX4 5HF",
    "addr:housenumber":"35",
    "addr:postcode":"ex4 5hf",
    "addr:street":"Linnet Close",
    "iso:country":"GB",
    "sg:address":"35 Linnet Close",
    "sg:city":"Exeter",
    "sg:classifiers":[
        {
            "category":"Manufacturing",
            "subcategory":"Petroleum Products",
            "type":"Manufacturing & Wholesale Goods"
        }
    ],
    "sg:phone":"+44 1392 436752",
    "sg:postcode":"EX4 5HF",
    "sg:province":"Devon",
    "sg:tags":[
        "double",
        "glazing"
    ],
    "wof:name":"PR Windows & Conservatories",
    "wof:placetype":"venue"
},
  "geometry": {"coordinates":[-3.519908,50.743839],"type":"Point"}
}