{
  "type": "Feature",
  "properties": {
    "addr:full":"337 North Deeside Road, Peterculter Aberdeen Aberdeen City AB14 0NA",
    "addr:housenumber":"337",
    "addr:postcode":"ab14 0na",
    "addr:street":"North Deeside Road",
    "iso:country":"GB",
    "sg:address":"337 North Deeside Road, Peterculter",
    "sg:city":"Aberdeen",
    "sg:classifiers":[
        {
            "category":"Fast Food",
            "type":"Food & Drink"
        }
    ],
    "sg:phone":"+44 1224 735323",
    "sg:postcode":"AB14 0NA",
    "sg:province":"Aberdeen City",
    "sg:tags":[
        "away",
        "take"
    ],
    "wof:name":"Borsalino Pizzeria",
    "wof:placetype":"venue"
},
  "geometry": {"coordinates":[-2.2641038895,57.0961494446],"type":"Point"}
}