{
  "type": "Feature",
  "properties": {
    "addr:full":"Sterling House, 18 Church Road Teddington Greater London TW11 8PD",
    "addr:housenumber":"18",
    "addr:postcode":"tw11 8pd",
    "addr:street":"Church Road",
    "iso:country":"GB",
    "sg:address":"Sterling House, 18 Church Road",
    "sg:city":"Teddington",
    "sg:classifiers":[
        {
            "category":"Professional",
            "subcategory":"Management & Consulting",
            "type":"Services"
        }
    ],
    "sg:phone":"+44 20 8977 9776",
    "sg:postcode":"TW11 8PD",
    "sg:province":"Greater London",
    "sg:tags":[
        "marketing",
        "consultant"
    ],
    "wof:name":"Projectlink Motivation Ltd.",
    "wof:placetype":"venue"
},
  "geometry": {"coordinates":[-0.3371819854,51.4272079468],"type":"Point"}
}