{
  "type": "Feature",
  "properties": {
    "iso:country":"GB",
    "sg:address":"Robert Runcie Ct, 2 Bucknell Clo",
    "sg:city":"Brixton",
    "sg:classifiers":[
        {
            "category":"Wholesale",
            "subcategory":"Apparel",
            "type":"Manufacturing & Wholesale Goods"
        }
    ],
    "sg:phone":"+44 20 7737 2219",
    "sg:postcode":"SW2 5SR",
    "sg:province":"Greater London",
    "sg:tags":[
        "babywear",
        "childrens"
    ],
    "wof:name":"Right Price Trading Co",
    "wof:placetype":"venue"
},
  "geometry": {"coordinates":[-0.121929,51.452366],"type":"Point"}
}