{
  "type": "Feature",
  "properties": {
    "iso:country":"GB",
    "sg:address":"Strongs Bank, Holbeach Fen, Holbeach",
    "sg:city":"Spalding",
    "sg:classifiers":[
        {
            "category":"Farming",
            "subcategory":"Farm",
            "type":"Manufacturing & Wholesale Goods"
        }
    ],
    "sg:phone":"+44 1406 540265",
    "sg:postcode":"PE12 8PJ",
    "sg:province":"Cambridgeshire",
    "sg:tags":[
        "mixed",
        "crop"
    ],
    "wof:name":"J A Sells",
    "wof:placetype":"venue"
},
  "geometry": {"coordinates":[0.0207250006,52.7763404846],"type":"Point"}
}