{
  "type": "Feature",
  "properties": {
    "addr:full":"34 Beckman Road Stourbridge West Midlands DY9 0TZ",
    "addr:housenumber":"34",
    "addr:postcode":"dy9 0tz",
    "addr:street":"Beckman Road",
    "iso:country":"GB",
    "sg:address":"34 Beckman Road",
    "sg:city":"Stourbridge",
    "sg:classifiers":[
        {
            "category":"Building & Trades",
            "subcategory":"Construction",
            "type":"Services"
        }
    ],
    "sg:phone":"+44 1562 885764",
    "sg:postcode":"DY9 0TZ",
    "sg:province":"West Midlands",
    "sg:tags":[
        "builder"
    ],
    "wof:name":"Carl J Shields",
    "wof:placetype":"venue"
},
  "geometry": {"coordinates":[-2.1279859543,52.4405212402],"type":"Point"}
}