{
  "type": "Feature",
  "properties": {
    "iso:country":"GB",
    "sg:address":"Wern Farm",
    "sg:city":"Bagillt",
    "sg:classifiers":[
        {
            "category":"Farming",
            "subcategory":"Livestock Farm",
            "type":"Manufacturing & Wholesale Goods"
        },
        {
            "category":"Farming",
            "subcategory":"Farm",
            "type":"Manufacturing & Wholesale Goods"
        }
    ],
    "sg:postcode":"CH6 6BY",
    "sg:province":"Flintshire",
    "sg:tags":[
        "mixed",
        "crop",
        "others"
    ],
    "wof:name":"Edward Gwilym Hughes",
    "wof:placetype":"venue"
},
  "geometry": {"coordinates":[-3.171054,53.268921],"type":"Point"}
}