{
  "type": "Feature",
  "properties": {
    "iso:country":"GB",
    "sg:address":"Troed Y Rhiw, Glas Pwll",
    "sg:city":"Machynlleth",
    "sg:classifiers":[
        {
            "category":"Farming",
            "subcategory":"Livestock Farm",
            "type":"Manufacturing & Wholesale Goods"
        }
    ],
    "sg:phone":"+44 1654 703172",
    "sg:postcode":"SY20 8TU",
    "sg:province":"Ceredigion",
    "sg:tags":[
        "others"
    ],
    "wof:name":"Gareth Evans",
    "wof:placetype":"venue"
},
  "geometry": {"coordinates":[-3.8467230797,52.5909614563],"type":"Point"}
}