{
  "type": "Feature",
  "properties": {
    "iso:country":"GB",
    "sg:address":"21 Vale Street, Upper Gornal",
    "sg:city":"Dudley",
    "sg:classifiers":[
        {
            "category":"Bars & Pubs",
            "type":"Food & Drink"
        }
    ],
    "sg:phone":"+44 1902 673414",
    "sg:postcode":"DY3 3XD",
    "sg:province":"Staffordshire",
    "sg:tags":[
        "pubs",
        "inn"
    ],
    "wof:name":"Ken & Diana Flannery",
    "wof:placetype":"venue"
},
  "geometry": {"coordinates":[-2.120645,52.5308],"type":"Point"}
}