{
  "type": "Feature",
  "properties": {
    "addr:full":"Hillesdon Road, Gawcott Buckingham Buckinghamshire MK18 4JF",
    "addr:postcode":"mk18 4jf",
    "addr:street":"Hillesdon Road",
    "iso:country":"GB",
    "sg:address":"Hillesdon Road, Gawcott",
    "sg:city":"Buckingham",
    "sg:classifiers":[
        {
            "category":"Bars & Pubs",
            "type":"Food & Drink"
        }
    ],
    "sg:phone":"+44 1280 816267",
    "sg:postcode":"MK18 4JF",
    "sg:province":"Buckinghamshire",
    "sg:tags":[
        "pubs",
        "inn"
    ],
    "wof:name":"K & B Rae",
    "wof:placetype":"venue"
},
  "geometry": {"coordinates":[-1.010549,51.981285],"type":"Point"}
}