{
  "type": "Feature",
  "properties": {
    "iso:country":"GB",
    "sg:address":"55 Trezaise Rd",
    "sg:city":"St Austell",
    "sg:classifiers":[
        {
            "category":"Building & Trades",
            "subcategory":"Equipment Rental",
            "type":"Services"
        }
    ],
    "sg:phone":"+44 1726 890800",
    "sg:postcode":"PL26 8HD",
    "sg:province":"Cornwall",
    "sg:tags":[
        "plant",
        "machinery"
    ],
    "wof:name":"P Warren",
    "wof:placetype":"venue"
},
  "geometry": {"coordinates":[-4.831235,50.400322],"type":"Point"}
}