{
  "type": "Feature",
  "properties": {
    "addr:full":"17 Brook Street, Bampton Tiverton Devon EX16 9LU",
    "addr:housenumber":"17",
    "addr:postcode":"ex16 9lu",
    "addr:street":"Brook Street",
    "iso:country":"GB",
    "sg:address":"17 Brook Street, Bampton",
    "sg:city":"Tiverton",
    "sg:classifiers":[
        {
            "category":"Food & Beverages",
            "subcategory":"Meat & Fish",
            "type":"Retail Goods"
        },
        {
            "category":"Food & Beverages",
            "subcategory":"Groceries & Convenience Stores",
            "type":"Retail Goods"
        }
    ],
    "sg:phone":"+44 1398 331969",
    "sg:postcode":"EX16 9LU",
    "sg:province":"Devon",
    "sg:tags":[
        "shop",
        "chip"
    ],
    "wof:name":"Bampton Fish Bar",
    "wof:placetype":"venue"
},
  "geometry": {"coordinates":[-3.4855940342,50.9903106689],"type":"Point"}
}