{
  "type": "Feature",
  "properties": {
    "iso:country":"GB",
    "sg:address":"3-5 Dartford Road",
    "sg:city":"March",
    "sg:classifiers":[
        {
            "category":"Shopping",
            "subcategory":"Gifts & Souvenirs",
            "type":"Retail Goods"
        }
    ],
    "sg:postcode":"PE15 8LA",
    "sg:province":"Cambridgeshire",
    "sg:tags":[
        "shop"
    ],
    "wof:name":"Marietta's Emporium",
    "wof:placetype":"venue"
},
  "geometry": {"coordinates":[0.0881400034,52.5513114929],"type":"Point"}
}