{
  "type": "Feature",
  "properties": {
    "iso:country":"GB",
    "sg:address":"18 Birch Gro, Hook",
    "sg:city":"Basingstoke",
    "sg:classifiers":[
        {
            "category":"Real Estate",
            "subcategory":"Architect",
            "type":"Services"
        }
    ],
    "sg:postcode":"RG27 9RJ",
    "sg:province":"Berkshire",
    "wof:name":"John Robertson Architect",
    "wof:placetype":"venue"
},
  "geometry": {"coordinates":[-0.9607700109,51.2854881287],"type":"Point"}
}