{
  "type": "Feature",
  "properties": {
    "addr:full":"The College Bakery, 85 College Street St Helens Merseyside WA10 1TP",
    "addr:housenumber":"85",
    "addr:postcode":"wa10 1tp",
    "addr:street":"College Street",
    "iso:country":"GB",
    "sg:address":"The College Bakery, 85 College Street",
    "sg:city":"St Helens",
    "sg:classifiers":[
        {
            "category":"Food & Beverages",
            "subcategory":"Bakery",
            "type":"Retail Goods"
        },
        {
            "category":"Farming",
            "subcategory":"Farm",
            "type":"Manufacturing & Wholesale Goods"
        }
    ],
    "sg:phone":"+44 1744 455500",
    "sg:postcode":"WA10 1TP",
    "sg:province":"Merseyside",
    "sg:tags":[
        "mixed",
        "baker",
        "crop"
    ],
    "wof:name":"John Pimblett & Sons Ltd.",
    "wof:placetype":"venue"
},
  "geometry": {"coordinates":[-2.738868,53.451687],"type":"Point"}
}