{
  "type": "Feature",
  "properties": {
    "iso:country":"GB",
    "sg:address":"Old Post Office, Llandeloy",
    "sg:city":"Haverfordwest",
    "sg:classifiers":[
        {
            "category":"Shopping",
            "subcategory":"Hobbies, Toys, & Games",
            "type":"Retail Goods"
        }
    ],
    "sg:phone":"+44 1348 831678",
    "sg:postcode":"SA62 6LJ",
    "sg:province":"Pembrokeshire",
    "sg:tags":[
        "stamp"
    ],
    "wof:name":"Mart Stamps",
    "wof:placetype":"venue"
},
  "geometry": {"coordinates":[-5.1159591675,51.8984107971],"type":"Point"}
}