{
  "type": "Feature",
  "properties": {
    "iso:country":"GB",
    "sg:address":"3 Town Square",
    "sg:city":"Bracknell",
    "sg:classifiers":[
        {
            "category":"Professional",
            "subcategory":"Art Services",
            "type":"Services"
        }
    ],
    "sg:phone":"+44 1344 423779",
    "sg:postcode":"RG12 1AT",
    "sg:province":"Berkshire",
    "sg:tags":[
        "photographer"
    ],
    "wof:name":"Photus Ltd.",
    "wof:placetype":"venue"
},
  "geometry": {"coordinates":[-0.7484899759,51.417930603],"type":"Point"}
}