{
  "type": "Feature",
  "properties": {
    "iso:country":"GB",
    "sg:address":"Belmont Road",
    "sg:city":"St Austell",
    "sg:classifiers":[
        {
            "category":"Banks & Credit Unions",
            "subcategory":"Atm",
            "type":"Services"
        }
    ],
    "sg:phone":"+44 1726 72864",
    "sg:postcode":"PL25 4UJ",
    "sg:province":"Cornwall",
    "sg:tags":[
        "carburettor"
    ],
    "wof:name":"R A E",
    "wof:placetype":"venue"
},
  "geometry": {"coordinates":[-4.788204,50.336552],"type":"Point"}
}