{
  "type": "Feature",
  "properties": {
    "iso:country":"GB",
    "sg:address":"19 Albert Road",
    "sg:city":"Morecambe",
    "sg:classifiers":[
        {
            "category":"Fast Food",
            "type":"Food & Drink"
        }
    ],
    "sg:postcode":"LA4 4HD",
    "sg:province":"Lancashire",
    "sg:tags":[
        "away",
        "take"
    ],
    "wof:name":"New Dragon Town",
    "wof:placetype":"venue"
},
  "geometry": {"coordinates":[-2.8788590431,54.0663223267],"type":"Point"}
}