{
  "type": "Feature",
  "properties": {
    "iso:country":"GB",
    "sg:address":"17a Queensway Trading Estate",
    "sg:city":"Leamington Spa",
    "sg:classifiers":[
        {
            "category":"Professional",
            "subcategory":"Printing & Photocopies",
            "type":"Services"
        }
    ],
    "sg:phone":"+44 1926 431331",
    "sg:postcode":"CV31 3LZ",
    "sg:province":"Warwickshire",
    "sg:tags":[
        "printer"
    ],
    "wof:name":"Welton Print Ltd.",
    "wof:placetype":"venue"
},
  "geometry": {"coordinates":[-1.542754,52.279362],"type":"Point"}
}