{
  "type": "Feature",
  "properties": {
    "iso:country":"GB",
    "sg:address":"The Firs, Heath Lane, Tedburn St Mary",
    "sg:city":"Exeter",
    "sg:classifiers":[
        {
            "category":"Manufacturing",
            "subcategory":"Jewelry",
            "type":"Manufacturing & Wholesale Goods"
        },
        {
            "category":"Building & Trades",
            "subcategory":"Construction",
            "type":"Services"
        }
    ],
    "sg:postcode":"EX6 6AG",
    "sg:province":"Devon",
    "sg:tags":[
        "joinery",
        "jewellery",
        "repair"
    ],
    "wof:name":"Peter Doxsey",
    "wof:placetype":"venue"
},
  "geometry": {"coordinates":[-3.63918,50.729839],"type":"Point"}
}