{
  "type": "Feature",
  "properties": {
    "addr:full":"Wycham The Heath, Appledore Ashford Kent TN26 2BB",
    "addr:postcode":"tn26 2bb",
    "iso:country":"GB",
    "sg:address":"Wycham The Heath, Appledore",
    "sg:city":"Ashford",
    "sg:classifiers":[
        {
            "category":"Shopping",
            "subcategory":"Used Merchandise",
            "type":"Retail Goods"
        }
    ],
    "sg:phone":"+44 1233 758342",
    "sg:postcode":"TN26 2BB",
    "sg:province":"Kent",
    "sg:tags":[
        "shop",
        "second-hand"
    ],
    "wof:name":"Alan W Walford",
    "wof:placetype":"venue"
},
  "geometry": {"coordinates":[0.7893610001,51.0296821594],"type":"Point"}
}