{
  "type": "Feature",
  "properties": {
    "addr:full":"P O Box 5098 Bromsgrove Worcestershire B61 9BD",
    "addr:housenumber":"p o;5098",
    "addr:postcode":"b61 9bd",
    "iso:country":"GB",
    "sg:address":"P O Box 5098",
    "sg:city":"Bromsgrove",
    "sg:classifiers":[
        {
            "category":"Shopping",
            "subcategory":"Bicycles & Sporting Goods",
            "type":"Retail Goods"
        }
    ],
    "sg:phone":"+44 1527 870044",
    "sg:postcode":"B61 9BD",
    "sg:province":"Worcestershire",
    "sg:tags":[
        "cycle",
        "accessory"
    ],
    "wof:name":"Brunel Leisure Products Ltd.",
    "wof:placetype":"venue"
},
  "geometry": {"coordinates":[-2.090359,52.35585],"type":"Point"}
}