{
  "type": "Feature",
  "properties": {
    "addr:full":"33 Kelvin Road North Glasgow Falkirk G67 2BD",
    "addr:housenumber":"33",
    "addr:postcode":"g67 2bd",
    "addr:street":"Kelvin Road North",
    "iso:country":"GB",
    "sg:address":"33 Kelvin Road North",
    "sg:city":"Glasgow",
    "sg:classifiers":[
        {
            "category":"Professional",
            "subcategory":"Printing & Photocopies",
            "type":"Services"
        }
    ],
    "sg:postcode":"G67 2BD",
    "sg:province":"Falkirk",
    "sg:tags":[
        "printer"
    ],
    "wof:name":"Paw Print",
    "wof:placetype":"venue"
},
  "geometry": {"coordinates":[-3.981165,55.939968],"type":"Point"}
}