{
  "type": "Feature",
  "properties": {
    "iso:country":"GB",
    "sg:address":"30-32 Bank Top, Southowran",
    "sg:city":"Halifax",
    "sg:classifiers":[
        {
            "category":"Food & Beverages",
            "subcategory":"Liquor & Beverages",
            "type":"Retail Goods"
        }
    ],
    "sg:phone":"+44 1422 353676",
    "sg:postcode":"HX3 9NJ",
    "sg:province":"West Yorkshire",
    "sg:tags":[
        "beer",
        "spirit",
        "wines"
    ],
    "wof:name":"J & B Whitham",
    "wof:placetype":"venue"
},
  "geometry": {"coordinates":[-1.841898,53.715691],"type":"Point"}
}