{
  "type": "Feature",
  "properties": {
    "addr:full":"3rd Floor, 42-46 Frederick Place Brighton East Sussex BN1 2RE",
    "addr:housenumber":"3rd floor 42-46",
    "addr:postcode":"bn1 2re",
    "addr:street":"Frederick Place",
    "iso:country":"GB",
    "sg:address":"3rd Floor, 42-46 Frederick Place",
    "sg:city":"Brighton",
    "sg:classifiers":[
        {
            "category":"Manufacturing",
            "subcategory":"Tools & Machinery",
            "type":"Manufacturing & Wholesale Goods"
        }
    ],
    "sg:phone":"+44 1273 323636",
    "sg:postcode":"BN1 2RE",
    "sg:province":"East Sussex",
    "sg:tags":[
        "society",
        "friendly"
    ],
    "wof:name":"Cunningham Ellis And Buckle",
    "wof:placetype":"venue"
},
  "geometry": {"coordinates":[-0.1411699951,50.8264465332],"type":"Point"}
}