{
  "type": "Feature",
  "properties": {
    "addr:full":"Unit 37, Britannia Way, Britannia Enterprise Park Lichfield Staffordshire WS14 9UY",
    "addr:housenumber":"unit 37",
    "addr:postcode":"ws14 9uy",
    "addr:street":"Britannia Way;Enterprise Park",
    "iso:country":"GB",
    "sg:address":"Unit 37, Britannia Way, Britannia Enterprise Park",
    "sg:city":"Lichfield",
    "sg:classifiers":[
        {
            "category":"Education",
            "subcategory":"Special Training",
            "type":"Public Place"
        }
    ],
    "sg:postcode":"WS14 9UY",
    "sg:province":"Staffordshire",
    "sg:tags":[
        "product",
        "centre"
    ],
    "wof:name":"Mechatronics International Ltd.",
    "wof:placetype":"venue"
},
  "geometry": {"coordinates":[-1.8019720316,52.68542099],"type":"Point"}
}