{
  "type": "Feature",
  "properties": {
    "addr:full":"Tegfan, Castle Caereinion Welshpool Shropshire SY21 9AY",
    "addr:postcode":"sy21 9ay",
    "addr:street":"Caereinion",
    "iso:country":"GB",
    "sg:address":"Tegfan, Castle Caereinion",
    "sg:city":"Welshpool",
    "sg:classifiers":[
        {
            "category":"Building & Trades",
            "subcategory":"Construction",
            "type":"Services"
        }
    ],
    "sg:phone":"+44 1938 850273",
    "sg:postcode":"SY21 9AY",
    "sg:province":"Shropshire",
    "sg:tags":[
        "builder"
    ],
    "wof:name":"D Davies",
    "wof:placetype":"venue"
},
  "geometry": {"coordinates":[-3.1452031136,52.661190033],"type":"Point"}
}