{
  "type": "Feature",
  "properties": {
    "addr:full":"60 Fort Road Newhaven East Sussex BN9 9EJ",
    "addr:housenumber":"60",
    "addr:postcode":"bn9 9ej",
    "addr:street":"Fort Road",
    "iso:country":"GB",
    "sg:address":"60 Fort Road",
    "sg:city":"Newhaven",
    "sg:classifiers":[
        {
            "category":"Arena",
            "subcategory":"Sports Club",
            "type":"Entertainment"
        }
    ],
    "sg:postcode":"BN9 9EJ",
    "sg:province":"East Sussex",
    "wof:name":"Blue Frog Ski Club",
    "wof:placetype":"venue"
},
  "geometry": {"coordinates":[0.05142,50.789261],"type":"Point"}
}