{
  "type": "Feature",
  "properties": {
    "iso:country":"GB",
    "sg:address":"154a College Road, Crosby",
    "sg:city":"Liverpool",
    "sg:classifiers":[
        {
            "category":"Shopping",
            "subcategory":"Gifts & Souvenirs",
            "type":"Retail Goods"
        }
    ],
    "sg:phone":"+44 151 284 4624",
    "sg:postcode":"L23 3DP",
    "sg:province":"Merseyside",
    "sg:tags":[
        "shop",
        "poster",
        "card"
    ],
    "wof:name":"Wishing Well",
    "wof:placetype":"venue"
},
  "geometry": {"coordinates":[-3.03294,53.486401],"type":"Point"}
}