{
  "type": "Feature",
  "properties": {
    "addr:full":"West Street Congleton Cheshire CW12 1JR",
    "addr:postcode":"cw12 1jr",
    "addr:street":"West Street",
    "iso:country":"GB",
    "sg:address":"West Street",
    "sg:city":"Congleton",
    "sg:classifiers":[
        {
            "category":"Autos & Motor Vehicles",
            "subcategory":"Automobile Sales",
            "type":"Retail Goods"
        }
    ],
    "sg:phone":"+44 1260 278800",
    "sg:postcode":"CW12 1JR",
    "sg:province":"Cheshire",
    "sg:tags":[
        "car",
        "commercial"
    ],
    "wof:name":"Ray Street Motors",
    "wof:placetype":"venue"
},
  "geometry": {"coordinates":[-2.2205140591,53.1645393372],"type":"Point"}
}