{
  "type": "Feature",
  "properties": {
    "iso:country":"GB",
    "sg:address":"3 Imperial Road, Bordesley Grn",
    "sg:city":"Birmingham",
    "sg:classifiers":[
        {
            "category":"Building & Trades",
            "subcategory":"Construction",
            "type":"Services"
        }
    ],
    "sg:postcode":"B9 5HB",
    "sg:province":"West Midlands",
    "sg:tags":[
        "builder"
    ],
    "wof:name":"Imperial Maintenance",
    "wof:placetype":"venue"
},
  "geometry": {"coordinates":[-1.8494,52.474785],"type":"Point"}
}