{
  "type": "Feature",
  "properties": {
    "iso:country":"GB",
    "sg:address":"319 South Norwood Hill",
    "sg:city":"South Norwood",
    "sg:classifiers":[
        {
            "category":"Autos & Motor Vehicles",
            "subcategory":"Fuel & Gas Station",
            "type":"Retail Goods"
        }
    ],
    "sg:phone":"+44 20 8653 4202",
    "sg:postcode":"SE25 6BS",
    "sg:province":"Greater London",
    "sg:tags":[
        "hr",
        "petrol"
    ],
    "wof:name":"Texaco Service Station",
    "wof:placetype":"venue"
},
  "geometry": {"coordinates":[-0.086739,51.40929],"type":"Point"}
}