{
  "type": "Feature",
  "properties": {
    "addr:full":"8 Charles Rd Salisbury Hampshire SP4 8EA",
    "addr:housenumber":"8",
    "addr:postcode":"sp4 8ea",
    "addr:street":"Charles Rd",
    "iso:country":"GB",
    "sg:address":"8 Charles Rd",
    "sg:city":"Salisbury",
    "sg:classifiers":[
        {
            "category":"Building & Trades",
            "subcategory":"Cleaning & Sanitation",
            "type":"Services"
        }
    ],
    "sg:phone":"+44 1980 652644",
    "sg:postcode":"SP4 8EA",
    "sg:province":"Hampshire",
    "sg:tags":[
        "sweep",
        "chimney"
    ],
    "wof:name":"W Flint",
    "wof:placetype":"venue"
},
  "geometry": {"coordinates":[-1.775962,51.197525],"type":"Point"}
}