{
  "type": "Feature",
  "properties": {
    "addr:full":"Carlisle Street East Sheffield South Yorkshire S4 7QN",
    "addr:postcode":"s4 7qn",
    "addr:street":"Carlisle Street East",
    "iso:country":"GB",
    "sg:address":"Carlisle Street East",
    "sg:city":"Sheffield",
    "sg:classifiers":[
        {
            "category":"Bars & Pubs",
            "type":"Food & Drink"
        }
    ],
    "sg:postcode":"S4 7QN",
    "sg:province":"South Yorkshire",
    "sg:tags":[
        "pubs",
        "inn"
    ],
    "wof:name":"The Carlisle Hotel",
    "wof:placetype":"venue"
},
  "geometry": {"coordinates":[-1.447544,53.396381],"type":"Point"}
}