{
  "type": "Feature",
  "properties": {
    "addr:full":"940 Stratford Road, Sparkhill Birmingham West Midlands B11 4BU",
    "addr:housenumber":"940",
    "addr:postcode":"b11 4bu",
    "addr:street":"Stratford Road",
    "iso:country":"GB",
    "sg:address":"940 Stratford Road, Sparkhill",
    "sg:city":"Birmingham",
    "sg:classifiers":[
        {
            "category":"Food & Beverages",
            "subcategory":"Bakery",
            "type":"Retail Goods"
        }
    ],
    "sg:phone":"+44 121 777 3427",
    "sg:postcode":"B11 4BU",
    "sg:province":"West Midlands",
    "sg:tags":[
        "shop",
        "baker",
        "confectionery"
    ],
    "sg:website":"http://www.druckers.co.uk",
    "wof:name":"Druckers Vienna Patisserie",
    "wof:placetype":"venue"
},
  "geometry": {"coordinates":[-1.8564389944,52.4434089661],"type":"Point"}
}