{
  "type": "Feature",
  "properties": {
    "addr:full":"Unit 365 Walton Summit, Four Oaks Road, Bamber Bridge Preston Lancashire PR5 8AS",
    "addr:housenumber":"365",
    "addr:postcode":"pr5 8as",
    "addr:street":"Walton Summit Four Oaks Road",
    "iso:country":"GB",
    "sg:address":"Unit 365 Walton Summit, Four Oaks Road, Bamber Bridge",
    "sg:city":"Preston",
    "sg:classifiers":[
        {
            "category":"Shopping",
            "subcategory":"Pharmacy",
            "type":"Retail Goods"
        }
    ],
    "sg:phone":"+44 1772 629461",
    "sg:postcode":"PR5 8AS",
    "sg:province":"Lancashire",
    "sg:tags":[
        "medical"
    ],
    "wof:name":"Vernon-Carus Ltd.",
    "wof:placetype":"venue"
},
  "geometry": {"coordinates":[-2.6454529762,53.7195892334],"type":"Point"}
}