{
  "type": "Feature",
  "properties": {
    "iso:country":"GB",
    "sg:address":"2a Caudle Street, High Street",
    "sg:city":"Henfield",
    "sg:classifiers":[
        {
            "category":"Shopping",
            "subcategory":"Pets & Pet Supplies",
            "type":"Retail Goods"
        }
    ],
    "sg:phone":"+44 1273 493809",
    "sg:postcode":"BN5 9DB",
    "sg:province":"West Sussex",
    "wof:name":"R & H Pet Supplies",
    "wof:placetype":"venue"
},
  "geometry": {"coordinates":[-0.272289,50.931419],"type":"Point"}
}