{
  "type": "Feature",
  "properties": {
    "iso:country":"GB",
    "sg:address":"The Workshop, Main Road, Wensley",
    "sg:city":"Matlock",
    "sg:classifiers":[
        {
            "category":"Shopping",
            "subcategory":"Antiques",
            "type":"Retail Goods"
        }
    ],
    "sg:phone":"+44 1629 734826",
    "sg:postcode":"DE4 2LH",
    "sg:province":"Derbyshire",
    "wof:name":"Stephen Simmons & Helen Miles",
    "wof:placetype":"venue"
},
  "geometry": {"coordinates":[-1.606864,53.146847],"type":"Point"}
}