{
  "type": "Feature",
  "properties": {
    "iso:country":"GB",
    "sg:address":"The Smithy, Edstaston",
    "sg:city":"Shrewsbury",
    "sg:classifiers":[
        {
            "category":"Professional",
            "subcategory":"Engineering",
            "type":"Services"
        },
        {
            "category":"Building & Trades",
            "subcategory":"Construction",
            "type":"Services"
        }
    ],
    "sg:phone":"+44 1939 232671",
    "sg:postcode":"SY4 5RG",
    "sg:province":"Shropshire",
    "sg:tags":[
        "builder",
        "engineer",
        "structural"
    ],
    "wof:name":"P E Wheeler & Son",
    "wof:placetype":"venue"
},
  "geometry": {"coordinates":[-2.729105,52.854366],"type":"Point"}
}