{
  "type": "Feature",
  "properties": {
    "iso:country":"GB",
    "sg:address":"South Street, Mintlaw",
    "sg:city":"Peterhead",
    "sg:classifiers":[
        {
            "category":"Autos & Motor Vehicles",
            "subcategory":"Fuel & Gas Station",
            "type":"Retail Goods"
        }
    ],
    "sg:phone":"+44 1771 623602",
    "sg:postcode":"AB42 5EL",
    "sg:province":"Aberdeenshire",
    "sg:tags":[
        "petrol",
        "filling"
    ],
    "wof:name":"Mintlaw Service Station",
    "wof:placetype":"venue"
},
  "geometry": {"coordinates":[-2.003859,57.525181],"type":"Point"}
}