{
  "type": "Feature",
  "properties": {
    "addr:full":"1 Whitleigh Avenue, Crownhill Plymouth Devon PL5 3BQ",
    "addr:housenumber":"1",
    "addr:postcode":"pl5 3bq",
    "addr:street":"Whitleigh Avenue",
    "iso:country":"GB",
    "sg:address":"1 Whitleigh Avenue, Crownhill",
    "sg:city":"Plymouth",
    "sg:classifiers":[
        {
            "category":"Shopping",
            "subcategory":"Stationery & Office Supplies",
            "type":"Retail Goods"
        }
    ],
    "sg:phone":"+44 1752 704769",
    "sg:postcode":"PL5 3BQ",
    "sg:province":"Devon",
    "sg:tags":[
        "recording",
        "machine",
        "time"
    ],
    "wof:name":"K Lorenc",
    "wof:placetype":"venue"
},
  "geometry": {"coordinates":[-4.136382103,50.4101409912],"type":"Point"}
}