{
  "type": "Feature",
  "properties": {
    "iso:country":"GB",
    "sg:address":"Vista Garage, Vista Road",
    "sg:city":"Newton-le-willows",
    "sg:classifiers":[
        {
            "category":"Autos & Motor Vehicles",
            "subcategory":"Automobile Sales",
            "type":"Retail Goods"
        },
        {
            "category":"Autos & Motor Vehicles",
            "subcategory":"Auto Supplies",
            "type":"Retail Goods"
        }
    ],
    "sg:phone":"+44 1925 225000",
    "sg:postcode":"WA12 9ER",
    "sg:province":"Cheshire",
    "sg:tags":[
        "car",
        "tyre"
    ],
    "wof:name":"Vista Car World Ltd.",
    "wof:placetype":"venue"
},
  "geometry": {"coordinates":[-2.632649,53.456444],"type":"Point"}
}