{
  "type": "Feature",
  "properties": {
    "addr:full":"128a Upper Brockley Rd Brockley Greater London SE4 1SS",
    "addr:housenumber":"128a",
    "addr:postcode":"se4 1ss",
    "addr:street":"Upper Brockley Rd",
    "iso:country":"GB",
    "sg:address":"128a Upper Brockley Rd",
    "sg:city":"Brockley",
    "sg:classifiers":[
        {
            "category":"Social Services",
            "subcategory":"Job Training",
            "type":"Services"
        }
    ],
    "sg:phone":"+44 20 8469 3360",
    "sg:postcode":"SE4 1SS",
    "sg:province":"Greater London",
    "sg:tags":[
        "translator",
        "interpreter"
    ],
    "wof:name":"B. Olivier French Translator",
    "wof:placetype":"venue"
},
  "geometry": {"coordinates":[-0.0338889994,51.4672279358],"type":"Point"}
}