{
  "type": "Feature",
  "properties": {
    "addr:full":"Springfield, Rookery Hill Ashtead Surrey KT21 1HY",
    "addr:postcode":"kt21 1hy",
    "addr:street":"Rookery Hill",
    "iso:country":"GB",
    "sg:address":"Springfield, Rookery Hill",
    "sg:city":"Ashtead",
    "sg:classifiers":[
        {
            "category":"Manufacturing",
            "subcategory":"Metals",
            "type":"Manufacturing & Wholesale Goods"
        }
    ],
    "sg:phone":"+44 1372 278181",
    "sg:postcode":"KT21 1HY",
    "sg:province":"Surrey",
    "sg:tags":[
        "industry",
        "f-a"
    ],
    "wof:name":"Sps Ltd.",
    "wof:placetype":"venue"
},
  "geometry": {"coordinates":[-0.300947994,51.3088989258],"type":"Point"}
}