{
  "type": "Feature",
  "properties": {
    "iso:country":"GB",
    "sg:address":"94 Station Road, Chingford",
    "sg:city":"London",
    "sg:classifiers":[
        {
            "category":"Shopping",
            "type":"Retail Goods"
        }
    ],
    "sg:postcode":"E4 7BA",
    "sg:province":"Greater London",
    "sg:tags":[
        "part",
        "accessory"
    ],
    "wof:name":"Ash Autoparts & Cycles",
    "wof:placetype":"venue"
},
  "geometry": {"coordinates":[0.007727,51.632874],"type":"Point"}
}