{
  "type": "Feature",
  "properties": {
    "addr:full":"Westview Hockley Essex SS5 4SS",
    "addr:postcode":"ss5 4ss",
    "addr:street":"Hockley",
    "iso:country":"GB",
    "sg:address":"Westview",
    "sg:city":"Hockley",
    "sg:classifiers":[
        {
            "category":"Shopping",
            "subcategory":"Party Supplies",
            "type":"Retail Goods"
        }
    ],
    "sg:postcode":"SS5 4SS",
    "sg:province":"Essex",
    "sg:tags":[
        "inflatables",
        "bouncy",
        "castle"
    ],
    "wof:name":"Camelot Castles",
    "wof:placetype":"venue"
},
  "geometry": {"coordinates":[0.655723,51.600704],"type":"Point"}
}