{
  "type": "Feature",
  "properties": {
    "iso:country":"GB",
    "sg:address":"North Road, Bridgend Industrial Estate",
    "sg:city":"Bridgend",
    "sg:classifiers":[
        {
            "category":"Shopping",
            "subcategory":"Computers & Home Electronics",
            "type":"Retail Goods"
        }
    ],
    "sg:phone":"+44 1656 768777",
    "sg:postcode":"CF31 3TP",
    "sg:province":"Bridgend",
    "sg:tags":[
        "hi-fi",
        "equipment",
        "mnfr"
    ],
    "wof:name":"Rel Acoustics Ltd.",
    "wof:placetype":"venue"
},
  "geometry": {"coordinates":[-3.5395190716,51.5042686462],"type":"Point"}
}