{
  "type": "Feature",
  "properties": {
    "iso:country":"GB",
    "sg:address":"164-166 High Street",
    "sg:city":"Rayleigh",
    "sg:classifiers":[
        {
            "category":"Professional",
            "subcategory":"Printing & Photocopies",
            "type":"Services"
        }
    ],
    "sg:phone":"+44 1268 775088",
    "sg:postcode":"SS6 7BS",
    "sg:province":"Essex",
    "sg:tags":[
        "printer"
    ],
    "wof:name":"Colour Leaflets Ltd.",
    "wof:placetype":"venue"
},
  "geometry": {"coordinates":[0.600869,51.5834503174],"type":"Point"}
}