{
  "type": "Feature",
  "properties": {
    "addr:full":"Unit 19 Borough Fields Shoping C, Entre, Wotton Bassett Swindon Wiltshire SN4 7AX",
    "addr:housenumber":"unit 19",
    "addr:postcode":"sn4 7ax",
    "addr:street":"Borough;Entre Wotton",
    "iso:country":"GB",
    "sg:address":"Unit 19 Borough Fields Shoping C, Entre, Wotton Bassett",
    "sg:city":"Swindon",
    "sg:classifiers":[
        {
            "category":"Shopping",
            "subcategory":"Pharmacy",
            "type":"Retail Goods"
        }
    ],
    "sg:phone":"+44 1793 852472",
    "sg:postcode":"SN4 7AX",
    "sg:province":"Wiltshire",
    "sg:tags":[
        "pharmacist",
        "dispensing",
        "chemist"
    ],
    "wof:name":"Lloyds Pharmacy",
    "wof:placetype":"venue"
},
  "geometry": {"coordinates":[-1.9019540548,51.5436897278],"type":"Point"}
}