{
  "type": "Feature",
  "properties": {
    "iso:country":"GB",
    "sg:address":"Red Wood, Swallowfield Road, Arborfield",
    "sg:city":"Reading",
    "sg:classifiers":[
        {
            "category":"Professional",
            "subcategory":"Engineering",
            "type":"Services"
        }
    ],
    "sg:phone":"+44 118 976 1040",
    "sg:postcode":"RG2 9JY",
    "sg:province":"Berkshire",
    "sg:tags":[
        "consulting",
        "engineer"
    ],
    "wof:name":"Peter Graham Associates",
    "wof:placetype":"venue"
},
  "geometry": {"coordinates":[-0.920774,51.401566],"type":"Point"}
}