{
  "type": "Feature",
  "properties": {
    "iso:country":"GB",
    "sg:address":"Rosewood Est, Shedden Park Rd",
    "sg:city":"Kelso",
    "sg:classifiers":[
        {
            "category":"Building & Trades",
            "subcategory":"Construction",
            "type":"Services"
        }
    ],
    "sg:postcode":"TD5 7PY",
    "sg:province":"Scottish Borders",
    "sg:tags":[
        "monumental",
        "mason"
    ],
    "wof:name":"Tate,Angus,",
    "wof:placetype":"venue"
},
  "geometry": {"coordinates":[-2.433349,55.597576],"type":"Point"}
}