{
  "type": "Feature",
  "properties": {
    "addr:full":"Blackford Primary School, Blackford Wedmore Somerset BS28 4NX",
    "addr:postcode":"bs28 4nx",
    "addr:street":"Blackford",
    "iso:country":"GB",
    "sg:address":"Blackford Primary School, Blackford",
    "sg:city":"Wedmore",
    "sg:classifiers":[
        {
            "category":"Shopping",
            "subcategory":"Used Merchandise",
            "type":"Retail Goods"
        }
    ],
    "sg:phone":"+44 1934 712372",
    "sg:postcode":"BS28 4NX",
    "sg:province":"Somerset",
    "sg:tags":[
        "shop",
        "second-hand"
    ],
    "wof:name":"L D Watts",
    "wof:placetype":"venue"
},
  "geometry": {"coordinates":[-2.81016,51.227631],"type":"Point"}
}