{
  "type": "Feature",
  "properties": {
    "iso:country":"GB",
    "sg:address":"16 Yorkshire Street",
    "sg:city":"Burnley",
    "sg:classifiers":[
        {
            "category":"Organizations",
            "subcategory":"Non-profit Organization",
            "type":"Services"
        }
    ],
    "sg:phone":"+44 1282 423980",
    "sg:postcode":"BB11 2DY",
    "sg:province":"Lancashire",
    "sg:tags":[
        "organisation",
        "voluntary",
        "charity"
    ],
    "wof:name":"Barnardo's",
    "wof:placetype":"venue"
},
  "geometry": {"coordinates":[-2.239156,53.789436],"type":"Point"}
}