{
  "type": "Feature",
  "properties": {
    "addr:full":"1 Concord House, Speculation Place Washington Tyne and Wear NE37 2AS",
    "addr:housenumber":"1",
    "addr:postcode":"ne37 2as",
    "addr:street":"Concord;Speculation Place",
    "iso:country":"GB",
    "sg:address":"1 Concord House, Speculation Place",
    "sg:city":"Washington",
    "sg:classifiers":[
        {
            "category":"Recreation",
            "subcategory":"Dog Park",
            "type":"Entertainment"
        }
    ],
    "sg:phone":"+44 191 416 5001",
    "sg:postcode":"NE37 2AS",
    "sg:province":"Tyne and Wear",
    "wof:name":"The Dog House",
    "wof:placetype":"venue"
},
  "geometry": {"coordinates":[-1.51994,54.91206],"type":"Point"}
}