{
  "type": "Feature",
  "properties": {
    "iso:country":"GB",
    "sg:address":"337 Holyhead Road",
    "sg:city":"Coventry",
    "sg:classifiers":[
        {
            "category":"Professional",
            "subcategory":"Detective & Security Services",
            "type":"Services"
        },
        {
            "category":"Building & Trades",
            "subcategory":"Electrical",
            "type":"Services"
        }
    ],
    "sg:phone":"+44 24 7659 4204",
    "sg:postcode":"CV5 8LD",
    "sg:province":"West Midlands",
    "sg:tags":[
        "burglar",
        "alarm",
        "electrician",
        "system",
        "contractor"
    ],
    "wof:name":"Classic Alarms Ltd",
    "wof:placetype":"venue"
},
  "geometry": {"coordinates":[-1.5367889404,52.4157524109],"type":"Point"}
}