{
  "type": "Feature",
  "properties": {
    "addr:full":"Granville, Newton Toney Salisbury Hampshire SP4 0HF",
    "addr:postcode":"sp4 0hf",
    "iso:country":"GB",
    "sg:address":"Granville, Newton Toney",
    "sg:city":"Salisbury",
    "sg:classifiers":[
        {
            "category":"Professional",
            "type":"Services"
        }
    ],
    "sg:phone":"+44 1980 629672",
    "sg:postcode":"SP4 0HF",
    "sg:province":"Hampshire",
    "sg:tags":[
        "writer"
    ],
    "wof:name":"Robin Kerrod",
    "wof:placetype":"venue"
},
  "geometry": {"coordinates":[-1.69153,51.161049],"type":"Point"}
}