{
  "type": "Feature",
  "properties": {
    "addr:full":"Room 7a Cerdic House, The Docks Felixstowe Suffolk IP11 3TX",
    "addr:housenumber":"7a cerdic house the",
    "addr:postcode":"ip11 3tx",
    "iso:country":"GB",
    "sg:address":"Room 7a Cerdic House, The Docks",
    "sg:city":"Felixstowe",
    "sg:classifiers":[
        {
            "category":"Freight",
            "type":"Transportation"
        }
    ],
    "sg:phone":"+44 1394 675267",
    "sg:postcode":"IP11 3TX",
    "sg:province":"Suffolk",
    "sg:tags":[
        "forwarders"
    ],
    "wof:name":"Contisped Ltd.",
    "wof:placetype":"venue"
},
  "geometry": {"coordinates":[1.3424650431,51.9613685608],"type":"Point"}
}