{
  "type": "Feature",
  "properties": {
    "addr:full":"Greenfoot Lane Barnsley South Yorkshire S75 1EG",
    "addr:postcode":"s75 1eg",
    "addr:street":"Greenfoot Lane;Yorkshire",
    "iso:country":"GB",
    "sg:address":"Greenfoot Lane",
    "sg:city":"Barnsley",
    "sg:classifiers":[
        {
            "category":"Education",
            "subcategory":"School",
            "type":"Public Place"
        }
    ],
    "sg:phone":"+44 1226 205364",
    "sg:postcode":"S75 1EG",
    "sg:province":"South Yorkshire",
    "sg:tags":[
        "local",
        "authority"
    ],
    "wof:name":"Wilthorpe Junior School",
    "wof:placetype":"venue"
},
  "geometry": {"coordinates":[-1.4947459698,53.565032959],"type":"Point"}
}