{
  "type": "Feature",
  "properties": {
    "addr:full":"12 Front Street, Colliery Row Houghton-le-spring Durham DH4 6LP",
    "addr:housenumber":"12",
    "addr:postcode":"dh4 6lp",
    "addr:street":"Front Street Colliery Row",
    "iso:country":"GB",
    "sg:address":"12 Front Street, Colliery Row",
    "sg:city":"Houghton-le-spring",
    "sg:classifiers":[
        {
            "category":"Personal",
            "subcategory":"Beauty Salon",
            "type":"Services"
        }
    ],
    "sg:phone":"+44 191 385 3305",
    "sg:postcode":"DH4 6LP",
    "sg:province":"Durham",
    "sg:tags":[
        "unisex",
        "hairdresser"
    ],
    "wof:name":"Janis Hairstylists",
    "wof:placetype":"venue"
},
  "geometry": {"coordinates":[-1.495845,54.841709],"type":"Point"}
}