{
  "type": "Feature",
  "properties": {
    "iso:country":"GB",
    "sg:address":"Talbot Road",
    "sg:city":"Glossop",
    "sg:classifiers":[
        {
            "category":"Education",
            "subcategory":"School",
            "type":"Public Place"
        }
    ],
    "sg:phone":"+44 1457 852006",
    "sg:postcode":"SK13 7DP",
    "sg:province":"Derbyshire",
    "sg:tags":[
        "local",
        "authority"
    ],
    "wof:name":"Talbot House",
    "wof:placetype":"venue"
},
  "geometry": {"coordinates":[-1.950859,53.449642],"type":"Point"}
}