{
  "type": "Feature",
  "properties": {
    "addr:full":"10 Oak Street Fakenham Norfolk NR21 9EH",
    "addr:housenumber":"10",
    "addr:postcode":"nr21 9eh",
    "addr:street":"Oak Street",
    "iso:country":"GB",
    "sg:address":"10 Oak Street",
    "sg:city":"Fakenham",
    "sg:classifiers":[
        {
            "category":"Banks & Credit Unions",
            "subcategory":"Financial Services",
            "type":"Services"
        }
    ],
    "sg:postcode":"NR21 9EH",
    "sg:province":"Norfolk",
    "sg:tags":[
        "consultant"
    ],
    "wof:name":"Fakenham Preservation Trust",
    "wof:placetype":"venue"
},
  "geometry": {"coordinates":[0.846764,52.830875],"type":"Point"}
}