{
  "type": "Feature",
  "properties": {
    "addr:full":"32 West End Arcade Nottingham Nottinghamshire NG1 6JP",
    "addr:housenumber":"32",
    "addr:postcode":"ng1 6jp",
    "addr:street":"West End Arcade",
    "iso:country":"GB",
    "sg:address":"32 West End Arcade",
    "sg:city":"Nottingham",
    "sg:classifiers":[
        {
            "category":"Home & Garden",
            "subcategory":"Kitchen Supply",
            "type":"Retail Goods"
        }
    ],
    "sg:postcode":"NG1 6JP",
    "sg:province":"Nottinghamshire",
    "sg:tags":[
        "brewing"
    ],
    "wof:name":"Eezee Brewing",
    "wof:placetype":"venue"
},
  "geometry": {"coordinates":[-1.1535589695,52.9540901184],"type":"Point"}
}