{
  "type": "Feature",
  "properties": {
    "addr:full":"The Quadrangle, Ruchill St, Maryhill Glasgow Glasgow City G20 9PX",
    "addr:postcode":"g20 9px",
    "addr:street":"St",
    "iso:country":"GB",
    "sg:address":"The Quadrangle, Ruchill St, Maryhill",
    "sg:city":"Glasgow",
    "sg:classifiers":[
        {
            "category":"Professional",
            "subcategory":"Art Services",
            "type":"Services"
        }
    ],
    "sg:postcode":"G20 9PX",
    "sg:province":"Glasgow City",
    "sg:tags":[
        "photographer"
    ],
    "wof:name":"McLean,Ron,",
    "wof:placetype":"venue"
},
  "geometry": {"coordinates":[-4.2829799652,55.8871612549],"type":"Point"}
}