{
  "type": "Feature",
  "properties": {
    "addr:full":"31 High Street, Dodworth Barnsley South Yorkshire S75 3RF",
    "addr:housenumber":"31",
    "addr:postcode":"s75 3rf",
    "addr:street":"High Street;Yorkshire",
    "iso:country":"GB",
    "sg:address":"31 High Street, Dodworth",
    "sg:city":"Barnsley",
    "sg:classifiers":[
        {
            "category":"Home & Garden",
            "subcategory":"Household Appliances",
            "type":"Retail Goods"
        }
    ],
    "sg:phone":"+44 1226 200110",
    "sg:postcode":"S75 3RF",
    "sg:province":"South Yorkshire",
    "sg:tags":[
        "electrical"
    ],
    "wof:name":"Dodworth Domestic",
    "wof:placetype":"venue"
},
  "geometry": {"coordinates":[-1.5247490406,53.5423965454],"type":"Point"}
}