{
  "type": "Feature",
  "properties": {
    "addr:full":"Group Medical Practice, The Health Centre, Kersiebank Av Grangemouth Falkirk FK3 9EL",
    "addr:postcode":"fk3 9el",
    "addr:street":"Av Grangemouth",
    "iso:country":"GB",
    "sg:address":"Group Medical Practice, The Health Centre, Kersiebank Av",
    "sg:city":"Grangemouth",
    "sg:classifiers":[
        {
            "category":"Health Services",
            "subcategory":"Doctor",
            "type":"Services"
        }
    ],
    "sg:phone":"+44 1324 471511",
    "sg:postcode":"FK3 9EL",
    "sg:province":"Falkirk",
    "sg:tags":[
        "practitioners"
    ],
    "wof:name":"Selfridge, D I",
    "wof:placetype":"venue"
},
  "geometry": {"coordinates":[-3.71085,56.011211],"type":"Point"}
}