{
  "type": "Feature",
  "properties": {
    "iso:country":"GB",
    "sg:address":"5-7 West Craibstone Street",
    "sg:city":"Aberdeen",
    "sg:classifiers":[
        {
            "category":"Organizations",
            "subcategory":"Community Association",
            "type":"Services"
        },
        {
            "category":"Organizations",
            "subcategory":"Membership Organization",
            "type":"Services"
        }
    ],
    "sg:phone":"+44 1224 591250",
    "sg:postcode":"AB11 6DL",
    "sg:province":"Aberdeen City",
    "sg:tags":[
        "club",
        "social"
    ],
    "wof:name":"R U A Masonic Social Club",
    "wof:placetype":"venue"
},
  "geometry": {"coordinates":[-2.107452,57.142475],"type":"Point"}
}