{
  "type": "Feature",
  "properties": {
    "iso:country":"GB",
    "sg:address":"Holydean Farm Cottages",
    "sg:city":"Melrose",
    "sg:classifiers":[
        {
            "category":"Real Estate",
            "subcategory":"Developer",
            "type":"Services"
        },
        {
            "category":"Real Estate",
            "subcategory":"Real Estate Agent",
            "type":"Services"
        }
    ],
    "sg:phone":"+44 1835 822642",
    "sg:postcode":"TD6 9HT",
    "sg:province":"Scottish Borders",
    "sg:tags":[
        "property"
    ],
    "wof:name":"Medlaw Properties Ltd.",
    "wof:placetype":"venue"
},
  "geometry": {"coordinates":[-2.737578,55.598831],"type":"Point"}
}