{
  "type": "Feature",
  "properties": {
    "addr:full":"13 Lakey Lane Birmingham West Midlands B28 9DU",
    "addr:housenumber":"13",
    "addr:postcode":"b28 9du",
    "addr:street":"Lakey Lane",
    "iso:country":"GB",
    "sg:address":"13 Lakey Lane",
    "sg:city":"Birmingham",
    "sg:classifiers":[
        {
            "category":"Shopping",
            "subcategory":"Computers & Home Electronics",
            "type":"Retail Goods"
        }
    ],
    "sg:phone":"+44 121 778 4653",
    "sg:postcode":"B28 9DU",
    "sg:province":"West Midlands",
    "sg:tags":[
        "electrical"
    ],
    "wof:name":"Hall Green Electrical Supplies",
    "wof:placetype":"venue"
},
  "geometry": {"coordinates":[-1.8399569988,52.4324874878],"type":"Point"}
}