{
  "type": "Feature",
  "properties": {
    "addr:full":"12 Church Street London Greater London E15 3HX",
    "addr:housenumber":"12",
    "addr:postcode":"e15 3hx",
    "addr:street":"Church Street",
    "iso:country":"GB",
    "sg:address":"12 Church Street",
    "sg:city":"London",
    "sg:classifiers":[
        {
            "category":"Professional",
            "subcategory":"Employment Agencies",
            "type":"Services"
        }
    ],
    "sg:postcode":"E15 3HX",
    "sg:province":"Greater London",
    "sg:tags":[
        "consultant"
    ],
    "wof:name":"Choice Employment",
    "wof:placetype":"venue"
},
  "geometry": {"coordinates":[0.007889,51.536209],"type":"Point"}
}