{
  "type": "Feature",
  "properties": {
    "iso:country":"GB",
    "sg:address":"Irish Street",
    "sg:city":"Maryport",
    "sg:classifiers":[
        {
            "category":"Bars & Pubs",
            "type":"Food & Drink"
        }
    ],
    "sg:postcode":"CA15 8AD",
    "sg:province":"Cumbria",
    "sg:tags":[
        "pubs",
        "inn"
    ],
    "wof:name":"Leo's",
    "wof:placetype":"venue"
},
  "geometry": {"coordinates":[-3.5018489361,54.7147445679],"type":"Point"}
}