{
  "type": "Feature",
  "properties": {
    "addr:full":"The Country Warehouse Warminster Somerset BA12 8AP",
    "addr:postcode":"ba12 8ap",
    "iso:country":"GB",
    "sg:address":"The Country Warehouse",
    "sg:city":"Warminster",
    "sg:classifiers":[
        {
            "category":"Shopping",
            "subcategory":"Baby Store",
            "type":"Retail Goods"
        }
    ],
    "sg:phone":"+44 1985 846882",
    "sg:postcode":"BA12 8AP",
    "sg:province":"Somerset",
    "sg:tags":[
        "nursery",
        "accessory"
    ],
    "wof:name":"Options",
    "wof:placetype":"venue"
},
  "geometry": {"coordinates":[-2.182784,51.208809],"type":"Point"}
}