{
  "type": "Feature",
  "properties": {
    "addr:full":"Foresters Ho, 2 King St King's Lynn Norfolk PE30 1ES",
    "addr:housenumber":"2",
    "addr:postcode":"pe30 1es",
    "addr:street":"King St",
    "iso:country":"GB",
    "sg:address":"Foresters Ho, 2 King St",
    "sg:city":"King's Lynn",
    "sg:classifiers":[
        {
            "category":"Shopping",
            "subcategory":"Mobile Phones",
            "type":"Retail Goods"
        }
    ],
    "sg:phone":"+44 1553 777777",
    "sg:postcode":"PE30 1ES",
    "sg:province":"Norfolk",
    "wof:name":"Frog Cellular",
    "wof:placetype":"venue"
},
  "geometry": {"coordinates":[0.3934310079,52.754032135],"type":"Point"}
}