{
  "type": "Feature",
  "properties": {
    "addr:full":"Unit 4 Alder Hills Industrial Estate, Parkstone Poole Dorset BH12 4AR",
    "addr:housenumber":"unit 4;estate",
    "addr:postcode":"bh12 4ar",
    "addr:street":"Alder Hills Industrial",
    "iso:country":"GB",
    "sg:address":"Unit 4 Alder Hills Industrial Estate, Parkstone",
    "sg:city":"Poole",
    "sg:classifiers":[
        {
            "category":"Wholesale",
            "subcategory":"Photographic Equipment",
            "type":"Manufacturing & Wholesale Goods"
        },
        {
            "category":"Shopping",
            "subcategory":"Photographic Equipment",
            "type":"Retail Goods"
        }
    ],
    "sg:phone":"+44 1202 723046",
    "sg:postcode":"BH12 4AR",
    "sg:province":"Dorset",
    "sg:tags":[
        "supply"
    ],
    "wof:name":"Robert White Photographic Ltd",
    "wof:placetype":"venue"
},
  "geometry": {"coordinates":[-1.914404,50.7402],"type":"Point"}
}