{
  "type": "Feature",
  "properties": {
    "iso:country":"GB",
    "sg:address":"24 Marsden Green",
    "sg:city":"Welwyn Garden City",
    "sg:classifiers":[
        {
            "category":"Social Services",
            "subcategory":"Job Training",
            "type":"Services"
        }
    ],
    "sg:phone":"+44 1707 332871",
    "sg:postcode":"AL8 6YA",
    "sg:province":"Hertfordshire",
    "sg:tags":[
        "translator",
        "interpreter"
    ],
    "wof:name":"German Translations",
    "wof:placetype":"venue"
},
  "geometry": {"coordinates":[-0.2190500051,51.7929191589],"type":"Point"}
}