{
  "type": "Feature",
  "properties": {
    "addr:full":"Cossington St Leicester Leicestershire LE4 6JD",
    "addr:postcode":"le4 6jd",
    "addr:street":"Cossington St",
    "iso:country":"GB",
    "sg:address":"Cossington St",
    "sg:city":"Leicester",
    "sg:classifiers":[
        {
            "category":"Social Services",
            "type":"Services"
        },
        {
            "category":"Education",
            "subcategory":"Library",
            "type":"Public Place"
        }
    ],
    "sg:phone":"+44 116 299 5500",
    "sg:postcode":"LE4 6JD",
    "sg:province":"Leicestershire",
    "sg:tags":[
        "book"
    ],
    "wof:name":"Belgrave Library",
    "wof:placetype":"venue"
},
  "geometry": {"coordinates":[-1.121078968,52.6509094238],"type":"Point"}
}