{
  "type": "Feature",
  "properties": {
    "iso:country":"GB",
    "sg:address":"17 Upminster Road South",
    "sg:city":"Rainham",
    "sg:classifiers":[
        {
            "category":"Manufacturing",
            "subcategory":"Signs",
            "type":"Manufacturing & Wholesale Goods"
        }
    ],
    "sg:phone":"+44 1708 500055",
    "sg:postcode":"RM13 9YS",
    "sg:province":"Essex",
    "sg:tags":[
        "writer"
    ],
    "wof:name":"Vinyl Graf-X",
    "wof:placetype":"venue"
},
  "geometry": {"coordinates":[0.1912270039,51.5186271667],"type":"Point"}
}