{
  "type": "Feature",
  "properties": {
    "addr:full":"65 St Edmunds Church Street Salisbury Wiltshire SP1 1EF",
    "addr:housenumber":"65",
    "addr:postcode":"sp1 1ef",
    "addr:street":"St;Church Street",
    "iso:country":"GB",
    "sg:address":"65 St Edmunds Church Street",
    "sg:city":"Salisbury",
    "sg:classifiers":[
        {
            "category":"Professional",
            "subcategory":"Computer Services",
            "type":"Services"
        }
    ],
    "sg:postcode":"SP1 1EF",
    "sg:province":"Wiltshire",
    "sg:tags":[
        "system",
        "software"
    ],
    "wof:name":"Ten Systems Ltd.",
    "wof:placetype":"venue"
},
  "geometry": {"coordinates":[-1.792419,51.071102],"type":"Point"}
}