{
  "type": "Feature",
  "properties": {
    "addr:full":"The Shipyard, Ashlake Copse Road, Fishbourne Ryde Isle of Wight PO33 4EY",
    "addr:postcode":"po33 4ey",
    "addr:street":"Ashlake Copse Road",
    "iso:country":"GB",
    "sg:address":"The Shipyard, Ashlake Copse Road, Fishbourne",
    "sg:city":"Ryde",
    "sg:classifiers":[
        {
            "category":"Autos & Motor Vehicles",
            "subcategory":"Boat Sales",
            "type":"Retail Goods"
        }
    ],
    "sg:phone":"+44 1983 882200",
    "sg:postcode":"PO33 4EY",
    "sg:province":"Isle of Wight",
    "sg:tags":[
        "repair",
        "builder"
    ],
    "wof:name":"Aluminium Shipbuilders Ltd.",
    "wof:placetype":"venue"
},
  "geometry": {"coordinates":[-1.2135070562,50.7317199707],"type":"Point"}
}