{
  "type": "Feature",
  "properties": {
    "iso:country":"GB",
    "sg:address":"Trinity Way, Trinity Park",
    "sg:city":"Enfield",
    "sg:classifiers":[
        {
            "category":"Shopping",
            "subcategory":"Stationery & Office Supplies",
            "type":"Retail Goods"
        }
    ],
    "sg:phone":"+44 1992 653007",
    "sg:postcode":"EN9 1EJ",
    "sg:province":"Essex",
    "sg:tags":[
        "equipment"
    ],
    "wof:name":"Tecnico",
    "wof:placetype":"venue"
},
  "geometry": {"coordinates":[0.00014,51.68671],"type":"Point"}
}