{
  "type": "Feature",
  "properties": {
    "addr:full":"402 Palatine Road, Northenden Manchester Greater Manchester M22 4FZ",
    "addr:housenumber":"402",
    "addr:postcode":"m22 4fz",
    "addr:street":"Palatine Road",
    "iso:country":"GB",
    "sg:address":"402 Palatine Road, Northenden",
    "sg:city":"Manchester",
    "sg:classifiers":[
        {
            "category":"Banks & Credit Unions",
            "subcategory":"Bank",
            "type":"Services"
        }
    ],
    "sg:phone":"+44 161 251 3000",
    "sg:postcode":"M22 4FZ",
    "sg:province":"Greater Manchester",
    "wof:name":"Barclays Bank Plc",
    "wof:placetype":"venue"
},
  "geometry": {"coordinates":[-2.2590329647,53.407459259],"type":"Point"}
}