{
  "type": "Feature",
  "properties": {
    "addr:full":"Old Farm Way, Crossways Dorchester Dorset DT2 8TU",
    "addr:postcode":"dt2 8tu",
    "addr:street":"Old Farm Way",
    "iso:country":"GB",
    "sg:address":"Old Farm Way, Crossways",
    "sg:city":"Dorchester",
    "sg:classifiers":[
        {
            "category":"Organizations",
            "subcategory":"Community Association",
            "type":"Services"
        },
        {
            "category":"Organizations",
            "subcategory":"Membership Organization",
            "type":"Services"
        }
    ],
    "sg:phone":"+44 1305 852266",
    "sg:postcode":"DT2 8TU",
    "sg:province":"Dorset",
    "sg:tags":[
        "club",
        "social"
    ],
    "wof:name":"Tavern Social Club",
    "wof:placetype":"venue"
},
  "geometry": {"coordinates":[-2.3265089989,50.6948356628],"type":"Point"}
}