{
  "type": "Feature",
  "properties": {
    "addr:full":"2 Pittville Street Edinburgh City of Edinburgh EH15 2BY",
    "addr:housenumber":"2",
    "addr:postcode":"eh15 2by",
    "addr:street":"Pittville Street",
    "iso:country":"GB",
    "sg:address":"2 Pittville Street",
    "sg:city":"Edinburgh",
    "sg:classifiers":[
        {
            "category":"Travel",
            "subcategory":"Hotels & Motels",
            "type":"Entertainment"
        }
    ],
    "sg:postcode":"EH15 2BY",
    "sg:province":"City of Edinburgh",
    "sg:tags":[
        "house",
        "guest"
    ],
    "wof:name":"Portobello House",
    "wof:placetype":"venue"
},
  "geometry": {"coordinates":[-3.106218,55.951942],"type":"Point"}
}