{
  "type": "Feature",
  "properties": {
    "addr:full":"239 Petersham Rd, Corner Of Sandy La Richmond Greater London TW10 7DA",
    "addr:housenumber":"239",
    "addr:postcode":"tw10 7da",
    "addr:street":"Petersham Rd Corner Of Sandy La Richmond",
    "iso:country":"GB",
    "sg:address":"239 Petersham Rd, Corner Of Sandy La",
    "sg:city":"Richmond",
    "sg:classifiers":[
        {
            "category":"Health Services",
            "subcategory":"Dentist",
            "type":"Services"
        }
    ],
    "sg:phone":"+44 20 8940 4747",
    "sg:postcode":"TW10 7DA",
    "sg:province":"Greater London",
    "wof:name":"Carmel Coombs",
    "wof:placetype":"venue"
},
  "geometry": {"coordinates":[-0.3041949868,51.4404754639],"type":"Point"}
}