{
  "type": "Feature",
  "properties": {
    "iso:country":"GB",
    "sg:address":"5 Sevenoaks Rd",
    "sg:city":"Sevenoaks",
    "sg:classifiers":[
        {
            "category":"Restaurant",
            "type":"Food & Drink"
        }
    ],
    "sg:phone":"+44 1732 886868",
    "sg:postcode":"TN15 8AX",
    "sg:province":"Kent",
    "sg:tags":[
        "indian"
    ],
    "wof:name":"Planet Spice",
    "wof:placetype":"venue"
},
  "geometry": {"coordinates":[0.304288,51.291492],"type":"Point"}
}