{
  "type": "Feature",
  "properties": {
    "addr:full":"Grange Primary School, Grange Road, Monifieth Dundee Angus DD5 4LU",
    "addr:postcode":"dd5 4lu",
    "addr:street":"Grange Road",
    "iso:country":"GB",
    "sg:address":"Grange Primary School, Grange Road, Monifieth",
    "sg:city":"Dundee",
    "sg:classifiers":[
        {
            "category":"Government",
            "subcategory":"Office",
            "type":"Public Place"
        }
    ],
    "sg:phone":"+44 1382 534795",
    "sg:postcode":"DD5 4LU",
    "sg:province":"Angus",
    "sg:tags":[
        "local",
        "agency",
        "education",
        "authority"
    ],
    "wof:name":"Monifeith Community Education Service Base",
    "wof:placetype":"venue"
},
  "geometry": {"coordinates":[-2.8200309277,56.4804039001],"type":"Point"}
}