{
  "type": "Feature",
  "properties": {
    "addr:full":"18-20 Bradwells Court Cambridge Cambridgeshire CB1 1NH",
    "addr:housenumber":"18-20",
    "addr:postcode":"cb1 1nh",
    "addr:street":"Bradwells Court",
    "iso:country":"GB",
    "sg:address":"18-20 Bradwells Court",
    "sg:city":"Cambridge",
    "sg:classifiers":[
        {
            "category":"Shopping",
            "subcategory":"News",
            "type":"Retail Goods"
        }
    ],
    "sg:phone":"+44 1223 350185",
    "sg:postcode":"CB1 1NH",
    "sg:province":"Cambridgeshire",
    "sg:tags":[
        "newsagent"
    ],
    "wof:name":"United News Shops Ltd.",
    "wof:placetype":"venue"
},
  "geometry": {"coordinates":[0.12333,52.2052],"type":"Point"}
}