{
  "type": "Feature",
  "properties": {
    "iso:country":"GB",
    "sg:address":"362 High Street, Methil",
    "sg:city":"Leven",
    "sg:classifiers":[
        {
            "category":"Home & Garden",
            "subcategory":"Furniture",
            "type":"Retail Goods"
        }
    ],
    "sg:postcode":"KY8 3EE",
    "sg:province":"Fife",
    "wof:name":"Thomas T Webster Ltd.",
    "wof:placetype":"venue"
},
  "geometry": {"coordinates":[-3.020397,56.18034],"type":"Point"}
}