{
  "type": "Feature",
  "properties": {
    "iso:country":"GB",
    "sg:address":"91 Mina Road, Walworth",
    "sg:city":"London",
    "sg:classifiers":[
        {
            "category":"Professional",
            "subcategory":"Research",
            "type":"Services"
        }
    ],
    "sg:postcode":"SE17 2QS",
    "sg:province":"Greater London",
    "sg:tags":[
        "market"
    ],
    "wof:name":"Dabhand Enterprises",
    "wof:placetype":"venue"
},
  "geometry": {"coordinates":[-0.0795980021,51.4870300293],"type":"Point"}
}