{
  "type": "Feature",
  "properties": {
    "iso:country":"GB",
    "sg:address":"2 Main Street, Livingston Village",
    "sg:city":"Livingston",
    "sg:classifiers":[
        {
            "category":"Travel",
            "subcategory":"Hotels & Motels",
            "type":"Entertainment"
        }
    ],
    "sg:phone":"+44 1506 413054",
    "sg:postcode":"EH54 7AF",
    "sg:province":"West Lothian",
    "wof:name":"Livingston Inn",
    "wof:placetype":"venue"
},
  "geometry": {"coordinates":[-3.539785,55.88559],"type":"Point"}
}