{
  "type": "Feature",
  "properties": {
    "iso:country":"GB",
    "sg:address":"60 Stenhouse Street",
    "sg:city":"Cowdenbeath",
    "sg:classifiers":[
        {
            "category":"Retail",
            "subcategory":"Veterinary Services",
            "type":"Services"
        }
    ],
    "sg:phone":"+44 1383 611410",
    "sg:postcode":"KY4 9DD",
    "sg:province":"Fife",
    "sg:tags":[
        "surgeon",
        "activity"
    ],
    "wof:name":"Cameron & Greig",
    "wof:placetype":"venue"
},
  "geometry": {"coordinates":[-3.346061,56.111721],"type":"Point"}
}