{
  "type": "Feature",
  "properties": {
    "addr:full":"8 Greatham Road, Findon Valley Worthing West Sussex BN14 0BE",
    "addr:housenumber":"8",
    "addr:postcode":"bn14 0be",
    "addr:street":"Greatham Road",
    "iso:country":"GB",
    "sg:address":"8 Greatham Road, Findon Valley",
    "sg:city":"Worthing",
    "sg:classifiers":[
        {
            "category":"Building & Trades",
            "subcategory":"Construction",
            "type":"Services"
        }
    ],
    "sg:postcode":"BN14 0BE",
    "sg:province":"West Sussex",
    "sg:tags":[
        "decorator",
        "painter"
    ],
    "wof:name":"Brian Stanley",
    "wof:placetype":"venue"
},
  "geometry": {"coordinates":[-0.395684,50.843971],"type":"Point"}
}