{
  "type": "Feature",
  "properties": {
    "addr:full":"Northfield, Matlock Road Belper Derbyshire DE56 1BE",
    "addr:postcode":"de56 1be",
    "addr:street":"Matlock Road",
    "iso:country":"GB",
    "sg:address":"Northfield, Matlock Road",
    "sg:city":"Belper",
    "sg:classifiers":[
        {
            "category":"Home & Garden",
            "subcategory":"Furniture",
            "type":"Retail Goods"
        },
        {
            "category":"Home & Garden",
            "subcategory":"Kitchen Supply",
            "type":"Retail Goods"
        }
    ],
    "sg:phone":"+44 1773 882606",
    "sg:postcode":"DE56 1BE",
    "sg:province":"Derbyshire",
    "sg:tags":[
        "ware"
    ],
    "wof:name":"B & B Products",
    "wof:placetype":"venue"
},
  "geometry": {"coordinates":[-1.4759819508,53.0286102295],"type":"Point"}
}