{
  "type": "Feature",
  "properties": {
    "iso:country":"GB",
    "sg:address":"Blackness Road",
    "sg:city":"Linlithgow",
    "sg:classifiers":[
        {
            "category":"Community Center",
            "subcategory":"Youth",
            "type":"Public Place"
        }
    ],
    "sg:phone":"+44 1506 842214",
    "sg:postcode":"EH49 7JA",
    "sg:province":"Falkirk",
    "sg:tags":[
        "organisation",
        "centre"
    ],
    "wof:name":"Laetare International Youth Centre",
    "wof:placetype":"venue"
},
  "geometry": {"coordinates":[-3.5936360359,55.9791603088],"type":"Point"}
}