{
  "type": "Feature",
  "properties": {
    "addr:full":"249-255 Denman St Central Nottingham Nottinghamshire NG7 3FQ",
    "addr:housenumber":"249-255",
    "addr:postcode":"ng7 3fq",
    "addr:street":"Denman St",
    "iso:country":"GB",
    "sg:address":"249-255 Denman St Central",
    "sg:city":"Nottingham",
    "sg:classifiers":[
        {
            "category":"Shopping",
            "subcategory":"Baby Store",
            "type":"Retail Goods"
        }
    ],
    "sg:postcode":"NG7 3FQ",
    "sg:province":"Nottinghamshire",
    "sg:tags":[
        "nursery",
        "accessory"
    ],
    "wof:name":"Rekha,Prev K,",
    "wof:placetype":"venue"
},
  "geometry": {"coordinates":[-1.171931,52.957954],"type":"Point"}
}