{
  "type": "Feature",
  "properties": {
    "iso:country":"GB",
    "sg:address":"44 High Street, Thornbury",
    "sg:city":"Bristol",
    "sg:classifiers":[
        {
            "category":"Real Estate",
            "subcategory":"Real Estate Agent",
            "type":"Services"
        }
    ],
    "sg:phone":"+44 1454 411505",
    "sg:postcode":"BS35 2AN",
    "sg:province":"Gloucestershire",
    "wof:name":"James Harvey",
    "wof:placetype":"venue"
},
  "geometry": {"coordinates":[-2.526307106,51.6068992615],"type":"Point"}
}