{
  "type": "Feature",
  "properties": {
    "iso:country":"GB",
    "sg:address":"The Parade",
    "sg:city":"Cowes",
    "sg:classifiers":[
        {
            "category":"Organizations",
            "subcategory":"Membership Organization",
            "type":"Services"
        }
    ],
    "sg:phone":"+44 1983 299727",
    "sg:postcode":"PO31 7QS",
    "sg:province":"Isle of Wight",
    "sg:tags":[
        "club",
        "social"
    ],
    "wof:name":"Royal London Yacht Club",
    "wof:placetype":"venue"
},
  "geometry": {"coordinates":[-1.2989230156,50.7653274536],"type":"Point"}
}