{
  "type": "Feature",
  "properties": {
    "addr:full":"17-18 West Street Tavistock Devon PL19 8AN",
    "addr:housenumber":"17-18",
    "addr:postcode":"pl19 8an",
    "addr:street":"West Street",
    "iso:country":"GB",
    "sg:address":"17-18 West Street",
    "sg:city":"Tavistock",
    "sg:classifiers":[
        {
            "category":"Restaurant",
            "type":"Food & Drink"
        }
    ],
    "sg:postcode":"PL19 8AN",
    "sg:province":"Devon",
    "wof:name":"Smashing Pumpkins",
    "wof:placetype":"venue"
},
  "geometry": {"coordinates":[-4.14739,50.549324],"type":"Point"}
}