{
  "type": "Feature",
  "properties": {
    "addr:full":"8 Mostyn Street Llandudno Conwy LL30 2PS",
    "addr:housenumber":"8",
    "addr:postcode":"ll30 2ps",
    "addr:street":"Mostyn Street",
    "iso:country":"GB",
    "sg:address":"8 Mostyn Street",
    "sg:city":"Llandudno",
    "sg:classifiers":[
        {
            "category":"Recreation",
            "subcategory":"Amusement Park",
            "type":"Entertainment"
        },
        {
            "category":"Autos & Motor Vehicles",
            "subcategory":"Boat Sales",
            "type":"Retail Goods"
        }
    ],
    "sg:phone":"+44 1492 860081",
    "sg:postcode":"LL30 2PS",
    "sg:province":"Conwy",
    "sg:tags":[
        "machine",
        "gaming",
        "arcade"
    ],
    "wof:name":"Fifth Avenue",
    "wof:placetype":"venue"
},
  "geometry": {"coordinates":[-3.825321,53.322109],"type":"Point"}
}