{
  "type": "Feature",
  "properties": {
    "addr:full":"Witheys Yard, High Street Stroud Gloucestershire GL5 1AP",
    "addr:postcode":"gl5 1ap",
    "addr:street":"High Street",
    "iso:country":"GB",
    "sg:address":"Witheys Yard, High Street",
    "sg:city":"Stroud",
    "sg:classifiers":[
        {
            "category":"Health Services",
            "subcategory":"Clinic",
            "type":"Services"
        }
    ],
    "sg:postcode":"GL5 1AP",
    "sg:province":"Gloucestershire",
    "sg:tags":[
        "aromatherapy"
    ],
    "wof:name":"Elgiva Tiptaft",
    "wof:placetype":"venue"
},
  "geometry": {"coordinates":[-2.232441,51.744934],"type":"Point"}
}