{
  "type": "Feature",
  "properties": {
    "addr:full":"Landews Meadow, Green Lane Ashford Kent TN25 4BL",
    "addr:postcode":"tn25 4bl",
    "addr:street":"Meadow Green Lane",
    "iso:country":"GB",
    "sg:address":"Landews Meadow, Green Lane",
    "sg:city":"Ashford",
    "sg:classifiers":[
        {
            "category":"Manufacturing",
            "subcategory":"Buildings",
            "type":"Manufacturing & Wholesale Goods"
        }
    ],
    "sg:phone":"+44 1233 740074",
    "sg:postcode":"TN25 4BL",
    "sg:province":"Kent",
    "sg:tags":[
        "framed",
        "timber"
    ],
    "wof:name":"W H Colt Son & Co. Ltd.",
    "wof:placetype":"venue"
},
  "geometry": {"coordinates":[0.86668,51.220798],"type":"Point"}
}