{
  "type": "Feature",
  "properties": {
    "addr:full":"Northgate, Uppingham Oakham Leicestershire LE15 9NX",
    "addr:postcode":"le15 9nx",
    "addr:street":"Northgate",
    "iso:country":"GB",
    "sg:address":"Northgate, Uppingham",
    "sg:city":"Oakham",
    "sg:classifiers":[
        {
            "category":"Professional",
            "subcategory":"Employment Agencies",
            "type":"Services"
        }
    ],
    "sg:phone":"+44 1572 824250",
    "sg:postcode":"LE15 9NX",
    "sg:province":"Leicestershire",
    "sg:tags":[
        "agricultural",
        "advice"
    ],
    "wof:name":"Nfu East Midlands Region",
    "wof:placetype":"venue"
},
  "geometry": {"coordinates":[-0.722652,52.587826],"type":"Point"}
}