{
  "type": "Feature",
  "properties": {
    "addr:full":"128 Wandsworth High St Wandsworth Greater London SW18 4LB",
    "addr:housenumber":"128",
    "addr:postcode":"sw18 4lb",
    "addr:street":"Wandsworth High St",
    "iso:country":"GB",
    "sg:address":"128 Wandsworth High St",
    "sg:city":"Wandsworth",
    "sg:classifiers":[
        {
            "category":"Retail",
            "subcategory":"Car Wash",
            "type":"Services"
        }
    ],
    "sg:phone":"+44 20 8877 9201",
    "sg:postcode":"SW18 4LB",
    "sg:province":"Greater London",
    "sg:tags":[
        "polishing",
        "washing"
    ],
    "wof:name":"Wash and Shine",
    "wof:placetype":"venue"
},
  "geometry": {"coordinates":[-0.1968600005,51.457244873],"type":"Point"}
}