{
  "type": "Feature",
  "properties": {
    "addr:full":"18 Adams Avenue Saltcoats North Ayrshire KA21 6AL",
    "addr:housenumber":"18",
    "addr:postcode":"ka21 6al",
    "addr:street":"Adams Avenue",
    "iso:country":"GB",
    "sg:address":"18 Adams Avenue",
    "sg:city":"Saltcoats",
    "sg:classifiers":[
        {
            "category":"Food & Beverages",
            "subcategory":"Fruits & Vegetables",
            "type":"Retail Goods"
        }
    ],
    "sg:postcode":"KA21 6AL",
    "sg:province":"North Ayrshire",
    "sg:tags":[
        "greengrocer"
    ],
    "wof:name":"Sanghera",
    "wof:placetype":"venue"
},
  "geometry": {"coordinates":[-4.7843599319,55.6443328857],"type":"Point"}
}