{
  "type": "Feature",
  "properties": {
    "addr:full":"25 Horse Fair Banbury Oxfordshire OX16 0AE",
    "addr:housenumber":"25",
    "addr:postcode":"ox16 0ae",
    "addr:street":"Horse Fair",
    "iso:country":"GB",
    "sg:address":"25 Horse Fair",
    "sg:city":"Banbury",
    "sg:classifiers":[
        {
            "category":"Farming",
            "subcategory":"Nursery",
            "type":"Manufacturing & Wholesale Goods"
        }
    ],
    "sg:phone":"+44 1295 259393",
    "sg:postcode":"OX16 0AE",
    "sg:province":"Oxfordshire",
    "sg:tags":[
        "creche"
    ],
    "wof:name":"Fledglings Day Nursery",
    "wof:placetype":"venue"
},
  "geometry": {"coordinates":[-1.339742,52.061302],"type":"Point"}
}