{
  "type": "Feature",
  "properties": {
    "addr:full":"9a Chester Street Mold Denbighshire CH7 1EA",
    "addr:housenumber":"9a",
    "addr:postcode":"ch7 1ea",
    "addr:street":"Chester Street",
    "iso:country":"GB",
    "sg:address":"9a Chester Street",
    "sg:city":"Mold",
    "sg:classifiers":[
        {
            "category":"Manufacturing",
            "subcategory":"Glass & Minerals",
            "type":"Manufacturing & Wholesale Goods"
        }
    ],
    "sg:postcode":"CH7 1EA",
    "sg:province":"Denbighshire",
    "sg:tags":[
        "chalk",
        "stone",
        "slate"
    ],
    "wof:name":"Lloyds Quarries & Sand & Gravel Co. Ltd.",
    "wof:placetype":"venue"
},
  "geometry": {"coordinates":[-3.138173,53.168125],"type":"Point"}
}