{
  "type": "Feature",
  "properties": {
    "iso:country":"GB",
    "sg:address":"5 High Street",
    "sg:city":"Lincoln",
    "sg:classifiers":[
        {
            "category":"Professional",
            "subcategory":"Business Services",
            "type":"Services"
        }
    ],
    "sg:postcode":"LN5 8BG",
    "sg:province":"Lincolnshire",
    "sg:tags":[
        "bookmaker"
    ],
    "wof:name":"Joe Rylatt",
    "wof:placetype":"venue"
},
  "geometry": {"coordinates":[-0.5462049842,53.2154045105],"type":"Point"}
}