{
  "type": "Feature",
  "properties": {
    "addr:full":"6 Wessex Avenue Chichester West Sussex PO20 8NP",
    "addr:housenumber":"6",
    "addr:postcode":"po20 8np",
    "addr:street":"Wessex Avenue",
    "iso:country":"GB",
    "sg:address":"6 Wessex Avenue",
    "sg:city":"Chichester",
    "sg:classifiers":[
        {
            "category":"Home & Garden",
            "subcategory":"Home Furnishings",
            "type":"Retail Goods"
        }
    ],
    "sg:postcode":"PO20 8NP",
    "sg:province":"West Sussex",
    "sg:tags":[
        "patio",
        "furniture"
    ],
    "wof:name":"Plan B Statuary",
    "wof:placetype":"venue"
},
  "geometry": {"coordinates":[-0.8655509949,50.7676506042],"type":"Point"}
}