{
  "type": "Feature",
  "properties": {
    "addr:full":"Thimblemill Rd Smethwick West Midlands B67 5QR",
    "addr:postcode":"b67 5qr",
    "addr:street":"Thimblemill Rd",
    "iso:country":"GB",
    "sg:address":"Thimblemill Rd",
    "sg:city":"Smethwick",
    "sg:classifiers":[
        {
            "category":"Autos & Motor Vehicles",
            "subcategory":"Fuel & Gas Station",
            "type":"Retail Goods"
        }
    ],
    "sg:phone":"+44 121 429 1319",
    "sg:postcode":"B67 5QR",
    "sg:province":"West Midlands",
    "sg:tags":[
        "petrol",
        "filling"
    ],
    "wof:name":"Thimblemill Service Station",
    "wof:placetype":"venue"
},
  "geometry": {"coordinates":[-1.976675,52.481415],"type":"Point"}
}