{
  "type": "Feature",
  "properties": {
    "iso:country":"GB",
    "sg:address":"Marash House, 2-5 Brook Street",
    "sg:city":"Tring",
    "sg:classifiers":[
        {
            "category":"Shopping",
            "subcategory":"Clothing, Apparel, & Fashions",
            "type":"Retail Goods"
        }
    ],
    "sg:postcode":"HP23 5ED",
    "sg:province":"Buckinghamshire",
    "sg:tags":[
        "tie",
        "clothing",
        "neckwear",
        "accessory"
    ],
    "wof:name":"John Gould Neckwear",
    "wof:placetype":"venue"
},
  "geometry": {"coordinates":[-0.658377,51.794785],"type":"Point"}
}