{
  "type": "Feature",
  "properties": {
    "iso:country":"GB",
    "sg:address":"1 Woodrush Close",
    "sg:city":"Taunton",
    "sg:classifiers":[
        {
            "category":"Banks & Credit Unions",
            "subcategory":"Financial Services",
            "type":"Services"
        }
    ],
    "sg:phone":"+44 1823 324278",
    "sg:postcode":"TA1 3XB",
    "sg:province":"Somerset",
    "sg:tags":[
        "adviser"
    ],
    "wof:name":"Worth Financial Planning",
    "wof:placetype":"venue"
},
  "geometry": {"coordinates":[-3.0810289383,51.0028610229],"type":"Point"}
}