{
  "type": "Feature",
  "properties": {
    "iso:country":"GB",
    "sg:address":"11 Crescent Rise",
    "sg:city":"Luton",
    "sg:classifiers":[
        {
            "category":"Manufacturing",
            "subcategory":"Petroleum Products",
            "type":"Manufacturing & Wholesale Goods"
        },
        {
            "category":"Building & Trades",
            "subcategory":"Construction",
            "type":"Services"
        }
    ],
    "sg:phone":"+44 1582 411805",
    "sg:postcode":"LU2 0AT",
    "sg:province":"Bedfordshire",
    "sg:tags":[
        "double",
        "glazing",
        "installers"
    ],
    "wof:name":"Chiltern Home Improvements Ltd.",
    "wof:placetype":"venue"
},
  "geometry": {"coordinates":[-0.4071890116,51.8830604553],"type":"Point"}
}