{
  "type": "Feature",
  "properties": {
    "addr:full":"37 The Shires, Droylsden Manchester Greater Manchester M43 7ER",
    "addr:housenumber":"37",
    "addr:postcode":"m43 7er",
    "addr:street":"The",
    "iso:country":"GB",
    "sg:address":"37 The Shires, Droylsden",
    "sg:city":"Manchester",
    "sg:classifiers":[
        {
            "category":"Recreation",
            "subcategory":"Water Park",
            "type":"Entertainment"
        }
    ],
    "sg:phone":"+44 161 203 5404",
    "sg:postcode":"M43 7ER",
    "sg:province":"Greater Manchester",
    "sg:tags":[
        "keg",
        "drums",
        "cask"
    ],
    "wof:name":"Manchester Drums",
    "wof:placetype":"venue"
},
  "geometry": {"coordinates":[-2.125768,53.488262],"type":"Point"}
}