{
  "type": "Feature",
  "properties": {
    "addr:full":"8 Nelson Road Ilkley North Yorkshire LS29 8HN",
    "addr:housenumber":"8",
    "addr:postcode":"ls29 8hn",
    "addr:street":"Nelson Road",
    "iso:country":"GB",
    "sg:address":"8 Nelson Road",
    "sg:city":"Ilkley",
    "sg:classifiers":[
        {
            "category":"Health Services",
            "subcategory":"Health Practitioner",
            "type":"Services"
        },
        {
            "category":"Shopping",
            "subcategory":"Pharmacy",
            "type":"Retail Goods"
        }
    ],
    "sg:phone":"+44 1943 602177",
    "sg:postcode":"LS29 8HN",
    "sg:province":"North Yorkshire",
    "sg:tags":[
        "medicine",
        "medical",
        "therapy",
        "treatment",
        "alternative"
    ],
    "wof:name":"Ilkley Healing Centre",
    "wof:placetype":"venue"
},
  "geometry": {"coordinates":[-1.819999,53.925823],"type":"Point"}
}