{
  "type": "Feature",
  "properties": {
    "addr:full":"79 Kingsway Avenue Paignton Devon TQ4 7AB",
    "addr:housenumber":"79",
    "addr:postcode":"tq4 7ab",
    "addr:street":"Kingsway Avenue",
    "iso:country":"GB",
    "sg:address":"79 Kingsway Avenue",
    "sg:city":"Paignton",
    "sg:classifiers":[
        {
            "category":"Retail",
            "subcategory":"Veterinary Services",
            "type":"Services"
        }
    ],
    "sg:phone":"+44 1803 843836",
    "sg:postcode":"TQ4 7AB",
    "sg:province":"Devon",
    "sg:tags":[
        "surgeon"
    ],
    "wof:name":"Greenbay Veterinary Surgery",
    "wof:placetype":"venue"
},
  "geometry": {"coordinates":[-3.576159,50.412579],"type":"Point"}
}