{
  "type": "Feature",
  "properties": {
    "addr:full":"Bromley Public Hall, Bow Rd Bow Greater London E3 3AA",
    "addr:postcode":"e3 3aa",
    "addr:street":"Bow Rd",
    "iso:country":"GB",
    "sg:address":"Bromley Public Hall, Bow Rd",
    "sg:city":"Bow",
    "sg:classifiers":[
        {
            "category":"Government",
            "subcategory":"Office",
            "type":"Public Place"
        }
    ],
    "sg:phone":"+44 20 8980 8025",
    "sg:postcode":"E3 3AA",
    "sg:province":"Greater London",
    "sg:tags":[
        "marriage",
        "death",
        "births"
    ],
    "wof:name":"Registration of Births Deaths & Marriages",
    "wof:placetype":"venue"
},
  "geometry": {"coordinates":[-0.0211200006,51.5278511047],"type":"Point"}
}