{
  "type": "Feature",
  "properties": {
    "addr:full":"556-558 Cowbridge Road East Cardiff Cardiff CF5 1BP",
    "addr:housenumber":"556-558",
    "addr:postcode":"cf5 1bp",
    "addr:street":"Cowbridge Road East",
    "iso:country":"GB",
    "sg:address":"556-558 Cowbridge Road East",
    "sg:city":"Cardiff",
    "sg:classifiers":[
        {
            "category":"Autos & Motor Vehicles",
            "subcategory":"Fuel & Gas Station",
            "type":"Retail Goods"
        }
    ],
    "sg:phone":"+44 29 2055 3652",
    "sg:postcode":"CF5 1BP",
    "sg:province":"Cardiff",
    "sg:tags":[
        "hr",
        "petrol"
    ],
    "wof:name":"Red Dragon Service Station",
    "wof:placetype":"venue"
},
  "geometry": {"coordinates":[-3.227067,51.484745],"type":"Point"}
}