{
  "type": "Feature",
  "properties": {
    "iso:country":"GB",
    "sg:address":"20 Cavendish Road",
    "sg:city":"London",
    "sg:classifiers":[
        {
            "category":"Building & Trades",
            "subcategory":"Plumbing",
            "type":"Services"
        }
    ],
    "sg:phone":"+44 20 8803 5339",
    "sg:postcode":"N18 2LS",
    "sg:province":"Greater London",
    "sg:tags":[
        "plumber",
        "heating"
    ],
    "wof:name":"C Berry Plumbing",
    "wof:placetype":"venue"
},
  "geometry": {"coordinates":[-0.054362,51.61396],"type":"Point"}
}