{
  "type": "Feature",
  "properties": {
    "iso:country":"GB",
    "sg:address":"47 Clarence Road",
    "sg:city":"Chesterfield",
    "sg:classifiers":[
        {
            "category":"Organizations",
            "subcategory":"Professional Association",
            "type":"Services"
        }
    ],
    "sg:phone":"+44 1246 211091",
    "sg:postcode":"S40 1LQ",
    "sg:province":"Derbyshire",
    "sg:tags":[
        "union",
        "trade"
    ],
    "wof:name":"National Union of Mineworkers",
    "wof:placetype":"venue"
},
  "geometry": {"coordinates":[-1.434262991,53.2378425598],"type":"Point"}
}