{
  "type": "Feature",
  "properties": {
    "iso:country":"GB",
    "sg:address":"36 St Margarets Road",
    "sg:city":"Eastleigh",
    "sg:classifiers":[
        {
            "category":"Building & Trades",
            "subcategory":"Plumbing",
            "type":"Services"
        }
    ],
    "sg:phone":"+44 23 8061 7635",
    "sg:postcode":"SO50 6DH",
    "sg:province":"Hampshire",
    "sg:tags":[
        "central",
        "heating"
    ],
    "wof:name":"D C Reeves",
    "wof:placetype":"venue"
},
  "geometry": {"coordinates":[-1.338791,50.975197],"type":"Point"}
}