{
  "type": "Feature",
  "properties": {
    "iso:country":"GB",
    "sg:address":"205 Brentwood Road, Herongate",
    "sg:city":"Brentwood",
    "sg:classifiers":[
        {
            "category":"Health Services",
            "subcategory":"Dentist",
            "type":"Services"
        }
    ],
    "sg:phone":"+44 1277 812593",
    "sg:postcode":"CM13 3PH",
    "sg:province":"Essex",
    "sg:tags":[
        "technician",
        "dental"
    ],
    "wof:name":"Amtec Dental Laboratories",
    "wof:placetype":"venue"
},
  "geometry": {"coordinates":[0.351792,51.594982],"type":"Point"}
}