{
  "type": "Feature",
  "properties": {
    "iso:country":"GB",
    "sg:address":"Old Mill Lane",
    "sg:city":"Barnsley",
    "sg:classifiers":[
        {
            "category":"Home & Garden",
            "subcategory":"Hardware",
            "type":"Retail Goods"
        }
    ],
    "sg:phone":"+44 1226 770659",
    "sg:postcode":"S71 1LS",
    "sg:province":"South Yorkshire",
    "sg:tags":[
        "retailer",
        "diy"
    ],
    "wof:name":"Wickes",
    "wof:placetype":"venue"
},
  "geometry": {"coordinates":[-1.478044,53.558071],"type":"Point"}
}