{
  "type": "Feature",
  "properties": {
    "addr:full":"132 Aldsworth Avenue Worthing West Sussex BN12 4UU",
    "addr:housenumber":"132",
    "addr:postcode":"bn12 4uu",
    "addr:street":"Aldsworth Avenue",
    "iso:country":"GB",
    "sg:address":"132 Aldsworth Avenue",
    "sg:city":"Worthing",
    "sg:classifiers":[
        {
            "category":"Home & Garden",
            "subcategory":"Hardware",
            "type":"Retail Goods"
        }
    ],
    "sg:phone":"+44 1903 241755",
    "sg:postcode":"BN12 4UU",
    "sg:province":"West Sussex",
    "sg:tags":[
        "lawnmowers",
        "machinery"
    ],
    "wof:name":"The Lawnmower Shop",
    "wof:placetype":"venue"
},
  "geometry": {"coordinates":[-0.431185,50.815151],"type":"Point"}
}