{
  "type": "Feature",
  "properties": {
    "addr:full":"18 Christchurch Lodge, Chalk Lane Barnet Hertfordshire EN4 9HS",
    "addr:housenumber":"18",
    "addr:postcode":"en4 9hs",
    "addr:street":"Chalk Lane",
    "iso:country":"GB",
    "sg:address":"18 Christchurch Lodge, Chalk Lane",
    "sg:city":"Barnet",
    "sg:classifiers":[
        {
            "category":"Organizations",
            "subcategory":"Community Association",
            "type":"Services"
        }
    ],
    "sg:phone":"+44 20 8440 2619",
    "sg:postcode":"EN4 9HS",
    "sg:province":"Hertfordshire",
    "sg:tags":[
        "society",
        "housing"
    ],
    "wof:name":"English Churches Housing Group Ltd.",
    "wof:placetype":"venue"
},
  "geometry": {"coordinates":[-0.157564,51.667404],"type":"Point"}
}