{
  "type": "Feature",
  "properties": {
    "addr:full":"12 Fourth Avenue Halstead Essex CO9 2SY",
    "addr:housenumber":"12",
    "addr:postcode":"co9 2sy",
    "addr:street":"Fourth Avenue",
    "iso:country":"GB",
    "sg:address":"12 Fourth Avenue",
    "sg:city":"Halstead",
    "sg:classifiers":[
        {
            "category":"Home & Garden",
            "subcategory":"Building Materials",
            "type":"Retail Goods"
        }
    ],
    "sg:postcode":"CO9 2SY",
    "sg:province":"Essex",
    "sg:tags":[
        "ornamental",
        "metalwork"
    ],
    "wof:name":"Otter Wrought Iron Products",
    "wof:placetype":"venue"
},
  "geometry": {"coordinates":[0.65714,51.94072],"type":"Point"}
}