{
  "type": "Feature",
  "properties": {
    "iso:country":"GB",
    "sg:address":"Mere Road, Branston",
    "sg:city":"Lincoln",
    "sg:classifiers":[
        {
            "category":"Professional",
            "subcategory":"Engineering",
            "type":"Services"
        },
        {
            "category":"Food & Beverages",
            "subcategory":"Groceries & Convenience Stores",
            "type":"Retail Goods"
        }
    ],
    "sg:phone":"+44 1522 794411",
    "sg:postcode":"LN4 1NJ",
    "sg:province":"Lincolnshire",
    "sg:tags":[
        "merchant",
        "potato"
    ],
    "wof:name":"Branston Ltd.",
    "wof:placetype":"venue"
},
  "geometry": {"coordinates":[-0.472625,53.189484],"type":"Point"}
}