{
  "type": "Feature",
  "properties": {
    "addr:full":"Hillhouse Farm, Kirklevington Yarm North Yorkshire TS15 9PY",
    "addr:postcode":"ts15 9py",
    "iso:country":"GB",
    "sg:address":"Hillhouse Farm, Kirklevington",
    "sg:city":"Yarm",
    "sg:classifiers":[
        {
            "category":"Farming",
            "subcategory":"Livestock Farm",
            "type":"Manufacturing & Wholesale Goods"
        }
    ],
    "sg:phone":"+44 1642 780202",
    "sg:postcode":"TS15 9PY",
    "sg:province":"North Yorkshire",
    "sg:tags":[
        "others"
    ],
    "wof:name":"J W Barker",
    "wof:placetype":"venue"
},
  "geometry": {"coordinates":[-1.354144,54.508636],"type":"Point"}
}