{
  "type": "Feature",
  "properties": {
    "iso:country":"GB",
    "sg:address":"Unit 3, Spring Farm, Moor Lane",
    "sg:city":"Romney Marsh",
    "sg:classifiers":[
        {
            "category":"Home & Garden",
            "subcategory":"Building Materials",
            "type":"Retail Goods"
        }
    ],
    "sg:postcode":"TN29 0AY",
    "sg:province":"Kent",
    "sg:tags":[
        "ornamental",
        "metalwork"
    ],
    "wof:name":"Specialist Metals Spinning",
    "wof:placetype":"venue"
},
  "geometry": {"coordinates":[0.9227,51.003883],"type":"Point"}
}