{
  "type": "Feature",
  "properties": {
    "iso:country":"GB",
    "sg:address":"45 Three Shires Oak Rd",
    "sg:city":"Smethwick",
    "sg:classifiers":[
        {
            "category":"Health Services",
            "subcategory":"Dentist",
            "type":"Services"
        }
    ],
    "sg:phone":"+44 121 429 5497",
    "sg:postcode":"B67 5BS",
    "sg:province":"West Midlands",
    "wof:name":"W.J Tolley",
    "wof:placetype":"venue"
},
  "geometry": {"coordinates":[-1.9741610289,52.4773406982],"type":"Point"}
}