{
  "type": "Feature",
  "properties": {
    "addr:full":"57 Chislehurst Road Chislehurst Kent BR7 5NP",
    "addr:housenumber":"57",
    "addr:postcode":"br7 5np",
    "addr:street":"Chislehurst Road",
    "iso:country":"GB",
    "sg:address":"57 Chislehurst Road",
    "sg:city":"Chislehurst",
    "sg:classifiers":[
        {
            "category":"Food & Beverages",
            "subcategory":"Liquor & Beverages",
            "type":"Retail Goods"
        }
    ],
    "sg:phone":"+44 20 8467 3528",
    "sg:postcode":"BR7 5NP",
    "sg:province":"Kent",
    "sg:tags":[
        "beer",
        "spirit",
        "wines"
    ],
    "wof:name":"Unwins Wine Merchants",
    "wof:placetype":"venue"
},
  "geometry": {"coordinates":[0.05558,51.407532],"type":"Point"}
}