{
  "type": "Feature",
  "properties": {
    "iso:country":"GB",
    "sg:address":"129 High Street",
    "sg:city":"Fort William",
    "sg:classifiers":[
        {
            "category":"Shopping",
            "subcategory":"Department Store",
            "type":"Retail Goods"
        }
    ],
    "sg:phone":"+44 1397 703011",
    "sg:postcode":"PH33 6DG",
    "sg:province":"Highland",
    "wof:name":"Highlands Prams & Toys",
    "wof:placetype":"venue"
},
  "geometry": {"coordinates":[-5.1133141518,56.8169555664],"type":"Point"}
}