{
  "type": "Feature",
  "properties": {
    "iso:country":"GB",
    "sg:address":"46 Paradise Road",
    "sg:city":"Teignmouth",
    "sg:classifiers":[
        {
            "category":"Professional",
            "subcategory":"Engineering",
            "type":"Services"
        }
    ],
    "sg:phone":"+44 1626 777200",
    "sg:postcode":"TQ14 8NR",
    "sg:province":"Devon",
    "sg:tags":[
        "gas",
        "engineer"
    ],
    "wof:name":"Energy Care",
    "wof:placetype":"venue"
},
  "geometry": {"coordinates":[-3.497347,50.554707],"type":"Point"}
}