{
  "type": "Feature",
  "properties": {
    "iso:country":"GB",
    "sg:address":"36 Canon Avenue",
    "sg:city":"Romford",
    "sg:classifiers":[
        {
            "category":"Professional",
            "subcategory":"Detective & Security Services",
            "type":"Services"
        }
    ],
    "sg:phone":"+44 20 8220 1344",
    "sg:postcode":"RM6 5RR",
    "sg:province":"Essex",
    "sg:tags":[
        "locksmith"
    ],
    "wof:name":"Locksmiths",
    "wof:placetype":"venue"
},
  "geometry": {"coordinates":[0.126439,51.577198],"type":"Point"}
}