{
  "type": "Feature",
  "properties": {
    "addr:full":"106 Cultenhove Road Stirling Falkirk FK7 9EB",
    "addr:housenumber":"106",
    "addr:postcode":"fk7 9eb",
    "addr:street":"Cultenhove Road",
    "iso:country":"GB",
    "sg:address":"106 Cultenhove Road",
    "sg:city":"Stirling",
    "sg:classifiers":[
        {
            "category":"Bars & Pubs",
            "type":"Food & Drink"
        }
    ],
    "sg:postcode":"FK7 9EB",
    "sg:province":"Falkirk",
    "sg:tags":[
        "pubs",
        "inn"
    ],
    "wof:name":"The Culten Bar",
    "wof:placetype":"venue"
},
  "geometry": {"coordinates":[-3.9469890594,56.1008682251],"type":"Point"}
}