{
  "type": "Feature",
  "properties": {
    "addr:full":"38a Saxon Way Cheltenham Gloucestershire GL52 6QX",
    "addr:housenumber":"38a",
    "addr:postcode":"gl52 6qx",
    "addr:street":"Saxon Way",
    "iso:country":"GB",
    "sg:address":"38a Saxon Way",
    "sg:city":"Cheltenham",
    "sg:classifiers":[
        {
            "category":"Manufacturing",
            "subcategory":"Metals",
            "type":"Manufacturing & Wholesale Goods"
        }
    ],
    "sg:phone":"+44 1242 527282",
    "sg:postcode":"GL52 6QX",
    "sg:province":"Gloucestershire",
    "sg:tags":[
        "work",
        "sheet"
    ],
    "wof:name":"J F Abbott & Co Ltd",
    "wof:placetype":"venue"
},
  "geometry": {"coordinates":[-2.05866,51.895302],"type":"Point"}
}