{
  "type": "Feature",
  "properties": {
    "addr:full":"Sixhills Walk Farm, Sixhills Market Rasen Lincolnshire LN8 6AY",
    "addr:housenumber":"sixhills",
    "addr:postcode":"ln8 6ay",
    "addr:street":"Sixhills Walk;Market Rasen",
    "iso:country":"GB",
    "sg:address":"Sixhills Walk Farm, Sixhills",
    "sg:city":"Market Rasen",
    "sg:classifiers":[
        {
            "category":"Farming",
            "subcategory":"Livestock Farm",
            "type":"Manufacturing & Wholesale Goods"
        }
    ],
    "sg:postcode":"LN8 6AY",
    "sg:province":"Lincolnshire",
    "sg:tags":[
        "others"
    ],
    "wof:name":"W Sergeant & Son",
    "wof:placetype":"venue"
},
  "geometry": {"coordinates":[-0.20985,53.37183],"type":"Point"}
}