{
  "type": "Feature",
  "properties": {
    "iso:country":"GB",
    "sg:address":"66 Chapel Street, Lye",
    "sg:city":"Stourbridge",
    "sg:classifiers":[
        {
            "category":"Health Services",
            "subcategory":"Dentist",
            "type":"Services"
        }
    ],
    "sg:phone":"+44 1384 895213",
    "sg:postcode":"DY9 8BX",
    "sg:province":"West Midlands",
    "wof:name":"Andrew Hargreaves Dental Practise",
    "wof:placetype":"venue"
},
  "geometry": {"coordinates":[-2.1160991192,52.4558258057],"type":"Point"}
}