{
  "type": "Feature",
  "properties": {
    "addr:full":"6 South Gyle Crescent Edinburgh City of Edinburgh EH12 9EA",
    "addr:housenumber":"6",
    "addr:postcode":"eh12 9ea",
    "addr:street":"South Gyle Crescent",
    "iso:country":"GB",
    "sg:address":"6 South Gyle Crescent",
    "sg:city":"Edinburgh",
    "sg:classifiers":[
        {
            "category":"Professional",
            "subcategory":"Computer Services",
            "type":"Services"
        }
    ],
    "sg:phone":"+44 131 314 2000",
    "sg:postcode":"EH12 9EA",
    "sg:province":"City of Edinburgh",
    "sg:tags":[
        "consultant",
        "system",
        "software"
    ],
    "wof:name":"Marconi Software Solutions Ltd.",
    "wof:placetype":"venue"
},
  "geometry": {"coordinates":[-3.297303915,55.9294700623],"type":"Point"}
}