{
  "type": "Feature",
  "properties": {
    "addr:full":"33c Bishops Road London Greater London N6 4HP",
    "addr:housenumber":"33c",
    "addr:postcode":"n6 4hp",
    "addr:street":"Bishops Road",
    "iso:country":"GB",
    "sg:address":"33c Bishops Road",
    "sg:city":"London",
    "sg:classifiers":[
        {
            "category":"Professional",
            "subcategory":"Management & Consulting",
            "type":"Services"
        }
    ],
    "sg:postcode":"N6 4HP",
    "sg:province":"Greater London",
    "sg:tags":[
        "consultant",
        "business"
    ],
    "wof:name":"Kornie Ventures Ltd",
    "wof:placetype":"venue"
},
  "geometry": {"coordinates":[-0.149868,51.577908],"type":"Point"}
}