{
  "type": "Feature",
  "properties": {
    "iso:country":"GB",
    "sg:address":"Unit 9, Churchill Court, 58 Station Road",
    "sg:city":"Harrow",
    "sg:classifiers":[
        {
            "category":"Shopping",
            "subcategory":"Clothing, Apparel, & Fashions",
            "type":"Retail Goods"
        }
    ],
    "sg:phone":"+44 20 8424 0847",
    "sg:postcode":"HA2 7SA",
    "sg:province":"Greater London",
    "sg:tags":[
        "clothing",
        "fabric"
    ],
    "wof:name":"Msji Ltd.",
    "wof:placetype":"venue"
},
  "geometry": {"coordinates":[-0.361564,51.585182],"type":"Point"}
}