{
  "type": "Feature",
  "properties": {
    "addr:full":"35 Bdwy Telford Shropshire TF1 5AS",
    "addr:housenumber":"35",
    "addr:postcode":"tf1 5as",
    "addr:street":"Bdwy",
    "iso:country":"GB",
    "sg:address":"35 Bdwy",
    "sg:city":"Telford",
    "sg:classifiers":[
        {
            "category":"Building & Trades",
            "subcategory":"Plumbing",
            "type":"Services"
        }
    ],
    "sg:postcode":"TF1 5AS",
    "sg:province":"Shropshire",
    "sg:tags":[
        "heating"
    ],
    "wof:name":"Bernard Robert Bailey",
    "wof:placetype":"venue"
},
  "geometry": {"coordinates":[-2.478687048,52.6986579895],"type":"Point"}
}