{
  "type": "Feature",
  "properties": {
    "iso:country":"GB",
    "sg:address":"P O Box 216, John Dryden House",
    "sg:city":"Northampton",
    "sg:classifiers":[
        {
            "category":"Government",
            "subcategory":"Office",
            "type":"Public Place"
        }
    ],
    "sg:phone":"+44 1604 237078",
    "sg:postcode":"NN4 7DD",
    "sg:province":"Northamptonshire",
    "sg:tags":[
        "education",
        "agency",
        "authority"
    ],
    "wof:name":"Nias Inspection Services",
    "wof:placetype":"venue"
},
  "geometry": {"coordinates":[-0.8570600152,52.2207183838],"type":"Point"}
}