{
  "type": "Feature",
  "properties": {
    "addr:full":"73 High St Royston Bedfordshire SG8 6LB",
    "addr:housenumber":"73",
    "addr:postcode":"sg8 6lb",
    "addr:street":"High St",
    "iso:country":"GB",
    "sg:address":"73 High St",
    "sg:city":"Royston",
    "sg:classifiers":[
        {
            "category":"Social Services",
            "subcategory":"Retirement Home",
            "type":"Services"
        }
    ],
    "sg:phone":"+44 1763 260217",
    "sg:postcode":"SG8 6LB",
    "sg:province":"Bedfordshire",
    "sg:tags":[
        "residential",
        "care"
    ],
    "wof:name":"Homestead The",
    "wof:placetype":"venue"
},
  "geometry": {"coordinates":[0.0065720002,52.0975112915],"type":"Point"}
}