{
  "type": "Feature",
  "properties": {
    "iso:country":"GB",
    "sg:address":"Aberdeen Ho, Horsham Rd",
    "sg:city":"Dorking",
    "sg:classifiers":[
        {
            "category":"Food & Beverages",
            "subcategory":"Meat & Fish",
            "type":"Retail Goods"
        }
    ],
    "sg:phone":"+44 1306 888708",
    "sg:postcode":"RH5 4NG",
    "sg:province":"Surrey",
    "sg:tags":[
        "butcher"
    ],
    "wof:name":"Weston Charles Butchers",
    "wof:placetype":"venue"
},
  "geometry": {"coordinates":[-0.3260099888,51.1942901611],"type":"Point"}
}