{
  "type": "Feature",
  "properties": {
    "addr:full":"144 Newport Road Cardiff Cardiff CF24 1DJ",
    "addr:housenumber":"144",
    "addr:postcode":"cf24 1dj",
    "addr:street":"Newport Road",
    "iso:country":"GB",
    "sg:address":"144 Newport Road",
    "sg:city":"Cardiff",
    "sg:classifiers":[
        {
            "category":"Travel",
            "subcategory":"Hotels & Motels",
            "type":"Entertainment"
        }
    ],
    "sg:postcode":"CF24 1DJ",
    "sg:province":"Cardiff",
    "wof:name":"Balkan Hotel",
    "wof:placetype":"venue"
},
  "geometry": {"coordinates":[-3.1573319435,51.4895858765],"type":"Point"}
}