{
  "type": "Feature",
  "properties": {
    "addr:full":"2 Third Avenue Bath Somerset BA2 3NY",
    "addr:housenumber":"2",
    "addr:postcode":"ba2 3ny",
    "addr:street":"Third Avenue",
    "iso:country":"GB",
    "sg:address":"2 Third Avenue",
    "sg:city":"Bath",
    "sg:classifiers":[
        {
            "category":"Shopping",
            "subcategory":"Hobbies, Toys, & Games",
            "type":"Retail Goods"
        }
    ],
    "sg:postcode":"BA2 3NY",
    "sg:province":"Somerset",
    "sg:tags":[
        "shop",
        "toy"
    ],
    "wof:name":"Park Value",
    "wof:placetype":"venue"
},
  "geometry": {"coordinates":[-2.3775279522,51.376663208],"type":"Point"}
}