{
  "type": "Feature",
  "properties": {
    "addr:full":"North Farm, Spetisbury Blandford Forum Dorset DT11 9DH",
    "addr:postcode":"dt11 9dh",
    "addr:street":"North",
    "iso:country":"GB",
    "sg:address":"North Farm, Spetisbury",
    "sg:city":"Blandford Forum",
    "sg:classifiers":[
        {
            "category":"Farming",
            "subcategory":"Livestock Farm",
            "type":"Manufacturing & Wholesale Goods"
        }
    ],
    "sg:phone":"+44 1258 452071",
    "sg:postcode":"DT11 9DH",
    "sg:province":"Dorset",
    "sg:tags":[
        "others"
    ],
    "wof:name":"J L Frampton & Sons",
    "wof:placetype":"venue"
},
  "geometry": {"coordinates":[-2.126326,50.821739],"type":"Point"}
}