{
  "type": "Feature",
  "properties": {
    "iso:country":"GB",
    "sg:address":"24 Overstrand Close",
    "sg:city":"Bicester",
    "sg:classifiers":[
        {
            "category":"Professional",
            "subcategory":"Computer Services",
            "type":"Services"
        }
    ],
    "sg:postcode":"OX26 4YP",
    "sg:province":"Oxfordshire",
    "sg:tags":[
        "system",
        "software"
    ],
    "wof:name":"Crayranch Ltd",
    "wof:placetype":"venue"
},
  "geometry": {"coordinates":[-1.138464,51.910564],"type":"Point"}
}