{
  "type": "Feature",
  "properties": {
    "iso:country":"GB",
    "sg:address":"12 Tresham Court",
    "sg:city":"Dewsbury",
    "sg:classifiers":[
        {
            "category":"Shopping",
            "subcategory":"Party Supplies",
            "type":"Retail Goods"
        },
        {
            "category":"Arts & Performance",
            "subcategory":"Music",
            "type":"Entertainment"
        }
    ],
    "sg:phone":"+44 1924 469962",
    "sg:postcode":"WF12 7EE",
    "sg:province":"West Yorkshire",
    "sg:tags":[
        "mobile",
        "operator",
        "disco"
    ],
    "wof:name":"Simply the Best Mobile Discos",
    "wof:placetype":"venue"
},
  "geometry": {"coordinates":[-1.6131290197,53.701171875],"type":"Point"}
}