{
  "type": "Feature",
  "properties": {
    "addr:full":"56 Dinting Vale Works, Dinting Vale Glossop Derbyshire SK13 6LG",
    "addr:housenumber":"56",
    "addr:postcode":"sk13 6lg",
    "addr:street":"Dinting Vale;Dinting Vale",
    "iso:country":"GB",
    "sg:address":"56 Dinting Vale Works, Dinting Vale",
    "sg:city":"Glossop",
    "sg:classifiers":[
        {
            "category":"Retail",
            "subcategory":"Auto Repair",
            "type":"Services"
        }
    ],
    "sg:postcode":"SK13 6LG",
    "sg:province":"Derbyshire",
    "sg:tags":[
        "modification",
        "garage"
    ],
    "wof:name":"Sharon Walsh",
    "wof:placetype":"venue"
},
  "geometry": {"coordinates":[-1.9685139656,53.4452095032],"type":"Point"}
}