{
  "type": "Feature",
  "properties": {
    "addr:full":"344 Bearwood Road Smethwick West Midlands B66 4ES",
    "addr:housenumber":"344",
    "addr:postcode":"b66 4es",
    "addr:street":"Bearwood Road",
    "iso:country":"GB",
    "sg:address":"344 Bearwood Road",
    "sg:city":"Smethwick",
    "sg:classifiers":[
        {
            "category":"Travel",
            "subcategory":"Hotels & Motels",
            "type":"Entertainment"
        }
    ],
    "sg:phone":"+44 121 429 2299",
    "sg:postcode":"B66 4ES",
    "sg:province":"West Midlands",
    "wof:name":"Hotel Dinara",
    "wof:placetype":"venue"
},
  "geometry": {"coordinates":[-1.969167,52.482334],"type":"Point"}
}