{
  "type": "Feature",
  "properties": {
    "iso:country":"GB",
    "sg:address":"St Bernard Drive, The Swans",
    "sg:city":"Malvern",
    "sg:classifiers":[
        {
            "category":"Manufacturing",
            "subcategory":"Petroleum Products",
            "type":"Manufacturing & Wholesale Goods"
        }
    ],
    "sg:phone":"+44 1684 566302",
    "sg:postcode":"WR14 3PY",
    "sg:province":"Herefordshire",
    "sg:tags":[
        "lubricant"
    ],
    "wof:name":"Swan Oils",
    "wof:placetype":"venue"
},
  "geometry": {"coordinates":[-2.319704,52.097073],"type":"Point"}
}