{
  "type": "Feature",
  "properties": {
    "addr:full":"Little Toothill, Triangle Sowerby Bridge West Yorkshire HX6 1NX",
    "addr:postcode":"hx6 1nx",
    "addr:street":"West",
    "iso:country":"GB",
    "sg:address":"Little Toothill, Triangle",
    "sg:city":"Sowerby Bridge",
    "sg:classifiers":[
        {
            "category":"Transit Center",
            "subcategory":"Passenger",
            "type":"Transportation"
        }
    ],
    "sg:postcode":"HX6 1NX",
    "sg:province":"West Yorkshire",
    "sg:tags":[
        "boarding",
        "kennel",
        "catteries"
    ],
    "wof:name":"All Breeds Boarding Kennels & Cattery",
    "wof:placetype":"venue"
},
  "geometry": {"coordinates":[-1.942004,53.705635],"type":"Point"}
}