{
  "type": "Feature",
  "properties": {
    "addr:full":"Ampthill Road, Kempston Bedford Bedfordshire MK42 9JN",
    "addr:postcode":"mk42 9jn",
    "addr:street":"Ampthill Road",
    "iso:country":"GB",
    "sg:address":"Ampthill Road, Kempston",
    "sg:city":"Bedford",
    "sg:classifiers":[
        {
            "category":"Freight",
            "type":"Transportation"
        }
    ],
    "sg:phone":"+44 1234 350712",
    "sg:postcode":"MK42 9JN",
    "sg:province":"Bedfordshire",
    "sg:tags":[
        "haulage",
        "road"
    ],
    "wof:name":"A E R Inskip & Co. (Kempston) Ltd.",
    "wof:placetype":"venue"
},
  "geometry": {"coordinates":[-0.470514,52.127254],"type":"Point"}
}