{
  "type": "Feature",
  "properties": {
    "addr:full":"43 New England Road Brighton East Sussex BN1 4GG",
    "addr:housenumber":"43",
    "addr:postcode":"bn1 4gg",
    "addr:street":"New England Road",
    "iso:country":"GB",
    "sg:address":"43 New England Road",
    "sg:city":"Brighton",
    "sg:classifiers":[
        {
            "category":"Fast Food",
            "type":"Food & Drink"
        },
        {
            "category":"Cafe",
            "type":"Food & Drink"
        }
    ],
    "sg:postcode":"BN1 4GG",
    "sg:province":"East Sussex",
    "sg:tags":[
        "tea",
        "away",
        "room",
        "take"
    ],
    "wof:name":"New Englan Deli",
    "wof:placetype":"venue"
},
  "geometry": {"coordinates":[-0.1399929971,50.8338127136],"type":"Point"}
}