{
  "type": "Feature",
  "properties": {
    "addr:full":"45 High Street Broadway Gloucestershire WR12 7DP",
    "addr:housenumber":"45",
    "addr:postcode":"wr12 7dp",
    "addr:street":"High Street",
    "iso:country":"GB",
    "sg:address":"45 High Street",
    "sg:city":"Broadway",
    "sg:classifiers":[
        {
            "category":"Cinema",
            "subcategory":"Movie Rental",
            "type":"Entertainment"
        }
    ],
    "sg:postcode":"WR12 7DP",
    "sg:province":"Gloucestershire",
    "sg:tags":[
        "video",
        "library"
    ],
    "wof:name":"The Movie Shop",
    "wof:placetype":"venue"
},
  "geometry": {"coordinates":[-1.8608139753,52.0358848572],"type":"Point"}
}