{
  "type": "Feature",
  "properties": {
    "addr:full":"Wilsons House, Wilsons Park Manchester Greater Manchester M40 8WN",
    "addr:postcode":"m40 8wn",
    "addr:street":"Wilsons Park",
    "iso:country":"GB",
    "sg:address":"Wilsons House, Wilsons Park",
    "sg:city":"Manchester",
    "sg:classifiers":[
        {
            "category":"Professional",
            "subcategory":"Advertising",
            "type":"Services"
        }
    ],
    "sg:phone":"+44 161 202 0202",
    "sg:postcode":"M40 8WN",
    "sg:province":"Greater Manchester",
    "sg:tags":[
        "agency"
    ],
    "wof:name":"A.B.C.I.",
    "wof:placetype":"venue"
},
  "geometry": {"coordinates":[-2.205053091,53.4996910095],"type":"Point"}
}