{
  "type": "Feature",
  "properties": {
    "addr:full":"32 Norfolk Crescent, St Johns Park, Bracebridge Heath Lincoln Lincolnshire LN4 2ST",
    "addr:housenumber":"32",
    "addr:postcode":"ln4 2st",
    "addr:street":"Norfolk Crescent St",
    "iso:country":"GB",
    "sg:address":"32 Norfolk Crescent, St Johns Park, Bracebridge Heath",
    "sg:city":"Lincoln",
    "sg:classifiers":[
        {
            "category":"Home & Garden",
            "subcategory":"Building Materials",
            "type":"Retail Goods"
        },
        {
            "category":"Building & Trades",
            "subcategory":"Construction",
            "type":"Services"
        }
    ],
    "sg:phone":"+44 1522 545477",
    "sg:postcode":"LN4 2ST",
    "sg:province":"Lincolnshire",
    "sg:tags":[
        "stairlifts",
        "builder"
    ],
    "wof:name":"J Y Stairlift Installations Ltd.",
    "wof:placetype":"venue"
},
  "geometry": {"coordinates":[-0.5364739895,53.1913948059],"type":"Point"}
}