{
  "type": "Feature",
  "properties": {
    "iso:country":"GB",
    "sg:address":"60 Mill La",
    "sg:city":"Ormskirk",
    "sg:classifiers":[
        {
            "category":"Building & Trades",
            "subcategory":"Construction",
            "type":"Services"
        }
    ],
    "sg:phone":"+44 1704 895545",
    "sg:postcode":"L40 5TJ",
    "sg:province":"Lancashire",
    "sg:tags":[
        "dry",
        "lining",
        "plasterers",
        "screeders"
    ],
    "wof:name":"A C M S",
    "wof:placetype":"venue"
},
  "geometry": {"coordinates":[-2.838635,53.60075],"type":"Point"}
}