{
  "type": "Feature",
  "properties": {
    "addr:full":"Hillside House, Pitchcombe Stroud Gloucestershire GL6 6LN",
    "addr:postcode":"gl6 6ln",
    "addr:street":"Pitchcombe",
    "iso:country":"GB",
    "sg:address":"Hillside House, Pitchcombe",
    "sg:city":"Stroud",
    "sg:classifiers":[
        {
            "category":"Professional",
            "subcategory":"Art Services",
            "type":"Services"
        }
    ],
    "sg:phone":"+44 1452 812550",
    "sg:postcode":"GL6 6LN",
    "sg:province":"Gloucestershire",
    "sg:tags":[
        "graphic",
        "designer"
    ],
    "wof:name":"Nicholas J Jones Graphics",
    "wof:placetype":"venue"
},
  "geometry": {"coordinates":[-2.2196490765,51.7784614563],"type":"Point"}
}