{
  "type": "Feature",
  "properties": {
    "addr:full":"3 Lower Dartmouth Street Birmingham West Midlands B9 4LG",
    "addr:housenumber":"3",
    "addr:postcode":"b9 4lg",
    "addr:street":"Lower Dartmouth Street",
    "iso:country":"GB",
    "sg:address":"3 Lower Dartmouth Street",
    "sg:city":"Birmingham",
    "sg:classifiers":[
        {
            "category":"Manufacturing",
            "subcategory":"Glass & Minerals",
            "type":"Manufacturing & Wholesale Goods"
        }
    ],
    "sg:phone":"+44 121 773 8714",
    "sg:postcode":"B9 4LG",
    "sg:province":"West Midlands",
    "sg:tags":[
        "fibre",
        "moulding"
    ],
    "wof:name":"Croy (Glass Fibre) Products",
    "wof:placetype":"venue"
},
  "geometry": {"coordinates":[-1.875815,52.479279],"type":"Point"}
}