{
  "type": "Feature",
  "properties": {
    "addr:full":"78 East Duck Lees Lane, Ponders End, Brimsdown Enfield Greater London EN3 7SR",
    "addr:housenumber":"78",
    "addr:postcode":"en3 7sr",
    "addr:street":"East Duck Lees Lane",
    "iso:country":"GB",
    "sg:address":"78 East Duck Lees Lane, Ponders End, Brimsdown",
    "sg:city":"Enfield",
    "sg:classifiers":[
        {
            "category":"Professional",
            "type":"Services"
        }
    ],
    "sg:phone":"+44 20 8805 8855",
    "sg:postcode":"EN3 7SR",
    "sg:province":"Greater London",
    "sg:tags":[
        "control",
        "system"
    ],
    "wof:name":"Chequers (U K) Ltd.",
    "wof:placetype":"venue"
},
  "geometry": {"coordinates":[-0.028354,51.647346],"type":"Point"}
}