{
  "type": "Feature",
  "properties": {
    "iso:country":"GB",
    "sg:address":"3 The Parade, Waterloo Estate",
    "sg:city":"Poole",
    "sg:classifiers":[
        {
            "category":"Food & Beverages",
            "subcategory":"Meat & Fish",
            "type":"Retail Goods"
        }
    ],
    "sg:phone":"+44 1202 267665",
    "sg:postcode":"BH17 7EZ",
    "sg:province":"Dorset",
    "sg:tags":[
        "chip"
    ],
    "wof:name":"The Perfect Plaice",
    "wof:placetype":"venue"
},
  "geometry": {"coordinates":[-1.989614,50.748745],"type":"Point"}
}