{
  "type": "Feature",
  "properties": {
    "addr:full":"Units 7 & 8, 147 Wareham Road, Corfe Mullen Wimborne Dorset BH21 3LA",
    "addr:housenumber":"units 7 & 8",
    "addr:postcode":"147;bh21 3la",
    "addr:street":"Wareham Road",
    "iso:country":"GB",
    "sg:address":"Units 7 & 8, 147 Wareham Road, Corfe Mullen",
    "sg:city":"Wimborne",
    "sg:classifiers":[
        {
            "category":"Retail",
            "subcategory":"Auto Rental",
            "type":"Services"
        }
    ],
    "sg:postcode":"BH21 3LA",
    "sg:province":"Dorset",
    "sg:tags":[
        "car"
    ],
    "wof:name":"Poole Trailers Ltd",
    "wof:placetype":"venue"
},
  "geometry": {"coordinates":[-2.0212860107,50.765296936],"type":"Point"}
}