{
  "type": "Feature",
  "properties": {
    "iso:country":"GB",
    "sg:address":"3 Gower Street",
    "sg:city":"Sheffield",
    "sg:classifiers":[
        {
            "category":"Home & Garden",
            "subcategory":"Household Appliances",
            "type":"Retail Goods"
        }
    ],
    "sg:phone":"+44 114 275 8381",
    "sg:postcode":"S4 7HA",
    "sg:province":"South Yorkshire",
    "sg:tags":[
        "domestic",
        "centre"
    ],
    "wof:name":"Gower Domestics",
    "wof:placetype":"venue"
},
  "geometry": {"coordinates":[-1.457141,53.39312],"type":"Point"}
}