{
  "type": "Feature",
  "properties": {
    "iso:country":"GB",
    "sg:address":"Ims House, Collier Row Road",
    "sg:city":"Romford",
    "sg:classifiers":[
        {
            "category":"Professional",
            "subcategory":"Advertising",
            "type":"Services"
        }
    ],
    "sg:phone":"+44 1708 707780",
    "sg:postcode":"RM5 2DB",
    "sg:province":"Essex",
    "sg:tags":[
        "outdoor"
    ],
    "wof:name":"Showcase",
    "wof:placetype":"venue"
},
  "geometry": {"coordinates":[0.1603650004,51.5985984802],"type":"Point"}
}