{
  "type": "Feature",
  "properties": {
    "addr:full":"Redlees Park, Worton Road Isleworth Greater London TW7 6DW",
    "addr:postcode":"tw7 6dw",
    "addr:street":"Worton Road",
    "iso:country":"GB",
    "sg:address":"Redlees Park, Worton Road",
    "sg:city":"Isleworth",
    "sg:classifiers":[
        {
            "category":"Sports & Exercise",
            "subcategory":"Bowling",
            "type":"Entertainment"
        },
        {
            "category":"Arena",
            "subcategory":"Sports Club",
            "type":"Entertainment"
        }
    ],
    "sg:phone":"+44 20 8758 1700",
    "sg:postcode":"TW7 6DW",
    "sg:province":"Greater London",
    "sg:tags":[
        "centre"
    ],
    "wof:name":"Isleworth Bowling Club",
    "wof:placetype":"venue"
},
  "geometry": {"coordinates":[-0.332574,51.467514],"type":"Point"}
}