{
  "type": "Feature",
  "properties": {
    "addr:full":"Unit 7 Woodroyd Mills, South Parade Cleckheaton West Yorkshire BD19 3AF",
    "addr:housenumber":"unit 7",
    "addr:postcode":"bd19 3af",
    "addr:street":"Woodroyd Mills South Parade",
    "iso:country":"GB",
    "sg:address":"Unit 7 Woodroyd Mills, South Parade",
    "sg:city":"Cleckheaton",
    "sg:classifiers":[
        {
            "category":"Education",
            "subcategory":"Preschool",
            "type":"Public Place"
        },
        {
            "category":"Community Center",
            "subcategory":"Youth",
            "type":"Public Place"
        }
    ],
    "sg:postcode":"BD19 3AF",
    "sg:province":"West Yorkshire",
    "sg:tags":[
        "children's",
        "pre-school",
        "activity",
        "playgroups",
        "centre"
    ],
    "wof:name":"Tumbles Playgym",
    "wof:placetype":"venue"
},
  "geometry": {"coordinates":[-1.711889,53.72517],"type":"Point"}
}