{
  "type": "Feature",
  "properties": {
    "iso:country":"GB",
    "sg:address":"13 Dean Street",
    "sg:city":"Blackpool",
    "sg:classifiers":[
        {
            "category":"Travel",
            "subcategory":"Hotels & Motels",
            "type":"Entertainment"
        }
    ],
    "sg:phone":"+44 1253 343638",
    "sg:postcode":"FY4 1AU",
    "sg:province":"Lancashire",
    "wof:name":"Dunes Hotel",
    "wof:placetype":"venue"
},
  "geometry": {"coordinates":[-3.05477,53.796177],"type":"Point"}
}