{
  "type": "Feature",
  "properties": {
    "iso:country":"GB",
    "sg:address":"Unit 12 Weights Farm Business Park",
    "sg:city":"Redditch",
    "sg:classifiers":[
        {
            "category":"Home & Garden",
            "subcategory":"Home Furnishings",
            "type":"Retail Goods"
        }
    ],
    "sg:phone":"+44 845 053 6000",
    "sg:postcode":"B97 6RG",
    "sg:province":"Warwickshire",
    "sg:tags":[
        "homefurnishings"
    ],
    "wof:name":"Sauvagnat (U K) Ltd.",
    "wof:placetype":"venue"
},
  "geometry": {"coordinates":[-1.941267,52.30727],"type":"Point"}
}