{
  "type": "Feature",
  "properties": {
    "addr:full":"900 Thornton Road, Fairweather Green Bradford West Yorkshire BD8 0JG",
    "addr:housenumber":"900",
    "addr:postcode":"bd8 0jg",
    "addr:street":"Thornton Road Fairweather Green Bradford West",
    "iso:country":"GB",
    "sg:address":"900 Thornton Road, Fairweather Green",
    "sg:city":"Bradford",
    "sg:classifiers":[
        {
            "category":"Professional",
            "subcategory":"Printing & Photocopies",
            "type":"Services"
        }
    ],
    "sg:postcode":"BD8 0JG",
    "sg:province":"West Yorkshire",
    "sg:tags":[
        "computer",
        "tag",
        "label"
    ],
    "wof:name":"Iac Systems Ltd.",
    "wof:placetype":"venue"
},
  "geometry": {"coordinates":[-1.802991,53.796398],"type":"Point"}
}