{
  "type": "Feature",
  "properties": {
    "addr:full":"7 Hamilton Way Wallington Surrey SM6 9NJ",
    "addr:housenumber":"7",
    "addr:postcode":"sm6 9nj",
    "addr:street":"Hamilton Way",
    "iso:country":"GB",
    "sg:address":"7 Hamilton Way",
    "sg:city":"Wallington",
    "sg:classifiers":[
        {
            "category":"Professional",
            "subcategory":"Business Services",
            "type":"Services"
        }
    ],
    "sg:phone":"+44 20 8669 8121",
    "sg:postcode":"SM6 9NJ",
    "sg:province":"Surrey",
    "sg:tags":[
        "organisation",
        "trade"
    ],
    "wof:name":"National Outdoor Events Association",
    "wof:placetype":"venue"
},
  "geometry": {"coordinates":[-0.1388790011,51.3490028381],"type":"Point"}
}