{
  "type": "Feature",
  "properties": {
    "addr:full":"Cedar House, 698 Green Lanes London Greater London N21 3RE",
    "addr:housenumber":"698",
    "addr:postcode":"n21 3re",
    "addr:street":"Green Lanes",
    "iso:country":"GB",
    "sg:address":"Cedar House, 698 Green Lanes",
    "sg:city":"London",
    "sg:classifiers":[
        {
            "category":"Communications",
            "type":"Services"
        }
    ],
    "sg:postcode":"N21 3RE",
    "sg:province":"Greater London",
    "sg:tags":[
        "audio-visual"
    ],
    "wof:name":"Drayton Technical Supplies Ltd",
    "wof:placetype":"venue"
},
  "geometry": {"coordinates":[-0.0970039964,51.6304588318],"type":"Point"}
}