{
  "type": "Feature",
  "properties": {
    "iso:country":"GB",
    "sg:address":"51 Grattons Drive",
    "sg:city":"Crawley",
    "sg:classifiers":[
        {
            "category":"Education",
            "subcategory":"Dance Studio",
            "type":"Public Place"
        }
    ],
    "sg:postcode":"RH10 3AQ",
    "sg:province":"Surrey",
    "sg:tags":[
        "school",
        "dancing"
    ],
    "wof:name":"Gillian Osborne School of Dancing",
    "wof:placetype":"venue"
},
  "geometry": {"coordinates":[-0.154929,51.12582],"type":"Point"}
}