{
  "type": "Feature",
  "properties": {
    "addr:full":"2 Oak Street York North Yorkshire YO26 4SE",
    "addr:housenumber":"2",
    "addr:postcode":"yo26 4se",
    "addr:street":"Oak Street",
    "iso:country":"GB",
    "sg:address":"2 Oak Street",
    "sg:city":"York",
    "sg:classifiers":[
        {
            "category":"Building & Trades",
            "subcategory":"Equipment Rental",
            "type":"Services"
        }
    ],
    "sg:phone":"+44 1904 788856",
    "sg:postcode":"YO26 4SE",
    "sg:province":"North Yorkshire",
    "sg:tags":[
        "hire",
        "centre"
    ],
    "wof:name":"S C M Hire",
    "wof:placetype":"venue"
},
  "geometry": {"coordinates":[-1.113347,53.960911],"type":"Point"}
}