{
  "type": "Feature",
  "properties": {
    "addr:full":"Cradlehall Farm, Cradlehall Inverness Highland IV2 5NG",
    "addr:postcode":"iv2 5ng",
    "addr:street":"Cradlehall",
    "iso:country":"GB",
    "sg:address":"Cradlehall Farm, Cradlehall",
    "sg:city":"Inverness",
    "sg:classifiers":[
        {
            "category":"Home & Garden",
            "subcategory":"Garden Supply",
            "type":"Retail Goods"
        },
        {
            "category":"Farming",
            "subcategory":"Farm",
            "type":"Manufacturing & Wholesale Goods"
        }
    ],
    "sg:postcode":"IV2 5NG",
    "sg:province":"Highland",
    "sg:tags":[
        "mixed",
        "bulb",
        "crop",
        "grower"
    ],
    "wof:name":"W F & W Hutcheson",
    "wof:placetype":"venue"
},
  "geometry": {"coordinates":[-4.161759,57.474716],"type":"Point"}
}