{
  "type": "Feature",
  "properties": {
    "iso:country":"GB",
    "sg:address":"9 Southgate",
    "sg:city":"Bath",
    "sg:classifiers":[
        {
            "category":"Home & Garden",
            "subcategory":"Household Appliances",
            "type":"Retail Goods"
        }
    ],
    "sg:phone":"+44 1225 443154",
    "sg:postcode":"BA1 1TD",
    "sg:province":"Bath and North East Somerset",
    "sg:tags":[
        "gas"
    ],
    "wof:name":"British Gas Energy Centre",
    "wof:placetype":"venue"
},
  "geometry": {"coordinates":[-2.359566927,51.3787651062],"type":"Point"}
}