{
  "type": "Feature",
  "properties": {
    "iso:country":"GB",
    "sg:address":"22 Parlaunt Rd, Langley",
    "sg:city":"Slough",
    "sg:classifiers":[
        {
            "category":"Shopping",
            "subcategory":"Florist",
            "type":"Retail Goods"
        }
    ],
    "sg:postcode":"SL3 8BB",
    "sg:province":"Berkshire",
    "wof:name":"Crick,Sandra,",
    "wof:placetype":"venue"
},
  "geometry": {"coordinates":[-0.5254489779,51.5016708374],"type":"Point"}
}