{
  "type": "Feature",
  "properties": {
    "addr:full":"1 Queens Lane, Bromfield Industrial Estate Mold Denbighshire CH7 1JR",
    "addr:housenumber":"1",
    "addr:postcode":"ch7 1jr",
    "addr:street":"Queens Lane;Industrial Estate",
    "iso:country":"GB",
    "sg:address":"1 Queens Lane, Bromfield Industrial Estate",
    "sg:city":"Mold",
    "sg:classifiers":[
        {
            "category":"Professional",
            "subcategory":"Business Services",
            "type":"Services"
        }
    ],
    "sg:postcode":"CH7 1JR",
    "sg:province":"Denbighshire",
    "sg:tags":[
        "tile",
        "stockist"
    ],
    "wof:name":"Highvogue Ltd.",
    "wof:placetype":"venue"
},
  "geometry": {"coordinates":[-3.1519489288,53.1670875549],"type":"Point"}
}