{
  "type": "Feature",
  "properties": {
    "iso:country":"GB",
    "sg:address":"Shaw House",
    "sg:city":"Brierley Hill",
    "sg:classifiers":[
        {
            "category":"Building & Trades",
            "subcategory":"Construction",
            "type":"Services"
        }
    ],
    "sg:phone":"+44 1384 77440",
    "sg:postcode":"DY5 1TA",
    "sg:province":"West Midlands",
    "sg:tags":[
        "furnace"
    ],
    "wof:name":"Seco/Warwick (U K) Ltd.",
    "wof:placetype":"venue"
},
  "geometry": {"coordinates":[-2.121301,52.482044],"type":"Point"}
}