{
  "type": "Feature",
  "properties": {
    "iso:country":"GB",
    "sg:address":"35 Lifford Close",
    "sg:city":"Birmingham",
    "sg:classifiers":[
        {
            "category":"Building & Trades",
            "subcategory":"Plumbing",
            "type":"Services"
        }
    ],
    "sg:phone":"+44 121 604 2323",
    "sg:postcode":"B14 6QL",
    "sg:province":"West Midlands",
    "sg:tags":[
        "plumber",
        "heating"
    ],
    "wof:name":"K D U Plumbing & Heating Services",
    "wof:placetype":"venue"
},
  "geometry": {"coordinates":[-1.9126149416,52.4180831909],"type":"Point"}
}