{
  "type": "Feature",
  "properties": {
    "addr:full":"Export House, 79a North Road Huddersfield South Yorkshire HD8 0RL",
    "addr:housenumber":"79a",
    "addr:postcode":"hd8 0rl",
    "addr:street":"North Road",
    "iso:country":"GB",
    "sg:address":"Export House, 79a North Road",
    "sg:city":"Huddersfield",
    "sg:classifiers":[
        {
            "category":"Freight",
            "type":"Transportation"
        }
    ],
    "sg:phone":"+44 1484 608707",
    "sg:postcode":"HD8 0RL",
    "sg:province":"South Yorkshire",
    "sg:tags":[
        "forwarders"
    ],
    "wof:name":"Jade Freight Ltd.",
    "wof:placetype":"venue"
},
  "geometry": {"coordinates":[-1.70381,53.612381],"type":"Point"}
}