{
  "type": "Feature",
  "properties": {
    "addr:full":"The Sail Loft, Croft Road Salcombe Devon TQ8 8DZ",
    "addr:postcode":"tq8 8dz",
    "addr:street":"Croft Road",
    "iso:country":"GB",
    "sg:address":"The Sail Loft, Croft Road",
    "sg:city":"Salcombe",
    "sg:classifiers":[
        {
            "category":"Manufacturing",
            "subcategory":"Watercraft",
            "type":"Manufacturing & Wholesale Goods"
        }
    ],
    "sg:postcode":"TQ8 8DZ",
    "sg:province":"Devon",
    "sg:tags":[
        "repairer",
        "sailmaker"
    ],
    "wof:name":"Jon Alsop",
    "wof:placetype":"venue"
},
  "geometry": {"coordinates":[-3.7747991085,50.237865448],"type":"Point"}
}