{
  "type": "Feature",
  "properties": {
    "iso:country":"GB",
    "sg:address":"2 Farley Hill",
    "sg:city":"Luton",
    "sg:classifiers":[
        {
            "category":"Social Services",
            "type":"Services"
        }
    ],
    "sg:phone":"+44 1582 736522",
    "sg:postcode":"LU1 5HQ",
    "sg:province":"Bedfordshire",
    "wof:name":"Luton Youth Justice Centre",
    "wof:placetype":"venue"
},
  "geometry": {"coordinates":[-0.4194569886,51.8740653992],"type":"Point"}
}