{
  "type": "Feature",
  "properties": {
    "addr:full":"Honeywood Close, White Cliffs Business Park, Whitfield Dover Kent CT16 3PF",
    "addr:postcode":"kent ct16 3pf",
    "addr:street":"Honeywood Close;Cliffs Business Park;Dover",
    "iso:country":"GB",
    "sg:address":"Honeywood Close, White Cliffs Business Park, Whitfield",
    "sg:city":"Dover",
    "sg:classifiers":[
        {
            "category":"Government",
            "subcategory":"Office",
            "type":"Public Place"
        }
    ],
    "sg:phone":"+44 1304 821199",
    "sg:postcode":"CT16 3PF",
    "sg:province":"Kent",
    "sg:tags":[
        "local"
    ],
    "wof:name":"Dover District Council",
    "wof:placetype":"venue"
},
  "geometry": {"coordinates":[1.29445,51.15443],"type":"Point"}
}