{
  "type": "Feature",
  "properties": {
    "addr:full":"50 Clerkhill Road Peterhead Aberdeenshire AB42 6XE",
    "addr:housenumber":"50",
    "addr:postcode":"ab42 6xe",
    "addr:street":"Clerkhill Road",
    "iso:country":"GB",
    "sg:address":"50 Clerkhill Road",
    "sg:city":"Peterhead",
    "sg:classifiers":[
        {
            "category":"Personal",
            "subcategory":"Beauty Salon",
            "type":"Services"
        }
    ],
    "sg:postcode":"AB42 6XE",
    "sg:province":"Aberdeenshire",
    "sg:tags":[
        "unisex",
        "hairdresser"
    ],
    "wof:name":"Hairtrix",
    "wof:placetype":"venue"
},
  "geometry": {"coordinates":[-1.7986710072,57.5026855469],"type":"Point"}
}