{
  "type": "Feature",
  "properties": {
    "iso:country":"GB",
    "sg:address":"21-25 Havant Road",
    "sg:city":"Emsworth",
    "sg:classifiers":[
        {
            "category":"Autos & Motor Vehicles",
            "subcategory":"Fuel & Gas Station",
            "type":"Retail Goods"
        }
    ],
    "sg:postcode":"PO10 7JD",
    "sg:province":"Hampshire",
    "sg:tags":[
        "hr",
        "filling",
        "petrol"
    ],
    "wof:name":"Emsworth Service Station",
    "wof:placetype":"venue"
},
  "geometry": {"coordinates":[-0.9427300096,50.8477973938],"type":"Point"}
}