{
  "type": "Feature",
  "properties": {
    "addr:full":"484 Durham Road, Low Fell Gateshead Tyne and Wear NE9 6HU",
    "addr:housenumber":"484",
    "addr:postcode":"ne9 6hu",
    "addr:street":"Durham Road",
    "iso:country":"GB",
    "sg:address":"484 Durham Road, Low Fell",
    "sg:city":"Gateshead",
    "sg:classifiers":[
        {
            "category":"Banks & Credit Unions",
            "subcategory":"Bank",
            "type":"Services"
        }
    ],
    "sg:phone":"+44 191 487 9249",
    "sg:postcode":"NE9 6HU",
    "sg:province":"Tyne and Wear",
    "sg:tags":[
        "financial",
        "institution"
    ],
    "wof:name":"Northern Rock Plc",
    "wof:placetype":"venue"
},
  "geometry": {"coordinates":[-1.599750042,54.9362602234],"type":"Point"}
}