{
  "type": "Feature",
  "properties": {
    "iso:country":"GB",
    "sg:address":"159 Central Drive",
    "sg:city":"Blackpool",
    "sg:classifiers":[
        {
            "category":"Travel",
            "subcategory":"Hotels & Motels",
            "type":"Entertainment"
        },
        {
            "category":"Bars & Pubs",
            "subcategory":"Hookah Bar",
            "type":"Food & Drink"
        }
    ],
    "sg:phone":"+44 1253 621187",
    "sg:postcode":"FY1 5ED",
    "sg:province":"Lancashire",
    "sg:tags":[
        "self",
        "holiday",
        "catering"
    ],
    "wof:name":"Regina Holiday Flats",
    "wof:placetype":"venue"
},
  "geometry": {"coordinates":[-3.049297,53.811722],"type":"Point"}
}