{
  "type": "Feature",
  "properties": {
    "addr:full":"C/o Simon Carter London Greater London W1F 9SS",
    "addr:housenumber":"/ o",
    "addr:postcode":"w1f 9ss",
    "addr:street":"C;Simon Carter",
    "iso:country":"GB",
    "sg:address":"C/o Simon Carter",
    "sg:city":"London",
    "sg:classifiers":[
        {
            "category":"Arts & Performance",
            "subcategory":"Theater",
            "type":"Entertainment"
        }
    ],
    "sg:postcode":"W1F 9SS",
    "sg:province":"Greater London",
    "sg:tags":[
        "theatrical",
        "agency"
    ],
    "wof:name":"The Spitfire Trust",
    "wof:placetype":"venue"
},
  "geometry": {"coordinates":[-0.1365700066,51.5128517151],"type":"Point"}
}