{
  "type": "Feature",
  "properties": {
    "addr:full":"191 Rushey Grn London Greater London SE6 4BD",
    "addr:housenumber":"191",
    "addr:postcode":"se6 4bd",
    "addr:street":"Rushey Grn",
    "iso:country":"GB",
    "sg:address":"191 Rushey Grn",
    "sg:city":"London",
    "sg:classifiers":[
        {
            "category":"Professional",
            "subcategory":"Lawyer & Legal Services",
            "type":"Services"
        }
    ],
    "sg:phone":"+44 20 8698 9200",
    "sg:postcode":"SE6 4BD",
    "sg:province":"Greater London",
    "sg:tags":[
        "solicitor"
    ],
    "wof:name":"Cocker Morrison Fowler",
    "wof:placetype":"venue"
},
  "geometry": {"coordinates":[-0.0198049992,51.4447822571],"type":"Point"}
}