{
  "type": "Feature",
  "properties": {
    "iso:country":"GB",
    "sg:address":"Unit 12 Capitol Park, Tuffley Trading Estate, Pearce Way",
    "sg:city":"Gloucester",
    "sg:classifiers":[
        {
            "category":"Social Services",
            "subcategory":"Job Training",
            "type":"Services"
        },
        {
            "category":"Building & Trades",
            "subcategory":"Construction",
            "type":"Services"
        }
    ],
    "sg:phone":"+44 1452 504791",
    "sg:postcode":"GL2 5YD",
    "sg:province":"Gloucestershire",
    "sg:tags":[
        "technology",
        "management",
        "traffic",
        "system"
    ],
    "wof:name":"Lux Traffic Controls Ltd.",
    "wof:placetype":"venue"
},
  "geometry": {"coordinates":[-2.2653200626,51.8389511108],"type":"Point"}
}