{
  "type": "Feature",
  "properties": {
    "addr:full":"Unit D, Happy Valley Industrial Estate, Primrose Hill King's Langley Hertfordshire WD4 8HD",
    "addr:housenumber":"unit d;estate",
    "addr:postcode":"wd4 8hd",
    "addr:street":"Happy Valley Industrial;Hill",
    "iso:country":"GB",
    "sg:address":"Unit D, Happy Valley Industrial Estate, Primrose Hill",
    "sg:city":"King's Langley",
    "sg:classifiers":[
        {
            "category":"Manufacturing",
            "subcategory":"Metals",
            "type":"Manufacturing & Wholesale Goods"
        }
    ],
    "sg:phone":"+44 1923 290320",
    "sg:postcode":"WD4 8HD",
    "sg:province":"Hertfordshire",
    "sg:tags":[
        "work",
        "sheet"
    ],
    "wof:name":"D M G Sheet Metal Fabrications",
    "wof:placetype":"venue"
},
  "geometry": {"coordinates":[-0.44398,51.715561],"type":"Point"}
}