{
  "type": "Feature",
  "properties": {
    "addr:full":"Grosvenor Court, Lea Hall Enterprise Park, Armitage Road Rugeley Staffordshire WS15 1LH",
    "addr:postcode":"ws15 1lh",
    "addr:street":"Grosvenor Court Lea;Enterprise Park Armitage Road",
    "iso:country":"GB",
    "sg:address":"Grosvenor Court, Lea Hall Enterprise Park, Armitage Road",
    "sg:city":"Rugeley",
    "sg:classifiers":[
        {
            "category":"Home & Garden",
            "subcategory":"Hardware",
            "type":"Retail Goods"
        }
    ],
    "sg:phone":"+44 1889 577975",
    "sg:postcode":"WS15 1LH",
    "sg:province":"Staffordshire",
    "sg:tags":[
        "generator"
    ],
    "wof:name":"H P International Ltd.",
    "wof:placetype":"venue"
},
  "geometry": {"coordinates":[-1.9135689735,52.7487258911],"type":"Point"}
}