{
  "type": "Feature",
  "properties": {
    "addr:full":"11 Lochend Street Motherwell North Lanarkshire ML1 1RX",
    "addr:housenumber":"11",
    "addr:postcode":"ml1 1rx",
    "addr:street":"Lochend Street",
    "iso:country":"GB",
    "sg:address":"11 Lochend Street",
    "sg:city":"Motherwell",
    "sg:classifiers":[
        {
            "category":"Building & Trades",
            "subcategory":"Construction",
            "type":"Services"
        }
    ],
    "sg:postcode":"ML1 1RX",
    "sg:province":"North Lanarkshire",
    "sg:tags":[
        "decorator",
        "painter"
    ],
    "wof:name":"Dickson Decorators",
    "wof:placetype":"venue"
},
  "geometry": {"coordinates":[-3.9838190079,55.7861061096],"type":"Point"}
}