{
  "type": "Feature",
  "properties": {
    "iso:country":"GB",
    "sg:address":"Unit D Fletchworth Gate",
    "sg:city":"Coventry",
    "sg:classifiers":[
        {
            "category":"Shopping",
            "subcategory":"Comic Books",
            "type":"Retail Goods"
        }
    ],
    "sg:phone":"+44 24 7667 7448",
    "sg:postcode":"CV5 6SP",
    "sg:province":"West Midlands",
    "sg:tags":[
        "jeweller"
    ],
    "wof:name":"Dominic Alan Ltd.",
    "wof:placetype":"venue"
},
  "geometry": {"coordinates":[-1.552796,52.396446],"type":"Point"}
}