{
  "type": "Feature",
  "properties": {
    "addr:full":"33 High Street Holt Norfolk NR25 6BN",
    "addr:housenumber":"33",
    "addr:postcode":"nr25 6bn",
    "addr:street":"High Street",
    "iso:country":"GB",
    "sg:address":"33 High Street",
    "sg:city":"Holt",
    "sg:classifiers":[
        {
            "category":"Shopping",
            "subcategory":"Clothing, Apparel, & Fashions",
            "type":"Retail Goods"
        }
    ],
    "sg:phone":"+44 1263 711230",
    "sg:postcode":"NR25 6BN",
    "sg:province":"Norfolk",
    "sg:tags":[
        "ladieswear"
    ],
    "wof:name":"Nicholsons",
    "wof:placetype":"venue"
},
  "geometry": {"coordinates":[1.087299943,52.9053688049],"type":"Point"}
}