{
  "type": "Feature",
  "properties": {
    "addr:full":"The Studio, Tobys Court, High Street Shaftesbury Dorset SP7 8NA",
    "addr:postcode":"sp7 8na",
    "addr:street":"Tobys;High Street",
    "iso:country":"GB",
    "sg:address":"The Studio, Tobys Court, High Street",
    "sg:city":"Shaftesbury",
    "sg:classifiers":[
        {
            "category":"Professional",
            "type":"Services"
        }
    ],
    "sg:postcode":"SP7 8NA",
    "sg:province":"Dorset",
    "sg:tags":[
        "interior",
        "furnishers",
        "designer"
    ],
    "wof:name":"The Showhouse Shop",
    "wof:placetype":"venue"
},
  "geometry": {"coordinates":[-2.198479,51.006538],"type":"Point"}
}