{
  "type": "Feature",
  "properties": {
    "addr:full":"60 Candleriggs Glasgow Glasgow City G1 1NQ",
    "addr:housenumber":"60",
    "addr:postcode":"g1 1nq",
    "addr:street":"Candleriggs",
    "iso:country":"GB",
    "sg:address":"60 Candleriggs",
    "sg:city":"Glasgow",
    "sg:classifiers":[
        {
            "category":"Arts & Performance",
            "subcategory":"Theater",
            "type":"Entertainment"
        }
    ],
    "sg:phone":"+44 141 287 5004",
    "sg:postcode":"G1 1NQ",
    "sg:province":"Glasgow City",
    "sg:tags":[
        "theatre"
    ],
    "wof:name":"The Scottish Actors Studio",
    "wof:placetype":"venue"
},
  "geometry": {"coordinates":[-4.2462887764,55.8571014404],"type":"Point"}
}