{
  "type": "Feature",
  "properties": {
    "iso:country":"GB",
    "sg:address":"Priory Ringway, Mathouse Circus",
    "sg:city":"Birmingham",
    "sg:classifiers":[
        {
            "category":"Bars & Pubs",
            "type":"Food & Drink"
        }
    ],
    "sg:phone":"+44 121 236 4171",
    "sg:postcode":"B4 7LN",
    "sg:province":"West Midlands",
    "sg:tags":[
        "pubs",
        "inn"
    ],
    "wof:name":"Punch Retail Ltd",
    "wof:placetype":"venue"
},
  "geometry": {"coordinates":[-1.8928899765,52.4812202454],"type":"Point"}
}