{
  "type": "Feature",
  "properties": {
    "addr:full":"30 St Marks Rd Salisbury Wiltshire SP1 3AZ",
    "addr:housenumber":"30",
    "addr:postcode":"sp1 3az",
    "addr:street":"St Marks Rd",
    "iso:country":"GB",
    "sg:address":"30 St Marks Rd",
    "sg:city":"Salisbury",
    "sg:classifiers":[
        {
            "category":"Professional",
            "subcategory":"Lawyer & Legal Services",
            "type":"Services"
        }
    ],
    "sg:phone":"+44 1722 414818",
    "sg:postcode":"SP1 3AZ",
    "sg:province":"Wiltshire",
    "sg:tags":[
        "advice",
        "counselling"
    ],
    "wof:name":"Gail Smalley Bsc Hons PG Dip Counselling",
    "wof:placetype":"venue"
},
  "geometry": {"coordinates":[-1.7884390354,51.0748023987],"type":"Point"}
}