{
  "type": "Feature",
  "properties": {
    "addr:full":"45 Calverley Rd Tunbridge Wells Kent TN1 2TT",
    "addr:housenumber":"45",
    "addr:postcode":"tn1 2tt",
    "addr:street":"Calverley Rd",
    "iso:country":"GB",
    "sg:address":"45 Calverley Rd",
    "sg:city":"Tunbridge Wells",
    "sg:classifiers":[
        {
            "category":"Shopping",
            "subcategory":"Clothing, Apparel, & Fashions",
            "type":"Retail Goods"
        }
    ],
    "sg:phone":"+44 1892 534781",
    "sg:postcode":"TN1 2TT",
    "sg:province":"Kent",
    "sg:tags":[
        "shop"
    ],
    "sg:website":"http://www.evans.co.uk",
    "wof:name":"Evans Ltd",
    "wof:placetype":"venue"
},
  "geometry": {"coordinates":[0.2683899999,51.1327781677],"type":"Point"}
}