{
  "type": "Feature",
  "properties": {
    "addr:full":"83 Harehills Lane Leeds West Yorkshire LS7 4HA",
    "addr:housenumber":"83",
    "addr:postcode":"ls7 4ha",
    "addr:street":"Harehills Lane",
    "iso:country":"GB",
    "sg:address":"83 Harehills Lane",
    "sg:city":"Leeds",
    "sg:classifiers":[
        {
            "category":"Communications",
            "type":"Services"
        }
    ],
    "sg:phone":"+44 113 262 2112",
    "sg:postcode":"LS7 4HA",
    "sg:province":"West Yorkshire",
    "sg:tags":[
        "broadcasting"
    ],
    "wof:name":"Henna Fm",
    "wof:placetype":"venue"
},
  "geometry": {"coordinates":[-1.5227999687,53.8214797974],"type":"Point"}
}