{
  "type": "Feature",
  "properties": {
    "addr:full":"23 Fife Street Sheffield South Yorkshire S9 1NJ",
    "addr:housenumber":"23",
    "addr:postcode":"s9 1nj",
    "addr:street":"Fife Street",
    "iso:country":"GB",
    "sg:address":"23 Fife Street",
    "sg:city":"Sheffield",
    "sg:classifiers":[
        {
            "category":"Organizations",
            "subcategory":"Membership Organization",
            "type":"Services"
        }
    ],
    "sg:phone":"+44 114 249 1265",
    "sg:postcode":"S9 1NJ",
    "sg:province":"South Yorkshire",
    "sg:tags":[
        "club",
        "social"
    ],
    "wof:name":"The Blackburn & Wincobank Conservative Club Ltd.",
    "wof:placetype":"venue"
},
  "geometry": {"coordinates":[-1.4193890095,53.4228439331],"type":"Point"}
}