{
  "type": "Feature",
  "properties": {
    "iso:country":"GB",
    "sg:address":"369 Tormusk Road",
    "sg:city":"Glasgow",
    "sg:classifiers":[
        {
            "category":"Communications",
            "type":"Services"
        },
        {
            "category":"Food & Beverages",
            "subcategory":"Fruits & Vegetables",
            "type":"Retail Goods"
        },
        {
            "category":"Food & Beverages",
            "subcategory":"Groceries & Convenience Stores",
            "type":"Retail Goods"
        }
    ],
    "sg:phone":"+44 141 634 8202",
    "sg:postcode":"G45 0HF",
    "sg:province":"Glasgow City",
    "sg:tags":[
        "grocer",
        "greengrocer",
        "telecommunication"
    ],
    "wof:name":"United Grocers",
    "wof:placetype":"venue"
},
  "geometry": {"coordinates":[-4.215089798,55.8049621582],"type":"Point"}
}