{
  "type": "Feature",
  "properties": {
    "addr:full":"148 New Road, Woodston Peterborough Cambridgeshire PE2 9HG",
    "addr:housenumber":"148",
    "addr:postcode":"pe2 9hg",
    "addr:street":"New Road",
    "iso:country":"GB",
    "sg:address":"148 New Road, Woodston",
    "sg:city":"Peterborough",
    "sg:classifiers":[
        {
            "category":"Building & Trades",
            "subcategory":"Construction",
            "type":"Services"
        }
    ],
    "sg:postcode":"PE2 9HG",
    "sg:province":"Cambridgeshire",
    "sg:tags":[
        "dry",
        "lining",
        "plasterers",
        "screeders"
    ],
    "wof:name":"D N T Plastering",
    "wof:placetype":"venue"
},
  "geometry": {"coordinates":[-0.249905,52.559242],"type":"Point"}
}