{
  "type": "Feature",
  "properties": {
    "addr:full":"Unit 7 Tentercroft Street Industrial, Estate Lincoln Lincolnshire LN5 7ED",
    "addr:housenumber":"unit 7",
    "addr:postcode":"ln5 7ed",
    "addr:street":"Tentercroft Street Industrial",
    "iso:country":"GB",
    "sg:address":"Unit 7 Tentercroft Street Industrial, Estate",
    "sg:city":"Lincoln",
    "sg:classifiers":[
        {
            "category":"Military Area",
            "subcategory":"Air Force Base",
            "type":"Public Place"
        }
    ],
    "sg:phone":"+44 1522 514555",
    "sg:postcode":"LN5 7ED",
    "sg:province":"Lincolnshire",
    "sg:tags":[
        "taxi",
        "hire",
        "private"
    ],
    "wof:name":"A 2 B Taxis",
    "wof:placetype":"venue"
},
  "geometry": {"coordinates":[-0.541159,53.225269],"type":"Point"}
}