{
  "type": "Feature",
  "properties": {
    "iso:country":"GB",
    "sg:address":"King Street",
    "sg:city":"Elgin",
    "sg:classifiers":[
        {
            "category":"Landmark",
            "subcategory":"Tourist Attraction",
            "type":"Public Place"
        }
    ],
    "sg:phone":"+44 1343 547171",
    "sg:postcode":"IV30 1HU",
    "sg:province":"Moray",
    "sg:tags":[
        "interest"
    ],
    "wof:name":"Elgin Cathedral",
    "wof:placetype":"venue"
},
  "geometry": {"coordinates":[-3.3062939644,57.6493301392],"type":"Point"}
}