{
  "type": "Feature",
  "properties": {
    "iso:country":"GB",
    "sg:address":"135 New Bond Street",
    "sg:city":"London",
    "sg:classifiers":[
        {
            "category":"Shopping",
            "subcategory":"Comic Books",
            "type":"Retail Goods"
        }
    ],
    "sg:phone":"+44 20 7493 2299",
    "sg:postcode":"W1S 2TG",
    "sg:province":"Greater London",
    "sg:tags":[
        "jeweller"
    ],
    "wof:name":"Wempe",
    "wof:placetype":"venue"
},
  "geometry": {"coordinates":[-0.1443980038,51.5119895935],"type":"Point"}
}