{
  "type": "Feature",
  "properties": {
    "addr:full":"Cartswell Cottage Morpeth Northumberland NE61 5JW",
    "addr:housenumber":"morpeth",
    "addr:postcode":"ne61 5jw",
    "addr:street":"Northumberland",
    "iso:country":"GB",
    "sg:address":"Cartswell Cottage",
    "sg:city":"Morpeth",
    "sg:classifiers":[
        {
            "category":"Farming",
            "subcategory":"Dairy Farm",
            "type":"Manufacturing & Wholesale Goods"
        }
    ],
    "sg:phone":"+44 1670 860080",
    "sg:postcode":"NE61 5JW",
    "sg:province":"Northumberland",
    "wof:name":"Brian Colleran",
    "wof:placetype":"venue"
},
  "geometry": {"coordinates":[-1.6889289618,55.1673965454],"type":"Point"}
}