{
  "type": "Feature",
  "properties": {
    "iso:country":"GB",
    "sg:address":"13 Westlecot Rd",
    "sg:city":"Swindon",
    "sg:classifiers":[
        {
            "category":"Professional",
            "type":"Services"
        }
    ],
    "sg:postcode":"SN1 4EZ",
    "sg:province":"Wiltshire",
    "sg:tags":[
        "caterer"
    ],
    "wof:name":"Vanity Fare Catering",
    "wof:placetype":"venue"
},
  "geometry": {"coordinates":[-1.781521,51.547829],"type":"Point"}
}