{
  "type": "Feature",
  "properties": {
    "iso:country":"GB",
    "sg:address":"18 Eugene Road",
    "sg:city":"Paignton",
    "sg:classifiers":[
        {
            "category":"Bus Charters",
            "type":"Transportation"
        }
    ],
    "sg:phone":"+44 1803 522149",
    "sg:postcode":"TQ3 2PQ",
    "sg:province":"Devon",
    "sg:tags":[
        "hire",
        "coach"
    ],
    "wof:name":"Torbay Luxiline Coaches",
    "wof:placetype":"venue"
},
  "geometry": {"coordinates":[-3.559212,50.445709],"type":"Point"}
}