{
  "type": "Feature",
  "properties": {
    "iso:country":"GB",
    "sg:address":"1st Floor Huddersfield Road, Darton",
    "sg:city":"Barnsley",
    "sg:classifiers":[
        {
            "category":"Social Services",
            "type":"Services"
        }
    ],
    "sg:phone":"+44 1226 775480",
    "sg:postcode":"S75 5NB",
    "sg:province":"South Yorkshire",
    "wof:name":"Darton Social Services",
    "wof:placetype":"venue"
},
  "geometry": {"coordinates":[-1.55152,53.589592],"type":"Point"}
}