{
  "type": "Feature",
  "properties": {
    "addr:full":"1a Rhoose Road, Rhoose Barry The Vale of Glamorgan CF62 3EQ",
    "addr:housenumber":"1a",
    "addr:postcode":"cf62 3eq",
    "addr:street":"Rhoose Road;Barry;Vale",
    "iso:country":"GB",
    "sg:address":"1a Rhoose Road, Rhoose",
    "sg:city":"Barry",
    "sg:classifiers":[
        {
            "category":"Building & Trades",
            "subcategory":"Construction",
            "type":"Services"
        }
    ],
    "sg:phone":"+44 1446 711541",
    "sg:postcode":"CF62 3EQ",
    "sg:province":"The Vale of Glamorgan",
    "sg:tags":[
        "builder"
    ],
    "wof:name":"D Wright & Sons",
    "wof:placetype":"venue"
},
  "geometry": {"coordinates":[-3.345099,51.391029],"type":"Point"}
}