{
  "type": "Feature",
  "properties": {
    "addr:full":"91 Collingwood Road Sutton Surrey SM1 2QH",
    "addr:housenumber":"91",
    "addr:postcode":"sm1 2qh",
    "addr:street":"Collingwood Road",
    "iso:country":"GB",
    "sg:address":"91 Collingwood Road",
    "sg:city":"Sutton",
    "sg:classifiers":[
        {
            "category":"Professional",
            "subcategory":"Engineering",
            "type":"Services"
        },
        {
            "category":"Building & Trades",
            "subcategory":"Electrical",
            "type":"Services"
        }
    ],
    "sg:phone":"+44 20 8642 8365",
    "sg:postcode":"SM1 2QH",
    "sg:province":"Surrey",
    "sg:tags":[
        "engineer",
        "electrician",
        "contractor"
    ],
    "wof:name":"P F E ELECTRICAL ENGINEERS LTD",
    "wof:placetype":"venue"
},
  "geometry": {"coordinates":[-0.200032,51.367653],"type":"Point"}
}