{
  "type": "Feature",
  "properties": {
    "iso:country":"GB",
    "sg:address":"Murtry Hill House, Buckland Dinham",
    "sg:city":"Frome",
    "sg:classifiers":[
        {
            "category":"Professional",
            "subcategory":"Management & Consulting",
            "type":"Services"
        }
    ],
    "sg:phone":"+44 1373 464384",
    "sg:postcode":"BA11 2QJ",
    "sg:province":"Somerset",
    "sg:tags":[
        "consultant",
        "business"
    ],
    "wof:name":"THE WESTACOTT CONSULTANCY",
    "wof:placetype":"venue"
},
  "geometry": {"coordinates":[-2.318807,51.228558],"type":"Point"}
}