{
  "type": "Feature",
  "properties": {
    "addr:full":"Abinger Street Burnley Lancashire BB10 3ED",
    "addr:postcode":"bb10 3ed",
    "addr:street":"Abinger Street",
    "iso:country":"GB",
    "sg:address":"Abinger Street",
    "sg:city":"Burnley",
    "sg:classifiers":[
        {
            "category":"Arena",
            "subcategory":"Sports Club",
            "type":"Entertainment"
        }
    ],
    "sg:phone":"+44 1282 422410",
    "sg:postcode":"BB10 3ED",
    "sg:province":"Lancashire",
    "wof:name":"St. Andrews Cricket & Bowling Club",
    "wof:placetype":"venue"
},
  "geometry": {"coordinates":[-2.2258388996,53.8039360046],"type":"Point"}
}