{
  "type": "Feature",
  "properties": {
    "addr:full":"Lakeside Industrial Estate, Colnbrook By Pass Slough Berkshire SL3 0EL",
    "addr:postcode":"sl3 0el",
    "addr:street":"By Pass",
    "iso:country":"GB",
    "sg:address":"Lakeside Industrial Estate, Colnbrook By Pass",
    "sg:city":"Slough",
    "sg:classifiers":[
        {
            "category":"Freight",
            "type":"Transportation"
        }
    ],
    "sg:phone":"+44 1753 683125",
    "sg:postcode":"SL3 0EL",
    "sg:province":"Berkshire",
    "sg:tags":[
        "forwarders"
    ],
    "wof:name":"Annorealm Ltd.",
    "wof:placetype":"venue"
},
  "geometry": {"coordinates":[-0.526976,51.484173],"type":"Point"}
}