{
  "type": "Feature",
  "properties": {
    "addr:full":"Park Drive Parade, Park Drive Colchester Essex CO7 0UD",
    "addr:postcode":"co7 0ud",
    "addr:street":"Park Drive Parade Park Drive",
    "iso:country":"GB",
    "sg:address":"Park Drive Parade, Park Drive",
    "sg:city":"Colchester",
    "sg:classifiers":[
        {
            "category":"Food & Beverages",
            "subcategory":"Supermarket",
            "type":"Retail Goods"
        }
    ],
    "sg:phone":"+44 1206 302663",
    "sg:postcode":"CO7 0UD",
    "sg:province":"Essex",
    "wof:name":"Manor Convenience Store",
    "wof:placetype":"venue"
},
  "geometry": {"coordinates":[1.0162400007,51.8153839111],"type":"Point"}
}