{
  "type": "Feature",
  "properties": {
    "iso:country":"GB",
    "sg:address":"Carlton Industrial Estate, Albion Road",
    "sg:city":"Barnsley",
    "sg:classifiers":[
        {
            "category":"Manufacturing",
            "subcategory":"Lumber",
            "type":"Manufacturing & Wholesale Goods"
        }
    ],
    "sg:postcode":"S71 3HW",
    "sg:province":"South Yorkshire",
    "sg:tags":[
        "importer",
        "merchants",
        "agent",
        "timber"
    ],
    "wof:name":"Barnsley Timber Merchants Ltd.",
    "wof:placetype":"venue"
},
  "geometry": {"coordinates":[-1.4520109892,53.5839767456],"type":"Point"}
}