{
  "type": "Feature",
  "properties": {
    "addr:full":"177 Hangleton Way Hove East Sussex BN3 8EY",
    "addr:housenumber":"177",
    "addr:postcode":"bn3 8ey",
    "addr:street":"Hangleton Way",
    "iso:country":"GB",
    "sg:address":"177 Hangleton Way",
    "sg:city":"Hove",
    "sg:classifiers":[
        {
            "category":"Retail",
            "subcategory":"Veterinary Services",
            "type":"Services"
        }
    ],
    "sg:phone":"+44 1273 430301",
    "sg:postcode":"BN3 8EY",
    "sg:province":"East Sussex",
    "sg:tags":[
        "surgeon"
    ],
    "wof:name":"Acorn House Veterinary Surgery",
    "wof:placetype":"venue"
},
  "geometry": {"coordinates":[-0.1980759948,50.8525924683],"type":"Point"}
}