{
  "type": "Feature",
  "properties": {
    "addr:full":"39 The Bdwy Epsom Surrey KT17 2JE",
    "addr:housenumber":"39;bdwy",
    "addr:postcode":"kt17 2je",
    "addr:street":"The",
    "iso:country":"GB",
    "sg:address":"39 The Bdwy",
    "sg:city":"Epsom",
    "sg:classifiers":[
        {
            "category":"Communications",
            "type":"Services"
        }
    ],
    "sg:postcode":"KT17 2JE",
    "sg:province":"Surrey",
    "sg:tags":[
        "tv",
        "video",
        "radio"
    ],
    "wof:name":"Stoneleigh Trading Co",
    "wof:placetype":"venue"
},
  "geometry": {"coordinates":[-0.2463099957,51.3629798889],"type":"Point"}
}