{
  "type": "Feature",
  "properties": {
    "addr:full":"Woolrow Farm, Woolrow Lane Brighouse West Yorkshire HD6 4JN",
    "addr:postcode":"hd6 4jn",
    "addr:street":"Woolrow Lane",
    "iso:country":"GB",
    "sg:address":"Woolrow Farm, Woolrow Lane",
    "sg:city":"Brighouse",
    "sg:classifiers":[
        {
            "category":"Farming",
            "subcategory":"Livestock Farm",
            "type":"Manufacturing & Wholesale Goods"
        }
    ],
    "sg:phone":"+44 1274 871427",
    "sg:postcode":"HD6 4JN",
    "sg:province":"West Yorkshire",
    "sg:tags":[
        "others"
    ],
    "wof:name":"David Gibson",
    "wof:placetype":"venue"
},
  "geometry": {"coordinates":[-1.773737,53.702194],"type":"Point"}
}