{
  "type": "Feature",
  "properties": {
    "addr:full":"165 Norden Road, Bamford Rochdale Lancashire OL11 5PT",
    "addr:housenumber":"165",
    "addr:postcode":"ol11 5pt",
    "addr:street":"Norden Road",
    "iso:country":"GB",
    "sg:address":"165 Norden Road, Bamford",
    "sg:city":"Rochdale",
    "sg:classifiers":[
        {
            "category":"Professional",
            "subcategory":"Management & Consulting",
            "type":"Services"
        }
    ],
    "sg:phone":"+44 1706 869500",
    "sg:postcode":"OL11 5PT",
    "sg:province":"Lancashire",
    "sg:tags":[
        "consultant",
        "business"
    ],
    "wof:name":"Quercetum Ltd.",
    "wof:placetype":"venue"
},
  "geometry": {"coordinates":[-2.2065420151,53.6158790588],"type":"Point"}
}