{
  "type": "Feature",
  "properties": {
    "iso:country":"GB",
    "sg:address":"Ruislip Road East",
    "sg:city":"West Ealing",
    "sg:classifiers":[
        {
            "category":"Sports & Exercise",
            "subcategory":"Swimming Pool",
            "type":"Entertainment"
        }
    ],
    "sg:phone":"+44 181 998 3241",
    "sg:postcode":"W13 0AL",
    "sg:province":"Greater London",
    "wof:name":"Gurnell Swimming Pool",
    "wof:placetype":"venue"
},
  "geometry": {"coordinates":[-0.328129,51.528725],"type":"Point"}
}