{
  "type": "Feature",
  "properties": {
    "iso:country":"GB",
    "sg:address":"128 Aigburth Road",
    "sg:city":"Liverpool",
    "sg:classifiers":[
        {
            "category":"Professional",
            "subcategory":"Business Services",
            "type":"Services"
        }
    ],
    "sg:phone":"+44 151 726 0975",
    "sg:postcode":"L17 7BP",
    "sg:province":"Merseyside",
    "sg:tags":[
        "bookmaker"
    ],
    "wof:name":"Cheshire Racing (Cash Betting) 1986",
    "wof:placetype":"venue"
},
  "geometry": {"coordinates":[-2.9509859085,53.3795127869],"type":"Point"}
}