{
  "type": "Feature",
  "properties": {
    "addr:full":"10 Watlington Road Oxford Oxfordshire OX4 2UF",
    "addr:housenumber":"10",
    "addr:postcode":"ox4 2uf",
    "addr:street":"Watlington Road",
    "iso:country":"GB",
    "sg:address":"10 Watlington Road",
    "sg:city":"Oxford",
    "sg:classifiers":[
        {
            "category":"Building & Trades",
            "subcategory":"Plumbing",
            "type":"Services"
        }
    ],
    "sg:phone":"+44 1865 749999",
    "sg:postcode":"OX4 2UF",
    "sg:province":"Oxfordshire",
    "sg:tags":[
        "central",
        "heating"
    ],
    "wof:name":"Aquatec",
    "wof:placetype":"venue"
},
  "geometry": {"coordinates":[-1.194829,51.726318],"type":"Point"}
}