{
  "type": "Feature",
  "properties": {
    "addr:full":"31 Powell Gardens Newhaven East Sussex BN9 0PS",
    "addr:housenumber":"31",
    "addr:postcode":"bn9 0ps",
    "addr:street":"Powell Gardens",
    "iso:country":"GB",
    "sg:address":"31 Powell Gardens",
    "sg:city":"Newhaven",
    "sg:classifiers":[
        {
            "category":"Building & Trades",
            "subcategory":"Landscaping Services",
            "type":"Services"
        },
        {
            "category":"Professional",
            "subcategory":"Credit Reporting & Collection",
            "type":"Services"
        }
    ],
    "sg:postcode":"BN9 0PS",
    "sg:province":"East Sussex",
    "sg:tags":[
        "collecting",
        "agency",
        "gardening"
    ],
    "wof:name":"South Coast Debt Recovery",
    "wof:placetype":"venue"
},
  "geometry": {"coordinates":[0.0569150001,50.8032608032],"type":"Point"}
}