{
  "type": "Feature",
  "properties": {
    "addr:full":"41 Cherrydown Close London Greater London E4 8DY",
    "addr:housenumber":"41",
    "addr:postcode":"e4 8dy",
    "addr:street":"Cherrydown Close",
    "iso:country":"GB",
    "sg:address":"41 Cherrydown Close",
    "sg:city":"London",
    "sg:classifiers":[
        {
            "category":"Recreation",
            "subcategory":"Amusement Park",
            "type":"Entertainment"
        }
    ],
    "sg:phone":"+44 20 8529 7634",
    "sg:postcode":"E4 8DY",
    "sg:province":"Greater London",
    "sg:tags":[
        "arcade"
    ],
    "wof:name":"Offord & Co",
    "wof:placetype":"venue"
},
  "geometry": {"coordinates":[-0.022035,51.621059],"type":"Point"}
}