{
  "type": "Feature",
  "properties": {
    "addr:full":"Yew Tree Studios, Stanford North Ashford Kent TN25 6DH",
    "addr:postcode":"tn25 6dh",
    "addr:street":"Yew;North",
    "iso:country":"GB",
    "sg:address":"Yew Tree Studios, Stanford North",
    "sg:city":"Ashford",
    "sg:classifiers":[
        {
            "category":"Recreation",
            "type":"Entertainment"
        }
    ],
    "sg:phone":"+44 800 032 5060",
    "sg:postcode":"TN25 6DH",
    "sg:province":"Kent",
    "sg:tags":[
        "hot",
        "balloon",
        "air"
    ],
    "wof:name":"Sky Trek Ballooning",
    "wof:placetype":"venue"
},
  "geometry": {"coordinates":[1.040275,51.101974],"type":"Point"}
}