{
  "type": "Feature",
  "properties": {
    "addr:full":"53 High Street Lymington Hampshire SO41 9ZB",
    "addr:housenumber":"53",
    "addr:postcode":"so41 9zb",
    "addr:street":"High Street",
    "iso:country":"GB",
    "sg:address":"53 High Street",
    "sg:city":"Lymington",
    "sg:classifiers":[
        {
            "category":"Real Estate",
            "subcategory":"Surveying",
            "type":"Services"
        }
    ],
    "sg:phone":"+44 1590 677233",
    "sg:postcode":"SO41 9ZB",
    "sg:province":"Hampshire",
    "sg:tags":[
        "surveyor",
        "valuer"
    ],
    "wof:name":"Home From Home Ltd.",
    "wof:placetype":"venue"
},
  "geometry": {"coordinates":[-1.544603,50.757488],"type":"Point"}
}