{
  "type": "Feature",
  "properties": {
    "iso:country":"GB",
    "sg:address":"404 Oxford Road, Gomersal",
    "sg:city":"Cleckheaton",
    "sg:classifiers":[
        {
            "category":"Bars & Pubs",
            "type":"Food & Drink"
        }
    ],
    "sg:phone":"+44 1274 872219",
    "sg:postcode":"BD19 4JZ",
    "sg:province":"West Yorkshire",
    "sg:tags":[
        "pubs",
        "inn"
    ],
    "wof:name":"Punch Retail Ltd.",
    "wof:placetype":"venue"
},
  "geometry": {"coordinates":[-1.686934,53.734703],"type":"Point"}
}