{
  "type": "Feature",
  "properties": {
    "addr:full":"Borough Corn Mill, Annie Street, Rawtenstall Rossendale Lancashire BB4 7NA",
    "addr:postcode":"bb4 7na",
    "addr:street":"Corn;Annie Street",
    "iso:country":"GB",
    "sg:address":"Borough Corn Mill, Annie Street, Rawtenstall",
    "sg:city":"Rossendale",
    "sg:classifiers":[
        {
            "category":"Manufacturing",
            "subcategory":"Food",
            "type":"Manufacturing & Wholesale Goods"
        }
    ],
    "sg:postcode":"BB4 7NA",
    "sg:province":"Lancashire",
    "sg:tags":[
        "miller",
        "mill"
    ],
    "wof:name":"T E Mansergh (Bury) Ltd.",
    "wof:placetype":"venue"
},
  "geometry": {"coordinates":[-2.2798690796,53.7003707886],"type":"Point"}
}