{
  "type": "Feature",
  "properties": {
    "iso:country":"GB",
    "sg:address":"22 Silver Street Lane",
    "sg:city":"Trowbridge",
    "sg:classifiers":[
        {
            "category":"Freight",
            "type":"Transportation"
        },
        {
            "category":"Government",
            "subcategory":"Post Office",
            "type":"Public Place"
        }
    ],
    "sg:phone":"+44 1225 777095",
    "sg:postcode":"BA14 0JN",
    "sg:province":"Wiltshire",
    "sg:tags":[
        "haulage",
        "messenger",
        "courier",
        "road"
    ],
    "wof:name":"Trowbridge Despatch",
    "wof:placetype":"venue"
},
  "geometry": {"coordinates":[-2.214399,51.306091],"type":"Point"}
}