{
  "type": "Feature",
  "properties": {
    "addr:full":"5 The Macies Bath Bath and North East Somerset BA1 4HS",
    "addr:housenumber":"5",
    "addr:postcode":"ba1 4hs",
    "addr:street":"The Macies Bath",
    "iso:country":"GB",
    "sg:address":"5 The Macies",
    "sg:city":"Bath",
    "sg:classifiers":[
        {
            "category":"Professional",
            "subcategory":"Engineering",
            "type":"Services"
        }
    ],
    "sg:phone":"+44 1225 333722",
    "sg:postcode":"BA1 4HS",
    "sg:province":"Bath and North East Somerset",
    "sg:tags":[
        "contractor",
        "electrical",
        "engineer"
    ],
    "wof:name":"P.P.S. Electrical",
    "wof:placetype":"venue"
},
  "geometry": {"coordinates":[-2.3951931,51.4018745422],"type":"Point"}
}