{
  "type": "Feature",
  "properties": {
    "addr:full":"36 Clarendon Rd Watford Hertfordshire WD1 1JP",
    "addr:housenumber":"36",
    "addr:postcode":"wd1 1jp",
    "addr:street":"Clarendon Rd",
    "iso:country":"GB",
    "sg:address":"36 Clarendon Rd",
    "sg:city":"Watford",
    "sg:classifiers":[
        {
            "category":"Government",
            "subcategory":"Office",
            "type":"Public Place"
        }
    ],
    "sg:phone":"+44 1923 240144",
    "sg:postcode":"WD1 1JP",
    "sg:province":"Hertfordshire",
    "sg:tags":[
        "central"
    ],
    "wof:name":"Hertfordshire Probation Service",
    "wof:placetype":"venue"
},
  "geometry": {"coordinates":[-0.3967570066,51.6593856812],"type":"Point"}
}