{
  "type": "Feature",
  "properties": {
    "addr:full":"Wyndham Street, Ogmore Vale Bridgend Bridgend CF32 7EU",
    "addr:postcode":"cf32 7eu",
    "addr:street":"Wyndham Street",
    "iso:country":"GB",
    "sg:address":"Wyndham Street, Ogmore Vale",
    "sg:city":"Bridgend",
    "sg:classifiers":[
        {
            "category":"Bars & Pubs",
            "type":"Food & Drink"
        },
        {
            "category":"Community Center",
            "subcategory":"Social",
            "type":"Public Place"
        }
    ],
    "sg:phone":"+44 1656 840392",
    "sg:postcode":"CF32 7EU",
    "sg:province":"Bridgend",
    "sg:tags":[
        "pubs",
        "house",
        "inn",
        "activity"
    ],
    "wof:name":"The Wyndham Arms",
    "wof:placetype":"venue"
},
  "geometry": {"coordinates":[-3.5430541039,51.6138458252],"type":"Point"}
}