{
  "type": "Feature",
  "properties": {
    "addr:full":"St Michaels Close, Penkridge Stafford Shropshire ST19 5AD",
    "addr:postcode":"st19 5ad",
    "addr:street":"St Michaels Close",
    "iso:country":"GB",
    "sg:address":"St Michaels Close, Penkridge",
    "sg:city":"Stafford",
    "sg:classifiers":[
        {
            "category":"Shopping",
            "subcategory":"Pharmacy",
            "type":"Retail Goods"
        }
    ],
    "sg:postcode":"ST19 5AD",
    "sg:province":"Shropshire",
    "sg:tags":[
        "pharmacist",
        "chemist"
    ],
    "wof:name":"Northwood,G & B A,",
    "wof:placetype":"venue"
},
  "geometry": {"coordinates":[-2.1186740398,52.7231178284],"type":"Point"}
}