{
  "type": "Feature",
  "properties": {
    "addr:full":"10-12 Carlton Street Nottingham Nottinghamshire NG1 1NN",
    "addr:housenumber":"10-12",
    "addr:postcode":"ng1 1nn",
    "addr:street":"Carlton Street",
    "iso:country":"GB",
    "sg:address":"10-12 Carlton Street",
    "sg:city":"Nottingham",
    "sg:classifiers":[
        {
            "category":"Manufacturing",
            "subcategory":"Tools & Machinery",
            "type":"Manufacturing & Wholesale Goods"
        }
    ],
    "sg:phone":"+44 115 959 9205",
    "sg:postcode":"NG1 1NN",
    "sg:province":"Nottinghamshire",
    "sg:tags":[
        "society",
        "friendly"
    ],
    "wof:name":"Dragoon Insurance Services Ltd.",
    "wof:placetype":"venue"
},
  "geometry": {"coordinates":[-1.144875,52.953426],"type":"Point"}
}