{
  "type": "Feature",
  "properties": {
    "addr:full":"Hilltop Works, Old Oak Common Lane London Greater London NW10 6DY",
    "addr:postcode":"nw10 6dy",
    "addr:street":"Old Oak Common Lane",
    "iso:country":"GB",
    "sg:address":"Hilltop Works, Old Oak Common Lane",
    "sg:city":"London",
    "sg:classifiers":[
        {
            "category":"Home & Garden",
            "subcategory":"Home Furnishings",
            "type":"Retail Goods"
        },
        {
            "category":"Professional",
            "subcategory":"Business Services",
            "type":"Services"
        }
    ],
    "sg:phone":"+44 20 8961 9408",
    "sg:postcode":"NW10 6DY",
    "sg:province":"Greater London",
    "sg:tags":[
        "import",
        "export",
        "soft",
        "agent"
    ],
    "wof:name":"Daniel James International Ltd.",
    "wof:placetype":"venue"
},
  "geometry": {"coordinates":[-0.2507809997,51.527923584],"type":"Point"}
}