{
  "type": "Feature",
  "properties": {
    "addr:full":"Llandaff Court, Fairwater Road, Llandaff Cardiff Cardiff CF5 2LN",
    "addr:postcode":"cf5 2ln",
    "addr:street":"Llandaff Court Fairwater Road",
    "iso:country":"GB",
    "sg:address":"Llandaff Court, Fairwater Road, Llandaff",
    "sg:city":"Cardiff",
    "sg:classifiers":[
        {
            "category":"Government",
            "subcategory":"Office",
            "type":"Public Place"
        }
    ],
    "sg:phone":"+44 29 2056 7949",
    "sg:postcode":"CF5 2LN",
    "sg:province":"Cardiff",
    "sg:tags":[
        "local"
    ],
    "wof:name":"Insole Gardens",
    "wof:placetype":"venue"
},
  "geometry": {"coordinates":[-3.2264640331,51.4940681458],"type":"Point"}
}