{
  "type": "Feature",
  "properties": {
    "addr:full":"67 May Lane, Hollywood Birmingham Worcestershire B47 5PA",
    "addr:housenumber":"67",
    "addr:postcode":"b47 5pa",
    "addr:street":"May Lane",
    "iso:country":"GB",
    "sg:address":"67 May Lane, Hollywood",
    "sg:city":"Birmingham",
    "sg:classifiers":[
        {
            "category":"Shopping",
            "subcategory":"Florist",
            "type":"Retail Goods"
        }
    ],
    "sg:postcode":"B47 5PA",
    "sg:province":"Worcestershire",
    "wof:name":"Hollywood Flowers",
    "wof:placetype":"venue"
},
  "geometry": {"coordinates":[-1.8794209957,52.3911628723],"type":"Point"}
}