{
  "type": "Feature",
  "properties": {
    "iso:country":"GB",
    "sg:address":"6 Pear Tree Clo",
    "sg:city":"Fordingbridge",
    "sg:classifiers":[
        {
            "category":"Professional",
            "subcategory":"Art Services",
            "type":"Services"
        }
    ],
    "sg:phone":"+44 1425 653456",
    "sg:postcode":"SP6 3ER",
    "sg:province":"Dorset",
    "sg:tags":[
        "model",
        "maker"
    ],
    "wof:name":"Nylet",
    "wof:placetype":"venue"
},
  "geometry": {"coordinates":[-1.8326450586,50.9120635986],"type":"Point"}
}