{
  "type": "Feature",
  "properties": {
    "iso:country":"GB",
    "sg:address":"Unit 3",
    "sg:city":"Slough",
    "sg:classifiers":[
        {
            "category":"Manufacturing",
            "subcategory":"Paper Products",
            "type":"Manufacturing & Wholesale Goods"
        }
    ],
    "sg:phone":"+44 1753 526565",
    "sg:postcode":"SL1 4XX",
    "sg:province":"Berkshire",
    "sg:tags":[
        "cardboard"
    ],
    "wof:name":"Smurfit Tubes (Slough) Ltd.",
    "wof:placetype":"venue"
},
  "geometry": {"coordinates":[-0.596417,51.507874],"type":"Point"}
}