{
  "type": "Feature",
  "properties": {
    "addr:full":"Moorside Colchester Essex CO1 2TJ",
    "addr:postcode":"co1 2tj",
    "addr:street":"Colchester",
    "iso:country":"GB",
    "sg:address":"Moorside",
    "sg:city":"Colchester",
    "sg:classifiers":[
        {
            "category":"Professional",
            "subcategory":"Engineering",
            "type":"Services"
        }
    ],
    "sg:phone":"+44 1206 867141",
    "sg:postcode":"CO1 2TJ",
    "sg:province":"Essex",
    "sg:tags":[
        "engineer"
    ],
    "wof:name":"D K Moriarty Ltd",
    "wof:placetype":"venue"
},
  "geometry": {"coordinates":[0.9185450077,51.8901290894],"type":"Point"}
}