{
  "type": "Feature",
  "properties": {
    "iso:country":"GB",
    "sg:address":"120 Hill Mountain, Houghton",
    "sg:city":"Milford Haven",
    "sg:classifiers":[
        {
            "category":"Shopping",
            "subcategory":"Department Store",
            "type":"Retail Goods"
        }
    ],
    "sg:phone":"+44 1646 601771",
    "sg:postcode":"SA73 1NB",
    "sg:province":"Pembrokeshire",
    "wof:name":"Glendale Stores",
    "wof:placetype":"venue"
},
  "geometry": {"coordinates":[-4.9233388901,51.7344894409],"type":"Point"}
}