{
  "type": "Feature",
  "properties": {
    "addr:full":"Coast Road South Shields Tyne and Wear NE34 7BS",
    "addr:postcode":"ne34 7bs",
    "addr:street":"Coast Road",
    "iso:country":"GB",
    "sg:address":"Coast Road",
    "sg:city":"South Shields",
    "sg:classifiers":[
        {
            "category":"Restaurant",
            "type":"Food & Drink"
        }
    ],
    "sg:phone":"+44 191 455 6060",
    "sg:postcode":"NE34 7BS",
    "sg:province":"Tyne and Wear",
    "sg:tags":[
        "seafood",
        "-"
    ],
    "wof:name":"The Marsden Grotto",
    "wof:placetype":"venue"
},
  "geometry": {"coordinates":[-1.3951940536,54.9853897095],"type":"Point"}
}