{
  "type": "Feature",
  "properties": {
    "addr:full":"105 Market Street St Andrews Fife KY16 9NX",
    "addr:housenumber":"105",
    "addr:postcode":"ky16 9nx",
    "addr:street":"Market Street",
    "iso:country":"GB",
    "sg:address":"105 Market Street",
    "sg:city":"St Andrews",
    "sg:classifiers":[
        {
            "category":"Shopping",
            "subcategory":"Clothing, Apparel, & Fashions",
            "type":"Retail Goods"
        }
    ],
    "sg:phone":"+44 1334 472123",
    "sg:postcode":"KY16 9NX",
    "sg:province":"Fife",
    "sg:tags":[
        "shop"
    ],
    "wof:name":"Wilkie's",
    "wof:placetype":"venue"
},
  "geometry": {"coordinates":[-2.79661,56.340652],"type":"Point"}
}