{
  "type": "Feature",
  "properties": {
    "iso:country":"GB",
    "sg:address":"9 Rockcliffe",
    "sg:city":"Whitley Bay",
    "sg:classifiers":[
        {
            "category":"Health Services",
            "subcategory":"Clinic",
            "type":"Services"
        }
    ],
    "sg:phone":"+44 191 251 5351",
    "sg:postcode":"NE26 2BG",
    "sg:province":"Northumberland",
    "sg:tags":[
        "aromatherapy"
    ],
    "wof:name":"Ladies Roamatherapist",
    "wof:placetype":"venue"
},
  "geometry": {"coordinates":[-1.433734,55.040649],"type":"Point"}
}