{
  "type": "Feature",
  "properties": {
    "iso:country":"GB",
    "sg:address":"Unit 6-6a Harrison Trading Estate, Crompton Street",
    "sg:city":"Preston",
    "sg:classifiers":[
        {
            "category":"Shopping",
            "subcategory":"Clothing, Apparel, & Fashions",
            "type":"Retail Goods"
        }
    ],
    "sg:phone":"+44 1772 704080",
    "sg:postcode":"PR1 5RT",
    "sg:province":"Lancashire",
    "sg:tags":[
        "clothing"
    ],
    "wof:name":"City Look",
    "wof:placetype":"venue"
},
  "geometry": {"coordinates":[-2.7057290077,53.7579612732],"type":"Point"}
}