{
  "type": "Feature",
  "properties": {
    "iso:country":"GB",
    "sg:address":"Gas Works Road, Off Kenavon Drive",
    "sg:city":"Reading",
    "sg:classifiers":[
        {
            "category":"Museum",
            "subcategory":"Art Museum",
            "type":"Entertainment"
        },
        {
            "category":"Government",
            "subcategory":"Office",
            "type":"Public Place"
        }
    ],
    "sg:phone":"+44 118 939 0918",
    "sg:postcode":"RG1 3DH",
    "sg:province":"Berkshire",
    "sg:tags":[
        "local",
        "gallery"
    ],
    "wof:name":"Blake's Lock Museum",
    "wof:placetype":"venue"
},
  "geometry": {"coordinates":[-0.9596120119,51.4556083679],"type":"Point"}
}