{
  "type": "Feature",
  "properties": {
    "addr:full":"16 Blackhorse Lane, Swavesey Cambridge Cambridgeshire CB4 5QR",
    "addr:housenumber":"16",
    "addr:postcode":"cb4 5qr",
    "addr:street":"Blackhorse Lane",
    "iso:country":"GB",
    "sg:address":"16 Blackhorse Lane, Swavesey",
    "sg:city":"Cambridge",
    "sg:classifiers":[
        {
            "category":"Military Area",
            "subcategory":"Air Force Base",
            "type":"Public Place"
        }
    ],
    "sg:phone":"+44 1954 206090",
    "sg:postcode":"CB4 5QR",
    "sg:province":"Cambridgeshire",
    "sg:tags":[
        "water",
        "treatment"
    ],
    "wof:name":"Aquasilk Ltd.",
    "wof:placetype":"venue"
},
  "geometry": {"coordinates":[-0.00599,52.30106],"type":"Point"}
}