{
  "type": "Feature",
  "properties": {
    "iso:country":"GB",
    "sg:address":"40 Cambrian Road",
    "sg:city":"Newport",
    "sg:classifiers":[
        {
            "category":"Retail",
            "subcategory":"Laundry & Dry Cleaning",
            "type":"Services"
        }
    ],
    "sg:phone":"+44 1633 267032",
    "sg:postcode":"NP9 4AB",
    "sg:province":"East Riding of Yorkshire",
    "sg:tags":[
        "alteration"
    ],
    "wof:name":"Sketchley Dry Cleaners",
    "wof:placetype":"venue"
},
  "geometry": {"coordinates":[-2.9981360435,51.5890731812],"type":"Point"}
}