{
  "type": "Feature",
  "properties": {
    "iso:country":"GB",
    "sg:address":"Falcon Works, Lynton Road",
    "sg:city":"London",
    "sg:classifiers":[
        {
            "category":"Shopping",
            "type":"Retail Goods"
        }
    ],
    "sg:phone":"+44 20 7237 1721",
    "sg:postcode":"SE1 5DG",
    "sg:province":"Greater London",
    "sg:tags":[
        "bag"
    ],
    "wof:name":"Thomas Norman Ltd.",
    "wof:placetype":"venue"
},
  "geometry": {"coordinates":[-0.0612,51.489891],"type":"Point"}
}