{
  "type": "Feature",
  "properties": {
    "addr:full":"107 Midland Road Bedford Bedfordshire MK40 1DB",
    "addr:housenumber":"107",
    "addr:postcode":"mk40 1db",
    "addr:street":"Midland Road",
    "iso:country":"GB",
    "sg:address":"107 Midland Road",
    "sg:city":"Bedford",
    "sg:classifiers":[
        {
            "category":"Manufacturing",
            "subcategory":"Tools & Machinery",
            "type":"Manufacturing & Wholesale Goods"
        }
    ],
    "sg:phone":"+44 1234 217744",
    "sg:postcode":"MK40 1DB",
    "sg:province":"Bedfordshire",
    "wof:name":"Cooks of Bedford Ltd.",
    "wof:placetype":"venue"
},
  "geometry": {"coordinates":[-0.473841,52.135757],"type":"Point"}
}