{
  "type": "Feature",
  "properties": {
    "addr:full":"33 Whitehorse Street Baldock Bedfordshire SG7 6QF",
    "addr:housenumber":"33",
    "addr:postcode":"sg7 6qf",
    "addr:street":"Whitehorse Street",
    "iso:country":"GB",
    "sg:address":"33 Whitehorse Street",
    "sg:city":"Baldock",
    "sg:classifiers":[
        {
            "category":"Retail",
            "subcategory":"Repair Shop",
            "type":"Services"
        }
    ],
    "sg:phone":"+44 1462 892385",
    "sg:postcode":"SG7 6QF",
    "sg:province":"Bedfordshire",
    "sg:tags":[
        "clocks",
        "watch"
    ],
    "wof:name":"Howard's",
    "wof:placetype":"venue"
},
  "geometry": {"coordinates":[-0.187053,51.991035],"type":"Point"}
}