{
  "type": "Feature",
  "properties": {
    "addr:full":"9 Stockwell Gate Mansfield Nottinghamshire NG18 1JY",
    "addr:housenumber":"9",
    "addr:postcode":"ng18 1jy",
    "addr:street":"Stockwell Gate",
    "iso:country":"GB",
    "sg:address":"9 Stockwell Gate",
    "sg:city":"Mansfield",
    "sg:classifiers":[
        {
            "category":"Banks & Credit Unions",
            "subcategory":"Financial Services",
            "type":"Services"
        }
    ],
    "sg:phone":"+44 1623 649911",
    "sg:postcode":"NG18 1JY",
    "sg:province":"Nottinghamshire",
    "sg:tags":[
        "building",
        "society"
    ],
    "wof:name":"Alliance & Leicester Plc",
    "wof:placetype":"venue"
},
  "geometry": {"coordinates":[-1.2011320591,53.1435508728],"type":"Point"}
}