{
  "type": "Feature",
  "properties": {
    "iso:country":"GB",
    "sg:address":"2nd Floor, 54 Warwick Sq",
    "sg:city":"Westminster",
    "sg:classifiers":[
        {
            "category":"Social Services",
            "subcategory":"Job Training",
            "type":"Services"
        }
    ],
    "sg:phone":"+44 20 7630 0161",
    "sg:postcode":"SW1V 2AJ",
    "sg:province":"Greater London",
    "wof:name":"Chisholm Roth & Co Ltd",
    "wof:placetype":"venue"
},
  "geometry": {"coordinates":[-0.140835,51.490391],"type":"Point"}
}