{
  "type": "Feature",
  "properties": {
    "addr:full":"23 Tiverton Drive Nuneaton Leicestershire CV11 6YJ",
    "addr:housenumber":"23",
    "addr:postcode":"cv11 6yj",
    "addr:street":"Tiverton Drive",
    "iso:country":"GB",
    "sg:address":"23 Tiverton Drive",
    "sg:city":"Nuneaton",
    "sg:classifiers":[
        {
            "category":"Professional",
            "subcategory":"Engineering",
            "type":"Services"
        },
        {
            "category":"Building & Trades",
            "subcategory":"Electrical",
            "type":"Services"
        }
    ],
    "sg:phone":"+44 24 7632 7408",
    "sg:postcode":"CV11 6YJ",
    "sg:province":"Leicestershire",
    "sg:tags":[
        "engineer",
        "electrician",
        "contractor"
    ],
    "wof:name":"G A Pratt",
    "wof:placetype":"venue"
},
  "geometry": {"coordinates":[-1.4498939514,52.5267906189],"type":"Point"}
}