{
  "type": "Feature",
  "properties": {
    "addr:full":"Workshop, Catterall Gates Lane, Catterall Preston Lancashire PR3 1XP",
    "addr:housenumber":"catterall",
    "addr:postcode":"pr3 1xp",
    "addr:street":"Gates Lane",
    "iso:country":"GB",
    "sg:address":"Workshop, Catterall Gates Lane, Catterall",
    "sg:city":"Preston",
    "sg:classifiers":[
        {
            "category":"Retail",
            "subcategory":"Auto Repair",
            "type":"Services"
        }
    ],
    "sg:phone":"+44 1995 605130",
    "sg:postcode":"PR3 1XP",
    "sg:province":"Lancashire",
    "sg:tags":[
        "bodybuilder",
        "repairer"
    ],
    "wof:name":"Trailer Technical Services",
    "wof:placetype":"venue"
},
  "geometry": {"coordinates":[-2.7647490501,53.8822097778],"type":"Point"}
}