{
  "type": "Feature",
  "properties": {
    "iso:country":"GB",
    "sg:address":"2 Castle Hill",
    "sg:city":"Lancaster",
    "sg:classifiers":[
        {
            "category":"Professional",
            "subcategory":"Lawyer & Legal Services",
            "type":"Services"
        }
    ],
    "sg:phone":"+44 1524 32484",
    "sg:postcode":"LA1 1YR",
    "sg:province":"Lancashire",
    "sg:tags":[
        "solicitor"
    ],
    "wof:name":"Holden & Wilson",
    "wof:placetype":"venue"
},
  "geometry": {"coordinates":[-2.8036000729,54.0501022339],"type":"Point"}
}