{
  "type": "Feature",
  "properties": {
    "addr:full":"The Parade, Orbital Park Ashford Kent TN24 0TH",
    "addr:postcode":"tn24 0th",
    "addr:street":"The Parade Orbital Park",
    "iso:country":"GB",
    "sg:address":"The Parade, Orbital Park",
    "sg:city":"Ashford",
    "sg:classifiers":[
        {
            "category":"Autos & Motor Vehicles",
            "subcategory":"Automobile Sales",
            "type":"Retail Goods"
        }
    ],
    "sg:phone":"+44 1233 506070",
    "sg:postcode":"TN24 0TH",
    "sg:province":"Kent",
    "sg:tags":[
        "car"
    ],
    "wof:name":"Barretts of Ashford",
    "wof:placetype":"venue"
},
  "geometry": {"coordinates":[0.896439,51.12714],"type":"Point"}
}