{
  "type": "Feature",
  "properties": {
    "iso:country":"GB",
    "sg:address":"35 Park Av",
    "sg:city":"Skegness",
    "sg:classifiers":[
        {
            "category":"Travel",
            "subcategory":"Hotels & Motels",
            "type":"Entertainment"
        }
    ],
    "sg:phone":"+44 1754 763941",
    "sg:postcode":"PE25 2TF",
    "sg:province":"Lincolnshire",
    "wof:name":"Glen Court Hotel",
    "wof:placetype":"venue"
},
  "geometry": {"coordinates":[0.3435020149,53.1478691101],"type":"Point"}
}