{
  "type": "Feature",
  "properties": {
    "iso:country":"GB",
    "sg:address":"Fordbridge Road",
    "sg:city":"Birmingham",
    "sg:classifiers":[
        {
            "category":"Organizations",
            "subcategory":"Membership Organization",
            "type":"Services"
        }
    ],
    "sg:phone":"+44 121 770 6358",
    "sg:postcode":"B37 6LX",
    "sg:province":"West Midlands",
    "sg:tags":[
        "club"
    ],
    "wof:name":"The Lakeside Club",
    "wof:placetype":"venue"
},
  "geometry": {"coordinates":[-1.747014,52.490891],"type":"Point"}
}