{
  "type": "Feature",
  "properties": {
    "iso:country":"GB",
    "sg:address":"25 Northgate",
    "sg:city":"Shipley",
    "sg:classifiers":[
        {
            "category":"Food & Beverages",
            "subcategory":"Supermarket",
            "type":"Retail Goods"
        }
    ],
    "sg:phone":"+44 1274 595318",
    "sg:postcode":"BD17 6JZ",
    "sg:province":"West Yorkshire",
    "wof:name":"Thorntons Village Store",
    "wof:placetype":"venue"
},
  "geometry": {"coordinates":[-1.766128,53.854439],"type":"Point"}
}