{
  "type": "Feature",
  "properties": {
    "iso:country":"GB",
    "sg:address":"Cowbridge Road",
    "sg:city":"Bridgend",
    "sg:classifiers":[
        {
            "category":"Retail",
            "subcategory":"Auto Repair",
            "type":"Services"
        }
    ],
    "sg:phone":"+44 1656 649390",
    "sg:postcode":"CF31 3PT",
    "sg:province":"Bridgend",
    "sg:tags":[
        "modification",
        "garage"
    ],
    "wof:name":"Jacksons Cars Ltd.",
    "wof:placetype":"venue"
},
  "geometry": {"coordinates":[-3.576164,51.501965],"type":"Point"}
}