{
  "type": "Feature",
  "properties": {
    "addr:full":"Bailgate Lincoln Lincolnshire LN1 3AR",
    "addr:postcode":"ln1 3ar",
    "addr:street":"Bailgate Lincoln",
    "iso:country":"GB",
    "sg:address":"Bailgate",
    "sg:city":"Lincoln",
    "sg:classifiers":[
        {
            "category":"Travel",
            "subcategory":"Hotels & Motels",
            "type":"Entertainment"
        }
    ],
    "sg:phone":"+44 1522 526222",
    "sg:postcode":"LN1 3AR",
    "sg:province":"Lincolnshire",
    "wof:name":"White Hart The",
    "wof:placetype":"venue"
},
  "geometry": {"coordinates":[-0.538749,53.234039],"type":"Point"}
}