{
  "type": "Feature",
  "properties": {
    "addr:full":"Michael House, Castle Street Exeter Devon EX4 3LQ",
    "addr:postcode":"ex4 3lq",
    "addr:street":"Castle Street",
    "iso:country":"GB",
    "sg:address":"Michael House, Castle Street",
    "sg:city":"Exeter",
    "sg:classifiers":[
        {
            "category":"Shopping",
            "subcategory":"Books",
            "type":"Retail Goods"
        },
        {
            "category":"Wholesale",
            "subcategory":"Books, Periodicals, & Newspapers",
            "type":"Manufacturing & Wholesale Goods"
        }
    ],
    "sg:postcode":"EX4 3LQ",
    "sg:province":"Devon",
    "sg:tags":[
        "publisher"
    ],
    "wof:name":"Havenpride Ltd",
    "wof:placetype":"venue"
},
  "geometry": {"coordinates":[-3.5291349888,50.7252464294],"type":"Point"}
}