{
  "type": "Feature",
  "properties": {
    "iso:country":"GB",
    "sg:address":"The Garage, Blackburn Rd",
    "sg:city":"Bolton",
    "sg:classifiers":[
        {
            "category":"Autos & Motor Vehicles",
            "subcategory":"Automobile Sales",
            "type":"Retail Goods"
        }
    ],
    "sg:phone":"+44 1204 592273",
    "sg:postcode":"BL7 9TH",
    "sg:province":"Lancashire",
    "sg:tags":[
        "car"
    ],
    "wof:name":"BP Motors",
    "wof:placetype":"venue"
},
  "geometry": {"coordinates":[-2.442734,53.632286],"type":"Point"}
}