{
  "type": "Feature",
  "properties": {
    "addr:full":"Skipton Road, Hampsthwaite, Felliscliffe Harrogate North Yorkshire HG3 2LX",
    "addr:postcode":"hg3 2lx",
    "addr:street":"Skipton Road",
    "iso:country":"GB",
    "sg:address":"Skipton Road, Hampsthwaite, Felliscliffe",
    "sg:city":"Harrogate",
    "sg:classifiers":[
        {
            "category":"Farming",
            "subcategory":"Livestock Farm",
            "type":"Manufacturing & Wholesale Goods"
        }
    ],
    "sg:postcode":"HG3 2LX",
    "sg:province":"North Yorkshire",
    "sg:tags":[
        "others"
    ],
    "wof:name":"Frank Morphet",
    "wof:placetype":"venue"
},
  "geometry": {"coordinates":[-1.568464,54.00687],"type":"Point"}
}