{
  "type": "Feature",
  "properties": {
    "addr:full":"Sycamores, School Lane Petworth West Sussex GU28 9DH",
    "addr:postcode":"gu28 9dh",
    "addr:street":"School Lane",
    "iso:country":"GB",
    "sg:address":"Sycamores, School Lane",
    "sg:city":"Petworth",
    "sg:classifiers":[
        {
            "category":"Retail",
            "subcategory":"Repair Shop",
            "type":"Services"
        },
        {
            "category":"Building & Trades",
            "subcategory":"Construction",
            "type":"Services"
        }
    ],
    "sg:phone":"+44 1798 861248",
    "sg:postcode":"GU28 9DH",
    "sg:province":"West Sussex",
    "sg:tags":[
        "monumental",
        "clocks",
        "watch",
        "mason"
    ],
    "wof:name":"Sally Hersh",
    "wof:placetype":"venue"
},
  "geometry": {"coordinates":[-0.6078540087,50.9861068726],"type":"Point"}
}