{
  "type": "Feature",
  "properties": {
    "addr:full":"Victoria Street Braintree Essex CM7 3HN",
    "addr:postcode":"cm7 3hn",
    "addr:street":"Victoria Street",
    "iso:country":"GB",
    "sg:address":"Victoria Street",
    "sg:city":"Braintree",
    "sg:classifiers":[
        {
            "category":"Cafe",
            "type":"Food & Drink"
        }
    ],
    "sg:postcode":"CM7 3HN",
    "sg:province":"Essex",
    "sg:tags":[
        "tea",
        "room"
    ],
    "wof:name":"Travellers Grill",
    "wof:placetype":"venue"
},
  "geometry": {"coordinates":[0.5560050011,51.8773384094],"type":"Point"}
}