{
  "type": "Feature",
  "properties": {
    "iso:country":"GB",
    "sg:address":"295 Lowfield Street",
    "sg:city":"Dartford",
    "sg:classifiers":[
        {
            "category":"Fast Food",
            "type":"Food & Drink"
        }
    ],
    "sg:phone":"+44 1322 279628",
    "sg:postcode":"DA1 1LB",
    "sg:province":"Kent",
    "sg:tags":[
        "away",
        "take"
    ],
    "wof:name":"Golden Palace",
    "wof:placetype":"venue"
},
  "geometry": {"coordinates":[0.215299,51.434551],"type":"Point"}
}