{
  "type": "Feature",
  "properties": {
    "addr:full":"Masons Rd Stratford-upon-avon Warwickshire CV37 9ND",
    "addr:postcode":"cv37 9nd",
    "addr:street":"Masons Rd",
    "iso:country":"GB",
    "sg:address":"Masons Rd",
    "sg:city":"Stratford-upon-avon",
    "sg:classifiers":[
        {
            "category":"Professional",
            "subcategory":"Engineering",
            "type":"Services"
        }
    ],
    "sg:phone":"+44 1789 299933",
    "sg:postcode":"CV37 9ND",
    "sg:province":"Warwickshire",
    "sg:tags":[
        "precision",
        "engineer"
    ],
    "wof:name":"Stratford Components Ltd",
    "wof:placetype":"venue"
},
  "geometry": {"coordinates":[-1.7266310453,52.1990966797],"type":"Point"}
}