{
  "type": "Feature",
  "properties": {
    "addr:full":"222 Stow Hill Newport Newport NP20 4HA",
    "addr:housenumber":"222",
    "addr:postcode":"np20 4ha",
    "addr:street":"Stow Hill",
    "iso:country":"GB",
    "sg:address":"222 Stow Hill",
    "sg:city":"Newport",
    "sg:classifiers":[
        {
            "category":"Shopping",
            "subcategory":"Pharmacy",
            "type":"Retail Goods"
        }
    ],
    "sg:phone":"+44 1633 253999",
    "sg:postcode":"NP20 4HA",
    "sg:province":"Newport",
    "sg:tags":[
        "pharmacist",
        "dispensing",
        "chemist"
    ],
    "wof:name":"Handpost Pharmacy",
    "wof:placetype":"venue"
},
  "geometry": {"coordinates":[-3.008789,51.583019],"type":"Point"}
}