{
  "type": "Feature",
  "properties": {
    "iso:country":"GB",
    "sg:address":"Ground Floor, 203 Mile End Rd, Stepney Green",
    "sg:city":"Whitechapel",
    "sg:classifiers":[
        {
            "category":"Professional",
            "subcategory":"Accounting & Tax Preparation",
            "type":"Services"
        }
    ],
    "sg:phone":"+44 20 7790 4141",
    "sg:postcode":"E1 4AA",
    "sg:province":"Greater London",
    "sg:tags":[
        "accountant"
    ],
    "wof:name":"M.N Haque & Co",
    "wof:placetype":"venue"
},
  "geometry": {"coordinates":[-0.0454300009,51.5221290588],"type":"Point"}
}