{
  "type": "Feature",
  "properties": {
    "addr:full":"41 Bridge Street Fakenham Norfolk NR21 9AG",
    "addr:housenumber":"41",
    "addr:postcode":"nr21 9ag",
    "addr:street":"Bridge Street",
    "iso:country":"GB",
    "sg:address":"41 Bridge Street",
    "sg:city":"Fakenham",
    "sg:classifiers":[
        {
            "category":"Bars & Pubs",
            "type":"Food & Drink"
        }
    ],
    "sg:phone":"+44 1328 862560",
    "sg:postcode":"NR21 9AG",
    "sg:province":"Norfolk",
    "sg:tags":[
        "pubs",
        "inn"
    ],
    "wof:name":"The Bull",
    "wof:placetype":"venue"
},
  "geometry": {"coordinates":[0.8487809896,52.8288803101],"type":"Point"}
}