{
  "type": "Feature",
  "properties": {
    "iso:country":"GB",
    "sg:address":"85 The Grn, Aston Abbotts",
    "sg:city":"Aylesbury",
    "sg:classifiers":[
        {
            "category":"Travel",
            "subcategory":"Hotels & Motels",
            "type":"Entertainment"
        }
    ],
    "sg:postcode":"HP22 4LY",
    "sg:province":"Buckinghamshire",
    "wof:name":"The Bull & Butcher",
    "wof:placetype":"venue"
},
  "geometry": {"coordinates":[-0.769771,51.872112],"type":"Point"}
}