{
  "type": "Feature",
  "properties": {
    "iso:country":"GB",
    "sg:address":"147 New Road",
    "sg:city":"Portsmouth",
    "sg:classifiers":[
        {
            "category":"Fast Food",
            "type":"Food & Drink"
        }
    ],
    "sg:phone":"+44 23 9266 8200",
    "sg:postcode":"PO2 7QS",
    "sg:province":"Hampshire",
    "sg:tags":[
        "away",
        "take"
    ],
    "wof:name":"Shopna Tandoori",
    "wof:placetype":"venue"
},
  "geometry": {"coordinates":[-1.071755,50.809189],"type":"Point"}
}