{
  "type": "Feature",
  "properties": {
    "iso:country":"GB",
    "sg:address":"138 St Pancras",
    "sg:city":"Chichester",
    "sg:classifiers":[
        {
            "category":"Professional",
            "subcategory":"Detective & Security Services",
            "type":"Services"
        }
    ],
    "sg:phone":"+44 1243 531219",
    "sg:postcode":"PO19 7LH",
    "sg:province":"West Sussex",
    "sg:tags":[
        "locksmith"
    ],
    "wof:name":"Fordham Security",
    "wof:placetype":"venue"
},
  "geometry": {"coordinates":[-0.771475,50.837185],"type":"Point"}
}