{
  "type": "Feature",
  "properties": {
    "addr:full":"32-33 New Street Chelmsford Essex CM1 1PH",
    "addr:housenumber":"32-33",
    "addr:postcode":"cm1 1ph",
    "addr:street":"New Street",
    "iso:country":"GB",
    "sg:address":"32-33 New Street",
    "sg:city":"Chelmsford",
    "sg:classifiers":[
        {
            "category":"Restaurant",
            "type":"Food & Drink"
        }
    ],
    "sg:phone":"+44 1245 494403",
    "sg:postcode":"CM1 1PH",
    "sg:province":"Essex",
    "sg:tags":[
        "indian"
    ],
    "wof:name":"Gulshan Curry House",
    "wof:placetype":"venue"
},
  "geometry": {"coordinates":[0.4735360146,51.7371635437],"type":"Point"}
}