{
  "type": "Feature",
  "properties": {
    "iso:country":"GB",
    "sg:address":"100-110 Euston Road",
    "sg:city":"London",
    "sg:classifiers":[
        {
            "category":"Arts & Performance",
            "subcategory":"Theater",
            "type":"Entertainment"
        }
    ],
    "sg:postcode":"NW1 2AJ",
    "sg:province":"Greater London",
    "sg:tags":[
        "theatre"
    ],
    "wof:name":"Pluto Productions",
    "wof:placetype":"venue"
},
  "geometry": {"coordinates":[-0.1268319935,51.5290145874],"type":"Point"}
}