{
  "type": "Feature",
  "properties": {
    "addr:full":"Wicken Manor, Church Lane, Wicken Milton Keynes Buckinghamshire MK19 6BU",
    "addr:housenumber":"wicken",
    "addr:postcode":"mk19 6bu",
    "addr:street":"Church Lane",
    "iso:country":"GB",
    "sg:address":"Wicken Manor, Church Lane, Wicken",
    "sg:city":"Milton Keynes",
    "sg:classifiers":[
        {
            "category":"Parking",
            "type":"Transportation"
        }
    ],
    "sg:phone":"+44 1908 571414",
    "sg:postcode":"MK19 6BU",
    "sg:province":"Buckinghamshire",
    "sg:tags":[
        "car",
        "valet"
    ],
    "wof:name":"Auto-Clean",
    "wof:placetype":"venue"
},
  "geometry": {"coordinates":[-0.912116,52.047756],"type":"Point"}
}