{
  "type": "Feature",
  "properties": {
    "iso:country":"GB",
    "sg:address":"Hanover Close, Edinburgh Drive",
    "sg:city":"Darlington",
    "sg:classifiers":[
        {
            "category":"Organizations",
            "subcategory":"Community Association",
            "type":"Services"
        }
    ],
    "sg:phone":"+44 1325 461938",
    "sg:postcode":"DL3 8BB",
    "sg:province":"Durham",
    "sg:tags":[
        "society",
        "housing"
    ],
    "wof:name":"Hanover Housing Association",
    "wof:placetype":"venue"
},
  "geometry": {"coordinates":[-1.5935310125,54.5239524841],"type":"Point"}
}