{
  "type": "Feature",
  "properties": {
    "iso:country":"GB",
    "sg:address":"Goodwin Close",
    "sg:city":"Warminster",
    "sg:classifiers":[
        {
            "category":"Government",
            "subcategory":"Post Office",
            "type":"Public Place"
        }
    ],
    "sg:phone":"+44 1985 212563",
    "sg:postcode":"BA12 0DF",
    "sg:province":"Somerset",
    "wof:name":"Goodwin Close Post Office",
    "wof:placetype":"venue"
},
  "geometry": {"coordinates":[-2.156724,51.210724],"type":"Point"}
}