{
  "type": "Feature",
  "properties": {
    "iso:country":"GB",
    "sg:address":"Paul Street, Coseley",
    "sg:city":"Bilston",
    "sg:classifiers":[
        {
            "category":"Education",
            "subcategory":"School",
            "type":"Public Place"
        },
        {
            "category":"Government",
            "subcategory":"Office",
            "type":"Public Place"
        }
    ],
    "sg:phone":"+44 1384 818845",
    "sg:postcode":"WV14 9AJ",
    "sg:province":"West Midlands",
    "sg:tags":[
        "local",
        "authority"
    ],
    "wof:name":"Hurst Hill Primary School",
    "wof:placetype":"venue"
},
  "geometry": {"coordinates":[-2.087084,52.540821],"type":"Point"}
}