{
  "type": "Feature",
  "properties": {
    "iso:country":"GB",
    "sg:address":"Imperial House, St Nicholas Circle",
    "sg:city":"Leicester",
    "sg:classifiers":[
        {
            "category":"Education",
            "subcategory":"School",
            "type":"Public Place"
        },
        {
            "category":"Education",
            "subcategory":"University",
            "type":"Public Place"
        }
    ],
    "sg:phone":"+44 116 242 4037",
    "sg:postcode":"LE1 4LF",
    "sg:province":"Leicestershire",
    "sg:tags":[
        "private",
        "tuition"
    ],
    "wof:name":"Clarendon Arts Education & Tuition Service",
    "wof:placetype":"venue"
},
  "geometry": {"coordinates":[-1.141229,52.634556],"type":"Point"}
}