{
  "type": "Feature",
  "properties": {
    "addr:full":"Porters Lodge, Palliser Rd West Kensington Greater London W14 9ED",
    "addr:postcode":"w14 9ed",
    "addr:street":"Palliser Rd",
    "iso:country":"GB",
    "sg:address":"Porters Lodge, Palliser Rd",
    "sg:city":"West Kensington",
    "sg:classifiers":[
        {
            "category":"Real Estate",
            "subcategory":"Real Estate Operator",
            "type":"Services"
        }
    ],
    "sg:phone":"+44 20 7385 9418",
    "sg:postcode":"W14 9ED",
    "sg:province":"Greater London",
    "sg:tags":[
        "letting",
        "agent"
    ],
    "wof:name":"Palliser Court",
    "wof:placetype":"venue"
},
  "geometry": {"coordinates":[-0.21321,51.489552],"type":"Point"}
}