{
  "type": "Feature",
  "properties": {
    "addr:full":"Dibbensdale Lodge, Dibbensdale Road, Bromborough Wirral Merseyside CH63 0HQ",
    "addr:postcode":"ch63 0hq",
    "addr:street":"Dibbensdale Road",
    "iso:country":"GB",
    "sg:address":"Dibbensdale Lodge, Dibbensdale Road, Bromborough",
    "sg:city":"Wirral",
    "sg:classifiers":[
        {
            "category":"Manufacturing",
            "subcategory":"Rubber & Plastics",
            "type":"Manufacturing & Wholesale Goods"
        }
    ],
    "sg:postcode":"CH63 0HQ",
    "sg:province":"Merseyside",
    "sg:tags":[
        "mould"
    ],
    "wof:name":"Acmos U.K. Ltd.",
    "wof:placetype":"venue"
},
  "geometry": {"coordinates":[-2.9945099354,53.3253517151],"type":"Point"}
}