{
  "type": "Feature",
  "properties": {
    "iso:country":"GB",
    "sg:address":"Image Makers City Trading Estate, Icknield Square",
    "sg:city":"Birmingham",
    "sg:classifiers":[
        {
            "category":"Professional",
            "subcategory":"Computer Services",
            "type":"Services"
        }
    ],
    "sg:postcode":"B16 0PP",
    "sg:province":"West Midlands",
    "sg:tags":[
        "consultant"
    ],
    "wof:name":"Net Result Ltd",
    "wof:placetype":"venue"
},
  "geometry": {"coordinates":[-1.9264340401,52.481754303],"type":"Point"}
}