{
  "type": "Feature",
  "properties": {
    "addr:full":"21 Nelson St Bristol City of Bristol BS1 2LA",
    "addr:housenumber":"21",
    "addr:postcode":"bs1 2la",
    "addr:street":"Nelson St",
    "iso:country":"GB",
    "sg:address":"21 Nelson St",
    "sg:city":"Bristol",
    "sg:classifiers":[
        {
            "category":"Banks & Credit Unions",
            "subcategory":"Financial Services",
            "type":"Services"
        }
    ],
    "sg:phone":"+44 117 987 3927",
    "sg:postcode":"BS1 2LA",
    "sg:province":"City of Bristol",
    "sg:tags":[
        "consultant"
    ],
    "wof:name":"Money Shop The",
    "wof:placetype":"venue"
},
  "geometry": {"coordinates":[-2.5931010246,51.4565315247],"type":"Point"}
}