{
  "type": "Feature",
  "properties": {
    "addr:full":"4 Long Pk, Chesham Bois Amersham Buckinghamshire HP6 5JX",
    "addr:housenumber":"4",
    "addr:postcode":"hp6 5jx",
    "addr:street":"Long Pk;Bois Amersham",
    "iso:country":"GB",
    "sg:address":"4 Long Pk, Chesham Bois",
    "sg:city":"Amersham",
    "sg:classifiers":[
        {
            "category":"Real Estate",
            "subcategory":"Architect",
            "type":"Services"
        }
    ],
    "sg:postcode":"HP6 5JX",
    "sg:province":"Buckinghamshire",
    "wof:name":"John Walton & Associates",
    "wof:placetype":"venue"
},
  "geometry": {"coordinates":[-0.6074519753,51.6841125488],"type":"Point"}
}