{
  "type": "Feature",
  "properties": {
    "addr:full":"94-102 High Street Dumbarton Argyll and Bute G82 1PQ",
    "addr:housenumber":"94-102",
    "addr:postcode":"g82 1pq",
    "addr:street":"High Street",
    "iso:country":"GB",
    "sg:address":"94-102 High Street",
    "sg:city":"Dumbarton",
    "sg:classifiers":[
        {
            "category":"Banks & Credit Unions",
            "subcategory":"Bank",
            "type":"Services"
        }
    ],
    "sg:phone":"+44 845 604 2310",
    "sg:postcode":"G82 1PQ",
    "sg:province":"Argyll and Bute",
    "wof:name":"Halifax Plc",
    "wof:placetype":"venue"
},
  "geometry": {"coordinates":[-4.571718,55.943722],"type":"Point"}
}