{
  "type": "Feature",
  "properties": {
    "iso:country":"GB",
    "sg:address":"Church Street, Gamlingay",
    "sg:city":"Sandy",
    "sg:classifiers":[
        {
            "category":"Manufacturing",
            "subcategory":"Rubber & Plastics",
            "type":"Manufacturing & Wholesale Goods"
        }
    ],
    "sg:phone":"+44 1767 650763",
    "sg:postcode":"SG19 3JJ",
    "sg:province":"Bedfordshire",
    "sg:tags":[
        "injection",
        "moulding"
    ],
    "wof:name":"J R Cooper Ltd.",
    "wof:placetype":"venue"
},
  "geometry": {"coordinates":[-0.19125,52.15546],"type":"Point"}
}