{
  "type": "Feature",
  "properties": {
    "addr:full":"1 Schoolhill Turriff Aberdeenshire AB53 7DX",
    "addr:housenumber":"1",
    "addr:postcode":"ab53 7dx",
    "addr:street":"Schoolhill Turriff",
    "iso:country":"GB",
    "sg:address":"1 Schoolhill",
    "sg:city":"Turriff",
    "sg:classifiers":[
        {
            "category":"Organizations",
            "subcategory":"Non-profit Organization",
            "type":"Services"
        }
    ],
    "sg:phone":"+44 1888 568209",
    "sg:postcode":"AB53 7DX",
    "sg:province":"Aberdeenshire",
    "sg:tags":[
        "organisation",
        "voluntary",
        "charity"
    ],
    "wof:name":"British Red Cross",
    "wof:placetype":"venue"
},
  "geometry": {"coordinates":[-2.460059,57.53701],"type":"Point"}
}