{
  "type": "Feature",
  "properties": {
    "addr:full":"241 Walmersley Old Road Bury Lancashire BL9 6RU",
    "addr:housenumber":"241",
    "addr:postcode":"bl9 6ru",
    "addr:street":"Walmersley Old Road",
    "iso:country":"GB",
    "sg:address":"241 Walmersley Old Road",
    "sg:city":"Bury",
    "sg:classifiers":[
        {
            "category":"Restaurant",
            "type":"Food & Drink"
        }
    ],
    "sg:phone":"+44 161 764 6883",
    "sg:postcode":"BL9 6RU",
    "sg:province":"Lancashire",
    "wof:name":"The Qualter Inns Ltd.",
    "wof:placetype":"venue"
},
  "geometry": {"coordinates":[-2.290612936,53.6240348816],"type":"Point"}
}