{
  "type": "Feature",
  "properties": {
    "addr:full":"78 Farm Lane, Fulham London Greater London SW6 1QA",
    "addr:housenumber":"78",
    "addr:postcode":"sw6 1qa",
    "addr:street":"Farm Lane",
    "iso:country":"GB",
    "sg:address":"78 Farm Lane, Fulham",
    "sg:city":"London",
    "sg:classifiers":[
        {
            "category":"Professional",
            "subcategory":"Business Services",
            "type":"Services"
        }
    ],
    "sg:postcode":"SW6 1QA",
    "sg:province":"Greater London",
    "sg:tags":[
        "accomodation"
    ],
    "wof:name":"Claxton Laundry Ltd",
    "wof:placetype":"venue"
},
  "geometry": {"coordinates":[-0.195814997,51.4826583862],"type":"Point"}
}