{
  "type": "Feature",
  "properties": {
    "iso:country":"GB",
    "sg:address":"12 The Centre, Church Road, Tiptree",
    "sg:city":"Colchester",
    "sg:classifiers":[
        {
            "category":"Shopping",
            "subcategory":"Optician",
            "type":"Retail Goods"
        },
        {
            "category":"Professional",
            "subcategory":"Business Services",
            "type":"Services"
        }
    ],
    "sg:postcode":"CO5 0HF",
    "sg:province":"Essex",
    "sg:tags":[
        "import",
        "export",
        "agent"
    ],
    "wof:name":"Don Tyler & Son Opticians",
    "wof:placetype":"venue"
},
  "geometry": {"coordinates":[0.7504050136,51.810760498],"type":"Point"}
}