{
  "type": "Feature",
  "properties": {
    "addr:full":"Market Hall, Spinning Gate Leigh Lancashire WN7 4PG",
    "addr:postcode":"wn7 4pg",
    "addr:street":"Spinning Gate Leigh",
    "iso:country":"GB",
    "sg:address":"Market Hall, Spinning Gate",
    "sg:city":"Leigh",
    "sg:classifiers":[
        {
            "category":"Shopping",
            "subcategory":"Optician",
            "type":"Retail Goods"
        }
    ],
    "sg:phone":"+44 1942 602607",
    "sg:postcode":"WN7 4PG",
    "sg:province":"Lancashire",
    "wof:name":"Crown Eyeglass Plc",
    "wof:placetype":"venue"
},
  "geometry": {"coordinates":[-2.5189940929,53.4969711304],"type":"Point"}
}