{
  "type": "Feature",
  "properties": {
    "addr:full":"35 Boot La, Dunton Biggleswade Bedfordshire SG18 8RP",
    "addr:housenumber":"35",
    "addr:postcode":"sg18 8rp",
    "addr:street":"Boot La Dunton",
    "iso:country":"GB",
    "sg:address":"35 Boot La, Dunton",
    "sg:city":"Biggleswade",
    "sg:classifiers":[
        {
            "category":"Social Services",
            "subcategory":"Job Training",
            "type":"Services"
        }
    ],
    "sg:postcode":"SG18 8RP",
    "sg:province":"Bedfordshire",
    "sg:tags":[
        "draughtsman",
        "drawing"
    ],
    "wof:name":"Bevan,Mike,",
    "wof:placetype":"venue"
},
  "geometry": {"coordinates":[-0.196863994,52.0851249695],"type":"Point"}
}