{
  "type": "Feature",
  "properties": {
    "iso:country":"GB",
    "sg:address":"Lingholme Road",
    "sg:city":"St Helens",
    "sg:classifiers":[
        {
            "category":"Government",
            "subcategory":"Post Office",
            "type":"Public Place"
        }
    ],
    "sg:phone":"+44 1744 24574",
    "sg:postcode":"WA10 6RG",
    "sg:province":"Merseyside",
    "wof:name":"Lingholme Road Sub Post Office",
    "wof:placetype":"venue"
},
  "geometry": {"coordinates":[-2.750319,53.457394],"type":"Point"}
}