{
  "type": "Feature",
  "properties": {
    "iso:country":"GB",
    "sg:address":"1st Floor, 29 Coleshill Rd",
    "sg:city":"Birmingham",
    "sg:classifiers":[
        {
            "category":"Building & Trades",
            "subcategory":"Plumbing",
            "type":"Services"
        },
        {
            "category":"Retail",
            "subcategory":"Repair Shop",
            "type":"Services"
        }
    ],
    "sg:postcode":"B36 8DS",
    "sg:province":"West Midlands",
    "sg:tags":[
        "heating",
        "maintenance"
    ],
    "wof:name":"Berkeley Maintenance Ltd",
    "wof:placetype":"venue"
},
  "geometry": {"coordinates":[-1.8169939518,52.4943466187],"type":"Point"}
}