{
  "type": "Feature",
  "properties": {
    "addr:full":"17 Wimbledon Clo, The Downs Raynes Park Greater London SW20 8HW",
    "addr:housenumber":"17",
    "addr:postcode":"sw20 8hw",
    "addr:street":"Wimbledon Clo;Downs;Park",
    "iso:country":"GB",
    "sg:address":"17 Wimbledon Clo, The Downs",
    "sg:city":"Raynes Park",
    "sg:classifiers":[
        {
            "category":"Professional",
            "subcategory":"Management & Consulting",
            "type":"Services"
        }
    ],
    "sg:phone":"+44 20 8879 3320",
    "sg:postcode":"SW20 8HW",
    "sg:province":"Greater London",
    "sg:tags":[
        "consultant",
        "business"
    ],
    "wof:name":"Training Associates",
    "wof:placetype":"venue"
},
  "geometry": {"coordinates":[-0.2265190035,51.4110946655],"type":"Point"}
}