{
  "type": "Feature",
  "properties": {
    "iso:country":"GB",
    "sg:address":"Grange Avenue, Stirchley",
    "sg:city":"Telford",
    "sg:classifiers":[
        {
            "category":"Food & Beverages",
            "subcategory":"Supermarket",
            "type":"Retail Goods"
        }
    ],
    "sg:phone":"+44 1952 592145",
    "sg:postcode":"TF3 1ET",
    "sg:province":"Shropshire",
    "wof:name":"Kwik Save Stores Ltd.",
    "wof:placetype":"venue"
},
  "geometry": {"coordinates":[-2.444429,52.658443],"type":"Point"}
}