{
  "type": "Feature",
  "properties": {
    "iso:country":"GB",
    "sg:address":"Weldon Road",
    "sg:city":"Corby",
    "sg:classifiers":[
        {
            "category":"Autos & Motor Vehicles",
            "subcategory":"Automobile Sales",
            "type":"Retail Goods"
        }
    ],
    "sg:phone":"+44 1536 356304",
    "sg:postcode":"NN17 5UE",
    "sg:province":"Northamptonshire",
    "sg:tags":[
        "car"
    ],
    "wof:name":"Premier Motor Co.",
    "wof:placetype":"venue"
},
  "geometry": {"coordinates":[-0.67438,52.490746],"type":"Point"}
}