{
  "type": "Feature",
  "properties": {
    "addr:full":"Unit 1, Kestrel Park, Tallon Road Brentwood Essex CM13 1TN",
    "addr:housenumber":"unit 1",
    "addr:postcode":"cm13 1tn",
    "addr:street":"Kestrel Park Tallon Road",
    "iso:country":"GB",
    "sg:address":"Unit 1, Kestrel Park, Tallon Road",
    "sg:city":"Brentwood",
    "sg:classifiers":[
        {
            "category":"Building & Trades",
            "subcategory":"Plumbing",
            "type":"Services"
        },
        {
            "category":"Manufacturing",
            "subcategory":"Building Materials",
            "type":"Manufacturing & Wholesale Goods"
        }
    ],
    "sg:phone":"+44 1277 213148",
    "sg:postcode":"CM13 1TN",
    "sg:province":"Essex",
    "sg:tags":[
        "merchant",
        "builder",
        "plumbers'"
    ],
    "wof:name":"Plumb Center Ltd",
    "wof:placetype":"venue"
},
  "geometry": {"coordinates":[0.35555,51.6367],"type":"Point"}
}