{
  "type": "Feature",
  "properties": {
    "addr:full":"The Forge, Gosport Road, Lower Farringdon Alton Hampshire GU34 3DL",
    "addr:postcode":"gu34 3dl",
    "addr:street":"Gosport Road",
    "iso:country":"GB",
    "sg:address":"The Forge, Gosport Road, Lower Farringdon",
    "sg:city":"Alton",
    "sg:classifiers":[
        {
            "category":"Manufacturing",
            "subcategory":"Metals",
            "type":"Manufacturing & Wholesale Goods"
        },
        {
            "category":"Utilities",
            "subcategory":"Natural Gas",
            "type":"Services"
        }
    ],
    "sg:phone":"+44 1420 587233",
    "sg:postcode":"GU34 3DL",
    "sg:province":"Hampshire",
    "sg:tags":[
        "blacksmith",
        "forgemasters"
    ],
    "wof:name":"Robert Smith",
    "wof:placetype":"venue"
},
  "geometry": {"coordinates":[-0.993929,51.110569],"type":"Point"}
}