{
  "type": "Feature",
  "properties": {
    "addr:full":"Rake Lane North Shields Tyne and Wear NE29 8NH",
    "addr:postcode":"ne29 8nh",
    "addr:street":"Rake Lane",
    "iso:country":"GB",
    "sg:address":"Rake Lane",
    "sg:city":"North Shields",
    "sg:classifiers":[
        {
            "category":"Health Services",
            "subcategory":"Hospital",
            "type":"Services"
        }
    ],
    "sg:phone":"+44 191 259 6660",
    "sg:postcode":"NE29 8NH",
    "sg:province":"Tyne and Wear",
    "wof:name":"North Tyneside General",
    "wof:placetype":"venue"
},
  "geometry": {"coordinates":[-1.4801340103,55.024520874],"type":"Point"}
}