{
  "type": "Feature",
  "properties": {
    "addr:full":"90 Romsey Avenue Fareham Hampshire PO16 9TA",
    "addr:housenumber":"90",
    "addr:postcode":"po16 9ta",
    "addr:street":"Romsey Avenue",
    "iso:country":"GB",
    "sg:address":"90 Romsey Avenue",
    "sg:city":"Fareham",
    "sg:classifiers":[
        {
            "category":"Building & Trades",
            "subcategory":"Plumbing",
            "type":"Services"
        }
    ],
    "sg:phone":"+44 1329 312796",
    "sg:postcode":"PO16 9TA",
    "sg:province":"Hampshire",
    "sg:tags":[
        "heating"
    ],
    "wof:name":"M J Charlton (Portchester) Ltd.",
    "wof:placetype":"venue"
},
  "geometry": {"coordinates":[-1.1489779949,50.8482437134],"type":"Point"}
}