{
  "type": "Feature",
  "properties": {
    "iso:country":"GB",
    "sg:address":"4 Cross Cheaping",
    "sg:city":"Coventry",
    "sg:classifiers":[
        {
            "category":"Professional",
            "subcategory":"Employment Agencies",
            "type":"Services"
        }
    ],
    "sg:phone":"+44 24 7663 1441",
    "sg:postcode":"CV1 1HG",
    "sg:province":"West Midlands",
    "sg:tags":[
        "consultant",
        "recruitment"
    ],
    "sg:website":"http://www.select.co.uk",
    "wof:name":"Select Appointments Plc",
    "wof:placetype":"venue"
},
  "geometry": {"coordinates":[-1.510453,52.409332],"type":"Point"}
}