{
  "type": "Feature",
  "properties": {
    "addr:full":"Unit 6 Shepley Industrial Estate North, Audenshaw Manchester Greater Manchester M34 5DR",
    "addr:housenumber":"unit 6",
    "addr:postcode":"m34 5dr",
    "addr:street":"Shepley Industrial Estate North Audenshaw",
    "iso:country":"GB",
    "sg:address":"Unit 6 Shepley Industrial Estate North, Audenshaw",
    "sg:city":"Manchester",
    "sg:classifiers":[
        {
            "category":"Shopping",
            "subcategory":"Stationery & Office Supplies",
            "type":"Retail Goods"
        }
    ],
    "sg:phone":"+44 161 336 2272",
    "sg:postcode":"M34 5DR",
    "sg:province":"Greater Manchester",
    "sg:tags":[
        "box",
        "carton"
    ],
    "wof:name":"GROSVENOR PACKAGING LTD",
    "wof:placetype":"venue"
},
  "geometry": {"coordinates":[-2.129179,53.471275],"type":"Point"}
}