{
  "type": "Feature",
  "properties": {
    "addr:full":"Mercia House, Mercia Gro London Greater London SE13 6BJ",
    "addr:postcode":"se13 6bj",
    "addr:street":"Gro",
    "iso:country":"GB",
    "sg:address":"Mercia House, Mercia Gro",
    "sg:city":"London",
    "sg:classifiers":[
        {
            "category":"Professional",
            "subcategory":"Lawyer & Legal Services",
            "type":"Services"
        }
    ],
    "sg:postcode":"SE13 6BJ",
    "sg:province":"Greater London",
    "sg:tags":[
        "advice",
        "counselling"
    ],
    "wof:name":"Counselling With Care",
    "wof:placetype":"venue"
},
  "geometry": {"coordinates":[-0.009273,51.461441],"type":"Point"}
}