{
  "type": "Feature",
  "properties": {
    "iso:country":"GB",
    "sg:address":"Central Street, Ramsbottom",
    "sg:city":"Bury",
    "sg:classifiers":[
        {
            "category":"Health Services",
            "subcategory":"Doctor",
            "type":"Services"
        },
        {
            "category":"Community Center",
            "subcategory":"Youth",
            "type":"Public Place"
        }
    ],
    "sg:phone":"+44 1706 822466",
    "sg:postcode":"BL0 9AF",
    "sg:province":"Lancashire",
    "sg:tags":[
        "organisation",
        "centre"
    ],
    "wof:name":"Ramsbottom Health Centre",
    "wof:placetype":"venue"
},
  "geometry": {"coordinates":[-2.3185989857,53.648475647],"type":"Point"}
}