{
  "type": "Feature",
  "properties": {
    "iso:country":"GB",
    "sg:address":"G1 Tudor Road, Hanover Business Park",
    "sg:city":"Altrincham",
    "sg:classifiers":[
        {
            "category":"Home & Garden",
            "subcategory":"Kitchen Supply",
            "type":"Retail Goods"
        }
    ],
    "sg:phone":"+44 161 926 9737",
    "sg:postcode":"WA14 5RZ",
    "sg:province":"Cheshire",
    "sg:tags":[
        "measuring",
        "scale"
    ],
    "wof:name":"Jab Engineering Ltd.",
    "wof:placetype":"venue"
},
  "geometry": {"coordinates":[-2.349209,53.386726],"type":"Point"}
}