{
  "type": "Feature",
  "properties": {
    "iso:country":"GB",
    "sg:address":"Exeter Education Officer, Bradninch Hall, Castle St",
    "sg:city":"Exeter",
    "sg:classifiers":[
        {
            "category":"Government",
            "subcategory":"Office",
            "type":"Public Place"
        }
    ],
    "sg:phone":"+44 1392 383900",
    "sg:postcode":"EX4 3PJ",
    "sg:province":"Devon",
    "sg:tags":[
        "local"
    ],
    "wof:name":"Devon County Council",
    "wof:placetype":"venue"
},
  "geometry": {"coordinates":[-3.5293200016,50.7257118225],"type":"Point"}
}