{
  "type": "Feature",
  "properties": {
    "addr:full":"Stone Barn Workshops, Park House Farm Leeds North Yorkshire LS25 3DH",
    "addr:postcode":"ls25 3dh",
    "addr:street":"Stone;Workshops;House Farm",
    "iso:country":"GB",
    "sg:address":"Stone Barn Workshops, Park House Farm",
    "sg:city":"Leeds",
    "sg:classifiers":[
        {
            "category":"Professional",
            "subcategory":"Engineering",
            "type":"Services"
        }
    ],
    "sg:postcode":"LS25 3DH",
    "sg:province":"North Yorkshire",
    "wof:name":"David Spirett",
    "wof:placetype":"venue"
},
  "geometry": {"coordinates":[-1.344139,53.831772],"type":"Point"}
}