{
  "type": "Feature",
  "properties": {
    "addr:full":"706 Chester Road Birmingham West Midlands B23 5TE",
    "addr:housenumber":"706",
    "addr:postcode":"b23 5te",
    "addr:street":"Chester Road",
    "iso:country":"GB",
    "sg:address":"706 Chester Road",
    "sg:city":"Birmingham",
    "sg:classifiers":[
        {
            "category":"Fast Food",
            "type":"Food & Drink"
        }
    ],
    "sg:phone":"+44 121 350 9151",
    "sg:postcode":"B23 5TE",
    "sg:province":"West Midlands",
    "sg:tags":[
        "away",
        "take"
    ],
    "wof:name":"Chester House",
    "wof:placetype":"venue"
},
  "geometry": {"coordinates":[-1.8297569752,52.5337486267],"type":"Point"}
}