{
  "type": "Feature",
  "properties": {
    "iso:country":"GB",
    "sg:address":"26a Railway Road",
    "sg:city":"King's Lynn",
    "sg:classifiers":[
        {
            "category":"Retail",
            "subcategory":"Auto Repair",
            "type":"Services"
        }
    ],
    "sg:phone":"+44 1553 810464",
    "sg:postcode":"PE30 1NF",
    "sg:province":"Norfolk",
    "sg:tags":[
        "modification",
        "garage"
    ],
    "wof:name":"J & S Motors",
    "wof:placetype":"venue"
},
  "geometry": {"coordinates":[0.40072,52.754219],"type":"Point"}
}