{
  "type": "Feature",
  "properties": {
    "iso:country":"GB",
    "sg:address":"43 Upr Dicconson St",
    "sg:city":"Wigan",
    "sg:classifiers":[
        {
            "category":"Travel",
            "subcategory":"Hotels & Motels",
            "type":"Entertainment"
        }
    ],
    "sg:postcode":"WN1 2AG",
    "sg:province":"Lancashire",
    "sg:tags":[
        "house",
        "guest"
    ],
    "wof:name":"Croft Guest House",
    "wof:placetype":"venue"
},
  "geometry": {"coordinates":[-2.629743,53.551334],"type":"Point"}
}