{
  "type": "Feature",
  "properties": {
    "iso:country":"GB",
    "sg:address":"14 Stanshaw Close",
    "sg:city":"Bristol",
    "sg:classifiers":[
        {
            "category":"Professional",
            "type":"Services"
        }
    ],
    "sg:postcode":"BS16 1JY",
    "sg:province":"City of Bristol",
    "sg:tags":[
        "entertainer"
    ],
    "wof:name":"Ace Fun Trampolines & Clown Co",
    "wof:placetype":"venue"
},
  "geometry": {"coordinates":[-2.5287270546,51.4934043884],"type":"Point"}
}