{
  "type": "Feature",
  "properties": {
    "iso:country":"GB",
    "sg:address":"62 Ford Road",
    "sg:city":"Arundel",
    "sg:classifiers":[
        {
            "category":"Professional",
            "subcategory":"Computer Services",
            "type":"Services"
        }
    ],
    "sg:postcode":"BN18 9EX",
    "sg:province":"West Sussex",
    "sg:tags":[
        "consultant"
    ],
    "wof:name":"Square Circle Ltd.",
    "wof:placetype":"venue"
},
  "geometry": {"coordinates":[-0.566766,50.848789],"type":"Point"}
}