{
  "type": "Feature",
  "properties": {
    "iso:country":"GB",
    "sg:address":"67 Ashby Road",
    "sg:city":"Loughborough",
    "sg:classifiers":[
        {
            "category":"Recreation",
            "subcategory":"Gun Range",
            "type":"Entertainment"
        }
    ],
    "sg:phone":"+44 1509 211612",
    "sg:postcode":"LE11 3AA",
    "sg:province":"Leicestershire",
    "sg:tags":[
        "operator",
        "tour"
    ],
    "wof:name":"Spanish Study Holidays Ltd.",
    "wof:placetype":"venue"
},
  "geometry": {"coordinates":[-1.21421,52.772457],"type":"Point"}
}