{
  "type": "Feature",
  "properties": {
    "addr:full":"Aird St Banff Aberdeenshire AB45 2RB",
    "addr:postcode":"ab45 2rb",
    "addr:street":"Aird St",
    "iso:country":"GB",
    "sg:address":"Aird St",
    "sg:city":"Banff",
    "sg:classifiers":[
        {
            "category":"Government",
            "subcategory":"Office",
            "type":"Public Place"
        }
    ],
    "sg:phone":"+44 1261 833799",
    "sg:postcode":"AB45 2RB",
    "sg:province":"Aberdeenshire",
    "sg:tags":[
        "education",
        "agency",
        "authority"
    ],
    "wof:name":"Portsoy Community Education Centre",
    "wof:placetype":"venue"
},
  "geometry": {"coordinates":[-2.6868839264,57.6808357239],"type":"Point"}
}