{
  "type": "Feature",
  "properties": {
    "iso:country":"GB",
    "sg:address":"58 Porchester Road",
    "sg:city":"London",
    "sg:classifiers":[
        {
            "category":"Restaurant",
            "type":"Food & Drink"
        }
    ],
    "sg:postcode":"W2 6ET",
    "sg:province":"Greater London",
    "wof:name":"Angelo Mourino",
    "wof:placetype":"venue"
},
  "geometry": {"coordinates":[-0.188811,51.518353],"type":"Point"}
}