{
  "type": "Feature",
  "properties": {
    "addr:full":"614b High Road London Greater London N17 9TB",
    "addr:housenumber":"614b",
    "addr:postcode":"n17 9tb",
    "addr:street":"High Road",
    "iso:country":"GB",
    "sg:address":"614b High Road",
    "sg:city":"London",
    "sg:classifiers":[
        {
            "category":"Home & Garden",
            "subcategory":"Carpets & Floor Coverings",
            "type":"Retail Goods"
        }
    ],
    "sg:phone":"+44 20 8493 0707",
    "sg:postcode":"N17 9TB",
    "sg:province":"Greater London",
    "sg:tags":[
        "carpets",
        "rug",
        "matting"
    ],
    "wof:name":"Collins Carpets",
    "wof:placetype":"venue"
},
  "geometry": {"coordinates":[-0.068109,51.596897],"type":"Point"}
}