{
  "type": "Feature",
  "properties": {
    "addr:full":"3 Lytchett Lane, Near Wool Wareham Dorset BH20 6PA",
    "addr:housenumber":"3",
    "addr:postcode":"bh20 6pa",
    "addr:street":"Lytchett Lane",
    "iso:country":"GB",
    "sg:address":"3 Lytchett Lane, Near Wool",
    "sg:city":"Wareham",
    "sg:classifiers":[
        {
            "category":"Professional",
            "subcategory":"Management & Consulting",
            "type":"Services"
        }
    ],
    "sg:postcode":"BH20 6PA",
    "sg:province":"Dorset",
    "sg:tags":[
        "consultant",
        "specialist"
    ],
    "wof:name":"J Gillingham",
    "wof:placetype":"venue"
},
  "geometry": {"coordinates":[-2.2250480652,50.6911621094],"type":"Point"}
}