{
  "type": "Feature",
  "properties": {
    "addr:full":"26 Wilfred Road Bournemouth Dorset BH5 1ND",
    "addr:housenumber":"26",
    "addr:postcode":"bh5 1nd",
    "addr:street":"Wilfred Road",
    "iso:country":"GB",
    "sg:address":"26 Wilfred Road",
    "sg:city":"Bournemouth",
    "sg:classifiers":[
        {
            "category":"Social Services",
            "subcategory":"Adult Care",
            "type":"Services"
        }
    ],
    "sg:postcode":"BH5 1ND",
    "sg:province":"Dorset",
    "sg:tags":[
        "housing",
        "sheltered"
    ],
    "wof:name":"Ashwell Lodge",
    "wof:placetype":"venue"
},
  "geometry": {"coordinates":[-1.83578,50.723541],"type":"Point"}
}