{
  "type": "Feature",
  "properties": {
    "iso:country":"GB",
    "sg:address":"Bay View Road",
    "sg:city":"Porthcawl",
    "sg:classifiers":[
        {
            "category":"Train Station",
            "subcategory":"Rail",
            "type":"Transportation"
        },
        {
            "category":"Community Center",
            "type":"Public Place"
        }
    ],
    "sg:postcode":"CF36 5NG",
    "sg:province":"Bridgend",
    "sg:tags":[
        "caravan",
        "recreation",
        "leisure",
        "centre"
    ],
    "wof:name":"Trecco Bay Leisure Park Ltd.",
    "wof:placetype":"venue"
},
  "geometry": {"coordinates":[-3.677669,51.479252],"type":"Point"}
}