{
  "type": "Feature",
  "properties": {
    "iso:country":"GB",
    "sg:address":"4 Lombard Street",
    "sg:city":"Stourport-on-severn",
    "sg:classifiers":[
        {
            "category":"Home & Garden",
            "subcategory":"Home Furnishings",
            "type":"Retail Goods"
        }
    ],
    "sg:phone":"+44 1299 871883",
    "sg:postcode":"DY13 8DT",
    "sg:province":"Worcestershire",
    "sg:tags":[
        "blind",
        "curtain",
        "fitting"
    ],
    "wof:name":"C D C Furnishings",
    "wof:placetype":"venue"
},
  "geometry": {"coordinates":[-2.277757,52.34087],"type":"Point"}
}