{
  "type": "Feature",
  "properties": {
    "addr:full":"Westminster Bldgs, High St Doncaster South Yorkshire DN1 1DQ",
    "addr:postcode":"dn1 1dq",
    "addr:street":"High St",
    "iso:country":"GB",
    "sg:address":"Westminster Bldgs, High St",
    "sg:city":"Doncaster",
    "sg:classifiers":[
        {
            "category":"Professional",
            "subcategory":"Employment Agencies",
            "type":"Services"
        }
    ],
    "sg:phone":"+44 1302 342526",
    "sg:postcode":"DN1 1DQ",
    "sg:province":"South Yorkshire",
    "sg:tags":[
        "consultant"
    ],
    "wof:name":"Heron Recruitment Ltd",
    "wof:placetype":"venue"
},
  "geometry": {"coordinates":[-1.130565,53.524391],"type":"Point"}
}