{
  "type": "Feature",
  "properties": {
    "addr:full":"14 Chinon Place Tiverton Devon EX16 5QE",
    "addr:housenumber":"14",
    "addr:postcode":"ex16 5qe",
    "addr:street":"Chinon Place",
    "iso:country":"GB",
    "sg:address":"14 Chinon Place",
    "sg:city":"Tiverton",
    "sg:classifiers":[
        {
            "category":"Professional",
            "subcategory":"Engineering",
            "type":"Services"
        }
    ],
    "sg:postcode":"EX16 5QE",
    "sg:province":"Devon",
    "sg:tags":[
        "contractor",
        "electrical",
        "engineer"
    ],
    "wof:name":"M & F Electrics",
    "wof:placetype":"venue"
},
  "geometry": {"coordinates":[-3.502584,50.913334],"type":"Point"}
}