{
  "type": "Feature",
  "properties": {
    "addr:full":"Unit 1a Aspen Drive Business Centre, Aspen Dr Derby Derbyshire DE21 7SG",
    "addr:housenumber":"unit 1a;centre",
    "addr:postcode":"business;de21 7sg",
    "addr:street":"Aspen Drive;Aspen Dr",
    "iso:country":"GB",
    "sg:address":"Unit 1a Aspen Drive Business Centre, Aspen Dr",
    "sg:city":"Derby",
    "sg:classifiers":[
        {
            "category":"Professional",
            "subcategory":"Engineering",
            "type":"Services"
        }
    ],
    "sg:phone":"+44 1332 281515",
    "sg:postcode":"DE21 7SG",
    "sg:province":"Derbyshire",
    "wof:name":"Powerprobe Ltd",
    "wof:placetype":"venue"
},
  "geometry": {"coordinates":[-1.4206750393,52.9179496765],"type":"Point"}
}