{
  "type": "Feature",
  "properties": {
    "addr:full":"Castle Street Dover Kent CT16 1TA",
    "addr:postcode":"ct16 1ta",
    "addr:street":"Castle Street",
    "iso:country":"GB",
    "sg:address":"Castle Street",
    "sg:city":"Dover",
    "sg:classifiers":[
        {
            "category":"Bars & Pubs",
            "subcategory":"Nightclub",
            "type":"Food & Drink"
        }
    ],
    "sg:postcode":"CT16 1TA",
    "sg:province":"Kent",
    "sg:tags":[
        "club",
        "night"
    ],
    "wof:name":"Snoops",
    "wof:placetype":"venue"
},
  "geometry": {"coordinates":[1.31596,51.12635],"type":"Point"}
}