{
  "type": "Feature",
  "properties": {
    "addr:full":"4 Elmond Court Falkirk Falkirk FK2 9HT",
    "addr:housenumber":"4",
    "addr:postcode":"fk2 9ht",
    "addr:street":"Elmond Court",
    "iso:country":"GB",
    "sg:address":"4 Elmond Court",
    "sg:city":"Falkirk",
    "sg:classifiers":[
        {
            "category":"Building & Trades",
            "subcategory":"Plumbing",
            "type":"Services"
        }
    ],
    "sg:phone":"+44 1324 629699",
    "sg:postcode":"FK2 9HT",
    "sg:province":"Falkirk",
    "sg:tags":[
        "merchant",
        "plumbers'"
    ],
    "wof:name":"Forth Plumbing Supplies",
    "wof:placetype":"venue"
},
  "geometry": {"coordinates":[-3.7412810326,55.991027832],"type":"Point"}
}