{
  "type": "Feature",
  "properties": {
    "addr:full":"24 Haleys Terrace York North Yorkshire YO31 8SB",
    "addr:housenumber":"24",
    "addr:postcode":"yo31 8sb",
    "addr:street":"Haleys Terrace",
    "iso:country":"GB",
    "sg:address":"24 Haleys Terrace",
    "sg:city":"York",
    "sg:classifiers":[
        {
            "category":"Professional",
            "subcategory":"Business Services",
            "type":"Services"
        },
        {
            "category":"Casinos & Gambling",
            "type":"Entertainment"
        }
    ],
    "sg:phone":"+44 1904 623110",
    "sg:postcode":"YO31 8SB",
    "sg:province":"North Yorkshire",
    "sg:tags":[
        "turf",
        "accountant",
        "bookmaker"
    ],
    "wof:name":"Ted Plant",
    "wof:placetype":"venue"
},
  "geometry": {"coordinates":[-1.075519,53.975201],"type":"Point"}
}