{
  "type": "Feature",
  "properties": {
    "addr:full":"229 Chiswick High Rd Chiswick Greater London W4 2DW",
    "addr:housenumber":"229",
    "addr:postcode":"w4 2dw",
    "addr:street":"Chiswick High Rd",
    "iso:country":"GB",
    "sg:address":"229 Chiswick High Rd",
    "sg:city":"Chiswick",
    "sg:classifiers":[
        {
            "category":"Personal",
            "subcategory":"Beauty Salon",
            "type":"Services"
        }
    ],
    "sg:phone":"+44 20 8995 4629",
    "sg:postcode":"W4 2DW",
    "sg:province":"Greater London",
    "sg:tags":[
        "lady",
        "hairdresser"
    ],
    "wof:name":"Dazzle Hair & Beauty",
    "wof:placetype":"venue"
},
  "geometry": {"coordinates":[-0.258489,51.492378],"type":"Point"}
}