{
  "type": "Feature",
  "properties": {
    "addr:full":"South Church Rd Bishop Auckland Durham DL14 7LB",
    "addr:postcode":"dl14 7lb",
    "addr:street":"South Church Rd",
    "iso:country":"GB",
    "sg:address":"South Church Rd",
    "sg:city":"Bishop Auckland",
    "sg:classifiers":[
        {
            "category":"Place Of Worship",
            "type":"Public Place"
        }
    ],
    "sg:phone":"+44 1388 604397",
    "sg:postcode":"DL14 7LB",
    "sg:province":"Durham",
    "wof:name":"St Andrew's Parish Church",
    "wof:placetype":"venue"
},
  "geometry": {"coordinates":[-1.6747939587,54.66147995],"type":"Point"}
}