{
  "type": "Feature",
  "properties": {
    "addr:full":"1135 Warwick Rd Solihull West Midlands B91 3HQ",
    "addr:housenumber":"1135",
    "addr:postcode":"b91 3hq",
    "addr:street":"Warwick Rd",
    "iso:country":"GB",
    "sg:address":"1135 Warwick Rd",
    "sg:city":"Solihull",
    "sg:classifiers":[
        {
            "category":"Professional",
            "subcategory":"Lawyer & Legal Services",
            "type":"Services"
        }
    ],
    "sg:phone":"+44 121 711 3606",
    "sg:postcode":"B91 3HQ",
    "sg:province":"West Midlands",
    "sg:tags":[
        "solicitor"
    ],
    "wof:name":"John A Eagle",
    "wof:placetype":"venue"
},
  "geometry": {"coordinates":[-1.759351,52.407104],"type":"Point"}
}