{
  "type": "Feature",
  "properties": {
    "addr:full":"12a Crescent Road Windermere Cumbria LA23 1EA",
    "addr:housenumber":"12a",
    "addr:postcode":"la23 1ea",
    "addr:street":"Crescent Road",
    "iso:country":"GB",
    "sg:address":"12a Crescent Road",
    "sg:city":"Windermere",
    "sg:classifiers":[
        {
            "category":"Shopping",
            "subcategory":"Gifts & Souvenirs",
            "type":"Retail Goods"
        }
    ],
    "sg:phone":"+44 15394 43275",
    "sg:postcode":"LA23 1EA",
    "sg:province":"Cumbria",
    "sg:tags":[
        "shop",
        "poster",
        "card"
    ],
    "wof:name":"Crescent Cards",
    "wof:placetype":"venue"
},
  "geometry": {"coordinates":[-2.9057691097,54.3783798218],"type":"Point"}
}