{
  "type": "Feature",
  "properties": {
    "addr:full":"Unit 9, Gas Works Industrial Estate, Victoria Road Port Talbot Neath Port Talbot SA12 6DB",
    "addr:housenumber":"unit 9;estate",
    "addr:postcode":"sa12 6db",
    "addr:street":"Industrial;Victoria Road",
    "iso:country":"GB",
    "sg:address":"Unit 9, Gas Works Industrial Estate, Victoria Road",
    "sg:city":"Port Talbot",
    "sg:classifiers":[
        {
            "category":"Bus Stop",
            "subcategory":"None",
            "type":"Transportation"
        }
    ],
    "sg:phone":"+44 1639 888612",
    "sg:postcode":"SA12 6DB",
    "sg:province":"Neath Port Talbot",
    "sg:tags":[
        "filter"
    ],
    "wof:name":"Filters 4 Power Ltd.",
    "wof:placetype":"venue"
},
  "geometry": {"coordinates":[-3.802369,51.591385],"type":"Point"}
}