{
  "type": "Feature",
  "properties": {
    "addr:full":"150 London Road Bedford Bedfordshire MK42 0PS",
    "addr:housenumber":"150",
    "addr:postcode":"mk42 0ps",
    "addr:street":"London Road",
    "iso:country":"GB",
    "sg:address":"150 London Road",
    "sg:city":"Bedford",
    "sg:classifiers":[
        {
            "category":"Manufacturing",
            "subcategory":"Signs",
            "type":"Manufacturing & Wholesale Goods"
        }
    ],
    "sg:phone":"+44 1234 211782",
    "sg:postcode":"MK42 0PS",
    "sg:province":"Bedfordshire",
    "sg:tags":[
        "nameplate"
    ],
    "wof:name":"Trade Signs",
    "wof:placetype":"venue"
},
  "geometry": {"coordinates":[-0.4565159976,52.1240501404],"type":"Point"}
}