{
  "type": "Feature",
  "properties": {
    "addr:full":"83 Lochend Road Glasgow Glasgow City G34 0LR",
    "addr:housenumber":"83",
    "addr:postcode":"g34 0lr",
    "addr:street":"Lochend Road",
    "iso:country":"GB",
    "sg:address":"83 Lochend Road",
    "sg:city":"Glasgow",
    "sg:classifiers":[
        {
            "category":"Food & Beverages",
            "subcategory":"Candy",
            "type":"Retail Goods"
        }
    ],
    "sg:postcode":"G34 0LR",
    "sg:province":"Glasgow City",
    "sg:tags":[
        "confectioner"
    ],
    "wof:name":"J & A Frame",
    "wof:placetype":"venue"
},
  "geometry": {"coordinates":[-4.1068229675,55.8704872131],"type":"Point"}
}