{
  "type": "Feature",
  "properties": {
    "iso:country":"GB",
    "sg:address":"Letchworth Business Centre, Avenue One",
    "sg:city":"Letchworth",
    "sg:classifiers":[
        {
            "category":"Personal",
            "subcategory":"Tanning Parlor",
            "type":"Services"
        }
    ],
    "sg:phone":"+44 1462 472400",
    "sg:postcode":"SG6 2HB",
    "sg:province":"Hertfordshire",
    "sg:tags":[
        "laser"
    ],
    "wof:name":"Electrox",
    "wof:placetype":"venue"
},
  "geometry": {"coordinates":[-0.207936,51.981407],"type":"Point"}
}