{
  "type": "Feature",
  "properties": {
    "addr:full":"59 The Square, Dunchurch Rugby Warwickshire CV22 6NU",
    "addr:housenumber":"59",
    "addr:postcode":"cv22 6nu",
    "addr:street":"The Square",
    "iso:country":"GB",
    "sg:address":"59 The Square, Dunchurch",
    "sg:city":"Rugby",
    "sg:classifiers":[
        {
            "category":"Building & Trades",
            "subcategory":"Construction",
            "type":"Services"
        }
    ],
    "sg:phone":"+44 1788 522168",
    "sg:postcode":"CV22 6NU",
    "sg:province":"Warwickshire",
    "sg:tags":[
        "flooring"
    ],
    "wof:name":"Mercia Flooring Ltd.",
    "wof:placetype":"venue"
},
  "geometry": {"coordinates":[-1.2903909683,52.3367462158],"type":"Point"}
}