{
  "type": "Feature",
  "properties": {
    "iso:country":"GB",
    "sg:address":"High Street, Newburn",
    "sg:city":"Newcastle-upon-tyne",
    "sg:classifiers":[
        {
            "category":"Health Services",
            "subcategory":"Nursing And Care Facility",
            "type":"Services"
        },
        {
            "category":"Social Services",
            "subcategory":"Retirement Home",
            "type":"Services"
        }
    ],
    "sg:phone":"+44 191 229 0500",
    "sg:postcode":"NE15 8LN",
    "sg:province":"Northumberland",
    "sg:tags":[
        "residential"
    ],
    "wof:name":"Newburn Valley View",
    "wof:placetype":"venue"
},
  "geometry": {"coordinates":[-1.741583,54.982098],"type":"Point"}
}