{
  "type": "Feature",
  "properties": {
    "addr:full":"57-59 Clarence Road Grays Essex RM17 6QJ",
    "addr:housenumber":"57-59",
    "addr:postcode":"rm17 6qj",
    "addr:street":"Clarence Road",
    "iso:country":"GB",
    "sg:address":"57-59 Clarence Road",
    "sg:city":"Grays",
    "sg:classifiers":[
        {
            "category":"Professional",
            "subcategory":"Business Services",
            "type":"Services"
        },
        {
            "category":"Shopping",
            "subcategory":"Pets & Pet Supplies",
            "type":"Retail Goods"
        }
    ],
    "sg:phone":"+44 1375 374080",
    "sg:postcode":"RM17 6QJ",
    "sg:province":"Essex",
    "sg:tags":[
        "import",
        "export",
        "agent"
    ],
    "wof:name":"W C Brainwoods",
    "wof:placetype":"venue"
},
  "geometry": {"coordinates":[0.3263550103,51.4779243469],"type":"Point"}
}