{
  "type": "Feature",
  "properties": {
    "addr:full":"London House, Market Street, Nailsworth Stroud Gloucestershire GL6 0DA",
    "addr:postcode":"gl6 0da",
    "addr:street":"Market Street",
    "iso:country":"GB",
    "sg:address":"London House, Market Street, Nailsworth",
    "sg:city":"Stroud",
    "sg:classifiers":[
        {
            "category":"Shopping",
            "subcategory":"Department Store",
            "type":"Retail Goods"
        }
    ],
    "sg:postcode":"GL6 0DA",
    "sg:province":"Gloucestershire",
    "wof:name":"Krayfish",
    "wof:placetype":"venue"
},
  "geometry": {"coordinates":[-2.217984,51.695816],"type":"Point"}
}