{
  "type": "Feature",
  "properties": {
    "addr:full":"Wellington House, 21 Canynge Road Bristol City of Bristol BS8 3JZ",
    "addr:housenumber":"21",
    "addr:postcode":"bs8 3jz",
    "addr:street":"Canynge Road",
    "iso:country":"GB",
    "sg:address":"Wellington House, 21 Canynge Road",
    "sg:city":"Bristol",
    "sg:classifiers":[
        {
            "category":"Professional",
            "subcategory":"Management & Consulting",
            "type":"Services"
        }
    ],
    "sg:postcode":"BS8 3JZ",
    "sg:province":"City of Bristol",
    "sg:tags":[
        "consultant",
        "business"
    ],
    "wof:name":"Sharon Toye Consulting Ltd.",
    "wof:placetype":"venue"
},
  "geometry": {"coordinates":[-2.6224861145,51.4587860107],"type":"Point"}
}