{
  "type": "Feature",
  "properties": {
    "iso:country":"GB",
    "sg:address":"London Road, Wendover Dean",
    "sg:city":"Aylesbury",
    "sg:classifiers":[
        {
            "category":"Building & Trades",
            "subcategory":"Construction",
            "type":"Services"
        }
    ],
    "sg:phone":"+44 1296 623729",
    "sg:postcode":"HP22 6PN",
    "sg:province":"Buckinghamshire",
    "sg:tags":[
        "excavation",
        "groundwork",
        "contractor"
    ],
    "wof:name":"C R Construction Ltd.",
    "wof:placetype":"venue"
},
  "geometry": {"coordinates":[-0.738753,51.755623],"type":"Point"}
}