{
  "type": "Feature",
  "properties": {
    "iso:country":"GB",
    "sg:address":"8 Rannoch Rd, Birkenshaw Indust Est",
    "sg:city":"Glasgow",
    "sg:classifiers":[
        {
            "category":"Home & Garden",
            "subcategory":"Furniture",
            "type":"Retail Goods"
        }
    ],
    "sg:phone":"+44 1698 816111",
    "sg:postcode":"G71 5PR",
    "sg:province":"Glasgow City",
    "wof:name":"Reid Group PLC",
    "wof:placetype":"venue"
},
  "geometry": {"coordinates":[-4.091624,55.837429],"type":"Point"}
}