{
  "type": "Feature",
  "properties": {
    "iso:country":"GB",
    "sg:address":"36 Station Road",
    "sg:city":"Liss",
    "sg:classifiers":[
        {
            "category":"Shopping",
            "subcategory":"Pets & Pet Supplies",
            "type":"Retail Goods"
        }
    ],
    "sg:phone":"+44 1730 894969",
    "sg:postcode":"GU33 7DP",
    "sg:province":"Hampshire",
    "wof:name":"David Platts",
    "wof:placetype":"venue"
},
  "geometry": {"coordinates":[-0.892456,51.043102],"type":"Point"}
}