{
  "type": "Feature",
  "properties": {
    "iso:country":"GB",
    "sg:address":"17a Saville Row",
    "sg:city":"Newcastle-upon-tyne",
    "sg:classifiers":[
        {
            "category":"Personal",
            "subcategory":"Psychics & Astrologers",
            "type":"Services"
        }
    ],
    "sg:phone":"+44 191 232 4832",
    "sg:postcode":"NE1 8JE",
    "sg:province":"Tyne and Wear",
    "sg:tags":[
        "clairvoyant",
        "palmist"
    ],
    "wof:name":"Gina",
    "wof:placetype":"venue"
},
  "geometry": {"coordinates":[-1.6115039587,54.9754905701],"type":"Point"}
}