{
  "type": "Feature",
  "properties": {
    "addr:full":"22 Oggy Street Bridgend Bridgend CF32 7SA",
    "addr:housenumber":"22",
    "addr:postcode":"cf32 7sa",
    "addr:street":"Oggy Street",
    "iso:country":"GB",
    "sg:address":"22 Oggy Street",
    "sg:city":"Bridgend",
    "sg:classifiers":[
        {
            "category":"Shopping",
            "subcategory":"Pharmacy",
            "type":"Retail Goods"
        }
    ],
    "sg:phone":"+44 1656 840440",
    "sg:postcode":"CF32 7SA",
    "sg:province":"Bridgend",
    "sg:tags":[
        "pharmacist",
        "chemist"
    ],
    "wof:name":"Alan T Brown Ltd.",
    "wof:placetype":"venue"
},
  "geometry": {"coordinates":[-3.536407,51.617989],"type":"Point"}
}