{
  "type": "Feature",
  "properties": {
    "addr:full":"174 Cromwell Road Newport Newport NP19 0HP",
    "addr:housenumber":"174",
    "addr:postcode":"np19 0hp",
    "addr:street":"Cromwell Road",
    "iso:country":"GB",
    "sg:address":"174 Cromwell Road",
    "sg:city":"Newport",
    "sg:classifiers":[
        {
            "category":"Food & Beverages",
            "subcategory":"Fruits & Vegetables",
            "type":"Retail Goods"
        }
    ],
    "sg:postcode":"NP19 0HP",
    "sg:province":"Newport",
    "sg:tags":[
        "greengrocer"
    ],
    "wof:name":"Fullwoods",
    "wof:placetype":"venue"
},
  "geometry": {"coordinates":[-2.9689910412,51.5826835632],"type":"Point"}
}