{
  "type": "Feature",
  "properties": {
    "addr:full":"The Main Barn, Charisworth, Thornicombe Blandford Forum Dorset DT11 9AL",
    "addr:postcode":"dt11 9al",
    "addr:street":"Charisworth",
    "iso:country":"GB",
    "sg:address":"The Main Barn, Charisworth, Thornicombe",
    "sg:city":"Blandford Forum",
    "sg:classifiers":[
        {
            "category":"Home & Garden",
            "subcategory":"Building Materials",
            "type":"Retail Goods"
        }
    ],
    "sg:phone":"+44 1258 453916",
    "sg:postcode":"DT11 9AL",
    "sg:province":"Dorset",
    "sg:tags":[
        "fencing"
    ],
    "wof:name":"Chris C Crabbe Fencing",
    "wof:placetype":"venue"
},
  "geometry": {"coordinates":[-2.185734,50.827976],"type":"Point"}
}