{
  "type": "Feature",
  "properties": {
    "addr:full":"3 Valley Rise, Sarisbury Grn Southampton Hampshire SO31 7BN",
    "addr:housenumber":"3",
    "addr:postcode":"so31 7bn",
    "addr:street":"Valley Rise Sarisbury Grn",
    "iso:country":"GB",
    "sg:address":"3 Valley Rise, Sarisbury Grn",
    "sg:city":"Southampton",
    "sg:classifiers":[
        {
            "category":"Social Services",
            "subcategory":"Job Training",
            "type":"Services"
        }
    ],
    "sg:postcode":"SO31 7BN",
    "sg:province":"Hampshire",
    "sg:tags":[
        "translator",
        "interpreter"
    ],
    "wof:name":"1ST Call Translations",
    "wof:placetype":"venue"
},
  "geometry": {"coordinates":[-1.28712,50.865852],"type":"Point"}
}