{
  "type": "Feature",
  "properties": {
    "iso:country":"GB",
    "sg:address":"Chapelcross Works",
    "sg:city":"Annan",
    "sg:classifiers":[
        {
            "category":"Professional",
            "type":"Services"
        }
    ],
    "sg:phone":"+44 1461 208238",
    "sg:postcode":"DG12 6RF",
    "sg:province":"Dumfries and Galloway",
    "sg:tags":[
        "repair",
        "tech",
        "maintenance"
    ],
    "wof:name":"I T Services Ltd",
    "wof:placetype":"venue"
},
  "geometry": {"coordinates":[-3.256819,54.987034],"type":"Point"}
}