{
  "type": "Feature",
  "properties": {
    "iso:country":"GB",
    "sg:address":"19 Palalwyf Ave",
    "sg:city":"Pontyclun",
    "sg:classifiers":[
        {
            "category":"Personal",
            "type":"Services"
        }
    ],
    "sg:phone":"+44 1443 226117",
    "sg:postcode":"CF72 9EG",
    "sg:province":"Bridgend",
    "sg:tags":[
        "wedding"
    ],
    "wof:name":"Head,David,",
    "wof:placetype":"venue"
},
  "geometry": {"coordinates":[-3.3909199238,51.5211219788],"type":"Point"}
}