{
  "type": "Feature",
  "properties": {
    "iso:country":"GB",
    "sg:address":"C/o Finley & Partners, 3rd Floor",
    "sg:city":"Sevenoaks",
    "sg:classifiers":[
        {
            "category":"Manufacturing",
            "subcategory":"Furniture",
            "type":"Manufacturing & Wholesale Goods"
        }
    ],
    "sg:postcode":"TN13 1BL",
    "sg:province":"Kent",
    "sg:tags":[
        "mnfr",
        "upholsterer"
    ],
    "wof:name":"The Chelsea Leather Co  Ltd",
    "wof:placetype":"venue"
},
  "geometry": {"coordinates":[0.18458,51.27607],"type":"Point"}
}