{
  "type": "Feature",
  "properties": {
    "addr:full":"Albert Rd Pontypridd Caerphilly CF37 1LB",
    "addr:postcode":"cf37 1lb",
    "addr:street":"Albert Rd",
    "iso:country":"GB",
    "sg:address":"Albert Rd",
    "sg:city":"Pontypridd",
    "sg:classifiers":[
        {
            "category":"Health Services",
            "subcategory":"Hospital",
            "type":"Services"
        }
    ],
    "sg:phone":"+44 1443 486222",
    "sg:postcode":"CF37 1LB",
    "sg:province":"Caerphilly",
    "wof:name":"Dewi Sant Hospital",
    "wof:placetype":"venue"
},
  "geometry": {"coordinates":[-3.3455638885,51.5970115662],"type":"Point"}
}