{
  "type": "Feature",
  "properties": {
    "iso:country":"GB",
    "sg:address":"159a Parkside",
    "sg:city":"Nottingham",
    "sg:classifiers":[
        {
            "category":"Building & Trades",
            "subcategory":"Plumbing",
            "type":"Services"
        }
    ],
    "sg:phone":"+44 115 928 2309",
    "sg:postcode":"NG8 2NL",
    "sg:province":"Nottinghamshire",
    "sg:tags":[
        "heating"
    ],
    "wof:name":"D Harwood",
    "wof:placetype":"venue"
},
  "geometry": {"coordinates":[-1.225182,52.949738],"type":"Point"}
}