{
  "type": "Feature",
  "properties": {
    "iso:country":"GB",
    "sg:address":"89-90 High Street, Twerton-on-avon",
    "sg:city":"Bath",
    "sg:classifiers":[
        {
            "category":"Shopping",
            "subcategory":"Department Store",
            "type":"Retail Goods"
        }
    ],
    "sg:postcode":"BA1 1DE",
    "sg:province":"Bath and North East Somerset",
    "wof:name":"Allsorts",
    "wof:placetype":"venue"
},
  "geometry": {"coordinates":[-2.3589539528,51.3818092346],"type":"Point"}
}