{
  "type": "Feature",
  "properties": {
    "addr:full":"16-17 Princes Street Edinburgh City of Edinburgh EH2 2AN",
    "addr:housenumber":"16-17",
    "addr:postcode":"eh2 2an",
    "addr:street":"Princes Street",
    "iso:country":"GB",
    "sg:address":"16-17 Princes Street",
    "sg:city":"Edinburgh",
    "sg:classifiers":[
        {
            "category":"Shopping",
            "subcategory":"Clothing, Apparel, & Fashions",
            "type":"Retail Goods"
        }
    ],
    "sg:phone":"+44 131 557 0120",
    "sg:postcode":"EH2 2AN",
    "sg:province":"City of Edinburgh",
    "sg:tags":[
        "shop"
    ],
    "wof:name":"Principles for Men",
    "wof:placetype":"venue"
},
  "geometry": {"coordinates":[-3.1905300617,55.9532737732],"type":"Point"}
}