{
  "type": "Feature",
  "properties": {
    "addr:full":"Unit 4, Horsbeck Industrial Estate, Horsbeck Way Norwich Norfolk NR10 3SS",
    "addr:housenumber":"unit 4",
    "addr:postcode":"nr10 3ss",
    "addr:street":"Horsbeck Industrial Estate Horsbeck Way",
    "iso:country":"GB",
    "sg:address":"Unit 4, Horsbeck Industrial Estate, Horsbeck Way",
    "sg:city":"Norwich",
    "sg:classifiers":[
        {
            "category":"Manufacturing",
            "subcategory":"Signs",
            "type":"Manufacturing & Wholesale Goods"
        }
    ],
    "sg:postcode":"NR10 3SS",
    "sg:province":"Norfolk",
    "sg:tags":[
        "commercial",
        "maker"
    ],
    "wof:name":"Anglia Sign Casting Co.",
    "wof:placetype":"venue"
},
  "geometry": {"coordinates":[1.2949,52.622494],"type":"Point"}
}