{
  "type": "Feature",
  "properties": {
    "addr:full":"16 Esk Way Romford Essex RM1 4YH",
    "addr:housenumber":"16",
    "addr:postcode":"rm1 4yh",
    "addr:street":"Esk Way",
    "iso:country":"GB",
    "sg:address":"16 Esk Way",
    "sg:city":"Romford",
    "sg:classifiers":[
        {
            "category":"Building & Trades",
            "subcategory":"Plumbing",
            "type":"Services"
        }
    ],
    "sg:postcode":"RM1 4YH",
    "sg:province":"Essex",
    "sg:tags":[
        "heating"
    ],
    "wof:name":"Riley,Stephen,",
    "wof:placetype":"venue"
},
  "geometry": {"coordinates":[0.179672,51.59927],"type":"Point"}
}