{
  "type": "Feature",
  "properties": {
    "addr:full":"195 King Cross Rd Halifax West Yorkshire HX1 2LB",
    "addr:housenumber":"195",
    "addr:postcode":"hx1 2lb",
    "addr:street":"King Cross Rd",
    "iso:country":"GB",
    "sg:address":"195 King Cross Rd",
    "sg:city":"Halifax",
    "sg:classifiers":[
        {
            "category":"Autos & Motor Vehicles",
            "subcategory":"Motorcycle Sales",
            "type":"Retail Goods"
        }
    ],
    "sg:phone":"+44 1422 345636",
    "sg:postcode":"HX1 2LB",
    "sg:province":"West Yorkshire",
    "sg:tags":[
        "chauffeur",
        "driven",
        "car"
    ],
    "wof:name":"All Occasions Weddng Gallery",
    "wof:placetype":"venue"
},
  "geometry": {"coordinates":[-1.87987,53.71566],"type":"Point"}
}