{
  "type": "Feature",
  "properties": {
    "iso:country":"GB",
    "sg:address":"Unit 4 Harvester Way, Fengate",
    "sg:city":"Peterborough",
    "sg:classifiers":[
        {
            "category":"Building & Trades",
            "subcategory":"Construction",
            "type":"Services"
        }
    ],
    "sg:phone":"+44 1733 344177",
    "sg:postcode":"PE1 5UT",
    "sg:province":"Cambridgeshire",
    "sg:tags":[
        "glazier"
    ],
    "wof:name":"R A Baker (Glaziers & Merchants)",
    "wof:placetype":"venue"
},
  "geometry": {"coordinates":[-0.2252289951,52.5707855225],"type":"Point"}
}