{
  "type": "Feature",
  "properties": {
    "addr:full":"192 Kingston Road New Malden Surrey KT3 3RJ",
    "addr:housenumber":"192",
    "addr:postcode":"kt3 3rj",
    "addr:street":"Kingston Road",
    "iso:country":"GB",
    "sg:address":"192 Kingston Road",
    "sg:city":"New Malden",
    "sg:classifiers":[
        {
            "category":"Shopping",
            "subcategory":"News",
            "type":"Retail Goods"
        }
    ],
    "sg:phone":"+44 20 8942 0572",
    "sg:postcode":"KT3 3RJ",
    "sg:province":"Surrey",
    "sg:tags":[
        "newsagent"
    ],
    "wof:name":"Topshop",
    "wof:placetype":"venue"
},
  "geometry": {"coordinates":[-0.272054,51.402557],"type":"Point"}
}