{
  "type": "Feature",
  "properties": {
    "iso:country":"GB",
    "sg:address":"64 High Street",
    "sg:city":"Milton Keynes",
    "sg:classifiers":[
        {
            "category":"Travel",
            "subcategory":"Hotels & Motels",
            "type":"Entertainment"
        },
        {
            "category":"Restaurant",
            "type":"Food & Drink"
        }
    ],
    "sg:phone":"+44 1908 561102",
    "sg:postcode":"MK11 1AQ",
    "sg:province":"Buckinghamshire",
    "sg:tags":[
        "mexican"
    ],
    "wof:name":"The Bull Hotel",
    "wof:placetype":"venue"
},
  "geometry": {"coordinates":[-0.8536440134,52.0574569702],"type":"Point"}
}