{
  "type": "Feature",
  "properties": {
    "iso:country":"GB",
    "sg:address":"100 Embankment Road",
    "sg:city":"Plymouth",
    "sg:classifiers":[
        {
            "category":"Wholesale",
            "subcategory":"Office Equipment",
            "type":"Manufacturing & Wholesale Goods"
        }
    ],
    "sg:phone":"+44 1752 251902",
    "sg:postcode":"PL4 9HY",
    "sg:province":"Devon",
    "sg:tags":[
        "register",
        "cash",
        "accessory"
    ],
    "wof:name":"Y C R",
    "wof:placetype":"venue"
},
  "geometry": {"coordinates":[-4.1192979813,50.3707695007],"type":"Point"}
}