{
  "type": "Feature",
  "properties": {
    "addr:full":"2 Hill Cottages, Littlestead Green Reading Berkshire RG4 9PY",
    "addr:housenumber":"2",
    "addr:postcode":"rg4 9py",
    "addr:street":"Hill Cottages Littlestead Green",
    "iso:country":"GB",
    "sg:address":"2 Hill Cottages, Littlestead Green",
    "sg:city":"Reading",
    "sg:classifiers":[
        {
            "category":"Building & Trades",
            "subcategory":"Construction",
            "type":"Services"
        }
    ],
    "sg:phone":"+44 7956 465987",
    "sg:postcode":"RG4 9PY",
    "sg:province":"Berkshire",
    "sg:tags":[
        "decorator",
        "painter"
    ],
    "wof:name":"E A West",
    "wof:placetype":"venue"
},
  "geometry": {"coordinates":[-0.94462,51.487911],"type":"Point"}
}