{
  "type": "Feature",
  "properties": {
    "iso:country":"GB",
    "sg:address":"9 Mawddwy Cottages",
    "sg:city":"Machynlleth",
    "sg:classifiers":[
        {
            "category":"Landmark",
            "subcategory":"Tourist Information",
            "type":"Public Place"
        }
    ],
    "sg:phone":"+44 1650 531354",
    "sg:postcode":"SY20 9LW",
    "sg:province":"Ceredigion",
    "sg:tags":[
        "tour",
        "guide",
        "sightseeing"
    ],
    "wof:name":"L Main",
    "wof:placetype":"venue"
},
  "geometry": {"coordinates":[-3.732663,52.679104],"type":"Point"}
}