{
  "type": "Feature",
  "properties": {
    "iso:country":"GB",
    "sg:address":"Aspenden Road",
    "sg:city":"Buntingford",
    "sg:classifiers":[
        {
            "category":"Autos & Motor Vehicles",
            "subcategory":"Auto Supplies",
            "type":"Retail Goods"
        }
    ],
    "sg:postcode":"SG9 9JB",
    "sg:province":"Hertfordshire",
    "sg:tags":[
        "tyre"
    ],
    "wof:name":"Buntingford Tyre & Exhaust",
    "wof:placetype":"venue"
},
  "geometry": {"coordinates":[-0.0167050008,51.9420166016],"type":"Point"}
}