{
  "type": "Feature",
  "properties": {
    "addr:full":"Unit 0 Farm Buildings, Maiden Lane Dartford Kent DA1 4LX",
    "addr:housenumber":"unit 0",
    "addr:postcode":"da1 4lx",
    "addr:street":"Farm Buildings Maiden Lane",
    "iso:country":"GB",
    "sg:address":"Unit 0 Farm Buildings, Maiden Lane",
    "sg:city":"Dartford",
    "sg:classifiers":[
        {
            "category":"Professional",
            "subcategory":"Engineering",
            "type":"Services"
        }
    ],
    "sg:phone":"+44 1322 558748",
    "sg:postcode":"DA1 4LX",
    "sg:province":"Kent",
    "sg:tags":[
        "precision",
        "engineer"
    ],
    "wof:name":"I Larcombe Universal Grinding Services",
    "wof:placetype":"venue"
},
  "geometry": {"coordinates":[0.192245,51.454311],"type":"Point"}
}