{
  "type": "Feature",
  "properties": {
    "iso:country":"GB",
    "sg:address":"25a Clerk Street",
    "sg:city":"Loanhead",
    "sg:classifiers":[
        {
            "category":"Retail",
            "subcategory":"Auto Repair",
            "type":"Services"
        }
    ],
    "sg:phone":"+44 131 440 0560",
    "sg:postcode":"EH20 9DP",
    "sg:province":"Midlothian",
    "sg:tags":[
        "modification",
        "garage"
    ],
    "wof:name":"Robertson's Garage Services",
    "wof:placetype":"venue"
},
  "geometry": {"coordinates":[-3.150569,55.879295],"type":"Point"}
}