{
  "type": "Feature",
  "properties": {
    "addr:full":"Unit 20, Hightown Industrial Estate Ringwood Dorset BH24 1ND",
    "addr:housenumber":"unit 20;estate",
    "addr:postcode":"bh24 1nd",
    "addr:street":"Hightown Industrial",
    "iso:country":"GB",
    "sg:address":"Unit 20, Hightown Industrial Estate",
    "sg:city":"Ringwood",
    "sg:classifiers":[
        {
            "category":"Manufacturing",
            "subcategory":"Signs",
            "type":"Manufacturing & Wholesale Goods"
        }
    ],
    "sg:phone":"+44 1425 471537",
    "sg:postcode":"BH24 1ND",
    "sg:province":"Dorset",
    "sg:tags":[
        "nameplate"
    ],
    "wof:name":"Multi-Signs",
    "wof:placetype":"venue"
},
  "geometry": {"coordinates":[-1.7929890156,50.8463287354],"type":"Point"}
}