{
  "type": "Feature",
  "properties": {
    "iso:country":"GB",
    "sg:address":"Vanston Place",
    "sg:city":"London",
    "sg:classifiers":[
        {
            "category":"Organizations",
            "subcategory":"Membership Organization",
            "type":"Services"
        }
    ],
    "sg:phone":"+44 20 7385 4181",
    "sg:postcode":"SW6 1AY",
    "sg:province":"Greater London",
    "sg:tags":[
        "club"
    ],
    "wof:name":"Mecca Bingo Ltd.",
    "wof:placetype":"venue"
},
  "geometry": {"coordinates":[-0.198682,51.481354],"type":"Point"}
}