{
  "type": "Feature",
  "properties": {
    "addr:full":"2 Radnor Place Liverpool Merseyside L6 4BD",
    "addr:housenumber":"2",
    "addr:postcode":"l6 4bd",
    "addr:street":"Radnor Place",
    "iso:country":"GB",
    "sg:address":"2 Radnor Place",
    "sg:city":"Liverpool",
    "sg:classifiers":[
        {
            "category":"Health Services",
            "subcategory":"Doctor",
            "type":"Services"
        }
    ],
    "sg:phone":"+44 151 263 3100",
    "sg:postcode":"L6 4BD",
    "sg:province":"Merseyside",
    "sg:tags":[
        "practitioners"
    ],
    "wof:name":"Radnor Medical Centre",
    "wof:placetype":"venue"
},
  "geometry": {"coordinates":[-2.939683,53.422985],"type":"Point"}
}