{
  "type": "Feature",
  "properties": {
    "addr:full":"16-18 Lancaster Road Preston Lancashire PR1 1DA",
    "addr:housenumber":"16-18",
    "addr:postcode":"pr1 1da",
    "addr:street":"Lancaster Road",
    "iso:country":"GB",
    "sg:address":"16-18 Lancaster Road",
    "sg:city":"Preston",
    "sg:classifiers":[
        {
            "category":"Restaurant",
            "type":"Food & Drink"
        }
    ],
    "sg:postcode":"PR1 1DA",
    "sg:province":"Lancashire",
    "wof:name":"Piccolo Restaurant",
    "wof:placetype":"venue"
},
  "geometry": {"coordinates":[-2.6974110603,53.758895874],"type":"Point"}
}