{
  "type": "Feature",
  "properties": {
    "iso:country":"GB",
    "sg:address":"51 Riland Road",
    "sg:city":"Sutton Coldfield",
    "sg:classifiers":[
        {
            "category":"Shopping",
            "subcategory":"Department Store",
            "type":"Retail Goods"
        }
    ],
    "sg:postcode":"B75 7AQ",
    "sg:province":"Staffordshire",
    "wof:name":"J N A G Beadman & Son",
    "wof:placetype":"venue"
},
  "geometry": {"coordinates":[-1.8164440393,52.5637168884],"type":"Point"}
}