{
  "type": "Feature",
  "properties": {
    "addr:full":"Ty Oldfield, Llantrisant Road Cardiff Cardiff CF5 2PU",
    "addr:postcode":"cf5 2pu",
    "addr:street":"Llantrisant Road",
    "iso:country":"GB",
    "sg:address":"Ty Oldfield, Llantrisant Road",
    "sg:city":"Cardiff",
    "sg:classifiers":[
        {
            "category":"Communications",
            "type":"Services"
        }
    ],
    "sg:phone":"+44 29 2057 5729",
    "sg:postcode":"CF5 2PU",
    "sg:province":"Cardiff",
    "sg:tags":[
        "broadcasting"
    ],
    "wof:name":"Presentable Productions Independent Tv & Radio Co.",
    "wof:placetype":"venue"
},
  "geometry": {"coordinates":[-3.236619,51.499729],"type":"Point"}
}