{
  "type": "Feature",
  "properties": {
    "addr:full":"169 Corporation Road Newport Newport NP19 0BJ",
    "addr:housenumber":"169",
    "addr:postcode":"np19 0bj",
    "addr:street":"Corporation Road",
    "iso:country":"GB",
    "sg:address":"169 Corporation Road",
    "sg:city":"Newport",
    "sg:classifiers":[
        {
            "category":"Shopping",
            "subcategory":"Crafts & Fabrics",
            "type":"Retail Goods"
        }
    ],
    "sg:phone":"+44 1633 263327",
    "sg:postcode":"NP19 0BJ",
    "sg:province":"Newport",
    "sg:tags":[
        "shop"
    ],
    "wof:name":"Sidhu Fabrics",
    "wof:placetype":"venue"
},
  "geometry": {"coordinates":[-2.982517,51.586735],"type":"Point"}
}