{
  "type": "Feature",
  "properties": {
    "iso:country":"GB",
    "sg:address":"Winsor Bridge Road, Lower Bristol Road",
    "sg:city":"Bath",
    "sg:classifiers":[
        {
            "category":"Manufacturing",
            "subcategory":"Wood Products",
            "type":"Manufacturing & Wholesale Goods"
        },
        {
            "category":"Building & Trades",
            "subcategory":"Construction",
            "type":"Services"
        }
    ],
    "sg:phone":"+44 1225 318356",
    "sg:postcode":"BA2 3AY",
    "sg:province":"Somerset",
    "sg:tags":[
        "joinery",
        "manufacturer"
    ],
    "wof:name":"Windsor Joinery Bath Ltd",
    "wof:placetype":"venue"
},
  "geometry": {"coordinates":[-2.3812739849,51.3823013306],"type":"Point"}
}