{
  "type": "Feature",
  "properties": {
    "addr:full":"139 Queen Emmas Dyke Witney Oxfordshire OX28 4DT",
    "addr:housenumber":"139",
    "addr:postcode":"ox28 4dt",
    "addr:street":"Queen Emmas Dyke",
    "iso:country":"GB",
    "sg:address":"139 Queen Emmas Dyke",
    "sg:city":"Witney",
    "sg:classifiers":[
        {
            "category":"Professional",
            "subcategory":"Management & Consulting",
            "type":"Services"
        }
    ],
    "sg:postcode":"OX28 4DT",
    "sg:province":"Oxfordshire",
    "sg:tags":[
        "marketing",
        "consultant"
    ],
    "wof:name":"Tucker,Chris,",
    "wof:placetype":"venue"
},
  "geometry": {"coordinates":[-1.494027,51.782459],"type":"Point"}
}