{
  "type": "Feature",
  "properties": {
    "iso:country":"GB",
    "sg:address":"34 Acre Lane",
    "sg:city":"London",
    "sg:classifiers":[
        {
            "category":"Autos & Motor Vehicles",
            "subcategory":"Auto Supplies",
            "type":"Retail Goods"
        }
    ],
    "sg:phone":"+44 20 7274 0082",
    "sg:postcode":"SW2 5SG",
    "sg:province":"Greater London",
    "sg:tags":[
        "component"
    ],
    "wof:name":"German & Swedish (Vee Wee)",
    "wof:placetype":"venue"
},
  "geometry": {"coordinates":[-0.118553,51.460541],"type":"Point"}
}