{
  "type": "Feature",
  "properties": {
    "addr:full":"The Minories Art Gallery, 74 High St Colchester Essex CO1 1UE",
    "addr:housenumber":"74",
    "addr:postcode":"co1 1ue",
    "addr:street":"High St",
    "iso:country":"GB",
    "sg:address":"The Minories Art Gallery, 74 High St",
    "sg:city":"Colchester",
    "sg:classifiers":[
        {
            "category":"Museum",
            "subcategory":"Art Museum",
            "type":"Entertainment"
        }
    ],
    "sg:phone":"+44 1206 577067",
    "sg:postcode":"CO1 1UE",
    "sg:province":"Essex",
    "sg:tags":[
        "gallery"
    ],
    "wof:name":"Firstsite",
    "wof:placetype":"venue"
},
  "geometry": {"coordinates":[0.9049000144,51.8897895813],"type":"Point"}
}