{
  "type": "Feature",
  "properties": {
    "iso:country":"GB",
    "sg:address":"Block B, 3rd Floor, 95-103 Zephyr Business Centre, Tottenham",
    "sg:city":"Seven Sisters",
    "sg:classifiers":[
        {
            "category":"Shopping",
            "subcategory":"Clothing, Apparel, & Fashions",
            "type":"Retail Goods"
        }
    ],
    "sg:phone":"+44 20 8880 1347",
    "sg:postcode":"N15 4EP",
    "sg:province":"Greater London",
    "sg:tags":[
        "clothing"
    ],
    "wof:name":"Tica Ltd",
    "wof:placetype":"venue"
},
  "geometry": {"coordinates":[-0.07967,51.5863],"type":"Point"}
}