{
  "type": "Feature",
  "properties": {
    "addr:full":"10 Hanborough Business Park, Long Hanborough Witney Oxfordshire OX29 8LH",
    "addr:housenumber":"10",
    "addr:postcode":"ox29 8lh",
    "addr:street":"Hanborough Business Park Long",
    "iso:country":"GB",
    "sg:address":"10 Hanborough Business Park, Long Hanborough",
    "sg:city":"Witney",
    "sg:classifiers":[
        {
            "category":"Wholesale",
            "subcategory":"Books, Periodicals, & Newspapers",
            "type":"Manufacturing & Wholesale Goods"
        }
    ],
    "sg:phone":"+44 1993 883161",
    "sg:postcode":"OX29 8LH",
    "sg:province":"Oxfordshire",
    "sg:tags":[
        "maps",
        "globe",
        "chart",
        "pub"
    ],
    "wof:name":"Lovell Johns Ltd.",
    "wof:placetype":"venue"
},
  "geometry": {"coordinates":[-1.3691389561,51.8259468079],"type":"Point"}
}