{
  "type": "Feature",
  "properties": {
    "addr:full":"6 Rydale Court, Haxby York North Yorkshire YO32 3SA",
    "addr:housenumber":"6",
    "addr:postcode":"yo32 3sa",
    "addr:street":"Rydale Court",
    "iso:country":"GB",
    "sg:address":"6 Rydale Court, Haxby",
    "sg:city":"York",
    "sg:classifiers":[
        {
            "category":"Health Services",
            "subcategory":"Optometrist",
            "type":"Services"
        }
    ],
    "sg:phone":"+44 1904 766217",
    "sg:postcode":"YO32 3SA",
    "sg:province":"North Yorkshire",
    "sg:tags":[
        "optician"
    ],
    "wof:name":"Lineastral Ltd.",
    "wof:placetype":"venue"
},
  "geometry": {"coordinates":[-1.0740089417,54.0157546997],"type":"Point"}
}