{
  "type": "Feature",
  "properties": {
    "addr:full":"29 Moor Hall Drive Sutton Coldfield Staffordshire B75 6LP",
    "addr:housenumber":"29",
    "addr:postcode":"b75 6lp",
    "addr:street":"Moor Hall Drive",
    "iso:country":"GB",
    "sg:address":"29 Moor Hall Drive",
    "sg:city":"Sutton Coldfield",
    "sg:classifiers":[
        {
            "category":"Banks & Credit Unions",
            "subcategory":"Financial Services",
            "type":"Services"
        }
    ],
    "sg:phone":"+44 121 323 2155",
    "sg:postcode":"B75 6LP",
    "sg:province":"Staffordshire",
    "sg:tags":[
        "adviser",
        "independent"
    ],
    "wof:name":"MCCORMACK & ASSOCIATES",
    "wof:placetype":"venue"
},
  "geometry": {"coordinates":[-1.813274,52.581921],"type":"Point"}
}