{
  "type": "Feature",
  "properties": {
    "addr:full":"21-25 Paynes Road Southampton Hampshire SO15 3DL",
    "addr:housenumber":"21-25",
    "addr:postcode":"so15 3dl",
    "addr:street":"Paynes Road",
    "iso:country":"GB",
    "sg:address":"21-25 Paynes Road",
    "sg:city":"Southampton",
    "sg:classifiers":[
        {
            "category":"Home & Garden",
            "subcategory":"Home Furnishings",
            "type":"Retail Goods"
        },
        {
            "category":"Social Services",
            "subcategory":"Adult Care",
            "type":"Services"
        }
    ],
    "sg:phone":"+44 23 8063 4779",
    "sg:postcode":"SO15 3DL",
    "sg:province":"Hampshire",
    "sg:tags":[
        "merchant",
        "decorator",
        "diy",
        "decorators'"
    ],
    "wof:name":"C Brewer & Sons Ltd",
    "wof:placetype":"venue"
},
  "geometry": {"coordinates":[-1.4243619442,50.9137535095],"type":"Point"}
}