{
  "type": "Feature",
  "properties": {
    "iso:country":"GB",
    "sg:address":"Whitehurst Farm, Dilhorne",
    "sg:city":"Stoke-on-trent",
    "sg:classifiers":[
        {
            "category":"Farming",
            "subcategory":"Livestock Farm",
            "type":"Manufacturing & Wholesale Goods"
        }
    ],
    "sg:phone":"+44 1538 753199",
    "sg:postcode":"ST10 2PG",
    "sg:province":"Staffordshire",
    "sg:tags":[
        "others"
    ],
    "wof:name":"S White",
    "wof:placetype":"venue"
},
  "geometry": {"coordinates":[-2.1750690937,53.0293693542],"type":"Point"}
}