{
  "type": "Feature",
  "properties": {
    "addr:full":"Main Road, Elderslie Johnstone Renfrewshire PA5 9EF",
    "addr:postcode":"pa5 9ef",
    "addr:street":"Main Road",
    "iso:country":"GB",
    "sg:address":"Main Road, Elderslie",
    "sg:city":"Johnstone",
    "sg:classifiers":[
        {
            "category":"Place Of Worship",
            "type":"Public Place"
        }
    ],
    "sg:phone":"+44 1505 323348",
    "sg:postcode":"PA5 9EF",
    "sg:province":"Renfrewshire",
    "wof:name":"The Elderslie Kirk",
    "wof:placetype":"venue"
},
  "geometry": {"coordinates":[-4.467989,55.839195],"type":"Point"}
}