{
  "type": "Feature",
  "properties": {
    "addr:full":"Marsh Farm House, Wardington Road, Chacombe Banbury Northamptonshire OX17 2JU",
    "addr:postcode":"ox17 2ju",
    "addr:street":"Wardington Road",
    "iso:country":"GB",
    "sg:address":"Marsh Farm House, Wardington Road, Chacombe",
    "sg:city":"Banbury",
    "sg:classifiers":[
        {
            "category":"Farming",
            "subcategory":"Livestock Farm",
            "type":"Manufacturing & Wholesale Goods"
        }
    ],
    "sg:phone":"+44 1295 758941",
    "sg:postcode":"OX17 2JU",
    "sg:province":"Northamptonshire",
    "sg:tags":[
        "others"
    ],
    "wof:name":"W W Stroud & Co.",
    "wof:placetype":"venue"
},
  "geometry": {"coordinates":[-1.2831259966,52.0908317566],"type":"Point"}
}