{
  "type": "Feature",
  "properties": {
    "addr:full":"20 Alvamley Gardens London Greater London NW6 1JD",
    "addr:housenumber":"20",
    "addr:postcode":"nw6 1jd",
    "addr:street":"Alvamley Gardens",
    "iso:country":"GB",
    "sg:address":"20 Alvamley Gardens",
    "sg:city":"London",
    "sg:classifiers":[
        {
            "category":"Professional",
            "subcategory":"Business Services",
            "type":"Services"
        }
    ],
    "sg:postcode":"NW6 1JD",
    "sg:province":"Greater London",
    "sg:tags":[
        "import",
        "export",
        "agent"
    ],
    "wof:name":"Icktro Ltd.",
    "wof:placetype":"venue"
},
  "geometry": {"coordinates":[-0.187923,51.552387],"type":"Point"}
}