{
  "type": "Feature",
  "properties": {
    "iso:country":"GB",
    "sg:address":"153 Effingham Street",
    "sg:city":"Rotherham",
    "sg:classifiers":[
        {
            "category":"Home & Garden",
            "subcategory":"Hardware",
            "type":"Retail Goods"
        }
    ],
    "sg:phone":"+44 1709 512842",
    "sg:postcode":"S65 1BL",
    "sg:province":"South Yorkshire",
    "sg:tags":[
        "shop",
        "retailer",
        "diy"
    ],
    "wof:name":"Hoylands D I Y",
    "wof:placetype":"venue"
},
  "geometry": {"coordinates":[-1.353908,53.43578],"type":"Point"}
}