{
  "type": "Feature",
  "properties": {
    "addr:full":"Rear Of 30 Whites Road Cleethorpes Lincolnshire DN35 8RN",
    "addr:housenumber":"rear of 30",
    "addr:postcode":"dn35 8rn",
    "addr:street":"Whites Road",
    "iso:country":"GB",
    "sg:address":"Rear Of 30 Whites Road",
    "sg:city":"Cleethorpes",
    "sg:classifiers":[
        {
            "category":"Professional",
            "subcategory":"Printing & Photocopies",
            "type":"Services"
        }
    ],
    "sg:postcode":"DN35 8RN",
    "sg:province":"Lincolnshire",
    "sg:tags":[
        "printer"
    ],
    "wof:name":"J & M Pullan Ltd.",
    "wof:placetype":"venue"
},
  "geometry": {"coordinates":[-0.0393589996,53.5594902039],"type":"Point"}
}