{
  "type": "Feature",
  "properties": {
    "iso:country":"GB",
    "sg:address":"Regency House, Lawfords Hill Close, Worplesdon",
    "sg:city":"Guildford",
    "sg:classifiers":[
        {
            "category":"Professional",
            "subcategory":"Accounting & Tax Preparation",
            "type":"Services"
        }
    ],
    "sg:phone":"+44 1483 232400",
    "sg:postcode":"GU3 3QD",
    "sg:province":"Surrey",
    "sg:tags":[
        "accountant"
    ],
    "wof:name":"Lau & Co",
    "wof:placetype":"venue"
},
  "geometry": {"coordinates":[-0.608898,51.275837],"type":"Point"}
}