{
  "type": "Feature",
  "properties": {
    "iso:country":"GB",
    "sg:address":"42 High Street",
    "sg:city":"Bembridge",
    "sg:classifiers":[
        {
            "category":"Retail",
            "subcategory":"Storage",
            "type":"Services"
        }
    ],
    "sg:phone":"+44 1983 872663",
    "sg:postcode":"PO35 5SF",
    "sg:province":"Isle of Wight",
    "sg:tags":[
        "household",
        "removal"
    ],
    "wof:name":"Lacey's (I O W) Ltd.",
    "wof:placetype":"venue"
},
  "geometry": {"coordinates":[-1.090258956,50.6894950867],"type":"Point"}
}