{
  "type": "Feature",
  "properties": {
    "addr:full":"Upper House, Little Cake Lane Huddersfield South Yorkshire HD9 1RW",
    "addr:postcode":"hd9 1rw",
    "addr:street":"Little Cake Lane",
    "iso:country":"GB",
    "sg:address":"Upper House, Little Cake Lane",
    "sg:city":"Huddersfield",
    "sg:classifiers":[
        {
            "category":"Social Services",
            "subcategory":"Retirement Home",
            "type":"Services"
        }
    ],
    "sg:phone":"+44 1484 605832",
    "sg:postcode":"HD9 1RW",
    "sg:province":"South Yorkshire",
    "sg:tags":[
        "care"
    ],
    "wof:name":"Choices Home Care Ltd.",
    "wof:placetype":"venue"
},
  "geometry": {"coordinates":[-1.76967,53.55051],"type":"Point"}
}