{
  "type": "Feature",
  "properties": {
    "addr:full":"Gascoigne Road Barking Essex IG11 7DR",
    "addr:postcode":"ig11 7dr",
    "addr:street":"Gascoigne Road",
    "iso:country":"GB",
    "sg:address":"Gascoigne Road",
    "sg:city":"Barking",
    "sg:classifiers":[
        {
            "category":"Education",
            "subcategory":"School",
            "type":"Public Place"
        }
    ],
    "sg:phone":"+44 20 8270 4291",
    "sg:postcode":"IG11 7DR",
    "sg:province":"Essex",
    "sg:tags":[
        "local",
        "authority"
    ],
    "wof:name":"Gascoigne Primary School",
    "wof:placetype":"venue"
},
  "geometry": {"coordinates":[0.078921,51.533688],"type":"Point"}
}