{
  "type": "Feature",
  "properties": {
    "iso:country":"GB",
    "sg:address":"9-11 Whitby Street",
    "sg:city":"Hartlepool",
    "sg:classifiers":[
        {
            "category":"Building & Trades",
            "subcategory":"Construction",
            "type":"Services"
        }
    ],
    "sg:phone":"+44 1429 263191",
    "sg:postcode":"TS24 7AD",
    "sg:province":"Durham",
    "sg:tags":[
        "heating",
        "contractor"
    ],
    "wof:name":"Crestbrook Heating Ltd.",
    "wof:placetype":"venue"
},
  "geometry": {"coordinates":[-1.2070200443,54.6854171753],"type":"Point"}
}