{
  "type": "Feature",
  "properties": {
    "addr:full":"147 Reculver Road Herne Bay Kent CT6 6PL",
    "addr:housenumber":"147",
    "addr:postcode":"ct6 6pl",
    "addr:street":"Reculver Road",
    "iso:country":"GB",
    "sg:address":"147 Reculver Road",
    "sg:city":"Herne Bay",
    "sg:classifiers":[
        {
            "category":"Manufacturing",
            "subcategory":"Signs",
            "type":"Manufacturing & Wholesale Goods"
        }
    ],
    "sg:postcode":"CT6 6PL",
    "sg:province":"Kent",
    "sg:tags":[
        "writer"
    ],
    "wof:name":"Lifestyle Signs",
    "wof:placetype":"venue"
},
  "geometry": {"coordinates":[1.1557070017,51.3705940247],"type":"Point"}
}