{
  "type": "Feature",
  "properties": {
    "iso:country":"GB",
    "sg:address":"45 Fern Gore Avenue",
    "sg:city":"Accrington",
    "sg:classifiers":[
        {
            "category":"Shopping",
            "subcategory":"News",
            "type":"Retail Goods"
        }
    ],
    "sg:phone":"+44 1254 234538",
    "sg:postcode":"BB5 0NF",
    "sg:province":"Lancashire",
    "sg:tags":[
        "newsagent"
    ],
    "wof:name":"Fern Gore News",
    "wof:placetype":"venue"
},
  "geometry": {"coordinates":[-2.377572,53.74197],"type":"Point"}
}