{
  "type": "Feature",
  "properties": {
    "addr:full":"178 Chillingham Road Newcastle-upon-tyne Tyne and Wear NE6 5BU",
    "addr:housenumber":"178",
    "addr:postcode":"ne6 5bu",
    "addr:street":"Chillingham Road",
    "iso:country":"GB",
    "sg:address":"178 Chillingham Road",
    "sg:city":"Newcastle-upon-tyne",
    "sg:classifiers":[
        {
            "category":"Building & Trades",
            "subcategory":"Plumbing",
            "type":"Services"
        }
    ],
    "sg:phone":"+44 191 265 6920",
    "sg:postcode":"NE6 5BU",
    "sg:province":"Tyne and Wear",
    "sg:tags":[
        "plumber",
        "heating"
    ],
    "wof:name":"B E Oakley",
    "wof:placetype":"venue"
},
  "geometry": {"coordinates":[-1.5763629675,54.9856567383],"type":"Point"}
}