{
  "type": "Feature",
  "properties": {
    "addr:full":"61 Broadway Manchester Lancashire M35 0DX",
    "addr:housenumber":"61",
    "addr:postcode":"m35 0dx",
    "addr:street":"Broadway",
    "iso:country":"GB",
    "sg:address":"61 Broadway",
    "sg:city":"Manchester",
    "sg:classifiers":[
        {
            "category":"Place Of Worship",
            "type":"Public Place"
        }
    ],
    "sg:phone":"+44 161 370 1831",
    "sg:postcode":"M35 0DX",
    "sg:province":"Lancashire",
    "wof:name":"Abbey Hey Methodist Church",
    "wof:placetype":"venue"
},
  "geometry": {"coordinates":[-2.170027,53.511879],"type":"Point"}
}