{
  "type": "Feature",
  "properties": {
    "addr:full":"306a Portobello Rd Ladbroke Grove Greater London W10 5TA",
    "addr:housenumber":"306a",
    "addr:postcode":"w10 5ta",
    "addr:street":"Portobello Rd",
    "iso:country":"GB",
    "sg:address":"306a Portobello Rd",
    "sg:city":"Ladbroke Grove",
    "sg:classifiers":[
        {
            "category":"Organizations",
            "subcategory":"Non-profit Organization",
            "type":"Services"
        }
    ],
    "sg:phone":"+44 20 8932 4000",
    "sg:postcode":"W10 5TA",
    "sg:province":"Greater London",
    "sg:tags":[
        "organisation",
        "voluntary",
        "charity"
    ],
    "wof:name":"Azafady",
    "wof:placetype":"venue"
},
  "geometry": {"coordinates":[-0.2086489946,51.5206565857],"type":"Point"}
}