{
  "type": "Feature",
  "properties": {
    "addr:full":"7 Virginia Street Aberdeen Aberdeen City AB11 5AZ",
    "addr:housenumber":"7",
    "addr:postcode":"ab11 5az",
    "addr:street":"Virginia Street",
    "iso:country":"GB",
    "sg:address":"7 Virginia Street",
    "sg:city":"Aberdeen",
    "sg:classifiers":[
        {
            "category":"Travel",
            "subcategory":"Hostel",
            "type":"Entertainment"
        }
    ],
    "sg:phone":"+44 1224 210547",
    "sg:postcode":"AB11 5AZ",
    "sg:province":"Aberdeen City",
    "wof:name":"Wernham House",
    "wof:placetype":"venue"
},
  "geometry": {"coordinates":[-2.0924749374,57.1472702026],"type":"Point"}
}