{
  "type": "Feature",
  "properties": {
    "iso:country":"GB",
    "sg:address":"Wilmot Road",
    "sg:city":"Swadlincote",
    "sg:classifiers":[
        {
            "category":"Professional",
            "subcategory":"Testing Lab",
            "type":"Services"
        }
    ],
    "sg:phone":"+44 1283 212993",
    "sg:postcode":"DE11 9BJ",
    "sg:province":"Derbyshire",
    "sg:tags":[
        "mot"
    ],
    "wof:name":"Hedgefield Motors",
    "wof:placetype":"venue"
},
  "geometry": {"coordinates":[-1.562974,52.771095],"type":"Point"}
}