{
  "type": "Feature",
  "properties": {
    "addr:full":"6 Edgcumbe Ave Newquay Cornwall TR7 2NH",
    "addr:housenumber":"6",
    "addr:postcode":"tr7 2nh",
    "addr:street":"Edgcumbe Ave",
    "iso:country":"GB",
    "sg:address":"6 Edgcumbe Ave",
    "sg:city":"Newquay",
    "sg:classifiers":[
        {
            "category":"Travel",
            "subcategory":"Hotels & Motels",
            "type":"Entertainment"
        }
    ],
    "sg:postcode":"TR7 2NH",
    "sg:province":"Cornwall",
    "sg:tags":[
        "house",
        "guest"
    ],
    "wof:name":"St Phillack",
    "wof:placetype":"venue"
},
  "geometry": {"coordinates":[-5.074491,50.416115],"type":"Point"}
}