{
  "type": "Feature",
  "properties": {
    "iso:country":"GB",
    "sg:address":"Unit 6, Lyndean Ind Est, Felixstowe Rd",
    "sg:city":"Abbey Wood",
    "sg:classifiers":[
        {
            "category":"Professional",
            "subcategory":"Accounting & Tax Preparation",
            "type":"Services"
        }
    ],
    "sg:phone":"+44 20 8312 0043",
    "sg:postcode":"SE2 9SG",
    "sg:province":"Greater London",
    "sg:tags":[
        "accountant"
    ],
    "wof:name":"Ladywell Business Services",
    "wof:placetype":"venue"
},
  "geometry": {"coordinates":[0.12124,51.492447],"type":"Point"}
}