{
  "type": "Feature",
  "properties": {
    "addr:full":"16 The Glen, Shepherdswell Dover Kent CT15 7PF",
    "addr:housenumber":"16",
    "addr:postcode":"ct15 7pf",
    "addr:street":"The Glen Shepherdswell Dover",
    "iso:country":"GB",
    "sg:address":"16 The Glen, Shepherdswell",
    "sg:city":"Dover",
    "sg:classifiers":[
        {
            "category":"Professional",
            "subcategory":"Management & Consulting",
            "type":"Services"
        }
    ],
    "sg:phone":"+44 1304 831855",
    "sg:postcode":"CT15 7PF",
    "sg:province":"Kent",
    "sg:tags":[
        "consultant",
        "business"
    ],
    "wof:name":"Peter Collins & Associates Ltd",
    "wof:placetype":"venue"
},
  "geometry": {"coordinates":[1.2360700369,51.116027832],"type":"Point"}
}