{
  "type": "Feature",
  "properties": {
    "iso:country":"GB",
    "sg:address":"23 Welholme Road",
    "sg:city":"Grimsby",
    "sg:classifiers":[
        {
            "category":"Professional",
            "subcategory":"Art Services",
            "type":"Services"
        }
    ],
    "sg:phone":"+44 1472 351000",
    "sg:postcode":"DN32 0DR",
    "sg:province":"Lincolnshire",
    "sg:tags":[
        "photographer"
    ],
    "wof:name":"Photocall",
    "wof:placetype":"venue"
},
  "geometry": {"coordinates":[-0.0857810006,53.5579948425],"type":"Point"}
}