{
  "type": "Feature",
  "properties": {
    "iso:country":"GB",
    "sg:address":"73 The Quantocks, Flitwick",
    "sg:city":"Bedford",
    "sg:classifiers":[
        {
            "category":"Building & Trades",
            "subcategory":"Construction",
            "type":"Services"
        }
    ],
    "sg:postcode":"MK45 1TG",
    "sg:province":"Bedfordshire",
    "sg:tags":[
        "joiner",
        "carpenter"
    ],
    "wof:name":"Brian C Shingfield",
    "wof:placetype":"venue"
},
  "geometry": {"coordinates":[-0.4965690076,52.0037384033],"type":"Point"}
}