{
  "type": "Feature",
  "properties": {
    "iso:country":"GB",
    "sg:address":"St. Georges House, 7 St. Georges Square",
    "sg:city":"Huddersfield",
    "sg:classifiers":[
        {
            "category":"Real Estate",
            "subcategory":"Surveying",
            "type":"Services"
        }
    ],
    "sg:phone":"+44 1484 435514",
    "sg:postcode":"HD1 1LA",
    "sg:province":"West Yorkshire",
    "sg:tags":[
        "surveyor",
        "quantity"
    ],
    "wof:name":"Building Cost Services",
    "wof:placetype":"venue"
},
  "geometry": {"coordinates":[-1.7834830284,53.6480789185],"type":"Point"}
}