{
  "type": "Feature",
  "properties": {
    "iso:country":"GB",
    "sg:address":"123 Main Street",
    "sg:city":"Lochgelly",
    "sg:classifiers":[
        {
            "category":"Health Services",
            "subcategory":"Optometrist",
            "type":"Services"
        }
    ],
    "sg:phone":"+44 1383 510507",
    "sg:postcode":"KY5 9AF",
    "sg:province":"Fife",
    "sg:tags":[
        "optician"
    ],
    "wof:name":"M Dorris",
    "wof:placetype":"venue"
},
  "geometry": {"coordinates":[-3.310215,56.12619],"type":"Point"}
}