{
  "type": "Feature",
  "properties": {
    "addr:full":"Whittington Hall Worcester Worcestershire WR5 2ZX",
    "addr:postcode":"wr5 2zx",
    "iso:country":"GB",
    "sg:address":"Whittington Hall",
    "sg:city":"Worcester",
    "sg:classifiers":[
        {
            "category":"Real Estate",
            "subcategory":"Real Estate Agent",
            "type":"Services"
        }
    ],
    "sg:phone":"+44 1905 360800",
    "sg:postcode":"WR5 2ZX",
    "sg:province":"Worcestershire",
    "wof:name":"C I M Management Ltd.",
    "wof:placetype":"venue"
},
  "geometry": {"coordinates":[-2.1856970787,52.1720733643],"type":"Point"}
}