{
  "type": "Feature",
  "properties": {
    "iso:country":"GB",
    "sg:address":"Joiners Shop, Back St",
    "sg:city":"Driffield",
    "sg:classifiers":[
        {
            "category":"Building & Trades",
            "subcategory":"Construction",
            "type":"Services"
        }
    ],
    "sg:phone":"+44 1377 267348",
    "sg:postcode":"YO25 0TG",
    "sg:province":"East Riding of Yorkshire",
    "sg:tags":[
        "joiner",
        "carpenter"
    ],
    "wof:name":"Ken Harland & Son",
    "wof:placetype":"venue"
},
  "geometry": {"coordinates":[-0.4363,54.008968],"type":"Point"}
}