{
  "type": "Feature",
  "properties": {
    "addr:full":"135 Palatine Road West, Didsbury Manchester Greater Manchester M20 3YA",
    "addr:housenumber":"135",
    "addr:postcode":"m20 3ya",
    "addr:street":"Palatine Road",
    "iso:country":"GB",
    "sg:address":"135 Palatine Road West, Didsbury",
    "sg:city":"Manchester",
    "sg:classifiers":[
        {
            "category":"Health Services",
            "subcategory":"Doctor",
            "type":"Services"
        }
    ],
    "sg:phone":"+44 161 445 0102",
    "sg:postcode":"M20 3YA",
    "sg:province":"Greater Manchester",
    "sg:tags":[
        "practitioners"
    ],
    "wof:name":"D E Markham",
    "wof:placetype":"venue"
},
  "geometry": {"coordinates":[-2.235882,53.425793],"type":"Point"}
}