{
  "type": "Feature",
  "properties": {
    "iso:country":"GB",
    "sg:address":"10 Moor La, Cleadon",
    "sg:city":"Sunderland",
    "sg:classifiers":[
        {
            "category":"Building & Trades",
            "subcategory":"Plumbing",
            "type":"Services"
        }
    ],
    "sg:postcode":"SR6 7TT",
    "sg:province":"Tyne and Wear",
    "sg:tags":[
        "central",
        "heating"
    ],
    "wof:name":"Sayers,Ken,",
    "wof:placetype":"venue"
},
  "geometry": {"coordinates":[-1.4023959637,54.9456138611],"type":"Point"}
}