{
  "type": "Feature",
  "properties": {
    "addr:full":"Lower Holt St Colchester Essex CO6 2PH",
    "addr:postcode":"co6 2ph",
    "addr:street":"Lower Holt St",
    "iso:country":"GB",
    "sg:address":"Lower Holt St",
    "sg:city":"Colchester",
    "sg:classifiers":[
        {
            "category":"Bars & Pubs",
            "type":"Food & Drink"
        }
    ],
    "sg:phone":"+44 1787 223930",
    "sg:postcode":"CO6 2PH",
    "sg:province":"Essex",
    "sg:tags":[
        "pubs",
        "inn"
    ],
    "wof:name":"Earl Trout The",
    "wof:placetype":"venue"
},
  "geometry": {"coordinates":[0.711944,51.926613],"type":"Point"}
}