{
  "type": "Feature",
  "properties": {
    "iso:country":"GB",
    "sg:address":"38 Marine Pl",
    "sg:city":"Buckie",
    "sg:classifiers":[
        {
            "category":"Building & Trades",
            "subcategory":"Landscaping Services",
            "type":"Services"
        },
        {
            "category":"Shopping",
            "subcategory":"Bicycles & Sporting Goods",
            "type":"Retail Goods"
        }
    ],
    "sg:phone":"+44 1542 831056",
    "sg:postcode":"AB56 1UY",
    "sg:province":"Moray",
    "sg:tags":[
        "equipment",
        "consultant",
        "horticultural",
        "marine",
        "supply"
    ],
    "wof:name":"Litton Marine Systems Ltd",
    "wof:placetype":"venue"
},
  "geometry": {"coordinates":[-2.962239027,57.6784286499],"type":"Point"}
}