{
  "type": "Feature",
  "properties": {
    "addr:full":"Valletta King's Lynn Norfolk PE32 1JX",
    "addr:postcode":"pe32 1jx",
    "addr:street":"Lynn",
    "iso:country":"GB",
    "sg:address":"Valletta",
    "sg:city":"King's Lynn",
    "sg:classifiers":[
        {
            "category":"Home & Garden",
            "subcategory":"Garden Supply",
            "type":"Retail Goods"
        }
    ],
    "sg:phone":"+44 1553 841123",
    "sg:postcode":"PE32 1JX",
    "sg:province":"Norfolk",
    "sg:tags":[
        "nursery",
        "centre"
    ],
    "wof:name":"S & S Nurseries",
    "wof:placetype":"venue"
},
  "geometry": {"coordinates":[0.4183270037,52.7575035095],"type":"Point"}
}