{
  "type": "Feature",
  "properties": {
    "iso:country":"GB",
    "sg:address":"Shore Street",
    "sg:city":"Fraserburgh",
    "sg:classifiers":[
        {
            "category":"Harbor",
            "type":"Transportation"
        },
        {
            "category":"Organizations",
            "subcategory":"Professional Association",
            "type":"Services"
        }
    ],
    "sg:phone":"+44 1346 515858",
    "sg:postcode":"AB43 9BR",
    "sg:province":"Aberdeenshire",
    "sg:tags":[
        "dock",
        "operation",
        "port",
        "harbour",
        "ports"
    ],
    "wof:name":"Fraserburgh Harbour Commissioners",
    "wof:placetype":"venue"
},
  "geometry": {"coordinates":[-2.003404,57.695595],"type":"Point"}
}