{
  "type": "Feature",
  "properties": {
    "addr:full":"150 Borough Rd Wallasey Merseyside L44 6NN",
    "addr:housenumber":"150",
    "addr:postcode":"l44 6nn",
    "addr:street":"Borough Rd",
    "iso:country":"GB",
    "sg:address":"150 Borough Rd",
    "sg:city":"Wallasey",
    "sg:classifiers":[
        {
            "category":"Home & Garden",
            "subcategory":"Home Furnishings",
            "type":"Retail Goods"
        }
    ],
    "sg:phone":"+44 151 691 1047",
    "sg:postcode":"L44 6NN",
    "sg:province":"Merseyside",
    "sg:tags":[
        "beds",
        "bedding",
        "blanket"
    ],
    "wof:name":"Bedtrade",
    "wof:placetype":"venue"
},
  "geometry": {"coordinates":[-3.02394,53.41206],"type":"Point"}
}