{
  "type": "Feature",
  "properties": {
    "addr:full":"9-11 Lower Bristol Road Bath Somerset BA2 1EP",
    "addr:housenumber":"9-11",
    "addr:postcode":"ba2 1ep",
    "addr:street":"Lower Bristol Road",
    "iso:country":"GB",
    "sg:address":"9-11 Lower Bristol Road",
    "sg:city":"Bath",
    "sg:classifiers":[
        {
            "category":"Wholesale",
            "subcategory":"Scrap",
            "type":"Manufacturing & Wholesale Goods"
        }
    ],
    "sg:phone":"+44 1225 466650",
    "sg:postcode":"BA2 1EP",
    "sg:province":"Somerset",
    "sg:tags":[
        "breaker",
        "dismantlers"
    ],
    "wof:name":"Impact Car Breakers",
    "wof:placetype":"venue"
},
  "geometry": {"coordinates":[-2.388538,51.380577],"type":"Point"}
}