{
  "type": "Feature",
  "properties": {
    "iso:country":"GB",
    "sg:address":"3 Aymer Rd",
    "sg:city":"Hove",
    "sg:classifiers":[
        {
            "category":"Social Services",
            "subcategory":"Retirement Home",
            "type":"Services"
        },
        {
            "category":"Government",
            "subcategory":"Office",
            "type":"Public Place"
        }
    ],
    "sg:postcode":"BN3 4GB",
    "sg:province":"East Sussex",
    "sg:tags":[
        "residential",
        "central",
        "care"
    ],
    "wof:name":"Ramdath,J,",
    "wof:placetype":"venue"
},
  "geometry": {"coordinates":[-0.180327,50.82869],"type":"Point"}
}