{
  "type": "Feature",
  "properties": {
    "addr:full":"23 Mapleton Rd Coventry Warwickshire CV6 2BA",
    "addr:housenumber":"23",
    "addr:postcode":"cv6 2ba",
    "addr:street":"Mapleton Rd",
    "iso:country":"GB",
    "sg:address":"23 Mapleton Rd",
    "sg:city":"Coventry",
    "sg:classifiers":[
        {
            "category":"Building & Trades",
            "subcategory":"Construction",
            "type":"Services"
        }
    ],
    "sg:phone":"+44 24 7633 5075",
    "sg:postcode":"CV6 2BA",
    "sg:province":"Warwickshire",
    "sg:tags":[
        "repair",
        "window",
        "replacement"
    ],
    "wof:name":"Crescent Windows",
    "wof:placetype":"venue"
},
  "geometry": {"coordinates":[-1.53669,52.432014],"type":"Point"}
}