{
  "type": "Feature",
  "properties": {
    "addr:full":"26 Lumley Avenue Skegness Lincolnshire PE25 2AT",
    "addr:housenumber":"26",
    "addr:postcode":"pe25 2at",
    "addr:street":"Lumley Avenue",
    "iso:country":"GB",
    "sg:address":"26 Lumley Avenue",
    "sg:city":"Skegness",
    "sg:classifiers":[
        {
            "category":"Travel",
            "subcategory":"Hotels & Motels",
            "type":"Entertainment"
        }
    ],
    "sg:phone":"+44 1754 763924",
    "sg:postcode":"PE25 2AT",
    "sg:province":"Lincolnshire",
    "sg:tags":[
        "house",
        "guest"
    ],
    "wof:name":"M & M CLARKE",
    "wof:placetype":"venue"
},
  "geometry": {"coordinates":[0.340628,53.14537],"type":"Point"}
}