{
  "type": "Feature",
  "properties": {
    "iso:country":"GB",
    "sg:address":"Unit 5, Tal Y Sarn",
    "sg:city":"Llandudno Junction",
    "sg:classifiers":[
        {
            "category":"Utilities",
            "subcategory":"Mobile Phone",
            "type":"Services"
        },
        {
            "category":"Retail",
            "subcategory":"Auto Repair",
            "type":"Services"
        }
    ],
    "sg:phone":"+44 1492 583444",
    "sg:postcode":"LL31 9PW",
    "sg:province":"Conwy",
    "sg:tags":[
        "battery",
        "supplier",
        "electrician"
    ],
    "wof:name":"S & R Auto Electrics",
    "wof:placetype":"venue"
},
  "geometry": {"coordinates":[-3.8018,53.281384],"type":"Point"}
}