{
  "type": "Feature",
  "properties": {
    "addr:full":"Unit 33, Bilton Industrial Estate, Humber Avenue Coventry Warwickshire CV3 1JL",
    "addr:housenumber":"unit 33",
    "addr:postcode":"cv3 1jl",
    "addr:street":"Industrial Estate Humber Avenue",
    "iso:country":"GB",
    "sg:address":"Unit 33, Bilton Industrial Estate, Humber Avenue",
    "sg:city":"Coventry",
    "sg:classifiers":[
        {
            "category":"Professional",
            "subcategory":"Engineering",
            "type":"Services"
        }
    ],
    "sg:phone":"+44 24 7663 5818",
    "sg:postcode":"CV3 1JL",
    "sg:province":"Warwickshire",
    "sg:tags":[
        "design",
        "engineer"
    ],
    "wof:name":"Richmond Design & Marketing Ltd",
    "wof:placetype":"venue"
},
  "geometry": {"coordinates":[-1.488379,52.40329],"type":"Point"}
}