{
  "type": "Feature",
  "properties": {
    "addr:full":"1 Granton Square Edinburgh City of Edinburgh EH5 1HE",
    "addr:housenumber":"1",
    "addr:postcode":"eh5 1he",
    "addr:street":"Granton Square",
    "iso:country":"GB",
    "sg:address":"1 Granton Square",
    "sg:city":"Edinburgh",
    "sg:classifiers":[
        {
            "category":"Arena",
            "subcategory":"Sports Club",
            "type":"Entertainment"
        }
    ],
    "sg:phone":"+44 131 552 5939",
    "sg:postcode":"EH5 1HE",
    "sg:province":"City of Edinburgh",
    "sg:website":"http://www.fcyc.org.uk",
    "wof:name":"Forth Corinthian Yacht Club",
    "wof:placetype":"venue"
},
  "geometry": {"coordinates":[-3.2247450352,55.9810066223],"type":"Point"}
}