{
  "type": "Feature",
  "properties": {
    "addr:full":"11 Holdenhurst Avenue Bournemouth Dorset BH7 6QZ",
    "addr:housenumber":"11",
    "addr:postcode":"bh7 6qz",
    "addr:street":"Holdenhurst Avenue",
    "iso:country":"GB",
    "sg:address":"11 Holdenhurst Avenue",
    "sg:city":"Bournemouth",
    "sg:classifiers":[
        {
            "category":"Personal",
            "type":"Services"
        },
        {
            "category":"Food & Beverages",
            "subcategory":"Supermarket",
            "type":"Retail Goods"
        }
    ],
    "sg:phone":"+44 1202 423866",
    "sg:postcode":"BH7 6QZ",
    "sg:province":"Dorset",
    "sg:tags":[
        "wedding"
    ],
    "wof:name":"Superwed Cars",
    "wof:placetype":"venue"
},
  "geometry": {"coordinates":[-1.815946,50.735783],"type":"Point"}
}