{
  "type": "Feature",
  "properties": {
    "addr:full":"10 Weymouth St Warminster Somerset BA12 9NR",
    "addr:housenumber":"10",
    "addr:postcode":"ba12 9nr",
    "addr:street":"Weymouth St",
    "iso:country":"GB",
    "sg:address":"10 Weymouth St",
    "sg:city":"Warminster",
    "sg:classifiers":[
        {
            "category":"Organizations",
            "subcategory":"Non-profit Organization",
            "type":"Services"
        }
    ],
    "sg:phone":"+44 1985 218520",
    "sg:postcode":"BA12 9NR",
    "sg:province":"Somerset",
    "sg:tags":[
        "organisation",
        "voluntary",
        "charity"
    ],
    "wof:name":"Barnardo's Shops",
    "wof:placetype":"venue"
},
  "geometry": {"coordinates":[-2.1816520691,51.2043571472],"type":"Point"}
}