{
  "type": "Feature",
  "properties": {
    "addr:full":"229 High Road, Willesden London Greater London NW10 2RY",
    "addr:housenumber":"229",
    "addr:postcode":"nw10 2ry",
    "addr:street":"High Road",
    "iso:country":"GB",
    "sg:address":"229 High Road, Willesden",
    "sg:city":"London",
    "sg:classifiers":[
        {
            "category":"Shopping",
            "subcategory":"Clothing, Apparel, & Fashions",
            "type":"Retail Goods"
        }
    ],
    "sg:phone":"+44 20 8459 0970",
    "sg:postcode":"NW10 2RY",
    "sg:province":"Greater London",
    "sg:tags":[
        "shop"
    ],
    "wof:name":"Modi & Co",
    "wof:placetype":"venue"
},
  "geometry": {"coordinates":[-0.236636,51.547981],"type":"Point"}
}