{
  "type": "Feature",
  "properties": {
    "addr:full":"73 Forest Road Loughton Essex IG10 1EE",
    "addr:housenumber":"73",
    "addr:postcode":"ig10 1ee",
    "addr:street":"Forest Road",
    "iso:country":"GB",
    "sg:address":"73 Forest Road",
    "sg:city":"Loughton",
    "sg:classifiers":[
        {
            "category":"Professional",
            "subcategory":"Art Services",
            "type":"Services"
        }
    ],
    "sg:phone":"+44 20 8502 4634",
    "sg:postcode":"IG10 1EE",
    "sg:province":"Essex",
    "sg:tags":[
        "picture",
        "framing"
    ],
    "wof:name":"Frames",
    "wof:placetype":"venue"
},
  "geometry": {"coordinates":[0.052211,51.64893],"type":"Point"}
}