{
  "type": "Feature",
  "properties": {
    "iso:country":"GB",
    "sg:address":"Flat 2 Paddoxs, 25 Dunsmore Avenue",
    "sg:city":"Rugby",
    "sg:classifiers":[
        {
            "category":"Health Services",
            "subcategory":"Health Practitioner",
            "type":"Services"
        }
    ],
    "sg:phone":"+44 1788 560793",
    "sg:postcode":"CV22 5HD",
    "sg:province":"Warwickshire",
    "sg:tags":[
        "hypnotherapists"
    ],
    "wof:name":"Pauline Wren Associates",
    "wof:placetype":"venue"
},
  "geometry": {"coordinates":[-1.260709,52.370338],"type":"Point"}
}