{
  "type": "Feature",
  "properties": {
    "iso:country":"GB",
    "sg:address":"Park Avenue, Burton Joyce",
    "sg:city":"Nottingham",
    "sg:classifiers":[
        {
            "category":"Health Services",
            "subcategory":"Nursing And Care Facility",
            "type":"Services"
        }
    ],
    "sg:phone":"+44 115 931 2279",
    "sg:postcode":"NG14 5AF",
    "sg:province":"Nottinghamshire",
    "sg:tags":[
        "home"
    ],
    "wof:name":"Braybrook Home For The Elderly",
    "wof:placetype":"venue"
},
  "geometry": {"coordinates":[-1.036324,52.987267],"type":"Point"}
}