{
  "type": "Feature",
  "properties": {
    "addr:full":"Unit 3 Newport Retail Park, Spytty Road Newport Newport NP19 0RH",
    "addr:housenumber":"unit 3",
    "addr:postcode":"np19 0rh",
    "addr:street":"Newport Retail Park Spytty Road",
    "iso:country":"GB",
    "sg:address":"Unit 3 Newport Retail Park, Spytty Road",
    "sg:city":"Newport",
    "sg:classifiers":[
        {
            "category":"Shopping",
            "subcategory":"Shoes",
            "type":"Retail Goods"
        }
    ],
    "sg:phone":"+44 1633 279636",
    "sg:postcode":"NP19 0RH",
    "sg:province":"Newport",
    "sg:tags":[
        "shop"
    ],
    "wof:name":"Shoe City",
    "wof:placetype":"venue"
},
  "geometry": {"coordinates":[-2.9882569313,51.5910491943],"type":"Point"}
}