{
  "type": "Feature",
  "properties": {
    "addr:full":"43 Milltown St Manchester Greater Manchester M26 1WD",
    "addr:housenumber":"43",
    "addr:postcode":"m26 1wd",
    "addr:street":"Milltown St",
    "iso:country":"GB",
    "sg:address":"43 Milltown St",
    "sg:city":"Manchester",
    "sg:classifiers":[
        {
            "category":"Manufacturing",
            "subcategory":"Electronics",
            "type":"Manufacturing & Wholesale Goods"
        }
    ],
    "sg:phone":"+44 161 280 2019",
    "sg:postcode":"M26 1WD",
    "sg:province":"Greater Manchester",
    "sg:tags":[
        "control",
        "component",
        "-",
        "electronic"
    ],
    "wof:name":"Electronica",
    "wof:placetype":"venue"
},
  "geometry": {"coordinates":[-2.3223888874,53.5588302612],"type":"Point"}
}