{
  "type": "Feature",
  "properties": {
    "addr:full":"29 Scots Hill, Croxley Grn Rickmansworth Hertfordshire WD3 3AE",
    "addr:housenumber":"29",
    "addr:postcode":"wd3 3ae",
    "addr:street":"Scots Hill Croxley Grn",
    "iso:country":"GB",
    "sg:address":"29 Scots Hill, Croxley Grn",
    "sg:city":"Rickmansworth",
    "sg:classifiers":[
        {
            "category":"Autos & Motor Vehicles",
            "subcategory":"Auto Supplies",
            "type":"Retail Goods"
        },
        {
            "category":"Retail",
            "subcategory":"Auto Repair",
            "type":"Services"
        }
    ],
    "sg:postcode":"WD3 3AE",
    "sg:province":"Hertfordshire",
    "sg:tags":[
        "modification",
        "garage",
        "windscreen"
    ],
    "wof:name":"Screencraft Windscreens",
    "wof:placetype":"venue"
},
  "geometry": {"coordinates":[-0.456192,51.645622],"type":"Point"}
}