{
  "type": "Feature",
  "properties": {
    "iso:country":"GB",
    "sg:address":"15-17 Coney Street",
    "sg:city":"York",
    "sg:classifiers":[
        {
            "category":"Shopping",
            "subcategory":"Music",
            "type":"Retail Goods"
        }
    ],
    "sg:phone":"+44 1904 611101",
    "sg:postcode":"YO1 1QL",
    "sg:province":"North Yorkshire",
    "sg:tags":[
        "record",
        "tape",
        "cd"
    ],
    "wof:name":"Virgin Megastore",
    "wof:placetype":"venue"
},
  "geometry": {"coordinates":[-1.0841189623,53.9593086243],"type":"Point"}
}