{
  "type": "Feature",
  "properties": {
    "iso:country":"GB",
    "sg:address":"Unit T2 Freshney Place",
    "sg:city":"Grimsby",
    "sg:classifiers":[
        {
            "category":"Shopping",
            "subcategory":"Optician",
            "type":"Retail Goods"
        }
    ],
    "sg:phone":"+44 1472 344244",
    "sg:postcode":"DN31 1QQ",
    "sg:province":"Lincolnshire",
    "wof:name":"Vision Express (Uk)",
    "wof:placetype":"venue"
},
  "geometry": {"coordinates":[-0.091644,53.569695],"type":"Point"}
}