{
  "type": "Feature",
  "properties": {
    "iso:country":"GB",
    "sg:address":"70 Morning Lane",
    "sg:city":"London",
    "sg:classifiers":[
        {
            "category":"Food & Beverages",
            "subcategory":"Liquor & Beverages",
            "type":"Retail Goods"
        }
    ],
    "sg:phone":"+44 20 8986 0623",
    "sg:postcode":"E9 6NA",
    "sg:province":"Greater London",
    "sg:tags":[
        "beer",
        "spirit",
        "wines"
    ],
    "wof:name":"Has (Uk) Ltd.",
    "wof:placetype":"venue"
},
  "geometry": {"coordinates":[-0.052068,51.546623],"type":"Point"}
}