{
  "type": "Feature",
  "properties": {
    "addr:full":"105a Clapham High Street London Greater London SW4 7TB",
    "addr:housenumber":"105a",
    "addr:postcode":"sw4 7tb",
    "addr:street":"Clapham High Street",
    "iso:country":"GB",
    "sg:address":"105a Clapham High Street",
    "sg:city":"London",
    "sg:classifiers":[
        {
            "category":"Fast Food",
            "type":"Food & Drink"
        }
    ],
    "sg:phone":"+44 20 7627 1477",
    "sg:postcode":"SW4 7TB",
    "sg:province":"Greater London",
    "sg:tags":[
        "away",
        "take"
    ],
    "wof:name":"The Savoury Sandwich Bar",
    "wof:placetype":"venue"
},
  "geometry": {"coordinates":[-0.1344829947,51.4629058838],"type":"Point"}
}