{
  "type": "Feature",
  "properties": {
    "addr:full":"57a High Street Feltham Greater London TW13 4EZ",
    "addr:housenumber":"57a",
    "addr:postcode":"tw13 4ez",
    "addr:street":"High Street",
    "iso:country":"GB",
    "sg:address":"57a High Street",
    "sg:city":"Feltham",
    "sg:classifiers":[
        {
            "category":"Professional",
            "subcategory":"Accounting & Tax Preparation",
            "type":"Services"
        }
    ],
    "sg:phone":"+44 20 8867 0488",
    "sg:postcode":"TW13 4EZ",
    "sg:province":"Greater London",
    "sg:tags":[
        "consultant"
    ],
    "wof:name":"Taxsolve U K Ltd.",
    "wof:placetype":"venue"
},
  "geometry": {"coordinates":[-0.412136,51.442871],"type":"Point"}
}