{
  "type": "Feature",
  "properties": {
    "iso:country":"GB",
    "sg:address":"C/o Hacker Young 168 Church Road",
    "sg:city":"Hove",
    "sg:classifiers":[
        {
            "category":"Professional",
            "subcategory":"Management & Consulting",
            "type":"Services"
        },
        {
            "category":"Professional",
            "subcategory":"Computer Services",
            "type":"Services"
        }
    ],
    "sg:postcode":"BN3 2DL",
    "sg:province":"East Sussex",
    "sg:tags":[
        "consultant",
        "system",
        "business",
        "software"
    ],
    "wof:name":"Boccon Associates Ltd",
    "wof:placetype":"venue"
},
  "geometry": {"coordinates":[-0.1824489981,50.8389434814],"type":"Point"}
}