{
  "type": "Feature",
  "properties": {
    "iso:country":"GB",
    "sg:address":"113-117 Charing Cross Rd",
    "sg:city":"Holborn",
    "sg:classifiers":[
        {
            "category":"Professional",
            "subcategory":"Printing & Photocopies",
            "type":"Services"
        }
    ],
    "sg:phone":"+44 20 7437 0715",
    "sg:postcode":"WC2H 0DT",
    "sg:province":"Greater London",
    "sg:tags":[
        "typesetter"
    ],
    "wof:name":"R & J Design",
    "wof:placetype":"venue"
},
  "geometry": {"coordinates":[-0.130255,51.516323],"type":"Point"}
}