{
  "type": "Feature",
  "properties": {
    "addr:full":"Central Ho, 3-5 Mill La Blackburn Lancashire BB2 2AU",
    "addr:housenumber":"3-5",
    "addr:postcode":"bb2 2au",
    "addr:street":"Mill La Blackburn",
    "iso:country":"GB",
    "sg:address":"Central Ho, 3-5 Mill La",
    "sg:city":"Blackburn",
    "sg:classifiers":[
        {
            "category":"Professional",
            "subcategory":"Printing & Photocopies",
            "type":"Services"
        }
    ],
    "sg:postcode":"BB2 2AU",
    "sg:province":"Lancashire",
    "sg:tags":[
        "process",
        "screen",
        "printer"
    ],
    "wof:name":"Embroidery & Screenprint Centre Ltd",
    "wof:placetype":"venue"
},
  "geometry": {"coordinates":[-2.4838399887,53.7456703186],"type":"Point"}
}