{
  "type": "Feature",
  "properties": {
    "iso:country":"GB",
    "sg:address":"20 Bridge Grn, Prestbury",
    "sg:city":"Macclesfield",
    "sg:classifiers":[
        {
            "category":"Health Services",
            "subcategory":"Health Practitioner",
            "type":"Services"
        }
    ],
    "sg:postcode":"SK10 4HR",
    "sg:province":"Cheshire",
    "sg:tags":[
        "physiotherapist"
    ],
    "wof:name":"Carol D Taylor",
    "wof:placetype":"venue"
},
  "geometry": {"coordinates":[-2.146533,53.289398],"type":"Point"}
}