{
  "type": "Feature",
  "properties": {
    "addr:full":"24-32 General Market, Green Street Neath Neath Port Talbot SA11 1DP",
    "addr:housenumber":"24-32",
    "addr:postcode":"sa11 1dp",
    "addr:street":"General Market Green Street",
    "iso:country":"GB",
    "sg:address":"24-32 General Market, Green Street",
    "sg:city":"Neath",
    "sg:classifiers":[
        {
            "category":"Shopping",
            "subcategory":"Gifts & Souvenirs",
            "type":"Retail Goods"
        }
    ],
    "sg:phone":"+44 1639 642313",
    "sg:postcode":"SA11 1DP",
    "sg:province":"Neath Port Talbot",
    "sg:tags":[
        "shop"
    ],
    "wof:name":"G V Rees & Son",
    "wof:placetype":"venue"
},
  "geometry": {"coordinates":[-3.799813,51.662712],"type":"Point"}
}