{
  "type": "Feature",
  "properties": {
    "iso:country":"GB",
    "sg:address":"Broadclose Farm",
    "sg:city":"Bude",
    "sg:classifiers":[
        {
            "category":"Farming",
            "subcategory":"Farm",
            "type":"Manufacturing & Wholesale Goods"
        }
    ],
    "sg:phone":"+44 1288 352315",
    "sg:postcode":"EX23 8DR",
    "sg:province":"Cornwall",
    "sg:tags":[
        "mixed",
        "crop"
    ],
    "wof:name":"A B & E M Bartlett",
    "wof:placetype":"venue"
},
  "geometry": {"coordinates":[-4.544478,50.828362],"type":"Point"}
}