{
  "type": "Feature",
  "properties": {
    "iso:country":"GB",
    "sg:address":"59 Main Street, Lowdham",
    "sg:city":"Nottingham",
    "sg:classifiers":[
        {
            "category":"Government",
            "subcategory":"Post Office",
            "type":"Public Place"
        }
    ],
    "sg:phone":"+44 115 966 3601",
    "sg:postcode":"NG14 7BD",
    "sg:province":"Nottinghamshire",
    "wof:name":"Lowdham Post Office",
    "wof:placetype":"venue"
},
  "geometry": {"coordinates":[-0.986981988,52.9892196655],"type":"Point"}
}