{
  "type": "Feature",
  "properties": {
    "iso:country":"GB",
    "sg:address":"12 Melrose Road",
    "sg:city":"Colchester",
    "sg:classifiers":[
        {
            "category":"Farming",
            "subcategory":"Nursery",
            "type":"Manufacturing & Wholesale Goods"
        }
    ],
    "sg:phone":"+44 1206 383898",
    "sg:postcode":"CO5 8AB",
    "sg:province":"Essex",
    "sg:tags":[
        "creche"
    ],
    "wof:name":"Mulberry Bush",
    "wof:placetype":"venue"
},
  "geometry": {"coordinates":[0.913209,51.776989],"type":"Point"}
}