{
  "type": "Feature",
  "properties": {
    "addr:full":"Craigview, Springholm Castle Douglas Dumfries and Galloway DG7 3LP",
    "addr:postcode":"dg7 3lp",
    "iso:country":"GB",
    "sg:address":"Craigview, Springholm",
    "sg:city":"Castle Douglas",
    "sg:classifiers":[
        {
            "category":"Freight",
            "type":"Transportation"
        }
    ],
    "sg:phone":"+44 1556 650342",
    "sg:postcode":"DG7 3LP",
    "sg:province":"Dumfries and Galloway",
    "sg:tags":[
        "haulage",
        "road"
    ],
    "wof:name":"MacTaggart Bros",
    "wof:placetype":"venue"
},
  "geometry": {"coordinates":[-3.8677499294,55.0101509094],"type":"Point"}
}