{
  "type": "Feature",
  "properties": {
    "iso:country":"GB",
    "sg:address":"3 Gulveal Villas, The Lizard",
    "sg:city":"Helston",
    "sg:classifiers":[
        {
            "category":"Professional",
            "subcategory":"Art Services",
            "type":"Services"
        }
    ],
    "sg:phone":"+44 1326 290765",
    "sg:postcode":"TR12 7NW",
    "sg:province":"Cornwall",
    "sg:tags":[
        "photographer"
    ],
    "wof:name":"Lizard Photography",
    "wof:placetype":"venue"
},
  "geometry": {"coordinates":[-5.202917,49.968857],"type":"Point"}
}