{
  "type": "Feature",
  "properties": {
    "addr:full":"Southfield Farm, Dishforth Thirsk North Yorkshire YO7 3DA",
    "addr:postcode":"yo7 3da",
    "iso:country":"GB",
    "sg:address":"Southfield Farm, Dishforth",
    "sg:city":"Thirsk",
    "sg:classifiers":[
        {
            "category":"Farming",
            "subcategory":"Farm",
            "type":"Manufacturing & Wholesale Goods"
        }
    ],
    "sg:phone":"+44 1765 640231",
    "sg:postcode":"YO7 3DA",
    "sg:province":"North Yorkshire",
    "sg:tags":[
        "mixed",
        "crop"
    ],
    "wof:name":"J W  Archer",
    "wof:placetype":"venue"
},
  "geometry": {"coordinates":[-1.419544,54.154331],"type":"Point"}
}