{
  "type": "Feature",
  "properties": {
    "iso:country":"GB",
    "sg:address":"Deans Yard, Orchard Way, Fontwell",
    "sg:city":"Arundel",
    "sg:classifiers":[
        {
            "category":"Building & Trades",
            "subcategory":"Construction",
            "type":"Services"
        }
    ],
    "sg:phone":"+44 1243 814637",
    "sg:postcode":"BN18 0SH",
    "sg:province":"West Sussex",
    "sg:tags":[
        "joiner",
        "carpenter"
    ],
    "wof:name":"Kestrel Joinery",
    "wof:placetype":"venue"
},
  "geometry": {"coordinates":[-0.648239,50.854923],"type":"Point"}
}