{
  "type": "Feature",
  "properties": {
    "iso:country":"GB",
    "sg:address":"25 Cowley Road",
    "sg:city":"Poole",
    "sg:classifiers":[
        {
            "category":"Manufacturing",
            "subcategory":"Tools & Machinery",
            "type":"Manufacturing & Wholesale Goods"
        }
    ],
    "sg:phone":"+44 1202 678108",
    "sg:postcode":"BH17 0UJ",
    "sg:province":"Dorset",
    "sg:tags":[
        "monitoring",
        "temperature",
        "thermometer"
    ],
    "wof:name":"Accurate Controls Ltd.",
    "wof:placetype":"venue"
},
  "geometry": {"coordinates":[-1.97583,50.745152],"type":"Point"}
}