{
  "type": "Feature",
  "properties": {
    "addr:full":"Unit 50 Offerton Industrial Estate Stockport Cheshire SK2 5TJ",
    "addr:housenumber":"unit 50",
    "addr:postcode":"sk2 5tj",
    "addr:street":"Offerton Industrial Estate",
    "iso:country":"GB",
    "sg:address":"Unit 50 Offerton Industrial Estate",
    "sg:city":"Stockport",
    "sg:classifiers":[
        {
            "category":"Manufacturing",
            "subcategory":"Metals",
            "type":"Manufacturing & Wholesale Goods"
        },
        {
            "category":"Wholesale",
            "subcategory":"Metals & Minerals",
            "type":"Manufacturing & Wholesale Goods"
        }
    ],
    "sg:phone":"+44 161 480 5009",
    "sg:postcode":"SK2 5TJ",
    "sg:province":"Cheshire",
    "sg:tags":[
        "fabricator",
        "work",
        "sheet"
    ],
    "wof:name":"Stainfab Sheet Metal Ltd",
    "wof:placetype":"venue"
},
  "geometry": {"coordinates":[-2.1348888874,53.4018211365],"type":"Point"}
}