{
  "type": "Feature",
  "properties": {
    "addr:full":"Moor La, Youlgrave Bakewell Derbyshire DE45 1US",
    "addr:postcode":"de45 1us",
    "addr:street":"Moor",
    "iso:country":"GB",
    "sg:address":"Moor La, Youlgrave",
    "sg:city":"Bakewell",
    "sg:classifiers":[
        {
            "category":"Home & Garden",
            "subcategory":"Home Furnishings",
            "type":"Retail Goods"
        }
    ],
    "sg:postcode":"DE45 1US",
    "sg:province":"Derbyshire",
    "sg:tags":[
        "blind",
        "curtain",
        "fitting"
    ],
    "wof:name":"Q C the Quality Curtain Co",
    "wof:placetype":"venue"
},
  "geometry": {"coordinates":[-1.6751190424,53.2133293152],"type":"Point"}
}