{
  "type": "Feature",
  "properties": {
    "addr:full":"137 Popes La Oldbury West Midlands B69 4ND",
    "addr:housenumber":"137",
    "addr:postcode":"b69 4nd",
    "addr:street":"Popes La Oldbury",
    "iso:country":"GB",
    "sg:address":"137 Popes La",
    "sg:city":"Oldbury",
    "sg:classifiers":[
        {
            "category":"Shopping",
            "subcategory":"Clothing, Apparel, & Fashions",
            "type":"Retail Goods"
        }
    ],
    "sg:phone":"+44 121 552 4441",
    "sg:postcode":"B69 4ND",
    "sg:province":"West Midlands",
    "sg:tags":[
        "cap",
        "hat"
    ],
    "wof:name":"Headmaster & Son Ltd",
    "wof:placetype":"venue"
},
  "geometry": {"coordinates":[-2.006989,52.497971],"type":"Point"}
}