{
  "type": "Feature",
  "properties": {
    "iso:country":"GB",
    "sg:address":"67 Liverpool Road",
    "sg:city":"Chester",
    "sg:classifiers":[
        {
            "category":"Organizations",
            "subcategory":"Non-profit Organization",
            "type":"Services"
        }
    ],
    "sg:phone":"+44 1244 382222",
    "sg:postcode":"CH2 1AP",
    "sg:province":"Cheshire",
    "sg:tags":[
        "organisation",
        "voluntary",
        "charity"
    ],
    "wof:name":"Chester Cheshire & Clwyd Society for the Blind",
    "wof:placetype":"venue"
},
  "geometry": {"coordinates":[-2.894373,53.2033],"type":"Point"}
}