{
  "type": "Feature",
  "properties": {
    "addr:full":"Halifax Road Dewsbury West Yorkshire WF13 2AS",
    "addr:postcode":"wf13 2as",
    "addr:street":"Halifax Road",
    "iso:country":"GB",
    "sg:address":"Halifax Road",
    "sg:city":"Dewsbury",
    "sg:classifiers":[
        {
            "category":"Education",
            "subcategory":"University",
            "type":"Public Place"
        }
    ],
    "sg:phone":"+44 1924 465916",
    "sg:postcode":"WF13 2AS",
    "sg:province":"West Yorkshire",
    "sg:tags":[
        "higher"
    ],
    "wof:name":"Dewsbury College of Further Education Corp",
    "wof:placetype":"venue"
},
  "geometry": {"coordinates":[-1.639894,53.698681],"type":"Point"}
}