{
  "type": "Feature",
  "properties": {
    "addr:full":"Unit 1 Rhodeswell Road London Greater London E14 7TN",
    "addr:housenumber":"unit 1",
    "addr:postcode":"e14 7tn",
    "addr:street":"Rhodeswell Road",
    "iso:country":"GB",
    "sg:address":"Unit 1 Rhodeswell Road",
    "sg:city":"London",
    "sg:classifiers":[
        {
            "category":"Professional",
            "subcategory":"Lawyer & Legal Services",
            "type":"Services"
        }
    ],
    "sg:postcode":"E14 7TN",
    "sg:province":"Greater London",
    "wof:name":"Accident Claim Assistance",
    "wof:placetype":"venue"
},
  "geometry": {"coordinates":[-0.0332739986,51.5145568848],"type":"Point"}
}