{
  "type": "Feature",
  "properties": {
    "addr:full":"34 Eldon Street, Clay Cross Chesterfield Derbyshire S45 9PE",
    "addr:housenumber":"34",
    "addr:postcode":"s45 9pe",
    "addr:street":"Eldon Street",
    "iso:country":"GB",
    "sg:address":"34 Eldon Street, Clay Cross",
    "sg:city":"Chesterfield",
    "sg:classifiers":[
        {
            "category":"Health Services",
            "subcategory":"Dentist",
            "type":"Services"
        }
    ],
    "sg:phone":"+44 1246 250325",
    "sg:postcode":"S45 9PE",
    "sg:province":"Derbyshire",
    "wof:name":"Davey Dental Care",
    "wof:placetype":"venue"
},
  "geometry": {"coordinates":[-1.4138000011,53.1675872803],"type":"Point"}
}