{
  "type": "Feature",
  "properties": {
    "addr:full":"St Nicholas Street Bodmin Cornwall PL31 1AG",
    "addr:postcode":"pl31 1ag",
    "addr:street":"St Nicholas Street",
    "iso:country":"GB",
    "sg:address":"St Nicholas Street",
    "sg:city":"Bodmin",
    "sg:classifiers":[
        {
            "category":"Social Services",
            "subcategory":"Retirement Home",
            "type":"Services"
        }
    ],
    "sg:postcode":"PL31 1AG",
    "sg:province":"Cornwall",
    "sg:tags":[
        "residential",
        "care"
    ],
    "wof:name":"St.Petrocs Residential Home",
    "wof:placetype":"venue"
},
  "geometry": {"coordinates":[-4.7184009552,50.4690551758],"type":"Point"}
}