{
  "type": "Feature",
  "properties": {
    "iso:country":"GB",
    "sg:address":"30 Devereux Drive",
    "sg:city":"Watford",
    "sg:classifiers":[
        {
            "category":"Social Services",
            "subcategory":"Child Care",
            "type":"Services"
        }
    ],
    "sg:postcode":"WD17 3DE",
    "sg:province":"Hertfordshire",
    "sg:tags":[
        "agency",
        "nanny"
    ],
    "wof:name":"Mulberry Nanny Agency",
    "wof:placetype":"venue"
},
  "geometry": {"coordinates":[-0.4171519876,51.6701431274],"type":"Point"}
}