{
  "type": "Feature",
  "properties": {
    "iso:country":"GB",
    "sg:address":"Clubhouse North, Pickenham Road",
    "sg:city":"Swaffham",
    "sg:classifiers":[
        {
            "category":"Arena",
            "subcategory":"Sports Club",
            "type":"Entertainment"
        }
    ],
    "sg:phone":"+44 1760 724829",
    "sg:postcode":"PE37 7QX",
    "sg:province":"Norfolk",
    "wof:name":"Swaffham Rugby Club",
    "wof:placetype":"venue"
},
  "geometry": {"coordinates":[0.6897969842,52.6438446045],"type":"Point"}
}