{
  "type": "Feature",
  "properties": {
    "iso:country":"GB",
    "sg:address":"8-12 Donovan Avenue, Muswell Hill",
    "sg:city":"London",
    "sg:classifiers":[
        {
            "category":"Health Services",
            "subcategory":"Nursing And Care Facility",
            "type":"Services"
        },
        {
            "category":"Social Services",
            "subcategory":"Retirement Home",
            "type":"Services"
        }
    ],
    "sg:phone":"+44 20 8883 4901",
    "sg:postcode":"N10 2JX",
    "sg:province":"Greater London",
    "sg:tags":[
        "residential"
    ],
    "wof:name":"Ernest Dene Residential Care Home",
    "wof:placetype":"venue"
},
  "geometry": {"coordinates":[-0.139411,51.594028],"type":"Point"}
}