{
  "type": "Feature",
  "properties": {
    "addr:full":"151 Blackstock Rd Finsbury Park Greater London N4 2JS",
    "addr:housenumber":"151",
    "addr:postcode":"n4 2js",
    "addr:street":"Blackstock Rd",
    "iso:country":"GB",
    "sg:address":"151 Blackstock Rd",
    "sg:city":"Finsbury Park",
    "sg:classifiers":[
        {
            "category":"Personal",
            "subcategory":"Beauty Salon",
            "type":"Services"
        }
    ],
    "sg:phone":"+44 20 7226 9971",
    "sg:postcode":"N4 2JS",
    "sg:province":"Greater London",
    "sg:tags":[
        "lady",
        "hairdresser"
    ],
    "wof:name":"O'Shea",
    "wof:placetype":"venue"
},
  "geometry": {"coordinates":[-0.0991109982,51.5614280701],"type":"Point"}
}