{
  "type": "Feature",
  "properties": {
    "addr:full":"96 Thorpe Lea Road Egham Surrey TW20 8BN",
    "addr:housenumber":"96",
    "addr:postcode":"tw20 8bn",
    "addr:street":"Thorpe Lea Road",
    "iso:country":"GB",
    "sg:address":"96 Thorpe Lea Road",
    "sg:city":"Egham",
    "sg:classifiers":[
        {
            "category":"Cinema",
            "subcategory":"Movie Rental",
            "type":"Entertainment"
        }
    ],
    "sg:phone":"+44 1784 460167",
    "sg:postcode":"TW20 8BN",
    "sg:province":"Surrey",
    "sg:tags":[
        "video",
        "library"
    ],
    "wof:name":"Derek Phillips Films",
    "wof:placetype":"venue"
},
  "geometry": {"coordinates":[-0.5257570148,51.4275970459],"type":"Point"}
}