{
  "type": "Feature",
  "properties": {
    "addr:full":"Studio 54 Glentham Road, Barnes London Greater London SW13 9JJ",
    "addr:postcode":"sw13 9jj",
    "addr:street":"Glentham Road",
    "iso:country":"GB",
    "sg:address":"Studio 54 Glentham Road, Barnes",
    "sg:city":"London",
    "sg:classifiers":[
        {
            "category":"Education",
            "subcategory":"College",
            "type":"Public Place"
        }
    ],
    "sg:phone":"+44 20 8748 4430",
    "sg:postcode":"SW13 9JJ",
    "sg:province":"Greater London",
    "sg:tags":[
        "technical",
        "agricultural"
    ],
    "wof:name":"The Make-Up Room Ltd.",
    "wof:placetype":"venue"
},
  "geometry": {"coordinates":[-0.235839,51.486668],"type":"Point"}
}