{
  "type": "Feature",
  "properties": {
    "addr:full":"Unit 18 Premier Partnership Estate, Leys Road Brierley Hill West Midlands DY5 3UP",
    "addr:housenumber":"unit 18",
    "addr:postcode":"dy5 3up",
    "addr:street":"Leys Road",
    "iso:country":"GB",
    "sg:address":"Unit 18 Premier Partnership Estate, Leys Road",
    "sg:city":"Brierley Hill",
    "sg:classifiers":[
        {
            "category":"Manufacturing",
            "subcategory":"Metals",
            "type":"Manufacturing & Wholesale Goods"
        }
    ],
    "sg:phone":"+44 1384 265255",
    "sg:postcode":"DY5 3UP",
    "sg:province":"West Midlands",
    "sg:tags":[
        "equipment",
        "work",
        "sheet",
        "fabrication"
    ],
    "wof:name":"Pratt Triumph 94 Ltd",
    "wof:placetype":"venue"
},
  "geometry": {"coordinates":[-2.121301,52.482044],"type":"Point"}
}