{
  "type": "Feature",
  "properties": {
    "iso:country":"GB",
    "sg:address":"Esher Court",
    "sg:city":"Northampton",
    "sg:classifiers":[
        {
            "category":"Education",
            "subcategory":"School",
            "type":"Public Place"
        }
    ],
    "sg:phone":"+44 1604 406746",
    "sg:postcode":"NN3 3RG",
    "sg:province":"Northamptonshire",
    "sg:tags":[
        "local",
        "authority"
    ],
    "wof:name":"Boothville Middle School",
    "wof:placetype":"venue"
},
  "geometry": {"coordinates":[-0.845828,52.265362],"type":"Point"}
}