{
  "type": "Feature",
  "properties": {
    "iso:country":"GB",
    "sg:address":"10 Warwick Way",
    "sg:city":"Exeter",
    "sg:classifiers":[
        {
            "category":"Shopping",
            "subcategory":"News",
            "type":"Retail Goods"
        }
    ],
    "sg:phone":"+44 1392 202283",
    "sg:postcode":"EX4 8EP",
    "sg:province":"Devon",
    "sg:tags":[
        "newsagent"
    ],
    "wof:name":"Warwick News",
    "wof:placetype":"venue"
},
  "geometry": {"coordinates":[-3.4826250076,50.7344360352],"type":"Point"}
}