{
  "type": "Feature",
  "properties": {
    "addr:full":"178 Archway Road London Greater London N6 5BB",
    "addr:housenumber":"178",
    "addr:postcode":"n6 5bb",
    "addr:street":"Archway Road",
    "iso:country":"GB",
    "sg:address":"178 Archway Road",
    "sg:city":"London",
    "sg:classifiers":[
        {
            "category":"Personal",
            "subcategory":"Beauty Salon",
            "type":"Services"
        },
        {
            "category":"Personal",
            "subcategory":"Barber",
            "type":"Services"
        }
    ],
    "sg:phone":"+44 20 8342 9493",
    "sg:postcode":"N6 5BB",
    "sg:province":"Greater London",
    "sg:tags":[
        "unisex",
        "hairdresser"
    ],
    "wof:name":"The Cutting Edge",
    "wof:placetype":"venue"
},
  "geometry": {"coordinates":[-0.1401270032,51.5727272034],"type":"Point"}
}