{
  "type": "Feature",
  "properties": {
    "addr:full":"99 High Street Godalming Surrey GU7 1AQ",
    "addr:housenumber":"99",
    "addr:postcode":"gu7 1aq",
    "addr:street":"High Street",
    "iso:country":"GB",
    "sg:address":"99 High Street",
    "sg:city":"Godalming",
    "sg:classifiers":[
        {
            "category":"Shopping",
            "subcategory":"Antiques",
            "type":"Retail Goods"
        }
    ],
    "sg:phone":"+44 1483 415889",
    "sg:postcode":"GU7 1AQ",
    "sg:province":"Surrey",
    "wof:name":"The Olde Curiosity Shoppe",
    "wof:placetype":"venue"
},
  "geometry": {"coordinates":[-0.6152799726,51.1852874756],"type":"Point"}
}