{
  "type": "Feature",
  "properties": {
    "iso:country":"GB",
    "sg:address":"50 Holme St",
    "sg:city":"Bradford",
    "sg:classifiers":[
        {
            "category":"Professional",
            "type":"Services"
        }
    ],
    "sg:phone":"+44 1274 393399",
    "sg:postcode":"BD5 0LE",
    "sg:province":"West Yorkshire",
    "sg:tags":[
        "caravan",
        "towing",
        "transport"
    ],
    "wof:name":"Premier Prestige Car & Van Rental",
    "wof:placetype":"venue"
},
  "geometry": {"coordinates":[-1.764093,53.781525],"type":"Point"}
}