{
  "type": "Feature",
  "properties": {
    "iso:country":"GB",
    "sg:address":"9 The Combe",
    "sg:city":"Eastbourne",
    "sg:classifiers":[
        {
            "category":"Building & Trades",
            "subcategory":"Construction",
            "type":"Services"
        }
    ],
    "sg:postcode":"BN20 9DB",
    "sg:province":"East Sussex",
    "sg:tags":[
        "builder"
    ],
    "wof:name":"Brian A Jones",
    "wof:placetype":"venue"
},
  "geometry": {"coordinates":[0.2472459972,50.79088974],"type":"Point"}
}