{
  "type": "Feature",
  "properties": {
    "iso:country":"GB",
    "sg:address":"97 Ladyshot",
    "sg:city":"Harlow",
    "sg:classifiers":[
        {
            "category":"Health Services",
            "subcategory":"Health Practitioner",
            "type":"Services"
        },
        {
            "category":"Government",
            "subcategory":"Office",
            "type":"Public Place"
        }
    ],
    "sg:postcode":"CM20 3EW",
    "sg:province":"Essex",
    "sg:tags":[
        "psychotherapist",
        "education",
        "agency",
        "authority"
    ],
    "wof:name":"Lynne Marsha Lomond",
    "wof:placetype":"venue"
},
  "geometry": {"coordinates":[0.121368,51.773319],"type":"Point"}
}