{
  "type": "Feature",
  "properties": {
    "addr:full":"Custom House, 80c Kenn Rd Clevedon Somerset BS21 6EX",
    "addr:housenumber":"80c",
    "addr:postcode":"bs21 6ex",
    "addr:street":"Kenn Rd",
    "iso:country":"GB",
    "sg:address":"Custom House, 80c Kenn Rd",
    "sg:city":"Clevedon",
    "sg:classifiers":[
        {
            "category":"Professional",
            "subcategory":"Management & Consulting",
            "type":"Services"
        }
    ],
    "sg:phone":"+44 1275 871033",
    "sg:postcode":"BS21 6EX",
    "sg:province":"Somerset",
    "sg:tags":[
        "marketing",
        "consultant"
    ],
    "wof:name":"Essential Marketing",
    "wof:placetype":"venue"
},
  "geometry": {"coordinates":[-2.8513169289,51.4331092834],"type":"Point"}
}