{
  "type": "Feature",
  "properties": {
    "addr:full":"42 Naisholt Road Shepton Mallet Somerset BA4 5GD",
    "addr:housenumber":"42",
    "addr:postcode":"ba4 5gd",
    "addr:street":"Naisholt Road",
    "iso:country":"GB",
    "sg:address":"42 Naisholt Road",
    "sg:city":"Shepton Mallet",
    "sg:classifiers":[
        {
            "category":"Education",
            "subcategory":"Special Training",
            "type":"Public Place"
        }
    ],
    "sg:postcode":"BA4 5GD",
    "sg:province":"Somerset",
    "sg:tags":[
        "martial art",
        "instruction"
    ],
    "wof:name":"South West Schools of Tae Kwon Do",
    "wof:placetype":"venue"
},
  "geometry": {"coordinates":[-2.558382,51.192116],"type":"Point"}
}