{
  "type": "Feature",
  "properties": {
    "addr:full":"Unit 1, Stoneholme Rd Rossendale Lancashire BB4 8BA",
    "addr:housenumber":"unit 1",
    "addr:postcode":"bb4 8ba",
    "addr:street":"Stoneholme Rd",
    "iso:country":"GB",
    "sg:address":"Unit 1, Stoneholme Rd",
    "sg:city":"Rossendale",
    "sg:classifiers":[
        {
            "category":"Retail",
            "subcategory":"Auto Repair",
            "type":"Services"
        }
    ],
    "sg:postcode":"BB4 8BA",
    "sg:province":"Lancashire",
    "sg:tags":[
        "modification",
        "garage"
    ],
    "wof:name":"Rawstron,Micheal,",
    "wof:placetype":"venue"
},
  "geometry": {"coordinates":[-2.2881140709,53.7249946594],"type":"Point"}
}