{
  "type": "Feature",
  "properties": {
    "addr:full":"5 Broadway Drive Halesworth Suffolk IP19 8QR",
    "addr:housenumber":"5",
    "addr:postcode":"ip19 8qr",
    "addr:street":"Broadway Drive",
    "iso:country":"GB",
    "sg:address":"5 Broadway Drive",
    "sg:city":"Halesworth",
    "sg:classifiers":[
        {
            "category":"Shopping",
            "subcategory":"Beauty & Cosmetics",
            "type":"Retail Goods"
        }
    ],
    "sg:phone":"+44 1986 874149",
    "sg:postcode":"IP19 8QR",
    "sg:province":"Suffolk",
    "wof:name":"Herrco Plastics",
    "wof:placetype":"venue"
},
  "geometry": {"coordinates":[1.509231,52.353466],"type":"Point"}
}