{
  "type": "Feature",
  "properties": {
    "iso:country":"GB",
    "sg:address":", Rendham Saxmundham",
    "sg:city":"Saxmundham",
    "sg:classifiers":[
        {
            "category":"Bars & Pubs",
            "type":"Food & Drink"
        }
    ],
    "sg:phone":"+44 1728 663497",
    "sg:postcode":"IP17 2AF",
    "sg:province":"Suffolk",
    "sg:tags":[
        "pubs",
        "inn"
    ],
    "wof:name":"The White Horse",
    "wof:placetype":"venue"
},
  "geometry": {"coordinates":[1.439956,52.22876],"type":"Point"}
}