{
  "type": "Feature",
  "properties": {
    "addr:full":"59 New Chester Road, New Ferry Wirral Cheshire CH62 1AB",
    "addr:housenumber":"59",
    "addr:postcode":"ch62 1ab",
    "addr:street":"New Chester Road",
    "iso:country":"GB",
    "sg:address":"59 New Chester Road, New Ferry",
    "sg:city":"Wirral",
    "sg:classifiers":[
        {
            "category":"Home & Garden",
            "subcategory":"Carpets & Floor Coverings",
            "type":"Retail Goods"
        }
    ],
    "sg:phone":"+44 151 643 1167",
    "sg:postcode":"CH62 1AB",
    "sg:province":"Cheshire",
    "sg:tags":[
        "carpets",
        "rug",
        "matting"
    ],
    "wof:name":"New Ferry Carpets",
    "wof:placetype":"venue"
},
  "geometry": {"coordinates":[-2.996659,53.36005],"type":"Point"}
}