{
  "type": "Feature",
  "properties": {
    "iso:country":"GB",
    "sg:address":"Aquarium House, Unit Z Green Street",
    "sg:city":"Kidderminster",
    "sg:classifiers":[
        {
            "category":"Building & Trades",
            "subcategory":"Landscaping Services",
            "type":"Services"
        }
    ],
    "sg:phone":"+44 1562 515539",
    "sg:postcode":"DY10 2BH",
    "sg:province":"Staffordshire",
    "sg:tags":[
        "pond",
        "aquarium"
    ],
    "wof:name":"Forty Fathoms",
    "wof:placetype":"venue"
},
  "geometry": {"coordinates":[-2.249084,52.388111],"type":"Point"}
}