{
  "type": "Feature",
  "properties": {
    "addr:full":"35 Chilton Road Bath Bath and North East Somerset BA1 6DR",
    "addr:housenumber":"35",
    "addr:postcode":"ba1 6dr",
    "addr:street":"Chilton Road",
    "iso:country":"GB",
    "sg:address":"35 Chilton Road",
    "sg:city":"Bath",
    "sg:classifiers":[
        {
            "category":"Home & Garden",
            "subcategory":"Carpets & Floor Coverings",
            "type":"Retail Goods"
        }
    ],
    "sg:phone":"+44 1225 315794",
    "sg:postcode":"BA1 6DR",
    "sg:province":"Bath and North East Somerset",
    "sg:tags":[
        "textile",
        "floorcoverings"
    ],
    "wof:name":"Howell & Partners",
    "wof:placetype":"venue"
},
  "geometry": {"coordinates":[-2.3518159389,51.3944015503],"type":"Point"}
}