{
  "type": "Feature",
  "properties": {
    "addr:full":"1 Winter Grn Cotts, Codicote Hitchin Hertfordshire SG4 8TG",
    "addr:housenumber":"1",
    "addr:postcode":"sg4 8tg",
    "addr:street":"Winter Grn",
    "iso:country":"GB",
    "sg:address":"1 Winter Grn Cotts, Codicote",
    "sg:city":"Hitchin",
    "sg:classifiers":[
        {
            "category":"Freight",
            "type":"Transportation"
        }
    ],
    "sg:postcode":"SG4 8TG",
    "sg:province":"Hertfordshire",
    "sg:tags":[
        "haulage",
        "road"
    ],
    "wof:name":"Monger,John Douglas,",
    "wof:placetype":"venue"
},
  "geometry": {"coordinates":[-0.2353589982,51.84923172],"type":"Point"}
}