{
  "type": "Feature",
  "properties": {
    "iso:country":"GB",
    "sg:address":"Unit 7 Cae Duke Lougher Road, Gorseinon",
    "sg:city":"Swansea",
    "sg:classifiers":[
        {
            "category":"Home & Garden",
            "subcategory":"Household Appliances",
            "type":"Retail Goods"
        }
    ],
    "sg:postcode":"SA4 6QU",
    "sg:province":"Carmarthenshire",
    "sg:tags":[
        "electrical"
    ],
    "wof:name":"South Wales Electrical Repairs",
    "wof:placetype":"venue"
},
  "geometry": {"coordinates":[-4.06326,51.665272],"type":"Point"}
}