{
  "type": "Feature",
  "properties": {
    "addr:full":"98 Spring La Oldham Lancashire OL4 5AZ",
    "addr:housenumber":"98",
    "addr:postcode":"ol4 5az",
    "addr:street":"Spring La Oldham",
    "iso:country":"GB",
    "sg:address":"98 Spring La",
    "sg:city":"Oldham",
    "sg:classifiers":[
        {
            "category":"Building & Trades",
            "subcategory":"Construction",
            "type":"Services"
        }
    ],
    "sg:phone":"+44 161 624 1687",
    "sg:postcode":"OL4 5AZ",
    "sg:province":"Lancashire",
    "sg:tags":[
        "decorator",
        "painter"
    ],
    "wof:name":"Roy Errock",
    "wof:placetype":"venue"
},
  "geometry": {"coordinates":[-2.076853,53.535152],"type":"Point"}
}