{
  "type": "Feature",
  "properties": {
    "iso:country":"GB",
    "sg:address":"11 Penda Way",
    "sg:city":"Sandbach",
    "sg:classifiers":[
        {
            "category":"Cinema",
            "subcategory":"Movie Rental",
            "type":"Entertainment"
        }
    ],
    "sg:phone":"+44 1270 762490",
    "sg:postcode":"CW11 1GS",
    "sg:province":"Cheshire",
    "sg:tags":[
        "video",
        "library"
    ],
    "wof:name":"Videoworld",
    "wof:placetype":"venue"
},
  "geometry": {"coordinates":[-2.363648,53.142208],"type":"Point"}
}