{
  "type": "Feature",
  "properties": {
    "addr:full":"268 High Street, Batheaston Bath Bath and North East Somerset BA1 7RA",
    "addr:housenumber":"268",
    "addr:postcode":"ba1 7ra",
    "addr:street":"High Street",
    "iso:country":"GB",
    "sg:address":"268 High Street, Batheaston",
    "sg:city":"Bath",
    "sg:classifiers":[
        {
            "category":"Food & Beverages",
            "subcategory":"Meat & Fish",
            "type":"Retail Goods"
        }
    ],
    "sg:postcode":"BA1 7RA",
    "sg:province":"Bath and North East Somerset",
    "sg:tags":[
        "butcher"
    ],
    "wof:name":"Quality Butchers",
    "wof:placetype":"venue"
},
  "geometry": {"coordinates":[-2.3213191032,51.4052772522],"type":"Point"}
}