{
  "type": "Feature",
  "properties": {
    "iso:country":"GB",
    "sg:address":"17 Rowley Close, Brantham",
    "sg:city":"Manningtree",
    "sg:classifiers":[
        {
            "category":"Building & Trades",
            "subcategory":"Construction",
            "type":"Services"
        }
    ],
    "sg:phone":"+44 1206 395812",
    "sg:postcode":"CO11 1RR",
    "sg:province":"Essex",
    "sg:tags":[
        "builder"
    ],
    "wof:name":"T Tatum General Building Contractor",
    "wof:placetype":"venue"
},
  "geometry": {"coordinates":[1.0629819632,51.9610137939],"type":"Point"}
}