{
  "type": "Feature",
  "properties": {
    "iso:country":"GB",
    "sg:address":"Shellingford Quarry, Stanford Road, Stanford-in-the-valeroad",
    "sg:city":"Faringdon",
    "sg:classifiers":[
        {
            "category":"Home & Garden",
            "subcategory":"Garden Supply",
            "type":"Retail Goods"
        }
    ],
    "sg:phone":"+44 1367 718949",
    "sg:postcode":"SN7 8HE",
    "sg:province":"Oxfordshire",
    "sg:tags":[
        "sand",
        "gravel"
    ],
    "wof:name":"Multi-Agg Ltd.",
    "wof:placetype":"venue"
},
  "geometry": {"coordinates":[-1.586654,51.65617],"type":"Point"}
}