{
  "type": "Feature",
  "properties": {
    "addr:full":"Kilkenny House, 77 Lower Rd, Fetcham Leatherhead Surrey KT22 9HG",
    "addr:housenumber":"77",
    "addr:postcode":"kt22 9hg",
    "addr:street":"Lower Rd",
    "iso:country":"GB",
    "sg:address":"Kilkenny House, 77 Lower Rd, Fetcham",
    "sg:city":"Leatherhead",
    "sg:classifiers":[
        {
            "category":"Professional",
            "subcategory":"Engineering",
            "type":"Services"
        }
    ],
    "sg:phone":"+44 1372 451123",
    "sg:postcode":"KT22 9HG",
    "sg:province":"Surrey",
    "sg:tags":[
        "design",
        "engineer"
    ],
    "wof:name":"Tyrrell Consultants",
    "wof:placetype":"venue"
},
  "geometry": {"coordinates":[-0.3567590117,51.2876701355],"type":"Point"}
}