{
  "type": "Feature",
  "properties": {
    "addr:full":"93 Southtown Rd Great Yarmouth Norfolk NR31 0JX",
    "addr:housenumber":"93",
    "addr:postcode":"nr31 0jx",
    "addr:street":"Southtown Rd",
    "iso:country":"GB",
    "sg:address":"93 Southtown Rd",
    "sg:city":"Great Yarmouth",
    "sg:classifiers":[
        {
            "category":"Social Services",
            "subcategory":"Retirement Home",
            "type":"Services"
        }
    ],
    "sg:phone":"+44 1493 657981",
    "sg:postcode":"NR31 0JX",
    "sg:province":"Norfolk",
    "sg:tags":[
        "residential",
        "care"
    ],
    "wof:name":"Eaglehurst",
    "wof:placetype":"venue"
},
  "geometry": {"coordinates":[1.725041,52.596691],"type":"Point"}
}