{
  "type": "Feature",
  "properties": {
    "addr:full":"21 Spring Lane Wellingborough Northamptonshire NN8 1EY",
    "addr:housenumber":"21",
    "addr:postcode":"nn8 1ey",
    "addr:street":"Spring Lane",
    "iso:country":"GB",
    "sg:address":"21 Spring Lane",
    "sg:city":"Wellingborough",
    "sg:classifiers":[
        {
            "category":"Sports & Exercise",
            "subcategory":"Sports Center",
            "type":"Entertainment"
        }
    ],
    "sg:phone":"+44 1933 222939",
    "sg:postcode":"NN8 1EY",
    "sg:province":"Northamptonshire",
    "sg:tags":[
        "shop",
        "good"
    ],
    "wof:name":"Sportsworld (G B) Plc",
    "wof:placetype":"venue"
},
  "geometry": {"coordinates":[-0.610706985,52.3278923035],"type":"Point"}
}