{
  "type": "Feature",
  "properties": {
    "addr:full":"Dacca House, 4 Croftshaw Rd Alva Clackmannanshire FK12 5ES",
    "addr:housenumber":"4",
    "addr:postcode":"fk12 5es",
    "addr:street":"Croftshaw Rd",
    "iso:country":"GB",
    "sg:address":"Dacca House, 4 Croftshaw Rd",
    "sg:city":"Alva",
    "sg:classifiers":[
        {
            "category":"Shopping",
            "subcategory":"Computers & Home Electronics",
            "type":"Retail Goods"
        }
    ],
    "sg:phone":"+44 1259 763195",
    "sg:postcode":"FK12 5ES",
    "sg:province":"Clackmannanshire",
    "wof:name":"G.R Technology Services",
    "wof:placetype":"venue"
},
  "geometry": {"coordinates":[-3.7978899479,56.1536865234],"type":"Point"}
}