{
  "type": "Feature",
  "properties": {
    "iso:country":"GB",
    "sg:address":"The Manor, Main Street",
    "sg:city":"Loughborough",
    "sg:classifiers":[
        {
            "category":"Utilities",
            "subcategory":"Natural Gas",
            "type":"Services"
        }
    ],
    "sg:phone":"+44 1509 843331",
    "sg:postcode":"LE12 5HB",
    "sg:province":"Leicestershire",
    "sg:tags":[
        "supplier",
        "industrial"
    ],
    "wof:name":"Gaslow International Ltd.",
    "wof:placetype":"venue"
},
  "geometry": {"coordinates":[-1.23429,52.803188],"type":"Point"}
}