{
  "type": "Feature",
  "properties": {
    "iso:country":"GB",
    "sg:address":"4 Achmore Road, Kyleakin",
    "sg:city":"Isle Of Skye",
    "sg:classifiers":[
        {
            "category":"Military Area",
            "subcategory":"Air Force Base",
            "type":"Public Place"
        }
    ],
    "sg:postcode":"IV41 8PS",
    "sg:province":"Highland",
    "sg:tags":[
        "taxi",
        "hire",
        "private"
    ],
    "wof:name":"Angus Anderson",
    "wof:placetype":"venue"
},
  "geometry": {"coordinates":[-5.7362761497,57.2725372314],"type":"Point"}
}