{
  "type": "Feature",
  "properties": {
    "iso:country":"GB",
    "sg:address":"22-24 High St",
    "sg:city":"Grays",
    "sg:classifiers":[
        {
            "category":"Home & Garden",
            "subcategory":"Home Furnishings",
            "type":"Retail Goods"
        }
    ],
    "sg:phone":"+44 1375 374207",
    "sg:postcode":"RM17 6LU",
    "sg:province":"Essex",
    "sg:tags":[
        "wall",
        "wallpaper",
        "covering"
    ],
    "wof:name":"Homestyle",
    "wof:placetype":"venue"
},
  "geometry": {"coordinates":[0.322896,51.477749],"type":"Point"}
}