{
  "type": "Feature",
  "properties": {
    "iso:country":"GB",
    "sg:address":"Unit 3 Tristar Business Centre, Star Road, Partridge Green",
    "sg:city":"Horsham",
    "sg:classifiers":[
        {
            "category":"Professional",
            "subcategory":"Detective & Security Services",
            "type":"Services"
        }
    ],
    "sg:phone":"+44 1403 711000",
    "sg:postcode":"RH13 8RA",
    "sg:province":"West Sussex",
    "sg:tags":[
        "alarm",
        "burglar",
        "system"
    ],
    "sg:website":"http://www.kestrelalarms.co.uk",
    "wof:name":"Kestrel Alarms Ltd",
    "wof:placetype":"venue"
},
  "geometry": {"coordinates":[-0.3059389889,50.9594192505],"type":"Point"}
}