{
  "type": "Feature",
  "properties": {
    "iso:country":"GB",
    "sg:address":"3 Culverin Square, Limberline Road, Hilsea",
    "sg:city":"Portsmouth",
    "sg:classifiers":[
        {
            "category":"Manufacturing",
            "subcategory":"Glass & Minerals",
            "type":"Manufacturing & Wholesale Goods"
        }
    ],
    "sg:phone":"+44 23 9267 9704",
    "sg:postcode":"PO3 5BU",
    "sg:province":"Hampshire",
    "sg:tags":[
        "fibre",
        "moulding"
    ],
    "wof:name":"Quality Mouldings",
    "wof:placetype":"venue"
},
  "geometry": {"coordinates":[-1.06284,50.831161],"type":"Point"}
}