{
  "type": "Feature",
  "properties": {
    "iso:country":"GB",
    "sg:address":"Lebasi, Stoneykirk Rd",
    "sg:city":"Stranraer",
    "sg:classifiers":[
        {
            "category":"Farming",
            "subcategory":"Dairy Farm",
            "type":"Manufacturing & Wholesale Goods"
        }
    ],
    "sg:phone":"+44 1776 702543",
    "sg:postcode":"DG9 7BT",
    "sg:province":"Dumfries and Galloway",
    "wof:name":"R Richardson",
    "wof:placetype":"venue"
},
  "geometry": {"coordinates":[-5.023004,54.894341],"type":"Point"}
}