{
  "type": "Feature",
  "properties": {
    "iso:country":"GB",
    "sg:address":"7-11 Baronald Street, Rutherglen",
    "sg:city":"Glasgow",
    "sg:classifiers":[
        {
            "category":"Distillery",
            "subcategory":"None",
            "type":"Food & Drink"
        }
    ],
    "sg:phone":"+44 141 647 4774",
    "sg:postcode":"G73 1AF",
    "sg:province":"Glasgow City",
    "wof:name":"Rutherglen Scotch Whiskey Co Ltd",
    "wof:placetype":"venue"
},
  "geometry": {"coordinates":[-4.2073698044,55.8339538574],"type":"Point"}
}