{
  "type": "Feature",
  "properties": {
    "addr:full":"27-29 King Street Norwich Norfolk NR1 1PD",
    "addr:housenumber":"27-29",
    "addr:postcode":"nr1 1pd",
    "addr:street":"King Street",
    "iso:country":"GB",
    "sg:address":"27-29 King Street",
    "sg:city":"Norwich",
    "sg:classifiers":[
        {
            "category":"Bars & Pubs",
            "type":"Food & Drink"
        }
    ],
    "sg:phone":"+44 1603 624078",
    "sg:postcode":"NR1 1PD",
    "sg:province":"Norfolk",
    "sg:tags":[
        "pubs",
        "inn"
    ],
    "wof:name":"The Nags Head",
    "wof:placetype":"venue"
},
  "geometry": {"coordinates":[1.299185,52.628311],"type":"Point"}
}