{
  "type": "Feature",
  "properties": {
    "addr:full":"9 Octagon Parade High Wycombe Buckinghamshire HP11 2HR",
    "addr:housenumber":"9",
    "addr:postcode":"hp11 2hr",
    "addr:street":"Octagon Parade",
    "iso:country":"GB",
    "sg:address":"9 Octagon Parade",
    "sg:city":"High Wycombe",
    "sg:classifiers":[
        {
            "category":"Communications",
            "type":"Services"
        }
    ],
    "sg:phone":"+44 1494 521367",
    "sg:postcode":"HP11 2HR",
    "sg:province":"Buckinghamshire",
    "sg:tags":[
        "telecommunication"
    ],
    "wof:name":"Phones 4 U Ltd.",
    "wof:placetype":"venue"
},
  "geometry": {"coordinates":[-0.7523,51.629162],"type":"Point"}
}