{
  "type": "Feature",
  "properties": {
    "addr:full":"Rothwell Sports Centre, Wakefield Rd Leeds West Yorkshire LS26 8EL",
    "addr:postcode":"ls26 8el",
    "addr:street":"Wakefield Rd",
    "iso:country":"GB",
    "sg:address":"Rothwell Sports Centre, Wakefield Rd",
    "sg:city":"Leeds",
    "sg:classifiers":[
        {
            "category":"Health Services",
            "subcategory":"Health Practitioner",
            "type":"Services"
        }
    ],
    "sg:phone":"+44 113 282 4110",
    "sg:postcode":"LS26 8EL",
    "sg:province":"West Yorkshire",
    "sg:tags":[
        "physiotherapist"
    ],
    "wof:name":"Simon Love",
    "wof:placetype":"venue"
},
  "geometry": {"coordinates":[-1.4207600355,53.7666893005],"type":"Point"}
}