{
  "type": "Feature",
  "properties": {
    "addr:full":"Etonbury Farm, Stotfold Road Arlesey Bedfordshire SG15 6SB",
    "addr:postcode":"sg15 6sb",
    "addr:street":"Stotfold Road",
    "iso:country":"GB",
    "sg:address":"Etonbury Farm, Stotfold Road",
    "sg:city":"Arlesey",
    "sg:classifiers":[
        {
            "category":"Home & Garden",
            "subcategory":"Garden Supply",
            "type":"Retail Goods"
        }
    ],
    "sg:phone":"+44 1462 731709",
    "sg:postcode":"SG15 6SB",
    "sg:province":"Bedfordshire",
    "sg:tags":[
        "pool",
        "swimming"
    ],
    "wof:name":"Fitwarmth Ltd.",
    "wof:placetype":"venue"
},
  "geometry": {"coordinates":[-0.2655990124,52.0059204102],"type":"Point"}
}