{
  "type": "Feature",
  "properties": {
    "iso:country":"GB",
    "sg:address":"Radnor House, 14 New Road",
    "sg:city":"Basingstoke",
    "sg:classifiers":[
        {
            "category":"Organizations",
            "subcategory":"Membership Organization",
            "type":"Services"
        }
    ],
    "sg:phone":"+44 1256 465060",
    "sg:postcode":"RG21 7PS",
    "sg:province":"Hampshire",
    "sg:tags":[
        "club"
    ],
    "wof:name":"Basingstoke Ex-Services Club Ltd.",
    "wof:placetype":"venue"
},
  "geometry": {"coordinates":[-1.084597,51.264828],"type":"Point"}
}