{
  "type": "Feature",
  "properties": {
    "iso:country":"GB",
    "sg:address":"Unit 6, Northwest Business Park, Servia Hill",
    "sg:city":"Leeds",
    "sg:classifiers":[
        {
            "category":"Professional",
            "subcategory":"Engineering",
            "type":"Services"
        },
        {
            "category":"Real Estate",
            "subcategory":"Surveying",
            "type":"Services"
        }
    ],
    "sg:phone":"+44 113 234 3800",
    "sg:postcode":"LS6 2QH",
    "sg:province":"West Yorkshire",
    "sg:tags":[
        "surveyor",
        "consulting",
        "quantity",
        "engineer"
    ],
    "wof:name":"Trett Consulting",
    "wof:placetype":"venue"
},
  "geometry": {"coordinates":[-1.54782,53.811031],"type":"Point"}
}