{
  "type": "Feature",
  "properties": {
    "addr:full":"54a East Street Thame Buckinghamshire OX9 3JS",
    "addr:housenumber":"54a",
    "addr:postcode":"ox9 3js",
    "addr:street":"East Street",
    "iso:country":"GB",
    "sg:address":"54a East Street",
    "sg:city":"Thame",
    "sg:classifiers":[
        {
            "category":"Retail",
            "subcategory":"Emissions Testing",
            "type":"Services"
        },
        {
            "category":"Retail",
            "subcategory":"Auto Repair",
            "type":"Services"
        }
    ],
    "sg:phone":"+44 1844 261885",
    "sg:postcode":"OX9 3JS",
    "sg:province":"Buckinghamshire",
    "sg:tags":[
        "specialist",
        "customizing",
        "mot",
        "car"
    ],
    "wof:name":"Thame One Stop Auto Centre",
    "wof:placetype":"venue"
},
  "geometry": {"coordinates":[-0.971339,51.744968],"type":"Point"}
}