{
  "type": "Feature",
  "properties": {
    "iso:country":"GB",
    "sg:address":"35 Waverley Road",
    "sg:city":"St Albans",
    "sg:classifiers":[
        {
            "category":"Professional",
            "subcategory":"Management & Consulting",
            "type":"Services"
        }
    ],
    "sg:phone":"+44 1727 862862",
    "sg:postcode":"AL3 5PH",
    "sg:province":"Hertfordshire",
    "sg:tags":[
        "consultant",
        "business"
    ],
    "wof:name":"Business Minds U K Ltd.",
    "wof:placetype":"venue"
},
  "geometry": {"coordinates":[-0.339584,51.759541],"type":"Point"}
}