{
  "type": "Feature",
  "properties": {
    "addr:full":"135 Ashley Road New Milton Hampshire BH25 5BL",
    "addr:housenumber":"135",
    "addr:postcode":"bh25 5bl",
    "addr:street":"Ashley Road",
    "iso:country":"GB",
    "sg:address":"135 Ashley Road",
    "sg:city":"New Milton",
    "sg:classifiers":[
        {
            "category":"Government",
            "subcategory":"Post Office",
            "type":"Public Place"
        }
    ],
    "sg:postcode":"BH25 5BL",
    "sg:province":"Hampshire",
    "wof:name":"Ashley Stores",
    "wof:placetype":"venue"
},
  "geometry": {"coordinates":[-1.6388839483,50.7577972412],"type":"Point"}
}