{
  "type": "Feature",
  "properties": {
    "addr:full":"The Industrial Estate, Station Road, Harrietsham Maidstone Kent ME17 1JA",
    "addr:postcode":"me17 1ja",
    "addr:street":"Station Road",
    "iso:country":"GB",
    "sg:address":"The Industrial Estate, Station Road, Harrietsham",
    "sg:city":"Maidstone",
    "sg:classifiers":[
        {
            "category":"Shopping",
            "subcategory":"Bicycles & Sporting Goods",
            "type":"Retail Goods"
        }
    ],
    "sg:phone":"+44 1622 858458",
    "sg:postcode":"ME17 1JA",
    "sg:province":"Kent",
    "sg:tags":[
        "equipment",
        "marine",
        "supply"
    ],
    "wof:name":"Sullivan Marine Ltd.",
    "wof:placetype":"venue"
},
  "geometry": {"coordinates":[0.671797,51.241665],"type":"Point"}
}