{
  "type": "Feature",
  "properties": {
    "iso:country":"GB",
    "sg:address":"9 Welles Street",
    "sg:city":"Sandbach",
    "sg:classifiers":[
        {
            "category":"Personal",
            "subcategory":"Beauty Salon",
            "type":"Services"
        }
    ],
    "sg:phone":"+44 1270 767396",
    "sg:postcode":"CW11 1GT",
    "sg:province":"Cheshire",
    "sg:tags":[
        "unisex",
        "hairdresser"
    ],
    "wof:name":"Carolyn of Welles Street",
    "wof:placetype":"venue"
},
  "geometry": {"coordinates":[-2.363931,53.145054],"type":"Point"}
}