{
  "type": "Feature",
  "properties": {
    "addr:full":"25 Bond End Knaresborough North Yorkshire HG5 9AW",
    "addr:housenumber":"25",
    "addr:postcode":"hg5 9aw",
    "addr:street":"Bond End",
    "iso:country":"GB",
    "sg:address":"25 Bond End",
    "sg:city":"Knaresborough",
    "sg:classifiers":[
        {
            "category":"Place Of Worship",
            "type":"Public Place"
        },
        {
            "category":"Organizations",
            "subcategory":"Non-profit Organization",
            "type":"Services"
        }
    ],
    "sg:phone":"+44 1423 862388",
    "sg:postcode":"HG5 9AW",
    "sg:province":"North Yorkshire",
    "sg:tags":[
        "charitable",
        "organisation",
        "charity"
    ],
    "wof:name":"St. Marys Roman Catholic Church",
    "wof:placetype":"venue"
},
  "geometry": {"coordinates":[-1.47255,54.010834],"type":"Point"}
}