{
  "type": "Feature",
  "properties": {
    "addr:full":"Windy Nook Rd Gateshead Tyne and Wear NE10 9RW",
    "addr:postcode":"ne10 9rw",
    "addr:street":"Nook Rd",
    "iso:country":"GB",
    "sg:address":"Windy Nook Rd",
    "sg:city":"Gateshead",
    "sg:classifiers":[
        {
            "category":"Health Services",
            "subcategory":"Hospital",
            "type":"Services"
        }
    ],
    "sg:phone":"+44 191 402 6000",
    "sg:postcode":"NE10 9RW",
    "sg:province":"Tyne and Wear",
    "wof:name":"Tranwell Unit",
    "wof:placetype":"venue"
},
  "geometry": {"coordinates":[-1.577450037,54.9401702881],"type":"Point"}
}