{
  "type": "Feature",
  "properties": {
    "iso:country":"GB",
    "sg:address":"5 Weston Park Road",
    "sg:city":"Plymouth",
    "sg:classifiers":[
        {
            "category":"Fast Food",
            "type":"Food & Drink"
        }
    ],
    "sg:phone":"+44 1752 662082",
    "sg:postcode":"PL3 4NS",
    "sg:province":"Devon",
    "sg:tags":[
        "away",
        "meal",
        "outlet",
        "take"
    ],
    "wof:name":"New Far East Kitchen",
    "wof:placetype":"venue"
},
  "geometry": {"coordinates":[-4.139015,50.387394],"type":"Point"}
}