{
  "type": "Feature",
  "properties": {
    "addr:full":"15 Drew Street Brixham Devon TQ5 9JU",
    "addr:housenumber":"15",
    "addr:postcode":"tq5 9ju",
    "addr:street":"Drew Street",
    "iso:country":"GB",
    "sg:address":"15 Drew Street",
    "sg:city":"Brixham",
    "sg:classifiers":[
        {
            "category":"Social Services",
            "type":"Services"
        },
        {
            "category":"Government",
            "subcategory":"Office",
            "type":"Public Place"
        }
    ],
    "sg:phone":"+44 1803 853249",
    "sg:postcode":"TQ5 9JU",
    "sg:province":"Devon",
    "sg:tags":[
        "local"
    ],
    "wof:name":"St. Kilda's Residential Home for the Elderly",
    "wof:placetype":"venue"
},
  "geometry": {"coordinates":[-3.51614,50.388119],"type":"Point"}
}