{
  "type": "Feature",
  "properties": {
    "iso:country":"GB",
    "sg:address":"Westons Chartered Accountants",
    "sg:city":"Sheffield",
    "sg:classifiers":[
        {
            "category":"Deli",
            "type":"Food & Drink"
        }
    ],
    "sg:phone":"+44 114 285 4011",
    "sg:postcode":"S1 2DX",
    "sg:province":"South Yorkshire",
    "sg:tags":[
        "delivery",
        "sandwich"
    ],
    "wof:name":"Hampshire 804 Ltd.",
    "wof:placetype":"venue"
},
  "geometry": {"coordinates":[-1.464544,53.38311],"type":"Point"}
}