{
  "type": "Feature",
  "properties": {
    "addr:full":"The Carisbrooke, 5 Alexandra Road Newquay Cornwall TR7 3ND",
    "addr:housenumber":"5",
    "addr:postcode":"tr7 3nd",
    "addr:street":"Alexandra Road",
    "iso:country":"GB",
    "sg:address":"The Carisbrooke, 5 Alexandra Road",
    "sg:city":"Newquay",
    "sg:classifiers":[
        {
            "category":"Travel",
            "subcategory":"Hotels & Motels",
            "type":"Entertainment"
        }
    ],
    "sg:phone":"+44 1637 874177",
    "sg:postcode":"TR7 3ND",
    "sg:province":"Cornwall",
    "sg:tags":[
        "house",
        "guest"
    ],
    "wof:name":"Carisbrooke Guest House",
    "wof:placetype":"venue"
},
  "geometry": {"coordinates":[-5.0718588829,50.4120864868],"type":"Point"}
}