{
  "type": "Feature",
  "properties": {
    "addr:full":"10a Balls Rd Prenton Merseyside CH43 5RE",
    "addr:housenumber":"10a",
    "addr:postcode":"ch43 5re",
    "addr:street":"Balls Rd",
    "iso:country":"GB",
    "sg:address":"10a Balls Rd",
    "sg:city":"Prenton",
    "sg:classifiers":[
        {
            "category":"Communications",
            "type":"Services"
        }
    ],
    "sg:postcode":"CH43 5RE",
    "sg:province":"Merseyside",
    "sg:tags":[
        "tv",
        "video",
        "radio"
    ],
    "wof:name":"Melia,Andrew,",
    "wof:placetype":"venue"
},
  "geometry": {"coordinates":[-3.03789,53.38504],"type":"Point"}
}