{
  "type": "Feature",
  "properties": {
    "iso:country":"GB",
    "sg:address":"32 Mill Hill",
    "sg:city":"Newmarket",
    "sg:classifiers":[
        {
            "category":"Organizations",
            "subcategory":"Non-profit Organization",
            "type":"Services"
        }
    ],
    "sg:phone":"+44 1638 663671",
    "sg:postcode":"CB8 0JB",
    "sg:province":"Cambridgeshire",
    "sg:tags":[
        "organisation",
        "voluntary",
        "charity"
    ],
    "wof:name":"British Red Cross Society",
    "wof:placetype":"venue"
},
  "geometry": {"coordinates":[0.402616,52.246162],"type":"Point"}
}