{
  "type": "Feature",
  "properties": {
    "addr:full":"7 Haslingden Old Road Rossendale Lancashire BB4 8SA",
    "addr:housenumber":"7",
    "addr:postcode":"bb4 8sa",
    "addr:street":"Haslingden Old Road",
    "iso:country":"GB",
    "sg:address":"7 Haslingden Old Road",
    "sg:city":"Rossendale",
    "sg:classifiers":[
        {
            "category":"Shopping",
            "subcategory":"Musical Instruments",
            "type":"Retail Goods"
        }
    ],
    "sg:postcode":"BB4 8SA",
    "sg:province":"Lancashire",
    "sg:tags":[
        "music",
        "sheet"
    ],
    "wof:name":"Creighton Music",
    "wof:placetype":"venue"
},
  "geometry": {"coordinates":[-2.2862489223,53.7047271729],"type":"Point"}
}