{
  "type": "Feature",
  "properties": {
    "addr:full":"Storage 9 Dragonville Industrial Park, Dragon Lane Durham Durham DH1 2XW",
    "addr:housenumber":"9",
    "addr:postcode":"dh1 2xw",
    "addr:street":"Dragonville Industrial Park Dragon Lane",
    "iso:country":"GB",
    "sg:address":"Storage 9 Dragonville Industrial Park, Dragon Lane",
    "sg:city":"Durham",
    "sg:classifiers":[
        {
            "category":"Professional",
            "subcategory":"Lawyer & Legal Services",
            "type":"Services"
        }
    ],
    "sg:phone":"+44 191 383 1515",
    "sg:postcode":"DH1 2XW",
    "sg:province":"Durham",
    "sg:tags":[
        "advice",
        "counselling"
    ],
    "wof:name":"Victim Support Durham",
    "wof:placetype":"venue"
},
  "geometry": {"coordinates":[-1.5438840389,54.7763748169],"type":"Point"}
}