{
  "type": "Feature",
  "properties": {
    "iso:country":"GB",
    "sg:address":"Unit 27, Wren Court",
    "sg:city":"Bellshill",
    "sg:classifiers":[
        {
            "category":"Professional",
            "subcategory":"Engineering",
            "type":"Services"
        },
        {
            "category":"Real Estate",
            "subcategory":"Real Estate Operator",
            "type":"Services"
        }
    ],
    "sg:phone":"+44 1698 747543",
    "sg:postcode":"ML4 3NQ",
    "sg:province":"North Lanarkshire",
    "sg:tags":[
        "instrumentation",
        "aviation",
        "engineer"
    ],
    "wof:name":"Avotec Ltd",
    "wof:placetype":"venue"
},
  "geometry": {"coordinates":[-4.0387339592,55.8312606812],"type":"Point"}
}