{
  "type": "Feature",
  "properties": {
    "addr:full":"Raldek House, 12-14 Lower Addiscombe Road Croydon Surrey CR0 6AA",
    "addr:housenumber":"12-14",
    "addr:postcode":"cr0 6aa",
    "addr:street":"Lower Addiscombe Road",
    "iso:country":"GB",
    "sg:address":"Raldek House, 12-14 Lower Addiscombe Road",
    "sg:city":"Croydon",
    "sg:classifiers":[
        {
            "category":"Building & Trades",
            "subcategory":"Construction",
            "type":"Services"
        }
    ],
    "sg:phone":"+44 20 8667 1585",
    "sg:postcode":"CR0 6AA",
    "sg:province":"Surrey",
    "sg:tags":[
        "builder"
    ],
    "wof:name":"Southern Drywall (South East) Ltd.",
    "wof:placetype":"venue"
},
  "geometry": {"coordinates":[-0.089035,51.380669],"type":"Point"}
}