{
  "type": "Feature",
  "properties": {
    "iso:country":"GB",
    "sg:address":"Duck Lane, Stalbridge",
    "sg:city":"Sturminster Newton",
    "sg:classifiers":[
        {
            "category":"Education",
            "subcategory":"School",
            "type":"Public Place"
        }
    ],
    "sg:phone":"+44 1963 362487",
    "sg:postcode":"DT10 2LP",
    "sg:province":"Dorset",
    "sg:tags":[
        "local",
        "authority"
    ],
    "wof:name":"Stalbridge C of E Primary School",
    "wof:placetype":"venue"
},
  "geometry": {"coordinates":[-2.37807,50.961201],"type":"Point"}
}