{
  "type": "Feature",
  "properties": {
    "iso:country":"GB",
    "sg:address":"East Cannock Industrial Estate, East Cannock Road",
    "sg:city":"Cannock",
    "sg:classifiers":[
        {
            "category":"Retail",
            "subcategory":"Driving School",
            "type":"Services"
        }
    ],
    "sg:postcode":"WS12 5LT",
    "sg:province":"Staffordshire",
    "wof:name":"H G V British Training Group",
    "wof:placetype":"venue"
},
  "geometry": {"coordinates":[-1.962696,52.710758],"type":"Point"}
}