{
  "type": "Feature",
  "properties": {
    "addr:full":"East Cannock Industrial Estate, East Cannock Road Cannock Staffordshire WS12 5LT",
    "addr:housenumber":"estate",
    "addr:postcode":"ws12 5lt",
    "addr:street":"East Cannock Industrial;East Cannock Road",
    "iso:country":"GB",
    "sg:address":"East Cannock Industrial Estate, East Cannock Road",
    "sg:city":"Cannock",
    "sg:classifiers":[
        {
            "category":"Retail",
            "subcategory":"Driving School",
            "type":"Services"
        }
    ],
    "sg:postcode":"WS12 5LT",
    "sg:province":"Staffordshire",
    "wof:name":"H G V British Training Group",
    "wof:placetype":"venue"
},
  "geometry": {"coordinates":[-1.962696,52.710758],"type":"Point"}
}