{
  "type": "Feature",
  "properties": {
    "addr:full":"18 Princes Road Burnham-on-crouch Essex CM0 8BX",
    "addr:housenumber":"18",
    "addr:postcode":"cm0 8bx",
    "addr:street":"Princes Road",
    "iso:country":"GB",
    "sg:address":"18 Princes Road",
    "sg:city":"Burnham-on-crouch",
    "sg:classifiers":[
        {
            "category":"Building & Trades",
            "subcategory":"Construction",
            "type":"Services"
        }
    ],
    "sg:postcode":"CM0 8BX",
    "sg:province":"Essex",
    "sg:tags":[
        "dry",
        "lining",
        "plasterers",
        "screeders"
    ],
    "wof:name":"J W Deed",
    "wof:placetype":"venue"
},
  "geometry": {"coordinates":[0.8160229921,51.6338500977],"type":"Point"}
}