{
  "type": "Feature",
  "properties": {
    "addr:full":"Unit 16 Clydesmuir Industrial Estate, Tremorfa Cardiff Cardiff CF24 2QS",
    "addr:housenumber":"unit 16",
    "addr:postcode":"cf24 2qs",
    "addr:street":"Clydesmuir Industrial Estate",
    "iso:country":"GB",
    "sg:address":"Unit 16 Clydesmuir Industrial Estate, Tremorfa",
    "sg:city":"Cardiff",
    "sg:classifiers":[
        {
            "category":"Retail",
            "subcategory":"Auto Rental",
            "type":"Services"
        }
    ],
    "sg:phone":"+44 29 2046 2770",
    "sg:postcode":"CF24 2QS",
    "sg:province":"Cardiff",
    "sg:tags":[
        "truck",
        "hire",
        "van"
    ],
    "wof:name":"Direct Vehicle Rentals Ltd.",
    "wof:placetype":"venue"
},
  "geometry": {"coordinates":[-3.143836,51.490372],"type":"Point"}
}