{
  "type": "Feature",
  "properties": {
    "addr:full":"1a Unit Barking Business Park, 25 Thames Road Barking Essex IG11 0JP",
    "addr:housenumber":"unit;25",
    "addr:postcode":"ig11 0jp",
    "addr:street":"Business Park;Thames Road",
    "iso:country":"GB",
    "sg:address":"1a Unit Barking Business Park, 25 Thames Road",
    "sg:city":"Barking",
    "sg:classifiers":[
        {
            "category":"Government",
            "subcategory":"Office",
            "type":"Public Place"
        }
    ],
    "sg:phone":"+44 20 8507 0999",
    "sg:postcode":"IG11 0JP",
    "sg:province":"Essex",
    "sg:tags":[
        "press",
        "cutting",
        "bureau"
    ],
    "wof:name":"Cutting It Fine Ltd.",
    "wof:placetype":"venue"
},
  "geometry": {"coordinates":[0.0811149999,51.539100647],"type":"Point"}
}