{
  "type": "Feature",
  "properties": {
    "addr:full":"65 Woodhill Road, Portishead Bristol Somerset BS20 7HA",
    "addr:housenumber":"65",
    "addr:postcode":"bs20 7ha",
    "addr:street":"Woodhill Road",
    "iso:country":"GB",
    "sg:address":"65 Woodhill Road, Portishead",
    "sg:city":"Bristol",
    "sg:classifiers":[
        {
            "category":"Professional",
            "subcategory":"Engineering",
            "type":"Services"
        }
    ],
    "sg:phone":"+44 1275 843943",
    "sg:postcode":"BS20 7HA",
    "sg:province":"Somerset",
    "sg:tags":[
        "consulting",
        "engineer"
    ],
    "wof:name":"Avon Analytical Services Ltd",
    "wof:placetype":"venue"
},
  "geometry": {"coordinates":[-2.769037962,51.4914207458],"type":"Point"}
}