{
  "type": "Feature",
  "properties": {
    "iso:country":"GB",
    "sg:address":"110 The Strand, Goring By Sea",
    "sg:city":"Worthing",
    "sg:classifiers":[
        {
            "category":"Personal",
            "subcategory":"Beauty Salon",
            "type":"Services"
        }
    ],
    "sg:postcode":"BN12 6DW",
    "sg:province":"West Sussex",
    "wof:name":"Beautona",
    "wof:placetype":"venue"
},
  "geometry": {"coordinates":[-0.418898,50.819107],"type":"Point"}
}