{
  "type": "Feature",
  "properties": {
    "addr:full":", Croesgoch Haverfordwest Pembrokeshire SA62 5JP",
    "addr:postcode":"sa62 5jp",
    "addr:street":"Croesgoch;Pembrokeshire",
    "iso:country":"GB",
    "sg:address":", Croesgoch",
    "sg:city":"Haverfordwest",
    "sg:classifiers":[
        {
            "category":"Bars & Pubs",
            "type":"Food & Drink"
        }
    ],
    "sg:phone":"+44 1348 831309",
    "sg:postcode":"SA62 5JP",
    "sg:province":"Pembrokeshire",
    "sg:tags":[
        "pubs",
        "inn"
    ],
    "wof:name":"Artramont Arms",
    "wof:placetype":"venue"
},
  "geometry": {"coordinates":[-5.1608462334,51.9280433655],"type":"Point"}
}