{
  "type": "Feature",
  "properties": {
    "addr:full":"4 Douglas Street, St Milngavie Glasgow East Dunbartonshire G62 6PB",
    "addr:housenumber":"4",
    "addr:postcode":"g62 6pb",
    "addr:street":"Douglas Street",
    "iso:country":"GB",
    "sg:address":"4 Douglas Street, St Milngavie",
    "sg:city":"Glasgow",
    "sg:classifiers":[
        {
            "category":"Shopping",
            "subcategory":"Shoes",
            "type":"Retail Goods"
        }
    ],
    "sg:phone":"+44 141 956 5012",
    "sg:postcode":"G62 6PB",
    "sg:province":"East Dunbartonshire",
    "wof:name":"Minit (U K) Plc",
    "wof:placetype":"venue"
},
  "geometry": {"coordinates":[-4.319064,55.940826],"type":"Point"}
}