{
  "type": "Feature",
  "properties": {
    "addr:full":"Cobham Road Birmingham West Midlands B9 4UP",
    "addr:postcode":"b9 4up",
    "addr:street":"Cobham Road",
    "iso:country":"GB",
    "sg:address":"Cobham Road",
    "sg:city":"Birmingham",
    "sg:classifiers":[
        {
            "category":"Building & Trades",
            "subcategory":"Construction",
            "type":"Services"
        }
    ],
    "sg:phone":"+44 121 772 5956",
    "sg:postcode":"B9 4UP",
    "sg:province":"West Midlands",
    "sg:tags":[
        "welder"
    ],
    "wof:name":"T Ward",
    "wof:placetype":"venue"
},
  "geometry": {"coordinates":[-1.854654,52.480145],"type":"Point"}
}