{
  "type": "Feature",
  "properties": {
    "addr:full":"17 Main Street Pembroke Pembrokeshire SA71 4JS",
    "addr:housenumber":"17",
    "addr:postcode":"sa71 4js",
    "addr:street":"Main Street",
    "iso:country":"GB",
    "sg:address":"17 Main Street",
    "sg:city":"Pembroke",
    "sg:classifiers":[
        {
            "category":"Bars & Pubs",
            "type":"Food & Drink"
        }
    ],
    "sg:phone":"+44 1646 682883",
    "sg:postcode":"SA71 4JS",
    "sg:province":"Pembrokeshire",
    "sg:tags":[
        "pubs",
        "inn"
    ],
    "wof:name":"The Castle Inn",
    "wof:placetype":"venue"
},
  "geometry": {"coordinates":[-4.917339,51.675854],"type":"Point"}
}