{
  "type": "Feature",
  "properties": {
    "addr:full":"Whiteheads Farm, Townsend Road, Upwell Wisbech Cambridgeshire PE14 9HJ",
    "addr:postcode":"pe14 9hj",
    "addr:street":"Townsend Road",
    "iso:country":"GB",
    "sg:address":"Whiteheads Farm, Townsend Road, Upwell",
    "sg:city":"Wisbech",
    "sg:classifiers":[
        {
            "category":"Farming",
            "subcategory":"Livestock Farm",
            "type":"Manufacturing & Wholesale Goods"
        }
    ],
    "sg:phone":"+44 1945 773205",
    "sg:postcode":"PE14 9HJ",
    "sg:province":"Cambridgeshire",
    "sg:tags":[
        "others"
    ],
    "wof:name":"Laurence J  Lunn",
    "wof:placetype":"venue"
},
  "geometry": {"coordinates":[0.211009,52.598125],"type":"Point"}
}