{
  "type": "Feature",
  "properties": {
    "addr:full":"Market Way Canterbury Kent CT2 7JX",
    "addr:postcode":"ct2 7jx",
    "addr:street":"Market Way",
    "iso:country":"GB",
    "sg:address":"Market Way",
    "sg:city":"Canterbury",
    "sg:classifiers":[
        {
            "category":"Insurance",
            "subcategory":"Insurance Agent",
            "type":"Services"
        }
    ],
    "sg:phone":"+44 1227 451088",
    "sg:postcode":"CT2 7JX",
    "sg:province":"Kent",
    "wof:name":"NFU Mutual & NFU",
    "wof:placetype":"venue"
},
  "geometry": {"coordinates":[1.086055994,51.2892532349],"type":"Point"}
}