{
  "type": "Feature",
  "properties": {
    "addr:full":"6 Springbridge Road London Greater London W5 2AA",
    "addr:housenumber":"6",
    "addr:postcode":"w5 2aa",
    "addr:street":"Springbridge Road",
    "iso:country":"GB",
    "sg:address":"6 Springbridge Road",
    "sg:city":"London",
    "sg:classifiers":[
        {
            "category":"Professional",
            "type":"Services"
        },
        {
            "category":"Home & Garden",
            "subcategory":"Building Materials",
            "type":"Retail Goods"
        }
    ],
    "sg:phone":"+44 20 8579 3688",
    "sg:postcode":"W5 2AA",
    "sg:province":"Greater London",
    "sg:tags":[
        "interior",
        "furnishers",
        "bathroom",
        "designer",
        "planner"
    ],
    "wof:name":"Watercolour Bathroom Designs",
    "wof:placetype":"venue"
},
  "geometry": {"coordinates":[-0.304682,51.514004],"type":"Point"}
}