{
  "type": "Feature",
  "properties": {
    "addr:full":"Unit 1, Barons Gate, 33 Rothschild Rd Chiswick Greater London W4 5HT",
    "addr:housenumber":"unit 1;33",
    "addr:postcode":"w4 5ht",
    "addr:street":"Barons Gate;Rothschild Rd",
    "iso:country":"GB",
    "sg:address":"Unit 1, Barons Gate, 33 Rothschild Rd",
    "sg:city":"Chiswick",
    "sg:classifiers":[
        {
            "category":"Arena",
            "subcategory":"Sports Club",
            "type":"Entertainment"
        }
    ],
    "sg:phone":"+44 20 8742 3032",
    "sg:postcode":"W4 5HT",
    "sg:province":"Greater London",
    "wof:name":"Amateur Fencing Assoc.",
    "wof:placetype":"venue"
},
  "geometry": {"coordinates":[-0.2682900131,51.4977798462],"type":"Point"}
}