{
  "type": "Feature",
  "properties": {
    "addr:full":"Akenside House, 3 Akenside Hill Newcastle Upon Tyne Tyne and Wear NE1 3JA",
    "addr:housenumber":"3",
    "addr:postcode":"ne1 3ja",
    "addr:street":"Akenside Hill",
    "iso:country":"GB",
    "sg:address":"Akenside House, 3 Akenside Hill",
    "sg:city":"Newcastle Upon Tyne",
    "sg:classifiers":[
        {
            "category":"Professional",
            "subcategory":"Art Services",
            "type":"Services"
        }
    ],
    "sg:phone":"+44 191 261 6300",
    "sg:postcode":"NE1 3JA",
    "sg:province":"Tyne and Wear",
    "sg:tags":[
        "consultant",
        "design"
    ],
    "wof:name":"Akenside Traders",
    "wof:placetype":"venue"
},
  "geometry": {"coordinates":[-1.6065,54.969601],"type":"Point"}
}