{
  "type": "Feature",
  "properties": {
    "addr:full":"The Rectory Ipswich Suffolk IP9 2QZ",
    "addr:postcode":"ip9 2qz",
    "iso:country":"GB",
    "sg:address":"The Rectory",
    "sg:city":"Ipswich",
    "sg:classifiers":[
        {
            "category":"Place Of Worship",
            "type":"Public Place"
        }
    ],
    "sg:phone":"+44 1473 328900",
    "sg:postcode":"IP9 2QZ",
    "sg:province":"Suffolk",
    "wof:name":"All Saints Holbrook",
    "wof:placetype":"venue"
},
  "geometry": {"coordinates":[1.041015,52.004036],"type":"Point"}
}