{
  "type": "Feature",
  "properties": {
    "addr:full":"Beaconhill Road, Beacon Hill Hindhead Hampshire GU26 6NT",
    "addr:postcode":"gu26 6nt",
    "addr:street":"Beaconhill Road",
    "iso:country":"GB",
    "sg:address":"Beaconhill Road, Beacon Hill",
    "sg:city":"Hindhead",
    "sg:classifiers":[
        {
            "category":"Home & Garden",
            "subcategory":"Furniture",
            "type":"Retail Goods"
        }
    ],
    "sg:phone":"+44 1428 605274",
    "sg:postcode":"GU26 6NT",
    "sg:province":"Hampshire",
    "wof:name":"Hindhead Furnishing",
    "wof:placetype":"venue"
},
  "geometry": {"coordinates":[-0.7530440092,51.1226081848],"type":"Point"}
}