{
  "type": "Feature",
  "properties": {
    "addr:full":"The Old Painswick Inn, Gloucester Street Stroud Gloucestershire GL5 1QG",
    "addr:postcode":"gl5 1qg",
    "addr:street":"Gloucester Street",
    "iso:country":"GB",
    "sg:address":"The Old Painswick Inn, Gloucester Street",
    "sg:city":"Stroud",
    "sg:classifiers":[
        {
            "category":"Organizations",
            "subcategory":"Non-profit Organization",
            "type":"Services"
        }
    ],
    "sg:postcode":"GL5 1QG",
    "sg:province":"Gloucestershire",
    "sg:tags":[
        "organisation",
        "voluntary",
        "charity"
    ],
    "wof:name":"Alternatives to Violence Project  Britain",
    "wof:placetype":"venue"
},
  "geometry": {"coordinates":[-2.2096989155,51.7452964783],"type":"Point"}
}