{
  "type": "Feature",
  "properties": {
    "addr:full":"58 Chapel Market London Greater London N1 9EW",
    "addr:housenumber":"58",
    "addr:postcode":"n1 9ew",
    "addr:street":"Chapel Market",
    "iso:country":"GB",
    "sg:address":"58 Chapel Market",
    "sg:city":"London",
    "sg:classifiers":[
        {
            "category":"Shopping",
            "subcategory":"Jewelry",
            "type":"Retail Goods"
        },
        {
            "category":"Shopping",
            "subcategory":"Comic Books",
            "type":"Retail Goods"
        }
    ],
    "sg:phone":"+44 20 7278 6258",
    "sg:postcode":"N1 9EW",
    "sg:province":"Greater London",
    "sg:tags":[
        "jeweller",
        "sale",
        "jewellery"
    ],
    "wof:name":"Islington Discount Jewellers",
    "wof:placetype":"venue"
},
  "geometry": {"coordinates":[-0.1080069989,51.5334968567],"type":"Point"}
}