{
  "type": "Feature",
  "properties": {
    "iso:country":"GB",
    "sg:address":"Ten Perch Road, Wincheap",
    "sg:city":"Canterbury",
    "sg:classifiers":[
        {
            "category":"Shopping",
            "type":"Retail Goods"
        }
    ],
    "sg:phone":"+44 1227 786006",
    "sg:postcode":"CT1 3TQ",
    "sg:province":"Kent",
    "sg:tags":[
        "part",
        "accessory"
    ],
    "wof:name":"Halfords Superstore",
    "wof:placetype":"venue"
},
  "geometry": {"coordinates":[1.070634,51.272449],"type":"Point"}
}