{
  "type": "Feature",
  "properties": {
    "addr:full":"30 Pillory Street Nantwich Cheshire CW5 5BG",
    "addr:housenumber":"30",
    "addr:postcode":"cw5 5bg",
    "addr:street":"Pillory Street",
    "iso:country":"GB",
    "sg:address":"30 Pillory Street",
    "sg:city":"Nantwich",
    "sg:classifiers":[
        {
            "category":"Home & Garden",
            "subcategory":"Home Furnishings",
            "type":"Retail Goods"
        },
        {
            "category":"Home & Garden",
            "subcategory":"Furniture",
            "type":"Retail Goods"
        }
    ],
    "sg:phone":"+44 1270 610707",
    "sg:postcode":"CW5 5BG",
    "sg:province":"Cheshire",
    "sg:tags":[
        "mantelpiece",
        "fireplace"
    ],
    "wof:name":"Gas Flame Centre",
    "wof:placetype":"venue"
},
  "geometry": {"coordinates":[-2.5214390755,53.0657463074],"type":"Point"}
}