{
  "type": "Feature",
  "properties": {
    "addr:full":"22 Morrison Dr Doncaster South Yorkshire DN11 0BB",
    "addr:housenumber":"22",
    "addr:postcode":"dn11 0bb",
    "addr:street":"Morrison Dr",
    "iso:country":"GB",
    "sg:address":"22 Morrison Dr",
    "sg:city":"Doncaster",
    "sg:classifiers":[
        {
            "category":"Building & Trades",
            "subcategory":"Construction",
            "type":"Services"
        }
    ],
    "sg:phone":"+44 1302 865272",
    "sg:postcode":"DN11 0BB",
    "sg:province":"South Yorkshire",
    "sg:tags":[
        "builder"
    ],
    "wof:name":"J & J Builders",
    "wof:placetype":"venue"
},
  "geometry": {"coordinates":[-1.0659990311,53.4735221863],"type":"Point"}
}