{
  "type": "Feature",
  "properties": {
    "addr:full":"Ditchling Common Burgess Hill East Sussex RH15 0SE",
    "addr:postcode":"rh15 0se",
    "addr:street":"Burgess Hill",
    "iso:country":"GB",
    "sg:address":"Ditchling Common",
    "sg:city":"Burgess Hill",
    "sg:classifiers":[
        {
            "category":"Sports & Exercise",
            "subcategory":"Stables",
            "type":"Entertainment"
        }
    ],
    "sg:phone":"+44 1444 236678",
    "sg:postcode":"RH15 0SE",
    "sg:province":"East Sussex",
    "sg:tags":[
        "education",
        "equestrian"
    ],
    "wof:name":"Ditchling Common Stud",
    "wof:placetype":"venue"
},
  "geometry": {"coordinates":[-0.139174,50.95533],"type":"Point"}
}