{
  "type": "Feature",
  "properties": {
    "iso:country":"GB",
    "sg:address":"11 Hebden Road",
    "sg:city":"Scunthorpe",
    "sg:classifiers":[
        {
            "category":"Structure",
            "subcategory":"Warehouse",
            "type":"Public Place"
        }
    ],
    "sg:phone":"+44 1724 864242",
    "sg:postcode":"DN15 8PT",
    "sg:province":"Lincolnshire",
    "wof:name":"Scunthorpe Forwarding Ltd.",
    "wof:placetype":"venue"
},
  "geometry": {"coordinates":[-0.682243,53.598434],"type":"Point"}
}