{
  "type": "Feature",
  "properties": {
    "addr:full":"Forest Edge 22 Salisbury Rd, Burton Christchurch Dorset BH23 7JQ",
    "addr:housenumber":"22",
    "addr:postcode":"bh23 7jq",
    "addr:street":"Forest;Salisbury Rd",
    "iso:country":"GB",
    "sg:address":"Forest Edge 22 Salisbury Rd, Burton",
    "sg:city":"Christchurch",
    "sg:classifiers":[
        {
            "category":"Professional",
            "subcategory":"Detective & Security Services",
            "type":"Services"
        }
    ],
    "sg:phone":"+44 1202 486661",
    "sg:postcode":"BH23 7JQ",
    "sg:province":"Dorset",
    "wof:name":"Sterling Security",
    "wof:placetype":"venue"
},
  "geometry": {"coordinates":[-1.77254498,50.7502822876],"type":"Point"}
}