{
  "type": "Feature",
  "properties": {
    "addr:full":"16a High St Kenilworth Warwickshire CV8 1LZ",
    "addr:housenumber":"16a",
    "addr:postcode":"cv8 1lz",
    "addr:street":"High St",
    "iso:country":"GB",
    "sg:address":"16a High St",
    "sg:city":"Kenilworth",
    "sg:classifiers":[
        {
            "category":"Home & Garden",
            "subcategory":"Kitchen Supply",
            "type":"Retail Goods"
        }
    ],
    "sg:phone":"+44 1926 850801",
    "sg:postcode":"CV8 1LZ",
    "sg:province":"Warwickshire",
    "sg:tags":[
        "table"
    ],
    "wof:name":"Simpsons Cookshop & Homestore",
    "wof:placetype":"venue"
},
  "geometry": {"coordinates":[-1.5821709633,52.3499565125],"type":"Point"}
}