{
  "type": "Feature",
  "properties": {
    "addr:full":"62 Austin Av Poole Dorset BH14 8HE",
    "addr:housenumber":"62",
    "addr:postcode":"bh14 8he",
    "addr:street":"Austin Av",
    "iso:country":"GB",
    "sg:address":"62 Austin Av",
    "sg:city":"Poole",
    "sg:classifiers":[
        {
            "category":"Professional",
            "subcategory":"Engineering",
            "type":"Services"
        }
    ],
    "sg:phone":"+44 1202 700663",
    "sg:postcode":"BH14 8HE",
    "sg:province":"Dorset",
    "sg:tags":[
        "contractor",
        "electrical",
        "engineer"
    ],
    "wof:name":"Keygrid Ltd",
    "wof:placetype":"venue"
},
  "geometry": {"coordinates":[-1.947453022,50.7116165161],"type":"Point"}
}