{
  "type": "Feature",
  "properties": {
    "addr:full":"Turnbull Court, Langtongate Duns East Lothian TD11 3BL",
    "addr:postcode":"td11 3bl",
    "addr:street":"Turnbull;Langtongate",
    "iso:country":"GB",
    "sg:address":"Turnbull Court, Langtongate",
    "sg:city":"Duns",
    "sg:classifiers":[
        {
            "category":"Organizations",
            "subcategory":"Community Association",
            "type":"Services"
        }
    ],
    "sg:phone":"+44 1361 882373",
    "sg:postcode":"TD11 3BL",
    "sg:province":"East Lothian",
    "sg:tags":[
        "society",
        "housing"
    ],
    "wof:name":"Bield Housing Association Ltd.",
    "wof:placetype":"venue"
},
  "geometry": {"coordinates":[-2.3478140831,55.7769241333],"type":"Point"}
}