{
  "type": "Feature",
  "properties": {
    "addr:full":"53 Highland Rd Waltham Abbey Essex EN9 2PU",
    "addr:housenumber":"53",
    "addr:postcode":"en9 2pu",
    "addr:street":"Highland Rd;Abbey",
    "iso:country":"GB",
    "sg:address":"53 Highland Rd",
    "sg:city":"Waltham Abbey",
    "sg:classifiers":[
        {
            "category":"Wholesale",
            "subcategory":"Furniture",
            "type":"Manufacturing & Wholesale Goods"
        }
    ],
    "sg:phone":"+44 1992 892898",
    "sg:postcode":"EN9 2PU",
    "sg:province":"Essex",
    "sg:tags":[
        "shop",
        "fitting"
    ],
    "wof:name":"Hertford Shelving & Displays",
    "wof:placetype":"venue"
},
  "geometry": {"coordinates":[0.01357,51.738495],"type":"Point"}
}