{
  "type": "Feature",
  "properties": {
    "iso:country":"GB",
    "sg:address":"The Glebe Hall, Church Square",
    "sg:city":"Basingstoke",
    "sg:classifiers":[
        {
            "category":"Organizations",
            "subcategory":"Non-profit Organization",
            "type":"Services"
        }
    ],
    "sg:phone":"+44 1256 332424",
    "sg:postcode":"RG21 7QW",
    "sg:province":"Hampshire",
    "sg:tags":[
        "organisation",
        "voluntary",
        "charity"
    ],
    "wof:name":"Basingstoke Neighbour Care",
    "wof:placetype":"venue"
},
  "geometry": {"coordinates":[-1.083089,51.262444],"type":"Point"}
}