{
  "type": "Feature",
  "properties": {
    "iso:country":"GB",
    "sg:address":"12 Hardwick Street",
    "sg:city":"Buxton",
    "sg:classifiers":[
        {
            "category":"Professional",
            "subcategory":"Lawyer & Legal Services",
            "type":"Services"
        }
    ],
    "sg:phone":"+44 1298 22874",
    "sg:postcode":"SK17 6BN",
    "sg:province":"Derbyshire",
    "sg:tags":[
        "solicitor"
    ],
    "wof:name":"The Prickett Partnership",
    "wof:placetype":"venue"
},
  "geometry": {"coordinates":[-1.911798954,53.2589454651],"type":"Point"}
}