{
  "type": "Feature",
  "properties": {
    "iso:country":"GB",
    "sg:address":"52 Willenhall Rd",
    "sg:city":"Bilston",
    "sg:classifiers":[
        {
            "category":"Health Services",
            "subcategory":"Nursing And Care Facility",
            "type":"Services"
        }
    ],
    "sg:phone":"+44 1902 408800",
    "sg:postcode":"WV14 6NW",
    "sg:province":"West Midlands",
    "sg:tags":[
        "home"
    ],
    "wof:name":"Midland Homecare",
    "wof:placetype":"venue"
},
  "geometry": {"coordinates":[-2.065184,52.571373],"type":"Point"}
}