{
  "type": "Feature",
  "properties": {
    "addr:full":"49 Spencer Avenue Hayes Greater London UB4 0QY",
    "addr:housenumber":"49",
    "addr:postcode":"ub4 0qy",
    "addr:street":"Spencer Avenue",
    "iso:country":"GB",
    "sg:address":"49 Spencer Avenue",
    "sg:city":"Hayes",
    "sg:classifiers":[
        {
            "category":"Home & Garden",
            "subcategory":"Household Appliances",
            "type":"Retail Goods"
        }
    ],
    "sg:postcode":"UB4 0QY",
    "sg:province":"Greater London",
    "sg:tags":[
        "electrical"
    ],
    "wof:name":"E J Coombes",
    "wof:placetype":"venue"
},
  "geometry": {"coordinates":[-0.412669,51.522106],"type":"Point"}
}