{
  "type": "Feature",
  "properties": {
    "iso:country":"GB",
    "sg:address":"49 Church Street",
    "sg:city":"Seaham",
    "sg:classifiers":[
        {
            "category":"Shopping",
            "subcategory":"News",
            "type":"Retail Goods"
        }
    ],
    "sg:phone":"+44 191 581 6481",
    "sg:postcode":"SR7 7HF",
    "sg:province":"Durham",
    "sg:tags":[
        "newsagent"
    ],
    "wof:name":"Foggins",
    "wof:placetype":"venue"
},
  "geometry": {"coordinates":[-1.335427,54.837158],"type":"Point"}
}