{
  "type": "Feature",
  "properties": {
    "iso:country":"GB",
    "sg:address":"Townfoot, Cumwhitton",
    "sg:city":"Brampton",
    "sg:classifiers":[
        {
            "category":"Farming",
            "subcategory":"Farm",
            "type":"Manufacturing & Wholesale Goods"
        }
    ],
    "sg:postcode":"CA8 9EX",
    "sg:province":"Cumbria",
    "sg:tags":[
        "mixed",
        "crop"
    ],
    "wof:name":"H & W G Robley",
    "wof:placetype":"venue"
},
  "geometry": {"coordinates":[-2.7685940266,54.865436554],"type":"Point"}
}