{
  "type": "Feature",
  "properties": {
    "addr:full":"52 Bromsgrove St Birmingham West Midlands B5 6PY",
    "addr:housenumber":"52",
    "addr:postcode":"b5 6py",
    "addr:street":"Bromsgrove St",
    "iso:country":"GB",
    "sg:address":"52 Bromsgrove St",
    "sg:city":"Birmingham",
    "sg:classifiers":[
        {
            "category":"Shopping",
            "subcategory":"Antiques",
            "type":"Retail Goods"
        }
    ],
    "sg:postcode":"B5 6PY",
    "sg:province":"West Midlands",
    "wof:name":"Squires Architectural Antiques",
    "wof:placetype":"venue"
},
  "geometry": {"coordinates":[-1.89624,52.47348],"type":"Point"}
}