{
  "type": "Feature",
  "properties": {
    "addr:full":"9 Almondvale Retail Park, Almondvale South Livingston West Lothian EH54 6RQ",
    "addr:housenumber":"9",
    "addr:postcode":"eh54 6rq",
    "addr:street":"Almondvale Retail Park Almondvale South",
    "iso:country":"GB",
    "sg:address":"9 Almondvale Retail Park, Almondvale South",
    "sg:city":"Livingston",
    "sg:classifiers":[
        {
            "category":"Shopping",
            "type":"Retail Goods"
        }
    ],
    "sg:phone":"+44 1506 419380",
    "sg:postcode":"EH54 6RQ",
    "sg:province":"West Lothian",
    "sg:tags":[
        "part",
        "accessory"
    ],
    "wof:name":"Halfords Superstore",
    "wof:placetype":"venue"
},
  "geometry": {"coordinates":[-3.5098340511,55.8862457275],"type":"Point"}
}