{
  "type": "Feature",
  "properties": {
    "addr:full":"Llwyncelyn Farm, Cantref Brecon Powys LD3 8LW",
    "addr:postcode":"ld3 8lw",
    "iso:country":"GB",
    "sg:address":"Llwyncelyn Farm, Cantref",
    "sg:city":"Brecon",
    "sg:classifiers":[
        {
            "category":"Farming",
            "subcategory":"Livestock Farm",
            "type":"Manufacturing & Wholesale Goods"
        }
    ],
    "sg:phone":"+44 1874 665256",
    "sg:postcode":"LD3 8LW",
    "sg:province":"Powys",
    "sg:tags":[
        "others"
    ],
    "wof:name":"June & Ian T Matthews",
    "wof:placetype":"venue"
},
  "geometry": {"coordinates":[-3.389515,51.929649],"type":"Point"}
}