{
  "type": "Feature",
  "properties": {
    "iso:country":"GB",
    "sg:address":"47 Oxford Road",
    "sg:city":"Reading",
    "sg:classifiers":[
        {
            "category":"Shopping",
            "subcategory":"Catalog Store",
            "type":"Retail Goods"
        }
    ],
    "sg:phone":"+44 118 950 2030",
    "sg:postcode":"RG1 7QG",
    "sg:province":"Berkshire",
    "sg:tags":[
        "catalogue",
        "showroom"
    ],
    "wof:name":"Argos Distributors",
    "wof:placetype":"venue"
},
  "geometry": {"coordinates":[-0.977334,51.455132],"type":"Point"}
}