{
  "type": "Feature",
  "properties": {
    "addr:full":"14 School Lane Petersfield Hampshire GU32 2AS",
    "addr:housenumber":"14",
    "addr:postcode":"gu32 2as",
    "addr:street":"School Lane",
    "iso:country":"GB",
    "sg:address":"14 School Lane",
    "sg:city":"Petersfield",
    "sg:classifiers":[
        {
            "category":"Professional",
            "subcategory":"Engineering",
            "type":"Services"
        }
    ],
    "sg:phone":"+44 1730 266099",
    "sg:postcode":"GU32 2AS",
    "sg:province":"Hampshire",
    "sg:tags":[
        "gas",
        "engineer"
    ],
    "wof:name":"J P H Heating",
    "wof:placetype":"venue"
},
  "geometry": {"coordinates":[-0.922516,51.015907],"type":"Point"}
}