{
  "type": "Feature",
  "properties": {
    "iso:country":"GB",
    "sg:address":"14 Edgecumbe Avenue",
    "sg:city":"Newquay",
    "sg:classifiers":[
        {
            "category":"Travel",
            "subcategory":"Hotels & Motels",
            "type":"Entertainment"
        }
    ],
    "sg:phone":"+44 1637 877635",
    "sg:postcode":"TR7 2NH",
    "sg:province":"Cornwall",
    "sg:tags":[
        "house",
        "guest"
    ],
    "wof:name":"West Side Stop",
    "wof:placetype":"venue"
},
  "geometry": {"coordinates":[-5.074301,50.41592],"type":"Point"}
}