{
  "type": "Feature",
  "properties": {
    "iso:country":"GB",
    "sg:address":"155 Glaisdale Drive West, Bilborough",
    "sg:city":"Nottingham",
    "sg:classifiers":[
        {
            "category":"Home & Garden",
            "subcategory":"Home Furnishings",
            "type":"Retail Goods"
        }
    ],
    "sg:phone":"+44 115 928 5724",
    "sg:postcode":"NG8 4GY",
    "sg:province":"Nottinghamshire",
    "sg:tags":[
        "tube",
        "fitting",
        "stockist"
    ],
    "wof:name":"Frazer Ashworth (East Midlands) Ltd.",
    "wof:placetype":"venue"
},
  "geometry": {"coordinates":[-1.233953,52.957211],"type":"Point"}
}