{
  "type": "Feature",
  "properties": {
    "iso:country":"GB",
    "sg:address":"71 Foryd Road, Kinmel Bay",
    "sg:city":"Rhyl",
    "sg:classifiers":[
        {
            "category":"Restaurant",
            "type":"Food & Drink"
        }
    ],
    "sg:phone":"+44 1745 336861",
    "sg:postcode":"LL18 5BB",
    "sg:province":"Conwy",
    "sg:tags":[
        "-",
        "chinese"
    ],
    "wof:name":"China City Restaurant",
    "wof:placetype":"venue"
},
  "geometry": {"coordinates":[-3.517638,53.311321],"type":"Point"}
}