{
  "type": "Feature",
  "properties": {
    "addr:full":"Fetcham Gro, Guildford Road, Fetcham Leatherhead Surrey KT22 9AS",
    "addr:postcode":"kt22 9as",
    "addr:street":"Gro Guildford Road",
    "iso:country":"GB",
    "sg:address":"Fetcham Gro, Guildford Road, Fetcham",
    "sg:city":"Leatherhead",
    "sg:classifiers":[
        {
            "category":"Bars & Pubs",
            "subcategory":"Nightclub",
            "type":"Food & Drink"
        },
        {
            "category":"Arena",
            "subcategory":"Sports Club",
            "type":"Entertainment"
        }
    ],
    "sg:phone":"+44 1372 360151",
    "sg:postcode":"KT22 9AS",
    "sg:province":"Surrey",
    "sg:tags":[
        "night"
    ],
    "wof:name":"Leatherhead Football Club Ltd.",
    "wof:placetype":"venue"
},
  "geometry": {"coordinates":[-0.345965,51.284187],"type":"Point"}
}