{
  "type": "Feature",
  "properties": {
    "addr:full":"202 Harrington Road Workington Cumbria CA14 3UJ",
    "addr:housenumber":"202",
    "addr:postcode":"ca14 3uj",
    "addr:street":"Harrington Road",
    "iso:country":"GB",
    "sg:address":"202 Harrington Road",
    "sg:city":"Workington",
    "sg:classifiers":[
        {
            "category":"Shopping",
            "subcategory":"Department Store",
            "type":"Retail Goods"
        }
    ],
    "sg:postcode":"CA14 3UJ",
    "sg:province":"Cumbria",
    "wof:name":"Martins General Store",
    "wof:placetype":"venue"
},
  "geometry": {"coordinates":[-3.553401,54.638039],"type":"Point"}
}