{
  "type": "Feature",
  "properties": {
    "addr:full":"Care Of Kiwk Save, Broad St Bristol City of Bristol BS16 5LN",
    "addr:postcode":"bs16 5ln",
    "addr:street":"Broad St",
    "iso:country":"GB",
    "sg:address":"Care Of Kiwk Save, Broad St",
    "sg:city":"Bristol",
    "sg:classifiers":[
        {
            "category":"Food & Beverages",
            "subcategory":"Meat & Fish",
            "type":"Retail Goods"
        }
    ],
    "sg:phone":"+44 117 957 5800",
    "sg:postcode":"BS16 5LN",
    "sg:province":"City of Bristol",
    "sg:tags":[
        "butcher"
    ],
    "wof:name":"M R Gay",
    "wof:placetype":"venue"
},
  "geometry": {"coordinates":[-2.591429,51.453667],"type":"Point"}
}