{
  "type": "Feature",
  "properties": {
    "iso:country":"GB",
    "sg:address":"18 Mayditch Pl",
    "sg:city":"Milton Keynes",
    "sg:classifiers":[
        {
            "category":"Building & Trades",
            "subcategory":"Construction",
            "type":"Services"
        }
    ],
    "sg:phone":"+44 1908 607071",
    "sg:postcode":"MK13 8DU",
    "sg:province":"Buckinghamshire",
    "sg:tags":[
        "glass",
        "replacement"
    ],
    "wof:name":"Bradwell Glass",
    "wof:placetype":"venue"
},
  "geometry": {"coordinates":[-0.77408,52.045349],"type":"Point"}
}