{
  "type": "Feature",
  "properties": {
    "addr:full":"42 High Street, Harriseahead Stoke-on-trent Cheshire ST7 4JT",
    "addr:housenumber":"42",
    "addr:postcode":"st7 4jt",
    "addr:street":"High Street",
    "iso:country":"GB",
    "sg:address":"42 High Street, Harriseahead",
    "sg:city":"Stoke-on-trent",
    "sg:classifiers":[
        {
            "category":"Bars & Pubs",
            "type":"Food & Drink"
        }
    ],
    "sg:postcode":"ST7 4JT",
    "sg:province":"Cheshire",
    "sg:tags":[
        "pubs",
        "inn"
    ],
    "wof:name":"The Royal Oak",
    "wof:placetype":"venue"
},
  "geometry": {"coordinates":[-2.2081620693,53.1007995605],"type":"Point"}
}