{
  "type": "Feature",
  "properties": {
    "addr:full":"Building, 9, Unit 5, Windmill Lane, Denton Manchester Greater Manchester M34 3QS",
    "addr:housenumber":"5",
    "addr:postcode":"m34 3qs",
    "addr:street":"Windmill Lane",
    "iso:country":"GB",
    "sg:address":"Building, 9, Unit 5, Windmill Lane, Denton",
    "sg:city":"Manchester",
    "sg:classifiers":[
        {
            "category":"Home & Garden",
            "subcategory":"Home Furnishings",
            "type":"Retail Goods"
        }
    ],
    "sg:phone":"+44 161 320 8899",
    "sg:postcode":"M34 3QS",
    "sg:province":"Greater Manchester",
    "sg:tags":[
        "blind",
        "curtain",
        "fitting"
    ],
    "wof:name":"Revlou Blinds",
    "wof:placetype":"venue"
},
  "geometry": {"coordinates":[-2.122496,53.455463],"type":"Point"}
}