{
  "type": "Feature",
  "properties": {
    "iso:country":"GB",
    "sg:address":"Kelly Street",
    "sg:city":"Prescot",
    "sg:classifiers":[
        {
            "category":"Retail",
            "subcategory":"Funeral Services",
            "type":"Services"
        }
    ],
    "sg:phone":"+44 151 426 6125",
    "sg:postcode":"L34 5RJ",
    "sg:province":"Merseyside",
    "sg:tags":[
        "mnfr",
        "monumental",
        "mason"
    ],
    "wof:name":"T Lyon & Son",
    "wof:placetype":"venue"
},
  "geometry": {"coordinates":[-2.798622,53.428143],"type":"Point"}
}