{
  "type": "Feature",
  "properties": {
    "iso:country":"GB",
    "sg:address":"202 Spies Lane",
    "sg:city":"Halesowen",
    "sg:classifiers":[
        {
            "category":"Food & Beverages",
            "subcategory":"Liquor & Beverages",
            "type":"Retail Goods"
        }
    ],
    "sg:phone":"+44 121 423 3640",
    "sg:postcode":"B62 9SW",
    "sg:province":"West Midlands",
    "sg:tags":[
        "beer",
        "spirit",
        "wines"
    ],
    "wof:name":"Victoria Wine",
    "wof:placetype":"venue"
},
  "geometry": {"coordinates":[-2.018645,52.458553],"type":"Point"}
}