{
  "type": "Feature",
  "properties": {
    "iso:country":"GB",
    "sg:address":"220 Kingsway, St George",
    "sg:city":"Bristol",
    "sg:classifiers":[
        {
            "category":"Shopping",
            "type":"Retail Goods"
        }
    ],
    "sg:postcode":"BS5 8NS",
    "sg:province":"City of Bristol",
    "sg:tags":[
        "part",
        "accessory"
    ],
    "wof:name":"Karparts Kingsway",
    "wof:placetype":"venue"
},
  "geometry": {"coordinates":[-2.52480793,51.4550552368],"type":"Point"}
}