{
  "type": "Feature",
  "properties": {
    "iso:country":"GB",
    "sg:address":"10 Hamilton Road",
    "sg:city":"Deeside",
    "sg:classifiers":[
        {
            "category":"Social Services",
            "subcategory":"Adult Care",
            "type":"Services"
        },
        {
            "category":"Government",
            "subcategory":"Office",
            "type":"Public Place"
        }
    ],
    "sg:phone":"+44 1244 819781",
    "sg:postcode":"CH5 4XB",
    "sg:province":"Flintshire",
    "sg:tags":[
        "housing",
        "local",
        "sheltered"
    ],
    "wof:name":"Lower Brook Street Shetltered Housing",
    "wof:placetype":"venue"
},
  "geometry": {"coordinates":[-3.067540884,53.2226066589],"type":"Point"}
}