{
  "type": "Feature",
  "properties": {
    "addr:full":"M S M Vehicles, Holyhead Road Shrewsbury Shropshire SY4 1AY",
    "addr:postcode":"sy4 1ay",
    "addr:street":"Holyhead Road",
    "iso:country":"GB",
    "sg:address":"M S M Vehicles, Holyhead Road",
    "sg:city":"Shrewsbury",
    "sg:classifiers":[
        {
            "category":"Autos & Motor Vehicles",
            "subcategory":"Automobile Sales",
            "type":"Retail Goods"
        }
    ],
    "sg:phone":"+44 1743 741399",
    "sg:postcode":"SY4 1AY",
    "sg:province":"Shropshire",
    "sg:tags":[
        "commercial"
    ],
    "wof:name":"M S M Vehicles Ltd.",
    "wof:placetype":"venue"
},
  "geometry": {"coordinates":[-2.9332098961,52.7807617188],"type":"Point"}
}