{
  "type": "Feature",
  "properties": {
    "addr:full":"23c Old St Clerkenwell Greater London EC1V 9HG",
    "addr:housenumber":"23c",
    "addr:postcode":"ec1v 9hg",
    "addr:street":"Old St",
    "iso:country":"GB",
    "sg:address":"23c Old St",
    "sg:city":"Clerkenwell",
    "sg:classifiers":[
        {
            "category":"Professional",
            "subcategory":"Art Services",
            "type":"Services"
        }
    ],
    "sg:phone":"+44 20 7250 4123",
    "sg:postcode":"EC1V 9HG",
    "sg:province":"Greater London",
    "sg:tags":[
        "consultant",
        "design"
    ],
    "wof:name":"Amalgam",
    "wof:placetype":"venue"
},
  "geometry": {"coordinates":[-0.0977379978,51.5237045288],"type":"Point"}
}