{
  "type": "Feature",
  "properties": {
    "addr:full":"High Street, Tilshead Salisbury Wiltshire SP3 4RX",
    "addr:postcode":"sp3 4rx",
    "addr:street":"High Street",
    "iso:country":"GB",
    "sg:address":"High Street, Tilshead",
    "sg:city":"Salisbury",
    "sg:classifiers":[
        {
            "category":"Communications",
            "subcategory":"Television Station",
            "type":"Services"
        }
    ],
    "sg:phone":"+44 1980 621295",
    "sg:postcode":"SP3 4RX",
    "sg:province":"Wiltshire",
    "sg:tags":[
        "video"
    ],
    "wof:name":"International Defence Electronics",
    "wof:placetype":"venue"
},
  "geometry": {"coordinates":[-1.899375,51.152374],"type":"Point"}
}