{
  "type": "Feature",
  "properties": {
    "iso:country":"GB",
    "sg:address":"82 Chaplin Road",
    "sg:city":"London",
    "sg:classifiers":[
        {
            "category":"Communications",
            "subcategory":"Film & Video Production",
            "type":"Services"
        }
    ],
    "sg:postcode":"NW2 5PR",
    "sg:province":"Greater London",
    "sg:tags":[
        "recording",
        "studio"
    ],
    "wof:name":"Alleycats Ltd",
    "wof:placetype":"venue"
},
  "geometry": {"coordinates":[-0.237785,51.549255],"type":"Point"}
}