{
  "type": "Feature",
  "properties": {
    "addr:full":"35 Knightsbridge Business Centre, Knightsbridge Green Cheltenham Gloucestershire GL51 9TA",
    "addr:housenumber":"35;business",
    "addr:postcode":"gl51 9ta",
    "addr:street":"Knightsbridge;Knightsbridge Green",
    "iso:country":"GB",
    "sg:address":"35 Knightsbridge Business Centre, Knightsbridge Green",
    "sg:city":"Cheltenham",
    "sg:classifiers":[
        {
            "category":"Communications",
            "type":"Services"
        }
    ],
    "sg:postcode":"GL51 9TA",
    "sg:province":"Gloucestershire",
    "sg:tags":[
        "data",
        "network"
    ],
    "wof:name":"A B Comtel Ltd.",
    "wof:placetype":"venue"
},
  "geometry": {"coordinates":[-2.156774,51.939156],"type":"Point"}
}