{
  "type": "Feature",
  "properties": {
    "addr:full":"3 Kennett House, Tadmarton Road, Bloxham Banbury Oxfordshire OX15 4HX",
    "addr:housenumber":"3",
    "addr:postcode":"ox15 4hx",
    "addr:street":"Tadmarton Road",
    "iso:country":"GB",
    "sg:address":"3 Kennett House, Tadmarton Road, Bloxham",
    "sg:city":"Banbury",
    "sg:classifiers":[
        {
            "category":"Professional",
            "subcategory":"Management & Consulting",
            "type":"Services"
        }
    ],
    "sg:phone":"+44 1295 721144",
    "sg:postcode":"OX15 4HX",
    "sg:province":"Oxfordshire",
    "sg:tags":[
        "consultant",
        "business"
    ],
    "wof:name":"P G Powell Electrical",
    "wof:placetype":"venue"
},
  "geometry": {"coordinates":[-1.3757590055,52.016834259],"type":"Point"}
}