{
  "type": "Feature",
  "properties": {
    "addr:full":"The Workshop, Curzon Street, Saltney Chester Cheshire CH4 8BP",
    "addr:postcode":"ch4 8bp",
    "addr:street":"Curzon Street",
    "iso:country":"GB",
    "sg:address":"The Workshop, Curzon Street, Saltney",
    "sg:city":"Chester",
    "sg:classifiers":[
        {
            "category":"Building & Trades",
            "subcategory":"Construction",
            "type":"Services"
        }
    ],
    "sg:phone":"+44 1244 682100",
    "sg:postcode":"CH4 8BP",
    "sg:province":"Cheshire",
    "sg:tags":[
        "flooring"
    ],
    "wof:name":"Wilmac Flooring Co.",
    "wof:placetype":"venue"
},
  "geometry": {"coordinates":[-2.894370079,53.188129425],"type":"Point"}
}