{
  "type": "Feature",
  "properties": {
    "addr:full":"2 Abbey Rd, Park Royal London Greater London NW10 7BS",
    "addr:housenumber":"2",
    "addr:postcode":"nw10 7bs",
    "addr:street":"Abbey",
    "iso:country":"GB",
    "sg:address":"2 Abbey Rd, Park Royal",
    "sg:city":"London",
    "sg:classifiers":[
        {
            "category":"Manufacturing",
            "subcategory":"Food",
            "type":"Manufacturing & Wholesale Goods"
        }
    ],
    "sg:phone":"+44 20 8453 1234",
    "sg:postcode":"NW10 7BS",
    "sg:province":"Greater London",
    "sg:tags":[
        "miller",
        "mill"
    ],
    "wof:name":"Bestway Milling Ltd",
    "wof:placetype":"venue"
},
  "geometry": {"coordinates":[-0.27389,51.539501],"type":"Point"}
}