{
  "type": "Feature",
  "properties": {
    "iso:country":"GB",
    "sg:address":"10a Hill Avenue",
    "sg:city":"Amersham",
    "sg:classifiers":[
        {
            "category":"Shopping",
            "subcategory":"Shoes",
            "type":"Retail Goods"
        }
    ],
    "sg:postcode":"HP6 5PW",
    "sg:province":"Buckinghamshire",
    "wof:name":"J D Finnigan",
    "wof:placetype":"venue"
},
  "geometry": {"coordinates":[-0.607837975,51.6754837036],"type":"Point"}
}