{
  "type": "Feature",
  "properties": {
    "addr:full":"69 Drumlanrig St Thornhill Dumfries and Galloway DG3 5LY",
    "addr:housenumber":"69",
    "addr:postcode":"dg3 5ly",
    "addr:street":"Drumlanrig St",
    "iso:country":"GB",
    "sg:address":"69 Drumlanrig St",
    "sg:city":"Thornhill",
    "sg:classifiers":[
        {
            "category":"Home & Garden",
            "subcategory":"Home Furnishings",
            "type":"Retail Goods"
        },
        {
            "category":"Home & Garden",
            "subcategory":"Furniture",
            "type":"Retail Goods"
        }
    ],
    "sg:phone":"+44 1848 331002",
    "sg:postcode":"DG3 5LY",
    "sg:province":"Dumfries and Galloway",
    "sg:tags":[
        "blind",
        "curtain",
        "fitting"
    ],
    "wof:name":"Clark,Josephine,",
    "wof:placetype":"venue"
},
  "geometry": {"coordinates":[-3.763588,55.239895],"type":"Point"}
}