{
  "type": "Feature",
  "properties": {
    "addr:full":"Highfield Road Ilfracombe Devon EX34 9LB",
    "addr:postcode":"ex34 9lb",
    "addr:street":"Highfield Road",
    "iso:country":"GB",
    "sg:address":"Highfield Road",
    "sg:city":"Ilfracombe",
    "sg:classifiers":[
        {
            "category":"Shopping",
            "subcategory":"Department Store",
            "type":"Retail Goods"
        },
        {
            "category":"Food & Beverages",
            "subcategory":"Groceries & Convenience Stores",
            "type":"Retail Goods"
        }
    ],
    "sg:phone":"+44 1271 862313",
    "sg:postcode":"EX34 9LB",
    "sg:province":"Devon",
    "wof:name":"Highfield Stores",
    "wof:placetype":"venue"
},
  "geometry": {"coordinates":[-4.116401,51.206924],"type":"Point"}
}