{
  "type": "Feature",
  "properties": {
    "addr:full":"69 Whitton Road Hounslow Greater London TW3 2DG",
    "addr:housenumber":"69",
    "addr:postcode":"tw3 2dg",
    "addr:street":"Whitton Road",
    "iso:country":"GB",
    "sg:address":"69 Whitton Road",
    "sg:city":"Hounslow",
    "sg:classifiers":[
        {
            "category":"Retail",
            "subcategory":"Auto Repair",
            "type":"Services"
        }
    ],
    "sg:phone":"+44 20 8572 0213",
    "sg:postcode":"TW3 2DG",
    "sg:province":"Greater London",
    "sg:tags":[
        "body",
        "car"
    ],
    "wof:name":"North Star Garage Ltd.",
    "wof:placetype":"venue"
},
  "geometry": {"coordinates":[-0.3629,51.462669],"type":"Point"}
}