{
  "type": "Feature",
  "properties": {
    "addr:full":"Fund Raising Line, 427a Oldham Road Rochdale Lancashire OL16 4PZ",
    "addr:housenumber":"427a",
    "addr:postcode":"ol16 4pz",
    "addr:street":"Raising Line;Oldham Road",
    "iso:country":"GB",
    "sg:address":"Fund Raising Line, 427a Oldham Road",
    "sg:city":"Rochdale",
    "sg:classifiers":[
        {
            "category":"Health Services",
            "subcategory":"Hospice",
            "type":"Services"
        }
    ],
    "sg:phone":"+44 1706 711144",
    "sg:postcode":"OL16 4PZ",
    "sg:province":"Lancashire",
    "wof:name":"Springhill Hospice",
    "wof:placetype":"venue"
},
  "geometry": {"coordinates":[-2.1392400265,53.597530365],"type":"Point"}
}