{
  "type": "Feature",
  "properties": {
    "addr:full":"Garthddulwyd Fach Llanarth Ceredigion SA47 0QS",
    "addr:postcode":"sa47 0qs",
    "addr:street":"Garthddulwyd",
    "iso:country":"GB",
    "sg:address":"Garthddulwyd Fach",
    "sg:city":"Llanarth",
    "sg:classifiers":[
        {
            "category":"Farming",
            "subcategory":"Livestock Farm",
            "type":"Manufacturing & Wholesale Goods"
        },
        {
            "category":"Farming",
            "subcategory":"Farm",
            "type":"Manufacturing & Wholesale Goods"
        }
    ],
    "sg:phone":"+44 1545 580340",
    "sg:postcode":"SA47 0QS",
    "sg:province":"Ceredigion",
    "sg:tags":[
        "mixed",
        "crop",
        "others"
    ],
    "wof:name":"David G Lloyd",
    "wof:placetype":"venue"
},
  "geometry": {"coordinates":[-4.3074989319,52.1941184998],"type":"Point"}
}