{
  "type": "Feature",
  "properties": {
    "addr:full":"57a Addington Rd South Croydon Surrey CR2 8RD",
    "addr:housenumber":"57a",
    "addr:postcode":"cr2 8rd",
    "addr:street":"Addington Rd",
    "iso:country":"GB",
    "sg:address":"57a Addington Rd",
    "sg:city":"South Croydon",
    "sg:classifiers":[
        {
            "category":"Professional",
            "subcategory":"Computer Services",
            "type":"Services"
        }
    ],
    "sg:phone":"+44 20 8651 4695",
    "sg:postcode":"CR2 8RD",
    "sg:province":"Surrey",
    "sg:tags":[
        "consultant"
    ],
    "wof:name":"Crossfield",
    "wof:placetype":"venue"
},
  "geometry": {"coordinates":[-0.068445,51.340355],"type":"Point"}
}