{
  "type": "Feature",
  "properties": {
    "addr:full":"Bredon House, 321 Tettenhall Road Wolverhampton Shropshire WV6 0JZ",
    "addr:housenumber":"321",
    "addr:postcode":"wv6 0jz",
    "addr:street":"Tettenhall Road",
    "iso:country":"GB",
    "sg:address":"Bredon House, 321 Tettenhall Road",
    "sg:city":"Wolverhampton",
    "sg:classifiers":[
        {
            "category":"Health Services",
            "subcategory":"Doctor",
            "type":"Services"
        },
        {
            "category":"Health Services",
            "subcategory":"Clinic",
            "type":"Services"
        }
    ],
    "sg:phone":"+44 1902 756334",
    "sg:postcode":"WV6 0JZ",
    "sg:province":"Shropshire",
    "sg:tags":[
        "practitioners",
        "private"
    ],
    "wof:name":"Private Healthcare",
    "wof:placetype":"venue"
},
  "geometry": {"coordinates":[-2.15935,52.596607],"type":"Point"}
}