{
  "type": "Feature",
  "properties": {
    "addr:full":"Bridlington Comm Resource Ctr, 4-6 Victoria Road Bridlington East Riding of Yorkshire YO15 2BW",
    "addr:housenumber":"4-6",
    "addr:postcode":"yo15 2bw",
    "addr:street":"Victoria Road",
    "iso:country":"GB",
    "sg:address":"Bridlington Comm Resource Ctr, 4-6 Victoria Road",
    "sg:city":"Bridlington",
    "sg:classifiers":[
        {
            "category":"Organizations",
            "subcategory":"Non-profit Organization",
            "type":"Services"
        }
    ],
    "sg:phone":"+44 1262 677555",
    "sg:postcode":"YO15 2BW",
    "sg:province":"East Riding of Yorkshire",
    "sg:tags":[
        "organisation",
        "voluntary",
        "charity"
    ],
    "wof:name":"East Yorkshire Council for Voluntary Service",
    "wof:placetype":"venue"
},
  "geometry": {"coordinates":[-0.192424,54.083496],"type":"Point"}
}