{
  "type": "Feature",
  "properties": {
    "iso:country":"GB",
    "sg:address":"Gray Court",
    "sg:city":"Aberdeen",
    "sg:classifiers":[
        {
            "category":"Social Services",
            "subcategory":"Adult Care",
            "type":"Services"
        },
        {
            "category":"Social Services",
            "subcategory":"Retirement Home",
            "type":"Services"
        }
    ],
    "sg:phone":"+44 1224 326208",
    "sg:postcode":"AB15 6EZ",
    "sg:province":"Aberdeen City",
    "sg:tags":[
        "housing",
        "sheltered",
        "accommodation"
    ],
    "wof:name":"Gray Court Sheltered Housing",
    "wof:placetype":"venue"
},
  "geometry": {"coordinates":[-2.163779,57.148685],"type":"Point"}
}