{
  "type": "Feature",
  "properties": {
    "addr:full":"Sherwood 9 Linden Avenue Kidderminster Staffordshire DY10 3AA",
    "addr:housenumber":"9",
    "addr:postcode":"dy10 3aa",
    "addr:street":"Sherwood;Linden Avenue",
    "iso:country":"GB",
    "sg:address":"Sherwood 9 Linden Avenue",
    "sg:city":"Kidderminster",
    "sg:classifiers":[
        {
            "category":"Banks & Credit Unions",
            "subcategory":"Financial Services",
            "type":"Services"
        }
    ],
    "sg:phone":"+44 1562 638338",
    "sg:postcode":"DY10 3AA",
    "sg:province":"Staffordshire",
    "sg:tags":[
        "adviser"
    ],
    "wof:name":"Alan J Bagley Associates",
    "wof:placetype":"venue"
},
  "geometry": {"coordinates":[-2.2490839958,52.3881111145],"type":"Point"}
}