{
  "type": "Feature",
  "properties": {
    "addr:full":"1 Newton St Holborn Greater London WC2B 5EL",
    "addr:housenumber":"1",
    "addr:postcode":"wc2b 5el",
    "addr:street":"Newton St",
    "iso:country":"GB",
    "sg:address":"1 Newton St",
    "sg:city":"Holborn",
    "sg:classifiers":[
        {
            "category":"Professional",
            "subcategory":"Management & Consulting",
            "type":"Services"
        }
    ],
    "sg:phone":"+44 20 7405 3800",
    "sg:postcode":"WC2B 5EL",
    "sg:province":"Greater London",
    "sg:tags":[
        "consultant",
        "business"
    ],
    "wof:name":"Communispond Incorporated",
    "wof:placetype":"venue"
},
  "geometry": {"coordinates":[-0.1216299981,51.5173072815],"type":"Point"}
}