{
  "type": "Feature",
  "properties": {
    "addr:full":"Dunwood Hall, Leek Road, Dunwood Stoke-on-trent Staffordshire ST9 9AR",
    "addr:postcode":"staffordshire st9 9ar",
    "addr:street":"Leek Road",
    "iso:country":"GB",
    "sg:address":"Dunwood Hall, Leek Road, Dunwood",
    "sg:city":"Stoke-on-trent",
    "sg:classifiers":[
        {
            "category":"Banks & Credit Unions",
            "subcategory":"Financial Services",
            "type":"Services"
        }
    ],
    "sg:phone":"+44 1538 388399",
    "sg:postcode":"ST9 9AR",
    "sg:province":"Staffordshire",
    "sg:tags":[
        "adviser"
    ],
    "wof:name":"A J T Financial Services",
    "wof:placetype":"venue"
},
  "geometry": {"coordinates":[-2.08361,53.087799],"type":"Point"}
}