{
  "type": "Feature",
  "properties": {
    "iso:country":"GB",
    "sg:address":"Cornbrook House, 1 Brindley Road",
    "sg:city":"Manchester",
    "sg:classifiers":[
        {
            "category":"Building & Trades",
            "subcategory":"Construction",
            "type":"Services"
        }
    ],
    "sg:phone":"+44 161 886 5700",
    "sg:postcode":"M16 9HR",
    "sg:province":"Cheshire",
    "sg:tags":[
        "builder"
    ],
    "wof:name":"John Laing Construction Ltd.",
    "wof:placetype":"venue"
},
  "geometry": {"coordinates":[-2.277716,53.463703],"type":"Point"}
}