{
  "type": "Feature",
  "properties": {
    "addr:full":"4 Chapel Road Tadworth Surrey KT20 5SB",
    "addr:housenumber":"4",
    "addr:postcode":"kt20 5sb",
    "addr:street":"Chapel Road",
    "iso:country":"GB",
    "sg:address":"4 Chapel Road",
    "sg:city":"Tadworth",
    "sg:classifiers":[
        {
            "category":"Social Services",
            "subcategory":"Adult Care",
            "type":"Services"
        }
    ],
    "sg:phone":"+44 1737 813118",
    "sg:postcode":"KT20 5SB",
    "sg:province":"Surrey",
    "sg:tags":[
        "housing",
        "sheltered"
    ],
    "wof:name":"Stokes View Management Co. Ltd.",
    "wof:placetype":"venue"
},
  "geometry": {"coordinates":[-0.227474,51.288593],"type":"Point"}
}