{
  "type": "Feature",
  "properties": {
    "addr:full":"1 West Terrace, Great Ayton Middlesbrough North Yorkshire TS9 6PA",
    "addr:housenumber":"1",
    "addr:postcode":"ts9 6pa",
    "addr:street":"West Terrace",
    "iso:country":"GB",
    "sg:address":"1 West Terrace, Great Ayton",
    "sg:city":"Middlesbrough",
    "sg:classifiers":[
        {
            "category":"Bars & Pubs",
            "type":"Food & Drink"
        },
        {
            "category":"Community Center",
            "subcategory":"Social",
            "type":"Public Place"
        }
    ],
    "sg:phone":"+44 1642 722242",
    "sg:postcode":"TS9 6PA",
    "sg:province":"North Yorkshire",
    "sg:tags":[
        "pubs",
        "house",
        "inn",
        "activity"
    ],
    "wof:name":"Buck Hotel",
    "wof:placetype":"venue"
},
  "geometry": {"coordinates":[-1.143089,54.488235],"type":"Point"}
}