{
  "type": "Feature",
  "properties": {
    "addr:full":"6 Old Kings Head Court, 11 High Street Dorking Surrey RH4 1AR",
    "addr:housenumber":"6;11",
    "addr:postcode":"rh4 1ar",
    "addr:street":"Old Kings Head;High Street",
    "iso:country":"GB",
    "sg:address":"6 Old Kings Head Court, 11 High Street",
    "sg:city":"Dorking",
    "sg:classifiers":[
        {
            "category":"Transit Center",
            "subcategory":"Freight",
            "type":"Transportation"
        }
    ],
    "sg:phone":"+44 1306 889355",
    "sg:postcode":"RH4 1AR",
    "sg:province":"Surrey",
    "sg:tags":[
        "shop",
        "craft",
        "centre"
    ],
    "wof:name":"Temptations Contempary British Arts",
    "wof:placetype":"venue"
},
  "geometry": {"coordinates":[-0.3288139999,51.233341217],"type":"Point"}
}