{
  "type": "Feature",
  "properties": {
    "iso:country":"GB",
    "sg:address":"17 Newmarket Road",
    "sg:city":"Doncaster",
    "sg:classifiers":[
        {
            "category":"Recreation",
            "subcategory":"Fishing",
            "type":"Entertainment"
        }
    ],
    "sg:phone":"+44 1302 537237",
    "sg:postcode":"DN4 6HP",
    "sg:province":"South Yorkshire",
    "sg:tags":[
        "angling"
    ],
    "wof:name":"Robs Fishing & Shooting",
    "wof:placetype":"venue"
},
  "geometry": {"coordinates":[-1.083445,53.517876],"type":"Point"}
}