{
  "type": "Feature",
  "properties": {
    "iso:country":"GB",
    "sg:address":"63 Millarbank Street",
    "sg:city":"Glasgow",
    "sg:classifiers":[
        {
            "category":"Organizations",
            "subcategory":"Community Association",
            "type":"Services"
        },
        {
            "category":"Organizations",
            "subcategory":"Membership Organization",
            "type":"Services"
        }
    ],
    "sg:phone":"+44 141 558 6225",
    "sg:postcode":"G21 1BT",
    "sg:province":"East Dunbartonshire",
    "sg:tags":[
        "club",
        "social"
    ],
    "wof:name":"Orange Halls Springburn",
    "wof:placetype":"venue"
},
  "geometry": {"coordinates":[-4.235196,55.880848],"type":"Point"}
}