{
  "type": "Feature",
  "properties": {
    "iso:country":"GB",
    "sg:address":"Aroma Ho, 85 Henry Rd",
    "sg:city":"Nottingham",
    "sg:classifiers":[
        {
            "category":"Health Services",
            "subcategory":"Health Practitioner",
            "type":"Services"
        }
    ],
    "sg:phone":"+44 115 982 0389",
    "sg:postcode":"NG2 7ND",
    "sg:province":"Nottinghamshire",
    "sg:tags":[
        "acupuncture"
    ],
    "wof:name":"Heather Fitton",
    "wof:placetype":"venue"
},
  "geometry": {"coordinates":[-1.1341899633,52.929851532],"type":"Point"}
}