{
  "type": "Feature",
  "properties": {
    "addr:full":"25 Broadwalk Saltash Cornwall PL12 4NT",
    "addr:housenumber":"25",
    "addr:postcode":"pl12 4nt",
    "addr:street":"Broadwalk",
    "iso:country":"GB",
    "sg:address":"25 Broadwalk",
    "sg:city":"Saltash",
    "sg:classifiers":[
        {
            "category":"Manufacturing",
            "subcategory":"Signs",
            "type":"Manufacturing & Wholesale Goods"
        }
    ],
    "sg:phone":"+44 1752 845146",
    "sg:postcode":"PL12 4NT",
    "sg:province":"Cornwall",
    "sg:tags":[
        "writer"
    ],
    "wof:name":"Thomas,Paul,",
    "wof:placetype":"venue"
},
  "geometry": {"coordinates":[-4.235489,50.41053],"type":"Point"}
}