{
  "type": "Feature",
  "properties": {
    "addr:full":"40-48 Buchanan Street Glasgow Glasgow City G1 3JX",
    "addr:housenumber":"40-48",
    "addr:postcode":"g1 3jx",
    "addr:street":"Buchanan Street",
    "iso:country":"GB",
    "sg:address":"40-48 Buchanan Street",
    "sg:city":"Glasgow",
    "sg:classifiers":[
        {
            "category":"Transit Center",
            "subcategory":"Freight",
            "type":"Transportation"
        },
        {
            "category":"Commercial Area",
            "type":"Public Place"
        }
    ],
    "sg:phone":"+44 141 221 0324",
    "sg:postcode":"G1 3JX",
    "sg:province":"Glasgow City",
    "sg:tags":[
        "shop",
        "shopping",
        "centre"
    ],
    "wof:name":"Princes Square Speciality Shopping Centre",
    "wof:placetype":"venue"
},
  "geometry": {"coordinates":[-4.25435,55.8592],"type":"Point"}
}