{
  "type": "Feature",
  "properties": {
    "addr:full":"28 Coolgreany Crescent, Malpas Newport Newport NP20 6EQ",
    "addr:housenumber":"28",
    "addr:postcode":"np20 6eq",
    "addr:street":"Coolgreany Crescent",
    "iso:country":"GB",
    "sg:address":"28 Coolgreany Crescent, Malpas",
    "sg:city":"Newport",
    "sg:classifiers":[
        {
            "category":"Home & Garden",
            "subcategory":"Home Furnishings",
            "type":"Retail Goods"
        }
    ],
    "sg:phone":"+44 1633 857476",
    "sg:postcode":"NP20 6EQ",
    "sg:province":"Newport",
    "sg:tags":[
        "awning",
        "canopy",
        "blinds"
    ],
    "wof:name":"Classic Canopies - Fibre Glass",
    "wof:placetype":"venue"
},
  "geometry": {"coordinates":[-3.0099220276,51.6079406738],"type":"Point"}
}