{
  "type": "Feature",
  "properties": {
    "iso:country":"GB",
    "sg:address":"Unit 36 29 Kyle Road, Irvine Industrial Estate",
    "sg:city":"Irvine",
    "sg:classifiers":[
        {
            "category":"Professional",
            "subcategory":"Business Services",
            "type":"Services"
        }
    ],
    "sg:phone":"+44 1294 312999",
    "sg:postcode":"KA12 8LE",
    "sg:province":"North Ayrshire",
    "sg:tags":[
        "distribution"
    ],
    "wof:name":"F E S (Distribution) Ltd.",
    "wof:placetype":"venue"
},
  "geometry": {"coordinates":[-4.674274,55.599022],"type":"Point"}
}