{
  "type": "Feature",
  "properties": {
    "addr:full":"Three Brindley Place Birmingham West Midlands B1 2BL",
    "addr:postcode":"b1 2bl",
    "addr:street":"Place",
    "iso:country":"GB",
    "sg:address":"Three Brindley Place",
    "sg:city":"Birmingham",
    "sg:classifiers":[
        {
            "category":"Professional",
            "subcategory":"Business Services",
            "type":"Services"
        }
    ],
    "sg:phone":"+44 121 224 3051",
    "sg:postcode":"B1 2BL",
    "sg:province":"West Midlands",
    "sg:tags":[
        "accomodation"
    ],
    "wof:name":"Midlands Psychological Services Ltd.",
    "wof:placetype":"venue"
},
  "geometry": {"coordinates":[-1.908604,52.478596],"type":"Point"}
}