{
  "type": "Feature",
  "properties": {
    "addr:full":"2 Coniston Gro, Baildon Shipley West Yorkshire BD17 5RR",
    "addr:housenumber":"2",
    "addr:postcode":"bd17 5rr",
    "addr:street":"Coniston Gro Baildon",
    "iso:country":"GB",
    "sg:address":"2 Coniston Gro, Baildon",
    "sg:city":"Shipley",
    "sg:classifiers":[
        {
            "category":"Building & Trades",
            "subcategory":"Pest Control",
            "type":"Services"
        },
        {
            "category":"Building & Trades",
            "subcategory":"Construction",
            "type":"Services"
        }
    ],
    "sg:phone":"+44 1274 426872",
    "sg:postcode":"BD17 5RR",
    "sg:province":"West Yorkshire",
    "sg:tags":[
        "painting",
        "decorator",
        "painter",
        "contractor"
    ],
    "wof:name":"Ward & Phillips",
    "wof:placetype":"venue"
},
  "geometry": {"coordinates":[-1.796469,53.84214],"type":"Point"}
}