{
  "type": "Feature",
  "properties": {
    "iso:country":"GB",
    "sg:address":"13 Boringdon Mill Business Park, Lister Close",
    "sg:city":"Plymouth",
    "sg:classifiers":[
        {
            "category":"Home & Garden",
            "subcategory":"Hardware",
            "type":"Retail Goods"
        }
    ],
    "sg:phone":"+44 1752 202204",
    "sg:postcode":"PL7 4BA",
    "sg:province":"Devon",
    "sg:tags":[
        "equipment",
        "welding"
    ],
    "wof:name":"Advanced Welding Supplies Ltd.",
    "wof:placetype":"venue"
},
  "geometry": {"coordinates":[-4.0460300446,50.3938598633],"type":"Point"}
}