{
  "type": "Feature",
  "properties": {
    "addr:full":"18 Caldey Road Dronfield Derbyshire S18 1RS",
    "addr:housenumber":"18",
    "addr:postcode":"s18 1rs",
    "addr:street":"Caldey Road",
    "iso:country":"GB",
    "sg:address":"18 Caldey Road",
    "sg:city":"Dronfield",
    "sg:classifiers":[
        {
            "category":"Shopping",
            "subcategory":"Stationery & Office Supplies",
            "type":"Retail Goods"
        }
    ],
    "sg:postcode":"S18 1RS",
    "sg:province":"Derbyshire",
    "sg:tags":[
        "item",
        "promotional"
    ],
    "wof:name":"Diamond Design & Print",
    "wof:placetype":"venue"
},
  "geometry": {"coordinates":[-1.4730329514,53.2972679138],"type":"Point"}
}