{
  "type": "Feature",
  "properties": {
    "addr:full":"Halifax House, Coronation Rd High Wycombe Buckinghamshire HP12 3SE",
    "addr:postcode":"hp12 3se",
    "addr:street":"Coronation Rd",
    "iso:country":"GB",
    "sg:address":"Halifax House, Coronation Rd",
    "sg:city":"High Wycombe",
    "sg:classifiers":[
        {
            "category":"Home & Garden",
            "subcategory":"Household Appliances",
            "type":"Retail Goods"
        }
    ],
    "sg:phone":"+44 1494 445151",
    "sg:postcode":"HP12 3SE",
    "sg:province":"Buckinghamshire",
    "sg:tags":[
        "electrical"
    ],
    "wof:name":"Hoover Service Centre",
    "wof:placetype":"venue"
},
  "geometry": {"coordinates":[-0.772834003,51.620803833],"type":"Point"}
}