{
  "type": "Feature",
  "properties": {
    "addr:full":"Unit 34 The Raylor Centre, James Street York North Yorkshire YO10 3DW",
    "addr:housenumber":"unit 34",
    "addr:postcode":"yo10 3dw",
    "addr:street":"The;James Street",
    "iso:country":"GB",
    "sg:address":"Unit 34 The Raylor Centre, James Street",
    "sg:city":"York",
    "sg:classifiers":[
        {
            "category":"Home & Garden",
            "subcategory":"Building Materials",
            "type":"Retail Goods"
        }
    ],
    "sg:phone":"+44 1904 430005",
    "sg:postcode":"YO10 3DW",
    "sg:province":"North Yorkshire",
    "sg:tags":[
        "ironwork",
        "wrought"
    ],
    "wof:name":"Iain Scott Fabrications Ltd.",
    "wof:placetype":"venue"
},
  "geometry": {"coordinates":[-1.0661400557,53.9567108154],"type":"Point"}
}