{
  "type": "Feature",
  "properties": {
    "iso:country":"GB",
    "sg:address":"79 Station Rd",
    "sg:city":"Harrow",
    "sg:classifiers":[
        {
            "category":"Food & Beverages",
            "subcategory":"Fruits & Vegetables",
            "type":"Retail Goods"
        }
    ],
    "sg:postcode":"HA2 7SW",
    "sg:province":"Greater London",
    "sg:tags":[
        "greengrocer"
    ],
    "wof:name":"Paramount",
    "wof:placetype":"venue"
},
  "geometry": {"coordinates":[-0.362096,51.58498],"type":"Point"}
}