{
  "type": "Feature",
  "properties": {
    "addr:full":"24 Cornwall Road Dorchester Dorset DT1 1RX",
    "addr:housenumber":"24",
    "addr:postcode":"dt1 1rx",
    "addr:street":"Cornwall Road",
    "iso:country":"GB",
    "sg:address":"24 Cornwall Road",
    "sg:city":"Dorchester",
    "sg:classifiers":[
        {
            "category":"Banks & Credit Unions",
            "subcategory":"Financial Services",
            "type":"Services"
        }
    ],
    "sg:postcode":"DT1 1RX",
    "sg:province":"Dorset",
    "sg:tags":[
        "adviser"
    ],
    "wof:name":"Oak Tree Independent Financial Solutions",
    "wof:placetype":"venue"
},
  "geometry": {"coordinates":[-2.442845,50.713589],"type":"Point"}
}