{
  "type": "Feature",
  "properties": {
    "addr:full":"Blue Badge Centre, Horndale Avenue Newton Aycliffe Durham DL5 6DX",
    "addr:postcode":"dl5 6dx",
    "addr:street":"Avenue",
    "iso:country":"GB",
    "sg:address":"Blue Badge Centre, Horndale Avenue",
    "sg:city":"Newton Aycliffe",
    "sg:classifiers":[
        {
            "category":"Building & Trades",
            "subcategory":"Construction",
            "type":"Services"
        }
    ],
    "sg:postcode":"DL5 6DX",
    "sg:province":"Durham",
    "sg:tags":[
        "builder"
    ],
    "wof:name":"Manor Construction",
    "wof:placetype":"venue"
},
  "geometry": {"coordinates":[-1.563024,54.596272],"type":"Point"}
}