{
  "type": "Feature",
  "properties": {
    "addr:full":"4 Wesley Road Saltash Cornwall PL12 6AS",
    "addr:housenumber":"4",
    "addr:postcode":"pl12 6as",
    "addr:street":"Wesley Road",
    "iso:country":"GB",
    "sg:address":"4 Wesley Road",
    "sg:city":"Saltash",
    "sg:classifiers":[
        {
            "category":"Professional",
            "subcategory":"Printing & Photocopies",
            "type":"Services"
        }
    ],
    "sg:phone":"+44 1752 847575",
    "sg:postcode":"PL12 6AS",
    "sg:province":"Cornwall",
    "sg:tags":[
        "trophy"
    ],
    "wof:name":"Saltash Trophies",
    "wof:placetype":"venue"
},
  "geometry": {"coordinates":[-4.214055,50.408718],"type":"Point"}
}