{
  "type": "Feature",
  "properties": {
    "addr:full":"6 Cornfield Terr Eastbourne East Sussex BN21 4NN",
    "addr:housenumber":"6",
    "addr:postcode":"bn21 4nn",
    "addr:street":"Cornfield Terr",
    "iso:country":"GB",
    "sg:address":"6 Cornfield Terr",
    "sg:city":"Eastbourne",
    "sg:classifiers":[
        {
            "category":"Real Estate",
            "subcategory":"Surveying",
            "type":"Services"
        }
    ],
    "sg:phone":"+44 1323 644666",
    "sg:postcode":"BN21 4NN",
    "sg:province":"East Sussex",
    "sg:tags":[
        "building",
        "surveyor"
    ],
    "wof:name":"John L Vincent",
    "wof:placetype":"venue"
},
  "geometry": {"coordinates":[0.285071,50.765156],"type":"Point"}
}