{
  "type": "Feature",
  "properties": {
    "addr:full":"82 Swan Road West Drayton Greater London UB7 7LA",
    "addr:housenumber":"82",
    "addr:postcode":"ub7 7la",
    "addr:street":"Swan Road",
    "iso:country":"GB",
    "sg:address":"82 Swan Road",
    "sg:city":"West Drayton",
    "sg:classifiers":[
        {
            "category":"Bars & Pubs",
            "type":"Food & Drink"
        }
    ],
    "sg:phone":"+44 1895 442410",
    "sg:postcode":"UB7 7LA",
    "sg:province":"Greater London",
    "sg:tags":[
        "pubs",
        "inn"
    ],
    "wof:name":"The Swan",
    "wof:placetype":"venue"
},
  "geometry": {"coordinates":[-0.475595,51.504814],"type":"Point"}
}