{
  "type": "Feature",
  "properties": {
    "addr:full":"Main Street, New Deer Turriff Aberdeenshire AB53 6SY",
    "addr:postcode":"ab53 6sy",
    "addr:street":"Main Street",
    "iso:country":"GB",
    "sg:address":"Main Street, New Deer",
    "sg:city":"Turriff",
    "sg:classifiers":[
        {
            "category":"Bars & Pubs",
            "type":"Food & Drink"
        },
        {
            "category":"Community Center",
            "subcategory":"Social",
            "type":"Public Place"
        }
    ],
    "sg:phone":"+44 1771 644287",
    "sg:postcode":"AB53 6SY",
    "sg:province":"Aberdeenshire",
    "sg:tags":[
        "pubs",
        "house",
        "inn",
        "activity"
    ],
    "wof:name":"Brucklay Arms",
    "wof:placetype":"venue"
},
  "geometry": {"coordinates":[-2.193004,57.511147],"type":"Point"}
}