{
  "type": "Feature",
  "properties": {
    "addr:full":"Appeal Office Blackberry Hill House, Spital, Fishponds Bristol City of Bristol BS16 2EW",
    "addr:postcode":"bs16 2ew",
    "addr:street":"Blackberry Hill",
    "iso:country":"GB",
    "sg:address":"Appeal Office Blackberry Hill House, Spital, Fishponds",
    "sg:city":"Bristol",
    "sg:classifiers":[
        {
            "category":"Organizations",
            "subcategory":"Non-profit Organization",
            "type":"Services"
        }
    ],
    "sg:phone":"+44 117 975 4831",
    "sg:postcode":"BS16 2EW",
    "sg:province":"City of Bristol",
    "sg:tags":[
        "organisation",
        "voluntary",
        "charity"
    ],
    "wof:name":"Brace-Alzheimer's Research",
    "wof:placetype":"venue"
},
  "geometry": {"coordinates":[-2.5914289951,51.453666687],"type":"Point"}
}