{
  "type": "Feature",
  "properties": {
    "iso:country":"GB",
    "sg:address":"42 Smith Drive, Orford",
    "sg:city":"Warrington",
    "sg:classifiers":[
        {
            "category":"Building & Trades",
            "subcategory":"Construction",
            "type":"Services"
        }
    ],
    "sg:postcode":"WA2 8ER",
    "sg:province":"Cheshire",
    "sg:tags":[
        "builder"
    ],
    "wof:name":"Acorn Builders",
    "wof:placetype":"venue"
},
  "geometry": {"coordinates":[-2.5774080753,53.4039802551],"type":"Point"}
}