{
  "type": "Feature",
  "properties": {
    "iso:country":"GB",
    "sg:address":"Unit 5a, Friars Garage, South Street",
    "sg:city":"Leominster",
    "sg:classifiers":[
        {
            "category":"Professional",
            "subcategory":"Testing Lab",
            "type":"Services"
        },
        {
            "category":"Autos & Motor Vehicles",
            "subcategory":"Auto Supplies",
            "type":"Retail Goods"
        }
    ],
    "sg:postcode":"HR6 8AE",
    "sg:province":"Herefordshire",
    "sg:tags":[
        "part",
        "motorcycle",
        "accessory",
        "mot"
    ],
    "wof:name":"A44 Motor Cycles",
    "wof:placetype":"venue"
},
  "geometry": {"coordinates":[-2.743553,52.227077],"type":"Point"}
}