{
  "type": "Feature",
  "properties": {
    "addr:full":"Norton, Cannons Lane Bishops Stortford Essex CM22 7HY",
    "addr:postcode":"cm22 7hy",
    "addr:street":"Cannons Lane",
    "iso:country":"GB",
    "sg:address":"Norton, Cannons Lane",
    "sg:city":"Bishops Stortford",
    "sg:classifiers":[
        {
            "category":"Utilities",
            "subcategory":"Telephone",
            "type":"Services"
        }
    ],
    "sg:phone":"+44 1279 718300",
    "sg:postcode":"CM22 7HY",
    "sg:province":"Essex",
    "sg:tags":[
        "telecommunication"
    ],
    "wof:name":"Sinclair Goulder & Co.",
    "wof:placetype":"venue"
},
  "geometry": {"coordinates":[0.2451850027,51.823677063],"type":"Point"}
}