{
  "type": "Feature",
  "properties": {
    "addr:full":"15 Adams Street London Greater London WC2N 6AA",
    "addr:housenumber":"15",
    "addr:postcode":"wc2n 6aa",
    "addr:street":"Adams Street",
    "iso:country":"GB",
    "sg:address":"15 Adams Street",
    "sg:city":"London",
    "sg:classifiers":[
        {
            "category":"Wholesale",
            "subcategory":"Medical Equipment & Supplies",
            "type":"Manufacturing & Wholesale Goods"
        }
    ],
    "sg:postcode":"WC2N 6AA",
    "sg:province":"Greater London",
    "sg:tags":[
        "hospital"
    ],
    "wof:name":"Smith & Nephew Beta Ltd.",
    "wof:placetype":"venue"
},
  "geometry": {"coordinates":[-0.150722,51.510113],"type":"Point"}
}