{
  "type": "Feature",
  "properties": {
    "iso:country":"GB",
    "sg:address":", Brackley Hatch",
    "sg:city":"Brackley",
    "sg:classifiers":[
        {
            "category":"Restaurant",
            "type":"Food & Drink"
        }
    ],
    "sg:phone":"+44 1280 850209",
    "sg:postcode":"NN13 5TX",
    "sg:province":"Buckinghamshire",
    "wof:name":"The Green Man Inn",
    "wof:placetype":"venue"
},
  "geometry": {"coordinates":[-1.069209,52.067169],"type":"Point"}
}