{
  "type": "Feature",
  "properties": {
    "addr:full":"Harlsdale, Symbister, Whalsay Lerwick Shetland Islands ZE2 9AA",
    "addr:postcode":"ze2 9aa",
    "addr:street":"Whalsay;Shetland",
    "iso:country":"GB",
    "sg:address":"Harlsdale, Symbister, Whalsay",
    "sg:city":"Lerwick",
    "sg:classifiers":[
        {
            "category":"Government",
            "subcategory":"Post Office",
            "type":"Public Place"
        }
    ],
    "sg:postcode":"ZE2 9AA",
    "sg:province":"Shetland Islands",
    "wof:name":"Anderson,Iris,",
    "wof:placetype":"venue"
},
  "geometry": {"coordinates":[-1.0192899704,60.3439788818],"type":"Point"}
}