{
  "type": "Feature",
  "properties": {
    "iso:country":"GB",
    "sg:address":"62 Pears Road",
    "sg:city":"Hounslow",
    "sg:classifiers":[
        {
            "category":"Building & Trades",
            "subcategory":"Construction",
            "type":"Services"
        }
    ],
    "sg:phone":"+44 20 8570 5785",
    "sg:postcode":"TW3 1SR",
    "sg:province":"Greater London",
    "sg:tags":[
        "builder"
    ],
    "wof:name":"Star Contractors Ltd.",
    "wof:placetype":"venue"
},
  "geometry": {"coordinates":[-0.355752,51.469051],"type":"Point"}
}