{
  "type": "Feature",
  "properties": {
    "iso:country":"GB",
    "sg:address":"Fairfax Cottage",
    "sg:city":"Market Rasen",
    "sg:classifiers":[
        {
            "category":"Social Services",
            "subcategory":"Adult Care",
            "type":"Services"
        }
    ],
    "sg:phone":"+44 1673 828722",
    "sg:postcode":"LN8 3PX",
    "sg:province":"Lincolnshire",
    "sg:tags":[
        "domestic",
        "cleaning"
    ],
    "wof:name":"Country Cleaners",
    "wof:placetype":"venue"
},
  "geometry": {"coordinates":[-0.428984,53.364586],"type":"Point"}
}