{
  "type": "Feature",
  "properties": {
    "addr:full":"204 Ballards Lane London Greater London N3 2NA",
    "addr:housenumber":"204",
    "addr:postcode":"n3 2na",
    "addr:street":"Ballards Lane",
    "iso:country":"GB",
    "sg:address":"204 Ballards Lane",
    "sg:city":"London",
    "sg:classifiers":[
        {
            "category":"Retail",
            "subcategory":"Auto Repair",
            "type":"Services"
        }
    ],
    "sg:phone":"+44 20 8343 3533",
    "sg:postcode":"N3 2NA",
    "sg:province":"Greater London",
    "sg:tags":[
        "modification",
        "garage"
    ],
    "wof:name":"Excel Motors Ltd.",
    "wof:placetype":"venue"
},
  "geometry": {"coordinates":[-0.183851,51.607811],"type":"Point"}
}