{
  "type": "Feature",
  "properties": {
    "addr:full":"220 Gooch Street Birmingham West Midlands B5 7HY",
    "addr:housenumber":"220",
    "addr:postcode":"b5 7hy",
    "addr:street":"Gooch Street",
    "iso:country":"GB",
    "sg:address":"220 Gooch Street",
    "sg:city":"Birmingham",
    "sg:classifiers":[
        {
            "category":"Home & Garden",
            "subcategory":"Kitchen Supply",
            "type":"Retail Goods"
        }
    ],
    "sg:phone":"+44 121 622 4330",
    "sg:postcode":"B5 7HY",
    "sg:province":"West Midlands",
    "sg:tags":[
        "equipment",
        "catering"
    ],
    "wof:name":"Manson Products Tools & Machines Ltd",
    "wof:placetype":"venue"
},
  "geometry": {"coordinates":[-1.893321,52.467373],"type":"Point"}
}