{
  "type": "Feature",
  "properties": {
    "addr:full":"5 Langston Street Manchester Greater Manchester M3 1EB",
    "addr:housenumber":"5",
    "addr:postcode":"m3 1eb",
    "addr:street":"Langston Street",
    "iso:country":"GB",
    "sg:address":"5 Langston Street",
    "sg:city":"Manchester",
    "sg:classifiers":[
        {
            "category":"Wholesale",
            "subcategory":"Non-durable Goods",
            "type":"Manufacturing & Wholesale Goods"
        }
    ],
    "sg:phone":"+44 161 832 2374",
    "sg:postcode":"M3 1EB",
    "sg:province":"Greater Manchester",
    "sg:tags":[
        "carry",
        "wholesaler",
        "cash"
    ],
    "wof:name":"Five Star Wholesale Cash & Carry Ltd",
    "wof:placetype":"venue"
},
  "geometry": {"coordinates":[-2.2489280701,53.4911766052],"type":"Point"}
}