{
  "type": "Feature",
  "properties": {
    "addr:full":"2-4 Askwith Road Gloucester Gloucestershire GL4 4PP",
    "addr:housenumber":"2-4",
    "addr:postcode":"gl4 4pp",
    "addr:street":"Askwith Road",
    "iso:country":"GB",
    "sg:address":"2-4 Askwith Road",
    "sg:city":"Gloucester",
    "sg:classifiers":[
        {
            "category":"Food & Beverages",
            "subcategory":"Groceries & Convenience Stores",
            "type":"Retail Goods"
        }
    ],
    "sg:phone":"+44 1452 527876",
    "sg:postcode":"GL4 4PP",
    "sg:province":"Gloucestershire",
    "wof:name":"Key Stores",
    "wof:placetype":"venue"
},
  "geometry": {"coordinates":[-2.2223799229,51.8496627808],"type":"Point"}
}