{
  "type": "Feature",
  "properties": {
    "addr:full":"20 Cross Lane Wirral Merseyside CH63 3AD",
    "addr:housenumber":"20",
    "addr:postcode":"ch63 3ad",
    "addr:street":"Cross Lane",
    "iso:country":"GB",
    "sg:address":"20 Cross Lane",
    "sg:city":"Wirral",
    "sg:classifiers":[
        {
            "category":"Food & Beverages",
            "subcategory":"Fruits & Vegetables",
            "type":"Retail Goods"
        }
    ],
    "sg:postcode":"CH63 3AD",
    "sg:province":"Merseyside",
    "sg:tags":[
        "greengrocer"
    ],
    "wof:name":"Bebington Fruit Hall",
    "wof:placetype":"venue"
},
  "geometry": {"coordinates":[-3.0114378929,53.3456726074],"type":"Point"}
}