{
  "type": "Feature",
  "properties": {
    "iso:country":"GB",
    "sg:address":"12 Marina Dr",
    "sg:city":"Dunstable",
    "sg:classifiers":[
        {
            "category":"Building & Trades",
            "subcategory":"Construction",
            "type":"Services"
        }
    ],
    "sg:phone":"+44 1908 234575",
    "sg:postcode":"LU6 1PN",
    "sg:province":"Bedfordshire",
    "sg:tags":[
        "roofing"
    ],
    "wof:name":"Greenwood P & M",
    "wof:placetype":"venue"
},
  "geometry": {"coordinates":[-0.5478429794,51.8818664551],"type":"Point"}
}