{
  "type": "Feature",
  "properties": {
    "iso:country":"GB",
    "sg:address":"52 High Street",
    "sg:city":"Kington",
    "sg:classifiers":[
        {
            "category":"Retail",
            "subcategory":"Repair Shop",
            "type":"Services"
        }
    ],
    "sg:phone":"+44 1544 230295",
    "sg:postcode":"HR5 3BJ",
    "sg:province":"Herefordshire",
    "sg:tags":[
        "radio",
        "television",
        "video"
    ],
    "wof:name":"Letts Radio & T V Repairs",
    "wof:placetype":"venue"
},
  "geometry": {"coordinates":[-3.029183,52.203556],"type":"Point"}
}