{
  "type": "Feature",
  "properties": {
    "addr:full":"Crompton House, Crompton Way Crawley Surrey RH10 9QZ",
    "addr:postcode":"rh10 9qz",
    "addr:street":"Crompton Way",
    "iso:country":"GB",
    "sg:address":"Crompton House, Crompton Way",
    "sg:city":"Crawley",
    "sg:classifiers":[
        {
            "category":"Professional",
            "subcategory":"Detective & Security Services",
            "type":"Services"
        },
        {
            "category":"Building & Trades",
            "subcategory":"Electrical",
            "type":"Services"
        }
    ],
    "sg:phone":"+44 1293 548301",
    "sg:postcode":"RH10 9QZ",
    "sg:province":"Surrey",
    "sg:tags":[
        "electrician",
        "contractor"
    ],
    "wof:name":"FRONTIER-PITTS LTD",
    "wof:placetype":"venue"
},
  "geometry": {"coordinates":[-0.183019,51.128391],"type":"Point"}
}