{
  "type": "Feature",
  "properties": {
    "addr:full":"28 Orchard Road Margate Kent CT9 5JS",
    "addr:housenumber":"28",
    "addr:postcode":"ct9 5js",
    "addr:street":"Orchard Road",
    "iso:country":"GB",
    "sg:address":"28 Orchard Road",
    "sg:city":"Margate",
    "sg:classifiers":[
        {
            "category":"Retail",
            "subcategory":"Auto Repair",
            "type":"Services"
        }
    ],
    "sg:phone":"+44 1843 834898",
    "sg:postcode":"CT9 5JS",
    "sg:province":"Kent",
    "sg:tags":[
        "body",
        "car",
        "repairer"
    ],
    "wof:name":"Body Repairs & Resprays",
    "wof:placetype":"venue"
},
  "geometry": {"coordinates":[1.353095,51.381287],"type":"Point"}
}