{
  "type": "Feature",
  "properties": {
    "addr:full":"128 Hartley Brook Road Sheffield South Yorkshire S5 0AW",
    "addr:housenumber":"128",
    "addr:postcode":"s5 0aw",
    "addr:street":"Hartley Brook Road",
    "iso:country":"GB",
    "sg:address":"128 Hartley Brook Road",
    "sg:city":"Sheffield",
    "sg:classifiers":[
        {
            "category":"Government",
            "subcategory":"Post Office",
            "type":"Public Place"
        }
    ],
    "sg:phone":"+44 114 245 1083",
    "sg:postcode":"S5 0AW",
    "sg:province":"South Yorkshire",
    "wof:name":"Hartley Brook Road Post Office",
    "wof:placetype":"venue"
},
  "geometry": {"coordinates":[-1.450273,53.432178],"type":"Point"}
}