{
  "type": "Feature",
  "properties": {
    "addr:full":"1 The Avenue, The Common Pontypridd Caerphilly CF37 4DF",
    "addr:housenumber":"1",
    "addr:postcode":"cf37 4df",
    "addr:street":"The Avenue The Common",
    "iso:country":"GB",
    "sg:address":"1 The Avenue, The Common",
    "sg:city":"Pontypridd",
    "sg:classifiers":[
        {
            "category":"Building & Trades",
            "subcategory":"Construction",
            "type":"Services"
        }
    ],
    "sg:phone":"+44 1443 404384",
    "sg:postcode":"CF37 4DF",
    "sg:province":"Caerphilly",
    "sg:tags":[
        "joiner",
        "carpenter"
    ],
    "wof:name":"D Thomas",
    "wof:placetype":"venue"
},
  "geometry": {"coordinates":[-3.3310329914,51.6059799194],"type":"Point"}
}