{
  "type": "Feature",
  "properties": {
    "addr:full":"54 George Iv Bridge Edinburgh City of Edinburgh EH1 1EJ",
    "addr:housenumber":"54",
    "addr:postcode":"eh1 1ej",
    "addr:street":"George Iv Bridge Edinburgh",
    "iso:country":"GB",
    "sg:address":"54 George Iv Bridge",
    "sg:city":"Edinburgh",
    "sg:classifiers":[
        {
            "category":"Bars & Pubs",
            "type":"Food & Drink"
        },
        {
            "category":"Community Center",
            "subcategory":"Social",
            "type":"Public Place"
        }
    ],
    "sg:phone":"+44 131 225 6936",
    "sg:postcode":"EH1 1EJ",
    "sg:province":"City of Edinburgh",
    "sg:tags":[
        "pubs",
        "house",
        "inn",
        "activity"
    ],
    "wof:name":"Bar Kohl",
    "wof:placetype":"venue"
},
  "geometry": {"coordinates":[-3.1917309761,55.9481277466],"type":"Point"}
}