{
  "type": "Feature",
  "properties": {
    "addr:full":"63 West Benhar Road, Harthill Shotts North Lanarkshire ML7 5TG",
    "addr:housenumber":"63",
    "addr:postcode":"ml7 5tg",
    "addr:street":"West Benhar Road;Shotts",
    "iso:country":"GB",
    "sg:address":"63 West Benhar Road, Harthill",
    "sg:city":"Shotts",
    "sg:classifiers":[
        {
            "category":"Wholesale",
            "subcategory":"Scrap",
            "type":"Manufacturing & Wholesale Goods"
        }
    ],
    "sg:phone":"+44 1501 753334",
    "sg:postcode":"ML7 5TG",
    "sg:province":"North Lanarkshire",
    "sg:tags":[
        "breaker",
        "dismantlers"
    ],
    "wof:name":"Central Carbusters",
    "wof:placetype":"venue"
},
  "geometry": {"coordinates":[-3.768789053,55.854888916],"type":"Point"}
}