{
  "type": "Feature",
  "properties": {
    "iso:country":"GB",
    "sg:address":"Peacock Buildings, County Road",
    "sg:city":"Ormskirk",
    "sg:classifiers":[
        {
            "category":"Personal",
            "subcategory":"Beauty Salon",
            "type":"Services"
        }
    ],
    "sg:phone":"+44 1695 576505",
    "sg:postcode":"L39 1NN",
    "sg:province":"Lancashire",
    "sg:tags":[
        "ladies",
        "lady",
        "hairdresser"
    ],
    "wof:name":"Trim Inn",
    "wof:placetype":"venue"
},
  "geometry": {"coordinates":[-2.8863,53.566277],"type":"Point"}
}