{
  "type": "Feature",
  "properties": {
    "addr:full":"1b Ling Way Norwich Norfolk NR12 7HX",
    "addr:housenumber":"1b",
    "addr:postcode":"nr12 7hx",
    "addr:street":"Ling Way",
    "iso:country":"GB",
    "sg:address":"1b Ling Way",
    "sg:city":"Norwich",
    "sg:classifiers":[
        {
            "category":"Military Area",
            "subcategory":"Air Force Base",
            "type":"Public Place"
        }
    ],
    "sg:phone":"+44 1603 737370",
    "sg:postcode":"NR12 7HX",
    "sg:province":"Norfolk",
    "sg:tags":[
        "taxi",
        "hire",
        "private"
    ],
    "wof:name":"Coltishall Cars",
    "wof:placetype":"venue"
},
  "geometry": {"coordinates":[1.361366,52.735962],"type":"Point"}
}