{
  "type": "Feature",
  "properties": {
    "iso:country":"GB",
    "sg:address":"Church Road, Swanmore",
    "sg:city":"Southampton",
    "sg:classifiers":[
        {
            "category":"Bars & Pubs",
            "type":"Food & Drink"
        }
    ],
    "sg:phone":"+44 1489 892461",
    "sg:postcode":"SO32 2PA",
    "sg:province":"Hampshire",
    "sg:tags":[
        "pubs",
        "inn"
    ],
    "wof:name":"The Bricklayers Arms",
    "wof:placetype":"venue"
},
  "geometry": {"coordinates":[-1.2009290457,50.9163856506],"type":"Point"}
}