{
  "type": "Feature",
  "properties": {
    "addr:full":"Ivy Cottage, Prisk Cowbridge The Vale of Glamorgan CF71 7TJ",
    "addr:postcode":"cf71 7tj",
    "addr:street":"Prisk;The Vale",
    "iso:country":"GB",
    "sg:address":"Ivy Cottage, Prisk",
    "sg:city":"Cowbridge",
    "sg:classifiers":[
        {
            "category":"Real Estate",
            "subcategory":"Real Estate Agent",
            "type":"Services"
        }
    ],
    "sg:phone":"+44 1446 774455",
    "sg:postcode":"CF71 7TJ",
    "sg:province":"The Vale of Glamorgan",
    "wof:name":"Cowbridge & County Property Management",
    "wof:placetype":"venue"
},
  "geometry": {"coordinates":[-3.4504249096,51.4623908997],"type":"Point"}
}