{
  "type": "Feature",
  "properties": {
    "iso:country":"GB",
    "sg:address":"Bloomfield Farm, School Road, Fen End",
    "sg:city":"Wisbech",
    "sg:classifiers":[
        {
            "category":"Home & Garden",
            "subcategory":"Garden Supply",
            "type":"Retail Goods"
        },
        {
            "category":"Farming",
            "subcategory":"Livestock Farm",
            "type":"Manufacturing & Wholesale Goods"
        }
    ],
    "sg:phone":"+44 1945 880285",
    "sg:postcode":"PE14 7SQ",
    "sg:province":"Cambridgeshire",
    "sg:tags":[
        "bulb",
        "grower",
        "others"
    ],
    "wof:name":"Bloomfield Farm",
    "wof:placetype":"venue"
},
  "geometry": {"coordinates":[0.2738299966,52.6882400513],"type":"Point"}
}