{
  "type": "Feature",
  "properties": {
    "addr:full":"Project House Alfreton Derbyshire DE55 7AD",
    "addr:postcode":"de55 7ad",
    "iso:country":"GB",
    "sg:address":"Project House",
    "sg:city":"Alfreton",
    "sg:classifiers":[
        {
            "category":"Building & Trades",
            "subcategory":"Construction",
            "type":"Services"
        }
    ],
    "sg:phone":"+44 1773 838350",
    "sg:postcode":"DE55 7AD",
    "sg:province":"Derbyshire",
    "sg:tags":[
        "flooring"
    ],
    "wof:name":"P F D Flooring Ltd.",
    "wof:placetype":"venue"
},
  "geometry": {"coordinates":[-1.3850489855,53.097618103],"type":"Point"}
}