{
  "type": "Feature",
  "properties": {
    "addr:full":"4 Mortlock Close, Melbourn Royston Bedfordshire SG8 6DA",
    "addr:housenumber":"4",
    "addr:postcode":"sg8 6da",
    "addr:street":"Mortlock Close",
    "iso:country":"GB",
    "sg:address":"4 Mortlock Close, Melbourn",
    "sg:city":"Royston",
    "sg:classifiers":[
        {
            "category":"Professional",
            "type":"Services"
        }
    ],
    "sg:phone":"+44 1763 262059",
    "sg:postcode":"SG8 6DA",
    "sg:province":"Bedfordshire",
    "sg:tags":[
        "shopfitters"
    ],
    "wof:name":"T A W Shopfitting & Building Services Ltd.",
    "wof:placetype":"venue"
},
  "geometry": {"coordinates":[0.017394,52.083199],"type":"Point"}
}