{
  "type": "Feature",
  "properties": {
    "iso:country":"GB",
    "sg:address":"Colegrove Road",
    "sg:city":"Peckham",
    "sg:classifiers":[
        {
            "category":"Health Services",
            "subcategory":"Doctor",
            "type":"Services"
        }
    ],
    "sg:phone":"+44 20 7635 0775",
    "sg:postcode":"SE15 6ND",
    "sg:province":"Greater London",
    "sg:tags":[
        "practitioners"
    ],
    "wof:name":"Colegrove Clinic",
    "wof:placetype":"venue"
},
  "geometry": {"coordinates":[-0.071753,51.480198],"type":"Point"}
}