{
  "type": "Feature",
  "properties": {
    "addr:full":"Green Lane Liverpool Merseyside L13 7HS",
    "addr:postcode":"l13 7hs",
    "addr:street":"Green Lane",
    "iso:country":"GB",
    "sg:address":"Green Lane",
    "sg:city":"Liverpool",
    "sg:classifiers":[
        {
            "category":"Bus Charters",
            "type":"Transportation"
        }
    ],
    "sg:phone":"+44 151 282 8305",
    "sg:postcode":"L13 7HS",
    "sg:province":"Merseyside",
    "sg:tags":[
        "coach"
    ],
    "wof:name":"Arriva Green Lane",
    "wof:placetype":"venue"
},
  "geometry": {"coordinates":[-2.9291539192,53.4242591858],"type":"Point"}
}