{
  "type": "Feature",
  "properties": {
    "addr:full":"Redstone Road Narberth Carmarthenshire SA67 7ES",
    "addr:postcode":"sa67 7es",
    "addr:street":"Redstone Road",
    "iso:country":"GB",
    "sg:address":"Redstone Road",
    "sg:city":"Narberth",
    "sg:classifiers":[
        {
            "category":"Retail",
            "subcategory":"Auto Repair",
            "type":"Services"
        }
    ],
    "sg:phone":"+44 1834 860573",
    "sg:postcode":"SA67 7ES",
    "sg:province":"Carmarthenshire",
    "sg:tags":[
        "modification",
        "garage"
    ],
    "wof:name":"Rushacre Garage",
    "wof:placetype":"venue"
},
  "geometry": {"coordinates":[-4.7443089485,51.8111190796],"type":"Point"}
}