{
  "type": "Feature",
  "properties": {
    "addr:full":"35a New Road Spalding Lincolnshire PE11 1DN",
    "addr:housenumber":"35a",
    "addr:postcode":"pe11 1dn",
    "addr:street":"New Road",
    "iso:country":"GB",
    "sg:address":"35a New Road",
    "sg:city":"Spalding",
    "sg:classifiers":[
        {
            "category":"Personal",
            "subcategory":"Beauty Salon",
            "type":"Services"
        },
        {
            "category":"Personal",
            "subcategory":"Barber",
            "type":"Services"
        }
    ],
    "sg:phone":"+44 1775 714500",
    "sg:postcode":"PE11 1DN",
    "sg:province":"Lincolnshire",
    "sg:tags":[
        "unisex",
        "hairdresser"
    ],
    "wof:name":"Uppercuts",
    "wof:placetype":"venue"
},
  "geometry": {"coordinates":[-0.1513479948,52.7882347107],"type":"Point"}
}