{
  "type": "Feature",
  "properties": {
    "addr:full":"Monument House, 215 Marsh Road Pinner Greater London HA5 5NE",
    "addr:housenumber":"215",
    "addr:postcode":"ha5 5ne",
    "addr:street":"Marsh Road",
    "iso:country":"GB",
    "sg:address":"Monument House, 215 Marsh Road",
    "sg:city":"Pinner",
    "sg:classifiers":[
        {
            "category":"Professional",
            "subcategory":"Accounting & Tax Preparation",
            "type":"Services"
        }
    ],
    "sg:phone":"+44 20 8429 0444",
    "sg:postcode":"HA5 5NE",
    "sg:province":"Greater London",
    "sg:tags":[
        "accountant",
        "activity"
    ],
    "wof:name":"Blacher Associates",
    "wof:placetype":"venue"
},
  "geometry": {"coordinates":[-0.382327,51.593014],"type":"Point"}
}