{
  "type": "Feature",
  "properties": {
    "addr:full":"1466 Wimbourne Rd, Kinson Bournemouth Dorset BH10 7AS",
    "addr:housenumber":"1466",
    "addr:postcode":"bh10 7as",
    "addr:street":"Wimbourne Rd",
    "iso:country":"GB",
    "sg:address":"1466 Wimbourne Rd, Kinson",
    "sg:city":"Bournemouth",
    "sg:classifiers":[
        {
            "category":"Taxi",
            "type":"Transportation"
        }
    ],
    "sg:phone":"+44 1202 241111",
    "sg:postcode":"BH10 7AS",
    "sg:province":"Dorset",
    "sg:tags":[
        "mini",
        "cab"
    ],
    "wof:name":"County & Bournemouth Services",
    "wof:placetype":"venue"
},
  "geometry": {"coordinates":[-1.90048,50.768623],"type":"Point"}
}