{
  "type": "Feature",
  "properties": {
    "addr:full":"Billinge Nook Farm, Under Billinge Lane Blackburn Lancashire BB2 6RN",
    "addr:postcode":"bb2 6rn",
    "addr:street":"Under Billinge Lane",
    "iso:country":"GB",
    "sg:address":"Billinge Nook Farm, Under Billinge Lane",
    "sg:city":"Blackburn",
    "sg:classifiers":[
        {
            "category":"Farming",
            "subcategory":"Livestock Farm",
            "type":"Manufacturing & Wholesale Goods"
        }
    ],
    "sg:phone":"+44 1254 580457",
    "sg:postcode":"BB2 6RN",
    "sg:province":"Lancashire",
    "sg:tags":[
        "others"
    ],
    "wof:name":"D Pawson",
    "wof:placetype":"venue"
},
  "geometry": {"coordinates":[-2.523716,53.750305],"type":"Point"}
}