{
  "type": "Feature",
  "properties": {
    "iso:country":"GB",
    "sg:address":"22 Arnside Avenue, Ince",
    "sg:city":"Wigan",
    "sg:classifiers":[
        {
            "category":"Building & Trades",
            "subcategory":"Construction",
            "type":"Services"
        }
    ],
    "sg:phone":"+44 1942 492288",
    "sg:postcode":"WN2 2NU",
    "sg:province":"Lancashire",
    "sg:tags":[
        "contractor",
        "paving",
        "driveway"
    ],
    "wof:name":"G C Construction",
    "wof:placetype":"venue"
},
  "geometry": {"coordinates":[-2.6011381149,53.544506073],"type":"Point"}
}