{
  "type": "Feature",
  "properties": {
    "addr:full":"5 Moores Place Brentwood Essex CM14 4AG",
    "addr:housenumber":"5",
    "addr:postcode":"cm14 4ag",
    "addr:street":"Moores Place",
    "iso:country":"GB",
    "sg:address":"5 Moores Place",
    "sg:city":"Brentwood",
    "sg:classifiers":[
        {
            "category":"Shopping",
            "subcategory":"Music",
            "type":"Retail Goods"
        }
    ],
    "sg:phone":"+44 1277 203040",
    "sg:postcode":"CM14 4AG",
    "sg:province":"Essex",
    "sg:tags":[
        "dvd",
        "record",
        "tape",
        "vinyl",
        "cd"
    ],
    "wof:name":"Eureka Records",
    "wof:placetype":"venue"
},
  "geometry": {"coordinates":[0.30432,51.620377],"type":"Point"}
}