{
  "type": "Feature",
  "properties": {
    "iso:country":"GB",
    "sg:address":"Onslow Mews, St Anns Road",
    "sg:city":"Chertsey",
    "sg:classifiers":[
        {
            "category":"Social Services",
            "subcategory":"Adult Care",
            "type":"Services"
        }
    ],
    "sg:phone":"+44 1932 568444",
    "sg:postcode":"KT16 9HQ",
    "sg:province":"Surrey",
    "sg:tags":[
        "housing",
        "sheltered"
    ],
    "wof:name":"Retirement Care",
    "wof:placetype":"venue"
},
  "geometry": {"coordinates":[-0.510437,51.395653],"type":"Point"}
}