{
  "type": "Feature",
  "properties": {
    "iso:country":"GB",
    "sg:address":"Royal Buildings, Pwllhai",
    "sg:city":"Cardigan",
    "sg:classifiers":[
        {
            "category":"Professional",
            "subcategory":"Management & Consulting",
            "type":"Services"
        }
    ],
    "sg:phone":"+44 1239 621004",
    "sg:postcode":"SA43 1BZ",
    "sg:province":"Ceredigion",
    "sg:tags":[
        "consultant",
        "business"
    ],
    "wof:name":"A G Business Management",
    "wof:placetype":"venue"
},
  "geometry": {"coordinates":[-4.655044,52.086868],"type":"Point"}
}