{
  "type": "Feature",
  "properties": {
    "addr:full":"Unit 2d Northlands Business Park, Bognor Road, Warnham Horsham West Sussex RH12 3SH",
    "addr:housenumber":"unit 2d",
    "addr:postcode":"rh12 3sh",
    "addr:street":"Northlands Business Park Bognor Road",
    "iso:country":"GB",
    "sg:address":"Unit 2d Northlands Business Park, Bognor Road, Warnham",
    "sg:city":"Horsham",
    "sg:classifiers":[
        {
            "category":"Building & Trades",
            "subcategory":"Landscaping Services",
            "type":"Services"
        }
    ],
    "sg:postcode":"RH12 3SH",
    "sg:province":"West Sussex",
    "sg:tags":[
        "forestry",
        "tree"
    ],
    "wof:name":"A Green Tree Services Ltd.",
    "wof:placetype":"venue"
},
  "geometry": {"coordinates":[-0.3695490062,51.1100921631],"type":"Point"}
}