{
  "type": "Feature",
  "properties": {
    "iso:country":"GB",
    "sg:address":"25 County Arcade",
    "sg:city":"Leeds",
    "sg:classifiers":[
        {
            "category":"Shopping",
            "subcategory":"Clothing, Apparel, & Fashions",
            "type":"Retail Goods"
        }
    ],
    "sg:phone":"+44 113 244 4132",
    "sg:postcode":"LS1 6BH",
    "sg:province":"West Yorkshire",
    "sg:tags":[
        "accessory"
    ],
    "wof:name":"Itiz",
    "wof:placetype":"venue"
},
  "geometry": {"coordinates":[-1.540454,53.798336],"type":"Point"}
}