{
  "type": "Feature",
  "properties": {
    "iso:country":"GB",
    "sg:address":"7 Lightbody St",
    "sg:city":"Liverpool",
    "sg:classifiers":[
        {
            "category":"Manufacturing",
            "subcategory":"Metals",
            "type":"Manufacturing & Wholesale Goods"
        }
    ],
    "sg:phone":"+44 151 207 4981",
    "sg:postcode":"L5 9UU",
    "sg:province":"Merseyside",
    "sg:tags":[
        "steel",
        "fabricator",
        "erectors"
    ],
    "wof:name":"Vanguard Fabrications",
    "wof:placetype":"venue"
},
  "geometry": {"coordinates":[-2.995399,53.422497],"type":"Point"}
}