{
  "type": "Feature",
  "properties": {
    "addr:full":"The Long Barn, Blackmoor Lane, Henstridge Templecombe Somerset BA8 0SN",
    "addr:postcode":"ba8 0sn",
    "addr:street":"Blackmoor Lane",
    "iso:country":"GB",
    "sg:address":"The Long Barn, Blackmoor Lane, Henstridge",
    "sg:city":"Templecombe",
    "sg:classifiers":[
        {
            "category":"Professional",
            "subcategory":"Art Services",
            "type":"Services"
        }
    ],
    "sg:postcode":"BA8 0SN",
    "sg:province":"Somerset",
    "sg:tags":[
        "framing"
    ],
    "wof:name":"Sherborne Frame Co. Ltd.",
    "wof:placetype":"venue"
},
  "geometry": {"coordinates":[-2.4152870178,51.0013809204],"type":"Point"}
}