{
  "type": "Feature",
  "properties": {
    "iso:country":"GB",
    "sg:address":"177-179 Ladbroke Gro",
    "sg:city":"London",
    "sg:classifiers":[
        {
            "category":"Shopping",
            "subcategory":"Department Store",
            "type":"Retail Goods"
        },
        {
            "category":"Food & Beverages",
            "subcategory":"Supermarket",
            "type":"Retail Goods"
        }
    ],
    "sg:phone":"+44 20 8969 7593",
    "sg:postcode":"W10 6HJ",
    "sg:province":"Greater London",
    "wof:name":"Price Check",
    "wof:placetype":"venue"
},
  "geometry": {"coordinates":[-0.213785,51.523674],"type":"Point"}
}