{
  "type": "Feature",
  "properties": {
    "iso:country":"GB",
    "sg:address":"17-19 Nicholas St",
    "sg:city":"Burnley",
    "sg:classifiers":[
        {
            "category":"Professional",
            "subcategory":"Lawyer & Legal Services",
            "type":"Services"
        }
    ],
    "sg:phone":"+44 1282 426722",
    "sg:postcode":"BB11 2AQ",
    "sg:province":"Lancashire",
    "sg:tags":[
        "solicitor"
    ],
    "wof:name":"Steele Greenwood",
    "wof:placetype":"venue"
},
  "geometry": {"coordinates":[-2.2436978817,53.7874488831],"type":"Point"}
}