{
  "type": "Feature",
  "properties": {
    "addr:full":"Hafod Yr Wyn Farm, Gorsgoch Llanybydder Carmarthenshire SA40 9TE",
    "addr:postcode":"sa40 9te",
    "iso:country":"GB",
    "sg:address":"Hafod Yr Wyn Farm, Gorsgoch",
    "sg:city":"Llanybydder",
    "sg:classifiers":[
        {
            "category":"Farming",
            "subcategory":"Livestock Farm",
            "type":"Manufacturing & Wholesale Goods"
        }
    ],
    "sg:postcode":"SA40 9TE",
    "sg:province":"Carmarthenshire",
    "sg:tags":[
        "others"
    ],
    "wof:name":"D E & R M Jones",
    "wof:placetype":"venue"
},
  "geometry": {"coordinates":[-4.158361,52.073936],"type":"Point"}
}