{
  "type": "Feature",
  "properties": {
    "addr:full":"Herries Road Sheffield South Yorkshire S6 1QW",
    "addr:postcode":"s6 1qw",
    "addr:street":"Herries Road",
    "iso:country":"GB",
    "sg:address":"Herries Road",
    "sg:city":"Sheffield",
    "sg:classifiers":[
        {
            "category":"Autos & Motor Vehicles",
            "subcategory":"Automobile Sales",
            "type":"Retail Goods"
        }
    ],
    "sg:phone":"+44 114 249 0990",
    "sg:postcode":"S6 1QW",
    "sg:province":"South Yorkshire",
    "sg:tags":[
        "car"
    ],
    "wof:name":"Select Executive Cars",
    "wof:placetype":"venue"
},
  "geometry": {"coordinates":[-1.495424,53.412743],"type":"Point"}
}