{
  "type": "Feature",
  "properties": {
    "iso:country":"GB",
    "sg:address":"145 Harrow Road",
    "sg:city":"London",
    "sg:classifiers":[
        {
            "category":"Retail",
            "subcategory":"Driving School",
            "type":"Services"
        }
    ],
    "sg:phone":"+44 20 7482 2167",
    "sg:postcode":"W2 1JP",
    "sg:province":"Greater London",
    "wof:name":"Drive & Travel Co. Ltd.",
    "wof:placetype":"venue"
},
  "geometry": {"coordinates":[-0.172465,51.519726],"type":"Point"}
}