{
  "type": "Feature",
  "properties": {
    "addr:full":"Severn Paper Mill, The Docks, Portishead Bristol Somerset BS20 7DJ",
    "addr:postcode":"bs20 7dj",
    "iso:country":"GB",
    "sg:address":"Severn Paper Mill, The Docks, Portishead",
    "sg:city":"Bristol",
    "sg:classifiers":[
        {
            "category":"Manufacturing",
            "subcategory":"Paper Products",
            "type":"Manufacturing & Wholesale Goods"
        }
    ],
    "sg:phone":"+44 1275 842454",
    "sg:postcode":"BS20 7DJ",
    "sg:province":"Somerset",
    "sg:tags":[
        "cardboard"
    ],
    "wof:name":"A P Burt & Sons Ltd.",
    "wof:placetype":"venue"
},
  "geometry": {"coordinates":[-2.7571799755,51.4869308472],"type":"Point"}
}