{
  "type": "Feature",
  "properties": {
    "iso:country":"GB",
    "sg:address":"59 Cross Way",
    "sg:city":"Havant",
    "sg:classifiers":[
        {
            "category":"Health Services",
            "subcategory":"Hospital",
            "type":"Services"
        }
    ],
    "sg:phone":"+44 23 9248 4256",
    "sg:postcode":"PO9 1NG",
    "sg:province":"Hampshire",
    "wof:name":"East Hampshire Primary Care Trust",
    "wof:placetype":"venue"
},
  "geometry": {"coordinates":[-0.987479,50.85453],"type":"Point"}
}