{
  "type": "Feature",
  "properties": {
    "addr:full":"Kistama 7 Southernhay Newton Abbot Devon TQ12 1AX",
    "addr:housenumber":"7;abbot",
    "addr:postcode":"tq12 1ax",
    "addr:street":"Kistama;Southernhay Newton",
    "iso:country":"GB",
    "sg:address":"Kistama 7 Southernhay",
    "sg:city":"Newton Abbot",
    "sg:classifiers":[
        {
            "category":"Food & Beverages",
            "subcategory":"Candy",
            "type":"Retail Goods"
        }
    ],
    "sg:phone":"+44 1626 367098",
    "sg:postcode":"TQ12 1AX",
    "sg:province":"Devon",
    "sg:tags":[
        "confectionery"
    ],
    "wof:name":"Kistama Creations",
    "wof:placetype":"venue"
},
  "geometry": {"coordinates":[-3.6367139816,50.5355110168],"type":"Point"}
}