{
  "type": "Feature",
  "properties": {
    "iso:country":"GB",
    "sg:address":"Fraser House, 84 Holton Road",
    "sg:city":"Barry",
    "sg:classifiers":[
        {
            "category":"Building & Trades",
            "subcategory":"Equipment Rental",
            "type":"Services"
        }
    ],
    "sg:postcode":"CF63 4HD",
    "sg:province":"The Vale of Glamorgan",
    "sg:tags":[
        "supply"
    ],
    "wof:name":"Mark Laity",
    "wof:placetype":"venue"
},
  "geometry": {"coordinates":[-3.268748045,51.4055633545],"type":"Point"}
}