{
  "type": "Feature",
  "properties": {
    "addr:full":"1 Station Road Durham Durham DH7 0EX",
    "addr:housenumber":"1",
    "addr:postcode":"dh7 0ex",
    "addr:street":"Station Road",
    "iso:country":"GB",
    "sg:address":"1 Station Road",
    "sg:city":"Durham",
    "sg:classifiers":[
        {
            "category":"Shopping",
            "subcategory":"Pets & Pet Supplies",
            "type":"Retail Goods"
        }
    ],
    "sg:phone":"+44 1207 529680",
    "sg:postcode":"DH7 0EX",
    "sg:province":"Durham",
    "wof:name":"Lilydale Pet Supplies Ltd.",
    "wof:placetype":"venue"
},
  "geometry": {"coordinates":[-1.742634,54.821072],"type":"Point"}
}