{
  "type": "Feature",
  "properties": {
    "addr:full":"1 Delta Drive Musselburgh City of Edinburgh EH21 8HY",
    "addr:housenumber":"1",
    "addr:postcode":"eh21 8hy",
    "addr:street":"Delta Drive",
    "iso:country":"GB",
    "sg:address":"1 Delta Drive",
    "sg:city":"Musselburgh",
    "sg:classifiers":[
        {
            "category":"Shopping",
            "subcategory":"Computers & Home Electronics",
            "type":"Retail Goods"
        }
    ],
    "sg:phone":"+44 131 665 8484",
    "sg:postcode":"EH21 8HY",
    "sg:province":"City of Edinburgh",
    "sg:tags":[
        "aerial",
        "television",
        "radio"
    ],
    "wof:name":"Aerial Services",
    "wof:placetype":"venue"
},
  "geometry": {"coordinates":[-3.090819,55.935131],"type":"Point"}
}