{
  "type": "Feature",
  "properties": {
    "iso:country":"GB",
    "sg:address":"Sylverdale Rd",
    "sg:city":"Purley",
    "sg:classifiers":[
        {
            "category":"Place Of Worship",
            "type":"Public Place"
        }
    ],
    "sg:phone":"+44 20 8645 9353",
    "sg:postcode":"CR8 2DT",
    "sg:province":"Surrey",
    "wof:name":"Kenley & Purley Methodist Church",
    "wof:placetype":"venue"
},
  "geometry": {"coordinates":[-0.108999,51.329857],"type":"Point"}
}