{
  "type": "Feature",
  "properties": {
    "addr:full":"19 Layton Rd Leicester Leicestershire LE5 0PU",
    "addr:housenumber":"19",
    "addr:postcode":"le5 0pu",
    "addr:street":"Layton Rd",
    "iso:country":"GB",
    "sg:address":"19 Layton Rd",
    "sg:city":"Leicester",
    "sg:classifiers":[
        {
            "category":"Shopping",
            "subcategory":"Stationery & Office Supplies",
            "type":"Retail Goods"
        }
    ],
    "sg:phone":"+44 116 274 0561",
    "sg:postcode":"LE5 0PU",
    "sg:province":"Leicestershire",
    "sg:tags":[
        "printers'"
    ],
    "wof:name":"Midland Provincial Studios Ltd",
    "wof:placetype":"venue"
},
  "geometry": {"coordinates":[-1.098589,52.642555],"type":"Point"}
}