{
  "type": "Feature",
  "properties": {
    "addr:full":"7 Carbis Road Poplar Greater London E14 7TH",
    "addr:housenumber":"7",
    "addr:postcode":"e14 7th",
    "addr:street":"Carbis Road",
    "iso:country":"GB",
    "sg:address":"7 Carbis Road",
    "sg:city":"Poplar",
    "sg:classifiers":[
        {
            "category":"Freight",
            "type":"Transportation"
        }
    ],
    "sg:phone":"+44 20 8305 0029",
    "sg:postcode":"E14 7TH",
    "sg:province":"Greater London",
    "sg:tags":[
        "haulage",
        "road"
    ],
    "wof:name":"John Small",
    "wof:placetype":"venue"
},
  "geometry": {"coordinates":[-0.0325380005,51.5147018433],"type":"Point"}
}