{
  "type": "Feature",
  "properties": {
    "iso:country":"GB",
    "sg:address":"Mayfield House, 256 Banbury Road",
    "sg:city":"Oxford",
    "sg:classifiers":[
        {
            "category":"Shopping",
            "subcategory":"Thrift Store",
            "type":"Retail Goods"
        },
        {
            "category":"Organizations",
            "subcategory":"Non-profit Organization",
            "type":"Services"
        }
    ],
    "sg:phone":"+44 1865 554770",
    "sg:postcode":"OX2 7DE",
    "sg:province":"Oxfordshire",
    "sg:tags":[
        "shop",
        "organisation",
        "voluntary",
        "charity"
    ],
    "wof:name":"Scope",
    "wof:placetype":"venue"
},
  "geometry": {"coordinates":[-1.2647629976,51.7772941589],"type":"Point"}
}