{
  "type": "Feature",
  "properties": {
    "iso:country":"GB",
    "sg:address":"The Packhouse, Little Fowle",
    "sg:city":"Tonbridge",
    "sg:classifiers":[
        {
            "category":"Manufacturing",
            "subcategory":"Building Materials",
            "type":"Manufacturing & Wholesale Goods"
        }
    ],
    "sg:phone":"+44 1892 836683",
    "sg:postcode":"TN12 6PJ",
    "sg:province":"Kent",
    "sg:tags":[
        "merchant",
        "builder"
    ],
    "wof:name":"Conquest Construction Products",
    "wof:placetype":"venue"
},
  "geometry": {"coordinates":[0.41226,51.185509],"type":"Point"}
}