{
  "type": "Feature",
  "properties": {
    "addr:full":"40 Normanton Road South Croydon Surrey CR2 7AR",
    "addr:housenumber":"40",
    "addr:postcode":"cr2 7ar",
    "addr:street":"Normanton Road",
    "iso:country":"GB",
    "sg:address":"40 Normanton Road",
    "sg:city":"South Croydon",
    "sg:classifiers":[
        {
            "category":"Travel",
            "subcategory":"Hotels & Motels",
            "type":"Entertainment"
        }
    ],
    "sg:phone":"+44 20 8686 8179",
    "sg:postcode":"CR2 7AR",
    "sg:province":"Surrey",
    "wof:name":"Amber House Hotel",
    "wof:placetype":"venue"
},
  "geometry": {"coordinates":[-0.089711003,51.3585586548],"type":"Point"}
}