{
  "type": "Feature",
  "properties": {
    "addr:full":"2 Telford Pl Crawley Surrey RH10 1TF",
    "addr:housenumber":"2",
    "addr:postcode":"rh10 1tf",
    "addr:street":"Telford Pl",
    "iso:country":"GB",
    "sg:address":"2 Telford Pl",
    "sg:city":"Crawley",
    "sg:classifiers":[
        {
            "category":"Government",
            "subcategory":"Post Office",
            "type":"Public Place"
        }
    ],
    "sg:postcode":"RH10 1TF",
    "sg:province":"Surrey",
    "sg:tags":[
        "messenger",
        "courier"
    ],
    "wof:name":"Be on Time",
    "wof:placetype":"venue"
},
  "geometry": {"coordinates":[-0.181182,51.112595],"type":"Point"}
}