{
  "type": "Feature",
  "properties": {
    "iso:country":"GB",
    "sg:address":"2 Telford Pl",
    "sg:city":"Crawley",
    "sg:classifiers":[
        {
            "category":"Government",
            "subcategory":"Post Office",
            "type":"Public Place"
        }
    ],
    "sg:postcode":"RH10 1TF",
    "sg:province":"Surrey",
    "sg:tags":[
        "messenger",
        "courier"
    ],
    "wof:name":"Be on Time",
    "wof:placetype":"venue"
},
  "geometry": {"coordinates":[-0.181182,51.112595],"type":"Point"}
}