{
  "type": "Feature",
  "properties": {
    "addr:full":"Oakwood, Castle Hill, Prestbury Macclesfield Cheshire SK10 4AR",
    "addr:postcode":"sk10 4ar",
    "addr:street":"Castle Hill",
    "iso:country":"GB",
    "sg:address":"Oakwood, Castle Hill, Prestbury",
    "sg:city":"Macclesfield",
    "sg:classifiers":[
        {
            "category":"Manufacturing",
            "subcategory":"Textiles",
            "type":"Manufacturing & Wholesale Goods"
        }
    ],
    "sg:postcode":"SK10 4AR",
    "sg:province":"Cheshire",
    "sg:tags":[
        "merchant",
        "agent"
    ],
    "wof:name":"Pastures Textile Converters",
    "wof:placetype":"venue"
},
  "geometry": {"coordinates":[-2.1506679058,53.2899703979],"type":"Point"}
}