{
  "type": "Feature",
  "properties": {
    "addr:full":"Quorn Road London Greater London SE22 8BY",
    "addr:postcode":"se22 8by",
    "addr:street":"Quorn Road",
    "iso:country":"GB",
    "sg:address":"Quorn Road",
    "sg:city":"London",
    "sg:classifiers":[
        {
            "category":"Professional",
            "subcategory":"Management & Consulting",
            "type":"Services"
        }
    ],
    "sg:phone":"+44 20 7274 3737",
    "sg:postcode":"SE22 8BY",
    "sg:province":"Greater London",
    "sg:tags":[
        "music"
    ],
    "wof:name":"Clarke Weber Management",
    "wof:placetype":"venue"
},
  "geometry": {"coordinates":[-0.080759,51.462284],"type":"Point"}
}