{
  "type": "Feature",
  "properties": {
    "addr:full":"38 Pepper Street Nantwich Cheshire CW5 5AB",
    "addr:housenumber":"38",
    "addr:postcode":"cw5 5ab",
    "addr:street":"Pepper Street",
    "iso:country":"GB",
    "sg:address":"38 Pepper Street",
    "sg:city":"Nantwich",
    "sg:classifiers":[
        {
            "category":"Real Estate",
            "subcategory":"Real Estate Agent",
            "type":"Services"
        }
    ],
    "sg:phone":"+44 1270 625214",
    "sg:postcode":"CW5 5AB",
    "sg:province":"Cheshire",
    "wof:name":"Baker Wynne & Wilson",
    "wof:placetype":"venue"
},
  "geometry": {"coordinates":[-2.5219891071,53.0679016113],"type":"Point"}
}