{
  "type": "Feature",
  "properties": {
    "addr:full":"Wind Road, Ystalyfera Swansea Carmarthenshire SA9 2JX",
    "addr:postcode":"sa9 2jx",
    "addr:street":"Wind Road",
    "iso:country":"GB",
    "sg:address":"Wind Road, Ystalyfera",
    "sg:city":"Swansea",
    "sg:classifiers":[
        {
            "category":"Retail",
            "subcategory":"Auto Repair",
            "type":"Services"
        }
    ],
    "sg:phone":"+44 1639 842205",
    "sg:postcode":"SA9 2JX",
    "sg:province":"Carmarthenshire",
    "sg:tags":[
        "modification",
        "garage"
    ],
    "wof:name":"Woodlands Service Station",
    "wof:placetype":"venue"
},
  "geometry": {"coordinates":[-3.776729,51.768101],"type":"Point"}
}