{
  "type": "Feature",
  "properties": {
    "addr:full":"83 Devizes Road, Bromham Chippenham Wiltshire SN15 2DZ",
    "addr:housenumber":"83",
    "addr:postcode":"sn15 2dz",
    "addr:street":"Devizes Road",
    "iso:country":"GB",
    "sg:address":"83 Devizes Road, Bromham",
    "sg:city":"Chippenham",
    "sg:classifiers":[
        {
            "category":"Food & Beverages",
            "subcategory":"Farmers Market",
            "type":"Retail Goods"
        }
    ],
    "sg:postcode":"SN15 2DZ",
    "sg:province":"Wiltshire",
    "sg:tags":[
        "farm",
        "shop",
        "pyo"
    ],
    "wof:name":"V T F & P M Collins",
    "wof:placetype":"venue"
},
  "geometry": {"coordinates":[-2.0455110073,51.3970222473],"type":"Point"}
}