{
  "type": "Feature",
  "properties": {
    "addr:full":"47 Westminster Avenue, Radcliffe Manchester Greater Manchester M26 3QL",
    "addr:housenumber":"47",
    "addr:postcode":"m26 3ql",
    "addr:street":"Westminster Avenue",
    "iso:country":"GB",
    "sg:address":"47 Westminster Avenue, Radcliffe",
    "sg:city":"Manchester",
    "sg:classifiers":[
        {
            "category":"Home & Garden",
            "subcategory":"Hardware",
            "type":"Retail Goods"
        }
    ],
    "sg:phone":"+44 161 723 3625",
    "sg:postcode":"M26 3QL",
    "sg:province":"Greater Manchester",
    "sg:tags":[
        "compressor",
        "air"
    ],
    "wof:name":"BELLAIR COMPRESSORS",
    "wof:placetype":"venue"
},
  "geometry": {"coordinates":[-2.3496448994,53.5677070618],"type":"Point"}
}