{
  "type": "Feature",
  "properties": {
    "addr:full":"293a Copnor Rd Portsmouth Hampshire PO3 5EG",
    "addr:housenumber":"293a",
    "addr:postcode":"hampshire po3 5eg",
    "addr:street":"Copnor Rd",
    "iso:country":"GB",
    "sg:address":"293a Copnor Rd",
    "sg:city":"Portsmouth",
    "sg:classifiers":[
        {
            "category":"Professional",
            "subcategory":"Art Services",
            "type":"Services"
        }
    ],
    "sg:postcode":"PO3 5EG",
    "sg:province":"Hampshire",
    "sg:tags":[
        "framing"
    ],
    "wof:name":"Allison,Helen,",
    "wof:placetype":"venue"
},
  "geometry": {"coordinates":[-1.065246,50.820721],"type":"Point"}
}