{
  "type": "Feature",
  "properties": {
    "addr:full":"12 Transport Avenue Brentford Greater London TW8 9HF",
    "addr:housenumber":"12",
    "addr:postcode":"tw8 9hf",
    "addr:street":"Transport Avenue",
    "iso:country":"GB",
    "sg:address":"12 Transport Avenue",
    "sg:city":"Brentford",
    "sg:classifiers":[
        {
            "category":"Home & Garden",
            "subcategory":"Building Materials",
            "type":"Retail Goods"
        }
    ],
    "sg:phone":"+44 20 8568 3111",
    "sg:postcode":"TW8 9HF",
    "sg:province":"Greater London",
    "sg:tags":[
        "ready",
        "mixed",
        "concrete"
    ],
    "wof:name":"London Marble & Granite Centre Ltd.",
    "wof:placetype":"venue"
},
  "geometry": {"coordinates":[-0.323458,51.490559],"type":"Point"}
}