{
  "type": "Feature",
  "properties": {
    "iso:country":"GB",
    "sg:address":"80 Clarence Street, Sedgley",
    "sg:city":"Dudley",
    "sg:classifiers":[
        {
            "category":"Organizations",
            "subcategory":"Membership Organization",
            "type":"Services"
        }
    ],
    "sg:phone":"+44 1902 882024",
    "sg:postcode":"DY3 1UP",
    "sg:province":"Staffordshire",
    "sg:tags":[
        "club",
        "social"
    ],
    "wof:name":"Gornal & Sedgley Labour Club",
    "wof:placetype":"venue"
},
  "geometry": {"coordinates":[-2.116769,52.528709],"type":"Point"}
}