{
  "type": "Feature",
  "properties": {
    "iso:country":"GB",
    "sg:address":"Unit 90, Woodside Business Park",
    "sg:city":"Birkenhead",
    "sg:classifiers":[
        {
            "category":"Manufacturing",
            "subcategory":"Tools & Machinery",
            "type":"Manufacturing & Wholesale Goods"
        }
    ],
    "sg:phone":"+44 151 647 9222",
    "sg:postcode":"CH41 1EL",
    "sg:province":"Merseyside",
    "sg:tags":[
        "bearing",
        "stockist"
    ],
    "wof:name":"Wyko-eWB",
    "wof:placetype":"venue"
},
  "geometry": {"coordinates":[-3.0101718903,53.3965301514],"type":"Point"}
}