{
  "type": "Feature",
  "properties": {
    "iso:country":"GB",
    "sg:address":"Crud Y Gwynt, Llanfwrog",
    "sg:city":"Ruthin",
    "sg:classifiers":[
        {
            "category":"Freight",
            "type":"Transportation"
        }
    ],
    "sg:phone":"+44 1824 702873",
    "sg:postcode":"LL15 2AB",
    "sg:province":"Denbighshire",
    "sg:tags":[
        "haulage",
        "transport",
        "road"
    ],
    "wof:name":"Glynne Davies & Son",
    "wof:placetype":"venue"
},
  "geometry": {"coordinates":[-3.32648,53.109814],"type":"Point"}
}