{
  "type": "Feature",
  "properties": {
    "addr:full":"205 Pasture Lane Bradford West Yorkshire BD7 2SQ",
    "addr:housenumber":"205",
    "addr:postcode":"bd7 2sq",
    "addr:street":"Pasture Lane",
    "iso:country":"GB",
    "sg:address":"205 Pasture Lane",
    "sg:city":"Bradford",
    "sg:classifiers":[
        {
            "category":"Personal",
            "subcategory":"Beauty Salon",
            "type":"Services"
        }
    ],
    "sg:postcode":"BD7 2SQ",
    "sg:province":"West Yorkshire",
    "wof:name":"Muscletone",
    "wof:placetype":"venue"
},
  "geometry": {"coordinates":[-1.80162,53.783558],"type":"Point"}
}