{
  "type": "Feature",
  "properties": {
    "iso:country":"GB",
    "sg:address":"205 Pasture Lane",
    "sg:city":"Bradford",
    "sg:classifiers":[
        {
            "category":"Personal",
            "subcategory":"Beauty Salon",
            "type":"Services"
        }
    ],
    "sg:postcode":"BD7 2SQ",
    "sg:province":"West Yorkshire",
    "wof:name":"Muscletone",
    "wof:placetype":"venue"
},
  "geometry": {"coordinates":[-1.80162,53.783558],"type":"Point"}
}