{
  "type": "Feature",
  "properties": {
    "addr:full":"Woodford Grn Farm, Woodford Berkeley Gloucestershire GL13 9JW",
    "addr:postcode":"gl13 9jw",
    "addr:street":"Woodford Grn Farm",
    "iso:country":"GB",
    "sg:address":"Woodford Grn Farm, Woodford",
    "sg:city":"Berkeley",
    "sg:classifiers":[
        {
            "category":"Farming",
            "subcategory":"Livestock Farm",
            "type":"Manufacturing & Wholesale Goods"
        }
    ],
    "sg:phone":"+44 1454 260400",
    "sg:postcode":"GL13 9JW",
    "sg:province":"Gloucestershire",
    "sg:tags":[
        "others"
    ],
    "wof:name":"A W Pullin",
    "wof:placetype":"venue"
},
  "geometry": {"coordinates":[-2.4595689774,51.6931877136],"type":"Point"}
}