{
  "type": "Feature",
  "properties": {
    "iso:country":"GB",
    "sg:address":"25 Glandwr",
    "sg:city":"Newtown",
    "sg:classifiers":[
        {
            "category":"Home & Garden",
            "subcategory":"Carpets & Floor Coverings",
            "type":"Retail Goods"
        }
    ],
    "sg:phone":"+44 1686 628740",
    "sg:postcode":"SY16 1RE",
    "sg:province":"Powys",
    "sg:tags":[
        "carpets",
        "rug",
        "matting"
    ],
    "wof:name":"Graham Hill",
    "wof:placetype":"venue"
},
  "geometry": {"coordinates":[-3.344021,52.50679],"type":"Point"}
}