{
  "type": "Feature",
  "properties": {
    "addr:full":"Barn 3 Hilton Bridgnorth Shropshire WV15 5PB",
    "addr:housenumber":"3;bridgnorth",
    "addr:postcode":"wv15 5pb",
    "addr:street":"Hilton",
    "iso:country":"GB",
    "sg:address":"Barn 3 Hilton",
    "sg:city":"Bridgnorth",
    "sg:classifiers":[
        {
            "category":"Personal",
            "type":"Services"
        }
    ],
    "sg:phone":"+44 1746 710001",
    "sg:postcode":"WV15 5PB",
    "sg:province":"Shropshire",
    "sg:tags":[
        "delivery"
    ],
    "wof:name":"Specialist Transport Services Ltd.",
    "wof:placetype":"venue"
},
  "geometry": {"coordinates":[-2.332637,52.555073],"type":"Point"}
}