{
  "type": "Feature",
  "properties": {
    "iso:country":"GB",
    "sg:address":"25 North Seaton Road",
    "sg:city":"Ashington",
    "sg:classifiers":[
        {
            "category":"Organizations",
            "subcategory":"Non-profit Organization",
            "type":"Services"
        }
    ],
    "sg:phone":"+44 1670 814222",
    "sg:postcode":"NE63 0AG",
    "sg:province":"Northumberland",
    "sg:tags":[
        "organisation",
        "voluntary",
        "charity"
    ],
    "wof:name":"The Samaritans",
    "wof:placetype":"venue"
},
  "geometry": {"coordinates":[-1.568796,55.182175],"type":"Point"}
}