{
  "type": "Feature",
  "properties": {
    "addr:full":"The Old School, Main Road, Orby Skegness Lincolnshire PE24 5HT",
    "addr:postcode":"pe24 5ht",
    "addr:street":"Main Road",
    "iso:country":"GB",
    "sg:address":"The Old School, Main Road, Orby",
    "sg:city":"Skegness",
    "sg:classifiers":[
        {
            "category":"Retail",
            "subcategory":"Repair Shop",
            "type":"Services"
        }
    ],
    "sg:phone":"+44 1754 810138",
    "sg:postcode":"PE24 5HT",
    "sg:province":"Lincolnshire",
    "sg:tags":[
        "radio",
        "television",
        "video"
    ],
    "wof:name":"T V & Audio Sales & Service",
    "wof:placetype":"venue"
},
  "geometry": {"coordinates":[0.229941994,53.1996307373],"type":"Point"}
}