{
  "type": "Feature",
  "properties": {
    "addr:full":"Mysca Ho, Kings Ash Rd Paignton Devon TQ3 3XF",
    "addr:postcode":"tq3 3xf",
    "addr:street":"Kings Ash Rd",
    "iso:country":"GB",
    "sg:address":"Mysca Ho, Kings Ash Rd",
    "sg:city":"Paignton",
    "sg:classifiers":[
        {
            "category":"Home & Garden",
            "subcategory":"Building Materials",
            "type":"Retail Goods"
        }
    ],
    "sg:phone":"+44 1803 525222",
    "sg:postcode":"TQ3 3XF",
    "sg:province":"Devon",
    "sg:tags":[
        "garage",
        "door"
    ],
    "wof:name":"Garafix",
    "wof:placetype":"venue"
},
  "geometry": {"coordinates":[-3.590782,50.439877],"type":"Point"}
}