{
  "type": "Feature",
  "properties": {
    "iso:country":"GB",
    "sg:address":"315 Kilburn High Rd",
    "sg:city":"Kilburn",
    "sg:classifiers":[
        {
            "category":"Shopping",
            "subcategory":"Clothing, Apparel, & Fashions",
            "type":"Retail Goods"
        }
    ],
    "sg:phone":"+44 20 7624 5647",
    "sg:postcode":"NW6 7JR",
    "sg:province":"Greater London",
    "sg:tags":[
        "ladieswear"
    ],
    "wof:name":"Temptations",
    "wof:placetype":"venue"
},
  "geometry": {"coordinates":[-0.200364,51.543678],"type":"Point"}
}