{
  "type": "Feature",
  "properties": {
    "addr:full":"Aston Heath Farm, Aston Lane, Sudbury Derby Derbyshire DE6 5HH",
    "addr:postcode":"de6 5hh",
    "addr:street":"Aston Heath Farm Aston Lane",
    "iso:country":"GB",
    "sg:address":"Aston Heath Farm, Aston Lane, Sudbury",
    "sg:city":"Derby",
    "sg:classifiers":[
        {
            "category":"Food & Beverages",
            "subcategory":"Meat & Fish",
            "type":"Retail Goods"
        }
    ],
    "sg:phone":"+44 1283 585195",
    "sg:postcode":"DE6 5HH",
    "sg:province":"Derbyshire",
    "sg:tags":[
        "butcher"
    ],
    "wof:name":"Keith Brandrick",
    "wof:placetype":"venue"
},
  "geometry": {"coordinates":[-1.7472089529,52.8849563599],"type":"Point"}
}