{
  "type": "Feature",
  "properties": {
    "addr:full":"Integra House, Prince William Road Loughborough Leicestershire LE11 5GU",
    "addr:postcode":"le11 5gu",
    "addr:street":"Prince William Road",
    "iso:country":"GB",
    "sg:address":"Integra House, Prince William Road",
    "sg:city":"Loughborough",
    "sg:classifiers":[
        {
            "category":"Shopping",
            "subcategory":"Computers & Home Electronics",
            "type":"Retail Goods"
        }
    ],
    "sg:phone":"+44 1509 234646",
    "sg:postcode":"LE11 5GU",
    "sg:province":"Leicestershire",
    "sg:tags":[
        "electrical"
    ],
    "wof:name":"I C W Switchgear Co. Ltd.",
    "wof:placetype":"venue"
},
  "geometry": {"coordinates":[-1.2101379633,52.7799987793],"type":"Point"}
}