{
  "type": "Feature",
  "properties": {
    "addr:full":"Sandy Lane, Weston Point Runcorn Cheshire WA7 4EU",
    "addr:postcode":"wa7 4eu",
    "addr:street":"Sandy Lane",
    "iso:country":"GB",
    "sg:address":"Sandy Lane, Weston Point",
    "sg:city":"Runcorn",
    "sg:classifiers":[
        {
            "category":"Retail",
            "subcategory":"Auto Repair",
            "type":"Services"
        }
    ],
    "sg:phone":"+44 1928 573632",
    "sg:postcode":"WA7 4EU",
    "sg:province":"Cheshire",
    "sg:tags":[
        "modification",
        "garage"
    ],
    "wof:name":"S T Motors",
    "wof:placetype":"venue"
},
  "geometry": {"coordinates":[-2.7466781139,53.3281898499],"type":"Point"}
}