{
  "type": "Feature",
  "properties": {
    "iso:country":"GB",
    "sg:address":"5 Alderson Road",
    "sg:city":"Worksop",
    "sg:classifiers":[
        {
            "category":"Professional",
            "subcategory":"Management & Consulting",
            "type":"Services"
        }
    ],
    "sg:postcode":"S80 1UZ",
    "sg:province":"Nottinghamshire",
    "sg:tags":[
        "marketing",
        "consultant"
    ],
    "wof:name":"John Murdoch Associates",
    "wof:placetype":"venue"
},
  "geometry": {"coordinates":[-1.1253809929,53.2984733582],"type":"Point"}
}