{
  "type": "Feature",
  "properties": {
    "addr:full":"40 Seres Road Glasgow East Renfrewshire G76 7QF",
    "addr:housenumber":"40",
    "addr:postcode":"g76 7qf",
    "addr:street":"Seres Road",
    "iso:country":"GB",
    "sg:address":"40 Seres Road",
    "sg:city":"Glasgow",
    "sg:classifiers":[
        {
            "category":"Food & Beverages",
            "subcategory":"Meat & Fish",
            "type":"Retail Goods"
        }
    ],
    "sg:postcode":"G76 7QF",
    "sg:province":"East Renfrewshire",
    "sg:tags":[
        "butcher"
    ],
    "wof:name":"Donald Lothian",
    "wof:placetype":"venue"
},
  "geometry": {"coordinates":[-4.28614,55.789757],"type":"Point"}
}