{
  "type": "Feature",
  "properties": {
    "iso:country":"GB",
    "sg:address":"17 Market Av",
    "sg:city":"Oldham",
    "sg:classifiers":[
        {
            "category":"Shopping",
            "subcategory":"Crafts & Fabrics",
            "type":"Retail Goods"
        }
    ],
    "sg:phone":"+44 161 624 3254",
    "sg:postcode":"OL1 3AH",
    "sg:province":"Lancashire",
    "sg:tags":[
        "shop"
    ],
    "wof:name":"Phil & Carole Fabrics",
    "wof:placetype":"venue"
},
  "geometry": {"coordinates":[-2.1238000393,53.5658950806],"type":"Point"}
}