{"geometry":{"type":"Point","coordinates":[-0.378571,51.475876]},"type":"Feature","id":102560341,"bbox":[-0.378571,51.475876,-0.378571,51.475876],"properties":{"sg:province":"Greater London","sg:tags":["breakdown","recovery"],"geom:longitude":-0.378571,"wof:breaches":[],"sg:href":"http://api.simplegeo.com/1.0/features/SG_0DKGhReh0Wkjj7j62uFlt8_51.475876_-0.378571@1300740015.json","sg:owner":"simplegeo","sg:postcode":"TW3 4LH","geom:latitude":51.475876,"sg:classifiers":[{"category":"Sports & Exercise","type":"Entertainment","subcategory":"Tennis Court"}],"sg:address":"38 Queenswood Av","sg:phone":"+44 20 8737 9866","wof:hierarchy":[{"locality_id":101750367,"venue_id":102560341,"country_id":85633159,"neighbourhood_id":85788147,"region_id":85684141}],"geom:area":0.000000,"sg:city":"Hounslow","wof:lastmodified":1438093232,"iso:country":"GB","wof:geomhash":"c61eb98d70c545dedba9c7be2b0c9d8b","wof:name":"Autolift","wof:belongsto":[101750367,85633159,85788147,85684141],"src:geom":"simplegeo","wof:placetype":"venue","wof:supersedes":[],"wof:id":102560341,"wof:superseded_by":[],"wof:concordances":{"sg:id":"SG_0DKGhReh0Wkjj7j62uFlt8_51.475876_-0.378571@1300740015"},"wof:parent_id":85788147}}