{
  "type": "Feature",
  "properties": {
    "addr:full":"38 Queenswood Av Hounslow Greater London TW3 4LH",
    "addr:housenumber":"38",
    "addr:postcode":"tw3 4lh",
    "addr:street":"Queenswood Av Hounslow",
    "iso:country":"GB",
    "sg:address":"38 Queenswood Av",
    "sg:city":"Hounslow",
    "sg:classifiers":[
        {
            "category":"Sports & Exercise",
            "subcategory":"Tennis Court",
            "type":"Entertainment"
        }
    ],
    "sg:href":"http://api.simplegeo.com/1.0/features/SG_0DKGhReh0Wkjj7j62uFlt8_51.475876_-0.378571@1300740015.json",
    "sg:phone":"+44 20 8737 9866",
    "sg:postcode":"TW3 4LH",
    "sg:province":"Greater London",
    "sg:tags":[
        "breakdown",
        "recovery"
    ],
    "wof:name":"Autolift",
    "wof:placetype":"venue"
},
  "geometry": {"coordinates":[-0.378571,51.475876],"type":"Point"}
}