{
  "type": "Feature",
  "properties": {
    "addr:full":"Unit 3 Fen Road Industrial Estate Huntingdon Bedfordshire PE28 3DD",
    "addr:housenumber":"unit 3",
    "addr:postcode":"pe28 3dd",
    "addr:street":"Fen Road Industrial Estate",
    "iso:country":"GB",
    "sg:address":"Unit 3 Fen Road Industrial Estate",
    "sg:city":"Huntingdon",
    "sg:classifiers":[
        {
            "category":"Retail",
            "subcategory":"Auto Repair",
            "type":"Services"
        }
    ],
    "sg:postcode":"PE28 3DD",
    "sg:province":"Bedfordshire",
    "sg:tags":[
        "modification",
        "garage"
    ],
    "wof:name":"Fairways Garage",
    "wof:placetype":"venue"
},
  "geometry": {"coordinates":[-0.044285,52.386471],"type":"Point"}
}