{
  "type": "Feature",
  "properties": {
    "iso:country":"GB",
    "sg:address":"20 Wessenden Bank, Offerton",
    "sg:city":"Stockport",
    "sg:classifiers":[
        {
            "category":"Building & Trades",
            "subcategory":"Construction",
            "type":"Services"
        }
    ],
    "sg:phone":"+44 161 456 6526",
    "sg:postcode":"SK2 5NA",
    "sg:province":"Cheshire",
    "sg:tags":[
        "roofing"
    ],
    "wof:name":"Buildrite Roofing",
    "wof:placetype":"venue"
},
  "geometry": {"coordinates":[-2.1246008873,53.3916435242],"type":"Point"}
}