{
  "type": "Feature",
  "properties": {
    "addr:full":"Blair Atholl Pitlochry Perth and Kinross PH18 5SG",
    "addr:postcode":"ph18 5sg",
    "iso:country":"GB",
    "sg:address":"Blair Atholl",
    "sg:city":"Pitlochry",
    "sg:classifiers":[
        {
            "category":"Travel",
            "subcategory":"Hotels & Motels",
            "type":"Entertainment"
        }
    ],
    "sg:phone":"+44 1796 481205",
    "sg:postcode":"PH18 5SG",
    "sg:province":"Perth and Kinross",
    "wof:name":"R T R Catering Ltd.",
    "wof:placetype":"venue"
},
  "geometry": {"coordinates":[-3.8479390144,56.7658462524],"type":"Point"}
}