{
  "type": "Feature",
  "properties": {
    "iso:country":"GB",
    "sg:address":"39 Ivel Way",
    "sg:city":"Baldock",
    "sg:classifiers":[
        {
            "category":"Building & Trades",
            "subcategory":"Plumbing",
            "type":"Services"
        }
    ],
    "sg:phone":"+44 1462 892482",
    "sg:postcode":"SG7 6LP",
    "sg:province":"Bedfordshire",
    "sg:tags":[
        "heating"
    ],
    "wof:name":"A.J Clark",
    "wof:placetype":"venue"
},
  "geometry": {"coordinates":[-0.1803690046,51.9810791016],"type":"Point"}
}