{
  "type": "Feature",
  "properties": {
    "addr:full":"5 Maristow St Westbury Wiltshire BA13 3DN",
    "addr:housenumber":"5",
    "addr:postcode":"ba13 3dn",
    "addr:street":"Maristow St",
    "iso:country":"GB",
    "sg:address":"5 Maristow St",
    "sg:city":"Westbury",
    "sg:classifiers":[
        {
            "category":"Shopping",
            "subcategory":"Clothing, Apparel, & Fashions",
            "type":"Retail Goods"
        }
    ],
    "sg:phone":"+44 1373 822174",
    "sg:postcode":"BA13 3DN",
    "sg:province":"Wiltshire",
    "sg:tags":[
        "menswear"
    ],
    "wof:name":"Suttons",
    "wof:placetype":"venue"
},
  "geometry": {"coordinates":[-2.182491,51.262264],"type":"Point"}
}