{
  "type": "Feature",
  "properties": {
    "addr:full":"The Old Town Hall, Temple Street Llandrindod Wells Powys LD1 5DL",
    "addr:postcode":"ld1 5dl",
    "addr:street":"Temple Street",
    "iso:country":"GB",
    "sg:address":"The Old Town Hall, Temple Street",
    "sg:city":"Llandrindod Wells",
    "sg:classifiers":[
        {
            "category":"Conference Center",
            "type":"Public Place"
        }
    ],
    "sg:phone":"+44 1597 824777",
    "sg:postcode":"LD1 5DL",
    "sg:province":"Powys",
    "sg:tags":[
        "business",
        "centre"
    ],
    "wof:name":"Business Connect Heart of Wales",
    "wof:placetype":"venue"
},
  "geometry": {"coordinates":[-3.3770289421,52.2457504272],"type":"Point"}
}