{
  "type": "Feature",
  "properties": {
    "addr:full":"1 Standish St Burnley Lancashire BB11 1AP",
    "addr:housenumber":"1",
    "addr:postcode":"bb11 1ap",
    "addr:street":"Standish St",
    "iso:country":"GB",
    "sg:address":"1 Standish St",
    "sg:city":"Burnley",
    "sg:classifiers":[
        {
            "category":"Organizations",
            "subcategory":"Non-profit Organization",
            "type":"Services"
        }
    ],
    "sg:postcode":"BB11 1AP",
    "sg:province":"Lancashire",
    "sg:tags":[
        "organisation",
        "voluntary",
        "charity"
    ],
    "wof:name":"Childrens Society (The)",
    "wof:placetype":"venue"
},
  "geometry": {"coordinates":[-2.2430570126,53.7907905579],"type":"Point"}
}