{
  "type": "Feature",
  "properties": {
    "iso:country":"GB",
    "sg:address":"Catterick Garrison, Vimy Barracks",
    "sg:city":"Catterick Garrison",
    "sg:classifiers":[
        {
            "category":"Organizations",
            "subcategory":"Membership Organization",
            "type":"Services"
        }
    ],
    "sg:phone":"+44 1748 833394",
    "sg:postcode":"DL9 3LT",
    "sg:province":"North Yorkshire",
    "sg:tags":[
        "club"
    ],
    "wof:name":"Junior Ranks Club",
    "wof:placetype":"venue"
},
  "geometry": {"coordinates":[-1.722312,54.376602],"type":"Point"}
}