{
  "type": "Feature",
  "properties": {
    "iso:country":"GB",
    "sg:address":"13 New Bridge St",
    "sg:city":"London",
    "sg:classifiers":[
        {
            "category":"Shopping",
            "subcategory":"Clothing, Apparel, & Fashions",
            "type":"Retail Goods"
        }
    ],
    "sg:postcode":"EC4V 6AU",
    "sg:province":"Greater London",
    "sg:tags":[
        "clothing"
    ],
    "wof:name":"Golf City",
    "wof:placetype":"venue"
},
  "geometry": {"coordinates":[-0.10442,51.512691],"type":"Point"}
}