{
  "type": "Feature",
  "properties": {
    "addr:full":"97-99 Queensway Stevenage Hertfordshire SG1 1EA",
    "addr:housenumber":"97-99",
    "addr:postcode":"sg1 1ea",
    "addr:street":"Queensway",
    "iso:country":"GB",
    "sg:address":"97-99 Queensway",
    "sg:city":"Stevenage",
    "sg:classifiers":[
        {
            "category":"Banks & Credit Unions",
            "subcategory":"Bank",
            "type":"Services"
        }
    ],
    "sg:phone":"+44 845 602 4610",
    "sg:postcode":"SG1 1EA",
    "sg:province":"Hertfordshire",
    "wof:name":"Halifax Plc",
    "wof:placetype":"venue"
},
  "geometry": {"coordinates":[-0.198279,51.899319],"type":"Point"}
}