{
  "type": "Feature",
  "properties": {
    "iso:country":"GB",
    "sg:address":"Unit 1, Far Field Road, Edenthorpe",
    "sg:city":"Doncaster",
    "sg:classifiers":[
        {
            "category":"Personal",
            "subcategory":"Beauty Salon",
            "type":"Services"
        }
    ],
    "sg:phone":"+44 1302 880580",
    "sg:postcode":"DN3 2NS",
    "sg:province":"South Yorkshire",
    "wof:name":"Masquerade Beauty Salon",
    "wof:placetype":"venue"
},
  "geometry": {"coordinates":[-1.0644129515,53.5566902161],"type":"Point"}
}