{
  "type": "Feature",
  "properties": {
    "addr:full":"23 Market Street, Whittlesey Peterborough Cambridgeshire PE7 1BA",
    "addr:housenumber":"23",
    "addr:postcode":"pe7 1ba",
    "addr:street":"Market Street",
    "iso:country":"GB",
    "sg:address":"23 Market Street, Whittlesey",
    "sg:city":"Peterborough",
    "sg:classifiers":[
        {
            "category":"Food & Beverages",
            "subcategory":"Meat & Fish",
            "type":"Retail Goods"
        }
    ],
    "sg:phone":"+44 1733 205919",
    "sg:postcode":"PE7 1BA",
    "sg:province":"Cambridgeshire",
    "sg:tags":[
        "chip"
    ],
    "wof:name":"Steven Lin",
    "wof:placetype":"venue"
},
  "geometry": {"coordinates":[-0.1298040003,52.5564498901],"type":"Point"}
}