{
  "type": "Feature",
  "properties": {
    "addr:full":"Beeches Bsns Park, Heysham Road Liverpool Merseyside L30 6UZ",
    "addr:postcode":"l30 6uz",
    "addr:street":"Heysham Road",
    "iso:country":"GB",
    "sg:address":"Beeches Bsns Park, Heysham Road",
    "sg:city":"Liverpool",
    "sg:classifiers":[
        {
            "category":"Home & Garden",
            "subcategory":"Kitchen Supply",
            "type":"Retail Goods"
        }
    ],
    "sg:phone":"+44 151 523 3334",
    "sg:postcode":"L30 6UZ",
    "sg:province":"Merseyside",
    "sg:tags":[
        "ware"
    ],
    "wof:name":"Paradigm (U K) Ltd.",
    "wof:placetype":"venue"
},
  "geometry": {"coordinates":[-2.95808,53.481972],"type":"Point"}
}