{
  "type": "Feature",
  "properties": {
    "iso:country":"GB",
    "sg:address":"Chirbury",
    "sg:city":"Montgomery",
    "sg:classifiers":[
        {
            "category":"Shopping",
            "subcategory":"Department Store",
            "type":"Retail Goods"
        }
    ],
    "sg:phone":"+44 1938 561201",
    "sg:postcode":"SY15 6BH",
    "sg:province":"Shropshire",
    "wof:name":"Chirbury Stores & Post Office",
    "wof:placetype":"venue"
},
  "geometry": {"coordinates":[-3.146039,52.564495],"type":"Point"}
}