{
  "type": "Feature",
  "properties": {
    "iso:country":"GB",
    "sg:address":"255-257 City Road, Fenton",
    "sg:city":"Stoke-on-trent",
    "sg:classifiers":[
        {
            "category":"Home & Garden",
            "subcategory":"Furniture",
            "type":"Retail Goods"
        }
    ],
    "sg:phone":"+44 1782 844315",
    "sg:postcode":"ST4 2PX",
    "sg:province":"Staffordshire",
    "wof:name":"Royal Oak Furnishers",
    "wof:placetype":"venue"
},
  "geometry": {"coordinates":[-2.164984,52.999725],"type":"Point"}
}