{
  "type": "Feature",
  "properties": {
    "addr:full":"100 Cambridge Street Rugby Warwickshire CV21 3NH",
    "addr:housenumber":"100",
    "addr:postcode":"cv21 3nh",
    "addr:street":"Cambridge Street",
    "iso:country":"GB",
    "sg:address":"100 Cambridge Street",
    "sg:city":"Rugby",
    "sg:classifiers":[
        {
            "category":"Shopping",
            "subcategory":"Bicycles & Sporting Goods",
            "type":"Retail Goods"
        }
    ],
    "sg:phone":"+44 1788 572440",
    "sg:postcode":"CV21 3NH",
    "sg:province":"Warwickshire",
    "sg:tags":[
        "cycle",
        "accessory"
    ],
    "wof:name":"Thorntons Cycle Centre",
    "wof:placetype":"venue"
},
  "geometry": {"coordinates":[-1.2472679615,52.3750076294],"type":"Point"}
}