{
  "type": "Feature",
  "properties": {
    "addr:full":"St Andrews Ho 26 Brighton Rd Crawley Surrey RH10 6AA",
    "addr:housenumber":"26",
    "addr:postcode":"rh10 6aa",
    "addr:street":"Brighton Rd",
    "iso:country":"GB",
    "sg:address":"St Andrews Ho 26 Brighton Rd",
    "sg:city":"Crawley",
    "sg:classifiers":[
        {
            "category":"Professional",
            "subcategory":"Engineering",
            "type":"Services"
        }
    ],
    "sg:phone":"+44 1293 543641",
    "sg:postcode":"RH10 6AA",
    "sg:province":"Surrey",
    "sg:tags":[
        "contractor",
        "electrical",
        "engineer"
    ],
    "wof:name":"Southern Electrical Services",
    "wof:placetype":"venue"
},
  "geometry": {"coordinates":[-0.184753,51.118458],"type":"Point"}
}