{
  "type": "Feature",
  "properties": {
    "addr:full":"Aged Persons Housing, The Shieling, Cairns Road Hexham Northumberland NE48 2DX",
    "addr:postcode":"ne48 2dx",
    "addr:street":"Cairns Road",
    "iso:country":"GB",
    "sg:address":"Aged Persons Housing, The Shieling, Cairns Road",
    "sg:city":"Hexham",
    "sg:classifiers":[
        {
            "category":"Social Services",
            "subcategory":"Adult Care",
            "type":"Services"
        }
    ],
    "sg:phone":"+44 1434 220406",
    "sg:postcode":"NE48 2DX",
    "sg:province":"Northumberland",
    "sg:tags":[
        "housing",
        "sheltered"
    ],
    "wof:name":"Tynedale Council",
    "wof:placetype":"venue"
},
  "geometry": {"coordinates":[-2.2574501038,55.1466407776],"type":"Point"}
}