{
  "type": "Feature",
  "properties": {
    "iso:country":"GB",
    "sg:address":"91 High Street",
    "sg:city":"Staines",
    "sg:classifiers":[
        {
            "category":"Professional",
            "subcategory":"Employment Agencies",
            "type":"Services"
        }
    ],
    "sg:phone":"+44 1784 458526",
    "sg:postcode":"TW18 4PQ",
    "sg:province":"Berkshire",
    "sg:tags":[
        "consultant",
        "recruitment"
    ],
    "sg:website":"http://www.reed.co.uk",
    "wof:name":"Reed Employment Ltd",
    "wof:placetype":"venue"
},
  "geometry": {"coordinates":[-0.5097360015,51.4344329834],"type":"Point"}
}