{
  "type": "Feature",
  "properties": {
    "iso:country":"GB",
    "sg:address":"315 Beulah Hill, Upper Norwood",
    "sg:city":"London",
    "sg:classifiers":[
        {
            "category":"Travel",
            "subcategory":"Hotels & Motels",
            "type":"Entertainment"
        }
    ],
    "sg:phone":"+44 20 8670 3744",
    "sg:postcode":"SE19 3HW",
    "sg:province":"Greater London",
    "wof:name":"Norfolk Court Hotel",
    "wof:placetype":"venue"
},
  "geometry": {"coordinates":[-0.1046079993,51.4187927246],"type":"Point"}
}