{
  "type": "Feature",
  "properties": {
    "addr:full":"78 Asheridge Road Chesham Buckinghamshire HP5 2PY",
    "addr:housenumber":"78",
    "addr:postcode":"hp5 2py",
    "addr:street":"Asheridge Road",
    "iso:country":"GB",
    "sg:address":"78 Asheridge Road",
    "sg:city":"Chesham",
    "sg:classifiers":[
        {
            "category":"Manufacturing",
            "subcategory":"Electronics",
            "type":"Manufacturing & Wholesale Goods"
        }
    ],
    "sg:phone":"+44 1494 791336",
    "sg:postcode":"HP5 2PY",
    "sg:province":"Buckinghamshire",
    "sg:tags":[
        "control",
        "component",
        "-",
        "electronic"
    ],
    "wof:name":"Jacarem Ltd.",
    "wof:placetype":"venue"
},
  "geometry": {"coordinates":[-0.620573,51.715874],"type":"Point"}
}