{
  "type": "Feature",
  "properties": {
    "addr:full":"25 Lochnell Street Lochgilphead Argyll and Bute PA31 8JL",
    "addr:housenumber":"25",
    "addr:postcode":"pa31 8jl",
    "addr:street":"Lochnell Street",
    "iso:country":"GB",
    "sg:address":"25 Lochnell Street",
    "sg:city":"Lochgilphead",
    "sg:classifiers":[
        {
            "category":"Shopping",
            "subcategory":"Shoes",
            "type":"Retail Goods"
        }
    ],
    "sg:postcode":"PA31 8JL",
    "sg:province":"Argyll and Bute",
    "sg:tags":[
        "shop"
    ],
    "wof:name":"Cinderella's",
    "wof:placetype":"venue"
},
  "geometry": {"coordinates":[-5.432431221,56.0364952087],"type":"Point"}
}