{
  "type": "Feature",
  "properties": {
    "iso:country":"GB",
    "sg:address":"15 Rosemount Road",
    "sg:city":"Bournemouth",
    "sg:classifiers":[
        {
            "category":"Travel",
            "subcategory":"Hotels & Motels",
            "type":"Entertainment"
        }
    ],
    "sg:phone":"+44 1202 761304",
    "sg:postcode":"BH4 8HB",
    "sg:province":"Dorset",
    "wof:name":"Upton Hall Hotel",
    "wof:placetype":"venue"
},
  "geometry": {"coordinates":[-1.902643,50.715698],"type":"Point"}
}