{
  "type": "Feature",
  "properties": {
    "iso:country":"GB",
    "sg:address":"Church Road, Wittering",
    "sg:city":"Peterborough",
    "sg:classifiers":[
        {
            "category":"Education",
            "subcategory":"School",
            "type":"Public Place"
        }
    ],
    "sg:phone":"+44 1780 782336",
    "sg:postcode":"PE8 6AF",
    "sg:province":"Cambridgeshire",
    "sg:tags":[
        "local",
        "authority"
    ],
    "wof:name":"Wittering County Primary School",
    "wof:placetype":"venue"
},
  "geometry": {"coordinates":[-0.4448580146,52.6089363098],"type":"Point"}
}