{
  "type": "Feature",
  "properties": {
    "addr:full":"170 Shrivenham Rd Swindon Wiltshire SN1 2NT",
    "addr:housenumber":"170",
    "addr:postcode":"sn1 2nt",
    "addr:street":"Shrivenham Rd",
    "iso:country":"GB",
    "sg:address":"170 Shrivenham Rd",
    "sg:city":"Swindon",
    "sg:classifiers":[
        {
            "category":"Building & Trades",
            "subcategory":"Plumbing",
            "type":"Services"
        }
    ],
    "sg:phone":"+44 1793 612579",
    "sg:postcode":"SN1 2NT",
    "sg:province":"Wiltshire",
    "sg:tags":[
        "central",
        "heating"
    ],
    "wof:name":"Ajd Heating & Plumbing",
    "wof:placetype":"venue"
},
  "geometry": {"coordinates":[-1.7648290396,51.5681686401],"type":"Point"}
}