{
  "type": "Feature",
  "properties": {
    "addr:full":"29 Tower Centre Hoddesdon Essex EN11 8UD",
    "addr:housenumber":"29",
    "addr:postcode":"en11 8ud",
    "addr:street":"Tower Centre Hoddesdon",
    "iso:country":"GB",
    "sg:address":"29 Tower Centre",
    "sg:city":"Hoddesdon",
    "sg:classifiers":[
        {
            "category":"Health Services",
            "subcategory":"Clinic",
            "type":"Services"
        }
    ],
    "sg:phone":"+44 1992 443300",
    "sg:postcode":"EN11 8UD",
    "sg:province":"Essex",
    "sg:tags":[
        "nh"
    ],
    "wof:name":"The Tower Centre Clinic",
    "wof:placetype":"venue"
},
  "geometry": {"coordinates":[-0.0123990001,51.7546234131],"type":"Point"}
}