{
  "type": "Feature",
  "properties": {
    "iso:country":"GB",
    "sg:address":"37 Lyndale Drive",
    "sg:city":"Wakefield",
    "sg:classifiers":[
        {
            "category":"Professional",
            "type":"Services"
        }
    ],
    "sg:phone":"+44 1924 314819",
    "sg:postcode":"WF2 0JZ",
    "sg:province":"West Yorkshire",
    "sg:tags":[
        "repair",
        "tech",
        "maintenance"
    ],
    "wof:name":"M-Tech Services (W R) Ltd.",
    "wof:placetype":"venue"
},
  "geometry": {"coordinates":[-1.525824,53.70026],"type":"Point"}
}