{
  "type": "Feature",
  "properties": {
    "iso:country":"GB",
    "sg:address":"99 Furnace Lane",
    "sg:city":"Sheffield",
    "sg:classifiers":[
        {
            "category":"Manufacturing",
            "subcategory":"Wood Products",
            "type":"Manufacturing & Wholesale Goods"
        }
    ],
    "sg:phone":"+44 114 254 0953",
    "sg:postcode":"S13 9XD",
    "sg:province":"South Yorkshire",
    "sg:tags":[
        "maker",
        "cabinet"
    ],
    "wof:name":"Purdy S Kitchens and Baths",
    "wof:placetype":"venue"
},
  "geometry": {"coordinates":[-1.352872,53.365669],"type":"Point"}
}