{
  "type": "Feature",
  "properties": {
    "addr:full":"Town Hall Chambers, 1 Quadrant (the) Wirral Merseyside CH47 2HR",
    "addr:housenumber":"1;wirral",
    "addr:postcode":"ch47 2hr",
    "addr:street":"Quadrant The",
    "iso:country":"GB",
    "sg:address":"Town Hall Chambers, 1 Quadrant (the)",
    "sg:city":"Wirral",
    "sg:classifiers":[
        {
            "category":"Professional",
            "subcategory":"Employment Agencies",
            "type":"Services"
        }
    ],
    "sg:phone":"+44 151 551 6400",
    "sg:postcode":"CH47 2HR",
    "sg:province":"Merseyside",
    "sg:tags":[
        "consultant"
    ],
    "wof:name":"Employment Service Jobcentre",
    "wof:placetype":"venue"
},
  "geometry": {"coordinates":[-3.17945,53.390701],"type":"Point"}
}