{
  "type": "Feature",
  "properties": {
    "addr:full":"9 Audrey Gardens Wembley Greater London HA0 3TF",
    "addr:housenumber":"9",
    "addr:postcode":"ha0 3tf",
    "addr:street":"Audrey Gardens",
    "iso:country":"GB",
    "sg:address":"9 Audrey Gardens",
    "sg:city":"Wembley",
    "sg:classifiers":[
        {
            "category":"Professional",
            "subcategory":"Art Services",
            "type":"Services"
        },
        {
            "category":"Building & Trades",
            "subcategory":"Construction",
            "type":"Services"
        }
    ],
    "sg:phone":"+44 20 8904 8390",
    "sg:postcode":"HA0 3TF",
    "sg:province":"Greater London",
    "sg:tags":[
        "decorator",
        "painter"
    ],
    "wof:name":"ABANESTA INTERIORS",
    "wof:placetype":"venue"
},
  "geometry": {"coordinates":[-0.315817,51.568882],"type":"Point"}
}