{
  "type": "Feature",
  "properties": {
    "addr:full":"Valley Road Cinderford Gloucestershire GL14 2LJ",
    "addr:postcode":"gl14 2lj",
    "addr:street":"Valley Road",
    "iso:country":"GB",
    "sg:address":"Valley Road",
    "sg:city":"Cinderford",
    "sg:classifiers":[
        {
            "category":"Social Services",
            "subcategory":"Adult Care",
            "type":"Services"
        }
    ],
    "sg:phone":"+44 1594 822088",
    "sg:postcode":"GL14 2LJ",
    "sg:province":"Gloucestershire",
    "sg:tags":[
        "day",
        "centre"
    ],
    "wof:name":"Royal Forest Centre",
    "wof:placetype":"venue"
},
  "geometry": {"coordinates":[-2.5060329437,51.8296127319],"type":"Point"}
}