{
  "type": "Feature",
  "properties": {
    "addr:full":"18 Front Street Stanley Durham DH9 0HX",
    "addr:housenumber":"18",
    "addr:postcode":"dh9 0hx",
    "addr:street":"Front Street",
    "iso:country":"GB",
    "sg:address":"18 Front Street",
    "sg:city":"Stanley",
    "sg:classifiers":[
        {
            "category":"Manufacturing",
            "subcategory":"Tools & Machinery",
            "type":"Manufacturing & Wholesale Goods"
        }
    ],
    "sg:phone":"+44 1207 233535",
    "sg:postcode":"DH9 0HX",
    "sg:province":"Durham",
    "sg:tags":[
        "society",
        "friendly"
    ],
    "wof:name":"Neil Cranston Insurance Services",
    "wof:placetype":"venue"
},
  "geometry": {"coordinates":[-1.6681330204,54.8535804749],"type":"Point"}
}