{
  "type": "Feature",
  "properties": {
    "iso:country":"GB",
    "sg:address":"Horton Road, Datchet",
    "sg:city":"Slough",
    "sg:classifiers":[
        {
            "category":"Education",
            "subcategory":"Library",
            "type":"Public Place"
        },
        {
            "category":"Government",
            "subcategory":"Office",
            "type":"Public Place"
        }
    ],
    "sg:phone":"+44 1753 545310",
    "sg:postcode":"SL3 9HR",
    "sg:province":"Berkshire",
    "sg:tags":[
        "book",
        "local"
    ],
    "wof:name":"Datchet Library",
    "wof:placetype":"venue"
},
  "geometry": {"coordinates":[-0.580488,51.484074],"type":"Point"}
}