{
  "type": "Feature",
  "properties": {
    "addr:full":"Unit 16 Long Meadow Mills Indust Est, Dixon St Kidderminster Staffordshire DY10 1HH",
    "addr:housenumber":"unit 16",
    "addr:postcode":"dy10 1hh",
    "addr:street":"Meadow Mills Indust Est;St",
    "iso:country":"GB",
    "sg:address":"Unit 16 Long Meadow Mills Indust Est, Dixon St",
    "sg:city":"Kidderminster",
    "sg:classifiers":[
        {
            "category":"Food & Beverages",
            "subcategory":"Candy",
            "type":"Retail Goods"
        }
    ],
    "sg:phone":"+44 1562 864395",
    "sg:postcode":"DY10 1HH",
    "sg:province":"Staffordshire",
    "sg:tags":[
        "confectionery"
    ],
    "wof:name":"G B Lucky Bags Co",
    "wof:placetype":"venue"
},
  "geometry": {"coordinates":[-2.2490839958,52.3881111145],"type":"Point"}
}