{
  "type": "Feature",
  "properties": {
    "iso:country":"GB",
    "sg:address":"24a Edward Road",
    "sg:city":"Dorchester",
    "sg:classifiers":[
        {
            "category":"Manufacturing",
            "subcategory":"Petroleum Products",
            "type":"Manufacturing & Wholesale Goods"
        }
    ],
    "sg:phone":"+44 1305 264299",
    "sg:postcode":"DT1 2HL",
    "sg:province":"Dorset",
    "sg:tags":[
        "double",
        "glazing"
    ],
    "wof:name":"Barretts Glass Centre",
    "wof:placetype":"venue"
},
  "geometry": {"coordinates":[-2.445232,50.709435],"type":"Point"}
}