{
  "type": "Feature",
  "properties": {
    "addr:full":"Russell Ho, Bepton Rd Midhurst West Sussex GU29 9NB",
    "addr:postcode":"gu29 9nb",
    "addr:street":"Bepton Rd",
    "iso:country":"GB",
    "sg:address":"Russell Ho, Bepton Rd",
    "sg:city":"Midhurst",
    "sg:classifiers":[
        {
            "category":"Professional",
            "subcategory":"Advertising",
            "type":"Services"
        }
    ],
    "sg:postcode":"GU29 9NB",
    "sg:province":"West Sussex",
    "wof:name":"Morris,Brian,",
    "wof:placetype":"venue"
},
  "geometry": {"coordinates":[-0.74058,50.984913],"type":"Point"}
}