{
  "type": "Feature",
  "properties": {
    "addr:full":"Unit 3 Beaufort Mews, 7 Horse Street, Chipping Sodbury Bristol Gloucestershire BS37 6DA",
    "addr:housenumber":"unit 3;7",
    "addr:postcode":"bs37 6da",
    "addr:street":"Beaufort;Horse Street Chipping;Bristol",
    "iso:country":"GB",
    "sg:address":"Unit 3 Beaufort Mews, 7 Horse Street, Chipping Sodbury",
    "sg:city":"Bristol",
    "sg:classifiers":[
        {
            "category":"Fast Food",
            "type":"Food & Drink"
        }
    ],
    "sg:phone":"+44 1454 312203",
    "sg:postcode":"BS37 6DA",
    "sg:province":"Gloucestershire",
    "sg:tags":[
        "away",
        "take"
    ],
    "wof:name":"At the Mews",
    "wof:placetype":"venue"
},
  "geometry": {"coordinates":[-2.386114,51.535542],"type":"Point"}
}