{
  "type": "Feature",
  "properties": {
    "iso:country":"GB",
    "sg:address":"201 Jesmond Road",
    "sg:city":"Newcastle-upon-tyne",
    "sg:classifiers":[
        {
            "category":"Personal",
            "subcategory":"Beauty Salon",
            "type":"Services"
        }
    ],
    "sg:phone":"+44 191 281 6714",
    "sg:postcode":"NE2 1LA",
    "sg:province":"Tyne and Wear",
    "sg:tags":[
        "unisex",
        "hairdresser"
    ],
    "wof:name":"Gary Hooker Hairdressing",
    "wof:placetype":"venue"
},
  "geometry": {"coordinates":[-1.595144,54.986881],"type":"Point"}
}