{
  "type": "Feature",
  "properties": {
    "addr:full":"18 Elmsleigh Road Paignton Devon TQ4 5AU",
    "addr:housenumber":"18",
    "addr:postcode":"tq4 5au",
    "addr:street":"Elmsleigh Road",
    "iso:country":"GB",
    "sg:address":"18 Elmsleigh Road",
    "sg:city":"Paignton",
    "sg:classifiers":[
        {
            "category":"Travel",
            "subcategory":"Hotels & Motels",
            "type":"Entertainment"
        }
    ],
    "sg:postcode":"TQ4 5AU",
    "sg:province":"Devon",
    "sg:tags":[
        "self",
        "catering"
    ],
    "wof:name":"Cherivale Holiday Flats",
    "wof:placetype":"venue"
},
  "geometry": {"coordinates":[-3.567155,50.431625],"type":"Point"}
}