{
  "type": "Feature",
  "properties": {
    "iso:country":"GB",
    "sg:address":"40 Lower High Street",
    "sg:city":"Burford",
    "sg:classifiers":[
        {
            "category":"Professional",
            "subcategory":"Management & Consulting",
            "type":"Services"
        }
    ],
    "sg:postcode":"OX18 4RR",
    "sg:province":"Gloucestershire",
    "sg:tags":[
        "consultant",
        "business"
    ],
    "wof:name":"Idea Mechanics",
    "wof:placetype":"venue"
},
  "geometry": {"coordinates":[-1.6350229979,51.8023376465],"type":"Point"}
}