{
  "type": "Feature",
  "properties": {
    "iso:country":"GB",
    "sg:address":"49 Station App, Hayes",
    "sg:city":"Bromley",
    "sg:classifiers":[
        {
            "category":"Travel",
            "subcategory":"Travel Agent",
            "type":"Entertainment"
        }
    ],
    "sg:phone":"+44 20 8462 8712",
    "sg:postcode":"BR2 7EB",
    "sg:province":"Kent",
    "wof:name":"Uniglobe Star Travel",
    "wof:placetype":"venue"
},
  "geometry": {"coordinates":[0.011054,51.375988],"type":"Point"}
}