{
  "type": "Feature",
  "properties": {
    "addr:full":"14 Rocks Lane London Greater London SW13 0DB",
    "addr:housenumber":"14",
    "addr:postcode":"sw13 0db",
    "addr:street":"Rocks Lane",
    "iso:country":"GB",
    "sg:address":"14 Rocks Lane",
    "sg:city":"London",
    "sg:classifiers":[
        {
            "category":"Health Services",
            "subcategory":"Health Practitioner",
            "type":"Services"
        }
    ],
    "sg:phone":"+44 20 8878 2213",
    "sg:postcode":"SW13 0DB",
    "sg:province":"Greater London",
    "sg:tags":[
        "psychologist"
    ],
    "wof:name":"Foxx Associates Ltd.",
    "wof:placetype":"venue"
},
  "geometry": {"coordinates":[-0.26068,51.466778],"type":"Point"}
}