{
  "type": "Feature",
  "properties": {
    "addr:full":"The Croft, Ludchurch Narberth Carmarthenshire SA67 8JA",
    "addr:postcode":"sa67 8ja",
    "iso:country":"GB",
    "sg:address":"The Croft, Ludchurch",
    "sg:city":"Narberth",
    "sg:classifiers":[
        {
            "category":"Farming",
            "subcategory":"Dairy Farm",
            "type":"Manufacturing & Wholesale Goods"
        }
    ],
    "sg:phone":"+44 1834 831661",
    "sg:postcode":"SA67 8JA",
    "sg:province":"Carmarthenshire",
    "wof:name":"E M & S F Jones",
    "wof:placetype":"venue"
},
  "geometry": {"coordinates":[-4.6957159042,51.7635231018],"type":"Point"}
}