{
  "type": "Feature",
  "properties": {
    "iso:country":"GB",
    "sg:address":"220 Grimshaw Lane, Middleton",
    "sg:city":"Manchester",
    "sg:classifiers":[
        {
            "category":"Building & Trades",
            "subcategory":"Landscaping Services",
            "type":"Services"
        }
    ],
    "sg:phone":"+44 161 654 6500",
    "sg:postcode":"M24 2AJ",
    "sg:province":"Greater Manchester",
    "sg:tags":[
        "landscape",
        "contractor"
    ],
    "wof:name":"Ray Sidlow",
    "wof:placetype":"venue"
},
  "geometry": {"coordinates":[-2.1792099476,53.5434265137],"type":"Point"}
}