{
  "type": "Feature",
  "properties": {
    "addr:full":"40-42 Bevois Valley Road Southampton Hampshire SO14 0JR",
    "addr:housenumber":"40-42",
    "addr:postcode":"so14 0jr",
    "addr:street":"Bevois Valley Road",
    "iso:country":"GB",
    "sg:address":"40-42 Bevois Valley Road",
    "sg:city":"Southampton",
    "sg:classifiers":[
        {
            "category":"Bars & Pubs",
            "type":"Food & Drink"
        }
    ],
    "sg:phone":"+44 23 8090 0529",
    "sg:postcode":"SO14 0JR",
    "sg:province":"Hampshire",
    "sg:tags":[
        "pubs",
        "inn"
    ],
    "wof:name":"W McDowall",
    "wof:placetype":"venue"
},
  "geometry": {"coordinates":[-1.3961390257,50.916431427],"type":"Point"}
}