{
  "type": "Feature",
  "properties": {
    "addr:full":"98 Red Lion Road, Tolworth Surbiton Surrey KT6 7QN",
    "addr:housenumber":"98",
    "addr:postcode":"kt6 7qn",
    "addr:street":"Red Lion Road",
    "iso:country":"GB",
    "sg:address":"98 Red Lion Road, Tolworth",
    "sg:city":"Surbiton",
    "sg:classifiers":[
        {
            "category":"Manufacturing",
            "subcategory":"Petroleum Products",
            "type":"Manufacturing & Wholesale Goods"
        },
        {
            "category":"Building & Trades",
            "subcategory":"Construction",
            "type":"Services"
        }
    ],
    "sg:phone":"+44 20 8399 3094",
    "sg:postcode":"KT6 7QN",
    "sg:province":"Surrey",
    "sg:tags":[
        "double",
        "glazing",
        "installers"
    ],
    "wof:name":"Jonman Contracts Ltd",
    "wof:placetype":"venue"
},
  "geometry": {"coordinates":[-0.29018,51.38068],"type":"Point"}
}