{
  "type": "Feature",
  "properties": {
    "iso:country":"GB",
    "sg:address":"Nutholme, Hooe",
    "sg:city":"Battle",
    "sg:classifiers":[
        {
            "category":"Farming",
            "subcategory":"Livestock Farm",
            "type":"Manufacturing & Wholesale Goods"
        }
    ],
    "sg:postcode":"TN33 9HD",
    "sg:province":"East Sussex",
    "sg:tags":[
        "others"
    ],
    "wof:name":"Neil C Smith",
    "wof:placetype":"venue"
},
  "geometry": {"coordinates":[0.398087,50.858673],"type":"Point"}
}