{
  "type": "Feature",
  "properties": {
    "iso:country":"GB",
    "sg:address":"95-97 Pasture Road",
    "sg:city":"Goole",
    "sg:classifiers":[
        {
            "category":"Shopping",
            "subcategory":"Clothing, Apparel, & Fashions",
            "type":"Retail Goods"
        }
    ],
    "sg:postcode":"DN14 6BP",
    "sg:province":"East Riding of Yorkshire",
    "sg:tags":[
        "menswear"
    ],
    "wof:name":"Outrigger",
    "wof:placetype":"venue"
},
  "geometry": {"coordinates":[-0.874843,53.706879],"type":"Point"}
}