{
  "type": "Feature",
  "properties": {
    "addr:full":"29 Bridge St Ellon Aberdeenshire AB41 9AA",
    "addr:housenumber":"29",
    "addr:postcode":"ab41 9aa",
    "addr:street":"Bridge St",
    "iso:country":"GB",
    "sg:address":"29 Bridge St",
    "sg:city":"Ellon",
    "sg:classifiers":[
        {
            "category":"Building & Trades",
            "subcategory":"Construction",
            "type":"Services"
        }
    ],
    "sg:phone":"+44 1358 720220",
    "sg:postcode":"AB41 9AA",
    "sg:province":"Aberdeenshire",
    "sg:tags":[
        "decorator",
        "painter"
    ],
    "wof:name":"Lawrence Milne & Sons",
    "wof:placetype":"venue"
},
  "geometry": {"coordinates":[-2.074422,57.365376],"type":"Point"}
}