{
  "type": "Feature",
  "properties": {
    "addr:full":"Crown Hill Rayleigh Essex SS6 7HA",
    "addr:postcode":"ss6 7ha",
    "addr:street":"Hill Rayleigh",
    "iso:country":"GB",
    "sg:address":"Crown Hill",
    "sg:city":"Rayleigh",
    "sg:classifiers":[
        {
            "category":"Place Of Worship",
            "type":"Public Place"
        }
    ],
    "sg:phone":"+44 1268 777185",
    "sg:postcode":"SS6 7HA",
    "sg:province":"Essex",
    "wof:name":"Christ Church United Reform Church",
    "wof:placetype":"venue"
},
  "geometry": {"coordinates":[0.600685,51.588749],"type":"Point"}
}