{
  "type": "Feature",
  "properties": {
    "iso:country":"GB",
    "sg:address":"385 Hoylake Rd, Moreton",
    "sg:city":"Wirral",
    "sg:classifiers":[
        {
            "category":"Food & Beverages",
            "subcategory":"Groceries & Convenience Stores",
            "type":"Retail Goods"
        }
    ],
    "sg:phone":"+44 151 677 3588",
    "sg:postcode":"L46 0RW",
    "sg:province":"Cheshire",
    "wof:name":"Meadowbrook Stores",
    "wof:placetype":"venue"
},
  "geometry": {"coordinates":[-3.11192,53.401932],"type":"Point"}
}