{
  "type": "Feature",
  "properties": {
    "addr:full":"183-191 Ballards Lane London Greater London N3 1LP",
    "addr:postcode":"183-191;n3 1lp",
    "addr:street":"Ballards Lane",
    "iso:country":"GB",
    "sg:address":"183-191 Ballards Lane",
    "sg:city":"London",
    "sg:classifiers":[
        {
            "category":"Professional",
            "subcategory":"Computer Services",
            "type":"Services"
        }
    ],
    "sg:phone":"+44 7775 645099",
    "sg:postcode":"N3 1LP",
    "sg:province":"Greater London",
    "sg:tags":[
        "system",
        "software"
    ],
    "wof:name":"Zonebuild Ltd.",
    "wof:placetype":"venue"
},
  "geometry": {"coordinates":[-0.187312007,51.6060028076],"type":"Point"}
}