{
  "type": "Feature",
  "properties": {
    "addr:full":"10 Marine Road, Broad Haven Haverfordwest Pembrokeshire SA62 3JR",
    "addr:housenumber":"10",
    "addr:postcode":"sa62 3jr",
    "addr:street":"Marine Road",
    "iso:country":"GB",
    "sg:address":"10 Marine Road, Broad Haven",
    "sg:city":"Haverfordwest",
    "sg:classifiers":[
        {
            "category":"Transit Center",
            "subcategory":"Freight",
            "type":"Transportation"
        }
    ],
    "sg:phone":"+44 1437 781555",
    "sg:postcode":"SA62 3JR",
    "sg:province":"Pembrokeshire",
    "sg:tags":[
        "shop",
        "craft",
        "centre"
    ],
    "wof:name":"The Welsh Dresser",
    "wof:placetype":"venue"
},
  "geometry": {"coordinates":[-5.1024918556,51.7797279358],"type":"Point"}
}