{
  "type": "Feature",
  "properties": {
    "iso:country":"GB",
    "sg:address":"32 Freeman Street",
    "sg:city":"Grimsby",
    "sg:classifiers":[
        {
            "category":"Home & Garden",
            "subcategory":"Household Appliances",
            "type":"Retail Goods"
        },
        {
            "category":"Retail",
            "subcategory":"Repair Shop",
            "type":"Services"
        }
    ],
    "sg:postcode":"DN32 7AG",
    "sg:province":"Lincolnshire",
    "sg:tags":[
        "electrical",
        "television",
        "video",
        "radio"
    ],
    "wof:name":"Avs",
    "wof:placetype":"venue"
},
  "geometry": {"coordinates":[-0.073168,53.574013],"type":"Point"}
}