{
  "type": "Feature",
  "properties": {
    "iso:country":"GB",
    "sg:address":"1 Glamis Centre",
    "sg:city":"Glenrothes",
    "sg:classifiers":[
        {
            "category":"Bars & Pubs",
            "type":"Food & Drink"
        }
    ],
    "sg:phone":"+44 1592 776901",
    "sg:postcode":"KY7 4RH",
    "sg:province":"Fife",
    "sg:tags":[
        "pubs",
        "inn"
    ],
    "wof:name":"Wee Cooper The",
    "wof:placetype":"venue"
},
  "geometry": {"coordinates":[-3.164719,56.182823],"type":"Point"}
}