{
  "type": "Feature",
  "properties": {
    "addr:full":"265-267 Old Kent Rd Southwark Greater London SE1 5LU",
    "addr:housenumber":"265-267",
    "addr:postcode":"se1 5lu",
    "addr:street":"Old Kent Rd",
    "iso:country":"GB",
    "sg:address":"265-267 Old Kent Rd",
    "sg:city":"Southwark",
    "sg:classifiers":[
        {
            "category":"Food & Beverages",
            "subcategory":"Supermarket",
            "type":"Retail Goods"
        }
    ],
    "sg:phone":"+44 20 7231 9530",
    "sg:postcode":"SE1 5LU",
    "sg:province":"Greater London",
    "wof:name":"Trivea Food & Wine",
    "wof:placetype":"venue"
},
  "geometry": {"coordinates":[-0.0792699978,51.4897651672],"type":"Point"}
}