{
  "type": "Feature",
  "properties": {
    "iso:country":"GB",
    "sg:address":"97 Sevier Street, St Wherburgs",
    "sg:city":"Bristol",
    "sg:classifiers":[
        {
            "category":"Retail",
            "subcategory":"Auto Repair",
            "type":"Services"
        }
    ],
    "sg:phone":"+44 117 955 8548",
    "sg:postcode":"BS2 9QX",
    "sg:province":"City of Bristol",
    "sg:tags":[
        "modification",
        "garage"
    ],
    "wof:name":"Heron Garage",
    "wof:placetype":"venue"
},
  "geometry": {"coordinates":[-2.575763,51.469402],"type":"Point"}
}