{
  "type": "Feature",
  "properties": {
    "iso:country":"GB",
    "sg:address":"16 Stafford Street",
    "sg:city":"Norwich",
    "sg:classifiers":[
        {
            "category":"Bars & Pubs",
            "type":"Food & Drink"
        }
    ],
    "sg:postcode":"NR2 3BB",
    "sg:province":"Norfolk",
    "sg:tags":[
        "pubs",
        "inn"
    ],
    "wof:name":"Alexandra Tavern",
    "wof:placetype":"venue"
},
  "geometry": {"coordinates":[1.276379,52.632389],"type":"Point"}
}