{
  "type": "Feature",
  "properties": {
    "addr:full":"222 Main Road, Hawkwell Hockley Essex SS5 4EG",
    "addr:housenumber":"222",
    "addr:postcode":"ss5 4eg",
    "addr:street":"Main Road;Hockley",
    "iso:country":"GB",
    "sg:address":"222 Main Road, Hawkwell",
    "sg:city":"Hockley",
    "sg:classifiers":[
        {
            "category":"Utilities",
            "subcategory":"Electric",
            "type":"Services"
        }
    ],
    "sg:postcode":"SS5 4EG",
    "sg:province":"Essex",
    "sg:tags":[
        "vehicle"
    ],
    "wof:name":"Associated Vehicle Services",
    "wof:placetype":"venue"
},
  "geometry": {"coordinates":[0.664704,51.597641],"type":"Point"}
}