{
  "type": "Feature",
  "properties": {
    "addr:full":"284 Heneage Road Grimsby Lincolnshire DN32 9NW",
    "addr:housenumber":"284",
    "addr:postcode":"dn32 9nw",
    "addr:street":"Heneage Road",
    "iso:country":"GB",
    "sg:address":"284 Heneage Road",
    "sg:city":"Grimsby",
    "sg:classifiers":[
        {
            "category":"Personal",
            "subcategory":"Beauty Salon",
            "type":"Services"
        },
        {
            "category":"Personal",
            "subcategory":"Barber",
            "type":"Services"
        }
    ],
    "sg:phone":"+44 1472 342386",
    "sg:postcode":"DN32 9NW",
    "sg:province":"Lincolnshire",
    "sg:tags":[
        "unisex",
        "hairdresser"
    ],
    "wof:name":"Headmaster",
    "wof:placetype":"venue"
},
  "geometry": {"coordinates":[-0.072905,53.557766],"type":"Point"}
}