{
  "type": "Feature",
  "properties": {
    "iso:country":"GB",
    "sg:address":"Shiloh House, Hickman Avenue",
    "sg:city":"Wolverhampton",
    "sg:classifiers":[
        {
            "category":"Professional",
            "subcategory":"Lawyer & Legal Services",
            "type":"Services"
        }
    ],
    "sg:phone":"+44 1902 871250",
    "sg:postcode":"WV1 2BS",
    "sg:province":"West Midlands",
    "sg:tags":[
        "advice",
        "counselling"
    ],
    "wof:name":"Mount Shiloh Health Advisory Centre",
    "wof:placetype":"venue"
},
  "geometry": {"coordinates":[-2.1051540375,52.5832633972],"type":"Point"}
}