{
  "type": "Feature",
  "properties": {
    "addr:full":"Towneley Park Burnley Lancashire BB11 3RQ",
    "addr:postcode":"bb11 3rq",
    "addr:street":"Burnley",
    "iso:country":"GB",
    "sg:address":"Towneley Park",
    "sg:city":"Burnley",
    "sg:classifiers":[
        {
            "category":"Restaurant",
            "type":"Food & Drink"
        }
    ],
    "sg:phone":"+44 1282 430111",
    "sg:postcode":"BB11 3RQ",
    "sg:province":"Lancashire",
    "wof:name":"Old Stables The",
    "wof:placetype":"venue"
},
  "geometry": {"coordinates":[-2.2331819534,53.7770767212],"type":"Point"}
}