{
  "type": "Feature",
  "properties": {
    "addr:full":"96 Bramhall La Stockport Cheshire SK2 6JG",
    "addr:housenumber":"96",
    "addr:postcode":"sk2 6jg",
    "addr:street":"La Stockport",
    "iso:country":"GB",
    "sg:address":"96 Bramhall La",
    "sg:city":"Stockport",
    "sg:classifiers":[
        {
            "category":"Building & Trades",
            "subcategory":"Plumbing",
            "type":"Services"
        }
    ],
    "sg:phone":"+44 161 483 6668",
    "sg:postcode":"SK2 6JG",
    "sg:province":"Cheshire",
    "sg:tags":[
        "heating"
    ],
    "wof:name":"R & K Mather",
    "wof:placetype":"venue"
},
  "geometry": {"coordinates":[-2.1529738903,53.3940391541],"type":"Point"}
}