{
  "type": "Feature",
  "properties": {
    "addr:full":"18 Fore Street Redruth Cornwall TR15 2BD",
    "addr:housenumber":"18",
    "addr:postcode":"tr15 2bd",
    "addr:street":"Fore Street",
    "iso:country":"GB",
    "sg:address":"18 Fore Street",
    "sg:city":"Redruth",
    "sg:classifiers":[
        {
            "category":"Shopping",
            "subcategory":"Gifts & Souvenirs",
            "type":"Retail Goods"
        }
    ],
    "sg:phone":"+44 1209 211101",
    "sg:postcode":"TR15 2BD",
    "sg:province":"Cornwall",
    "sg:tags":[
        "greeting",
        "card"
    ],
    "wof:name":"Bargain Cards",
    "wof:placetype":"venue"
},
  "geometry": {"coordinates":[-5.2287011147,50.2332572937],"type":"Point"}
}