{
  "type": "Feature",
  "properties": {
    "addr:full":"7 Autumn Crescent Leeds West Yorkshire LS18 4HT",
    "addr:housenumber":"7",
    "addr:postcode":"ls18 4ht",
    "addr:street":"Autumn Crescent",
    "iso:country":"GB",
    "sg:address":"7 Autumn Crescent",
    "sg:city":"Leeds",
    "sg:classifiers":[
        {
            "category":"Professional",
            "type":"Services"
        }
    ],
    "sg:postcode":"LS18 4HT",
    "sg:province":"West Yorkshire",
    "sg:tags":[
        "directory",
        "pub"
    ],
    "wof:name":"Abbey Design & Printing Services",
    "wof:placetype":"venue"
},
  "geometry": {"coordinates":[-1.6270639896,53.8324508667],"type":"Point"}
}