{
  "type": "Feature",
  "properties": {
    "addr:full":"12 North Silver St Aberdeen Aberdeen City AB1 1RL",
    "addr:housenumber":"12",
    "addr:postcode":"ab1 1rl",
    "addr:street":"North Silver St",
    "iso:country":"GB",
    "sg:address":"12 North Silver St",
    "sg:city":"Aberdeen",
    "sg:classifiers":[
        {
            "category":"Professional",
            "subcategory":"Management & Consulting",
            "type":"Services"
        }
    ],
    "sg:phone":"+44 1224 620001",
    "sg:postcode":"AB1 1RL",
    "sg:province":"Aberdeen City",
    "sg:tags":[
        "consultant",
        "business"
    ],
    "wof:name":"Romsa Systems Ltd",
    "wof:placetype":"venue"
},
  "geometry": {"coordinates":[-2.1055719852,57.1467704773],"type":"Point"}
}