{
  "type": "Feature",
  "properties": {
    "addr:full":"55a Flaxpiece Road, Clay Cross Chesterfield Derbyshire S45 9HD",
    "addr:housenumber":"55a",
    "addr:postcode":"s45 9hd",
    "addr:street":"Flaxpiece Road",
    "iso:country":"GB",
    "sg:address":"55a Flaxpiece Road, Clay Cross",
    "sg:city":"Chesterfield",
    "sg:classifiers":[
        {
            "category":"Personal",
            "subcategory":"Beauty Salon",
            "type":"Services"
        }
    ],
    "sg:phone":"+44 1246 863060",
    "sg:postcode":"S45 9HD",
    "sg:province":"Derbyshire",
    "sg:tags":[
        "unisex",
        "hairdresser"
    ],
    "wof:name":"Danesmoor Hair Fashions",
    "wof:placetype":"venue"
},
  "geometry": {"coordinates":[-1.4096859694,53.1618461609],"type":"Point"}
}