{
  "type": "Feature",
  "properties": {
    "iso:country":"GB",
    "sg:address":"2 Peartree Ct",
    "sg:city":"Clerkenwell",
    "sg:classifiers":[
        {
            "category":"Professional",
            "subcategory":"Lawyer & Legal Services",
            "type":"Services"
        }
    ],
    "sg:phone":"+44 20 7253 1563",
    "sg:postcode":"EC1R 0DS",
    "sg:province":"Greater London",
    "sg:tags":[
        "patent",
        "agent"
    ],
    "wof:name":"Batchellor Kirk & Co",
    "wof:placetype":"venue"
},
  "geometry": {"coordinates":[-0.1074900031,51.5240287781],"type":"Point"}
}