{
  "type": "Feature",
  "properties": {
    "addr:full":"22 Prince Maurice Road Plymouth Devon PL4 7LJ",
    "addr:housenumber":"22",
    "addr:postcode":"pl4 7lj",
    "addr:street":"Prince Maurice Road",
    "iso:country":"GB",
    "sg:address":"22 Prince Maurice Road",
    "sg:city":"Plymouth",
    "sg:classifiers":[
        {
            "category":"Professional",
            "subcategory":"Engineering",
            "type":"Services"
        }
    ],
    "sg:postcode":"PL4 7LJ",
    "sg:province":"Devon",
    "sg:tags":[
        "engineer",
        "structural"
    ],
    "wof:name":"Mast & Tower Inspectorate",
    "wof:placetype":"venue"
},
  "geometry": {"coordinates":[-4.126772,50.380821],"type":"Point"}
}