{
  "type": "Feature",
  "properties": {
    "iso:country":"GB",
    "sg:address":"70 Main Street",
    "sg:city":"Barry",
    "sg:classifiers":[
        {
            "category":"Retail",
            "subcategory":"Laundry & Dry Cleaning",
            "type":"Services"
        },
        {
            "category":"Manufacturing",
            "subcategory":"Signs",
            "type":"Manufacturing & Wholesale Goods"
        }
    ],
    "sg:postcode":"CF63 2HN",
    "sg:province":"The Vale of Glamorgan",
    "sg:tags":[
        "launderette",
        "nameplate"
    ],
    "wof:name":"The Wash Inn",
    "wof:placetype":"venue"
},
  "geometry": {"coordinates":[-3.254421,51.413673],"type":"Point"}
}