{
  "type": "Feature",
  "properties": {
    "iso:country":"GB",
    "sg:address":"112 Coatsworth Road",
    "sg:city":"Gateshead",
    "sg:classifiers":[
        {
            "category":"Personal",
            "subcategory":"Barber",
            "type":"Services"
        }
    ],
    "sg:phone":"+44 191 477 7494",
    "sg:postcode":"NE8 1QQ",
    "sg:province":"Tyne and Wear",
    "sg:tags":[
        "men's",
        "hairdresser"
    ],
    "wof:name":"Paul's Barber Shop",
    "wof:placetype":"venue"
},
  "geometry": {"coordinates":[-1.602046,54.96104],"type":"Point"}
}