{
  "type": "Feature",
  "properties": {
    "addr:full":"25 Kenmore Cott Oban Argyll and Bute PA37 1RJ",
    "addr:housenumber":"25",
    "addr:postcode":"pa37 1rj",
    "iso:country":"GB",
    "sg:address":"25 Kenmore Cott",
    "sg:city":"Oban",
    "sg:classifiers":[
        {
            "category":"Government",
            "subcategory":"Post Office",
            "type":"Public Place"
        }
    ],
    "sg:phone":"+44 1631 750232",
    "sg:postcode":"PA37 1RJ",
    "sg:province":"Argyll and Bute",
    "wof:name":"Bonawe Sub Post Office",
    "wof:placetype":"venue"
},
  "geometry": {"coordinates":[-5.3811688423,56.4751777649],"type":"Point"}
}