{
  "type": "Feature",
  "properties": {
    "addr:full":"181 Broomloan Rd Glasgow Glasgow City G51 2JE",
    "addr:housenumber":"181",
    "addr:postcode":"g51 2je",
    "addr:street":"Broomloan Rd",
    "iso:country":"GB",
    "sg:address":"181 Broomloan Rd",
    "sg:city":"Glasgow",
    "sg:classifiers":[
        {
            "category":"Retail",
            "subcategory":"Auto Repair",
            "type":"Services"
        }
    ],
    "sg:phone":"+44 141 445 2899",
    "sg:postcode":"G51 2JE",
    "sg:province":"Glasgow City",
    "sg:tags":[
        "modification",
        "garage"
    ],
    "wof:name":"J W Autos",
    "wof:placetype":"venue"
},
  "geometry": {"coordinates":[-4.312332,55.851269],"type":"Point"}
}