{
  "type": "Feature",
  "properties": {
    "iso:country":"GB",
    "sg:address":"44 Newcombe Rd",
    "sg:city":"Northampton",
    "sg:classifiers":[
        {
            "category":"Building & Trades",
            "subcategory":"Construction",
            "type":"Services"
        }
    ],
    "sg:phone":"+44 1604 754078",
    "sg:postcode":"NN5 7AZ",
    "sg:province":"Northamptonshire",
    "sg:tags":[
        "decorator",
        "painter"
    ],
    "wof:name":"W B Clarke",
    "wof:placetype":"venue"
},
  "geometry": {"coordinates":[-0.915667,52.242851],"type":"Point"}
}