{
  "type": "Feature",
  "properties": {
    "addr:full":"23 Foster Lane Hebden Bridge West Yorkshire HX7 8JZ",
    "addr:housenumber":"23",
    "addr:postcode":"hx7 8jz",
    "addr:street":"Foster Lane",
    "iso:country":"GB",
    "sg:address":"23 Foster Lane",
    "sg:city":"Hebden Bridge",
    "sg:classifiers":[
        {
            "category":"Personal",
            "subcategory":"Beauty Salon",
            "type":"Services"
        }
    ],
    "sg:phone":"+44 1422 842552",
    "sg:postcode":"HX7 8JZ",
    "sg:province":"West Yorkshire",
    "sg:tags":[
        "ladies",
        "lady",
        "hairdresser"
    ],
    "wof:name":"Cathys Hair Stylist",
    "wof:placetype":"venue"
},
  "geometry": {"coordinates":[-2.011196,53.745621],"type":"Point"}
}