{
  "type": "Feature",
  "properties": {
    "addr:full":"Ocean Spirit House, 33 Waterloo Quay Aberdeen Aberdeen City AB11 5BS",
    "addr:housenumber":"33",
    "addr:postcode":"ab11 5bs",
    "addr:street":"Waterloo Quay",
    "iso:country":"GB",
    "sg:address":"Ocean Spirit House, 33 Waterloo Quay",
    "sg:city":"Aberdeen",
    "sg:classifiers":[
        {
            "category":"Utilities",
            "subcategory":"Fuel Oil & Lpg",
            "type":"Services"
        }
    ],
    "sg:phone":"+44 1224 585331",
    "sg:postcode":"AB11 5BS",
    "sg:province":"Aberdeen City",
    "sg:tags":[
        "gas"
    ],
    "wof:name":"VAM Field Service International",
    "wof:placetype":"venue"
},
  "geometry": {"coordinates":[-2.083209,57.145489],"type":"Point"}
}