{
  "type": "Feature",
  "properties": {
    "addr:full":"Fosse House, High Street Moreton-in-marsh Gloucestershire GL56 0LH",
    "addr:postcode":"gl56 0lh",
    "addr:street":"High Street",
    "iso:country":"GB",
    "sg:address":"Fosse House, High Street",
    "sg:city":"Moreton-in-marsh",
    "sg:classifiers":[
        {
            "category":"Real Estate",
            "subcategory":"Real Estate Agent",
            "type":"Services"
        }
    ],
    "sg:phone":"+44 1608 650502",
    "sg:postcode":"GL56 0LH",
    "sg:province":"Gloucestershire",
    "wof:name":"Strutt & Parker",
    "wof:placetype":"venue"
},
  "geometry": {"coordinates":[-1.7031639814,51.9901008606],"type":"Point"}
}