{
  "type": "Feature",
  "properties": {
    "iso:country":"GB",
    "sg:address":"5 The Dencora Centre, Dundee Way",
    "sg:city":"Enfield",
    "sg:classifiers":[
        {
            "category":"Home & Garden",
            "subcategory":"Household Appliances",
            "type":"Retail Goods"
        }
    ],
    "sg:phone":"+44 20 8443 9999",
    "sg:postcode":"EN3 7SX",
    "sg:province":"Greater London",
    "sg:tags":[
        "electrical"
    ],
    "wof:name":"American Appliance Centre Ltd.",
    "wof:placetype":"venue"
},
  "geometry": {"coordinates":[-0.0313,51.64893],"type":"Point"}
}