{
  "type": "Feature",
  "properties": {
    "addr:full":"Bank Top, Station Road Prudhoe Northumberland NE42 5PY",
    "addr:postcode":"ne42 5py",
    "addr:street":"Station Road",
    "iso:country":"GB",
    "sg:address":"Bank Top, Station Road",
    "sg:city":"Prudhoe",
    "sg:classifiers":[
        {
            "category":"Autos & Motor Vehicles",
            "subcategory":"Motorcycle Sales",
            "type":"Retail Goods"
        }
    ],
    "sg:phone":"+44 1661 833913",
    "sg:postcode":"NE42 5PY",
    "sg:province":"Northumberland",
    "wof:name":"Bewick School of Motoring",
    "wof:placetype":"venue"
},
  "geometry": {"coordinates":[-1.850924,54.961655],"type":"Point"}
}