{
  "type": "Feature",
  "properties": {
    "iso:country":"GB",
    "sg:address":"Old Post Office",
    "sg:city":"Avoch",
    "sg:classifiers":[
        {
            "category":"Shopping",
            "subcategory":"Antiques",
            "type":"Retail Goods"
        }
    ],
    "sg:postcode":"IV9 8RQ",
    "sg:province":"Highland",
    "wof:name":"Hesling,Jack,",
    "wof:placetype":"venue"
},
  "geometry": {"coordinates":[-4.16898489,57.5672073364],"type":"Point"}
}