{
  "type": "Feature",
  "properties": {
    "iso:country":"GB",
    "sg:address":"Rear Of Ham Villa, West End, Foxham",
    "sg:city":"Chippenham",
    "sg:classifiers":[
        {
            "category":"Travel",
            "subcategory":"Travel Agent",
            "type":"Entertainment"
        }
    ],
    "sg:phone":"+44 1249 740260",
    "sg:postcode":"SN15 4NB",
    "sg:province":"Wiltshire",
    "wof:name":"AC Hillier",
    "wof:placetype":"venue"
},
  "geometry": {"coordinates":[-2.0359179974,51.4942550659],"type":"Point"}
}