{
  "type": "Feature",
  "properties": {
    "addr:full":"The Chase, Wivenhoe Road, Alresford Colchester Essex CO7 8AJ",
    "addr:postcode":"co7 8aj",
    "addr:street":"Wivenhoe Road",
    "iso:country":"GB",
    "sg:address":"The Chase, Wivenhoe Road, Alresford",
    "sg:city":"Colchester",
    "sg:classifiers":[
        {
            "category":"Professional",
            "subcategory":"Art Services",
            "type":"Services"
        }
    ],
    "sg:phone":"+44 1206 827008",
    "sg:postcode":"CO7 8AJ",
    "sg:province":"Essex",
    "sg:tags":[
        "photographer",
        "graphic",
        "designer"
    ],
    "wof:name":"Warren Graphics",
    "wof:placetype":"venue"
},
  "geometry": {"coordinates":[1.0072029829,51.853225708],"type":"Point"}
}