{
  "type": "Feature",
  "properties": {
    "addr:full":"546 Lytham Road Blackpool Lancashire FY4 1RE",
    "addr:housenumber":"546",
    "addr:postcode":"fy4 1re",
    "addr:street":"Lytham Road",
    "iso:country":"GB",
    "sg:address":"546 Lytham Road",
    "sg:city":"Blackpool",
    "sg:classifiers":[
        {
            "category":"Health Services",
            "subcategory":"Clinic",
            "type":"Services"
        }
    ],
    "sg:phone":"+44 1253 345210",
    "sg:postcode":"FY4 1RE",
    "sg:province":"Lancashire",
    "sg:tags":[
        "aromatherapy"
    ],
    "wof:name":"Maureen Mechen",
    "wof:placetype":"venue"
},
  "geometry": {"coordinates":[-3.047378,53.786419],"type":"Point"}
}