{
  "type": "Feature",
  "properties": {
    "iso:country":"GB",
    "sg:address":"127 Lynchford Rd",
    "sg:city":"Farnborough",
    "sg:classifiers":[
        {
            "category":"Manufacturing",
            "subcategory":"Electronics",
            "type":"Manufacturing & Wholesale Goods"
        }
    ],
    "sg:phone":"+44 1252 548018",
    "sg:postcode":"GU14 6ET",
    "sg:province":"Hampshire",
    "sg:tags":[
        "mnfr",
        "component",
        "electronic"
    ],
    "wof:name":"Basic Components",
    "wof:placetype":"venue"
},
  "geometry": {"coordinates":[-0.747455,51.274479],"type":"Point"}
}