{
  "type": "Feature",
  "properties": {
    "iso:country":"GB",
    "sg:address":"130-132 Desborough Road",
    "sg:city":"High Wycombe",
    "sg:classifiers":[
        {
            "category":"Professional",
            "subcategory":"Computer Services",
            "type":"Services"
        }
    ],
    "sg:postcode":"HP11 2PU",
    "sg:province":"Buckinghamshire",
    "sg:tags":[
        "system",
        "software"
    ],
    "wof:name":"Kingsley Computers Ltd.",
    "wof:placetype":"venue"
},
  "geometry": {"coordinates":[-0.7590939999,51.631187439],"type":"Point"}
}