{
  "type": "Feature",
  "properties": {
    "iso:country":"GB",
    "sg:address":"Unit A Victoria Road West",
    "sg:city":"Thornton-cleveleys",
    "sg:classifiers":[
        {
            "category":"Shopping",
            "subcategory":"Catalog Store",
            "type":"Retail Goods"
        }
    ],
    "sg:phone":"+44 1253 826252",
    "sg:postcode":"FY5 1BS",
    "sg:province":"Lancashire",
    "sg:tags":[
        "catalogue",
        "showroom"
    ],
    "wof:name":"Argos Distributors",
    "wof:placetype":"venue"
},
  "geometry": {"coordinates":[-3.022859,53.873226],"type":"Point"}
}