{
  "type": "Feature",
  "properties": {
    "addr:full":"41 Topping Street Blackpool Lancashire FY1 3AF",
    "addr:housenumber":"41",
    "addr:postcode":"fy1 3af",
    "addr:street":"Topping Street",
    "iso:country":"GB",
    "sg:address":"41 Topping Street",
    "sg:city":"Blackpool",
    "sg:classifiers":[
        {
            "category":"Home & Garden",
            "subcategory":"Furniture",
            "type":"Retail Goods"
        }
    ],
    "sg:phone":"+44 1253 622618",
    "sg:postcode":"FY1 3AF",
    "sg:province":"Lancashire",
    "wof:name":"Lefton S",
    "wof:placetype":"venue"
},
  "geometry": {"coordinates":[-3.050558,53.819454],"type":"Point"}
}