{
  "type": "Feature",
  "properties": {
    "iso:country":"GB",
    "sg:address":"1 Union Street",
    "sg:city":"Fareham",
    "sg:classifiers":[
        {
            "category":"Real Estate",
            "subcategory":"Surveying",
            "type":"Services"
        }
    ],
    "sg:phone":"+44 1329 230870",
    "sg:postcode":"PO16 7XX",
    "sg:province":"Hampshire",
    "sg:tags":[
        "surveyor",
        "valuer"
    ],
    "wof:name":"Paul Beason & Partners",
    "wof:placetype":"venue"
},
  "geometry": {"coordinates":[-1.17379,50.852299],"type":"Point"}
}