{
  "type": "Feature",
  "properties": {
    "addr:full":"Eastmill Estate Brechin Aberdeenshire DD9 7EL",
    "addr:postcode":"dd9 7el",
    "iso:country":"GB",
    "sg:address":"Eastmill Estate",
    "sg:city":"Brechin",
    "sg:classifiers":[
        {
            "category":"Shopping",
            "subcategory":"Computers & Home Electronics",
            "type":"Retail Goods"
        }
    ],
    "sg:phone":"+44 1356 626826",
    "sg:postcode":"DD9 7EL",
    "sg:province":"Aberdeenshire",
    "sg:tags":[
        "consumables"
    ],
    "wof:name":"Ribbon Revival Grafitay",
    "wof:placetype":"venue"
},
  "geometry": {"coordinates":[-2.6588079929,56.7705574036],"type":"Point"}
}