{
  "type": "Feature",
  "properties": {
    "addr:full":"Thamesgate House, 37 Victoria Av Southend On Sea Essex SS2 6JW",
    "addr:housenumber":"37",
    "addr:postcode":"ss2 6jw",
    "addr:street":"Thamesgate;Victoria Av Southend On Sea",
    "iso:country":"GB",
    "sg:address":"Thamesgate House, 37 Victoria Av",
    "sg:city":"Southend On Sea",
    "sg:classifiers":[
        {
            "category":"Insurance",
            "subcategory":"Insurance Agent",
            "type":"Services"
        }
    ],
    "sg:phone":"+44 1702 353833",
    "sg:postcode":"SS2 6JW",
    "sg:province":"Essex",
    "sg:tags":[
        "broker"
    ],
    "wof:name":"E J Welton Co Ltd",
    "wof:placetype":"venue"
},
  "geometry": {"coordinates":[0.708825,51.543396],"type":"Point"}
}