{
  "type": "Feature",
  "properties": {
    "addr:full":"9 Falconers Field Harpenden Hertfordshire AL5 3EU",
    "addr:housenumber":"9",
    "addr:postcode":"al5 3eu",
    "addr:street":"Falconers Field",
    "iso:country":"GB",
    "sg:address":"9 Falconers Field",
    "sg:city":"Harpenden",
    "sg:classifiers":[
        {
            "category":"Professional",
            "subcategory":"Management & Consulting",
            "type":"Services"
        }
    ],
    "sg:phone":"+44 1582 460474",
    "sg:postcode":"AL5 3EU",
    "sg:province":"Hertfordshire",
    "sg:tags":[
        "consultant",
        "business"
    ],
    "wof:name":"Barton Management Associates",
    "wof:placetype":"venue"
},
  "geometry": {"coordinates":[-0.377023,51.823666],"type":"Point"}
}