{
  "type": "Feature",
  "properties": {
    "addr:full":"538 High Road London Greater London N17 9SY",
    "addr:housenumber":"538",
    "addr:postcode":"n17 9sy",
    "addr:street":"High Road",
    "iso:country":"GB",
    "sg:address":"538 High Road",
    "sg:city":"London",
    "sg:classifiers":[
        {
            "category":"Shopping",
            "subcategory":"Mobile Phones",
            "type":"Retail Goods"
        }
    ],
    "sg:postcode":"N17 9SY",
    "sg:province":"Greater London",
    "sg:tags":[
        "supplier"
    ],
    "wof:name":"RINGERS MOBILE PHONES",
    "wof:placetype":"venue"
},
  "geometry": {"coordinates":[-0.069087,51.594864],"type":"Point"}
}