{
  "type": "Feature",
  "properties": {
    "iso:country":"GB",
    "sg:address":"78a Kent Road",
    "sg:city":"Nottingham",
    "sg:classifiers":[
        {
            "category":"Building & Trades",
            "subcategory":"Plumbing",
            "type":"Services"
        }
    ],
    "sg:postcode":"NG3 6BN",
    "sg:province":"Nottinghamshire",
    "sg:tags":[
        "heating"
    ],
    "wof:name":"Robert Briggs",
    "wof:placetype":"venue"
},
  "geometry": {"coordinates":[-1.1186180115,52.9811515808],"type":"Point"}
}