{
  "type": "Feature",
  "properties": {
    "iso:country":"GB",
    "sg:address":"1 Lewis Terrace, Llanbradach",
    "sg:city":"Caerphilly",
    "sg:classifiers":[
        {
            "category":"Shopping",
            "subcategory":"News",
            "type":"Retail Goods"
        }
    ],
    "sg:phone":"+44 29 2086 2240",
    "sg:postcode":"CF83 3JZ",
    "sg:province":"Caerphilly",
    "sg:tags":[
        "newsagent"
    ],
    "wof:name":"P & A Williams",
    "wof:placetype":"venue"
},
  "geometry": {"coordinates":[-3.225851059,51.5815391541],"type":"Point"}
}