{
  "type": "Feature",
  "properties": {
    "addr:full":"30 Station Road Rowlands Gill Durham NE39 1PZ",
    "addr:housenumber":"30",
    "addr:postcode":"ne39 1pz",
    "addr:street":"Station Road",
    "iso:country":"GB",
    "sg:address":"30 Station Road",
    "sg:city":"Rowlands Gill",
    "sg:classifiers":[
        {
            "category":"Real Estate",
            "subcategory":"Real Estate Agent",
            "type":"Services"
        }
    ],
    "sg:phone":"+44 1207 542266",
    "sg:postcode":"NE39 1PZ",
    "sg:province":"Durham",
    "wof:name":"Rook Matthews Sayer",
    "wof:placetype":"venue"
},
  "geometry": {"coordinates":[-1.7425960302,54.9198532104],"type":"Point"}
}