{
  "type": "Feature",
  "properties": {
    "iso:country":"GB",
    "sg:address":"26 Dolphin Road",
    "sg:city":"Shoreham-by-sea",
    "sg:classifiers":[
        {
            "category":"Shopping",
            "subcategory":"Clothing, Apparel, & Fashions",
            "type":"Retail Goods"
        }
    ],
    "sg:phone":"+44 1273 463710",
    "sg:postcode":"BN43 6PS",
    "sg:province":"West Sussex",
    "sg:tags":[
        "shop",
        "clothing",
        "fabric"
    ],
    "wof:name":"Claremont Factory Shop",
    "wof:placetype":"venue"
},
  "geometry": {"coordinates":[-0.261602,50.833458],"type":"Point"}
}