{
  "type": "Feature",
  "properties": {
    "addr:full":"Newlands House, Arundel Road Arundel West Sussex BN18 0PJ",
    "addr:postcode":"bn18 0pj",
    "addr:street":"Arundel Road",
    "iso:country":"GB",
    "sg:address":"Newlands House, Arundel Road",
    "sg:city":"Arundel",
    "sg:classifiers":[
        {
            "category":"Health Services",
            "subcategory":"Health Practitioner",
            "type":"Services"
        }
    ],
    "sg:phone":"+44 1243 554031",
    "sg:postcode":"BN18 0PJ",
    "sg:province":"West Sussex",
    "sg:tags":[
        "physiotherapist"
    ],
    "wof:name":"Simpson Physiotherapy Clinic",
    "wof:placetype":"venue"
},
  "geometry": {"coordinates":[-0.597108,50.857426],"type":"Point"}
}