{
  "type": "Feature",
  "properties": {
    "iso:country":"GB",
    "sg:address":"Middle Chare",
    "sg:city":"Chester-le-street",
    "sg:classifiers":[
        {
            "category":"Shopping",
            "subcategory":"Pharmacy",
            "type":"Retail Goods"
        }
    ],
    "sg:phone":"+44 191 388 4857",
    "sg:postcode":"DH3 3QD",
    "sg:province":"Durham",
    "sg:tags":[
        "pharmacist",
        "dispensing",
        "chemist"
    ],
    "wof:name":"Middle Chare Pharmacy Ltd",
    "wof:placetype":"venue"
},
  "geometry": {"coordinates":[-1.5729290247,54.8557815552],"type":"Point"}
}