{
  "type": "Feature",
  "properties": {
    "addr:full":"Unit 20, The Courtyard, Montpellier Street Cheltenham Gloucestershire GL50 1SR",
    "addr:housenumber":"unit 20",
    "addr:postcode":"gl50 1sr",
    "addr:street":"The Courtyard Montpellier Street",
    "iso:country":"GB",
    "sg:address":"Unit 20, The Courtyard, Montpellier Street",
    "sg:city":"Cheltenham",
    "sg:classifiers":[
        {
            "category":"Home & Garden",
            "subcategory":"Carpets & Floor Coverings",
            "type":"Retail Goods"
        }
    ],
    "sg:phone":"+44 1242 238611",
    "sg:postcode":"GL50 1SR",
    "sg:province":"Gloucestershire",
    "sg:tags":[
        "carpets",
        "rug",
        "matting"
    ],
    "wof:name":"Carpet Shop Plus Ltd.",
    "wof:placetype":"venue"
},
  "geometry": {"coordinates":[-2.0784590244,51.8980484009],"type":"Point"}
}