{
  "type": "Feature",
  "properties": {
    "iso:country":"GB",
    "sg:address":"Unit 6-7 Lee Mills Industrial Park, Scholes",
    "sg:city":"Huddersfield",
    "sg:classifiers":[
        {
            "category":"Building & Trades",
            "subcategory":"Plumbing",
            "type":"Services"
        }
    ],
    "sg:phone":"+44 1484 689055",
    "sg:postcode":"HD9 1SS",
    "sg:province":"South Yorkshire",
    "sg:tags":[
        "drain",
        "clearance",
        "sewer"
    ],
    "wof:name":"C S G Eurovac Ltd.",
    "wof:placetype":"venue"
},
  "geometry": {"coordinates":[-1.7635339499,53.5634460449],"type":"Point"}
}