{
  "type": "Feature",
  "properties": {
    "addr:full":"Foss House Garage York North Yorkshire YO31 7UR",
    "addr:postcode":"yo31 7ur",
    "iso:country":"GB",
    "sg:address":"Foss House Garage",
    "sg:city":"York",
    "sg:classifiers":[
        {
            "category":"Retail",
            "subcategory":"Storage",
            "type":"Services"
        }
    ],
    "sg:phone":"+44 1904 613578",
    "sg:postcode":"YO31 7UR",
    "sg:province":"North Yorkshire",
    "sg:tags":[
        "household",
        "removal"
    ],
    "wof:name":"Always Removals & Storage",
    "wof:placetype":"venue"
},
  "geometry": {"coordinates":[-1.0717899799,53.9589691162],"type":"Point"}
}