{
  "type": "Feature",
  "properties": {
    "iso:country":"GB",
    "sg:address":"Vintin Terrace",
    "sg:city":"Porthcawl",
    "sg:classifiers":[
        {
            "category":"Building & Trades",
            "subcategory":"Construction",
            "type":"Services"
        }
    ],
    "sg:href":"http://api.simplegeo.com/1.0/features/SG_3xGH0KRitjbfwkUU1iQwG4_51.482079_-3.697089@1300740015.json",
    "sg:phone":"+44 1656 786336",
    "sg:postcode":"CF36 5LS",
    "sg:province":"Bridgend",
    "sg:tags":[
        "roofing",
        "joiner",
        "carpenter",
        "contracting"
    ],
    "wof:name":"J M C Ryan & Son",
    "wof:placetype":"venue"
},
  "geometry": {"coordinates":[-3.697089,51.482079],"type":"Point"}
}