{"geometry":{"type":"Point","coordinates":[-3.697089,51.482079]},"type":"Feature","id":102560975,"bbox":[-3.697089,51.482079,-3.697089,51.482079],"properties":{"sg:province":"Bridgend","sg:tags":["roofing","joiner","carpenter","contracting"],"geom:longitude":-3.697089,"wof:breaches":[],"sg:href":"http://api.simplegeo.com/1.0/features/SG_3xGH0KRitjbfwkUU1iQwG4_51.482079_-3.697089@1300740015.json","sg:owner":"simplegeo","sg:postcode":"CF36 5LS","geom:latitude":51.482079,"sg:classifiers":[{"category":"Building & Trades","type":"Services","subcategory":"Construction"}],"sg:address":"Vintin Terrace","sg:phone":"+44 1656 786336","wof:hierarchy":[{"locality_id":101852765,"venue_id":102560975,"country_id":85633159,"region_id":85684263}],"geom:area":0.000000,"sg:city":"Porthcawl","wof:lastmodified":1438093423,"iso:country":"GB","wof:geomhash":"d919413a37f5a308120fcf6d46d9ca7d","wof:name":"J M C Ryan & Son","wof:belongsto":[101852765,85633159,85684263],"src:geom":"simplegeo","wof:placetype":"venue","wof:supersedes":[],"wof:id":102560975,"wof:superseded_by":[],"wof:concordances":{"sg:id":"SG_3xGH0KRitjbfwkUU1iQwG4_51.482079_-3.697089@1300740015"},"wof:parent_id":101852765}}