{
  "type": "Feature",
  "properties": {
    "addr:full":"20 Chorlton Gro Wallasey Merseyside CH45 8QQ",
    "addr:housenumber":"20",
    "addr:postcode":"ch45 8qq",
    "addr:street":"Chorlton Gro",
    "iso:country":"GB",
    "sg:address":"20 Chorlton Gro",
    "sg:city":"Wallasey",
    "sg:classifiers":[
        {
            "category":"Professional",
            "subcategory":"Business Services",
            "type":"Services"
        }
    ],
    "sg:phone":"+44 151 630 1883",
    "sg:postcode":"CH45 8QQ",
    "sg:province":"Merseyside",
    "sg:tags":[
        "accomodation"
    ],
    "wof:name":"Meghna Ltd.",
    "wof:placetype":"venue"
},
  "geometry": {"coordinates":[-3.074404,53.420612],"type":"Point"}
}