{
  "type": "Feature",
  "properties": {
    "addr:full":"197 Cottenham Park Road London Greater London SW20 0SY",
    "addr:housenumber":"197",
    "addr:postcode":"sw20 0sy",
    "addr:street":"Cottenham Park Road",
    "iso:country":"GB",
    "sg:address":"197 Cottenham Park Road",
    "sg:city":"London",
    "sg:classifiers":[
        {
            "category":"Transit Center",
            "subcategory":"Passenger",
            "type":"Transportation"
        }
    ],
    "sg:phone":"+44 20 8946 2815",
    "sg:postcode":"SW20 0SY",
    "sg:province":"Greater London",
    "sg:tags":[
        "airport"
    ],
    "wof:name":"Airport Car Service Wimbledon",
    "wof:placetype":"venue"
},
  "geometry": {"coordinates":[-0.24493,51.413967],"type":"Point"}
}