{
  "type": "Feature",
  "properties": {
    "iso:country":"GB",
    "sg:address":"44 Goldsmith Drive",
    "sg:city":"Newport Pagnell",
    "sg:classifiers":[
        {
            "category":"Professional",
            "subcategory":"Computer Services",
            "type":"Services"
        }
    ],
    "sg:phone":"+44 1908 211753",
    "sg:postcode":"MK16 8RS",
    "sg:province":"Buckinghamshire",
    "sg:tags":[
        "consultant"
    ],
    "wof:name":"Androcom Business Services",
    "wof:placetype":"venue"
},
  "geometry": {"coordinates":[-0.7477930188,52.0855102539],"type":"Point"}
}