{
  "type": "Feature",
  "properties": {
    "addr:full":"9 Bradford Rd Cleckheaton West Yorkshire BD19 5AG",
    "addr:housenumber":"9",
    "addr:postcode":"bd19 5ag",
    "addr:street":"Bradford Rd",
    "iso:country":"GB",
    "sg:address":"9 Bradford Rd",
    "sg:city":"Cleckheaton",
    "sg:classifiers":[
        {
            "category":"Food & Beverages",
            "subcategory":"Liquor & Beverages",
            "type":"Retail Goods"
        }
    ],
    "sg:phone":"+44 1274 852681",
    "sg:postcode":"BD19 5AG",
    "sg:province":"West Yorkshire",
    "sg:tags":[
        "beer",
        "spirit",
        "wines"
    ],
    "wof:name":"Berkeley Wines",
    "wof:placetype":"venue"
},
  "geometry": {"coordinates":[-1.712313,53.72435],"type":"Point"}
}