{
  "type": "Feature",
  "properties": {
    "addr:full":"22 Buddon Lane, Quorn Loughborough Leicestershire LE12 8AA",
    "addr:housenumber":"22",
    "addr:postcode":"le12 8aa",
    "addr:street":"Buddon Lane",
    "iso:country":"GB",
    "sg:address":"22 Buddon Lane, Quorn",
    "sg:city":"Loughborough",
    "sg:classifiers":[
        {
            "category":"Building & Trades",
            "subcategory":"Construction",
            "type":"Services"
        }
    ],
    "sg:postcode":"LE12 8AA",
    "sg:province":"Leicestershire",
    "sg:tags":[
        "builder"
    ],
    "wof:name":"S G Turner & Sons Ltd.",
    "wof:placetype":"venue"
},
  "geometry": {"coordinates":[-1.183477,52.738487],"type":"Point"}
}