{
  "type": "Feature",
  "properties": {
    "addr:full":"107 Trent Blvd Nottingham Nottinghamshire NG2 5BN",
    "addr:housenumber":"107",
    "addr:postcode":"ng2 5bn",
    "addr:street":"Trent Blvd",
    "iso:country":"GB",
    "sg:address":"107 Trent Blvd",
    "sg:city":"Nottingham",
    "sg:classifiers":[
        {
            "category":"Food & Beverages",
            "subcategory":"Liquor & Beverages",
            "type":"Retail Goods"
        }
    ],
    "sg:phone":"+44 115 982 1476",
    "sg:postcode":"NG2 5BN",
    "sg:province":"Nottinghamshire",
    "sg:tags":[
        "beer",
        "spirit",
        "wines"
    ],
    "wof:name":"Booze Buster",
    "wof:placetype":"venue"
},
  "geometry": {"coordinates":[-1.1202869415,52.9385185242],"type":"Point"}
}