{
  "type": "Feature",
  "properties": {
    "iso:country":"GB",
    "sg:address":"Unit 2, Johnson Street",
    "sg:city":"Manchester",
    "sg:classifiers":[
        {
            "category":"Building & Trades",
            "subcategory":"Construction",
            "type":"Services"
        }
    ],
    "sg:postcode":"M15 4BL",
    "sg:province":"Cheshire",
    "sg:tags":[
        "roofing"
    ],
    "wof:name":"Range Roofing Ltd.",
    "wof:placetype":"venue"
},
  "geometry": {"coordinates":[-2.2633190155,53.465473175],"type":"Point"}
}