{
  "type": "Feature",
  "properties": {
    "iso:country":"GB",
    "sg:address":"4 Bodmin Street",
    "sg:city":"Holsworthy",
    "sg:classifiers":[
        {
            "category":"Health Services",
            "subcategory":"Optometrist",
            "type":"Services"
        }
    ],
    "sg:phone":"+44 1409 253215",
    "sg:postcode":"EX22 6BB",
    "sg:province":"Cornwall",
    "sg:tags":[
        "optician"
    ],
    "wof:name":"Batemans (Opticians)",
    "wof:placetype":"venue"
},
  "geometry": {"coordinates":[-4.353085041,50.8092346191],"type":"Point"}
}