{
  "type": "Feature",
  "properties": {
    "addr:full":"2 Ellon Road, Bridge Of Don Aberdeen Aberdeen City AB23 8EA",
    "addr:housenumber":"2",
    "addr:postcode":"ab23 8ea",
    "addr:street":"Ellon Road",
    "iso:country":"GB",
    "sg:address":"2 Ellon Road, Bridge Of Don",
    "sg:city":"Aberdeen",
    "sg:classifiers":[
        {
            "category":"Bars & Pubs",
            "type":"Food & Drink"
        },
        {
            "category":"Community Center",
            "subcategory":"Social",
            "type":"Public Place"
        }
    ],
    "sg:phone":"+44 1224 703239",
    "sg:postcode":"AB23 8EA",
    "sg:province":"Aberdeen City",
    "sg:tags":[
        "pubs",
        "house",
        "inn",
        "activity"
    ],
    "wof:name":"Don View Bar",
    "wof:placetype":"venue"
},
  "geometry": {"coordinates":[-2.0899159908,57.1765098572],"type":"Point"}
}