{
  "type": "Feature",
  "properties": {
    "iso:country":"GB",
    "sg:address":"Unit G Baxtergate Freshney Place",
    "sg:city":"Grimsby",
    "sg:classifiers":[
        {
            "category":"Shopping",
            "subcategory":"Books",
            "type":"Retail Goods"
        }
    ],
    "sg:phone":"+44 1472 353212",
    "sg:postcode":"DN31 1QL",
    "sg:province":"Lincolnshire",
    "sg:tags":[
        "bookseller"
    ],
    "wof:name":"Ottakar's Plc",
    "wof:placetype":"venue"
},
  "geometry": {"coordinates":[-0.0868399963,53.5662689209],"type":"Point"}
}