{
  "type": "Feature",
  "properties": {
    "addr:full":"107 The Business Village, Broomhill Rd Wandsworth Greater London SW18 4JQ",
    "addr:housenumber":"107",
    "addr:postcode":"sw18 4jq",
    "addr:street":"The Business Village Broomhill Rd",
    "iso:country":"GB",
    "sg:address":"107 The Business Village, Broomhill Rd",
    "sg:city":"Wandsworth",
    "sg:classifiers":[
        {
            "category":"Building & Trades",
            "subcategory":"Construction",
            "type":"Services"
        }
    ],
    "sg:phone":"+44 20 8871 5074",
    "sg:postcode":"SW18 4JQ",
    "sg:province":"Greater London",
    "sg:tags":[
        "joinery"
    ],
    "wof:name":"Giffordmead",
    "wof:placetype":"venue"
},
  "geometry": {"coordinates":[-0.194479,51.456871],"type":"Point"}
}