{
  "type": "Feature",
  "properties": {
    "addr:full":"83a Great Stone Road, Stretford Manchester Cheshire M32 8GR",
    "addr:housenumber":"83a",
    "addr:postcode":"m32 8gr",
    "addr:street":"Great Stone Road",
    "iso:country":"GB",
    "sg:address":"83a Great Stone Road, Stretford",
    "sg:city":"Manchester",
    "sg:classifiers":[
        {
            "category":"Professional",
            "type":"Services"
        },
        {
            "category":"Health Services",
            "subcategory":"Health Practitioner",
            "type":"Services"
        },
        {
            "category":"Shopping",
            "subcategory":"Pharmacy",
            "type":"Retail Goods"
        }
    ],
    "sg:phone":"+44 161 881 3421",
    "sg:postcode":"M32 8GR",
    "sg:province":"Cheshire",
    "sg:tags":[
        "medicine",
        "reflexologists",
        "hypnotherapists",
        "therapy"
    ],
    "wof:name":"Human Touch",
    "wof:placetype":"venue"
},
  "geometry": {"coordinates":[-2.2862389088,53.4527168274],"type":"Point"}
}