{
  "type": "Feature",
  "properties": {
    "addr:full":"4a St. Georges Place Brighton East Sussex BN1 4GA",
    "addr:housenumber":"4a",
    "addr:postcode":"bn1 4ga",
    "addr:street":"St. Georges Place",
    "iso:country":"GB",
    "sg:address":"4a St. Georges Place",
    "sg:city":"Brighton",
    "sg:classifiers":[
        {
            "category":"Professional",
            "subcategory":"Accounting & Tax Preparation",
            "type":"Services"
        }
    ],
    "sg:phone":"+44 1273 231366",
    "sg:postcode":"BN1 4GA",
    "sg:province":"East Sussex",
    "sg:tags":[
        "accountant"
    ],
    "wof:name":"Aiden Accounting Associates",
    "wof:placetype":"venue"
},
  "geometry": {"coordinates":[-0.1354189962,50.8274688721],"type":"Point"}
}