{
  "type": "Feature",
  "properties": {
    "iso:country":"GB",
    "sg:address":"84 Wide Bargate",
    "sg:city":"Boston",
    "sg:classifiers":[
        {
            "category":"Health Services",
            "subcategory":"Optometrist",
            "type":"Services"
        },
        {
            "category":"Shopping",
            "subcategory":"Optician",
            "type":"Retail Goods"
        }
    ],
    "sg:phone":"+44 1205 311181",
    "sg:postcode":"PE21 6SE",
    "sg:province":"Lincolnshire",
    "sg:tags":[
        "ophthalmic"
    ],
    "wof:name":"Enderbys Of Boston",
    "wof:placetype":"venue"
},
  "geometry": {"coordinates":[-0.019565,52.981262],"type":"Point"}
}