{
  "type": "Feature",
  "properties": {
    "iso:country":"GB",
    "sg:address":"Anne Dale County Infant School, Cuckoo Lane, Stubbington",
    "sg:city":"Fareham",
    "sg:classifiers":[
        {
            "category":"Education",
            "subcategory":"School",
            "type":"Public Place"
        }
    ],
    "sg:postcode":"PO14 3PH",
    "sg:province":"Hampshire",
    "sg:tags":[
        "local",
        "authority"
    ],
    "wof:name":"Crofton Anne Dale Infant School",
    "wof:placetype":"venue"
},
  "geometry": {"coordinates":[-1.21988,50.823738],"type":"Point"}
}