{
  "type": "Feature",
  "properties": {
    "addr:full":"Unit 3 Forgeside Cwmbran Monmouthshire NP44 3LN",
    "addr:housenumber":"unit 3",
    "addr:postcode":"np44 3ln",
    "addr:street":"Forgeside",
    "iso:country":"GB",
    "sg:address":"Unit 3 Forgeside",
    "sg:city":"Cwmbran",
    "sg:classifiers":[
        {
            "category":"Retail",
            "subcategory":"Auto Repair",
            "type":"Services"
        }
    ],
    "sg:postcode":"NP44 3LN",
    "sg:province":"Monmouthshire",
    "sg:tags":[
        "modification",
        "garage"
    ],
    "wof:name":"M W Auto Services",
    "wof:placetype":"venue"
},
  "geometry": {"coordinates":[-3.0254189968,51.6552619934],"type":"Point"}
}