{
  "type": "Feature",
  "properties": {
    "addr:full":"Unit 21 Alma Works, Alma Street Bradford West Yorkshire BD4 9JE",
    "addr:housenumber":"unit 21",
    "addr:postcode":"bd4 9je",
    "addr:street":"Alma Works Alma Street",
    "iso:country":"GB",
    "sg:address":"Unit 21 Alma Works, Alma Street",
    "sg:city":"Bradford",
    "sg:classifiers":[
        {
            "category":"Manufacturing",
            "subcategory":"Metals",
            "type":"Manufacturing & Wholesale Goods"
        },
        {
            "category":"Manufacturing",
            "subcategory":"Tools & Machinery",
            "type":"Manufacturing & Wholesale Goods"
        }
    ],
    "sg:phone":"+44 1274 686795",
    "sg:postcode":"BD4 9JE",
    "sg:province":"West Yorkshire",
    "sg:tags":[
        "foundry",
        "supply"
    ],
    "wof:name":"Bernard Beaumont Engineer",
    "wof:placetype":"venue"
},
  "geometry": {"coordinates":[-1.7190400362,53.7795600891],"type":"Point"}
}