{
  "type": "Feature",
  "properties": {
    "addr:full":"Muller Road, M32, Eastville Park Bristol City of Bristol BS5 6PX",
    "addr:postcode":"m32;bs5 6px",
    "addr:street":"Muller Road;Park",
    "iso:country":"GB",
    "sg:address":"Muller Road, M32, Eastville Park",
    "sg:city":"Bristol",
    "sg:classifiers":[
        {
            "category":"Autos & Motor Vehicles",
            "subcategory":"Fuel & Gas Station",
            "type":"Retail Goods"
        }
    ],
    "sg:phone":"+44 117 958 0000",
    "sg:postcode":"BS5 6PX",
    "sg:province":"City of Bristol",
    "sg:tags":[
        "hr",
        "filling",
        "petrol"
    ],
    "wof:name":"Shell Eastville Park",
    "wof:placetype":"venue"
},
  "geometry": {"coordinates":[-2.560383,51.476555],"type":"Point"}
}