{
  "type": "Feature",
  "properties": {
    "addr:full":"Rockstone Dauby Lane, Kexby York East Riding of Yorkshire YO41 5LH",
    "addr:postcode":"yo41 5lh",
    "addr:street":"Dauby Lane",
    "iso:country":"GB",
    "sg:address":"Rockstone Dauby Lane, Kexby",
    "sg:city":"York",
    "sg:classifiers":[
        {
            "category":"Building & Trades",
            "subcategory":"Construction",
            "type":"Services"
        }
    ],
    "sg:postcode":"YO41 5LH",
    "sg:province":"East Riding of Yorkshire",
    "sg:tags":[
        "joiner",
        "carpenter"
    ],
    "wof:name":"Eddie Van Beveren Ltd",
    "wof:placetype":"venue"
},
  "geometry": {"coordinates":[-0.929258,53.950649],"type":"Point"}
}