{
  "type": "Feature",
  "properties": {
    "addr:full":"49 Nevil Road Bristol City of Bristol BS7 9EG",
    "addr:housenumber":"49",
    "addr:postcode":"bs7 9eg",
    "addr:street":"Nevil Road",
    "iso:country":"GB",
    "sg:address":"49 Nevil Road",
    "sg:city":"Bristol",
    "sg:classifiers":[
        {
            "category":"Real Estate",
            "subcategory":"Real Estate Operator",
            "type":"Services"
        }
    ],
    "sg:phone":"+44 117 924 8637",
    "sg:postcode":"BS7 9EG",
    "sg:province":"City of Bristol",
    "sg:tags":[
        "letting",
        "agent"
    ],
    "wof:name":"Brynland Properties",
    "wof:placetype":"venue"
},
  "geometry": {"coordinates":[-2.586661,51.47784],"type":"Point"}
}