{
  "type": "Feature",
  "properties": {
    "addr:full":"55 Great Tindal Street, Ladywood Birmingham West Midlands B16 8PR",
    "addr:housenumber":"55",
    "addr:postcode":"b16 8pr",
    "addr:street":"Great Tindal Street",
    "iso:country":"GB",
    "sg:address":"55 Great Tindal Street, Ladywood",
    "sg:city":"Birmingham",
    "sg:classifiers":[
        {
            "category":"Home & Garden",
            "subcategory":"Hardware",
            "type":"Retail Goods"
        }
    ],
    "sg:phone":"+44 121 454 9070",
    "sg:postcode":"B16 8PR",
    "sg:province":"West Midlands",
    "sg:tags":[
        "paint",
        "coating"
    ],
    "wof:name":"L A S T (Metals) Ltd.",
    "wof:placetype":"venue"
},
  "geometry": {"coordinates":[-1.9204679728,52.4787864685],"type":"Point"}
}