{
  "type": "Feature",
  "properties": {
    "addr:full":"40 Dudley Rd Walton On Thames Surrey KT12 2JU",
    "addr:housenumber":"40",
    "addr:postcode":"kt12 2ju",
    "addr:street":"Dudley Rd",
    "iso:country":"GB",
    "sg:address":"40 Dudley Rd",
    "sg:city":"Walton On Thames",
    "sg:classifiers":[
        {
            "category":"Retail",
            "subcategory":"Animal Services",
            "type":"Services"
        }
    ],
    "sg:phone":"+44 1932 222022",
    "sg:postcode":"KT12 2JU",
    "sg:province":"Surrey",
    "sg:tags":[
        "training",
        "dog"
    ],
    "wof:name":"Scrambles Agility & Obedience Training Centre",
    "wof:placetype":"venue"
},
  "geometry": {"coordinates":[-0.416693002,51.3910522461],"type":"Point"}
}