{
  "type": "Feature",
  "properties": {
    "addr:full":"Callow Farm, Hillside, Martley Worcester Herefordshire WR6 6QW",
    "addr:postcode":"wr6 6qw",
    "addr:street":"Hillside",
    "iso:country":"GB",
    "sg:address":"Callow Farm, Hillside, Martley",
    "sg:city":"Worcester",
    "sg:classifiers":[
        {
            "category":"Shopping",
            "subcategory":"Gifts & Souvenirs",
            "type":"Retail Goods"
        }
    ],
    "sg:postcode":"WR6 6QW",
    "sg:province":"Herefordshire",
    "sg:tags":[
        "christmas"
    ],
    "wof:name":"Festive Forestry Services",
    "wof:placetype":"venue"
},
  "geometry": {"coordinates":[-2.3633608818,52.2360458374],"type":"Point"}
}