{
  "type": "Feature",
  "properties": {
    "addr:full":"36 Fearon Road, North End Portsmouth Hampshire PO2 0NJ",
    "addr:housenumber":"36",
    "addr:postcode":"hampshire po2 0nj",
    "addr:street":"Fearon Road",
    "iso:country":"GB",
    "sg:address":"36 Fearon Road, North End",
    "sg:city":"Portsmouth",
    "sg:classifiers":[
        {
            "category":"Arts & Performance",
            "subcategory":"Music",
            "type":"Entertainment"
        }
    ],
    "sg:phone":"+44 870 220 1551",
    "sg:postcode":"PO2 0NJ",
    "sg:province":"Hampshire",
    "sg:tags":[
        "mobile",
        "disco"
    ],
    "wof:name":"D J Mikie",
    "wof:placetype":"venue"
},
  "geometry": {"coordinates":[-1.073464,50.818291],"type":"Point"}
}