{
  "type": "Feature",
  "properties": {
    "iso:country":"GB",
    "sg:address":"Little Breach",
    "sg:city":"Chichester",
    "sg:classifiers":[
        {
            "category":"Organizations",
            "subcategory":"Non-profit Organization",
            "type":"Services"
        }
    ],
    "sg:phone":"+44 1243 775330",
    "sg:postcode":"PO19 5UA",
    "sg:province":"West Sussex",
    "sg:tags":[
        "charitable",
        "organisation",
        "voluntary",
        "charity"
    ],
    "wof:name":"Scope West Sussex",
    "wof:placetype":"venue"
},
  "geometry": {"coordinates":[-0.7815440297,50.8456459045],"type":"Point"}
}