{
  "type": "Feature",
  "properties": {
    "iso:country":"GB",
    "sg:address":"76 Aversley Road",
    "sg:city":"Birmingham",
    "sg:classifiers":[
        {
            "category":"Building & Trades",
            "subcategory":"Construction",
            "type":"Services"
        }
    ],
    "sg:postcode":"B38 8PL",
    "sg:province":"West Midlands",
    "sg:tags":[
        "builder"
    ],
    "wof:name":"G D Walters Building Services",
    "wof:placetype":"venue"
},
  "geometry": {"coordinates":[-1.942767,52.401253],"type":"Point"}
}