{
  "type": "Feature",
  "properties": {
    "iso:country":"GB",
    "sg:address":"169 Salmon Street",
    "sg:city":"London",
    "sg:classifiers":[
        {
            "category":"Retail",
            "subcategory":"Driving School",
            "type":"Services"
        }
    ],
    "sg:postcode":"NW9 8NE",
    "sg:province":"Greater London",
    "wof:name":"Stewart School of Motoring",
    "wof:placetype":"venue"
},
  "geometry": {"coordinates":[-0.2681879997,51.5739326477],"type":"Point"}
}