{
  "type": "Feature",
  "properties": {
    "addr:full":"The Orange House Windlesham Surrey GU20 6BT",
    "addr:postcode":"gu20 6bt",
    "iso:country":"GB",
    "sg:address":"The Orange House",
    "sg:city":"Windlesham",
    "sg:classifiers":[
        {
            "category":"Shopping",
            "subcategory":"Pharmacy",
            "type":"Retail Goods"
        }
    ],
    "sg:phone":"+44 1276 473371",
    "sg:postcode":"GU20 6BT",
    "sg:province":"Surrey",
    "sg:tags":[
        "medicine",
        "therapy"
    ],
    "wof:name":"The Seekers Centre for Yoga & Natural Health",
    "wof:placetype":"venue"
},
  "geometry": {"coordinates":[-0.6548969746,51.3649597168],"type":"Point"}
}