{
  "type": "Feature",
  "properties": {
    "addr:full":"5 Downsland Ct Basingstoke Hampshire RG21 8TY",
    "addr:housenumber":"5",
    "addr:postcode":"rg21 8ty",
    "addr:street":"Downsland Ct",
    "iso:country":"GB",
    "sg:address":"5 Downsland Ct",
    "sg:city":"Basingstoke",
    "sg:classifiers":[
        {
            "category":"Shopping",
            "subcategory":"News",
            "type":"Retail Goods"
        }
    ],
    "sg:phone":"+44 1256 842292",
    "sg:postcode":"RG21 8TY",
    "sg:province":"Hampshire",
    "sg:tags":[
        "newsagent"
    ],
    "wof:name":"D & R News",
    "wof:placetype":"venue"
},
  "geometry": {"coordinates":[-1.098222971,51.2629470825],"type":"Point"}
}