{
  "type": "Feature",
  "properties": {
    "iso:country":"GB",
    "sg:address":"Unit 17, James Watt Close, Drayton Fields Industrial Estate",
    "sg:city":"Daventry",
    "sg:classifiers":[
        {
            "category":"Manufacturing",
            "subcategory":"Metals",
            "type":"Manufacturing & Wholesale Goods"
        }
    ],
    "sg:postcode":"NN11 5RJ",
    "sg:province":"Northamptonshire",
    "sg:tags":[
        "steel",
        "fabricator",
        "erectors"
    ],
    "wof:name":"Weldtech Services",
    "wof:placetype":"venue"
},
  "geometry": {"coordinates":[-1.179744,52.268951],"type":"Point"}
}