{
  "type": "Feature",
  "properties": {
    "addr:full":"Unit 6 Roman Way Business Centre Droitwich Worcestershire WR9 9AJ",
    "addr:housenumber":"unit 6",
    "addr:postcode":"wr9 9aj",
    "addr:street":"Roman Way",
    "iso:country":"GB",
    "sg:address":"Unit 6 Roman Way Business Centre",
    "sg:city":"Droitwich",
    "sg:classifiers":[
        {
            "category":"Banks & Credit Unions",
            "subcategory":"Financial Services",
            "type":"Services"
        }
    ],
    "sg:phone":"+44 1905 793900",
    "sg:postcode":"WR9 9AJ",
    "sg:province":"Worcestershire",
    "sg:tags":[
        "consultant"
    ],
    "wof:name":"Wesleyan Unit Trust Managers Ltd.",
    "wof:placetype":"venue"
},
  "geometry": {"coordinates":[-2.1597139835,52.2749938965],"type":"Point"}
}