{
  "type": "Feature",
  "properties": {
    "addr:full":"15 Courtfield Road London Greater London SW7 4DA",
    "addr:housenumber":"15",
    "addr:postcode":"sw7 4da",
    "addr:street":"Courtfield Road",
    "iso:country":"GB",
    "sg:address":"15 Courtfield Road",
    "sg:city":"London",
    "sg:classifiers":[
        {
            "category":"Professional",
            "subcategory":"Engineering",
            "type":"Services"
        }
    ],
    "sg:phone":"+44 20 7370 4906",
    "sg:postcode":"SW7 4DA",
    "sg:province":"Greater London",
    "sg:tags":[
        "engineer",
        "mechanical"
    ],
    "wof:name":"Demech Contractors Ltd.",
    "wof:placetype":"venue"
},
  "geometry": {"coordinates":[-0.1844229996,51.4936294556],"type":"Point"}
}