{
  "type": "Feature",
  "properties": {
    "addr:full":"29 St. Mary St Ilkeston Derbyshire DE7 8AB",
    "addr:housenumber":"29",
    "addr:postcode":"de7 8ab",
    "addr:street":"St. Mary St",
    "iso:country":"GB",
    "sg:address":"29 St. Mary St",
    "sg:city":"Ilkeston",
    "sg:classifiers":[
        {
            "category":"Shopping",
            "subcategory":"Computers & Home Electronics",
            "type":"Retail Goods"
        }
    ],
    "sg:phone":"+44 115 932 7171",
    "sg:postcode":"DE7 8AB",
    "sg:province":"Derbyshire",
    "wof:name":"Action Desk Solutions Ltd",
    "wof:placetype":"venue"
},
  "geometry": {"coordinates":[-1.31121099,52.9723434448],"type":"Point"}
}