{
  "type": "Feature",
  "properties": {
    "addr:full":"3 Trinity Street Huddersfield West Yorkshire HD1 4DA",
    "addr:housenumber":"3",
    "addr:postcode":"hd1 4da",
    "addr:street":"Trinity Street",
    "iso:country":"GB",
    "sg:address":"3 Trinity Street",
    "sg:city":"Huddersfield",
    "sg:classifiers":[
        {
            "category":"Shopping",
            "subcategory":"Music",
            "type":"Retail Goods"
        }
    ],
    "sg:phone":"+44 1484 512972",
    "sg:postcode":"HD1 4DA",
    "sg:province":"West Yorkshire",
    "sg:tags":[
        "record",
        "tape",
        "cd"
    ],
    "wof:name":"Fourth Wave",
    "wof:placetype":"venue"
},
  "geometry": {"coordinates":[-1.7864990234,53.6468811035],"type":"Point"}
}