{
  "type": "Feature",
  "properties": {
    "addr:full":"13 Framlingham Pl Sheffield South Yorkshire S2 2GT",
    "addr:housenumber":"13",
    "addr:postcode":"s2 2gt",
    "addr:street":"Framlingham Pl",
    "iso:country":"GB",
    "sg:address":"13 Framlingham Pl",
    "sg:city":"Sheffield",
    "sg:classifiers":[
        {
            "category":"Building & Trades",
            "subcategory":"Construction",
            "type":"Services"
        }
    ],
    "sg:postcode":"S2 2GT",
    "sg:province":"South Yorkshire",
    "sg:tags":[
        "roofing"
    ],
    "wof:name":"Ian Vickers Roofing",
    "wof:placetype":"venue"
},
  "geometry": {"coordinates":[-1.446119,53.361259],"type":"Point"}
}