{
  "type": "Feature",
  "properties": {
    "addr:full":"Connaught Business Centre, Ihalham Road London Greater London SE23 1AH",
    "addr:postcode":"se23 1ah",
    "addr:street":"Ihalham Road",
    "iso:country":"GB",
    "sg:address":"Connaught Business Centre, Ihalham Road",
    "sg:city":"London",
    "sg:classifiers":[
        {
            "category":"Retail",
            "subcategory":"Auto Repair",
            "type":"Services"
        }
    ],
    "sg:phone":"+44 20 8699 4455",
    "sg:postcode":"SE23 1AH",
    "sg:province":"Greater London",
    "sg:tags":[
        "modification",
        "garage"
    ],
    "wof:name":"Sovereign Motor Centre",
    "wof:placetype":"venue"
},
  "geometry": {"coordinates":[-0.0486500002,51.4431800842],"type":"Point"}
}