{
  "type": "Feature",
  "properties": {
    "iso:country":"GB",
    "sg:address":"The Le-clair Enterprise Centre, St Ives Clo",
    "sg:city":"Reading",
    "sg:classifiers":[
        {
            "category":"Retail",
            "subcategory":"Photofinishing",
            "type":"Services"
        }
    ],
    "sg:phone":"+44 118 930 5322",
    "sg:postcode":"RG7 5DP",
    "sg:province":"Berkshire",
    "sg:tags":[
        "photographic",
        "processor"
    ],
    "wof:name":"Colour Works",
    "wof:placetype":"venue"
},
  "geometry": {"coordinates":[-1.0861,51.434719],"type":"Point"}
}