{
  "type": "Feature",
  "properties": {
    "addr:full":"Unit 3 Northgate Industrial Park, Collier Row Road Romford Essex RM5 2BG",
    "addr:housenumber":"unit 3",
    "addr:postcode":"rm5 2bg",
    "addr:street":"Northgate Industrial Park Collier Row Road",
    "iso:country":"GB",
    "sg:address":"Unit 3 Northgate Industrial Park, Collier Row Road",
    "sg:city":"Romford",
    "sg:classifiers":[
        {
            "category":"Government",
            "subcategory":"Post Office",
            "type":"Public Place"
        }
    ],
    "sg:phone":"+44 20 8548 7230",
    "sg:postcode":"RM5 2BG",
    "sg:province":"Essex",
    "sg:tags":[
        "cutting"
    ],
    "wof:name":"Atlas Laser Dyes",
    "wof:placetype":"venue"
},
  "geometry": {"coordinates":[0.14419,51.593632],"type":"Point"}
}