{
  "type": "Feature",
  "properties": {
    "iso:country":"GB",
    "sg:address":"38-40 Layton Road",
    "sg:city":"Blackpool",
    "sg:classifiers":[
        {
            "category":"Manufacturing",
            "subcategory":"Petroleum Products",
            "type":"Manufacturing & Wholesale Goods"
        },
        {
            "category":"Building & Trades",
            "subcategory":"Construction",
            "type":"Services"
        }
    ],
    "sg:phone":"+44 1253 395695",
    "sg:postcode":"FY3 8HT",
    "sg:province":"Lancashire",
    "sg:tags":[
        "double",
        "glazing",
        "installers"
    ],
    "wof:name":"Kestrel Window Systems Ltd",
    "wof:placetype":"venue"
},
  "geometry": {"coordinates":[-3.032379,53.823551],"type":"Point"}
}