{
  "type": "Feature",
  "properties": {
    "addr:full":"25 Aden Gro London Greater London N16 9NP",
    "addr:housenumber":"25",
    "addr:postcode":"n16 9np",
    "addr:street":"Aden Gro",
    "iso:country":"GB",
    "sg:address":"25 Aden Gro",
    "sg:city":"London",
    "sg:classifiers":[
        {
            "category":"Professional",
            "subcategory":"Computer Services",
            "type":"Services"
        }
    ],
    "sg:phone":"+44 20 7690 9700",
    "sg:postcode":"N16 9NP",
    "sg:province":"Greater London",
    "sg:tags":[
        "consultant"
    ],
    "wof:name":"Scott Mihajlovic Associates Ltd.",
    "wof:placetype":"venue"
},
  "geometry": {"coordinates":[-0.08641,51.55471],"type":"Point"}
}