{
  "type": "Feature",
  "properties": {
    "addr:full":"51-53 Chapel Road Sale Cheshire M33 7FD",
    "addr:housenumber":"51-53",
    "addr:postcode":"m33 7fd",
    "addr:street":"Chapel Road",
    "iso:country":"GB",
    "sg:address":"51-53 Chapel Road",
    "sg:city":"Sale",
    "sg:classifiers":[
        {
            "category":"Wholesale",
            "subcategory":"Construction Materials",
            "type":"Manufacturing & Wholesale Goods"
        }
    ],
    "sg:phone":"+44 161 973 0373",
    "sg:postcode":"M33 7FD",
    "sg:province":"Cheshire",
    "sg:tags":[
        "merchant",
        "glass"
    ],
    "wof:name":"Sale Joinery & Glass Centre",
    "wof:placetype":"venue"
},
  "geometry": {"coordinates":[-2.3188099861,53.4262123108],"type":"Point"}
}