{
  "type": "Feature",
  "properties": {
    "iso:country":"GB",
    "sg:address":"159 Willowbrae Road",
    "sg:city":"Edinburgh",
    "sg:classifiers":[
        {
            "category":"Fast Food",
            "type":"Food & Drink"
        }
    ],
    "sg:phone":"+44 131 661 9500",
    "sg:postcode":"EH8 7JB",
    "sg:province":"City of Edinburgh",
    "sg:tags":[
        "away",
        "meal",
        "outlet",
        "take"
    ],
    "wof:name":"Kam Lo",
    "wof:placetype":"venue"
},
  "geometry": {"coordinates":[-3.1422250271,55.9515914917],"type":"Point"}
}