{
  "type": "Feature",
  "properties": {
    "iso:country":"GB",
    "sg:address":"Abec House, Percy Rd",
    "sg:city":"Birmingham",
    "sg:classifiers":[
        {
            "category":"Manufacturing",
            "subcategory":"Tools & Machinery",
            "type":"Manufacturing & Wholesale Goods"
        }
    ],
    "sg:phone":"+44 121 702 2910",
    "sg:postcode":"B11 3LG",
    "sg:province":"West Midlands",
    "sg:tags":[
        "bearing",
        "stockist"
    ],
    "wof:name":"BSL Ltd",
    "wof:placetype":"venue"
},
  "geometry": {"coordinates":[-1.858379,52.453476],"type":"Point"}
}