{
  "type": "Feature",
  "properties": {
    "iso:country":"GB",
    "sg:address":"Suite 1, Mclaren House",
    "sg:city":"Seahouses",
    "sg:classifiers":[
        {
            "category":"Communications",
            "type":"Services"
        }
    ],
    "sg:postcode":"NE68 7RE",
    "sg:province":"Northumberland",
    "sg:tags":[
        "broadcasting"
    ],
    "wof:name":"Studio Arts Television Ltd.",
    "wof:placetype":"venue"
},
  "geometry": {"coordinates":[-1.6618789434,55.5774993896],"type":"Point"}
}