{
  "type": "Feature",
  "properties": {
    "addr:full":"426 Limpsfield Road Warlingham Kent CR6 9LA",
    "addr:housenumber":"426",
    "addr:postcode":"cr6 9la",
    "addr:street":"Limpsfield Road",
    "iso:country":"GB",
    "sg:address":"426 Limpsfield Road",
    "sg:city":"Warlingham",
    "sg:classifiers":[
        {
            "category":"Real Estate",
            "subcategory":"Surveying",
            "type":"Services"
        },
        {
            "category":"Real Estate",
            "subcategory":"Architect",
            "type":"Services"
        }
    ],
    "sg:phone":"+44 1883 626326",
    "sg:postcode":"CR6 9LA",
    "sg:province":"Kent",
    "sg:tags":[
        "surveyor",
        "valuer"
    ],
    "wof:name":"Brace Bidwell Estates",
    "wof:placetype":"venue"
},
  "geometry": {"coordinates":[-0.0540769994,51.3091201782],"type":"Point"}
}