{
  "type": "Feature",
  "properties": {
    "addr:full":"59 Trafalgar Street Sheffield South Yorkshire S1 4GN",
    "addr:housenumber":"59",
    "addr:postcode":"s1 4gn",
    "addr:street":"Trafalgar Street",
    "iso:country":"GB",
    "sg:address":"59 Trafalgar Street",
    "sg:city":"Sheffield",
    "sg:classifiers":[
        {
            "category":"Professional",
            "subcategory":"Engineering",
            "type":"Services"
        }
    ],
    "sg:phone":"+44 114 249 5616",
    "sg:postcode":"S1 4GN",
    "sg:province":"South Yorkshire",
    "sg:tags":[
        "contractor",
        "electrical",
        "engineer"
    ],
    "wof:name":"Ellis Electrical",
    "wof:placetype":"venue"
},
  "geometry": {"coordinates":[-1.475749,53.378605],"type":"Point"}
}