{
  "type": "Feature",
  "properties": {
    "addr:full":"Geach Tower, 64 Uxbridge St Birmingham West Midlands B19 3UP",
    "addr:housenumber":"64",
    "addr:postcode":"b19 3up",
    "addr:street":"Uxbridge St",
    "iso:country":"GB",
    "sg:address":"Geach Tower, 64 Uxbridge St",
    "sg:city":"Birmingham",
    "sg:classifiers":[
        {
            "category":"Government",
            "subcategory":"Office",
            "type":"Public Place"
        }
    ],
    "sg:phone":"+44 121 554 4043",
    "sg:postcode":"B19 3UP",
    "sg:province":"West Midlands",
    "sg:tags":[
        "local"
    ],
    "wof:name":"Birmingham City Council",
    "wof:placetype":"venue"
},
  "geometry": {"coordinates":[-1.908604,52.478596],"type":"Point"}
}