{
  "type": "Feature",
  "properties": {
    "iso:country":"GB",
    "sg:address":"Ilbert Road",
    "sg:city":"Kingsbridge",
    "sg:classifiers":[
        {
            "category":"Education",
            "subcategory":"Library",
            "type":"Public Place"
        },
        {
            "category":"Government",
            "subcategory":"Office",
            "type":"Public Place"
        }
    ],
    "sg:phone":"+44 1548 852315",
    "sg:postcode":"TQ7 1EB",
    "sg:province":"Devon",
    "sg:tags":[
        "book",
        "local"
    ],
    "wof:name":"Kingsbridge Library",
    "wof:placetype":"venue"
},
  "geometry": {"coordinates":[-3.779062,50.282932],"type":"Point"}
}