{
  "type": "Feature",
  "properties": {
    "iso:country":"GB",
    "sg:address":"101 Central Avenue",
    "sg:city":"Welling",
    "sg:classifiers":[
        {
            "category":"Personal",
            "subcategory":"Beauty Salon",
            "type":"Services"
        },
        {
            "category":"Personal",
            "subcategory":"Barber",
            "type":"Services"
        }
    ],
    "sg:phone":"+44 20 8317 9822",
    "sg:postcode":"DA16 3BG",
    "sg:province":"Kent",
    "sg:tags":[
        "unisex",
        "hairdresser"
    ],
    "wof:name":"Shampers",
    "wof:placetype":"venue"
},
  "geometry": {"coordinates":[0.100797,51.468018],"type":"Point"}
}