{
  "type": "Feature",
  "properties": {
    "addr:full":"26 Melcombe Ave, Greenhill Weymouth Dorset DT4 7TH",
    "addr:housenumber":"26",
    "addr:postcode":"dt4 7th",
    "addr:street":"Melcombe Ave",
    "iso:country":"GB",
    "sg:address":"26 Melcombe Ave, Greenhill",
    "sg:city":"Weymouth",
    "sg:classifiers":[
        {
            "category":"Professional",
            "type":"Services"
        }
    ],
    "sg:postcode":"DT4 7TH",
    "sg:province":"Dorset",
    "sg:tags":[
        "caterer"
    ],
    "wof:name":"Homebake Catering",
    "wof:placetype":"venue"
},
  "geometry": {"coordinates":[-2.449145,50.622334],"type":"Point"}
}