{
  "type": "Feature",
  "properties": {
    "addr:full":"Unit 7 Flitwick Indust Est, Lyall Ct Bedford Bedfordshire MK45 1UX",
    "addr:housenumber":"unit 7",
    "addr:postcode":"mk45 1ux",
    "addr:street":"Indust;Lyall Ct",
    "iso:country":"GB",
    "sg:address":"Unit 7 Flitwick Indust Est, Lyall Ct",
    "sg:city":"Bedford",
    "sg:classifiers":[
        {
            "category":"Building & Trades",
            "subcategory":"Cleaning & Sanitation",
            "type":"Services"
        }
    ],
    "sg:phone":"+44 1234 824064",
    "sg:postcode":"MK45 1UX",
    "sg:province":"Bedfordshire",
    "sg:tags":[
        "door",
        "manufacturer"
    ],
    "wof:name":"Almond Door Services",
    "wof:placetype":"venue"
},
  "geometry": {"coordinates":[-0.48514,52.01012],"type":"Point"}
}