{
  "type": "Feature",
  "properties": {
    "iso:country":"GB",
    "sg:address":"Stalybridge Library, Trinity Street",
    "sg:city":"Stalybridge",
    "sg:classifiers":[
        {
            "category":"Education",
            "subcategory":"Library",
            "type":"Public Place"
        }
    ],
    "sg:phone":"+44 161 303 7937",
    "sg:postcode":"SK15 2BN",
    "sg:province":"Greater Manchester",
    "sg:tags":[
        "book"
    ],
    "wof:name":"The Tameside Local Studies Library",
    "wof:placetype":"venue"
},
  "geometry": {"coordinates":[-2.057569,53.483543],"type":"Point"}
}