{
  "type": "Feature",
  "properties": {
    "addr:full":"Calderwood St, Woolwich Woolwich Greater London SE18 6QW",
    "addr:postcode":"se18 6qw",
    "addr:street":"Calderwood St",
    "iso:country":"GB",
    "sg:address":"Calderwood St, Woolwich",
    "sg:city":"Woolwich",
    "sg:classifiers":[
        {
            "category":"Parking",
            "type":"Transportation"
        }
    ],
    "sg:phone":"+44 20 8317 9052",
    "sg:postcode":"SE18 6QW",
    "sg:province":"Greater London",
    "sg:tags":[
        "car",
        "park"
    ],
    "wof:name":"Calderwood Street Car Park",
    "wof:placetype":"venue"
},
  "geometry": {"coordinates":[0.0650549978,51.4893951416],"type":"Point"}
}