{
  "type": "Feature",
  "properties": {
    "addr:full":"7 Provost Rd Hampstead Greater London NW3 4ST",
    "addr:housenumber":"7",
    "addr:postcode":"nw3 4st",
    "addr:street":"Provost Rd",
    "iso:country":"GB",
    "sg:address":"7 Provost Rd",
    "sg:city":"Hampstead",
    "sg:classifiers":[
        {
            "category":"Real Estate",
            "subcategory":"Architect",
            "type":"Services"
        }
    ],
    "sg:phone":"+44 20 7722 1790",
    "sg:postcode":"NW3 4ST",
    "sg:province":"Greater London",
    "wof:name":"Julia Wilson Jones Architect",
    "wof:placetype":"venue"
},
  "geometry": {"coordinates":[-0.1566690058,51.544593811],"type":"Point"}
}