{
  "type": "Feature",
  "properties": {
    "addr:full":"1 Meadow Close, Thurlton Norwich Norfolk NR14 6RQ",
    "addr:housenumber":"1",
    "addr:postcode":"nr14 6rq",
    "addr:street":"Meadow Close",
    "iso:country":"GB",
    "sg:address":"1 Meadow Close, Thurlton",
    "sg:city":"Norwich",
    "sg:classifiers":[
        {
            "category":"Home & Garden",
            "subcategory":"Home Furnishings",
            "type":"Retail Goods"
        }
    ],
    "sg:phone":"+44 1508 548418",
    "sg:postcode":"NR14 6RQ",
    "sg:province":"Norfolk",
    "sg:tags":[
        "tube",
        "fitting",
        "stockist"
    ],
    "wof:name":"Spareline Supplies Ltd.",
    "wof:placetype":"venue"
},
  "geometry": {"coordinates":[1.5577299595,52.5282211304],"type":"Point"}
}