{
  "type": "Feature",
  "properties": {
    "addr:full":"Sovereign House, St Dunstans Road Feltham Greater London TW13 4JU",
    "addr:postcode":"tw13 4ju",
    "addr:street":"St Dunstans Road",
    "iso:country":"GB",
    "sg:address":"Sovereign House, St Dunstans Road",
    "sg:city":"Feltham",
    "sg:classifiers":[
        {
            "category":"Freight",
            "type":"Transportation"
        }
    ],
    "sg:postcode":"TW13 4JU",
    "sg:province":"Greater London",
    "sg:tags":[
        "forwarders"
    ],
    "wof:name":"Sovereign International Freight",
    "wof:placetype":"venue"
},
  "geometry": {"coordinates":[-0.420252,51.439693],"type":"Point"}
}