{
  "type": "Feature",
  "properties": {
    "addr:full":"Cheriton High Street Folkestone Kent CT18 8AN",
    "addr:postcode":"ct18 8an",
    "addr:street":"High Street",
    "iso:country":"GB",
    "sg:address":"Cheriton High Street",
    "sg:city":"Folkestone",
    "sg:classifiers":[
        {
            "category":"Social Services",
            "subcategory":"Child Care",
            "type":"Services"
        },
        {
            "category":"Social Services",
            "subcategory":"Adult Care",
            "type":"Services"
        }
    ],
    "sg:phone":"+44 1303 279051",
    "sg:postcode":"CT18 8AN",
    "sg:province":"Kent",
    "sg:tags":[
        "day",
        "centre"
    ],
    "wof:name":"Brockman Family Centre",
    "wof:placetype":"venue"
},
  "geometry": {"coordinates":[1.134845,51.088558],"type":"Point"}
}