{
  "type": "Feature",
  "properties": {
    "addr:full":"Brumstead Norwich Norfolk NR12 9ER",
    "addr:postcode":"nr12 9er",
    "addr:street":"Norwich",
    "iso:country":"GB",
    "sg:address":"Brumstead",
    "sg:city":"Norwich",
    "sg:classifiers":[
        {
            "category":"Wholesale",
            "subcategory":"Machinery & Supplies",
            "type":"Manufacturing & Wholesale Goods"
        }
    ],
    "sg:phone":"+44 1692 580522",
    "sg:postcode":"NR12 9ER",
    "sg:province":"Norfolk",
    "wof:name":"Sands Agricultural Machinery Ltd.",
    "wof:placetype":"venue"
},
  "geometry": {"coordinates":[1.4990700483,52.7885093689],"type":"Point"}
}