{
  "type": "Feature",
  "properties": {
    "addr:full":"Albany Rd Newcastle Staffordshire ST5 9EJ",
    "addr:postcode":"st5 9ej",
    "addr:street":"Albany Rd",
    "iso:country":"GB",
    "sg:address":"Albany Rd",
    "sg:city":"Newcastle",
    "sg:classifiers":[
        {
            "category":"Retail",
            "subcategory":"Auto Repair",
            "type":"Services"
        }
    ],
    "sg:phone":"+44 1782 613434",
    "sg:postcode":"ST5 9EJ",
    "sg:province":"Staffordshire",
    "sg:tags":[
        "car",
        "specialist",
        "customizing"
    ],
    "wof:name":"Crossheath Tyre & Battery",
    "wof:placetype":"venue"
},
  "geometry": {"coordinates":[-2.229024,53.01778],"type":"Point"}
}