{
  "type": "Feature",
  "properties": {
    "addr:full":"Unit 11, Monkspath Business Park Solihull West Midlands B90 4NY",
    "addr:housenumber":"unit 11",
    "addr:postcode":"b90 4ny",
    "addr:street":"Monkspath Business Park",
    "iso:country":"GB",
    "sg:address":"Unit 11, Monkspath Business Park",
    "sg:city":"Solihull",
    "sg:classifiers":[
        {
            "category":"Building & Trades",
            "subcategory":"Plumbing",
            "type":"Services"
        }
    ],
    "sg:phone":"+44 121 744 3900",
    "sg:postcode":"B90 4NY",
    "sg:province":"West Midlands",
    "sg:tags":[
        "merchant",
        "plumbers'"
    ],
    "wof:name":"Centreglow Ltd.",
    "wof:placetype":"venue"
},
  "geometry": {"coordinates":[-1.792019,52.387974],"type":"Point"}
}