{
  "type": "Feature",
  "properties": {
    "addr:full":"10a Manor Rd Bath Bath and North East Somerset BA1 4BW",
    "addr:housenumber":"10a",
    "addr:postcode":"ba1 4bw",
    "addr:street":"Manor Rd",
    "iso:country":"GB",
    "sg:address":"10a Manor Rd",
    "sg:city":"Bath",
    "sg:classifiers":[
        {
            "category":"Autos & Motor Vehicles",
            "subcategory":"Auto Supplies",
            "type":"Retail Goods"
        }
    ],
    "sg:phone":"+44 1225 311317",
    "sg:postcode":"BA1 4BW",
    "sg:province":"Bath and North East Somerset",
    "sg:tags":[
        "tyre"
    ],
    "wof:name":"T Linkins Tyres",
    "wof:placetype":"venue"
},
  "geometry": {"coordinates":[-2.388735,51.394402],"type":"Point"}
}