{
  "type": "Feature",
  "properties": {
    "addr:full":"87-89 Brickhill Drive Bedford Bedfordshire MK41 7QF",
    "addr:housenumber":"87-89",
    "addr:postcode":"mk41 7qf",
    "addr:street":"Brickhill Drive",
    "iso:country":"GB",
    "sg:address":"87-89 Brickhill Drive",
    "sg:city":"Bedford",
    "sg:classifiers":[
        {
            "category":"Autos & Motor Vehicles",
            "subcategory":"Fuel & Gas Station",
            "type":"Retail Goods"
        }
    ],
    "sg:phone":"+44 1234 354284",
    "sg:postcode":"MK41 7QF",
    "sg:province":"Bedfordshire",
    "sg:tags":[
        "petrol",
        "filling"
    ],
    "wof:name":"Brickhill Drive Service Station",
    "wof:placetype":"venue"
},
  "geometry": {"coordinates":[-0.462893,52.153122],"type":"Point"}
}