{
  "type": "Feature",
  "properties": {
    "addr:full":"Commercial Centre, Moray Way North Dunfermline Fife KY11 5NH",
    "addr:postcode":"ky11 5nh",
    "addr:street":"Moray Way North",
    "iso:country":"GB",
    "sg:address":"Commercial Centre, Moray Way North",
    "sg:city":"Dunfermline",
    "sg:classifiers":[
        {
            "category":"Health Services",
            "subcategory":"Dentist",
            "type":"Services"
        }
    ],
    "sg:phone":"+44 1383 823372",
    "sg:postcode":"KY11 5NH",
    "sg:province":"Fife",
    "wof:name":"P Shields",
    "wof:placetype":"venue"
},
  "geometry": {"coordinates":[-3.46137,56.074841],"type":"Point"}
}