{
  "type": "Feature",
  "properties": {
    "addr:full":"1 Amwell Street Hoddesdon Essex EN11 8TP",
    "addr:housenumber":"1",
    "addr:postcode":"en11 8tp",
    "addr:street":"Amwell Street",
    "iso:country":"GB",
    "sg:address":"1 Amwell Street",
    "sg:city":"Hoddesdon",
    "sg:classifiers":[
        {
            "category":"Home & Garden",
            "subcategory":"Home Furnishings",
            "type":"Retail Goods"
        }
    ],
    "sg:phone":"+44 1992 440824",
    "sg:postcode":"EN11 8TP",
    "sg:province":"Essex",
    "sg:tags":[
        "blind",
        "curtain",
        "fitting"
    ],
    "wof:name":"P & M Curtains",
    "wof:placetype":"venue"
},
  "geometry": {"coordinates":[-0.011777,51.76165],"type":"Point"}
}