{
  "type": "Feature",
  "properties": {
    "iso:country":"GB",
    "sg:address":"16 Chorley Road, Heath Chanrock",
    "sg:city":"Chorley",
    "sg:classifiers":[
        {
            "category":"Banks & Credit Unions",
            "subcategory":"Investment Brokerage",
            "type":"Services"
        }
    ],
    "sg:phone":"+44 1257 482169",
    "sg:postcode":"PR6 9LB",
    "sg:province":"Lancashire",
    "sg:tags":[
        "contractor"
    ],
    "wof:name":"Gregory's Agricultural Contractors",
    "wof:placetype":"venue"
},
  "geometry": {"coordinates":[-2.603182,53.62088],"type":"Point"}
}