{
  "type": "Feature",
  "properties": {
    "addr:full":"2 Bridgegate Barnard Castle Cumbria DL12 8QF",
    "addr:housenumber":"2",
    "addr:postcode":"dl12 8qf",
    "addr:street":"Bridgegate",
    "iso:country":"GB",
    "sg:address":"2 Bridgegate",
    "sg:city":"Barnard Castle",
    "sg:classifiers":[
        {
            "category":"Bars & Pubs",
            "type":"Food & Drink"
        }
    ],
    "sg:postcode":"DL12 8QF",
    "sg:province":"Cumbria",
    "sg:tags":[
        "pubs",
        "inn"
    ],
    "wof:name":"The Blue Bell",
    "wof:placetype":"venue"
},
  "geometry": {"coordinates":[-1.923809,54.543152],"type":"Point"}
}