{
  "type": "Feature",
  "properties": {
    "addr:full":"Market Place, 51 Unit, Crystal Peaks Market Sheffield South Yorkshire S20 7PL",
    "addr:housenumber":"51 unit crystal",
    "addr:postcode":"s20 7pl",
    "addr:street":"Market;Yorkshire",
    "iso:country":"GB",
    "sg:address":"Market Place, 51 Unit, Crystal Peaks Market",
    "sg:city":"Sheffield",
    "sg:classifiers":[
        {
            "category":"Shopping",
            "subcategory":"Crafts & Fabrics",
            "type":"Retail Goods"
        }
    ],
    "sg:phone":"+44 114 248 1140",
    "sg:postcode":"S20 7PL",
    "sg:province":"South Yorkshire",
    "sg:tags":[
        "shop"
    ],
    "wof:name":"Grace's Fabrics",
    "wof:placetype":"venue"
},
  "geometry": {"coordinates":[-1.3459290266,53.3398857117],"type":"Point"}
}