{
  "type": "Feature",
  "properties": {
    "iso:country":"GB",
    "sg:address":"83 Maybank Avenue",
    "sg:city":"Wembley",
    "sg:classifiers":[
        {
            "category":"Shopping",
            "subcategory":"Used Merchandise",
            "type":"Retail Goods"
        }
    ],
    "sg:phone":"+44 20 8903 0275",
    "sg:postcode":"HA0 2TQ",
    "sg:province":"Greater London",
    "sg:tags":[
        "shop",
        "second-hand"
    ],
    "wof:name":"Warehouse Discount",
    "wof:placetype":"venue"
},
  "geometry": {"coordinates":[-0.326516,51.555561],"type":"Point"}
}