{
  "type": "Feature",
  "properties": {
    "addr:full":"Midland Bank Chambers March Cambridgeshire PE15 9LD",
    "addr:postcode":"pe15 9ld",
    "iso:country":"GB",
    "sg:address":"Midland Bank Chambers",
    "sg:city":"March",
    "sg:classifiers":[
        {
            "category":"Professional",
            "subcategory":"Lawyer & Legal Services",
            "type":"Services"
        }
    ],
    "sg:phone":"+44 1354 652601",
    "sg:postcode":"PE15 9LD",
    "sg:province":"Cambridgeshire",
    "sg:tags":[
        "practitioner",
        "insolvency"
    ],
    "wof:name":"Eckley Neville",
    "wof:placetype":"venue"
},
  "geometry": {"coordinates":[0.0875699967,52.5473213196],"type":"Point"}
}