{
  "type": "Feature",
  "properties": {
    "addr:full":"1-2 Yallop Way Honiton Devon EX14 8GG",
    "addr:housenumber":"1-2",
    "addr:postcode":"ex14 8gg",
    "addr:street":"Yallop Way",
    "iso:country":"GB",
    "sg:address":"1-2 Yallop Way",
    "sg:city":"Honiton",
    "sg:classifiers":[
        {
            "category":"Real Estate",
            "subcategory":"Developer",
            "type":"Services"
        }
    ],
    "sg:phone":"+44 1404 44012",
    "sg:postcode":"EX14 8GG",
    "sg:province":"Devon",
    "sg:tags":[
        "property"
    ],
    "wof:name":"Prowting Homes",
    "wof:placetype":"venue"
},
  "geometry": {"coordinates":[-3.196534,50.790508],"type":"Point"}
}