{
  "type": "Feature",
  "properties": {
    "iso:country":"GB",
    "sg:address":"Southend Borough Combination Hq, Eastwoodbury Lane",
    "sg:city":"Southend-on-sea",
    "sg:classifiers":[
        {
            "category":"Farming",
            "subcategory":"Nursery",
            "type":"Manufacturing & Wholesale Goods"
        }
    ],
    "sg:phone":"+44 1702 344197",
    "sg:postcode":"SS2 6UH",
    "sg:province":"Essex",
    "sg:tags":[
        "creche"
    ],
    "wof:name":"Belle Enfant Nursery",
    "wof:placetype":"venue"
},
  "geometry": {"coordinates":[0.6775100231,51.5669288635],"type":"Point"}
}