{
  "type": "Feature",
  "properties": {
    "iso:country":"GB",
    "sg:address":"31 Grange Rd",
    "sg:city":"Darlington",
    "sg:classifiers":[
        {
            "category":"Professional",
            "subcategory":"Printing & Photocopies",
            "type":"Services"
        }
    ],
    "sg:phone":"+44 1325 462040",
    "sg:postcode":"DL1 5NB",
    "sg:province":"Durham",
    "sg:tags":[
        "engraving"
    ],
    "wof:name":"Wilsons Of Darlington",
    "wof:placetype":"venue"
},
  "geometry": {"coordinates":[-1.5578819513,54.5233001709],"type":"Point"}
}