{
  "type": "Feature",
  "properties": {
    "addr:full":"The Oast House Summerford Farm, Beech Green Lane Withyham Tunbridge Wells East Sussex TN7 4DA",
    "addr:postcode":"tn7 4da",
    "addr:street":"Summerford;Beech Green Lane",
    "iso:country":"GB",
    "sg:address":"The Oast House Summerford Farm, Beech Green Lane Withyham",
    "sg:city":"Tunbridge Wells",
    "sg:classifiers":[
        {
            "category":"Professional",
            "subcategory":"Management & Consulting",
            "type":"Services"
        }
    ],
    "sg:postcode":"TN7 4DA",
    "sg:province":"East Sussex",
    "sg:tags":[
        "consultant",
        "business"
    ],
    "wof:name":"Arcade Consultants Ltd",
    "wof:placetype":"venue"
},
  "geometry": {"coordinates":[0.1321389973,51.1008834839],"type":"Point"}
}