{
  "type": "Feature",
  "properties": {
    "iso:country":"GB",
    "sg:address":"Unit 4 Kemble Airfield, Kemble",
    "sg:city":"Cirencester",
    "sg:classifiers":[
        {
            "category":"Professional",
            "subcategory":"Employment Agencies",
            "type":"Services"
        }
    ],
    "sg:phone":"+44 1285 770061",
    "sg:postcode":"GL7 6BA",
    "sg:province":"Gloucestershire",
    "sg:tags":[
        "consultant",
        "recruitment"
    ],
    "wof:name":"Corexe Ltd",
    "wof:placetype":"venue"
},
  "geometry": {"coordinates":[-2.0183339119,51.6752090454],"type":"Point"}
}