{
  "type": "Feature",
  "properties": {
    "addr:full":"Windsor House, 55-56 St James Street London Greater London SW1A 1LA",
    "addr:housenumber":"55-56",
    "addr:postcode":"sw1a 1la",
    "addr:street":"St James Street",
    "iso:country":"GB",
    "sg:address":"Windsor House, 55-56 St James Street",
    "sg:city":"London",
    "sg:classifiers":[
        {
            "category":"Professional",
            "subcategory":"Management & Consulting",
            "type":"Services"
        }
    ],
    "sg:phone":"+44 20 7355 3030",
    "sg:postcode":"SW1A 1LA",
    "sg:province":"Greater London",
    "sg:tags":[
        "project"
    ],
    "wof:name":"Churchfield Associates West Ltd.",
    "wof:placetype":"venue"
},
  "geometry": {"coordinates":[-0.1400389969,51.5070877075],"type":"Point"}
}