{
  "type": "Feature",
  "properties": {
    "addr:full":"Bury Road Bolton Lancashire BL2 6HZ",
    "addr:postcode":"bl2 6hz",
    "addr:street":"Bury Road",
    "iso:country":"GB",
    "sg:address":"Bury Road",
    "sg:city":"Bolton",
    "sg:classifiers":[
        {
            "category":"Communications",
            "type":"Services"
        }
    ],
    "sg:phone":"+44 1204 392430",
    "sg:postcode":"BL2 6HZ",
    "sg:province":"Lancashire",
    "sg:tags":[
        "broadcasting"
    ],
    "wof:name":"Mediavision",
    "wof:placetype":"venue"
},
  "geometry": {"coordinates":[-2.396224,53.580742],"type":"Point"}
}