{
  "type": "Feature",
  "properties": {
    "iso:country":"GB",
    "sg:address":"Clarence Street",
    "sg:city":"Chorley",
    "sg:classifiers":[
        {
            "category":"Building & Trades",
            "subcategory":"Construction",
            "type":"Services"
        }
    ],
    "sg:phone":"+44 1257 264512",
    "sg:postcode":"PR7 2BJ",
    "sg:province":"Lancashire",
    "sg:tags":[
        "restoration",
        "refurbishment"
    ],
    "wof:name":"E Rylance & Sons Ltd.",
    "wof:placetype":"venue"
},
  "geometry": {"coordinates":[-2.627634,53.650757],"type":"Point"}
}