{
  "type": "Feature",
  "properties": {
    "addr:full":"35 Honey Lane, Cholsey Wallingford Oxfordshire OX10 9NL",
    "addr:housenumber":"35",
    "addr:postcode":"ox10 9nl",
    "addr:street":"Honey Lane",
    "iso:country":"GB",
    "sg:address":"35 Honey Lane, Cholsey",
    "sg:city":"Wallingford",
    "sg:classifiers":[
        {
            "category":"Professional",
            "subcategory":"Art Services",
            "type":"Services"
        }
    ],
    "sg:phone":"+44 1491 651871",
    "sg:postcode":"OX10 9NL",
    "sg:province":"Oxfordshire",
    "sg:tags":[
        "photographer"
    ],
    "wof:name":"David M Smith Photography",
    "wof:placetype":"venue"
},
  "geometry": {"coordinates":[-1.15235,51.572468],"type":"Point"}
}