{
  "type": "Feature",
  "properties": {
    "addr:full":"Egyptian House, 170-173 Piccadilly London Greater London W1J 9EJ",
    "addr:housenumber":"170-173",
    "addr:postcode":"w1j 9ej",
    "addr:street":"Piccadilly",
    "iso:country":"GB",
    "sg:address":"Egyptian House, 170-173 Piccadilly",
    "sg:city":"London",
    "sg:classifiers":[
        {
            "category":"Professional",
            "subcategory":"Business Services",
            "type":"Services"
        }
    ],
    "sg:phone":"+44 20 7499 3119",
    "sg:postcode":"W1J 9EJ",
    "sg:province":"Greater London",
    "sg:tags":[
        "holding"
    ],
    "wof:name":"Bellandvision Ltd.",
    "wof:placetype":"venue"
},
  "geometry": {"coordinates":[-0.135579,51.50946],"type":"Point"}
}