{
  "type": "Feature",
  "properties": {
    "addr:full":"286 Brixton Road London Greater London SW9 6AG",
    "addr:housenumber":"286",
    "addr:postcode":"sw9 6ag",
    "addr:street":"Brixton Road",
    "iso:country":"GB",
    "sg:address":"286 Brixton Road",
    "sg:city":"London",
    "sg:classifiers":[
        {
            "category":"Retail",
            "subcategory":"Laundry & Dry Cleaning",
            "type":"Services"
        }
    ],
    "sg:phone":"+44 20 7733 2144",
    "sg:postcode":"SW9 6AG",
    "sg:province":"Greater London",
    "sg:tags":[
        "alteration"
    ],
    "wof:name":"Unit Cleaners Ltd.",
    "wof:placetype":"venue"
},
  "geometry": {"coordinates":[-0.1125909984,51.4704704285],"type":"Point"}
}