{
  "type": "Feature",
  "properties": {
    "iso:country":"GB",
    "sg:address":"11 Barrow Mkt",
    "sg:city":"Barrow-in-furness",
    "sg:classifiers":[
        {
            "category":"Shopping",
            "subcategory":"Department Store",
            "type":"Retail Goods"
        }
    ],
    "sg:postcode":"LA14 4NB",
    "sg:province":"Cumbria",
    "wof:name":"Danson,Diane,",
    "wof:placetype":"venue"
},
  "geometry": {"coordinates":[-3.225847,54.111088],"type":"Point"}
}