{
  "type": "Feature",
  "properties": {
    "addr:full":"20 Delmont Gro Stroud Gloucestershire GL5 1UN",
    "addr:housenumber":"20",
    "addr:postcode":"gl5 1un",
    "addr:street":"Delmont Gro",
    "iso:country":"GB",
    "sg:address":"20 Delmont Gro",
    "sg:city":"Stroud",
    "sg:classifiers":[
        {
            "category":"Military Area",
            "subcategory":"Air Force Base",
            "type":"Public Place"
        }
    ],
    "sg:phone":"+44 1453 753700",
    "sg:postcode":"GL5 1UN",
    "sg:province":"Gloucestershire",
    "sg:tags":[
        "taxi",
        "hire",
        "private"
    ],
    "wof:name":"Abcab Taxis",
    "wof:placetype":"venue"
},
  "geometry": {"coordinates":[-2.2145578861,51.7506637573],"type":"Point"}
}