{
  "type": "Feature",
  "properties": {
    "addr:full":"10 Crown Avenue Clydebank East Dunbartonshire G81 3BW",
    "addr:housenumber":"10",
    "addr:postcode":"g81 3bw",
    "addr:street":"Crown Avenue",
    "iso:country":"GB",
    "sg:address":"10 Crown Avenue",
    "sg:city":"Clydebank",
    "sg:classifiers":[
        {
            "category":"Shopping",
            "subcategory":"News",
            "type":"Retail Goods"
        }
    ],
    "sg:postcode":"G81 3BW",
    "sg:province":"East Dunbartonshire",
    "sg:tags":[
        "newsagent"
    ],
    "wof:name":"Malik Newsagents",
    "wof:placetype":"venue"
},
  "geometry": {"coordinates":[-4.4047088623,55.9100456238],"type":"Point"}
}