{
  "type": "Feature",
  "properties": {
    "iso:country":"GB",
    "sg:address":"72 Bunting Road",
    "sg:city":"Northampton",
    "sg:classifiers":[
        {
            "category":"Utilities",
            "subcategory":"Telephone",
            "type":"Services"
        }
    ],
    "sg:phone":"+44 1604 722244",
    "sg:postcode":"NN2 6EE",
    "sg:province":"Northamptonshire",
    "sg:tags":[
        "telecommunication"
    ],
    "wof:name":"D B Communications",
    "wof:placetype":"venue"
},
  "geometry": {"coordinates":[-0.89569,52.251255],"type":"Point"}
}