{
  "type": "Feature",
  "properties": {
    "addr:full":"6 The Gro, Kippax Leeds North Yorkshire LS25 7ND",
    "addr:housenumber":"6",
    "addr:postcode":"ls25 7nd",
    "addr:street":"The Gro Kippax Leeds",
    "iso:country":"GB",
    "sg:address":"6 The Gro, Kippax",
    "sg:city":"Leeds",
    "sg:classifiers":[
        {
            "category":"Building & Trades",
            "subcategory":"Construction",
            "type":"Services"
        }
    ],
    "sg:phone":"+44 113 287 1140",
    "sg:postcode":"LS25 7ND",
    "sg:province":"North Yorkshire",
    "sg:tags":[
        "builder"
    ],
    "wof:name":"Michael Ferris",
    "wof:placetype":"venue"
},
  "geometry": {"coordinates":[-1.371276,53.770832],"type":"Point"}
}