{
  "type": "Feature",
  "properties": {
    "iso:country":"GB",
    "sg:address":"73 Leeds Road",
    "sg:city":"Harrogate",
    "sg:classifiers":[
        {
            "category":"Food & Beverages",
            "subcategory":"Supermarket",
            "type":"Retail Goods"
        }
    ],
    "sg:phone":"+44 1423 871599",
    "sg:postcode":"HG2 8EZ",
    "sg:province":"North Yorkshire",
    "wof:name":"Yorkshire Co-Operatives Ltd.",
    "wof:placetype":"venue"
},
  "geometry": {"coordinates":[-1.5340319872,53.9771881104],"type":"Point"}
}