{
  "type": "Feature",
  "properties": {
    "addr:full":"Malthouse Lane Salisbury Wiltshire SP2 7RA",
    "addr:postcode":"sp2 7ra",
    "addr:street":"Malthouse Lane",
    "iso:country":"GB",
    "sg:address":"Malthouse Lane",
    "sg:city":"Salisbury",
    "sg:classifiers":[
        {
            "category":"Arts & Performance",
            "subcategory":"Theater",
            "type":"Entertainment"
        }
    ],
    "sg:phone":"+44 1722 320117",
    "sg:postcode":"SP2 7RA",
    "sg:province":"Wiltshire",
    "sg:tags":[
        "hall",
        "theatre",
        "concert"
    ],
    "wof:name":"The Salisbury Arts Theatre Ltd.",
    "wof:placetype":"venue"
},
  "geometry": {"coordinates":[-1.799462,51.069435],"type":"Point"}
}