{
  "type": "Feature",
  "properties": {
    "iso:country":"GB",
    "sg:address":"Priory Lodge, 7 Priory Road",
    "sg:city":"Wells",
    "sg:classifiers":[
        {
            "category":"Banks & Credit Unions",
            "subcategory":"Bank",
            "type":"Services"
        }
    ],
    "sg:phone":"+44 1749 670046",
    "sg:postcode":"BA5 1SR",
    "sg:province":"Somerset",
    "sg:tags":[
        "broker",
        "mortgage"
    ],
    "wof:name":"INTEGRAL MORTGAGE CONSULTANTS LTD",
    "wof:placetype":"venue"
},
  "geometry": {"coordinates":[-2.645954,51.211349],"type":"Point"}
}