{
  "type": "Feature",
  "properties": {
    "addr:full":"Barnack Rd Stamford Cambridgeshire PE9 2BD",
    "addr:postcode":"pe9 2bd",
    "addr:street":"Barnack Rd",
    "iso:country":"GB",
    "sg:address":"Barnack Rd",
    "sg:city":"Stamford",
    "sg:classifiers":[
        {
            "category":"Arena",
            "subcategory":"Sports Club",
            "type":"Entertainment"
        }
    ],
    "sg:phone":"+44 1780 762484",
    "sg:postcode":"PE9 2BD",
    "sg:province":"Cambridgeshire",
    "wof:name":"Burghley Park Cricket Club",
    "wof:placetype":"venue"
},
  "geometry": {"coordinates":[-0.4668630064,52.6499977112],"type":"Point"}
}