{
  "type": "Feature",
  "properties": {
    "iso:country":"GB",
    "sg:address":"South Quintinespie, Laurieston",
    "sg:city":"Castle Douglas",
    "sg:classifiers":[
        {
            "category":"Farming",
            "subcategory":"Livestock Farm",
            "type":"Manufacturing & Wholesale Goods"
        },
        {
            "category":"Farming",
            "subcategory":"Farm",
            "type":"Manufacturing & Wholesale Goods"
        }
    ],
    "sg:phone":"+44 1644 450285",
    "sg:postcode":"DG7 2PL",
    "sg:province":"Dumfries and Galloway",
    "sg:tags":[
        "mixed",
        "crop",
        "others"
    ],
    "wof:name":"William & Jean Young",
    "wof:placetype":"venue"
},
  "geometry": {"coordinates":[-3.928704,54.94162],"type":"Point"}
}