{
  "type": "Feature",
  "properties": {
    "addr:full":"83 South Road Southall Greater London UB1 1SQ",
    "addr:housenumber":"83",
    "addr:postcode":"ub1 1sq",
    "addr:street":"South Road",
    "iso:country":"GB",
    "sg:address":"83 South Road",
    "sg:city":"Southall",
    "sg:classifiers":[
        {
            "category":"Personal",
            "type":"Services"
        },
        {
            "category":"Travel",
            "subcategory":"Travel Agent",
            "type":"Entertainment"
        }
    ],
    "sg:phone":"+44 870 011 0220",
    "sg:postcode":"UB1 1SQ",
    "sg:province":"Greater London",
    "sg:tags":[
        "introduction",
        "agency",
        "friendship",
        "dating"
    ],
    "wof:name":"Suman Marriage Bureau",
    "wof:placetype":"venue"
},
  "geometry": {"coordinates":[-0.377859,51.507572],"type":"Point"}
}