{
  "type": "Feature",
  "properties": {
    "addr:full":"2a Astwood Rd Worcester Worcestershire WR3 8ET",
    "addr:housenumber":"2a",
    "addr:postcode":"wr3 8et",
    "addr:street":"Astwood Rd",
    "iso:country":"GB",
    "sg:address":"2a Astwood Rd",
    "sg:city":"Worcester",
    "sg:classifiers":[
        {
            "category":"Building & Trades",
            "subcategory":"Construction",
            "type":"Services"
        }
    ],
    "sg:phone":"+44 1905 29600",
    "sg:postcode":"WR3 8ET",
    "sg:province":"Worcestershire",
    "sg:tags":[
        "roofing"
    ],
    "wof:name":"Sky-Line",
    "wof:placetype":"venue"
},
  "geometry": {"coordinates":[-2.208879,52.20269],"type":"Point"}
}