{
  "type": "Feature",
  "properties": {
    "addr:full":"Cornhill, 36-38 Cornhill London Greater London EC3V 3NG",
    "addr:housenumber":"36-38",
    "addr:postcode":"ec3v 3ng",
    "addr:street":"Cornhill;Cornhill",
    "iso:country":"GB",
    "sg:address":"Cornhill, 36-38 Cornhill",
    "sg:city":"London",
    "sg:classifiers":[
        {
            "category":"Freight",
            "type":"Transportation"
        }
    ],
    "sg:phone":"+44 20 7929 0966",
    "sg:postcode":"EC3V 3NG",
    "sg:province":"Greater London",
    "sg:tags":[
        "haulage",
        "road"
    ],
    "wof:name":"Jes Logistics Ltd.",
    "wof:placetype":"venue"
},
  "geometry": {"coordinates":[-0.0860700011,51.513168335],"type":"Point"}
}