{
  "type": "Feature",
  "properties": {
    "addr:full":"Sandford Mill Cottage, Sandford Reading Berkshire RG5 4TD",
    "addr:postcode":"rg5 4td",
    "addr:street":"Sandford",
    "iso:country":"GB",
    "sg:address":"Sandford Mill Cottage, Sandford",
    "sg:city":"Reading",
    "sg:classifiers":[
        {
            "category":"Banks & Credit Unions",
            "subcategory":"Financial Services",
            "type":"Services"
        }
    ],
    "sg:postcode":"RG5 4TD",
    "sg:province":"Berkshire",
    "sg:tags":[
        "consultant"
    ],
    "wof:name":"Christopher Spittle",
    "wof:placetype":"venue"
},
  "geometry": {"coordinates":[-0.8794549704,51.4515533447],"type":"Point"}
}