{
  "type": "Feature",
  "properties": {
    "iso:country":"GB",
    "sg:address":"Stanemuir Toll",
    "sg:city":"Lanark",
    "sg:classifiers":[
        {
            "category":"Community Center",
            "subcategory":"Youth",
            "type":"Public Place"
        }
    ],
    "sg:phone":"+44 1555 840517",
    "sg:postcode":"ML11 8LQ",
    "sg:province":"South Lanarkshire",
    "sg:tags":[
        "organisation",
        "centre"
    ],
    "wof:name":"Guide Association The",
    "wof:placetype":"venue"
},
  "geometry": {"coordinates":[-3.631189,55.700539],"type":"Point"}
}