{
  "type": "Feature",
  "properties": {
    "addr:full":"Unit 19, Southlodge, Henrietta Street Birmingham West Midlands B19 3QD",
    "addr:housenumber":"unit 19",
    "addr:postcode":"b19 3qd",
    "addr:street":"Southlodge Henrietta Street",
    "iso:country":"GB",
    "sg:address":"Unit 19, Southlodge, Henrietta Street",
    "sg:city":"Birmingham",
    "sg:classifiers":[
        {
            "category":"Shopping",
            "subcategory":"Clothing, Apparel, & Fashions",
            "type":"Retail Goods"
        }
    ],
    "sg:phone":"+44 121 236 0605",
    "sg:postcode":"B19 3QD",
    "sg:province":"West Midlands",
    "sg:tags":[
        "clothing"
    ],
    "wof:name":"The Link",
    "wof:placetype":"venue"
},
  "geometry": {"coordinates":[-1.9086040258,52.4785957336],"type":"Point"}
}