{
  "type": "Feature",
  "properties": {
    "iso:country":"GB",
    "sg:address":"328 Wells Road",
    "sg:city":"Bristol",
    "sg:classifiers":[
        {
            "category":"Travel",
            "subcategory":"Hostel",
            "type":"Entertainment"
        }
    ],
    "sg:phone":"+44 117 977 4528",
    "sg:postcode":"BS4 2QL",
    "sg:province":"City of Bristol",
    "wof:name":"The Young Women's Christian Association of Great Britian",
    "wof:placetype":"venue"
},
  "geometry": {"coordinates":[-2.566015,51.433891],"type":"Point"}
}