{
  "type": "Feature",
  "properties": {
    "iso:country":"GB",
    "sg:address":"8 Greenlea Fold, Yeadon",
    "sg:city":"Leeds",
    "sg:classifiers":[
        {
            "category":"Building & Trades",
            "subcategory":"Construction",
            "type":"Services"
        }
    ],
    "sg:phone":"+44 113 250 8715",
    "sg:postcode":"LS19 7JJ",
    "sg:province":"West Yorkshire",
    "sg:tags":[
        "joiner",
        "carpenter"
    ],
    "wof:name":"Kevin Gallagher Fitted Kitchens Bedrooms & Bathro",
    "wof:placetype":"venue"
},
  "geometry": {"coordinates":[-1.69668,53.863125],"type":"Point"}
}