{
  "type": "Feature",
  "properties": {
    "iso:country":"GB",
    "sg:address":"37 Ivy House Rd",
    "sg:city":"Whitstable",
    "sg:classifiers":[
        {
            "category":"Manufacturing",
            "subcategory":"Petroleum Products",
            "type":"Manufacturing & Wholesale Goods"
        }
    ],
    "sg:phone":"+44 1227 772383",
    "sg:postcode":"CT5 1PL",
    "sg:province":"Kent",
    "sg:tags":[
        "double",
        "glazing"
    ],
    "wof:name":"D W Systems",
    "wof:placetype":"venue"
},
  "geometry": {"coordinates":[1.03891,51.356415],"type":"Point"}
}