{
  "type": "Feature",
  "properties": {
    "iso:country":"GB",
    "sg:address":"Lynter, Market Weighton Road, North Cave",
    "sg:city":"Brough",
    "sg:classifiers":[
        {
            "category":"Recreation",
            "subcategory":"Dog Park",
            "type":"Entertainment"
        },
        {
            "category":"Transit Center",
            "subcategory":"Passenger",
            "type":"Transportation"
        }
    ],
    "sg:phone":"+44 1430 422605",
    "sg:postcode":"HU15 2LY",
    "sg:province":"East Riding of Yorkshire",
    "sg:tags":[
        "boarding",
        "kennel",
        "catteries"
    ],
    "wof:name":"The Mews Luxury Boarding Cattery",
    "wof:placetype":"venue"
},
  "geometry": {"coordinates":[-0.64621,53.780151],"type":"Point"}
}