{
  "type": "Feature",
  "properties": {
    "iso:country":"GB",
    "sg:address":"Naseby Road, Welford",
    "sg:city":"Northampton",
    "sg:classifiers":[
        {
            "category":"Farming",
            "subcategory":"Livestock Farm",
            "type":"Manufacturing & Wholesale Goods"
        }
    ],
    "sg:postcode":"NN6 6HZ",
    "sg:province":"Northamptonshire",
    "sg:tags":[
        "others"
    ],
    "wof:name":"John Williams",
    "wof:placetype":"venue"
},
  "geometry": {"coordinates":[-0.991369,52.394596],"type":"Point"}
}