{
  "type": "Feature",
  "properties": {
    "addr:full":"Eastern Av Gloucester Gloucestershire GL4 7BD",
    "addr:postcode":"gl4 7bd",
    "addr:street":"Eastern Av",
    "iso:country":"GB",
    "sg:address":"Eastern Av",
    "sg:city":"Gloucester",
    "sg:classifiers":[
        {
            "category":"Government",
            "subcategory":"Office",
            "type":"Public Place"
        }
    ],
    "sg:phone":"+44 1452 302636",
    "sg:postcode":"GL4 7BD",
    "sg:province":"Gloucestershire",
    "sg:tags":[
        "armed",
        "reserve"
    ],
    "wof:name":"TAVRA",
    "wof:placetype":"venue"
},
  "geometry": {"coordinates":[-2.2135579586,51.8635597229],"type":"Point"}
}