{
  "type": "Feature",
  "properties": {
    "addr:full":"206 Yarm Road Darlington Durham DL1 1XD",
    "addr:housenumber":"206",
    "addr:postcode":"dl1 1xd",
    "addr:street":"Yarm Road",
    "iso:country":"GB",
    "sg:address":"206 Yarm Road",
    "sg:city":"Darlington",
    "sg:classifiers":[
        {
            "category":"Professional",
            "subcategory":"Art Services",
            "type":"Services"
        },
        {
            "category":"Home & Garden",
            "subcategory":"Building Materials",
            "type":"Retail Goods"
        }
    ],
    "sg:phone":"+44 1325 489601",
    "sg:postcode":"DL1 1XD",
    "sg:province":"Durham",
    "sg:tags":[
        "merchant",
        "supplier",
        "decorating",
        "painting"
    ],
    "wof:name":"Glenwood Paints Supplies Ltd",
    "wof:placetype":"venue"
},
  "geometry": {"coordinates":[-1.530799,54.523193],"type":"Point"}
}