{
  "type": "Feature",
  "properties": {
    "addr:full":"6 Lasham Walk Fareham Hampshire PO14 1SD",
    "addr:housenumber":"6",
    "addr:postcode":"po14 1sd",
    "addr:street":"Lasham Walk",
    "iso:country":"GB",
    "sg:address":"6 Lasham Walk",
    "sg:city":"Fareham",
    "sg:classifiers":[
        {
            "category":"Health Services",
            "subcategory":"Health Practitioner",
            "type":"Services"
        }
    ],
    "sg:phone":"+44 1329 282657",
    "sg:postcode":"PO14 1SD",
    "sg:province":"Hampshire",
    "sg:tags":[
        "hypnotherapists"
    ],
    "wof:name":"Dianna Winton",
    "wof:placetype":"venue"
},
  "geometry": {"coordinates":[-1.20915,50.846298],"type":"Point"}
}