{
  "type": "Feature",
  "properties": {
    "addr:full":"68 Thornes La Wakefield West Yorkshire WF1 5RR",
    "addr:housenumber":"68",
    "addr:postcode":"wf1 5rr",
    "addr:street":"Thornes La Wakefield West",
    "iso:country":"GB",
    "sg:address":"68 Thornes La",
    "sg:city":"Wakefield",
    "sg:classifiers":[
        {
            "category":"Bars & Pubs",
            "type":"Food & Drink"
        }
    ],
    "sg:postcode":"WF1 5RR",
    "sg:province":"West Yorkshire",
    "sg:tags":[
        "pubs",
        "inn"
    ],
    "wof:name":"The Thorne",
    "wof:placetype":"venue"
},
  "geometry": {"coordinates":[-1.495865,53.674591],"type":"Point"}
}