{
  "type": "Feature",
  "properties": {
    "addr:full":"Ovington Lane Richmond Durham DL11 7BL",
    "addr:postcode":"dl11 7bl",
    "addr:street":"Ovington Lane",
    "iso:country":"GB",
    "sg:address":"Ovington Lane",
    "sg:city":"Richmond",
    "sg:classifiers":[
        {
            "category":"Manufacturing",
            "subcategory":"Buildings",
            "type":"Manufacturing & Wholesale Goods"
        }
    ],
    "sg:phone":"+44 1325 730536",
    "sg:postcode":"DL11 7BL",
    "sg:province":"Durham",
    "sg:tags":[
        "mobile",
        "home"
    ],
    "wof:name":"Winston Bridge Caravan Park",
    "wof:placetype":"venue"
},
  "geometry": {"coordinates":[-1.7976380587,54.527557373],"type":"Point"}
}