{
  "type": "Feature",
  "properties": {
    "iso:country":"GB",
    "sg:address":"1 Chapel Lane, East Huntspill",
    "sg:city":"Highbridge",
    "sg:classifiers":[
        {
            "category":"Farming",
            "subcategory":"Livestock Farm",
            "type":"Manufacturing & Wholesale Goods"
        }
    ],
    "sg:postcode":"TA9 3NQ",
    "sg:province":"Somerset",
    "sg:tags":[
        "others"
    ],
    "wof:name":"N Wall",
    "wof:placetype":"venue"
},
  "geometry": {"coordinates":[-2.937995,51.205235],"type":"Point"}
}