{
  "type": "Feature",
  "properties": {
    "addr:full":"83 Queensway West Wickham Kent BR4 9DT",
    "addr:housenumber":"83",
    "addr:postcode":"br4 9dt",
    "addr:street":"Queensway West Wickham",
    "iso:country":"GB",
    "sg:address":"83 Queensway",
    "sg:city":"West Wickham",
    "sg:classifiers":[
        {
            "category":"Bus Charters",
            "type":"Transportation"
        }
    ],
    "sg:phone":"+44 20 8325 8567",
    "sg:postcode":"BR4 9DT",
    "sg:province":"Kent",
    "sg:tags":[
        "mini",
        "hire",
        "leasing"
    ],
    "wof:name":"McCarthy Mini Buses",
    "wof:placetype":"venue"
},
  "geometry": {"coordinates":[0.0045540002,51.3663330078],"type":"Point"}
}