{
  "type": "Feature",
  "properties": {
    "iso:country":"GB",
    "sg:address":"5 Warren Row, Fernbank Place",
    "sg:city":"Ascot",
    "sg:classifiers":[
        {
            "category":"Shopping",
            "subcategory":"Clothing, Apparel, & Fashions",
            "type":"Retail Goods"
        }
    ],
    "sg:phone":"+44 1344 882197",
    "sg:postcode":"SL5 8HN",
    "sg:province":"Berkshire",
    "sg:tags":[
        "haberdasher"
    ],
    "wof:name":"Precious Moments",
    "wof:placetype":"venue"
},
  "geometry": {"coordinates":[-0.698718,51.417046],"type":"Point"}
}