{
  "type": "Feature",
  "properties": {
    "iso:country":"GB",
    "sg:address":"20 Forest Road East",
    "sg:city":"Nottingham",
    "sg:classifiers":[
        {
            "category":"Health Services",
            "subcategory":"Nursing And Care Facility",
            "type":"Services"
        }
    ],
    "sg:phone":"+44 115 978 0617",
    "sg:postcode":"NG1 4HH",
    "sg:province":"Nottinghamshire",
    "sg:tags":[
        "home"
    ],
    "wof:name":"Forest Lodge Rest Home",
    "wof:placetype":"venue"
},
  "geometry": {"coordinates":[-1.162087,52.963058],"type":"Point"}
}