{
  "type": "Feature",
  "properties": {
    "addr:full":"Fish Quay North Shields Northumberland NE27 0SZ",
    "addr:postcode":"ne27 0sz",
    "addr:street":"Fish Quay",
    "iso:country":"GB",
    "sg:address":"Fish Quay",
    "sg:city":"North Shields",
    "sg:classifiers":[
        {
            "category":"Shopping",
            "subcategory":"Crafts & Fabrics",
            "type":"Retail Goods"
        },
        {
            "category":"Recreation",
            "subcategory":"Fishing",
            "type":"Entertainment"
        }
    ],
    "sg:phone":"+44 191 296 1809",
    "sg:postcode":"NE27 0SZ",
    "sg:province":"Northumberland",
    "sg:tags":[
        "angling",
        "netting"
    ],
    "wof:name":"Whiting Nets",
    "wof:placetype":"venue"
},
  "geometry": {"coordinates":[-1.432822,55.010887],"type":"Point"}
}