{
  "type": "Feature",
  "properties": {
    "addr:full":"1a Vivian Road Wellingborough Northamptonshire NN8 1JL",
    "addr:housenumber":"1a",
    "addr:postcode":"nn8 1jl",
    "addr:street":"Vivian Road",
    "iso:country":"GB",
    "sg:address":"1a Vivian Road",
    "sg:city":"Wellingborough",
    "sg:classifiers":[
        {
            "category":"Personal",
            "subcategory":"Beauty Salon",
            "type":"Services"
        }
    ],
    "sg:phone":"+44 1933 225103",
    "sg:postcode":"NN8 1JL",
    "sg:province":"Northamptonshire",
    "sg:tags":[
        "lady",
        "hairdresser"
    ],
    "wof:name":"Linda Hair Fashions",
    "wof:placetype":"venue"
},
  "geometry": {"coordinates":[-0.681789,52.304913],"type":"Point"}
}