{
  "type": "Feature",
  "properties": {
    "addr:full":"Saxtead Road, Framlingham Woodbridge Suffolk IP13 9HE",
    "addr:postcode":"ip13 9he",
    "addr:street":"Saxtead Road",
    "iso:country":"GB",
    "sg:address":"Saxtead Road, Framlingham",
    "sg:city":"Woodbridge",
    "sg:classifiers":[
        {
            "category":"Community Center",
            "subcategory":"Youth",
            "type":"Public Place"
        }
    ],
    "sg:phone":"+44 1728 723594",
    "sg:postcode":"IP13 9HE",
    "sg:province":"Suffolk",
    "sg:tags":[
        "organisation",
        "centre"
    ],
    "wof:name":"Framlingham Youth Club",
    "wof:placetype":"venue"
},
  "geometry": {"coordinates":[1.343332,52.221081],"type":"Point"}
}