{
  "type": "Feature",
  "properties": {
    "iso:country":"GB",
    "sg:address":"St Andrews Well",
    "sg:city":"Bridport",
    "sg:classifiers":[
        {
            "category":"Travel",
            "subcategory":"Hotels & Motels",
            "type":"Entertainment"
        }
    ],
    "sg:phone":"+44 1308 424156",
    "sg:postcode":"DT6 3DL",
    "sg:province":"Dorset",
    "sg:tags":[
        "house",
        "guest"
    ],
    "wof:name":"The Well",
    "wof:placetype":"venue"
},
  "geometry": {"coordinates":[-2.7439639568,50.7417411804],"type":"Point"}
}