{
  "type": "Feature",
  "properties": {
    "iso:country":"GB",
    "sg:address":"63 Grand Parade Green Lane, Harringay",
    "sg:city":"Finsbury Park",
    "sg:classifiers":[
        {
            "category":"Professional",
            "subcategory":"Printing & Photocopies",
            "type":"Services"
        }
    ],
    "sg:phone":"+44 20 8880 2322",
    "sg:postcode":"N4 1AF",
    "sg:province":"Greater London",
    "sg:tags":[
        "plate",
        "lithographic",
        "maker"
    ],
    "wof:name":"Harringay Press",
    "wof:placetype":"venue"
},
  "geometry": {"coordinates":[-0.09877,51.578388],"type":"Point"}
}