{
  "type": "Feature",
  "properties": {
    "iso:country":"GB",
    "sg:address":"96 High Street, Strood",
    "sg:city":"Rochester",
    "sg:classifiers":[
        {
            "category":"Shopping",
            "subcategory":"Jewelry",
            "type":"Retail Goods"
        },
        {
            "category":"Shopping",
            "subcategory":"Comic Books",
            "type":"Retail Goods"
        }
    ],
    "sg:phone":"+44 1634 722754",
    "sg:postcode":"ME2 4TP",
    "sg:province":"Kent",
    "sg:tags":[
        "jeweller",
        "sale",
        "jewellery"
    ],
    "wof:name":"The Medway Diamond House",
    "wof:placetype":"venue"
},
  "geometry": {"coordinates":[0.49529,51.395767],"type":"Point"}
}