{
  "type": "Feature",
  "properties": {
    "iso:country":"GB",
    "sg:address":"35 High Causeway, Whittlesey",
    "sg:city":"Peterborough",
    "sg:classifiers":[
        {
            "category":"Shopping",
            "subcategory":"Pets & Pet Supplies",
            "type":"Retail Goods"
        }
    ],
    "sg:phone":"+44 1733 203803",
    "sg:postcode":"PE7 1AN",
    "sg:province":"Cambridgeshire",
    "sg:tags":[
        "shop"
    ],
    "wof:name":"June's Pet Foods",
    "wof:placetype":"venue"
},
  "geometry": {"coordinates":[-0.1270650029,52.5576896667],"type":"Point"}
}