{
  "type": "Feature",
  "properties": {
    "addr:full":"Berwick Lodge, Berwick Road Shrewsbury Shropshire SY1 2NA",
    "addr:postcode":"sy1 2na",
    "addr:street":"Berwick Road",
    "iso:country":"GB",
    "sg:address":"Berwick Lodge, Berwick Road",
    "sg:city":"Shrewsbury",
    "sg:classifiers":[
        {
            "category":"Building & Trades",
            "subcategory":"Construction",
            "type":"Services"
        }
    ],
    "sg:postcode":"SY1 2NA",
    "sg:province":"Shropshire",
    "sg:tags":[
        "builder"
    ],
    "wof:name":"F R G Micklewright",
    "wof:placetype":"venue"
},
  "geometry": {"coordinates":[-2.758059,52.718811],"type":"Point"}
}