{
  "type": "Feature",
  "properties": {
    "iso:country":"GB",
    "sg:address":"13 Castle Dene",
    "sg:city":"Maidstone",
    "sg:classifiers":[
        {
            "category":"Shopping",
            "subcategory":"Clothing, Apparel, & Fashions",
            "type":"Retail Goods"
        }
    ],
    "sg:postcode":"ME14 2NH",
    "sg:province":"Kent",
    "sg:tags":[
        "dresswear"
    ],
    "wof:name":"A Touch of Class",
    "wof:placetype":"venue"
},
  "geometry": {"coordinates":[0.5155140162,51.2930603027],"type":"Point"}
}