{
  "type": "Feature",
  "properties": {
    "addr:full":"Grange Farm, Grange Road, Elswick Preston Lancashire PR4 3UA",
    "addr:postcode":"pr4 3ua",
    "addr:street":"Grange Road",
    "iso:country":"GB",
    "sg:address":"Grange Farm, Grange Road, Elswick",
    "sg:city":"Preston",
    "sg:classifiers":[
        {
            "category":"Farming",
            "subcategory":"Farm",
            "type":"Manufacturing & Wholesale Goods"
        },
        {
            "category":"Recreation",
            "subcategory":"Campground",
            "type":"Entertainment"
        }
    ],
    "sg:phone":"+44 1995 670223",
    "sg:postcode":"PR4 3UA",
    "sg:province":"Lancashire",
    "sg:tags":[
        "mixed",
        "caravan",
        "park"
    ],
    "wof:name":"W & A H Thistlethwaite & Son",
    "wof:placetype":"venue"
},
  "geometry": {"coordinates":[-2.88721,53.837421],"type":"Point"}
}