{
  "type": "Feature",
  "properties": {
    "addr:full":"186 Valence Wood Road Dagenham Essex RM8 3AH",
    "addr:housenumber":"186",
    "addr:postcode":"rm8 3ah",
    "addr:street":"Valence Wood Road",
    "iso:country":"GB",
    "sg:address":"186 Valence Wood Road",
    "sg:city":"Dagenham",
    "sg:classifiers":[
        {
            "category":"Shopping",
            "subcategory":"Computers & Home Electronics",
            "type":"Retail Goods"
        }
    ],
    "sg:phone":"+44 20 8517 6742",
    "sg:postcode":"RM8 3AH",
    "sg:province":"Essex",
    "sg:tags":[
        "aerial",
        "television",
        "radio"
    ],
    "wof:name":"Advanced Aerials",
    "wof:placetype":"venue"
},
  "geometry": {"coordinates":[0.1410250068,51.5555992126],"type":"Point"}
}