{
  "type": "Feature",
  "properties": {
    "addr:full":"Main Street, Walesby Newark Nottinghamshire NG22 9NU",
    "addr:postcode":"ng22 9nu",
    "addr:street":"Main Street",
    "iso:country":"GB",
    "sg:address":"Main Street, Walesby",
    "sg:city":"Newark",
    "sg:classifiers":[
        {
            "category":"Bars & Pubs",
            "type":"Food & Drink"
        }
    ],
    "sg:phone":"+44 1623 836209",
    "sg:postcode":"NG22 9NU",
    "sg:province":"Nottinghamshire",
    "sg:tags":[
        "pubs",
        "inn"
    ],
    "wof:name":"Red Lion Inn",
    "wof:placetype":"venue"
},
  "geometry": {"coordinates":[-0.968734026,53.2128753662],"type":"Point"}
}