{
  "type": "Feature",
  "properties": {
    "addr:full":"446 Blackburn Road Bolton Lancashire BL1 8NL",
    "addr:housenumber":"446",
    "addr:postcode":"bl1 8nl",
    "addr:street":"Blackburn Road",
    "iso:country":"GB",
    "sg:address":"446 Blackburn Road",
    "sg:city":"Bolton",
    "sg:classifiers":[
        {
            "category":"Retail",
            "subcategory":"Funeral Services",
            "type":"Services"
        },
        {
            "category":"Building & Trades",
            "subcategory":"Construction",
            "type":"Services"
        }
    ],
    "sg:phone":"+44 1204 309189",
    "sg:postcode":"BL1 8NL",
    "sg:province":"Lancashire",
    "sg:tags":[
        "mnfr",
        "monumental",
        "mason"
    ],
    "wof:name":"J Child & Son Ltd",
    "wof:placetype":"venue"
},
  "geometry": {"coordinates":[-2.432774,53.598049],"type":"Point"}
}