{
  "type": "Feature",
  "properties": {
    "iso:country":"GB",
    "sg:address":"38 Pleasance Way",
    "sg:city":"New Milton",
    "sg:classifiers":[
        {
            "category":"Home & Garden",
            "subcategory":"Household Appliances",
            "type":"Retail Goods"
        }
    ],
    "sg:phone":"+44 1425 616333",
    "sg:postcode":"BH25 6TD",
    "sg:province":"Hampshire",
    "sg:tags":[
        "cleaner",
        "domestic",
        "vacuum"
    ],
    "wof:name":"Invac Central Cleaning Systems",
    "wof:placetype":"venue"
},
  "geometry": {"coordinates":[-1.664079,50.754417],"type":"Point"}
}