{
  "type": "Feature",
  "properties": {
    "addr:full":"2 Station Road, Rogiet Caldicot Monmouthshire NP26 3UE",
    "addr:housenumber":"2",
    "addr:postcode":"np26 3ue",
    "addr:street":"Station Road",
    "iso:country":"GB",
    "sg:address":"2 Station Road, Rogiet",
    "sg:city":"Caldicot",
    "sg:classifiers":[
        {
            "category":"Building & Trades",
            "subcategory":"Construction",
            "type":"Services"
        }
    ],
    "sg:postcode":"NP26 3UE",
    "sg:province":"Monmouthshire",
    "sg:tags":[
        "roofing"
    ],
    "wof:name":"K J Lewis",
    "wof:placetype":"venue"
},
  "geometry": {"coordinates":[-2.748045,51.585957],"type":"Point"}
}