{
  "type": "Feature",
  "properties": {
    "iso:country":"GB",
    "sg:address":"39 Delves Wood Rd, Beaumont Pk",
    "sg:city":"Huddersfield",
    "sg:classifiers":[
        {
            "category":"Building & Trades",
            "subcategory":"Construction",
            "type":"Services"
        }
    ],
    "sg:postcode":"HD4 7AS",
    "sg:province":"West Yorkshire",
    "sg:tags":[
        "builder"
    ],
    "wof:name":"Lees,Norman, Joiners & Contractors",
    "wof:placetype":"venue"
},
  "geometry": {"coordinates":[-1.817287,53.622501],"type":"Point"}
}