{
  "type": "Feature",
  "properties": {
    "addr:full":"39 Delves Wood Rd, Beaumont Pk Huddersfield West Yorkshire HD4 7AS",
    "addr:housenumber":"39",
    "addr:postcode":"hd4 7as",
    "addr:street":"Delves Wood Rd;West",
    "iso:country":"GB",
    "sg:address":"39 Delves Wood Rd, Beaumont Pk",
    "sg:city":"Huddersfield",
    "sg:classifiers":[
        {
            "category":"Building & Trades",
            "subcategory":"Construction",
            "type":"Services"
        }
    ],
    "sg:postcode":"HD4 7AS",
    "sg:province":"West Yorkshire",
    "sg:tags":[
        "builder"
    ],
    "wof:name":"Lees,Norman, Joiners & Contractors",
    "wof:placetype":"venue"
},
  "geometry": {"coordinates":[-1.817287,53.622501],"type":"Point"}
}