{
  "type": "Feature",
  "properties": {
    "iso:country":"GB",
    "sg:address":"70 Wood Lane",
    "sg:city":"Dagenham",
    "sg:classifiers":[
        {
            "category":"Fast Food",
            "type":"Food & Drink"
        }
    ],
    "sg:phone":"+44 20 8592 0555",
    "sg:postcode":"RM8 2NT",
    "sg:province":"Essex",
    "sg:tags":[
        "away",
        "take"
    ],
    "wof:name":"le Spice",
    "wof:placetype":"venue"
},
  "geometry": {"coordinates":[0.129291,51.551563],"type":"Point"}
}