{
  "type": "Feature",
  "properties": {
    "addr:full":"97 Walton Vale Liverpool Merseyside L9 4SR",
    "addr:housenumber":"97",
    "addr:postcode":"l9 4sr",
    "addr:street":"Walton Vale",
    "iso:country":"GB",
    "sg:address":"97 Walton Vale",
    "sg:city":"Liverpool",
    "sg:classifiers":[
        {
            "category":"Food & Beverages",
            "subcategory":"Liquor & Beverages",
            "type":"Retail Goods"
        }
    ],
    "sg:phone":"+44 151 525 0512",
    "sg:postcode":"L9 4SR",
    "sg:province":"Merseyside",
    "sg:tags":[
        "beer",
        "spirit",
        "wines"
    ],
    "wof:name":"Huttons",
    "wof:placetype":"venue"
},
  "geometry": {"coordinates":[-2.959159,53.463749],"type":"Point"}
}