{
  "type": "Feature",
  "properties": {
    "addr:full":"73 Waterloo Road Blackpool Lancashire FY4 1AD",
    "addr:housenumber":"73",
    "addr:postcode":"fy4 1ad",
    "addr:street":"Waterloo Road",
    "iso:country":"GB",
    "sg:address":"73 Waterloo Road",
    "sg:city":"Blackpool",
    "sg:classifiers":[
        {
            "category":"Shopping",
            "subcategory":"Jewelry",
            "type":"Retail Goods"
        },
        {
            "category":"Shopping",
            "subcategory":"Comic Books",
            "type":"Retail Goods"
        }
    ],
    "sg:phone":"+44 1253 344393",
    "sg:postcode":"FY4 1AD",
    "sg:province":"Lancashire",
    "sg:tags":[
        "jeweller",
        "sale",
        "jewellery"
    ],
    "wof:name":"DAVID & K T SIMPSON",
    "wof:placetype":"venue"
},
  "geometry": {"coordinates":[-3.051485,53.79879],"type":"Point"}
}