{
  "type": "Feature",
  "properties": {
    "iso:country":"GB",
    "sg:address":"Owler Lodge Alkham Valley Road, Alkham",
    "sg:city":"Dover",
    "sg:classifiers":[
        {
            "category":"Travel",
            "subcategory":"Hotels & Motels",
            "type":"Entertainment"
        }
    ],
    "sg:phone":"+44 1304 826375",
    "sg:postcode":"CT15 7DS",
    "sg:province":"Kent",
    "sg:tags":[
        "house",
        "guest"
    ],
    "wof:name":"Owler Lodge Guest House",
    "wof:placetype":"venue"
},
  "geometry": {"coordinates":[1.224187,51.135864],"type":"Point"}
}