{
  "type": "Feature",
  "properties": {
    "addr:full":"48 Eastgate Street Bury St Edmunds Suffolk IP33 1YW",
    "addr:housenumber":"48",
    "addr:postcode":"ip33 1yw",
    "addr:street":"Eastgate Street",
    "iso:country":"GB",
    "sg:address":"48 Eastgate Street",
    "sg:city":"Bury St Edmunds",
    "sg:classifiers":[
        {
            "category":"Banks & Credit Unions",
            "subcategory":"Atm",
            "type":"Services"
        }
    ],
    "sg:postcode":"IP33 1YW",
    "sg:province":"Suffolk",
    "sg:tags":[
        "recording",
        "answering"
    ],
    "wof:name":"Radiocare",
    "wof:placetype":"venue"
},
  "geometry": {"coordinates":[0.7250819802,52.2485084534],"type":"Point"}
}