{
  "type": "Feature",
  "properties": {
    "addr:full":"61 Weybridge Mead Studio Yateley Hampshire GU46 7UX",
    "addr:housenumber":"61",
    "addr:postcode":"gu46 7ux",
    "addr:street":"Weybridge Mead",
    "iso:country":"GB",
    "sg:address":"61 Weybridge Mead Studio",
    "sg:city":"Yateley",
    "sg:classifiers":[
        {
            "category":"Communications",
            "type":"Services"
        }
    ],
    "sg:phone":"+44 1252 409077",
    "sg:postcode":"GU46 7UX",
    "sg:province":"Hampshire",
    "sg:tags":[
        "audio-visual"
    ],
    "wof:name":"Youngvision & Omnific Videos",
    "wof:placetype":"venue"
},
  "geometry": {"coordinates":[-0.8171010017,51.3425636292],"type":"Point"}
}