{
  "type": "Feature",
  "properties": {
    "addr:full":"First Avenue, Cliftonville Margate Kent CT9 2LF",
    "addr:postcode":"ct9 2lf",
    "addr:street":"First Avenue;Margate",
    "iso:country":"GB",
    "sg:address":"First Avenue, Cliftonville",
    "sg:city":"Margate",
    "sg:classifiers":[
        {
            "category":"Travel",
            "subcategory":"Hotels & Motels",
            "type":"Entertainment"
        }
    ],
    "sg:postcode":"CT9 2LF",
    "sg:province":"Kent",
    "wof:name":"Endcliffe Hotel",
    "wof:placetype":"venue"
},
  "geometry": {"coordinates":[1.4018599987,51.3907814026],"type":"Point"}
}