{
  "type": "Feature",
  "properties": {
    "addr:full":"3 Parkside Road, Westclyst, Pinhoe Exeter Devon EX1 3TN",
    "addr:housenumber":"3",
    "addr:postcode":"ex1 3tn",
    "addr:street":"Parkside Road",
    "iso:country":"GB",
    "sg:address":"3 Parkside Road, Westclyst, Pinhoe",
    "sg:city":"Exeter",
    "sg:classifiers":[
        {
            "category":"Building & Trades",
            "subcategory":"Construction",
            "type":"Services"
        }
    ],
    "sg:postcode":"EX1 3TN",
    "sg:province":"Devon",
    "sg:tags":[
        "decorator",
        "painter"
    ],
    "wof:name":"M J Helman",
    "wof:placetype":"venue"
},
  "geometry": {"coordinates":[-3.4629240036,50.7479934692],"type":"Point"}
}