{
  "type": "Feature",
  "properties": {
    "addr:full":"16 High Street Rochester Kent ME1 1PX",
    "addr:housenumber":"16",
    "addr:postcode":"me1 1px",
    "addr:street":"High Street",
    "iso:country":"GB",
    "sg:address":"16 High Street",
    "sg:city":"Rochester",
    "sg:classifiers":[
        {
            "category":"Travel",
            "subcategory":"Hotels & Motels",
            "type":"Entertainment"
        }
    ],
    "sg:phone":"+44 1634 846266",
    "sg:postcode":"ME1 1PX",
    "sg:province":"Kent",
    "wof:name":"Rabb Inns Ltd.",
    "wof:placetype":"venue"
},
  "geometry": {"coordinates":[0.5025269985,51.390789032],"type":"Point"}
}