{
  "type": "Feature",
  "properties": {
    "iso:country":"GB",
    "sg:address":"Tyddyn Solomon, Cyttir Lane",
    "sg:city":"Bangor",
    "sg:classifiers":[
        {
            "category":"Farming",
            "subcategory":"Livestock Farm",
            "type":"Manufacturing & Wholesale Goods"
        },
        {
            "category":"Building & Trades",
            "subcategory":"Construction",
            "type":"Services"
        }
    ],
    "sg:phone":"+44 1248 351738",
    "sg:postcode":"LL57 4DA",
    "sg:province":"Gwynedd",
    "sg:tags":[
        "installation",
        "system",
        "heating",
        "servicing",
        "others",
        "central"
    ],
    "wof:name":"Alwyn S Williams",
    "wof:placetype":"venue"
},
  "geometry": {"coordinates":[-4.1260638237,53.2295951843],"type":"Point"}
}