{
  "type": "Feature",
  "properties": {
    "addr:full":"Meadow Farm, Marsh Lane, Lower Whitley Warrington Cheshire WA4 4EU",
    "addr:postcode":"wa4 4eu",
    "addr:street":"Meadow;Marsh Lane",
    "iso:country":"GB",
    "sg:address":"Meadow Farm, Marsh Lane, Lower Whitley",
    "sg:city":"Warrington",
    "sg:classifiers":[
        {
            "category":"Farming",
            "subcategory":"Livestock Farm",
            "type":"Manufacturing & Wholesale Goods"
        },
        {
            "category":"Farming",
            "subcategory":"Farm",
            "type":"Manufacturing & Wholesale Goods"
        }
    ],
    "sg:phone":"+44 1928 718020",
    "sg:postcode":"WA4 4EU",
    "sg:province":"Cheshire",
    "sg:tags":[
        "mixed",
        "crop",
        "others"
    ],
    "wof:name":"D J & S M Rutter",
    "wof:placetype":"venue"
},
  "geometry": {"coordinates":[-2.581244,53.305546],"type":"Point"}
}