{
  "type": "Feature",
  "properties": {
    "iso:country":"GB",
    "sg:address":"1-3 Monnow Bridge",
    "sg:city":"Monmouth",
    "sg:classifiers":[
        {
            "category":"Personal",
            "subcategory":"Beauty Salon",
            "type":"Services"
        }
    ],
    "sg:postcode":"NP25 5ER",
    "sg:province":"Gloucestershire",
    "sg:tags":[
        "unisex",
        "hairdresser"
    ],
    "wof:name":"Mr John Stanley",
    "wof:placetype":"venue"
},
  "geometry": {"coordinates":[-2.720606,51.808769],"type":"Point"}
}