{
  "type": "Feature",
  "properties": {
    "addr:full":"422 Worsley Rd Manchester Greater Manchester M30 8HQ",
    "addr:housenumber":"422",
    "addr:postcode":"m30 8hq",
    "addr:street":"Worsley Rd",
    "iso:country":"GB",
    "sg:address":"422 Worsley Rd",
    "sg:city":"Manchester",
    "sg:classifiers":[
        {
            "category":"Shopping",
            "subcategory":"Department Store",
            "type":"Retail Goods"
        }
    ],
    "sg:phone":"+44 161 789 3521",
    "sg:postcode":"M30 8HQ",
    "sg:province":"Greater Manchester",
    "wof:name":"Arrods",
    "wof:placetype":"venue"
},
  "geometry": {"coordinates":[-2.37249,53.491455],"type":"Point"}
}