{
  "type": "Feature",
  "properties": {
    "iso:country":"GB",
    "sg:address":"St. Mary's Ct, St. Mary's Gate",
    "sg:city":"Chesterfield",
    "sg:classifiers":[
        {
            "category":"Wholesale",
            "subcategory":"Office Equipment",
            "type":"Manufacturing & Wholesale Goods"
        }
    ],
    "sg:phone":"+44 1246 551158",
    "sg:postcode":"S41 7TD",
    "sg:province":"Derbyshire",
    "sg:tags":[
        "agency",
        "business",
        "enterprise"
    ],
    "wof:name":"North Derbyshire Training & Enterprise C",
    "wof:placetype":"venue"
},
  "geometry": {"coordinates":[-1.404415,53.274338],"type":"Point"}
}