{
  "type": "Feature",
  "properties": {
    "iso:country":"GB",
    "sg:address":"The Shalet, Broad Acres, Headley",
    "sg:city":"Thatcham",
    "sg:classifiers":[
        {
            "category":"Home & Garden",
            "subcategory":"Building Materials",
            "type":"Retail Goods"
        }
    ],
    "sg:phone":"+44 1635 268354",
    "sg:postcode":"RG19 8JY",
    "sg:province":"Berkshire",
    "sg:tags":[
        "fencing"
    ],
    "wof:name":"J.M Nobes",
    "wof:placetype":"venue"
},
  "geometry": {"coordinates":[-1.257991,51.358124],"type":"Point"}
}