{
  "type": "Feature",
  "properties": {
    "iso:country":"GB",
    "sg:address":"182-184 Walworth Road",
    "sg:city":"Elephant And Castle",
    "sg:classifiers":[
        {
            "category":"Communications",
            "type":"Services"
        }
    ],
    "sg:phone":"+44 20 7277 0101",
    "sg:postcode":"SE17 1JJ",
    "sg:province":"Greater London",
    "sg:tags":[
        "telecommunication"
    ],
    "wof:name":"Netcom International Communications Ltd",
    "wof:placetype":"venue"
},
  "geometry": {"coordinates":[-0.096668,51.489616],"type":"Point"}
}