{
  "type": "Feature",
  "properties": {
    "addr:full":"12 Seaview Rd Peacehaven East Sussex BN10 8PX",
    "addr:housenumber":"12",
    "addr:postcode":"bn10 8px",
    "addr:street":"Seaview Rd Peacehaven",
    "iso:country":"GB",
    "sg:address":"12 Seaview Rd",
    "sg:city":"Peacehaven",
    "sg:classifiers":[
        {
            "category":"Organizations",
            "subcategory":"Membership Organization",
            "type":"Services"
        }
    ],
    "sg:postcode":"BN10 8PX",
    "sg:province":"East Sussex",
    "sg:tags":[
        "club"
    ],
    "wof:name":"New Peacehaven Club (The)",
    "wof:placetype":"venue"
},
  "geometry": {"coordinates":[0.0164340008,50.7865371704],"type":"Point"}
}