{
  "type": "Feature",
  "properties": {
    "addr:full":"13 Hillfield Rd Sevenoaks Kent TN13 2UH",
    "addr:housenumber":"13",
    "addr:postcode":"tn13 2uh",
    "addr:street":"Hillfield Rd",
    "iso:country":"GB",
    "sg:address":"13 Hillfield Rd",
    "sg:city":"Sevenoaks",
    "sg:classifiers":[
        {
            "category":"Wholesale",
            "subcategory":"Scrap",
            "type":"Manufacturing & Wholesale Goods"
        }
    ],
    "sg:phone":"+44 1732 462654",
    "sg:postcode":"TN13 2UH",
    "sg:province":"Kent",
    "sg:tags":[
        "waste",
        "metal"
    ],
    "wof:name":"E P Hocking",
    "wof:placetype":"venue"
},
  "geometry": {"coordinates":[0.165502,51.293034],"type":"Point"}
}