{
  "type": "Feature",
  "properties": {
    "addr:full":"Unit 15 Craven Court, High St Skipton Lancashire BD23 1DG",
    "addr:housenumber":"unit 15",
    "addr:postcode":"bd23 1dg",
    "addr:street":"Craven Court High St",
    "iso:country":"GB",
    "sg:address":"Unit 15 Craven Court, High St",
    "sg:city":"Skipton",
    "sg:classifiers":[
        {
            "category":"Shopping",
            "subcategory":"Clothing, Apparel, & Fashions",
            "type":"Retail Goods"
        }
    ],
    "sg:phone":"+44 1756 700319",
    "sg:postcode":"BD23 1DG",
    "sg:province":"Lancashire",
    "sg:tags":[
        "shop",
        "wear",
        "leisure"
    ],
    "wof:name":"Hawkshead",
    "wof:placetype":"venue"
},
  "geometry": {"coordinates":[-2.0163290501,53.9625015259],"type":"Point"}
}