{
  "type": "Feature",
  "properties": {
    "addr:full":"Bell Lane, Byfield Daventry Northamptonshire NN11 6US",
    "addr:postcode":"nn11 6us",
    "addr:street":"Bell Lane",
    "iso:country":"GB",
    "sg:address":"Bell Lane, Byfield",
    "sg:city":"Daventry",
    "sg:classifiers":[
        {
            "category":"Retail",
            "subcategory":"Auto Repair",
            "type":"Services"
        }
    ],
    "sg:postcode":"NN11 6US",
    "sg:province":"Northamptonshire",
    "sg:tags":[
        "modification",
        "garage"
    ],
    "wof:name":"Greenwood Motors Ltd.",
    "wof:placetype":"venue"
},
  "geometry": {"coordinates":[-1.247649,52.173904],"type":"Point"}
}