{
  "type": "Feature",
  "properties": {
    "iso:country":"GB",
    "sg:address":"Unit 3 Maltings Lane, Hadham Cross",
    "sg:city":"Much Hadham",
    "sg:classifiers":[
        {
            "category":"Professional",
            "subcategory":"Engineering",
            "type":"Services"
        }
    ],
    "sg:phone":"+44 1279 842170",
    "sg:postcode":"SG10 6AP",
    "sg:province":"Hertfordshire",
    "sg:tags":[
        "engineer",
        "mechanical"
    ],
    "wof:name":"Aircraft Equipment International",
    "wof:placetype":"venue"
},
  "geometry": {"coordinates":[0.071041,51.847054],"type":"Point"}
}