{
  "type": "Feature",
  "properties": {
    "addr:full":"4 Home Farm Way, Easter Compton Bristol Gloucestershire BS35 5SE",
    "addr:housenumber":"4",
    "addr:postcode":"bs35 5se",
    "addr:street":"Home Farm Way",
    "iso:country":"GB",
    "sg:address":"4 Home Farm Way, Easter Compton",
    "sg:city":"Bristol",
    "sg:classifiers":[
        {
            "category":"Banks & Credit Unions",
            "subcategory":"Financial Services",
            "type":"Services"
        }
    ],
    "sg:phone":"+44 1454 633319",
    "sg:postcode":"BS35 5SE",
    "sg:province":"Gloucestershire",
    "sg:tags":[
        "adviser"
    ],
    "wof:name":"Monarch Financial Advisers Ltd",
    "wof:placetype":"venue"
},
  "geometry": {"coordinates":[-2.614889,51.537609],"type":"Point"}
}