{
  "type": "Feature",
  "properties": {
    "addr:full":"6 Chapel Hill Hayle Cornwall TR27 4JU",
    "addr:housenumber":"6",
    "addr:postcode":"tr27 4ju",
    "addr:street":"Chapel",
    "iso:country":"GB",
    "sg:address":"6 Chapel Hill",
    "sg:city":"Hayle",
    "sg:classifiers":[
        {
            "category":"Place Of Worship",
            "type":"Public Place"
        }
    ],
    "sg:phone":"+44 1736 753325",
    "sg:postcode":"TR27 4JU",
    "sg:province":"Cornwall",
    "wof:name":"Hayle Methodist Church",
    "wof:placetype":"venue"
},
  "geometry": {"coordinates":[-5.4167408943,50.1882781982],"type":"Point"}
}