{
  "type": "Feature",
  "properties": {
    "iso:country":"GB",
    "sg:address":"Crown Industrial Estate, Anglesey Road",
    "sg:city":"Burton-on-trent",
    "sg:classifiers":[
        {
            "category":"Autos & Motor Vehicles",
            "subcategory":"Auto Supplies",
            "type":"Retail Goods"
        }
    ],
    "sg:phone":"+44 1283 561931",
    "sg:postcode":"DE14 3NT",
    "sg:province":"Derbyshire",
    "sg:tags":[
        "tyre"
    ],
    "wof:name":"Hi-Q Tyreservices",
    "wof:placetype":"venue"
},
  "geometry": {"coordinates":[-1.6466039419,52.8000488281],"type":"Point"}
}