{
  "type": "Feature",
  "properties": {
    "addr:full":"89 Beer St Yeovil Somerset BA20 2AD",
    "addr:housenumber":"89",
    "addr:postcode":"ba20 2ad",
    "addr:street":"Beer St",
    "iso:country":"GB",
    "sg:address":"89 Beer St",
    "sg:city":"Yeovil",
    "sg:classifiers":[
        {
            "category":"Food & Beverages",
            "subcategory":"Meat & Fish",
            "type":"Retail Goods"
        }
    ],
    "sg:phone":"+44 1935 474337",
    "sg:postcode":"BA20 2AD",
    "sg:province":"Somerset",
    "sg:tags":[
        "chip"
    ],
    "wof:name":"Corner House Fish Bar",
    "wof:placetype":"venue"
},
  "geometry": {"coordinates":[-2.642184,50.940086],"type":"Point"}
}