{
  "type": "Feature",
  "properties": {
    "addr:full":"65 Carlisle Rd Hove East Sussex BN3 4FQ",
    "addr:housenumber":"65",
    "addr:postcode":"bn3 4fq",
    "addr:street":"Carlisle Rd",
    "iso:country":"GB",
    "sg:address":"65 Carlisle Rd",
    "sg:city":"Hove",
    "sg:classifiers":[
        {
            "category":"Personal",
            "type":"Services"
        }
    ],
    "sg:postcode":"BN3 4FQ",
    "sg:province":"East Sussex",
    "sg:tags":[
        "slimming",
        "product"
    ],
    "wof:name":"Westgate,Carol,",
    "wof:placetype":"venue"
},
  "geometry": {"coordinates":[-0.187539,50.828957],"type":"Point"}
}