{
  "type": "Feature",
  "properties": {
    "iso:country":"GB",
    "sg:address":"Unit 11, Colemeadow Road",
    "sg:city":"Redditch",
    "sg:classifiers":[
        {
            "category":"Manufacturing",
            "subcategory":"Glass & Minerals",
            "type":"Manufacturing & Wholesale Goods"
        }
    ],
    "sg:phone":"+44 1527 69936",
    "sg:postcode":"B98 9PB",
    "sg:province":"Warwickshire",
    "sg:tags":[
        "fibre",
        "material"
    ],
    "wof:name":"R & G Mouldings",
    "wof:placetype":"venue"
},
  "geometry": {"coordinates":[-1.890987,52.31472],"type":"Point"}
}