{
  "type": "Feature",
  "properties": {
    "addr:full":"44 Aylesbury Road Thame Buckinghamshire OX9 3AW",
    "addr:housenumber":"44",
    "addr:postcode":"ox9 3aw",
    "addr:street":"Aylesbury Road",
    "iso:country":"GB",
    "sg:address":"44 Aylesbury Road",
    "sg:city":"Thame",
    "sg:classifiers":[
        {
            "category":"Professional",
            "type":"Services"
        }
    ],
    "sg:postcode":"OX9 3AW",
    "sg:province":"Buckinghamshire",
    "sg:tags":[
        "reflexologists"
    ],
    "wof:name":"Feet First",
    "wof:placetype":"venue"
},
  "geometry": {"coordinates":[-0.9729539752,51.7591514587],"type":"Point"}
}