{
  "type": "Feature",
  "properties": {
    "iso:country":"GB",
    "sg:address":"6a Mews Business Park",
    "sg:city":"Drybrook",
    "sg:classifiers":[
        {
            "category":"Fast Food",
            "type":"Food & Drink"
        },
        {
            "category":"Cafe",
            "type":"Food & Drink"
        }
    ],
    "sg:phone":"+44 1594 544872",
    "sg:postcode":"GL17 9EA",
    "sg:province":"Gloucestershire",
    "sg:tags":[
        "tea",
        "away",
        "room",
        "take"
    ],
    "wof:name":"Wellwisher Cafe",
    "wof:placetype":"venue"
},
  "geometry": {"coordinates":[-2.5157539845,51.8558387756],"type":"Point"}
}