{
  "type": "Feature",
  "properties": {
    "addr:full":"Unit 5 Crombie Road Aberdeen Aberdeen City AB11 9QQ",
    "addr:housenumber":"unit 5",
    "addr:postcode":"ab11 9qq",
    "addr:street":"Crombie Road",
    "iso:country":"GB",
    "sg:address":"Unit 5 Crombie Road",
    "sg:city":"Aberdeen",
    "sg:classifiers":[
        {
            "category":"Government",
            "subcategory":"Fire Station",
            "type":"Public Place"
        }
    ],
    "sg:postcode":"AB11 9QQ",
    "sg:province":"Aberdeen City",
    "sg:tags":[
        "w'sale",
        "lighting"
    ],
    "wof:name":"Trilight",
    "wof:placetype":"venue"
},
  "geometry": {"coordinates":[-2.0819990635,57.137424469],"type":"Point"}
}