{
  "type": "Feature",
  "properties": {
    "addr:full":"14 Moor View, Marldon Paignton Devon TQ3 1PL",
    "addr:housenumber":"14",
    "addr:postcode":"tq3 1pl",
    "addr:street":"Moor View",
    "iso:country":"GB",
    "sg:address":"14 Moor View, Marldon",
    "sg:city":"Paignton",
    "sg:classifiers":[
        {
            "category":"Building & Trades",
            "subcategory":"Construction",
            "type":"Services"
        },
        {
            "category":"Home & Garden",
            "subcategory":"Carpets & Floor Coverings",
            "type":"Retail Goods"
        }
    ],
    "sg:postcode":"TQ3 1PL",
    "sg:province":"Devon",
    "sg:tags":[
        "carpets",
        "tiling",
        "rug",
        "matting",
        "contractor"
    ],
    "wof:name":"J B Burton",
    "wof:placetype":"venue"
},
  "geometry": {"coordinates":[-3.593077,50.454876],"type":"Point"}
}