{
  "type": "Feature",
  "properties": {
    "addr:full":"165 James Street Glasgow Glasgow City G40 1BS",
    "addr:housenumber":"165",
    "addr:postcode":"g40 1bs",
    "addr:street":"James Street",
    "iso:country":"GB",
    "sg:address":"165 James Street",
    "sg:city":"Glasgow",
    "sg:classifiers":[
        {
            "category":"Personal",
            "subcategory":"Beauty Salon",
            "type":"Services"
        },
        {
            "category":"Personal",
            "subcategory":"Barber",
            "type":"Services"
        }
    ],
    "sg:phone":"+44 141 556 1044",
    "sg:postcode":"G40 1BS",
    "sg:province":"Glasgow City",
    "sg:tags":[
        "unisex",
        "hairdresser"
    ],
    "wof:name":"Amanda's",
    "wof:placetype":"venue"
},
  "geometry": {"coordinates":[-4.2279171944,55.8486022949],"type":"Point"}
}