{
  "type": "Feature",
  "properties": {
    "addr:full":"The New Vicarage, 7 High St Northampton Northamptonshire NN6 0JG",
    "addr:housenumber":"7",
    "addr:postcode":"nn6 0jg",
    "addr:street":"High St",
    "iso:country":"GB",
    "sg:address":"The New Vicarage, 7 High St",
    "sg:city":"Northampton",
    "sg:classifiers":[
        {
            "category":"Place Of Worship",
            "type":"Public Place"
        },
        {
            "category":"Organizations",
            "subcategory":"Non-profit Organization",
            "type":"Services"
        }
    ],
    "sg:phone":"+44 1604 810447",
    "sg:postcode":"NN6 0JG",
    "sg:province":"Northamptonshire",
    "sg:tags":[
        "charitable",
        "organisation",
        "charity"
    ],
    "wof:name":"ALL SAINTS C OF E CHURCH",
    "wof:placetype":"venue"
},
  "geometry": {"coordinates":[-0.752390027,52.2653388977],"type":"Point"}
}