{
  "type": "Feature",
  "properties": {
    "iso:country":"GB",
    "sg:address":"Camberley Health Centre, 159 Frimley Rd",
    "sg:city":"Camberley",
    "sg:classifiers":[
        {
            "category":"Health Services",
            "subcategory":"Doctor",
            "type":"Services"
        }
    ],
    "sg:phone":"+44 1276 20101",
    "sg:postcode":"GU15 2PZ",
    "sg:province":"Berkshire",
    "sg:tags":[
        "practitioners"
    ],
    "wof:name":"Sarah E Barker",
    "wof:placetype":"venue"
},
  "geometry": {"coordinates":[-0.7342299819,51.3362159729],"type":"Point"}
}