{
  "type": "Feature",
  "properties": {
    "iso:country":"GB",
    "sg:address":"3 Coalway Rd",
    "sg:city":"Wolverhampton",
    "sg:classifiers":[
        {
            "category":"Shopping",
            "subcategory":"Florist",
            "type":"Retail Goods"
        }
    ],
    "sg:phone":"+44 1902 337789",
    "sg:postcode":"WV3 7LR",
    "sg:province":"Staffordshire",
    "wof:name":"Jillie Flowers",
    "wof:placetype":"venue"
},
  "geometry": {"coordinates":[-2.144265,52.568581],"type":"Point"}
}