{
  "type": "Feature",
  "properties": {
    "addr:full":"19 Westwood Close Cowes Isle of Wight PO31 7NS",
    "addr:housenumber":"19",
    "addr:postcode":"po31 7ns",
    "addr:street":"Westwood Close",
    "iso:country":"GB",
    "sg:address":"19 Westwood Close",
    "sg:city":"Cowes",
    "sg:classifiers":[
        {
            "category":"Professional",
            "type":"Services"
        }
    ],
    "sg:postcode":"PO31 7NS",
    "sg:province":"Isle of Wight",
    "sg:tags":[
        "reflexologists"
    ],
    "wof:name":"Sarah Croutear",
    "wof:placetype":"venue"
},
  "geometry": {"coordinates":[-1.310737,50.759048],"type":"Point"}
}