{
  "type": "Feature",
  "properties": {
    "addr:full":"2 Beaufort Court, Somerset Road Barnet Hertfordshire EN5 1RW",
    "addr:housenumber":"2",
    "addr:postcode":"en5 1rw",
    "addr:street":"Beaufort Court Somerset Road",
    "iso:country":"GB",
    "sg:address":"2 Beaufort Court, Somerset Road",
    "sg:city":"Barnet",
    "sg:classifiers":[
        {
            "category":"Professional",
            "subcategory":"Management & Consulting",
            "type":"Services"
        }
    ],
    "sg:postcode":"EN5 1RW",
    "sg:province":"Hertfordshire",
    "sg:tags":[
        "consultant",
        "business"
    ],
    "wof:name":"R P A Management Consultants",
    "wof:placetype":"venue"
},
  "geometry": {"coordinates":[-0.182829,51.647968],"type":"Point"}
}