{
  "type": "Feature",
  "properties": {
    "iso:country":"GB",
    "sg:address":"25 Abbotts Drive",
    "sg:city":"Stoke-on-trent",
    "sg:classifiers":[
        {
            "category":"Food & Beverages",
            "subcategory":"Liquor & Beverages",
            "type":"Retail Goods"
        }
    ],
    "sg:phone":"+44 1782 267089",
    "sg:postcode":"ST1 6HX",
    "sg:province":"Staffordshire",
    "sg:tags":[
        "beer",
        "spirit",
        "wines"
    ],
    "wof:name":"Bargain Booze",
    "wof:placetype":"venue"
},
  "geometry": {"coordinates":[-2.1637248993,53.0439682007],"type":"Point"}
}