{
  "type": "Feature",
  "properties": {
    "iso:country":"GB",
    "sg:address":"90 Sunbridge Road",
    "sg:city":"Bradford",
    "sg:classifiers":[
        {
            "category":"Organizations",
            "subcategory":"Membership Organization",
            "type":"Services"
        }
    ],
    "sg:phone":"+44 1274 723608",
    "sg:postcode":"BD1 2AQ",
    "sg:province":"West Yorkshire",
    "sg:tags":[
        "club"
    ],
    "wof:name":"Yorkshire Rider Club",
    "wof:placetype":"venue"
},
  "geometry": {"coordinates":[-1.7567440271,53.7940673828],"type":"Point"}
}