{
  "type": "Feature",
  "properties": {
    "iso:country":"GB",
    "sg:address":"46 Park Road, Sandhurst",
    "sg:city":"Camberley",
    "sg:classifiers":[
        {
            "category":"Building & Trades",
            "subcategory":"Construction",
            "type":"Services"
        }
    ],
    "sg:postcode":"GU47 9AA",
    "sg:province":"Berkshire",
    "sg:tags":[
        "decorator",
        "painter"
    ],
    "wof:name":"B P Jones & Son",
    "wof:placetype":"venue"
},
  "geometry": {"coordinates":[-0.792871,51.347504],"type":"Point"}
}