{
  "type": "Feature",
  "properties": {
    "addr:full":"11 George Street Lancaster Lancashire LA1 1XQ",
    "addr:housenumber":"11",
    "addr:postcode":"la1 1xq",
    "addr:street":"George Street",
    "iso:country":"GB",
    "sg:address":"11 George Street",
    "sg:city":"Lancaster",
    "sg:classifiers":[
        {
            "category":"Restaurant",
            "type":"Food & Drink"
        }
    ],
    "sg:phone":"+44 1524 33100",
    "sg:postcode":"LA1 1XQ",
    "sg:province":"Lancashire",
    "sg:tags":[
        "-",
        "chinese"
    ],
    "wof:name":"Golden Dragon",
    "wof:placetype":"venue"
},
  "geometry": {"coordinates":[-2.799555,54.046944],"type":"Point"}
}