{
  "type": "Feature",
  "properties": {
    "addr:full":"The White House, Clifton Marine Pde Gravesend Kent DA11 0DY",
    "addr:postcode":"da11 0dy",
    "addr:street":"Clifton",
    "iso:country":"GB",
    "sg:address":"The White House, Clifton Marine Pde",
    "sg:city":"Gravesend",
    "sg:classifiers":[
        {
            "category":"Building & Trades",
            "subcategory":"Construction",
            "type":"Services"
        }
    ],
    "sg:phone":"+44 1474 361647",
    "sg:postcode":"DA11 0DY",
    "sg:province":"Kent",
    "sg:tags":[
        "builder"
    ],
    "wof:name":"Scorpio",
    "wof:placetype":"venue"
},
  "geometry": {"coordinates":[0.361739,51.445271],"type":"Point"}
}