{
  "type": "Feature",
  "properties": {
    "iso:country":"GB",
    "sg:address":"15 Dickens Walk",
    "sg:city":"Newbury",
    "sg:classifiers":[
        {
            "category":"Manufacturing",
            "subcategory":"Petroleum Products",
            "type":"Manufacturing & Wholesale Goods"
        },
        {
            "category":"Building & Trades",
            "subcategory":"Construction",
            "type":"Services"
        }
    ],
    "sg:phone":"+44 1635 33817",
    "sg:postcode":"RG14 7UQ",
    "sg:province":"Berkshire",
    "sg:tags":[
        "double",
        "glazing",
        "installers"
    ],
    "wof:name":"A C S WINDOWS",
    "wof:placetype":"venue"
},
  "geometry": {"coordinates":[-1.3258719444,51.405872345],"type":"Point"}
}