{
  "type": "Feature",
  "properties": {
    "iso:country":"GB",
    "sg:address":"62-64 Woodsend Road, Urmston",
    "sg:city":"Manchester",
    "sg:classifiers":[
        {
            "category":"Retail",
            "subcategory":"Auto Repair",
            "type":"Services"
        }
    ],
    "sg:phone":"+44 161 748 7677",
    "sg:postcode":"M41 8GX",
    "sg:province":"Cheshire",
    "sg:tags":[
        "modification",
        "garage"
    ],
    "wof:name":"J C Motors",
    "wof:placetype":"venue"
},
  "geometry": {"coordinates":[-2.3917191029,53.4498214722],"type":"Point"}
}