{
  "type": "Feature",
  "properties": {
    "iso:country":"GB",
    "sg:address":"26 Shepherds Close, Hurley",
    "sg:city":"Maidenhead",
    "sg:classifiers":[
        {
            "category":"Health Services",
            "subcategory":"Doctor",
            "type":"Services"
        }
    ],
    "sg:phone":"+44 1628 824447",
    "sg:postcode":"SL6 5LY",
    "sg:province":"Berkshire",
    "sg:tags":[
        "practitioners"
    ],
    "wof:name":"DRS HAYTER MOSTON & PARTNERS",
    "wof:placetype":"venue"
},
  "geometry": {"coordinates":[-0.8103430271,51.5425071716],"type":"Point"}
}