{
  "type": "Feature",
  "properties": {
    "iso:country":"GB",
    "sg:address":"2 Stanley Rd",
    "sg:city":"Bradford",
    "sg:classifiers":[
        {
            "category":"Professional",
            "subcategory":"Engineering",
            "type":"Services"
        }
    ],
    "sg:phone":"+44 1274 391140",
    "sg:postcode":"BD2 1AS",
    "sg:province":"West Yorkshire",
    "sg:tags":[
        "civil",
        "engineer"
    ],
    "wof:name":"Martin,P K,Ltd",
    "wof:placetype":"venue"
},
  "geometry": {"coordinates":[-1.7625089884,53.8176689148],"type":"Point"}
}