{
  "type": "Feature",
  "properties": {
    "addr:full":"High Street Henlow Bedfordshire SG16 6AB",
    "addr:postcode":"sg16 6ab",
    "addr:street":"High Street",
    "iso:country":"GB",
    "sg:address":"High Street",
    "sg:city":"Henlow",
    "sg:classifiers":[
        {
            "category":"Social Services",
            "subcategory":"Retirement Home",
            "type":"Services"
        }
    ],
    "sg:phone":"+44 1462 811028",
    "sg:postcode":"SG16 6AB",
    "sg:province":"Bedfordshire",
    "sg:tags":[
        "residential",
        "care"
    ],
    "wof:name":"Limes Residential Home",
    "wof:placetype":"venue"
},
  "geometry": {"coordinates":[-0.285639,52.037251],"type":"Point"}
}