{
  "type": "Feature",
  "properties": {
    "addr:full":"North Road Indstl Est Berwick-upon-tweed Northumberland TD15 1UN",
    "addr:postcode":"td15 1un",
    "addr:street":"North Road Indstl Est;Northumberland",
    "iso:country":"GB",
    "sg:address":"North Road Indstl Est",
    "sg:city":"Berwick-upon-tweed",
    "sg:classifiers":[
        {
            "category":"Home & Garden",
            "subcategory":"Hardware",
            "type":"Retail Goods"
        }
    ],
    "sg:phone":"+44 1289 308444",
    "sg:postcode":"TD15 1UN",
    "sg:province":"Northumberland",
    "sg:tags":[
        "lawnmowers",
        "machinery"
    ],
    "wof:name":"Davidsons Garden Machinery",
    "wof:placetype":"venue"
},
  "geometry": {"coordinates":[-2.011494,55.781616],"type":"Point"}
}