{
  "type": "Feature",
  "properties": {
    "iso:country":"GB",
    "sg:address":"66 Rossendale Crescent",
    "sg:city":"Bacup",
    "sg:classifiers":[
        {
            "category":"Building & Trades",
            "subcategory":"Construction",
            "type":"Services"
        }
    ],
    "sg:phone":"+44 70 5029 3989",
    "sg:postcode":"OL13 9LN",
    "sg:province":"Lancashire",
    "sg:tags":[
        "decorator",
        "painter"
    ],
    "wof:name":"Anthony White",
    "wof:placetype":"venue"
},
  "geometry": {"coordinates":[-2.190469,53.704369],"type":"Point"}
}