{
  "type": "Feature",
  "properties": {
    "addr:full":"The Poplars, Normans Place Altrincham Cheshire WA14 2AB",
    "addr:postcode":"wa14 2ab",
    "addr:street":"Normans Place Altrincham",
    "iso:country":"GB",
    "sg:address":"The Poplars, Normans Place",
    "sg:city":"Altrincham",
    "sg:classifiers":[
        {
            "category":"Organizations",
            "subcategory":"Community Association",
            "type":"Services"
        }
    ],
    "sg:phone":"+44 161 928 6800",
    "sg:postcode":"WA14 2AB",
    "sg:province":"Cheshire",
    "sg:tags":[
        "society",
        "housing"
    ],
    "wof:name":"Anchor Trust",
    "wof:placetype":"venue"
},
  "geometry": {"coordinates":[-2.349209,53.386726],"type":"Point"}
}