{
  "type": "Feature",
  "properties": {
    "addr:full":"Upton Farm Cullompton Devon EX15 1RA",
    "addr:housenumber":"cullompton",
    "addr:postcode":"ex15 1ra",
    "addr:street":"Devon",
    "iso:country":"GB",
    "sg:address":"Upton Farm",
    "sg:city":"Cullompton",
    "sg:classifiers":[
        {
            "category":"Recreation",
            "subcategory":"Fishing",
            "type":"Entertainment"
        },
        {
            "category":"Farming",
            "subcategory":"Dairy Farm",
            "type":"Manufacturing & Wholesale Goods"
        },
        {
            "category":"Farming",
            "subcategory":"Livestock Farm",
            "type":"Manufacturing & Wholesale Goods"
        },
        {
            "category":"Train Station",
            "subcategory":"Rail",
            "type":"Transportation"
        }
    ],
    "sg:phone":"+44 7830 199690",
    "sg:postcode":"EX15 1RA",
    "sg:province":"Devon",
    "sg:tags":[
        "angling",
        "others"
    ],
    "wof:name":"Upton Lake",
    "wof:placetype":"venue"
},
  "geometry": {"coordinates":[-3.3926339149,50.858165741],"type":"Point"}
}