{
  "type": "Feature",
  "properties": {
    "addr:full":"25/27 Naylor Street Liverpool Merseyside L3 6DR",
    "addr:housenumber":"25 / 27",
    "addr:postcode":"l3 6dr",
    "addr:street":"Naylor Street",
    "iso:country":"GB",
    "sg:address":"25/27 Naylor Street",
    "sg:city":"Liverpool",
    "sg:classifiers":[
        {
            "category":"Building & Trades",
            "subcategory":"Construction",
            "type":"Services"
        }
    ],
    "sg:phone":"+44 151 236 2181",
    "sg:postcode":"L3 6DR",
    "sg:province":"Merseyside",
    "sg:tags":[
        "demolition",
        "contractor"
    ],
    "wof:name":"J G McVey & Co. Ltd.",
    "wof:placetype":"venue"
},
  "geometry": {"coordinates":[-2.98684,53.41412],"type":"Point"}
}