{
  "type": "Feature",
  "properties": {
    "addr:full":"John Montagu Building, Beaulieu Brockenhurst Hampshire SO42 7ZN",
    "addr:postcode":"so42 7zn",
    "addr:street":"Hampshire",
    "iso:country":"GB",
    "sg:address":"John Montagu Building, Beaulieu",
    "sg:city":"Brockenhurst",
    "sg:classifiers":[
        {
            "category":"Retail",
            "subcategory":"Event Space",
            "type":"Services"
        },
        {
            "category":"Landmark",
            "subcategory":"Tourist Attraction",
            "type":"Public Place"
        }
    ],
    "sg:phone":"+44 1590 612345",
    "sg:postcode":"SO42 7ZN",
    "sg:province":"Hampshire",
    "sg:tags":[
        "banqueting",
        "room",
        "interest"
    ],
    "wof:name":"Beaulieu Enterprises Ltd.",
    "wof:placetype":"venue"
},
  "geometry": {"coordinates":[-1.5720039606,50.8186416626],"type":"Point"}
}