{
  "type": "Feature",
  "properties": {
    "iso:country":"GB",
    "sg:address":"20 Holcombe Village",
    "sg:city":"Bury",
    "sg:classifiers":[
        {
            "category":"Fast Food",
            "type":"Food & Drink"
        }
    ],
    "sg:phone":"+44 1706 825702",
    "sg:postcode":"BL8 4LZ",
    "sg:province":"Lancashire",
    "sg:tags":[
        "away",
        "take"
    ],
    "wof:name":"Andertons Restaurant",
    "wof:placetype":"venue"
},
  "geometry": {"coordinates":[-2.342189,53.61879],"type":"Point"}
}