{
  "type": "Feature",
  "properties": {
    "iso:country":"GB",
    "sg:address":"19 Duke St",
    "sg:city":"Reading",
    "sg:classifiers":[
        {
            "category":"Restaurant",
            "type":"Food & Drink"
        }
    ],
    "sg:postcode":"RG1 4SA",
    "sg:province":"Berkshire",
    "wof:name":"Hawaiian Wine Bar",
    "wof:placetype":"venue"
},
  "geometry": {"coordinates":[-0.968506,51.454308],"type":"Point"}
}