{
  "type": "Feature",
  "properties": {
    "iso:country":"GB",
    "sg:address":"12 Broadwood Road, Chattenden",
    "sg:city":"Rochester",
    "sg:classifiers":[
        {
            "category":"Real Estate",
            "subcategory":"Architect",
            "type":"Services"
        }
    ],
    "sg:postcode":"ME3 8LU",
    "sg:province":"Kent",
    "wof:name":"C P L ELECTRICAL ENGINEERING",
    "wof:placetype":"venue"
},
  "geometry": {"coordinates":[0.529614,51.417809],"type":"Point"}
}