{
  "type": "Feature",
  "properties": {
    "iso:country":"GB",
    "sg:address":"1 Claremont Mews",
    "sg:city":"Aberdeen",
    "sg:classifiers":[
        {
            "category":"Building & Trades",
            "subcategory":"Construction",
            "type":"Services"
        }
    ],
    "sg:phone":"+44 1224 580487",
    "sg:postcode":"AB1 6QR",
    "sg:province":"Aberdeen City",
    "sg:tags":[
        "builder"
    ],
    "wof:name":"John A B Beattie",
    "wof:placetype":"venue"
},
  "geometry": {"coordinates":[-2.121786,57.138672],"type":"Point"}
}