{
  "type": "Feature",
  "properties": {
    "addr:full":"Cavendish Street Barrow-in-furness Cumbria LA14 1QD",
    "addr:postcode":"la14 1qd",
    "addr:street":"Cavendish Street",
    "iso:country":"GB",
    "sg:address":"Cavendish Street",
    "sg:city":"Barrow-in-furness",
    "sg:classifiers":[
        {
            "category":"Travel",
            "subcategory":"Hotels & Motels",
            "type":"Entertainment"
        }
    ],
    "sg:phone":"+44 1229 825272",
    "sg:postcode":"LA14 1QD",
    "sg:province":"Cumbria",
    "wof:name":"Theatre Hotel",
    "wof:placetype":"venue"
},
  "geometry": {"coordinates":[-3.2239439487,54.1147384644],"type":"Point"}
}