{
  "type": "Feature",
  "properties": {
    "iso:country":"GB",
    "sg:address":"67-69 Scarborough Road, Norton",
    "sg:city":"Malton",
    "sg:classifiers":[
        {
            "category":"Shopping",
            "subcategory":"Department Store",
            "type":"Retail Goods"
        },
        {
            "category":"Professional",
            "type":"Services"
        }
    ],
    "sg:phone":"+44 1653 697333",
    "sg:postcode":"YO17 8AA",
    "sg:province":"North Yorkshire",
    "sg:tags":[
        "shop",
        "fitting",
        "shopfitters",
        "manufacturer"
    ],
    "wof:name":"Rohan Woodworking Ltd",
    "wof:placetype":"venue"
},
  "geometry": {"coordinates":[-0.7783849835,54.1350288391],"type":"Point"}
}