{
  "type": "Feature",
  "properties": {
    "addr:full":"526 High Road Benfleet Essex SS7 5RE",
    "addr:housenumber":"526",
    "addr:postcode":"ss7 5re",
    "addr:street":"High Road",
    "iso:country":"GB",
    "sg:address":"526 High Road",
    "sg:city":"Benfleet",
    "sg:classifiers":[
        {
            "category":"Health Services",
            "subcategory":"Dentist",
            "type":"Services"
        }
    ],
    "sg:phone":"+44 1268 792746",
    "sg:postcode":"SS7 5RE",
    "sg:province":"Essex",
    "wof:name":"Papineni S B.D.S",
    "wof:placetype":"venue"
},
  "geometry": {"coordinates":[0.550755024,51.5609550476],"type":"Point"}
}