{
  "type": "Feature",
  "properties": {
    "addr:full":"40 George Moore Close Oxford Oxfordshire OX4 4DA",
    "addr:housenumber":"40",
    "addr:postcode":"ox4 4da",
    "addr:street":"George Moore Close",
    "iso:country":"GB",
    "sg:address":"40 George Moore Close",
    "sg:city":"Oxford",
    "sg:classifiers":[
        {
            "category":"Professional",
            "subcategory":"Detective & Security Services",
            "type":"Services"
        }
    ],
    "sg:phone":"+44 1865 246720",
    "sg:postcode":"OX4 4DA",
    "sg:province":"Oxfordshire",
    "wof:name":"Nightguard Security",
    "wof:placetype":"venue"
},
  "geometry": {"coordinates":[-1.232763052,51.7375564575],"type":"Point"}
}