{
  "type": "Feature",
  "properties": {
    "iso:country":"GB",
    "sg:address":"Church Meadow, Bath Road",
    "sg:city":"Hounslow",
    "sg:classifiers":[
        {
            "category":"Arena",
            "subcategory":"Sports Club",
            "type":"Entertainment"
        }
    ],
    "sg:phone":"+44 20 8570 1762",
    "sg:postcode":"TW3 3DA",
    "sg:province":"Greater London",
    "wof:name":"Hounslow Cricket & Sports Club",
    "wof:placetype":"venue"
},
  "geometry": {"coordinates":[-0.381474,51.471432],"type":"Point"}
}