{
  "type": "Feature",
  "properties": {
    "iso:country":"GB",
    "sg:address":"Ivy Ho, Gateford Rd, Gateford",
    "sg:city":"Worksop",
    "sg:classifiers":[
        {
            "category":"Insurance",
            "subcategory":"Insurance Agent",
            "type":"Services"
        }
    ],
    "sg:postcode":"S81 8AE",
    "sg:province":"Nottinghamshire",
    "sg:tags":[
        "broker"
    ],
    "wof:name":"Thirkell,Rob,",
    "wof:placetype":"venue"
},
  "geometry": {"coordinates":[-1.1382930279,53.327091217],"type":"Point"}
}