{
  "type": "Feature",
  "properties": {
    "iso:country":"GB",
    "sg:address":"69 West Street",
    "sg:city":"Penryn",
    "sg:classifiers":[
        {
            "category":"Professional",
            "subcategory":"Engineering",
            "type":"Services"
        }
    ],
    "sg:phone":"+44 1326 373935",
    "sg:postcode":"TR10 8ET",
    "sg:province":"Cornwall",
    "sg:tags":[
        "civil",
        "engineer"
    ],
    "wof:name":"E J Shelton & Associates",
    "wof:placetype":"venue"
},
  "geometry": {"coordinates":[-5.107409,50.169376],"type":"Point"}
}