{
  "type": "Feature",
  "properties": {
    "iso:country":"GB",
    "sg:address":"10 Wood St",
    "sg:city":"Calne",
    "sg:classifiers":[
        {
            "category":"Professional",
            "subcategory":"Art Services",
            "type":"Services"
        }
    ],
    "sg:phone":"+44 1249 816405",
    "sg:postcode":"SN11 0DA",
    "sg:province":"Wiltshire",
    "sg:tags":[
        "photographer"
    ],
    "wof:name":"Photoshop",
    "wof:placetype":"venue"
},
  "geometry": {"coordinates":[-2.005439,51.439827],"type":"Point"}
}