{
  "type": "Feature",
  "properties": {
    "iso:country":"GB",
    "sg:address":"Wishes Come True,1 Merlin Pl, Mousehole",
    "sg:city":"Penzance",
    "sg:classifiers":[
        {
            "category":"Professional",
            "subcategory":"Management & Consulting",
            "type":"Services"
        }
    ],
    "sg:postcode":"TR19 6SH",
    "sg:province":"Cornwall",
    "sg:tags":[
        "consultant",
        "safety"
    ],
    "wof:name":"Waters,M J,",
    "wof:placetype":"venue"
},
  "geometry": {"coordinates":[-5.539893,50.082569],"type":"Point"}
}