{
  "type": "Feature",
  "properties": {
    "addr:full":"5b Rough Hey Place, Grimsargh Preston Lancashire PR2 5AR",
    "addr:housenumber":"5b",
    "addr:postcode":"pr2 5ar",
    "addr:street":"Rough Hey Place",
    "iso:country":"GB",
    "sg:address":"5b Rough Hey Place, Grimsargh",
    "sg:city":"Preston",
    "sg:classifiers":[
        {
            "category":"Home & Garden",
            "subcategory":"Building Materials",
            "type":"Retail Goods"
        }
    ],
    "sg:phone":"+44 1772 704244",
    "sg:postcode":"PR2 5AR",
    "sg:province":"Lancashire",
    "sg:tags":[
        "ready",
        "mixed",
        "concrete"
    ],
    "wof:name":"Spotmix Preston",
    "wof:placetype":"venue"
},
  "geometry": {"coordinates":[-2.641661,53.793224],"type":"Point"}
}