{
  "type": "Feature",
  "properties": {
    "iso:country":"GB",
    "sg:address":"Calder Court, Calder Farm, Fands Lane",
    "sg:city":"Mirfield",
    "sg:classifiers":[
        {
            "category":"Sports & Exercise",
            "subcategory":"Stables",
            "type":"Entertainment"
        }
    ],
    "sg:postcode":"WF14 8HJ",
    "sg:province":"West Yorkshire",
    "sg:tags":[
        "education",
        "equestrian"
    ],
    "wof:name":"A & W Chappelow",
    "wof:placetype":"venue"
},
  "geometry": {"coordinates":[-1.6981569529,53.6719055176],"type":"Point"}
}