{
  "type": "Feature",
  "properties": {
    "iso:country":"GB",
    "sg:address":"137 Wyngate Drive",
    "sg:city":"Leicester",
    "sg:classifiers":[
        {
            "category":"Shopping",
            "subcategory":"News",
            "type":"Retail Goods"
        },
        {
            "category":"Food & Beverages",
            "subcategory":"Supermarket",
            "type":"Retail Goods"
        }
    ],
    "sg:phone":"+44 116 255 7560",
    "sg:postcode":"LE3 0UW",
    "sg:province":"Leicestershire",
    "sg:tags":[
        "newsagent"
    ],
    "wof:name":"Wyngate Supermarket",
    "wof:placetype":"venue"
},
  "geometry": {"coordinates":[-1.162144,52.628582],"type":"Point"}
}