{
  "type": "Feature",
  "properties": {
    "addr:full":"Fox Talbot House Ware Hertfordshire SG12 9HN",
    "addr:postcode":"sg12 9hn",
    "iso:country":"GB",
    "sg:address":"Fox Talbot House",
    "sg:city":"Ware",
    "sg:classifiers":[
        {
            "category":"Professional",
            "subcategory":"Art Services",
            "type":"Services"
        },
        {
            "category":"Communications",
            "type":"Services"
        }
    ],
    "sg:phone":"+44 1920 464011",
    "sg:postcode":"SG12 9HN",
    "sg:province":"Hertfordshire",
    "sg:tags":[
        "photographer",
        "audio-visual"
    ],
    "wof:name":"The Audio Visual Association",
    "wof:placetype":"venue"
},
  "geometry": {"coordinates":[-0.0178089999,51.7940216064],"type":"Point"}
}