{
  "type": "Feature",
  "properties": {
    "addr:full":"22 Eastgate Leeds West Yorkshire LS2 7JL",
    "addr:housenumber":"22",
    "addr:postcode":"ls2 7jl",
    "addr:street":"Eastgate Leeds West",
    "iso:country":"GB",
    "sg:address":"22 Eastgate",
    "sg:city":"Leeds",
    "sg:classifiers":[
        {
            "category":"Shopping",
            "subcategory":"Discount & Variety Stores",
            "type":"Retail Goods"
        }
    ],
    "sg:phone":"+44 113 245 5739",
    "sg:postcode":"LS2 7JL",
    "sg:province":"West Yorkshire",
    "sg:tags":[
        "shop",
        "model"
    ],
    "wof:name":"Britannia Hobbies",
    "wof:placetype":"venue"
},
  "geometry": {"coordinates":[-1.538006,53.798588],"type":"Point"}
}