{
  "type": "Feature",
  "properties": {
    "iso:country":"GB",
    "sg:address":"5 Kildermorie Path, Easterhouse",
    "sg:city":"Glasgow",
    "sg:classifiers":[
        {
            "category":"Organizations",
            "subcategory":"Non-profit Organization",
            "type":"Services"
        }
    ],
    "sg:phone":"+44 141 773 3533",
    "sg:postcode":"G34 9EJ",
    "sg:province":"Glasgow City",
    "sg:tags":[
        "organisation",
        "voluntary",
        "charity"
    ],
    "wof:name":"Greater Easterhouse Womens Aid",
    "wof:placetype":"venue"
},
  "geometry": {"coordinates":[-4.120324,55.865776],"type":"Point"}
}