{
  "type": "Feature",
  "properties": {
    "iso:country":"GB",
    "sg:address":"32a Market Parade",
    "sg:city":"Havant",
    "sg:classifiers":[
        {
            "category":"Professional",
            "subcategory":"Employment Agencies",
            "type":"Services"
        }
    ],
    "sg:phone":"+44 23 9249 2278",
    "sg:postcode":"PO9 1QF",
    "sg:province":"Hampshire",
    "sg:tags":[
        "consultant"
    ],
    "wof:name":"Manpower Technical",
    "wof:placetype":"venue"
},
  "geometry": {"coordinates":[-0.981829,50.853516],"type":"Point"}
}