{
  "type": "Feature",
  "properties": {
    "iso:country":"GB",
    "sg:address":"Avery Hill Road",
    "sg:city":"London",
    "sg:classifiers":[
        {
            "category":"Autos & Motor Vehicles",
            "subcategory":"Fuel & Gas Station",
            "type":"Retail Goods"
        }
    ],
    "sg:phone":"+44 20 8859 7119",
    "sg:postcode":"SE9 2BD",
    "sg:province":"Greater London",
    "sg:tags":[
        "petrol",
        "filling"
    ],
    "wof:name":"B P Avery Hill Filling Station",
    "wof:placetype":"venue"
},
  "geometry": {"coordinates":[0.0736500025,51.4383392334],"type":"Point"}
}