{
  "type": "Feature",
  "properties": {
    "iso:country":"GB",
    "sg:address":"Shady Lane",
    "sg:city":"Southwell",
    "sg:classifiers":[
        {
            "category":"Building & Trades",
            "subcategory":"Landscaping Services",
            "type":"Services"
        }
    ],
    "sg:phone":"+44 1636 812003",
    "sg:postcode":"NG25 0HX",
    "sg:province":"Nottinghamshire",
    "sg:tags":[
        "landscape",
        "contractor"
    ],
    "wof:name":"Agricultural Crop Sprayers (Nottingham) Ltd.",
    "wof:placetype":"venue"
},
  "geometry": {"coordinates":[-0.947554,53.076382],"type":"Point"}
}