{
  "type": "Feature",
  "properties": {
    "addr:full":"59 Salterton Road Exmouth Devon EX8 2EQ",
    "addr:postcode":"ex8 2eq",
    "addr:street":"Salterton Road",
    "iso:country":"GB",
    "sg:address":"59 Salterton Road",
    "sg:city":"Exmouth",
    "sg:classifiers":[
        {
            "category":"Travel",
            "subcategory":"Hotels & Motels",
            "type":"Entertainment"
        }
    ],
    "sg:postcode":"EX8 2EQ",
    "sg:province":"Devon",
    "sg:tags":[
        "house",
        "guest"
    ],
    "wof:name":"Sandrevin",
    "wof:placetype":"venue"
},
  "geometry": {"coordinates":[-3.3998889923,50.6200408936],"type":"Point"}
}