{
  "type": "Feature",
  "properties": {
    "addr:full":"15 Winchester Road Basingstoke Hampshire RG21 8UE",
    "addr:housenumber":"15",
    "addr:postcode":"rg21 8ue",
    "addr:street":"Winchester Road",
    "iso:country":"GB",
    "sg:address":"15 Winchester Road",
    "sg:city":"Basingstoke",
    "sg:classifiers":[
        {
            "category":"Real Estate",
            "subcategory":"Real Estate Agent",
            "type":"Services"
        }
    ],
    "sg:phone":"+44 1256 462222",
    "sg:postcode":"RG21 8UE",
    "sg:province":"Hampshire",
    "wof:name":"London Clancy Ltd.",
    "wof:placetype":"venue"
},
  "geometry": {"coordinates":[-1.091285,51.261932],"type":"Point"}
}