{
  "type": "Feature",
  "properties": {
    "addr:full":"Riverside Caravan Centre, Shripney Rd Bognor Regis West Sussex PO22 9NJ",
    "addr:postcode":"po22 9nj",
    "addr:street":"Shripney Rd",
    "iso:country":"GB",
    "sg:address":"Riverside Caravan Centre, Shripney Rd",
    "sg:city":"Bognor Regis",
    "sg:classifiers":[
        {
            "category":"Building & Trades",
            "subcategory":"Equipment Rental",
            "type":"Services"
        }
    ],
    "sg:phone":"+44 1243 868043",
    "sg:postcode":"PO22 9NJ",
    "sg:province":"West Sussex",
    "sg:tags":[
        "hire",
        "centre"
    ],
    "wof:name":"Hire Shop The",
    "wof:placetype":"venue"
},
  "geometry": {"coordinates":[-0.669748,50.812191],"type":"Point"}
}