{
  "type": "Feature",
  "properties": {
    "iso:country":"GB",
    "sg:address":"143 Queensway, Bletchley",
    "sg:city":"Milton Keynes",
    "sg:classifiers":[
        {
            "category":"Shopping",
            "subcategory":"Thrift Store",
            "type":"Retail Goods"
        }
    ],
    "sg:phone":"+44 1908 644788",
    "sg:postcode":"MK2 2DY",
    "sg:province":"Buckinghamshire",
    "sg:tags":[
        "shop",
        "charity"
    ],
    "wof:name":"C C H A Extra Care",
    "wof:placetype":"venue"
},
  "geometry": {"coordinates":[-0.727894,51.995239],"type":"Point"}
}