{
  "type": "Feature",
  "properties": {
    "addr:full":"2 Piccadilly Nottingham Nottinghamshire NG6 9FN",
    "addr:housenumber":"2",
    "addr:postcode":"ng6 9fn",
    "addr:street":"Piccadilly",
    "iso:country":"GB",
    "sg:address":"2 Piccadilly",
    "sg:city":"Nottingham",
    "sg:classifiers":[
        {
            "category":"Personal",
            "subcategory":"Beauty Salon",
            "type":"Services"
        }
    ],
    "sg:phone":"+44 115 975 5808",
    "sg:postcode":"NG6 9FN",
    "sg:province":"Nottinghamshire",
    "sg:tags":[
        "unisex",
        "hairdresser"
    ],
    "wof:name":"Hair by Pauline",
    "wof:placetype":"venue"
},
  "geometry": {"coordinates":[-1.1851789951,52.9967384338],"type":"Point"}
}