{
  "type": "Feature",
  "properties": {
    "iso:country":"GB",
    "sg:address":"19 Wellington Street",
    "sg:city":"Ripley",
    "sg:classifiers":[
        {
            "category":"Retail",
            "subcategory":"Auto Repair",
            "type":"Services"
        }
    ],
    "sg:phone":"+44 1773 748333",
    "sg:postcode":"DE5 3EH",
    "sg:province":"Derbyshire",
    "sg:tags":[
        "engine",
        "car",
        "specialist"
    ],
    "wof:name":"Super Tune",
    "wof:placetype":"venue"
},
  "geometry": {"coordinates":[-1.403305,53.049583],"type":"Point"}
}