{
  "type": "Feature",
  "properties": {
    "addr:full":"12 Tintern Way Bedworth Warwickshire CV12 9SS",
    "addr:housenumber":"12",
    "addr:postcode":"cv12 9ss",
    "addr:street":"Tintern Way",
    "iso:country":"GB",
    "sg:address":"12 Tintern Way",
    "sg:city":"Bedworth",
    "sg:classifiers":[
        {
            "category":"Retail",
            "subcategory":"Driving School",
            "type":"Services"
        }
    ],
    "sg:phone":"+44 24 7664 0240",
    "sg:postcode":"CV12 9SS",
    "sg:province":"Warwickshire",
    "wof:name":"Takhar School Of Motoring The",
    "wof:placetype":"venue"
},
  "geometry": {"coordinates":[-1.465858,52.47998],"type":"Point"}
}