{
  "type": "Feature",
  "properties": {
    "iso:country":"GB",
    "sg:address":"Madeira Clo",
    "sg:city":"Basingstoke",
    "sg:classifiers":[
        {
            "category":"Shopping",
            "subcategory":"Department Store",
            "type":"Retail Goods"
        }
    ],
    "sg:postcode":"RG24 9AT",
    "sg:province":"Hampshire",
    "wof:name":"Yeoman,S,",
    "wof:placetype":"venue"
},
  "geometry": {"coordinates":[-1.074099,51.285954],"type":"Point"}
}