{
  "type": "Feature",
  "properties": {
    "iso:country":"GB",
    "sg:address":"47a Byron St",
    "sg:city":"Dundee",
    "sg:classifiers":[
        {
            "category":"Professional",
            "subcategory":"Engineering",
            "type":"Services"
        }
    ],
    "sg:phone":"+44 1382 835962",
    "sg:postcode":"DD3 6QT",
    "sg:province":"Dundee City",
    "sg:tags":[
        "precision",
        "engineer"
    ],
    "wof:name":"C.N.C Engineering",
    "wof:placetype":"venue"
},
  "geometry": {"coordinates":[-2.985721,56.472778],"type":"Point"}
}