{
  "type": "Feature",
  "properties": {
    "iso:country":"GB",
    "sg:address":"2 Old Brompton Road",
    "sg:city":"London",
    "sg:classifiers":[
        {
            "category":"Professional",
            "subcategory":"Business Services",
            "type":"Services"
        },
        {
            "category":"Government",
            "subcategory":"Post Office",
            "type":"Public Place"
        }
    ],
    "sg:phone":"+44 20 7584 8648",
    "sg:postcode":"SW7 3DQ",
    "sg:province":"Greater London",
    "sg:tags":[
        "information"
    ],
    "wof:name":"Citibox Mayfair Ltd.",
    "wof:placetype":"venue"
},
  "geometry": {"coordinates":[-0.175109,51.493599],"type":"Point"}
}