{
  "type": "Feature",
  "properties": {
    "addr:full":"Westside, Eaglesfield Lockerbie Dumfries and Galloway DG11 3PH",
    "addr:postcode":"dg11 3ph",
    "iso:country":"GB",
    "sg:address":"Westside, Eaglesfield",
    "sg:city":"Lockerbie",
    "sg:classifiers":[
        {
            "category":"Building & Trades",
            "subcategory":"Construction",
            "type":"Services"
        }
    ],
    "sg:postcode":"DG11 3PH",
    "sg:province":"Dumfries and Galloway",
    "sg:tags":[
        "builder"
    ],
    "wof:name":"Graham Construction Ltd",
    "wof:placetype":"venue"
},
  "geometry": {"coordinates":[-3.2056241035,55.0563240051],"type":"Point"}
}