{
  "type": "Feature",
  "properties": {
    "iso:country":"GB",
    "sg:address":"19 Orinana House, 10 Victory Place",
    "sg:city":"London",
    "sg:classifiers":[
        {
            "category":"Banks & Credit Unions",
            "subcategory":"Financial Services",
            "type":"Services"
        }
    ],
    "sg:phone":"+44 20 7935 4701",
    "sg:postcode":"E14 8BQ",
    "sg:province":"Greater London",
    "sg:tags":[
        "adviser"
    ],
    "wof:name":"Kingfisher Financial Planning",
    "wof:placetype":"venue"
},
  "geometry": {"coordinates":[-0.03465,51.51017],"type":"Point"}
}