{
  "type": "Feature",
  "properties": {
    "addr:full":"Po Box 1737 Fordingbridge Dorset SP6 1FA",
    "addr:housenumber":"po",
    "addr:postcode":"1737;sp6 1fa",
    "addr:street":"Box",
    "iso:country":"GB",
    "sg:address":"Po Box 1737",
    "sg:city":"Fordingbridge",
    "sg:classifiers":[
        {
            "category":"Real Estate",
            "subcategory":"Real Estate Agent",
            "type":"Services"
        }
    ],
    "sg:phone":"+44 1425 653355",
    "sg:postcode":"SP6 1FA",
    "sg:province":"Dorset",
    "wof:name":"Simmonds En France",
    "wof:placetype":"venue"
},
  "geometry": {"coordinates":[-1.7946089506,50.9309883118],"type":"Point"}
}