{
  "type": "Feature",
  "properties": {
    "iso:country":"GB",
    "sg:address":"13 Waterloo Road",
    "sg:city":"Wolverhampton",
    "sg:classifiers":[
        {
            "category":"Real Estate",
            "subcategory":"Real Estate Agent",
            "type":"Services"
        }
    ],
    "sg:phone":"+44 1902 575555",
    "sg:postcode":"WV1 4DJ",
    "sg:province":"West Midlands",
    "wof:name":"Sanders Wright & Freeman",
    "wof:placetype":"venue"
},
  "geometry": {"coordinates":[-2.1325590611,52.5865058899],"type":"Point"}
}