{
  "type": "Feature",
  "properties": {
    "addr:full":"12 Grains Rd Oldham Lancashire OL3 5DS",
    "addr:housenumber":"12",
    "addr:postcode":"ol3 5ds",
    "addr:street":"Grains Rd",
    "iso:country":"GB",
    "sg:address":"12 Grains Rd",
    "sg:city":"Oldham",
    "sg:classifiers":[
        {
            "category":"Professional",
            "subcategory":"Detective & Security Services",
            "type":"Services"
        }
    ],
    "sg:phone":"+44 76 4110 9548",
    "sg:postcode":"OL3 5DS",
    "sg:province":"Lancashire",
    "wof:name":"Security Control Services",
    "wof:placetype":"venue"
},
  "geometry": {"coordinates":[-2.024938,53.567211],"type":"Point"}
}