{
  "type": "Feature",
  "properties": {
    "addr:full":"16 Market Street, Bingham Nottingham Leicestershire NG13 8AB",
    "addr:housenumber":"16",
    "addr:postcode":"ng13 8ab",
    "addr:street":"Market Street",
    "iso:country":"GB",
    "sg:address":"16 Market Street, Bingham",
    "sg:city":"Nottingham",
    "sg:classifiers":[
        {
            "category":"Personal",
            "subcategory":"Beauty Salon",
            "type":"Services"
        },
        {
            "category":"Personal",
            "subcategory":"Barber",
            "type":"Services"
        }
    ],
    "sg:phone":"+44 1949 839678",
    "sg:postcode":"NG13 8AB",
    "sg:province":"Leicestershire",
    "sg:tags":[
        "unisex",
        "hairdresser"
    ],
    "wof:name":"Scissor Happy",
    "wof:placetype":"venue"
},
  "geometry": {"coordinates":[-0.9530779719,52.9515266418],"type":"Point"}
}