{
  "type": "Feature",
  "properties": {
    "iso:country":"GB",
    "sg:address":"130/132 Nantwich Road",
    "sg:city":"Crewe",
    "sg:classifiers":[
        {
            "category":"Professional",
            "subcategory":"Management & Consulting",
            "type":"Services"
        }
    ],
    "sg:postcode":"CW2 6AZ",
    "sg:province":"Cheshire",
    "sg:tags":[
        "consultant",
        "business"
    ],
    "wof:name":"Thaddeus Consultants Ltd.",
    "wof:placetype":"venue"
},
  "geometry": {"coordinates":[-2.44197,53.088032],"type":"Point"}
}