{
  "type": "Feature",
  "properties": {
    "addr:full":"356 Sipson Road West Drayton Greater London UB7 0HR",
    "addr:housenumber":"356",
    "addr:postcode":"ub7 0hr",
    "addr:street":"Sipson Road",
    "iso:country":"GB",
    "sg:address":"356 Sipson Road",
    "sg:city":"West Drayton",
    "sg:classifiers":[
        {
            "category":"Building & Trades",
            "subcategory":"Plumbing",
            "type":"Services"
        }
    ],
    "sg:phone":"+44 20 8897 1875",
    "sg:postcode":"UB7 0HR",
    "sg:province":"Greater London",
    "sg:tags":[
        "central",
        "heating"
    ],
    "wof:name":"C T Brown",
    "wof:placetype":"venue"
},
  "geometry": {"coordinates":[-0.458987,51.494083],"type":"Point"}
}