{
  "type": "Feature",
  "properties": {
    "addr:full":"8 Craigbarnet Crescent, Millerstone Glasgow Glasgow City G33 6NF",
    "addr:housenumber":"8",
    "addr:postcode":"g33 6nf",
    "addr:street":"Craigbarnet Crescent Millerstone",
    "iso:country":"GB",
    "sg:address":"8 Craigbarnet Crescent, Millerstone",
    "sg:city":"Glasgow",
    "sg:classifiers":[
        {
            "category":"Professional",
            "subcategory":"Management & Consulting",
            "type":"Services"
        }
    ],
    "sg:postcode":"G33 6NF",
    "sg:province":"Glasgow City",
    "sg:tags":[
        "consultant",
        "business"
    ],
    "wof:name":"Infotech Consulting Services Ltd",
    "wof:placetype":"venue"
},
  "geometry": {"coordinates":[-4.1652832031,55.8846130371],"type":"Point"}
}