{
  "type": "Feature",
  "properties": {
    "iso:country":"GB",
    "sg:address":", Gwyddelwern",
    "sg:city":"Corwen",
    "sg:classifiers":[
        {
            "category":"Bars & Pubs",
            "type":"Food & Drink"
        }
    ],
    "sg:phone":"+44 1490 412113",
    "sg:postcode":"LL21 9DH",
    "sg:province":"Conwy",
    "sg:tags":[
        "pubs",
        "inn"
    ],
    "wof:name":"The Rose & Crown",
    "wof:placetype":"venue"
},
  "geometry": {"coordinates":[-3.393733,53.013809],"type":"Point"}
}