{
  "type": "Feature",
  "properties": {
    "addr:full":"108-116 Humber Rd Coventry Warwickshire CV3 1BA",
    "addr:housenumber":"108-116",
    "addr:postcode":"cv3 1ba",
    "addr:street":"Humber Rd",
    "iso:country":"GB",
    "sg:address":"108-116 Humber Rd",
    "sg:city":"Coventry",
    "sg:classifiers":[
        {
            "category":"Retail",
            "subcategory":"Auto Repair",
            "type":"Services"
        }
    ],
    "sg:phone":"+44 24 7644 9800",
    "sg:postcode":"CV3 1BA",
    "sg:province":"Warwickshire",
    "sg:tags":[
        "modification",
        "garage"
    ],
    "wof:name":"G M S",
    "wof:placetype":"venue"
},
  "geometry": {"coordinates":[-1.4876610041,52.4011955261],"type":"Point"}
}