{
  "type": "Feature",
  "properties": {
    "addr:full":"2c Birchwood Drive, Lower Peover Knutsford Cheshire WA16 9QJ",
    "addr:housenumber":"2c",
    "addr:postcode":"wa16 9qj",
    "addr:street":"Birchwood Drive",
    "iso:country":"GB",
    "sg:address":"2c Birchwood Drive, Lower Peover",
    "sg:city":"Knutsford",
    "sg:classifiers":[
        {
            "category":"Farming",
            "subcategory":"Dairy Farm",
            "type":"Manufacturing & Wholesale Goods"
        }
    ],
    "sg:postcode":"WA16 9QJ",
    "sg:province":"Cheshire",
    "wof:name":"Mervyn Hamer Milking Installation",
    "wof:placetype":"venue"
},
  "geometry": {"coordinates":[-2.394934,53.256104],"type":"Point"}
}