{
  "type": "Feature",
  "properties": {
    "addr:full":"Baydon Ho Farm, Baydon Marlborough Berkshire SN8 2JB",
    "addr:housenumber":"baydon",
    "addr:postcode":"sn8 2jb",
    "iso:country":"GB",
    "sg:address":"Baydon Ho Farm, Baydon",
    "sg:city":"Marlborough",
    "sg:classifiers":[
        {
            "category":"Farming",
            "subcategory":"Livestock Farm",
            "type":"Manufacturing & Wholesale Goods"
        }
    ],
    "sg:postcode":"SN8 2JB",
    "sg:province":"Berkshire",
    "sg:tags":[
        "others"
    ],
    "wof:name":"Furteck,Jean,",
    "wof:placetype":"venue"
},
  "geometry": {"coordinates":[-1.592334,51.498859],"type":"Point"}
}