{
  "type": "Feature",
  "properties": {
    "iso:country":"GB",
    "sg:address":"Woodslee Primary School, Croft Av",
    "sg:city":"Wirral",
    "sg:classifiers":[
        {
            "category":"Government",
            "subcategory":"Office",
            "type":"Public Place"
        }
    ],
    "sg:phone":"+44 151 334 5477",
    "sg:postcode":"CH62 2BP",
    "sg:province":"Cheshire",
    "sg:tags":[
        "local"
    ],
    "wof:name":"Metropolitan Borough of Wirral",
    "wof:placetype":"venue"
},
  "geometry": {"coordinates":[-2.985,53.334911],"type":"Point"}
}