{
  "type": "Feature",
  "properties": {
    "addr:full":"78 Sandhurst Ave Mansfield Nottinghamshire NG18 4BG",
    "addr:housenumber":"78",
    "addr:postcode":"ng18 4bg",
    "addr:street":"Sandhurst Ave",
    "iso:country":"GB",
    "sg:address":"78 Sandhurst Ave",
    "sg:city":"Mansfield",
    "sg:classifiers":[
        {
            "category":"Building & Trades",
            "subcategory":"Construction",
            "type":"Services"
        }
    ],
    "sg:postcode":"NG18 4BG",
    "sg:province":"Nottinghamshire",
    "sg:tags":[
        "decorator",
        "painter"
    ],
    "wof:name":"Berry,W,& P Hurt",
    "wof:placetype":"venue"
},
  "geometry": {"coordinates":[-1.1928399801,53.1301498413],"type":"Point"}
}