{
  "type": "Feature",
  "properties": {
    "iso:country":"GB",
    "sg:address":"16 Encombe, Sandgate",
    "sg:city":"Folkestone",
    "sg:classifiers":[
        {
            "category":"Professional",
            "type":"Services"
        }
    ],
    "sg:phone":"+44 1303 252333",
    "sg:postcode":"CT20 3DE",
    "sg:province":"Kent",
    "sg:tags":[
        "shopfitters"
    ],
    "wof:name":"New Image",
    "wof:placetype":"venue"
},
  "geometry": {"coordinates":[1.153615,51.076008],"type":"Point"}
}