{
  "type": "Feature",
  "properties": {
    "addr:full":"St Johns Street, Farncombe Godalming Surrey GU7 3EH",
    "addr:postcode":"gu7 3eh",
    "addr:street":"St Johns Street",
    "iso:country":"GB",
    "sg:address":"St Johns Street, Farncombe",
    "sg:city":"Godalming",
    "sg:classifiers":[
        {
            "category":"Social Services",
            "subcategory":"Adult Care",
            "type":"Services"
        },
        {
            "category":"Government",
            "subcategory":"Office",
            "type":"Public Place"
        }
    ],
    "sg:phone":"+44 1483 426685",
    "sg:postcode":"GU7 3EH",
    "sg:province":"Surrey",
    "sg:tags":[
        "agency",
        "education",
        "day",
        "authority",
        "centre"
    ],
    "wof:name":"Farncombe Day Centre",
    "wof:placetype":"venue"
},
  "geometry": {"coordinates":[-0.6041240096,51.1947860718],"type":"Point"}
}