{
  "type": "Feature",
  "properties": {
    "iso:country":"GB",
    "sg:address":"White Lion House, 70 Queensway",
    "sg:city":"Hemel Hempstead",
    "sg:classifiers":[
        {
            "category":"Organizations",
            "subcategory":"Community Association",
            "type":"Services"
        }
    ],
    "sg:phone":"+44 1442 292300",
    "sg:postcode":"HP2 5HD",
    "sg:province":"Hertfordshire",
    "sg:tags":[
        "co-operatives",
        "society",
        "housing",
        "trust"
    ],
    "wof:name":"Hightown Praetorian Housing Association Ltd",
    "wof:placetype":"venue"
},
  "geometry": {"coordinates":[-0.4684099853,51.7582511902],"type":"Point"}
}