{
  "type": "Feature",
  "properties": {
    "addr:full":"95 Hungerford Rd Holloway Greater London N7 9LB",
    "addr:housenumber":"95",
    "addr:postcode":"n7 9lb",
    "addr:street":"Hungerford Rd",
    "iso:country":"GB",
    "sg:address":"95 Hungerford Rd",
    "sg:city":"Holloway",
    "sg:classifiers":[
        {
            "category":"Professional",
            "subcategory":"Accounting & Tax Preparation",
            "type":"Services"
        }
    ],
    "sg:phone":"+44 20 7607 5842",
    "sg:postcode":"N7 9LB",
    "sg:province":"Greater London",
    "sg:tags":[
        "accountant"
    ],
    "wof:name":"Patikis & Co",
    "wof:placetype":"venue"
},
  "geometry": {"coordinates":[-0.1244700029,51.5505867004],"type":"Point"}
}