{
  "type": "Feature",
  "properties": {
    "addr:full":"City Buildings, 28-30 Carrington Street Nottingham Nottinghamshire NG1 7FG",
    "addr:housenumber":"28-30",
    "addr:postcode":"ng1 7fg",
    "addr:street":"Carrington Street",
    "iso:country":"GB",
    "sg:address":"City Buildings, 28-30 Carrington Street",
    "sg:city":"Nottingham",
    "sg:classifiers":[
        {
            "category":"Education",
            "subcategory":"Dance Studio",
            "type":"Public Place"
        }
    ],
    "sg:phone":"+44 115 941 1993",
    "sg:postcode":"NG1 7FG",
    "sg:province":"Nottinghamshire",
    "sg:tags":[
        "school",
        "dancing"
    ],
    "wof:name":"The Dance Studios",
    "wof:placetype":"venue"
},
  "geometry": {"coordinates":[-1.1479790211,52.9487800598],"type":"Point"}
}