{
  "type": "Feature",
  "properties": {
    "addr:full":"140 Uxbridge Road Hayes Greater London UB4 0JH",
    "addr:housenumber":"140",
    "addr:postcode":"ub4 0jh",
    "addr:street":"Uxbridge Road",
    "iso:country":"GB",
    "sg:address":"140 Uxbridge Road",
    "sg:city":"Hayes",
    "sg:classifiers":[
        {
            "category":"Home & Garden",
            "subcategory":"Home Furnishings",
            "type":"Retail Goods"
        }
    ],
    "sg:phone":"+44 20 8813 6952",
    "sg:postcode":"UB4 0JH",
    "sg:province":"Greater London",
    "sg:tags":[
        "furnishers",
        "planner",
        "kitchen"
    ],
    "wof:name":"Heathrow Kitchens",
    "wof:placetype":"venue"
},
  "geometry": {"coordinates":[-0.3949300051,51.5145721436],"type":"Point"}
}