{
  "type": "Feature",
  "properties": {
    "addr:full":"1 Tanzieknowe Avenue, Cambuslang Glasgow South Lanarkshire G72 8RQ",
    "addr:housenumber":"1",
    "addr:postcode":"south;g72 8rq",
    "addr:street":"Tanzieknowe Avenue",
    "iso:country":"GB",
    "sg:address":"1 Tanzieknowe Avenue, Cambuslang",
    "sg:city":"Glasgow",
    "sg:classifiers":[
        {
            "category":"Building & Trades",
            "subcategory":"Construction",
            "type":"Services"
        }
    ],
    "sg:phone":"+44 141 641 2395",
    "sg:postcode":"G72 8RQ",
    "sg:province":"South Lanarkshire",
    "sg:tags":[
        "roofing"
    ],
    "wof:name":"Roster Property Maintenance",
    "wof:placetype":"venue"
},
  "geometry": {"coordinates":[-4.1605501175,55.8092880249],"type":"Point"}
}