{
  "type": "Feature",
  "properties": {
    "iso:country":"GB",
    "sg:address":"34 Byron Road",
    "sg:city":"Gillingham",
    "sg:classifiers":[
        {
            "category":"Government",
            "subcategory":"Post Office",
            "type":"Public Place"
        }
    ],
    "sg:phone":"+44 1634 853223",
    "sg:postcode":"ME7 5QH",
    "sg:province":"Kent",
    "wof:name":"Byron Post Office",
    "wof:placetype":"venue"
},
  "geometry": {"coordinates":[0.545199,51.377373],"type":"Point"}
}