{
  "type": "Feature",
  "properties": {
    "iso:country":"GB",
    "sg:address":"221 Upper College Ride",
    "sg:city":"Camberley",
    "sg:classifiers":[
        {
            "category":"Building & Trades",
            "subcategory":"Cleaning & Sanitation",
            "type":"Services"
        }
    ],
    "sg:phone":"+44 1276 501398",
    "sg:postcode":"GU15 4HE",
    "sg:province":"Berkshire",
    "sg:tags":[
        "commercial"
    ],
    "wof:name":"Albright Cleaning Services",
    "wof:placetype":"venue"
},
  "geometry": {"coordinates":[-0.724542,51.348148],"type":"Point"}
}