{
  "type": "Feature",
  "properties": {
    "addr:full":"Abbey Farmhouse Church Street, Wroxton Banbury Oxfordshire OX15 6QE",
    "addr:postcode":"ox15 6qe",
    "addr:street":"Church Street",
    "iso:country":"GB",
    "sg:address":"Abbey Farmhouse Church Street, Wroxton",
    "sg:city":"Banbury",
    "sg:classifiers":[
        {
            "category":"Building & Trades",
            "subcategory":"Construction",
            "type":"Services"
        }
    ],
    "sg:postcode":"OX15 6QE",
    "sg:province":"Oxfordshire",
    "sg:tags":[
        "builder"
    ],
    "wof:name":"Freeman & O Carroll R.W",
    "wof:placetype":"venue"
},
  "geometry": {"coordinates":[-1.397626,52.074318],"type":"Point"}
}