{
  "type": "Feature",
  "properties": {
    "addr:full":"103/106 Chadwick Rd, Astmoor Indstl Est, Astmoor Runcorn Cheshire WA7 1PW",
    "addr:housenumber":"103 / 106",
    "addr:postcode":"wa7 1pw",
    "addr:street":"Chadwick Rd;Indstl;Astmoor",
    "iso:country":"GB",
    "sg:address":"103/106 Chadwick Rd, Astmoor Indstl Est, Astmoor",
    "sg:city":"Runcorn",
    "sg:classifiers":[
        {
            "category":"Manufacturing",
            "subcategory":"Metals",
            "type":"Manufacturing & Wholesale Goods"
        }
    ],
    "sg:phone":"+44 1928 580460",
    "sg:postcode":"WA7 1PW",
    "sg:province":"Cheshire",
    "sg:tags":[
        "steel",
        "fabricator",
        "erectors"
    ],
    "wof:name":"C J Systems Ltd",
    "wof:placetype":"venue"
},
  "geometry": {"coordinates":[-2.6982998848,53.3417205811],"type":"Point"}
}