{
  "type": "Feature",
  "properties": {
    "addr:full":"24a Prescott Place, Clapham Clapham Greater London SW4 6BT",
    "addr:housenumber":"24a",
    "addr:postcode":"sw4 6bt",
    "addr:street":"Prescott Place",
    "iso:country":"GB",
    "sg:address":"24a Prescott Place, Clapham",
    "sg:city":"Clapham",
    "sg:classifiers":[
        {
            "category":"Professional",
            "type":"Services"
        }
    ],
    "sg:phone":"+44 20 7622 7126",
    "sg:postcode":"SW4 6BT",
    "sg:province":"Greater London",
    "sg:tags":[
        "interior",
        "furnishers",
        "designer"
    ],
    "wof:name":"Two Busy Hands Ltd",
    "wof:placetype":"venue"
},
  "geometry": {"coordinates":[-0.135568,51.46368],"type":"Point"}
}