{
  "type": "Feature",
  "properties": {
    "addr:full":"1 The Lexicon, Cornhill Bury St Edmunds Suffolk IP33 1BT",
    "addr:housenumber":"1",
    "addr:postcode":"ip33 1bt",
    "addr:street":"The Lexicon Cornhill",
    "iso:country":"GB",
    "sg:address":"1 The Lexicon, Cornhill",
    "sg:city":"Bury St Edmunds",
    "sg:classifiers":[
        {
            "category":"Shopping",
            "subcategory":"Clothing, Apparel, & Fashions",
            "type":"Retail Goods"
        }
    ],
    "sg:phone":"+44 1284 755658",
    "sg:postcode":"IP33 1BT",
    "sg:province":"Suffolk",
    "sg:tags":[
        "shop"
    ],
    "wof:name":"Laura Ashley",
    "wof:placetype":"venue"
},
  "geometry": {"coordinates":[0.7121899724,52.2453804016],"type":"Point"}
}