{
  "type": "Feature",
  "properties": {
    "addr:full":"2 Mt Pleasant Rd Aldershot Hampshire GU12 4NL",
    "addr:housenumber":"2",
    "addr:postcode":"gu12 4nl",
    "addr:street":"Mt Pleasant Rd",
    "iso:country":"GB",
    "sg:address":"2 Mt Pleasant Rd",
    "sg:city":"Aldershot",
    "sg:classifiers":[
        {
            "category":"Professional",
            "subcategory":"Computer Services",
            "type":"Services"
        }
    ],
    "sg:postcode":"GU12 4NL",
    "sg:province":"Hampshire",
    "sg:tags":[
        "consultant"
    ],
    "wof:name":"Brittanic Software Services Ltd",
    "wof:placetype":"venue"
},
  "geometry": {"coordinates":[-0.752154,51.247356],"type":"Point"}
}