{
  "type": "Feature",
  "properties": {
    "addr:full":"75 Bridge Road, Litherland Liverpool Merseyside L21 2PA",
    "addr:housenumber":"75",
    "addr:postcode":"l21 2pa",
    "addr:street":"Bridge Road",
    "iso:country":"GB",
    "sg:address":"75 Bridge Road, Litherland",
    "sg:city":"Liverpool",
    "sg:classifiers":[
        {
            "category":"Home & Garden",
            "subcategory":"Home Furnishings",
            "type":"Retail Goods"
        }
    ],
    "sg:postcode":"L21 2PA",
    "sg:province":"Merseyside",
    "sg:tags":[
        "decorative",
        "glass",
        "mirror"
    ],
    "wof:name":"The Mirror Shop",
    "wof:placetype":"venue"
},
  "geometry": {"coordinates":[-3.00237,53.467697],"type":"Point"}
}