{
  "type": "Feature",
  "properties": {
    "iso:country":"GB",
    "sg:address":"41 The Broadway",
    "sg:city":"Southall",
    "sg:classifiers":[
        {
            "category":"Shopping",
            "subcategory":"Music",
            "type":"Retail Goods"
        },
        {
            "category":"Restaurant",
            "type":"Food & Drink"
        }
    ],
    "sg:phone":"+44 20 8574 4739",
    "sg:postcode":"UB1 1JY",
    "sg:province":"Greater London",
    "sg:tags":[
        "record",
        "tape",
        "cd"
    ],
    "wof:name":"Indian Record House",
    "wof:placetype":"venue"
},
  "geometry": {"coordinates":[-0.3903439939,51.5131797791],"type":"Point"}
}