{
  "type": "Feature",
  "properties": {
    "iso:country":"GB",
    "sg:address":"Wiltshire Road",
    "sg:city":"Hull",
    "sg:classifiers":[
        {
            "category":"Retail",
            "subcategory":"Auto Repair",
            "type":"Services"
        }
    ],
    "sg:phone":"+44 1482 575555",
    "sg:postcode":"HU4 6PA",
    "sg:province":"East Riding of Yorkshire",
    "sg:tags":[
        "bodybuilder",
        "repairer"
    ],
    "wof:name":"David Conman",
    "wof:placetype":"venue"
},
  "geometry": {"coordinates":[-0.384929,53.73243],"type":"Point"}
}