{
  "type": "Feature",
  "properties": {
    "addr:full":"11 Portland Mews London Greater London W1F 8JL",
    "addr:housenumber":"11",
    "addr:postcode":"w1f 8jl",
    "addr:street":"Portland Mews",
    "iso:country":"GB",
    "sg:address":"11 Portland Mews",
    "sg:city":"London",
    "sg:classifiers":[
        {
            "category":"Communications",
            "type":"Services"
        }
    ],
    "sg:phone":"+44 20 8788 4719",
    "sg:postcode":"W1F 8JL",
    "sg:province":"Greater London",
    "sg:tags":[
        "audio-visual"
    ],
    "wof:name":"Ocelot Productions Ltd.",
    "wof:placetype":"venue"
},
  "geometry": {"coordinates":[-0.1364459991,51.5144767761],"type":"Point"}
}