{
  "type": "Feature",
  "properties": {
    "addr:full":"286 Cumbernauld Road Glasgow Glasgow City G31 2UL",
    "addr:housenumber":"286",
    "addr:postcode":"g31 2ul",
    "addr:street":"Cumbernauld Road",
    "iso:country":"GB",
    "sg:address":"286 Cumbernauld Road",
    "sg:city":"Glasgow",
    "sg:classifiers":[
        {
            "category":"Government",
            "subcategory":"Post Office",
            "type":"Public Place"
        }
    ],
    "sg:phone":"+44 141 554 0635",
    "sg:postcode":"G31 2UL",
    "sg:province":"Glasgow City",
    "wof:name":"Alexandra Park Post Office",
    "wof:placetype":"venue"
},
  "geometry": {"coordinates":[-4.208207,55.86253],"type":"Point"}
}