{
  "type": "Feature",
  "properties": {
    "addr:full":"17 Rosslyn Rd Twickenham Greater London TW1 2AR",
    "addr:housenumber":"17",
    "addr:postcode":"tw1 2ar",
    "addr:street":"Rosslyn Rd",
    "iso:country":"GB",
    "sg:address":"17 Rosslyn Rd",
    "sg:city":"Twickenham",
    "sg:classifiers":[
        {
            "category":"Health Services",
            "subcategory":"Doctor",
            "type":"Services"
        }
    ],
    "sg:phone":"+44 20 8892 1991",
    "sg:postcode":"TW1 2AR",
    "sg:province":"Greater London",
    "sg:tags":[
        "practitioners"
    ],
    "wof:name":"Twickenham Park Surgery",
    "wof:placetype":"venue"
},
  "geometry": {"coordinates":[-0.314368993,51.4548416138],"type":"Point"}
}