{
  "type": "Feature",
  "properties": {
    "addr:full":"257 Holburn Street Aberdeen Aberdeen City AB1 6DL",
    "addr:housenumber":"257",
    "addr:postcode":"ab1 6dl",
    "addr:street":"Holburn Street",
    "iso:country":"GB",
    "sg:address":"257 Holburn Street",
    "sg:city":"Aberdeen",
    "sg:classifiers":[
        {
            "category":"Food & Beverages",
            "subcategory":"Bakery",
            "type":"Retail Goods"
        }
    ],
    "sg:phone":"+44 1224 584111",
    "sg:postcode":"AB1 6DL",
    "sg:province":"Aberdeen City",
    "sg:tags":[
        "baker"
    ],
    "wof:name":"Thain's Bakery",
    "wof:placetype":"venue"
},
  "geometry": {"coordinates":[-2.1143629551,57.1370582581],"type":"Point"}
}