{
  "type": "Feature",
  "properties": {
    "iso:country":"GB",
    "sg:address":"39a High Street",
    "sg:city":"Sittingbourne",
    "sg:classifiers":[
        {
            "category":"Professional",
            "subcategory":"Business Services",
            "type":"Services"
        }
    ],
    "sg:phone":"+44 1795 429516",
    "sg:postcode":"ME10 4AW",
    "sg:province":"Kent",
    "sg:tags":[
        "accomodation"
    ],
    "wof:name":"Bradford Property Management Ltd.",
    "wof:placetype":"venue"
},
  "geometry": {"coordinates":[0.738553,51.339428],"type":"Point"}
}