{
  "type": "Feature",
  "properties": {
    "addr:full":"68 Station Road, Marston Grn Birmingham West Midlands B37 7BA",
    "addr:housenumber":"68",
    "addr:postcode":"b37 7ba",
    "addr:street":"Station Road;Grn",
    "iso:country":"GB",
    "sg:address":"68 Station Road, Marston Grn",
    "sg:city":"Birmingham",
    "sg:classifiers":[
        {
            "category":"Farming",
            "subcategory":"Nursery",
            "type":"Manufacturing & Wholesale Goods"
        },
        {
            "category":"Social Services",
            "subcategory":"Child Care",
            "type":"Services"
        }
    ],
    "sg:phone":"+44 121 779 2024",
    "sg:postcode":"B37 7BA",
    "sg:province":"West Midlands",
    "sg:tags":[
        "childcare",
        "creche"
    ],
    "wof:name":"Wellies Private Day Nursery",
    "wof:placetype":"venue"
},
  "geometry": {"coordinates":[-1.7489540577,52.4673461914],"type":"Point"}
}