{
  "type": "Feature",
  "properties": {
    "iso:country":"GB",
    "sg:address":"1a Crescent Road",
    "sg:city":"Birchington",
    "sg:classifiers":[
        {
            "category":"Shopping",
            "subcategory":"Pharmacy",
            "type":"Retail Goods"
        }
    ],
    "sg:phone":"+44 1843 848600",
    "sg:postcode":"CT7 9DP",
    "sg:province":"Kent",
    "sg:tags":[
        "medicine",
        "therapy"
    ],
    "wof:name":"Enchantment",
    "wof:placetype":"venue"
},
  "geometry": {"coordinates":[1.305148,51.375465],"type":"Point"}
}