{
  "type": "Feature",
  "properties": {
    "iso:country":"GB",
    "sg:address":"Queen Street House, 4 Queen Street",
    "sg:city":"Bath",
    "sg:classifiers":[
        {
            "category":"Shopping",
            "subcategory":"Books",
            "type":"Retail Goods"
        }
    ],
    "sg:phone":"+44 1225 478888",
    "sg:postcode":"BA1 1HE",
    "sg:province":"Bath and North East Somerset",
    "wof:name":"Parragon Book Service Ltd.",
    "wof:placetype":"venue"
},
  "geometry": {"coordinates":[-2.3620688915,51.3828735352],"type":"Point"}
}