{
  "type": "Feature",
  "properties": {
    "addr:full":"23 Lower Merton Rise London Greater London NW3 3SP",
    "addr:housenumber":"23",
    "addr:postcode":"nw3 3sp",
    "addr:street":"Lower Merton Rise",
    "iso:country":"GB",
    "sg:address":"23 Lower Merton Rise",
    "sg:city":"London",
    "sg:classifiers":[
        {
            "category":"Food & Beverages",
            "subcategory":"Groceries & Convenience Stores",
            "type":"Retail Goods"
        }
    ],
    "sg:phone":"+44 20 7586 1752",
    "sg:postcode":"NW3 3SP",
    "sg:province":"Greater London",
    "wof:name":"M & W Local Store",
    "wof:placetype":"venue"
},
  "geometry": {"coordinates":[-0.166138,51.542622],"type":"Point"}
}