{
  "type": "Feature",
  "properties": {
    "iso:country":"GB",
    "sg:address":"Marr House, The Landing",
    "sg:city":"Brough",
    "sg:classifiers":[
        {
            "category":"Professional",
            "subcategory":"Accounting & Tax Preparation",
            "type":"Services"
        }
    ],
    "sg:phone":"+44 1430 423747",
    "sg:postcode":"HU15 1RT",
    "sg:province":"East Riding of Yorkshire",
    "sg:tags":[
        "accountant"
    ],
    "wof:name":"F N Prescott",
    "wof:placetype":"venue"
},
  "geometry": {"coordinates":[-0.572144,53.729919],"type":"Point"}
}