{
  "type": "Feature",
  "properties": {
    "addr:full":"Cripps Lodge Milton Keynes Buckinghamshire MK6 4JJ",
    "addr:postcode":"mk6 4jj",
    "iso:country":"GB",
    "sg:address":"Cripps Lodge",
    "sg:city":"Milton Keynes",
    "sg:classifiers":[
        {
            "category":"Social Services",
            "subcategory":"Adult Care",
            "type":"Services"
        }
    ],
    "sg:phone":"+44 1908 835881",
    "sg:postcode":"MK6 4JJ",
    "sg:province":"Buckinghamshire",
    "sg:tags":[
        "day",
        "centre"
    ],
    "wof:name":"Keystone Day Centre",
    "wof:placetype":"venue"
},
  "geometry": {"coordinates":[-0.7369400263,52.0219993591],"type":"Point"}
}