{
  "type": "Feature",
  "properties": {
    "addr:full":"5 Bradstocks Way, Sutton Courtenay Abingdon Oxfordshire OX14 4BY",
    "addr:housenumber":"5",
    "addr:postcode":"ox14 4by",
    "addr:street":"Bradstocks Way",
    "iso:country":"GB",
    "sg:address":"5 Bradstocks Way, Sutton Courtenay",
    "sg:city":"Abingdon",
    "sg:classifiers":[
        {
            "category":"Home & Garden",
            "subcategory":"Building Materials",
            "type":"Retail Goods"
        },
        {
            "category":"Building & Trades",
            "subcategory":"Construction",
            "type":"Services"
        }
    ],
    "sg:phone":"+44 1235 848555",
    "sg:postcode":"OX14 4BY",
    "sg:province":"Oxfordshire",
    "sg:tags":[
        "dry",
        "plastering",
        "plasterers",
        "lining",
        "related",
        "installers",
        "insulation",
        "screeders"
    ],
    "wof:name":"PAUL JAMES KELLY",
    "wof:placetype":"venue"
},
  "geometry": {"coordinates":[-1.284878,51.631985],"type":"Point"}
}