{
  "type": "Feature",
  "properties": {
    "addr:full":"30 Spruce Road, Woodley Reading Berkshire RG5 4BB",
    "addr:housenumber":"30",
    "addr:postcode":"rg5 4bb",
    "addr:street":"Spruce Road",
    "iso:country":"GB",
    "sg:address":"30 Spruce Road, Woodley",
    "sg:city":"Reading",
    "sg:classifiers":[
        {
            "category":"Wholesale",
            "subcategory":"Electrical",
            "type":"Manufacturing & Wholesale Goods"
        },
        {
            "category":"Building & Trades",
            "subcategory":"Electrical",
            "type":"Services"
        }
    ],
    "sg:phone":"+44 118 944 1239",
    "sg:postcode":"RG5 4BB",
    "sg:province":"Berkshire",
    "sg:tags":[
        "equipment",
        "industrial",
        "commercial",
        "refrigeration"
    ],
    "wof:name":"Larchfield Services",
    "wof:placetype":"venue"
},
  "geometry": {"coordinates":[-0.887732,51.447021],"type":"Point"}
}