{
  "type": "Feature",
  "properties": {
    "addr:full":"23 Skinner Street Newport Newport NP20 1HB",
    "addr:housenumber":"23",
    "addr:postcode":"np20 1hb",
    "addr:street":"Skinner Street",
    "iso:country":"GB",
    "sg:address":"23 Skinner Street",
    "sg:city":"Newport",
    "sg:classifiers":[
        {
            "category":"Shopping",
            "subcategory":"Comic Books",
            "type":"Retail Goods"
        }
    ],
    "sg:phone":"+44 1633 254735",
    "sg:postcode":"NP20 1HB",
    "sg:province":"Newport",
    "sg:tags":[
        "jeweller"
    ],
    "wof:name":"C L Jeffries Ltd.",
    "wof:placetype":"venue"
},
  "geometry": {"coordinates":[-2.99577,51.588146],"type":"Point"}
}