{
  "type": "Feature",
  "properties": {
    "iso:country":"GB",
    "sg:address":"103-105 Spring Bank",
    "sg:city":"Hull",
    "sg:classifiers":[
        {
            "category":"Autos & Motor Vehicles",
            "subcategory":"Auto Supplies",
            "type":"Retail Goods"
        }
    ],
    "sg:phone":"+44 1482 217596",
    "sg:postcode":"HU3 1BH",
    "sg:province":"East Riding of Yorkshire",
    "sg:tags":[
        "exhaust",
        "absorber",
        "shock"
    ],
    "wof:name":"Kwik-Fit",
    "wof:placetype":"venue"
},
  "geometry": {"coordinates":[-0.3526909947,53.749710083],"type":"Point"}
}