{
  "type": "Feature",
  "properties": {
    "addr:full":"95 Meadow Lane Coalville Leicestershire LE67 4DN",
    "addr:housenumber":"95",
    "addr:postcode":"le67 4dn",
    "addr:street":"Meadow Lane",
    "iso:country":"GB",
    "sg:address":"95 Meadow Lane",
    "sg:city":"Coalville",
    "sg:classifiers":[
        {
            "category":"Shopping",
            "subcategory":"Department Store",
            "type":"Retail Goods"
        },
        {
            "category":"Food & Beverages",
            "subcategory":"Groceries & Convenience Stores",
            "type":"Retail Goods"
        }
    ],
    "sg:phone":"+44 1530 832423",
    "sg:postcode":"LE67 4DN",
    "sg:province":"Leicestershire",
    "wof:name":"Meadow Lane Post Office",
    "wof:placetype":"venue"
},
  "geometry": {"coordinates":[-1.333138,52.730015],"type":"Point"}
}