{
  "type": "Feature",
  "properties": {
    "addr:full":"The Oaks, Unit5 Frame Field Road, Buxted Uckfield East Sussex TN22 4PP",
    "addr:postcode":"tn22 4pp",
    "addr:street":"Field Road",
    "iso:country":"GB",
    "sg:address":"The Oaks, Unit5 Frame Field Road, Buxted",
    "sg:city":"Uckfield",
    "sg:classifiers":[
        {
            "category":"Manufacturing",
            "subcategory":"Metals",
            "type":"Manufacturing & Wholesale Goods"
        },
        {
            "category":"Professional",
            "subcategory":"Engineering",
            "type":"Services"
        }
    ],
    "sg:phone":"+44 1825 890884",
    "sg:postcode":"TN22 4PP",
    "sg:province":"East Sussex",
    "sg:tags":[
        "steel",
        "fabricator",
        "erectors",
        "engineer"
    ],
    "wof:name":"I D I Metal Fabrications",
    "wof:placetype":"venue"
},
  "geometry": {"coordinates":[0.1417350024,50.9915885925],"type":"Point"}
}