{
  "type": "Feature",
  "properties": {
    "addr:full":"1 Dipton Gardens, Tunstall Sunderland Tyne and Wear SR3 1AN",
    "addr:housenumber":"1",
    "addr:postcode":"sr3 1an",
    "addr:street":"Dipton Gardens",
    "iso:country":"GB",
    "sg:address":"1 Dipton Gardens, Tunstall",
    "sg:city":"Sunderland",
    "sg:classifiers":[
        {
            "category":"Professional",
            "subcategory":"Engineering",
            "type":"Services"
        }
    ],
    "sg:phone":"+44 191 522 7603",
    "sg:postcode":"SR3 1AN",
    "sg:province":"Tyne and Wear",
    "sg:tags":[
        "gas",
        "engineer"
    ],
    "wof:name":"Weargas",
    "wof:placetype":"venue"
},
  "geometry": {"coordinates":[-1.3947279453,54.8861045837],"type":"Point"}
}