{
  "type": "Feature",
  "properties": {
    "addr:full":"Grays Farm, Peterborough Road, Crowland Peterborough Cambridgeshire PE6 0AD",
    "addr:postcode":"pe6 0ad",
    "addr:street":"Grays;Peterborough Road",
    "iso:country":"GB",
    "sg:address":"Grays Farm, Peterborough Road, Crowland",
    "sg:city":"Peterborough",
    "sg:classifiers":[
        {
            "category":"Education",
            "subcategory":"Special Training",
            "type":"Public Place"
        }
    ],
    "sg:phone":"+44 1733 210346",
    "sg:postcode":"PE6 0AD",
    "sg:province":"Cambridgeshire",
    "sg:tags":[
        "product",
        "centre"
    ],
    "wof:name":"Peterborough Area Training Group",
    "wof:placetype":"venue"
},
  "geometry": {"coordinates":[-0.167112,52.675121],"type":"Point"}
}