{
  "type": "Feature",
  "properties": {
    "iso:country":"GB",
    "sg:address":"3 Lavinia Road",
    "sg:city":"Poole",
    "sg:classifiers":[
        {
            "category":"Building & Trades",
            "subcategory":"Construction",
            "type":"Services"
        }
    ],
    "sg:phone":"+44 1202 744805",
    "sg:postcode":"BH12 3JH",
    "sg:province":"Dorset",
    "sg:tags":[
        "builder"
    ],
    "wof:name":"John Trunwit",
    "wof:placetype":"venue"
},
  "geometry": {"coordinates":[-1.9440640211,50.7396812439],"type":"Point"}
}