{
  "type": "Feature",
  "properties": {
    "iso:country":"GB",
    "sg:address":"Cypress Clo",
    "sg:city":"Merthyr Tydfil",
    "sg:classifiers":[
        {
            "category":"Bars & Pubs",
            "type":"Food & Drink"
        }
    ],
    "sg:phone":"+44 1685 389240",
    "sg:postcode":"CF47 9BP",
    "sg:province":"Merthyr Tydfil",
    "sg:tags":[
        "pubs",
        "inn"
    ],
    "wof:name":"Albion Pub Contracts Ltd",
    "wof:placetype":"venue"
},
  "geometry": {"coordinates":[-3.381984,51.766178],"type":"Point"}
}