{
  "type": "Feature",
  "properties": {
    "addr:full":"Farm Office, Manor Farm Abingdon Oxfordshire OX14 4HZ",
    "addr:postcode":"ox14 4hz",
    "iso:country":"GB",
    "sg:address":"Farm Office, Manor Farm",
    "sg:city":"Abingdon",
    "sg:classifiers":[
        {
            "category":"Farming",
            "subcategory":"Livestock Farm",
            "type":"Manufacturing & Wholesale Goods"
        }
    ],
    "sg:phone":"+44 1235 522897",
    "sg:postcode":"OX14 4HZ",
    "sg:province":"Oxfordshire",
    "sg:tags":[
        "others"
    ],
    "wof:name":"Plymouth Estates",
    "wof:placetype":"venue"
},
  "geometry": {"coordinates":[-1.285489,51.673325],"type":"Point"}
}