{
  "type": "Feature",
  "properties": {
    "addr:full":"17 Church Street, Wye Ashford Kent TN25 5BN",
    "addr:housenumber":"17",
    "addr:postcode":"tn25 5bn",
    "addr:street":"Church Street",
    "iso:country":"GB",
    "sg:address":"17 Church Street, Wye",
    "sg:city":"Ashford",
    "sg:classifiers":[
        {
            "category":"Food & Beverages",
            "subcategory":"Meat & Fish",
            "type":"Retail Goods"
        }
    ],
    "sg:postcode":"TN25 5BN",
    "sg:province":"Kent",
    "sg:tags":[
        "butcher"
    ],
    "wof:name":"K Wakelin",
    "wof:placetype":"venue"
},
  "geometry": {"coordinates":[0.936878,51.183029],"type":"Point"}
}