{
  "type": "Feature",
  "properties": {
    "iso:country":"GB",
    "sg:address":"Northover Boardroom, Northover",
    "sg:city":"Glastonbury",
    "sg:classifiers":[
        {
            "category":"Building & Trades",
            "subcategory":"Plumbing",
            "type":"Services"
        }
    ],
    "sg:postcode":"BA6 9NU",
    "sg:province":"Somerset",
    "sg:tags":[
        "heating"
    ],
    "wof:name":"Norman Parsons",
    "wof:placetype":"venue"
},
  "geometry": {"coordinates":[-2.7170090675,51.1475906372],"type":"Point"}
}