{
  "type": "Feature",
  "properties": {
    "addr:full":"Gun Court 70 Wapping Lane, Wapping London Greater London E1W 2RF",
    "addr:housenumber":"70",
    "addr:postcode":"e1w 2rf",
    "addr:street":"Wapping Lane",
    "iso:country":"GB",
    "sg:address":"Gun Court 70 Wapping Lane, Wapping",
    "sg:city":"London",
    "sg:classifiers":[
        {
            "category":"Real Estate",
            "subcategory":"Developer",
            "type":"Services"
        }
    ],
    "sg:postcode":"E1W 2RF",
    "sg:province":"Greater London",
    "sg:tags":[
        "property"
    ],
    "wof:name":"Gullivers Wharf Freehold Ltd",
    "wof:placetype":"venue"
},
  "geometry": {"coordinates":[-0.05756,51.504692],"type":"Point"}
}