{
  "type": "Feature",
  "properties": {
    "iso:country":"GB",
    "sg:address":"34 Foxglove Road, Birstall",
    "sg:city":"Batley",
    "sg:classifiers":[
        {
            "category":"Social Services",
            "subcategory":"Job Training",
            "type":"Services"
        }
    ],
    "sg:phone":"+44 1924 440022",
    "sg:postcode":"WF17 9NW",
    "sg:province":"West Yorkshire",
    "sg:tags":[
        "draughtsman",
        "drawing"
    ],
    "wof:name":"T Stockhill",
    "wof:placetype":"venue"
},
  "geometry": {"coordinates":[-1.662269,53.736481],"type":"Point"}
}