{
  "type": "Feature",
  "properties": {
    "addr:full":"4 Shakespeare St Newcastle-upon-tyne Tyne and Wear NE1 6AQ",
    "addr:housenumber":"4",
    "addr:postcode":"ne1 6aq",
    "addr:street":"Shakespeare St",
    "iso:country":"GB",
    "sg:address":"4 Shakespeare St",
    "sg:city":"Newcastle-upon-tyne",
    "sg:classifiers":[
        {
            "category":"Retail",
            "subcategory":"Repair Shop",
            "type":"Services"
        }
    ],
    "sg:postcode":"NE1 6AQ",
    "sg:province":"Tyne and Wear",
    "sg:tags":[
        "clocks",
        "watch"
    ],
    "wof:name":"Ryder,G,",
    "wof:placetype":"venue"
},
  "geometry": {"coordinates":[-1.611982,54.972469],"type":"Point"}
}