{
  "type": "Feature",
  "properties": {
    "addr:full":"29 Brock St Bath Bath and North East Somerset BA1 2LN",
    "addr:housenumber":"29",
    "addr:postcode":"ba1 2ln",
    "addr:street":"Brock St",
    "iso:country":"GB",
    "sg:address":"29 Brock St",
    "sg:city":"Bath",
    "sg:classifiers":[
        {
            "category":"Health Services",
            "subcategory":"Health Practitioner",
            "type":"Services"
        }
    ],
    "sg:phone":"+44 1225 445164",
    "sg:postcode":"BA1 2LN",
    "sg:province":"Bath and North East Somerset",
    "sg:tags":[
        "acupuncture"
    ],
    "wof:name":"James Willder",
    "wof:placetype":"venue"
},
  "geometry": {"coordinates":[-2.3653149605,51.386302948],"type":"Point"}
}