{
  "type": "Feature",
  "properties": {
    "addr:full":"15 The Quadrant Richmond Greater London TW9 1BP",
    "addr:housenumber":"15",
    "addr:postcode":"tw9 1bp",
    "addr:street":"The Quadrant",
    "iso:country":"GB",
    "sg:address":"15 The Quadrant",
    "sg:city":"Richmond",
    "sg:classifiers":[
        {
            "category":"Shopping",
            "subcategory":"Mobile Phones",
            "type":"Retail Goods"
        },
        {
            "category":"Communications",
            "type":"Services"
        }
    ],
    "sg:phone":"+44 20 8255 8100",
    "sg:postcode":"TW9 1BP",
    "sg:province":"Greater London",
    "sg:tags":[
        "telecommunication"
    ],
    "wof:name":"Vodafone",
    "wof:placetype":"venue"
},
  "geometry": {"coordinates":[-0.303371,51.461716],"type":"Point"}
}