{
  "type": "Feature",
  "properties": {
    "iso:country":"GB",
    "sg:address":"Livingstone Road",
    "sg:city":"Bradford",
    "sg:classifiers":[
        {
            "category":"Community Center",
            "type":"Public Place"
        }
    ],
    "sg:phone":"+44 1274 588684",
    "sg:postcode":"BD2 1BD",
    "sg:province":"West Yorkshire",
    "sg:tags":[
        "centre"
    ],
    "wof:name":"Bolton Woods Community Centre",
    "wof:placetype":"venue"
},
  "geometry": {"coordinates":[-1.7453639507,53.8250045776],"type":"Point"}
}