{
  "type": "Feature",
  "properties": {
    "addr:full":"28 Woodland Way Burntwood Staffordshire WS7 8UP",
    "addr:housenumber":"28",
    "addr:postcode":"ws7 8up",
    "addr:street":"Woodland Way",
    "iso:country":"GB",
    "sg:address":"28 Woodland Way",
    "sg:city":"Burntwood",
    "sg:classifiers":[
        {
            "category":"Building & Trades",
            "subcategory":"Plumbing",
            "type":"Services"
        }
    ],
    "sg:phone":"+44 1543 683663",
    "sg:postcode":"WS7 8UP",
    "sg:province":"Staffordshire",
    "sg:tags":[
        "heating"
    ],
    "wof:name":"Tom Thumb Plumbing & Heating",
    "wof:placetype":"venue"
},
  "geometry": {"coordinates":[-1.921515,52.676743],"type":"Point"}
}