{
  "type": "Feature",
  "properties": {
    "iso:country":"GB",
    "sg:address":"117 Patch Lane",
    "sg:city":"Redditch",
    "sg:classifiers":[
        {
            "category":"Building & Trades",
            "subcategory":"Construction",
            "type":"Services"
        }
    ],
    "sg:phone":"+44 1527 547474",
    "sg:postcode":"B98 7XE",
    "sg:province":"Warwickshire",
    "sg:tags":[
        "decorator",
        "painter"
    ],
    "wof:name":"M.C.C Painter's & Decorators",
    "wof:placetype":"venue"
},
  "geometry": {"coordinates":[-1.931802,52.280361],"type":"Point"}
}