{
  "type": "Feature",
  "properties": {
    "iso:country":"GB",
    "sg:address":"Halsteads Close Industrial Estate, Dove Holes",
    "sg:city":"Buxton",
    "sg:classifiers":[
        {
            "category":"Retail",
            "subcategory":"Auto Repair",
            "type":"Services"
        }
    ],
    "sg:phone":"+44 1298 816122",
    "sg:postcode":"SK17 8BP",
    "sg:province":"Derbyshire",
    "sg:tags":[
        "body",
        "car"
    ],
    "wof:name":"Fletchers Accident Repair Centre",
    "wof:placetype":"venue"
},
  "geometry": {"coordinates":[-1.886569,53.302528],"type":"Point"}
}