{
  "type": "Feature",
  "properties": {
    "addr:full":"260 Newmarket Road Cambridge Cambridgeshire CB5 8JL",
    "addr:housenumber":"260",
    "addr:postcode":"cb5 8jl",
    "addr:street":"Newmarket Road",
    "iso:country":"GB",
    "sg:address":"260 Newmarket Road",
    "sg:city":"Cambridge",
    "sg:classifiers":[
        {
            "category":"Shopping",
            "subcategory":"Mobile Phones",
            "type":"Retail Goods"
        },
        {
            "category":"Professional",
            "subcategory":"Business Services",
            "type":"Services"
        },
        {
            "category":"Communications",
            "type":"Services"
        }
    ],
    "sg:phone":"+44 1223 462482",
    "sg:postcode":"CB5 8JL",
    "sg:province":"Cambridgeshire",
    "sg:tags":[
        "import",
        "export",
        "telecommunication",
        "agent"
    ],
    "wof:name":"Mobile Phone Centre",
    "wof:placetype":"venue"
},
  "geometry": {"coordinates":[0.1478579938,52.2113990784],"type":"Point"}
}