{
  "type": "Feature",
  "properties": {
    "iso:country":"GB",
    "sg:address":"Parsonage Street",
    "sg:city":"Halstead",
    "sg:classifiers":[
        {
            "category":"Home & Garden",
            "subcategory":"Household Appliances",
            "type":"Retail Goods"
        }
    ],
    "sg:phone":"+44 1787 474703",
    "sg:postcode":"CO9 1EZ",
    "sg:province":"Essex",
    "sg:tags":[
        "domestic",
        "centre"
    ],
    "wof:name":"Blythe Electrical Appliances",
    "wof:placetype":"venue"
},
  "geometry": {"coordinates":[0.6396250129,51.9401664734],"type":"Point"}
}