{
  "type": "Feature",
  "properties": {
    "addr:full":"2 Woodlea View, Yeadon Leeds West Yorkshire LS19 7LS",
    "addr:housenumber":"2",
    "addr:postcode":"ls19 7ls",
    "addr:street":"Woodlea View Yeadon Leeds West",
    "iso:country":"GB",
    "sg:address":"2 Woodlea View, Yeadon",
    "sg:city":"Leeds",
    "sg:classifiers":[
        {
            "category":"Building & Trades",
            "subcategory":"Landscaping Services",
            "type":"Services"
        }
    ],
    "sg:phone":"+44 113 250 8289",
    "sg:postcode":"LS19 7LS",
    "sg:province":"West Yorkshire",
    "sg:tags":[
        "gardening"
    ],
    "wof:name":"Aireborough Home & Garden Services",
    "wof:placetype":"venue"
},
  "geometry": {"coordinates":[-1.700958,53.858242],"type":"Point"}
}