{
  "type": "Feature",
  "properties": {
    "addr:full":"103 Chorley Road, Swinton Manchester Greater Manchester M27 4AA",
    "addr:housenumber":"103",
    "addr:postcode":"m27 4aa",
    "addr:street":"Chorley Road",
    "iso:country":"GB",
    "sg:address":"103 Chorley Road, Swinton",
    "sg:city":"Manchester",
    "sg:classifiers":[
        {
            "category":"Professional",
            "subcategory":"Employment Agencies",
            "type":"Services"
        }
    ],
    "sg:phone":"+44 161 848 8440",
    "sg:postcode":"M27 4AA",
    "sg:province":"Greater Manchester",
    "sg:tags":[
        "consultant"
    ],
    "wof:name":"Chess Consultants (U K) Ltd.",
    "wof:placetype":"venue"
},
  "geometry": {"coordinates":[-2.3367660046,53.5106468201],"type":"Point"}
}