{
  "type": "Feature",
  "properties": {
    "addr:full":"31 Rodney Gardens, Eastcote Pinner Greater London HA5 2RT",
    "addr:housenumber":"31",
    "addr:postcode":"ha5 2rt",
    "addr:street":"Rodney Gardens",
    "iso:country":"GB",
    "sg:address":"31 Rodney Gardens, Eastcote",
    "sg:city":"Pinner",
    "sg:classifiers":[
        {
            "category":"Real Estate",
            "subcategory":"Architect",
            "type":"Services"
        }
    ],
    "sg:phone":"+44 20 8429 0224",
    "sg:postcode":"HA5 2RT",
    "sg:province":"Greater London",
    "sg:tags":[
        "architectural"
    ],
    "wof:name":"Oakleaf Designs Ltd.",
    "wof:placetype":"venue"
},
  "geometry": {"coordinates":[-0.398945,51.587513],"type":"Point"}
}