{
  "type": "Feature",
  "properties": {
    "iso:country":"GB",
    "sg:address":"7 Newcroft Drive, Edgeley",
    "sg:city":"Stockport",
    "sg:classifiers":[
        {
            "category":"Professional",
            "subcategory":"Computer Services",
            "type":"Services"
        }
    ],
    "sg:phone":"+44 161 480 8621",
    "sg:postcode":"SK3 9RY",
    "sg:province":"Cheshire",
    "sg:tags":[
        "system",
        "software"
    ],
    "wof:name":"Dinsgrove Limited",
    "wof:placetype":"venue"
},
  "geometry": {"coordinates":[-2.173968,53.397179],"type":"Point"}
}