{
  "type": "Feature",
  "properties": {
    "iso:country":"GB",
    "sg:address":"34 Salop St",
    "sg:city":"Penarth",
    "sg:classifiers":[
        {
            "category":"Professional",
            "subcategory":"Lawyer & Legal Services",
            "type":"Services"
        }
    ],
    "sg:phone":"+44 29 2070 8407",
    "sg:postcode":"CF64 1HH",
    "sg:province":"The Vale of Glamorgan",
    "sg:tags":[
        "advice",
        "counselling"
    ],
    "wof:name":"Churches Counselling Service In Wales The",
    "wof:placetype":"venue"
},
  "geometry": {"coordinates":[-3.1728448868,51.4406700134],"type":"Point"}
}