{
  "type": "Feature",
  "properties": {
    "addr:full":"354 Rayleigh Road, Eastwood Leigh-on-sea Essex SS9 5PU",
    "addr:housenumber":"354",
    "addr:postcode":"ss9 5pu",
    "addr:street":"Rayleigh Road",
    "iso:country":"GB",
    "sg:address":"354 Rayleigh Road, Eastwood",
    "sg:city":"Leigh-on-sea",
    "sg:classifiers":[
        {
            "category":"Travel",
            "subcategory":"Travel Agent",
            "type":"Entertainment"
        }
    ],
    "sg:phone":"+44 1702 421747",
    "sg:postcode":"SS9 5PU",
    "sg:province":"Essex",
    "wof:name":"Travel House of Eastwood Ltd.",
    "wof:placetype":"venue"
},
  "geometry": {"coordinates":[0.6499490142,51.5700073242],"type":"Point"}
}