{
  "type": "Feature",
  "properties": {
    "addr:full":"97 Swan Street, Sible Hedingham Halstead Essex CO9 3HP",
    "addr:housenumber":"97",
    "addr:postcode":"co9 3hp",
    "addr:street":"Swan Street",
    "iso:country":"GB",
    "sg:address":"97 Swan Street, Sible Hedingham",
    "sg:city":"Halstead",
    "sg:classifiers":[
        {
            "category":"Farming",
            "subcategory":"Fish & Marine Products",
            "type":"Manufacturing & Wholesale Goods"
        },
        {
            "category":"Food & Beverages",
            "subcategory":"Meat & Fish",
            "type":"Retail Goods"
        }
    ],
    "sg:phone":"+44 1787 460278",
    "sg:postcode":"CO9 3HP",
    "sg:province":"Essex",
    "sg:tags":[
        "fishmonger",
        "butcher"
    ],
    "wof:name":"D R Earey & Son",
    "wof:placetype":"venue"
},
  "geometry": {"coordinates":[0.593151,51.975922],"type":"Point"}
}