{
  "type": "Feature",
  "properties": {
    "iso:country":"GB",
    "sg:address":"Steamboat Quay, Fraserburgh",
    "sg:city":"Aberdeen",
    "sg:classifiers":[
        {
            "category":"Shopping",
            "subcategory":"Crafts & Fabrics",
            "type":"Retail Goods"
        }
    ],
    "sg:phone":"+44 1346 518461",
    "sg:postcode":"AB43 9EE",
    "sg:province":"Aberdeenshire",
    "sg:tags":[
        "netting"
    ],
    "wof:name":"T Nets",
    "wof:placetype":"venue"
},
  "geometry": {"coordinates":[-2.015844,57.69442],"type":"Point"}
}