{
  "type": "Feature",
  "properties": {
    "iso:country":"GB",
    "sg:address":"78 Oldbury Road",
    "sg:city":"Rowley Regis",
    "sg:classifiers":[
        {
            "category":"Shopping",
            "subcategory":"Bicycles & Sporting Goods",
            "type":"Retail Goods"
        }
    ],
    "sg:phone":"+44 121 559 0701",
    "sg:postcode":"B65 0JS",
    "sg:province":"West Midlands",
    "sg:tags":[
        "equipment",
        "leisure"
    ],
    "wof:name":"Rocky Cove",
    "wof:placetype":"venue"
},
  "geometry": {"coordinates":[-2.03571,52.477695],"type":"Point"}
}