{
  "type": "Feature",
  "properties": {
    "iso:country":"GB",
    "sg:address":"Tolney Lane",
    "sg:city":"Newark",
    "sg:classifiers":[
        {
            "category":"Wholesale",
            "subcategory":"Scrap",
            "type":"Manufacturing & Wholesale Goods"
        }
    ],
    "sg:postcode":"NG24 1DB",
    "sg:province":"Nottinghamshire",
    "sg:tags":[
        "breaker",
        "dismantlers"
    ],
    "wof:name":"Thomas W Crowden",
    "wof:placetype":"venue"
},
  "geometry": {"coordinates":[-0.816615,53.077423],"type":"Point"}
}