{
  "type": "Feature",
  "properties": {
    "iso:country":"GB",
    "sg:address":"630 Cranbrook Road",
    "sg:city":"Ilford",
    "sg:classifiers":[
        {
            "category":"Home & Garden",
            "subcategory":"Garden Supply",
            "type":"Retail Goods"
        },
        {
            "category":"Building & Trades",
            "subcategory":"Construction",
            "type":"Services"
        }
    ],
    "sg:phone":"+44 20 8554 5716",
    "sg:postcode":"IG6 1HJ",
    "sg:province":"Essex",
    "sg:tags":[
        "builder",
        "centre"
    ],
    "wof:name":"A Houghton & Co. Ltd.",
    "wof:placetype":"venue"
},
  "geometry": {"coordinates":[0.074028,51.581318],"type":"Point"}
}