{
  "type": "Feature",
  "properties": {
    "addr:full":"Avondale Business Centre, Woodland Way, Kingswood Bristol City of Bristol BS15 1AW",
    "addr:postcode":"bs15 1aw",
    "addr:street":"Woodland Way",
    "iso:country":"GB",
    "sg:address":"Avondale Business Centre, Woodland Way, Kingswood",
    "sg:city":"Bristol",
    "sg:classifiers":[
        {
            "category":"Social Services",
            "subcategory":"Job Training",
            "type":"Services"
        }
    ],
    "sg:phone":"+44 117 914 5510",
    "sg:postcode":"BS15 1AW",
    "sg:province":"City of Bristol",
    "sg:tags":[
        "technology",
        "management",
        "traffic"
    ],
    "wof:name":"Dok-Tek Systems Ltd.",
    "wof:placetype":"venue"
},
  "geometry": {"coordinates":[-2.515534,51.471107],"type":"Point"}
}