{
  "type": "Feature",
  "properties": {
    "iso:country":"GB",
    "sg:address":"Day House Farm, Hillesley",
    "sg:city":"Wotton-under-edge",
    "sg:classifiers":[
        {
            "category":"Farming",
            "subcategory":"Livestock Farm",
            "type":"Manufacturing & Wholesale Goods"
        }
    ],
    "sg:phone":"+44 1453 843150",
    "sg:postcode":"GL12 7QY",
    "sg:province":"Gloucestershire",
    "sg:tags":[
        "others"
    ],
    "wof:name":"J J & V M Tewkesbury",
    "wof:placetype":"venue"
},
  "geometry": {"coordinates":[-2.3518939018,51.6389846802],"type":"Point"}
}