{
  "type": "Feature",
  "properties": {
    "addr:full":"102 Everton Road Lymington Hampshire SO41 0FD",
    "addr:housenumber":"102",
    "addr:postcode":"so41 0fd",
    "addr:street":"Everton Road",
    "iso:country":"GB",
    "sg:address":"102 Everton Road",
    "sg:city":"Lymington",
    "sg:classifiers":[
        {
            "category":"Military Area",
            "subcategory":"Air Force Base",
            "type":"Public Place"
        }
    ],
    "sg:postcode":"SO41 0FD",
    "sg:province":"Hampshire",
    "sg:tags":[
        "taxi",
        "hire",
        "private"
    ],
    "wof:name":"Hordle Private Hire",
    "wof:placetype":"venue"
},
  "geometry": {"coordinates":[-1.613529,50.75597],"type":"Point"}
}