{
  "type": "Feature",
  "properties": {
    "addr:full":"Unit 7 Moorview Indust Est Okehampton Devon EX20 3LP",
    "addr:housenumber":"unit 7",
    "addr:postcode":"ex20 3lp",
    "addr:street":"Moorview Indust Est",
    "iso:country":"GB",
    "sg:address":"Unit 7 Moorview Indust Est",
    "sg:city":"Okehampton",
    "sg:classifiers":[
        {
            "category":"Professional",
            "subcategory":"Business Services",
            "type":"Services"
        }
    ],
    "sg:phone":"+44 1837 810877",
    "sg:postcode":"EX20 3LP",
    "sg:province":"Devon",
    "sg:tags":[
        "house",
        "mailing"
    ],
    "wof:name":"Salestrac Ltd",
    "wof:placetype":"venue"
},
  "geometry": {"coordinates":[-4.078247,50.815018],"type":"Point"}
}