{
  "type": "Feature",
  "properties": {
    "iso:country":"GB",
    "sg:address":"84 High Street",
    "sg:city":"Arbroath",
    "sg:classifiers":[
        {
            "category":"Banks & Credit Unions",
            "subcategory":"Financial Services",
            "type":"Services"
        }
    ],
    "sg:phone":"+44 1241 870717",
    "sg:postcode":"DD11 1HL",
    "sg:province":"Angus",
    "sg:tags":[
        "adviser",
        "independent"
    ],
    "wof:name":"Pennant Independent Financial Services Ltd",
    "wof:placetype":"venue"
},
  "geometry": {"coordinates":[-2.5816659927,56.5585517883],"type":"Point"}
}