{
  "type": "Feature",
  "properties": {
    "addr:full":"Knowle Braunton Devon EX33 2NA",
    "addr:postcode":"ex33 2na",
    "iso:country":"GB",
    "sg:address":"Knowle",
    "sg:city":"Braunton",
    "sg:classifiers":[
        {
            "category":"Wholesale",
            "subcategory":"Non-durable Goods",
            "type":"Manufacturing & Wholesale Goods"
        }
    ],
    "sg:postcode":"EX33 2NA",
    "sg:province":"Devon",
    "sg:tags":[
        "carry",
        "cash"
    ],
    "wof:name":"Braunton Wholesale",
    "wof:placetype":"venue"
},
  "geometry": {"coordinates":[-4.154759,51.11219],"type":"Point"}
}