{
  "type": "Feature",
  "properties": {
    "iso:country":"GB",
    "sg:address":"Unit 6 Master Close, Master Park",
    "sg:city":"Oxted",
    "sg:classifiers":[
        {
            "category":"Building & Trades",
            "subcategory":"Construction",
            "type":"Services"
        }
    ],
    "sg:phone":"+44 1883 716657",
    "sg:postcode":"RH8 9NA",
    "sg:province":"Surrey",
    "sg:tags":[
        "decorator",
        "painter"
    ],
    "wof:name":"C & C Southern Property Services",
    "wof:placetype":"venue"
},
  "geometry": {"coordinates":[-0.0064790002,51.2580337524],"type":"Point"}
}