{
  "type": "Feature",
  "properties": {
    "addr:full":"Huyton Training Workshop, Link Road, Huyton Liverpool Merseyside L36 6AP",
    "addr:postcode":"l36 6ap",
    "addr:street":"Link Road",
    "iso:country":"GB",
    "sg:address":"Huyton Training Workshop, Link Road, Huyton",
    "sg:city":"Liverpool",
    "sg:classifiers":[
        {
            "category":"Education",
            "subcategory":"School",
            "type":"Public Place"
        }
    ],
    "sg:postcode":"L36 6AP",
    "sg:province":"Merseyside",
    "sg:tags":[
        "local",
        "authority"
    ],
    "wof:name":"The Autocrime Rehabilitation And Training Scheme",
    "wof:placetype":"venue"
},
  "geometry": {"coordinates":[-2.82051,53.405918],"type":"Point"}
}