{
  "type": "Feature",
  "properties": {
    "iso:country":"GB",
    "sg:address":"115 Butt Road",
    "sg:city":"Colchester",
    "sg:classifiers":[
        {
            "category":"Shopping",
            "type":"Retail Goods"
        }
    ],
    "sg:phone":"+44 1206 764474",
    "sg:postcode":"CO3 3DL",
    "sg:province":"Essex",
    "sg:tags":[
        "part",
        "accessory"
    ],
    "wof:name":"Wilco Motor Spares Ltd.",
    "wof:placetype":"venue"
},
  "geometry": {"coordinates":[0.891602993,51.883605957],"type":"Point"}
}