{
  "type": "Feature",
  "properties": {
    "addr:full":"Newbury Road, Enham Alamein Andover Hampshire SP11 6JS",
    "addr:postcode":"sp11 6js",
    "addr:street":"Newbury Road",
    "iso:country":"GB",
    "sg:address":"Newbury Road, Enham Alamein",
    "sg:city":"Andover",
    "sg:classifiers":[
        {
            "category":"Shopping",
            "subcategory":"Stationery & Office Supplies",
            "type":"Retail Goods"
        }
    ],
    "sg:phone":"+44 1264 349400",
    "sg:postcode":"SP11 6JS",
    "sg:province":"Hampshire",
    "sg:tags":[
        "equipment"
    ],
    "wof:name":"Office Corp Furniture Ltd.",
    "wof:placetype":"venue"
},
  "geometry": {"coordinates":[-1.476875,51.243927],"type":"Point"}
}