{
  "type": "Feature",
  "properties": {
    "addr:full":"81 Shrewsbury Rd Market Drayton Shropshire TF9 3DN",
    "addr:housenumber":"81",
    "addr:postcode":"tf9 3dn",
    "addr:street":"Shrewsbury Rd",
    "iso:country":"GB",
    "sg:address":"81 Shrewsbury Rd",
    "sg:city":"Market Drayton",
    "sg:classifiers":[
        {
            "category":"Health Services",
            "subcategory":"Dentist",
            "type":"Services"
        }
    ],
    "sg:phone":"+44 1630 654344",
    "sg:postcode":"TF9 3DN",
    "sg:province":"Shropshire",
    "sg:tags":[
        "technician",
        "dental"
    ],
    "wof:name":"D Meakin",
    "wof:placetype":"venue"
},
  "geometry": {"coordinates":[-2.493476,52.901016],"type":"Point"}
}