{
  "type": "Feature",
  "properties": {
    "iso:country":"GB",
    "sg:address":"The Star Centre, Oxted Library, Gresham Road",
    "sg:city":"Oxted",
    "sg:classifiers":[
        {
            "category":"Organizations",
            "subcategory":"Non-profit Organization",
            "type":"Services"
        }
    ],
    "sg:phone":"+44 1883 722593",
    "sg:postcode":"RH8 0BQ",
    "sg:province":"Surrey",
    "sg:tags":[
        "organisation",
        "voluntary",
        "charity"
    ],
    "wof:name":"Tandridge Voluntary Service Council",
    "wof:placetype":"venue"
},
  "geometry": {"coordinates":[-0.00468,51.254894],"type":"Point"}
}