{
  "type": "Feature",
  "properties": {
    "addr:full":"35 Yeaman Shore Dundee Dundee City DD1 4BU",
    "addr:housenumber":"35",
    "addr:postcode":"dd1 4bu",
    "addr:street":"Yeaman Shore",
    "iso:country":"GB",
    "sg:address":"35 Yeaman Shore",
    "sg:city":"Dundee",
    "sg:classifiers":[
        {
            "category":"Insurance",
            "subcategory":"Insurance Agent",
            "type":"Services"
        }
    ],
    "sg:phone":"+44 1382 200587",
    "sg:postcode":"DD1 4BU",
    "sg:province":"Dundee City",
    "wof:name":"The Standard Life Assurance Co.",
    "wof:placetype":"venue"
},
  "geometry": {"coordinates":[-2.9714319706,56.4583091736],"type":"Point"}
}