{
  "type": "Feature",
  "properties": {
    "iso:country":"GB",
    "sg:address":"15 The Rodings",
    "sg:city":"Upminster",
    "sg:classifiers":[
        {
            "category":"Shopping",
            "subcategory":"Clothing, Apparel, & Fashions",
            "type":"Retail Goods"
        }
    ],
    "sg:phone":"+44 1708 780629",
    "sg:postcode":"RM14 1RL",
    "sg:province":"Essex",
    "sg:tags":[
        "workwear",
        "protective"
    ],
    "wof:name":"R W H Supplies",
    "wof:placetype":"venue"
},
  "geometry": {"coordinates":[0.26329,51.569088],"type":"Point"}
}