{
  "type": "Feature",
  "properties": {
    "addr:full":"North Cottages, Farnham Road, Farnham Royal Slough Berkshire SL2 3AS",
    "addr:postcode":"sl2 3as",
    "addr:street":"North Cottages Farnham Road",
    "iso:country":"GB",
    "sg:address":"North Cottages, Farnham Road, Farnham Royal",
    "sg:city":"Slough",
    "sg:classifiers":[
        {
            "category":"Shopping",
            "subcategory":"News",
            "type":"Retail Goods"
        }
    ],
    "sg:phone":"+44 1753 644186",
    "sg:postcode":"SL2 3AS",
    "sg:province":"Berkshire",
    "sg:tags":[
        "newsagent"
    ],
    "wof:name":"Farnham Royal News",
    "wof:placetype":"venue"
},
  "geometry": {"coordinates":[-0.6166840196,51.5395545959],"type":"Point"}
}