{
  "type": "Feature",
  "properties": {
    "addr:full":"47 Denham Avenue Llanelli Carmarthenshire SA15 4DB",
    "addr:housenumber":"47",
    "addr:postcode":"sa15 4db",
    "addr:street":"Denham Avenue",
    "iso:country":"GB",
    "sg:address":"47 Denham Avenue",
    "sg:city":"Llanelli",
    "sg:classifiers":[
        {
            "category":"Professional",
            "type":"Services"
        }
    ],
    "sg:postcode":"SA15 4DB",
    "sg:province":"Carmarthenshire",
    "sg:tags":[
        "reflexologists"
    ],
    "wof:name":"Christine Williams Reflexologist",
    "wof:placetype":"venue"
},
  "geometry": {"coordinates":[-4.1800489426,51.6866493225],"type":"Point"}
}