{
  "type": "Feature",
  "properties": {
    "addr:full":"70 Pomphlett Road Plymouth Devon PL9 7BN",
    "addr:housenumber":"70",
    "addr:postcode":"pl9 7bn",
    "addr:street":"Pomphlett Road",
    "iso:country":"GB",
    "sg:address":"70 Pomphlett Road",
    "sg:city":"Plymouth",
    "sg:classifiers":[
        {
            "category":"Retail",
            "subcategory":"Veterinary Services",
            "type":"Services"
        }
    ],
    "sg:phone":"+44 1752 492293",
    "sg:postcode":"PL9 7BN",
    "sg:province":"Devon",
    "sg:tags":[
        "surgeon",
        "activity"
    ],
    "wof:name":"Bower Hunt Youngs Coulson & O'Shea",
    "wof:placetype":"venue"
},
  "geometry": {"coordinates":[-4.096997,50.364433],"type":"Point"}
}