{
  "type": "Feature",
  "properties": {
    "iso:country":"GB",
    "sg:address":"Seamer Road",
    "sg:city":"Scarborough",
    "sg:classifiers":[
        {
            "category":"Home & Garden",
            "subcategory":"Garden Supply",
            "type":"Retail Goods"
        }
    ],
    "sg:phone":"+44 1723 361814",
    "sg:postcode":"YO12 4LW",
    "sg:province":"North Yorkshire",
    "sg:tags":[
        "nursery",
        "centre"
    ],
    "wof:name":"Deans Garden Centre",
    "wof:placetype":"venue"
},
  "geometry": {"coordinates":[-0.416144,54.275265],"type":"Point"}
}