{
  "type": "Feature",
  "properties": {
    "addr:full":"17a Arden Crescent London Greater London E14 9WA",
    "addr:housenumber":"17a",
    "addr:postcode":"e14 9wa",
    "addr:street":"Arden Crescent",
    "iso:country":"GB",
    "sg:address":"17a Arden Crescent",
    "sg:city":"London",
    "sg:classifiers":[
        {
            "category":"Organizations",
            "subcategory":"Community Association",
            "type":"Services"
        }
    ],
    "sg:phone":"+44 20 7538 0881",
    "sg:postcode":"E14 9WA",
    "sg:province":"Greater London",
    "sg:tags":[
        "co-operatives",
        "society",
        "housing",
        "trust"
    ],
    "wof:name":"The Samuel Lewis Housing Trust",
    "wof:placetype":"venue"
},
  "geometry": {"coordinates":[-0.022812,51.493065],"type":"Point"}
}