{
  "type": "Feature",
  "properties": {
    "addr:full":"Checkbar, Nigg Aberdeen Aberdeen City AB12 4LQ",
    "addr:postcode":"ab12 4lq",
    "iso:country":"GB",
    "sg:address":"Checkbar, Nigg",
    "sg:city":"Aberdeen",
    "sg:classifiers":[
        {
            "category":"Home & Garden",
            "subcategory":"Garden Supply",
            "type":"Retail Goods"
        }
    ],
    "sg:phone":"+44 1224 783333",
    "sg:postcode":"AB12 4LQ",
    "sg:province":"Aberdeen City",
    "sg:tags":[
        "nursery",
        "centre"
    ],
    "wof:name":"Marywell Garden & Pet Centre",
    "wof:placetype":"venue"
},
  "geometry": {"coordinates":[-2.1182699203,57.0827407837],"type":"Point"}
}