{
  "type": "Feature",
  "properties": {
    "addr:full":"Poets Walk Penrith Cumbria CA11 7HJ",
    "addr:postcode":"ca11 7hj",
    "addr:street":"Poets Walk",
    "iso:country":"GB",
    "sg:address":"Poets Walk",
    "sg:city":"Penrith",
    "sg:classifiers":[
        {
            "category":"Building & Trades",
            "subcategory":"Construction",
            "type":"Services"
        }
    ],
    "sg:postcode":"CA11 7HJ",
    "sg:province":"Cumbria",
    "sg:tags":[
        "builder"
    ],
    "wof:name":"A Roper & Sons Ltd",
    "wof:placetype":"venue"
},
  "geometry": {"coordinates":[-2.754873991,54.6641311646],"type":"Point"}
}