{
  "type": "Feature",
  "properties": {
    "iso:country":"GB",
    "sg:address":"49-50 Peascod St",
    "sg:city":"Windsor",
    "sg:classifiers":[
        {
            "category":"Museum",
            "subcategory":"Art Museum",
            "type":"Entertainment"
        }
    ],
    "sg:phone":"+44 1753 833773",
    "sg:postcode":"SL4 1DE",
    "sg:province":"Berkshire",
    "sg:tags":[
        "gallery"
    ],
    "wof:name":"Crown Jewels Exhibitions",
    "wof:placetype":"venue"
},
  "geometry": {"coordinates":[-0.611358,51.480843],"type":"Point"}
}