{
  "type": "Feature",
  "properties": {
    "iso:country":"GB",
    "sg:address":"The Dome, Doncaster Leisure Park Bawtry Ro",
    "sg:city":"Doncaster",
    "sg:classifiers":[
        {
            "category":"Sports & Exercise",
            "subcategory":"Swimming Pool",
            "type":"Entertainment"
        }
    ],
    "sg:phone":"+44 1302 370777",
    "sg:postcode":"DN4 7PD",
    "sg:province":"South Yorkshire",
    "wof:name":"Doncaster Leisure (Management) Ltd.",
    "wof:placetype":"venue"
},
  "geometry": {"coordinates":[-1.06257,53.49398],"type":"Point"}
}