{
  "type": "Feature",
  "properties": {
    "addr:full":"86 Western Lea Crediton Devon EX17 3JE",
    "addr:housenumber":"86",
    "addr:postcode":"ex17 3je",
    "addr:street":"Western Lea",
    "iso:country":"GB",
    "sg:address":"86 Western Lea",
    "sg:city":"Crediton",
    "sg:classifiers":[
        {
            "category":"Home & Garden",
            "subcategory":"Carpets & Floor Coverings",
            "type":"Retail Goods"
        }
    ],
    "sg:postcode":"EX17 3JE",
    "sg:province":"Devon",
    "sg:tags":[
        "carpets",
        "retailer",
        "rug",
        "matting"
    ],
    "wof:name":"HOME CHOICE CARPETS",
    "wof:placetype":"venue"
},
  "geometry": {"coordinates":[-3.6755139828,50.7908744812],"type":"Point"}
}