{
  "type": "Feature",
  "properties": {
    "addr:full":"3/5 Rachel Street, Dryden Street Liverpool Merseyside L5 5BR",
    "addr:housenumber":"3 / 5",
    "addr:postcode":"l5 5br",
    "addr:street":"Rachel Street Dryden Street",
    "iso:country":"GB",
    "sg:address":"3/5 Rachel Street, Dryden Street",
    "sg:city":"Liverpool",
    "sg:classifiers":[
        {
            "category":"Building & Trades",
            "subcategory":"Construction",
            "type":"Services"
        }
    ],
    "sg:phone":"+44 151 207 1666",
    "sg:postcode":"L5 5BR",
    "sg:province":"Merseyside",
    "sg:tags":[
        "platform",
        "work",
        "scaffolding"
    ],
    "wof:name":"Victoria Scaffolding North West Ltd.",
    "wof:placetype":"venue"
},
  "geometry": {"coordinates":[-2.98037,53.419819],"type":"Point"}
}