{
  "type": "Feature",
  "properties": {
    "addr:full":"Lake Yard Poole Dorset BH15 4DT",
    "addr:postcode":"bh15 4dt",
    "addr:street":"Lake",
    "iso:country":"GB",
    "sg:address":"Lake Yard",
    "sg:city":"Poole",
    "sg:classifiers":[
        {
            "category":"Autos & Motor Vehicles",
            "subcategory":"Boat Sales",
            "type":"Retail Goods"
        },
        {
            "category":"Retail",
            "subcategory":"Event Space",
            "type":"Services"
        }
    ],
    "sg:phone":"+44 1202 674534",
    "sg:postcode":"BH15 4DT",
    "sg:province":"Dorset",
    "wof:name":"Dorset Yacht Co",
    "wof:placetype":"venue"
},
  "geometry": {"coordinates":[-2.0208659172,50.7136039734],"type":"Point"}
}