{
  "type": "Feature",
  "properties": {
    "iso:country":"GB",
    "sg:address":"11 Oak Lane",
    "sg:city":"Bradford",
    "sg:classifiers":[
        {
            "category":"Food & Beverages",
            "subcategory":"Bakery",
            "type":"Retail Goods"
        }
    ],
    "sg:phone":"+44 1274 545311",
    "sg:postcode":"BD9 4PU",
    "sg:province":"West Yorkshire",
    "sg:tags":[
        "baker"
    ],
    "wof:name":"Chubbs",
    "wof:placetype":"venue"
},
  "geometry": {"coordinates":[-1.768617,53.809113],"type":"Point"}
}