{
  "type": "Feature",
  "properties": {
    "addr:full":"The Old Tanks, Penpole Lane, Shirehampton Bristol City of Bristol BS11 0EA",
    "addr:postcode":"bs11 0ea",
    "addr:street":"Penpole Lane",
    "iso:country":"GB",
    "sg:address":"The Old Tanks, Penpole Lane, Shirehampton",
    "sg:city":"Bristol",
    "sg:classifiers":[
        {
            "category":"Wholesale",
            "subcategory":"Sporting Goods",
            "type":"Manufacturing & Wholesale Goods"
        }
    ],
    "sg:phone":"+44 117 982 9057",
    "sg:postcode":"BS11 0EA",
    "sg:province":"City of Bristol",
    "sg:tags":[
        "mnfr",
        "sport",
        "equipment"
    ],
    "wof:name":"Karakal Worldwide Ltd.",
    "wof:placetype":"venue"
},
  "geometry": {"coordinates":[-2.669549942,51.4909706116],"type":"Point"}
}