{
  "type": "Feature",
  "properties": {
    "iso:country":"GB",
    "sg:address":"Ridgefield Mill, Ridgefield Street",
    "sg:city":"Manchester",
    "sg:classifiers":[
        {
            "category":"Communications",
            "subcategory":"Film & Video Production",
            "type":"Services"
        }
    ],
    "sg:postcode":"M35 0HJ",
    "sg:province":"Lancashire",
    "sg:tags":[
        "product",
        "wire",
        "mfrs"
    ],
    "wof:name":"A M P",
    "wof:placetype":"venue"
},
  "geometry": {"coordinates":[-2.167204,53.505539],"type":"Point"}
}