{
  "type": "Feature",
  "properties": {
    "iso:country":"GB",
    "sg:address":"Chelsea Wks, 72a Moorland Rd",
    "sg:city":"Stoke-on-trent",
    "sg:classifiers":[
        {
            "category":"Shopping",
            "subcategory":"Crafts & Fabrics",
            "type":"Retail Goods"
        }
    ],
    "sg:postcode":"ST6 1DY",
    "sg:province":"Staffordshire",
    "sg:tags":[
        "ceramic"
    ],
    "wof:name":"Ceramic Design Associates",
    "wof:placetype":"venue"
},
  "geometry": {"coordinates":[-2.19305,53.046371],"type":"Point"}
}