{
  "type": "Feature",
  "properties": {
    "addr:full":"104 Shoreditch High St Whitechapel Greater London E1 6JN",
    "addr:housenumber":"104",
    "addr:postcode":"e1 6jn",
    "addr:street":"Shoreditch High St",
    "iso:country":"GB",
    "sg:address":"104 Shoreditch High St",
    "sg:city":"Whitechapel",
    "sg:classifiers":[
        {
            "category":"Professional",
            "type":"Services"
        }
    ],
    "sg:phone":"+44 20 7729 3911",
    "sg:postcode":"E1 6JN",
    "sg:province":"Greater London",
    "sg:tags":[
        "caterer"
    ],
    "wof:name":"Cafe Dune",
    "wof:placetype":"venue"
},
  "geometry": {"coordinates":[-0.077799,51.52261],"type":"Point"}
}