{
  "type": "Feature",
  "properties": {
    "addr:full":"5-9 Kingsleigh Road Stockport Cheshire SK4 3QF",
    "addr:housenumber":"5-9",
    "addr:postcode":"sk4 3qf",
    "addr:street":"Kingsleigh Road",
    "iso:country":"GB",
    "sg:address":"5-9 Kingsleigh Road",
    "sg:city":"Stockport",
    "sg:classifiers":[
        {
            "category":"Government",
            "subcategory":"Post Office",
            "type":"Public Place"
        }
    ],
    "sg:phone":"+44 161 431 3990",
    "sg:postcode":"SK4 3QF",
    "sg:province":"Cheshire",
    "wof:name":"Kingsleigh Road Post Office",
    "wof:placetype":"venue"
},
  "geometry": {"coordinates":[-2.198797,53.423092],"type":"Point"}
}