{
  "type": "Feature",
  "properties": {
    "addr:full":"166 Everton Road, Hordle Lymington Hampshire SO41 0HB",
    "addr:housenumber":"166",
    "addr:postcode":"so41 0hb",
    "addr:street":"Everton Road",
    "iso:country":"GB",
    "sg:address":"166 Everton Road, Hordle",
    "sg:city":"Lymington",
    "sg:classifiers":[
        {
            "category":"Building & Trades",
            "subcategory":"Construction",
            "type":"Services"
        }
    ],
    "sg:phone":"+44 1425 618481",
    "sg:postcode":"SO41 0HB",
    "sg:province":"Hampshire",
    "sg:tags":[
        "roofing",
        "contracting"
    ],
    "wof:name":"Browning Roofing Contractors",
    "wof:placetype":"venue"
},
  "geometry": {"coordinates":[-1.608591,50.753597],"type":"Point"}
}