{
  "type": "Feature",
  "properties": {
    "addr:full":"Bodmin Road Coventry Warwickshire CV2 5DB",
    "addr:postcode":"cv2 5db",
    "addr:street":"Bodmin Road",
    "iso:country":"GB",
    "sg:address":"Bodmin Road",
    "sg:city":"Coventry",
    "sg:classifiers":[
        {
            "category":"Manufacturing",
            "subcategory":"Metals",
            "type":"Manufacturing & Wholesale Goods"
        }
    ],
    "sg:phone":"+44 23 7660 2009",
    "sg:postcode":"CV2 5DB",
    "sg:province":"Warwickshire",
    "sg:tags":[
        "steel",
        "fabricator",
        "erectors"
    ],
    "wof:name":"Steel Construction Ltd",
    "wof:placetype":"venue"
},
  "geometry": {"coordinates":[-1.447924,52.41893],"type":"Point"}
}