{
  "type": "Feature",
  "properties": {
    "addr:full":"145 Victoria Road Aldershot Hampshire GU11 1JW",
    "addr:housenumber":"145",
    "addr:postcode":"gu11 1jw",
    "addr:street":"Victoria Road",
    "iso:country":"GB",
    "sg:address":"145 Victoria Road",
    "sg:city":"Aldershot",
    "sg:classifiers":[
        {
            "category":"Shopping",
            "subcategory":"Pets & Pet Supplies",
            "type":"Retail Goods"
        }
    ],
    "sg:phone":"+44 1252 876899",
    "sg:postcode":"GU11 1JW",
    "sg:province":"Hampshire",
    "sg:tags":[
        "shop"
    ],
    "wof:name":"Pet Emporium",
    "wof:placetype":"venue"
},
  "geometry": {"coordinates":[-0.7648140192,51.2483634949],"type":"Point"}
}