{
  "type": "Feature",
  "properties": {
    "addr:full":"85 Stopford Rd Plaistow Greater London E13 0NA",
    "addr:housenumber":"85",
    "addr:postcode":"e13 0na",
    "addr:street":"Stopford Rd",
    "iso:country":"GB",
    "sg:address":"85 Stopford Rd",
    "sg:city":"Plaistow",
    "sg:classifiers":[
        {
            "category":"Health Services",
            "subcategory":"Doctor",
            "type":"Services"
        }
    ],
    "sg:phone":"+44 20 8472 3901",
    "sg:postcode":"E13 0NA",
    "sg:province":"Greater London",
    "sg:tags":[
        "practitioners"
    ],
    "wof:name":"Choudhuri Dr B B",
    "wof:placetype":"venue"
},
  "geometry": {"coordinates":[0.022722,51.533581],"type":"Point"}
}