{
  "type": "Feature",
  "properties": {
    "addr:full":"5 Northgate St Aberystwyth Ceredigion SY23 2JS",
    "addr:housenumber":"5",
    "addr:postcode":"sy23 2js",
    "addr:street":"Northgate St",
    "iso:country":"GB",
    "sg:address":"5 Northgate St",
    "sg:city":"Aberystwyth",
    "sg:classifiers":[
        {
            "category":"Shopping",
            "subcategory":"Used Merchandise",
            "type":"Retail Goods"
        }
    ],
    "sg:postcode":"SY23 2JS",
    "sg:province":"Ceredigion",
    "sg:tags":[
        "shop",
        "second-hand"
    ],
    "wof:name":"Coates,Basil,",
    "wof:placetype":"venue"
},
  "geometry": {"coordinates":[-4.0801239014,52.4161605835],"type":"Point"}
}