{
  "type": "Feature",
  "properties": {
    "iso:country":"GB",
    "sg:address":"Priestlands Lane",
    "sg:city":"Sherborne",
    "sg:classifiers":[
        {
            "category":"Manufacturing",
            "subcategory":"Wood Products",
            "type":"Manufacturing & Wholesale Goods"
        },
        {
            "category":"Building & Trades",
            "subcategory":"Electrical",
            "type":"Services"
        }
    ],
    "sg:phone":"+44 1935 817444",
    "sg:postcode":"DT9 4HL",
    "sg:province":"Dorset",
    "sg:tags":[
        "equipment",
        "manufacturer",
        "lighting",
        "consultant"
    ],
    "wof:name":"Charles Lighting Ltd",
    "wof:placetype":"venue"
},
  "geometry": {"coordinates":[-2.518675,50.950981],"type":"Point"}
}