{
  "type": "Feature",
  "properties": {
    "addr:full":"19 Empire Close Biggleswade Bedfordshire SG18 8AF",
    "addr:housenumber":"19",
    "addr:postcode":"sg18 8af",
    "addr:street":"Empire Close",
    "iso:country":"GB",
    "sg:address":"19 Empire Close",
    "sg:city":"Biggleswade",
    "sg:classifiers":[
        {
            "category":"Personal",
            "type":"Services"
        },
        {
            "category":"Professional",
            "subcategory":"Art Services",
            "type":"Services"
        }
    ],
    "sg:postcode":"SG18 8AF",
    "sg:province":"Bedfordshire",
    "sg:tags":[
        "photographer",
        "wedding"
    ],
    "wof:name":"Reeves Photographic",
    "wof:placetype":"venue"
},
  "geometry": {"coordinates":[-0.2659690082,52.0845985413],"type":"Point"}
}