{
  "type": "Feature",
  "properties": {
    "addr:full":"Brigstock Rd Thornton Heath Surrey CR7 7JH",
    "addr:postcode":"cr7 7jh",
    "addr:street":"Brigstock Rd",
    "iso:country":"GB",
    "sg:address":"Brigstock Rd",
    "sg:city":"Thornton Heath",
    "sg:classifiers":[
        {
            "category":"Park",
            "type":"Public Place"
        },
        {
            "category":"Landmark",
            "subcategory":"Tourist Attraction",
            "type":"Public Place"
        }
    ],
    "sg:phone":"+44 20 8689 8201",
    "sg:postcode":"CR7 7JH",
    "sg:province":"Surrey",
    "sg:tags":[
        "garden",
        "interest"
    ],
    "wof:name":"Trumble Gardens",
    "wof:placetype":"venue"
},
  "geometry": {"coordinates":[-0.098864,51.398663],"type":"Point"}
}