{
  "type": "Feature",
  "properties": {
    "iso:country":"GB",
    "sg:address":"P O Box 2593",
    "sg:city":"Poole",
    "sg:classifiers":[
        {
            "category":"Banks & Credit Unions",
            "subcategory":"Investment Brokerage",
            "type":"Services"
        }
    ],
    "sg:phone":"+44 1202 623800",
    "sg:postcode":"BH16 6YW",
    "sg:province":"Dorset",
    "sg:tags":[
        "additive",
        "colouring",
        "flavouring"
    ],
    "wof:name":"Scanchem (UK) Ltd",
    "wof:placetype":"venue"
},
  "geometry": {"coordinates":[-2.072369,50.73354],"type":"Point"}
}