{
  "type": "Feature",
  "properties": {
    "addr:full":"109 7a Daimler Drive, Cospen Lane Industrial Estate Billingham Durham TS23 4JD",
    "addr:housenumber":"109 7a",
    "addr:postcode":"ts23 4jd",
    "addr:street":"Daimler Drive Cospen Lane Industrial Estate",
    "iso:country":"GB",
    "sg:address":"109 7a Daimler Drive, Cospen Lane Industrial Estate",
    "sg:city":"Billingham",
    "sg:classifiers":[
        {
            "category":"Professional",
            "subcategory":"Engineering",
            "type":"Services"
        }
    ],
    "sg:phone":"+44 1642 560790",
    "sg:postcode":"TS23 4JD",
    "sg:province":"Durham",
    "sg:tags":[
        "engineer",
        "mechanical"
    ],
    "wof:name":"G Hall Engineering Associates",
    "wof:placetype":"venue"
},
  "geometry": {"coordinates":[-1.2604739666,54.6105041504],"type":"Point"}
}