{
  "type": "Feature",
  "properties": {
    "addr:full":"Rear Of 351 Loxley Rd Sheffield South Yorkshire S6 4TH",
    "addr:postcode":"s6 4th",
    "addr:street":"Loxley Rd",
    "iso:country":"GB",
    "sg:address":"Rear Of 351 Loxley Rd",
    "sg:city":"Sheffield",
    "sg:classifiers":[
        {
            "category":"Retail",
            "subcategory":"Auto Repair",
            "type":"Services"
        }
    ],
    "sg:phone":"+44 114 234 9581",
    "sg:postcode":"S6 4TH",
    "sg:province":"South Yorkshire",
    "sg:tags":[
        "body",
        "car",
        "repairer",
        "sprayer",
        "painter"
    ],
    "wof:name":"M H Motors",
    "wof:placetype":"venue"
},
  "geometry": {"coordinates":[-1.52289,53.403118],"type":"Point"}
}