{
  "type": "Feature",
  "properties": {
    "iso:country":"GB",
    "sg:address":"64 Baxtergate",
    "sg:city":"Whitby",
    "sg:classifiers":[
        {
            "category":"Shopping",
            "subcategory":"Pharmacy",
            "type":"Retail Goods"
        }
    ],
    "sg:phone":"+44 1947 602219",
    "sg:postcode":"YO21 1BL",
    "sg:province":"North Yorkshire",
    "sg:tags":[
        "pharmacist",
        "chemist"
    ],
    "wof:name":"Boots the Chemist",
    "wof:placetype":"venue"
},
  "geometry": {"coordinates":[-0.6153290272,54.4856567383],"type":"Point"}
}