{
  "type": "Feature",
  "properties": {
    "addr:full":"10 Dale Street, Longwood Huddersfield West Yorkshire HD3 4TG",
    "addr:housenumber":"10",
    "addr:postcode":"hd3 4tg",
    "addr:street":"Dale Street;West",
    "iso:country":"GB",
    "sg:address":"10 Dale Street, Longwood",
    "sg:city":"Huddersfield",
    "sg:classifiers":[
        {
            "category":"Autos & Motor Vehicles",
            "subcategory":"Auto Supplies",
            "type":"Retail Goods"
        }
    ],
    "sg:postcode":"HD3 4TG",
    "sg:province":"West Yorkshire",
    "sg:tags":[
        "component"
    ],
    "wof:name":"Partsource Ltd.",
    "wof:placetype":"venue"
},
  "geometry": {"coordinates":[-1.8319590092,53.6441268921],"type":"Point"}
}