{
  "type": "Feature",
  "properties": {
    "addr:full":"Holwell Barton, Neopardy Crediton Devon EX17 5EP",
    "addr:housenumber":"holwell;neopardy",
    "addr:postcode":"ex17 5ep",
    "iso:country":"GB",
    "sg:address":"Holwell Barton, Neopardy",
    "sg:city":"Crediton",
    "sg:classifiers":[
        {
            "category":"Retail",
            "subcategory":"Repair Shop",
            "type":"Services"
        },
        {
            "category":"Wholesale",
            "subcategory":"Machinery & Supplies",
            "type":"Manufacturing & Wholesale Goods"
        }
    ],
    "sg:phone":"+44 1363 774209",
    "sg:postcode":"EX17 5EP",
    "sg:province":"Devon",
    "sg:tags":[
        "agricultural",
        "sale"
    ],
    "wof:name":"Farm Machines and Agricultural",
    "wof:placetype":"venue"
},
  "geometry": {"coordinates":[-3.725949049,50.7788391113],"type":"Point"}
}