{
  "type": "Feature",
  "properties": {
    "addr:full":"43 Hullbridge Road, South Woodham Ferrers Chelmsford Essex CM3 5NG",
    "addr:housenumber":"43",
    "addr:postcode":"cm3 5ng",
    "addr:street":"Hullbridge Road",
    "iso:country":"GB",
    "sg:address":"43 Hullbridge Road, South Woodham Ferrers",
    "sg:city":"Chelmsford",
    "sg:classifiers":[
        {
            "category":"Building & Trades",
            "subcategory":"Equipment Rental",
            "type":"Services"
        }
    ],
    "sg:postcode":"CM3 5NG",
    "sg:province":"Essex",
    "sg:tags":[
        "hire",
        "centre"
    ],
    "wof:name":"Popular Hire Service",
    "wof:placetype":"venue"
},
  "geometry": {"coordinates":[0.607404,51.650364],"type":"Point"}
}