{
  "type": "Feature",
  "properties": {
    "addr:full":"2 Princes Street Dorchester Dorset DT1 1TP",
    "addr:housenumber":"2",
    "addr:postcode":"dt1 1tp",
    "addr:street":"Princes Street",
    "iso:country":"GB",
    "sg:address":"2 Princes Street",
    "sg:city":"Dorchester",
    "sg:classifiers":[
        {
            "category":"Cafe",
            "type":"Food & Drink"
        }
    ],
    "sg:phone":"+44 1305 261758",
    "sg:postcode":"DT1 1TP",
    "sg:province":"Dorset",
    "sg:tags":[
        "tea",
        "snack",
        "bar",
        "room"
    ],
    "wof:name":"Choice",
    "wof:placetype":"venue"
},
  "geometry": {"coordinates":[-2.4381279945,50.714679718],"type":"Point"}
}