{
  "type": "Feature",
  "properties": {
    "addr:full":"Sherbourne Ho, 23-25 Northolt Rd Harrow Greater London HA2 0LH",
    "addr:housenumber":"23-25",
    "addr:postcode":"ha2 0lh",
    "addr:street":"Northolt Rd",
    "iso:country":"GB",
    "sg:address":"Sherbourne Ho, 23-25 Northolt Rd",
    "sg:city":"Harrow",
    "sg:classifiers":[
        {
            "category":"Travel",
            "subcategory":"Travel Agent",
            "type":"Entertainment"
        }
    ],
    "sg:phone":"+44 20 8864 5700",
    "sg:postcode":"HA2 0LH",
    "sg:province":"Greater London",
    "wof:name":"Sun & City Holidays Ltd",
    "wof:placetype":"venue"
},
  "geometry": {"coordinates":[-0.34725,51.56889],"type":"Point"}
}