{
  "type": "Feature",
  "properties": {
    "addr:full":"Piccadilly Place Bath Bath and North East Somerset BA1 6PW",
    "addr:postcode":"ba1 6pw",
    "addr:street":"Piccadilly Place",
    "iso:country":"GB",
    "sg:address":"Piccadilly Place",
    "sg:city":"Bath",
    "sg:classifiers":[
        {
            "category":"Autos & Motor Vehicles",
            "subcategory":"Auto Supplies",
            "type":"Retail Goods"
        }
    ],
    "sg:phone":"+44 1225 338899",
    "sg:postcode":"BA1 6PW",
    "sg:province":"Bath and North East Somerset",
    "sg:tags":[
        "tyre"
    ],
    "wof:name":"A T S",
    "wof:placetype":"venue"
},
  "geometry": {"coordinates":[-2.351754,51.392395],"type":"Point"}
}