{
  "type": "Feature",
  "properties": {
    "addr:full":"10 Manchester Road Nelson Lancashire BB9 7EG",
    "addr:housenumber":"10",
    "addr:postcode":"bb9 7eg",
    "addr:street":"Manchester Road",
    "iso:country":"GB",
    "sg:address":"10 Manchester Road",
    "sg:city":"Nelson",
    "sg:classifiers":[
        {
            "category":"Health Services",
            "subcategory":"Optometrist",
            "type":"Services"
        }
    ],
    "sg:phone":"+44 1282 613875",
    "sg:postcode":"BB9 7EG",
    "sg:province":"Lancashire",
    "sg:tags":[
        "optician"
    ],
    "wof:name":"Opticians Express",
    "wof:placetype":"venue"
},
  "geometry": {"coordinates":[-2.215435,53.836281],"type":"Point"}
}