{
  "type": "Feature",
  "properties": {
    "iso:country":"GB",
    "sg:address":"68-70 Prendergast",
    "sg:city":"Haverfordwest",
    "sg:classifiers":[
        {
            "category":"Bars & Pubs",
            "type":"Food & Drink"
        }
    ],
    "sg:postcode":"SA61 2PP",
    "sg:province":"Pembrokeshire",
    "sg:tags":[
        "pubs",
        "inn"
    ],
    "wof:name":"The Horse & Groom",
    "wof:placetype":"venue"
},
  "geometry": {"coordinates":[-4.96576,51.806602],"type":"Point"}
}