{
  "type": "Feature",
  "properties": {
    "addr:full":"S S B Buildings, 16 Rolfe Street Smethwick West Midlands B66 2AA",
    "addr:housenumber":"b;16",
    "addr:postcode":"s s;b66 2aa",
    "addr:street":"Buildings;Rolfe Street",
    "iso:country":"GB",
    "sg:address":"S S B Buildings, 16 Rolfe Street",
    "sg:city":"Smethwick",
    "sg:classifiers":[
        {
            "category":"Shopping",
            "subcategory":"Clothing, Apparel, & Fashions",
            "type":"Retail Goods"
        }
    ],
    "sg:postcode":"B66 2AA",
    "sg:province":"West Midlands",
    "sg:tags":[
        "clothing",
        "fabric"
    ],
    "wof:name":"Y K O F Ltd.",
    "wof:placetype":"venue"
},
  "geometry": {"coordinates":[-1.971184,52.495926],"type":"Point"}
}