{
  "type": "Feature",
  "properties": {
    "addr:full":"62 Fore Street Saltash Cornwall PL12 6JW",
    "addr:housenumber":"62",
    "addr:postcode":"pl12 6jw",
    "addr:street":"Fore Street",
    "iso:country":"GB",
    "sg:address":"62 Fore Street",
    "sg:city":"Saltash",
    "sg:classifiers":[
        {
            "category":"Food & Beverages",
            "subcategory":"Specialty",
            "type":"Retail Goods"
        }
    ],
    "sg:phone":"+44 1752 844926",
    "sg:postcode":"PL12 6JW",
    "sg:province":"Cornwall",
    "sg:tags":[
        "product",
        "health"
    ],
    "wof:name":"A & N Health Foods",
    "wof:placetype":"venue"
},
  "geometry": {"coordinates":[-4.212479,50.40884],"type":"Point"}
}