{
  "type": "Feature",
  "properties": {
    "addr:full":"Thames Exchange, 72 Upper Thames Street London Greater London EC4R 3TA",
    "addr:housenumber":"72",
    "addr:postcode":"ec4r 3ta",
    "addr:street":"Upper Thames Street",
    "iso:country":"GB",
    "sg:address":"Thames Exchange, 72 Upper Thames Street",
    "sg:city":"London",
    "sg:classifiers":[
        {
            "category":"Autos & Motor Vehicles",
            "subcategory":"Automobile Sales",
            "type":"Retail Goods"
        },
        {
            "category":"Retail",
            "subcategory":"Auto Repair",
            "type":"Services"
        }
    ],
    "sg:phone":"+44 20 7236 3745",
    "sg:postcode":"EC4R 3TA",
    "sg:province":"Greater London",
    "sg:tags":[
        "modification",
        "garage",
        "car"
    ],
    "wof:name":"Normand City of London Ltd.",
    "wof:placetype":"venue"
},
  "geometry": {"coordinates":[-0.092840001,51.5101318359],"type":"Point"}
}