{
  "type": "Feature",
  "properties": {
    "addr:full":"5000 John Smith Drive, Oxford Business Park South Oxford Oxfordshire OX4 2BH",
    "addr:housenumber":"5000",
    "addr:postcode":"ox4 2bh",
    "addr:street":"John Smith Drive;Business Park South",
    "iso:country":"GB",
    "sg:address":"5000 John Smith Drive, Oxford Business Park South",
    "sg:city":"Oxford",
    "sg:classifiers":[
        {
            "category":"Manufacturing",
            "subcategory":"Electronics",
            "type":"Manufacturing & Wholesale Goods"
        }
    ],
    "sg:phone":"+44 1865 204000",
    "sg:postcode":"OX4 2BH",
    "sg:province":"Oxfordshire",
    "sg:tags":[
        "control",
        "component",
        "-",
        "electronic"
    ],
    "wof:name":"Electrocomponents Plc",
    "wof:placetype":"venue"
},
  "geometry": {"coordinates":[-1.206161,51.730827],"type":"Point"}
}