{
  "type": "Feature",
  "properties": {
    "iso:country":"GB",
    "sg:address":"241a Bury Old Road, Prestwich",
    "sg:city":"Manchester",
    "sg:classifiers":[
        {
            "category":"Professional",
            "subcategory":"Accounting & Tax Preparation",
            "type":"Services"
        }
    ],
    "sg:phone":"+44 161 773 1900",
    "sg:postcode":"M25 1JE",
    "sg:province":"Greater Manchester",
    "sg:tags":[
        "accountant"
    ],
    "wof:name":"Rowley & Co",
    "wof:placetype":"venue"
},
  "geometry": {"coordinates":[-2.266649,53.531345],"type":"Point"}
}