{
  "type": "Feature",
  "properties": {
    "addr:full":"46-48 Carolgate Retford Nottinghamshire DN22 6DY",
    "addr:housenumber":"46-48",
    "addr:postcode":"dn22 6dy",
    "addr:street":"Carolgate Retford",
    "iso:country":"GB",
    "sg:address":"46-48 Carolgate",
    "sg:city":"Retford",
    "sg:classifiers":[
        {
            "category":"Shopping",
            "subcategory":"Pharmacy",
            "type":"Retail Goods"
        }
    ],
    "sg:phone":"+44 1777 703812",
    "sg:postcode":"DN22 6DY",
    "sg:province":"Nottinghamshire",
    "sg:tags":[
        "pharmacist",
        "chemist"
    ],
    "wof:name":"Boots the Chemist",
    "wof:placetype":"venue"
},
  "geometry": {"coordinates":[-0.942103,53.320736],"type":"Point"}
}