{
  "type": "Feature",
  "properties": {
    "iso:country":"GB",
    "sg:address":"30 Parkway",
    "sg:city":"London",
    "sg:classifiers":[
        {
            "category":"Deli",
            "type":"Food & Drink"
        }
    ],
    "sg:phone":"+44 20 7267 0076",
    "sg:postcode":"NW1 7AH",
    "sg:province":"Greater London",
    "sg:tags":[
        "delicatessen"
    ],
    "wof:name":"Parkway Delicatessen",
    "wof:placetype":"venue"
},
  "geometry": {"coordinates":[-0.1442990005,51.5384788513],"type":"Point"}
}