{
  "type": "Feature",
  "properties": {
    "iso:country":"GB",
    "sg:address":"28 Newlands Drive",
    "sg:city":"Doncaster",
    "sg:classifiers":[
        {
            "category":"Personal",
            "subcategory":"Beauty Salon",
            "type":"Services"
        },
        {
            "category":"Personal",
            "subcategory":"Barber",
            "type":"Services"
        }
    ],
    "sg:phone":"+44 1302 390000",
    "sg:postcode":"DN5 8HX",
    "sg:province":"South Yorkshire",
    "sg:tags":[
        "unisex",
        "hairdresser"
    ],
    "wof:name":"T J Snippers",
    "wof:placetype":"venue"
},
  "geometry": {"coordinates":[-1.160597,53.534748],"type":"Point"}
}