{
  "type": "Feature",
  "properties": {
    "addr:full":"48 Yoden Way Peterlee Durham SR8 1AS",
    "addr:housenumber":"48",
    "addr:postcode":"sr8 1as",
    "addr:street":"Yoden Way",
    "iso:country":"GB",
    "sg:address":"48 Yoden Way",
    "sg:city":"Peterlee",
    "sg:classifiers":[
        {
            "category":"Shopping",
            "subcategory":"Discount & Variety Stores",
            "type":"Retail Goods"
        }
    ],
    "sg:postcode":"SR8 1AS",
    "sg:province":"Durham",
    "sg:tags":[
        "centre"
    ],
    "wof:name":"Your More Stores",
    "wof:placetype":"venue"
},
  "geometry": {"coordinates":[-1.3308589458,54.7586898804],"type":"Point"}
}