{
  "type": "Feature",
  "properties": {
    "addr:full":"Gigg Mill, Nailsworth Stroud Gloucestershire GL6 0JP",
    "addr:postcode":"gl6 0jp",
    "addr:street":"Gigg",
    "iso:country":"GB",
    "sg:address":"Gigg Mill, Nailsworth",
    "sg:city":"Stroud",
    "sg:classifiers":[
        {
            "category":"Building & Trades",
            "subcategory":"Construction",
            "type":"Services"
        }
    ],
    "sg:phone":"+44 1453 836536",
    "sg:postcode":"GL6 0JP",
    "sg:province":"Gloucestershire",
    "sg:tags":[
        "joiner",
        "carpenter"
    ],
    "wof:name":"Woodwright Carpentry & Joinery",
    "wof:placetype":"venue"
},
  "geometry": {"coordinates":[-2.2224099636,51.691318512],"type":"Point"}
}