{
  "type": "Feature",
  "properties": {
    "iso:country":"GB",
    "sg:address":"A47 Acle Bypass, Acle",
    "sg:city":"Norwich",
    "sg:classifiers":[
        {
            "category":"Travel",
            "subcategory":"Hotels & Motels",
            "type":"Entertainment"
        }
    ],
    "sg:phone":"+44 1493 751970",
    "sg:postcode":"NR13 3BE",
    "sg:province":"Norfolk",
    "wof:name":"Travelodge Great Yarmouth/Acle",
    "wof:placetype":"venue"
},
  "geometry": {"coordinates":[1.554894,52.637409],"type":"Point"}
}