{
  "type": "Feature",
  "properties": {
    "iso:country":"GB",
    "sg:address":"7 Little Western Street",
    "sg:city":"Brighton",
    "sg:classifiers":[
        {
            "category":"Retail",
            "subcategory":"Auto Repair",
            "type":"Services"
        }
    ],
    "sg:phone":"+44 1273 771602",
    "sg:postcode":"BN1 2PU",
    "sg:province":"East Sussex",
    "sg:tags":[
        "modification",
        "garage"
    ],
    "wof:name":"L & M Motor Engineers",
    "wof:placetype":"venue"
},
  "geometry": {"coordinates":[-0.155669,50.824638],"type":"Point"}
}