{
  "type": "Feature",
  "properties": {
    "iso:country":"GB",
    "sg:address":"Bardolf Manor, Puddletown",
    "sg:city":"Dorchester",
    "sg:classifiers":[
        {
            "category":"Farming",
            "subcategory":"Livestock Farm",
            "type":"Manufacturing & Wholesale Goods"
        }
    ],
    "sg:phone":"+44 1305 848225",
    "sg:postcode":"DT2 7LL",
    "sg:province":"Dorset",
    "sg:tags":[
        "others"
    ],
    "wof:name":"Badolf Farms Ltd.",
    "wof:placetype":"venue"
},
  "geometry": {"coordinates":[-2.339799881,50.7577514648],"type":"Point"}
}