{
  "type": "Feature",
  "properties": {
    "iso:country":"GB",
    "sg:address":"36 Hart Street",
    "sg:city":"Henley-on-thames",
    "sg:classifiers":[
        {
            "category":"Real Estate",
            "subcategory":"Real Estate Operator",
            "type":"Services"
        }
    ],
    "sg:phone":"+44 1491 410411",
    "sg:postcode":"RG9 2AU",
    "sg:province":"Berkshire",
    "sg:tags":[
        "rental"
    ],
    "wof:name":"Enterprise House Serviced Office Centre",
    "wof:placetype":"venue"
},
  "geometry": {"coordinates":[-0.90247,51.537537],"type":"Point"}
}