{
  "type": "Feature",
  "properties": {
    "addr:full":"16 Crossways Crescent Harrogate North Yorkshire HG2 7DQ",
    "addr:housenumber":"16",
    "addr:postcode":"hg2 7dq",
    "addr:street":"Crossways Crescent",
    "iso:country":"GB",
    "sg:address":"16 Crossways Crescent",
    "sg:city":"Harrogate",
    "sg:classifiers":[
        {
            "category":"Shopping",
            "subcategory":"Party Supplies",
            "type":"Retail Goods"
        }
    ],
    "sg:phone":"+44 1423 885311",
    "sg:postcode":"HG2 7DQ",
    "sg:province":"North Yorkshire",
    "sg:tags":[
        "inflatables",
        "bouncy",
        "castle"
    ],
    "wof:name":"L & L Steel",
    "wof:placetype":"venue"
},
  "geometry": {"coordinates":[-1.492499,53.995003],"type":"Point"}
}