{
  "type": "Feature",
  "properties": {
    "addr:full":"362 Harlington Road Uxbridge Buckinghamshire UB8 3HG",
    "addr:housenumber":"362",
    "addr:postcode":"ub8 3hg",
    "addr:street":"Harlington Road",
    "iso:country":"GB",
    "sg:address":"362 Harlington Road",
    "sg:city":"Uxbridge",
    "sg:classifiers":[
        {
            "category":"Home & Garden",
            "subcategory":"Household Appliances",
            "type":"Retail Goods"
        }
    ],
    "sg:phone":"+44 20 8573 6245",
    "sg:postcode":"UB8 3HG",
    "sg:province":"Buckinghamshire",
    "sg:tags":[
        "electrical"
    ],
    "wof:name":"M J M Domestics",
    "wof:placetype":"venue"
},
  "geometry": {"coordinates":[-0.445975,51.5205],"type":"Point"}
}