{
  "type": "Feature",
  "properties": {
    "iso:country":"GB",
    "sg:address":"Greenshields House, Perimeter Road, Knowsley Industrial Park",
    "sg:city":"Liverpool",
    "sg:classifiers":[
        {
            "category":"Organizations",
            "subcategory":"Labor Organization",
            "type":"Services"
        }
    ],
    "sg:phone":"+44 151 549 2570",
    "sg:postcode":"L33 3BA",
    "sg:province":"Lancashire",
    "sg:tags":[
        "woodworking",
        "machinery"
    ],
    "wof:name":"TCR Associates Limited",
    "wof:placetype":"venue"
},
  "geometry": {"coordinates":[-2.843771,53.487083],"type":"Point"}
}