{
  "type": "Feature",
  "properties": {
    "addr:full":"19 Fore Street, St Marychurch Torquay Devon TQ1 4PU",
    "addr:housenumber":"19",
    "addr:postcode":"tq1 4pu",
    "addr:street":"Fore Street",
    "iso:country":"GB",
    "sg:address":"19 Fore Street, St Marychurch",
    "sg:city":"Torquay",
    "sg:classifiers":[
        {
            "category":"Professional",
            "subcategory":"Business Services",
            "type":"Services"
        },
        {
            "category":"Casinos & Gambling",
            "type":"Entertainment"
        }
    ],
    "sg:phone":"+44 1803 312795",
    "sg:postcode":"TQ1 4PU",
    "sg:province":"Devon",
    "sg:tags":[
        "turf",
        "accountant",
        "bookmaker"
    ],
    "wof:name":"Jack Bevan & Co",
    "wof:placetype":"venue"
},
  "geometry": {"coordinates":[-3.5231750011,50.4825935364],"type":"Point"}
}