{
  "type": "Feature",
  "properties": {
    "iso:country":"GB",
    "sg:address":"Hallsteads, Dove Holes",
    "sg:city":"Buxton",
    "sg:classifiers":[
        {
            "category":"Manufacturing",
            "subcategory":"Paper Products",
            "type":"Manufacturing & Wholesale Goods"
        }
    ],
    "sg:phone":"+44 1298 816692",
    "sg:postcode":"SK17 8BJ",
    "sg:province":"Derbyshire",
    "sg:tags":[
        "mill",
        "pulp"
    ],
    "wof:name":"Cell Ltd.",
    "wof:placetype":"venue"
},
  "geometry": {"coordinates":[-1.88638,53.301376],"type":"Point"}
}