{
  "type": "Feature",
  "properties": {
    "iso:country":"GB",
    "sg:address":"18 Brewery La",
    "sg:city":"Dewsbury",
    "sg:classifiers":[
        {
            "category":"Health Services",
            "subcategory":"Doctor",
            "type":"Services"
        }
    ],
    "sg:phone":"+44 1924 458787",
    "sg:postcode":"WF12 9DZ",
    "sg:province":"West Yorkshire",
    "sg:tags":[
        "practitioners"
    ],
    "wof:name":"Sutherland, W G M",
    "wof:placetype":"venue"
},
  "geometry": {"coordinates":[-1.6367739439,53.674949646],"type":"Point"}
}