{
  "type": "Feature",
  "properties": {
    "addr:full":"Bayhorne Lane, Balcombe Rd Horley Surrey RH6 9ES",
    "addr:postcode":"rh6 9es",
    "addr:street":"Bayhorne Lane Balcombe Rd",
    "iso:country":"GB",
    "sg:address":"Bayhorne Lane, Balcombe Rd",
    "sg:city":"Horley",
    "sg:classifiers":[
        {
            "category":"Professional",
            "subcategory":"Printing & Photocopies",
            "type":"Services"
        }
    ],
    "sg:phone":"+44 1293 820688",
    "sg:postcode":"RH6 9ES",
    "sg:province":"Surrey",
    "sg:tags":[
        "engraving"
    ],
    "wof:name":"Rapid Engraving & Silk Screen Printers",
    "wof:placetype":"venue"
},
  "geometry": {"coordinates":[-0.154381007,51.1639671326],"type":"Point"}
}