{
  "type": "Feature",
  "properties": {
    "iso:country":"GB",
    "sg:address":"12 Midholm, Hampstead Garden Suburb",
    "sg:city":"London",
    "sg:classifiers":[
        {
            "category":"Building & Trades",
            "subcategory":"Construction",
            "type":"Services"
        }
    ],
    "sg:postcode":"NW11 6JJ",
    "sg:province":"Greater London",
    "sg:tags":[
        "builder"
    ],
    "wof:name":"Skyco Incorporated Ltd",
    "wof:placetype":"venue"
},
  "geometry": {"coordinates":[-0.18268,51.585579],"type":"Point"}
}