{
  "type": "Feature",
  "properties": {
    "addr:full":"Court Street, Moreton Hampstead Newton Abbot Devon TQ13 8LZ",
    "addr:postcode":"tq13 8lz",
    "addr:street":"Court Street",
    "iso:country":"GB",
    "sg:address":"Court Street, Moreton Hampstead",
    "sg:city":"Newton Abbot",
    "sg:classifiers":[
        {
            "category":"Health Services",
            "subcategory":"Nursing And Care Facility",
            "type":"Services"
        }
    ],
    "sg:phone":"+44 1647 440729",
    "sg:postcode":"TQ13 8LZ",
    "sg:province":"Devon",
    "sg:tags":[
        "home"
    ],
    "wof:name":"Coppelia House",
    "wof:placetype":"venue"
},
  "geometry": {"coordinates":[-3.7670869827,50.660446167],"type":"Point"}
}