{
  "type": "Feature",
  "properties": {
    "iso:country":"GB",
    "sg:address":"13 Well Street",
    "sg:city":"Porthcawl",
    "sg:classifiers":[
        {
            "category":"Food & Beverages",
            "subcategory":"Meat & Fish",
            "type":"Retail Goods"
        },
        {
            "category":"Food & Beverages",
            "subcategory":"Groceries & Convenience Stores",
            "type":"Retail Goods"
        }
    ],
    "sg:phone":"+44 1656 783766",
    "sg:postcode":"CF36 3BE",
    "sg:province":"Bridgend",
    "sg:tags":[
        "shop",
        "chip"
    ],
    "wof:name":"Sidoli Bros",
    "wof:placetype":"venue"
},
  "geometry": {"coordinates":[-3.705059,51.477009],"type":"Point"}
}