{
  "type": "Feature",
  "properties": {
    "iso:country":"GB",
    "sg:address":"7 Connaught Ave",
    "sg:city":"Frinton-on-sea",
    "sg:classifiers":[
        {
            "category":"Shopping",
            "subcategory":"Antiques",
            "type":"Retail Goods"
        }
    ],
    "sg:phone":"+44 1255 674637",
    "sg:postcode":"CO13 9PN",
    "sg:province":"Essex",
    "wof:name":"Antiques & Gifts",
    "wof:placetype":"venue"
},
  "geometry": {"coordinates":[1.2455470562,51.8305358887],"type":"Point"}
}