{
  "type": "Feature",
  "properties": {
    "addr:full":"11 Sanderstead Rd Leyton Greater London E10 7PW",
    "addr:housenumber":"11",
    "addr:postcode":"e10 7pw",
    "addr:street":"Sanderstead Rd",
    "iso:country":"GB",
    "sg:address":"11 Sanderstead Rd",
    "sg:city":"Leyton",
    "sg:classifiers":[
        {
            "category":"Bus Charters",
            "type":"Transportation"
        }
    ],
    "sg:phone":"+44 20 8556 0815",
    "sg:postcode":"E10 7PW",
    "sg:province":"Greater London",
    "sg:tags":[
        "hire",
        "coach"
    ],
    "wof:name":"Wells Travel",
    "wof:placetype":"venue"
},
  "geometry": {"coordinates":[-0.0336420015,51.5678100586],"type":"Point"}
}