{
  "type": "Feature",
  "properties": {
    "addr:full":"Ashtrees, Milden Tyres Darlington Durham DL3 7JA",
    "addr:postcode":"dl3 7ja",
    "iso:country":"GB",
    "sg:address":"Ashtrees, Milden Tyres",
    "sg:city":"Darlington",
    "sg:classifiers":[
        {
            "category":"Retail",
            "subcategory":"Repair Shop",
            "type":"Services"
        }
    ],
    "sg:phone":"+44 1325 358976",
    "sg:postcode":"DL3 7JA",
    "sg:province":"Durham",
    "sg:tags":[
        "upholsterer"
    ],
    "wof:name":"Roberts Furnishers",
    "wof:placetype":"venue"
},
  "geometry": {"coordinates":[-1.5554200411,54.5260887146],"type":"Point"}
}