{
  "type": "Feature",
  "properties": {
    "addr:full":"9 Atkyns Road, Headington Oxford Oxfordshire OX3 8RA",
    "addr:housenumber":"9",
    "addr:postcode":"ox3 8ra",
    "addr:street":"Atkyns Road",
    "iso:country":"GB",
    "sg:address":"9 Atkyns Road, Headington",
    "sg:city":"Oxford",
    "sg:classifiers":[
        {
            "category":"Personal",
            "subcategory":"Beauty Salon",
            "type":"Services"
        }
    ],
    "sg:phone":"+44 1865 763944",
    "sg:postcode":"OX3 8RA",
    "sg:province":"Oxfordshire",
    "sg:tags":[
        "unisex",
        "hairdresser"
    ],
    "wof:name":"Acute-Cut",
    "wof:placetype":"venue"
},
  "geometry": {"coordinates":[-1.20084,51.748619],"type":"Point"}
}