{
  "type": "Feature",
  "properties": {
    "addr:full":"21 College Fields Marlborough Berkshire SN8 1UA",
    "addr:housenumber":"21",
    "addr:postcode":"sn8 1ua",
    "addr:street":"College Fields",
    "iso:country":"GB",
    "sg:address":"21 College Fields",
    "sg:city":"Marlborough",
    "sg:classifiers":[
        {
            "category":"Professional",
            "subcategory":"Lawyer & Legal Services",
            "type":"Services"
        }
    ],
    "sg:phone":"+44 1672 514100",
    "sg:postcode":"SN8 1UA",
    "sg:province":"Berkshire",
    "wof:name":"Claims Direct",
    "wof:placetype":"venue"
},
  "geometry": {"coordinates":[-1.743339,51.419327],"type":"Point"}
}