{
  "type": "Feature",
  "properties": {
    "iso:country":"GB",
    "sg:address":"Saxton House, 5'9 Maude Street",
    "sg:city":"Leeds",
    "sg:classifiers":[
        {
            "category":"Professional",
            "subcategory":"Employment Agencies",
            "type":"Services"
        }
    ],
    "sg:postcode":"LS2 7HB",
    "sg:province":"West Yorkshire",
    "sg:tags":[
        "consultant"
    ],
    "wof:name":"The M B I Register Ltd.",
    "wof:placetype":"venue"
},
  "geometry": {"coordinates":[-1.534613,53.794891],"type":"Point"}
}