{
  "type": "Feature",
  "properties": {
    "addr:full":"30 Fintry Drive Dundee Dundee City DD4 9PB",
    "addr:housenumber":"30",
    "addr:postcode":"dd4 9pb",
    "addr:street":"Fintry Drive",
    "iso:country":"GB",
    "sg:address":"30 Fintry Drive",
    "sg:city":"Dundee",
    "sg:classifiers":[
        {
            "category":"Personal",
            "subcategory":"Beauty Salon",
            "type":"Services"
        }
    ],
    "sg:phone":"+44 1382 505067",
    "sg:postcode":"DD4 9PB",
    "sg:province":"Dundee City",
    "sg:tags":[
        "unisex",
        "hairdresser"
    ],
    "wof:name":"Sophisticut",
    "wof:placetype":"venue"
},
  "geometry": {"coordinates":[-2.9465560913,56.4916648865],"type":"Point"}
}