{
  "type": "Feature",
  "properties": {
    "iso:country":"GB",
    "sg:address":"8 Cants Lane",
    "sg:city":"Burgess Hill",
    "sg:classifiers":[
        {
            "category":"Shopping",
            "type":"Retail Goods"
        }
    ],
    "sg:phone":"+44 1444 258831",
    "sg:postcode":"RH15 0LS",
    "sg:province":"East Sussex",
    "sg:tags":[
        "part",
        "accessory"
    ],
    "wof:name":"C P A",
    "wof:placetype":"venue"
},
  "geometry": {"coordinates":[-0.1184950024,50.9597396851],"type":"Point"}
}