{
  "type": "Feature",
  "properties": {
    "iso:country":"GB",
    "sg:address":"9 The Crescent",
    "sg:city":"Egham",
    "sg:classifiers":[
        {
            "category":"Health Services",
            "subcategory":"Podiatrist",
            "type":"Services"
        }
    ],
    "sg:postcode":"TW20 9PQ",
    "sg:province":"Surrey",
    "sg:tags":[
        "podiatrists",
        "chiropodist"
    ],
    "wof:name":"Rosemary Anderson",
    "wof:placetype":"venue"
},
  "geometry": {"coordinates":[-0.5568590164,51.4277191162],"type":"Point"}
}