{
  "type": "Feature",
  "properties": {
    "iso:country":"GB",
    "sg:address":"15 Ryton Street",
    "sg:city":"Worksop",
    "sg:classifiers":[
        {
            "category":"Personal",
            "subcategory":"Beauty Salon",
            "type":"Services"
        }
    ],
    "sg:phone":"+44 1909 472274",
    "sg:postcode":"S80 2AY",
    "sg:province":"Nottinghamshire",
    "sg:tags":[
        "unisex",
        "hairdresser"
    ],
    "wof:name":"Roscoe's",
    "wof:placetype":"venue"
},
  "geometry": {"coordinates":[-1.122759,53.305389],"type":"Point"}
}