{
  "type": "Feature",
  "properties": {
    "addr:full":"Jamphlars Road, Cardenden Lochgelly Fife KY5 0ND",
    "addr:postcode":"ky5 0nd",
    "addr:street":"Jamphlars Road;Lochgelly",
    "iso:country":"GB",
    "sg:address":"Jamphlars Road, Cardenden",
    "sg:city":"Lochgelly",
    "sg:classifiers":[
        {
            "category":"Retail",
            "subcategory":"Auto Repair",
            "type":"Services"
        }
    ],
    "sg:phone":"+44 1592 720344",
    "sg:postcode":"KY5 0ND",
    "sg:province":"Fife",
    "sg:tags":[
        "body",
        "car",
        "repairer"
    ],
    "wof:name":"S D Coachworks",
    "wof:placetype":"venue"
},
  "geometry": {"coordinates":[-3.2639119625,56.1473617554],"type":"Point"}
}