{
  "type": "Feature",
  "properties": {
    "iso:country":"GB",
    "sg:address":"Unit 1a, The Mayfield, Southcrest",
    "sg:city":"Redditch",
    "sg:classifiers":[
        {
            "category":"Manufacturing",
            "subcategory":"Rubber & Plastics",
            "type":"Manufacturing & Wholesale Goods"
        },
        {
            "category":"Manufacturing",
            "subcategory":"Building Materials",
            "type":"Manufacturing & Wholesale Goods"
        }
    ],
    "sg:postcode":"B98 7DU",
    "sg:province":"Warwickshire",
    "sg:tags":[
        "product",
        "extrusion"
    ],
    "wof:name":"N G C Consultancy",
    "wof:placetype":"venue"
},
  "geometry": {"coordinates":[-1.943019,52.29834],"type":"Point"}
}