{
  "type": "Feature",
  "properties": {
    "addr:full":"2 Frances Street Truro Cornwall TR1 3DN",
    "addr:housenumber":"2",
    "addr:postcode":"tr1 3dn",
    "addr:street":"Frances Street",
    "iso:country":"GB",
    "sg:address":"2 Frances Street",
    "sg:city":"Truro",
    "sg:classifiers":[
        {
            "category":"Home & Garden",
            "subcategory":"Home Furnishings",
            "type":"Retail Goods"
        }
    ],
    "sg:postcode":"TR1 3DN",
    "sg:province":"Cornwall",
    "sg:tags":[
        "furnishers",
        "planner",
        "kitchen"
    ],
    "wof:name":"Out of Wood Ltd.",
    "wof:placetype":"venue"
},
  "geometry": {"coordinates":[-5.0557188988,50.2634963989],"type":"Point"}
}