{
  "type": "Feature",
  "properties": {
    "addr:full":"The Style Gallery 7 Angel Gate, High St Guildford Surrey GU1 3DP",
    "addr:housenumber":"7",
    "addr:postcode":"gu1 3dp",
    "addr:street":"Angel Gate High St",
    "iso:country":"GB",
    "sg:address":"The Style Gallery 7 Angel Gate, High St",
    "sg:city":"Guildford",
    "sg:classifiers":[
        {
            "category":"Professional",
            "subcategory":"Management & Consulting",
            "type":"Services"
        }
    ],
    "sg:phone":"+44 1483 455860",
    "sg:postcode":"GU1 3DP",
    "sg:province":"Surrey",
    "sg:tags":[
        "consultant",
        "specialist"
    ],
    "wof:name":"Color Me Beautiful",
    "wof:placetype":"venue"
},
  "geometry": {"coordinates":[-0.570516,51.237087],"type":"Point"}
}