{
  "type": "Feature",
  "properties": {
    "addr:full":"Unit 2-3 Kangley Bridge Road, Lower Sydenham London Greater London SE26 5AR",
    "addr:housenumber":"unit 2-3",
    "addr:postcode":"se26 5ar",
    "addr:street":"Kangley Bridge Road",
    "iso:country":"GB",
    "sg:address":"Unit 2-3 Kangley Bridge Road, Lower Sydenham",
    "sg:city":"London",
    "sg:classifiers":[
        {
            "category":"Professional",
            "subcategory":"Printing & Photocopies",
            "type":"Services"
        }
    ],
    "sg:phone":"+44 20 8676 6700",
    "sg:postcode":"SE26 5AR",
    "sg:province":"Greater London",
    "sg:tags":[
        "printer"
    ],
    "wof:name":"Quadracolor Ltd.",
    "wof:placetype":"venue"
},
  "geometry": {"coordinates":[-0.034264,51.428059],"type":"Point"}
}