{
  "type": "Feature",
  "properties": {
    "addr:full":"Mansfield Road Mansfield Derbyshire NG20 0DG",
    "addr:postcode":"ng20 0dg",
    "addr:street":"Mansfield Road",
    "iso:country":"GB",
    "sg:address":"Mansfield Road",
    "sg:city":"Mansfield",
    "sg:classifiers":[
        {
            "category":"Autos & Motor Vehicles",
            "subcategory":"Automobile Sales",
            "type":"Retail Goods"
        }
    ],
    "sg:phone":"+44 1623 842516",
    "sg:postcode":"NG20 0DG",
    "sg:province":"Derbyshire",
    "sg:tags":[
        "car"
    ],
    "wof:name":"Warsop Motor Co",
    "wof:placetype":"venue"
},
  "geometry": {"coordinates":[-1.158998,53.201393],"type":"Point"}
}