{
  "type": "Feature",
  "properties": {
    "iso:country":"GB",
    "sg:address":"1b Mill Street",
    "sg:city":"Cannock",
    "sg:classifiers":[
        {
            "category":"Banks & Credit Unions",
            "subcategory":"Bank",
            "type":"Services"
        }
    ],
    "sg:phone":"+44 1543 500555",
    "sg:postcode":"WS11 3DN",
    "sg:province":"Staffordshire",
    "sg:tags":[
        "broker",
        "mortgage"
    ],
    "wof:name":"First Stop Mortgage Shop Ltd.",
    "wof:placetype":"venue"
},
  "geometry": {"coordinates":[-2.027096,52.688526],"type":"Point"}
}