{
  "type": "Feature",
  "properties": {
    "addr:full":"116 College Road, Kensal Rise London Greater London NW10 5HD",
    "addr:housenumber":"116",
    "addr:postcode":"nw10 5hd",
    "addr:street":"College Road",
    "iso:country":"GB",
    "sg:address":"116 College Road, Kensal Rise",
    "sg:city":"London",
    "sg:classifiers":[
        {
            "category":"Shopping",
            "subcategory":"Pharmacy",
            "type":"Retail Goods"
        }
    ],
    "sg:postcode":"NW10 5HD",
    "sg:province":"Greater London",
    "sg:tags":[
        "pharmacist",
        "chemist"
    ],
    "wof:name":"Cocking Chemist",
    "wof:placetype":"venue"
},
  "geometry": {"coordinates":[-0.2262710035,51.5356254578],"type":"Point"}
}