{
  "type": "Feature",
  "properties": {
    "iso:country":"GB",
    "sg:address":"Lanner Moor Garage, Lanner Moor",
    "sg:city":"Redruth",
    "sg:classifiers":[
        {
            "category":"Personal",
            "subcategory":"Beauty Salon",
            "type":"Services"
        }
    ],
    "sg:phone":"+44 1209 314206",
    "sg:postcode":"TR16 6HT",
    "sg:province":"Cornwall",
    "sg:tags":[
        "unisex",
        "hairdresser"
    ],
    "wof:name":"Upperkuts",
    "wof:placetype":"venue"
},
  "geometry": {"coordinates":[-5.204954,50.216274],"type":"Point"}
}