{
  "type": "Feature",
  "properties": {
    "iso:country":"GB",
    "sg:address":"14 Charlotte Street",
    "sg:city":"Bath",
    "sg:classifiers":[
        {
            "category":"Building & Trades",
            "subcategory":"Construction",
            "type":"Services"
        }
    ],
    "sg:phone":"+44 1225 424944",
    "sg:postcode":"BA1 2JP",
    "sg:province":"Bath and North East Somerset",
    "sg:tags":[
        "builder"
    ],
    "wof:name":"Stock Assessment Co. Ltd.",
    "wof:placetype":"venue"
},
  "geometry": {"coordinates":[-2.365669,51.383503],"type":"Point"}
}