{
  "type": "Feature",
  "properties": {
    "iso:country":"GB",
    "sg:address":"17 Main Street, Stoneyburn",
    "sg:city":"Bathgate",
    "sg:classifiers":[
        {
            "category":"Food & Beverages",
            "subcategory":"Fruits & Vegetables",
            "type":"Retail Goods"
        }
    ],
    "sg:phone":"+44 1501 762397",
    "sg:postcode":"EH47 8BB",
    "sg:province":"North Lanarkshire",
    "sg:tags":[
        "greengrocer"
    ],
    "wof:name":"Ali Bros",
    "wof:placetype":"venue"
},
  "geometry": {"coordinates":[-3.679258,55.845051],"type":"Point"}
}