{
  "type": "Feature",
  "properties": {
    "addr:full":"Bennett Ho, 1 High St Edgware Greater London HA8 7TA",
    "addr:housenumber":"1",
    "addr:postcode":"ha8 7ta",
    "addr:street":"High St",
    "iso:country":"GB",
    "sg:address":"Bennett Ho, 1 High St",
    "sg:city":"Edgware",
    "sg:classifiers":[
        {
            "category":"Shopping",
            "subcategory":"Bicycles & Sporting Goods",
            "type":"Retail Goods"
        },
        {
            "category":"Farming",
            "subcategory":"Fish & Marine Products",
            "type":"Manufacturing & Wholesale Goods"
        }
    ],
    "sg:phone":"+44 20 8951 4446",
    "sg:postcode":"HA8 7TA",
    "sg:province":"Greater London",
    "sg:tags":[
        "equipment",
        "supply"
    ],
    "wof:name":"Scorpio Navigation Services",
    "wof:placetype":"venue"
},
  "geometry": {"coordinates":[-0.277564,51.612083],"type":"Point"}
}