{
  "type": "Feature",
  "properties": {
    "iso:country":"GB",
    "sg:address":"Waterside Industrial Park, Waterside Road, Hunslet",
    "sg:city":"Leeds",
    "sg:classifiers":[
        {
            "category":"Building & Trades",
            "subcategory":"Construction",
            "type":"Services"
        },
        {
            "category":"Manufacturing",
            "subcategory":"Building Materials",
            "type":"Manufacturing & Wholesale Goods"
        }
    ],
    "sg:phone":"+44 113 271 9940",
    "sg:postcode":"LS10 1RW",
    "sg:province":"West Yorkshire",
    "sg:tags":[
        "merchant",
        "roofing",
        "product",
        "builder",
        "related",
        "contracting"
    ],
    "wof:name":"Hunslet Roofing Supplies",
    "wof:placetype":"venue"
},
  "geometry": {"coordinates":[-1.5276399851,53.7816925049],"type":"Point"}
}