{
  "type": "Feature",
  "properties": {
    "iso:country":"GB",
    "sg:address":"Flat 1 Kings Cottage, Churchtown",
    "sg:city":"Helston",
    "sg:classifiers":[
        {
            "category":"Building & Trades",
            "subcategory":"Construction",
            "type":"Services"
        }
    ],
    "sg:phone":"+44 1326 241344",
    "sg:postcode":"TR12 7BZ",
    "sg:province":"Cornwall",
    "sg:tags":[
        "roofing"
    ],
    "wof:name":"Roofs R Us",
    "wof:placetype":"venue"
},
  "geometry": {"coordinates":[-5.2427802086,50.0266494751],"type":"Point"}
}