{
  "type": "Feature",
  "properties": {
    "addr:full":"19 The Foxgloves Southampton Hampshire SO30 0UG",
    "addr:housenumber":"19",
    "addr:postcode":"so30 0ug",
    "addr:street":"The Foxgloves",
    "iso:country":"GB",
    "sg:address":"19 The Foxgloves",
    "sg:city":"Southampton",
    "sg:classifiers":[
        {
            "category":"Building & Trades",
            "subcategory":"Construction",
            "type":"Services"
        }
    ],
    "sg:phone":"+44 23 8039 2139",
    "sg:postcode":"SO30 0UG",
    "sg:province":"Hampshire",
    "sg:tags":[
        "roofing"
    ],
    "wof:name":"A & A Building & Roofing Services",
    "wof:placetype":"venue"
},
  "geometry": {"coordinates":[-1.296143,50.907932],"type":"Point"}
}