{
  "type": "Feature",
  "properties": {
    "addr:full":"101 Coupe Lane, Old Tupton Chesterfield Derbyshire S42 6HA",
    "addr:housenumber":"101",
    "addr:postcode":"s42 6ha",
    "addr:street":"Coupe Lane",
    "iso:country":"GB",
    "sg:address":"101 Coupe Lane, Old Tupton",
    "sg:city":"Chesterfield",
    "sg:classifiers":[
        {
            "category":"Home & Garden",
            "subcategory":"Building Materials",
            "type":"Retail Goods"
        }
    ],
    "sg:phone":"+44 1246 861738",
    "sg:postcode":"S42 6HA",
    "sg:province":"Derbyshire",
    "sg:tags":[
        "access",
        "equipment"
    ],
    "wof:name":"Richard Turner Ltd.",
    "wof:placetype":"venue"
},
  "geometry": {"coordinates":[-1.4268100262,53.1774291992],"type":"Point"}
}