{
  "type": "Feature",
  "properties": {
    "addr:full":"Main Street, Blackridge Bathgate West Lothian EH48 3RJ",
    "addr:postcode":"eh48 3rj",
    "addr:street":"Main Street;Bathgate",
    "iso:country":"GB",
    "sg:address":"Main Street, Blackridge",
    "sg:city":"Bathgate",
    "sg:classifiers":[
        {
            "category":"Government",
            "subcategory":"Post Office",
            "type":"Public Place"
        }
    ],
    "sg:phone":"+44 1501 751646",
    "sg:postcode":"EH48 3RJ",
    "sg:province":"West Lothian",
    "wof:name":"BLACKRIDGE POST OFFICE",
    "wof:placetype":"venue"
},
  "geometry": {"coordinates":[-3.771669,55.884369],"type":"Point"}
}