{
  "type": "Feature",
  "properties": {
    "iso:country":"GB",
    "sg:address":"Cramley Court",
    "sg:city":"South Petherton",
    "sg:classifiers":[
        {
            "category":"Building & Trades",
            "subcategory":"Plumbing",
            "type":"Services"
        }
    ],
    "sg:phone":"+44 1460 240519",
    "sg:postcode":"TA13 5EA",
    "sg:province":"Somerset",
    "sg:tags":[
        "heating"
    ],
    "wof:name":"Beale Heating Co",
    "wof:placetype":"venue"
},
  "geometry": {"coordinates":[-2.805539,50.949532],"type":"Point"}
}