{
  "type": "Feature",
  "properties": {
    "addr:full":"St Dominick Saltash Cornwall PL12 6SQ",
    "addr:postcode":"pl12 6sq",
    "addr:street":"St",
    "iso:country":"GB",
    "sg:address":"St Dominick",
    "sg:city":"Saltash",
    "sg:classifiers":[
        {
            "category":"Farming",
            "subcategory":"Livestock Farm",
            "type":"Manufacturing & Wholesale Goods"
        }
    ],
    "sg:phone":"+44 1579 350410",
    "sg:postcode":"PL12 6SQ",
    "sg:province":"Cornwall",
    "sg:tags":[
        "others"
    ],
    "wof:name":"D H Daw & Son",
    "wof:placetype":"venue"
},
  "geometry": {"coordinates":[-4.2634601593,50.4853401184],"type":"Point"}
}