{
  "type": "Feature",
  "properties": {
    "addr:full":"104 West Parade Rhyl Conwy LL18 1HP",
    "addr:housenumber":"104",
    "addr:postcode":"ll18 1hp",
    "addr:street":"West Parade",
    "iso:country":"GB",
    "sg:address":"104 West Parade",
    "sg:city":"Rhyl",
    "sg:classifiers":[
        {
            "category":"Recreation",
            "subcategory":"Amusement Park",
            "type":"Entertainment"
        }
    ],
    "sg:phone":"+44 1745 342092",
    "sg:postcode":"LL18 1HP",
    "sg:province":"Conwy",
    "sg:tags":[
        "arcade"
    ],
    "wof:name":"Baylis Amusements",
    "wof:placetype":"venue"
},
  "geometry": {"coordinates":[-3.4919390678,53.3224906921],"type":"Point"}
}