{
  "type": "Feature",
  "properties": {
    "addr:full":"The Vicarage, Woodbury Exeter Devon EX5 1EF",
    "addr:postcode":"ex5 1ef",
    "addr:street":"Woodbury",
    "iso:country":"GB",
    "sg:address":"The Vicarage, Woodbury",
    "sg:city":"Exeter",
    "sg:classifiers":[
        {
            "category":"Place Of Worship",
            "type":"Public Place"
        }
    ],
    "sg:phone":"+44 1395 232315",
    "sg:postcode":"EX5 1EF",
    "sg:province":"Devon",
    "wof:name":"St Swithun C Of E Church",
    "wof:placetype":"venue"
},
  "geometry": {"coordinates":[-3.40239,50.673195],"type":"Point"}
}