{
  "type": "Feature",
  "properties": {
    "addr:full":"Marton Rd Middlesbrough North Yorkshire TS4 3BS",
    "addr:postcode":"ts4 3bs",
    "addr:street":"Marton Rd",
    "iso:country":"GB",
    "sg:address":"Marton Rd",
    "sg:city":"Middlesbrough",
    "sg:classifiers":[
        {
            "category":"Travel",
            "subcategory":"Hotels & Motels",
            "type":"Entertainment"
        }
    ],
    "sg:phone":"+44 1642 817651",
    "sg:postcode":"TS4 3BS",
    "sg:province":"North Yorkshire",
    "wof:name":"Marton Way Toby",
    "wof:placetype":"venue"
},
  "geometry": {"coordinates":[-1.2219779491,54.5562095642],"type":"Point"}
}