{
  "type": "Feature",
  "properties": {
    "iso:country":"GB",
    "sg:address":"24 Hammond Close",
    "sg:city":"Hampton",
    "sg:classifiers":[
        {
            "category":"Building & Trades",
            "subcategory":"Cleaning & Sanitation",
            "type":"Services"
        }
    ],
    "sg:phone":"+44 20 8783 1333",
    "sg:postcode":"TW12 2DE",
    "sg:province":"Greater London",
    "sg:tags":[
        "commercial"
    ],
    "wof:name":"Window & Office Cleaning",
    "wof:placetype":"venue"
},
  "geometry": {"coordinates":[-0.3751260042,51.4140815735],"type":"Point"}
}