{
  "type": "Feature",
  "properties": {
    "addr:full":"Pinfold Lane Stafford Shropshire ST19 9PD",
    "addr:postcode":"st19 9pd",
    "addr:street":"Pinfold Lane",
    "iso:country":"GB",
    "sg:address":"Pinfold Lane",
    "sg:city":"Stafford",
    "sg:classifiers":[
        {
            "category":"Professional",
            "subcategory":"Art Services",
            "type":"Services"
        }
    ],
    "sg:phone":"+44 1785 840308",
    "sg:postcode":"ST19 9PD",
    "sg:province":"Shropshire",
    "sg:tags":[
        "model",
        "maker"
    ],
    "wof:name":"S H G Model Supplies",
    "wof:placetype":"venue"
},
  "geometry": {"coordinates":[-2.224834,52.712566],"type":"Point"}
}