{
  "type": "Feature",
  "properties": {
    "iso:country":"GB",
    "sg:address":"105 Durham Road, Blackhill",
    "sg:city":"Consett",
    "sg:classifiers":[
        {
            "category":"Food & Beverages",
            "subcategory":"Bakery",
            "type":"Retail Goods"
        }
    ],
    "sg:phone":"+44 1207 581221",
    "sg:postcode":"DH8 8RP",
    "sg:province":"Durham",
    "sg:tags":[
        "baker"
    ],
    "wof:name":"Harrisons",
    "wof:placetype":"venue"
},
  "geometry": {"coordinates":[-1.8485120535,54.8611488342],"type":"Point"}
}