{
  "type": "Feature",
  "properties": {
    "iso:country":"GB",
    "sg:address":"1 Littlemill Road, Drongan",
    "sg:city":"Ayr",
    "sg:classifiers":[
        {
            "category":"Professional",
            "subcategory":"Business Services",
            "type":"Services"
        }
    ],
    "sg:phone":"+44 1292 591984",
    "sg:postcode":"KA6 7BP",
    "sg:province":"East Ayrshire",
    "sg:tags":[
        "distribution"
    ],
    "wof:name":"Wincanton Distribution",
    "wof:placetype":"venue"
},
  "geometry": {"coordinates":[-4.458089,55.437561],"type":"Point"}
}