{
  "type": "Feature",
  "properties": {
    "addr:full":"77 Fancourt Avenue Wolverhampton Staffordshire WV4 4HZ",
    "addr:housenumber":"77",
    "addr:postcode":"wv4 4hz",
    "addr:street":"Fancourt Avenue",
    "iso:country":"GB",
    "sg:address":"77 Fancourt Avenue",
    "sg:city":"Wolverhampton",
    "sg:classifiers":[
        {
            "category":"Arts & Performance",
            "subcategory":"Art Gallery",
            "type":"Entertainment"
        }
    ],
    "sg:postcode":"WV4 4HZ",
    "sg:province":"Staffordshire",
    "wof:name":"Lamb Antique Fine Art",
    "wof:placetype":"venue"
},
  "geometry": {"coordinates":[-2.1644310951,52.5620651245],"type":"Point"}
}