{
  "type": "Feature",
  "properties": {
    "addr:full":"34 Bower Mount Road Maidstone Kent ME16 8AU",
    "addr:housenumber":"34",
    "addr:postcode":"me16 8au",
    "addr:street":"Bower Mount Road",
    "iso:country":"GB",
    "sg:address":"34 Bower Mount Road",
    "sg:city":"Maidstone",
    "sg:classifiers":[
        {
            "category":"Professional",
            "subcategory":"Business Services",
            "type":"Services"
        }
    ],
    "sg:postcode":"ME16 8AU",
    "sg:province":"Kent",
    "sg:tags":[
        "import",
        "export",
        "agent"
    ],
    "wof:name":"Levitt Tomkins Limited",
    "wof:placetype":"venue"
},
  "geometry": {"coordinates":[0.505934,51.273029],"type":"Point"}
}