{
  "type": "Feature",
  "properties": {
    "iso:country":"GB",
    "sg:address":"Studio 1 Garden Cottage",
    "sg:city":"Alresford",
    "sg:classifiers":[
        {
            "category":"Professional",
            "subcategory":"Art Services",
            "type":"Services"
        }
    ],
    "sg:phone":"+44 1962 736466",
    "sg:postcode":"SO24 0QU",
    "sg:province":"Hampshire",
    "sg:tags":[
        "photographer"
    ],
    "wof:name":"Comfortable Maxwell Photography",
    "wof:placetype":"venue"
},
  "geometry": {"coordinates":[-1.20149,51.08778],"type":"Point"}
}