{
  "type": "Feature",
  "properties": {
    "iso:country":"GB",
    "sg:address":"296 Haydons Road",
    "sg:city":"London",
    "sg:classifiers":[
        {
            "category":"Fast Food",
            "type":"Food & Drink"
        }
    ],
    "sg:phone":"+44 20 8543 4008",
    "sg:postcode":"SW19 8JZ",
    "sg:province":"Greater London",
    "sg:tags":[
        "away",
        "take"
    ],
    "wof:name":"R K Indian Takeaway",
    "wof:placetype":"venue"
},
  "geometry": {"coordinates":[-0.19054,51.426392],"type":"Point"}
}