{
  "type": "Feature",
  "properties": {
    "addr:full":"248 Collier Row Lane Romford Essex RM5 3JB",
    "addr:housenumber":"248",
    "addr:postcode":"rm5 3jb",
    "addr:street":"Collier Row Lane",
    "iso:country":"GB",
    "sg:address":"248 Collier Row Lane",
    "sg:city":"Romford",
    "sg:classifiers":[
        {
            "category":"Bars & Pubs",
            "type":"Food & Drink"
        }
    ],
    "sg:phone":"+44 1708 765080",
    "sg:postcode":"RM5 3JB",
    "sg:province":"Essex",
    "sg:tags":[
        "pubs",
        "inn"
    ],
    "wof:name":"The Bell & Gate",
    "wof:placetype":"venue"
},
  "geometry": {"coordinates":[0.1644439995,51.5955734253],"type":"Point"}
}