{
  "type": "Feature",
  "properties": {
    "iso:country":"GB",
    "sg:address":"29 Hole House Lane, Stocksbridge",
    "sg:city":"Sheffield",
    "sg:classifiers":[
        {
            "category":"Home & Garden",
            "subcategory":"Building Materials",
            "type":"Retail Goods"
        }
    ],
    "sg:phone":"+44 114 288 7411",
    "sg:postcode":"S36 1BS",
    "sg:province":"South Yorkshire",
    "sg:tags":[
        "ironwork",
        "wrought"
    ],
    "wof:name":"Graces Ornamental Iron Work",
    "wof:placetype":"venue"
},
  "geometry": {"coordinates":[-1.5969209671,53.4812316895],"type":"Point"}
}