{
  "type": "Feature",
  "properties": {
    "iso:country":"GB",
    "sg:address":"34-36 Longton Market",
    "sg:city":"Stoke On Trent",
    "sg:classifiers":[
        {
            "category":"Manufacturing",
            "subcategory":"Textiles",
            "type":"Manufacturing & Wholesale Goods"
        }
    ],
    "sg:phone":"+44 1782 314679",
    "sg:postcode":"ST3 1BS",
    "sg:province":"Staffordshire",
    "sg:tags":[
        "made-up"
    ],
    "wof:name":"Andrews Bedding Store",
    "wof:placetype":"venue"
},
  "geometry": {"coordinates":[-2.1929779053,52.9647941589],"type":"Point"}
}