{
  "type": "Feature",
  "properties": {
    "addr:full":"26 Main St Skipton Lancashire BD23 6RE",
    "addr:housenumber":"26",
    "addr:postcode":"bd23 6re",
    "addr:street":"Main St",
    "iso:country":"GB",
    "sg:address":"26 Main St",
    "sg:city":"Skipton",
    "sg:classifiers":[
        {
            "category":"Manufacturing",
            "subcategory":"Signs",
            "type":"Manufacturing & Wholesale Goods"
        }
    ],
    "sg:phone":"+44 1756 798474",
    "sg:postcode":"BD23 6RE",
    "sg:province":"Lancashire",
    "sg:tags":[
        "writer"
    ],
    "wof:name":"I J Crocker",
    "wof:placetype":"venue"
},
  "geometry": {"coordinates":[-1.984867,53.980789],"type":"Point"}
}