{
  "type": "Feature",
  "properties": {
    "addr:full":"Blackdown Clinic, Blackdown Leamington Spa Warwickshire CV32 6RW",
    "addr:postcode":"cv32 6rw",
    "addr:street":"Blackdown",
    "iso:country":"GB",
    "sg:address":"Blackdown Clinic, Blackdown",
    "sg:city":"Leamington Spa",
    "sg:classifiers":[
        {
            "category":"Professional",
            "subcategory":"Lawyer & Legal Services",
            "type":"Services"
        }
    ],
    "sg:phone":"+44 1926 334664",
    "sg:postcode":"CV32 6RW",
    "sg:province":"Warwickshire",
    "sg:tags":[
        "advice",
        "counselling"
    ],
    "wof:name":"British Pregnancy Advisory Service",
    "wof:placetype":"venue"
},
  "geometry": {"coordinates":[-1.536614,52.31509],"type":"Point"}
}