{
  "type": "Feature",
  "properties": {
    "iso:country":"GB",
    "sg:address":"540 Durham Road, Low Fell",
    "sg:city":"Gateshead",
    "sg:classifiers":[
        {
            "category":"Food & Beverages",
            "subcategory":"Liquor & Beverages",
            "type":"Retail Goods"
        }
    ],
    "sg:phone":"+44 191 491 3544",
    "sg:postcode":"NE9 6HX",
    "sg:province":"Tyne and Wear",
    "sg:tags":[
        "beer",
        "spirit",
        "wines"
    ],
    "wof:name":"Victoria Wine",
    "wof:placetype":"venue"
},
  "geometry": {"coordinates":[-1.599752,54.93568],"type":"Point"}
}