{
  "type": "Feature",
  "properties": {
    "addr:full":"35a Long Acre Nottingham Leicestershire NG13 8AF",
    "addr:housenumber":"35a",
    "addr:postcode":"ng13 8af",
    "addr:street":"Long Acre",
    "iso:country":"GB",
    "sg:address":"35a Long Acre",
    "sg:city":"Nottingham",
    "sg:classifiers":[
        {
            "category":"Shopping",
            "subcategory":"Thrift Store",
            "type":"Retail Goods"
        }
    ],
    "sg:phone":"+44 1949 836790",
    "sg:postcode":"NG13 8AF",
    "sg:province":"Leicestershire",
    "sg:tags":[
        "shop",
        "charity"
    ],
    "wof:name":"Winged Fellowship Charity Shop The",
    "wof:placetype":"venue"
},
  "geometry": {"coordinates":[-0.9534010291,52.9514808655],"type":"Point"}
}