{
  "type": "Feature",
  "properties": {
    "iso:country":"GB",
    "sg:address":"666 Coventry Road, Small Heath",
    "sg:city":"Birmingham",
    "sg:classifiers":[
        {
            "category":"Shopping",
            "subcategory":"Pharmacy",
            "type":"Retail Goods"
        }
    ],
    "sg:postcode":"B10 0UU",
    "sg:province":"West Midlands",
    "sg:tags":[
        "pharmacist",
        "chemist"
    ],
    "wof:name":"Medicare Chemists",
    "wof:placetype":"venue"
},
  "geometry": {"coordinates":[-1.850091,52.467121],"type":"Point"}
}