{
  "type": "Feature",
  "properties": {
    "iso:country":"GB",
    "sg:address":"59 Morrish Road",
    "sg:city":"London",
    "sg:classifiers":[
        {
            "category":"Fast Food",
            "type":"Food & Drink"
        }
    ],
    "sg:phone":"+44 20 8674 5891",
    "sg:postcode":"SW2 4EG",
    "sg:province":"Greater London",
    "sg:tags":[
        "away",
        "take"
    ],
    "wof:name":"Balti House",
    "wof:placetype":"venue"
},
  "geometry": {"coordinates":[-0.124729,51.44627],"type":"Point"}
}