{
  "type": "Feature",
  "properties": {
    "iso:country":"GB",
    "sg:address":"5 Willow Street, Girlington",
    "sg:city":"Bradford",
    "sg:classifiers":[
        {
            "category":"Education",
            "subcategory":"Dance Studio",
            "type":"Public Place"
        }
    ],
    "sg:postcode":"BD8 9LT",
    "sg:province":"West Yorkshire",
    "sg:tags":[
        "school",
        "dancing"
    ],
    "wof:name":"The Windsor Ballroom",
    "wof:placetype":"venue"
},
  "geometry": {"coordinates":[-1.7858170271,53.800075531],"type":"Point"}
}