{
  "type": "Feature",
  "properties": {
    "addr:full":"55 Sidford High Street, Sidford Sidmouth Devon EX10 9SH",
    "addr:housenumber":"55",
    "addr:postcode":"ex10 9sh",
    "addr:street":"Sidford High Street",
    "iso:country":"GB",
    "sg:address":"55 Sidford High Street, Sidford",
    "sg:city":"Sidmouth",
    "sg:classifiers":[
        {
            "category":"Health Services",
            "subcategory":"Dentist",
            "type":"Services"
        }
    ],
    "sg:phone":"+44 1395 512977",
    "sg:postcode":"EX10 9SH",
    "sg:province":"Devon",
    "sg:tags":[
        "technician",
        "dental"
    ],
    "wof:name":"Brian Godbeer",
    "wof:placetype":"venue"
},
  "geometry": {"coordinates":[-3.2344739437,50.702381134],"type":"Point"}
}