{
  "type": "Feature",
  "properties": {
    "addr:full":"The Old Blacksmith Shop, 82 Commonside Brierley Hill West Midlands DY5 4AJ",
    "addr:housenumber":"82",
    "addr:postcode":"dy5 4aj",
    "addr:street":"Commonside Brierley Hill",
    "iso:country":"GB",
    "sg:address":"The Old Blacksmith Shop, 82 Commonside",
    "sg:city":"Brierley Hill",
    "sg:classifiers":[
        {
            "category":"Building & Trades",
            "subcategory":"Construction",
            "type":"Services"
        }
    ],
    "sg:postcode":"DY5 4AJ",
    "sg:province":"West Midlands",
    "sg:tags":[
        "joinery"
    ],
    "wof:name":"P & P Dean Joinery",
    "wof:placetype":"venue"
},
  "geometry": {"coordinates":[-2.121301,52.482044],"type":"Point"}
}