{
  "type": "Feature",
  "properties": {
    "iso:country":"GB",
    "sg:address":"47 Lawrence Hill Rd",
    "sg:city":"Dartford",
    "sg:classifiers":[
        {
            "category":"Health Services",
            "subcategory":"Health Practitioner",
            "type":"Services"
        }
    ],
    "sg:phone":"+44 1322 220928",
    "sg:postcode":"DA1 3AG",
    "sg:province":"Kent",
    "sg:tags":[
        "acupuncture",
        "osteopath"
    ],
    "wof:name":"Sarah Breare",
    "wof:placetype":"venue"
},
  "geometry": {"coordinates":[0.2038609982,51.4483566284],"type":"Point"}
}