{
  "type": "Feature",
  "properties": {
    "iso:country":"GB",
    "sg:address":"30 Market St",
    "sg:city":"Birkenhead",
    "sg:classifiers":[
        {
            "category":"Home & Garden",
            "subcategory":"Building Materials",
            "type":"Retail Goods"
        }
    ],
    "sg:phone":"+44 151 666 2625",
    "sg:postcode":"CH41 5ER",
    "sg:province":"Merseyside",
    "sg:tags":[
        "foam"
    ],
    "wof:name":"Colemans Cut Foam & Upholstery Supplies",
    "wof:placetype":"venue"
},
  "geometry": {"coordinates":[-3.015527,53.392216],"type":"Point"}
}