{
  "type": "Feature",
  "properties": {
    "addr:full":"79 High Street Swansea Carmarthenshire SA4 4BL",
    "addr:housenumber":"79",
    "addr:postcode":"sa4 4bl",
    "addr:street":"High Street",
    "iso:country":"GB",
    "sg:address":"79 High Street",
    "sg:city":"Swansea",
    "sg:classifiers":[
        {
            "category":"Travel",
            "subcategory":"Travel Agent",
            "type":"Entertainment"
        }
    ],
    "sg:phone":"+44 1792 229400",
    "sg:postcode":"SA4 4BL",
    "sg:province":"Carmarthenshire",
    "wof:name":"The Travel House",
    "wof:placetype":"venue"
},
  "geometry": {"coordinates":[-4.040768,51.669155],"type":"Point"}
}