{
  "type": "Feature",
  "properties": {
    "addr:full":"Unit B8, Imperial Business Estate, West Mill Gravesend Kent DA11 0DL",
    "addr:postcode":"da11 0dl",
    "addr:street":"West Mill",
    "iso:country":"GB",
    "sg:address":"Unit B8, Imperial Business Estate, West Mill",
    "sg:city":"Gravesend",
    "sg:classifiers":[
        {
            "category":"Manufacturing",
            "subcategory":"Wood Products",
            "type":"Manufacturing & Wholesale Goods"
        },
        {
            "category":"Building & Trades",
            "subcategory":"Construction",
            "type":"Services"
        },
        {
            "category":"Manufacturing",
            "subcategory":"Lumber",
            "type":"Manufacturing & Wholesale Goods"
        }
    ],
    "sg:phone":"+44 1474 323234",
    "sg:postcode":"DA11 0DL",
    "sg:province":"Kent",
    "sg:tags":[
        "merchants",
        "joinery",
        "agent",
        "importer",
        "timber",
        "manufacturer"
    ],
    "wof:name":"Cox Joinery",
    "wof:placetype":"venue"
},
  "geometry": {"coordinates":[0.364606,51.432827],"type":"Point"}
}