{
  "type": "Feature",
  "properties": {
    "iso:country":"GB",
    "sg:address":"280 George St",
    "sg:city":"Aberdeen",
    "sg:classifiers":[
        {
            "category":"Professional",
            "subcategory":"Accounting & Tax Preparation",
            "type":"Services"
        }
    ],
    "sg:phone":"+44 1224 645654",
    "sg:postcode":"AB25 1HL",
    "sg:province":"Aberdeen City",
    "sg:tags":[
        "herb",
        "spice"
    ],
    "wof:name":"The Spice Shop",
    "wof:placetype":"venue"
},
  "geometry": {"coordinates":[-2.1033000946,57.1519165039],"type":"Point"}
}