{
  "type": "Feature",
  "properties": {
    "addr:full":"12 Lynford Avenue Winchester Hampshire SO22 6BN",
    "addr:housenumber":"12",
    "addr:postcode":"so22 6bn",
    "addr:street":"Lynford Avenue",
    "iso:country":"GB",
    "sg:address":"12 Lynford Avenue",
    "sg:city":"Winchester",
    "sg:classifiers":[
        {
            "category":"Shopping",
            "subcategory":"Catalog Store",
            "type":"Retail Goods"
        }
    ],
    "sg:phone":"+44 1962 855274",
    "sg:postcode":"SO22 6BN",
    "sg:province":"Hampshire",
    "sg:tags":[
        "mail",
        "order"
    ],
    "wof:name":"Kleeneze A-Z Direct Distributor",
    "wof:placetype":"venue"
},
  "geometry": {"coordinates":[-1.326273,51.074825],"type":"Point"}
}