{
  "type": "Feature",
  "properties": {
    "iso:country":"GB",
    "sg:address":"128 Western Way",
    "sg:city":"Basingstoke",
    "sg:classifiers":[
        {
            "category":"Building & Trades",
            "subcategory":"Construction",
            "type":"Services"
        }
    ],
    "sg:phone":"+44 1256 415546",
    "sg:postcode":"RG22 6ES",
    "sg:province":"Hampshire",
    "sg:tags":[
        "joiner",
        "carpenter"
    ],
    "wof:name":"In-line Carpentry Services",
    "wof:placetype":"venue"
},
  "geometry": {"coordinates":[-1.11352,51.255627],"type":"Point"}
}