{
  "type": "Feature",
  "properties": {
    "addr:full":"217 Primrose Crescent Perth Perth and Kinross PH1 2QL",
    "addr:housenumber":"217",
    "addr:postcode":"ph1 2ql",
    "addr:street":"Primrose Crescent",
    "iso:country":"GB",
    "sg:address":"217 Primrose Crescent",
    "sg:city":"Perth",
    "sg:classifiers":[
        {
            "category":"Professional",
            "subcategory":"Management & Consulting",
            "type":"Services"
        }
    ],
    "sg:postcode":"PH1 2QL",
    "sg:province":"Perth and Kinross",
    "sg:tags":[
        "marketing",
        "consultant"
    ],
    "wof:name":"North Marketing Services",
    "wof:placetype":"venue"
},
  "geometry": {"coordinates":[-3.4670920372,56.4136390686],"type":"Point"}
}