{
  "type": "Feature",
  "properties": {
    "addr:full":"Sceptre House, 57 The Hundred Romsey Hampshire SO51 8BZ",
    "addr:housenumber":"57",
    "addr:postcode":"so51 8bz",
    "addr:street":"The Hundred",
    "iso:country":"GB",
    "sg:address":"Sceptre House, 57 The Hundred",
    "sg:city":"Romsey",
    "sg:classifiers":[
        {
            "category":"Social Services",
            "subcategory":"Retirement Home",
            "type":"Services"
        }
    ],
    "sg:phone":"+44 1794 515127",
    "sg:postcode":"SO51 8BZ",
    "sg:province":"Hampshire",
    "sg:tags":[
        "care"
    ],
    "wof:name":"Homecare",
    "wof:placetype":"venue"
},
  "geometry": {"coordinates":[-1.495857954,50.9884872437],"type":"Point"}
}