{
  "type": "Feature",
  "properties": {
    "addr:full":"Stangwrach, Llanfynydd Carmarthen Carmarthenshire SA32 7TG",
    "addr:postcode":"sa32 7tg",
    "addr:street":"Llanfynydd;Carmarthenshire",
    "iso:country":"GB",
    "sg:address":"Stangwrach, Llanfynydd",
    "sg:city":"Carmarthen",
    "sg:classifiers":[
        {
            "category":"Home & Garden",
            "subcategory":"Home Furnishings",
            "type":"Retail Goods"
        }
    ],
    "sg:postcode":"SA32 7TG",
    "sg:province":"Carmarthenshire",
    "sg:tags":[
        "patio",
        "furniture"
    ],
    "wof:name":"Stangwrach Garden Furniture",
    "wof:placetype":"venue"
},
  "geometry": {"coordinates":[-4.098479,51.928185],"type":"Point"}
}