{
  "type": "Feature",
  "properties": {
    "iso:country":"GB",
    "sg:address":"Great Osbaston Farm, Osbaston",
    "sg:city":"Monmouth",
    "sg:classifiers":[
        {
            "category":"Farming",
            "subcategory":"Vineyard",
            "type":"Manufacturing & Wholesale Goods"
        }
    ],
    "sg:postcode":"NP25 5DL",
    "sg:province":"Gloucestershire",
    "wof:name":"Monnow Valley Vineyards",
    "wof:placetype":"venue"
},
  "geometry": {"coordinates":[-2.7257010937,51.8232345581],"type":"Point"}
}