{
  "type": "Feature",
  "properties": {
    "iso:country":"GB",
    "sg:address":"108-110 Napiershall St",
    "sg:city":"Glasgow",
    "sg:classifiers":[
        {
            "category":"Building & Trades",
            "subcategory":"Construction",
            "type":"Services"
        }
    ],
    "sg:phone":"+44 141 353 0463",
    "sg:postcode":"G20 6HS",
    "sg:province":"Glasgow City",
    "sg:tags":[
        "decorator",
        "painter"
    ],
    "wof:name":"Grovebank Decorators Ltd",
    "wof:placetype":"venue"
},
  "geometry": {"coordinates":[-4.2718830109,55.8758926392],"type":"Point"}
}