{
  "type": "Feature",
  "properties": {
    "iso:country":"GB",
    "sg:address":"Prescott Speed Hill Climb, Gotherington",
    "sg:city":"Cheltenham",
    "sg:classifiers":[
        {
            "category":"Retail",
            "subcategory":"Event Space",
            "type":"Services"
        }
    ],
    "sg:postcode":"GL52 9RD",
    "sg:province":"Gloucestershire",
    "sg:tags":[
        "function",
        "room"
    ],
    "wof:name":"Prescott Lodge",
    "wof:placetype":"venue"
},
  "geometry": {"coordinates":[-2.0561490059,51.9652404785],"type":"Point"}
}