{
  "type": "Feature",
  "properties": {
    "addr:full":"25 Meadow Drive Bude Cornwall EX23 8HZ",
    "addr:housenumber":"25",
    "addr:postcode":"ex23 8hz",
    "addr:street":"Meadow Drive",
    "iso:country":"GB",
    "sg:address":"25 Meadow Drive",
    "sg:city":"Bude",
    "sg:classifiers":[
        {
            "category":"Building & Trades",
            "subcategory":"Landscaping Services",
            "type":"Services"
        },
        {
            "category":"Banks & Credit Unions",
            "subcategory":"Investment Brokerage",
            "type":"Services"
        }
    ],
    "sg:phone":"+44 1288 355006",
    "sg:postcode":"EX23 8HZ",
    "sg:province":"Cornwall",
    "sg:tags":[
        "gardening",
        "contractor"
    ],
    "wof:name":"S T A DINNIS",
    "wof:placetype":"venue"
},
  "geometry": {"coordinates":[-4.5356521606,50.8339538574],"type":"Point"}
}