{
  "type": "Feature",
  "properties": {
    "iso:country":"GB",
    "sg:address":"30b Ashley Road",
    "sg:city":"Bournemouth",
    "sg:classifiers":[
        {
            "category":"Shopping",
            "subcategory":"Books",
            "type":"Retail Goods"
        }
    ],
    "sg:postcode":"BH1 4LH",
    "sg:province":"Dorset",
    "sg:tags":[
        "second-hand"
    ],
    "wof:name":"Ashley Bookshop",
    "wof:placetype":"venue"
},
  "geometry": {"coordinates":[-1.8377850056,50.7282600403],"type":"Point"}
}