{
  "type": "Feature",
  "properties": {
    "iso:country":"GB",
    "sg:address":"47 Stamford Street, Mossley",
    "sg:city":"Ashton-under-lyne",
    "sg:classifiers":[
        {
            "category":"Professional",
            "subcategory":"Detective & Security Services",
            "type":"Services"
        }
    ],
    "sg:phone":"+44 1457 838007",
    "sg:postcode":"OL5 0LN",
    "sg:province":"Greater Manchester",
    "wof:name":"Eagle Retail Security Services",
    "wof:placetype":"venue"
},
  "geometry": {"coordinates":[-2.0469288826,53.518032074],"type":"Point"}
}