{
  "type": "Feature",
  "properties": {
    "iso:country":"GB",
    "sg:address":"67 The Terrace",
    "sg:city":"Penryn",
    "sg:classifiers":[
        {
            "category":"Manufacturing",
            "subcategory":"Textiles",
            "type":"Manufacturing & Wholesale Goods"
        }
    ],
    "sg:phone":"+44 1326 377310",
    "sg:postcode":"TR10 8EH",
    "sg:province":"Cornwall",
    "sg:tags":[
        "designer"
    ],
    "wof:name":"1st Impressions",
    "wof:placetype":"venue"
},
  "geometry": {"coordinates":[-5.104809,50.168575],"type":"Point"}
}