{
  "type": "Feature",
  "properties": {
    "addr:full":"41 Maple Drive Huntingdon Cambridgeshire PE29 7JE",
    "addr:housenumber":"41",
    "addr:postcode":"pe29 7je",
    "addr:street":"Maple Drive",
    "iso:country":"GB",
    "sg:address":"41 Maple Drive",
    "sg:city":"Huntingdon",
    "sg:classifiers":[
        {
            "category":"Military Area",
            "subcategory":"Air Force Base",
            "type":"Public Place"
        }
    ],
    "sg:phone":"+44 1480 453342",
    "sg:postcode":"PE29 7JE",
    "sg:province":"Cambridgeshire",
    "sg:tags":[
        "taxi",
        "hire",
        "private"
    ],
    "wof:name":"Ace Taxis",
    "wof:placetype":"venue"
},
  "geometry": {"coordinates":[-0.1778170019,52.3457603455],"type":"Point"}
}