{
  "type": "Feature",
  "properties": {
    "iso:country":"GB",
    "sg:address":"9 Great Bowden Road",
    "sg:city":"Market Harborough",
    "sg:classifiers":[
        {
            "category":"Farming",
            "subcategory":"Nursery",
            "type":"Manufacturing & Wholesale Goods"
        },
        {
            "category":"Social Services",
            "subcategory":"Child Care",
            "type":"Services"
        }
    ],
    "sg:phone":"+44 1858 468006",
    "sg:postcode":"LE16 7DE",
    "sg:province":"Leicestershire",
    "sg:tags":[
        "creche"
    ],
    "wof:name":"Castle Lane Day Nursery",
    "wof:placetype":"venue"
},
  "geometry": {"coordinates":[-0.9116060138,52.4794158936],"type":"Point"}
}