{
  "type": "Feature",
  "properties": {
    "iso:country":"GB",
    "sg:address":"91 Main St, Stoneyburn",
    "sg:city":"Bathgate",
    "sg:classifiers":[
        {
            "category":"Building & Trades",
            "subcategory":"Construction",
            "type":"Services"
        }
    ],
    "sg:postcode":"EH47 8EL",
    "sg:province":"North Lanarkshire",
    "sg:tags":[
        "joiner",
        "carpenter"
    ],
    "wof:name":"Ovens,C,& Sons",
    "wof:placetype":"venue"
},
  "geometry": {"coordinates":[-3.6420919895,55.8444671631],"type":"Point"}
}