{
  "type": "Feature",
  "properties": {
    "addr:full":"Hebble Brook Business Park, Hays Lane Halifax West Yorkshire HX2 8UL",
    "addr:postcode":"hx2 8ul",
    "addr:street":"Hebble Brook Business Park Hays Lane",
    "iso:country":"GB",
    "sg:address":"Hebble Brook Business Park, Hays Lane",
    "sg:city":"Halifax",
    "sg:classifiers":[
        {
            "category":"Insurance",
            "subcategory":"Insurance Agent",
            "type":"Services"
        }
    ],
    "sg:phone":"+44 1422 243333",
    "sg:postcode":"HX2 8UL",
    "sg:province":"West Yorkshire",
    "wof:name":"Colonnade Insurance Brokers Ltd.",
    "wof:placetype":"venue"
},
  "geometry": {"coordinates":[-1.8865690231,53.7428207397],"type":"Point"}
}