{
  "type": "Feature",
  "properties": {
    "iso:country":"GB",
    "sg:address":"22 Harrington Road",
    "sg:city":"Workington",
    "sg:classifiers":[
        {
            "category":"Food & Beverages",
            "subcategory":"Specialty",
            "type":"Retail Goods"
        },
        {
            "category":"Food & Beverages",
            "subcategory":"Supermarket",
            "type":"Retail Goods"
        }
    ],
    "sg:phone":"+44 1900 66132",
    "sg:postcode":"CA14 3ED",
    "sg:province":"Cumbria",
    "sg:tags":[
        "retailer",
        "health"
    ],
    "wof:name":"Golden Harvest Health Foods",
    "wof:placetype":"venue"
},
  "geometry": {"coordinates":[-3.5508890152,54.6388816833],"type":"Point"}
}