{
  "type": "Feature",
  "properties": {
    "addr:full":"Unit 20, Moss Side Ind Est Callington Cornwall PL17 7XG",
    "addr:housenumber":"unit 20",
    "addr:postcode":"pl17 7xg",
    "addr:street":"Moss Side;Est",
    "iso:country":"GB",
    "sg:address":"Unit 20, Moss Side Ind Est",
    "sg:city":"Callington",
    "sg:classifiers":[
        {
            "category":"Autos & Motor Vehicles",
            "subcategory":"Automobile Sales",
            "type":"Retail Goods"
        }
    ],
    "sg:phone":"+44 1579 384180",
    "sg:postcode":"PL17 7XG",
    "sg:province":"Cornwall",
    "sg:tags":[
        "commercial"
    ],
    "wof:name":"Sellecks Volvo",
    "wof:placetype":"venue"
},
  "geometry": {"coordinates":[-4.3104901314,50.5004081726],"type":"Point"}
}