{
  "type": "Feature",
  "properties": {
    "addr:full":"10 12 Finch Dv, Springwood Industrial Estate Braintree Essex CM7 2SS",
    "addr:housenumber":"12",
    "addr:postcode":"cm7 2ss",
    "addr:street":"Finch Dv;Industrial Estate",
    "iso:country":"GB",
    "sg:address":"10 12 Finch Dv, Springwood Industrial Estate",
    "sg:city":"Braintree",
    "sg:classifiers":[
        {
            "category":"Personal",
            "type":"Services"
        }
    ],
    "sg:phone":"+44 1376 326556",
    "sg:postcode":"CM7 2SS",
    "sg:province":"Essex",
    "sg:tags":[
        "delivery"
    ],
    "wof:name":"Business Post",
    "wof:placetype":"venue"
},
  "geometry": {"coordinates":[0.534644,51.87915],"type":"Point"}
}