{
  "type": "Feature",
  "properties": {
    "iso:country":"GB",
    "sg:address":"6 Ness Bank",
    "sg:city":"Inverness",
    "sg:classifiers":[
        {
            "category":"Health Services",
            "subcategory":"Dentist",
            "type":"Services"
        }
    ],
    "sg:phone":"+44 1463 236295",
    "sg:postcode":"IV2 4SF",
    "sg:province":"Highland",
    "wof:name":"A Graham",
    "wof:placetype":"venue"
},
  "geometry": {"coordinates":[-4.226215,57.474415],"type":"Point"}
}