{
  "type": "Feature",
  "properties": {
    "addr:full":"5a5 Millsborough Ho Redditch Warwickshire B98 7AL",
    "addr:housenumber":"5a5",
    "addr:postcode":"b98 7al",
    "addr:street":"Millsborough Ho",
    "iso:country":"GB",
    "sg:address":"5a5 Millsborough Ho",
    "sg:city":"Redditch",
    "sg:classifiers":[
        {
            "category":"Professional",
            "subcategory":"Business Services",
            "type":"Services"
        }
    ],
    "sg:postcode":"B98 7AL",
    "sg:province":"Warwickshire",
    "sg:tags":[
        "import",
        "export",
        "agent"
    ],
    "wof:name":"Watson - Harris Partnership (The)",
    "wof:placetype":"venue"
},
  "geometry": {"coordinates":[-1.9365099669,52.3045196533],"type":"Point"}
}