{
  "type": "Feature",
  "properties": {
    "addr:full":"1 Haxter Close, Roborough Plymouth Devon PL6 7DD",
    "addr:housenumber":"1",
    "addr:postcode":"pl6 7dd",
    "addr:street":"Haxter Close",
    "iso:country":"GB",
    "sg:address":"1 Haxter Close, Roborough",
    "sg:city":"Plymouth",
    "sg:classifiers":[
        {
            "category":"Government",
            "subcategory":"Post Office",
            "type":"Public Place"
        }
    ],
    "sg:postcode":"PL6 7DD",
    "sg:province":"Devon",
    "sg:tags":[
        "messenger",
        "courier"
    ],
    "wof:name":"Rod Huntley",
    "wof:placetype":"venue"
},
  "geometry": {"coordinates":[-4.1154341698,50.441280365],"type":"Point"}
}