{
  "type": "Feature",
  "properties": {
    "addr:full":"27 Grange Way, Houghton Regis Dunstable Bedfordshire LU5 5PR",
    "addr:housenumber":"27",
    "addr:postcode":"lu5 5pr",
    "addr:street":"Grange Way",
    "iso:country":"GB",
    "sg:address":"27 Grange Way, Houghton Regis",
    "sg:city":"Dunstable",
    "sg:classifiers":[
        {
            "category":"Building & Trades",
            "subcategory":"Construction",
            "type":"Services"
        }
    ],
    "sg:postcode":"LU5 5PR",
    "sg:province":"Bedfordshire",
    "sg:tags":[
        "bricklaying"
    ],
    "wof:name":"A H Byrne",
    "wof:placetype":"venue"
},
  "geometry": {"coordinates":[-0.5001580119,51.9114608765],"type":"Point"}
}