{
  "type": "Feature",
  "properties": {
    "addr:full":"85 Belmont St Swadlincote Derbyshire DE11 8JZ",
    "addr:housenumber":"85",
    "addr:postcode":"de11 8jz",
    "addr:street":"Belmont St",
    "iso:country":"GB",
    "sg:address":"85 Belmont St",
    "sg:city":"Swadlincote",
    "sg:classifiers":[
        {
            "category":"Home & Garden",
            "subcategory":"Building Materials",
            "type":"Retail Goods"
        }
    ],
    "sg:postcode":"DE11 8JZ",
    "sg:province":"Derbyshire",
    "sg:tags":[
        "fencing"
    ],
    "wof:name":"Worker,W,",
    "wof:placetype":"venue"
},
  "geometry": {"coordinates":[-1.556621,52.773914],"type":"Point"}
}