{
  "type": "Feature",
  "properties": {
    "iso:country":"GB",
    "sg:address":"4 Forster Rd",
    "sg:city":"Doncaster",
    "sg:classifiers":[
        {
            "category":"Freight",
            "type":"Transportation"
        }
    ],
    "sg:phone":"+44 1302 853443",
    "sg:postcode":"DN4 8JY",
    "sg:province":"South Yorkshire",
    "sg:tags":[
        "haulage",
        "road"
    ],
    "wof:name":"Direct Choice",
    "wof:placetype":"venue"
},
  "geometry": {"coordinates":[-1.149531,53.501255],"type":"Point"}
}