{
  "type": "Feature",
  "properties": {
    "iso:country":"GB",
    "sg:address":"36 New Road",
    "sg:city":"Eastleigh",
    "sg:classifiers":[
        {
            "category":"Professional",
            "subcategory":"Engineering",
            "type":"Services"
        }
    ],
    "sg:postcode":"SO50 8EN",
    "sg:province":"Hampshire",
    "sg:tags":[
        "gas",
        "engineer"
    ],
    "wof:name":"Patrick L Gibby",
    "wof:placetype":"venue"
},
  "geometry": {"coordinates":[-1.309196,50.966122],"type":"Point"}
}