{
  "type": "Feature",
  "properties": {
    "iso:country":"GB",
    "sg:address":"8 Milton Fields",
    "sg:city":"Chalfont St. Giles",
    "sg:classifiers":[
        {
            "category":"Building & Trades",
            "subcategory":"Plumbing",
            "type":"Services"
        }
    ],
    "sg:phone":"+44 1494 872631",
    "sg:postcode":"HP8 4ER",
    "sg:province":"Buckinghamshire",
    "sg:tags":[
        "plumber",
        "heating"
    ],
    "wof:name":"Paul Raine",
    "wof:placetype":"venue"
},
  "geometry": {"coordinates":[-0.577334,51.631016],"type":"Point"}
}