{
  "type": "Feature",
  "properties": {
    "addr:full":"Heddon Banks Farm, Heddon Banks, Heddon-on-the-wall Newcastle-upon-tyne Northumberland NE15 0BU",
    "addr:housenumber":"newcastle-upon-tyne",
    "addr:postcode":"ne15 0bu",
    "addr:street":"Northumberland",
    "iso:country":"GB",
    "sg:address":"Heddon Banks Farm, Heddon Banks, Heddon-on-the-wall",
    "sg:city":"Newcastle-upon-tyne",
    "sg:classifiers":[
        {
            "category":"Farming",
            "subcategory":"Livestock Farm",
            "type":"Manufacturing & Wholesale Goods"
        }
    ],
    "sg:postcode":"NE15 0BU",
    "sg:province":"Northumberland",
    "sg:tags":[
        "others"
    ],
    "wof:name":"A Watson",
    "wof:placetype":"venue"
},
  "geometry": {"coordinates":[-1.794768,54.997303],"type":"Point"}
}