{
  "type": "Feature",
  "properties": {
    "addr:full":"102 Longden Road Shrewsbury Shropshire SY3 7HS",
    "addr:housenumber":"102",
    "addr:postcode":"sy3 7hs",
    "addr:street":"Longden Road",
    "iso:country":"GB",
    "sg:address":"102 Longden Road",
    "sg:city":"Shrewsbury",
    "sg:classifiers":[
        {
            "category":"Shopping",
            "subcategory":"News",
            "type":"Retail Goods"
        }
    ],
    "sg:phone":"+44 1743 354076",
    "sg:postcode":"SY3 7HS",
    "sg:province":"Shropshire",
    "sg:tags":[
        "newsagent"
    ],
    "wof:name":"Beehive Stores",
    "wof:placetype":"venue"
},
  "geometry": {"coordinates":[-2.7602319717,52.6979255676],"type":"Point"}
}