{
  "type": "Feature",
  "properties": {
    "addr:full":"31 Maiden Street Weymouth Dorset DT4 8BA",
    "addr:housenumber":"31",
    "addr:postcode":"dt4 8ba",
    "addr:street":"Maiden Street",
    "iso:country":"GB",
    "sg:address":"31 Maiden Street",
    "sg:city":"Weymouth",
    "sg:classifiers":[
        {
            "category":"Fast Food",
            "type":"Food & Drink"
        }
    ],
    "sg:phone":"+44 1305 761317",
    "sg:postcode":"DT4 8BA",
    "sg:province":"Dorset",
    "sg:tags":[
        "away",
        "meal",
        "outlet",
        "take"
    ],
    "wof:name":"PICKNICS",
    "wof:placetype":"venue"
},
  "geometry": {"coordinates":[-2.4536271095,50.6086502075],"type":"Point"}
}