{
  "type": "Feature",
  "properties": {
    "addr:full":"Unit 7a Wheatley Hall Road Doncaster South Yorkshire DN2 4LP",
    "addr:housenumber":"unit 7a wheatley",
    "addr:postcode":"dn2 4lp",
    "addr:street":"Hall Road",
    "iso:country":"GB",
    "sg:address":"Unit 7a Wheatley Hall Road",
    "sg:city":"Doncaster",
    "sg:classifiers":[
        {
            "category":"Shopping",
            "subcategory":"Discount & Variety Stores",
            "type":"Retail Goods"
        }
    ],
    "sg:phone":"+44 1302 322052",
    "sg:postcode":"DN2 4LP",
    "sg:province":"South Yorkshire",
    "sg:tags":[
        "centre"
    ],
    "wof:name":"Poundstretcher Ltd.",
    "wof:placetype":"venue"
},
  "geometry": {"coordinates":[-1.1229590178,53.5340652466],"type":"Point"}
}