{
  "type": "Feature",
  "properties": {
    "iso:country":"GB",
    "sg:address":"33 Redhill Road, Northfield",
    "sg:city":"Birmingham",
    "sg:classifiers":[
        {
            "category":"Food & Beverages",
            "subcategory":"Supermarket",
            "type":"Retail Goods"
        },
        {
            "category":"Food & Beverages",
            "subcategory":"Groceries & Convenience Stores",
            "type":"Retail Goods"
        }
    ],
    "sg:phone":"+44 121 604 5757",
    "sg:postcode":"B31 3JS",
    "sg:province":"West Midlands",
    "wof:name":"K A P SUPERMARKET",
    "wof:placetype":"venue"
},
  "geometry": {"coordinates":[-1.9605489969,52.3987159729],"type":"Point"}
}