{
  "type": "Feature",
  "properties": {
    "addr:full":"Moor Allerton Centre Leeds North Yorkshire LS17 5NY",
    "addr:postcode":"ls17 5ny",
    "addr:street":"Leeds",
    "iso:country":"GB",
    "sg:address":"Moor Allerton Centre",
    "sg:city":"Leeds",
    "sg:classifiers":[
        {
            "category":"Shopping",
            "subcategory":"Pharmacy",
            "type":"Retail Goods"
        }
    ],
    "sg:phone":"+44 113 269 6462",
    "sg:postcode":"LS17 5NY",
    "sg:province":"North Yorkshire",
    "sg:tags":[
        "pharmacist",
        "chemist"
    ],
    "wof:name":"Moss Chemists",
    "wof:placetype":"venue"
},
  "geometry": {"coordinates":[-1.549536,53.84539],"type":"Point"}
}