{
  "type": "Feature",
  "properties": {
    "iso:country":"GB",
    "sg:address":"55 Fuller Way, Croxley Grn",
    "sg:city":"Rickmansworth",
    "sg:classifiers":[
        {
            "category":"Building & Trades",
            "subcategory":"Equipment Rental",
            "type":"Services"
        }
    ],
    "sg:phone":"+44 1923 779044",
    "sg:postcode":"WD3 3PL",
    "sg:province":"Hertfordshire",
    "sg:tags":[
        "plant",
        "machinery"
    ],
    "wof:name":"P Lawrence Plant Hire",
    "wof:placetype":"venue"
},
  "geometry": {"coordinates":[-0.449158,51.650223],"type":"Point"}
}