{
  "type": "Feature",
  "properties": {
    "addr:full":"9 Herron Way Truro Cornwall TR1 2XN",
    "addr:housenumber":"9",
    "addr:postcode":"tr1 2xn",
    "addr:street":"Herron Way",
    "iso:country":"GB",
    "sg:address":"9 Herron Way",
    "sg:city":"Truro",
    "sg:classifiers":[
        {
            "category":"Manufacturing",
            "subcategory":"Tools & Machinery",
            "type":"Manufacturing & Wholesale Goods"
        }
    ],
    "sg:phone":"+44 1872 266320",
    "sg:postcode":"TR1 2XN",
    "sg:province":"Cornwall",
    "sg:tags":[
        "monitoring",
        "temperature",
        "thermometer"
    ],
    "wof:name":"Silvertree Engineering Ltd.",
    "wof:placetype":"venue"
},
  "geometry": {"coordinates":[-5.0450220108,50.2508506775],"type":"Point"}
}