{
  "type": "Feature",
  "properties": {
    "addr:full":"240 Wellington Rd Birmingham West Midlands B20 2QL",
    "addr:housenumber":"240",
    "addr:postcode":"b20 2ql",
    "addr:street":"Wellington Rd",
    "iso:country":"GB",
    "sg:address":"240 Wellington Rd",
    "sg:city":"Birmingham",
    "sg:classifiers":[
        {
            "category":"Food & Beverages",
            "subcategory":"Candy",
            "type":"Retail Goods"
        }
    ],
    "sg:postcode":"B20 2QL",
    "sg:province":"West Midlands",
    "sg:tags":[
        "confectioner"
    ],
    "wof:name":"Priekh,J R,",
    "wof:placetype":"venue"
},
  "geometry": {"coordinates":[-1.904009,52.515697],"type":"Point"}
}