{
  "type": "Feature",
  "properties": {
    "iso:country":"GB",
    "sg:address":"Waterton Road",
    "sg:city":"Bridgend",
    "sg:classifiers":[
        {
            "category":"Wholesale",
            "subcategory":"Groceries",
            "type":"Manufacturing & Wholesale Goods"
        }
    ],
    "sg:phone":"+44 1656 660033",
    "sg:postcode":"CF31 3XS",
    "sg:province":"Bridgend",
    "sg:tags":[
        "food",
        "supplier",
        "drink"
    ],
    "wof:name":"Cearns & Brown Catering Supplies Ltd.",
    "wof:placetype":"venue"
},
  "geometry": {"coordinates":[-3.545669,51.494995],"type":"Point"}
}