{
  "type": "Feature",
  "properties": {
    "iso:country":"GB",
    "sg:address":"24 High Street, Erdington",
    "sg:city":"Birmingham",
    "sg:classifiers":[
        {
            "category":"Professional",
            "subcategory":"Lawyer & Legal Services",
            "type":"Services"
        }
    ],
    "sg:phone":"+44 121 373 7397",
    "sg:postcode":"B23 6RR",
    "sg:province":"West Midlands",
    "sg:tags":[
        "solicitor"
    ],
    "sg:website":"http://www.epar.co.uk",
    "wof:name":"Eddowes Perry Adams Roberts & Co.",
    "wof:placetype":"venue"
},
  "geometry": {"coordinates":[-1.8367079496,52.5264472961],"type":"Point"}
}