{
  "type": "Feature",
  "properties": {
    "addr:full":"72 Victoria St Perth Perth and Kinross PH2 8JS",
    "addr:housenumber":"72",
    "addr:postcode":"ph2 8js",
    "addr:street":"Victoria St",
    "iso:country":"GB",
    "sg:address":"72 Victoria St",
    "sg:city":"Perth",
    "sg:classifiers":[
        {
            "category":"Banks & Credit Unions",
            "subcategory":"Financial Services",
            "type":"Services"
        }
    ],
    "sg:phone":"+44 1738 630180",
    "sg:postcode":"PH2 8JS",
    "sg:province":"Perth and Kinross",
    "sg:tags":[
        "consultant"
    ],
    "wof:name":"Grampian Credit Services",
    "wof:placetype":"venue"
},
  "geometry": {"coordinates":[-3.4331960678,56.3933868408],"type":"Point"}
}