{
  "type": "Feature",
  "properties": {
    "iso:country":"GB",
    "sg:address":"29 Manor Drive",
    "sg:city":"Pickering",
    "sg:classifiers":[
        {
            "category":"Building & Trades",
            "subcategory":"Construction",
            "type":"Services"
        },
        {
            "category":"Manufacturing",
            "subcategory":"Building Materials",
            "type":"Manufacturing & Wholesale Goods"
        }
    ],
    "sg:phone":"+44 1751 474188",
    "sg:postcode":"YO18 8DF",
    "sg:province":"North Yorkshire",
    "sg:tags":[
        "tarmac",
        "paving",
        "asphalt",
        "contractor"
    ],
    "wof:name":"Keith Collier",
    "wof:placetype":"venue"
},
  "geometry": {"coordinates":[-0.792612,54.247513],"type":"Point"}
}