{
  "type": "Feature",
  "properties": {
    "addr:full":"27 Wheelock Street Middlewich Cheshire CW10 9AG",
    "addr:housenumber":"27",
    "addr:postcode":"cw10 9ag",
    "addr:street":"Wheelock Street",
    "iso:country":"GB",
    "sg:address":"27 Wheelock Street",
    "sg:city":"Middlewich",
    "sg:classifiers":[
        {
            "category":"Shopping",
            "subcategory":"Clothing, Apparel, & Fashions",
            "type":"Retail Goods"
        }
    ],
    "sg:phone":"+44 1606 834487",
    "sg:postcode":"CW10 9AG",
    "sg:province":"Cheshire",
    "sg:tags":[
        "shop"
    ],
    "wof:name":"Margaret's",
    "wof:placetype":"venue"
},
  "geometry": {"coordinates":[-2.446934,53.192917],"type":"Point"}
}