{
  "type": "Feature",
  "properties": {
    "addr:full":"The Old Bakehouse, Head Street Pershore Worcestershire WR10 1DA",
    "addr:postcode":"wr10 1da",
    "addr:street":"Head Street",
    "iso:country":"GB",
    "sg:address":"The Old Bakehouse, Head Street",
    "sg:city":"Pershore",
    "sg:classifiers":[
        {
            "category":"Government",
            "subcategory":"Post Office",
            "type":"Public Place"
        },
        {
            "category":"Home & Garden",
            "subcategory":"Carpets & Floor Coverings",
            "type":"Retail Goods"
        }
    ],
    "sg:phone":"+44 1386 556417",
    "sg:postcode":"WR10 1DA",
    "sg:province":"Worcestershire",
    "sg:tags":[
        "carpets",
        "messenger",
        "rug",
        "courier",
        "matting"
    ],
    "wof:name":"Jigsaw Carpets",
    "wof:placetype":"venue"
},
  "geometry": {"coordinates":[-2.079339,52.113766],"type":"Point"}
}