{
  "type": "Feature",
  "properties": {
    "addr:full":"16 Addington Close Bedford Bedfordshire MK41 9SP",
    "addr:housenumber":"16",
    "addr:postcode":"mk41 9sp",
    "addr:street":"Addington Close",
    "iso:country":"GB",
    "sg:address":"16 Addington Close",
    "sg:city":"Bedford",
    "sg:classifiers":[
        {
            "category":"Building & Trades",
            "subcategory":"Plumbing",
            "type":"Services"
        }
    ],
    "sg:phone":"+44 1234 355726",
    "sg:postcode":"MK41 9SP",
    "sg:province":"Bedfordshire",
    "sg:tags":[
        "central",
        "heating"
    ],
    "wof:name":"Jan Lesinski",
    "wof:placetype":"venue"
},
  "geometry": {"coordinates":[-0.433018,52.140106],"type":"Point"}
}