{
  "type": "Feature",
  "properties": {
    "iso:country":"GB",
    "sg:address":"187-189 Thorndon Avenue, West Horndon",
    "sg:city":"Brentwood",
    "sg:classifiers":[
        {
            "category":"Shopping",
            "subcategory":"News",
            "type":"Retail Goods"
        }
    ],
    "sg:phone":"+44 1277 811457",
    "sg:postcode":"CM13 3TP",
    "sg:province":"Essex",
    "sg:tags":[
        "newsagent"
    ],
    "wof:name":"Jacksons",
    "wof:placetype":"venue"
},
  "geometry": {"coordinates":[0.343441993,51.569606781],"type":"Point"}
}