{
  "type": "Feature",
  "properties": {
    "addr:full":"15 Catherine Rd, Crumpfall Manchester Greater Manchester M8 4HA",
    "addr:housenumber":"15",
    "addr:postcode":"m8 4ha",
    "addr:street":"Catherine Rd",
    "iso:country":"GB",
    "sg:address":"15 Catherine Rd, Crumpfall",
    "sg:city":"Manchester",
    "sg:classifiers":[
        {
            "category":"Building & Trades",
            "subcategory":"Construction",
            "type":"Services"
        }
    ],
    "sg:phone":"+44 161 740 1030",
    "sg:postcode":"M8 4HA",
    "sg:province":"Greater Manchester",
    "sg:tags":[
        "builder"
    ],
    "wof:name":"Alliance Builers & Plumbers",
    "wof:placetype":"venue"
},
  "geometry": {"coordinates":[-2.251031,53.517353],"type":"Point"}
}