{
  "type": "Feature",
  "properties": {
    "addr:full":"Apex Court, Unit 2 Bristol Gloucestershire BS35 1JT",
    "addr:housenumber":"unit 2",
    "addr:postcode":"bs35 1jt",
    "addr:street":"Apex",
    "iso:country":"GB",
    "sg:address":"Apex Court, Unit 2",
    "sg:city":"Bristol",
    "sg:classifiers":[
        {
            "category":"Communications",
            "type":"Services"
        }
    ],
    "sg:postcode":"BS35 1JT",
    "sg:province":"Gloucestershire",
    "sg:tags":[
        "telecommunication"
    ],
    "wof:name":"Teleglobe Communications S A",
    "wof:placetype":"venue"
},
  "geometry": {"coordinates":[-2.517209053,51.6172103882],"type":"Point"}
}