{
  "type": "Feature",
  "properties": {
    "addr:full":"23 Rathbone Street London Greater London W1T 1NG",
    "addr:housenumber":"23",
    "addr:postcode":"w1t 1ng",
    "addr:street":"Rathbone Street",
    "iso:country":"GB",
    "sg:address":"23 Rathbone Street",
    "sg:city":"London",
    "sg:classifiers":[
        {
            "category":"Bars & Pubs",
            "type":"Food & Drink"
        }
    ],
    "sg:phone":"+44 20 7636 1127",
    "sg:postcode":"W1T 1NG",
    "sg:province":"Greater London",
    "sg:tags":[
        "pubs",
        "inn"
    ],
    "wof:name":"The Newman Arms",
    "wof:placetype":"venue"
},
  "geometry": {"coordinates":[-0.13533,51.518208],"type":"Point"}
}