{
  "type": "Feature",
  "properties": {
    "addr:full":"99 Monkhams Avenue Woodford Green Essex IG8 0ER",
    "addr:housenumber":"99",
    "addr:postcode":"ig8 0er",
    "addr:street":"Monkhams Avenue",
    "iso:country":"GB",
    "sg:address":"99 Monkhams Avenue",
    "sg:city":"Woodford Green",
    "sg:classifiers":[
        {
            "category":"Professional",
            "subcategory":"Management & Consulting",
            "type":"Services"
        }
    ],
    "sg:postcode":"IG8 0ER",
    "sg:province":"Essex",
    "sg:tags":[
        "consultant",
        "business"
    ],
    "wof:name":"Antelope Consulting",
    "wof:placetype":"venue"
},
  "geometry": {"coordinates":[0.0282799993,51.611946106],"type":"Point"}
}