{
  "type": "Feature",
  "properties": {
    "iso:country":"GB",
    "sg:address":"15 Conway St",
    "sg:city":"Barnsley",
    "sg:classifiers":[
        {
            "category":"Professional",
            "subcategory":"Engineering",
            "type":"Services"
        }
    ],
    "sg:phone":"+44 1226 244855",
    "sg:postcode":"S70 3ER",
    "sg:province":"South Yorkshire",
    "sg:tags":[
        "underpinning",
        "foundation",
        "engineer"
    ],
    "wof:name":"Falco Structural Repairs",
    "wof:placetype":"venue"
},
  "geometry": {"coordinates":[-1.446681,53.547901],"type":"Point"}
}