{
  "type": "Feature",
  "properties": {
    "addr:full":"Kexby Grange, Kexby Gainsborough Lincolnshire DN21 5PJ",
    "addr:housenumber":"kexby;kexby",
    "addr:postcode":"dn21 5pj",
    "iso:country":"GB",
    "sg:address":"Kexby Grange, Kexby",
    "sg:city":"Gainsborough",
    "sg:classifiers":[
        {
            "category":"Farming",
            "subcategory":"Farm",
            "type":"Manufacturing & Wholesale Goods"
        }
    ],
    "sg:phone":"+44 1427 788265",
    "sg:postcode":"DN21 5PJ",
    "sg:province":"Lincolnshire",
    "sg:tags":[
        "mixed",
        "crop"
    ],
    "wof:name":"E Edwardson & Son",
    "wof:placetype":"venue"
},
  "geometry": {"coordinates":[-0.692373,53.361889],"type":"Point"}
}