{
  "type": "Feature",
  "properties": {
    "addr:full":"316 Kings Road Reading Berkshire RG1 4HX",
    "addr:housenumber":"316",
    "addr:postcode":"rg1 4hx",
    "addr:street":"Kings Road",
    "iso:country":"GB",
    "sg:address":"316 Kings Road",
    "sg:city":"Reading",
    "sg:classifiers":[
        {
            "category":"Organizations",
            "subcategory":"Membership Organization",
            "type":"Services"
        }
    ],
    "sg:phone":"+44 118 926 5804",
    "sg:postcode":"RG1 4HX",
    "sg:province":"Berkshire",
    "sg:tags":[
        "club"
    ],
    "wof:name":"Salisbury Conservative Club",
    "wof:placetype":"venue"
},
  "geometry": {"coordinates":[-0.952199,51.453194],"type":"Point"}
}