{
  "type": "Feature",
  "properties": {
    "iso:country":"GB",
    "sg:address":"Unit 1 Borders Business Park, Longtown",
    "sg:city":"Carlisle",
    "sg:classifiers":[
        {
            "category":"Retail",
            "subcategory":"Veterinary Services",
            "type":"Services"
        }
    ],
    "sg:phone":"+44 1228 791245",
    "sg:postcode":"CA6 5TD",
    "sg:province":"Cumbria",
    "sg:tags":[
        "surgeon",
        "activity"
    ],
    "wof:name":"Esk Veterinary Practice",
    "wof:placetype":"venue"
},
  "geometry": {"coordinates":[-2.9694559574,55.0072631836],"type":"Point"}
}