{
  "type": "Feature",
  "properties": {
    "iso:country":"GB",
    "sg:address":"84 High Street",
    "sg:city":"Cradley Heath",
    "sg:classifiers":[
        {
            "category":"Shopping",
            "subcategory":"Pawn Shop",
            "type":"Retail Goods"
        }
    ],
    "sg:postcode":"B64 5HA",
    "sg:province":"West Midlands",
    "sg:tags":[
        "pawnbroker"
    ],
    "wof:name":"Arthur Griffiths Jewellers",
    "wof:placetype":"venue"
},
  "geometry": {"coordinates":[-2.084511,52.470985],"type":"Point"}
}