{
  "type": "Feature",
  "properties": {
    "addr:full":"87 Mortlake Road Richmond Greater London TW9 4AA",
    "addr:housenumber":"87",
    "addr:postcode":"tw9 4aa",
    "addr:street":"Mortlake Road",
    "iso:country":"GB",
    "sg:address":"87 Mortlake Road",
    "sg:city":"Richmond",
    "sg:classifiers":[
        {
            "category":"Banks & Credit Unions",
            "subcategory":"Financial Services",
            "type":"Services"
        }
    ],
    "sg:postcode":"TW9 4AA",
    "sg:province":"Greater London",
    "sg:tags":[
        "adviser"
    ],
    "wof:name":"Michael Redwood & Co.",
    "wof:placetype":"venue"
},
  "geometry": {"coordinates":[-0.281734,51.479385],"type":"Point"}
}