{
  "type": "Feature",
  "properties": {
    "addr:full":"3 Rosemary Lane Richmond North Yorkshire DL10 4DP",
    "addr:housenumber":"3",
    "addr:postcode":"dl10 4dp",
    "addr:street":"Rosemary Lane",
    "iso:country":"GB",
    "sg:address":"3 Rosemary Lane",
    "sg:city":"Richmond",
    "sg:classifiers":[
        {
            "category":"Arts & Performance",
            "subcategory":"Theater",
            "type":"Entertainment"
        }
    ],
    "sg:phone":"+44 1748 825288",
    "sg:postcode":"DL10 4DP",
    "sg:province":"North Yorkshire",
    "sg:tags":[
        "theatre"
    ],
    "wof:name":"North Country Theatre",
    "wof:placetype":"venue"
},
  "geometry": {"coordinates":[-1.739426,54.404289],"type":"Point"}
}