{
  "type": "Feature",
  "properties": {
    "addr:full":"3 Ibstock Road Coventry Warwickshire CV6 6NL",
    "addr:housenumber":"3",
    "addr:postcode":"cv6 6nl",
    "addr:street":"Ibstock Road",
    "iso:country":"GB",
    "sg:address":"3 Ibstock Road",
    "sg:city":"Coventry",
    "sg:classifiers":[
        {
            "category":"Professional",
            "subcategory":"Engineering",
            "type":"Services"
        },
        {
            "category":"Wholesale",
            "subcategory":"Machinery & Supplies",
            "type":"Manufacturing & Wholesale Goods"
        }
    ],
    "sg:phone":"+44 24 7636 4897",
    "sg:postcode":"CV6 6NL",
    "sg:province":"Warwickshire",
    "sg:tags":[
        "equipment",
        "ge",
        "engineer",
        "railway",
        "mechanical"
    ],
    "wof:name":"Railcare Ltd.",
    "wof:placetype":"venue"
},
  "geometry": {"coordinates":[-1.482192,52.456722],"type":"Point"}
}