{
  "type": "Feature",
  "properties": {
    "iso:country":"GB",
    "sg:address":"Claypit Hall, Weston Lullingfields",
    "sg:city":"Shrewsbury",
    "sg:classifiers":[
        {
            "category":"Farming",
            "subcategory":"Dairy Farm",
            "type":"Manufacturing & Wholesale Goods"
        }
    ],
    "sg:postcode":"SY4 2AD",
    "sg:province":"Shropshire",
    "wof:name":"Thomas E Higgins",
    "wof:placetype":"venue"
},
  "geometry": {"coordinates":[-2.8548400402,52.8206291199],"type":"Point"}
}