{
  "type": "Feature",
  "properties": {
    "addr:full":"Lewinshope Farm Selkirk Scottish Borders TD7 5JY",
    "addr:postcode":"td7 5jy",
    "addr:street":"Selkirk",
    "iso:country":"GB",
    "sg:address":"Lewinshope Farm",
    "sg:city":"Selkirk",
    "sg:classifiers":[
        {
            "category":"Building & Trades",
            "subcategory":"Landscaping Services",
            "type":"Services"
        }
    ],
    "sg:phone":"+44 1750 76266",
    "sg:postcode":"TD7 5JY",
    "sg:province":"Scottish Borders",
    "sg:tags":[
        "forestry",
        "tree"
    ],
    "wof:name":"Border Tree Services",
    "wof:placetype":"venue"
},
  "geometry": {"coordinates":[-2.841429,55.547329],"type":"Point"}
}