{
  "type": "Feature",
  "properties": {
    "addr:full":"240 Peniel Green Road, Llansamlet Swansea Neath Port Talbot SA7 9BD",
    "addr:housenumber":"240",
    "addr:postcode":"sa7 9bd",
    "addr:street":"Peniel Green Road",
    "iso:country":"GB",
    "sg:address":"240 Peniel Green Road, Llansamlet",
    "sg:city":"Swansea",
    "sg:classifiers":[
        {
            "category":"Shopping",
            "subcategory":"Stationery & Office Supplies",
            "type":"Retail Goods"
        }
    ],
    "sg:phone":"+44 1792 772075",
    "sg:postcode":"SA7 9BD",
    "sg:province":"Neath Port Talbot",
    "sg:tags":[
        "item",
        "promotional"
    ],
    "wof:name":"Inspiration Ltd.",
    "wof:placetype":"venue"
},
  "geometry": {"coordinates":[-3.886441,51.661865],"type":"Point"}
}