{
  "type": "Feature",
  "properties": {
    "iso:country":"GB",
    "sg:address":"60 Winchester Road",
    "sg:city":"Petersfield",
    "sg:classifiers":[
        {
            "category":"Autos & Motor Vehicles",
            "subcategory":"Auto Supplies",
            "type":"Retail Goods"
        }
    ],
    "sg:phone":"+44 1730 264541",
    "sg:postcode":"GU32 3PL",
    "sg:province":"Hampshire",
    "sg:tags":[
        "tyre"
    ],
    "wof:name":"The Stroud Tyre & Exhaust Centre",
    "wof:placetype":"venue"
},
  "geometry": {"coordinates":[-0.963888,51.0079],"type":"Point"}
}