{
  "type": "Feature",
  "properties": {
    "addr:full":"24 High Street, Quarry Bank Brierley Hill West Midlands DY5 2JW",
    "addr:housenumber":"24",
    "addr:postcode":"dy5 2jw",
    "addr:street":"High Street;Brierley Hill",
    "iso:country":"GB",
    "sg:address":"24 High Street, Quarry Bank",
    "sg:city":"Brierley Hill",
    "sg:classifiers":[
        {
            "category":"Shopping",
            "subcategory":"Crafts & Fabrics",
            "type":"Retail Goods"
        }
    ],
    "sg:phone":"+44 1384 637350",
    "sg:postcode":"DY5 2JW",
    "sg:province":"West Midlands",
    "sg:tags":[
        "shop",
        "needlecraft",
        "wool",
        "retailer"
    ],
    "wof:name":"Mary's Fashions",
    "wof:placetype":"venue"
},
  "geometry": {"coordinates":[-2.105971,52.472771],"type":"Point"}
}