{
  "type": "Feature",
  "properties": {
    "iso:country":"GB",
    "sg:address":"125 Tonbridge Road",
    "sg:city":"Maidstone",
    "sg:classifiers":[
        {
            "category":"Health Services",
            "subcategory":"Dentist",
            "type":"Services"
        }
    ],
    "sg:phone":"+44 1622 675996",
    "sg:postcode":"ME16 8JS",
    "sg:province":"Kent",
    "wof:name":"Mid Kent Orthodontics",
    "wof:placetype":"venue"
},
  "geometry": {"coordinates":[0.503337,51.269039],"type":"Point"}
}