{
  "type": "Feature",
  "properties": {
    "addr:full":"The Green, Finchingfield Braintree Essex CM7 4JX",
    "addr:postcode":"cm7 4jx",
    "addr:street":"Green",
    "iso:country":"GB",
    "sg:address":"The Green, Finchingfield",
    "sg:city":"Braintree",
    "sg:classifiers":[
        {
            "category":"Shopping",
            "subcategory":"Antiques",
            "type":"Retail Goods"
        }
    ],
    "sg:phone":"+44 1371 810258",
    "sg:postcode":"CM7 4JX",
    "sg:province":"Essex",
    "wof:name":"Finchingfield Antiques Centre",
    "wof:placetype":"venue"
},
  "geometry": {"coordinates":[0.50193,51.937389],"type":"Point"}
}