{
  "type": "Feature",
  "properties": {
    "addr:full":"Riverside Ho, Leaside Rd Clapton Greater London E5 9LU",
    "addr:postcode":"e5 9lu",
    "addr:street":"Leaside Rd",
    "iso:country":"GB",
    "sg:address":"Riverside Ho, Leaside Rd",
    "sg:city":"Clapton",
    "sg:classifiers":[
        {
            "category":"Shopping",
            "subcategory":"Baby Store",
            "type":"Retail Goods"
        }
    ],
    "sg:phone":"+44 20 8806 5166",
    "sg:postcode":"E5 9LU",
    "sg:province":"Greater London",
    "sg:tags":[
        "nursery",
        "accessory"
    ],
    "wof:name":"Wooden Tots",
    "wof:placetype":"venue"
},
  "geometry": {"coordinates":[-0.048637,51.564896],"type":"Point"}
}