{
  "type": "Feature",
  "properties": {
    "iso:country":"GB",
    "sg:address":"9 Crescent Road",
    "sg:city":"Ramsgate",
    "sg:classifiers":[
        {
            "category":"Home & Garden",
            "subcategory":"Household Appliances",
            "type":"Retail Goods"
        }
    ],
    "sg:phone":"+44 1843 587815",
    "sg:postcode":"CT11 9QU",
    "sg:province":"Kent",
    "sg:tags":[
        "electrical"
    ],
    "wof:name":"Worth Servicing",
    "wof:placetype":"venue"
},
  "geometry": {"coordinates":[1.410951,51.332726],"type":"Point"}
}