{
  "type": "Feature",
  "properties": {
    "addr:full":"46 Hazel Rd, Rubery Birmingham West Midlands B45 9DY",
    "addr:housenumber":"46",
    "addr:postcode":"b45 9dy",
    "addr:street":"Hazel Rd",
    "iso:country":"GB",
    "sg:address":"46 Hazel Rd, Rubery",
    "sg:city":"Birmingham",
    "sg:classifiers":[
        {
            "category":"Professional",
            "subcategory":"Management & Consulting",
            "type":"Services"
        }
    ],
    "sg:phone":"+44 121 453 8640",
    "sg:postcode":"B45 9DY",
    "sg:province":"West Midlands",
    "sg:tags":[
        "consultant",
        "business"
    ],
    "wof:name":"O.W.L Training & Development",
    "wof:placetype":"venue"
},
  "geometry": {"coordinates":[-2.022085,52.388428],"type":"Point"}
}