{
  "type": "Feature",
  "properties": {
    "addr:full":"Unit 1 Halls Workspace Mansfield Nottinghamshire NG18 5HF",
    "addr:housenumber":"unit 1",
    "addr:postcode":"ng18 5hf",
    "addr:street":"Halls Workspace",
    "iso:country":"GB",
    "sg:address":"Unit 1 Halls Workspace",
    "sg:city":"Mansfield",
    "sg:classifiers":[
        {
            "category":"Professional",
            "subcategory":"Engineering",
            "type":"Services"
        }
    ],
    "sg:postcode":"NG18 5HF",
    "sg:province":"Nottinghamshire",
    "sg:tags":[
        "printing"
    ],
    "wof:name":"D Hall",
    "wof:placetype":"venue"
},
  "geometry": {"coordinates":[-1.216079,53.1376],"type":"Point"}
}