{
  "type": "Feature",
  "properties": {
    "addr:full":"Commercial House, Commercial Street Llantwit Major The Vale of Glamorgan CF61 1RB",
    "addr:postcode":"cf61 1rb",
    "addr:street":"Commercial Street;Vale",
    "iso:country":"GB",
    "sg:address":"Commercial House, Commercial Street",
    "sg:city":"Llantwit Major",
    "sg:classifiers":[
        {
            "category":"Arts & Performance",
            "subcategory":"Art Gallery",
            "type":"Entertainment"
        },
        {
            "category":"Home & Garden",
            "subcategory":"Furniture",
            "type":"Retail Goods"
        }
    ],
    "sg:postcode":"CF61 1RB",
    "sg:province":"The Vale of Glamorgan",
    "wof:name":"Woodford Gallery",
    "wof:placetype":"venue"
},
  "geometry": {"coordinates":[-3.485422,51.408768],"type":"Point"}
}