{
  "type": "Feature",
  "properties": {
    "addr:full":"157 London Road Mitcham Greater London CR4 2YR",
    "addr:housenumber":"157",
    "addr:postcode":"cr4 2yr",
    "addr:street":"London Road",
    "iso:country":"GB",
    "sg:address":"157 London Road",
    "sg:city":"Mitcham",
    "sg:classifiers":[
        {
            "category":"Education",
            "subcategory":"Library",
            "type":"Public Place"
        },
        {
            "category":"Government",
            "subcategory":"Office",
            "type":"Public Place"
        }
    ],
    "sg:phone":"+44 20 8648 4070",
    "sg:postcode":"CR4 2YR",
    "sg:province":"Greater London",
    "sg:tags":[
        "book",
        "local"
    ],
    "wof:name":"Mitcham Library",
    "wof:placetype":"venue"
},
  "geometry": {"coordinates":[-0.1637289971,51.4072189331],"type":"Point"}
}