{
  "type": "Feature",
  "properties": {
    "addr:full":"6 Cowper Street Bristol City of Bristol BS5 9JZ",
    "addr:housenumber":"6",
    "addr:postcode":"bs5 9jz",
    "addr:street":"Cowper Street",
    "iso:country":"GB",
    "sg:address":"6 Cowper Street",
    "sg:city":"Bristol",
    "sg:classifiers":[
        {
            "category":"Professional",
            "subcategory":"Business Services",
            "type":"Services"
        }
    ],
    "sg:phone":"+44 117 935 1158",
    "sg:postcode":"BS5 9JZ",
    "sg:province":"City of Bristol",
    "sg:tags":[
        "shop",
        "cleaning"
    ],
    "wof:name":"Five Star Cleaning Services",
    "wof:placetype":"venue"
},
  "geometry": {"coordinates":[-2.5597689152,51.4577903748],"type":"Point"}
}