{
  "type": "Feature",
  "properties": {
    "addr:full":"Bridgwater Trading Estate, Bridgwater Road London Greater London E15 2NS",
    "addr:postcode":"e15 2ns",
    "addr:street":"Bridgwater Road",
    "iso:country":"GB",
    "sg:address":"Bridgwater Trading Estate, Bridgwater Road",
    "sg:city":"London",
    "sg:classifiers":[
        {
            "category":"Shopping",
            "subcategory":"Beauty & Cosmetics",
            "type":"Retail Goods"
        }
    ],
    "sg:phone":"+44 20 8519 5353",
    "sg:postcode":"E15 2NS",
    "sg:province":"Greater London",
    "sg:tags":[
        "product"
    ],
    "wof:name":"Clarins (U K) Ltd.",
    "wof:placetype":"venue"
},
  "geometry": {"coordinates":[-0.01137,51.531731],"type":"Point"}
}