{
  "type": "Feature",
  "properties": {
    "addr:full":"3 High Street Peebles Scottish Borders EH45 8AG",
    "addr:housenumber":"3",
    "addr:postcode":"eh45 8ag",
    "addr:street":"High Street",
    "iso:country":"GB",
    "sg:address":"3 High Street",
    "sg:city":"Peebles",
    "sg:classifiers":[
        {
            "category":"Shopping",
            "subcategory":"Bicycles & Sporting Goods",
            "type":"Retail Goods"
        }
    ],
    "sg:phone":"+44 1721 720844",
    "sg:postcode":"EH45 8AG",
    "sg:province":"Scottish Borders",
    "sg:tags":[
        "cycle",
        "accessory"
    ],
    "wof:name":"George Pennel Cycles",
    "wof:placetype":"venue"
},
  "geometry": {"coordinates":[-3.189149,55.651779],"type":"Point"}
}