{
  "type": "Feature",
  "properties": {
    "iso:country":"GB",
    "sg:address":"Gordon Hall, Huntly Dr",
    "sg:city":"Finchley Central",
    "sg:classifiers":[
        {
            "category":"Community Center",
            "subcategory":"Youth",
            "type":"Public Place"
        }
    ],
    "sg:phone":"+44 20 8346 3322",
    "sg:postcode":"N3 1NU",
    "sg:province":"Greater London",
    "sg:tags":[
        "organisation",
        "centre"
    ],
    "wof:name":"The Tenth Finchley (Scottish) Scout Group",
    "wof:placetype":"venue"
},
  "geometry": {"coordinates":[-0.1890300065,51.6087913513],"type":"Point"}
}