{
  "type": "Feature",
  "properties": {
    "addr:full":"24 The Mall Montrose Aberdeenshire DD10 8NW",
    "addr:housenumber":"24",
    "addr:postcode":"dd10 8nw",
    "addr:street":"The Mall",
    "iso:country":"GB",
    "sg:address":"24 The Mall",
    "sg:city":"Montrose",
    "sg:classifiers":[
        {
            "category":"Travel",
            "subcategory":"Hotels & Motels",
            "type":"Entertainment"
        }
    ],
    "sg:phone":"+44 1674 676386",
    "sg:postcode":"DD10 8NW",
    "sg:province":"Aberdeenshire",
    "sg:tags":[
        "house",
        "guest"
    ],
    "wof:name":"Fairfield Guest House",
    "wof:placetype":"venue"
},
  "geometry": {"coordinates":[-2.4662799835,56.7177658081],"type":"Point"}
}