{
  "type": "Feature",
  "properties": {
    "addr:full":"Ferry Street Torpoint Cornwall PL11 2AX",
    "addr:postcode":"pl11 2ax",
    "addr:street":"Ferry Street",
    "iso:country":"GB",
    "sg:address":"Ferry Street",
    "sg:city":"Torpoint",
    "sg:classifiers":[
        {
            "category":"Arena",
            "subcategory":"Sports Club",
            "type":"Entertainment"
        }
    ],
    "sg:postcode":"PL11 2AX",
    "sg:province":"Cornwall",
    "wof:name":"D Harris",
    "wof:placetype":"venue"
},
  "geometry": {"coordinates":[-4.195038,50.373573],"type":"Point"}
}