{
  "type": "Feature",
  "properties": {
    "addr:full":"41-43 High Street Ibstock Leicestershire LE67 6LH",
    "addr:housenumber":"41-43",
    "addr:postcode":"le67 6lh",
    "addr:street":"High Street",
    "iso:country":"GB",
    "sg:address":"41-43 High Street",
    "sg:city":"Ibstock",
    "sg:classifiers":[
        {
            "category":"Retail",
            "subcategory":"Repair Shop",
            "type":"Services"
        }
    ],
    "sg:phone":"+44 1530 260404",
    "sg:postcode":"LE67 6LH",
    "sg:province":"Leicestershire",
    "sg:tags":[
        "radio",
        "television",
        "video"
    ],
    "wof:name":"Burditts (Ibstock) Ltd.",
    "wof:placetype":"venue"
},
  "geometry": {"coordinates":[-1.399053,52.686069],"type":"Point"}
}