{
  "type": "Feature",
  "properties": {
    "iso:country":"GB",
    "sg:address":"Victoria House, Upham Street",
    "sg:city":"Southampton",
    "sg:classifiers":[
        {
            "category":"Professional",
            "subcategory":"Management & Consulting",
            "type":"Services"
        }
    ],
    "sg:phone":"+44 1489 860795",
    "sg:postcode":"SO32 1JA",
    "sg:province":"Hampshire",
    "sg:tags":[
        "consultant",
        "business"
    ],
    "wof:name":"David Markham Ltd.",
    "wof:placetype":"venue"
},
  "geometry": {"coordinates":[-1.251919,50.975262],"type":"Point"}
}