{
  "type": "Feature",
  "properties": {
    "addr:full":"C/o B & T Reclamation Ltd, Wood Wharf Business Pk, 100 Prestons Rd London Greater London E14 9QL",
    "addr:postcode":"/ o;e14 9ql",
    "addr:street":"C;Wood Wharf Business Pk 100 Prestons Rd",
    "iso:country":"GB",
    "sg:address":"C/o B & T Reclamation Ltd, Wood Wharf Business Pk, 100 Prestons Rd",
    "sg:city":"London",
    "sg:classifiers":[
        {
            "category":"Shopping",
            "subcategory":"Department Store",
            "type":"Retail Goods"
        }
    ],
    "sg:postcode":"E14 9QL",
    "sg:province":"Greater London",
    "wof:name":"T & M Trade Sales Ltd",
    "wof:placetype":"venue"
},
  "geometry": {"coordinates":[-0.01351,51.502529],"type":"Point"}
}