{
  "type": "Feature",
  "properties": {
    "addr:full":"Unit 8, Baldock Industrial Estate London Rd Baldock Bedfordshire SG7 6NG",
    "addr:housenumber":"unit 8",
    "addr:postcode":"sg7 6ng",
    "addr:street":"Baldock Industrial Estate London Rd",
    "iso:country":"GB",
    "sg:address":"Unit 8, Baldock Industrial Estate London Rd",
    "sg:city":"Baldock",
    "sg:classifiers":[
        {
            "category":"Manufacturing",
            "subcategory":"Metals",
            "type":"Manufacturing & Wholesale Goods"
        }
    ],
    "sg:phone":"+44 1462 896668",
    "sg:postcode":"SG7 6NG",
    "sg:province":"Bedfordshire",
    "sg:tags":[
        "die-casting"
    ],
    "wof:name":"D & M Mould Specialists",
    "wof:placetype":"venue"
},
  "geometry": {"coordinates":[-0.1878540069,51.9887695312],"type":"Point"}
}