{
  "type": "Feature",
  "properties": {
    "iso:country":"GB",
    "sg:address":"Bell Lane House, Bell Lane",
    "sg:city":"Stroud",
    "sg:classifiers":[
        {
            "category":"Manufacturing",
            "subcategory":"Textiles",
            "type":"Manufacturing & Wholesale Goods"
        }
    ],
    "sg:postcode":"GL6 9BP",
    "sg:province":"Gloucestershire",
    "sg:tags":[
        "made-up"
    ],
    "wof:name":"Textile Machinery Engineering Co.",
    "wof:placetype":"venue"
},
  "geometry": {"coordinates":[-2.1868889332,51.7062568665],"type":"Point"}
}