{
  "type": "Feature",
  "properties": {
    "addr:full":"20 Dock St Whitechapel Greater London E1 8JP",
    "addr:housenumber":"20",
    "addr:postcode":"e1 8jp",
    "addr:street":"Dock St",
    "iso:country":"GB",
    "sg:address":"20 Dock St",
    "sg:city":"Whitechapel",
    "sg:classifiers":[
        {
            "category":"Communications",
            "type":"Services"
        }
    ],
    "sg:phone":"+44 20 7481 2522",
    "sg:postcode":"E1 8JP",
    "sg:province":"Greater London",
    "sg:tags":[
        "audio-visual"
    ],
    "wof:name":"Phono Genius",
    "wof:placetype":"venue"
},
  "geometry": {"coordinates":[-0.0683600008,51.5102386475],"type":"Point"}
}