{
  "type": "Feature",
  "properties": {
    "addr:full":"2 Eastwood Road Ilford Essex IG3 8XB",
    "addr:housenumber":"2",
    "addr:postcode":"ig3 8xb",
    "addr:street":"Eastwood Road",
    "iso:country":"GB",
    "sg:address":"2 Eastwood Road",
    "sg:city":"Ilford",
    "sg:classifiers":[
        {
            "category":"Farming",
            "subcategory":"Nursery",
            "type":"Manufacturing & Wholesale Goods"
        },
        {
            "category":"Education",
            "subcategory":"Preschool",
            "type":"Public Place"
        }
    ],
    "sg:phone":"+44 20 8599 3744",
    "sg:postcode":"IG3 8XB",
    "sg:province":"Essex",
    "sg:tags":[
        "school",
        "creche"
    ],
    "wof:name":"Maytime Montessori Nursery",
    "wof:placetype":"venue"
},
  "geometry": {"coordinates":[0.109516,51.566605],"type":"Point"}
}