{
  "type": "Feature",
  "properties": {
    "addr:full":"83 Faringdon Road Swindon Wiltshire SN1 5DQ",
    "addr:housenumber":"83",
    "addr:postcode":"sn1 5dq",
    "addr:street":"Faringdon Road",
    "iso:country":"GB",
    "sg:address":"83 Faringdon Road",
    "sg:city":"Swindon",
    "sg:classifiers":[
        {
            "category":"Building & Trades",
            "subcategory":"Construction",
            "type":"Services"
        }
    ],
    "sg:phone":"+44 1793 496880",
    "sg:postcode":"SN1 5DQ",
    "sg:province":"Wiltshire",
    "sg:tags":[
        "glazier"
    ],
    "wof:name":"Complete Glazing Services",
    "wof:placetype":"venue"
},
  "geometry": {"coordinates":[-1.79193,51.560143],"type":"Point"}
}