{
  "type": "Feature",
  "properties": {
    "iso:country":"GB",
    "sg:address":"Unit 30, Greenhill Business Centre",
    "sg:city":"Coatbridge",
    "sg:classifiers":[
        {
            "category":"Professional",
            "subcategory":"Engineering",
            "type":"Services"
        }
    ],
    "sg:phone":"+44 1236 627727",
    "sg:postcode":"ML5 2AG",
    "sg:province":"North Lanarkshire",
    "sg:tags":[
        "contractor",
        "electrical",
        "engineer"
    ],
    "wof:name":"E P Electrical Services Ltd",
    "wof:placetype":"venue"
},
  "geometry": {"coordinates":[-4.036569,55.907612],"type":"Point"}
}