{
  "type": "Feature",
  "properties": {
    "addr:full":"Unit 1-3 The Octagon High Wycombe Buckinghamshire HP11 2HT",
    "addr:housenumber":"unit 1-3",
    "addr:postcode":"hp11 2ht",
    "addr:street":"The",
    "iso:country":"GB",
    "sg:address":"Unit 1-3 The Octagon",
    "sg:city":"High Wycombe",
    "sg:classifiers":[
        {
            "category":"Shopping",
            "subcategory":"Optician",
            "type":"Retail Goods"
        }
    ],
    "sg:phone":"+44 1494 473399",
    "sg:postcode":"HP11 2HT",
    "sg:province":"Buckinghamshire",
    "wof:name":"Vision Express (U K) Ltd.",
    "wof:placetype":"venue"
},
  "geometry": {"coordinates":[-0.75225,51.629169],"type":"Point"}
}