{
  "type": "Feature",
  "properties": {
    "iso:country":"GB",
    "sg:address":"15 Thatch Leach Lane, Whitefield",
    "sg:city":"Manchester",
    "sg:classifiers":[
        {
            "category":"Food & Beverages",
            "subcategory":"Liquor & Beverages",
            "type":"Retail Goods"
        }
    ],
    "sg:phone":"+44 161 280 1868",
    "sg:postcode":"M45 6AU",
    "sg:province":"Lancashire",
    "sg:tags":[
        "beer",
        "wine",
        "spirit",
        "wines"
    ],
    "wof:name":"Legendary Lancashire Heroes",
    "wof:placetype":"venue"
},
  "geometry": {"coordinates":[-2.28626,53.542839],"type":"Point"}
}