{
  "type": "Feature",
  "properties": {
    "iso:country":"GB",
    "sg:address":"6 Foundry Walk",
    "sg:city":"Daventry",
    "sg:classifiers":[
        {
            "category":"Shopping",
            "subcategory":"Thrift Store",
            "type":"Retail Goods"
        }
    ],
    "sg:phone":"+44 1327 311094",
    "sg:postcode":"NN11 4PN",
    "sg:province":"Northamptonshire",
    "sg:tags":[
        "shop",
        "charity"
    ],
    "wof:name":"Young Men's Christian Association",
    "wof:placetype":"venue"
},
  "geometry": {"coordinates":[-1.1620839834,52.2573852539],"type":"Point"}
}