{
  "type": "Feature",
  "properties": {
    "iso:country":"GB",
    "sg:address":"315-317 Coleford Road, Darnall",
    "sg:city":"Sheffield",
    "sg:classifiers":[
        {
            "category":"Professional",
            "subcategory":"Engineering",
            "type":"Services"
        }
    ],
    "sg:phone":"+44 114 244 1483",
    "sg:postcode":"S9 5NF",
    "sg:province":"South Yorkshire",
    "wof:name":"Hallamshire Hardmetal Products Ltd.",
    "wof:placetype":"venue"
},
  "geometry": {"coordinates":[-1.4050309658,53.391166687],"type":"Point"}
}