{
  "type": "Feature",
  "properties": {
    "addr:full":"8 Bairstow Street Blackpool Lancashire FY1 5BN",
    "addr:housenumber":"8",
    "addr:postcode":"fy1 5bn",
    "addr:street":"Bairstow Street",
    "iso:country":"GB",
    "sg:address":"8 Bairstow Street",
    "sg:city":"Blackpool",
    "sg:classifiers":[
        {
            "category":"Fast Food",
            "type":"Food & Drink"
        },
        {
            "category":"Food & Beverages",
            "subcategory":"Groceries & Convenience Stores",
            "type":"Retail Goods"
        }
    ],
    "sg:phone":"+44 1253 291384",
    "sg:postcode":"FY1 5BN",
    "sg:province":"Lancashire",
    "sg:tags":[
        "shop",
        "fish",
        "take",
        "chip",
        "away"
    ],
    "wof:name":"Walkers Fish & Chips",
    "wof:placetype":"venue"
},
  "geometry": {"coordinates":[-3.0546400547,53.8095626831],"type":"Point"}
}