{
  "type": "Feature",
  "properties": {
    "addr:full":"2 Aberdeen Street Nottingham Nottinghamshire NG3 1JB",
    "addr:housenumber":"2",
    "addr:postcode":"ng3 1jb",
    "addr:street":"Aberdeen Street",
    "iso:country":"GB",
    "sg:address":"2 Aberdeen Street",
    "sg:city":"Nottingham",
    "sg:classifiers":[
        {
            "category":"Wholesale",
            "subcategory":"Fruits & Vegetables",
            "type":"Manufacturing & Wholesale Goods"
        }
    ],
    "sg:phone":"+44 115 950 2607",
    "sg:postcode":"NG3 1JB",
    "sg:province":"Nottinghamshire",
    "wof:name":"J T Soar Ltd.",
    "wof:placetype":"venue"
},
  "geometry": {"coordinates":[-1.1367540359,52.954460144],"type":"Point"}
}