{
  "type": "Feature",
  "properties": {
    "addr:full":"70 Bank Hey Lane South Blackburn Lancashire BB1 5RQ",
    "addr:housenumber":"70",
    "addr:postcode":"bb1 5rq",
    "addr:street":"Bank Hey Lane South",
    "iso:country":"GB",
    "sg:address":"70 Bank Hey Lane South",
    "sg:city":"Blackburn",
    "sg:classifiers":[
        {
            "category":"Place Of Worship",
            "type":"Public Place"
        },
        {
            "category":"Organizations",
            "subcategory":"Non-profit Organization",
            "type":"Services"
        }
    ],
    "sg:phone":"+44 1254 682841",
    "sg:postcode":"BB1 5RQ",
    "sg:province":"Lancashire",
    "sg:tags":[
        "charitable",
        "organisation",
        "charity"
    ],
    "wof:name":"WESTBURY GARDENS UNITED REFORMED CHURCH",
    "wof:placetype":"venue"
},
  "geometry": {"coordinates":[-2.465567,53.768478],"type":"Point"}
}