{
  "type": "Feature",
  "properties": {
    "addr:full":"71 Broad St Peterhead Aberdeenshire AB42 6JL",
    "addr:housenumber":"71",
    "addr:postcode":"ab42 6jl",
    "addr:street":"Broad St",
    "iso:country":"GB",
    "sg:address":"71 Broad St",
    "sg:city":"Peterhead",
    "sg:classifiers":[
        {
            "category":"Utilities",
            "subcategory":"Fuel Oil & Lpg",
            "type":"Services"
        }
    ],
    "sg:phone":"+44 1779 479419",
    "sg:postcode":"AB42 6JL",
    "sg:province":"Aberdeenshire",
    "sg:tags":[
        "distributor"
    ],
    "wof:name":"John A Smith & Sons",
    "wof:placetype":"venue"
},
  "geometry": {"coordinates":[-1.79731,57.506531],"type":"Point"}
}