{
  "type": "Feature",
  "properties": {
    "addr:full":"21 Enterprise Way, Cheltenham Trade Park Cheltenham Gloucestershire GL51 8LZ",
    "addr:housenumber":"21",
    "addr:postcode":"gl51 8lz",
    "addr:street":"Enterprise Way;Trade Park",
    "iso:country":"GB",
    "sg:address":"21 Enterprise Way, Cheltenham Trade Park",
    "sg:city":"Cheltenham",
    "sg:classifiers":[
        {
            "category":"Professional",
            "subcategory":"Engineering",
            "type":"Services"
        }
    ],
    "sg:phone":"+44 1242 245146",
    "sg:postcode":"GL51 8LZ",
    "sg:province":"Gloucestershire",
    "sg:tags":[
        "contractor",
        "electrical",
        "engineer"
    ],
    "wof:name":"Davis Electrical Services Ltd.",
    "wof:placetype":"venue"
},
  "geometry": {"coordinates":[-2.094191,51.906673],"type":"Point"}
}