{
  "type": "Feature",
  "properties": {
    "addr:full":"2 Bambourgh Court, First Avenue Gateshead Tyne and Wear NE11 0TX",
    "addr:housenumber":"2",
    "addr:postcode":"ne11 0tx",
    "addr:street":"Bambourgh Court First Avenue",
    "iso:country":"GB",
    "sg:address":"2 Bambourgh Court, First Avenue",
    "sg:city":"Gateshead",
    "sg:classifiers":[
        {
            "category":"Manufacturing",
            "subcategory":"Tools & Machinery",
            "type":"Manufacturing & Wholesale Goods"
        },
        {
            "category":"Government",
            "subcategory":"Office",
            "type":"Public Place"
        }
    ],
    "sg:phone":"+44 191 482 5577",
    "sg:postcode":"NE11 0TX",
    "sg:province":"Tyne and Wear",
    "sg:tags":[
        "central"
    ],
    "wof:name":"APEX INDUSTRIAL LTD",
    "wof:placetype":"venue"
},
  "geometry": {"coordinates":[-1.6212689877,54.9430847168],"type":"Point"}
}