{
  "type": "Feature",
  "properties": {
    "addr:full":"291 Ham Drive Plymouth Devon PL2 3NH",
    "addr:housenumber":"291",
    "addr:postcode":"pl2 3nh",
    "addr:street":"Ham Drive",
    "iso:country":"GB",
    "sg:address":"291 Ham Drive",
    "sg:city":"Plymouth",
    "sg:classifiers":[
        {
            "category":"Bars & Pubs",
            "type":"Food & Drink"
        }
    ],
    "sg:phone":"+44 1752 771981",
    "sg:postcode":"PL2 3NH",
    "sg:province":"Devon",
    "sg:tags":[
        "pubs",
        "inn"
    ],
    "wof:name":"Cherry Tree Inn",
    "wof:placetype":"venue"
},
  "geometry": {"coordinates":[-4.1457791328,50.3966293335],"type":"Point"}
}