{
  "type": "Feature",
  "properties": {
    "iso:country":"GB",
    "sg:address":"14 London Rd",
    "sg:city":"Wickford",
    "sg:classifiers":[
        {
            "category":"Government",
            "subcategory":"Police Station",
            "type":"Public Place"
        }
    ],
    "sg:phone":"+44 1268 561312",
    "sg:postcode":"SS12 0AN",
    "sg:province":"Essex",
    "sg:tags":[
        "support"
    ],
    "wof:name":"Police",
    "wof:placetype":"venue"
},
  "geometry": {"coordinates":[0.50913,51.611019],"type":"Point"}
}