{
  "type": "Feature",
  "properties": {
    "iso:country":"GB",
    "sg:address":"Bankfield House, Bankfield Gardens",
    "sg:city":"Leeds",
    "sg:classifiers":[
        {
            "category":"Organizations",
            "subcategory":"Membership Organization",
            "type":"Services"
        }
    ],
    "sg:phone":"+44 113 275 2971",
    "sg:postcode":"LS4 2JS",
    "sg:province":"West Yorkshire",
    "sg:tags":[
        "club",
        "social"
    ],
    "wof:name":"Burley Conservative Club",
    "wof:placetype":"venue"
},
  "geometry": {"coordinates":[-1.5852539539,53.8090744019],"type":"Point"}
}