{
  "type": "Feature",
  "properties": {
    "iso:country":"GB",
    "sg:address":"142 Church Path",
    "sg:city":"Deal",
    "sg:classifiers":[
        {
            "category":"Social Services",
            "subcategory":"Retirement Home",
            "type":"Services"
        }
    ],
    "sg:phone":"+44 1304 373650",
    "sg:postcode":"CT14 9PY",
    "sg:province":"Kent",
    "sg:tags":[
        "residential",
        "care"
    ],
    "wof:name":"Cameron Lodge Ltd.",
    "wof:placetype":"venue"
},
  "geometry": {"coordinates":[1.390414,51.221519],"type":"Point"}
}