{
  "type": "Feature",
  "properties": {
    "addr:full":"16 First Av Manor Park Greater London E12 6AN",
    "addr:housenumber":"16",
    "addr:postcode":"e12 6an",
    "addr:street":"First Av Manor Park",
    "iso:country":"GB",
    "sg:address":"16 First Av",
    "sg:city":"Manor Park",
    "sg:classifiers":[
        {
            "category":"Retail",
            "subcategory":"Repair Shop",
            "type":"Services"
        }
    ],
    "sg:phone":"+44 20 8478 5525",
    "sg:postcode":"E12 6AN",
    "sg:province":"Greater London",
    "sg:tags":[
        "radio",
        "television",
        "video"
    ],
    "wof:name":"Adair Teledeals",
    "wof:placetype":"venue"
},
  "geometry": {"coordinates":[0.051329,51.551147],"type":"Point"}
}