{
  "type": "Feature",
  "properties": {
    "iso:country":"GB",
    "sg:address":"21 Hamilton Road",
    "sg:city":"Bellshill",
    "sg:classifiers":[
        {
            "category":"Shopping",
            "subcategory":"Florist",
            "type":"Retail Goods"
        }
    ],
    "sg:phone":"+44 1698 746594",
    "sg:postcode":"ML4 1AF",
    "sg:province":"North Lanarkshire",
    "wof:name":"Blyth's Flowers",
    "wof:placetype":"venue"
},
  "geometry": {"coordinates":[-4.0256071091,55.8181762695],"type":"Point"}
}