{
  "type": "Feature",
  "properties": {
    "addr:full":"Cutlers Brook Junior School, Stafford Rd Bristol City of Bristol BS2 9UR",
    "addr:postcode":"bs2 9ur",
    "addr:street":"Stafford Rd",
    "iso:country":"GB",
    "sg:address":"Cutlers Brook Junior School, Stafford Rd",
    "sg:city":"Bristol",
    "sg:classifiers":[
        {
            "category":"Government",
            "subcategory":"Office",
            "type":"Public Place"
        }
    ],
    "sg:phone":"+44 117 955 7268",
    "sg:postcode":"BS2 9UR",
    "sg:province":"City of Bristol",
    "sg:tags":[
        "local"
    ],
    "wof:name":"Bristol City Council",
    "wof:placetype":"venue"
},
  "geometry": {"coordinates":[-2.57281,51.469479],"type":"Point"}
}