{
  "type": "Feature",
  "properties": {
    "addr:full":"Crosshall Road, Eaton Ford St Neots Bedfordshire PE19 7GE",
    "addr:postcode":"pe19 7ge",
    "addr:street":"Crosshall Road;Ford",
    "iso:country":"GB",
    "sg:address":"Crosshall Road, Eaton Ford",
    "sg:city":"St Neots",
    "sg:classifiers":[
        {
            "category":"Recreation",
            "subcategory":"Marina",
            "type":"Entertainment"
        }
    ],
    "sg:phone":"+44 1480 472763",
    "sg:postcode":"PE19 7GE",
    "sg:province":"Bedfordshire",
    "sg:tags":[
        "activity"
    ],
    "wof:name":"Crosshall Marine Ltd",
    "wof:placetype":"venue"
},
  "geometry": {"coordinates":[-0.2764590085,52.227268219],"type":"Point"}
}