{
  "type": "Feature",
  "properties": {
    "addr:full":"Oyne School Insch Aberdeenshire AB52 6QT",
    "addr:postcode":"ab52 6qt",
    "iso:country":"GB",
    "sg:address":"Oyne School",
    "sg:city":"Insch",
    "sg:classifiers":[
        {
            "category":"Government",
            "subcategory":"Office",
            "type":"Public Place"
        }
    ],
    "sg:phone":"+44 1464 851232",
    "sg:postcode":"AB52 6QT",
    "sg:province":"Aberdeenshire",
    "sg:tags":[
        "local"
    ],
    "wof:name":"Aberdeenshire Council",
    "wof:placetype":"venue"
},
  "geometry": {"coordinates":[-2.6130108833,57.342918396],"type":"Point"}
}