{
  "type": "Feature",
  "properties": {
    "addr:full":"94a Rushey Grn, Catford London Greater London SE6 4HW",
    "addr:housenumber":"94a",
    "addr:postcode":"se6 4hw",
    "addr:street":"Rushey Grn Catford",
    "iso:country":"GB",
    "sg:address":"94a Rushey Grn, Catford",
    "sg:city":"London",
    "sg:classifiers":[
        {
            "category":"Banks & Credit Unions",
            "subcategory":"Financial Services",
            "type":"Services"
        }
    ],
    "sg:postcode":"SE6 4HW",
    "sg:province":"Greater London",
    "sg:tags":[
        "consultant"
    ],
    "wof:name":"Crownway Financial Services Ltd",
    "wof:placetype":"venue"
},
  "geometry": {"coordinates":[-0.0186100006,51.4469032288],"type":"Point"}
}