{
  "type": "Feature",
  "properties": {
    "iso:country":"GB",
    "sg:address":"50 Eastgate Row",
    "sg:city":"Chester",
    "sg:classifiers":[
        {
            "category":"Shopping",
            "subcategory":"Clothing, Apparel, & Fashions",
            "type":"Retail Goods"
        }
    ],
    "sg:phone":"+44 1244 313964",
    "sg:postcode":"CH1 1LF",
    "sg:province":"Cheshire",
    "sg:tags":[
        "shop"
    ],
    "wof:name":"Laura Ashley",
    "wof:placetype":"venue"
},
  "geometry": {"coordinates":[-2.890031,53.190765],"type":"Point"}
}