{
  "type": "Feature",
  "properties": {
    "iso:country":"GB",
    "sg:address":"60 Ashmead Rise, Cofton Hackett",
    "sg:city":"Birmingham",
    "sg:classifiers":[
        {
            "category":"Manufacturing",
            "subcategory":"Petroleum Products",
            "type":"Manufacturing & Wholesale Goods"
        }
    ],
    "sg:phone":"+44 121 445 2883",
    "sg:postcode":"B45 8AD",
    "sg:province":"West Midlands",
    "sg:tags":[
        "double",
        "glazing"
    ],
    "wof:name":"Cofton Windows",
    "wof:placetype":"venue"
},
  "geometry": {"coordinates":[-1.9971940517,52.3789253235],"type":"Point"}
}