{
  "type": "Feature",
  "properties": {
    "addr:full":"27 Beauchamp Place London Greater London SW3 1NJ",
    "addr:housenumber":"27",
    "addr:postcode":"sw3 1nj",
    "addr:street":"Beauchamp Place",
    "iso:country":"GB",
    "sg:address":"27 Beauchamp Place",
    "sg:city":"London",
    "sg:classifiers":[
        {
            "category":"Manufacturing",
            "subcategory":"Apparel",
            "type":"Manufacturing & Wholesale Goods"
        }
    ],
    "sg:phone":"+44 20 7584 1363",
    "sg:postcode":"SW3 1NJ",
    "sg:province":"Greater London",
    "sg:tags":[
        "garment",
        "designer"
    ],
    "wof:name":"Classicfactor Ltd.",
    "wof:placetype":"venue"
},
  "geometry": {"coordinates":[-0.163913995,51.4973678589],"type":"Point"}
}