{
  "type": "Feature",
  "properties": {
    "iso:country":"GB",
    "sg:address":"Linen Hall, 162 Regent St",
    "sg:city":"West End",
    "sg:classifiers":[
        {
            "category":"Professional",
            "subcategory":"Engineering",
            "type":"Services"
        }
    ],
    "sg:phone":"+44 20 7439 4567",
    "sg:postcode":"W1R 5TB",
    "sg:province":"Hampshire",
    "sg:tags":[
        "consulting",
        "engineer"
    ],
    "wof:name":"Arc Innovations Ltd",
    "wof:placetype":"venue"
},
  "geometry": {"coordinates":[-0.139375,51.511906],"type":"Point"}
}