{
  "type": "Feature",
  "properties": {
    "addr:full":"47 Ladies Mile Road Brighton East Sussex BN1 8TA",
    "addr:housenumber":"47",
    "addr:postcode":"bn1 8ta",
    "addr:street":"Ladies Mile Road",
    "iso:country":"GB",
    "sg:address":"47 Ladies Mile Road",
    "sg:city":"Brighton",
    "sg:classifiers":[
        {
            "category":"Professional",
            "subcategory":"Engineering",
            "type":"Services"
        }
    ],
    "sg:phone":"+44 1273 888000",
    "sg:postcode":"BN1 8TA",
    "sg:province":"East Sussex",
    "sg:tags":[
        "contractor",
        "electrical",
        "engineer"
    ],
    "wof:name":"Enercell",
    "wof:placetype":"venue"
},
  "geometry": {"coordinates":[-0.144382,50.86393],"type":"Point"}
}