{
  "type": "Feature",
  "properties": {
    "iso:country":"GB",
    "sg:address":"156 Walton Rd",
    "sg:city":"East Molesey",
    "sg:classifiers":[
        {
            "category":"Retail",
            "subcategory":"Funeral Services",
            "type":"Services"
        }
    ],
    "sg:phone":"+44 20 8941 1412",
    "sg:postcode":"KT8 0HP",
    "sg:province":"Greater London",
    "sg:tags":[
        "director"
    ],
    "wof:name":"Edmund & Sons",
    "wof:placetype":"venue"
},
  "geometry": {"coordinates":[-0.3573850095,51.4008407593],"type":"Point"}
}