{
  "type": "Feature",
  "properties": {
    "addr:full":"5c Swanpool Walk, St Johns Worcester Worcestershire WR2 4EL",
    "addr:housenumber":"5c",
    "addr:postcode":"wr2 4el",
    "addr:street":"Swanpool Walk",
    "iso:country":"GB",
    "sg:address":"5c Swanpool Walk, St Johns",
    "sg:city":"Worcester",
    "sg:classifiers":[
        {
            "category":"Building & Trades",
            "subcategory":"Construction",
            "type":"Services"
        }
    ],
    "sg:phone":"+44 1905 748808",
    "sg:postcode":"WR2 4EL",
    "sg:province":"Worcestershire",
    "sg:tags":[
        "builder"
    ],
    "wof:name":"Bourne Builders (Worcester) Ltd.",
    "wof:placetype":"venue"
},
  "geometry": {"coordinates":[-2.23342,52.187111],"type":"Point"}
}