{
  "type": "Feature",
  "properties": {
    "iso:country":"GB",
    "sg:address":"26 Wareham Road, Owermoigne",
    "sg:city":"Dorchester",
    "sg:classifiers":[
        {
            "category":"Home & Garden",
            "subcategory":"Hardware",
            "type":"Retail Goods"
        }
    ],
    "sg:phone":"+44 1305 853450",
    "sg:postcode":"DT2 8BY",
    "sg:province":"Dorset",
    "sg:tags":[
        "lawnmowers",
        "machinery"
    ],
    "wof:name":"Osmington Horticultural Engineers Ltd.",
    "wof:placetype":"venue"
},
  "geometry": {"coordinates":[-2.31638,50.663177],"type":"Point"}
}