{
  "type": "Feature",
  "properties": {
    "addr:full":"Wyndham Clo, Brackla Indust Est Bridgend Bridgend CF31 2AN",
    "addr:postcode":"cf31 2an",
    "addr:street":"Indust",
    "iso:country":"GB",
    "sg:address":"Wyndham Clo, Brackla Indust Est",
    "sg:city":"Bridgend",
    "sg:classifiers":[
        {
            "category":"Building & Trades",
            "subcategory":"Landscaping Services",
            "type":"Services"
        }
    ],
    "sg:phone":"+44 1656 768928",
    "sg:postcode":"CF31 2AN",
    "sg:province":"Bridgend",
    "sg:tags":[
        "horticultural",
        "consultant"
    ],
    "wof:name":"Jeff's Earthmover Equipment",
    "wof:placetype":"venue"
},
  "geometry": {"coordinates":[-3.549163,51.517918],"type":"Point"}
}