{
  "type": "Feature",
  "properties": {
    "iso:country":"GB",
    "sg:address":"66 Welbeck Road, East",
    "sg:city":"Barnet",
    "sg:classifiers":[
        {
            "category":"Building & Trades",
            "subcategory":"Construction",
            "type":"Services"
        }
    ],
    "sg:postcode":"EN4 8RZ",
    "sg:province":"Hertfordshire",
    "sg:tags":[
        "builder"
    ],
    "wof:name":"H I C (Home Improvement Consultants) Ltd.",
    "wof:placetype":"venue"
},
  "geometry": {"coordinates":[-0.16641,51.641792],"type":"Point"}
}