{
  "type": "Feature",
  "properties": {
    "iso:country":"GB",
    "sg:address":"136 Corporation Road",
    "sg:city":"Grimsby",
    "sg:classifiers":[
        {
            "category":"Shopping",
            "subcategory":"Department Store",
            "type":"Retail Goods"
        }
    ],
    "sg:phone":"+44 1472 349240",
    "sg:postcode":"DN31 1UP",
    "sg:province":"Lincolnshire",
    "wof:name":"B S & G K Sidhu",
    "wof:placetype":"venue"
},
  "geometry": {"coordinates":[-0.093117,53.571014],"type":"Point"}
}