{
  "type": "Feature",
  "properties": {
    "addr:full":"146-148 Warley Hill Brentwood Essex CM14 5HE",
    "addr:housenumber":"146-148",
    "addr:postcode":"cm14 5he",
    "addr:street":"Warley Hill",
    "iso:country":"GB",
    "sg:address":"146-148 Warley Hill",
    "sg:city":"Brentwood",
    "sg:classifiers":[
        {
            "category":"Autos & Motor Vehicles",
            "subcategory":"Fuel & Gas Station",
            "type":"Retail Goods"
        }
    ],
    "sg:phone":"+44 1277 245090",
    "sg:postcode":"CM14 5HE",
    "sg:province":"Essex",
    "sg:tags":[
        "petrol",
        "filling"
    ],
    "wof:name":"Total Convenience Stores",
    "wof:placetype":"venue"
},
  "geometry": {"coordinates":[0.297731,51.607323],"type":"Point"}
}