{
  "type": "Feature",
  "properties": {
    "addr:full":"14 Minehead Avenue, Sully Penarth The Vale of Glamorgan CF64 5TH",
    "addr:housenumber":"14",
    "addr:postcode":"cf64 5th",
    "addr:street":"Minehead Avenue Sully;Vale",
    "iso:country":"GB",
    "sg:address":"14 Minehead Avenue, Sully",
    "sg:city":"Penarth",
    "sg:classifiers":[
        {
            "category":"Organizations",
            "subcategory":"Non-profit Organization",
            "type":"Services"
        }
    ],
    "sg:phone":"+44 29 2053 0291",
    "sg:postcode":"CF64 5TH",
    "sg:province":"The Vale of Glamorgan",
    "sg:tags":[
        "organisation",
        "voluntary",
        "charity"
    ],
    "wof:name":"The Leukaemia Care Society",
    "wof:placetype":"venue"
},
  "geometry": {"coordinates":[-3.2178030014,51.4048347473],"type":"Point"}
}