{
  "type": "Feature",
  "properties": {
    "addr:full":"40 East Dulwich Rd East Dulwich Greater London SE22 9AX",
    "addr:housenumber":"40",
    "addr:postcode":"se22 9ax",
    "addr:street":"East Dulwich Rd",
    "iso:country":"GB",
    "sg:address":"40 East Dulwich Rd",
    "sg:city":"East Dulwich",
    "sg:classifiers":[
        {
            "category":"Building & Trades",
            "subcategory":"Construction",
            "type":"Services"
        }
    ],
    "sg:phone":"+44 20 7277 6677",
    "sg:postcode":"SE22 9AX",
    "sg:province":"Greater London",
    "sg:tags":[
        "decorator",
        "painter"
    ],
    "wof:name":"Enstone Decorations",
    "wof:placetype":"venue"
},
  "geometry": {"coordinates":[-0.0696849972,51.4620056152],"type":"Point"}
}