{
  "type": "Feature",
  "properties": {
    "addr:full":"56 Nest Lane Wellingborough Northamptonshire NN8 4AU",
    "addr:postcode":"nn8 4au",
    "addr:street":"Nest Lane",
    "iso:country":"GB",
    "sg:address":"56 Nest Lane",
    "sg:city":"Wellingborough",
    "sg:classifiers":[
        {
            "category":"Professional",
            "subcategory":"Engineering",
            "type":"Services"
        }
    ],
    "sg:phone":"+44 1933 275900",
    "sg:postcode":"NN8 4AU",
    "sg:province":"Northamptonshire",
    "sg:tags":[
        "contractor",
        "electrical",
        "engineer"
    ],
    "wof:name":"R.A Wood",
    "wof:placetype":"venue"
},
  "geometry": {"coordinates":[-0.6859700084,52.3131866455],"type":"Point"}
}