{
  "type": "Feature",
  "properties": {
    "addr:full":"42 Pembridge Road London Greater London W11 3HN",
    "addr:housenumber":"42",
    "addr:postcode":"w11 3hn",
    "addr:street":"Pembridge Road",
    "iso:country":"GB",
    "sg:address":"42 Pembridge Road",
    "sg:city":"London",
    "sg:classifiers":[
        {
            "category":"Health Services",
            "subcategory":"Doctor",
            "type":"Services"
        }
    ],
    "sg:postcode":"W11 3HN",
    "sg:province":"Greater London",
    "sg:tags":[
        "practitioners"
    ],
    "wof:name":"Sayed M Y Ibrahim",
    "wof:placetype":"venue"
},
  "geometry": {"coordinates":[-0.197723,51.512478],"type":"Point"}
}