{
  "type": "Feature",
  "properties": {
    "iso:country":"GB",
    "sg:address":"Wellingore Hall, Wellingore",
    "sg:city":"Lincoln",
    "sg:classifiers":[
        {
            "category":"Organizations",
            "subcategory":"Non-profit Organization",
            "type":"Services"
        }
    ],
    "sg:phone":"+44 1522 811634",
    "sg:postcode":"LN5 0HX",
    "sg:province":"Lincolnshire",
    "sg:tags":[
        "charitable",
        "organisation",
        "voluntary",
        "charity"
    ],
    "wof:name":"The Royal British Legion",
    "wof:placetype":"venue"
},
  "geometry": {"coordinates":[-0.533302,53.098854],"type":"Point"}
}