{
  "type": "Feature",
  "properties": {
    "iso:country":"GB",
    "sg:address":"141 Tankerton Rd",
    "sg:city":"Whitstable",
    "sg:classifiers":[
        {
            "category":"Shopping",
            "subcategory":"News",
            "type":"Retail Goods"
        }
    ],
    "sg:phone":"+44 1227 770902",
    "sg:postcode":"CT5 2AW",
    "sg:province":"Kent",
    "sg:tags":[
        "newsagent"
    ],
    "wof:name":"Dillons One-Stop",
    "wof:placetype":"venue"
},
  "geometry": {"coordinates":[1.0455679893,51.3638496399],"type":"Point"}
}