{
  "type": "Feature",
  "properties": {
    "addr:full":"177 Dunstable Road Luton Bedfordshire LU1 1BT",
    "addr:housenumber":"177",
    "addr:postcode":"lu1 1bt",
    "addr:street":"Dunstable Road",
    "iso:country":"GB",
    "sg:address":"177 Dunstable Road",
    "sg:city":"Luton",
    "sg:classifiers":[
        {
            "category":"Fast Food",
            "type":"Food & Drink"
        }
    ],
    "sg:phone":"+44 1582 457630",
    "sg:postcode":"LU1 1BT",
    "sg:province":"Bedfordshire",
    "sg:tags":[
        "away",
        "meal",
        "outlet",
        "take"
    ],
    "wof:name":"Southern Fried Chicken",
    "wof:placetype":"venue"
},
  "geometry": {"coordinates":[-0.427599,51.884537],"type":"Point"}
}