{
  "type": "Feature",
  "properties": {
    "iso:country":"GB",
    "sg:address":"Central Park, Gooshays Drive",
    "sg:city":"Romford",
    "sg:classifiers":[
        {
            "category":"Arena",
            "subcategory":"Sports Club",
            "type":"Entertainment"
        }
    ],
    "sg:phone":"+44 1708 371441",
    "sg:postcode":"RM3 9LB",
    "sg:province":"Essex",
    "wof:name":"Ardleigh Green Cricket Club",
    "wof:placetype":"venue"
},
  "geometry": {"coordinates":[0.22454,51.607262],"type":"Point"}
}