{
  "type": "Feature",
  "properties": {
    "addr:full":"Unit 1 West Broomley Farm Stocksfield Northumberland NE43 7HR",
    "addr:housenumber":"unit 1;stocksfield",
    "addr:postcode":"ne43 7hr",
    "addr:street":"West Broomley;Northumberland",
    "iso:country":"GB",
    "sg:address":"Unit 1 West Broomley Farm",
    "sg:city":"Stocksfield",
    "sg:classifiers":[
        {
            "category":"Home & Garden",
            "subcategory":"Kitchen Supply",
            "type":"Retail Goods"
        }
    ],
    "sg:postcode":"NE43 7HR",
    "sg:province":"Northumberland",
    "sg:tags":[
        "ware"
    ],
    "wof:name":"Broomley Furniture Makers",
    "wof:placetype":"venue"
},
  "geometry": {"coordinates":[-1.9163589478,54.9457092285],"type":"Point"}
}