{
  "type": "Feature",
  "properties": {
    "addr:full":"Alexandra Buildings Windermere Cumbria LA23 1BQ",
    "addr:postcode":"la23 1bq",
    "iso:country":"GB",
    "sg:address":"Alexandra Buildings",
    "sg:city":"Windermere",
    "sg:classifiers":[
        {
            "category":"Home & Garden",
            "subcategory":"Kitchen Supply",
            "type":"Retail Goods"
        }
    ],
    "sg:phone":"+44 15394 88100",
    "sg:postcode":"LA23 1BQ",
    "sg:province":"Cumbria",
    "sg:tags":[
        "ware"
    ],
    "wof:name":"Lakeland Plastics Ltd.",
    "wof:placetype":"venue"
},
  "geometry": {"coordinates":[-2.906404,54.379665],"type":"Point"}
}