{
  "type": "Feature",
  "properties": {
    "addr:full":"4 Channel View Terrace, Lipson Plymouth Devon PL4 8SH",
    "addr:housenumber":"4",
    "addr:postcode":"pl4 8sh",
    "addr:street":"Channel View Terrace",
    "iso:country":"GB",
    "sg:address":"4 Channel View Terrace, Lipson",
    "sg:city":"Plymouth",
    "sg:classifiers":[
        {
            "category":"Professional",
            "subcategory":"Accounting & Tax Preparation",
            "type":"Services"
        }
    ],
    "sg:postcode":"PL4 8SH",
    "sg:province":"Devon",
    "sg:tags":[
        "payroll"
    ],
    "wof:name":"Accuserve Ltd.",
    "wof:placetype":"venue"
},
  "geometry": {"coordinates":[-4.1221132278,50.3773193359],"type":"Point"}
}