{
  "type": "Feature",
  "properties": {
    "iso:country":"GB",
    "sg:address":"Hicks Rd",
    "sg:city":"St Albans",
    "sg:classifiers":[
        {
            "category":"Professional",
            "subcategory":"Engineering",
            "type":"Services"
        }
    ],
    "sg:postcode":"AL3 8LJ",
    "sg:province":"Hertfordshire",
    "sg:tags":[
        "precision",
        "engineer"
    ],
    "wof:name":"Truturn Engineering",
    "wof:placetype":"venue"
},
  "geometry": {"coordinates":[-0.453696,51.837349],"type":"Point"}
}