{
  "type": "Feature",
  "properties": {
    "addr:full":"58 Hammonds Drive Eastbourne East Sussex BN23 6PW",
    "addr:housenumber":"58",
    "addr:postcode":"bn23 6pw",
    "addr:street":"Hammonds Drive",
    "iso:country":"GB",
    "sg:address":"58 Hammonds Drive",
    "sg:city":"Eastbourne",
    "sg:classifiers":[
        {
            "category":"Shopping",
            "subcategory":"Computers & Home Electronics",
            "type":"Retail Goods"
        }
    ],
    "sg:phone":"+44 1323 412456",
    "sg:postcode":"BN23 6PW",
    "sg:province":"East Sussex",
    "sg:tags":[
        "electrical"
    ],
    "wof:name":"Edmundson Electrical Ltd.",
    "wof:placetype":"venue"
},
  "geometry": {"coordinates":[0.2965370119,50.7891998291],"type":"Point"}
}