{
  "type": "Feature",
  "properties": {
    "addr:full":"Waterloo Road, Bidford On Avon Alcester Warwickshire B50 4JH",
    "addr:postcode":"avon;b50 4jh",
    "addr:street":"Waterloo Road",
    "iso:country":"GB",
    "sg:address":"Waterloo Road, Bidford On Avon",
    "sg:city":"Alcester",
    "sg:classifiers":[
        {
            "category":"Social Services",
            "subcategory":"Retirement Home",
            "type":"Services"
        }
    ],
    "sg:phone":"+44 1789 773359",
    "sg:postcode":"B50 4JH",
    "sg:province":"Warwickshire",
    "sg:tags":[
        "residential",
        "care"
    ],
    "wof:name":"Waterloo Residential Home",
    "wof:placetype":"venue"
},
  "geometry": {"coordinates":[-1.8532589674,52.1690101624],"type":"Point"}
}