{
  "type": "Feature",
  "properties": {
    "addr:full":"Willow Bank, Kiblers Lane Warwick Warwickshire CV35 0PS",
    "addr:postcode":"cv35 0ps",
    "addr:street":"Willow;Kiblers Lane",
    "iso:country":"GB",
    "sg:address":"Willow Bank, Kiblers Lane",
    "sg:city":"Warwick",
    "sg:classifiers":[
        {
            "category":"Building & Trades",
            "subcategory":"Construction",
            "type":"Services"
        }
    ],
    "sg:postcode":"CV35 0PS",
    "sg:province":"Warwickshire",
    "sg:tags":[
        "builder"
    ],
    "wof:name":"R J Thompson Building Services",
    "wof:placetype":"venue"
},
  "geometry": {"coordinates":[-1.540274,52.110458],"type":"Point"}
}