{
  "type": "Feature",
  "properties": {
    "iso:country":"GB",
    "sg:address":"Goldthorpe Road, Goldthorpe",
    "sg:city":"Rotherham",
    "sg:classifiers":[
        {
            "category":"Health Services",
            "subcategory":"Clinic",
            "type":"Services"
        }
    ],
    "sg:phone":"+44 1709 881282",
    "sg:postcode":"S63 9EQ",
    "sg:province":"South Yorkshire",
    "sg:tags":[
        "nh"
    ],
    "wof:name":"Goldthorpe Clinic",
    "wof:placetype":"venue"
},
  "geometry": {"coordinates":[-1.304249,53.532574],"type":"Point"}
}