{
  "type": "Feature",
  "properties": {
    "addr:full":"228 High Street Gateshead Tyne and Wear NE8 1AQ",
    "addr:housenumber":"228",
    "addr:postcode":"ne8 1aq",
    "addr:street":"High Street",
    "iso:country":"GB",
    "sg:address":"228 High Street",
    "sg:city":"Gateshead",
    "sg:classifiers":[
        {
            "category":"Shopping",
            "subcategory":"Pawn Shop",
            "type":"Retail Goods"
        }
    ],
    "sg:phone":"+44 191 478 1730",
    "sg:postcode":"NE8 1AQ",
    "sg:province":"Tyne and Wear",
    "sg:tags":[
        "pawnbroker"
    ],
    "wof:name":"Albemarle & Bond Pawnbrokers Ltd.",
    "wof:placetype":"venue"
},
  "geometry": {"coordinates":[-1.6007879972,54.9623031616],"type":"Point"}
}