{
  "type": "Feature",
  "properties": {
    "addr:full":"28 Little Hill Way, South Woodgate Birmingham West Midlands B32 3RZ",
    "addr:housenumber":"28",
    "addr:postcode":"b32 3rz",
    "addr:street":"Little Hill Way South Woodgate",
    "iso:country":"GB",
    "sg:address":"28 Little Hill Way, South Woodgate",
    "sg:city":"Birmingham",
    "sg:classifiers":[
        {
            "category":"Professional",
            "subcategory":"Management & Consulting",
            "type":"Services"
        }
    ],
    "sg:phone":"+44 121 422 4040",
    "sg:postcode":"B32 3RZ",
    "sg:province":"West Midlands",
    "sg:tags":[
        "consultant",
        "business"
    ],
    "wof:name":"Itec Consultants Ltd",
    "wof:placetype":"venue"
},
  "geometry": {"coordinates":[-1.9895000458,52.443157196],"type":"Point"}
}