{
  "type": "Feature",
  "properties": {
    "iso:country":"GB",
    "sg:address":"23 Gravelly Hill North, Erdington",
    "sg:city":"Birmingham",
    "sg:classifiers":[
        {
            "category":"Social Services",
            "subcategory":"Adult Care",
            "type":"Services"
        },
        {
            "category":"Social Services",
            "subcategory":"Retirement Home",
            "type":"Services"
        }
    ],
    "sg:phone":"+44 121 686 6588",
    "sg:postcode":"B23 6BT",
    "sg:province":"West Midlands",
    "sg:tags":[
        "housing",
        "sheltered",
        "accommodation"
    ],
    "wof:name":"Albert Weedhall Centre",
    "wof:placetype":"venue"
},
  "geometry": {"coordinates":[-1.849784,52.515903],"type":"Point"}
}