{
  "type": "Feature",
  "properties": {
    "addr:full":"335 Old St Clerkenwell Greater London EC1V 9LL",
    "addr:housenumber":"335",
    "addr:postcode":"ec1v 9ll",
    "addr:street":"Old St",
    "iso:country":"GB",
    "sg:address":"335 Old St",
    "sg:city":"Clerkenwell",
    "sg:classifiers":[
        {
            "category":"Government",
            "subcategory":"Police Station",
            "type":"Public Place"
        }
    ],
    "sg:phone":"+44 20 7613 1212",
    "sg:postcode":"EC1V 9LL",
    "sg:province":"Greater London",
    "sg:tags":[
        "support"
    ],
    "wof:name":"Metropolitan Police",
    "wof:placetype":"venue"
},
  "geometry": {"coordinates":[-0.079752,51.527328],"type":"Point"}
}