{
  "type": "Feature",
  "properties": {
    "iso:country":"GB",
    "sg:address":"Sweet F1 North Of England",
    "sg:city":"Sunderland",
    "sg:classifiers":[
        {
            "category":"Social Services",
            "subcategory":"Retirement Home",
            "type":"Services"
        }
    ],
    "sg:phone":"+44 191 516 6503",
    "sg:postcode":"SR5 2TA",
    "sg:province":"Tyne and Wear",
    "sg:tags":[
        "care"
    ],
    "wof:name":"Care At Home",
    "wof:placetype":"venue"
},
  "geometry": {"coordinates":[-1.41556,54.918678],"type":"Point"}
}