{
  "type": "Feature",
  "properties": {
    "addr:full":"192 Southfield Avenue, Preston Paignton Devon TQ3 1JX",
    "addr:housenumber":"192",
    "addr:postcode":"tq3 1jx",
    "addr:street":"Southfield Avenue",
    "iso:country":"GB",
    "sg:address":"192 Southfield Avenue, Preston",
    "sg:city":"Paignton",
    "sg:classifiers":[
        {
            "category":"Professional",
            "subcategory":"Engineering",
            "type":"Services"
        },
        {
            "category":"Professional",
            "subcategory":"Computer Services",
            "type":"Services"
        }
    ],
    "sg:phone":"+44 1803 666080",
    "sg:postcode":"TQ3 1JX",
    "sg:province":"Devon",
    "sg:tags":[
        "aided",
        "consulting",
        "design",
        "engineer"
    ],
    "wof:name":"S C I'entec",
    "wof:placetype":"venue"
},
  "geometry": {"coordinates":[-3.5852410793,50.4488067627],"type":"Point"}
}