{
  "type": "Feature",
  "properties": {
    "iso:country":"GB",
    "sg:address":"Church Street, Stenhousemuir",
    "sg:city":"Larbert",
    "sg:classifiers":[
        {
            "category":"Sports & Exercise",
            "subcategory":"Bowling",
            "type":"Entertainment"
        }
    ],
    "sg:phone":"+44 1324 554686",
    "sg:postcode":"FK5 4QR",
    "sg:province":"Falkirk",
    "sg:tags":[
        "centre"
    ],
    "wof:name":"Stenhousemuir Bowling Club",
    "wof:placetype":"venue"
},
  "geometry": {"coordinates":[-3.802606,56.032612],"type":"Point"}
}