{
  "type": "Feature",
  "properties": {
    "iso:country":"GB",
    "sg:address":"Fort House Factory, 36 East St",
    "sg:city":"South Molton",
    "sg:classifiers":[
        {
            "category":"Home & Garden",
            "subcategory":"Building Materials",
            "type":"Retail Goods"
        }
    ],
    "sg:phone":"+44 1769 574408",
    "sg:postcode":"EX36 3DF",
    "sg:province":"Devon",
    "sg:tags":[
        "ornamental",
        "metalwork"
    ],
    "wof:name":"Kilburn Engineering Services",
    "wof:placetype":"venue"
},
  "geometry": {"coordinates":[-3.8318240643,51.0176467896],"type":"Point"}
}