{
  "type": "Feature",
  "properties": {
    "addr:full":"391 Crofton Rd Orpington Kent BR6 8NL",
    "addr:housenumber":"391",
    "addr:postcode":"br6 8nl",
    "addr:street":"Crofton Rd",
    "iso:country":"GB",
    "sg:address":"391 Crofton Rd",
    "sg:city":"Orpington",
    "sg:classifiers":[
        {
            "category":"Autos & Motor Vehicles",
            "subcategory":"Fuel & Gas Station",
            "type":"Retail Goods"
        }
    ],
    "sg:phone":"+44 1689 857196",
    "sg:postcode":"BR6 8NL",
    "sg:province":"Kent",
    "sg:tags":[
        "hr",
        "petrol"
    ],
    "wof:name":"Rosetta Service Station",
    "wof:placetype":"venue"
},
  "geometry": {"coordinates":[0.05519,51.36721],"type":"Point"}
}