{
  "type": "Feature",
  "properties": {
    "iso:country":"GB",
    "sg:address":"26 Hollands Road",
    "sg:city":"Haverhill",
    "sg:classifiers":[
        {
            "category":"Manufacturing",
            "subcategory":"Electronics",
            "type":"Manufacturing & Wholesale Goods"
        }
    ],
    "sg:phone":"+44 1440 707010",
    "sg:postcode":"CB9 8PR",
    "sg:province":"Essex",
    "sg:tags":[
        "control",
        "component",
        "-",
        "electronic"
    ],
    "wof:name":"Micrometics Ltd.",
    "wof:placetype":"venue"
},
  "geometry": {"coordinates":[0.442393,52.07555],"type":"Point"}
}