{
  "type": "Feature",
  "properties": {
    "addr:full":"Pickhill Thirsk North Yorkshire YO7 4JG",
    "addr:postcode":"yo7 4jg",
    "iso:country":"GB",
    "sg:address":"Pickhill",
    "sg:city":"Thirsk",
    "sg:classifiers":[
        {
            "category":"Bars & Pubs",
            "type":"Food & Drink"
        }
    ],
    "sg:phone":"+44 1845 567391",
    "sg:postcode":"YO7 4JG",
    "sg:province":"North Yorkshire",
    "sg:tags":[
        "pubs",
        "inn"
    ],
    "wof:name":"The Nag's Head Hotel",
    "wof:placetype":"venue"
},
  "geometry": {"coordinates":[-1.4705959558,54.2475166321],"type":"Point"}
}