{
  "type": "Feature",
  "properties": {
    "addr:full":"1 Farebrother Street Grimsby Lincolnshire DN32 0NH",
    "addr:housenumber":"1",
    "addr:postcode":"dn32 0nh",
    "addr:street":"Farebrother Street",
    "iso:country":"GB",
    "sg:address":"1 Farebrother Street",
    "sg:city":"Grimsby",
    "sg:classifiers":[
        {
            "category":"Fast Food",
            "type":"Food & Drink"
        }
    ],
    "sg:postcode":"DN32 0NH",
    "sg:province":"Lincolnshire",
    "sg:tags":[
        "away",
        "take"
    ],
    "wof:name":"Hungry Jacks",
    "wof:placetype":"venue"
},
  "geometry": {"coordinates":[-0.080711,53.560501],"type":"Point"}
}