{
  "type": "Feature",
  "properties": {
    "iso:country":"GB",
    "sg:address":"40 Muir Road, Townhill",
    "sg:city":"Dunfermline",
    "sg:classifiers":[
        {
            "category":"Real Estate",
            "subcategory":"Developer",
            "type":"Services"
        },
        {
            "category":"Building & Trades",
            "subcategory":"Construction",
            "type":"Services"
        }
    ],
    "sg:phone":"+44 1383 736561",
    "sg:postcode":"KY12 0EG",
    "sg:province":"Fife",
    "sg:tags":[
        "residential",
        "builder",
        "property"
    ],
    "wof:name":"Carneil Homes Ltd",
    "wof:placetype":"venue"
},
  "geometry": {"coordinates":[-3.430091,56.086372],"type":"Point"}
}