{
  "type": "Feature",
  "properties": {
    "addr:full":"7 Mottingham Road London Greater London N9 8DX",
    "addr:housenumber":"7",
    "addr:postcode":"n9 8dx",
    "addr:street":"Mottingham Road",
    "iso:country":"GB",
    "sg:address":"7 Mottingham Road",
    "sg:city":"London",
    "sg:classifiers":[
        {
            "category":"Food & Beverages",
            "subcategory":"Liquor & Beverages",
            "type":"Retail Goods"
        },
        {
            "category":"Food & Beverages",
            "subcategory":"Groceries & Convenience Stores",
            "type":"Retail Goods"
        }
    ],
    "sg:phone":"+44 20 8804 2394",
    "sg:postcode":"N9 8DX",
    "sg:province":"Greater London",
    "sg:tags":[
        "beer",
        "spirit",
        "wine"
    ],
    "wof:name":"WAVY LINE FOODSTORE",
    "wof:placetype":"venue"
},
  "geometry": {"coordinates":[-0.0418559983,51.6364517212],"type":"Point"}
}