{
  "type": "Feature",
  "properties": {
    "addr:full":"125 Godstone Road Whyteleafe Surrey CR3 0EH",
    "addr:housenumber":"125",
    "addr:postcode":"cr3 0eh",
    "addr:street":"Godstone Road",
    "iso:country":"GB",
    "sg:address":"125 Godstone Road",
    "sg:city":"Whyteleafe",
    "sg:classifiers":[
        {
            "category":"Organizations",
            "subcategory":"Community Association",
            "type":"Services"
        },
        {
            "category":"Organizations",
            "subcategory":"Membership Organization",
            "type":"Services"
        }
    ],
    "sg:phone":"+44 20 8660 3846",
    "sg:postcode":"CR3 0EH",
    "sg:province":"Surrey",
    "sg:tags":[
        "club",
        "social"
    ],
    "wof:name":"The Royal British Legion",
    "wof:placetype":"venue"
},
  "geometry": {"coordinates":[-0.080415,51.311863],"type":"Point"}
}