{
  "type": "Feature",
  "properties": {
    "addr:full":"138 Pelham Road Gravesend Kent DA11 0JH",
    "addr:housenumber":"138",
    "addr:postcode":"da11 0jh",
    "addr:street":"Pelham Road",
    "iso:country":"GB",
    "sg:address":"138 Pelham Road",
    "sg:city":"Gravesend",
    "sg:classifiers":[
        {
            "category":"Communications",
            "subcategory":"Film & Video Production",
            "type":"Services"
        },
        {
            "category":"Communications",
            "type":"Services"
        }
    ],
    "sg:phone":"+44 1474 569601",
    "sg:postcode":"DA11 0JH",
    "sg:province":"Kent",
    "sg:tags":[
        "tv",
        "studio",
        "radio"
    ],
    "wof:name":"Electrical Discount Centre",
    "wof:placetype":"venue"
},
  "geometry": {"coordinates":[0.357322,51.43565],"type":"Point"}
}