{
  "type": "Feature",
  "properties": {
    "addr:full":"The Oak, Clun Craven Arms Herefordshire SY7 8QA",
    "addr:postcode":"sy7 8qa",
    "addr:street":"Clun;Herefordshire",
    "iso:country":"GB",
    "sg:address":"The Oak, Clun",
    "sg:city":"Craven Arms",
    "sg:classifiers":[
        {
            "category":"Farming",
            "subcategory":"Livestock Farm",
            "type":"Manufacturing & Wholesale Goods"
        }
    ],
    "sg:phone":"+44 1588 640411",
    "sg:postcode":"SY7 8QA",
    "sg:province":"Herefordshire",
    "sg:tags":[
        "others"
    ],
    "wof:name":"R N Brereton",
    "wof:placetype":"venue"
},
  "geometry": {"coordinates":[-3.0270490646,52.4214401245],"type":"Point"}
}