{
  "type": "Feature",
  "properties": {
    "addr:full":"21 Barton Cross, Horndean Waterlooville Hampshire PO8 9PQ",
    "addr:housenumber":"21",
    "addr:postcode":"po8 9pq",
    "addr:street":"Barton Cross",
    "iso:country":"GB",
    "sg:address":"21 Barton Cross, Horndean",
    "sg:city":"Waterlooville",
    "sg:classifiers":[
        {
            "category":"Building & Trades",
            "subcategory":"Construction",
            "type":"Services"
        }
    ],
    "sg:postcode":"PO8 9PQ",
    "sg:province":"Hampshire",
    "sg:tags":[
        "builder"
    ],
    "wof:name":"Oakland Contractors Ltd",
    "wof:placetype":"venue"
},
  "geometry": {"coordinates":[-1.0102299452,50.9130516052],"type":"Point"}
}