{
  "type": "Feature",
  "properties": {
    "iso:country":"GB",
    "sg:address":"Unit 5 Rhymney River, Bridge Rd",
    "sg:city":"Cardiff",
    "sg:classifiers":[
        {
            "category":"Professional",
            "subcategory":"Art Services",
            "type":"Services"
        }
    ],
    "sg:phone":"+44 29 2048 1797",
    "sg:postcode":"CF3 7AF",
    "sg:province":"Caerphilly",
    "sg:tags":[
        "decorating",
        "painting"
    ],
    "wof:name":"Courtaulds Coatings",
    "wof:placetype":"venue"
},
  "geometry": {"coordinates":[-3.139013,51.498596],"type":"Point"}
}