{
  "type": "Feature",
  "properties": {
    "addr:full":"24 Osborne Street Barrow-in-furness Cumbria LA14 5SA",
    "addr:housenumber":"24",
    "addr:postcode":"la14 5sa",
    "addr:street":"Osborne Street",
    "iso:country":"GB",
    "sg:address":"24 Osborne Street",
    "sg:city":"Barrow-in-furness",
    "sg:classifiers":[
        {
            "category":"Personal",
            "subcategory":"Adult",
            "type":"Services"
        }
    ],
    "sg:phone":"+44 1229 830342",
    "sg:postcode":"LA14 5SA",
    "sg:province":"Cumbria",
    "sg:tags":[
        "equestrian"
    ],
    "wof:name":"Oaklea Livery Stables",
    "wof:placetype":"venue"
},
  "geometry": {"coordinates":[-3.2321059704,54.1200714111],"type":"Point"}
}