{
  "type": "Feature",
  "properties": {
    "addr:full":"88 Pinchbeck Road Spalding Lincolnshire PE11 1QF",
    "addr:housenumber":"88",
    "addr:postcode":"pe11 1qf",
    "addr:street":"Pinchbeck Road",
    "iso:country":"GB",
    "sg:address":"88 Pinchbeck Road",
    "sg:city":"Spalding",
    "sg:classifiers":[
        {
            "category":"Retail",
            "subcategory":"Auto Repair",
            "type":"Services"
        }
    ],
    "sg:phone":"+44 1775 710280",
    "sg:postcode":"PE11 1QF",
    "sg:province":"Lincolnshire",
    "sg:tags":[
        "body",
        "car"
    ],
    "wof:name":"Grays Body Shop",
    "wof:placetype":"venue"
},
  "geometry": {"coordinates":[-0.151753,52.794334],"type":"Point"}
}