{
  "type": "Feature",
  "properties": {
    "addr:full":"Parklea Playing Fields, Greenock Road Port Glasgow Inverclyde PA14 6TR",
    "addr:postcode":"pa14 6tr",
    "addr:street":"Greenock Road",
    "iso:country":"GB",
    "sg:address":"Parklea Playing Fields, Greenock Road",
    "sg:city":"Port Glasgow",
    "sg:classifiers":[
        {
            "category":"Education",
            "subcategory":"Special Training",
            "type":"Public Place"
        }
    ],
    "sg:phone":"+44 1475 744516",
    "sg:postcode":"PA14 6TR",
    "sg:province":"Inverclyde",
    "sg:tags":[
        "product",
        "centre"
    ],
    "wof:name":"Parklea Association Branching Out Ltd.",
    "wof:placetype":"venue"
},
  "geometry": {"coordinates":[-4.6425800323,55.9301490784],"type":"Point"}
}