{
  "type": "Feature",
  "properties": {
    "addr:full":"31 Clarence Arcade Ashton-under-lyne Greater Manchester OL6 7PT",
    "addr:housenumber":"31;arcade",
    "addr:postcode":"ol6 7pt",
    "addr:street":"Clarence",
    "iso:country":"GB",
    "sg:address":"31 Clarence Arcade",
    "sg:city":"Ashton-under-lyne",
    "sg:classifiers":[
        {
            "category":"Shopping",
            "subcategory":"Clothing, Apparel, & Fashions",
            "type":"Retail Goods"
        }
    ],
    "sg:phone":"+44 161 339 4730",
    "sg:postcode":"OL6 7PT",
    "sg:province":"Greater Manchester",
    "sg:tags":[
        "shop"
    ],
    "wof:name":"Bonanza Shop",
    "wof:placetype":"venue"
},
  "geometry": {"coordinates":[-2.0936388969,53.4872398376],"type":"Point"}
}