{
  "type": "Feature",
  "properties": {
    "iso:country":"GB",
    "sg:address":"96 Silbury Arcade",
    "sg:city":"Milton Keynes",
    "sg:classifiers":[
        {
            "category":"Shopping",
            "subcategory":"Gifts & Souvenirs",
            "type":"Retail Goods"
        }
    ],
    "sg:postcode":"MK9 3BE",
    "sg:province":"Buckinghamshire",
    "sg:tags":[
        "poster",
        "card"
    ],
    "wof:name":"Birthdays Ltd",
    "wof:placetype":"venue"
},
  "geometry": {"coordinates":[-0.7602180243,52.0425033569],"type":"Point"}
}