{
  "type": "Feature",
  "properties": {
    "iso:country":"GB",
    "sg:address":"Harley Industrial Park, Paxton Hill",
    "sg:city":"St Neots",
    "sg:classifiers":[
        {
            "category":"Professional",
            "type":"Services"
        }
    ],
    "sg:phone":"+44 1480 477070",
    "sg:postcode":"PE19 6TA",
    "sg:province":"Bedfordshire",
    "sg:tags":[
        "control",
        "system"
    ],
    "wof:name":"Colridge Ltd.",
    "wof:placetype":"venue"
},
  "geometry": {"coordinates":[-0.235239,52.248627],"type":"Point"}
}