{
  "type": "Feature",
  "properties": {
    "addr:full":"18 Lincoln Rd Bedford Bedfordshire MK42 0UX",
    "addr:housenumber":"18",
    "addr:postcode":"mk42 0ux",
    "addr:street":"Lincoln Rd",
    "iso:country":"GB",
    "sg:address":"18 Lincoln Rd",
    "sg:city":"Bedford",
    "sg:classifiers":[
        {
            "category":"Home & Garden",
            "subcategory":"Carpets & Floor Coverings",
            "type":"Retail Goods"
        }
    ],
    "sg:phone":"+44 1234 741585",
    "sg:postcode":"MK42 0UX",
    "sg:province":"Bedfordshire",
    "sg:tags":[
        "cleaner",
        "upholstery"
    ],
    "wof:name":"G P Auto Cleaning",
    "wof:placetype":"venue"
},
  "geometry": {"coordinates":[-0.438218,52.110695],"type":"Point"}
}