{
  "type": "Feature",
  "properties": {
    "iso:country":"GB",
    "sg:address":"P O Box 48",
    "sg:city":"Rickmansworth",
    "sg:classifiers":[
        {
            "category":"Professional",
            "type":"Services"
        }
    ],
    "sg:postcode":"WD3 4NZ",
    "sg:province":"Hertfordshire",
    "sg:tags":[
        "specialist",
        "coating"
    ],
    "wof:name":"Rico Engineering Ltd.",
    "wof:placetype":"venue"
},
  "geometry": {"coordinates":[-0.485759,51.655571],"type":"Point"}
}