{
  "type": "Feature",
  "properties": {
    "iso:country":"GB",
    "sg:address":"89 High Street",
    "sg:city":"Brechin",
    "sg:classifiers":[
        {
            "category":"Fast Food",
            "type":"Food & Drink"
        }
    ],
    "sg:phone":"+44 1356 625002",
    "sg:postcode":"DD9 6HF",
    "sg:province":"Aberdeenshire",
    "sg:tags":[
        "away",
        "take"
    ],
    "wof:name":"Snappy Jacks",
    "wof:placetype":"venue"
},
  "geometry": {"coordinates":[-2.65813,56.730598],"type":"Point"}
}