{
  "type": "Feature",
  "properties": {
    "addr:full":"95a Linaker Street Southport Lancashire PR8 5BU",
    "addr:housenumber":"95a",
    "addr:postcode":"pr8 5bu",
    "addr:street":"Linaker Street",
    "iso:country":"GB",
    "sg:address":"95a Linaker Street",
    "sg:city":"Southport",
    "sg:classifiers":[
        {
            "category":"Professional",
            "type":"Services"
        },
        {
            "category":"Professional",
            "subcategory":"Business Services",
            "type":"Services"
        }
    ],
    "sg:phone":"+44 1704 530800",
    "sg:postcode":"PR8 5BU",
    "sg:province":"Lancashire",
    "sg:tags":[
        "shopfitting",
        "shopfitters",
        "contractor"
    ],
    "sg:website":"http://www.mentha-halsall.com",
    "wof:name":"Mentha & Halsall (Shopfitters) Ltd.",
    "wof:placetype":"venue"
},
  "geometry": {"coordinates":[-3.003572,53.638283],"type":"Point"}
}