{
  "type": "Feature",
  "properties": {
    "iso:country":"GB",
    "sg:address":"Oak Dene, Gordon Road",
    "sg:city":"Cheltenham",
    "sg:classifiers":[
        {
            "category":"Building & Trades",
            "subcategory":"Construction",
            "type":"Services"
        }
    ],
    "sg:phone":"+44 1242 242086",
    "sg:postcode":"GL53 0ES",
    "sg:province":"Gloucestershire",
    "sg:tags":[
        "restoration",
        "refurbishment"
    ],
    "wof:name":"Green Archer Renovations & Decorations",
    "wof:placetype":"venue"
},
  "geometry": {"coordinates":[-2.0818,51.881989],"type":"Point"}
}