{
  "type": "Feature",
  "properties": {
    "addr:full":"Old Sarum Park, Lysander Way, Old Sarum Salisbury Hampshire SP4 6BU",
    "addr:postcode":"sp4 6bu",
    "addr:street":"Lysander Way",
    "iso:country":"GB",
    "sg:address":"Old Sarum Park, Lysander Way, Old Sarum",
    "sg:city":"Salisbury",
    "sg:classifiers":[
        {
            "category":"Home & Garden",
            "subcategory":"Home Furnishings",
            "type":"Retail Goods"
        },
        {
            "category":"Shopping",
            "type":"Retail Goods"
        }
    ],
    "sg:phone":"+44 1722 411585",
    "sg:postcode":"SP4 6BU",
    "sg:province":"Hampshire",
    "sg:tags":[
        "racking",
        "part",
        "shelving",
        "diy",
        "accessory"
    ],
    "wof:name":"Sortimo International Ltd.",
    "wof:placetype":"venue"
},
  "geometry": {"coordinates":[-1.7799839973,51.1025733948],"type":"Point"}
}