{
  "type": "Feature",
  "properties": {
    "iso:country":"GB",
    "sg:address":"Ashling House, Works Lane, Lostock Gralam",
    "sg:city":"Northwich",
    "sg:classifiers":[
        {
            "category":"Social Services",
            "type":"Services"
        },
        {
            "category":"Health Services",
            "subcategory":"Doctor",
            "type":"Services"
        }
    ],
    "sg:phone":"+44 1606 330660",
    "sg:postcode":"CW9 7FA",
    "sg:province":"Cheshire",
    "sg:tags":[
        "practitioners",
        "authority"
    ],
    "sg:website":"http://www.ashling.co.uk",
    "wof:name":"Ashling Occupational Health Ltd.",
    "wof:placetype":"venue"
},
  "geometry": {"coordinates":[-2.477542,53.266563],"type":"Point"}
}