{
  "type": "Feature",
  "properties": {
    "addr:full":"30 The Maltings St Albans Hertfordshire AL1 3HL",
    "addr:housenumber":"30",
    "addr:postcode":"al1 3hl",
    "addr:street":"The Maltings",
    "iso:country":"GB",
    "sg:address":"30 The Maltings",
    "sg:city":"St Albans",
    "sg:classifiers":[
        {
            "category":"Shopping",
            "subcategory":"Department Store",
            "type":"Retail Goods"
        },
        {
            "category":"Shopping",
            "subcategory":"Music",
            "type":"Retail Goods"
        }
    ],
    "sg:phone":"+44 1727 840147",
    "sg:postcode":"AL1 3HL",
    "sg:province":"Hertfordshire",
    "sg:tags":[
        "record",
        "tape",
        "cd"
    ],
    "wof:name":"Moore,F L,",
    "wof:placetype":"venue"
},
  "geometry": {"coordinates":[-0.3372280002,51.7511787415],"type":"Point"}
}