{
  "type": "Feature",
  "properties": {
    "addr:full":"296 Ilford La Ilford Essex IG1 2LP",
    "addr:housenumber":"296",
    "addr:postcode":"ig1 2lp",
    "addr:street":"Ilford La Ilford",
    "iso:country":"GB",
    "sg:address":"296 Ilford La",
    "sg:city":"Ilford",
    "sg:classifiers":[
        {
            "category":"Fast Food",
            "type":"Food & Drink"
        }
    ],
    "sg:phone":"+44 20 8478 2229",
    "sg:postcode":"IG1 2LP",
    "sg:province":"Essex",
    "sg:tags":[
        "away",
        "take"
    ],
    "wof:name":"Green Cafe",
    "wof:placetype":"venue"
},
  "geometry": {"coordinates":[0.0746489987,51.5501708984],"type":"Point"}
}