{
  "type": "Feature",
  "properties": {
    "addr:full":"12-28 Longford Road Bognor Regis West Sussex PO21 1AQ",
    "addr:housenumber":"12-28",
    "addr:postcode":"po21 1aq",
    "addr:street":"Longford Road",
    "iso:country":"GB",
    "sg:address":"12-28 Longford Road",
    "sg:city":"Bognor Regis",
    "sg:classifiers":[
        {
            "category":"Professional",
            "subcategory":"Testing Lab",
            "type":"Services"
        }
    ],
    "sg:phone":"+44 1243 865515",
    "sg:postcode":"PO21 1AQ",
    "sg:province":"West Sussex",
    "sg:tags":[
        "mot"
    ],
    "wof:name":"Bogner Motors Ltd.",
    "wof:placetype":"venue"
},
  "geometry": {"coordinates":[-0.676434,50.787548],"type":"Point"}
}