{
  "type": "Feature",
  "properties": {
    "addr:full":"Ryelands, Gorsley Ross-on-wye Gloucestershire HR9 7SP",
    "addr:postcode":"hr9 7sp",
    "iso:country":"GB",
    "sg:address":"Ryelands, Gorsley",
    "sg:city":"Ross-on-wye",
    "sg:classifiers":[
        {
            "category":"Social Services",
            "subcategory":"Retirement Home",
            "type":"Services"
        }
    ],
    "sg:phone":"+44 1989 720425",
    "sg:postcode":"HR9 7SP",
    "sg:province":"Gloucestershire",
    "sg:tags":[
        "residential",
        "care"
    ],
    "wof:name":"Salters Hill Charity Ltd.",
    "wof:placetype":"venue"
},
  "geometry": {"coordinates":[-2.581733,51.916481],"type":"Point"}
}