{
  "type": "Feature",
  "properties": {
    "iso:country":"GB",
    "sg:address":"Orchard House City Lane, Colmworth",
    "sg:city":"Bedford",
    "sg:classifiers":[
        {
            "category":"Organizations",
            "subcategory":"Membership Organization",
            "type":"Services"
        }
    ],
    "sg:postcode":"MK44 2LE",
    "sg:province":"Bedfordshire",
    "sg:tags":[
        "club"
    ],
    "wof:name":"City Lane Consultancy Ltd",
    "wof:placetype":"venue"
},
  "geometry": {"coordinates":[-0.375837,52.219681],"type":"Point"}
}