{
  "type": "Feature",
  "properties": {
    "addr:full":"Thorley Manor, Thorley Yarmouth Isle of Wight PO41 0SJ",
    "addr:postcode":"po41 0sj",
    "iso:country":"GB",
    "sg:address":"Thorley Manor, Thorley",
    "sg:city":"Yarmouth",
    "sg:classifiers":[
        {
            "category":"Farming",
            "subcategory":"Livestock Farm",
            "type":"Manufacturing & Wholesale Goods"
        }
    ],
    "sg:phone":"+44 1983 760210",
    "sg:postcode":"PO41 0SJ",
    "sg:province":"Isle of Wight",
    "sg:tags":[
        "others"
    ],
    "wof:name":"S & J Bastian",
    "wof:placetype":"venue"
},
  "geometry": {"coordinates":[-1.496659,50.705009],"type":"Point"}
}