{
  "type": "Feature",
  "properties": {
    "iso:country":"GB",
    "sg:address":"34 Craigewan Crescent",
    "sg:city":"Peterhead",
    "sg:classifiers":[
        {
            "category":"Building & Trades",
            "subcategory":"Construction",
            "type":"Services"
        }
    ],
    "sg:phone":"+44 1779 470612",
    "sg:postcode":"AB42 1HL",
    "sg:province":"Aberdeenshire",
    "sg:tags":[
        "decorator",
        "painter"
    ],
    "wof:name":"G Davidson",
    "wof:placetype":"venue"
},
  "geometry": {"coordinates":[-1.794275,57.512875],"type":"Point"}
}