{
  "type": "Feature",
  "properties": {
    "addr:full":"Stockbridge House, 272 Abbeydale Road Wembley Greater London HA0 1PZ",
    "addr:housenumber":"272",
    "addr:postcode":"ha0 1pz",
    "addr:street":"Abbeydale Road",
    "iso:country":"GB",
    "sg:address":"Stockbridge House, 272 Abbeydale Road",
    "sg:city":"Wembley",
    "sg:classifiers":[
        {
            "category":"Professional",
            "subcategory":"Printing & Photocopies",
            "type":"Services"
        }
    ],
    "sg:phone":"+44 20 8998 9937",
    "sg:postcode":"HA0 1PZ",
    "sg:province":"Greater London",
    "sg:tags":[
        "plate",
        "lithographic",
        "maker"
    ],
    "wof:name":"M A Litho Ltd.",
    "wof:placetype":"venue"
},
  "geometry": {"coordinates":[-0.284045,51.538822],"type":"Point"}
}