{
  "type": "Feature",
  "properties": {
    "addr:full":"Unit D3 Double Row Whitley Bay Northumberland NE25 0PP",
    "addr:housenumber":"d3",
    "addr:postcode":"ne25 0pp",
    "addr:street":"Double Row",
    "iso:country":"GB",
    "sg:address":"Unit D3 Double Row",
    "sg:city":"Whitley Bay",
    "sg:classifiers":[
        {
            "category":"Home & Garden",
            "subcategory":"Building Materials",
            "type":"Retail Goods"
        },
        {
            "category":"Military Area",
            "subcategory":"Air Force Base",
            "type":"Public Place"
        }
    ],
    "sg:phone":"+44 191 298 0441",
    "sg:postcode":"NE25 0PP",
    "sg:province":"Northumberland",
    "sg:tags":[
        "ornamental",
        "metalwork",
        "production"
    ],
    "wof:name":"JOHN AYNSLEY (ARCHITECTURAL METALWORK) LTD",
    "wof:placetype":"venue"
},
  "geometry": {"coordinates":[-1.5348379612,55.0779266357],"type":"Point"}
}