{
  "type": "Feature",
  "properties": {
    "addr:full":"Rainford Hall, Crank Road, Crank St Helens Lancashire WA11 7RP",
    "addr:housenumber":"rainford",
    "addr:postcode":"wa11 7rp",
    "addr:street":"Hall Crank Road Crank",
    "iso:country":"GB",
    "sg:address":"Rainford Hall, Crank Road, Crank",
    "sg:city":"St Helens",
    "sg:classifiers":[
        {
            "category":"Real Estate",
            "subcategory":"Surveying",
            "type":"Services"
        }
    ],
    "sg:phone":"+44 1744 451145",
    "sg:postcode":"WA11 7RP",
    "sg:province":"Lancashire",
    "sg:tags":[
        "surveyor",
        "valuer"
    ],
    "wof:name":"John Royle Chartered Surveyors",
    "wof:placetype":"venue"
},
  "geometry": {"coordinates":[-2.7473499775,53.4835700989],"type":"Point"}
}