{
  "type": "Feature",
  "properties": {
    "addr:full":"High Road Ware Hertfordshire SG11 1AZ",
    "addr:postcode":"sg11 1az",
    "addr:street":"High Road Ware",
    "iso:country":"GB",
    "sg:address":"High Road",
    "sg:city":"Ware",
    "sg:classifiers":[
        {
            "category":"Retail",
            "subcategory":"Auto Repair",
            "type":"Services"
        }
    ],
    "sg:phone":"+44 1920 462024",
    "sg:postcode":"SG11 1AZ",
    "sg:province":"Hertfordshire",
    "sg:tags":[
        "modification",
        "garage"
    ],
    "wof:name":"H C Motors Ltd.",
    "wof:placetype":"venue"
},
  "geometry": {"coordinates":[0.0273369998,51.8819351196],"type":"Point"}
}