{
  "type": "Feature",
  "properties": {
    "addr:full":"57 Westfield Road Leeds West Yorkshire LS3 1DF",
    "addr:housenumber":"57",
    "addr:postcode":"ls3 1df",
    "addr:street":"Westfield Road",
    "iso:country":"GB",
    "sg:address":"57 Westfield Road",
    "sg:city":"Leeds",
    "sg:classifiers":[
        {
            "category":"Autos & Motor Vehicles",
            "subcategory":"Auto Supplies",
            "type":"Retail Goods"
        },
        {
            "category":"Retail",
            "subcategory":"Auto Repair",
            "type":"Services"
        }
    ],
    "sg:phone":"+44 113 243 0732",
    "sg:postcode":"LS3 1DF",
    "sg:province":"West Yorkshire",
    "sg:tags":[
        "car",
        "specialist",
        "tyre",
        "customizing"
    ],
    "wof:name":"C & T Tyre Services",
    "wof:placetype":"venue"
},
  "geometry": {"coordinates":[-1.5673569441,53.8041725159],"type":"Point"}
}