{
  "type": "Feature",
  "properties": {
    "addr:full":"Borve, Skeabost Bridge Portree Highland IV51 9PE",
    "addr:postcode":"iv51 9pe",
    "addr:street":"Skeabost Bridge Portree",
    "iso:country":"GB",
    "sg:address":"Borve, Skeabost Bridge",
    "sg:city":"Portree",
    "sg:classifiers":[
        {
            "category":"Bus Charters",
            "type":"Transportation"
        }
    ],
    "sg:phone":"+44 1470 532472",
    "sg:postcode":"IV51 9PE",
    "sg:province":"Highland",
    "sg:tags":[
        "hire",
        "coach"
    ],
    "wof:name":"Nicolson Coach & Plant Services",
    "wof:placetype":"venue"
},
  "geometry": {"coordinates":[-6.1961350441,57.4127845764],"type":"Point"}
}