{
  "type": "Feature",
  "properties": {
    "addr:full":"157 Slateford Rd Edinburgh City of Edinburgh EH14 1PB",
    "addr:housenumber":"157",
    "addr:postcode":"eh14 1pb",
    "addr:street":"Slateford Rd",
    "iso:country":"GB",
    "sg:address":"157 Slateford Rd",
    "sg:city":"Edinburgh",
    "sg:classifiers":[
        {
            "category":"Organizations",
            "subcategory":"Non-profit Organization",
            "type":"Services"
        }
    ],
    "sg:phone":"+44 131 455 8521",
    "sg:postcode":"EH14 1PB",
    "sg:province":"City of Edinburgh",
    "sg:tags":[
        "organisation",
        "voluntary",
        "charity"
    ],
    "wof:name":"Edinburgh Furniture Initiative",
    "wof:placetype":"venue"
},
  "geometry": {"coordinates":[-3.2381339073,55.9311408997],"type":"Point"}
}