{
  "type": "Feature",
  "properties": {
    "iso:country":"GB",
    "sg:address":"16 Commercial Rd",
    "sg:city":"Blackburn",
    "sg:classifiers":[
        {
            "category":"Building & Trades",
            "subcategory":"Construction",
            "type":"Services"
        }
    ],
    "sg:phone":"+44 1254 888181",
    "sg:postcode":"BB6 7HX",
    "sg:province":"Lancashire",
    "sg:tags":[
        "roofing"
    ],
    "wof:name":"Helping Hands Roofing & Fluelining",
    "wof:placetype":"venue"
},
  "geometry": {"coordinates":[-2.409534,53.785675],"type":"Point"}
}