{
  "type": "Feature",
  "properties": {
    "addr:full":"19-23 Grove Road Fareham Hampshire PO16 7TF",
    "addr:housenumber":"19-23",
    "addr:postcode":"po16 7tf",
    "addr:street":"Grove Road",
    "iso:country":"GB",
    "sg:address":"19-23 Grove Road",
    "sg:city":"Fareham",
    "sg:classifiers":[
        {
            "category":"Health Services",
            "subcategory":"Nursing And Care Facility",
            "type":"Services"
        },
        {
            "category":"Social Services",
            "subcategory":"Retirement Home",
            "type":"Services"
        }
    ],
    "sg:phone":"+44 1329 283973",
    "sg:postcode":"PO16 7TF",
    "sg:province":"Hampshire",
    "sg:tags":[
        "residential",
        "agency"
    ],
    "wof:name":"Grove Domiciliary Care Services",
    "wof:placetype":"venue"
},
  "geometry": {"coordinates":[-1.187999,50.853592],"type":"Point"}
}