{
  "type": "Feature",
  "properties": {
    "iso:country":"GB",
    "sg:address":"43 Robey Street",
    "sg:city":"Lincoln",
    "sg:classifiers":[
        {
            "category":"Autos & Motor Vehicles",
            "subcategory":"Automobile Sales",
            "type":"Retail Goods"
        }
    ],
    "sg:phone":"+44 1522 537533",
    "sg:postcode":"LN5 8AT",
    "sg:province":"Lincolnshire",
    "sg:tags":[
        "car"
    ],
    "wof:name":"Dickinson & Ling",
    "wof:placetype":"venue"
},
  "geometry": {"coordinates":[-0.545935,53.218094],"type":"Point"}
}