{
  "type": "Feature",
  "properties": {
    "iso:country":"GB",
    "sg:address":"18 Greengate Street",
    "sg:city":"Stafford",
    "sg:classifiers":[
        {
            "category":"Shopping",
            "subcategory":"Pharmacy",
            "type":"Retail Goods"
        }
    ],
    "sg:phone":"+44 1785 211753",
    "sg:postcode":"ST16 2HS",
    "sg:province":"Staffordshire",
    "sg:tags":[
        "pharmacist",
        "store",
        "drug",
        "chemist"
    ],
    "wof:name":"Superdrug Stores Plc",
    "wof:placetype":"venue"
},
  "geometry": {"coordinates":[-2.1165289879,52.8057594299],"type":"Point"}
}