{
  "type": "Feature",
  "properties": {
    "addr:full":"65 Alltiago Road Swansea Carmarthenshire SA4 8HU",
    "addr:housenumber":"65",
    "addr:postcode":"sa4 8hu",
    "addr:street":"Alltiago Road",
    "iso:country":"GB",
    "sg:address":"65 Alltiago Road",
    "sg:city":"Swansea",
    "sg:classifiers":[
        {
            "category":"Building & Trades",
            "subcategory":"Construction",
            "type":"Services"
        }
    ],
    "sg:postcode":"SA4 8HU",
    "sg:province":"Carmarthenshire",
    "sg:tags":[
        "builder"
    ],
    "wof:name":"Emperor Construction",
    "wof:placetype":"venue"
},
  "geometry": {"coordinates":[-4.032506,51.714039],"type":"Point"}
}