{
  "type": "Feature",
  "properties": {
    "iso:country":"GB",
    "sg:address":"Thermo House, Pegamoid Road",
    "sg:city":"London",
    "sg:classifiers":[
        {
            "category":"Professional",
            "subcategory":"Printing & Photocopies",
            "type":"Services"
        }
    ],
    "sg:postcode":"N18 2PQ",
    "sg:province":"Greater London",
    "sg:tags":[
        "printer"
    ],
    "wof:name":"Foster & Edwards (Printers)",
    "wof:placetype":"venue"
},
  "geometry": {"coordinates":[-0.04864,51.619999],"type":"Point"}
}