{
  "type": "Feature",
  "properties": {
    "addr:full":"Moreton Cottage, Clovelly Road Bideford Devon EX39 3QU",
    "addr:postcode":"ex39 3qu",
    "addr:street":"Clovelly Road",
    "iso:country":"GB",
    "sg:address":"Moreton Cottage, Clovelly Road",
    "sg:city":"Bideford",
    "sg:classifiers":[
        {
            "category":"Building & Trades",
            "subcategory":"Construction",
            "type":"Services"
        }
    ],
    "sg:phone":"+44 1237 476927",
    "sg:postcode":"EX39 3QU",
    "sg:province":"Devon",
    "sg:tags":[
        "builder"
    ],
    "wof:name":"Blight Builders",
    "wof:placetype":"venue"
},
  "geometry": {"coordinates":[-4.2235689163,51.0133781433],"type":"Point"}
}