{
  "type": "Feature",
  "properties": {
    "addr:full":"9 Katharine Street Croydon Surrey CR0 1NX",
    "addr:housenumber":"9",
    "addr:postcode":"cr0 1nx",
    "addr:street":"Katharine Street",
    "iso:country":"GB",
    "sg:address":"9 Katharine Street",
    "sg:city":"Croydon",
    "sg:classifiers":[
        {
            "category":"Health Services",
            "subcategory":"Optometrist",
            "type":"Services"
        }
    ],
    "sg:phone":"+44 20 8686 8282",
    "sg:postcode":"CR0 1NX",
    "sg:province":"Surrey",
    "sg:tags":[
        "optician"
    ],
    "wof:name":"Arthur Hayes Opticians Ltd.",
    "wof:placetype":"venue"
},
  "geometry": {"coordinates":[-0.099446997,51.372215271],"type":"Point"}
}