{
  "type": "Feature",
  "properties": {
    "iso:country":"GB",
    "sg:address":"Greenacres, Broadgreen",
    "sg:city":"Worcester",
    "sg:classifiers":[
        {
            "category":"Professional",
            "type":"Services"
        }
    ],
    "sg:postcode":"WR6 5NW",
    "sg:province":"Herefordshire",
    "sg:tags":[
        "shopfitters"
    ],
    "wof:name":"Blakewood Construction Ltd.",
    "wof:placetype":"venue"
},
  "geometry": {"coordinates":[-2.3811,52.173836],"type":"Point"}
}