{
  "type": "Feature",
  "properties": {
    "addr:full":"Iron Mill Tiverton Devon EX16 9EN",
    "addr:postcode":"ex16 9en",
    "addr:street":"Iron",
    "iso:country":"GB",
    "sg:address":"Iron Mill",
    "sg:city":"Tiverton",
    "sg:classifiers":[
        {
            "category":"Professional",
            "subcategory":"Lawyer & Legal Services",
            "type":"Services"
        }
    ],
    "sg:phone":"+44 1398 351379",
    "sg:postcode":"EX16 9EN",
    "sg:province":"Devon",
    "sg:tags":[
        "advice",
        "counselling"
    ],
    "wof:name":"Iron Mill Centre The",
    "wof:placetype":"venue"
},
  "geometry": {"coordinates":[-3.516078949,50.9902305603],"type":"Point"}
}