{
  "type": "Feature",
  "properties": {
    "iso:country":"GB",
    "sg:address":"Clayhanger Hall, Maw La",
    "sg:city":"Crewe",
    "sg:classifiers":[
        {
            "category":"Farming",
            "subcategory":"Livestock Farm",
            "type":"Manufacturing & Wholesale Goods"
        }
    ],
    "sg:phone":"+44 1270 583952",
    "sg:postcode":"CW1 5SH",
    "sg:province":"Cheshire",
    "sg:tags":[
        "others"
    ],
    "wof:name":"D J Hughes",
    "wof:placetype":"venue"
},
  "geometry": {"coordinates":[-2.409806,53.095119],"type":"Point"}
}