{
  "type": "Feature",
  "properties": {
    "iso:country":"GB",
    "sg:address":"Sunnybrae, Eaglesfield",
    "sg:city":"Lockerbie",
    "sg:classifiers":[
        {
            "category":"Freight",
            "type":"Transportation"
        }
    ],
    "sg:phone":"+44 1461 500392",
    "sg:postcode":"DG11 3NU",
    "sg:province":"Dumfries and Galloway",
    "sg:tags":[
        "haulage",
        "road"
    ],
    "wof:name":"Wrights Transport",
    "wof:placetype":"venue"
},
  "geometry": {"coordinates":[-3.205624,55.056324],"type":"Point"}
}