{
  "type": "Feature",
  "properties": {
    "iso:country":"GB",
    "sg:address":"37 Linden Drive, Lostock Hall",
    "sg:city":"Preston",
    "sg:classifiers":[
        {
            "category":"Shopping",
            "subcategory":"News",
            "type":"Retail Goods"
        }
    ],
    "sg:phone":"+44 1772 336101",
    "sg:postcode":"PR5 5AR",
    "sg:province":"Lancashire",
    "sg:tags":[
        "newsagent"
    ],
    "wof:name":"B Forder",
    "wof:placetype":"venue"
},
  "geometry": {"coordinates":[-2.6872000694,53.7299804688],"type":"Point"}
}