{
  "type": "Feature",
  "properties": {
    "addr:full":"Admin Building, Admin Road Liverpool Lancashire L33 7TX",
    "addr:postcode":"l33 7tx",
    "addr:street":"Admin Road",
    "iso:country":"GB",
    "sg:address":"Admin Building, Admin Road",
    "sg:city":"Liverpool",
    "sg:classifiers":[
        {
            "category":"Building & Trades",
            "subcategory":"Construction",
            "type":"Services"
        }
    ],
    "sg:postcode":"L33 7TX",
    "sg:province":"Lancashire",
    "sg:tags":[
        "roofing"
    ],
    "wof:name":"Fae Cladding Ltd",
    "wof:placetype":"venue"
},
  "geometry": {"coordinates":[-2.8548579216,53.4729270935],"type":"Point"}
}