{
  "type": "Feature",
  "properties": {
    "addr:full":"6 Rye Close, Hatfield Peverel Chelmsford Essex CM3 2LN",
    "addr:housenumber":"6",
    "addr:postcode":"cm3 2ln",
    "addr:street":"Rye Close;Peverel",
    "iso:country":"GB",
    "sg:address":"6 Rye Close, Hatfield Peverel",
    "sg:city":"Chelmsford",
    "sg:classifiers":[
        {
            "category":"Home & Garden",
            "subcategory":"Building Materials",
            "type":"Retail Goods"
        },
        {
            "category":"Building & Trades",
            "subcategory":"Construction",
            "type":"Services"
        }
    ],
    "sg:phone":"+44 1245 380793",
    "sg:postcode":"CM3 2LN",
    "sg:province":"Essex",
    "sg:tags":[
        "fencing",
        "contractor"
    ],
    "wof:name":"C P",
    "wof:placetype":"venue"
},
  "geometry": {"coordinates":[0.5965830088,51.7719192505],"type":"Point"}
}