{
  "type": "Feature",
  "properties": {
    "addr:full":"163 High Street Bromley Kent BR1 1NJ",
    "addr:housenumber":"163",
    "addr:postcode":"br1 1nj",
    "addr:street":"High Street",
    "iso:country":"GB",
    "sg:address":"163 High Street",
    "sg:city":"Bromley",
    "sg:classifiers":[
        {
            "category":"Shopping",
            "subcategory":"Clothing, Apparel, & Fashions",
            "type":"Retail Goods"
        }
    ],
    "sg:postcode":"BR1 1NJ",
    "sg:province":"Kent",
    "sg:tags":[
        "ladieswear"
    ],
    "wof:name":"Grantleigh 2",
    "wof:placetype":"venue"
},
  "geometry": {"coordinates":[0.0148719996,51.4054946899],"type":"Point"}
}