{
  "type": "Feature",
  "properties": {
    "iso:country":"GB",
    "sg:address":"14 Melior Street",
    "sg:city":"London",
    "sg:classifiers":[
        {
            "category":"Place Of Worship",
            "type":"Public Place"
        }
    ],
    "sg:phone":"+44 20 7407 1948",
    "sg:postcode":"SE1 3QP",
    "sg:province":"Greater London",
    "wof:name":"Our Lady of la Salette & St.Josephs",
    "wof:placetype":"venue"
},
  "geometry": {"coordinates":[-0.084977001,51.5028800964],"type":"Point"}
}