{
  "type": "Feature",
  "properties": {
    "iso:country":"GB",
    "sg:address":"11 North Street",
    "sg:city":"Midhurst",
    "sg:classifiers":[
        {
            "category":"Bars & Pubs",
            "type":"Food & Drink"
        }
    ],
    "sg:phone":"+44 1730 817227",
    "sg:postcode":"GU29 9DH",
    "sg:province":"West Sussex",
    "sg:tags":[
        "pubs",
        "inn"
    ],
    "wof:name":"The Silver Horseshoe",
    "wof:placetype":"venue"
},
  "geometry": {"coordinates":[-0.73882,50.987343],"type":"Point"}
}