{
  "type": "Feature",
  "properties": {
    "iso:country":"GB",
    "sg:address":"10 Nightingale Place",
    "sg:city":"Bicester",
    "sg:classifiers":[
        {
            "category":"Bars & Pubs",
            "type":"Food & Drink"
        },
        {
            "category":"Community Center",
            "subcategory":"Social",
            "type":"Public Place"
        }
    ],
    "sg:phone":"+44 1869 369492",
    "sg:postcode":"OX26 6XX",
    "sg:province":"Oxfordshire",
    "sg:tags":[
        "pubs",
        "house",
        "inn",
        "activity"
    ],
    "wof:name":"The Nightingale",
    "wof:placetype":"venue"
},
  "geometry": {"coordinates":[-1.138029,51.891708],"type":"Point"}
}