{
  "type": "Feature",
  "properties": {
    "iso:country":"GB",
    "sg:address":"5-7 Market Pl",
    "sg:city":"Eyemouth",
    "sg:classifiers":[
        {
            "category":"Community Center",
            "subcategory":"Youth",
            "type":"Public Place"
        }
    ],
    "sg:phone":"+44 1890 751560",
    "sg:postcode":"TD14 5HE",
    "sg:province":"Scottish Borders",
    "sg:tags":[
        "organisation",
        "centre"
    ],
    "wof:name":"Dry Dock The",
    "wof:placetype":"venue"
},
  "geometry": {"coordinates":[-2.121085,55.863972],"type":"Point"}
}