{
  "type": "Feature",
  "properties": {
    "iso:country":"GB",
    "sg:address":"64 Torquay Road",
    "sg:city":"Paignton",
    "sg:classifiers":[
        {
            "category":"Home & Garden",
            "subcategory":"Household Appliances",
            "type":"Retail Goods"
        }
    ],
    "sg:phone":"+44 1803 556793",
    "sg:postcode":"TQ3 2SA",
    "sg:province":"Devon",
    "sg:tags":[
        "cleaner",
        "domestic",
        "vacuum"
    ],
    "wof:name":"Sure Vacs",
    "wof:placetype":"venue"
},
  "geometry": {"coordinates":[-3.567555,50.43774],"type":"Point"}
}