{
  "type": "Feature",
  "properties": {
    "iso:country":"GB",
    "sg:address":"Shorts Road",
    "sg:city":"Carshalton",
    "sg:classifiers":[
        {
            "category":"Education",
            "subcategory":"School",
            "type":"Public Place"
        }
    ],
    "sg:phone":"+44 20 8647 4342",
    "sg:postcode":"SM5 2PB",
    "sg:province":"Surrey",
    "sg:tags":[
        "local",
        "authority"
    ],
    "wof:name":"St Mary's R C Junior School",
    "wof:placetype":"venue"
},
  "geometry": {"coordinates":[-0.1708,51.364227],"type":"Point"}
}