{
  "type": "Feature",
  "properties": {
    "iso:country":"GB",
    "sg:address":"Main Street, South Hiendley",
    "sg:city":"Barnsley",
    "sg:classifiers":[
        {
            "category":"Bars & Pubs",
            "type":"Food & Drink"
        }
    ],
    "sg:phone":"+44 1226 711469",
    "sg:postcode":"S72 9BP",
    "sg:province":"South Yorkshire",
    "sg:tags":[
        "pubs",
        "inn"
    ],
    "wof:name":"S H Ward & Co. Ltd.",
    "wof:placetype":"venue"
},
  "geometry": {"coordinates":[-1.4023339748,53.6093406677],"type":"Point"}
}