{
  "type": "Feature",
  "properties": {
    "addr:full":"Rose Cottage, Welford Road, South Kilworth Lutterworth Leicestershire LE17 6DY",
    "addr:postcode":"le17 6dy",
    "addr:street":"Welford Road South",
    "iso:country":"GB",
    "sg:address":"Rose Cottage, Welford Road, South Kilworth",
    "sg:city":"Lutterworth",
    "sg:classifiers":[
        {
            "category":"Building & Trades",
            "subcategory":"Construction",
            "type":"Services"
        }
    ],
    "sg:phone":"+44 1858 575432",
    "sg:postcode":"LE17 6DY",
    "sg:province":"Leicestershire",
    "sg:tags":[
        "joiner",
        "carpenter"
    ],
    "wof:name":"Colin Swinfen",
    "wof:placetype":"venue"
},
  "geometry": {"coordinates":[-1.1119170189,52.431350708],"type":"Point"}
}