{
  "type": "Feature",
  "properties": {
    "addr:full":"Penwerris Lane Falmouth Cornwall TR11 2PF",
    "addr:postcode":"tr11 2pf",
    "addr:street":"Penwerris Lane",
    "iso:country":"GB",
    "sg:address":"Penwerris Lane",
    "sg:city":"Falmouth",
    "sg:classifiers":[
        {
            "category":"Retail",
            "subcategory":"Auto Repair",
            "type":"Services"
        }
    ],
    "sg:phone":"+44 1326 314963",
    "sg:postcode":"TR11 2PF",
    "sg:province":"Cornwall",
    "sg:tags":[
        "body",
        "car"
    ],
    "wof:name":"Falmouth Coachworks Ltd.",
    "wof:placetype":"venue"
},
  "geometry": {"coordinates":[-5.0790681839,50.1627883911],"type":"Point"}
}