{
  "type": "Feature",
  "properties": {
    "addr:full":"116 Chartridge Lane Chesham Buckinghamshire HP5 2RG",
    "addr:housenumber":"116",
    "addr:postcode":"hp5 2rg",
    "addr:street":"Chartridge Lane",
    "iso:country":"GB",
    "sg:address":"116 Chartridge Lane",
    "sg:city":"Chesham",
    "sg:classifiers":[
        {
            "category":"Building & Trades",
            "subcategory":"Landscaping Services",
            "type":"Services"
        }
    ],
    "sg:postcode":"HP5 2RG",
    "sg:province":"Buckinghamshire",
    "sg:tags":[
        "gardening"
    ],
    "wof:name":"Avant Gardens",
    "wof:placetype":"venue"
},
  "geometry": {"coordinates":[-0.624912,51.7113],"type":"Point"}
}