{
  "type": "Feature",
  "properties": {
    "addr:full":"13 Ashcroft Road Newcastle Staffordshire ST5 8EZ",
    "addr:housenumber":"13",
    "addr:postcode":"st5 8ez",
    "addr:street":"Ashcroft Road",
    "iso:country":"GB",
    "sg:address":"13 Ashcroft Road",
    "sg:city":"Newcastle",
    "sg:classifiers":[
        {
            "category":"Personal",
            "type":"Services"
        }
    ],
    "sg:phone":"+44 1782 562452",
    "sg:postcode":"ST5 8EZ",
    "sg:province":"Staffordshire",
    "sg:tags":[
        "tailor"
    ],
    "wof:name":"C H & S R Malpass",
    "wof:placetype":"venue"
},
  "geometry": {"coordinates":[-2.233144,53.03537],"type":"Point"}
}