{
  "type": "Feature",
  "properties": {
    "addr:full":"171 Long Lane Reading Berkshire RG30 6YW",
    "addr:housenumber":"171",
    "addr:postcode":"rg30 6yw",
    "addr:street":"Long Lane",
    "iso:country":"GB",
    "sg:address":"171 Long Lane",
    "sg:city":"Reading",
    "sg:classifiers":[
        {
            "category":"Building & Trades",
            "subcategory":"Plumbing",
            "type":"Services"
        }
    ],
    "sg:phone":"+44 118 945 4308",
    "sg:postcode":"RG30 6YW",
    "sg:province":"Berkshire",
    "sg:tags":[
        "central",
        "heating"
    ],
    "wof:name":"A S A P Highlea",
    "wof:placetype":"venue"
},
  "geometry": {"coordinates":[-1.053976059,51.4691886902],"type":"Point"}
}