{
  "type": "Feature",
  "properties": {
    "addr:full":"Cromwell House, 124-128 Littleton Road Salford Greater Manchester M7 3TW",
    "addr:housenumber":"124-128",
    "addr:postcode":"m7 3tw",
    "addr:street":"Littleton Road",
    "iso:country":"GB",
    "sg:address":"Cromwell House, 124-128 Littleton Road",
    "sg:city":"Salford",
    "sg:classifiers":[
        {
            "category":"Professional",
            "subcategory":"Detective & Security Services",
            "type":"Services"
        },
        {
            "category":"Shopping",
            "subcategory":"Pawn Shop",
            "type":"Retail Goods"
        },
        {
            "category":"Professional",
            "subcategory":"Credit Reporting & Collection",
            "type":"Services"
        }
    ],
    "sg:phone":"+44 161 792 8752",
    "sg:postcode":"M7 3TW",
    "sg:province":"Greater Manchester",
    "sg:tags":[
        "collecting",
        "agency",
        "pawnbroker"
    ],
    "wof:name":"H Bescoby & Co. Ltd.",
    "wof:placetype":"venue"
},
  "geometry": {"coordinates":[-2.278938,53.503529],"type":"Point"}
}