{
  "type": "Feature",
  "properties": {
    "addr:full":"Gloddaeth Cresent Llandudno Conwy LL30 2XS",
    "addr:postcode":"ll30 2xs",
    "addr:street":"Gloddaeth Cresent",
    "iso:country":"GB",
    "sg:address":"Gloddaeth Cresent",
    "sg:city":"Llandudno",
    "sg:classifiers":[
        {
            "category":"Travel",
            "subcategory":"Hotels & Motels",
            "type":"Entertainment"
        }
    ],
    "sg:phone":"+44 1492 876053",
    "sg:postcode":"LL30 2XS",
    "sg:province":"Conwy",
    "wof:name":"Lockyers",
    "wof:placetype":"venue"
},
  "geometry": {"coordinates":[-3.8367540836,53.323425293],"type":"Point"}
}