{
  "type": "Feature",
  "properties": {
    "iso:country":"GB",
    "sg:address":"Unit 3 Gorgie Park Road",
    "sg:city":"Edinburgh",
    "sg:classifiers":[
        {
            "category":"Deli",
            "type":"Food & Drink"
        }
    ],
    "sg:postcode":"EH14 1NL",
    "sg:province":"City of Edinburgh",
    "sg:tags":[
        "delivery",
        "sandwich"
    ],
    "wof:name":"Taylor Made Cuisine",
    "wof:placetype":"venue"
},
  "geometry": {"coordinates":[-3.2366490364,55.9333496094],"type":"Point"}
}