{
  "type": "Feature",
  "properties": {
    "addr:full":"25 Southside Road Inverness Highland IV2 3BG",
    "addr:housenumber":"25",
    "addr:postcode":"iv2 3bg",
    "addr:street":"Southside Road",
    "iso:country":"GB",
    "sg:address":"25 Southside Road",
    "sg:city":"Inverness",
    "sg:classifiers":[
        {
            "category":"Travel",
            "subcategory":"Hotels & Motels",
            "type":"Entertainment"
        }
    ],
    "sg:phone":"+44 1463 234816",
    "sg:postcode":"IV2 3BG",
    "sg:province":"Highland",
    "wof:name":"Crown Court Hotel",
    "wof:placetype":"venue"
},
  "geometry": {"coordinates":[-4.2175459862,57.4733772278],"type":"Point"}
}