{
  "type": "Feature",
  "properties": {
    "addr:full":"Sharman Beer Court Thame Buckinghamshire OX9 2DD",
    "addr:postcode":"ox9 2dd",
    "addr:street":"Court",
    "iso:country":"GB",
    "sg:address":"Sharman Beer Court",
    "sg:city":"Thame",
    "sg:classifiers":[
        {
            "category":"Organizations",
            "subcategory":"Community Association",
            "type":"Services"
        }
    ],
    "sg:phone":"+44 1844 215470",
    "sg:postcode":"OX9 2DD",
    "sg:province":"Buckinghamshire",
    "sg:tags":[
        "society",
        "housing"
    ],
    "wof:name":"Shaftesbury Family Housing Association Ltd.",
    "wof:placetype":"venue"
},
  "geometry": {"coordinates":[-0.980399,51.74543],"type":"Point"}
}