{
  "type": "Feature",
  "properties": {
    "addr:full":"108 John St Sheffield South Yorkshire S2 4QU",
    "addr:housenumber":"108",
    "addr:postcode":"s2 4qu",
    "addr:street":"John St",
    "iso:country":"GB",
    "sg:address":"108 John St",
    "sg:city":"Sheffield",
    "sg:classifiers":[
        {
            "category":"Retail",
            "subcategory":"Auto Repair",
            "type":"Services"
        }
    ],
    "sg:phone":"+44 114 272 9384",
    "sg:postcode":"S2 4QU",
    "sg:province":"South Yorkshire",
    "sg:tags":[
        "car",
        "servicing",
        "radiator"
    ],
    "wof:name":"Serck Marston",
    "wof:placetype":"venue"
},
  "geometry": {"coordinates":[-1.474049,53.370689],"type":"Point"}
}