{
  "type": "Feature",
  "properties": {
    "iso:country":"GB",
    "sg:address":"329 Putney Bridge Rd",
    "sg:city":"Putney",
    "sg:classifiers":[
        {
            "category":"Professional",
            "subcategory":"Employment Agencies",
            "type":"Services"
        }
    ],
    "sg:phone":"+44 20 8918 8300",
    "sg:postcode":"SW15 2PG",
    "sg:province":"Greater London",
    "sg:tags":[
        "consultant"
    ],
    "wof:name":"Employment Service Jobcentre",
    "wof:placetype":"venue"
},
  "geometry": {"coordinates":[-0.214587003,51.4645729065],"type":"Point"}
}