{
  "type": "Feature",
  "properties": {
    "addr:full":"Unit 6 Ironbridge Industrial Estate, Ate Sheffield South Yorkshire S13 9RE",
    "addr:housenumber":"unit 6",
    "addr:postcode":"s13 9re",
    "addr:street":"Ironbridge Industrial Estate;Yorkshire",
    "iso:country":"GB",
    "sg:address":"Unit 6 Ironbridge Industrial Estate, Ate",
    "sg:city":"Sheffield",
    "sg:classifiers":[
        {
            "category":"Food & Beverages",
            "subcategory":"Meat & Fish",
            "type":"Retail Goods"
        }
    ],
    "sg:phone":"+44 114 269 8666",
    "sg:postcode":"S13 9RE",
    "sg:province":"South Yorkshire",
    "sg:tags":[
        "butcher"
    ],
    "wof:name":"RAYMOND & JUNE M WOODHEAD",
    "wof:placetype":"venue"
},
  "geometry": {"coordinates":[-1.4645440578,53.3831100464],"type":"Point"}
}