{
  "type": "Feature",
  "properties": {
    "addr:full":"Ebbw Vale Campus, College Road Ebbw Vale Blaenau Gwent NP23 6LE",
    "addr:postcode":"np23 6le",
    "addr:street":"College Road",
    "iso:country":"GB",
    "sg:address":"Ebbw Vale Campus, College Road",
    "sg:city":"Ebbw Vale",
    "sg:classifiers":[
        {
            "category":"Education",
            "subcategory":"School",
            "type":"Public Place"
        }
    ],
    "sg:phone":"+44 1495 333000",
    "sg:postcode":"NP23 6LE",
    "sg:province":"Blaenau Gwent",
    "sg:tags":[
        "college"
    ],
    "wof:name":"L S Price",
    "wof:placetype":"venue"
},
  "geometry": {"coordinates":[-3.196762,51.757011],"type":"Point"}
}