{
  "type": "Feature",
  "properties": {
    "iso:country":"GB",
    "sg:address":"Vicarage Field, Health Centre, Vicarage Drive",
    "sg:city":"Barking",
    "sg:classifiers":[
        {
            "category":"Health Services",
            "subcategory":"Clinic",
            "type":"Services"
        }
    ],
    "sg:phone":"+44 20 8594 6194",
    "sg:postcode":"IG11 7NR",
    "sg:province":"Essex",
    "sg:tags":[
        "private"
    ],
    "wof:name":"Community Dental Service",
    "wof:placetype":"venue"
},
  "geometry": {"coordinates":[0.081602,51.537037],"type":"Point"}
}