{
  "type": "Feature",
  "properties": {
    "iso:country":"GB",
    "sg:address":"498 Bellhouse Road",
    "sg:city":"Sheffield",
    "sg:classifiers":[
        {
            "category":"Social Services",
            "subcategory":"Retirement Home",
            "type":"Services"
        }
    ],
    "sg:phone":"+44 114 245 6377",
    "sg:postcode":"S5 0RG",
    "sg:province":"South Yorkshire",
    "sg:tags":[
        "residential",
        "care"
    ],
    "wof:name":"Colburn House",
    "wof:placetype":"venue"
},
  "geometry": {"coordinates":[-1.4409359694,53.429851532],"type":"Point"}
}