{
  "type": "Feature",
  "properties": {
    "addr:full":"21 Ysguthan Road Port Talbot Neath Port Talbot SA12 6NB",
    "addr:housenumber":"21",
    "addr:postcode":"sa12 6nb",
    "addr:street":"Ysguthan Road",
    "iso:country":"GB",
    "sg:address":"21 Ysguthan Road",
    "sg:city":"Port Talbot",
    "sg:classifiers":[
        {
            "category":"Fast Food",
            "type":"Food & Drink"
        }
    ],
    "sg:phone":"+44 1639 898563",
    "sg:postcode":"SA12 6NB",
    "sg:province":"Neath Port Talbot",
    "sg:tags":[
        "away",
        "meal",
        "outlet",
        "take"
    ],
    "wof:name":"Aberavon Packed Meals",
    "wof:placetype":"venue"
},
  "geometry": {"coordinates":[-3.795122,51.594131],"type":"Point"}
}