{
  "type": "Feature",
  "properties": {
    "addr:full":"97 Commercial Street Lerwick Shetland Islands ZE1 0BD",
    "addr:housenumber":"97",
    "addr:postcode":"ze1 0bd",
    "addr:street":"Commercial Street;Shetland",
    "iso:country":"GB",
    "sg:address":"97 Commercial Street",
    "sg:city":"Lerwick",
    "sg:classifiers":[
        {
            "category":"Shopping",
            "subcategory":"Clothing, Apparel, & Fashions",
            "type":"Retail Goods"
        }
    ],
    "sg:phone":"+44 1595 695056",
    "sg:postcode":"ZE1 0BD",
    "sg:province":"Shetland Islands",
    "sg:tags":[
        "lingerie",
        "hosiery",
        "ladieswear"
    ],
    "wof:name":"Smiths of Lerwick",
    "wof:placetype":"venue"
},
  "geometry": {"coordinates":[-1.142245,60.153107],"type":"Point"}
}