{
  "type": "Feature",
  "properties": {
    "addr:full":"250 St Vincent St Glasgow Glasgow City G2 5SH",
    "addr:housenumber":"250",
    "addr:postcode":"g2 5sh",
    "addr:street":"St Vincent St",
    "iso:country":"GB",
    "sg:address":"250 St Vincent St",
    "sg:city":"Glasgow",
    "sg:classifiers":[
        {
            "category":"Insurance",
            "subcategory":"Insurance Agent",
            "type":"Services"
        }
    ],
    "sg:phone":"+44 141 226 8877",
    "sg:postcode":"G2 5SH",
    "sg:province":"Glasgow City",
    "wof:name":"Direct Line",
    "wof:placetype":"venue"
},
  "geometry": {"coordinates":[-4.2640891075,55.8624267578],"type":"Point"}
}