{
  "type": "Feature",
  "properties": {
    "iso:country":"GB",
    "sg:address":"45-46 Hay Hill Industrial Estate, Sileby Road",
    "sg:city":"Loughborough",
    "sg:classifiers":[
        {
            "category":"Shopping",
            "subcategory":"Clothing, Apparel, & Fashions",
            "type":"Retail Goods"
        }
    ],
    "sg:phone":"+44 1509 816123",
    "sg:postcode":"LE12 8LD",
    "sg:province":"Leicestershire",
    "sg:tags":[
        "workwear",
        "protective"
    ],
    "wof:name":"Broadweave Ltd.",
    "wof:placetype":"venue"
},
  "geometry": {"coordinates":[-1.12447,52.741859],"type":"Point"}
}