{
  "type": "Feature",
  "properties": {
    "addr:full":"364-366 High St Birmingham West Midlands B17 9PY",
    "addr:housenumber":"364-366",
    "addr:postcode":"b17 9py",
    "addr:street":"High St",
    "iso:country":"GB",
    "sg:address":"364-366 High St",
    "sg:city":"Birmingham",
    "sg:classifiers":[
        {
            "category":"Home & Garden",
            "subcategory":"Furniture",
            "type":"Retail Goods"
        }
    ],
    "sg:postcode":"B17 9PY",
    "sg:province":"West Midlands",
    "wof:name":"Perry,Patricia,",
    "wof:placetype":"venue"
},
  "geometry": {"coordinates":[-1.9572390318,52.4579544067],"type":"Point"}
}