{
  "type": "Feature",
  "properties": {
    "iso:country":"GB",
    "sg:address":"38a Millers Rd",
    "sg:city":"Brighton",
    "sg:classifiers":[
        {
            "category":"Home & Garden",
            "subcategory":"Household Appliances",
            "type":"Retail Goods"
        }
    ],
    "sg:phone":"+44 1273 540404",
    "sg:postcode":"BN1 5NQ",
    "sg:province":"East Sussex",
    "sg:tags":[
        "spare",
        "heating"
    ],
    "wof:name":"Heating Replacement Parts & Controls",
    "wof:placetype":"venue"
},
  "geometry": {"coordinates":[-0.1539160013,50.8400306702],"type":"Point"}
}