{
  "type": "Feature",
  "properties": {
    "addr:full":"289 Walsall Road, Perry Barr Birmingham West Midlands B42 1TY",
    "addr:housenumber":"289",
    "addr:postcode":"b42 1ty",
    "addr:street":"Walsall Road",
    "iso:country":"GB",
    "sg:address":"289 Walsall Road, Perry Barr",
    "sg:city":"Birmingham",
    "sg:classifiers":[
        {
            "category":"Shopping",
            "subcategory":"Bicycles & Sporting Goods",
            "type":"Retail Goods"
        },
        {
            "category":"Sports & Exercise",
            "subcategory":"Sports Center",
            "type":"Entertainment"
        }
    ],
    "sg:phone":"+44 121 356 6090",
    "sg:postcode":"B42 1TY",
    "sg:province":"West Midlands",
    "sg:tags":[
        "shop",
        "sale"
    ],
    "wof:name":"Murrain Sports",
    "wof:placetype":"venue"
},
  "geometry": {"coordinates":[-1.904804945,52.5258865356],"type":"Point"}
}