{
  "type": "Feature",
  "properties": {
    "iso:country":"GB",
    "sg:address":"47 Hungarton Drive, Syston",
    "sg:city":"Leicester",
    "sg:classifiers":[
        {
            "category":"Freight",
            "type":"Transportation"
        }
    ],
    "sg:postcode":"LE7 2AU",
    "sg:province":"Leicestershire",
    "sg:tags":[
        "haulage",
        "road"
    ],
    "wof:name":"Neal Harby Transport",
    "wof:placetype":"venue"
},
  "geometry": {"coordinates":[-1.0663260221,52.6965141296],"type":"Point"}
}