{
  "type": "Feature",
  "properties": {
    "iso:country":"GB",
    "sg:address":"Cardale Park Beckwith Shaw",
    "sg:city":"Harrogate",
    "sg:classifiers":[
        {
            "category":"Shopping",
            "subcategory":"Clothing, Apparel, & Fashions",
            "type":"Retail Goods"
        }
    ],
    "sg:phone":"+44 1423 530530",
    "sg:postcode":"HG3 1RY",
    "sg:province":"North Yorkshire",
    "sg:tags":[
        "clothing",
        "fabric"
    ],
    "wof:name":"Albion Plc",
    "wof:placetype":"venue"
},
  "geometry": {"coordinates":[-1.5797510147,53.9691390991],"type":"Point"}
}