{
  "type": "Feature",
  "properties": {
    "addr:full":"46 Camelsdale Road Haslemere Hampshire GU27 3SQ",
    "addr:housenumber":"46",
    "addr:postcode":"gu27 3sq",
    "addr:street":"Camelsdale Road",
    "iso:country":"GB",
    "sg:address":"46 Camelsdale Road",
    "sg:city":"Haslemere",
    "sg:classifiers":[
        {
            "category":"Professional",
            "subcategory":"Engineering",
            "type":"Services"
        }
    ],
    "sg:phone":"+44 1428 651977",
    "sg:postcode":"GU27 3SQ",
    "sg:province":"Hampshire",
    "sg:tags":[
        "contractor",
        "electrical",
        "engineer"
    ],
    "wof:name":"B J Electrics",
    "wof:placetype":"venue"
},
  "geometry": {"coordinates":[-0.732577,51.081345],"type":"Point"}
}