{
  "type": "Feature",
  "properties": {
    "addr:full":"92 Station Road Liss Hampshire GU33 7AD",
    "addr:housenumber":"92",
    "addr:postcode":"gu33 7ad",
    "addr:street":"Station Road",
    "iso:country":"GB",
    "sg:address":"92 Station Road",
    "sg:city":"Liss",
    "sg:classifiers":[
        {
            "category":"Retail",
            "subcategory":"Auto Repair",
            "type":"Services"
        }
    ],
    "sg:postcode":"GU33 7AD",
    "sg:province":"Hampshire",
    "sg:tags":[
        "modification",
        "garage"
    ],
    "wof:name":"D J Arnold",
    "wof:placetype":"venue"
},
  "geometry": {"coordinates":[-0.894307971,51.0444374084],"type":"Point"}
}