{
  "type": "Feature",
  "properties": {
    "addr:full":"16/19 Market Place Braintree Essex CM7 3HQ",
    "addr:housenumber":"16 / 19",
    "addr:postcode":"cm7 3hq",
    "addr:street":"Market Place",
    "iso:country":"GB",
    "sg:address":"16/19 Market Place",
    "sg:city":"Braintree",
    "sg:classifiers":[
        {
            "category":"Manufacturing",
            "subcategory":"Tools & Machinery",
            "type":"Manufacturing & Wholesale Goods"
        },
        {
            "category":"Insurance",
            "subcategory":"Insurance Agent",
            "type":"Services"
        }
    ],
    "sg:phone":"+44 1376 341414",
    "sg:postcode":"CM7 3HQ",
    "sg:province":"Essex",
    "sg:tags":[
        "society",
        "friendly"
    ],
    "wof:name":"Hill House Hammond Ltd.",
    "wof:placetype":"venue"
},
  "geometry": {"coordinates":[0.5524669886,51.8785209656],"type":"Point"}
}