{
  "type": "Feature",
  "properties": {
    "addr:full":"8 Springwell Court Leeds West Yorkshire LS12 1AL",
    "addr:housenumber":"8",
    "addr:postcode":"ls12 1al",
    "addr:street":"Springwell Court",
    "iso:country":"GB",
    "sg:address":"8 Springwell Court",
    "sg:city":"Leeds",
    "sg:classifiers":[
        {
            "category":"Professional",
            "subcategory":"Printing & Photocopies",
            "type":"Services"
        }
    ],
    "sg:phone":"+44 113 236 3260",
    "sg:postcode":"LS12 1AL",
    "sg:province":"West Yorkshire",
    "sg:tags":[
        "photocopier"
    ],
    "wof:name":"Copyform",
    "wof:placetype":"venue"
},
  "geometry": {"coordinates":[-1.5626820326,53.7905082703],"type":"Point"}
}