{
  "type": "Feature",
  "properties": {
    "addr:full":"187 Buxton Road Stockport Cheshire SK2 7AB",
    "addr:housenumber":"187",
    "addr:postcode":"sk2 7ab",
    "addr:street":"Buxton Road",
    "iso:country":"GB",
    "sg:address":"187 Buxton Road",
    "sg:city":"Stockport",
    "sg:classifiers":[
        {
            "category":"Travel",
            "subcategory":"Hotels & Motels",
            "type":"Entertainment"
        }
    ],
    "sg:phone":"+44 161 483 6172",
    "sg:postcode":"SK2 7AB",
    "sg:province":"Cheshire",
    "wof:name":"ACTON COURT HOTEL LTD",
    "wof:placetype":"venue"
},
  "geometry": {"coordinates":[-2.1442101002,53.3917160034],"type":"Point"}
}