{
  "type": "Feature",
  "properties": {
    "addr:full":"Meridian Leisure Park, Lubbesthorpe Way, Braunstone Leicester Leicestershire LE3 1AH",
    "addr:postcode":"le3 1ah",
    "addr:street":"Park Lubbesthorpe Way",
    "iso:country":"GB",
    "sg:address":"Meridian Leisure Park, Lubbesthorpe Way, Braunstone",
    "sg:city":"Leicester",
    "sg:classifiers":[
        {
            "category":"Cinema",
            "subcategory":"Movie Theater",
            "type":"Entertainment"
        }
    ],
    "sg:phone":"+44 116 282 7722",
    "sg:postcode":"LE3 1AH",
    "sg:province":"Leicestershire",
    "wof:name":"Warner Bros Cinemas",
    "wof:placetype":"venue"
},
  "geometry": {"coordinates":[-1.15916,52.623871],"type":"Point"}
}