{
  "type": "Feature",
  "properties": {
    "addr:full":"White Lane Sheffield Derbyshire S12 3GH",
    "addr:postcode":"s12 3gh",
    "addr:street":"White Lane",
    "iso:country":"GB",
    "sg:address":"White Lane",
    "sg:city":"Sheffield",
    "sg:classifiers":[
        {
            "category":"Health Services",
            "subcategory":"Clinic",
            "type":"Services"
        }
    ],
    "sg:phone":"+44 114 239 9202",
    "sg:postcode":"S12 3GH",
    "sg:province":"Derbyshire",
    "sg:tags":[
        "nh"
    ],
    "wof:name":"White Lane Surgery",
    "wof:placetype":"venue"
},
  "geometry": {"coordinates":[-1.4271589518,53.3446350098],"type":"Point"}
}