{
  "type": "Feature",
  "properties": {
    "addr:full":"10a High Street, Aberlady Longniddry East Lothian EH32 0RB",
    "addr:housenumber":"10a",
    "addr:postcode":"eh32 0rb",
    "addr:street":"High Street;Longniddry",
    "iso:country":"GB",
    "sg:address":"10a High Street, Aberlady",
    "sg:city":"Longniddry",
    "sg:classifiers":[
        {
            "category":"Food & Beverages",
            "subcategory":"Fruits & Vegetables",
            "type":"Retail Goods"
        }
    ],
    "sg:postcode":"EH32 0RB",
    "sg:province":"East Lothian",
    "sg:tags":[
        "greengrocer"
    ],
    "wof:name":"D J H Licensed Grocers",
    "wof:placetype":"venue"
},
  "geometry": {"coordinates":[-2.8622589111,56.0091667175],"type":"Point"}
}