{
  "type": "Feature",
  "properties": {
    "iso:country":"GB",
    "sg:address":"139 Bolling Road",
    "sg:city":"Ilkley",
    "sg:classifiers":[
        {
            "category":"Food & Beverages",
            "subcategory":"Fruits & Vegetables",
            "type":"Retail Goods"
        }
    ],
    "sg:phone":"+44 1943 609091",
    "sg:postcode":"LS29 8PN",
    "sg:province":"North Yorkshire",
    "sg:tags":[
        "greengrocer"
    ],
    "wof:name":"Red Pepper Delhi",
    "wof:placetype":"venue"
},
  "geometry": {"coordinates":[-1.797672987,53.9249191284],"type":"Point"}
}