{
  "type": "Feature",
  "properties": {
    "addr:full":"46 West Street South Molton Devon EX36 4DG",
    "addr:housenumber":"46",
    "addr:postcode":"ex36 4dg",
    "addr:street":"West Street South",
    "iso:country":"GB",
    "sg:address":"46 West Street",
    "sg:city":"South Molton",
    "sg:classifiers":[
        {
            "category":"Building & Trades",
            "subcategory":"Construction",
            "type":"Services"
        }
    ],
    "sg:phone":"+44 1769 572032",
    "sg:postcode":"EX36 4DG",
    "sg:province":"Devon",
    "sg:tags":[
        "builder"
    ],
    "wof:name":"Hulland S H & Sons",
    "wof:placetype":"venue"
},
  "geometry": {"coordinates":[-3.837532,51.018921],"type":"Point"}
}