{
  "type": "Feature",
  "properties": {
    "iso:country":"GB",
    "sg:address":"255a High Street",
    "sg:city":"Birmingham",
    "sg:classifiers":[
        {
            "category":"Home & Garden",
            "subcategory":"Carpets & Floor Coverings",
            "type":"Retail Goods"
        }
    ],
    "sg:postcode":"B23 6SR",
    "sg:province":"West Midlands",
    "sg:tags":[
        "carpets",
        "rug",
        "matting"
    ],
    "wof:name":"G J F Carpets",
    "wof:placetype":"venue"
},
  "geometry": {"coordinates":[-1.842863,52.522346],"type":"Point"}
}