{
  "type": "Feature",
  "properties": {
    "addr:full":"Kelton Shaw, Glencaple Road Dumfries Dumfries and Galloway DG1 4TZ",
    "addr:postcode":"dg1 4tz",
    "addr:street":"Kelton;Glencaple Road",
    "iso:country":"GB",
    "sg:address":"Kelton Shaw, Glencaple Road",
    "sg:city":"Dumfries",
    "sg:classifiers":[
        {
            "category":"Social Services",
            "subcategory":"Job Training",
            "type":"Services"
        }
    ],
    "sg:phone":"+44 1387 259910",
    "sg:postcode":"DG1 4TZ",
    "sg:province":"Dumfries and Galloway",
    "sg:tags":[
        "engineering",
        "marine"
    ],
    "wof:name":"Ian H Livingstone",
    "wof:placetype":"venue"
},
  "geometry": {"coordinates":[-3.573032,55.003132],"type":"Point"}
}