{
  "type": "Feature",
  "properties": {
    "addr:full":"7 Littlestane Row Irvine East Ayrshire KA11 2DJ",
    "addr:housenumber":"7",
    "addr:postcode":"ka11 2dj",
    "addr:street":"Littlestane Row",
    "iso:country":"GB",
    "sg:address":"7 Littlestane Row",
    "sg:city":"Irvine",
    "sg:classifiers":[
        {
            "category":"Building & Trades",
            "subcategory":"Construction",
            "type":"Services"
        }
    ],
    "sg:phone":"+44 1294 217420",
    "sg:postcode":"KA11 2DJ",
    "sg:province":"East Ayrshire",
    "sg:tags":[
        "builder"
    ],
    "wof:name":"Main Page Property Maintenance Management",
    "wof:placetype":"venue"
},
  "geometry": {"coordinates":[-4.636067,55.634109],"type":"Point"}
}