{
  "type": "Feature",
  "properties": {
    "iso:country":"GB",
    "sg:address":"79 Castle Road, Mountsorrel",
    "sg:city":"Loughborough",
    "sg:classifiers":[
        {
            "category":"Social Services",
            "type":"Services"
        }
    ],
    "sg:phone":"+44 116 237 5434",
    "sg:postcode":"LE12 7ET",
    "sg:province":"Leicestershire",
    "sg:tags":[
        "helplines"
    ],
    "wof:name":"Abaco Counselling",
    "wof:placetype":"venue"
},
  "geometry": {"coordinates":[-1.1424729824,52.7174453735],"type":"Point"}
}