{
  "type": "Feature",
  "properties": {
    "iso:country":"GB",
    "sg:address":"4 Westwick Crescent",
    "sg:city":"Sheffield",
    "sg:classifiers":[
        {
            "category":"Shopping",
            "subcategory":"Stationery & Office Supplies",
            "type":"Retail Goods"
        }
    ],
    "sg:postcode":"S8 7DG",
    "sg:province":"Derbyshire",
    "wof:name":"Greenhill Post Office",
    "wof:placetype":"venue"
},
  "geometry": {"coordinates":[-1.488651,53.327469],"type":"Point"}
}