{
  "type": "Feature",
  "properties": {
    "iso:country":"GB",
    "sg:address":"Free Yard, Park Way",
    "sg:city":"Newbury",
    "sg:classifiers":[
        {
            "category":"Shopping",
            "subcategory":"Pets & Pet Supplies",
            "type":"Retail Goods"
        }
    ],
    "sg:phone":"+44 118 981 1971",
    "sg:postcode":"RG14 1EE",
    "sg:province":"Berkshire",
    "wof:name":"Tadley Pet Supplies",
    "wof:placetype":"venue"
},
  "geometry": {"coordinates":[-1.325872,51.405872],"type":"Point"}
}