{
  "type": "Feature",
  "properties": {
    "iso:country":"GB",
    "sg:address":"Sunny View Ho, 40 Newton Rd",
    "sg:city":"Leeds",
    "sg:classifiers":[
        {
            "category":"Professional",
            "subcategory":"Detective & Security Services",
            "type":"Services"
        }
    ],
    "sg:phone":"+44 113 237 4736",
    "sg:postcode":"LS7 4HE",
    "sg:province":"West Yorkshire",
    "wof:name":"Bernies' Secure",
    "wof:placetype":"venue"
},
  "geometry": {"coordinates":[-1.52824,53.821621],"type":"Point"}
}