{
  "type": "Feature",
  "properties": {
    "addr:full":"46-46a Market Place Newark Nottinghamshire NG24 1EG",
    "addr:housenumber":"46-46a",
    "addr:postcode":"ng24 1eg",
    "addr:street":"Market Place",
    "iso:country":"GB",
    "sg:address":"46-46a Market Place",
    "sg:city":"Newark",
    "sg:classifiers":[
        {
            "category":"Shopping",
            "subcategory":"Clothing, Apparel, & Fashions",
            "type":"Retail Goods"
        }
    ],
    "sg:phone":"+44 1636 610355",
    "sg:postcode":"NG24 1EG",
    "sg:province":"Nottinghamshire",
    "sg:tags":[
        "shop",
        "lady",
        "fashionwear",
        "ladieswear"
    ],
    "wof:name":"Bon Marche",
    "wof:placetype":"venue"
},
  "geometry": {"coordinates":[-0.808749,53.07592],"type":"Point"}
}