{
  "type": "Feature",
  "properties": {
    "addr:full":"Millmoor Ground, Masbrough Street Rotherham South Yorkshire S60 1HR",
    "addr:postcode":"s60 1hr",
    "addr:street":"Masbrough Street",
    "iso:country":"GB",
    "sg:address":"Millmoor Ground, Masbrough Street",
    "sg:city":"Rotherham",
    "sg:classifiers":[
        {
            "category":"Arena",
            "subcategory":"Sports Club",
            "type":"Entertainment"
        }
    ],
    "sg:phone":"+44 1709 512434",
    "sg:postcode":"S60 1HR",
    "sg:province":"South Yorkshire",
    "wof:name":"Rotherham United Football Club Ltd.",
    "wof:placetype":"venue"
},
  "geometry": {"coordinates":[-1.3694159985,53.4285392761],"type":"Point"}
}