{
  "type": "Feature",
  "properties": {
    "addr:full":"Wineham Lodge, Wineham Lane, Bolney Haywards Heath East Sussex RH17 5SD",
    "addr:postcode":"rh17 5sd",
    "addr:street":"Wineham Lane",
    "iso:country":"GB",
    "sg:address":"Wineham Lodge, Wineham Lane, Bolney",
    "sg:city":"Haywards Heath",
    "sg:classifiers":[
        {
            "category":"Home & Garden",
            "subcategory":"Home Furnishings",
            "type":"Retail Goods"
        }
    ],
    "sg:phone":"+44 1444 881012",
    "sg:postcode":"RH17 5SD",
    "sg:province":"East Sussex",
    "sg:tags":[
        "mantelpiece",
        "fireplace"
    ],
    "wof:name":"Wealden Building Products Ltd",
    "wof:placetype":"venue"
},
  "geometry": {"coordinates":[-0.2044519931,50.9905815125],"type":"Point"}
}