{
  "type": "Feature",
  "properties": {
    "addr:full":"16 Widley Gardens Waterlooville Hampshire PO7 5RB",
    "addr:housenumber":"16",
    "addr:postcode":"po7 5rb",
    "addr:street":"Widley Gardens",
    "iso:country":"GB",
    "sg:address":"16 Widley Gardens",
    "sg:city":"Waterlooville",
    "sg:classifiers":[
        {
            "category":"Building & Trades",
            "subcategory":"Construction",
            "type":"Services"
        }
    ],
    "sg:phone":"+44 23 9237 6304",
    "sg:postcode":"PO7 5RB",
    "sg:province":"Hampshire",
    "sg:tags":[
        "builder"
    ],
    "wof:name":"D J Legge",
    "wof:placetype":"venue"
},
  "geometry": {"coordinates":[-1.0371810198,50.8602523804],"type":"Point"}
}