{
  "type": "Feature",
  "properties": {
    "addr:full":"82 Russia La, Bethnal Green London Greater London E2 9LU",
    "addr:housenumber":"82",
    "addr:postcode":"e2 9lu",
    "addr:street":"Russia La Bethnal",
    "iso:country":"GB",
    "sg:address":"82 Russia La, Bethnal Green",
    "sg:city":"London",
    "sg:classifiers":[
        {
            "category":"Organizations",
            "subcategory":"Non-profit Organization",
            "type":"Services"
        }
    ],
    "sg:phone":"+44 20 8981 7124",
    "sg:postcode":"E2 9LU",
    "sg:province":"Greater London",
    "sg:tags":[
        "organisation",
        "voluntary",
        "charity"
    ],
    "wof:name":"Age Concern Tower Hamlets",
    "wof:placetype":"venue"
},
  "geometry": {"coordinates":[-0.053035,51.530914],"type":"Point"}
}