{
  "type": "Feature",
  "properties": {
    "addr:full":"34 Friars Square Aylesbury Buckinghamshire HP20 2SP",
    "addr:housenumber":"34",
    "addr:postcode":"hp20 2sp",
    "addr:street":"Friars Square",
    "iso:country":"GB",
    "sg:address":"34 Friars Square",
    "sg:city":"Aylesbury",
    "sg:classifiers":[
        {
            "category":"Shopping",
            "subcategory":"Clothing, Apparel, & Fashions",
            "type":"Retail Goods"
        }
    ],
    "sg:phone":"+44 1296 392298",
    "sg:postcode":"HP20 2SP",
    "sg:province":"Buckinghamshire",
    "sg:tags":[
        "ladieswear"
    ],
    "wof:name":"Select",
    "wof:placetype":"venue"
},
  "geometry": {"coordinates":[-0.811864,51.818779],"type":"Point"}
}