{
  "type": "Feature",
  "properties": {
    "iso:country":"GB",
    "sg:address":"Unit7, Corporation Yard, 2a Harwich Road",
    "sg:city":"Colchester",
    "sg:classifiers":[
        {
            "category":"Retail",
            "subcategory":"Auto Repair",
            "type":"Services"
        }
    ],
    "sg:phone":"+44 1206 794155",
    "sg:postcode":"CO4 3BN",
    "sg:province":"Essex",
    "sg:tags":[
        "body",
        "car",
        "repairer"
    ],
    "wof:name":"Ken Baker Car Repairs",
    "wof:placetype":"venue"
},
  "geometry": {"coordinates":[0.920144,51.890518],"type":"Point"}
}