{
  "type": "Feature",
  "properties": {
    "addr:full":"304 Birchfield Rd, Webheath Redditch Warwickshire B97 4LZ",
    "addr:housenumber":"304",
    "addr:postcode":"b97 4lz",
    "addr:street":"Birchfield Rd",
    "iso:country":"GB",
    "sg:address":"304 Birchfield Rd, Webheath",
    "sg:city":"Redditch",
    "sg:classifiers":[
        {
            "category":"Professional",
            "subcategory":"Accounting & Tax Preparation",
            "type":"Services"
        }
    ],
    "sg:phone":"+44 1527 547644",
    "sg:postcode":"B97 4LZ",
    "sg:province":"Warwickshire",
    "sg:tags":[
        "accountant"
    ],
    "wof:name":"Freeman & Co Accountants",
    "wof:placetype":"venue"
},
  "geometry": {"coordinates":[-1.9649809599,52.2987442017],"type":"Point"}
}