{
  "type": "Feature",
  "properties": {
    "addr:full":"192 High Street Barnet Hertfordshire EN5 5SZ",
    "addr:housenumber":"192",
    "addr:postcode":"en5 5sz",
    "addr:street":"High Street",
    "iso:country":"GB",
    "sg:address":"192 High Street",
    "sg:city":"Barnet",
    "sg:classifiers":[
        {
            "category":"Restaurant",
            "type":"Food & Drink"
        }
    ],
    "sg:phone":"+44 20 8849 8498",
    "sg:postcode":"EN5 5SZ",
    "sg:province":"Hertfordshire",
    "wof:name":"Golden Bird",
    "wof:placetype":"venue"
},
  "geometry": {"coordinates":[-0.2016649991,51.6557121277],"type":"Point"}
}