{
  "type": "Feature",
  "properties": {
    "addr:full":"24 Buckingham Gate Westminster Greater London SW1E 6LB",
    "addr:housenumber":"24",
    "addr:postcode":"sw1e 6lb",
    "addr:street":"Buckingham Gate",
    "iso:country":"GB",
    "sg:address":"24 Buckingham Gate",
    "sg:city":"Westminster",
    "sg:classifiers":[
        {
            "category":"Organizations",
            "subcategory":"Non-profit Organization",
            "type":"Services"
        }
    ],
    "sg:phone":"+44 20 7828 8878",
    "sg:postcode":"SW1E 6LB",
    "sg:province":"Greater London",
    "sg:tags":[
        "organisation",
        "voluntary",
        "charity"
    ],
    "wof:name":"Foundation for Manufacturing",
    "wof:placetype":"venue"
},
  "geometry": {"coordinates":[-0.139607,51.499374],"type":"Point"}
}