{
  "type": "Feature",
  "properties": {
    "addr:full":"Biglis House, Unit 4 & 5 Ty Verlon Industrial Estate, Off Cardiff Road Barry The Vale of Glamorgan CF63 2BE",
    "addr:housenumber":"unit 4 & 5;estate",
    "addr:postcode":"cf63 2be",
    "addr:street":"Ty Verlon Industrial;Off Cardiff Road;Vale",
    "iso:country":"GB",
    "sg:address":"Biglis House, Unit 4 & 5 Ty Verlon Industrial Estate, Off Cardiff Road",
    "sg:city":"Barry",
    "sg:classifiers":[
        {
            "category":"Home & Garden",
            "subcategory":"Building Materials",
            "type":"Retail Goods"
        }
    ],
    "sg:phone":"+44 1446 745544",
    "sg:postcode":"CF63 2BE",
    "sg:province":"The Vale of Glamorgan",
    "sg:tags":[
        "window",
        "frame"
    ],
    "wof:name":"Specialist Sealed Units Ltd.",
    "wof:placetype":"venue"
},
  "geometry": {"coordinates":[-3.23486,51.414989],"type":"Point"}
}