{
  "type": "Feature",
  "properties": {
    "addr:full":"Circuit Ho Holsworthy Cornwall EX22 6RR",
    "addr:postcode":"ex22 6rr",
    "addr:street":"Circuit",
    "iso:country":"GB",
    "sg:address":"Circuit Ho",
    "sg:city":"Holsworthy",
    "sg:classifiers":[
        {
            "category":"Professional",
            "subcategory":"Engineering",
            "type":"Services"
        }
    ],
    "sg:phone":"+44 1409 271431",
    "sg:postcode":"EX22 6RR",
    "sg:province":"Cornwall",
    "sg:tags":[
        "precision",
        "engineer"
    ],
    "wof:name":"Clawton Precision Engineering",
    "wof:placetype":"venue"
},
  "geometry": {"coordinates":[-4.352734,50.810013],"type":"Point"}
}