{
  "type": "Feature",
  "properties": {
    "addr:full":"Unit 2, West Orchards Shopping Centre, Smithford Way Coventry West Midlands CV1 1QX",
    "addr:housenumber":"unit 2",
    "addr:postcode":"cv1 1qx",
    "addr:street":"West;Shopping;Smithford Way",
    "iso:country":"GB",
    "sg:address":"Unit 2, West Orchards Shopping Centre, Smithford Way",
    "sg:city":"Coventry",
    "sg:classifiers":[
        {
            "category":"Shopping",
            "subcategory":"Beauty & Cosmetics",
            "type":"Retail Goods"
        }
    ],
    "sg:phone":"+44 24 7663 3997",
    "sg:postcode":"CV1 1QX",
    "sg:province":"West Midlands",
    "sg:tags":[
        "product"
    ],
    "wof:name":"A M A Dablam Ltd.",
    "wof:placetype":"venue"
},
  "geometry": {"coordinates":[-1.5111839771,52.411075592],"type":"Point"}
}