{
  "type": "Feature",
  "properties": {
    "addr:full":"Unit 1/7, Rowleys Green Industrial Estate, Rowleys Green Lane Coventry Warwickshire CV6 6AN",
    "addr:housenumber":"unit 1 / 7;estate",
    "addr:postcode":"cv6 6an",
    "addr:street":"Rowleys Green Industrial;Rowleys Green Lane",
    "iso:country":"GB",
    "sg:address":"Unit 1/7, Rowleys Green Industrial Estate, Rowleys Green Lane",
    "sg:city":"Coventry",
    "sg:classifiers":[
        {
            "category":"Professional",
            "subcategory":"Engineering",
            "type":"Services"
        }
    ],
    "sg:phone":"+44 121 683 6200",
    "sg:postcode":"CV6 6AN",
    "sg:province":"Warwickshire",
    "sg:tags":[
        "precision",
        "engineer"
    ],
    "wof:name":"Avionic Components Ltd.",
    "wof:placetype":"venue"
},
  "geometry": {"coordinates":[-1.496199,52.451199],"type":"Point"}
}