{
  "type": "Feature",
  "properties": {
    "iso:country":"GB",
    "sg:address":"121 High Street",
    "sg:city":"Stevenage",
    "sg:classifiers":[
        {
            "category":"Fast Food",
            "type":"Food & Drink"
        }
    ],
    "sg:phone":"+44 1438 352644",
    "sg:postcode":"SG1 3HS",
    "sg:province":"Hertfordshire",
    "sg:tags":[
        "away",
        "take"
    ],
    "wof:name":"Sam-Pan Chinese Food",
    "wof:placetype":"venue"
},
  "geometry": {"coordinates":[-0.2073220015,51.9102706909],"type":"Point"}
}