{
  "type": "Feature",
  "properties": {
    "iso:country":"GB",
    "sg:address":"13 Moray Street",
    "sg:city":"Wick",
    "sg:classifiers":[
        {
            "category":"Home & Garden",
            "subcategory":"Carpets & Floor Coverings",
            "type":"Retail Goods"
        }
    ],
    "sg:phone":"+44 1955 604548",
    "sg:postcode":"KW1 5QF",
    "sg:province":"Highland",
    "sg:tags":[
        "textile",
        "floorcoverings"
    ],
    "wof:name":"Murray Anderson Floor Coverings",
    "wof:placetype":"venue"
},
  "geometry": {"coordinates":[-3.0937430859,58.4383621216],"type":"Point"}
}