{
  "type": "Feature",
  "properties": {
    "addr:full":"Longdon House, 1588a High St, Knowle Solihull Warwickshire B93 0LF",
    "addr:housenumber":"longdon;1588a",
    "addr:postcode":"b93 0lf",
    "addr:street":"High St",
    "iso:country":"GB",
    "sg:address":"Longdon House, 1588a High St, Knowle",
    "sg:city":"Solihull",
    "sg:classifiers":[
        {
            "category":"Professional",
            "subcategory":"Lawyer & Legal Services",
            "type":"Services"
        }
    ],
    "sg:phone":"+44 1564 777359",
    "sg:postcode":"B93 0LF",
    "sg:province":"Warwickshire",
    "sg:tags":[
        "solicitor"
    ],
    "wof:name":"Compensation Claims Service",
    "wof:placetype":"venue"
},
  "geometry": {"coordinates":[-1.736011982,52.3898658752],"type":"Point"}
}