{
  "type": "Feature",
  "properties": {
    "addr:full":"Station Road, Wilburton Ely Cambridgeshire CB6 3RR",
    "addr:postcode":"cb6 3rr",
    "addr:street":"Station Road",
    "iso:country":"GB",
    "sg:address":"Station Road, Wilburton",
    "sg:city":"Ely",
    "sg:classifiers":[
        {
            "category":"Education",
            "subcategory":"Special Training",
            "type":"Public Place"
        },
        {
            "category":"Education",
            "subcategory":"School",
            "type":"Public Place"
        }
    ],
    "sg:phone":"+44 1353 740229",
    "sg:postcode":"CB6 3RR",
    "sg:province":"Cambridgeshire",
    "wof:name":"The Manor Special School",
    "wof:placetype":"venue"
},
  "geometry": {"coordinates":[0.1792600006,52.3552513123],"type":"Point"}
}