{
  "type": "Feature",
  "properties": {
    "addr:full":"Rosemarie, Sorrell Lane, Foster Houses Doncaster South Yorkshire DN7 5LG",
    "addr:postcode":"dn7 5lg",
    "addr:street":"Sorrell Lane",
    "iso:country":"GB",
    "sg:address":"Rosemarie, Sorrell Lane, Foster Houses",
    "sg:city":"Doncaster",
    "sg:classifiers":[
        {
            "category":"Transit Center",
            "subcategory":"Passenger",
            "type":"Transportation"
        }
    ],
    "sg:phone":"+44 1302 843416",
    "sg:postcode":"DN7 5LG",
    "sg:province":"South Yorkshire",
    "sg:tags":[
        "boarding",
        "kennel",
        "catteries"
    ],
    "wof:name":"Trade Fencing Supplies",
    "wof:placetype":"venue"
},
  "geometry": {"coordinates":[-1.01195,53.625191],"type":"Point"}
}