{
  "type": "Feature",
  "properties": {
    "iso:country":"GB",
    "sg:address":"Nettlebed Farm, Old Alresford",
    "sg:city":"Alresford",
    "sg:classifiers":[
        {
            "category":"Building & Trades",
            "subcategory":"Construction",
            "type":"Services"
        }
    ],
    "sg:phone":"+44 1962 732147",
    "sg:postcode":"SO24 9RF",
    "sg:province":"Hampshire",
    "sg:tags":[
        "builder"
    ],
    "wof:name":"A M Short Ltd.",
    "wof:placetype":"venue"
},
  "geometry": {"coordinates":[-1.162316,51.102249],"type":"Point"}
}