{
  "type": "Feature",
  "properties": {
    "iso:country":"GB",
    "sg:address":"14 Woodham Lane, New Haw",
    "sg:city":"Addlestone",
    "sg:classifiers":[
        {
            "category":"Professional",
            "subcategory":"Engineering",
            "type":"Services"
        }
    ],
    "sg:phone":"+44 1932 849336",
    "sg:postcode":"KT15 3NA",
    "sg:province":"Surrey",
    "sg:tags":[
        "contractor",
        "electrical",
        "engineer"
    ],
    "wof:name":"Bestelec 87",
    "wof:placetype":"venue"
},
  "geometry": {"coordinates":[-0.487193,51.356705],"type":"Point"}
}