{
  "type": "Feature",
  "properties": {
    "addr:full":"Chapel Farm Keswick Cumbria CA12 4QH",
    "addr:postcode":"ca12 4qh",
    "iso:country":"GB",
    "sg:address":"Chapel Farm",
    "sg:city":"Keswick",
    "sg:classifiers":[
        {
            "category":"Farming",
            "subcategory":"Farm",
            "type":"Manufacturing & Wholesale Goods"
        }
    ],
    "sg:phone":"+44 17687 76495",
    "sg:postcode":"CA12 4QH",
    "sg:province":"Cumbria",
    "sg:tags":[
        "mixed",
        "crop"
    ],
    "wof:name":"W W Fell",
    "wof:placetype":"venue"
},
  "geometry": {"coordinates":[-3.1389639378,54.6017303467],"type":"Point"}
}