{
  "type": "Feature",
  "properties": {
    "iso:country":"GB",
    "sg:address":"Suite 6, 2nd Floor 93 Hartington Rd",
    "sg:city":"Stockton On Tees",
    "sg:classifiers":[
        {
            "category":"Professional",
            "subcategory":"Employment Agencies",
            "type":"Services"
        }
    ],
    "sg:phone":"+44 1642 884605",
    "sg:postcode":"TS18 1HD",
    "sg:province":"Durham",
    "sg:tags":[
        "consultant"
    ],
    "wof:name":"Resolve Recruitment",
    "wof:placetype":"venue"
},
  "geometry": {"coordinates":[-1.3174339533,54.5612792969],"type":"Point"}
}