{
  "type": "Feature",
  "properties": {
    "iso:country":"GB",
    "sg:address":"5 Barton Close",
    "sg:city":"Plymouth",
    "sg:classifiers":[
        {
            "category":"Building & Trades",
            "subcategory":"Plumbing",
            "type":"Services"
        }
    ],
    "sg:postcode":"PL9 0LF",
    "sg:province":"Devon",
    "sg:tags":[
        "heating"
    ],
    "wof:name":"J Betts Plumbing",
    "wof:placetype":"venue"
},
  "geometry": {"coordinates":[-4.070478,50.326618],"type":"Point"}
}