{
  "type": "Feature",
  "properties": {
    "iso:country":"GB",
    "sg:address":"86 High Street",
    "sg:city":"Oldham",
    "sg:classifiers":[
        {
            "category":"Fast Food",
            "type":"Food & Drink"
        }
    ],
    "sg:phone":"+44 161 628 0400",
    "sg:postcode":"OL4 5AA",
    "sg:province":"Lancashire",
    "sg:tags":[
        "away",
        "take"
    ],
    "wof:name":"The Balti Taste",
    "wof:placetype":"venue"
},
  "geometry": {"coordinates":[-2.070919,53.537621],"type":"Point"}
}