{
  "type": "Feature",
  "properties": {
    "addr:full":"South West Regional Business Cen Bristol City of Bristol BS1 4AE",
    "addr:postcode":"bs1 4ae",
    "iso:country":"GB",
    "sg:address":"South West Regional Business Cen",
    "sg:city":"Bristol",
    "sg:classifiers":[
        {
            "category":"Banks & Credit Unions",
            "subcategory":"Bank",
            "type":"Services"
        }
    ],
    "sg:phone":"+44 117 973 2462",
    "sg:postcode":"BS1 4AE",
    "sg:province":"City of Bristol",
    "wof:name":"U C B Corporate Services Ltd.",
    "wof:placetype":"venue"
},
  "geometry": {"coordinates":[-2.5914289951,51.453666687],"type":"Point"}
}