{
  "type": "Feature",
  "properties": {
    "addr:full":"2 Rouse St Liversedge West Yorkshire WF15 6LG",
    "addr:housenumber":"2",
    "addr:postcode":"wf15 6lg",
    "addr:street":"Rouse St",
    "iso:country":"GB",
    "sg:address":"2 Rouse St",
    "sg:city":"Liversedge",
    "sg:classifiers":[
        {
            "category":"Home & Garden",
            "subcategory":"Building Materials",
            "type":"Retail Goods"
        }
    ],
    "sg:postcode":"WF15 6LG",
    "sg:province":"West Yorkshire",
    "sg:tags":[
        "ironwork",
        "diy",
        "wrought"
    ],
    "wof:name":"Beltham,Colin,",
    "wof:placetype":"venue"
},
  "geometry": {"coordinates":[-1.6936320066,53.7103996277],"type":"Point"}
}