{
  "type": "Feature",
  "properties": {
    "iso:country":"GB",
    "sg:address":"Heath Pig Unit Heath Farm, Normanby By Spital",
    "sg:city":"Lincoln",
    "sg:classifiers":[
        {
            "category":"Farming",
            "subcategory":"Livestock Farm",
            "type":"Manufacturing & Wholesale Goods"
        }
    ],
    "sg:phone":"+44 1673 878324",
    "sg:postcode":"LN2 3HE",
    "sg:province":"Lincolnshire",
    "sg:tags":[
        "others"
    ],
    "wof:name":"Ermine Farms Ltd.",
    "wof:placetype":"venue"
},
  "geometry": {"coordinates":[-0.4901300073,53.316078186],"type":"Point"}
}