{
  "type": "Feature",
  "properties": {
    "iso:country":"GB",
    "sg:address":"Brierley Rd",
    "sg:city":"Barnsley",
    "sg:classifiers":[
        {
            "category":"Place Of Worship",
            "type":"Public Place"
        }
    ],
    "sg:phone":"+44 1226 711377",
    "sg:postcode":"S72 9JQ",
    "sg:province":"South Yorkshire",
    "wof:name":"St Pauls Church",
    "wof:placetype":"venue"
},
  "geometry": {"coordinates":[-1.3820149899,53.5947761536],"type":"Point"}
}