{
  "type": "Feature",
  "properties": {
    "addr:full":"Grainger Ho, 528 Fulham Rd London Greater London SW6 5NR",
    "addr:housenumber":"528",
    "addr:postcode":"sw6 5nr",
    "addr:street":"Fulham Rd",
    "iso:country":"GB",
    "sg:address":"Grainger Ho, 528 Fulham Rd",
    "sg:city":"London",
    "sg:classifiers":[
        {
            "category":"Real Estate",
            "subcategory":"Real Estate Agent",
            "type":"Services"
        }
    ],
    "sg:postcode":"SW6 5NR",
    "sg:province":"Greater London",
    "wof:name":"N & D London Ltd",
    "wof:placetype":"venue"
},
  "geometry": {"coordinates":[-0.201511,51.477642],"type":"Point"}
}