{
  "type": "Feature",
  "properties": {
    "addr:full":"Appulcombe, Guildford Road Guildford Surrey GU3 2AR",
    "addr:postcode":"gu3 2ar",
    "addr:street":"Guildford Road",
    "iso:country":"GB",
    "sg:address":"Appulcombe, Guildford Road",
    "sg:city":"Guildford",
    "sg:classifiers":[
        {
            "category":"Professional",
            "subcategory":"Accounting & Tax Preparation",
            "type":"Services"
        }
    ],
    "sg:postcode":"GU3 2AR",
    "sg:province":"Surrey",
    "sg:tags":[
        "accountant"
    ],
    "wof:name":"Haley Asquith",
    "wof:placetype":"venue"
},
  "geometry": {"coordinates":[-0.6650800109,51.2572212219],"type":"Point"}
}