{
  "type": "Feature",
  "properties": {
    "addr:full":"21 Blackmoor Road, Ebblake Industrial Estate Verwood Dorset BH31 6AX",
    "addr:housenumber":"21",
    "addr:postcode":"bh31 6ax",
    "addr:street":"Blackmoor Road Ebblake Industrial Estate",
    "iso:country":"GB",
    "sg:address":"21 Blackmoor Road, Ebblake Industrial Estate",
    "sg:city":"Verwood",
    "sg:classifiers":[
        {
            "category":"Manufacturing",
            "subcategory":"Wood Products",
            "type":"Manufacturing & Wholesale Goods"
        }
    ],
    "sg:postcode":"BH31 6AX",
    "sg:province":"Dorset",
    "sg:tags":[
        "woodturning"
    ],
    "wof:name":"Briggs Trading Co. (Southern) Ltd.",
    "wof:placetype":"venue"
},
  "geometry": {"coordinates":[-1.8531819582,50.8688430786],"type":"Point"}
}