{
  "type": "Feature",
  "properties": {
    "addr:full":"10 Melbourne Avenue, Winnersh Wokingham Berkshire RG41 5EL",
    "addr:housenumber":"10",
    "addr:postcode":"rg41 5el",
    "addr:street":"Melbourne Avenue",
    "iso:country":"GB",
    "sg:address":"10 Melbourne Avenue, Winnersh",
    "sg:city":"Wokingham",
    "sg:classifiers":[
        {
            "category":"Health Services",
            "subcategory":"Doctor",
            "type":"Services"
        },
        {
            "category":"Health Services",
            "subcategory":"Clinic",
            "type":"Services"
        }
    ],
    "sg:phone":"+44 118 979 2111",
    "sg:postcode":"RG41 5EL",
    "sg:province":"Berkshire",
    "sg:tags":[
        "nh",
        "practitioners"
    ],
    "wof:name":"Winnersh Surgery",
    "wof:placetype":"venue"
},
  "geometry": {"coordinates":[-0.874497,51.426922],"type":"Point"}
}