{
  "type": "Feature",
  "properties": {
    "addr:full":"89 Park Street Salisbury Wiltshire SP1 3AT",
    "addr:housenumber":"89",
    "addr:postcode":"sp1 3at",
    "addr:street":"Park Street",
    "iso:country":"GB",
    "sg:address":"89 Park Street",
    "sg:city":"Salisbury",
    "sg:classifiers":[
        {
            "category":"Home & Garden",
            "subcategory":"Household Appliances",
            "type":"Retail Goods"
        }
    ],
    "sg:postcode":"SP1 3AT",
    "sg:province":"Wiltshire",
    "sg:tags":[
        "electrical"
    ],
    "wof:name":"Darren",
    "wof:placetype":"venue"
},
  "geometry": {"coordinates":[-1.7903939486,51.0741233826],"type":"Point"}
}