{
  "type": "Feature",
  "properties": {
    "iso:country":"GB",
    "sg:address":"Ashburton, Copes Road, Great Kingshill",
    "sg:city":"High Wycombe",
    "sg:classifiers":[
        {
            "category":"Building & Trades",
            "subcategory":"Construction",
            "type":"Services"
        }
    ],
    "sg:phone":"+44 1494 713829",
    "sg:postcode":"HP15 6JE",
    "sg:province":"Buckinghamshire",
    "sg:tags":[
        "joiner",
        "carpenter"
    ],
    "wof:name":"David Palmer",
    "wof:placetype":"venue"
},
  "geometry": {"coordinates":[-0.732474,51.671333],"type":"Point"}
}