{
  "type": "Feature",
  "properties": {
    "addr:full":"5 Skye Drive, Ravenswood, Cumbernauld Glasgow Falkirk G67 1NY",
    "addr:housenumber":"5",
    "addr:postcode":"g67 1ny",
    "addr:street":"Skye Drive",
    "iso:country":"GB",
    "sg:address":"5 Skye Drive, Ravenswood, Cumbernauld",
    "sg:city":"Glasgow",
    "sg:classifiers":[
        {
            "category":"Bus Stop",
            "subcategory":"None",
            "type":"Transportation"
        }
    ],
    "sg:phone":"+44 1236 738096",
    "sg:postcode":"G67 1NY",
    "sg:province":"Falkirk",
    "sg:tags":[
        "seal"
    ],
    "wof:name":"Chris Brown Sealants",
    "wof:placetype":"venue"
},
  "geometry": {"coordinates":[-4.005457,55.940945],"type":"Point"}
}