{
  "type": "Feature",
  "properties": {
    "addr:full":"Masters House, Lewes Road, Lindfield Haywards Heath East Sussex RH16 2LE",
    "addr:postcode":"rh16 2le",
    "addr:street":"Lewes Road",
    "iso:country":"GB",
    "sg:address":"Masters House, Lewes Road, Lindfield",
    "sg:city":"Haywards Heath",
    "sg:classifiers":[
        {
            "category":"Retail",
            "subcategory":"Funeral Services",
            "type":"Services"
        }
    ],
    "sg:phone":"+44 1444 482107",
    "sg:postcode":"RH16 2LE",
    "sg:province":"East Sussex",
    "sg:tags":[
        "director"
    ],
    "wof:name":"Masters & Son Lindfield Ltd",
    "wof:placetype":"venue"
},
  "geometry": {"coordinates":[-0.080877997,51.0116424561],"type":"Point"}
}