{
  "type": "Feature",
  "properties": {
    "addr:full":"Park Works, Belle-eau Park, Bilsthorpe Newark Nottinghamshire NG22 8TX",
    "addr:postcode":"ng22 8tx",
    "addr:street":"Park;Belle-Eau",
    "iso:country":"GB",
    "sg:address":"Park Works, Belle-eau Park, Bilsthorpe",
    "sg:city":"Newark",
    "sg:classifiers":[
        {
            "category":"Professional",
            "subcategory":"Engineering",
            "type":"Services"
        }
    ],
    "sg:postcode":"NG22 8TX",
    "sg:province":"Nottinghamshire",
    "wof:name":"Corbett Haynes Engineering Ltd.",
    "wof:placetype":"venue"
},
  "geometry": {"coordinates":[-1.0280840397,53.1300354004],"type":"Point"}
}