{
  "type": "Feature",
  "properties": {
    "addr:full":"58 Fore Street Bodmin Cornwall PL31 2HR",
    "addr:housenumber":"58",
    "addr:postcode":"pl31 2hr",
    "addr:street":"Fore Street",
    "iso:country":"GB",
    "sg:address":"58 Fore Street",
    "sg:city":"Bodmin",
    "sg:classifiers":[
        {
            "category":"Shopping",
            "subcategory":"Music",
            "type":"Retail Goods"
        }
    ],
    "sg:phone":"+44 1208 78722",
    "sg:postcode":"PL31 2HR",
    "sg:province":"Cornwall",
    "sg:tags":[
        "record",
        "tape",
        "cd"
    ],
    "wof:name":"Shelly Semmens",
    "wof:placetype":"venue"
},
  "geometry": {"coordinates":[-4.7218008041,50.4711074829],"type":"Point"}
}