{
  "type": "Feature",
  "properties": {
    "iso:country":"GB",
    "sg:address":"Unit 11 Victoria Industrial Estate, Victoria Street",
    "sg:city":"Leigh",
    "sg:classifiers":[
        {
            "category":"Building & Trades",
            "subcategory":"Construction",
            "type":"Services"
        }
    ],
    "sg:phone":"+44 1942 683282",
    "sg:postcode":"WN7 5SE",
    "sg:province":"Lancashire",
    "sg:tags":[
        "ceiling",
        "contractor"
    ],
    "wof:name":"Marton Contractors",
    "wof:placetype":"venue"
},
  "geometry": {"coordinates":[-2.5248599052,53.5044517517],"type":"Point"}
}