{
  "type": "Feature",
  "properties": {
    "addr:full":"83 King St Kilmarnock East Ayrshire KA1 1QD",
    "addr:housenumber":"83",
    "addr:postcode":"ka1 1qd",
    "addr:street":"King St",
    "iso:country":"GB",
    "sg:address":"83 King St",
    "sg:city":"Kilmarnock",
    "sg:classifiers":[
        {
            "category":"Food & Beverages",
            "subcategory":"Candy",
            "type":"Retail Goods"
        }
    ],
    "sg:phone":"+44 1563 534611",
    "sg:postcode":"KA1 1QD",
    "sg:province":"East Ayrshire",
    "sg:tags":[
        "confectioner"
    ],
    "wof:name":"Kilmarnock News Box The",
    "wof:placetype":"venue"
},
  "geometry": {"coordinates":[-4.497101,55.608353],"type":"Point"}
}