{
  "type": "Feature",
  "properties": {
    "iso:country":"GB",
    "sg:address":"44 St Thomas Drive, Hatch End",
    "sg:city":"Pinner",
    "sg:classifiers":[
        {
            "category":"Bus Charters",
            "type":"Transportation"
        }
    ],
    "sg:phone":"+44 20 8421 4601",
    "sg:postcode":"HA5 4SS",
    "sg:province":"Greater London",
    "sg:tags":[
        "hire",
        "coach"
    ],
    "wof:name":"D & J Coaches of Harrow",
    "wof:placetype":"venue"
},
  "geometry": {"coordinates":[-0.3764,51.603374],"type":"Point"}
}