{
  "type": "Feature",
  "properties": {
    "iso:country":"GB",
    "sg:address":"Mill Reef House, 9-15 Cheap Street",
    "sg:city":"Newbury",
    "sg:classifiers":[
        {
            "category":"Professional",
            "subcategory":"Computer Services",
            "type":"Services"
        }
    ],
    "sg:phone":"+44 1635 32741",
    "sg:postcode":"RG14 5DD",
    "sg:province":"Berkshire",
    "sg:tags":[
        "system",
        "software"
    ],
    "wof:name":"Infodata Systems Ltd.",
    "wof:placetype":"venue"
},
  "geometry": {"coordinates":[-1.321999,51.399029],"type":"Point"}
}