{
  "type": "Feature",
  "properties": {
    "addr:full":"1a The Walks East Huntingdon Cambridgeshire PE29 3AP",
    "addr:housenumber":"1a",
    "addr:postcode":"pe29 3ap",
    "addr:street":"The Walks East Huntingdon",
    "iso:country":"GB",
    "sg:address":"1a The Walks East",
    "sg:city":"Huntingdon",
    "sg:classifiers":[
        {
            "category":"Professional",
            "subcategory":"Employment Agencies",
            "type":"Services"
        }
    ],
    "sg:postcode":"PE29 3AP",
    "sg:province":"Cambridgeshire",
    "sg:tags":[
        "agricultural",
        "advice"
    ],
    "wof:name":"Burt Research Ltd",
    "wof:placetype":"venue"
},
  "geometry": {"coordinates":[-0.1835470051,52.3277626038],"type":"Point"}
}