{
  "type": "Feature",
  "properties": {
    "iso:country":"GB",
    "sg:address":"18-22 Birch Road East, Wyrley Trading Estate, Witton",
    "sg:city":"Birmingham",
    "sg:classifiers":[
        {
            "category":"Wholesale",
            "subcategory":"Metals & Minerals",
            "type":"Manufacturing & Wholesale Goods"
        }
    ],
    "sg:phone":"+44 121 328 7700",
    "sg:postcode":"B6 7DB",
    "sg:province":"West Midlands",
    "sg:tags":[
        "aluminium",
        "stockholder"
    ],
    "wof:name":"Aquarius Metals Ltd.",
    "wof:placetype":"venue"
},
  "geometry": {"coordinates":[-1.876469,52.51717],"type":"Point"}
}