{
  "type": "Feature",
  "properties": {
    "addr:full":"Stream Street Mountain Ash Rhondda, Cynon, Taff CF45 3LL",
    "addr:postcode":"cf45 3ll",
    "addr:street":"Stream Street;Cynon Taff",
    "iso:country":"GB",
    "sg:address":"Stream Street",
    "sg:city":"Mountain Ash",
    "sg:classifiers":[
        {
            "category":"Manufacturing",
            "subcategory":"Glass & Minerals",
            "type":"Manufacturing & Wholesale Goods"
        }
    ],
    "sg:postcode":"CF45 3LL",
    "sg:province":"Rhondda, Cynon, Taff",
    "sg:tags":[
        "glassworker"
    ],
    "wof:name":"Delyn Glass",
    "wof:placetype":"venue"
},
  "geometry": {"coordinates":[-3.3810939789,51.680683136],"type":"Point"}
}