{
  "type": "Feature",
  "properties": {
    "addr:full":"1 High Street West Wickham Kent BR4 0LP",
    "addr:housenumber":"1",
    "addr:postcode":"br4 0lp",
    "addr:street":"High Street",
    "iso:country":"GB",
    "sg:address":"1 High Street",
    "sg:city":"West Wickham",
    "sg:classifiers":[
        {
            "category":"Real Estate",
            "subcategory":"Real Estate Agent",
            "type":"Services"
        }
    ],
    "sg:phone":"+44 20 8289 3333",
    "sg:postcode":"BR4 0LP",
    "sg:province":"Kent",
    "wof:name":"Alan De Maid",
    "wof:placetype":"venue"
},
  "geometry": {"coordinates":[-0.0148609998,51.3757019043],"type":"Point"}
}