{
  "type": "Feature",
  "properties": {
    "addr:full":"Godswell Natural Therapy Centre, Godswell Lodge, Church Street Bicester Oxfordshire OX15 4ES",
    "addr:postcode":"ox15 4es",
    "addr:street":"Church Street",
    "iso:country":"GB",
    "sg:address":"Godswell Natural Therapy Centre, Godswell Lodge, Church Street",
    "sg:city":"Bicester",
    "sg:classifiers":[
        {
            "category":"Health Services",
            "subcategory":"Health Practitioner",
            "type":"Services"
        }
    ],
    "sg:phone":"+44 1865 331681",
    "sg:postcode":"OX15 4ES",
    "sg:province":"Oxfordshire",
    "sg:tags":[
        "homoeopathic"
    ],
    "wof:name":"Juliet L Smith",
    "wof:placetype":"venue"
},
  "geometry": {"coordinates":[-1.3750400543,52.0186080933],"type":"Point"}
}