{
  "type": "Feature",
  "properties": {
    "addr:full":"Patton Grange, Bourton Much Wenlock Shropshire TF13 6JW",
    "addr:postcode":"tf13 6jw",
    "addr:street":"Wenlock",
    "iso:country":"GB",
    "sg:address":"Patton Grange, Bourton",
    "sg:city":"Much Wenlock",
    "sg:classifiers":[
        {
            "category":"Farming",
            "subcategory":"Farm",
            "type":"Manufacturing & Wholesale Goods"
        }
    ],
    "sg:postcode":"TF13 6JW",
    "sg:province":"Shropshire",
    "sg:tags":[
        "mixed",
        "crop"
    ],
    "wof:name":"D E Wadlow",
    "wof:placetype":"venue"
},
  "geometry": {"coordinates":[-2.559925,52.594009],"type":"Point"}
}