{
  "type": "Feature",
  "properties": {
    "iso:country":"GB",
    "sg:address":"23 York St",
    "sg:city":"Stourport-on-severn",
    "sg:classifiers":[
        {
            "category":"Professional",
            "subcategory":"Business Services",
            "type":"Services"
        }
    ],
    "sg:postcode":"DY13 9EH",
    "sg:province":"Worcestershire",
    "sg:tags":[
        "import",
        "export",
        "agent"
    ],
    "wof:name":"Mair,Kamal,",
    "wof:placetype":"venue"
},
  "geometry": {"coordinates":[-2.278647,52.338577],"type":"Point"}
}