{
  "type": "Feature",
  "properties": {
    "iso:country":"GB",
    "sg:address":"Hungary Hill",
    "sg:city":"Stourbridge",
    "sg:classifiers":[
        {
            "category":"Education",
            "subcategory":"Special Training",
            "type":"Public Place"
        }
    ],
    "sg:phone":"+44 1384 393339",
    "sg:postcode":"DY9 7NJ",
    "sg:province":"West Midlands",
    "sg:tags":[
        "product",
        "centre"
    ],
    "wof:name":"Hansons Road Transport",
    "wof:placetype":"venue"
},
  "geometry": {"coordinates":[-2.1311819553,52.4573936462],"type":"Point"}
}