{
  "type": "Feature",
  "properties": {
    "addr:full":"6c Grange Road, Houstoun Industrial Estate Livingston West Lothian EH54 5DE",
    "addr:housenumber":"6c",
    "addr:postcode":"eh54 5de",
    "addr:street":"Grange Road Houstoun Industrial Estate",
    "iso:country":"GB",
    "sg:address":"6c Grange Road, Houstoun Industrial Estate",
    "sg:city":"Livingston",
    "sg:classifiers":[
        {
            "category":"Home & Garden",
            "subcategory":"Hardware",
            "type":"Retail Goods"
        }
    ],
    "sg:phone":"+44 1506 430552",
    "sg:postcode":"EH54 5DE",
    "sg:province":"West Lothian",
    "sg:tags":[
        "equipment",
        "wire",
        "cable"
    ],
    "wof:name":"Techdyne (Scotland) Ltd",
    "wof:placetype":"venue"
},
  "geometry": {"coordinates":[-3.5001370907,55.9064788818],"type":"Point"}
}