{
  "type": "Feature",
  "properties": {
    "addr:full":"1 Brooksbank House, Pound Lane, Copythorne Southampton Hampshire SO40 2PD",
    "addr:housenumber":"1",
    "addr:postcode":"so40 2pd",
    "addr:street":"Brooksbank House Pound Lane",
    "iso:country":"GB",
    "sg:address":"1 Brooksbank House, Pound Lane, Copythorne",
    "sg:city":"Southampton",
    "sg:classifiers":[
        {
            "category":"Manufacturing",
            "subcategory":"Petroleum Products",
            "type":"Manufacturing & Wholesale Goods"
        }
    ],
    "sg:phone":"+44 23 8081 3352",
    "sg:postcode":"SO40 2PD",
    "sg:province":"Hampshire",
    "sg:tags":[
        "double",
        "glazing"
    ],
    "wof:name":"Southern Window Services",
    "wof:placetype":"venue"
},
  "geometry": {"coordinates":[-1.5557539463,50.9260940552],"type":"Point"}
}