{
  "type": "Feature",
  "properties": {
    "addr:full":"St Peters Medical Centre, Colbeck Rd Harrow Greater London HA1 4BS",
    "addr:postcode":"ha1 4bs",
    "addr:street":"Colbeck Rd",
    "iso:country":"GB",
    "sg:address":"St Peters Medical Centre, Colbeck Rd",
    "sg:city":"Harrow",
    "sg:classifiers":[
        {
            "category":"Health Services",
            "subcategory":"Doctor",
            "type":"Services"
        }
    ],
    "sg:phone":"+44 20 8864 4868",
    "sg:postcode":"HA1 4BS",
    "sg:province":"Greater London",
    "sg:tags":[
        "practitioners"
    ],
    "wof:name":"Rosemary Green",
    "wof:placetype":"venue"
},
  "geometry": {"coordinates":[-0.3360820115,51.5787849426],"type":"Point"}
}