{
  "type": "Feature",
  "properties": {
    "addr:full":"7 Bedale Street London Greater London SE1 9AL",
    "addr:housenumber":"7",
    "addr:postcode":"se1 9al",
    "addr:street":"Bedale Street",
    "iso:country":"GB",
    "sg:address":"7 Bedale Street",
    "sg:city":"London",
    "sg:classifiers":[
        {
            "category":"Health Services",
            "subcategory":"Optometrist",
            "type":"Services"
        }
    ],
    "sg:phone":"+44 20 7403 6179",
    "sg:postcode":"SE1 9AL",
    "sg:province":"Greater London",
    "sg:tags":[
        "optician"
    ],
    "wof:name":"Quinlan's Opticians",
    "wof:placetype":"venue"
},
  "geometry": {"coordinates":[-0.090237,51.505585],"type":"Point"}
}