{
  "type": "Feature",
  "properties": {
    "addr:full":"31 Crescent Road Barnet Hertfordshire EN4 9RD",
    "addr:housenumber":"31",
    "addr:postcode":"en4 9rd",
    "addr:street":"Crescent Road",
    "iso:country":"GB",
    "sg:address":"31 Crescent Road",
    "sg:city":"Barnet",
    "sg:classifiers":[
        {
            "category":"Building & Trades",
            "subcategory":"Construction",
            "type":"Services"
        }
    ],
    "sg:phone":"+44 20 8364 8121",
    "sg:postcode":"EN4 9RD",
    "sg:province":"Hertfordshire",
    "sg:tags":[
        "builder"
    ],
    "wof:name":"P Harris Builders",
    "wof:placetype":"venue"
},
  "geometry": {"coordinates":[-0.166758,51.651165],"type":"Point"}
}