{
  "type": "Feature",
  "properties": {
    "addr:full":"The Clockwork Shop, 79 Corn Street Witney Oxfordshire OX28 6AS",
    "addr:housenumber":"79",
    "addr:postcode":"ox28 6as",
    "addr:street":"Corn Street",
    "iso:country":"GB",
    "sg:address":"The Clockwork Shop, 79 Corn Street",
    "sg:city":"Witney",
    "sg:classifiers":[
        {
            "category":"Retail",
            "subcategory":"Repair Shop",
            "type":"Services"
        }
    ],
    "sg:phone":"+44 1993 772123",
    "sg:postcode":"OX28 6AS",
    "sg:province":"Oxfordshire",
    "sg:tags":[
        "clocks",
        "watch"
    ],
    "wof:name":"The Clockwork Shop",
    "wof:placetype":"venue"
},
  "geometry": {"coordinates":[-1.496171,51.782642],"type":"Point"}
}