{
  "type": "Feature",
  "properties": {
    "addr:full":"13b Kingfisher Shopping Centre, Kingfisher Walk Redditch Warwickshire B97 4EY",
    "addr:housenumber":"13b",
    "addr:postcode":"b97 4ey",
    "addr:street":"Kingfisher Shopping;Kingfisher Walk",
    "iso:country":"GB",
    "sg:address":"13b Kingfisher Shopping Centre, Kingfisher Walk",
    "sg:city":"Redditch",
    "sg:classifiers":[
        {
            "category":"Shopping",
            "subcategory":"Department Store",
            "type":"Retail Goods"
        },
        {
            "category":"Shopping",
            "subcategory":"Clothing, Apparel, & Fashions",
            "type":"Retail Goods"
        }
    ],
    "sg:phone":"+44 1527 62771",
    "sg:postcode":"B97 4EY",
    "sg:province":"Warwickshire",
    "sg:tags":[
        "shop",
        "departmental"
    ],
    "wof:name":"Peacocks Stores Ltd",
    "wof:placetype":"venue"
},
  "geometry": {"coordinates":[-1.9412670135,52.30727005],"type":"Point"}
}