{
  "type": "Feature",
  "properties": {
    "iso:country":"GB",
    "sg:address":"Unit 3, Silva Island Way",
    "sg:city":"Wickford",
    "sg:classifiers":[
        {
            "category":"Personal",
            "subcategory":"Beauty Salon",
            "type":"Services"
        }
    ],
    "sg:phone":"+44 1268 571007",
    "sg:postcode":"SS12 9NR",
    "sg:province":"Essex",
    "sg:tags":[
        "unisex",
        "hairdresser"
    ],
    "wof:name":"Technicutz",
    "wof:placetype":"venue"
},
  "geometry": {"coordinates":[0.5351629853,51.6022186279],"type":"Point"}
}