{
  "type": "Feature",
  "properties": {
    "iso:country":"GB",
    "sg:address":"47 Salisbury Street",
    "sg:city":"Blandford Forum",
    "sg:classifiers":[
        {
            "category":"Shopping",
            "subcategory":"Clothing, Apparel, & Fashions",
            "type":"Retail Goods"
        }
    ],
    "sg:postcode":"DT11 7PX",
    "sg:province":"Dorset",
    "sg:tags":[
        "lingerie",
        "hosiery"
    ],
    "wof:name":"Gemini",
    "wof:placetype":"venue"
},
  "geometry": {"coordinates":[-2.164939,50.857594],"type":"Point"}
}