{
  "type": "Feature",
  "properties": {
    "iso:country":"GB",
    "sg:address":"10 Fryern Arcade, Winchester Road, Chandlers Ford",
    "sg:city":"Eastleigh",
    "sg:classifiers":[
        {
            "category":"Bars & Pubs",
            "subcategory":"Wine Bar",
            "type":"Food & Drink"
        }
    ],
    "sg:phone":"+44 23 8027 5237",
    "sg:postcode":"SO53 2DP",
    "sg:province":"Hampshire",
    "wof:name":"Jones Wine Bar",
    "wof:placetype":"venue"
},
  "geometry": {"coordinates":[-1.372641,50.985359],"type":"Point"}
}