{
  "type": "Feature",
  "properties": {
    "addr:full":"Levedale Stafford Staffordshire ST18 9AH",
    "addr:postcode":"st18 9ah",
    "addr:street":"Levedale",
    "iso:country":"GB",
    "sg:address":"Levedale",
    "sg:city":"Stafford",
    "sg:classifiers":[
        {
            "category":"Wholesale",
            "subcategory":"Construction Materials",
            "type":"Manufacturing & Wholesale Goods"
        }
    ],
    "sg:phone":"+44 1785 780335",
    "sg:postcode":"ST18 9AH",
    "sg:province":"Staffordshire",
    "sg:tags":[
        "merchant",
        "brick"
    ],
    "wof:name":"P.J Allen",
    "wof:placetype":"venue"
},
  "geometry": {"coordinates":[-2.1505789757,52.7455673218],"type":"Point"}
}