{
  "type": "Feature",
  "properties": {
    "iso:country":"GB",
    "sg:address":"Unit 3d, West Ealing Business Ctr, Alexandria Road",
    "sg:city":"London",
    "sg:classifiers":[
        {
            "category":"Retail",
            "subcategory":"Auto Repair",
            "type":"Services"
        }
    ],
    "sg:phone":"+44 20 8566 5597",
    "sg:postcode":"W13 0NJ",
    "sg:province":"Greater London",
    "sg:tags":[
        "modification",
        "garage"
    ],
    "wof:name":"Suri Motors",
    "wof:placetype":"venue"
},
  "geometry": {"coordinates":[-0.32267,51.5131],"type":"Point"}
}