{
  "type": "Feature",
  "properties": {
    "iso:country":"GB",
    "sg:address":"4 Wesley St, Carrington",
    "sg:city":"Nottingham",
    "sg:classifiers":[
        {
            "category":"Personal",
            "subcategory":"Skin Care",
            "type":"Services"
        }
    ],
    "sg:phone":"+44 115 960 9474",
    "sg:postcode":"NG5 2BJ",
    "sg:province":"Nottinghamshire",
    "sg:tags":[
        "leather",
        "merchant"
    ],
    "wof:name":"K & M Manufacturing Co.Ltd",
    "wof:placetype":"venue"
},
  "geometry": {"coordinates":[-1.1537430286,52.9734420776],"type":"Point"}
}