{
  "type": "Feature",
  "properties": {
    "addr:full":"150 Chiltern Heights Amersham Buckinghamshire HP7 9RX",
    "addr:housenumber":"150",
    "addr:postcode":"hp7 9rx",
    "addr:street":"Chiltern Heights Amersham",
    "iso:country":"GB",
    "sg:address":"150 Chiltern Heights",
    "sg:city":"Amersham",
    "sg:classifiers":[
        {
            "category":"Retail",
            "subcategory":"Storage",
            "type":"Services"
        }
    ],
    "sg:phone":"+44 1494 766360",
    "sg:postcode":"HP7 9RX",
    "sg:province":"Buckinghamshire",
    "sg:tags":[
        "household",
        "removal"
    ],
    "wof:name":"Mikes Transport Service",
    "wof:placetype":"venue"
},
  "geometry": {"coordinates":[-0.5786340237,51.6707344055],"type":"Point"}
}