{
  "type": "Feature",
  "properties": {
    "iso:country":"GB",
    "sg:address":"16 Caughall Road, Upton",
    "sg:city":"Chester",
    "sg:classifiers":[
        {
            "category":"Professional",
            "subcategory":"Research",
            "type":"Services"
        }
    ],
    "sg:phone":"+44 1244 380433",
    "sg:postcode":"CH2 1LS",
    "sg:province":"Cheshire",
    "sg:tags":[
        "organisation",
        "market"
    ],
    "wof:name":"Colin McNae & Associates",
    "wof:placetype":"venue"
},
  "geometry": {"coordinates":[-2.878681,53.222363],"type":"Point"}
}