{
  "type": "Feature",
  "properties": {
    "iso:country":"GB",
    "sg:address":"234 Willerby Road",
    "sg:city":"Hull",
    "sg:classifiers":[
        {
            "category":"Health Services",
            "subcategory":"Health Practitioner",
            "type":"Services"
        }
    ],
    "sg:phone":"+44 1482 353194",
    "sg:postcode":"HU5 5JR",
    "sg:province":"East Riding of Yorkshire",
    "sg:tags":[
        "physiotherapist"
    ],
    "wof:name":"Barbara Taylor",
    "wof:placetype":"venue"
},
  "geometry": {"coordinates":[-0.4115920067,53.7529335022],"type":"Point"}
}