{
  "type": "Feature",
  "properties": {
    "iso:country":"GB",
    "sg:address":"15 Central Shopping Centre, Ranelagh Street",
    "sg:city":"Liverpool",
    "sg:classifiers":[
        {
            "category":"Shopping",
            "subcategory":"Pharmacy",
            "type":"Retail Goods"
        }
    ],
    "sg:phone":"+44 151 709 5366",
    "sg:postcode":"L1 1QE",
    "sg:province":"Merseyside",
    "sg:tags":[
        "store",
        "drug",
        "outlet"
    ],
    "sg:website":"http://www.superdrug.com",
    "wof:name":"Superdrug Stores plc",
    "wof:placetype":"venue"
},
  "geometry": {"coordinates":[-2.980079,53.404804],"type":"Point"}
}