{
  "type": "Feature",
  "properties": {
    "iso:country":"GB",
    "sg:address":"17 West Main Street, Harthill",
    "sg:city":"Shotts",
    "sg:classifiers":[
        {
            "category":"Personal",
            "subcategory":"Beauty Salon",
            "type":"Services"
        }
    ],
    "sg:phone":"+44 1501 752888",
    "sg:postcode":"ML7 5QD",
    "sg:province":"North Lanarkshire",
    "sg:tags":[
        "unisex",
        "hairdresser"
    ],
    "wof:name":"Salon 17",
    "wof:placetype":"venue"
},
  "geometry": {"coordinates":[-3.750365,55.860279],"type":"Point"}
}