{
  "type": "Feature",
  "properties": {
    "addr:full":"Uppertown House Farm, Ashover Chesterfield Derbyshire S45 0JF",
    "addr:housenumber":"ashover",
    "addr:postcode":"s45 0jf",
    "addr:street":"Chesterfield Derbyshire",
    "iso:country":"GB",
    "sg:address":"Uppertown House Farm, Ashover",
    "sg:city":"Chesterfield",
    "sg:classifiers":[
        {
            "category":"Farming",
            "subcategory":"Livestock Farm",
            "type":"Manufacturing & Wholesale Goods"
        }
    ],
    "sg:postcode":"S45 0JF",
    "sg:province":"Derbyshire",
    "sg:tags":[
        "others"
    ],
    "wof:name":"Keith E Montague",
    "wof:placetype":"venue"
},
  "geometry": {"coordinates":[-1.492899,53.170292],"type":"Point"}
}