{
  "type": "Feature",
  "properties": {
    "addr:full":"49 Thornleigh Road, Horfield Bristol City of Bristol BS7 8PQ",
    "addr:housenumber":"49",
    "addr:postcode":"bs7 8pq",
    "addr:street":"Thornleigh Road",
    "iso:country":"GB",
    "sg:address":"49 Thornleigh Road, Horfield",
    "sg:city":"Bristol",
    "sg:classifiers":[
        {
            "category":"Professional",
            "subcategory":"Business Services",
            "type":"Services"
        }
    ],
    "sg:phone":"+44 117 942 9022",
    "sg:postcode":"BS7 8PQ",
    "sg:province":"City of Bristol",
    "sg:tags":[
        "import",
        "export",
        "agent"
    ],
    "wof:name":"Kinnersley Brothers Ltd.",
    "wof:placetype":"venue"
},
  "geometry": {"coordinates":[-2.5886740685,51.4823188782],"type":"Point"}
}