{
  "type": "Feature",
  "properties": {
    "iso:country":"GB",
    "sg:address":"63 Turner Road",
    "sg:city":"London",
    "sg:classifiers":[
        {
            "category":"Building & Trades",
            "subcategory":"Construction",
            "type":"Services"
        }
    ],
    "sg:phone":"+44 20 8520 0073",
    "sg:postcode":"E17 3JG",
    "sg:province":"Greater London",
    "sg:tags":[
        "restoration",
        "refurbishment"
    ],
    "wof:name":"Catherall by Design",
    "wof:placetype":"venue"
},
  "geometry": {"coordinates":[-0.005499,51.588161],"type":"Point"}
}