{
  "type": "Feature",
  "properties": {
    "iso:country":"GB",
    "sg:address":"107 Derby Rd",
    "sg:city":"Northampton",
    "sg:classifiers":[
        {
            "category":"Manufacturing",
            "subcategory":"Petroleum Products",
            "type":"Manufacturing & Wholesale Goods"
        }
    ],
    "sg:phone":"+44 1604 234550",
    "sg:postcode":"NN1 4JP",
    "sg:province":"Northamptonshire",
    "sg:tags":[
        "double",
        "glazing"
    ],
    "wof:name":"Diplomats",
    "wof:placetype":"venue"
},
  "geometry": {"coordinates":[-0.878183,52.246773],"type":"Point"}
}