{
  "type": "Feature",
  "properties": {
    "addr:full":"Unit 1b, Mint Bridge Rd, Whitehaven Kendal Cumbria LA9 6NH",
    "addr:housenumber":"unit 1b",
    "addr:postcode":"la9 6nh",
    "addr:street":"Mint Bridge Rd",
    "iso:country":"GB",
    "sg:address":"Unit 1b, Mint Bridge Rd, Whitehaven",
    "sg:city":"Kendal",
    "sg:classifiers":[
        {
            "category":"Building & Trades",
            "subcategory":"Construction",
            "type":"Services"
        }
    ],
    "sg:phone":"+44 1946 592003",
    "sg:postcode":"LA9 6NH",
    "sg:province":"Cumbria",
    "sg:tags":[
        "ventilation",
        "contractor"
    ],
    "wof:name":"Terminix Peter Cox",
    "wof:placetype":"venue"
},
  "geometry": {"coordinates":[-2.737624,54.341236],"type":"Point"}
}