{
  "type": "Feature",
  "properties": {
    "addr:full":"Tyn-y-coed Farm, Elan Valley Rhayader Powys LD6 5HL",
    "addr:postcode":"ld6 5hl",
    "iso:country":"GB",
    "sg:address":"Tyn-y-coed Farm, Elan Valley",
    "sg:city":"Rhayader",
    "sg:classifiers":[
        {
            "category":"Farming",
            "subcategory":"Livestock Farm",
            "type":"Manufacturing & Wholesale Goods"
        }
    ],
    "sg:postcode":"LD6 5HL",
    "sg:province":"Powys",
    "sg:tags":[
        "others"
    ],
    "wof:name":"W D & M L Griffiths & Son",
    "wof:placetype":"venue"
},
  "geometry": {"coordinates":[-3.51158,52.302761],"type":"Point"}
}