{
  "type": "Feature",
  "properties": {
    "iso:country":"GB",
    "sg:address":"56 West Wellbrae Crescent",
    "sg:city":"Hamilton",
    "sg:classifiers":[
        {
            "category":"Real Estate",
            "subcategory":"Real Estate Agent",
            "type":"Services"
        }
    ],
    "sg:postcode":"ML3 8HE",
    "sg:province":"South Lanarkshire",
    "wof:name":"Clydesdale Properties (Hamilton) Limited",
    "wof:placetype":"venue"
},
  "geometry": {"coordinates":[-4.058344,55.761051],"type":"Point"}
}