{
  "type": "Feature",
  "properties": {
    "iso:country":"GB",
    "sg:address":"Park Road, Newbridge",
    "sg:city":"Wrexham",
    "sg:classifiers":[
        {
            "category":"Bars & Pubs",
            "type":"Food & Drink"
        }
    ],
    "sg:postcode":"LL14 3YS",
    "sg:province":"Wrexham",
    "sg:tags":[
        "pubs",
        "inn"
    ],
    "wof:name":"Royal Oak",
    "wof:placetype":"venue"
},
  "geometry": {"coordinates":[-3.066065,52.966209],"type":"Point"}
}