{
  "type": "Feature",
  "properties": {
    "iso:country":"GB",
    "sg:address":"293 Conway Road, Mochdre",
    "sg:city":"Colwyn Bay",
    "sg:classifiers":[
        {
            "category":"Health Services",
            "subcategory":"Chiropractor",
            "type":"Services"
        }
    ],
    "sg:postcode":"LL28 5AA",
    "sg:province":"Conwy",
    "wof:name":"R J Mewis Chiropractor",
    "wof:placetype":"venue"
},
  "geometry": {"coordinates":[-3.758544,53.296116],"type":"Point"}
}