{
  "type": "Feature",
  "properties": {
    "iso:country":"GB",
    "sg:address":"Electro House Edinburgh Wa, Crowridge Road",
    "sg:city":"Harlow",
    "sg:classifiers":[
        {
            "category":"Professional",
            "subcategory":"Management & Consulting",
            "type":"Services"
        }
    ],
    "sg:phone":"+44 1279 635668",
    "sg:postcode":"CM20 2TP",
    "sg:province":"Essex",
    "sg:tags":[
        "fire",
        "consultant",
        "protection"
    ],
    "wof:name":"Electro-Detectors Ltd.",
    "wof:placetype":"venue"
},
  "geometry": {"coordinates":[0.097731,51.780609],"type":"Point"}
}