{
  "type": "Feature",
  "properties": {
    "addr:full":"23 High Street Uckfield East Sussex TN22 1AG",
    "addr:housenumber":"23",
    "addr:postcode":"tn22 1ag",
    "addr:street":"High Street",
    "iso:country":"GB",
    "sg:address":"23 High Street",
    "sg:city":"Uckfield",
    "sg:classifiers":[
        {
            "category":"Deli",
            "type":"Food & Drink"
        }
    ],
    "sg:phone":"+44 1825 766670",
    "sg:postcode":"TN22 1AG",
    "sg:province":"East Sussex",
    "sg:tags":[
        "delicatessen"
    ],
    "wof:name":"Corbins of Uckfield",
    "wof:placetype":"venue"
},
  "geometry": {"coordinates":[0.095913,50.970009],"type":"Point"}
}