{
  "type": "Feature",
  "properties": {
    "iso:country":"GB",
    "sg:address":"Chadwick Road, Eccles",
    "sg:city":"Manchester",
    "sg:classifiers":[
        {
            "category":"Wholesale",
            "subcategory":"Meat",
            "type":"Manufacturing & Wholesale Goods"
        }
    ],
    "sg:phone":"+44 161 707 4767",
    "sg:postcode":"M30 0NZ",
    "sg:province":"Greater Manchester",
    "sg:tags":[
        "-"
    ],
    "wof:name":"Ringwood Marketing",
    "wof:placetype":"venue"
},
  "geometry": {"coordinates":[-2.340709,53.483456],"type":"Point"}
}