{
  "type": "Feature",
  "properties": {
    "addr:full":"13-19 Fareham Industrial Park, Standard Way Fareham Hampshire PO16 8XB",
    "addr:housenumber":"13-19",
    "addr:postcode":"po16 8xb",
    "addr:street":"Fareham Industrial Park Standard Way",
    "iso:country":"GB",
    "sg:address":"13-19 Fareham Industrial Park, Standard Way",
    "sg:city":"Fareham",
    "sg:classifiers":[
        {
            "category":"Professional",
            "subcategory":"Business Services",
            "type":"Services"
        },
        {
            "category":"Food & Beverages",
            "subcategory":"Supermarket",
            "type":"Retail Goods"
        },
        {
            "category":"Food & Beverages",
            "subcategory":"Groceries & Convenience Stores",
            "type":"Retail Goods"
        }
    ],
    "sg:phone":"+44 1329 823124",
    "sg:postcode":"PO16 8XB",
    "sg:province":"Hampshire",
    "sg:tags":[
        "distribution"
    ],
    "wof:name":"Southern Co-Operatives Ltd.",
    "wof:placetype":"venue"
},
  "geometry": {"coordinates":[-1.1740989685,50.8527336121],"type":"Point"}
}