{
  "type": "Feature",
  "properties": {
    "iso:country":"GB",
    "sg:address":"10 Adelaide Road",
    "sg:city":"Chichester",
    "sg:classifiers":[
        {
            "category":"Fast Food",
            "type":"Food & Drink"
        },
        {
            "category":"Food & Beverages",
            "subcategory":"Meat & Fish",
            "type":"Retail Goods"
        }
    ],
    "sg:phone":"+44 1243 782623",
    "sg:postcode":"PO19 7NB",
    "sg:province":"West Sussex",
    "sg:tags":[
        "shop",
        "chip"
    ],
    "wof:name":"Fish Regal",
    "wof:placetype":"venue"
},
  "geometry": {"coordinates":[-0.770678,50.841518],"type":"Point"}
}