{
  "type": "Feature",
  "properties": {
    "iso:country":"GB",
    "sg:address":"20 Thetford Road",
    "sg:city":"Thetford",
    "sg:classifiers":[
        {
            "category":"Shopping",
            "subcategory":"Clothing, Apparel, & Fashions",
            "type":"Retail Goods"
        }
    ],
    "sg:phone":"+44 1953 885210",
    "sg:postcode":"IP25 6BS",
    "sg:province":"Norfolk",
    "sg:tags":[
        "dresswear"
    ],
    "wof:name":"Gladrags",
    "wof:placetype":"venue"
},
  "geometry": {"coordinates":[0.8234099746,52.567401886],"type":"Point"}
}