{
  "type": "Feature",
  "properties": {
    "iso:country":"GB",
    "sg:address":"Unit 2a, Ipsley Street, Millsborough House",
    "sg:city":"Redditch",
    "sg:classifiers":[
        {
            "category":"Wholesale",
            "subcategory":"Office Equipment",
            "type":"Manufacturing & Wholesale Goods"
        }
    ],
    "sg:phone":"+44 1527 450035",
    "sg:postcode":"B98 7AL",
    "sg:province":"Warwickshire",
    "sg:tags":[
        "partition",
        "cubicle"
    ],
    "wof:name":"Design Products (U K) Ltd.",
    "wof:placetype":"venue"
},
  "geometry": {"coordinates":[-1.9368089437,52.3047218323],"type":"Point"}
}