{
  "type": "Feature",
  "properties": {
    "addr:full":"37 Station Rd Sevenoaks Kent TN15 6AR",
    "addr:housenumber":"37",
    "addr:postcode":"tn15 6ar",
    "addr:street":"Station Rd",
    "iso:country":"GB",
    "sg:address":"37 Station Rd",
    "sg:city":"Sevenoaks",
    "sg:classifiers":[
        {
            "category":"Professional",
            "subcategory":"Accounting & Tax Preparation",
            "type":"Services"
        }
    ],
    "sg:phone":"+44 1474 853856",
    "sg:postcode":"TN15 6AR",
    "sg:province":"Kent",
    "sg:tags":[
        "accountant"
    ],
    "wof:name":"Stephen Hill Partnership",
    "wof:placetype":"venue"
},
  "geometry": {"coordinates":[0.307279,51.29229],"type":"Point"}
}