{
  "type": "Feature",
  "properties": {
    "iso:country":"GB",
    "sg:address":"55 Carwood Road, Glasshoughton",
    "sg:city":"Castleford",
    "sg:classifiers":[
        {
            "category":"Sports & Exercise",
            "subcategory":"Race Track",
            "type":"Entertainment"
        }
    ],
    "sg:phone":"+44 1977 552348",
    "sg:postcode":"WF10 4SB",
    "sg:province":"West Yorkshire",
    "sg:tags":[
        "motor"
    ],
    "wof:name":"B T R Preparations",
    "wof:placetype":"venue"
},
  "geometry": {"coordinates":[-1.344208,53.721699],"type":"Point"}
}