{
  "type": "Feature",
  "properties": {
    "addr:full":"Dudley Road East, Tividale, Oldbury Smethwick West Midlands B69 3HJ",
    "addr:postcode":"b69 3hj",
    "addr:street":"Dudley Road East Tividale",
    "iso:country":"GB",
    "sg:address":"Dudley Road East, Tividale, Oldbury",
    "sg:city":"Smethwick",
    "sg:classifiers":[
        {
            "category":"Home & Garden",
            "subcategory":"Furniture",
            "type":"Retail Goods"
        }
    ],
    "sg:phone":"+44 121 520 8828",
    "sg:postcode":"B69 3HJ",
    "sg:province":"West Midlands",
    "wof:name":"Bankrupt Warehouse",
    "wof:placetype":"venue"
},
  "geometry": {"coordinates":[-2.025274,52.508286],"type":"Point"}
}