{
  "type": "Feature",
  "properties": {
    "iso:country":"GB",
    "sg:address":"1 Mackie Crescent, Markinch",
    "sg:city":"Glenrothes",
    "sg:classifiers":[
        {
            "category":"Building & Trades",
            "subcategory":"Plumbing",
            "type":"Services"
        }
    ],
    "sg:postcode":"KY7 6BB",
    "sg:province":"Fife",
    "sg:tags":[
        "heating"
    ],
    "wof:name":"David Scott",
    "wof:placetype":"venue"
},
  "geometry": {"coordinates":[-3.141157,56.199482],"type":"Point"}
}