{
  "type": "Feature",
  "properties": {
    "addr:full":"709 Leek Rd Stoke On Trent Staffordshire ST1 3NG",
    "addr:housenumber":"709",
    "addr:street":"Leek Rd",
    "iso:country":"GB",
    "sg:address":"709 Leek Rd",
    "sg:city":"Stoke On Trent",
    "sg:classifiers":[
        {
            "category":"Manufacturing",
            "subcategory":"Building Materials",
            "type":"Manufacturing & Wholesale Goods"
        }
    ],
    "sg:phone":"+44 1782 202205",
    "sg:postcode":"ST1 3NG",
    "sg:province":"Staffordshire",
    "sg:tags":[
        "merchant",
        "builder"
    ],
    "wof:name":"Hall & Co Ltd",
    "wof:placetype":"venue"
},
  "geometry": {"coordinates":[-2.162757,53.019817],"type":"Point"}
}