{
  "type": "Feature",
  "properties": {
    "iso:country":"GB",
    "sg:address":"Otterton Mill, Otterton",
    "sg:city":"Budleigh Salterton",
    "sg:classifiers":[
        {
            "category":"Arts & Performance",
            "subcategory":"Art Gallery",
            "type":"Entertainment"
        }
    ],
    "sg:phone":"+44 1395 567028",
    "sg:postcode":"EX9 7HG",
    "sg:province":"Devon",
    "wof:name":"The Lester Studio",
    "wof:placetype":"venue"
},
  "geometry": {"coordinates":[-3.2985210419,50.6601295471],"type":"Point"}
}