{
  "type": "Feature",
  "properties": {
    "iso:country":"GB",
    "sg:address":"77 Thurleigh Rd",
    "sg:city":"Balham",
    "sg:classifiers":[
        {
            "category":"Health Services",
            "subcategory":"Doctor",
            "type":"Services"
        }
    ],
    "sg:phone":"+44 20 8675 3521",
    "sg:postcode":"SW12 8TZ",
    "sg:province":"Greater London",
    "sg:tags":[
        "practitioners"
    ],
    "wof:name":"Schofield Dr R",
    "wof:placetype":"venue"
},
  "geometry": {"coordinates":[-0.160078,51.451584],"type":"Point"}
}