{
  "type": "Feature",
  "properties": {
    "iso:country":"GB",
    "sg:address":"Manor Cottage, 5 West St, Barkston",
    "sg:city":"Grantham",
    "sg:classifiers":[
        {
            "category":"Professional",
            "subcategory":"Accounting & Tax Preparation",
            "type":"Services"
        }
    ],
    "sg:postcode":"NG32 2NL",
    "sg:province":"Leicestershire",
    "sg:tags":[
        "accountant"
    ],
    "wof:name":"Champney Bell Accountants",
    "wof:placetype":"venue"
},
  "geometry": {"coordinates":[-0.614802,52.964802],"type":"Point"}
}