{
  "type": "Feature",
  "properties": {
    "addr:full":"5 Benarty Square, Ballingry Lochgelly Fife KY5 8NR",
    "addr:housenumber":"5",
    "addr:postcode":"ky5 8nr",
    "addr:street":"Benarty Square Ballingry Lochgelly",
    "iso:country":"GB",
    "sg:address":"5 Benarty Square, Ballingry",
    "sg:city":"Lochgelly",
    "sg:classifiers":[
        {
            "category":"Food & Beverages",
            "subcategory":"Supermarket",
            "type":"Retail Goods"
        }
    ],
    "sg:phone":"+44 1592 861002",
    "sg:postcode":"KY5 8NR",
    "sg:province":"Fife",
    "wof:name":"S R Supermarket",
    "wof:placetype":"venue"
},
  "geometry": {"coordinates":[-3.3242731094,56.1518173218],"type":"Point"}
}