{
  "type": "Feature",
  "properties": {
    "iso:country":"GB",
    "sg:address":"517 Bath Road, Saltford",
    "sg:city":"Bristol",
    "sg:classifiers":[
        {
            "category":"Retail",
            "subcategory":"Driving School",
            "type":"Services"
        }
    ],
    "sg:phone":"+44 1225 874114",
    "sg:postcode":"BS31 3HH",
    "sg:province":"City of Bristol",
    "wof:name":"1ST Myles Driving School",
    "wof:placetype":"venue"
},
  "geometry": {"coordinates":[-2.4556388855,51.4011611938],"type":"Point"}
}