{
  "type": "Feature",
  "properties": {
    "addr:full":"50 Grange Road, Bramhall Stockport Cheshire SK7 3BD",
    "addr:housenumber":"50",
    "addr:postcode":"sk7 3bd",
    "addr:street":"Grange Road",
    "iso:country":"GB",
    "sg:address":"50 Grange Road, Bramhall",
    "sg:city":"Stockport",
    "sg:classifiers":[
        {
            "category":"Education",
            "subcategory":"Music School",
            "type":"Public Place"
        }
    ],
    "sg:postcode":"SK7 3BD",
    "sg:province":"Cheshire",
    "sg:tags":[
        "teacher"
    ],
    "wof:name":"Barbara Pope Qualified Music Teacher",
    "wof:placetype":"venue"
},
  "geometry": {"coordinates":[-2.1510920525,53.3782577515],"type":"Point"}
}