{
  "type": "Feature",
  "properties": {
    "iso:country":"GB",
    "sg:address":"Gipsy Lane",
    "sg:city":"Leicester",
    "sg:classifiers":[
        {
            "category":"Education",
            "subcategory":"School",
            "type":"Public Place"
        }
    ],
    "sg:phone":"+44 116 266 1114",
    "sg:postcode":"LE4 6RB",
    "sg:province":"Leicestershire",
    "sg:tags":[
        "local",
        "authority"
    ],
    "wof:name":"Rushey Mead Primary School",
    "wof:placetype":"venue"
},
  "geometry": {"coordinates":[-1.111594,52.65593],"type":"Point"}
}