{
  "type": "Feature",
  "properties": {
    "addr:full":"1 Penmaen Villas Blackwood Caerphilly NP12 0DL",
    "addr:housenumber":"1",
    "addr:postcode":"np12 0dl",
    "addr:street":"Penmaen Villas",
    "iso:country":"GB",
    "sg:address":"1 Penmaen Villas",
    "sg:city":"Blackwood",
    "sg:classifiers":[
        {
            "category":"Government",
            "subcategory":"Post Office",
            "type":"Public Place"
        }
    ],
    "sg:postcode":"NP12 0DL",
    "sg:province":"Caerphilly",
    "wof:name":"V C & A G Howells",
    "wof:placetype":"venue"
},
  "geometry": {"coordinates":[-3.175941,51.680672],"type":"Point"}
}