{
  "type": "Feature",
  "properties": {
    "addr:full":"296 Spen La Cleckheaton West Yorkshire BD19 4PJ",
    "addr:housenumber":"296",
    "addr:postcode":"bd19 4pj",
    "addr:street":"Spen La Cleckheaton West",
    "iso:country":"GB",
    "sg:address":"296 Spen La",
    "sg:city":"Cleckheaton",
    "sg:classifiers":[
        {
            "category":"Building & Trades",
            "subcategory":"Construction",
            "type":"Services"
        }
    ],
    "sg:phone":"+44 1274 873748",
    "sg:postcode":"BD19 4PJ",
    "sg:province":"West Yorkshire",
    "sg:tags":[
        "joiner",
        "carpenter"
    ],
    "wof:name":"G Armitage",
    "wof:placetype":"venue"
},
  "geometry": {"coordinates":[-1.694778,53.728695],"type":"Point"}
}