{
  "type": "Feature",
  "properties": {
    "iso:country":"GB",
    "sg:address":"4 The Paragon, Clifton",
    "sg:city":"Bristol",
    "sg:classifiers":[
        {
            "category":"Real Estate",
            "subcategory":"Architect",
            "type":"Services"
        }
    ],
    "sg:postcode":"BS8 4LA",
    "sg:province":"City of Bristol",
    "wof:name":"Adrian Jones",
    "wof:placetype":"venue"
},
  "geometry": {"coordinates":[-2.623294,51.452534],"type":"Point"}
}