{
  "type": "Feature",
  "properties": {
    "addr:full":"772 College Road Birmingham West Midlands B44 0AL",
    "addr:housenumber":"772",
    "addr:postcode":"b44 0al",
    "addr:street":"College Road",
    "iso:country":"GB",
    "sg:address":"772 College Road",
    "sg:city":"Birmingham",
    "sg:classifiers":[
        {
            "category":"Health Services",
            "subcategory":"Nursing And Care Facility",
            "type":"Services"
        },
        {
            "category":"Social Services",
            "subcategory":"Retirement Home",
            "type":"Services"
        }
    ],
    "sg:phone":"+44 121 373 3003",
    "sg:postcode":"B44 0AL",
    "sg:province":"West Midlands",
    "sg:tags":[
        "residential"
    ],
    "wof:name":"FIRST CHOICE CARE AGENCY LTD",
    "wof:placetype":"venue"
},
  "geometry": {"coordinates":[-1.8637590408,52.544090271],"type":"Point"}
}