{
  "type": "Feature",
  "properties": {
    "addr:full":"53 Holly Park Rd Friern Barnet Greater London N11 3EY",
    "addr:housenumber":"53",
    "addr:postcode":"n11 3ey",
    "addr:street":"Holly Park Rd",
    "iso:country":"GB",
    "sg:address":"53 Holly Park Rd",
    "sg:city":"Friern Barnet",
    "sg:classifiers":[
        {
            "category":"Education",
            "subcategory":"Music School",
            "type":"Public Place"
        }
    ],
    "sg:phone":"+44 20 8361 9648",
    "sg:postcode":"N11 3EY",
    "sg:province":"Greater London",
    "sg:tags":[
        "teacher"
    ],
    "wof:name":"Peter L Bedford",
    "wof:placetype":"venue"
},
  "geometry": {"coordinates":[-0.1509419978,51.615852356],"type":"Point"}
}