{
  "type": "Feature",
  "properties": {
    "addr:full":"44 Wisbech Road, Long Sutton Spalding Cambridgeshire PE12 9AG",
    "addr:housenumber":"44",
    "addr:postcode":"pe12 9ag",
    "addr:street":"Wisbech Road",
    "iso:country":"GB",
    "sg:address":"44 Wisbech Road, Long Sutton",
    "sg:city":"Spalding",
    "sg:classifiers":[
        {
            "category":"Professional",
            "subcategory":"Business Services",
            "type":"Services"
        },
        {
            "category":"Farming",
            "subcategory":"Livestock Farm",
            "type":"Manufacturing & Wholesale Goods"
        },
        {
            "category":"Farming",
            "subcategory":"Farm",
            "type":"Manufacturing & Wholesale Goods"
        }
    ],
    "sg:phone":"+44 1406 363146",
    "sg:postcode":"PE12 9AG",
    "sg:province":"Cambridgeshire",
    "sg:tags":[
        "mixed",
        "accomodation",
        "others"
    ],
    "wof:name":"H & G White",
    "wof:placetype":"venue"
},
  "geometry": {"coordinates":[0.1357489973,52.7697181702],"type":"Point"}
}