{
  "type": "Feature",
  "properties": {
    "addr:full":"Wigan Road, Ashton In Makerfield Wigan Lancashire WN4 9BH",
    "addr:postcode":"wn4 9bh",
    "addr:street":"Wigan Road",
    "iso:country":"GB",
    "sg:address":"Wigan Road, Ashton In Makerfield",
    "sg:city":"Wigan",
    "sg:classifiers":[
        {
            "category":"Education",
            "subcategory":"Library",
            "type":"Public Place"
        }
    ],
    "sg:phone":"+44 1942 727119",
    "sg:postcode":"WN4 9BH",
    "sg:province":"Lancashire",
    "sg:tags":[
        "book"
    ],
    "wof:name":"Ashton in Makerfield Library",
    "wof:placetype":"venue"
},
  "geometry": {"coordinates":[-2.6430439949,53.494468689],"type":"Point"}
}