{
  "type": "Feature",
  "properties": {
    "iso:country":"GB",
    "sg:address":"134 Hoxton Street",
    "sg:city":"London",
    "sg:classifiers":[
        {
            "category":"Shopping",
            "subcategory":"Beauty & Cosmetics",
            "type":"Retail Goods"
        }
    ],
    "sg:postcode":"N1 6SH",
    "sg:province":"Greater London",
    "sg:tags":[
        "product"
    ],
    "wof:name":"JULIUS AKINWANDE",
    "wof:placetype":"venue"
},
  "geometry": {"coordinates":[-0.080001,51.531822],"type":"Point"}
}