{
  "type": "Feature",
  "properties": {
    "iso:country":"GB",
    "sg:address":"Unit 1 Ridgacre Enterprise Park, Ridgacre Rd",
    "sg:city":"West Bromwich",
    "sg:classifiers":[
        {
            "category":"Professional",
            "subcategory":"Engineering",
            "type":"Services"
        }
    ],
    "sg:phone":"+44 121 500 5439",
    "sg:postcode":"B71 1BW",
    "sg:province":"West Midlands",
    "wof:name":"Spevco Engineering",
    "wof:placetype":"venue"
},
  "geometry": {"coordinates":[-2.00302,52.533428],"type":"Point"}
}