{
  "type": "Feature",
  "properties": {
    "iso:country":"GB",
    "sg:address":"Units 4 & 5 Charnwood Court, Viking Way",
    "sg:city":"Swansea",
    "sg:classifiers":[
        {
            "category":"Shopping",
            "subcategory":"Computers & Home Electronics",
            "type":"Retail Goods"
        }
    ],
    "sg:phone":"+44 1792 796333",
    "sg:postcode":"SA1 7DA",
    "sg:province":"Neath Port Talbot",
    "sg:tags":[
        "electrical"
    ],
    "wof:name":"R&M (Fixings & Supports) Ltd.",
    "wof:placetype":"venue"
},
  "geometry": {"coordinates":[-3.90457,51.65403],"type":"Point"}
}