{
  "type": "Feature",
  "properties": {
    "addr:full":"Unit 7 Stirling Road Industrial Estate Airdrie North Lanarkshire ML6 7UD",
    "addr:housenumber":"unit 7",
    "addr:postcode":"ml6 7ud",
    "addr:street":"Stirling Road Industrial Estate",
    "iso:country":"GB",
    "sg:address":"Unit 7 Stirling Road Industrial Estate",
    "sg:city":"Airdrie",
    "sg:classifiers":[
        {
            "category":"Communications",
            "subcategory":"Television Station",
            "type":"Services"
        }
    ],
    "sg:phone":"+44 1236 764162",
    "sg:postcode":"ML6 7UD",
    "sg:province":"North Lanarkshire",
    "sg:tags":[
        "video"
    ],
    "wof:name":"P A V Electronics Ltd.",
    "wof:placetype":"venue"
},
  "geometry": {"coordinates":[-3.9694190025,55.8809509277],"type":"Point"}
}