{
  "type": "Feature",
  "properties": {
    "addr:full":"57 Corporation Road Middlesbrough North Yorkshire TS1 1LT",
    "addr:housenumber":"57",
    "addr:postcode":"ts1 1lt",
    "addr:street":"Corporation Road",
    "iso:country":"GB",
    "sg:address":"57 Corporation Road",
    "sg:city":"Middlesbrough",
    "sg:classifiers":[
        {
            "category":"Travel",
            "subcategory":"Travel Agent",
            "type":"Entertainment"
        }
    ],
    "sg:phone":"+44 1642 230710",
    "sg:postcode":"TS1 1LT",
    "sg:province":"North Yorkshire",
    "wof:name":"Wallace Arnold Travel Shop",
    "wof:placetype":"venue"
},
  "geometry": {"coordinates":[-1.2329310179,54.5762443542],"type":"Point"}
}