{
  "type": "Feature",
  "properties": {
    "iso:country":"GB",
    "sg:address":"308-314 Kings Road",
    "sg:city":"Reading",
    "sg:classifiers":[
        {
            "category":"Banks & Credit Unions",
            "subcategory":"Financial Services",
            "type":"Services"
        }
    ],
    "sg:phone":"+44 118 929 5111",
    "sg:postcode":"RG1 4NR",
    "sg:province":"Berkshire",
    "sg:tags":[
        "consultant"
    ],
    "wof:name":"Cananwill Europe Ltd.",
    "wof:placetype":"venue"
},
  "geometry": {"coordinates":[-0.952293,51.453163],"type":"Point"}
}