{
  "type": "Feature",
  "properties": {
    "addr:full":"The Old Post Office Buckingham Buckinghamshire MK18 5DU",
    "addr:postcode":"mk18 5du",
    "addr:street":"Buckingham",
    "iso:country":"GB",
    "sg:address":"The Old Post Office",
    "sg:city":"Buckingham",
    "sg:classifiers":[
        {
            "category":"Arts & Performance",
            "subcategory":"Art Gallery",
            "type":"Entertainment"
        }
    ],
    "sg:phone":"+44 1908 560643",
    "sg:postcode":"MK18 5DU",
    "sg:province":"Buckinghamshire",
    "wof:name":"Liam Ivers Fine Art",
    "wof:placetype":"venue"
},
  "geometry": {"coordinates":[-0.9864789844,52.0007514954],"type":"Point"}
}