{
  "type": "Feature",
  "properties": {
    "iso:country":"GB",
    "sg:address":"5 Deerlands Road, Wingerworth",
    "sg:city":"Chesterfield",
    "sg:classifiers":[
        {
            "category":"Real Estate",
            "subcategory":"Surveying",
            "type":"Services"
        }
    ],
    "sg:postcode":"S42 6UL",
    "sg:province":"Derbyshire",
    "sg:tags":[
        "surveyor",
        "quantity"
    ],
    "wof:name":"Peter Dickie",
    "wof:placetype":"venue"
},
  "geometry": {"coordinates":[-1.432184,53.194538],"type":"Point"}
}