{
  "type": "Feature",
  "properties": {
    "iso:country":"GB",
    "sg:address":"15 St Hildas Close, Christchurch Avenue",
    "sg:city":"London",
    "sg:classifiers":[
        {
            "category":"Professional",
            "subcategory":"Business Services",
            "type":"Services"
        }
    ],
    "sg:postcode":"NW6 7NY",
    "sg:province":"Greater London",
    "sg:tags":[
        "import",
        "export",
        "agent"
    ],
    "wof:name":"The Brynmills Co. Ltd.",
    "wof:placetype":"venue"
},
  "geometry": {"coordinates":[-0.2155,51.541321],"type":"Point"}
}