{
  "type": "Feature",
  "properties": {
    "addr:full":"15 St Hildas Close, Christchurch Avenue London Greater London NW6 7NY",
    "addr:housenumber":"15",
    "addr:postcode":"nw6 7ny",
    "addr:street":"St Hildas Close Christchurch Avenue",
    "iso:country":"GB",
    "sg:address":"15 St Hildas Close, Christchurch Avenue",
    "sg:city":"London",
    "sg:classifiers":[
        {
            "category":"Professional",
            "subcategory":"Business Services",
            "type":"Services"
        }
    ],
    "sg:postcode":"NW6 7NY",
    "sg:province":"Greater London",
    "sg:tags":[
        "import",
        "export",
        "agent"
    ],
    "wof:name":"The Brynmills Co. Ltd.",
    "wof:placetype":"venue"
},
  "geometry": {"coordinates":[-0.2155,51.541321],"type":"Point"}
}