{
  "type": "Feature",
  "properties": {
    "addr:full":"103 Islingword Road Brighton East Sussex BN2 9SG",
    "addr:housenumber":"103",
    "addr:postcode":"bn2 9sg",
    "addr:street":"Islingword Road",
    "iso:country":"GB",
    "sg:address":"103 Islingword Road",
    "sg:city":"Brighton",
    "sg:classifiers":[
        {
            "category":"Communications",
            "subcategory":"Film & Video Production",
            "type":"Services"
        }
    ],
    "sg:phone":"+44 1273 690149",
    "sg:postcode":"BN2 9SG",
    "sg:province":"East Sussex",
    "sg:tags":[
        "recording",
        "studio"
    ],
    "wof:name":"Lumen Soundsmiths",
    "wof:placetype":"venue"
},
  "geometry": {"coordinates":[-0.126242,50.82967],"type":"Point"}
}