{
  "type": "Feature",
  "properties": {
    "iso:country":"GB",
    "sg:address":"64 Elwyn Road",
    "sg:city":"March",
    "sg:classifiers":[
        {
            "category":"Farming",
            "subcategory":"Farm",
            "type":"Manufacturing & Wholesale Goods"
        }
    ],
    "sg:phone":"+44 1326 280080",
    "sg:postcode":"PE15 9DB",
    "sg:province":"Cambridgeshire",
    "sg:tags":[
        "mixed",
        "crop"
    ],
    "wof:name":"Exmoor Farming Co. Ltd.",
    "wof:placetype":"venue"
},
  "geometry": {"coordinates":[0.092701,52.545895],"type":"Point"}
}