{
  "type": "Feature",
  "properties": {
    "iso:country":"GB",
    "sg:address":"The Old Post Office, Church Street",
    "sg:city":"Oswestry",
    "sg:classifiers":[
        {
            "category":"Structure",
            "subcategory":"Warehouse",
            "type":"Public Place"
        }
    ],
    "sg:phone":"+44 1691 670390",
    "sg:postcode":"SY10 9QE",
    "sg:province":"Shropshire",
    "wof:name":"Kirkhams",
    "wof:placetype":"venue"
},
  "geometry": {"coordinates":[-3.1028199196,52.8325996399],"type":"Point"}
}