{
  "type": "Feature",
  "properties": {
    "iso:country":"GB",
    "sg:address":"Abbotsford Road",
    "sg:city":"Galashiels",
    "sg:classifiers":[
        {
            "category":"Professional",
            "subcategory":"Art Services",
            "type":"Services"
        }
    ],
    "sg:postcode":"TD1 3DS",
    "sg:province":"Scottish Borders",
    "sg:tags":[
        "carver",
        "sculptor"
    ],
    "wof:name":"George S Sutherland",
    "wof:placetype":"venue"
},
  "geometry": {"coordinates":[-2.801994,55.611599],"type":"Point"}
}