{
  "type": "Feature",
  "properties": {
    "addr:full":"53 Drumau Road, Birchgrove Swansea Neath Port Talbot SA7 9QA",
    "addr:housenumber":"53",
    "addr:postcode":"sa7 9qa",
    "addr:street":"Drumau Road",
    "iso:country":"GB",
    "sg:address":"53 Drumau Road, Birchgrove",
    "sg:city":"Swansea",
    "sg:classifiers":[
        {
            "category":"Shopping",
            "subcategory":"Computers & Home Electronics",
            "type":"Retail Goods"
        }
    ],
    "sg:phone":"+44 1792 815093",
    "sg:postcode":"SA7 9QA",
    "sg:province":"Neath Port Talbot",
    "sg:tags":[
        "aerial",
        "television",
        "radio"
    ],
    "wof:name":"G Benton",
    "wof:placetype":"venue"
},
  "geometry": {"coordinates":[-3.8696420193,51.6676368713],"type":"Point"}
}