{
  "type": "Feature",
  "properties": {
    "addr:full":"25 Mayo Road, Sherwood Nottingham Nottinghamshire NG5 1BL",
    "addr:housenumber":"25",
    "addr:postcode":"ng5 1bl",
    "addr:street":"Mayo Road",
    "iso:country":"GB",
    "sg:address":"25 Mayo Road, Sherwood",
    "sg:city":"Nottingham",
    "sg:classifiers":[
        {
            "category":"Health Services",
            "subcategory":"Nursing And Care Facility",
            "type":"Services"
        }
    ],
    "sg:phone":"+44 115 962 1100",
    "sg:postcode":"NG5 1BL",
    "sg:province":"Nottinghamshire",
    "sg:tags":[
        "home"
    ],
    "wof:name":"Arden Lea Nursing Home",
    "wof:placetype":"venue"
},
  "geometry": {"coordinates":[-1.158777,52.973999],"type":"Point"}
}