{
  "type": "Feature",
  "properties": {
    "iso:country":"GB",
    "sg:address":"The Farm Yard, Castle Ashby",
    "sg:city":"Northampton",
    "sg:classifiers":[
        {
            "category":"Professional",
            "type":"Services"
        },
        {
            "category":"Farming",
            "subcategory":"Farm",
            "type":"Manufacturing & Wholesale Goods"
        }
    ],
    "sg:phone":"+44 1604 696787",
    "sg:postcode":"NN7 1LF",
    "sg:province":"Buckinghamshire",
    "sg:tags":[
        "interior",
        "furnishers",
        "designer",
        "mixed",
        "crop"
    ],
    "wof:name":"Jeffrey S Wright Fine Paintings",
    "wof:placetype":"venue"
},
  "geometry": {"coordinates":[-0.7412490249,52.2262535095],"type":"Point"}
}