{
  "type": "Feature",
  "properties": {
    "iso:country":"GB",
    "sg:address":"5 Guildown Rd",
    "sg:city":"Guildford",
    "sg:classifiers":[
        {
            "category":"Utilities",
            "subcategory":"Mobile Phone",
            "type":"Services"
        }
    ],
    "sg:postcode":"GU2 4EW",
    "sg:province":"Surrey",
    "sg:tags":[
        "battery",
        "supplier"
    ],
    "wof:name":"Weylec",
    "wof:placetype":"venue"
},
  "geometry": {"coordinates":[-0.580213,51.227722],"type":"Point"}
}