{
  "type": "Feature",
  "properties": {
    "iso:country":"GB",
    "sg:address":"Humfrey Lodge, Rochelle Close, Thaxted",
    "sg:city":"Dunmow",
    "sg:classifiers":[
        {
            "category":"Health Services",
            "subcategory":"Nursing And Care Facility",
            "type":"Services"
        },
        {
            "category":"Government",
            "subcategory":"Office",
            "type":"Public Place"
        }
    ],
    "sg:phone":"+44 1371 830878",
    "sg:postcode":"CM6 2PX",
    "sg:province":"Essex",
    "sg:tags":[
        "residential",
        "local"
    ],
    "wof:name":"ESSEX COUNTY COUNCIL",
    "wof:placetype":"venue"
},
  "geometry": {"coordinates":[0.344765,51.953163],"type":"Point"}
}