{
  "type": "Feature",
  "properties": {
    "addr:full":"75 High Street Blackwood Caerphilly NP2 1YX",
    "addr:housenumber":"75",
    "addr:postcode":"np2 1yx",
    "addr:street":"High Street",
    "iso:country":"GB",
    "sg:address":"75 High Street",
    "sg:city":"Blackwood",
    "sg:classifiers":[
        {
            "category":"Government",
            "subcategory":"Office",
            "type":"Public Place"
        }
    ],
    "sg:phone":"+44 1495 232600",
    "sg:postcode":"NP2 1YX",
    "sg:province":"Caerphilly",
    "sg:tags":[
        "local"
    ],
    "wof:name":"Department for Work & Pensions",
    "wof:placetype":"venue"
},
  "geometry": {"coordinates":[-3.195947,51.66758],"type":"Point"}
}