{
  "type": "Feature",
  "properties": {
    "addr:full":"31 Staveley Avenue Stalybridge Greater Manchester SK15 1BU",
    "addr:housenumber":"31",
    "addr:postcode":"sk15 1bu",
    "addr:street":"Staveley Avenue",
    "iso:country":"GB",
    "sg:address":"31 Staveley Avenue",
    "sg:city":"Stalybridge",
    "sg:classifiers":[
        {
            "category":"Building & Trades",
            "subcategory":"Construction",
            "type":"Services"
        }
    ],
    "sg:phone":"+44 161 343 3428",
    "sg:postcode":"SK15 1BU",
    "sg:province":"Greater Manchester",
    "sg:tags":[
        "builder"
    ],
    "wof:name":"P B Builders",
    "wof:placetype":"venue"
},
  "geometry": {"coordinates":[-2.057463,53.489559],"type":"Point"}
}