{
  "type": "Feature",
  "properties": {
    "iso:country":"GB",
    "sg:address":"Station Road, Salwick",
    "sg:city":"Preston",
    "sg:classifiers":[
        {
            "category":"Bars & Pubs",
            "type":"Food & Drink"
        }
    ],
    "sg:phone":"+44 1772 687203",
    "sg:postcode":"PR4 0YH",
    "sg:province":"Lancashire",
    "sg:tags":[
        "pubs",
        "house",
        "inn",
        "public",
        "activity"
    ],
    "wof:name":"The Windmill Tavern",
    "wof:placetype":"venue"
},
  "geometry": {"coordinates":[-2.8158960342,53.7879447937],"type":"Point"}
}