{
  "type": "Feature",
  "properties": {
    "addr:full":"White Rose Way, Doncaster Carr Industrial Estate Doncaster South Yorkshire DN4 5JH",
    "addr:postcode":"dn4 5jh",
    "addr:street":"Rose Way;Carr Industrial Estate",
    "iso:country":"GB",
    "sg:address":"White Rose Way, Doncaster Carr Industrial Estate",
    "sg:city":"Doncaster",
    "sg:classifiers":[
        {
            "category":"Autos & Motor Vehicles",
            "subcategory":"Automobile Sales",
            "type":"Retail Goods"
        }
    ],
    "sg:phone":"+44 1302 304100",
    "sg:postcode":"DN4 5JH",
    "sg:province":"South Yorkshire",
    "sg:tags":[
        "car"
    ],
    "wof:name":"Reg Vardy Renault",
    "wof:placetype":"venue"
},
  "geometry": {"coordinates":[-1.1149890423,53.501209259],"type":"Point"}
}