{
  "type": "Feature",
  "properties": {
    "addr:full":"13 King Street, Brierfield Nelson Lancashire BB9 5PN",
    "addr:housenumber":"13",
    "addr:postcode":"bb9 5pn",
    "addr:street":"King Street",
    "iso:country":"GB",
    "sg:address":"13 King Street, Brierfield",
    "sg:city":"Nelson",
    "sg:classifiers":[
        {
            "category":"Building & Trades",
            "subcategory":"Construction",
            "type":"Services"
        }
    ],
    "sg:postcode":"BB9 5PN",
    "sg:province":"Lancashire",
    "sg:tags":[
        "builder"
    ],
    "wof:name":"Attention to Detail",
    "wof:placetype":"venue"
},
  "geometry": {"coordinates":[-2.237673,53.82338],"type":"Point"}
}