{
  "type": "Feature",
  "properties": {
    "iso:country":"GB",
    "sg:address":"Gooder Lane",
    "sg:city":"Brighouse",
    "sg:classifiers":[
        {
            "category":"Retail",
            "subcategory":"Auto Repair",
            "type":"Services"
        }
    ],
    "sg:postcode":"HD6 1HT",
    "sg:province":"West Yorkshire",
    "sg:tags":[
        "modification",
        "garage"
    ],
    "wof:name":"Victoria Garage",
    "wof:placetype":"venue"
},
  "geometry": {"coordinates":[-1.780489,53.698078],"type":"Point"}
}