{
  "type": "Feature",
  "properties": {
    "iso:country":"GB",
    "sg:address":"147-150 Charles Henry St",
    "sg:city":"Birmingham",
    "sg:classifiers":[
        {
            "category":"Military Area",
            "subcategory":"Air Force Base",
            "type":"Public Place"
        }
    ],
    "sg:phone":"+44 870 570 8060",
    "sg:postcode":"B12 0SD",
    "sg:province":"West Midlands",
    "sg:tags":[
        "taxi",
        "hire",
        "private"
    ],
    "wof:name":"Cabs Direct",
    "wof:placetype":"venue"
},
  "geometry": {"coordinates":[-1.8897110224,52.4702835083],"type":"Point"}
}