{
  "type": "Feature",
  "properties": {
    "iso:country":"GB",
    "sg:address":"11 Eldon Close, Audenshaw",
    "sg:city":"Manchester",
    "sg:classifiers":[
        {
            "category":"Parking",
            "type":"Transportation"
        }
    ],
    "sg:phone":"+44 161 292 3359",
    "sg:postcode":"M34 5FD",
    "sg:province":"Greater Manchester",
    "sg:tags":[
        "car",
        "valet"
    ],
    "wof:name":"C B S Mobile Valeting Services",
    "wof:placetype":"venue"
},
  "geometry": {"coordinates":[-2.114182,53.470516],"type":"Point"}
}