{
  "type": "Feature",
  "properties": {
    "iso:country":"GB",
    "sg:address":"North Devon Heritage Coast, Council Offices, Northfield Rd",
    "sg:city":"Ilfracombe",
    "sg:classifiers":[
        {
            "category":"Government",
            "subcategory":"Office",
            "type":"Public Place"
        }
    ],
    "sg:phone":"+44 1271 867496",
    "sg:postcode":"EX34 8AL",
    "sg:province":"Devon",
    "sg:tags":[
        "local"
    ],
    "wof:name":"Devon County Council",
    "wof:placetype":"venue"
},
  "geometry": {"coordinates":[-4.1235542297,51.2081604004],"type":"Point"}
}