{
  "type": "Feature",
  "properties": {
    "addr:full":"95 Sherwood Rd Grimsby Lincolnshire DN34 5TQ",
    "addr:housenumber":"95",
    "addr:postcode":"dn34 5tq",
    "addr:street":"Sherwood Rd",
    "iso:country":"GB",
    "sg:address":"95 Sherwood Rd",
    "sg:city":"Grimsby",
    "sg:classifiers":[
        {
            "category":"Government",
            "subcategory":"Post Office",
            "type":"Public Place"
        }
    ],
    "sg:phone":"+44 1472 276979",
    "sg:postcode":"DN34 5TQ",
    "sg:province":"Lincolnshire",
    "sg:tags":[
        "messenger",
        "courier"
    ],
    "wof:name":"ETL Couriers",
    "wof:placetype":"venue"
},
  "geometry": {"coordinates":[-0.117851,53.554142],"type":"Point"}
}