{
  "type": "Feature",
  "properties": {
    "iso:country":"GB",
    "sg:address":"3-4 Lawe Road",
    "sg:city":"South Shields",
    "sg:classifiers":[
        {
            "category":"Travel",
            "subcategory":"Hotels & Motels",
            "type":"Entertainment"
        }
    ],
    "sg:phone":"+44 191 455 5800",
    "sg:postcode":"NE33 2JN",
    "sg:province":"Tyne and Wear",
    "sg:tags":[
        "house",
        "guest"
    ],
    "wof:name":"The Park Hotel",
    "wof:placetype":"venue"
},
  "geometry": {"coordinates":[-1.424208045,55.0006942749],"type":"Point"}
}