{
  "type": "Feature",
  "properties": {
    "addr:full":"Stablegate Way Market Harborough Leicestershire LE16 8FA",
    "addr:postcode":"le16 8fa",
    "addr:street":"Stablegate Way",
    "iso:country":"GB",
    "sg:address":"Stablegate Way",
    "sg:city":"Market Harborough",
    "sg:classifiers":[
        {
            "category":"Shopping",
            "subcategory":"Party Supplies",
            "type":"Retail Goods"
        }
    ],
    "sg:postcode":"LE16 8FA",
    "sg:province":"Leicestershire",
    "sg:tags":[
        "inflatables",
        "bouncy",
        "castle"
    ],
    "wof:name":"Tumbledowns",
    "wof:placetype":"venue"
},
  "geometry": {"coordinates":[-0.906443,52.476437],"type":"Point"}
}