{
  "type": "Feature",
  "properties": {
    "addr:full":"63 Halfpenny Lane Knaresborough North Yorkshire HG5 0NS",
    "addr:housenumber":"63",
    "addr:postcode":"hg5 0ns",
    "addr:street":"Halfpenny Lane",
    "iso:country":"GB",
    "sg:address":"63 Halfpenny Lane",
    "sg:city":"Knaresborough",
    "sg:classifiers":[
        {
            "category":"Building & Trades",
            "subcategory":"Construction",
            "type":"Services"
        }
    ],
    "sg:postcode":"HG5 0NS",
    "sg:province":"North Yorkshire",
    "sg:tags":[
        "builder"
    ],
    "wof:name":"S L Pedel & Sons",
    "wof:placetype":"venue"
},
  "geometry": {"coordinates":[-1.461428,54.017815],"type":"Point"}
}