{
  "type": "Feature",
  "properties": {
    "addr:full":"Thamesbourne Lodge, Station Rd Bourne End Berkshire SL8 5QH",
    "addr:postcode":"sl8 5qh",
    "addr:street":"Station Rd",
    "iso:country":"GB",
    "sg:address":"Thamesbourne Lodge, Station Rd",
    "sg:city":"Bourne End",
    "sg:classifiers":[
        {
            "category":"Shopping",
            "subcategory":"Computers & Home Electronics",
            "type":"Retail Goods"
        },
        {
            "category":"Professional",
            "subcategory":"Computer Services",
            "type":"Services"
        }
    ],
    "sg:phone":"+44 1628 522516",
    "sg:postcode":"SL8 5QH",
    "sg:province":"Berkshire",
    "sg:tags":[
        "system",
        "software"
    ],
    "wof:name":"Netguard U K Ltd",
    "wof:placetype":"venue"
},
  "geometry": {"coordinates":[-0.7131739855,51.5795059204],"type":"Point"}
}