{
  "type": "Feature",
  "properties": {
    "addr:full":"5 High Street, Honeybourne Evesham Gloucestershire WR11 7PQ",
    "addr:housenumber":"5",
    "addr:postcode":"wr11 7pq",
    "addr:street":"High Street",
    "iso:country":"GB",
    "sg:address":"5 High Street, Honeybourne",
    "sg:city":"Evesham",
    "sg:classifiers":[
        {
            "category":"Real Estate",
            "subcategory":"Architect",
            "type":"Services"
        }
    ],
    "sg:postcode":"WR11 7PQ",
    "sg:province":"Gloucestershire",
    "wof:name":"John C Goom",
    "wof:placetype":"venue"
},
  "geometry": {"coordinates":[-1.8990939856,52.0885391235],"type":"Point"}
}