{
  "type": "Feature",
  "properties": {
    "addr:full":"Unit 6-7 Otterham Quay Lane Gillingham Kent ME8 7UX",
    "addr:housenumber":"unit 6-7",
    "addr:postcode":"me8 7ux",
    "addr:street":"Otterham Quay Lane",
    "iso:country":"GB",
    "sg:address":"Unit 6-7 Otterham Quay Lane",
    "sg:city":"Gillingham",
    "sg:classifiers":[
        {
            "category":"Retail",
            "subcategory":"Auto Repair",
            "type":"Services"
        }
    ],
    "sg:phone":"+44 1634 361666",
    "sg:postcode":"ME8 7UX",
    "sg:province":"Kent",
    "sg:tags":[
        "body",
        "car"
    ],
    "wof:name":"Kar Kraft",
    "wof:placetype":"venue"
},
  "geometry": {"coordinates":[0.629848,51.37328],"type":"Point"}
}