{
  "type": "Feature",
  "properties": {
    "addr:full":"2-4 City Rd Bristol City of Bristol BS2 8TP",
    "addr:housenumber":"2-4",
    "addr:postcode":"bs2 8tp",
    "addr:street":"City Rd",
    "iso:country":"GB",
    "sg:address":"2-4 City Rd",
    "sg:city":"Bristol",
    "sg:classifiers":[
        {
            "category":"Place Of Worship",
            "type":"Public Place"
        }
    ],
    "sg:phone":"+44 117 942 5811",
    "sg:postcode":"BS2 8TP",
    "sg:province":"City of Bristol",
    "wof:name":"City Road Baptist Church",
    "wof:placetype":"venue"
},
  "geometry": {"coordinates":[-2.589885,51.462021],"type":"Point"}
}