{
  "type": "Feature",
  "properties": {
    "addr:full":"38a Greenwood Street Altrincham Cheshire WA14 1RZ",
    "addr:housenumber":"38a",
    "addr:postcode":"wa14 1rz",
    "addr:street":"Greenwood Street",
    "iso:country":"GB",
    "sg:address":"38a Greenwood Street",
    "sg:city":"Altrincham",
    "sg:classifiers":[
        {
            "category":"Autos & Motor Vehicles",
            "subcategory":"Boat Sales",
            "type":"Retail Goods"
        }
    ],
    "sg:postcode":"WA14 1RZ",
    "sg:province":"Cheshire",
    "sg:tags":[
        "surveyor",
        "yacht"
    ],
    "wof:name":"Marker & Eccles Ltd.",
    "wof:placetype":"venue"
},
  "geometry": {"coordinates":[-2.352175,53.38665],"type":"Point"}
}