{
  "type": "Feature",
  "properties": {
    "addr:full":"6 Cross Street Ellesmere Shropshire SY12 0AR",
    "addr:housenumber":"6",
    "addr:postcode":"sy12 0ar",
    "addr:street":"Cross Street",
    "iso:country":"GB",
    "sg:address":"6 Cross Street",
    "sg:city":"Ellesmere",
    "sg:classifiers":[
        {
            "category":"Deli",
            "type":"Food & Drink"
        }
    ],
    "sg:phone":"+44 1691 622521",
    "sg:postcode":"SY12 0AR",
    "sg:province":"Shropshire",
    "sg:tags":[
        "delicatessen"
    ],
    "wof:name":"Vermeulen & Son",
    "wof:placetype":"venue"
},
  "geometry": {"coordinates":[-2.893001,52.908035],"type":"Point"}
}