{
  "type": "Feature",
  "properties": {
    "iso:country":"GB",
    "sg:address":"16 St Jude's Avenue, Mapperley",
    "sg:city":"Nottingham",
    "sg:classifiers":[
        {
            "category":"Building & Trades",
            "subcategory":"Construction",
            "type":"Services"
        }
    ],
    "sg:phone":"+44 115 952 5441",
    "sg:postcode":"NG3 5FG",
    "sg:province":"Nottinghamshire",
    "sg:tags":[
        "decorator",
        "painter"
    ],
    "wof:name":"Jeff Taylor Decorating",
    "wof:placetype":"venue"
},
  "geometry": {"coordinates":[-1.13826,52.977718],"type":"Point"}
}