{
  "type": "Feature",
  "properties": {
    "iso:country":"GB",
    "sg:address":"The Cattle Market, St Oswald Road",
    "sg:city":"Gloucester",
    "sg:classifiers":[
        {
            "category":"Building & Trades",
            "subcategory":"Equipment Rental",
            "type":"Services"
        }
    ],
    "sg:phone":"+44 1452 500959",
    "sg:postcode":"GL1 2SR",
    "sg:province":"Gloucestershire",
    "sg:tags":[
        "plant",
        "machinery"
    ],
    "wof:name":"Hewden Plant Hire Ltd.",
    "wof:placetype":"venue"
},
  "geometry": {"coordinates":[-2.2496240139,51.8638114929],"type":"Point"}
}