{
  "type": "Feature",
  "properties": {
    "iso:country":"GB",
    "sg:address":"Unit 1 The Horns Trading Estate, Bromyard Road",
    "sg:city":"Tenbury Wells",
    "sg:classifiers":[
        {
            "category":"Shopping",
            "subcategory":"Hobbies, Toys, & Games",
            "type":"Retail Goods"
        }
    ],
    "sg:postcode":"WR15 8DE",
    "sg:province":"Herefordshire",
    "sg:tags":[
        "shop",
        "toy"
    ],
    "wof:name":"Toy City",
    "wof:placetype":"venue"
},
  "geometry": {"coordinates":[-2.594178915,52.3125839233],"type":"Point"}
}