{
  "type": "Feature",
  "properties": {
    "addr:full":"20 Hiltons Arcade Oldham Lancashire OL1 3AQ",
    "addr:housenumber":"20;arcade",
    "addr:postcode":"ol1 3aq",
    "addr:street":"Hiltons",
    "iso:country":"GB",
    "sg:address":"20 Hiltons Arcade",
    "sg:city":"Oldham",
    "sg:classifiers":[
        {
            "category":"Shopping",
            "subcategory":"Baby Store",
            "type":"Retail Goods"
        }
    ],
    "sg:postcode":"OL1 3AQ",
    "sg:province":"Lancashire",
    "sg:tags":[
        "babywear",
        "childrens"
    ],
    "wof:name":"Jumping Jacks",
    "wof:placetype":"venue"
},
  "geometry": {"coordinates":[-2.1195631027,53.5329780579],"type":"Point"}
}