{
  "type": "Feature",
  "properties": {
    "addr:full":"89 Trafalgar Street Brighton East Sussex BN1 4ER",
    "addr:housenumber":"89",
    "addr:postcode":"bn1 4er",
    "addr:street":"Trafalgar Street",
    "iso:country":"GB",
    "sg:address":"89 Trafalgar Street",
    "sg:city":"Brighton",
    "sg:classifiers":[
        {
            "category":"Transit Center",
            "subcategory":"Freight",
            "type":"Transportation"
        }
    ],
    "sg:phone":"+44 1273 628440",
    "sg:postcode":"BN1 4ER",
    "sg:province":"East Sussex",
    "sg:tags":[
        "shop",
        "craft",
        "centre"
    ],
    "wof:name":"Arkham",
    "wof:placetype":"venue"
},
  "geometry": {"coordinates":[-0.1377239972,50.8282356262],"type":"Point"}
}