{
  "type": "Feature",
  "properties": {
    "iso:country":"GB",
    "sg:address":"Stadhampton, Ascott",
    "sg:city":"Oxford",
    "sg:classifiers":[
        {
            "category":"Farming",
            "subcategory":"Livestock Farm",
            "type":"Manufacturing & Wholesale Goods"
        }
    ],
    "sg:postcode":"OX44 7UH",
    "sg:province":"Oxfordshire",
    "sg:tags":[
        "others"
    ],
    "wof:name":"P Colegrave",
    "wof:placetype":"venue"
},
  "geometry": {"coordinates":[-1.114083,51.680107],"type":"Point"}
}