{
  "type": "Feature",
  "properties": {
    "addr:full":"Friths Cottage, Bacup Road Todmorden Lancashire OL14 7PJ",
    "addr:postcode":"ol14 7pj",
    "addr:street":"Bacup Road",
    "iso:country":"GB",
    "sg:address":"Friths Cottage, Bacup Road",
    "sg:city":"Todmorden",
    "sg:classifiers":[
        {
            "category":"Health Services",
            "subcategory":"Podiatrist",
            "type":"Services"
        }
    ],
    "sg:phone":"+44 1706 818808",
    "sg:postcode":"OL14 7PJ",
    "sg:province":"Lancashire",
    "sg:tags":[
        "podiatrists",
        "chiropodist"
    ],
    "wof:name":"M B Sherry Chiropodist",
    "wof:placetype":"venue"
},
  "geometry": {"coordinates":[-2.0973079205,53.7143096924],"type":"Point"}
}