{
  "type": "Feature",
  "properties": {
    "addr:full":"The Spinney Old Hall Lane, Fradley Grn Lichfield Staffordshire WS13 8PA",
    "addr:postcode":"ws13 8pa",
    "addr:street":"The Spinney Old Hall Lane",
    "iso:country":"GB",
    "sg:address":"The Spinney Old Hall Lane, Fradley Grn",
    "sg:city":"Lichfield",
    "sg:classifiers":[
        {
            "category":"Professional",
            "subcategory":"Advertising",
            "type":"Services"
        }
    ],
    "sg:phone":"+44 1283 791415",
    "sg:postcode":"WS13 8PA",
    "sg:province":"Staffordshire",
    "wof:name":"Denson Edwards",
    "wof:placetype":"venue"
},
  "geometry": {"coordinates":[-1.762938,52.720444],"type":"Point"}
}