{
  "type": "Feature",
  "properties": {
    "iso:country":"GB",
    "sg:address":"Unit 9, Shamrock Enterprise Centre, Wingate Road",
    "sg:city":"Gosport",
    "sg:classifiers":[
        {
            "category":"Professional",
            "subcategory":"Engineering",
            "type":"Services"
        }
    ],
    "sg:phone":"+44 23 9250 3532",
    "sg:postcode":"PO12 4DP",
    "sg:province":"Hampshire",
    "sg:tags":[
        "precision",
        "engineer"
    ],
    "wof:name":"Concept (Design & Engineering) Ltd.",
    "wof:placetype":"venue"
},
  "geometry": {"coordinates":[-1.1215339899,50.7943611145],"type":"Point"}
}