{
  "type": "Feature",
  "properties": {
    "iso:country":"GB",
    "sg:address":"64-65a Market St",
    "sg:city":"Haddington",
    "sg:classifiers":[
        {
            "category":"Professional",
            "subcategory":"Art Services",
            "type":"Services"
        }
    ],
    "sg:phone":"+44 1620 823176",
    "sg:postcode":"EH41 3JG",
    "sg:province":"East Lothian",
    "sg:tags":[
        "framing"
    ],
    "wof:name":"Freelance Frames",
    "wof:placetype":"venue"
},
  "geometry": {"coordinates":[-2.7768449783,55.9558868408],"type":"Point"}
}