{
  "type": "Feature",
  "properties": {
    "addr:full":"Millwalk, Thurlow Street, Walworth London Greater London SE17 2UB",
    "addr:postcode":"se17 2ub",
    "addr:street":"Thurlow Street",
    "iso:country":"GB",
    "sg:address":"Millwalk, Thurlow Street, Walworth",
    "sg:city":"London",
    "sg:classifiers":[
        {
            "category":"Government",
            "subcategory":"Office",
            "type":"Public Place"
        }
    ],
    "sg:phone":"+44 20 7525 5820",
    "sg:postcode":"SE17 2UB",
    "sg:province":"Greater London",
    "sg:tags":[
        "local"
    ],
    "wof:name":"Taplow Neighbourhood Office",
    "wof:placetype":"venue"
},
  "geometry": {"coordinates":[-0.095332,51.4874],"type":"Point"}
}