{
  "type": "Feature",
  "properties": {
    "addr:full":"Wenallt Bungalow, Candwr Road, Ponthir Newport Monmouthshire NP18 1HR",
    "addr:postcode":"np18 1hr",
    "addr:street":"Candwr Road",
    "iso:country":"GB",
    "sg:address":"Wenallt Bungalow, Candwr Road, Ponthir",
    "sg:city":"Newport",
    "sg:classifiers":[
        {
            "category":"Transit Center",
            "subcategory":"Passenger",
            "type":"Transportation"
        }
    ],
    "sg:phone":"+44 1633 422895",
    "sg:postcode":"NP18 1HR",
    "sg:province":"Monmouthshire",
    "sg:tags":[
        "boarding",
        "kennel",
        "catteries"
    ],
    "wof:name":"Brookside",
    "wof:placetype":"venue"
},
  "geometry": {"coordinates":[-2.97201,51.629665],"type":"Point"}
}