{
  "type": "Feature",
  "properties": {
    "iso:country":"GB",
    "sg:address":"Fairlop Road",
    "sg:city":"London",
    "sg:classifiers":[
        {
            "category":"Health Services",
            "subcategory":"Doctor",
            "type":"Services"
        },
        {
            "category":"Health Services",
            "subcategory":"Clinic",
            "type":"Services"
        }
    ],
    "sg:phone":"+44 20 8539 2513",
    "sg:postcode":"E11 1BN",
    "sg:province":"Greater London",
    "sg:tags":[
        "nh",
        "practitioners"
    ],
    "wof:name":"Allum Medical Centre",
    "wof:placetype":"venue"
},
  "geometry": {"coordinates":[0.001233,51.570831],"type":"Point"}
}