{
  "type": "Feature",
  "properties": {
    "iso:country":"GB",
    "sg:address":"Leafland Street Works",
    "sg:city":"Halifax",
    "sg:classifiers":[
        {
            "category":"Professional",
            "subcategory":"Engineering",
            "type":"Services"
        }
    ],
    "sg:phone":"+44 1422 352698",
    "sg:postcode":"HX1 4LX",
    "sg:province":"West Yorkshire",
    "wof:name":"William B Swift Ltd.",
    "wof:placetype":"venue"
},
  "geometry": {"coordinates":[-1.880098,53.722332],"type":"Point"}
}