{
  "type": "Feature",
  "properties": {
    "addr:full":"73 Lloyds Av Lowestoft Suffolk NR33 7TS",
    "addr:housenumber":"73",
    "addr:postcode":"nr33 7ts",
    "addr:street":"Lloyds Av",
    "iso:country":"GB",
    "sg:address":"73 Lloyds Av",
    "sg:city":"Lowestoft",
    "sg:classifiers":[
        {
            "category":"Shopping",
            "subcategory":"Computers & Home Electronics",
            "type":"Retail Goods"
        }
    ],
    "sg:phone":"+44 1502 740559",
    "sg:postcode":"NR33 7TS",
    "sg:province":"Suffolk",
    "sg:tags":[
        "equipment",
        "video",
        "cctv"
    ],
    "wof:name":"Alan Morrison Security Devices Ltd",
    "wof:placetype":"venue"
},
  "geometry": {"coordinates":[1.713135004,52.4188842773],"type":"Point"}
}