{
  "type": "Feature",
  "properties": {
    "addr:full":"127 Jamaica Road London Greater London SE16 4SH",
    "addr:housenumber":"127",
    "addr:postcode":"se16 4sh",
    "addr:street":"Jamaica Road",
    "iso:country":"GB",
    "sg:address":"127 Jamaica Road",
    "sg:city":"London",
    "sg:classifiers":[
        {
            "category":"Building & Trades",
            "subcategory":"Plumbing",
            "type":"Services"
        }
    ],
    "sg:postcode":"SE16 4SH",
    "sg:province":"Greater London",
    "sg:tags":[
        "heating"
    ],
    "wof:name":"Brown,A G & R J,",
    "wof:placetype":"venue"
},
  "geometry": {"coordinates":[-0.06581,51.498142],"type":"Point"}
}