{
  "type": "Feature",
  "properties": {
    "addr:full":"P O Box 8408, Lewisham London Greater London SE13 5ZH",
    "addr:housenumber":"p o;8408",
    "addr:postcode":"se13 5zh",
    "iso:country":"GB",
    "sg:address":"P O Box 8408, Lewisham",
    "sg:city":"London",
    "sg:classifiers":[
        {
            "category":"Professional",
            "subcategory":"Art Services",
            "type":"Services"
        }
    ],
    "sg:postcode":"SE13 5ZH",
    "sg:province":"Greater London",
    "sg:tags":[
        "photographer"
    ],
    "wof:name":"Campbwell,Cherylin,",
    "wof:placetype":"venue"
},
  "geometry": {"coordinates":[-0.0031600001,51.4576187134],"type":"Point"}
}