{
  "type": "Feature",
  "properties": {
    "iso:country":"GB",
    "sg:address":"156 Hockley Hill",
    "sg:city":"Birmingham",
    "sg:classifiers":[
        {
            "category":"Professional",
            "subcategory":"Engineering",
            "type":"Services"
        }
    ],
    "sg:phone":"+44 121 523 2044",
    "sg:postcode":"B18 5AN",
    "sg:province":"West Midlands",
    "sg:tags":[
        "consulting",
        "design",
        "engineer"
    ],
    "wof:name":"R.B. Hinton and Associates Limited",
    "wof:placetype":"venue"
},
  "geometry": {"coordinates":[-1.913158,52.493717],"type":"Point"}
}