{
  "type": "Feature",
  "properties": {
    "addr:full":"Unit 3 Enterprise Estate, Chapman Way Tunbridge Wells East Sussex TN2 3EF",
    "addr:housenumber":"unit 3",
    "addr:postcode":"tn2 3ef",
    "addr:street":"Enterprise Estate Chapman Way",
    "iso:country":"GB",
    "sg:address":"Unit 3 Enterprise Estate, Chapman Way",
    "sg:city":"Tunbridge Wells",
    "sg:classifiers":[
        {
            "category":"Shopping",
            "subcategory":"Optical Goods",
            "type":"Retail Goods"
        }
    ],
    "sg:postcode":"TN2 3EF",
    "sg:province":"East Sussex",
    "sg:tags":[
        "medical"
    ],
    "wof:name":"Norville Optical Co. Ltd.",
    "wof:placetype":"venue"
},
  "geometry": {"coordinates":[0.27736,51.15242],"type":"Point"}
}