{
  "type": "Feature",
  "properties": {
    "iso:country":"GB",
    "sg:address":"5-7 Market Place",
    "sg:city":"Shipston-on-stour",
    "sg:classifiers":[
        {
            "category":"Professional",
            "type":"Services"
        }
    ],
    "sg:phone":"+44 1608 661545",
    "sg:postcode":"CV36 4AG",
    "sg:province":"Warwickshire",
    "sg:tags":[
        "caterer"
    ],
    "wof:name":"Bruce's Catering",
    "wof:placetype":"venue"
},
  "geometry": {"coordinates":[-1.624466,52.063538],"type":"Point"}
}