{
  "type": "Feature",
  "properties": {
    "addr:full":"Haydock Lane, Haydock St. Helens St. Helens Lancashire WA11 9UY",
    "addr:postcode":"wa11 9uy",
    "addr:street":"Haydock Lane Haydock",
    "iso:country":"GB",
    "sg:address":"Haydock Lane, Haydock St. Helens",
    "sg:city":"St. Helens",
    "sg:classifiers":[
        {
            "category":"Manufacturing",
            "subcategory":"Rubber & Plastics",
            "type":"Manufacturing & Wholesale Goods"
        }
    ],
    "sg:phone":"+44 1942 270908",
    "sg:postcode":"WA11 9UY",
    "sg:province":"Lancashire",
    "sg:tags":[
        "product"
    ],
    "wof:name":"A B R Plastics",
    "wof:placetype":"venue"
},
  "geometry": {"coordinates":[-2.670074,53.473404],"type":"Point"}
}