{
  "type": "Feature",
  "properties": {
    "addr:full":"Lythe, St Margarets Hope Orkney Orkney Islands KW17 2RN",
    "addr:postcode":"kw17 2rn",
    "iso:country":"GB",
    "sg:address":"Lythe, St Margarets Hope",
    "sg:city":"Orkney",
    "sg:classifiers":[
        {
            "category":"Farming",
            "subcategory":"Livestock Farm",
            "type":"Manufacturing & Wholesale Goods"
        }
    ],
    "sg:postcode":"KW17 2RN",
    "sg:province":"Orkney Islands",
    "sg:tags":[
        "others"
    ],
    "wof:name":"M & E Tomison",
    "wof:placetype":"venue"
},
  "geometry": {"coordinates":[-2.9429941177,58.7921867371],"type":"Point"}
}