{
  "type": "Feature",
  "properties": {
    "iso:country":"GB",
    "sg:address":"34 Queen St",
    "sg:city":"Newton-le-willows",
    "sg:classifiers":[
        {
            "category":"Shopping",
            "subcategory":"Clothing, Apparel, & Fashions",
            "type":"Retail Goods"
        }
    ],
    "sg:postcode":"WA12 9AZ",
    "sg:province":"Cheshire",
    "sg:tags":[
        "shop",
        "dress",
        "fancy"
    ],
    "wof:name":"Avery,Betty,",
    "wof:placetype":"venue"
},
  "geometry": {"coordinates":[-2.6398010254,53.451587677],"type":"Point"}
}