{
  "type": "Feature",
  "properties": {
    "addr:full":"123 Southend Croydon Surrey CR0 1BJ",
    "addr:housenumber":"123",
    "addr:postcode":"cr0 1bj",
    "addr:street":"Southend",
    "iso:country":"GB",
    "sg:address":"123 Southend",
    "sg:city":"Croydon",
    "sg:classifiers":[
        {
            "category":"Professional",
            "subcategory":"Secretarial Services",
            "type":"Services"
        }
    ],
    "sg:phone":"+44 20 8688 4440",
    "sg:postcode":"CR0 1BJ",
    "sg:province":"Surrey",
    "wof:name":"The Secretary",
    "wof:placetype":"venue"
},
  "geometry": {"coordinates":[-0.0980100036,51.3638000488],"type":"Point"}
}