{
  "type": "Feature",
  "properties": {
    "addr:full":"School Road, Portessie Buckie Moray AB56 1TN",
    "addr:postcode":"ab56 1tn",
    "addr:street":"School Road",
    "iso:country":"GB",
    "sg:address":"School Road, Portessie",
    "sg:city":"Buckie",
    "sg:classifiers":[
        {
            "category":"Education",
            "subcategory":"School",
            "type":"Public Place"
        },
        {
            "category":"Government",
            "subcategory":"Office",
            "type":"Public Place"
        }
    ],
    "sg:phone":"+44 1542 832288",
    "sg:postcode":"AB56 1TN",
    "sg:province":"Moray",
    "sg:tags":[
        "local",
        "authority"
    ],
    "wof:name":"Portessie Primary School",
    "wof:placetype":"venue"
},
  "geometry": {"coordinates":[-2.965224,57.676701],"type":"Point"}
}