{
  "type": "Feature",
  "properties": {
    "addr:full":"266 Ashton Road Oldham Lancashire OL8 1QN",
    "addr:housenumber":"266",
    "addr:postcode":"ol8 1qn",
    "addr:street":"Ashton Road",
    "iso:country":"GB",
    "sg:address":"266 Ashton Road",
    "sg:city":"Oldham",
    "sg:classifiers":[
        {
            "category":"Personal",
            "subcategory":"Beauty Salon",
            "type":"Services"
        }
    ],
    "sg:postcode":"OL8 1QN",
    "sg:province":"Lancashire",
    "sg:tags":[
        "unisex",
        "hairdresser"
    ],
    "wof:name":"Rose Bowl Hair & Beauty Salon",
    "wof:placetype":"venue"
},
  "geometry": {"coordinates":[-2.1121621132,53.5284729004],"type":"Point"}
}