{
  "type": "Feature",
  "properties": {
    "addr:full":"10 Parsons St, Adderbury Banbury Northamptonshire OX17 3LX",
    "addr:housenumber":"10",
    "addr:postcode":"ox17 3lx",
    "addr:street":"Parsons St",
    "iso:country":"GB",
    "sg:address":"10 Parsons St, Adderbury",
    "sg:city":"Banbury",
    "sg:classifiers":[
        {
            "category":"Wholesale",
            "subcategory":"Vending Machines",
            "type":"Manufacturing & Wholesale Goods"
        }
    ],
    "sg:phone":"+44 70 7453 6273",
    "sg:postcode":"OX17 3LX",
    "sg:province":"Northamptonshire",
    "sg:tags":[
        "generator"
    ],
    "wof:name":"P.L..M. Lighting",
    "wof:placetype":"venue"
},
  "geometry": {"coordinates":[-1.3146569729,52.0162467957],"type":"Point"}
}