{
  "type": "Feature",
  "properties": {
    "addr:full":"Webnor Industrial Estate, Ettingshall Road Wolverhampton West Midlands WV2 2LD",
    "addr:postcode":"wv2 2ld",
    "addr:street":"Estate Ettingshall Road",
    "iso:country":"GB",
    "sg:address":"Webnor Industrial Estate, Ettingshall Road",
    "sg:city":"Wolverhampton",
    "sg:classifiers":[
        {
            "category":"Shopping",
            "subcategory":"Stationery & Office Supplies",
            "type":"Retail Goods"
        }
    ],
    "sg:postcode":"WV2 2LD",
    "sg:province":"West Midlands",
    "wof:name":"Parker Office Supplies Ltd.",
    "wof:placetype":"venue"
},
  "geometry": {"coordinates":[-2.102959,52.56855],"type":"Point"}
}