{
  "type": "Feature",
  "properties": {
    "iso:country":"GB",
    "sg:address":"Unit 12 Kirkbride Airfield",
    "sg:city":"Carlisle",
    "sg:classifiers":[
        {
            "category":"Farming",
            "subcategory":"Livestock Farm",
            "type":"Manufacturing & Wholesale Goods"
        }
    ],
    "sg:phone":"+44 16973 51295",
    "sg:postcode":"CA5 5HP",
    "sg:province":"Cumbria",
    "sg:tags":[
        "breeder"
    ],
    "wof:name":"Vivienne Cole",
    "wof:placetype":"venue"
},
  "geometry": {"coordinates":[-3.18639,54.94788],"type":"Point"}
}