{
  "type": "Feature",
  "properties": {
    "addr:full":"Carbost Village, Carbost Isle Of Skye Highland IV47 8SR",
    "addr:postcode":"iv47 8sr",
    "addr:street":"Carbost;Carbost",
    "iso:country":"GB",
    "sg:address":"Carbost Village, Carbost",
    "sg:city":"Isle Of Skye",
    "sg:classifiers":[
        {
            "category":"Education",
            "subcategory":"School",
            "type":"Public Place"
        },
        {
            "category":"Government",
            "subcategory":"Office",
            "type":"Public Place"
        }
    ],
    "sg:phone":"+44 1478 640237",
    "sg:postcode":"IV47 8SR",
    "sg:province":"Highland",
    "sg:tags":[
        "local",
        "authority"
    ],
    "wof:name":"Carbost Primary School",
    "wof:placetype":"venue"
},
  "geometry": {"coordinates":[-6.3562488556,57.3029594421],"type":"Point"}
}