{
  "type": "Feature",
  "properties": {
    "iso:country":"GB",
    "sg:address":"70 Surtees Street",
    "sg:city":"Bishop Auckland",
    "sg:classifiers":[
        {
            "category":"Home & Garden",
            "subcategory":"Household Appliances",
            "type":"Retail Goods"
        }
    ],
    "sg:phone":"+44 1388 602279",
    "sg:postcode":"DL14 7DJ",
    "sg:province":"Durham",
    "sg:tags":[
        "electrical"
    ],
    "wof:name":"Colin Young",
    "wof:placetype":"venue"
},
  "geometry": {"coordinates":[-1.679123044,54.6622924805],"type":"Point"}
}