{
  "type": "Feature",
  "properties": {
    "iso:country":"GB",
    "sg:address":"The Forge, Hempshaw Lane",
    "sg:city":"Stockport",
    "sg:classifiers":[
        {
            "category":"Home & Garden",
            "subcategory":"Building Materials",
            "type":"Retail Goods"
        }
    ],
    "sg:phone":"+44 161 480 6305",
    "sg:postcode":"SK1 4PF",
    "sg:province":"Cheshire",
    "sg:tags":[
        "ironwork",
        "diy",
        "wrought"
    ],
    "wof:name":"John Finnigan",
    "wof:placetype":"venue"
},
  "geometry": {"coordinates":[-2.1401000023,53.4018783569],"type":"Point"}
}