{
  "type": "Feature",
  "properties": {
    "addr:full":"Wickness Lockerbie Dumfries and Galloway DG11 1DX",
    "addr:postcode":"dg11 1dx",
    "iso:country":"GB",
    "sg:address":"Wickness",
    "sg:city":"Lockerbie",
    "sg:classifiers":[
        {
            "category":"Building & Trades",
            "subcategory":"Equipment Rental",
            "type":"Services"
        }
    ],
    "sg:phone":"+44 1387 840221",
    "sg:postcode":"DG11 1DX",
    "sg:province":"Dumfries and Galloway",
    "sg:tags":[
        "plant",
        "machinery"
    ],
    "wof:name":"Solway Plant",
    "wof:placetype":"venue"
},
  "geometry": {"coordinates":[-3.420439,55.12104],"type":"Point"}
}