{
  "type": "Feature",
  "properties": {
    "addr:full":"41 Greenwich Church Street London Greater London SE10 9BL",
    "addr:housenumber":"41",
    "addr:postcode":"se10 9bl",
    "addr:street":"Greenwich Church Street",
    "iso:country":"GB",
    "sg:address":"41 Greenwich Church Street",
    "sg:city":"London",
    "sg:classifiers":[
        {
            "category":"Shopping",
            "subcategory":"News",
            "type":"Retail Goods"
        }
    ],
    "sg:postcode":"SE10 9BL",
    "sg:province":"Greater London",
    "sg:tags":[
        "newsagent"
    ],
    "wof:name":"Cutty Sark Newsagents",
    "wof:placetype":"venue"
},
  "geometry": {"coordinates":[-0.010247,51.481514],"type":"Point"}
}