{
  "type": "Feature",
  "properties": {
    "iso:country":"GB",
    "sg:address":"Gorse Industrial Estate, Barnham",
    "sg:city":"Thetford",
    "sg:classifiers":[
        {
            "category":"Retail",
            "subcategory":"Auto Repair",
            "type":"Services"
        }
    ],
    "sg:postcode":"IP24 2PH",
    "sg:province":"Norfolk",
    "sg:tags":[
        "modification",
        "garage"
    ],
    "wof:name":"Gorse Motors Ltd.",
    "wof:placetype":"venue"
},
  "geometry": {"coordinates":[0.74055,52.378857],"type":"Point"}
}