{
  "type": "Feature",
  "properties": {
    "iso:country":"GB",
    "sg:address":"Club House, Penygroes Road, Blaenau",
    "sg:city":"Ammanford",
    "sg:classifiers":[
        {
            "category":"Arena",
            "subcategory":"Sports Club",
            "type":"Entertainment"
        }
    ],
    "sg:phone":"+44 1269 850229",
    "sg:postcode":"SA18 3BZ",
    "sg:province":"Carmarthenshire",
    "wof:name":"Blaenau Rugby Club",
    "wof:placetype":"venue"
},
  "geometry": {"coordinates":[-3.988945,51.792397],"type":"Point"}
}