{
  "type": "Feature",
  "properties": {
    "addr:full":"Abbey St Dorchester Dorset DT2 7JQ",
    "addr:postcode":"dt2 7jq",
    "addr:street":"Abbey St",
    "iso:country":"GB",
    "sg:address":"Abbey St",
    "sg:city":"Dorchester",
    "sg:classifiers":[
        {
            "category":"Place Of Worship",
            "type":"Public Place"
        }
    ],
    "sg:phone":"+44 1300 341251",
    "sg:postcode":"DT2 7JQ",
    "sg:province":"Dorset",
    "wof:name":"St Mary C Of E Church",
    "wof:placetype":"venue"
},
  "geometry": {"coordinates":[-2.476006,50.809933],"type":"Point"}
}