{
  "type": "Feature",
  "properties": {
    "addr:full":"Bampton Road, Aston Bampton Gloucestershire OX18 2BT",
    "addr:postcode":"ox18 2bt",
    "addr:street":"Bampton Road",
    "iso:country":"GB",
    "sg:address":"Bampton Road, Aston",
    "sg:city":"Bampton",
    "sg:classifiers":[
        {
            "category":"Farming",
            "subcategory":"Livestock Farm",
            "type":"Manufacturing & Wholesale Goods"
        }
    ],
    "sg:postcode":"OX18 2BT",
    "sg:province":"Gloucestershire",
    "sg:tags":[
        "others"
    ],
    "wof:name":"Edward Baughan",
    "wof:placetype":"venue"
},
  "geometry": {"coordinates":[-1.546758,51.727924],"type":"Point"}
}