{
  "type": "Feature",
  "properties": {
    "addr:full":"6 Thornsett Road Sheffield South Yorkshire S7 1NA",
    "addr:housenumber":"6",
    "addr:postcode":"s7 1na",
    "addr:street":"Thornsett Road",
    "iso:country":"GB",
    "sg:address":"6 Thornsett Road",
    "sg:city":"Sheffield",
    "sg:classifiers":[
        {
            "category":"Organizations",
            "subcategory":"Membership Organization",
            "type":"Services"
        }
    ],
    "sg:phone":"+44 114 255 0844",
    "sg:postcode":"S7 1NA",
    "sg:province":"South Yorkshire",
    "sg:tags":[
        "club",
        "social"
    ],
    "wof:name":"Sheffield Bridge Club",
    "wof:placetype":"venue"
},
  "geometry": {"coordinates":[-1.482989,53.365112],"type":"Point"}
}