{
  "type": "Feature",
  "properties": {
    "iso:country":"GB",
    "sg:address":"Higher Town Farm, Eworthy, Germansweek",
    "sg:city":"Beaworthy",
    "sg:classifiers":[
        {
            "category":"Farming",
            "subcategory":"Livestock Farm",
            "type":"Manufacturing & Wholesale Goods"
        }
    ],
    "sg:phone":"+44 1837 871283",
    "sg:postcode":"EX21 5AH",
    "sg:province":"Devon",
    "sg:tags":[
        "others"
    ],
    "wof:name":"Higher Town Farm",
    "wof:placetype":"venue"
},
  "geometry": {"coordinates":[-4.1833848953,50.7753067017],"type":"Point"}
}