{
  "type": "Feature",
  "properties": {
    "iso:country":"GB",
    "sg:address":"26 Richmond Hill",
    "sg:city":"Richmond",
    "sg:classifiers":[
        {
            "category":"Arts & Performance",
            "subcategory":"Art Gallery",
            "type":"Entertainment"
        }
    ],
    "sg:phone":"+44 20 8940 2435",
    "sg:postcode":"TW10 6QX",
    "sg:province":"Greater London",
    "wof:name":"Piano Nobile Fine Paintings",
    "wof:placetype":"venue"
},
  "geometry": {"coordinates":[-0.302969,51.456722],"type":"Point"}
}