{
  "type": "Feature",
  "properties": {
    "addr:full":"St John's Farm, Brooks Green Horsham West Sussex RH13 0JN",
    "addr:postcode":"rh13 0jn",
    "addr:street":"Brooks Green",
    "iso:country":"GB",
    "sg:address":"St John's Farm, Brooks Green",
    "sg:city":"Horsham",
    "sg:classifiers":[
        {
            "category":"Banks & Credit Unions",
            "subcategory":"Investment Brokerage",
            "type":"Services"
        }
    ],
    "sg:postcode":"RH13 0JN",
    "sg:province":"West Sussex",
    "sg:tags":[
        "contractor"
    ],
    "wof:name":"Peter M Healy",
    "wof:placetype":"venue"
},
  "geometry": {"coordinates":[-0.3887299895,51.0156784058],"type":"Point"}
}