{
  "type": "Feature",
  "properties": {
    "addr:full":"101 Marsh Lane Bootle Merseyside L20 4JB",
    "addr:housenumber":"101",
    "addr:postcode":"l20 4jb",
    "addr:street":"Marsh Lane",
    "iso:country":"GB",
    "sg:address":"101 Marsh Lane",
    "sg:city":"Bootle",
    "sg:classifiers":[
        {
            "category":"Shopping",
            "subcategory":"News",
            "type":"Retail Goods"
        }
    ],
    "sg:phone":"+44 151 287 7235",
    "sg:postcode":"L20 4JB",
    "sg:province":"Merseyside",
    "sg:tags":[
        "newsagent"
    ],
    "wof:name":"Dunne's Newsagents",
    "wof:placetype":"venue"
},
  "geometry": {"coordinates":[-3.001275,53.455479],"type":"Point"}
}