{
  "type": "Feature",
  "properties": {
    "iso:country":"GB",
    "sg:address":"Scott St",
    "sg:city":"Stanley",
    "sg:classifiers":[
        {
            "category":"Health Services",
            "subcategory":"Clinic",
            "type":"Services"
        }
    ],
    "sg:phone":"+44 1207 232384",
    "sg:postcode":"DH9 8AD",
    "sg:province":"Durham",
    "sg:tags":[
        "nh"
    ],
    "wof:name":"Tanfield View Surgery",
    "wof:placetype":"venue"
},
  "geometry": {"coordinates":[-1.7007499933,54.8692321777],"type":"Point"}
}