{
  "type": "Feature",
  "properties": {
    "iso:country":"GB",
    "sg:address":"21 Wilmar Close",
    "sg:city":"Uxbridge",
    "sg:classifiers":[
        {
            "category":"Professional",
            "subcategory":"Management & Consulting",
            "type":"Services"
        }
    ],
    "sg:postcode":"UB8 1AS",
    "sg:province":"Buckinghamshire",
    "sg:tags":[
        "consultant",
        "business"
    ],
    "wof:name":"Suburban Consultants Ltd",
    "wof:placetype":"venue"
},
  "geometry": {"coordinates":[-0.478967011,51.5485305786],"type":"Point"}
}