{
  "type": "Feature",
  "properties": {
    "addr:full":"8b High Street, Cosham Portsmouth Hampshire PO6 3BZ",
    "addr:housenumber":"8b",
    "addr:postcode":"hampshire po6 3bz",
    "addr:street":"High Street Cosham",
    "iso:country":"GB",
    "sg:address":"8b High Street, Cosham",
    "sg:city":"Portsmouth",
    "sg:classifiers":[
        {
            "category":"Home & Garden",
            "subcategory":"Home Furnishings",
            "type":"Retail Goods"
        }
    ],
    "sg:postcode":"PO6 3BZ",
    "sg:province":"Hampshire",
    "sg:tags":[
        "beds",
        "bedding",
        "blanket"
    ],
    "wof:name":"Findons Beds",
    "wof:placetype":"venue"
},
  "geometry": {"coordinates":[-1.0671390295,50.8451004028],"type":"Point"}
}