{
  "type": "Feature",
  "properties": {
    "addr:full":"Unit 9-11 Halls Rd Tarding Est Bristol City of Bristol BS15 2JD",
    "addr:housenumber":"9-11",
    "addr:postcode":"bs15 2jd",
    "addr:street":"Halls Rd;Est",
    "iso:country":"GB",
    "sg:address":"Unit 9-11 Halls Rd Tarding Est",
    "sg:city":"Bristol",
    "sg:classifiers":[
        {
            "category":"Wholesale",
            "subcategory":"Vending Machines",
            "type":"Manufacturing & Wholesale Goods"
        }
    ],
    "sg:phone":"+44 117 961 1546",
    "sg:postcode":"BS15 2JD",
    "sg:province":"City of Bristol",
    "sg:tags":[
        "sale"
    ],
    "wof:name":"Strategic Services Ltd",
    "wof:placetype":"venue"
},
  "geometry": {"coordinates":[-2.5038199425,51.4523086548],"type":"Point"}
}