{
  "type": "Feature",
  "properties": {
    "iso:country":"GB",
    "sg:address":"1 Abbots Drive",
    "sg:city":"Wirral",
    "sg:classifiers":[
        {
            "category":"Health Services",
            "subcategory":"Nursing And Care Facility",
            "type":"Services"
        }
    ],
    "sg:phone":"+44 151 643 1591",
    "sg:postcode":"CH63 3BW",
    "sg:province":"Merseyside",
    "sg:tags":[
        "home"
    ],
    "wof:name":"Safe Harbour Nursing Home",
    "wof:placetype":"venue"
},
  "geometry": {"coordinates":[-3.00983,53.349808],"type":"Point"}
}