{
  "type": "Feature",
  "properties": {
    "addr:full":"186 Kennington Park Road London Greater London SE11 4BT",
    "addr:housenumber":"186",
    "addr:postcode":"se11 4bt",
    "addr:street":"Kennington Park Road",
    "iso:country":"GB",
    "sg:address":"186 Kennington Park Road",
    "sg:city":"London",
    "sg:classifiers":[
        {
            "category":"Organizations",
            "subcategory":"Non-profit Organization",
            "type":"Services"
        }
    ],
    "sg:phone":"+44 20 7207 2100",
    "sg:postcode":"SE11 4BT",
    "sg:province":"Greater London",
    "sg:tags":[
        "charitable",
        "organisation",
        "voluntary",
        "charity"
    ],
    "wof:name":"The Evangelical Alliance",
    "wof:placetype":"venue"
},
  "geometry": {"coordinates":[-0.109126,51.485462],"type":"Point"}
}