{
  "type": "Feature",
  "properties": {
    "iso:country":"GB",
    "sg:address":"Summerton Farm, Carew",
    "sg:city":"Tenby",
    "sg:classifiers":[
        {
            "category":"Farming",
            "subcategory":"Farm",
            "type":"Manufacturing & Wholesale Goods"
        }
    ],
    "sg:postcode":"SA70 8NS",
    "sg:province":"Pembrokeshire",
    "sg:tags":[
        "mixed",
        "crop"
    ],
    "wof:name":"G L Mathias",
    "wof:placetype":"venue"
},
  "geometry": {"coordinates":[-4.712056,51.6768],"type":"Point"}
}