{
  "type": "Feature",
  "properties": {
    "addr:full":"67 Alkington Rd Whitchurch Cheshire SY13 1SU",
    "addr:housenumber":"67",
    "addr:postcode":"sy13 1su",
    "addr:street":"Alkington Rd",
    "iso:country":"GB",
    "sg:address":"67 Alkington Rd",
    "sg:city":"Whitchurch",
    "sg:classifiers":[
        {
            "category":"Shopping",
            "subcategory":"Department Store",
            "type":"Retail Goods"
        }
    ],
    "sg:phone":"+44 1948 665229",
    "sg:postcode":"SY13 1SU",
    "sg:province":"Cheshire",
    "wof:name":"Alkington Stores",
    "wof:placetype":"venue"
},
  "geometry": {"coordinates":[-2.686609,52.964081],"type":"Point"}
}