{
  "type": "Feature",
  "properties": {
    "addr:full":"72 Brocket Way Chigwell Essex IG7 4ES",
    "addr:housenumber":"72",
    "addr:postcode":"ig7 4es",
    "addr:street":"Brocket Way",
    "iso:country":"GB",
    "sg:address":"72 Brocket Way",
    "sg:city":"Chigwell",
    "sg:classifiers":[
        {
            "category":"Personal",
            "type":"Services"
        }
    ],
    "sg:postcode":"IG7 4ES",
    "sg:province":"Essex",
    "sg:tags":[
        "wedding"
    ],
    "wof:name":"Supreme Catering Wedding Group",
    "wof:placetype":"venue"
},
  "geometry": {"coordinates":[0.1019480005,51.6123275757],"type":"Point"}
}