{
  "type": "Feature",
  "properties": {
    "addr:full":"3 Millers Yard, Church Square Market Harborough Leicestershire LE16 7PW",
    "addr:housenumber":"3",
    "addr:postcode":"le16 7pw",
    "addr:street":"Millers Yard Church Square",
    "iso:country":"GB",
    "sg:address":"3 Millers Yard, Church Square",
    "sg:city":"Market Harborough",
    "sg:classifiers":[
        {
            "category":"Real Estate",
            "subcategory":"Architect",
            "type":"Services"
        }
    ],
    "sg:phone":"+44 1858 410151",
    "sg:postcode":"LE16 7PW",
    "sg:province":"Leicestershire",
    "wof:name":"Henderson Scott",
    "wof:placetype":"venue"
},
  "geometry": {"coordinates":[-0.9225789905,52.4793968201],"type":"Point"}
}