{
  "type": "Feature",
  "properties": {
    "iso:country":"GB",
    "sg:address":"2 Grove Arc",
    "sg:city":"Wilmslow",
    "sg:classifiers":[
        {
            "category":"Shopping",
            "subcategory":"Gifts & Souvenirs",
            "type":"Retail Goods"
        }
    ],
    "sg:phone":"+44 1625 549008",
    "sg:postcode":"SK9 1HB",
    "sg:province":"Cheshire",
    "sg:tags":[
        "poster",
        "card"
    ],
    "wof:name":"Greetings",
    "wof:placetype":"venue"
},
  "geometry": {"coordinates":[-2.2308399677,53.3275146484],"type":"Point"}
}