{
  "type": "Feature",
  "properties": {
    "addr:full":"1a Albert Road Southsea Hampshire PO5 2SE",
    "addr:housenumber":"1a",
    "addr:postcode":"po5 2se",
    "addr:street":"Albert Road",
    "iso:country":"GB",
    "sg:address":"1a Albert Road",
    "sg:city":"Southsea",
    "sg:classifiers":[
        {
            "category":"Organizations",
            "subcategory":"Political Organization",
            "type":"Services"
        }
    ],
    "sg:phone":"+44 23 9286 1055",
    "sg:postcode":"PO5 2SE",
    "sg:province":"Hampshire",
    "sg:tags":[
        "party"
    ],
    "wof:name":"The Liberal Democrat Party",
    "wof:placetype":"venue"
},
  "geometry": {"coordinates":[-1.082407,50.7887],"type":"Point"}
}