{
  "type": "Feature",
  "properties": {
    "addr:full":"Waggoners Court, The Street, Manuden Bishops Stortford Essex CM23 1DW",
    "addr:postcode":"cm23 1dw",
    "addr:street":"Waggoners;The Street",
    "iso:country":"GB",
    "sg:address":"Waggoners Court, The Street, Manuden",
    "sg:city":"Bishops Stortford",
    "sg:classifiers":[
        {
            "category":"Professional",
            "subcategory":"Engineering",
            "type":"Services"
        }
    ],
    "sg:phone":"+44 1279 813700",
    "sg:postcode":"CM23 1DW",
    "sg:province":"Essex",
    "sg:tags":[
        "consultant",
        "structural"
    ],
    "wof:name":"Roberts Hay Partnership",
    "wof:placetype":"venue"
},
  "geometry": {"coordinates":[0.135667,51.947353],"type":"Point"}
}