{
  "type": "Feature",
  "properties": {
    "addr:full":"Parkers Farm, Warish Hall Road, Takeley Bishops Stortford Essex CM22 6NY",
    "addr:postcode":"cm22 6ny",
    "addr:street":"Hall Road",
    "iso:country":"GB",
    "sg:address":"Parkers Farm, Warish Hall Road, Takeley",
    "sg:city":"Bishops Stortford",
    "sg:classifiers":[
        {
            "category":"Professional",
            "type":"Services"
        },
        {
            "category":"Banks & Credit Unions",
            "subcategory":"Investment Brokerage",
            "type":"Services"
        }
    ],
    "sg:phone":"+44 1279 870345",
    "sg:postcode":"CM22 6NY",
    "sg:province":"Essex",
    "sg:tags":[
        "farm",
        "agricultural",
        "contractor"
    ],
    "wof:name":"G A Coleman & Partners",
    "wof:placetype":"venue"
},
  "geometry": {"coordinates":[0.2668350041,51.8677711487],"type":"Point"}
}