{
  "type": "Feature",
  "properties": {
    "addr:full":"Dental Surgery, Rose Garth, Brewery La Stafford Staffordshire ST18 0SN",
    "addr:postcode":"st18 0sn",
    "addr:street":"Rose;La",
    "iso:country":"GB",
    "sg:address":"Dental Surgery, Rose Garth, Brewery La",
    "sg:city":"Stafford",
    "sg:classifiers":[
        {
            "category":"Health Services",
            "subcategory":"Dentist",
            "type":"Services"
        }
    ],
    "sg:phone":"+44 1889 882873",
    "sg:postcode":"ST18 0SN",
    "sg:province":"Staffordshire",
    "wof:name":"Peter Nadin",
    "wof:placetype":"venue"
},
  "geometry": {"coordinates":[-2.0034101009,52.802570343],"type":"Point"}
}