{
  "type": "Feature",
  "properties": {
    "addr:full":"189 Barns Road, Templar Square Shopping Centre, Cowley Oxford Oxfordshire OX4 3UT",
    "addr:housenumber":"189",
    "addr:postcode":"ox4 3ut",
    "addr:street":"Barns Road Templar Square Shopping",
    "iso:country":"GB",
    "sg:address":"189 Barns Road, Templar Square Shopping Centre, Cowley",
    "sg:city":"Oxford",
    "sg:classifiers":[
        {
            "category":"Shopping",
            "subcategory":"Crafts & Fabrics",
            "type":"Retail Goods"
        }
    ],
    "sg:postcode":"OX4 3UT",
    "sg:province":"Oxfordshire",
    "sg:tags":[
        "shop",
        "needlecraft",
        "wool"
    ],
    "wof:name":"The Busy Bee",
    "wof:placetype":"venue"
},
  "geometry": {"coordinates":[-1.214612,51.731228],"type":"Point"}
}