{
  "type": "Feature",
  "properties": {
    "iso:country":"GB",
    "sg:address":"24 Blue Street",
    "sg:city":"Carmarthen",
    "sg:classifiers":[
        {
            "category":"Health Services",
            "subcategory":"Dentist",
            "type":"Services"
        }
    ],
    "sg:phone":"+44 1267 236091",
    "sg:postcode":"SA31 3LE",
    "sg:province":"Carmarthenshire",
    "wof:name":"S J Lewis",
    "wof:placetype":"venue"
},
  "geometry": {"coordinates":[-4.308241,51.855389],"type":"Point"}
}