{
  "type": "Feature",
  "properties": {
    "addr:full":"90 Thorpedene Gardens, Shoeburyness Southend-on-sea Essex SS3 9JD",
    "addr:housenumber":"90",
    "addr:postcode":"ss3 9jd",
    "addr:street":"Thorpedene Gardens",
    "iso:country":"GB",
    "sg:address":"90 Thorpedene Gardens, Shoeburyness",
    "sg:city":"Southend-on-sea",
    "sg:classifiers":[
        {
            "category":"Place Of Worship",
            "type":"Public Place"
        }
    ],
    "sg:phone":"+44 1702 292620",
    "sg:postcode":"SS3 9JD",
    "sg:province":"Essex",
    "wof:name":"Shoeburyness & Thorpe Bay baptist Church",
    "wof:placetype":"venue"
},
  "geometry": {"coordinates":[0.777187,51.530838],"type":"Point"}
}