{
  "type": "Feature",
  "properties": {
    "addr:full":"15 Knockbuckle Avenue Kilmacolm Inverclyde PA13 4JB",
    "addr:housenumber":"15",
    "addr:postcode":"pa13 4jb",
    "addr:street":"Knockbuckle Avenue",
    "iso:country":"GB",
    "sg:address":"15 Knockbuckle Avenue",
    "sg:city":"Kilmacolm",
    "sg:classifiers":[
        {
            "category":"Building & Trades",
            "subcategory":"Plumbing",
            "type":"Services"
        }
    ],
    "sg:phone":"+44 1475 783311",
    "sg:postcode":"PA13 4JB",
    "sg:province":"Inverclyde",
    "sg:tags":[
        "heating"
    ],
    "wof:name":"W Kirkwood",
    "wof:placetype":"venue"
},
  "geometry": {"coordinates":[-4.6414518356,55.8951454163],"type":"Point"}
}