{
  "type": "Feature",
  "properties": {
    "iso:country":"GB",
    "sg:address":"Business Station, Commercial Road",
    "sg:city":"Hereford",
    "sg:classifiers":[
        {
            "category":"Personal",
            "subcategory":"Beauty Salon",
            "type":"Services"
        }
    ],
    "sg:phone":"+44 1432 267124",
    "sg:postcode":"HR1 2BL",
    "sg:province":"Herefordshire",
    "sg:tags":[
        "unisex",
        "hairdresser"
    ],
    "wof:name":"Cervantis Hair Fashions",
    "wof:placetype":"venue"
},
  "geometry": {"coordinates":[-2.70965,52.058262],"type":"Point"}
}