{
  "type": "Feature",
  "properties": {
    "addr:full":"P O Box 245 Slough Berkshire SL1 4YT",
    "addr:housenumber":"245",
    "addr:postcode":"sl1 4yt",
    "addr:street":"P O Box",
    "iso:country":"GB",
    "sg:address":"P O Box 245",
    "sg:city":"Slough",
    "sg:classifiers":[
        {
            "category":"Communications",
            "subcategory":"Film & Video Production",
            "type":"Services"
        }
    ],
    "sg:phone":"+44 1923 268081",
    "sg:postcode":"SL1 4YT",
    "sg:province":"Berkshire",
    "sg:tags":[
        "tv"
    ],
    "wof:name":"Dial-a-TV (RG) Ltd",
    "wof:placetype":"venue"
},
  "geometry": {"coordinates":[-0.596417,51.507874],"type":"Point"}
}