{
  "type": "Feature",
  "properties": {
    "iso:country":"GB",
    "sg:address":"Resource Centre, Station Road",
    "sg:city":"Carmarthen",
    "sg:classifiers":[
        {
            "category":"Professional",
            "subcategory":"Employment Agencies",
            "type":"Services"
        }
    ],
    "sg:phone":"+44 1994 231866",
    "sg:postcode":"SA33 4BT",
    "sg:province":"Carmarthenshire",
    "sg:tags":[
        "consultant"
    ],
    "wof:name":"Carmarthenshire County Council",
    "wof:placetype":"venue"
},
  "geometry": {"coordinates":[-4.4895501137,51.823600769],"type":"Point"}
}