{
  "type": "Feature",
  "properties": {
    "iso:country":"GB",
    "sg:address":"Benzole House, 48 Old Wolverton Rd, Old Wolverton",
    "sg:city":"Milton Keynes",
    "sg:classifiers":[
        {
            "category":"Building & Trades",
            "subcategory":"Construction",
            "type":"Services"
        }
    ],
    "sg:phone":"+44 1908 225224",
    "sg:postcode":"MK12 5NL",
    "sg:province":"Buckinghamshire",
    "sg:tags":[
        "decorator",
        "painter"
    ],
    "wof:name":"W E Waterston Decorators",
    "wof:placetype":"venue"
},
  "geometry": {"coordinates":[-0.806285,52.067898],"type":"Point"}
}