{
  "type": "Feature",
  "properties": {
    "addr:full":"53 Albany Road, Hersham Walton-on-thames Surrey KT12 5QG",
    "addr:housenumber":"53",
    "addr:postcode":"kt12 5qg",
    "addr:street":"Albany Road",
    "iso:country":"GB",
    "sg:address":"53 Albany Road, Hersham",
    "sg:city":"Walton-on-thames",
    "sg:classifiers":[
        {
            "category":"Health Services",
            "subcategory":"Podiatrist",
            "type":"Services"
        }
    ],
    "sg:postcode":"KT12 5QG",
    "sg:province":"Surrey",
    "sg:tags":[
        "podiatrists",
        "chiropodist"
    ],
    "wof:name":"P M S Dougan",
    "wof:placetype":"venue"
},
  "geometry": {"coordinates":[-0.397768,51.369751],"type":"Point"}
}