{
  "type": "Feature",
  "properties": {
    "addr:full":"Alexandra House, 34 Reading Road South Fleet Hampshire GU52 7QL",
    "addr:housenumber":"34",
    "addr:postcode":"gu52 7ql",
    "addr:street":"Reading Road South Fleet",
    "iso:country":"GB",
    "sg:address":"Alexandra House, 34 Reading Road South",
    "sg:city":"Fleet",
    "sg:classifiers":[
        {
            "category":"Professional",
            "subcategory":"Detective & Security Services",
            "type":"Services"
        }
    ],
    "sg:phone":"+44 1252 624877",
    "sg:postcode":"GU52 7QL",
    "sg:province":"Hampshire",
    "sg:tags":[
        "equipment",
        "activity"
    ],
    "wof:name":"LOGIC SECURITY SYSTEMS LTD",
    "wof:placetype":"venue"
},
  "geometry": {"coordinates":[-0.8409489989,51.2751083374],"type":"Point"}
}