{
  "type": "Feature",
  "properties": {
    "addr:full":"A D C Ho, 47 Allesley Old Rd Coventry West Midlands CV5 8BU",
    "addr:housenumber":"47",
    "addr:postcode":"cv5 8bu",
    "addr:street":"D C Ho;Old Rd",
    "iso:country":"GB",
    "sg:address":"A D C Ho, 47 Allesley Old Rd",
    "sg:city":"Coventry",
    "sg:classifiers":[
        {
            "category":"Professional",
            "subcategory":"Computer Services",
            "type":"Services"
        }
    ],
    "sg:phone":"+44 24 7671 5858",
    "sg:postcode":"CV5 8BU",
    "sg:province":"West Midlands",
    "sg:tags":[
        "system",
        "software"
    ],
    "wof:name":"A D C Systems",
    "wof:placetype":"venue"
},
  "geometry": {"coordinates":[-1.5309000015,52.4082794189],"type":"Point"}
}