{
  "type": "Feature",
  "properties": {
    "iso:country":"GB",
    "sg:address":"37a Canterbury Road",
    "sg:city":"Worthing",
    "sg:classifiers":[
        {
            "category":"Education",
            "subcategory":"Special Training",
            "type":"Public Place"
        },
        {
            "category":"Professional",
            "subcategory":"Employment Agencies",
            "type":"Services"
        }
    ],
    "sg:phone":"+44 1903 263344",
    "sg:postcode":"BN13 1AN",
    "sg:province":"West Sussex",
    "sg:tags":[
        "consultant",
        "product",
        "centre"
    ],
    "wof:name":"Jarvis Bentley Recruitment",
    "wof:placetype":"venue"
},
  "geometry": {"coordinates":[-0.398043,50.819267],"type":"Point"}
}