{
  "type": "Feature",
  "properties": {
    "addr:full":"5 Canal Bridge Enterprise Centre, Meadow Lane Ellesmere Port Cheshire CH65 4EH",
    "addr:housenumber":"5;enterprise",
    "addr:postcode":"ch65 4eh",
    "addr:street":"Canal Bridge;Centre Meadow Lane",
    "iso:country":"GB",
    "sg:address":"5 Canal Bridge Enterprise Centre, Meadow Lane",
    "sg:city":"Ellesmere Port",
    "sg:classifiers":[
        {
            "category":"Home & Garden",
            "subcategory":"Home Furnishings",
            "type":"Retail Goods"
        }
    ],
    "sg:phone":"+44 151 355 2600",
    "sg:postcode":"CH65 4EH",
    "sg:province":"Cheshire",
    "sg:tags":[
        "household",
        "furniture"
    ],
    "wof:name":"Boyds Clearance House",
    "wof:placetype":"venue"
},
  "geometry": {"coordinates":[-2.905574,53.277199],"type":"Point"}
}