{
  "type": "Feature",
  "properties": {
    "addr:full":"Morlich Road, Dalgety Bay Dunfermline Fife KY11 9UE",
    "addr:postcode":"ky11 9ue",
    "addr:street":"Morlich Road",
    "iso:country":"GB",
    "sg:address":"Morlich Road, Dalgety Bay",
    "sg:city":"Dunfermline",
    "sg:classifiers":[
        {
            "category":"Education",
            "subcategory":"School",
            "type":"Public Place"
        },
        {
            "category":"Government",
            "subcategory":"Office",
            "type":"Public Place"
        }
    ],
    "sg:phone":"+44 1383 823552",
    "sg:postcode":"KY11 9UE",
    "sg:province":"Fife",
    "sg:tags":[
        "local",
        "authority"
    ],
    "wof:name":"Donibristle Primary School",
    "wof:placetype":"venue"
},
  "geometry": {"coordinates":[-3.3635380268,56.0424156189],"type":"Point"}
}