{
  "type": "Feature",
  "properties": {
    "addr:full":"4 Mapperley Lane, West Hallam Ilkeston Derbyshire DE7 6HN",
    "addr:housenumber":"4",
    "addr:postcode":"de7 6hn",
    "addr:street":"Mapperley Lane",
    "iso:country":"GB",
    "sg:address":"4 Mapperley Lane, West Hallam",
    "sg:city":"Ilkeston",
    "sg:classifiers":[
        {
            "category":"Retail",
            "subcategory":"Repair Shop",
            "type":"Services"
        }
    ],
    "sg:phone":"+44 115 932 6453",
    "sg:postcode":"DE7 6HN",
    "sg:province":"Derbyshire",
    "sg:tags":[
        "upholsterer"
    ],
    "wof:name":"Prince Upholstery",
    "wof:placetype":"venue"
},
  "geometry": {"coordinates":[-1.353703022,52.9757003784],"type":"Point"}
}