{
  "type": "Feature",
  "properties": {
    "addr:full":"Vicarage, Church La Cambridge Cambridgeshire CB2 4JR",
    "addr:postcode":"cb2 4jr",
    "addr:street":"La Cambridge",
    "iso:country":"GB",
    "sg:address":"Vicarage, Church La",
    "sg:city":"Cambridge",
    "sg:classifiers":[
        {
            "category":"Place Of Worship",
            "type":"Public Place"
        }
    ],
    "sg:phone":"+44 1223 832248",
    "sg:postcode":"CB2 4JR",
    "sg:province":"Cambridgeshire",
    "wof:name":"St Mary The Virgin",
    "wof:placetype":"venue"
},
  "geometry": {"coordinates":[0.144494,52.111561],"type":"Point"}
}