{
  "type": "Feature",
  "properties": {
    "iso:country":"GB",
    "sg:address":"33 Milton Road",
    "sg:city":"Rotherham",
    "sg:classifiers":[
        {
            "category":"Farming",
            "subcategory":"Fish & Marine Products",
            "type":"Manufacturing & Wholesale Goods"
        },
        {
            "category":"Food & Beverages",
            "subcategory":"Meat & Fish",
            "type":"Retail Goods"
        }
    ],
    "sg:phone":"+44 1709 364154",
    "sg:postcode":"S65 1QT",
    "sg:province":"South Yorkshire",
    "sg:tags":[
        "fishmonger",
        "butcher"
    ],
    "wof:name":"Robert M Knowles",
    "wof:placetype":"venue"
},
  "geometry": {"coordinates":[-1.345081,53.437313],"type":"Point"}
}