{
  "type": "Feature",
  "properties": {
    "addr:full":"The Pharmacy, 1 High Street Llangefni Gwynedd LL77 7LT",
    "addr:housenumber":"1",
    "addr:postcode":"ll77 7lt",
    "addr:street":"High Street",
    "iso:country":"GB",
    "sg:address":"The Pharmacy, 1 High Street",
    "sg:city":"Llangefni",
    "sg:classifiers":[
        {
            "category":"Shopping",
            "subcategory":"Pharmacy",
            "type":"Retail Goods"
        }
    ],
    "sg:phone":"+44 1248 722214",
    "sg:postcode":"LL77 7LT",
    "sg:province":"Gwynedd",
    "sg:tags":[
        "pharmacist",
        "dispensing",
        "chemist"
    ],
    "wof:name":"L Rowland & Co",
    "wof:placetype":"venue"
},
  "geometry": {"coordinates":[-4.3084640503,53.2556037903],"type":"Point"}
}