{
  "type": "Feature",
  "properties": {
    "addr:full":"9-11 Queens Parade Newcastle Staffordshire ST5 1RW",
    "addr:housenumber":"9-11",
    "addr:postcode":"st5 1rw",
    "addr:street":"Queens Parade",
    "iso:country":"GB",
    "sg:address":"9-11 Queens Parade",
    "sg:city":"Newcastle",
    "sg:classifiers":[
        {
            "category":"Parking",
            "type":"Transportation"
        },
        {
            "category":"Retail",
            "subcategory":"Auto Repair",
            "type":"Services"
        }
    ],
    "sg:phone":"+44 1782 719999",
    "sg:postcode":"ST5 1RW",
    "sg:province":"Staffordshire",
    "sg:tags":[
        "car",
        "upholsterer",
        "valet"
    ],
    "wof:name":"Direct Valeting Ltd.",
    "wof:placetype":"venue"
},
  "geometry": {"coordinates":[-2.2229630947,53.0144348145],"type":"Point"}
}