{
  "type": "Feature",
  "properties": {
    "addr:full":"The Triangle, Birchett Road Aldershot Hampshire GU11 1LS",
    "addr:postcode":"gu11 1ls",
    "addr:street":"Birchett Road",
    "iso:country":"GB",
    "sg:address":"The Triangle, Birchett Road",
    "sg:city":"Aldershot",
    "sg:classifiers":[
        {
            "category":"Military Area",
            "subcategory":"Air Force Base",
            "type":"Public Place"
        }
    ],
    "sg:postcode":"GU11 1LS",
    "sg:province":"Hampshire",
    "sg:tags":[
        "taxi",
        "hire",
        "private"
    ],
    "wof:name":"Melita Taxis",
    "wof:placetype":"venue"
},
  "geometry": {"coordinates":[-0.759346,51.249603],"type":"Point"}
}