{
  "type": "Feature",
  "properties": {
    "iso:country":"GB",
    "sg:address":"3 Mitcham Road",
    "sg:city":"London",
    "sg:classifiers":[
        {
            "category":"Food & Beverages",
            "subcategory":"Specialty",
            "type":"Retail Goods"
        }
    ],
    "sg:phone":"+44 20 8767 8552",
    "sg:postcode":"SW17 9PA",
    "sg:province":"Greater London",
    "sg:tags":[
        "product",
        "health"
    ],
    "wof:name":"Holland & Barrett",
    "wof:placetype":"venue"
},
  "geometry": {"coordinates":[-0.166569,51.426941],"type":"Point"}
}