{
  "type": "Feature",
  "properties": {
    "iso:country":"GB",
    "sg:address":"Unit 7 Boardman Indstl Est, Boardman Rd",
    "sg:city":"Swadlincote",
    "sg:classifiers":[
        {
            "category":"Retail",
            "subcategory":"Auto Repair",
            "type":"Services"
        }
    ],
    "sg:postcode":"DE11 9DL",
    "sg:province":"Derbyshire",
    "sg:tags":[
        "engine",
        "specialist",
        "garage",
        "modification",
        "car"
    ],
    "wof:name":"Phelps,S,",
    "wof:placetype":"venue"
},
  "geometry": {"coordinates":[-1.552209,52.774094],"type":"Point"}
}