{
  "type": "Feature",
  "properties": {
    "iso:country":"GB",
    "sg:address":"9 Churchfield Road",
    "sg:city":"London",
    "sg:classifiers":[
        {
            "category":"Professional",
            "type":"Services"
        }
    ],
    "sg:phone":"+44 20 8992 2007",
    "sg:postcode":"W3 6BH",
    "sg:province":"Greater London",
    "sg:tags":[
        "interior",
        "furnishers",
        "designer"
    ],
    "wof:name":"D'Abo & Co",
    "wof:placetype":"venue"
},
  "geometry": {"coordinates":[-0.2634429932,51.5087471008],"type":"Point"}
}