{
  "type": "Feature",
  "properties": {
    "addr:full":"32 Chertsey Road, Chobham Woking Surrey GU24 8PQ",
    "addr:housenumber":"32",
    "addr:postcode":"gu24 8pq",
    "addr:street":"Chertsey Road",
    "iso:country":"GB",
    "sg:address":"32 Chertsey Road, Chobham",
    "sg:city":"Woking",
    "sg:classifiers":[
        {
            "category":"Home & Garden",
            "subcategory":"Carpets & Floor Coverings",
            "type":"Retail Goods"
        }
    ],
    "sg:phone":"+44 1276 856441",
    "sg:postcode":"GU24 8PQ",
    "sg:province":"Surrey",
    "sg:tags":[
        "carpets",
        "rug",
        "matting"
    ],
    "wof:name":"Acs Carpets & Fabrics",
    "wof:placetype":"venue"
},
  "geometry": {"coordinates":[-0.5983909965,51.3498802185],"type":"Point"}
}