{
  "type": "Feature",
  "properties": {
    "iso:country":"GB",
    "sg:address":"135 Gipsy Lane",
    "sg:city":"Leicester",
    "sg:classifiers":[
        {
            "category":"Shopping",
            "subcategory":"Clothing, Apparel, & Fashions",
            "type":"Retail Goods"
        }
    ],
    "sg:phone":"+44 116 261 1122",
    "sg:postcode":"LE4 6RH",
    "sg:province":"Leicestershire",
    "sg:tags":[
        "clothing",
        "fabric"
    ],
    "wof:name":"Fashion Wear",
    "wof:placetype":"venue"
},
  "geometry": {"coordinates":[-1.105146,52.654282],"type":"Point"}
}