{
  "type": "Feature",
  "properties": {
    "iso:country":"GB",
    "sg:address":"4 Wellhead Lane",
    "sg:city":"Westbury",
    "sg:classifiers":[
        {
            "category":"Professional",
            "subcategory":"Secretarial Services",
            "type":"Services"
        },
        {
            "category":"Professional",
            "subcategory":"Art Services",
            "type":"Services"
        }
    ],
    "sg:phone":"+44 1373 823053",
    "sg:postcode":"BA13 3PW",
    "sg:province":"Wiltshire",
    "sg:tags":[
        "photographer"
    ],
    "wof:name":"Westbury Star Service",
    "wof:placetype":"venue"
},
  "geometry": {"coordinates":[-2.185841,51.253414],"type":"Point"}
}