{
  "type": "Feature",
  "properties": {
    "addr:full":"116 Victoria Rd Aldershot Hampshire GU11 1JX",
    "addr:housenumber":"116",
    "addr:postcode":"gu11 1jx",
    "addr:street":"Victoria Rd",
    "iso:country":"GB",
    "sg:address":"116 Victoria Rd",
    "sg:city":"Aldershot",
    "sg:classifiers":[
        {
            "category":"Banks & Credit Unions",
            "subcategory":"Financial Services",
            "type":"Services"
        }
    ],
    "sg:postcode":"GU11 1JX",
    "sg:province":"Hampshire",
    "sg:tags":[
        "building",
        "society"
    ],
    "wof:name":"Newbury Building Society",
    "wof:placetype":"venue"
},
  "geometry": {"coordinates":[-0.7623630166,51.2484741211],"type":"Point"}
}