{
  "type": "Feature",
  "properties": {
    "iso:country":"GB",
    "sg:address":"Byley Warehouse, Moss Lane, Byley",
    "sg:city":"Middlewich",
    "sg:classifiers":[
        {
            "category":"Retail",
            "subcategory":"Storage",
            "type":"Services"
        }
    ],
    "sg:postcode":"CW10 9NG",
    "sg:province":"Cheshire",
    "sg:tags":[
        "household",
        "removal"
    ],
    "wof:name":"Freeman's Removals & Storage Ltd.",
    "wof:placetype":"venue"
},
  "geometry": {"coordinates":[-2.4531340599,53.1922988892],"type":"Point"}
}