{
  "type": "Feature",
  "properties": {
    "addr:full":"4 Combe Road, Portishead Bristol Somerset BS20 6BJ",
    "addr:housenumber":"4",
    "addr:postcode":"bs20 6bj",
    "addr:street":"Combe Road",
    "iso:country":"GB",
    "sg:address":"4 Combe Road, Portishead",
    "sg:city":"Bristol",
    "sg:classifiers":[
        {
            "category":"Professional",
            "subcategory":"Engineering",
            "type":"Services"
        }
    ],
    "sg:phone":"+44 1275 849600",
    "sg:postcode":"BS20 6BJ",
    "sg:province":"Somerset",
    "sg:tags":[
        "civil",
        "engineer"
    ],
    "wof:name":"C O B Construction Ltd.",
    "wof:placetype":"venue"
},
  "geometry": {"coordinates":[-2.76943,51.484425],"type":"Point"}
}