{
  "type": "Feature",
  "properties": {
    "addr:full":"54 High Street Lyndhurst Hampshire SO43 7BG",
    "addr:housenumber":"54",
    "addr:postcode":"so43 7bg",
    "addr:street":"High Street",
    "iso:country":"GB",
    "sg:address":"54 High Street",
    "sg:city":"Lyndhurst",
    "sg:classifiers":[
        {
            "category":"Food & Beverages",
            "subcategory":"Meat & Fish",
            "type":"Retail Goods"
        }
    ],
    "sg:phone":"+44 23 8028 2637",
    "sg:postcode":"SO43 7BG",
    "sg:province":"Hampshire",
    "sg:tags":[
        "butcher"
    ],
    "wof:name":"Burgoyne's",
    "wof:placetype":"venue"
},
  "geometry": {"coordinates":[-1.5740690231,50.8723449707],"type":"Point"}
}