{
  "type": "Feature",
  "properties": {
    "addr:full":"17-19 Upr Tachbrook St London Greater London SW1V 1SN",
    "addr:housenumber":"17-19",
    "addr:postcode":"sw1v 1sn",
    "addr:street":"Upr Tachbrook St",
    "iso:country":"GB",
    "sg:address":"17-19 Upr Tachbrook St",
    "sg:city":"London",
    "sg:classifiers":[
        {
            "category":"Shopping",
            "subcategory":"Thrift Store",
            "type":"Retail Goods"
        }
    ],
    "sg:phone":"+44 20 7233 8736",
    "sg:postcode":"SW1V 1SN",
    "sg:province":"Greater London",
    "sg:tags":[
        "shop",
        "charity"
    ],
    "wof:name":"Crusaid (Enterprises) Ltd",
    "wof:placetype":"venue"
},
  "geometry": {"coordinates":[-0.139008,51.492912],"type":"Point"}
}