{
  "type": "Feature",
  "properties": {
    "addr:full":"Sapphire Kennels Headcorn Road, Sutton Valence Maidstone Kent ME17 3EH",
    "addr:postcode":"me17 3eh",
    "addr:street":"Headcorn Road",
    "iso:country":"GB",
    "sg:address":"Sapphire Kennels Headcorn Road, Sutton Valence",
    "sg:city":"Maidstone",
    "sg:classifiers":[
        {
            "category":"Professional",
            "subcategory":"Business Services",
            "type":"Services"
        }
    ],
    "sg:postcode":"ME17 3EH",
    "sg:province":"Kent",
    "sg:tags":[
        "accomodation"
    ],
    "wof:name":"Sapphire Housing Ltd.",
    "wof:placetype":"venue"
},
  "geometry": {"coordinates":[0.590929,51.212746],"type":"Point"}
}