{
  "type": "Feature",
  "properties": {
    "addr:full":"18 Churchfields, Devauden Chepstow Gloucestershire NP16 6NB",
    "addr:housenumber":"18",
    "addr:postcode":"np16 6nb",
    "addr:street":"Churchfields",
    "iso:country":"GB",
    "sg:address":"18 Churchfields, Devauden",
    "sg:city":"Chepstow",
    "sg:classifiers":[
        {
            "category":"Real Estate",
            "subcategory":"Architect",
            "type":"Services"
        }
    ],
    "sg:postcode":"NP16 6NB",
    "sg:province":"Gloucestershire",
    "wof:name":"Nield,Kevin,",
    "wof:placetype":"venue"
},
  "geometry": {"coordinates":[-2.73409,51.66061],"type":"Point"}
}