{
  "type": "Feature",
  "properties": {
    "addr:full":"Unit 5 Astra Business Park, Guinness Road, Trafford Park Manchester Cheshire M17 1SU",
    "addr:housenumber":"unit 5",
    "addr:postcode":"m17 1su",
    "addr:street":"Business Park Guinness Road",
    "iso:country":"GB",
    "sg:address":"Unit 5 Astra Business Park, Guinness Road, Trafford Park",
    "sg:city":"Manchester",
    "sg:classifiers":[
        {
            "category":"Retail",
            "subcategory":"Auto Rental",
            "type":"Services"
        }
    ],
    "sg:phone":"+44 161 877 3311",
    "sg:postcode":"M17 1SU",
    "sg:province":"Cheshire",
    "sg:tags":[
        "truck",
        "hire",
        "van"
    ],
    "wof:name":"Smith Self Drive Ltd.",
    "wof:placetype":"venue"
},
  "geometry": {"coordinates":[-2.3339989185,53.4741096497],"type":"Point"}
}