{
  "type": "Feature",
  "properties": {
    "addr:full":"151 Garstang Rd, Fulwood Preston Lancashire PR2 3BH",
    "addr:housenumber":"151",
    "addr:postcode":"pr2 3bh",
    "addr:street":"Garstang Rd",
    "iso:country":"GB",
    "sg:address":"151 Garstang Rd, Fulwood",
    "sg:city":"Preston",
    "sg:classifiers":[
        {
            "category":"Organizations",
            "subcategory":"Non-profit Organization",
            "type":"Services"
        }
    ],
    "sg:phone":"+44 1772 788993",
    "sg:postcode":"PR2 3BH",
    "sg:province":"Lancashire",
    "sg:tags":[
        "organisation",
        "voluntary",
        "charity"
    ],
    "wof:name":"Barnardos",
    "wof:placetype":"venue"
},
  "geometry": {"coordinates":[-2.709471,53.776787],"type":"Point"}
}