{
  "type": "Feature",
  "properties": {
    "addr:full":"48 High Street, May Bank Newcastle Staffordshire ST5 0JB",
    "addr:housenumber":"48",
    "addr:postcode":"st5 0jb",
    "addr:street":"High Street",
    "iso:country":"GB",
    "sg:address":"48 High Street, May Bank",
    "sg:city":"Newcastle",
    "sg:classifiers":[
        {
            "category":"Professional",
            "subcategory":"Secretarial Services",
            "type":"Services"
        }
    ],
    "sg:phone":"+44 1782 715151",
    "sg:postcode":"ST5 0JB",
    "sg:province":"Staffordshire",
    "wof:name":"U K Secretariat",
    "wof:placetype":"venue"
},
  "geometry": {"coordinates":[-2.217468,53.031475],"type":"Point"}
}