{
  "type": "Feature",
  "properties": {
    "addr:full":"4 Albion Parade, Wall Heath Brierley Hill Staffordshire DY6 0NP",
    "addr:housenumber":"4",
    "addr:postcode":"dy6 0np",
    "addr:street":"Albion Parade Wall Heath",
    "iso:country":"GB",
    "sg:address":"4 Albion Parade, Wall Heath",
    "sg:city":"Brierley Hill",
    "sg:classifiers":[
        {
            "category":"Shopping",
            "subcategory":"Thrift Store",
            "type":"Retail Goods"
        },
        {
            "category":"Organizations",
            "subcategory":"Non-profit Organization",
            "type":"Services"
        }
    ],
    "sg:phone":"+44 1384 401117",
    "sg:postcode":"DY6 0NP",
    "sg:province":"Staffordshire",
    "sg:tags":[
        "shop",
        "organisation",
        "voluntary",
        "charity"
    ],
    "wof:name":"Wordsley Hospital Kidney Patient Association",
    "wof:placetype":"venue"
},
  "geometry": {"coordinates":[-2.178913,52.504311],"type":"Point"}
}