{
  "type": "Feature",
  "properties": {
    "addr:full":"Middle Hulme Farm, Meerbrook Leek Staffordshire ST13 8SW",
    "addr:postcode":"st13 8sw",
    "addr:street":"Meerbrook",
    "iso:country":"GB",
    "sg:address":"Middle Hulme Farm, Meerbrook",
    "sg:city":"Leek",
    "sg:classifiers":[
        {
            "category":"Farming",
            "subcategory":"Farm",
            "type":"Manufacturing & Wholesale Goods"
        }
    ],
    "sg:postcode":"ST13 8SW",
    "sg:province":"Staffordshire",
    "sg:tags":[
        "mixed",
        "crop"
    ],
    "wof:name":"B R Goldstraw",
    "wof:placetype":"venue"
},
  "geometry": {"coordinates":[-2.01706,53.144169],"type":"Point"}
}