{
  "type": "Feature",
  "properties": {
    "iso:country":"GB",
    "sg:address":"Lanens Lane",
    "sg:city":"Hebden Bridge",
    "sg:classifiers":[
        {
            "category":"Shopping",
            "subcategory":"Crafts & Fabrics",
            "type":"Retail Goods"
        }
    ],
    "sg:phone":"+44 1422 846527",
    "sg:postcode":"HX7 8TN",
    "sg:province":"West Yorkshire",
    "sg:tags":[
        "merchant",
        "wool"
    ],
    "wof:name":"Wilcock Ltd.",
    "wof:placetype":"venue"
},
  "geometry": {"coordinates":[-2.014491,53.741226],"type":"Point"}
}