{
  "type": "Feature",
  "properties": {
    "addr:full":"32 Sclattie Park, Broxburn Aberdeen Aberdeen City AB21 9QR",
    "addr:housenumber":"32",
    "addr:postcode":"ab21 9qr",
    "addr:street":"Sclattie Park",
    "iso:country":"GB",
    "sg:address":"32 Sclattie Park, Broxburn",
    "sg:city":"Aberdeen",
    "sg:classifiers":[
        {
            "category":"Building & Trades",
            "subcategory":"Plumbing",
            "type":"Services"
        }
    ],
    "sg:postcode":"AB21 9QR",
    "sg:province":"Aberdeen City",
    "sg:tags":[
        "heating"
    ],
    "wof:name":"Brian Melvin",
    "wof:placetype":"venue"
},
  "geometry": {"coordinates":[-2.1873788834,57.1789703369],"type":"Point"}
}