{
  "type": "Feature",
  "properties": {
    "iso:country":"GB",
    "sg:address":"4 St Albans Place",
    "sg:city":"Chorley",
    "sg:classifiers":[
        {
            "category":"Building & Trades",
            "subcategory":"Construction",
            "type":"Services"
        }
    ],
    "sg:phone":"+44 1257 264094",
    "sg:postcode":"PR7 3EY",
    "sg:province":"Lancashire",
    "sg:tags":[
        "demolition",
        "contractor"
    ],
    "wof:name":"J R Trafford & Son",
    "wof:placetype":"venue"
},
  "geometry": {"coordinates":[-2.623155,53.643059],"type":"Point"}
}