{
  "type": "Feature",
  "properties": {
    "iso:country":"GB",
    "sg:address":"6 The Swan Centre",
    "sg:city":"Eastleigh",
    "sg:classifiers":[
        {
            "category":"Shopping",
            "subcategory":"Clothing, Apparel, & Fashions",
            "type":"Retail Goods"
        }
    ],
    "sg:phone":"+44 23 8062 0181",
    "sg:postcode":"SO50 5SG",
    "sg:province":"Hampshire",
    "sg:tags":[
        "shop"
    ],
    "wof:name":"Evans Ltd",
    "wof:placetype":"venue"
},
  "geometry": {"coordinates":[-1.350593,50.968323],"type":"Point"}
}