{
  "type": "Feature",
  "properties": {
    "addr:full":"54 Southbourne Gro Bournemouth Dorset BH6 3RB",
    "addr:housenumber":"54",
    "addr:postcode":"bh6 3rb",
    "addr:street":"Southbourne Gro",
    "iso:country":"GB",
    "sg:address":"54 Southbourne Gro",
    "sg:city":"Bournemouth",
    "sg:classifiers":[
        {
            "category":"Shopping",
            "subcategory":"Department Store",
            "type":"Retail Goods"
        }
    ],
    "sg:phone":"+44 1202 434402",
    "sg:postcode":"BH6 3RB",
    "sg:province":"Dorset",
    "wof:name":"Superbuys",
    "wof:placetype":"venue"
},
  "geometry": {"coordinates":[-1.8133770227,50.7262878418],"type":"Point"}
}