{
  "type": "Feature",
  "properties": {
    "addr:full":"Thompson St East Darlington Durham DL1 3BA",
    "addr:postcode":"dl1 3ba",
    "addr:street":"Thompson St",
    "iso:country":"GB",
    "sg:address":"Thompson St East",
    "sg:city":"Darlington",
    "sg:classifiers":[
        {
            "category":"Bars & Pubs",
            "type":"Food & Drink"
        }
    ],
    "sg:phone":"+44 1325 381235",
    "sg:postcode":"DL1 3BA",
    "sg:province":"Durham",
    "sg:tags":[
        "pubs",
        "inn"
    ],
    "wof:name":"The Burns Tavern",
    "wof:placetype":"venue"
},
  "geometry": {"coordinates":[-1.535149,54.546085],"type":"Point"}
}