{
  "type": "Feature",
  "properties": {
    "addr:full":"12 Hampden Gro Manchester Greater Manchester M30 0QU",
    "addr:housenumber":"12",
    "addr:postcode":"m30 0qu",
    "addr:street":"Hampden Gro",
    "iso:country":"GB",
    "sg:address":"12 Hampden Gro",
    "sg:city":"Manchester",
    "sg:classifiers":[
        {
            "category":"Building & Trades",
            "subcategory":"Plumbing",
            "type":"Services"
        }
    ],
    "sg:phone":"+44 161 789 1702",
    "sg:postcode":"M30 0QU",
    "sg:province":"Greater Manchester",
    "sg:tags":[
        "heating"
    ],
    "wof:name":"R W Hardie",
    "wof:placetype":"venue"
},
  "geometry": {"coordinates":[-2.3501260281,53.4851455688],"type":"Point"}
}