{
  "type": "Feature",
  "properties": {
    "addr:full":"Bournelake Farm, Cricklade Swindon Gloucestershire SN6 6QZ",
    "addr:housenumber":"cricklade",
    "addr:postcode":"sn6 6qz",
    "iso:country":"GB",
    "sg:address":"Bournelake Farm, Cricklade",
    "sg:city":"Swindon",
    "sg:classifiers":[
        {
            "category":"Farming",
            "subcategory":"Dairy Farm",
            "type":"Manufacturing & Wholesale Goods"
        }
    ],
    "sg:postcode":"SN6 6QZ",
    "sg:province":"Gloucestershire",
    "wof:name":"P Denton",
    "wof:placetype":"venue"
},
  "geometry": {"coordinates":[-1.85699,51.640049],"type":"Point"}
}