{
  "type": "Feature",
  "properties": {
    "iso:country":"GB",
    "sg:address":"199 Bell Hagg Rd",
    "sg:city":"Sheffield",
    "sg:classifiers":[
        {
            "category":"Building & Trades",
            "subcategory":"Construction",
            "type":"Services"
        }
    ],
    "sg:phone":"+44 114 234 3963",
    "sg:postcode":"S6 5DA",
    "sg:province":"South Yorkshire",
    "sg:tags":[
        "builder"
    ],
    "wof:name":"Marren S",
    "wof:placetype":"venue"
},
  "geometry": {"coordinates":[-1.506696,53.394604],"type":"Point"}
}