{
  "type": "Feature",
  "properties": {
    "addr:full":"Maidstone Road, Off Underlyn Lane, Marden Tonbridge Kent TN12 9BQ",
    "addr:postcode":"tn12 9bq",
    "addr:street":"Maidstone Road Off Underlyn Lane",
    "iso:country":"GB",
    "sg:address":"Maidstone Road, Off Underlyn Lane, Marden",
    "sg:city":"Tonbridge",
    "sg:classifiers":[
        {
            "category":"Retail",
            "subcategory":"Auto Repair",
            "type":"Services"
        }
    ],
    "sg:postcode":"TN12 9BQ",
    "sg:province":"Kent",
    "sg:tags":[
        "car",
        "assembler",
        "kit"
    ],
    "wof:name":"Fisher Sportscars",
    "wof:placetype":"venue"
},
  "geometry": {"coordinates":[0.5173699856,51.2002487183],"type":"Point"}
}