{
  "type": "Feature",
  "properties": {
    "iso:country":"GB",
    "sg:address":"85 Mountergate",
    "sg:city":"Norwich",
    "sg:classifiers":[
        {
            "category":"Manufacturing",
            "subcategory":"Tools & Machinery",
            "type":"Manufacturing & Wholesale Goods"
        }
    ],
    "sg:phone":"+44 1603 627600",
    "sg:postcode":"NR1 1PY",
    "sg:province":"Norfolk",
    "sg:tags":[
        "power"
    ],
    "wof:name":"Black & Decker",
    "wof:placetype":"venue"
},
  "geometry": {"coordinates":[1.301398,52.626671],"type":"Point"}
}