{
  "type": "Feature",
  "properties": {
    "iso:country":"GB",
    "sg:address":"Grange Lodge, Grange Road, Monifieth",
    "sg:city":"Dundee",
    "sg:classifiers":[
        {
            "category":"Retail",
            "subcategory":"Auto Repair",
            "type":"Services"
        }
    ],
    "sg:postcode":"DD5 4LU",
    "sg:province":"Angus",
    "sg:tags":[
        "body",
        "car"
    ],
    "wof:name":"Chips Away",
    "wof:placetype":"venue"
},
  "geometry": {"coordinates":[-2.8200309277,56.4804039001],"type":"Point"}
}