{
  "type": "Feature",
  "properties": {
    "addr:full":"Jockstown, Annan Dumfries Dumfries and Galloway DG12 6RW",
    "addr:postcode":"dg12 6rw",
    "iso:country":"GB",
    "sg:address":"Jockstown, Annan",
    "sg:city":"Dumfries",
    "sg:classifiers":[
        {
            "category":"Farming",
            "subcategory":"Farm",
            "type":"Manufacturing & Wholesale Goods"
        }
    ],
    "sg:postcode":"DG12 6RW",
    "sg:province":"Dumfries and Galloway",
    "sg:tags":[
        "mixed",
        "crop"
    ],
    "wof:name":"E & A Williamson",
    "wof:placetype":"venue"
},
  "geometry": {"coordinates":[-3.23599,55.026058],"type":"Point"}
}