{
  "type": "Feature",
  "properties": {
    "iso:country":"GB",
    "sg:address":"23 Holywell Street",
    "sg:city":"Chesterfield",
    "sg:classifiers":[
        {
            "category":"Bars & Pubs",
            "type":"Food & Drink"
        }
    ],
    "sg:postcode":"S41 7SA",
    "sg:province":"Derbyshire",
    "sg:tags":[
        "pubs",
        "inn"
    ],
    "wof:name":"The Pink Panther",
    "wof:placetype":"venue"
},
  "geometry": {"coordinates":[-1.425038,53.237358],"type":"Point"}
}