{
  "type": "Feature",
  "properties": {
    "addr:full":"Unit B, Nabisco Wks Leicester Leicestershire LE4 0AW",
    "addr:postcode":"le4 0aw",
    "iso:country":"GB",
    "sg:address":"Unit B, Nabisco Wks",
    "sg:city":"Leicester",
    "sg:classifiers":[
        {
            "category":"Manufacturing",
            "subcategory":"Textiles",
            "type":"Manufacturing & Wholesale Goods"
        }
    ],
    "sg:postcode":"LE4 0AW",
    "sg:province":"Leicestershire",
    "sg:tags":[
        "dyer"
    ],
    "wof:name":"Top Colours Ltd",
    "wof:placetype":"venue"
},
  "geometry": {"coordinates":[-1.1459699869,52.6446990967],"type":"Point"}
}