{
  "type": "Feature",
  "properties": {
    "iso:country":"GB",
    "sg:address":"London Road",
    "sg:city":"Ascot",
    "sg:classifiers":[
        {
            "category":"Government",
            "subcategory":"City Hall",
            "type":"Public Place"
        },
        {
            "category":"Place Of Worship",
            "type":"Public Place"
        },
        {
            "category":"Retail",
            "subcategory":"Event Space",
            "type":"Services"
        }
    ],
    "sg:phone":"+44 1344 291162",
    "sg:postcode":"SL5 8DH",
    "sg:province":"Berkshire",
    "sg:tags":[
        "function",
        "hire",
        "room"
    ],
    "wof:name":"All Saints Church Hall",
    "wof:placetype":"venue"
},
  "geometry": {"coordinates":[-0.6955739856,51.4113311768],"type":"Point"}
}