{
  "type": "Feature",
  "properties": {
    "addr:full":"26 Webbscroft Road Dagenham Essex RM10 7NL",
    "addr:housenumber":"26",
    "addr:postcode":"rm10 7nl",
    "addr:street":"Webbscroft Road",
    "iso:country":"GB",
    "sg:address":"26 Webbscroft Road",
    "sg:city":"Dagenham",
    "sg:classifiers":[
        {
            "category":"Education",
            "subcategory":"Special Training",
            "type":"Public Place"
        }
    ],
    "sg:phone":"+44 20 8595 4220",
    "sg:postcode":"RM10 7NL",
    "sg:province":"Essex",
    "sg:tags":[
        "product",
        "centre"
    ],
    "wof:name":"Michael Sands",
    "wof:placetype":"venue"
},
  "geometry": {"coordinates":[0.159045,51.552128],"type":"Point"}
}