{
  "type": "Feature",
  "properties": {
    "iso:country":"GB",
    "sg:address":"10a Park Road",
    "sg:city":"Peterborough",
    "sg:classifiers":[
        {
            "category":"Restaurant",
            "type":"Food & Drink"
        }
    ],
    "sg:phone":"+44 1733 561544",
    "sg:postcode":"PE1 2TD",
    "sg:province":"Cambridgeshire",
    "sg:tags":[
        "indian"
    ],
    "wof:name":"Planet Papadom",
    "wof:placetype":"venue"
},
  "geometry": {"coordinates":[-0.24299,52.574905],"type":"Point"}
}