{
  "type": "Feature",
  "properties": {
    "addr:full":"Pine Lodge, Great North Rd, Bawtry Doncaster Lincolnshire DN10 6DF",
    "addr:postcode":"dn10 6df",
    "addr:street":"Great North Rd",
    "iso:country":"GB",
    "sg:address":"Pine Lodge, Great North Rd, Bawtry",
    "sg:city":"Doncaster",
    "sg:classifiers":[
        {
            "category":"Autos & Motor Vehicles",
            "subcategory":"Automobile Sales",
            "type":"Retail Goods"
        }
    ],
    "sg:phone":"+44 1302 711111",
    "sg:postcode":"DN10 6DF",
    "sg:province":"Lincolnshire",
    "sg:tags":[
        "commercial"
    ],
    "wof:name":"Clive Watson Car Sales",
    "wof:placetype":"venue"
},
  "geometry": {"coordinates":[-1.0205390453,53.4304504395],"type":"Point"}
}