{
  "type": "Feature",
  "properties": {
    "addr:full":"St James Norlands Church, St James Gardens London Greater London W11 4RB",
    "addr:postcode":"w11 4rb",
    "addr:street":"St James Gardens",
    "iso:country":"GB",
    "sg:address":"St James Norlands Church, St James Gardens",
    "sg:city":"London",
    "sg:classifiers":[
        {
            "category":"Farming",
            "subcategory":"Nursery",
            "type":"Manufacturing & Wholesale Goods"
        }
    ],
    "sg:phone":"+44 20 7603 6095",
    "sg:postcode":"W11 4RB",
    "sg:province":"Greater London",
    "sg:tags":[
        "creche"
    ],
    "wof:name":"Miss Delaneys Nursery School",
    "wof:placetype":"venue"
},
  "geometry": {"coordinates":[-0.21471,51.50766],"type":"Point"}
}