{
  "type": "Feature",
  "properties": {
    "addr:full":"7 Shaftesbury Ct, 18 Chalvey Park Slough Berkshire SL1 2ER",
    "addr:housenumber":"7;18",
    "addr:postcode":"sl1 2er",
    "addr:street":"Shaftesbury Ct;Park",
    "iso:country":"GB",
    "sg:address":"7 Shaftesbury Ct, 18 Chalvey Park",
    "sg:city":"Slough",
    "sg:classifiers":[
        {
            "category":"Professional",
            "subcategory":"Management & Consulting",
            "type":"Services"
        }
    ],
    "sg:phone":"+44 1753 819227",
    "sg:postcode":"SL1 2ER",
    "sg:province":"Berkshire",
    "sg:tags":[
        "consultant",
        "business"
    ],
    "wof:name":"N B Selection Ltd",
    "wof:placetype":"venue"
},
  "geometry": {"coordinates":[-0.5964170098,51.5078735352],"type":"Point"}
}