{
  "type": "Feature",
  "properties": {
    "addr:full":"Blyth Service Area, Junction A1m-a614, Hilltop Roundabout Worksop Nottinghamshire S81 8HG",
    "addr:housenumber":"a1m-a614",
    "addr:postcode":"s81 8hg",
    "addr:street":"Hilltop Roundabout",
    "iso:country":"GB",
    "sg:address":"Blyth Service Area, Junction A1m-a614, Hilltop Roundabout",
    "sg:city":"Worksop",
    "sg:classifiers":[
        {
            "category":"Travel",
            "subcategory":"Hotels & Motels",
            "type":"Entertainment"
        }
    ],
    "sg:phone":"+44 1909 591841",
    "sg:postcode":"S81 8HG",
    "sg:province":"Nottinghamshire",
    "wof:name":"Granada Motorway Service Station",
    "wof:placetype":"venue"
},
  "geometry": {"coordinates":[-1.06233,53.382061],"type":"Point"}
}