{
  "type": "Feature",
  "properties": {
    "iso:country":"GB",
    "sg:address":"2 Seymour Mews, Lipson",
    "sg:city":"Plymouth",
    "sg:classifiers":[
        {
            "category":"Manufacturing",
            "subcategory":"Apparel",
            "type":"Manufacturing & Wholesale Goods"
        },
        {
            "category":"Military Area",
            "subcategory":"Air Force Base",
            "type":"Public Place"
        }
    ],
    "sg:phone":"+44 1752 600260",
    "sg:postcode":"PL4 8RX",
    "sg:province":"Devon",
    "sg:tags":[
        "mnfr",
        "trimmer",
        "accessory",
        "manufacturer",
        "clothing",
        "trimming"
    ],
    "wof:name":"Asquith Supplies",
    "wof:placetype":"venue"
},
  "geometry": {"coordinates":[-4.125041008,50.3758659363],"type":"Point"}
}