{
  "type": "Feature",
  "properties": {
    "addr:full":"Unit 4 Shaw House Wychbury Court, Two Woods Lane Brierley Hill West Midlands DY5 1TA",
    "addr:housenumber":"unit 4",
    "addr:postcode":"dy5 1ta",
    "addr:street":"Shaw House Wychbury Court Two Woods Lane",
    "iso:country":"GB",
    "sg:address":"Unit 4 Shaw House Wychbury Court, Two Woods Lane",
    "sg:city":"Brierley Hill",
    "sg:classifiers":[
        {
            "category":"Home & Garden",
            "subcategory":"Building Materials",
            "type":"Retail Goods"
        }
    ],
    "sg:phone":"+44 1384 484242",
    "sg:postcode":"DY5 1TA",
    "sg:province":"West Midlands",
    "sg:tags":[
        "hinge"
    ],
    "wof:name":"Grass (U K) Ltd.",
    "wof:placetype":"venue"
},
  "geometry": {"coordinates":[-2.109609,52.476116],"type":"Point"}
}