{
  "type": "Feature",
  "properties": {
    "iso:country":"GB",
    "sg:address":"7 Gilchrist Thomas Industrial Estate",
    "sg:city":"Pontypool",
    "sg:classifiers":[
        {
            "category":"Professional",
            "subcategory":"Detective & Security Services",
            "type":"Services"
        }
    ],
    "sg:phone":"+44 1495 791194",
    "sg:postcode":"NP4 9RL",
    "sg:province":"Monmouthshire",
    "sg:tags":[
        "equipment"
    ],
    "wof:name":"Home Automation Logic Ltd.",
    "wof:placetype":"venue"
},
  "geometry": {"coordinates":[-3.04319,51.703087],"type":"Point"}
}