{
  "type": "Feature",
  "properties": {
    "addr:full":"27 High Street, Sunninghill Ascot Berkshire SL5 9NG",
    "addr:housenumber":"27",
    "addr:postcode":"sl5 9ng",
    "addr:street":"High Street",
    "iso:country":"GB",
    "sg:address":"27 High Street, Sunninghill",
    "sg:city":"Ascot",
    "sg:classifiers":[
        {
            "category":"Home & Garden",
            "subcategory":"Carpets & Floor Coverings",
            "type":"Retail Goods"
        }
    ],
    "sg:phone":"+44 1344 622022",
    "sg:postcode":"SL5 9NG",
    "sg:province":"Berkshire",
    "sg:tags":[
        "carpets",
        "rug",
        "matting"
    ],
    "wof:name":"Sunninghill Carpets & Flooring Ltd.",
    "wof:placetype":"venue"
},
  "geometry": {"coordinates":[-0.656471014,51.4006004333],"type":"Point"}
}