{
  "type": "Feature",
  "properties": {
    "addr:full":"Wendover Road, Rackheath Norwich Norfolk NR13 6LR",
    "addr:postcode":"nr13 6lr",
    "addr:street":"Wendover Road",
    "iso:country":"GB",
    "sg:address":"Wendover Road, Rackheath",
    "sg:city":"Norwich",
    "sg:classifiers":[
        {
            "category":"Manufacturing",
            "subcategory":"Rubber & Plastics",
            "type":"Manufacturing & Wholesale Goods"
        }
    ],
    "sg:phone":"+44 1603 720651",
    "sg:postcode":"NR13 6LR",
    "sg:province":"Norfolk",
    "sg:tags":[
        "mould"
    ],
    "wof:name":"Aquafibre Properties Ltd.",
    "wof:placetype":"venue"
},
  "geometry": {"coordinates":[1.370659,52.675293],"type":"Point"}
}