{
  "type": "Feature",
  "properties": {
    "addr:full":"55 Broadmead Road Folkestone Kent CT19 5AW",
    "addr:housenumber":"55",
    "addr:postcode":"ct19 5aw",
    "addr:street":"Broadmead Road",
    "iso:country":"GB",
    "sg:address":"55 Broadmead Road",
    "sg:city":"Folkestone",
    "sg:classifiers":[
        {
            "category":"Home & Garden",
            "subcategory":"Carpets & Floor Coverings",
            "type":"Retail Goods"
        }
    ],
    "sg:phone":"+44 1303 220047",
    "sg:postcode":"CT19 5AW",
    "sg:province":"Kent",
    "sg:tags":[
        "wall",
        "tie",
        "replacement"
    ],
    "wof:name":"R J Engineering",
    "wof:placetype":"venue"
},
  "geometry": {"coordinates":[1.1743689775,51.0833358765],"type":"Point"}
}