{
  "type": "Feature",
  "properties": {
    "iso:country":"GB",
    "sg:address":"19 Boldmere Rd",
    "sg:city":"Sutton Coldfield",
    "sg:classifiers":[
        {
            "category":"Food & Beverages",
            "subcategory":"Bakery",
            "type":"Retail Goods"
        }
    ],
    "sg:phone":"+44 121 355 2482",
    "sg:postcode":"B73 5UY",
    "sg:province":"West Midlands",
    "sg:tags":[
        "baker"
    ],
    "wof:name":"Hindley,Graham A,",
    "wof:placetype":"venue"
},
  "geometry": {"coordinates":[-1.841444,52.549873],"type":"Point"}
}