{
  "type": "Feature",
  "properties": {
    "addr:full":"66-70 North Lindsay Street Dundee Dundee City DD1 1PS",
    "addr:housenumber":"66-70",
    "addr:postcode":"dd1 1ps",
    "addr:street":"North Lindsay Street",
    "iso:country":"GB",
    "sg:address":"66-70 North Lindsay Street",
    "sg:city":"Dundee",
    "sg:classifiers":[
        {
            "category":"Recreation",
            "type":"Entertainment"
        }
    ],
    "sg:postcode":"DD1 1PS",
    "sg:province":"Dundee City",
    "sg:tags":[
        "snooker",
        "billiards",
        "pool"
    ],
    "wof:name":"Masters Snooker Club",
    "wof:placetype":"venue"
},
  "geometry": {"coordinates":[-2.976069,56.460827],"type":"Point"}
}