{
  "type": "Feature",
  "properties": {
    "addr:full":"Unit 25 Bates Industrial Estate, Church Road, Harold Wood Romford Essex RM3 0HU",
    "addr:housenumber":"unit 25;estate",
    "addr:postcode":"rm3 0hu",
    "addr:street":"Industrial;Church Road",
    "iso:country":"GB",
    "sg:address":"Unit 25 Bates Industrial Estate, Church Road, Harold Wood",
    "sg:city":"Romford",
    "sg:classifiers":[
        {
            "category":"Manufacturing",
            "subcategory":"Rubber & Plastics",
            "type":"Manufacturing & Wholesale Goods"
        }
    ],
    "sg:phone":"+44 870 777 0471",
    "sg:postcode":"RM3 0HU",
    "sg:province":"Essex",
    "sg:tags":[
        "injection",
        "moulding"
    ],
    "wof:name":"Diamond Enterprises (U K) Ltd.",
    "wof:placetype":"venue"
},
  "geometry": {"coordinates":[0.2328000069,51.5918006897],"type":"Point"}
}