{
  "type": "Feature",
  "properties": {
    "addr:full":"15 Handsworth Rd Sheffield South Yorkshire S9 4AA",
    "addr:housenumber":"15",
    "addr:postcode":"s9 4aa",
    "addr:street":"Handsworth Rd",
    "iso:country":"GB",
    "sg:address":"15 Handsworth Rd",
    "sg:city":"Sheffield",
    "sg:classifiers":[
        {
            "category":"Retail",
            "subcategory":"Auto Repair",
            "type":"Services"
        }
    ],
    "sg:phone":"+44 114 244 1933",
    "sg:postcode":"S9 4AA",
    "sg:province":"South Yorkshire",
    "sg:tags":[
        "modification",
        "garage"
    ],
    "wof:name":"Triangle Service Station",
    "wof:placetype":"venue"
},
  "geometry": {"coordinates":[-1.400863,53.382732],"type":"Point"}
}