{
  "type": "Feature",
  "properties": {
    "iso:country":"GB",
    "sg:address":"3 Pear Tree Lane, Chesterton",
    "sg:city":"Newcastle",
    "sg:classifiers":[
        {
            "category":"Military Area",
            "subcategory":"Air Force Base",
            "type":"Public Place"
        }
    ],
    "sg:postcode":"ST5 7EY",
    "sg:province":"Staffordshire",
    "sg:tags":[
        "taxi",
        "hire",
        "private"
    ],
    "wof:name":"Falcon Air Courier Services",
    "wof:placetype":"venue"
},
  "geometry": {"coordinates":[-2.2606790066,53.0459327698],"type":"Point"}
}