{
  "type": "Feature",
  "properties": {
    "addr:full":"193 Stanstead Road London Greater London SE23 1HP",
    "addr:housenumber":"193",
    "addr:postcode":"se23 1hp",
    "addr:street":"Stanstead Road",
    "iso:country":"GB",
    "sg:address":"193 Stanstead Road",
    "sg:city":"London",
    "sg:classifiers":[
        {
            "category":"Taxi",
            "type":"Transportation"
        }
    ],
    "sg:postcode":"SE23 1HP",
    "sg:province":"Greater London",
    "sg:tags":[
        "mini",
        "cab"
    ],
    "wof:name":"Carib Cars",
    "wof:placetype":"venue"
},
  "geometry": {"coordinates":[-0.043831,51.44212],"type":"Point"}
}