{
  "type": "Feature",
  "properties": {
    "addr:full":"203 Askew Rd Shepherd's Bush Greater London W12 9AZ",
    "addr:housenumber":"203",
    "addr:postcode":"w12 9az",
    "addr:street":"Askew Rd",
    "iso:country":"GB",
    "sg:address":"203 Askew Rd",
    "sg:city":"Shepherd's Bush",
    "sg:classifiers":[
        {
            "category":"Home & Garden",
            "subcategory":"Household Appliances",
            "type":"Retail Goods"
        }
    ],
    "sg:phone":"+44 20 8746 2198",
    "sg:postcode":"W12 9AZ",
    "sg:province":"Greater London",
    "sg:tags":[
        "electrical"
    ],
    "wof:name":"Discovery Home Appliances",
    "wof:placetype":"venue"
},
  "geometry": {"coordinates":[-0.2395610064,51.500869751],"type":"Point"}
}