{
  "type": "Feature",
  "properties": {
    "addr:full":"Unit 16, Shannon Place Sandy Bedfordshire SG19 2SP",
    "addr:housenumber":"unit 16",
    "addr:postcode":"sg19 2sp",
    "addr:street":"Shannon Place",
    "iso:country":"GB",
    "sg:address":"Unit 16, Shannon Place",
    "sg:city":"Sandy",
    "sg:classifiers":[
        {
            "category":"Manufacturing",
            "subcategory":"Metals",
            "type":"Manufacturing & Wholesale Goods"
        }
    ],
    "sg:postcode":"SG19 2SP",
    "sg:province":"Bedfordshire",
    "sg:tags":[
        "work",
        "sheet"
    ],
    "wof:name":"Metalcrafts (Bedford)",
    "wof:placetype":"venue"
},
  "geometry": {"coordinates":[-0.219668,52.1287],"type":"Point"}
}