{
  "type": "Feature",
  "properties": {
    "iso:country":"GB",
    "sg:address":"Tower Gardens Rd",
    "sg:city":"Tottenham",
    "sg:classifiers":[
        {
            "category":"Community Center",
            "type":"Public Place"
        }
    ],
    "sg:phone":"+44 20 8801 0866",
    "sg:postcode":"N17 7PN",
    "sg:province":"Greater London",
    "sg:tags":[
        "centre"
    ],
    "wof:name":"Tower Gardens Community Play Centre",
    "wof:placetype":"venue"
},
  "geometry": {"coordinates":[-0.0805590004,51.5986633301],"type":"Point"}
}