{
  "type": "Feature",
  "properties": {
    "addr:full":"15 Jura Drive, Tweedbank Galashiels Scottish Borders TD1 3ST",
    "addr:housenumber":"15",
    "addr:postcode":"td1 3st",
    "addr:street":"Jura Drive Tweedbank",
    "iso:country":"GB",
    "sg:address":"15 Jura Drive, Tweedbank",
    "sg:city":"Galashiels",
    "sg:classifiers":[
        {
            "category":"Professional",
            "subcategory":"Computer Services",
            "type":"Services"
        }
    ],
    "sg:postcode":"TD1 3ST",
    "sg:province":"Scottish Borders",
    "sg:tags":[
        "consultant"
    ],
    "wof:name":"Simple Systems",
    "wof:placetype":"venue"
},
  "geometry": {"coordinates":[-2.762615,55.606243],"type":"Point"}
}