{
  "type": "Feature",
  "properties": {
    "iso:country":"GB",
    "sg:address":"4 Maypole Street, Wombourne",
    "sg:city":"Wolverhampton",
    "sg:classifiers":[
        {
            "category":"Shopping",
            "subcategory":"Shoes",
            "type":"Retail Goods"
        }
    ],
    "sg:phone":"+44 1902 892195",
    "sg:postcode":"WV5 9JB",
    "sg:province":"Shropshire",
    "sg:tags":[
        "shop"
    ],
    "wof:name":"The Shoe Tree",
    "wof:placetype":"venue"
},
  "geometry": {"coordinates":[-2.1856060028,52.5352363586],"type":"Point"}
}