{
  "type": "Feature",
  "properties": {
    "addr:full":"2 Godley Hill Hyde Cheshire SK14 3BL",
    "addr:housenumber":"2",
    "addr:postcode":"sk14 3bl",
    "addr:street":"Godley Hill Hyde",
    "iso:country":"GB",
    "sg:address":"2 Godley Hill",
    "sg:city":"Hyde",
    "sg:classifiers":[
        {
            "category":"Building & Trades",
            "subcategory":"Construction",
            "type":"Services"
        }
    ],
    "sg:postcode":"SK14 3BL",
    "sg:province":"Cheshire",
    "sg:tags":[
        "decorator",
        "painter"
    ],
    "wof:name":"Ken Brookes",
    "wof:placetype":"venue"
},
  "geometry": {"coordinates":[-2.051017046,53.4511604309],"type":"Point"}
}