{
  "type": "Feature",
  "properties": {
    "iso:country":"GB",
    "sg:address":"Unit 9 Orwell Court, Hurricane Way",
    "sg:city":"Wickford",
    "sg:classifiers":[
        {
            "category":"Wholesale",
            "subcategory":"Office Equipment",
            "type":"Manufacturing & Wholesale Goods"
        }
    ],
    "sg:phone":"+44 1268 766500",
    "sg:postcode":"SS11 8YJ",
    "sg:province":"Essex",
    "wof:name":"G & T Office Equipment",
    "wof:placetype":"venue"
},
  "geometry": {"coordinates":[0.544492,51.602749],"type":"Point"}
}