{
  "type": "Feature",
  "properties": {
    "addr:full":"105 Liscombe Bracknell Berkshire RG12 7DE",
    "addr:housenumber":"105",
    "addr:postcode":"rg12 7de",
    "addr:street":"Liscombe",
    "iso:country":"GB",
    "sg:address":"105 Liscombe",
    "sg:city":"Bracknell",
    "sg:classifiers":[
        {
            "category":"Professional",
            "subcategory":"Printing & Photocopies",
            "type":"Services"
        }
    ],
    "sg:phone":"+44 1344 868680",
    "sg:postcode":"RG12 7DE",
    "sg:province":"Berkshire",
    "sg:tags":[
        "duplicating",
        "copying"
    ],
    "wof:name":"Manpres Print Services",
    "wof:placetype":"venue"
},
  "geometry": {"coordinates":[-0.752075,51.391994],"type":"Point"}
}