{
  "type": "Feature",
  "properties": {
    "iso:country":"GB",
    "sg:address":"Pegasus Court, Rivers Close",
    "sg:city":"Farnborough",
    "sg:classifiers":[
        {
            "category":"Organizations",
            "subcategory":"Community Association",
            "type":"Services"
        }
    ],
    "sg:phone":"+44 1252 520411",
    "sg:postcode":"GU14 6LZ",
    "sg:province":"Hampshire",
    "sg:tags":[
        "society",
        "housing"
    ],
    "wof:name":"Pegasus Court",
    "wof:placetype":"venue"
},
  "geometry": {"coordinates":[-0.739587,51.280018],"type":"Point"}
}