{
  "type": "Feature",
  "properties": {
    "addr:full":"48 High Street Shrewsbury Shropshire SY1 1ST",
    "addr:housenumber":"48",
    "addr:postcode":"sy1 1st",
    "addr:street":"High Street",
    "iso:country":"GB",
    "sg:address":"48 High Street",
    "sg:city":"Shrewsbury",
    "sg:classifiers":[
        {
            "category":"Shopping",
            "subcategory":"Antiques",
            "type":"Retail Goods"
        }
    ],
    "sg:phone":"+44 1743 362251",
    "sg:postcode":"SY1 1ST",
    "sg:province":"Shropshire",
    "wof:name":"de Ja Vu Antiques",
    "wof:placetype":"venue"
},
  "geometry": {"coordinates":[-2.7525699139,52.706943512],"type":"Point"}
}