{
  "type": "Feature",
  "properties": {
    "addr:full":"186 Monkmoor Road Shrewsbury Shropshire SY2 5BH",
    "addr:housenumber":"186",
    "addr:postcode":"sy2 5bh",
    "addr:street":"Monkmoor Road",
    "iso:country":"GB",
    "sg:address":"186 Monkmoor Road",
    "sg:city":"Shrewsbury",
    "sg:classifiers":[
        {
            "category":"Shopping",
            "subcategory":"Used Merchandise",
            "type":"Retail Goods"
        }
    ],
    "sg:phone":"+44 1743 235180",
    "sg:postcode":"SY2 5BH",
    "sg:province":"Shropshire",
    "sg:tags":[
        "shop",
        "second-hand"
    ],
    "wof:name":"Ancient & Modern",
    "wof:placetype":"venue"
},
  "geometry": {"coordinates":[-2.727761,52.716179],"type":"Point"}
}