{
  "type": "Feature",
  "properties": {
    "iso:country":"GB",
    "sg:address":"Unit 11 Hassocks Workshops, Stroudley Road",
    "sg:city":"Basingstoke",
    "sg:classifiers":[
        {
            "category":"Utilities",
            "subcategory":"Telephone",
            "type":"Services"
        }
    ],
    "sg:phone":"+44 1256 840000",
    "sg:postcode":"RG24 8UQ",
    "sg:province":"Hampshire",
    "sg:tags":[
        "telecommunication"
    ],
    "wof:name":"Southern Communications Ltd.",
    "wof:placetype":"venue"
},
  "geometry": {"coordinates":[-1.06362,51.275051],"type":"Point"}
}