{
  "type": "Feature",
  "properties": {
    "addr:full":"Huglith Farm, Habberley Shrewsbury Shropshire SY5 0SQ",
    "addr:postcode":"sy5 0sq",
    "addr:street":"Habberley",
    "iso:country":"GB",
    "sg:address":"Huglith Farm, Habberley",
    "sg:city":"Shrewsbury",
    "sg:classifiers":[
        {
            "category":"Farming",
            "subcategory":"Livestock Farm",
            "type":"Manufacturing & Wholesale Goods"
        }
    ],
    "sg:phone":"+44 1743 790340",
    "sg:postcode":"SY5 0SQ",
    "sg:province":"Shropshire",
    "sg:tags":[
        "others"
    ],
    "wof:name":"P Roberts",
    "wof:placetype":"venue"
},
  "geometry": {"coordinates":[-2.8930299282,52.6146888733],"type":"Point"}
}