{
  "type": "Feature",
  "properties": {
    "iso:country":"GB",
    "sg:address":"51 Ardmore Avenue",
    "sg:city":"Guildford",
    "sg:classifiers":[
        {
            "category":"Building & Trades",
            "subcategory":"Plumbing",
            "type":"Services"
        }
    ],
    "sg:phone":"+44 1483 533246",
    "sg:postcode":"GU2 9NJ",
    "sg:province":"Surrey",
    "sg:tags":[
        "heating"
    ],
    "wof:name":"A.B.J Wise M.I.P H.N.C",
    "wof:placetype":"venue"
},
  "geometry": {"coordinates":[-0.587639,51.251389],"type":"Point"}
}