{
  "type": "Feature",
  "properties": {
    "iso:country":"GB",
    "sg:address":"23 Ludgate",
    "sg:city":"Tamworth",
    "sg:classifiers":[
        {
            "category":"Personal",
            "subcategory":"Barber",
            "type":"Services"
        }
    ],
    "sg:phone":"+44 1827 54740",
    "sg:postcode":"B79 7EQ",
    "sg:province":"Staffordshire",
    "sg:tags":[
        "men's",
        "gents",
        "hairdresser"
    ],
    "wof:name":"Just For Men",
    "wof:placetype":"venue"
},
  "geometry": {"coordinates":[-1.6997840405,52.6383399963],"type":"Point"}
}