{
  "type": "Feature",
  "properties": {
    "addr:full":"2 Osmaston Rd Derby Derbyshire DE1 2HR",
    "addr:housenumber":"2",
    "addr:postcode":"de1 2hr",
    "addr:street":"Osmaston Rd",
    "iso:country":"GB",
    "sg:address":"2 Osmaston Rd",
    "sg:city":"Derby",
    "sg:classifiers":[
        {
            "category":"Organizations",
            "subcategory":"Non-profit Organization",
            "type":"Services"
        }
    ],
    "sg:phone":"+44 1332 341699",
    "sg:postcode":"DE1 2HR",
    "sg:province":"Derbyshire",
    "sg:tags":[
        "organisation",
        "voluntary",
        "charity"
    ],
    "wof:name":"Save The Children Charity Shop",
    "wof:placetype":"venue"
},
  "geometry": {"coordinates":[-1.475105,52.918819],"type":"Point"}
}