{
  "type": "Feature",
  "properties": {
    "addr:full":"31 Stewarts Grove Chelsea Greater London SW3 6PH",
    "addr:housenumber":"31",
    "addr:postcode":"sw3 6ph",
    "addr:street":"Stewarts Grove",
    "iso:country":"GB",
    "sg:address":"31 Stewarts Grove",
    "sg:city":"Chelsea",
    "sg:classifiers":[
        {
            "category":"Professional",
            "type":"Services"
        }
    ],
    "sg:phone":"+44 20 7349 0573",
    "sg:postcode":"SW3 6PH",
    "sg:province":"Greater London",
    "sg:tags":[
        "interior",
        "furnishers",
        "designer"
    ],
    "wof:name":"Stephen Tsang Designs",
    "wof:placetype":"venue"
},
  "geometry": {"coordinates":[-0.1713079959,51.4906272888],"type":"Point"}
}