{
  "type": "Feature",
  "properties": {
    "addr:full":"38 Furze Hill Rd Shipston On Stour Warwickshire CV36 4EU",
    "addr:housenumber":"38",
    "addr:postcode":"cv36 4eu",
    "addr:street":"Furze Hill Rd",
    "iso:country":"GB",
    "sg:address":"38 Furze Hill Rd",
    "sg:city":"Shipston On Stour",
    "sg:classifiers":[
        {
            "category":"Home & Garden",
            "subcategory":"Furniture",
            "type":"Retail Goods"
        }
    ],
    "sg:phone":"+44 1608 662973",
    "sg:postcode":"CV36 4EU",
    "sg:province":"Warwickshire",
    "wof:name":"EOS Contract Interiors",
    "wof:placetype":"venue"
},
  "geometry": {"coordinates":[-1.6264799833,52.0558204651],"type":"Point"}
}