{
  "type": "Feature",
  "properties": {
    "iso:country":"GB",
    "sg:address":"Unit 9 Sovereign Court, Graham St",
    "sg:city":"Birmingham",
    "sg:classifiers":[
        {
            "category":"Professional",
            "subcategory":"Art Services",
            "type":"Services"
        }
    ],
    "sg:phone":"+44 121 233 2727",
    "sg:postcode":"B1 3JR",
    "sg:province":"West Midlands",
    "sg:tags":[
        "graphic",
        "designer"
    ],
    "wof:name":"Switch Business Communication",
    "wof:placetype":"venue"
},
  "geometry": {"coordinates":[-1.910854,52.484337],"type":"Point"}
}