{
  "type": "Feature",
  "properties": {
    "addr:full":"1209a Neath Rd Swansea Swansea SA6 8JT",
    "addr:housenumber":"1209a",
    "addr:postcode":"sa6 8jt",
    "addr:street":"Neath Rd",
    "iso:country":"GB",
    "sg:address":"1209a Neath Rd",
    "sg:city":"Swansea",
    "sg:classifiers":[
        {
            "category":"Building & Trades",
            "subcategory":"Construction",
            "type":"Services"
        }
    ],
    "sg:phone":"+44 1792 411251",
    "sg:postcode":"SA6 8JT",
    "sg:province":"Swansea",
    "sg:tags":[
        "glazier"
    ],
    "wof:name":"Morriston Glazing Services",
    "wof:placetype":"venue"
},
  "geometry": {"coordinates":[-3.935242,51.647327],"type":"Point"}
}