{
  "type": "Feature",
  "properties": {
    "addr:full":"Crosshill Service Station, Heanor Road Codnor Ripley Derbyshire DE5 9SH",
    "addr:postcode":"de5 9sh",
    "addr:street":"Heanor Road",
    "iso:country":"GB",
    "sg:address":"Crosshill Service Station, Heanor Road Codnor",
    "sg:city":"Ripley",
    "sg:classifiers":[
        {
            "category":"Autos & Motor Vehicles",
            "subcategory":"Automobile Sales",
            "type":"Retail Goods"
        }
    ],
    "sg:phone":"+44 1773 744445",
    "sg:postcode":"DE5 9SH",
    "sg:province":"Derbyshire",
    "sg:tags":[
        "commercial"
    ],
    "wof:name":"Westhill Car Sales",
    "wof:placetype":"venue"
},
  "geometry": {"coordinates":[-1.375829,53.044216],"type":"Point"}
}