{
  "type": "Feature",
  "properties": {
    "addr:full":"3 Constable Court, Barn Street, Lavenham Sudbury Essex CO10 9RB",
    "addr:housenumber":"3",
    "addr:postcode":"co10 9rb",
    "addr:street":"Constable Court Barn Street",
    "iso:country":"GB",
    "sg:address":"3 Constable Court, Barn Street, Lavenham",
    "sg:city":"Sudbury",
    "sg:classifiers":[
        {
            "category":"Professional",
            "subcategory":"Accounting & Tax Preparation",
            "type":"Services"
        }
    ],
    "sg:phone":"+44 1787 247905",
    "sg:postcode":"CO10 9RB",
    "sg:province":"Essex",
    "sg:tags":[
        "accountant"
    ],
    "wof:name":"White Knight South East & Suffolk",
    "wof:placetype":"venue"
},
  "geometry": {"coordinates":[0.795288,52.107121],"type":"Point"}
}