{
  "type": "Feature",
  "properties": {
    "addr:full":"69-70 Victoria Arcade Great Yarmouth Norfolk NR30 2NU",
    "addr:housenumber":"69-70",
    "addr:postcode":"nr30 2nu",
    "addr:street":"Victoria Arcade;Yarmouth",
    "iso:country":"GB",
    "sg:address":"69-70 Victoria Arcade",
    "sg:city":"Great Yarmouth",
    "sg:classifiers":[
        {
            "category":"Shopping",
            "subcategory":"Baby Store",
            "type":"Retail Goods"
        }
    ],
    "sg:postcode":"NR30 2NU",
    "sg:province":"Norfolk",
    "sg:tags":[
        "nursery",
        "accessory"
    ],
    "wof:name":"Fordham,Jackie,",
    "wof:placetype":"venue"
},
  "geometry": {"coordinates":[1.7260550261,52.606426239],"type":"Point"}
}