{
  "type": "Feature",
  "properties": {
    "iso:country":"GB",
    "sg:address":"164 Trundleys Road, Deptford",
    "sg:city":"London",
    "sg:classifiers":[
        {
            "category":"Manufacturing",
            "subcategory":"Metals",
            "type":"Manufacturing & Wholesale Goods"
        }
    ],
    "sg:phone":"+44 20 8691 8406",
    "sg:postcode":"SE8 5JE",
    "sg:province":"Greater London",
    "wof:name":"Slade Green Plating (1992) Ltd.",
    "wof:placetype":"venue"
},
  "geometry": {"coordinates":[-0.04204,51.483883],"type":"Point"}
}