{
  "type": "Feature",
  "properties": {
    "iso:country":"GB",
    "sg:address":"39-40 Eastcastle Street",
    "sg:city":"London",
    "sg:classifiers":[
        {
            "category":"Shopping",
            "subcategory":"Clothing, Apparel, & Fashions",
            "type":"Retail Goods"
        },
        {
            "category":"Manufacturing",
            "subcategory":"Textiles",
            "type":"Manufacturing & Wholesale Goods"
        }
    ],
    "sg:phone":"+44 20 7631 3393",
    "sg:postcode":"W1W 8DT",
    "sg:province":"Greater London",
    "sg:tags":[
        "knitwear",
        "clothing"
    ],
    "wof:name":"Rinku Group Plc",
    "wof:placetype":"venue"
},
  "geometry": {"coordinates":[-0.139359,51.516544],"type":"Point"}
}