{
  "type": "Feature",
  "properties": {
    "addr:full":"Lochend House, Cardenen Lochgelly Fife KY5 0AX",
    "addr:postcode":"ky5 0ax",
    "addr:street":"Lochgelly",
    "iso:country":"GB",
    "sg:address":"Lochend House, Cardenen",
    "sg:city":"Lochgelly",
    "sg:classifiers":[
        {
            "category":"Freight",
            "type":"Transportation"
        }
    ],
    "sg:phone":"+44 1592 783322",
    "sg:postcode":"KY5 0AX",
    "sg:province":"Fife",
    "sg:tags":[
        "haulage",
        "road"
    ],
    "wof:name":"RED ALERT EXPRESS DELIVERIES",
    "wof:placetype":"venue"
},
  "geometry": {"coordinates":[-3.258836031,56.1438598633],"type":"Point"}
}