{
  "type": "Feature",
  "properties": {
    "iso:country":"GB",
    "sg:address":"Rear Of Henry St",
    "sg:city":"Redcar",
    "sg:classifiers":[
        {
            "category":"Retail",
            "subcategory":"Auto Repair",
            "type":"Services"
        }
    ],
    "sg:phone":"+44 1642 491717",
    "sg:postcode":"TS10 1BH",
    "sg:province":"North Yorkshire",
    "sg:tags":[
        "modification",
        "garage"
    ],
    "wof:name":"Grahams Auto Repairs",
    "wof:placetype":"venue"
},
  "geometry": {"coordinates":[-1.068344,54.614059],"type":"Point"}
}