{
  "type": "Feature",
  "properties": {
    "iso:country":"GB",
    "sg:address":"9 Beatrice Street",
    "sg:city":"Oswestry",
    "sg:classifiers":[
        {
            "category":"Personal",
            "subcategory":"Beauty Salon",
            "type":"Services"
        }
    ],
    "sg:phone":"+44 1691 652858",
    "sg:postcode":"SY11 1QE",
    "sg:province":"Shropshire",
    "sg:tags":[
        "unisex",
        "hairdresser"
    ],
    "wof:name":"Tina Edwards & Helen Hughes",
    "wof:placetype":"venue"
},
  "geometry": {"coordinates":[-3.05329,52.860832],"type":"Point"}
}