{
  "type": "Feature",
  "properties": {
    "addr:full":"39 Salisbury Road, Amesbury Salisbury Hampshire SP4 7HH",
    "addr:housenumber":"39",
    "addr:postcode":"sp4 7hh",
    "addr:street":"Salisbury Road",
    "iso:country":"GB",
    "sg:address":"39 Salisbury Road, Amesbury",
    "sg:city":"Salisbury",
    "sg:classifiers":[
        {
            "category":"Government",
            "subcategory":"City Hall",
            "type":"Public Place"
        }
    ],
    "sg:phone":"+44 1980 622435",
    "sg:postcode":"SP4 7HH",
    "sg:province":"Hampshire",
    "wof:name":"Lady Antrobus Trust",
    "wof:placetype":"venue"
},
  "geometry": {"coordinates":[-1.7783139944,51.1703414917],"type":"Point"}
}