{
  "type": "Feature",
  "properties": {
    "addr:full":"Unit 1 Gelli-hirion Industrial Estate Pontypridd Caerphilly CF37 5SX",
    "addr:housenumber":"unit 1",
    "addr:postcode":"cf37 5sx",
    "addr:street":"Gelli-Hirion Industrial Estate",
    "iso:country":"GB",
    "sg:address":"Unit 1 Gelli-hirion Industrial Estate",
    "sg:city":"Pontypridd",
    "sg:classifiers":[
        {
            "category":"Shopping",
            "subcategory":"Discount & Variety Stores",
            "type":"Retail Goods"
        }
    ],
    "sg:phone":"+44 1443 841027",
    "sg:postcode":"CF37 5SX",
    "sg:province":"Caerphilly",
    "sg:tags":[
        "centre"
    ],
    "wof:name":"Poundstretcher Ltd.",
    "wof:placetype":"venue"
},
  "geometry": {"coordinates":[-3.2937018871,51.5808410645],"type":"Point"}
}