{
  "type": "Feature",
  "properties": {
    "addr:full":"14a Common Lane, Setchey King's Lynn Norfolk PE33 0BE",
    "addr:housenumber":"14a",
    "addr:postcode":"pe33 0be",
    "addr:street":"Common Lane;Lynn",
    "iso:country":"GB",
    "sg:address":"14a Common Lane, Setchey",
    "sg:city":"King's Lynn",
    "sg:classifiers":[
        {
            "category":"Building & Trades",
            "subcategory":"Construction",
            "type":"Services"
        }
    ],
    "sg:phone":"+44 1553 811544",
    "sg:postcode":"PE33 0BE",
    "sg:province":"Norfolk",
    "sg:tags":[
        "builder"
    ],
    "wof:name":"Kentek Ltd.",
    "wof:placetype":"venue"
},
  "geometry": {"coordinates":[0.4153400064,52.6989898682],"type":"Point"}
}