{
  "type": "Feature",
  "properties": {
    "addr:full":"14 Morley St Manchester Greater Manchester M46 0AE",
    "addr:housenumber":"14",
    "addr:postcode":"m46 0ae",
    "addr:street":"Morley St",
    "iso:country":"GB",
    "sg:address":"14 Morley St",
    "sg:city":"Manchester",
    "sg:classifiers":[
        {
            "category":"Professional",
            "subcategory":"Engineering",
            "type":"Services"
        }
    ],
    "sg:phone":"+44 1942 882741",
    "sg:postcode":"M46 0AE",
    "sg:province":"Greater Manchester",
    "sg:tags":[
        "contractor",
        "electrical",
        "engineer"
    ],
    "wof:name":"J H Park & Son Ltd",
    "wof:placetype":"venue"
},
  "geometry": {"coordinates":[-2.4943490028,53.523223877],"type":"Point"}
}