{
  "type": "Feature",
  "properties": {
    "addr:full":"2 Abercrombie Street London Greater London SW11 2JD",
    "addr:housenumber":"2",
    "addr:postcode":"sw11 2jd",
    "addr:street":"Abercrombie Street",
    "iso:country":"GB",
    "sg:address":"2 Abercrombie Street",
    "sg:city":"London",
    "sg:classifiers":[
        {
            "category":"Food & Beverages",
            "subcategory":"Liquor & Beverages",
            "type":"Retail Goods"
        }
    ],
    "sg:phone":"+44 20 7652 6229",
    "sg:postcode":"SW11 2JD",
    "sg:province":"Greater London",
    "sg:tags":[
        "beer",
        "spirit",
        "wines"
    ],
    "wof:name":"Imperial Wines",
    "wof:placetype":"venue"
},
  "geometry": {"coordinates":[-0.1663890034,51.4710388184],"type":"Point"}
}