{
  "type": "Feature",
  "properties": {
    "addr:full":"29-31 Parkway Camden Greater London NW1 7PN",
    "addr:housenumber":"29-31",
    "addr:postcode":"nw1 7pn",
    "addr:street":"Parkway Camden",
    "iso:country":"GB",
    "sg:address":"29-31 Parkway",
    "sg:city":"Camden",
    "sg:classifiers":[
        {
            "category":"Restaurant",
            "type":"Food & Drink"
        }
    ],
    "sg:phone":"+44 20 7482 3940",
    "sg:postcode":"NW1 7PN",
    "sg:province":"Greater London",
    "sg:tags":[
        "chinese"
    ],
    "wof:name":"China Jazz",
    "wof:placetype":"venue"
},
  "geometry": {"coordinates":[-0.1439840049,51.5382881165],"type":"Point"}
}