{
  "type": "Feature",
  "properties": {
    "addr:full":"83 Prince Avenue Southend-on-sea Essex SS2 6RL",
    "addr:housenumber":"83",
    "addr:postcode":"ss2 6rl",
    "addr:street":"Prince Avenue",
    "iso:country":"GB",
    "sg:address":"83 Prince Avenue",
    "sg:city":"Southend-on-sea",
    "sg:classifiers":[
        {
            "category":"Personal",
            "subcategory":"Beauty Salon",
            "type":"Services"
        }
    ],
    "sg:phone":"+44 1702 341928",
    "sg:postcode":"SS2 6RL",
    "sg:province":"Essex",
    "sg:tags":[
        "unisex",
        "hairdresser"
    ],
    "wof:name":"Jamela",
    "wof:placetype":"venue"
},
  "geometry": {"coordinates":[0.6973850131,51.55834198],"type":"Point"}
}