{
  "type": "Feature",
  "properties": {
    "iso:country":"GB",
    "sg:address":"Old Birchills",
    "sg:city":"Walsall",
    "sg:classifiers":[
        {
            "category":"Museum",
            "subcategory":"Art Museum",
            "type":"Entertainment"
        },
        {
            "category":"Government",
            "subcategory":"Office",
            "type":"Public Place"
        }
    ],
    "sg:phone":"+44 1922 645778",
    "sg:postcode":"WS2 8QH",
    "sg:province":"West Midlands",
    "sg:tags":[
        "local",
        "gallery"
    ],
    "wof:name":"Canal Museum",
    "wof:placetype":"venue"
},
  "geometry": {"coordinates":[-1.990281,52.591908],"type":"Point"}
}