{
  "type": "Feature",
  "properties": {
    "iso:country":"GB",
    "sg:address":"73 Crown St West",
    "sg:city":"Lowestoft",
    "sg:classifiers":[
        {
            "category":"Bars & Pubs",
            "type":"Food & Drink"
        },
        {
            "category":"Community Center",
            "subcategory":"Social",
            "type":"Public Place"
        }
    ],
    "sg:phone":"+44 1502 537246",
    "sg:postcode":"NR32 1SQ",
    "sg:province":"Suffolk",
    "sg:tags":[
        "pubs",
        "house",
        "inn",
        "activity"
    ],
    "wof:name":"Oak Tavern",
    "wof:placetype":"venue"
},
  "geometry": {"coordinates":[1.7507590055,52.4828033447],"type":"Point"}
}