{
  "type": "Feature",
  "properties": {
    "addr:full":"37 Queens Road Thame Buckinghamshire OX9 3NF",
    "addr:housenumber":"37",
    "addr:postcode":"ox9 3nf",
    "addr:street":"Queens Road",
    "iso:country":"GB",
    "sg:address":"37 Queens Road",
    "sg:city":"Thame",
    "sg:classifiers":[
        {
            "category":"Professional",
            "subcategory":"Accounting & Tax Preparation",
            "type":"Services"
        }
    ],
    "sg:phone":"+44 1844 215595",
    "sg:postcode":"OX9 3NF",
    "sg:province":"Buckinghamshire",
    "sg:tags":[
        "accountant"
    ],
    "wof:name":"Lander Powell",
    "wof:placetype":"venue"
},
  "geometry": {"coordinates":[-0.967321,51.743137],"type":"Point"}
}