{
  "type": "Feature",
  "properties": {
    "addr:full":"4 Granville Rd Ilford Essex IG1 4JY",
    "addr:housenumber":"4",
    "addr:postcode":"ig1 4jy",
    "addr:street":"Granville Rd",
    "iso:country":"GB",
    "sg:address":"4 Granville Rd",
    "sg:city":"Ilford",
    "sg:classifiers":[
        {
            "category":"Health Services",
            "subcategory":"Doctor",
            "type":"Services"
        }
    ],
    "sg:phone":"+44 20 8270 0400",
    "sg:postcode":"IG1 4JY",
    "sg:province":"Essex",
    "sg:tags":[
        "practitioners"
    ],
    "wof:name":"Raina, C P",
    "wof:placetype":"venue"
},
  "geometry": {"coordinates":[0.0714839995,51.5631904602],"type":"Point"}
}