{
  "type": "Feature",
  "properties": {
    "iso:country":"GB",
    "sg:address":"250 Longs Drive, Yate",
    "sg:city":"Bristol",
    "sg:classifiers":[
        {
            "category":"Shopping",
            "subcategory":"Stationery & Office Supplies",
            "type":"Retail Goods"
        }
    ],
    "sg:phone":"+44 1454 880080",
    "sg:postcode":"BS37 5XR",
    "sg:province":"Gloucestershire",
    "wof:name":"Yate Express Stationers",
    "wof:placetype":"venue"
},
  "geometry": {"coordinates":[-2.4271860123,51.5456542969],"type":"Point"}
}