{
  "type": "Feature",
  "properties": {
    "iso:country":"GB",
    "sg:address":"479 Newport Rd",
    "sg:city":"Cardiff",
    "sg:classifiers":[
        {
            "category":"Shopping",
            "subcategory":"Mobile Phones",
            "type":"Retail Goods"
        }
    ],
    "sg:phone":"+44 29 2046 2137",
    "sg:postcode":"CF3 7AA",
    "sg:province":"Caerphilly",
    "wof:name":"DX Communications Ltd",
    "wof:placetype":"venue"
},
  "geometry": {"coordinates":[-3.098616,51.532078],"type":"Point"}
}