{
  "type": "Feature",
  "properties": {
    "iso:country":"GB",
    "sg:address":"18a Highdown Road, Sydenham Indstl Est",
    "sg:city":"Leamington Spa",
    "sg:classifiers":[
        {
            "category":"Professional",
            "subcategory":"Business Services",
            "type":"Services"
        }
    ],
    "sg:phone":"+44 1926 339979",
    "sg:postcode":"CV31 1XT",
    "sg:province":"Warwickshire",
    "sg:tags":[
        "house",
        "mailing"
    ],
    "wof:name":"Packmaster Ltd",
    "wof:placetype":"venue"
},
  "geometry": {"coordinates":[-1.518906,52.280884],"type":"Point"}
}