{
  "type": "Feature",
  "properties": {
    "iso:country":"GB",
    "sg:address":"4 Piper Road",
    "sg:city":"Sheffield",
    "sg:classifiers":[
        {
            "category":"Building & Trades",
            "subcategory":"Cleaning & Sanitation",
            "type":"Services"
        }
    ],
    "sg:phone":"+44 114 244 4682",
    "sg:postcode":"S5 7HY",
    "sg:province":"South Yorkshire",
    "sg:tags":[
        "commercial"
    ],
    "wof:name":"Action Cleaning",
    "wof:placetype":"venue"
},
  "geometry": {"coordinates":[-1.463693,53.413933],"type":"Point"}
}