{
  "type": "Feature",
  "properties": {
    "addr:full":"37 Smith Lane, Bromley Cross Bolton Lancashire BL7 9EZ",
    "addr:housenumber":"37",
    "addr:postcode":"bl7 9ez",
    "addr:street":"Smith Lane",
    "iso:country":"GB",
    "sg:address":"37 Smith Lane, Bromley Cross",
    "sg:city":"Bolton",
    "sg:classifiers":[
        {
            "category":"Wholesale",
            "subcategory":"Chemicals & Plastics",
            "type":"Manufacturing & Wholesale Goods"
        }
    ],
    "sg:phone":"+44 1204 304833",
    "sg:postcode":"BL7 9EZ",
    "sg:province":"Lancashire",
    "sg:tags":[
        "product",
        "allied"
    ],
    "wof:name":"Lesco Trading Ltd.",
    "wof:placetype":"venue"
},
  "geometry": {"coordinates":[-2.430313,53.623379],"type":"Point"}
}