{
  "type": "Feature",
  "properties": {
    "addr:full":"10 Milton St Dundee Dundee City DD3 6QQ",
    "addr:housenumber":"10",
    "addr:postcode":"dd3 6qq",
    "addr:street":"Milton St",
    "iso:country":"GB",
    "sg:address":"10 Milton St",
    "sg:city":"Dundee",
    "sg:classifiers":[
        {
            "category":"Shopping",
            "subcategory":"Photographic Equipment",
            "type":"Retail Goods"
        }
    ],
    "sg:phone":"+44 1382 906001",
    "sg:postcode":"DD3 6QQ",
    "sg:province":"Dundee City",
    "wof:name":"Nemisis Photographic",
    "wof:placetype":"venue"
},
  "geometry": {"coordinates":[-2.9826738834,56.4734382629],"type":"Point"}
}