{
  "type": "Feature",
  "properties": {
    "iso:country":"GB",
    "sg:address":"1 Deerhurst Avenue, Winnersh",
    "sg:city":"Wokingham",
    "sg:classifiers":[
        {
            "category":"Professional",
            "subcategory":"Engineering",
            "type":"Services"
        }
    ],
    "sg:phone":"+44 118 977 5070",
    "sg:postcode":"RG41 5NN",
    "sg:province":"Berkshire",
    "sg:tags":[
        "contractor",
        "electrical",
        "engineer"
    ],
    "wof:name":"Taylor Electrical Contractors",
    "wof:placetype":"venue"
},
  "geometry": {"coordinates":[-0.8736749887,51.4318199158],"type":"Point"}
}