{
  "type": "Feature",
  "properties": {
    "iso:country":"GB",
    "sg:address":"176 West Ferry Road, Isle Of Dogs",
    "sg:city":"London",
    "sg:classifiers":[
        {
            "category":"Food & Beverages",
            "subcategory":"Supermarket",
            "type":"Retail Goods"
        }
    ],
    "sg:phone":"+44 20 7987 1104",
    "sg:postcode":"E14 3RY",
    "sg:province":"Greater London",
    "wof:name":"Zara Food & Wine",
    "wof:placetype":"venue"
},
  "geometry": {"coordinates":[-0.013902,51.488785],"type":"Point"}
}