{
  "type": "Feature",
  "properties": {
    "iso:country":"GB",
    "sg:address":"Flat B Craig Logie, Westquarter Avenue, Westquarter",
    "sg:city":"Falkirk",
    "sg:classifiers":[
        {
            "category":"Building & Trades",
            "subcategory":"Plumbing",
            "type":"Services"
        }
    ],
    "sg:phone":"+44 1324 716591",
    "sg:postcode":"FK2 9SP",
    "sg:province":"Falkirk",
    "sg:tags":[
        "heating"
    ],
    "wof:name":"J Craig",
    "wof:placetype":"venue"
},
  "geometry": {"coordinates":[-3.739474,55.987465],"type":"Point"}
}