{
  "type": "Feature",
  "properties": {
    "addr:full":"39 Chalkwell Esplanade Westcliff-on-sea Essex SS0 8JQ",
    "addr:housenumber":"39",
    "addr:postcode":"ss0 8jq",
    "addr:street":"Chalkwell Esplanade",
    "iso:country":"GB",
    "sg:address":"39 Chalkwell Esplanade",
    "sg:city":"Westcliff-on-sea",
    "sg:classifiers":[
        {
            "category":"Professional",
            "subcategory":"Business Services",
            "type":"Services"
        }
    ],
    "sg:postcode":"SS0 8JQ",
    "sg:province":"Essex",
    "sg:tags":[
        "holding"
    ],
    "wof:name":"A Plaskow Holdings Ltd.",
    "wof:placetype":"venue"
},
  "geometry": {"coordinates":[0.6780350208,51.5368881226],"type":"Point"}
}