{
  "type": "Feature",
  "properties": {
    "iso:country":"GB",
    "sg:address":"Coles Yd, Penycoedcae",
    "sg:city":"Pontypridd",
    "sg:classifiers":[
        {
            "category":"Wholesale",
            "subcategory":"Scrap",
            "type":"Manufacturing & Wholesale Goods"
        }
    ],
    "sg:postcode":"CF37 1PL",
    "sg:province":"Caerphilly",
    "sg:tags":[
        "waste",
        "metal"
    ],
    "wof:name":"A C Iron & Steel",
    "wof:placetype":"venue"
},
  "geometry": {"coordinates":[-3.3309590816,51.5975494385],"type":"Point"}
}