{
  "type": "Feature",
  "properties": {
    "addr:full":"2 The Westbrook Centre, Grassmere Way Waterlooville Hampshire PO7 8SE",
    "addr:housenumber":"2",
    "addr:postcode":"po7 8se",
    "addr:street":"The;Grassmere Way",
    "iso:country":"GB",
    "sg:address":"2 The Westbrook Centre, Grassmere Way",
    "sg:city":"Waterlooville",
    "sg:classifiers":[
        {
            "category":"Cinema",
            "subcategory":"Movie Rental",
            "type":"Entertainment"
        },
        {
            "category":"Communications",
            "type":"Services"
        }
    ],
    "sg:postcode":"PO7 8SE",
    "sg:province":"Hampshire",
    "sg:tags":[
        "tv",
        "video",
        "radio",
        "library"
    ],
    "wof:name":"Nite Vision",
    "wof:placetype":"venue"
},
  "geometry": {"coordinates":[-1.028854,50.882633],"type":"Point"}
}