{
  "type": "Feature",
  "properties": {
    "addr:full":"6 Holford Rd Hampstead Greater London NW3 1AD",
    "addr:housenumber":"6",
    "addr:postcode":"nw3 1ad",
    "addr:street":"Holford Rd",
    "iso:country":"GB",
    "sg:address":"6 Holford Rd",
    "sg:city":"Hampstead",
    "sg:classifiers":[
        {
            "category":"Communications",
            "subcategory":"Film & Video Production",
            "type":"Services"
        }
    ],
    "sg:phone":"+44 20 7435 8674",
    "sg:postcode":"NW3 1AD",
    "sg:province":"Greater London",
    "sg:tags":[
        "tv",
        "studio"
    ],
    "wof:name":"Halas & Batchelor Animation Ltd",
    "wof:placetype":"venue"
},
  "geometry": {"coordinates":[-0.17741,51.560547],"type":"Point"}
}