{
  "type": "Feature",
  "properties": {
    "iso:country":"GB",
    "sg:address":"1a The Square, Mickleover",
    "sg:city":"Derby",
    "sg:classifiers":[
        {
            "category":"Personal",
            "subcategory":"Beauty Salon",
            "type":"Services"
        }
    ],
    "sg:phone":"+44 1332 516448",
    "sg:postcode":"DE3 0DD",
    "sg:province":"Derbyshire",
    "wof:name":"Foxy Lady Beauty Salon",
    "wof:placetype":"venue"
},
  "geometry": {"coordinates":[-1.545421,52.904018],"type":"Point"}
}