{
  "type": "Feature",
  "properties": {
    "addr:full":"2 East Forest Hall Rd Newcastle Upon Tyne Tyne and Wear NE12 9AU",
    "addr:housenumber":"2",
    "addr:postcode":"ne12 9au",
    "addr:street":"East;Hall Rd",
    "iso:country":"GB",
    "sg:address":"2 East Forest Hall Rd",
    "sg:city":"Newcastle Upon Tyne",
    "sg:classifiers":[
        {
            "category":"Food & Beverages",
            "subcategory":"Candy",
            "type":"Retail Goods"
        }
    ],
    "sg:phone":"+44 191 266 2417",
    "sg:postcode":"NE12 9AU",
    "sg:province":"Tyne and Wear",
    "sg:tags":[
        "confectioner"
    ],
    "wof:name":"SAY IT WITH CHOCOLATES",
    "wof:placetype":"venue"
},
  "geometry": {"coordinates":[-1.561396,55.0224],"type":"Point"}
}