{
  "type": "Feature",
  "properties": {
    "iso:country":"GB",
    "sg:address":"4 Woodside Avenue",
    "sg:city":"London",
    "sg:classifiers":[
        {
            "category":"Wholesale",
            "subcategory":"Machinery & Supplies",
            "type":"Manufacturing & Wholesale Goods"
        }
    ],
    "sg:phone":"+44 20 8654 4391",
    "sg:postcode":"SE25 5DJ",
    "sg:province":"Greater London",
    "sg:tags":[
        "theatrical"
    ],
    "wof:name":"Robert Allsop",
    "wof:placetype":"venue"
},
  "geometry": {"coordinates":[-0.067429,51.390129],"type":"Point"}
}