{
  "type": "Feature",
  "properties": {
    "addr:full":"Morells Barn, Park Lane,, Lower Bognor Road, Lagness, Chichester West Sussex PO20 1LR",
    "addr:postcode":"po20 1lr",
    "addr:street":"Park Lane Lower Bognor Road Lagness",
    "iso:country":"GB",
    "sg:address":"Morells Barn, Park Lane,, Lower Bognor Road, Lagness,",
    "sg:city":"Chichester",
    "sg:classifiers":[
        {
            "category":"Professional",
            "subcategory":"Accounting & Tax Preparation",
            "type":"Services"
        }
    ],
    "sg:phone":"+44 1243 266628",
    "sg:postcode":"PO20 1LR",
    "sg:province":"West Sussex",
    "sg:tags":[
        "accountant"
    ],
    "wof:name":"Acumen Wages Service",
    "wof:placetype":"venue"
},
  "geometry": {"coordinates":[-0.727784,50.800491],"type":"Point"}
}