{
  "type": "Feature",
  "properties": {
    "addr:full":"Tregevis Farm, St Martin Helston Cornwall TR12 6DN",
    "addr:postcode":"tr12 6dn",
    "iso:country":"GB",
    "sg:address":"Tregevis Farm, St Martin",
    "sg:city":"Helston",
    "sg:classifiers":[
        {
            "category":"Farming",
            "subcategory":"Dairy Farm",
            "type":"Manufacturing & Wholesale Goods"
        }
    ],
    "sg:phone":"+44 1326 231265",
    "sg:postcode":"TR12 6DN",
    "sg:province":"Cornwall",
    "wof:name":"A D & J A Bray",
    "wof:placetype":"venue"
},
  "geometry": {"coordinates":[-5.1604099274,50.069278717],"type":"Point"}
}