{
  "type": "Feature",
  "properties": {
    "addr:full":"Barton Road, Thurston Bury St Edmunds Suffolk IP31 3PD",
    "addr:postcode":"ip31 3pd",
    "addr:street":"Barton Road",
    "iso:country":"GB",
    "sg:address":"Barton Road, Thurston",
    "sg:city":"Bury St Edmunds",
    "sg:classifiers":[
        {
            "category":"Bars & Pubs",
            "type":"Food & Drink"
        }
    ],
    "sg:phone":"+44 1359 232228",
    "sg:postcode":"IP31 3PD",
    "sg:province":"Suffolk",
    "sg:tags":[
        "pubs",
        "inn"
    ],
    "wof:name":"Fox & Hounds",
    "wof:placetype":"venue"
},
  "geometry": {"coordinates":[0.804241,52.255482],"type":"Point"}
}