{
  "type": "Feature",
  "properties": {
    "addr:full":"65 Lynmouth Avenue Chelmsford Essex CM2 0TR",
    "addr:housenumber":"65",
    "addr:postcode":"cm2 0tr",
    "addr:street":"Lynmouth Avenue",
    "iso:country":"GB",
    "sg:address":"65 Lynmouth Avenue",
    "sg:city":"Chelmsford",
    "sg:classifiers":[
        {
            "category":"Building & Trades",
            "subcategory":"Construction",
            "type":"Services"
        }
    ],
    "sg:phone":"+44 1245 252488",
    "sg:postcode":"CM2 0TR",
    "sg:province":"Essex",
    "sg:tags":[
        "joiner",
        "carpenter"
    ],
    "wof:name":"John Peter Double",
    "wof:placetype":"venue"
},
  "geometry": {"coordinates":[0.478228,51.727993],"type":"Point"}
}