{
  "type": "Feature",
  "properties": {
    "addr:full":"83 Deanston Drive Glasgow Glasgow City G41 3AQ",
    "addr:housenumber":"83",
    "addr:postcode":"g41 3aq",
    "addr:street":"Deanston Drive",
    "iso:country":"GB",
    "sg:address":"83 Deanston Drive",
    "sg:city":"Glasgow",
    "sg:classifiers":[
        {
            "category":"Education",
            "subcategory":"College",
            "type":"Public Place"
        },
        {
            "category":"Education",
            "subcategory":"University",
            "type":"Public Place"
        }
    ],
    "sg:phone":"+44 141 632 8617",
    "sg:postcode":"G41 3AQ",
    "sg:province":"Glasgow City",
    "sg:tags":[
        "school",
        "outfitter"
    ],
    "wof:name":"R W Stevens & Co",
    "wof:placetype":"venue"
},
  "geometry": {"coordinates":[-4.281367,55.828735],"type":"Point"}
}