{
  "type": "Feature",
  "properties": {
    "addr:full":"12 High Street, Llanbradach Caerphilly Caerphilly CF83 3LQ",
    "addr:housenumber":"12",
    "addr:postcode":"cf83 3lq",
    "addr:street":"High Street",
    "iso:country":"GB",
    "sg:address":"12 High Street, Llanbradach",
    "sg:city":"Caerphilly",
    "sg:classifiers":[
        {
            "category":"Fast Food",
            "type":"Food & Drink"
        }
    ],
    "sg:phone":"+44 29 2088 7728",
    "sg:postcode":"CF83 3LQ",
    "sg:province":"Caerphilly",
    "sg:tags":[
        "away",
        "take"
    ],
    "wof:name":"Euro Balti",
    "wof:placetype":"venue"
},
  "geometry": {"coordinates":[-3.231112957,51.6044311523],"type":"Point"}
}