{
  "type": "Feature",
  "properties": {
    "iso:country":"GB",
    "sg:address":"St Wilfrids Square, Calverton",
    "sg:city":"Nottingham",
    "sg:classifiers":[
        {
            "category":"Health Services",
            "subcategory":"Doctor",
            "type":"Services"
        },
        {
            "category":"Restaurant",
            "type":"Food & Drink"
        }
    ],
    "sg:phone":"+44 115 965 4291",
    "sg:postcode":"NG14 6FP",
    "sg:province":"Nottinghamshire",
    "sg:tags":[
        "practitioners"
    ],
    "wof:name":"THE SURGERY",
    "wof:placetype":"venue"
},
  "geometry": {"coordinates":[-1.082414031,53.0370445251],"type":"Point"}
}