{
  "type": "Feature",
  "properties": {
    "iso:country":"GB",
    "sg:address":"Melling Road, Hornby",
    "sg:city":"Lancaster",
    "sg:classifiers":[
        {
            "category":"Sports & Exercise",
            "subcategory":"Swimming Pool",
            "type":"Entertainment"
        }
    ],
    "sg:phone":"+44 15242 21119",
    "sg:postcode":"LA2 8LH",
    "sg:province":"Lancashire",
    "wof:name":"Lunesdale Swimming Pool",
    "wof:placetype":"venue"
},
  "geometry": {"coordinates":[-2.6379880905,54.1164054871],"type":"Point"}
}