{
  "type": "Feature",
  "properties": {
    "iso:country":"GB",
    "sg:address":"Centurion Way, Centurion Park, Watling St",
    "sg:city":"Tamworth",
    "sg:classifiers":[
        {
            "category":"Professional",
            "subcategory":"Business Services",
            "type":"Services"
        }
    ],
    "sg:phone":"+44 1827 260200",
    "sg:postcode":"B77 5PN",
    "sg:province":"Staffordshire",
    "sg:tags":[
        "distribution"
    ],
    "wof:name":"UCI Logistics",
    "wof:placetype":"venue"
},
  "geometry": {"coordinates":[-1.649594,52.604424],"type":"Point"}
}