{
  "type": "Feature",
  "properties": {
    "iso:country":"GB",
    "sg:address":"Hoggatts House, Wheatley Lane, Kingsley",
    "sg:city":"Bordon",
    "sg:classifiers":[
        {
            "category":"Real Estate",
            "subcategory":"Architect",
            "type":"Services"
        }
    ],
    "sg:phone":"+44 1420 488556",
    "sg:postcode":"GU35 9NY",
    "sg:province":"Hampshire",
    "wof:name":"Ben Macdonald Associates",
    "wof:placetype":"venue"
},
  "geometry": {"coordinates":[-0.880864,51.15007],"type":"Point"}
}