{
  "type": "Feature",
  "properties": {
    "iso:country":"GB",
    "sg:address":"Snippersgate Farm, South Hetton",
    "sg:city":"Durham",
    "sg:classifiers":[
        {
            "category":"Retail",
            "subcategory":"Storage",
            "type":"Services"
        }
    ],
    "sg:phone":"+44 191 517 3577",
    "sg:postcode":"DH6 2UQ",
    "sg:province":"Durham",
    "sg:tags":[
        "household",
        "removal"
    ],
    "wof:name":"Franklin Removals & Haulage",
    "wof:placetype":"venue"
},
  "geometry": {"coordinates":[-1.4085780382,54.7999763489],"type":"Point"}
}