{
  "type": "Feature",
  "properties": {
    "addr:full":"103 Cable Depot Road Clydebank East Dunbartonshire G81 1UY",
    "addr:housenumber":"103",
    "addr:postcode":"g81 1uy",
    "addr:street":"Cable Depot Road",
    "iso:country":"GB",
    "sg:address":"103 Cable Depot Road",
    "sg:city":"Clydebank",
    "sg:classifiers":[
        {
            "category":"Wholesale",
            "subcategory":"Non-durable Goods",
            "type":"Manufacturing & Wholesale Goods"
        }
    ],
    "sg:postcode":"G81 1UY",
    "sg:province":"East Dunbartonshire",
    "sg:tags":[
        "carry",
        "cash"
    ],
    "wof:name":"Fast Foods Faster",
    "wof:placetype":"venue"
},
  "geometry": {"coordinates":[-4.419395,55.904236],"type":"Point"}
}