{
  "type": "Feature",
  "properties": {
    "iso:country":"GB",
    "sg:address":"5 Vanguard Road",
    "sg:city":"Gosport",
    "sg:classifiers":[
        {
            "category":"Professional",
            "subcategory":"Employment Agencies",
            "type":"Services"
        }
    ],
    "sg:phone":"+44 870 165 6900",
    "sg:postcode":"PO12 4FE",
    "sg:province":"Hampshire",
    "sg:tags":[
        "pair",
        "au"
    ],
    "wof:name":"Adventure Zivot Esperienza Ltd.",
    "wof:placetype":"venue"
},
  "geometry": {"coordinates":[-1.132729,50.810509],"type":"Point"}
}