{
  "type": "Feature",
  "properties": {
    "iso:country":"GB",
    "sg:address":"42 Chiltern Street",
    "sg:city":"London",
    "sg:classifiers":[
        {
            "category":"Shopping",
            "subcategory":"Clothing, Apparel, & Fashions",
            "type":"Retail Goods"
        }
    ],
    "sg:phone":"+44 20 7486 9838",
    "sg:postcode":"W1U 7QQ",
    "sg:province":"Greater London",
    "sg:tags":[
        "shop"
    ],
    "wof:name":"Sahara",
    "wof:placetype":"venue"
},
  "geometry": {"coordinates":[-0.154761,51.519215],"type":"Point"}
}