{
  "type": "Feature",
  "properties": {
    "iso:country":"GB",
    "sg:address":"New Zealand Ho, 18 Water St",
    "sg:city":"Liverpool",
    "sg:classifiers":[
        {
            "category":"Professional",
            "subcategory":"Lawyer & Legal Services",
            "type":"Services"
        }
    ],
    "sg:postcode":"L2 8TD",
    "sg:province":"Merseyside",
    "sg:tags":[
        "solicitor"
    ],
    "wof:name":"France-Hayhurst & Partners",
    "wof:placetype":"venue"
},
  "geometry": {"coordinates":[-2.9934298992,53.4063186646],"type":"Point"}
}