{
  "type": "Feature",
  "properties": {
    "iso:country":"GB",
    "sg:address":"29 The Green",
    "sg:city":"Southall",
    "sg:classifiers":[
        {
            "category":"Manufacturing",
            "subcategory":"Petroleum Products",
            "type":"Manufacturing & Wholesale Goods"
        }
    ],
    "sg:phone":"+44 20 8574 8342",
    "sg:postcode":"UB2 4AN",
    "sg:province":"Greater London",
    "sg:tags":[
        "double",
        "glazing"
    ],
    "wof:name":"Ideal Glazing (Euro) Ltd.",
    "wof:placetype":"venue"
},
  "geometry": {"coordinates":[-0.379631,51.504276],"type":"Point"}
}