{
  "type": "Feature",
  "properties": {
    "addr:full":"Elmtree House, Old Walls Swansea Swansea SA3 1HA",
    "addr:postcode":"sa3 1ha",
    "addr:street":"Old Walls",
    "iso:country":"GB",
    "sg:address":"Elmtree House, Old Walls",
    "sg:city":"Swansea",
    "sg:classifiers":[
        {
            "category":"Building & Trades",
            "subcategory":"Landscaping Services",
            "type":"Services"
        }
    ],
    "sg:postcode":"SA3 1HA",
    "sg:province":"Swansea",
    "sg:tags":[
        "contractor",
        "drainage"
    ],
    "wof:name":"Alan Williams Drainage Ltd.",
    "wof:placetype":"venue"
},
  "geometry": {"coordinates":[-4.1840901375,51.6054611206],"type":"Point"}
}