{
  "type": "Feature",
  "properties": {
    "addr:full":"Emergency Care Line Service, Basildon Centre, St Martins Sq Basildon Essex SS14 1DL",
    "addr:postcode":"ss14 1dl",
    "addr:street":"St Martins Sq",
    "iso:country":"GB",
    "sg:address":"Emergency Care Line Service, Basildon Centre, St Martins Sq",
    "sg:city":"Basildon",
    "sg:classifiers":[
        {
            "category":"Social Services",
            "subcategory":"Retirement Home",
            "type":"Services"
        }
    ],
    "sg:phone":"+44 1268 294477",
    "sg:postcode":"SS14 1DL",
    "sg:province":"Essex",
    "sg:tags":[
        "care"
    ],
    "wof:name":"Basildon Care Line",
    "wof:placetype":"venue"
},
  "geometry": {"coordinates":[0.4546999931,51.570728302],"type":"Point"}
}