{
  "type": "Feature",
  "properties": {
    "addr:full":"Brewery Ho, 18-20 Hambrook St Southsea Hampshire PO5 3BE",
    "addr:housenumber":"18-20",
    "addr:postcode":"po5 3be",
    "addr:street":"Hambrook St",
    "iso:country":"GB",
    "sg:address":"Brewery Ho, 18-20 Hambrook St",
    "sg:city":"Southsea",
    "sg:classifiers":[
        {
            "category":"Community Center",
            "subcategory":"Youth",
            "type":"Public Place"
        }
    ],
    "sg:phone":"+44 23 9281 1120",
    "sg:postcode":"PO5 3BE",
    "sg:province":"Hampshire",
    "sg:tags":[
        "organisation",
        "centre"
    ],
    "wof:name":"Air Training Corps",
    "wof:placetype":"venue"
},
  "geometry": {"coordinates":[-1.0881639719,50.7846641541],"type":"Point"}
}