{
  "type": "Feature",
  "properties": {
    "addr:full":"12 Woodhurst Avenue Watford Hertfordshire WD25 9RQ",
    "addr:housenumber":"12",
    "addr:postcode":"wd25 9rq",
    "addr:street":"Woodhurst Avenue",
    "iso:country":"GB",
    "sg:address":"12 Woodhurst Avenue",
    "sg:city":"Watford",
    "sg:classifiers":[
        {
            "category":"Real Estate",
            "subcategory":"Architect",
            "type":"Services"
        }
    ],
    "sg:phone":"+44 1923 893431",
    "sg:postcode":"WD25 9RQ",
    "sg:province":"Hertfordshire",
    "wof:name":"Kelly Morrell Architects Ltd.",
    "wof:placetype":"venue"
},
  "geometry": {"coordinates":[-0.3852759898,51.6883354187],"type":"Point"}
}