{
  "type": "Feature",
  "properties": {
    "iso:country":"GB",
    "sg:address":"259 Watling Street",
    "sg:city":"Radlett",
    "sg:classifiers":[
        {
            "category":"Personal",
            "subcategory":"Beauty Salon",
            "type":"Services"
        }
    ],
    "sg:phone":"+44 1923 853202",
    "sg:postcode":"WD7 7LA",
    "sg:province":"Hertfordshire",
    "wof:name":"Apricot Beauty Studio",
    "wof:placetype":"venue"
},
  "geometry": {"coordinates":[-0.317549,51.683929],"type":"Point"}
}