{
  "type": "Feature",
  "properties": {
    "addr:full":"97 School Street, Darfield Barnsley South Yorkshire S73 9EZ",
    "addr:housenumber":"97",
    "addr:postcode":"s73 9ez",
    "addr:street":"School Street;Yorkshire",
    "iso:country":"GB",
    "sg:address":"97 School Street, Darfield",
    "sg:city":"Barnsley",
    "sg:classifiers":[
        {
            "category":"Organizations",
            "subcategory":"Membership Organization",
            "type":"Services"
        }
    ],
    "sg:phone":"+44 1226 752993",
    "sg:postcode":"S73 9EZ",
    "sg:province":"South Yorkshire",
    "sg:tags":[
        "club",
        "social"
    ],
    "wof:name":"Darfield Conservative Club",
    "wof:placetype":"venue"
},
  "geometry": {"coordinates":[-1.372789,53.536671],"type":"Point"}
}