{
  "type": "Feature",
  "properties": {
    "iso:country":"GB",
    "sg:address":"7-8 Nelson Street, Jericho",
    "sg:city":"Oxford",
    "sg:classifiers":[
        {
            "category":"Bars & Pubs",
            "type":"Food & Drink"
        }
    ],
    "sg:postcode":"OX2 6BD",
    "sg:province":"Oxfordshire",
    "sg:tags":[
        "pubs",
        "inn"
    ],
    "wof:name":"Carpenters Arms",
    "wof:placetype":"venue"
},
  "geometry": {"coordinates":[-1.266831,51.756832],"type":"Point"}
}