{
  "type": "Feature",
  "properties": {
    "iso:country":"GB",
    "sg:address":"99 St Marks Road",
    "sg:city":"Henley-on-thames",
    "sg:classifiers":[
        {
            "category":"Professional",
            "subcategory":"Management & Consulting",
            "type":"Services"
        }
    ],
    "sg:postcode":"RG9 1LP",
    "sg:province":"Berkshire",
    "sg:tags":[
        "consultant",
        "business"
    ],
    "wof:name":"Wits End Consulting",
    "wof:placetype":"venue"
},
  "geometry": {"coordinates":[-0.9097210169,51.5295372009],"type":"Point"}
}