{
  "type": "Feature",
  "properties": {
    "addr:full":", Dylife Llanbrynmair Powys SY19 7BW",
    "addr:postcode":"sy19 7bw",
    "addr:street":"Llanbrynmair",
    "iso:country":"GB",
    "sg:address":", Dylife",
    "sg:city":"Llanbrynmair",
    "sg:classifiers":[
        {
            "category":"Bars & Pubs",
            "type":"Food & Drink"
        }
    ],
    "sg:phone":"+44 1650 521345",
    "sg:postcode":"SY19 7BW",
    "sg:province":"Powys",
    "sg:tags":[
        "pubs",
        "inn"
    ],
    "wof:name":"Star Inn",
    "wof:placetype":"venue"
},
  "geometry": {"coordinates":[-3.636218071,52.5857391357],"type":"Point"}
}