{
  "type": "Feature",
  "properties": {
    "addr:full":"77 Grangepans Bo'ness Falkirk EH51 9PH",
    "addr:housenumber":"77",
    "addr:postcode":"eh51 9ph",
    "addr:street":"Grangepans",
    "iso:country":"GB",
    "sg:address":"77 Grangepans",
    "sg:city":"Bo'ness",
    "sg:classifiers":[
        {
            "category":"Food & Beverages",
            "subcategory":"Bakery",
            "type":"Retail Goods"
        }
    ],
    "sg:phone":"+44 1506 823503",
    "sg:postcode":"EH51 9PH",
    "sg:province":"Falkirk",
    "sg:tags":[
        "shop",
        "baker"
    ],
    "wof:name":"James Horn & Sons",
    "wof:placetype":"venue"
},
  "geometry": {"coordinates":[-3.5932300091,56.0161209106],"type":"Point"}
}