{
  "type": "Feature",
  "properties": {
    "iso:country":"GB",
    "sg:address":"19 Marian Square",
    "sg:city":"Bootle",
    "sg:classifiers":[
        {
            "category":"Shopping",
            "subcategory":"News",
            "type":"Retail Goods"
        }
    ],
    "sg:phone":"+44 151 524 1646",
    "sg:postcode":"L30 5QA",
    "sg:province":"Merseyside",
    "sg:tags":[
        "newsagent"
    ],
    "wof:name":"Martin the Newsagent",
    "wof:placetype":"venue"
},
  "geometry": {"coordinates":[-2.971981,53.487915],"type":"Point"}
}