{
  "type": "Feature",
  "properties": {
    "addr:full":"27 Pavenhill, Purton Swindon Wiltshire SN5 4BZ",
    "addr:housenumber":"27",
    "addr:postcode":"sn5 4bz",
    "addr:street":"Pavenhill",
    "iso:country":"GB",
    "sg:address":"27 Pavenhill, Purton",
    "sg:city":"Swindon",
    "sg:classifiers":[
        {
            "category":"Bars & Pubs",
            "type":"Food & Drink"
        }
    ],
    "sg:phone":"+44 1793 770378",
    "sg:postcode":"SN5 4BZ",
    "sg:province":"Wiltshire",
    "sg:tags":[
        "pubs",
        "inn"
    ],
    "wof:name":"The Royal George Inn",
    "wof:placetype":"venue"
},
  "geometry": {"coordinates":[-1.872827,51.592167],"type":"Point"}
}