{
  "type": "Feature",
  "properties": {
    "addr:full":"Unit 1, Erskine Street, Nechells Birmingham West Midlands B7 4RU",
    "addr:housenumber":"unit 1",
    "addr:postcode":"b7 4ru",
    "addr:street":"Erskine Street",
    "iso:country":"GB",
    "sg:address":"Unit 1, Erskine Street, Nechells",
    "sg:city":"Birmingham",
    "sg:classifiers":[
        {
            "category":"Manufacturing",
            "subcategory":"Metals",
            "type":"Manufacturing & Wholesale Goods"
        }
    ],
    "sg:phone":"+44 121 359 1018",
    "sg:postcode":"B7 4RU",
    "sg:province":"West Midlands",
    "sg:tags":[
        "product",
        "fabricated"
    ],
    "wof:name":"A G Lester & Sons Ltd",
    "wof:placetype":"venue"
},
  "geometry": {"coordinates":[-1.8754919767,52.4858856201],"type":"Point"}
}