{
  "type": "Feature",
  "properties": {
    "addr:full":"A M I, Supplies Charlesfield, St.boswells Melrose Scottish Borders TD6 0HH",
    "addr:postcode":"td6 0hh",
    "addr:street":"A",
    "iso:country":"GB",
    "sg:address":"A M I, Supplies Charlesfield, St.boswells",
    "sg:city":"Melrose",
    "sg:classifiers":[
        {
            "category":"Manufacturing",
            "subcategory":"Chemicals & Compounds",
            "type":"Manufacturing & Wholesale Goods"
        }
    ],
    "sg:phone":"+44 1835 823750",
    "sg:postcode":"TD6 0HH",
    "sg:province":"Scottish Borders",
    "sg:tags":[
        "manufacturer"
    ],
    "sg:website":"http://www.amtecindustries.co.uk",
    "wof:name":"Amtech Industries",
    "wof:placetype":"venue"
},
  "geometry": {"coordinates":[-2.6619598866,55.5573387146],"type":"Point"}
}