{
  "type": "Feature",
  "properties": {
    "iso:country":"GB",
    "sg:address":"Plot 3, Brunel Drve Indstl Est",
    "sg:city":"Newark",
    "sg:classifiers":[
        {
            "category":"Home & Garden",
            "subcategory":"Home Furnishings",
            "type":"Retail Goods"
        },
        {
            "category":"Manufacturing",
            "subcategory":"Building Materials",
            "type":"Manufacturing & Wholesale Goods"
        }
    ],
    "sg:postcode":"NG24 1XR",
    "sg:province":"Nottinghamshire",
    "sg:tags":[
        "planner",
        "door",
        "supp",
        "shutter",
        "furnishers",
        "kitchen"
    ],
    "wof:name":"Belvoir Interiors",
    "wof:placetype":"venue"
},
  "geometry": {"coordinates":[-0.8093469739,53.0738945007],"type":"Point"}
}