{
  "type": "Feature",
  "properties": {
    "addr:full":"22 Hemdean Road, Caversham Reading Berkshire RG4 7SU",
    "addr:housenumber":"22",
    "addr:postcode":"rg4 7su",
    "addr:street":"Hemdean Road",
    "iso:country":"GB",
    "sg:address":"22 Hemdean Road, Caversham",
    "sg:city":"Reading",
    "sg:classifiers":[
        {
            "category":"Health Services",
            "subcategory":"Health Practitioner",
            "type":"Services"
        }
    ],
    "sg:postcode":"RG4 7SU",
    "sg:province":"Berkshire",
    "sg:tags":[
        "technique",
        "alexander"
    ],
    "wof:name":"Michelle Holdaway",
    "wof:placetype":"venue"
},
  "geometry": {"coordinates":[-0.9740059972,51.4696083069],"type":"Point"}
}