{
  "type": "Feature",
  "properties": {
    "iso:country":"GB",
    "sg:address":"Chester St",
    "sg:city":"Wrexham",
    "sg:classifiers":[
        {
            "category":"Government",
            "subcategory":"Office",
            "type":"Public Place"
        }
    ],
    "sg:phone":"+44 1978 351574",
    "sg:postcode":"LL13 8BG",
    "sg:province":"Wrexham",
    "sg:tags":[
        "education",
        "agency",
        "authority"
    ],
    "wof:name":"Office of Her Majesty's Chief Inspector",
    "wof:placetype":"venue"
},
  "geometry": {"coordinates":[-2.9915189743,53.0455513],"type":"Point"}
}