{
  "type": "Feature",
  "properties": {
    "addr:full":"Unit 5, Crownfield Wycombe Rd, Saunderton Princes Risborough Buckinghamshire HP27 9NR",
    "addr:housenumber":"unit 5",
    "addr:postcode":"hp27 9nr",
    "addr:street":"Crownfield Wycombe Rd",
    "iso:country":"GB",
    "sg:address":"Unit 5, Crownfield Wycombe Rd, Saunderton",
    "sg:city":"Princes Risborough",
    "sg:classifiers":[
        {
            "category":"Bus Charters",
            "type":"Transportation"
        }
    ],
    "sg:phone":"+44 1844 273304",
    "sg:postcode":"HP27 9NR",
    "sg:province":"Buckinghamshire",
    "sg:tags":[
        "hire",
        "coach"
    ],
    "wof:name":"Wootten's Luxury Travel",
    "wof:placetype":"venue"
},
  "geometry": {"coordinates":[-0.8505380154,51.711265564],"type":"Point"}
}