{
  "type": "Feature",
  "properties": {
    "addr:full":"Unit 5, Chapmans Park, 388 High Street London Greater London NW10 2DY",
    "addr:housenumber":"unit 5;388",
    "addr:postcode":"nw10 2dy",
    "addr:street":"Chapmans Park;High Street",
    "iso:country":"GB",
    "sg:address":"Unit 5, Chapmans Park, 388 High Street",
    "sg:city":"London",
    "sg:classifiers":[
        {
            "category":"Shopping",
            "subcategory":"Computers & Home Electronics",
            "type":"Retail Goods"
        }
    ],
    "sg:phone":"+44 20 8451 5544",
    "sg:postcode":"NW10 2DY",
    "sg:province":"Greater London",
    "sg:tags":[
        "equipment",
        "audio-visual"
    ],
    "wof:name":"Zomba Music Publishers Ltd.",
    "wof:placetype":"venue"
},
  "geometry": {"coordinates":[-0.243599996,51.5492286682],"type":"Point"}
}