{
  "type": "Feature",
  "properties": {
    "iso:country":"GB",
    "sg:address":"21 Bradford Lane",
    "sg:city":"Bradford",
    "sg:classifiers":[
        {
            "category":"Building & Trades",
            "subcategory":"Cleaning & Sanitation",
            "type":"Services"
        }
    ],
    "sg:postcode":"BD3 8LP",
    "sg:province":"West Yorkshire",
    "sg:tags":[
        "dry",
        "control",
        "damp",
        "rot"
    ],
    "wof:name":"Multiskill",
    "wof:placetype":"venue"
},
  "geometry": {"coordinates":[-1.714971,53.794094],"type":"Point"}
}