{
  "type": "Feature",
  "properties": {
    "addr:full":"21 Bradford Lane Bradford West Yorkshire BD3 8LP",
    "addr:housenumber":"21",
    "addr:postcode":"bd3 8lp",
    "addr:street":"Bradford Lane",
    "iso:country":"GB",
    "sg:address":"21 Bradford Lane",
    "sg:city":"Bradford",
    "sg:classifiers":[
        {
            "category":"Building & Trades",
            "subcategory":"Cleaning & Sanitation",
            "type":"Services"
        }
    ],
    "sg:postcode":"BD3 8LP",
    "sg:province":"West Yorkshire",
    "sg:tags":[
        "dry",
        "control",
        "damp",
        "rot"
    ],
    "wof:name":"Multiskill",
    "wof:placetype":"venue"
},
  "geometry": {"coordinates":[-1.714971,53.794094],"type":"Point"}
}