{
  "type": "Feature",
  "properties": {
    "addr:full":"Unit 6 Barkington Business Park, Staverton Totnes Devon TQ9 6AN",
    "addr:housenumber":"unit 6",
    "addr:postcode":"tq9 6an",
    "addr:street":"Barkington Business Park",
    "iso:country":"GB",
    "sg:address":"Unit 6 Barkington Business Park, Staverton",
    "sg:city":"Totnes",
    "sg:classifiers":[
        {
            "category":"Professional",
            "subcategory":"Art Services",
            "type":"Services"
        }
    ],
    "sg:phone":"+44 1803 762311",
    "sg:postcode":"TQ9 6AN",
    "sg:province":"Devon",
    "sg:tags":[
        "framing"
    ],
    "wof:name":"On Reflection",
    "wof:placetype":"venue"
},
  "geometry": {"coordinates":[-3.701889,50.463982],"type":"Point"}
}