{
  "type": "Feature",
  "properties": {
    "iso:country":"GB",
    "sg:address":"31 High Street",
    "sg:city":"Buxton",
    "sg:classifiers":[
        {
            "category":"Fast Food",
            "type":"Food & Drink"
        }
    ],
    "sg:phone":"+44 1298 78476",
    "sg:postcode":"SK17 6HA",
    "sg:province":"Derbyshire",
    "sg:tags":[
        "away",
        "take"
    ],
    "wof:name":"The Corner Cupboard",
    "wof:placetype":"venue"
},
  "geometry": {"coordinates":[-1.915283,53.254452],"type":"Point"}
}