{
  "type": "Feature",
  "properties": {
    "addr:full":"71 Regents Park Rd Camden Greater London NW1 8UY",
    "addr:housenumber":"71",
    "addr:postcode":"nw1 8uy",
    "addr:street":"Regents Park Rd",
    "iso:country":"GB",
    "sg:address":"71 Regents Park Rd",
    "sg:city":"Camden",
    "sg:classifiers":[
        {
            "category":"Cafe",
            "type":"Food & Drink"
        }
    ],
    "sg:phone":"+44 20 7586 7067",
    "sg:postcode":"NW1 8UY",
    "sg:province":"Greater London",
    "sg:tags":[
        "tea",
        "room"
    ],
    "wof:name":"Park's Cafe",
    "wof:placetype":"venue"
},
  "geometry": {"coordinates":[-0.1575330049,51.5411682129],"type":"Point"}
}