{
  "type": "Feature",
  "properties": {
    "iso:country":"GB",
    "sg:address":"38 Replingham Road",
    "sg:city":"London",
    "sg:classifiers":[
        {
            "category":"Deli",
            "type":"Food & Drink"
        }
    ],
    "sg:phone":"+44 20 8874 2138",
    "sg:postcode":"SW18 5LR",
    "sg:province":"Greater London",
    "sg:tags":[
        "delicatessen"
    ],
    "wof:name":"Brotherhoods Quality Food & Wine",
    "wof:placetype":"venue"
},
  "geometry": {"coordinates":[-0.204118,51.444881],"type":"Point"}
}