{
  "type": "Feature",
  "properties": {
    "addr:full":"4 St Marys Park Grn, Hill Top Leeds West Yorkshire LS12 3UY",
    "addr:housenumber":"4",
    "addr:postcode":"ls12 3uy",
    "addr:street":"St Marys Park Grn;Top;West",
    "iso:country":"GB",
    "sg:address":"4 St Marys Park Grn, Hill Top",
    "sg:city":"Leeds",
    "sg:classifiers":[
        {
            "category":"Professional",
            "subcategory":"Detective & Security Services",
            "type":"Services"
        }
    ],
    "sg:postcode":"LS12 3UY",
    "sg:province":"West Yorkshire",
    "wof:name":"Total Security Systems (U K) Ltd",
    "wof:placetype":"venue"
},
  "geometry": {"coordinates":[-1.610435,53.799023],"type":"Point"}
}