{
  "type": "Feature",
  "properties": {
    "addr:full":"59-60 High St Battle East Sussex TN33 0EN",
    "addr:housenumber":"59-60",
    "addr:postcode":"tn33 0en",
    "addr:street":"High St",
    "iso:country":"GB",
    "sg:address":"59-60 High St",
    "sg:city":"Battle",
    "sg:classifiers":[
        {
            "category":"Shopping",
            "subcategory":"Clothing, Apparel, & Fashions",
            "type":"Retail Goods"
        }
    ],
    "sg:postcode":"TN33 0EN",
    "sg:province":"East Sussex",
    "sg:tags":[
        "lingerie",
        "hosiery"
    ],
    "wof:name":"Whispers of Battle Ltd",
    "wof:placetype":"venue"
},
  "geometry": {"coordinates":[0.48554,50.915791],"type":"Point"}
}