{
  "type": "Feature",
  "properties": {
    "iso:country":"GB",
    "sg:address":"16 Greenhill Crescent, Watford Business Park",
    "sg:city":"Watford",
    "sg:classifiers":[
        {
            "category":"Wholesale",
            "subcategory":"Machinery & Supplies",
            "type":"Manufacturing & Wholesale Goods"
        }
    ],
    "sg:phone":"+44 1923 231661",
    "sg:postcode":"WD18 8SE",
    "sg:province":"Hertfordshire",
    "sg:tags":[
        "hydraulic"
    ],
    "wof:name":"Ram Power Ltd.",
    "wof:placetype":"venue"
},
  "geometry": {"coordinates":[-0.425377,51.645634],"type":"Point"}
}