{
  "type": "Feature",
  "properties": {
    "iso:country":"GB",
    "sg:address":"47b Overstone Road, Northampton",
    "sg:city":"Northampton",
    "sg:classifiers":[
        {
            "category":"Professional",
            "subcategory":"Management & Consulting",
            "type":"Services"
        }
    ],
    "sg:postcode":"NN1 3JL",
    "sg:province":"Northamptonshire",
    "sg:tags":[
        "consultant",
        "business"
    ],
    "wof:name":"Winterburn Consulting Services Ltd.",
    "wof:placetype":"venue"
},
  "geometry": {"coordinates":[-0.889961,52.242558],"type":"Point"}
}