{
  "type": "Feature",
  "properties": {
    "addr:full":"46 Sinclair Street Helensburgh Argyll and Bute G84 8TQ",
    "addr:housenumber":"46",
    "addr:postcode":"g84 8tq",
    "addr:street":"Sinclair Street",
    "iso:country":"GB",
    "sg:address":"46 Sinclair Street",
    "sg:city":"Helensburgh",
    "sg:classifiers":[
        {
            "category":"Personal",
            "subcategory":"Beauty Salon",
            "type":"Services"
        }
    ],
    "sg:phone":"+44 1436 672262",
    "sg:postcode":"G84 8TQ",
    "sg:province":"Argyll and Bute",
    "sg:tags":[
        "lady",
        "hairdresser"
    ],
    "wof:name":"Central Hairdressers",
    "wof:placetype":"venue"
},
  "geometry": {"coordinates":[-4.7333750725,56.0039176941],"type":"Point"}
}