{
  "type": "Feature",
  "properties": {
    "addr:full":"Southern Av Leominster Herefordshire HR6 0QF",
    "addr:postcode":"hr6 0qf",
    "addr:street":"Av Leominster",
    "iso:country":"GB",
    "sg:address":"Southern Av",
    "sg:city":"Leominster",
    "sg:classifiers":[
        {
            "category":"Freight",
            "type":"Transportation"
        }
    ],
    "sg:phone":"+44 1568 615878",
    "sg:postcode":"HR6 0QF",
    "sg:province":"Herefordshire",
    "sg:tags":[
        "haulage",
        "road"
    ],
    "wof:name":"Coldstream",
    "wof:placetype":"venue"
},
  "geometry": {"coordinates":[-2.733699,52.218327],"type":"Point"}
}