{
  "type": "Feature",
  "properties": {
    "addr:full":"18 Medland Avenue Coventry Warwickshire CV3 6NW",
    "addr:housenumber":"18",
    "addr:postcode":"cv3 6nw",
    "addr:street":"Medland Avenue",
    "iso:country":"GB",
    "sg:address":"18 Medland Avenue",
    "sg:city":"Coventry",
    "sg:classifiers":[
        {
            "category":"Bus Charters",
            "type":"Transportation"
        }
    ],
    "sg:postcode":"CV3 6NW",
    "sg:province":"Warwickshire",
    "sg:tags":[
        "hire",
        "coach"
    ],
    "wof:name":"Miles Travel",
    "wof:placetype":"venue"
},
  "geometry": {"coordinates":[-1.532319,52.381313],"type":"Point"}
}