{
  "type": "Feature",
  "properties": {
    "addr:full":"Rosebank, Carnbo Kinross Clackmannanshire KY13 7NX",
    "addr:postcode":"ky13 7nx",
    "iso:country":"GB",
    "sg:address":"Rosebank, Carnbo",
    "sg:city":"Kinross",
    "sg:classifiers":[
        {
            "category":"Building & Trades",
            "subcategory":"Construction",
            "type":"Services"
        }
    ],
    "sg:phone":"+44 1577 840281",
    "sg:postcode":"KY13 7NX",
    "sg:province":"Clackmannanshire",
    "sg:tags":[
        "joiner",
        "carpenter"
    ],
    "wof:name":"Ben & John Anderson",
    "wof:placetype":"venue"
},
  "geometry": {"coordinates":[-3.425514,56.211327],"type":"Point"}
}