{
  "type": "Feature",
  "properties": {
    "iso:country":"GB",
    "sg:address":"50 Culver Street",
    "sg:city":"Newent",
    "sg:classifiers":[
        {
            "category":"Professional",
            "subcategory":"Management & Consulting",
            "type":"Services"
        },
        {
            "category":"Real Estate",
            "subcategory":"Architect",
            "type":"Services"
        }
    ],
    "sg:phone":"+44 1531 822121",
    "sg:postcode":"GL18 1DA",
    "sg:province":"Gloucestershire",
    "sg:tags":[
        "consultant",
        "energy",
        "conservation"
    ],
    "wof:name":"Vilnis Vesma & Co.",
    "wof:placetype":"venue"
},
  "geometry": {"coordinates":[-2.4061551094,51.9291725159],"type":"Point"}
}