{
  "type": "Feature",
  "properties": {
    "addr:full":"17 Farfield Park Oak Road, Wath Upon Dearne Rotherham South Yorkshire S63 7BD",
    "addr:housenumber":"17",
    "addr:postcode":"s63 7bd",
    "addr:street":"Farfield Park Oak Road",
    "iso:country":"GB",
    "sg:address":"17 Farfield Park Oak Road, Wath Upon Dearne",
    "sg:city":"Rotherham",
    "sg:classifiers":[
        {
            "category":"Manufacturing",
            "subcategory":"Wood Products",
            "type":"Manufacturing & Wholesale Goods"
        }
    ],
    "sg:postcode":"S63 7BD",
    "sg:province":"South Yorkshire",
    "sg:tags":[
        "packaging",
        "crate",
        "pallets"
    ],
    "wof:name":"Pro-Pack Packaging Ltd",
    "wof:placetype":"venue"
},
  "geometry": {"coordinates":[-1.343864,53.503567],"type":"Point"}
}