{
  "type": "Feature",
  "properties": {
    "addr:full":"6 Hendrix Drive, Crownhill Milton Keynes Buckinghamshire MK8 0EH",
    "addr:housenumber":"6",
    "addr:postcode":"mk8 0eh",
    "addr:street":"Hendrix Drive",
    "iso:country":"GB",
    "sg:address":"6 Hendrix Drive, Crownhill",
    "sg:city":"Milton Keynes",
    "sg:classifiers":[
        {
            "category":"Health Services",
            "subcategory":"Nursing And Care Facility",
            "type":"Services"
        },
        {
            "category":"Organizations",
            "subcategory":"Non-profit Organization",
            "type":"Services"
        }
    ],
    "sg:phone":"+44 1908 562741",
    "sg:postcode":"MK8 0EH",
    "sg:province":"Buckinghamshire",
    "sg:tags":[
        "charitable",
        "organisation",
        "charity",
        "home"
    ],
    "wof:name":"Milton Keynes Carr-Gomm Society Ltd.",
    "wof:placetype":"venue"
},
  "geometry": {"coordinates":[-0.807969,52.02787],"type":"Point"}
}