{
  "type": "Feature",
  "properties": {
    "iso:country":"GB",
    "sg:address":"95 Ashby Rd",
    "sg:city":"Loughborough",
    "sg:classifiers":[
        {
            "category":"Health Services",
            "subcategory":"Health Practitioner",
            "type":"Services"
        }
    ],
    "sg:phone":"+44 1509 262880",
    "sg:postcode":"LE11 3AB",
    "sg:province":"Leicestershire",
    "sg:tags":[
        "osteopath"
    ],
    "wof:name":"J.D Butler",
    "wof:placetype":"venue"
},
  "geometry": {"coordinates":[-1.215216,52.772469],"type":"Point"}
}