{
  "type": "Feature",
  "properties": {
    "addr:full":"25 Lock Cres Kidlington Buckinghamshire OX5 1HD",
    "addr:housenumber":"25",
    "addr:postcode":"ox5 1hd",
    "addr:street":"Lock Cres",
    "iso:country":"GB",
    "sg:address":"25 Lock Cres",
    "sg:city":"Kidlington",
    "sg:classifiers":[
        {
            "category":"Military Area",
            "subcategory":"Air Force Base",
            "type":"Public Place"
        }
    ],
    "sg:phone":"+44 1865 377313",
    "sg:postcode":"OX5 1HD",
    "sg:province":"Buckinghamshire",
    "sg:tags":[
        "taxi",
        "hire",
        "private"
    ],
    "wof:name":"K Cars",
    "wof:placetype":"venue"
},
  "geometry": {"coordinates":[-1.286031,51.810417],"type":"Point"}
}