{
  "type": "Feature",
  "properties": {
    "iso:country":"GB",
    "sg:address":"521 Seven Sisters Rd",
    "sg:city":"Seven Sisters",
    "sg:classifiers":[
        {
            "category":"Taxi",
            "type":"Transportation"
        }
    ],
    "sg:phone":"+44 20 8802 5166",
    "sg:postcode":"N15 6EP",
    "sg:province":"Greater London",
    "sg:tags":[
        "mini",
        "hire",
        "cab",
        "private",
        "vehicle"
    ],
    "wof:name":"Prestige Car Services",
    "wof:placetype":"venue"
},
  "geometry": {"coordinates":[-0.081363,51.57922],"type":"Point"}
}