{
  "type": "Feature",
  "properties": {
    "iso:country":"GB",
    "sg:address":"12 Manton Centre, Manton Lane, Manton Industrial Estate",
    "sg:city":"Bedford",
    "sg:classifiers":[
        {
            "category":"Wholesale",
            "subcategory":"Books, Periodicals, & Newspapers",
            "type":"Manufacturing & Wholesale Goods"
        }
    ],
    "sg:phone":"+44 1234 306900",
    "sg:postcode":"MK41 7PX",
    "sg:province":"Bedfordshire",
    "sg:tags":[
        "publishing"
    ],
    "wof:name":"3 Cheers Publications Ltd.",
    "wof:placetype":"venue"
},
  "geometry": {"coordinates":[-0.477326,52.151211],"type":"Point"}
}