{
  "type": "Feature",
  "properties": {
    "addr:full":"Manor Farm, Childs Ercall Market Drayton Shropshire TF9 2DG",
    "addr:postcode":"tf9 2dg",
    "addr:street":"Manor",
    "iso:country":"GB",
    "sg:address":"Manor Farm, Childs Ercall",
    "sg:city":"Market Drayton",
    "sg:classifiers":[
        {
            "category":"Farming",
            "subcategory":"Livestock Farm",
            "type":"Manufacturing & Wholesale Goods"
        }
    ],
    "sg:phone":"+44 1952 840205",
    "sg:postcode":"TF9 2DG",
    "sg:province":"Shropshire",
    "sg:tags":[
        "others"
    ],
    "wof:name":"G Perry",
    "wof:placetype":"venue"
},
  "geometry": {"coordinates":[-2.4943039417,52.8222732544],"type":"Point"}
}