{
  "type": "Feature",
  "properties": {
    "addr:full":"652 Blackburn Road, Astley Bridge Bolton Lancashire BL1 7AL",
    "addr:housenumber":"652",
    "addr:postcode":"bl1 7al",
    "addr:street":"Blackburn Road",
    "iso:country":"GB",
    "sg:address":"652 Blackburn Road, Astley Bridge",
    "sg:city":"Bolton",
    "sg:classifiers":[
        {
            "category":"Personal",
            "type":"Services"
        }
    ],
    "sg:postcode":"BL1 7AL",
    "sg:province":"Lancashire",
    "sg:tags":[
        "wedding"
    ],
    "wof:name":"Petals",
    "wof:placetype":"venue"
},
  "geometry": {"coordinates":[-2.4326620102,53.6019363403],"type":"Point"}
}