{
  "type": "Feature",
  "properties": {
    "addr:full":"20 Craddocks Parade Ashtead Surrey KT21 1QJ",
    "addr:housenumber":"20",
    "addr:postcode":"kt21 1qj",
    "addr:street":"Craddocks Parade",
    "iso:country":"GB",
    "sg:address":"20 Craddocks Parade",
    "sg:city":"Ashtead",
    "sg:classifiers":[
        {
            "category":"Professional",
            "type":"Services"
        }
    ],
    "sg:phone":"+44 1372 276337",
    "sg:postcode":"KT21 1QJ",
    "sg:province":"Surrey",
    "sg:tags":[
        "caterer"
    ],
    "wof:name":"Occasions Party Hire",
    "wof:placetype":"venue"
},
  "geometry": {"coordinates":[-0.303017,51.317436],"type":"Point"}
}