{
  "type": "Feature",
  "properties": {
    "addr:full":"114 Brixton Hill, Brixton London Greater London SW2 1RS",
    "addr:housenumber":"114",
    "addr:postcode":"sw2 1rs",
    "addr:street":"Brixton Hill",
    "iso:country":"GB",
    "sg:address":"114 Brixton Hill, Brixton",
    "sg:city":"London",
    "sg:classifiers":[
        {
            "category":"Retail",
            "subcategory":"Repair Shop",
            "type":"Services"
        }
    ],
    "sg:phone":"+44 20 8674 4232",
    "sg:postcode":"SW2 1RS",
    "sg:province":"Greater London",
    "sg:tags":[
        "radio",
        "television",
        "video"
    ],
    "wof:name":"Television Audio Services",
    "wof:placetype":"venue"
},
  "geometry": {"coordinates":[-0.118671,51.456715],"type":"Point"}
}