{
  "type": "Feature",
  "properties": {
    "addr:full":"13 Pine Clo Thetford Norfolk IP24 3LA",
    "addr:housenumber":"13",
    "addr:postcode":"ip24 3la",
    "addr:street":"Pine Clo",
    "iso:country":"GB",
    "sg:address":"13 Pine Clo",
    "sg:city":"Thetford",
    "sg:classifiers":[
        {
            "category":"Food & Beverages",
            "subcategory":"Meat & Fish",
            "type":"Retail Goods"
        }
    ],
    "sg:phone":"+44 1842 763683",
    "sg:postcode":"IP24 3LA",
    "sg:province":"Norfolk",
    "sg:tags":[
        "chip"
    ],
    "wof:name":"Happy Fryer The",
    "wof:placetype":"venue"
},
  "geometry": {"coordinates":[0.737807,52.404636],"type":"Point"}
}