{
  "type": "Feature",
  "properties": {
    "addr:full":"40 Brookly Gdns Fleet Hampshire GU51 3LL",
    "addr:housenumber":"40",
    "addr:postcode":"gu51 3ll",
    "addr:street":"Brookly Gdns",
    "iso:country":"GB",
    "sg:address":"40 Brookly Gdns",
    "sg:city":"Fleet",
    "sg:classifiers":[
        {
            "category":"Building & Trades",
            "subcategory":"Landscaping Services",
            "type":"Services"
        }
    ],
    "sg:postcode":"GU51 3LL",
    "sg:province":"Hampshire",
    "sg:tags":[
        "landscape",
        "contractor"
    ],
    "wof:name":"Rivendell Landscaping Ltd",
    "wof:placetype":"venue"
},
  "geometry": {"coordinates":[-0.828088,51.283997],"type":"Point"}
}