{
  "type": "Feature",
  "properties": {
    "iso:country":"GB",
    "sg:address":"50 Abbotsford Road",
    "sg:city":"Wishaw",
    "sg:classifiers":[
        {
            "category":"Manufacturing",
            "subcategory":"Tools & Machinery",
            "type":"Manufacturing & Wholesale Goods"
        }
    ],
    "sg:postcode":"ML2 7DN",
    "sg:province":"North Lanarkshire",
    "sg:tags":[
        "society",
        "friendly"
    ],
    "wof:name":"D Robinson",
    "wof:placetype":"venue"
},
  "geometry": {"coordinates":[-3.911468,55.779945],"type":"Point"}
}