{
  "type": "Feature",
  "properties": {
    "iso:country":"GB",
    "sg:address":"30 Kaims Court",
    "sg:city":"Livingston",
    "sg:classifiers":[
        {
            "category":"Building & Trades",
            "subcategory":"Construction",
            "type":"Services"
        }
    ],
    "sg:phone":"+44 1506 419991",
    "sg:postcode":"EH54 7DB",
    "sg:province":"West Lothian",
    "sg:tags":[
        "flooring"
    ],
    "wof:name":"Scotpave",
    "wof:placetype":"venue"
},
  "geometry": {"coordinates":[-3.536219,55.883549],"type":"Point"}
}