{
  "type": "Feature",
  "properties": {
    "addr:full":"62 London Rd Leicester Leicestershire LE2 0QD",
    "addr:housenumber":"62",
    "addr:postcode":"le2 0qd",
    "addr:street":"London Rd",
    "iso:country":"GB",
    "sg:address":"62 London Rd",
    "sg:city":"Leicester",
    "sg:classifiers":[
        {
            "category":"Home & Garden",
            "subcategory":"Furniture",
            "type":"Retail Goods"
        }
    ],
    "sg:phone":"+44 116 299 2000",
    "sg:postcode":"LE2 0QD",
    "sg:province":"Leicestershire",
    "wof:name":"Pinewood Studios",
    "wof:placetype":"venue"
},
  "geometry": {"coordinates":[-1.123588,52.629929],"type":"Point"}
}