{
  "type": "Feature",
  "properties": {
    "addr:full":"101 High Street Chatham Kent ME4 4DJ",
    "addr:housenumber":"101",
    "addr:postcode":"me4 4dj",
    "addr:street":"High Street",
    "iso:country":"GB",
    "sg:address":"101 High Street",
    "sg:city":"Chatham",
    "sg:classifiers":[
        {
            "category":"Personal",
            "subcategory":"Beauty Salon",
            "type":"Services"
        }
    ],
    "sg:phone":"+44 1634 844633",
    "sg:postcode":"ME4 4DJ",
    "sg:province":"Kent",
    "sg:tags":[
        "unisex",
        "hairdresser"
    ],
    "wof:name":"Hekkle",
    "wof:placetype":"venue"
},
  "geometry": {"coordinates":[0.521227,51.383781],"type":"Point"}
}