{
  "type": "Feature",
  "properties": {
    "addr:full":"25 Fulmar Rd Christchurch Dorset BH23 4BJ",
    "addr:housenumber":"25",
    "addr:postcode":"bh23 4bj",
    "addr:street":"Fulmar Rd",
    "iso:country":"GB",
    "sg:address":"25 Fulmar Rd",
    "sg:city":"Christchurch",
    "sg:classifiers":[
        {
            "category":"Professional",
            "subcategory":"Engineering",
            "type":"Services"
        }
    ],
    "sg:phone":"+44 1425 273855",
    "sg:postcode":"BH23 4BJ",
    "sg:province":"Dorset",
    "wof:name":"B D Power Marine",
    "wof:placetype":"venue"
},
  "geometry": {"coordinates":[-1.740907,50.728535],"type":"Point"}
}