{
  "type": "Feature",
  "properties": {
    "iso:country":"GB",
    "sg:address":"87 Wilkins Road",
    "sg:city":"Oxford",
    "sg:classifiers":[
        {
            "category":"Building & Trades",
            "subcategory":"Construction",
            "type":"Services"
        }
    ],
    "sg:phone":"+44 1865 778293",
    "sg:postcode":"OX4 2JB",
    "sg:province":"Oxfordshire",
    "sg:tags":[
        "builder"
    ],
    "wof:name":"M C M Contractors Ltd.",
    "wof:placetype":"venue"
},
  "geometry": {"coordinates":[-1.2056349516,51.7353286743],"type":"Point"}
}