{
  "type": "Feature",
  "properties": {
    "iso:country":"GB",
    "sg:address":"Crown House, Mucking Wharf Road",
    "sg:city":"Stanford-le-hope",
    "sg:classifiers":[
        {
            "category":"Utilities",
            "subcategory":"Refuse",
            "type":"Services"
        }
    ],
    "sg:phone":"+44 1375 671227",
    "sg:postcode":"SS17 0RN",
    "sg:province":"Essex",
    "sg:tags":[
        "disposal",
        "waste"
    ],
    "wof:name":"Cory Environmental Pollution Control Services",
    "wof:placetype":"venue"
},
  "geometry": {"coordinates":[0.427365,51.503819],"type":"Point"}
}