{
  "type": "Feature",
  "properties": {
    "addr:full":"129 Speldhurst Close Ashford Kent TN23 5TP",
    "addr:housenumber":"129",
    "addr:postcode":"tn23 5tp",
    "addr:street":"Speldhurst Close",
    "iso:country":"GB",
    "sg:address":"129 Speldhurst Close",
    "sg:city":"Ashford",
    "sg:classifiers":[
        {
            "category":"Building & Trades",
            "subcategory":"Landscaping Services",
            "type":"Services"
        }
    ],
    "sg:phone":"+44 1233 641214",
    "sg:postcode":"TN23 5TP",
    "sg:province":"Kent",
    "sg:tags":[
        "gardening",
        "landscape",
        "contractor"
    ],
    "wof:name":"Peter Pearson",
    "wof:placetype":"venue"
},
  "geometry": {"coordinates":[0.847958982,51.129070282],"type":"Point"}
}