{
  "type": "Feature",
  "properties": {
    "addr:full":"1 Islington High Street London Greater London N1 9TR",
    "addr:housenumber":"1",
    "addr:postcode":"n1 9tr",
    "addr:street":"Islington High Street",
    "iso:country":"GB",
    "sg:address":"1 Islington High Street",
    "sg:city":"London",
    "sg:classifiers":[
        {
            "category":"Banks & Credit Unions",
            "subcategory":"Bank",
            "type":"Services"
        }
    ],
    "sg:phone":"+44 20 7837 8408",
    "sg:postcode":"N1 9TR",
    "sg:province":"Greater London",
    "wof:name":"The Co-Operative Bank Plc",
    "wof:placetype":"venue"
},
  "geometry": {"coordinates":[-0.1063219979,51.5319976807],"type":"Point"}
}