{
  "type": "Feature",
  "properties": {
    "iso:country":"GB",
    "sg:address":"Unit 4 Newhall Place, 16-17 Newhall Hill",
    "sg:city":"Birmingham",
    "sg:classifiers":[
        {
            "category":"Professional",
            "subcategory":"Business Services",
            "type":"Services"
        },
        {
            "category":"Organizations",
            "subcategory":"Membership Organization",
            "type":"Services"
        }
    ],
    "sg:phone":"+44 121 233 2232",
    "sg:postcode":"B1 3JH",
    "sg:province":"West Midlands",
    "sg:tags":[
        "club",
        "accomodation"
    ],
    "wof:name":"Midlands Industrial Association Ltd.",
    "wof:placetype":"venue"
},
  "geometry": {"coordinates":[-1.908604,52.478596],"type":"Point"}
}