{
  "type": "Feature",
  "properties": {
    "addr:full":"1 Monmouth Gardens Nuneaton Leicestershire CV10 8DA",
    "addr:housenumber":"1",
    "addr:postcode":"cv10 8da",
    "addr:street":"Monmouth Gardens",
    "iso:country":"GB",
    "sg:address":"1 Monmouth Gardens",
    "sg:city":"Nuneaton",
    "sg:classifiers":[
        {
            "category":"Manufacturing",
            "subcategory":"Building Materials",
            "type":"Manufacturing & Wholesale Goods"
        }
    ],
    "sg:phone":"+44 24 7637 2835",
    "sg:postcode":"CV10 8DA",
    "sg:province":"Leicestershire",
    "sg:tags":[
        "flag",
        "banner"
    ],
    "wof:name":"McCall Banners & Pennants Ltd",
    "wof:placetype":"venue"
},
  "geometry": {"coordinates":[-1.494099021,52.5199356079],"type":"Point"}
}