{
  "type": "Feature",
  "properties": {
    "iso:country":"GB",
    "sg:address":"45 Victoria Road",
    "sg:city":"Southampton",
    "sg:classifiers":[
        {
            "category":"Shopping",
            "subcategory":"Crafts & Fabrics",
            "type":"Retail Goods"
        }
    ],
    "sg:phone":"+44 23 8044 8081",
    "sg:postcode":"SO19 9DY",
    "sg:province":"Hampshire",
    "sg:tags":[
        "shop",
        "needlecraft",
        "wool"
    ],
    "wof:name":"Williamsons",
    "wof:placetype":"venue"
},
  "geometry": {"coordinates":[-1.380182,50.896458],"type":"Point"}
}