{
  "type": "Feature",
  "properties": {
    "addr:full":"41a High Street Tewkesbury Gloucestershire GL20 5BB",
    "addr:housenumber":"41a",
    "addr:postcode":"gl20 5bb",
    "addr:street":"High Street",
    "iso:country":"GB",
    "sg:address":"41a High Street",
    "sg:city":"Tewkesbury",
    "sg:classifiers":[
        {
            "category":"Taxi",
            "type":"Transportation"
        },
        {
            "category":"Military Area",
            "subcategory":"Air Force Base",
            "type":"Public Place"
        }
    ],
    "sg:phone":"+44 1684 294122",
    "sg:postcode":"GL20 5BB",
    "sg:province":"Gloucestershire",
    "sg:tags":[
        "hire",
        "private"
    ],
    "wof:name":"AVONSIDE TAXIS",
    "wof:placetype":"venue"
},
  "geometry": {"coordinates":[-2.156704,51.995083],"type":"Point"}
}