{
  "type": "Feature",
  "properties": {
    "addr:full":"48 Peckham High Street, Southwalk London Greater London SE15 5DP",
    "addr:housenumber":"48",
    "addr:postcode":"se15 5dp",
    "addr:street":"Peckham High Street",
    "iso:country":"GB",
    "sg:address":"48 Peckham High Street, Southwalk",
    "sg:city":"London",
    "sg:classifiers":[
        {
            "category":"Personal",
            "subcategory":"Beauty Salon",
            "type":"Services"
        }
    ],
    "sg:postcode":"SE15 5DP",
    "sg:province":"Greater London",
    "sg:tags":[
        "unisex",
        "hairdresser"
    ],
    "wof:name":"Constance Executive U K Ltd",
    "wof:placetype":"venue"
},
  "geometry": {"coordinates":[-0.0705149993,51.4732246399],"type":"Point"}
}