{
  "type": "Feature",
  "properties": {
    "iso:country":"GB",
    "sg:address":"49 Chestergate",
    "sg:city":"Macclesfield",
    "sg:classifiers":[
        {
            "category":"Personal",
            "subcategory":"Beauty Salon",
            "type":"Services"
        }
    ],
    "sg:phone":"+44 1625 423039",
    "sg:postcode":"SK11 6DG",
    "sg:province":"Cheshire",
    "sg:tags":[
        "unisex",
        "hairdresser"
    ],
    "wof:name":"Miro Designer Hair",
    "wof:placetype":"venue"
},
  "geometry": {"coordinates":[-2.1284689903,53.2611465454],"type":"Point"}
}