{
  "type": "Feature",
  "properties": {
    "addr:full":"324 Fratton Road Portsmouth Hampshire PO1 5JX",
    "addr:housenumber":"324",
    "addr:postcode":"hampshire po1 5jx",
    "addr:street":"Fratton Road",
    "iso:country":"GB",
    "sg:address":"324 Fratton Road",
    "sg:city":"Portsmouth",
    "sg:classifiers":[
        {
            "category":"Bars & Pubs",
            "type":"Food & Drink"
        }
    ],
    "sg:phone":"+44 23 9282 0289",
    "sg:postcode":"PO1 5JX",
    "sg:province":"Hampshire",
    "sg:tags":[
        "pubs",
        "inn"
    ],
    "wof:name":"The Florist",
    "wof:placetype":"venue"
},
  "geometry": {"coordinates":[-1.076671958,50.8053741455],"type":"Point"}
}