{
  "type": "Feature",
  "properties": {
    "iso:country":"GB",
    "sg:address":"Brough Road, South Cave",
    "sg:city":"Brough",
    "sg:classifiers":[
        {
            "category":"Autos & Motor Vehicles",
            "subcategory":"Automobile Sales",
            "type":"Retail Goods"
        }
    ],
    "sg:phone":"+44 1430 424575",
    "sg:postcode":"HU15 2DA",
    "sg:province":"East Riding of Yorkshire",
    "sg:tags":[
        "car"
    ],
    "wof:name":"Cawthorn Cars Ltd.",
    "wof:placetype":"venue"
},
  "geometry": {"coordinates":[-0.6004689932,53.7668418884],"type":"Point"}
}