{
  "type": "Feature",
  "properties": {
    "addr:full":"Unit 1, Bonnyton Indstl Est, Munro Pl Kilmarnock East Ayrshire KA1 2NP",
    "addr:housenumber":"unit 1",
    "addr:postcode":"ka1 2np",
    "addr:street":"Indstl Est;Pl",
    "iso:country":"GB",
    "sg:address":"Unit 1, Bonnyton Indstl Est, Munro Pl",
    "sg:city":"Kilmarnock",
    "sg:classifiers":[
        {
            "category":"Real Estate",
            "subcategory":"Real Estate Services",
            "type":"Services"
        },
        {
            "category":"Building & Trades",
            "subcategory":"Equipment Rental",
            "type":"Services"
        }
    ],
    "sg:phone":"+44 1563 543543",
    "sg:postcode":"KA1 2NP",
    "sg:province":"East Ayrshire",
    "sg:tags":[
        "hire",
        "leasing",
        "plant",
        "machinery"
    ],
    "wof:name":"ANDERSON PLANT LTD",
    "wof:placetype":"venue"
},
  "geometry": {"coordinates":[-4.5097298622,55.6088943481],"type":"Point"}
}