{
  "type": "Feature",
  "properties": {
    "addr:full":"Horden Youth Club, Eden St Horden Peterlee Durham SR8 4LH",
    "addr:postcode":"sr8 4lh",
    "addr:street":"Eden St",
    "iso:country":"GB",
    "sg:address":"Horden Youth Club, Eden St Horden",
    "sg:city":"Peterlee",
    "sg:classifiers":[
        {
            "category":"Community Center",
            "subcategory":"Youth",
            "type":"Public Place"
        }
    ],
    "sg:phone":"+44 191 586 7576",
    "sg:postcode":"SR8 4LH",
    "sg:province":"Durham",
    "sg:tags":[
        "organisation",
        "centre"
    ],
    "wof:name":"East Durham Youth in Action",
    "wof:placetype":"venue"
},
  "geometry": {"coordinates":[-1.311139,54.75956],"type":"Point"}
}