{
  "type": "Feature",
  "properties": {
    "addr:full":"21 Devonshire Road Ipswich Suffolk IP3 8AU",
    "addr:housenumber":"21",
    "addr:postcode":"ip3 8au",
    "addr:street":"Devonshire Road",
    "iso:country":"GB",
    "sg:address":"21 Devonshire Road",
    "sg:city":"Ipswich",
    "sg:classifiers":[
        {
            "category":"Building & Trades",
            "subcategory":"Cleaning & Sanitation",
            "type":"Services"
        }
    ],
    "sg:phone":"+44 1473 254267",
    "sg:postcode":"IP3 8AU",
    "sg:province":"Suffolk",
    "sg:tags":[
        "cleaner",
        "window"
    ],
    "wof:name":"Davey & Burgess",
    "wof:placetype":"venue"
},
  "geometry": {"coordinates":[1.1718779802,52.0528793335],"type":"Point"}
}