{
  "type": "Feature",
  "properties": {
    "iso:country":"GB",
    "sg:address":"Unit 6, Riverside",
    "sg:city":"Rochester",
    "sg:classifiers":[
        {
            "category":"Retail",
            "subcategory":"Auto Repair",
            "type":"Services"
        }
    ],
    "sg:phone":"+44 1474 822825",
    "sg:postcode":"ME2 4DP",
    "sg:province":"Kent",
    "sg:tags":[
        "car",
        "servicing",
        "radiator"
    ],
    "wof:name":"Radicool Services",
    "wof:placetype":"venue"
},
  "geometry": {"coordinates":[0.51215,51.404209],"type":"Point"}
}