{
  "type": "Feature",
  "properties": {
    "iso:country":"GB",
    "sg:address":"79 Edale Rd",
    "sg:city":"Sheffield",
    "sg:classifiers":[
        {
            "category":"Social Services",
            "subcategory":"Adult Care",
            "type":"Services"
        }
    ],
    "sg:phone":"+44 114 266 1198",
    "sg:postcode":"S11 7PJ",
    "sg:province":"Derbyshire",
    "sg:tags":[
        "lubrication"
    ],
    "wof:name":"Peter F Drake (Sales) Ltd",
    "wof:placetype":"venue"
},
  "geometry": {"coordinates":[-1.519489,53.36145],"type":"Point"}
}