{
  "type": "Feature",
  "properties": {
    "iso:country":"GB",
    "sg:address":"171 Francis Avenue",
    "sg:city":"Southsea",
    "sg:classifiers":[
        {
            "category":"Shopping",
            "subcategory":"Clothing, Apparel, & Fashions",
            "type":"Retail Goods"
        }
    ],
    "sg:postcode":"PO4 0EP",
    "sg:province":"Hampshire",
    "sg:tags":[
        "shop",
        "dress",
        "fancy"
    ],
    "wof:name":"Pumpkins",
    "wof:placetype":"venue"
},
  "geometry": {"coordinates":[-1.070623,50.792068],"type":"Point"}
}