{
  "type": "Feature",
  "properties": {
    "addr:full":"3 Fairfax Gardens, Needham Market Ipswich Suffolk IP6 8AZ",
    "addr:housenumber":"3",
    "addr:postcode":"ip6 8az",
    "addr:street":"Fairfax Gardens",
    "iso:country":"GB",
    "sg:address":"3 Fairfax Gardens, Needham Market",
    "sg:city":"Ipswich",
    "sg:classifiers":[
        {
            "category":"Manufacturing",
            "subcategory":"Lumber",
            "type":"Manufacturing & Wholesale Goods"
        }
    ],
    "sg:postcode":"IP6 8AZ",
    "sg:province":"Suffolk",
    "sg:tags":[
        "importer",
        "merchants",
        "agent",
        "timber"
    ],
    "wof:name":"R H Wilden & Sons Ltd.",
    "wof:placetype":"venue"
},
  "geometry": {"coordinates":[1.0550969839,52.1518745422],"type":"Point"}
}