{
  "type": "Feature",
  "properties": {
    "addr:full":"19 Hunts Lane, Grappenhall Warrington Cheshire WA4 2DU",
    "addr:housenumber":"19",
    "addr:postcode":"wa4 2du",
    "addr:street":"Hunts Lane",
    "iso:country":"GB",
    "sg:address":"19 Hunts Lane, Grappenhall",
    "sg:city":"Warrington",
    "sg:classifiers":[
        {
            "category":"Arts & Performance",
            "subcategory":"Art Gallery",
            "type":"Entertainment"
        }
    ],
    "sg:phone":"+44 1925 211233",
    "sg:postcode":"WA4 2DU",
    "sg:province":"Cheshire",
    "wof:name":"Cheshire Framing",
    "wof:placetype":"venue"
},
  "geometry": {"coordinates":[-2.561014,53.376114],"type":"Point"}
}