{
  "type": "Feature",
  "properties": {
    "addr:full":"20 Nevin Gro, Perry Barr Birmingham West Midlands B42 1PE",
    "addr:housenumber":"20",
    "addr:postcode":"b42 1pe",
    "addr:street":"Nevin Gro",
    "iso:country":"GB",
    "sg:address":"20 Nevin Gro, Perry Barr",
    "sg:city":"Birmingham",
    "sg:classifiers":[
        {
            "category":"Building & Trades",
            "subcategory":"Construction",
            "type":"Services"
        }
    ],
    "sg:phone":"+44 121 681 6865",
    "sg:postcode":"B42 1PE",
    "sg:province":"West Midlands",
    "sg:tags":[
        "roofing",
        "contractor"
    ],
    "wof:name":"Brewer Construction",
    "wof:placetype":"venue"
},
  "geometry": {"coordinates":[-1.904859,52.522518],"type":"Point"}
}