{
  "type": "Feature",
  "properties": {
    "iso:country":"GB",
    "sg:address":"Amwell End, Down Green La",
    "sg:city":"St Albans",
    "sg:classifiers":[
        {
            "category":"Autos & Motor Vehicles",
            "subcategory":"Automobile Sales",
            "type":"Retail Goods"
        }
    ],
    "sg:phone":"+44 1582 831222",
    "sg:postcode":"AL4 8EB",
    "sg:province":"Hertfordshire",
    "sg:tags":[
        "car"
    ],
    "wof:name":"Chase Vehicles",
    "wof:placetype":"venue"
},
  "geometry": {"coordinates":[-0.30804,51.805611],"type":"Point"}
}