{
  "type": "Feature",
  "properties": {
    "addr:full":"Strath Cottage, 8 West Shore St Ullapool Highland IV26 2UR",
    "addr:housenumber":"8",
    "addr:postcode":"iv26 2ur",
    "addr:street":"West;St",
    "iso:country":"GB",
    "sg:address":"Strath Cottage, 8 West Shore St",
    "sg:city":"Ullapool",
    "sg:classifiers":[
        {
            "category":"Organizations",
            "subcategory":"Non-profit Organization",
            "type":"Services"
        }
    ],
    "sg:phone":"+44 1854 613300",
    "sg:postcode":"IV26 2UR",
    "sg:province":"Highland",
    "sg:tags":[
        "organisation",
        "animal",
        "welfare"
    ],
    "wof:name":"Ullapool Veterinary Surgery",
    "wof:placetype":"venue"
},
  "geometry": {"coordinates":[-5.1589241028,57.895778656],"type":"Point"}
}