{
  "type": "Feature",
  "properties": {
    "addr:full":"491 Pitsmoor Rd Sheffield South Yorkshire S3 9AT",
    "addr:housenumber":"491",
    "addr:postcode":"s3 9at",
    "addr:street":"Pitsmoor Rd",
    "iso:country":"GB",
    "sg:address":"491 Pitsmoor Rd",
    "sg:city":"Sheffield",
    "sg:phone":"+44 114 276 5709",
    "sg:postcode":"S3 9AT",
    "sg:province":"South Yorkshire",
    "wof:name":"John Fantham",
    "wof:placetype":"venue"
},
  "geometry": {"coordinates":[-1.4651360512,53.400894165],"type":"Point"}
}