{
  "type": "Feature",
  "properties": {
    "addr:full":"13 Longcraigs Av Ardrossan North Ayrshire KA22 7PU",
    "addr:housenumber":"13",
    "addr:postcode":"ka22 7pu",
    "addr:street":"Av Ardrossan",
    "iso:country":"GB",
    "sg:address":"13 Longcraigs Av",
    "sg:city":"Ardrossan",
    "sg:classifiers":[
        {
            "category":"Shopping",
            "subcategory":"Pharmacy",
            "type":"Retail Goods"
        }
    ],
    "sg:phone":"+44 1294 468931",
    "sg:postcode":"KA22 7PU",
    "sg:province":"North Ayrshire",
    "sg:tags":[
        "medicine",
        "therapy"
    ],
    "wof:name":"Margaret Muir",
    "wof:placetype":"venue"
},
  "geometry": {"coordinates":[-4.813294,55.658451],"type":"Point"}
}