{
  "type": "Feature",
  "properties": {
    "addr:full":"604 Clifton Road Aberdeen Aberdeen City AB24 4ED",
    "addr:housenumber":"604",
    "addr:postcode":"ab24 4ed",
    "addr:street":"Clifton Road",
    "iso:country":"GB",
    "sg:address":"604 Clifton Road",
    "sg:city":"Aberdeen",
    "sg:classifiers":[
        {
            "category":"Shopping",
            "subcategory":"Department Store",
            "type":"Retail Goods"
        },
        {
            "category":"Shopping",
            "subcategory":"News",
            "type":"Retail Goods"
        },
        {
            "category":"Food & Beverages",
            "subcategory":"Supermarket",
            "type":"Retail Goods"
        }
    ],
    "sg:phone":"+44 1224 696453",
    "sg:postcode":"AB24 4ED",
    "sg:province":"Aberdeen City",
    "sg:tags":[
        "newsagent"
    ],
    "wof:name":"Neil McDonald",
    "wof:placetype":"venue"
},
  "geometry": {"coordinates":[-2.134279,57.17136],"type":"Point"}
}