{
  "type": "Feature",
  "properties": {
    "addr:full":"Trindledown Farm, Webbs Lane, Beenahm Village Reading Berkshire RG7 5LJ",
    "addr:postcode":"rg7 5lj",
    "addr:street":"Webbs Lane Beenahm Village",
    "iso:country":"GB",
    "sg:address":"Trindledown Farm, Webbs Lane, Beenahm Village",
    "sg:city":"Reading",
    "sg:classifiers":[
        {
            "category":"Professional",
            "subcategory":"Lawyer & Legal Services",
            "type":"Services"
        },
        {
            "category":"Farming",
            "subcategory":"Farm",
            "type":"Manufacturing & Wholesale Goods"
        }
    ],
    "sg:phone":"+44 118 974 5208",
    "sg:postcode":"RG7 5LJ",
    "sg:province":"Berkshire",
    "sg:tags":[
        "mixed",
        "crop",
        "solicitor"
    ],
    "wof:name":"M G Stone",
    "wof:placetype":"venue"
},
  "geometry": {"coordinates":[-1.13481,51.421532],"type":"Point"}
}