{
  "type": "Feature",
  "properties": {
    "addr:full":"Unit 6 Galley Hill Yard Waltham Abbey Essex EN9 2AG",
    "addr:housenumber":"unit 6",
    "addr:postcode":"en9 2ag",
    "addr:street":"Galley Hill Yard;Abbey",
    "iso:country":"GB",
    "sg:address":"Unit 6 Galley Hill Yard",
    "sg:city":"Waltham Abbey",
    "sg:classifiers":[
        {
            "category":"Building & Trades",
            "subcategory":"Construction",
            "type":"Services"
        }
    ],
    "sg:phone":"+44 1992 768868",
    "sg:postcode":"EN9 2AG",
    "sg:province":"Essex",
    "sg:tags":[
        "flooring"
    ],
    "wof:name":"T & G Hardwood Flooring Specialists",
    "wof:placetype":"venue"
},
  "geometry": {"coordinates":[0.0177829992,51.6925544739],"type":"Point"}
}