{
  "type": "Feature",
  "properties": {
    "addr:full":"31 London End Beaconsfield Buckinghamshire HP9 2HW",
    "addr:housenumber":"31",
    "addr:postcode":"hp9 2hw",
    "addr:street":"London End",
    "iso:country":"GB",
    "sg:address":"31 London End",
    "sg:city":"Beaconsfield",
    "sg:classifiers":[
        {
            "category":"Banks & Credit Unions",
            "subcategory":"Investment Brokerage",
            "type":"Services"
        }
    ],
    "sg:phone":"+44 1494 672513",
    "sg:postcode":"HP9 2HW",
    "sg:province":"Buckinghamshire",
    "wof:name":"Mellawood Properties Ltd.",
    "wof:placetype":"venue"
},
  "geometry": {"coordinates":[-0.635122,51.602139],"type":"Point"}
}