{
  "type": "Feature",
  "properties": {
    "iso:country":"GB",
    "sg:address":"Drayton Manor Drive",
    "sg:city":"Tamworth",
    "sg:classifiers":[
        {
            "category":"Sports & Exercise",
            "subcategory":"Golf",
            "type":"Entertainment"
        }
    ],
    "sg:phone":"+44 1827 251139",
    "sg:postcode":"B78 3TN",
    "sg:province":"Staffordshire",
    "sg:tags":[
        "club",
        "course"
    ],
    "wof:name":"Drayton Park Golf Club Ltd",
    "wof:placetype":"venue"
},
  "geometry": {"coordinates":[-1.708763,52.607162],"type":"Point"}
}