{
  "type": "Feature",
  "properties": {
    "iso:country":"GB",
    "sg:address":"47 Southey Ave",
    "sg:city":"Sheffield",
    "sg:classifiers":[
        {
            "category":"Shopping",
            "subcategory":"Department Store",
            "type":"Retail Goods"
        }
    ],
    "sg:postcode":"S5 7NN",
    "sg:province":"South Yorkshire",
    "wof:name":"R & A Quality Carpets & Furnishings",
    "wof:placetype":"venue"
},
  "geometry": {"coordinates":[-1.47218,53.4174],"type":"Point"}
}