{
  "type": "Feature",
  "properties": {
    "addr:full":"Emberton House, Yeomans Way Bournemouth Dorset BH8 0BP",
    "addr:housenumber":"emberton",
    "addr:postcode":"bh8 0bp",
    "addr:street":"Yeomans Way",
    "iso:country":"GB",
    "sg:address":"Emberton House, Yeomans Way",
    "sg:city":"Bournemouth",
    "sg:classifiers":[
        {
            "category":"Shopping",
            "subcategory":"Stationery & Office Supplies",
            "type":"Retail Goods"
        }
    ],
    "sg:phone":"+44 1202 240000",
    "sg:postcode":"BH8 0BP",
    "sg:province":"Dorset",
    "sg:tags":[
        "commercial"
    ],
    "wof:name":"Ace Office Supplies Ltd",
    "wof:placetype":"venue"
},
  "geometry": {"coordinates":[-1.836219,50.753391],"type":"Point"}
}