{
  "type": "Feature",
  "properties": {
    "iso:country":"GB",
    "sg:address":"Borron Street",
    "sg:city":"Stockport",
    "sg:classifiers":[
        {
            "category":"Home & Garden",
            "subcategory":"Hardware",
            "type":"Retail Goods"
        }
    ],
    "sg:phone":"+44 161 480 7138",
    "sg:postcode":"SK1 2JD",
    "sg:province":"Cheshire",
    "sg:tags":[
        "retailer",
        "diy"
    ],
    "wof:name":"Chestergate Wood Supplies Ltd.",
    "wof:placetype":"venue"
},
  "geometry": {"coordinates":[-2.146144,53.415581],"type":"Point"}
}