{
  "type": "Feature",
  "properties": {
    "iso:country":"GB",
    "sg:address":"2266 Paisley Road West",
    "sg:city":"Glasgow",
    "sg:classifiers":[
        {
            "category":"Arts & Performance",
            "subcategory":"Theater",
            "type":"Entertainment"
        }
    ],
    "sg:phone":"+44 141 882 3781",
    "sg:postcode":"G52 3QL",
    "sg:province":"Glasgow City",
    "sg:tags":[
        "theatrical",
        "agency"
    ],
    "wof:name":"The Whatever Crew",
    "wof:placetype":"venue"
},
  "geometry": {"coordinates":[-4.3601269722,55.8458633423],"type":"Point"}
}