{
  "type": "Feature",
  "properties": {
    "addr:full":"Unit 4 Congleton Business Centre Congleton Cheshire CW12 1QU",
    "addr:housenumber":"unit 4;business",
    "addr:postcode":"cw12 1qu",
    "iso:country":"GB",
    "sg:address":"Unit 4 Congleton Business Centre",
    "sg:city":"Congleton",
    "sg:classifiers":[
        {
            "category":"Professional",
            "subcategory":"Management & Consulting",
            "type":"Services"
        }
    ],
    "sg:phone":"+44 1260 276013",
    "sg:postcode":"CW12 1QU",
    "sg:province":"Cheshire",
    "sg:tags":[
        "consultant",
        "promotion",
        "direct",
        "sale"
    ],
    "wof:name":"China Originals",
    "wof:placetype":"venue"
},
  "geometry": {"coordinates":[-2.2122049332,53.1636352539],"type":"Point"}
}