{
  "type": "Feature",
  "properties": {
    "iso:country":"GB",
    "sg:address":"372 Dumbarton Road",
    "sg:city":"Glasgow",
    "sg:classifiers":[
        {
            "category":"Shopping",
            "subcategory":"Shoes",
            "type":"Retail Goods"
        }
    ],
    "sg:postcode":"G11 6RZ",
    "sg:province":"Glasgow City",
    "sg:tags":[
        "shop"
    ],
    "wof:name":"Shoefayre",
    "wof:placetype":"venue"
},
  "geometry": {"coordinates":[-4.3084878922,55.8710021973],"type":"Point"}
}