{
  "type": "Feature",
  "properties": {
    "addr:full":"Basement Flat 28a Westwick, Gardens London Greater London W14 0BU",
    "addr:housenumber":"28a",
    "addr:postcode":"w14 0bu",
    "addr:street":"Westwick Gardens",
    "iso:country":"GB",
    "sg:address":"Basement Flat 28a Westwick, Gardens",
    "sg:city":"London",
    "sg:classifiers":[
        {
            "category":"Organizations",
            "subcategory":"Membership Organization",
            "type":"Services"
        }
    ],
    "sg:postcode":"W14 0BU",
    "sg:province":"Greater London",
    "sg:tags":[
        "club"
    ],
    "wof:name":"26-28 Westwick Gardens Residents Associa",
    "wof:placetype":"venue"
},
  "geometry": {"coordinates":[-0.2210700065,51.5016212463],"type":"Point"}
}