{
  "type": "Feature",
  "properties": {
    "addr:full":"387 Ongar Road, Pilgrims Hatch Brentwood Essex CM15 9JA",
    "addr:housenumber":"387",
    "addr:postcode":"cm15 9ja",
    "addr:street":"Ongar Road",
    "iso:country":"GB",
    "sg:address":"387 Ongar Road, Pilgrims Hatch",
    "sg:city":"Brentwood",
    "sg:classifiers":[
        {
            "category":"Professional",
            "subcategory":"Management & Consulting",
            "type":"Services"
        },
        {
            "category":"Professional",
            "subcategory":"Computer Services",
            "type":"Services"
        }
    ],
    "sg:phone":"+44 1277 225830",
    "sg:postcode":"CM15 9JA",
    "sg:province":"Essex",
    "sg:tags":[
        "consultant",
        "business",
        "information"
    ],
    "wof:name":"Essjay Consultancy Services Ltd",
    "wof:placetype":"venue"
},
  "geometry": {"coordinates":[0.29103,51.63007],"type":"Point"}
}