{
  "type": "Feature",
  "properties": {
    "iso:country":"GB",
    "sg:address":"27 Preston Road",
    "sg:city":"Portsmouth",
    "sg:classifiers":[
        {
            "category":"Manufacturing",
            "subcategory":"Printing",
            "type":"Manufacturing & Wholesale Goods"
        }
    ],
    "sg:phone":"+44 23 9266 8364",
    "sg:postcode":"PO2 7JT",
    "sg:province":"Hampshire",
    "sg:tags":[
        "bookbinder"
    ],
    "wof:name":"R A White",
    "wof:placetype":"venue"
},
  "geometry": {"coordinates":[-1.070038,50.812901],"type":"Point"}
}