{
  "type": "Feature",
  "properties": {
    "iso:country":"GB",
    "sg:address":"38 Barnes Street, Church",
    "sg:city":"Accrington",
    "sg:classifiers":[
        {
            "category":"Building & Trades",
            "subcategory":"Construction",
            "type":"Services"
        }
    ],
    "sg:postcode":"BB5 4JF",
    "sg:province":"Lancashire",
    "sg:tags":[
        "joiner",
        "carpenter"
    ],
    "wof:name":"W Pollard & Sons",
    "wof:placetype":"venue"
},
  "geometry": {"coordinates":[-2.388532,53.755901],"type":"Point"}
}