{
  "type": "Feature",
  "properties": {
    "addr:full":"122 Little Glen Road, Glen Parva Leicester Leicestershire LE2 9TS",
    "addr:housenumber":"122",
    "addr:postcode":"le2 9ts",
    "addr:street":"Little Glen Road",
    "iso:country":"GB",
    "sg:address":"122 Little Glen Road, Glen Parva",
    "sg:city":"Leicester",
    "sg:classifiers":[
        {
            "category":"Personal",
            "type":"Services"
        }
    ],
    "sg:postcode":"LE2 9TS",
    "sg:province":"Leicestershire",
    "sg:tags":[
        "wedding"
    ],
    "wof:name":"White Rose Wedding Car Hire",
    "wof:placetype":"venue"
},
  "geometry": {"coordinates":[-1.145912,52.578819],"type":"Point"}
}