{
  "type": "Feature",
  "properties": {
    "iso:country":"GB",
    "sg:address":"Heather View, Onslow Rd",
    "sg:city":"Ascot",
    "sg:classifiers":[
        {
            "category":"Real Estate",
            "subcategory":"Surveying",
            "type":"Services"
        }
    ],
    "sg:phone":"+44 1344 874591",
    "sg:postcode":"SL5 0HW",
    "sg:province":"Berkshire",
    "sg:tags":[
        "surveyor",
        "valuer"
    ],
    "wof:name":"Richard Greed",
    "wof:placetype":"venue"
},
  "geometry": {"coordinates":[-0.620692,51.391659],"type":"Point"}
}