{
  "type": "Feature",
  "properties": {
    "addr:full":"128 Parklands Wotton-under-edge Gloucestershire GL12 7NR",
    "addr:housenumber":"128",
    "addr:postcode":"gl12 7nr",
    "addr:street":"Parklands",
    "iso:country":"GB",
    "sg:address":"128 Parklands",
    "sg:city":"Wotton-under-edge",
    "sg:classifiers":[
        {
            "category":"Shopping",
            "subcategory":"Hobbies, Toys, & Games",
            "type":"Retail Goods"
        }
    ],
    "sg:postcode":"GL12 7NR",
    "sg:province":"Gloucestershire",
    "sg:tags":[
        "pesticide",
        "vermin",
        "pest"
    ],
    "wof:name":"Flyscreens Direct",
    "wof:placetype":"venue"
},
  "geometry": {"coordinates":[-2.3487019539,51.6395454407],"type":"Point"}
}