{
  "type": "Feature",
  "properties": {
    "iso:country":"GB",
    "sg:address":"Windmill Farm, Baston",
    "sg:city":"Peterborough",
    "sg:classifiers":[
        {
            "category":"Farming",
            "subcategory":"Livestock Farm",
            "type":"Manufacturing & Wholesale Goods"
        }
    ],
    "sg:postcode":"PE6 9PX",
    "sg:province":"Cambridgeshire",
    "sg:tags":[
        "others"
    ],
    "wof:name":"J Ward & Son",
    "wof:placetype":"venue"
},
  "geometry": {"coordinates":[-0.356869,52.710545],"type":"Point"}
}