{
  "type": "Feature",
  "properties": {
    "addr:full":"Alpha Numeric House, Little Milton Oxford Oxfordshire OX44 7QD",
    "addr:postcode":"ox44 7qd",
    "iso:country":"GB",
    "sg:address":"Alpha Numeric House, Little Milton",
    "sg:city":"Oxford",
    "sg:classifiers":[
        {
            "category":"Professional",
            "subcategory":"Computer Services",
            "type":"Services"
        }
    ],
    "sg:postcode":"OX44 7QD",
    "sg:province":"Oxfordshire",
    "sg:tags":[
        "system",
        "software"
    ],
    "wof:name":"Alpha Numeric Developments Ltd.",
    "wof:placetype":"venue"
},
  "geometry": {"coordinates":[-1.10512,51.702274],"type":"Point"}
}