{
  "type": "Feature",
  "properties": {
    "addr:full":"Old Mill Lane, Wakefield Road Barnsley South Yorkshire S71 1LP",
    "addr:postcode":"s71 1lp",
    "addr:street":"Old Mill Lane Wakefield Road;Yorkshire",
    "iso:country":"GB",
    "sg:address":"Old Mill Lane, Wakefield Road",
    "sg:city":"Barnsley",
    "sg:classifiers":[
        {
            "category":"Home & Garden",
            "subcategory":"Hardware",
            "type":"Retail Goods"
        }
    ],
    "sg:phone":"+44 1226 786700",
    "sg:postcode":"S71 1LP",
    "sg:province":"South Yorkshire",
    "sg:tags":[
        "retailer",
        "diy"
    ],
    "wof:name":"B & Q Supercentre",
    "wof:placetype":"venue"
},
  "geometry": {"coordinates":[-1.478044,53.558071],"type":"Point"}
}