{
  "type": "Feature",
  "properties": {
    "addr:full":"8 Arran Ave Kilmarnock East Ayrshire KA3 1TP",
    "addr:housenumber":"8",
    "addr:postcode":"ka3 1tp",
    "addr:street":"Arran Ave",
    "iso:country":"GB",
    "sg:address":"8 Arran Ave",
    "sg:city":"Kilmarnock",
    "sg:classifiers":[
        {
            "category":"Building & Trades",
            "subcategory":"Cleaning & Sanitation",
            "type":"Services"
        }
    ],
    "sg:postcode":"KA3 1TP",
    "sg:province":"East Ayrshire",
    "sg:tags":[
        "cleaner",
        "window"
    ],
    "wof:name":"Dumigan,James,",
    "wof:placetype":"venue"
},
  "geometry": {"coordinates":[-4.4908919334,55.6240653992],"type":"Point"}
}