{
  "type": "Feature",
  "properties": {
    "iso:country":"GB",
    "sg:address":"Westwood Hypermarket, 475 Margate Rd",
    "sg:city":"Broadstairs",
    "sg:classifiers":[
        {
            "category":"Food & Beverages",
            "subcategory":"Supermarket",
            "type":"Retail Goods"
        }
    ],
    "sg:phone":"+44 1843 868941",
    "sg:postcode":"CT10 2QJ",
    "sg:province":"Kent",
    "wof:name":"South East Co-op",
    "wof:placetype":"venue"
},
  "geometry": {"coordinates":[1.44106,51.358604],"type":"Point"}
}