{
  "type": "Feature",
  "properties": {
    "iso:country":"GB",
    "sg:address":"223 Dunchurch Road",
    "sg:city":"Rugby",
    "sg:classifiers":[
        {
            "category":"Building & Trades",
            "subcategory":"Equipment Rental",
            "type":"Services"
        }
    ],
    "sg:phone":"+44 1788 522401",
    "sg:postcode":"CV22 6HP",
    "sg:province":"Warwickshire",
    "sg:tags":[
        "plant",
        "machinery"
    ],
    "wof:name":"Roc Hire Ltd.",
    "wof:placetype":"venue"
},
  "geometry": {"coordinates":[-1.269234,52.359272],"type":"Point"}
}