{
  "type": "Feature",
  "properties": {
    "addr:full":"50b Dunure Street Coatbridge North Lanarkshire ML5 5DL",
    "addr:housenumber":"50b",
    "addr:postcode":"ml5 5dl",
    "addr:street":"Dunure Street",
    "iso:country":"GB",
    "sg:address":"50b Dunure Street",
    "sg:city":"Coatbridge",
    "sg:classifiers":[
        {
            "category":"Personal",
            "subcategory":"Beauty Salon",
            "type":"Services"
        }
    ],
    "sg:postcode":"ML5 5DL",
    "sg:province":"North Lanarkshire",
    "sg:tags":[
        "unisex",
        "hairdresser"
    ],
    "wof:name":"Cut Above",
    "wof:placetype":"venue"
},
  "geometry": {"coordinates":[-4.0428738594,55.8452911377],"type":"Point"}
}