{
  "type": "Feature",
  "properties": {
    "iso:country":"GB",
    "sg:address":"23 Henry Street",
    "sg:city":"Gillingham",
    "sg:classifiers":[
        {
            "category":"Manufacturing",
            "subcategory":"Building Materials",
            "type":"Manufacturing & Wholesale Goods"
        }
    ],
    "sg:postcode":"ME8 8HE",
    "sg:province":"Kent",
    "sg:tags":[
        "merchant",
        "builder"
    ],
    "wof:name":"Arnold Bros",
    "wof:placetype":"venue"
},
  "geometry": {"coordinates":[0.6157190204,51.3674545288],"type":"Point"}
}