{
  "type": "Feature",
  "properties": {
    "addr:full":"17 St John Street Manchester Greater Manchester M3 4DR",
    "addr:housenumber":"17",
    "addr:postcode":"m3 4dr",
    "addr:street":"St John Street",
    "iso:country":"GB",
    "sg:address":"17 St John Street",
    "sg:city":"Manchester",
    "sg:classifiers":[
        {
            "category":"Health Services",
            "subcategory":"Doctor",
            "type":"Services"
        }
    ],
    "sg:phone":"+44 161 907 2780",
    "sg:postcode":"M3 4DR",
    "sg:province":"Greater Manchester",
    "sg:tags":[
        "surgeon",
        "practitioners"
    ],
    "wof:name":"Bernard S Sylvester",
    "wof:placetype":"venue"
},
  "geometry": {"coordinates":[-2.2515521049,53.4776420593],"type":"Point"}
}