{
  "type": "Feature",
  "properties": {
    "iso:country":"GB",
    "sg:address":"Solway, Chapel La",
    "sg:city":"Hastings",
    "sg:classifiers":[
        {
            "category":"Manufacturing",
            "subcategory":"Furniture",
            "type":"Manufacturing & Wholesale Goods"
        }
    ],
    "sg:phone":"+44 1424 756187",
    "sg:postcode":"TN35 4QX",
    "sg:province":"East Sussex",
    "sg:tags":[
        "polishing",
        "french"
    ],
    "wof:name":"Andrews Polishers",
    "wof:placetype":"venue"
},
  "geometry": {"coordinates":[0.6320530176,50.8943557739],"type":"Point"}
}