{
  "type": "Feature",
  "properties": {
    "iso:country":"GB",
    "sg:address":"76 Stafford Road",
    "sg:city":"Wallington",
    "sg:classifiers":[
        {
            "category":"Home & Garden",
            "subcategory":"Garden Supply",
            "type":"Retail Goods"
        },
        {
            "category":"Sports & Exercise",
            "subcategory":"Swimming Pool",
            "type":"Entertainment"
        }
    ],
    "sg:phone":"+44 20 8669 0657",
    "sg:postcode":"SM6 9AY",
    "sg:province":"Surrey",
    "sg:tags":[
        "supplier",
        "equipment"
    ],
    "wof:name":"Pool Filtration Ltd.",
    "wof:placetype":"venue"
},
  "geometry": {"coordinates":[-0.144241,51.358727],"type":"Point"}
}