{
  "type": "Feature",
  "properties": {
    "iso:country":"GB",
    "sg:address":"Llanaelhaiarn",
    "sg:city":"Caernarfon",
    "sg:classifiers":[
        {
            "category":"Government",
            "subcategory":"Post Office",
            "type":"Public Place"
        }
    ],
    "sg:phone":"+44 1758 750279",
    "sg:postcode":"LL54 5AL",
    "sg:province":"Gwynedd",
    "wof:name":"Llanaelhaiarn Post Office",
    "wof:placetype":"venue"
},
  "geometry": {"coordinates":[-4.4030599594,52.9758796692],"type":"Point"}
}