{
  "type": "Feature",
  "properties": {
    "iso:country":"GB",
    "sg:address":"Union Street",
    "sg:city":"Oxford",
    "sg:classifiers":[
        {
            "category":"Education",
            "subcategory":"School",
            "type":"Public Place"
        }
    ],
    "sg:phone":"+44 1865 240219",
    "sg:postcode":"OX4 1JP",
    "sg:province":"Oxfordshire",
    "sg:tags":[
        "local",
        "authority"
    ],
    "wof:name":"East Oxford First School",
    "wof:placetype":"venue"
},
  "geometry": {"coordinates":[-1.2363690138,51.7478942871],"type":"Point"}
}