{
  "type": "Feature",
  "properties": {
    "iso:country":"GB",
    "sg:address":"Mohair Farm, York Rd, Barmby Moor",
    "sg:city":"York",
    "sg:classifiers":[
        {
            "category":"Health Services",
            "subcategory":"Clinic",
            "type":"Services"
        }
    ],
    "sg:phone":"+44 1759 380308",
    "sg:postcode":"YO42 4HU",
    "sg:province":"East Riding of Yorkshire",
    "sg:tags":[
        "injury",
        "sport"
    ],
    "wof:name":"L.G Scott B.T.E.R",
    "wof:placetype":"venue"
},
  "geometry": {"coordinates":[-0.81449,53.932056],"type":"Point"}
}