{
  "type": "Feature",
  "properties": {
    "addr:full":"9 Kingsmills Rd Inverness Highland IV2 3JT",
    "addr:housenumber":"9",
    "addr:postcode":"iv2 3jt",
    "addr:street":"Kingsmills Rd",
    "iso:country":"GB",
    "sg:address":"9 Kingsmills Rd",
    "sg:city":"Inverness",
    "sg:classifiers":[
        {
            "category":"Banks & Credit Unions",
            "subcategory":"Bank",
            "type":"Services"
        }
    ],
    "sg:phone":"+44 1463 250510",
    "sg:postcode":"IV2 3JT",
    "sg:province":"Highland",
    "sg:tags":[
        "broker",
        "mortgage"
    ],
    "wof:name":"Crown Mortgage & Investments",
    "wof:placetype":"venue"
},
  "geometry": {"coordinates":[-4.2178411484,57.4766769409],"type":"Point"}
}