{
  "type": "Feature",
  "properties": {
    "addr:full":"12 Alvescot Road Carterton Gloucestershire OX18 3JH",
    "addr:housenumber":"12",
    "addr:postcode":"ox18 3jh",
    "addr:street":"Alvescot Road",
    "iso:country":"GB",
    "sg:address":"12 Alvescot Road",
    "sg:city":"Carterton",
    "sg:classifiers":[
        {
            "category":"Military Area",
            "subcategory":"Air Force Base",
            "type":"Public Place"
        }
    ],
    "sg:phone":"+44 1993 841771",
    "sg:postcode":"OX18 3JH",
    "sg:province":"Gloucestershire",
    "sg:tags":[
        "taxi",
        "hire",
        "private"
    ],
    "wof:name":"Carterton Cars Private Hire",
    "wof:placetype":"venue"
},
  "geometry": {"coordinates":[-1.5961099863,51.7584075928],"type":"Point"}
}