{
  "type": "Feature",
  "properties": {
    "iso:country":"GB",
    "sg:address":"299 Northborough Road, Norbury",
    "sg:city":"London",
    "sg:classifiers":[
        {
            "category":"Professional",
            "subcategory":"Accounting & Tax Preparation",
            "type":"Services"
        }
    ],
    "sg:postcode":"SW16 4TR",
    "sg:province":"Greater London",
    "sg:tags":[
        "accountant"
    ],
    "wof:name":"Leroy Reid & Co.",
    "wof:placetype":"venue"
},
  "geometry": {"coordinates":[-0.136449,51.404152],"type":"Point"}
}