{
  "type": "Feature",
  "properties": {
    "addr:full":"14 York Road Birmingham West Midlands B28 8BE",
    "addr:housenumber":"14",
    "addr:postcode":"b28 8be",
    "addr:street":"York Road",
    "iso:country":"GB",
    "sg:address":"14 York Road",
    "sg:city":"Birmingham",
    "sg:classifiers":[
        {
            "category":"Shopping",
            "subcategory":"Clothing, Apparel, & Fashions",
            "type":"Retail Goods"
        }
    ],
    "sg:phone":"+44 121 777 1468",
    "sg:postcode":"B28 8BE",
    "sg:province":"West Midlands",
    "sg:tags":[
        "haberdasher"
    ],
    "wof:name":"Reg Gardener",
    "wof:placetype":"venue"
},
  "geometry": {"coordinates":[-1.847916,52.440701],"type":"Point"}
}