{
  "type": "Feature",
  "properties": {
    "iso:country":"GB",
    "sg:address":"Hill Farm Lane, Tirley",
    "sg:city":"Gloucester",
    "sg:classifiers":[
        {
            "category":"Home & Garden",
            "subcategory":"Garden Supply",
            "type":"Retail Goods"
        },
        {
            "category":"Farming",
            "subcategory":"Livestock Farm",
            "type":"Manufacturing & Wholesale Goods"
        }
    ],
    "sg:phone":"+44 1452 780208",
    "sg:postcode":"GL19 4HA",
    "sg:province":"Gloucestershire",
    "sg:tags":[
        "bulb",
        "grower",
        "others"
    ],
    "wof:name":"D E S Smith",
    "wof:placetype":"venue"
},
  "geometry": {"coordinates":[-2.242275,51.956245],"type":"Point"}
}