{
  "type": "Feature",
  "properties": {
    "addr:full":"8 Deerhurst House, Deerhurst Crescent Portsmouth Hampshire PO6 4EL",
    "addr:housenumber":"8",
    "addr:postcode":"hampshire po6 4el",
    "addr:street":"Deerhurst House Deerhurst Crescent",
    "iso:country":"GB",
    "sg:address":"8 Deerhurst House, Deerhurst Crescent",
    "sg:city":"Portsmouth",
    "sg:classifiers":[
        {
            "category":"Health Services",
            "subcategory":"Chiropractor",
            "type":"Services"
        }
    ],
    "sg:phone":"+44 23 9232 5816",
    "sg:postcode":"PO6 4EL",
    "sg:province":"Hampshire",
    "wof:name":"Paul Bridle D.S M.R.S.S",
    "wof:placetype":"venue"
},
  "geometry": {"coordinates":[-1.10417,50.853081],"type":"Point"}
}