{
  "type": "Feature",
  "properties": {
    "addr:full":"2 Mount Connerton Close Angarrack La Hayle Cornwall TR27 5JF",
    "addr:housenumber":"2",
    "addr:postcode":"tr27 5jf",
    "addr:street":"Mount Connerton Close;La Hayle",
    "iso:country":"GB",
    "sg:address":"2 Mount Connerton Close Angarrack La",
    "sg:city":"Hayle",
    "sg:classifiers":[
        {
            "category":"Military Area",
            "subcategory":"Air Force Base",
            "type":"Public Place"
        }
    ],
    "sg:phone":"+44 1736 795599",
    "sg:postcode":"TR27 5JF",
    "sg:province":"Cornwall",
    "sg:tags":[
        "taxi",
        "hire",
        "private"
    ],
    "wof:name":"White Line Taxis",
    "wof:placetype":"venue"
},
  "geometry": {"coordinates":[-5.3866782188,50.1945457458],"type":"Point"}
}