{
  "type": "Feature",
  "properties": {
    "addr:full":"2 Eagle Brow Lymm Cheshire WA13 0AD",
    "addr:housenumber":"2",
    "addr:postcode":"wa13 0ad",
    "addr:street":"Eagle Brow",
    "iso:country":"GB",
    "sg:address":"2 Eagle Brow",
    "sg:city":"Lymm",
    "sg:classifiers":[
        {
            "category":"Food & Beverages",
            "subcategory":"Bakery",
            "type":"Retail Goods"
        }
    ],
    "sg:phone":"+44 1925 753669",
    "sg:postcode":"WA13 0AD",
    "sg:province":"Cheshire",
    "sg:tags":[
        "baker"
    ],
    "wof:name":"S Sexton Ltd.",
    "wof:placetype":"venue"
},
  "geometry": {"coordinates":[-2.4789121151,53.3808326721],"type":"Point"}
}