{
  "type": "Feature",
  "properties": {
    "iso:country":"GB",
    "sg:address":"12 Redcliffe Road",
    "sg:city":"Mansfield",
    "sg:classifiers":[
        {
            "category":"Building & Trades",
            "subcategory":"Construction",
            "type":"Services"
        }
    ],
    "sg:phone":"+44 1623 471420",
    "sg:postcode":"NG18 2QN",
    "sg:province":"Nottinghamshire",
    "sg:tags":[
        "builder"
    ],
    "wof:name":"Accomplished Plastering & Building Services",
    "wof:placetype":"venue"
},
  "geometry": {"coordinates":[-1.184473,53.143787],"type":"Point"}
}