{
  "type": "Feature",
  "properties": {
    "addr:full":"4 Ifton Road, Rogiet Caldicot Monmouthshire NP26 3SS",
    "addr:housenumber":"4",
    "addr:postcode":"np26 3ss",
    "addr:street":"Ifton Road",
    "iso:country":"GB",
    "sg:address":"4 Ifton Road, Rogiet",
    "sg:city":"Caldicot",
    "sg:classifiers":[
        {
            "category":"Retail",
            "subcategory":"Repair Shop",
            "type":"Services"
        }
    ],
    "sg:phone":"+44 1291 424809",
    "sg:postcode":"NP26 3SS",
    "sg:province":"Monmouthshire",
    "sg:tags":[
        "radio",
        "television",
        "video"
    ],
    "wof:name":"Kenneth Berriman",
    "wof:placetype":"venue"
},
  "geometry": {"coordinates":[-2.748045,51.585957],"type":"Point"}
}