{
  "type": "Feature",
  "properties": {
    "iso:country":"GB",
    "sg:address":"66 Shepherds Green Road",
    "sg:city":"Birmingham",
    "sg:classifiers":[
        {
            "category":"Building & Trades",
            "subcategory":"Landscaping Services",
            "type":"Services"
        }
    ],
    "sg:phone":"+44 121 373 1799",
    "sg:postcode":"B24 8EU",
    "sg:province":"West Midlands",
    "sg:tags":[
        "gardening"
    ],
    "wof:name":"Tom Conway",
    "wof:placetype":"venue"
},
  "geometry": {"coordinates":[-1.8457870483,52.5129394531],"type":"Point"}
}