{
  "type": "Feature",
  "properties": {
    "iso:country":"GB",
    "sg:address":"102 Blackford Avenue",
    "sg:city":"Edinburgh",
    "sg:classifiers":[
        {
            "category":"Health Services",
            "subcategory":"Dentist",
            "type":"Services"
        }
    ],
    "sg:phone":"+44 131 662 4560",
    "sg:postcode":"EH9 3ES",
    "sg:province":"City of Edinburgh",
    "sg:tags":[
        "technician",
        "dental"
    ],
    "wof:name":"Pentland Crown & Bridge",
    "wof:placetype":"venue"
},
  "geometry": {"coordinates":[-3.185622,55.926319],"type":"Point"}
}