{
  "type": "Feature",
  "properties": {
    "iso:country":"GB",
    "sg:address":"28 Market Place",
    "sg:city":"Brampton",
    "sg:classifiers":[
        {
            "category":"Food & Beverages",
            "subcategory":"Groceries & Convenience Stores",
            "type":"Retail Goods"
        }
    ],
    "sg:phone":"+44 16977 3967",
    "sg:postcode":"CA8 1RW",
    "sg:province":"Cumbria",
    "wof:name":"Spar Eight Till Late",
    "wof:placetype":"venue"
},
  "geometry": {"coordinates":[-2.73594,54.942196],"type":"Point"}
}