{
  "type": "Feature",
  "properties": {
    "iso:country":"GB",
    "sg:address":"47e West End",
    "sg:city":"West Calder",
    "sg:classifiers":[
        {
            "category":"Autos & Motor Vehicles",
            "subcategory":"Automobile Sales",
            "type":"Retail Goods"
        }
    ],
    "sg:phone":"+44 1506 872333",
    "sg:postcode":"EH55 8EJ",
    "sg:province":"South Lanarkshire",
    "sg:tags":[
        "car"
    ],
    "wof:name":"David Macmurchie",
    "wof:placetype":"venue"
},
  "geometry": {"coordinates":[-3.575547,55.850147],"type":"Point"}
}