{
  "type": "Feature",
  "properties": {
    "iso:country":"GB",
    "sg:address":"Ely Road, Waterbeach",
    "sg:city":"Cambridge",
    "sg:classifiers":[
        {
            "category":"Utilities",
            "subcategory":"Refuse",
            "type":"Services"
        }
    ],
    "sg:postcode":"CB5 9PG",
    "sg:province":"Cambridgeshire",
    "sg:tags":[
        "skip",
        "hire"
    ],
    "wof:name":"Donarbon Ltd.",
    "wof:placetype":"venue"
},
  "geometry": {"coordinates":[0.1803209931,52.2675895691],"type":"Point"}
}