{
  "type": "Feature",
  "properties": {
    "addr:full":"58 The Street, Wrecclesham Farnham Hampshire GU10 4QR",
    "addr:housenumber":"58",
    "addr:postcode":"gu10 4qr",
    "addr:street":"The Street",
    "iso:country":"GB",
    "sg:address":"58 The Street, Wrecclesham",
    "sg:city":"Farnham",
    "sg:classifiers":[
        {
            "category":"Home & Garden",
            "subcategory":"Home Furnishings",
            "type":"Retail Goods"
        }
    ],
    "sg:phone":"+44 1252 737723",
    "sg:postcode":"GU10 4QR",
    "sg:province":"Hampshire",
    "sg:tags":[
        "mantelpiece",
        "fireplace"
    ],
    "wof:name":"Artistic Masonry and Regency Fireplaces",
    "wof:placetype":"venue"
},
  "geometry": {"coordinates":[-0.8196280003,51.1980743408],"type":"Point"}
}