{
  "type": "Feature",
  "properties": {
    "addr:full":"5 Lampton House Close Wimbledon Greater London SW19 5EX",
    "addr:housenumber":"5",
    "addr:postcode":"sw19 5ex",
    "addr:street":"Lampton House Close",
    "iso:country":"GB",
    "sg:address":"5 Lampton House Close",
    "sg:city":"Wimbledon",
    "sg:classifiers":[
        {
            "category":"Food & Beverages",
            "subcategory":"Groceries & Convenience Stores",
            "type":"Retail Goods"
        }
    ],
    "sg:phone":"+44 20 8879 7767",
    "sg:postcode":"SW19 5EX",
    "sg:province":"Greater London",
    "sg:tags":[
        "frozen",
        "ice"
    ],
    "wof:name":"Duncan Hamilton Ice Sculptor",
    "wof:placetype":"venue"
},
  "geometry": {"coordinates":[-0.221487,51.429619],"type":"Point"}
}