{
  "type": "Feature",
  "properties": {
    "iso:country":"GB",
    "sg:address":"58-62 Fort Street, Broughty Ferry",
    "sg:city":"Dundee",
    "sg:classifiers":[
        {
            "category":"Travel",
            "subcategory":"Hotels & Motels",
            "type":"Entertainment"
        }
    ],
    "sg:phone":"+44 1382 737999",
    "sg:postcode":"DD5 2AB",
    "sg:province":"Angus",
    "wof:name":"Fort Hotel",
    "wof:placetype":"venue"
},
  "geometry": {"coordinates":[-2.876284,56.466541],"type":"Point"}
}