{
  "type": "Feature",
  "properties": {
    "addr:full":"1 Binfield Road Wokingham Berkshire RG40 1SL",
    "addr:housenumber":"1",
    "addr:postcode":"rg40 1sl",
    "addr:street":"Binfield Road",
    "iso:country":"GB",
    "sg:address":"1 Binfield Road",
    "sg:city":"Wokingham",
    "sg:classifiers":[
        {
            "category":"Professional",
            "subcategory":"Computer Services",
            "type":"Services"
        }
    ],
    "sg:phone":"+44 118 989 2625",
    "sg:postcode":"RG40 1SL",
    "sg:province":"Berkshire",
    "sg:tags":[
        "system",
        "software"
    ],
    "wof:name":"Tailormade",
    "wof:placetype":"venue"
},
  "geometry": {"coordinates":[-0.819894,51.411377],"type":"Point"}
}