{
  "type": "Feature",
  "properties": {
    "addr:full":"The Garages Station Road Milton Keynes Buckinghamshire MK16 0AG",
    "addr:postcode":"mk16 0ag",
    "addr:street":"Station Road",
    "iso:country":"GB",
    "sg:address":"The Garages Station Road",
    "sg:city":"Milton Keynes",
    "sg:classifiers":[
        {
            "category":"Retail",
            "subcategory":"Auto Repair",
            "type":"Services"
        }
    ],
    "sg:phone":"+44 1908 612871",
    "sg:postcode":"MK16 0AG",
    "sg:province":"Buckinghamshire",
    "sg:tags":[
        "modification",
        "garage"
    ],
    "wof:name":"D J C Autos",
    "wof:placetype":"venue"
},
  "geometry": {"coordinates":[-0.7284790277,52.0837783813],"type":"Point"}
}