{
  "type": "Feature",
  "properties": {
    "iso:country":"GB",
    "sg:address":"7 Harley St",
    "sg:city":"West End",
    "sg:classifiers":[
        {
            "category":"Building & Trades",
            "subcategory":"Construction",
            "type":"Services"
        }
    ],
    "sg:phone":"+44 20 7636 1992",
    "sg:postcode":"W1N 1DA",
    "sg:province":"Hampshire",
    "sg:tags":[
        "management"
    ],
    "wof:name":"Charter Project Management",
    "wof:placetype":"venue"
},
  "geometry": {"coordinates":[-0.146317,51.517159],"type":"Point"}
}