{
  "type": "Feature",
  "properties": {
    "addr:full":"1 Wood Nook, Norland Sowerby Bridge West Yorkshire HX6 3RZ",
    "addr:housenumber":"1",
    "addr:postcode":"hx6 3rz",
    "addr:street":"Wood Nook Norland;West",
    "iso:country":"GB",
    "sg:address":"1 Wood Nook, Norland",
    "sg:city":"Sowerby Bridge",
    "sg:classifiers":[
        {
            "category":"Professional",
            "subcategory":"Computer Services",
            "type":"Services"
        }
    ],
    "sg:phone":"+44 1422 831331",
    "sg:postcode":"HX6 3RZ",
    "sg:province":"West Yorkshire",
    "sg:tags":[
        "system",
        "software"
    ],
    "wof:name":"Abc (Northern) Ltd",
    "wof:placetype":"venue"
},
  "geometry": {"coordinates":[-1.913934,53.706539],"type":"Point"}
}