{
  "type": "Feature",
  "properties": {
    "addr:full":"4 Royce Road Peterborough Cambridgeshire PE1 5YB",
    "addr:housenumber":"4",
    "addr:postcode":"pe1 5yb",
    "addr:street":"Royce Road",
    "iso:country":"GB",
    "sg:address":"4 Royce Road",
    "sg:city":"Peterborough",
    "sg:classifiers":[
        {
            "category":"Building & Trades",
            "subcategory":"Construction",
            "type":"Services"
        },
        {
            "category":"Building & Trades",
            "subcategory":"Pest Control",
            "type":"Services"
        }
    ],
    "sg:phone":"+44 1733 560338",
    "sg:postcode":"PE1 5YB",
    "sg:province":"Cambridgeshire",
    "sg:tags":[
        "equipment",
        "hire",
        "crane",
        "sales"
    ],
    "wof:name":"Quinto Crane & Plant Ltd.",
    "wof:placetype":"venue"
},
  "geometry": {"coordinates":[-0.2196190059,52.579120636],"type":"Point"}
}