{
  "type": "Feature",
  "properties": {
    "iso:country":"GB",
    "sg:address":"Bear Lane, Stadhampton",
    "sg:city":"Oxford",
    "sg:classifiers":[
        {
            "category":"Bars & Pubs",
            "type":"Food & Drink"
        }
    ],
    "sg:phone":"+44 1865 890714",
    "sg:postcode":"OX44 7UR",
    "sg:province":"Oxfordshire",
    "sg:tags":[
        "pubs",
        "inn"
    ],
    "wof:name":"The Crazy Bear & Ragged Staff",
    "wof:placetype":"venue"
},
  "geometry": {"coordinates":[-1.129404,51.683094],"type":"Point"}
}