{
  "type": "Feature",
  "properties": {
    "iso:country":"GB",
    "sg:address":"10 Hayling Road",
    "sg:city":"Sale",
    "sg:classifiers":[
        {
            "category":"Building & Trades",
            "subcategory":"Landscaping Services",
            "type":"Services"
        }
    ],
    "sg:phone":"+44 161 905 2871",
    "sg:postcode":"M33 6GW",
    "sg:province":"Cheshire",
    "sg:tags":[
        "landscape",
        "contractor"
    ],
    "wof:name":"K O'Shea Landscapes",
    "wof:placetype":"venue"
},
  "geometry": {"coordinates":[-2.340379,53.425869],"type":"Point"}
}