{
  "type": "Feature",
  "properties": {
    "addr:full":"11 Harwill App Leeds West Yorkshire LS27 7DW",
    "addr:housenumber":"11",
    "addr:postcode":"ls27 7dw",
    "addr:street":"Harwill",
    "iso:country":"GB",
    "sg:address":"11 Harwill App",
    "sg:city":"Leeds",
    "sg:classifiers":[
        {
            "category":"Professional",
            "subcategory":"Engineering",
            "type":"Services"
        }
    ],
    "sg:postcode":"LS27 7DW",
    "sg:province":"West Yorkshire",
    "sg:tags":[
        "contractor",
        "electrical",
        "engineer"
    ],
    "wof:name":"Taylor,S,",
    "wof:placetype":"venue"
},
  "geometry": {"coordinates":[-1.6331700087,53.7594451904],"type":"Point"}
}