{
  "type": "Feature",
  "properties": {
    "iso:country":"GB",
    "sg:address":"The Old Cottage, Spencers Orchard",
    "sg:city":"Bradford-on-avon",
    "sg:classifiers":[
        {
            "category":"Travel",
            "subcategory":"Hotels & Motels",
            "type":"Entertainment"
        }
    ],
    "sg:phone":"+44 1225 868414",
    "sg:postcode":"BA15 1TJ",
    "sg:province":"Wiltshire",
    "sg:tags":[
        "house",
        "guest"
    ],
    "wof:name":"The Old Cottage",
    "wof:placetype":"venue"
},
  "geometry": {"coordinates":[-2.251777,51.348358],"type":"Point"}
}