{
  "type": "Feature",
  "properties": {
    "addr:full":"457 Stratford Road, Shirley Solihull West Midlands B90 4AA",
    "addr:housenumber":"457",
    "addr:postcode":"b90 4aa",
    "addr:street":"Stratford Road",
    "iso:country":"GB",
    "sg:address":"457 Stratford Road, Shirley",
    "sg:city":"Solihull",
    "sg:classifiers":[
        {
            "category":"Autos & Motor Vehicles",
            "subcategory":"Fuel & Gas Station",
            "type":"Retail Goods"
        }
    ],
    "sg:phone":"+44 121 745 9316",
    "sg:postcode":"B90 4AA",
    "sg:province":"West Midlands",
    "sg:tags":[
        "hr",
        "petrol"
    ],
    "wof:name":"B P",
    "wof:placetype":"venue"
},
  "geometry": {"coordinates":[-1.821877,52.403896],"type":"Point"}
}