{
  "type": "Feature",
  "properties": {
    "addr:full":"15-19 Pit Hey Place Skelmersdale Lancashire WN8 9PS",
    "addr:housenumber":"15-19",
    "addr:postcode":"wn8 9ps",
    "addr:street":"Pit Hey Place Skelmersdale",
    "iso:country":"GB",
    "sg:address":"15-19 Pit Hey Place",
    "sg:city":"Skelmersdale",
    "sg:classifiers":[
        {
            "category":"Manufacturing",
            "subcategory":"Textiles",
            "type":"Manufacturing & Wholesale Goods"
        }
    ],
    "sg:phone":"+44 1695 723946",
    "sg:postcode":"WN8 9PS",
    "sg:province":"Lancashire",
    "sg:tags":[
        "made-up"
    ],
    "wof:name":"Bayex Ltd",
    "wof:placetype":"venue"
},
  "geometry": {"coordinates":[-2.765605,53.531246],"type":"Point"}
}