{
  "type": "Feature",
  "properties": {
    "addr:full":"Beals Cottage, Beals Lane, Tilehurst Reading Berkshire RG31 5UD",
    "addr:postcode":"rg31 5ud",
    "addr:street":"Beals Lane",
    "iso:country":"GB",
    "sg:address":"Beals Cottage, Beals Lane, Tilehurst",
    "sg:city":"Reading",
    "sg:classifiers":[
        {
            "category":"Personal",
            "subcategory":"Hair Removal",
            "type":"Services"
        }
    ],
    "sg:postcode":"RG31 5UD",
    "sg:province":"Berkshire",
    "sg:tags":[
        "electrolysis"
    ],
    "wof:name":"Kathryn Elliott",
    "wof:placetype":"venue"
},
  "geometry": {"coordinates":[-1.036564,51.46077],"type":"Point"}
}