{
  "type": "Feature",
  "properties": {
    "addr:full":"55 Water St Abergele Conwy LL22 7SN",
    "addr:housenumber":"55",
    "addr:postcode":"ll22 7sn",
    "addr:street":"Water St",
    "iso:country":"GB",
    "sg:address":"55 Water St",
    "sg:city":"Abergele",
    "sg:classifiers":[
        {
            "category":"Home & Garden",
            "subcategory":"Hardware",
            "type":"Retail Goods"
        }
    ],
    "sg:postcode":"LL22 7SN",
    "sg:province":"Conwy",
    "sg:tags":[
        "centre",
        "improvement"
    ],
    "wof:name":"Dulas Home Improvements",
    "wof:placetype":"venue"
},
  "geometry": {"coordinates":[-3.5828790665,53.2862167358],"type":"Point"}
}