{
  "type": "Feature",
  "properties": {
    "addr:full":"30 Earl Gardens Falmouth Cornwall TR11 2JB",
    "addr:housenumber":"30",
    "addr:postcode":"tr11 2jb",
    "addr:street":"Earl Gardens",
    "iso:country":"GB",
    "sg:address":"30 Earl Gardens",
    "sg:city":"Falmouth",
    "sg:classifiers":[
        {
            "category":"Building & Trades",
            "subcategory":"Plumbing",
            "type":"Services"
        }
    ],
    "sg:phone":"+44 1326 311316",
    "sg:postcode":"TR11 2JB",
    "sg:province":"Cornwall",
    "sg:tags":[
        "heating"
    ],
    "wof:name":"A Wijer",
    "wof:placetype":"venue"
},
  "geometry": {"coordinates":[-5.0800328255,50.1522064209],"type":"Point"}
}