{
  "type": "Feature",
  "properties": {
    "addr:full":"45 Southill Road Bournemouth Dorset BH9 1SH",
    "addr:housenumber":"45",
    "addr:postcode":"bh9 1sh",
    "addr:street":"Southill Road",
    "iso:country":"GB",
    "sg:address":"45 Southill Road",
    "sg:city":"Bournemouth",
    "sg:classifiers":[
        {
            "category":"Retail",
            "subcategory":"Driving School",
            "type":"Services"
        }
    ],
    "sg:postcode":"BH9 1SH",
    "sg:province":"Dorset",
    "wof:name":"Jeff Gawler",
    "wof:placetype":"venue"
},
  "geometry": {"coordinates":[-1.866758,50.748264],"type":"Point"}
}