{
  "type": "Feature",
  "properties": {
    "iso:country":"GB",
    "sg:address":"45 Southill Road",
    "sg:city":"Bournemouth",
    "sg:classifiers":[
        {
            "category":"Retail",
            "subcategory":"Driving School",
            "type":"Services"
        }
    ],
    "sg:postcode":"BH9 1SH",
    "sg:province":"Dorset",
    "wof:name":"Jeff Gawler",
    "wof:placetype":"venue"
},
  "geometry": {"coordinates":[-1.866758,50.748264],"type":"Point"}
}