{
  "type": "Feature",
  "properties": {
    "iso:country":"GB",
    "sg:address":"118 Grahamston Park, Barrhead",
    "sg:city":"Glasgow",
    "sg:classifiers":[
        {
            "category":"Home & Garden",
            "subcategory":"Home Furnishings",
            "type":"Retail Goods"
        },
        {
            "category":"Home & Garden",
            "subcategory":"Carpets & Floor Coverings",
            "type":"Retail Goods"
        }
    ],
    "sg:phone":"+44 141 876 0770",
    "sg:postcode":"G78 1NJ",
    "sg:province":"East Ayrshire",
    "sg:tags":[
        "fitting",
        "rug",
        "matting",
        "carpets"
    ],
    "wof:name":"G Haveron",
    "wof:placetype":"venue"
},
  "geometry": {"coordinates":[-4.3950490952,55.8103485107],"type":"Point"}
}