{
  "type": "Feature",
  "properties": {
    "addr:full":"Unit 4, Newhouse Industrial Estate Motherwell North Lanarkshire ML1 5RX",
    "addr:housenumber":"unit 4",
    "addr:postcode":"ml1 5rx",
    "addr:street":"Newhouse Industrial Estate",
    "iso:country":"GB",
    "sg:address":"Unit 4, Newhouse Industrial Estate",
    "sg:city":"Motherwell",
    "sg:classifiers":[
        {
            "category":"Manufacturing",
            "subcategory":"Rubber & Plastics",
            "type":"Manufacturing & Wholesale Goods"
        }
    ],
    "sg:phone":"+44 1698 832343",
    "sg:postcode":"ML1 5RX",
    "sg:province":"North Lanarkshire",
    "sg:tags":[
        "product"
    ],
    "wof:name":"Olgelin Ltd.",
    "wof:placetype":"venue"
},
  "geometry": {"coordinates":[-3.9915189743,55.7887649536],"type":"Point"}
}