{
  "type": "Feature",
  "properties": {
    "iso:country":"GB",
    "sg:address":"150 South Parade, Matlock Bath",
    "sg:city":"Matlock",
    "sg:classifiers":[
        {
            "category":"Travel",
            "subcategory":"Hotels & Motels",
            "type":"Entertainment"
        }
    ],
    "sg:phone":"+44 1629 582170",
    "sg:postcode":"DE4 3NR",
    "sg:province":"Derbyshire",
    "wof:name":"Hodgkinsons Hotel",
    "wof:placetype":"venue"
},
  "geometry": {"coordinates":[-1.563525,53.12038],"type":"Point"}
}