{
  "type": "Feature",
  "properties": {
    "addr:full":"The Old Stables, Gainsborough Road, Drinsey Nook Lincoln Lincolnshire LN1 2JJ",
    "addr:postcode":"ln1 2jj",
    "addr:street":"Gainsborough Road Drinsey Nook Lincoln",
    "iso:country":"GB",
    "sg:address":"The Old Stables, Gainsborough Road, Drinsey Nook",
    "sg:city":"Lincoln",
    "sg:classifiers":[
        {
            "category":"Professional",
            "subcategory":"Art Services",
            "type":"Services"
        }
    ],
    "sg:phone":"+44 1522 704485",
    "sg:postcode":"LN1 2JJ",
    "sg:province":"Lincolnshire",
    "sg:tags":[
        "model",
        "maker"
    ],
    "wof:name":"Mobile Marine Models",
    "wof:placetype":"venue"
},
  "geometry": {"coordinates":[-0.6963239908,53.2591896057],"type":"Point"}
}