{
  "type": "Feature",
  "properties": {
    "iso:country":"GB",
    "sg:address":"1 Burrow Road",
    "sg:city":"Ilfracombe",
    "sg:classifiers":[
        {
            "category":"Food & Beverages",
            "subcategory":"Liquor & Beverages",
            "type":"Retail Goods"
        }
    ],
    "sg:postcode":"EX34 8JD",
    "sg:province":"Devon",
    "sg:tags":[
        "beer",
        "spirit",
        "wines"
    ],
    "wof:name":"Thirst Quenchers",
    "wof:placetype":"venue"
},
  "geometry": {"coordinates":[-4.12508,51.205406],"type":"Point"}
}