{
  "type": "Feature",
  "properties": {
    "iso:country":"GB",
    "sg:address":"212 Dudley Road",
    "sg:city":"Wolverhampton",
    "sg:classifiers":[
        {
            "category":"Shopping",
            "type":"Retail Goods"
        }
    ],
    "sg:phone":"+44 1902 334429",
    "sg:postcode":"WV2 3JP",
    "sg:province":"West Midlands",
    "sg:tags":[
        "part",
        "accessory"
    ],
    "wof:name":"Topgear Motospot",
    "wof:placetype":"venue"
},
  "geometry": {"coordinates":[-2.1264619827,52.5757827759],"type":"Point"}
}