{
  "type": "Feature",
  "properties": {
    "addr:full":"Bellease Farm, Belchalwell Blandford Forum Dorset DT11 0EQ",
    "addr:postcode":"dt11 0eq",
    "addr:street":"Belchalwell",
    "iso:country":"GB",
    "sg:address":"Bellease Farm, Belchalwell",
    "sg:city":"Blandford Forum",
    "sg:classifiers":[
        {
            "category":"Farming",
            "subcategory":"Livestock Farm",
            "type":"Manufacturing & Wholesale Goods"
        }
    ],
    "sg:phone":"+44 1258 472328",
    "sg:postcode":"DT11 0EQ",
    "sg:province":"Dorset",
    "sg:tags":[
        "others"
    ],
    "wof:name":"R W Courage & Son",
    "wof:placetype":"venue"
},
  "geometry": {"coordinates":[-2.2986090183,50.8861274719],"type":"Point"}
}