{
  "type": "Feature",
  "properties": {
    "iso:country":"GB",
    "sg:address":"Forest View, Groby",
    "sg:city":"Leicester",
    "sg:classifiers":[
        {
            "category":"Education",
            "subcategory":"School",
            "type":"Public Place"
        }
    ],
    "sg:phone":"+44 116 287 6749",
    "sg:postcode":"LE6 0BB",
    "sg:province":"Leicestershire",
    "sg:tags":[
        "local",
        "authority"
    ],
    "wof:name":"Martinshaw County Primary School",
    "wof:placetype":"venue"
},
  "geometry": {"coordinates":[-1.229483,52.661114],"type":"Point"}
}