{
  "type": "Feature",
  "properties": {
    "addr:full":"Bell Lane, Cocking Midhurst West Sussex GU29 0HN",
    "addr:postcode":"gu29 0hn",
    "addr:street":"Bell Lane",
    "iso:country":"GB",
    "sg:address":"Bell Lane, Cocking",
    "sg:city":"Midhurst",
    "sg:classifiers":[
        {
            "category":"Bars & Pubs",
            "type":"Food & Drink"
        }
    ],
    "sg:phone":"+44 1730 813449",
    "sg:postcode":"GU29 0HN",
    "sg:province":"West Sussex",
    "sg:tags":[
        "pubs",
        "inn"
    ],
    "wof:name":"The Blue Bell Inn",
    "wof:placetype":"venue"
},
  "geometry": {"coordinates":[-0.7504889965,50.9521560669],"type":"Point"}
}