{
  "type": "Feature",
  "properties": {
    "addr:full":"North Cestrian Grammar School, Durham Rd Altrincham Cheshire WA14 4AJ",
    "addr:postcode":"wa14 4aj",
    "addr:street":"North;Durham Rd",
    "iso:country":"GB",
    "sg:address":"North Cestrian Grammar School, Durham Rd",
    "sg:city":"Altrincham",
    "sg:classifiers":[
        {
            "category":"Education",
            "subcategory":"School",
            "type":"Public Place"
        }
    ],
    "sg:postcode":"WA14 4AJ",
    "sg:province":"Cheshire",
    "sg:tags":[
        "independent",
        "preparatory"
    ],
    "wof:name":"North Cestrian Grammar School Ltd",
    "wof:placetype":"venue"
},
  "geometry": {"coordinates":[-2.349209,53.386726],"type":"Point"}
}