{
  "type": "Feature",
  "properties": {
    "addr:full":"Fairney House, Unit 14 Wesley Drive Newcastle-upon-tyne Tyne and Wear NE12 9UP",
    "addr:housenumber":"unit 14",
    "addr:postcode":"ne12 9up",
    "addr:street":"Wesley Drive",
    "iso:country":"GB",
    "sg:address":"Fairney House, Unit 14 Wesley Drive",
    "sg:city":"Newcastle-upon-tyne",
    "sg:classifiers":[
        {
            "category":"Professional",
            "subcategory":"Computer Services",
            "type":"Services"
        }
    ],
    "sg:phone":"+44 191 280 8660",
    "sg:postcode":"NE12 9UP",
    "sg:province":"Tyne and Wear",
    "sg:tags":[
        "system",
        "software"
    ],
    "wof:name":"Rombus Computers Ltd.",
    "wof:placetype":"venue"
},
  "geometry": {"coordinates":[-1.5342259407,55.0245323181],"type":"Point"}
}