{
  "type": "Feature",
  "properties": {
    "iso:country":"GB",
    "sg:address":"33 London Road",
    "sg:city":"Dover",
    "sg:classifiers":[
        {
            "category":"Banks & Credit Unions",
            "subcategory":"Financial Services",
            "type":"Services"
        }
    ],
    "sg:phone":"+44 1304 211031",
    "sg:postcode":"CT17 0SS",
    "sg:province":"Kent",
    "sg:tags":[
        "cashing",
        "cheque"
    ],
    "wof:name":"Cash Centres",
    "wof:placetype":"venue"
},
  "geometry": {"coordinates":[1.3039050102,51.1318206787],"type":"Point"}
}