{
  "type": "Feature",
  "properties": {
    "addr:full":"82 Broomside Lane Durham Durham DH1 2QT",
    "addr:housenumber":"82",
    "addr:postcode":"dh1 2qt",
    "addr:street":"Broomside Lane",
    "iso:country":"GB",
    "sg:address":"82 Broomside Lane",
    "sg:city":"Durham",
    "sg:classifiers":[
        {
            "category":"Food & Beverages",
            "subcategory":"Specialty",
            "type":"Retail Goods"
        }
    ],
    "sg:phone":"+44 191 384 7049",
    "sg:postcode":"DH1 2QT",
    "sg:province":"Durham",
    "sg:tags":[
        "dietetic",
        "homogenised"
    ],
    "wof:name":"Optimum Nutrition & Aloe Vera",
    "wof:placetype":"venue"
},
  "geometry": {"coordinates":[-1.5195610523,54.7890052795],"type":"Point"}
}