{
  "type": "Feature",
  "properties": {
    "iso:country":"GB",
    "sg:address":"12 Egan Street",
    "sg:city":"Preston",
    "sg:classifiers":[
        {
            "category":"Bars & Pubs",
            "type":"Food & Drink"
        }
    ],
    "sg:phone":"+44 1772 908565",
    "sg:postcode":"PR1 1TX",
    "sg:province":"Lancashire",
    "sg:tags":[
        "pubs",
        "inn"
    ],
    "wof:name":"Windsor Castle Hotel",
    "wof:placetype":"venue"
},
  "geometry": {"coordinates":[-2.694739,53.76302],"type":"Point"}
}