{
  "type": "Feature",
  "properties": {
    "iso:country":"GB",
    "sg:address":"16 Woodside Terr",
    "sg:city":"Glasgow",
    "sg:classifiers":[
        {
            "category":"Professional",
            "subcategory":"Management & Consulting",
            "type":"Services"
        }
    ],
    "sg:postcode":"G3 7XH",
    "sg:province":"Glasgow City",
    "sg:tags":[
        "consultant",
        "business"
    ],
    "wof:name":"Fletcher,Paul,",
    "wof:placetype":"venue"
},
  "geometry": {"coordinates":[-4.275203,55.867649],"type":"Point"}
}