{
  "type": "Feature",
  "properties": {
    "iso:country":"GB",
    "sg:address":"Unit 7 Gatehouse View, Marchington Industrial Estate",
    "sg:city":"Uttoxeter",
    "sg:classifiers":[
        {
            "category":"Military Area",
            "subcategory":"Army Base",
            "type":"Public Place"
        },
        {
            "category":"Manufacturing",
            "subcategory":"Electronics",
            "type":"Manufacturing & Wholesale Goods"
        }
    ],
    "sg:postcode":"ST14 8LP",
    "sg:province":"Derbyshire",
    "sg:tags":[
        "mnfr",
        "printed",
        "circuit"
    ],
    "wof:name":"Hawthorne Components Ltd",
    "wof:placetype":"venue"
},
  "geometry": {"coordinates":[-1.807716012,52.8694610596],"type":"Point"}
}