{
  "type": "Feature",
  "properties": {
    "addr:full":"2 Robin Down Clo Mansfield Nottinghamshire NG18 4ST",
    "addr:housenumber":"2",
    "addr:postcode":"ng18 4st",
    "addr:street":"Robin Down",
    "iso:country":"GB",
    "sg:address":"2 Robin Down Clo",
    "sg:city":"Mansfield",
    "sg:classifiers":[
        {
            "category":"Organizations",
            "subcategory":"Non-profit Organization",
            "type":"Services"
        }
    ],
    "sg:phone":"+44 1623 625399",
    "sg:postcode":"NG18 4ST",
    "sg:province":"Nottinghamshire",
    "sg:tags":[
        "organisation",
        "voluntary",
        "charity"
    ],
    "wof:name":"Cancer Research Campaign",
    "wof:placetype":"venue"
},
  "geometry": {"coordinates":[-1.1853990555,53.124458313],"type":"Point"}
}