{
  "type": "Feature",
  "properties": {
    "iso:country":"GB",
    "sg:address":"Unit 2a West Pde",
    "sg:city":"Halifax",
    "sg:classifiers":[
        {
            "category":"Manufacturing",
            "subcategory":"Tools & Machinery",
            "type":"Manufacturing & Wholesale Goods"
        }
    ],
    "sg:postcode":"HX1 2TE",
    "sg:province":"West Yorkshire",
    "sg:tags":[
        "power"
    ],
    "wof:name":"Halifax Power Tools",
    "wof:placetype":"venue"
},
  "geometry": {"coordinates":[-1.866384,53.719715],"type":"Point"}
}