{
  "type": "Feature",
  "properties": {
    "iso:country":"GB",
    "sg:address":"3 Derehams Lane, Loudwater",
    "sg:city":"High Wycombe",
    "sg:classifiers":[
        {
            "category":"Government",
            "subcategory":"Post Office",
            "type":"Public Place"
        }
    ],
    "sg:phone":"+44 1494 441479",
    "sg:postcode":"HP10 9RH",
    "sg:province":"Buckinghamshire",
    "sg:tags":[
        "fax",
        "bureau",
        "telex",
        "provider"
    ],
    "wof:name":"Loudwater Telefax Bureau",
    "wof:placetype":"venue"
},
  "geometry": {"coordinates":[-0.6978210211,51.6090011597],"type":"Point"}
}