{
  "type": "Feature",
  "properties": {
    "iso:country":"GB",
    "sg:address":"Townsend Farm, Pilton",
    "sg:city":"Shepton Mallet",
    "sg:classifiers":[
        {
            "category":"Home & Garden",
            "subcategory":"Garden Supply",
            "type":"Retail Goods"
        },
        {
            "category":"Farming",
            "subcategory":"Livestock Farm",
            "type":"Manufacturing & Wholesale Goods"
        }
    ],
    "sg:phone":"+44 1749 890528",
    "sg:postcode":"BA4 4NX",
    "sg:province":"Somerset",
    "sg:tags":[
        "bulb",
        "grower",
        "others"
    ],
    "wof:name":"Gordon Butt",
    "wof:placetype":"venue"
},
  "geometry": {"coordinates":[-2.588659,51.166908],"type":"Point"}
}