{
  "type": "Feature",
  "properties": {
    "iso:country":"GB",
    "sg:address":"85 Poole Rd",
    "sg:city":"Bournemouth",
    "sg:classifiers":[
        {
            "category":"Organizations",
            "subcategory":"Community Association",
            "type":"Services"
        }
    ],
    "sg:phone":"+44 1202 752929",
    "sg:postcode":"BH4 9BB",
    "sg:province":"Dorset",
    "sg:tags":[
        "relation",
        "public"
    ],
    "wof:name":"Redwood Communications",
    "wof:placetype":"venue"
},
  "geometry": {"coordinates":[-1.90361,50.72303],"type":"Point"}
}