{
  "type": "Feature",
  "properties": {
    "addr:full":"Trocoll Ho, Wakering Rd Barking Essex IG11 8PD",
    "addr:postcode":"ig11 8pd",
    "addr:street":"Wakering Rd",
    "iso:country":"GB",
    "sg:address":"Trocoll Ho, Wakering Rd",
    "sg:city":"Barking",
    "sg:classifiers":[
        {
            "category":"Shopping",
            "subcategory":"Computers & Home Electronics",
            "type":"Retail Goods"
        }
    ],
    "sg:postcode":"IG11 8PD",
    "sg:province":"Essex",
    "wof:name":"Computer Sales & Maintenance",
    "wof:placetype":"venue"
},
  "geometry": {"coordinates":[0.081115,51.539101],"type":"Point"}
}