{
  "type": "Feature",
  "properties": {
    "addr:full":"60 Sunset Dr, Havering Atte Bower Romford Essex RM4 1QL",
    "addr:housenumber":"60",
    "addr:postcode":"rm4 1ql",
    "addr:street":"Sunset Dr",
    "iso:country":"GB",
    "sg:address":"60 Sunset Dr, Havering Atte Bower",
    "sg:city":"Romford",
    "sg:classifiers":[
        {
            "category":"Home & Garden",
            "subcategory":"Building Materials",
            "type":"Retail Goods"
        }
    ],
    "sg:postcode":"RM4 1QL",
    "sg:province":"Essex",
    "sg:tags":[
        "fencing"
    ],
    "wof:name":"Noak Hill Fencing",
    "wof:placetype":"venue"
},
  "geometry": {"coordinates":[0.2070199996,51.6113014221],"type":"Point"}
}