{
  "type": "Feature",
  "properties": {
    "iso:country":"GB",
    "sg:address":"47, West St",
    "sg:city":"Horsham",
    "sg:classifiers":[
        {
            "category":"Real Estate",
            "subcategory":"Real Estate Agent",
            "type":"Services"
        }
    ],
    "sg:phone":"+44 1403 242666",
    "sg:postcode":"RH12 1PP",
    "sg:province":"West Sussex",
    "wof:name":"Woolwich Property Services",
    "wof:placetype":"venue"
},
  "geometry": {"coordinates":[-0.3319149911,51.0630645752],"type":"Point"}
}