{
  "type": "Feature",
  "properties": {
    "addr:full":"173 Walshaw Road Bury Lancashire BL8 1NH",
    "addr:housenumber":"173",
    "addr:postcode":"bl8 1nh",
    "addr:street":"Walshaw Road",
    "iso:country":"GB",
    "sg:address":"173 Walshaw Road",
    "sg:city":"Bury",
    "sg:classifiers":[
        {
            "category":"Building & Trades",
            "subcategory":"Construction",
            "type":"Services"
        }
    ],
    "sg:phone":"+44 161 705 1322",
    "sg:postcode":"BL8 1NH",
    "sg:province":"Lancashire",
    "sg:tags":[
        "joiner",
        "carpenter"
    ],
    "wof:name":"Alan R Leach",
    "wof:placetype":"venue"
},
  "geometry": {"coordinates":[-2.317082,53.598419],"type":"Point"}
}