{
  "type": "Feature",
  "properties": {
    "addr:full":"358 Gloucester Road, Horfield Bristol City of Bristol BS7 8TP",
    "addr:housenumber":"358",
    "addr:postcode":"bs7 8tp",
    "addr:street":"Gloucester Road",
    "iso:country":"GB",
    "sg:address":"358 Gloucester Road, Horfield",
    "sg:city":"Bristol",
    "sg:classifiers":[
        {
            "category":"Organizations",
            "subcategory":"Non-profit Organization",
            "type":"Services"
        }
    ],
    "sg:phone":"+44 117 924 7832",
    "sg:postcode":"BS7 8TP",
    "sg:province":"City of Bristol",
    "sg:tags":[
        "organisation",
        "animal",
        "welfare"
    ],
    "wof:name":"Animal Health Centre",
    "wof:placetype":"venue"
},
  "geometry": {"coordinates":[-2.5873129368,51.483291626],"type":"Point"}
}