{
  "type": "Feature",
  "properties": {
    "addr:full":"17 Church Rd Blandford Forum Dorset DT11 8UB",
    "addr:housenumber":"17",
    "addr:postcode":"dt11 8ub",
    "addr:street":"Church Rd",
    "iso:country":"GB",
    "sg:address":"17 Church Rd",
    "sg:city":"Blandford Forum",
    "sg:classifiers":[
        {
            "category":"Organizations",
            "subcategory":"Non-profit Organization",
            "type":"Services"
        }
    ],
    "sg:phone":"+44 1258 455332",
    "sg:postcode":"DT11 8UB",
    "sg:province":"Dorset",
    "sg:tags":[
        "organisation",
        "voluntary",
        "charity"
    ],
    "wof:name":"Dorset Community Action",
    "wof:placetype":"venue"
},
  "geometry": {"coordinates":[-2.1365270615,50.8838500977],"type":"Point"}
}