{
  "type": "Feature",
  "properties": {
    "addr:full":"Garden Flat, Bridge View, Ridge Road Inverurie Aberdeenshire AB51 5QT",
    "addr:postcode":"ab51 5qt",
    "addr:street":"Bridge View Ridge Road",
    "iso:country":"GB",
    "sg:address":"Garden Flat, Bridge View, Ridge Road",
    "sg:city":"Inverurie",
    "sg:classifiers":[
        {
            "category":"Retail",
            "subcategory":"Driving School",
            "type":"Services"
        }
    ],
    "sg:phone":"+44 1467 642667",
    "sg:postcode":"AB51 5QT",
    "sg:province":"Aberdeenshire",
    "wof:name":"G S A School of Motoring",
    "wof:placetype":"venue"
},
  "geometry": {"coordinates":[-2.389794,57.291119],"type":"Point"}
}