{
  "type": "Feature",
  "properties": {
    "iso:country":"GB",
    "sg:address":"113 Lower Richmond Rd",
    "sg:city":"Putney",
    "sg:classifiers":[
        {
            "category":"Bars & Pubs",
            "subcategory":"Wine Bar",
            "type":"Food & Drink"
        }
    ],
    "sg:phone":"+44 20 8785 4522",
    "sg:postcode":"SW15 1EX",
    "sg:province":"Greater London",
    "wof:name":"Hudsons Wine Bar",
    "wof:placetype":"venue"
},
  "geometry": {"coordinates":[-0.221497,51.467716],"type":"Point"}
}