{
  "type": "Feature",
  "properties": {
    "addr:full":"25 Graeme Road Enfield Greater London EN1 3UU",
    "addr:housenumber":"25",
    "addr:postcode":"en1 3uu",
    "addr:street":"Graeme Road",
    "iso:country":"GB",
    "sg:address":"25 Graeme Road",
    "sg:city":"Enfield",
    "sg:classifiers":[
        {
            "category":"Professional",
            "subcategory":"Testing Lab",
            "type":"Services"
        }
    ],
    "sg:phone":"+44 20 8366 0883",
    "sg:postcode":"EN1 3UU",
    "sg:province":"Greater London",
    "sg:tags":[
        "inspection",
        "calibration"
    ],
    "wof:name":"Southern Time Recorders",
    "wof:placetype":"venue"
},
  "geometry": {"coordinates":[-0.078305997,51.6582260132],"type":"Point"}
}