{
  "type": "Feature",
  "properties": {
    "addr:full":"21 Essex Road Stamford Cambridgeshire PE9 1LG",
    "addr:housenumber":"21",
    "addr:postcode":"pe9 1lg",
    "addr:street":"Essex Road",
    "iso:country":"GB",
    "sg:address":"21 Essex Road",
    "sg:city":"Stamford",
    "sg:classifiers":[
        {
            "category":"Building & Trades",
            "subcategory":"Cleaning & Sanitation",
            "type":"Services"
        }
    ],
    "sg:postcode":"PE9 1LG",
    "sg:province":"Cambridgeshire",
    "sg:tags":[
        "cleaner",
        "window"
    ],
    "wof:name":"A A WINDOW CLEANING SERVICES",
    "wof:placetype":"venue"
},
  "geometry": {"coordinates":[-0.4853700101,52.6571960449],"type":"Point"}
}