{
  "type": "Feature",
  "properties": {
    "addr:full":"20 Argyle Place Edinburgh City of Edinburgh EH9 1JJ",
    "addr:housenumber":"20",
    "addr:postcode":"eh9 1jj",
    "addr:street":"Argyle Place Edinburgh",
    "iso:country":"GB",
    "sg:address":"20 Argyle Place",
    "sg:city":"Edinburgh",
    "sg:classifiers":[
        {
            "category":"Food & Beverages",
            "subcategory":"Specialty",
            "type":"Retail Goods"
        }
    ],
    "sg:phone":"+44 131 228 8840",
    "sg:postcode":"EH9 1JJ",
    "sg:province":"City of Edinburgh",
    "sg:tags":[
        "organic"
    ],
    "wof:name":"The New Leaf",
    "wof:placetype":"venue"
},
  "geometry": {"coordinates":[-3.191646,55.938381],"type":"Point"}
}