{
  "type": "Feature",
  "properties": {
    "addr:full":"High Beech, The Cut Worthing West Sussex BN14 0TP",
    "addr:postcode":"bn14 0tp",
    "addr:street":"The Cut",
    "iso:country":"GB",
    "sg:address":"High Beech, The Cut",
    "sg:city":"Worthing",
    "sg:classifiers":[
        {
            "category":"Autos & Motor Vehicles",
            "subcategory":"Automobile Sales",
            "type":"Retail Goods"
        }
    ],
    "sg:postcode":"BN14 0TP",
    "sg:province":"West Sussex",
    "sg:tags":[
        "car"
    ],
    "wof:name":"D R S Car Sales",
    "wof:placetype":"venue"
},
  "geometry": {"coordinates":[-0.4084669948,50.8638153076],"type":"Point"}
}