{
  "type": "Feature",
  "properties": {
    "addr:full":"22 Main St York North Yorkshire YO1 4PH",
    "addr:housenumber":"22",
    "addr:postcode":"yo1 4ph",
    "addr:street":"Main St",
    "iso:country":"GB",
    "sg:address":"22 Main St",
    "sg:city":"York",
    "sg:classifiers":[
        {
            "category":"Shopping",
            "subcategory":"Department Store",
            "type":"Retail Goods"
        }
    ],
    "sg:phone":"+44 1904 634909",
    "sg:postcode":"YO1 4PH",
    "sg:province":"North Yorkshire",
    "wof:name":"Whitaker's Mini Market",
    "wof:placetype":"venue"
},
  "geometry": {"coordinates":[-1.04415,53.877495],"type":"Point"}
}