{
  "type": "Feature",
  "properties": {
    "addr:full":"Green Lane, Orleton Ludlow Herefordshire SY8 4JE",
    "addr:postcode":"sy8 4je",
    "addr:street":"Green Lane",
    "iso:country":"GB",
    "sg:address":"Green Lane, Orleton",
    "sg:city":"Ludlow",
    "sg:classifiers":[
        {
            "category":"Recreation",
            "subcategory":"Campground",
            "type":"Entertainment"
        }
    ],
    "sg:phone":"+44 1584 831617",
    "sg:postcode":"SY8 4JE",
    "sg:province":"Herefordshire",
    "sg:tags":[
        "caravan",
        "park"
    ],
    "wof:name":"Gary & Debbie Williams",
    "wof:placetype":"venue"
},
  "geometry": {"coordinates":[-2.7541890144,52.301071167],"type":"Point"}
}