{
  "type": "Feature",
  "properties": {
    "addr:full":"Surrey St Glossop Derbyshire SK13 7AJ",
    "addr:postcode":"sk13 7aj",
    "addr:street":"Surrey St",
    "iso:country":"GB",
    "sg:address":"Surrey St",
    "sg:city":"Glossop",
    "sg:classifiers":[
        {
            "category":"Home & Garden",
            "subcategory":"Building Materials",
            "type":"Retail Goods"
        }
    ],
    "sg:postcode":"SK13 7AJ",
    "sg:province":"Derbyshire",
    "sg:tags":[
        "insulation",
        "installers"
    ],
    "wof:name":"Pur Systems Ltd",
    "wof:placetype":"venue"
},
  "geometry": {"coordinates":[-1.957435,53.445919],"type":"Point"}
}