{
  "type": "Feature",
  "properties": {
    "addr:full":"529a Burnley Road East Rossendale Lancashire BB4 9LQ",
    "addr:housenumber":"529a",
    "addr:postcode":"bb4 9lq",
    "addr:street":"Burnley Road East",
    "iso:country":"GB",
    "sg:address":"529a Burnley Road East",
    "sg:city":"Rossendale",
    "sg:classifiers":[
        {
            "category":"Retail",
            "subcategory":"Auto Repair",
            "type":"Services"
        }
    ],
    "sg:phone":"+44 1706 211100",
    "sg:postcode":"BB4 9LQ",
    "sg:province":"Lancashire",
    "sg:tags":[
        "modification",
        "garage"
    ],
    "wof:name":"The Garage",
    "wof:placetype":"venue"
},
  "geometry": {"coordinates":[-2.2501749992,53.7097358704],"type":"Point"}
}