{
  "type": "Feature",
  "properties": {
    "addr:full":"52 Winter Hey Lane, Horwich Bolton Lancashire BL6 7NU",
    "addr:housenumber":"52",
    "addr:postcode":"bl6 7nu",
    "addr:street":"Winter Hey Lane",
    "iso:country":"GB",
    "sg:address":"52 Winter Hey Lane, Horwich",
    "sg:city":"Bolton",
    "sg:classifiers":[
        {
            "category":"Government",
            "subcategory":"Post Office",
            "type":"Public Place"
        }
    ],
    "sg:phone":"+44 1204 697884",
    "sg:postcode":"BL6 7NU",
    "sg:province":"Lancashire",
    "wof:name":"Winter Hey Post Office",
    "wof:placetype":"venue"
},
  "geometry": {"coordinates":[-2.547832,53.598824],"type":"Point"}
}