{
  "type": "Feature",
  "properties": {
    "iso:country":"GB",
    "sg:address":"3 Ormidale Place",
    "sg:city":"Dingwall",
    "sg:classifiers":[
        {
            "category":"Home & Garden",
            "subcategory":"Kitchen Supply",
            "type":"Retail Goods"
        }
    ],
    "sg:postcode":"IV15 9RU",
    "sg:province":"Highland",
    "sg:tags":[
        "glassware",
        "china"
    ],
    "wof:name":"China Grove",
    "wof:placetype":"venue"
},
  "geometry": {"coordinates":[-4.4314479828,57.5961799622],"type":"Point"}
}