{
  "type": "Feature",
  "properties": {
    "addr:full":"Old Farm, Main Street, Sawdon Scarborough North Yorkshire YO13 9DY",
    "addr:postcode":"yo13 9dy",
    "addr:street":"Main Street",
    "iso:country":"GB",
    "sg:address":"Old Farm, Main Street, Sawdon",
    "sg:city":"Scarborough",
    "sg:classifiers":[
        {
            "category":"Home & Garden",
            "subcategory":"Garden Supply",
            "type":"Retail Goods"
        },
        {
            "category":"Farming",
            "subcategory":"Farm",
            "type":"Manufacturing & Wholesale Goods"
        }
    ],
    "sg:postcode":"YO13 9DY",
    "sg:province":"North Yorkshire",
    "sg:tags":[
        "mixed",
        "bulb",
        "crop",
        "grower"
    ],
    "wof:name":"R & M E Temple",
    "wof:placetype":"venue"
},
  "geometry": {"coordinates":[-0.5584179759,54.2525367737],"type":"Point"}
}