{
  "type": "Feature",
  "properties": {
    "iso:country":"GB",
    "sg:address":"14 Bronzegarth, Weelsby Meadows",
    "sg:city":"Grimsby",
    "sg:classifiers":[
        {
            "category":"Organizations",
            "subcategory":"Non-profit Organization",
            "type":"Services"
        }
    ],
    "sg:phone":"+44 1472 602163",
    "sg:postcode":"DN32 8QU",
    "sg:province":"Lincolnshire",
    "sg:tags":[
        "alarm",
        "system"
    ],
    "wof:name":"Alpha Security Systems",
    "wof:placetype":"venue"
},
  "geometry": {"coordinates":[-0.060499,53.555256],"type":"Point"}
}