{
  "type": "Feature",
  "properties": {
    "addr:full":"18 Bannels Avenue Derby Derbyshire DE23 2GG",
    "addr:housenumber":"18",
    "addr:postcode":"de23 2gg",
    "addr:street":"Bannels Avenue",
    "iso:country":"GB",
    "sg:address":"18 Bannels Avenue",
    "sg:city":"Derby",
    "sg:classifiers":[
        {
            "category":"Building & Trades",
            "subcategory":"Plumbing",
            "type":"Services"
        }
    ],
    "sg:postcode":"DE23 2GG",
    "sg:province":"Derbyshire",
    "sg:tags":[
        "heating"
    ],
    "wof:name":"All Gas & Electrical Services",
    "wof:placetype":"venue"
},
  "geometry": {"coordinates":[-1.511224,52.894119],"type":"Point"}
}