{
  "type": "Feature",
  "properties": {
    "iso:country":"GB",
    "sg:address":"2 Pamber Heath Road, Pamber Heath",
    "sg:city":"Tadley",
    "sg:classifiers":[
        {
            "category":"Personal",
            "subcategory":"Beauty Salon",
            "type":"Services"
        }
    ],
    "sg:phone":"+44 118 970 0563",
    "sg:postcode":"RG26 3TH",
    "sg:province":"Berkshire",
    "sg:tags":[
        "lady",
        "hairdresser"
    ],
    "wof:name":"The Hair Shack",
    "wof:placetype":"venue"
},
  "geometry": {"coordinates":[-1.127417,51.351196],"type":"Point"}
}