{
  "type": "Feature",
  "properties": {
    "iso:country":"GB",
    "sg:address":"41bury New Road, Preswich",
    "sg:city":"Manchester",
    "sg:classifiers":[
        {
            "category":"Communications",
            "type":"Services"
        }
    ],
    "sg:phone":"+44 161 773 7711",
    "sg:postcode":"M25 9JY",
    "sg:province":"Greater Manchester",
    "sg:tags":[
        "audio-visual"
    ],
    "wof:name":"Edric Audio Visual Ltd.",
    "wof:placetype":"venue"
},
  "geometry": {"coordinates":[-2.272209,53.519619],"type":"Point"}
}