{
  "type": "Feature",
  "properties": {
    "addr:full":"Unit 43, Highfield Industrial Estate Chorley Lancashire PR7 1QD",
    "addr:housenumber":"unit 43;estate",
    "addr:postcode":"pr7 1qd",
    "addr:street":"Highfield Industrial",
    "iso:country":"GB",
    "sg:address":"Unit 43, Highfield Industrial Estate",
    "sg:city":"Chorley",
    "sg:classifiers":[
        {
            "category":"Building & Trades",
            "subcategory":"Plumbing",
            "type":"Services"
        }
    ],
    "sg:phone":"+44 1257 269631",
    "sg:postcode":"PR7 1QD",
    "sg:province":"Lancashire",
    "sg:tags":[
        "merchant",
        "plumbers'"
    ],
    "wof:name":"Mayalls Plumbing & Decorating Centre",
    "wof:placetype":"venue"
},
  "geometry": {"coordinates":[-2.6558489799,53.6502189636],"type":"Point"}
}