{
  "type": "Feature",
  "properties": {
    "addr:full":"2 Quex Road London Greater London NW6 4PH",
    "addr:housenumber":"2",
    "addr:postcode":"nw6 4ph",
    "addr:street":"Quex Road",
    "iso:country":"GB",
    "sg:address":"2 Quex Road",
    "sg:city":"London",
    "sg:classifiers":[
        {
            "category":"Food & Beverages",
            "subcategory":"Meat & Fish",
            "type":"Retail Goods"
        }
    ],
    "sg:phone":"+44 20 7372 2731",
    "sg:postcode":"NW6 4PH",
    "sg:province":"Greater London",
    "sg:tags":[
        "butcher"
    ],
    "wof:name":"H R Halal Meat",
    "wof:placetype":"venue"
},
  "geometry": {"coordinates":[-0.1946540028,51.5399017334],"type":"Point"}
}