{
  "type": "Feature",
  "properties": {
    "addr:full":"New Street Walsall West Midlands WS1 3DF",
    "addr:postcode":"ws1 3df",
    "addr:street":"New Street",
    "iso:country":"GB",
    "sg:address":"New Street",
    "sg:city":"Walsall",
    "sg:classifiers":[
        {
            "category":"Shopping",
            "subcategory":"Bicycles & Sporting Goods",
            "type":"Retail Goods"
        }
    ],
    "sg:phone":"+44 1922 659080",
    "sg:postcode":"WS1 3DF",
    "sg:province":"West Midlands",
    "sg:tags":[
        "riding",
        "saddlery",
        "wear"
    ],
    "wof:name":"County Saddlery Ltd.",
    "wof:placetype":"venue"
},
  "geometry": {"coordinates":[-1.978824,52.581375],"type":"Point"}
}