{
  "type": "Feature",
  "properties": {
    "addr:full":"45 Church Road, Southbourne Bournemouth Dorset BH6 4BB",
    "addr:housenumber":"45",
    "addr:postcode":"bh6 4bb",
    "addr:street":"Church Road",
    "iso:country":"GB",
    "sg:address":"45 Church Road, Southbourne",
    "sg:city":"Bournemouth",
    "sg:classifiers":[
        {
            "category":"Travel",
            "subcategory":"Hotels & Motels",
            "type":"Entertainment"
        }
    ],
    "sg:phone":"+44 1202 428868",
    "sg:postcode":"BH6 4BB",
    "sg:province":"Dorset",
    "wof:name":"White Topps Hotel",
    "wof:placetype":"venue"
},
  "geometry": {"coordinates":[-1.7890720367,50.7208786011],"type":"Point"}
}