{
  "type": "Feature",
  "properties": {
    "addr:full":"5 Trewen Llandinam Powys SY17 5BU",
    "addr:housenumber":"5",
    "addr:postcode":"sy17 5bu",
    "addr:street":"Trewen Llandinam",
    "iso:country":"GB",
    "sg:address":"5 Trewen",
    "sg:city":"Llandinam",
    "sg:classifiers":[
        {
            "category":"Professional",
            "subcategory":"Computer Services",
            "type":"Services"
        }
    ],
    "sg:phone":"+44 1686 688915",
    "sg:postcode":"SY17 5BU",
    "sg:province":"Powys",
    "sg:tags":[
        "system",
        "software"
    ],
    "wof:name":"Kevin P Edwards",
    "wof:placetype":"venue"
},
  "geometry": {"coordinates":[-3.4772670269,52.5154876709],"type":"Point"}
}