{
  "type": "Feature",
  "properties": {
    "iso:country":"GB",
    "sg:address":"Quinton Service Station, Quinton Road",
    "sg:city":"Coventry",
    "sg:classifiers":[
        {
            "category":"Retail",
            "subcategory":"Auto Rental",
            "type":"Services"
        }
    ],
    "sg:phone":"+44 24 7650 3748",
    "sg:postcode":"CV3 5FD",
    "sg:province":"Warwickshire",
    "sg:tags":[
        "truck",
        "hire",
        "van"
    ],
    "wof:name":"Quinton Self Drive",
    "wof:placetype":"venue"
},
  "geometry": {"coordinates":[-1.50775,52.395088],"type":"Point"}
}