{
  "type": "Feature",
  "properties": {
    "iso:country":"GB",
    "sg:address":"268 Leagrave Rd",
    "sg:city":"Luton",
    "sg:classifiers":[
        {
            "category":"Shopping",
            "subcategory":"Florist",
            "type":"Retail Goods"
        }
    ],
    "sg:phone":"+44 1582 493003",
    "sg:postcode":"LU3 1RB",
    "sg:province":"Bedfordshire",
    "wof:name":"Fox's Of Luton",
    "wof:placetype":"venue"
},
  "geometry": {"coordinates":[-0.434638,51.892296],"type":"Point"}
}