{
  "type": "Feature",
  "properties": {
    "iso:country":"GB",
    "sg:address":"59 High Street",
    "sg:city":"Colchester",
    "sg:classifiers":[
        {
            "category":"Restaurant",
            "type":"Food & Drink"
        }
    ],
    "sg:phone":"+44 1206 541839",
    "sg:postcode":"CO1 1DH",
    "sg:province":"Essex",
    "wof:name":"Cafe Rouge Ltd.",
    "wof:placetype":"venue"
},
  "geometry": {"coordinates":[0.9018309712,51.8896064758],"type":"Point"}
}