{
  "type": "Feature",
  "properties": {
    "addr:full":"3 Ailsa Road, Kyle Estate Irvine North Ayrshire KA12 8LL",
    "addr:housenumber":"3",
    "addr:postcode":"ka12 8ll",
    "addr:street":"Ailsa Road;Estate",
    "iso:country":"GB",
    "sg:address":"3 Ailsa Road, Kyle Estate",
    "sg:city":"Irvine",
    "sg:classifiers":[
        {
            "category":"Professional",
            "subcategory":"Printing & Photocopies",
            "type":"Services"
        }
    ],
    "sg:phone":"+44 1294 311100",
    "sg:postcode":"KA12 8LL",
    "sg:province":"North Ayrshire",
    "sg:tags":[
        "printer"
    ],
    "wof:name":"A M Fasprint Services (Irvine) Ltd.",
    "wof:placetype":"venue"
},
  "geometry": {"coordinates":[-4.673259,55.601974],"type":"Point"}
}