{
  "type": "Feature",
  "properties": {
    "addr:full":"14-18 Gates Green Road West Wickham Kent BR4 9JW",
    "addr:housenumber":"14-18",
    "addr:postcode":"br4 9jw",
    "addr:street":"Gates Green Road",
    "iso:country":"GB",
    "sg:address":"14-18 Gates Green Road",
    "sg:city":"West Wickham",
    "sg:classifiers":[
        {
            "category":"Government",
            "subcategory":"City Hall",
            "type":"Public Place"
        }
    ],
    "sg:phone":"+44 20 8462 5208",
    "sg:postcode":"BR4 9JW",
    "sg:province":"Kent",
    "wof:name":"The Assembly Rooms",
    "wof:placetype":"venue"
},
  "geometry": {"coordinates":[0.0046529998,51.3690032959],"type":"Point"}
}