{
  "type": "Feature",
  "properties": {
    "iso:country":"GB",
    "sg:address":"Dental Surgery, 25 Tetbury St",
    "sg:city":"Stroud",
    "sg:classifiers":[
        {
            "category":"Health Services",
            "subcategory":"Dentist",
            "type":"Services"
        }
    ],
    "sg:phone":"+44 1453 883867",
    "sg:postcode":"GL6 9JH",
    "sg:province":"Gloucestershire",
    "wof:name":"G Lloyd",
    "wof:placetype":"venue"
},
  "geometry": {"coordinates":[-2.18472,51.703918],"type":"Point"}
}