{
  "type": "Feature",
  "properties": {
    "iso:country":"GB",
    "sg:address":"71 Queensberry Street",
    "sg:city":"Dumfries",
    "sg:classifiers":[
        {
            "category":"Professional",
            "type":"Services"
        },
        {
            "category":"Professional",
            "subcategory":"Art Services",
            "type":"Services"
        }
    ],
    "sg:phone":"+44 1387 252655",
    "sg:postcode":"DG1 1BH",
    "sg:province":"Dumfries and Galloway",
    "sg:tags":[
        "interior",
        "furnishers",
        "designer"
    ],
    "wof:name":"David Cole Interior Designs",
    "wof:placetype":"venue"
},
  "geometry": {"coordinates":[-3.6107881069,55.0693740845],"type":"Point"}
}