{
  "type": "Feature",
  "properties": {
    "iso:country":"GB",
    "sg:address":"2 Bankside, 128 Middleton Rd",
    "sg:city":"Bognor Regis",
    "sg:classifiers":[
        {
            "category":"Food & Beverages",
            "subcategory":"Fruits & Vegetables",
            "type":"Retail Goods"
        }
    ],
    "sg:postcode":"PO22 6BJ",
    "sg:province":"West Sussex",
    "sg:tags":[
        "greengrocer"
    ],
    "wof:name":"Middleton Green Grocery",
    "wof:placetype":"venue"
},
  "geometry": {"coordinates":[-0.63731,50.79388],"type":"Point"}
}