{
  "type": "Feature",
  "properties": {
    "addr:full":"79 Churchtown, Gwinear Hayle Cornwall TR27 5LH",
    "addr:housenumber":"79",
    "addr:postcode":"tr27 5lh",
    "addr:street":"Churchtown Gwinear",
    "iso:country":"GB",
    "sg:address":"79 Churchtown, Gwinear",
    "sg:city":"Hayle",
    "sg:classifiers":[
        {
            "category":"Farming",
            "subcategory":"Farm",
            "type":"Manufacturing & Wholesale Goods"
        }
    ],
    "sg:phone":"+44 1736 850228",
    "sg:postcode":"TR27 5LH",
    "sg:province":"Cornwall",
    "sg:tags":[
        "mixed",
        "crop"
    ],
    "wof:name":"T H E Laity",
    "wof:placetype":"venue"
},
  "geometry": {"coordinates":[-5.4147691727,50.1949882507],"type":"Point"}
}