{
  "type": "Feature",
  "properties": {
    "addr:full":"Woods Farm, Rimington Lane, Rimington Clitheroe Lancashire BB7 4DP",
    "addr:postcode":"bb7 4dp",
    "addr:street":"Rimington Lane",
    "iso:country":"GB",
    "sg:address":"Woods Farm, Rimington Lane, Rimington",
    "sg:city":"Clitheroe",
    "sg:classifiers":[
        {
            "category":"Farming",
            "subcategory":"Dairy Farm",
            "type":"Manufacturing & Wholesale Goods"
        }
    ],
    "sg:phone":"+44 1200 445359",
    "sg:postcode":"BB7 4DP",
    "sg:province":"Lancashire",
    "sg:tags":[
        "farmer"
    ],
    "wof:name":"J N Lund",
    "wof:placetype":"venue"
},
  "geometry": {"coordinates":[-2.2866580486,53.908416748],"type":"Point"}
}