{
  "type": "Feature",
  "properties": {
    "addr:full":"71-73 Manchester Rd Altrincham Cheshire WA14 4RJ",
    "addr:housenumber":"71-73",
    "addr:postcode":"wa14 4rj",
    "addr:street":"Manchester Rd",
    "iso:country":"GB",
    "sg:address":"71-73 Manchester Rd",
    "sg:city":"Altrincham",
    "sg:classifiers":[
        {
            "category":"Education",
            "subcategory":"Dance Studio",
            "type":"Public Place"
        }
    ],
    "sg:phone":"+44 161 928 7691",
    "sg:postcode":"WA14 4RJ",
    "sg:province":"Cheshire",
    "sg:tags":[
        "school",
        "dancing"
    ],
    "wof:name":"Beesons Of Stretford",
    "wof:placetype":"venue"
},
  "geometry": {"coordinates":[-2.352347,53.396526],"type":"Point"}
}