{
  "type": "Feature",
  "properties": {
    "addr:full":"Wheatfield Road Newcastle-upon-tyne Tyne and Wear NE5 5HQ",
    "addr:postcode":"ne5 5hq",
    "addr:street":"Wheatfield Road",
    "iso:country":"GB",
    "sg:address":"Wheatfield Road",
    "sg:city":"Newcastle-upon-tyne",
    "sg:classifiers":[
        {
            "category":"Health Services",
            "subcategory":"Nursing And Care Facility",
            "type":"Services"
        }
    ],
    "sg:phone":"+44 191 214 5104",
    "sg:postcode":"NE5 5HQ",
    "sg:province":"Tyne and Wear",
    "sg:tags":[
        "home"
    ],
    "wof:name":"Wheatfield Court Nursing Home",
    "wof:placetype":"venue"
},
  "geometry": {"coordinates":[-1.6938209534,54.9986839294],"type":"Point"}
}