{
  "type": "Feature",
  "properties": {
    "iso:country":"GB",
    "sg:address":"18 High Street, Wickham Market",
    "sg:city":"Woodbridge",
    "sg:classifiers":[
        {
            "category":"Autos & Motor Vehicles",
            "subcategory":"Automobile Sales",
            "type":"Retail Goods"
        }
    ],
    "sg:phone":"+44 1728 746161",
    "sg:postcode":"IP13 0HE",
    "sg:province":"Suffolk",
    "sg:tags":[
        "car"
    ],
    "wof:name":"Marshall Motor Group Ltd.",
    "wof:placetype":"venue"
},
  "geometry": {"coordinates":[1.3631379604,52.1508255005],"type":"Point"}
}