{
  "type": "Feature",
  "properties": {
    "iso:country":"GB",
    "sg:address":"The Sidings, Warwick Road",
    "sg:city":"Stratford-upon-avon",
    "sg:classifiers":[
        {
            "category":"Professional",
            "subcategory":"Engineering",
            "type":"Services"
        }
    ],
    "sg:postcode":"CV37 7PN",
    "sg:province":"Warwickshire",
    "sg:tags":[
        "agricultural",
        "engineer"
    ],
    "wof:name":"T Spencer Machinery",
    "wof:placetype":"venue"
},
  "geometry": {"coordinates":[-1.7072689533,52.1941337585],"type":"Point"}
}