{
  "type": "Feature",
  "properties": {
    "addr:full":"25 Parkside Way Harrow Greater London HA2 6DE",
    "addr:housenumber":"25",
    "addr:postcode":"ha2 6de",
    "addr:street":"Parkside Way",
    "iso:country":"GB",
    "sg:address":"25 Parkside Way",
    "sg:city":"Harrow",
    "sg:classifiers":[
        {
            "category":"Freight",
            "type":"Transportation"
        }
    ],
    "sg:phone":"+44 20 8427 7431",
    "sg:postcode":"HA2 6DE",
    "sg:province":"Greater London",
    "sg:tags":[
        "forwarders"
    ],
    "wof:name":"Pentagold Ltd",
    "wof:placetype":"venue"
},
  "geometry": {"coordinates":[-0.3566269875,51.5894622803],"type":"Point"}
}