{
  "type": "Feature",
  "properties": {
    "iso:country":"GB",
    "sg:address":"Borsdane Avenue, Hindley",
    "sg:city":"Wigan",
    "sg:classifiers":[
        {
            "category":"Sports & Exercise",
            "subcategory":"Swimming Pool",
            "type":"Entertainment"
        }
    ],
    "sg:phone":"+44 1942 255401",
    "sg:postcode":"WN2 3QN",
    "sg:province":"Lancashire",
    "wof:name":"Hindley Swimming Pool",
    "wof:placetype":"venue"
},
  "geometry": {"coordinates":[-2.5649340153,53.5342521667],"type":"Point"}
}