{
  "type": "Feature",
  "properties": {
    "iso:country":"GB",
    "sg:address":"49 Canal Street",
    "sg:city":"Derby",
    "sg:classifiers":[
        {
            "category":"Professional",
            "subcategory":"Engineering",
            "type":"Services"
        }
    ],
    "sg:phone":"+44 1332 285000",
    "sg:postcode":"DE1 2RJ",
    "sg:province":"Derbyshire",
    "sg:tags":[
        "consultant",
        "structural"
    ],
    "wof:name":"Rodgers Leask Ltd",
    "wof:placetype":"venue"
},
  "geometry": {"coordinates":[-1.4657390118,52.9178619385],"type":"Point"}
}