{
  "type": "Feature",
  "properties": {
    "addr:full":"Hart St Maidstone Kent ME16 8RA",
    "addr:postcode":"me16 8ra",
    "addr:street":"Hart St",
    "iso:country":"GB",
    "sg:address":"Hart St",
    "sg:city":"Maidstone",
    "sg:classifiers":[
        {
            "category":"Autos & Motor Vehicles",
            "subcategory":"Automobile Sales",
            "type":"Retail Goods"
        }
    ],
    "sg:phone":"+44 1622 606500",
    "sg:postcode":"ME16 8RA",
    "sg:province":"Kent",
    "sg:tags":[
        "commercial"
    ],
    "wof:name":"Whitehouse Honda",
    "wof:placetype":"venue"
},
  "geometry": {"coordinates":[0.5171769857,51.2696495056],"type":"Point"}
}