{
  "type": "Feature",
  "properties": {
    "addr:full":"Holly Bank House, 17 Scalpcliffe Close Burton-on-trent Derbyshire DE15 9AX",
    "addr:housenumber":"17",
    "addr:postcode":"de15 9ax",
    "addr:street":"Scalpcliffe Close",
    "iso:country":"GB",
    "sg:address":"Holly Bank House, 17 Scalpcliffe Close",
    "sg:city":"Burton-on-trent",
    "sg:classifiers":[
        {
            "category":"Autos & Motor Vehicles",
            "subcategory":"Motorcycle Sales",
            "type":"Retail Goods"
        }
    ],
    "sg:phone":"+44 1283 511277",
    "sg:postcode":"DE15 9AX",
    "sg:province":"Derbyshire",
    "sg:tags":[
        "chauffeur",
        "driven",
        "car"
    ],
    "wof:name":"Rolleston Private Hire & Chauffeur Service",
    "wof:placetype":"venue"
},
  "geometry": {"coordinates":[-1.6195759773,52.8037757874],"type":"Point"}
}