{
  "type": "Feature",
  "properties": {
    "addr:full":"64 Reddish Road Stockport Cheshire SK5 7QU",
    "addr:housenumber":"64",
    "addr:postcode":"sk5 7qu",
    "addr:street":"Reddish Road",
    "iso:country":"GB",
    "sg:address":"64 Reddish Road",
    "sg:city":"Stockport",
    "sg:classifiers":[
        {
            "category":"Fast Food",
            "type":"Food & Drink"
        }
    ],
    "sg:phone":"+44 161 429 9162",
    "sg:postcode":"SK5 7QU",
    "sg:province":"Cheshire",
    "sg:tags":[
        "away",
        "take"
    ],
    "wof:name":"Reddish Friery",
    "wof:placetype":"venue"
},
  "geometry": {"coordinates":[-2.1566650867,53.4222984314],"type":"Point"}
}