{
  "type": "Feature",
  "properties": {
    "addr:full":"Burwash Manor Farm, School Lane, Barton Cambridge Cambridgeshire CB3 7BD",
    "addr:postcode":"cb3 7bd",
    "addr:street":"School Lane",
    "iso:country":"GB",
    "sg:address":"Burwash Manor Farm, School Lane, Barton",
    "sg:city":"Cambridge",
    "sg:classifiers":[
        {
            "category":"Shopping",
            "subcategory":"Hobbies, Toys, & Games",
            "type":"Retail Goods"
        }
    ],
    "sg:phone":"+44 1223 264674",
    "sg:postcode":"CB3 7BD",
    "sg:province":"Cambridgeshire",
    "sg:tags":[
        "shop",
        "toy"
    ],
    "wof:name":"The Rocking Horse Country Toy Shop",
    "wof:placetype":"venue"
},
  "geometry": {"coordinates":[0.065409,52.180141],"type":"Point"}
}