{
  "type": "Feature",
  "properties": {
    "iso:country":"GB",
    "sg:address":"Lower Venn, Sutton St Nicholas",
    "sg:city":"Hereford",
    "sg:classifiers":[
        {
            "category":"Farming",
            "subcategory":"Livestock Farm",
            "type":"Manufacturing & Wholesale Goods"
        }
    ],
    "sg:phone":"+44 1568 797270",
    "sg:postcode":"HR1 3HL",
    "sg:province":"Herefordshire",
    "sg:tags":[
        "others"
    ],
    "wof:name":"J R Badham & Son",
    "wof:placetype":"venue"
},
  "geometry": {"coordinates":[-2.66946,52.13858],"type":"Point"}
}