{
  "type": "Feature",
  "properties": {
    "iso:country":"GB",
    "sg:address":"1 Occupation Lane",
    "sg:city":"Pudsey",
    "sg:classifiers":[
        {
            "category":"Retail",
            "subcategory":"Auto Repair",
            "type":"Services"
        }
    ],
    "sg:postcode":"LS28 8HL",
    "sg:province":"West Yorkshire",
    "sg:tags":[
        "modification",
        "garage"
    ],
    "wof:name":"Victoria Garage",
    "wof:placetype":"venue"
},
  "geometry": {"coordinates":[-1.676987052,53.7940101624],"type":"Point"}
}