{
  "type": "Feature",
  "properties": {
    "addr:full":"86-88 Leytonstone Road London Greater London E15 1TQ",
    "addr:housenumber":"86-88",
    "addr:postcode":"e15 1tq",
    "addr:street":"Leytonstone Road",
    "iso:country":"GB",
    "sg:address":"86-88 Leytonstone Road",
    "sg:city":"London",
    "sg:classifiers":[
        {
            "category":"Personal",
            "subcategory":"Beauty Salon",
            "type":"Services"
        }
    ],
    "sg:postcode":"E15 1TQ",
    "sg:province":"Greater London",
    "wof:name":"YASMINS NAIL & BEAUTY STUDIO",
    "wof:placetype":"venue"
},
  "geometry": {"coordinates":[0.0056,51.550781],"type":"Point"}
}