{
  "type": "Feature",
  "properties": {
    "iso:country":"GB",
    "sg:address":"7 Victoria Arcade, Union Street",
    "sg:city":"Ryde",
    "sg:classifiers":[
        {
            "category":"Cafe",
            "type":"Food & Drink"
        }
    ],
    "sg:phone":"+44 1983 566861",
    "sg:postcode":"PO33 2LQ",
    "sg:province":"Isle of Wight",
    "sg:tags":[
        "tea",
        "snack",
        "bar",
        "room"
    ],
    "wof:name":"Sameanns Cafe & Take Away",
    "wof:placetype":"venue"
},
  "geometry": {"coordinates":[-1.164791,50.728916],"type":"Point"}
}