{
  "type": "Feature",
  "properties": {
    "addr:full":"High Street, Kempton Mandeville Taunton Somerset TA11 6ED",
    "addr:postcode":"ta11 6ed",
    "addr:street":"High Street;Mandeville",
    "iso:country":"GB",
    "sg:address":"High Street, Kempton Mandeville",
    "sg:city":"Taunton",
    "sg:classifiers":[
        {
            "category":"Food & Beverages",
            "subcategory":"Groceries & Convenience Stores",
            "type":"Retail Goods"
        },
        {
            "category":"Food & Beverages",
            "subcategory":"Meat & Fish",
            "type":"Retail Goods"
        }
    ],
    "sg:phone":"+44 1458 223562",
    "sg:postcode":"TA11 6ED",
    "sg:province":"Somerset",
    "sg:tags":[
        "butcher"
    ],
    "wof:name":"Mark Curtiss",
    "wof:placetype":"venue"
},
  "geometry": {"coordinates":[-2.653219,51.076702],"type":"Point"}
}