{
  "type": "Feature",
  "properties": {
    "iso:country":"GB",
    "sg:address":"21-23 New Rd",
    "sg:city":"Chatham",
    "sg:classifiers":[
        {
            "category":"Education",
            "subcategory":"Library",
            "type":"Public Place"
        },
        {
            "category":"Retail",
            "subcategory":"Repair Shop",
            "type":"Services"
        }
    ],
    "sg:phone":"+44 1634 407885",
    "sg:postcode":"ME4 4QJ",
    "sg:province":"Kent",
    "sg:tags":[
        "reproduction",
        "upholsterer",
        "furniture"
    ],
    "wof:name":"Repro-Furniture Ltd",
    "wof:placetype":"venue"
},
  "geometry": {"coordinates":[0.524215,51.380798],"type":"Point"}
}