{
  "type": "Feature",
  "properties": {
    "addr:full":"Easton Business Centre, Felix Rd Bristol City of Bristol BS5 0HE",
    "addr:postcode":"bs5 0he",
    "addr:street":"Felix Rd",
    "iso:country":"GB",
    "sg:address":"Easton Business Centre, Felix Rd",
    "sg:city":"Bristol",
    "sg:classifiers":[
        {
            "category":"Education",
            "subcategory":"Special Training",
            "type":"Public Place"
        }
    ],
    "sg:href":"http://api.simplegeo.com/1.0/features/SG_4oaKrFkpqwOVJXz5UEiKeQ_51.478325_-2.691005@1300740015.json",
    "sg:postcode":"BS5 0HE",
    "sg:province":"City of Bristol",
    "sg:tags":[
        "product",
        "centre"
    ],
    "wof:name":"Groups in Learning",
    "wof:placetype":"venue"
},
  "geometry": {"coordinates":[-2.691005,51.478325],"type":"Point"}
}