{"geometry":{"type":"Point","coordinates":[-2.691005,51.478325]},"type":"Feature","id":102560261,"bbox":[-2.691005,51.478325,-2.691005,51.478325],"properties":{"sg:province":"City of Bristol","sg:tags":["product","centre"],"geom:longitude":-2.691005,"wof:breaches":[],"sg:href":"http://api.simplegeo.com/1.0/features/SG_4oaKrFkpqwOVJXz5UEiKeQ_51.478325_-2.691005@1300740015.json","sg:owner":"simplegeo","sg:postcode":"BS5 0HE","geom:latitude":51.478325,"sg:classifiers":[{"category":"Education","type":"Public Place","subcategory":"Special Training"}],"sg:address":"Easton Business Centre, Felix Rd","wof:hierarchy":[{"venue_id":102560261,"country_id":85633159,"neighbourhood_id":85789823,"region_id":85683793}],"geom:area":0.000000,"sg:city":"Bristol","wof:lastmodified":1438093221,"iso:country":"GB","wof:geomhash":"de0457d0e322b010b7fc762db31c31eb","wof:name":"Groups in Learning","wof:belongsto":[85633159,85789823,85683793],"src:geom":"simplegeo","wof:placetype":"venue","wof:supersedes":[],"wof:id":102560261,"wof:superseded_by":[],"wof:concordances":{"sg:id":"SG_4oaKrFkpqwOVJXz5UEiKeQ_51.478325_-2.691005@1300740015"},"wof:parent_id":85789823}}