{
  "type": "Feature",
  "properties": {
    "iso:country":"GB",
    "sg:address":"45 Sheaf St",
    "sg:city":"Daventry",
    "sg:classifiers":[
        {
            "category":"Personal",
            "subcategory":"Hair Removal",
            "type":"Services"
        }
    ],
    "sg:phone":"+44 1327 301865",
    "sg:postcode":"NN11 4AA",
    "sg:province":"Northamptonshire",
    "sg:tags":[
        "electrolysis"
    ],
    "wof:name":"Notions",
    "wof:placetype":"venue"
},
  "geometry": {"coordinates":[-1.162932992,52.2564544678],"type":"Point"}
}