{
  "type": "Feature",
  "properties": {
    "iso:country":"GB",
    "sg:address":"The Granary, 3 Peddlars Walk",
    "sg:city":"Ringwood",
    "sg:classifiers":[
        {
            "category":"Organizations",
            "subcategory":"Non-profit Organization",
            "type":"Services"
        }
    ],
    "sg:phone":"+44 1425 461303",
    "sg:postcode":"BH24 1EZ",
    "sg:province":"Dorset",
    "sg:tags":[
        "organisation",
        "voluntary",
        "charity"
    ],
    "wof:name":"British Red Cross",
    "wof:placetype":"venue"
},
  "geometry": {"coordinates":[-1.792989,50.846329],"type":"Point"}
}