{
  "type": "Feature",
  "properties": {
    "addr:full":"Mattock Lane, Ealing London Greater London W5 5EQ",
    "addr:postcode":"w5 5eq",
    "addr:street":"Mattock Lane",
    "iso:country":"GB",
    "sg:address":"Mattock Lane, Ealing",
    "sg:city":"London",
    "sg:classifiers":[
        {
            "category":"Museum",
            "subcategory":"Art Museum",
            "type":"Entertainment"
        }
    ],
    "sg:phone":"+44 20 8567 1227",
    "sg:postcode":"W5 5EQ",
    "sg:province":"Greater London",
    "sg:tags":[
        "gallery"
    ],
    "wof:name":"Pitshanger Manor & Gallery",
    "wof:placetype":"venue"
},
  "geometry": {"coordinates":[-0.306844,51.511425],"type":"Point"}
}