{
  "type": "Feature",
  "properties": {
    "iso:country":"GB",
    "sg:address":"12 Field Close",
    "sg:city":"Derby",
    "sg:classifiers":[
        {
            "category":"Building & Trades",
            "subcategory":"Construction",
            "type":"Services"
        }
    ],
    "sg:postcode":"DE72 3HJ",
    "sg:province":"Derbyshire",
    "sg:tags":[
        "roofing"
    ],
    "wof:name":"Simon Charlton",
    "wof:placetype":"venue"
},
  "geometry": {"coordinates":[-1.3787970543,52.9130554199],"type":"Point"}
}