{
  "type": "Feature",
  "properties": {
    "iso:country":"GB",
    "sg:address":"Portside 1, Merseyton Road",
    "sg:city":"Ellesmere Port",
    "sg:classifiers":[
        {
            "category":"Building & Trades",
            "subcategory":"Cleaning & Sanitation",
            "type":"Services"
        }
    ],
    "sg:phone":"+44 151 356 1222",
    "sg:postcode":"CH65 2HQ",
    "sg:province":"Cheshire",
    "sg:tags":[
        "blast"
    ],
    "wof:name":"Cleanright Environmental Services Ltd.",
    "wof:placetype":"venue"
},
  "geometry": {"coordinates":[-2.905574,53.277199],"type":"Point"}
}