{
  "type": "Feature",
  "properties": {
    "iso:country":"GB",
    "sg:address":"59 Causewayhead",
    "sg:city":"Penzance",
    "sg:classifiers":[
        {
            "category":"Shopping",
            "subcategory":"Gifts & Souvenirs",
            "type":"Retail Goods"
        }
    ],
    "sg:phone":"+44 1736 362129",
    "sg:postcode":"TR18 2SS",
    "sg:province":"Cornwall",
    "sg:tags":[
        "poster",
        "card"
    ],
    "wof:name":"Supercards",
    "wof:placetype":"venue"
},
  "geometry": {"coordinates":[-5.53836,50.119709],"type":"Point"}
}