{
  "type": "Feature",
  "properties": {
    "addr:full":"168 Greenford Road Harrow Greater London HA1 3QX",
    "addr:housenumber":"168",
    "addr:postcode":"ha1 3qx",
    "addr:street":"Greenford Road",
    "iso:country":"GB",
    "sg:address":"168 Greenford Road",
    "sg:city":"Harrow",
    "sg:classifiers":[
        {
            "category":"Professional",
            "subcategory":"Engineering",
            "type":"Services"
        }
    ],
    "sg:phone":"+44 20 8423 1104",
    "sg:postcode":"HA1 3QX",
    "sg:province":"Greater London",
    "sg:tags":[
        "contractor",
        "electrical",
        "engineer"
    ],
    "wof:name":"Pegasus Systems Ltd.",
    "wof:placetype":"venue"
},
  "geometry": {"coordinates":[-0.33564,51.556961],"type":"Point"}
}