{
  "type": "Feature",
  "properties": {
    "addr:full":"Unit 4 Stoke-on-trent Cheshire ST7 3AG",
    "addr:housenumber":"unit 4",
    "addr:postcode":"st7 3ag",
    "iso:country":"GB",
    "sg:address":"Unit 4",
    "sg:city":"Stoke-on-trent",
    "sg:classifiers":[
        {
            "category":"Retail",
            "subcategory":"Auto Repair",
            "type":"Services"
        }
    ],
    "sg:phone":"+44 1782 783800",
    "sg:postcode":"ST7 3AG",
    "sg:province":"Cheshire",
    "sg:tags":[
        "modification",
        "garage"
    ],
    "wof:name":"Lawton Hall Garage",
    "wof:placetype":"venue"
},
  "geometry": {"coordinates":[-2.254849,53.110241],"type":"Point"}
}