{
  "type": "Feature",
  "properties": {
    "addr:full":"6 Wetheral Close, Hindley Grn, Hindley Industrial Estate Wigan Lancashire WN2 4HS",
    "addr:housenumber":"6",
    "addr:postcode":"wn2 4hs",
    "addr:street":"Wetheral Close;Industrial Estate",
    "iso:country":"GB",
    "sg:address":"6 Wetheral Close, Hindley Grn, Hindley Industrial Estate",
    "sg:city":"Wigan",
    "sg:classifiers":[
        {
            "category":"Professional",
            "subcategory":"Engineering",
            "type":"Services"
        }
    ],
    "sg:phone":"+44 1942 521991",
    "sg:postcode":"WN2 4HS",
    "sg:province":"Lancashire",
    "wof:name":"Esca Engineering Ltd.",
    "wof:placetype":"venue"
},
  "geometry": {"coordinates":[-2.5431339741,53.5268554688],"type":"Point"}
}