{
  "type": "Feature",
  "properties": {
    "addr:full":"Higher Checkridge Farm, Hawkchurch Axminster Devon EX13 5UD",
    "addr:housenumber":"hawkchurch",
    "addr:postcode":"ex13 5ud",
    "iso:country":"GB",
    "sg:address":"Higher Checkridge Farm, Hawkchurch",
    "sg:city":"Axminster",
    "sg:classifiers":[
        {
            "category":"Freight",
            "type":"Transportation"
        }
    ],
    "sg:phone":"+44 1297 678260",
    "sg:postcode":"EX13 5UD",
    "sg:province":"Devon",
    "sg:tags":[
        "haulage",
        "road"
    ],
    "wof:name":"Fredrick George Marchant",
    "wof:placetype":"venue"
},
  "geometry": {"coordinates":[-3.0005619526,50.7812767029],"type":"Point"}
}