{
  "type": "Feature",
  "properties": {
    "addr:full":"636 London Rd Westcliff On Sea Essex SS0 9HW",
    "addr:housenumber":"636",
    "addr:postcode":"ss0 9hw",
    "addr:street":"London Rd",
    "iso:country":"GB",
    "sg:address":"636 London Rd",
    "sg:city":"Westcliff On Sea",
    "sg:classifiers":[
        {
            "category":"Autos & Motor Vehicles",
            "subcategory":"Motorcycle Sales",
            "type":"Retail Goods"
        }
    ],
    "sg:phone":"+44 1702 352859",
    "sg:postcode":"SS0 9HW",
    "sg:province":"Essex",
    "wof:name":"The Scooter Emporium",
    "wof:placetype":"venue"
},
  "geometry": {"coordinates":[0.6830430031,51.5455245972],"type":"Point"}
}