{
  "type": "Feature",
  "properties": {
    "addr:full":"36 Main Street, Ratho Newbridge City of Edinburgh EH28 8RB",
    "addr:housenumber":"36",
    "addr:postcode":"eh28 8rb",
    "addr:street":"Main Street",
    "iso:country":"GB",
    "sg:address":"36 Main Street, Ratho",
    "sg:city":"Newbridge",
    "sg:classifiers":[
        {
            "category":"Professional",
            "subcategory":"Computer Services",
            "type":"Services"
        }
    ],
    "sg:phone":"+44 131 333 1547",
    "sg:postcode":"EH28 8RB",
    "sg:province":"City of Edinburgh",
    "sg:tags":[
        "system",
        "software"
    ],
    "wof:name":"McLeod 9 Ltd.",
    "wof:placetype":"venue"
},
  "geometry": {"coordinates":[-3.379134,55.922096],"type":"Point"}
}