{
  "type": "Feature",
  "properties": {
    "iso:country":"GB",
    "sg:address":"104 Bolton Rd",
    "sg:city":"Rochdale",
    "sg:classifiers":[
        {
            "category":"Shopping",
            "subcategory":"News",
            "type":"Retail Goods"
        }
    ],
    "sg:phone":"+44 1706 632918",
    "sg:postcode":"OL11 4QX",
    "sg:province":"Lancashire",
    "sg:tags":[
        "newsagent"
    ],
    "wof:name":"Pullans",
    "wof:placetype":"venue"
},
  "geometry": {"coordinates":[-2.1809389591,53.6022987366],"type":"Point"}
}