{
  "type": "Feature",
  "properties": {
    "addr:full":"64 Lozells Road Birmingham West Midlands B19 2TD",
    "addr:housenumber":"64",
    "addr:postcode":"b19 2td",
    "addr:street":"Lozells Road",
    "iso:country":"GB",
    "sg:address":"64 Lozells Road",
    "sg:city":"Birmingham",
    "sg:classifiers":[
        {
            "category":"Cafe",
            "type":"Food & Drink"
        }
    ],
    "sg:postcode":"B19 2TD",
    "sg:province":"West Midlands",
    "sg:tags":[
        "tea",
        "room"
    ],
    "wof:name":"Joe's Cafe",
    "wof:placetype":"venue"
},
  "geometry": {"coordinates":[-1.90458,52.502628],"type":"Point"}
}