{
  "type": "Feature",
  "properties": {
    "addr:full":"57b Wellgate Rotherham South Yorkshire S60 2LT",
    "addr:housenumber":"57b",
    "addr:postcode":"s60 2lt",
    "addr:street":"Wellgate Rotherham South",
    "iso:country":"GB",
    "sg:address":"57b Wellgate",
    "sg:city":"Rotherham",
    "sg:classifiers":[
        {
            "category":"Social Services",
            "subcategory":"Retirement Home",
            "type":"Services"
        }
    ],
    "sg:phone":"+44 1709 820042",
    "sg:postcode":"S60 2LT",
    "sg:province":"South Yorkshire",
    "sg:tags":[
        "care"
    ],
    "wof:name":"Community Care Line Services",
    "wof:placetype":"venue"
},
  "geometry": {"coordinates":[-1.3536770344,53.4295310974],"type":"Point"}
}