{
  "type": "Feature",
  "properties": {
    "addr:full":"121 Chase Side, Southgate London Greater London N14 5HD",
    "addr:housenumber":"121",
    "addr:postcode":"n14 5hd",
    "addr:street":"Chase Side",
    "iso:country":"GB",
    "sg:address":"121 Chase Side, Southgate",
    "sg:city":"London",
    "sg:classifiers":[
        {
            "category":"Professional",
            "subcategory":"Accounting & Tax Preparation",
            "type":"Services"
        }
    ],
    "sg:phone":"+44 20 8882 1700",
    "sg:postcode":"N14 5HD",
    "sg:province":"Greater London",
    "sg:tags":[
        "accountant"
    ],
    "wof:name":"Anthony Lawson Ltd.",
    "wof:placetype":"venue"
},
  "geometry": {"coordinates":[-0.134113,51.634472],"type":"Point"}
}