{
  "type": "Feature",
  "properties": {
    "addr:full":"95 Derwent Road, Highwoods Colchester Essex CO4 4RL",
    "addr:housenumber":"95",
    "addr:postcode":"co4 4rl",
    "addr:street":"Derwent Road Highwoods Colchester",
    "iso:country":"GB",
    "sg:address":"95 Derwent Road, Highwoods",
    "sg:city":"Colchester",
    "sg:classifiers":[
        {
            "category":"Retail",
            "subcategory":"Driving School",
            "type":"Services"
        }
    ],
    "sg:phone":"+44 1206 510342",
    "sg:postcode":"CO4 4RL",
    "sg:province":"Essex",
    "wof:name":"Stevenson School Of Motoring",
    "wof:placetype":"venue"
},
  "geometry": {"coordinates":[0.92661,51.914379],"type":"Point"}
}