{
  "type": "Feature",
  "properties": {
    "iso:country":"GB",
    "sg:address":"Birch Hall Farm, Birch Road",
    "sg:city":"Ellesmere",
    "sg:classifiers":[
        {
            "category":"Home & Garden",
            "subcategory":"Garden Supply",
            "type":"Retail Goods"
        }
    ],
    "sg:phone":"+44 1691 624741",
    "sg:postcode":"SY12 9AA",
    "sg:province":"Shropshire",
    "sg:tags":[
        "bulb",
        "grower"
    ],
    "wof:name":"Es & A J & H Gilman",
    "wof:placetype":"venue"
},
  "geometry": {"coordinates":[-2.896755,52.907684],"type":"Point"}
}