{
  "type": "Feature",
  "properties": {
    "addr:full":"220 High St North, East Ham London Greater London E6 2JA",
    "addr:housenumber":"220",
    "addr:postcode":"e6 2ja",
    "addr:street":"High St North",
    "iso:country":"GB",
    "sg:address":"220 High St North, East Ham",
    "sg:city":"London",
    "sg:classifiers":[
        {
            "category":"Sports & Exercise",
            "subcategory":"Playing Field",
            "type":"Entertainment"
        }
    ],
    "sg:phone":"+44 20 8503 4752",
    "sg:postcode":"E6 2JA",
    "sg:province":"Greater London",
    "sg:tags":[
        "ticket",
        "agency",
        "airline"
    ],
    "wof:name":"Call Home International Ltd",
    "wof:placetype":"venue"
},
  "geometry": {"coordinates":[0.0507169999,51.5398788452],"type":"Point"}
}