{
  "type": "Feature",
  "properties": {
    "addr:full":"East Links Road Gullane East Lothian EH31 2AF",
    "addr:postcode":"eh31 2af",
    "addr:street":"East Links Road",
    "iso:country":"GB",
    "sg:address":"East Links Road",
    "sg:city":"Gullane",
    "sg:classifiers":[
        {
            "category":"Restaurant",
            "type":"Food & Drink"
        },
        {
            "category":"Bars & Pubs",
            "subcategory":"Wine Bar",
            "type":"Food & Drink"
        }
    ],
    "sg:phone":"+44 1620 842008",
    "sg:postcode":"EH31 2AF",
    "sg:province":"East Lothian",
    "sg:tags":[
        "-",
        "english"
    ],
    "wof:name":"The Old Clubhouse",
    "wof:placetype":"venue"
},
  "geometry": {"coordinates":[-2.8316869736,56.034412384],"type":"Point"}
}