{
  "type": "Feature",
  "properties": {
    "addr:full":"56 New Oxford Street London Greater London WC1A 1ES",
    "addr:housenumber":"56",
    "addr:postcode":"wc1a 1es",
    "addr:street":"New Oxford Street",
    "iso:country":"GB",
    "sg:address":"56 New Oxford Street",
    "sg:city":"London",
    "sg:classifiers":[
        {
            "category":"Banks & Credit Unions",
            "subcategory":"Bureau De Change",
            "type":"Services"
        }
    ],
    "sg:phone":"+44 20 7637 5288",
    "sg:postcode":"WC1A 1ES",
    "sg:province":"Greater London",
    "wof:name":"J S F Finance & Currency Exchange Co. Ltd.",
    "wof:placetype":"venue"
},
  "geometry": {"coordinates":[-0.1262290031,51.516998291],"type":"Point"}
}