{
  "type": "Feature",
  "properties": {
    "iso:country":"GB",
    "sg:address":"Town Road, Hanley",
    "sg:city":"Stoke-on-trent",
    "sg:classifiers":[
        {
            "category":"Building & Trades",
            "subcategory":"Construction",
            "type":"Services"
        }
    ],
    "sg:phone":"+44 1782 280251",
    "sg:postcode":"ST1 2LA",
    "sg:province":"Staffordshire",
    "sg:tags":[
        "heating",
        "contractor"
    ],
    "wof:name":"George S Hall Central Ltd.",
    "wof:placetype":"venue"
},
  "geometry": {"coordinates":[-2.169259,53.032024],"type":"Point"}
}