{
  "type": "Feature",
  "properties": {
    "addr:full":"Units 4-5, Monmore Park Industrial Estate Wolverhampton West Midlands WV2 2LQ",
    "addr:housenumber":"units 4-5",
    "addr:postcode":"wv2 2lq",
    "addr:street":"Monmore Park Industrial",
    "iso:country":"GB",
    "sg:address":"Units 4-5, Monmore Park Industrial Estate",
    "sg:city":"Wolverhampton",
    "sg:classifiers":[
        {
            "category":"Professional",
            "subcategory":"Management & Consulting",
            "type":"Services"
        }
    ],
    "sg:postcode":"WV2 2LQ",
    "sg:province":"West Midlands",
    "sg:tags":[
        "consultant",
        "business"
    ],
    "wof:name":"Northelton Ltd.",
    "wof:placetype":"venue"
},
  "geometry": {"coordinates":[-2.1039600372,52.571521759],"type":"Point"}
}