{
  "type": "Feature",
  "properties": {
    "addr:full":"Glebe House Barn, Avely Hall La, Assington Sudbury Essex CO10 5LG",
    "addr:housenumber":"avely",
    "addr:postcode":"co10 5lg",
    "addr:street":"La Assington",
    "iso:country":"GB",
    "sg:address":"Glebe House Barn, Avely Hall La, Assington",
    "sg:city":"Sudbury",
    "sg:classifiers":[
        {
            "category":"Shopping",
            "subcategory":"Used Merchandise",
            "type":"Retail Goods"
        }
    ],
    "sg:postcode":"CO10 5LG",
    "sg:province":"Essex",
    "sg:tags":[
        "shop",
        "second-hand"
    ],
    "wof:name":"Strickland,Roland,",
    "wof:placetype":"venue"
},
  "geometry": {"coordinates":[0.81761,52.011089],"type":"Point"}
}