{
  "type": "Feature",
  "properties": {
    "addr:full":"End House, Church Lane, Old Somerby Grantham Leicestershire NG33 4AA",
    "addr:postcode":"ng33 4aa",
    "addr:street":"Church Lane",
    "iso:country":"GB",
    "sg:address":"End House, Church Lane, Old Somerby",
    "sg:city":"Grantham",
    "sg:classifiers":[
        {
            "category":"Shopping",
            "subcategory":"Computers & Home Electronics",
            "type":"Retail Goods"
        }
    ],
    "sg:phone":"+44 1476 591159",
    "sg:postcode":"NG33 4AA",
    "sg:province":"Leicestershire",
    "wof:name":"The Office Junior",
    "wof:placetype":"venue"
},
  "geometry": {"coordinates":[-0.574959,52.889854],"type":"Point"}
}