{
  "type": "Feature",
  "properties": {
    "addr:full":"Dale Farm, Spofforth Harrogate North Yorkshire HG3 1BY",
    "addr:housenumber":"spofforth",
    "addr:postcode":"hg3 1by",
    "addr:street":"Dale",
    "iso:country":"GB",
    "sg:address":"Dale Farm, Spofforth",
    "sg:city":"Harrogate",
    "sg:classifiers":[
        {
            "category":"Utilities",
            "subcategory":"Refuse",
            "type":"Services"
        }
    ],
    "sg:postcode":"HG3 1BY",
    "sg:province":"North Yorkshire",
    "sg:tags":[
        "skip",
        "hire"
    ],
    "wof:name":"Dale Farm Skip Hire",
    "wof:placetype":"venue"
},
  "geometry": {"coordinates":[-1.4434490204,53.9548797607],"type":"Point"}
}