{
  "type": "Feature",
  "properties": {
    "iso:country":"GB",
    "sg:address":"The Old Palace, High Street",
    "sg:city":"St Asaph",
    "sg:classifiers":[
        {
            "category":"Health Services",
            "subcategory":"Nursing And Care Facility",
            "type":"Services"
        },
        {
            "category":"Social Services",
            "subcategory":"Adult Care",
            "type":"Services"
        }
    ],
    "sg:phone":"+44 1745 583707",
    "sg:postcode":"LL17 0RQ",
    "sg:province":"Conwy",
    "sg:tags":[
        "residential",
        "housing",
        "sheltered"
    ],
    "wof:name":"JOHNNIE JOHNSON HOUSING TRUST LTD",
    "wof:placetype":"venue"
},
  "geometry": {"coordinates":[-3.444866,53.256863],"type":"Point"}
}