{
  "type": "Feature",
  "properties": {
    "addr:full":"Martinstown Dorchester Dorset DT2 9LB",
    "addr:postcode":"dt2 9lb",
    "iso:country":"GB",
    "sg:address":"Martinstown",
    "sg:city":"Dorchester",
    "sg:classifiers":[
        {
            "category":"Bars & Pubs",
            "type":"Food & Drink"
        },
        {
            "category":"Community Center",
            "subcategory":"Social",
            "type":"Public Place"
        }
    ],
    "sg:phone":"+44 1305 889361",
    "sg:postcode":"DT2 9LB",
    "sg:province":"Dorset",
    "sg:tags":[
        "pubs",
        "house",
        "inn",
        "activity"
    ],
    "wof:name":"The Brewers Arms",
    "wof:placetype":"venue"
},
  "geometry": {"coordinates":[-2.5042,50.69912],"type":"Point"}
}