{
  "type": "Feature",
  "properties": {
    "addr:full":"760-762 Green Lanes London Greater London N21 3RE",
    "addr:housenumber":"760-762",
    "addr:postcode":"n21 3re",
    "addr:street":"Green Lanes",
    "iso:country":"GB",
    "sg:address":"760-762 Green Lanes",
    "sg:city":"London",
    "sg:classifiers":[
        {
            "category":"Real Estate",
            "subcategory":"Real Estate Agent",
            "type":"Services"
        }
    ],
    "sg:phone":"+44 20 8360 9999",
    "sg:postcode":"N21 3RE",
    "sg:province":"Greater London",
    "wof:name":"Peter Graff",
    "wof:placetype":"venue"
},
  "geometry": {"coordinates":[-0.0958380029,51.6312179565],"type":"Point"}
}