{
  "type": "Feature",
  "properties": {
    "iso:country":"GB",
    "sg:address":"60 Sherwood Drive",
    "sg:city":"Harrogate",
    "sg:classifiers":[
        {
            "category":"Building & Trades",
            "subcategory":"Construction",
            "type":"Services"
        }
    ],
    "sg:phone":"+44 1423 881407",
    "sg:postcode":"HG2 7HF",
    "sg:province":"North Yorkshire",
    "sg:tags":[
        "builder"
    ],
    "wof:name":"Eurolink",
    "wof:placetype":"venue"
},
  "geometry": {"coordinates":[-1.49341,53.990086],"type":"Point"}
}