{
  "type": "Feature",
  "properties": {
    "addr:full":"310 Wigan Road, Atherton Manchester Greater Manchester M46 0GD",
    "addr:housenumber":"310",
    "addr:postcode":"m46 0gd",
    "addr:street":"Wigan Road",
    "iso:country":"GB",
    "sg:address":"310 Wigan Road, Atherton",
    "sg:city":"Manchester",
    "sg:classifiers":[
        {
            "category":"Professional",
            "subcategory":"Detective & Security Services",
            "type":"Services"
        }
    ],
    "sg:phone":"+44 1942 893844",
    "sg:postcode":"M46 0GD",
    "sg:province":"Greater Manchester",
    "wof:name":"Direct Security",
    "wof:placetype":"venue"
},
  "geometry": {"coordinates":[-2.5100300312,53.5229568481],"type":"Point"}
}