{
  "type": "Feature",
  "properties": {
    "addr:full":"400 Otley Rd Bradford West Yorkshire BD2 4QP",
    "addr:housenumber":"400",
    "addr:postcode":"bd2 4qp",
    "addr:street":"Otley Rd",
    "iso:country":"GB",
    "sg:address":"400 Otley Rd",
    "sg:city":"Bradford",
    "sg:classifiers":[
        {
            "category":"Banks & Credit Unions",
            "subcategory":"Financial Services",
            "type":"Services"
        }
    ],
    "sg:phone":"+44 1274 626929",
    "sg:postcode":"BD2 4QP",
    "sg:province":"West Yorkshire",
    "sg:tags":[
        "consultant"
    ],
    "wof:name":"City House Finance",
    "wof:placetype":"venue"
},
  "geometry": {"coordinates":[-1.730107,53.808563],"type":"Point"}
}