{
  "type": "Feature",
  "properties": {
    "iso:country":"GB",
    "sg:address":"213 Mansfield Road",
    "sg:city":"Nottingham",
    "sg:classifiers":[
        {
            "category":"Shopping",
            "subcategory":"Bicycles & Sporting Goods",
            "type":"Retail Goods"
        }
    ],
    "sg:phone":"+44 115 941 9282",
    "sg:postcode":"NG1 3FS",
    "sg:province":"Nottinghamshire",
    "sg:tags":[
        "cycle",
        "accessory"
    ],
    "wof:name":"Mike Poyzer",
    "wof:placetype":"venue"
},
  "geometry": {"coordinates":[-1.152035,52.963402],"type":"Point"}
}