{
  "type": "Feature",
  "properties": {
    "addr:full":"Brandon Rd Coventry Warwickshire CV3 2AQ",
    "addr:postcode":"cv3 2aq",
    "addr:street":"Brandon Rd",
    "iso:country":"GB",
    "sg:address":"Brandon Rd",
    "sg:city":"Coventry",
    "sg:classifiers":[
        {
            "category":"Autos & Motor Vehicles",
            "subcategory":"Automobile Sales",
            "type":"Retail Goods"
        }
    ],
    "sg:phone":"+44 24 7645 1795",
    "sg:postcode":"CV3 2AQ",
    "sg:province":"Warwickshire",
    "sg:tags":[
        "commercial"
    ],
    "wof:name":"Ford & Slater Of Coventry",
    "wof:placetype":"venue"
},
  "geometry": {"coordinates":[-1.4435130358,52.4003257751],"type":"Point"}
}