{
  "type": "Feature",
  "properties": {
    "addr:full":"Badentoy Industrial Estate, Portlethen Aberdeen Aberdeen City AB12 4YA",
    "addr:postcode":"ab12 4ya",
    "addr:street":"Estate Portlethen",
    "iso:country":"GB",
    "sg:address":"Badentoy Industrial Estate, Portlethen",
    "sg:city":"Aberdeen",
    "sg:classifiers":[
        {
            "category":"Professional",
            "subcategory":"Engineering",
            "type":"Services"
        }
    ],
    "sg:phone":"+44 1224 782211",
    "sg:postcode":"AB12 4YA",
    "sg:province":"Aberdeen City",
    "wof:name":"Cansco Pressure Control Ltd.",
    "wof:placetype":"venue"
},
  "geometry": {"coordinates":[-2.137104,57.057838],"type":"Point"}
}