{
  "type": "Feature",
  "properties": {
    "iso:country":"GB",
    "sg:address":"39 Blencathra Street",
    "sg:city":"Keswick",
    "sg:classifiers":[
        {
            "category":"Travel",
            "subcategory":"Hotels & Motels",
            "type":"Entertainment"
        }
    ],
    "sg:phone":"+44 17687 73344",
    "sg:postcode":"CA12 4HX",
    "sg:province":"Cumbria",
    "sg:tags":[
        "house",
        "guest"
    ],
    "wof:name":"Cragside Guest House",
    "wof:placetype":"venue"
},
  "geometry": {"coordinates":[-3.1294059753,54.6014213562],"type":"Point"}
}