{
  "type": "Feature",
  "properties": {
    "addr:full":"Office 30 Manor House, 40 Moat Lane Birmingham West Midlands B5 5BD",
    "addr:housenumber":"30;40",
    "addr:postcode":"b5 5bd",
    "addr:street":"Manor;Moat Lane",
    "iso:country":"GB",
    "sg:address":"Office 30 Manor House, 40 Moat Lane",
    "sg:city":"Birmingham",
    "sg:classifiers":[
        {
            "category":"Professional",
            "subcategory":"Business Services",
            "type":"Services"
        }
    ],
    "sg:phone":"+44 121 622 4900",
    "sg:postcode":"B5 5BD",
    "sg:province":"West Midlands",
    "sg:tags":[
        "trade"
    ],
    "wof:name":"Birmingham & District Butchers Association",
    "wof:placetype":"venue"
},
  "geometry": {"coordinates":[-1.891422,52.475731],"type":"Point"}
}