{
  "type": "Feature",
  "properties": {
    "iso:country":"GB",
    "sg:address":"Victoria House",
    "sg:city":"Epsom",
    "sg:classifiers":[
        {
            "category":"Professional",
            "subcategory":"Employment Agencies",
            "type":"Services"
        },
        {
            "category":"Education",
            "subcategory":"School",
            "type":"Public Place"
        }
    ],
    "sg:phone":"+44 1372 728823",
    "sg:postcode":"KT17 1HH",
    "sg:province":"Surrey",
    "sg:tags":[
        "consultant",
        "college",
        "commercial"
    ],
    "wof:name":"Collins Commercial College",
    "wof:placetype":"venue"
},
  "geometry": {"coordinates":[-0.250559,51.34692],"type":"Point"}
}