{
  "type": "Feature",
  "properties": {
    "iso:country":"GB",
    "sg:address":"Stanhope Square",
    "sg:city":"Ashford",
    "sg:classifiers":[
        {
            "category":"Food & Beverages",
            "subcategory":"Meat & Fish",
            "type":"Retail Goods"
        }
    ],
    "sg:phone":"+44 1233 623557",
    "sg:postcode":"TN23 5SH",
    "sg:province":"Kent",
    "sg:tags":[
        "chip"
    ],
    "wof:name":"Wye Fisheries",
    "wof:placetype":"venue"
},
  "geometry": {"coordinates":[0.8539249897,51.1318702698],"type":"Point"}
}