{
  "type": "Feature",
  "properties": {
    "addr:full":"Denmark Ho, 143 High St, Chalfont St Peter Gerrards Cross Buckinghamshire SL9 9QL",
    "addr:housenumber":"143",
    "addr:postcode":"sl9 9ql",
    "addr:street":"High St",
    "iso:country":"GB",
    "sg:address":"Denmark Ho, 143 High St, Chalfont St Peter",
    "sg:city":"Gerrards Cross",
    "sg:classifiers":[
        {
            "category":"Real Estate",
            "subcategory":"Real Estate Agent",
            "type":"Services"
        }
    ],
    "sg:postcode":"SL9 9QL",
    "sg:province":"Buckinghamshire",
    "wof:name":"Eelbrook Properties Ltd",
    "wof:placetype":"venue"
},
  "geometry": {"coordinates":[-0.55557,51.607811],"type":"Point"}
}