{
  "type": "Feature",
  "properties": {
    "iso:country":"GB",
    "sg:address":"The Old Pound Ho, London Rd, Sunningdale",
    "sg:city":"Ascot",
    "sg:classifiers":[
        {
            "category":"Professional",
            "subcategory":"Employment Agencies",
            "type":"Services"
        }
    ],
    "sg:postcode":"SL5 0DJ",
    "sg:province":"Berkshire",
    "sg:tags":[
        "consultant"
    ],
    "wof:name":"Child Salmon Associates Ltd",
    "wof:placetype":"venue"
},
  "geometry": {"coordinates":[-0.6289899945,51.3929595947],"type":"Point"}
}