{
  "type": "Feature",
  "properties": {
    "iso:country":"GB",
    "sg:address":"18 Gillibrand St",
    "sg:city":"Chorley",
    "sg:classifiers":[
        {
            "category":"Shopping",
            "subcategory":"Antiques",
            "type":"Retail Goods"
        }
    ],
    "sg:postcode":"PR7 2EJ",
    "sg:province":"Lancashire",
    "wof:name":"Nostalgia",
    "wof:placetype":"venue"
},
  "geometry": {"coordinates":[-2.632535,53.651443],"type":"Point"}
}