{
  "type": "Feature",
  "properties": {
    "addr:full":"42 Bannister Street Withernsea East Riding of Yorkshire HU19 2DT",
    "addr:housenumber":"42",
    "addr:postcode":"hu19 2dt",
    "addr:street":"Bannister Street",
    "iso:country":"GB",
    "sg:address":"42 Bannister Street",
    "sg:city":"Withernsea",
    "sg:classifiers":[
        {
            "category":"Personal",
            "subcategory":"Adult",
            "type":"Services"
        }
    ],
    "sg:postcode":"HU19 2DT",
    "sg:province":"East Riding of Yorkshire",
    "sg:tags":[
        "equestrian"
    ],
    "wof:name":"M Brashill",
    "wof:placetype":"venue"
},
  "geometry": {"coordinates":[0.0315850005,53.733127594],"type":"Point"}
}