{
  "type": "Feature",
  "properties": {
    "iso:country":"GB",
    "sg:address":"Praed Street",
    "sg:city":"London",
    "sg:classifiers":[
        {
            "category":"Health Services",
            "subcategory":"Hospital",
            "type":"Services"
        }
    ],
    "sg:phone":"+44 20 7886 6666",
    "sg:postcode":"W2 1NY",
    "sg:province":"Greater London",
    "wof:name":"St.Mary's N H S Trust",
    "wof:placetype":"venue"
},
  "geometry": {"coordinates":[-0.169539,51.51899],"type":"Point"}
}