{
  "type": "Feature",
  "properties": {
    "addr:full":"Unit 28, The Tanneries, Brockhampton Havant Hampshire PO9 1JB",
    "addr:housenumber":"unit 28;tanneries",
    "addr:postcode":"po9 1jb",
    "addr:street":"The",
    "iso:country":"GB",
    "sg:address":"Unit 28, The Tanneries, Brockhampton",
    "sg:city":"Havant",
    "sg:classifiers":[
        {
            "category":"Autos & Motor Vehicles",
            "subcategory":"Auto Supplies",
            "type":"Retail Goods"
        }
    ],
    "sg:postcode":"PO9 1JB",
    "sg:province":"Hampshire",
    "sg:tags":[
        "car",
        "accessory"
    ],
    "wof:name":"Phillips,Paul,",
    "wof:placetype":"venue"
},
  "geometry": {"coordinates":[-0.9855440259,50.8544960022],"type":"Point"}
}