{
  "type": "Feature",
  "properties": {
    "addr:full":"Blackbull Farm Grantham Leicestershire NG33 5LL",
    "addr:postcode":"ng33 5ll",
    "iso:country":"GB",
    "sg:address":"Blackbull Farm",
    "sg:city":"Grantham",
    "sg:classifiers":[
        {
            "category":"Travel",
            "subcategory":"Hotels & Motels",
            "type":"Entertainment"
        }
    ],
    "sg:phone":"+44 1476 860086",
    "sg:postcode":"NG33 5LL",
    "sg:province":"Leicestershire",
    "wof:name":"Blackbull Motel",
    "wof:placetype":"venue"
},
  "geometry": {"coordinates":[-0.6104900241,52.7808303833],"type":"Point"}
}