{
  "type": "Feature",
  "properties": {
    "addr:full":"11 Old Burlington Street London Greater London W1S 3AQ",
    "addr:housenumber":"11",
    "addr:postcode":"w1s 3aq",
    "addr:street":"Old Burlington Street",
    "iso:country":"GB",
    "sg:address":"11 Old Burlington Street",
    "sg:city":"London",
    "sg:classifiers":[
        {
            "category":"Organizations",
            "subcategory":"Community Association",
            "type":"Services"
        }
    ],
    "sg:phone":"+44 20 7734 5211",
    "sg:postcode":"W1S 3AQ",
    "sg:province":"Greater London",
    "sg:tags":[
        "relation",
        "public"
    ],
    "wof:name":"Timothy Glazier Associates",
    "wof:placetype":"venue"
},
  "geometry": {"coordinates":[-0.140877,51.51086],"type":"Point"}
}