{
  "type": "Feature",
  "properties": {
    "addr:full":"265 Clifton Road Rugby Warwickshire CV21 3QY",
    "addr:housenumber":"265",
    "addr:postcode":"cv21 3qy",
    "addr:street":"Clifton Road",
    "iso:country":"GB",
    "sg:address":"265 Clifton Road",
    "sg:city":"Rugby",
    "sg:classifiers":[
        {
            "category":"Organizations",
            "subcategory":"Community Association",
            "type":"Services"
        }
    ],
    "sg:phone":"+44 24 7638 3520",
    "sg:postcode":"CV21 3QY",
    "sg:province":"Warwickshire",
    "sg:tags":[
        "society",
        "housing"
    ],
    "wof:name":"Abbeyfield Rugby Society",
    "wof:placetype":"venue"
},
  "geometry": {"coordinates":[-1.2429209948,52.373626709],"type":"Point"}
}