{
  "type": "Feature",
  "properties": {
    "addr:full":"12-14 Abergele Road Colwyn Bay Conwy LL29 7NU",
    "addr:housenumber":"12-14",
    "addr:postcode":"ll29 7nu",
    "addr:street":"Abergele Road",
    "iso:country":"GB",
    "sg:address":"12-14 Abergele Road",
    "sg:city":"Colwyn Bay",
    "sg:classifiers":[
        {
            "category":"Shopping",
            "subcategory":"Department Store",
            "type":"Retail Goods"
        }
    ],
    "sg:phone":"+44 1492 532912",
    "sg:postcode":"LL29 7NU",
    "sg:province":"Conwy",
    "sg:tags":[
        "departmental"
    ],
    "wof:name":"Woolworths Plc",
    "wof:placetype":"venue"
},
  "geometry": {"coordinates":[-3.7272601128,53.29479599],"type":"Point"}
}