{
  "type": "Feature",
  "properties": {
    "addr:full":"Unit 11, Camphill Industrial Estate, Camphill Road West Byfleet Surrey KT14 6EW",
    "addr:housenumber":"unit 11",
    "addr:postcode":"kt14 6ew",
    "addr:street":"Industrial Estate Camphill Road West",
    "iso:country":"GB",
    "sg:address":"Unit 11, Camphill Industrial Estate, Camphill Road",
    "sg:city":"West Byfleet",
    "sg:classifiers":[
        {
            "category":"Professional",
            "subcategory":"Computer Services",
            "type":"Services"
        }
    ],
    "sg:phone":"+44 1932 336636",
    "sg:postcode":"KT14 6EW",
    "sg:province":"Surrey",
    "sg:tags":[
        "system",
        "software"
    ],
    "wof:name":"Pickwick (Computer Supplies) Ltd.",
    "wof:placetype":"venue"
},
  "geometry": {"coordinates":[-0.4969210029,51.3384208679],"type":"Point"}
}