{
  "type": "Feature",
  "properties": {
    "addr:full":"Po Box 222 Chesterfield Derbyshire S40 1YY",
    "addr:housenumber":"po;222",
    "addr:postcode":"s40 1yy",
    "addr:street":"Box",
    "iso:country":"GB",
    "sg:address":"Po Box 222",
    "sg:city":"Chesterfield",
    "sg:classifiers":[
        {
            "category":"Professional",
            "subcategory":"Engineering",
            "type":"Services"
        }
    ],
    "sg:postcode":"S40 1YY",
    "sg:province":"Derbyshire",
    "sg:tags":[
        "precision",
        "engineer"
    ],
    "wof:name":"Hallrite Precision Engineering",
    "wof:placetype":"venue"
},
  "geometry": {"coordinates":[-1.434589982,53.2353286743],"type":"Point"}
}