{
  "type": "Feature",
  "properties": {
    "iso:country":"GB",
    "sg:address":"Tamworth Street",
    "sg:city":"Lichfield",
    "sg:classifiers":[
        {
            "category":"Place Of Worship",
            "type":"Public Place"
        }
    ],
    "sg:postcode":"WS13 6JJ",
    "sg:province":"Staffordshire",
    "wof:name":"Lichfield Methodist Church",
    "wof:placetype":"venue"
},
  "geometry": {"coordinates":[-1.8242540359,52.6839675903],"type":"Point"}
}