{
  "type": "Feature",
  "properties": {
    "iso:country":"GB",
    "sg:address":"Polmear Hill",
    "sg:city":"Par",
    "sg:classifiers":[
        {
            "category":"Fast Food",
            "type":"Food & Drink"
        },
        {
            "category":"Restaurant",
            "type":"Food & Drink"
        }
    ],
    "sg:phone":"+44 1726 812667",
    "sg:postcode":"PL24 2AR",
    "sg:province":"Cornwall",
    "sg:tags":[
        "away",
        "mexican",
        "take"
    ],
    "wof:name":"Pepe's",
    "wof:placetype":"venue"
},
  "geometry": {"coordinates":[-4.683631,50.34856],"type":"Point"}
}