{
  "type": "Feature",
  "properties": {
    "iso:country":"GB",
    "sg:address":"15 Riverside View, Wickham Market",
    "sg:city":"Woodbridge",
    "sg:classifiers":[
        {
            "category":"Retail",
            "subcategory":"Auto Repair",
            "type":"Services"
        }
    ],
    "sg:phone":"+44 1728 746999",
    "sg:postcode":"IP13 0TA",
    "sg:province":"Suffolk",
    "sg:tags":[
        "modification",
        "garage",
        "related"
    ],
    "wof:name":"All in Auto Services",
    "wof:placetype":"venue"
},
  "geometry": {"coordinates":[1.363956,52.157551],"type":"Point"}
}