{
  "type": "Feature",
  "properties": {
    "addr:full":"72 Marl Drive Llandudno Junction Conwy LL31 9LL",
    "addr:housenumber":"72",
    "addr:postcode":"ll31 9ll",
    "addr:street":"Marl Drive",
    "iso:country":"GB",
    "sg:address":"72 Marl Drive",
    "sg:city":"Llandudno Junction",
    "sg:classifiers":[
        {
            "category":"Professional",
            "subcategory":"Computer Services",
            "type":"Services"
        }
    ],
    "sg:phone":"+44 1492 583251",
    "sg:postcode":"LL31 9LL",
    "sg:province":"Conwy",
    "sg:tags":[
        "system",
        "software"
    ],
    "wof:name":"Marl Electronics",
    "wof:placetype":"venue"
},
  "geometry": {"coordinates":[-3.8062601089,53.2875366211],"type":"Point"}
}