{
  "type": "Feature",
  "properties": {
    "iso:country":"GB",
    "sg:address":"Woodside, The Lane, Alwoodley",
    "sg:city":"Leeds",
    "sg:classifiers":[
        {
            "category":"Health Services",
            "subcategory":"Clinic",
            "type":"Services"
        }
    ],
    "sg:phone":"+44 113 267 3339",
    "sg:postcode":"LS17 7BX",
    "sg:province":"North Yorkshire",
    "sg:tags":[
        "aromatherapy"
    ],
    "wof:name":"Ursula Shaw MNHR",
    "wof:placetype":"venue"
},
  "geometry": {"coordinates":[-1.533779,53.862099],"type":"Point"}
}