{
  "type": "Feature",
  "properties": {
    "addr:full":"12 Riverside Road Blandford Forum Dorset DT11 7ES",
    "addr:housenumber":"12",
    "addr:postcode":"dt11 7es",
    "addr:street":"Riverside Road",
    "iso:country":"GB",
    "sg:address":"12 Riverside Road",
    "sg:city":"Blandford Forum",
    "sg:classifiers":[
        {
            "category":"Building & Trades",
            "subcategory":"Construction",
            "type":"Services"
        }
    ],
    "sg:phone":"+44 1258 452976",
    "sg:postcode":"DT11 7ES",
    "sg:province":"Dorset",
    "sg:tags":[
        "builder",
        "guttering"
    ],
    "wof:name":"R H Miles",
    "wof:placetype":"venue"
},
  "geometry": {"coordinates":[-2.1556680202,50.8549423218],"type":"Point"}
}