{
  "type": "Feature",
  "properties": {
    "addr:full":"Lankhurst Oak Uckfield East Sussex TN22 5HD",
    "addr:postcode":"tn22 5hd",
    "addr:street":"Lankhurst",
    "iso:country":"GB",
    "sg:address":"Lankhurst Oak",
    "sg:city":"Uckfield",
    "sg:classifiers":[
        {
            "category":"Shopping",
            "subcategory":"Department Store",
            "type":"Retail Goods"
        }
    ],
    "sg:postcode":"TN22 5HD",
    "sg:province":"East Sussex",
    "wof:name":"Loosley,Hilary & Roy,",
    "wof:placetype":"venue"
},
  "geometry": {"coordinates":[0.0966499969,50.9718132019],"type":"Point"}
}