{
  "type": "Feature",
  "properties": {
    "iso:country":"GB",
    "sg:address":"39 Infirmary Street",
    "sg:city":"Bradford",
    "sg:classifiers":[
        {
            "category":"Banks & Credit Unions",
            "subcategory":"Bank",
            "type":"Services"
        }
    ],
    "sg:postcode":"BD1 3SF",
    "sg:province":"West Yorkshire",
    "sg:tags":[
        "broker",
        "mortgage"
    ],
    "wof:name":"S Mahmood",
    "wof:placetype":"venue"
},
  "geometry": {"coordinates":[-1.759259,53.796726],"type":"Point"}
}