{
  "type": "Feature",
  "properties": {
    "addr:full":"Unit 39a, Holme Mills Industrial Estate Carnforth Cumbria LA6 1RD",
    "addr:housenumber":"unit 39a;estate",
    "addr:postcode":"la6 1rd",
    "addr:street":"Holme Mills Industrial",
    "iso:country":"GB",
    "sg:address":"Unit 39a, Holme Mills Industrial Estate",
    "sg:city":"Carnforth",
    "sg:classifiers":[
        {
            "category":"Professional",
            "subcategory":"Engineering",
            "type":"Services"
        }
    ],
    "sg:phone":"+44 1524 782334",
    "sg:postcode":"LA6 1RD",
    "sg:province":"Cumbria",
    "sg:tags":[
        "electronic",
        "engineer"
    ],
    "wof:name":"Panoptic Ltd.",
    "wof:placetype":"venue"
},
  "geometry": {"coordinates":[-2.73198,54.194618],"type":"Point"}
}