{
  "type": "Feature",
  "properties": {
    "addr:full":"Mill Lane, Barnham Thetford Norfolk IP24 2NG",
    "addr:postcode":"ip24 2ng",
    "addr:street":"Mill Lane",
    "iso:country":"GB",
    "sg:address":"Mill Lane, Barnham",
    "sg:city":"Thetford",
    "sg:classifiers":[
        {
            "category":"Education",
            "subcategory":"School",
            "type":"Public Place"
        },
        {
            "category":"Government",
            "subcategory":"Office",
            "type":"Public Place"
        }
    ],
    "sg:phone":"+44 1842 890253",
    "sg:postcode":"IP24 2NG",
    "sg:province":"Norfolk",
    "sg:tags":[
        "local",
        "authority"
    ],
    "wof:name":"Barnham C Of E School",
    "wof:placetype":"venue"
},
  "geometry": {"coordinates":[0.74055,52.378857],"type":"Point"}
}