{
  "type": "Feature",
  "properties": {
    "iso:country":"GB",
    "sg:address":"Lion Street",
    "sg:city":"Rye",
    "sg:classifiers":[
        {
            "category":"Cafe",
            "type":"Food & Drink"
        }
    ],
    "sg:phone":"+44 1797 222227",
    "sg:postcode":"TN31 7LB",
    "sg:province":"East Sussex",
    "sg:tags":[
        "tea",
        "room"
    ],
    "wof:name":"Fletchers House",
    "wof:placetype":"venue"
},
  "geometry": {"coordinates":[0.7338550091,50.9507637024],"type":"Point"}
}