{
  "type": "Feature",
  "properties": {
    "iso:country":"GB",
    "sg:address":"20 Oatland Drive",
    "sg:city":"Weybridge",
    "sg:classifiers":[
        {
            "category":"Professional",
            "subcategory":"Computer Services",
            "type":"Services"
        }
    ],
    "sg:phone":"+44 1932 237500",
    "sg:postcode":"KT13 9LZ",
    "sg:province":"Surrey",
    "sg:tags":[
        "system",
        "software"
    ],
    "wof:name":"Manufacturing Products & Services Ltd.",
    "wof:placetype":"venue"
},
  "geometry": {"coordinates":[-0.43451,51.37788],"type":"Point"}
}