{
  "type": "Feature",
  "properties": {
    "iso:country":"GB",
    "sg:address":"61 Holbrook Road",
    "sg:city":"Cambridge",
    "sg:classifiers":[
        {
            "category":"Professional",
            "subcategory":"Management & Consulting",
            "type":"Services"
        }
    ],
    "sg:postcode":"CB1 7SX",
    "sg:province":"Cambridgeshire",
    "sg:tags":[
        "consultant",
        "business"
    ],
    "wof:name":"Delta Technology International Ltd.",
    "wof:placetype":"venue"
},
  "geometry": {"coordinates":[0.145225,52.180725],"type":"Point"}
}