{
  "type": "Feature",
  "properties": {
    "iso:country":"GB",
    "sg:address":"5 Kenilworth Gdns, South Oxhey",
    "sg:city":"Watford",
    "sg:classifiers":[
        {
            "category":"Retail",
            "subcategory":"Auto Repair",
            "type":"Services"
        }
    ],
    "sg:postcode":"WD19 6TS",
    "sg:province":"Hertfordshire",
    "sg:tags":[
        "modification",
        "garage"
    ],
    "wof:name":"Auto-Moto Centre Ltd",
    "wof:placetype":"venue"
},
  "geometry": {"coordinates":[-0.395362,51.619213],"type":"Point"}
}