{
  "type": "Feature",
  "properties": {
    "addr:full":"481 Gorgie Road Edinburgh City of Edinburgh EH11 3AD",
    "addr:housenumber":"481",
    "addr:postcode":"eh11 3ad",
    "addr:street":"Gorgie Road",
    "iso:country":"GB",
    "sg:address":"481 Gorgie Road",
    "sg:city":"Edinburgh",
    "sg:classifiers":[
        {
            "category":"Shopping",
            "subcategory":"Stationery & Office Supplies",
            "type":"Retail Goods"
        },
        {
            "category":"Professional",
            "subcategory":"Business Services",
            "type":"Services"
        }
    ],
    "sg:phone":"+44 131 443 5000",
    "sg:postcode":"EH11 3AD",
    "sg:province":"City of Edinburgh",
    "sg:tags":[
        "box",
        "carton",
        "manufacturer"
    ],
    "sg:website":"http://www.cal-pack.co.uk",
    "wof:name":"Caledonian Packaging Ltd",
    "wof:placetype":"venue"
},
  "geometry": {"coordinates":[-3.250294,55.931812],"type":"Point"}
}