{
  "type": "Feature",
  "properties": {
    "addr:full":"49 Furnace Lane Sheffield South Yorkshire S13 9XB",
    "addr:housenumber":"49",
    "addr:postcode":"s13 9xb",
    "addr:street":"Furnace Lane",
    "iso:country":"GB",
    "sg:address":"49 Furnace Lane",
    "sg:city":"Sheffield",
    "sg:classifiers":[
        {
            "category":"Shopping",
            "subcategory":"News",
            "type":"Retail Goods"
        }
    ],
    "sg:phone":"+44 114 269 3621",
    "sg:postcode":"S13 9XB",
    "sg:province":"South Yorkshire",
    "sg:tags":[
        "newsagent"
    ],
    "wof:name":"E & V HOUSLEY",
    "wof:placetype":"venue"
},
  "geometry": {"coordinates":[-1.353829,53.364304],"type":"Point"}
}