{
  "type": "Feature",
  "properties": {
    "addr:full":"5 Anvil Ct, High St, Stanford In The Vale Faringdon Oxfordshire SN7 8NQ",
    "addr:housenumber":"5",
    "addr:postcode":"sn7 8nq",
    "addr:street":"Anvil Ct High St",
    "iso:country":"GB",
    "sg:address":"5 Anvil Ct, High St, Stanford In The Vale",
    "sg:city":"Faringdon",
    "sg:classifiers":[
        {
            "category":"Community Center",
            "subcategory":"Youth",
            "type":"Public Place"
        }
    ],
    "sg:postcode":"SN7 8NQ",
    "sg:province":"Oxfordshire",
    "sg:tags":[
        "children's",
        "activity"
    ],
    "wof:name":"Super Camps Ltd",
    "wof:placetype":"venue"
},
  "geometry": {"coordinates":[-1.509714,51.634995],"type":"Point"}
}