{
  "type": "Feature",
  "properties": {
    "addr:full":"53a Worcester Lane, Pedmore Stourbridge Staffordshire DY8 2PA",
    "addr:housenumber":"53a",
    "addr:postcode":"dy8 2pa",
    "addr:street":"Worcester Lane",
    "iso:country":"GB",
    "sg:address":"53a Worcester Lane, Pedmore",
    "sg:city":"Stourbridge",
    "sg:classifiers":[
        {
            "category":"Professional",
            "subcategory":"Management & Consulting",
            "type":"Services"
        }
    ],
    "sg:phone":"+44 1384 374111",
    "sg:postcode":"DY8 2PA",
    "sg:province":"Staffordshire",
    "sg:tags":[
        "consultant",
        "business"
    ],
    "wof:name":"Tye Management Services Ltd.",
    "wof:placetype":"venue"
},
  "geometry": {"coordinates":[-2.140241,52.44138],"type":"Point"}
}