{
  "type": "Feature",
  "properties": {
    "addr:full":"Camberley Drive Liverpool Merseyside L25 9PS",
    "addr:postcode":"l25 9ps",
    "addr:street":"Camberley Drive",
    "iso:country":"GB",
    "sg:address":"Camberley Drive",
    "sg:city":"Liverpool",
    "sg:classifiers":[
        {
            "category":"Health Services",
            "subcategory":"Doctor",
            "type":"Services"
        }
    ],
    "sg:phone":"+44 151 486 1178",
    "sg:postcode":"L25 9PS",
    "sg:province":"Merseyside",
    "sg:tags":[
        "practitioners"
    ],
    "wof:name":"Camberley Medical Centre",
    "wof:placetype":"venue"
},
  "geometry": {"coordinates":[-2.8472490311,53.3680038452],"type":"Point"}
}