{
  "type": "Feature",
  "properties": {
    "addr:full":"4 Edensor Court, London Road Newcastle Staffordshire ST5 7EA",
    "addr:housenumber":"4",
    "addr:postcode":"st5 7ea",
    "addr:street":"Edensor Court London Road",
    "iso:country":"GB",
    "sg:address":"4 Edensor Court, London Road",
    "sg:city":"Newcastle",
    "sg:classifiers":[
        {
            "category":"Home & Garden",
            "subcategory":"Household Appliances",
            "type":"Retail Goods"
        }
    ],
    "sg:postcode":"ST5 7EA",
    "sg:province":"Staffordshire",
    "sg:tags":[
        "electrical",
        "domestic"
    ],
    "wof:name":"Scragg & Lunt",
    "wof:placetype":"venue"
},
  "geometry": {"coordinates":[-2.250804,53.042213],"type":"Point"}
}