{
  "type": "Feature",
  "properties": {
    "addr:full":"70 Coplaw St Glasgow Glasgow City G42 7JG",
    "addr:housenumber":"70",
    "addr:postcode":"g42 7jg",
    "addr:street":"Coplaw St",
    "iso:country":"GB",
    "sg:address":"70 Coplaw St",
    "sg:city":"Glasgow",
    "sg:classifiers":[
        {
            "category":"Government",
            "subcategory":"City Hall",
            "type":"Public Place"
        }
    ],
    "sg:phone":"+44 141 423 3317",
    "sg:postcode":"G42 7JG",
    "sg:province":"Glasgow City",
    "wof:name":"Kashatri Sabha",
    "wof:placetype":"venue"
},
  "geometry": {"coordinates":[-4.258049,55.839458],"type":"Point"}
}