{
  "type": "Feature",
  "properties": {
    "addr:full":"Balcary House, Buccleuch Road Hawick Cumbria TD9 0EH",
    "addr:postcode":"td9 0eh",
    "addr:street":"Buccleuch Road",
    "iso:country":"GB",
    "sg:address":"Balcary House, Buccleuch Road",
    "sg:city":"Hawick",
    "sg:classifiers":[
        {
            "category":"Organizations",
            "subcategory":"Religious Organization",
            "type":"Services"
        }
    ],
    "sg:phone":"+44 1450 372966",
    "sg:postcode":"TD9 0EH",
    "sg:province":"Cumbria",
    "sg:tags":[
        "organisation"
    ],
    "wof:name":"People With A Mission Ministries",
    "wof:placetype":"venue"
},
  "geometry": {"coordinates":[-2.7975258827,55.4210319519],"type":"Point"}
}