{
  "type": "Feature",
  "properties": {
    "iso:country":"GB",
    "sg:address":"83 High St",
    "sg:city":"Norwich",
    "sg:classifiers":[
        {
            "category":"Fast Food",
            "type":"Food & Drink"
        }
    ],
    "sg:phone":"+44 1692 582848",
    "sg:postcode":"NR12 9BB",
    "sg:province":"Norfolk",
    "sg:tags":[
        "away",
        "take"
    ],
    "wof:name":"Norfolk Pizza",
    "wof:placetype":"venue"
},
  "geometry": {"coordinates":[1.513755,52.772243],"type":"Point"}
}