{
  "type": "Feature",
  "properties": {
    "addr:full":"Warren House Farm, Middleton On The Wolds Driffield East Riding of Yorkshire YO25 9DQ",
    "addr:postcode":"yo25 9dq",
    "addr:street":"Warren House Farm",
    "iso:country":"GB",
    "sg:address":"Warren House Farm, Middleton On The Wolds",
    "sg:city":"Driffield",
    "sg:classifiers":[
        {
            "category":"Farming",
            "subcategory":"Livestock Farm",
            "type":"Manufacturing & Wholesale Goods"
        }
    ],
    "sg:phone":"+44 1377 217326",
    "sg:postcode":"YO25 9DQ",
    "sg:province":"East Riding of Yorkshire",
    "sg:tags":[
        "others"
    ],
    "wof:name":"Maltas Farms Ltd.",
    "wof:placetype":"venue"
},
  "geometry": {"coordinates":[-0.531303,53.953842],"type":"Point"}
}