{
  "type": "Feature",
  "properties": {
    "iso:country":"GB",
    "sg:address":"20 Taff Vale Shopping Centre",
    "sg:city":"Pontypridd",
    "sg:classifiers":[
        {
            "category":"Shopping",
            "subcategory":"Gifts & Souvenirs",
            "type":"Retail Goods"
        },
        {
            "category":"Government",
            "subcategory":"Post Office",
            "type":"Public Place"
        }
    ],
    "sg:phone":"+44 1443 402434",
    "sg:postcode":"CF37 4TH",
    "sg:province":"Caerphilly",
    "sg:tags":[
        "poster",
        "card"
    ],
    "wof:name":"Special Occasions",
    "wof:placetype":"venue"
},
  "geometry": {"coordinates":[-3.3406000137,51.6038894653],"type":"Point"}
}