{
  "type": "Feature",
  "properties": {
    "iso:country":"GB",
    "sg:address":"44 Balmoral Place",
    "sg:city":"Aberdeen",
    "sg:classifiers":[
        {
            "category":"Retail",
            "subcategory":"Repair Shop",
            "type":"Services"
        }
    ],
    "sg:phone":"+44 1224 574055",
    "sg:postcode":"AB10 6HP",
    "sg:province":"Aberdeen City",
    "sg:tags":[
        "radio",
        "television",
        "video"
    ],
    "wof:name":"Videotech",
    "wof:placetype":"venue"
},
  "geometry": {"coordinates":[-2.118624,57.13509],"type":"Point"}
}