{
  "type": "Feature",
  "properties": {
    "addr:full":"4-6 Wigan Road, Atherton Manchester Greater Manchester M46 0JQ",
    "addr:housenumber":"4-6",
    "addr:postcode":"m46 0jq",
    "addr:street":"Wigan Road",
    "iso:country":"GB",
    "sg:address":"4-6 Wigan Road, Atherton",
    "sg:city":"Manchester",
    "sg:classifiers":[
        {
            "category":"Shopping",
            "subcategory":"News",
            "type":"Retail Goods"
        }
    ],
    "sg:phone":"+44 1942 883916",
    "sg:postcode":"M46 0JQ",
    "sg:province":"Greater Manchester",
    "sg:tags":[
        "newsagent"
    ],
    "wof:name":"K Snape",
    "wof:placetype":"venue"
},
  "geometry": {"coordinates":[-2.4983010292,53.5234375],"type":"Point"}
}