{
  "type": "Feature",
  "properties": {
    "iso:country":"GB",
    "sg:address":"52 Carisbrooke High Street",
    "sg:city":"Newport",
    "sg:classifiers":[
        {
            "category":"Food & Beverages",
            "subcategory":"Supermarket",
            "type":"Retail Goods"
        },
        {
            "category":"Food & Beverages",
            "subcategory":"Groceries & Convenience Stores",
            "type":"Retail Goods"
        }
    ],
    "sg:phone":"+44 1983 522040",
    "sg:postcode":"PO30 1NR",
    "sg:province":"Isle of Wight",
    "wof:name":"David'S Foodmarket",
    "wof:placetype":"venue"
},
  "geometry": {"coordinates":[-1.3000279665,50.6978797913],"type":"Point"}
}