{
  "type": "Feature",
  "properties": {
    "iso:country":"GB",
    "sg:address":"27 Askrigg Close, Ouston",
    "sg:city":"Chester-le-street",
    "sg:classifiers":[
        {
            "category":"Military Area",
            "subcategory":"Air Force Base",
            "type":"Public Place"
        }
    ],
    "sg:postcode":"DH2 1TX",
    "sg:province":"Durham",
    "sg:tags":[
        "taxi",
        "hire",
        "private"
    ],
    "wof:name":"Grange Taxis",
    "wof:placetype":"venue"
},
  "geometry": {"coordinates":[-1.60974,54.888515],"type":"Point"}
}