{
  "type": "Feature",
  "properties": {
    "addr:full":"Knight House, Foxhall Road Southminster Essex CM0 7LB",
    "addr:postcode":"cm0 7lb",
    "addr:street":"Foxhall Road",
    "iso:country":"GB",
    "sg:address":"Knight House, Foxhall Road",
    "sg:city":"Southminster",
    "sg:classifiers":[
        {
            "category":"Shopping",
            "subcategory":"Computers & Home Electronics",
            "type":"Retail Goods"
        }
    ],
    "sg:phone":"+44 1621 774874",
    "sg:postcode":"CM0 7LB",
    "sg:province":"Essex",
    "wof:name":"Conifer Furniture",
    "wof:placetype":"venue"
},
  "geometry": {"coordinates":[0.821646,51.675407],"type":"Point"}
}