{
  "type": "Feature",
  "properties": {
    "iso:country":"GB",
    "sg:address":"Booth Street",
    "sg:city":"Stalybridge",
    "sg:classifiers":[
        {
            "category":"Retail",
            "subcategory":"Funeral Services",
            "type":"Services"
        }
    ],
    "sg:phone":"+44 161 338 2461",
    "sg:postcode":"SK15 1TS",
    "sg:province":"Greater Manchester",
    "wof:name":"Murrays Funeral Directors",
    "wof:placetype":"venue"
},
  "geometry": {"coordinates":[-2.0683190823,53.477973938],"type":"Point"}
}