{
  "type": "Feature",
  "properties": {
    "addr:full":"Hardman, High Street Deal Kent CT14 6EG",
    "addr:postcode":"ct14 6eg",
    "addr:street":"High Street Deal",
    "iso:country":"GB",
    "sg:address":"Hardman, High Street",
    "sg:city":"Deal",
    "sg:classifiers":[
        {
            "category":"Education",
            "subcategory":"Dance Studio",
            "type":"Public Place"
        }
    ],
    "sg:postcode":"CT14 6EG",
    "sg:province":"Kent",
    "sg:tags":[
        "school",
        "dancing"
    ],
    "wof:name":"Footsteps Dance Centre",
    "wof:placetype":"venue"
},
  "geometry": {"coordinates":[1.4032349586,51.2231292725],"type":"Point"}
}