{
  "type": "Feature",
  "properties": {
    "iso:country":"GB",
    "sg:address":"6 Hall Close",
    "sg:city":"Bedford",
    "sg:classifiers":[
        {
            "category":"Building & Trades",
            "subcategory":"Plumbing",
            "type":"Services"
        }
    ],
    "sg:postcode":"MK43 7DU",
    "sg:province":"Bedfordshire",
    "sg:tags":[
        "heating"
    ],
    "wof:name":"D T G Cook",
    "wof:placetype":"venue"
},
  "geometry": {"coordinates":[-0.604646,52.199677],"type":"Point"}
}