{
  "type": "Feature",
  "properties": {
    "iso:country":"GB",
    "sg:address":"Suite 129, Airport Ho, Purley Way",
    "sg:city":"Croydon",
    "sg:classifiers":[
        {
            "category":"Professional",
            "subcategory":"Employment Agencies",
            "type":"Services"
        }
    ],
    "sg:phone":"+44 20 8781 1912",
    "sg:postcode":"CR0 0XZ",
    "sg:province":"Surrey",
    "sg:tags":[
        "consultant"
    ],
    "wof:name":"Options Employment Ltd",
    "wof:placetype":"venue"
},
  "geometry": {"coordinates":[-0.01071,51.343342],"type":"Point"}
}