{
  "type": "Feature",
  "properties": {
    "addr:full":"3 Twyford Road Bishops Stortford Essex CM23 3JL",
    "addr:housenumber":"3",
    "addr:postcode":"cm23 3jl",
    "addr:street":"Twyford Road",
    "iso:country":"GB",
    "sg:address":"3 Twyford Road",
    "sg:city":"Bishops Stortford",
    "sg:classifiers":[
        {
            "category":"Home & Garden",
            "subcategory":"Home Furnishings",
            "type":"Retail Goods"
        }
    ],
    "sg:phone":"+44 1279 755501",
    "sg:postcode":"CM23 3JL",
    "sg:province":"Essex",
    "sg:tags":[
        "furnishers",
        "planner",
        "kitchen"
    ],
    "wof:name":"Naturally Wood (Kitchens) Ltd.",
    "wof:placetype":"venue"
},
  "geometry": {"coordinates":[0.1658010036,51.8606872559],"type":"Point"}
}