{
  "type": "Feature",
  "properties": {
    "iso:country":"GB",
    "sg:address":"118 Gelderd Road",
    "sg:city":"Halifax",
    "sg:classifiers":[
        {
            "category":"Building & Trades",
            "subcategory":"Construction",
            "type":"Services"
        }
    ],
    "sg:phone":"+44 113 263 6343",
    "sg:postcode":"LS12 6DE",
    "sg:province":"West Yorkshire",
    "sg:tags":[
        "builder"
    ],
    "wof:name":"Tarmac Building",
    "wof:placetype":"venue"
},
  "geometry": {"coordinates":[-1.5810199976,53.7807006836],"type":"Point"}
}