{
  "type": "Feature",
  "properties": {
    "addr:full":"Fern Cottage, Market Place Settle North Yorkshire BD24 9EJ",
    "addr:postcode":"bd24 9ej",
    "addr:street":"Market Place",
    "iso:country":"GB",
    "sg:address":"Fern Cottage, Market Place",
    "sg:city":"Settle",
    "sg:classifiers":[
        {
            "category":"Restaurant",
            "type":"Food & Drink"
        }
    ],
    "sg:phone":"+44 1729 822901",
    "sg:postcode":"BD24 9EJ",
    "sg:province":"North Yorkshire",
    "sg:tags":[
        "indian"
    ],
    "wof:name":"Golden Gate Two Indian Restaurant & Take Away",
    "wof:placetype":"venue"
},
  "geometry": {"coordinates":[-2.2776060104,54.0697593689],"type":"Point"}
}