{
  "type": "Feature",
  "properties": {
    "addr:full":"Lime Oaks, Setch Road, Blackborough End King's Lynn Norfolk PE32 1SL",
    "addr:postcode":"pe32 1sl",
    "addr:street":"Lime;Setch Road Blackborough End",
    "iso:country":"GB",
    "sg:address":"Lime Oaks, Setch Road, Blackborough End",
    "sg:city":"King's Lynn",
    "sg:classifiers":[
        {
            "category":"Professional",
            "subcategory":"Art Services",
            "type":"Services"
        },
        {
            "category":"Building & Trades",
            "subcategory":"Construction",
            "type":"Services"
        }
    ],
    "sg:phone":"+44 1553 842379",
    "sg:postcode":"PE32 1SL",
    "sg:province":"Norfolk",
    "sg:tags":[
        "decorator",
        "painter"
    ],
    "wof:name":"Griggs & Massen",
    "wof:placetype":"venue"
},
  "geometry": {"coordinates":[0.4602699876,52.7048187256],"type":"Point"}
}