{
  "type": "Feature",
  "properties": {
    "addr:full":"Unit 24, Verdin Exchange, High St Winsford Cheshire CW7 2AN",
    "addr:housenumber":"unit 24 verdin",
    "addr:postcode":"cw7 2an",
    "addr:street":"High St",
    "iso:country":"GB",
    "sg:address":"Unit 24, Verdin Exchange, High St",
    "sg:city":"Winsford",
    "sg:classifiers":[
        {
            "category":"Communications",
            "subcategory":"Newspaper",
            "type":"Services"
        }
    ],
    "sg:phone":"+44 1606 590154",
    "sg:postcode":"CW7 2AN",
    "sg:province":"Cheshire",
    "sg:tags":[
        "magazine"
    ],
    "wof:name":"Big Mag UK",
    "wof:placetype":"venue"
},
  "geometry": {"coordinates":[-2.5303459167,53.1918144226],"type":"Point"}
}