{
  "type": "Feature",
  "properties": {
    "iso:country":"GB",
    "sg:address":"61 Tat Bank Road, Oldbury",
    "sg:city":"Smethwick",
    "sg:classifiers":[
        {
            "category":"Cafe",
            "type":"Food & Drink"
        }
    ],
    "sg:phone":"+44 121 552 6599",
    "sg:postcode":"B69 4NJ",
    "sg:province":"West Midlands",
    "sg:tags":[
        "tea",
        "room"
    ],
    "wof:name":"The Green Olive",
    "wof:placetype":"venue"
},
  "geometry": {"coordinates":[-2.007259,52.497025],"type":"Point"}
}