{
  "type": "Feature",
  "properties": {
    "addr:full":"Hilton Road Ashford Kent TN23 1EW",
    "addr:postcode":"tn23 1ew",
    "addr:street":"Hilton Road",
    "iso:country":"GB",
    "sg:address":"Hilton Road",
    "sg:city":"Ashford",
    "sg:classifiers":[
        {
            "category":"Autos & Motor Vehicles",
            "subcategory":"Automobile Sales",
            "type":"Retail Goods"
        }
    ],
    "sg:phone":"+44 1233 648686",
    "sg:postcode":"TN23 1EW",
    "sg:province":"Kent",
    "sg:tags":[
        "car"
    ],
    "wof:name":"Motorline",
    "wof:placetype":"venue"
},
  "geometry": {"coordinates":[0.85495,51.151695],"type":"Point"}
}