{
  "type": "Feature",
  "properties": {
    "addr:full":"5 Revenge Road, Lordswood Industrial Estate Chatham Kent ME5 8UD",
    "addr:housenumber":"5",
    "addr:postcode":"me5 8ud",
    "addr:street":"Revenge Road Lordswood Industrial Estate",
    "iso:country":"GB",
    "sg:address":"5 Revenge Road, Lordswood Industrial Estate",
    "sg:city":"Chatham",
    "sg:classifiers":[
        {
            "category":"Shopping",
            "subcategory":"Computers & Home Electronics",
            "type":"Retail Goods"
        }
    ],
    "sg:phone":"+44 1634 660767",
    "sg:postcode":"ME5 8UD",
    "sg:province":"Kent",
    "sg:tags":[
        "electrical"
    ],
    "wof:name":"Medway Electrical Wholesalers Ltd.",
    "wof:placetype":"venue"
},
  "geometry": {"coordinates":[0.54125,51.330898],"type":"Point"}
}