{
  "type": "Feature",
  "properties": {
    "addr:full":"North Parade Llandudno Conwy LL30 2LP",
    "addr:postcode":"ll30 2lp",
    "addr:street":"North Parade",
    "iso:country":"GB",
    "sg:address":"North Parade",
    "sg:city":"Llandudno",
    "sg:classifiers":[
        {
            "category":"Travel",
            "subcategory":"Hotels & Motels",
            "type":"Entertainment"
        }
    ],
    "sg:phone":"+44 1492 875858",
    "sg:postcode":"LL30 2LP",
    "sg:province":"Conwy",
    "wof:name":"Baytree Hotel Promenade",
    "wof:placetype":"venue"
},
  "geometry": {"coordinates":[-3.830676,53.327862],"type":"Point"}
}