{
  "type": "Feature",
  "properties": {
    "iso:country":"GB",
    "sg:address":"38 Montpelier Crescent",
    "sg:city":"Brighton",
    "sg:classifiers":[
        {
            "category":"Military Area",
            "subcategory":"Air Force Base",
            "type":"Public Place"
        }
    ],
    "sg:phone":"+44 1273 204060",
    "sg:postcode":"BN1 3JL",
    "sg:province":"East Sussex",
    "sg:tags":[
        "taxi",
        "hire",
        "private"
    ],
    "wof:name":"Brighton & Hove Radio Cabs Ltd.",
    "wof:placetype":"venue"
},
  "geometry": {"coordinates":[-0.147845,50.830166],"type":"Point"}
}