{
  "type": "Feature",
  "properties": {
    "addr:full":"Coney Lane Keighley West Yorkshire BD21 5JE",
    "addr:postcode":"bd21 5je",
    "addr:street":"Coney Lane",
    "iso:country":"GB",
    "sg:address":"Coney Lane",
    "sg:city":"Keighley",
    "sg:classifiers":[
        {
            "category":"Autos & Motor Vehicles",
            "subcategory":"Automobile Sales",
            "type":"Retail Goods"
        }
    ],
    "sg:postcode":"BD21 5JE",
    "sg:province":"West Yorkshire",
    "sg:tags":[
        "car"
    ],
    "wof:name":"Sunwin Motors",
    "wof:placetype":"venue"
},
  "geometry": {"coordinates":[-1.905354023,53.8656044006],"type":"Point"}
}