{
  "type": "Feature",
  "properties": {
    "iso:country":"GB",
    "sg:address":"251 Ridgeway, Plympton",
    "sg:city":"Plymouth",
    "sg:classifiers":[
        {
            "category":"Autos & Motor Vehicles",
            "subcategory":"Fuel & Gas Station",
            "type":"Retail Goods"
        }
    ],
    "sg:phone":"+44 1752 340404",
    "sg:postcode":"PL7 1AJ",
    "sg:province":"Devon",
    "sg:tags":[
        "petrol",
        "filling"
    ],
    "wof:name":"Chaddlewood Service Station",
    "wof:placetype":"venue"
},
  "geometry": {"coordinates":[-4.0367021561,50.3840827942],"type":"Point"}
}