{
  "type": "Feature",
  "properties": {
    "addr:full":"108a South Street, Ponders End Enfield Greater London EN3 4QA",
    "addr:housenumber":"108a",
    "addr:postcode":"en3 4qa",
    "addr:street":"South Street Ponders End",
    "iso:country":"GB",
    "sg:address":"108a South Street, Ponders End",
    "sg:city":"Enfield",
    "sg:classifiers":[
        {
            "category":"Fast Food",
            "type":"Food & Drink"
        }
    ],
    "sg:postcode":"EN3 4QA",
    "sg:province":"Greater London",
    "sg:tags":[
        "away",
        "take"
    ],
    "wof:name":"Alma Cafe & Kebabs",
    "wof:placetype":"venue"
},
  "geometry": {"coordinates":[-0.0371729992,51.6427497864],"type":"Point"}
}