{
  "type": "Feature",
  "properties": {
    "addr:full":"1 Marine Parade, St Mawes Truro Cornwall TR2 5DW",
    "addr:housenumber":"1",
    "addr:postcode":"tr2 5dw",
    "addr:street":"Marine Parade",
    "iso:country":"GB",
    "sg:address":"1 Marine Parade, St Mawes",
    "sg:city":"Truro",
    "sg:classifiers":[
        {
            "category":"Real Estate",
            "subcategory":"Real Estate Agent",
            "type":"Services"
        }
    ],
    "sg:phone":"+44 1326 270744",
    "sg:postcode":"TR2 5DW",
    "sg:province":"Cornwall",
    "wof:name":"Millers",
    "wof:placetype":"venue"
},
  "geometry": {"coordinates":[-5.0164,50.157749],"type":"Point"}
}