{
  "type": "Feature",
  "properties": {
    "addr:full":"Arden St, New Mills High Peak Cheshire SK22 4NS",
    "addr:postcode":"sk22 4ns",
    "addr:street":"Arden St;Peak",
    "iso:country":"GB",
    "sg:address":"Arden St, New Mills",
    "sg:city":"High Peak",
    "sg:classifiers":[
        {
            "category":"Retail",
            "subcategory":"Auto Repair",
            "type":"Services"
        }
    ],
    "sg:phone":"+44 1663 747429",
    "sg:postcode":"SK22 4NS",
    "sg:province":"Cheshire",
    "sg:tags":[
        "modification",
        "garage"
    ],
    "wof:name":"Arden Street Autos",
    "wof:placetype":"venue"
},
  "geometry": {"coordinates":[-1.997495,53.36591],"type":"Point"}
}