{
  "type": "Feature",
  "properties": {
    "addr:full":"16 Creighton Av London Greater London N10 1NU",
    "addr:housenumber":"16",
    "addr:postcode":"n10 1nu",
    "addr:street":"Creighton Av",
    "iso:country":"GB",
    "sg:address":"16 Creighton Av",
    "sg:city":"London",
    "sg:classifiers":[
        {
            "category":"Professional",
            "subcategory":"Accounting & Tax Preparation",
            "type":"Services"
        }
    ],
    "sg:phone":"+44 20 8444 3692",
    "sg:postcode":"N10 1NU",
    "sg:province":"Greater London",
    "sg:tags":[
        "accountant"
    ],
    "wof:name":"Bookkeeping & Accountancy Services",
    "wof:placetype":"venue"
},
  "geometry": {"coordinates":[-0.1479039937,51.5953788757],"type":"Point"}
}