{
  "type": "Feature",
  "properties": {
    "addr:full":"319 New Cross Rd New Cross Greater London SE14 6AS",
    "addr:housenumber":"319",
    "addr:postcode":"se14 6as",
    "addr:street":"New Cross Rd New",
    "iso:country":"GB",
    "sg:address":"319 New Cross Rd",
    "sg:city":"New Cross",
    "sg:classifiers":[
        {
            "category":"Professional",
            "type":"Services"
        }
    ],
    "sg:phone":"+44 20 8692 7913",
    "sg:postcode":"SE14 6AS",
    "sg:province":"Greater London",
    "sg:tags":[
        "caterer"
    ],
    "wof:name":"Brincastle Ltd",
    "wof:placetype":"venue"
},
  "geometry": {"coordinates":[-0.037609,51.475677],"type":"Point"}
}