{
  "type": "Feature",
  "properties": {
    "iso:country":"GB",
    "sg:address":"3 Forsythia Close, Hedge End",
    "sg:city":"Southampton",
    "sg:classifiers":[
        {
            "category":"Shopping",
            "subcategory":"Computers & Home Electronics",
            "type":"Retail Goods"
        }
    ],
    "sg:phone":"+44 1489 789960",
    "sg:postcode":"SO30 4TP",
    "sg:province":"Hampshire",
    "sg:tags":[
        "aerial",
        "television",
        "radio"
    ],
    "wof:name":"Aerials by Alpha Aerials",
    "wof:placetype":"venue"
},
  "geometry": {"coordinates":[-1.3065090179,50.9188957214],"type":"Point"}
}