{
  "type": "Feature",
  "properties": {
    "iso:country":"GB",
    "sg:address":"69 Primrose Hill",
    "sg:city":"King's Langley",
    "sg:classifiers":[
        {
            "category":"Professional",
            "subcategory":"Computer Services",
            "type":"Services"
        }
    ],
    "sg:phone":"+44 1923 260134",
    "sg:postcode":"WD4 8HX",
    "sg:province":"Hertfordshire",
    "sg:tags":[
        "system",
        "software"
    ],
    "wof:name":"Standard Systems Ltd.",
    "wof:placetype":"venue"
},
  "geometry": {"coordinates":[-0.441531,51.715164],"type":"Point"}
}