{
  "type": "Feature",
  "properties": {
    "iso:country":"GB",
    "sg:address":"Gelderd Road",
    "sg:city":"Batley",
    "sg:classifiers":[
        {
            "category":"Building & Trades",
            "subcategory":"Construction",
            "type":"Services"
        }
    ],
    "sg:phone":"+44 1924 423223",
    "sg:postcode":"WF17 9LX",
    "sg:province":"West Yorkshire",
    "sg:tags":[
        "decorator",
        "painter"
    ],
    "wof:name":"W I Commercial Painters",
    "wof:placetype":"venue"
},
  "geometry": {"coordinates":[-1.642013,53.744965],"type":"Point"}
}