{
  "type": "Feature",
  "properties": {
    "iso:country":"GB",
    "sg:address":"Lye Cross Farm, Redhill",
    "sg:city":"Bristol",
    "sg:classifiers":[
        {
            "category":"Farming",
            "subcategory":"Dairy Farm",
            "type":"Manufacturing & Wholesale Goods"
        }
    ],
    "sg:phone":"+44 1934 862320",
    "sg:postcode":"BS40 5RH",
    "sg:province":"Somerset",
    "wof:name":"Alvis Brothers Ltd.",
    "wof:placetype":"venue"
},
  "geometry": {"coordinates":[-2.723039,51.363483],"type":"Point"}
}