{
  "type": "Feature",
  "properties": {
    "addr:full":"Aquila Drive, Heddon-on-the-wall Newcastle-upon-tyne Northumberland NE15 0BS",
    "addr:postcode":"ne15 0bs",
    "addr:street":"Aquila Drive",
    "iso:country":"GB",
    "sg:address":"Aquila Drive, Heddon-on-the-wall",
    "sg:city":"Newcastle-upon-tyne",
    "sg:classifiers":[
        {
            "category":"Real Estate",
            "subcategory":"Real Estate Services",
            "type":"Services"
        },
        {
            "category":"Shopping",
            "subcategory":"Books",
            "type":"Retail Goods"
        }
    ],
    "sg:phone":"+44 1661 852031",
    "sg:postcode":"NE15 0BS",
    "sg:province":"Northumberland",
    "sg:tags":[
        "building",
        "bookseller"
    ],
    "wof:name":"Ian Allan Building & Property Repairs",
    "wof:placetype":"venue"
},
  "geometry": {"coordinates":[-1.794768,54.997303],"type":"Point"}
}