{
  "type": "Feature",
  "properties": {
    "addr:full":"5/6 Garrick Buildings, Oxford Street Harrogate North Yorkshire HG1 1QE",
    "addr:housenumber":"5 / 6",
    "addr:postcode":"hg1 1qe",
    "addr:street":"Garrick Buildings Oxford Street",
    "iso:country":"GB",
    "sg:address":"5/6 Garrick Buildings, Oxford Street",
    "sg:city":"Harrogate",
    "sg:classifiers":[
        {
            "category":"Shopping",
            "subcategory":"News",
            "type":"Retail Goods"
        }
    ],
    "sg:phone":"+44 1423 540390",
    "sg:postcode":"HG1 1QE",
    "sg:province":"North Yorkshire",
    "sg:tags":[
        "newsagent"
    ],
    "wof:name":"A R News Ltd.",
    "wof:placetype":"venue"
},
  "geometry": {"coordinates":[-1.5445239544,53.9946899414],"type":"Point"}
}