{
  "type": "Feature",
  "properties": {
    "iso:country":"GB",
    "sg:address":"Grampian Road",
    "sg:city":"Aviemore",
    "sg:classifiers":[
        {
            "category":"Personal",
            "subcategory":"Beauty Salon",
            "type":"Services"
        }
    ],
    "sg:phone":"+44 1479 811782",
    "sg:postcode":"PH22 1RH",
    "sg:province":"Highland",
    "sg:tags":[
        "unisex",
        "hairdresser"
    ],
    "wof:name":"la-Boheme",
    "wof:placetype":"venue"
},
  "geometry": {"coordinates":[-3.829109,57.194675],"type":"Point"}
}