{
  "type": "Feature",
  "properties": {
    "iso:country":"GB",
    "sg:address":"80 Town Street, Earlsheaton",
    "sg:city":"Dewsbury",
    "sg:classifiers":[
        {
            "category":"Social Services",
            "subcategory":"Child Care",
            "type":"Services"
        },
        {
            "category":"Retail",
            "subcategory":"Repair Shop",
            "type":"Services"
        }
    ],
    "sg:phone":"+44 1924 450999",
    "sg:postcode":"WF12 8JL",
    "sg:province":"West Yorkshire",
    "sg:tags":[
        "television",
        "good",
        "video",
        "servicing",
        "maintenance",
        "radio"
    ],
    "wof:name":"Malcolms",
    "wof:placetype":"venue"
},
  "geometry": {"coordinates":[-1.613122,53.686329],"type":"Point"}
}