{
  "type": "Feature",
  "properties": {
    "iso:country":"GB",
    "sg:address":"Devils Lane, Thorpe Lea",
    "sg:city":"Egham",
    "sg:classifiers":[
        {
            "category":"Social Services",
            "type":"Services"
        }
    ],
    "sg:phone":"+44 1784 451258",
    "sg:postcode":"TW20 8HF",
    "sg:province":"Surrey",
    "sg:tags":[
        "disability"
    ],
    "wof:name":"C F Hewerdine Ltd",
    "wof:placetype":"venue"
},
  "geometry": {"coordinates":[-0.536077,51.406357],"type":"Point"}
}