{
  "type": "Feature",
  "properties": {
    "addr:full":"139 Longden Coleham Shrewsbury Shropshire SY3 7DN",
    "addr:housenumber":"139",
    "addr:postcode":"sy3 7dn",
    "addr:street":"Longden Coleham",
    "iso:country":"GB",
    "sg:address":"139 Longden Coleham",
    "sg:city":"Shrewsbury",
    "sg:classifiers":[
        {
            "category":"Professional",
            "subcategory":"Engineering",
            "type":"Services"
        },
        {
            "category":"Home & Garden",
            "subcategory":"Hardware",
            "type":"Retail Goods"
        }
    ],
    "sg:postcode":"SY3 7DN",
    "sg:province":"Shropshire",
    "sg:tags":[
        "engineer",
        "lighting",
        "electrical",
        "retailer",
        "contractor"
    ],
    "wof:name":"The Lighthouse",
    "wof:placetype":"venue"
},
  "geometry": {"coordinates":[-2.7463469505,52.7046470642],"type":"Point"}
}