{
  "type": "Feature",
  "properties": {
    "iso:country":"GB",
    "sg:address":"479 Smithdown Road",
    "sg:city":"Liverpool",
    "sg:classifiers":[
        {
            "category":"Shopping",
            "subcategory":"Computers & Home Electronics",
            "type":"Retail Goods"
        },
        {
            "category":"Communications",
            "type":"Services"
        }
    ],
    "sg:phone":"+44 151 733 8687",
    "sg:postcode":"L15 5AE",
    "sg:province":"Merseyside",
    "sg:tags":[
        "tv",
        "video",
        "television",
        "aerial",
        "radio"
    ],
    "wof:name":"A & J Aerials",
    "wof:placetype":"venue"
},
  "geometry": {"coordinates":[-2.926194,53.38987],"type":"Point"}
}