{
  "type": "Feature",
  "properties": {
    "addr:full":"High Street Kirkcudbright Dumfries and Galloway DG6 4JL",
    "addr:postcode":"dg6 4jl",
    "addr:street":"High Street",
    "iso:country":"GB",
    "sg:address":"High Street",
    "sg:city":"Kirkcudbright",
    "sg:classifiers":[
        {
            "category":"Arts & Performance",
            "subcategory":"Art Gallery",
            "type":"Entertainment"
        },
        {
            "category":"Museum",
            "subcategory":"Art Museum",
            "type":"Entertainment"
        }
    ],
    "sg:phone":"+44 1557 331556",
    "sg:postcode":"DG6 4JL",
    "sg:province":"Dumfries and Galloway",
    "wof:name":"Tolbooth Art Centre",
    "wof:placetype":"venue"
},
  "geometry": {"coordinates":[-4.054079,54.837078],"type":"Point"}
}