{
  "type": "Feature",
  "properties": {
    "iso:country":"GB",
    "sg:address":"Creswell House, Field Way, Heath",
    "sg:city":"Cardiff",
    "sg:classifiers":[
        {
            "category":"Professional",
            "subcategory":"Business Services",
            "type":"Services"
        },
        {
            "category":"Building & Trades",
            "subcategory":"Construction",
            "type":"Services"
        }
    ],
    "sg:postcode":"CF14 4UH",
    "sg:province":"Cardiff",
    "sg:tags":[
        "builder",
        "holding"
    ],
    "wof:name":"Knox & Wells Holdings Ltd.",
    "wof:placetype":"venue"
},
  "geometry": {"coordinates":[-3.195939064,51.5206069946],"type":"Point"}
}