{
  "type": "Feature",
  "properties": {
    "iso:country":"GB",
    "sg:address":"1-3 Catsley Place",
    "sg:city":"Bath",
    "sg:classifiers":[
        {
            "category":"Bars & Pubs",
            "type":"Food & Drink"
        },
        {
            "category":"Community Center",
            "subcategory":"Social",
            "type":"Public Place"
        }
    ],
    "sg:phone":"+44 1225 423177",
    "sg:postcode":"BA1 6TA",
    "sg:province":"Bath and North East Somerset",
    "sg:tags":[
        "pubs",
        "house",
        "inn",
        "activity"
    ],
    "wof:name":"BLADUDS HEAD",
    "wof:placetype":"venue"
},
  "geometry": {"coordinates":[-2.343919,51.40152],"type":"Point"}
}