{
  "type": "Feature",
  "properties": {
    "addr:full":"29 Southfield Park York East Riding of Yorkshire YO4 3QL",
    "addr:housenumber":"29",
    "addr:postcode":"yo4 3ql",
    "addr:street":"Southfield Park",
    "iso:country":"GB",
    "sg:address":"29 Southfield Park",
    "sg:city":"York",
    "sg:classifiers":[
        {
            "category":"Government",
            "subcategory":"Post Office",
            "type":"Public Place"
        }
    ],
    "sg:phone":"+44 1430 871701",
    "sg:postcode":"YO4 3QL",
    "sg:province":"East Riding of Yorkshire",
    "sg:tags":[
        "print",
        "typesetter"
    ],
    "wof:name":"X Y Z",
    "wof:placetype":"venue"
},
  "geometry": {"coordinates":[-0.6650969982,53.8616981506],"type":"Point"}
}