{
  "type": "Feature",
  "properties": {
    "iso:country":"GB",
    "sg:address":"6 Woodburn Road",
    "sg:city":"Dalkeith",
    "sg:classifiers":[
        {
            "category":"Government",
            "subcategory":"Office",
            "type":"Public Place"
        }
    ],
    "sg:phone":"+44 131 654 1899",
    "sg:postcode":"EH22 2AP",
    "sg:province":"City of Edinburgh",
    "sg:tags":[
        "education",
        "agency",
        "authority"
    ],
    "wof:name":"Midlothian Council",
    "wof:placetype":"venue"
},
  "geometry": {"coordinates":[-3.054089,55.891472],"type":"Point"}
}