{
  "type": "Feature",
  "properties": {
    "addr:full":"1 Green St Eastbourne East Sussex BN21 1QN",
    "addr:housenumber":"1",
    "addr:postcode":"bn21 1qn",
    "addr:street":"Green St",
    "iso:country":"GB",
    "sg:address":"1 Green St",
    "sg:city":"Eastbourne",
    "sg:classifiers":[
        {
            "category":"Professional",
            "subcategory":"Business Services",
            "type":"Services"
        }
    ],
    "sg:phone":"+44 1323 431833",
    "sg:postcode":"BN21 1QN",
    "sg:province":"East Sussex",
    "sg:tags":[
        "distribution"
    ],
    "wof:name":"Clearfrate Ltd",
    "wof:placetype":"venue"
},
  "geometry": {"coordinates":[0.2615199983,50.7728729248],"type":"Point"}
}