{
  "type": "Feature",
  "properties": {
    "addr:full":"2 Victoria Arcade London Greater London SW1E 5ND",
    "addr:housenumber":"2",
    "addr:postcode":"sw1e 5nd",
    "addr:street":"Victoria Arcade",
    "iso:country":"GB",
    "sg:address":"2 Victoria Arcade",
    "sg:city":"London",
    "sg:classifiers":[
        {
            "category":"Banks & Credit Unions",
            "subcategory":"Bureau De Change",
            "type":"Services"
        }
    ],
    "sg:phone":"+44 20 7931 9090",
    "sg:postcode":"SW1E 5ND",
    "sg:province":"Greater London",
    "wof:name":"Link F X Plc",
    "wof:placetype":"venue"
},
  "geometry": {"coordinates":[-0.1436039954,51.4962654114],"type":"Point"}
}