{
  "type": "Feature",
  "properties": {
    "iso:country":"GB",
    "sg:address":"40 Tolcarne St",
    "sg:city":"Camborne",
    "sg:classifiers":[
        {
            "category":"Building & Trades",
            "subcategory":"Construction",
            "type":"Services"
        }
    ],
    "sg:phone":"+44 1209 716151",
    "sg:postcode":"TR14 8JH",
    "sg:province":"Cornwall",
    "sg:tags":[
        "builder"
    ],
    "wof:name":"Peter Pearce",
    "wof:placetype":"venue"
},
  "geometry": {"coordinates":[-5.2970609665,50.2127113342],"type":"Point"}
}