{
  "type": "Feature",
  "properties": {
    "addr:full":"110 Station Road, Hednesford Cannock Staffordshire WS12 4DN",
    "addr:housenumber":"110",
    "addr:postcode":"ws12 4dn",
    "addr:street":"Station Road",
    "iso:country":"GB",
    "sg:address":"110 Station Road, Hednesford",
    "sg:city":"Cannock",
    "sg:classifiers":[
        {
            "category":"Food & Beverages",
            "subcategory":"Meat & Fish",
            "type":"Retail Goods"
        }
    ],
    "sg:phone":"+44 1543 422633",
    "sg:postcode":"WS12 4DN",
    "sg:province":"Staffordshire",
    "sg:tags":[
        "chip"
    ],
    "wof:name":"Station Road Fish & Chip Shop",
    "wof:placetype":"venue"
},
  "geometry": {"coordinates":[-1.9980759621,52.714302063],"type":"Point"}
}