{
  "type": "Feature",
  "properties": {
    "iso:country":"GB",
    "sg:address":"49 Erdington Rd",
    "sg:city":"Blackpool",
    "sg:classifiers":[
        {
            "category":"Professional",
            "subcategory":"Engineering",
            "type":"Services"
        }
    ],
    "sg:phone":"+44 1253 624708",
    "sg:postcode":"FY1 5EH",
    "sg:province":"Lancashire",
    "sg:tags":[
        "contractor",
        "electrical",
        "engineer"
    ],
    "wof:name":"Ainsworths Electrical",
    "wof:placetype":"venue"
},
  "geometry": {"coordinates":[-3.047999,53.80991],"type":"Point"}
}