{
  "type": "Feature",
  "properties": {
    "iso:country":"GB",
    "sg:address":"44 Seafield Road",
    "sg:city":"Blackpool",
    "sg:classifiers":[
        {
            "category":"Travel",
            "subcategory":"Hotels & Motels",
            "type":"Entertainment"
        }
    ],
    "sg:postcode":"FY1 2LS",
    "sg:province":"Lancashire",
    "wof:name":"Storeyville Hotel",
    "wof:placetype":"venue"
},
  "geometry": {"coordinates":[-3.0508880615,53.8328018188],"type":"Point"}
}