{
  "type": "Feature",
  "properties": {
    "iso:country":"GB",
    "sg:address":"100 Belgrave Road",
    "sg:city":"Torquay",
    "sg:classifiers":[
        {
            "category":"Shopping",
            "subcategory":"Bicycles & Sporting Goods",
            "type":"Retail Goods"
        }
    ],
    "sg:phone":"+44 1803 200024",
    "sg:postcode":"TQ2 5HZ",
    "sg:province":"Devon",
    "sg:tags":[
        "cycle",
        "accessory"
    ],
    "wof:name":"Simply the Bike Ltd.",
    "wof:placetype":"venue"
},
  "geometry": {"coordinates":[-3.540509,50.468796],"type":"Point"}
}