{
  "type": "Feature",
  "properties": {
    "addr:full":"145 Harwood Street Darwen Lancashire BB3 1JD",
    "addr:housenumber":"145",
    "addr:postcode":"bb3 1jd",
    "addr:street":"Harwood Street",
    "iso:country":"GB",
    "sg:address":"145 Harwood Street",
    "sg:city":"Darwen",
    "sg:classifiers":[
        {
            "category":"Home & Garden",
            "subcategory":"Home Furnishings",
            "type":"Retail Goods"
        },
        {
            "category":"Building & Trades",
            "subcategory":"Construction",
            "type":"Services"
        },
        {
            "category":"Home & Garden",
            "subcategory":"Carpets & Floor Coverings",
            "type":"Retail Goods"
        }
    ],
    "sg:phone":"+44 1254 704769",
    "sg:postcode":"BB3 1JD",
    "sg:province":"Lancashire",
    "sg:tags":[
        "rug",
        "contractor",
        "fitting",
        "tiling",
        "matting",
        "carpets"
    ],
    "wof:name":"P S W Preston",
    "wof:placetype":"venue"
},
  "geometry": {"coordinates":[-2.482192,53.701935],"type":"Point"}
}