{
  "type": "Feature",
  "properties": {
    "iso:country":"GB",
    "sg:address":"31 Kirton Way, Houghton Regis",
    "sg:city":"Dunstable",
    "sg:classifiers":[
        {
            "category":"Building & Trades",
            "subcategory":"Construction",
            "type":"Services"
        }
    ],
    "sg:phone":"+44 1582 863867",
    "sg:postcode":"LU5 5PZ",
    "sg:province":"Bedfordshire",
    "sg:tags":[
        "joiner",
        "carpenter"
    ],
    "wof:name":"G T Carpentry",
    "wof:placetype":"venue"
},
  "geometry": {"coordinates":[-0.498189,51.911083],"type":"Point"}
}