{
  "type": "Feature",
  "properties": {
    "addr:full":"Unit 6 Adco Business Centre, Plantation Side Nottingham Nottinghamshire NG7 5NR",
    "addr:housenumber":"unit 6",
    "addr:postcode":"ng7 5nr",
    "addr:street":"Adco Business Centre",
    "iso:country":"GB",
    "sg:address":"Unit 6 Adco Business Centre, Plantation Side",
    "sg:city":"Nottingham",
    "sg:classifiers":[
        {
            "category":"Shopping",
            "subcategory":"Stationery & Office Supplies",
            "type":"Retail Goods"
        }
    ],
    "sg:phone":"+44 115 970 0012",
    "sg:postcode":"NG7 5NR",
    "sg:province":"Nottinghamshire",
    "wof:name":"N B Office Supplies",
    "wof:placetype":"venue"
},
  "geometry": {"coordinates":[-1.17935,52.9683],"type":"Point"}
}