{
  "type": "Feature",
  "properties": {
    "iso:country":"GB",
    "sg:address":"Stithians Lake, Menherion",
    "sg:city":"Redruth",
    "sg:classifiers":[
        {
            "category":"Bars & Pubs",
            "type":"Food & Drink"
        }
    ],
    "sg:phone":"+44 1209 860332",
    "sg:postcode":"TR16 6NW",
    "sg:province":"Cornwall",
    "sg:tags":[
        "pubs",
        "inn"
    ],
    "wof:name":"The Golden Lion",
    "wof:placetype":"venue"
},
  "geometry": {"coordinates":[-5.2161841393,50.1841011047],"type":"Point"}
}