{
  "type": "Feature",
  "properties": {
    "addr:full":"Rocklyn Pentraeth Isle of Anglesey LL75 8YG",
    "addr:postcode":"ll75 8yg",
    "addr:street":"Pentraeth",
    "iso:country":"GB",
    "sg:address":"Rocklyn",
    "sg:city":"Pentraeth",
    "sg:classifiers":[
        {
            "category":"Building & Trades",
            "subcategory":"Equipment Rental",
            "type":"Services"
        },
        {
            "category":"Building & Trades",
            "subcategory":"Construction",
            "type":"Services"
        }
    ],
    "sg:phone":"+44 1248 450869",
    "sg:postcode":"LL75 8YG",
    "sg:province":"Isle of Anglesey",
    "sg:tags":[
        "plant",
        "machinery"
    ],
    "wof:name":"Rocklyn Plant Hire",
    "wof:placetype":"venue"
},
  "geometry": {"coordinates":[-4.2174677849,53.2860336304],"type":"Point"}
}