{
  "type": "Feature",
  "properties": {
    "addr:full":"4 Bullbrook Row Bracknell Berkshire RG12 2NL",
    "addr:housenumber":"4",
    "addr:postcode":"rg12 2nl",
    "addr:street":"Bullbrook Row",
    "iso:country":"GB",
    "sg:address":"4 Bullbrook Row",
    "sg:city":"Bracknell",
    "sg:classifiers":[
        {
            "category":"Shopping",
            "subcategory":"News",
            "type":"Retail Goods"
        }
    ],
    "sg:phone":"+44 1344 483683",
    "sg:postcode":"RG12 2NL",
    "sg:province":"Berkshire",
    "sg:tags":[
        "newsagent"
    ],
    "wof:name":"Balfour News",
    "wof:placetype":"venue"
},
  "geometry": {"coordinates":[-0.7349079847,51.4191207886],"type":"Point"}
}