{
  "type": "Feature",
  "properties": {
    "addr:full":"Old Towns Yard, Every St Bury Lancashire BL9 5BE",
    "addr:postcode":"bl9 5be",
    "addr:street":"Old;Every St",
    "iso:country":"GB",
    "sg:address":"Old Towns Yard, Every St",
    "sg:city":"Bury",
    "sg:classifiers":[
        {
            "category":"Wholesale",
            "subcategory":"Scrap",
            "type":"Manufacturing & Wholesale Goods"
        }
    ],
    "sg:phone":"+44 161 763 5406",
    "sg:postcode":"BL9 5BE",
    "sg:province":"Lancashire",
    "sg:tags":[
        "salvage"
    ],
    "wof:name":"J T J Salvage",
    "wof:placetype":"venue"
},
  "geometry": {"coordinates":[-2.3010540009,53.5897331238],"type":"Point"}
}