{
  "type": "Feature",
  "properties": {
    "addr:full":"232 Gourlay Street Glasgow East Dunbartonshire G21 1EJ",
    "addr:housenumber":"232",
    "addr:postcode":"g21 1ej",
    "addr:street":"Gourlay Street",
    "iso:country":"GB",
    "sg:address":"232 Gourlay Street",
    "sg:city":"Glasgow",
    "sg:classifiers":[
        {
            "category":"Social Services",
            "subcategory":"Retirement Home",
            "type":"Services"
        },
        {
            "category":"Organizations",
            "subcategory":"Community Association",
            "type":"Services"
        }
    ],
    "sg:phone":"+44 141 557 1584",
    "sg:postcode":"G21 1EJ",
    "sg:province":"East Dunbartonshire",
    "sg:tags":[
        "society",
        "housing",
        "sheltered",
        "accommodation"
    ],
    "wof:name":"West Of Scotland Housing Association Ltd",
    "wof:placetype":"venue"
},
  "geometry": {"coordinates":[-4.242002,55.87952],"type":"Point"}
}