{
  "type": "Feature",
  "properties": {
    "iso:country":"GB",
    "sg:address":"60b High Street",
    "sg:city":"South Ockendon",
    "sg:classifiers":[
        {
            "category":"Taxi",
            "type":"Transportation"
        },
        {
            "category":"Military Area",
            "subcategory":"Air Force Base",
            "type":"Public Place"
        }
    ],
    "sg:phone":"+44 1708 853249",
    "sg:postcode":"RM15 4BX",
    "sg:province":"Essex",
    "sg:tags":[
        "mini",
        "hire",
        "private",
        "cab"
    ],
    "wof:name":"Target Cars",
    "wof:placetype":"venue"
},
  "geometry": {"coordinates":[0.25617,51.498684],"type":"Point"}
}