{
  "type": "Feature",
  "properties": {
    "addr:full":"Kirkwynd Forfar Angus DD8 1RT",
    "addr:postcode":"dd8 1rt",
    "iso:country":"GB",
    "sg:address":"Kirkwynd",
    "sg:city":"Forfar",
    "sg:classifiers":[
        {
            "category":"Museum",
            "subcategory":"Art Museum",
            "type":"Entertainment"
        }
    ],
    "sg:phone":"+44 1307 840288",
    "sg:postcode":"DD8 1RT",
    "sg:province":"Angus",
    "sg:tags":[
        "gallery"
    ],
    "wof:name":"Angus Folk Museum",
    "wof:placetype":"venue"
},
  "geometry": {"coordinates":[-3.0026540756,56.6096000671],"type":"Point"}
}