{
  "type": "Feature",
  "properties": {
    "iso:country":"GB",
    "sg:address":"37 Firs Drive",
    "sg:city":"Hounslow",
    "sg:classifiers":[
        {
            "category":"Retail",
            "subcategory":"Driving School",
            "type":"Services"
        }
    ],
    "sg:phone":"+44 20 8384 0863",
    "sg:postcode":"TW5 9TA",
    "sg:province":"Greater London",
    "wof:name":"Gill School of Motoring",
    "wof:placetype":"venue"
},
  "geometry": {"coordinates":[-0.407258,51.481117],"type":"Point"}
}