{
  "type": "Feature",
  "properties": {
    "iso:country":"GB",
    "sg:address":"Units 22-23 In Shops, Aberdeen Market",
    "sg:city":"Aberdeen",
    "sg:classifiers":[
        {
            "category":"Shopping",
            "subcategory":"Clothing, Apparel, & Fashions",
            "type":"Retail Goods"
        }
    ],
    "sg:phone":"+44 1224 211908",
    "sg:postcode":"AB11 5PA",
    "sg:province":"Aberdeen City",
    "sg:tags":[
        "shop"
    ],
    "wof:name":"Depot Discount Clothing",
    "wof:placetype":"venue"
},
  "geometry": {"coordinates":[-2.09734,57.14653],"type":"Point"}
}