{
  "type": "Feature",
  "properties": {
    "addr:full":"Higher Walton Road, Walton Le Dale Preston Lancashire PR5 4HD",
    "addr:postcode":"pr5 4hd",
    "addr:street":"Higher Walton Road",
    "iso:country":"GB",
    "sg:address":"Higher Walton Road, Walton Le Dale",
    "sg:city":"Preston",
    "sg:classifiers":[
        {
            "category":"Place Of Worship",
            "type":"Public Place"
        }
    ],
    "sg:phone":"+44 1772 253709",
    "sg:postcode":"PR5 4HD",
    "sg:province":"Lancashire",
    "wof:name":"Our Lady & St Patrick'S R C Church",
    "wof:placetype":"venue"
},
  "geometry": {"coordinates":[-2.645204,53.743851],"type":"Point"}
}