{
  "type": "Feature",
  "properties": {
    "addr:full":"Everett Hall, Everett St Hartlepool Durham TS26 0JA",
    "addr:postcode":"ts26 0ja",
    "addr:street":"Everett St",
    "iso:country":"GB",
    "sg:address":"Everett Hall, Everett St",
    "sg:city":"Hartlepool",
    "sg:classifiers":[
        {
            "category":"Education",
            "subcategory":"Dance Studio",
            "type":"Public Place"
        }
    ],
    "sg:phone":"+44 1429 233923",
    "sg:postcode":"TS26 0JA",
    "sg:province":"Durham",
    "sg:tags":[
        "school",
        "dancing"
    ],
    "wof:name":"Carol Hammond",
    "wof:placetype":"venue"
},
  "geometry": {"coordinates":[-1.2300200462,54.6922683716],"type":"Point"}
}