{
  "type": "Feature",
  "properties": {
    "addr:full":"21 Alford Road High Wycombe Buckinghamshire HP12 4PT",
    "addr:housenumber":"21",
    "addr:postcode":"hp12 4pt",
    "addr:street":"Alford Road",
    "iso:country":"GB",
    "sg:address":"21 Alford Road",
    "sg:city":"High Wycombe",
    "sg:classifiers":[
        {
            "category":"Home & Garden",
            "subcategory":"Kitchen Supply",
            "type":"Retail Goods"
        }
    ],
    "sg:phone":"+44 1494 639736",
    "sg:postcode":"HP12 4PT",
    "sg:province":"Buckinghamshire",
    "sg:tags":[
        "equipment",
        "catering"
    ],
    "wof:name":"Catering Needs Ltd.",
    "wof:placetype":"venue"
},
  "geometry": {"coordinates":[-0.78545,51.613068],"type":"Point"}
}