{
  "type": "Feature",
  "properties": {
    "iso:country":"GB",
    "sg:address":"Unit 11 Parrs Corner, Stanley Road",
    "sg:city":"Bootle",
    "sg:classifiers":[
        {
            "category":"Manufacturing",
            "subcategory":"Signs",
            "type":"Manufacturing & Wholesale Goods"
        }
    ],
    "sg:phone":"+44 151 933 2906",
    "sg:postcode":"L20 5EX",
    "sg:province":"Merseyside",
    "sg:tags":[
        "writer"
    ],
    "wof:name":"Graffiti Signs",
    "wof:placetype":"venue"
},
  "geometry": {"coordinates":[-2.986464,53.455811],"type":"Point"}
}