{
  "type": "Feature",
  "properties": {
    "iso:country":"GB",
    "sg:address":"Coombe Avenue, Coombe Road",
    "sg:city":"Croydon",
    "sg:classifiers":[
        {
            "category":"Building & Trades",
            "subcategory":"Construction",
            "type":"Services"
        }
    ],
    "sg:phone":"+44 20 8681 0140",
    "sg:postcode":"CR0 5SD",
    "sg:province":"Surrey",
    "sg:tags":[
        "builder"
    ],
    "wof:name":"Pearce & Gough Ltd.",
    "wof:placetype":"venue"
},
  "geometry": {"coordinates":[-0.084944,51.365356],"type":"Point"}
}