{
  "type": "Feature",
  "properties": {
    "addr:full":"The Deanery Ho, Chapel Rd Southampton Hampshire SO14 5GL",
    "addr:postcode":"so14 5gl",
    "addr:street":"Chapel Rd",
    "iso:country":"GB",
    "sg:address":"The Deanery Ho, Chapel Rd",
    "sg:city":"Southampton",
    "sg:classifiers":[
        {
            "category":"Government",
            "subcategory":"Office",
            "type":"Public Place"
        }
    ],
    "sg:phone":"+44 23 8022 8480",
    "sg:postcode":"SO14 5GL",
    "sg:province":"Hampshire",
    "sg:tags":[
        "education",
        "agency",
        "authority"
    ],
    "wof:name":"Southampton R E Resources Centre",
    "wof:placetype":"venue"
},
  "geometry": {"coordinates":[-1.39215,50.90218],"type":"Point"}
}