{
  "type": "Feature",
  "properties": {
    "iso:country":"GB",
    "sg:address":"The Innes Building, 11-13 The Square",
    "sg:city":"Hessle",
    "sg:classifiers":[
        {
            "category":"Communications",
            "type":"Services"
        }
    ],
    "sg:phone":"+44 1482 627193",
    "sg:postcode":"HU13 0AF",
    "sg:province":"East Riding of Yorkshire",
    "sg:tags":[
        "audio-visual"
    ],
    "wof:name":"Forest Edge Films",
    "wof:placetype":"venue"
},
  "geometry": {"coordinates":[-0.4497089982,53.72423172],"type":"Point"}
}