{
  "type": "Feature",
  "properties": {
    "iso:country":"GB",
    "sg:address":"8 Relclaimed Ground, Harbour Rd",
    "sg:city":"Fraserburgh",
    "sg:classifiers":[
        {
            "category":"Food & Beverages",
            "subcategory":"Meat & Fish",
            "type":"Retail Goods"
        }
    ],
    "sg:postcode":"AB43 9TD",
    "sg:province":"Aberdeenshire",
    "sg:tags":[
        "merchant"
    ],
    "wof:name":"Viper Seafoods",
    "wof:placetype":"venue"
},
  "geometry": {"coordinates":[-2.0158441067,57.6944198608],"type":"Point"}
}