{
  "type": "Feature",
  "properties": {
    "iso:country":"GB",
    "sg:address":"Fieldhead, Calthwaite",
    "sg:city":"Penrith",
    "sg:classifiers":[
        {
            "category":"Wholesale",
            "subcategory":"Metals & Minerals",
            "type":"Manufacturing & Wholesale Goods"
        },
        {
            "category":"Building & Trades",
            "subcategory":"Construction",
            "type":"Services"
        }
    ],
    "sg:phone":"+44 1768 885237",
    "sg:postcode":"CA11 9PU",
    "sg:province":"Cumbria",
    "sg:tags":[
        "joinery",
        "sheet",
        "fabricator"
    ],
    "wof:name":"D & M Porter Ltd.",
    "wof:placetype":"venue"
},
  "geometry": {"coordinates":[-2.826264,54.753235],"type":"Point"}
}