{
  "type": "Feature",
  "properties": {
    "iso:country":"GB",
    "sg:address":"The Street",
    "sg:city":"Ashford",
    "sg:classifiers":[
        {
            "category":"Shopping",
            "subcategory":"Department Store",
            "type":"Retail Goods"
        }
    ],
    "sg:phone":"+44 1233 750338",
    "sg:postcode":"TN25 5HU",
    "sg:province":"Kent",
    "wof:name":"Hastingleigh Stores",
    "wof:placetype":"venue"
},
  "geometry": {"coordinates":[0.9659900069,51.1665458679],"type":"Point"}
}