{
  "type": "Feature",
  "properties": {
    "addr:full":"104 Beacon Road Bradford West Yorkshire BD6 3EU",
    "addr:housenumber":"104",
    "addr:postcode":"bd6 3eu",
    "addr:street":"Beacon Road",
    "iso:country":"GB",
    "sg:address":"104 Beacon Road",
    "sg:city":"Bradford",
    "sg:classifiers":[
        {
            "category":"Professional",
            "type":"Services"
        }
    ],
    "sg:phone":"+44 1274 677443",
    "sg:postcode":"BD6 3EU",
    "sg:province":"West Yorkshire",
    "sg:tags":[
        "caterer"
    ],
    "sg:website":"http://www.salcater.co.uk",
    "wof:name":"S A Leyland",
    "wof:placetype":"venue"
},
  "geometry": {"coordinates":[-1.787329,53.768688],"type":"Point"}
}