{
  "type": "Feature",
  "properties": {
    "addr:full":"Unit 7, Broomsleigh Business Park, Worsley Bridge Rd, Sydenham Sydenham Greater London SE26 5BN",
    "addr:housenumber":"unit 7",
    "addr:postcode":"se26 5bn",
    "addr:street":"Broomsleigh Business Park Worsley Bridge Rd",
    "iso:country":"GB",
    "sg:address":"Unit 7, Broomsleigh Business Park, Worsley Bridge Rd, Sydenham",
    "sg:city":"Sydenham",
    "sg:classifiers":[
        {
            "category":"Building & Trades",
            "subcategory":"Cleaning & Sanitation",
            "type":"Services"
        }
    ],
    "sg:phone":"+44 20 8778 9694",
    "sg:postcode":"SE26 5BN",
    "sg:province":"Greater London",
    "sg:tags":[
        "asbestos",
        "removal"
    ],
    "wof:name":"Shepherds Asbestos Removals Ltd",
    "wof:placetype":"venue"
},
  "geometry": {"coordinates":[-0.03189,51.427811],"type":"Point"}
}