{
  "type": "Feature",
  "properties": {
    "iso:country":"GB",
    "sg:address":"17-21 Victoria Road",
    "sg:city":"Swindon",
    "sg:classifiers":[
        {
            "category":"Wholesale",
            "subcategory":"Machinery & Supplies",
            "type":"Manufacturing & Wholesale Goods"
        }
    ],
    "sg:phone":"+44 1793 491717",
    "sg:postcode":"SN1 3AW",
    "sg:province":"Wiltshire",
    "sg:tags":[
        "industrial",
        "commercial"
    ],
    "wof:name":"Machine Mart",
    "wof:placetype":"venue"
},
  "geometry": {"coordinates":[-1.778908968,51.5567703247],"type":"Point"}
}