{
  "type": "Feature",
  "properties": {
    "addr:full":"13 Commercial St Camborne Cornwall TR14 8JZ",
    "addr:housenumber":"13",
    "addr:postcode":"tr14 8jz",
    "addr:street":"Commercial St",
    "iso:country":"GB",
    "sg:address":"13 Commercial St",
    "sg:city":"Camborne",
    "sg:classifiers":[
        {
            "category":"Shopping",
            "subcategory":"Shoes",
            "type":"Retail Goods"
        }
    ],
    "sg:phone":"+44 1209 719970",
    "sg:postcode":"TR14 8JZ",
    "sg:province":"Cornwall",
    "wof:name":"South West Key And Security",
    "wof:placetype":"venue"
},
  "geometry": {"coordinates":[-5.301076889,50.2132263184],"type":"Point"}
}