{
  "type": "Feature",
  "properties": {
    "addr:full":"8 Murrayburn Pk Edinburgh City of Edinburgh EH14 2PY",
    "addr:housenumber":"8",
    "addr:postcode":"eh14 2py",
    "addr:street":"Murrayburn Pk Edinburgh",
    "iso:country":"GB",
    "sg:address":"8 Murrayburn Pk",
    "sg:city":"Edinburgh",
    "sg:classifiers":[
        {
            "category":"Health Services",
            "subcategory":"Clinic",
            "type":"Services"
        }
    ],
    "sg:postcode":"EH14 2PY",
    "sg:province":"City of Edinburgh",
    "sg:tags":[
        "abuse",
        "drug"
    ],
    "wof:name":"Prescribed Drugs Project",
    "wof:placetype":"venue"
},
  "geometry": {"coordinates":[-3.2789189816,55.9203643799],"type":"Point"}
}