{
  "type": "Feature",
  "properties": {
    "iso:country":"GB",
    "sg:address":"Unit L Kingsfield Business Cntr, Philanthropic Road",
    "sg:city":"Redhill",
    "sg:classifiers":[
        {
            "category":"Home & Garden",
            "subcategory":"Hardware",
            "type":"Retail Goods"
        }
    ],
    "sg:phone":"+44 1737 859900",
    "sg:postcode":"RH1 4DP",
    "sg:province":"Surrey",
    "sg:tags":[
        "heat",
        "mech",
        "exchanger"
    ],
    "wof:name":"Advanced Engineering Ltd.",
    "wof:placetype":"venue"
},
  "geometry": {"coordinates":[-0.168879,51.238178],"type":"Point"}
}