{
  "type": "Feature",
  "properties": {
    "iso:country":"GB",
    "sg:address":"151 Edgeley Road, Edgeley",
    "sg:city":"Stockport",
    "sg:classifiers":[
        {
            "category":"Organizations",
            "subcategory":"Community Association",
            "type":"Services"
        },
        {
            "category":"Organizations",
            "subcategory":"Membership Organization",
            "type":"Services"
        }
    ],
    "sg:phone":"+44 161 480 3696",
    "sg:postcode":"SK3 0TL",
    "sg:province":"Cheshire",
    "sg:tags":[
        "club",
        "social"
    ],
    "wof:name":"The Grange Club",
    "wof:placetype":"venue"
},
  "geometry": {"coordinates":[-2.178306,53.399445],"type":"Point"}
}