{
  "type": "Feature",
  "properties": {
    "addr:full":"42a Catcote Road Hartlepool Durham TS25 4HG",
    "addr:housenumber":"42a",
    "addr:postcode":"ts25 4hg",
    "addr:street":"Catcote Road",
    "iso:country":"GB",
    "sg:address":"42a Catcote Road",
    "sg:city":"Hartlepool",
    "sg:classifiers":[
        {
            "category":"Personal",
            "subcategory":"Beauty Salon",
            "type":"Services"
        }
    ],
    "sg:phone":"+44 1429 280266",
    "sg:postcode":"TS25 4HG",
    "sg:province":"Durham",
    "sg:tags":[
        "unisex",
        "hairdresser"
    ],
    "wof:name":"Monroe's",
    "wof:placetype":"venue"
},
  "geometry": {"coordinates":[-1.236232,54.671997],"type":"Point"}
}