{
  "type": "Feature",
  "properties": {
    "addr:full":"2 Cardiff Avenue Grimsby Lincolnshire DN36 4QD",
    "addr:housenumber":"2",
    "addr:postcode":"dn36 4qd",
    "addr:street":"Cardiff Avenue",
    "iso:country":"GB",
    "sg:address":"2 Cardiff Avenue",
    "sg:city":"Grimsby",
    "sg:classifiers":[
        {
            "category":"Professional",
            "subcategory":"Management & Consulting",
            "type":"Services"
        }
    ],
    "sg:phone":"+44 1472 828272",
    "sg:postcode":"DN36 4QD",
    "sg:province":"Lincolnshire",
    "sg:tags":[
        "consultant",
        "business"
    ],
    "wof:name":"R A M Scientific",
    "wof:placetype":"venue"
},
  "geometry": {"coordinates":[-0.070032,53.524719],"type":"Point"}
}