{
  "type": "Feature",
  "properties": {
    "addr:full":"6 Town House Rd Littleborough Lancashire OL15 9BQ",
    "addr:housenumber":"6",
    "addr:postcode":"ol15 9bq",
    "addr:street":"Town House Rd",
    "iso:country":"GB",
    "sg:address":"6 Town House Rd",
    "sg:city":"Littleborough",
    "sg:classifiers":[
        {
            "category":"Retail",
            "subcategory":"Repair Shop",
            "type":"Services"
        },
        {
            "category":"Building & Trades",
            "subcategory":"Construction",
            "type":"Services"
        }
    ],
    "sg:postcode":"OL15 9BQ",
    "sg:province":"Lancashire",
    "sg:tags":[
        "builder",
        "maintenance"
    ],
    "wof:name":"Powles,Douglas Terrence,",
    "wof:placetype":"venue"
},
  "geometry": {"coordinates":[-2.095789,53.645206],"type":"Point"}
}