{
  "type": "Feature",
  "properties": {
    "addr:full":"3 Baytree Rd Chorley Lancashire PR6 7JW",
    "addr:housenumber":"3",
    "addr:postcode":"pr6 7jw",
    "addr:street":"Baytree Rd",
    "iso:country":"GB",
    "sg:address":"3 Baytree Rd",
    "sg:city":"Chorley",
    "sg:classifiers":[
        {
            "category":"Education",
            "subcategory":"Music School",
            "type":"Public Place"
        }
    ],
    "sg:phone":"+44 1772 336850",
    "sg:postcode":"PR6 7JW",
    "sg:province":"Lancashire",
    "sg:tags":[
        "teacher"
    ],
    "wof:name":"Sue Wild",
    "wof:placetype":"venue"
},
  "geometry": {"coordinates":[-2.6427469254,53.7020950317],"type":"Point"}
}