{
  "type": "Feature",
  "properties": {
    "iso:country":"GB",
    "sg:address":"72 Brooms Road",
    "sg:city":"Dumfries",
    "sg:classifiers":[
        {
            "category":"Building & Trades",
            "subcategory":"Construction",
            "type":"Services"
        }
    ],
    "sg:phone":"+44 1387 254480",
    "sg:postcode":"DG1 2LA",
    "sg:province":"Dumfries and Galloway",
    "sg:tags":[
        "joiner",
        "carpenter"
    ],
    "wof:name":"G T  Smith",
    "wof:placetype":"venue"
},
  "geometry": {"coordinates":[-3.605191946,55.0663909912],"type":"Point"}
}