{
  "type": "Feature",
  "properties": {
    "iso:country":"GB",
    "sg:address":"37 Grimsby Road",
    "sg:city":"Cleethorpes",
    "sg:classifiers":[
        {
            "category":"Home & Garden",
            "subcategory":"Hardware",
            "type":"Retail Goods"
        }
    ],
    "sg:phone":"+44 1472 356801",
    "sg:postcode":"DN35 7AQ",
    "sg:province":"Lincolnshire",
    "sg:tags":[
        "retailer",
        "lighting"
    ],
    "wof:name":"Focus Lighting",
    "wof:placetype":"venue"
},
  "geometry": {"coordinates":[-0.054742,53.571194],"type":"Point"}
}