{
  "type": "Feature",
  "properties": {
    "addr:full":"117 Park Road, Toxteth Liverpool Merseyside L8 6SE",
    "addr:housenumber":"117",
    "addr:postcode":"l8 6se",
    "addr:street":"Park Road",
    "iso:country":"GB",
    "sg:address":"117 Park Road, Toxteth",
    "sg:city":"Liverpool",
    "sg:classifiers":[
        {
            "category":"Retail",
            "subcategory":"Auto Repair",
            "type":"Services"
        }
    ],
    "sg:postcode":"L8 6SE",
    "sg:province":"Merseyside",
    "sg:tags":[
        "modification",
        "garage"
    ],
    "wof:name":"Park Motors",
    "wof:placetype":"venue"
},
  "geometry": {"coordinates":[-2.9695050716,53.3874511719],"type":"Point"}
}