{
  "type": "Feature",
  "properties": {
    "addr:full":"Trehwfa Road Holyhead Isle of Anglesey LL65 1LE",
    "addr:postcode":"ll65 1le",
    "addr:street":"Trehwfa Road",
    "iso:country":"GB",
    "sg:address":"Trehwfa Road",
    "sg:city":"Holyhead",
    "sg:classifiers":[
        {
            "category":"Bus Charters",
            "type":"Transportation"
        }
    ],
    "sg:phone":"+44 1407 763506",
    "sg:postcode":"LL65 1LE",
    "sg:province":"Isle of Anglesey",
    "sg:tags":[
        "hire",
        "coach"
    ],
    "wof:name":"Goodsir Coach Depot",
    "wof:placetype":"venue"
},
  "geometry": {"coordinates":[-4.6477842331,53.3100967407],"type":"Point"}
}