{
  "type": "Feature",
  "properties": {
    "addr:full":"Cwrt-y-celyn Farm, Upper Boat Pontypridd Caerphilly CF37 5BJ",
    "addr:postcode":"cf37 5bj",
    "addr:street":"Upper",
    "iso:country":"GB",
    "sg:address":"Cwrt-y-celyn Farm, Upper Boat",
    "sg:city":"Pontypridd",
    "sg:classifiers":[
        {
            "category":"Professional",
            "subcategory":"Accounting & Tax Preparation",
            "type":"Services"
        },
        {
            "category":"Sports & Exercise",
            "subcategory":"Race Track",
            "type":"Entertainment"
        },
        {
            "category":"Recreation",
            "type":"Entertainment"
        }
    ],
    "sg:phone":"+44 29 2083 1658",
    "sg:postcode":"CF37 5BJ",
    "sg:province":"Caerphilly",
    "sg:tags":[
        "outdoor",
        "pursuit",
        "motor"
    ],
    "wof:name":"Taff Valley Buggy Trails",
    "wof:placetype":"venue"
},
  "geometry": {"coordinates":[-3.286219,51.573849],"type":"Point"}
}