{
  "type": "Feature",
  "properties": {
    "iso:country":"GB",
    "sg:address":"51-53 High Street North, Crail",
    "sg:city":"Anstruther",
    "sg:classifiers":[
        {
            "category":"Travel",
            "subcategory":"Hotels & Motels",
            "type":"Entertainment"
        }
    ],
    "sg:postcode":"KY10 3RA",
    "sg:province":"Fife",
    "sg:tags":[
        "house",
        "guest"
    ],
    "wof:name":"Caiplie Guest House",
    "wof:placetype":"venue"
},
  "geometry": {"coordinates":[-2.701419,56.223541],"type":"Point"}
}