{
  "type": "Feature",
  "properties": {
    "addr:full":"Merlin Way, Bowerhill Melksham Wiltshire SN12 6TJ",
    "addr:postcode":"sn12 6tj",
    "addr:street":"Merlin Way Bowerhill",
    "iso:country":"GB",
    "sg:address":"Merlin Way, Bowerhill",
    "sg:city":"Melksham",
    "sg:classifiers":[
        {
            "category":"Retail",
            "subcategory":"Auto Rental",
            "type":"Services"
        }
    ],
    "sg:phone":"+44 1225 790741",
    "sg:postcode":"SN12 6TJ",
    "sg:province":"Wiltshire",
    "sg:tags":[
        "car",
        "hire",
        "truck"
    ],
    "wof:name":"Industrial Services (Material Handling) Ltd.",
    "wof:placetype":"venue"
},
  "geometry": {"coordinates":[-2.130822897,51.3610534668],"type":"Point"}
}