{
  "type": "Feature",
  "properties": {
    "iso:country":"GB",
    "sg:address":"11 Cemmaes Court Road",
    "sg:city":"Hemel Hempstead",
    "sg:classifiers":[
        {
            "category":"Building & Trades",
            "subcategory":"Construction",
            "type":"Services"
        }
    ],
    "sg:phone":"+44 1442 62580",
    "sg:postcode":"HP1 1ST",
    "sg:province":"Hertfordshire",
    "sg:tags":[
        "platform",
        "work",
        "scaffolding"
    ],
    "wof:name":"M P Tully Scaffolding",
    "wof:placetype":"venue"
},
  "geometry": {"coordinates":[-0.477412,51.754734],"type":"Point"}
}