{
  "type": "Feature",
  "properties": {
    "addr:full":"The Post Office, Chapel Street Banbury Oxfordshire OX15 5ND",
    "addr:postcode":"ox15 5nd",
    "addr:street":"Chapel Street",
    "iso:country":"GB",
    "sg:address":"The Post Office, Chapel Street",
    "sg:city":"Banbury",
    "sg:classifiers":[
        {
            "category":"Personal",
            "subcategory":"Beauty Salon",
            "type":"Services"
        }
    ],
    "sg:postcode":"OX15 5ND",
    "sg:province":"Oxfordshire",
    "sg:tags":[
        "unisex",
        "hairdresser"
    ],
    "wof:name":"Sandra Farmers",
    "wof:placetype":"venue"
},
  "geometry": {"coordinates":[-1.5376260281,52.0492362976],"type":"Point"}
}