{
  "type": "Feature",
  "properties": {
    "addr:full":"41 Crescent Road Sheffield South Yorkshire S7 1HL",
    "addr:housenumber":"41",
    "addr:postcode":"s7 1hl",
    "addr:street":"Crescent Road",
    "iso:country":"GB",
    "sg:address":"41 Crescent Road",
    "sg:city":"Sheffield",
    "sg:classifiers":[
        {
            "category":"Building & Trades",
            "subcategory":"Construction",
            "type":"Services"
        }
    ],
    "sg:phone":"+44 114 264 9929",
    "sg:postcode":"S7 1HL",
    "sg:province":"South Yorkshire",
    "sg:tags":[
        "guttering"
    ],
    "wof:name":"Gutter & Roofing Services",
    "wof:placetype":"venue"
},
  "geometry": {"coordinates":[-1.48219,53.361912],"type":"Point"}
}