{
  "type": "Feature",
  "properties": {
    "iso:country":"GB",
    "sg:address":"35 Broadmead",
    "sg:city":"Bristol",
    "sg:classifiers":[
        {
            "category":"Shopping",
            "subcategory":"Shoes",
            "type":"Retail Goods"
        }
    ],
    "sg:phone":"+44 117 929 0992",
    "sg:postcode":"BS1 3EU",
    "sg:province":"City of Bristol",
    "sg:tags":[
        "shop"
    ],
    "wof:name":"Clarks Shoes",
    "wof:placetype":"venue"
},
  "geometry": {"coordinates":[-2.588324,51.457783],"type":"Point"}
}