{
  "type": "Feature",
  "properties": {
    "addr:full":"53-55 Lakedale Rd Woolwich Greater London SE18 1PR",
    "addr:housenumber":"53-55",
    "addr:postcode":"se18 1pr",
    "addr:street":"Lakedale Rd",
    "iso:country":"GB",
    "sg:address":"53-55 Lakedale Rd",
    "sg:city":"Woolwich",
    "sg:classifiers":[
        {
            "category":"Home & Garden",
            "subcategory":"Household Appliances",
            "type":"Retail Goods"
        }
    ],
    "sg:phone":"+44 20 8855 6888",
    "sg:postcode":"SE18 1PR",
    "sg:province":"Greater London",
    "sg:tags":[
        "electrical"
    ],
    "wof:name":"Alltype Discount Domestic Repair Centre",
    "wof:placetype":"venue"
},
  "geometry": {"coordinates":[0.0909700021,51.486240387],"type":"Point"}
}