{
  "type": "Feature",
  "properties": {
    "iso:country":"GB",
    "sg:address":"65 Lowesmoor",
    "sg:city":"Worcester",
    "sg:classifiers":[
        {
            "category":"Personal",
            "type":"Services"
        }
    ],
    "sg:phone":"+44 1905 23722",
    "sg:postcode":"WR1 2RS",
    "sg:province":"Worcestershire",
    "sg:tags":[
        "dressmaker"
    ],
    "wof:name":"The Alteration Centre",
    "wof:placetype":"venue"
},
  "geometry": {"coordinates":[-2.2170350552,52.1948471069],"type":"Point"}
}