{
  "type": "Feature",
  "properties": {
    "iso:country":"GB",
    "sg:address":"170 Peveril Road, Newbold",
    "sg:city":"Chesterfield",
    "sg:classifiers":[
        {
            "category":"Building & Trades",
            "subcategory":"Plumbing",
            "type":"Services"
        }
    ],
    "sg:postcode":"S41 8SH",
    "sg:province":"Derbyshire",
    "sg:tags":[
        "heating"
    ],
    "wof:name":"A Boulton Plumbing & Heating",
    "wof:placetype":"venue"
},
  "geometry": {"coordinates":[-1.435015,53.255623],"type":"Point"}
}