{
  "type": "Feature",
  "properties": {
    "addr:full":"19 Bungalow Park, Holders Road Salisbury Hampshire SP4 7PJ",
    "addr:housenumber":"19",
    "addr:postcode":"sp4 7pj",
    "addr:street":"Bungalow Park Holders Road",
    "iso:country":"GB",
    "sg:address":"19 Bungalow Park, Holders Road",
    "sg:city":"Salisbury",
    "sg:classifiers":[
        {
            "category":"Manufacturing",
            "subcategory":"Buildings",
            "type":"Manufacturing & Wholesale Goods"
        }
    ],
    "sg:postcode":"SP4 7PJ",
    "sg:province":"Hampshire",
    "sg:tags":[
        "mobile",
        "home"
    ],
    "wof:name":"Marshall & Co.",
    "wof:placetype":"venue"
},
  "geometry": {"coordinates":[-1.7690399885,51.1734695435],"type":"Point"}
}