{
  "type": "Feature",
  "properties": {
    "iso:country":"GB",
    "sg:address":"25a Aldergate",
    "sg:city":"Tamworth",
    "sg:classifiers":[
        {
            "category":"Military Area",
            "subcategory":"Air Force Base",
            "type":"Public Place"
        }
    ],
    "sg:phone":"+44 1827 55595",
    "sg:postcode":"B79 7DX",
    "sg:province":"Staffordshire",
    "sg:tags":[
        "taxi",
        "hire",
        "private"
    ],
    "wof:name":"Tamworth Road Taxis",
    "wof:placetype":"venue"
},
  "geometry": {"coordinates":[-1.6948809624,52.6361351013],"type":"Point"}
}