{
  "type": "Feature",
  "properties": {
    "iso:country":"GB",
    "sg:address":"9 Woodland Close",
    "sg:city":"Horsham",
    "sg:classifiers":[
        {
            "category":"Professional",
            "type":"Services"
        }
    ],
    "sg:phone":"+44 1403 260400",
    "sg:postcode":"RH13 6AN",
    "sg:province":"West Sussex",
    "sg:tags":[
        "caterer"
    ],
    "wof:name":"Falstaff Caterers",
    "wof:placetype":"venue"
},
  "geometry": {"coordinates":[-0.2952130139,51.0718383789],"type":"Point"}
}