{
  "type": "Feature",
  "properties": {
    "addr:full":"18 Netham Road Bristol City of Bristol BS5 9PF",
    "addr:housenumber":"18",
    "addr:postcode":"bs5 9pf",
    "addr:street":"Netham Road",
    "iso:country":"GB",
    "sg:address":"18 Netham Road",
    "sg:city":"Bristol",
    "sg:classifiers":[
        {
            "category":"Professional",
            "subcategory":"Printing & Photocopies",
            "type":"Services"
        }
    ],
    "sg:postcode":"BS5 9PF",
    "sg:province":"City of Bristol",
    "sg:tags":[
        "process",
        "screen",
        "printer"
    ],
    "wof:name":"Sureprint",
    "wof:placetype":"venue"
},
  "geometry": {"coordinates":[-2.55412,51.456924],"type":"Point"}
}