{
  "type": "Feature",
  "properties": {
    "iso:country":"GB",
    "sg:address":"Hillside, Ardens Grafton",
    "sg:city":"Alcester",
    "sg:classifiers":[
        {
            "category":"Building & Trades",
            "subcategory":"Construction",
            "type":"Services"
        }
    ],
    "sg:phone":"+44 1789 772980",
    "sg:postcode":"B49 6DS",
    "sg:province":"Warwickshire",
    "sg:tags":[
        "dry",
        "lining",
        "plasterers",
        "screeders"
    ],
    "wof:name":"Brixarus Ltd.",
    "wof:placetype":"venue"
},
  "geometry": {"coordinates":[-1.860992,52.221798],"type":"Point"}
}