{
  "type": "Feature",
  "properties": {
    "iso:country":"GB",
    "sg:address":"Bank House, Bury Old Road",
    "sg:city":"Salford",
    "sg:classifiers":[
        {
            "category":"Home & Garden",
            "subcategory":"Kitchen Supply",
            "type":"Retail Goods"
        }
    ],
    "sg:phone":"+44 161 740 2409",
    "sg:postcode":"M7 4PX",
    "sg:province":"Greater Manchester",
    "sg:tags":[
        "glassware",
        "china"
    ],
    "wof:name":"Allweis China & Crystal",
    "wof:placetype":"venue"
},
  "geometry": {"coordinates":[-2.2537739277,53.5172157288],"type":"Point"}
}