{
  "type": "Feature",
  "properties": {
    "addr:full":"50 Queens Rd Thame Buckinghamshire OX9 3NQ",
    "addr:housenumber":"50",
    "addr:postcode":"ox9 3nq",
    "addr:street":"Queens Rd",
    "iso:country":"GB",
    "sg:address":"50 Queens Rd",
    "sg:city":"Thame",
    "sg:classifiers":[
        {
            "category":"Professional",
            "subcategory":"Lawyer & Legal Services",
            "type":"Services"
        }
    ],
    "sg:phone":"+44 1844 212059",
    "sg:postcode":"OX9 3NQ",
    "sg:province":"Buckinghamshire",
    "sg:tags":[
        "advice",
        "counselling"
    ],
    "wof:name":"David Colbourne",
    "wof:placetype":"venue"
},
  "geometry": {"coordinates":[-0.965476,51.744415],"type":"Point"}
}