{
  "type": "Feature",
  "properties": {
    "addr:full":"The Fortress Works, Foxton Road, Lubenham Market Harborough Leicestershire LE16 7RY",
    "addr:postcode":"le16 7ry",
    "addr:street":"Foxton Road",
    "iso:country":"GB",
    "sg:address":"The Fortress Works, Foxton Road, Lubenham",
    "sg:city":"Market Harborough",
    "sg:classifiers":[
        {
            "category":"Retail",
            "subcategory":"Auto Repair",
            "type":"Services"
        }
    ],
    "sg:postcode":"LE16 7RY",
    "sg:province":"Leicestershire",
    "sg:tags":[
        "modification",
        "garage"
    ],
    "wof:name":"L J Morris",
    "wof:placetype":"venue"
},
  "geometry": {"coordinates":[-0.922579,52.479397],"type":"Point"}
}