{
  "type": "Feature",
  "properties": {
    "iso:country":"GB",
    "sg:address":"15 Briscoe Road",
    "sg:city":"Hoddesdon",
    "sg:classifiers":[
        {
            "category":"Education",
            "subcategory":"Special Training",
            "type":"Public Place"
        }
    ],
    "sg:phone":"+44 1992 420044",
    "sg:postcode":"EN11 9DQ",
    "sg:province":"Essex",
    "sg:tags":[
        "product",
        "centre"
    ],
    "wof:name":"The Letting Training Centre",
    "wof:placetype":"venue"
},
  "geometry": {"coordinates":[-0.015623,51.769073],"type":"Point"}
}