{
  "type": "Feature",
  "properties": {
    "addr:full":"Station Approach, North Lane Colchester Essex CO6 1EG",
    "addr:postcode":"co6 1eg",
    "addr:street":"Station Approach North Lane",
    "iso:country":"GB",
    "sg:address":"Station Approach, North Lane",
    "sg:city":"Colchester",
    "sg:classifiers":[
        {
            "category":"Professional",
            "type":"Services"
        },
        {
            "category":"Professional",
            "subcategory":"Printing & Photocopies",
            "type":"Services"
        }
    ],
    "sg:phone":"+44 1206 212336",
    "sg:postcode":"CO6 1EG",
    "sg:province":"Essex",
    "sg:tags":[
        "directory",
        "printer",
        "pub"
    ],
    "wof:name":"Design & Print Integration",
    "wof:placetype":"venue"
},
  "geometry": {"coordinates":[0.78479,51.883141],"type":"Point"}
}