{
  "type": "Feature",
  "properties": {
    "addr:full":"15 Daws Lane London Greater London NW7 4SD",
    "addr:housenumber":"15",
    "addr:postcode":"nw7 4sd",
    "addr:street":"Daws Lane",
    "iso:country":"GB",
    "sg:address":"15 Daws Lane",
    "sg:city":"London",
    "sg:classifiers":[
        {
            "category":"Building & Trades",
            "subcategory":"Construction",
            "type":"Services"
        }
    ],
    "sg:phone":"+44 20 8959 5090",
    "sg:postcode":"NW7 4SD",
    "sg:province":"Greater London",
    "sg:tags":[
        "welder"
    ],
    "wof:name":"Rocar Welding",
    "wof:placetype":"venue"
},
  "geometry": {"coordinates":[-0.242489,51.616066],"type":"Point"}
}