{
  "type": "Feature",
  "properties": {
    "addr:full":"114 Oxford Road Wokingham Berkshire RG41 2YN",
    "addr:housenumber":"114",
    "addr:postcode":"rg41 2yn",
    "addr:street":"Oxford Road",
    "iso:country":"GB",
    "sg:address":"114 Oxford Road",
    "sg:city":"Wokingham",
    "sg:classifiers":[
        {
            "category":"Professional",
            "subcategory":"Lawyer & Legal Services",
            "type":"Services"
        }
    ],
    "sg:postcode":"RG41 2YN",
    "sg:province":"Berkshire",
    "wof:name":"Home Wills Berkshire",
    "wof:placetype":"venue"
},
  "geometry": {"coordinates":[-0.8487560153,51.4162254333],"type":"Point"}
}