{
  "type": "Feature",
  "properties": {
    "addr:full":"3-4 South Square Bloomsbury Greater London WC1R 5HP",
    "addr:housenumber":"3-4",
    "addr:postcode":"wc1r 5hp",
    "addr:street":"South Square",
    "iso:country":"GB",
    "sg:address":"3-4 South Square",
    "sg:city":"Bloomsbury",
    "sg:classifiers":[
        {
            "category":"Professional",
            "subcategory":"Lawyer & Legal Services",
            "type":"Services"
        }
    ],
    "sg:phone":"+44 171 696 9900",
    "sg:postcode":"WC1R 5HP",
    "sg:province":"Greater London",
    "sg:tags":[
        "barrister"
    ],
    "wof:name":"Barristars Chambers",
    "wof:placetype":"venue"
},
  "geometry": {"coordinates":[-0.112276,51.518833],"type":"Point"}
}