{
  "type": "Feature",
  "properties": {
    "iso:country":"GB",
    "sg:address":"Slade Farm, Witcham",
    "sg:city":"Ely",
    "sg:classifiers":[
        {
            "category":"Farming",
            "subcategory":"Farm",
            "type":"Manufacturing & Wholesale Goods"
        }
    ],
    "sg:phone":"+44 1353 778343",
    "sg:postcode":"CB6 2LA",
    "sg:province":"Cambridgeshire",
    "sg:tags":[
        "mixed",
        "crop"
    ],
    "wof:name":"D H Sulman",
    "wof:placetype":"venue"
},
  "geometry": {"coordinates":[0.1488240063,52.3998718262],"type":"Point"}
}