{
  "type": "Feature",
  "properties": {
    "iso:country":"GB",
    "sg:address":"The Spinney, 8 Tudor Court",
    "sg:city":"Wrexham",
    "sg:classifiers":[
        {
            "category":"Organizations",
            "subcategory":"Membership Organization",
            "type":"Services"
        }
    ],
    "sg:postcode":"LL12 9PJ",
    "sg:province":"Wrexham",
    "sg:tags":[
        "club"
    ],
    "wof:name":"The Dinner Club",
    "wof:placetype":"venue"
},
  "geometry": {"coordinates":[-3.04067,53.119678],"type":"Point"}
}