{
  "type": "Feature",
  "properties": {
    "addr:full":"Georgian Court, 56a High Street Haslemere Hampshire GU27 2LA",
    "addr:housenumber":"56a",
    "addr:postcode":"gu27 2la",
    "addr:street":"Georgian Court;High Street",
    "iso:country":"GB",
    "sg:address":"Georgian Court, 56a High Street",
    "sg:city":"Haslemere",
    "sg:classifiers":[
        {
            "category":"Real Estate",
            "subcategory":"Real Estate Agent",
            "type":"Services"
        }
    ],
    "sg:postcode":"GU27 2LA",
    "sg:province":"Hampshire",
    "wof:name":"Burns & Webber",
    "wof:placetype":"venue"
},
  "geometry": {"coordinates":[-0.708994,51.088329],"type":"Point"}
}