{
  "type": "Feature",
  "properties": {
    "addr:full":"Tylers Ride, South Woodham Ferrers Chelmsford Essex CM3 5XD",
    "addr:postcode":"cm3 5xd",
    "addr:street":"South Woodham Ferrers Chelmsford",
    "iso:country":"GB",
    "sg:address":"Tylers Ride, South Woodham Ferrers",
    "sg:city":"Chelmsford",
    "sg:classifiers":[
        {
            "category":"Health Services",
            "subcategory":"Doctor",
            "type":"Services"
        },
        {
            "category":"Health Services",
            "subcategory":"Clinic",
            "type":"Services"
        }
    ],
    "sg:phone":"+44 1245 322443",
    "sg:postcode":"CM3 5XD",
    "sg:province":"Essex",
    "sg:tags":[
        "nh",
        "practitioners"
    ],
    "wof:name":"Greenwood Surgery",
    "wof:placetype":"venue"
},
  "geometry": {"coordinates":[0.621143,51.644249],"type":"Point"}
}