{
  "type": "Feature",
  "properties": {
    "addr:full":"31 Audley Road Colchester Essex CO3 3TY",
    "addr:housenumber":"31",
    "addr:postcode":"co3 3ty",
    "addr:street":"Audley Road Colchester",
    "iso:country":"GB",
    "sg:address":"31 Audley Road",
    "sg:city":"Colchester",
    "sg:classifiers":[
        {
            "category":"Real Estate",
            "subcategory":"Real Estate Operator",
            "type":"Services"
        }
    ],
    "sg:postcode":"CO3 3TY",
    "sg:province":"Essex",
    "sg:tags":[
        "letting",
        "agent"
    ],
    "wof:name":"Carol Smith Residential Lettings",
    "wof:placetype":"venue"
},
  "geometry": {"coordinates":[0.8787459731,51.8812675476],"type":"Point"}
}