{
  "type": "Feature",
  "properties": {
    "iso:country":"GB",
    "sg:address":"Deeside Enterprise Centre, Rowleys Drive",
    "sg:city":"Deeside",
    "sg:classifiers":[
        {
            "category":"Organizations",
            "subcategory":"Non-profit Organization",
            "type":"Services"
        }
    ],
    "sg:phone":"+44 1244 822884",
    "sg:postcode":"CH5 1PP",
    "sg:province":"Flintshire",
    "sg:tags":[
        "organisation",
        "voluntary",
        "charity"
    ],
    "wof:name":"British Dyslexics",
    "wof:placetype":"venue"
},
  "geometry": {"coordinates":[-3.034369,53.211449],"type":"Point"}
}