{
  "type": "Feature",
  "properties": {
    "iso:country":"GB",
    "sg:address":"47 King Street",
    "sg:city":"Seahouses",
    "sg:classifiers":[
        {
            "category":"Recreation",
            "subcategory":"Boat Charter",
            "type":"Entertainment"
        }
    ],
    "sg:phone":"+44 1665 721210",
    "sg:postcode":"NE68 7XW",
    "sg:province":"Northumberland",
    "sg:tags":[
        "excursion"
    ],
    "wof:name":"John Baron & Mary Shiel",
    "wof:placetype":"venue"
},
  "geometry": {"coordinates":[-1.650648,55.579063],"type":"Point"}
}