{
  "type": "Feature",
  "properties": {
    "addr:full":"Hagg Lane, Belton Doncaster Lincolnshire DN9 1QL",
    "addr:postcode":"dn9 1ql",
    "addr:street":"Hagg Lane",
    "iso:country":"GB",
    "sg:address":"Hagg Lane, Belton",
    "sg:city":"Doncaster",
    "sg:classifiers":[
        {
            "category":"Building & Trades",
            "subcategory":"Construction",
            "type":"Services"
        }
    ],
    "sg:postcode":"DN9 1QL",
    "sg:province":"Lincolnshire",
    "sg:tags":[
        "guttering"
    ],
    "wof:name":"Eltech",
    "wof:placetype":"venue"
},
  "geometry": {"coordinates":[-0.8168269992,53.5665817261],"type":"Point"}
}