{
  "type": "Feature",
  "properties": {
    "addr:full":"60-64 Lymburn Street Glasgow Glasgow City G3 8PD",
    "addr:housenumber":"60-64",
    "addr:postcode":"g3 8pd",
    "addr:street":"Lymburn Street",
    "iso:country":"GB",
    "sg:address":"60-64 Lymburn Street",
    "sg:city":"Glasgow",
    "sg:classifiers":[
        {
            "category":"Sports & Exercise",
            "subcategory":"Golf",
            "type":"Entertainment"
        }
    ],
    "sg:phone":"+44 141 226 3444",
    "sg:postcode":"G3 8PD",
    "sg:province":"Glasgow City",
    "sg:tags":[
        "equipment"
    ],
    "wof:name":"H Silverdale & Co",
    "wof:placetype":"venue"
},
  "geometry": {"coordinates":[-4.288933,55.865688],"type":"Point"}
}