{
  "type": "Feature",
  "properties": {
    "addr:full":"20 Renfrew St Glasgow Glasgow City G2 3BW",
    "addr:housenumber":"20",
    "addr:postcode":"g2 3bw",
    "addr:street":"Renfrew St",
    "iso:country":"GB",
    "sg:address":"20 Renfrew St",
    "sg:city":"Glasgow",
    "sg:classifiers":[
        {
            "category":"Shopping",
            "subcategory":"Clothing, Apparel, & Fashions",
            "type":"Retail Goods"
        }
    ],
    "sg:phone":"+44 141 332 7849",
    "sg:postcode":"G2 3BW",
    "sg:province":"Glasgow City",
    "sg:tags":[
        "sportswear"
    ],
    "wof:name":"Direct Sport",
    "wof:placetype":"venue"
},
  "geometry": {"coordinates":[-4.254735,55.865307],"type":"Point"}
}