{
  "type": "Feature",
  "properties": {
    "addr:full":"High View, Common Lane, Corley Coventry Warwickshire CV7 8AQ",
    "addr:postcode":"cv7 8aq",
    "addr:street":"Common Lane",
    "iso:country":"GB",
    "sg:address":"High View, Common Lane, Corley",
    "sg:city":"Coventry",
    "sg:classifiers":[
        {
            "category":"Banks & Credit Unions",
            "subcategory":"Investment Brokerage",
            "type":"Services"
        }
    ],
    "sg:phone":"+44 1676 540270",
    "sg:postcode":"CV7 8AQ",
    "sg:province":"Warwickshire",
    "sg:tags":[
        "contractor"
    ],
    "wof:name":"Heritage & Sons",
    "wof:placetype":"venue"
},
  "geometry": {"coordinates":[-1.558937,52.464916],"type":"Point"}
}