{
  "type": "Feature",
  "properties": {
    "iso:country":"GB",
    "sg:address":"Rushmere Farm, Rushmere Lane, Hambledon",
    "sg:city":"Waterlooville",
    "sg:classifiers":[
        {
            "category":"Personal",
            "subcategory":"Adult",
            "type":"Services"
        }
    ],
    "sg:phone":"+44 23 9263 2679",
    "sg:postcode":"PO7 4SG",
    "sg:province":"Hampshire",
    "sg:tags":[
        "equestrian"
    ],
    "wof:name":"Rushmere Farm Stables",
    "wof:placetype":"venue"
},
  "geometry": {"coordinates":[-1.0867869854,50.9303131104],"type":"Point"}
}