{
  "type": "Feature",
  "properties": {
    "addr:full":"34 Sackville St West End Hampshire W1X 1DB",
    "addr:housenumber":"34",
    "addr:postcode":"w1x 1db",
    "addr:street":"Sackville St",
    "iso:country":"GB",
    "sg:address":"34 Sackville St",
    "sg:city":"West End",
    "sg:classifiers":[
        {
            "category":"Real Estate",
            "subcategory":"Surveying",
            "type":"Services"
        }
    ],
    "sg:phone":"+44 20 7439 4050",
    "sg:postcode":"W1X 1DB",
    "sg:province":"Hampshire",
    "sg:tags":[
        "building",
        "surveyor"
    ],
    "wof:name":"Merlin Project Management",
    "wof:placetype":"venue"
},
  "geometry": {"coordinates":[-0.1385349929,51.5095596313],"type":"Point"}
}