{
  "type": "Feature",
  "properties": {
    "iso:country":"GB",
    "sg:address":"Holywells Rd",
    "sg:city":"Ipswich",
    "sg:classifiers":[
        {
            "category":"Building & Trades",
            "subcategory":"Equipment Rental",
            "type":"Services"
        }
    ],
    "sg:phone":"+44 1473 214839",
    "sg:postcode":"IP3 0DL",
    "sg:province":"Suffolk",
    "sg:tags":[
        "hire",
        "centre"
    ],
    "wof:name":"Hewden Hire Centres",
    "wof:placetype":"venue"
},
  "geometry": {"coordinates":[1.166569,52.046951],"type":"Point"}
}