{
  "type": "Feature",
  "properties": {
    "addr:full":"23 Heath Close, Polstead Heath Colchester Essex CO6 5BE",
    "addr:housenumber":"23",
    "addr:postcode":"co6 5be",
    "addr:street":"Heath Close",
    "iso:country":"GB",
    "sg:address":"23 Heath Close, Polstead Heath",
    "sg:city":"Colchester",
    "sg:classifiers":[
        {
            "category":"Professional",
            "subcategory":"Computer Services",
            "type":"Services"
        }
    ],
    "sg:phone":"+44 1787 210530",
    "sg:postcode":"CO6 5BE",
    "sg:province":"Essex",
    "sg:tags":[
        "aided",
        "design"
    ],
    "wof:name":"Graham Webber Associates",
    "wof:placetype":"venue"
},
  "geometry": {"coordinates":[0.8991829753,52.0058708191],"type":"Point"}
}