{
  "type": "Feature",
  "properties": {
    "iso:country":"GB",
    "sg:address":"Commercial Street, Bitterne",
    "sg:city":"Southampton",
    "sg:classifiers":[
        {
            "category":"Bars & Pubs",
            "type":"Food & Drink"
        },
        {
            "category":"Community Center",
            "subcategory":"Social",
            "type":"Public Place"
        }
    ],
    "sg:phone":"+44 23 8043 7577",
    "sg:postcode":"SO18 6LY",
    "sg:province":"Hampshire",
    "sg:tags":[
        "pubs",
        "house",
        "inn",
        "activity"
    ],
    "wof:name":"Wadworth & Co. (Burford) Ltd",
    "wof:placetype":"venue"
},
  "geometry": {"coordinates":[-1.353169,50.918236],"type":"Point"}
}