{
  "type": "Feature",
  "properties": {
    "iso:country":"GB",
    "sg:address":"Munsdale, Greasbrough",
    "sg:city":"Rotherham",
    "sg:classifiers":[
        {
            "category":"Social Services",
            "subcategory":"Adult Care",
            "type":"Services"
        },
        {
            "category":"Government",
            "subcategory":"Office",
            "type":"Public Place"
        }
    ],
    "sg:phone":"+44 1709 558276",
    "sg:postcode":"S61 4RA",
    "sg:province":"South Yorkshire",
    "sg:tags":[
        "housing",
        "local",
        "sheltered"
    ],
    "wof:name":"Munsdale Sheltered Housing",
    "wof:placetype":"venue"
},
  "geometry": {"coordinates":[-1.368032,53.453503],"type":"Point"}
}