{
  "type": "Feature",
  "properties": {
    "addr:full":"36 Mount Pleasant, Quarry Bank Brierley Hill West Midlands DY5 2YZ",
    "addr:housenumber":"36",
    "addr:postcode":"dy5 2yz",
    "addr:street":"Mount Pleasant;Bank Brierley Hill",
    "iso:country":"GB",
    "sg:address":"36 Mount Pleasant, Quarry Bank",
    "sg:city":"Brierley Hill",
    "sg:classifiers":[
        {
            "category":"Bars & Pubs",
            "type":"Food & Drink"
        }
    ],
    "sg:phone":"+44 1384 572463",
    "sg:postcode":"DY5 2YZ",
    "sg:province":"West Midlands",
    "sg:tags":[
        "pubs",
        "house",
        "inn",
        "public",
        "activity"
    ],
    "wof:name":"Brickmakers Arms",
    "wof:placetype":"venue"
},
  "geometry": {"coordinates":[-2.110908,52.473831],"type":"Point"}
}