{
  "type": "Feature",
  "properties": {
    "iso:country":"GB",
    "sg:address":"61 Mill St",
    "sg:city":"Leominster",
    "sg:classifiers":[
        {
            "category":"Professional",
            "subcategory":"Management & Consulting",
            "type":"Services"
        },
        {
            "category":"Social Services",
            "subcategory":"Job Training",
            "type":"Services"
        }
    ],
    "sg:postcode":"HR6 8EE",
    "sg:province":"Herefordshire",
    "sg:tags":[
        "consultant",
        "drawing",
        "business",
        "draughtsman"
    ],
    "wof:name":"Tootell,John Steven,",
    "wof:placetype":"venue"
},
  "geometry": {"coordinates":[-2.73558,52.231529],"type":"Point"}
}