{
  "type": "Feature",
  "properties": {
    "addr:full":"Sandy Lane, South Nutfield Redhill Surrey RH1 4EJ",
    "addr:postcode":"rh1 4ej",
    "addr:street":"Sandy Lane",
    "iso:country":"GB",
    "sg:address":"Sandy Lane, South Nutfield",
    "sg:city":"Redhill",
    "sg:classifiers":[
        {
            "category":"Food & Beverages",
            "subcategory":"Farmers Market",
            "type":"Retail Goods"
        }
    ],
    "sg:phone":"+44 1737 822484",
    "sg:postcode":"RH1 4EJ",
    "sg:province":"Surrey",
    "sg:tags":[
        "farm",
        "shop",
        "pyo"
    ],
    "wof:name":"Priory Farm P Y O",
    "wof:placetype":"venue"
},
  "geometry": {"coordinates":[-0.109392,51.247185],"type":"Point"}
}