{
  "type": "Feature",
  "properties": {
    "addr:full":"11 \u2013 21 Paul Street London EC2A 4JU",
    "addr:housenumber":"21",
    "addr:postcode":"ec2a 4ju",
    "addr:street":"Paul Street",
    "iso:country":"GB",
    "sg:address":"11 \u2013 21 Paul Street",
    "sg:city":"London",
    "sg:classifiers":[
        {
            "category":"Professional",
            "subcategory":"Computer Services",
            "type":"Services"
        }
    ],
    "sg:postcode":"EC2A 4JU",
    "sg:website":"http://www.iomart.com",
    "wof:name":"iomart Group",
    "wof:placetype":"venue"
},
  "geometry": {"coordinates":[-0.0994103,51.5133444],"type":"Point"}
}