{
  "type": "Feature",
  "properties": {
    "addr:full":"4 Mercers Rd Archway Greater London N19 4PJ",
    "addr:housenumber":"4",
    "addr:postcode":"n19 4pj",
    "addr:street":"Mercers Rd",
    "iso:country":"GB",
    "sg:address":"4 Mercers Rd",
    "sg:city":"Archway",
    "sg:classifiers":[
        {
            "category":"Organizations",
            "subcategory":"Non-profit Organization",
            "type":"Services"
        }
    ],
    "sg:phone":"+44 20 7281 9322",
    "sg:postcode":"N19 4PJ",
    "sg:province":"Greater London",
    "sg:tags":[
        "organisation",
        "voluntary",
        "charity"
    ],
    "wof:name":"Parent Network (North London)",
    "wof:placetype":"venue"
},
  "geometry": {"coordinates":[-0.1232969984,51.5598716736],"type":"Point"}
}