{
  "type": "Feature",
  "properties": {
    "iso:country":"GB",
    "sg:address":"208 Oakbrook Road",
    "sg:city":"Sheffield",
    "sg:classifiers":[
        {
            "category":"Home & Garden",
            "subcategory":"Household Appliances",
            "type":"Retail Goods"
        }
    ],
    "sg:postcode":"S11 7ED",
    "sg:province":"Derbyshire",
    "sg:tags":[
        "electrical"
    ],
    "wof:name":"Alan Bayne Electrical",
    "wof:placetype":"venue"
},
  "geometry": {"coordinates":[-1.523264,53.368416],"type":"Point"}
}