{
  "type": "Feature",
  "properties": {
    "addr:full":"12 Old Burlington Street London Greater London W1S 3AH",
    "addr:housenumber":"12",
    "addr:postcode":"w1s 3ah",
    "addr:street":"Old Burlington Street",
    "iso:country":"GB",
    "sg:address":"12 Old Burlington Street",
    "sg:city":"London",
    "sg:classifiers":[
        {
            "category":"Real Estate",
            "subcategory":"Surveying",
            "type":"Services"
        }
    ],
    "sg:phone":"+44 20 7287 2282",
    "sg:postcode":"W1S 3AH",
    "sg:province":"Greater London",
    "sg:tags":[
        "surveyor",
        "valuer"
    ],
    "wof:name":"David Newman & Co",
    "wof:placetype":"venue"
},
  "geometry": {"coordinates":[-0.1409489959,51.5109481812],"type":"Point"}
}