{
  "type": "Feature",
  "properties": {
    "addr:full":"46a Syon La, Osterley Isleworth Greater London TW7 5NQ",
    "addr:housenumber":"46a",
    "addr:postcode":"tw7 5nq",
    "addr:street":"Syon La Osterley",
    "iso:country":"GB",
    "sg:address":"46a Syon La, Osterley",
    "sg:city":"Isleworth",
    "sg:classifiers":[
        {
            "category":"Communications",
            "type":"Services"
        }
    ],
    "sg:postcode":"TW7 5NQ",
    "sg:province":"Greater London",
    "sg:tags":[
        "data",
        "network"
    ],
    "wof:name":"Impac-Data Ltd",
    "wof:placetype":"venue"
},
  "geometry": {"coordinates":[-0.328363,51.483597],"type":"Point"}
}