{
  "type": "Feature",
  "properties": {
    "iso:country":"GB",
    "sg:address":"Powlett Road",
    "sg:city":"Bath",
    "sg:classifiers":[
        {
            "category":"Social Services",
            "type":"Services"
        },
        {
            "category":"Social Services",
            "subcategory":"Child Care",
            "type":"Services"
        },
        {
            "category":"Government",
            "subcategory":"Office",
            "type":"Public Place"
        }
    ],
    "sg:phone":"+44 1225 462094",
    "sg:postcode":"BA2 6QH",
    "sg:province":"Somerset",
    "sg:tags":[
        "local",
        "creche"
    ],
    "wof:name":"BATH & NORTH EAST SOMERSET COUNCIL",
    "wof:placetype":"venue"
},
  "geometry": {"coordinates":[-2.352263,51.388042],"type":"Point"}
}