{
  "type": "Feature",
  "properties": {
    "addr:full":"49 Merrion Centre Leeds West Yorkshire LS2 8PJ",
    "addr:housenumber":"49",
    "addr:postcode":"ls2 8pj",
    "addr:street":"Merrion Centre Leeds West",
    "iso:country":"GB",
    "sg:address":"49 Merrion Centre",
    "sg:city":"Leeds",
    "sg:classifiers":[
        {
            "category":"Shopping",
            "subcategory":"Pharmacy",
            "type":"Retail Goods"
        }
    ],
    "sg:phone":"+44 113 242 8194",
    "sg:postcode":"LS2 8PJ",
    "sg:province":"West Yorkshire",
    "sg:tags":[
        "pharmacist",
        "dispensing",
        "chemist"
    ],
    "sg:website":"http://www.boots.com",
    "wof:name":"Boots The Chemists Ltd",
    "wof:placetype":"venue"
},
  "geometry": {"coordinates":[-1.543578,53.801586],"type":"Point"}
}