{
  "type": "Feature",
  "properties": {
    "iso:country":"GB",
    "sg:address":"37 Maple Avenue",
    "sg:city":"Ripley",
    "sg:classifiers":[
        {
            "category":"Personal",
            "subcategory":"Beauty Salon",
            "type":"Services"
        }
    ],
    "sg:phone":"+44 1773 744113",
    "sg:postcode":"DE5 3PY",
    "sg:province":"Derbyshire",
    "sg:tags":[
        "unisex",
        "hairdresser"
    ],
    "wof:name":"Sarah Anthony Hair Studio",
    "wof:placetype":"venue"
},
  "geometry": {"coordinates":[-1.413233,53.045994],"type":"Point"}
}