{
  "type": "Feature",
  "properties": {
    "iso:country":"GB",
    "sg:address":"Narrow Wood Cottage, Station Road",
    "sg:city":"Worcester",
    "sg:classifiers":[
        {
            "category":"Building & Trades",
            "subcategory":"Plumbing",
            "type":"Services"
        }
    ],
    "sg:postcode":"WR8 9HA",
    "sg:province":"Gloucestershire",
    "sg:tags":[
        "heating"
    ],
    "wof:name":"Colin Boother",
    "wof:placetype":"venue"
},
  "geometry": {"coordinates":[-2.1471199989,52.1265716553],"type":"Point"}
}