{
  "type": "Feature",
  "properties": {
    "addr:full":"Sheffield Road Chesterfield Derbyshire S41 9EH",
    "addr:postcode":"s41 9eh",
    "addr:street":"Sheffield Road",
    "iso:country":"GB",
    "sg:address":"Sheffield Road",
    "sg:city":"Chesterfield",
    "sg:classifiers":[
        {
            "category":"Travel",
            "subcategory":"Hotels & Motels",
            "type":"Entertainment"
        }
    ],
    "sg:phone":"+44 1246 450550",
    "sg:postcode":"S41 9EH",
    "sg:province":"Derbyshire",
    "wof:name":"Sandpiper Hotel",
    "wof:placetype":"venue"
},
  "geometry": {"coordinates":[-1.437284,53.269997],"type":"Point"}
}