{
  "type": "Feature",
  "properties": {
    "iso:country":"GB",
    "sg:address":"Mansfield Road, Edwinstowe",
    "sg:city":"Mansfield",
    "sg:classifiers":[
        {
            "category":"Education",
            "subcategory":"School",
            "type":"Public Place"
        }
    ],
    "sg:phone":"+44 1623 823490",
    "sg:postcode":"NG21 9NP",
    "sg:province":"Nottinghamshire",
    "sg:tags":[
        "local",
        "authority"
    ],
    "wof:name":"The Rufford School",
    "wof:placetype":"venue"
},
  "geometry": {"coordinates":[-1.068122983,53.1949691772],"type":"Point"}
}