{
  "type": "Feature",
  "properties": {
    "iso:country":"GB",
    "sg:address":"39 Bro Myrddin",
    "sg:city":"Carmarthen",
    "sg:classifiers":[
        {
            "category":"Manufacturing",
            "subcategory":"Petroleum Products",
            "type":"Manufacturing & Wholesale Goods"
        }
    ],
    "sg:phone":"+44 1267 233247",
    "sg:postcode":"SA31 3HE",
    "sg:province":"Carmarthenshire",
    "sg:tags":[
        "double",
        "glazing"
    ],
    "wof:name":"Betabuild",
    "wof:placetype":"venue"
},
  "geometry": {"coordinates":[-4.330466,51.855118],"type":"Point"}
}