{
  "type": "Feature",
  "properties": {
    "addr:full":"90 Windsor Road Southport Lancashire PR9 9BY",
    "addr:housenumber":"90",
    "addr:postcode":"pr9 9by",
    "addr:street":"Windsor Road",
    "iso:country":"GB",
    "sg:address":"90 Windsor Road",
    "sg:city":"Southport",
    "sg:classifiers":[
        {
            "category":"Health Services",
            "subcategory":"Nursing And Care Facility",
            "type":"Services"
        }
    ],
    "sg:phone":"+44 1704 546032",
    "sg:postcode":"PR9 9BY",
    "sg:province":"Lancashire",
    "sg:tags":[
        "home"
    ],
    "wof:name":"Windsor House",
    "wof:placetype":"venue"
},
  "geometry": {"coordinates":[-2.9864621162,53.6483688354],"type":"Point"}
}