{
  "type": "Feature",
  "properties": {
    "iso:country":"GB",
    "sg:address":"Grove Ave, Leysdown On Sea",
    "sg:city":"Sheerness",
    "sg:classifiers":[
        {
            "category":"Recreation",
            "subcategory":"Amusement Park",
            "type":"Entertainment"
        }
    ],
    "sg:postcode":"ME12 4QE",
    "sg:province":"Kent",
    "sg:tags":[
        "arcade"
    ],
    "wof:name":"Stokes,B, & Son",
    "wof:placetype":"venue"
},
  "geometry": {"coordinates":[0.92139,51.399471],"type":"Point"}
}