{
  "type": "Feature",
  "properties": {
    "iso:country":"GB",
    "sg:address":"37 Wenhill Heights",
    "sg:city":"Calne",
    "sg:classifiers":[
        {
            "category":"Manufacturing",
            "subcategory":"Chemicals & Compounds",
            "type":"Manufacturing & Wholesale Goods"
        }
    ],
    "sg:phone":"+44 1249 814122",
    "sg:postcode":"SN11 0JZ",
    "sg:province":"Wiltshire",
    "sg:tags":[
        "abrasive",
        "product",
        "cleaning"
    ],
    "wof:name":"Swindon Abrasives Ltd.",
    "wof:placetype":"venue"
},
  "geometry": {"coordinates":[-2.006793,51.434013],"type":"Point"}
}