{
  "type": "Feature",
  "properties": {
    "addr:full":"Southlands Leisure Centre, Endeston Road Middlesbrough North Yorkshire TS3 0HG",
    "addr:postcode":"ts3 0hg",
    "addr:street":"Endeston Road",
    "iso:country":"GB",
    "sg:address":"Southlands Leisure Centre, Endeston Road",
    "sg:city":"Middlesbrough",
    "sg:classifiers":[
        {
            "category":"Organizations",
            "subcategory":"Non-profit Organization",
            "type":"Services"
        }
    ],
    "sg:phone":"+44 1642 324994",
    "sg:postcode":"TS3 0HG",
    "sg:province":"North Yorkshire",
    "sg:tags":[
        "organisation",
        "voluntary",
        "charity"
    ],
    "wof:name":"M E Association",
    "wof:placetype":"venue"
},
  "geometry": {"coordinates":[-1.19062,54.5527],"type":"Point"}
}