{
  "type": "Feature",
  "properties": {
    "addr:full":"Berkeley Arc, 209a Baker St Camden Greater London NW1 6AB",
    "addr:housenumber":"209a",
    "addr:postcode":"nw1 6ab",
    "addr:street":"Baker St",
    "iso:country":"GB",
    "sg:address":"Berkeley Arc, 209a Baker St",
    "sg:city":"Camden",
    "sg:classifiers":[
        {
            "category":"Arts & Performance",
            "subcategory":"Comedy Club",
            "type":"Entertainment"
        }
    ],
    "sg:phone":"+44 20 7486 5026",
    "sg:postcode":"NW1 6AB",
    "sg:province":"Greater London",
    "sg:tags":[
        "japanese"
    ],
    "wof:name":"Asuka The",
    "wof:placetype":"venue"
},
  "geometry": {"coordinates":[-0.1582300067,51.5224914551],"type":"Point"}
}