{
  "type": "Feature",
  "properties": {
    "addr:full":"Unit 4, Latchmore Industrial Park, Low Fields Rd Leeds West Yorkshire LS12 6DN",
    "addr:housenumber":"unit 4",
    "addr:postcode":"ls12 6dn",
    "addr:street":"Latchmore Industrial Park Low Fields Rd",
    "iso:country":"GB",
    "sg:address":"Unit 4, Latchmore Industrial Park, Low Fields Rd",
    "sg:city":"Leeds",
    "sg:classifiers":[
        {
            "category":"Government",
            "subcategory":"Post Office",
            "type":"Public Place"
        }
    ],
    "sg:phone":"+44 113 247 0102",
    "sg:postcode":"LS12 6DN",
    "sg:province":"West Yorkshire",
    "sg:tags":[
        "print",
        "typesetter"
    ],
    "wof:name":"The Mac Factory",
    "wof:placetype":"venue"
},
  "geometry": {"coordinates":[-1.575794,53.7798],"type":"Point"}
}