{
  "type": "Feature",
  "properties": {
    "iso:country":"GB",
    "sg:address":"Caroline House, High Street",
    "sg:city":"Stalybridge",
    "sg:classifiers":[
        {
            "category":"Building & Trades",
            "subcategory":"Cleaning & Sanitation",
            "type":"Services"
        }
    ],
    "sg:phone":"+44 161 303 1899",
    "sg:postcode":"SK15 1SE",
    "sg:province":"Greater Manchester",
    "sg:tags":[
        "asbestos",
        "removal"
    ],
    "wof:name":"Northern Insulation Contractors Ltd.",
    "wof:placetype":"venue"
},
  "geometry": {"coordinates":[-2.067339,53.479259],"type":"Point"}
}