{
  "type": "Feature",
  "properties": {
    "addr:full":"134 Queens Rd Carterton Gloucestershire OX18 3YQ",
    "addr:housenumber":"134",
    "addr:postcode":"ox18 3yq",
    "addr:street":"Queens Rd",
    "iso:country":"GB",
    "sg:address":"134 Queens Rd",
    "sg:city":"Carterton",
    "sg:classifiers":[
        {
            "category":"Utilities",
            "subcategory":"Electric",
            "type":"Services"
        }
    ],
    "sg:phone":"+44 1993 212644",
    "sg:postcode":"OX18 3YQ",
    "sg:province":"Gloucestershire",
    "sg:tags":[
        "electrical",
        "contractor"
    ],
    "wof:name":"Amp Electrical",
    "wof:placetype":"venue"
},
  "geometry": {"coordinates":[-1.5902849436,51.7547073364],"type":"Point"}
}