{
  "type": "Feature",
  "properties": {
    "addr:full":"79 Berkeley Street Glasgow Glasgow City G3 7DX",
    "addr:housenumber":"79",
    "addr:postcode":"g3 7dx",
    "addr:street":"Berkeley Street",
    "iso:country":"GB",
    "sg:address":"79 Berkeley Street",
    "sg:city":"Glasgow",
    "sg:classifiers":[
        {
            "category":"Building & Trades",
            "subcategory":"Equipment Rental",
            "type":"Services"
        },
        {
            "category":"Professional",
            "subcategory":"Computer Services",
            "type":"Services"
        }
    ],
    "sg:phone":"+44 141 221 7797",
    "sg:postcode":"G3 7DX",
    "sg:province":"Glasgow City",
    "sg:tags":[
        "leasing",
        "system",
        "software"
    ],
    "wof:name":"Berkeley Computer Hire Ltd.",
    "wof:placetype":"venue"
},
  "geometry": {"coordinates":[-4.2751932144,55.865196228],"type":"Point"}
}