{
  "type": "Feature",
  "properties": {
    "addr:full":"88-90 Commercial Street London Greater London E1 6LY",
    "addr:housenumber":"88-90",
    "addr:postcode":"e1 6ly",
    "addr:street":"Commercial Street",
    "iso:country":"GB",
    "sg:address":"88-90 Commercial Street",
    "sg:city":"London",
    "sg:classifiers":[
        {
            "category":"Shopping",
            "subcategory":"Clothing, Apparel, & Fashions",
            "type":"Retail Goods"
        }
    ],
    "sg:phone":"+44 20 7377 5488",
    "sg:postcode":"E1 6LY",
    "sg:province":"Greater London",
    "sg:tags":[
        "lingerie"
    ],
    "wof:name":"Eastern Hosiery",
    "wof:placetype":"venue"
},
  "geometry": {"coordinates":[-0.0742859989,51.5194702148],"type":"Point"}
}