{
  "type": "Feature",
  "properties": {
    "addr:full":"East Burnside Cupar Fife KY15 4BH",
    "addr:postcode":"ky15 4bh",
    "addr:street":"East Burnside",
    "iso:country":"GB",
    "sg:address":"East Burnside",
    "sg:city":"Cupar",
    "sg:classifiers":[
        {
            "category":"Building & Trades",
            "subcategory":"Cleaning & Sanitation",
            "type":"Services"
        }
    ],
    "sg:postcode":"KY15 4BH",
    "sg:province":"Fife",
    "sg:tags":[
        "commercial"
    ],
    "wof:name":"Eden Valet Carpet Cleaning",
    "wof:placetype":"venue"
},
  "geometry": {"coordinates":[-3.0117590427,56.3194961548],"type":"Point"}
}