{
  "type": "Feature",
  "properties": {
    "addr:full":"Ringway Northampton Northamptonshire NN4 8SQ",
    "addr:postcode":"nn4 8sq",
    "iso:country":"GB",
    "sg:address":"Ringway",
    "sg:city":"Northampton",
    "sg:classifiers":[
        {
            "category":"Bars & Pubs",
            "type":"Food & Drink"
        }
    ],
    "sg:phone":"+44 1604 766552",
    "sg:postcode":"NN4 8SQ",
    "sg:province":"Northamptonshire",
    "sg:tags":[
        "pubs",
        "inn"
    ],
    "wof:name":"The Double Four",
    "wof:placetype":"venue"
},
  "geometry": {"coordinates":[-0.917307,52.228523],"type":"Point"}
}