{
  "type": "Feature",
  "properties": {
    "addr:full":"17 Station Road Sidcup Kent DA15 7EN",
    "addr:housenumber":"17",
    "addr:postcode":"da15 7en",
    "addr:street":"Station Road",
    "iso:country":"GB",
    "sg:address":"17 Station Road",
    "sg:city":"Sidcup",
    "sg:classifiers":[
        {
            "category":"Retail",
            "subcategory":"Veterinary Services",
            "type":"Services"
        }
    ],
    "sg:phone":"+44 20 8303 4134",
    "sg:postcode":"DA15 7EN",
    "sg:province":"Kent",
    "sg:tags":[
        "surgeon"
    ],
    "wof:name":"Sidcup Veterinary Surgeons",
    "wof:placetype":"venue"
},
  "geometry": {"coordinates":[0.1010029987,51.4275054932],"type":"Point"}
}