{
  "type": "Feature",
  "properties": {
    "addr:full":"129-131 Grainger Street Newcastle-upon-tyne Tyne and Wear NE1 5AE",
    "addr:housenumber":"129-131",
    "addr:postcode":"ne1 5ae",
    "addr:street":"Grainger Street",
    "iso:country":"GB",
    "sg:address":"129-131 Grainger Street",
    "sg:city":"Newcastle-upon-tyne",
    "sg:classifiers":[
        {
            "category":"Sports & Exercise",
            "subcategory":"Sports Center",
            "type":"Entertainment"
        }
    ],
    "sg:phone":"+44 191 261 5737",
    "sg:postcode":"NE1 5AE",
    "sg:province":"Tyne and Wear",
    "sg:tags":[
        "shop",
        "good"
    ],
    "wof:name":"First Sport Ltd.",
    "wof:placetype":"venue"
},
  "geometry": {"coordinates":[-1.613587,54.973022],"type":"Point"}
}