{
  "type": "Feature",
  "properties": {
    "addr:full":"39 West Don Street Sheffield South Yorkshire S6 3BH",
    "addr:housenumber":"39",
    "addr:postcode":"s6 3bh",
    "addr:street":"West Don Street",
    "iso:country":"GB",
    "sg:address":"39 West Don Street",
    "sg:city":"Sheffield",
    "sg:classifiers":[
        {
            "category":"Building & Trades",
            "subcategory":"Construction",
            "type":"Services"
        }
    ],
    "sg:phone":"+44 114 285 5973",
    "sg:postcode":"S6 3BH",
    "sg:province":"South Yorkshire",
    "sg:tags":[
        "repair",
        "window",
        "replacement"
    ],
    "wof:name":"Don Valley Window Systems Ltd.",
    "wof:placetype":"venue"
},
  "geometry": {"coordinates":[-1.4853509665,53.3928375244],"type":"Point"}
}