{
  "type": "Feature",
  "properties": {
    "iso:country":"GB",
    "sg:address":"Woodbridge Mill",
    "sg:city":"Devizes",
    "sg:classifiers":[
        {
            "category":"Farming",
            "subcategory":"Livestock Farm",
            "type":"Manufacturing & Wholesale Goods"
        }
    ],
    "sg:postcode":"SN10 5RP",
    "sg:province":"Wiltshire",
    "sg:tags":[
        "others"
    ],
    "wof:name":"T D Sharp & Sons",
    "wof:placetype":"venue"
},
  "geometry": {"coordinates":[-1.9950309992,51.3514785767],"type":"Point"}
}