{
  "type": "Feature",
  "properties": {
    "addr:full":"Rowan Court, Green Street Manchester Greater Manchester M14 6TN",
    "addr:postcode":"m14 6tn",
    "addr:street":"Rowan Court;Street",
    "iso:country":"GB",
    "sg:address":"Rowan Court, Green Street",
    "sg:city":"Manchester",
    "sg:classifiers":[
        {
            "category":"Organizations",
            "subcategory":"Community Association",
            "type":"Services"
        }
    ],
    "sg:phone":"+44 161 224 8699",
    "sg:postcode":"M14 6TN",
    "sg:province":"Greater Manchester",
    "sg:tags":[
        "co-operatives",
        "society",
        "housing",
        "trust"
    ],
    "sg:website":"http://www.anchor.org.uk",
    "wof:name":"Anchor Trust",
    "wof:placetype":"venue"
},
  "geometry": {"coordinates":[-2.2114241123,53.4358100891],"type":"Point"}
}