{
  "type": "Feature",
  "properties": {
    "iso:country":"GB",
    "sg:address":"Tooks Farm  Great Warley St, Great Warley",
    "sg:city":"Brentwood",
    "sg:classifiers":[
        {
            "category":"Farming",
            "subcategory":"Livestock Farm",
            "type":"Manufacturing & Wholesale Goods"
        }
    ],
    "sg:postcode":"CM13 3JP",
    "sg:province":"Essex",
    "sg:tags":[
        "others"
    ],
    "wof:name":"Tooks Farm Ltd",
    "wof:placetype":"venue"
},
  "geometry": {"coordinates":[0.286459,51.594494],"type":"Point"}
}