{
  "type": "Feature",
  "properties": {
    "iso:country":"GB",
    "sg:address":"400 Harrow Road",
    "sg:city":"London",
    "sg:classifiers":[
        {
            "category":"Building & Trades",
            "subcategory":"Construction",
            "type":"Services"
        }
    ],
    "sg:postcode":"W9 2HU",
    "sg:province":"Greater London",
    "sg:tags":[
        "builder"
    ],
    "wof:name":"M.C.R. (Building Contractors) Ltd",
    "wof:placetype":"venue"
},
  "geometry": {"coordinates":[-0.196849,51.523453],"type":"Point"}
}