{
  "type": "Feature",
  "properties": {
    "iso:country":"GB",
    "sg:address":"48 Station Approach",
    "sg:city":"Bicester",
    "sg:classifiers":[
        {
            "category":"Taxi",
            "type":"Transportation"
        }
    ],
    "sg:phone":"+44 1869 252552",
    "sg:postcode":"OX6 7BZ",
    "sg:province":"Oxfordshire",
    "sg:tags":[
        "mini",
        "cab"
    ],
    "wof:name":"001 Alpha Cars",
    "wof:placetype":"venue"
},
  "geometry": {"coordinates":[-1.1491910219,51.8930702209],"type":"Point"}
}