{
  "type": "Feature",
  "properties": {
    "iso:country":"GB",
    "sg:address":"Denby, Ripley",
    "sg:city":"Derby",
    "sg:classifiers":[
        {
            "category":"Shopping",
            "subcategory":"Crafts & Fabrics",
            "type":"Retail Goods"
        }
    ],
    "sg:phone":"+44 1773 570800",
    "sg:postcode":"DE5 8NX",
    "sg:province":"Derbyshire",
    "sg:tags":[
        "ceramic"
    ],
    "wof:name":"Ross Ceramics Ltd.",
    "wof:placetype":"venue"
},
  "geometry": {"coordinates":[-1.4139,53.022331],"type":"Point"}
}