{
  "type": "Feature",
  "properties": {
    "addr:full":"18 Brougham Glades, Stanway Colchester Essex CO3 5YF",
    "addr:housenumber":"18",
    "addr:postcode":"co3 5yf",
    "addr:street":"Brougham Glades",
    "iso:country":"GB",
    "sg:address":"18 Brougham Glades, Stanway",
    "sg:city":"Colchester",
    "sg:classifiers":[
        {
            "category":"Professional",
            "subcategory":"Business Services",
            "type":"Services"
        }
    ],
    "sg:phone":"+44 1206 765471",
    "sg:postcode":"CO3 5YF",
    "sg:province":"Essex",
    "sg:tags":[
        "shop",
        "cleaning"
    ],
    "wof:name":"Avondale Office Cleaning",
    "wof:placetype":"venue"
},
  "geometry": {"coordinates":[0.84286,51.883598],"type":"Point"}
}