{
  "type": "Feature",
  "properties": {
    "iso:country":"GB",
    "sg:address":"178 Hope Street",
    "sg:city":"Glasgow",
    "sg:classifiers":[
        {
            "category":"Professional",
            "subcategory":"Printing & Photocopies",
            "type":"Services"
        }
    ],
    "sg:phone":"+44 141 332 5552",
    "sg:postcode":"G2 2TZ",
    "sg:province":"Glasgow City",
    "sg:tags":[
        "computer",
        "tag",
        "label"
    ],
    "wof:name":"N S  Macfarlane & Co.  Ltd.",
    "wof:placetype":"venue"
},
  "geometry": {"coordinates":[-4.257352,55.86372],"type":"Point"}
}