{
  "type": "Feature",
  "properties": {
    "addr:full":"403 Seaside Eastbourne East Sussex BN22 7RT",
    "addr:housenumber":"403",
    "addr:postcode":"bn22 7rt",
    "addr:street":"Seaside",
    "iso:country":"GB",
    "sg:address":"403 Seaside",
    "sg:city":"Eastbourne",
    "sg:classifiers":[
        {
            "category":"Building & Trades",
            "subcategory":"Equipment Rental",
            "type":"Services"
        }
    ],
    "sg:phone":"+44 1323 410057",
    "sg:postcode":"BN22 7RT",
    "sg:province":"East Sussex",
    "sg:tags":[
        "hire",
        "centre"
    ],
    "wof:name":"Hss Hire Shops",
    "wof:placetype":"venue"
},
  "geometry": {"coordinates":[0.303394,50.782749],"type":"Point"}
}