{
  "type": "Feature",
  "properties": {
    "iso:country":"GB",
    "sg:address":"Benett, High Street, Wrington",
    "sg:city":"Bristol",
    "sg:classifiers":[
        {
            "category":"Banks & Credit Unions",
            "subcategory":"Financial Services",
            "type":"Services"
        }
    ],
    "sg:postcode":"BS40 5QB",
    "sg:province":"Somerset",
    "sg:tags":[
        "consultant"
    ],
    "wof:name":"Sion Investments Ltd",
    "wof:placetype":"venue"
},
  "geometry": {"coordinates":[-2.762419,51.361034],"type":"Point"}
}