{
  "type": "Feature",
  "properties": {
    "addr:full":"4 Free School Court Bridgend Bridgend CF31 3AF",
    "addr:housenumber":"4",
    "addr:postcode":"cf31 3af",
    "addr:street":"Free School Court",
    "iso:country":"GB",
    "sg:address":"4 Free School Court",
    "sg:city":"Bridgend",
    "sg:classifiers":[
        {
            "category":"Shopping",
            "type":"Retail Goods"
        }
    ],
    "sg:phone":"+44 1656 767684",
    "sg:postcode":"CF31 3AF",
    "sg:province":"Bridgend",
    "sg:tags":[
        "part",
        "accessory"
    ],
    "wof:name":"Sparesworld Ltd.",
    "wof:placetype":"venue"
},
  "geometry": {"coordinates":[-3.574434042,51.5035400391],"type":"Point"}
}