{
  "type": "Feature",
  "properties": {
    "iso:country":"GB",
    "sg:address":"8 Bold Street",
    "sg:city":"Southport",
    "sg:classifiers":[
        {
            "category":"Shopping",
            "subcategory":"Shoes",
            "type":"Retail Goods"
        }
    ],
    "sg:phone":"+44 1704 535114",
    "sg:postcode":"PR9 0DD",
    "sg:province":"Lancashire",
    "sg:tags":[
        "shop",
        "retailer",
        "footwear"
    ],
    "wof:name":"T Gelder & Sons",
    "wof:placetype":"venue"
},
  "geometry": {"coordinates":[-3.002602,53.650696],"type":"Point"}
}