{
  "type": "Feature",
  "properties": {
    "iso:country":"GB",
    "sg:address":"48-49 Churchgate",
    "sg:city":"Loughborough",
    "sg:classifiers":[
        {
            "category":"Shopping",
            "subcategory":"Clothing, Apparel, & Fashions",
            "type":"Retail Goods"
        },
        {
            "category":"Shopping",
            "subcategory":"Baby Store",
            "type":"Retail Goods"
        }
    ],
    "sg:phone":"+44 1509 234532",
    "sg:postcode":"LE11 1UE",
    "sg:province":"Leicestershire",
    "sg:tags":[
        "child",
        "nursery",
        "babywear",
        "accessory"
    ],
    "wof:name":"KINDERGARDEN ENTERPRISES",
    "wof:placetype":"venue"
},
  "geometry": {"coordinates":[-1.2053339481,52.7732658386],"type":"Point"}
}