{
  "type": "Feature",
  "properties": {
    "iso:country":"GB",
    "sg:address":"8 Higher Strand, St Marys",
    "sg:city":"St Marys",
    "sg:classifiers":[
        {
            "category":"Building & Trades",
            "subcategory":"Construction",
            "type":"Services"
        }
    ],
    "sg:phone":"+44 1720 422344",
    "sg:postcode":"TR21 0PT",
    "sg:province":"Cornwall",
    "sg:tags":[
        "builder"
    ],
    "wof:name":"Dovetail Builders",
    "wof:placetype":"venue"
},
  "geometry": {"coordinates":[-6.314754,49.914474],"type":"Point"}
}