{
  "type": "Feature",
  "properties": {
    "addr:full":"Manor Mills, Manor Road Leeds West Yorkshire LS11 5PZ",
    "addr:postcode":"ls11 5pz",
    "addr:street":"Manor Mills Manor Road",
    "iso:country":"GB",
    "sg:address":"Manor Mills, Manor Road",
    "sg:city":"Leeds",
    "sg:classifiers":[
        {
            "category":"Retail",
            "subcategory":"Auto Repair",
            "type":"Services"
        }
    ],
    "sg:postcode":"LS11 5PZ",
    "sg:province":"West Yorkshire",
    "sg:tags":[
        "modification",
        "garage"
    ],
    "wof:name":"Manor Motors",
    "wof:placetype":"venue"
},
  "geometry": {"coordinates":[-1.546587,53.794495],"type":"Point"}
}