{
  "type": "Feature",
  "properties": {
    "iso:country":"GB",
    "sg:address":"4-6 Abbey Walk",
    "sg:city":"Grimsby",
    "sg:classifiers":[
        {
            "category":"Professional",
            "subcategory":"Employment Agencies",
            "type":"Services"
        }
    ],
    "sg:phone":"+44 1472 311067",
    "sg:postcode":"DN31 1NB",
    "sg:province":"Lincolnshire",
    "sg:tags":[
        "consultant"
    ],
    "wof:name":"Interim Employment Ltd.",
    "wof:placetype":"venue"
},
  "geometry": {"coordinates":[-0.0840469971,53.564491272],"type":"Point"}
}