{
  "type": "Feature",
  "properties": {
    "addr:full":"13 Naseby Road, Moordown Bournemouth Dorset BH9 1SP",
    "addr:housenumber":"13",
    "addr:postcode":"bh9 1sp",
    "addr:street":"Naseby Road",
    "iso:country":"GB",
    "sg:address":"13 Naseby Road, Moordown",
    "sg:city":"Bournemouth",
    "sg:classifiers":[
        {
            "category":"Retail",
            "subcategory":"Auto Repair",
            "type":"Services"
        }
    ],
    "sg:phone":"+44 1202 514422",
    "sg:postcode":"BH9 1SP",
    "sg:province":"Dorset",
    "sg:tags":[
        "engine",
        "car",
        "specialist"
    ],
    "wof:name":"Tune Up",
    "wof:placetype":"venue"
},
  "geometry": {"coordinates":[-1.869563,50.749798],"type":"Point"}
}