{
  "type": "Feature",
  "properties": {
    "addr:full":"49 Princes Place London Greater London W11 4QA",
    "addr:housenumber":"49",
    "addr:postcode":"w11 4qa",
    "addr:street":"Princes Place",
    "iso:country":"GB",
    "sg:address":"49 Princes Place",
    "sg:city":"London",
    "sg:classifiers":[
        {
            "category":"Professional",
            "subcategory":"Management & Consulting",
            "type":"Services"
        }
    ],
    "sg:postcode":"W11 4QA",
    "sg:province":"Greater London",
    "sg:tags":[
        "consultant",
        "promotion",
        "direct",
        "sale"
    ],
    "wof:name":"Creative Concept Development",
    "wof:placetype":"venue"
},
  "geometry": {"coordinates":[-0.209989,51.508034],"type":"Point"}
}