{
  "type": "Feature",
  "properties": {
    "addr:full":"Unit 6a National Avenue Industrial Estat, Bontoft Avenue Hull East Riding of Yorkshire HU5 4HF",
    "addr:housenumber":"unit 6a",
    "addr:postcode":"hu5 4hf",
    "addr:street":"National Avenue;Estat Bontoft Avenue",
    "iso:country":"GB",
    "sg:address":"Unit 6a National Avenue Industrial Estat, Bontoft Avenue",
    "sg:city":"Hull",
    "sg:classifiers":[
        {
            "category":"Wholesale",
            "subcategory":"Machinery & Supplies",
            "type":"Manufacturing & Wholesale Goods"
        }
    ],
    "sg:phone":"+44 1482 442123",
    "sg:postcode":"HU5 4HF",
    "sg:province":"East Riding of Yorkshire",
    "sg:tags":[
        "pump"
    ],
    "wof:name":"Sld Pumps",
    "wof:placetype":"venue"
},
  "geometry": {"coordinates":[-0.382984,53.763691],"type":"Point"}
}