{
  "type": "Feature",
  "properties": {
    "addr:full":"London Road East Grinstead East Sussex RH19 1QE",
    "addr:postcode":"rh19 1qe",
    "addr:street":"London Road",
    "iso:country":"GB",
    "sg:address":"London Road",
    "sg:city":"East Grinstead",
    "sg:classifiers":[
        {
            "category":"Travel",
            "subcategory":"Hotels & Motels",
            "type":"Entertainment"
        }
    ],
    "sg:phone":"+44 1342 317222",
    "sg:postcode":"RH19 1QE",
    "sg:province":"East Sussex",
    "sg:tags":[
        "house",
        "guest"
    ],
    "sg:website":"http://www.grinsteadlodge.co.uk",
    "wof:name":"Grinstead Lodge Guest House",
    "wof:placetype":"venue"
},
  "geometry": {"coordinates":[-0.03084,51.135735],"type":"Point"}
}