{
  "type": "Feature",
  "properties": {
    "addr:full":"38-40 Upper Clapton Road London Greater London E5 8BQ",
    "addr:housenumber":"38-40",
    "addr:postcode":"e5 8bq",
    "addr:street":"Upper Clapton Road",
    "iso:country":"GB",
    "sg:address":"38-40 Upper Clapton Road",
    "sg:city":"London",
    "sg:classifiers":[
        {
            "category":"Shopping",
            "subcategory":"Computers & Home Electronics",
            "type":"Retail Goods"
        }
    ],
    "sg:phone":"+44 20 8806 5072",
    "sg:postcode":"E5 8BQ",
    "sg:province":"Greater London",
    "wof:name":"Ness Industries Ltd.",
    "wof:placetype":"venue"
},
  "geometry": {"coordinates":[-0.056684,51.5602],"type":"Point"}
}