{
  "type": "Feature",
  "properties": {
    "addr:full":"1 Cayton Drive, Acklam Middlesbrough North Yorkshire TS5 7NJ",
    "addr:housenumber":"1",
    "addr:postcode":"ts5 7nj",
    "addr:street":"Cayton Drive",
    "iso:country":"GB",
    "sg:address":"1 Cayton Drive, Acklam",
    "sg:city":"Middlesbrough",
    "sg:classifiers":[
        {
            "category":"Health Services",
            "subcategory":"Podiatrist",
            "type":"Services"
        }
    ],
    "sg:postcode":"TS5 7NJ",
    "sg:province":"North Yorkshire",
    "sg:tags":[
        "podiatrists",
        "chiropodist"
    ],
    "wof:name":"C M O'Donnell",
    "wof:placetype":"venue"
},
  "geometry": {"coordinates":[-1.2392090559,54.5468940735],"type":"Point"}
}