{
  "type": "Feature",
  "properties": {
    "addr:full":"2nd Floor, 18 Temple Street Aylesbury Buckinghamshire HP20 2RQ",
    "addr:housenumber":"2nd floor 18",
    "addr:postcode":"hp20 2rq",
    "addr:street":"Temple Street",
    "iso:country":"GB",
    "sg:address":"2nd Floor, 18 Temple Street",
    "sg:city":"Aylesbury",
    "sg:classifiers":[
        {
            "category":"Freight",
            "type":"Transportation"
        },
        {
            "category":"Government",
            "subcategory":"Post Office",
            "type":"Public Place"
        }
    ],
    "sg:phone":"+44 1296 394553",
    "sg:postcode":"HP20 2RQ",
    "sg:province":"Buckinghamshire",
    "sg:tags":[
        "haulage",
        "messenger",
        "courier",
        "road"
    ],
    "wof:name":"Red Shift Motorcycle & Van Despatch",
    "wof:placetype":"venue"
},
  "geometry": {"coordinates":[-0.814185,51.816345],"type":"Point"}
}