{
  "type": "Feature",
  "properties": {
    "addr:full":"11 Hall Street Stoke-on-trent Staffordshire ST6 4BB",
    "addr:housenumber":"11",
    "addr:postcode":"st6 4bb",
    "addr:street":"Hall Street",
    "iso:country":"GB",
    "sg:address":"11 Hall Street",
    "sg:city":"Stoke-on-trent",
    "sg:classifiers":[
        {
            "category":"Retail",
            "subcategory":"Auto Repair",
            "type":"Services"
        }
    ],
    "sg:phone":"+44 1782 836565",
    "sg:postcode":"ST6 4BB",
    "sg:province":"Staffordshire",
    "sg:tags":[
        "modification",
        "garage"
    ],
    "wof:name":"Malcolm's Motor Care",
    "wof:placetype":"venue"
},
  "geometry": {"coordinates":[-2.2013630867,53.045627594],"type":"Point"}
}