{
  "type": "Feature",
  "properties": {
    "addr:full":"Taroveor Road Penzance Cornwall TR18 2AA",
    "addr:postcode":"tr18 2aa",
    "addr:street":"Taroveor Road",
    "iso:country":"GB",
    "sg:address":"Taroveor Road",
    "sg:city":"Penzance",
    "sg:classifiers":[
        {
            "category":"Cinema",
            "subcategory":"Movie Rental",
            "type":"Entertainment"
        }
    ],
    "sg:phone":"+44 1736 367516",
    "sg:postcode":"TR18 2AA",
    "sg:province":"Cornwall",
    "sg:tags":[
        "video",
        "library"
    ],
    "wof:name":"Penwith Video Library",
    "wof:placetype":"venue"
},
  "geometry": {"coordinates":[-5.5386691093,50.1209831238],"type":"Point"}
}