{
  "type": "Feature",
  "properties": {
    "addr:full":"11 Pedmore Road, Lye Stourbridge West Midlands DY9 8DJ",
    "addr:housenumber":"11",
    "addr:postcode":"dy9 8dj",
    "addr:street":"Pedmore Road",
    "iso:country":"GB",
    "sg:address":"11 Pedmore Road, Lye",
    "sg:city":"Stourbridge",
    "sg:classifiers":[
        {
            "category":"Personal",
            "subcategory":"Beauty Salon",
            "type":"Services"
        }
    ],
    "sg:phone":"+44 1384 896100",
    "sg:postcode":"DY9 8DJ",
    "sg:province":"West Midlands",
    "sg:tags":[
        "unisex",
        "ladies",
        "hairdresser"
    ],
    "wof:name":"Hair Charm",
    "wof:placetype":"venue"
},
  "geometry": {"coordinates":[-2.1179130077,52.4574317932],"type":"Point"}
}