{
  "type": "Feature",
  "properties": {
    "addr:full":"Tea Garden, Chine Lodge Shanklin Isle of Wight PO37 6BW",
    "addr:postcode":"po37 6bw",
    "addr:street":"Shanklin",
    "iso:country":"GB",
    "sg:address":"Tea Garden, Chine Lodge",
    "sg:city":"Shanklin",
    "sg:classifiers":[
        {
            "category":"Cafe",
            "type":"Food & Drink"
        }
    ],
    "sg:phone":"+44 1983 867142",
    "sg:postcode":"PO37 6BW",
    "sg:province":"Isle of Wight",
    "sg:tags":[
        "tea",
        "room"
    ],
    "wof:name":"Shanklin Chine",
    "wof:placetype":"venue"
},
  "geometry": {"coordinates":[-1.179239,50.626976],"type":"Point"}
}