{
  "type": "Feature",
  "properties": {
    "iso:country":"GB",
    "sg:address":"86 St Johns Road",
    "sg:city":"Faversham",
    "sg:classifiers":[
        {
            "category":"Freight",
            "type":"Transportation"
        }
    ],
    "sg:postcode":"ME13 8EN",
    "sg:province":"Kent",
    "sg:tags":[
        "haulage",
        "road"
    ],
    "wof:name":"P K Trucking",
    "wof:placetype":"venue"
},
  "geometry": {"coordinates":[0.894084,51.312794],"type":"Point"}
}