{
  "type": "Feature",
  "properties": {
    "addr:full":"Coast Road, Mostyn Holywell Denbighshire CH8 9HF",
    "addr:postcode":"ch8 9hf",
    "addr:street":"Coast Road",
    "iso:country":"GB",
    "sg:address":"Coast Road, Mostyn",
    "sg:city":"Holywell",
    "sg:classifiers":[
        {
            "category":"Bars & Pubs",
            "type":"Food & Drink"
        }
    ],
    "sg:phone":"+44 1745 560292",
    "sg:postcode":"CH8 9HF",
    "sg:province":"Denbighshire",
    "sg:tags":[
        "pubs",
        "inn"
    ],
    "wof:name":"Lletty Hotel",
    "wof:placetype":"venue"
},
  "geometry": {"coordinates":[-3.258082,53.312134],"type":"Point"}
}