{
  "type": "Feature",
  "properties": {
    "addr:full":"100 Wavertree Blvd, Wavertree Technology Park Liverpool Merseyside L7 9PT",
    "addr:housenumber":"100",
    "addr:postcode":"l7 9pt",
    "addr:street":"Wavertree Blvd;Technology Park",
    "iso:country":"GB",
    "sg:address":"100 Wavertree Blvd, Wavertree Technology Park",
    "sg:city":"Liverpool",
    "sg:classifiers":[
        {
            "category":"Wholesale",
            "subcategory":"Medical Equipment & Supplies",
            "type":"Manufacturing & Wholesale Goods"
        }
    ],
    "sg:postcode":"L7 9PT",
    "sg:province":"Merseyside",
    "sg:tags":[
        "hospital"
    ],
    "wof:name":"Scientific Hospital Supplies Holdings Ltd.",
    "wof:placetype":"venue"
},
  "geometry": {"coordinates":[-2.937933,53.405418],"type":"Point"}
}