{
  "type": "Feature",
  "properties": {
    "iso:country":"GB",
    "sg:address":"32 Greenways, Bunwell",
    "sg:city":"Norwich",
    "sg:classifiers":[
        {
            "category":"Personal",
            "type":"Services"
        }
    ],
    "sg:postcode":"NR16 1QZ",
    "sg:province":"Norfolk",
    "sg:tags":[
        "dressmaker"
    ],
    "wof:name":"C A Bunting",
    "wof:placetype":"venue"
},
  "geometry": {"coordinates":[1.15279,52.499561],"type":"Point"}
}