{
  "type": "Feature",
  "properties": {
    "iso:country":"GB",
    "sg:address":"Sandy Hill Lane, Overstone Road",
    "sg:city":"Northampton",
    "sg:classifiers":[
        {
            "category":"Retail",
            "subcategory":"Auto Repair",
            "type":"Services"
        }
    ],
    "sg:postcode":"NN3 7JB",
    "sg:province":"Northamptonshire",
    "sg:tags":[
        "modification",
        "garage"
    ],
    "wof:name":"Moulton Autocare",
    "wof:placetype":"venue"
},
  "geometry": {"coordinates":[-0.842276,52.290173],"type":"Point"}
}