{
  "type": "Feature",
  "properties": {
    "iso:country":"GB",
    "sg:address":"3 Wirral Way, Noctorum",
    "sg:city":"Prenton",
    "sg:classifiers":[
        {
            "category":"Building & Trades",
            "subcategory":"Construction",
            "type":"Services"
        }
    ],
    "sg:postcode":"CH43 9SF",
    "sg:province":"Merseyside",
    "sg:tags":[
        "builder"
    ],
    "wof:name":"Plant,Graham & Cathy Plant,",
    "wof:placetype":"venue"
},
  "geometry": {"coordinates":[-3.0804400444,53.3878898621],"type":"Point"}
}