{
  "type": "Feature",
  "properties": {
    "addr:full":"16-18 Archangel Square, Camp Hill Northampton Northamptonshire NN4 9RA",
    "addr:housenumber":"16-18",
    "addr:postcode":"nn4 9ra",
    "addr:street":"Archangel Square",
    "iso:country":"GB",
    "sg:address":"16-18 Archangel Square, Camp Hill",
    "sg:city":"Northampton",
    "sg:classifiers":[
        {
            "category":"Farming",
            "subcategory":"Nursery",
            "type":"Manufacturing & Wholesale Goods"
        }
    ],
    "sg:phone":"+44 1604 701291",
    "sg:postcode":"NN4 9RA",
    "sg:province":"Northamptonshire",
    "sg:tags":[
        "creche"
    ],
    "wof:name":"Brats Day Nursery Ltd.",
    "wof:placetype":"venue"
},
  "geometry": {"coordinates":[-0.9253389835,52.2234344482],"type":"Point"}
}