{
  "type": "Feature",
  "properties": {
    "addr:full":"20 Hawkins La Burton On Trent Derbyshire DE14 1PT",
    "addr:housenumber":"20",
    "addr:postcode":"de14 1pt",
    "addr:street":"Hawkins La Burton On",
    "iso:country":"GB",
    "sg:address":"20 Hawkins La",
    "sg:city":"Burton On Trent",
    "sg:classifiers":[
        {
            "category":"Shopping",
            "subcategory":"News",
            "type":"Retail Goods"
        }
    ],
    "sg:phone":"+44 1283 510581",
    "sg:postcode":"DE14 1PT",
    "sg:province":"Derbyshire",
    "sg:tags":[
        "newsagent"
    ],
    "wof:name":"Mughal News",
    "wof:placetype":"venue"
},
  "geometry": {"coordinates":[-1.6331410408,52.809261322],"type":"Point"}
}