{
  "type": "Feature",
  "properties": {
    "addr:full":"43a The Avenue Minehead Somerset TA24 5BB",
    "addr:housenumber":"43a",
    "addr:postcode":"ta24 5bb",
    "addr:street":"The Avenue",
    "iso:country":"GB",
    "sg:address":"43a The Avenue",
    "sg:city":"Minehead",
    "sg:classifiers":[
        {
            "category":"Shopping",
            "subcategory":"Department Store",
            "type":"Retail Goods"
        }
    ],
    "sg:postcode":"TA24 5BB",
    "sg:province":"Somerset",
    "wof:name":"Gladeday",
    "wof:placetype":"venue"
},
  "geometry": {"coordinates":[-3.472863,51.206863],"type":"Point"}
}