{
  "type": "Feature",
  "properties": {
    "iso:country":"GB",
    "sg:address":"The Clubhouse, Minley Road",
    "sg:city":"Fleet",
    "sg:classifiers":[
        {
            "category":"Sports & Exercise",
            "subcategory":"Golf",
            "type":"Entertainment"
        }
    ],
    "sg:phone":"+44 1252 616443",
    "sg:postcode":"GU51 1RE",
    "sg:province":"Hampshire",
    "sg:tags":[
        "club",
        "course"
    ],
    "wof:name":"North Hants Golf Club",
    "wof:placetype":"venue"
},
  "geometry": {"coordinates":[-0.8306699991,51.2963409424],"type":"Point"}
}