{
  "type": "Feature",
  "properties": {
    "addr:full":"24 Mead View Cambridge Cambridgeshire CB4 5BH",
    "addr:housenumber":"24",
    "addr:postcode":"cb4 5bh",
    "addr:street":"Mead View",
    "iso:country":"GB",
    "sg:address":"24 Mead View",
    "sg:city":"Cambridge",
    "sg:classifiers":[
        {
            "category":"Freight",
            "type":"Transportation"
        }
    ],
    "sg:phone":"+44 1223 233769",
    "sg:postcode":"CB4 5BH",
    "sg:province":"Cambridgeshire",
    "sg:tags":[
        "forwarders"
    ],
    "wof:name":"Camefreight International",
    "wof:placetype":"venue"
},
  "geometry": {"coordinates":[0.0625599995,52.2599258423],"type":"Point"}
}