{
  "type": "Feature",
  "properties": {
    "iso:country":"GB",
    "sg:address":"Baugh Road",
    "sg:city":"Sidcup",
    "sg:classifiers":[
        {
            "category":"Education",
            "subcategory":"School",
            "type":"Public Place"
        }
    ],
    "sg:phone":"+44 20 8302 6029",
    "sg:postcode":"DA14 5ED",
    "sg:province":"Kent",
    "sg:tags":[
        "local",
        "authority"
    ],
    "wof:name":"St. Peter Chanel R C Primary School",
    "wof:placetype":"venue"
},
  "geometry": {"coordinates":[0.118872,51.42049],"type":"Point"}
}