{
  "type": "Feature",
  "properties": {
    "iso:country":"GB",
    "sg:address":"126 Drymen Road, Bearsden",
    "sg:city":"Glasgow",
    "sg:classifiers":[
        {
            "category":"Professional",
            "subcategory":"Accounting & Tax Preparation",
            "type":"Services"
        }
    ],
    "sg:phone":"+44 141 942 7010",
    "sg:postcode":"G61 3RB",
    "sg:province":"East Dunbartonshire",
    "sg:tags":[
        "accountant"
    ],
    "wof:name":"Camhouse Ltd.",
    "wof:placetype":"venue"
},
  "geometry": {"coordinates":[-4.3340611458,55.9202919006],"type":"Point"}
}