{
  "type": "Feature",
  "properties": {
    "addr:full":"948 Brighton Rd Purley Surrey CR8 2LP",
    "addr:housenumber":"948",
    "addr:postcode":"cr8 2lp",
    "addr:street":"Brighton Rd",
    "iso:country":"GB",
    "sg:address":"948 Brighton Rd",
    "sg:city":"Purley",
    "sg:classifiers":[
        {
            "category":"Food & Beverages",
            "subcategory":"Supermarket",
            "type":"Retail Goods"
        }
    ],
    "sg:postcode":"CR8 2LP",
    "sg:province":"Surrey",
    "wof:name":"Ahmad,M,",
    "wof:placetype":"venue"
},
  "geometry": {"coordinates":[-0.116381,51.339119],"type":"Point"}
}