{
  "type": "Feature",
  "properties": {
    "iso:country":"GB",
    "sg:address":"15 Smedley Lane",
    "sg:city":"Manchester",
    "sg:classifiers":[
        {
            "category":"Health Services",
            "subcategory":"Nursing And Care Facility",
            "type":"Services"
        }
    ],
    "sg:phone":"+44 161 203 4137",
    "sg:postcode":"M8 8UJ",
    "sg:province":"Greater Manchester",
    "sg:tags":[
        "home"
    ],
    "wof:name":"Laburnam Lodge",
    "wof:placetype":"venue"
},
  "geometry": {"coordinates":[-2.233852,53.504234],"type":"Point"}
}