{
  "type": "Feature",
  "properties": {
    "addr:full":"Unthank Rd Norwich Norfolk NR4 7QJ",
    "addr:postcode":"nr4 7qj",
    "addr:street":"Unthank Rd",
    "iso:country":"GB",
    "sg:address":"Unthank Rd",
    "sg:city":"Norwich",
    "sg:classifiers":[
        {
            "category":"Organizations",
            "subcategory":"Non-profit Organization",
            "type":"Services"
        }
    ],
    "sg:phone":"+44 1603 259916",
    "sg:postcode":"NR4 7QJ",
    "sg:province":"Norfolk",
    "sg:tags":[
        "organisation",
        "voluntary",
        "charity"
    ],
    "wof:name":"Pym House",
    "wof:placetype":"venue"
},
  "geometry": {"coordinates":[1.2675750256,52.619140625],"type":"Point"}
}