{
  "type": "Feature",
  "properties": {
    "addr:full":"7 Caroe Court, Bery Street London Greater London N9 7LE",
    "addr:housenumber":"7",
    "addr:postcode":"n9 7le",
    "addr:street":"Caroe Court Bery Street",
    "iso:country":"GB",
    "sg:address":"7 Caroe Court, Bery Street",
    "sg:city":"London",
    "sg:classifiers":[
        {
            "category":"Government",
            "subcategory":"Office",
            "type":"Public Place"
        }
    ],
    "sg:postcode":"N9 7LE",
    "sg:province":"Greater London",
    "sg:tags":[
        "press",
        "cutting",
        "bureau"
    ],
    "wof:name":"Charity Media Monotoring",
    "wof:placetype":"venue"
},
  "geometry": {"coordinates":[-0.05602,51.630421],"type":"Point"}
}