{
  "type": "Feature",
  "properties": {
    "iso:country":"GB",
    "sg:address":"Kingswood Nursery, Bullsmoor La",
    "sg:city":"Enfield",
    "sg:classifiers":[
        {
            "category":"Retail",
            "subcategory":"Repair Shop",
            "type":"Services"
        }
    ],
    "sg:postcode":"EN1 4SF",
    "sg:province":"Greater London",
    "sg:tags":[
        "upholsterer"
    ],
    "wof:name":"Redfern,K,",
    "wof:placetype":"venue"
},
  "geometry": {"coordinates":[-0.05167,51.68055],"type":"Point"}
}