{
  "type": "Feature",
  "properties": {
    "addr:full":"40 Commercial Street Shipley West Yorkshire BD18 3SP",
    "addr:housenumber":"40",
    "addr:postcode":"bd18 3sp",
    "addr:street":"Commercial Street",
    "iso:country":"GB",
    "sg:address":"40 Commercial Street",
    "sg:city":"Shipley",
    "sg:classifiers":[
        {
            "category":"Shopping",
            "subcategory":"Used Merchandise",
            "type":"Retail Goods"
        }
    ],
    "sg:phone":"+44 1274 582642",
    "sg:postcode":"BD18 3SP",
    "sg:province":"West Yorkshire",
    "sg:tags":[
        "shop",
        "second-hand"
    ],
    "wof:name":"Trader",
    "wof:placetype":"venue"
},
  "geometry": {"coordinates":[-1.778634,53.834805],"type":"Point"}
}