{
  "type": "Feature",
  "properties": {
    "iso:country":"GB",
    "sg:address":"Unit 4 Canderside Indust Est",
    "sg:city":"Larkhall",
    "sg:classifiers":[
        {
            "category":"Professional",
            "subcategory":"Engineering",
            "type":"Services"
        }
    ],
    "sg:phone":"+44 1698 888861",
    "sg:postcode":"ML9 3PN",
    "sg:province":"South Lanarkshire",
    "sg:tags":[
        "design",
        "engineer"
    ],
    "wof:name":"Production Solutions",
    "wof:placetype":"venue"
},
  "geometry": {"coordinates":[-3.948,55.696522],"type":"Point"}
}