{
  "type": "Feature",
  "properties": {
    "addr:full":"10 Menshil Road Edinburgh City of Edinburgh EH9 1QS",
    "addr:housenumber":"10",
    "addr:postcode":"eh9 1qs",
    "addr:street":"Menshil Road",
    "iso:country":"GB",
    "sg:address":"10 Menshil Road",
    "sg:city":"Edinburgh",
    "sg:classifiers":[
        {
            "category":"Wholesale",
            "subcategory":"Books, Periodicals, & Newspapers",
            "type":"Manufacturing & Wholesale Goods"
        }
    ],
    "sg:postcode":"EH9 1QS",
    "sg:province":"City of Edinburgh",
    "sg:tags":[
        "publishing"
    ],
    "wof:name":"John Donald Publishers Ltd.",
    "wof:placetype":"venue"
},
  "geometry": {"coordinates":[-3.1793100834,55.9387283325],"type":"Point"}
}