{
  "type": "Feature",
  "properties": {
    "addr:full":"Peterson Rd Norwich Norfolk NR3 2QL",
    "addr:postcode":"nr3 2ql",
    "addr:street":"Peterson Rd",
    "iso:country":"GB",
    "sg:address":"Peterson Rd",
    "sg:city":"Norwich",
    "sg:classifiers":[
        {
            "category":"Community Center",
            "subcategory":"Youth",
            "type":"Public Place"
        },
        {
            "category":"Government",
            "subcategory":"Office",
            "type":"Public Place"
        }
    ],
    "sg:phone":"+44 1603 403814",
    "sg:postcode":"NR3 2QL",
    "sg:province":"Norfolk",
    "sg:tags":[
        "organisation",
        "local",
        "centre"
    ],
    "wof:name":"Norfolk County Council",
    "wof:placetype":"venue"
},
  "geometry": {"coordinates":[1.275645,52.650314],"type":"Point"}
}