{
  "type": "Feature",
  "properties": {
    "iso:country":"GB",
    "sg:address":"30 Lakeside Gardens",
    "sg:city":"Merthyr Tydfil",
    "sg:classifiers":[
        {
            "category":"Building & Trades",
            "subcategory":"Construction",
            "type":"Services"
        }
    ],
    "sg:phone":"+44 1685 384865",
    "sg:postcode":"CF48 1EN",
    "sg:province":"Caerphilly",
    "sg:tags":[
        "builder"
    ],
    "wof:name":"M.J Griffiths & Son",
    "wof:placetype":"venue"
},
  "geometry": {"coordinates":[-3.396431,51.760254],"type":"Point"}
}