{
  "type": "Feature",
  "properties": {
    "addr:full":"22 Drumlanrig Avenue Glasgow Glasgow City G34 0JD",
    "addr:housenumber":"22",
    "addr:postcode":"g34 0jd",
    "addr:street":"Drumlanrig Avenue",
    "iso:country":"GB",
    "sg:address":"22 Drumlanrig Avenue",
    "sg:city":"Glasgow",
    "sg:classifiers":[
        {
            "category":"Education",
            "subcategory":"School",
            "type":"Public Place"
        }
    ],
    "sg:phone":"+44 141 771 2911",
    "sg:postcode":"G34 0JD",
    "sg:province":"Glasgow City",
    "sg:tags":[
        "local",
        "authority"
    ],
    "wof:name":"St. Clare's (Easterhouse) R C Primary School",
    "wof:placetype":"venue"
},
  "geometry": {"coordinates":[-4.0989117622,55.8689041138],"type":"Point"}
}