{
  "type": "Feature",
  "properties": {
    "iso:country":"GB",
    "sg:address":"120 Bedford Road",
    "sg:city":"Ruislip",
    "sg:classifiers":[
        {
            "category":"Utilities",
            "subcategory":"Telephone",
            "type":"Services"
        }
    ],
    "sg:postcode":"HA4 6LZ",
    "sg:province":"Greater London",
    "sg:tags":[
        "telecommunication"
    ],
    "wof:name":"Videoquest Ltd.",
    "wof:placetype":"venue"
},
  "geometry": {"coordinates":[-0.41952,51.559856],"type":"Point"}
}