{
  "type": "Feature",
  "properties": {
    "iso:country":"GB",
    "sg:address":"Cyttir Lane, Caernarfon Road",
    "sg:city":"Bangor",
    "sg:classifiers":[
        {
            "category":"Wholesale",
            "subcategory":"Meat",
            "type":"Manufacturing & Wholesale Goods"
        }
    ],
    "sg:phone":"+44 1248 352370",
    "sg:postcode":"LL57 4DA",
    "sg:province":"Gwynedd",
    "sg:tags":[
        "-"
    ],
    "wof:name":"Hughes Meats Co. Ltd.",
    "wof:placetype":"venue"
},
  "geometry": {"coordinates":[-4.162602,53.201881],"type":"Point"}
}