{
  "type": "Feature",
  "properties": {
    "iso:country":"GB",
    "sg:address":"9 Aintree Close",
    "sg:city":"Doncaster",
    "sg:classifiers":[
        {
            "category":"Health Services",
            "subcategory":"Podiatrist",
            "type":"Services"
        }
    ],
    "sg:postcode":"DN5 8UA",
    "sg:province":"South Yorkshire",
    "sg:tags":[
        "podiatrists",
        "chiropodist"
    ],
    "wof:name":"J Peat",
    "wof:placetype":"venue"
},
  "geometry": {"coordinates":[-1.1750990152,53.5337905884],"type":"Point"}
}