{
  "type": "Feature",
  "properties": {
    "iso:country":"GB",
    "sg:address":"9 Church Street, Scalford",
    "sg:city":"Melton Mowbray",
    "sg:classifiers":[
        {
            "category":"Government",
            "subcategory":"Post Office",
            "type":"Public Place"
        }
    ],
    "sg:phone":"+44 1664 444201",
    "sg:postcode":"LE14 4DL",
    "sg:province":"Leicestershire",
    "wof:name":"Scalford Sub Post Office",
    "wof:placetype":"venue"
},
  "geometry": {"coordinates":[-0.869449,52.810143],"type":"Point"}
}