{
  "type": "Feature",
  "properties": {
    "iso:country":"GB",
    "sg:address":"148-150 Curtain Road",
    "sg:city":"London",
    "sg:classifiers":[
        {
            "category":"Professional",
            "subcategory":"Printing & Photocopies",
            "type":"Services"
        }
    ],
    "sg:phone":"+44 20 7729 8333",
    "sg:postcode":"EC2A 3AT",
    "sg:province":"Greater London",
    "sg:tags":[
        "printer"
    ],
    "wof:name":"Angel Press",
    "wof:placetype":"venue"
},
  "geometry": {"coordinates":[-0.080196999,51.5267868042],"type":"Point"}
}