{
  "type": "Feature",
  "properties": {
    "iso:country":"GB",
    "sg:address":"34 High Street, Stilton",
    "sg:city":"Peterborough",
    "sg:classifiers":[
        {
            "category":"Sports & Exercise",
            "subcategory":"Golf",
            "type":"Entertainment"
        }
    ],
    "sg:phone":"+44 1733 245233",
    "sg:postcode":"PE7 3RA",
    "sg:province":"Cambridgeshire",
    "sg:tags":[
        "club",
        "course"
    ],
    "wof:name":"Stilton Oaks Golf Course",
    "wof:placetype":"venue"
},
  "geometry": {"coordinates":[-0.2883000076,52.4875030518],"type":"Point"}
}