{
  "type": "Feature",
  "properties": {
    "iso:country":"GB",
    "sg:address":"Unit 1, Heer House",
    "sg:city":"Coventry",
    "sg:classifiers":[
        {
            "category":"Wholesale",
            "subcategory":"Electrical",
            "type":"Manufacturing & Wholesale Goods"
        }
    ],
    "sg:phone":"+44 24 7666 5252",
    "sg:postcode":"CV1 4JT",
    "sg:province":"West Midlands",
    "sg:tags":[
        "equipment",
        "refrigeration"
    ],
    "wof:name":"Huntley Refrigeration & Air-Conditioning",
    "wof:placetype":"venue"
},
  "geometry": {"coordinates":[-1.507768,52.406986],"type":"Point"}
}