{
  "type": "Feature",
  "properties": {
    "iso:country":"GB",
    "sg:address":"141 Grainger Street",
    "sg:city":"Newcastle-upon-tyne",
    "sg:classifiers":[
        {
            "category":"Travel",
            "subcategory":"Travel Agent",
            "type":"Entertainment"
        }
    ],
    "sg:phone":"+44 191 261 0907",
    "sg:postcode":"NE1 5AE",
    "sg:province":"Tyne and Wear",
    "wof:name":"Going Places Leisure Travel",
    "wof:placetype":"venue"
},
  "geometry": {"coordinates":[-1.6149,54.971916],"type":"Point"}
}