{
  "type": "Feature",
  "properties": {
    "addr:full":"173e Wattville Road Birmingham West Midlands B21 0DN",
    "addr:housenumber":"173e",
    "addr:postcode":"b21 0dn",
    "addr:street":"Wattville Road",
    "iso:country":"GB",
    "sg:address":"173e Wattville Road",
    "sg:city":"Birmingham",
    "sg:classifiers":[
        {
            "category":"Cafe",
            "type":"Food & Drink"
        }
    ],
    "sg:phone":"+44 121 554 9711",
    "sg:postcode":"B21 0DN",
    "sg:province":"West Midlands",
    "sg:tags":[
        "tea",
        "snack",
        "bar",
        "room"
    ],
    "wof:name":"Wattville Cafe",
    "wof:placetype":"venue"
},
  "geometry": {"coordinates":[-1.9568339586,52.503578186],"type":"Point"}
}