{
  "type": "Feature",
  "properties": {
    "addr:full":"9 Lockwood Road Doncaster South Yorkshire DN1 2TU",
    "addr:housenumber":"9",
    "addr:postcode":"dn1 2tu",
    "addr:street":"Lockwood Road",
    "iso:country":"GB",
    "sg:address":"9 Lockwood Road",
    "sg:city":"Doncaster",
    "sg:classifiers":[
        {
            "category":"Professional",
            "subcategory":"Business Services",
            "type":"Services"
        },
        {
            "category":"Government",
            "subcategory":"Post Office",
            "type":"Public Place"
        }
    ],
    "sg:phone":"+44 1302 364304",
    "sg:postcode":"DN1 2TU",
    "sg:province":"South Yorkshire",
    "sg:tags":[
        "messenger",
        "courier"
    ],
    "wof:name":"Swift Deliveries Ltd.",
    "wof:placetype":"venue"
},
  "geometry": {"coordinates":[-1.1230789423,53.5310668945],"type":"Point"}
}