{
  "type": "Feature",
  "properties": {
    "iso:country":"GB",
    "sg:address":"171 Park Rd",
    "sg:city":"Hendon",
    "sg:classifiers":[
        {
            "category":"Health Services",
            "subcategory":"Nursing And Care Facility",
            "type":"Services"
        }
    ],
    "sg:phone":"+44 20 8202 6177",
    "sg:postcode":"NW4 3TH",
    "sg:province":"Greater London",
    "sg:tags":[
        "home"
    ],
    "wof:name":"Elmstead House",
    "wof:placetype":"venue"
},
  "geometry": {"coordinates":[-0.2253209949,51.5794296265],"type":"Point"}
}