{
  "type": "Feature",
  "properties": {
    "addr:full":"22a Poplar Gro New Malden Surrey KT3 3BY",
    "addr:housenumber":"22a",
    "addr:postcode":"kt3 3by",
    "addr:street":"Poplar Gro",
    "iso:country":"GB",
    "sg:address":"22a Poplar Gro",
    "sg:city":"New Malden",
    "sg:classifiers":[
        {
            "category":"Building & Trades",
            "subcategory":"Construction",
            "type":"Services"
        }
    ],
    "sg:postcode":"KT3 3BY",
    "sg:province":"Surrey",
    "sg:tags":[
        "builder"
    ],
    "wof:name":"Green,D W,",
    "wof:placetype":"venue"
},
  "geometry": {"coordinates":[-0.262964,51.404194],"type":"Point"}
}