{
  "type": "Feature",
  "properties": {
    "addr:full":"21 Victoria Rd Romford Essex RM1 2JT",
    "addr:housenumber":"21",
    "addr:postcode":"rm1 2jt",
    "addr:street":"Victoria Rd",
    "iso:country":"GB",
    "sg:address":"21 Victoria Rd",
    "sg:city":"Romford",
    "sg:classifiers":[
        {
            "category":"Wholesale",
            "subcategory":"Vending Machines",
            "type":"Manufacturing & Wholesale Goods"
        }
    ],
    "sg:phone":"+44 1708 722022",
    "sg:postcode":"RM1 2JT",
    "sg:province":"Essex",
    "sg:tags":[
        "business"
    ],
    "wof:name":"Rigby Typewriters Business Solution",
    "wof:placetype":"venue"
},
  "geometry": {"coordinates":[0.1849330068,51.5745849609],"type":"Point"}
}