{
  "type": "Feature",
  "properties": {
    "iso:country":"GB",
    "sg:address":"Unit 12a",
    "sg:city":"Witney",
    "sg:classifiers":[
        {
            "category":"Building & Trades",
            "subcategory":"Construction",
            "type":"Services"
        }
    ],
    "sg:phone":"+44 1993 703954",
    "sg:postcode":"OX29 9TJ",
    "sg:province":"Oxfordshire",
    "sg:tags":[
        "joinery"
    ],
    "wof:name":"Jacob-Brown Woodworking",
    "wof:placetype":"venue"
},
  "geometry": {"coordinates":[-1.525759,51.82],"type":"Point"}
}