{
  "type": "Feature",
  "properties": {
    "iso:country":"GB",
    "sg:address":"6 Woodhouse Square",
    "sg:city":"Leeds",
    "sg:classifiers":[
        {
            "category":"Education",
            "subcategory":"School",
            "type":"Public Place"
        },
        {
            "category":"Education",
            "subcategory":"University",
            "type":"Public Place"
        }
    ],
    "sg:phone":"+44 113 245 3304",
    "sg:postcode":"LS3 1AD",
    "sg:province":"West Yorkshire",
    "sg:tags":[
        "adult",
        "location"
    ],
    "sg:website":"http://www.wea-yn.org.uk",
    "wof:name":"Workers Educational Association",
    "wof:placetype":"venue"
},
  "geometry": {"coordinates":[-1.556511,53.801384],"type":"Point"}
}