{
  "type": "Feature",
  "properties": {
    "addr:full":"28 Ludlow Street, Hanley Stoke-on-trent Staffordshire ST1 3QJ",
    "addr:housenumber":"28",
    "addr:postcode":"staffordshire st1 3qj",
    "addr:street":"Ludlow Street",
    "iso:country":"GB",
    "sg:address":"28 Ludlow Street, Hanley",
    "sg:city":"Stoke-on-trent",
    "sg:classifiers":[
        {
            "category":"Building & Trades",
            "subcategory":"Construction",
            "type":"Services"
        }
    ],
    "sg:phone":"+44 1782 269104",
    "sg:postcode":"ST1 3QJ",
    "sg:province":"Staffordshire",
    "sg:tags":[
        "decorator",
        "painter"
    ],
    "wof:name":"Thomas Rowley",
    "wof:placetype":"venue"
},
  "geometry": {"coordinates":[-2.1660869122,53.0247077942],"type":"Point"}
}