{
  "type": "Feature",
  "properties": {
    "iso:country":"GB",
    "sg:address":"3 Catherine Street",
    "sg:city":"Salisbury",
    "sg:classifiers":[
        {
            "category":"Shopping",
            "subcategory":"Thrift Store",
            "type":"Retail Goods"
        }
    ],
    "sg:phone":"+44 1722 421088",
    "sg:postcode":"SP1 2DF",
    "sg:province":"Wiltshire",
    "sg:tags":[
        "shop",
        "charity"
    ],
    "wof:name":"Marie Curie Cancer Care",
    "wof:placetype":"venue"
},
  "geometry": {"coordinates":[-1.7941529751,51.0685653687],"type":"Point"}
}