{
  "type": "Feature",
  "properties": {
    "iso:country":"GB",
    "sg:address":"8-10 Westgate, Honley",
    "sg:city":"Huddersfield",
    "sg:classifiers":[
        {
            "category":"Shopping",
            "subcategory":"Pharmacy",
            "type":"Retail Goods"
        }
    ],
    "sg:phone":"+44 1484 661818",
    "sg:postcode":"HD9 6AA",
    "sg:province":"South Yorkshire",
    "sg:tags":[
        "pharmacist",
        "dispensing",
        "chemist"
    ],
    "wof:name":"Medicare Chemists Ltd.",
    "wof:placetype":"venue"
},
  "geometry": {"coordinates":[-1.792492,53.603878],"type":"Point"}
}