{
  "type": "Feature",
  "properties": {
    "iso:country":"GB",
    "sg:address":"3 Whitworth Road",
    "sg:city":"Sheffield",
    "sg:classifiers":[
        {
            "category":"Health Services",
            "subcategory":"Doctor",
            "type":"Services"
        },
        {
            "category":"Building & Trades",
            "subcategory":"Construction",
            "type":"Services"
        },
        {
            "category":"Manufacturing",
            "subcategory":"Building Materials",
            "type":"Manufacturing & Wholesale Goods"
        }
    ],
    "sg:postcode":"S10 3HD",
    "sg:province":"South Yorkshire",
    "sg:tags":[
        "merchant",
        "roofing",
        "builder",
        "practitioners"
    ],
    "wof:name":"Thomas W D Smith",
    "wof:placetype":"venue"
},
  "geometry": {"coordinates":[-1.525825,53.374577],"type":"Point"}
}