{
  "type": "Feature",
  "properties": {
    "addr:full":"Strathblane House, Ashfield Road Cheadle Cheshire SK8 1BB",
    "addr:postcode":"sk8 1bb",
    "addr:street":"Ashfield Road Cheadle",
    "iso:country":"GB",
    "sg:address":"Strathblane House, Ashfield Road",
    "sg:city":"Cheadle",
    "sg:classifiers":[
        {
            "category":"Professional",
            "subcategory":"Employment Agencies",
            "type":"Services"
        }
    ],
    "sg:phone":"+44 161 282 2220",
    "sg:postcode":"SK8 1BB",
    "sg:province":"Cheshire",
    "sg:tags":[
        "career",
        "guidance"
    ],
    "wof:name":"Lifetime Careers Stockport & High Peak Ltd.",
    "wof:placetype":"venue"
},
  "geometry": {"coordinates":[-2.2135090828,53.3945503235],"type":"Point"}
}