{
  "type": "Feature",
  "properties": {
    "iso:country":"GB",
    "sg:address":"17 Livingstone Terr, Redding",
    "sg:city":"Falkirk",
    "sg:classifiers":[
        {
            "category":"Building & Trades",
            "subcategory":"Construction",
            "type":"Services"
        }
    ],
    "sg:phone":"+44 1324 711100",
    "sg:postcode":"FK2 9TU",
    "sg:province":"Falkirk",
    "sg:tags":[
        "builder"
    ],
    "wof:name":"Triangle Building Consultants Ltd",
    "wof:placetype":"venue"
},
  "geometry": {"coordinates":[-3.738741,55.985241],"type":"Point"}
}