{
  "type": "Feature",
  "properties": {
    "iso:country":"GB",
    "sg:address":"Scarletts Well, Scarletts Well Road",
    "sg:city":"Bodmin",
    "sg:classifiers":[
        {
            "category":"Professional",
            "subcategory":"Engineering",
            "type":"Services"
        }
    ],
    "sg:postcode":"PL31 2PL",
    "sg:province":"Cornwall",
    "sg:tags":[
        "design",
        "engineer"
    ],
    "wof:name":"E K S Design",
    "wof:placetype":"venue"
},
  "geometry": {"coordinates":[-4.732859,50.474915],"type":"Point"}
}