{
  "type": "Feature",
  "properties": {
    "addr:full":"Ellis Of Dumbreck, Udny Ellon Aberdeenshire AB41 0PG",
    "addr:postcode":"ab41 0pg",
    "addr:street":"Ellon",
    "iso:country":"GB",
    "sg:address":"Ellis Of Dumbreck, Udny",
    "sg:city":"Ellon",
    "sg:classifiers":[
        {
            "category":"Farming",
            "subcategory":"Farm",
            "type":"Manufacturing & Wholesale Goods"
        }
    ],
    "sg:phone":"+44 1651 842341",
    "sg:postcode":"AB41 0PG",
    "sg:province":"Aberdeenshire",
    "sg:tags":[
        "mixed",
        "crop"
    ],
    "wof:name":"I J Keith",
    "wof:placetype":"venue"
},
  "geometry": {"coordinates":[-2.0728139877,57.3641357422],"type":"Point"}
}