{
  "type": "Feature",
  "properties": {
    "iso:country":"GB",
    "sg:address":"Highgate Farm, Swim Road",
    "sg:city":"Great Yarmouth",
    "sg:classifiers":[
        {
            "category":"Home & Garden",
            "subcategory":"Building Materials",
            "type":"Retail Goods"
        }
    ],
    "sg:postcode":"NR29 3EH",
    "sg:province":"Norfolk",
    "sg:tags":[
        "fencing"
    ],
    "wof:name":"M & L Smith",
    "wof:placetype":"venue"
},
  "geometry": {"coordinates":[1.65499,52.6343],"type":"Point"}
}