{
  "type": "Feature",
  "properties": {
    "iso:country":"GB",
    "sg:address":"23 Wragby Road",
    "sg:city":"Lincoln",
    "sg:classifiers":[
        {
            "category":"Bars & Pubs",
            "type":"Food & Drink"
        }
    ],
    "sg:phone":"+44 1522 524703",
    "sg:postcode":"LN2 5SH",
    "sg:province":"Lincolnshire",
    "sg:tags":[
        "pubs",
        "inn"
    ],
    "wof:name":"The Peacock Inn",
    "wof:placetype":"venue"
},
  "geometry": {"coordinates":[-0.5296120048,53.2351646423],"type":"Point"}
}