{
  "type": "Feature",
  "properties": {
    "addr:full":"95 Stanmer Villas Brighton East Sussex BN1 7HN",
    "addr:housenumber":"95",
    "addr:postcode":"bn1 7hn",
    "addr:street":"Stanmer Villas",
    "iso:country":"GB",
    "sg:address":"95 Stanmer Villas",
    "sg:city":"Brighton",
    "sg:classifiers":[
        {
            "category":"Building & Trades",
            "subcategory":"Construction",
            "type":"Services"
        }
    ],
    "sg:phone":"+44 1273 561674",
    "sg:postcode":"BN1 7HN",
    "sg:province":"East Sussex",
    "sg:tags":[
        "joiner",
        "carpenter"
    ],
    "wof:name":"J L Stephenson Carpenters",
    "wof:placetype":"venue"
},
  "geometry": {"coordinates":[-0.132969,50.846966],"type":"Point"}
}