{
  "type": "Feature",
  "properties": {
    "addr:full":"Forge Farm, Upton Magna Shrewsbury Shropshire SY4 4UD",
    "addr:postcode":"sy4 4ud",
    "iso:country":"GB",
    "sg:address":"Forge Farm, Upton Magna",
    "sg:city":"Shrewsbury",
    "sg:classifiers":[
        {
            "category":"Farming",
            "subcategory":"Dairy Farm",
            "type":"Manufacturing & Wholesale Goods"
        }
    ],
    "sg:phone":"+44 1743 709212",
    "sg:postcode":"SY4 4UD",
    "sg:province":"Shropshire",
    "wof:name":"James Home & Partners",
    "wof:placetype":"venue"
},
  "geometry": {"coordinates":[-2.661499,52.708794],"type":"Point"}
}