{
  "type": "Feature",
  "properties": {
    "addr:full":"The Esplanade Woolacombe Devon EX34 7DJ",
    "addr:postcode":"ex34 7dj",
    "addr:street":"The Esplanade Woolacombe",
    "iso:country":"GB",
    "sg:address":"The Esplanade",
    "sg:city":"Woolacombe",
    "sg:classifiers":[
        {
            "category":"Travel",
            "subcategory":"Hotels & Motels",
            "type":"Entertainment"
        }
    ],
    "sg:phone":"+44 1271 870444",
    "sg:postcode":"EX34 7DJ",
    "sg:province":"Devon",
    "sg:tags":[
        "house",
        "self",
        "guest",
        "catering"
    ],
    "wof:name":"Barricane Holiday Homes",
    "wof:placetype":"venue"
},
  "geometry": {"coordinates":[-4.206484,51.172867],"type":"Point"}
}