{
  "type": "Feature",
  "properties": {
    "addr:full":"90 George Street Edinburgh City of Edinburgh EH2 3DF",
    "addr:housenumber":"90",
    "addr:postcode":"eh2 3df",
    "addr:street":"George Street",
    "iso:country":"GB",
    "sg:address":"90 George Street",
    "sg:city":"Edinburgh",
    "sg:classifiers":[
        {
            "category":"Shopping",
            "subcategory":"Clothing, Apparel, & Fashions",
            "type":"Retail Goods"
        }
    ],
    "sg:phone":"+44 131 225 1121",
    "sg:postcode":"EH2 3DF",
    "sg:province":"City of Edinburgh",
    "sg:tags":[
        "shop"
    ],
    "wof:name":"Laura",
    "wof:placetype":"venue"
},
  "geometry": {"coordinates":[-3.2016699314,55.9525718689],"type":"Point"}
}