{
  "type": "Feature",
  "properties": {
    "iso:country":"GB",
    "sg:address":"Blackwell Lane, Melbourne",
    "sg:city":"Derby",
    "sg:classifiers":[
        {
            "category":"Transit Center",
            "subcategory":"Passenger",
            "type":"Transportation"
        }
    ],
    "sg:phone":"+44 1332 862770",
    "sg:postcode":"DE73 1EL",
    "sg:province":"Derbyshire",
    "sg:tags":[
        "boarding",
        "kennel",
        "catteries"
    ],
    "wof:name":"Coppice Boarding Kennels & Cattery",
    "wof:placetype":"venue"
},
  "geometry": {"coordinates":[-1.423514,52.821747],"type":"Point"}
}