{
  "type": "Feature",
  "properties": {
    "addr:full":"Jessops Mill, Station Road Batley West Yorkshire WF17 5SW",
    "addr:postcode":"wf17 5sw",
    "addr:street":"Station Road",
    "iso:country":"GB",
    "sg:address":"Jessops Mill, Station Road",
    "sg:city":"Batley",
    "sg:classifiers":[
        {
            "category":"Professional",
            "type":"Services"
        }
    ],
    "sg:postcode":"WF17 5SW",
    "sg:province":"West Yorkshire",
    "sg:tags":[
        "auctioneer"
    ],
    "wof:name":"Batley Auctions",
    "wof:placetype":"venue"
},
  "geometry": {"coordinates":[-1.654499054,53.7264213562],"type":"Point"}
}