{
  "type": "Feature",
  "properties": {
    "iso:country":"GB",
    "sg:address":"Sycamore Road",
    "sg:city":"Burntwood",
    "sg:classifiers":[
        {
            "category":"Social Services",
            "type":"Services"
        },
        {
            "category":"Government",
            "subcategory":"Office",
            "type":"Public Place"
        }
    ],
    "sg:phone":"+44 1543 510410",
    "sg:postcode":"WS7 4RR",
    "sg:province":"Staffordshire",
    "sg:tags":[
        "local"
    ],
    "wof:name":"Burntwood Social Services",
    "wof:placetype":"venue"
},
  "geometry": {"coordinates":[-1.930489,52.679813],"type":"Point"}
}