{
  "type": "Feature",
  "properties": {
    "iso:country":"GB",
    "sg:address":"29 Cambria Grn, South Hylton",
    "sg:city":"Sunderland",
    "sg:classifiers":[
        {
            "category":"Building & Trades",
            "subcategory":"Construction",
            "type":"Services"
        }
    ],
    "sg:phone":"+44 191 534 2754",
    "sg:postcode":"SR4 0NN",
    "sg:province":"Tyne and Wear",
    "sg:tags":[
        "roofing"
    ],
    "wof:name":"R A Greener",
    "wof:placetype":"venue"
},
  "geometry": {"coordinates":[-1.453244,54.90321],"type":"Point"}
}