{
  "type": "Feature",
  "properties": {
    "addr:full":"146 Warwick Road Carlisle Cumbria CA1 1LG",
    "addr:housenumber":"146",
    "addr:postcode":"ca1 1lg",
    "addr:street":"Warwick Road",
    "iso:country":"GB",
    "sg:address":"146 Warwick Road",
    "sg:city":"Carlisle",
    "sg:classifiers":[
        {
            "category":"Travel",
            "subcategory":"Hotels & Motels",
            "type":"Entertainment"
        }
    ],
    "sg:postcode":"CA1 1LG",
    "sg:province":"Cumbria",
    "sg:tags":[
        "house",
        "guest"
    ],
    "wof:name":"ACER HOUSE",
    "wof:placetype":"venue"
},
  "geometry": {"coordinates":[-2.920545,54.894283],"type":"Point"}
}