{
  "type": "Feature",
  "properties": {
    "iso:country":"GB",
    "sg:address":"15 Sumner Road Workshops, 80 Sumner Rd",
    "sg:city":"Peckham",
    "sg:classifiers":[
        {
            "category":"Professional",
            "subcategory":"Printing & Photocopies",
            "type":"Services"
        }
    ],
    "sg:phone":"+44 20 7701 1890",
    "sg:postcode":"SE15 6LA",
    "sg:province":"Greater London",
    "sg:tags":[
        "printer"
    ],
    "wof:name":"Elliott Printers",
    "wof:placetype":"venue"
},
  "geometry": {"coordinates":[-0.0677940026,51.4721794128],"type":"Point"}
}