{
  "type": "Feature",
  "properties": {
    "iso:country":"GB",
    "sg:address":"48 Kingsmead",
    "sg:city":"Farnborough",
    "sg:classifiers":[
        {
            "category":"Shopping",
            "subcategory":"Shoes",
            "type":"Retail Goods"
        }
    ],
    "sg:phone":"+44 1252 373831",
    "sg:postcode":"GU14 7SL",
    "sg:province":"Hampshire",
    "sg:tags":[
        "shop"
    ],
    "wof:name":"Stead & Simpson Ltd.",
    "wof:placetype":"venue"
},
  "geometry": {"coordinates":[-0.7538130283,51.2910652161],"type":"Point"}
}