{
  "type": "Feature",
  "properties": {
    "addr:full":"317 Carlton Hill Nottingham Nottinghamshire NG4 1GL",
    "addr:housenumber":"317",
    "addr:postcode":"ng4 1gl",
    "addr:street":"Carlton Hill",
    "iso:country":"GB",
    "sg:address":"317 Carlton Hill",
    "sg:city":"Nottingham",
    "sg:classifiers":[
        {
            "category":"Real Estate",
            "subcategory":"Real Estate Agent",
            "type":"Services"
        }
    ],
    "sg:phone":"+44 115 987 8957",
    "sg:postcode":"NG4 1GL",
    "sg:province":"Nottinghamshire",
    "wof:name":"Independent Mortgage Shop",
    "wof:placetype":"venue"
},
  "geometry": {"coordinates":[-1.109279,52.965851],"type":"Point"}
}