{
  "type": "Feature",
  "properties": {
    "addr:full":"Unit B3, Hilton Main Business Park, Bognop Rd Wolverhampton Staffordshire WV11 2BE",
    "addr:postcode":"wv11 2be",
    "addr:street":"Business Park Bognop Rd",
    "iso:country":"GB",
    "sg:address":"Unit B3, Hilton Main Business Park, Bognop Rd",
    "sg:city":"Wolverhampton",
    "sg:classifiers":[
        {
            "category":"Professional",
            "subcategory":"Engineering",
            "type":"Services"
        }
    ],
    "sg:phone":"+44 1902 306757",
    "sg:postcode":"WV11 2BE",
    "sg:province":"Staffordshire",
    "sg:tags":[
        "contractor",
        "electrical",
        "engineer"
    ],
    "wof:name":"Kaltec Ltd",
    "wof:placetype":"venue"
},
  "geometry": {"coordinates":[-2.121669,52.58865],"type":"Point"}
}