{
  "type": "Feature",
  "properties": {
    "iso:country":"GB",
    "sg:address":"112 Main Street",
    "sg:city":"Alexandria",
    "sg:classifiers":[
        {
            "category":"Professional",
            "subcategory":"Lawyer & Legal Services",
            "type":"Services"
        }
    ],
    "sg:phone":"+44 1389 756979",
    "sg:postcode":"G83 0NZ",
    "sg:province":"Argyll and Bute",
    "sg:tags":[
        "solicitor"
    ],
    "wof:name":"Cairns Brown",
    "wof:placetype":"venue"
},
  "geometry": {"coordinates":[-4.5822272301,55.9873313904],"type":"Point"}
}