{
  "type": "Feature",
  "properties": {
    "iso:country":"GB",
    "sg:address":"Lower Henwick Farm, Turnpike Road",
    "sg:city":"Thatcham",
    "sg:classifiers":[
        {
            "category":"Restaurant",
            "type":"Food & Drink"
        },
        {
            "category":"Organizations",
            "subcategory":"Membership Organization",
            "type":"Services"
        }
    ],
    "sg:phone":"+44 1635 869760",
    "sg:postcode":"RG18 3AP",
    "sg:province":"Berkshire",
    "sg:tags":[
        "club",
        "-",
        "english"
    ],
    "wof:name":"The Taste of England",
    "wof:placetype":"venue"
},
  "geometry": {"coordinates":[-1.263599,51.403831],"type":"Point"}
}