{
  "type": "Feature",
  "properties": {
    "addr:full":"173 Silverdale Road Tunbridge Wells Kent TN4 9HT",
    "addr:housenumber":"173",
    "addr:postcode":"tn4 9ht",
    "addr:street":"Silverdale Road",
    "iso:country":"GB",
    "sg:address":"173 Silverdale Road",
    "sg:city":"Tunbridge Wells",
    "sg:classifiers":[
        {
            "category":"Retail",
            "subcategory":"Laundry & Dry Cleaning",
            "type":"Services"
        }
    ],
    "sg:postcode":"TN4 9HT",
    "sg:province":"Kent",
    "sg:tags":[
        "alteration"
    ],
    "wof:name":"Silverdale Dry Cleaners",
    "wof:placetype":"venue"
},
  "geometry": {"coordinates":[0.2739619911,51.1470031738],"type":"Point"}
}