{
  "type": "Feature",
  "properties": {
    "addr:full":"Unit 5a 193 The Garth Road Indu, Strial Centre Morden Surrey SM4 4LZ",
    "addr:housenumber":"unit 5a 193",
    "addr:postcode":"sm4 4lz",
    "addr:street":"The Garth Road Indu Strial;Morden",
    "iso:country":"GB",
    "sg:address":"Unit 5a 193 The Garth Road Indu, Strial Centre",
    "sg:city":"Morden",
    "sg:classifiers":[
        {
            "category":"Professional",
            "subcategory":"Art Services",
            "type":"Services"
        }
    ],
    "sg:postcode":"SM4 4LZ",
    "sg:province":"Surrey",
    "sg:tags":[
        "photographer"
    ],
    "wof:name":"Richard Hadley Photography",
    "wof:placetype":"venue"
},
  "geometry": {"coordinates":[-0.2260639966,51.3853034973],"type":"Point"}
}