{
  "type": "Feature",
  "properties": {
    "addr:full":"167 Rolfe Street Smethwick West Midlands B66 2AU",
    "addr:housenumber":"167",
    "addr:postcode":"b66 2au",
    "addr:street":"Rolfe Street",
    "iso:country":"GB",
    "sg:address":"167 Rolfe Street",
    "sg:city":"Smethwick",
    "sg:classifiers":[
        {
            "category":"Manufacturing",
            "subcategory":"Rubber & Plastics",
            "type":"Manufacturing & Wholesale Goods"
        }
    ],
    "sg:phone":"+44 121 555 8554",
    "sg:postcode":"B66 2AU",
    "sg:province":"West Midlands",
    "sg:tags":[
        "mould"
    ],
    "wof:name":"D C R Tools",
    "wof:placetype":"venue"
},
  "geometry": {"coordinates":[-1.960753,52.497349],"type":"Point"}
}