{
  "type": "Feature",
  "properties": {
    "iso:country":"GB",
    "sg:address":"10 The Dene, Abinger Hammer",
    "sg:city":"Dorking",
    "sg:classifiers":[
        {
            "category":"Building & Trades",
            "subcategory":"Construction",
            "type":"Services"
        }
    ],
    "sg:postcode":"RH5 6PX",
    "sg:province":"Surrey",
    "sg:tags":[
        "contractor",
        "pool",
        "swimming"
    ],
    "wof:name":"Burgess Electrical & Building Contractors",
    "wof:placetype":"venue"
},
  "geometry": {"coordinates":[-0.432434,51.215931],"type":"Point"}
}