{
  "type": "Feature",
  "properties": {
    "addr:full":"34 Bowater Road London Greater London SE18 5TF",
    "addr:housenumber":"34",
    "addr:postcode":"se18 5tf",
    "addr:street":"Bowater Road",
    "iso:country":"GB",
    "sg:address":"34 Bowater Road",
    "sg:city":"London",
    "sg:classifiers":[
        {
            "category":"Professional",
            "type":"Services"
        },
        {
            "category":"Organizations",
            "subcategory":"Community Association",
            "type":"Services"
        }
    ],
    "sg:phone":"+44 20 8854 5151",
    "sg:postcode":"SE18 5TF",
    "sg:province":"Greater London",
    "sg:tags":[
        "hire",
        "display",
        "maker",
        "furniture"
    ],
    "wof:name":"Display Makers",
    "wof:placetype":"venue"
},
  "geometry": {"coordinates":[0.040589,51.494423],"type":"Point"}
}