{
  "type": "Feature",
  "properties": {
    "iso:country":"GB",
    "sg:address":"Suite 5a 99 Holdenhurst Rd",
    "sg:city":"Bournemouth",
    "sg:classifiers":[
        {
            "category":"Communications",
            "subcategory":"News Services",
            "type":"Services"
        }
    ],
    "sg:phone":"+44 1202 316233",
    "sg:postcode":"BH8 8DY",
    "sg:province":"Dorset",
    "sg:tags":[
        "illustrator"
    ],
    "wof:name":"ti illustration",
    "wof:placetype":"venue"
},
  "geometry": {"coordinates":[-1.863738,50.724781],"type":"Point"}
}