{
  "type": "Feature",
  "properties": {
    "addr:full":"Motion Control Studio, 8 Silver Rd Shepherd's Bush Greater London W12 7SG",
    "addr:housenumber":"8",
    "addr:postcode":"w12 7sg",
    "addr:street":"Silver Rd",
    "iso:country":"GB",
    "sg:address":"Motion Control Studio, 8 Silver Rd",
    "sg:city":"Shepherd's Bush",
    "sg:classifiers":[
        {
            "category":"Communications",
            "subcategory":"Film & Video Production",
            "type":"Services"
        }
    ],
    "sg:phone":"+44 20 8749 1600",
    "sg:postcode":"W12 7SG",
    "sg:province":"Greater London",
    "sg:tags":[
        "tv",
        "studio"
    ],
    "wof:name":"SVC White City",
    "wof:placetype":"venue"
},
  "geometry": {"coordinates":[-0.2208389938,51.5104942322],"type":"Point"}
}