{
  "type": "Feature",
  "properties": {
    "addr:full":"Doncaster Road, Hatfield Doncaster South Yorkshire DN7 6AD",
    "addr:postcode":"dn7 6ad",
    "addr:street":"Doncaster Road",
    "iso:country":"GB",
    "sg:address":"Doncaster Road, Hatfield",
    "sg:city":"Doncaster",
    "sg:classifiers":[
        {
            "category":"Bars & Pubs",
            "type":"Food & Drink"
        },
        {
            "category":"Community Center",
            "subcategory":"Social",
            "type":"Public Place"
        }
    ],
    "sg:phone":"+44 1302 840508",
    "sg:postcode":"DN7 6AD",
    "sg:province":"South Yorkshire",
    "sg:tags":[
        "pubs",
        "house",
        "inn",
        "activity"
    ],
    "wof:name":"Hatfield Chace",
    "wof:placetype":"venue"
},
  "geometry": {"coordinates":[-1.0064439774,53.5744018555],"type":"Point"}
}