{
  "type": "Feature",
  "properties": {
    "addr:full":"Courtlands Road Eastbourne East Sussex BN22 8TR",
    "addr:postcode":"bn22 8tr",
    "addr:street":"Courtlands Road",
    "iso:country":"GB",
    "sg:address":"Courtlands Road",
    "sg:city":"Eastbourne",
    "sg:classifiers":[
        {
            "category":"Retail",
            "subcategory":"Auto Repair",
            "type":"Services"
        }
    ],
    "sg:phone":"+44 1323 417111",
    "sg:postcode":"BN22 8TR",
    "sg:province":"East Sussex",
    "sg:tags":[
        "modification",
        "garage"
    ],
    "wof:name":"Ebley Tyre & Auto Centres",
    "wof:placetype":"venue"
},
  "geometry": {"coordinates":[0.2882499993,50.7790336609],"type":"Point"}
}