{
  "type": "Feature",
  "properties": {
    "iso:country":"GB",
    "sg:address":"Testa Teres House, Copse Road",
    "sg:city":"Fleetwood",
    "sg:classifiers":[
        {
            "category":"Building & Trades",
            "subcategory":"Construction",
            "type":"Services"
        }
    ],
    "sg:phone":"+44 1253 772504",
    "sg:postcode":"FY7 7NY",
    "sg:province":"Lancashire",
    "sg:tags":[
        "dry",
        "lining",
        "plasterers",
        "screeders"
    ],
    "wof:name":"Testa Teres Ltd.",
    "wof:placetype":"venue"
},
  "geometry": {"coordinates":[-3.027597,53.908901],"type":"Point"}
}