{
  "type": "Feature",
  "properties": {
    "addr:full":"Ground Floor Shop, 275 Hornsey Road London Greater London N7 6RZ",
    "addr:housenumber":"275",
    "addr:postcode":"n7 6rz",
    "addr:street":"Hornsey Road",
    "iso:country":"GB",
    "sg:address":"Ground Floor Shop, 275 Hornsey Road",
    "sg:city":"London",
    "sg:classifiers":[
        {
            "category":"Food & Beverages",
            "subcategory":"Specialty",
            "type":"Retail Goods"
        }
    ],
    "sg:postcode":"N7 6RZ",
    "sg:province":"Greater London",
    "sg:tags":[
        "product",
        "health"
    ],
    "wof:name":"Noahs Ark",
    "wof:placetype":"venue"
},
  "geometry": {"coordinates":[-0.1166990027,51.5576400757],"type":"Point"}
}