{
  "type": "Feature",
  "properties": {
    "addr:full":"15 Dean Park, Newstead Melrose Scottish Borders TD6 9RQ",
    "addr:housenumber":"15",
    "addr:postcode":"td6 9rq",
    "addr:street":"Dean Park",
    "iso:country":"GB",
    "sg:address":"15 Dean Park, Newstead",
    "sg:city":"Melrose",
    "sg:classifiers":[
        {
            "category":"Personal",
            "subcategory":"Beauty Salon",
            "type":"Services"
        }
    ],
    "sg:postcode":"TD6 9RQ",
    "sg:province":"Scottish Borders",
    "sg:tags":[
        "unisex",
        "hairdresser"
    ],
    "wof:name":"Hair by Kim",
    "wof:placetype":"venue"
},
  "geometry": {"coordinates":[-2.702141,55.598812],"type":"Point"}
}