{
  "type": "Feature",
  "properties": {
    "addr:full":"Britannia Chambers, 185 High St New Malden Surrey KT3 4BH",
    "addr:housenumber":"185",
    "addr:postcode":"kt3 4bh",
    "addr:street":"High St",
    "iso:country":"GB",
    "sg:address":"Britannia Chambers, 185 High St",
    "sg:city":"New Malden",
    "sg:classifiers":[
        {
            "category":"Building & Trades",
            "subcategory":"Equipment Rental",
            "type":"Services"
        }
    ],
    "sg:postcode":"KT3 4BH",
    "sg:province":"Surrey",
    "sg:tags":[
        "hire",
        "centre"
    ],
    "wof:name":"R S Leisure Ltd",
    "wof:placetype":"venue"
},
  "geometry": {"coordinates":[-0.2561939955,51.4017715454],"type":"Point"}
}