{
  "type": "Feature",
  "properties": {
    "addr:full":"Unit 1/5 London Greater London SW10 0XE",
    "addr:housenumber":"unit 1 / 5",
    "addr:postcode":"sw10 0xe",
    "iso:country":"GB",
    "sg:address":"Unit 1/5",
    "sg:city":"London",
    "sg:classifiers":[
        {
            "category":"Home & Garden",
            "subcategory":"Furniture",
            "type":"Retail Goods"
        }
    ],
    "sg:phone":"+44 20 7823 3848",
    "sg:postcode":"SW10 0XE",
    "sg:province":"Greater London",
    "sg:tags":[
        "outlet"
    ],
    "sg:website":"http://www.davidseyfried.com",
    "wof:name":"David Seyfried",
    "wof:placetype":"venue"
},
  "geometry": {"coordinates":[-0.1612890065,51.4202079773],"type":"Point"}
}