{
  "type": "Feature",
  "properties": {
    "addr:full":"74 Kingsway Woking Surrey GU21 6NS",
    "addr:housenumber":"74",
    "addr:postcode":"gu21 6ns",
    "addr:street":"Kingsway",
    "iso:country":"GB",
    "sg:address":"74 Kingsway",
    "sg:city":"Woking",
    "sg:classifiers":[
        {
            "category":"Shopping",
            "subcategory":"Pharmacy",
            "type":"Retail Goods"
        }
    ],
    "sg:postcode":"GU21 6NS",
    "sg:province":"Surrey",
    "sg:tags":[
        "medicine",
        "therapy"
    ],
    "wof:name":"Body Calm for Women",
    "wof:placetype":"venue"
},
  "geometry": {"coordinates":[-0.5714579821,51.3149375916],"type":"Point"}
}