{
  "type": "Feature",
  "properties": {
    "addr:full":"16 The Drive, Kingsley Northampton Northamptonshire NN1 4SH",
    "addr:housenumber":"16",
    "addr:postcode":"nn1 4sh",
    "addr:street":"The Drive",
    "iso:country":"GB",
    "sg:address":"16 The Drive, Kingsley",
    "sg:city":"Northampton",
    "sg:classifiers":[
        {
            "category":"Professional",
            "subcategory":"Management & Consulting",
            "type":"Services"
        }
    ],
    "sg:postcode":"NN1 4SH",
    "sg:province":"Northamptonshire",
    "sg:tags":[
        "consultant",
        "business"
    ],
    "wof:name":"Corbin Consulting",
    "wof:placetype":"venue"
},
  "geometry": {"coordinates":[-0.875738,52.252106],"type":"Point"}
}