{
  "type": "Feature",
  "properties": {
    "iso:country":"GB",
    "sg:address":"20 Jubilee Drive, Thornbury",
    "sg:city":"Bristol",
    "sg:classifiers":[
        {
            "category":"Professional",
            "subcategory":"Management & Consulting",
            "type":"Services"
        }
    ],
    "sg:postcode":"BS35 2YG",
    "sg:province":"Gloucestershire",
    "sg:tags":[
        "consultant",
        "business",
        "marketing"
    ],
    "wof:name":"121 Communications",
    "wof:placetype":"venue"
},
  "geometry": {"coordinates":[-2.508679,51.60849],"type":"Point"}
}