{
  "type": "Feature",
  "properties": {
    "iso:country":"GB",
    "sg:address":"55 Welley Rd",
    "sg:city":"Staines",
    "sg:classifiers":[
        {
            "category":"Place Of Worship",
            "type":"Public Place"
        }
    ],
    "sg:phone":"+44 1784 481258",
    "sg:postcode":"TW19 5ER",
    "sg:province":"Berkshire",
    "wof:name":"The Vicarage",
    "wof:placetype":"venue"
},
  "geometry": {"coordinates":[-0.561859,51.46365],"type":"Point"}
}