{
  "type": "Feature",
  "properties": {
    "iso:country":"GB",
    "sg:address":"Unit 3 New Wharf, Brighton Road",
    "sg:city":"Shoreham-by-sea",
    "sg:classifiers":[
        {
            "category":"Shopping",
            "subcategory":"Gifts & Souvenirs",
            "type":"Retail Goods"
        }
    ],
    "sg:phone":"+44 1273 230037",
    "sg:postcode":"BN43 6RN",
    "sg:province":"West Sussex",
    "sg:tags":[
        "giftware"
    ],
    "wof:name":"Paladone Products Ltd.",
    "wof:placetype":"venue"
},
  "geometry": {"coordinates":[-0.2764689922,50.8319168091],"type":"Point"}
}