{
  "type": "Feature",
  "properties": {
    "iso:country":"GB",
    "sg:address":"19 Clarkson Road",
    "sg:city":"Cambridge",
    "sg:classifiers":[
        {
            "category":"Communications",
            "type":"Services"
        }
    ],
    "sg:postcode":"CB3 0EH",
    "sg:province":"Cambridgeshire",
    "sg:tags":[
        "data",
        "network"
    ],
    "wof:name":"Grandmaster Data Services Ltd",
    "wof:placetype":"venue"
},
  "geometry": {"coordinates":[0.1009130031,52.2095870972],"type":"Point"}
}