{
  "type": "Feature",
  "properties": {
    "addr:full":"522 Liverpool Road, Irlam Manchester Greater Manchester M44 6AJ",
    "addr:housenumber":"522",
    "addr:postcode":"m44 6aj",
    "addr:street":"Liverpool Road",
    "iso:country":"GB",
    "sg:address":"522 Liverpool Road, Irlam",
    "sg:city":"Manchester",
    "sg:classifiers":[
        {
            "category":"Fast Food",
            "type":"Food & Drink"
        }
    ],
    "sg:phone":"+44 161 777 8020",
    "sg:postcode":"M44 6AJ",
    "sg:province":"Greater Manchester",
    "sg:tags":[
        "away",
        "take"
    ],
    "wof:name":"D & S J Poll",
    "wof:placetype":"venue"
},
  "geometry": {"coordinates":[-2.426439,53.439583],"type":"Point"}
}