{
  "type": "Feature",
  "properties": {
    "iso:country":"GB",
    "sg:address":"6 Lynwood Dr, Grn Acres",
    "sg:city":"Oldham",
    "sg:classifiers":[
        {
            "category":"Building & Trades",
            "subcategory":"Construction",
            "type":"Services"
        }
    ],
    "sg:postcode":"OL4 3HA",
    "sg:province":"Lancashire",
    "sg:tags":[
        "decorator",
        "painter"
    ],
    "wof:name":"Starling,David Brian,",
    "wof:placetype":"venue"
},
  "geometry": {"coordinates":[-2.0769209862,53.5465736389],"type":"Point"}
}