{
  "type": "Feature",
  "properties": {
    "iso:country":"GB",
    "sg:address":"19 Temple Street",
    "sg:city":"Birmingham",
    "sg:classifiers":[
        {
            "category":"Building & Trades",
            "subcategory":"Landscaping Services",
            "type":"Services"
        }
    ],
    "sg:phone":"+44 121 608 4008",
    "sg:postcode":"B2 5BG",
    "sg:province":"West Midlands",
    "sg:tags":[
        "landscape",
        "contractor"
    ],
    "wof:name":"Able Gardeners",
    "wof:placetype":"venue"
},
  "geometry": {"coordinates":[-1.899602,52.479416],"type":"Point"}
}