{
  "type": "Feature",
  "properties": {
    "addr:full":"2 Mill Hill Road Derby Derbyshire DE23 6SF",
    "addr:housenumber":"2",
    "addr:postcode":"de23 6sf",
    "addr:street":"Mill Hill Road",
    "iso:country":"GB",
    "sg:address":"2 Mill Hill Road",
    "sg:city":"Derby",
    "sg:classifiers":[
        {
            "category":"Health Services",
            "subcategory":"Dentist",
            "type":"Services"
        }
    ],
    "sg:phone":"+44 1332 364540",
    "sg:postcode":"DE23 6SF",
    "sg:province":"Derbyshire",
    "wof:name":"Mill Hill Dental Clinic",
    "wof:placetype":"venue"
},
  "geometry": {"coordinates":[-1.481524,52.912964],"type":"Point"}
}