{
  "type": "Feature",
  "properties": {
    "iso:country":"GB",
    "sg:address":"38 Pope Lane, Ribbleton",
    "sg:city":"Preston",
    "sg:classifiers":[
        {
            "category":"Utilities",
            "subcategory":"Natural Gas",
            "type":"Services"
        }
    ],
    "sg:phone":"+44 1772 705002",
    "sg:postcode":"PR2 6JL",
    "sg:province":"Lancashire",
    "sg:tags":[
        "supplier"
    ],
    "wof:name":"Jack's Gas",
    "wof:placetype":"venue"
},
  "geometry": {"coordinates":[-2.6532039642,53.7732582092],"type":"Point"}
}