{
  "type": "Feature",
  "properties": {
    "iso:country":"GB",
    "sg:address":"29 St Georges Pl",
    "sg:city":"Canterbury",
    "sg:classifiers":[
        {
            "category":"Home & Garden",
            "subcategory":"Carpets & Floor Coverings",
            "type":"Retail Goods"
        }
    ],
    "sg:phone":"+44 1227 788588",
    "sg:postcode":"CT1 1UT",
    "sg:province":"Kent",
    "sg:tags":[
        "carpets",
        "rug",
        "matting"
    ],
    "wof:name":"Clarks",
    "wof:placetype":"venue"
},
  "geometry": {"coordinates":[1.086291,51.275459],"type":"Point"}
}