{
  "type": "Feature",
  "properties": {
    "addr:full":"6-8 St Helens Square York North Yorkshire YO1 8QP",
    "addr:housenumber":"6-8",
    "addr:postcode":"yo1 8qp",
    "addr:street":"St Helens Square",
    "iso:country":"GB",
    "sg:address":"6-8 St Helens Square",
    "sg:city":"York",
    "sg:classifiers":[
        {
            "category":"Coffee & Tea",
            "type":"Food & Drink"
        },
        {
            "category":"Cafe",
            "type":"Food & Drink"
        }
    ],
    "sg:phone":"+44 1904 659142",
    "sg:postcode":"YO1 8QP",
    "sg:province":"North Yorkshire",
    "sg:tags":[
        "shop",
        "snack",
        "bar",
        "room"
    ],
    "wof:name":"Betty's Cafe Tea Rooms",
    "wof:placetype":"venue"
},
  "geometry": {"coordinates":[-1.084532,53.960114],"type":"Point"}
}