{
  "type": "Feature",
  "properties": {
    "iso:country":"GB",
    "sg:address":"37 Maud Road",
    "sg:city":"Dorchester",
    "sg:classifiers":[
        {
            "category":"Fast Food",
            "type":"Food & Drink"
        }
    ],
    "sg:phone":"+44 1305 268188",
    "sg:postcode":"DT1 2LP",
    "sg:province":"Dorset",
    "sg:tags":[
        "away",
        "meal",
        "outlet",
        "take"
    ],
    "wof:name":"The Imperial Dragon",
    "wof:placetype":"venue"
},
  "geometry": {"coordinates":[-2.446183,50.709774],"type":"Point"}
}