{
  "type": "Feature",
  "properties": {
    "iso:country":"GB",
    "sg:address":"Maudland Bank",
    "sg:city":"Preston",
    "sg:classifiers":[
        {
            "category":"Social Services",
            "subcategory":"Adult Care",
            "type":"Services"
        },
        {
            "category":"Social Services",
            "subcategory":"Retirement Home",
            "type":"Services"
        }
    ],
    "sg:phone":"+44 1772 823078",
    "sg:postcode":"PR1 2YJ",
    "sg:province":"Lancashire",
    "sg:tags":[
        "housing",
        "sheltered",
        "accommodation"
    ],
    "wof:name":"Maudland House",
    "wof:placetype":"venue"
},
  "geometry": {"coordinates":[-2.7126638889,53.7645950317],"type":"Point"}
}