{
  "type": "Feature",
  "properties": {
    "addr:full":"Robinswood, Central Avenue Hockley Essex SS5 6AU",
    "addr:postcode":"ss5 6au",
    "addr:street":"Central Avenue Hockley",
    "iso:country":"GB",
    "sg:address":"Robinswood, Central Avenue",
    "sg:city":"Hockley",
    "sg:classifiers":[
        {
            "category":"Building & Trades",
            "subcategory":"Cleaning & Sanitation",
            "type":"Services"
        }
    ],
    "sg:phone":"+44 1702 231662",
    "sg:postcode":"SS5 6AU",
    "sg:province":"Essex",
    "sg:tags":[
        "sweep",
        "chimney"
    ],
    "wof:name":"Ray Foster",
    "wof:placetype":"venue"
},
  "geometry": {"coordinates":[0.666821,51.606663],"type":"Point"}
}