{
  "type": "Feature",
  "properties": {
    "iso:country":"GB",
    "sg:address":"2 Burbage Rd",
    "sg:city":"Herne Hill",
    "sg:classifiers":[
        {
            "category":"Health Services",
            "subcategory":"Doctor",
            "type":"Services"
        }
    ],
    "sg:phone":"+44 20 7274 6138",
    "sg:postcode":"SE24 9HJ",
    "sg:province":"Greater London",
    "sg:tags":[
        "practitioners"
    ],
    "wof:name":"Drs Rathbone Stephens & Ledger",
    "wof:placetype":"venue"
},
  "geometry": {"coordinates":[-0.0962229967,51.4523506165],"type":"Point"}
}