{
  "type": "Feature",
  "properties": {
    "addr:full":"Ocean Road East Sunderland Tyne and Wear SR2 9RZ",
    "addr:postcode":"sr2 9rz",
    "addr:street":"Ocean Road East",
    "iso:country":"GB",
    "sg:address":"Ocean Road East",
    "sg:city":"Sunderland",
    "sg:classifiers":[
        {
            "category":"Professional",
            "subcategory":"Testing Lab",
            "type":"Services"
        }
    ],
    "sg:phone":"+44 191 567 2274",
    "sg:postcode":"SR2 9RZ",
    "sg:province":"Tyne and Wear",
    "sg:tags":[
        "mot"
    ],
    "wof:name":"Parkers Car Servicing",
    "wof:placetype":"venue"
},
  "geometry": {"coordinates":[-1.3652839661,54.8853034973],"type":"Point"}
}