{
  "type": "Feature",
  "properties": {
    "addr:full":"20 Woodhill Road Glasgow East Dunbartonshire G64 1JL",
    "addr:housenumber":"20",
    "addr:postcode":"g64 1jl",
    "addr:street":"Woodhill Road",
    "iso:country":"GB",
    "sg:address":"20 Woodhill Road",
    "sg:city":"Glasgow",
    "sg:classifiers":[
        {
            "category":"Fast Food",
            "type":"Food & Drink"
        }
    ],
    "sg:phone":"+44 141 762 3216",
    "sg:postcode":"G64 1JL",
    "sg:province":"East Dunbartonshire",
    "sg:tags":[
        "delivery"
    ],
    "wof:name":"The Woodhill Chinese Carry-Out",
    "wof:placetype":"venue"
},
  "geometry": {"coordinates":[-4.204020977,55.9001693726],"type":"Point"}
}