{
  "type": "Feature",
  "properties": {
    "addr:full":"171a High Street, Hampton Hill Hampton Greater London TW12 1NL",
    "addr:housenumber":"171a",
    "addr:postcode":"tw12 1nl",
    "addr:street":"High Street",
    "iso:country":"GB",
    "sg:address":"171a High Street, Hampton Hill",
    "sg:city":"Hampton",
    "sg:classifiers":[
        {
            "category":"Health Services",
            "subcategory":"Health Practitioner",
            "type":"Services"
        }
    ],
    "sg:phone":"+44 20 8979 4519",
    "sg:postcode":"TW12 1NL",
    "sg:province":"Greater London",
    "sg:tags":[
        "osteopath"
    ],
    "wof:name":"Osteopathic Care",
    "wof:placetype":"venue"
},
  "geometry": {"coordinates":[-0.3553990126,51.4277801514],"type":"Point"}
}