{
  "type": "Feature",
  "properties": {
    "iso:country":"GB",
    "sg:address":"13 Burhill Rd, Hersham",
    "sg:city":"Walton On Thames",
    "sg:classifiers":[
        {
            "category":"Professional",
            "subcategory":"Accounting & Tax Preparation",
            "type":"Services"
        }
    ],
    "sg:phone":"+44 1932 245078",
    "sg:postcode":"KT12 4JB",
    "sg:province":"Surrey",
    "sg:tags":[
        "accountant"
    ],
    "wof:name":"A.Y Jones",
    "wof:placetype":"venue"
},
  "geometry": {"coordinates":[-0.401573,51.36179],"type":"Point"}
}