{
  "type": "Feature",
  "properties": {
    "iso:country":"GB",
    "sg:address":"53 Crossdale Street, North Repps",
    "sg:city":"Cromer",
    "sg:classifiers":[
        {
            "category":"Building & Trades",
            "subcategory":"Cleaning & Sanitation",
            "type":"Services"
        }
    ],
    "sg:postcode":"NR27 9LB",
    "sg:province":"Norfolk",
    "sg:tags":[
        "steam"
    ],
    "wof:name":"A G Tool Hire",
    "wof:placetype":"venue"
},
  "geometry": {"coordinates":[1.310449,52.898281],"type":"Point"}
}