{
  "type": "Feature",
  "properties": {
    "addr:full":"12 East Street Tewkesbury Gloucestershire GL20 5NR",
    "addr:housenumber":"12",
    "addr:postcode":"gl20 5nr",
    "addr:street":"East Street",
    "iso:country":"GB",
    "sg:address":"12 East Street",
    "sg:city":"Tewkesbury",
    "sg:classifiers":[
        {
            "category":"Taxi",
            "type":"Transportation"
        },
        {
            "category":"Military Area",
            "subcategory":"Air Force Base",
            "type":"Public Place"
        }
    ],
    "sg:phone":"+44 1684 296153",
    "sg:postcode":"GL20 5NR",
    "sg:province":"Gloucestershire",
    "sg:tags":[
        "mini",
        "hire",
        "private",
        "cab"
    ],
    "wof:name":"N W B Taxis",
    "wof:placetype":"venue"
},
  "geometry": {"coordinates":[-2.153475,51.993286],"type":"Point"}
}