{
  "type": "Feature",
  "properties": {
    "addr:full":"1-9 St Marks Road London Greater London W11 1RG",
    "addr:housenumber":"1-9",
    "addr:postcode":"w11 1rg",
    "addr:street":"St Marks Road",
    "iso:country":"GB",
    "sg:address":"1-9 St Marks Road",
    "sg:city":"London",
    "sg:classifiers":[
        {
            "category":"Social Services",
            "subcategory":"Adult Care",
            "type":"Services"
        }
    ],
    "sg:phone":"+44 20 7727 6210",
    "sg:postcode":"W11 1RG",
    "sg:province":"Greater London",
    "sg:tags":[
        "day",
        "centre"
    ],
    "wof:name":"St Marks Mental Health Day Centre",
    "wof:placetype":"venue"
},
  "geometry": {"coordinates":[-0.209983,51.514683],"type":"Point"}
}