{
  "type": "Feature",
  "properties": {
    "addr:full":"Rutland Mills, Tootal St Wakefield West Yorkshire WF1 5JN",
    "addr:postcode":"wf1 5jn",
    "addr:street":"Rutland;St",
    "iso:country":"GB",
    "sg:address":"Rutland Mills, Tootal St",
    "sg:city":"Wakefield",
    "sg:classifiers":[
        {
            "category":"Education",
            "subcategory":"Music School",
            "type":"Public Place"
        }
    ],
    "sg:phone":"+44 1924 362636",
    "sg:postcode":"WF1 5JN",
    "sg:province":"West Yorkshire",
    "wof:name":"Springtime Studios",
    "wof:placetype":"venue"
},
  "geometry": {"coordinates":[-1.49043,53.675442],"type":"Point"}
}