{
  "type": "Feature",
  "properties": {
    "addr:full":"14 Osborne St Cleethorpes Lincolnshire DN35 8LB",
    "addr:housenumber":"14",
    "addr:postcode":"dn35 8lb",
    "addr:street":"Osborne St",
    "iso:country":"GB",
    "sg:address":"14 Osborne St",
    "sg:city":"Cleethorpes",
    "sg:classifiers":[
        {
            "category":"Organizations",
            "subcategory":"Non-profit Organization",
            "type":"Services"
        }
    ],
    "sg:phone":"+44 1472 605395",
    "sg:postcode":"DN35 8LB",
    "sg:province":"Lincolnshire",
    "sg:tags":[
        "organisation",
        "voluntary",
        "charity"
    ],
    "wof:name":"Age Concern",
    "wof:placetype":"venue"
},
  "geometry": {"coordinates":[-0.0304920003,53.560333252],"type":"Point"}
}