{
  "type": "Feature",
  "properties": {
    "addr:full":"9 Queens Chambers, Boldmere Road Sutton Coldfield West Midlands B73 5XA",
    "addr:housenumber":"9;chambers",
    "addr:postcode":"b73 5xa",
    "addr:street":"Queens;Boldmere Road",
    "iso:country":"GB",
    "sg:address":"9 Queens Chambers, Boldmere Road",
    "sg:city":"Sutton Coldfield",
    "sg:classifiers":[
        {
            "category":"Professional",
            "subcategory":"Employment Agencies",
            "type":"Services"
        }
    ],
    "sg:postcode":"B73 5XA",
    "sg:province":"West Midlands",
    "sg:tags":[
        "consultant"
    ],
    "wof:name":"Passing Trade",
    "wof:placetype":"venue"
},
  "geometry": {"coordinates":[-1.8411099911,52.5485687256],"type":"Point"}
}