{
  "type": "Feature",
  "properties": {
    "addr:full":"The Crescent, Tilsdown Dursley Gloucestershire GL11 5QS",
    "addr:postcode":"gl11 5qs",
    "addr:street":"The Crescent Tilsdown",
    "iso:country":"GB",
    "sg:address":"The Crescent, Tilsdown",
    "sg:city":"Dursley",
    "sg:classifiers":[
        {
            "category":"Shopping",
            "subcategory":"Department Store",
            "type":"Retail Goods"
        },
        {
            "category":"Food & Beverages",
            "subcategory":"Groceries & Convenience Stores",
            "type":"Retail Goods"
        }
    ],
    "sg:phone":"+44 1453 542608",
    "sg:postcode":"GL11 5QS",
    "sg:province":"Gloucestershire",
    "wof:name":"Summer Hayes Stores",
    "wof:placetype":"venue"
},
  "geometry": {"coordinates":[-2.3644089699,51.6976966858],"type":"Point"}
}