{
  "type": "Feature",
  "properties": {
    "addr:full":"151 Queen Street Glasgow Glasgow City G1 3BJ",
    "addr:housenumber":"151",
    "addr:postcode":"g1 3bj",
    "addr:street":"Queen Street",
    "iso:country":"GB",
    "sg:address":"151 Queen Street",
    "sg:city":"Glasgow",
    "sg:classifiers":[
        {
            "category":"Food & Beverages",
            "subcategory":"Bakery",
            "type":"Retail Goods"
        }
    ],
    "sg:phone":"+44 141 221 3333",
    "sg:postcode":"G1 3BJ",
    "sg:province":"Glasgow City",
    "sg:tags":[
        "pizza"
    ],
    "wof:name":"Pizzaexpress (Soho)",
    "wof:placetype":"venue"
},
  "geometry": {"coordinates":[-4.2518930435,55.8604354858],"type":"Point"}
}