{
  "type": "Feature",
  "properties": {
    "iso:country":"GB",
    "sg:address":"The Arts Centre, Vane Terrace",
    "sg:city":"Darlington",
    "sg:classifiers":[
        {
            "category":"Social Services",
            "subcategory":"Job Training",
            "type":"Services"
        },
        {
            "category":"Education",
            "subcategory":"Special Training",
            "type":"Public Place"
        }
    ],
    "sg:phone":"+44 1325 355750",
    "sg:postcode":"DL3 7AX",
    "sg:province":"Durham",
    "sg:tags":[
        "product",
        "centre"
    ],
    "wof:name":"Collin Associates",
    "wof:placetype":"venue"
},
  "geometry": {"coordinates":[-1.56596,54.52655],"type":"Point"}
}