{
  "type": "Feature",
  "properties": {
    "iso:country":"GB",
    "sg:address":"Heaton House, 64 King Street",
    "sg:city":"Nairn",
    "sg:classifiers":[
        {
            "category":"Professional",
            "subcategory":"Accounting & Tax Preparation",
            "type":"Services"
        }
    ],
    "sg:postcode":"IV12 4DN",
    "sg:province":"Highland",
    "sg:tags":[
        "accountant"
    ],
    "wof:name":"John Sutton & Co",
    "wof:placetype":"venue"
},
  "geometry": {"coordinates":[-3.8700690269,57.585609436],"type":"Point"}
}