{
  "type": "Feature",
  "properties": {
    "iso:country":"GB",
    "sg:address":"149 Oriental Rd",
    "sg:city":"Woking",
    "sg:classifiers":[
        {
            "category":"Place Of Worship",
            "type":"Public Place"
        }
    ],
    "sg:phone":"+44 1483 760679",
    "sg:postcode":"GU22 7BA",
    "sg:province":"Surrey",
    "wof:name":"Shahjahan Mosque",
    "wof:placetype":"venue"
},
  "geometry": {"coordinates":[-0.543828,51.322121],"type":"Point"}
}