{
  "type": "Feature",
  "properties": {
    "addr:full":"Anglia Ho, 103 Cherry Hinton Rd Cambridge Cambridgeshire CB1 7BS",
    "addr:housenumber":"103",
    "addr:postcode":"cb1 7bs",
    "addr:street":"Anglia;Cherry Hinton Rd",
    "iso:country":"GB",
    "sg:address":"Anglia Ho, 103 Cherry Hinton Rd",
    "sg:city":"Cambridge",
    "sg:classifiers":[
        {
            "category":"Building & Trades",
            "subcategory":"Construction",
            "type":"Services"
        }
    ],
    "sg:phone":"+44 1223 412000",
    "sg:postcode":"CB1 7BS",
    "sg:province":"Cambridgeshire",
    "sg:tags":[
        "builder"
    ],
    "wof:name":"Anglia Construction (Cambridge) Ltd",
    "wof:placetype":"venue"
},
  "geometry": {"coordinates":[0.1426399946,52.1884384155],"type":"Point"}
}