{
  "type": "Feature",
  "properties": {
    "addr:full":"37-41 High Street Bridlington East Riding of Yorkshire YO16 4PR",
    "addr:housenumber":"37-41",
    "addr:postcode":"yo16 4pr",
    "addr:street":"High Street",
    "iso:country":"GB",
    "sg:address":"37-41 High Street",
    "sg:city":"Bridlington",
    "sg:classifiers":[
        {
            "category":"Manufacturing",
            "subcategory":"Wood Products",
            "type":"Manufacturing & Wholesale Goods"
        }
    ],
    "sg:phone":"+44 1262 401064",
    "sg:postcode":"YO16 4PR",
    "sg:province":"East Riding of Yorkshire",
    "sg:tags":[
        "craftsman"
    ],
    "wof:name":"Crysalis (U K) Ltd.",
    "wof:placetype":"venue"
},
  "geometry": {"coordinates":[-0.2064950019,54.0930404663],"type":"Point"}
}