{
  "type": "Feature",
  "properties": {
    "addr:full":"Manhead Castle Exeter Devon EX6 8HD",
    "addr:postcode":"ex6 8hd",
    "iso:country":"GB",
    "sg:address":"Manhead Castle",
    "sg:city":"Exeter",
    "sg:classifiers":[
        {
            "category":"Building & Trades",
            "subcategory":"Landscaping Services",
            "type":"Services"
        }
    ],
    "sg:phone":"+44 1626 890405",
    "sg:postcode":"EX6 8HD",
    "sg:province":"Devon",
    "sg:tags":[
        "horticultural",
        "consultant"
    ],
    "wof:name":"South West Horticulture 2000 Ltd.",
    "wof:placetype":"venue"
},
  "geometry": {"coordinates":[-3.482239,50.65012],"type":"Point"}
}