{
  "type": "Feature",
  "properties": {
    "addr:full":"Cherry Rd Wisbech Cambridgeshire PE13 3NP",
    "addr:postcode":"pe13 3np",
    "addr:street":"Cherry Rd",
    "iso:country":"GB",
    "sg:address":"Cherry Rd",
    "sg:city":"Wisbech",
    "sg:classifiers":[
        {
            "category":"Education",
            "subcategory":"School",
            "type":"Public Place"
        }
    ],
    "sg:phone":"+44 1945 584026",
    "sg:postcode":"PE13 3NP",
    "sg:province":"Cambridgeshire",
    "sg:tags":[
        "local",
        "authority"
    ],
    "wof:name":"St Augustine's C Of E School",
    "wof:placetype":"venue"
},
  "geometry": {"coordinates":[0.1636780053,52.6788520813],"type":"Point"}
}