{
  "type": "Feature",
  "properties": {
    "addr:full":"20 West High Street, Kirkintilloch Glasgow East Dunbartonshire G66 1AA",
    "addr:housenumber":"20",
    "addr:postcode":"g66 1aa",
    "addr:street":"West High Street",
    "iso:country":"GB",
    "sg:address":"20 West High Street, Kirkintilloch",
    "sg:city":"Glasgow",
    "sg:classifiers":[
        {
            "category":"Personal",
            "subcategory":"Barber",
            "type":"Services"
        }
    ],
    "sg:phone":"+44 141 777 8667",
    "sg:postcode":"G66 1AA",
    "sg:province":"East Dunbartonshire",
    "sg:tags":[
        "men's",
        "hairdresser"
    ],
    "wof:name":"The Gent's Barbers",
    "wof:placetype":"venue"
},
  "geometry": {"coordinates":[-4.159952,55.941299],"type":"Point"}
}