{
  "type": "Feature",
  "properties": {
    "addr:full":"Cambridge Centre, 39 Cambridge St Glasgow Glasgow City G3 6TH",
    "addr:housenumber":"39",
    "addr:postcode":"g3 6th",
    "addr:street":"Cambridge St",
    "iso:country":"GB",
    "sg:address":"Cambridge Centre, 39 Cambridge St",
    "sg:city":"Glasgow",
    "sg:classifiers":[
        {
            "category":"Travel",
            "subcategory":"Travel Agent",
            "type":"Entertainment"
        }
    ],
    "sg:phone":"+44 141 331 2418",
    "sg:postcode":"G3 6TH",
    "sg:province":"Glasgow City",
    "wof:name":"Carlson Worldchoice",
    "wof:placetype":"venue"
},
  "geometry": {"coordinates":[-4.26015,55.86581],"type":"Point"}
}