{
  "type": "Feature",
  "properties": {
    "iso:country":"GB",
    "sg:address":"15 Baileydrive, Norwood Industrial Estate",
    "sg:city":"Sheffield",
    "sg:classifiers":[
        {
            "category":"Building & Trades",
            "subcategory":"Construction",
            "type":"Services"
        }
    ],
    "sg:phone":"+44 114 247 1163",
    "sg:postcode":"S21 2JF",
    "sg:province":"Derbyshire",
    "sg:tags":[
        "contractor",
        "paving",
        "driveway"
    ],
    "wof:name":"Upton Construction Ltd.",
    "wof:placetype":"venue"
},
  "geometry": {"coordinates":[-1.30397,53.33091],"type":"Point"}
}