{
  "type": "Feature",
  "properties": {
    "addr:full":"Coles La Dorking Surrey RH5 5SY",
    "addr:postcode":"rh5 5sy",
    "addr:street":"La Dorking",
    "iso:country":"GB",
    "sg:address":"Coles La",
    "sg:city":"Dorking",
    "sg:classifiers":[
        {
            "category":"Place Of Worship",
            "type":"Public Place"
        }
    ],
    "sg:phone":"+44 1306 712594",
    "sg:postcode":"RH5 5SY",
    "sg:province":"Surrey",
    "wof:name":"St Margaret's Church",
    "wof:placetype":"venue"
},
  "geometry": {"coordinates":[-0.3357439935,51.1502609253],"type":"Point"}
}