{
  "type": "Feature",
  "properties": {
    "iso:country":"GB",
    "sg:address":"161 Rosebery Avenue",
    "sg:city":"London",
    "sg:classifiers":[
        {
            "category":"Wholesale",
            "subcategory":"Books, Periodicals, & Newspapers",
            "type":"Manufacturing & Wholesale Goods"
        }
    ],
    "sg:phone":"+44 20 7837 0143",
    "sg:postcode":"EC1R 4QX",
    "sg:province":"Greater London",
    "sg:tags":[
        "publishing"
    ],
    "wof:name":"Architecture Today Plc",
    "wof:placetype":"venue"
},
  "geometry": {"coordinates":[-0.107705,51.52758],"type":"Point"}
}