{
  "type": "Feature",
  "properties": {
    "addr:full":"15 High Street, Whitton Twickenham Greater London TW2 7LA",
    "addr:housenumber":"15",
    "addr:postcode":"tw2 7la",
    "addr:street":"High Street",
    "iso:country":"GB",
    "sg:address":"15 High Street, Whitton",
    "sg:city":"Twickenham",
    "sg:classifiers":[
        {
            "category":"Shopping",
            "subcategory":"Bicycles & Sporting Goods",
            "type":"Retail Goods"
        }
    ],
    "sg:phone":"+44 20 8755 0441",
    "sg:postcode":"TW2 7LA",
    "sg:province":"Greater London",
    "sg:tags":[
        "dance",
        "balletwear"
    ],
    "wof:name":"Just Dancing",
    "wof:placetype":"venue"
},
  "geometry": {"coordinates":[-0.3578389883,51.4527282715],"type":"Point"}
}