{
  "type": "Feature",
  "properties": {
    "addr:full":"19 Glasgow Road Paisley Renfrewshire PA1 3QX",
    "addr:housenumber":"19",
    "addr:postcode":"pa1 3qx",
    "addr:street":"Glasgow Road",
    "iso:country":"GB",
    "sg:address":"19 Glasgow Road",
    "sg:city":"Paisley",
    "sg:classifiers":[
        {
            "category":"Professional",
            "subcategory":"Business Services",
            "type":"Services"
        }
    ],
    "sg:postcode":"PA1 3QX",
    "sg:province":"Renfrewshire",
    "sg:tags":[
        "distributor",
        "film"
    ],
    "wof:name":"Be-Biaz Entertainment Ltd",
    "wof:placetype":"venue"
},
  "geometry": {"coordinates":[-4.414228,55.847275],"type":"Point"}
}