{
  "type": "Feature",
  "properties": {
    "addr:full":"Llanfaenor Court Farm, Newcastle Monmouth Gloucestershire NP25 5NF",
    "addr:postcode":"np25 5nf",
    "addr:street":"Llanfaenor",
    "iso:country":"GB",
    "sg:address":"Llanfaenor Court Farm, Newcastle",
    "sg:city":"Monmouth",
    "sg:classifiers":[
        {
            "category":"Building & Trades",
            "subcategory":"Landscaping Services",
            "type":"Services"
        },
        {
            "category":"Building & Trades",
            "subcategory":"Cleaning & Sanitation",
            "type":"Services"
        }
    ],
    "sg:phone":"+44 1600 772126",
    "sg:postcode":"NP25 5NF",
    "sg:province":"Gloucestershire",
    "sg:tags":[
        "steel",
        "agricultural"
    ],
    "wof:name":"Industrial Development & Farm Services",
    "wof:placetype":"venue"
},
  "geometry": {"coordinates":[-2.8024799824,51.8515625],"type":"Point"}
}