{
  "type": "Feature",
  "properties": {
    "iso:country":"GB",
    "sg:address":"9 Gower Street",
    "sg:city":"London",
    "sg:classifiers":[
        {
            "category":"Professional",
            "subcategory":"Advertising",
            "type":"Services"
        }
    ],
    "sg:phone":"+44 20 7916 3791",
    "sg:postcode":"WC1E 6HB",
    "sg:province":"Greater London",
    "sg:tags":[
        "agency"
    ],
    "wof:name":"Dacosta & Co. Ltd.",
    "wof:placetype":"venue"
},
  "geometry": {"coordinates":[-0.130194,51.520123],"type":"Point"}
}