{
  "type": "Feature",
  "properties": {
    "iso:country":"GB",
    "sg:address":"82f James Carter Road, Mildenhall",
    "sg:city":"Bury St Edmunds",
    "sg:classifiers":[
        {
            "category":"Retail",
            "subcategory":"Repair Shop",
            "type":"Services"
        }
    ],
    "sg:phone":"+44 1638 515375",
    "sg:postcode":"IP28 7DE",
    "sg:province":"Cambridgeshire",
    "sg:tags":[
        "upholstering",
        "upholsterer"
    ],
    "wof:name":"A B CRAFT UPHOLSTERY",
    "wof:placetype":"venue"
},
  "geometry": {"coordinates":[0.501271,52.35363],"type":"Point"}
}