{
  "type": "Feature",
  "properties": {
    "addr:full":"30 South Avenue Stourbridge Staffordshire DY8 3XY",
    "addr:housenumber":"30",
    "addr:postcode":"dy8 3xy",
    "addr:street":"South Avenue",
    "iso:country":"GB",
    "sg:address":"30 South Avenue",
    "sg:city":"Stourbridge",
    "sg:classifiers":[
        {
            "category":"Shopping",
            "subcategory":"Books",
            "type":"Retail Goods"
        },
        {
            "category":"Professional",
            "subcategory":"Business Services",
            "type":"Services"
        }
    ],
    "sg:phone":"+44 1384 397475",
    "sg:postcode":"DY8 3XY",
    "sg:province":"Staffordshire",
    "sg:tags":[
        "publishers'"
    ],
    "wof:name":"The Robinswood Press",
    "wof:placetype":"venue"
},
  "geometry": {"coordinates":[-2.1537048817,52.451713562],"type":"Point"}
}