{
  "type": "Feature",
  "properties": {
    "iso:country":"GB",
    "sg:address":"Bridge Wharf Ho, The Quay",
    "sg:city":"Sandwich",
    "sg:classifiers":[
        {
            "category":"Banks & Credit Unions",
            "subcategory":"Financial Services",
            "type":"Services"
        }
    ],
    "sg:phone":"+44 1304 619001",
    "sg:postcode":"CT13 9EN",
    "sg:province":"Kent",
    "sg:tags":[
        "adviser"
    ],
    "wof:name":"Calkin & Parr",
    "wof:placetype":"venue"
},
  "geometry": {"coordinates":[1.342304,51.276169],"type":"Point"}
}