{
  "type": "Feature",
  "properties": {
    "iso:country":"GB",
    "sg:address":"The Gravel, Mere Brow",
    "sg:city":"Preston",
    "sg:classifiers":[
        {
            "category":"Education",
            "subcategory":"School",
            "type":"Public Place"
        },
        {
            "category":"Government",
            "subcategory":"Office",
            "type":"Public Place"
        }
    ],
    "sg:phone":"+44 1772 812689",
    "sg:postcode":"PR4 6JX",
    "sg:province":"Lancashire",
    "sg:tags":[
        "local",
        "authority"
    ],
    "wof:name":"Mere Brow C of E Primary School",
    "wof:placetype":"venue"
},
  "geometry": {"coordinates":[-2.8803129196,53.6623497009],"type":"Point"}
}