{
  "type": "Feature",
  "properties": {
    "addr:full":"16 Park Rd New Milton Hampshire BH25 5DR",
    "addr:housenumber":"16",
    "addr:postcode":"bh25 5dr",
    "addr:street":"Park Rd",
    "iso:country":"GB",
    "sg:address":"16 Park Rd",
    "sg:city":"New Milton",
    "sg:classifiers":[
        {
            "category":"Recreation",
            "subcategory":"Dance Hall",
            "type":"Entertainment"
        }
    ],
    "sg:phone":"+44 1425 617610",
    "sg:postcode":"BH25 5DR",
    "sg:province":"Hampshire",
    "sg:tags":[
        "disco"
    ],
    "wof:name":"3D Disco",
    "wof:placetype":"venue"
},
  "geometry": {"coordinates":[-1.642737031,50.7640762329],"type":"Point"}
}