{
  "type": "Feature",
  "properties": {
    "addr:full":"Homestead Cottage Faringdon Oxfordshire SN7 7XR",
    "addr:postcode":"sn7 7xr",
    "addr:street":"Faringdon",
    "iso:country":"GB",
    "sg:address":"Homestead Cottage",
    "sg:city":"Faringdon",
    "sg:classifiers":[
        {
            "category":"Home & Garden",
            "subcategory":"Carpets & Floor Coverings",
            "type":"Retail Goods"
        }
    ],
    "sg:phone":"+44 1367 243752",
    "sg:postcode":"SN7 7XR",
    "sg:province":"Oxfordshire",
    "sg:tags":[
        "cleaner",
        "upholstery"
    ],
    "wof:name":"G N C Contract Services",
    "wof:placetype":"venue"
},
  "geometry": {"coordinates":[-1.5866539478,51.6561698914],"type":"Point"}
}