{
  "type": "Feature",
  "properties": {
    "iso:country":"GB",
    "sg:address":"11-12 Lansdowne Row",
    "sg:city":"London",
    "sg:classifiers":[
        {
            "category":"Shopping",
            "subcategory":"Clothing, Apparel, & Fashions",
            "type":"Retail Goods"
        }
    ],
    "sg:phone":"+44 20 7495 3695",
    "sg:postcode":"W1J 6DP",
    "sg:province":"Greater London",
    "sg:tags":[
        "menswear"
    ],
    "wof:name":"Hugo Morelli Menswear",
    "wof:placetype":"venue"
},
  "geometry": {"coordinates":[-0.207067,51.509209],"type":"Point"}
}