{
  "type": "Feature",
  "properties": {
    "addr:full":"Knowlton Court, Knowlton Canterbury Kent CT3 1PT",
    "addr:postcode":"ct3 1pt",
    "addr:street":"Knowlton Court",
    "iso:country":"GB",
    "sg:address":"Knowlton Court, Knowlton",
    "sg:city":"Canterbury",
    "sg:classifiers":[
        {
            "category":"Travel",
            "subcategory":"Hotels & Motels",
            "type":"Entertainment"
        }
    ],
    "sg:postcode":"CT3 1PT",
    "sg:province":"Kent",
    "sg:tags":[
        "house",
        "self",
        "guest",
        "catering"
    ],
    "wof:name":"O Fox-Pitt",
    "wof:placetype":"venue"
},
  "geometry": {"coordinates":[1.268337965,51.2332572937],"type":"Point"}
}