{
  "type": "Feature",
  "properties": {
    "addr:full":"Main Street, Tomintoul Ballindalloch Moray AB37 9EX",
    "addr:postcode":"ab37 9ex",
    "addr:street":"Main Street",
    "iso:country":"GB",
    "sg:address":"Main Street, Tomintoul",
    "sg:city":"Ballindalloch",
    "sg:classifiers":[
        {
            "category":"Travel",
            "subcategory":"Hotels & Motels",
            "type":"Entertainment"
        }
    ],
    "sg:postcode":"AB37 9EX",
    "sg:province":"Moray",
    "sg:tags":[
        "house",
        "guest"
    ],
    "wof:name":"Argyle House",
    "wof:placetype":"venue"
},
  "geometry": {"coordinates":[-3.378499,57.251144],"type":"Point"}
}