{
  "type": "Feature",
  "properties": {
    "iso:country":"GB",
    "sg:address":"West Street",
    "sg:city":"Sowerby Bridge",
    "sg:classifiers":[
        {
            "category":"Autos & Motor Vehicles",
            "subcategory":"Fuel & Gas Station",
            "type":"Retail Goods"
        }
    ],
    "sg:postcode":"HX6 3AP",
    "sg:province":"West Yorkshire",
    "sg:tags":[
        "petrol",
        "filling"
    ],
    "wof:name":"West End Filling Station",
    "wof:placetype":"venue"
},
  "geometry": {"coordinates":[-1.913379,53.706974],"type":"Point"}
}