{
  "type": "Feature",
  "properties": {
    "addr:full":"116 Ashley Road St Albans Hertfordshire AL1 5JR",
    "addr:housenumber":"116",
    "addr:postcode":"al1 5jr",
    "addr:street":"Ashley Road",
    "iso:country":"GB",
    "sg:address":"116 Ashley Road",
    "sg:city":"St Albans",
    "sg:classifiers":[
        {
            "category":"Autos & Motor Vehicles",
            "subcategory":"Fuel & Gas Station",
            "type":"Retail Goods"
        }
    ],
    "sg:postcode":"AL1 5JR",
    "sg:province":"Hertfordshire",
    "sg:tags":[
        "petrol",
        "filling"
    ],
    "wof:name":"Total Convenience Store",
    "wof:placetype":"venue"
},
  "geometry": {"coordinates":[-0.3054850101,51.7490921021],"type":"Point"}
}