{
  "type": "Feature",
  "properties": {
    "iso:country":"GB",
    "sg:address":"Montrose House, 143 Newgate Street",
    "sg:city":"Bishop Auckland",
    "sg:classifiers":[
        {
            "category":"Manufacturing",
            "subcategory":"Wood Products",
            "type":"Manufacturing & Wholesale Goods"
        }
    ],
    "sg:postcode":"DL14 7EN",
    "sg:province":"Durham",
    "sg:tags":[
        "maker",
        "cabinet"
    ],
    "wof:name":"Montrose Designs",
    "wof:placetype":"venue"
},
  "geometry": {"coordinates":[-1.675387,54.660637],"type":"Point"}
}