{
  "type": "Feature",
  "properties": {
    "addr:full":"College Farm, Butlers Marston Warwick Warwickshire CV35 0NE",
    "addr:housenumber":"butlers",
    "addr:postcode":"cv35 0ne",
    "iso:country":"GB",
    "sg:address":"College Farm, Butlers Marston",
    "sg:city":"Warwick",
    "sg:classifiers":[
        {
            "category":"Farming",
            "subcategory":"Livestock Farm",
            "type":"Manufacturing & Wholesale Goods"
        }
    ],
    "sg:postcode":"CV35 0NE",
    "sg:province":"Warwickshire",
    "sg:tags":[
        "others"
    ],
    "wof:name":"W H Faulkner Horse Slaughterers",
    "wof:placetype":"venue"
},
  "geometry": {"coordinates":[-1.5353490114,52.1475296021],"type":"Point"}
}