{
  "type": "Feature",
  "properties": {
    "iso:country":"GB",
    "sg:address":"126 Nearmoor Rd",
    "sg:city":"Birmingham",
    "sg:classifiers":[
        {
            "category":"Education",
            "subcategory":"Special Training",
            "type":"Public Place"
        }
    ],
    "sg:phone":"+44 121 747 1811",
    "sg:postcode":"B34 7QE",
    "sg:province":"West Midlands",
    "sg:tags":[
        "product",
        "centre"
    ],
    "wof:name":"Charles Payne Training",
    "wof:placetype":"venue"
},
  "geometry": {"coordinates":[-1.768902,52.495052],"type":"Point"}
}