{
  "type": "Feature",
  "properties": {
    "iso:country":"GB",
    "sg:address":"The Old Smithy Pont Ar Hydfer, Glasfynydd Trecastle",
    "sg:city":"Brecon",
    "sg:classifiers":[
        {
            "category":"Professional",
            "subcategory":"Management & Consulting",
            "type":"Services"
        }
    ],
    "sg:phone":"+44 1874 638042",
    "sg:postcode":"LD3 8YE",
    "sg:province":"Powys",
    "sg:tags":[
        "consultant",
        "business"
    ],
    "wof:name":"Decision Dynamics Ltd.",
    "wof:placetype":"venue"
},
  "geometry": {"coordinates":[-3.6314361095,51.9502601624],"type":"Point"}
}