{
  "type": "Feature",
  "properties": {
    "addr:full":"31 High Street Snodland Kent ME6 5AG",
    "addr:housenumber":"31",
    "addr:postcode":"me6 5ag",
    "addr:street":"High Street",
    "iso:country":"GB",
    "sg:address":"31 High Street",
    "sg:city":"Snodland",
    "sg:classifiers":[
        {
            "category":"Retail",
            "subcategory":"Funeral Services",
            "type":"Services"
        }
    ],
    "sg:phone":"+44 1634 240458",
    "sg:postcode":"ME6 5AG",
    "sg:province":"Kent",
    "sg:tags":[
        "director"
    ],
    "wof:name":"Clarkes Funeral Services Ltd.",
    "wof:placetype":"venue"
},
  "geometry": {"coordinates":[0.444055,51.32996],"type":"Point"}
}