{
  "type": "Feature",
  "properties": {
    "addr:full":"11 Langley High Street Oldbury West Midlands B69 4SN",
    "addr:housenumber":"11",
    "addr:postcode":"b69 4sn",
    "addr:street":"Langley High Street",
    "iso:country":"GB",
    "sg:address":"11 Langley High Street",
    "sg:city":"Oldbury",
    "sg:classifiers":[
        {
            "category":"Shopping",
            "subcategory":"Department Store",
            "type":"Retail Goods"
        },
        {
            "category":"Shopping",
            "subcategory":"Gifts & Souvenirs",
            "type":"Retail Goods"
        }
    ],
    "sg:phone":"+44 121 552 9977",
    "sg:postcode":"B69 4SN",
    "sg:province":"West Midlands",
    "sg:tags":[
        "shop",
        "poster",
        "card"
    ],
    "wof:name":"Luv N Kissiz Greeting Cards",
    "wof:placetype":"venue"
},
  "geometry": {"coordinates":[-2.012463,52.490894],"type":"Point"}
}