{
  "type": "Feature",
  "properties": {
    "iso:country":"GB",
    "sg:address":"55 The Ridgeway",
    "sg:city":"Burntwood",
    "sg:classifiers":[
        {
            "category":"Social Services",
            "subcategory":"Retirement Home",
            "type":"Services"
        }
    ],
    "sg:phone":"+44 1543 676305",
    "sg:postcode":"WS7 8SP",
    "sg:province":"Staffordshire",
    "sg:tags":[
        "care"
    ],
    "wof:name":"Tender Loving Care Home Care Services",
    "wof:placetype":"venue"
},
  "geometry": {"coordinates":[-1.9232970476,52.6703987122],"type":"Point"}
}