{
  "type": "Feature",
  "properties": {
    "iso:country":"GB",
    "sg:address":"122 London Road, Headington",
    "sg:city":"Oxford",
    "sg:classifiers":[
        {
            "category":"Real Estate",
            "subcategory":"Real Estate Agent",
            "type":"Services"
        }
    ],
    "sg:phone":"+44 1865 760881",
    "sg:postcode":"OX3 9AZ",
    "sg:province":"Oxfordshire",
    "wof:name":"Buckell & Ballard",
    "wof:placetype":"venue"
},
  "geometry": {"coordinates":[-1.210706,51.760105],"type":"Point"}
}