{
  "type": "Feature",
  "properties": {
    "iso:country":"GB",
    "sg:address":"Sheffield Road",
    "sg:city":"Dronfield",
    "sg:classifiers":[
        {
            "category":"Bars & Pubs",
            "type":"Food & Drink"
        }
    ],
    "sg:phone":"+44 1246 412326",
    "sg:postcode":"S18 2GA",
    "sg:province":"Derbyshire",
    "sg:tags":[
        "pubs",
        "inn"
    ],
    "wof:name":"Bowshaw Inn",
    "wof:placetype":"venue"
},
  "geometry": {"coordinates":[-1.472709,53.30328],"type":"Point"}
}