{
  "type": "Feature",
  "properties": {
    "iso:country":"GB",
    "sg:address":"9-9b Unit Blackbrook Valley Industrial, Ustrial Estate",
    "sg:city":"Dudley",
    "sg:classifiers":[
        {
            "category":"Manufacturing",
            "subcategory":"Tools & Machinery",
            "type":"Manufacturing & Wholesale Goods"
        },
        {
            "category":"Home & Garden",
            "subcategory":"Building Materials",
            "type":"Retail Goods"
        },
        {
            "category":"Home & Garden",
            "subcategory":"Hardware",
            "type":"Retail Goods"
        }
    ],
    "sg:phone":"+44 1384 457081",
    "sg:postcode":"DY2 0XQ",
    "sg:province":"West Midlands",
    "sg:tags":[
        "merchant",
        "supplier",
        "ironmonger"
    ],
    "sg:website":"http://www.intertool.co.uk",
    "wof:name":"Intertool Ltd",
    "wof:placetype":"venue"
},
  "geometry": {"coordinates":[-2.0979819298,52.4838218689],"type":"Point"}
}