{
  "type": "Feature",
  "properties": {
    "addr:full":"844 Stratford Rd Birmingham West Midlands B11 4BS",
    "addr:housenumber":"844",
    "addr:postcode":"b11 4bs",
    "addr:street":"Stratford Rd",
    "iso:country":"GB",
    "sg:address":"844 Stratford Rd",
    "sg:city":"Birmingham",
    "sg:classifiers":[
        {
            "category":"Shopping",
            "subcategory":"Shoes",
            "type":"Retail Goods"
        }
    ],
    "sg:postcode":"B11 4BS",
    "sg:province":"West Midlands",
    "sg:tags":[
        "shop"
    ],
    "wof:name":"Springfield,R N,",
    "wof:placetype":"venue"
},
  "geometry": {"coordinates":[-1.8590129614,52.4448432922],"type":"Point"}
}