{
  "type": "Feature",
  "properties": {
    "addr:full":"40-42 High Street Weybridge Surrey KT13 8AB",
    "addr:housenumber":"40-42",
    "addr:postcode":"kt13 8ab",
    "addr:street":"High Street",
    "iso:country":"GB",
    "sg:address":"40-42 High Street",
    "sg:city":"Weybridge",
    "sg:classifiers":[
        {
            "category":"Home & Garden",
            "subcategory":"Furniture",
            "type":"Retail Goods"
        }
    ],
    "sg:phone":"+44 1932 856745",
    "sg:postcode":"KT13 8AB",
    "sg:province":"Surrey",
    "wof:name":"S L B Holdings Ltd.",
    "wof:placetype":"venue"
},
  "geometry": {"coordinates":[-0.457713,51.373089],"type":"Point"}
}