{
  "type": "Feature",
  "properties": {
    "addr:full":"157 Edwin Rd Gillingham Kent ME8 0AQ",
    "addr:housenumber":"157",
    "addr:postcode":"me8 0aq",
    "addr:street":"Edwin Rd",
    "iso:country":"GB",
    "sg:address":"157 Edwin Rd",
    "sg:city":"Gillingham",
    "sg:classifiers":[
        {
            "category":"Building & Trades",
            "subcategory":"Construction",
            "type":"Services"
        }
    ],
    "sg:phone":"+44 1634 232363",
    "sg:postcode":"ME8 0AQ",
    "sg:province":"Kent",
    "sg:tags":[
        "builder"
    ],
    "wof:name":"Brieth Builders",
    "wof:placetype":"venue"
},
  "geometry": {"coordinates":[0.585441,51.359921],"type":"Point"}
}