{
  "type": "Feature",
  "properties": {
    "iso:country":"GB",
    "sg:address":"Heath Street",
    "sg:city":"Buxton",
    "sg:classifiers":[
        {
            "category":"Retail",
            "subcategory":"Auto Repair",
            "type":"Services"
        }
    ],
    "sg:phone":"+44 1298 26388",
    "sg:postcode":"SK17 6LT",
    "sg:province":"Derbyshire",
    "sg:tags":[
        "modification",
        "garage"
    ],
    "wof:name":"Heath Street Garage Ltd.",
    "wof:placetype":"venue"
},
  "geometry": {"coordinates":[-1.9126839638,53.2534408569],"type":"Point"}
}