{
  "type": "Feature",
  "properties": {
    "iso:country":"GB",
    "sg:address":"21 Belleisle Place, Capington Estate",
    "sg:city":"Kilmarnock",
    "sg:classifiers":[
        {
            "category":"Retail",
            "subcategory":"Driving School",
            "type":"Services"
        }
    ],
    "sg:postcode":"KA1 4UD",
    "sg:province":"East Ayrshire",
    "wof:name":"Kerr School of Motoring",
    "wof:placetype":"venue"
},
  "geometry": {"coordinates":[-4.505786,55.590492],"type":"Point"}
}