{
  "type": "Feature",
  "properties": {
    "addr:full":"Minavil House, Ealing Road Wembley Greater London HA0 4EL",
    "addr:postcode":"ha0 4el",
    "addr:street":"Ealing Road",
    "iso:country":"GB",
    "sg:address":"Minavil House, Ealing Road",
    "sg:city":"Wembley",
    "sg:classifiers":[
        {
            "category":"Professional",
            "subcategory":"Accounting & Tax Preparation",
            "type":"Services"
        }
    ],
    "sg:postcode":"HA0 4EL",
    "sg:province":"Greater London",
    "sg:tags":[
        "accountant"
    ],
    "wof:name":"Ashley Eaton & Co. Limited",
    "wof:placetype":"venue"
},
  "geometry": {"coordinates":[-0.298694,51.551109],"type":"Point"}
}