{
  "type": "Feature",
  "properties": {
    "addr:full":"Laurels Court, Rock Road, Borrow Grn Sevenoaks Kent TN15 8RD",
    "addr:postcode":"tn15 8rd",
    "addr:street":"Laurels Court Rock Road Borrow Grn",
    "iso:country":"GB",
    "sg:address":"Laurels Court, Rock Road, Borrow Grn",
    "sg:city":"Sevenoaks",
    "sg:classifiers":[
        {
            "category":"Building & Trades",
            "subcategory":"Construction",
            "type":"Services"
        }
    ],
    "sg:phone":"+44 1732 883240",
    "sg:postcode":"TN15 8RD",
    "sg:province":"Kent",
    "sg:tags":[
        "decorator",
        "painter"
    ],
    "wof:name":"Imperial Painting Contractors Ltd.",
    "wof:placetype":"venue"
},
  "geometry": {"coordinates":[0.303226,51.291237],"type":"Point"}
}