{
  "type": "Feature",
  "properties": {
    "iso:country":"GB",
    "sg:address":"211 Ashby Road",
    "sg:city":"Burton-on-trent",
    "sg:classifiers":[
        {
            "category":"Professional",
            "subcategory":"Research",
            "type":"Services"
        }
    ],
    "sg:postcode":"DE15 0LA",
    "sg:province":"Derbyshire",
    "sg:tags":[
        "market"
    ],
    "wof:name":"Quali Tate",
    "wof:placetype":"venue"
},
  "geometry": {"coordinates":[-1.6164540052,52.8045730591],"type":"Point"}
}