{
  "type": "Feature",
  "properties": {
    "addr:full":"Unit 3 Shard Clo Liverpool Merseyside L11 0DW",
    "addr:housenumber":"unit 3",
    "addr:postcode":"l11 0dw",
    "addr:street":"Shard Clo",
    "iso:country":"GB",
    "sg:address":"Unit 3 Shard Clo",
    "sg:city":"Liverpool",
    "sg:classifiers":[
        {
            "category":"Recreation",
            "type":"Entertainment"
        }
    ],
    "sg:phone":"+44 151 284 9064",
    "sg:postcode":"L11 0DW",
    "sg:province":"Merseyside",
    "sg:tags":[
        "snooker",
        "billiards",
        "pool"
    ],
    "wof:name":"Croxteth Snooker Hall",
    "wof:placetype":"venue"
},
  "geometry": {"coordinates":[-2.9083580971,53.4583282471],"type":"Point"}
}