{
  "type": "Feature",
  "properties": {
    "iso:country":"GB",
    "sg:address":"Blacklocks Hill",
    "sg:city":"Banbury",
    "sg:classifiers":[
        {
            "category":"Education",
            "subcategory":"School",
            "type":"Public Place"
        }
    ],
    "sg:phone":"+44 1295 262144",
    "sg:postcode":"OX17 2BS",
    "sg:province":"Northamptonshire",
    "sg:tags":[
        "foundation",
        "college"
    ],
    "wof:name":"Overthorpe Preparatory School",
    "wof:placetype":"venue"
},
  "geometry": {"coordinates":[-1.304967,52.070332],"type":"Point"}
}