{
  "type": "Feature",
  "properties": {
    "addr:full":"240 Amhurst Road London Greater London E8 2BS",
    "addr:housenumber":"240",
    "addr:postcode":"e8 2bs",
    "addr:street":"Amhurst Road",
    "iso:country":"GB",
    "sg:address":"240 Amhurst Road",
    "sg:city":"London",
    "sg:classifiers":[
        {
            "category":"Bars & Pubs",
            "type":"Food & Drink"
        }
    ],
    "sg:phone":"+44 20 7254 6410",
    "sg:postcode":"E8 2BS",
    "sg:province":"Greater London",
    "sg:tags":[
        "pubs",
        "inn"
    ],
    "wof:name":"The Amhurst Arms",
    "wof:placetype":"venue"
},
  "geometry": {"coordinates":[-0.0681999996,51.5545692444],"type":"Point"}
}