{
  "type": "Feature",
  "properties": {
    "iso:country":"GB",
    "sg:address":"48 High Street",
    "sg:city":"Maryport",
    "sg:classifiers":[
        {
            "category":"Taxi",
            "type":"Transportation"
        }
    ],
    "sg:phone":"+44 1900 818686",
    "sg:postcode":"CA15 6BQ",
    "sg:province":"Cumbria",
    "sg:tags":[
        "mini",
        "hire",
        "cab",
        "private",
        "vehicle"
    ],
    "wof:name":"Keith's Kabs",
    "wof:placetype":"venue"
},
  "geometry": {"coordinates":[-3.499882,54.714058],"type":"Point"}
}