{
  "type": "Feature",
  "properties": {
    "addr:full":"7 Boverton Road Llantwit Major The Vale of Glamorgan CF61 1XZ",
    "addr:housenumber":"7",
    "addr:postcode":"cf61 1xz",
    "addr:street":"Boverton Road;Vale",
    "iso:country":"GB",
    "sg:address":"7 Boverton Road",
    "sg:city":"Llantwit Major",
    "sg:classifiers":[
        {
            "category":"Shopping",
            "subcategory":"Pharmacy",
            "type":"Retail Goods"
        },
        {
            "category":"Food & Beverages",
            "subcategory":"Groceries & Convenience Stores",
            "type":"Retail Goods"
        }
    ],
    "sg:phone":"+44 1446 792300",
    "sg:postcode":"CF61 1XZ",
    "sg:province":"The Vale of Glamorgan",
    "sg:tags":[
        "pharmacist",
        "chemist"
    ],
    "wof:name":"SARAH EDWARDS",
    "wof:placetype":"venue"
},
  "geometry": {"coordinates":[-3.4806149006,51.407951355],"type":"Point"}
}