{
  "type": "Feature",
  "properties": {
    "addr:full":"401 Cannock Road Wolverhampton Staffordshire WV10 0BQ",
    "addr:housenumber":"401",
    "addr:postcode":"wv10 0bq",
    "addr:street":"Cannock Road",
    "iso:country":"GB",
    "sg:address":"401 Cannock Road",
    "sg:city":"Wolverhampton",
    "sg:classifiers":[
        {
            "category":"Autos & Motor Vehicles",
            "subcategory":"Automobile Sales",
            "type":"Retail Goods"
        }
    ],
    "sg:phone":"+44 1902 733377",
    "sg:postcode":"WV10 0BQ",
    "sg:province":"Staffordshire",
    "sg:tags":[
        "car"
    ],
    "wof:name":"Hylton of Wolverhampton",
    "wof:placetype":"venue"
},
  "geometry": {"coordinates":[-2.1119689941,52.5974693298],"type":"Point"}
}