{
  "type": "Feature",
  "properties": {
    "addr:full":"2 Chester Walksy, Bredbury Grn Stockport Cheshire SK6 3HJ",
    "addr:housenumber":"2",
    "addr:postcode":"sk6 3hj",
    "addr:street":"Bredbury Grn",
    "iso:country":"GB",
    "sg:address":"2 Chester Walksy, Bredbury Grn",
    "sg:city":"Stockport",
    "sg:classifiers":[
        {
            "category":"Government",
            "subcategory":"Customs House",
            "type":"Public Place"
        }
    ],
    "sg:phone":"+44 161 430 8926",
    "sg:postcode":"SK6 3HJ",
    "sg:province":"Cheshire",
    "sg:tags":[
        "clearance"
    ],
    "wof:name":"Atherton Allsorts",
    "wof:placetype":"venue"
},
  "geometry": {"coordinates":[-2.10149,53.408882],"type":"Point"}
}