{
  "type": "Feature",
  "properties": {
    "addr:full":"Birch House, Hen Lon Parcwr Ruthin Denbighshire LL15 1NA",
    "addr:postcode":"ll15 1na",
    "iso:country":"GB",
    "sg:address":"Birch House, Hen Lon Parcwr",
    "sg:city":"Ruthin",
    "sg:classifiers":[
        {
            "category":"Professional",
            "subcategory":"Accounting & Tax Preparation",
            "type":"Services"
        }
    ],
    "sg:postcode":"LL15 1NA",
    "sg:province":"Denbighshire",
    "sg:tags":[
        "accountant"
    ],
    "wof:name":"De Longa & Co",
    "wof:placetype":"venue"
},
  "geometry": {"coordinates":[-3.304522,53.114017],"type":"Point"}
}