{
  "type": "Feature",
  "properties": {
    "addr:full":"6 Brown Street Carnoustie Angus DD7 7EZ",
    "addr:housenumber":"6",
    "addr:postcode":"dd7 7ez",
    "addr:street":"Brown Street",
    "iso:country":"GB",
    "sg:address":"6 Brown Street",
    "sg:city":"Carnoustie",
    "sg:classifiers":[
        {
            "category":"Health Services",
            "subcategory":"Dentist",
            "type":"Services"
        }
    ],
    "sg:phone":"+44 1241 854832",
    "sg:postcode":"DD7 7EZ",
    "sg:province":"Angus",
    "wof:name":"Fraser Kidd Dental Practice",
    "wof:placetype":"venue"
},
  "geometry": {"coordinates":[-2.725241,56.500389],"type":"Point"}
}