{
  "type": "Feature",
  "properties": {
    "addr:full":"91 Brunswick Quay, Surrey Quays London Greater London SE16 7PX",
    "addr:housenumber":"91",
    "addr:postcode":"se16 7px",
    "addr:street":"Brunswick Quay",
    "iso:country":"GB",
    "sg:address":"91 Brunswick Quay, Surrey Quays",
    "sg:city":"London",
    "sg:classifiers":[
        {
            "category":"Communications",
            "type":"Services"
        }
    ],
    "sg:postcode":"SE16 7PX",
    "sg:province":"Greater London",
    "sg:tags":[
        "telecommunication"
    ],
    "wof:name":"St. George Communications Ltd",
    "wof:placetype":"venue"
},
  "geometry": {"coordinates":[-0.0435680002,51.4947433472],"type":"Point"}
}