{
  "type": "Feature",
  "properties": {
    "addr:full":"Lower Prescoed Farm Usk Monmouthshire NP15 1PS",
    "addr:postcode":"np15 1ps",
    "iso:country":"GB",
    "sg:address":"Lower Prescoed Farm",
    "sg:city":"Usk",
    "sg:classifiers":[
        {
            "category":"Taxi",
            "type":"Transportation"
        }
    ],
    "sg:phone":"+44 1291 672734",
    "sg:postcode":"NP15 1PS",
    "sg:province":"Monmouthshire",
    "sg:tags":[
        "mini",
        "cab"
    ],
    "wof:name":"John Lewis Taxis",
    "wof:placetype":"venue"
},
  "geometry": {"coordinates":[-2.902848959,51.7037353516],"type":"Point"}
}