{
  "type": "Feature",
  "properties": {
    "addr:full":"Cauldon Low Quarry Stoke On Trent Staffordshire ST10 3EW",
    "addr:postcode":"st10 3ew",
    "addr:street":"Stoke",
    "iso:country":"GB",
    "sg:address":"Cauldon Low Quarry",
    "sg:city":"Stoke On Trent",
    "sg:classifiers":[
        {
            "category":"Manufacturing",
            "subcategory":"Glass & Minerals",
            "type":"Manufacturing & Wholesale Goods"
        }
    ],
    "sg:phone":"+44 1538 308282",
    "sg:postcode":"ST10 3EW",
    "sg:province":"Staffordshire",
    "sg:tags":[
        "chalk",
        "stone",
        "slate"
    ],
    "wof:name":"Tarmac Quarry Products (Central) Ltd",
    "wof:placetype":"venue"
},
  "geometry": {"coordinates":[-1.8781150579,53.0287590027],"type":"Point"}
}