{
  "type": "Feature",
  "properties": {
    "iso:country":"GB",
    "sg:address":"Unit 22 Phoenix Indust Est Charles St",
    "sg:city":"West Bromwich",
    "sg:classifiers":[
        {
            "category":"Manufacturing",
            "subcategory":"Tools & Machinery",
            "type":"Manufacturing & Wholesale Goods"
        },
        {
            "category":"Wholesale",
            "subcategory":"Scrap",
            "type":"Manufacturing & Wholesale Goods"
        }
    ],
    "sg:postcode":"B70 0AY",
    "sg:province":"West Midlands",
    "sg:tags":[
        "waste",
        "metal",
        "power"
    ],
    "wof:name":"R S A Metals",
    "wof:placetype":"venue"
},
  "geometry": {"coordinates":[-2.0233900547,52.524974823],"type":"Point"}
}