{
  "type": "Feature",
  "properties": {
    "iso:country":"GB",
    "sg:address":"60 Worsley Road, Farnworth",
    "sg:city":"Bolton",
    "sg:classifiers":[
        {
            "category":"Building & Trades",
            "subcategory":"Construction",
            "type":"Services"
        }
    ],
    "sg:phone":"+44 1204 573158",
    "sg:postcode":"BL4 9LT",
    "sg:province":"Lancashire",
    "sg:tags":[
        "builder"
    ],
    "wof:name":"Terence O'Connor",
    "wof:placetype":"venue"
},
  "geometry": {"coordinates":[-2.4001379013,53.5411491394],"type":"Point"}
}