{
  "type": "Feature",
  "properties": {
    "addr:full":"Atlantic Street Altrincham Cheshire WA14 5EB",
    "addr:postcode":"wa14 5eb",
    "addr:street":"Atlantic Street",
    "iso:country":"GB",
    "sg:address":"Atlantic Street",
    "sg:city":"Altrincham",
    "sg:classifiers":[
        {
            "category":"Professional",
            "subcategory":"Printing & Photocopies",
            "type":"Services"
        }
    ],
    "sg:postcode":"WA14 5EB",
    "sg:province":"Cheshire",
    "sg:tags":[
        "printer"
    ],
    "wof:name":"B D Print Ltd.",
    "wof:placetype":"venue"
},
  "geometry": {"coordinates":[-2.354186,53.398666],"type":"Point"}
}