{
  "type": "Feature",
  "properties": {
    "iso:country":"GB",
    "sg:address":"Market Square, Llay",
    "sg:city":"Wrexham",
    "sg:classifiers":[
        {
            "category":"Food & Beverages",
            "subcategory":"Meat & Fish",
            "type":"Retail Goods"
        }
    ],
    "sg:phone":"+44 1978 856172",
    "sg:postcode":"LL12 0SA",
    "sg:province":"Wrexham",
    "sg:tags":[
        "butcher"
    ],
    "wof:name":"J T James Family Butchers",
    "wof:placetype":"venue"
},
  "geometry": {"coordinates":[-3.000814,53.093639],"type":"Point"}
}