{
  "type": "Feature",
  "properties": {
    "addr:full":"Lea Valley Trading Estate, Harbet Road, Edmonton London Greater London N18 3LA",
    "addr:postcode":"n18 3la",
    "addr:street":"Harbet Road Edmonton",
    "iso:country":"GB",
    "sg:address":"Lea Valley Trading Estate, Harbet Road, Edmonton",
    "sg:city":"London",
    "sg:classifiers":[
        {
            "category":"Shopping",
            "subcategory":"Stationery & Office Supplies",
            "type":"Retail Goods"
        }
    ],
    "sg:phone":"+44 20 8803 4433",
    "sg:postcode":"N18 3LA",
    "sg:province":"Greater London",
    "sg:tags":[
        "equipment",
        "furniture"
    ],
    "wof:name":"Roseberry Office Furniture Ltd.",
    "wof:placetype":"venue"
},
  "geometry": {"coordinates":[-0.04085,51.608398],"type":"Point"}
}