{
  "type": "Feature",
  "properties": {
    "iso:country":"GB",
    "sg:address":"High House Farm, Ockendon Road",
    "sg:city":"Upminster",
    "sg:classifiers":[
        {
            "category":"Retail",
            "subcategory":"Auto Repair",
            "type":"Services"
        }
    ],
    "sg:postcode":"RM14 2DN",
    "sg:province":"Essex",
    "sg:tags":[
        "engine",
        "car",
        "specialist"
    ],
    "wof:name":"Freeway Engines",
    "wof:placetype":"venue"
},
  "geometry": {"coordinates":[0.24926,51.556339],"type":"Point"}
}