{
  "type": "Feature",
  "properties": {
    "iso:country":"GB",
    "sg:address":"11 Northfield Way",
    "sg:city":"Brighton",
    "sg:classifiers":[
        {
            "category":"Building & Trades",
            "subcategory":"Construction",
            "type":"Services"
        }
    ],
    "sg:postcode":"BN1 8EH",
    "sg:province":"East Sussex",
    "sg:tags":[
        "roofing"
    ],
    "wof:name":"Roy Colin Duke",
    "wof:placetype":"venue"
},
  "geometry": {"coordinates":[-0.1373949945,50.8553581238],"type":"Point"}
}