{
  "type": "Feature",
  "properties": {
    "addr:full":"33 Mosbach Gardens, Hutton Brentwood Essex CM13 2UW",
    "addr:housenumber":"33",
    "addr:postcode":"cm13 2uw",
    "addr:street":"Mosbach Gardens Hutton",
    "iso:country":"GB",
    "sg:address":"33 Mosbach Gardens, Hutton",
    "sg:city":"Brentwood",
    "sg:classifiers":[
        {
            "category":"Building & Trades",
            "subcategory":"Construction",
            "type":"Services"
        }
    ],
    "sg:phone":"+44 1277 200346",
    "sg:postcode":"CM13 2UW",
    "sg:province":"Essex",
    "sg:tags":[
        "tile",
        "fitting",
        "tiling",
        "laying",
        "contractor"
    ],
    "wof:name":"Uptown Tiling",
    "wof:placetype":"venue"
},
  "geometry": {"coordinates":[0.333337,51.619576],"type":"Point"}
}