{
  "type": "Feature",
  "properties": {
    "addr:full":"66 Park St Camberley Berkshire GU15 3PE",
    "addr:housenumber":"66",
    "addr:postcode":"gu15 3pe",
    "addr:street":"Park St",
    "iso:country":"GB",
    "sg:address":"66 Park St",
    "sg:city":"Camberley",
    "sg:classifiers":[
        {
            "category":"Shopping",
            "subcategory":"Department Store",
            "type":"Retail Goods"
        }
    ],
    "sg:postcode":"GU15 3PE",
    "sg:province":"Berkshire",
    "wof:name":"Browne,Keith,",
    "wof:placetype":"venue"
},
  "geometry": {"coordinates":[-0.7478039861,51.3364944458],"type":"Point"}
}