{
  "type": "Feature",
  "properties": {
    "addr:full":"46 London Road Southampton Hampshire SO15 2AH",
    "addr:housenumber":"46",
    "addr:postcode":"so15 2ah",
    "addr:street":"London Road",
    "iso:country":"GB",
    "sg:address":"46 London Road",
    "sg:city":"Southampton",
    "sg:classifiers":[
        {
            "category":"Real Estate",
            "subcategory":"Surveying",
            "type":"Services"
        }
    ],
    "sg:phone":"+44 23 8022 6941",
    "sg:postcode":"SO15 2AH",
    "sg:province":"Hampshire",
    "sg:tags":[
        "surveyor",
        "valuer"
    ],
    "wof:name":"Connell Survey & Valuation",
    "wof:placetype":"venue"
},
  "geometry": {"coordinates":[-1.4036420584,50.9119033813],"type":"Point"}
}