{
  "type": "Feature",
  "properties": {
    "addr:full":"179 High Road, Chilwell Nottingham Nottinghamshire NG9 5BA",
    "addr:housenumber":"179",
    "addr:postcode":"ng9 5ba",
    "addr:street":"High Road",
    "iso:country":"GB",
    "sg:address":"179 High Road, Chilwell",
    "sg:city":"Nottingham",
    "sg:classifiers":[
        {
            "category":"Food & Beverages",
            "subcategory":"Liquor & Beverages",
            "type":"Retail Goods"
        }
    ],
    "sg:postcode":"NG9 5BA",
    "sg:province":"Nottinghamshire",
    "sg:tags":[
        "beer",
        "spirit",
        "wines"
    ],
    "wof:name":"Plumb's",
    "wof:placetype":"venue"
},
  "geometry": {"coordinates":[-1.2278529406,52.9190864563],"type":"Point"}
}