{
  "type": "Feature",
  "properties": {
    "addr:full":"1092 Melton Rd Leicester Leicestershire LE7 2HA",
    "addr:housenumber":"1092",
    "addr:postcode":"le7 2ha",
    "addr:street":"Melton Rd",
    "iso:country":"GB",
    "sg:address":"1092 Melton Rd",
    "sg:city":"Leicester",
    "sg:classifiers":[
        {
            "category":"Shopping",
            "subcategory":"News",
            "type":"Retail Goods"
        }
    ],
    "sg:phone":"+44 116 260 8725",
    "sg:postcode":"LE7 2HA",
    "sg:province":"Leicestershire",
    "sg:tags":[
        "newsagent"
    ],
    "wof:name":"Jogis News",
    "wof:placetype":"venue"
},
  "geometry": {"coordinates":[-1.0809910297,52.694103241],"type":"Point"}
}