{
  "type": "Feature",
  "properties": {
    "addr:full":"Manor Cottage, Bremhill Calne Wiltshire SN11 9LA",
    "addr:postcode":"sn11 9la",
    "iso:country":"GB",
    "sg:address":"Manor Cottage, Bremhill",
    "sg:city":"Calne",
    "sg:classifiers":[
        {
            "category":"Farming",
            "subcategory":"Farm",
            "type":"Manufacturing & Wholesale Goods"
        }
    ],
    "sg:phone":"+44 1249 812115",
    "sg:postcode":"SN11 9LA",
    "sg:province":"Wiltshire",
    "sg:tags":[
        "mixed",
        "crop"
    ],
    "wof:name":"T R C Vines",
    "wof:placetype":"venue"
},
  "geometry": {"coordinates":[-2.0307838917,51.4569320679],"type":"Point"}
}