{
  "type": "Feature",
  "properties": {
    "addr:full":"Penn Street Rochdale Lancashire OL16 1HX",
    "addr:postcode":"ol16 1hx",
    "addr:street":"Penn Street",
    "iso:country":"GB",
    "sg:address":"Penn Street",
    "sg:city":"Rochdale",
    "sg:classifiers":[
        {
            "category":"Professional",
            "subcategory":"Lawyer & Legal Services",
            "type":"Services"
        }
    ],
    "sg:phone":"+44 1706 755024",
    "sg:postcode":"OL16 1HX",
    "sg:province":"Lancashire",
    "sg:tags":[
        "advice",
        "counselling"
    ],
    "wof:name":"The Pennine Acute Hospitals N H S Trust",
    "wof:placetype":"venue"
},
  "geometry": {"coordinates":[-2.1551389694,53.6192550659],"type":"Point"}
}