{
  "type": "Feature",
  "properties": {
    "addr:full":"4 Marine Parade North Berwick East Lothian EH39 4LD",
    "addr:housenumber":"4",
    "addr:postcode":"eh39 4ld",
    "addr:street":"Marine Parade;Berwick",
    "iso:country":"GB",
    "sg:address":"4 Marine Parade",
    "sg:city":"North Berwick",
    "sg:classifiers":[
        {
            "category":"Travel",
            "subcategory":"Hotels & Motels",
            "type":"Entertainment"
        }
    ],
    "sg:postcode":"EH39 4LD",
    "sg:province":"East Lothian",
    "wof:name":"Tantallon Inn",
    "wof:placetype":"venue"
},
  "geometry": {"coordinates":[-2.7115681171,56.0581970215],"type":"Point"}
}