{
  "type": "Feature",
  "properties": {
    "iso:country":"GB",
    "sg:address":"4 Marine Parade",
    "sg:city":"North Berwick",
    "sg:classifiers":[
        {
            "category":"Travel",
            "subcategory":"Hotels & Motels",
            "type":"Entertainment"
        }
    ],
    "sg:postcode":"EH39 4LD",
    "sg:province":"East Lothian",
    "wof:name":"Tantallon Inn",
    "wof:placetype":"venue"
},
  "geometry": {"coordinates":[-2.7115681171,56.0581970215],"type":"Point"}
}