{
  "type": "Feature",
  "properties": {
    "iso:country":"GB",
    "sg:address":"Snag Lane Farm, Snag Lane",
    "sg:city":"Sevenoaks",
    "sg:classifiers":[
        {
            "category":"Real Estate",
            "subcategory":"Real Estate Agent",
            "type":"Services"
        }
    ],
    "sg:postcode":"TN14 7RG",
    "sg:province":"Kent",
    "wof:name":"Rumble Property & Management Ltd.",
    "wof:placetype":"venue"
},
  "geometry": {"coordinates":[0.08275,51.338612],"type":"Point"}
}