{
  "type": "Feature",
  "properties": {
    "iso:country":"GB",
    "sg:address":"23 Market Place",
    "sg:city":"Leek",
    "sg:classifiers":[
        {
            "category":"Shopping",
            "subcategory":"Gifts & Souvenirs",
            "type":"Retail Goods"
        }
    ],
    "sg:phone":"+44 1538 382280",
    "sg:postcode":"ST13 5HJ",
    "sg:province":"Staffordshire",
    "sg:tags":[
        "shop"
    ],
    "wof:name":"Beechcraft",
    "wof:placetype":"venue"
},
  "geometry": {"coordinates":[-2.025399,53.105949],"type":"Point"}
}