{
  "type": "Feature",
  "properties": {
    "addr:full":"Jasmin House, Ayscough Street, West Marsh Industrial Estate Grimsby Lincolnshire DN31 1TG",
    "addr:postcode":"dn31 1tg",
    "addr:street":"Ayscough Street West Marsh Industrial Estate",
    "iso:country":"GB",
    "sg:address":"Jasmin House, Ayscough Street, West Marsh Industrial Estate",
    "sg:city":"Grimsby",
    "sg:classifiers":[
        {
            "category":"Manufacturing",
            "subcategory":"Wood Products",
            "type":"Manufacturing & Wholesale Goods"
        }
    ],
    "sg:phone":"+44 1472 250868",
    "sg:postcode":"DN31 1TG",
    "sg:province":"Lincolnshire",
    "sg:tags":[
        "packaging",
        "crate",
        "pallets"
    ],
    "wof:name":"Tach-It (U K) Ltd.",
    "wof:placetype":"venue"
},
  "geometry": {"coordinates":[-0.0922589973,53.5720939636],"type":"Point"}
}