{
  "type": "Feature",
  "properties": {
    "addr:full":"Unit 5, Shaftesbury Road, Leyton London Greater London E10 7DA",
    "addr:housenumber":"unit 5",
    "addr:postcode":"e10 7da",
    "addr:street":"Shaftesbury Road",
    "iso:country":"GB",
    "sg:address":"Unit 5, Shaftesbury Road, Leyton",
    "sg:city":"London",
    "sg:classifiers":[
        {
            "category":"Manufacturing",
            "subcategory":"Wood Products",
            "type":"Manufacturing & Wholesale Goods"
        },
        {
            "category":"Building & Trades",
            "subcategory":"Construction",
            "type":"Services"
        }
    ],
    "sg:phone":"+44 20 8539 2276",
    "sg:postcode":"E10 7DA",
    "sg:province":"Greater London",
    "sg:tags":[
        "joinery",
        "sawmill",
        "shaving"
    ],
    "wof:name":"Nash Conversions (Leytonstone)",
    "wof:placetype":"venue"
},
  "geometry": {"coordinates":[-0.019504,51.565945],"type":"Point"}
}