{
  "type": "Feature",
  "properties": {
    "iso:country":"GB",
    "sg:address":"Event House, Queen Margarets Road",
    "sg:city":"Scarborough",
    "sg:classifiers":[
        {
            "category":"Wholesale",
            "subcategory":"Machinery & Supplies",
            "type":"Manufacturing & Wholesale Goods"
        }
    ],
    "sg:phone":"+44 1723 374791",
    "sg:postcode":"YO11 2SA",
    "sg:province":"North Yorkshire",
    "sg:tags":[
        "theatrical"
    ],
    "wof:name":"Q D O S Entertainment Plc",
    "wof:placetype":"venue"
},
  "geometry": {"coordinates":[-0.403754,54.270573],"type":"Point"}
}