{
  "type": "Feature",
  "properties": {
    "iso:country":"GB",
    "sg:address":"Taplow Health Centre, 3 Minton Rise",
    "sg:city":"Maidenhead",
    "sg:classifiers":[
        {
            "category":"Health Services",
            "subcategory":"Doctor",
            "type":"Services"
        }
    ],
    "sg:phone":"+44 1628 602345",
    "sg:postcode":"SL6 0PD",
    "sg:province":"Berkshire",
    "sg:tags":[
        "practitioners"
    ],
    "wof:name":"Obi, B C",
    "wof:placetype":"venue"
},
  "geometry": {"coordinates":[-0.727257,51.522373],"type":"Point"}
}