{
  "type": "Feature",
  "properties": {
    "addr:full":"3 Cote Hill Drive, Ponteland Newcastle-upon-tyne Northumberland NE20 9HW",
    "addr:housenumber":"3",
    "addr:postcode":"ne20 9hw",
    "addr:street":"Cote Hill Drive Ponteland",
    "iso:country":"GB",
    "sg:address":"3 Cote Hill Drive, Ponteland",
    "sg:city":"Newcastle-upon-tyne",
    "sg:classifiers":[
        {
            "category":"Retail",
            "subcategory":"Auto Repair",
            "type":"Services"
        }
    ],
    "sg:phone":"+44 191 488 1788",
    "sg:postcode":"NE20 9HW",
    "sg:province":"Northumberland",
    "sg:tags":[
        "modification",
        "garage"
    ],
    "wof:name":"Brackwell Ltd.",
    "wof:placetype":"venue"
},
  "geometry": {"coordinates":[-1.7723770142,55.0414047241],"type":"Point"}
}