{
  "type": "Feature",
  "properties": {
    "iso:country":"GB",
    "sg:address":"8 Parade Mews, Norwood Road",
    "sg:city":"London",
    "sg:classifiers":[
        {
            "category":"Retail",
            "subcategory":"Repair Shop",
            "type":"Services"
        }
    ],
    "sg:postcode":"SE27 9AX",
    "sg:province":"Greater London",
    "sg:tags":[
        "upholsterer"
    ],
    "wof:name":"A I Tapley",
    "wof:placetype":"venue"
},
  "geometry": {"coordinates":[-0.1069400012,51.4397583008],"type":"Point"}
}