{
  "type": "Feature",
  "properties": {
    "iso:country":"GB",
    "sg:address":"12 Ludlow Road",
    "sg:city":"Guildford",
    "sg:classifiers":[
        {
            "category":"Communications",
            "type":"Services"
        }
    ],
    "sg:postcode":"GU2 7NR",
    "sg:province":"Surrey",
    "sg:tags":[
        "audio-visual"
    ],
    "wof:name":"Video Image",
    "wof:placetype":"venue"
},
  "geometry": {"coordinates":[-0.5849450231,51.2364425659],"type":"Point"}
}