{
  "type": "Feature",
  "properties": {
    "iso:country":"GB",
    "sg:address":"Unit 4, 50 Rutland Rd",
    "sg:city":"Sheffield",
    "sg:classifiers":[
        {
            "category":"Shopping",
            "subcategory":"Bicycles & Sporting Goods",
            "type":"Retail Goods"
        },
        {
            "category":"Recreation",
            "subcategory":"Fishing",
            "type":"Entertainment"
        }
    ],
    "sg:phone":"+44 114 273 7049",
    "sg:postcode":"S3 8BD",
    "sg:province":"South Yorkshire",
    "sg:tags":[
        "equipment",
        "angling"
    ],
    "wof:name":"Yorkshire Groundbaits",
    "wof:placetype":"venue"
},
  "geometry": {"coordinates":[-1.476981,53.392937],"type":"Point"}
}