{
  "type": "Feature",
  "properties": {
    "addr:full":"14-16 High Street Newcastle Staffordshire ST5 1RA",
    "addr:housenumber":"14-16",
    "addr:postcode":"st5 1ra",
    "addr:street":"High Street",
    "iso:country":"GB",
    "sg:address":"14-16 High Street",
    "sg:city":"Newcastle",
    "sg:classifiers":[
        {
            "category":"Food & Beverages",
            "subcategory":"Meat & Fish",
            "type":"Retail Goods"
        }
    ],
    "sg:phone":"+44 1782 610130",
    "sg:postcode":"ST5 1RA",
    "sg:province":"Staffordshire",
    "sg:tags":[
        "butcher"
    ],
    "wof:name":"Plant & Wilton Ltd.",
    "wof:placetype":"venue"
},
  "geometry": {"coordinates":[-2.2294130325,53.0121421814],"type":"Point"}
}