{
  "type": "Feature",
  "properties": {
    "iso:country":"GB",
    "sg:address":"9 Stephenson Close",
    "sg:city":"Royston",
    "sg:classifiers":[
        {
            "category":"Organizations",
            "subcategory":"Non-profit Organization",
            "type":"Services"
        }
    ],
    "sg:phone":"+44 1763 230350",
    "sg:postcode":"SG8 5TT",
    "sg:province":"Bedfordshire",
    "sg:tags":[
        "organisation",
        "voluntary",
        "charity"
    ],
    "wof:name":"Royston Area Community Church",
    "wof:placetype":"venue"
},
  "geometry": {"coordinates":[-0.032994,52.0513],"type":"Point"}
}