{
  "type": "Feature",
  "properties": {
    "addr:full":"2 Upper High St Thame Buckinghamshire OX9 2ER",
    "addr:housenumber":"2",
    "addr:postcode":"ox9 2er",
    "addr:street":"Upper High St",
    "iso:country":"GB",
    "sg:address":"2 Upper High St",
    "sg:city":"Thame",
    "sg:classifiers":[
        {
            "category":"Building & Trades",
            "subcategory":"Locksmith",
            "type":"Services"
        }
    ],
    "sg:phone":"+44 1844 216355",
    "sg:postcode":"OX9 2ER",
    "sg:province":"Buckinghamshire",
    "sg:tags":[
        "cutting",
        "key"
    ],
    "wof:name":"Lock & Key Shop",
    "wof:placetype":"venue"
},
  "geometry": {"coordinates":[-0.976769,51.746662],"type":"Point"}
}