{
  "type": "Feature",
  "properties": {
    "iso:country":"GB",
    "sg:address":"P O Box 342",
    "sg:city":"West Byfleet",
    "sg:classifiers":[
        {
            "category":"Professional",
            "subcategory":"Lawyer & Legal Services",
            "type":"Services"
        }
    ],
    "sg:phone":"+44 1932 355800",
    "sg:postcode":"KT14 6YX",
    "sg:province":"Surrey",
    "sg:tags":[
        "solicitor"
    ],
    "wof:name":"Graham White & Co",
    "wof:placetype":"venue"
},
  "geometry": {"coordinates":[-0.496921,51.338421],"type":"Point"}
}