{
  "type": "Feature",
  "properties": {
    "addr:full":"296 Newark Road, North Hykeham Lincoln Lincolnshire LN6 8JX",
    "addr:housenumber":"296",
    "addr:postcode":"ln6 8jx",
    "addr:street":"Newark Road North",
    "iso:country":"GB",
    "sg:address":"296 Newark Road, North Hykeham",
    "sg:city":"Lincoln",
    "sg:classifiers":[
        {
            "category":"Autos & Motor Vehicles",
            "subcategory":"Automobile Sales",
            "type":"Retail Goods"
        }
    ],
    "sg:phone":"+44 1522 684842",
    "sg:postcode":"LN6 8JX",
    "sg:province":"Lincolnshire",
    "sg:tags":[
        "car"
    ],
    "wof:name":"Cars Sales",
    "wof:placetype":"venue"
},
  "geometry": {"coordinates":[-0.561160028,53.2012786865],"type":"Point"}
}