{
  "type": "Feature",
  "properties": {
    "iso:country":"GB",
    "sg:address":"Holly Walk",
    "sg:city":"Enfield",
    "sg:classifiers":[
        {
            "category":"Education",
            "subcategory":"School",
            "type":"Public Place"
        }
    ],
    "sg:phone":"+44 20 8363 3030",
    "sg:postcode":"EN2 6QG",
    "sg:province":"Greater London",
    "sg:tags":[
        "local",
        "authority"
    ],
    "wof:name":"Enfield County Upper School",
    "wof:placetype":"venue"
},
  "geometry": {"coordinates":[-0.086589,51.654705],"type":"Point"}
}