{
  "type": "Feature",
  "properties": {
    "addr:full":"12 Gowthorpe Selby East Riding of Yorkshire YO8 4ET",
    "addr:housenumber":"12",
    "addr:postcode":"yo8 4et",
    "addr:street":"Gowthorpe",
    "iso:country":"GB",
    "sg:address":"12 Gowthorpe",
    "sg:city":"Selby",
    "sg:classifiers":[
        {
            "category":"Food & Beverages",
            "subcategory":"Supermarket",
            "type":"Retail Goods"
        }
    ],
    "sg:phone":"+44 1757 210211",
    "sg:postcode":"YO8 4ET",
    "sg:province":"East Riding of Yorkshire",
    "wof:name":"G T Smith Ltd.",
    "wof:placetype":"venue"
},
  "geometry": {"coordinates":[-1.070082,53.784019],"type":"Point"}
}