{
  "type": "Feature",
  "properties": {
    "iso:country":"GB",
    "sg:address":"7 General Havelock Road",
    "sg:city":"Sunderland",
    "sg:classifiers":[
        {
            "category":"Building & Trades",
            "subcategory":"Construction",
            "type":"Services"
        }
    ],
    "sg:phone":"+44 191 565 7379",
    "sg:postcode":"SR4 6XN",
    "sg:province":"Tyne and Wear",
    "sg:tags":[
        "tiling",
        "contractor"
    ],
    "wof:name":"Elegant Tiling",
    "wof:placetype":"venue"
},
  "geometry": {"coordinates":[-1.420821,54.903168],"type":"Point"}
}