{
  "type": "Feature",
  "properties": {
    "iso:country":"GB",
    "sg:address":"94 Dovedale Road",
    "sg:city":"Wolverhampton",
    "sg:classifiers":[
        {
            "category":"Cinema",
            "subcategory":"Movie Rental",
            "type":"Entertainment"
        }
    ],
    "sg:phone":"+44 1902 662515",
    "sg:postcode":"WV4 6RB",
    "sg:province":"Staffordshire",
    "sg:tags":[
        "video",
        "library"
    ],
    "wof:name":"Choice Video",
    "wof:placetype":"venue"
},
  "geometry": {"coordinates":[-2.114251,52.553516],"type":"Point"}
}