{
  "type": "Feature",
  "properties": {
    "addr:full":"Drake House, Drake Avenue Staines Berkshire TW18 2AW",
    "addr:postcode":"tw18 2aw",
    "addr:street":"Drake Avenue",
    "iso:country":"GB",
    "sg:address":"Drake House, Drake Avenue",
    "sg:city":"Staines",
    "sg:classifiers":[
        {
            "category":"Education",
            "subcategory":"Special Training",
            "type":"Public Place"
        }
    ],
    "sg:postcode":"TW18 2AW",
    "sg:province":"Berkshire",
    "sg:tags":[
        "product",
        "centre"
    ],
    "wof:name":"Combinations",
    "wof:placetype":"venue"
},
  "geometry": {"coordinates":[-0.505894,51.431622],"type":"Point"}
}