{
  "type": "Feature",
  "properties": {
    "iso:country":"GB",
    "sg:address":"36 Lennox Street",
    "sg:city":"Weymouth",
    "sg:classifiers":[
        {
            "category":"Travel",
            "subcategory":"Hotels & Motels",
            "type":"Entertainment"
        }
    ],
    "sg:phone":"+44 1305 785903",
    "sg:postcode":"DT4 7HD",
    "sg:province":"Dorset",
    "sg:tags":[
        "house",
        "guest"
    ],
    "wof:name":"Stephen Edward Merrill",
    "wof:placetype":"venue"
},
  "geometry": {"coordinates":[-2.453099966,50.6181411743],"type":"Point"}
}