{
  "type": "Feature",
  "properties": {
    "addr:full":"8 High Street Esher Surrey KT10 9RT",
    "addr:housenumber":"8",
    "addr:postcode":"kt10 9rt",
    "addr:street":"High Street",
    "iso:country":"GB",
    "sg:address":"8 High Street",
    "sg:city":"Esher",
    "sg:classifiers":[
        {
            "category":"Personal",
            "subcategory":"Beauty Salon",
            "type":"Services"
        }
    ],
    "sg:phone":"+44 1372 464240",
    "sg:postcode":"KT10 9RT",
    "sg:province":"Surrey",
    "sg:tags":[
        "unisex",
        "hairdresser"
    ],
    "wof:name":"Elliot Hairdressing",
    "wof:placetype":"venue"
},
  "geometry": {"coordinates":[-0.3632520139,51.3709449768],"type":"Point"}
}