{
  "type": "Feature",
  "properties": {
    "addr:full":"84 Kings Road, North Ormesby Middlesbrough North Yorkshire TS3 6EU",
    "addr:housenumber":"84",
    "addr:postcode":"ts3 6eu",
    "addr:street":"Kings Road",
    "iso:country":"GB",
    "sg:address":"84 Kings Road, North Ormesby",
    "sg:city":"Middlesbrough",
    "sg:classifiers":[
        {
            "category":"Personal",
            "subcategory":"Beauty Salon",
            "type":"Services"
        },
        {
            "category":"Personal",
            "subcategory":"Barber",
            "type":"Services"
        }
    ],
    "sg:phone":"+44 1642 242321",
    "sg:postcode":"TS3 6EU",
    "sg:province":"North Yorkshire",
    "sg:tags":[
        "unisex",
        "hairdresser"
    ],
    "wof:name":"Rapport",
    "wof:placetype":"venue"
},
  "geometry": {"coordinates":[-1.210477,54.568012],"type":"Point"}
}