{
  "type": "Feature",
  "properties": {
    "addr:full":"34 Ledbury Road London Greater London W11 2AB",
    "addr:housenumber":"34",
    "addr:postcode":"w11 2ab",
    "addr:street":"Ledbury Road",
    "iso:country":"GB",
    "sg:address":"34 Ledbury Road",
    "sg:city":"London",
    "sg:classifiers":[
        {
            "category":"Shopping",
            "subcategory":"Antiques",
            "type":"Retail Goods"
        }
    ],
    "sg:phone":"+44 20 7229 6880",
    "sg:postcode":"W11 2AB",
    "sg:province":"Greater London",
    "wof:name":"Cura Antiques",
    "wof:placetype":"venue"
},
  "geometry": {"coordinates":[-0.19871,51.513554],"type":"Point"}
}