{
  "type": "Feature",
  "properties": {
    "addr:full":"203 Two Mile Hill Road Bristol City of Bristol BS15 1AZ",
    "addr:housenumber":"203",
    "addr:postcode":"bs15 1az",
    "addr:street":"Two Mile Hill Road",
    "iso:country":"GB",
    "sg:address":"203 Two Mile Hill Road",
    "sg:city":"Bristol",
    "sg:classifiers":[
        {
            "category":"Manufacturing",
            "subcategory":"Building Materials",
            "type":"Manufacturing & Wholesale Goods"
        }
    ],
    "sg:postcode":"BS15 1AZ",
    "sg:province":"City of Bristol",
    "sg:tags":[
        "merchant",
        "builder"
    ],
    "wof:name":"Fireplaces At Phipps",
    "wof:placetype":"venue"
},
  "geometry": {"coordinates":[-2.514919,51.463234],"type":"Point"}
}