{
  "type": "Feature",
  "properties": {
    "iso:country":"GB",
    "sg:address":"25 Morefields",
    "sg:city":"Tring",
    "sg:classifiers":[
        {
            "category":"Wholesale",
            "subcategory":"Computers",
            "type":"Manufacturing & Wholesale Goods"
        },
        {
            "category":"Professional",
            "subcategory":"Computer Services",
            "type":"Services"
        }
    ],
    "sg:phone":"+44 1442 890782",
    "sg:postcode":"HP23 5EU",
    "sg:province":"Buckinghamshire",
    "sg:tags":[
        "supplier",
        "consultant",
        "consumables"
    ],
    "wof:name":"HARRISON CONSULTING LTD",
    "wof:placetype":"venue"
},
  "geometry": {"coordinates":[-0.660538,51.803673],"type":"Point"}
}