{
  "type": "Feature",
  "properties": {
    "addr:full":"30 Artillery Lane London Greater London E1 7LS",
    "addr:housenumber":"30",
    "addr:postcode":"e1 7ls",
    "addr:street":"Artillery Lane",
    "iso:country":"GB",
    "sg:address":"30 Artillery Lane",
    "sg:city":"London",
    "sg:classifiers":[
        {
            "category":"Government",
            "subcategory":"Office",
            "type":"Public Place"
        }
    ],
    "sg:phone":"+44 20 7377 5077",
    "sg:postcode":"E1 7LS",
    "sg:province":"Greater London",
    "sg:tags":[
        "local"
    ],
    "wof:name":"Human Fertilization & Embryology Authority",
    "wof:placetype":"venue"
},
  "geometry": {"coordinates":[-0.0783350021,51.5183906555],"type":"Point"}
}