{
  "type": "Feature",
  "properties": {
    "addr:full":"479 Mansfield Road Nottingham Nottinghamshire NG1 2JJ",
    "addr:housenumber":"479",
    "addr:postcode":"ng1 2jj",
    "addr:street":"Mansfield Road",
    "iso:country":"GB",
    "sg:address":"479 Mansfield Road",
    "sg:city":"Nottingham",
    "sg:classifiers":[
        {
            "category":"Organizations",
            "subcategory":"Membership Organization",
            "type":"Services"
        }
    ],
    "sg:phone":"+44 115 962 1499",
    "sg:postcode":"NG1 2JJ",
    "sg:province":"Nottinghamshire",
    "sg:tags":[
        "club"
    ],
    "wof:name":"Sherwood Social Club",
    "wof:placetype":"venue"
},
  "geometry": {"coordinates":[-1.1477869749,52.9793167114],"type":"Point"}
}