{
  "type": "Feature",
  "properties": {
    "iso:country":"GB",
    "sg:address":"1 Westbourne Avenue",
    "sg:city":"Cannock",
    "sg:classifiers":[
        {
            "category":"Shopping",
            "subcategory":"Department Store",
            "type":"Retail Goods"
        }
    ],
    "sg:phone":"+44 1543 506683",
    "sg:postcode":"WS11 2AN",
    "sg:province":"Staffordshire",
    "wof:name":"Owen's Off Licence",
    "wof:placetype":"venue"
},
  "geometry": {"coordinates":[-2.033916,52.696728],"type":"Point"}
}