{
  "type": "Feature",
  "properties": {
    "addr:full":"The College, Chesham Road Tring Buckinghamshire HP23 6HH",
    "addr:postcode":"hp23 6hh",
    "addr:street":"Chesham Road",
    "iso:country":"GB",
    "sg:address":"The College, Chesham Road",
    "sg:city":"Tring",
    "sg:classifiers":[
        {
            "category":"Education",
            "subcategory":"College",
            "type":"Public Place"
        }
    ],
    "sg:postcode":"HP23 6HH",
    "sg:province":"Buckinghamshire",
    "sg:tags":[
        "technical",
        "agricultural"
    ],
    "wof:name":"Champneys College",
    "wof:placetype":"venue"
},
  "geometry": {"coordinates":[-0.6417940259,51.7831115723],"type":"Point"}
}