{
  "type": "Feature",
  "properties": {
    "addr:full":"Crow Farm, Crow Ringwood Dorset BH24 3EA",
    "addr:housenumber":"ringwood",
    "addr:postcode":"bh24 3ea",
    "iso:country":"GB",
    "sg:address":"Crow Farm, Crow",
    "sg:city":"Ringwood",
    "sg:classifiers":[
        {
            "category":"Shopping",
            "type":"Retail Goods"
        }
    ],
    "sg:postcode":"BH24 3EA",
    "sg:province":"Dorset",
    "sg:tags":[
        "merchant"
    ],
    "wof:name":"Aivly Country Store",
    "wof:placetype":"venue"
},
  "geometry": {"coordinates":[-1.759059,50.835884],"type":"Point"}
}