{
  "type": "Feature",
  "properties": {
    "addr:full":"134 North Western Av Watford Hertfordshire WD2 6AN",
    "addr:housenumber":"134",
    "addr:postcode":"wd2 6an",
    "addr:street":"North Western Av",
    "iso:country":"GB",
    "sg:address":"134 North Western Av",
    "sg:city":"Watford",
    "sg:classifiers":[
        {
            "category":"Professional",
            "subcategory":"Art Services",
            "type":"Services"
        }
    ],
    "sg:phone":"+44 1923 662371",
    "sg:postcode":"WD2 6AN",
    "sg:province":"Hertfordshire",
    "sg:tags":[
        "graphic",
        "designer"
    ],
    "wof:name":"Eurografix",
    "wof:placetype":"venue"
},
  "geometry": {"coordinates":[-0.4017159939,51.6829681396],"type":"Point"}
}