{
  "type": "Feature",
  "properties": {
    "iso:country":"GB",
    "sg:address":"Unit 1 Oakwood Business Park, I Standard Road Park Royal",
    "sg:city":"London",
    "sg:classifiers":[
        {
            "category":"Professional",
            "subcategory":"Computer Services",
            "type":"Services"
        }
    ],
    "sg:postcode":"NW10 6EX",
    "sg:province":"Greater London",
    "sg:tags":[
        "system",
        "software"
    ],
    "wof:name":"Yushoo Electronics Ltd.",
    "wof:placetype":"venue"
},
  "geometry": {"coordinates":[-0.259718,51.528389],"type":"Point"}
}