{
  "type": "Feature",
  "properties": {
    "iso:country":"GB",
    "sg:address":"37 Well St",
    "sg:city":"Bury St Edmunds",
    "sg:classifiers":[
        {
            "category":"Place Of Worship",
            "type":"Public Place"
        }
    ],
    "sg:phone":"+44 1284 754335",
    "sg:postcode":"IP33 1EQ",
    "sg:province":"Suffolk",
    "wof:name":"St Georges Church",
    "wof:placetype":"venue"
},
  "geometry": {"coordinates":[0.713902,52.246838],"type":"Point"}
}