{
  "type": "Feature",
  "properties": {
    "iso:country":"GB",
    "sg:address":"18 Ratby Road, Groby",
    "sg:city":"Leicester",
    "sg:classifiers":[
        {
            "category":"Fast Food",
            "type":"Food & Drink"
        }
    ],
    "sg:phone":"+44 116 231 3168",
    "sg:postcode":"LE6 0GG",
    "sg:province":"Leicestershire",
    "sg:tags":[
        "away",
        "meal",
        "outlet",
        "take"
    ],
    "wof:name":"Groby Chinese Takeaway",
    "wof:placetype":"venue"
},
  "geometry": {"coordinates":[-1.2271,52.662655],"type":"Point"}
}