{
  "type": "Feature",
  "properties": {
    "addr:full":"252 Norwood Road London Greater London SE27 9AJ",
    "addr:housenumber":"252",
    "addr:postcode":"se27 9aj",
    "addr:street":"Norwood Road",
    "iso:country":"GB",
    "sg:address":"252 Norwood Road",
    "sg:city":"London",
    "sg:classifiers":[
        {
            "category":"Shopping",
            "subcategory":"Clothing, Apparel, & Fashions",
            "type":"Retail Goods"
        }
    ],
    "sg:phone":"+44 20 8670 7188",
    "sg:postcode":"SE27 9AJ",
    "sg:province":"Greater London",
    "sg:tags":[
        "shop"
    ],
    "wof:name":"Olive",
    "wof:placetype":"venue"
},
  "geometry": {"coordinates":[-0.1054859981,51.4374046326],"type":"Point"}
}