{
  "type": "Feature",
  "properties": {
    "addr:full":"Swallowdale Lane, Hemel Hempstead Industrial Estate Hemel Hempstead Hertfordshire HP2 7EW",
    "addr:postcode":"hp2 7ew",
    "addr:street":"Swallowdale Lane;Industrial Estate",
    "iso:country":"GB",
    "sg:address":"Swallowdale Lane, Hemel Hempstead Industrial Estate",
    "sg:city":"Hemel Hempstead",
    "sg:classifiers":[
        {
            "category":"Autos & Motor Vehicles",
            "subcategory":"Auto Supplies",
            "type":"Retail Goods"
        }
    ],
    "sg:phone":"+44 1442 233211",
    "sg:postcode":"HP2 7EW",
    "sg:province":"Hertfordshire",
    "sg:tags":[
        "exhaust",
        "absorber",
        "shock"
    ],
    "wof:name":"Timax Exhaust Systems",
    "wof:placetype":"venue"
},
  "geometry": {"coordinates":[-0.437566,51.769482],"type":"Point"}
}