{
  "type": "Feature",
  "properties": {
    "iso:country":"GB",
    "sg:address":"Holly House, Adelaide Place",
    "sg:city":"Sunderland",
    "sg:classifiers":[
        {
            "category":"Organizations",
            "subcategory":"Community Association",
            "type":"Services"
        }
    ],
    "sg:phone":"+44 191 567 8366",
    "sg:postcode":"SR1 2JW",
    "sg:province":"Tyne and Wear",
    "sg:tags":[
        "society",
        "housing"
    ],
    "wof:name":"Anchor Trust",
    "wof:placetype":"venue"
},
  "geometry": {"coordinates":[-1.3694829941,54.9070777893],"type":"Point"}
}