{
  "type": "Feature",
  "properties": {
    "addr:full":"Unit 3 St Annes Trading Est St Annes Row London Greater London E14 7HN",
    "addr:housenumber":"unit 3",
    "addr:postcode":"e14 7hn",
    "addr:street":"St Annes Trading Est St Annes Row",
    "iso:country":"GB",
    "sg:address":"Unit 3 St Annes Trading Est St Annes Row",
    "sg:city":"London",
    "sg:classifiers":[
        {
            "category":"Shopping",
            "subcategory":"Stationery & Office Supplies",
            "type":"Retail Goods"
        }
    ],
    "sg:postcode":"E14 7HN",
    "sg:province":"Greater London",
    "sg:tags":[
        "printers'"
    ],
    "wof:name":"Wheeler Colour",
    "wof:placetype":"venue"
},
  "geometry": {"coordinates":[-0.02872,51.512939],"type":"Point"}
}