{
  "type": "Feature",
  "properties": {
    "iso:country":"GB",
    "sg:address":"Hortonwood 2",
    "sg:city":"Telford",
    "sg:classifiers":[
        {
            "category":"Wholesale",
            "subcategory":"Groceries",
            "type":"Manufacturing & Wholesale Goods"
        }
    ],
    "sg:phone":"+44 1952 608414",
    "sg:postcode":"TF1 4GW",
    "sg:province":"Shropshire",
    "sg:tags":[
        "food",
        "supplier",
        "drink"
    ],
    "wof:name":"Single Service Ltd",
    "wof:placetype":"venue"
},
  "geometry": {"coordinates":[-2.469529,52.714169],"type":"Point"}
}