{
  "type": "Feature",
  "properties": {
    "iso:country":"GB",
    "sg:address":"8 Priory Gro",
    "sg:city":"London",
    "sg:classifiers":[
        {
            "category":"Professional",
            "subcategory":"Art Services",
            "type":"Services"
        }
    ],
    "sg:postcode":"SW8 2PH",
    "sg:province":"Greater London",
    "sg:tags":[
        "graphic",
        "designer"
    ],
    "wof:name":"Sue Callister Designs",
    "wof:placetype":"venue"
},
  "geometry": {"coordinates":[-0.128513,51.474747],"type":"Point"}
}