{
  "type": "Feature",
  "properties": {
    "iso:country":"GB",
    "sg:address":"Old Tiverton Rd",
    "sg:city":"Crediton",
    "sg:classifiers":[
        {
            "category":"Sports & Exercise",
            "subcategory":"Sports Center",
            "type":"Entertainment"
        }
    ],
    "sg:phone":"+44 1363 774434",
    "sg:postcode":"EX17 1EG",
    "sg:province":"Devon",
    "sg:tags":[
        "game",
        "combat"
    ],
    "wof:name":"Crackshots Exeter",
    "wof:placetype":"venue"
},
  "geometry": {"coordinates":[-3.647119,50.794224],"type":"Point"}
}