{
  "type": "Feature",
  "properties": {
    "addr:full":"25 Robertsbridge Road Carshalton Surrey SM5 1AZ",
    "addr:housenumber":"25",
    "addr:postcode":"sm5 1az",
    "addr:street":"Robertsbridge Road",
    "iso:country":"GB",
    "sg:address":"25 Robertsbridge Road",
    "sg:city":"Carshalton",
    "sg:classifiers":[
        {
            "category":"Building & Trades",
            "subcategory":"Construction",
            "type":"Services"
        }
    ],
    "sg:postcode":"SM5 1AZ",
    "sg:province":"Surrey",
    "sg:tags":[
        "builder"
    ],
    "wof:name":"Rosehill Construction",
    "wof:placetype":"venue"
},
  "geometry": {"coordinates":[-0.1857039928,51.3836288452],"type":"Point"}
}