{
  "type": "Feature",
  "properties": {
    "addr:full":"104 Queens Road, Bishopsworth Bristol City of Bristol BS13 8PQ",
    "addr:housenumber":"104",
    "addr:postcode":"bs13 8pq",
    "addr:street":"Queens Road",
    "iso:country":"GB",
    "sg:address":"104 Queens Road, Bishopsworth",
    "sg:city":"Bristol",
    "sg:classifiers":[
        {
            "category":"Food & Beverages",
            "subcategory":"Supermarket",
            "type":"Retail Goods"
        }
    ],
    "sg:phone":"+44 117 964 0064",
    "sg:postcode":"BS13 8PQ",
    "sg:province":"City of Bristol",
    "wof:name":"Spar",
    "wof:placetype":"venue"
},
  "geometry": {"coordinates":[-2.621239,51.40852],"type":"Point"}
}