{
  "type": "Feature",
  "properties": {
    "addr:full":"Broadway Oldham Lancashire OL9 8DW",
    "addr:postcode":"ol9 8dw",
    "addr:street":"Broadway",
    "iso:country":"GB",
    "sg:address":"Broadway",
    "sg:city":"Oldham",
    "sg:classifiers":[
        {
            "category":"Restaurant",
            "type":"Food & Drink"
        }
    ],
    "sg:phone":"+44 161 681 1373",
    "sg:postcode":"OL9 8DW",
    "sg:province":"Lancashire",
    "wof:name":"The Whitegate Inn Beefeater & Travel Inn",
    "wof:placetype":"venue"
},
  "geometry": {"coordinates":[-2.149724,53.540871],"type":"Point"}
}