{
  "type": "Feature",
  "properties": {
    "addr:full":"Lee Ward Drive, Estaury House, Llanishen Liverpool Merseyside L24 8RE",
    "addr:postcode":"l24 8re",
    "addr:street":"Ward Drive",
    "iso:country":"GB",
    "sg:address":"Lee Ward Drive, Estaury House, Llanishen",
    "sg:city":"Liverpool",
    "sg:classifiers":[
        {
            "category":"Banks & Credit Unions",
            "subcategory":"Financial Services",
            "type":"Services"
        }
    ],
    "sg:phone":"+44 845 300 1531",
    "sg:postcode":"L24 8RE",
    "sg:province":"Merseyside",
    "sg:tags":[
        "consultant"
    ],
    "wof:name":"Forthright Finance Ltd.",
    "wof:placetype":"venue"
},
  "geometry": {"coordinates":[-2.8674900532,53.3488998413],"type":"Point"}
}