{
  "type": "Feature",
  "properties": {
    "addr:full":"8 Southcote Woking Surrey GU21 4QX",
    "addr:housenumber":"8",
    "addr:postcode":"gu21 4qx",
    "addr:street":"Southcote",
    "iso:country":"GB",
    "sg:address":"8 Southcote",
    "sg:city":"Woking",
    "sg:classifiers":[
        {
            "category":"Professional",
            "subcategory":"Engineering",
            "type":"Services"
        }
    ],
    "sg:phone":"+44 1483 755888",
    "sg:postcode":"GU21 4QX",
    "sg:province":"Surrey",
    "sg:tags":[
        "consulting",
        "engineer"
    ],
    "wof:name":"Angel Thompson & Partners",
    "wof:placetype":"venue"
},
  "geometry": {"coordinates":[-0.56684798,51.3259391785],"type":"Point"}
}