{
  "type": "Feature",
  "properties": {
    "iso:country":"GB",
    "sg:address":"Minster Rd",
    "sg:city":"Ripon",
    "sg:classifiers":[
        {
            "category":"Place Of Worship",
            "type":"Public Place"
        }
    ],
    "sg:phone":"+44 1765 603462",
    "sg:postcode":"HG4 1QT",
    "sg:province":"North Yorkshire",
    "wof:name":"Cathedral Church Of St Peter & St Wilfrid",
    "wof:placetype":"venue"
},
  "geometry": {"coordinates":[-1.5199879408,54.1353416443],"type":"Point"}
}