{
  "type": "Feature",
  "properties": {
    "addr:full":"Chancery House York Road, Erdington Birmingham West Midlands B23 6TF",
    "addr:postcode":"b23 6tf",
    "addr:street":"York Road",
    "iso:country":"GB",
    "sg:address":"Chancery House York Road, Erdington",
    "sg:city":"Birmingham",
    "sg:classifiers":[
        {
            "category":"Professional",
            "subcategory":"Business Services",
            "type":"Services"
        }
    ],
    "sg:postcode":"B23 6TF",
    "sg:province":"West Midlands",
    "sg:tags":[
        "import",
        "export",
        "agent"
    ],
    "wof:name":"Trade Products Ltd",
    "wof:placetype":"venue"
},
  "geometry": {"coordinates":[-1.8427890539,52.5239067078],"type":"Point"}
}