{
  "type": "Feature",
  "properties": {
    "iso:country":"GB",
    "sg:address":"209 Thorpe Rd",
    "sg:city":"Melton Mowbray",
    "sg:classifiers":[
        {
            "category":"Retail",
            "subcategory":"Portrait Studio",
            "type":"Services"
        },
        {
            "category":"Shopping",
            "subcategory":"Photographic Equipment",
            "type":"Retail Goods"
        }
    ],
    "sg:phone":"+44 1664 564079",
    "sg:postcode":"LE13 1SH",
    "sg:province":"Leicestershire",
    "sg:tags":[
        "photographer",
        "commercial"
    ],
    "wof:name":"Richard Drewe Photography",
    "wof:placetype":"venue"
},
  "geometry": {"coordinates":[-0.872377,52.769413],"type":"Point"}
}