{
  "type": "Feature",
  "properties": {
    "iso:country":"GB",
    "sg:address":"28 Adderley Street",
    "sg:city":"Birmingham",
    "sg:classifiers":[
        {
            "category":"Bars & Pubs",
            "type":"Food & Drink"
        },
        {
            "category":"Community Center",
            "subcategory":"Social",
            "type":"Public Place"
        }
    ],
    "sg:phone":"+44 121 772 1403",
    "sg:postcode":"B9 4ED",
    "sg:province":"West Midlands",
    "sg:tags":[
        "pubs",
        "house",
        "inn",
        "activity"
    ],
    "wof:name":"THE WAGGON & HORSES",
    "wof:placetype":"venue"
},
  "geometry": {"coordinates":[-1.8795540333,52.4749412537],"type":"Point"}
}