{
  "type": "Feature",
  "properties": {
    "addr:full":"1 Yew Tree Cottage Alresford Hampshire SO24 0PD",
    "addr:housenumber":"1",
    "addr:postcode":"so24 0pd",
    "addr:street":"Yew",
    "iso:country":"GB",
    "sg:address":"1 Yew Tree Cottage",
    "sg:city":"Alresford",
    "sg:classifiers":[
        {
            "category":"Utilities",
            "subcategory":"Fuel Oil & Lpg",
            "type":"Services"
        }
    ],
    "sg:phone":"+44 1962 771716",
    "sg:postcode":"SO24 0PD",
    "sg:province":"Hampshire",
    "sg:tags":[
        "peat",
        "firewood",
        "logs"
    ],
    "wof:name":"R White",
    "wof:placetype":"venue"
},
  "geometry": {"coordinates":[-1.1876699924,51.0199813843],"type":"Point"}
}