{
  "type": "Feature",
  "properties": {
    "addr:full":"Phoenix House, 25a Weston Road Bristol Somerset BS41 9LA",
    "addr:housenumber":"25a",
    "addr:postcode":"bs41 9la",
    "addr:street":"Weston Road",
    "iso:country":"GB",
    "sg:address":"Phoenix House, 25a Weston Road",
    "sg:city":"Bristol",
    "sg:classifiers":[
        {
            "category":"Professional",
            "subcategory":"Engineering",
            "type":"Services"
        }
    ],
    "sg:postcode":"BS41 9LA",
    "sg:province":"Somerset",
    "sg:tags":[
        "consulting",
        "engineer"
    ],
    "wof:name":"R F & A Consultants Ltd.",
    "wof:placetype":"venue"
},
  "geometry": {"coordinates":[-2.664095,51.429127],"type":"Point"}
}