{
  "type": "Feature",
  "properties": {
    "addr:full":"11c Milton Park Abingdon Oxfordshire OX14 4RS",
    "addr:housenumber":"11c",
    "addr:postcode":"ox14 4rs",
    "addr:street":"Milton Park",
    "iso:country":"GB",
    "sg:address":"11c Milton Park",
    "sg:city":"Abingdon",
    "sg:classifiers":[
        {
            "category":"Professional",
            "subcategory":"Computer Services",
            "type":"Services"
        }
    ],
    "sg:postcode":"OX14 4RS",
    "sg:province":"Oxfordshire",
    "sg:tags":[
        "consultant"
    ],
    "wof:name":"Netgenics U K Ltd.",
    "wof:placetype":"venue"
},
  "geometry": {"coordinates":[-1.279976964,51.6332206726],"type":"Point"}
}