{
  "type": "Feature",
  "properties": {
    "iso:country":"GB",
    "sg:address":"3 Monks Walk",
    "sg:city":"Buntingford",
    "sg:classifiers":[
        {
            "category":"Retail",
            "subcategory":"Repair Shop",
            "type":"Services"
        }
    ],
    "sg:phone":"+44 1763 271914",
    "sg:postcode":"SG9 9EE",
    "sg:province":"Hertfordshire",
    "sg:tags":[
        "maintenance"
    ],
    "wof:name":"Layber Services",
    "wof:placetype":"venue"
},
  "geometry": {"coordinates":[-0.025518,51.946682],"type":"Point"}
}