{
  "type": "Feature",
  "properties": {
    "addr:full":"Runnymead Campus, Englefield Grn Egham Surrey TW20 0JZ",
    "addr:postcode":"tw20 0jz",
    "addr:street":"Englefield Grn Egham",
    "iso:country":"GB",
    "sg:address":"Runnymead Campus, Englefield Grn",
    "sg:city":"Egham",
    "sg:classifiers":[
        {
            "category":"Education",
            "subcategory":"University",
            "type":"Public Place"
        }
    ],
    "sg:phone":"+44 1784 432111",
    "sg:postcode":"TW20 0JZ",
    "sg:province":"Surrey",
    "sg:tags":[
        "medical",
        "school"
    ],
    "wof:name":"Brunel University",
    "wof:placetype":"venue"
},
  "geometry": {"coordinates":[-0.5474889874,51.430896759],"type":"Point"}
}