{
  "type": "Feature",
  "properties": {
    "addr:full":"Waverley House, Old Gloucester Road, Hambrook Bristol City of Bristol BS16 1RP",
    "addr:postcode":"bs16 1rp",
    "addr:street":"Old Gloucester Road",
    "iso:country":"GB",
    "sg:address":"Waverley House, Old Gloucester Road, Hambrook",
    "sg:city":"Bristol",
    "sg:classifiers":[
        {
            "category":"Professional",
            "type":"Services"
        }
    ],
    "sg:phone":"+44 117 970 2560",
    "sg:postcode":"BS16 1RP",
    "sg:province":"City of Bristol",
    "sg:tags":[
        "writer"
    ],
    "wof:name":"Arcus International",
    "wof:placetype":"venue"
},
  "geometry": {"coordinates":[-2.5227,51.517639],"type":"Point"}
}