{
  "type": "Feature",
  "properties": {
    "iso:country":"GB",
    "sg:address":"Larkhill Road, Durrington",
    "sg:city":"Salisbury",
    "sg:classifiers":[
        {
            "category":"Autos & Motor Vehicles",
            "subcategory":"Automobile Sales",
            "type":"Retail Goods"
        }
    ],
    "sg:phone":"+44 1980 654999",
    "sg:postcode":"SP4 8DS",
    "sg:province":"Hampshire",
    "sg:tags":[
        "commercial"
    ],
    "wof:name":"P A Reich",
    "wof:placetype":"venue"
},
  "geometry": {"coordinates":[-1.773042,51.202339],"type":"Point"}
}