{
  "type": "Feature",
  "properties": {
    "iso:country":"GB",
    "sg:address":"6 Towngate, Guiseley",
    "sg:city":"Leeds",
    "sg:classifiers":[
        {
            "category":"Personal",
            "subcategory":"Barber",
            "type":"Services"
        }
    ],
    "sg:phone":"+44 1943 879490",
    "sg:postcode":"LS20 9JA",
    "sg:province":"West Yorkshire",
    "sg:tags":[
        "men's",
        "hairdresser"
    ],
    "wof:name":"North Barber Shop",
    "wof:placetype":"venue"
},
  "geometry": {"coordinates":[-1.705655,53.876003],"type":"Point"}
}