{
  "type": "Feature",
  "properties": {
    "addr:full":"Oaks (the), Oak Road Wrexham Wrexham LL13 9RG",
    "addr:postcode":"ll13 9rg",
    "addr:street":"Oak Road",
    "iso:country":"GB",
    "sg:address":"Oaks (the), Oak Road",
    "sg:city":"Wrexham",
    "sg:classifiers":[
        {
            "category":"Building & Trades",
            "subcategory":"Construction",
            "type":"Services"
        }
    ],
    "sg:phone":"+44 1978 661000",
    "sg:postcode":"LL13 9RG",
    "sg:province":"Wrexham",
    "sg:tags":[
        "builder"
    ],
    "wof:name":"North & South Granite",
    "wof:placetype":"venue"
},
  "geometry": {"coordinates":[-2.915790081,53.0391082764],"type":"Point"}
}