{
  "type": "Feature",
  "properties": {
    "addr:full":"6 Easton Street High Wycombe Buckinghamshire HP11 1NJ",
    "addr:housenumber":"6",
    "addr:postcode":"hp11 1nj",
    "addr:street":"Easton Street",
    "iso:country":"GB",
    "sg:address":"6 Easton Street",
    "sg:city":"High Wycombe",
    "sg:classifiers":[
        {
            "category":"Professional",
            "subcategory":"Lawyer & Legal Services",
            "type":"Services"
        }
    ],
    "sg:phone":"+44 1494 450361",
    "sg:postcode":"HP11 1NJ",
    "sg:province":"Buckinghamshire",
    "sg:tags":[
        "conveyancing"
    ],
    "wof:name":"Fendom Dawson & Partners",
    "wof:placetype":"venue"
},
  "geometry": {"coordinates":[-0.7474520206,51.6283302307],"type":"Point"}
}