{
  "type": "Feature",
  "properties": {
    "addr:full":"55 Harley Street London Greater London W1G 8QY",
    "addr:housenumber":"55",
    "addr:postcode":"w1g 8qy",
    "addr:street":"Harley Street",
    "iso:country":"GB",
    "sg:address":"55 Harley Street",
    "sg:city":"London",
    "sg:classifiers":[
        {
            "category":"Health Services",
            "subcategory":"Doctor",
            "type":"Services"
        }
    ],
    "sg:postcode":"W1G 8QY",
    "sg:province":"Greater London",
    "sg:tags":[
        "practitioners"
    ],
    "wof:name":"R Earlam",
    "wof:placetype":"venue"
},
  "geometry": {"coordinates":[-0.14713,51.51894],"type":"Point"}
}