{
  "type": "Feature",
  "properties": {
    "addr:full":"43 Rutland Ave Blackburn Lancashire BB1 2DF",
    "addr:housenumber":"43",
    "addr:postcode":"bb1 2df",
    "addr:street":"Rutland Ave",
    "iso:country":"GB",
    "sg:address":"43 Rutland Ave",
    "sg:city":"Blackburn",
    "sg:classifiers":[
        {
            "category":"Personal",
            "type":"Services"
        }
    ],
    "sg:postcode":"BB1 2DF",
    "sg:province":"Lancashire",
    "sg:tags":[
        "wedding"
    ],
    "wof:name":"Lord,R,",
    "wof:placetype":"venue"
},
  "geometry": {"coordinates":[-2.440387,53.745281],"type":"Point"}
}