{
  "type": "Feature",
  "properties": {
    "addr:full":"8 Orchard Gardens Wrexham Wrexham LL11 2RS",
    "addr:housenumber":"8",
    "addr:postcode":"ll11 2rs",
    "addr:street":"Orchard Gardens",
    "iso:country":"GB",
    "sg:address":"8 Orchard Gardens",
    "sg:city":"Wrexham",
    "sg:classifiers":[
        {
            "category":"Professional",
            "subcategory":"Management & Consulting",
            "type":"Services"
        }
    ],
    "sg:phone":"+44 1978 354520",
    "sg:postcode":"LL11 2RS",
    "sg:province":"Wrexham",
    "sg:tags":[
        "consultant",
        "geophysical",
        "geological"
    ],
    "wof:name":"R Lumley",
    "wof:placetype":"venue"
},
  "geometry": {"coordinates":[-2.9941160679,53.0622673035],"type":"Point"}
}