{
  "type": "Feature",
  "properties": {
    "addr:full":"53 Dells Lane Biggleswade Bedfordshire SG18 8LJ",
    "addr:housenumber":"53",
    "addr:postcode":"sg18 8lj",
    "addr:street":"Dells Lane",
    "iso:country":"GB",
    "sg:address":"53 Dells Lane",
    "sg:city":"Biggleswade",
    "sg:classifiers":[
        {
            "category":"Health Services",
            "subcategory":"Dentist",
            "type":"Services"
        }
    ],
    "sg:phone":"+44 1767 317477",
    "sg:postcode":"SG18 8LJ",
    "sg:province":"Bedfordshire",
    "sg:tags":[
        "technician",
        "dental"
    ],
    "wof:name":"John Carrick",
    "wof:placetype":"venue"
},
  "geometry": {"coordinates":[-0.257355988,52.0836105347],"type":"Point"}
}