{
  "type": "Feature",
  "properties": {
    "addr:full":"3 Matthews La Manchester Greater Manchester M12 4QW",
    "addr:housenumber":"3",
    "addr:postcode":"m12 4qw",
    "addr:street":"Matthews La Manchester",
    "iso:country":"GB",
    "sg:address":"3 Matthews La",
    "sg:city":"Manchester",
    "sg:classifiers":[
        {
            "category":"Retail",
            "subcategory":"Auto Repair",
            "type":"Services"
        }
    ],
    "sg:phone":"+44 161 248 5600",
    "sg:postcode":"M12 4QW",
    "sg:province":"Greater Manchester",
    "sg:tags":[
        "modification",
        "garage"
    ],
    "wof:name":"Midway Garage",
    "wof:placetype":"venue"
},
  "geometry": {"coordinates":[-2.1909160614,53.4491577148],"type":"Point"}
}