{
  "type": "Feature",
  "properties": {
    "addr:full":"24 Deer Park Rd Wimbledon Greater London SW19 3UF",
    "addr:housenumber":"24",
    "addr:postcode":"sw19 3uf",
    "addr:street":"Deer Park Rd",
    "iso:country":"GB",
    "sg:address":"24 Deer Park Rd",
    "sg:city":"Wimbledon",
    "sg:classifiers":[
        {
            "category":"Utilities",
            "subcategory":"Natural Gas",
            "type":"Services"
        }
    ],
    "sg:phone":"+44 20 8542 6677",
    "sg:postcode":"SW19 3UF",
    "sg:province":"Greater London",
    "sg:tags":[
        "supplier",
        "industrial"
    ],
    "wof:name":"BOC Gases",
    "wof:placetype":"venue"
},
  "geometry": {"coordinates":[-0.1915269941,51.408416748],"type":"Point"}
}