{
  "type": "Feature",
  "properties": {
    "addr:full":"26 Purbeck Drive, West Bridgford Nottingham Nottinghamshire NG2 7UA",
    "addr:housenumber":"26",
    "addr:postcode":"ng2 7ua",
    "addr:street":"Purbeck Drive",
    "iso:country":"GB",
    "sg:address":"26 Purbeck Drive, West Bridgford",
    "sg:city":"Nottingham",
    "sg:classifiers":[
        {
            "category":"Professional",
            "subcategory":"Art Services",
            "type":"Services"
        }
    ],
    "sg:phone":"+44 115 982 5895",
    "sg:postcode":"NG2 7UA",
    "sg:province":"Nottinghamshire",
    "sg:tags":[
        "photographer"
    ],
    "wof:name":"Creative Images",
    "wof:placetype":"venue"
},
  "geometry": {"coordinates":[-1.1522099972,52.9210624695],"type":"Point"}
}