{
  "type": "Feature",
  "properties": {
    "iso:country":"GB",
    "sg:address":"Beckfield Lane, Acomb",
    "sg:city":"York",
    "sg:classifiers":[
        {
            "category":"Building & Trades",
            "subcategory":"Construction",
            "type":"Services"
        }
    ],
    "sg:postcode":"YO26 5QS",
    "sg:province":"North Yorkshire",
    "sg:tags":[
        "tiling",
        "contractor"
    ],
    "wof:name":"Acomb Tilers",
    "wof:placetype":"venue"
},
  "geometry": {"coordinates":[-1.13373,53.96907],"type":"Point"}
}