{
  "type": "Feature",
  "properties": {
    "addr:full":"45 Claters Clo Retford Nottinghamshire DN22 6QE",
    "addr:housenumber":"45",
    "addr:postcode":"dn22 6qe",
    "addr:street":"Claters Clo",
    "iso:country":"GB",
    "sg:address":"45 Claters Clo",
    "sg:city":"Retford",
    "sg:classifiers":[
        {
            "category":"Building & Trades",
            "subcategory":"Landscaping Services",
            "type":"Services"
        }
    ],
    "sg:postcode":"DN22 6QE",
    "sg:province":"Nottinghamshire",
    "sg:tags":[
        "gardening"
    ],
    "wof:name":"Jack's Gardening Service",
    "wof:placetype":"venue"
},
  "geometry": {"coordinates":[-0.930554986,53.3257102966],"type":"Point"}
}