{
  "type": "Feature",
  "properties": {
    "addr:full":"59 Thornhill Road Sutton Coldfield Staffordshire B74 3EN",
    "addr:housenumber":"59",
    "addr:postcode":"b74 3en",
    "addr:street":"Thornhill Road",
    "iso:country":"GB",
    "sg:address":"59 Thornhill Road",
    "sg:city":"Sutton Coldfield",
    "sg:classifiers":[
        {
            "category":"Banks & Credit Unions",
            "subcategory":"Financial Services",
            "type":"Services"
        }
    ],
    "sg:phone":"+44 121 353 4856",
    "sg:postcode":"B74 3EN",
    "sg:province":"Staffordshire",
    "sg:tags":[
        "adviser",
        "independent"
    ],
    "wof:name":"Hunter & Co",
    "wof:placetype":"venue"
},
  "geometry": {"coordinates":[-1.8724420071,52.5852050781],"type":"Point"}
}