{
  "type": "Feature",
  "properties": {
    "addr:full":"239 Chase Side Enfield Greater London EN2 0RA",
    "addr:housenumber":"239",
    "addr:postcode":"en2 0ra",
    "addr:street":"Chase",
    "iso:country":"GB",
    "sg:address":"239 Chase Side",
    "sg:city":"Enfield",
    "sg:classifiers":[
        {
            "category":"Communications",
            "type":"Services"
        }
    ],
    "sg:postcode":"EN2 0RA",
    "sg:province":"Greater London",
    "sg:tags":[
        "data",
        "network"
    ],
    "wof:name":"Opus Data Services Ltd",
    "wof:placetype":"venue"
},
  "geometry": {"coordinates":[-0.086276,51.66357],"type":"Point"}
}