{
  "type": "Feature",
  "properties": {
    "iso:country":"GB",
    "sg:address":"Pantygenau, Sarnau",
    "sg:city":"Llandysul",
    "sg:classifiers":[
        {
            "category":"Farming",
            "subcategory":"Livestock Farm",
            "type":"Manufacturing & Wholesale Goods"
        }
    ],
    "sg:phone":"+44 1239 810261",
    "sg:postcode":"SA44 6RA",
    "sg:province":"Carmarthenshire",
    "sg:tags":[
        "others"
    ],
    "wof:name":"A & Y D Reed",
    "wof:placetype":"venue"
},
  "geometry": {"coordinates":[-4.463222,52.131851],"type":"Point"}
}