{
  "type": "Feature",
  "properties": {
    "addr:full":"44 Walham Gro London Greater London SW6 1QR",
    "addr:housenumber":"44",
    "addr:postcode":"sw6 1qr",
    "addr:street":"Walham Gro",
    "iso:country":"GB",
    "sg:address":"44 Walham Gro",
    "sg:city":"London",
    "sg:classifiers":[
        {
            "category":"Professional",
            "subcategory":"Management & Consulting",
            "type":"Services"
        }
    ],
    "sg:phone":"+44 20 7386 7077",
    "sg:postcode":"SW6 1QR",
    "sg:province":"Greater London",
    "sg:tags":[
        "marketing",
        "consultant"
    ],
    "wof:name":"The Black Dahlia Co. Ltd.",
    "wof:placetype":"venue"
},
  "geometry": {"coordinates":[-0.196142,51.483086],"type":"Point"}
}