{
  "type": "Feature",
  "properties": {
    "addr:full":"242 Southchurch Drive Nottingham Nottinghamshire NG11 8AA",
    "addr:housenumber":"242",
    "addr:postcode":"ng11 8aa",
    "addr:street":"Southchurch Drive",
    "iso:country":"GB",
    "sg:address":"242 Southchurch Drive",
    "sg:city":"Nottingham",
    "sg:classifiers":[
        {
            "category":"Taxi",
            "type":"Transportation"
        },
        {
            "category":"Military Area",
            "subcategory":"Air Force Base",
            "type":"Public Place"
        }
    ],
    "sg:phone":"+44 115 914 1414",
    "sg:postcode":"NG11 8AA",
    "sg:province":"Nottinghamshire",
    "sg:tags":[
        "hire",
        "private"
    ],
    "wof:name":"Southside Cars",
    "wof:placetype":"venue"
},
  "geometry": {"coordinates":[-1.1778919697,52.9027862549],"type":"Point"}
}