{
  "type": "Feature",
  "properties": {
    "iso:country":"GB",
    "sg:address":"Unit 5, 3 Park Lane",
    "sg:city":"Halesowen",
    "sg:classifiers":[
        {
            "category":"Manufacturing",
            "subcategory":"Wood Products",
            "type":"Manufacturing & Wholesale Goods"
        },
        {
            "category":"Home & Garden",
            "subcategory":"Building Materials",
            "type":"Retail Goods"
        }
    ],
    "sg:phone":"+44 1384 569791",
    "sg:postcode":"B63 2NT",
    "sg:province":"West Midlands",
    "sg:tags":[
        "pallet",
        "crate",
        "packaging",
        "packing",
        "pallets",
        "supplier"
    ],
    "sg:website":"http://www.paltech.co.uk",
    "wof:name":"Paltech",
    "wof:placetype":"venue"
},
  "geometry": {"coordinates":[-2.087999,52.459888],"type":"Point"}
}