{
  "type": "Feature",
  "properties": {
    "addr:full":"98 Upper Tooting Road London Greater London SW17 7EN",
    "addr:housenumber":"98",
    "addr:postcode":"sw17 7en",
    "addr:street":"Upper Tooting Road",
    "iso:country":"GB",
    "sg:address":"98 Upper Tooting Road",
    "sg:city":"London",
    "sg:classifiers":[
        {
            "category":"Food & Beverages",
            "subcategory":"Candy",
            "type":"Retail Goods"
        }
    ],
    "sg:postcode":"SW17 7EN",
    "sg:province":"Greater London",
    "sg:tags":[
        "confectioner"
    ],
    "wof:name":"Alauddin Sweetmeat (U K) Ltd.",
    "wof:placetype":"venue"
},
  "geometry": {"coordinates":[-0.1633339971,51.433265686],"type":"Point"}
}