{
  "type": "Feature",
  "properties": {
    "addr:full":"Cloisters, The Abbey, Preston Road Yeovil Somerset BA20 2EZ",
    "addr:postcode":"ba20 2ez",
    "addr:street":"Preston Road",
    "iso:country":"GB",
    "sg:address":"Cloisters, The Abbey, Preston Road",
    "sg:city":"Yeovil",
    "sg:classifiers":[
        {
            "category":"Real Estate",
            "subcategory":"Surveying",
            "type":"Services"
        }
    ],
    "sg:phone":"+44 1935 472000",
    "sg:postcode":"BA20 2EZ",
    "sg:province":"Somerset",
    "sg:tags":[
        "surveyor",
        "valuer"
    ],
    "wof:name":"A S A Commercial Property Surveyors",
    "wof:placetype":"venue"
},
  "geometry": {"coordinates":[-2.6628699303,50.9434700012],"type":"Point"}
}