{
  "type": "Feature",
  "properties": {
    "iso:country":"GB",
    "sg:address":"117 Abbey St",
    "sg:city":"Nuneaton",
    "sg:classifiers":[
        {
            "category":"Restaurant",
            "type":"Food & Drink"
        }
    ],
    "sg:phone":"+44 24 7664 2038",
    "sg:postcode":"CV11 5BX",
    "sg:province":"Leicestershire",
    "sg:tags":[
        "indian"
    ],
    "wof:name":"Noor Tandoori Restaurant",
    "wof:placetype":"venue"
},
  "geometry": {"coordinates":[-1.471239,52.524101],"type":"Point"}
}