{
  "type": "Feature",
  "properties": {
    "iso:country":"GB",
    "sg:address":"Foxwood House, Dobbs Lane",
    "sg:city":"Ipswich",
    "sg:classifiers":[
        {
            "category":"Professional",
            "subcategory":"Computer Services",
            "type":"Services"
        }
    ],
    "sg:postcode":"IP5 2QQ",
    "sg:province":"Suffolk",
    "sg:tags":[
        "system",
        "software"
    ],
    "wof:name":"Cib Group Ltd.",
    "wof:placetype":"venue"
},
  "geometry": {"coordinates":[1.260365,52.06612],"type":"Point"}
}