{
  "type": "Feature",
  "properties": {
    "iso:country":"GB",
    "sg:address":"9 Hazeldine House, Central Square, Town Centre",
    "sg:city":"Telford",
    "sg:classifiers":[
        {
            "category":"Professional",
            "subcategory":"Employment Agencies",
            "type":"Services"
        }
    ],
    "sg:phone":"+44 1952 292600",
    "sg:postcode":"TF3 4JL",
    "sg:province":"Shropshire",
    "sg:tags":[
        "consultant"
    ],
    "wof:name":"Blue Arrow Personnel Services",
    "wof:placetype":"venue"
},
  "geometry": {"coordinates":[-2.44176507,52.6766624451],"type":"Point"}
}