{
  "type": "Feature",
  "properties": {
    "iso:country":"GB",
    "sg:address":"Harrops Croft",
    "sg:city":"Bootle",
    "sg:classifiers":[
        {
            "category":"Social Services",
            "subcategory":"Retirement Home",
            "type":"Services"
        }
    ],
    "sg:postcode":"L30 0QP",
    "sg:province":"Merseyside",
    "sg:tags":[
        "residential",
        "care"
    ],
    "wof:name":"James Dixon Court",
    "wof:placetype":"venue"
},
  "geometry": {"coordinates":[-2.97919,53.492447],"type":"Point"}
}