{
  "type": "Feature",
  "properties": {
    "addr:full":"Mortomley House, Mortomley Lane, High Grn Sheffield South Yorkshire S35 3HR",
    "addr:postcode":"s35 3hr",
    "addr:street":"Mortomley Lane High Grn",
    "iso:country":"GB",
    "sg:address":"Mortomley House, Mortomley Lane, High Grn",
    "sg:city":"Sheffield",
    "sg:classifiers":[
        {
            "category":"Social Services",
            "subcategory":"Retirement Home",
            "type":"Services"
        }
    ],
    "sg:postcode":"S35 3HR",
    "sg:province":"South Yorkshire",
    "sg:tags":[
        "residential",
        "care"
    ],
    "wof:name":"Mortomley",
    "wof:placetype":"venue"
},
  "geometry": {"coordinates":[-1.480839,53.470341],"type":"Point"}
}