{
  "type": "Feature",
  "properties": {
    "addr:full":"Mathon Court, West Malvern Road Malvern Gloucestershire WR13 5NZ",
    "addr:postcode":"wr13 5nz",
    "addr:street":"Mathon Court West Malvern Road",
    "iso:country":"GB",
    "sg:address":"Mathon Court, West Malvern Road",
    "sg:city":"Malvern",
    "sg:classifiers":[
        {
            "category":"Manufacturing",
            "subcategory":"Metals",
            "type":"Manufacturing & Wholesale Goods"
        }
    ],
    "sg:phone":"+44 1684 892550",
    "sg:postcode":"WR13 5NZ",
    "sg:province":"Gloucestershire",
    "sg:tags":[
        "ore"
    ],
    "wof:name":"Greenwich Resources Plc",
    "wof:placetype":"venue"
},
  "geometry": {"coordinates":[-2.361822,52.099724],"type":"Point"}
}