{
  "type": "Feature",
  "properties": {
    "addr:full":"6th Floor Quadrant Ho, Church St Dunstable Bedfordshire LU5 4RP",
    "addr:housenumber":"6th floor;ho",
    "addr:postcode":"lu5 4rp",
    "addr:street":"Quadrant;St",
    "iso:country":"GB",
    "sg:address":"6th Floor Quadrant Ho, Church St",
    "sg:city":"Dunstable",
    "sg:classifiers":[
        {
            "category":"Wholesale",
            "subcategory":"Books, Periodicals, & Newspapers",
            "type":"Manufacturing & Wholesale Goods"
        }
    ],
    "sg:phone":"+44 1582 605721",
    "sg:postcode":"LU5 4RP",
    "sg:province":"Bedfordshire",
    "sg:tags":[
        "maps",
        "globe",
        "chart",
        "pub"
    ],
    "wof:name":"Ordnance Survey",
    "wof:placetype":"venue"
},
  "geometry": {"coordinates":[-0.5188699961,51.8871116638],"type":"Point"}
}