{
  "type": "Feature",
  "properties": {
    "iso:country":"GB",
    "sg:address":"108 Marmion Road",
    "sg:city":"Southsea",
    "sg:classifiers":[
        {
            "category":"Professional",
            "subcategory":"Printing & Photocopies",
            "type":"Services"
        }
    ],
    "sg:phone":"+44 23 9282 1451",
    "sg:postcode":"PO5 2BB",
    "sg:province":"Hampshire",
    "sg:tags":[
        "printer"
    ],
    "wof:name":"Printcraft",
    "wof:placetype":"venue"
},
  "geometry": {"coordinates":[-1.083624959,50.7851371765],"type":"Point"}
}