{
  "type": "Feature",
  "properties": {
    "addr:full":"31 Riverside Gardens Enfield Greater London EN2 6JW",
    "addr:housenumber":"31",
    "addr:postcode":"en2 6jw",
    "addr:street":"Riverside Gardens",
    "iso:country":"GB",
    "sg:address":"31 Riverside Gardens",
    "sg:city":"Enfield",
    "sg:classifiers":[
        {
            "category":"Building & Trades",
            "subcategory":"Construction",
            "type":"Services"
        }
    ],
    "sg:postcode":"EN2 6JW",
    "sg:province":"Greater London",
    "sg:tags":[
        "joiner",
        "carpenter"
    ],
    "wof:name":"Stratton Joinery",
    "wof:placetype":"venue"
},
  "geometry": {"coordinates":[-0.085023,51.657925],"type":"Point"}
}