{
  "type": "Feature",
  "properties": {
    "iso:country":"GB",
    "sg:address":"159 Dyke Road",
    "sg:city":"Hove",
    "sg:classifiers":[
        {
            "category":"Deli",
            "type":"Food & Drink"
        }
    ],
    "sg:postcode":"BN3 1TJ",
    "sg:province":"East Sussex",
    "sg:tags":[
        "delicatessen"
    ],
    "wof:name":"Le Gourmet",
    "wof:placetype":"venue"
},
  "geometry": {"coordinates":[-0.148128,50.831741],"type":"Point"}
}