{
  "type": "Feature",
  "properties": {
    "addr:full":"Unit 8 Accrington Lancashire BB5 0RJ",
    "addr:housenumber":"unit 8",
    "addr:postcode":"bb5 0rj",
    "iso:country":"GB",
    "sg:address":"Unit 8",
    "sg:city":"Accrington",
    "sg:classifiers":[
        {
            "category":"Wholesale",
            "subcategory":"Meat",
            "type":"Manufacturing & Wholesale Goods"
        },
        {
            "category":"Deli",
            "type":"Food & Drink"
        }
    ],
    "sg:phone":"+44 1254 391861",
    "sg:postcode":"BB5 0RJ",
    "sg:province":"Lancashire",
    "sg:tags":[
        "wholesaler",
        "delicatessen"
    ],
    "wof:name":"Fresh Fayre",
    "wof:placetype":"venue"
},
  "geometry": {"coordinates":[-2.3706440926,53.7553291321],"type":"Point"}
}