{
  "type": "Feature",
  "properties": {
    "iso:country":"GB",
    "sg:address":"32 Hough Grn",
    "sg:city":"Chester",
    "sg:classifiers":[
        {
            "category":"Farming",
            "subcategory":"Nursery",
            "type":"Manufacturing & Wholesale Goods"
        }
    ],
    "sg:phone":"+44 1244 674473",
    "sg:postcode":"CH4 8JQ",
    "sg:province":"Cheshire",
    "sg:tags":[
        "creche"
    ],
    "wof:name":"Hough Green Pre-School Nursery",
    "wof:placetype":"venue"
},
  "geometry": {"coordinates":[-2.903086,53.179474],"type":"Point"}
}