{
  "type": "Feature",
  "properties": {
    "addr:full":"278-280 London Road Westcliff On Sea Essex SS0 7JG",
    "addr:housenumber":"278-280",
    "addr:postcode":"ss0 7jg",
    "addr:street":"London Road",
    "iso:country":"GB",
    "sg:address":"278-280 London Road",
    "sg:city":"Westcliff On Sea",
    "sg:classifiers":[
        {
            "category":"Professional",
            "subcategory":"Lawyer & Legal Services",
            "type":"Services"
        }
    ],
    "sg:phone":"+44 1702 301202",
    "sg:postcode":"SS0 7JG",
    "sg:province":"Essex",
    "wof:name":"Prestige Wills & Estates",
    "wof:placetype":"venue"
},
  "geometry": {"coordinates":[0.699318,51.540478],"type":"Point"}
}