{
  "type": "Feature",
  "properties": {
    "addr:full":"Lower Hutcherleigh, Blackawton Totnes Devon TQ9 7AD",
    "addr:postcode":"tq9 7ad",
    "addr:street":"Blackawton",
    "iso:country":"GB",
    "sg:address":"Lower Hutcherleigh, Blackawton",
    "sg:city":"Totnes",
    "sg:classifiers":[
        {
            "category":"Wholesale",
            "subcategory":"Metals & Minerals",
            "type":"Manufacturing & Wholesale Goods"
        }
    ],
    "sg:phone":"+44 1548 521404",
    "sg:postcode":"TQ9 7AD",
    "sg:province":"Devon",
    "sg:tags":[
        "merchant"
    ],
    "wof:name":"Agriwise",
    "wof:placetype":"venue"
},
  "geometry": {"coordinates":[-3.6811139584,50.3460159302],"type":"Point"}
}