{
  "type": "Feature",
  "properties": {
    "addr:full":"6 Hurstwood Avenue Bexley Kent DA5 3PH",
    "addr:housenumber":"6",
    "addr:postcode":"da5 3ph",
    "addr:street":"Hurstwood Avenue",
    "iso:country":"GB",
    "sg:address":"6 Hurstwood Avenue",
    "sg:city":"Bexley",
    "sg:classifiers":[
        {
            "category":"Building & Trades",
            "subcategory":"Construction",
            "type":"Services"
        }
    ],
    "sg:postcode":"DA5 3PH",
    "sg:province":"Kent",
    "sg:tags":[
        "supplier",
        "installers",
        "cladding"
    ],
    "wof:name":"Regal Design Systems",
    "wof:placetype":"venue"
},
  "geometry": {"coordinates":[0.1315380037,51.4389076233],"type":"Point"}
}