{
  "type": "Feature",
  "properties": {
    "iso:country":"GB",
    "sg:address":"Grawen Street",
    "sg:city":"Porth",
    "sg:classifiers":[
        {
            "category":"Government",
            "subcategory":"Office",
            "type":"Public Place"
        }
    ],
    "sg:phone":"+44 1442 744000",
    "sg:postcode":"CF39 0BU",
    "sg:province":"Bridgend",
    "sg:tags":[
        "local",
        "agency",
        "education",
        "authority"
    ],
    "wof:name":"The Education Centre",
    "wof:placetype":"venue"
},
  "geometry": {"coordinates":[-3.414909,51.61586],"type":"Point"}
}