{
  "type": "Feature",
  "properties": {
    "addr:full":"1-2 Junction Mews London Greater London W2 1PN",
    "addr:housenumber":"1-2",
    "addr:postcode":"w2 1pn",
    "addr:street":"Junction Mews",
    "iso:country":"GB",
    "sg:address":"1-2 Junction Mews",
    "sg:city":"London",
    "sg:classifiers":[
        {
            "category":"Organizations",
            "subcategory":"Non-profit Organization",
            "type":"Services"
        }
    ],
    "sg:phone":"+44 20 7706 4232",
    "sg:postcode":"W2 1PN",
    "sg:province":"Greater London",
    "sg:tags":[
        "organisation",
        "voluntary",
        "charity"
    ],
    "wof:name":"Changing Faces",
    "wof:placetype":"venue"
},
  "geometry": {"coordinates":[-0.169125,51.5177],"type":"Point"}
}