{
  "type": "Feature",
  "properties": {
    "addr:full":"12 Spring Head Wednesbury West Midlands WS10 9AD",
    "addr:housenumber":"12",
    "addr:postcode":"ws10 9ad",
    "addr:street":"Spring Head Wednesbury West",
    "iso:country":"GB",
    "sg:address":"12 Spring Head",
    "sg:city":"Wednesbury",
    "sg:classifiers":[
        {
            "category":"Professional",
            "subcategory":"Lawyer & Legal Services",
            "type":"Services"
        }
    ],
    "sg:phone":"+44 121 556 0040",
    "sg:postcode":"WS10 9AD",
    "sg:province":"West Midlands",
    "sg:tags":[
        "solicitor"
    ],
    "wof:name":"Sydney W Smith & Co.",
    "wof:placetype":"venue"
},
  "geometry": {"coordinates":[-2.0172240734,52.55286026],"type":"Point"}
}