{
  "type": "Feature",
  "properties": {
    "iso:country":"GB",
    "sg:address":"Etrona Buildings, 174 Granville Road",
    "sg:city":"London",
    "sg:classifiers":[
        {
            "category":"Cafe",
            "type":"Food & Drink"
        },
        {
            "category":"Professional",
            "subcategory":"Business Services",
            "type":"Services"
        }
    ],
    "sg:phone":"+44 20 8458 0441",
    "sg:postcode":"NW2 2LP",
    "sg:province":"Greater London",
    "sg:tags":[
        "tea",
        "export",
        "room",
        "agent",
        "import"
    ],
    "wof:name":"Ivax Ltd.",
    "wof:placetype":"venue"
},
  "geometry": {"coordinates":[-0.2021300048,51.5609016418],"type":"Point"}
}