{
  "type": "Feature",
  "properties": {
    "iso:country":"GB",
    "sg:address":"27 Milton Rd",
    "sg:city":"Cambridge",
    "sg:classifiers":[
        {
            "category":"Health Services",
            "subcategory":"Dentist",
            "type":"Services"
        }
    ],
    "sg:phone":"+44 1223 312345",
    "sg:postcode":"CB4 1UZ",
    "sg:province":"Cambridgeshire",
    "wof:name":"D R Vincent & Associates",
    "wof:placetype":"venue"
},
  "geometry": {"coordinates":[0.125708,52.215904],"type":"Point"}
}