{
  "type": "Feature",
  "properties": {
    "iso:country":"GB",
    "sg:address":"195 Wakefield Road, Scissett",
    "sg:city":"Huddersfield",
    "sg:classifiers":[
        {
            "category":"Home & Garden",
            "subcategory":"Furniture",
            "type":"Retail Goods"
        }
    ],
    "sg:phone":"+44 1484 865042",
    "sg:postcode":"HD8 9JL",
    "sg:province":"South Yorkshire",
    "sg:tags":[
        "outlet"
    ],
    "wof:name":"Portman Furnitures Ltd",
    "wof:placetype":"venue"
},
  "geometry": {"coordinates":[-1.6289069653,53.5867576599],"type":"Point"}
}