{
  "type": "Feature",
  "properties": {
    "addr:full":"Brynyrmor Road, Gowerton Swansea Carmarthenshire SA4 3AQ",
    "addr:postcode":"sa4 3aq",
    "addr:street":"Brynyrmor Road",
    "iso:country":"GB",
    "sg:address":"Brynyrmor Road, Gowerton",
    "sg:city":"Swansea",
    "sg:classifiers":[
        {
            "category":"Autos & Motor Vehicles",
            "subcategory":"Fuel & Gas Station",
            "type":"Retail Goods"
        }
    ],
    "sg:phone":"+44 1792 873837",
    "sg:postcode":"SA4 3AQ",
    "sg:province":"Carmarthenshire",
    "sg:tags":[
        "hr",
        "petrol"
    ],
    "wof:name":"Gowerton Service Station",
    "wof:placetype":"venue"
},
  "geometry": {"coordinates":[-4.0588722229,51.6500167847],"type":"Point"}
}