{
  "type": "Feature",
  "properties": {
    "addr:full":"Chapel Street Leigh Lancashire WN7 2DA",
    "addr:postcode":"wn7 2da",
    "addr:street":"Chapel Street Leigh",
    "iso:country":"GB",
    "sg:address":"Chapel Street",
    "sg:city":"Leigh",
    "sg:classifiers":[
        {
            "category":"Sports & Exercise",
            "subcategory":"Gym",
            "type":"Entertainment"
        }
    ],
    "sg:postcode":"WN7 2DA",
    "sg:province":"Lancashire",
    "sg:tags":[
        "fitness",
        "health",
        "centre"
    ],
    "wof:name":"Fit for Life Health Studios",
    "wof:placetype":"venue"
},
  "geometry": {"coordinates":[-2.510709,53.49538],"type":"Point"}
}