{
  "type": "Feature",
  "properties": {
    "addr:full":"38 Tressider Ho, Poynders Rd Clapham Greater London SW4 8PU",
    "addr:housenumber":"38",
    "addr:postcode":"sw4 8pu",
    "addr:street":"Tressider Ho Poynders Rd",
    "iso:country":"GB",
    "sg:address":"38 Tressider Ho, Poynders Rd",
    "sg:city":"Clapham",
    "sg:classifiers":[
        {
            "category":"Real Estate",
            "subcategory":"Architect",
            "type":"Services"
        }
    ],
    "sg:phone":"+44 20 8678 7296",
    "sg:postcode":"SW4 8PU",
    "sg:province":"Greater London",
    "wof:name":"Community Building Support",
    "wof:placetype":"venue"
},
  "geometry": {"coordinates":[-0.13439,51.4482],"type":"Point"}
}