{
  "type": "Feature",
  "properties": {
    "iso:country":"GB",
    "sg:address":"Printing Office St",
    "sg:city":"Doncaster",
    "sg:classifiers":[
        {
            "category":"Travel",
            "subcategory":"Travel Agent",
            "type":"Entertainment"
        }
    ],
    "sg:phone":"+44 1302 364703",
    "sg:postcode":"DN1 1TR",
    "sg:province":"South Yorkshire",
    "wof:name":"Co-op Travelcare",
    "wof:placetype":"venue"
},
  "geometry": {"coordinates":[-1.135559,53.52227],"type":"Point"}
}