{
  "type": "Feature",
  "properties": {
    "addr:full":"351 Mare Street London Greater London E8 1JB",
    "addr:housenumber":"351",
    "addr:postcode":"e8 1jb",
    "addr:street":"Mare Street",
    "iso:country":"GB",
    "sg:address":"351 Mare Street",
    "sg:city":"London",
    "sg:classifiers":[
        {
            "category":"Shopping",
            "subcategory":"Department Store",
            "type":"Retail Goods"
        }
    ],
    "sg:phone":"+44 20 8986 3821",
    "sg:postcode":"E8 1JB",
    "sg:province":"Greater London",
    "wof:name":"Marks & Spencer Plc",
    "wof:placetype":"venue"
},
  "geometry": {"coordinates":[-0.0550590008,51.5471115112],"type":"Point"}
}