{
  "type": "Feature",
  "properties": {
    "iso:country":"GB",
    "sg:address":"Grange Farm, Bishop Wilton",
    "sg:city":"York",
    "sg:classifiers":[
        {
            "category":"Travel",
            "subcategory":"Hotels & Motels",
            "type":"Entertainment"
        },
        {
            "category":"Farming",
            "subcategory":"Livestock Farm",
            "type":"Manufacturing & Wholesale Goods"
        }
    ],
    "sg:phone":"+44 1759 368400",
    "sg:postcode":"YO42 1SA",
    "sg:province":"East Riding of Yorkshire",
    "sg:tags":[
        "house",
        "self",
        "others",
        "guest",
        "catering"
    ],
    "wof:name":"Angela Wood",
    "wof:placetype":"venue"
},
  "geometry": {"coordinates":[-0.7857980132,53.9864768982],"type":"Point"}
}