{
  "type": "Feature",
  "properties": {
    "addr:full":"2 East Road Reigate Surrey RH2 9EX",
    "addr:housenumber":"2",
    "addr:postcode":"rh2 9ex",
    "addr:street":"East Road",
    "iso:country":"GB",
    "sg:address":"2 East Road",
    "sg:city":"Reigate",
    "sg:classifiers":[
        {
            "category":"Shopping",
            "subcategory":"Antiques",
            "type":"Retail Goods"
        }
    ],
    "sg:phone":"+44 1737 222430",
    "sg:postcode":"RH2 9EX",
    "sg:province":"Surrey",
    "wof:name":"A D Gardner",
    "wof:placetype":"venue"
},
  "geometry": {"coordinates":[-0.21153,51.2417068481],"type":"Point"}
}