{
  "type": "Feature",
  "properties": {
    "iso:country":"GB",
    "sg:address":"3-5 Athenaeum Street",
    "sg:city":"Sunderland",
    "sg:classifiers":[
        {
            "category":"Real Estate",
            "subcategory":"Real Estate Agent",
            "type":"Services"
        }
    ],
    "sg:phone":"+44 191 514 5666",
    "sg:postcode":"SR1 1QX",
    "sg:province":"Tyne and Wear",
    "wof:name":"Chadwick Airey",
    "wof:placetype":"venue"
},
  "geometry": {"coordinates":[-1.380219,54.905521],"type":"Point"}
}