{
  "type": "Feature",
  "properties": {
    "addr:full":"20 Ravensworth Avenue Bishop Auckland Durham DL14 6AZ",
    "addr:housenumber":"20",
    "addr:postcode":"dl14 6az",
    "addr:street":"Ravensworth Avenue",
    "iso:country":"GB",
    "sg:address":"20 Ravensworth Avenue",
    "sg:city":"Bishop Auckland",
    "sg:classifiers":[
        {
            "category":"Taxi",
            "type":"Transportation"
        },
        {
            "category":"Military Area",
            "subcategory":"Air Force Base",
            "type":"Public Place"
        }
    ],
    "sg:phone":"+44 1388 601101",
    "sg:postcode":"DL14 6AZ",
    "sg:province":"Durham",
    "sg:tags":[
        "mini",
        "hire",
        "private",
        "cab"
    ],
    "wof:name":"Carroll's Taxis",
    "wof:placetype":"venue"
},
  "geometry": {"coordinates":[-1.6799570322,54.6522521973],"type":"Point"}
}