{
  "type": "Feature",
  "properties": {
    "iso:country":"GB",
    "sg:address":"1043 Leeds Road",
    "sg:city":"Bradford",
    "sg:classifiers":[
        {
            "category":"Shopping",
            "subcategory":"Computers & Home Electronics",
            "type":"Retail Goods"
        }
    ],
    "sg:phone":"+44 1274 665670",
    "sg:postcode":"BD3 7DB",
    "sg:province":"West Yorkshire",
    "sg:tags":[
        "electrical"
    ],
    "wof:name":"In Store Electrics Ltd.",
    "wof:placetype":"venue"
},
  "geometry": {"coordinates":[-1.707717,53.801025],"type":"Point"}
}