{
  "type": "Feature",
  "properties": {
    "iso:country":"GB",
    "sg:address":"Field House, Worthington",
    "sg:city":"Ashby-de-la-zouch",
    "sg:classifiers":[
        {
            "category":"Farming",
            "subcategory":"Livestock Farm",
            "type":"Manufacturing & Wholesale Goods"
        },
        {
            "category":"Farming",
            "subcategory":"Farm",
            "type":"Manufacturing & Wholesale Goods"
        }
    ],
    "sg:postcode":"LE65 1SE",
    "sg:province":"Derbyshire",
    "sg:tags":[
        "mixed",
        "crop",
        "others"
    ],
    "wof:name":"A Wheatley & Son",
    "wof:placetype":"venue"
},
  "geometry": {"coordinates":[-1.4138499498,52.7813491821],"type":"Point"}
}