{
  "type": "Feature",
  "properties": {
    "iso:country":"GB",
    "sg:address":"82 Marine Parade, Tankerton",
    "sg:city":"Whitstable",
    "sg:classifiers":[
        {
            "category":"Travel",
            "subcategory":"Hotels & Motels",
            "type":"Entertainment"
        }
    ],
    "sg:phone":"+44 1227 273707",
    "sg:postcode":"CT5 2BA",
    "sg:province":"Kent",
    "sg:tags":[
        "house",
        "guest"
    ],
    "wof:name":"Marine Lodge",
    "wof:placetype":"venue"
},
  "geometry": {"coordinates":[1.053888,51.364452],"type":"Point"}
}