{
  "type": "Feature",
  "properties": {
    "iso:country":"GB",
    "sg:address":"86 Seacroft Road",
    "sg:city":"Mablethorpe",
    "sg:classifiers":[
        {
            "category":"Professional",
            "subcategory":"Business Services",
            "type":"Services"
        }
    ],
    "sg:phone":"+44 1507 472053",
    "sg:postcode":"LN12 2DR",
    "sg:province":"Lincolnshire",
    "sg:tags":[
        "bookmaker"
    ],
    "wof:name":"Don Noble",
    "wof:placetype":"venue"
},
  "geometry": {"coordinates":[0.260348,53.340443],"type":"Point"}
}