{
  "type": "Feature",
  "properties": {
    "iso:country":"GB",
    "sg:address":"14 Alder Hills",
    "sg:city":"Poole",
    "sg:classifiers":[
        {
            "category":"Social Services",
            "subcategory":"Retirement Home",
            "type":"Services"
        },
        {
            "category":"Shopping",
            "type":"Retail Goods"
        }
    ],
    "sg:phone":"+44 1202 743445",
    "sg:postcode":"BH12 4AS",
    "sg:province":"Dorset",
    "sg:tags":[
        "supplier",
        "equipment",
        "clothing",
        "safety"
    ],
    "wof:name":"Remploy Ltd",
    "wof:placetype":"venue"
},
  "geometry": {"coordinates":[-1.91494,50.739956],"type":"Point"}
}