{
  "type": "Feature",
  "properties": {
    "iso:country":"GB",
    "sg:address":"Grove Works, West Road",
    "sg:city":"Bridport",
    "sg:classifiers":[
        {
            "category":"Social Services",
            "subcategory":"Job Training",
            "type":"Services"
        },
        {
            "category":"Professional",
            "subcategory":"Engineering",
            "type":"Services"
        }
    ],
    "sg:phone":"+44 1308 456232",
    "sg:postcode":"DT6 5JT",
    "sg:province":"Dorset",
    "sg:tags":[
        "marine"
    ],
    "wof:name":"Leygard Ltd.",
    "wof:placetype":"venue"
},
  "geometry": {"coordinates":[-2.7580189705,50.7335662842],"type":"Point"}
}