{
  "type": "Feature",
  "properties": {
    "addr:full":"45 Oak Way, Parc Penllergaer Swansea Carmarthenshire SA4 9WW",
    "addr:housenumber":"45",
    "addr:postcode":"sa4 9ww",
    "addr:street":"Oak Way",
    "iso:country":"GB",
    "sg:address":"45 Oak Way, Parc Penllergaer",
    "sg:city":"Swansea",
    "sg:classifiers":[
        {
            "category":"Manufacturing",
            "subcategory":"Aerospace",
            "type":"Manufacturing & Wholesale Goods"
        }
    ],
    "sg:postcode":"SA4 9WW",
    "sg:province":"Carmarthenshire",
    "sg:tags":[
        "aircraft",
        "furnishing",
        "fitting"
    ],
    "wof:name":"Pennair Ltd.",
    "wof:placetype":"venue"
},
  "geometry": {"coordinates":[-4.00218,51.686199],"type":"Point"}
}