{
  "type": "Feature",
  "properties": {
    "iso:country":"GB",
    "sg:address":"110 Green Lane, Rawmarsh",
    "sg:city":"Rotherham",
    "sg:classifiers":[
        {
            "category":"Taxi",
            "type":"Transportation"
        }
    ],
    "sg:phone":"+44 1709 522811",
    "sg:postcode":"S62 6JX",
    "sg:province":"South Yorkshire",
    "sg:tags":[
        "mini",
        "cab"
    ],
    "wof:name":"Eastman Private Hire",
    "wof:placetype":"venue"
},
  "geometry": {"coordinates":[-1.338024,53.460449],"type":"Point"}
}