{
  "type": "Feature",
  "properties": {
    "iso:country":"GB",
    "sg:address":"10 Duke St",
    "sg:city":"Henley On Thames",
    "sg:classifiers":[
        {
            "category":"Shopping",
            "subcategory":"Clothing, Apparel, & Fashions",
            "type":"Retail Goods"
        }
    ],
    "sg:phone":"+44 1491 573454",
    "sg:postcode":"RG9 1UP",
    "sg:province":"Berkshire",
    "sg:tags":[
        "shop"
    ],
    "wof:name":"Reason",
    "wof:placetype":"venue"
},
  "geometry": {"coordinates":[-0.9045979977,51.5371131897],"type":"Point"}
}