{
  "type": "Feature",
  "properties": {
    "addr:full":"56 Seagarth Lane, Hollybrook Southampton Hampshire SO16 6RL",
    "addr:housenumber":"56",
    "addr:postcode":"so16 6rl",
    "addr:street":"Seagarth Lane",
    "iso:country":"GB",
    "sg:address":"56 Seagarth Lane, Hollybrook",
    "sg:city":"Southampton",
    "sg:classifiers":[
        {
            "category":"Retail",
            "subcategory":"Repair Shop",
            "type":"Services"
        }
    ],
    "sg:phone":"+44 23 8070 5504",
    "sg:postcode":"SO16 6RL",
    "sg:province":"Hampshire",
    "sg:tags":[
        "maintenance"
    ],
    "wof:name":"Drain Ray",
    "wof:placetype":"venue"
},
  "geometry": {"coordinates":[-1.4218280315,50.9348640442],"type":"Point"}
}