{
  "type": "Feature",
  "properties": {
    "iso:country":"GB",
    "sg:address":"Unit 55, The Pembroke Centre, Cheney Manor",
    "sg:city":"Swindon",
    "sg:classifiers":[
        {
            "category":"Sports & Exercise",
            "subcategory":"Race Track",
            "type":"Entertainment"
        }
    ],
    "sg:phone":"+44 1793 527373",
    "sg:postcode":"SN2 2PQ",
    "sg:province":"Wiltshire",
    "sg:tags":[
        "motor"
    ],
    "wof:name":"G.W.R Motor Sport",
    "wof:placetype":"venue"
},
  "geometry": {"coordinates":[-1.808233,51.576378],"type":"Point"}
}