{
  "type": "Feature",
  "properties": {
    "addr:full":"Jubilee Industrial Estate Ashington Northumberland NE63 8UF",
    "addr:housenumber":"estate ashington",
    "addr:postcode":"ne63 8uf",
    "addr:street":"Northumberland",
    "iso:country":"GB",
    "sg:address":"Jubilee Industrial Estate",
    "sg:city":"Ashington",
    "sg:classifiers":[
        {
            "category":"Shopping",
            "subcategory":"Clothing, Apparel, & Fashions",
            "type":"Retail Goods"
        }
    ],
    "sg:phone":"+44 1670 813593",
    "sg:postcode":"NE63 8UF",
    "sg:province":"Northumberland",
    "sg:tags":[
        "clothing",
        "fabric"
    ],
    "wof:name":"Dewhirst Ladieswear",
    "wof:placetype":"venue"
},
  "geometry": {"coordinates":[-1.5694190264,55.1683540344],"type":"Point"}
}