{
  "type": "Feature",
  "properties": {
    "addr:full":"72 Church Road Ashford Greater London TW15 2TW",
    "addr:housenumber":"72",
    "addr:postcode":"tw15 2tw",
    "addr:street":"Church Road",
    "iso:country":"GB",
    "sg:address":"72 Church Road",
    "sg:city":"Ashford",
    "sg:classifiers":[
        {
            "category":"Shopping",
            "subcategory":"Pharmacy",
            "type":"Retail Goods"
        }
    ],
    "sg:phone":"+44 1784 252080",
    "sg:postcode":"TW15 2TW",
    "sg:province":"Greater London",
    "sg:tags":[
        "pharmacist",
        "chemist"
    ],
    "wof:name":"Moss Chemists",
    "wof:placetype":"venue"
},
  "geometry": {"coordinates":[-0.461639,51.43272],"type":"Point"}
}