{
  "type": "Feature",
  "properties": {
    "addr:full":"196 Clapham High Street London Greater London SW4 7UD",
    "addr:housenumber":"196",
    "addr:postcode":"sw4 7ud",
    "addr:street":"Clapham High Street",
    "iso:country":"GB",
    "sg:address":"196 Clapham High Street",
    "sg:city":"London",
    "sg:classifiers":[
        {
            "category":"Bars & Pubs",
            "type":"Food & Drink"
        }
    ],
    "sg:phone":"+44 20 7498 4931",
    "sg:postcode":"SW4 7UD",
    "sg:province":"Greater London",
    "sg:tags":[
        "pubs",
        "inn"
    ],
    "wof:name":"Goose & Granite",
    "wof:placetype":"venue"
},
  "geometry": {"coordinates":[-0.1377999932,51.4621009827],"type":"Point"}
}