{
  "type": "Feature",
  "properties": {
    "iso:country":"GB",
    "sg:address":"35 Mains Lane",
    "sg:city":"Poulton-le-fylde",
    "sg:classifiers":[
        {
            "category":"Home & Garden",
            "subcategory":"Garden Supply",
            "type":"Retail Goods"
        }
    ],
    "sg:postcode":"FY6 7LJ",
    "sg:province":"Lancashire",
    "sg:tags":[
        "nursery",
        "centre"
    ],
    "wof:name":"Brigus Nurseries",
    "wof:placetype":"venue"
},
  "geometry": {"coordinates":[-2.955187,53.84972],"type":"Point"}
}