{
  "type": "Feature",
  "properties": {
    "iso:country":"GB",
    "sg:address":"4 Sheppey Walk",
    "sg:city":"Hailsham",
    "sg:classifiers":[
        {
            "category":"Professional",
            "subcategory":"Accounting & Tax Preparation",
            "type":"Services"
        }
    ],
    "sg:phone":"+44 1323 440978",
    "sg:postcode":"BN27 3BR",
    "sg:province":"East Sussex",
    "sg:tags":[
        "accountant"
    ],
    "wof:name":"M Ramchandarni",
    "wof:placetype":"venue"
},
  "geometry": {"coordinates":[0.245795,50.877647],"type":"Point"}
}