{
  "type": "Feature",
  "properties": {
    "addr:full":"1 Rushfield Road Liss Hampshire GU33 7LW",
    "addr:housenumber":"1",
    "addr:postcode":"gu33 7lw",
    "addr:street":"Rushfield Road",
    "iso:country":"GB",
    "sg:address":"1 Rushfield Road",
    "sg:city":"Liss",
    "sg:classifiers":[
        {
            "category":"Professional",
            "subcategory":"Engineering",
            "type":"Services"
        }
    ],
    "sg:postcode":"GU33 7LW",
    "sg:province":"Hampshire",
    "sg:tags":[
        "contractor",
        "electrical",
        "engineer"
    ],
    "wof:name":"R J Lintott",
    "wof:placetype":"venue"
},
  "geometry": {"coordinates":[-0.8940060139,51.040561676],"type":"Point"}
}