{
  "type": "Feature",
  "properties": {
    "addr:full":"27 Liddle Street, Stoke Stoke-on-trent Staffordshire ST4 5RL",
    "addr:housenumber":"27",
    "addr:postcode":"staffordshire st4 5rl",
    "addr:street":"Liddle Street",
    "iso:country":"GB",
    "sg:address":"27 Liddle Street, Stoke",
    "sg:city":"Stoke-on-trent",
    "sg:classifiers":[
        {
            "category":"Building & Trades",
            "subcategory":"Construction",
            "type":"Services"
        }
    ],
    "sg:phone":"+44 1782 746465",
    "sg:postcode":"ST4 5RL",
    "sg:province":"Staffordshire",
    "sg:tags":[
        "contractor",
        "paving",
        "driveway"
    ],
    "wof:name":"Designer Drives & Building",
    "wof:placetype":"venue"
},
  "geometry": {"coordinates":[-2.1909809113,52.9996681213],"type":"Point"}
}