{
  "type": "Feature",
  "properties": {
    "addr:full":"65 Constitution Street Edinburgh City of Edinburgh EH6 7AF",
    "addr:housenumber":"65",
    "addr:postcode":"eh6 7af",
    "addr:street":"Constitution Street",
    "iso:country":"GB",
    "sg:address":"65 Constitution Street",
    "sg:city":"Edinburgh",
    "sg:classifiers":[
        {
            "category":"Retail",
            "subcategory":"Repair Shop",
            "type":"Services"
        }
    ],
    "sg:phone":"+44 131 467 5525",
    "sg:postcode":"EH6 7AF",
    "sg:province":"City of Edinburgh",
    "sg:tags":[
        "furniture"
    ],
    "wof:name":"Rowland Gomm",
    "wof:placetype":"venue"
},
  "geometry": {"coordinates":[-3.1676459312,55.9737663269],"type":"Point"}
}