{
  "type": "Feature",
  "properties": {
    "iso:country":"GB",
    "sg:address":"54 Ripple Road",
    "sg:city":"Barking",
    "sg:classifiers":[
        {
            "category":"Organizations",
            "subcategory":"Non-profit Organization",
            "type":"Services"
        }
    ],
    "sg:phone":"+44 20 8594 2986",
    "sg:postcode":"IG11 7NT",
    "sg:province":"Essex",
    "sg:tags":[
        "organisation",
        "voluntary",
        "charity"
    ],
    "wof:name":"Barnardo's",
    "wof:placetype":"venue"
},
  "geometry": {"coordinates":[0.081341,51.536438],"type":"Point"}
}