{
  "type": "Feature",
  "properties": {
    "iso:country":"GB",
    "sg:address":"7 Crossway, Ffosyffin",
    "sg:city":"Aberaeron",
    "sg:classifiers":[
        {
            "category":"Shopping",
            "type":"Retail Goods"
        }
    ],
    "sg:phone":"+44 1545 571312",
    "sg:postcode":"SA46 0HD",
    "sg:province":"Ceredigion",
    "sg:tags":[
        "merchant"
    ],
    "wof:name":"Maskell Agricultural Service",
    "wof:placetype":"venue"
},
  "geometry": {"coordinates":[-4.258728981,52.2373313904],"type":"Point"}
}