{
  "type": "Feature",
  "properties": {
    "iso:country":"GB",
    "sg:address":"27 Heol Ceirios",
    "sg:city":"Ammanford",
    "sg:classifiers":[
        {
            "category":"Building & Trades",
            "subcategory":"Plumbing",
            "type":"Services"
        }
    ],
    "sg:phone":"+44 1269 850279",
    "sg:postcode":"SA18 2SR",
    "sg:province":"Carmarthenshire",
    "sg:tags":[
        "heating"
    ],
    "wof:name":"G Mosford",
    "wof:placetype":"venue"
},
  "geometry": {"coordinates":[-3.997482,51.81216],"type":"Point"}
}