{
  "type": "Feature",
  "properties": {
    "iso:country":"GB",
    "sg:address":"47 Neilston Road",
    "sg:city":"Paisley",
    "sg:classifiers":[
        {
            "category":"Autos & Motor Vehicles",
            "subcategory":"Automobile Sales",
            "type":"Retail Goods"
        }
    ],
    "sg:postcode":"PA2 6LY",
    "sg:province":"East Renfrewshire",
    "sg:tags":[
        "car"
    ],
    "wof:name":"Abbey Automobiles",
    "wof:placetype":"venue"
},
  "geometry": {"coordinates":[-4.423472,55.836212],"type":"Point"}
}