{
  "type": "Feature",
  "properties": {
    "iso:country":"GB",
    "sg:address":"11 St. Johns Rd",
    "sg:city":"Windsor",
    "sg:classifiers":[
        {
            "category":"Wholesale",
            "subcategory":"Toys & Hobbies",
            "type":"Manufacturing & Wholesale Goods"
        }
    ],
    "sg:postcode":"SL4 3QN",
    "sg:province":"Berkshire",
    "sg:tags":[
        "balloon",
        "novelty"
    ],
    "wof:name":"Marron-Keen,Yvette,",
    "wof:placetype":"venue"
},
  "geometry": {"coordinates":[-0.628375,51.478687],"type":"Point"}
}