{
  "type": "Feature",
  "properties": {
    "addr:full":"Potten Farm, Main Road Ashford Kent TN25 6EQ",
    "addr:postcode":"tn25 6eq",
    "addr:street":"Main Road",
    "iso:country":"GB",
    "sg:address":"Potten Farm, Main Road",
    "sg:city":"Ashford",
    "sg:classifiers":[
        {
            "category":"Home & Garden",
            "subcategory":"Garden Supply",
            "type":"Retail Goods"
        }
    ],
    "sg:postcode":"TN25 6EQ",
    "sg:province":"Kent",
    "sg:tags":[
        "nursery",
        "centre"
    ],
    "wof:name":"Potten Farm Nursery",
    "wof:placetype":"venue"
},
  "geometry": {"coordinates":[0.9939500093,51.1061706543],"type":"Point"}
}