{
  "type": "Feature",
  "properties": {
    "iso:country":"GB",
    "sg:address":"7 Gordon Harvey Court",
    "sg:city":"Littleborough",
    "sg:classifiers":[
        {
            "category":"Social Services",
            "subcategory":"Job Training",
            "type":"Services"
        }
    ],
    "sg:postcode":"OL15 9BN",
    "sg:province":"Lancashire",
    "sg:tags":[
        "translator",
        "interpreter"
    ],
    "wof:name":"Dermot Byrne",
    "wof:placetype":"venue"
},
  "geometry": {"coordinates":[-2.096913,53.643787],"type":"Point"}
}