{
  "type": "Feature",
  "properties": {
    "iso:country":"GB",
    "sg:address":"48 White Hart Lane",
    "sg:city":"Fareham",
    "sg:classifiers":[
        {
            "category":"Shopping",
            "subcategory":"Florist",
            "type":"Retail Goods"
        }
    ],
    "sg:postcode":"PO16 9BH",
    "sg:province":"Hampshire",
    "wof:name":"Flower Spot",
    "wof:placetype":"venue"
},
  "geometry": {"coordinates":[-1.1245880127,50.8414039612],"type":"Point"}
}