{
  "type": "Feature",
  "properties": {
    "addr:full":"17 Clwyd Street Rhyl Conwy LL18 3LH",
    "addr:housenumber":"17",
    "addr:postcode":"ll18 3lh",
    "addr:street":"Clwyd Street",
    "iso:country":"GB",
    "sg:address":"17 Clwyd Street",
    "sg:city":"Rhyl",
    "sg:classifiers":[
        {
            "category":"Organizations",
            "subcategory":"Professional Association",
            "type":"Services"
        }
    ],
    "sg:postcode":"LL18 3LH",
    "sg:province":"Conwy",
    "sg:tags":[
        "tech",
        "system",
        "automation"
    ],
    "wof:name":"Exor Control Systems Ltd.",
    "wof:placetype":"venue"
},
  "geometry": {"coordinates":[-3.4887239933,53.3206443787],"type":"Point"}
}