{
  "type": "Feature",
  "properties": {
    "addr:full":"21 Sunningdale Dr Salford Greater Manchester M6 7PH",
    "addr:housenumber":"21",
    "addr:postcode":"m6 7ph",
    "addr:street":"Sunningdale Dr",
    "iso:country":"GB",
    "sg:address":"21 Sunningdale Dr",
    "sg:city":"Salford",
    "sg:classifiers":[
        {
            "category":"Building & Trades",
            "subcategory":"Construction",
            "type":"Services"
        }
    ],
    "sg:phone":"+44 161 793 0514",
    "sg:postcode":"M6 7PH",
    "sg:province":"Greater Manchester",
    "sg:tags":[
        "roofing"
    ],
    "wof:name":"J & S Roofing",
    "wof:placetype":"venue"
},
  "geometry": {"coordinates":[-2.3231859207,53.49949646],"type":"Point"}
}