{
  "type": "Feature",
  "properties": {
    "iso:country":"GB",
    "sg:address":"46 Albemarle Street",
    "sg:city":"London",
    "sg:classifiers":[
        {
            "category":"Arts & Performance",
            "subcategory":"Art Gallery",
            "type":"Entertainment"
        }
    ],
    "sg:postcode":"W1S 4JQ",
    "sg:province":"Greater London",
    "wof:name":"Johan C E  Omell",
    "wof:placetype":"venue"
},
  "geometry": {"coordinates":[-0.14124,51.508099],"type":"Point"}
}