{
  "type": "Feature",
  "properties": {
    "iso:country":"GB",
    "sg:address":"50 Patmos, Burnley Road",
    "sg:city":"Todmorden",
    "sg:classifiers":[
        {
            "category":"Shopping",
            "subcategory":"News",
            "type":"Retail Goods"
        }
    ],
    "sg:postcode":"OL14 5EY",
    "sg:province":"Lancashire",
    "sg:tags":[
        "newsagent"
    ],
    "wof:name":"P O & E Bruniges",
    "wof:placetype":"venue"
},
  "geometry": {"coordinates":[-2.098719,53.7169],"type":"Point"}
}