{
  "type": "Feature",
  "properties": {
    "iso:country":"GB",
    "sg:address":"34 Bowness Street, Stretford",
    "sg:city":"Manchester",
    "sg:classifiers":[
        {
            "category":"Building & Trades",
            "subcategory":"Construction",
            "type":"Services"
        }
    ],
    "sg:postcode":"M32 0FA",
    "sg:province":"Cheshire",
    "sg:tags":[
        "builder"
    ],
    "wof:name":"F N S Builders",
    "wof:placetype":"venue"
},
  "geometry": {"coordinates":[-2.308878,53.454372],"type":"Point"}
}