{
  "type": "Feature",
  "properties": {
    "addr:full":"12 Ampthill Road Bedford Bedfordshire MK42 9HE",
    "addr:housenumber":"12",
    "addr:postcode":"mk42 9he",
    "addr:street":"Ampthill Road",
    "iso:country":"GB",
    "sg:address":"12 Ampthill Road",
    "sg:city":"Bedford",
    "sg:classifiers":[
        {
            "category":"Home & Garden",
            "subcategory":"Household Appliances",
            "type":"Retail Goods"
        }
    ],
    "sg:postcode":"MK42 9HE",
    "sg:province":"Bedfordshire",
    "sg:tags":[
        "domestic",
        "centre"
    ],
    "wof:name":"Bedford Recon Centre",
    "wof:placetype":"venue"
},
  "geometry": {"coordinates":[-0.470114,52.127613],"type":"Point"}
}