{
  "type": "Feature",
  "properties": {
    "iso:country":"GB",
    "sg:address":"3 Orme Street",
    "sg:city":"Blackpool",
    "sg:classifiers":[
        {
            "category":"Building & Trades",
            "subcategory":"Cleaning & Sanitation",
            "type":"Services"
        }
    ],
    "sg:phone":"+44 1253 627480",
    "sg:postcode":"FY1 4AL",
    "sg:province":"Lancashire",
    "sg:tags":[
        "sweep",
        "chimney"
    ],
    "wof:name":"WILLIAM HARDMAN",
    "wof:placetype":"venue"
},
  "geometry": {"coordinates":[-3.043852,53.810993],"type":"Point"}
}