{
  "type": "Feature",
  "properties": {
    "addr:full":"100 High Street Kingussie Highland PH21 1HY",
    "addr:housenumber":"100",
    "addr:postcode":"ph21 1hy",
    "addr:street":"High Street",
    "iso:country":"GB",
    "sg:address":"100 High Street",
    "sg:city":"Kingussie",
    "sg:classifiers":[
        {
            "category":"Education",
            "subcategory":"Library",
            "type":"Public Place"
        }
    ],
    "sg:phone":"+44 1540 661596",
    "sg:postcode":"PH21 1HY",
    "sg:province":"Highland",
    "sg:tags":[
        "book"
    ],
    "wof:name":"Kingussie Library",
    "wof:placetype":"venue"
},
  "geometry": {"coordinates":[-4.044593811,57.0817337036],"type":"Point"}
}