{
  "type": "Feature",
  "properties": {
    "iso:country":"GB",
    "sg:address":"18 Harvist Rd",
    "sg:city":"Kilburn",
    "sg:classifiers":[
        {
            "category":"Health Services",
            "subcategory":"Doctor",
            "type":"Services"
        }
    ],
    "sg:phone":"+44 20 8969 7711",
    "sg:postcode":"NW6 6SD",
    "sg:province":"Greater London",
    "sg:tags":[
        "practitioners"
    ],
    "wof:name":"Drs Tooth & Landau",
    "wof:placetype":"venue"
},
  "geometry": {"coordinates":[-0.2069389969,51.5344238281],"type":"Point"}
}