{
  "type": "Feature",
  "properties": {
    "iso:country":"GB",
    "sg:address":"Tod Point Rd",
    "sg:city":"Redcar",
    "sg:classifiers":[
        {
            "category":"Cafe",
            "type":"Food & Drink"
        }
    ],
    "sg:phone":"+44 1642 492772",
    "sg:postcode":"TS10 5AW",
    "sg:province":"North Yorkshire",
    "sg:tags":[
        "tea",
        "room"
    ],
    "wof:name":"Drop Inn Cafe The",
    "wof:placetype":"venue"
},
  "geometry": {"coordinates":[-1.103049,54.617329],"type":"Point"}
}