{
  "type": "Feature",
  "properties": {
    "addr:full":"116 King Street South Shields Tyne and Wear NE33 1JE",
    "addr:housenumber":"116",
    "addr:postcode":"ne33 1je",
    "addr:street":"King Street",
    "iso:country":"GB",
    "sg:address":"116 King Street",
    "sg:city":"South Shields",
    "sg:classifiers":[
        {
            "category":"Shopping",
            "subcategory":"Shoes",
            "type":"Retail Goods"
        }
    ],
    "sg:phone":"+44 191 454 5280",
    "sg:postcode":"NE33 1JE",
    "sg:province":"Tyne and Wear",
    "sg:tags":[
        "shop"
    ],
    "wof:name":"Waynes Shoes",
    "wof:placetype":"venue"
},
  "geometry": {"coordinates":[-1.4372810125,54.9978256226],"type":"Point"}
}