{
  "type": "Feature",
  "properties": {
    "iso:country":"GB",
    "sg:address":"5 Queensway Arcade",
    "sg:city":"Dewsbury",
    "sg:classifiers":[
        {
            "category":"Recreation",
            "subcategory":"Amusement Park",
            "type":"Entertainment"
        }
    ],
    "sg:phone":"+44 1924 461003",
    "sg:postcode":"WF13 1DY",
    "sg:province":"West Yorkshire",
    "sg:tags":[
        "arcade"
    ],
    "wof:name":"Quicksilver",
    "wof:placetype":"venue"
},
  "geometry": {"coordinates":[-1.631109,53.691605],"type":"Point"}
}