{
  "type": "Feature",
  "properties": {
    "iso:country":"GB",
    "sg:address":"2 White Horse Lane",
    "sg:city":"Abergavenny",
    "sg:classifiers":[
        {
            "category":"Professional",
            "type":"Services"
        }
    ],
    "sg:phone":"+44 1873 853708",
    "sg:postcode":"NP7 5AS",
    "sg:province":"Herefordshire",
    "sg:tags":[
        "repair",
        "tech",
        "maintenance"
    ],
    "wof:name":"S T Computers",
    "wof:placetype":"venue"
},
  "geometry": {"coordinates":[-3.02068,51.825008],"type":"Point"}
}