{
  "type": "Feature",
  "properties": {
    "addr:full":"82-84 Hotwell Road Bristol City of Bristol BS8 4UB",
    "addr:housenumber":"82-84",
    "addr:postcode":"bs8 4ub",
    "addr:street":"Hotwell Road",
    "iso:country":"GB",
    "sg:address":"82-84 Hotwell Road",
    "sg:city":"Bristol",
    "sg:classifiers":[
        {
            "category":"Professional",
            "subcategory":"Accounting & Tax Preparation",
            "type":"Services"
        },
        {
            "category":"Shopping",
            "type":"Retail Goods"
        }
    ],
    "sg:postcode":"BS8 4UB",
    "sg:province":"City of Bristol",
    "sg:tags":[
        "accountant",
        "part",
        "accessory"
    ],
    "wof:name":"Keith M Vickers",
    "wof:placetype":"venue"
},
  "geometry": {"coordinates":[-2.6086490154,51.4504814148],"type":"Point"}
}