{
  "type": "Feature",
  "properties": {
    "iso:country":"GB",
    "sg:address":"15 Manor Walk",
    "sg:city":"Market Harborough",
    "sg:classifiers":[
        {
            "category":"Health Services",
            "subcategory":"Optometrist",
            "type":"Services"
        }
    ],
    "sg:postcode":"LE16 9BP",
    "sg:province":"Leicestershire",
    "sg:tags":[
        "optician"
    ],
    "wof:name":"T J Hanby & Partners",
    "wof:placetype":"venue"
},
  "geometry": {"coordinates":[-0.9060789943,52.4935951233],"type":"Point"}
}