{
  "type": "Feature",
  "properties": {
    "addr:full":"Stand La Manchester Greater Manchester M26 1JP",
    "addr:postcode":"m26 1jp",
    "addr:street":"La",
    "iso:country":"GB",
    "sg:address":"Stand La",
    "sg:city":"Manchester",
    "sg:classifiers":[
        {
            "category":"Autos & Motor Vehicles",
            "subcategory":"Automobile Sales",
            "type":"Retail Goods"
        }
    ],
    "sg:phone":"+44 161 766 8816",
    "sg:postcode":"M26 1JP",
    "sg:province":"Greater Manchester",
    "sg:tags":[
        "car"
    ],
    "wof:name":"Ferguson Ford",
    "wof:placetype":"venue"
},
  "geometry": {"coordinates":[-2.3226089478,53.557144165],"type":"Point"}
}