{
  "type": "Feature",
  "properties": {
    "addr:full":"Chartwell House, 230-232 London Road East Grinstead East Sussex RH19 1HF",
    "addr:housenumber":"230-232",
    "addr:postcode":"rh19 1hf",
    "addr:street":"London Road",
    "iso:country":"GB",
    "sg:address":"Chartwell House, 230-232 London Road",
    "sg:city":"East Grinstead",
    "sg:classifiers":[
        {
            "category":"Professional",
            "subcategory":"Employment Agencies",
            "type":"Services"
        }
    ],
    "sg:phone":"+44 1342 313755",
    "sg:postcode":"RH19 1HF",
    "sg:province":"East Sussex",
    "sg:tags":[
        "consultant"
    ],
    "wof:name":"E M S Recruitment",
    "wof:placetype":"venue"
},
  "geometry": {"coordinates":[-0.016728,51.129635],"type":"Point"}
}