{
  "type": "Feature",
  "properties": {
    "addr:full":"67 Howard Street North Shields Tyne and Wear NE30 1AF",
    "addr:housenumber":"67",
    "addr:postcode":"ne30 1af",
    "addr:street":"Howard Street",
    "iso:country":"GB",
    "sg:address":"67 Howard Street",
    "sg:city":"North Shields",
    "sg:classifiers":[
        {
            "category":"Real Estate",
            "subcategory":"Real Estate Agent",
            "type":"Services"
        }
    ],
    "sg:phone":"+44 191 257 3117",
    "sg:postcode":"NE30 1AF",
    "sg:province":"Tyne and Wear",
    "wof:name":"Sims & Brown",
    "wof:placetype":"venue"
},
  "geometry": {"coordinates":[-1.44464,55.009758],"type":"Point"}
}