{
  "type": "Feature",
  "properties": {
    "addr:full":"Heath Rd, Coxheath Maidstone Kent ME17 4AH",
    "addr:postcode":"me17 4ah",
    "addr:street":"Heath Rd",
    "iso:country":"GB",
    "sg:address":"Heath Rd, Coxheath",
    "sg:city":"Maidstone",
    "sg:classifiers":[
        {
            "category":"Government",
            "subcategory":"Office",
            "type":"Public Place"
        }
    ],
    "sg:phone":"+44 1622 741870",
    "sg:postcode":"ME17 4AH",
    "sg:province":"Kent",
    "sg:tags":[
        "project",
        "gov",
        "community"
    ],
    "wof:name":"Heathside House",
    "wof:placetype":"venue"
},
  "geometry": {"coordinates":[0.4947499931,51.2325935364],"type":"Point"}
}