{
  "type": "Feature",
  "properties": {
    "iso:country":"GB",
    "sg:address":"33 High Street",
    "sg:city":"Evesham",
    "sg:classifiers":[
        {
            "category":"Professional",
            "subcategory":"Employment Agencies",
            "type":"Services"
        }
    ],
    "sg:phone":"+44 1386 444270",
    "sg:postcode":"WR11 4DA",
    "sg:province":"Gloucestershire",
    "sg:tags":[
        "consultant"
    ],
    "wof:name":"Westbourne Services Ltd.",
    "wof:placetype":"venue"
},
  "geometry": {"coordinates":[-1.947429,52.092884],"type":"Point"}
}