{
  "type": "Feature",
  "properties": {
    "iso:country":"GB",
    "sg:address":"72-74 Eyre Place",
    "sg:city":"Edinburgh",
    "sg:classifiers":[
        {
            "category":"Manufacturing",
            "subcategory":"Building Materials",
            "type":"Manufacturing & Wholesale Goods"
        }
    ],
    "sg:phone":"+44 131 557 1717",
    "sg:postcode":"EH3 5EL",
    "sg:province":"City of Edinburgh",
    "sg:tags":[
        "merchant",
        "builder"
    ],
    "wof:name":"Builder Center Ltd",
    "wof:placetype":"venue"
},
  "geometry": {"coordinates":[-3.205111,55.962589],"type":"Point"}
}