{
  "type": "Feature",
  "properties": {
    "iso:country":"GB",
    "sg:address":"363 New Kings Road",
    "sg:city":"London",
    "sg:classifiers":[
        {
            "category":"Shopping",
            "subcategory":"Antiques",
            "type":"Retail Goods"
        }
    ],
    "sg:phone":"+44 20 7736 1095",
    "sg:postcode":"SW6 4RJ",
    "sg:province":"Greater London",
    "wof:name":"Hurlingham Antiques",
    "wof:placetype":"venue"
},
  "geometry": {"coordinates":[-0.20653,51.471104],"type":"Point"}
}