{
  "type": "Feature",
  "properties": {
    "addr:full":"45 Bridge Street Witney Oxfordshire OX28 1NA",
    "addr:housenumber":"45",
    "addr:postcode":"ox28 1na",
    "addr:street":"Bridge Street",
    "iso:country":"GB",
    "sg:address":"45 Bridge Street",
    "sg:city":"Witney",
    "sg:classifiers":[
        {
            "category":"Retail",
            "subcategory":"Repair Shop",
            "type":"Services"
        },
        {
            "category":"Shopping",
            "subcategory":"Antiques",
            "type":"Retail Goods"
        }
    ],
    "sg:phone":"+44 1993 705384",
    "sg:postcode":"OX28 1NA",
    "sg:province":"Oxfordshire",
    "sg:tags":[
        "sale",
        "second-hand"
    ],
    "wof:name":"John D Soame",
    "wof:placetype":"venue"
},
  "geometry": {"coordinates":[-1.481112,51.790569],"type":"Point"}
}