{
  "type": "Feature",
  "properties": {
    "addr:full":"1 New Broadway, Tarring Worthing West Sussex BN11 4HP",
    "addr:housenumber":"1",
    "addr:postcode":"bn11 4hp",
    "addr:street":"New Broadway",
    "iso:country":"GB",
    "sg:address":"1 New Broadway, Tarring",
    "sg:city":"Worthing",
    "sg:classifiers":[
        {
            "category":"Professional",
            "subcategory":"Computer Services",
            "type":"Services"
        }
    ],
    "sg:phone":"+44 1903 531494",
    "sg:postcode":"BN11 4HP",
    "sg:province":"West Sussex",
    "sg:tags":[
        "system",
        "software"
    ],
    "wof:name":"M P Internet Working Ltd",
    "wof:placetype":"venue"
},
  "geometry": {"coordinates":[-0.3754239976,50.8136253357],"type":"Point"}
}