{
  "type": "Feature",
  "properties": {
    "iso:country":"GB",
    "sg:address":"1 Church Lane",
    "sg:city":"London",
    "sg:classifiers":[
        {
            "category":"Travel",
            "subcategory":"Hotels & Motels",
            "type":"Entertainment"
        }
    ],
    "sg:phone":"+44 20 8348 9765",
    "sg:postcode":"N8 7BU",
    "sg:province":"Greater London",
    "sg:tags":[
        "house",
        "guest"
    ],
    "wof:name":"The White Lodge Hotel",
    "wof:placetype":"venue"
},
  "geometry": {"coordinates":[-0.115765,51.584846],"type":"Point"}
}