{
  "type": "Feature",
  "properties": {
    "addr:full":"14 The Woolmead Farnham Surrey GU9 7TX",
    "addr:housenumber":"14",
    "addr:postcode":"gu9 7tx",
    "addr:street":"The Woolmead Farnham",
    "iso:country":"GB",
    "sg:address":"14 The Woolmead",
    "sg:city":"Farnham",
    "sg:classifiers":[
        {
            "category":"Professional",
            "subcategory":"Art Services",
            "type":"Services"
        }
    ],
    "sg:postcode":"GU9 7TX",
    "sg:province":"Surrey",
    "sg:tags":[
        "framing"
    ],
    "wof:name":"Farnham Framing Studios",
    "wof:placetype":"venue"
},
  "geometry": {"coordinates":[-0.7983689904,51.2118492126],"type":"Point"}
}