{
  "type": "Feature",
  "properties": {
    "addr:full":"Belbins Dene, Sandy Lane Romsey Hampshire SO51 0PD",
    "addr:postcode":"so51 0pd",
    "addr:street":"Dene Sandy Lane",
    "iso:country":"GB",
    "sg:address":"Belbins Dene, Sandy Lane",
    "sg:city":"Romsey",
    "sg:classifiers":[
        {
            "category":"Building & Trades",
            "subcategory":"Equipment Rental",
            "type":"Services"
        },
        {
            "category":"Building & Trades",
            "subcategory":"Construction",
            "type":"Services"
        }
    ],
    "sg:phone":"+44 1794 367606",
    "sg:postcode":"SO51 0PD",
    "sg:province":"Hampshire",
    "sg:tags":[
        "excavation",
        "groundwork",
        "plant",
        "machinery",
        "contractor"
    ],
    "wof:name":"R H C Groundworks Ltd.",
    "wof:placetype":"venue"
},
  "geometry": {"coordinates":[-1.487264,51.009476],"type":"Point"}
}