{
  "type": "Feature",
  "properties": {
    "iso:country":"GB",
    "sg:address":"1022 The Whitgift Centre",
    "sg:city":"Croydon",
    "sg:classifiers":[
        {
            "category":"Shopping",
            "subcategory":"Clothing, Apparel, & Fashions",
            "type":"Retail Goods"
        }
    ],
    "sg:phone":"+44 20 8686 6668",
    "sg:postcode":"CR0 1UU",
    "sg:province":"Surrey",
    "sg:tags":[
        "shop"
    ],
    "wof:name":"Clobbers",
    "wof:placetype":"venue"
},
  "geometry": {"coordinates":[-0.0956000015,51.3655014038],"type":"Point"}
}