{
  "type": "Feature",
  "properties": {
    "iso:country":"GB",
    "sg:address":"Caru, Beckfield Lane",
    "sg:city":"Knottingley",
    "sg:classifiers":[
        {
            "category":"Professional",
            "subcategory":"Business Services",
            "type":"Services"
        }
    ],
    "sg:phone":"+44 1977 672222",
    "sg:postcode":"WF11 9JP",
    "sg:province":"North Yorkshire",
    "sg:tags":[
        "import",
        "export",
        "agent"
    ],
    "wof:name":"Dobson Imports",
    "wof:placetype":"venue"
},
  "geometry": {"coordinates":[-1.2925280333,53.7464599609],"type":"Point"}
}