{
  "type": "Feature",
  "properties": {
    "addr:full":"84 Temple Chambers, Temple Avenue London Greater London EC4Y 0HP",
    "addr:housenumber":"84",
    "addr:postcode":"ec4y 0hp",
    "addr:street":"Temple Chambers Temple Avenue",
    "iso:country":"GB",
    "sg:address":"84 Temple Chambers, Temple Avenue",
    "sg:city":"London",
    "sg:classifiers":[
        {
            "category":"Professional",
            "subcategory":"Business Services",
            "type":"Services"
        }
    ],
    "sg:postcode":"EC4Y 0HP",
    "sg:province":"Greater London",
    "sg:tags":[
        "holding"
    ],
    "wof:name":"W. Darby (Holdings) Limited",
    "wof:placetype":"venue"
},
  "geometry": {"coordinates":[-0.107969,51.512539],"type":"Point"}
}