{
  "type": "Feature",
  "properties": {
    "iso:country":"GB",
    "sg:address":"Moulsham Street",
    "sg:city":"Chelmsford",
    "sg:classifiers":[
        {
            "category":"Health Services",
            "subcategory":"Nursing And Care Facility",
            "type":"Services"
        },
        {
            "category":"Social Services",
            "subcategory":"Retirement Home",
            "type":"Services"
        }
    ],
    "sg:phone":"+44 1245 494674",
    "sg:postcode":"CM2 9AQ",
    "sg:province":"Essex",
    "sg:tags":[
        "residential"
    ],
    "wof:name":"Ashley House",
    "wof:placetype":"venue"
},
  "geometry": {"coordinates":[0.462455,51.72374],"type":"Point"}
}