{
  "type": "Feature",
  "properties": {
    "addr:full":"Lees Rd, Mossley Ashton Under Lyne Greater Manchester OL5 0PQ",
    "addr:postcode":"ol5 0pq",
    "addr:street":"Lees Rd;Under Lyne",
    "iso:country":"GB",
    "sg:address":"Lees Rd, Mossley",
    "sg:city":"Ashton Under Lyne",
    "sg:classifiers":[
        {
            "category":"Health Services",
            "subcategory":"Nursing And Care Facility",
            "type":"Services"
        }
    ],
    "sg:phone":"+44 1457 833200",
    "sg:postcode":"OL5 0PQ",
    "sg:province":"Greater Manchester",
    "sg:tags":[
        "home"
    ],
    "wof:name":"Leighbank House",
    "wof:placetype":"venue"
},
  "geometry": {"coordinates":[-2.0468890667,53.5205764771],"type":"Point"}
}