{
  "type": "Feature",
  "properties": {
    "addr:full":"5 Ancton Drive Bognor Regis West Sussex PO22 6NA",
    "addr:housenumber":"5",
    "addr:postcode":"po22 6na",
    "addr:street":"Ancton Drive",
    "iso:country":"GB",
    "sg:address":"5 Ancton Drive",
    "sg:city":"Bognor Regis",
    "sg:classifiers":[
        {
            "category":"Manufacturing",
            "subcategory":"Furniture",
            "type":"Manufacturing & Wholesale Goods"
        }
    ],
    "sg:phone":"+44 1243 583272",
    "sg:postcode":"PO22 6NA",
    "sg:province":"West Sussex",
    "sg:tags":[
        "polishing",
        "french"
    ],
    "wof:name":"G R Pearce",
    "wof:placetype":"venue"
},
  "geometry": {"coordinates":[-0.609658,50.795303],"type":"Point"}
}