{
  "type": "Feature",
  "properties": {
    "iso:country":"GB",
    "sg:address":"276 Northdown Rd, Cliftonville",
    "sg:city":"Margate",
    "sg:classifiers":[
        {
            "category":"Museum",
            "subcategory":"Art Museum",
            "type":"Entertainment"
        }
    ],
    "sg:phone":"+44 1843 223710",
    "sg:postcode":"CT9 2PT",
    "sg:province":"Kent",
    "sg:tags":[
        "gallery"
    ],
    "wof:name":"Deardens",
    "wof:placetype":"venue"
},
  "geometry": {"coordinates":[1.39641,51.387959],"type":"Point"}
}