{
  "type": "Feature",
  "properties": {
    "addr:full":"128-130 Belgrave Gate Leicester Leicestershire LE1 3XJ",
    "addr:housenumber":"128-130",
    "addr:postcode":"le1 3xj",
    "addr:street":"Belgrave Gate",
    "iso:country":"GB",
    "sg:address":"128-130 Belgrave Gate",
    "sg:city":"Leicester",
    "sg:classifiers":[
        {
            "category":"Professional",
            "subcategory":"Detective & Security Services",
            "type":"Services"
        }
    ],
    "sg:phone":"+44 116 233 3266",
    "sg:postcode":"LE1 3XJ",
    "sg:province":"Leicestershire",
    "wof:name":"Smart Security Systems (Leics)",
    "wof:placetype":"venue"
},
  "geometry": {"coordinates":[-1.130752,52.640045],"type":"Point"}
}