{
  "type": "Feature",
  "properties": {
    "addr:full":"Forty Avenue Wembley Greater London HA9 9JE",
    "addr:postcode":"ha9 9je",
    "addr:street":"Forty Avenue",
    "iso:country":"GB",
    "sg:address":"Forty Avenue",
    "sg:city":"Wembley",
    "sg:classifiers":[
        {
            "category":"Autos & Motor Vehicles",
            "subcategory":"Fuel & Gas Station",
            "type":"Retail Goods"
        }
    ],
    "sg:phone":"+44 20 8385 0297",
    "sg:postcode":"HA9 9JE",
    "sg:province":"Greater London",
    "sg:tags":[
        "hr",
        "petrol"
    ],
    "wof:name":"Forty Avenue Service Station",
    "wof:placetype":"venue"
},
  "geometry": {"coordinates":[-0.278127,51.565529],"type":"Point"}
}