{
  "type": "Feature",
  "properties": {
    "addr:full":"710 Prescot Road, Old Swan Liverpool Merseyside L13 5XG",
    "addr:housenumber":"710",
    "addr:postcode":"l13 5xg",
    "addr:street":"Prescot Road",
    "iso:country":"GB",
    "sg:address":"710 Prescot Road, Old Swan",
    "sg:city":"Liverpool",
    "sg:classifiers":[
        {
            "category":"Community Center",
            "subcategory":"Social",
            "type":"Public Place"
        }
    ],
    "sg:phone":"+44 151 220 8324",
    "sg:postcode":"L13 5XG",
    "sg:province":"Merseyside",
    "sg:tags":[
        "frozen",
        "food",
        "freezer",
        "centre"
    ],
    "wof:name":"Iceland Foods Plc",
    "wof:placetype":"venue"
},
  "geometry": {"coordinates":[-2.907171011,53.4147148132],"type":"Point"}
}