{
  "type": "Feature",
  "properties": {
    "iso:country":"GB",
    "sg:address":"61 Queens Street",
    "sg:city":"Newton Abbot",
    "sg:classifiers":[
        {
            "category":"Military Area",
            "subcategory":"Air Force Base",
            "type":"Public Place"
        }
    ],
    "sg:phone":"+44 1803 872225",
    "sg:postcode":"TQ12 2AU",
    "sg:province":"Devon",
    "sg:tags":[
        "taxi",
        "hire",
        "private"
    ],
    "wof:name":"Alansway Taxis Ltd.",
    "wof:placetype":"venue"
},
  "geometry": {"coordinates":[-3.60648,50.53093],"type":"Point"}
}