{
  "type": "Feature",
  "properties": {
    "iso:country":"GB",
    "sg:address":"178 Northam Road",
    "sg:city":"Southampton",
    "sg:classifiers":[
        {
            "category":"Education",
            "subcategory":"Special Training",
            "type":"Public Place"
        }
    ],
    "sg:phone":"+44 23 8048 0035",
    "sg:postcode":"SO14 0QF",
    "sg:province":"Hampshire",
    "sg:tags":[
        "product",
        "centre"
    ],
    "wof:name":"Shewstone Ltd.",
    "wof:placetype":"venue"
},
  "geometry": {"coordinates":[-1.3880369663,50.9113998413],"type":"Point"}
}