{
  "type": "Feature",
  "properties": {
    "addr:full":"167 North Road Ferndale Rhondda, Cynon, Taff CF43 4RA",
    "addr:housenumber":"167",
    "addr:postcode":"cf43 4ra",
    "addr:street":"North Road",
    "iso:country":"GB",
    "sg:address":"167 North Road",
    "sg:city":"Ferndale",
    "sg:classifiers":[
        {
            "category":"Health Services",
            "subcategory":"Podiatrist",
            "type":"Services"
        }
    ],
    "sg:phone":"+44 1443 732037",
    "sg:postcode":"CF43 4RA",
    "sg:province":"Rhondda, Cynon, Taff",
    "sg:tags":[
        "podiatrists",
        "chiropodist"
    ],
    "wof:name":"G & G Jenkins",
    "wof:placetype":"venue"
},
  "geometry": {"coordinates":[-3.450571,51.665272],"type":"Point"}
}