{
  "type": "Feature",
  "properties": {
    "addr:full":"Hereford Rd Ledbury Gloucestershire HR8 2PZ",
    "addr:postcode":"hr8 2pz",
    "addr:street":"Hereford Rd",
    "iso:country":"GB",
    "sg:address":"Hereford Rd",
    "sg:city":"Ledbury",
    "sg:classifiers":[
        {
            "category":"Professional",
            "subcategory":"Business Services",
            "type":"Services"
        }
    ],
    "sg:phone":"+44 1531 670891",
    "sg:postcode":"HR8 2PZ",
    "sg:province":"Gloucestershire",
    "sg:tags":[
        "distribution"
    ],
    "wof:name":"Berwick Industries Ltd",
    "wof:placetype":"venue"
},
  "geometry": {"coordinates":[-2.435159,52.044506],"type":"Point"}
}