{
  "type": "Feature",
  "properties": {
    "addr:full":"Macdonald Rd Coventry Warwickshire CV2 5FE",
    "addr:postcode":"cv2 5fe",
    "addr:street":"Macdonald Rd",
    "iso:country":"GB",
    "sg:address":"Macdonald Rd",
    "sg:city":"Coventry",
    "sg:classifiers":[
        {
            "category":"Place Of Worship",
            "type":"Public Place"
        }
    ],
    "sg:phone":"+44 24 7644 4062",
    "sg:postcode":"CV2 5FE",
    "sg:province":"Warwickshire",
    "wof:name":"Macdonald Road Methodist Church",
    "wof:placetype":"venue"
},
  "geometry": {"coordinates":[-1.4605300426,52.411907196],"type":"Point"}
}