{
  "type": "Feature",
  "properties": {
    "addr:full":"17 Royde Road Cardiff Cardiff CF4 4UP",
    "addr:housenumber":"17",
    "addr:postcode":"cf4 4up",
    "addr:street":"Royde Road",
    "iso:country":"GB",
    "sg:address":"17 Royde Road",
    "sg:city":"Cardiff",
    "sg:classifiers":[
        {
            "category":"Building & Trades",
            "subcategory":"Plumbing",
            "type":"Services"
        }
    ],
    "sg:postcode":"CF4 4UP",
    "sg:province":"Cardiff",
    "sg:tags":[
        "heating"
    ],
    "wof:name":"J D Heating & Plumbing & Mechanical Services Ltd.",
    "wof:placetype":"venue"
},
  "geometry": {"coordinates":[-3.277348,51.473228],"type":"Point"}
}