{
  "type": "Feature",
  "properties": {
    "iso:country":"GB",
    "sg:address":"Thoroughfare",
    "sg:city":"Halesworth",
    "sg:classifiers":[
        {
            "category":"Shopping",
            "subcategory":"Bicycles & Sporting Goods",
            "type":"Retail Goods"
        }
    ],
    "sg:postcode":"IP19 8AR",
    "sg:province":"Suffolk",
    "sg:tags":[
        "cycle",
        "accessory"
    ],
    "wof:name":"O'Neil,R,",
    "wof:placetype":"venue"
},
  "geometry": {"coordinates":[1.5022219419,52.3437461853],"type":"Point"}
}