{
  "type": "Feature",
  "properties": {
    "iso:country":"GB",
    "sg:address":"10 Robin Hood Road",
    "sg:city":"Woking",
    "sg:classifiers":[
        {
            "category":"Autos & Motor Vehicles",
            "subcategory":"Auto Supplies",
            "type":"Retail Goods"
        }
    ],
    "sg:phone":"+44 1483 764391",
    "sg:postcode":"GU21 8SP",
    "sg:province":"Surrey",
    "sg:tags":[
        "tyre"
    ],
    "wof:name":"Merityre Specialists Ltd.",
    "wof:placetype":"venue"
},
  "geometry": {"coordinates":[-0.596763,51.313324],"type":"Point"}
}