{
  "type": "Feature",
  "properties": {
    "addr:full":"Spring Hall, Greyhound Rd Willesden Greater London NW10 5QH",
    "addr:postcode":"nw10 5qh",
    "addr:street":"Greyhound Rd",
    "iso:country":"GB",
    "sg:address":"Spring Hall, Greyhound Rd",
    "sg:city":"Willesden",
    "sg:classifiers":[
        {
            "category":"Place Of Worship",
            "type":"Public Place"
        }
    ],
    "sg:phone":"+44 20 8960 9134",
    "sg:postcode":"NW10 5QH",
    "sg:province":"Greater London",
    "wof:name":"Calvery Church Of God In Christ",
    "wof:placetype":"venue"
},
  "geometry": {"coordinates":[-0.228550002,51.5308494568],"type":"Point"}
}