{
  "type": "Feature",
  "properties": {
    "iso:country":"GB",
    "sg:address":"Eridge Road",
    "sg:city":"Crowborough",
    "sg:classifiers":[
        {
            "category":"Building & Trades",
            "subcategory":"Cleaning & Sanitation",
            "type":"Services"
        },
        {
            "category":"Home & Garden",
            "subcategory":"Carpets & Floor Coverings",
            "type":"Retail Goods"
        }
    ],
    "sg:phone":"+44 1892 661234",
    "sg:postcode":"TN6 2SL",
    "sg:province":"East Sussex",
    "sg:tags":[
        "cleaner",
        "hygiene",
        "upholstery",
        "commercial"
    ],
    "wof:name":"Double Dutch Cleaning Contractors",
    "wof:placetype":"venue"
},
  "geometry": {"coordinates":[0.176749,51.062973],"type":"Point"}
}