{
  "type": "Feature",
  "properties": {
    "iso:country":"GB",
    "sg:address":"7-9 Fengate",
    "sg:city":"Peterborough",
    "sg:classifiers":[
        {
            "category":"Retail",
            "subcategory":"Auto Repair",
            "type":"Services"
        }
    ],
    "sg:postcode":"PE1 5BA",
    "sg:province":"Cambridgeshire",
    "sg:tags":[
        "modification",
        "garage"
    ],
    "wof:name":"Hinkins,Neil,",
    "wof:placetype":"venue"
},
  "geometry": {"coordinates":[-0.2249239981,52.5711555481],"type":"Point"}
}