{
  "type": "Feature",
  "properties": {
    "addr:full":"280-284 Portobello High Street Edinburgh City of Edinburgh EH15 2AT",
    "addr:housenumber":"280-284",
    "addr:postcode":"eh15 2at",
    "addr:street":"Portobello High Street",
    "iso:country":"GB",
    "sg:address":"280-284 Portobello High Street",
    "sg:city":"Edinburgh",
    "sg:classifiers":[
        {
            "category":"Restaurant",
            "type":"Food & Drink"
        }
    ],
    "sg:phone":"+44 131 669 2850",
    "sg:postcode":"EH15 2AT",
    "sg:province":"City of Edinburgh",
    "sg:tags":[
        "italian"
    ],
    "wof:name":"Ristorante Sant'andrea",
    "wof:placetype":"venue"
},
  "geometry": {"coordinates":[-3.109789,55.951851],"type":"Point"}
}