{
  "type": "Feature",
  "properties": {
    "addr:full":"288 Battersea Park Road London Greater London SW11 3BT",
    "addr:housenumber":"288",
    "addr:postcode":"sw11 3bt",
    "addr:street":"Battersea Park Road",
    "iso:country":"GB",
    "sg:address":"288 Battersea Park Road",
    "sg:city":"London",
    "sg:classifiers":[
        {
            "category":"Shopping",
            "subcategory":"Antiques",
            "type":"Retail Goods"
        },
        {
            "category":"Home & Garden",
            "subcategory":"Furniture",
            "type":"Retail Goods"
        }
    ],
    "sg:phone":"+44 20 7223 6950",
    "sg:postcode":"SW11 3BT",
    "sg:province":"Greater London",
    "sg:tags":[
        "outlet"
    ],
    "wof:name":"Heritage House",
    "wof:placetype":"venue"
},
  "geometry": {"coordinates":[-0.1677470058,51.4717216492],"type":"Point"}
}