{
  "type": "Feature",
  "properties": {
    "addr:full":"Higham House, Higham Place Newcastle-upon-tyne Tyne and Wear NE1 8AF",
    "addr:postcode":"ne1 8af",
    "addr:street":"Higham Place",
    "iso:country":"GB",
    "sg:address":"Higham House, Higham Place",
    "sg:city":"Newcastle-upon-tyne",
    "sg:classifiers":[
        {
            "category":"Personal",
            "subcategory":"Beauty Salon",
            "type":"Services"
        },
        {
            "category":"Personal",
            "subcategory":"Barber",
            "type":"Services"
        }
    ],
    "sg:phone":"+44 191 230 3059",
    "sg:postcode":"NE1 8AF",
    "sg:province":"Tyne and Wear",
    "sg:tags":[
        "unisex",
        "hairdresser"
    ],
    "wof:name":"Green Ginger",
    "wof:placetype":"venue"
},
  "geometry": {"coordinates":[-1.6090439558,54.9751586914],"type":"Point"}
}