{
  "type": "Feature",
  "properties": {
    "addr:full":"Downhayne Farm Colyton Devon EX24 6SJ",
    "addr:postcode":"ex24 6sj",
    "iso:country":"GB",
    "sg:address":"Downhayne Farm",
    "sg:city":"Colyton",
    "sg:classifiers":[
        {
            "category":"Farming",
            "subcategory":"Crops",
            "type":"Manufacturing & Wholesale Goods"
        },
        {
            "category":"Farming",
            "subcategory":"Livestock Farm",
            "type":"Manufacturing & Wholesale Goods"
        }
    ],
    "sg:phone":"+44 1297 552205",
    "sg:postcode":"EX24 6SJ",
    "sg:province":"Devon",
    "sg:tags":[
        "arable",
        "others"
    ],
    "wof:name":"L J BRIGHT",
    "wof:placetype":"venue"
},
  "geometry": {"coordinates":[-3.0702440739,50.7403373718],"type":"Point"}
}