{
  "type": "Feature",
  "properties": {
    "addr:full":"Millway Rise Industrial Estate Axminster Devon EX13 5HU",
    "addr:postcode":"ex13 5hu",
    "addr:street":"Millway Rise Industrial Estate",
    "iso:country":"GB",
    "sg:address":"Millway Rise Industrial Estate",
    "sg:city":"Axminster",
    "sg:classifiers":[
        {
            "category":"Wholesale",
            "subcategory":"Machinery & Supplies",
            "type":"Manufacturing & Wholesale Goods"
        }
    ],
    "sg:phone":"+44 1297 630250",
    "sg:postcode":"EX13 5HU",
    "sg:province":"Devon",
    "sg:tags":[
        "pump"
    ],
    "wof:name":"Lowara U K Ltd.",
    "wof:placetype":"venue"
},
  "geometry": {"coordinates":[-2.9847590923,50.7905387878],"type":"Point"}
}