{
  "type": "Feature",
  "properties": {
    "iso:country":"GB",
    "sg:address":"78 Hospital Hill",
    "sg:city":"Dunfermline",
    "sg:classifiers":[
        {
            "category":"Cafe",
            "type":"Food & Drink"
        }
    ],
    "sg:postcode":"KY11 3AT",
    "sg:province":"Fife",
    "sg:tags":[
        "tea",
        "room"
    ],
    "wof:name":"Brucefield Cafe",
    "wof:placetype":"venue"
},
  "geometry": {"coordinates":[-3.446662,56.062222],"type":"Point"}
}