{
  "type": "Feature",
  "properties": {
    "iso:country":"GB",
    "sg:address":"Lighthouse Road",
    "sg:city":"Helston",
    "sg:classifiers":[
        {
            "category":"Restaurant",
            "type":"Food & Drink"
        }
    ],
    "sg:phone":"+44 1326 290662",
    "sg:postcode":"TR12 7NJ",
    "sg:province":"Cornwall",
    "wof:name":"P M & I M Parker",
    "wof:placetype":"venue"
},
  "geometry": {"coordinates":[-5.204434,49.96719],"type":"Point"}
}