{
  "type": "Feature",
  "properties": {
    "iso:country":"GB",
    "sg:address":"39 Marshalls Cross Road",
    "sg:city":"St Helens",
    "sg:classifiers":[
        {
            "category":"Shopping",
            "subcategory":"Department Store",
            "type":"Retail Goods"
        }
    ],
    "sg:phone":"+44 1744 27673",
    "sg:postcode":"WA9 3BJ",
    "sg:province":"Cheshire",
    "wof:name":"Peasley Cross Post Office",
    "wof:placetype":"venue"
},
  "geometry": {"coordinates":[-2.721535,53.442379],"type":"Point"}
}