{
  "type": "Feature",
  "properties": {
    "iso:country":"GB",
    "sg:address":"3 George Lane",
    "sg:city":"Folkestone",
    "sg:classifiers":[
        {
            "category":"Restaurant",
            "type":"Food & Drink"
        }
    ],
    "sg:phone":"+44 1303 251221",
    "sg:postcode":"CT20 1RH",
    "sg:province":"Kent",
    "wof:name":"Hillside Restaurant",
    "wof:placetype":"venue"
},
  "geometry": {"coordinates":[1.1501100063,51.0864639282],"type":"Point"}
}