{
  "type": "Feature",
  "properties": {
    "iso:country":"GB",
    "sg:address":"Ferry View, Bath Road",
    "sg:city":"Lymington",
    "sg:classifiers":[
        {
            "category":"Health Services",
            "subcategory":"Hospital",
            "type":"Services"
        }
    ],
    "sg:postcode":"SO41 3SE",
    "sg:province":"Hampshire",
    "sg:tags":[
        "ambulance"
    ],
    "wof:name":"D & M Ambulances",
    "wof:placetype":"venue"
},
  "geometry": {"coordinates":[-1.538911,50.758938],"type":"Point"}
}