{
  "type": "Feature",
  "properties": {
    "iso:country":"GB",
    "sg:address":"Bristol Road South, Rubery",
    "sg:city":"Birmingham",
    "sg:classifiers":[
        {
            "category":"Autos & Motor Vehicles",
            "subcategory":"Fuel & Gas Station",
            "type":"Retail Goods"
        },
        {
            "category":"Farming",
            "subcategory":"Nursery",
            "type":"Manufacturing & Wholesale Goods"
        },
        {
            "category":"Food & Beverages",
            "subcategory":"Supermarket",
            "type":"Retail Goods"
        }
    ],
    "sg:phone":"+44 121 460 1940",
    "sg:postcode":"B45 9NY",
    "sg:province":"West Midlands",
    "sg:tags":[
        "petrol",
        "filling",
        "creche"
    ],
    "wof:name":"Creche",
    "wof:placetype":"venue"
},
  "geometry": {"coordinates":[-2.000779,52.39603],"type":"Point"}
}