{
  "type": "Feature",
  "properties": {
    "addr:full":"10 Ripon Drive, Blaby Leicester Leicestershire LE8 4AU",
    "addr:housenumber":"10",
    "addr:postcode":"le8 4au",
    "addr:street":"Ripon Drive",
    "iso:country":"GB",
    "sg:address":"10 Ripon Drive, Blaby",
    "sg:city":"Leicester",
    "sg:classifiers":[
        {
            "category":"Building & Trades",
            "subcategory":"Construction",
            "type":"Services"
        }
    ],
    "sg:postcode":"LE8 4AU",
    "sg:province":"Leicestershire",
    "sg:tags":[
        "conversion",
        "loft"
    ],
    "wof:name":"M & S Loft Conversions",
    "wof:placetype":"venue"
},
  "geometry": {"coordinates":[-1.16612,52.566673],"type":"Point"}
}