{
  "type": "Feature",
  "properties": {
    "iso:country":"GB",
    "sg:address":"West Park Cres",
    "sg:city":"Billericay",
    "sg:classifiers":[
        {
            "category":"Place Of Worship",
            "type":"Public Place"
        }
    ],
    "sg:phone":"+44 1277 652916",
    "sg:postcode":"CM12 9ED",
    "sg:province":"Essex",
    "wof:name":"Kingdom Hall Of Jehovah's Witnesses",
    "wof:placetype":"venue"
},
  "geometry": {"coordinates":[0.416855,51.624748],"type":"Point"}
}