{
  "type": "Feature",
  "properties": {
    "addr:full":"21e Briardale Road Blyth Northumberland NE24 5LA",
    "addr:housenumber":"21e",
    "addr:postcode":"ne24 5la",
    "addr:street":"Briardale Road;Northumberland",
    "iso:country":"GB",
    "sg:address":"21e Briardale Road",
    "sg:city":"Blyth",
    "sg:classifiers":[
        {
            "category":"Government",
            "subcategory":"Post Office",
            "type":"Public Place"
        }
    ],
    "sg:phone":"+44 1670 367105",
    "sg:postcode":"NE24 5LA",
    "sg:province":"Northumberland",
    "wof:name":"Briardale Newsagents",
    "wof:placetype":"venue"
},
  "geometry": {"coordinates":[-1.5402909517,55.1275253296],"type":"Point"}
}