{
  "type": "Feature",
  "properties": {
    "addr:full":"Trinity Ho, Heather Park Dr Wembley Greater London HA0 1SU",
    "addr:postcode":"ha0 1su",
    "addr:street":"Park Dr",
    "iso:country":"GB",
    "sg:address":"Trinity Ho, Heather Park Dr",
    "sg:city":"Wembley",
    "sg:classifiers":[
        {
            "category":"Professional",
            "subcategory":"Lawyer & Legal Services",
            "type":"Services"
        }
    ],
    "sg:phone":"+44 20 8903 3555",
    "sg:postcode":"HA0 1SU",
    "sg:province":"Greater London",
    "sg:tags":[
        "solicitor"
    ],
    "wof:name":"Aaron Soni Solicitors",
    "wof:placetype":"venue"
},
  "geometry": {"coordinates":[-0.282949,51.543411],"type":"Point"}
}