{
  "type": "Feature",
  "properties": {
    "addr:full":"14 Rochester Street Bradford West Yorkshire BD3 8ED",
    "addr:housenumber":"14",
    "addr:postcode":"bd3 8ed",
    "addr:street":"Rochester Street",
    "iso:country":"GB",
    "sg:address":"14 Rochester Street",
    "sg:city":"Bradford",
    "sg:classifiers":[
        {
            "category":"Food & Beverages",
            "subcategory":"Supermarket",
            "type":"Retail Goods"
        }
    ],
    "sg:phone":"+44 1274 668927",
    "sg:postcode":"BD3 8ED",
    "sg:province":"West Yorkshire",
    "wof:name":"Food Fair",
    "wof:placetype":"venue"
},
  "geometry": {"coordinates":[-1.7200930119,53.7947235107],"type":"Point"}
}