{
  "type": "Feature",
  "properties": {
    "addr:full":"4 Willowbrook Park Loughborough Leicestershire LE11 5HG",
    "addr:housenumber":"4",
    "addr:postcode":"le11 5hg",
    "addr:street":"Willowbrook Park",
    "iso:country":"GB",
    "sg:address":"4 Willowbrook Park",
    "sg:city":"Loughborough",
    "sg:classifiers":[
        {
            "category":"Home & Garden",
            "subcategory":"Furniture",
            "type":"Retail Goods"
        }
    ],
    "sg:phone":"+44 1509 611115",
    "sg:postcode":"LE11 5HG",
    "sg:province":"Leicestershire",
    "wof:name":"Mfi Furniture Centre",
    "wof:placetype":"venue"
},
  "geometry": {"coordinates":[-1.2234740257,52.7685241699],"type":"Point"}
}