{
  "type": "Feature",
  "properties": {
    "addr:full":"39 Westfield Street St Helens Merseyside WA10 1QA",
    "addr:housenumber":"39",
    "addr:postcode":"wa10 1qa",
    "addr:street":"Westfield Street",
    "iso:country":"GB",
    "sg:address":"39 Westfield Street",
    "sg:city":"St Helens",
    "sg:classifiers":[
        {
            "category":"Personal",
            "subcategory":"Beauty Salon",
            "type":"Services"
        }
    ],
    "sg:phone":"+44 1744 25185",
    "sg:postcode":"WA10 1QA",
    "sg:province":"Merseyside",
    "sg:tags":[
        "unisex",
        "hairdresser"
    ],
    "wof:name":"Avanti Hair Team",
    "wof:placetype":"venue"
},
  "geometry": {"coordinates":[-2.740760088,53.4532699585],"type":"Point"}
}