{
  "type": "Feature",
  "properties": {
    "addr:full":"Toller La Bradford West Yorkshire BD8 9DE",
    "addr:postcode":"bd8 9de",
    "addr:street":"West",
    "iso:country":"GB",
    "sg:address":"Toller La",
    "sg:city":"Bradford",
    "sg:classifiers":[
        {
            "category":"Place Of Worship",
            "type":"Public Place"
        }
    ],
    "sg:phone":"+44 1274 543957",
    "sg:postcode":"BD8 9DE",
    "sg:province":"West Yorkshire",
    "wof:name":"St Chad C Of E Church",
    "wof:placetype":"venue"
},
  "geometry": {"coordinates":[-1.786464,53.806252],"type":"Point"}
}