{
  "type": "Feature",
  "properties": {
    "iso:country":"GB",
    "sg:address":"17 Islington High St",
    "sg:city":"Islington",
    "sg:classifiers":[
        {
            "category":"Government",
            "subcategory":"Office",
            "type":"Public Place"
        }
    ],
    "sg:phone":"+44 20 7278 3388",
    "sg:postcode":"N1 9LQ",
    "sg:province":"Greater London",
    "sg:tags":[
        "education",
        "agency",
        "authority"
    ],
    "wof:name":"Educational Support Services",
    "wof:placetype":"venue"
},
  "geometry": {"coordinates":[-0.106427,51.532494],"type":"Point"}
}