{
  "type": "Feature",
  "properties": {
    "addr:full":"Rugwood Farm, Foulness Island Southend-on-sea Essex SS3 9XG",
    "addr:housenumber":"foulness",
    "addr:postcode":"ss3 9xg",
    "iso:country":"GB",
    "sg:address":"Rugwood Farm, Foulness Island",
    "sg:city":"Southend-on-sea",
    "sg:classifiers":[
        {
            "category":"Farming",
            "subcategory":"Livestock Farm",
            "type":"Manufacturing & Wholesale Goods"
        }
    ],
    "sg:phone":"+44 1702 219466",
    "sg:postcode":"SS3 9XG",
    "sg:province":"Essex",
    "sg:tags":[
        "others"
    ],
    "wof:name":"I F Burroughs & Son",
    "wof:placetype":"venue"
},
  "geometry": {"coordinates":[0.8745030165,51.5821647644],"type":"Point"}
}