{
  "type": "Feature",
  "properties": {
    "addr:full":"71 Milngavie Road Glasgow East Dunbartonshire G61 2DW",
    "addr:housenumber":"71",
    "addr:postcode":"g61 2dw",
    "addr:street":"Milngavie Road",
    "iso:country":"GB",
    "sg:address":"71 Milngavie Road",
    "sg:city":"Glasgow",
    "sg:classifiers":[
        {
            "category":"Fast Food",
            "type":"Food & Drink"
        }
    ],
    "sg:phone":"+44 141 943 0023",
    "sg:postcode":"G61 2DW",
    "sg:province":"East Dunbartonshire",
    "sg:tags":[
        "away",
        "take"
    ],
    "wof:name":"Qismat Tandoori",
    "wof:placetype":"venue"
},
  "geometry": {"coordinates":[-4.321514,55.915646],"type":"Point"}
}