{
  "type": "Feature",
  "properties": {
    "addr:full":"47b Kingsland Road, West Mersea Colchester Essex CO5 8RA",
    "addr:housenumber":"47b",
    "addr:postcode":"co5 8ra",
    "addr:street":"Kingsland Road West;Colchester",
    "iso:country":"GB",
    "sg:address":"47b Kingsland Road, West Mersea",
    "sg:city":"Colchester",
    "sg:classifiers":[
        {
            "category":"Social Services",
            "subcategory":"Job Training",
            "type":"Services"
        }
    ],
    "sg:phone":"+44 1206 384677",
    "sg:postcode":"CO5 8RA",
    "sg:province":"Essex",
    "sg:tags":[
        "engineering",
        "marine"
    ],
    "wof:name":"Lapline Ltd.",
    "wof:placetype":"venue"
},
  "geometry": {"coordinates":[0.9194520116,51.7777633667],"type":"Point"}
}