{
  "type": "Feature",
  "properties": {
    "addr:full":"10 The Osiers, Mill La, Kegworth Derby Leicestershire DE74 2GD",
    "addr:housenumber":"10",
    "addr:postcode":"de74 2gd",
    "addr:street":"The Osiers Mill La Kegworth",
    "iso:country":"GB",
    "sg:address":"10 The Osiers, Mill La, Kegworth",
    "sg:city":"Derby",
    "sg:classifiers":[
        {
            "category":"Manufacturing",
            "subcategory":"Metals",
            "type":"Manufacturing & Wholesale Goods"
        }
    ],
    "sg:postcode":"DE74 2GD",
    "sg:province":"Leicestershire",
    "sg:tags":[
        "steel",
        "fabricator",
        "erectors"
    ],
    "wof:name":"Dawes,Simon A,",
    "wof:placetype":"venue"
},
  "geometry": {"coordinates":[-1.2798409462,52.8367424011],"type":"Point"}
}