{
  "type": "Feature",
  "properties": {
    "addr:full":"20 Mowlem Trading Estate, Leeside Road London Greater London N17 0QJ",
    "addr:housenumber":"20",
    "addr:postcode":"n17 0qj",
    "addr:street":"Mowlem Trading Estate Leeside Road",
    "iso:country":"GB",
    "sg:address":"20 Mowlem Trading Estate, Leeside Road",
    "sg:city":"London",
    "sg:classifiers":[
        {
            "category":"Food & Beverages",
            "subcategory":"Liquor & Beverages",
            "type":"Retail Goods"
        },
        {
            "category":"Military Area",
            "subcategory":"Air Force Base",
            "type":"Public Place"
        }
    ],
    "sg:phone":"+44 20 8808 4181",
    "sg:postcode":"N17 0QJ",
    "sg:province":"Greater London",
    "sg:tags":[
        "wholesale",
        "beer",
        "wine",
        "spirit",
        "wines"
    ],
    "wof:name":"Amathus Wines Ltd",
    "wof:placetype":"venue"
},
  "geometry": {"coordinates":[-0.047694,51.60553],"type":"Point"}
}