{
  "type": "Feature",
  "properties": {
    "addr:full":"Plas Madoc, Acrefair Wrexham Wrexham LL14 3HL",
    "addr:postcode":"ll14 3hl",
    "addr:street":"Plas;Acrefair",
    "iso:country":"GB",
    "sg:address":"Plas Madoc, Acrefair",
    "sg:city":"Wrexham",
    "sg:classifiers":[
        {
            "category":"Social Services",
            "type":"Services"
        },
        {
            "category":"Social Services",
            "subcategory":"Retirement Home",
            "type":"Services"
        },
        {
            "category":"Government",
            "subcategory":"Office",
            "type":"Public Place"
        }
    ],
    "sg:phone":"+44 1978 822553",
    "sg:postcode":"LL14 3HL",
    "sg:province":"Wrexham",
    "sg:tags":[
        "local",
        "rest"
    ],
    "wof:name":"Llys Madoc Elderly Person Home",
    "wof:placetype":"venue"
},
  "geometry": {"coordinates":[-3.082656,52.978378],"type":"Point"}
}