{
  "type": "Feature",
  "properties": {
    "iso:country":"GB",
    "sg:address":"Keighley Business Centre, South St",
    "sg:city":"Keighley",
    "sg:classifiers":[
        {
            "category":"Professional",
            "subcategory":"Computer Services",
            "type":"Services"
        }
    ],
    "sg:phone":"+44 1535 610225",
    "sg:postcode":"BD21 1AG",
    "sg:province":"West Yorkshire",
    "sg:tags":[
        "system",
        "software"
    ],
    "wof:name":"A V L Multimedia",
    "wof:placetype":"venue"
},
  "geometry": {"coordinates":[-1.909674,53.866364],"type":"Point"}
}