{
  "type": "Feature",
  "properties": {
    "addr:full":"51 Southend Road Grays Essex RM17 6ST",
    "addr:housenumber":"51",
    "addr:postcode":"rm17 6st",
    "addr:street":"Southend Road",
    "iso:country":"GB",
    "sg:address":"51 Southend Road",
    "sg:city":"Grays",
    "sg:classifiers":[
        {
            "category":"Retail",
            "subcategory":"Auto Repair",
            "type":"Services"
        }
    ],
    "sg:postcode":"RM17 6ST",
    "sg:province":"Essex",
    "sg:tags":[
        "modification",
        "garage"
    ],
    "wof:name":"A D Grant",
    "wof:placetype":"venue"
},
  "geometry": {"coordinates":[0.3360869884,51.4844551086],"type":"Point"}
}