{
  "type": "Feature",
  "properties": {
    "iso:country":"GB",
    "sg:address":"25 Broad Street",
    "sg:city":"Leek",
    "sg:classifiers":[
        {
            "category":"Autos & Motor Vehicles",
            "subcategory":"Auto Supplies",
            "type":"Retail Goods"
        },
        {
            "category":"Retail",
            "subcategory":"Auto Repair",
            "type":"Services"
        }
    ],
    "sg:phone":"+44 1538 398555",
    "sg:postcode":"ST13 5NX",
    "sg:province":"Staffordshire",
    "sg:tags":[
        "rubber",
        "car",
        "specialist",
        "tyre",
        "customizing"
    ],
    "wof:name":"Bronco 4 X 4 Ltd.",
    "wof:placetype":"venue"
},
  "geometry": {"coordinates":[-2.02797,53.10347],"type":"Point"}
}