{
  "type": "Feature",
  "properties": {
    "iso:country":"GB",
    "sg:address":"Riverside Studios, Dogley Mill",
    "sg:city":"Huddersfield",
    "sg:classifiers":[
        {
            "category":"Professional",
            "subcategory":"Art Services",
            "type":"Services"
        }
    ],
    "sg:phone":"+44 1484 605405",
    "sg:postcode":"HD8 0LE",
    "sg:province":"South Yorkshire",
    "sg:tags":[
        "consultant",
        "design"
    ],
    "wof:name":"Planet Design",
    "wof:placetype":"venue"
},
  "geometry": {"coordinates":[-1.71893,53.62241],"type":"Point"}
}