{
  "type": "Feature",
  "properties": {
    "iso:country":"GB",
    "sg:address":"452-458 High Road",
    "sg:city":"Ilford",
    "sg:classifiers":[
        {
            "category":"Professional",
            "subcategory":"Engineering",
            "type":"Services"
        }
    ],
    "sg:phone":"+44 20 8514 4997",
    "sg:postcode":"IG1 1UF",
    "sg:province":"Essex",
    "sg:tags":[
        "consulting",
        "engineer"
    ],
    "wof:name":"Quest Environmental Services Ltd.",
    "wof:placetype":"venue"
},
  "geometry": {"coordinates":[0.088697,51.562023],"type":"Point"}
}