{
  "type": "Feature",
  "properties": {
    "iso:country":"GB",
    "sg:address":"Mounthorn Burnside Of Letham",
    "sg:city":"Leven",
    "sg:classifiers":[
        {
            "category":"Real Estate",
            "subcategory":"Architect",
            "type":"Services"
        }
    ],
    "sg:phone":"+44 1333 350702",
    "sg:postcode":"KY8 5NP",
    "sg:province":"Fife",
    "sg:tags":[
        "architectural"
    ],
    "wof:name":"Mitan Services",
    "wof:placetype":"venue"
},
  "geometry": {"coordinates":[-2.998787,56.194401],"type":"Point"}
}