{
  "type": "Feature",
  "properties": {
    "iso:country":"GB",
    "sg:address":"10a Monmouth Place",
    "sg:city":"Bath",
    "sg:classifiers":[
        {
            "category":"Shopping",
            "subcategory":"Antiques",
            "type":"Retail Goods"
        },
        {
            "category":"Shopping",
            "subcategory":"Used Merchandise",
            "type":"Retail Goods"
        }
    ],
    "sg:phone":"+44 1225 429413",
    "sg:postcode":"BA1 2AU",
    "sg:province":"Bath and North East Somerset",
    "sg:tags":[
        "shop",
        "second-hand"
    ],
    "wof:name":"Arkea Antiques",
    "wof:placetype":"venue"
},
  "geometry": {"coordinates":[-2.3665730953,51.3828430176],"type":"Point"}
}