{
  "type": "Feature",
  "properties": {
    "addr:full":"New Building Tilbury Fort, Fort Road Tilbury Essex RM18 7NR",
    "addr:postcode":"rm18 7nr",
    "addr:street":"Tilbury Fort Fort Road",
    "iso:country":"GB",
    "sg:address":"New Building Tilbury Fort, Fort Road",
    "sg:city":"Tilbury",
    "sg:classifiers":[
        {
            "category":"Landmark",
            "subcategory":"Tourist Attraction",
            "type":"Public Place"
        }
    ],
    "sg:phone":"+44 1375 858489",
    "sg:postcode":"RM18 7NR",
    "sg:province":"Essex",
    "sg:tags":[
        "interest"
    ],
    "wof:name":"English Heritage",
    "wof:placetype":"venue"
},
  "geometry": {"coordinates":[0.3501150012,51.4638748169],"type":"Point"}
}