{
  "type": "Feature",
  "properties": {
    "addr:full":"Unit 1&2 648 Chester Road, Sutton Coldfield Birmingham West Midlands B73 5JR",
    "addr:housenumber":"unit 1 & 2 648",
    "addr:postcode":"b73 5jr",
    "addr:street":"Chester Road",
    "iso:country":"GB",
    "sg:address":"Unit 1&2 648 Chester Road, Sutton Coldfield",
    "sg:city":"Birmingham",
    "sg:classifiers":[
        {
            "category":"Retail",
            "subcategory":"Auto Repair",
            "type":"Services"
        }
    ],
    "sg:phone":"+44 121 686 3100",
    "sg:postcode":"B73 5JR",
    "sg:province":"West Midlands",
    "sg:tags":[
        "modification",
        "garage"
    ],
    "wof:name":"A S A P Tyres & Exhausts Ltd.",
    "wof:placetype":"venue"
},
  "geometry": {"coordinates":[-1.8325020075,52.5349693298],"type":"Point"}
}