{
  "type": "Feature",
  "properties": {
    "addr:full":"181 New Road, Rednal Birmingham West Midlands B45 9JW",
    "addr:housenumber":"181",
    "addr:postcode":"b45 9jw",
    "addr:street":"New Road",
    "iso:country":"GB",
    "sg:address":"181 New Road, Rednal",
    "sg:city":"Birmingham",
    "sg:classifiers":[
        {
            "category":"Food & Beverages",
            "subcategory":"Meat & Fish",
            "type":"Retail Goods"
        }
    ],
    "sg:phone":"+44 121 453 2747",
    "sg:postcode":"B45 9JW",
    "sg:province":"West Midlands",
    "sg:tags":[
        "butcher"
    ],
    "wof:name":"Behan Bros",
    "wof:placetype":"venue"
},
  "geometry": {"coordinates":[-2.018237114,52.3936958313],"type":"Point"}
}