{
  "type": "Feature",
  "properties": {
    "addr:full":"11 Collins Street Northampton Northamptonshire NN1 4TG",
    "addr:housenumber":"11",
    "addr:postcode":"nn1 4tg",
    "addr:street":"Collins Street",
    "iso:country":"GB",
    "sg:address":"11 Collins Street",
    "sg:city":"Northampton",
    "sg:classifiers":[
        {
            "category":"Building & Trades",
            "subcategory":"Landscaping Services",
            "type":"Services"
        }
    ],
    "sg:phone":"+44 1604 603107",
    "sg:postcode":"NN1 4TG",
    "sg:province":"Northamptonshire",
    "sg:tags":[
        "gardening"
    ],
    "wof:name":"Bruce E Wood Gardening Services",
    "wof:placetype":"venue"
},
  "geometry": {"coordinates":[-0.87421,52.242138],"type":"Point"}
}