{
  "type": "Feature",
  "properties": {
    "iso:country":"GB",
    "sg:address":"16 Camden Road",
    "sg:city":"Tunbridge Wells",
    "sg:classifiers":[
        {
            "category":"Professional",
            "type":"Services"
        }
    ],
    "sg:phone":"+44 1892 616160",
    "sg:postcode":"TN1 2PT",
    "sg:province":"Kent",
    "sg:tags":[
        "repair",
        "tech",
        "maintenance"
    ],
    "wof:name":"Acg Computer Services Ltd.",
    "wof:placetype":"venue"
},
  "geometry": {"coordinates":[0.2675099969,51.1345596313],"type":"Point"}
}