{
  "type": "Feature",
  "properties": {
    "iso:country":"GB",
    "sg:address":"Within Debenhams Plc, 334-348 Oxford Street",
    "sg:city":"London",
    "sg:classifiers":[
        {
            "category":"Banks & Credit Unions",
            "subcategory":"Bureau De Change",
            "type":"Services"
        },
        {
            "category":"Travel",
            "subcategory":"Travel Agent",
            "type":"Entertainment"
        }
    ],
    "sg:phone":"+44 20 7707 2000",
    "sg:postcode":"W1C 1JG",
    "sg:province":"Greater London",
    "wof:name":"Thomas Cook",
    "wof:placetype":"venue"
},
  "geometry": {"coordinates":[-0.14439,51.514931],"type":"Point"}
}