{
  "type": "Feature",
  "properties": {
    "addr:full":"2 Forest Avenue Mansfield Nottinghamshire NG18 4BX",
    "addr:housenumber":"2",
    "addr:postcode":"ng18 4bx",
    "addr:street":"Forest Avenue",
    "iso:country":"GB",
    "sg:address":"2 Forest Avenue",
    "sg:city":"Mansfield",
    "sg:classifiers":[
        {
            "category":"Retail",
            "subcategory":"Auto Repair",
            "type":"Services"
        }
    ],
    "sg:phone":"+44 1623 720205",
    "sg:postcode":"NG18 4BX",
    "sg:province":"Nottinghamshire",
    "sg:tags":[
        "modification",
        "garage"
    ],
    "wof:name":"Derby Rd Repairs",
    "wof:placetype":"venue"
},
  "geometry": {"coordinates":[-1.1914949417,53.1356277466],"type":"Point"}
}