{
  "type": "Feature",
  "properties": {
    "iso:country":"GB",
    "sg:address":"29 George St",
    "sg:city":"Oxford",
    "sg:classifiers":[
        {
            "category":"Bars & Pubs",
            "subcategory":"Wine Bar",
            "type":"Food & Drink"
        }
    ],
    "sg:phone":"+44 1865 726036",
    "sg:postcode":"OX1 2AY",
    "sg:province":"Oxfordshire",
    "wof:name":"Yes But",
    "wof:placetype":"venue"
},
  "geometry": {"coordinates":[-1.2602989674,51.7535820007],"type":"Point"}
}