{
  "type": "Feature",
  "properties": {
    "iso:country":"GB",
    "sg:address":"55 Maryborough Road",
    "sg:city":"Prestwick",
    "sg:classifiers":[
        {
            "category":"Real Estate",
            "subcategory":"Developer",
            "type":"Services"
        },
        {
            "category":"Building & Trades",
            "subcategory":"Construction",
            "type":"Services"
        }
    ],
    "sg:phone":"+44 1292 478288",
    "sg:postcode":"KA9 1SW",
    "sg:province":"South Ayrshire",
    "sg:tags":[
        "residential",
        "builder",
        "property"
    ],
    "wof:name":"Dalgarven Homes Ltd",
    "wof:placetype":"venue"
},
  "geometry": {"coordinates":[-4.6253600121,55.4902496338],"type":"Point"}
}