{
  "type": "Feature",
  "properties": {
    "addr:full":"1 Pepper Road, Calverton Nottingham Nottinghamshire NG14 6LJ",
    "addr:housenumber":"1",
    "addr:postcode":"ng14 6lj",
    "addr:street":"Pepper Road",
    "iso:country":"GB",
    "sg:address":"1 Pepper Road, Calverton",
    "sg:city":"Nottingham",
    "sg:classifiers":[
        {
            "category":"Building & Trades",
            "subcategory":"Cleaning & Sanitation",
            "type":"Services"
        }
    ],
    "sg:phone":"+44 115 965 2657",
    "sg:postcode":"NG14 6LJ",
    "sg:province":"Nottinghamshire",
    "sg:tags":[
        "sweep",
        "chimney"
    ],
    "wof:name":"Vivian Leaper",
    "wof:placetype":"venue"
},
  "geometry": {"coordinates":[-1.089323,53.04023],"type":"Point"}
}