{
  "type": "Feature",
  "properties": {
    "iso:country":"GB",
    "sg:address":"The Lodge, Premier Business Park",
    "sg:city":"Walsall",
    "sg:classifiers":[
        {
            "category":"Home & Garden",
            "subcategory":"Household Appliances",
            "type":"Retail Goods"
        },
        {
            "category":"Retail",
            "subcategory":"Repair Shop",
            "type":"Services"
        }
    ],
    "sg:phone":"+44 1922 632774",
    "sg:postcode":"WS2 9DY",
    "sg:province":"West Midlands",
    "sg:tags":[
        "video",
        "television",
        "domestic",
        "radio",
        "centre"
    ],
    "wof:name":"Beaver Electronic Services Ltd.",
    "wof:placetype":"venue"
},
  "geometry": {"coordinates":[-1.9905699492,52.5814590454],"type":"Point"}
}