{
  "type": "Feature",
  "properties": {
    "addr:full":"4 Treveneth Pl Penzance Cornwall TR18 5NQ",
    "addr:housenumber":"4",
    "addr:postcode":"tr18 5nq",
    "addr:street":"Treveneth Pl",
    "iso:country":"GB",
    "sg:address":"4 Treveneth Pl",
    "sg:city":"Penzance",
    "sg:classifiers":[
        {
            "category":"Shopping",
            "subcategory":"Computers & Home Electronics",
            "type":"Retail Goods"
        }
    ],
    "sg:phone":"+44 1736 365013",
    "sg:postcode":"TR18 5NQ",
    "sg:province":"Cornwall",
    "sg:tags":[
        "aerial",
        "television",
        "radio"
    ],
    "wof:name":"Aerial Services",
    "wof:placetype":"venue"
},
  "geometry": {"coordinates":[-5.5520777702,50.0976982117],"type":"Point"}
}