{
  "type": "Feature",
  "properties": {
    "addr:full":"Lushington House, Middleton Road Camberley Berkshire GU15 3TU",
    "addr:postcode":"gu15 3tu",
    "addr:street":"Middleton Road",
    "iso:country":"GB",
    "sg:address":"Lushington House, Middleton Road",
    "sg:city":"Camberley",
    "sg:classifiers":[
        {
            "category":"Education",
            "subcategory":"Special Training",
            "type":"Public Place"
        }
    ],
    "sg:postcode":"GU15 3TU",
    "sg:province":"Berkshire",
    "sg:tags":[
        "product",
        "centre"
    ],
    "wof:name":"Training Resources Ltd",
    "wof:placetype":"venue"
},
  "geometry": {"coordinates":[-0.7264209986,51.3444213867],"type":"Point"}
}