{
  "type": "Feature",
  "properties": {
    "iso:country":"GB",
    "sg:address":"176 Henleaze Road",
    "sg:city":"Bristol",
    "sg:classifiers":[
        {
            "category":"Food & Beverages",
            "subcategory":"Specialty",
            "type":"Retail Goods"
        }
    ],
    "sg:phone":"+44 117 962 1115",
    "sg:postcode":"BS9 4NE",
    "sg:province":"City of Bristol",
    "sg:tags":[
        "product",
        "health"
    ],
    "wof:name":"The Bay Tree",
    "wof:placetype":"venue"
},
  "geometry": {"coordinates":[-2.609079,51.487282],"type":"Point"}
}