{
  "type": "Feature",
  "properties": {
    "addr:full":"Ghyll Way, Airedale Business Centre Skipton Lancashire BD23 2TZ",
    "addr:housenumber":"business",
    "addr:postcode":"bd23 2tz",
    "addr:street":"Ghyll Way Airedale;Centre Skipton",
    "iso:country":"GB",
    "sg:address":"Ghyll Way, Airedale Business Centre",
    "sg:city":"Skipton",
    "sg:classifiers":[
        {
            "category":"Wholesale",
            "subcategory":"Construction Materials",
            "type":"Manufacturing & Wholesale Goods"
        }
    ],
    "sg:phone":"+44 1756 797979",
    "sg:postcode":"BD23 2TZ",
    "sg:province":"Lancashire",
    "sg:tags":[
        "distributor",
        "spring"
    ],
    "wof:name":"John Binns & Son (Springs) Ltd.",
    "wof:placetype":"venue"
},
  "geometry": {"coordinates":[-2.0156478882,53.942325592],"type":"Point"}
}