{
  "type": "Feature",
  "properties": {
    "iso:country":"GB",
    "sg:address":"Ty Myrddin, Dan Y Banc Road",
    "sg:city":"Carmarthen",
    "sg:classifiers":[
        {
            "category":"Social Services",
            "type":"Services"
        }
    ],
    "sg:phone":"+44 1267 322100",
    "sg:postcode":"SA31 1GS",
    "sg:province":"Carmarthenshire",
    "sg:tags":[
        "benefit",
        "agency"
    ],
    "wof:name":"Department for Work & Pensions",
    "wof:placetype":"venue"
},
  "geometry": {"coordinates":[-4.2994041443,51.8602752686],"type":"Point"}
}