{
  "type": "Feature",
  "properties": {
    "addr:full":"Telegraph Way, Morn Hill Winchester Hampshire SO21 1HX",
    "addr:postcode":"so21 1hx",
    "addr:street":"Telegraph Way Morn Hill",
    "iso:country":"GB",
    "sg:address":"Telegraph Way, Morn Hill",
    "sg:city":"Winchester",
    "sg:classifiers":[
        {
            "category":"Organizations",
            "subcategory":"Non-profit Organization",
            "type":"Services"
        }
    ],
    "sg:phone":"+44 1962 863791",
    "sg:postcode":"SO21 1HX",
    "sg:province":"Hampshire",
    "sg:tags":[
        "organisation",
        "voluntary",
        "charity"
    ],
    "wof:name":"The Hampshire Tech Centre Trust Ltd.",
    "wof:placetype":"venue"
},
  "geometry": {"coordinates":[-1.2632139921,51.0608253479],"type":"Point"}
}