{
  "type": "Feature",
  "properties": {
    "iso:country":"GB",
    "sg:address":"15 Effinch Lane, Barton-under-needwooeffinch",
    "sg:city":"Burton-on-trent",
    "sg:classifiers":[
        {
            "category":"Building & Trades",
            "subcategory":"Landscaping Services",
            "type":"Services"
        }
    ],
    "sg:postcode":"DE11 8ET",
    "sg:province":"Derbyshire",
    "sg:tags":[
        "landscape",
        "contractor"
    ],
    "wof:name":"Jayco Landscapes",
    "wof:placetype":"venue"
},
  "geometry": {"coordinates":[-1.6477,52.804352],"type":"Point"}
}