{
  "type": "Feature",
  "properties": {
    "iso:country":"GB",
    "sg:address":"Holmescales Farm",
    "sg:city":"Kendal",
    "sg:classifiers":[
        {
            "category":"Shopping",
            "subcategory":"Pets & Pet Supplies",
            "type":"Retail Goods"
        }
    ],
    "sg:phone":"+44 1539 734163",
    "sg:postcode":"LA8 0NB",
    "sg:province":"Cumbria",
    "sg:tags":[
        "food"
    ],
    "wof:name":"Franklands Feeds",
    "wof:placetype":"venue"
},
  "geometry": {"coordinates":[-2.6796689034,54.2908401489],"type":"Point"}
}