{
  "type": "Feature",
  "properties": {
    "iso:country":"GB",
    "sg:address":"7 Tan-y-grisiau Terrace",
    "sg:city":"Criccieth",
    "sg:classifiers":[
        {
            "category":"Shopping",
            "subcategory":"Stationery & Office Supplies",
            "type":"Retail Goods"
        }
    ],
    "sg:postcode":"LL52 0DL",
    "sg:province":"Gwynedd",
    "wof:name":"Craig McKenzie",
    "wof:placetype":"venue"
},
  "geometry": {"coordinates":[-4.232244,52.919266],"type":"Point"}
}