{
  "type": "Feature",
  "properties": {
    "addr:full":"88-92 Alfreton Road Nottingham Nottinghamshire NG7 3NN",
    "addr:housenumber":"88-92",
    "addr:postcode":"ng7 3nn",
    "addr:street":"Alfreton Road",
    "iso:country":"GB",
    "sg:address":"88-92 Alfreton Road",
    "sg:city":"Nottingham",
    "sg:classifiers":[
        {
            "category":"Professional",
            "subcategory":"Detective & Security Services",
            "type":"Services"
        },
        {
            "category":"Building & Trades",
            "subcategory":"Locksmith",
            "type":"Services"
        }
    ],
    "sg:phone":"+44 115 978 0141",
    "sg:postcode":"NG7 3NN",
    "sg:province":"Nottinghamshire",
    "wof:name":"Halls Locksmiths Ltd.",
    "wof:placetype":"venue"
},
  "geometry": {"coordinates":[-1.1650170088,52.9577407837],"type":"Point"}
}