{
  "type": "Feature",
  "properties": {
    "addr:full":"65 Grove Road Romford Essex RM6 4PD",
    "addr:housenumber":"65",
    "addr:postcode":"rm6 4pd",
    "addr:street":"Grove Road",
    "iso:country":"GB",
    "sg:address":"65 Grove Road",
    "sg:city":"Romford",
    "sg:classifiers":[
        {
            "category":"Shopping",
            "subcategory":"News",
            "type":"Retail Goods"
        }
    ],
    "sg:phone":"+44 20 8590 2643",
    "sg:postcode":"RM6 4PD",
    "sg:province":"Essex",
    "sg:tags":[
        "newsagent"
    ],
    "wof:name":"Grovr Road Newsagents & Off Licence",
    "wof:placetype":"venue"
},
  "geometry": {"coordinates":[0.1201739982,51.5708007812],"type":"Point"}
}