{
  "type": "Feature",
  "properties": {
    "iso:country":"GB",
    "sg:address":"94 Woodcote Way, Caversham Heights",
    "sg:city":"Reading",
    "sg:classifiers":[
        {
            "category":"Shopping",
            "subcategory":"Musical Instruments",
            "type":"Retail Goods"
        }
    ],
    "sg:postcode":"RG4 7HP",
    "sg:province":"Berkshire",
    "wof:name":"Paul Corby Piano Tuning",
    "wof:placetype":"venue"
},
  "geometry": {"coordinates":[-0.9951,51.483089],"type":"Point"}
}