{
  "type": "Feature",
  "properties": {
    "addr:full":"Royal Veterinary College, Royal College Street London Greater London NW1 0TU",
    "addr:postcode":"nw1 0tu",
    "addr:street":"College Street",
    "iso:country":"GB",
    "sg:address":"Royal Veterinary College, Royal College Street",
    "sg:city":"London",
    "sg:classifiers":[
        {
            "category":"Professional",
            "subcategory":"Computer Services",
            "type":"Services"
        }
    ],
    "sg:phone":"+44 20 7388 7003",
    "sg:postcode":"NW1 0TU",
    "sg:province":"Greater London",
    "sg:tags":[
        "information"
    ],
    "wof:name":"Wildlife Information Network",
    "wof:placetype":"venue"
},
  "geometry": {"coordinates":[-0.1335,51.5368],"type":"Point"}
}