{
  "type": "Feature",
  "properties": {
    "iso:country":"GB",
    "sg:address":"18 Hanover Street, 1st Floor",
    "sg:city":"Edinburgh",
    "sg:classifiers":[
        {
            "category":"Education",
            "subcategory":"Special Training",
            "type":"Public Place"
        }
    ],
    "sg:phone":"+44 131 539 7097",
    "sg:postcode":"EH2 2EN",
    "sg:province":"City of Edinburgh",
    "sg:tags":[
        "product",
        "centre"
    ],
    "wof:name":"Lothian Management Centre",
    "wof:placetype":"venue"
},
  "geometry": {"coordinates":[-3.197019,55.952621],"type":"Point"}
}