{
  "type": "Feature",
  "properties": {
    "iso:country":"GB",
    "sg:address":"High Street",
    "sg:city":"Rochester",
    "sg:classifiers":[
        {
            "category":"Autos & Motor Vehicles",
            "subcategory":"Motorcycle Sales",
            "type":"Retail Goods"
        }
    ],
    "sg:phone":"+44 1634 845512",
    "sg:postcode":"ME1 1QB",
    "sg:province":"Kent",
    "wof:name":"Chambers of Rochester Ltd.",
    "wof:placetype":"venue"
},
  "geometry": {"coordinates":[0.503018,51.390526],"type":"Point"}
}