{
  "type": "Feature",
  "properties": {
    "iso:country":"GB",
    "sg:address":"21 London Street",
    "sg:city":"Fleetwood",
    "sg:classifiers":[
        {
            "category":"Personal",
            "subcategory":"Beauty Salon",
            "type":"Services"
        },
        {
            "category":"Education",
            "subcategory":"Dance Studio",
            "type":"Public Place"
        }
    ],
    "sg:phone":"+44 1253 773080",
    "sg:postcode":"FY7 6JE",
    "sg:province":"Lancashire",
    "sg:tags":[
        "unisex",
        "hairdresser",
        "toning"
    ],
    "wof:name":"Fleetwood Tanning Centre",
    "wof:placetype":"venue"
},
  "geometry": {"coordinates":[-3.0122900009,53.922908783],"type":"Point"}
}