{
  "type": "Feature",
  "properties": {
    "iso:country":"GB",
    "sg:address":"Cornel Farm, Maesycrugiau",
    "sg:city":"Pencader",
    "sg:classifiers":[
        {
            "category":"Farming",
            "subcategory":"Livestock Farm",
            "type":"Manufacturing & Wholesale Goods"
        }
    ],
    "sg:phone":"+44 1570 480337",
    "sg:postcode":"SA39 9DL",
    "sg:province":"Carmarthenshire",
    "sg:tags":[
        "others"
    ],
    "wof:name":"David Daniel James",
    "wof:placetype":"venue"
},
  "geometry": {"coordinates":[-4.2658638954,52.0002288818],"type":"Point"}
}