{
  "type": "Feature",
  "properties": {
    "addr:full":"189 High Street Herne Bay Kent CT6 5AF",
    "addr:housenumber":"189",
    "addr:postcode":"ct6 5af",
    "addr:street":"High Street",
    "iso:country":"GB",
    "sg:address":"189 High Street",
    "sg:city":"Herne Bay",
    "sg:classifiers":[
        {
            "category":"Real Estate",
            "subcategory":"Real Estate Agent",
            "type":"Services"
        }
    ],
    "sg:phone":"+44 1227 367225",
    "sg:postcode":"CT6 5AF",
    "sg:province":"Kent",
    "wof:name":"Harvey Richards J",
    "wof:placetype":"venue"
},
  "geometry": {"coordinates":[1.131544,51.371506],"type":"Point"}
}