{
  "type": "Feature",
  "properties": {
    "iso:country":"GB",
    "sg:address":"170 Clive Street",
    "sg:city":"Cardiff",
    "sg:classifiers":[
        {
            "category":"Home & Garden",
            "subcategory":"Furniture",
            "type":"Retail Goods"
        }
    ],
    "sg:postcode":"CF11 7JF",
    "sg:province":"Cardiff",
    "wof:name":"M E Atkins",
    "wof:placetype":"venue"
},
  "geometry": {"coordinates":[-3.187136,51.46426],"type":"Point"}
}