{
  "type": "Feature",
  "properties": {
    "iso:country":"GB",
    "sg:address":"1 Beal Terrace, Milnrow",
    "sg:city":"Rochdale",
    "sg:classifiers":[
        {
            "category":"Manufacturing",
            "subcategory":"Wood Products",
            "type":"Manufacturing & Wholesale Goods"
        },
        {
            "category":"Building & Trades",
            "subcategory":"Construction",
            "type":"Services"
        }
    ],
    "sg:phone":"+44 1706 359922",
    "sg:postcode":"OL16 4HN",
    "sg:province":"Lancashire",
    "sg:tags":[
        "joinery",
        "manufacturer"
    ],
    "wof:name":"NEIL COCKER",
    "wof:placetype":"venue"
},
  "geometry": {"coordinates":[-2.134481,53.624134],"type":"Point"}
}