{
  "type": "Feature",
  "properties": {
    "addr:full":"87 Salisbury Avenue, Warden Hill Cheltenham Gloucestershire GL51 3DA",
    "addr:housenumber":"87",
    "addr:postcode":"gl51 3da",
    "addr:street":"Salisbury Avenue Warden Hill",
    "iso:country":"GB",
    "sg:address":"87 Salisbury Avenue, Warden Hill",
    "sg:city":"Cheltenham",
    "sg:classifiers":[
        {
            "category":"Personal",
            "subcategory":"Beauty Salon",
            "type":"Services"
        }
    ],
    "sg:phone":"+44 1242 522563",
    "sg:postcode":"GL51 3DA",
    "sg:province":"Gloucestershire",
    "sg:tags":[
        "ladies",
        "lady",
        "hairdresser"
    ],
    "wof:name":"Snips & Curls",
    "wof:placetype":"venue"
},
  "geometry": {"coordinates":[-2.100372,51.882294],"type":"Point"}
}