{
  "type": "Feature",
  "properties": {
    "addr:full":"St James Crescent Darwen Lancashire BB3 0EY",
    "addr:postcode":"bb3 0ey",
    "addr:street":"St James Crescent",
    "iso:country":"GB",
    "sg:address":"St James Crescent",
    "sg:city":"Darwen",
    "sg:classifiers":[
        {
            "category":"Social Services",
            "subcategory":"Retirement Home",
            "type":"Services"
        }
    ],
    "sg:phone":"+44 1254 873623",
    "sg:postcode":"BB3 0EY",
    "sg:province":"Lancashire",
    "sg:tags":[
        "residential",
        "care"
    ],
    "wof:name":"St. James House Residential Home",
    "wof:placetype":"venue"
},
  "geometry": {"coordinates":[-2.463128,53.701412],"type":"Point"}
}