{
  "type": "Feature",
  "properties": {
    "iso:country":"GB",
    "sg:address":"Pedmore Road, Woodside",
    "sg:city":"Dudley",
    "sg:classifiers":[
        {
            "category":"Home & Garden",
            "subcategory":"Home Furnishings",
            "type":"Retail Goods"
        }
    ],
    "sg:phone":"+44 1384 480333",
    "sg:postcode":"DY2 0RE",
    "sg:province":"West Midlands",
    "sg:tags":[
        "tube",
        "fitting",
        "stockist"
    ],
    "wof:name":"S S E Pipe Fittings Ltd.",
    "wof:placetype":"venue"
},
  "geometry": {"coordinates":[-2.105491,52.494175],"type":"Point"}
}