{
  "type": "Feature",
  "properties": {
    "addr:full":"38 Preston Old Road Blackpool Lancashire FY3 9PL",
    "addr:housenumber":"38",
    "addr:postcode":"fy3 9pl",
    "addr:street":"Preston Old Road",
    "iso:country":"GB",
    "sg:address":"38 Preston Old Road",
    "sg:city":"Blackpool",
    "sg:classifiers":[
        {
            "category":"Bars & Pubs",
            "type":"Food & Drink"
        }
    ],
    "sg:phone":"+44 1253 693579",
    "sg:postcode":"FY3 9PL",
    "sg:province":"Lancashire",
    "sg:tags":[
        "pubs",
        "inn"
    ],
    "wof:name":"Punch Retail Ltd.",
    "wof:placetype":"venue"
},
  "geometry": {"coordinates":[-3.027047,53.806488],"type":"Point"}
}