{
  "type": "Feature",
  "properties": {
    "addr:full":"22 Gorsehill Gateshead Tyne and Wear NE9 6SH",
    "addr:housenumber":"22",
    "addr:postcode":"ne9 6sh",
    "addr:street":"Gorsehill",
    "iso:country":"GB",
    "sg:address":"22 Gorsehill",
    "sg:city":"Gateshead",
    "sg:classifiers":[
        {
            "category":"Bus Charters",
            "type":"Transportation"
        }
    ],
    "sg:phone":"+44 191 422 6182",
    "sg:postcode":"NE9 6SH",
    "sg:province":"Tyne and Wear",
    "sg:tags":[
        "hire",
        "coach"
    ],
    "wof:name":"Angel Minibus Hire",
    "wof:placetype":"venue"
},
  "geometry": {"coordinates":[-1.5753530264,54.9362373352],"type":"Point"}
}