{
  "type": "Feature",
  "properties": {
    "addr:full":"41 Bluecoat Chambers, School Lane Liverpool Merseyside L1 3BX",
    "addr:housenumber":"41",
    "addr:postcode":"l1 3bx",
    "addr:street":"School Lane",
    "iso:country":"GB",
    "sg:address":"41 Bluecoat Chambers, School Lane",
    "sg:city":"Liverpool",
    "sg:classifiers":[
        {
            "category":"Professional",
            "subcategory":"Art Services",
            "type":"Services"
        }
    ],
    "sg:phone":"+44 151 708 6808",
    "sg:postcode":"L1 3BX",
    "sg:province":"Merseyside",
    "sg:tags":[
        "picture",
        "restoration",
        "cleaning"
    ],
    "wof:name":"H.A Owen-hughes",
    "wof:placetype":"venue"
},
  "geometry": {"coordinates":[-2.9784810543,53.4097747803],"type":"Point"}
}