{
  "type": "Feature",
  "properties": {
    "iso:country":"GB",
    "sg:address":"Trintiy Court Church Street",
    "sg:city":"Rickmansworth",
    "sg:classifiers":[
        {
            "category":"Building & Trades",
            "subcategory":"Construction",
            "type":"Services"
        }
    ],
    "sg:phone":"+44 1923 484848",
    "sg:postcode":"WD3 1RT",
    "sg:province":"Hertfordshire",
    "sg:tags":[
        "contractor"
    ],
    "wof:name":"Magnesium Elektron Ltd",
    "wof:placetype":"venue"
},
  "geometry": {"coordinates":[-0.469056,51.638428],"type":"Point"}
}