{
  "type": "Feature",
  "properties": {
    "addr:full":"Puma House, Preston Street Bradford West Yorkshire BD7 1JE",
    "addr:postcode":"bd7 1je",
    "addr:street":"Preston Street",
    "iso:country":"GB",
    "sg:address":"Puma House, Preston Street",
    "sg:city":"Bradford",
    "sg:classifiers":[
        {
            "category":"Professional",
            "subcategory":"Employment Agencies",
            "type":"Services"
        }
    ],
    "sg:phone":"+44 1274 778544",
    "sg:postcode":"BD7 1JE",
    "sg:province":"West Yorkshire",
    "sg:tags":[
        "consultant"
    ],
    "wof:name":"Driver Hire Bradford",
    "wof:placetype":"venue"
},
  "geometry": {"coordinates":[-1.7705,53.794109],"type":"Point"}
}