{
  "type": "Feature",
  "properties": {
    "iso:country":"GB",
    "sg:address":"66a Magdalen Lane, Wingfield",
    "sg:city":"Trowbridge",
    "sg:classifiers":[
        {
            "category":"Professional",
            "subcategory":"Engineering",
            "type":"Services"
        }
    ],
    "sg:phone":"+44 1225 777545",
    "sg:postcode":"BA14 9LQ",
    "sg:province":"Wiltshire",
    "sg:tags":[
        "instrumentation",
        "engineer"
    ],
    "wof:name":"Tierway Systems Ltd.",
    "wof:placetype":"venue"
},
  "geometry": {"coordinates":[-2.260605,51.315228],"type":"Point"}
}