{
  "type": "Feature",
  "properties": {
    "addr:full":"46 Cargo Fleet Lane Middlesbrough North Yorkshire TS3 0PL",
    "addr:housenumber":"46",
    "addr:postcode":"ts3 0pl",
    "addr:street":"Cargo Fleet Lane",
    "iso:country":"GB",
    "sg:address":"46 Cargo Fleet Lane",
    "sg:city":"Middlesbrough",
    "sg:classifiers":[
        {
            "category":"Shopping",
            "subcategory":"News",
            "type":"Retail Goods"
        }
    ],
    "sg:phone":"+44 1642 314558",
    "sg:postcode":"TS3 0PL",
    "sg:province":"North Yorkshire",
    "sg:tags":[
        "newsagent"
    ],
    "wof:name":"Hillsons",
    "wof:placetype":"venue"
},
  "geometry": {"coordinates":[-1.182363987,54.5531158447],"type":"Point"}
}