{
  "type": "Feature",
  "properties": {
    "addr:full":"56 Lady Street Kidwelly Carmarthenshire SA17 4UD",
    "addr:housenumber":"56",
    "addr:postcode":"sa17 4ud",
    "addr:street":"Lady Street",
    "iso:country":"GB",
    "sg:address":"56 Lady Street",
    "sg:city":"Kidwelly",
    "sg:classifiers":[
        {
            "category":"Bars & Pubs",
            "type":"Food & Drink"
        }
    ],
    "sg:phone":"+44 1554 890250",
    "sg:postcode":"SA17 4UD",
    "sg:province":"Carmarthenshire",
    "sg:tags":[
        "pubs",
        "house",
        "inn",
        "public",
        "activity"
    ],
    "wof:name":"The Plough & Harrow",
    "wof:placetype":"venue"
},
  "geometry": {"coordinates":[-4.3039259911,51.7369384766],"type":"Point"}
}