{
  "type": "Feature",
  "properties": {
    "iso:country":"GB",
    "sg:address":"1 Portways Farm Cotts, Cuckfield Lane, Warninglid",
    "sg:city":"Haywards Heath",
    "sg:classifiers":[
        {
            "category":"Building & Trades",
            "subcategory":"Construction",
            "type":"Services"
        }
    ],
    "sg:postcode":"RH17 5SN",
    "sg:province":"East Sussex",
    "sg:tags":[
        "tiling",
        "flooring",
        "contractor"
    ],
    "wof:name":"Simon Taylor",
    "wof:placetype":"venue"
},
  "geometry": {"coordinates":[-0.1406289935,51.0108146667],"type":"Point"}
}