{
  "type": "Feature",
  "properties": {
    "iso:country":"GB",
    "sg:address":"22b Leslie Sq, Aldridge Rd",
    "sg:city":"Birmingham",
    "sg:classifiers":[
        {
            "category":"Travel",
            "subcategory":"Travel Agent",
            "type":"Entertainment"
        }
    ],
    "sg:phone":"+44 121 688 8833",
    "sg:postcode":"B44 8NH",
    "sg:province":"West Midlands",
    "wof:name":"Interchoice Holidays",
    "wof:placetype":"venue"
},
  "geometry": {"coordinates":[-1.89786,52.533829],"type":"Point"}
}