{
  "type": "Feature",
  "properties": {
    "addr:full":"Victoria Road Skegness Lincolnshire PE25 3SL",
    "addr:postcode":"pe25 3sl",
    "addr:street":"Victoria Road",
    "iso:country":"GB",
    "sg:address":"Victoria Road",
    "sg:city":"Skegness",
    "sg:classifiers":[
        {
            "category":"Retail",
            "subcategory":"Auto Repair",
            "type":"Services"
        }
    ],
    "sg:phone":"+44 1754 766217",
    "sg:postcode":"PE25 3SL",
    "sg:province":"Lincolnshire",
    "sg:tags":[
        "modification",
        "garage"
    ],
    "wof:name":"Hudson Motors",
    "wof:placetype":"venue"
},
  "geometry": {"coordinates":[0.329468,53.144077],"type":"Point"}
}