{
  "type": "Feature",
  "properties": {
    "iso:country":"GB",
    "sg:address":"11 Eltham Avenue, Great Moor",
    "sg:city":"Stockport",
    "sg:classifiers":[
        {
            "category":"Professional",
            "subcategory":"Detective & Security Services",
            "type":"Services"
        }
    ],
    "sg:phone":"+44 161 456 1235",
    "sg:postcode":"SK2 7PJ",
    "sg:province":"Cheshire",
    "sg:tags":[
        "locksmith"
    ],
    "wof:name":"Great Moor Lock & Key Service",
    "wof:placetype":"venue"
},
  "geometry": {"coordinates":[-2.135295,53.389919],"type":"Point"}
}