{
  "type": "Feature",
  "properties": {
    "addr:full":"34 Grange Road, West Kirby Wirral Merseyside CH48 4EF",
    "addr:housenumber":"34",
    "addr:postcode":"ch48 4ef",
    "addr:street":"Grange Road",
    "iso:country":"GB",
    "sg:address":"34 Grange Road, West Kirby",
    "sg:city":"Wirral",
    "sg:classifiers":[
        {
            "category":"Professional",
            "subcategory":"Lawyer & Legal Services",
            "type":"Services"
        }
    ],
    "sg:phone":"+44 151 625 9154",
    "sg:postcode":"CH48 4EF",
    "sg:province":"Merseyside",
    "sg:tags":[
        "solicitor"
    ],
    "wof:name":"Maxwell Entwistle & Byrne",
    "wof:placetype":"venue"
},
  "geometry": {"coordinates":[-3.183318,53.37281],"type":"Point"}
}