{
  "type": "Feature",
  "properties": {
    "addr:full":"115-117 Spone Lane West Bromwich West Midlands B70 6AS",
    "addr:housenumber":"115-117",
    "addr:postcode":"b70 6as",
    "addr:street":"Spone Lane West",
    "iso:country":"GB",
    "sg:address":"115-117 Spone Lane",
    "sg:city":"West Bromwich",
    "sg:classifiers":[
        {
            "category":"Shopping",
            "subcategory":"Clothing, Apparel, & Fashions",
            "type":"Retail Goods"
        }
    ],
    "sg:phone":"+44 121 525 6428",
    "sg:postcode":"B70 6AS",
    "sg:province":"West Midlands",
    "sg:tags":[
        "clothing"
    ],
    "wof:name":"Charlie Browns",
    "wof:placetype":"venue"
},
  "geometry": {"coordinates":[-1.9918249846,52.5125579834],"type":"Point"}
}