{
  "type": "Feature",
  "properties": {
    "addr:full":"65 Chatsworth Road London Greater London E5 0LH",
    "addr:housenumber":"65",
    "addr:postcode":"e5 0lh",
    "addr:street":"Chatsworth Road",
    "iso:country":"GB",
    "sg:address":"65 Chatsworth Road",
    "sg:city":"London",
    "sg:classifiers":[
        {
            "category":"Personal",
            "subcategory":"Beauty Salon",
            "type":"Services"
        },
        {
            "category":"Personal",
            "subcategory":"Barber",
            "type":"Services"
        }
    ],
    "sg:phone":"+44 20 8985 5465",
    "sg:postcode":"E5 0LH",
    "sg:province":"Greater London",
    "sg:tags":[
        "unisex",
        "hairdresser"
    ],
    "wof:name":"Edward Hair Fashions",
    "wof:placetype":"venue"
},
  "geometry": {"coordinates":[-0.0450620018,51.5535392761],"type":"Point"}
}