{
  "type": "Feature",
  "properties": {
    "iso:country":"GB",
    "sg:address":"60 Commercial Road, Skelmanthorpe",
    "sg:city":"Huddersfield",
    "sg:classifiers":[
        {
            "category":"Fast Food",
            "type":"Food & Drink"
        }
    ],
    "sg:phone":"+44 1484 863130",
    "sg:postcode":"HD8 9DS",
    "sg:province":"South Yorkshire",
    "sg:tags":[
        "away",
        "take"
    ],
    "wof:name":"Jimbo",
    "wof:placetype":"venue"
},
  "geometry": {"coordinates":[-1.648751,53.591335],"type":"Point"}
}