{
  "type": "Feature",
  "properties": {
    "iso:country":"GB",
    "sg:address":"65 Grosvenor Road",
    "sg:city":"Shipley",
    "sg:classifiers":[
        {
            "category":"Building & Trades",
            "subcategory":"Plumbing",
            "type":"Services"
        },
        {
            "category":"Utilities",
            "subcategory":"Telephone",
            "type":"Services"
        }
    ],
    "sg:phone":"+44 1274 597240",
    "sg:postcode":"BD18 4RB",
    "sg:province":"West Yorkshire",
    "sg:tags":[
        "telecom",
        "heating"
    ],
    "wof:name":"RAYMOND GRAYSON",
    "wof:placetype":"venue"
},
  "geometry": {"coordinates":[-1.793446,53.830917],"type":"Point"}
}