{
  "type": "Feature",
  "properties": {
    "iso:country":"GB",
    "sg:address":"21 Woodfield St",
    "sg:city":"Swansea",
    "sg:classifiers":[
        {
            "category":"Banks & Credit Unions",
            "subcategory":"Bank",
            "type":"Services"
        }
    ],
    "sg:phone":"+44 1792 771800",
    "sg:postcode":"SA6 8AQ",
    "sg:province":"Swansea",
    "wof:name":"NatWest",
    "wof:placetype":"venue"
},
  "geometry": {"coordinates":[-3.925578,51.665287],"type":"Point"}
}