{
  "type": "Feature",
  "properties": {
    "addr:full":"14 Moorfield Walk, Urmston Manchester Cheshire M41 0TT",
    "addr:housenumber":"14",
    "addr:postcode":"m41 0tt",
    "addr:street":"Moorfield Walk",
    "iso:country":"GB",
    "sg:address":"14 Moorfield Walk, Urmston",
    "sg:city":"Manchester",
    "sg:classifiers":[
        {
            "category":"Food & Beverages",
            "subcategory":"Supermarket",
            "type":"Retail Goods"
        }
    ],
    "sg:phone":"+44 161 748 0317",
    "sg:postcode":"M41 0TT",
    "sg:province":"Cheshire",
    "wof:name":"Gateway Food Markets",
    "wof:placetype":"venue"
},
  "geometry": {"coordinates":[-2.35448,53.449261],"type":"Point"}
}