{
  "type": "Feature",
  "properties": {
    "addr:full":"Avenue Road, Handsworth Birmingham West Midlands B21 8ED",
    "addr:postcode":"b21 8ed",
    "addr:street":"Avenue Road",
    "iso:country":"GB",
    "sg:address":"Avenue Road, Handsworth",
    "sg:city":"Birmingham",
    "sg:classifiers":[
        {
            "category":"Education",
            "subcategory":"School",
            "type":"Public Place"
        },
        {
            "category":"Government",
            "subcategory":"Office",
            "type":"Public Place"
        }
    ],
    "sg:phone":"+44 121 554 5069",
    "sg:postcode":"B21 8ED",
    "sg:province":"West Midlands",
    "sg:tags":[
        "local",
        "authority"
    ],
    "wof:name":"St Augustine's R C Junior & Infant School",
    "wof:placetype":"venue"
},
  "geometry": {"coordinates":[-1.94442,52.514729],"type":"Point"}
}