{
  "type": "Feature",
  "properties": {
    "addr:full":"Ormesby Road Middlesbrough North Yorkshire TS3 0NB",
    "addr:postcode":"ts3 0nb",
    "addr:street":"Ormesby Road",
    "iso:country":"GB",
    "sg:address":"Ormesby Road",
    "sg:city":"Middlesbrough",
    "sg:classifiers":[
        {
            "category":"Autos & Motor Vehicles",
            "subcategory":"Fuel & Gas Station",
            "type":"Retail Goods"
        }
    ],
    "sg:phone":"+44 1642 303000",
    "sg:postcode":"TS3 0NB",
    "sg:province":"North Yorkshire",
    "sg:tags":[
        "petrol",
        "filling"
    ],
    "wof:name":"Shell Parkend",
    "wof:placetype":"venue"
},
  "geometry": {"coordinates":[-1.1949490309,54.5534591675],"type":"Point"}
}