{
  "type": "Feature",
  "properties": {
    "iso:country":"GB",
    "sg:address":"New Festival Lesiure Park, Cranes Farm Rd",
    "sg:city":"Basildon",
    "sg:classifiers":[
        {
            "category":"Cinema",
            "subcategory":"Movie Theater",
            "type":"Entertainment"
        }
    ],
    "sg:phone":"+44 1268 243500",
    "sg:postcode":"SS14 3TJ",
    "sg:province":"Essex",
    "wof:name":"Uci United Cinemas International Ltd",
    "wof:placetype":"venue"
},
  "geometry": {"coordinates":[0.464393,51.583912],"type":"Point"}
}