{
  "type": "Feature",
  "properties": {
    "addr:full":"188 Court Rd London Greater London SE9 4EW",
    "addr:housenumber":"188",
    "addr:postcode":"se9 4ew",
    "addr:street":"Court Rd",
    "iso:country":"GB",
    "sg:address":"188 Court Rd",
    "sg:city":"London",
    "sg:classifiers":[
        {
            "category":"Retail",
            "subcategory":"Auto Rental",
            "type":"Services"
        }
    ],
    "sg:postcode":"SE9 4EW",
    "sg:province":"Greater London",
    "sg:tags":[
        "truck",
        "hire",
        "van"
    ],
    "wof:name":"Odey,Lee,",
    "wof:placetype":"venue"
},
  "geometry": {"coordinates":[0.050409,51.438839],"type":"Point"}
}