{
  "type": "Feature",
  "properties": {
    "addr:full":"241 London Road, Charlton Kings Cheltenham Gloucestershire GL52 6YE",
    "addr:housenumber":"241",
    "addr:postcode":"gl52 6ye",
    "addr:street":"London Road",
    "iso:country":"GB",
    "sg:address":"241 London Road, Charlton Kings",
    "sg:city":"Cheltenham",
    "sg:classifiers":[
        {
            "category":"Professional",
            "subcategory":"Management & Consulting",
            "type":"Services"
        }
    ],
    "sg:phone":"+44 1242 579330",
    "sg:postcode":"GL52 6YE",
    "sg:province":"Gloucestershire",
    "sg:tags":[
        "consultant",
        "business"
    ],
    "wof:name":"Stratagies 4 Profits",
    "wof:placetype":"venue"
},
  "geometry": {"coordinates":[-2.0516269207,51.8874435425],"type":"Point"}
}