{
  "type": "Feature",
  "properties": {
    "addr:full":"1a Herald Rd, Herald Indstl Est Southampton Hampshire SO30 2JW",
    "addr:housenumber":"1a",
    "addr:postcode":"so30 2jw",
    "addr:street":"Herald Rd;Indstl Est",
    "iso:country":"GB",
    "sg:address":"1a Herald Rd, Herald Indstl Est",
    "sg:city":"Southampton",
    "sg:classifiers":[
        {
            "category":"Autos & Motor Vehicles",
            "subcategory":"Auto Supplies",
            "type":"Retail Goods"
        }
    ],
    "sg:postcode":"SO30 2JW",
    "sg:province":"Hampshire",
    "sg:tags":[
        "exhaust",
        "absorber",
        "shock"
    ],
    "wof:name":"1A Target Auto Centre",
    "wof:placetype":"venue"
},
  "geometry": {"coordinates":[-1.308704,50.925999],"type":"Point"}
}