{
  "type": "Feature",
  "properties": {
    "addr:full":"308 Garratt La Wandsworth Greater London SW18 4EH",
    "addr:housenumber":"308",
    "addr:postcode":"sw18 4eh",
    "addr:street":"Garratt La Wandsworth",
    "iso:country":"GB",
    "sg:address":"308 Garratt La",
    "sg:city":"Wandsworth",
    "sg:classifiers":[
        {
            "category":"Professional",
            "subcategory":"Accounting & Tax Preparation",
            "type":"Services"
        }
    ],
    "sg:phone":"+44 20 8875 1558",
    "sg:postcode":"SW18 4EH",
    "sg:province":"Greater London",
    "sg:tags":[
        "consultant"
    ],
    "wof:name":"Sunny Gold Real Estates Ltd",
    "wof:placetype":"venue"
},
  "geometry": {"coordinates":[-0.1904229969,51.4440193176],"type":"Point"}
}