{
  "type": "Feature",
  "properties": {
    "addr:full":"P O Box 1, Rowe House Newcastle Upon Tyne Tyne and Wear NE99 1PN",
    "addr:housenumber":"1",
    "addr:postcode":"ne99 1pn",
    "addr:street":"P O Box",
    "iso:country":"GB",
    "sg:address":"P O Box 1, Rowe House",
    "sg:city":"Newcastle Upon Tyne",
    "sg:classifiers":[
        {
            "category":"Shopping",
            "subcategory":"Books",
            "type":"Retail Goods"
        }
    ],
    "sg:phone":"+44 191 273 1421",
    "sg:postcode":"NE99 1PN",
    "sg:province":"Tyne and Wear",
    "sg:tags":[
        "bookseller"
    ],
    "wof:name":"W H Smith News",
    "wof:placetype":"venue"
},
  "geometry": {"coordinates":[-1.61577,54.967701],"type":"Point"}
}