{
  "type": "Feature",
  "properties": {
    "addr:full":"52-54 Salisbury Road Plymouth Devon PL4 8SY",
    "addr:housenumber":"52-54",
    "addr:postcode":"pl4 8sy",
    "addr:street":"Salisbury Road",
    "iso:country":"GB",
    "sg:address":"52-54 Salisbury Road",
    "sg:city":"Plymouth",
    "sg:classifiers":[
        {
            "category":"Organizations",
            "subcategory":"Community Association",
            "type":"Services"
        },
        {
            "category":"Organizations",
            "subcategory":"Membership Organization",
            "type":"Services"
        }
    ],
    "sg:phone":"+44 1752 662420",
    "sg:postcode":"PL4 8SY",
    "sg:province":"Devon",
    "sg:tags":[
        "club",
        "social"
    ],
    "wof:name":"The Saltram Club",
    "wof:placetype":"venue"
},
  "geometry": {"coordinates":[-4.1230330467,50.3757553101],"type":"Point"}
}