{
  "type": "Feature",
  "properties": {
    "addr:full":"The Garage, May Street Hartlepool Durham TS24 7BL",
    "addr:postcode":"ts24 7bl",
    "addr:street":"May Street",
    "iso:country":"GB",
    "sg:address":"The Garage, May Street",
    "sg:city":"Hartlepool",
    "sg:classifiers":[
        {
            "category":"Retail",
            "subcategory":"Auto Repair",
            "type":"Services"
        }
    ],
    "sg:phone":"+44 1429 267486",
    "sg:postcode":"TS24 7BL",
    "sg:province":"Durham",
    "sg:tags":[
        "modification",
        "garage"
    ],
    "wof:name":"Henderson Auto Repairs & Recovery Services",
    "wof:placetype":"venue"
},
  "geometry": {"coordinates":[-1.2141189575,54.6854057312],"type":"Point"}
}