{
  "type": "Feature",
  "properties": {
    "iso:country":"GB",
    "sg:address":"North Merchiston Boys Club, 48 Watson Crescent",
    "sg:city":"Edinburgh",
    "sg:classifiers":[
        {
            "category":"Education",
            "subcategory":"Special Training",
            "type":"Public Place"
        }
    ],
    "sg:postcode":"EH11 1ER",
    "sg:province":"City of Edinburgh",
    "sg:tags":[
        "martial art",
        "instruction"
    ],
    "wof:name":"Ashihara Karate",
    "wof:placetype":"venue"
},
  "geometry": {"coordinates":[-3.22261,55.937038],"type":"Point"}
}