{
  "type": "Feature",
  "properties": {
    "iso:country":"GB",
    "sg:address":"8 Talza Way",
    "sg:city":"Southend-on-sea",
    "sg:classifiers":[
        {
            "category":"Shopping",
            "subcategory":"Shoes",
            "type":"Retail Goods"
        }
    ],
    "sg:phone":"+44 1702 612888",
    "sg:postcode":"SS2 5BG",
    "sg:province":"Essex",
    "wof:name":"Presto Shoe Repairs",
    "wof:placetype":"venue"
},
  "geometry": {"coordinates":[0.70843,51.560551],"type":"Point"}
}