{
  "type": "Feature",
  "properties": {
    "addr:full":"55 Gibwood Rd, Northingdon Manchester Greater Manchester M22 4BS",
    "addr:housenumber":"55",
    "addr:postcode":"m22 4bs",
    "addr:street":"Gibwood Rd",
    "iso:country":"GB",
    "sg:address":"55 Gibwood Rd, Northingdon",
    "sg:city":"Manchester",
    "sg:classifiers":[
        {
            "category":"Building & Trades",
            "subcategory":"Construction",
            "type":"Services"
        }
    ],
    "sg:phone":"+44 161 998 0350",
    "sg:postcode":"M22 4BS",
    "sg:province":"Greater Manchester",
    "sg:tags":[
        "ventilation",
        "contractor"
    ],
    "wof:name":"Approved Damp & Timber Preservations",
    "wof:placetype":"venue"
},
  "geometry": {"coordinates":[-2.265832901,53.4028587341],"type":"Point"}
}