{
  "type": "Feature",
  "properties": {
    "iso:country":"GB",
    "sg:address":"Peters Way, Sandy Lane West",
    "sg:city":"Oxford",
    "sg:classifiers":[
        {
            "category":"Organizations",
            "subcategory":"Non-profit Organization",
            "type":"Services"
        }
    ],
    "sg:phone":"+44 1865 717070",
    "sg:postcode":"OX4 6HG",
    "sg:province":"Oxfordshire",
    "sg:tags":[
        "organisation",
        "voluntary",
        "charity"
    ],
    "wof:name":"Christian Aid",
    "wof:placetype":"venue"
},
  "geometry": {"coordinates":[-1.210664,51.723309],"type":"Point"}
}