{
  "type": "Feature",
  "properties": {
    "addr:full":"40 Bridge Road Grays Essex RM17 6BU",
    "addr:housenumber":"40",
    "addr:postcode":"rm17 6bu",
    "addr:street":"Bridge Road",
    "iso:country":"GB",
    "sg:address":"40 Bridge Road",
    "sg:city":"Grays",
    "sg:classifiers":[
        {
            "category":"Shopping",
            "subcategory":"News",
            "type":"Retail Goods"
        }
    ],
    "sg:phone":"+44 1375 372566",
    "sg:postcode":"RM17 6BU",
    "sg:province":"Essex",
    "sg:tags":[
        "newsagent"
    ],
    "wof:name":"S & N Patel",
    "wof:placetype":"venue"
},
  "geometry": {"coordinates":[0.3306429982,51.4752807617],"type":"Point"}
}