{
  "type": "Feature",
  "properties": {
    "iso:country":"GB",
    "sg:address":"15-17 Shakespear Street",
    "sg:city":"Glasgow",
    "sg:classifiers":[
        {
            "category":"Place Of Worship",
            "type":"Public Place"
        }
    ],
    "sg:phone":"+44 141 946 0466",
    "sg:postcode":"G20 8TQ",
    "sg:province":"Glasgow City",
    "wof:name":"Ruchill Church of Scotland",
    "wof:placetype":"venue"
},
  "geometry": {"coordinates":[-4.2857351303,55.8858375549],"type":"Point"}
}