{
  "type": "Feature",
  "properties": {
    "addr:full":"The Stables, 34b High St, Nash Milton Keynes Bedfordshire MK17 0EP",
    "addr:housenumber":"34b",
    "addr:postcode":"mk17 0ep",
    "addr:street":"High St",
    "iso:country":"GB",
    "sg:address":"The Stables, 34b High St, Nash",
    "sg:city":"Milton Keynes",
    "sg:classifiers":[
        {
            "category":"Building & Trades",
            "subcategory":"Construction",
            "type":"Services"
        }
    ],
    "sg:phone":"+44 1525 240919",
    "sg:postcode":"MK17 0EP",
    "sg:province":"Bedfordshire",
    "sg:tags":[
        "joinery"
    ],
    "wof:name":"Cheval Joinery",
    "wof:placetype":"venue"
},
  "geometry": {"coordinates":[-0.8612999916,51.9996185303],"type":"Point"}
}