{
  "type": "Feature",
  "properties": {
    "iso:country":"GB",
    "sg:address":"Curzon Business Centre, Curzon Street",
    "sg:city":"Burton-on-trent",
    "sg:classifiers":[
        {
            "category":"Manufacturing",
            "subcategory":"Pottery",
            "type":"Manufacturing & Wholesale Goods"
        }
    ],
    "sg:phone":"+44 1283 511556",
    "sg:postcode":"DE14 2DH",
    "sg:province":"Derbyshire",
    "wof:name":"Diamond Print & Ceramics",
    "wof:placetype":"venue"
},
  "geometry": {"coordinates":[-1.647701,52.804352],"type":"Point"}
}