{
  "type": "Feature",
  "properties": {
    "addr:full":"Assembly Rooms, Market Place Derby Derbyshire DE1 3AH",
    "addr:postcode":"de1 3ah",
    "addr:street":"Market Place",
    "iso:country":"GB",
    "sg:address":"Assembly Rooms, Market Place",
    "sg:city":"Derby",
    "sg:classifiers":[
        {
            "category":"Professional",
            "type":"Services"
        }
    ],
    "sg:phone":"+44 1332 368508",
    "sg:postcode":"DE1 3AH",
    "sg:province":"Derbyshire",
    "sg:tags":[
        "caterer"
    ],
    "wof:name":"Bromwich Catering Ltd",
    "wof:placetype":"venue"
},
  "geometry": {"coordinates":[-1.4836839437,52.9251708984],"type":"Point"}
}