{
  "type": "Feature",
  "properties": {
    "addr:full":"4 Chakeshill Close, Brentry Bristol City of Bristol BS10 6NX",
    "addr:housenumber":"4",
    "addr:postcode":"bs10 6nx",
    "addr:street":"Chakeshill Close",
    "iso:country":"GB",
    "sg:address":"4 Chakeshill Close, Brentry",
    "sg:city":"Bristol",
    "sg:classifiers":[
        {
            "category":"Building & Trades",
            "subcategory":"Construction",
            "type":"Services"
        }
    ],
    "sg:phone":"+44 117 950 6205",
    "sg:postcode":"BS10 6NX",
    "sg:province":"City of Bristol",
    "sg:tags":[
        "builder"
    ],
    "wof:name":"B Robinson Building Services",
    "wof:placetype":"venue"
},
  "geometry": {"coordinates":[-2.602686,51.511509],"type":"Point"}
}