{
  "type": "Feature",
  "properties": {
    "iso:country":"GB",
    "sg:address":"445 Fair Oak Road, Fair Oak",
    "sg:city":"Eastleigh",
    "sg:classifiers":[
        {
            "category":"Professional",
            "subcategory":"Accounting & Tax Preparation",
            "type":"Services"
        }
    ],
    "sg:phone":"+44 23 8060 1219",
    "sg:postcode":"SO50 7AJ",
    "sg:province":"Hampshire",
    "sg:tags":[
        "accountant"
    ],
    "wof:name":"Don Roper Accountant",
    "wof:placetype":"venue"
},
  "geometry": {"coordinates":[-1.2985639572,50.96459198],"type":"Point"}
}