{
  "type": "Feature",
  "properties": {
    "addr:full":"Po Box 309 Banbury Northamptonshire OX17 3XJ",
    "addr:housenumber":"po",
    "addr:postcode":"ox17 3xj",
    "addr:street":"Box 309",
    "iso:country":"GB",
    "sg:address":"Po Box 309",
    "sg:city":"Banbury",
    "sg:classifiers":[
        {
            "category":"Professional",
            "subcategory":"Management & Consulting",
            "type":"Services"
        }
    ],
    "sg:phone":"+44 1869 336030",
    "sg:postcode":"OX17 3XJ",
    "sg:province":"Northamptonshire",
    "sg:tags":[
        "marketing",
        "consultant"
    ],
    "wof:name":"Potential Development Ltd.",
    "wof:placetype":"venue"
},
  "geometry": {"coordinates":[-1.2783089876,52.0214500427],"type":"Point"}
}