{
  "type": "Feature",
  "properties": {
    "iso:country":"GB",
    "sg:address":"1a Purton Road",
    "sg:city":"Swindon",
    "sg:classifiers":[
        {
            "category":"Food & Beverages",
            "subcategory":"Fruits & Vegetables",
            "type":"Retail Goods"
        }
    ],
    "sg:postcode":"SN2 2LN",
    "sg:province":"Wiltshire",
    "sg:tags":[
        "greengrocer"
    ],
    "wof:name":"Gardeners Delight",
    "wof:placetype":"venue"
},
  "geometry": {"coordinates":[-1.812456,51.583736],"type":"Point"}
}