{
  "type": "Feature",
  "properties": {
    "addr:full":"4b Addington Street Ramsgate Kent CT11 9JL",
    "addr:housenumber":"4b",
    "addr:postcode":"ct11 9jl",
    "addr:street":"Addington Street Ramsgate",
    "iso:country":"GB",
    "sg:address":"4b Addington Street",
    "sg:city":"Ramsgate",
    "sg:classifiers":[
        {
            "category":"Manufacturing",
            "subcategory":"Metals",
            "type":"Manufacturing & Wholesale Goods"
        }
    ],
    "sg:phone":"+44 1843 588330",
    "sg:postcode":"CT11 9JL",
    "sg:province":"Kent",
    "sg:tags":[
        "blacksmith",
        "forgemasters"
    ],
    "wof:name":"Laytem Craft",
    "wof:placetype":"venue"
},
  "geometry": {"coordinates":[1.4141720533,51.3312606812],"type":"Point"}
}