{
  "type": "Feature",
  "properties": {
    "iso:country":"GB",
    "sg:address":"69 St Marys Road",
    "sg:city":"Portsmouth",
    "sg:classifiers":[
        {
            "category":"Fast Food",
            "type":"Food & Drink"
        }
    ],
    "sg:phone":"+44 23 9273 4729",
    "sg:postcode":"PO1 5PG",
    "sg:province":"Hampshire",
    "sg:tags":[
        "away",
        "take"
    ],
    "wof:name":"The Curry House",
    "wof:placetype":"venue"
},
  "geometry": {"coordinates":[-1.073456,50.803719],"type":"Point"}
}