{
  "type": "Feature",
  "properties": {
    "iso:country":"GB",
    "sg:address":"15 Ware Road",
    "sg:city":"Hertford",
    "sg:classifiers":[
        {
            "category":"Real Estate",
            "subcategory":"Architect",
            "type":"Services"
        }
    ],
    "sg:postcode":"SG13 7DZ",
    "sg:province":"Hertfordshire",
    "wof:name":"Michael Plastow Architect",
    "wof:placetype":"venue"
},
  "geometry": {"coordinates":[-0.0696410015,51.7980804443],"type":"Point"}
}