{
  "type": "Feature",
  "properties": {
    "iso:country":"GB",
    "sg:address":"1 Crispin Centre",
    "sg:city":"Street",
    "sg:classifiers":[
        {
            "category":"Shopping",
            "subcategory":"Department Store",
            "type":"Retail Goods"
        }
    ],
    "sg:phone":"+44 1458 442785",
    "sg:postcode":"BA16 0HP",
    "sg:province":"Somerset",
    "wof:name":"H Nicholls Sports",
    "wof:placetype":"venue"
},
  "geometry": {"coordinates":[-2.740859,51.126251],"type":"Point"}
}