{
  "type": "Feature",
  "properties": {
    "iso:country":"GB",
    "sg:address":"47 Challis Place",
    "sg:city":"Bracknell",
    "sg:classifiers":[
        {
            "category":"Professional",
            "subcategory":"Computer Services",
            "type":"Services"
        }
    ],
    "sg:phone":"+44 1344 301155",
    "sg:postcode":"RG42 1FT",
    "sg:province":"Berkshire",
    "sg:tags":[
        "system",
        "software"
    ],
    "wof:name":"Future Labs Ltd.",
    "wof:placetype":"venue"
},
  "geometry": {"coordinates":[-0.777475,51.418411],"type":"Point"}
}