{
  "type": "Feature",
  "properties": {
    "iso:country":"GB",
    "sg:address":"35 Woodford Avenue",
    "sg:city":"Ilford",
    "sg:classifiers":[
        {
            "category":"Professional",
            "subcategory":"Business Services",
            "type":"Services"
        }
    ],
    "sg:phone":"+44 20 8551 2627",
    "sg:postcode":"IG2 6UF",
    "sg:province":"Essex",
    "sg:tags":[
        "broker",
        "commodity"
    ],
    "wof:name":"Ondeck Distributors Ltd",
    "wof:placetype":"venue"
},
  "geometry": {"coordinates":[0.064319998,51.577922821],"type":"Point"}
}