{
  "type": "Feature",
  "properties": {
    "addr:full":"64 Angel Hill Sutton Surrey SM1 3EW",
    "addr:housenumber":"64",
    "addr:postcode":"sm1 3ew",
    "addr:street":"Angel Hill",
    "iso:country":"GB",
    "sg:address":"64 Angel Hill",
    "sg:city":"Sutton",
    "sg:classifiers":[
        {
            "category":"Food & Beverages",
            "subcategory":"Candy",
            "type":"Retail Goods"
        }
    ],
    "sg:phone":"+44 20 8641 8543",
    "sg:postcode":"SM1 3EW",
    "sg:province":"Surrey",
    "sg:tags":[
        "confectioner"
    ],
    "wof:name":"Angel Hill Post Office",
    "wof:placetype":"venue"
},
  "geometry": {"coordinates":[-0.193009004,51.3753700256],"type":"Point"}
}