{
  "type": "Feature",
  "properties": {
    "iso:country":"GB",
    "sg:address":"Trinity Works, Johnson St",
    "sg:city":"Sheffield",
    "sg:classifiers":[
        {
            "category":"Building & Trades",
            "subcategory":"Construction",
            "type":"Services"
        }
    ],
    "sg:phone":"+44 114 233 2189",
    "sg:postcode":"S3 8GT",
    "sg:province":"South Yorkshire",
    "sg:tags":[
        "builder"
    ],
    "wof:name":"Crofton Builders & Co",
    "wof:placetype":"venue"
},
  "geometry": {"coordinates":[-1.46468,53.388142],"type":"Point"}
}