{
  "type": "Feature",
  "properties": {
    "iso:country":"GB",
    "sg:address":"Unit 15, White Cross Indstl Est, White Cross",
    "sg:city":"Newquay",
    "sg:classifiers":[
        {
            "category":"Autos & Motor Vehicles",
            "subcategory":"Auto Supplies",
            "type":"Retail Goods"
        }
    ],
    "sg:postcode":"TR8 4LW",
    "sg:province":"Cornwall",
    "sg:tags":[
        "tyre"
    ],
    "wof:name":"Wort,N A,",
    "wof:placetype":"venue"
},
  "geometry": {"coordinates":[-4.9700880051,50.399684906],"type":"Point"}
}