{
  "type": "Feature",
  "properties": {
    "addr:full":"1 Bdwy, West Ealing London Greater London W13 9DA",
    "addr:housenumber":"1",
    "addr:postcode":"w13 9da",
    "addr:street":"Bdwy West",
    "iso:country":"GB",
    "sg:address":"1 Bdwy, West Ealing",
    "sg:city":"London",
    "sg:classifiers":[
        {
            "category":"Food & Beverages",
            "subcategory":"Bakery",
            "type":"Retail Goods"
        }
    ],
    "sg:postcode":"W13 9DA",
    "sg:province":"Greater London",
    "sg:tags":[
        "pizza"
    ],
    "wof:name":"Luciano's Pizza Pasta Restaurant",
    "wof:placetype":"venue"
},
  "geometry": {"coordinates":[-0.3224599957,51.5103607178],"type":"Point"}
}