{
  "type": "Feature",
  "properties": {
    "addr:full":"34 Tudor Way Waltham Abbey Essex EN9 1PX",
    "addr:housenumber":"34",
    "addr:postcode":"en9 1px",
    "addr:street":"Tudor Way",
    "iso:country":"GB",
    "sg:address":"34 Tudor Way",
    "sg:city":"Waltham Abbey",
    "sg:classifiers":[
        {
            "category":"Autos & Motor Vehicles",
            "subcategory":"Automobile Sales",
            "type":"Retail Goods"
        }
    ],
    "sg:postcode":"EN9 1PX",
    "sg:province":"Essex",
    "sg:tags":[
        "car"
    ],
    "wof:name":"Bannister,Colin Brian,",
    "wof:placetype":"venue"
},
  "geometry": {"coordinates":[0.0041660001,51.6887016296],"type":"Point"}
}