{
  "type": "Feature",
  "properties": {
    "addr:full":"Unit 7 Chartmoor Road Leighton Buzzard Bedfordshire LU7 4WG",
    "addr:housenumber":"unit 7",
    "addr:postcode":"lu7 4wg",
    "addr:street":"Chartmoor Road",
    "iso:country":"GB",
    "sg:address":"Unit 7 Chartmoor Road",
    "sg:city":"Leighton Buzzard",
    "sg:classifiers":[
        {
            "category":"Freight",
            "type":"Transportation"
        }
    ],
    "sg:phone":"+44 1525 244700",
    "sg:postcode":"LU7 4WG",
    "sg:province":"Bedfordshire",
    "sg:tags":[
        "haulage",
        "road"
    ],
    "wof:name":"Mini Clipper Ltd.",
    "wof:placetype":"venue"
},
  "geometry": {"coordinates":[-0.657859,51.906559],"type":"Point"}
}