{
  "type": "Feature",
  "properties": {
    "addr:full":"110 Beverley Road Hessle East Riding of Yorkshire HU13 9BU",
    "addr:housenumber":"110",
    "addr:postcode":"hu13 9bu",
    "addr:street":"Beverley Road",
    "iso:country":"GB",
    "sg:address":"110 Beverley Road",
    "sg:city":"Hessle",
    "sg:classifiers":[
        {
            "category":"Retail",
            "subcategory":"Repair Shop",
            "type":"Services"
        }
    ],
    "sg:phone":"+44 1482 640303",
    "sg:postcode":"HU13 9BU",
    "sg:province":"East Riding of Yorkshire",
    "sg:tags":[
        "radio",
        "television",
        "video"
    ],
    "wof:name":"Redivision Ltd.",
    "wof:placetype":"venue"
},
  "geometry": {"coordinates":[-0.435444,53.729725],"type":"Point"}
}