{
  "type": "Feature",
  "properties": {
    "addr:full":"Estate Office, Danestone Aberdeen Aberdeen City AB22 8AR",
    "addr:postcode":"ab22 8ar",
    "addr:street":"Danestone",
    "iso:country":"GB",
    "sg:address":"Estate Office, Danestone",
    "sg:city":"Aberdeen",
    "sg:classifiers":[
        {
            "category":"Real Estate",
            "subcategory":"Surveying",
            "type":"Services"
        }
    ],
    "sg:phone":"+44 1224 722202",
    "sg:postcode":"AB22 8AR",
    "sg:province":"Aberdeen City",
    "sg:tags":[
        "surveyor",
        "valuer"
    ],
    "wof:name":"David R Paton Chartered Sureyors",
    "wof:placetype":"venue"
},
  "geometry": {"coordinates":[-2.1339919567,57.179309845],"type":"Point"}
}