{
  "type": "Feature",
  "properties": {
    "addr:full":"100 Dowson Rd, Gee Cross Hyde Cheshire SK14 5BN",
    "addr:housenumber":"100",
    "addr:postcode":"sk14 5bn",
    "addr:street":"Dowson Rd Gee Cross Hyde",
    "iso:country":"GB",
    "sg:address":"100 Dowson Rd, Gee Cross",
    "sg:city":"Hyde",
    "sg:classifiers":[
        {
            "category":"Retail",
            "subcategory":"Auto Repair",
            "type":"Services"
        }
    ],
    "sg:phone":"+44 161 367 8038",
    "sg:postcode":"SK14 5BN",
    "sg:province":"Cheshire",
    "sg:tags":[
        "modification",
        "garage"
    ],
    "wof:name":"Autosave",
    "wof:placetype":"venue"
},
  "geometry": {"coordinates":[-2.0760710239,53.44272995],"type":"Point"}
}