{
  "type": "Feature",
  "properties": {
    "iso:country":"GB",
    "sg:address":"19 High Street",
    "sg:city":"Honiton",
    "sg:classifiers":[
        {
            "category":"Shopping",
            "subcategory":"Antiques",
            "type":"Retail Goods"
        }
    ],
    "sg:phone":"+44 1404 42694",
    "sg:postcode":"EX14 1PR",
    "sg:province":"Devon",
    "wof:name":"Merchant House Antiques Ltd",
    "wof:placetype":"venue"
},
  "geometry": {"coordinates":[-3.1849739552,50.8009986877],"type":"Point"}
}