{
  "type": "Feature",
  "properties": {
    "addr:full":"14 Wharf Road, Ash Vale Aldershot Hampshire GU12 5AS",
    "addr:housenumber":"14",
    "addr:postcode":"gu12 5as",
    "addr:street":"Wharf Road Ash",
    "iso:country":"GB",
    "sg:address":"14 Wharf Road, Ash Vale",
    "sg:city":"Aldershot",
    "sg:classifiers":[
        {
            "category":"Food & Beverages",
            "subcategory":"Supermarket",
            "type":"Retail Goods"
        }
    ],
    "sg:phone":"+44 1252 331505",
    "sg:postcode":"GU12 5AS",
    "sg:province":"Hampshire",
    "wof:name":"Budgens Stores Ltd.",
    "wof:placetype":"venue"
},
  "geometry": {"coordinates":[-0.719961,51.257439],"type":"Point"}
}