{
  "type": "Feature",
  "properties": {
    "iso:country":"GB",
    "sg:address":"48 Lincoln Road, Skellingthorpe",
    "sg:city":"Lincoln",
    "sg:classifiers":[
        {
            "category":"Professional",
            "subcategory":"Business Services",
            "type":"Services"
        },
        {
            "category":"Manufacturing",
            "subcategory":"Musical Instruments",
            "type":"Manufacturing & Wholesale Goods"
        }
    ],
    "sg:phone":"+44 1522 509060",
    "sg:postcode":"LN6 5UU",
    "sg:province":"Lincolnshire",
    "sg:tags":[
        "manufacturers'",
        "agent",
        "manufacturer"
    ],
    "wof:name":"D Hardman",
    "wof:placetype":"venue"
},
  "geometry": {"coordinates":[-0.610651,53.232887],"type":"Point"}
}