{
  "type": "Feature",
  "properties": {
    "iso:country":"GB",
    "sg:address":"2 Market Parade, Hazlemere",
    "sg:city":"High Wycombe",
    "sg:classifiers":[
        {
            "category":"Shopping",
            "subcategory":"Pharmacy",
            "type":"Retail Goods"
        }
    ],
    "sg:phone":"+44 1494 711557",
    "sg:postcode":"HP15 7LQ",
    "sg:province":"Buckinghamshire",
    "sg:tags":[
        "pharmacist",
        "chemist"
    ],
    "wof:name":"Hazlemere Pharmacy Ltd.",
    "wof:placetype":"venue"
},
  "geometry": {"coordinates":[-0.71288,51.651501],"type":"Point"}
}