{
  "type": "Feature",
  "properties": {
    "addr:full":"8 Fairview Parade, Beaulieu Road, Hythe Southampton Hampshire SO45 5GT",
    "addr:housenumber":"8",
    "addr:postcode":"so45 5gt",
    "addr:street":"Fairview Parade Beaulieu Road",
    "iso:country":"GB",
    "sg:address":"8 Fairview Parade, Beaulieu Road, Hythe",
    "sg:city":"Southampton",
    "sg:classifiers":[
        {
            "category":"Retail",
            "subcategory":"Laundry & Dry Cleaning",
            "type":"Services"
        }
    ],
    "sg:phone":"+44 23 8084 5768",
    "sg:postcode":"SO45 5GT",
    "sg:province":"Hampshire",
    "sg:tags":[
        "cleaner",
        "alteration"
    ],
    "wof:name":"Atherley Cleaners Ltd.",
    "wof:placetype":"venue"
},
  "geometry": {"coordinates":[-1.4051,50.859852],"type":"Point"}
}