{
  "type": "Feature",
  "properties": {
    "addr:full":"45 Kingsmere Park London Greater London NW9 8PJ",
    "addr:housenumber":"45",
    "addr:postcode":"nw9 8pj",
    "addr:street":"Kingsmere Park",
    "iso:country":"GB",
    "sg:address":"45 Kingsmere Park",
    "sg:city":"London",
    "sg:classifiers":[
        {
            "category":"Building & Trades",
            "subcategory":"Construction",
            "type":"Services"
        }
    ],
    "sg:postcode":"NW9 8PJ",
    "sg:province":"Greater London",
    "sg:tags":[
        "builder"
    ],
    "wof:name":"Thomas Mulrennan",
    "wof:placetype":"venue"
},
  "geometry": {"coordinates":[-0.270393,51.570763],"type":"Point"}
}