{
  "type": "Feature",
  "properties": {
    "iso:country":"GB",
    "sg:address":"Kinnock Park, Burtonwood",
    "sg:city":"Warrington",
    "sg:classifiers":[
        {
            "category":"Health Services",
            "subcategory":"Doctor",
            "type":"Services"
        },
        {
            "category":"Health Services",
            "subcategory":"Clinic",
            "type":"Services"
        }
    ],
    "sg:phone":"+44 1925 222012",
    "sg:postcode":"WA5 4PU",
    "sg:province":"Cheshire",
    "sg:tags":[
        "nh",
        "practitioners"
    ],
    "wof:name":"Burtonwood Village Surgery",
    "wof:placetype":"venue"
},
  "geometry": {"coordinates":[-2.65711,53.431156],"type":"Point"}
}