{
  "type": "Feature",
  "properties": {
    "addr:full":"Lawnfield, Bellingdon Chesham Buckinghamshire HP5 2XU",
    "addr:postcode":"hp5 2xu",
    "iso:country":"GB",
    "sg:address":"Lawnfield, Bellingdon",
    "sg:city":"Chesham",
    "sg:classifiers":[
        {
            "category":"Communications",
            "subcategory":"Film & Video Production",
            "type":"Services"
        }
    ],
    "sg:phone":"+44 1494 758100",
    "sg:postcode":"HP5 2XU",
    "sg:province":"Buckinghamshire",
    "sg:tags":[
        "recording",
        "studio"
    ],
    "wof:name":"Martin Atkinson",
    "wof:placetype":"venue"
},
  "geometry": {"coordinates":[-0.636425,51.7384],"type":"Point"}
}