{
  "type": "Feature",
  "properties": {
    "addr:full":"111 Regents Park Rd London Greater London NW1 8UR",
    "addr:housenumber":"111",
    "addr:postcode":"nw1 8ur",
    "addr:street":"Regents Park Rd",
    "iso:country":"GB",
    "sg:address":"111 Regents Park Rd",
    "sg:city":"London",
    "sg:classifiers":[
        {
            "category":"Professional",
            "subcategory":"Management & Consulting",
            "type":"Services"
        }
    ],
    "sg:postcode":"NW1 8UR",
    "sg:province":"Greater London",
    "sg:tags":[
        "consultant",
        "promotion",
        "direct",
        "sale"
    ],
    "wof:name":"Pma Marketing Ltd",
    "wof:placetype":"venue"
},
  "geometry": {"coordinates":[-0.1558180004,51.5424690247],"type":"Point"}
}