{
  "type": "Feature",
  "properties": {
    "addr:full":"Woodgate Studios Midhurst West Sussex GU29 0PY",
    "addr:postcode":"gu29 0py",
    "iso:country":"GB",
    "sg:address":"Woodgate Studios",
    "sg:city":"Midhurst",
    "sg:classifiers":[
        {
            "category":"Professional",
            "subcategory":"Art Services",
            "type":"Services"
        }
    ],
    "sg:phone":"+44 1730 816682",
    "sg:postcode":"GU29 0PY",
    "sg:province":"West Sussex",
    "sg:tags":[
        "photographer"
    ],
    "wof:name":"John Gill",
    "wof:placetype":"venue"
},
  "geometry": {"coordinates":[-0.7405800223,50.9849128723],"type":"Point"}
}