{
  "type": "Feature",
  "properties": {
    "addr:full":"63-65 Winter Hey Lane, Horwich Bolton Lancashire BL6 7NT",
    "addr:housenumber":"63-65",
    "addr:postcode":"bl6 7nt",
    "addr:street":"Winter Hey Lane",
    "iso:country":"GB",
    "sg:address":"63-65 Winter Hey Lane, Horwich",
    "sg:city":"Bolton",
    "sg:classifiers":[
        {
            "category":"Personal",
            "subcategory":"Beauty Salon",
            "type":"Services"
        }
    ],
    "sg:postcode":"BL6 7NT",
    "sg:province":"Lancashire",
    "sg:tags":[
        "unisex",
        "hairdresser"
    ],
    "wof:name":"Paul Street",
    "wof:placetype":"venue"
},
  "geometry": {"coordinates":[-2.548063,53.59893],"type":"Point"}
}