{
  "type": "Feature",
  "properties": {
    "addr:full":"Unit 11 Shakespeare Industrial Estate, Shakespeare Street Watford Hertfordshire WD24 5RR",
    "addr:housenumber":"unit 11;estate",
    "addr:postcode":"wd24 5rr",
    "addr:street":"Shakespeare Industrial;Shakespeare Street",
    "iso:country":"GB",
    "sg:address":"Unit 11 Shakespeare Industrial Estate, Shakespeare Street",
    "sg:city":"Watford",
    "sg:classifiers":[
        {
            "category":"Professional",
            "subcategory":"Printing & Photocopies",
            "type":"Services"
        }
    ],
    "sg:phone":"+44 1923 235413",
    "sg:postcode":"WD24 5RR",
    "sg:province":"Hertfordshire",
    "sg:tags":[
        "duplicating",
        "copying"
    ],
    "wof:name":"Buckingham Reprographic Services Ltd.",
    "wof:placetype":"venue"
},
  "geometry": {"coordinates":[-0.4042699933,51.671131134],"type":"Point"}
}