{
  "type": "Feature",
  "properties": {
    "addr:full":"39a Paisley Shopping Centre, High Street Paisley Renfrewshire PA1 2AQ",
    "addr:housenumber":"39a",
    "addr:postcode":"pa1 2aq",
    "addr:street":"Paisley Shopping;High Street",
    "iso:country":"GB",
    "sg:address":"39a Paisley Shopping Centre, High Street",
    "sg:city":"Paisley",
    "sg:classifiers":[
        {
            "category":"Retail",
            "subcategory":"Photofinishing",
            "type":"Services"
        }
    ],
    "sg:phone":"+44 141 849 6030",
    "sg:postcode":"PA1 2AQ",
    "sg:province":"Renfrewshire",
    "sg:tags":[
        "photographic",
        "processor"
    ],
    "wof:name":"Munroe & Klik Photopoint",
    "wof:placetype":"venue"
},
  "geometry": {"coordinates":[-4.4245500565,55.8446006775],"type":"Point"}
}