{
  "type": "Feature",
  "properties": {
    "addr:full":"Greenlands Farm, Charlton Musgrove Wincanton Somerset BA9 8EZ",
    "addr:housenumber":"musgrove",
    "addr:postcode":"ba9 8ez",
    "iso:country":"GB",
    "sg:address":"Greenlands Farm, Charlton Musgrove",
    "sg:city":"Wincanton",
    "sg:classifiers":[
        {
            "category":"Farming",
            "subcategory":"Dairy Farm",
            "type":"Manufacturing & Wholesale Goods"
        }
    ],
    "sg:postcode":"BA9 8EZ",
    "sg:province":"Somerset",
    "wof:name":"Bristol,Andrew Robert,",
    "wof:placetype":"venue"
},
  "geometry": {"coordinates":[-2.388379097,51.083480835],"type":"Point"}
}