{
  "type": "Feature",
  "properties": {
    "iso:country":"GB",
    "sg:address":"Unit 17 Radway Industrial Estate",
    "sg:city":"Solihull",
    "sg:classifiers":[
        {
            "category":"Fast Food",
            "type":"Food & Drink"
        }
    ],
    "sg:phone":"+44 121 711 4142",
    "sg:postcode":"B90 4NR",
    "sg:province":"West Midlands",
    "sg:tags":[
        "away",
        "take"
    ],
    "wof:name":"Red Peppers Balti",
    "wof:placetype":"venue"
},
  "geometry": {"coordinates":[-1.80353,52.395611],"type":"Point"}
}