{
  "type": "Feature",
  "properties": {
    "iso:country":"GB",
    "sg:address":"Morley Nurseries Southend Road, Great Wakering",
    "sg:city":"Rayleigh",
    "sg:classifiers":[
        {
            "category":"Manufacturing",
            "subcategory":"Building Materials",
            "type":"Manufacturing & Wholesale Goods"
        }
    ],
    "sg:phone":"+44 1702 585182",
    "sg:postcode":"SS3 0PU",
    "sg:province":"Essex",
    "sg:tags":[
        "concrete",
        "product"
    ],
    "wof:name":"Gardenware",
    "wof:placetype":"venue"
},
  "geometry": {"coordinates":[0.799884975,51.5531959534],"type":"Point"}
}