{
  "type": "Feature",
  "properties": {
    "iso:country":"GB",
    "sg:address":"P O Box 389",
    "sg:city":"Windlesham",
    "sg:classifiers":[
        {
            "category":"Real Estate",
            "subcategory":"Developer",
            "type":"Services"
        }
    ],
    "sg:phone":"+44 1276 479111",
    "sg:postcode":"GU20 6YH",
    "sg:province":"Surrey",
    "sg:tags":[
        "property"
    ],
    "wof:name":"Scammell Securities Plc",
    "wof:placetype":"venue"
},
  "geometry": {"coordinates":[-0.6654189825,51.3652305603],"type":"Point"}
}