{
  "type": "Feature",
  "properties": {
    "iso:country":"GB",
    "sg:address":"Hospital St",
    "sg:city":"Walsall",
    "sg:classifiers":[
        {
            "category":"Professional",
            "subcategory":"Business Services",
            "type":"Services"
        }
    ],
    "sg:phone":"+44 1922 725535",
    "sg:postcode":"WS2 8QQ",
    "sg:province":"West Midlands",
    "sg:tags":[
        "holding"
    ],
    "wof:name":"Ferrum Holdings Plc",
    "wof:placetype":"venue"
},
  "geometry": {"coordinates":[-1.986919,52.5942],"type":"Point"}
}