{
  "type": "Feature",
  "properties": {
    "iso:country":"GB",
    "sg:address":"Mains St",
    "sg:city":"Nottingham",
    "sg:classifiers":[
        {
            "category":"Bars & Pubs",
            "type":"Food & Drink"
        }
    ],
    "sg:phone":"+44 115 946 2384",
    "sg:postcode":"NG10 1GJ",
    "sg:province":"Derbyshire",
    "sg:tags":[
        "pubs",
        "inn"
    ],
    "wof:name":"Famous Stillage The",
    "wof:placetype":"venue"
},
  "geometry": {"coordinates":[-1.2665690184,52.8959236145],"type":"Point"}
}