{
  "type": "Feature",
  "properties": {
    "addr:full":"Lichfield Road Walsall West Midlands WS4 1PQ",
    "addr:postcode":"ws4 1pq",
    "addr:street":"Lichfield Road",
    "iso:country":"GB",
    "sg:address":"Lichfield Road",
    "sg:city":"Walsall",
    "sg:classifiers":[
        {
            "category":"Autos & Motor Vehicles",
            "subcategory":"Fuel & Gas Station",
            "type":"Retail Goods"
        }
    ],
    "sg:phone":"+44 1922 693439",
    "sg:postcode":"WS4 1PQ",
    "sg:province":"West Midlands",
    "sg:tags":[
        "petrol",
        "filling"
    ],
    "wof:name":"The Dave Norris Group",
    "wof:placetype":"venue"
},
  "geometry": {"coordinates":[-1.968364,52.598347],"type":"Point"}
}