{
  "type": "Feature",
  "properties": {
    "iso:country":"GB",
    "sg:address":"Ashdale Cottage, Ashdale Lane, Hill Mountain",
    "sg:city":"Milford Haven",
    "sg:classifiers":[
        {
            "category":"Utilities",
            "type":"Services"
        }
    ],
    "sg:phone":"+44 1646 602403",
    "sg:postcode":"SA73 1NB",
    "sg:province":"Pembrokeshire",
    "sg:tags":[
        "internet"
    ],
    "wof:name":"Bird-Online Co. Uk Ltd.",
    "wof:placetype":"venue"
},
  "geometry": {"coordinates":[-4.9289698601,51.7367515564],"type":"Point"}
}