{
  "type": "Feature",
  "properties": {
    "addr:full":"23 Bostonthorpe Rd London Greater London W7 2HD",
    "addr:housenumber":"23",
    "addr:postcode":"w7 2hd",
    "addr:street":"Bostonthorpe Rd",
    "iso:country":"GB",
    "sg:address":"23 Bostonthorpe Rd",
    "sg:city":"London",
    "sg:classifiers":[
        {
            "category":"Professional",
            "subcategory":"Engineering",
            "type":"Services"
        }
    ],
    "sg:postcode":"W7 2HD",
    "sg:province":"Greater London",
    "sg:tags":[
        "precision",
        "engineer"
    ],
    "wof:name":"Brown,Charles,",
    "wof:placetype":"venue"
},
  "geometry": {"coordinates":[-0.336537,51.503876],"type":"Point"}
}