{
  "type": "Feature",
  "properties": {
    "addr:full":"Lloyds Avenue Ho, 6 Lloyds Ave London Greater London EC3N 3ES",
    "addr:housenumber":"6",
    "addr:postcode":"ec3n 3es",
    "addr:street":"Lloyds Avenue;Lloyds Ave",
    "iso:country":"GB",
    "sg:address":"Lloyds Avenue Ho, 6 Lloyds Ave",
    "sg:city":"London",
    "sg:classifiers":[
        {
            "category":"Organizations",
            "subcategory":"Community Association",
            "type":"Services"
        }
    ],
    "sg:postcode":"EC3N 3ES",
    "sg:province":"Greater London",
    "sg:tags":[
        "relation",
        "public"
    ],
    "wof:name":"Grosvenor P R Ltd",
    "wof:placetype":"venue"
},
  "geometry": {"coordinates":[-0.07846,51.51236],"type":"Point"}
}