{
  "type": "Feature",
  "properties": {
    "addr:full":"5 Collington Mansions, Collington Avenue Bexhill-on-sea East Sussex TN39 3PU",
    "addr:housenumber":"5",
    "addr:postcode":"tn39 3pu",
    "addr:street":"Collington Avenue",
    "iso:country":"GB",
    "sg:address":"5 Collington Mansions, Collington Avenue",
    "sg:city":"Bexhill-on-sea",
    "sg:classifiers":[
        {
            "category":"Personal",
            "subcategory":"Beauty Salon",
            "type":"Services"
        }
    ],
    "sg:phone":"+44 1424 213344",
    "sg:postcode":"TN39 3PU",
    "sg:province":"East Sussex",
    "sg:tags":[
        "unisex",
        "hairdresser"
    ],
    "wof:name":"Studio 5",
    "wof:placetype":"venue"
},
  "geometry": {"coordinates":[0.4619899988,50.8404998779],"type":"Point"}
}