{
  "type": "Feature",
  "properties": {
    "addr:full":"36 The Nursery, Bath Rd Devizes Wiltshire SN10 2AG",
    "addr:housenumber":"36",
    "addr:postcode":"sn10 2ag",
    "addr:street":"The Nursery Bath Rd",
    "iso:country":"GB",
    "sg:address":"36 The Nursery, Bath Rd",
    "sg:city":"Devizes",
    "sg:classifiers":[
        {
            "category":"Professional",
            "subcategory":"Business Services",
            "type":"Services"
        }
    ],
    "sg:phone":"+44 1380 729214",
    "sg:postcode":"SN10 2AG",
    "sg:province":"Wiltshire",
    "sg:tags":[
        "tile",
        "stockist"
    ],
    "wof:name":"ARTISANS OF DEVIZES",
    "wof:placetype":"venue"
},
  "geometry": {"coordinates":[-2.0013260841,51.3544807434],"type":"Point"}
}