{
  "type": "Feature",
  "properties": {
    "addr:full":"Ledsham Lane, Ledsham Ellesmere Port Cheshire CH66 0NB",
    "addr:postcode":"ch66 0nb",
    "addr:street":"Ledsham Lane",
    "iso:country":"GB",
    "sg:address":"Ledsham Lane, Ledsham",
    "sg:city":"Ellesmere Port",
    "sg:classifiers":[
        {
            "category":"Farming",
            "subcategory":"Nursery",
            "type":"Manufacturing & Wholesale Goods"
        },
        {
            "category":"Home & Garden",
            "subcategory":"Garden Supply",
            "type":"Retail Goods"
        }
    ],
    "sg:phone":"+44 151 347 1492",
    "sg:postcode":"CH66 0NB",
    "sg:province":"Cheshire",
    "sg:tags":[
        "planting",
        "tree",
        "shrub"
    ],
    "wof:name":"Sutton's Nurseries Ltd",
    "wof:placetype":"venue"
},
  "geometry": {"coordinates":[-2.9625389576,53.2644691467],"type":"Point"}
}