{
  "type": "Feature",
  "properties": {
    "addr:full":"121 Cannons Gate Clevedon Somerset BS21 5HN",
    "addr:housenumber":"121",
    "addr:postcode":"bs21 5hn",
    "addr:street":"Cannons Gate",
    "iso:country":"GB",
    "sg:address":"121 Cannons Gate",
    "sg:city":"Clevedon",
    "sg:classifiers":[
        {
            "category":"Professional",
            "subcategory":"Art Services",
            "type":"Services"
        }
    ],
    "sg:postcode":"BS21 5HN",
    "sg:province":"Somerset",
    "sg:tags":[
        "graphic",
        "designer"
    ],
    "wof:name":"Keely & McMahon",
    "wof:placetype":"venue"
},
  "geometry": {"coordinates":[-2.857699,51.424854],"type":"Point"}
}