{
  "type": "Feature",
  "properties": {
    "addr:full":"555 Roman Road London Greater London E3 5EL",
    "addr:housenumber":"555",
    "addr:postcode":"e3 5el",
    "addr:street":"Roman Road",
    "iso:country":"GB",
    "sg:address":"555 Roman Road",
    "sg:city":"London",
    "sg:classifiers":[
        {
            "category":"Shopping",
            "subcategory":"Comic Books",
            "type":"Retail Goods"
        }
    ],
    "sg:phone":"+44 20 8983 4211",
    "sg:postcode":"E3 5EL",
    "sg:province":"Greater London",
    "sg:tags":[
        "jeweller"
    ],
    "wof:name":"Gold 'N' Image",
    "wof:placetype":"venue"
},
  "geometry": {"coordinates":[-0.030043,51.533085],"type":"Point"}
}