{
  "type": "Feature",
  "properties": {
    "iso:country":"GB",
    "sg:address":"21 Southgate St",
    "sg:city":"Winchester",
    "sg:classifiers":[
        {
            "category":"Health Services",
            "subcategory":"Dentist",
            "type":"Services"
        }
    ],
    "sg:phone":"+44 1962 852488",
    "sg:postcode":"SO23 9EB",
    "sg:province":"Hampshire",
    "wof:name":"A.J Woodman MSc BDS",
    "wof:placetype":"venue"
},
  "geometry": {"coordinates":[-1.317334,51.061962],"type":"Point"}
}