{
  "type": "Feature",
  "properties": {
    "addr:full":"187 Lytchet Way Enfield Greater London EN3 5XU",
    "addr:housenumber":"187",
    "addr:postcode":"en3 5xu",
    "addr:street":"Lytchet Way",
    "iso:country":"GB",
    "sg:address":"187 Lytchet Way",
    "sg:city":"Enfield",
    "sg:classifiers":[
        {
            "category":"Home & Garden",
            "subcategory":"Building Materials",
            "type":"Retail Goods"
        }
    ],
    "sg:phone":"+44 20 8805 5906",
    "sg:postcode":"EN3 5XU",
    "sg:province":"Greater London",
    "sg:tags":[
        "fencing"
    ],
    "wof:name":"Morris Garden Fencing",
    "wof:placetype":"venue"
},
  "geometry": {"coordinates":[-0.048851,51.661861],"type":"Point"}
}