{
  "type": "Feature",
  "properties": {
    "iso:country":"GB",
    "sg:address":"The Mansion House, Heaton Lodge, Colnebridge",
    "sg:city":"Huddersfield",
    "sg:classifiers":[
        {
            "category":"Health Services",
            "subcategory":"Doctor",
            "type":"Services"
        }
    ],
    "sg:phone":"+44 1484 540848",
    "sg:postcode":"HD5 0PW",
    "sg:province":"West Yorkshire",
    "sg:tags":[
        "surgeon"
    ],
    "wof:name":"P J Lyndon",
    "wof:placetype":"venue"
},
  "geometry": {"coordinates":[-1.7321699858,53.6776390076],"type":"Point"}
}