{
  "type": "Feature",
  "properties": {
    "addr:full":"2nd Floor, Titchfield Ho, 69-85 Tabernac London Greater London EC2A 4RR",
    "addr:housenumber":"2nd floor;69-85",
    "addr:postcode":"ec2a 4rr",
    "addr:street":"Titchfield Ho",
    "iso:country":"GB",
    "sg:address":"2nd Floor, Titchfield Ho, 69-85 Tabernac",
    "sg:city":"London",
    "sg:classifiers":[
        {
            "category":"Professional",
            "subcategory":"Management & Consulting",
            "type":"Services"
        }
    ],
    "sg:postcode":"EC2A 4RR",
    "sg:province":"Greater London",
    "sg:tags":[
        "marketing",
        "consultant"
    ],
    "wof:name":"Kontax Ltd",
    "wof:placetype":"venue"
},
  "geometry": {"coordinates":[-0.0834999979,51.5240211487],"type":"Point"}
}