{
  "type": "Feature",
  "properties": {
    "addr:full":"Edgefield Grn, Bicton Heath Shrewsbury Shropshire SY3 5HB",
    "addr:postcode":"sy3 5hb",
    "addr:street":"Edgefield Grn",
    "iso:country":"GB",
    "sg:address":"Edgefield Grn, Bicton Heath",
    "sg:city":"Shrewsbury",
    "sg:classifiers":[
        {
            "category":"Government",
            "subcategory":"Office",
            "type":"Public Place"
        }
    ],
    "sg:phone":"+44 1743 247318",
    "sg:postcode":"SY3 5HB",
    "sg:province":"Shropshire",
    "sg:tags":[
        "local"
    ],
    "wof:name":"Edgefield Green Sheltered Housing",
    "wof:placetype":"venue"
},
  "geometry": {"coordinates":[-2.806864,52.711617],"type":"Point"}
}