{
  "type": "Feature",
  "properties": {
    "addr:full":"22 Bellfields Street Market Harborough Leicestershire LE16 8AB",
    "addr:housenumber":"22",
    "addr:postcode":"le16 8ab",
    "addr:street":"Bellfields Street",
    "iso:country":"GB",
    "sg:address":"22 Bellfields Street",
    "sg:city":"Market Harborough",
    "sg:classifiers":[
        {
            "category":"Building & Trades",
            "subcategory":"Plumbing",
            "type":"Services"
        }
    ],
    "sg:phone":"+44 1858 431637",
    "sg:postcode":"LE16 8AB",
    "sg:province":"Leicestershire",
    "sg:tags":[
        "plumber",
        "heating"
    ],
    "wof:name":"Bowden Plumbing Services",
    "wof:placetype":"venue"
},
  "geometry": {"coordinates":[-0.9078390002,52.4744529724],"type":"Point"}
}