{
  "type": "Feature",
  "properties": {
    "iso:country":"GB",
    "sg:address":"The Quarry, Kewstoke Road, Kewstoke",
    "sg:city":"Weston-super-mare",
    "sg:classifiers":[
        {
            "category":"Home & Garden",
            "subcategory":"Building Materials",
            "type":"Retail Goods"
        }
    ],
    "sg:phone":"+44 1934 510277",
    "sg:postcode":"BS22 9LF",
    "sg:province":"Somerset",
    "sg:tags":[
        "ready",
        "mixed",
        "concrete"
    ],
    "wof:name":"Ready Mixed Concrete (Western) Ltd.",
    "wof:placetype":"venue"
},
  "geometry": {"coordinates":[-2.9550058842,51.3656654358],"type":"Point"}
}