{
  "type": "Feature",
  "properties": {
    "addr:full":"Crownquay Industrial Estate Sittingbourne Kent ME10 3LG",
    "addr:postcode":"me10 3lg",
    "addr:street":"Estate Sittingbourne",
    "iso:country":"GB",
    "sg:address":"Crownquay Industrial Estate",
    "sg:city":"Sittingbourne",
    "sg:classifiers":[
        {
            "category":"Shopping",
            "subcategory":"Computers & Home Electronics",
            "type":"Retail Goods"
        }
    ],
    "sg:phone":"+44 1795 421641",
    "sg:postcode":"ME10 3LG",
    "sg:province":"Kent",
    "sg:tags":[
        "electrical"
    ],
    "wof:name":"Newey & Eyre Ltd.",
    "wof:placetype":"venue"
},
  "geometry": {"coordinates":[0.73791,51.34082],"type":"Point"}
}