{
  "type": "Feature",
  "properties": {
    "iso:country":"GB",
    "sg:address":"137 Woodfield Street, Morriston",
    "sg:city":"Swansea",
    "sg:classifiers":[
        {
            "category":"Personal",
            "subcategory":"Beauty Salon",
            "type":"Services"
        }
    ],
    "sg:postcode":"SA6 8AL",
    "sg:province":"Swansea",
    "sg:tags":[
        "unisex",
        "hairdresser"
    ],
    "wof:name":"Murphys Hair Salon",
    "wof:placetype":"venue"
},
  "geometry": {"coordinates":[-3.924873,51.666393],"type":"Point"}
}