{
  "type": "Feature",
  "properties": {
    "iso:country":"GB",
    "sg:address":"Little Meadow Bulldock Road",
    "sg:city":"Hatfield",
    "sg:classifiers":[
        {
            "category":"Retail",
            "subcategory":"Auto Repair",
            "type":"Services"
        }
    ],
    "sg:postcode":"SG9 9RH",
    "sg:province":"Hertfordshire",
    "sg:tags":[
        "garage"
    ],
    "wof:name":"T & C Services",
    "wof:placetype":"venue"
},
  "geometry": {"coordinates":[-0.0197500009,51.9466590881],"type":"Point"}
}