{
  "type": "Feature",
  "properties": {
    "addr:full":"1st Floor, Cheethams Mill-park St, Acres La Stalybridge Greater Manchester SK15 2BT",
    "addr:postcode":"sk15 2bt",
    "addr:street":"Mill-Park St",
    "iso:country":"GB",
    "sg:address":"1st Floor, Cheethams Mill-park St, Acres La",
    "sg:city":"Stalybridge",
    "sg:classifiers":[
        {
            "category":"Professional",
            "subcategory":"Business Services",
            "type":"Services"
        }
    ],
    "sg:postcode":"SK15 2BT",
    "sg:province":"Greater Manchester",
    "sg:tags":[
        "import",
        "export",
        "agent"
    ],
    "wof:name":"Sobrinca U K Ltd",
    "wof:placetype":"venue"
},
  "geometry": {"coordinates":[-2.057569,53.483543],"type":"Point"}
}