{
  "type": "Feature",
  "properties": {
    "addr:full":"Wroxham Barns, Tunstead Road, Hoveton Norwich Norfolk NR12 8QU",
    "addr:postcode":"nr12 8qu",
    "addr:street":"Tunstead Road;Norwich",
    "iso:country":"GB",
    "sg:address":"Wroxham Barns, Tunstead Road, Hoveton",
    "sg:city":"Norwich",
    "sg:classifiers":[
        {
            "category":"Park",
            "subcategory":"Town Common",
            "type":"Public Place"
        },
        {
            "category":"Manufacturing",
            "subcategory":"Signs",
            "type":"Manufacturing & Wholesale Goods"
        }
    ],
    "sg:phone":"+44 1603 784118",
    "sg:postcode":"NR12 8QU",
    "sg:province":"Norfolk",
    "sg:tags":[
        "manufacture",
        "article",
        "funfair"
    ],
    "wof:name":"P & J Amusements",
    "wof:placetype":"venue"
},
  "geometry": {"coordinates":[1.414644,52.714527],"type":"Point"}
}