{
  "type": "Feature",
  "properties": {
    "addr:full":"141 Commercial Rd Poole Dorset BH14 0JD",
    "addr:housenumber":"141",
    "addr:postcode":"bh14 0jd",
    "addr:street":"Commercial Rd",
    "iso:country":"GB",
    "sg:address":"141 Commercial Rd",
    "sg:city":"Poole",
    "sg:classifiers":[
        {
            "category":"Fast Food",
            "type":"Food & Drink"
        }
    ],
    "sg:postcode":"BH14 0JD",
    "sg:province":"Dorset",
    "sg:tags":[
        "away",
        "take"
    ],
    "wof:name":"Berkleys Brasserie",
    "wof:placetype":"venue"
},
  "geometry": {"coordinates":[-1.951017,50.724136],"type":"Point"}
}