{
  "type": "Feature",
  "properties": {
    "iso:country":"GB",
    "sg:address":"114 Green Lane Road",
    "sg:city":"Leicester",
    "sg:classifiers":[
        {
            "category":"Shopping",
            "subcategory":"Clothing, Apparel, & Fashions",
            "type":"Retail Goods"
        }
    ],
    "sg:phone":"+44 116 276 4677",
    "sg:postcode":"LE5 3TJ",
    "sg:province":"Leicestershire",
    "sg:tags":[
        "ladieswear"
    ],
    "wof:name":"Gani's Fashions",
    "wof:placetype":"venue"
},
  "geometry": {"coordinates":[-1.102661,52.638969],"type":"Point"}
}