{
  "type": "Feature",
  "properties": {
    "iso:country":"GB",
    "sg:address":"3 St Mary Street",
    "sg:city":"Cardiff",
    "sg:classifiers":[
        {
            "category":"Food & Beverages",
            "subcategory":"Specialty",
            "type":"Retail Goods"
        }
    ],
    "sg:phone":"+44 29 2025 1671",
    "sg:postcode":"CF10 1AT",
    "sg:province":"Cardiff",
    "sg:tags":[
        "retailer",
        "product",
        "health"
    ],
    "wof:name":"Beanfreaks Ltd",
    "wof:placetype":"venue"
},
  "geometry": {"coordinates":[-3.242679,51.470646],"type":"Point"}
}