{
  "type": "Feature",
  "properties": {
    "addr:full":"Unit 4 Industrial Estate, Stainton Gro Barnard Castle Cumbria DL12 8UJ",
    "addr:housenumber":"unit 4",
    "addr:postcode":"cumbria dl12 8uj",
    "addr:street":"Industrial Estate;Gro",
    "iso:country":"GB",
    "sg:address":"Unit 4 Industrial Estate, Stainton Gro",
    "sg:city":"Barnard Castle",
    "sg:classifiers":[
        {
            "category":"Building & Trades",
            "subcategory":"Construction",
            "type":"Services"
        }
    ],
    "sg:phone":"+44 1833 690605",
    "sg:postcode":"DL12 8UJ",
    "sg:province":"Cumbria",
    "sg:tags":[
        "joinery"
    ],
    "wof:name":"Alan Heavisides",
    "wof:placetype":"venue"
},
  "geometry": {"coordinates":[-1.8896809816,54.5567893982],"type":"Point"}
}