{
  "type": "Feature",
  "properties": {
    "addr:full":"Sunrise Cottage, Queens Road Crowborough East Sussex TN6 1PT",
    "addr:postcode":"tn6 1pt",
    "addr:street":"Queens Road",
    "iso:country":"GB",
    "sg:address":"Sunrise Cottage, Queens Road",
    "sg:city":"Crowborough",
    "sg:classifiers":[
        {
            "category":"Recreation",
            "subcategory":"Dog Park",
            "type":"Entertainment"
        },
        {
            "category":"Retail",
            "subcategory":"Animal Services",
            "type":"Services"
        }
    ],
    "sg:phone":"+44 1892 663210",
    "sg:postcode":"TN6 1PT",
    "sg:province":"East Sussex",
    "sg:tags":[
        "grooming",
        "clipping"
    ],
    "wof:name":"Karens Dog Parlour",
    "wof:placetype":"venue"
},
  "geometry": {"coordinates":[0.171893,51.053196],"type":"Point"}
}