{
  "type": "Feature",
  "properties": {
    "iso:country":"GB",
    "sg:address":"5 Chapel Close",
    "sg:city":"Seaford",
    "sg:classifiers":[
        {
            "category":"Autos & Motor Vehicles",
            "subcategory":"Automobile Sales",
            "type":"Retail Goods"
        }
    ],
    "sg:phone":"+44 1323 899990",
    "sg:postcode":"BN25 2JJ",
    "sg:province":"East Sussex",
    "sg:tags":[
        "car"
    ],
    "wof:name":"Sussex Estate Cars",
    "wof:placetype":"venue"
},
  "geometry": {"coordinates":[0.103066,50.778072],"type":"Point"}
}