{
  "type": "Feature",
  "properties": {
    "addr:full":"18 Princes Grn Halesworth Suffolk IP19 8DP",
    "addr:housenumber":"18",
    "addr:postcode":"ip19 8dp",
    "addr:street":"Princes Grn",
    "iso:country":"GB",
    "sg:address":"18 Princes Grn",
    "sg:city":"Halesworth",
    "sg:classifiers":[
        {
            "category":"Retail",
            "subcategory":"Event Space",
            "type":"Services"
        }
    ],
    "sg:phone":"+44 1986 872368",
    "sg:postcode":"IP19 8DP",
    "sg:province":"Suffolk",
    "sg:tags":[
        "exhibition",
        "organiser"
    ],
    "wof:name":"Anglian Arts & Antiques",
    "wof:placetype":"venue"
},
  "geometry": {"coordinates":[1.4952039719,52.3365821838],"type":"Point"}
}