{
  "type": "Feature",
  "properties": {
    "iso:country":"GB",
    "sg:address":"38 Charles Street",
    "sg:city":"Leicester",
    "sg:classifiers":[
        {
            "category":"Shopping",
            "subcategory":"Music",
            "type":"Retail Goods"
        }
    ],
    "sg:phone":"+44 116 262 7475",
    "sg:postcode":"LE1 1FB",
    "sg:province":"Leicestershire",
    "sg:tags":[
        "record",
        "tape",
        "cd"
    ],
    "wof:name":"5 H Q",
    "wof:placetype":"venue"
},
  "geometry": {"coordinates":[-1.130089,52.636028],"type":"Point"}
}