{
  "type": "Feature",
  "properties": {
    "addr:full":"50 The Broadway, Joel Street Northwood Greater London HA6 1PA",
    "addr:housenumber":"50",
    "addr:postcode":"ha6 1pa",
    "addr:street":"The Broadway Joel Street",
    "iso:country":"GB",
    "sg:address":"50 The Broadway, Joel Street",
    "sg:city":"Northwood",
    "sg:classifiers":[
        {
            "category":"Shopping",
            "subcategory":"Clothing, Apparel, & Fashions",
            "type":"Retail Goods"
        }
    ],
    "sg:phone":"+44 1923 822163",
    "sg:postcode":"HA6 1PA",
    "sg:province":"Greater London",
    "sg:tags":[
        "lingerie",
        "hosiery"
    ],
    "wof:name":"Rosalyn",
    "wof:placetype":"venue"
},
  "geometry": {"coordinates":[-0.4241859913,51.611541748],"type":"Point"}
}