{
  "type": "Feature",
  "properties": {
    "iso:country":"GB",
    "sg:address":"34 Boulevard",
    "sg:city":"Weston-super-mare",
    "sg:classifiers":[
        {
            "category":"Professional",
            "subcategory":"Accounting & Tax Preparation",
            "type":"Services"
        }
    ],
    "sg:postcode":"BS23 1NF",
    "sg:province":"Somerset",
    "sg:tags":[
        "accountant"
    ],
    "wof:name":"T P Lewis & Partners",
    "wof:placetype":"venue"
},
  "geometry": {"coordinates":[-2.9745700359,51.3501663208],"type":"Point"}
}