{
  "type": "Feature",
  "properties": {
    "iso:country":"GB",
    "sg:address":"Douglas House, East Street",
    "sg:city":"Tonbridge",
    "sg:classifiers":[
        {
            "category":"Insurance",
            "subcategory":"Health Insurance",
            "type":"Services"
        }
    ],
    "sg:phone":"+44 1452 531300",
    "sg:postcode":"TN9 1HP",
    "sg:province":"Kent",
    "wof:name":"Partners in Health Ltd.",
    "wof:placetype":"venue"
},
  "geometry": {"coordinates":[0.278795,51.1973],"type":"Point"}
}