{
  "type": "Feature",
  "properties": {
    "iso:country":"GB",
    "sg:address":"The Stone Mason, Trafalgar Place",
    "sg:city":"Portsmouth",
    "sg:classifiers":[
        {
            "category":"Autos & Motor Vehicles",
            "subcategory":"Automobile Sales",
            "type":"Retail Goods"
        }
    ],
    "sg:phone":"+44 23 9273 3132",
    "sg:postcode":"PO1 5JJ",
    "sg:province":"Hampshire",
    "sg:tags":[
        "car"
    ],
    "wof:name":"SAM HARTLEY",
    "wof:placetype":"venue"
},
  "geometry": {"coordinates":[-1.087284,50.804008],"type":"Point"}
}