{
  "type": "Feature",
  "properties": {
    "iso:country":"GB",
    "sg:address":"Unit D1, Tariff Rd, Tottenham",
    "sg:city":"London",
    "sg:classifiers":[
        {
            "category":"Professional",
            "subcategory":"Computer Services",
            "type":"Services"
        }
    ],
    "sg:postcode":"N17 0EH",
    "sg:province":"Greater London",
    "sg:tags":[
        "system",
        "software"
    ],
    "wof:name":"Quickshot (Europe) Ltd",
    "wof:placetype":"venue"
},
  "geometry": {"coordinates":[-0.0610390007,51.6058616638],"type":"Point"}
}