{
  "type": "Feature",
  "properties": {
    "addr:full":"37 Cromwell Av Waltham Cross Greater London EN7 5DJ",
    "addr:housenumber":"37",
    "addr:postcode":"en7 5dj",
    "addr:street":"Cromwell Av Waltham Cross",
    "iso:country":"GB",
    "sg:address":"37 Cromwell Av",
    "sg:city":"Waltham Cross",
    "sg:classifiers":[
        {
            "category":"Building & Trades",
            "subcategory":"Plumbing",
            "type":"Services"
        }
    ],
    "sg:phone":"+44 1992 625183",
    "sg:postcode":"EN7 5DJ",
    "sg:province":"Greater London",
    "sg:tags":[
        "heating"
    ],
    "wof:name":"D W Parish",
    "wof:placetype":"venue"
},
  "geometry": {"coordinates":[-0.0510409996,51.7018814087],"type":"Point"}
}