{
  "type": "Feature",
  "properties": {
    "iso:country":"GB",
    "sg:address":"4a Pembroke Road, Ansdell",
    "sg:city":"Lytham St Annes",
    "sg:classifiers":[
        {
            "category":"Organizations",
            "subcategory":"Membership Organization",
            "type":"Services"
        }
    ],
    "sg:phone":"+44 1253 734122",
    "sg:postcode":"FY8 1AN",
    "sg:province":"Lancashire",
    "sg:tags":[
        "club"
    ],
    "wof:name":"Lytham Bridge Club",
    "wof:placetype":"venue"
},
  "geometry": {"coordinates":[-2.992318,53.7402],"type":"Point"}
}