{
  "type": "Feature",
  "properties": {
    "iso:country":"GB",
    "sg:address":"10 George Street",
    "sg:city":"Edinburgh",
    "sg:classifiers":[
        {
            "category":"Communications",
            "subcategory":"Newspaper",
            "type":"Services"
        }
    ],
    "sg:phone":"+44 131 200 8100",
    "sg:postcode":"EH2 2DU",
    "sg:province":"City of Edinburgh",
    "sg:tags":[
        "magazine"
    ],
    "wof:name":"The Herald",
    "wof:placetype":"venue"
},
  "geometry": {"coordinates":[-3.194794,55.953747],"type":"Point"}
}