{
  "type": "Feature",
  "properties": {
    "iso:country":"GB",
    "sg:address":"Cold Harbour, Amesbury",
    "sg:city":"Salisbury",
    "sg:classifiers":[
        {
            "category":"Education",
            "subcategory":"School",
            "type":"Public Place"
        },
        {
            "category":"Government",
            "subcategory":"Office",
            "type":"Public Place"
        }
    ],
    "sg:phone":"+44 1980 623879",
    "sg:postcode":"SP4 7AH",
    "sg:province":"Hampshire",
    "sg:tags":[
        "local",
        "authority"
    ],
    "wof:name":"Amesbury County Infant School",
    "wof:placetype":"venue"
},
  "geometry": {"coordinates":[-1.77721,51.169476],"type":"Point"}
}