{
  "type": "Feature",
  "properties": {
    "addr:full":"Platt Avenue Sandbach Cheshire CW11 1DF",
    "addr:postcode":"cw11 1df",
    "addr:street":"Platt Avenue",
    "iso:country":"GB",
    "sg:address":"Platt Avenue",
    "sg:city":"Sandbach",
    "sg:classifiers":[
        {
            "category":"Health Services",
            "subcategory":"Clinic",
            "type":"Services"
        },
        {
            "category":"Health Services",
            "subcategory":"Dentist",
            "type":"Services"
        }
    ],
    "sg:phone":"+44 1270 762960",
    "sg:postcode":"CW11 1DF",
    "sg:province":"Cheshire",
    "sg:tags":[
        "nh"
    ],
    "wof:name":"Sandbach Clinic",
    "wof:placetype":"venue"
},
  "geometry": {"coordinates":[-2.3700389862,53.1477165222],"type":"Point"}
}