{
  "type": "Feature",
  "properties": {
    "addr:full":"Duirland Farm, Glenfruin Helensburgh Argyll and Bute G84 9ED",
    "addr:postcode":"g84 9ed",
    "addr:street":"Glenfruin",
    "iso:country":"GB",
    "sg:address":"Duirland Farm, Glenfruin",
    "sg:city":"Helensburgh",
    "sg:classifiers":[
        {
            "category":"Farming",
            "subcategory":"Farm",
            "type":"Manufacturing & Wholesale Goods"
        }
    ],
    "sg:phone":"+44 1436 673370",
    "sg:postcode":"G84 9ED",
    "sg:province":"Argyll and Bute",
    "sg:tags":[
        "mixed",
        "crop"
    ],
    "wof:name":"Andrew Borland",
    "wof:placetype":"venue"
},
  "geometry": {"coordinates":[-4.732149,56.006584],"type":"Point"}
}