{
  "type": "Feature",
  "properties": {
    "addr:full":"51 North St, Bedminster Bristol City of Bristol BS3 1EN",
    "addr:housenumber":"51",
    "addr:postcode":"bs3 1en",
    "addr:street":"North St",
    "iso:country":"GB",
    "sg:address":"51 North St, Bedminster",
    "sg:city":"Bristol",
    "sg:classifiers":[
        {
            "category":"Bars & Pubs",
            "type":"Food & Drink"
        }
    ],
    "sg:postcode":"BS3 1EN",
    "sg:province":"City of Bristol",
    "sg:tags":[
        "pubs",
        "inn"
    ],
    "wof:name":"Fagnangi,Giulio,",
    "wof:placetype":"venue"
},
  "geometry": {"coordinates":[-2.603737,51.440918],"type":"Point"}
}