{
  "type": "Feature",
  "properties": {
    "iso:country":"GB",
    "sg:address":"Gobbits Yd, The Thoroughfare,",
    "sg:city":"Woodbridge",
    "sg:classifiers":[
        {
            "category":"Building & Trades",
            "subcategory":"Construction",
            "type":"Services"
        }
    ],
    "sg:postcode":"IP12 1AQ",
    "sg:province":"Suffolk",
    "sg:tags":[
        "builder"
    ],
    "wof:name":"Consolidated Management & Construction L",
    "wof:placetype":"venue"
},
  "geometry": {"coordinates":[1.3253899813,52.1054496765],"type":"Point"}
}