{
  "type": "Feature",
  "properties": {
    "iso:country":"GB",
    "sg:address":"Riverdale 89 Graham Road, Ranmoor",
    "sg:city":"Sheffield",
    "sg:classifiers":[
        {
            "category":"Professional",
            "subcategory":"Management & Consulting",
            "type":"Services"
        }
    ],
    "sg:phone":"+44 114 230 9998",
    "sg:postcode":"S10 3GP",
    "sg:province":"South Yorkshire",
    "sg:tags":[
        "consultant",
        "business"
    ],
    "wof:name":"Isis Projects Uk Ltd.",
    "wof:placetype":"venue"
},
  "geometry": {"coordinates":[-1.52194,53.369461],"type":"Point"}
}