{
  "type": "Feature",
  "properties": {
    "iso:country":"GB",
    "sg:address":"Eastlands, Coal Park Lane",
    "sg:city":"Southampton",
    "sg:classifiers":[
        {
            "category":"Recreation",
            "subcategory":"Marina",
            "type":"Entertainment"
        }
    ],
    "sg:phone":"+44 23 8040 3556",
    "sg:postcode":"SO31 7GW",
    "sg:province":"Hampshire",
    "sg:tags":[
        "mooring",
        "boat"
    ],
    "wof:name":"Eastlands Boatyards",
    "wof:placetype":"venue"
},
  "geometry": {"coordinates":[-1.290982,50.887428],"type":"Point"}
}