{
  "type": "Feature",
  "properties": {
    "addr:full":"211 Arthur Rd Windsor Berkshire SL4 1RZ",
    "addr:housenumber":"211",
    "addr:postcode":"sl4 1rz",
    "addr:street":"Arthur Rd",
    "iso:country":"GB",
    "sg:address":"211 Arthur Rd",
    "sg:city":"Windsor",
    "sg:classifiers":[
        {
            "category":"Professional",
            "subcategory":"Management & Consulting",
            "type":"Services"
        }
    ],
    "sg:phone":"+44 1753 858087",
    "sg:postcode":"SL4 1RZ",
    "sg:province":"Berkshire",
    "sg:tags":[
        "consultant",
        "specialist"
    ],
    "wof:name":"Elizabeth Of Windsor",
    "wof:placetype":"venue"
},
  "geometry": {"coordinates":[-0.619525,51.483341],"type":"Point"}
}