{
  "type": "Feature",
  "properties": {
    "addr:full":"5 Llwynderi Road Newport Newport NP20 4LW",
    "addr:housenumber":"5",
    "addr:postcode":"np20 4lw",
    "addr:street":"Llwynderi Road",
    "iso:country":"GB",
    "sg:address":"5 Llwynderi Road",
    "sg:city":"Newport",
    "sg:classifiers":[
        {
            "category":"Government",
            "subcategory":"Fire Station",
            "type":"Public Place"
        },
        {
            "category":"Building & Trades",
            "subcategory":"Equipment Rental",
            "type":"Services"
        }
    ],
    "sg:phone":"+44 1633 266207",
    "sg:postcode":"NP20 4LW",
    "sg:province":"Newport",
    "sg:tags":[
        "security",
        "firefighting"
    ],
    "wof:name":"Celtic Fire Protection Ltd.",
    "wof:placetype":"venue"
},
  "geometry": {"coordinates":[-3.011177,51.585819],"type":"Point"}
}