{
  "type": "Feature",
  "properties": {
    "addr:full":"4 Walmley Close Sutton Coldfield Warwickshire B76 1NQ",
    "addr:housenumber":"4",
    "addr:postcode":"b76 1nq",
    "addr:street":"Walmley Close",
    "iso:country":"GB",
    "sg:address":"4 Walmley Close",
    "sg:city":"Sutton Coldfield",
    "sg:classifiers":[
        {
            "category":"Food & Beverages",
            "subcategory":"Groceries & Convenience Stores",
            "type":"Retail Goods"
        }
    ],
    "sg:phone":"+44 121 351 1743",
    "sg:postcode":"B76 1NQ",
    "sg:province":"Warwickshire",
    "wof:name":"Alldays Stores Ltd.",
    "wof:placetype":"venue"
},
  "geometry": {"coordinates":[-1.800682,52.540462],"type":"Point"}
}