{
  "type": "Feature",
  "properties": {
    "addr:full":"Park Lane Medical Centre, 187 Park La Macclesfield Cheshire SK11 6UD",
    "addr:housenumber":"187",
    "addr:postcode":"sk11 6ud",
    "addr:street":"Park La Macclesfield",
    "iso:country":"GB",
    "sg:address":"Park Lane Medical Centre, 187 Park La",
    "sg:city":"Macclesfield",
    "sg:classifiers":[
        {
            "category":"Health Services",
            "subcategory":"Doctor",
            "type":"Services"
        }
    ],
    "sg:phone":"+44 1625 422893",
    "sg:postcode":"SK11 6UD",
    "sg:province":"Cheshire",
    "sg:tags":[
        "practitioners"
    ],
    "wof:name":"Heyworth, R C F",
    "wof:placetype":"venue"
},
  "geometry": {"coordinates":[-2.125756,53.255669],"type":"Point"}
}