{
  "type": "Feature",
  "properties": {
    "iso:country":"GB",
    "sg:address":"New Road",
    "sg:city":"Huddersfield",
    "sg:classifiers":[
        {
            "category":"Education",
            "subcategory":"School",
            "type":"Public Place"
        }
    ],
    "sg:phone":"+44 1484 226667",
    "sg:postcode":"HD5 0HR",
    "sg:province":"West Yorkshire",
    "sg:tags":[
        "local",
        "authority"
    ],
    "wof:name":"J & I Kirkheaton School",
    "wof:placetype":"venue"
},
  "geometry": {"coordinates":[-1.7336809635,53.6660232544],"type":"Point"}
}