{
  "type": "Feature",
  "properties": {
    "addr:full":"1 Tavern Lane Dereham Norfolk NR19 1PX",
    "addr:housenumber":"1",
    "addr:postcode":"nr19 1px",
    "addr:street":"Tavern Lane",
    "iso:country":"GB",
    "sg:address":"1 Tavern Lane",
    "sg:city":"Dereham",
    "sg:classifiers":[
        {
            "category":"Professional",
            "subcategory":"Computer Services",
            "type":"Services"
        }
    ],
    "sg:phone":"+44 1362 691999",
    "sg:postcode":"NR19 1PX",
    "sg:province":"Norfolk",
    "sg:tags":[
        "system",
        "software"
    ],
    "wof:name":"M D F Systems Ltd.",
    "wof:placetype":"venue"
},
  "geometry": {"coordinates":[0.9458619952,52.6724777222],"type":"Point"}
}