{
  "type": "Feature",
  "properties": {
    "iso:country":"GB",
    "sg:address":"36 Vere Rd",
    "sg:city":"Rugby",
    "sg:classifiers":[
        {
            "category":"Building & Trades",
            "subcategory":"Construction",
            "type":"Services"
        }
    ],
    "sg:postcode":"CV21 4HR",
    "sg:province":"Warwickshire",
    "sg:tags":[
        "builder"
    ],
    "wof:name":"Lawson,J,",
    "wof:placetype":"venue"
},
  "geometry": {"coordinates":[-1.228289,52.363525],"type":"Point"}
}