{
  "type": "Feature",
  "properties": {
    "addr:full":"Dark Lane, Sunningwell Abingdon Oxfordshire OX13 6RE",
    "addr:postcode":"ox13 6re",
    "addr:street":"Dark Lane",
    "iso:country":"GB",
    "sg:address":"Dark Lane, Sunningwell",
    "sg:city":"Abingdon",
    "sg:classifiers":[
        {
            "category":"Education",
            "subcategory":"School",
            "type":"Public Place"
        }
    ],
    "sg:phone":"+44 1865 739378",
    "sg:postcode":"OX13 6RE",
    "sg:province":"Oxfordshire",
    "sg:tags":[
        "local",
        "authority"
    ],
    "wof:name":"Sunningwell C of E Primary School",
    "wof:placetype":"venue"
},
  "geometry": {"coordinates":[-1.2889480591,51.7007713318],"type":"Point"}
}