{
  "type": "Feature",
  "properties": {
    "addr:full":"101 London Road, Copford Colchester Essex CO6 1LG",
    "addr:housenumber":"101",
    "addr:postcode":"co6 1lg",
    "addr:street":"London Road",
    "iso:country":"GB",
    "sg:address":"101 London Road, Copford",
    "sg:city":"Colchester",
    "sg:classifiers":[
        {
            "category":"Professional",
            "subcategory":"Secretarial Services",
            "type":"Services"
        },
        {
            "category":"Professional",
            "subcategory":"Art Services",
            "type":"Services"
        }
    ],
    "sg:phone":"+44 1206 211621",
    "sg:postcode":"CO6 1LG",
    "sg:province":"Essex",
    "sg:tags":[
        "photographer"
    ],
    "wof:name":"Anglian Care Services",
    "wof:placetype":"venue"
},
  "geometry": {"coordinates":[0.7985950112,51.8802680969],"type":"Point"}
}