{
  "type": "Feature",
  "properties": {
    "iso:country":"GB",
    "sg:address":"29a Tavistock Street, Bedford",
    "sg:city":"Bedford",
    "sg:classifiers":[
        {
            "category":"Shopping",
            "subcategory":"Beauty & Cosmetics",
            "type":"Retail Goods"
        }
    ],
    "sg:phone":"+44 1234 346563",
    "sg:postcode":"MK40 2RB",
    "sg:province":"Bedfordshire",
    "sg:tags":[
        "equipment",
        "supply",
        "hairdressing"
    ],
    "wof:name":"Trendpack Ltd.",
    "wof:placetype":"venue"
},
  "geometry": {"coordinates":[-0.4689509869,52.1403236389],"type":"Point"}
}