{
  "type": "Feature",
  "properties": {
    "addr:full":"57 Exeter Road, Kingsteignton Newton Abbot Devon TQ12 3HY",
    "addr:housenumber":"57",
    "addr:postcode":"tq12 3hy",
    "addr:street":"Exeter Road",
    "iso:country":"GB",
    "sg:address":"57 Exeter Road, Kingsteignton",
    "sg:city":"Newton Abbot",
    "sg:classifiers":[
        {
            "category":"Shopping",
            "subcategory":"Bicycles & Sporting Goods",
            "type":"Retail Goods"
        }
    ],
    "sg:phone":"+44 1626 335799",
    "sg:postcode":"TQ12 3HY",
    "sg:province":"Devon",
    "sg:tags":[
        "cycle",
        "accessory"
    ],
    "wof:name":"Green Machine",
    "wof:placetype":"venue"
},
  "geometry": {"coordinates":[-3.5970311165,50.552028656],"type":"Point"}
}