{
  "type": "Feature",
  "properties": {
    "addr:full":"Britannia Way Wisbech Cambridgeshire PE13 2RB",
    "addr:postcode":"pe13 2rb",
    "addr:street":"Britannia Way",
    "iso:country":"GB",
    "sg:address":"Britannia Way",
    "sg:city":"Wisbech",
    "sg:classifiers":[
        {
            "category":"Building & Trades",
            "subcategory":"Construction",
            "type":"Services"
        }
    ],
    "sg:phone":"+44 1945 588433",
    "sg:postcode":"PE13 2RB",
    "sg:province":"Cambridgeshire",
    "sg:tags":[
        "builder"
    ],
    "wof:name":"J W Tuck Ltd",
    "wof:placetype":"venue"
},
  "geometry": {"coordinates":[0.1584510058,52.6519317627],"type":"Point"}
}