{
  "type": "Feature",
  "properties": {
    "iso:country":"GB",
    "sg:address":"Unit 7 Castle Street, Castlepark Industrial Estate",
    "sg:city":"Ellon",
    "sg:classifiers":[
        {
            "category":"Retail",
            "subcategory":"Auto Repair",
            "type":"Services"
        }
    ],
    "sg:postcode":"AB41 9RF",
    "sg:province":"Aberdeenshire",
    "sg:tags":[
        "modification",
        "garage"
    ],
    "wof:name":"Castlepark Garage",
    "wof:placetype":"venue"
},
  "geometry": {"coordinates":[-2.058032,57.368958],"type":"Point"}
}