{
  "type": "Feature",
  "properties": {
    "iso:country":"GB",
    "sg:address":"Unit 3, Crewe Close, Blidworth Industrial Estate",
    "sg:city":"Mansfield",
    "sg:classifiers":[
        {
            "category":"Home & Garden",
            "subcategory":"Hardware",
            "type":"Retail Goods"
        }
    ],
    "sg:phone":"+44 1623 795695",
    "sg:postcode":"NG21 0TA",
    "sg:province":"Nottinghamshire",
    "sg:tags":[
        "compressor",
        "air"
    ],
    "wof:name":"Compressed Air Repairs",
    "wof:placetype":"venue"
},
  "geometry": {"coordinates":[-1.117757,53.102161],"type":"Point"}
}