{
  "type": "Feature",
  "properties": {
    "iso:country":"GB",
    "sg:address":"92 High St",
    "sg:city":"Dudley",
    "sg:classifiers":[
        {
            "category":"Shopping",
            "subcategory":"Jewelry",
            "type":"Retail Goods"
        }
    ],
    "sg:phone":"+44 1384 252122",
    "sg:postcode":"DY1 1QP",
    "sg:province":"West Midlands",
    "sg:tags":[
        "gold",
        "silversmith"
    ],
    "wof:name":"Kashmir Jewellers of Kotli",
    "wof:placetype":"venue"
},
  "geometry": {"coordinates":[-2.0883169174,52.5080070496],"type":"Point"}
}