{
  "type": "Feature",
  "properties": {
    "iso:country":"GB",
    "sg:address":"Buckhole Farm Cottage, Cooling Road, High Halstow",
    "sg:city":"Rochester",
    "sg:classifiers":[
        {
            "category":"Professional",
            "subcategory":"Accounting & Tax Preparation",
            "type":"Services"
        },
        {
            "category":"Banks & Credit Unions",
            "subcategory":"Bank",
            "type":"Services"
        }
    ],
    "sg:phone":"+44 1634 255143",
    "sg:postcode":"ME3 8SE",
    "sg:province":"Kent",
    "sg:tags":[
        "accountant",
        "financial",
        "institution"
    ],
    "wof:name":"SMALL BUSINESS ACCOUNTING SERVICES",
    "wof:placetype":"venue"
},
  "geometry": {"coordinates":[0.531158,51.456314],"type":"Point"}
}