{
  "type": "Feature",
  "properties": {
    "addr:full":"West Side, Tyne Dock South Shields Tyne and Wear NE34 9PJ",
    "addr:postcode":"ne34 9pj",
    "addr:street":"West;Dock",
    "iso:country":"GB",
    "sg:address":"West Side, Tyne Dock",
    "sg:city":"South Shields",
    "sg:classifiers":[
        {
            "category":"Manufacturing",
            "subcategory":"Lumber",
            "type":"Manufacturing & Wholesale Goods"
        }
    ],
    "sg:phone":"+44 191 489 8134",
    "sg:postcode":"NE34 9PJ",
    "sg:province":"Tyne and Wear",
    "sg:tags":[
        "importer",
        "merchants",
        "agent",
        "timber"
    ],
    "wof:name":"Edmund Robson & Co. Ltd.",
    "wof:placetype":"venue"
},
  "geometry": {"coordinates":[-1.454589963,54.9846992493],"type":"Point"}
}