{
  "type": "Feature",
  "properties": {
    "addr:full":"Unit 32 Moorlands Business Centre, Balme Rd Cleckheaton West Yorkshire BD19 4EZ",
    "addr:housenumber":"unit 32",
    "addr:postcode":"bd19 4ez",
    "addr:street":"Balme Rd",
    "iso:country":"GB",
    "sg:address":"Unit 32 Moorlands Business Centre, Balme Rd",
    "sg:city":"Cleckheaton",
    "sg:classifiers":[
        {
            "category":"Professional",
            "subcategory":"Advertising",
            "type":"Services"
        }
    ],
    "sg:phone":"+44 1274 852566",
    "sg:postcode":"BD19 4EZ",
    "sg:province":"West Yorkshire",
    "sg:tags":[
        "agency"
    ],
    "wof:name":"Creative Edge Advertising & Marketing Ltd",
    "wof:placetype":"venue"
},
  "geometry": {"coordinates":[-1.7118890285,53.7251701355],"type":"Point"}
}