{
  "type": "Feature",
  "properties": {
    "addr:full":"5 The Lawns Cambridge Cambridgeshire CB2 4NG",
    "addr:housenumber":"5",
    "addr:postcode":"cb2 4ng",
    "addr:street":"The Lawns",
    "iso:country":"GB",
    "sg:address":"5 The Lawns",
    "sg:city":"Cambridge",
    "sg:classifiers":[
        {
            "category":"Building & Trades",
            "subcategory":"Construction",
            "type":"Services"
        }
    ],
    "sg:phone":"+44 1223 833888",
    "sg:postcode":"CB2 4NG",
    "sg:province":"Cambridgeshire",
    "sg:tags":[
        "builder"
    ],
    "wof:name":"Dennis A Mcguigan",
    "wof:placetype":"venue"
},
  "geometry": {"coordinates":[0.1518640071,52.1143836975],"type":"Point"}
}