{
  "type": "Feature",
  "properties": {
    "addr:full":"74 St Thomas Street Wells Somerset BA5 2UZ",
    "addr:housenumber":"74",
    "addr:postcode":"ba5 2uz",
    "addr:street":"St Thomas Street",
    "iso:country":"GB",
    "sg:address":"74 St Thomas Street",
    "sg:city":"Wells",
    "sg:classifiers":[
        {
            "category":"Shopping",
            "subcategory":"Antiques",
            "type":"Retail Goods"
        }
    ],
    "sg:phone":"+44 1749 672520",
    "sg:postcode":"BA5 2UZ",
    "sg:province":"Somerset",
    "wof:name":"Ken Holdsworth",
    "wof:placetype":"venue"
},
  "geometry": {"coordinates":[-2.6374759674,51.2129974365],"type":"Point"}
}