{
  "type": "Feature",
  "properties": {
    "addr:full":"Green Lane, Quidenam Norwich Norfolk NR16 2AP",
    "addr:postcode":"nr16 2ap",
    "addr:street":"Green Lane Quidenam Norwich",
    "iso:country":"GB",
    "sg:address":"Green Lane, Quidenam",
    "sg:city":"Norwich",
    "sg:classifiers":[
        {
            "category":"Cafe",
            "type":"Food & Drink"
        }
    ],
    "sg:phone":"+44 1953 887200",
    "sg:postcode":"NR16 2AP",
    "sg:province":"Norfolk",
    "sg:tags":[
        "tea",
        "room"
    ],
    "wof:name":"Quidenham P.O",
    "wof:placetype":"venue"
},
  "geometry": {"coordinates":[0.9256650209,52.4394683838],"type":"Point"}
}