{
  "type": "Feature",
  "properties": {
    "iso:country":"GB",
    "sg:address":"11 Bury Road",
    "sg:city":"Newmarket",
    "sg:classifiers":[
        {
            "category":"Travel",
            "subcategory":"Hotels & Motels",
            "type":"Entertainment"
        },
        {
            "category":"Community Center",
            "type":"Public Place"
        }
    ],
    "sg:phone":"+44 1638 663175",
    "sg:postcode":"CB8 7BX",
    "sg:province":"Cambridgeshire",
    "sg:tags":[
        "recreation",
        "leisure",
        "centre"
    ],
    "wof:name":"Bedford Lodge Hotel",
    "wof:placetype":"venue"
},
  "geometry": {"coordinates":[0.4212149978,52.2536315918],"type":"Point"}
}