{
  "type": "Feature",
  "properties": {
    "addr:full":"161 High Street, Hampton Hill Hampton Greater London TW12 1NG",
    "addr:housenumber":"161",
    "addr:postcode":"tw12 1ng",
    "addr:street":"High Street",
    "iso:country":"GB",
    "sg:address":"161 High Street, Hampton Hill",
    "sg:city":"Hampton",
    "sg:classifiers":[
        {
            "category":"Insurance",
            "subcategory":"Insurance Agent",
            "type":"Services"
        }
    ],
    "sg:phone":"+44 20 8941 1535",
    "sg:postcode":"TW12 1NG",
    "sg:province":"Greater London",
    "sg:tags":[
        "broker"
    ],
    "wof:name":"Allen & Allen",
    "wof:placetype":"venue"
},
  "geometry": {"coordinates":[-0.3555150032,51.4276123047],"type":"Point"}
}