{
  "type": "Feature",
  "properties": {
    "addr:full":"23 Yarm Durham TS18 3NJ",
    "addr:housenumber":"23 yarm",
    "addr:postcode":"ts18 3nj",
    "iso:country":"GB",
    "sg:address":"23",
    "sg:city":"Yarm",
    "sg:classifiers":[
        {
            "category":"Professional",
            "subcategory":"Management & Consulting",
            "type":"Services"
        }
    ],
    "sg:postcode":"TS18 3NJ",
    "sg:province":"Durham",
    "sg:tags":[
        "consultant",
        "business"
    ],
    "wof:name":"Vento Consultants Ltd",
    "wof:placetype":"venue"
},
  "geometry": {"coordinates":[-1.322053,54.559944],"type":"Point"}
}