{
  "type": "Feature",
  "properties": {
    "iso:country":"GB",
    "sg:address":"25 Alma Square",
    "sg:city":"Scarborough",
    "sg:classifiers":[
        {
            "category":"Professional",
            "subcategory":"Lawyer & Legal Services",
            "type":"Services"
        }
    ],
    "sg:phone":"+44 1723 371426",
    "sg:postcode":"YO11 1JR",
    "sg:province":"North Yorkshire",
    "sg:tags":[
        "solicitor"
    ],
    "wof:name":"Birdfall & Snowball Solicitors",
    "wof:placetype":"venue"
},
  "geometry": {"coordinates":[-0.40493,54.28093],"type":"Point"}
}