{
  "type": "Feature",
  "properties": {
    "addr:full":"443 Victoria Road Ruislip Greater London HA4 0EG",
    "addr:housenumber":"443",
    "addr:postcode":"ha4 0eg",
    "addr:street":"Victoria Road",
    "iso:country":"GB",
    "sg:address":"443 Victoria Road",
    "sg:city":"Ruislip",
    "sg:classifiers":[
        {
            "category":"Cafe",
            "type":"Food & Drink"
        }
    ],
    "sg:phone":"+44 20 8845 9365",
    "sg:postcode":"HA4 0EG",
    "sg:province":"Greater London",
    "sg:tags":[
        "tea",
        "snack",
        "bar",
        "room"
    ],
    "wof:name":"New Rumbling Tum Cafe",
    "wof:placetype":"venue"
},
  "geometry": {"coordinates":[-0.399255991,51.5601234436],"type":"Point"}
}