{
  "type": "Feature",
  "properties": {
    "addr:full":"12-14 Holme Lane Sheffield South Yorkshire S6 4JQ",
    "addr:housenumber":"12-14",
    "addr:postcode":"s6 4jq",
    "addr:street":"Holme Lane",
    "iso:country":"GB",
    "sg:address":"12-14 Holme Lane",
    "sg:city":"Sheffield",
    "sg:classifiers":[
        {
            "category":"Shopping",
            "subcategory":"Florist",
            "type":"Retail Goods"
        }
    ],
    "sg:phone":"+44 114 234 4163",
    "sg:postcode":"S6 4JQ",
    "sg:province":"South Yorkshire",
    "wof:name":"The Flower Bowl",
    "wof:placetype":"venue"
},
  "geometry": {"coordinates":[-1.5019949675,53.4023246765],"type":"Point"}
}