{
  "type": "Feature",
  "properties": {
    "addr:full":"A1 Northbound, Foston Grantham Leicestershire NG32 2LD",
    "addr:postcode":"ng32 2ld",
    "addr:street":"Foston",
    "iso:country":"GB",
    "sg:address":"A1 Northbound, Foston",
    "sg:city":"Grantham",
    "sg:classifiers":[
        {
            "category":"Autos & Motor Vehicles",
            "subcategory":"Fuel & Gas Station",
            "type":"Retail Goods"
        }
    ],
    "sg:phone":"+44 1400 281862",
    "sg:postcode":"NG32 2LD",
    "sg:province":"Leicestershire",
    "sg:tags":[
        "hr",
        "petrol"
    ],
    "wof:name":"Foston Service Station",
    "wof:placetype":"venue"
},
  "geometry": {"coordinates":[-0.7243520021,52.9727020264],"type":"Point"}
}