{
  "type": "Feature",
  "properties": {
    "addr:full":"3 Station Parade, Upper Clapton Road London Greater London E5 8BD",
    "addr:housenumber":"3",
    "addr:postcode":"e5 8bd",
    "addr:street":"Station Parade Upper Clapton Road",
    "iso:country":"GB",
    "sg:address":"3 Station Parade, Upper Clapton Road",
    "sg:city":"London",
    "sg:classifiers":[
        {
            "category":"Personal",
            "subcategory":"Beauty Salon",
            "type":"Services"
        }
    ],
    "sg:phone":"+44 20 8806 7030",
    "sg:postcode":"E5 8BD",
    "sg:province":"Greater London",
    "sg:tags":[
        "unisex",
        "hairdresser"
    ],
    "wof:name":"Vallaine's",
    "wof:placetype":"venue"
},
  "geometry": {"coordinates":[-0.05619,51.56031],"type":"Point"}
}