{
  "type": "Feature",
  "properties": {
    "iso:country":"GB",
    "sg:address":"66 The Homend",
    "sg:city":"Ledbury",
    "sg:classifiers":[
        {
            "category":"Autos & Motor Vehicles",
            "subcategory":"Auto Supplies",
            "type":"Retail Goods"
        },
        {
            "category":"Shopping",
            "type":"Retail Goods"
        }
    ],
    "sg:phone":"+44 1531 633275",
    "sg:postcode":"HR8 1BT",
    "sg:province":"Gloucestershire",
    "sg:tags":[
        "car",
        "part",
        "accessory"
    ],
    "wof:name":"John Moss",
    "wof:placetype":"venue"
},
  "geometry": {"coordinates":[-2.4246571064,52.0390548706],"type":"Point"}
}