{
  "type": "Feature",
  "properties": {
    "iso:country":"GB",
    "sg:address":"Glaziers Lane Farm, Glaziers Lane, Culcheth",
    "sg:city":"Warrington",
    "sg:classifiers":[
        {
            "category":"Farming",
            "subcategory":"Livestock Farm",
            "type":"Manufacturing & Wholesale Goods"
        }
    ],
    "sg:postcode":"WA3 4AH",
    "sg:province":"Cheshire",
    "sg:tags":[
        "others"
    ],
    "wof:name":"W L Higginson",
    "wof:placetype":"venue"
},
  "geometry": {"coordinates":[-2.525525,53.445278],"type":"Point"}
}