{
  "type": "Feature",
  "properties": {
    "addr:full":"Arden Road Smethwick West Midlands B67 6AL",
    "addr:postcode":"b67 6al",
    "addr:street":"Arden Road",
    "iso:country":"GB",
    "sg:address":"Arden Road",
    "sg:city":"Smethwick",
    "sg:classifiers":[
        {
            "category":"Education",
            "subcategory":"Special Training",
            "type":"Public Place"
        },
        {
            "category":"Government",
            "subcategory":"Office",
            "type":"Public Place"
        }
    ],
    "sg:phone":"+44 121 558 0275",
    "sg:postcode":"B67 6AL",
    "sg:province":"West Midlands",
    "sg:tags":[
        "school",
        "local"
    ],
    "wof:name":"Sandwell Metropolitan Borough Council Key Stage 4",
    "wof:placetype":"venue"
},
  "geometry": {"coordinates":[-1.9691590071,52.4921302795],"type":"Point"}
}