{
  "type": "Feature",
  "properties": {
    "iso:country":"GB",
    "sg:address":"Challenge Ho, 57-59 Queens Rd",
    "sg:city":"Buckhurst Hill",
    "sg:classifiers":[
        {
            "category":"Professional",
            "subcategory":"Business Services",
            "type":"Services"
        }
    ],
    "sg:phone":"+44 20 8505 7777",
    "sg:postcode":"IG9 5BU",
    "sg:province":"Essex",
    "sg:tags":[
        "holding"
    ],
    "wof:name":"Henson Corporation Ltd The",
    "wof:placetype":"venue"
},
  "geometry": {"coordinates":[0.030989,51.624306],"type":"Point"}
}