{
  "type": "Feature",
  "properties": {
    "addr:full":"Cefn Parc Stud, Cefn Cribbwr Bridgend Bridgend CF32 0BP",
    "addr:postcode":"cf32 0bp",
    "addr:street":"Cefn Cribbwr",
    "iso:country":"GB",
    "sg:address":"Cefn Parc Stud, Cefn Cribbwr",
    "sg:city":"Bridgend",
    "sg:classifiers":[
        {
            "category":"Farming",
            "subcategory":"Livestock Farm",
            "type":"Manufacturing & Wholesale Goods"
        }
    ],
    "sg:phone":"+44 1656 740365",
    "sg:postcode":"CF32 0BP",
    "sg:province":"Bridgend",
    "sg:tags":[
        "others"
    ],
    "wof:name":"T E Thomas",
    "wof:placetype":"venue"
},
  "geometry": {"coordinates":[-3.6637380123,51.5320281982],"type":"Point"}
}