{
  "type": "Feature",
  "properties": {
    "iso:country":"GB",
    "sg:address":"Barn Farm, Flawforth Lane, Ruddington",
    "sg:city":"Nottingham",
    "sg:classifiers":[
        {
            "category":"Food & Beverages",
            "subcategory":"Groceries & Convenience Stores",
            "type":"Retail Goods"
        }
    ],
    "sg:postcode":"NG11 6NG",
    "sg:province":"Nottinghamshire",
    "sg:tags":[
        "merchant",
        "potato"
    ],
    "wof:name":"A & K Merchants",
    "wof:placetype":"venue"
},
  "geometry": {"coordinates":[-1.149353981,52.8920631409],"type":"Point"}
}