{
  "type": "Feature",
  "properties": {
    "iso:country":"GB",
    "sg:address":"10 Iliffe Yard, Crampton Street",
    "sg:city":"London",
    "sg:classifiers":[
        {
            "category":"Building & Trades",
            "subcategory":"Cleaning & Sanitation",
            "type":"Services"
        }
    ],
    "sg:postcode":"SE17 3QA",
    "sg:province":"Greater London",
    "sg:tags":[
        "commercial"
    ],
    "wof:name":"6 O'Clock Cleaning Services Ltd.",
    "wof:placetype":"venue"
},
  "geometry": {"coordinates":[-0.1004199982,51.4895935059],"type":"Point"}
}