{
  "type": "Feature",
  "properties": {
    "iso:country":"GB",
    "sg:address":"Rear Of 84 Douglas Road",
    "sg:city":"Hornchurch",
    "sg:classifiers":[
        {
            "category":"Retail",
            "subcategory":"Auto Repair",
            "type":"Services"
        }
    ],
    "sg:phone":"+44 1708 726518",
    "sg:postcode":"RM11 1AR",
    "sg:province":"Essex",
    "sg:tags":[
        "modification",
        "garage"
    ],
    "wof:name":"Grove Garage",
    "wof:placetype":"venue"
},
  "geometry": {"coordinates":[0.2203799933,51.5620994568],"type":"Point"}
}