{
  "type": "Feature",
  "properties": {
    "iso:country":"GB",
    "sg:address":"Swyncombe Rectory",
    "sg:city":"Henley On Thames",
    "sg:classifiers":[
        {
            "category":"Place Of Worship",
            "type":"Public Place"
        }
    ],
    "sg:phone":"+44 1491 641249",
    "sg:postcode":"RG9 6EA",
    "sg:province":"Berkshire",
    "wof:name":"St Nicholas Britwell Salome",
    "wof:placetype":"venue"
},
  "geometry": {"coordinates":[-1.0149099827,51.60572052],"type":"Point"}
}