{
  "type": "Feature",
  "properties": {
    "addr:full":"344 Baker Street Enfield Greater London EN1 3LQ",
    "addr:housenumber":"344",
    "addr:postcode":"en1 3lq",
    "addr:street":"Baker Street",
    "iso:country":"GB",
    "sg:address":"344 Baker Street",
    "sg:city":"Enfield",
    "sg:classifiers":[
        {
            "category":"Home & Garden",
            "subcategory":"Household Appliances",
            "type":"Retail Goods"
        }
    ],
    "sg:phone":"+44 20 8363 3538",
    "sg:postcode":"EN1 3LQ",
    "sg:province":"Greater London",
    "sg:tags":[
        "electrical"
    ],
    "wof:name":"A 1 Electrics of Enfield Ltd.",
    "wof:placetype":"venue"
},
  "geometry": {"coordinates":[-0.0766130015,51.6636276245],"type":"Point"}
}