{
  "type": "Feature",
  "properties": {
    "iso:country":"GB",
    "sg:address":"42 Wellington Road, Denton",
    "sg:city":"Newhaven",
    "sg:classifiers":[
        {
            "category":"Building & Trades",
            "subcategory":"Landscaping Services",
            "type":"Services"
        }
    ],
    "sg:postcode":"BN9 0RD",
    "sg:province":"East Sussex",
    "sg:tags":[
        "gardening"
    ],
    "wof:name":"Michel Robert Hill",
    "wof:placetype":"venue"
},
  "geometry": {"coordinates":[0.0652230009,50.8061828613],"type":"Point"}
}