{
  "type": "Feature",
  "properties": {
    "iso:country":"GB",
    "sg:address":"7 Larchdale Close, Warsash",
    "sg:city":"Southampton",
    "sg:classifiers":[
        {
            "category":"Freight",
            "type":"Transportation"
        }
    ],
    "sg:postcode":"SO31 9PU",
    "sg:province":"Hampshire",
    "sg:tags":[
        "forwarders"
    ],
    "wof:name":"Relayaim Ltd.",
    "wof:placetype":"venue"
},
  "geometry": {"coordinates":[-1.292154,50.849026],"type":"Point"}
}