{
  "type": "Feature",
  "properties": {
    "addr:full":"7 Larchdale Close, Warsash Southampton Hampshire SO31 9PU",
    "addr:housenumber":"7",
    "addr:postcode":"so31 9pu",
    "addr:street":"Larchdale Close",
    "iso:country":"GB",
    "sg:address":"7 Larchdale Close, Warsash",
    "sg:city":"Southampton",
    "sg:classifiers":[
        {
            "category":"Freight",
            "type":"Transportation"
        }
    ],
    "sg:postcode":"SO31 9PU",
    "sg:province":"Hampshire",
    "sg:tags":[
        "forwarders"
    ],
    "wof:name":"Relayaim Ltd.",
    "wof:placetype":"venue"
},
  "geometry": {"coordinates":[-1.292154,50.849026],"type":"Point"}
}