{
  "type": "Feature",
  "properties": {
    "iso:country":"GB",
    "sg:address":"Euro House 1394 High Road",
    "sg:city":"London",
    "sg:classifiers":[
        {
            "category":"Autos & Motor Vehicles",
            "subcategory":"Motorcycle Sales",
            "type":"Retail Goods"
        }
    ],
    "sg:postcode":"N20 9YZ",
    "sg:province":"Greater London",
    "sg:tags":[
        "chauffeur",
        "driven",
        "car"
    ],
    "wof:name":"Executive Travel Associates Ltd",
    "wof:placetype":"venue"
},
  "geometry": {"coordinates":[-0.1756100059,51.6333312988],"type":"Point"}
}