{
  "type": "Feature",
  "properties": {
    "iso:country":"GB",
    "sg:address":"1 Heol Y Bryn, Upper Tumble",
    "sg:city":"Llanelli",
    "sg:classifiers":[
        {
            "category":"Government",
            "subcategory":"Post Office",
            "type":"Public Place"
        }
    ],
    "sg:postcode":"SA14 6DP",
    "sg:province":"Carmarthenshire",
    "wof:name":"Upper Tumble Post Office",
    "wof:placetype":"venue"
},
  "geometry": {"coordinates":[-4.112030983,51.7855186462],"type":"Point"}
}