{
  "type": "Feature",
  "properties": {
    "iso:country":"GB",
    "sg:address":"12 Silverdale Close",
    "sg:city":"Retford",
    "sg:classifiers":[
        {
            "category":"Professional",
            "subcategory":"Engineering",
            "type":"Services"
        }
    ],
    "sg:phone":"+44 1777 706158",
    "sg:postcode":"DN22 7XP",
    "sg:province":"Nottinghamshire",
    "sg:tags":[
        "contractor",
        "electrical",
        "engineer"
    ],
    "wof:name":"Live Wires",
    "wof:placetype":"venue"
},
  "geometry": {"coordinates":[-0.962071,53.331642],"type":"Point"}
}