{
  "type": "Feature",
  "properties": {
    "addr:full":"Bell Businesspk, Rochsolloch Road Airdrie North Lanarkshire ML6 9BG",
    "addr:postcode":"ml6 9bg",
    "addr:street":"Rochsolloch Road",
    "iso:country":"GB",
    "sg:address":"Bell Businesspk, Rochsolloch Road",
    "sg:city":"Airdrie",
    "sg:classifiers":[
        {
            "category":"Building & Trades",
            "subcategory":"Construction",
            "type":"Services"
        }
    ],
    "sg:phone":"+44 1236 753584",
    "sg:postcode":"ML6 9BG",
    "sg:province":"North Lanarkshire",
    "sg:tags":[
        "decorator",
        "painter"
    ],
    "wof:name":"Lapwing Design",
    "wof:placetype":"venue"
},
  "geometry": {"coordinates":[-3.9807839394,55.8658638],"type":"Point"}
}