{
  "type": "Feature",
  "properties": {
    "iso:country":"GB",
    "sg:address":"Brymers Avenue",
    "sg:city":"Portland",
    "sg:classifiers":[
        {
            "category":"Farming",
            "subcategory":"Fish & Marine Products",
            "type":"Manufacturing & Wholesale Goods"
        }
    ],
    "sg:phone":"+44 1932 743333",
    "sg:postcode":"DT5 1JS",
    "sg:province":"Dorset",
    "sg:tags":[
        "equipment",
        "electrical"
    ],
    "wof:name":"Thorn Security Ltd.",
    "wof:placetype":"venue"
},
  "geometry": {"coordinates":[-2.4359691143,50.5469017029],"type":"Point"}
}