{
  "type": "Feature",
  "properties": {
    "iso:country":"GB",
    "sg:address":"47 Trinity View, Caerleon",
    "sg:city":"Newport",
    "sg:classifiers":[
        {
            "category":"Professional",
            "subcategory":"Lawyer & Legal Services",
            "type":"Services"
        }
    ],
    "sg:phone":"+44 1633 420476",
    "sg:postcode":"NP18 3SU",
    "sg:province":"Monmouthshire",
    "wof:name":"Employment Contracts Advisory Services",
    "wof:placetype":"venue"
},
  "geometry": {"coordinates":[-2.95921,51.616547],"type":"Point"}
}