{
  "type": "Feature",
  "properties": {
    "addr:full":"11 Hertford Road Alcester Warwickshire B49 6AL",
    "addr:housenumber":"11",
    "addr:postcode":"b49 6al",
    "addr:street":"Hertford Road",
    "iso:country":"GB",
    "sg:address":"11 Hertford Road",
    "sg:city":"Alcester",
    "sg:classifiers":[
        {
            "category":"Food & Beverages",
            "subcategory":"Meat & Fish",
            "type":"Retail Goods"
        }
    ],
    "sg:postcode":"B49 6AL",
    "sg:province":"Warwickshire",
    "sg:tags":[
        "chip"
    ],
    "wof:name":"Hertford Road Chippy",
    "wof:placetype":"venue"
},
  "geometry": {"coordinates":[-1.865525,52.220478],"type":"Point"}
}