{
  "type": "Feature",
  "properties": {
    "addr:full":"163 Clarence Road London Greater London E5 8EE",
    "addr:housenumber":"163",
    "addr:postcode":"e5 8ee",
    "addr:street":"Clarence Road",
    "iso:country":"GB",
    "sg:address":"163 Clarence Road",
    "sg:city":"London",
    "sg:classifiers":[
        {
            "category":"Retail",
            "subcategory":"Repair Shop",
            "type":"Services"
        }
    ],
    "sg:phone":"+44 20 8986 4929",
    "sg:postcode":"E5 8EE",
    "sg:province":"Greater London",
    "sg:tags":[
        "upholsterer"
    ],
    "wof:name":"Cyprus Upholstery",
    "wof:placetype":"venue"
},
  "geometry": {"coordinates":[-0.0562620014,51.5553665161],"type":"Point"}
}