{
  "type": "Feature",
  "properties": {
    "addr:full":"85 Prince Avenue Southend-on-sea Essex SS2 6RL",
    "addr:housenumber":"85",
    "addr:postcode":"ss2 6rl",
    "addr:street":"Prince Avenue",
    "iso:country":"GB",
    "sg:address":"85 Prince Avenue",
    "sg:city":"Southend-on-sea",
    "sg:classifiers":[
        {
            "category":"Professional",
            "type":"Services"
        }
    ],
    "sg:phone":"+44 1702 302000",
    "sg:postcode":"SS2 6RL",
    "sg:province":"Essex",
    "sg:tags":[
        "repair",
        "tech",
        "maintenance"
    ],
    "wof:name":"Brunel Computer Services Ltd.",
    "wof:placetype":"venue"
},
  "geometry": {"coordinates":[0.6973059773,51.558380127],"type":"Point"}
}