{
  "type": "Feature",
  "properties": {
    "iso:country":"GB",
    "sg:address":"268 Old Kent Road",
    "sg:city":"London",
    "sg:classifiers":[
        {
            "category":"Communications",
            "type":"Services"
        }
    ],
    "sg:phone":"+44 20 7708 1243",
    "sg:postcode":"SE1 5UB",
    "sg:province":"Greater London",
    "sg:tags":[
        "tv",
        "video",
        "radio"
    ],
    "wof:name":"Bobsboxes",
    "wof:placetype":"venue"
},
  "geometry": {"coordinates":[-0.07895,51.489342],"type":"Point"}
}