{
  "type": "Feature",
  "properties": {
    "addr:full":"69a High St Huntingdon Cambridgeshire PE18 6DN",
    "addr:housenumber":"69a",
    "addr:postcode":"pe18 6dn",
    "addr:street":"High St",
    "iso:country":"GB",
    "sg:address":"69a High St",
    "sg:city":"Huntingdon",
    "sg:classifiers":[
        {
            "category":"Sports & Exercise",
            "subcategory":"Golf",
            "type":"Entertainment"
        }
    ],
    "sg:phone":"+44 1480 454411",
    "sg:postcode":"PE18 6DN",
    "sg:province":"Cambridgeshire",
    "sg:tags":[
        "equipment"
    ],
    "wof:name":"Hole In One Golf Shop",
    "wof:placetype":"venue"
},
  "geometry": {"coordinates":[-0.18571,52.331322],"type":"Point"}
}