{
  "type": "Feature",
  "properties": {
    "addr:full":"Liverpool House, Lower Bridge Street Chester Cheshire CH1 1RS",
    "addr:postcode":"ch1 1rs",
    "addr:street":"Lower Bridge Street",
    "iso:country":"GB",
    "sg:address":"Liverpool House, Lower Bridge Street",
    "sg:city":"Chester",
    "sg:classifiers":[
        {
            "category":"Professional",
            "subcategory":"Management & Consulting",
            "type":"Services"
        }
    ],
    "sg:postcode":"CH1 1RS",
    "sg:province":"Cheshire",
    "sg:tags":[
        "consultant",
        "business"
    ],
    "wof:name":"McSpadden Environmental Consultancy Ltd",
    "wof:placetype":"venue"
},
  "geometry": {"coordinates":[-2.8900489807,53.1870231628],"type":"Point"}
}