{
  "type": "Feature",
  "properties": {
    "addr:full":"475 Green Lanes London Greater London N4 1AJ",
    "addr:housenumber":"475",
    "addr:postcode":"n4 1aj",
    "addr:street":"Green Lanes",
    "iso:country":"GB",
    "sg:address":"475 Green Lanes",
    "sg:city":"London",
    "sg:classifiers":[
        {
            "category":"Food & Beverages",
            "subcategory":"Supermarket",
            "type":"Retail Goods"
        }
    ],
    "sg:phone":"+44 20 8340 4958",
    "sg:postcode":"N4 1AJ",
    "sg:province":"Greater London",
    "wof:name":"Guluzar",
    "wof:placetype":"venue"
},
  "geometry": {"coordinates":[-0.09961,51.580448],"type":"Point"}
}