{
  "type": "Feature",
  "properties": {
    "addr:full":"3 Cameron Road Ilford Essex IG3 8LG",
    "addr:housenumber":"3",
    "addr:postcode":"ig3 8lg",
    "addr:street":"Cameron Road",
    "iso:country":"GB",
    "sg:address":"3 Cameron Road",
    "sg:city":"Ilford",
    "sg:classifiers":[
        {
            "category":"Fast Food",
            "type":"Food & Drink"
        }
    ],
    "sg:phone":"+44 20 8599 8443",
    "sg:postcode":"IG3 8LG",
    "sg:province":"Essex",
    "sg:tags":[
        "away",
        "meal",
        "outlet",
        "take"
    ],
    "wof:name":"LEES GARDEN",
    "wof:placetype":"venue"
},
  "geometry": {"coordinates":[0.0959400013,51.5643119812],"type":"Point"}
}