{
  "type": "Feature",
  "properties": {
    "addr:full":"109 High Street Invergordon Highland IV18 0AB",
    "addr:housenumber":"109",
    "addr:postcode":"iv18 0ab",
    "addr:street":"High Street",
    "iso:country":"GB",
    "sg:address":"109 High Street",
    "sg:city":"Invergordon",
    "sg:classifiers":[
        {
            "category":"Retail",
            "subcategory":"Auto Rental",
            "type":"Services"
        },
        {
            "category":"Retail",
            "subcategory":"Auto Repair",
            "type":"Services"
        }
    ],
    "sg:phone":"+44 1349 853020",
    "sg:postcode":"IV18 0AB",
    "sg:province":"Highland",
    "sg:tags":[
        "modification",
        "garage",
        "car"
    ],
    "wof:name":"Campbell Autos",
    "wof:placetype":"venue"
},
  "geometry": {"coordinates":[-4.167069,57.688763],"type":"Point"}
}