{
  "type": "Feature",
  "properties": {
    "iso:country":"GB",
    "sg:address":"Floodgates Yard, Knepp Castle Estate Worthing Road",
    "sg:city":"Horsham",
    "sg:classifiers":[
        {
            "category":"Building & Trades",
            "subcategory":"Construction",
            "type":"Services"
        }
    ],
    "sg:phone":"+44 1403 710827",
    "sg:postcode":"RH13 8LH",
    "sg:province":"West Sussex",
    "sg:tags":[
        "builder"
    ],
    "wof:name":"Oakleigh Building Services Ltd.",
    "wof:placetype":"venue"
},
  "geometry": {"coordinates":[-0.34475,50.978939],"type":"Point"}
}