{
  "type": "Feature",
  "properties": {
    "addr:full":"High Street Leiston Suffolk IP16 4EW",
    "addr:postcode":"ip16 4ew",
    "addr:street":"High Street",
    "iso:country":"GB",
    "sg:address":"High Street",
    "sg:city":"Leiston",
    "sg:classifiers":[
        {
            "category":"Bars & Pubs",
            "type":"Food & Drink"
        },
        {
            "category":"Community Center",
            "subcategory":"Social",
            "type":"Public Place"
        }
    ],
    "sg:phone":"+44 1728 830670",
    "sg:postcode":"IP16 4EW",
    "sg:province":"Suffolk",
    "sg:tags":[
        "pubs",
        "house",
        "inn",
        "activity"
    ],
    "wof:name":"C RUSSELL",
    "wof:placetype":"venue"
},
  "geometry": {"coordinates":[1.577176,52.207031],"type":"Point"}
}