{
  "type": "Feature",
  "properties": {
    "iso:country":"GB",
    "sg:address":"3 Tannery Close, Off Power Station Road",
    "sg:city":"Rugeley",
    "sg:classifiers":[
        {
            "category":"Retail",
            "subcategory":"Auto Repair",
            "type":"Services"
        }
    ],
    "sg:phone":"+44 1889 582826",
    "sg:postcode":"WS15 2HS",
    "sg:province":"Staffordshire",
    "sg:tags":[
        "modification",
        "garage"
    ],
    "wof:name":"Alan Morris Vehicle Repair of Rugeley",
    "wof:placetype":"venue"
},
  "geometry": {"coordinates":[-1.929684,52.762333],"type":"Point"}
}