{
  "type": "Feature",
  "properties": {
    "iso:country":"GB",
    "sg:address":"4 Central Parade, High St, Maresfield",
    "sg:city":"Uckfield",
    "sg:classifiers":[
        {
            "category":"Government",
            "subcategory":"Post Office",
            "type":"Public Place"
        }
    ],
    "sg:phone":"+44 1825 762441",
    "sg:postcode":"TN22 2EN",
    "sg:province":"East Sussex",
    "wof:name":"Maresfield P.O",
    "wof:placetype":"venue"
},
  "geometry": {"coordinates":[0.085984,50.997238],"type":"Point"}
}