{
  "type": "Feature",
  "properties": {
    "addr:full":"St Georges Rd Richmond Greater London TW9 2LE",
    "addr:postcode":"tw9 2le",
    "addr:street":"St Georges Rd",
    "iso:country":"GB",
    "sg:address":"St Georges Rd",
    "sg:city":"Richmond",
    "sg:classifiers":[
        {
            "category":"Professional",
            "subcategory":"Printing & Photocopies",
            "type":"Services"
        }
    ],
    "sg:phone":"+44 20 8940 5887",
    "sg:postcode":"TW9 2LE",
    "sg:province":"Greater London",
    "sg:tags":[
        "engraving"
    ],
    "wof:name":"Avenue Engraving Co",
    "wof:placetype":"venue"
},
  "geometry": {"coordinates":[-0.2892139852,51.4668960571],"type":"Point"}
}