{
  "type": "Feature",
  "properties": {
    "addr:full":"15 Metchall Way Alexandria Argyll and Bute G83 0LW",
    "addr:housenumber":"15",
    "addr:postcode":"g83 0lw",
    "addr:street":"Metchall Way",
    "iso:country":"GB",
    "sg:address":"15 Metchall Way",
    "sg:city":"Alexandria",
    "sg:classifiers":[
        {
            "category":"Banks & Credit Unions",
            "subcategory":"Bank",
            "type":"Services"
        }
    ],
    "sg:phone":"+44 1389 759731",
    "sg:postcode":"G83 0LW",
    "sg:province":"Argyll and Bute",
    "sg:tags":[
        "financial",
        "institution"
    ],
    "sg:website":"http://www.rbs.co.uk",
    "wof:name":"The Royal Bank of Scotland plc",
    "wof:placetype":"venue"
},
  "geometry": {"coordinates":[-4.5797448158,55.9868850708],"type":"Point"}
}