{
  "type": "Feature",
  "properties": {
    "addr:full":"Wadsworth Mill, Oxon Hope Keighley North Yorkshire BD22 9NE",
    "addr:postcode":"bd22 9ne",
    "addr:street":"Wadsworth Mill",
    "iso:country":"GB",
    "sg:address":"Wadsworth Mill, Oxon Hope",
    "sg:city":"Keighley",
    "sg:classifiers":[
        {
            "category":"Wholesale",
            "subcategory":"Construction Materials",
            "type":"Manufacturing & Wholesale Goods"
        }
    ],
    "sg:phone":"+44 1535 643733",
    "sg:postcode":"BD22 9NE",
    "sg:province":"North Yorkshire",
    "sg:tags":[
        "distributor",
        "spring"
    ],
    "wof:name":"Emmott Pawsons Holdings Ltd.",
    "wof:placetype":"venue"
},
  "geometry": {"coordinates":[-1.9491859674,53.8070755005],"type":"Point"}
}