{
  "type": "Feature",
  "properties": {
    "iso:country":"GB",
    "sg:address":"Gwentfro Building, Technology Park",
    "sg:city":"Wrexham",
    "sg:classifiers":[
        {
            "category":"Health Services",
            "subcategory":"Medical Lab",
            "type":"Services"
        }
    ],
    "sg:phone":"+44 1978 310818",
    "sg:postcode":"LL13 7YP",
    "sg:province":"Wrexham",
    "sg:tags":[
        "dental"
    ],
    "wof:name":"National Health Service Executive Headqu",
    "wof:placetype":"venue"
},
  "geometry": {"coordinates":[-2.997129,53.041954],"type":"Point"}
}