{
  "type": "Feature",
  "properties": {
    "addr:full":"Copperas Lane, Haigh Wigan Lancashire WN2 1PA",
    "addr:postcode":"wn2 1pa",
    "addr:street":"Copperas Lane",
    "iso:country":"GB",
    "sg:address":"Copperas Lane, Haigh",
    "sg:city":"Wigan",
    "sg:classifiers":[
        {
            "category":"Education",
            "subcategory":"School",
            "type":"Public Place"
        }
    ],
    "sg:phone":"+44 1942 831310",
    "sg:postcode":"WN2 1PA",
    "sg:province":"Lancashire",
    "sg:tags":[
        "local",
        "authority"
    ],
    "wof:name":"St Davids Church of England Junior & Infant School",
    "wof:placetype":"venue"
},
  "geometry": {"coordinates":[-2.5953760147,53.5760345459],"type":"Point"}
}