{
  "type": "Feature",
  "properties": {
    "addr:full":"Teal House, Middle St Guildford Surrey GU5 9HF",
    "addr:postcode":"gu5 9hf",
    "addr:street":"Middle St",
    "iso:country":"GB",
    "sg:address":"Teal House, Middle St",
    "sg:city":"Guildford",
    "sg:classifiers":[
        {
            "category":"Real Estate",
            "subcategory":"Real Estate Agent",
            "type":"Services"
        }
    ],
    "sg:phone":"+44 1483 202016",
    "sg:postcode":"GU5 9HF",
    "sg:province":"Surrey",
    "wof:name":"Clarke Gammon",
    "wof:placetype":"venue"
},
  "geometry": {"coordinates":[-0.464639008,51.219959259],"type":"Point"}
}