{
  "type": "Feature",
  "properties": {
    "iso:country":"GB",
    "sg:address":"23 Barnabas Road",
    "sg:city":"Birmingham",
    "sg:classifiers":[
        {
            "category":"Banks & Credit Unions",
            "subcategory":"Financial Services",
            "type":"Services"
        }
    ],
    "sg:phone":"+44 121 377 6969",
    "sg:postcode":"B23 6SH",
    "sg:province":"West Midlands",
    "sg:tags":[
        "cashing",
        "cheque"
    ],
    "wof:name":"Cheque Centres",
    "wof:placetype":"venue"
},
  "geometry": {"coordinates":[-1.840028,52.524536],"type":"Point"}
}