{
  "type": "Feature",
  "properties": {
    "addr:full":"46 Coombe Road Kingston-upon-thames Greater London KT2 7AF",
    "addr:housenumber":"46",
    "addr:postcode":"kt2 7af",
    "addr:street":"Coombe Road",
    "iso:country":"GB",
    "sg:address":"46 Coombe Road",
    "sg:city":"Kingston-upon-thames",
    "sg:classifiers":[
        {
            "category":"Cinema",
            "subcategory":"Movie Rental",
            "type":"Entertainment"
        }
    ],
    "sg:phone":"+44 20 8546 4970",
    "sg:postcode":"KT2 7AF",
    "sg:province":"Greater London",
    "sg:tags":[
        "video",
        "library"
    ],
    "wof:name":"Moonlight Movies",
    "wof:placetype":"venue"
},
  "geometry": {"coordinates":[-0.2830359936,51.4128875732],"type":"Point"}
}