{
  "type": "Feature",
  "properties": {
    "addr:full":"5-12 Midsomer Enterprise Park, Wheelers Hill Bath Somerset BA3 2BB",
    "addr:housenumber":"5-12",
    "addr:postcode":"ba3 2bb",
    "addr:street":"Midsomer Enterprise Park",
    "iso:country":"GB",
    "sg:address":"5-12 Midsomer Enterprise Park, Wheelers Hill",
    "sg:city":"Bath",
    "sg:classifiers":[
        {
            "category":"Professional",
            "subcategory":"Printing & Photocopies",
            "type":"Services"
        }
    ],
    "sg:phone":"+44 1761 410410",
    "sg:postcode":"BA3 2BB",
    "sg:province":"Somerset",
    "sg:tags":[
        "printer"
    ],
    "wof:name":"LooseLeaf",
    "wof:placetype":"venue"
},
  "geometry": {"coordinates":[-2.47478,51.289909],"type":"Point"}
}