{
  "type": "Feature",
  "properties": {
    "iso:country":"GB",
    "sg:address":"Unit 4 Maybrook Industrial Estate, Maybrook Road",
    "sg:city":"Walsall",
    "sg:classifiers":[
        {
            "category":"Building & Trades",
            "subcategory":"Construction",
            "type":"Services"
        }
    ],
    "sg:postcode":"WS8 7DG",
    "sg:province":"Staffordshire",
    "sg:tags":[
        "equipment"
    ],
    "wof:name":"Central Boring Services",
    "wof:placetype":"venue"
},
  "geometry": {"coordinates":[-1.93196,52.635929],"type":"Point"}
}