{
  "type": "Feature",
  "properties": {
    "addr:full":"62 Honeysuckle Way Witham Essex CM8 2XQ",
    "addr:housenumber":"62",
    "addr:postcode":"cm8 2xq",
    "addr:street":"Honeysuckle Way",
    "iso:country":"GB",
    "sg:address":"62 Honeysuckle Way",
    "sg:city":"Witham",
    "sg:classifiers":[
        {
            "category":"Building & Trades",
            "subcategory":"Cleaning & Sanitation",
            "type":"Services"
        }
    ],
    "sg:postcode":"CM8 2XQ",
    "sg:province":"Essex",
    "sg:tags":[
        "cleaner",
        "window"
    ],
    "wof:name":"Baker,Kirk,",
    "wof:placetype":"venue"
},
  "geometry": {"coordinates":[0.6233040094,51.8109321594],"type":"Point"}
}