{
  "type": "Feature",
  "properties": {
    "addr:full":"5 Tugela St Catford Greater London SE6 4DQ",
    "addr:housenumber":"5",
    "addr:postcode":"se6 4dq",
    "addr:street":"Tugela St",
    "iso:country":"GB",
    "sg:address":"5 Tugela St",
    "sg:city":"Catford",
    "sg:classifiers":[
        {
            "category":"Transit Center",
            "subcategory":"Freight",
            "type":"Transportation"
        }
    ],
    "sg:phone":"+44 20 8291 4503",
    "sg:postcode":"SE6 4DQ",
    "sg:province":"Greater London",
    "sg:tags":[
        "piano",
        "accessory"
    ],
    "wof:name":"Robert Parr",
    "wof:placetype":"venue"
},
  "geometry": {"coordinates":[-0.03156,51.4366950989],"type":"Point"}
}