{
  "type": "Feature",
  "properties": {
    "addr:full":"50 Parsons Green Lane London Greater London SW6 4HU",
    "addr:housenumber":"50",
    "addr:postcode":"sw6 4hu",
    "addr:street":"Parsons Green Lane",
    "iso:country":"GB",
    "sg:address":"50 Parsons Green Lane",
    "sg:city":"London",
    "sg:classifiers":[
        {
            "category":"Real Estate",
            "subcategory":"Real Estate Agent",
            "type":"Services"
        }
    ],
    "sg:phone":"+44 20 7731 2054",
    "sg:postcode":"SW6 4HU",
    "sg:province":"Greater London",
    "wof:name":"Anderson Residential",
    "wof:placetype":"venue"
},
  "geometry": {"coordinates":[-0.2009530067,51.4753646851],"type":"Point"}
}