{
  "type": "Feature",
  "properties": {
    "addr:full":"55 Calthorpe Road, Edgbaston Birmingham West Midlands B15 1TL",
    "addr:housenumber":"55",
    "addr:postcode":"b15 1tl",
    "addr:street":"Calthorpe Road",
    "iso:country":"GB",
    "sg:address":"55 Calthorpe Road, Edgbaston",
    "sg:city":"Birmingham",
    "sg:classifiers":[
        {
            "category":"Banks & Credit Unions",
            "subcategory":"Financial Services",
            "type":"Services"
        }
    ],
    "sg:phone":"+44 121 452 8700",
    "sg:postcode":"B15 1TL",
    "sg:province":"West Midlands",
    "sg:tags":[
        "consultant"
    ],
    "wof:name":"Jobson James Financial Services Ltd.",
    "wof:placetype":"venue"
},
  "geometry": {"coordinates":[-1.9196039438,52.4707717896],"type":"Point"}
}