{
  "type": "Feature",
  "properties": {
    "iso:country":"GB",
    "sg:address":"5 York Place",
    "sg:city":"Scarborough",
    "sg:classifiers":[
        {
            "category":"Restaurant",
            "type":"Food & Drink"
        }
    ],
    "sg:phone":"+44 1723 372646",
    "sg:postcode":"YO11 2NP",
    "sg:province":"North Yorkshire",
    "sg:tags":[
        "greek",
        "-",
        "french"
    ],
    "wof:name":"George Michael's",
    "wof:placetype":"venue"
},
  "geometry": {"coordinates":[-0.4034410119,54.2807273865],"type":"Point"}
}