{
  "type": "Feature",
  "properties": {
    "iso:country":"GB",
    "sg:address":"2 South Parade, Horley Row",
    "sg:city":"Horley",
    "sg:classifiers":[
        {
            "category":"Recreation",
            "subcategory":"Fishing",
            "type":"Entertainment"
        }
    ],
    "sg:postcode":"RH6 8BH",
    "sg:province":"Surrey",
    "sg:tags":[
        "equipment",
        "angling"
    ],
    "wof:name":"Salfords Angling Centre",
    "wof:placetype":"venue"
},
  "geometry": {"coordinates":[-0.167728,51.177616],"type":"Point"}
}