{
  "type": "Feature",
  "properties": {
    "addr:full":"23 Commonside Lytham St Annes Lancashire FY8 4EX",
    "addr:housenumber":"23",
    "addr:postcode":"fy8 4ex",
    "addr:street":"Commonside Lytham St Annes",
    "iso:country":"GB",
    "sg:address":"23 Commonside",
    "sg:city":"Lytham St Annes",
    "sg:classifiers":[
        {
            "category":"Social Services",
            "subcategory":"Retirement Home",
            "type":"Services"
        }
    ],
    "sg:phone":"+44 1253 733563",
    "sg:postcode":"FY8 4EX",
    "sg:province":"Lancashire",
    "sg:tags":[
        "historian",
        "family"
    ],
    "wof:name":"Datestone",
    "wof:placetype":"venue"
},
  "geometry": {"coordinates":[-2.9890611172,53.7431755066],"type":"Point"}
}