{
  "type": "Feature",
  "properties": {
    "iso:country":"GB",
    "sg:address":"9 Railway Road",
    "sg:city":"Blackburn",
    "sg:classifiers":[
        {
            "category":"Professional",
            "subcategory":"Employment Agencies",
            "type":"Services"
        }
    ],
    "sg:phone":"+44 1254 660020",
    "sg:postcode":"BB1 5AX",
    "sg:province":"Lancashire",
    "sg:tags":[
        "consultant"
    ],
    "wof:name":"Personnel Logistics & Recruitment Ltd.",
    "wof:placetype":"venue"
},
  "geometry": {"coordinates":[-2.480369091,53.7481307983],"type":"Point"}
}