{
  "type": "Feature",
  "properties": {
    "addr:full":"Euro House, Field Road, Mildenhall Bury St. Edmunds Cambridgeshire IP28 7AP",
    "addr:postcode":"ip28 7ap",
    "addr:street":"Field Road",
    "iso:country":"GB",
    "sg:address":"Euro House, Field Road, Mildenhall",
    "sg:city":"Bury St. Edmunds",
    "sg:classifiers":[
        {
            "category":"Professional",
            "subcategory":"Business Services",
            "type":"Services"
        }
    ],
    "sg:phone":"+44 1638 515335",
    "sg:postcode":"IP28 7AP",
    "sg:province":"Cambridgeshire",
    "sg:tags":[
        "import",
        "export",
        "agent"
    ],
    "wof:name":"Euro-Usa Worldwide Forwarding Ltd",
    "wof:placetype":"venue"
},
  "geometry": {"coordinates":[0.511935,52.350937],"type":"Point"}
}