{
  "type": "Feature",
  "properties": {
    "iso:country":"GB",
    "sg:address":"33 High Street",
    "sg:city":"Jedburgh",
    "sg:classifiers":[
        {
            "category":"Food & Beverages",
            "subcategory":"Specialty",
            "type":"Retail Goods"
        }
    ],
    "sg:postcode":"TD8 6AQ",
    "sg:province":"Scottish Borders",
    "sg:tags":[
        "product",
        "health"
    ],
    "wof:name":"William & Caroline Ann McDermont",
    "wof:placetype":"venue"
},
  "geometry": {"coordinates":[-2.554071,55.478493],"type":"Point"}
}