{
  "type": "Feature",
  "properties": {
    "addr:full":"92-94 Barlow Moor Rd Manchester Greater Manchester M20 2PN",
    "addr:housenumber":"92-94",
    "addr:postcode":"m20 2pn",
    "addr:street":"Barlow Moor Rd",
    "iso:country":"GB",
    "sg:address":"92-94 Barlow Moor Rd",
    "sg:city":"Manchester",
    "sg:classifiers":[
        {
            "category":"Food & Beverages",
            "subcategory":"Liquor & Beverages",
            "type":"Retail Goods"
        }
    ],
    "sg:phone":"+44 161 448 2415",
    "sg:postcode":"M20 2PN",
    "sg:province":"Greater Manchester",
    "sg:tags":[
        "beer",
        "spirit",
        "wines"
    ],
    "wof:name":"Victoria Wine",
    "wof:placetype":"venue"
},
  "geometry": {"coordinates":[-2.2422790527,53.4211845398],"type":"Point"}
}