{
  "type": "Feature",
  "properties": {
    "addr:full":"65 Dudley Road Wolverhampton West Midlands WV2 3BY",
    "addr:housenumber":"65",
    "addr:postcode":"wv2 3by",
    "addr:street":"Dudley Road",
    "iso:country":"GB",
    "sg:address":"65 Dudley Road",
    "sg:city":"Wolverhampton",
    "sg:classifiers":[
        {
            "category":"Shopping",
            "subcategory":"Crafts & Fabrics",
            "type":"Retail Goods"
        }
    ],
    "sg:phone":"+44 1902 451454",
    "sg:postcode":"WV2 3BY",
    "sg:province":"West Midlands",
    "sg:tags":[
        "shop"
    ],
    "wof:name":"M S Silk Store",
    "wof:placetype":"venue"
},
  "geometry": {"coordinates":[-2.126096,52.576614],"type":"Point"}
}