{
  "type": "Feature",
  "properties": {
    "iso:country":"GB",
    "sg:address":"26 Central Avenue",
    "sg:city":"Church Stretton",
    "sg:classifiers":[
        {
            "category":"Building & Trades",
            "subcategory":"Construction",
            "type":"Services"
        }
    ],
    "sg:phone":"+44 1694 724010",
    "sg:postcode":"SY6 6EF",
    "sg:province":"Shropshire",
    "sg:tags":[
        "glazier",
        "decorator",
        "painter"
    ],
    "wof:name":"E B Jones",
    "wof:placetype":"venue"
},
  "geometry": {"coordinates":[-2.805545,52.536964],"type":"Point"}
}