{
  "type": "Feature",
  "properties": {
    "iso:country":"GB",
    "sg:address":"Poole Farm, Thorverton",
    "sg:city":"Exeter",
    "sg:classifiers":[
        {
            "category":"Farming",
            "subcategory":"Livestock Farm",
            "type":"Manufacturing & Wholesale Goods"
        },
        {
            "category":"Farming",
            "subcategory":"Farm",
            "type":"Manufacturing & Wholesale Goods"
        }
    ],
    "sg:phone":"+44 1392 860444",
    "sg:postcode":"EX5 5PN",
    "sg:province":"Devon",
    "sg:tags":[
        "mixed",
        "crop",
        "others"
    ],
    "wof:name":"Nancy A McInerney",
    "wof:placetype":"venue"
},
  "geometry": {"coordinates":[-3.520387,50.806702],"type":"Point"}
}