{
  "type": "Feature",
  "properties": {
    "addr:full":"Avondale Way, Avondale Industrial Estate Cwmbran Monmouthshire NP44 1TS",
    "addr:postcode":"np44 1ts",
    "addr:street":"Avondale Way;Estate",
    "iso:country":"GB",
    "sg:address":"Avondale Way, Avondale Industrial Estate",
    "sg:city":"Cwmbran",
    "sg:classifiers":[
        {
            "category":"Manufacturing",
            "subcategory":"Rubber & Plastics",
            "type":"Manufacturing & Wholesale Goods"
        }
    ],
    "sg:phone":"+44 1633 873229",
    "sg:postcode":"NP44 1TS",
    "sg:province":"Monmouthshire",
    "sg:tags":[
        "supplier",
        "stockist"
    ],
    "wof:name":"A M F Polymers (Cwmbran) Ltd.",
    "wof:placetype":"venue"
},
  "geometry": {"coordinates":[-3.0196089745,51.6674385071],"type":"Point"}
}