{
  "type": "Feature",
  "properties": {
    "iso:country":"GB",
    "sg:address":"Haydens Farm",
    "sg:city":"Henley-on-thames",
    "sg:classifiers":[
        {
            "category":"Food & Beverages",
            "subcategory":"Liquor & Beverages",
            "type":"Retail Goods"
        }
    ],
    "sg:postcode":"RG9 5TX",
    "sg:province":"Berkshire",
    "sg:tags":[
        "beer",
        "spirit",
        "wines"
    ],
    "wof:name":"Woods Wines",
    "wof:placetype":"venue"
},
  "geometry": {"coordinates":[-1.015309,51.57793],"type":"Point"}
}