{
  "type": "Feature",
  "properties": {
    "addr:full":"29-33 Victoria Rd Romford Essex RM1 2JT",
    "addr:housenumber":"29-33",
    "addr:postcode":"rm1 2jt",
    "addr:street":"Victoria Rd",
    "iso:country":"GB",
    "sg:address":"29-33 Victoria Rd",
    "sg:city":"Romford",
    "sg:classifiers":[
        {
            "category":"Government",
            "subcategory":"Police Station",
            "type":"Public Place"
        }
    ],
    "sg:phone":"+44 1708 753555",
    "sg:postcode":"RM1 2JT",
    "sg:province":"Essex",
    "sg:tags":[
        "support"
    ],
    "wof:name":"Community Service & Resource Centre",
    "wof:placetype":"venue"
},
  "geometry": {"coordinates":[0.1853079945,51.5746955872],"type":"Point"}
}