{
  "type": "Feature",
  "properties": {
    "addr:full":"37a Liverpool Road, Birkdale Southport Lancashire PR8 4AG",
    "addr:housenumber":"37a",
    "addr:postcode":"pr8 4ag",
    "addr:street":"Liverpool Road",
    "iso:country":"GB",
    "sg:address":"37a Liverpool Road, Birkdale",
    "sg:city":"Southport",
    "sg:classifiers":[
        {
            "category":"Retail",
            "subcategory":"Laundry & Dry Cleaning",
            "type":"Services"
        }
    ],
    "sg:postcode":"PR8 4AG",
    "sg:province":"Lancashire",
    "sg:tags":[
        "alteration"
    ],
    "wof:name":"Andrews Dry Cleaners",
    "wof:placetype":"venue"
},
  "geometry": {"coordinates":[-3.012555,53.63335],"type":"Point"}
}