{
  "type": "Feature",
  "properties": {
    "addr:full":"659-663 Nuthall Road, Cinderhill Nottingham Nottinghamshire NG8 6AF",
    "addr:housenumber":"659-663",
    "addr:postcode":"ng8 6af",
    "addr:street":"Nuthall Road",
    "iso:country":"GB",
    "sg:address":"659-663 Nuthall Road, Cinderhill",
    "sg:city":"Nottingham",
    "sg:classifiers":[
        {
            "category":"Retail",
            "subcategory":"Auto Repair",
            "type":"Services"
        }
    ],
    "sg:phone":"+44 115 927 2404",
    "sg:postcode":"NG8 6AF",
    "sg:province":"Nottinghamshire",
    "sg:tags":[
        "car",
        "specialist",
        "customizing"
    ],
    "wof:name":"Embassy Tyres",
    "wof:placetype":"venue"
},
  "geometry": {"coordinates":[-1.201205,52.985317],"type":"Point"}
}