{
  "type": "Feature",
  "properties": {
    "iso:country":"GB",
    "sg:address":"80 Bexley High Street",
    "sg:city":"Bexley",
    "sg:classifiers":[
        {
            "category":"Restaurant",
            "type":"Food & Drink"
        }
    ],
    "sg:phone":"+44 1322 529905",
    "sg:postcode":"DA5 1LB",
    "sg:province":"Kent",
    "sg:tags":[
        "italian"
    ],
    "wof:name":"Alberello",
    "wof:placetype":"venue"
},
  "geometry": {"coordinates":[0.1506460011,51.4413108826],"type":"Point"}
}