{
  "type": "Feature",
  "properties": {
    "addr:full":"Building 37 Second Avenue, The Pensnett Estate, Kingswinford Brierley Hill Staffordshire DY6 7TR",
    "addr:housenumber":"37",
    "addr:postcode":"dy6 7tr",
    "addr:street":"Second Avenue",
    "iso:country":"GB",
    "sg:address":"Building 37 Second Avenue, The Pensnett Estate, Kingswinford",
    "sg:city":"Brierley Hill",
    "sg:classifiers":[
        {
            "category":"Professional",
            "subcategory":"Engineering",
            "type":"Services"
        }
    ],
    "sg:phone":"+44 1384 355000",
    "sg:postcode":"DY6 7TR",
    "sg:province":"Staffordshire",
    "wof:name":"Ashworth Europe Ltd.",
    "wof:placetype":"venue"
},
  "geometry": {"coordinates":[-2.151539,52.505814],"type":"Point"}
}