{
  "type": "Feature",
  "properties": {
    "addr:full":"Windsor Trading Estate, Windsor Road Billericay Essex CM11 1QE",
    "addr:postcode":"cm11 1qe",
    "addr:street":"Windsor Road",
    "iso:country":"GB",
    "sg:address":"Windsor Trading Estate, Windsor Road",
    "sg:city":"Billericay",
    "sg:classifiers":[
        {
            "category":"Retail",
            "subcategory":"Auto Repair",
            "type":"Services"
        }
    ],
    "sg:postcode":"CM11 1QE",
    "sg:province":"Essex",
    "sg:tags":[
        "modification",
        "garage"
    ],
    "wof:name":"J Ibson",
    "wof:placetype":"venue"
},
  "geometry": {"coordinates":[0.482066,51.634716],"type":"Point"}
}