{
  "type": "Feature",
  "properties": {
    "addr:full":"Middle Gate, White Lund Morecambe Lancashire LA3 3PE",
    "addr:postcode":"la3 3pe",
    "addr:street":"Middle Gate White",
    "iso:country":"GB",
    "sg:address":"Middle Gate, White Lund",
    "sg:city":"Morecambe",
    "sg:classifiers":[
        {
            "category":"Recreation",
            "subcategory":"Gun Range",
            "type":"Entertainment"
        }
    ],
    "sg:phone":"+44 1524 380000",
    "sg:postcode":"LA3 3PE",
    "sg:province":"Lancashire",
    "sg:tags":[
        "operator",
        "tour"
    ],
    "wof:name":"Harrisons Coaches (Morecambe) Ltd.",
    "wof:placetype":"venue"
},
  "geometry": {"coordinates":[-2.8960039616,54.0331001282],"type":"Point"}
}