{
  "type": "Feature",
  "properties": {
    "iso:country":"GB",
    "sg:address":"981 High Road, North Finchley",
    "sg:city":"London",
    "sg:classifiers":[
        {
            "category":"Retail",
            "subcategory":"Repair Shop",
            "type":"Services"
        }
    ],
    "sg:phone":"+44 20 8445 6581",
    "sg:postcode":"N12 8QR",
    "sg:province":"Greater London",
    "sg:tags":[
        "radio",
        "television",
        "video"
    ],
    "wof:name":"Warrens Video & Audio Services",
    "wof:placetype":"venue"
},
  "geometry": {"coordinates":[-0.176794,51.622009],"type":"Point"}
}