{
  "type": "Feature",
  "properties": {
    "addr:full":"36 Potters Field St Albans Hertfordshire AL3 6LJ",
    "addr:housenumber":"36",
    "addr:postcode":"al3 6lj",
    "addr:street":"Potters Field",
    "iso:country":"GB",
    "sg:address":"36 Potters Field",
    "sg:city":"St Albans",
    "sg:classifiers":[
        {
            "category":"Real Estate",
            "subcategory":"Surveying",
            "type":"Services"
        }
    ],
    "sg:phone":"+44 1727 750866",
    "sg:postcode":"AL3 6LJ",
    "sg:province":"Hertfordshire",
    "sg:tags":[
        "building",
        "surveyor"
    ],
    "wof:name":"C M S Consultancy",
    "wof:placetype":"venue"
},
  "geometry": {"coordinates":[-0.327809006,51.7698516846],"type":"Point"}
}