{
  "type": "Feature",
  "properties": {
    "iso:country":"GB",
    "sg:address":"1 Hillside Crescent",
    "sg:city":"Edinburgh",
    "sg:classifiers":[
        {
            "category":"Sports & Exercise",
            "subcategory":"Gym",
            "type":"Entertainment"
        }
    ],
    "sg:postcode":"EH7 5DY",
    "sg:province":"City of Edinburgh",
    "sg:tags":[
        "fitness",
        "health",
        "centre"
    ],
    "wof:name":"The Edinburgh Club Ltd.",
    "wof:placetype":"venue"
},
  "geometry": {"coordinates":[-3.180678,55.957909],"type":"Point"}
}