{
  "type": "Feature",
  "properties": {
    "addr:full":"34 Walton Street Oxford Oxfordshire OX2 6AA",
    "addr:housenumber":"34",
    "addr:postcode":"ox2 6aa",
    "addr:street":"Walton Street",
    "iso:country":"GB",
    "sg:address":"34 Walton Street",
    "sg:city":"Oxford",
    "sg:classifiers":[
        {
            "category":"Personal",
            "type":"Services"
        }
    ],
    "sg:phone":"+44 1865 554972",
    "sg:postcode":"OX2 6AA",
    "sg:province":"Oxfordshire",
    "sg:tags":[
        "tailor"
    ],
    "wof:name":"Penge Di Roma",
    "wof:placetype":"venue"
},
  "geometry": {"coordinates":[-1.2647680044,51.7588653564],"type":"Point"}
}