{
  "type": "Feature",
  "properties": {
    "addr:full":"23 Hall Grn, Upholland Skelmersdale Lancashire WN8 0PD",
    "addr:housenumber":"23",
    "addr:postcode":"wn8 0pd",
    "addr:street":"Hall Grn Upholland",
    "iso:country":"GB",
    "sg:address":"23 Hall Grn, Upholland",
    "sg:city":"Skelmersdale",
    "sg:classifiers":[
        {
            "category":"Government",
            "subcategory":"Post Office",
            "type":"Public Place"
        }
    ],
    "sg:postcode":"WN8 0PD",
    "sg:province":"Lancashire",
    "wof:name":"Mark Edwards",
    "wof:placetype":"venue"
},
  "geometry": {"coordinates":[-2.7275490761,53.5419998169],"type":"Point"}
}