{
  "type": "Feature",
  "properties": {
    "iso:country":"GB",
    "sg:address":"10 Robert Close",
    "sg:city":"Tamworth",
    "sg:classifiers":[
        {
            "category":"Professional",
            "subcategory":"Employment Agencies",
            "type":"Services"
        }
    ],
    "sg:phone":"+44 1827 67108",
    "sg:postcode":"B79 8JR",
    "sg:province":"Staffordshire",
    "sg:tags":[
        "consultant",
        "recruitment"
    ],
    "wof:name":"Copeland Associates",
    "wof:placetype":"venue"
},
  "geometry": {"coordinates":[-1.70704,52.64592],"type":"Point"}
}