{
  "type": "Feature",
  "properties": {
    "addr:full":"Century Ho, 19 High St Marlow Berkshire SL7 1AU",
    "addr:housenumber":"19",
    "addr:postcode":"sl7 1au",
    "addr:street":"High St",
    "iso:country":"GB",
    "sg:address":"Century Ho, 19 High St",
    "sg:city":"Marlow",
    "sg:classifiers":[
        {
            "category":"Professional",
            "subcategory":"Computer Services",
            "type":"Services"
        }
    ],
    "sg:postcode":"SL7 1AU",
    "sg:province":"Berkshire",
    "sg:tags":[
        "bureau",
        "facility"
    ],
    "wof:name":"Fleetway Systems Services Ltd",
    "wof:placetype":"venue"
},
  "geometry": {"coordinates":[-0.7761890292,51.5730667114],"type":"Point"}
}