{
  "type": "Feature",
  "properties": {
    "addr:full":"First Floor South East Annexe, Manchester Airport Manchester Greater Manchester M90 1NP",
    "addr:postcode":"m90 1np",
    "addr:street":"East",
    "iso:country":"GB",
    "sg:address":"First Floor South East Annexe, Manchester Airport",
    "sg:city":"Manchester",
    "sg:classifiers":[
        {
            "category":"Airline",
            "type":"Transportation"
        }
    ],
    "sg:postcode":"M90 1NP",
    "sg:province":"Greater Manchester",
    "sg:tags":[
        "airport"
    ],
    "wof:name":"Northwest Aviation Services Ltd.",
    "wof:placetype":"venue"
},
  "geometry": {"coordinates":[-2.26608,53.3606],"type":"Point"}
}