{
  "type": "Feature",
  "properties": {
    "addr:full":"52 Newhampton Road West Wolverhampton Shropshire WV6 0RY",
    "addr:housenumber":"52",
    "addr:postcode":"wv6 0ry",
    "addr:street":"Newhampton Road West",
    "iso:country":"GB",
    "sg:address":"52 Newhampton Road West",
    "sg:city":"Wolverhampton",
    "sg:classifiers":[
        {
            "category":"Shopping",
            "subcategory":"Department Store",
            "type":"Retail Goods"
        }
    ],
    "sg:phone":"+44 1902 421612",
    "sg:postcode":"WV6 0RY",
    "sg:province":"Shropshire",
    "wof:name":"K Ram & Son",
    "wof:placetype":"venue"
},
  "geometry": {"coordinates":[-2.148194,52.5947],"type":"Point"}
}