{
  "type": "Feature",
  "properties": {
    "iso:country":"GB",
    "sg:address":"Po Box 10504 Wood Grn",
    "sg:city":"London",
    "sg:classifiers":[
        {
            "category":"Organizations",
            "subcategory":"Membership Organization",
            "type":"Services"
        }
    ],
    "sg:phone":"+44 20 8889 5221",
    "sg:postcode":"N22 8PR",
    "sg:province":"Greater London",
    "sg:tags":[
        "club"
    ],
    "wof:name":"Escape From Samsara",
    "wof:placetype":"venue"
},
  "geometry": {"coordinates":[-0.1158,51.604801],"type":"Point"}
}