{
  "type": "Feature",
  "properties": {
    "addr:full":"86 Hilderthorpe Road Bridlington East Riding of Yorkshire YO15 3BQ",
    "addr:housenumber":"86",
    "addr:postcode":"yo15 3bq",
    "addr:street":"Hilderthorpe Road",
    "iso:country":"GB",
    "sg:address":"86 Hilderthorpe Road",
    "sg:city":"Bridlington",
    "sg:classifiers":[
        {
            "category":"Food & Beverages",
            "subcategory":"Meat & Fish",
            "type":"Retail Goods"
        }
    ],
    "sg:phone":"+44 1262 603992",
    "sg:postcode":"YO15 3BQ",
    "sg:province":"East Riding of Yorkshire",
    "sg:tags":[
        "chip"
    ],
    "wof:name":"Jack's Fish & Chip Shop",
    "wof:placetype":"venue"
},
  "geometry": {"coordinates":[-0.196941,54.083332],"type":"Point"}
}