{
  "type": "Feature",
  "properties": {
    "iso:country":"GB",
    "sg:address":"Unit 22-23 Neath Abbey Business, Park, Neath Abbey",
    "sg:city":"Swansea",
    "sg:classifiers":[
        {
            "category":"Professional",
            "subcategory":"Engineering",
            "type":"Services"
        }
    ],
    "sg:phone":"+44 1792 813449",
    "sg:postcode":"SA10 7DR",
    "sg:province":"Neath Port Talbot",
    "sg:tags":[
        "precision",
        "engineer"
    ],
    "wof:name":"Diamond Precision Engineering Ltd.",
    "wof:placetype":"venue"
},
  "geometry": {"coordinates":[-3.833705,51.658108],"type":"Point"}
}