{
  "type": "Feature",
  "properties": {
    "addr:full":"41 Brudenell, Orton Goldhay Peterborough Cambridgeshire PE2 5SX",
    "addr:housenumber":"41",
    "addr:postcode":"pe2 5sx",
    "iso:country":"GB",
    "sg:address":"41 Brudenell, Orton Goldhay",
    "sg:city":"Peterborough",
    "sg:classifiers":[
        {
            "category":"Retail",
            "subcategory":"Driving School",
            "type":"Services"
        }
    ],
    "sg:phone":"+44 1733 235807",
    "sg:postcode":"PE2 5SX",
    "sg:province":"Cambridgeshire",
    "wof:name":"David's School of Motoring",
    "wof:placetype":"venue"
},
  "geometry": {"coordinates":[-0.301314,52.538658],"type":"Point"}
}