{
  "type": "Feature",
  "properties": {
    "iso:country":"GB",
    "sg:address":"Oakdene 352 Christchurch Road, West Parley",
    "sg:city":"Ferndown",
    "sg:classifiers":[
        {
            "category":"Professional",
            "subcategory":"Art Services",
            "type":"Services"
        }
    ],
    "sg:phone":"+44 1202 572647",
    "sg:postcode":"BH22 8SN",
    "sg:province":"Dorset",
    "sg:tags":[
        "photographer"
    ],
    "wof:name":"Anthony King",
    "wof:placetype":"venue"
},
  "geometry": {"coordinates":[-1.881239,50.784801],"type":"Point"}
}