{
  "type": "Feature",
  "properties": {
    "addr:full":"7 Heron Quays, Marsh Wall London Greater London E14 9XN",
    "addr:housenumber":"7",
    "addr:postcode":"e14 9xn",
    "addr:street":"Heron Quays Marsh Wall",
    "iso:country":"GB",
    "sg:address":"7 Heron Quays, Marsh Wall",
    "sg:city":"London",
    "sg:classifiers":[
        {
            "category":"Organizations",
            "subcategory":"Professional Association",
            "type":"Services"
        }
    ],
    "sg:phone":"+44 20 7538 9502",
    "sg:postcode":"E14 9XN",
    "sg:province":"Greater London",
    "sg:tags":[
        "institute"
    ],
    "wof:name":"B I R A",
    "wof:placetype":"venue"
},
  "geometry": {"coordinates":[-0.0201299991,51.5009994507],"type":"Point"}
}