{
  "type": "Feature",
  "properties": {
    "addr:full":"Council Road Basingstoke Hampshire RG21 3DH",
    "addr:postcode":"rg21 3dh",
    "addr:street":"Council Road",
    "iso:country":"GB",
    "sg:address":"Council Road",
    "sg:city":"Basingstoke",
    "sg:classifiers":[
        {
            "category":"Community Center",
            "type":"Public Place"
        }
    ],
    "sg:phone":"+44 1256 464031",
    "sg:postcode":"RG21 3DH",
    "sg:province":"Hampshire",
    "sg:tags":[
        "centre"
    ],
    "wof:name":"Basingstoke Carnival Hall",
    "wof:placetype":"venue"
},
  "geometry": {"coordinates":[-1.088465,51.259689],"type":"Point"}
}