{
  "type": "Feature",
  "properties": {
    "addr:full":"Unit C Nigel Court, Ward Road Buckingham Road Indus Brackley Buckinghamshire NN13 7LF",
    "addr:housenumber":"unit c",
    "addr:postcode":"nn13 7lf",
    "addr:street":"Nigel Court Ward Road Buckingham Road",
    "iso:country":"GB",
    "sg:address":"Unit C Nigel Court, Ward Road Buckingham Road Indus",
    "sg:city":"Brackley",
    "sg:classifiers":[
        {
            "category":"Wholesale",
            "subcategory":"Painting Supplies",
            "type":"Manufacturing & Wholesale Goods"
        }
    ],
    "sg:phone":"+44 1280 840630",
    "sg:postcode":"NN13 7LF",
    "sg:province":"Buckinghamshire",
    "sg:tags":[
        "carbon",
        "product"
    ],
    "wof:name":"Crosby Composites Ltd.",
    "wof:placetype":"venue"
},
  "geometry": {"coordinates":[-1.1492660046,52.0273208618],"type":"Point"}
}