{
  "type": "Feature",
  "properties": {
    "iso:country":"GB",
    "sg:address":"Lynn Road, Stoke Ferry",
    "sg:city":"King's Lynn",
    "sg:classifiers":[
        {
            "category":"Retail",
            "subcategory":"Auto Repair",
            "type":"Services"
        }
    ],
    "sg:phone":"+44 1366 500254",
    "sg:postcode":"PE33 9SW",
    "sg:province":"Norfolk",
    "sg:tags":[
        "modification",
        "garage",
        "related"
    ],
    "wof:name":"E W English & Son",
    "wof:placetype":"venue"
},
  "geometry": {"coordinates":[0.50933,52.573292],"type":"Point"}
}