{
  "type": "Feature",
  "properties": {
    "addr:full":"Woodlands Vale House, Calthorpe Road Ryde Isle of Wight PO33 1PR",
    "addr:postcode":"po33 1pr",
    "addr:street":"Woodlands;Calthorpe Road",
    "iso:country":"GB",
    "sg:address":"Woodlands Vale House, Calthorpe Road",
    "sg:city":"Ryde",
    "sg:classifiers":[
        {
            "category":"Manufacturing",
            "subcategory":"Metals",
            "type":"Manufacturing & Wholesale Goods"
        },
        {
            "category":"Manufacturing",
            "subcategory":"Electronics",
            "type":"Manufacturing & Wholesale Goods"
        }
    ],
    "sg:phone":"+44 1983 811386",
    "sg:postcode":"PO33 1PR",
    "sg:province":"Isle of Wight",
    "sg:tags":[
        "merchant",
        "mnfr",
        "component",
        "electronic"
    ],
    "wof:name":"Valve & Tube Supplies",
    "wof:placetype":"venue"
},
  "geometry": {"coordinates":[-1.1375030279,50.7225761414],"type":"Point"}
}