{
  "type": "Feature",
  "properties": {
    "addr:full":"Moorlands Welwyn Garden City Hertfordshire AL7 4PW",
    "addr:postcode":"al7 4pw",
    "iso:country":"GB",
    "sg:address":"Moorlands",
    "sg:city":"Welwyn Garden City",
    "sg:classifiers":[
        {
            "category":"Retail",
            "subcategory":"Auto Repair",
            "type":"Services"
        }
    ],
    "sg:phone":"+44 1707 392050",
    "sg:postcode":"AL7 4PW",
    "sg:province":"Hertfordshire",
    "sg:tags":[
        "modification",
        "garage"
    ],
    "wof:name":"H M C",
    "wof:placetype":"venue"
},
  "geometry": {"coordinates":[-0.1808940023,51.7889213562],"type":"Point"}
}