{
  "type": "Feature",
  "properties": {
    "addr:full":"Kirkstall Valley Nature Reserve, Hollybush Lane Leeds West Yorkshire LS5 3BP",
    "addr:postcode":"ls5 3bp",
    "addr:street":"Hollybush Lane",
    "iso:country":"GB",
    "sg:address":"Kirkstall Valley Nature Reserve, Hollybush Lane",
    "sg:city":"Leeds",
    "sg:classifiers":[
        {
            "category":"Landmark",
            "subcategory":"Tourist Attraction",
            "type":"Public Place"
        }
    ],
    "sg:phone":"+44 113 230 6264",
    "sg:postcode":"LS5 3BP",
    "sg:province":"West Yorkshire",
    "sg:tags":[
        "interest"
    ],
    "wof:name":"Yorkshire Wildlife Trust",
    "wof:placetype":"venue"
},
  "geometry": {"coordinates":[-1.598139,53.816055],"type":"Point"}
}