{
  "type": "Feature",
  "properties": {
    "iso:country":"GB",
    "sg:address":"82 Bridlington Street, Hunmanby",
    "sg:city":"Filey",
    "sg:classifiers":[
        {
            "category":"Building & Trades",
            "subcategory":"Construction",
            "type":"Services"
        }
    ],
    "sg:phone":"+44 1723 890674",
    "sg:postcode":"YO14 0LP",
    "sg:province":"North Yorkshire",
    "sg:tags":[
        "joiner",
        "carpenter"
    ],
    "wof:name":"B Edmond",
    "wof:placetype":"venue"
},
  "geometry": {"coordinates":[-0.319128,54.177422],"type":"Point"}
}