{
  "type": "Feature",
  "properties": {
    "addr:full":"4a Moor Park, Benica Road Beccles Norfolk NR34 7TQ",
    "addr:housenumber":"4a",
    "addr:postcode":"nr34 7tq",
    "addr:street":"Moor Park Benica Road",
    "iso:country":"GB",
    "sg:address":"4a Moor Park, Benica Road",
    "sg:city":"Beccles",
    "sg:classifiers":[
        {
            "category":"Bus Charters",
            "type":"Transportation"
        }
    ],
    "sg:phone":"+44 1502 717579",
    "sg:postcode":"NR34 7TQ",
    "sg:province":"Norfolk",
    "sg:tags":[
        "hire",
        "coach"
    ],
    "wof:name":"Lamberts Coaches (Beccles) Ltd.",
    "wof:placetype":"venue"
},
  "geometry": {"coordinates":[1.5672450066,52.453666687],"type":"Point"}
}