{
  "type": "Feature",
  "properties": {
    "addr:full":"76 Rookery Road Birmingham West Midlands B21 9NL",
    "addr:housenumber":"76",
    "addr:postcode":"b21 9nl",
    "addr:street":"Rookery Road",
    "iso:country":"GB",
    "sg:address":"76 Rookery Road",
    "sg:city":"Birmingham",
    "sg:classifiers":[
        {
            "category":"Shopping",
            "subcategory":"Comic Books",
            "type":"Retail Goods"
        }
    ],
    "sg:postcode":"B21 9NL",
    "sg:province":"West Midlands",
    "sg:tags":[
        "jeweller"
    ],
    "wof:name":"J Singh",
    "wof:placetype":"venue"
},
  "geometry": {"coordinates":[-1.9403020144,52.5074081421],"type":"Point"}
}