{
  "type": "Feature",
  "properties": {
    "iso:country":"GB",
    "sg:address":"Unit 13 Basset Down, Wroughton",
    "sg:city":"Swindon",
    "sg:classifiers":[
        {
            "category":"Building & Trades",
            "subcategory":"Construction",
            "type":"Services"
        }
    ],
    "sg:postcode":"SN4 9QP",
    "sg:province":"Wiltshire",
    "sg:tags":[
        "builder"
    ],
    "wof:name":"Trowelcraft",
    "wof:placetype":"venue"
},
  "geometry": {"coordinates":[-1.8388999701,51.5207595825],"type":"Point"}
}