{
  "type": "Feature",
  "properties": {
    "addr:full":"87 Park Hall Road, Dulwich London Greater London SE21 8ES",
    "addr:housenumber":"87",
    "addr:postcode":"se21 8es",
    "addr:street":"Park Hall Road",
    "iso:country":"GB",
    "sg:address":"87 Park Hall Road, Dulwich",
    "sg:city":"London",
    "sg:classifiers":[
        {
            "category":"Building & Trades",
            "subcategory":"Construction",
            "type":"Services"
        }
    ],
    "sg:postcode":"SE21 8ES",
    "sg:province":"Greater London",
    "sg:tags":[
        "decorator",
        "painter"
    ],
    "wof:name":"Green & Ball (Builders) Ltd.",
    "wof:placetype":"venue"
},
  "geometry": {"coordinates":[-0.089542,51.436443],"type":"Point"}
}