{
  "type": "Feature",
  "properties": {
    "addr:full":"Unit 2 23 Angel Place Worcester Worcestershire WR1 3QN",
    "addr:housenumber":"unit;23",
    "addr:postcode":"wr1 3qn",
    "addr:street":"Angel Place",
    "iso:country":"GB",
    "sg:address":"Unit 2 23 Angel Place",
    "sg:city":"Worcester",
    "sg:classifiers":[
        {
            "category":"Shopping",
            "subcategory":"Optician",
            "type":"Retail Goods"
        }
    ],
    "sg:phone":"+44 1905 729313",
    "sg:postcode":"WR1 3QN",
    "sg:province":"Worcestershire",
    "wof:name":"Direct Specs Ltd.",
    "wof:placetype":"venue"
},
  "geometry": {"coordinates":[-2.223093,52.19355],"type":"Point"}
}