{
  "type": "Feature",
  "properties": {
    "addr:full":"Station Garage, Oakwell Road Castle Douglas Dumfries and Galloway DG7 1LA",
    "addr:postcode":"dg7 1la",
    "addr:street":"Oakwell Road",
    "iso:country":"GB",
    "sg:address":"Station Garage, Oakwell Road",
    "sg:city":"Castle Douglas",
    "sg:classifiers":[
        {
            "category":"Retail",
            "subcategory":"Auto Repair",
            "type":"Services"
        }
    ],
    "sg:postcode":"DG7 1LA",
    "sg:province":"Dumfries and Galloway",
    "sg:tags":[
        "car",
        "specialist",
        "customizing"
    ],
    "wof:name":"Motofit Auto Centre",
    "wof:placetype":"venue"
},
  "geometry": {"coordinates":[-3.9287040234,54.941619873],"type":"Point"}
}