{
  "type": "Feature",
  "properties": {
    "addr:full":"167 Widmore Road Bromley Kent BR1 3AX",
    "addr:housenumber":"167",
    "addr:postcode":"br1 3ax",
    "addr:street":"Widmore Road",
    "iso:country":"GB",
    "sg:address":"167 Widmore Road",
    "sg:city":"Bromley",
    "sg:classifiers":[
        {
            "category":"Shopping",
            "subcategory":"Clothing, Apparel, & Fashions",
            "type":"Retail Goods"
        }
    ],
    "sg:phone":"+44 20 8466 9866",
    "sg:postcode":"BR1 3AX",
    "sg:province":"Kent",
    "sg:tags":[
        "ladieswear"
    ],
    "wof:name":"Chantilly",
    "wof:placetype":"venue"
},
  "geometry": {"coordinates":[0.032026,51.406376],"type":"Point"}
}