{
  "type": "Feature",
  "properties": {
    "addr:full":"11a Sheep Market Leek Staffordshire ST13 5HN",
    "addr:housenumber":"11a",
    "addr:postcode":"st13 5hn",
    "addr:street":"Market",
    "iso:country":"GB",
    "sg:address":"11a Sheep Market",
    "sg:city":"Leek",
    "sg:classifiers":[
        {
            "category":"Shopping",
            "subcategory":"Shoes",
            "type":"Retail Goods"
        }
    ],
    "sg:phone":"+44 1538 373999",
    "sg:postcode":"ST13 5HN",
    "sg:province":"Staffordshire",
    "sg:tags":[
        "shop"
    ],
    "wof:name":"Instep Shoes",
    "wof:placetype":"venue"
},
  "geometry": {"coordinates":[-2.026258,53.105892],"type":"Point"}
}