{
  "type": "Feature",
  "properties": {
    "addr:full":"Component Ho, Longford Trading Est, Thomas St Manchester Cheshire M32 0LB",
    "addr:postcode":"m32 0lb",
    "addr:street":"Thomas St",
    "iso:country":"GB",
    "sg:address":"Component Ho, Longford Trading Est, Thomas St",
    "sg:city":"Manchester",
    "sg:classifiers":[
        {
            "category":"Professional",
            "subcategory":"Detective & Security Services",
            "type":"Services"
        }
    ],
    "sg:phone":"+44 161 865 6926",
    "sg:postcode":"M32 0LB",
    "sg:province":"Cheshire",
    "sg:tags":[
        "alarm",
        "burglar",
        "system"
    ],
    "wof:name":"C S D Professional",
    "wof:placetype":"venue"
},
  "geometry": {"coordinates":[-2.303554,53.455303],"type":"Point"}
}