{
  "type": "Feature",
  "properties": {
    "iso:country":"GB",
    "sg:address":"8 The Pyghton",
    "sg:city":"Buntingford",
    "sg:classifiers":[
        {
            "category":"Recreation",
            "subcategory":"Dog Park",
            "type":"Entertainment"
        }
    ],
    "sg:postcode":"SG9 9EJ",
    "sg:province":"Hertfordshire",
    "wof:name":"Broomridge Grooming Services",
    "wof:placetype":"venue"
},
  "geometry": {"coordinates":[-0.025562,51.947319],"type":"Point"}
}