{
  "type": "Feature",
  "properties": {
    "addr:full":"19 Low St Buckie Moray AB56 1UX",
    "addr:housenumber":"19",
    "addr:postcode":"ab56 1ux",
    "addr:street":"Low St",
    "iso:country":"GB",
    "sg:address":"19 Low St",
    "sg:city":"Buckie",
    "sg:classifiers":[
        {
            "category":"Retail",
            "subcategory":"Auto Repair",
            "type":"Services"
        }
    ],
    "sg:postcode":"AB56 1UX",
    "sg:province":"Moray",
    "sg:tags":[
        "body",
        "car"
    ],
    "wof:name":"Green,Mark,",
    "wof:placetype":"venue"
},
  "geometry": {"coordinates":[-2.9634668827,57.6782875061],"type":"Point"}
}