{
  "type": "Feature",
  "properties": {
    "addr:full":"Chapel Bar Nottingham Nottinghamshire NG1 6HJ",
    "addr:postcode":"ng1 6hj",
    "addr:street":"Chapel Bar",
    "iso:country":"GB",
    "sg:address":"Chapel Bar",
    "sg:city":"Nottingham",
    "sg:classifiers":[
        {
            "category":"Cinema",
            "subcategory":"Movie Theater",
            "type":"Entertainment"
        }
    ],
    "sg:postcode":"NG1 6HJ",
    "sg:province":"Nottinghamshire",
    "wof:name":"A B C Cinema",
    "wof:placetype":"venue"
},
  "geometry": {"coordinates":[-1.1538900137,52.9541664124],"type":"Point"}
}