{
  "type": "Feature",
  "properties": {
    "iso:country":"GB",
    "sg:address":"Allens Drove, Gorefield",
    "sg:city":"Wisbech",
    "sg:classifiers":[
        {
            "category":"Shopping",
            "type":"Retail Goods"
        }
    ],
    "sg:postcode":"PE13 4PD",
    "sg:province":"Cambridgeshire",
    "sg:tags":[
        "merchant"
    ],
    "wof:name":"Carney Agricultural Services",
    "wof:placetype":"venue"
},
  "geometry": {"coordinates":[0.101585,52.686039],"type":"Point"}
}