{
  "type": "Feature",
  "properties": {
    "addr:full":"206 Grange Rd Southwark Greater London SE1 3AA",
    "addr:housenumber":"206",
    "addr:postcode":"se1 3aa",
    "addr:street":"Grange Rd",
    "iso:country":"GB",
    "sg:address":"206 Grange Rd",
    "sg:city":"Southwark",
    "sg:classifiers":[
        {
            "category":"Health Services",
            "subcategory":"Dentist",
            "type":"Services"
        }
    ],
    "sg:phone":"+44 20 7237 2085",
    "sg:postcode":"SE1 3AA",
    "sg:province":"Greater London",
    "wof:name":"S T Djaba",
    "wof:placetype":"venue"
},
  "geometry": {"coordinates":[-0.0802569985,51.4963417053],"type":"Point"}
}