{
  "type": "Feature",
  "properties": {
    "iso:country":"GB",
    "sg:address":"Unit 10 Lufton Heights, Boundary Way",
    "sg:city":"Yeovil",
    "sg:classifiers":[
        {
            "category":"Communications",
            "subcategory":"Film & Video Production",
            "type":"Services"
        },
        {
            "category":"Professional",
            "subcategory":"Printing & Photocopies",
            "type":"Services"
        }
    ],
    "sg:phone":"+44 1935 706914",
    "sg:postcode":"BA22 8UY",
    "sg:province":"Dorset",
    "sg:tags":[
        "supplier",
        "duplicating",
        "copying",
        "photocopier"
    ],
    "wof:name":"Lynx Copiers",
    "wof:placetype":"venue"
},
  "geometry": {"coordinates":[-2.6499290466,51.0045204163],"type":"Point"}
}