{
  "type": "Feature",
  "properties": {
    "iso:country":"GB",
    "sg:address":"3a St James Road",
    "sg:city":"Exeter",
    "sg:classifiers":[
        {
            "category":"Professional",
            "subcategory":"Employment Agencies",
            "type":"Services"
        }
    ],
    "sg:phone":"+44 1392 215205",
    "sg:postcode":"EX4 6PU",
    "sg:province":"Devon",
    "sg:tags":[
        "consultant"
    ],
    "wof:name":"Drivers",
    "wof:placetype":"venue"
},
  "geometry": {"coordinates":[-3.5208070278,50.7295608521],"type":"Point"}
}