{
  "type": "Feature",
  "properties": {
    "iso:country":"GB",
    "sg:address":"6 Collinson Court Church Street, Frodsham",
    "sg:city":"Warrington",
    "sg:classifiers":[
        {
            "category":"Home & Garden",
            "subcategory":"Hardware",
            "type":"Retail Goods"
        }
    ],
    "sg:phone":"+44 1928 734494",
    "sg:postcode":"WA6 6PN",
    "sg:province":"Cheshire",
    "sg:tags":[
        "device",
        "fixing",
        "fastener"
    ],
    "wof:name":"Max Pac Ltd.",
    "wof:placetype":"venue"
},
  "geometry": {"coordinates":[-2.7243599892,53.2948913574],"type":"Point"}
}