{
  "type": "Feature",
  "properties": {
    "iso:country":"GB",
    "sg:address":"13 Green Moor Link",
    "sg:city":"London",
    "sg:classifiers":[
        {
            "category":"Banks & Credit Unions",
            "subcategory":"Bank",
            "type":"Services"
        },
        {
            "category":"Professional",
            "subcategory":"Business Services",
            "type":"Services"
        }
    ],
    "sg:phone":"+44 20 8360 2491",
    "sg:postcode":"N21 2NN",
    "sg:province":"Greater London",
    "sg:tags":[
        "stocktaking",
        "inventory"
    ],
    "wof:name":"Nikhar Ltd",
    "wof:placetype":"venue"
},
  "geometry": {"coordinates":[-0.0970119983,51.6372261047],"type":"Point"}
}