{
  "type": "Feature",
  "properties": {
    "iso:country":"GB",
    "sg:address":"24 Fore St",
    "sg:city":"Newquay",
    "sg:classifiers":[
        {
            "category":"Shopping",
            "subcategory":"Clothing, Apparel, & Fashions",
            "type":"Retail Goods"
        }
    ],
    "sg:phone":"+44 1637 878128",
    "sg:postcode":"TR7 1LN",
    "sg:province":"Cornwall",
    "sg:tags":[
        "shop"
    ],
    "wof:name":"Two Xs",
    "wof:placetype":"venue"
},
  "geometry": {"coordinates":[-5.087008,50.4146],"type":"Point"}
}