{
  "type": "Feature",
  "properties": {
    "iso:country":"GB",
    "sg:address":"2-6 Heather Gardens",
    "sg:city":"Golders Green",
    "sg:classifiers":[
        {
            "category":"Health Services",
            "subcategory":"Nursing And Care Facility",
            "type":"Services"
        }
    ],
    "sg:phone":"+44 20 8455 8575",
    "sg:postcode":"NW11 9HS",
    "sg:province":"Greater London",
    "sg:tags":[
        "home"
    ],
    "wof:name":"Agnew House",
    "wof:placetype":"venue"
},
  "geometry": {"coordinates":[-0.2094890028,51.5796127319],"type":"Point"}
}