{
  "type": "Feature",
  "properties": {
    "iso:country":"GB",
    "sg:address":"10 High Street",
    "sg:city":"Ilminster",
    "sg:classifiers":[
        {
            "category":"Building & Trades",
            "subcategory":"Plumbing",
            "type":"Services"
        }
    ],
    "sg:phone":"+44 1460 53967",
    "sg:postcode":"TA19 9AW",
    "sg:province":"Somerset",
    "sg:tags":[
        "central",
        "installation",
        "system",
        "servicing",
        "heating"
    ],
    "wof:name":"P Wade",
    "wof:placetype":"venue"
},
  "geometry": {"coordinates":[-2.911698,50.928413],"type":"Point"}
}