{
  "type": "Feature",
  "properties": {
    "addr:full":"Weeton Camp, Singleton Road Preston Lancashire PR4 3JQ",
    "addr:housenumber":"weeton",
    "addr:postcode":"pr4 3jq",
    "addr:street":"Camp Singleton Road",
    "iso:country":"GB",
    "sg:address":"Weeton Camp, Singleton Road",
    "sg:city":"Preston",
    "sg:classifiers":[
        {
            "category":"Home & Garden",
            "subcategory":"Kitchen Supply",
            "type":"Retail Goods"
        }
    ],
    "sg:phone":"+44 20 7963 0000",
    "sg:postcode":"PR4 3JQ",
    "sg:province":"Lancashire",
    "sg:tags":[
        "equipment",
        "catering"
    ],
    "wof:name":"Aramark",
    "wof:placetype":"venue"
},
  "geometry": {"coordinates":[-2.935829,53.805031],"type":"Point"}
}