{
  "type": "Feature",
  "properties": {
    "iso:country":"GB",
    "sg:address":"Southbound Carriageway M5",
    "sg:city":"Worcester",
    "sg:classifiers":[
        {
            "category":"Shopping",
            "subcategory":"Mobile Phones",
            "type":"Retail Goods"
        }
    ],
    "sg:phone":"+44 1684 276116",
    "sg:postcode":"WR8 9LE",
    "sg:province":"Gloucestershire",
    "wof:name":"Midland Mobile Communications Ltd",
    "wof:placetype":"venue"
},
  "geometry": {"coordinates":[-2.1789090633,52.0840682983],"type":"Point"}
}