{
  "type": "Feature",
  "properties": {
    "addr:full":"Lower Bedfords Road Romford Essex RM1 4DG",
    "addr:postcode":"rm1 4dg",
    "addr:street":"Bedfords Road",
    "iso:country":"GB",
    "sg:address":"Lower Bedfords Road",
    "sg:city":"Romford",
    "sg:classifiers":[
        {
            "category":"Sports & Exercise",
            "subcategory":"Golf",
            "type":"Entertainment"
        }
    ],
    "sg:postcode":"RM1 4DG",
    "sg:province":"Essex",
    "sg:tags":[
        "club",
        "course"
    ],
    "wof:name":"Risebridge Golf Centre",
    "wof:placetype":"venue"
},
  "geometry": {"coordinates":[0.180967,51.603683],"type":"Point"}
}