{
  "type": "Feature",
  "properties": {
    "addr:full":"Unit 4, The Maltings, Green Drift Royston Bedfordshire SG8 5DY",
    "addr:housenumber":"unit 4",
    "addr:postcode":"sg8 5dy",
    "addr:street":"The Maltings Green Drift",
    "iso:country":"GB",
    "sg:address":"Unit 4, The Maltings, Green Drift",
    "sg:city":"Royston",
    "sg:classifiers":[
        {
            "category":"Autos & Motor Vehicles",
            "subcategory":"Auto Supplies",
            "type":"Retail Goods"
        }
    ],
    "sg:phone":"+44 1763 236400",
    "sg:postcode":"SG8 5DY",
    "sg:province":"Bedfordshire",
    "sg:tags":[
        "car",
        "accessory"
    ],
    "wof:name":"Progress Europe",
    "wof:placetype":"venue"
},
  "geometry": {"coordinates":[-0.027304,52.051979],"type":"Point"}
}