{
  "type": "Feature",
  "properties": {
    "iso:country":"GB",
    "sg:address":"Unit 1, Peacock Industrial Estate, 20 White Hart Lane",
    "sg:city":"London",
    "sg:classifiers":[
        {
            "category":"Manufacturing",
            "subcategory":"Apparel",
            "type":"Manufacturing & Wholesale Goods"
        }
    ],
    "sg:phone":"+44 20 8885 5806",
    "sg:postcode":"N17 8DS",
    "sg:province":"Greater London",
    "sg:tags":[
        "shirt",
        "maker"
    ],
    "wof:name":"Han-Sol Ltd.",
    "wof:placetype":"venue"
},
  "geometry": {"coordinates":[-0.07675,51.603668],"type":"Point"}
}