{
  "type": "Feature",
  "properties": {
    "iso:country":"GB",
    "sg:address":"14 Campbell St",
    "sg:city":"Hamilton",
    "sg:classifiers":[
        {
            "category":"Shopping",
            "subcategory":"Crafts & Fabrics",
            "type":"Retail Goods"
        }
    ],
    "sg:postcode":"ML3 6AS",
    "sg:province":"South Lanarkshire",
    "sg:tags":[
        "shop",
        "needlecraft",
        "wool"
    ],
    "wof:name":"Bryson,Agnes,",
    "wof:placetype":"venue"
},
  "geometry": {"coordinates":[-4.035609,55.776192],"type":"Point"}
}