{
  "type": "Feature",
  "properties": {
    "addr:full":"42 Church Street Croydon Surrey CR0 1RB",
    "addr:housenumber":"42",
    "addr:postcode":"cr0 1rb",
    "addr:street":"Church Street",
    "iso:country":"GB",
    "sg:address":"42 Church Street",
    "sg:city":"Croydon",
    "sg:classifiers":[
        {
            "category":"Cafe",
            "type":"Food & Drink"
        }
    ],
    "sg:phone":"+44 20 8688 8202",
    "sg:postcode":"CR0 1RB",
    "sg:province":"Surrey",
    "sg:tags":[
        "tea",
        "room"
    ],
    "wof:name":"Cafe Montego",
    "wof:placetype":"venue"
},
  "geometry": {"coordinates":[-0.102741003,51.3735122681],"type":"Point"}
}