{
  "type": "Feature",
  "properties": {
    "addr:full":"Ashley House, Malt Kiln Lane, Appleton Roebuck York North Yorkshire YO23 7DT",
    "addr:postcode":"yo23 7dt",
    "addr:street":"Malt Kiln Lane",
    "iso:country":"GB",
    "sg:address":"Ashley House, Malt Kiln Lane, Appleton Roebuck",
    "sg:city":"York",
    "sg:classifiers":[
        {
            "category":"Sports & Exercise",
            "subcategory":"Swimming Pool",
            "type":"Entertainment"
        }
    ],
    "sg:phone":"+44 1904 744424",
    "sg:postcode":"YO23 7DT",
    "sg:province":"North Yorkshire",
    "sg:tags":[
        "diver"
    ],
    "wof:name":"THE DIVER TRAINING COLLEGE",
    "wof:placetype":"venue"
},
  "geometry": {"coordinates":[-1.1590240002,53.8764381409],"type":"Point"}
}