{
  "type": "Feature",
  "properties": {
    "addr:full":"Silverstone House, 46 Newport Road, Woolstones Milton Keynes Buckinghamshire MK15 0AA",
    "addr:housenumber":"46",
    "addr:postcode":"mk15 0aa",
    "addr:street":"Newport Road",
    "iso:country":"GB",
    "sg:address":"Silverstone House, 46 Newport Road, Woolstones",
    "sg:city":"Milton Keynes",
    "sg:classifiers":[
        {
            "category":"Professional",
            "subcategory":"Art Services",
            "type":"Services"
        }
    ],
    "sg:postcode":"MK15 0AA",
    "sg:province":"Buckinghamshire",
    "sg:tags":[
        "consultant",
        "design"
    ],
    "wof:name":"C G M Ltd.",
    "wof:placetype":"venue"
},
  "geometry": {"coordinates":[-0.7263849974,52.0394706726],"type":"Point"}
}