{
  "type": "Feature",
  "properties": {
    "iso:country":"GB",
    "sg:address":"32-34 Church Street",
    "sg:city":"Seaford",
    "sg:classifiers":[
        {
            "category":"Fast Food",
            "type":"Food & Drink"
        }
    ],
    "sg:phone":"+44 20 8341 0281",
    "sg:postcode":"BN25 1LD",
    "sg:province":"East Sussex",
    "sg:tags":[
        "away",
        "take"
    ],
    "wof:name":"Oldbylands (Bexhill) Ltd.",
    "wof:placetype":"venue"
},
  "geometry": {"coordinates":[0.100851,50.772358],"type":"Point"}
}