{
  "type": "Feature",
  "properties": {
    "iso:country":"GB",
    "sg:address":"10 Ashby Road",
    "sg:city":"Coalville",
    "sg:classifiers":[
        {
            "category":"Personal",
            "subcategory":"Beauty Salon",
            "type":"Services"
        }
    ],
    "sg:postcode":"LE67 3LA",
    "sg:province":"Leicestershire",
    "sg:tags":[
        "lady",
        "hairdresser"
    ],
    "wof:name":"The Londoner Hair Gallery",
    "wof:placetype":"venue"
},
  "geometry": {"coordinates":[-1.395185,52.731468],"type":"Point"}
}