{
  "type": "Feature",
  "properties": {
    "addr:full":"10 Victoria Crescent, High Street Dover Kent CT16 1DU",
    "addr:housenumber":"10",
    "addr:postcode":"ct16 1du",
    "addr:street":"Victoria Crescent High Street",
    "iso:country":"GB",
    "sg:address":"10 Victoria Crescent, High Street",
    "sg:city":"Dover",
    "sg:classifiers":[
        {
            "category":"Professional",
            "subcategory":"Lawyer & Legal Services",
            "type":"Services"
        }
    ],
    "sg:phone":"+44 1304 212206",
    "sg:postcode":"CT16 1DU",
    "sg:province":"Kent",
    "sg:tags":[
        "solicitor"
    ],
    "wof:name":"Peter F Pigott & Co.",
    "wof:placetype":"venue"
},
  "geometry": {"coordinates":[1.318909049,51.1273803711],"type":"Point"}
}