{
  "type": "Feature",
  "properties": {
    "iso:country":"GB",
    "sg:address":"Avon St",
    "sg:city":"Bristol",
    "sg:classifiers":[
        {
            "category":"Autos & Motor Vehicles",
            "subcategory":"Motorcycle Sales",
            "type":"Retail Goods"
        }
    ],
    "sg:phone":"+44 117 977 2272",
    "sg:postcode":"BS2 0PX",
    "sg:province":"City of Bristol",
    "wof:name":"Arriva Kawasaki (bristol)",
    "wof:placetype":"venue"
},
  "geometry": {"coordinates":[-2.578993,51.451694],"type":"Point"}
}