{
  "type": "Feature",
  "properties": {
    "addr:full":"224a Chorley Road, Swinton Manchester Greater Manchester M27 6BA",
    "addr:housenumber":"224a",
    "addr:postcode":"m27 6ba",
    "addr:street":"Chorley Road",
    "iso:country":"GB",
    "sg:address":"224a Chorley Road, Swinton",
    "sg:city":"Manchester",
    "sg:classifiers":[
        {
            "category":"Communications",
            "type":"Services"
        }
    ],
    "sg:postcode":"M27 6BA",
    "sg:province":"Greater Manchester",
    "sg:tags":[
        "telecommunication"
    ],
    "wof:name":"Get Mobile",
    "wof:placetype":"venue"
},
  "geometry": {"coordinates":[-2.3432319164,53.5140266418],"type":"Point"}
}