{
  "type": "Feature",
  "properties": {
    "iso:country":"GB",
    "sg:address":"Unit 2 Schoolhouse Industrial Estate, Blackburn Road",
    "sg:city":"West Calder",
    "sg:classifiers":[
        {
            "category":"Home & Garden",
            "subcategory":"Carpets & Floor Coverings",
            "type":"Retail Goods"
        }
    ],
    "sg:postcode":"EH55 8NF",
    "sg:province":"South Lanarkshire",
    "sg:tags":[
        "carpets",
        "rug",
        "matting"
    ],
    "wof:name":"Mr Carpet",
    "wof:placetype":"venue"
},
  "geometry": {"coordinates":[-3.572372,55.851124],"type":"Point"}
}