{
  "type": "Feature",
  "properties": {
    "iso:country":"GB",
    "sg:address":"Unit 4 Rosemary Lane Industrial Estate",
    "sg:city":"Halstead",
    "sg:classifiers":[
        {
            "category":"Retail",
            "subcategory":"Auto Repair",
            "type":"Services"
        }
    ],
    "sg:postcode":"CO9 1HR",
    "sg:province":"Essex",
    "sg:tags":[
        "modification",
        "garage"
    ],
    "wof:name":"J & A Halim",
    "wof:placetype":"venue"
},
  "geometry": {"coordinates":[0.6337140203,51.9455032349],"type":"Point"}
}