{
  "type": "Feature",
  "properties": {
    "addr:full":"7 Hamilton Sq Birkenhead Merseyside L41 6AU",
    "addr:housenumber":"7",
    "addr:postcode":"l41 6au",
    "addr:street":"Hamilton Sq",
    "iso:country":"GB",
    "sg:address":"7 Hamilton Sq",
    "sg:city":"Birkenhead",
    "sg:classifiers":[
        {
            "category":"Building & Trades",
            "subcategory":"Construction",
            "type":"Services"
        }
    ],
    "sg:phone":"+44 151 632 1094",
    "sg:postcode":"L41 6AU",
    "sg:province":"Merseyside",
    "sg:tags":[
        "decorator",
        "painter"
    ],
    "wof:name":"K J Mock",
    "wof:placetype":"venue"
},
  "geometry": {"coordinates":[-3.015217,53.394203],"type":"Point"}
}