{
  "type": "Feature",
  "properties": {
    "iso:country":"GB",
    "sg:address":"191 High Street",
    "sg:city":"Lincoln",
    "sg:classifiers":[
        {
            "category":"Shopping",
            "subcategory":"Clothing, Apparel, & Fashions",
            "type":"Retail Goods"
        }
    ],
    "sg:postcode":"LN5 7AL",
    "sg:province":"Lincolnshire",
    "sg:tags":[
        "shop"
    ],
    "wof:name":"River Island Clothing Co. Ltd.",
    "wof:placetype":"venue"
},
  "geometry": {"coordinates":[-0.541294,53.2272],"type":"Point"}
}