{
  "type": "Feature",
  "properties": {
    "iso:country":"GB",
    "sg:address":"40 Victoria Road",
    "sg:city":"Aberdeen",
    "sg:classifiers":[
        {
            "category":"Home & Garden",
            "subcategory":"Hardware",
            "type":"Retail Goods"
        }
    ],
    "sg:postcode":"AB11 9DR",
    "sg:province":"Aberdeen City",
    "sg:tags":[
        "retailer",
        "diy"
    ],
    "wof:name":"Price Busters Mini Markets",
    "wof:placetype":"venue"
},
  "geometry": {"coordinates":[-2.089008,57.138477],"type":"Point"}
}