{
  "type": "Feature",
  "properties": {
    "iso:country":"GB",
    "sg:address":"111 Woodfield Street, Morriston",
    "sg:city":"Swansea",
    "sg:classifiers":[
        {
            "category":"Banks & Credit Unions",
            "subcategory":"Bank",
            "type":"Services"
        }
    ],
    "sg:phone":"+44 1792 781668",
    "sg:postcode":"SA6 8AU",
    "sg:province":"Swansea",
    "wof:name":"Lloyds T S B Bank Plc",
    "wof:placetype":"venue"
},
  "geometry": {"coordinates":[-3.926095,51.665073],"type":"Point"}
}