{
  "type": "Feature",
  "properties": {
    "addr:full":"Turney St Halifax West Yorkshire HX3 5PP",
    "addr:postcode":"hx3 5pp",
    "addr:street":"Turney St",
    "iso:country":"GB",
    "sg:address":"Turney St",
    "sg:city":"Halifax",
    "sg:classifiers":[
        {
            "category":"Professional",
            "subcategory":"Engineering",
            "type":"Services"
        }
    ],
    "sg:phone":"+44 1422 323313",
    "sg:postcode":"HX3 5PP",
    "sg:province":"West Yorkshire",
    "wof:name":"Ratcliffe Threaded Bar Services",
    "wof:placetype":"venue"
},
  "geometry": {"coordinates":[-1.876039,53.735939],"type":"Point"}
}