{
  "type": "Feature",
  "properties": {
    "addr:full":"Wharf House, Station Road, Oundle Peterborough Cambridgeshire PE8 4DE",
    "addr:postcode":"pe8 4de",
    "addr:street":"Station Road",
    "iso:country":"GB",
    "sg:address":"Wharf House, Station Road, Oundle",
    "sg:city":"Peterborough",
    "sg:classifiers":[
        {
            "category":"Retail",
            "subcategory":"Event Space",
            "type":"Services"
        }
    ],
    "sg:phone":"+44 1832 274622",
    "sg:postcode":"PE8 4DE",
    "sg:province":"Cambridgeshire",
    "sg:tags":[
        "sale",
        "boat"
    ],
    "wof:name":"B A Peters Plc",
    "wof:placetype":"venue"
},
  "geometry": {"coordinates":[-0.4708699882,52.4808273315],"type":"Point"}
}