{
  "type": "Feature",
  "properties": {
    "iso:country":"GB",
    "sg:address":"63 Raynville Rise, Bramley",
    "sg:city":"Leeds",
    "sg:classifiers":[
        {
            "category":"Building & Trades",
            "subcategory":"Construction",
            "type":"Services"
        }
    ],
    "sg:phone":"+44 113 278 7305",
    "sg:postcode":"LS13 2QG",
    "sg:province":"West Yorkshire",
    "sg:tags":[
        "heating",
        "contractor"
    ],
    "wof:name":"Heating Plumbing & Boiler Services",
    "wof:placetype":"venue"
},
  "geometry": {"coordinates":[-1.617711,53.810436],"type":"Point"}
}