{
  "type": "Feature",
  "properties": {
    "addr:full":"Nivelles, Fen Street, Old Buckenham Attleborough Norfolk NR17 1NW",
    "addr:postcode":"nr17 1nw",
    "addr:street":"Fen Street",
    "iso:country":"GB",
    "sg:address":"Nivelles, Fen Street, Old Buckenham",
    "sg:city":"Attleborough",
    "sg:classifiers":[
        {
            "category":"Building & Trades",
            "subcategory":"Construction",
            "type":"Services"
        }
    ],
    "sg:phone":"+44 1953 453802",
    "sg:postcode":"NR17 1NW",
    "sg:province":"Norfolk",
    "sg:tags":[
        "heating",
        "contractor"
    ],
    "wof:name":"Graham Turner Plumbing & Heating",
    "wof:placetype":"venue"
},
  "geometry": {"coordinates":[1.0342999697,52.4800987244],"type":"Point"}
}