{
  "type": "Feature",
  "properties": {
    "addr:full":"280 Earlsfield Road London Greater London SW18 3EH",
    "addr:housenumber":"280",
    "addr:postcode":"sw18 3eh",
    "addr:street":"Earlsfield Road",
    "iso:country":"GB",
    "sg:address":"280 Earlsfield Road",
    "sg:city":"London",
    "sg:classifiers":[
        {
            "category":"Real Estate",
            "subcategory":"Surveying",
            "type":"Services"
        }
    ],
    "sg:phone":"+44 20 8874 4959",
    "sg:postcode":"SW18 3EH",
    "sg:province":"Greater London",
    "sg:tags":[
        "surveyor",
        "valuer"
    ],
    "wof:name":"David Ingles Associates",
    "wof:placetype":"venue"
},
  "geometry": {"coordinates":[-0.1868110001,51.444694519],"type":"Point"}
}