{
  "type": "Feature",
  "properties": {
    "iso:country":"GB",
    "sg:address":"165 Wollaston Road, Irchester",
    "sg:city":"Wellingborough",
    "sg:classifiers":[
        {
            "category":"Building & Trades",
            "subcategory":"Plumbing",
            "type":"Services"
        }
    ],
    "sg:phone":"+44 1933 311542",
    "sg:postcode":"NN29 7DD",
    "sg:province":"Bedfordshire",
    "sg:tags":[
        "heating"
    ],
    "wof:name":"Donald Jones",
    "wof:placetype":"venue"
},
  "geometry": {"coordinates":[-0.652529,52.27932],"type":"Point"}
}