{
  "type": "Feature",
  "properties": {
    "addr:full":"1 Addison Rd, Chilton Estate Sudbury Essex CO10 2YW",
    "addr:housenumber":"1",
    "addr:postcode":"co10 2yw",
    "addr:street":"Addison Rd;Estate",
    "iso:country":"GB",
    "sg:address":"1 Addison Rd, Chilton Estate",
    "sg:city":"Sudbury",
    "sg:classifiers":[
        {
            "category":"Professional",
            "subcategory":"Management & Consulting",
            "type":"Services"
        }
    ],
    "sg:phone":"+44 1787 373811",
    "sg:postcode":"CO10 2YW",
    "sg:province":"Essex",
    "sg:tags":[
        "consultant",
        "business"
    ],
    "wof:name":"Wilkinson Hatton Associates",
    "wof:placetype":"venue"
},
  "geometry": {"coordinates":[0.7493020296,52.0441818237],"type":"Point"}
}