{
  "type": "Feature",
  "properties": {
    "addr:full":"Unit 13 Aireside Mills Keighley North Yorkshire BD20 8LW",
    "addr:housenumber":"unit 13",
    "addr:postcode":"bd20 8lw",
    "addr:street":"Aireside Mills",
    "iso:country":"GB",
    "sg:address":"Unit 13 Aireside Mills",
    "sg:city":"Keighley",
    "sg:classifiers":[
        {
            "category":"Shopping",
            "subcategory":"Computers & Home Electronics",
            "type":"Retail Goods"
        }
    ],
    "sg:phone":"+44 1535 630855",
    "sg:postcode":"BD20 8LW",
    "sg:province":"North Yorkshire",
    "wof:name":"Croft Furniture",
    "wof:placetype":"venue"
},
  "geometry": {"coordinates":[-2.0017390251,53.8993988037],"type":"Point"}
}