{
  "type": "Feature",
  "properties": {
    "addr:full":"Church Lane, Fradley Lichfield Staffordshire WS13 8NL",
    "addr:postcode":"ws13 8nl",
    "addr:street":"Church Lane",
    "iso:country":"GB",
    "sg:address":"Church Lane, Fradley",
    "sg:city":"Lichfield",
    "sg:classifiers":[
        {
            "category":"Education",
            "subcategory":"School",
            "type":"Public Place"
        }
    ],
    "sg:phone":"+44 1283 790268",
    "sg:postcode":"WS13 8NL",
    "sg:province":"Staffordshire",
    "sg:tags":[
        "local",
        "authority"
    ],
    "wof:name":"St Stephens Primary School",
    "wof:placetype":"venue"
},
  "geometry": {"coordinates":[-1.761432,52.719864],"type":"Point"}
}