{
  "type": "Feature",
  "properties": {
    "addr:full":"93 Shenley Avenue Ruislip Greater London HA4 6BT",
    "addr:housenumber":"93",
    "addr:postcode":"ha4 6bt",
    "addr:street":"Shenley Avenue",
    "iso:country":"GB",
    "sg:address":"93 Shenley Avenue",
    "sg:city":"Ruislip",
    "sg:classifiers":[
        {
            "category":"Arena",
            "subcategory":"Sports Club",
            "type":"Entertainment"
        }
    ],
    "sg:phone":"+44 1895 632851",
    "sg:postcode":"HA4 6BT",
    "sg:province":"Greater London",
    "sg:tags":[
        "ground"
    ],
    "wof:name":"G W Sports Associates",
    "wof:placetype":"venue"
},
  "geometry": {"coordinates":[-0.417829,51.570747],"type":"Point"}
}