{
  "type": "Feature",
  "properties": {
    "addr:full":"16 Birch Grn Staines Berkshire TW18 4HA",
    "addr:housenumber":"16",
    "addr:postcode":"tw18 4ha",
    "addr:street":"Birch Grn",
    "iso:country":"GB",
    "sg:address":"16 Birch Grn",
    "sg:city":"Staines",
    "sg:classifiers":[
        {
            "category":"Home & Garden",
            "subcategory":"Home Furnishings",
            "type":"Retail Goods"
        }
    ],
    "sg:postcode":"TW18 4HA",
    "sg:province":"Berkshire",
    "sg:tags":[
        "furnishers",
        "planner",
        "kitchen"
    ],
    "wof:name":"Trans-Form",
    "wof:placetype":"venue"
},
  "geometry": {"coordinates":[-0.5039439797,51.4369621277],"type":"Point"}
}