{
  "type": "Feature",
  "properties": {
    "iso:country":"GB",
    "sg:address":"9 Olive Branch Crescent, Briton Ferry",
    "sg:city":"Neath",
    "sg:classifiers":[
        {
            "category":"Real Estate",
            "subcategory":"Surveying",
            "type":"Services"
        }
    ],
    "sg:phone":"+44 1639 821091",
    "sg:postcode":"SA11 2UF",
    "sg:province":"Neath Port Talbot",
    "sg:tags":[
        "surveyor",
        "land"
    ],
    "wof:name":"John Cole Surveying Agency Ltd.",
    "wof:placetype":"venue"
},
  "geometry": {"coordinates":[-3.822065115,51.6426315308],"type":"Point"}
}