{
  "type": "Feature",
  "properties": {
    "addr:full":"32a Mansfield Road Rotherham South Yorkshire S60 2DR",
    "addr:housenumber":"32a",
    "addr:postcode":"s60 2dr",
    "addr:street":"Mansfield Road",
    "iso:country":"GB",
    "sg:address":"32a Mansfield Road",
    "sg:city":"Rotherham",
    "sg:classifiers":[
        {
            "category":"Professional",
            "subcategory":"Art Services",
            "type":"Services"
        }
    ],
    "sg:phone":"+44 1709 363935",
    "sg:postcode":"S60 2DR",
    "sg:province":"South Yorkshire",
    "sg:tags":[
        "framing"
    ],
    "wof:name":"Frameways",
    "wof:placetype":"venue"
},
  "geometry": {"coordinates":[-1.35388,53.427956],"type":"Point"}
}