{
  "type": "Feature",
  "properties": {
    "iso:country":"GB",
    "sg:address":"32a Mansfield Road",
    "sg:city":"Rotherham",
    "sg:classifiers":[
        {
            "category":"Professional",
            "subcategory":"Art Services",
            "type":"Services"
        }
    ],
    "sg:phone":"+44 1709 363935",
    "sg:postcode":"S60 2DR",
    "sg:province":"South Yorkshire",
    "sg:tags":[
        "framing"
    ],
    "wof:name":"Frameways",
    "wof:placetype":"venue"
},
  "geometry": {"coordinates":[-1.35388,53.427956],"type":"Point"}
}