{
  "type": "Feature",
  "properties": {
    "addr:full":"83 Tulsemere Rd London Greater London SE27 9EH",
    "addr:housenumber":"83",
    "addr:postcode":"se27 9eh",
    "addr:street":"Tulsemere Rd",
    "iso:country":"GB",
    "sg:address":"83 Tulsemere Rd",
    "sg:city":"London",
    "sg:classifiers":[
        {
            "category":"Personal",
            "subcategory":"Beauty Salon",
            "type":"Services"
        }
    ],
    "sg:postcode":"SE27 9EH",
    "sg:province":"Greater London",
    "sg:tags":[
        "unisex",
        "hairdresser"
    ],
    "wof:name":"Cunningham,Angela,",
    "wof:placetype":"venue"
},
  "geometry": {"coordinates":[-0.0969720036,51.4365348816],"type":"Point"}
}