{
  "type": "Feature",
  "properties": {
    "iso:country":"GB",
    "sg:address":"46 Montclair Drive, Childwall",
    "sg:city":"Liverpool",
    "sg:classifiers":[
        {
            "category":"Building & Trades",
            "subcategory":"Construction",
            "type":"Services"
        }
    ],
    "sg:postcode":"L18 0HB",
    "sg:province":"Merseyside",
    "sg:tags":[
        "builder"
    ],
    "wof:name":"J A Roberts General Building Contractors",
    "wof:placetype":"venue"
},
  "geometry": {"coordinates":[-2.9048919678,53.3914070129],"type":"Point"}
}