{
  "type": "Feature",
  "properties": {
    "addr:full":"Flat 14 Egerton Court, Upper Park Road, Victoria Park Manchester Greater Manchester M14 5SL",
    "addr:housenumber":"flat 14",
    "addr:postcode":"m14 5sl",
    "addr:street":"Egerton Court Upper Park Road",
    "iso:country":"GB",
    "sg:address":"Flat 14 Egerton Court, Upper Park Road, Victoria Park",
    "sg:city":"Manchester",
    "sg:classifiers":[
        {
            "category":"Retail",
            "subcategory":"Driving School",
            "type":"Services"
        }
    ],
    "sg:phone":"+44 161 248 9563",
    "sg:postcode":"M14 5SL",
    "sg:province":"Greater Manchester",
    "wof:name":"K E Smith",
    "wof:placetype":"venue"
},
  "geometry": {"coordinates":[-2.21991,53.45718],"type":"Point"}
}