{
  "type": "Feature",
  "properties": {
    "iso:country":"GB",
    "sg:address":"7a Deans Court",
    "sg:city":"Bicester",
    "sg:classifiers":[
        {
            "category":"Professional",
            "subcategory":"Employment Agencies",
            "type":"Services"
        }
    ],
    "sg:phone":"+44 1869 323444",
    "sg:postcode":"OX26 6RD",
    "sg:province":"Oxfordshire",
    "sg:tags":[
        "consultant"
    ],
    "wof:name":"Workworld",
    "wof:placetype":"venue"
},
  "geometry": {"coordinates":[-1.15354,51.898026],"type":"Point"}
}