{
  "type": "Feature",
  "properties": {
    "addr:full":"Three Acres Chapel Lane, Easton Winchester Hampshire SO21 1HQ",
    "addr:postcode":"so21 1hq",
    "addr:street":"Chapel Lane",
    "iso:country":"GB",
    "sg:address":"Three Acres Chapel Lane, Easton",
    "sg:city":"Winchester",
    "sg:classifiers":[
        {
            "category":"Health Services",
            "subcategory":"Clinic",
            "type":"Services"
        }
    ],
    "sg:phone":"+44 1962 861378",
    "sg:postcode":"SO21 1HQ",
    "sg:province":"Hampshire",
    "sg:tags":[
        "aromatherapy"
    ],
    "wof:name":"Emma Mitchell ITEC RAW",
    "wof:placetype":"venue"
},
  "geometry": {"coordinates":[-1.2718290091,51.0859298706],"type":"Point"}
}