{
  "type": "Feature",
  "properties": {
    "iso:country":"GB",
    "sg:address":"15 Bournemouth Road",
    "sg:city":"Southampton",
    "sg:classifiers":[
        {
            "category":"Communications",
            "type":"Services"
        }
    ],
    "sg:postcode":"SO53 3DA",
    "sg:province":"Hampshire",
    "sg:tags":[
        "tv",
        "video",
        "radio"
    ],
    "wof:name":"A J Hoskins T V Services",
    "wof:placetype":"venue"
},
  "geometry": {"coordinates":[-1.402199,50.954441],"type":"Point"}
}