{
  "type": "Feature",
  "properties": {
    "iso:country":"GB",
    "sg:address":"Mawbry House, Fore Street",
    "sg:city":"Chard",
    "sg:classifiers":[
        {
            "category":"Organizations",
            "subcategory":"Community Association",
            "type":"Services"
        }
    ],
    "sg:phone":"+44 1460 67578",
    "sg:postcode":"TA20 1PH",
    "sg:province":"Devon",
    "sg:tags":[
        "associations",
        "housing",
        "co-operatives",
        "society",
        "trust",
        "societies"
    ],
    "wof:name":"STONHAM HOUSING ASSOCIATION LTD",
    "wof:placetype":"venue"
},
  "geometry": {"coordinates":[-2.961709,50.873173],"type":"Point"}
}