{
  "type": "Feature",
  "properties": {
    "iso:country":"GB",
    "sg:address":"Leek & Rushden Branch, 16 Leonard Street",
    "sg:city":"Leek",
    "sg:classifiers":[
        {
            "category":"Insurance",
            "subcategory":"Insurance Agent",
            "type":"Services"
        }
    ],
    "sg:phone":"+44 1538 382965",
    "sg:postcode":"ST13 5JP",
    "sg:province":"Staffordshire",
    "wof:name":"National Farmers Union",
    "wof:placetype":"venue"
},
  "geometry": {"coordinates":[-2.021736,53.103554],"type":"Point"}
}