{
  "type": "Feature",
  "properties": {
    "iso:country":"GB",
    "sg:address":"Fox Hill",
    "sg:city":"Norwich",
    "sg:classifiers":[
        {
            "category":"Organizations",
            "subcategory":"Community Association",
            "type":"Services"
        }
    ],
    "sg:postcode":"NR12 9HZ",
    "sg:province":"Norfolk",
    "sg:tags":[
        "relation",
        "public"
    ],
    "wof:name":"Beverley Wigg P R & Communications Ltd.",
    "wof:placetype":"venue"
},
  "geometry": {"coordinates":[1.483402,52.804718],"type":"Point"}
}