{
  "type": "Feature",
  "properties": {
    "addr:full":"27 Temple Rise Leeds West Yorkshire LS15 0JU",
    "addr:housenumber":"27",
    "addr:postcode":"ls15 0ju",
    "addr:street":"Temple Rise",
    "iso:country":"GB",
    "sg:address":"27 Temple Rise",
    "sg:city":"Leeds",
    "sg:classifiers":[
        {
            "category":"Retail",
            "subcategory":"Driving School",
            "type":"Services"
        }
    ],
    "sg:phone":"+44 113 260 9308",
    "sg:postcode":"LS15 0JU",
    "sg:province":"West Yorkshire",
    "wof:name":"Metro School of Motoring",
    "wof:placetype":"venue"
},
  "geometry": {"coordinates":[-1.467127,53.790924],"type":"Point"}
}