{
  "type": "Feature",
  "properties": {
    "iso:country":"GB",
    "sg:address":"3 Woodhall Park Mount",
    "sg:city":"Pudsey",
    "sg:classifiers":[
        {
            "category":"Professional",
            "subcategory":"Management & Consulting",
            "type":"Services"
        }
    ],
    "sg:phone":"+44 113 256 4393",
    "sg:postcode":"LS28 7HE",
    "sg:province":"West Yorkshire",
    "sg:tags":[
        "consultant",
        "business"
    ],
    "wof:name":"John B Spaull",
    "wof:placetype":"venue"
},
  "geometry": {"coordinates":[-1.69062,53.806805],"type":"Point"}
}