{
  "type": "Feature",
  "properties": {
    "addr:full":"41 High St Twickenham Greater London TW2 7LB",
    "addr:housenumber":"41",
    "addr:postcode":"tw2 7lb",
    "addr:street":"High St",
    "iso:country":"GB",
    "sg:address":"41 High St",
    "sg:city":"Twickenham",
    "sg:classifiers":[
        {
            "category":"Shopping",
            "subcategory":"News",
            "type":"Retail Goods"
        }
    ],
    "sg:phone":"+44 20 8894 7065",
    "sg:postcode":"TW2 7LB",
    "sg:province":"Greater London",
    "sg:tags":[
        "newsagent"
    ],
    "wof:name":"Marks Newsagents",
    "wof:placetype":"venue"
},
  "geometry": {"coordinates":[-0.357804,51.452122],"type":"Point"}
}