{
  "type": "Feature",
  "properties": {
    "addr:full":"The Management Centre, 31 Newington Grn London Greater London N16 9PU",
    "addr:housenumber":"31",
    "addr:postcode":"n16 9pu",
    "addr:street":"Newington Grn",
    "iso:country":"GB",
    "sg:address":"The Management Centre, 31 Newington Grn",
    "sg:city":"London",
    "sg:classifiers":[
        {
            "category":"Professional",
            "subcategory":"Management & Consulting",
            "type":"Services"
        }
    ],
    "sg:postcode":"N16 9PU",
    "sg:province":"Greater London",
    "sg:tags":[
        "consultant",
        "training",
        "business"
    ],
    "wof:name":"Network Training & Research",
    "wof:placetype":"venue"
},
  "geometry": {"coordinates":[-0.0841299966,51.5511703491],"type":"Point"}
}