{
  "type": "Feature",
  "properties": {
    "addr:full":"4 Church Street Edenbridge East Sussex TN8 5BD",
    "addr:housenumber":"4",
    "addr:postcode":"tn8 5bd",
    "addr:street":"Church Street",
    "iso:country":"GB",
    "sg:address":"4 Church Street",
    "sg:city":"Edenbridge",
    "sg:classifiers":[
        {
            "category":"Travel",
            "subcategory":"Travel Agent",
            "type":"Entertainment"
        }
    ],
    "sg:phone":"+44 1732 867445",
    "sg:postcode":"TN8 5BD",
    "sg:province":"East Sussex",
    "wof:name":"Nautilus Yachting",
    "wof:placetype":"venue"
},
  "geometry": {"coordinates":[0.065689,51.195618],"type":"Point"}
}