{
  "type": "Feature",
  "properties": {
    "addr:full":"Penrhys Estate Ferndale Rhondda, Cynon, Taff CF43 3PL",
    "addr:postcode":"cf43 3pl",
    "addr:street":"Cynon Taff",
    "iso:country":"GB",
    "sg:address":"Penrhys Estate",
    "sg:city":"Ferndale",
    "sg:classifiers":[
        {
            "category":"Education",
            "subcategory":"School",
            "type":"Public Place"
        },
        {
            "category":"Government",
            "subcategory":"Office",
            "type":"Public Place"
        }
    ],
    "sg:phone":"+44 1443 730037",
    "sg:postcode":"CF43 3PL",
    "sg:province":"Rhondda, Cynon, Taff",
    "sg:tags":[
        "local",
        "authority"
    ],
    "wof:name":"Penrhys Primary School",
    "wof:placetype":"venue"
},
  "geometry": {"coordinates":[-3.4404900074,51.6414527893],"type":"Point"}
}