{
  "type": "Feature",
  "properties": {
    "addr:full":"Shaftesbury Avenue, Goring By Sea Worthing West Sussex BN12 4ET",
    "addr:postcode":"bn12 4et",
    "addr:street":"Shaftesbury Avenue",
    "iso:country":"GB",
    "sg:address":"Shaftesbury Avenue, Goring By Sea",
    "sg:city":"Worthing",
    "sg:classifiers":[
        {
            "category":"Community Center",
            "type":"Public Place"
        },
        {
            "category":"Government",
            "subcategory":"Office",
            "type":"Public Place"
        }
    ],
    "sg:phone":"+44 1903 502237",
    "sg:postcode":"BN12 4ET",
    "sg:province":"West Sussex",
    "sg:tags":[
        "recreation",
        "local",
        "leisure",
        "centre"
    ],
    "wof:name":"Worthing Leisure Centre",
    "wof:placetype":"venue"
},
  "geometry": {"coordinates":[-0.409614,50.815586],"type":"Point"}
}