{
  "type": "Feature",
  "properties": {
    "addr:full":"106a Furtherwick Road Canvey Island Essex SS8 7AL",
    "addr:housenumber":"106a",
    "addr:postcode":"ss8 7al",
    "addr:street":"Furtherwick Road",
    "iso:country":"GB",
    "sg:address":"106a Furtherwick Road",
    "sg:city":"Canvey Island",
    "sg:classifiers":[
        {
            "category":"Professional",
            "subcategory":"Accounting & Tax Preparation",
            "type":"Services"
        }
    ],
    "sg:postcode":"SS8 7AL",
    "sg:province":"Essex",
    "sg:tags":[
        "accountant"
    ],
    "wof:name":"Michael D Jones",
    "wof:placetype":"venue"
},
  "geometry": {"coordinates":[0.5926210284,51.5200767517],"type":"Point"}
}