{
  "type": "Feature",
  "properties": {
    "addr:full":"92-94 High Street, Stony Stratford Milton Keynes Buckinghamshire MK11 1AH",
    "addr:housenumber":"92-94",
    "addr:postcode":"mk11 1ah",
    "addr:street":"High Street",
    "iso:country":"GB",
    "sg:address":"92-94 High Street, Stony Stratford",
    "sg:city":"Milton Keynes",
    "sg:classifiers":[
        {
            "category":"Travel",
            "subcategory":"Hotels & Motels",
            "type":"Entertainment"
        },
        {
            "category":"Food & Beverages",
            "subcategory":"Meat & Fish",
            "type":"Retail Goods"
        }
    ],
    "sg:phone":"+44 1908 564733",
    "sg:postcode":"MK11 1AH",
    "sg:province":"Buckinghamshire",
    "sg:tags":[
        "seafood"
    ],
    "wof:name":"Different Drummer Hotel",
    "wof:placetype":"venue"
},
  "geometry": {"coordinates":[-0.8555340171,52.0584602356],"type":"Point"}
}