{
  "type": "Feature",
  "properties": {
    "addr:full":"Kales Building, 53-55 Gatwick Rd Crawley Surrey RH10 2RB",
    "addr:housenumber":"53-55",
    "addr:postcode":"rh10 2rb",
    "addr:street":"Gatwick Rd",
    "iso:country":"GB",
    "sg:address":"Kales Building, 53-55 Gatwick Rd",
    "sg:city":"Crawley",
    "sg:classifiers":[
        {
            "category":"Real Estate",
            "subcategory":"Real Estate Operator",
            "type":"Services"
        }
    ],
    "sg:phone":"+44 1293 406161",
    "sg:postcode":"RH10 2RB",
    "sg:province":"Surrey",
    "sg:tags":[
        "letting",
        "agent"
    ],
    "wof:name":"Martin & Co",
    "wof:placetype":"venue"
},
  "geometry": {"coordinates":[-0.184753,51.118458],"type":"Point"}
}