{
  "type": "Feature",
  "properties": {
    "iso:country":"GB",
    "sg:address":"5 South Avenue, Clydebank Business Park",
    "sg:city":"Clydebank",
    "sg:classifiers":[
        {
            "category":"Government",
            "subcategory":"Post Office",
            "type":"Public Place"
        }
    ],
    "sg:phone":"+44 141 951 4221",
    "sg:postcode":"G81 2LG",
    "sg:province":"East Dunbartonshire",
    "sg:tags":[
        "organisation",
        "soc",
        "research"
    ],
    "wof:name":"Scottish Biomedical Foundation",
    "wof:placetype":"venue"
},
  "geometry": {"coordinates":[-4.3972887993,55.9060211182],"type":"Point"}
}