{
  "type": "Feature",
  "properties": {
    "addr:full":"49 Stamford Rd Altrincham Cheshire WA14 2RQ",
    "addr:housenumber":"49",
    "addr:postcode":"wa14 2rq",
    "addr:street":"Stamford Rd",
    "iso:country":"GB",
    "sg:address":"49 Stamford Rd",
    "sg:city":"Altrincham",
    "sg:classifiers":[
        {
            "category":"Shopping",
            "subcategory":"Discount & Variety Stores",
            "type":"Retail Goods"
        }
    ],
    "sg:phone":"+44 161 929 9282",
    "sg:postcode":"WA14 2RQ",
    "sg:province":"Cheshire",
    "sg:tags":[
        "centre"
    ],
    "wof:name":"Big Save",
    "wof:placetype":"venue"
},
  "geometry": {"coordinates":[-2.3575530052,53.3784065247],"type":"Point"}
}