{
  "type": "Feature",
  "properties": {
    "addr:full":"42 Springfield Cres Solihull West Midlands B92 9AF",
    "addr:housenumber":"42",
    "addr:postcode":"b92 9af",
    "addr:street":"Springfield Cres",
    "iso:country":"GB",
    "sg:address":"42 Springfield Cres",
    "sg:city":"Solihull",
    "sg:classifiers":[
        {
            "category":"Organizations",
            "subcategory":"Non-profit Organization",
            "type":"Services"
        }
    ],
    "sg:phone":"+44 121 743 7280",
    "sg:postcode":"B92 9AF",
    "sg:province":"West Midlands",
    "sg:tags":[
        "organisation",
        "voluntary",
        "charity"
    ],
    "wof:name":"Cystic Fibrosis Research Investment Trus",
    "wof:placetype":"venue"
},
  "geometry": {"coordinates":[-1.7757099867,52.4481315613],"type":"Point"}
}