{
  "type": "Feature",
  "properties": {
    "iso:country":"GB",
    "sg:address":"16 Ribblesdale Road, Stirchley",
    "sg:city":"Birmingham",
    "sg:classifiers":[
        {
            "category":"Building & Trades",
            "subcategory":"Landscaping Services",
            "type":"Services"
        }
    ],
    "sg:phone":"+44 121 472 5151",
    "sg:postcode":"B30 2YP",
    "sg:province":"West Midlands",
    "sg:tags":[
        "horticultural",
        "consultant"
    ],
    "wof:name":"Alexanders (Horticultural) Ltd.",
    "wof:placetype":"venue"
},
  "geometry": {"coordinates":[-1.9230389595,52.431388855],"type":"Point"}
}