{
  "type": "Feature",
  "properties": {
    "addr:full":"3 Courtlands Avenue Hampton Greater London TW12 3NS",
    "addr:housenumber":"3",
    "addr:postcode":"tw12 3ns",
    "addr:street":"Courtlands Avenue",
    "iso:country":"GB",
    "sg:address":"3 Courtlands Avenue",
    "sg:city":"Hampton",
    "sg:classifiers":[
        {
            "category":"Professional",
            "subcategory":"Art Services",
            "type":"Services"
        }
    ],
    "sg:phone":"+44 20 8783 1167",
    "sg:postcode":"TW12 3NS",
    "sg:province":"Greater London",
    "sg:tags":[
        "consultant",
        "design"
    ],
    "wof:name":"Tony Lawrence",
    "wof:placetype":"venue"
},
  "geometry": {"coordinates":[-0.3771010041,51.423084259],"type":"Point"}
}