{
  "type": "Feature",
  "properties": {
    "iso:country":"GB",
    "sg:address":"Unit 14 Wivenhoe Business Centre, Brook Street, Wivenhoe",
    "sg:city":"Colchester",
    "sg:classifiers":[
        {
            "category":"Professional",
            "subcategory":"Engineering",
            "type":"Services"
        }
    ],
    "sg:phone":"+44 1206 824341",
    "sg:postcode":"CO7 9DP",
    "sg:province":"Essex",
    "sg:tags":[
        "electronic",
        "engineer"
    ],
    "wof:name":"Keartronics Electronic Engineering",
    "wof:placetype":"venue"
},
  "geometry": {"coordinates":[0.95947,51.856838],"type":"Point"}
}