{
  "type": "Feature",
  "properties": {
    "iso:country":"GB",
    "sg:address":"3 Gas Lane, St Phillips",
    "sg:city":"Bristol",
    "sg:classifiers":[
        {
            "category":"Home & Garden",
            "subcategory":"Kitchen Supply",
            "type":"Retail Goods"
        }
    ],
    "sg:postcode":"BS2 0QT",
    "sg:province":"City of Bristol",
    "sg:tags":[
        "equipment",
        "catering"
    ],
    "wof:name":"Udell Services",
    "wof:placetype":"venue"
},
  "geometry": {"coordinates":[-2.574469,51.450722],"type":"Point"}
}