{
  "type": "Feature",
  "properties": {
    "iso:country":"GB",
    "sg:address":"Newtons Lane, Cossall",
    "sg:city":"Nottingham",
    "sg:classifiers":[
        {
            "category":"Building & Trades",
            "subcategory":"Construction",
            "type":"Services"
        }
    ],
    "sg:phone":"+44 115 932 0911",
    "sg:postcode":"NG16 2SF",
    "sg:province":"Derbyshire",
    "sg:tags":[
        "demolition",
        "contractor"
    ],
    "wof:name":"Stansfield Group Ltd.",
    "wof:placetype":"venue"
},
  "geometry": {"coordinates":[-1.281036,52.975155],"type":"Point"}
}