{
  "type": "Feature",
  "properties": {
    "iso:country":"GB",
    "sg:address":"3-5 Lansdowne Road",
    "sg:city":"Croydon",
    "sg:classifiers":[
        {
            "category":"Professional",
            "subcategory":"Accounting & Tax Preparation",
            "type":"Services"
        }
    ],
    "sg:postcode":"CR0 2BX",
    "sg:province":"Surrey",
    "sg:tags":[
        "accountant"
    ],
    "wof:name":"S & P Financial Planners Ltd.",
    "wof:placetype":"venue"
},
  "geometry": {"coordinates":[-0.0934989974,51.3784599304],"type":"Point"}
}