{
  "type": "Feature",
  "properties": {
    "addr:full":"99 Hazelbourne Road London Greater London SW12 9NT",
    "addr:housenumber":"99",
    "addr:postcode":"sw12 9nt",
    "addr:street":"Hazelbourne Road",
    "iso:country":"GB",
    "sg:address":"99 Hazelbourne Road",
    "sg:city":"London",
    "sg:classifiers":[
        {
            "category":"Real Estate",
            "subcategory":"Real Estate Agent",
            "type":"Services"
        }
    ],
    "sg:postcode":"SW12 9NT",
    "sg:province":"Greater London",
    "wof:name":"Midshire Properties Limited",
    "wof:placetype":"venue"
},
  "geometry": {"coordinates":[-0.142482996,51.4511260986],"type":"Point"}
}