{
  "type": "Feature",
  "properties": {
    "iso:country":"GB",
    "sg:address":"38 Topsfield Parade, Tottenham Lane",
    "sg:city":"London",
    "sg:classifiers":[
        {
            "category":"Personal",
            "subcategory":"Beauty Salon",
            "type":"Services"
        }
    ],
    "sg:phone":"+44 20 8340 8930",
    "sg:postcode":"N8 8PT",
    "sg:province":"Greater London",
    "sg:tags":[
        "unisex",
        "hairdresser"
    ],
    "wof:name":"Pat Stasoulli",
    "wof:placetype":"venue"
},
  "geometry": {"coordinates":[-0.122362,51.580994],"type":"Point"}
}