{
  "type": "Feature",
  "properties": {
    "addr:full":"127 Dodworth Road Barnsley South Yorkshire S70 6HL",
    "addr:housenumber":"127",
    "addr:postcode":"s70 6hl",
    "addr:street":"Dodworth Road;Yorkshire",
    "iso:country":"GB",
    "sg:address":"127 Dodworth Road",
    "sg:city":"Barnsley",
    "sg:classifiers":[
        {
            "category":"Farming",
            "subcategory":"Nursery",
            "type":"Manufacturing & Wholesale Goods"
        }
    ],
    "sg:phone":"+44 1226 244878",
    "sg:postcode":"S70 6HL",
    "sg:province":"South Yorkshire",
    "sg:tags":[
        "creche"
    ],
    "wof:name":"White Rose Kindergarten",
    "wof:placetype":"venue"
},
  "geometry": {"coordinates":[-1.494549,53.552338],"type":"Point"}
}