{
  "type": "Feature",
  "properties": {
    "addr:full":"Womanby St Cardiff Cardiff CF1 2BR",
    "addr:postcode":"cf1 2br",
    "addr:street":"St",
    "iso:country":"GB",
    "sg:address":"Womanby St",
    "sg:city":"Cardiff",
    "sg:classifiers":[
        {
            "category":"Bars & Pubs",
            "type":"Food & Drink"
        }
    ],
    "sg:phone":"+44 29 2064 9881",
    "sg:postcode":"CF1 2BR",
    "sg:province":"Cardiff",
    "sg:tags":[
        "pubs",
        "inn"
    ],
    "wof:name":"Horse & Groom The",
    "wof:placetype":"venue"
},
  "geometry": {"coordinates":[-3.1815519333,51.4804344177],"type":"Point"}
}