{
  "type": "Feature",
  "properties": {
    "iso:country":"GB",
    "sg:address":"20 Tennyson Road",
    "sg:city":"Ashford",
    "sg:classifiers":[
        {
            "category":"Building & Trades",
            "subcategory":"Plumbing",
            "type":"Services"
        }
    ],
    "sg:postcode":"TW15 2LN",
    "sg:province":"Greater London",
    "sg:tags":[
        "heating"
    ],
    "wof:name":"J M Services",
    "wof:placetype":"venue"
},
  "geometry": {"coordinates":[-0.470362,51.430889],"type":"Point"}
}