{
  "type": "Feature",
  "properties": {
    "iso:country":"GB",
    "sg:address":"106 Cheylesmore Drive, Frimley",
    "sg:city":"Camberley",
    "sg:classifiers":[
        {
            "category":"Building & Trades",
            "subcategory":"Construction",
            "type":"Services"
        }
    ],
    "sg:postcode":"GU16 9BP",
    "sg:province":"Hampshire",
    "sg:tags":[
        "joinery",
        "joiner",
        "carpenter",
        "carpentry"
    ],
    "wof:name":"Paul Shorter",
    "wof:placetype":"venue"
},
  "geometry": {"coordinates":[-0.698611,51.322823],"type":"Point"}
}