{
  "type": "Feature",
  "properties": {
    "addr:full":"Bowling Mill Halifax West Yorkshire HX3 5WA",
    "addr:postcode":"hx3 5wa",
    "iso:country":"GB",
    "sg:address":"Bowling Mill",
    "sg:city":"Halifax",
    "sg:classifiers":[
        {
            "category":"Insurance",
            "subcategory":"Insurance Agent",
            "type":"Services"
        }
    ],
    "sg:phone":"+44 113 244 3188",
    "sg:postcode":"HX3 5WA",
    "sg:province":"West Yorkshire",
    "wof:name":"Sun Alliance Insurance Group",
    "wof:placetype":"venue"
},
  "geometry": {"coordinates":[-1.8681000471,53.7285194397],"type":"Point"}
}