{
  "type": "Feature",
  "properties": {
    "iso:country":"GB",
    "sg:address":"8 Pennine Drive",
    "sg:city":"Cricklewood",
    "sg:classifiers":[
        {
            "category":"Health Services",
            "subcategory":"Doctor",
            "type":"Services"
        }
    ],
    "sg:phone":"+44 20 8455 9977",
    "sg:postcode":"NW2 1PA",
    "sg:province":"Greater London",
    "sg:tags":[
        "practitioners"
    ],
    "wof:name":"Drs McCollum Rudge Jolles Frosh & Halsted",
    "wof:placetype":"venue"
},
  "geometry": {"coordinates":[-0.208998993,51.5681915283],"type":"Point"}
}