{
  "type": "Feature",
  "properties": {
    "addr:full":"Admin Office, 61 Frodsham St Chester Cheshire CH1 3JJ",
    "addr:housenumber":"61",
    "addr:postcode":"ch1 3jj",
    "addr:street":"St",
    "iso:country":"GB",
    "sg:address":"Admin Office, 61 Frodsham St",
    "sg:city":"Chester",
    "sg:classifiers":[
        {
            "category":"Recreation",
            "subcategory":"Campground",
            "type":"Entertainment"
        }
    ],
    "sg:phone":"+44 1244 351550",
    "sg:postcode":"CH1 3JJ",
    "sg:province":"Cheshire",
    "sg:tags":[
        "caravan",
        "park"
    ],
    "wof:name":"Haulfryn Estate Co Ltd",
    "wof:placetype":"venue"
},
  "geometry": {"coordinates":[-2.8943688869,53.188129425],"type":"Point"}
}