{
  "type": "Feature",
  "properties": {
    "addr:full":"Eagle Road, Morton, Swinderby Lincoln Lincolnshire LN6 9HT",
    "addr:postcode":"ln6 9ht",
    "addr:street":"Eagle Road",
    "iso:country":"GB",
    "sg:address":"Eagle Road, Morton, Swinderby",
    "sg:city":"Lincoln",
    "sg:classifiers":[
        {
            "category":"Building & Trades",
            "subcategory":"Landscaping Services",
            "type":"Services"
        }
    ],
    "sg:phone":"+44 1522 868816",
    "sg:postcode":"LN6 9HT",
    "sg:province":"Lincolnshire",
    "sg:tags":[
        "horticultural",
        "consultant"
    ],
    "wof:name":"C G Plant Sales",
    "wof:placetype":"venue"
},
  "geometry": {"coordinates":[-0.7031810284,53.198600769],"type":"Point"}
}