{
  "type": "Feature",
  "properties": {
    "addr:full":"Nedrabs, Pett Road, Pett Hastings East Sussex TN35 4HA",
    "addr:postcode":"tn35 4ha",
    "addr:street":"Pett Road",
    "iso:country":"GB",
    "sg:address":"Nedrabs, Pett Road, Pett",
    "sg:city":"Hastings",
    "sg:classifiers":[
        {
            "category":"Building & Trades",
            "subcategory":"Plumbing",
            "type":"Services"
        }
    ],
    "sg:phone":"+44 1424 812551",
    "sg:postcode":"TN35 4HA",
    "sg:province":"East Sussex",
    "sg:tags":[
        "heating"
    ],
    "wof:name":"R D  Barden",
    "wof:placetype":"venue"
},
  "geometry": {"coordinates":[0.6634899974,50.8948783875],"type":"Point"}
}