{
  "type": "Feature",
  "properties": {
    "iso:country":"GB",
    "sg:address":"47 St Johns Road, Boscombe",
    "sg:city":"Bournemouth",
    "sg:classifiers":[
        {
            "category":"Travel",
            "subcategory":"Hotels & Motels",
            "type":"Entertainment"
        }
    ],
    "sg:phone":"+44 1202 393134",
    "sg:postcode":"BH5 1AQ",
    "sg:province":"Dorset",
    "sg:tags":[
        "house",
        "guest"
    ],
    "wof:name":"Pine Lodge Guest House",
    "wof:placetype":"venue"
},
  "geometry": {"coordinates":[-1.843434,50.721817],"type":"Point"}
}