{
  "type": "Feature",
  "properties": {
    "iso:country":"GB",
    "sg:address":"2 Rock Cottage, Warrs Hill Road, North Chailey",
    "sg:city":"Lewes",
    "sg:classifiers":[
        {
            "category":"Utilities",
            "subcategory":"Fuel Oil & Lpg",
            "type":"Services"
        },
        {
            "category":"Building & Trades",
            "subcategory":"Construction",
            "type":"Services"
        }
    ],
    "sg:phone":"+44 1825 723176",
    "sg:postcode":"BN8 4JF",
    "sg:province":"East Sussex",
    "sg:tags":[
        "peat",
        "firewood",
        "joiner",
        "logs",
        "carpenter"
    ],
    "wof:name":"Stevenson Installers",
    "wof:placetype":"venue"
},
  "geometry": {"coordinates":[-0.018703,50.972286],"type":"Point"}
}