{
  "type": "Feature",
  "properties": {
    "addr:full":"46 Guildford Road Bagshot Berkshire GU19 5LE",
    "addr:housenumber":"46",
    "addr:postcode":"gu19 5le",
    "addr:street":"Guildford Road",
    "iso:country":"GB",
    "sg:address":"46 Guildford Road",
    "sg:city":"Bagshot",
    "sg:classifiers":[
        {
            "category":"Communications",
            "type":"Services"
        }
    ],
    "sg:postcode":"GU19 5LE",
    "sg:province":"Berkshire",
    "sg:tags":[
        "data",
        "network"
    ],
    "wof:name":"Visicom Data Ltd",
    "wof:placetype":"venue"
},
  "geometry": {"coordinates":[-0.6872640252,51.3605461121],"type":"Point"}
}