{
  "type": "Feature",
  "properties": {
    "iso:country":"GB",
    "sg:address":"3 School Road",
    "sg:city":"Sale",
    "sg:classifiers":[
        {
            "category":"Home & Garden",
            "subcategory":"Home Furnishings",
            "type":"Retail Goods"
        }
    ],
    "sg:phone":"+44 161 291 8561",
    "sg:postcode":"M33 7XY",
    "sg:province":"Cheshire",
    "sg:tags":[
        "blind",
        "manufacture",
        "fitting",
        "curtain"
    ],
    "wof:name":"Curtain Shop & Agency",
    "wof:placetype":"venue"
},
  "geometry": {"coordinates":[-2.319266,53.424549],"type":"Point"}
}