{
  "type": "Feature",
  "properties": {
    "iso:country":"GB",
    "sg:address":"North Hill, Horndon On The Hill",
    "sg:city":"Stanford-le-hope",
    "sg:classifiers":[
        {
            "category":"Wholesale",
            "subcategory":"Meat",
            "type":"Manufacturing & Wholesale Goods"
        }
    ],
    "sg:phone":"+44 1375 678050",
    "sg:postcode":"SS17 8QA",
    "sg:province":"Essex",
    "sg:tags":[
        "-"
    ],
    "wof:name":"Essex Poultry",
    "wof:placetype":"venue"
},
  "geometry": {"coordinates":[0.40201,51.526279],"type":"Point"}
}