{
  "type": "Feature",
  "properties": {
    "addr:full":"Glenmidge Smithy, Auldgirth Dumfries Dumfries and Galloway DG2 0SW",
    "addr:postcode":"dg2 0sw",
    "iso:country":"GB",
    "sg:address":"Glenmidge Smithy, Auldgirth",
    "sg:city":"Dumfries",
    "sg:classifiers":[
        {
            "category":"Professional",
            "subcategory":"Engineering",
            "type":"Services"
        }
    ],
    "sg:phone":"+44 1387 740328",
    "sg:postcode":"DG2 0SW",
    "sg:province":"Dumfries and Galloway",
    "sg:tags":[
        "agricultural",
        "engineer"
    ],
    "wof:name":"J A Steele",
    "wof:placetype":"venue"
},
  "geometry": {"coordinates":[-3.706328,55.153996],"type":"Point"}
}