{
  "type": "Feature",
  "properties": {
    "addr:full":"407 Hoylake Rd Wirral Merseyside CH46 6DQ",
    "addr:housenumber":"407",
    "addr:postcode":"ch46 6dq",
    "addr:street":"Hoylake Rd",
    "iso:country":"GB",
    "sg:address":"407 Hoylake Rd",
    "sg:city":"Wirral",
    "sg:classifiers":[
        {
            "category":"Bars & Pubs",
            "type":"Food & Drink"
        }
    ],
    "sg:phone":"+44 151 604 0193",
    "sg:postcode":"CH46 6DQ",
    "sg:province":"Merseyside",
    "sg:tags":[
        "pubs",
        "inn"
    ],
    "wof:name":"Grange The",
    "wof:placetype":"venue"
},
  "geometry": {"coordinates":[-3.122834,53.396858],"type":"Point"}
}