{
  "type": "Feature",
  "properties": {
    "iso:country":"GB",
    "sg:address":"2 Brackenwood Road, Hermitage Woods, St Johns",
    "sg:city":"Woking",
    "sg:classifiers":[
        {
            "category":"Professional",
            "subcategory":"Accounting & Tax Preparation",
            "type":"Services"
        }
    ],
    "sg:phone":"+44 1483 473954",
    "sg:postcode":"GU21 8XF",
    "sg:province":"Surrey",
    "sg:tags":[
        "accountant"
    ],
    "wof:name":"J & C Associates",
    "wof:placetype":"venue"
},
  "geometry": {"coordinates":[-0.6122689843,51.3096733093],"type":"Point"}
}