{
  "type": "Feature",
  "properties": {
    "addr:full":"Athlone Avenue Bury Lancashire BL9 5EE",
    "addr:postcode":"bl9 5ee",
    "addr:street":"Athlone Avenue",
    "iso:country":"GB",
    "sg:address":"Athlone Avenue",
    "sg:city":"Bury",
    "sg:classifiers":[
        {
            "category":"Education",
            "subcategory":"School",
            "type":"Public Place"
        },
        {
            "category":"Government",
            "subcategory":"Office",
            "type":"Public Place"
        }
    ],
    "sg:phone":"+44 161 764 5330",
    "sg:postcode":"BL9 5EE",
    "sg:province":"Lancashire",
    "sg:tags":[
        "local",
        "authority"
    ],
    "wof:name":"St John's C of E Primary School",
    "wof:placetype":"venue"
},
  "geometry": {"coordinates":[-2.295061,53.603275],"type":"Point"}
}