{
  "type": "Feature",
  "properties": {
    "iso:country":"GB",
    "sg:address":"18 Norfolk Rd",
    "sg:city":"Maidenhead",
    "sg:classifiers":[
        {
            "category":"Communications",
            "type":"Services"
        }
    ],
    "sg:postcode":"SL6 7AT",
    "sg:province":"Berkshire",
    "sg:tags":[
        "audio-visual"
    ],
    "wof:name":"Design Initatives",
    "wof:placetype":"venue"
},
  "geometry": {"coordinates":[-0.721908,51.526489],"type":"Point"}
}