{
  "type": "Feature",
  "properties": {
    "addr:full":"2 Tudor Parade, Jaywick Clacton-on-sea Essex CO15 2PL",
    "addr:housenumber":"2",
    "addr:postcode":"co15 2pl",
    "addr:street":"Tudor Parade",
    "iso:country":"GB",
    "sg:address":"2 Tudor Parade, Jaywick",
    "sg:city":"Clacton-on-sea",
    "sg:classifiers":[
        {
            "category":"Food & Beverages",
            "subcategory":"Meat & Fish",
            "type":"Retail Goods"
        }
    ],
    "sg:phone":"+44 1255 427749",
    "sg:postcode":"CO15 2PL",
    "sg:province":"Essex",
    "sg:tags":[
        "butcher"
    ],
    "wof:name":"Tudor Butchers",
    "wof:placetype":"venue"
},
  "geometry": {"coordinates":[1.1137700081,51.7821121216],"type":"Point"}
}