{
  "type": "Feature",
  "properties": {
    "addr:full":"14 Bridge St Haverfordwest Pembrokeshire SA61 2AD",
    "addr:housenumber":"14",
    "addr:postcode":"sa61 2ad",
    "addr:street":"Bridge St",
    "iso:country":"GB",
    "sg:address":"14 Bridge St",
    "sg:city":"Haverfordwest",
    "sg:classifiers":[
        {
            "category":"Shopping",
            "subcategory":"Clothing, Apparel, & Fashions",
            "type":"Retail Goods"
        }
    ],
    "sg:phone":"+44 1437 763564",
    "sg:postcode":"SA61 2AD",
    "sg:province":"Pembrokeshire",
    "sg:tags":[
        "shop"
    ],
    "wof:name":"Whicher,C H,(Milford Haven) Ltd",
    "wof:placetype":"venue"
},
  "geometry": {"coordinates":[-4.9688668251,51.8026809692],"type":"Point"}
}