{
  "type": "Feature",
  "properties": {
    "addr:full":"43 Queens Square Corby Northamptonshire NN17 1PD",
    "addr:housenumber":"43",
    "addr:postcode":"nn17 1pd",
    "addr:street":"Queens Square",
    "iso:country":"GB",
    "sg:address":"43 Queens Square",
    "sg:city":"Corby",
    "sg:classifiers":[
        {
            "category":"Food & Beverages",
            "subcategory":"Specialty",
            "type":"Retail Goods"
        }
    ],
    "sg:phone":"+44 1536 408914",
    "sg:postcode":"NN17 1PD",
    "sg:province":"Northamptonshire",
    "sg:tags":[
        "product",
        "health"
    ],
    "wof:name":"Holland & Barrett Retail Ltd.",
    "wof:placetype":"venue"
},
  "geometry": {"coordinates":[-0.7017490268,52.4871711731],"type":"Point"}
}