{
  "type": "Feature",
  "properties": {
    "addr:full":"7 Grayson Clo, Stocksbridge Sheffield South Yorkshire S36 2BJ",
    "addr:housenumber":"7",
    "addr:postcode":"s36 2bj",
    "addr:street":"Stocksbridge",
    "iso:country":"GB",
    "sg:address":"7 Grayson Clo, Stocksbridge",
    "sg:city":"Sheffield",
    "sg:classifiers":[
        {
            "category":"Social Services",
            "type":"Services"
        }
    ],
    "sg:postcode":"S36 2BJ",
    "sg:province":"South Yorkshire",
    "sg:tags":[
        "helplines"
    ],
    "wof:name":"Outreach for the Housebound Elderly & Di",
    "wof:placetype":"venue"
},
  "geometry": {"coordinates":[-1.5928100348,53.4770812988],"type":"Point"}
}