{
  "type": "Feature",
  "properties": {
    "addr:full":"Argill House, South Stainmore Kirkby Stephen Cumbria CA17 4DH",
    "addr:postcode":"ca17 4dh",
    "addr:street":"South Stainmore",
    "iso:country":"GB",
    "sg:address":"Argill House, South Stainmore",
    "sg:city":"Kirkby Stephen",
    "sg:classifiers":[
        {
            "category":"Farming",
            "subcategory":"Livestock Farm",
            "type":"Manufacturing & Wholesale Goods"
        }
    ],
    "sg:phone":"+44 17683 41417",
    "sg:postcode":"CA17 4DH",
    "sg:province":"Cumbria",
    "sg:tags":[
        "others"
    ],
    "wof:name":"A & M N Coulthard",
    "wof:placetype":"venue"
},
  "geometry": {"coordinates":[-2.352925,54.466953],"type":"Point"}
}