{
  "type": "Feature",
  "properties": {
    "addr:full":"9 Bodnant Grove, Connah's Quay Deeside Flintshire CH5 4NA",
    "addr:housenumber":"9",
    "addr:postcode":"ch5 4na",
    "addr:street":"Bodnant Grove;Quay",
    "iso:country":"GB",
    "sg:address":"9 Bodnant Grove, Connah's Quay",
    "sg:city":"Deeside",
    "sg:classifiers":[
        {
            "category":"Building & Trades",
            "subcategory":"Construction",
            "type":"Services"
        }
    ],
    "sg:phone":"+44 1244 810781",
    "sg:postcode":"CH5 4NA",
    "sg:province":"Flintshire",
    "sg:tags":[
        "glazier"
    ],
    "wof:name":"David Blackshaw",
    "wof:placetype":"venue"
},
  "geometry": {"coordinates":[-3.06916,53.211021],"type":"Point"}
}