{
  "type": "Feature",
  "properties": {
    "iso:country":"GB",
    "sg:address":"50 Carlton Road",
    "sg:city":"Walton-on-thames",
    "sg:classifiers":[
        {
            "category":"Building & Trades",
            "subcategory":"Plumbing",
            "type":"Services"
        }
    ],
    "sg:postcode":"KT12 2DG",
    "sg:province":"Surrey",
    "sg:tags":[
        "central",
        "installation",
        "system",
        "servicing",
        "heating"
    ],
    "wof:name":"RODNEY HARBOTTLE",
    "wof:placetype":"venue"
},
  "geometry": {"coordinates":[-0.407905,51.389568],"type":"Point"}
}