{
  "type": "Feature",
  "properties": {
    "iso:country":"GB",
    "sg:address":"Badgers End, Ouston Lane",
    "sg:city":"Tadcaster",
    "sg:classifiers":[
        {
            "category":"Shopping",
            "subcategory":"Stationery & Office Supplies",
            "type":"Retail Goods"
        }
    ],
    "sg:phone":"+44 1937 835053",
    "sg:postcode":"LS24 8DP",
    "sg:province":"North Yorkshire",
    "sg:tags":[
        "item",
        "promotional"
    ],
    "wof:name":"Partners in Design",
    "wof:placetype":"venue"
},
  "geometry": {"coordinates":[-1.266114,53.882275],"type":"Point"}
}