{
  "type": "Feature",
  "properties": {
    "iso:country":"GB",
    "sg:address":"15 Woking Rd",
    "sg:city":"Poole",
    "sg:classifiers":[
        {
            "category":"Building & Trades",
            "subcategory":"Cleaning & Sanitation",
            "type":"Services"
        }
    ],
    "sg:phone":"+44 1202 700560",
    "sg:postcode":"BH14 0BZ",
    "sg:province":"Dorset",
    "sg:tags":[
        "commercial"
    ],
    "wof:name":"Flat Maintenance Services",
    "wof:placetype":"venue"
},
  "geometry": {"coordinates":[-1.940815,50.727501],"type":"Point"}
}