{
  "type": "Feature",
  "properties": {
    "addr:full":"7-7a Uppingham Rd, Medbourne Leicester Leicestershire LE16 8ED",
    "addr:housenumber":"7-7a",
    "addr:postcode":"le16 8ed",
    "addr:street":"Uppingham Rd",
    "iso:country":"GB",
    "sg:address":"7-7a Uppingham Rd, Medbourne",
    "sg:city":"Leicester",
    "sg:classifiers":[
        {
            "category":"Shopping",
            "subcategory":"Catalog Store",
            "type":"Retail Goods"
        }
    ],
    "sg:postcode":"LE16 8ED",
    "sg:province":"Leicestershire",
    "sg:tags":[
        "mail",
        "order"
    ],
    "wof:name":"Excel Direct Ltd",
    "wof:placetype":"venue"
},
  "geometry": {"coordinates":[-0.8230289817,52.5285949707],"type":"Point"}
}