{
  "type": "Feature",
  "properties": {
    "iso:country":"GB",
    "sg:address":"Unit 1 The Acorn Centre, Barry Street",
    "sg:city":"Oldham",
    "sg:classifiers":[
        {
            "category":"Home & Garden",
            "subcategory":"Hardware",
            "type":"Retail Goods"
        }
    ],
    "sg:phone":"+44 161 652 2674",
    "sg:postcode":"OL1 3NE",
    "sg:province":"Lancashire",
    "wof:name":"Charles Green (Ironmongery) Ltd.",
    "wof:placetype":"venue"
},
  "geometry": {"coordinates":[-2.095757,53.547592],"type":"Point"}
}