{
  "type": "Feature",
  "properties": {
    "addr:full":"Pool End Farm, Leycett Newcastle Staffordshire ST5 6AN",
    "addr:postcode":"st5 6an",
    "addr:street":"Leycett",
    "iso:country":"GB",
    "sg:address":"Pool End Farm, Leycett",
    "sg:city":"Newcastle",
    "sg:classifiers":[
        {
            "category":"Farming",
            "subcategory":"Livestock Farm",
            "type":"Manufacturing & Wholesale Goods"
        }
    ],
    "sg:phone":"+44 1782 624399",
    "sg:postcode":"ST5 6AN",
    "sg:province":"Staffordshire",
    "sg:tags":[
        "others"
    ],
    "wof:name":"G & L J Fairbanks",
    "wof:placetype":"venue"
},
  "geometry": {"coordinates":[-2.3147358894,53.0152244568],"type":"Point"}
}