{
  "type": "Feature",
  "properties": {
    "addr:full":"5a High Street, Long Buckby Northampton Northamptonshire NN6 7RE",
    "addr:housenumber":"5a",
    "addr:postcode":"nn6 7re",
    "addr:street":"High Street",
    "iso:country":"GB",
    "sg:address":"5a High Street, Long Buckby",
    "sg:city":"Northampton",
    "sg:classifiers":[
        {
            "category":"Shopping",
            "subcategory":"Gifts & Souvenirs",
            "type":"Retail Goods"
        }
    ],
    "sg:phone":"+44 1327 843638",
    "sg:postcode":"NN6 7RE",
    "sg:province":"Northamptonshire",
    "sg:tags":[
        "shop"
    ],
    "wof:name":"Peep Hole Crafts & Gallery",
    "wof:placetype":"venue"
},
  "geometry": {"coordinates":[-1.136491,52.346451],"type":"Point"}
}