{
  "type": "Feature",
  "properties": {
    "addr:full":"East Glamorgan General Hospital Pontypridd Rhondda, Cynon, Taff CF38 1AB",
    "addr:postcode":"cf38 1ab",
    "addr:street":"East;Cynon Taff",
    "iso:country":"GB",
    "sg:address":"East Glamorgan General Hospital",
    "sg:city":"Pontypridd",
    "sg:classifiers":[
        {
            "category":"Health Services",
            "subcategory":"Medical Lab",
            "type":"Services"
        }
    ],
    "sg:phone":"+44 1443 207749",
    "sg:postcode":"CF38 1AB",
    "sg:province":"Rhondda, Cynon, Taff",
    "sg:tags":[
        "dental"
    ],
    "wof:name":"Area Dental Laboratory",
    "wof:placetype":"venue"
},
  "geometry": {"coordinates":[-3.3315799236,51.5656013489],"type":"Point"}
}