{
  "type": "Feature",
  "properties": {
    "iso:country":"GB",
    "sg:address":"Chester Rd, Tattenhall",
    "sg:city":"Chester",
    "sg:classifiers":[
        {
            "category":"Education",
            "subcategory":"School",
            "type":"Public Place"
        },
        {
            "category":"Government",
            "subcategory":"Office",
            "type":"Public Place"
        }
    ],
    "sg:phone":"+44 1829 770477",
    "sg:postcode":"CH3 9AH",
    "sg:province":"Cheshire",
    "sg:tags":[
        "local",
        "authority"
    ],
    "wof:name":"Cheshire County Council",
    "wof:placetype":"venue"
},
  "geometry": {"coordinates":[-2.772879,53.119156],"type":"Point"}
}