{
  "type": "Feature",
  "properties": {
    "addr:full":"103 Vicarage Farm Rd Hounslow Greater London TW3 4NN",
    "addr:housenumber":"103",
    "addr:postcode":"tw3 4nn",
    "addr:street":"Vicarage Farm Rd",
    "iso:country":"GB",
    "sg:address":"103 Vicarage Farm Rd",
    "sg:city":"Hounslow",
    "sg:classifiers":[
        {
            "category":"Professional",
            "subcategory":"Engineering",
            "type":"Services"
        }
    ],
    "sg:phone":"+44 20 8572 4320",
    "sg:postcode":"TW3 4NN",
    "sg:province":"Greater London",
    "sg:tags":[
        "gas",
        "engineer"
    ],
    "wof:name":"J L Plumbing",
    "wof:placetype":"venue"
},
  "geometry": {"coordinates":[-0.384223,51.476124],"type":"Point"}
}