{
  "type": "Feature",
  "properties": {
    "iso:country":"GB",
    "sg:address":"1 Station Rd, Landor",
    "sg:city":"Swansea",
    "sg:classifiers":[
        {
            "category":"Professional",
            "subcategory":"Engineering",
            "type":"Services"
        },
        {
            "category":"Shopping",
            "subcategory":"Computers & Home Electronics",
            "type":"Retail Goods"
        }
    ],
    "sg:phone":"+44 1792 654133",
    "sg:postcode":"SA1 2JE",
    "sg:province":"Neath Port Talbot",
    "sg:tags":[
        "sound",
        "equipment",
        "engineer",
        "acoustic"
    ],
    "wof:name":"Vaughan Sound Systems Ltd",
    "wof:placetype":"venue"
},
  "geometry": {"coordinates":[-3.938346,51.642826],"type":"Point"}
}