{
  "type": "Feature",
  "properties": {
    "addr:full":"8 Fountains Way, Bloxwich Walsall Staffordshire WS3 2RN",
    "addr:housenumber":"8",
    "addr:postcode":"ws3 2rn",
    "addr:street":"Fountains Way",
    "iso:country":"GB",
    "sg:address":"8 Fountains Way, Bloxwich",
    "sg:city":"Walsall",
    "sg:classifiers":[
        {
            "category":"Home & Garden",
            "subcategory":"Building Materials",
            "type":"Retail Goods"
        }
    ],
    "sg:phone":"+44 1922 408061",
    "sg:postcode":"WS3 2RN",
    "sg:province":"Staffordshire",
    "sg:tags":[
        "fencing"
    ],
    "wof:name":"Beaver Fencing",
    "wof:placetype":"venue"
},
  "geometry": {"coordinates":[-2.0233490467,52.6230506897],"type":"Point"}
}