{
  "type": "Feature",
  "properties": {
    "iso:country":"GB",
    "sg:address":"21-22 The Lanes, Wylde Grn",
    "sg:city":"Sutton Coldfield",
    "sg:classifiers":[
        {
            "category":"Home & Garden",
            "subcategory":"Carpets & Floor Coverings",
            "type":"Retail Goods"
        }
    ],
    "sg:phone":"+44 121 350 5339",
    "sg:postcode":"B72 1YG",
    "sg:province":"West Midlands",
    "sg:tags":[
        "carpets",
        "retailer",
        "rug",
        "matting"
    ],
    "wof:name":"Reachlord Ltd.",
    "wof:placetype":"venue"
},
  "geometry": {"coordinates":[-1.82757,52.537251],"type":"Point"}
}