{
  "type": "Feature",
  "properties": {
    "addr:full":"35 Sheen Park Richmond Greater London TW9 1UN",
    "addr:housenumber":"35",
    "addr:postcode":"tw9 1un",
    "addr:street":"Sheen Park",
    "iso:country":"GB",
    "sg:address":"35 Sheen Park",
    "sg:city":"Richmond",
    "sg:classifiers":[
        {
            "category":"Professional",
            "subcategory":"Management & Consulting",
            "type":"Services"
        }
    ],
    "sg:phone":"+44 20 8940 1006",
    "sg:postcode":"TW9 1UN",
    "sg:province":"Greater London",
    "sg:tags":[
        "consultant",
        "business"
    ],
    "wof:name":"R & E Associates Ltd.",
    "wof:placetype":"venue"
},
  "geometry": {"coordinates":[-0.295422,51.463306],"type":"Point"}
}