{
  "type": "Feature",
  "properties": {
    "addr:full":"Long St Thirsk North Yorkshire YO7 1AT",
    "addr:postcode":"yo7 1at",
    "addr:street":"Long St",
    "iso:country":"GB",
    "sg:address":"Long St",
    "sg:city":"Thirsk",
    "sg:classifiers":[
        {
            "category":"Retail",
            "subcategory":"Auto Repair",
            "type":"Services"
        }
    ],
    "sg:postcode":"YO7 1AT",
    "sg:province":"North Yorkshire",
    "sg:tags":[
        "modification",
        "garage"
    ],
    "wof:name":"Swales,Bryan,",
    "wof:placetype":"venue"
},
  "geometry": {"coordinates":[-1.340425,54.236473],"type":"Point"}
}