{
  "type": "Feature",
  "properties": {
    "addr:full":"3 Leigh St Bloomsbury Greater London WC1H 9EW",
    "addr:housenumber":"3",
    "addr:postcode":"wc1h 9ew",
    "addr:street":"Leigh St",
    "iso:country":"GB",
    "sg:address":"3 Leigh St",
    "sg:city":"Bloomsbury",
    "sg:classifiers":[
        {
            "category":"Utilities",
            "type":"Services"
        }
    ],
    "sg:phone":"+44 20 7387 3810",
    "sg:postcode":"WC1H 9EW",
    "sg:province":"Greater London",
    "sg:tags":[
        "internet"
    ],
    "wof:name":"Cybergate",
    "wof:placetype":"venue"
},
  "geometry": {"coordinates":[-0.12517,51.52644],"type":"Point"}
}