{
  "type": "Feature",
  "properties": {
    "addr:full":"Delapre Rd Weston Super Mare Somerset BS23 4NS",
    "addr:postcode":"bs23 4ns",
    "addr:street":"Delapre Rd",
    "iso:country":"GB",
    "sg:address":"Delapre Rd",
    "sg:city":"Weston Super Mare",
    "sg:classifiers":[
        {
            "category":"Professional",
            "subcategory":"Accounting & Tax Preparation",
            "type":"Services"
        }
    ],
    "sg:phone":"+44 1934 625541",
    "sg:postcode":"BS23 4NS",
    "sg:province":"Somerset",
    "sg:tags":[
        "accountant"
    ],
    "wof:name":"Delapre Accounting Services",
    "wof:placetype":"venue"
},
  "geometry": {"coordinates":[-2.977614,51.330315],"type":"Point"}
}