{
  "type": "Feature",
  "properties": {
    "addr:full":"Milton Court, Churchfield Road, Chalfont St Peter Gerrards Cross Buckinghamshire SL9 9EW",
    "addr:postcode":"sl9 9ew",
    "addr:street":"Milton Court Churchfield Road",
    "iso:country":"GB",
    "sg:address":"Milton Court, Churchfield Road, Chalfont St Peter",
    "sg:city":"Gerrards Cross",
    "sg:classifiers":[
        {
            "category":"Professional",
            "subcategory":"Testing Lab",
            "type":"Services"
        },
        {
            "category":"Retail",
            "subcategory":"Veterinary Services",
            "type":"Services"
        }
    ],
    "sg:phone":"+44 1753 891660",
    "sg:postcode":"SL9 9EW",
    "sg:province":"Buckinghamshire",
    "sg:tags":[
        "laboratory",
        "pharmacy"
    ],
    "wof:name":"Idexx Laboratories Ltd",
    "wof:placetype":"venue"
},
  "geometry": {"coordinates":[-0.5576589704,51.6074028015],"type":"Point"}
}