{
  "type": "Feature",
  "properties": {
    "iso:country":"GB",
    "sg:address":"70 Crouch Hall Road",
    "sg:city":"London",
    "sg:classifiers":[
        {
            "category":"Health Services",
            "subcategory":"Dentist",
            "type":"Services"
        }
    ],
    "sg:phone":"+44 20 8340 1453",
    "sg:postcode":"N8 8HA",
    "sg:province":"Greater London",
    "wof:name":"Crouch End Dental Surgery",
    "wof:placetype":"venue"
},
  "geometry": {"coordinates":[-0.124332,51.579792],"type":"Point"}
}