{
  "type": "Feature",
  "properties": {
    "addr:full":"Orchard Cottage, Sebergham Carlisle Cumbria CA5 7HR",
    "addr:postcode":"ca5 7hr",
    "iso:country":"GB",
    "sg:address":"Orchard Cottage, Sebergham",
    "sg:city":"Carlisle",
    "sg:classifiers":[
        {
            "category":"Communications",
            "type":"Services"
        }
    ],
    "sg:postcode":"CA5 7HR",
    "sg:province":"Cumbria",
    "sg:tags":[
        "audio-visual"
    ],
    "wof:name":"Short,Laurence,",
    "wof:placetype":"venue"
},
  "geometry": {"coordinates":[-3.000906,54.767574],"type":"Point"}
}