{
  "type": "Feature",
  "properties": {
    "iso:country":"GB",
    "sg:address":"44t Sandwich Indust Est",
    "sg:city":"Sandwich",
    "sg:classifiers":[
        {
            "category":"Retail",
            "subcategory":"Auto Repair",
            "type":"Services"
        }
    ],
    "sg:phone":"+44 1304 620433",
    "sg:postcode":"CT13 9LR",
    "sg:province":"Kent",
    "sg:tags":[
        "body",
        "car"
    ],
    "wof:name":"J F Horton",
    "wof:placetype":"venue"
},
  "geometry": {"coordinates":[1.3423039913,51.2761688232],"type":"Point"}
}