{
  "type": "Feature",
  "properties": {
    "addr:full":"Falgate Corner, Sandy Lane Fakenham Norfolk NR21 9ES",
    "addr:postcode":"nr21 9es",
    "addr:street":"Falgate;Sandy Lane",
    "iso:country":"GB",
    "sg:address":"Falgate Corner, Sandy Lane",
    "sg:city":"Fakenham",
    "sg:classifiers":[
        {
            "category":"Building & Trades",
            "subcategory":"Construction",
            "type":"Services"
        }
    ],
    "sg:phone":"+44 1328 864985",
    "sg:postcode":"NR21 9ES",
    "sg:province":"Norfolk",
    "sg:tags":[
        "builder"
    ],
    "wof:name":"Mann Builders (Fakenham) Ltd.",
    "wof:placetype":"venue"
},
  "geometry": {"coordinates":[0.850265,52.834694],"type":"Point"}
}