{
  "type": "Feature",
  "properties": {
    "addr:full":"12 Benezet Street Ipswich Suffolk IP1 2JQ",
    "addr:housenumber":"12",
    "addr:postcode":"ip1 2jq",
    "addr:street":"Benezet Street",
    "iso:country":"GB",
    "sg:address":"12 Benezet Street",
    "sg:city":"Ipswich",
    "sg:classifiers":[
        {
            "category":"Real Estate",
            "subcategory":"Real Estate Services",
            "type":"Services"
        },
        {
            "category":"Real Estate",
            "subcategory":"Real Estate Agent",
            "type":"Services"
        }
    ],
    "sg:phone":"+44 1473 213718",
    "sg:postcode":"IP1 2JQ",
    "sg:province":"Suffolk",
    "sg:tags":[
        "management"
    ],
    "wof:name":"Aldwych Investments Ltd",
    "wof:placetype":"venue"
},
  "geometry": {"coordinates":[1.142686,52.060986],"type":"Point"}
}