{
  "type": "Feature",
  "properties": {
    "iso:country":"GB",
    "sg:address":"22 Stafford Street, Eccleshall",
    "sg:city":"Stafford",
    "sg:classifiers":[
        {
            "category":"Fast Food",
            "type":"Food & Drink"
        }
    ],
    "sg:phone":"+44 1785 851459",
    "sg:postcode":"ST21 6BH",
    "sg:province":"Staffordshire",
    "sg:tags":[
        "away",
        "take"
    ],
    "wof:name":"Great Wall",
    "wof:placetype":"venue"
},
  "geometry": {"coordinates":[-2.251599,52.858921],"type":"Point"}
}