{
  "type": "Feature",
  "properties": {
    "iso:country":"GB",
    "sg:address":"37 Spenser Road",
    "sg:city":"Herne Bay",
    "sg:classifiers":[
        {
            "category":"Health Services",
            "subcategory":"Nursing And Care Facility",
            "type":"Services"
        },
        {
            "category":"Social Services",
            "subcategory":"Retirement Home",
            "type":"Services"
        }
    ],
    "sg:phone":"+44 1227 741114",
    "sg:postcode":"CT6 5QP",
    "sg:province":"Kent",
    "sg:tags":[
        "residential"
    ],
    "wof:name":"Family Care Homes Ltd.",
    "wof:placetype":"venue"
},
  "geometry": {"coordinates":[1.126883,51.366123],"type":"Point"}
}