{
  "type": "Feature",
  "properties": {
    "addr:full":"Gray Street Workington Cumbria CA14 2NQ",
    "addr:postcode":"ca14 2nq",
    "addr:street":"Gray Street",
    "iso:country":"GB",
    "sg:address":"Gray Street",
    "sg:city":"Workington",
    "sg:classifiers":[
        {
            "category":"Retail",
            "subcategory":"Veterinary Services",
            "type":"Services"
        }
    ],
    "sg:phone":"+44 1900 602138",
    "sg:postcode":"CA14 2NQ",
    "sg:province":"Cumbria",
    "sg:tags":[
        "surgeon",
        "activity"
    ],
    "wof:name":"GALE MYER VETERINARY HOSPITAL",
    "wof:placetype":"venue"
},
  "geometry": {"coordinates":[-3.5483579636,54.6422767639],"type":"Point"}
}