{
  "type": "Feature",
  "properties": {
    "addr:full":"9 Lorne Street Middlesbrough North Yorkshire TS1 5QY",
    "addr:housenumber":"9",
    "addr:postcode":"ts1 5qy",
    "addr:street":"Lorne Street",
    "iso:country":"GB",
    "sg:address":"9 Lorne Street",
    "sg:city":"Middlesbrough",
    "sg:classifiers":[
        {
            "category":"Building & Trades",
            "subcategory":"Construction",
            "type":"Services"
        },
        {
            "category":"Organizations",
            "subcategory":"Non-profit Organization",
            "type":"Services"
        }
    ],
    "sg:phone":"+44 1642 211195",
    "sg:postcode":"TS1 5QY",
    "sg:province":"North Yorkshire",
    "sg:tags":[
        "organisation",
        "decorator",
        "voluntary",
        "painter",
        "charity"
    ],
    "wof:name":"Dunningham Decorators Ltd.",
    "wof:placetype":"venue"
},
  "geometry": {"coordinates":[-1.250426,54.570492],"type":"Point"}
}