{
  "type": "Feature",
  "properties": {
    "addr:full":"272-274 High Street Sutton Surrey SM1 1PJ",
    "addr:housenumber":"272-274",
    "addr:postcode":"sm1 1pj",
    "addr:street":"High Street",
    "iso:country":"GB",
    "sg:address":"272-274 High Street",
    "sg:city":"Sutton",
    "sg:classifiers":[
        {
            "category":"Manufacturing",
            "subcategory":"Lumber",
            "type":"Manufacturing & Wholesale Goods"
        }
    ],
    "sg:phone":"+44 20 8642 8291",
    "sg:postcode":"SM1 1PJ",
    "sg:province":"Surrey",
    "sg:tags":[
        "importer",
        "merchants",
        "agent",
        "timber"
    ],
    "wof:name":"A W Champion (Sutton) Ltd.",
    "wof:placetype":"venue"
},
  "geometry": {"coordinates":[-0.1950950027,51.3682441711],"type":"Point"}
}