{
  "type": "Feature",
  "properties": {
    "addr:full":"59 Oak Gro Cricklewood Greater London NW2 3LS",
    "addr:housenumber":"59",
    "addr:postcode":"nw2 3ls",
    "addr:street":"Oak Gro",
    "iso:country":"GB",
    "sg:address":"59 Oak Gro",
    "sg:city":"Cricklewood",
    "sg:classifiers":[
        {
            "category":"Organizations",
            "subcategory":"Community Association",
            "type":"Services"
        }
    ],
    "sg:phone":"+44 20 8450 1455",
    "sg:postcode":"NW2 3LS",
    "sg:province":"Greater London",
    "sg:tags":[
        "relation",
        "public"
    ],
    "wof:name":"33 RPM",
    "wof:placetype":"venue"
},
  "geometry": {"coordinates":[-0.2115949988,51.5534439087],"type":"Point"}
}