{
  "type": "Feature",
  "properties": {
    "addr:full":"116 Tong Street Bradford West Yorkshire BD4 6HD",
    "addr:housenumber":"116",
    "addr:postcode":"bd4 6hd",
    "addr:street":"Tong Street",
    "iso:country":"GB",
    "sg:address":"116 Tong Street",
    "sg:city":"Bradford",
    "sg:classifiers":[
        {
            "category":"Personal",
            "subcategory":"Beauty Salon",
            "type":"Services"
        },
        {
            "category":"Personal",
            "subcategory":"Barber",
            "type":"Services"
        }
    ],
    "sg:phone":"+44 1274 770120",
    "sg:postcode":"BD4 6HD",
    "sg:province":"West Yorkshire",
    "sg:tags":[
        "unisex",
        "hairdresser"
    ],
    "wof:name":"Toppers Hairdressers",
    "wof:placetype":"venue"
},
  "geometry": {"coordinates":[-1.721248,53.771435],"type":"Point"}
}