{
  "type": "Feature",
  "properties": {
    "iso:country":"GB",
    "sg:address":"34 Mortimer Avenue",
    "sg:city":"Batley",
    "sg:classifiers":[
        {
            "category":"Building & Trades",
            "subcategory":"Construction",
            "type":"Services"
        }
    ],
    "sg:postcode":"WF17 8BU",
    "sg:province":"West Yorkshire",
    "sg:tags":[
        "decorator",
        "painter"
    ],
    "wof:name":"David Lloyd",
    "wof:placetype":"venue"
},
  "geometry": {"coordinates":[-1.6553900242,53.7139472961],"type":"Point"}
}