{
  "type": "Feature",
  "properties": {
    "addr:full":"5 Avenell Mansions, Avenell Road London Greater London N5 1BN",
    "addr:housenumber":"5",
    "addr:postcode":"n5 1bn",
    "addr:street":"Avenell Road",
    "iso:country":"GB",
    "sg:address":"5 Avenell Mansions, Avenell Road",
    "sg:city":"London",
    "sg:classifiers":[
        {
            "category":"Communications",
            "type":"Services"
        }
    ],
    "sg:postcode":"N5 1BN",
    "sg:province":"Greater London",
    "sg:tags":[
        "data",
        "network"
    ],
    "wof:name":"Yes Data Systems Ltd",
    "wof:placetype":"venue"
},
  "geometry": {"coordinates":[-0.10106,51.556911],"type":"Point"}
}