{
  "type": "Feature",
  "properties": {
    "iso:country":"GB",
    "sg:address":"123a Berkeley Avenue",
    "sg:city":"Chesham",
    "sg:classifiers":[
        {
            "category":"Professional",
            "subcategory":"Accounting & Tax Preparation",
            "type":"Services"
        }
    ],
    "sg:phone":"+44 1494 783008",
    "sg:postcode":"HP5 2RT",
    "sg:province":"Buckinghamshire",
    "sg:tags":[
        "accountant"
    ],
    "wof:name":"Mandy Pritchard",
    "wof:placetype":"venue"
},
  "geometry": {"coordinates":[-0.631267,51.717827],"type":"Point"}
}