{
  "type": "Feature",
  "properties": {
    "addr:full":"45 Spon End Coventry West Midlands CV1 3HE",
    "addr:housenumber":"45",
    "addr:postcode":"cv1 3he",
    "addr:street":"Spon",
    "iso:country":"GB",
    "sg:address":"45 Spon End",
    "sg:city":"Coventry",
    "sg:classifiers":[
        {
            "category":"Cafe",
            "type":"Food & Drink"
        }
    ],
    "sg:phone":"+44 247676900",
    "sg:postcode":"CV1 3HE",
    "sg:province":"West Midlands",
    "sg:tags":[
        "tea",
        "room"
    ],
    "wof:name":"Mittens Munchies",
    "wof:placetype":"venue"
},
  "geometry": {"coordinates":[-1.527359,52.408409],"type":"Point"}
}