{
  "type": "Feature",
  "properties": {
    "addr:full":"2-4 Bluebell Avenue Peterborough Cambridgeshire PE1 3XG",
    "addr:housenumber":"2-4",
    "addr:postcode":"pe1 3xg",
    "addr:street":"Bluebell Avenue",
    "iso:country":"GB",
    "sg:address":"2-4 Bluebell Avenue",
    "sg:city":"Peterborough",
    "sg:classifiers":[
        {
            "category":"Shopping",
            "subcategory":"News",
            "type":"Retail Goods"
        }
    ],
    "sg:phone":"+44 1733 567933",
    "sg:postcode":"PE1 3XG",
    "sg:province":"Cambridgeshire",
    "sg:tags":[
        "newsagent"
    ],
    "wof:name":"Hitchborn",
    "wof:placetype":"venue"
},
  "geometry": {"coordinates":[-0.2363429964,52.599609375],"type":"Point"}
}