{
  "type": "Feature",
  "properties": {
    "addr:full":"4 Hermitage La Windsor Berkshire SL4 4AZ",
    "addr:housenumber":"4",
    "addr:postcode":"sl4 4az",
    "addr:street":"Hermitage La Windsor",
    "iso:country":"GB",
    "sg:address":"4 Hermitage La",
    "sg:city":"Windsor",
    "sg:classifiers":[
        {
            "category":"Professional",
            "subcategory":"Art Services",
            "type":"Services"
        }
    ],
    "sg:postcode":"SL4 4AZ",
    "sg:province":"Berkshire",
    "sg:tags":[
        "consultant",
        "design"
    ],
    "wof:name":"Abil Partnership (The)",
    "wof:placetype":"venue"
},
  "geometry": {"coordinates":[-0.628681004,51.470615387],"type":"Point"}
}