{
  "type": "Feature",
  "properties": {
    "addr:full":"41a Espedair Street Paisley East Renfrewshire PA2 6NU",
    "addr:housenumber":"41a",
    "addr:postcode":"pa2 6nu",
    "addr:street":"Espedair Street",
    "iso:country":"GB",
    "sg:address":"41a Espedair Street",
    "sg:city":"Paisley",
    "sg:classifiers":[
        {
            "category":"Building & Trades",
            "subcategory":"Landscaping Services",
            "type":"Services"
        }
    ],
    "sg:postcode":"PA2 6NU",
    "sg:province":"East Renfrewshire",
    "sg:tags":[
        "gardening"
    ],
    "wof:name":"TIDY GARDENS",
    "wof:placetype":"venue"
},
  "geometry": {"coordinates":[-4.422133,55.83672],"type":"Point"}
}