{
  "type": "Feature",
  "properties": {
    "iso:country":"GB",
    "sg:address":"73 High Street",
    "sg:city":"Wimborne",
    "sg:classifiers":[
        {
            "category":"Personal",
            "subcategory":"Beauty Salon",
            "type":"Services"
        }
    ],
    "sg:phone":"+44 1202 841060",
    "sg:postcode":"BH21 1HS",
    "sg:province":"Dorset",
    "sg:tags":[
        "unisex",
        "hairdresser"
    ],
    "wof:name":"Cutters",
    "wof:placetype":"venue"
},
  "geometry": {"coordinates":[-1.9868559837,50.7988471985],"type":"Point"}
}