{
  "type": "Feature",
  "properties": {
    "addr:full":"122-124 West Street Boston Lincolnshire PE21 8QZ",
    "addr:housenumber":"122-124",
    "addr:postcode":"pe21 8qz",
    "addr:street":"West Street",
    "iso:country":"GB",
    "sg:address":"122-124 West Street",
    "sg:city":"Boston",
    "sg:classifiers":[
        {
            "category":"Shopping",
            "subcategory":"Bicycles & Sporting Goods",
            "type":"Retail Goods"
        }
    ],
    "sg:phone":"+44 1205 355325",
    "sg:postcode":"PE21 8QZ",
    "sg:province":"Lincolnshire",
    "sg:tags":[
        "cycle",
        "accessory"
    ],
    "wof:name":"Don White",
    "wof:placetype":"venue"
},
  "geometry": {"coordinates":[-0.0296459999,52.9761009216],"type":"Point"}
}