{
  "type": "Feature",
  "properties": {
    "iso:country":"GB",
    "sg:address":"47 High Street",
    "sg:city":"Sheerness",
    "sg:classifiers":[
        {
            "category":"Shopping",
            "subcategory":"Florist",
            "type":"Retail Goods"
        }
    ],
    "sg:postcode":"ME12 1NX",
    "sg:province":"Kent",
    "wof:name":"Rebecca Cripps Florists",
    "wof:placetype":"venue"
},
  "geometry": {"coordinates":[0.760592,51.440479],"type":"Point"}
}