{
  "type": "Feature",
  "properties": {
    "addr:full":"66 Abbey Road Torquay Devon TQ2 5NH",
    "addr:housenumber":"66",
    "addr:postcode":"tq2 5nh",
    "addr:street":"Abbey Road",
    "iso:country":"GB",
    "sg:address":"66 Abbey Road",
    "sg:city":"Torquay",
    "sg:classifiers":[
        {
            "category":"Health Services",
            "subcategory":"Podiatrist",
            "type":"Services"
        }
    ],
    "sg:postcode":"TQ2 5NH",
    "sg:province":"Devon",
    "sg:tags":[
        "podiatrists",
        "chiropodist"
    ],
    "wof:name":"Abbey Road Podiatry/Chiropody Practice",
    "wof:placetype":"venue"
},
  "geometry": {"coordinates":[-3.531054,50.46587],"type":"Point"}
}