{
  "type": "Feature",
  "properties": {
    "addr:full":"Top Floor Moreton House Farnham Hampshire GU10 2JA",
    "addr:housenumber":"farnham",
    "addr:postcode":"gu10 2ja",
    "addr:street":"Hampshire",
    "iso:country":"GB",
    "sg:address":"Top Floor Moreton House",
    "sg:city":"Farnham",
    "sg:classifiers":[
        {
            "category":"Conference Center",
            "type":"Public Place"
        }
    ],
    "sg:postcode":"GU10 2JA",
    "sg:province":"Hampshire",
    "wof:name":"Akela Communications Ltd.",
    "wof:placetype":"venue"
},
  "geometry": {"coordinates":[-0.7570689917,51.1565284729],"type":"Point"}
}