{
  "type": "Feature",
  "properties": {
    "iso:country":"GB",
    "sg:address":"Top Floor Moreton House",
    "sg:city":"Farnham",
    "sg:classifiers":[
        {
            "category":"Conference Center",
            "type":"Public Place"
        }
    ],
    "sg:postcode":"GU10 2JA",
    "sg:province":"Hampshire",
    "wof:name":"Akela Communications Ltd.",
    "wof:placetype":"venue"
},
  "geometry": {"coordinates":[-0.7570689917,51.1565284729],"type":"Point"}
}