{
  "type": "Feature",
  "properties": {
    "iso:country":"GB",
    "sg:address":"66 Green Lane, Clanfield",
    "sg:city":"Waterlooville",
    "sg:classifiers":[
        {
            "category":"Professional",
            "subcategory":"Computer Services",
            "type":"Services"
        }
    ],
    "sg:phone":"+44 23 9259 2951",
    "sg:postcode":"PO8 0JX",
    "sg:province":"Hampshire",
    "sg:tags":[
        "consultant"
    ],
    "wof:name":"Itb Ltd.",
    "wof:placetype":"venue"
},
  "geometry": {"coordinates":[-0.997919,50.939857],"type":"Point"}
}