{
  "type": "Feature",
  "properties": {
    "addr:full":"15 Greenbank Close, Chingford London Greater London E4 6TT",
    "addr:housenumber":"15",
    "addr:postcode":"e4 6tt",
    "addr:street":"Greenbank Close",
    "iso:country":"GB",
    "sg:address":"15 Greenbank Close, Chingford",
    "sg:city":"London",
    "sg:classifiers":[
        {
            "category":"Building & Trades",
            "subcategory":"Construction",
            "type":"Services"
        }
    ],
    "sg:postcode":"E4 6TT",
    "sg:province":"Greater London",
    "sg:tags":[
        "builder"
    ],
    "wof:name":"R Weal & Son",
    "wof:placetype":"venue"
},
  "geometry": {"coordinates":[-0.006101,51.626797],"type":"Point"}
}