{
  "type": "Feature",
  "properties": {
    "iso:country":"GB",
    "sg:address":"50 East Dulwich Road",
    "sg:city":"London",
    "sg:classifiers":[
        {
            "category":"Government",
            "subcategory":"Post Office",
            "type":"Public Place"
        }
    ],
    "sg:phone":"+44 20 7639 9425",
    "sg:postcode":"SE22 9AX",
    "sg:province":"Greater London",
    "wof:name":"East Dulwich Road Post Office",
    "wof:placetype":"venue"
},
  "geometry": {"coordinates":[-0.0699319988,51.4618339539],"type":"Point"}
}