{
  "type": "Feature",
  "properties": {
    "iso:country":"GB",
    "sg:address":"67 Charlotte Street",
    "sg:city":"Aberdeen",
    "sg:classifiers":[
        {
            "category":"Transit Center",
            "subcategory":"Freight",
            "type":"Transportation"
        }
    ],
    "sg:phone":"+44 1224 640987",
    "sg:postcode":"AB25 1LU",
    "sg:province":"Aberdeen City",
    "sg:tags":[
        "shop",
        "craft",
        "centre"
    ],
    "wof:name":"Royston Ceramics",
    "wof:placetype":"venue"
},
  "geometry": {"coordinates":[-2.10529,57.151535],"type":"Point"}
}