{
  "type": "Feature",
  "properties": {
    "iso:country":"GB",
    "sg:address":"16 Leicester Square",
    "sg:city":"London",
    "sg:classifiers":[
        {
            "category":"Education",
            "subcategory":"Special Training",
            "type":"Public Place"
        }
    ],
    "sg:phone":"+44 20 7437 8339",
    "sg:postcode":"WC2H 7NH",
    "sg:province":"Greater London",
    "sg:tags":[
        "school",
        "language"
    ],
    "wof:name":"The French Centre",
    "wof:placetype":"venue"
},
  "geometry": {"coordinates":[-0.129637,51.510841],"type":"Point"}
}