{
  "type": "Feature",
  "properties": {
    "iso:country":"GB",
    "sg:address":"73 Manor Road",
    "sg:city":"Brackley",
    "sg:classifiers":[
        {
            "category":"Manufacturing",
            "subcategory":"Signs",
            "type":"Manufacturing & Wholesale Goods"
        }
    ],
    "sg:postcode":"NN13 6ED",
    "sg:province":"Buckinghamshire",
    "sg:tags":[
        "marquee"
    ],
    "wof:name":"A C S Window Treatments",
    "wof:placetype":"venue"
},
  "geometry": {"coordinates":[-1.146741,52.032581],"type":"Point"}
}