{
  "type": "Feature",
  "properties": {
    "addr:full":"Pans Cottage, Shepherds Walk, Chestfield Whitstable Kent CT5 3NB",
    "addr:postcode":"ct5 3nb",
    "addr:street":"Shepherds Walk;Whitstable",
    "iso:country":"GB",
    "sg:address":"Pans Cottage, Shepherds Walk, Chestfield",
    "sg:city":"Whitstable",
    "sg:classifiers":[
        {
            "category":"Retail",
            "subcategory":"Laundry & Dry Cleaning",
            "type":"Services"
        }
    ],
    "sg:phone":"+44 1227 792817",
    "sg:postcode":"CT5 3NB",
    "sg:province":"Kent",
    "sg:tags":[
        "home",
        "ironing"
    ],
    "wof:name":"The Iron Maidens",
    "wof:placetype":"venue"
},
  "geometry": {"coordinates":[1.0642819405,51.3547019958],"type":"Point"}
}