{
  "type": "Feature",
  "properties": {
    "iso:country":"GB",
    "sg:address":"31 Liddle Close",
    "sg:city":"Carlisle",
    "sg:classifiers":[
        {
            "category":"Food & Beverages",
            "subcategory":"Liquor & Beverages",
            "type":"Retail Goods"
        }
    ],
    "sg:phone":"+44 1228 525011",
    "sg:postcode":"CA3 0DS",
    "sg:province":"Cumbria",
    "sg:tags":[
        "drink",
        "soft"
    ],
    "wof:name":"Underwoods & McMichaels Soft Drinks",
    "wof:placetype":"venue"
},
  "geometry": {"coordinates":[-2.950698,54.91927],"type":"Point"}
}