{
  "type": "Feature",
  "properties": {
    "iso:country":"GB",
    "sg:address":"1 Mill Street",
    "sg:city":"Whitchurch",
    "sg:classifiers":[
        {
            "category":"Shopping",
            "subcategory":"Department Store",
            "type":"Retail Goods"
        }
    ],
    "sg:phone":"+44 1948 665353",
    "sg:postcode":"SY13 1SE",
    "sg:province":"Cheshire",
    "wof:name":"Housemakers",
    "wof:placetype":"venue"
},
  "geometry": {"coordinates":[-2.684177,52.968292],"type":"Point"}
}