{
  "type": "Feature",
  "properties": {
    "iso:country":"GB",
    "sg:address":"Poyner Road",
    "sg:city":"Ludlow",
    "sg:classifiers":[
        {
            "category":"Social Services",
            "subcategory":"Retirement Home",
            "type":"Services"
        }
    ],
    "sg:phone":"+44 1584 872412",
    "sg:postcode":"SY8 1QT",
    "sg:province":"Herefordshire",
    "sg:tags":[
        "rest"
    ],
    "wof:name":"Alexandra House",
    "wof:placetype":"venue"
},
  "geometry": {"coordinates":[-2.711777,52.372318],"type":"Point"}
}