{
  "type": "Feature",
  "properties": {
    "addr:full":"Unit 5 Scotshaw Brook Industrial Estate, Branch Road, Lower Darwen Darwen Lancashire BB3 0PR",
    "addr:housenumber":"unit 5",
    "addr:postcode":"bb3 0pr",
    "addr:street":"Scotshaw Brook Industrial Estate Branch Road",
    "iso:country":"GB",
    "sg:address":"Unit 5 Scotshaw Brook Industrial Estate, Branch Road, Lower Darwen",
    "sg:city":"Darwen",
    "sg:classifiers":[
        {
            "category":"Wholesale",
            "subcategory":"Machinery & Supplies",
            "type":"Manufacturing & Wholesale Goods"
        }
    ],
    "sg:postcode":"BB3 0PR",
    "sg:province":"Lancashire",
    "sg:tags":[
        "industrial",
        "commercial"
    ],
    "wof:name":"Converting Solutions Ltd.",
    "wof:placetype":"venue"
},
  "geometry": {"coordinates":[-2.47119,53.722862],"type":"Point"}
}