{
  "type": "Feature",
  "properties": {
    "addr:full":"1 Uxbridge Rd Kingston-upon-thames Greater London KT1 2LH",
    "addr:housenumber":"1",
    "addr:postcode":"kt1 2lh",
    "addr:street":"Uxbridge Rd",
    "iso:country":"GB",
    "sg:address":"1 Uxbridge Rd",
    "sg:city":"Kingston-upon-thames",
    "sg:classifiers":[
        {
            "category":"Travel",
            "subcategory":"Hotels & Motels",
            "type":"Entertainment"
        }
    ],
    "sg:postcode":"KT1 2LH",
    "sg:province":"Greater London",
    "sg:tags":[
        "house",
        "guest"
    ],
    "wof:name":"Ford,Harry,",
    "wof:placetype":"venue"
},
  "geometry": {"coordinates":[-0.3044559956,51.3982315063],"type":"Point"}
}