{
  "type": "Feature",
  "properties": {
    "iso:country":"GB",
    "sg:address":"24 Belgravia Road",
    "sg:city":"Wakefield",
    "sg:classifiers":[
        {
            "category":"Real Estate",
            "subcategory":"Architect",
            "type":"Services"
        }
    ],
    "sg:phone":"+44 1629 650859",
    "sg:postcode":"WF1 3JP",
    "sg:province":"West Yorkshire",
    "sg:tags":[
        "architectural"
    ],
    "wof:name":"Robinson Associates Stone Consultants Ltd.",
    "wof:placetype":"venue"
},
  "geometry": {"coordinates":[-1.504243,53.689629],"type":"Point"}
}