{
  "type": "Feature",
  "properties": {
    "iso:country":"GB",
    "sg:address":"2 Stanley Avenue, Bishopston",
    "sg:city":"Bristol",
    "sg:classifiers":[
        {
            "category":"Food & Beverages",
            "subcategory":"Liquor & Beverages",
            "type":"Retail Goods"
        }
    ],
    "sg:phone":"+44 117 940 1206",
    "sg:postcode":"BS7 9AH",
    "sg:province":"City of Bristol",
    "sg:tags":[
        "beer",
        "spirit",
        "wines"
    ],
    "wof:name":"Stanley Food & Wine Store",
    "wof:placetype":"venue"
},
  "geometry": {"coordinates":[-2.586715,51.474777],"type":"Point"}
}