{
  "type": "Feature",
  "properties": {
    "iso:country":"GB",
    "sg:address":"108 The Rock",
    "sg:city":"Bury",
    "sg:classifiers":[
        {
            "category":"Shopping",
            "subcategory":"Clothing, Apparel, & Fashions",
            "type":"Retail Goods"
        }
    ],
    "sg:postcode":"BL9 0PJ",
    "sg:province":"Lancashire",
    "sg:tags":[
        "workwear",
        "protective"
    ],
    "wof:name":"Bond,Derek,",
    "wof:placetype":"venue"
},
  "geometry": {"coordinates":[-2.293309,53.595039],"type":"Point"}
}