{
  "type": "Feature",
  "properties": {
    "iso:country":"GB",
    "sg:address":"13 Claremont Road",
    "sg:city":"Basildon",
    "sg:classifiers":[
        {
            "category":"Building & Trades",
            "subcategory":"Construction",
            "type":"Services"
        }
    ],
    "sg:postcode":"SS15 5QB",
    "sg:province":"Essex",
    "sg:tags":[
        "builder"
    ],
    "wof:name":"Claremont Construction",
    "wof:placetype":"venue"
},
  "geometry": {"coordinates":[0.4235579967,51.5804824829],"type":"Point"}
}