{
  "type": "Feature",
  "properties": {
    "iso:country":"GB",
    "sg:address":"2 West St",
    "sg:city":"Dudley",
    "sg:classifiers":[
        {
            "category":"Food & Beverages",
            "subcategory":"Meat & Fish",
            "type":"Retail Goods"
        }
    ],
    "sg:postcode":"DY1 2TA",
    "sg:province":"West Midlands",
    "sg:tags":[
        "butcher"
    ],
    "wof:name":"Johnson,Robert,",
    "wof:placetype":"venue"
},
  "geometry": {"coordinates":[-2.100823,52.515121],"type":"Point"}
}