{
  "type": "Feature",
  "properties": {
    "addr:full":"London Road, Sunningdale Ascot Berkshire SL5 0DJ",
    "addr:postcode":"sl5 0dj",
    "addr:street":"London Road",
    "iso:country":"GB",
    "sg:address":"London Road, Sunningdale",
    "sg:city":"Ascot",
    "sg:classifiers":[
        {
            "category":"Personal",
            "subcategory":"Beauty Salon",
            "type":"Services"
        }
    ],
    "sg:phone":"+44 1344 621501",
    "sg:postcode":"SL5 0DJ",
    "sg:province":"Berkshire",
    "sg:tags":[
        "unisex",
        "hairdresser"
    ],
    "wof:name":"Stuarts Gift Shop",
    "wof:placetype":"venue"
},
  "geometry": {"coordinates":[-0.6305090189,51.398601532],"type":"Point"}
}