{
  "type": "Feature",
  "properties": {
    "addr:full":"Alma Close, Kingswood Bristol City of Bristol BS15 4EN",
    "addr:postcode":"bs15 4en",
    "addr:street":"Alma Close",
    "iso:country":"GB",
    "sg:address":"Alma Close, Kingswood",
    "sg:city":"Bristol",
    "sg:classifiers":[
        {
            "category":"Social Services",
            "subcategory":"Adult Care",
            "type":"Services"
        },
        {
            "category":"Government",
            "subcategory":"Office",
            "type":"Public Place"
        }
    ],
    "sg:phone":"+44 117 960 0906",
    "sg:postcode":"BS15 4EN",
    "sg:province":"City of Bristol",
    "sg:tags":[
        "housing",
        "local",
        "sheltered"
    ],
    "wof:name":"Poplar Gardens House",
    "wof:placetype":"venue"
},
  "geometry": {"coordinates":[-2.499019,51.462044],"type":"Point"}
}