{
  "type": "Feature",
  "properties": {
    "addr:full":"22 Fleming Avenue Clydebank East Dunbartonshire G81 1AJ",
    "addr:housenumber":"22",
    "addr:postcode":"g81 1aj",
    "addr:street":"Fleming Avenue",
    "iso:country":"GB",
    "sg:address":"22 Fleming Avenue",
    "sg:city":"Clydebank",
    "sg:classifiers":[
        {
            "category":"Personal",
            "subcategory":"Beauty Salon",
            "type":"Services"
        },
        {
            "category":"Personal",
            "subcategory":"Barber",
            "type":"Services"
        }
    ],
    "sg:phone":"+44 141 952 7940",
    "sg:postcode":"G81 1AJ",
    "sg:province":"East Dunbartonshire",
    "sg:tags":[
        "unisex",
        "hairdresser"
    ],
    "wof:name":"Visage Hair Design",
    "wof:placetype":"venue"
},
  "geometry": {"coordinates":[-4.3880290985,55.8981666565],"type":"Point"}
}