{
  "type": "Feature",
  "properties": {
    "iso:country":"GB",
    "sg:address":"P O Box 19",
    "sg:city":"Spalding",
    "sg:classifiers":[
        {
            "category":"Social Services",
            "type":"Services"
        }
    ],
    "sg:phone":"+44 1775 822192",
    "sg:postcode":"PE11 4UU",
    "sg:province":"Lincolnshire",
    "sg:tags":[
        "need",
        "disability",
        "special"
    ],
    "wof:name":"Bridge-It",
    "wof:placetype":"venue"
},
  "geometry": {"coordinates":[-0.165149,52.872631],"type":"Point"}
}