{
  "type": "Feature",
  "properties": {
    "addr:full":"67 Embankment Road, Prince Rock Plymouth Devon PL4 9HX",
    "addr:postcode":"pl4 9hx",
    "addr:street":"Embankment Road",
    "iso:country":"GB",
    "sg:address":"67 Embankment Road, Prince Rock",
    "sg:city":"Plymouth",
    "sg:classifiers":[
        {
            "category":"Travel",
            "subcategory":"Hotels & Motels",
            "type":"Entertainment"
        }
    ],
    "sg:phone":"+44 1752 661871",
    "sg:postcode":"PL4 9HX",
    "sg:province":"Devon",
    "sg:tags":[
        "house",
        "guest"
    ],
    "wof:name":"Terry & June Guesthouse",
    "wof:placetype":"venue"
},
  "geometry": {"coordinates":[-4.1219072342,50.3706588745],"type":"Point"}
}