{
  "type": "Feature",
  "properties": {
    "iso:country":"GB",
    "sg:address":"8 The Borough",
    "sg:city":"Hinckley",
    "sg:classifiers":[
        {
            "category":"Real Estate",
            "subcategory":"Real Estate Agent",
            "type":"Services"
        }
    ],
    "sg:phone":"+44 1455 632028",
    "sg:postcode":"LE10 1NL",
    "sg:province":"Leicestershire",
    "wof:name":"Suttons (Hinckley) Ltd.",
    "wof:placetype":"venue"
},
  "geometry": {"coordinates":[-1.373199,52.541359],"type":"Point"}
}