{
  "type": "Feature",
  "properties": {
    "addr:full":"81 Croydon Road Beckenham Kent BR3 4AG",
    "addr:housenumber":"81",
    "addr:postcode":"br3 4ag",
    "addr:street":"Croydon Road",
    "iso:country":"GB",
    "sg:address":"81 Croydon Road",
    "sg:city":"Beckenham",
    "sg:classifiers":[
        {
            "category":"Wholesale",
            "subcategory":"Toys & Hobbies",
            "type":"Manufacturing & Wholesale Goods"
        }
    ],
    "sg:phone":"+44 20 8402 9880",
    "sg:postcode":"BR3 4AG",
    "sg:province":"Kent",
    "sg:tags":[
        "balloon",
        "novelty"
    ],
    "wof:name":"Party Costumes Ltd.",
    "wof:placetype":"venue"
},
  "geometry": {"coordinates":[-0.0456749983,51.3984565735],"type":"Point"}
}