{
  "type": "Feature",
  "properties": {
    "addr:full":"518 Inglemire La Hull East Riding of Yorkshire HU6 8JL",
    "addr:housenumber":"518",
    "addr:postcode":"hu6 8jl",
    "addr:street":"Inglemire La Hull",
    "iso:country":"GB",
    "sg:address":"518 Inglemire La",
    "sg:city":"Hull",
    "sg:classifiers":[
        {
            "category":"Retail",
            "subcategory":"Laundry & Dry Cleaning",
            "type":"Services"
        }
    ],
    "sg:phone":"+44 1482 857231",
    "sg:postcode":"HU6 8JL",
    "sg:province":"East Riding of Yorkshire",
    "sg:tags":[
        "launderette"
    ],
    "wof:name":"Laundry Services Of Hull",
    "wof:placetype":"venue"
},
  "geometry": {"coordinates":[-0.3814300001,53.775806427],"type":"Point"}
}