{
  "type": "Feature",
  "properties": {
    "iso:country":"GB",
    "sg:address":"66 Main Street, Forth",
    "sg:city":"Lanark",
    "sg:classifiers":[
        {
            "category":"Health Services",
            "subcategory":"Clinic",
            "type":"Services"
        }
    ],
    "sg:phone":"+44 1555 811476",
    "sg:postcode":"ML11 8AA",
    "sg:province":"South Lanarkshire",
    "sg:tags":[
        "private"
    ],
    "wof:name":"Forth Child Health Clinic",
    "wof:placetype":"venue"
},
  "geometry": {"coordinates":[-3.626016,55.700165],"type":"Point"}
}