{
  "type": "Feature",
  "properties": {
    "addr:full":"16 Main Street, Garforth Leeds North Yorkshire LS25 1EX",
    "addr:housenumber":"16",
    "addr:postcode":"ls25 1ex",
    "addr:street":"Main Street",
    "iso:country":"GB",
    "sg:address":"16 Main Street, Garforth",
    "sg:city":"Leeds",
    "sg:classifiers":[
        {
            "category":"Shopping",
            "subcategory":"Clothing, Apparel, & Fashions",
            "type":"Retail Goods"
        }
    ],
    "sg:phone":"+44 113 287 3787",
    "sg:postcode":"LS25 1EX",
    "sg:province":"North Yorkshire",
    "sg:tags":[
        "shop"
    ],
    "wof:name":"Dorothy Anne Ltd.",
    "wof:placetype":"venue"
},
  "geometry": {"coordinates":[-1.388182,53.793564],"type":"Point"}
}