{
  "type": "Feature",
  "properties": {
    "iso:country":"GB",
    "sg:address":"10 Maple Dr",
    "sg:city":"South Ockendon",
    "sg:classifiers":[
        {
            "category":"Real Estate",
            "subcategory":"Real Estate Agent",
            "type":"Services"
        }
    ],
    "sg:postcode":"RM15 6XE",
    "sg:province":"Essex",
    "wof:name":"Indoor Markets (Saltley) Ltd",
    "wof:placetype":"venue"
},
  "geometry": {"coordinates":[0.299107,51.516666],"type":"Point"}
}