{
  "type": "Feature",
  "properties": {
    "iso:country":"GB",
    "sg:address":"East Gate, High Street",
    "sg:city":"Moffat",
    "sg:classifiers":[
        {
            "category":"Government",
            "subcategory":"Post Office",
            "type":"Public Place"
        }
    ],
    "sg:phone":"+44 1683 221023",
    "sg:postcode":"DG10 9JH",
    "sg:province":"Dumfries and Galloway",
    "wof:name":"Royal Mail",
    "wof:placetype":"venue"
},
  "geometry": {"coordinates":[-3.445039,55.334625],"type":"Point"}
}