{
  "type": "Feature",
  "properties": {
    "iso:country":"GB",
    "sg:address":"Halcyon House, Sandholme Landing, Newport",
    "sg:city":"Brough",
    "sg:classifiers":[
        {
            "category":"Professional",
            "subcategory":"Engineering",
            "type":"Services"
        }
    ],
    "sg:phone":"+44 1430 441765",
    "sg:postcode":"HU15 2RU",
    "sg:province":"East Riding of Yorkshire",
    "sg:tags":[
        "consulting",
        "engineer"
    ],
    "wof:name":"A & F Consulting Engineers",
    "wof:placetype":"venue"
},
  "geometry": {"coordinates":[-0.6953539848,53.7641181946],"type":"Point"}
}