{
  "type": "Feature",
  "properties": {
    "addr:full":"Unit 1, Riverway Trading Estate Trowbridge Wiltshire BA14 8LL",
    "addr:housenumber":"unit 1",
    "addr:postcode":"ba14 8ll",
    "addr:street":"Riverway Trading Estate",
    "iso:country":"GB",
    "sg:address":"Unit 1, Riverway Trading Estate",
    "sg:city":"Trowbridge",
    "sg:classifiers":[
        {
            "category":"Sports & Exercise",
            "subcategory":"Tennis Court",
            "type":"Entertainment"
        }
    ],
    "sg:phone":"+44 1225 777889",
    "sg:postcode":"BA14 8LL",
    "sg:province":"Wiltshire",
    "sg:tags":[
        "breakdown",
        "recovery"
    ],
    "wof:name":"Riverway Breakdown Recovery",
    "wof:placetype":"venue"
},
  "geometry": {"coordinates":[-2.213158,51.322186],"type":"Point"}
}