{
  "type": "Feature",
  "properties": {
    "iso:country":"GB",
    "sg:address":"23 Quay Road, Tate Street",
    "sg:city":"Blyth",
    "sg:classifiers":[
        {
            "category":"Banks & Credit Unions",
            "subcategory":"Financial Services",
            "type":"Services"
        }
    ],
    "sg:phone":"+44 1670 367539",
    "sg:postcode":"NE24 2AS",
    "sg:province":"Northumberland",
    "sg:tags":[
        "consultant"
    ],
    "wof:name":"Vulcan Finance Ltd.",
    "wof:placetype":"venue"
},
  "geometry": {"coordinates":[-1.5037050247,55.1289100647],"type":"Point"}
}