{
  "type": "Feature",
  "properties": {
    "addr:full":"93 Bean Oak Road Wokingham Berkshire RG40 1RJ",
    "addr:housenumber":"93",
    "addr:postcode":"rg40 1rj",
    "addr:street":"Bean Oak Road",
    "iso:country":"GB",
    "sg:address":"93 Bean Oak Road",
    "sg:city":"Wokingham",
    "sg:classifiers":[
        {
            "category":"Shopping",
            "subcategory":"News",
            "type":"Retail Goods"
        }
    ],
    "sg:phone":"+44 118 978 6529",
    "sg:postcode":"RG40 1RJ",
    "sg:province":"Berkshire",
    "sg:tags":[
        "newsagent"
    ],
    "wof:name":"Bean Oak Newsagents",
    "wof:placetype":"venue"
},
  "geometry": {"coordinates":[-0.8168359995,51.4129486084],"type":"Point"}
}