{
  "type": "Feature",
  "properties": {
    "addr:full":"6 Hartsbourne Road, Bushey Heath Watford Hertfordshire WD23 1JH",
    "addr:housenumber":"6",
    "addr:postcode":"wd23 1jh",
    "addr:street":"Hartsbourne Road",
    "iso:country":"GB",
    "sg:address":"6 Hartsbourne Road, Bushey Heath",
    "sg:city":"Watford",
    "sg:classifiers":[
        {
            "category":"Education",
            "subcategory":"School",
            "type":"Public Place"
        }
    ],
    "sg:phone":"+44 20 8950 1138",
    "sg:postcode":"WD23 1JH",
    "sg:province":"Hertfordshire",
    "sg:tags":[
        "independent",
        "preparatory"
    ],
    "wof:name":"Westwood School",
    "wof:placetype":"venue"
},
  "geometry": {"coordinates":[-0.3403150141,51.6322975159],"type":"Point"}
}