{
  "type": "Feature",
  "properties": {
    "addr:full":"Main Building, Horseguards Avenue, Whitehall London Greater London SW1A 2HB",
    "addr:postcode":"sw1a 2hb",
    "addr:street":"Horseguards Avenue",
    "iso:country":"GB",
    "sg:address":"Main Building, Horseguards Avenue, Whitehall",
    "sg:city":"London",
    "sg:classifiers":[
        {
            "category":"Government",
            "subcategory":"Office",
            "type":"Public Place"
        }
    ],
    "sg:phone":"+44 870 607 4455",
    "sg:postcode":"SW1A 2HB",
    "sg:province":"Greater London",
    "sg:tags":[
        "central"
    ],
    "wof:name":"Ministry of Defence",
    "wof:placetype":"venue"
},
  "geometry": {"coordinates":[-0.127143994,51.5063247681],"type":"Point"}
}