{
  "type": "Feature",
  "properties": {
    "iso:country":"GB",
    "sg:address":"1a Church Dr",
    "sg:city":"Nottingham",
    "sg:classifiers":[
        {
            "category":"Professional",
            "subcategory":"Management & Consulting",
            "type":"Services"
        }
    ],
    "sg:phone":"+44 115 920 8144",
    "sg:postcode":"NG5 6JD",
    "sg:province":"Nottinghamshire",
    "sg:tags":[
        "consultant",
        "specialist"
    ],
    "wof:name":"Complexions The Complete Beauty Centre",
    "wof:placetype":"venue"
},
  "geometry": {"coordinates":[-1.138114,53.001019],"type":"Point"}
}