{
  "type": "Feature",
  "properties": {
    "addr:full":"9 Earl Haig Rd Glasgow Glasgow City G52 4JN",
    "addr:housenumber":"9",
    "addr:postcode":"g52 4jn",
    "addr:street":"Earl Haig Rd",
    "iso:country":"GB",
    "sg:address":"9 Earl Haig Rd",
    "sg:city":"Glasgow",
    "sg:classifiers":[
        {
            "category":"Building & Trades",
            "subcategory":"Construction",
            "type":"Services"
        }
    ],
    "sg:phone":"+44 141 891 5737",
    "sg:postcode":"G52 4JN",
    "sg:province":"Glasgow City",
    "sg:tags":[
        "joinery"
    ],
    "wof:name":"John MacDonald & Son",
    "wof:placetype":"venue"
},
  "geometry": {"coordinates":[-4.366799,55.860119],"type":"Point"}
}