{
  "type": "Feature",
  "properties": {
    "addr:full":"28 Manor Crescent Guildford Surrey GU2 9NF",
    "addr:housenumber":"28",
    "addr:postcode":"gu2 9nf",
    "addr:street":"Manor Crescent",
    "iso:country":"GB",
    "sg:address":"28 Manor Crescent",
    "sg:city":"Guildford",
    "sg:classifiers":[
        {
            "category":"Building & Trades",
            "subcategory":"Construction",
            "type":"Services"
        }
    ],
    "sg:phone":"+44 1483 822028",
    "sg:postcode":"GU2 9NF",
    "sg:province":"Surrey",
    "sg:tags":[
        "builder"
    ],
    "wof:name":"D Clark Building",
    "wof:placetype":"venue"
},
  "geometry": {"coordinates":[-0.585419,51.251095],"type":"Point"}
}