{
  "type": "Feature",
  "properties": {
    "addr:full":"11 Borough Rd Middlesbrough North Yorkshire TS1 4AA",
    "addr:housenumber":"11",
    "addr:postcode":"ts1 4aa",
    "addr:street":"Borough Rd",
    "iso:country":"GB",
    "sg:address":"11 Borough Rd",
    "sg:city":"Middlesbrough",
    "sg:classifiers":[
        {
            "category":"Shopping",
            "subcategory":"Gifts & Souvenirs",
            "type":"Retail Goods"
        }
    ],
    "sg:phone":"+44 1642 223560",
    "sg:postcode":"TS1 4AA",
    "sg:province":"North Yorkshire",
    "sg:tags":[
        "shop"
    ],
    "wof:name":"The Holy Shop",
    "wof:placetype":"venue"
},
  "geometry": {"coordinates":[-1.2403810024,54.5731315613],"type":"Point"}
}