{
  "type": "Feature",
  "properties": {
    "addr:full":"37 Blacklands Road, Benson Wallingford Oxfordshire OX10 6NW",
    "addr:housenumber":"37",
    "addr:postcode":"ox10 6nw",
    "addr:street":"Blacklands Road",
    "iso:country":"GB",
    "sg:address":"37 Blacklands Road, Benson",
    "sg:city":"Wallingford",
    "sg:classifiers":[
        {
            "category":"Professional",
            "subcategory":"Engineering",
            "type":"Services"
        }
    ],
    "sg:postcode":"OX10 6NW",
    "sg:province":"Oxfordshire",
    "sg:tags":[
        "contractor",
        "electrical",
        "engineer"
    ],
    "wof:name":"Bruce Ferriman Electrical Services",
    "wof:placetype":"venue"
},
  "geometry": {"coordinates":[-1.1042720079,51.6244697571],"type":"Point"}
}