{
  "type": "Feature",
  "properties": {
    "addr:full":"9 Hare And Billet Road London Greater London SE3 0RB",
    "addr:housenumber":"9",
    "addr:postcode":"se3 0rb",
    "addr:street":"Hare And Billet Road",
    "iso:country":"GB",
    "sg:address":"9 Hare And Billet Road",
    "sg:city":"London",
    "sg:classifiers":[
        {
            "category":"Professional",
            "type":"Services"
        }
    ],
    "sg:phone":"+44 20 8852 0170",
    "sg:postcode":"SE3 0RB",
    "sg:province":"Greater London",
    "sg:tags":[
        "interior",
        "furnishers",
        "designer"
    ],
    "wof:name":"Jane Bottomley Interiors",
    "wof:placetype":"venue"
},
  "geometry": {"coordinates":[0.002567,51.4682197571],"type":"Point"}
}