{
  "type": "Feature",
  "properties": {
    "addr:full":"Manor Court, Bloswood Lane Whitchurch Hampshire RG28 7BN",
    "addr:postcode":"rg28 7bn",
    "addr:street":"Manor;Bloswood Lane",
    "iso:country":"GB",
    "sg:address":"Manor Court, Bloswood Lane",
    "sg:city":"Whitchurch",
    "sg:classifiers":[
        {
            "category":"Building & Trades",
            "subcategory":"Construction",
            "type":"Services"
        }
    ],
    "sg:phone":"+44 1256 892276",
    "sg:postcode":"RG28 7BN",
    "sg:province":"Hampshire",
    "sg:tags":[
        "builder"
    ],
    "wof:name":"Reglensa Ltd.",
    "wof:placetype":"venue"
},
  "geometry": {"coordinates":[-1.346324,51.232605],"type":"Point"}
}