{
  "type": "Feature",
  "properties": {
    "addr:full":"184b Greenacres Road Oldham Lancashire OL4 3EG",
    "addr:housenumber":"184b",
    "addr:postcode":"ol4 3eg",
    "addr:street":"Greenacres Road",
    "iso:country":"GB",
    "sg:address":"184b Greenacres Road",
    "sg:city":"Oldham",
    "sg:classifiers":[
        {
            "category":"Shopping",
            "subcategory":"News",
            "type":"Retail Goods"
        }
    ],
    "sg:postcode":"OL4 3EG",
    "sg:province":"Lancashire",
    "sg:tags":[
        "newsagent"
    ],
    "wof:name":"E & V Pauley",
    "wof:placetype":"venue"
},
  "geometry": {"coordinates":[-2.087442,53.544666],"type":"Point"}
}