{
  "type": "Feature",
  "properties": {
    "iso:country":"GB",
    "sg:address":"44 Throckmorton Rd",
    "sg:city":"Alcester",
    "sg:classifiers":[
        {
            "category":"Building & Trades",
            "subcategory":"Construction",
            "type":"Services"
        }
    ],
    "sg:postcode":"B49 6QB",
    "sg:province":"Warwickshire",
    "sg:tags":[
        "builder"
    ],
    "wof:name":"Clarke,Adrian,",
    "wof:placetype":"venue"
},
  "geometry": {"coordinates":[-1.858298,52.218494],"type":"Point"}
}