{
  "type": "Feature",
  "properties": {
    "iso:country":"GB",
    "sg:address":"30 North Road",
    "sg:city":"Cardiff",
    "sg:classifiers":[
        {
            "category":"Retail",
            "subcategory":"Funeral Services",
            "type":"Services"
        }
    ],
    "sg:phone":"+44 29 2037 2321",
    "sg:postcode":"CF10 3DY",
    "sg:province":"Cardiff",
    "sg:tags":[
        "director"
    ],
    "wof:name":"Rosemount Funeral Homes",
    "wof:placetype":"venue"
},
  "geometry": {"coordinates":[-3.1884229183,51.4922904968],"type":"Point"}
}