{
  "type": "Feature",
  "properties": {
    "iso:country":"GB",
    "sg:address":"42 Storforth Lane Terrace",
    "sg:city":"Chesterfield",
    "sg:classifiers":[
        {
            "category":"Home & Garden",
            "subcategory":"Carpets & Floor Coverings",
            "type":"Retail Goods"
        }
    ],
    "sg:phone":"+44 1246 558008",
    "sg:postcode":"S41 0PY",
    "sg:province":"Derbyshire",
    "sg:tags":[
        "carpets",
        "rug",
        "matting"
    ],
    "wof:name":"Lee M Waddington",
    "wof:placetype":"venue"
},
  "geometry": {"coordinates":[-1.411547,53.220154],"type":"Point"}
}