{
  "type": "Feature",
  "properties": {
    "addr:full":"35 Kingshill Dr, Hoo Rochester Kent ME3 9JW",
    "addr:housenumber":"35",
    "addr:postcode":"me3 9jw",
    "addr:street":"Kingshill Dr",
    "iso:country":"GB",
    "sg:address":"35 Kingshill Dr, Hoo",
    "sg:city":"Rochester",
    "sg:classifiers":[
        {
            "category":"Building & Trades",
            "subcategory":"Construction",
            "type":"Services"
        }
    ],
    "sg:postcode":"ME3 9JW",
    "sg:province":"Kent",
    "sg:tags":[
        "builder"
    ],
    "wof:name":"Galler,J,",
    "wof:placetype":"venue"
},
  "geometry": {"coordinates":[0.5578299761,51.4269371033],"type":"Point"}
}