{
  "type": "Feature",
  "properties": {
    "addr:full":"Unit G2 Tenterfields Business Pa, Rk Burnley Road Halifax West Yorkshire HX2 6EQ",
    "addr:housenumber":"business;rk",
    "addr:postcode":"hx2 6eq",
    "addr:street":"Burnley Road",
    "iso:country":"GB",
    "sg:address":"Unit G2 Tenterfields Business Pa, Rk Burnley Road",
    "sg:city":"Halifax",
    "sg:classifiers":[
        {
            "category":"Manufacturing",
            "subcategory":"Metals",
            "type":"Manufacturing & Wholesale Goods"
        }
    ],
    "sg:postcode":"HX2 6EQ",
    "sg:province":"West Yorkshire",
    "sg:tags":[
        "steel",
        "stockholder"
    ],
    "wof:name":"Novametal",
    "wof:placetype":"venue"
},
  "geometry": {"coordinates":[-1.9380400181,53.7131385803],"type":"Point"}
}