{
  "type": "Feature",
  "properties": {
    "addr:full":"26 Grove Street Oxford Oxfordshire OX2 7JT",
    "addr:housenumber":"26",
    "addr:postcode":"ox2 7jt",
    "addr:street":"Grove Street",
    "iso:country":"GB",
    "sg:address":"26 Grove Street",
    "sg:city":"Oxford",
    "sg:classifiers":[
        {
            "category":"Shopping",
            "subcategory":"Books",
            "type":"Retail Goods"
        }
    ],
    "sg:phone":"+44 1865 514770",
    "sg:postcode":"OX2 7JT",
    "sg:province":"Oxfordshire",
    "sg:tags":[
        "bookseller"
    ],
    "wof:name":"John H Ltd.",
    "wof:placetype":"venue"
},
  "geometry": {"coordinates":[-1.267665,51.779842],"type":"Point"}
}