{
  "type": "Feature",
  "properties": {
    "addr:full":"124a Waterloo Road Manchester Greater Manchester M8 8AF",
    "addr:housenumber":"124a",
    "addr:postcode":"m8 8af",
    "addr:street":"Waterloo Road",
    "iso:country":"GB",
    "sg:address":"124a Waterloo Road",
    "sg:city":"Manchester",
    "sg:classifiers":[
        {
            "category":"Home & Garden",
            "subcategory":"Home Furnishings",
            "type":"Retail Goods"
        }
    ],
    "sg:phone":"+44 161 839 1026",
    "sg:postcode":"M8 8AF",
    "sg:province":"Greater Manchester",
    "sg:tags":[
        "beds",
        "bedding",
        "blanket"
    ],
    "wof:name":"Neatmade Ltd.",
    "wof:placetype":"venue"
},
  "geometry": {"coordinates":[-2.2465679646,53.4989204407],"type":"Point"}
}