{
  "type": "Feature",
  "properties": {
    "addr:full":"Nichols Road Southampton Hampshire SO14 0NT",
    "addr:postcode":"so14 0nt",
    "addr:street":"Nichols Road",
    "iso:country":"GB",
    "sg:address":"Nichols Road",
    "sg:city":"Southampton",
    "sg:classifiers":[
        {
            "category":"Autos & Motor Vehicles",
            "subcategory":"Auto Supplies",
            "type":"Retail Goods"
        },
        {
            "category":"Retail",
            "subcategory":"Auto Repair",
            "type":"Services"
        }
    ],
    "sg:phone":"+44 23 8063 0539",
    "sg:postcode":"SO14 0NT",
    "sg:province":"Hampshire",
    "sg:tags":[
        "car",
        "specialist",
        "tyre",
        "customizing"
    ],
    "wof:name":"CHESSINGTON TYRES LTD",
    "wof:placetype":"venue"
},
  "geometry": {"coordinates":[-1.395034,50.909321],"type":"Point"}
}