{
  "type": "Feature",
  "properties": {
    "iso:country":"GB",
    "sg:address":"145 Church Lane East",
    "sg:city":"Aldershot",
    "sg:classifiers":[
        {
            "category":"Communications",
            "type":"Services"
        }
    ],
    "sg:phone":"+44 1252 666770",
    "sg:postcode":"GU11 3ST",
    "sg:province":"Hampshire",
    "sg:tags":[
        "telecommunication"
    ],
    "wof:name":"Datatel Communications Ltd.",
    "wof:placetype":"venue"
},
  "geometry": {"coordinates":[-0.752639,51.239948],"type":"Point"}
}