{
  "type": "Feature",
  "properties": {
    "addr:full":"13 Worthington Street Dover Kent CT17 9AF",
    "addr:housenumber":"13",
    "addr:postcode":"ct17 9af",
    "addr:street":"Worthington Street",
    "iso:country":"GB",
    "sg:address":"13 Worthington Street",
    "sg:city":"Dover",
    "sg:classifiers":[
        {
            "category":"Food & Beverages",
            "subcategory":"Liquor & Beverages",
            "type":"Retail Goods"
        }
    ],
    "sg:phone":"+44 1304 201406",
    "sg:postcode":"CT17 9AF",
    "sg:province":"Kent",
    "sg:tags":[
        "beer",
        "spirit",
        "wines"
    ],
    "wof:name":"Unwins Wine Merchants",
    "wof:placetype":"venue"
},
  "geometry": {"coordinates":[1.310925,51.126431],"type":"Point"}
}