{
  "type": "Feature",
  "properties": {
    "addr:full":"The Downs Road, Wickwar Wotton-under-edge Gloucestershire GL12 8LF",
    "addr:postcode":"gl12 8lf",
    "addr:street":"The Downs Road",
    "iso:country":"GB",
    "sg:address":"The Downs Road, Wickwar",
    "sg:city":"Wotton-under-edge",
    "sg:classifiers":[
        {
            "category":"Manufacturing",
            "subcategory":"Glass & Minerals",
            "type":"Manufacturing & Wholesale Goods"
        }
    ],
    "sg:phone":"+44 1454 294521",
    "sg:postcode":"GL12 8LF",
    "sg:province":"Gloucestershire",
    "sg:tags":[
        "chalk",
        "stone",
        "slate"
    ],
    "wof:name":"R M C Roadstone Ltd.",
    "wof:placetype":"venue"
},
  "geometry": {"coordinates":[-2.4044690132,51.5976600647],"type":"Point"}
}