{
  "type": "Feature",
  "properties": {
    "iso:country":"GB",
    "sg:address":"52 Kingsland High Street",
    "sg:city":"London",
    "sg:classifiers":[
        {
            "category":"Shopping",
            "subcategory":"Pawn Shop",
            "type":"Retail Goods"
        }
    ],
    "sg:phone":"+44 20 7254 1788",
    "sg:postcode":"E8 2JP",
    "sg:province":"Greater London",
    "sg:tags":[
        "pawnbroker"
    ],
    "wof:name":"Harvey & Thompson Ltd.",
    "wof:placetype":"venue"
},
  "geometry": {"coordinates":[-0.075354,51.54752],"type":"Point"}
}