{
  "type": "Feature",
  "properties": {
    "addr:full":"Homer Much Wenlock Shropshire TF13 6NQ",
    "addr:postcode":"tf13 6nq",
    "addr:street":"Homer;Wenlock",
    "iso:country":"GB",
    "sg:address":"Homer",
    "sg:city":"Much Wenlock",
    "sg:classifiers":[
        {
            "category":"Freight",
            "type":"Transportation"
        }
    ],
    "sg:phone":"+44 1952 727553",
    "sg:postcode":"TF13 6NQ",
    "sg:province":"Shropshire",
    "sg:tags":[
        "haulage",
        "road"
    ],
    "wof:name":"Homer Garage",
    "wof:placetype":"venue"
},
  "geometry": {"coordinates":[-2.5599250793,52.5940093994],"type":"Point"}
}