{
  "type": "Feature",
  "properties": {
    "iso:country":"GB",
    "sg:address":"22 Stone Street",
    "sg:city":"Gravesend",
    "sg:classifiers":[
        {
            "category":"Professional",
            "subcategory":"Art Services",
            "type":"Services"
        }
    ],
    "sg:phone":"+44 1474 328082",
    "sg:postcode":"DA11 0NP",
    "sg:province":"Kent",
    "sg:tags":[
        "photographer"
    ],
    "wof:name":"J & J Lowman",
    "wof:placetype":"venue"
},
  "geometry": {"coordinates":[0.3684639931,51.4408988953],"type":"Point"}
}