{
  "type": "Feature",
  "properties": {
    "addr:full":"87 Belvedere Rd Upper Norwood Greater London SE19 2HX",
    "addr:housenumber":"87",
    "addr:postcode":"se19 2hx",
    "addr:street":"Belvedere Rd",
    "iso:country":"GB",
    "sg:address":"87 Belvedere Rd",
    "sg:city":"Upper Norwood",
    "sg:classifiers":[
        {
            "category":"Shopping",
            "subcategory":"Catalog Store",
            "type":"Retail Goods"
        }
    ],
    "sg:phone":"+44 20 8771 0614",
    "sg:postcode":"SE19 2HX",
    "sg:province":"Greater London",
    "sg:tags":[
        "mail",
        "order"
    ],
    "wof:name":"Kleeneze",
    "wof:placetype":"venue"
},
  "geometry": {"coordinates":[-0.0761440024,51.4148826599],"type":"Point"}
}