{
  "type": "Feature",
  "properties": {
    "addr:full":"22 Wigan Road, Hindley Wigan Lancashire WN2 3BE",
    "addr:housenumber":"22",
    "addr:postcode":"wn2 3be",
    "addr:street":"Wigan Road",
    "iso:country":"GB",
    "sg:address":"22 Wigan Road, Hindley",
    "sg:city":"Wigan",
    "sg:classifiers":[
        {
            "category":"Shopping",
            "subcategory":"Discount & Variety Stores",
            "type":"Retail Goods"
        }
    ],
    "sg:phone":"+44 1942 523505",
    "sg:postcode":"WN2 3BE",
    "sg:province":"Lancashire",
    "sg:tags":[
        "shop",
        "model"
    ],
    "wof:name":"North West Model Supplies",
    "wof:placetype":"venue"
},
  "geometry": {"coordinates":[-2.580824,53.533611],"type":"Point"}
}