{
  "type": "Feature",
  "properties": {
    "addr:full":"7 Mount Road, Penn Wolverhampton Staffordshire WV4 5SN",
    "addr:housenumber":"7",
    "addr:postcode":"wv4 5sn",
    "addr:street":"Mount Road",
    "iso:country":"GB",
    "sg:address":"7 Mount Road, Penn",
    "sg:city":"Wolverhampton",
    "sg:classifiers":[
        {
            "category":"Retail",
            "subcategory":"Repair Shop",
            "type":"Services"
        }
    ],
    "sg:phone":"+44 1902 332086",
    "sg:postcode":"WV4 5SN",
    "sg:province":"Staffordshire",
    "sg:tags":[
        "radio",
        "television",
        "video"
    ],
    "wof:name":"Pritchard T V Services",
    "wof:placetype":"venue"
},
  "geometry": {"coordinates":[-2.1458570957,52.5654373169],"type":"Point"}
}