{
  "type": "Feature",
  "properties": {
    "iso:country":"GB",
    "sg:address":"2a London Road, Horndean",
    "sg:city":"Waterlooville",
    "sg:classifiers":[
        {
            "category":"Fast Food",
            "type":"Food & Drink"
        }
    ],
    "sg:postcode":"PO8 0BZ",
    "sg:province":"Hampshire",
    "sg:tags":[
        "away",
        "take"
    ],
    "wof:name":"Kim's Kitchen",
    "wof:placetype":"venue"
},
  "geometry": {"coordinates":[-0.996746,50.939312],"type":"Point"}
}