{
  "type": "Feature",
  "properties": {
    "addr:full":"48 Town Street, Marple Bridge Stockport Cheshire SK6 5AA",
    "addr:housenumber":"48",
    "addr:postcode":"sk6 5aa",
    "addr:street":"Town Street",
    "iso:country":"GB",
    "sg:address":"48 Town Street, Marple Bridge",
    "sg:city":"Stockport",
    "sg:classifiers":[
        {
            "category":"Bars & Pubs",
            "type":"Food & Drink"
        }
    ],
    "sg:phone":"+44 161 427 3149",
    "sg:postcode":"SK6 5AA",
    "sg:province":"Cheshire",
    "sg:tags":[
        "pubs",
        "inn"
    ],
    "wof:name":"The Royal Scot",
    "wof:placetype":"venue"
},
  "geometry": {"coordinates":[-2.053291,53.400421],"type":"Point"}
}