{
  "type": "Feature",
  "properties": {
    "iso:country":"GB",
    "sg:address":"7 Angel Square",
    "sg:city":"Penrith",
    "sg:classifiers":[
        {
            "category":"Shopping",
            "subcategory":"Clothing, Apparel, & Fashions",
            "type":"Retail Goods"
        }
    ],
    "sg:phone":"+44 1768 890358",
    "sg:postcode":"CA11 7BP",
    "sg:province":"Cumbria",
    "sg:tags":[
        "ladieswear"
    ],
    "wof:name":"Bon Marche",
    "wof:placetype":"venue"
},
  "geometry": {"coordinates":[-2.75228,54.663464],"type":"Point"}
}