{
  "type": "Feature",
  "properties": {
    "addr:full":"57 Shakespeare Rd Neston Cheshire CH64 9TG",
    "addr:housenumber":"57",
    "addr:postcode":"ch64 9tg",
    "addr:street":"Shakespeare Rd",
    "iso:country":"GB",
    "sg:address":"57 Shakespeare Rd",
    "sg:city":"Neston",
    "sg:classifiers":[
        {
            "category":"Building & Trades",
            "subcategory":"Construction",
            "type":"Services"
        }
    ],
    "sg:phone":"+44 151 353 1859",
    "sg:postcode":"CH64 9TG",
    "sg:province":"Cheshire",
    "sg:tags":[
        "flooring"
    ],
    "wof:name":"Arrow Paving",
    "wof:placetype":"venue"
},
  "geometry": {"coordinates":[-3.0612499714,53.2949905396],"type":"Point"}
}