{
  "type": "Feature",
  "properties": {
    "addr:full":"The Beeches, Swafield North Walsham Norfolk NR28 0RP",
    "addr:postcode":"nr28 0rp",
    "addr:street":"North Walsham",
    "iso:country":"GB",
    "sg:address":"The Beeches, Swafield",
    "sg:city":"North Walsham",
    "sg:classifiers":[
        {
            "category":"Farming",
            "subcategory":"Farm",
            "type":"Manufacturing & Wholesale Goods"
        }
    ],
    "sg:postcode":"NR28 0RP",
    "sg:province":"Norfolk",
    "sg:tags":[
        "mixed",
        "crop"
    ],
    "wof:name":"R C Cattling",
    "wof:placetype":"venue"
},
  "geometry": {"coordinates":[1.3847600222,52.8183135986],"type":"Point"}
}