{
  "type": "Feature",
  "properties": {
    "iso:country":"GB",
    "sg:address":"14 Regency Parade Finchley Road",
    "sg:city":"London",
    "sg:classifiers":[
        {
            "category":"Wholesale",
            "subcategory":"Machinery & Supplies",
            "type":"Manufacturing & Wholesale Goods"
        }
    ],
    "sg:postcode":"NW3 5EG",
    "sg:province":"Greater London",
    "wof:name":"Trac Systems Ltd.",
    "wof:placetype":"venue"
},
  "geometry": {"coordinates":[-0.1750299931,51.5421295166],"type":"Point"}
}