{
  "type": "Feature",
  "properties": {
    "iso:country":"GB",
    "sg:address":"347-351 Bath Road",
    "sg:city":"Slough",
    "sg:classifiers":[
        {
            "category":"Autos & Motor Vehicles",
            "subcategory":"Automobile Sales",
            "type":"Retail Goods"
        }
    ],
    "sg:phone":"+44 1628 666226",
    "sg:postcode":"SL1 5PR",
    "sg:province":"Berkshire",
    "sg:tags":[
        "commercial"
    ],
    "wof:name":"Slough van & Truck Centre Ltd.",
    "wof:placetype":"venue"
},
  "geometry": {"coordinates":[-0.639064,51.520424],"type":"Point"}
}