{
  "type": "Feature",
  "properties": {
    "iso:country":"GB",
    "sg:address":"Melville Street",
    "sg:city":"Lincoln",
    "sg:classifiers":[
        {
            "category":"Health Services",
            "subcategory":"Nursing And Care Facility",
            "type":"Services"
        },
        {
            "category":"Government",
            "subcategory":"Office",
            "type":"Public Place"
        }
    ],
    "sg:phone":"+44 1522 800100",
    "sg:postcode":"LN5 7HW",
    "sg:province":"Lincolnshire",
    "sg:tags":[
        "residential",
        "central"
    ],
    "wof:name":"Dial-A-Ride Community Transport",
    "wof:placetype":"venue"
},
  "geometry": {"coordinates":[-0.536589,53.227726],"type":"Point"}
}