{
  "type": "Feature",
  "properties": {
    "addr:full":"38 Portland Road Kilmarnock East Ayrshire KA1 2DL",
    "addr:housenumber":"38",
    "addr:postcode":"ka1 2dl",
    "addr:street":"Portland Road",
    "iso:country":"GB",
    "sg:address":"38 Portland Road",
    "sg:city":"Kilmarnock",
    "sg:classifiers":[
        {
            "category":"Community Center",
            "subcategory":"Youth",
            "type":"Public Place"
        }
    ],
    "sg:phone":"+44 1563 531237",
    "sg:postcode":"KA1 2DL",
    "sg:province":"East Ayrshire",
    "sg:tags":[
        "organisation",
        "centre"
    ],
    "wof:name":"The Rathbone Society",
    "wof:placetype":"venue"
},
  "geometry": {"coordinates":[-4.5041828156,55.6080360413],"type":"Point"}
}