{
  "type": "Feature",
  "properties": {
    "addr:full":"19 Princelet Street, Spitalfields London Greater London E1 6QH",
    "addr:housenumber":"19",
    "addr:postcode":"e1 6qh",
    "addr:street":"Princelet Street",
    "iso:country":"GB",
    "sg:address":"19 Princelet Street, Spitalfields",
    "sg:city":"London",
    "sg:classifiers":[
        {
            "category":"Organizations",
            "subcategory":"Non-profit Organization",
            "type":"Services"
        }
    ],
    "sg:phone":"+44 20 7247 0971",
    "sg:postcode":"E1 6QH",
    "sg:province":"Greater London",
    "sg:tags":[
        "organisation",
        "voluntary",
        "charity"
    ],
    "wof:name":"Spitalfields Historic Buildings Trust Ltd.",
    "wof:placetype":"venue"
},
  "geometry": {"coordinates":[-0.0724150017,51.519908905],"type":"Point"}
}