{
  "type": "Feature",
  "properties": {
    "addr:full":"63 Wentworth Drive, Thorley Park Bishops Stortford Essex CM23 2PD",
    "addr:housenumber":"63",
    "addr:postcode":"cm23 2pd",
    "addr:street":"Wentworth Drive Thorley Park Bishops",
    "iso:country":"GB",
    "sg:address":"63 Wentworth Drive, Thorley Park",
    "sg:city":"Bishops Stortford",
    "sg:classifiers":[
        {
            "category":"Professional",
            "subcategory":"Engineering",
            "type":"Services"
        }
    ],
    "sg:postcode":"CM23 2PD",
    "sg:province":"Essex",
    "sg:tags":[
        "contractor",
        "electrical",
        "engineer"
    ],
    "wof:name":"D D S Electrical",
    "wof:placetype":"venue"
},
  "geometry": {"coordinates":[0.1469260007,51.8660545349],"type":"Point"}
}