{
  "type": "Feature",
  "properties": {
    "addr:full":"39 Panton Street Cambridge Cambridgeshire CB2 1HL",
    "addr:housenumber":"39",
    "addr:postcode":"cb2 1hl",
    "addr:street":"Panton Street",
    "iso:country":"GB",
    "sg:address":"39 Panton Street",
    "sg:city":"Cambridge",
    "sg:classifiers":[
        {
            "category":"Professional",
            "subcategory":"Management & Consulting",
            "type":"Services"
        }
    ],
    "sg:postcode":"CB2 1HL",
    "sg:province":"Cambridgeshire",
    "sg:tags":[
        "consultant",
        "business"
    ],
    "wof:name":"Shelford Consulting Ltd.",
    "wof:placetype":"venue"
},
  "geometry": {"coordinates":[0.124932,52.196613],"type":"Point"}
}