{
  "type": "Feature",
  "properties": {
    "addr:full":"Limborough Rd Wantage Berkshire OX12 9AJ",
    "addr:postcode":"ox12 9aj",
    "addr:street":"Limborough Rd",
    "iso:country":"GB",
    "sg:address":"Limborough Rd",
    "sg:city":"Wantage",
    "sg:classifiers":[
        {
            "category":"Food & Beverages",
            "subcategory":"Supermarket",
            "type":"Retail Goods"
        }
    ],
    "sg:postcode":"OX12 9AJ",
    "sg:province":"Berkshire",
    "wof:name":"Buy-Lo",
    "wof:placetype":"venue"
},
  "geometry": {"coordinates":[-1.4257919788,51.5912361145],"type":"Point"}
}