{
  "type": "Feature",
  "properties": {
    "iso:country":"GB",
    "sg:address":"14 Hillcrest Road, Acton",
    "sg:city":"London",
    "sg:classifiers":[
        {
            "category":"Professional",
            "subcategory":"Art Services",
            "type":"Services"
        }
    ],
    "sg:postcode":"W3 9RZ",
    "sg:province":"Greater London",
    "sg:tags":[
        "consultant",
        "design"
    ],
    "wof:name":"Simon Jenkins Associates",
    "wof:placetype":"venue"
},
  "geometry": {"coordinates":[-0.279709,51.507385],"type":"Point"}
}