{
  "type": "Feature",
  "properties": {
    "addr:full":"36 West Bar Street Banbury Oxfordshire OX16 9RU",
    "addr:housenumber":"36",
    "addr:postcode":"ox16 9ru",
    "addr:street":"West Bar Street",
    "iso:country":"GB",
    "sg:address":"36 West Bar Street",
    "sg:city":"Banbury",
    "sg:classifiers":[
        {
            "category":"Professional",
            "subcategory":"Lawyer & Legal Services",
            "type":"Services"
        }
    ],
    "sg:phone":"+44 1295 251234",
    "sg:postcode":"OX16 9RU",
    "sg:province":"Oxfordshire",
    "sg:tags":[
        "solicitor"
    ],
    "wof:name":"APLIN STOCKTON FAIRFAX",
    "wof:placetype":"venue"
},
  "geometry": {"coordinates":[-1.342752,52.059734],"type":"Point"}
}