{
  "type": "Feature",
  "properties": {
    "iso:country":"GB",
    "sg:address":"4 Drozier House, Market Place",
    "sg:city":"Holt",
    "sg:classifiers":[
        {
            "category":"Shopping",
            "subcategory":"Baby Store",
            "type":"Retail Goods"
        }
    ],
    "sg:phone":"+44 1263 713031",
    "sg:postcode":"NR25 6BE",
    "sg:province":"Norfolk",
    "sg:tags":[
        "babywear",
        "childrens"
    ],
    "wof:name":"Bishops of Holt",
    "wof:placetype":"venue"
},
  "geometry": {"coordinates":[1.0899460316,52.9030570984],"type":"Point"}
}