{
  "type": "Feature",
  "properties": {
    "iso:country":"GB",
    "sg:address":"Henbant, Cwmann",
    "sg:city":"Lampeter",
    "sg:classifiers":[
        {
            "category":"Farming",
            "subcategory":"Livestock Farm",
            "type":"Manufacturing & Wholesale Goods"
        }
    ],
    "sg:phone":"+44 1570 422614",
    "sg:postcode":"SA48 8DX",
    "sg:province":"Carmarthenshire",
    "sg:tags":[
        "others"
    ],
    "wof:name":"D H Davies",
    "wof:placetype":"venue"
},
  "geometry": {"coordinates":[-4.068253994,52.1056365967],"type":"Point"}
}