{
  "type": "Feature",
  "properties": {
    "iso:country":"GB",
    "sg:address":"1 Sir Johns Square",
    "sg:city":"Thurso",
    "sg:classifiers":[
        {
            "category":"Shopping",
            "subcategory":"Beauty & Cosmetics",
            "type":"Retail Goods"
        },
        {
            "category":"Personal",
            "type":"Services"
        }
    ],
    "sg:phone":"+44 1847 895558",
    "sg:postcode":"KW14 7AN",
    "sg:province":"Highland",
    "sg:tags":[
        "consultant",
        "product"
    ],
    "sg:website":"http://www.bth.co.uk",
    "wof:name":"Beauty Through Herbs Ltd.",
    "wof:placetype":"venue"
},
  "geometry": {"coordinates":[-3.522357,58.593388],"type":"Point"}
}