{
  "type": "Feature",
  "properties": {
    "iso:country":"GB",
    "sg:address":"1020 Lincoln Road",
    "sg:city":"Peterborough",
    "sg:classifiers":[
        {
            "category":"Manufacturing",
            "subcategory":"Buildings",
            "type":"Manufacturing & Wholesale Goods"
        }
    ],
    "sg:postcode":"PE4 6AL",
    "sg:province":"Cambridgeshire",
    "sg:tags":[
        "portable"
    ],
    "wof:name":"Walton Sectional Buildings",
    "wof:placetype":"venue"
},
  "geometry": {"coordinates":[-0.26815,52.602505],"type":"Point"}
}