{
  "type": "Feature",
  "properties": {
    "addr:full":"46 Fore Street, Shaldon Teignmouth Devon TQ14 0EA",
    "addr:housenumber":"46",
    "addr:postcode":"tq14 0ea",
    "addr:street":"Fore Street",
    "iso:country":"GB",
    "sg:address":"46 Fore Street, Shaldon",
    "sg:city":"Teignmouth",
    "sg:classifiers":[
        {
            "category":"Travel",
            "subcategory":"Hotels & Motels",
            "type":"Entertainment"
        }
    ],
    "sg:phone":"+44 1626 872314",
    "sg:postcode":"TQ14 0EA",
    "sg:province":"Devon",
    "sg:tags":[
        "self",
        "catering"
    ],
    "wof:name":"Cottages South West",
    "wof:placetype":"venue"
},
  "geometry": {"coordinates":[-3.506624,50.540707],"type":"Point"}
}