{
  "type": "Feature",
  "properties": {
    "addr:full":"Next To Tulse House, Tulse Hill London Greater London SW2 2HT",
    "addr:postcode":"sw2 2ht",
    "addr:street":"Tulse Hill",
    "iso:country":"GB",
    "sg:address":"Next To Tulse House, Tulse Hill",
    "sg:city":"London",
    "sg:classifiers":[
        {
            "category":"Building & Trades",
            "subcategory":"Landscaping Services",
            "type":"Services"
        }
    ],
    "sg:phone":"+44 20 8674 9039",
    "sg:postcode":"SW2 2HT",
    "sg:province":"Greater London",
    "sg:tags":[
        "forestry",
        "tree"
    ],
    "wof:name":"Continental Landscapes Ltd.",
    "wof:placetype":"venue"
},
  "geometry": {"coordinates":[-0.113518998,51.454826355],"type":"Point"}
}