{
  "type": "Feature",
  "properties": {
    "iso:country":"GB",
    "sg:address":"5 Victoria Embkmt, Trent Bridge",
    "sg:city":"Nottingham",
    "sg:classifiers":[
        {
            "category":"Health Services",
            "subcategory":"Health Practitioner",
            "type":"Services"
        },
        {
            "category":"Shopping",
            "subcategory":"Pharmacy",
            "type":"Retail Goods"
        },
        {
            "category":"Health Services",
            "subcategory":"Dentist",
            "type":"Services"
        }
    ],
    "sg:phone":"+44 115 986 4741",
    "sg:postcode":"NG2 2JY",
    "sg:province":"Nottinghamshire",
    "sg:tags":[
        "medicine",
        "psychotherapist",
        "therapy"
    ],
    "wof:name":"The Smile Centre",
    "wof:placetype":"venue"
},
  "geometry": {"coordinates":[-1.138352,52.938591],"type":"Point"}
}