{
  "type": "Feature",
  "properties": {
    "iso:country":"GB",
    "sg:address":"1 Ebor Terrace, Hunslet",
    "sg:city":"Leeds",
    "sg:classifiers":[
        {
            "category":"Professional",
            "subcategory":"Computer Services",
            "type":"Services"
        }
    ],
    "sg:phone":"+44 113 270 6315",
    "sg:postcode":"LS10 2EQ",
    "sg:province":"West Yorkshire",
    "sg:tags":[
        "system",
        "software"
    ],
    "wof:name":"Cheeky Ink Graphics & Computer Services",
    "wof:placetype":"venue"
},
  "geometry": {"coordinates":[-1.5256329775,53.7707939148],"type":"Point"}
}