{
  "type": "Feature",
  "properties": {
    "iso:country":"GB",
    "sg:address":"Lower Hallfield, Chardleigh Grn, Wadeford",
    "sg:city":"Chard",
    "sg:classifiers":[
        {
            "category":"Farming",
            "subcategory":"Livestock Farm",
            "type":"Manufacturing & Wholesale Goods"
        }
    ],
    "sg:postcode":"TA20 3AJ",
    "sg:province":"Devon",
    "sg:tags":[
        "others"
    ],
    "wof:name":"J B Cockburn & Partners",
    "wof:placetype":"venue"
},
  "geometry": {"coordinates":[-2.9828848839,50.8906898499],"type":"Point"}
}