{
  "type": "Feature",
  "properties": {
    "iso:country":"GB",
    "sg:address":"30-31 Wright's Houses",
    "sg:city":"Edinburgh",
    "sg:classifiers":[
        {
            "category":"Bars & Pubs",
            "type":"Food & Drink"
        }
    ],
    "sg:phone":"+44 131 229 3235",
    "sg:postcode":"EH10 4HR",
    "sg:province":"City of Edinburgh",
    "sg:tags":[
        "pubs",
        "inn"
    ],
    "wof:name":"Golf Tavern",
    "wof:placetype":"venue"
},
  "geometry": {"coordinates":[-3.1859738827,55.947555542],"type":"Point"}
}