{
  "type": "Feature",
  "properties": {
    "addr:full":"9 Stockdale Parade Tipton West Midlands DY4 8QL",
    "addr:housenumber":"9",
    "addr:postcode":"dy4 8ql",
    "addr:street":"Stockdale Parade",
    "iso:country":"GB",
    "sg:address":"9 Stockdale Parade",
    "sg:city":"Tipton",
    "sg:classifiers":[
        {
            "category":"Shopping",
            "subcategory":"Clothing, Apparel, & Fashions",
            "type":"Retail Goods"
        }
    ],
    "sg:phone":"+44 121 557 5775",
    "sg:postcode":"DY4 8QL",
    "sg:province":"West Midlands",
    "sg:tags":[
        "shop"
    ],
    "wof:name":"Budget Box",
    "wof:placetype":"venue"
},
  "geometry": {"coordinates":[-2.0706970692,52.528137207],"type":"Point"}
}