{
  "type": "Feature",
  "properties": {
    "addr:full":"12 Uttoxeter Rd, Tean Stoke-on-trent Staffordshire ST10 4LJ",
    "addr:housenumber":"12",
    "addr:postcode":"st10 4lj",
    "addr:street":"Uttoxeter Rd",
    "iso:country":"GB",
    "sg:address":"12 Uttoxeter Rd, Tean",
    "sg:city":"Stoke-on-trent",
    "sg:classifiers":[
        {
            "category":"Building & Trades",
            "subcategory":"Construction",
            "type":"Services"
        }
    ],
    "sg:postcode":"ST10 4LJ",
    "sg:province":"Staffordshire",
    "sg:tags":[
        "platform",
        "work",
        "scaffolding"
    ],
    "wof:name":"Ledwith,D P,",
    "wof:placetype":"venue"
},
  "geometry": {"coordinates":[-1.958418,52.952461],"type":"Point"}
}