{
  "type": "Feature",
  "properties": {
    "addr:full":"43 Anglers Lane, Spondon Derby Derbyshire DE21 7NT",
    "addr:housenumber":"43",
    "addr:postcode":"de21 7nt",
    "addr:street":"Anglers Lane",
    "iso:country":"GB",
    "sg:address":"43 Anglers Lane, Spondon",
    "sg:city":"Derby",
    "sg:classifiers":[
        {
            "category":"Retail",
            "subcategory":"Auto Repair",
            "type":"Services"
        }
    ],
    "sg:phone":"+44 1332 678991",
    "sg:postcode":"DE21 7NT",
    "sg:province":"Derbyshire",
    "sg:tags":[
        "modification",
        "garage"
    ],
    "wof:name":"Davmin Motor Repairs",
    "wof:placetype":"venue"
},
  "geometry": {"coordinates":[-1.4026349783,52.9107513428],"type":"Point"}
}