{
  "type": "Feature",
  "properties": {
    "addr:full":"70 Camden High Street London Greater London NW1 0LT",
    "addr:housenumber":"70",
    "addr:postcode":"nw1 0lt",
    "addr:street":"Camden High Street",
    "iso:country":"GB",
    "sg:address":"70 Camden High Street",
    "sg:city":"London",
    "sg:classifiers":[
        {
            "category":"Communications",
            "subcategory":"Film & Video Production",
            "type":"Services"
        }
    ],
    "sg:phone":"+44 20 7388 0764",
    "sg:postcode":"NW1 0LT",
    "sg:province":"Greater London",
    "sg:tags":[
        "tv"
    ],
    "wof:name":"Radio Rentals",
    "wof:placetype":"venue"
},
  "geometry": {"coordinates":[-0.140051,51.536419],"type":"Point"}
}