{
  "type": "Feature",
  "properties": {
    "iso:country":"GB",
    "sg:address":"46 Middlewich Rd",
    "sg:city":"Sandbach",
    "sg:classifiers":[
        {
            "category":"Professional",
            "subcategory":"Printing & Photocopies",
            "type":"Services"
        }
    ],
    "sg:phone":"+44 1270 762080",
    "sg:postcode":"CW11 9DU",
    "sg:province":"Cheshire",
    "sg:tags":[
        "printer"
    ],
    "wof:name":"R & A Simcox",
    "wof:placetype":"venue"
},
  "geometry": {"coordinates":[-2.368136,53.144917],"type":"Point"}
}