{
  "type": "Feature",
  "properties": {
    "addr:full":"9 Lower Eastern Green Lane Coventry West Midlands CV5 7LR",
    "addr:housenumber":"9",
    "addr:postcode":"cv5 7lr",
    "addr:street":"Lower Eastern Green Lane",
    "iso:country":"GB",
    "sg:address":"9 Lower Eastern Green Lane",
    "sg:city":"Coventry",
    "sg:classifiers":[
        {
            "category":"Building & Trades",
            "subcategory":"Construction",
            "type":"Services"
        }
    ],
    "sg:phone":"+44 24 7669 4272",
    "sg:postcode":"CV5 7LR",
    "sg:province":"West Midlands",
    "sg:tags":[
        "builder"
    ],
    "wof:name":"Peter Luckett & Sons",
    "wof:placetype":"venue"
},
  "geometry": {"coordinates":[-1.5744589567,52.4160423279],"type":"Point"}
}