{
  "type": "Feature",
  "properties": {
    "addr:full":"36 Kings Avenue Rye East Sussex TN31 7LX",
    "addr:housenumber":"36",
    "addr:postcode":"tn31 7lx",
    "addr:street":"Kings Avenue",
    "iso:country":"GB",
    "sg:address":"36 Kings Avenue",
    "sg:city":"Rye",
    "sg:classifiers":[
        {
            "category":"Military Area",
            "subcategory":"Air Force Base",
            "type":"Public Place"
        }
    ],
    "sg:phone":"+44 1797 224554",
    "sg:postcode":"TN31 7LX",
    "sg:province":"East Sussex",
    "sg:tags":[
        "taxi",
        "hire",
        "private"
    ],
    "wof:name":"Rother Cabs",
    "wof:placetype":"venue"
},
  "geometry": {"coordinates":[0.7402960062,50.9553337097],"type":"Point"}
}