{
  "type": "Feature",
  "properties": {
    "addr:full":"The Cedars Wisbech Cambridgeshire PE14 7RX",
    "addr:postcode":"pe14 7rx",
    "iso:country":"GB",
    "sg:address":"The Cedars",
    "sg:city":"Wisbech",
    "sg:classifiers":[
        {
            "category":"Professional",
            "subcategory":"Printing & Photocopies",
            "type":"Services"
        }
    ],
    "sg:phone":"+44 1945 881331",
    "sg:postcode":"PE14 7RX",
    "sg:province":"Cambridgeshire",
    "sg:tags":[
        "typesetter"
    ],
    "wof:name":"Spectra Electronics",
    "wof:placetype":"venue"
},
  "geometry": {"coordinates":[0.220791,52.733204],"type":"Point"}
}