{
  "type": "Feature",
  "properties": {
    "addr:full":"Allways Northmoor Grn, Moorland Bridgwater Somerset TA7 0AX",
    "addr:housenumber":"allways",
    "addr:postcode":"ta7 0ax",
    "addr:street":"Northmoor Grn",
    "iso:country":"GB",
    "sg:address":"Allways Northmoor Grn, Moorland",
    "sg:city":"Bridgwater",
    "sg:classifiers":[
        {
            "category":"Building & Trades",
            "subcategory":"Construction",
            "type":"Services"
        },
        {
            "category":"Manufacturing",
            "subcategory":"Building Materials",
            "type":"Manufacturing & Wholesale Goods"
        }
    ],
    "sg:phone":"+44 1278 691633",
    "sg:postcode":"TA7 0AX",
    "sg:province":"Somerset",
    "sg:tags":[
        "stonemason",
        "monumental",
        "mason"
    ],
    "wof:name":"Derek Bristow",
    "wof:placetype":"venue"
},
  "geometry": {"coordinates":[-2.9345788956,51.0767936707],"type":"Point"}
}