{
  "type": "Feature",
  "properties": {
    "iso:country":"GB",
    "sg:address":"The Mill, 1 Blair Road",
    "sg:city":"Dalry",
    "sg:classifiers":[
        {
            "category":"Home & Garden",
            "subcategory":"Furniture",
            "type":"Retail Goods"
        }
    ],
    "sg:phone":"+44 1294 833241",
    "sg:postcode":"KA24 4DE",
    "sg:province":"North Ayrshire",
    "wof:name":"Dales of Dalry (Furnishing Centre) Ltd.",
    "wof:placetype":"venue"
},
  "geometry": {"coordinates":[-4.720990181,55.7065963745],"type":"Point"}
}