{
  "type": "Feature",
  "properties": {
    "iso:country":"GB",
    "sg:address":"272 High Street",
    "sg:city":"West Bromwich",
    "sg:classifiers":[
        {
            "category":"Restaurant",
            "type":"Food & Drink"
        }
    ],
    "sg:phone":"+44 121 553 4893",
    "sg:postcode":"B70 8AQ",
    "sg:province":"West Midlands",
    "sg:tags":[
        "greek"
    ],
    "wof:name":"La Casa",
    "wof:placetype":"venue"
},
  "geometry": {"coordinates":[-1.995278,52.519131],"type":"Point"}
}