{
  "type": "Feature",
  "properties": {
    "addr:full":"Stable Barn, Holcombe Rogus Wellington Devon TA21 0NE",
    "addr:postcode":"ta21 0ne",
    "iso:country":"GB",
    "sg:address":"Stable Barn, Holcombe Rogus",
    "sg:city":"Wellington",
    "sg:classifiers":[
        {
            "category":"Real Estate",
            "subcategory":"Surveying",
            "type":"Services"
        },
        {
            "category":"Real Estate",
            "subcategory":"Architect",
            "type":"Services"
        }
    ],
    "sg:postcode":"TA21 0NE",
    "sg:province":"Devon",
    "sg:tags":[
        "surveyor",
        "land"
    ],
    "wof:name":"Stephen John Rawle",
    "wof:placetype":"venue"
},
  "geometry": {"coordinates":[-3.3426029682,50.9610214233],"type":"Point"}
}