{
  "type": "Feature",
  "properties": {
    "iso:country":"GB",
    "sg:address":"40 Hoghton Street",
    "sg:city":"Southport",
    "sg:classifiers":[
        {
            "category":"Insurance",
            "subcategory":"Insurance Agent",
            "type":"Services"
        }
    ],
    "sg:phone":"+44 1704 548999",
    "sg:postcode":"PR9 0PQ",
    "sg:province":"Lancashire",
    "sg:tags":[
        "broker"
    ],
    "sg:website":"http://www.drpinsurance.com",
    "wof:name":"David Roberts & Partners",
    "wof:placetype":"venue"
},
  "geometry": {"coordinates":[-2.9991419315,53.6494178772],"type":"Point"}
}