{
  "type": "Feature",
  "properties": {
    "addr:full":"4 The Poplars, Clee Hill Ludlow Herefordshire SY8 3QP",
    "addr:housenumber":"4",
    "addr:postcode":"sy8 3qp",
    "addr:street":"The Poplars Clee Hill",
    "iso:country":"GB",
    "sg:address":"4 The Poplars, Clee Hill",
    "sg:city":"Ludlow",
    "sg:classifiers":[
        {
            "category":"Building & Trades",
            "subcategory":"Construction",
            "type":"Services"
        }
    ],
    "sg:postcode":"SY8 3QP",
    "sg:province":"Herefordshire",
    "sg:tags":[
        "decorator",
        "painter"
    ],
    "wof:name":"Price & Hughes",
    "wof:placetype":"venue"
},
  "geometry": {"coordinates":[-2.7190139294,52.3705940247],"type":"Point"}
}