{
  "type": "Feature",
  "properties": {
    "addr:full":"2 Woodbine Terr Sunderland Tyne and Wear SR4 6TY",
    "addr:housenumber":"2",
    "addr:postcode":"sr4 6ty",
    "addr:street":"Woodbine Terr",
    "iso:country":"GB",
    "sg:address":"2 Woodbine Terr",
    "sg:city":"Sunderland",
    "sg:classifiers":[
        {
            "category":"Food & Beverages",
            "subcategory":"Meat & Fish",
            "type":"Retail Goods"
        }
    ],
    "sg:phone":"+44 191 567 1277",
    "sg:postcode":"SR4 6TY",
    "sg:province":"Tyne and Wear",
    "sg:tags":[
        "butcher"
    ],
    "wof:name":"Edward Owsnett",
    "wof:placetype":"venue"
},
  "geometry": {"coordinates":[-1.42018,54.913681],"type":"Point"}
}