{
  "type": "Feature",
  "properties": {
    "iso:country":"GB",
    "sg:address":"51 Crail Close",
    "sg:city":"Wokingham",
    "sg:classifiers":[
        {
            "category":"Professional",
            "subcategory":"Computer Services",
            "type":"Services"
        }
    ],
    "sg:phone":"+44 118 978 2040",
    "sg:postcode":"RG41 2PZ",
    "sg:province":"Berkshire",
    "sg:tags":[
        "system",
        "software"
    ],
    "wof:name":"Calibre Computer Co. Ltd.",
    "wof:placetype":"venue"
},
  "geometry": {"coordinates":[-0.844687,51.39922],"type":"Point"}
}