{
  "type": "Feature",
  "properties": {
    "iso:country":"GB",
    "sg:address":"Unit 2 Amey Industrial Estate, Frenchmans Road",
    "sg:city":"Petersfield",
    "sg:classifiers":[
        {
            "category":"Home & Garden",
            "subcategory":"Household Appliances",
            "type":"Retail Goods"
        }
    ],
    "sg:phone":"+44 1730 710523",
    "sg:postcode":"GU32 3AN",
    "sg:province":"Hampshire",
    "sg:tags":[
        "refrigeration",
        "air conditioning"
    ],
    "wof:name":"H V A C (U K) Ltd.",
    "wof:placetype":"venue"
},
  "geometry": {"coordinates":[-0.935826,51.003796],"type":"Point"}
}