{
  "type": "Feature",
  "properties": {
    "addr:full":"Unit B/h Wallsend Industrial Estate, Cattedown Plymouth Devon PL4 0RW",
    "addr:postcode":"pl4 0rw",
    "addr:street":"Estate Cattedown",
    "iso:country":"GB",
    "sg:address":"Unit B/h Wallsend Industrial Estate, Cattedown",
    "sg:city":"Plymouth",
    "sg:classifiers":[
        {
            "category":"Wholesale",
            "subcategory":"Scrap",
            "type":"Manufacturing & Wholesale Goods"
        }
    ],
    "sg:phone":"+44 1752 220809",
    "sg:postcode":"PL4 0RW",
    "sg:province":"Devon",
    "sg:tags":[
        "breaker",
        "dismantlers"
    ],
    "wof:name":"R P B Auto Salvage",
    "wof:placetype":"venue"
},
  "geometry": {"coordinates":[-4.127699852,50.3677711487],"type":"Point"}
}