{
  "type": "Feature",
  "properties": {
    "addr:full":"199 Finchley Road London Greater London NW3 6NN",
    "addr:housenumber":"199",
    "addr:postcode":"nw3 6nn",
    "addr:street":"Finchley Road",
    "iso:country":"GB",
    "sg:address":"199 Finchley Road",
    "sg:city":"London",
    "sg:classifiers":[
        {
            "category":"Food & Beverages",
            "subcategory":"Supermarket",
            "type":"Retail Goods"
        }
    ],
    "sg:phone":"+44 20 7624 0453",
    "sg:postcode":"NW3 6NN",
    "sg:province":"Greater London",
    "sg:website":"http://www.waitrose.co.uk",
    "wof:name":"Waitrose Ltd",
    "wof:placetype":"venue"
},
  "geometry": {"coordinates":[-0.179634,51.546471],"type":"Point"}
}