{
  "type": "Feature",
  "properties": {
    "addr:full":"145 Bowes Road London Greater London N13 4SE",
    "addr:housenumber":"145",
    "addr:postcode":"n13 4se",
    "addr:street":"Bowes Road",
    "iso:country":"GB",
    "sg:address":"145 Bowes Road",
    "sg:city":"London",
    "sg:classifiers":[
        {
            "category":"Bakery",
            "type":"Food & Drink"
        }
    ],
    "sg:phone":"+44 20 8889 7700",
    "sg:postcode":"N13 4SE",
    "sg:province":"Greater London",
    "sg:tags":[
        "cake",
        "maker"
    ],
    "wof:name":"Piece of Cake",
    "wof:placetype":"venue"
},
  "geometry": {"coordinates":[-0.1209639981,51.6128311157],"type":"Point"}
}