{
  "type": "Feature",
  "properties": {
    "iso:country":"GB",
    "sg:address":"Suite 2 Shrieves Walk",
    "sg:city":"Stratford-upon-avon",
    "sg:classifiers":[
        {
            "category":"Real Estate",
            "subcategory":"Real Estate Operator",
            "type":"Services"
        }
    ],
    "sg:phone":"+44 1789 451045",
    "sg:postcode":"CV37 6GJ",
    "sg:province":"Warwickshire",
    "sg:tags":[
        "letting",
        "agent"
    ],
    "wof:name":"Heritage",
    "wof:placetype":"venue"
},
  "geometry": {"coordinates":[-1.7072689533,52.1941337585],"type":"Point"}
}