{
  "type": "Feature",
  "properties": {
    "iso:country":"GB",
    "sg:address":"4 Grenadier Ct, Park Rd",
    "sg:city":"Staines",
    "sg:classifiers":[
        {
            "category":"Retail",
            "subcategory":"Repair Shop",
            "type":"Services"
        }
    ],
    "sg:phone":"+44 1784 249161",
    "sg:postcode":"TW19 7NY",
    "sg:province":"Berkshire",
    "sg:tags":[
        "upholsterer"
    ],
    "wof:name":"Stitch & Stuff Upholstery",
    "wof:placetype":"venue"
},
  "geometry": {"coordinates":[-0.48454,51.45768],"type":"Point"}
}