{
  "type": "Feature",
  "properties": {
    "iso:country":"GB",
    "sg:address":"6 Sunway, Braunstone",
    "sg:city":"Leicester",
    "sg:classifiers":[
        {
            "category":"Shopping",
            "subcategory":"News",
            "type":"Retail Goods"
        }
    ],
    "sg:phone":"+44 116 289 7668",
    "sg:postcode":"LE3 3DS",
    "sg:province":"Leicestershire",
    "sg:tags":[
        "newsagent"
    ],
    "wof:name":"Sunway News",
    "wof:placetype":"venue"
},
  "geometry": {"coordinates":[-1.2073489428,52.6205101013],"type":"Point"}
}