{
  "type": "Feature",
  "properties": {
    "iso:country":"GB",
    "sg:address":"Willow Tree Farm, Colliers End",
    "sg:city":"Ware",
    "sg:classifiers":[
        {
            "category":"Sports & Exercise",
            "subcategory":"Stables",
            "type":"Entertainment"
        }
    ],
    "sg:phone":"+44 1920 821792",
    "sg:postcode":"SG11 1EN",
    "sg:province":"Hertfordshire",
    "sg:tags":[
        "equestrian",
        "centre",
        "livery",
        "schools",
        "riding",
        "education"
    ],
    "sg:website":"http://www.contessa-riding.com",
    "wof:name":"Contessa Riding Centre",
    "wof:placetype":"venue"
},
  "geometry": {"coordinates":[-0.01028,51.8675765991],"type":"Point"}
}