{
  "type": "Feature",
  "properties": {
    "addr:full":"41a Derby Road Heanor Derbyshire DE75 7QG",
    "addr:housenumber":"41a",
    "addr:postcode":"de75 7qg",
    "addr:street":"Derby Road",
    "iso:country":"GB",
    "sg:address":"41a Derby Road",
    "sg:city":"Heanor",
    "sg:classifiers":[
        {
            "category":"Professional",
            "subcategory":"Engineering",
            "type":"Services"
        }
    ],
    "sg:phone":"+44 1773 768645",
    "sg:postcode":"DE75 7QG",
    "sg:province":"Derbyshire",
    "sg:tags":[
        "consultant",
        "structural"
    ],
    "wof:name":"H M Chambers & Partners",
    "wof:placetype":"venue"
},
  "geometry": {"coordinates":[-1.358706,53.013779],"type":"Point"}
}