{
  "type": "Feature",
  "properties": {
    "addr:full":"145-157 St John Street London  EC1V 4PY ",
    "addr:housenumber":"145-157",
    "addr:postcode":"ec1v 4py",
    "addr:street":"St John Street",
    "iso:country":"GB",
    "sg:address":"145-157 St John Street",
    "sg:city":"London ",
    "sg:classifiers":[
        {
            "category":"Professional",
            "subcategory":"Computer Services",
            "type":"Services"
        }
    ],
    "sg:postcode":"EC1V 4PY ",
    "sg:tags":[
        "weight-loss",
        "bmi-calculator",
        "waist-to-hip-ratio",
        "calorie-calculator",
        "diet",
        "exercise",
        "gym",
        "fitness",
        "weight-management",
        "online-weight-tracker"
    ],
    "sg:website":"http://www.gymnag.com",
    "wof:name":"Gymnag",
    "wof:placetype":"venue"
},
  "geometry": {"coordinates":[-0.1372806,51.511266],"type":"Point"}
}