{
  "type": "Feature",
  "properties": {
    "addr:full":"Alexandra Road Swansea Neath Port Talbot SA1 5DZ",
    "addr:postcode":"sa1 5dz",
    "addr:street":"Alexandra Road",
    "iso:country":"GB",
    "sg:address":"Alexandra Road",
    "sg:city":"Swansea",
    "sg:classifiers":[
        {
            "category":"Arts & Performance",
            "subcategory":"Art Gallery",
            "type":"Entertainment"
        },
        {
            "category":"Museum",
            "subcategory":"Art Museum",
            "type":"Entertainment"
        }
    ],
    "sg:phone":"+44 1792 516900",
    "sg:postcode":"SA1 5DZ",
    "sg:province":"Neath Port Talbot",
    "sg:website":"http://www.swansea.gov.uk",
    "wof:name":"The Glynn Vivian Art Gallery",
    "wof:placetype":"venue"
},
  "geometry": {"coordinates":[-3.9419980049,51.6248664856],"type":"Point"}
}