{
  "type": "Feature",
  "properties": {
    "iso:country":"GB",
    "sg:address":"20 Whalley Place",
    "sg:city":"Lytham St Annes",
    "sg:classifiers":[
        {
            "category":"Food & Beverages",
            "subcategory":"Supermarket",
            "type":"Retail Goods"
        }
    ],
    "sg:phone":"+44 1253 727401",
    "sg:postcode":"FY8 3PU",
    "sg:province":"Lancashire",
    "wof:name":"D & D S Eastham (supermarkets) Ltd",
    "wof:placetype":"venue"
},
  "geometry": {"coordinates":[-3.002682,53.752525],"type":"Point"}
}