{
  "type": "Feature",
  "properties": {
    "addr:full":"3a Station Road, Marston Moreteyne Bedford Bedfordshire MK43 0PH",
    "addr:housenumber":"3a",
    "addr:postcode":"mk43 0ph",
    "addr:street":"Station Road;Moreteyne",
    "iso:country":"GB",
    "sg:address":"3a Station Road, Marston Moreteyne",
    "sg:city":"Bedford",
    "sg:classifiers":[
        {
            "category":"Shopping",
            "subcategory":"News",
            "type":"Retail Goods"
        }
    ],
    "sg:postcode":"MK43 0PH",
    "sg:province":"Bedfordshire",
    "sg:tags":[
        "newsagent"
    ],
    "wof:name":"A M Newsmart",
    "wof:placetype":"venue"
},
  "geometry": {"coordinates":[-0.559049,52.041435],"type":"Point"}
}