{
  "type": "Feature",
  "properties": {
    "addr:full":"54 Eastcroft Road Wolverhampton Staffordshire WV4 4NN",
    "addr:housenumber":"54",
    "addr:postcode":"wv4 4nn",
    "addr:street":"Eastcroft Road",
    "iso:country":"GB",
    "sg:address":"54 Eastcroft Road",
    "sg:city":"Wolverhampton",
    "sg:classifiers":[
        {
            "category":"Freight",
            "type":"Transportation"
        }
    ],
    "sg:phone":"+44 1902 455229",
    "sg:postcode":"WV4 4NN",
    "sg:province":"Staffordshire",
    "sg:tags":[
        "haulage",
        "road"
    ],
    "wof:name":"T M Lewis & Son",
    "wof:placetype":"venue"
},
  "geometry": {"coordinates":[-2.173099041,52.5631332397],"type":"Point"}
}