{
  "type": "Feature",
  "properties": {
    "iso:country":"GB",
    "sg:address":"Grange Motors, Llanfrechfa Way",
    "sg:city":"Cwmbran",
    "sg:classifiers":[
        {
            "category":"Retail",
            "subcategory":"Auto Repair",
            "type":"Services"
        }
    ],
    "sg:phone":"+44 1633 870460",
    "sg:postcode":"NP44 8HT",
    "sg:province":"Monmouthshire",
    "sg:tags":[
        "modification",
        "garage"
    ],
    "wof:name":"Peter Jeffries Auto Services",
    "wof:placetype":"venue"
},
  "geometry": {"coordinates":[-3.025864,51.657467],"type":"Point"}
}