{
  "type": "Feature",
  "properties": {
    "addr:full":"Portacabin, Mitchell Street London Greater London EC1V 3QD",
    "addr:postcode":"ec1v 3qd",
    "addr:street":"Mitchell Street",
    "iso:country":"GB",
    "sg:address":"Portacabin, Mitchell Street",
    "sg:city":"London",
    "sg:classifiers":[
        {
            "category":"Farming",
            "subcategory":"Nursery",
            "type":"Manufacturing & Wholesale Goods"
        }
    ],
    "sg:phone":"+44 20 7490 1790",
    "sg:postcode":"EC1V 3QD",
    "sg:province":"Greater London",
    "sg:tags":[
        "creche"
    ],
    "wof:name":"East West Community Nursery",
    "wof:placetype":"venue"
},
  "geometry": {"coordinates":[-0.09375,51.525669],"type":"Point"}
}