{
  "type": "Feature",
  "properties": {
    "iso:country":"GB",
    "sg:address":"Sanderson House, Poplar Way",
    "sg:city":"Sheffield",
    "sg:classifiers":[
        {
            "category":"Professional",
            "subcategory":"Computer Services",
            "type":"Services"
        }
    ],
    "sg:phone":"+44 1709 787787",
    "sg:postcode":"S60 5TR",
    "sg:province":"South Yorkshire",
    "sg:tags":[
        "system",
        "software"
    ],
    "wof:name":"Civica Commercial Systems Ltd.",
    "wof:placetype":"venue"
},
  "geometry": {"coordinates":[-1.36997,53.387169],"type":"Point"}
}