{
  "type": "Feature",
  "properties": {
    "addr:full":"66 Westgate Guisborough North Yorkshire TS14 6AY",
    "addr:housenumber":"66",
    "addr:postcode":"ts14 6ay",
    "addr:street":"Westgate Guisborough",
    "iso:country":"GB",
    "sg:address":"66 Westgate",
    "sg:city":"Guisborough",
    "sg:classifiers":[
        {
            "category":"Professional",
            "subcategory":"Lawyer & Legal Services",
            "type":"Services"
        }
    ],
    "sg:phone":"+44 1287 633242",
    "sg:postcode":"TS14 6AY",
    "sg:province":"North Yorkshire",
    "sg:tags":[
        "solicitor"
    ],
    "wof:name":"Atha Barton & Co.",
    "wof:placetype":"venue"
},
  "geometry": {"coordinates":[-1.0552899837,54.5349998474],"type":"Point"}
}