{
  "type": "Feature",
  "properties": {
    "addr:full":"4 Charlevelle Road London Greater London W14 9JL",
    "addr:housenumber":"4",
    "addr:postcode":"w14 9jl",
    "addr:street":"Charlevelle Road",
    "iso:country":"GB",
    "sg:address":"4 Charlevelle Road",
    "sg:city":"London",
    "sg:classifiers":[
        {
            "category":"Taxi",
            "type":"Transportation"
        }
    ],
    "sg:phone":"+44 20 7381 5254",
    "sg:postcode":"W14 9JL",
    "sg:province":"Greater London",
    "sg:tags":[
        "mini",
        "cab"
    ],
    "wof:name":"North End Cars",
    "wof:placetype":"venue"
},
  "geometry": {"coordinates":[-0.206438,51.489246],"type":"Point"}
}