{
  "type": "Feature",
  "properties": {
    "addr:full":"53-55 High Street, Whitton Twickenham Greater London TW2 7LB",
    "addr:housenumber":"53-55",
    "addr:postcode":"tw2 7lb",
    "addr:street":"High Street",
    "iso:country":"GB",
    "sg:address":"53-55 High Street, Whitton",
    "sg:city":"Twickenham",
    "sg:classifiers":[
        {
            "category":"Autos & Motor Vehicles",
            "subcategory":"Automobile Sales",
            "type":"Retail Goods"
        }
    ],
    "sg:phone":"+44 20 8894 6893",
    "sg:postcode":"TW2 7LB",
    "sg:province":"Greater London",
    "sg:tags":[
        "car"
    ],
    "wof:name":"Speedwell Garage (Whitton) Ltd.",
    "wof:placetype":"venue"
},
  "geometry": {"coordinates":[-0.357756,51.451439],"type":"Point"}
}