{
  "type": "Feature",
  "properties": {
    "addr:full":"9 Reynoldstown Lane Polegate East Sussex BN26 5HJ",
    "addr:housenumber":"9",
    "addr:postcode":"bn26 5hj",
    "addr:street":"Reynoldstown Lane",
    "iso:country":"GB",
    "sg:address":"9 Reynoldstown Lane",
    "sg:city":"Polegate",
    "sg:classifiers":[
        {
            "category":"Building & Trades",
            "subcategory":"Construction",
            "type":"Services"
        }
    ],
    "sg:phone":"+44 1323 487680",
    "sg:postcode":"BN26 5HJ",
    "sg:province":"East Sussex",
    "sg:tags":[
        "builder"
    ],
    "wof:name":"S L F Keates Builders & Decorators",
    "wof:placetype":"venue"
},
  "geometry": {"coordinates":[0.238323,50.819313],"type":"Point"}
}