{
  "type": "Feature",
  "properties": {
    "addr:full":"Sturrock Way, Bretton Peterborough Cambridgeshire PE3 8YJ",
    "addr:postcode":"pe3 8yj",
    "addr:street":"Sturrock Way",
    "iso:country":"GB",
    "sg:address":"Sturrock Way, Bretton",
    "sg:city":"Peterborough",
    "sg:classifiers":[
        {
            "category":"Autos & Motor Vehicles",
            "subcategory":"Automobile Sales",
            "type":"Retail Goods"
        }
    ],
    "sg:phone":"+44 1733 334300",
    "sg:postcode":"PE3 8YJ",
    "sg:province":"Cambridgeshire",
    "wof:name":"Hindles Ltd.",
    "wof:placetype":"venue"
},
  "geometry": {"coordinates":[-0.288839,52.6008],"type":"Point"}
}