{
  "type": "Feature",
  "properties": {
    "addr:full":"Cemaes Bay, Anglesey Cemaes Bay Isle of Anglesey LL67 0EW",
    "addr:postcode":"ll67 0ew",
    "addr:street":"Cemaes Bay",
    "iso:country":"GB",
    "sg:address":"Cemaes Bay, Anglesey",
    "sg:city":"Cemaes Bay",
    "sg:classifiers":[
        {
            "category":"Bars & Pubs",
            "type":"Food & Drink"
        }
    ],
    "sg:phone":"+44 1407 710281",
    "sg:postcode":"LL67 0EW",
    "sg:province":"Isle of Anglesey",
    "sg:tags":[
        "pubs",
        "inn"
    ],
    "wof:name":"The Stag Inn",
    "wof:placetype":"venue"
},
  "geometry": {"coordinates":[-4.451802,53.412247],"type":"Point"}
}