{
  "type": "Feature",
  "properties": {
    "iso:country":"GB",
    "sg:address":"Ross Mill Cottage, Rodley Lane",
    "sg:city":"Leeds",
    "sg:classifiers":[
        {
            "category":"Retail",
            "subcategory":"Auto Repair",
            "type":"Services"
        }
    ],
    "sg:phone":"+44 113 236 3535",
    "sg:postcode":"LS13 1BG",
    "sg:province":"West Yorkshire",
    "sg:tags":[
        "car",
        "sprayer",
        "painter"
    ],
    "wof:name":"Re-Finishers",
    "wof:placetype":"venue"
},
  "geometry": {"coordinates":[-1.661319,53.823101],"type":"Point"}
}