{
  "type": "Feature",
  "properties": {
    "addr:full":"Unit 2 Teknol House, Victoria Road Burgess Hill East Sussex RH15 9LH",
    "addr:housenumber":"unit 2 teknol house",
    "addr:postcode":"rh15 9lh",
    "addr:street":"Victoria Road",
    "iso:country":"GB",
    "sg:address":"Unit 2 Teknol House, Victoria Road",
    "sg:city":"Burgess Hill",
    "sg:classifiers":[
        {
            "category":"Professional",
            "subcategory":"Detective & Security Services",
            "type":"Services"
        }
    ],
    "sg:phone":"+44 1444 243428",
    "sg:postcode":"RH15 9LH",
    "sg:province":"East Sussex",
    "sg:tags":[
        "equipment",
        "installers"
    ],
    "wof:name":"Initial Electronic Security Systems Ltd.",
    "wof:placetype":"venue"
},
  "geometry": {"coordinates":[-0.149742,50.955669],"type":"Point"}
}