{
  "type": "Feature",
  "properties": {
    "addr:full":"Victoria Road, Draycott Derby Derbyshire DE72 3PS",
    "addr:postcode":"de72 3ps",
    "addr:street":"Victoria Road",
    "iso:country":"GB",
    "sg:address":"Victoria Road, Draycott",
    "sg:city":"Derby",
    "sg:classifiers":[
        {
            "category":"Bars & Pubs",
            "type":"Food & Drink"
        }
    ],
    "sg:phone":"+44 1332 872483",
    "sg:postcode":"DE72 3PS",
    "sg:province":"Derbyshire",
    "sg:tags":[
        "pubs",
        "inn"
    ],
    "wof:name":"Coach & Horses",
    "wof:placetype":"venue"
},
  "geometry": {"coordinates":[-1.343294,52.895134],"type":"Point"}
}