{
  "type": "Feature",
  "properties": {
    "iso:country":"GB",
    "sg:address":"96 Beulah Road",
    "sg:city":"Thornton Heath",
    "sg:classifiers":[
        {
            "category":"Retail",
            "subcategory":"Laundry & Dry Cleaning",
            "type":"Services"
        }
    ],
    "sg:phone":"+44 20 8771 3380",
    "sg:postcode":"CR7 8JF",
    "sg:province":"Surrey",
    "sg:tags":[
        "launderette"
    ],
    "wof:name":"Zaki Laundrette",
    "wof:placetype":"venue"
},
  "geometry": {"coordinates":[-0.1000209972,51.4038963318],"type":"Point"}
}