{
  "type": "Feature",
  "properties": {
    "addr:full":"130 Commercial Street Newport Newport NP20 1LY",
    "addr:housenumber":"130",
    "addr:postcode":"np20 1ly",
    "addr:street":"Commercial Street",
    "iso:country":"GB",
    "sg:address":"130 Commercial Street",
    "sg:city":"Newport",
    "sg:classifiers":[
        {
            "category":"Shopping",
            "subcategory":"Thrift Store",
            "type":"Retail Goods"
        },
        {
            "category":"Organizations",
            "subcategory":"Non-profit Organization",
            "type":"Services"
        }
    ],
    "sg:phone":"+44 1633 264228",
    "sg:postcode":"NP20 1LY",
    "sg:province":"Newport",
    "sg:tags":[
        "shop",
        "organisation",
        "voluntary",
        "charity"
    ],
    "wof:name":"Scope",
    "wof:placetype":"venue"
},
  "geometry": {"coordinates":[-2.993761,51.584087],"type":"Point"}
}