{
  "type": "Feature",
  "properties": {
    "iso:country":"GB",
    "sg:address":"30 Kings Road",
    "sg:city":"Stoke-sub-hamdon",
    "sg:classifiers":[
        {
            "category":"Building & Trades",
            "subcategory":"Construction",
            "type":"Services"
        }
    ],
    "sg:phone":"+44 1935 825340",
    "sg:postcode":"TA14 6QY",
    "sg:province":"Somerset",
    "sg:tags":[
        "builder"
    ],
    "wof:name":"W H Adams & Sons",
    "wof:placetype":"venue"
},
  "geometry": {"coordinates":[-2.7525439262,50.9595413208],"type":"Point"}
}