{
  "type": "Feature",
  "properties": {
    "addr:full":"11 Magdalen Road London Greater London SW18 3NB",
    "addr:housenumber":"11",
    "addr:postcode":"sw18 3nb",
    "addr:street":"Magdalen Road",
    "iso:country":"GB",
    "sg:address":"11 Magdalen Road",
    "sg:city":"London",
    "sg:classifiers":[
        {
            "category":"Building & Trades",
            "subcategory":"Construction",
            "type":"Services"
        }
    ],
    "sg:postcode":"SW18 3NB",
    "sg:province":"Greater London",
    "sg:tags":[
        "contractor"
    ],
    "wof:name":"Atlantek Projects Ltd.",
    "wof:placetype":"venue"
},
  "geometry": {"coordinates":[-0.17331,51.448586],"type":"Point"}
}