{
  "type": "Feature",
  "properties": {
    "addr:full":"51 Liptraps La Tunbridge Wells East Sussex TN2 3BU",
    "addr:housenumber":"51",
    "addr:postcode":"tn2 3bu",
    "addr:street":"Liptraps La Tunbridge",
    "iso:country":"GB",
    "sg:address":"51 Liptraps La",
    "sg:city":"Tunbridge Wells",
    "sg:classifiers":[
        {
            "category":"Building & Trades",
            "subcategory":"Landscaping Services",
            "type":"Services"
        }
    ],
    "sg:phone":"+44 1892 520677",
    "sg:postcode":"TN2 3BU",
    "sg:province":"East Sussex",
    "sg:tags":[
        "forestry",
        "tree"
    ],
    "wof:name":"J M Tree Surgeons",
    "wof:placetype":"venue"
},
  "geometry": {"coordinates":[0.2852799892,51.1498794556],"type":"Point"}
}