{
  "type": "Feature",
  "properties": {
    "addr:full":"41 Maidstone Road, Borough Green Sevenoaks Kent TN15 8BQ",
    "addr:housenumber":"41",
    "addr:postcode":"tn15 8bq",
    "addr:street":"Maidstone Road",
    "iso:country":"GB",
    "sg:address":"41 Maidstone Road, Borough Green",
    "sg:city":"Sevenoaks",
    "sg:classifiers":[
        {
            "category":"Retail",
            "subcategory":"Storage",
            "type":"Services"
        }
    ],
    "sg:phone":"+44 1732 882880",
    "sg:postcode":"TN15 8BQ",
    "sg:province":"Kent",
    "sg:tags":[
        "household",
        "removal"
    ],
    "wof:name":"Cast Trading Ltd.",
    "wof:placetype":"venue"
},
  "geometry": {"coordinates":[0.3288139999,51.294052124],"type":"Point"}
}