{
  "type": "Feature",
  "properties": {
    "iso:country":"GB",
    "sg:address":"Laurie Walk",
    "sg:city":"Romford",
    "sg:classifiers":[
        {
            "category":"Professional",
            "subcategory":"Computer Services",
            "type":"Services"
        }
    ],
    "sg:phone":"+44 1708 731731",
    "sg:postcode":"RM1 3RT",
    "sg:province":"Essex",
    "sg:tags":[
        "system",
        "software"
    ],
    "wof:name":"Tiny Computers Ltd.",
    "wof:placetype":"venue"
},
  "geometry": {"coordinates":[0.183982,51.579193],"type":"Point"}
}