{
  "type": "Feature",
  "properties": {
    "iso:country":"GB",
    "sg:address":"Main Street, Scropton",
    "sg:city":"Derby",
    "sg:classifiers":[
        {
            "category":"Bars & Pubs",
            "type":"Food & Drink"
        }
    ],
    "sg:phone":"+44 1283 812525",
    "sg:postcode":"DE65 5PN",
    "sg:province":"Derbyshire",
    "sg:tags":[
        "pubs",
        "inn"
    ],
    "wof:name":"Foresters Arms",
    "wof:placetype":"venue"
},
  "geometry": {"coordinates":[-1.7145040035,52.8690490723],"type":"Point"}
}