{
  "type": "Feature",
  "properties": {
    "iso:country":"GB",
    "sg:address":"12 The Fairway, Flackwell Heath",
    "sg:city":"High Wycombe",
    "sg:classifiers":[
        {
            "category":"Home & Garden",
            "subcategory":"Household Appliances",
            "type":"Retail Goods"
        },
        {
            "category":"Professional",
            "subcategory":"Computer Services",
            "type":"Services"
        }
    ],
    "sg:phone":"+44 1628 523491",
    "sg:postcode":"HP10 9NF",
    "sg:province":"Buckinghamshire",
    "sg:tags":[
        "development",
        "electrical",
        "software"
    ],
    "wof:name":"Link Services Ltd.",
    "wof:placetype":"venue"
},
  "geometry": {"coordinates":[-0.697564,51.596512],"type":"Point"}
}