{
  "type": "Feature",
  "properties": {
    "addr:full":"25 Mill Rd Milton Keynes Buckinghamshire MK2 2LB",
    "addr:housenumber":"25",
    "addr:postcode":"mk2 2lb",
    "addr:street":"Mill Rd",
    "iso:country":"GB",
    "sg:address":"25 Mill Rd",
    "sg:city":"Milton Keynes",
    "sg:classifiers":[
        {
            "category":"Professional",
            "type":"Services"
        }
    ],
    "sg:phone":"+44 1908 378143",
    "sg:postcode":"MK2 2LB",
    "sg:province":"Buckinghamshire",
    "sg:tags":[
        "shopfitters"
    ],
    "wof:name":"Henderson Falconer Ltd",
    "wof:placetype":"venue"
},
  "geometry": {"coordinates":[-0.719810009,51.9888038635],"type":"Point"}
}