{
  "type": "Feature",
  "properties": {
    "addr:full":"Hilton House, 26 Hilton St Manchester Greater Manchester M1 2EH",
    "addr:housenumber":"26",
    "addr:postcode":"m1 2eh",
    "addr:street":"Hilton St",
    "iso:country":"GB",
    "sg:address":"Hilton House, 26 Hilton St",
    "sg:city":"Manchester",
    "sg:classifiers":[
        {
            "category":"Professional",
            "subcategory":"Business Services",
            "type":"Services"
        }
    ],
    "sg:phone":"+44 161 237 1900",
    "sg:postcode":"M1 2EH",
    "sg:province":"Greater Manchester",
    "sg:tags":[
        "import",
        "export",
        "agent"
    ],
    "wof:name":"Al Bukhari Enterprises",
    "wof:placetype":"venue"
},
  "geometry": {"coordinates":[-2.231759,53.48122],"type":"Point"}
}