{
  "type": "Feature",
  "properties": {
    "addr:full":"132a Main Street, Stenhousemuir Larbert Falkirk FK5 3JF",
    "addr:housenumber":"132a",
    "addr:postcode":"fk5 3jf",
    "addr:street":"Main Street",
    "iso:country":"GB",
    "sg:address":"132a Main Street, Stenhousemuir",
    "sg:city":"Larbert",
    "sg:classifiers":[
        {
            "category":"Professional",
            "subcategory":"Computer Services",
            "type":"Services"
        }
    ],
    "sg:postcode":"FK5 3JF",
    "sg:province":"Falkirk",
    "sg:tags":[
        "system",
        "software"
    ],
    "wof:name":"Backup Information Technology Training",
    "wof:placetype":"venue"
},
  "geometry": {"coordinates":[-3.826196,56.023426],"type":"Point"}
}