{
  "type": "Feature",
  "properties": {
    "addr:full":"Langtoft Grange, Cottam Lane, Langtoft Driffield East Riding of Yorkshire YO25 3BX",
    "addr:postcode":"yo25 3bx",
    "addr:street":"Langtoft;Cottam Lane",
    "iso:country":"GB",
    "sg:address":"Langtoft Grange, Cottam Lane, Langtoft",
    "sg:city":"Driffield",
    "sg:classifiers":[
        {
            "category":"Farming",
            "subcategory":"Farm",
            "type":"Manufacturing & Wholesale Goods"
        }
    ],
    "sg:phone":"+44 1377 267247",
    "sg:postcode":"YO25 3BX",
    "sg:province":"East Riding of Yorkshire",
    "sg:tags":[
        "mixed",
        "crop"
    ],
    "wof:name":"F W & G ULLYOT",
    "wof:placetype":"venue"
},
  "geometry": {"coordinates":[-0.4571619928,54.0876464844],"type":"Point"}
}