{
  "type": "Feature",
  "properties": {
    "addr:full":"38 High St, Stock Ingatestone Essex CM4 9BW",
    "addr:housenumber":"38",
    "addr:postcode":"cm4 9bw",
    "addr:street":"High St",
    "iso:country":"GB",
    "sg:address":"38 High St, Stock",
    "sg:city":"Ingatestone",
    "sg:classifiers":[
        {
            "category":"Shopping",
            "subcategory":"Antiques",
            "type":"Retail Goods"
        }
    ],
    "sg:phone":"+44 1277 840871",
    "sg:postcode":"CM4 9BW",
    "sg:province":"Essex",
    "wof:name":"ADEM",
    "wof:placetype":"venue"
},
  "geometry": {"coordinates":[0.387154,51.672077],"type":"Point"}
}