{
  "type": "Feature",
  "properties": {
    "iso:country":"GB",
    "sg:address":"6 William St",
    "sg:city":"Cardigan",
    "sg:classifiers":[
        {
            "category":"Building & Trades",
            "subcategory":"Locksmith",
            "type":"Services"
        }
    ],
    "sg:phone":"+44 1239 612077",
    "sg:postcode":"SA43 1EL",
    "sg:province":"Ceredigion",
    "wof:name":"B Davies",
    "wof:placetype":"venue"
},
  "geometry": {"coordinates":[-4.659928,52.084332],"type":"Point"}
}