{
  "type": "Feature",
  "properties": {
    "iso:country":"GB",
    "sg:address":"Unit 2 Ascot Park Industrial Estate, Lenton Street, Sandiacre",
    "sg:city":"Nottingham",
    "sg:classifiers":[
        {
            "category":"Utilities",
            "subcategory":"Electric",
            "type":"Services"
        },
        {
            "category":"Manufacturing",
            "subcategory":"Electronics",
            "type":"Manufacturing & Wholesale Goods"
        }
    ],
    "sg:phone":"+44 115 939 0303",
    "sg:postcode":"NG10 5DJ",
    "sg:province":"Derbyshire",
    "sg:tags":[
        "mnfrs",
        "transformer",
        "manufacturer"
    ],
    "wof:name":"Laystone Ltd.",
    "wof:placetype":"venue"
},
  "geometry": {"coordinates":[-1.291806,52.926853],"type":"Point"}
}