{
  "type": "Feature",
  "properties": {
    "iso:country":"GB",
    "sg:address":"38 Castle Street, Nether Stowey",
    "sg:city":"Bridgwater",
    "sg:classifiers":[
        {
            "category":"Shopping",
            "subcategory":"Catalog Store",
            "type":"Retail Goods"
        }
    ],
    "sg:phone":"+44 1278 733630",
    "sg:postcode":"TA5 1LW",
    "sg:province":"Somerset",
    "sg:tags":[
        "mail",
        "order"
    ],
    "wof:name":"Catwork",
    "wof:placetype":"venue"
},
  "geometry": {"coordinates":[-3.158784,51.150528],"type":"Point"}
}