{
  "type": "Feature",
  "properties": {
    "addr:full":"358 Leeds Road Bradford West Yorkshire BD3 9QX",
    "addr:housenumber":"358",
    "addr:postcode":"bd3 9qx",
    "addr:street":"Leeds Road",
    "iso:country":"GB",
    "sg:address":"358 Leeds Road",
    "sg:city":"Bradford",
    "sg:classifiers":[
        {
            "category":"Home & Garden",
            "subcategory":"Home Furnishings",
            "type":"Retail Goods"
        },
        {
            "category":"Building & Trades",
            "subcategory":"Construction",
            "type":"Services"
        }
    ],
    "sg:phone":"+44 1274 731545",
    "sg:postcode":"BD3 9QX",
    "sg:province":"West Yorkshire",
    "sg:tags":[
        "mantelpiece",
        "fireplace"
    ],
    "wof:name":"Bradford Fire Surround Centre",
    "wof:placetype":"venue"
},
  "geometry": {"coordinates":[-1.738657,53.792645],"type":"Point"}
}