{
  "type": "Feature",
  "properties": {
    "iso:country":"GB",
    "sg:address":"Alderman Lacey Library, 98 Tangier Road",
    "sg:city":"Portsmouth",
    "sg:classifiers":[
        {
            "category":"Education",
            "subcategory":"Library",
            "type":"Public Place"
        },
        {
            "category":"Government",
            "subcategory":"Office",
            "type":"Public Place"
        }
    ],
    "sg:phone":"+44 23 9282 3991",
    "sg:postcode":"PO3 6HU",
    "sg:province":"Hampshire",
    "sg:tags":[
        "book",
        "local"
    ],
    "wof:name":"Alderman Lacey Library",
    "wof:placetype":"venue"
},
  "geometry": {"coordinates":[-1.0574820042,50.8078918457],"type":"Point"}
}