{
  "type": "Feature",
  "properties": {
    "iso:country":"GB",
    "sg:address":"119 Marton Road",
    "sg:city":"Middlesbrough",
    "sg:classifiers":[
        {
            "category":"Organizations",
            "subcategory":"Professional Association",
            "type":"Services"
        }
    ],
    "sg:phone":"+44 1642 244200",
    "sg:postcode":"TS1 2DU",
    "sg:province":"North Yorkshire",
    "sg:tags":[
        "union",
        "trade"
    ],
    "wof:name":"Cleveland Trade Unionist's & Unemployed Workers Resource Centre",
    "wof:placetype":"venue"
},
  "geometry": {"coordinates":[-1.226859,54.574142],"type":"Point"}
}