{
  "type": "Feature",
  "properties": {
    "iso:country":"GB",
    "sg:address":"4 Whitegate Shopping Complex, Henver Road",
    "sg:city":"Newquay",
    "sg:classifiers":[
        {
            "category":"Shopping",
            "subcategory":"Clothing, Apparel, & Fashions",
            "type":"Retail Goods"
        }
    ],
    "sg:phone":"+44 1637 851251",
    "sg:postcode":"TR7 3BP",
    "sg:province":"Cornwall",
    "sg:tags":[
        "menswear"
    ],
    "wof:name":"Rogers Menswear",
    "wof:placetype":"venue"
},
  "geometry": {"coordinates":[-5.071859,50.412086],"type":"Point"}
}