{
  "type": "Feature",
  "properties": {
    "iso:country":"GB",
    "sg:address":"Unit 15 Designer Outlet Village, Pen Y Cae La",
    "sg:city":"Bridgend",
    "sg:classifiers":[
        {
            "category":"Shopping",
            "subcategory":"Clothing, Apparel, & Fashions",
            "type":"Retail Goods"
        }
    ],
    "sg:phone":"+44 1656 660546",
    "sg:postcode":"CF32 9ST",
    "sg:province":"Bridgend",
    "sg:tags":[
        "shop"
    ],
    "wof:name":"Nicklebys",
    "wof:placetype":"venue"
},
  "geometry": {"coordinates":[-3.5773339272,51.5304450989],"type":"Point"}
}