{
  "type": "Feature",
  "properties": {
    "addr:full":"Brenda Road Hartlepool Durham TS25 2BT",
    "addr:postcode":"ts25 2bt",
    "addr:street":"Brenda Road",
    "iso:country":"GB",
    "sg:address":"Brenda Road",
    "sg:city":"Hartlepool",
    "sg:classifiers":[
        {
            "category":"Community Center",
            "type":"Public Place"
        }
    ],
    "sg:phone":"+44 1429 866999",
    "sg:postcode":"TS25 2BT",
    "sg:province":"Durham",
    "sg:tags":[
        "centre",
        "entertainment"
    ],
    "wof:name":"Auto Leisure Park Services Ltd.",
    "wof:placetype":"venue"
},
  "geometry": {"coordinates":[-1.2004640102,54.6469764709],"type":"Point"}
}