{
  "type": "Feature",
  "properties": {
    "addr:full":"Blaen Y Nant Denbigh Conwy LL16 5EP",
    "addr:postcode":"ll16 5ep",
    "addr:street":"Denbigh",
    "iso:country":"GB",
    "sg:address":"Blaen Y Nant",
    "sg:city":"Denbigh",
    "sg:classifiers":[
        {
            "category":"Farming",
            "subcategory":"Livestock Farm",
            "type":"Manufacturing & Wholesale Goods"
        }
    ],
    "sg:phone":"+44 1745 540232",
    "sg:postcode":"LL16 5EP",
    "sg:province":"Conwy",
    "sg:tags":[
        "others"
    ],
    "wof:name":"T O Roberts",
    "wof:placetype":"venue"
},
  "geometry": {"coordinates":[-3.421149,53.183411],"type":"Point"}
}