{
  "type": "Feature",
  "properties": {
    "iso:country":"GB",
    "sg:address":"60 Sparrow Hill",
    "sg:city":"Loughborough",
    "sg:classifiers":[
        {
            "category":"Autos & Motor Vehicles",
            "subcategory":"Automobile Sales",
            "type":"Retail Goods"
        },
        {
            "category":"Parking",
            "type":"Transportation"
        }
    ],
    "sg:phone":"+44 1509 213322",
    "sg:postcode":"LE11 1BU",
    "sg:province":"Leicestershire",
    "sg:tags":[
        "car",
        "valet"
    ],
    "wof:name":"MALYON JONES RETAIL CARS",
    "wof:placetype":"venue"
},
  "geometry": {"coordinates":[-1.203019,52.773678],"type":"Point"}
}