{
  "type": "Feature",
  "properties": {
    "addr:full":"102-104 South St Lancing West Sussex BN15 8AJ",
    "addr:housenumber":"102-104",
    "addr:postcode":"bn15 8aj",
    "addr:street":"South St",
    "iso:country":"GB",
    "sg:address":"102-104 South St",
    "sg:city":"Lancing",
    "sg:classifiers":[
        {
            "category":"Farming",
            "subcategory":"Farm",
            "type":"Manufacturing & Wholesale Goods"
        }
    ],
    "sg:postcode":"BN15 8AJ",
    "sg:province":"West Sussex",
    "sg:tags":[
        "agricultural"
    ],
    "wof:name":"C & D Lighting",
    "wof:placetype":"venue"
},
  "geometry": {"coordinates":[-0.3232960105,50.8238716125],"type":"Point"}
}