{
  "type": "Feature",
  "properties": {
    "addr:full":"Ivybank, Hillside Terrace Selkirk Scottish Borders TD7 4LT",
    "addr:postcode":"td7 4lt",
    "addr:street":"Hillside Terrace",
    "iso:country":"GB",
    "sg:address":"Ivybank, Hillside Terrace",
    "sg:city":"Selkirk",
    "sg:classifiers":[
        {
            "category":"Building & Trades",
            "subcategory":"Plumbing",
            "type":"Services"
        }
    ],
    "sg:postcode":"TD7 4LT",
    "sg:province":"Scottish Borders",
    "sg:tags":[
        "heating"
    ],
    "wof:name":"South East Heating Services",
    "wof:placetype":"venue"
},
  "geometry": {"coordinates":[-2.841429,55.547329],"type":"Point"}
}