{
  "type": "Feature",
  "properties": {
    "iso:country":"GB",
    "sg:address":"12a Lichfield Street",
    "sg:city":"Burton-on-trent",
    "sg:classifiers":[
        {
            "category":"Autos & Motor Vehicles",
            "subcategory":"Auto Supplies",
            "type":"Retail Goods"
        }
    ],
    "sg:phone":"+44 1283 547831",
    "sg:postcode":"DE14 3QZ",
    "sg:province":"Derbyshire",
    "sg:tags":[
        "tyre"
    ],
    "wof:name":"Tyre Sales (Birmingham) Ltd.",
    "wof:placetype":"venue"
},
  "geometry": {"coordinates":[-1.631572,52.800747],"type":"Point"}
}