{
  "type": "Feature",
  "properties": {
    "iso:country":"GB",
    "sg:address":"Knowle Hills Farm, Ingleby Lane, Ticknall",
    "sg:city":"Derby",
    "sg:classifiers":[
        {
            "category":"Farming",
            "subcategory":"Livestock Farm",
            "type":"Manufacturing & Wholesale Goods"
        }
    ],
    "sg:phone":"+44 1332 862044",
    "sg:postcode":"DE73 1JQ",
    "sg:province":"Derbyshire",
    "sg:tags":[
        "others"
    ],
    "wof:name":"S G Stanton & Son",
    "wof:placetype":"venue"
},
  "geometry": {"coordinates":[-1.476204,52.812077],"type":"Point"}
}