{
  "type": "Feature",
  "properties": {
    "addr:full":"33 Main Street, Kirkby Lonsdale Carnforth Cumbria LA6 2AH",
    "addr:housenumber":"33",
    "addr:postcode":"la6 2ah",
    "addr:street":"Main Street",
    "iso:country":"GB",
    "sg:address":"33 Main Street, Kirkby Lonsdale",
    "sg:city":"Carnforth",
    "sg:classifiers":[
        {
            "category":"Bars & Pubs",
            "type":"Food & Drink"
        },
        {
            "category":"Community Center",
            "subcategory":"Social",
            "type":"Public Place"
        }
    ],
    "sg:phone":"+44 15242 71308",
    "sg:postcode":"LA6 2AH",
    "sg:province":"Cumbria",
    "sg:tags":[
        "pubs",
        "house",
        "inn",
        "activity"
    ],
    "wof:name":"The Snooty Fox Tavern",
    "wof:placetype":"venue"
},
  "geometry": {"coordinates":[-2.597053051,54.2022094727],"type":"Point"}
}