{
  "type": "Feature",
  "properties": {
    "addr:full":"Faringdon Avenue, Harold Hill Romford Essex RM3 0AB",
    "addr:postcode":"rm3 0ab",
    "addr:street":"Faringdon Avenue Harold Hill",
    "iso:country":"GB",
    "sg:address":"Faringdon Avenue, Harold Hill",
    "sg:city":"Romford",
    "sg:classifiers":[
        {
            "category":"Professional",
            "subcategory":"Testing Lab",
            "type":"Services"
        },
        {
            "category":"Social Services",
            "subcategory":"Adult Care",
            "type":"Services"
        }
    ],
    "sg:phone":"+44 1708 371769",
    "sg:postcode":"RM3 0AB",
    "sg:province":"Essex",
    "sg:tags":[
        "centre",
        "day",
        "mot"
    ],
    "wof:name":"Faringdon Service Station",
    "wof:placetype":"venue"
},
  "geometry": {"coordinates":[0.21698,51.597149],"type":"Point"}
}