{
  "type": "Feature",
  "properties": {
    "addr:full":"Shephards Grove Industrial Estate, Stanton Bury St Edmunds Suffolk IP31 2AR",
    "addr:housenumber":"estate",
    "addr:postcode":"ip31 2ar",
    "addr:street":"Shephards Grove Industrial",
    "iso:country":"GB",
    "sg:address":"Shephards Grove Industrial Estate, Stanton",
    "sg:city":"Bury St Edmunds",
    "sg:classifiers":[
        {
            "category":"Professional",
            "subcategory":"Employment Agencies",
            "type":"Services"
        }
    ],
    "sg:postcode":"IP31 2AR",
    "sg:province":"Suffolk",
    "sg:tags":[
        "agricultural",
        "advice"
    ],
    "wof:name":"Microcide Ltd.",
    "wof:placetype":"venue"
},
  "geometry": {"coordinates":[0.882333,52.326672],"type":"Point"}
}