{
  "type": "Feature",
  "properties": {
    "addr:full":"84 Altwood Rd Maidenhead Berkshire SL6 4QB",
    "addr:housenumber":"84",
    "addr:postcode":"sl6 4qb",
    "addr:street":"Altwood Rd",
    "iso:country":"GB",
    "sg:address":"84 Altwood Rd",
    "sg:city":"Maidenhead",
    "sg:classifiers":[
        {
            "category":"Autos & Motor Vehicles",
            "subcategory":"Automobile Sales",
            "type":"Retail Goods"
        }
    ],
    "sg:phone":"+44 1494 680007",
    "sg:postcode":"SL6 4QB",
    "sg:province":"Berkshire",
    "sg:tags":[
        "commercial"
    ],
    "wof:name":"Stockbridge & McGahan Ltd",
    "wof:placetype":"venue"
},
  "geometry": {"coordinates":[-0.759213984,51.5158843994],"type":"Point"}
}