{
  "type": "Feature",
  "properties": {
    "addr:full":"Low Dowgill, North Stainmore Kirkby Stephen Cumbria CA17 4EX",
    "addr:postcode":"ca17 4ex",
    "addr:street":"North",
    "iso:country":"GB",
    "sg:address":"Low Dowgill, North Stainmore",
    "sg:city":"Kirkby Stephen",
    "sg:classifiers":[
        {
            "category":"Farming",
            "subcategory":"Livestock Farm",
            "type":"Manufacturing & Wholesale Goods"
        },
        {
            "category":"Farming",
            "subcategory":"Farm",
            "type":"Manufacturing & Wholesale Goods"
        }
    ],
    "sg:phone":"+44 17683 41686",
    "sg:postcode":"CA17 4EX",
    "sg:province":"Cumbria",
    "sg:tags":[
        "mixed",
        "crop",
        "others"
    ],
    "wof:name":"John Lord",
    "wof:placetype":"venue"
},
  "geometry": {"coordinates":[-2.348623,54.472717],"type":"Point"}
}