{
  "type": "Feature",
  "properties": {
    "addr:full":"Tame Valley Industrial Estate, Wilnecote Tamworth Staffordshire B77 5DQ",
    "addr:housenumber":"estate",
    "addr:postcode":"b77 5dq",
    "addr:street":"Tame Valley Industrial",
    "iso:country":"GB",
    "sg:address":"Tame Valley Industrial Estate, Wilnecote",
    "sg:city":"Tamworth",
    "sg:classifiers":[
        {
            "category":"Shopping",
            "subcategory":"Clothing, Apparel, & Fashions",
            "type":"Retail Goods"
        },
        {
            "category":"Utilities",
            "subcategory":"Refuse",
            "type":"Services"
        }
    ],
    "sg:phone":"+44 1827 250808",
    "sg:postcode":"B77 5DQ",
    "sg:province":"Staffordshire",
    "sg:tags":[
        "equipment",
        "workwear",
        "protective"
    ],
    "wof:name":"Hurricane Protective Clothing",
    "wof:placetype":"venue"
},
  "geometry": {"coordinates":[-1.6755119562,52.6010398865],"type":"Point"}
}