{
  "type": "Feature",
  "properties": {
    "iso:country":"GB",
    "sg:address":"76 Fir Street, Cadishead",
    "sg:city":"Manchester",
    "sg:classifiers":[
        {
            "category":"Food & Beverages",
            "subcategory":"Liquor & Beverages",
            "type":"Retail Goods"
        }
    ],
    "sg:phone":"+44 161 775 2164",
    "sg:postcode":"M44 5AG",
    "sg:province":"Greater Manchester",
    "sg:tags":[
        "beer",
        "wine",
        "spirit",
        "wines"
    ],
    "wof:name":"Fir Street Off Licence",
    "wof:placetype":"venue"
},
  "geometry": {"coordinates":[-2.44467,53.428925],"type":"Point"}
}