{
  "type": "Feature",
  "properties": {
    "addr:full":"34 Allison Street Glasgow Glasgow City G42 8NN",
    "addr:housenumber":"34",
    "addr:postcode":"g42 8nn",
    "addr:street":"Allison Street",
    "iso:country":"GB",
    "sg:address":"34 Allison Street",
    "sg:city":"Glasgow",
    "sg:classifiers":[
        {
            "category":"Autos & Motor Vehicles",
            "subcategory":"Automobile Sales",
            "type":"Retail Goods"
        }
    ],
    "sg:phone":"+44 141 424 1059",
    "sg:postcode":"G42 8NN",
    "sg:province":"Glasgow City",
    "sg:tags":[
        "car"
    ],
    "wof:name":"Park Trade Sales",
    "wof:placetype":"venue"
},
  "geometry": {"coordinates":[-4.2672519684,55.8368797302],"type":"Point"}
}