{
  "type": "Feature",
  "properties": {
    "addr:full":"2 Lupus Street London Greater London SW1V 3DY",
    "addr:housenumber":"2",
    "addr:postcode":"sw1v 3dy",
    "addr:street":"Lupus Street",
    "iso:country":"GB",
    "sg:address":"2 Lupus Street",
    "sg:city":"London",
    "sg:classifiers":[
        {
            "category":"Professional",
            "subcategory":"Art Services",
            "type":"Services"
        }
    ],
    "sg:postcode":"SW1V 3DY",
    "sg:province":"Greater London",
    "sg:tags":[
        "photographer"
    ],
    "wof:name":"Mann Bros",
    "wof:placetype":"venue"
},
  "geometry": {"coordinates":[-0.1343879998,51.4889411926],"type":"Point"}
}