{
  "type": "Feature",
  "properties": {
    "addr:full":"34-37 Liverpool Street London Greater London EC2M 7PP",
    "addr:housenumber":"34-37",
    "addr:postcode":"ec2m 7pp",
    "addr:street":"Liverpool Street",
    "iso:country":"GB",
    "sg:address":"34-37 Liverpool Street",
    "sg:city":"London",
    "sg:classifiers":[
        {
            "category":"Shopping",
            "subcategory":"Clothing, Apparel, & Fashions",
            "type":"Retail Goods"
        }
    ],
    "sg:phone":"+44 20 7929 1852",
    "sg:postcode":"EC2M 7PP",
    "sg:province":"Greater London",
    "sg:tags":[
        "shop"
    ],
    "wof:name":"Next Retail Ltd.",
    "wof:placetype":"venue"
},
  "geometry": {"coordinates":[-0.0839869976,51.5175666809],"type":"Point"}
}