{
  "type": "Feature",
  "properties": {
    "iso:country":"GB",
    "sg:address":"Saundercroft Farm, Whimple",
    "sg:city":"Exeter",
    "sg:classifiers":[
        {
            "category":"Farming",
            "subcategory":"Livestock Farm",
            "type":"Manufacturing & Wholesale Goods"
        }
    ],
    "sg:postcode":"EX5 2PF",
    "sg:province":"Devon",
    "sg:tags":[
        "others"
    ],
    "wof:name":"Elizabeth J Darbey",
    "wof:placetype":"venue"
},
  "geometry": {"coordinates":[-3.356575,50.766689],"type":"Point"}
}