{
  "type": "Feature",
  "properties": {
    "iso:country":"GB",
    "sg:address":"3rd Floor, Magdalen House, 148 Tooley Street",
    "sg:city":"London",
    "sg:classifiers":[
        {
            "category":"Professional",
            "subcategory":"Art Services",
            "type":"Services"
        }
    ],
    "sg:phone":"+44 20 7378 0146",
    "sg:postcode":"SE1 2TU",
    "sg:province":"Greater London",
    "sg:tags":[
        "consultant",
        "design"
    ],
    "wof:name":"Design Acumen Ltd.",
    "wof:placetype":"venue"
},
  "geometry": {"coordinates":[-0.0814459994,51.5038452148],"type":"Point"}
}