{
  "type": "Feature",
  "properties": {
    "iso:country":"GB",
    "sg:address":"11-13 Macklin Street",
    "sg:city":"London",
    "sg:classifiers":[
        {
            "category":"Communications",
            "subcategory":"Film & Video Production",
            "type":"Services"
        }
    ],
    "sg:phone":"+44 20 7430 9146",
    "sg:postcode":"WC2B 5NH",
    "sg:province":"Greater London",
    "sg:tags":[
        "illustrator",
        "artist"
    ],
    "wof:name":"Black Hat Ltd.",
    "wof:placetype":"venue"
},
  "geometry": {"coordinates":[-0.1228540018,51.5159225464],"type":"Point"}
}