{
  "type": "Feature",
  "properties": {
    "addr:full":"1a Chingford Mount Road, Chingford London Greater London E4 8LU",
    "addr:housenumber":"1a",
    "addr:postcode":"e4 8lu",
    "addr:street":"Chingford Mount Road",
    "iso:country":"GB",
    "sg:address":"1a Chingford Mount Road, Chingford",
    "sg:city":"London",
    "sg:classifiers":[
        {
            "category":"Retail",
            "subcategory":"Auto Repair",
            "type":"Services"
        }
    ],
    "sg:phone":"+44 20 8527 8250",
    "sg:postcode":"E4 8LU",
    "sg:province":"Greater London",
    "sg:tags":[
        "body",
        "car",
        "repairer"
    ],
    "wof:name":"T & L Motors",
    "wof:placetype":"venue"
},
  "geometry": {"coordinates":[-0.0171220005,51.6080551147],"type":"Point"}
}