{
  "type": "Feature",
  "properties": {
    "iso:country":"GB",
    "sg:address":"Kildrum Ring Road, Cumbernauld",
    "sg:city":"Glasgow",
    "sg:classifiers":[
        {
            "category":"Education",
            "subcategory":"School",
            "type":"Public Place"
        }
    ],
    "sg:phone":"+44 1236 736904",
    "sg:postcode":"G67 2EL",
    "sg:province":"Falkirk",
    "sg:tags":[
        "local",
        "authority"
    ],
    "wof:name":"Redburn School",
    "wof:placetype":"venue"
},
  "geometry": {"coordinates":[-3.9706161022,55.9563713074],"type":"Point"}
}