{
  "type": "Feature",
  "properties": {
    "iso:country":"GB",
    "sg:address":"53 The Ridgeway, Waddon",
    "sg:city":"Croydon",
    "sg:classifiers":[
        {
            "category":"Wholesale",
            "subcategory":"Machinery & Supplies",
            "type":"Manufacturing & Wholesale Goods"
        }
    ],
    "sg:postcode":"CR0 4AD",
    "sg:province":"Surrey",
    "sg:tags":[
        "control",
        "instrument",
        "industrial",
        "-"
    ],
    "wof:name":"Allard Trading Post Ltd.",
    "wof:placetype":"venue"
},
  "geometry": {"coordinates":[-0.122856,51.3703],"type":"Point"}
}