{
  "type": "Feature",
  "properties": {
    "addr:full":"Alston Works, Alston Road Keighley West Yorkshire BD21 3NF",
    "addr:postcode":"bd21 3nf",
    "addr:street":"Alston Road",
    "iso:country":"GB",
    "sg:address":"Alston Works, Alston Road",
    "sg:city":"Keighley",
    "sg:classifiers":[
        {
            "category":"Home & Garden",
            "subcategory":"Carpets & Floor Coverings",
            "type":"Retail Goods"
        }
    ],
    "sg:phone":"+44 1535 603253",
    "sg:postcode":"BD21 3NF",
    "sg:province":"West Yorkshire",
    "sg:tags":[
        "rubber",
        "plastic"
    ],
    "wof:name":"Ondura Ltd.",
    "wof:placetype":"venue"
},
  "geometry": {"coordinates":[-1.909674,53.866364],"type":"Point"}
}