{
  "type": "Feature",
  "properties": {
    "iso:country":"GB",
    "sg:address":"8a Honeybourne Road, West Hampstead",
    "sg:city":"London",
    "sg:classifiers":[
        {
            "category":"Building & Trades",
            "subcategory":"Landscaping Services",
            "type":"Services"
        }
    ],
    "sg:phone":"+44 20 7794 6723",
    "sg:postcode":"NW6 1JJ",
    "sg:province":"Greater London",
    "sg:tags":[
        "gardening"
    ],
    "wof:name":"North West Gardeners",
    "wof:placetype":"venue"
},
  "geometry": {"coordinates":[-0.190278,51.551407],"type":"Point"}
}