{
  "type": "Feature",
  "properties": {
    "addr:full":"Unit 10 Southmill Trading Centre, Southmill Road Bishops Stortford Essex CM23 3DY",
    "addr:housenumber":"unit 10",
    "addr:postcode":"cm23 3dy",
    "addr:street":"Southmill Road",
    "iso:country":"GB",
    "sg:address":"Unit 10 Southmill Trading Centre, Southmill Road",
    "sg:city":"Bishops Stortford",
    "sg:classifiers":[
        {
            "category":"Retail",
            "subcategory":"Repair Shop",
            "type":"Services"
        }
    ],
    "sg:postcode":"CM23 3DY",
    "sg:province":"Essex",
    "sg:tags":[
        "sharpening",
        "tool"
    ],
    "wof:name":"Orion Tool Repairs",
    "wof:placetype":"venue"
},
  "geometry": {"coordinates":[0.1640360057,51.8641281128],"type":"Point"}
}