{
  "type": "Feature",
  "properties": {
    "iso:country":"GB",
    "sg:address":"7 Church St",
    "sg:city":"Newent",
    "sg:classifiers":[
        {
            "category":"Organizations",
            "subcategory":"Non-profit Organization",
            "type":"Services"
        }
    ],
    "sg:phone":"+44 1531 822946",
    "sg:postcode":"GL18 1PU",
    "sg:province":"Gloucestershire",
    "sg:tags":[
        "organisation",
        "voluntary",
        "charity"
    ],
    "wof:name":"Fair Shares",
    "wof:placetype":"venue"
},
  "geometry": {"coordinates":[-2.404157,51.930511],"type":"Point"}
}