{
  "type": "Feature",
  "properties": {
    "addr:full":"37 Gyles Park Stanmore Greater London HA7 1AN",
    "addr:housenumber":"37",
    "addr:postcode":"ha7 1an",
    "addr:street":"Gyles Park",
    "iso:country":"GB",
    "sg:address":"37 Gyles Park",
    "sg:city":"Stanmore",
    "sg:classifiers":[
        {
            "category":"Retail",
            "subcategory":"Driving School",
            "type":"Services"
        }
    ],
    "sg:phone":"+44 20 8952 3834",
    "sg:postcode":"HA7 1AN",
    "sg:province":"Greater London",
    "wof:name":"Aim School Of Motoring",
    "wof:placetype":"venue"
},
  "geometry": {"coordinates":[-0.3061130047,51.6043548584],"type":"Point"}
}