{
  "type": "Feature",
  "properties": {
    "addr:full":"Roseberry Grange Golf Club, Grange Villa Chester-le-street Durham DH2 3NF",
    "addr:postcode":"dh2 3nf",
    "iso:country":"GB",
    "sg:address":"Roseberry Grange Golf Club, Grange Villa",
    "sg:city":"Chester-le-street",
    "sg:classifiers":[
        {
            "category":"Sports & Exercise",
            "subcategory":"Golf",
            "type":"Entertainment"
        }
    ],
    "sg:phone":"+44 191 370 0660",
    "sg:postcode":"DH2 3NF",
    "sg:province":"Durham",
    "sg:tags":[
        "equipment"
    ],
    "wof:name":"Hartley,Alan,",
    "wof:placetype":"venue"
},
  "geometry": {"coordinates":[-1.638739,54.861969],"type":"Point"}
}