{
  "type": "Feature",
  "properties": {
    "addr:full":"3 Birch Street Jarrow Tyne and Wear NE32 5HY",
    "addr:housenumber":"3",
    "addr:postcode":"ne32 5hy",
    "addr:street":"Birch Street",
    "iso:country":"GB",
    "sg:address":"3 Birch Street",
    "sg:city":"Jarrow",
    "sg:classifiers":[
        {
            "category":"Building & Trades",
            "subcategory":"Plumbing",
            "type":"Services"
        }
    ],
    "sg:phone":"+44 191 489 7030",
    "sg:postcode":"NE32 5HY",
    "sg:province":"Tyne and Wear",
    "sg:tags":[
        "heating"
    ],
    "wof:name":"D Matthews",
    "wof:placetype":"venue"
},
  "geometry": {"coordinates":[-1.496563,54.979851],"type":"Point"}
}