{
  "type": "Feature",
  "properties": {
    "addr:full":"Allendale Rd Newcastle Upon Tyne Tyne and Wear NE6 2SB",
    "addr:postcode":"ne6 2sb",
    "addr:street":"Allendale Rd",
    "iso:country":"GB",
    "sg:address":"Allendale Rd",
    "sg:city":"Newcastle Upon Tyne",
    "sg:classifiers":[
        {
            "category":"Health Services",
            "subcategory":"Nursing And Care Facility",
            "type":"Services"
        }
    ],
    "sg:phone":"+44 191 224 0588",
    "sg:postcode":"NE6 2SB",
    "sg:province":"Tyne and Wear",
    "sg:tags":[
        "home"
    ],
    "wof:name":"Byker Hall Nursing Home",
    "wof:placetype":"venue"
},
  "geometry": {"coordinates":[-1.5695899725,54.9730491638],"type":"Point"}
}