{
  "type": "Feature",
  "properties": {
    "addr:full":"The Promenade, Scarthin, Cromford Matlock Derbyshire DE4 3QF",
    "addr:postcode":"de4 3qf",
    "addr:street":"The Promenade Scarthin",
    "iso:country":"GB",
    "sg:address":"The Promenade, Scarthin, Cromford",
    "sg:city":"Matlock",
    "sg:classifiers":[
        {
            "category":"Shopping",
            "subcategory":"Books",
            "type":"Retail Goods"
        }
    ],
    "sg:phone":"+44 1629 823272",
    "sg:postcode":"DE4 3QF",
    "sg:province":"Derbyshire",
    "sg:tags":[
        "bookseller"
    ],
    "wof:name":"Scarthin Books",
    "wof:placetype":"venue"
},
  "geometry": {"coordinates":[-1.5482740402,53.1356163025],"type":"Point"}
}