{
  "type": "Feature",
  "properties": {
    "iso:country":"GB",
    "sg:address":"Whitepit Lodge, Philip Dr, Flackwell Heath",
    "sg:city":"High Wycombe",
    "sg:classifiers":[
        {
            "category":"Retail",
            "subcategory":"Auto Rental",
            "type":"Services"
        }
    ],
    "sg:postcode":"HP10 9JB",
    "sg:province":"Buckinghamshire",
    "sg:tags":[
        "car"
    ],
    "wof:name":"A Cheap Rent A Car",
    "wof:placetype":"venue"
},
  "geometry": {"coordinates":[-0.701705,51.593517],"type":"Point"}
}