{
  "type": "Feature",
  "properties": {
    "iso:country":"GB",
    "sg:address":"52 Linacre Close",
    "sg:city":"Norwich",
    "sg:classifiers":[
        {
            "category":"Building & Trades",
            "subcategory":"Plumbing",
            "type":"Services"
        }
    ],
    "sg:phone":"+44 1603 413758",
    "sg:postcode":"NR7 8PQ",
    "sg:province":"Norfolk",
    "sg:tags":[
        "central",
        "heating"
    ],
    "wof:name":"Broadland Heating & Plumbing",
    "wof:placetype":"venue"
},
  "geometry": {"coordinates":[1.330628,52.653973],"type":"Point"}
}