{
  "type": "Feature",
  "properties": {
    "iso:country":"GB",
    "sg:address":"57a Nolton Street",
    "sg:city":"Bridgend",
    "sg:classifiers":[
        {
            "category":"Personal",
            "subcategory":"Beauty Salon",
            "type":"Services"
        }
    ],
    "sg:phone":"+44 1656 663188",
    "sg:postcode":"CF31 3AE",
    "sg:province":"Bridgend",
    "sg:tags":[
        "unisex",
        "hairdresser"
    ],
    "wof:name":"C W 1",
    "wof:placetype":"venue"
},
  "geometry": {"coordinates":[-3.5764389038,51.5031166077],"type":"Point"}
}