{
  "type": "Feature",
  "properties": {
    "iso:country":"GB",
    "sg:address":"185 Grimsby Road",
    "sg:city":"Cleethorpes",
    "sg:classifiers":[
        {
            "category":"Food & Beverages",
            "subcategory":"Fruits & Vegetables",
            "type":"Retail Goods"
        }
    ],
    "sg:postcode":"DN35 7HB",
    "sg:province":"Lincolnshire",
    "sg:tags":[
        "greengrocer"
    ],
    "wof:name":"J R Business Promotions",
    "wof:placetype":"venue"
},
  "geometry": {"coordinates":[-0.045984,53.568474],"type":"Point"}
}