{
  "type": "Feature",
  "properties": {
    "addr:full":"Unit 4 Bus Station Concourse, Smith St Rochdale Lancashire OL16 1YG",
    "addr:housenumber":"unit 4 bus station",
    "addr:postcode":"ol16 1yg",
    "addr:street":"Concourse Smith St",
    "iso:country":"GB",
    "sg:address":"Unit 4 Bus Station Concourse, Smith St",
    "sg:city":"Rochdale",
    "sg:classifiers":[
        {
            "category":"Cafe",
            "type":"Food & Drink"
        }
    ],
    "sg:postcode":"OL16 1YG",
    "sg:province":"Lancashire",
    "sg:tags":[
        "tea",
        "room"
    ],
    "wof:name":"Fed Up Sandwich Bar",
    "wof:placetype":"venue"
},
  "geometry": {"coordinates":[-2.1546299458,53.6177101135],"type":"Point"}
}