{
  "type": "Feature",
  "properties": {
    "addr:full":"The Baytree 17 Burnaby Road Bournemouth Dorset BH4 8JF",
    "addr:housenumber":"17",
    "addr:postcode":"bh4 8jf",
    "addr:street":"Burnaby Road",
    "iso:country":"GB",
    "sg:address":"The Baytree 17 Burnaby Road",
    "sg:city":"Bournemouth",
    "sg:classifiers":[
        {
            "category":"Travel",
            "subcategory":"Hotels & Motels",
            "type":"Entertainment"
        }
    ],
    "sg:postcode":"BH4 8JF",
    "sg:province":"Dorset",
    "wof:name":"Bay Tree (Burnaby Road) Management Co. Ltd.",
    "wof:placetype":"venue"
},
  "geometry": {"coordinates":[-1.89964,50.711819],"type":"Point"}
}