{
  "type": "Feature",
  "properties": {
    "iso:country":"GB",
    "sg:address":"40 Park Crescent Rd",
    "sg:city":"Brighton",
    "sg:classifiers":[
        {
            "category":"Building & Trades",
            "subcategory":"Construction",
            "type":"Services"
        }
    ],
    "sg:phone":"+44 1273 276348",
    "sg:postcode":"BN2 3HS",
    "sg:province":"East Sussex",
    "sg:tags":[
        "joiner",
        "carpenter"
    ],
    "wof:name":"F.J Rich",
    "wof:placetype":"venue"
},
  "geometry": {"coordinates":[-0.1290159971,50.8343315125],"type":"Point"}
}