{
  "type": "Feature",
  "properties": {
    "addr:full":"482-484 Liverpool Road, Eccles Manchester Greater Manchester M30 7HZ",
    "addr:housenumber":"482-484",
    "addr:postcode":"m30 7hz",
    "addr:street":"Liverpool Road",
    "iso:country":"GB",
    "sg:address":"482-484 Liverpool Road, Eccles",
    "sg:city":"Manchester",
    "sg:classifiers":[
        {
            "category":"Real Estate",
            "subcategory":"Surveying",
            "type":"Services"
        }
    ],
    "sg:phone":"+44 161 789 8213",
    "sg:postcode":"M30 7HZ",
    "sg:province":"Greater Manchester",
    "sg:tags":[
        "surveyor",
        "quantity"
    ],
    "wof:name":"J A Magnall & Associates",
    "wof:placetype":"venue"
},
  "geometry": {"coordinates":[-2.364916,53.478806],"type":"Point"}
}