{
  "type": "Feature",
  "properties": {
    "addr:full":"North Manor Farm, Watery La Weymouth Dorset DT3 5QD",
    "addr:housenumber":"watery",
    "addr:postcode":"dt3 5qd",
    "addr:street":"La Weymouth",
    "iso:country":"GB",
    "sg:address":"North Manor Farm, Watery La",
    "sg:city":"Weymouth",
    "sg:classifiers":[
        {
            "category":"Farming",
            "subcategory":"Livestock Farm",
            "type":"Manufacturing & Wholesale Goods"
        }
    ],
    "sg:phone":"+44 1305 812431",
    "sg:postcode":"DT3 5QD",
    "sg:province":"Dorset",
    "sg:tags":[
        "others"
    ],
    "wof:name":"R Brunt",
    "wof:placetype":"venue"
},
  "geometry": {"coordinates":[-2.4749100208,50.6554718018],"type":"Point"}
}