{
  "type": "Feature",
  "properties": {
    "iso:country":"GB",
    "sg:address":"Tregarn Rd, Langstone",
    "sg:city":"Newport",
    "sg:classifiers":[
        {
            "category":"Professional",
            "subcategory":"Business Services",
            "type":"Services"
        }
    ],
    "sg:phone":"+44 1633 400683",
    "sg:postcode":"NP18 2JT",
    "sg:province":"Monmouthshire",
    "sg:tags":[
        "import",
        "export",
        "agent"
    ],
    "wof:name":"Viraghaz",
    "wof:placetype":"venue"
},
  "geometry": {"coordinates":[-2.907216,51.603886],"type":"Point"}
}