{
  "type": "Feature",
  "properties": {
    "addr:full":"Unit 9 Buckhurst Moors, North View, Amen Corner Bracknell Berkshire RG12 8TD",
    "addr:housenumber":"unit 9",
    "addr:postcode":"rg12 8td",
    "addr:street":"Buckhurst Moors North View Amen Corner",
    "iso:country":"GB",
    "sg:address":"Unit 9 Buckhurst Moors, North View, Amen Corner",
    "sg:city":"Bracknell",
    "sg:classifiers":[
        {
            "category":"Retail",
            "subcategory":"Auto Repair",
            "type":"Services"
        }
    ],
    "sg:phone":"+44 1344 869997",
    "sg:postcode":"RG12 8TD",
    "sg:province":"Berkshire",
    "sg:tags":[
        "modification",
        "garage",
        "related"
    ],
    "wof:name":"Mel's Motors",
    "wof:placetype":"venue"
},
  "geometry": {"coordinates":[-0.7875800133,51.4127807617],"type":"Point"}
}