{
  "type": "Feature",
  "properties": {
    "addr:full":"Unit 3 Twelve O'clock Court, Attercliffe Road Sheffield South Yorkshire S4 7WW",
    "addr:housenumber":"unit 3",
    "addr:postcode":"s4 7ww",
    "addr:street":"Twelve O'Clock Court Attercliffe Road",
    "iso:country":"GB",
    "sg:address":"Unit 3 Twelve O'clock Court, Attercliffe Road",
    "sg:city":"Sheffield",
    "sg:classifiers":[
        {
            "category":"Insurance",
            "subcategory":"Insurance Agent",
            "type":"Services"
        }
    ],
    "sg:phone":"+44 114 272 2423",
    "sg:postcode":"S4 7WW",
    "sg:province":"South Yorkshire",
    "wof:name":"Royal Liver Assurance Ltd.",
    "wof:placetype":"venue"
},
  "geometry": {"coordinates":[-1.4517500401,53.3900794983],"type":"Point"}
}