{
  "type": "Feature",
  "properties": {
    "addr:full":"Unit 12 Crown Close, Crown Industrial Estate Taunton Somerset TA2 8RT",
    "addr:housenumber":"unit 12",
    "addr:postcode":"ta2 8rt",
    "addr:street":"Crown Close;Industrial Estate",
    "iso:country":"GB",
    "sg:address":"Unit 12 Crown Close, Crown Industrial Estate",
    "sg:city":"Taunton",
    "sg:classifiers":[
        {
            "category":"Retail",
            "subcategory":"Repair Shop",
            "type":"Services"
        }
    ],
    "sg:phone":"+44 1823 353300",
    "sg:postcode":"TA2 8RT",
    "sg:province":"Somerset",
    "sg:tags":[
        "maintenance"
    ],
    "wof:name":"R T S Gunpoint",
    "wof:placetype":"venue"
},
  "geometry": {"coordinates":[-3.081442,51.027267],"type":"Point"}
}