{
  "type": "Feature",
  "properties": {
    "addr:full":"Galley Hill Waltham Abbey Essex EN9 2AJ",
    "addr:postcode":"en9 2aj",
    "addr:street":"Galley Hill",
    "iso:country":"GB",
    "sg:address":"Galley Hill",
    "sg:city":"Waltham Abbey",
    "sg:classifiers":[
        {
            "category":"Recreation",
            "subcategory":"Dog Park",
            "type":"Entertainment"
        }
    ],
    "sg:postcode":"EN9 2AJ",
    "sg:province":"Essex",
    "wof:name":"Stanley Kennett",
    "wof:placetype":"venue"
},
  "geometry": {"coordinates":[0.0177829992,51.6925544739],"type":"Point"}
}