{
  "type": "Feature",
  "properties": {
    "addr:full":"Nidd Ho, 9 Bond End Knaresborough North Yorkshire HG5 9AW",
    "addr:housenumber":"9",
    "addr:postcode":"hg5 9aw",
    "addr:street":"Nidd;Bond End",
    "iso:country":"GB",
    "sg:address":"Nidd Ho, 9 Bond End",
    "sg:city":"Knaresborough",
    "sg:classifiers":[
        {
            "category":"Insurance",
            "subcategory":"Insurance Agent",
            "type":"Services"
        }
    ],
    "sg:phone":"+44 1423 867650",
    "sg:postcode":"HG5 9AW",
    "sg:province":"North Yorkshire",
    "sg:tags":[
        "broker"
    ],
    "wof:name":"Baird Insurance Brokers",
    "wof:placetype":"venue"
},
  "geometry": {"coordinates":[-1.466372,54.008289],"type":"Point"}
}