{
  "type": "Feature",
  "properties": {
    "iso:country":"GB",
    "sg:address":"29 Whitegate Drive",
    "sg:city":"Blackpool",
    "sg:classifiers":[
        {
            "category":"Professional",
            "subcategory":"Lawyer & Legal Services",
            "type":"Services"
        }
    ],
    "sg:phone":"+44 1253 302933",
    "sg:postcode":"FY3 9AA",
    "sg:province":"Lancashire",
    "sg:tags":[
        "solicitor"
    ],
    "wof:name":"Baker Hoyle & Lees",
    "wof:placetype":"venue"
},
  "geometry": {"coordinates":[-3.037658,53.817356],"type":"Point"}
}