{
  "type": "Feature",
  "properties": {
    "iso:country":"GB",
    "sg:address":"Shalloch Park",
    "sg:city":"Girvan",
    "sg:classifiers":[
        {
            "category":"Professional",
            "subcategory":"Management & Consulting",
            "type":"Services"
        }
    ],
    "sg:phone":"+44 1465 713426",
    "sg:postcode":"KA26 0HW",
    "sg:province":"South Ayrshire",
    "sg:tags":[
        "consultant",
        "business"
    ],
    "wof:name":"Brendon Marketing",
    "wof:placetype":"venue"
},
  "geometry": {"coordinates":[-4.8577218056,55.2360305786],"type":"Point"}
}