{
  "type": "Feature",
  "properties": {
    "addr:full":"509 Barking Rd Plaistow Greater London E13 8PS",
    "addr:housenumber":"509",
    "addr:postcode":"e13 8ps",
    "addr:street":"Barking Rd",
    "iso:country":"GB",
    "sg:address":"509 Barking Rd",
    "sg:city":"Plaistow",
    "sg:classifiers":[
        {
            "category":"Health Services",
            "subcategory":"Doctor",
            "type":"Services"
        }
    ],
    "sg:phone":"+44 20 8470 7448",
    "sg:postcode":"E13 8PS",
    "sg:province":"Greater London",
    "sg:tags":[
        "practitioners"
    ],
    "wof:name":"Sarkar Dr I B",
    "wof:placetype":"venue"
},
  "geometry": {"coordinates":[0.028839,51.525829],"type":"Point"}
}