{
  "type": "Feature",
  "properties": {
    "iso:country":"GB",
    "sg:address":"302 Main Street",
    "sg:city":"Falkirk",
    "sg:classifiers":[
        {
            "category":"Personal",
            "subcategory":"Beauty Salon",
            "type":"Services"
        }
    ],
    "sg:phone":"+44 1324 638985",
    "sg:postcode":"FK1 4EG",
    "sg:province":"Falkirk",
    "sg:tags":[
        "unisex",
        "hairdresser"
    ],
    "wof:name":"Shona's Hair Shop",
    "wof:placetype":"venue"
},
  "geometry": {"coordinates":[-3.812865,56.003258],"type":"Point"}
}