{
  "type": "Feature",
  "properties": {
    "addr:full":"18 Trewartha Ct, Whitchurch Cardiff Cardiff CF14 1BS",
    "addr:housenumber":"18",
    "addr:postcode":"cf14 1bs",
    "addr:street":"Trewartha Ct",
    "iso:country":"GB",
    "sg:address":"18 Trewartha Ct, Whitchurch",
    "sg:city":"Cardiff",
    "sg:classifiers":[
        {
            "category":"Sports & Exercise",
            "subcategory":"Bowling",
            "type":"Entertainment"
        }
    ],
    "sg:postcode":"CF14 1BS",
    "sg:province":"Cardiff",
    "sg:tags":[
        "photography"
    ],
    "wof:name":"Thomas,Mathias,",
    "wof:placetype":"venue"
},
  "geometry": {"coordinates":[-3.218832016,51.5145606995],"type":"Point"}
}