{
  "type": "Feature",
  "properties": {
    "addr:full":"Railway Terrace, Portreath Redruth Cornwall TR16 4LD",
    "addr:postcode":"tr16 4ld",
    "addr:street":"Railway Terrace",
    "iso:country":"GB",
    "sg:address":"Railway Terrace, Portreath",
    "sg:city":"Redruth",
    "sg:classifiers":[
        {
            "category":"Farming",
            "subcategory":"Nursery",
            "type":"Manufacturing & Wholesale Goods"
        }
    ],
    "sg:phone":"+44 1209 842158",
    "sg:postcode":"TR16 4LD",
    "sg:province":"Cornwall",
    "sg:tags":[
        "creche"
    ],
    "wof:name":"Windmill Nursery School",
    "wof:placetype":"venue"
},
  "geometry": {"coordinates":[-5.290253,50.25972],"type":"Point"}
}