{
  "type": "Feature",
  "properties": {
    "addr:full":"11 Horace Rd Billericay Essex CM11 1AA",
    "addr:housenumber":"11",
    "addr:postcode":"cm11 1aa",
    "addr:street":"Horace Rd",
    "iso:country":"GB",
    "sg:address":"11 Horace Rd",
    "sg:city":"Billericay",
    "sg:classifiers":[
        {
            "category":"Building & Trades",
            "subcategory":"Construction",
            "type":"Services"
        }
    ],
    "sg:phone":"+44 1277 625386",
    "sg:postcode":"CM11 1AA",
    "sg:province":"Essex",
    "sg:tags":[
        "builder"
    ],
    "wof:name":"M G Bourne",
    "wof:placetype":"venue"
},
  "geometry": {"coordinates":[0.427098,51.634174],"type":"Point"}
}