{
  "type": "Feature",
  "properties": {
    "addr:full":"Churchgate Waltham Cross Essex EN8 9DY",
    "addr:postcode":"en8 9dy",
    "addr:street":"Churchgate Waltham Cross",
    "iso:country":"GB",
    "sg:address":"Churchgate",
    "sg:city":"Waltham Cross",
    "sg:classifiers":[
        {
            "category":"Place Of Worship",
            "type":"Public Place"
        }
    ],
    "sg:phone":"+44 1992 623121",
    "sg:postcode":"EN8 9DY",
    "sg:province":"Essex",
    "wof:name":"St Mary C Of E Church",
    "wof:placetype":"venue"
},
  "geometry": {"coordinates":[-0.0493329987,51.7064323425],"type":"Point"}
}