{
  "type": "Feature",
  "properties": {
    "iso:country":"GB",
    "sg:address":"Nutts Lane Industrial Estate",
    "sg:city":"Hinckley",
    "sg:classifiers":[
        {
            "category":"Professional",
            "subcategory":"Engineering",
            "type":"Services"
        }
    ],
    "sg:phone":"+44 1455 618373",
    "sg:postcode":"LE10 3EJ",
    "sg:province":"Leicestershire",
    "wof:name":"C W Parish Ltd.",
    "wof:placetype":"venue"
},
  "geometry": {"coordinates":[-1.397019,52.531414],"type":"Point"}
}