{
  "type": "Feature",
  "properties": {
    "iso:country":"GB",
    "sg:address":"St Nicholas Cliff",
    "sg:city":"Scarborough",
    "sg:classifiers":[
        {
            "category":"Travel",
            "subcategory":"Hotels & Motels",
            "type":"Entertainment"
        }
    ],
    "sg:phone":"+44 1723 375371",
    "sg:postcode":"YO11 2ET",
    "sg:province":"North Yorkshire",
    "wof:name":"Grand Hotel",
    "wof:placetype":"venue"
},
  "geometry": {"coordinates":[-0.398717,54.28072],"type":"Point"}
}