{
  "type": "Feature",
  "properties": {
    "addr:full":"25 Barnsdale Drive, Westcroft Milton Keynes Buckinghamshire MK4 4DD",
    "addr:housenumber":"25",
    "addr:postcode":"mk4 4dd",
    "addr:street":"Barnsdale Drive",
    "iso:country":"GB",
    "sg:address":"25 Barnsdale Drive, Westcroft",
    "sg:city":"Milton Keynes",
    "sg:classifiers":[
        {
            "category":"Fast Food",
            "type":"Food & Drink"
        },
        {
            "category":"Restaurant",
            "type":"Food & Drink"
        }
    ],
    "sg:phone":"+44 1908 501471",
    "sg:postcode":"MK4 4DD",
    "sg:province":"Buckinghamshire",
    "sg:tags":[
        "american",
        "-",
        "away",
        "take"
    ],
    "wof:name":"McDonald's Restaurants Ltd",
    "wof:placetype":"venue"
},
  "geometry": {"coordinates":[-0.7918469906,52.0049209595],"type":"Point"}
}