{
  "type": "Feature",
  "properties": {
    "addr:full":"P O Box 46 Stroud Gloucestershire GL5 2ET",
    "addr:housenumber":"box 46",
    "addr:postcode":"gl5 2et",
    "addr:street":"P O",
    "iso:country":"GB",
    "sg:address":"P O Box 46",
    "sg:city":"Stroud",
    "sg:classifiers":[
        {
            "category":"Home & Garden",
            "subcategory":"Kitchen Supply",
            "type":"Retail Goods"
        }
    ],
    "sg:phone":"+44 1453 886440",
    "sg:postcode":"GL5 2ET",
    "sg:province":"Gloucestershire",
    "sg:tags":[
        "measuring",
        "scale"
    ],
    "wof:name":"Nesslegrove Technologies Ltd.",
    "wof:placetype":"venue"
},
  "geometry": {"coordinates":[-2.1986689568,51.7259407043],"type":"Point"}
}