{
  "type": "Feature",
  "properties": {
    "addr:full":"16 King Street Bristol City of Bristol BS1 4EF",
    "addr:housenumber":"16",
    "addr:postcode":"bs1 4ef",
    "addr:street":"King Street",
    "iso:country":"GB",
    "sg:address":"16 King Street",
    "sg:city":"Bristol",
    "sg:classifiers":[
        {
            "category":"Real Estate",
            "subcategory":"Architect",
            "type":"Services"
        }
    ],
    "sg:phone":"+44 117 927 7296",
    "sg:postcode":"BS1 4EF",
    "sg:province":"City of Bristol",
    "wof:name":"Robert Elliott Hill",
    "wof:placetype":"venue"
},
  "geometry": {"coordinates":[-2.594381094,51.4517326355],"type":"Point"}
}