{
  "type": "Feature",
  "properties": {
    "addr:full":"122 The Broadway Southall Greater London UB1 1QF",
    "addr:housenumber":"122",
    "addr:postcode":"ub1 1qf",
    "addr:street":"The Broadway",
    "iso:country":"GB",
    "sg:address":"122 The Broadway",
    "sg:city":"Southall",
    "sg:classifiers":[
        {
            "category":"Shopping",
            "subcategory":"Clothing, Apparel, & Fashions",
            "type":"Retail Goods"
        },
        {
            "category":"Manufacturing",
            "subcategory":"Textiles",
            "type":"Manufacturing & Wholesale Goods"
        }
    ],
    "sg:phone":"+44 20 8843 9828",
    "sg:postcode":"UB1 1QF",
    "sg:province":"Greater London",
    "sg:tags":[
        "shop",
        "knitwear"
    ],
    "wof:name":"Middlesex Knitwear",
    "wof:placetype":"venue"
},
  "geometry": {"coordinates":[-0.3903439939,51.5131797791],"type":"Point"}
}