{
  "type": "Feature",
  "properties": {
    "iso:country":"GB",
    "sg:address":"282 Whitehouse La",
    "sg:city":"Sheffield",
    "sg:classifiers":[
        {
            "category":"Bars & Pubs",
            "type":"Food & Drink"
        }
    ],
    "sg:phone":"+44 114 234 3677",
    "sg:postcode":"S6 2WA",
    "sg:province":"South Yorkshire",
    "sg:tags":[
        "pubs",
        "inn"
    ],
    "wof:name":"Belle Vue Hotel The",
    "wof:placetype":"venue"
},
  "geometry": {"coordinates":[-1.494017005,53.3949050903],"type":"Point"}
}