{
  "type": "Feature",
  "properties": {
    "addr:full":"42 Fullarton Street Kilmarnock East Ayrshire KA1 2JJ",
    "addr:housenumber":"42",
    "addr:postcode":"ka1 2jj",
    "addr:street":"Fullarton Street",
    "iso:country":"GB",
    "sg:address":"42 Fullarton Street",
    "sg:city":"Kilmarnock",
    "sg:classifiers":[
        {
            "category":"Professional",
            "subcategory":"Art Services",
            "type":"Services"
        }
    ],
    "sg:phone":"+44 1563 530657",
    "sg:postcode":"KA1 2JJ",
    "sg:province":"East Ayrshire",
    "sg:tags":[
        "photographer"
    ],
    "wof:name":"Eyelevel Photography",
    "wof:placetype":"venue"
},
  "geometry": {"coordinates":[-4.5068101883,55.6096038818],"type":"Point"}
}