{
  "type": "Feature",
  "properties": {
    "addr:full":"96 Pontefract Lane Leeds West Yorkshire LS9 9HN",
    "addr:housenumber":"96",
    "addr:postcode":"ls9 9hn",
    "addr:street":"Pontefract Lane",
    "iso:country":"GB",
    "sg:address":"96 Pontefract Lane",
    "sg:city":"Leeds",
    "sg:classifiers":[
        {
            "category":"Bars & Pubs",
            "type":"Food & Drink"
        }
    ],
    "sg:phone":"+44 113 248 2022",
    "sg:postcode":"LS9 9HN",
    "sg:province":"West Yorkshire",
    "sg:tags":[
        "pubs",
        "inn"
    ],
    "wof:name":"Original Leisure Ltd.",
    "wof:placetype":"venue"
},
  "geometry": {"coordinates":[-1.5197370052,53.7953605652],"type":"Point"}
}