{
  "type": "Feature",
  "properties": {
    "iso:country":"GB",
    "sg:address":"29 Eastgate Row",
    "sg:city":"Chester",
    "sg:classifiers":[
        {
            "category":"Personal",
            "subcategory":"Beauty Salon",
            "type":"Services"
        }
    ],
    "sg:phone":"+44 1244 313900",
    "sg:postcode":"CH1 1LG",
    "sg:province":"Cheshire",
    "sg:tags":[
        "unisex",
        "hairdresser"
    ],
    "wof:name":"B O A",
    "wof:placetype":"venue"
},
  "geometry": {"coordinates":[-2.890524,53.19067],"type":"Point"}
}