{
  "type": "Feature",
  "properties": {
    "iso:country":"GB",
    "sg:address":"1 Rockingham Rd, Mountsorrell",
    "sg:city":"Loughborough",
    "sg:classifiers":[
        {
            "category":"Professional",
            "subcategory":"Business Services",
            "type":"Services"
        }
    ],
    "sg:phone":"+44 116 230 2495",
    "sg:postcode":"LE12 7UJ",
    "sg:province":"Leicestershire",
    "sg:tags":[
        "distribution"
    ],
    "wof:name":"Kleeneze",
    "wof:placetype":"venue"
},
  "geometry": {"coordinates":[-1.1506769657,52.719329834],"type":"Point"}
}