{
  "type": "Feature",
  "properties": {
    "addr:full":"Refinish House Leicester Leicestershire LE12 9NH",
    "addr:postcode":"le12 9nh",
    "iso:country":"GB",
    "sg:address":"Refinish House",
    "sg:city":"Leicester",
    "sg:classifiers":[
        {
            "category":"Autos & Motor Vehicles",
            "subcategory":"Auto Supplies",
            "type":"Retail Goods"
        }
    ],
    "sg:phone":"+44 1509 231898",
    "sg:postcode":"LE12 9NH",
    "sg:province":"Leicestershire",
    "sg:tags":[
        "component"
    ],
    "wof:name":"Hex Holdings Ltd.",
    "wof:placetype":"venue"
},
  "geometry": {"coordinates":[-1.301596,52.768856],"type":"Point"}
}