{
  "type": "Feature",
  "properties": {
    "addr:full":"224a Clapham Road London Greater London SW9 9BE",
    "addr:housenumber":"224a",
    "addr:postcode":"sw9 9be",
    "addr:street":"Clapham Road",
    "iso:country":"GB",
    "sg:address":"224a Clapham Road",
    "sg:city":"London",
    "sg:classifiers":[
        {
            "category":"Taxi",
            "type":"Transportation"
        }
    ],
    "sg:phone":"+44 20 7720 2111",
    "sg:postcode":"SW9 9BE",
    "sg:province":"Greater London",
    "sg:tags":[
        "mini",
        "hire",
        "cab",
        "private",
        "vehicle"
    ],
    "wof:name":"Direct Transport",
    "wof:placetype":"venue"
},
  "geometry": {"coordinates":[-0.1229000017,51.4716911316],"type":"Point"}
}