{
  "type": "Feature",
  "properties": {
    "addr:full":"Clifford Road Stanley Durham DH9 0AD",
    "addr:postcode":"dh9 0ad",
    "addr:street":"Clifford Road",
    "iso:country":"GB",
    "sg:address":"Clifford Road",
    "sg:city":"Stanley",
    "sg:classifiers":[
        {
            "category":"Organizations",
            "subcategory":"Membership Organization",
            "type":"Services"
        }
    ],
    "sg:phone":"+44 1207 232882",
    "sg:postcode":"DH9 0AD",
    "sg:province":"Durham",
    "sg:tags":[
        "club"
    ],
    "wof:name":"Stanley Central Club & Institute Ltd.",
    "wof:placetype":"venue"
},
  "geometry": {"coordinates":[-1.6903380156,54.872379303],"type":"Point"}
}