{
  "type": "Feature",
  "properties": {
    "iso:country":"GB",
    "sg:address":"Unit 3 Carthouse Offices, Cambridge Hill Farm, Cambridge Rd",
    "sg:city":"Cambridge",
    "sg:classifiers":[
        {
            "category":"Travel",
            "subcategory":"Hotels & Motels",
            "type":"Entertainment"
        }
    ],
    "sg:phone":"+44 1223 830803",
    "sg:postcode":"CB2 4AF",
    "sg:province":"Cambridgeshire",
    "wof:name":"Betta-Brew Hotels",
    "wof:placetype":"venue"
},
  "geometry": {"coordinates":[0.19246,52.1479],"type":"Point"}
}