{
  "type": "Feature",
  "properties": {
    "iso:country":"GB",
    "sg:address":"Dryden Road",
    "sg:city":"Gateshead",
    "sg:classifiers":[
        {
            "category":"Education",
            "subcategory":"School",
            "type":"Public Place"
        },
        {
            "category":"Government",
            "subcategory":"Office",
            "type":"Public Place"
        }
    ],
    "sg:phone":"+44 191 487 8233",
    "sg:postcode":"NE9 5TU",
    "sg:province":"Tyne and Wear",
    "sg:tags":[
        "local",
        "authority"
    ],
    "wof:name":"St Peter's R C (Aided) Primary School",
    "wof:placetype":"venue"
},
  "geometry": {"coordinates":[-1.597399,54.9482],"type":"Point"}
}