{
  "type": "Feature",
  "properties": {
    "addr:full":"Ivy House, Lower St, Willoughby Rugby Northamptonshire CV23 8BX",
    "addr:postcode":"cv23 8bx",
    "addr:street":"Lower St",
    "iso:country":"GB",
    "sg:address":"Ivy House, Lower St, Willoughby",
    "sg:city":"Rugby",
    "sg:classifiers":[
        {
            "category":"Organizations",
            "subcategory":"Community Association",
            "type":"Services"
        }
    ],
    "sg:phone":"+44 1788 891210",
    "sg:postcode":"CV23 8BX",
    "sg:province":"Northamptonshire",
    "sg:tags":[
        "relation",
        "public"
    ],
    "wof:name":"Laura Ridley Marketing Communications",
    "wof:placetype":"venue"
},
  "geometry": {"coordinates":[-1.235101,52.303169],"type":"Point"}
}