{
  "type": "Feature",
  "properties": {
    "iso:country":"GB",
    "sg:address":"20 Newbury Gro",
    "sg:city":"Heywood",
    "sg:classifiers":[
        {
            "category":"Building & Trades",
            "subcategory":"Plumbing",
            "type":"Services"
        }
    ],
    "sg:phone":"+44 1706 622484",
    "sg:postcode":"OL10 2PL",
    "sg:province":"Lancashire",
    "sg:tags":[
        "heating"
    ],
    "wof:name":"B Ellison Plumbing & Heating",
    "wof:placetype":"venue"
},
  "geometry": {"coordinates":[-2.2202560902,53.5840873718],"type":"Point"}
}