{
  "type": "Feature",
  "properties": {
    "addr:full":"Puckstye, Holtye Common, Cowden Edenbridge East Sussex TN8 7EL",
    "addr:postcode":"tn8 7el",
    "addr:street":"Common;Edenbridge",
    "iso:country":"GB",
    "sg:address":"Puckstye, Holtye Common, Cowden",
    "sg:city":"Edenbridge",
    "sg:classifiers":[
        {
            "category":"Organizations",
            "subcategory":"Political Organization",
            "type":"Services"
        }
    ],
    "sg:phone":"+44 1342 850285",
    "sg:postcode":"TN8 7EL",
    "sg:province":"East Sussex",
    "sg:tags":[
        "party"
    ],
    "wof:name":"Jack Stewart-Clark",
    "wof:placetype":"venue"
},
  "geometry": {"coordinates":[0.0937770009,51.1448059082],"type":"Point"}
}