{
  "type": "Feature",
  "properties": {
    "addr:full":"106 South Road, Waterloo Liverpool Merseyside L22 0ND",
    "addr:housenumber":"106",
    "addr:postcode":"l22 0nd",
    "addr:street":"South Road",
    "iso:country":"GB",
    "sg:address":"106 South Road, Waterloo",
    "sg:city":"Liverpool",
    "sg:classifiers":[
        {
            "category":"Shopping",
            "subcategory":"Thrift Store",
            "type":"Retail Goods"
        }
    ],
    "sg:phone":"+44 151 949 0493",
    "sg:postcode":"L22 0ND",
    "sg:province":"Merseyside",
    "sg:tags":[
        "shop",
        "charity"
    ],
    "wof:name":"Imperial Cancer Research Fund",
    "wof:placetype":"venue"
},
  "geometry": {"coordinates":[-3.024387,53.475498],"type":"Point"}
}