{
  "type": "Feature",
  "properties": {
    "addr:full":"West Kent Ho, Croft Rd Crowborough East Sussex TN6 1DL",
    "addr:postcode":"tn6 1dl",
    "addr:street":"Croft Rd",
    "iso:country":"GB",
    "sg:address":"West Kent Ho, Croft Rd",
    "sg:city":"Crowborough",
    "sg:classifiers":[
        {
            "category":"Professional",
            "subcategory":"Management & Consulting",
            "type":"Services"
        }
    ],
    "sg:postcode":"TN6 1DL",
    "sg:province":"East Sussex",
    "sg:tags":[
        "consultant",
        "business"
    ],
    "wof:name":"New Business Horizons Ltd",
    "wof:placetype":"venue"
},
  "geometry": {"coordinates":[0.1718930006,51.0531959534],"type":"Point"}
}