{
  "type": "Feature",
  "properties": {
    "iso:country":"GB",
    "sg:address":"1082 Christchurch, Boscombe",
    "sg:city":"Bournemouth",
    "sg:classifiers":[
        {
            "category":"Home & Garden",
            "subcategory":"Household Appliances",
            "type":"Retail Goods"
        }
    ],
    "sg:phone":"+44 1202 429984",
    "sg:postcode":"BH7 6DS",
    "sg:province":"Dorset",
    "sg:tags":[
        "cleaner",
        "domestic",
        "vacuum"
    ],
    "wof:name":"Vacuum Cleaner Spares",
    "wof:placetype":"venue"
},
  "geometry": {"coordinates":[-1.818146944,50.7340660095],"type":"Point"}
}