{
  "type": "Feature",
  "properties": {
    "addr:full":"Espen House Kirkcaldy Fife KY1 3PD",
    "addr:postcode":"ky1 3pd",
    "addr:street":"Kirkcaldy",
    "iso:country":"GB",
    "sg:address":"Espen House",
    "sg:city":"Kirkcaldy",
    "sg:classifiers":[
        {
            "category":"Wholesale",
            "subcategory":"Office Equipment",
            "type":"Manufacturing & Wholesale Goods"
        },
        {
            "category":"Shopping",
            "subcategory":"Stationery & Office Supplies",
            "type":"Retail Goods"
        }
    ],
    "sg:phone":"+44 1592 655616",
    "sg:postcode":"KY1 3PD",
    "sg:province":"Fife",
    "sg:tags":[
        "supplier",
        "furniture"
    ],
    "wof:name":"New House Office Furniture",
    "wof:placetype":"venue"
},
  "geometry": {"coordinates":[-3.1459190845,56.1341896057],"type":"Point"}
}