{
  "type": "Feature",
  "properties": {
    "iso:country":"GB",
    "sg:address":"Metro House, Woodside Road",
    "sg:city":"Amersham",
    "sg:classifiers":[
        {
            "category":"Banks & Credit Unions",
            "subcategory":"Financial Services",
            "type":"Services"
        }
    ],
    "sg:phone":"+44 1494 432611",
    "sg:postcode":"HP6 6AA",
    "sg:province":"Buckinghamshire",
    "sg:tags":[
        "consultant"
    ],
    "wof:name":"Chequers Financial Services Ltd.",
    "wof:placetype":"venue"
},
  "geometry": {"coordinates":[-0.6045039892,51.6786651611],"type":"Point"}
}