{
  "type": "Feature",
  "properties": {
    "addr:full":"144a Barrs Rd, Cradley Heath Cradley Heath West Midlands B64 7EZ",
    "addr:housenumber":"144a",
    "addr:postcode":"b64 7ez",
    "addr:street":"Barrs Rd",
    "iso:country":"GB",
    "sg:address":"144a Barrs Rd, Cradley Heath",
    "sg:city":"Cradley Heath",
    "sg:classifiers":[
        {
            "category":"Arts & Performance",
            "subcategory":"Music",
            "type":"Entertainment"
        }
    ],
    "sg:postcode":"B64 7EZ",
    "sg:province":"West Midlands",
    "sg:tags":[
        "mobile",
        "disco"
    ],
    "wof:name":"Sonic Sounds Mobile Disco",
    "wof:placetype":"venue"
},
  "geometry": {"coordinates":[-2.0655128956,52.4685974121],"type":"Point"}
}