{
  "type": "Feature",
  "properties": {
    "iso:country":"GB",
    "sg:address":"Lower Heath Waen, Knockin",
    "sg:city":"Oswestry",
    "sg:classifiers":[
        {
            "category":"Transit Center",
            "subcategory":"Passenger",
            "type":"Transportation"
        }
    ],
    "sg:phone":"+44 1691 682394",
    "sg:postcode":"SY10 8DA",
    "sg:province":"Shropshire",
    "sg:tags":[
        "taxidermist"
    ],
    "wof:name":"English Classics Hunts",
    "wof:placetype":"venue"
},
  "geometry": {"coordinates":[-2.994354,52.794407],"type":"Point"}
}