{
  "type": "Feature",
  "properties": {
    "addr:full":"Redwood House, Woodville Road, Hartshorne Swadlincote Derbyshire DE11 7ET",
    "addr:postcode":"de11 7et",
    "addr:street":"Woodville Road",
    "iso:country":"GB",
    "sg:address":"Redwood House, Woodville Road, Hartshorne",
    "sg:city":"Swadlincote",
    "sg:classifiers":[
        {
            "category":"Building & Trades",
            "subcategory":"Landscaping Services",
            "type":"Services"
        }
    ],
    "sg:phone":"+44 1283 551417",
    "sg:postcode":"DE11 7ET",
    "sg:province":"Derbyshire",
    "sg:tags":[
        "contractor",
        "sport",
        "ground"
    ],
    "wof:name":"Turfdry Ltd.",
    "wof:placetype":"venue"
},
  "geometry": {"coordinates":[-1.526178,52.776649],"type":"Point"}
}