{
  "type": "Feature",
  "properties": {
    "iso:country":"GB",
    "sg:address":"College Mains & Maryholm, College Road",
    "sg:city":"Dumfries",
    "sg:classifiers":[
        {
            "category":"Farming",
            "subcategory":"Farm",
            "type":"Manufacturing & Wholesale Goods"
        }
    ],
    "sg:postcode":"DG2 0BQ",
    "sg:province":"Dumfries and Galloway",
    "sg:tags":[
        "mixed",
        "crop"
    ],
    "wof:name":"Austin Hoggan",
    "wof:placetype":"venue"
},
  "geometry": {"coordinates":[-3.6190600395,55.0773582458],"type":"Point"}
}