{
  "type": "Feature",
  "properties": {
    "addr:full":"50 High Gate, Woodley Reading Berkshire RG5 3QR",
    "addr:housenumber":"50",
    "addr:postcode":"rg5 3qr",
    "addr:street":"High Gate",
    "iso:country":"GB",
    "sg:address":"50 High Gate, Woodley",
    "sg:city":"Reading",
    "sg:classifiers":[
        {
            "category":"Retail",
            "subcategory":"Repair Shop",
            "type":"Services"
        }
    ],
    "sg:postcode":"RG5 3QR",
    "sg:province":"Berkshire",
    "sg:tags":[
        "upholsterer"
    ],
    "wof:name":"Abacus Upholstery",
    "wof:placetype":"venue"
},
  "geometry": {"coordinates":[-0.9134389758,51.4519615173],"type":"Point"}
}