{
  "type": "Feature",
  "properties": {
    "addr:full":"Church Farm, Framingham Earl Norwich Norfolk NR14 7PE",
    "addr:postcode":"nr14 7pe",
    "iso:country":"GB",
    "sg:address":"Church Farm, Framingham Earl",
    "sg:city":"Norwich",
    "sg:classifiers":[
        {
            "category":"Farming",
            "subcategory":"Farm",
            "type":"Manufacturing & Wholesale Goods"
        }
    ],
    "sg:phone":"+44 1508 492293",
    "sg:postcode":"NR14 7PE",
    "sg:province":"Norfolk",
    "sg:tags":[
        "mixed",
        "crop"
    ],
    "wof:name":"Aldis & Sons",
    "wof:placetype":"venue"
},
  "geometry": {"coordinates":[1.3589,52.575119],"type":"Point"}
}