{
  "type": "Feature",
  "properties": {
    "iso:country":"GB",
    "sg:address":"Fisher Farm, Fisher Lane, South Mundham",
    "sg:city":"Chichester",
    "sg:classifiers":[
        {
            "category":"Farming",
            "subcategory":"Livestock Farm",
            "type":"Manufacturing & Wholesale Goods"
        }
    ],
    "sg:phone":"+44 1243 262252",
    "sg:postcode":"PO20 1ND",
    "sg:province":"West Sussex",
    "sg:tags":[
        "others"
    ],
    "wof:name":"R J Hutchings & Sons",
    "wof:placetype":"venue"
},
  "geometry": {"coordinates":[-0.76292,50.796429],"type":"Point"}
}