{
  "type": "Feature",
  "properties": {
    "addr:full":"2 Gilton House, Glenarm Road Bristol City of Bristol BS4 4LL",
    "addr:housenumber":"2",
    "addr:postcode":"bs4 4ll",
    "addr:street":"Glenarm Road",
    "iso:country":"GB",
    "sg:address":"2 Gilton House, Glenarm Road",
    "sg:city":"Bristol",
    "sg:classifiers":[
        {
            "category":"Social Services",
            "subcategory":"Adult Care",
            "type":"Services"
        },
        {
            "category":"Government",
            "subcategory":"Office",
            "type":"Public Place"
        }
    ],
    "sg:phone":"+44 117 972 1922",
    "sg:postcode":"BS4 4LL",
    "sg:province":"City of Bristol",
    "sg:tags":[
        "housing",
        "local",
        "sheltered"
    ],
    "wof:name":"Gilton House Elderly Persons Residence",
    "wof:placetype":"venue"
},
  "geometry": {"coordinates":[-2.5466899872,51.4332809448],"type":"Point"}
}