{
  "type": "Feature",
  "properties": {
    "addr:full":"Beansheaf Farm, Malton Road, Kirby Misperton Malton North Yorkshire YO17 6UE",
    "addr:postcode":"yo17 6ue",
    "addr:street":"Malton Road",
    "iso:country":"GB",
    "sg:address":"Beansheaf Farm, Malton Road, Kirby Misperton",
    "sg:city":"Malton",
    "sg:classifiers":[
        {
            "category":"Recreation",
            "subcategory":"Amusement Park",
            "type":"Entertainment"
        }
    ],
    "sg:postcode":"YO17 6UE",
    "sg:province":"North Yorkshire",
    "sg:tags":[
        "arcade"
    ],
    "wof:name":"Carousel Games",
    "wof:placetype":"venue"
},
  "geometry": {"coordinates":[-0.8065059781,54.2040061951],"type":"Point"}
}