{
  "type": "Feature",
  "properties": {
    "addr:full":"Marden Ho, Solway Av North Shields Tyne and Wear NE30 3AY",
    "addr:postcode":"ne30 3ay",
    "addr:street":"Solway Av",
    "iso:country":"GB",
    "sg:address":"Marden Ho, Solway Av",
    "sg:city":"North Shields",
    "sg:classifiers":[
        {
            "category":"Social Services",
            "type":"Services"
        }
    ],
    "sg:phone":"+44 191 200 5889",
    "sg:postcode":"NE30 3AY",
    "sg:province":"Tyne and Wear",
    "wof:name":"Mental Health Befriending & Support Worker",
    "wof:placetype":"venue"
},
  "geometry": {"coordinates":[-1.4480700493,55.0297088623],"type":"Point"}
}