{
  "type": "Feature",
  "properties": {
    "addr:full":"1-2 Ross Parade Wallington Surrey SM6 8QL",
    "addr:housenumber":"1-2",
    "addr:postcode":"sm6 8ql",
    "addr:street":"Ross Parade",
    "iso:country":"GB",
    "sg:address":"1-2 Ross Parade",
    "sg:city":"Wallington",
    "sg:classifiers":[
        {
            "category":"Government",
            "subcategory":"Post Office",
            "type":"Public Place"
        }
    ],
    "sg:phone":"+44 20 8647 4519",
    "sg:postcode":"SM6 8QL",
    "sg:province":"Surrey",
    "wof:name":"Post Office Counters Ltd.",
    "wof:placetype":"venue"
},
  "geometry": {"coordinates":[-0.1477150023,51.3604507446],"type":"Point"}
}