{
  "type": "Feature",
  "properties": {
    "iso:country":"GB",
    "sg:address":"Bullows Road, Captain Fold Road, Little Hulton",
    "sg:city":"Manchester",
    "sg:classifiers":[
        {
            "category":"Sports & Exercise",
            "subcategory":"Golf",
            "type":"Entertainment"
        }
    ],
    "sg:phone":"+44 161 790 6076",
    "sg:postcode":"M38 9TR",
    "sg:province":"Greater Manchester",
    "sg:tags":[
        "club",
        "course"
    ],
    "wof:name":"Brackley Golf Course",
    "wof:placetype":"venue"
},
  "geometry": {"coordinates":[-2.423644,53.531345],"type":"Point"}
}