{
  "type": "Feature",
  "properties": {
    "addr:full":"4 Balivanich Isle Of Benbecula Eilean Siar HS7 5LA",
    "addr:housenumber":"4",
    "addr:postcode":"hs7 5la",
    "addr:street":"Balivanich Isle",
    "iso:country":"GB",
    "sg:address":"4 Balivanich",
    "sg:city":"Isle Of Benbecula",
    "sg:classifiers":[
        {
            "category":"Organizations",
            "subcategory":"Non-profit Organization",
            "type":"Services"
        }
    ],
    "sg:phone":"+44 1870 602111",
    "sg:postcode":"HS7 5LA",
    "sg:province":"Eilean Siar",
    "sg:tags":[
        "organisation",
        "voluntary",
        "charity"
    ],
    "wof:name":"Alzheimer's Scotland",
    "wof:placetype":"venue"
},
  "geometry": {"coordinates":[-7.3627290726,57.4340705872],"type":"Point"}
}