{
  "type": "Feature",
  "properties": {
    "addr:full":"235 Staines Rd Hounslow Greater London TW3 3JJ",
    "addr:housenumber":"235",
    "addr:postcode":"tw3 3jj",
    "addr:street":"Staines Rd",
    "iso:country":"GB",
    "sg:address":"235 Staines Rd",
    "sg:city":"Hounslow",
    "sg:classifiers":[
        {
            "category":"Place Of Worship",
            "type":"Public Place"
        }
    ],
    "sg:phone":"+44 20 8570 0938",
    "sg:postcode":"TW3 3JJ",
    "sg:province":"Greater London",
    "wof:name":"Jamia Mosque",
    "wof:placetype":"venue"
},
  "geometry": {"coordinates":[-0.37625,51.465725],"type":"Point"}
}