{
  "type": "Feature",
  "properties": {
    "iso:country":"GB",
    "sg:address":"Rejarrah Farm, Rejerrah",
    "sg:city":"Newquay",
    "sg:classifiers":[
        {
            "category":"Transit Center",
            "subcategory":"Passenger",
            "type":"Transportation"
        }
    ],
    "sg:postcode":"TR8 5QD",
    "sg:province":"Cornwall",
    "sg:tags":[
        "boarding",
        "kennel",
        "catteries"
    ],
    "wof:name":"Rejerrah Farm Kennels & Cattery",
    "wof:placetype":"venue"
},
  "geometry": {"coordinates":[-5.090639,50.364574],"type":"Point"}
}