{
  "type": "Feature",
  "properties": {
    "addr:full":"Lewisham High Street London Greater London SE13 6JX",
    "addr:postcode":"se13 6jx",
    "addr:street":"Lewisham High Street",
    "iso:country":"GB",
    "sg:address":"Lewisham High Street",
    "sg:city":"London",
    "sg:classifiers":[
        {
            "category":"Professional",
            "subcategory":"Computer Services",
            "type":"Services"
        }
    ],
    "sg:postcode":"SE13 6JX",
    "sg:province":"Greater London",
    "sg:tags":[
        "system",
        "software"
    ],
    "wof:name":"I Love Computers",
    "wof:placetype":"venue"
},
  "geometry": {"coordinates":[-0.012449,51.4588356018],"type":"Point"}
}