{
  "type": "Feature",
  "properties": {
    "addr:full":"45 Cheadle Road, Cheadle Hulme Cheadle Cheshire SK8 5EU",
    "addr:housenumber":"45",
    "addr:postcode":"sk8 5eu",
    "addr:street":"Cheadle Road",
    "iso:country":"GB",
    "sg:address":"45 Cheadle Road, Cheadle Hulme",
    "sg:city":"Cheadle",
    "sg:classifiers":[
        {
            "category":"Professional",
            "subcategory":"Accounting & Tax Preparation",
            "type":"Services"
        }
    ],
    "sg:phone":"+44 161 486 9125",
    "sg:postcode":"SK8 5EU",
    "sg:province":"Cheshire",
    "sg:tags":[
        "accountant"
    ],
    "wof:name":"Salimian & Co",
    "wof:placetype":"venue"
},
  "geometry": {"coordinates":[-2.1996459961,53.3802642822],"type":"Point"}
}