{
  "type": "Feature",
  "properties": {
    "iso:country":"GB",
    "sg:address":"Chorley New Road, Horwich",
    "sg:city":"Bolton",
    "sg:classifiers":[
        {
            "category":"Education",
            "subcategory":"School",
            "type":"Public Place"
        },
        {
            "category":"Government",
            "subcategory":"Office",
            "type":"Public Place"
        }
    ],
    "sg:phone":"+44 1204 697835",
    "sg:postcode":"BL6 6EW",
    "sg:province":"Lancashire",
    "sg:tags":[
        "local",
        "authority"
    ],
    "wof:name":"Chorley New Road Primary School",
    "wof:placetype":"venue"
},
  "geometry": {"coordinates":[-2.5413789749,53.5923233032],"type":"Point"}
}