{
  "type": "Feature",
  "properties": {
    "addr:full":"Maindy Rd Pentre Rhondda, Cynon, Taff CF41 7HA",
    "addr:postcode":"cf41 7ha",
    "addr:street":"Maindy Rd;Cynon Taff",
    "iso:country":"GB",
    "sg:address":"Maindy Rd",
    "sg:city":"Pentre",
    "sg:classifiers":[
        {
            "category":"Government",
            "subcategory":"Police Station",
            "type":"Public Place"
        }
    ],
    "sg:phone":"+44 1443 434222",
    "sg:postcode":"CF41 7HA",
    "sg:province":"Rhondda, Cynon, Taff",
    "sg:tags":[
        "support",
        "force"
    ],
    "wof:name":"Ton Pentre Police Station",
    "wof:placetype":"venue"
},
  "geometry": {"coordinates":[-3.4928939342,51.6553268433],"type":"Point"}
}