{
  "type": "Feature",
  "properties": {
    "iso:country":"GB",
    "sg:address":"Heol-y-gors, Cwmgors",
    "sg:city":"Ammanford",
    "sg:classifiers":[
        {
            "category":"Wholesale",
            "subcategory":"Scrap",
            "type":"Manufacturing & Wholesale Goods"
        }
    ],
    "sg:phone":"+44 1269 826492",
    "sg:postcode":"SA18 1PE",
    "sg:province":"Carmarthenshire",
    "sg:tags":[
        "waste",
        "metal"
    ],
    "wof:name":"Adzorb-Oil",
    "wof:placetype":"venue"
},
  "geometry": {"coordinates":[-3.8799090385,51.7780189514],"type":"Point"}
}