{
  "type": "Feature",
  "properties": {
    "addr:full":"23 Holly Court Wymondham Norfolk NR18 0HG",
    "addr:housenumber":"23",
    "addr:postcode":"nr18 0hg",
    "addr:street":"Holly Court",
    "iso:country":"GB",
    "sg:address":"23 Holly Court",
    "sg:city":"Wymondham",
    "sg:classifiers":[
        {
            "category":"Manufacturing",
            "subcategory":"Lumber",
            "type":"Manufacturing & Wholesale Goods"
        }
    ],
    "sg:postcode":"NR18 0HG",
    "sg:province":"Norfolk",
    "sg:tags":[
        "importer",
        "merchants",
        "agent",
        "timber"
    ],
    "wof:name":"K J Saunders",
    "wof:placetype":"venue"
},
  "geometry": {"coordinates":[1.128931,52.57946],"type":"Point"}
}