{
  "type": "Feature",
  "properties": {
    "addr:full":"15 Temple Road Glasgow Glasgow City G13 1EL",
    "addr:housenumber":"15",
    "addr:postcode":"g13 1el",
    "addr:street":"Temple Road",
    "iso:country":"GB",
    "sg:address":"15 Temple Road",
    "sg:city":"Glasgow",
    "sg:classifiers":[
        {
            "category":"Retail",
            "subcategory":"Auto Repair",
            "type":"Services"
        }
    ],
    "sg:phone":"+44 141 959 0768",
    "sg:postcode":"G13 1EL",
    "sg:province":"Glasgow City",
    "sg:tags":[
        "modification",
        "garage",
        "related"
    ],
    "wof:name":"Gough & Tomsett Autos",
    "wof:placetype":"venue"
},
  "geometry": {"coordinates":[-4.3201651573,55.8954925537],"type":"Point"}
}