{
  "type": "Feature",
  "properties": {
    "iso:country":"GB",
    "sg:address":"Mersey Road Industrial Estate, Mersey Road North, Failsworth",
    "sg:city":"Manchester",
    "sg:classifiers":[
        {
            "category":"Manufacturing",
            "subcategory":"Building Materials",
            "type":"Manufacturing & Wholesale Goods"
        }
    ],
    "sg:phone":"+44 161 684 8882",
    "sg:postcode":"M35 9LU",
    "sg:province":"Lancashire",
    "sg:tags":[
        "merchant",
        "builder"
    ],
    "wof:name":"Bms Superfactors",
    "wof:placetype":"venue"
},
  "geometry": {"coordinates":[-2.143859,53.515079],"type":"Point"}
}