{
  "type": "Feature",
  "properties": {
    "iso:country":"GB",
    "sg:address":"16 C Whitehall Estate, Whitehall Road",
    "sg:city":"Leeds",
    "sg:classifiers":[
        {
            "category":"Retail",
            "subcategory":"Auto Repair",
            "type":"Services"
        }
    ],
    "sg:phone":"+44 113 231 1062",
    "sg:postcode":"LS12 5JB",
    "sg:province":"West Yorkshire",
    "sg:tags":[
        "modification",
        "garage"
    ],
    "wof:name":"Yorkshire Cab Centre Ltd.",
    "wof:placetype":"venue"
},
  "geometry": {"coordinates":[-1.5999770164,53.7815551758],"type":"Point"}
}