{
  "type": "Feature",
  "properties": {
    "addr:full":"High Street, Queen Camel Yeovil Dorset BA22 7NQ",
    "addr:postcode":"ba22 7nq",
    "addr:street":"High Street",
    "iso:country":"GB",
    "sg:address":"High Street, Queen Camel",
    "sg:city":"Yeovil",
    "sg:classifiers":[
        {
            "category":"Retail",
            "subcategory":"Auto Repair",
            "type":"Services"
        }
    ],
    "sg:postcode":"BA22 7NQ",
    "sg:province":"Dorset",
    "sg:tags":[
        "modification",
        "garage"
    ],
    "wof:name":"Sedna Service Station Ltd.",
    "wof:placetype":"venue"
},
  "geometry": {"coordinates":[-2.5769040585,51.0196990967],"type":"Point"}
}