{
  "type": "Feature",
  "properties": {
    "addr:full":"33 Zetland Rd Bristol City of Bristol BS6 7AH",
    "addr:housenumber":"33",
    "addr:postcode":"bs6 7ah",
    "addr:street":"Zetland Rd",
    "iso:country":"GB",
    "sg:address":"33 Zetland Rd",
    "sg:city":"Bristol",
    "sg:classifiers":[
        {
            "category":"Building & Trades",
            "subcategory":"Construction",
            "type":"Services"
        }
    ],
    "sg:phone":"+44 117 907 8600",
    "sg:postcode":"BS6 7AH",
    "sg:province":"City of Bristol",
    "sg:tags":[
        "builder"
    ],
    "wof:name":"Zenith Residential Ltd",
    "wof:placetype":"venue"
},
  "geometry": {"coordinates":[-2.6042790413,51.4791488647],"type":"Point"}
}