{
  "type": "Feature",
  "properties": {
    "addr:full":"20 Tithebarn Street Liverpool Merseyside L2 2DT",
    "addr:housenumber":"20",
    "addr:postcode":"l2 2dt",
    "addr:street":"Tithebarn Street",
    "iso:country":"GB",
    "sg:address":"20 Tithebarn Street",
    "sg:city":"Liverpool",
    "sg:classifiers":[
        {
            "category":"Banks & Credit Unions",
            "subcategory":"Financial Services",
            "type":"Services"
        }
    ],
    "sg:postcode":"L2 2DT",
    "sg:province":"Merseyside",
    "sg:tags":[
        "adviser"
    ],
    "wof:name":"Carr & Associates",
    "wof:placetype":"venue"
},
  "geometry": {"coordinates":[-2.9904448986,53.4090423584],"type":"Point"}
}