{
  "type": "Feature",
  "properties": {
    "iso:country":"GB",
    "sg:address":"The Surgery, 1 Leighton Rd",
    "sg:city":"Leighton Buzzard",
    "sg:classifiers":[
        {
            "category":"Health Services",
            "subcategory":"Doctor",
            "type":"Services"
        }
    ],
    "sg:phone":"+44 1525 372571",
    "sg:postcode":"LU7 7LA",
    "sg:province":"Bedfordshire",
    "sg:tags":[
        "practitioners"
    ],
    "wof:name":"Taylor, B",
    "wof:placetype":"venue"
},
  "geometry": {"coordinates":[-0.663909018,51.917350769],"type":"Point"}
}