{
  "type": "Feature",
  "properties": {
    "iso:country":"GB",
    "sg:address":"Sydenham Delivery Office, 4 Silverdale Sydenham",
    "sg:city":"London",
    "sg:classifiers":[
        {
            "category":"Personal",
            "type":"Services"
        }
    ],
    "sg:phone":"+44 20 8778 8371",
    "sg:postcode":"SE26 4TB",
    "sg:province":"Greater London",
    "sg:tags":[
        "delivery"
    ],
    "wof:name":"Royal Mail",
    "wof:placetype":"venue"
},
  "geometry": {"coordinates":[-0.05314,51.427208],"type":"Point"}
}