{
  "type": "Feature",
  "properties": {
    "addr:full":"108 Chiswick High Rd London Greater London W4 1PU",
    "addr:housenumber":"108",
    "addr:postcode":"w4 1pu",
    "addr:street":"Chiswick High Rd",
    "iso:country":"GB",
    "sg:address":"108 Chiswick High Rd",
    "sg:city":"London",
    "sg:classifiers":[
        {
            "category":"Professional",
            "subcategory":"Art Services",
            "type":"Services"
        }
    ],
    "sg:postcode":"W4 1PU",
    "sg:province":"Greater London",
    "sg:tags":[
        "photographer"
    ],
    "wof:name":"Cresswell Photographic Studios",
    "wof:placetype":"venue"
},
  "geometry": {"coordinates":[-0.252238,51.492977],"type":"Point"}
}