{
  "type": "Feature",
  "properties": {
    "addr:full":"54 Welbeck Street London Greater London W1G 9XS",
    "addr:housenumber":"54",
    "addr:postcode":"w1g 9xs",
    "addr:street":"Welbeck Street",
    "iso:country":"GB",
    "sg:address":"54 Welbeck Street",
    "sg:city":"London",
    "sg:classifiers":[
        {
            "category":"Fast Food",
            "type":"Food & Drink"
        }
    ],
    "sg:phone":"+44 20 7935 1339",
    "sg:postcode":"W1G 9XS",
    "sg:province":"Greater London",
    "sg:tags":[
        "away",
        "take"
    ],
    "wof:name":"Bidfort (Restaurants) Ltd.",
    "wof:placetype":"venue"
},
  "geometry": {"coordinates":[-0.149345,51.51733],"type":"Point"}
}