{
  "type": "Feature",
  "properties": {
    "iso:country":"GB",
    "sg:address":"29 Trinity Crescent",
    "sg:city":"Edinburgh",
    "sg:classifiers":[
        {
            "category":"Building & Trades",
            "subcategory":"Construction",
            "type":"Services"
        }
    ],
    "sg:postcode":"EH5 3EE",
    "sg:province":"City of Edinburgh",
    "sg:tags":[
        "dry",
        "lining",
        "plasterers",
        "screeders"
    ],
    "wof:name":"White Harmony Scotland",
    "wof:placetype":"venue"
},
  "geometry": {"coordinates":[-3.203895092,55.9799041748],"type":"Point"}
}