{
  "type": "Feature",
  "properties": {
    "iso:country":"GB",
    "sg:address":"300 Upper Richmond Road West",
    "sg:city":"London",
    "sg:classifiers":[
        {
            "category":"Home & Garden",
            "subcategory":"Hardware",
            "type":"Retail Goods"
        }
    ],
    "sg:phone":"+44 20 8878 0141",
    "sg:postcode":"SW14 7JG",
    "sg:province":"Greater London",
    "sg:tags":[
        "retailer",
        "diy"
    ],
    "wof:name":"D.I.Y. Richmond",
    "wof:placetype":"venue"
},
  "geometry": {"coordinates":[-0.2691949904,51.4643325806],"type":"Point"}
}