{
  "type": "Feature",
  "properties": {
    "iso:country":"GB",
    "sg:address":"22 Thackeray Street",
    "sg:city":"London",
    "sg:classifiers":[
        {
            "category":"Cafe",
            "type":"Food & Drink"
        }
    ],
    "sg:phone":"+44 20 7376 2212",
    "sg:postcode":"W8 5ET",
    "sg:province":"Greater London",
    "sg:tags":[
        "tea",
        "snack",
        "bar",
        "room"
    ],
    "wof:name":"Montparnasse Cafe",
    "wof:placetype":"venue"
},
  "geometry": {"coordinates":[-0.1890970021,51.500579834],"type":"Point"}
}