{
  "type": "Feature",
  "properties": {
    "addr:full":"Rear Of 85-91 Malden Road, Cheam Sutton Surrey SM3 8QU",
    "addr:housenumber":"rear of 85-91",
    "addr:postcode":"sm3 8qu",
    "addr:street":"Malden Road",
    "iso:country":"GB",
    "sg:address":"Rear Of 85-91 Malden Road, Cheam",
    "sg:city":"Sutton",
    "sg:classifiers":[
        {
            "category":"Retail",
            "subcategory":"Auto Repair",
            "type":"Services"
        }
    ],
    "sg:phone":"+44 20 8641 7309",
    "sg:postcode":"SM3 8QU",
    "sg:province":"Surrey",
    "sg:tags":[
        "modification",
        "garage"
    ],
    "wof:name":"C & P Motors",
    "wof:placetype":"venue"
},
  "geometry": {"coordinates":[-0.216711998,51.3576278687],"type":"Point"}
}