{
  "type": "Feature",
  "properties": {
    "iso:country":"GB",
    "sg:address":"20 Bridge Street",
    "sg:city":"Stockport",
    "sg:classifiers":[
        {
            "category":"Health Services",
            "subcategory":"Optometrist",
            "type":"Services"
        }
    ],
    "sg:phone":"+44 161 480 4980",
    "sg:postcode":"SK1 1XR",
    "sg:province":"Cheshire",
    "sg:tags":[
        "optician"
    ],
    "wof:name":"Maloney Opticians",
    "wof:placetype":"venue"
},
  "geometry": {"coordinates":[-2.158355,53.412189],"type":"Point"}
}