{
  "type": "Feature",
  "properties": {
    "iso:country":"GB",
    "sg:address":"9 Duffus Hill, Moreton Morrell",
    "sg:city":"Warwick",
    "sg:classifiers":[
        {
            "category":"Professional",
            "subcategory":"Printing & Photocopies",
            "type":"Services"
        },
        {
            "category":"Government",
            "subcategory":"Post Office",
            "type":"Public Place"
        }
    ],
    "sg:postcode":"CV35 9AX",
    "sg:province":"Warwickshire",
    "sg:tags":[
        "print",
        "typesetter",
        "typesetting"
    ],
    "wof:name":"Terry Maynard",
    "wof:placetype":"venue"
},
  "geometry": {"coordinates":[-1.545864,52.20208],"type":"Point"}
}