{
  "type": "Feature",
  "properties": {
    "addr:full":"P O Box 9, Washway Lane St Helens Merseyside WA10 6FE",
    "addr:housenumber":"9",
    "addr:postcode":"wa10 6fe",
    "addr:street":"P O Box;Washway Lane",
    "iso:country":"GB",
    "sg:address":"P O Box 9, Washway Lane",
    "sg:city":"St Helens",
    "sg:classifiers":[
        {
            "category":"Home & Garden",
            "subcategory":"Hardware",
            "type":"Retail Goods"
        }
    ],
    "sg:phone":"+44 1744 744744",
    "sg:postcode":"WA10 6FE",
    "sg:province":"Merseyside",
    "sg:tags":[
        "equipment",
        "heating"
    ],
    "wof:name":"Flamco Flexcon Ltd.",
    "wof:placetype":"venue"
},
  "geometry": {"coordinates":[-2.7388679981,53.4516868591],"type":"Point"}
}