{
  "type": "Feature",
  "properties": {
    "iso:country":"GB",
    "sg:address":"4 Albion Hill",
    "sg:city":"Oswestry",
    "sg:classifiers":[
        {
            "category":"Home & Garden",
            "subcategory":"Home Furnishings",
            "type":"Retail Goods"
        }
    ],
    "sg:phone":"+44 1691 654156",
    "sg:postcode":"SY11 1QA",
    "sg:province":"Shropshire",
    "sg:tags":[
        "blind",
        "curtain",
        "fitting"
    ],
    "wof:name":"Something Different",
    "wof:placetype":"venue"
},
  "geometry": {"coordinates":[-3.054415,52.860443],"type":"Point"}
}