{
  "type": "Feature",
  "properties": {
    "iso:country":"GB",
    "sg:address":"High Road, Whaplode",
    "sg:city":"Spalding",
    "sg:classifiers":[
        {
            "category":"Bars & Pubs",
            "type":"Food & Drink"
        }
    ],
    "sg:phone":"+44 1406 370521",
    "sg:postcode":"PE12 6TG",
    "sg:province":"Cambridgeshire",
    "sg:tags":[
        "pubs",
        "inn"
    ],
    "wof:name":"The Star Inn",
    "wof:placetype":"venue"
},
  "geometry": {"coordinates":[-0.070671998,52.8063964844],"type":"Point"}
}