{
  "type": "Feature",
  "properties": {
    "iso:country":"GB",
    "sg:address":"27 Victoria Park Road, St Leonards",
    "sg:city":"Exeter",
    "sg:classifiers":[
        {
            "category":"Real Estate",
            "subcategory":"Surveying",
            "type":"Services"
        }
    ],
    "sg:phone":"+44 1392 496233",
    "sg:postcode":"EX2 4NT",
    "sg:province":"Devon",
    "sg:tags":[
        "surveyor",
        "quantity"
    ],
    "wof:name":"Taylor Lewis Ltd.",
    "wof:placetype":"venue"
},
  "geometry": {"coordinates":[-3.5136868954,50.7197265625],"type":"Point"}
}