{
  "type": "Feature",
  "properties": {
    "iso:country":"GB",
    "sg:address":"16 Whitton Way",
    "sg:city":"Newport Pagnell",
    "sg:classifiers":[
        {
            "category":"Building & Trades",
            "subcategory":"Construction",
            "type":"Services"
        }
    ],
    "sg:phone":"+44 1908 582149",
    "sg:postcode":"MK16 0PS",
    "sg:province":"Buckinghamshire",
    "sg:tags":[
        "builder"
    ],
    "wof:name":"Broderick & Sons",
    "wof:placetype":"venue"
},
  "geometry": {"coordinates":[-0.7296469808,52.0816917419],"type":"Point"}
}