{
  "type": "Feature",
  "properties": {
    "addr:full":"Unit 6, Ladygrove Business Park, Gloucester Road Mitcheldean Gloucestershire GL17 0DS",
    "addr:housenumber":"unit 6",
    "addr:postcode":"gl17 0ds",
    "addr:street":"Ladygrove Business Park Gloucester Road",
    "iso:country":"GB",
    "sg:address":"Unit 6, Ladygrove Business Park, Gloucester Road",
    "sg:city":"Mitcheldean",
    "sg:classifiers":[
        {
            "category":"Manufacturing",
            "subcategory":"Metals",
            "type":"Manufacturing & Wholesale Goods"
        }
    ],
    "sg:postcode":"GL17 0DS",
    "sg:province":"Gloucestershire",
    "wof:name":"Metric Co.",
    "wof:placetype":"venue"
},
  "geometry": {"coordinates":[-2.489088,51.865383],"type":"Point"}
}