{
  "type": "Feature",
  "properties": {
    "iso:country":"GB",
    "sg:address":"East Haddon Grange, East Haddon",
    "sg:city":"Northampton",
    "sg:classifiers":[
        {
            "category":"Building & Trades",
            "subcategory":"Construction",
            "type":"Services"
        }
    ],
    "sg:phone":"+44 1604 770368",
    "sg:postcode":"NN6 8DR",
    "sg:province":"Northamptonshire",
    "sg:tags":[
        "builder"
    ],
    "wof:name":"A C Adam Developments Ltd.",
    "wof:placetype":"venue"
},
  "geometry": {"coordinates":[-1.023206,52.307194],"type":"Point"}
}