{
  "type": "Feature",
  "properties": {
    "addr:full":"636 Old Kent Road London Greater London SE15 1JE",
    "addr:housenumber":"636",
    "addr:postcode":"se15 1je",
    "addr:street":"Old Kent Road",
    "iso:country":"GB",
    "sg:address":"636 Old Kent Road",
    "sg:city":"London",
    "sg:classifiers":[
        {
            "category":"Retail",
            "subcategory":"Auto Repair",
            "type":"Services"
        }
    ],
    "sg:phone":"+44 20 7639 8761",
    "sg:postcode":"SE15 1JE",
    "sg:province":"Greater London",
    "sg:tags":[
        "engine",
        "car",
        "specialist"
    ],
    "wof:name":"Tipler Engineering Co. Ltd.",
    "wof:placetype":"venue"
},
  "geometry": {"coordinates":[-0.0639489964,51.4828033447],"type":"Point"}
}