{
  "type": "Feature",
  "properties": {
    "addr:full":"Unit 15, Wildman Road, Law Carluke South Lanarkshire ML8 5ET",
    "addr:housenumber":"unit 15",
    "addr:postcode":"ml8 5et",
    "addr:street":"Wildman Road",
    "iso:country":"GB",
    "sg:address":"Unit 15, Wildman Road, Law",
    "sg:city":"Carluke",
    "sg:classifiers":[
        {
            "category":"Professional",
            "type":"Services"
        }
    ],
    "sg:phone":"+44 1698 374413",
    "sg:postcode":"ML8 5ET",
    "sg:province":"South Lanarkshire",
    "sg:tags":[
        "repair",
        "tech",
        "maintenance"
    ],
    "wof:name":"I & A Grant",
    "wof:placetype":"venue"
},
  "geometry": {"coordinates":[-3.866797924,55.7578239441],"type":"Point"}
}