{
  "type": "Feature",
  "properties": {
    "addr:full":"130 Beeston Road Leeds West Yorkshire LS11 8BB",
    "addr:housenumber":"130",
    "addr:postcode":"ls11 8bb",
    "addr:street":"Beeston Road",
    "iso:country":"GB",
    "sg:address":"130 Beeston Road",
    "sg:city":"Leeds",
    "sg:classifiers":[
        {
            "category":"Organizations",
            "subcategory":"Membership Organization",
            "type":"Services"
        }
    ],
    "sg:phone":"+44 113 270 1939",
    "sg:postcode":"LS11 8BB",
    "sg:province":"West Yorkshire",
    "sg:tags":[
        "club",
        "social"
    ],
    "sg:website":"http://www.leedssocialclubs.co.uk/#/beeston-hill-social-club/4527883793",
    "wof:name":"Beeston Hill Social Club",
    "wof:placetype":"venue"
},
  "geometry": {"coordinates":[-1.551689,53.783428],"type":"Point"}
}