{
  "type": "Feature",
  "properties": {
    "iso:country":"GB",
    "sg:address":"38 Lombard Street",
    "sg:city":"Barry",
    "sg:classifiers":[
        {
            "category":"Retail",
            "subcategory":"Driving School",
            "type":"Services"
        }
    ],
    "sg:phone":"+44 1446 743396",
    "sg:postcode":"CF62 8DQ",
    "sg:province":"The Vale of Glamorgan",
    "wof:name":"Cindy's School of Motoring",
    "wof:placetype":"venue"
},
  "geometry": {"coordinates":[-3.271784,51.405796],"type":"Point"}
}