{
  "type": "Feature",
  "properties": {
    "addr:full":"Unit 4, 29 St Johns Road Huddersfield West Yorkshire HD1 5BW",
    "addr:housenumber":"unit;29",
    "addr:postcode":"hd1 5bw",
    "addr:street":"St Johns Road",
    "iso:country":"GB",
    "sg:address":"Unit 4, 29 St Johns Road",
    "sg:city":"Huddersfield",
    "sg:classifiers":[
        {
            "category":"Manufacturing",
            "subcategory":"Textiles",
            "type":"Manufacturing & Wholesale Goods"
        }
    ],
    "sg:phone":"+44 1484 431700",
    "sg:postcode":"HD1 5BW",
    "sg:province":"West Yorkshire",
    "sg:tags":[
        "mnfr",
        "rug",
        "carpet"
    ],
    "wof:name":"Tassels Partnership",
    "wof:placetype":"venue"
},
  "geometry": {"coordinates":[-1.784129,53.650791],"type":"Point"}
}