{
  "type": "Feature",
  "properties": {
    "iso:country":"GB",
    "sg:address":"Carisbrooke Lodge",
    "sg:city":"Bristol",
    "sg:classifiers":[
        {
            "category":"Education",
            "subcategory":"Special Training",
            "type":"Public Place"
        }
    ],
    "sg:phone":"+44 117 973 6875",
    "sg:postcode":"BS6 7JE",
    "sg:province":"City of Bristol",
    "sg:tags":[
        "school"
    ],
    "wof:name":"St.Christopher's School (Bristol)",
    "wof:placetype":"venue"
},
  "geometry": {"coordinates":[-2.61428,51.476601],"type":"Point"}
}