{
  "type": "Feature",
  "properties": {
    "iso:country":"GB",
    "sg:address":"Cuckmans Farm, Ragged Hall La",
    "sg:city":"St Albans",
    "sg:classifiers":[
        {
            "category":"Farming",
            "subcategory":"Livestock Farm",
            "type":"Manufacturing & Wholesale Goods"
        }
    ],
    "sg:postcode":"AL2 3NP",
    "sg:province":"Hertfordshire",
    "sg:tags":[
        "others"
    ],
    "wof:name":"Pope,Francis J,",
    "wof:placetype":"venue"
},
  "geometry": {"coordinates":[-0.36495,51.734051],"type":"Point"}
}