{
  "type": "Feature",
  "properties": {
    "addr:full":"477 Roman Road London Greater London E3 5LX",
    "addr:housenumber":"477",
    "addr:postcode":"e3 5lx",
    "addr:street":"Roman Road",
    "iso:country":"GB",
    "sg:address":"477 Roman Road",
    "sg:city":"London",
    "sg:classifiers":[
        {
            "category":"Building & Trades",
            "subcategory":"Landscaping Services",
            "type":"Services"
        },
        {
            "category":"Shopping",
            "subcategory":"Pets & Pet Supplies",
            "type":"Retail Goods"
        }
    ],
    "sg:phone":"+44 20 8980 4959",
    "sg:postcode":"E3 5LX",
    "sg:province":"Greater London",
    "sg:tags":[
        "supplier",
        "pond",
        "aquarium"
    ],
    "wof:name":"T & L Aqua World",
    "wof:placetype":"venue"
},
  "geometry": {"coordinates":[-0.034345,51.532154],"type":"Point"}
}