{
  "type": "Feature",
  "properties": {
    "addr:full":"Harrison Street Rotherham South Yorkshire S61 1EE",
    "addr:postcode":"s61 1ee",
    "addr:street":"Harrison Street",
    "iso:country":"GB",
    "sg:address":"Harrison Street",
    "sg:city":"Rotherham",
    "sg:classifiers":[
        {
            "category":"Professional",
            "subcategory":"Engineering",
            "type":"Services"
        }
    ],
    "sg:phone":"+44 1709 561617",
    "sg:postcode":"S61 1EE",
    "sg:province":"South Yorkshire",
    "wof:name":"The Paramo Tools Group Ltd.",
    "wof:placetype":"venue"
},
  "geometry": {"coordinates":[-1.3832540512,53.4289398193],"type":"Point"}
}