{
  "type": "Feature",
  "properties": {
    "addr:full":"3 Hough Lane, Wombwell Barnsley South Yorkshire S73 0DP",
    "addr:housenumber":"3",
    "addr:postcode":"s73 0dp",
    "addr:street":"Hough Lane;Yorkshire",
    "iso:country":"GB",
    "sg:address":"3 Hough Lane, Wombwell",
    "sg:city":"Barnsley",
    "sg:classifiers":[
        {
            "category":"Personal",
            "subcategory":"Beauty Salon",
            "type":"Services"
        },
        {
            "category":"Personal",
            "subcategory":"Barber",
            "type":"Services"
        }
    ],
    "sg:phone":"+44 1226 759330",
    "sg:postcode":"S73 0DP",
    "sg:province":"South Yorkshire",
    "sg:tags":[
        "unisex",
        "hairdresser"
    ],
    "wof:name":"Korner Kuts",
    "wof:placetype":"venue"
},
  "geometry": {"coordinates":[-1.400729,53.52002],"type":"Point"}
}