{
  "type": "Feature",
  "properties": {
    "addr:full":"61 King Street Belper Derbyshire DE56 1QA",
    "addr:housenumber":"61",
    "addr:postcode":"de56 1qa",
    "addr:street":"King Street",
    "iso:country":"GB",
    "sg:address":"61 King Street",
    "sg:city":"Belper",
    "sg:classifiers":[
        {
            "category":"Cafe",
            "type":"Food & Drink"
        }
    ],
    "sg:phone":"+44 1773 828800",
    "sg:postcode":"DE56 1QA",
    "sg:province":"Derbyshire",
    "sg:tags":[
        "tea",
        "room"
    ],
    "wof:name":"The Green Room Restaurants Ltd.",
    "wof:placetype":"venue"
},
  "geometry": {"coordinates":[-1.479848,53.02346],"type":"Point"}
}