{
  "type": "Feature",
  "properties": {
    "addr:full":"11 Hermitage Lane Mansfield Nottinghamshire NG18 5HB",
    "addr:housenumber":"11",
    "addr:postcode":"ng18 5hb",
    "addr:street":"Hermitage Lane",
    "iso:country":"GB",
    "sg:address":"11 Hermitage Lane",
    "sg:city":"Mansfield",
    "sg:classifiers":[
        {
            "category":"Manufacturing",
            "subcategory":"Furniture",
            "type":"Manufacturing & Wholesale Goods"
        }
    ],
    "sg:phone":"+44 1623 654165",
    "sg:postcode":"NG18 5HB",
    "sg:province":"Nottinghamshire",
    "sg:tags":[
        "mnfr",
        "upholsterer"
    ],
    "wof:name":"T.W Marsh",
    "wof:placetype":"venue"
},
  "geometry": {"coordinates":[-1.216144,53.136177],"type":"Point"}
}