{
  "type": "Feature",
  "properties": {
    "iso:country":"GB",
    "sg:address":"5 Teme Court, Teme Street",
    "sg:city":"Tenbury Wells",
    "sg:classifiers":[
        {
            "category":"Home & Garden",
            "subcategory":"Building Materials",
            "type":"Retail Goods"
        }
    ],
    "sg:phone":"+44 1584 819399",
    "sg:postcode":"WR15 8AA",
    "sg:province":"Herefordshire",
    "sg:tags":[
        "hinge"
    ],
    "wof:name":"N G Automatics Ltd.",
    "wof:placetype":"venue"
},
  "geometry": {"coordinates":[-2.593921,52.311554],"type":"Point"}
}