{
  "type": "Feature",
  "properties": {
    "addr:full":"133 West Street Crewe Cheshire CW1 3HH",
    "addr:housenumber":"133",
    "addr:postcode":"cw1 3hh",
    "addr:street":"West Street",
    "iso:country":"GB",
    "sg:address":"133 West Street",
    "sg:city":"Crewe",
    "sg:classifiers":[
        {
            "category":"Fast Food",
            "type":"Food & Drink"
        }
    ],
    "sg:phone":"+44 1270 211530",
    "sg:postcode":"CW1 3HH",
    "sg:province":"Cheshire",
    "sg:tags":[
        "away",
        "take"
    ],
    "wof:name":"Bella Mama",
    "wof:placetype":"venue"
},
  "geometry": {"coordinates":[-2.453846,53.102074],"type":"Point"}
}