{
  "type": "Feature",
  "properties": {
    "iso:country":"GB",
    "sg:address":"William Street, Treherbert",
    "sg:city":"Treorchy",
    "sg:classifiers":[
        {
            "category":"Shopping",
            "subcategory":"Pharmacy",
            "type":"Retail Goods"
        }
    ],
    "sg:phone":"+44 1443 771259",
    "sg:postcode":"CF42 5JJ",
    "sg:province":"Rhondda, Cynon, Taff",
    "sg:tags":[
        "dispensing",
        "store",
        "pharmacist",
        "chemist",
        "drug"
    ],
    "wof:name":"S & C Jones Chemist",
    "wof:placetype":"venue"
},
  "geometry": {"coordinates":[-3.540826,51.67704],"type":"Point"}
}