{
  "type": "Feature",
  "properties": {
    "addr:full":"Low Bleansley Farm Broughton-in-furness Cumbria LA20 6AR",
    "addr:postcode":"la20 6ar",
    "addr:street":"Broughton-In-Furness",
    "iso:country":"GB",
    "sg:address":"Low Bleansley Farm",
    "sg:city":"Broughton-in-furness",
    "sg:classifiers":[
        {
            "category":"Farming",
            "subcategory":"Dairy Farm",
            "type":"Manufacturing & Wholesale Goods"
        }
    ],
    "sg:phone":"+44 1229 716342",
    "sg:postcode":"LA20 6AR",
    "sg:province":"Cumbria",
    "wof:name":"D P & I Troughton",
    "wof:placetype":"venue"
},
  "geometry": {"coordinates":[-3.2109539509,54.2766799927],"type":"Point"}
}