{
  "type": "Feature",
  "properties": {
    "addr:full":"55 Frith Road Croydon Surrey CR0 1TB",
    "addr:housenumber":"55",
    "addr:postcode":"cr0 1tb",
    "addr:street":"Frith Road",
    "iso:country":"GB",
    "sg:address":"55 Frith Road",
    "sg:city":"Croydon",
    "sg:classifiers":[
        {
            "category":"Shopping",
            "subcategory":"Music",
            "type":"Retail Goods"
        }
    ],
    "sg:phone":"+44 20 8649 7220",
    "sg:postcode":"CR0 1TB",
    "sg:province":"Surrey",
    "sg:tags":[
        "record",
        "tape",
        "cd"
    ],
    "wof:name":"Memory Lane Records",
    "wof:placetype":"venue"
},
  "geometry": {"coordinates":[-0.1024010032,51.3741416931],"type":"Point"}
}