{
  "type": "Feature",
  "properties": {
    "addr:full":"72 New Bond Street London Greater London W1S 1RR",
    "addr:housenumber":"72",
    "addr:postcode":"w1s 1rr",
    "addr:street":"New Bond Street",
    "iso:country":"GB",
    "sg:address":"72 New Bond Street",
    "sg:city":"London",
    "sg:classifiers":[
        {
            "category":"Arts & Performance",
            "subcategory":"Arts Center",
            "type":"Entertainment"
        }
    ],
    "sg:postcode":"W1S 1RR",
    "sg:province":"Greater London",
    "sg:tags":[
        "centre"
    ],
    "wof:name":"Pictura Fine Arts Ltd",
    "wof:placetype":"venue"
},
  "geometry": {"coordinates":[-0.145802,51.513821],"type":"Point"}
}