{
  "type": "Feature",
  "properties": {
    "iso:country":"GB",
    "sg:address":"52 East Street",
    "sg:city":"London",
    "sg:classifiers":[
        {
            "category":"Shopping",
            "subcategory":"Clothing, Apparel, & Fashions",
            "type":"Retail Goods"
        }
    ],
    "sg:postcode":"SE17 2DN",
    "sg:province":"Greater London",
    "sg:tags":[
        "shop"
    ],
    "wof:name":"Blondies",
    "wof:placetype":"venue"
},
  "geometry": {"coordinates":[-0.093375,51.488209],"type":"Point"}
}