{
  "type": "Feature",
  "properties": {
    "iso:country":"GB",
    "sg:address":"Grosvenor Works, Grosvenor Street",
    "sg:city":"Ashton-under-lyne",
    "sg:classifiers":[
        {
            "category":"Manufacturing",
            "subcategory":"Rubber & Plastics",
            "type":"Manufacturing & Wholesale Goods"
        },
        {
            "category":"Manufacturing",
            "subcategory":"Chemicals & Compounds",
            "type":"Manufacturing & Wholesale Goods"
        }
    ],
    "sg:phone":"+44 161 330 8573",
    "sg:postcode":"OL7 0RG",
    "sg:province":"Greater Manchester",
    "sg:tags":[
        "supplier",
        "product",
        "allied",
        "stockist"
    ],
    "wof:name":"Synrein Plastics Ltd.",
    "wof:placetype":"venue"
},
  "geometry": {"coordinates":[-2.105099,53.479546],"type":"Point"}
}