{
  "type": "Feature",
  "properties": {
    "addr:full":"Unit 21 Shardlowes Farm, Hedingham Road, Gosfield Halstead Essex CO9 1PL",
    "addr:housenumber":"unit 21 shardlowes farm",
    "addr:postcode":"co9 1pl",
    "addr:street":"Hedingham Road Gosfield",
    "iso:country":"GB",
    "sg:address":"Unit 21 Shardlowes Farm, Hedingham Road, Gosfield",
    "sg:city":"Halstead",
    "sg:classifiers":[
        {
            "category":"Retail",
            "subcategory":"Auto Repair",
            "type":"Services"
        }
    ],
    "sg:phone":"+44 1787 478123",
    "sg:postcode":"CO9 1PL",
    "sg:province":"Essex",
    "sg:tags":[
        "body",
        "car"
    ],
    "wof:name":"B D Autos",
    "wof:placetype":"venue"
},
  "geometry": {"coordinates":[0.5912200212,51.9385604858],"type":"Point"}
}