{
  "type": "Feature",
  "properties": {
    "addr:full":"Beaumont's Of Harrogate Harrogate North Yorkshire HG2 8BW",
    "addr:postcode":"hg2 8bw",
    "iso:country":"GB",
    "sg:address":"Beaumont's Of Harrogate",
    "sg:city":"Harrogate",
    "sg:classifiers":[
        {
            "category":"Professional",
            "subcategory":"Art Services",
            "type":"Services"
        }
    ],
    "sg:phone":"+44 1423 873767",
    "sg:postcode":"HG2 8BW",
    "sg:province":"North Yorkshire",
    "sg:tags":[
        "photographer"
    ],
    "wof:name":"J M J Photography",
    "wof:placetype":"venue"
},
  "geometry": {"coordinates":[-1.5471160412,53.9909286499],"type":"Point"}
}