{
  "type": "Feature",
  "properties": {
    "iso:country":"GB",
    "sg:address":"8 Glenmore Parade, Ealing Road",
    "sg:city":"Wembley",
    "sg:classifiers":[
        {
            "category":"Personal",
            "subcategory":"Beauty Salon",
            "type":"Services"
        },
        {
            "category":"Personal",
            "subcategory":"Barber",
            "type":"Services"
        }
    ],
    "sg:phone":"+44 20 8795 2493",
    "sg:postcode":"HA0 4PJ",
    "sg:province":"Greater London",
    "sg:tags":[
        "unisex",
        "hairdresser"
    ],
    "wof:name":"Perfect Image",
    "wof:placetype":"venue"
},
  "geometry": {"coordinates":[-0.29738,51.541981],"type":"Point"}
}