{
  "type": "Feature",
  "properties": {
    "iso:country":"GB",
    "sg:address":"7 Eden Close, Heighington Village",
    "sg:city":"Newton Aycliffe",
    "sg:classifiers":[
        {
            "category":"Manufacturing",
            "subcategory":"Metals",
            "type":"Manufacturing & Wholesale Goods"
        }
    ],
    "sg:postcode":"DL5 6RU",
    "sg:province":"Durham",
    "sg:tags":[
        "steel",
        "stockholder"
    ],
    "wof:name":"Langron Steel Services Ltd.",
    "wof:placetype":"venue"
},
  "geometry": {"coordinates":[-1.563024,54.596272],"type":"Point"}
}