{
  "type": "Feature",
  "properties": {
    "addr:full":"Avonmouth Way, Avonmouth Bristol City of Bristol BS11 8DQ",
    "addr:postcode":"bs11 8dq",
    "addr:street":"Avonmouth Way",
    "iso:country":"GB",
    "sg:address":"Avonmouth Way, Avonmouth",
    "sg:city":"Bristol",
    "sg:classifiers":[
        {
            "category":"Food & Beverages",
            "subcategory":"Bakery",
            "type":"Retail Goods"
        }
    ],
    "sg:phone":"+44 117 982 5145",
    "sg:postcode":"BS11 8DQ",
    "sg:province":"City of Bristol",
    "sg:tags":[
        "confectionery"
    ],
    "wof:name":"British Bakeries Ltd.",
    "wof:placetype":"venue"
},
  "geometry": {"coordinates":[-2.674899,51.504978],"type":"Point"}
}