{
  "type": "Feature",
  "properties": {
    "addr:full":"Radnor Park Av Folkestone Kent CT19 5HX",
    "addr:postcode":"ct19 5hx",
    "addr:street":"Park Av",
    "iso:country":"GB",
    "sg:address":"Radnor Park Av",
    "sg:city":"Folkestone",
    "sg:classifiers":[
        {
            "category":"Sports & Exercise",
            "subcategory":"Sports Center",
            "type":"Entertainment"
        }
    ],
    "sg:phone":"+44 1303 850777",
    "sg:postcode":"CT19 5HX",
    "sg:province":"Kent",
    "sg:tags":[
        "shop",
        "good"
    ],
    "wof:name":"Folkestone Sports Centre Sports Shop",
    "wof:placetype":"venue"
},
  "geometry": {"coordinates":[1.167666,51.086792],"type":"Point"}
}