{
  "type": "Feature",
  "properties": {
    "addr:full":"High Rd Chigwell Essex IG7 6QQ",
    "addr:postcode":"ig7 6qq",
    "addr:street":"High Rd",
    "iso:country":"GB",
    "sg:address":"High Rd",
    "sg:city":"Chigwell",
    "sg:classifiers":[
        {
            "category":"Building & Trades",
            "subcategory":"Construction",
            "type":"Services"
        }
    ],
    "sg:phone":"+44 20 8500 3111",
    "sg:postcode":"IG7 6QQ",
    "sg:province":"Essex",
    "sg:tags":[
        "builder"
    ],
    "wof:name":"Radleys Ltd",
    "wof:placetype":"venue"
},
  "geometry": {"coordinates":[0.085838,51.632473],"type":"Point"}
}