{
  "type": "Feature",
  "properties": {
    "addr:full":"4 Waingate Sheffield South Yorkshire S3 8LB",
    "addr:housenumber":"4",
    "addr:postcode":"s3 8lb",
    "addr:street":"Waingate Sheffield South",
    "iso:country":"GB",
    "sg:address":"4 Waingate",
    "sg:city":"Sheffield",
    "sg:classifiers":[
        {
            "category":"Shopping",
            "subcategory":"Optician",
            "type":"Retail Goods"
        }
    ],
    "sg:phone":"+44 114 272 0388",
    "sg:postcode":"S3 8LB",
    "sg:province":"South Yorkshire",
    "wof:name":"Dollond & Aitchison",
    "wof:placetype":"venue"
},
  "geometry": {"coordinates":[-1.4639680386,53.3844528198],"type":"Point"}
}