{
  "type": "Feature",
  "properties": {
    "addr:full":"Ogilface Craigs Bathgate West Lothian EH48 3AE",
    "addr:postcode":"eh48 3ae",
    "addr:street":"Bathgate",
    "iso:country":"GB",
    "sg:address":"Ogilface Craigs",
    "sg:city":"Bathgate",
    "sg:classifiers":[
        {
            "category":"Utilities",
            "subcategory":"Fuel Oil & Lpg",
            "type":"Services"
        }
    ],
    "sg:phone":"+44 1501 753753",
    "sg:postcode":"EH48 3AE",
    "sg:province":"West Lothian",
    "wof:name":"Graeme & Lorraine Bryce",
    "wof:placetype":"venue"
},
  "geometry": {"coordinates":[-3.775569,55.882725],"type":"Point"}
}