{
  "type": "Feature",
  "properties": {
    "iso:country":"GB",
    "sg:address":"10 High Street, Overton",
    "sg:city":"Basingstoke",
    "sg:classifiers":[
        {
            "category":"Food & Beverages",
            "subcategory":"Bakery",
            "type":"Retail Goods"
        }
    ],
    "sg:phone":"+44 1256 771128",
    "sg:postcode":"RG25 3HA",
    "sg:province":"Hampshire",
    "sg:tags":[
        "shop",
        "baker"
    ],
    "wof:name":"The Village Bakery",
    "wof:placetype":"venue"
},
  "geometry": {"coordinates":[-1.2636129856,51.2441062927],"type":"Point"}
}