{
  "type": "Feature",
  "properties": {
    "addr:full":"97 Carron Place, Castlepark Irvine North Ayrshire KA12 9NF",
    "addr:housenumber":"97",
    "addr:postcode":"ka12 9nf",
    "addr:street":"Carron Place Castlepark",
    "iso:country":"GB",
    "sg:address":"97 Carron Place, Castlepark",
    "sg:city":"Irvine",
    "sg:classifiers":[
        {
            "category":"Building & Trades",
            "subcategory":"Construction",
            "type":"Services"
        }
    ],
    "sg:postcode":"KA12 9NF",
    "sg:province":"North Ayrshire",
    "sg:tags":[
        "roofing"
    ],
    "wof:name":"J & J Slaters",
    "wof:placetype":"venue"
},
  "geometry": {"coordinates":[-4.662998,55.631149],"type":"Point"}
}