{
  "type": "Feature",
  "properties": {
    "addr:full":"Midleys Mhc Centre St Ives Cambridgeshire PE27 6RU",
    "addr:postcode":"pe27 6ru",
    "iso:country":"GB",
    "sg:address":"Midleys Mhc Centre",
    "sg:city":"St Ives",
    "sg:classifiers":[
        {
            "category":"Farming",
            "subcategory":"Nursery",
            "type":"Manufacturing & Wholesale Goods"
        },
        {
            "category":"Organizations",
            "subcategory":"Non-profit Organization",
            "type":"Services"
        }
    ],
    "sg:postcode":"PE27 6RU",
    "sg:province":"Cambridgeshire",
    "sg:tags":[
        "organisation",
        "creche",
        "voluntary",
        "charity"
    ],
    "wof:name":"St. Ives & District Society for Mentally Handicapp",
    "wof:placetype":"venue"
},
  "geometry": {"coordinates":[-0.0833899975,52.3327903748],"type":"Point"}
}