{
  "type": "Feature",
  "properties": {
    "iso:country":"GB",
    "sg:address":"20 Waverley Road",
    "sg:city":"Epsom",
    "sg:classifiers":[
        {
            "category":"Professional",
            "subcategory":"Engineering",
            "type":"Services"
        }
    ],
    "sg:phone":"+44 20 8393 6800",
    "sg:postcode":"KT17 2LT",
    "sg:province":"Surrey",
    "sg:tags":[
        "contractor",
        "electrical",
        "engineer"
    ],
    "wof:name":"B G I (Electrical) Ltd.",
    "wof:placetype":"venue"
},
  "geometry": {"coordinates":[-0.2411089987,51.3620796204],"type":"Point"}
}