{
  "type": "Feature",
  "properties": {
    "addr:full":"191 Park View Whitley Bay Northumberland NE26 3RD",
    "addr:housenumber":"191",
    "addr:postcode":"ne26 3rd",
    "addr:street":"Park View",
    "iso:country":"GB",
    "sg:address":"191 Park View",
    "sg:city":"Whitley Bay",
    "sg:classifiers":[
        {
            "category":"Organizations",
            "subcategory":"Non-profit Organization",
            "type":"Services"
        }
    ],
    "sg:phone":"+44 191 251 4014",
    "sg:postcode":"NE26 3RD",
    "sg:province":"Northumberland",
    "sg:tags":[
        "organisation",
        "voluntary",
        "charity"
    ],
    "wof:name":"Churches Acting Together",
    "wof:placetype":"venue"
},
  "geometry": {"coordinates":[-1.452281,55.045284],"type":"Point"}
}