{
  "type": "Feature",
  "properties": {
    "addr:full":"25 Abbeville Mews London Greater London SW4 7BX",
    "addr:housenumber":"25",
    "addr:postcode":"sw4 7bx",
    "addr:street":"Abbeville Mews",
    "iso:country":"GB",
    "sg:address":"25 Abbeville Mews",
    "sg:city":"London",
    "sg:classifiers":[
        {
            "category":"Real Estate",
            "subcategory":"Architect",
            "type":"Services"
        }
    ],
    "sg:phone":"+44 20 7720 9609",
    "sg:postcode":"SW4 7BX",
    "sg:province":"Greater London",
    "wof:name":"Tessa Lam Designs Ltd.",
    "wof:placetype":"venue"
},
  "geometry": {"coordinates":[-0.134452,51.459351],"type":"Point"}
}