{
  "type": "Feature",
  "properties": {
    "iso:country":"GB",
    "sg:address":"20 Parkway",
    "sg:city":"Wirral",
    "sg:classifiers":[
        {
            "category":"Professional",
            "subcategory":"Business Services",
            "type":"Services"
        }
    ],
    "sg:phone":"+44 151 648 0044",
    "sg:postcode":"CH61 3XJ",
    "sg:province":"Merseyside",
    "sg:tags":[
        "transfer",
        "agent"
    ],
    "wof:name":"D Sinclair & Son",
    "wof:placetype":"venue"
},
  "geometry": {"coordinates":[-3.099954,53.357761],"type":"Point"}
}