{
  "type": "Feature",
  "properties": {
    "addr:full":"139 Main Road Northampton Northamptonshire NN5 6RA",
    "addr:housenumber":"139",
    "addr:postcode":"nn5 6ra",
    "addr:street":"Main Road",
    "iso:country":"GB",
    "sg:address":"139 Main Road",
    "sg:city":"Northampton",
    "sg:classifiers":[
        {
            "category":"Building & Trades",
            "subcategory":"Construction",
            "type":"Services"
        }
    ],
    "sg:phone":"+44 1604 587414",
    "sg:postcode":"NN5 6RA",
    "sg:province":"Northamptonshire",
    "sg:tags":[
        "builder"
    ],
    "wof:name":"Gregory Winterburn",
    "wof:placetype":"venue"
},
  "geometry": {"coordinates":[-0.950484,52.249416],"type":"Point"}
}