{
  "type": "Feature",
  "properties": {
    "addr:full":"Carr Lane, Maltby Rotherham South Yorkshire S66 8NB",
    "addr:postcode":"s66 8nb",
    "addr:street":"Carr Lane",
    "iso:country":"GB",
    "sg:address":"Carr Lane, Maltby",
    "sg:city":"Rotherham",
    "sg:classifiers":[
        {
            "category":"Building & Trades",
            "subcategory":"Construction",
            "type":"Services"
        }
    ],
    "sg:postcode":"S66 8NB",
    "sg:province":"South Yorkshire",
    "sg:tags":[
        "joinery"
    ],
    "wof:name":"D & B Fencing (Rochell)",
    "wof:placetype":"venue"
},
  "geometry": {"coordinates":[-1.220354,53.419476],"type":"Point"}
}