{
  "type": "Feature",
  "properties": {
    "addr:full":"19 Cone Terr Chester Le Street Durham DH3 3QH",
    "addr:housenumber":"19",
    "addr:postcode":"dh3 3qh",
    "addr:street":"Cone Terr;Le Street",
    "iso:country":"GB",
    "sg:address":"19 Cone Terr",
    "sg:city":"Chester Le Street",
    "sg:classifiers":[
        {
            "category":"Education",
            "subcategory":"Special Training",
            "type":"Public Place"
        }
    ],
    "sg:phone":"+44 191 388 0066",
    "sg:postcode":"DH3 3QH",
    "sg:province":"Durham",
    "sg:tags":[
        "product",
        "centre"
    ],
    "wof:name":"Action Community College",
    "wof:placetype":"venue"
},
  "geometry": {"coordinates":[-1.5749640465,54.8591346741],"type":"Point"}
}