{
  "type": "Feature",
  "properties": {
    "addr:full":"41 Old Raise Road Saltcoats North Ayrshire KA21 5RB",
    "addr:housenumber":"41",
    "addr:postcode":"ka21 5rb",
    "addr:street":"Old Raise Road",
    "iso:country":"GB",
    "sg:address":"41 Old Raise Road",
    "sg:city":"Saltcoats",
    "sg:classifiers":[
        {
            "category":"Personal",
            "subcategory":"Beauty Salon",
            "type":"Services"
        }
    ],
    "sg:postcode":"KA21 5RB",
    "sg:province":"North Ayrshire",
    "sg:tags":[
        "lady",
        "hairdresser"
    ],
    "wof:name":"Agnes Jones",
    "wof:placetype":"venue"
},
  "geometry": {"coordinates":[-4.7782588005,55.6409454346],"type":"Point"}
}