{
  "type": "Feature",
  "properties": {
    "iso:country":"GB",
    "sg:address":"Kilmahog",
    "sg:city":"Callander",
    "sg:classifiers":[
        {
            "category":"Bars & Pubs",
            "type":"Food & Drink"
        }
    ],
    "sg:phone":"+44 1877 30152",
    "sg:postcode":"FK17 8HD",
    "sg:province":"Stirling",
    "sg:tags":[
        "pubs",
        "inn"
    ],
    "wof:name":"The Lade Inn",
    "wof:placetype":"venue"
},
  "geometry": {"coordinates":[-4.209564209,56.24243927],"type":"Point"}
}