{
  "type": "Feature",
  "properties": {
    "iso:country":"GB",
    "sg:address":"Old School, Chesham Road, Ashley Green",
    "sg:city":"Chesham",
    "sg:classifiers":[
        {
            "category":"Government",
            "subcategory":"City Hall",
            "type":"Public Place"
        },
        {
            "category":"Retail",
            "subcategory":"Event Space",
            "type":"Services"
        }
    ],
    "sg:phone":"+44 1442 874834",
    "sg:postcode":"HP5 3PP",
    "sg:province":"Buckinghamshire",
    "sg:tags":[
        "function",
        "hire",
        "room"
    ],
    "wof:name":"Ashley Green & District Community Association",
    "wof:placetype":"venue"
},
  "geometry": {"coordinates":[-0.609333,51.710537],"type":"Point"}
}