{
  "type": "Feature",
  "properties": {
    "addr:full":"78 Well Meadow Bridgnorth Shropshire WV15 6DE",
    "addr:housenumber":"78",
    "addr:postcode":"wv15 6de",
    "addr:street":"Well Meadow",
    "iso:country":"GB",
    "sg:address":"78 Well Meadow",
    "sg:city":"Bridgnorth",
    "sg:classifiers":[
        {
            "category":"Retail",
            "subcategory":"Repair Shop",
            "type":"Services"
        }
    ],
    "sg:phone":"+44 1746 764121",
    "sg:postcode":"WV15 6DE",
    "sg:province":"Shropshire",
    "sg:tags":[
        "radio",
        "television",
        "video"
    ],
    "wof:name":"D & S Electronic Services",
    "wof:placetype":"venue"
},
  "geometry": {"coordinates":[-2.414125,52.530231],"type":"Point"}
}