{
  "type": "Feature",
  "properties": {
    "addr:full":"Lake St Oxford Oxfordshire OX1 4RP",
    "addr:postcode":"ox1 4rp",
    "addr:street":"Lake St",
    "iso:country":"GB",
    "sg:address":"Lake St",
    "sg:city":"Oxford",
    "sg:classifiers":[
        {
            "category":"Sports & Exercise",
            "subcategory":"Swimming Pool",
            "type":"Entertainment"
        }
    ],
    "sg:phone":"+44 1865 247737",
    "sg:postcode":"OX1 4RP",
    "sg:province":"Oxfordshire",
    "wof:name":"Hinksey Pools",
    "wof:placetype":"venue"
},
  "geometry": {"coordinates":[-1.254474,51.739979],"type":"Point"}
}