{
  "type": "Feature",
  "properties": {
    "iso:country":"GB",
    "sg:address":"357 Edgware Road",
    "sg:city":"London",
    "sg:classifiers":[
        {
            "category":"Fast Food",
            "type":"Food & Drink"
        }
    ],
    "sg:phone":"+44 20 7724 1968",
    "sg:postcode":"W2 1BS",
    "sg:province":"Greater London",
    "sg:tags":[
        "away",
        "take"
    ],
    "wof:name":"Southern Fried Chicken",
    "wof:placetype":"venue"
},
  "geometry": {"coordinates":[-0.1733199954,51.5221252441],"type":"Point"}
}