{
  "type": "Feature",
  "properties": {
    "iso:country":"GB",
    "sg:address":"Moorland Rd, Burslem",
    "sg:city":"Stoke-on-trent",
    "sg:classifiers":[
        {
            "category":"Conference Center",
            "type":"Public Place"
        }
    ],
    "sg:postcode":"ST6 1JQ",
    "sg:province":"Staffordshire",
    "sg:tags":[
        "business",
        "centre"
    ],
    "wof:name":"Stoke-on-Trent City Council",
    "wof:placetype":"venue"
},
  "geometry": {"coordinates":[-2.1941690445,53.0462684631],"type":"Point"}
}