{
  "type": "Feature",
  "properties": {
    "iso:country":"GB",
    "sg:address":"Heron Mews House, 1a Balfour Road",
    "sg:city":"Ilford",
    "sg:classifiers":[
        {
            "category":"Professional",
            "subcategory":"Business Services",
            "type":"Services"
        },
        {
            "category":"Manufacturing",
            "subcategory":"Lumber",
            "type":"Manufacturing & Wholesale Goods"
        }
    ],
    "sg:phone":"+44 20 8553 3471",
    "sg:postcode":"IG1 4HP",
    "sg:province":"Essex",
    "sg:tags":[
        "merchants",
        "importer",
        "agent",
        "timber"
    ],
    "sg:website":"http://www.plautint.co.uk",
    "wof:name":"Plaut International Ltd.",
    "wof:placetype":"venue"
},
  "geometry": {"coordinates":[0.070542,51.560253],"type":"Point"}
}