{
  "type": "Feature",
  "properties": {
    "addr:full":"14 Church Street Market Harborough Leicestershire LE16 7AB",
    "addr:housenumber":"14",
    "addr:postcode":"le16 7ab",
    "addr:street":"Church Street",
    "iso:country":"GB",
    "sg:address":"14 Church Street",
    "sg:city":"Market Harborough",
    "sg:classifiers":[
        {
            "category":"Manufacturing",
            "subcategory":"Wood Products",
            "type":"Manufacturing & Wholesale Goods"
        }
    ],
    "sg:phone":"+44 1858 462641",
    "sg:postcode":"LE16 7AB",
    "sg:province":"Leicestershire",
    "sg:tags":[
        "packaging",
        "crate",
        "pallets"
    ],
    "wof:name":"Metal-Woods Ltd.",
    "wof:placetype":"venue"
},
  "geometry": {"coordinates":[-0.9217159748,52.4791488647],"type":"Point"}
}