{
  "type": "Feature",
  "properties": {
    "addr:full":"20 Mount Road Mitcham Greater London CR4 3EY",
    "addr:housenumber":"20",
    "addr:postcode":"cr4 3ey",
    "addr:street":"Mount Road",
    "iso:country":"GB",
    "sg:address":"20 Mount Road",
    "sg:city":"Mitcham",
    "sg:classifiers":[
        {
            "category":"Retail",
            "subcategory":"Repair Shop",
            "type":"Services"
        }
    ],
    "sg:phone":"+44 20 8395 3024",
    "sg:postcode":"CR4 3EY",
    "sg:province":"Greater London",
    "sg:tags":[
        "maintenance"
    ],
    "wof:name":"Allcraft",
    "wof:placetype":"venue"
},
  "geometry": {"coordinates":[-0.173689,51.409866],"type":"Point"}
}