{
  "type": "Feature",
  "properties": {
    "addr:full":"Turpin Green La Preston Lancashire PR5 2HA",
    "addr:postcode":"pr5 2ha",
    "addr:street":"Turpin Green La Preston",
    "iso:country":"GB",
    "sg:address":"Turpin Green La",
    "sg:city":"Preston",
    "sg:classifiers":[
        {
            "category":"Place Of Worship",
            "type":"Public Place"
        }
    ],
    "sg:phone":"+44 1772 422613",
    "sg:postcode":"PR5 2HA",
    "sg:province":"Lancashire",
    "wof:name":"Leyland Methodist Church",
    "wof:placetype":"venue"
},
  "geometry": {"coordinates":[-2.63084,53.745762],"type":"Point"}
}