{
  "type": "Feature",
  "properties": {
    "iso:country":"GB",
    "sg:address":"Wye Valley, Llandogo",
    "sg:city":"Monmouth",
    "sg:classifiers":[
        {
            "category":"Autos & Motor Vehicles",
            "subcategory":"Fuel & Gas Station",
            "type":"Retail Goods"
        }
    ],
    "sg:postcode":"NP25 4TL",
    "sg:province":"Gloucestershire",
    "sg:tags":[
        "petrol",
        "filling"
    ],
    "wof:name":"Llandogo Development Ltd",
    "wof:placetype":"venue"
},
  "geometry": {"coordinates":[-2.6876709461,51.7337913513],"type":"Point"}
}