{
  "type": "Feature",
  "properties": {
    "iso:country":"GB",
    "sg:address":"45 Market Place",
    "sg:city":"Wetherby",
    "sg:classifiers":[
        {
            "category":"Food & Beverages",
            "subcategory":"Bakery",
            "type":"Retail Goods"
        }
    ],
    "sg:phone":"+44 1937 580059",
    "sg:postcode":"LS22 4LN",
    "sg:province":"North Yorkshire",
    "sg:tags":[
        "baker"
    ],
    "wof:name":"Ainsleys of Leeds Ltd.",
    "wof:placetype":"venue"
},
  "geometry": {"coordinates":[-1.386645,53.928375],"type":"Point"}
}