{
  "type": "Feature",
  "properties": {
    "addr:full":"9 Gurney Crescent, Littlethorpe Leicester Leicestershire LE9 5JL",
    "addr:housenumber":"9",
    "addr:postcode":"le9 5jl",
    "addr:street":"Gurney Crescent",
    "iso:country":"GB",
    "sg:address":"9 Gurney Crescent, Littlethorpe",
    "sg:city":"Leicester",
    "sg:classifiers":[
        {
            "category":"Professional",
            "subcategory":"Business Services",
            "type":"Services"
        }
    ],
    "sg:phone":"+44 116 286 3501",
    "sg:postcode":"LE9 5JL",
    "sg:province":"Leicestershire",
    "sg:tags":[
        "distributor",
        "film"
    ],
    "wof:name":"Rouse Studios",
    "wof:placetype":"venue"
},
  "geometry": {"coordinates":[-1.2017300129,52.5675697327],"type":"Point"}
}