{
  "type": "Feature",
  "properties": {
    "addr:full":"140 Dean Rd South Shields Tyne and Wear NE33 4AW",
    "addr:housenumber":"140",
    "addr:postcode":"ne33 4aw",
    "addr:street":"Dean Rd",
    "iso:country":"GB",
    "sg:address":"140 Dean Rd",
    "sg:city":"South Shields",
    "sg:classifiers":[
        {
            "category":"Organizations",
            "subcategory":"Non-profit Organization",
            "type":"Services"
        }
    ],
    "sg:phone":"+44 191 455 2787",
    "sg:postcode":"NE33 4AW",
    "sg:province":"Tyne and Wear",
    "sg:tags":[
        "organisation",
        "voluntary",
        "charity"
    ],
    "wof:name":"The Children's Society",
    "wof:placetype":"venue"
},
  "geometry": {"coordinates":[-1.42887,54.98661],"type":"Point"}
}