{
  "type": "Feature",
  "properties": {
    "iso:country":"GB",
    "sg:address":"210 Pall Mall",
    "sg:city":"Chorley",
    "sg:classifiers":[
        {
            "category":"Food & Beverages",
            "subcategory":"Bakery",
            "type":"Retail Goods"
        },
        {
            "category":"Food & Beverages",
            "subcategory":"Meat & Fish",
            "type":"Retail Goods"
        }
    ],
    "sg:phone":"+44 1257 262331",
    "sg:postcode":"PR7 2LH",
    "sg:province":"Lancashire",
    "sg:tags":[
        "baker",
        "butcher"
    ],
    "wof:name":"Reuben Marsden Ltd.",
    "wof:placetype":"venue"
},
  "geometry": {"coordinates":[-2.636464,53.645008],"type":"Point"}
}