{
  "type": "Feature",
  "properties": {
    "addr:full":"3 Old Post Office Street Fakenham Norfolk NR21 9DT",
    "addr:housenumber":"3",
    "addr:postcode":"nr21 9dt",
    "addr:street":"Old Post Office Street",
    "iso:country":"GB",
    "sg:address":"3 Old Post Office Street",
    "sg:city":"Fakenham",
    "sg:classifiers":[
        {
            "category":"Food & Beverages",
            "subcategory":"Meat & Fish",
            "type":"Retail Goods"
        }
    ],
    "sg:postcode":"NR21 9DT",
    "sg:province":"Norfolk",
    "sg:tags":[
        "chip"
    ],
    "wof:name":"Drifters Fish & Chip Shop",
    "wof:placetype":"venue"
},
  "geometry": {"coordinates":[0.8464819789,52.8303413391],"type":"Point"}
}