{
  "type": "Feature",
  "properties": {
    "addr:full":"3 Granta Close, Great Chesterford Saffron Walden Cambridgeshire CB10 1QP",
    "addr:housenumber":"3",
    "addr:postcode":"cb10 1qp",
    "addr:street":"Granta Close",
    "iso:country":"GB",
    "sg:address":"3 Granta Close, Great Chesterford",
    "sg:city":"Saffron Walden",
    "sg:classifiers":[
        {
            "category":"Building & Trades",
            "subcategory":"Construction",
            "type":"Services"
        }
    ],
    "sg:postcode":"CB10 1QP",
    "sg:province":"Cambridgeshire",
    "sg:tags":[
        "builder"
    ],
    "wof:name":"Welding Codes  &  Standards Expertise Lt",
    "wof:placetype":"venue"
},
  "geometry": {"coordinates":[0.2399380058,52.0205764771],"type":"Point"}
}