{
  "type": "Feature",
  "properties": {
    "iso:country":"GB",
    "sg:address":"Broughton Mill Lane, Bretton",
    "sg:city":"Chester",
    "sg:classifiers":[
        {
            "category":"Wholesale",
            "subcategory":"Scrap",
            "type":"Manufacturing & Wholesale Goods"
        }
    ],
    "sg:postcode":"CH4 0BY",
    "sg:province":"Cheshire",
    "sg:tags":[
        "breaker",
        "dismantlers"
    ],
    "wof:name":"Chadwicks Car Dismantlers",
    "wof:placetype":"venue"
},
  "geometry": {"coordinates":[-2.887633,53.185108],"type":"Point"}
}