{
  "type": "Feature",
  "properties": {
    "addr:full":"Endlee, South Petherwin Launceston Cornwall PL15 7LG",
    "addr:postcode":"pl15 7lg",
    "addr:street":"South",
    "iso:country":"GB",
    "sg:address":"Endlee, South Petherwin",
    "sg:city":"Launceston",
    "sg:classifiers":[
        {
            "category":"Building & Trades",
            "subcategory":"Landscaping Services",
            "type":"Services"
        }
    ],
    "sg:phone":"+44 1566 782893",
    "sg:postcode":"PL15 7LG",
    "sg:province":"Cornwall",
    "sg:tags":[
        "horticultural",
        "consultant"
    ],
    "wof:name":"Brian Bloomfield",
    "wof:placetype":"venue"
},
  "geometry": {"coordinates":[-4.390977,50.611439],"type":"Point"}
}