{
  "type": "Feature",
  "properties": {
    "iso:country":"GB",
    "sg:address":"Abbey Mill, Business Centre, 22 St. James Buildings, Anchor Mills",
    "sg:city":"Paisley",
    "sg:classifiers":[
        {
            "category":"Retail",
            "subcategory":"Auto Repair",
            "type":"Services"
        }
    ],
    "sg:phone":"+44 1908 365533",
    "sg:postcode":"PA1 1TJ",
    "sg:province":"Renfrewshire",
    "sg:tags":[
        "body",
        "car"
    ],
    "wof:name":"Motorclaims UK Ltd",
    "wof:placetype":"venue"
},
  "geometry": {"coordinates":[-4.40504,55.842869],"type":"Point"}
}