{
  "type": "Feature",
  "properties": {
    "addr:full":"182a Portland Street Southport Lancashire PR8 6LU",
    "addr:housenumber":"182a",
    "addr:postcode":"pr8 6lu",
    "addr:street":"Portland Street",
    "iso:country":"GB",
    "sg:address":"182a Portland Street",
    "sg:city":"Southport",
    "sg:classifiers":[
        {
            "category":"Retail",
            "subcategory":"Auto Repair",
            "type":"Services"
        }
    ],
    "sg:phone":"+44 1704 534916",
    "sg:postcode":"PR8 6LU",
    "sg:province":"Lancashire",
    "sg:tags":[
        "modification",
        "garage",
        "related"
    ],
    "wof:name":"Carlton Auto Engineering",
    "wof:placetype":"venue"
},
  "geometry": {"coordinates":[-2.996523,53.636551],"type":"Point"}
}