{
  "type": "Feature",
  "properties": {
    "addr:full":"109b London Rd, Cowplain Waterlooville Hampshire PO8 8XJ",
    "addr:housenumber":"109b",
    "addr:postcode":"po8 8xj",
    "addr:street":"London Rd",
    "iso:country":"GB",
    "sg:address":"109b London Rd, Cowplain",
    "sg:city":"Waterlooville",
    "sg:classifiers":[
        {
            "category":"Health Services",
            "subcategory":"Dentist",
            "type":"Services"
        }
    ],
    "sg:phone":"+44 23 9226 2045",
    "sg:postcode":"PO8 8XJ",
    "sg:province":"Hampshire",
    "wof:name":"O St. John Dee BA. B.Dent.Sc",
    "wof:placetype":"venue"
},
  "geometry": {"coordinates":[-1.017148,50.896362],"type":"Point"}
}