{
  "type": "Feature",
  "properties": {
    "addr:full":"223 Hartington Road Brighton East Sussex BN2 3PA",
    "addr:housenumber":"223",
    "addr:postcode":"bn2 3pa",
    "addr:street":"Hartington Road",
    "iso:country":"GB",
    "sg:address":"223 Hartington Road",
    "sg:city":"Brighton",
    "sg:classifiers":[
        {
            "category":"Manufacturing",
            "subcategory":"Tools & Machinery",
            "type":"Manufacturing & Wholesale Goods"
        },
        {
            "category":"Insurance",
            "subcategory":"Life Insurance",
            "type":"Services"
        }
    ],
    "sg:phone":"+44 1273 389333",
    "sg:postcode":"BN2 3PA",
    "sg:province":"East Sussex",
    "sg:tags":[
        "society",
        "friendly",
        "assurance"
    ],
    "wof:name":"Medical Insurance Services",
    "wof:placetype":"venue"
},
  "geometry": {"coordinates":[-0.115923,50.832874],"type":"Point"}
}