{
  "type": "Feature",
  "properties": {
    "addr:full":"81-82 Wright Street Birmingham West Midlands B10 9SP",
    "addr:housenumber":"81-82",
    "addr:postcode":"b10 9sp",
    "addr:street":"Wright Street",
    "iso:country":"GB",
    "sg:address":"81-82 Wright Street",
    "sg:city":"Birmingham",
    "sg:classifiers":[
        {
            "category":"Retail",
            "subcategory":"Auto Repair",
            "type":"Services"
        }
    ],
    "sg:phone":"+44 121 766 7427",
    "sg:postcode":"B10 9SP",
    "sg:province":"West Midlands",
    "sg:tags":[
        "modification",
        "garage",
        "related"
    ],
    "wof:name":"Hanif Autos",
    "wof:placetype":"venue"
},
  "geometry": {"coordinates":[-1.855961,52.469444],"type":"Point"}
}