{
  "type": "Feature",
  "properties": {
    "addr:full":"234 Whitchurch Road Tavistock Devon PL19 9DQ",
    "addr:housenumber":"234",
    "addr:postcode":"pl19 9dq",
    "addr:street":"Whitchurch Road",
    "iso:country":"GB",
    "sg:address":"234 Whitchurch Road",
    "sg:city":"Tavistock",
    "sg:classifiers":[
        {
            "category":"Shopping",
            "subcategory":"News",
            "type":"Retail Goods"
        }
    ],
    "sg:postcode":"PL19 9DQ",
    "sg:province":"Devon",
    "sg:tags":[
        "newsagent"
    ],
    "wof:name":"Whitchurch Post Office & General Store",
    "wof:placetype":"venue"
},
  "geometry": {"coordinates":[-4.1411190033,50.5399017334],"type":"Point"}
}