{
  "type": "Feature",
  "properties": {
    "addr:full":"Chapel Lane, Milford Godalming Surrey GU8 5HU",
    "addr:postcode":"gu8 5hu",
    "addr:street":"Chapel Lane",
    "iso:country":"GB",
    "sg:address":"Chapel Lane, Milford",
    "sg:city":"Godalming",
    "sg:classifiers":[
        {
            "category":"Manufacturing",
            "subcategory":"Wood Products",
            "type":"Manufacturing & Wholesale Goods"
        }
    ],
    "sg:postcode":"GU8 5HU",
    "sg:province":"Surrey",
    "sg:tags":[
        "packaging",
        "crate",
        "pallets"
    ],
    "wof:name":"Thames Valley Farms Ltd.",
    "wof:placetype":"venue"
},
  "geometry": {"coordinates":[-0.6479039788,51.1753997803],"type":"Point"}
}