{
  "type": "Feature",
  "properties": {
    "addr:full":"10 Norland Place London Greater London W11 4QG",
    "addr:housenumber":"10",
    "addr:postcode":"w11 4qg",
    "addr:street":"Norland Place",
    "iso:country":"GB",
    "sg:address":"10 Norland Place",
    "sg:city":"London",
    "sg:classifiers":[
        {
            "category":"Real Estate",
            "subcategory":"Real Estate Operator",
            "type":"Services"
        }
    ],
    "sg:postcode":"W11 4QG",
    "sg:province":"Greater London",
    "sg:tags":[
        "letting",
        "agent"
    ],
    "wof:name":"Temple Crest",
    "wof:placetype":"venue"
},
  "geometry": {"coordinates":[-0.209258,51.506828],"type":"Point"}
}