{
  "type": "Feature",
  "properties": {
    "addr:full":"14 Station Road, Milngavie Glasgow East Dunbartonshire G62 8AB",
    "addr:housenumber":"14",
    "addr:postcode":"g62 8ab",
    "addr:street":"Station Road",
    "iso:country":"GB",
    "sg:address":"14 Station Road, Milngavie",
    "sg:city":"Glasgow",
    "sg:classifiers":[
        {
            "category":"Food & Beverages",
            "subcategory":"Meat & Fish",
            "type":"Retail Goods"
        }
    ],
    "sg:phone":"+44 141 956 1704",
    "sg:postcode":"G62 8AB",
    "sg:province":"East Dunbartonshire",
    "sg:tags":[
        "butcher"
    ],
    "wof:name":"W & J Lewis (Butchers) Ltd.",
    "wof:placetype":"venue"
},
  "geometry": {"coordinates":[-4.3157191277,55.9421691895],"type":"Point"}
}