{
  "type": "Feature",
  "properties": {
    "addr:full":"1a Crayfield Rd, Levenshulme Manchester Greater Manchester M19 3NN",
    "addr:housenumber":"1a",
    "addr:postcode":"m19 3nn",
    "addr:street":"Crayfield Rd",
    "iso:country":"GB",
    "sg:address":"1a Crayfield Rd, Levenshulme",
    "sg:city":"Manchester",
    "sg:classifiers":[
        {
            "category":"Wholesale",
            "subcategory":"Scrap",
            "type":"Manufacturing & Wholesale Goods"
        }
    ],
    "sg:phone":"+44 161 256 2728",
    "sg:postcode":"M19 3NN",
    "sg:province":"Greater Manchester",
    "sg:tags":[
        "salvage"
    ],
    "wof:name":"Manchester Architectural Salvage Centre",
    "wof:placetype":"venue"
},
  "geometry": {"coordinates":[-2.1886110306,53.4411735535],"type":"Point"}
}