{
  "type": "Feature",
  "properties": {
    "addr:full":"Wessex House, 137 Stewart Rd Bournemouth Dorset BH8 8PA",
    "addr:housenumber":"137",
    "addr:postcode":"bh8 8pa",
    "addr:street":"Stewart Rd",
    "iso:country":"GB",
    "sg:address":"Wessex House, 137 Stewart Rd",
    "sg:city":"Bournemouth",
    "sg:classifiers":[
        {
            "category":"Bus Charters",
            "type":"Transportation"
        }
    ],
    "sg:phone":"+44 1202 311799",
    "sg:postcode":"BH8 8PA",
    "sg:province":"Dorset",
    "sg:tags":[
        "hire",
        "coach"
    ],
    "wof:name":"Richard Green Travel",
    "wof:placetype":"venue"
},
  "geometry": {"coordinates":[-1.862918973,50.7328910828],"type":"Point"}
}