{
  "type": "Feature",
  "properties": {
    "iso:country":"GB",
    "sg:address":"Maldon Road, Birch",
    "sg:city":"Colchester",
    "sg:classifiers":[
        {
            "category":"Retail",
            "subcategory":"Auto Repair",
            "type":"Services"
        }
    ],
    "sg:phone":"+44 1206 330227",
    "sg:postcode":"CO2 0LT",
    "sg:province":"Essex",
    "sg:tags":[
        "modification",
        "garage"
    ],
    "wof:name":"Lawes Garage",
    "wof:placetype":"venue"
},
  "geometry": {"coordinates":[0.818881,51.844532],"type":"Point"}
}