{
  "type": "Feature",
  "properties": {
    "iso:country":"GB",
    "sg:address":"Hardings Farm",
    "sg:city":"Ingatestone",
    "sg:classifiers":[
        {
            "category":"Building & Trades",
            "subcategory":"Electrical",
            "type":"Services"
        }
    ],
    "sg:postcode":"CM4 0HZ",
    "sg:province":"Essex",
    "sg:tags":[
        "lighting"
    ],
    "wof:name":"Lumisphere Products Ltd.",
    "wof:placetype":"venue"
},
  "geometry": {"coordinates":[0.383585,51.669922],"type":"Point"}
}