{
  "type": "Feature",
  "properties": {
    "addr:full":"Westgate House, Westgate Walsall Staffordshire WS9 8EX",
    "addr:postcode":"ws9 8ex",
    "addr:street":"Westgate;Westgate",
    "iso:country":"GB",
    "sg:address":"Westgate House, Westgate",
    "sg:city":"Walsall",
    "sg:classifiers":[
        {
            "category":"Banks & Credit Unions",
            "subcategory":"Bank",
            "type":"Services"
        }
    ],
    "sg:phone":"+44 1922 452333",
    "sg:postcode":"WS9 8EX",
    "sg:province":"Staffordshire",
    "sg:tags":[
        "belt",
        "conveyor"
    ],
    "wof:name":"Owens Conveyor Co.",
    "wof:placetype":"venue"
},
  "geometry": {"coordinates":[-1.942856,52.609409],"type":"Point"}
}