{
  "type": "Feature",
  "properties": {
    "addr:full":"Unit 2 Jarman Way Chard Devon TA20 1FB",
    "addr:housenumber":"unit 2",
    "addr:postcode":"ta20 1fb",
    "addr:street":"Jarman Way",
    "iso:country":"GB",
    "sg:address":"Unit 2 Jarman Way",
    "sg:city":"Chard",
    "sg:classifiers":[
        {
            "category":"Manufacturing",
            "subcategory":"Apparel",
            "type":"Manufacturing & Wholesale Goods"
        }
    ],
    "sg:phone":"+44 1460 61511",
    "sg:postcode":"TA20 1FB",
    "sg:province":"Devon",
    "sg:tags":[
        "shirt",
        "maker"
    ],
    "wof:name":"Cleeve of London Ltd.",
    "wof:placetype":"venue"
},
  "geometry": {"coordinates":[-2.9546198845,50.8845596313],"type":"Point"}
}