{
  "type": "Feature",
  "properties": {
    "addr:full":"Po Box 55 88 Thatcham Berkshire RG19 8XY",
    "addr:housenumber":"po box 55 88",
    "addr:postcode":"rg19 8xy",
    "iso:country":"GB",
    "sg:address":"Po Box 55 88",
    "sg:city":"Thatcham",
    "sg:classifiers":[
        {
            "category":"Home & Garden",
            "subcategory":"Home Furnishings",
            "type":"Retail Goods"
        }
    ],
    "sg:postcode":"RG19 8XY",
    "sg:province":"Berkshire",
    "sg:tags":[
        "household",
        "furniture"
    ],
    "wof:name":"Jeremy Loxton & Co.",
    "wof:placetype":"venue"
},
  "geometry": {"coordinates":[-1.2546789646,51.3729782104],"type":"Point"}
}