{
  "type": "Feature",
  "properties": {
    "addr:full":"1 Aalborg Square Lancaster Lancashire LA1 1GG",
    "addr:housenumber":"1",
    "addr:postcode":"la1 1gg",
    "addr:street":"Aalborg Square",
    "iso:country":"GB",
    "sg:address":"1 Aalborg Square",
    "sg:city":"Lancaster",
    "sg:classifiers":[
        {
            "category":"Professional",
            "subcategory":"Employment Agencies",
            "type":"Services"
        }
    ],
    "sg:phone":"+44 1524 387600",
    "sg:postcode":"LA1 1GG",
    "sg:province":"Lancashire",
    "sg:tags":[
        "career",
        "guidance"
    ],
    "wof:name":"Careers Service Lancashire Area West Ltd.",
    "wof:placetype":"venue"
},
  "geometry": {"coordinates":[-2.79693,54.046253],"type":"Point"}
}