{
  "type": "Feature",
  "properties": {
    "addr:full":"Seckford Hall Road, Great Bealings Woodbridge Suffolk IP13 6NU",
    "addr:postcode":"ip13 6nu",
    "addr:street":"Hall Road",
    "iso:country":"GB",
    "sg:address":"Seckford Hall Road, Great Bealings",
    "sg:city":"Woodbridge",
    "sg:classifiers":[
        {
            "category":"Travel",
            "subcategory":"Hotels & Motels",
            "type":"Entertainment"
        },
        {
            "category":"Retail",
            "subcategory":"Auto Repair",
            "type":"Services"
        }
    ],
    "sg:phone":"+44 1394 385678",
    "sg:postcode":"IP13 6NU",
    "sg:province":"Suffolk",
    "sg:tags":[
        "modification",
        "garage"
    ],
    "wof:name":"Seckford Hall Hotel Ltd.",
    "wof:placetype":"venue"
},
  "geometry": {"coordinates":[1.2576049566,52.093585968],"type":"Point"}
}