{
  "type": "Feature",
  "properties": {
    "iso:country":"GB",
    "sg:address":"19 Neilston Road",
    "sg:city":"Paisley",
    "sg:classifiers":[
        {
            "category":"Shopping",
            "subcategory":"Pharmacy",
            "type":"Retail Goods"
        }
    ],
    "sg:phone":"+44 141 889 2216",
    "sg:postcode":"PA2 6LL",
    "sg:province":"East Renfrewshire",
    "sg:tags":[
        "pharmacist",
        "chemist"
    ],
    "wof:name":"Bannermans",
    "wof:placetype":"venue"
},
  "geometry": {"coordinates":[-4.424452,55.838177],"type":"Point"}
}