{
  "type": "Feature",
  "properties": {
    "iso:country":"GB",
    "sg:address":"Holly Ho, 26 Barrack St",
    "sg:city":"Bridport",
    "sg:classifiers":[
        {
            "category":"Real Estate",
            "subcategory":"Architect",
            "type":"Services"
        }
    ],
    "sg:postcode":"DT6 3LY",
    "sg:province":"Dorset",
    "wof:name":"Pinion,Roy A,",
    "wof:placetype":"venue"
},
  "geometry": {"coordinates":[-2.758019,50.733566],"type":"Point"}
}