{
  "type": "Feature",
  "properties": {
    "addr:full":"36-38 Gilda Parade Bristol City of Bristol BS14 9HY",
    "addr:housenumber":"36-38",
    "addr:postcode":"bs14 9hy",
    "addr:street":"Gilda Parade",
    "iso:country":"GB",
    "sg:address":"36-38 Gilda Parade",
    "sg:city":"Bristol",
    "sg:classifiers":[
        {
            "category":"Communications",
            "type":"Services"
        }
    ],
    "sg:phone":"+44 1275 833096",
    "sg:postcode":"BS14 9HY",
    "sg:province":"City of Bristol",
    "sg:tags":[
        "tv",
        "video",
        "radio"
    ],
    "wof:name":"H & R Vision",
    "wof:placetype":"venue"
},
  "geometry": {"coordinates":[-2.5657150745,51.4163742065],"type":"Point"}
}