{"geometry":{"type":"Point","coordinates":[-0.272958,50.932102]},"type":"Feature","id":102560687,"bbox":[-0.272958,50.932102,-0.272958,50.932102],"properties":{"sg:province":"West Sussex","sg:tags":["rest"],"geom:longitude":-0.272958,"wof:breaches":[],"sg:href":"http://api.simplegeo.com/1.0/features/SG_4bbXLykt4XdPwE7YQAQgsn_50.932102_-0.272958@1300740015.json","sg:owner":"simplegeo","sg:postcode":"BN5 9NR","geom:latitude":50.932102,"sg:classifiers":[{"category":"Social Services","type":"Services","subcategory":"Retirement Home"}],"sg:address":"Church St","sg:phone":"+44 1273 492881","wof:hierarchy":[{"locality_id":101853485,"venue_id":102560687,"country_id":85633159,"region_id":85684583}],"geom:area":0.000000,"sg:city":"Henfield","wof:lastmodified":1438093329,"iso:country":"GB","wof:geomhash":"2e74cb9db0eee415e64793b8f8b4bb0b","wof:name":"Martyn Lodge","wof:belongsto":[101853485,85633159,85684583],"src:geom":"simplegeo","wof:placetype":"venue","wof:supersedes":[],"wof:id":102560687,"wof:superseded_by":[],"wof:concordances":{"sg:id":"SG_4bbXLykt4XdPwE7YQAQgsn_50.932102_-0.272958@1300740015"},"wof:parent_id":101853485}}