{
  "type": "Feature",
  "properties": {
    "addr:full":"Church St Henfield West Sussex BN5 9NR",
    "addr:postcode":"bn5 9nr",
    "addr:street":"Church St",
    "iso:country":"GB",
    "sg:address":"Church St",
    "sg:city":"Henfield",
    "sg:classifiers":[
        {
            "category":"Social Services",
            "subcategory":"Retirement Home",
            "type":"Services"
        }
    ],
    "sg:href":"http://api.simplegeo.com/1.0/features/SG_4bbXLykt4XdPwE7YQAQgsn_50.932102_-0.272958@1300740015.json",
    "sg:phone":"+44 1273 492881",
    "sg:postcode":"BN5 9NR",
    "sg:province":"West Sussex",
    "sg:tags":[
        "rest"
    ],
    "wof:name":"Martyn Lodge",
    "wof:placetype":"venue"
},
  "geometry": {"coordinates":[-0.272958,50.932102],"type":"Point"}
}