{
  "type": "Feature",
  "properties": {
    "addr:full":"Shepherds Cottage, Attleford Lane, Shackleford Godalming Surrey GU8 6BL",
    "addr:postcode":"gu8 6bl",
    "addr:street":"Attleford Lane",
    "iso:country":"GB",
    "sg:address":"Shepherds Cottage, Attleford Lane, Shackleford",
    "sg:city":"Godalming",
    "sg:classifiers":[
        {
            "category":"Building & Trades",
            "subcategory":"Construction",
            "type":"Services"
        }
    ],
    "sg:phone":"+44 1252 703311",
    "sg:postcode":"GU8 6BL",
    "sg:province":"Surrey",
    "sg:tags":[
        "restoration",
        "refurbishment"
    ],
    "wof:name":"N M Interiors",
    "wof:placetype":"venue"
},
  "geometry": {"coordinates":[-0.662429,51.199493],"type":"Point"}
}