{
  "type": "Feature",
  "properties": {
    "addr:full":"Wild Acre, Kirk Lane, Hipperholme Halifax West Yorkshire HX3 8EU",
    "addr:postcode":"hx3 8eu",
    "addr:street":"Wild;Kirk Lane",
    "iso:country":"GB",
    "sg:address":"Wild Acre, Kirk Lane, Hipperholme",
    "sg:city":"Halifax",
    "sg:classifiers":[
        {
            "category":"Retail",
            "subcategory":"Funeral Services",
            "type":"Services"
        }
    ],
    "sg:postcode":"HX3 8EU",
    "sg:province":"West Yorkshire",
    "wof:name":"R Kenyon & Co",
    "wof:placetype":"venue"
},
  "geometry": {"coordinates":[-1.808218956,53.7263412476],"type":"Point"}
}