{
  "type": "Feature",
  "properties": {
    "addr:full":"Liberty 2 Romford Essex RM1 3EE",
    "addr:housenumber":"2",
    "addr:postcode":"rm1 3ee",
    "iso:country":"GB",
    "sg:address":"Liberty 2",
    "sg:city":"Romford",
    "sg:classifiers":[
        {
            "category":"Shopping",
            "subcategory":"Clothing, Apparel, & Fashions",
            "type":"Retail Goods"
        }
    ],
    "sg:phone":"+44 1708 767857",
    "sg:postcode":"RM1 3EE",
    "sg:province":"Essex",
    "sg:tags":[
        "shop"
    ],
    "wof:name":"Peacock's Stores Ltd.",
    "wof:placetype":"venue"
},
  "geometry": {"coordinates":[0.184514001,51.5803337097],"type":"Point"}
}