{
  "type": "Feature",
  "properties": {
    "addr:full":"10/11 North Pallant Chichester West Sussex PO19 1TQ",
    "addr:housenumber":"10 / 11",
    "addr:postcode":"po19 1tq",
    "addr:street":"North Pallant",
    "iso:country":"GB",
    "sg:address":"10/11 North Pallant",
    "sg:city":"Chichester",
    "sg:classifiers":[
        {
            "category":"Freight",
            "type":"Transportation"
        }
    ],
    "sg:postcode":"PO19 1TQ",
    "sg:province":"West Sussex",
    "sg:tags":[
        "haulage",
        "road"
    ],
    "wof:name":"Eurosurv Transport Ltd.",
    "wof:placetype":"venue"
},
  "geometry": {"coordinates":[-0.7780539989,50.8356399536],"type":"Point"}
}