{
  "type": "Feature",
  "properties": {
    "iso:country":"GB",
    "sg:address":"296a Queens Road",
    "sg:city":"Halifax",
    "sg:classifiers":[
        {
            "category":"Taxi",
            "type":"Transportation"
        },
        {
            "category":"Military Area",
            "subcategory":"Air Force Base",
            "type":"Public Place"
        }
    ],
    "sg:phone":"+44 1422 341231",
    "sg:postcode":"HX1 4NS",
    "sg:province":"West Yorkshire",
    "sg:tags":[
        "hire",
        "private",
        "vehicle"
    ],
    "wof:name":"Pennine Taxis Ltd",
    "wof:placetype":"venue"
},
  "geometry": {"coordinates":[-1.8810470104,53.7259368896],"type":"Point"}
}