{
  "type": "Feature",
  "properties": {
    "iso:country":"GB",
    "sg:address":"Charity Farm House, Charity Lane",
    "sg:city":"Ipswich",
    "sg:classifiers":[
        {
            "category":"Wholesale",
            "subcategory":"Groceries",
            "type":"Manufacturing & Wholesale Goods"
        }
    ],
    "sg:phone":"+44 1473 785883",
    "sg:postcode":"IP6 9NB",
    "sg:province":"Suffolk",
    "sg:tags":[
        "food",
        "supplier",
        "drink"
    ],
    "wof:name":"Tastes of Anglia Ltd.",
    "wof:placetype":"venue"
},
  "geometry": {"coordinates":[1.2151969671,52.1343612671],"type":"Point"}
}