{
  "type": "Feature",
  "properties": {
    "addr:full":"107 Cliddesden Rd Basingstoke Hampshire RG21 3EY",
    "addr:housenumber":"107",
    "addr:postcode":"rg21 3ey",
    "addr:street":"Cliddesden Rd",
    "iso:country":"GB",
    "sg:address":"107 Cliddesden Rd",
    "sg:city":"Basingstoke",
    "sg:classifiers":[
        {
            "category":"Restaurant",
            "type":"Food & Drink"
        }
    ],
    "sg:phone":"+44 1256 328528",
    "sg:postcode":"RG21 3EY",
    "sg:province":"Hampshire",
    "wof:name":"Quills",
    "wof:placetype":"venue"
},
  "geometry": {"coordinates":[-1.0869890451,51.2535591125],"type":"Point"}
}