{
  "type": "Feature",
  "properties": {
    "iso:country":"GB",
    "sg:address":"35 Bedford Road, Clophill",
    "sg:city":"Bedford",
    "sg:classifiers":[
        {
            "category":"Real Estate",
            "subcategory":"Architect",
            "type":"Services"
        }
    ],
    "sg:postcode":"MK45 4AE",
    "sg:province":"Bedfordshire",
    "wof:name":"V G Grabecki",
    "wof:placetype":"venue"
},
  "geometry": {"coordinates":[-0.4274950027,51.966293335],"type":"Point"}
}