{
  "type": "Feature",
  "properties": {
    "iso:country":"GB",
    "sg:address":"103 Windsor Rd",
    "sg:city":"Halesowen",
    "sg:classifiers":[
        {
            "category":"Building & Trades",
            "subcategory":"Plumbing",
            "type":"Services"
        }
    ],
    "sg:phone":"+44 121 550 3514",
    "sg:postcode":"B63 4BH",
    "sg:province":"West Midlands",
    "sg:tags":[
        "heating"
    ],
    "wof:name":"J M",
    "wof:placetype":"venue"
},
  "geometry": {"coordinates":[-2.061664,52.449646],"type":"Point"}
}