{
  "type": "Feature",
  "properties": {
    "addr:full":"423a Ewell Road Surbiton Surrey KT6 7DG",
    "addr:housenumber":"423a",
    "addr:postcode":"kt6 7dg",
    "addr:street":"Ewell Road",
    "iso:country":"GB",
    "sg:address":"423a Ewell Road",
    "sg:city":"Surbiton",
    "sg:classifiers":[
        {
            "category":"Professional",
            "subcategory":"Engineering",
            "type":"Services"
        }
    ],
    "sg:phone":"+44 20 8241 8272",
    "sg:postcode":"KT6 7DG",
    "sg:province":"Surrey",
    "sg:tags":[
        "electronic",
        "engineer"
    ],
    "wof:name":"Williams Electronic Design Ltd.",
    "wof:placetype":"venue"
},
  "geometry": {"coordinates":[-0.281972,51.382301],"type":"Point"}
}