{
  "type": "Feature",
  "properties": {
    "iso:country":"GB",
    "sg:address":"Huntingdon House, Princess Street",
    "sg:city":"Bolton",
    "sg:classifiers":[
        {
            "category":"Shopping",
            "subcategory":"Discount & Variety Stores",
            "type":"Retail Goods"
        }
    ],
    "sg:phone":"+44 1204 363634",
    "sg:postcode":"BL1 1EJ",
    "sg:province":"Lancashire",
    "sg:tags":[
        "cleaning",
        "supply"
    ],
    "wof:name":"Sachtleben Chemie Gmbh",
    "wof:placetype":"venue"
},
  "geometry": {"coordinates":[-2.426024,53.578983],"type":"Point"}
}