{
  "type": "Feature",
  "properties": {
    "addr:full":"St Claire, Bowfield Road Johnstone Renfrewshire PA9 1BZ",
    "addr:postcode":"pa9 1bz",
    "addr:street":"Bowfield Road",
    "iso:country":"GB",
    "sg:address":"St Claire, Bowfield Road",
    "sg:city":"Johnstone",
    "sg:classifiers":[
        {
            "category":"Building & Trades",
            "subcategory":"Construction",
            "type":"Services"
        }
    ],
    "sg:postcode":"PA9 1BZ",
    "sg:province":"Renfrewshire",
    "sg:tags":[
        "builder"
    ],
    "wof:name":"Martin McCambridge",
    "wof:placetype":"venue"
},
  "geometry": {"coordinates":[-4.55899,55.80756],"type":"Point"}
}