{
  "type": "Feature",
  "properties": {
    "addr:full":"41 Ringstead Road Sutton Surrey SM1 4SJ",
    "addr:housenumber":"41",
    "addr:postcode":"sm1 4sj",
    "addr:street":"Ringstead Road",
    "iso:country":"GB",
    "sg:address":"41 Ringstead Road",
    "sg:city":"Sutton",
    "sg:classifiers":[
        {
            "category":"Communications",
            "type":"Services"
        }
    ],
    "sg:postcode":"SM1 4SJ",
    "sg:province":"Surrey",
    "sg:tags":[
        "data",
        "network"
    ],
    "wof:name":"Technique Data Ltd",
    "wof:placetype":"venue"
},
  "geometry": {"coordinates":[-0.177904,51.365593],"type":"Point"}
}