{
  "type": "Feature",
  "properties": {
    "addr:full":"Beech Avenue Exeter Devon EX4 6HE",
    "addr:postcode":"ex4 6he",
    "addr:street":"Beech Avenue",
    "iso:country":"GB",
    "sg:address":"Beech Avenue",
    "sg:city":"Exeter",
    "sg:classifiers":[
        {
            "category":"Health Services",
            "subcategory":"Nursing And Care Facility",
            "type":"Services"
        }
    ],
    "sg:postcode":"EX4 6HE",
    "sg:province":"Devon",
    "sg:tags":[
        "home"
    ],
    "wof:name":"Mornexe Nursing Home",
    "wof:placetype":"venue"
},
  "geometry": {"coordinates":[-3.521534,50.73756],"type":"Point"}
}