{
  "type": "Feature",
  "properties": {
    "addr:full":", Clopton Kettering Northamptonshire NN14 3DZ",
    "addr:postcode":"nn14 3dz",
    "iso:country":"GB",
    "sg:address":", Clopton",
    "sg:city":"Kettering",
    "sg:classifiers":[
        {
            "category":"Government",
            "subcategory":"Post Office",
            "type":"Public Place"
        }
    ],
    "sg:phone":"+44 1832 720220",
    "sg:postcode":"NN14 3DZ",
    "sg:province":"Northamptonshire",
    "wof:name":"Clopton PO",
    "wof:placetype":"venue"
},
  "geometry": {"coordinates":[-0.4385040104,52.410610199],"type":"Point"}
}