{
  "type": "Feature",
  "properties": {
    "addr:full":"140-142 Elm Road Wisbech Cambridgeshire PE13 2SG",
    "addr:housenumber":"140-142",
    "addr:postcode":"pe13 2sg",
    "addr:street":"Elm Road",
    "iso:country":"GB",
    "sg:address":"140-142 Elm Road",
    "sg:city":"Wisbech",
    "sg:classifiers":[
        {
            "category":"Food & Beverages",
            "subcategory":"Groceries & Convenience Stores",
            "type":"Retail Goods"
        }
    ],
    "sg:phone":"+44 1945 584547",
    "sg:postcode":"PE13 2SG",
    "sg:province":"Cambridgeshire",
    "wof:name":"B & E Driver",
    "wof:placetype":"venue"
},
  "geometry": {"coordinates":[0.1680489928,52.6555023193],"type":"Point"}
}