{
  "type": "Feature",
  "properties": {
    "iso:country":"GB",
    "sg:address":"5 Spital St",
    "sg:city":"Dartford",
    "sg:classifiers":[
        {
            "category":"Real Estate",
            "subcategory":"Real Estate Agent",
            "type":"Services"
        }
    ],
    "sg:phone":"+44 1322 229433",
    "sg:postcode":"DA1 2DJ",
    "sg:province":"Kent",
    "wof:name":"Woolwich Property Services",
    "wof:placetype":"venue"
},
  "geometry": {"coordinates":[0.214578,51.444939],"type":"Point"}
}