{
  "type": "Feature",
  "properties": {
    "addr:full":"9a Leicester Road, Anstley Leicester Leicestershire LE7 7AT",
    "addr:housenumber":"9a",
    "addr:postcode":"le7 7at",
    "addr:street":"Leicester Road Anstley",
    "iso:country":"GB",
    "sg:address":"9a Leicester Road, Anstley",
    "sg:city":"Leicester",
    "sg:classifiers":[
        {
            "category":"Professional",
            "subcategory":"Computer Services",
            "type":"Services"
        }
    ],
    "sg:postcode":"LE7 7AT",
    "sg:province":"Leicestershire",
    "sg:tags":[
        "system",
        "software"
    ],
    "wof:name":"C A Designs (Leicester) Ltd.",
    "wof:placetype":"venue"
},
  "geometry": {"coordinates":[-1.186123,52.67207],"type":"Point"}
}