{
  "type": "Feature",
  "properties": {
    "addr:full":"Longueville House, Hawks Mill Street Ipswich Suffolk IP6 8AA",
    "addr:postcode":"ip6 8aa",
    "addr:street":"Hawks Mill Street",
    "iso:country":"GB",
    "sg:address":"Longueville House, Hawks Mill Street",
    "sg:city":"Ipswich",
    "sg:classifiers":[
        {
            "category":"Home & Garden",
            "subcategory":"Household Appliances",
            "type":"Retail Goods"
        }
    ],
    "sg:phone":"+44 1449 720380",
    "sg:postcode":"IP6 8AA",
    "sg:province":"Suffolk",
    "sg:tags":[
        "domestic",
        "centre"
    ],
    "wof:name":"E T Coleman",
    "wof:placetype":"venue"
},
  "geometry": {"coordinates":[1.0515249968,52.1572685242],"type":"Point"}
}