{
  "type": "Feature",
  "properties": {
    "addr:full":"1 Wilbraham Road, Acton Nantwich Cheshire CW5 8LQ",
    "addr:housenumber":"1",
    "addr:postcode":"cw5 8lq",
    "addr:street":"Wilbraham Road",
    "iso:country":"GB",
    "sg:address":"1 Wilbraham Road, Acton",
    "sg:city":"Nantwich",
    "sg:classifiers":[
        {
            "category":"Shopping",
            "subcategory":"Stationery & Office Supplies",
            "type":"Retail Goods"
        },
        {
            "category":"Building & Trades",
            "subcategory":"Cleaning & Sanitation",
            "type":"Services"
        }
    ],
    "sg:postcode":"CW5 8LQ",
    "sg:province":"Cheshire",
    "sg:tags":[
        "item",
        "organiser",
        "exhibition",
        "fair",
        "promotional"
    ],
    "wof:name":"Excellent Group",
    "wof:placetype":"venue"
},
  "geometry": {"coordinates":[-2.550177,53.074718],"type":"Point"}
}