{
  "type": "Feature",
  "properties": {
    "addr:full":"1172-1180 Christchurch Rd Bournemouth Dorset BH7 6DY",
    "addr:housenumber":"1172-1180",
    "addr:postcode":"bh7 6dy",
    "addr:street":"Christchurch Rd",
    "iso:country":"GB",
    "sg:address":"1172-1180 Christchurch Rd",
    "sg:city":"Bournemouth",
    "sg:classifiers":[
        {
            "category":"Autos & Motor Vehicles",
            "subcategory":"Automobile Sales",
            "type":"Retail Goods"
        }
    ],
    "sg:postcode":"BH7 6DY",
    "sg:province":"Dorset",
    "sg:tags":[
        "car"
    ],
    "wof:name":"Swanmore Garage",
    "wof:placetype":"venue"
},
  "geometry": {"coordinates":[-1.8152190447,50.7356262207],"type":"Point"}
}