{
  "type": "Feature",
  "properties": {
    "addr:full":"Ravenstone Street London Greater London SW12 9SS",
    "addr:postcode":"sw12 9ss",
    "addr:street":"Ravenstone Street",
    "iso:country":"GB",
    "sg:address":"Ravenstone Street",
    "sg:city":"London",
    "sg:classifiers":[
        {
            "category":"Education",
            "subcategory":"School",
            "type":"Public Place"
        }
    ],
    "sg:phone":"+44 20 8673 8277",
    "sg:postcode":"SW12 9SS",
    "sg:province":"Greater London",
    "sg:tags":[
        "local",
        "authority"
    ],
    "wof:name":"Ravenstone Primary School",
    "wof:placetype":"venue"
},
  "geometry": {"coordinates":[-0.1525779963,51.4418525696],"type":"Point"}
}