{
  "type": "Feature",
  "properties": {
    "addr:full":"Access House, The Promenade Bristol City of Bristol BS8 3AQ",
    "addr:postcode":"bs8 3aq",
    "addr:street":"The Promenade",
    "iso:country":"GB",
    "sg:address":"Access House, The Promenade",
    "sg:city":"Bristol",
    "sg:classifiers":[
        {
            "category":"Shopping",
            "subcategory":"Stationery & Office Supplies",
            "type":"Retail Goods"
        }
    ],
    "sg:phone":"+44 117 933 1000",
    "sg:postcode":"BS8 3AQ",
    "sg:province":"City of Bristol",
    "sg:tags":[
        "printers'"
    ],
    "wof:name":"Access Plus Print Management Ltd.",
    "wof:placetype":"venue"
},
  "geometry": {"coordinates":[-2.592892,51.47121],"type":"Point"}
}