{
  "type": "Feature",
  "properties": {
    "addr:full":"20 Compton Terr, London Greater London N1 2UN",
    "addr:housenumber":"20",
    "addr:postcode":"n1 2un",
    "addr:street":"Compton Terr",
    "iso:country":"GB",
    "sg:address":"20 Compton Terr,",
    "sg:city":"London",
    "sg:classifiers":[
        {
            "category":"Professional",
            "subcategory":"Lawyer & Legal Services",
            "type":"Services"
        }
    ],
    "sg:postcode":"N1 2UN",
    "sg:province":"Greater London",
    "wof:name":"Children's Legal Centre Ltd (The)",
    "wof:placetype":"venue"
},
  "geometry": {"coordinates":[-0.1026709974,51.544921875],"type":"Point"}
}