{
  "type": "Feature",
  "properties": {
    "iso:country":"GB",
    "sg:address":"Castlemains",
    "sg:city":"Sanquhar",
    "sg:classifiers":[
        {
            "category":"Farming",
            "subcategory":"Livestock Farm",
            "type":"Manufacturing & Wholesale Goods"
        }
    ],
    "sg:phone":"+44 1659 50310",
    "sg:postcode":"DG4 6HN",
    "sg:province":"Dumfries and Galloway",
    "sg:tags":[
        "others"
    ],
    "wof:name":"Archibald Kirk",
    "wof:placetype":"venue"
},
  "geometry": {"coordinates":[-3.920284,55.366493],"type":"Point"}
}