{
  "type": "Feature",
  "properties": {
    "iso:country":"GB",
    "sg:address":"111 London Rd",
    "sg:city":"Luton",
    "sg:classifiers":[
        {
            "category":"Organizations",
            "subcategory":"Non-profit Organization",
            "type":"Services"
        }
    ],
    "sg:phone":"+44 1582 736966",
    "sg:postcode":"LU1 3RH",
    "sg:province":"Bedfordshire",
    "sg:tags":[
        "organisation",
        "voluntary",
        "charity"
    ],
    "wof:name":"Bedfordshire Social Services",
    "wof:placetype":"venue"
},
  "geometry": {"coordinates":[-0.417686,51.866322],"type":"Point"}
}