{
  "type": "Feature",
  "properties": {
    "iso:country":"GB",
    "sg:address":"Strippers Point, Goonabarn, St Stephen",
    "sg:city":"St Austell",
    "sg:classifiers":[
        {
            "category":"Military Area",
            "subcategory":"Air Force Base",
            "type":"Public Place"
        }
    ],
    "sg:postcode":"PL26 7QZ",
    "sg:province":"Cornwall",
    "sg:tags":[
        "taxi",
        "hire",
        "private"
    ],
    "wof:name":"Central Cabs",
    "wof:placetype":"venue"
},
  "geometry": {"coordinates":[-4.8719000816,50.357170105],"type":"Point"}
}