{
  "type": "Feature",
  "properties": {
    "iso:country":"GB",
    "sg:address":"Front Street, Burnopfield",
    "sg:city":"Newcastle-upon-tyne",
    "sg:classifiers":[
        {
            "category":"Education",
            "subcategory":"School",
            "type":"Public Place"
        },
        {
            "category":"Government",
            "subcategory":"Office",
            "type":"Public Place"
        }
    ],
    "sg:phone":"+44 1207 270397",
    "sg:postcode":"NE16 6PT",
    "sg:province":"Durham",
    "sg:tags":[
        "local",
        "authority"
    ],
    "wof:name":"Burnopfield Primary School",
    "wof:placetype":"venue"
},
  "geometry": {"coordinates":[-1.727454,54.906704],"type":"Point"}
}