{
  "type": "Feature",
  "properties": {
    "addr:full":"Waterhouse, High Street Etchingham East Sussex TN19 7AH",
    "addr:postcode":"tn19 7ah",
    "addr:street":"High Street",
    "iso:country":"GB",
    "sg:address":"Waterhouse, High Street",
    "sg:city":"Etchingham",
    "sg:classifiers":[
        {
            "category":"Shopping",
            "subcategory":"Florist",
            "type":"Retail Goods"
        }
    ],
    "sg:phone":"+44 1580 819312",
    "sg:postcode":"TN19 7AH",
    "sg:province":"East Sussex",
    "wof:name":"Valerie Floral Art",
    "wof:placetype":"venue"
},
  "geometry": {"coordinates":[0.4416419864,51.0093803406],"type":"Point"}
}