{
  "type": "Feature",
  "properties": {
    "iso:country":"GB",
    "sg:address":"128 Bennett Road",
    "sg:city":"Bournemouth",
    "sg:classifiers":[
        {
            "category":"Organizations",
            "subcategory":"Membership Organization",
            "type":"Services"
        }
    ],
    "sg:postcode":"BH8 8RN",
    "sg:province":"Dorset",
    "sg:tags":[
        "club"
    ],
    "wof:name":"Studland United Nudists Ltd.",
    "wof:placetype":"venue"
},
  "geometry": {"coordinates":[-1.8548699617,50.73620224],"type":"Point"}
}