{
  "type": "Feature",
  "properties": {
    "iso:country":"GB",
    "sg:address":"5 Frobisher Street",
    "sg:city":"Stoke-on-trent",
    "sg:classifiers":[
        {
            "category":"Bars & Pubs",
            "type":"Food & Drink"
        }
    ],
    "sg:postcode":"ST6 8PD",
    "sg:province":"Staffordshire",
    "sg:tags":[
        "pubs",
        "inn"
    ],
    "wof:name":"The Foaming Quart",
    "wof:placetype":"venue"
},
  "geometry": {"coordinates":[-2.1501278877,53.0661888123],"type":"Point"}
}