{
  "type": "Feature",
  "properties": {
    "addr:full":"Maidstone Road Felixstowe Suffolk IP11 9EF",
    "addr:postcode":"ip11 9ef",
    "addr:street":"Maidstone Road",
    "iso:country":"GB",
    "sg:address":"Maidstone Road",
    "sg:city":"Felixstowe",
    "sg:classifiers":[
        {
            "category":"Community Center",
            "type":"Public Place"
        },
        {
            "category":"Government",
            "subcategory":"Office",
            "type":"Public Place"
        }
    ],
    "sg:phone":"+44 1394 283091",
    "sg:postcode":"IP11 9EF",
    "sg:province":"Suffolk",
    "sg:tags":[
        "local",
        "centre"
    ],
    "wof:name":"Felixstowe Community Resource Unit",
    "wof:placetype":"venue"
},
  "geometry": {"coordinates":[1.336313,51.971428],"type":"Point"}
}