{
  "type": "Feature",
  "properties": {
    "addr:full":"Unit 4, Airspeed Rd, Priory Ind Est Christchurch Dorset BH23 4HD",
    "addr:housenumber":"unit 4",
    "addr:postcode":"est;bh23 4hd",
    "addr:street":"Airspeed Rd",
    "iso:country":"GB",
    "sg:address":"Unit 4, Airspeed Rd, Priory Ind Est",
    "sg:city":"Christchurch",
    "sg:classifiers":[
        {
            "category":"Manufacturing",
            "subcategory":"Rubber & Plastics",
            "type":"Manufacturing & Wholesale Goods"
        }
    ],
    "sg:phone":"+44 1425 278092",
    "sg:postcode":"BH23 4HD",
    "sg:province":"Dorset",
    "sg:tags":[
        "product"
    ],
    "wof:name":"Shrinkwrap",
    "wof:placetype":"venue"
},
  "geometry": {"coordinates":[-1.735384,50.738091],"type":"Point"}
}