{
  "type": "Feature",
  "properties": {
    "addr:full":"78 Warmingham Lane Middlewich Cheshire CW10 0DJ",
    "addr:housenumber":"78",
    "addr:postcode":"cw10 0dj",
    "addr:street":"Warmingham Lane",
    "iso:country":"GB",
    "sg:address":"78 Warmingham Lane",
    "sg:city":"Middlewich",
    "sg:classifiers":[
        {
            "category":"Bars & Pubs",
            "type":"Food & Drink"
        }
    ],
    "sg:phone":"+44 1606 738714",
    "sg:postcode":"CW10 0DJ",
    "sg:province":"Cheshire",
    "sg:tags":[
        "pubs",
        "house",
        "inn",
        "public",
        "activity"
    ],
    "wof:name":"The Turnpike",
    "wof:placetype":"venue"
},
  "geometry": {"coordinates":[-2.4389090538,53.1826782227],"type":"Point"}
}