{
  "type": "Feature",
  "properties": {
    "addr:full":"32 Standing Butts Close, Walton On Trent Swadlincote Derbyshire DE12 8NJ",
    "addr:housenumber":"32",
    "addr:postcode":"de12 8nj",
    "addr:street":"Standing Butts Close",
    "iso:country":"GB",
    "sg:address":"32 Standing Butts Close, Walton On Trent",
    "sg:city":"Swadlincote",
    "sg:classifiers":[
        {
            "category":"Building & Trades",
            "subcategory":"Construction",
            "type":"Services"
        }
    ],
    "sg:postcode":"DE12 8NJ",
    "sg:province":"Derbyshire",
    "sg:tags":[
        "joiner",
        "carpenter"
    ],
    "wof:name":"Coates Joinery",
    "wof:placetype":"venue"
},
  "geometry": {"coordinates":[-1.676939,52.757462],"type":"Point"}
}