{
  "type": "Feature",
  "properties": {
    "iso:country":"GB",
    "sg:address":"Alice Street",
    "sg:city":"Keighley",
    "sg:classifiers":[
        {
            "category":"Retail",
            "subcategory":"Auto Repair",
            "type":"Services"
        }
    ],
    "sg:phone":"+44 1535 662523",
    "sg:postcode":"BD21 3JD",
    "sg:province":"West Yorkshire",
    "sg:tags":[
        "modification",
        "garage"
    ],
    "wof:name":"Sunwin Motors Peugot Centre",
    "wof:placetype":"venue"
},
  "geometry": {"coordinates":[-1.909179,53.86935],"type":"Point"}
}