{
  "type": "Feature",
  "properties": {
    "iso:country":"GB",
    "sg:address":"Wallbrook House, 23-29 Walbrook",
    "sg:city":"London",
    "sg:classifiers":[
        {
            "category":"Professional",
            "subcategory":"Business Services",
            "type":"Services"
        }
    ],
    "sg:postcode":"EC4N 8BT",
    "sg:province":"Greater London",
    "sg:tags":[
        "trade"
    ],
    "wof:name":"The Helios Group London",
    "wof:placetype":"venue"
},
  "geometry": {"coordinates":[-0.09029,51.51265],"type":"Point"}
}