{
  "type": "Feature",
  "properties": {
    "addr:full":"Julians, West Putford Holsworthy Cornwall EX22 7UY",
    "addr:housenumber":"putford",
    "addr:postcode":"ex22 7uy",
    "iso:country":"GB",
    "sg:address":"Julians, West Putford",
    "sg:city":"Holsworthy",
    "sg:classifiers":[
        {
            "category":"Home & Garden",
            "subcategory":"Garden Supply",
            "type":"Retail Goods"
        },
        {
            "category":"Farming",
            "subcategory":"Farm",
            "type":"Manufacturing & Wholesale Goods"
        }
    ],
    "sg:phone":"+44 1409 241374",
    "sg:postcode":"EX22 7UY",
    "sg:province":"Cornwall",
    "sg:tags":[
        "mixed",
        "bulb",
        "crop",
        "grower"
    ],
    "wof:name":"J & E Guy",
    "wof:placetype":"venue"
},
  "geometry": {"coordinates":[-4.3350148201,50.9181480408],"type":"Point"}
}