{
  "type": "Feature",
  "properties": {
    "addr:full":"69-70 Dean Street London Greater London W1D 3SE",
    "addr:housenumber":"69-70",
    "addr:postcode":"w1d 3se",
    "addr:street":"Dean Street",
    "iso:country":"GB",
    "sg:address":"69-70 Dean Street",
    "sg:city":"London",
    "sg:classifiers":[
        {
            "category":"Bars & Pubs",
            "subcategory":"Nightclub",
            "type":"Food & Drink"
        }
    ],
    "sg:phone":"+44 20 7434 4480",
    "sg:postcode":"W1D 3SE",
    "sg:province":"Greater London",
    "sg:tags":[
        "club",
        "night"
    ],
    "wof:name":"Gossips",
    "wof:placetype":"venue"
},
  "geometry": {"coordinates":[-0.1326469928,51.5135345459],"type":"Point"}
}