{
  "type": "Feature",
  "properties": {
    "addr:full":"Mundford Road, Weeting Brandon Norfolk IP27 0PL",
    "addr:postcode":"ip27 0pl",
    "addr:street":"Mundford Road",
    "iso:country":"GB",
    "sg:address":"Mundford Road, Weeting",
    "sg:city":"Brandon",
    "sg:classifiers":[
        {
            "category":"Utilities",
            "subcategory":"Fuel Oil & Lpg",
            "type":"Services"
        },
        {
            "category":"Utilities",
            "subcategory":"Natural Gas",
            "type":"Services"
        }
    ],
    "sg:phone":"+44 1842 811794",
    "sg:postcode":"IP27 0PL",
    "sg:province":"Norfolk",
    "sg:tags":[
        "injector",
        "injection",
        "diesel",
        "system"
    ],
    "wof:name":"Universal Diesel Services",
    "wof:placetype":"venue"
},
  "geometry": {"coordinates":[0.6277819872,52.4590034485],"type":"Point"}
}