{
  "type": "Feature",
  "properties": {
    "iso:country":"GB",
    "sg:address":"Orchard Cottage, Hambleden",
    "sg:city":"Henley-on-thames",
    "sg:classifiers":[
        {
            "category":"Professional",
            "subcategory":"Computer Services",
            "type":"Services"
        }
    ],
    "sg:phone":"+44 1491 412982",
    "sg:postcode":"RG9 6SX",
    "sg:province":"Berkshire",
    "sg:tags":[
        "consultant"
    ],
    "wof:name":"Redkite Systems",
    "wof:placetype":"venue"
},
  "geometry": {"coordinates":[-0.8708059788,51.5703735352],"type":"Point"}
}