{
  "type": "Feature",
  "properties": {
    "iso:country":"GB",
    "sg:address":"12 King St",
    "sg:city":"Portnahaven",
    "sg:classifiers":[
        {
            "category":"Arena",
            "subcategory":"Sports Club",
            "type":"Entertainment"
        }
    ],
    "sg:phone":"+44 1496 860362",
    "sg:postcode":"PA47 7SP",
    "sg:province":"Argyll and Bute",
    "wof:name":"A & C Sporting Services",
    "wof:placetype":"venue"
},
  "geometry": {"coordinates":[-6.5077338219,55.6793174744],"type":"Point"}
}