{
  "type": "Feature",
  "properties": {
    "iso:country":"GB",
    "sg:address":"Po Box 893, Cumbernauld",
    "sg:city":"Glasgow",
    "sg:classifiers":[
        {
            "category":"Manufacturing",
            "subcategory":"Petroleum Products",
            "type":"Manufacturing & Wholesale Goods"
        }
    ],
    "sg:postcode":"G67 3DD",
    "sg:province":"Falkirk",
    "sg:tags":[
        "double",
        "glazing"
    ],
    "wof:name":"B & A Glass Glaziers",
    "wof:placetype":"venue"
},
  "geometry": {"coordinates":[-3.95144,55.9594],"type":"Point"}
}