{
  "type": "Feature",
  "properties": {
    "iso:country":"GB",
    "sg:address":"81 Graverly Lane, Birdington",
    "sg:city":"Birmingham",
    "sg:classifiers":[
        {
            "category":"Home & Garden",
            "subcategory":"Hardware",
            "type":"Retail Goods"
        }
    ],
    "sg:postcode":"B23 6LR",
    "sg:province":"West Midlands",
    "sg:tags":[
        "wheel",
        "castor"
    ],
    "wof:name":"Bournville Wheels Ltd.",
    "wof:placetype":"venue"
},
  "geometry": {"coordinates":[-1.84129,52.528893],"type":"Point"}
}