{
  "type": "Feature",
  "properties": {
    "iso:country":"GB",
    "sg:address":"100 Yarm Lane",
    "sg:city":"Stockton-on-tees",
    "sg:classifiers":[
        {
            "category":"Autos & Motor Vehicles",
            "subcategory":"Automobile Sales",
            "type":"Retail Goods"
        }
    ],
    "sg:phone":"+44 1642 611544",
    "sg:postcode":"TS18 1LB",
    "sg:province":"Durham",
    "sg:tags":[
        "car"
    ],
    "wof:name":"Wentane Motors Ltd.",
    "wof:placetype":"venue"
},
  "geometry": {"coordinates":[-1.3215090036,54.5608482361],"type":"Point"}
}