{
  "type": "Feature",
  "properties": {
    "iso:country":"GB",
    "sg:address":"12 Wilson Rd, Huyton",
    "sg:city":"Liverpool",
    "sg:classifiers":[
        {
            "category":"Shopping",
            "subcategory":"Pets & Pet Supplies",
            "type":"Retail Goods"
        }
    ],
    "sg:phone":"+44 151 480 4377",
    "sg:postcode":"L36 6AF",
    "sg:province":"Merseyside",
    "sg:tags":[
        "food"
    ],
    "wof:name":"Hammond Feeds (Huyton) Ltd",
    "wof:placetype":"venue"
},
  "geometry": {"coordinates":[-2.825839,53.406986],"type":"Point"}
}