{
  "type": "Feature",
  "properties": {
    "iso:country":"GB",
    "sg:address":"45 Waverley Lane",
    "sg:city":"Burton-on-trent",
    "sg:classifiers":[
        {
            "category":"Professional",
            "type":"Services"
        }
    ],
    "sg:postcode":"DE14 2HG",
    "sg:province":"Derbyshire",
    "sg:tags":[
        "caterer"
    ],
    "wof:name":"David Manning Catering",
    "wof:placetype":"venue"
},
  "geometry": {"coordinates":[-1.6523820162,52.8083496094],"type":"Point"}
}