{
  "type": "Feature",
  "properties": {
    "addr:full":"45 Waverley Lane Burton-on-trent Derbyshire DE14 2HG",
    "addr:housenumber":"45",
    "addr:postcode":"de14 2hg",
    "addr:street":"Waverley Lane",
    "iso:country":"GB",
    "sg:address":"45 Waverley Lane",
    "sg:city":"Burton-on-trent",
    "sg:classifiers":[
        {
            "category":"Professional",
            "type":"Services"
        }
    ],
    "sg:postcode":"DE14 2HG",
    "sg:province":"Derbyshire",
    "sg:tags":[
        "caterer"
    ],
    "wof:name":"David Manning Catering",
    "wof:placetype":"venue"
},
  "geometry": {"coordinates":[-1.6523820162,52.8083496094],"type":"Point"}
}