{
  "type": "Feature",
  "properties": {
    "addr:full":"29 Linden Avenue Thornton-cleveleys Lancashire FY5 2EZ",
    "addr:housenumber":"29",
    "addr:postcode":"fy5 2ez",
    "addr:street":"Linden Avenue",
    "iso:country":"GB",
    "sg:address":"29 Linden Avenue",
    "sg:city":"Thornton-cleveleys",
    "sg:classifiers":[
        {
            "category":"Shopping",
            "subcategory":"News",
            "type":"Retail Goods"
        }
    ],
    "sg:phone":"+44 1253 821239",
    "sg:postcode":"FY5 2EZ",
    "sg:province":"Lancashire",
    "sg:tags":[
        "newsagent"
    ],
    "wof:name":"E & F M Robinson",
    "wof:placetype":"venue"
},
  "geometry": {"coordinates":[-3.020658,53.879425],"type":"Point"}
}