{
  "type": "Feature",
  "properties": {
    "addr:full":"4 Queen Street Neath Neath Port Talbot SA11 1DL",
    "addr:housenumber":"4",
    "addr:postcode":"sa11 1dl",
    "addr:street":"Queen Street",
    "iso:country":"GB",
    "sg:address":"4 Queen Street",
    "sg:city":"Neath",
    "sg:classifiers":[
        {
            "category":"Food & Beverages",
            "subcategory":"Specialty",
            "type":"Retail Goods"
        }
    ],
    "sg:phone":"+44 1639 645745",
    "sg:postcode":"SA11 1DL",
    "sg:province":"Neath Port Talbot",
    "sg:tags":[
        "retailer",
        "product",
        "health"
    ],
    "wof:name":"Holland & Barrett Ltd",
    "wof:placetype":"venue"
},
  "geometry": {"coordinates":[-3.805296,51.66256],"type":"Point"}
}