{
  "type": "Feature",
  "properties": {
    "addr:full":"Chapel Street Penzance Cornwall TR18 4AF",
    "addr:postcode":"tr18 4af",
    "addr:street":"Chapel Street",
    "iso:country":"GB",
    "sg:address":"Chapel Street",
    "sg:city":"Penzance",
    "sg:classifiers":[
        {
            "category":"Bars & Pubs",
            "type":"Food & Drink"
        }
    ],
    "sg:postcode":"TR18 4AF",
    "sg:province":"Cornwall",
    "sg:tags":[
        "pubs",
        "inn"
    ],
    "wof:name":"Turks Head Inn",
    "wof:placetype":"venue"
},
  "geometry": {"coordinates":[-5.536859,50.118015],"type":"Point"}
}