{
  "type": "Feature",
  "properties": {
    "iso:country":"GB",
    "sg:address":"2 Gresham Road",
    "sg:city":"Brentwood",
    "sg:classifiers":[
        {
            "category":"Manufacturing",
            "subcategory":"Chemicals & Compounds",
            "type":"Manufacturing & Wholesale Goods"
        },
        {
            "category":"Retail",
            "subcategory":"Event Space",
            "type":"Services"
        }
    ],
    "sg:phone":"+44 1277 260820",
    "sg:postcode":"CM14 4HN",
    "sg:province":"Essex",
    "sg:tags":[
        "distribution"
    ],
    "wof:name":"Loader Chemicals & Plastics Ltd",
    "wof:placetype":"venue"
},
  "geometry": {"coordinates":[0.299937,51.615593],"type":"Point"}
}