{
  "type": "Feature",
  "properties": {
    "addr:full":"Lombard Business Park, 8 Lombard Rd Wimbledon Greater London SW19 3TZ",
    "addr:housenumber":"8",
    "addr:postcode":"sw19 3tz",
    "addr:street":"Park;Lombard Rd",
    "iso:country":"GB",
    "sg:address":"Lombard Business Park, 8 Lombard Rd",
    "sg:city":"Wimbledon",
    "sg:classifiers":[
        {
            "category":"Building & Trades",
            "subcategory":"Cleaning & Sanitation",
            "type":"Services"
        }
    ],
    "sg:phone":"+44 20 8542 0091",
    "sg:postcode":"SW19 3TZ",
    "sg:province":"Greater London",
    "sg:tags":[
        "commercial"
    ],
    "wof:name":"Efco Facilities Management",
    "wof:placetype":"venue"
},
  "geometry": {"coordinates":[-0.207024,51.420998],"type":"Point"}
}