{
  "type": "Feature",
  "properties": {
    "addr:full":"Mile End Mill, Abbey Mill Business Centre Paisley Renfrewshire PA1 1JS",
    "addr:postcode":"pa1 1js",
    "addr:street":"End Mill Abbey Mill",
    "iso:country":"GB",
    "sg:address":"Mile End Mill, Abbey Mill Business Centre",
    "sg:city":"Paisley",
    "sg:classifiers":[
        {
            "category":"Building & Trades",
            "subcategory":"Landscaping Services",
            "type":"Services"
        }
    ],
    "sg:phone":"+44 141 561 7770",
    "sg:postcode":"PA1 1JS",
    "sg:province":"Renfrewshire",
    "sg:tags":[
        "designer",
        "architect",
        "landscape",
        "contractor"
    ],
    "wof:name":"C D Environmental Design Ltd.",
    "wof:placetype":"venue"
},
  "geometry": {"coordinates":[-4.420864,55.84264],"type":"Point"}
}