{
  "type": "Feature",
  "properties": {
    "addr:full":"Hundah Farm, Scargill Barnard Castle Cumbria DL12 9SU",
    "addr:postcode":"dl12 9su",
    "iso:country":"GB",
    "sg:address":"Hundah Farm, Scargill",
    "sg:city":"Barnard Castle",
    "sg:classifiers":[
        {
            "category":"Farming",
            "subcategory":"Livestock Farm",
            "type":"Manufacturing & Wholesale Goods"
        }
    ],
    "sg:phone":"+44 1833 637184",
    "sg:postcode":"DL12 9SU",
    "sg:province":"Cumbria",
    "sg:tags":[
        "others"
    ],
    "wof:name":"David E Stones",
    "wof:placetype":"venue"
},
  "geometry": {"coordinates":[-1.919659,54.490978],"type":"Point"}
}