{
  "type": "Feature",
  "properties": {
    "iso:country":"GB",
    "sg:address":"Belvedere, 36 Elmhirst Road",
    "sg:city":"Horncastle",
    "sg:classifiers":[
        {
            "category":"Manufacturing",
            "subcategory":"Buildings",
            "type":"Manufacturing & Wholesale Goods"
        }
    ],
    "sg:postcode":"LN9 5LU",
    "sg:province":"Lincolnshire",
    "sg:tags":[
        "shed",
        "greenhouse"
    ],
    "wof:name":"Lincolnshire Leisure Buildings",
    "wof:placetype":"venue"
},
  "geometry": {"coordinates":[-0.114765,53.208523],"type":"Point"}
}