{
  "type": "Feature",
  "properties": {
    "iso:country":"GB",
    "sg:address":"Church Lane, Gaddesby",
    "sg:city":"Leicester",
    "sg:classifiers":[
        {
            "category":"Banks & Credit Unions",
            "subcategory":"Investment Brokerage",
            "type":"Services"
        }
    ],
    "sg:postcode":"LE7 4WE",
    "sg:province":"Leicestershire",
    "sg:tags":[
        "contractor"
    ],
    "wof:name":"Richard Ingram Land Drainage",
    "wof:placetype":"venue"
},
  "geometry": {"coordinates":[-0.9826390147,52.7092208862],"type":"Point"}
}