{
  "type": "Feature",
  "properties": {
    "addr:full":"156 Croftside Avenue Glasgow East Renfrewshire G44 5ND",
    "addr:housenumber":"156;g44",
    "addr:street":"Croftside Avenue;5Nd",
    "iso:country":"GB",
    "sg:address":"156 Croftside Avenue",
    "sg:city":"Glasgow",
    "sg:classifiers":[
        {
            "category":"Health Services",
            "subcategory":"Health Practitioner",
            "type":"Services"
        }
    ],
    "sg:postcode":"G44 5ND",
    "sg:province":"East Renfrewshire",
    "sg:tags":[
        "hypnotherapists"
    ],
    "wof:name":"Association of Stress Management",
    "wof:placetype":"venue"
},
  "geometry": {"coordinates":[-4.229245,55.81287],"type":"Point"}
}