{
  "type": "Feature",
  "properties": {
    "iso:country":"GB",
    "sg:address":"5 Bellevue Parade",
    "sg:city":"London",
    "sg:classifiers":[
        {
            "category":"Shopping",
            "subcategory":"Baby Store",
            "type":"Retail Goods"
        }
    ],
    "sg:postcode":"SW17 7EQ",
    "sg:province":"Greater London",
    "sg:tags":[
        "babywear",
        "childrens"
    ],
    "wof:name":"Smartees",
    "wof:placetype":"venue"
},
  "geometry": {"coordinates":[-0.165497005,51.4460906982],"type":"Point"}
}