{
  "type": "Feature",
  "properties": {
    "addr:full":"32 High Street Irvine North Ayrshire KA12 0AY",
    "addr:housenumber":"32",
    "addr:postcode":"ka12 0ay",
    "addr:street":"High Street",
    "iso:country":"GB",
    "sg:address":"32 High Street",
    "sg:city":"Irvine",
    "sg:classifiers":[
        {
            "category":"Shopping",
            "subcategory":"Clothing, Apparel, & Fashions",
            "type":"Retail Goods"
        }
    ],
    "sg:postcode":"KA12 0AY",
    "sg:province":"North Ayrshire",
    "sg:tags":[
        "lingerie",
        "hosiery"
    ],
    "wof:name":"Dangerous Liaisons",
    "wof:placetype":"venue"
},
  "geometry": {"coordinates":[-4.664191,55.614155],"type":"Point"}
}