{
  "type": "Feature",
  "properties": {
    "iso:country":"GB",
    "sg:address":"78 Merthyr Road, Whitchurch",
    "sg:city":"Cardiff",
    "sg:classifiers":[
        {
            "category":"Personal",
            "subcategory":"Beauty Salon",
            "type":"Services"
        }
    ],
    "sg:phone":"+44 29 2062 5877",
    "sg:postcode":"CF14 1DJ",
    "sg:province":"Cardiff",
    "sg:tags":[
        "unisex",
        "hairdresser"
    ],
    "wof:name":"Bellezza Unisex Hair Design",
    "wof:placetype":"venue"
},
  "geometry": {"coordinates":[-3.217305,51.511196],"type":"Point"}
}