{
  "type": "Feature",
  "properties": {
    "iso:country":"GB",
    "sg:address":"Berona House, 31 Charles Street",
    "sg:city":"Sheffield",
    "sg:classifiers":[
        {
            "category":"Professional",
            "subcategory":"Management & Consulting",
            "type":"Services"
        }
    ],
    "sg:phone":"+44 114 272 8919",
    "sg:postcode":"S1 2HU",
    "sg:province":"South Yorkshire",
    "sg:tags":[
        "consultant",
        "specialist"
    ],
    "wof:name":"Sheffield Beauty Therapy Clinic",
    "wof:placetype":"venue"
},
  "geometry": {"coordinates":[-1.470949,53.37888],"type":"Point"}
}