{
  "type": "Feature",
  "properties": {
    "addr:full":"14 Castlebrook Close London Greater London SE11 4UL",
    "addr:housenumber":"14",
    "addr:postcode":"se11 4ul",
    "addr:street":"Castlebrook Close",
    "iso:country":"GB",
    "sg:address":"14 Castlebrook Close",
    "sg:city":"London",
    "sg:classifiers":[
        {
            "category":"Shopping",
            "subcategory":"Department Store",
            "type":"Retail Goods"
        }
    ],
    "sg:postcode":"SE11 4UL",
    "sg:province":"Greater London",
    "wof:name":"The Video Unit Ltd",
    "wof:placetype":"venue"
},
  "geometry": {"coordinates":[-0.1056760028,51.4933700562],"type":"Point"}
}