{
  "type": "Feature",
  "properties": {
    "iso:country":"GB",
    "sg:address":"Suite 5 Manor Ho, Heron Ct, Cranes Farm Rd",
    "sg:city":"Basildon",
    "sg:classifiers":[
        {
            "category":"Building & Trades",
            "subcategory":"Construction",
            "type":"Services"
        }
    ],
    "sg:postcode":"SS14 3DF",
    "sg:province":"Essex",
    "sg:tags":[
        "builder"
    ],
    "wof:name":"Ewart Construction Ltd",
    "wof:placetype":"venue"
},
  "geometry": {"coordinates":[0.49494,51.586411],"type":"Point"}
}