{
  "type": "Feature",
  "properties": {
    "addr:full":"116 Holden Road Leigh Lancashire WN7 1HA",
    "addr:housenumber":"116",
    "addr:postcode":"wn7 1ha",
    "addr:street":"Holden Road Leigh",
    "iso:country":"GB",
    "sg:address":"116 Holden Road",
    "sg:city":"Leigh",
    "sg:classifiers":[
        {
            "category":"Building & Trades",
            "subcategory":"Construction",
            "type":"Services"
        }
    ],
    "sg:postcode":"WN7 1HA",
    "sg:province":"Lancashire",
    "sg:tags":[
        "conversion",
        "loft"
    ],
    "wof:name":"R S M Loft Conversions Joinery",
    "wof:placetype":"venue"
},
  "geometry": {"coordinates":[-2.5125799179,53.4999961853],"type":"Point"}
}