{
  "type": "Feature",
  "properties": {
    "addr:full":"Midland Centre For Complementary Medicin, 52 Stourbridge Rd Bromsgrove Worcestershire B61 0AH",
    "addr:housenumber":"52",
    "addr:postcode":"worcestershire b61 0ah",
    "addr:street":"Stourbridge Rd",
    "iso:country":"GB",
    "sg:address":"Midland Centre For Complementary Medicin, 52 Stourbridge Rd",
    "sg:city":"Bromsgrove",
    "sg:classifiers":[
        {
            "category":"Personal",
            "subcategory":"Beauty Salon",
            "type":"Services"
        }
    ],
    "sg:postcode":"B61 0AH",
    "sg:province":"Worcestershire",
    "sg:tags":[
        "unisex",
        "hairdresser"
    ],
    "wof:name":"Santos,O,",
    "wof:placetype":"venue"
},
  "geometry": {"coordinates":[-2.058112,52.336594],"type":"Point"}
}