{
  "type": "Feature",
  "properties": {
    "addr:full":"High Street Shefford Bedfordshire SG17 5DD",
    "addr:postcode":"sg17 5dd",
    "addr:street":"High Street",
    "iso:country":"GB",
    "sg:address":"High Street",
    "sg:city":"Shefford",
    "sg:classifiers":[
        {
            "category":"Food & Beverages",
            "subcategory":"Supermarket",
            "type":"Retail Goods"
        }
    ],
    "sg:phone":"+44 1462 811148",
    "sg:postcode":"SG17 5DD",
    "sg:province":"Bedfordshire",
    "wof:name":"Somerfield",
    "wof:placetype":"venue"
},
  "geometry": {"coordinates":[-0.3360289931,52.0378684998],"type":"Point"}
}