{
  "type": "Feature",
  "properties": {
    "iso:country":"GB",
    "sg:address":"The Depot, 26a Bennetts Hill, Oxton",
    "sg:city":"Prenton",
    "sg:classifiers":[
        {
            "category":"Professional",
            "subcategory":"Business Services",
            "type":"Services"
        }
    ],
    "sg:postcode":"CH43 5RS",
    "sg:province":"Merseyside",
    "sg:tags":[
        "import",
        "export",
        "agent"
    ],
    "wof:name":"Flarherty,Terence,",
    "wof:placetype":"venue"
},
  "geometry": {"coordinates":[-3.0379,53.381321],"type":"Point"}
}