{
  "type": "Feature",
  "properties": {
    "iso:country":"GB",
    "sg:address":"55 Hormead Rd",
    "sg:city":"Maida Vale",
    "sg:classifiers":[
        {
            "category":"Professional",
            "subcategory":"Engineering",
            "type":"Services"
        }
    ],
    "sg:phone":"+44 20 8969 5638",
    "sg:postcode":"W9 3NQ",
    "sg:province":"Greater London",
    "sg:tags":[
        "precision",
        "engineer"
    ],
    "wof:name":"Paulson Precision Engineering",
    "wof:placetype":"venue"
},
  "geometry": {"coordinates":[-0.2043969929,51.5246810913],"type":"Point"}
}