{
  "type": "Feature",
  "properties": {
    "addr:full":"41 Thingwall Road Wirral Merseyside CH61 3UE",
    "addr:housenumber":"41",
    "addr:postcode":"ch61 3ue",
    "addr:street":"Thingwall Road",
    "iso:country":"GB",
    "sg:address":"41 Thingwall Road",
    "sg:city":"Wirral",
    "sg:classifiers":[
        {
            "category":"Food & Beverages",
            "subcategory":"Meat & Fish",
            "type":"Retail Goods"
        }
    ],
    "sg:phone":"+44 151 648 1571",
    "sg:postcode":"CH61 3UE",
    "sg:province":"Merseyside",
    "sg:tags":[
        "butcher"
    ],
    "wof:name":"I S Dawson",
    "wof:placetype":"venue"
},
  "geometry": {"coordinates":[-3.097244,53.354561],"type":"Point"}
}