{
  "type": "Feature",
  "properties": {
    "iso:country":"GB",
    "sg:address":"98 Witard Road",
    "sg:city":"Norwich",
    "sg:classifiers":[
        {
            "category":"Home & Garden",
            "subcategory":"Household Appliances",
            "type":"Retail Goods"
        }
    ],
    "sg:postcode":"NR7 9XD",
    "sg:province":"Norfolk",
    "sg:tags":[
        "electrical"
    ],
    "wof:name":"Norwich Domestic Appliances Service Division",
    "wof:placetype":"venue"
},
  "geometry": {"coordinates":[1.337518,52.641258],"type":"Point"}
}