{
  "type": "Feature",
  "properties": {
    "addr:full":"8a7 Ringwood Road Poole Dorset BH14 0RH",
    "addr:housenumber":"8a7",
    "addr:postcode":"bh14 0rh",
    "addr:street":"Ringwood Road",
    "iso:country":"GB",
    "sg:address":"8a7 Ringwood Road",
    "sg:city":"Poole",
    "sg:classifiers":[
        {
            "category":"Manufacturing",
            "subcategory":"Wood Products",
            "type":"Manufacturing & Wholesale Goods"
        }
    ],
    "sg:phone":"+44 1202 733300",
    "sg:postcode":"BH14 0RH",
    "sg:province":"Dorset",
    "sg:tags":[
        "packaging",
        "crate",
        "pallets"
    ],
    "wof:name":"Abbotts Packaging",
    "wof:placetype":"venue"
},
  "geometry": {"coordinates":[-1.9665180445,50.7256507874],"type":"Point"}
}