{
  "type": "Feature",
  "properties": {
    "addr:full":"2 Mead Ct, Buck La Colindale Greater London NW9 0XN",
    "addr:housenumber":"2",
    "addr:postcode":"nw9 0xn",
    "addr:street":"Mead Ct Buck La Colindale",
    "iso:country":"GB",
    "sg:address":"2 Mead Ct, Buck La",
    "sg:city":"Colindale",
    "sg:classifiers":[
        {
            "category":"Building & Trades",
            "subcategory":"Construction",
            "type":"Services"
        }
    ],
    "sg:phone":"+44 20 8205 9008",
    "sg:postcode":"NW9 0XN",
    "sg:province":"Greater London",
    "sg:tags":[
        "glazier"
    ],
    "wof:name":"Pioneer Glass Services",
    "wof:placetype":"venue"
},
  "geometry": {"coordinates":[-0.2628450096,51.5837745667],"type":"Point"}
}