{
  "type": "Feature",
  "properties": {
    "addr:full":"7 Afonwen Terrace, Afonwen Pwllheli Gwynedd LL53 6RJ",
    "addr:housenumber":"7",
    "addr:postcode":"ll53 6rj",
    "addr:street":"Afonwen Terrace Afonwen Pwllheli",
    "iso:country":"GB",
    "sg:address":"7 Afonwen Terrace, Afonwen",
    "sg:city":"Pwllheli",
    "sg:classifiers":[
        {
            "category":"Building & Trades",
            "subcategory":"Cleaning & Sanitation",
            "type":"Services"
        }
    ],
    "sg:phone":"+44 1766 810507",
    "sg:postcode":"LL53 6RJ",
    "sg:province":"Gwynedd",
    "sg:tags":[
        "commercial"
    ],
    "wof:name":"Robert F Griffith",
    "wof:placetype":"venue"
},
  "geometry": {"coordinates":[-4.3207650185,52.9134750366],"type":"Point"}
}