{
  "type": "Feature",
  "properties": {
    "iso:country":"GB",
    "sg:address":"19-21 Nether Hall Road",
    "sg:city":"Doncaster",
    "sg:classifiers":[
        {
            "category":"Shopping",
            "subcategory":"Hobbies, Toys, & Games",
            "type":"Retail Goods"
        }
    ],
    "sg:phone":"+44 1302 815522",
    "sg:postcode":"DN1 2PH",
    "sg:province":"South Yorkshire",
    "sg:tags":[
        "toy"
    ],
    "wof:name":"The War Room",
    "wof:placetype":"venue"
},
  "geometry": {"coordinates":[-1.1299730539,53.5253219604],"type":"Point"}
}