{
  "type": "Feature",
  "properties": {
    "addr:full":"Taxi Inspection Depot, 38 Powis Terr Aberdeen Aberdeen City AB25 3QE",
    "addr:housenumber":"38",
    "addr:postcode":"ab25 3qe",
    "addr:street":"Powis Terr",
    "iso:country":"GB",
    "sg:address":"Taxi Inspection Depot, 38 Powis Terr",
    "sg:city":"Aberdeen",
    "sg:classifiers":[
        {
            "category":"Government",
            "subcategory":"Office",
            "type":"Public Place"
        }
    ],
    "sg:phone":"+44 1224 492537",
    "sg:postcode":"AB25 3QE",
    "sg:province":"Aberdeen City",
    "sg:tags":[
        "local"
    ],
    "wof:name":"City of Aberdeen District Council",
    "wof:placetype":"venue"
},
  "geometry": {"coordinates":[-2.1155478954,57.1577987671],"type":"Point"}
}