{
  "type": "Feature",
  "properties": {
    "addr:full":"Toddington Lane Littlehampton West Sussex BN17 7PP",
    "addr:postcode":"bn17 7pp",
    "addr:street":"Toddington Lane",
    "iso:country":"GB",
    "sg:address":"Toddington Lane",
    "sg:city":"Littlehampton",
    "sg:classifiers":[
        {
            "category":"Home & Garden",
            "subcategory":"Garden Supply",
            "type":"Retail Goods"
        }
    ],
    "sg:postcode":"BN17 7PP",
    "sg:province":"West Sussex",
    "sg:tags":[
        "nursery",
        "centre"
    ],
    "wof:name":"Westholme Nurseries",
    "wof:placetype":"venue"
},
  "geometry": {"coordinates":[-0.5366200209,50.8256034851],"type":"Point"}
}