{
  "type": "Feature",
  "properties": {
    "addr:full":"12 Fernhill Road, Cowley Oxford Oxfordshire OX4 2JN",
    "addr:housenumber":"12",
    "addr:postcode":"ox4 2jn",
    "addr:street":"Fernhill Road",
    "iso:country":"GB",
    "sg:address":"12 Fernhill Road, Cowley",
    "sg:city":"Oxford",
    "sg:classifiers":[
        {
            "category":"Building & Trades",
            "subcategory":"Plumbing",
            "type":"Services"
        }
    ],
    "sg:phone":"+44 1865 771104",
    "sg:postcode":"OX4 2JN",
    "sg:province":"Oxfordshire",
    "sg:tags":[
        "central",
        "heating"
    ],
    "wof:name":"Brian Watts",
    "wof:placetype":"venue"
},
  "geometry": {"coordinates":[-1.2082979679,51.7354698181],"type":"Point"}
}