{
  "type": "Feature",
  "properties": {
    "addr:full":"8 Chadwick Road, South Woodham Ferrers Chelmsford Essex CM3 5PG",
    "addr:housenumber":"8",
    "addr:postcode":"cm3 5pg",
    "addr:street":"Chadwick Road",
    "iso:country":"GB",
    "sg:address":"8 Chadwick Road, South Woodham Ferrers",
    "sg:city":"Chelmsford",
    "sg:classifiers":[
        {
            "category":"Professional",
            "subcategory":"Engineering",
            "type":"Services"
        }
    ],
    "sg:postcode":"CM3 5PG",
    "sg:province":"Essex",
    "sg:tags":[
        "contractor",
        "electrical",
        "engineer"
    ],
    "wof:name":"B & W Electrical & Building Services",
    "wof:placetype":"venue"
},
  "geometry": {"coordinates":[0.6174319983,51.6521873474],"type":"Point"}
}