{
  "type": "Feature",
  "properties": {
    "addr:full":"11 Berkeley St London Greater London W1J 8BU",
    "addr:housenumber":"11",
    "addr:postcode":"w1j 8bu",
    "addr:street":"Berkeley St",
    "iso:country":"GB",
    "sg:address":"11 Berkeley St",
    "sg:city":"London",
    "sg:classifiers":[
        {
            "category":"Professional",
            "subcategory":"Management & Consulting",
            "type":"Services"
        }
    ],
    "sg:postcode":"W1J 8BU",
    "sg:province":"Greater London",
    "sg:tags":[
        "consultant",
        "business"
    ],
    "wof:name":"Hudson,Grant,",
    "wof:placetype":"venue"
},
  "geometry": {"coordinates":[-0.14301,51.508194],"type":"Point"}
}