{
  "type": "Feature",
  "properties": {
    "addr:full":"55 The Grn, Southwick Sunderland Tyne and Wear SR5 2HT",
    "addr:housenumber":"55",
    "addr:postcode":"sr5 2ht",
    "addr:street":"The Grn",
    "iso:country":"GB",
    "sg:address":"55 The Grn, Southwick",
    "sg:city":"Sunderland",
    "sg:classifiers":[
        {
            "category":"Food & Beverages",
            "subcategory":"Meat & Fish",
            "type":"Retail Goods"
        }
    ],
    "sg:phone":"+44 191 548 6530",
    "sg:postcode":"SR5 2HT",
    "sg:province":"Tyne and Wear",
    "sg:tags":[
        "butcher"
    ],
    "wof:name":"Ron's Family Butchers",
    "wof:placetype":"venue"
},
  "geometry": {"coordinates":[-1.405312,54.919559],"type":"Point"}
}