{
  "type": "Feature",
  "properties": {
    "iso:country":"GB",
    "sg:address":"Po Box 41",
    "sg:city":"Watford",
    "sg:classifiers":[
        {
            "category":"Manufacturing",
            "subcategory":"Metals",
            "type":"Manufacturing & Wholesale Goods"
        }
    ],
    "sg:phone":"+44 1923 252089",
    "sg:postcode":"WD19 4SD",
    "sg:province":"Hertfordshire",
    "sg:tags":[
        "steel",
        "stockholder"
    ],
    "wof:name":"South Midland Steel Ltd.",
    "wof:placetype":"venue"
},
  "geometry": {"coordinates":[-0.39972,51.640301],"type":"Point"}
}