{
  "type": "Feature",
  "properties": {
    "addr:full":"Pittenweem Library, Town Hall, Cove Wynd Anstruther Fife KY10 2LE",
    "addr:postcode":"ky10 2le",
    "addr:street":"Hall Cove Wynd",
    "iso:country":"GB",
    "sg:address":"Pittenweem Library, Town Hall, Cove Wynd",
    "sg:city":"Anstruther",
    "sg:classifiers":[
        {
            "category":"Government",
            "subcategory":"Office",
            "type":"Public Place"
        }
    ],
    "sg:phone":"+44 1333 311496",
    "sg:postcode":"KY10 2LE",
    "sg:province":"Fife",
    "sg:tags":[
        "local"
    ],
    "wof:name":"Fife Council",
    "wof:placetype":"venue"
},
  "geometry": {"coordinates":[-2.730864,56.214314],"type":"Point"}
}