{
  "type": "Feature",
  "properties": {
    "addr:full":"14 Bridghe End Southam Warwickshire CV47 1PD",
    "addr:housenumber":"14",
    "addr:postcode":"cv47 1pd",
    "addr:street":"Bridghe End",
    "iso:country":"GB",
    "sg:address":"14 Bridghe End",
    "sg:city":"Southam",
    "sg:classifiers":[
        {
            "category":"Recreation",
            "subcategory":"Water Park",
            "type":"Entertainment"
        }
    ],
    "sg:phone":"+44 1926 881254",
    "sg:postcode":"CV47 1PD",
    "sg:province":"Warwickshire",
    "sg:tags":[
        "sport"
    ],
    "wof:name":"Mid Warwickshire Yacht Club",
    "wof:placetype":"venue"
},
  "geometry": {"coordinates":[-1.386987,52.250843],"type":"Point"}
}