{
  "type": "Feature",
  "properties": {
    "iso:country":"GB",
    "sg:address":"Ty Newydd, Maenaddwyn",
    "sg:city":"Llanerchymedd",
    "sg:classifiers":[
        {
            "category":"Farming",
            "subcategory":"Livestock Farm",
            "type":"Manufacturing & Wholesale Goods"
        }
    ],
    "sg:phone":"+44 1248 470364",
    "sg:postcode":"LL71 8BD",
    "sg:province":"Isle of Anglesey",
    "sg:tags":[
        "others"
    ],
    "wof:name":"Sydney Gerard",
    "wof:placetype":"venue"
},
  "geometry": {"coordinates":[-4.376363,53.330353],"type":"Point"}
}