{
  "type": "Feature",
  "properties": {
    "iso:country":"GB",
    "sg:address":"The Estate Office Acklington, Mart Acklington",
    "sg:city":"Morpeth",
    "sg:classifiers":[
        {
            "category":"Real Estate",
            "subcategory":"Real Estate Agent",
            "type":"Services"
        }
    ],
    "sg:phone":"+44 1670 761170",
    "sg:postcode":"NE65 9BU",
    "sg:province":"Northumberland",
    "wof:name":"North East Property Services Ltd.",
    "wof:placetype":"venue"
},
  "geometry": {"coordinates":[-1.635109,55.31089],"type":"Point"}
}