{
  "type": "Feature",
  "properties": {
    "iso:country":"GB",
    "sg:address":"176-176a Slade Rd, Erdington",
    "sg:city":"Birmingham",
    "sg:classifiers":[
        {
            "category":"Autos & Motor Vehicles",
            "subcategory":"Auto Supplies",
            "type":"Retail Goods"
        }
    ],
    "sg:postcode":"B23 7PX",
    "sg:province":"West Midlands",
    "sg:tags":[
        "car",
        "audio"
    ],
    "wof:name":"Morgan,Anthony,",
    "wof:placetype":"venue"
},
  "geometry": {"coordinates":[-1.8571360111,52.5147628784],"type":"Point"}
}