{
  "type": "Feature",
  "properties": {
    "addr:full":"11 Windsor Terrace, Grangetown Sunderland Tyne and Wear SR2 9RQ",
    "addr:housenumber":"11",
    "addr:postcode":"sr2 9rq",
    "addr:street":"Windsor Terrace",
    "iso:country":"GB",
    "sg:address":"11 Windsor Terrace, Grangetown",
    "sg:city":"Sunderland",
    "sg:classifiers":[
        {
            "category":"Shopping",
            "type":"Retail Goods"
        }
    ],
    "sg:phone":"+44 191 510 9959",
    "sg:postcode":"SR2 9RQ",
    "sg:province":"Tyne and Wear",
    "sg:tags":[
        "part",
        "accessory"
    ],
    "wof:name":"Auto Save Cliffy's",
    "wof:placetype":"venue"
},
  "geometry": {"coordinates":[-1.3674999475,54.8855018616],"type":"Point"}
}