{
  "type": "Feature",
  "properties": {
    "addr:full":"Tithe Barn Road Stafford Staffordshire ST16 3PP",
    "addr:housenumber":"tithe",
    "addr:postcode":"st16 3pp",
    "addr:street":"Barn Road",
    "iso:country":"GB",
    "sg:address":"Tithe Barn Road",
    "sg:city":"Stafford",
    "sg:classifiers":[
        {
            "category":"Social Services",
            "subcategory":"Adult Care",
            "type":"Services"
        },
        {
            "category":"Real Estate",
            "subcategory":"Real Estate Agent",
            "type":"Services"
        }
    ],
    "sg:phone":"+44 1785 242934",
    "sg:postcode":"ST16 3PP",
    "sg:province":"Staffordshire",
    "sg:tags":[
        "housing",
        "sheltered"
    ],
    "wof:name":"Tithe Barn Court Sheltered Housing",
    "wof:placetype":"venue"
},
  "geometry": {"coordinates":[-2.102575,52.811436],"type":"Point"}
}