{
  "type": "Feature",
  "properties": {
    "addr:full":"34 Queens Road Buckhurst Hill Essex IG9 5BY",
    "addr:housenumber":"34",
    "addr:postcode":"ig9 5by",
    "addr:street":"Queens Road",
    "iso:country":"GB",
    "sg:address":"34 Queens Road",
    "sg:city":"Buckhurst Hill",
    "sg:classifiers":[
        {
            "category":"Shopping",
            "subcategory":"News",
            "type":"Retail Goods"
        }
    ],
    "sg:phone":"+44 20 8504 4213",
    "sg:postcode":"IG9 5BY",
    "sg:province":"Essex",
    "sg:tags":[
        "newsagent"
    ],
    "wof:name":"Broomes",
    "wof:placetype":"venue"
},
  "geometry": {"coordinates":[0.044461,51.625122],"type":"Point"}
}