{
  "type": "Feature",
  "properties": {
    "iso:country":"GB",
    "sg:address":"3 Station Road, Knowle",
    "sg:city":"Solihull",
    "sg:classifiers":[
        {
            "category":"Restaurant",
            "type":"Food & Drink"
        }
    ],
    "sg:phone":"+44 1564 772222",
    "sg:postcode":"B93 0HL",
    "sg:province":"Warwickshire",
    "wof:name":"Loyds Restaurant",
    "wof:placetype":"venue"
},
  "geometry": {"coordinates":[-1.734675,52.386826],"type":"Point"}
}