{
  "type": "Feature",
  "properties": {
    "addr:full":"Po Box 1072 Winchester Hampshire SO23 8FT",
    "addr:housenumber":"po;1072",
    "addr:postcode":"so23 8ft",
    "addr:street":"Box",
    "iso:country":"GB",
    "sg:address":"Po Box 1072",
    "sg:city":"Winchester",
    "sg:classifiers":[
        {
            "category":"Communications",
            "type":"Services"
        }
    ],
    "sg:phone":"+44 1962 841071",
    "sg:postcode":"SO23 8FT",
    "sg:province":"Hampshire",
    "sg:tags":[
        "broadcasting"
    ],
    "wof:name":"Winchester Independent Radio Ltd.",
    "wof:placetype":"venue"
},
  "geometry": {"coordinates":[-1.3168090582,51.0630683899],"type":"Point"}
}