{
  "type": "Feature",
  "properties": {
    "iso:country":"GB",
    "sg:address":"69 Knighton Road",
    "sg:city":"Southampton",
    "sg:classifiers":[
        {
            "category":"Building & Trades",
            "subcategory":"Construction",
            "type":"Services"
        }
    ],
    "sg:phone":"+44 23 8043 2112",
    "sg:postcode":"SO19 2FP",
    "sg:province":"Hampshire",
    "sg:tags":[
        "builder"
    ],
    "wof:name":"Beggan & Bush",
    "wof:placetype":"venue"
},
  "geometry": {"coordinates":[-1.366967,50.900436],"type":"Point"}
}