{
  "type": "Feature",
  "properties": {
    "iso:country":"GB",
    "sg:address":"Unit J3, Dudley Central Trading Estate, Shaw Road",
    "sg:city":"Dudley",
    "sg:classifiers":[
        {
            "category":"Building & Trades",
            "subcategory":"Cleaning & Sanitation",
            "type":"Services"
        }
    ],
    "sg:phone":"+44 1384 457980",
    "sg:postcode":"DY2 8TS",
    "sg:province":"West Midlands",
    "sg:tags":[
        "blast"
    ],
    "wof:name":"J & S Metal Finishers",
    "wof:placetype":"venue"
},
  "geometry": {"coordinates":[-2.088521,52.504314],"type":"Point"}
}