{
  "type": "Feature",
  "properties": {
    "iso:country":"GB",
    "sg:address":"Lincoln Rd",
    "sg:city":"High Wycombe",
    "sg:classifiers":[
        {
            "category":"Autos & Motor Vehicles",
            "subcategory":"Auto Supplies",
            "type":"Retail Goods"
        }
    ],
    "sg:phone":"+44 1494 532845",
    "sg:postcode":"HP12 3RH",
    "sg:province":"Buckinghamshire",
    "sg:tags":[
        "tyre"
    ],
    "wof:name":"Motorway Tyres & Autocentres",
    "wof:placetype":"venue"
},
  "geometry": {"coordinates":[-0.772314,51.622009],"type":"Point"}
}