{
  "type": "Feature",
  "properties": {
    "addr:full":"227 Greengate, Middleton Manchester Greater Manchester M24 1RU",
    "addr:housenumber":"227",
    "addr:postcode":"m24 1ru",
    "addr:street":"Greengate Middleton",
    "iso:country":"GB",
    "sg:address":"227 Greengate, Middleton",
    "sg:city":"Manchester",
    "sg:classifiers":[
        {
            "category":"Retail",
            "subcategory":"Emissions Testing",
            "type":"Services"
        },
        {
            "category":"Professional",
            "subcategory":"Testing Lab",
            "type":"Services"
        }
    ],
    "sg:phone":"+44 161 643 0099",
    "sg:postcode":"M24 1RU",
    "sg:province":"Greater Manchester",
    "sg:tags":[
        "mot"
    ],
    "wof:name":"Greengate Service Station",
    "wof:placetype":"venue"
},
  "geometry": {"coordinates":[-2.174758,53.533035],"type":"Point"}
}