{
  "type": "Feature",
  "properties": {
    "iso:country":"GB",
    "sg:address":"42b Thornbush Rd",
    "sg:city":"Inverness",
    "sg:classifiers":[
        {
            "category":"Retail",
            "subcategory":"Laundry & Dry Cleaning",
            "type":"Services"
        }
    ],
    "sg:postcode":"IV3 8AB",
    "sg:province":"Highland",
    "sg:tags":[
        "launderette"
    ],
    "wof:name":"McDonald,C,",
    "wof:placetype":"venue"
},
  "geometry": {"coordinates":[-4.2374038696,57.488571167],"type":"Point"}
}