{
  "type": "Feature",
  "properties": {
    "addr:full":"Park Road, Hartlepool Middlesbrough Durham TS26 9HU",
    "addr:postcode":"ts26 9hu",
    "addr:street":"Park Road",
    "iso:country":"GB",
    "sg:address":"Park Road, Hartlepool",
    "sg:city":"Middlesbrough",
    "sg:classifiers":[
        {
            "category":"Bars & Pubs",
            "type":"Food & Drink"
        }
    ],
    "sg:phone":"+44 1429 274287",
    "sg:postcode":"TS26 9HU",
    "sg:province":"Durham",
    "sg:tags":[
        "pubs",
        "inn"
    ],
    "wof:name":"Park Hotel",
    "wof:placetype":"venue"
},
  "geometry": {"coordinates":[-1.2268840075,54.6823616028],"type":"Point"}
}