{
  "type": "Feature",
  "properties": {
    "iso:country":"GB",
    "sg:address":"1 West St",
    "sg:city":"Dudley",
    "sg:classifiers":[
        {
            "category":"Fast Food",
            "type":"Food & Drink"
        }
    ],
    "sg:phone":"+44 1384 242002",
    "sg:postcode":"DY1 2TA",
    "sg:province":"West Midlands",
    "sg:tags":[
        "away",
        "take"
    ],
    "wof:name":"Pizza Time",
    "wof:placetype":"venue"
},
  "geometry": {"coordinates":[-2.097549,52.507198],"type":"Point"}
}