{
  "type": "Feature",
  "properties": {
    "iso:country":"GB",
    "sg:address":"62 Machon Bank, Nether Edge",
    "sg:city":"Sheffield",
    "sg:classifiers":[
        {
            "category":"Building & Trades",
            "subcategory":"Plumbing",
            "type":"Services"
        }
    ],
    "sg:postcode":"S7 1GP",
    "sg:province":"South Yorkshire",
    "sg:tags":[
        "central",
        "heating"
    ],
    "wof:name":"Safetask Ltd.",
    "wof:placetype":"venue"
},
  "geometry": {"coordinates":[-1.4835729599,53.3593826294],"type":"Point"}
}