{
  "type": "Feature",
  "properties": {
    "addr:full":"St Pauls Avenue Lytham St Annes Lancashire FY8 1ED",
    "addr:postcode":"fy8 1ed",
    "addr:street":"St Pauls Avenue;St",
    "iso:country":"GB",
    "sg:address":"St Pauls Avenue",
    "sg:city":"Lytham St Annes",
    "sg:classifiers":[
        {
            "category":"Banks & Credit Unions",
            "subcategory":"Financial Services",
            "type":"Services"
        }
    ],
    "sg:postcode":"FY8 1ED",
    "sg:province":"Lancashire",
    "sg:tags":[
        "consultant"
    ],
    "wof:name":"Farley Finance",
    "wof:placetype":"venue"
},
  "geometry": {"coordinates":[-3.006589,53.741226],"type":"Point"}
}