{
  "type": "Feature",
  "properties": {
    "addr:full":"13 Leechwell Street Totnes Devon TQ9 5SX",
    "addr:housenumber":"13",
    "addr:postcode":"tq9 5sx",
    "addr:street":"Leechwell Street",
    "iso:country":"GB",
    "sg:address":"13 Leechwell Street",
    "sg:city":"Totnes",
    "sg:classifiers":[
        {
            "category":"Organizations",
            "subcategory":"Non-profit Organization",
            "type":"Services"
        }
    ],
    "sg:phone":"+44 1803 866559",
    "sg:postcode":"TQ9 5SX",
    "sg:province":"Devon",
    "sg:tags":[
        "organisation",
        "voluntary",
        "charity"
    ],
    "wof:name":"The Child Assault Prevention Project",
    "wof:placetype":"venue"
},
  "geometry": {"coordinates":[-3.6910998821,50.4296798706],"type":"Point"}
}