{
  "type": "Feature",
  "properties": {
    "addr:full":"Unit 4 Almondvale Avenue Retail Park Livingston West Lothian EH54 6QX",
    "addr:housenumber":"unit 4",
    "addr:postcode":"eh54 6qx",
    "addr:street":"Almondvale Avenue Retail Park",
    "iso:country":"GB",
    "sg:address":"Unit 4 Almondvale Avenue Retail Park",
    "sg:city":"Livingston",
    "sg:classifiers":[
        {
            "category":"Retail",
            "subcategory":"Veterinary Services",
            "type":"Services"
        }
    ],
    "sg:phone":"+44 1506 463085",
    "sg:postcode":"EH54 6QX",
    "sg:province":"West Lothian",
    "sg:tags":[
        "surgeon"
    ],
    "wof:name":"Elshie Ltd.",
    "wof:placetype":"venue"
},
  "geometry": {"coordinates":[-3.5184841156,55.8840751648],"type":"Point"}
}