{
  "type": "Feature",
  "properties": {
    "addr:full":"14 Alderwood Parc Penryn Cornwall TR10 8RJ",
    "addr:housenumber":"14",
    "addr:postcode":"tr10 8rj",
    "addr:street":"Alderwood Parc",
    "iso:country":"GB",
    "sg:address":"14 Alderwood Parc",
    "sg:city":"Penryn",
    "sg:classifiers":[
        {
            "category":"Building & Trades",
            "subcategory":"Construction",
            "type":"Services"
        }
    ],
    "sg:phone":"+44 1326 377632",
    "sg:postcode":"TR10 8RJ",
    "sg:province":"Cornwall",
    "sg:tags":[
        "joiner",
        "carpenter"
    ],
    "wof:name":"Roger Wayne Rundle",
    "wof:placetype":"venue"
},
  "geometry": {"coordinates":[-5.1130290031,50.1707878113],"type":"Point"}
}