{
  "type": "Feature",
  "properties": {
    "iso:country":"GB",
    "sg:address":"37 Manor Farm Close, Adwick-le-street",
    "sg:city":"Doncaster",
    "sg:classifiers":[
        {
            "category":"Shopping",
            "subcategory":"Party Supplies",
            "type":"Retail Goods"
        },
        {
            "category":"Wholesale",
            "subcategory":"Toys & Hobbies",
            "type":"Manufacturing & Wholesale Goods"
        }
    ],
    "sg:phone":"+44 1302 330568",
    "sg:postcode":"DN6 7AE",
    "sg:province":"North Yorkshire",
    "sg:tags":[
        "balloon",
        "novelty"
    ],
    "wof:name":"Balloon Spice Spotlight",
    "wof:placetype":"venue"
},
  "geometry": {"coordinates":[-1.1873179674,53.5720405579],"type":"Point"}
}