{
  "type": "Feature",
  "properties": {
    "addr:full":"Devon Dr Nottingham Nottinghamshire NG5 2ET",
    "addr:postcode":"ng5 2et",
    "addr:street":"Devon Dr",
    "iso:country":"GB",
    "sg:address":"Devon Dr",
    "sg:city":"Nottingham",
    "sg:classifiers":[
        {
            "category":"Place Of Worship",
            "type":"Public Place"
        }
    ],
    "sg:phone":"+44 115 953 1186",
    "sg:postcode":"NG5 2ET",
    "sg:province":"Nottinghamshire",
    "wof:name":"Sherwood Methodist Church",
    "wof:placetype":"venue"
},
  "geometry": {"coordinates":[-1.152538,52.978851],"type":"Point"}
}