{
  "type": "Feature",
  "properties": {
    "addr:full":"78 Friar Gate Derby Derbyshire DE1 1FL",
    "addr:housenumber":"78",
    "addr:postcode":"de1 1fl",
    "addr:street":"Friar Gate",
    "iso:country":"GB",
    "sg:address":"78 Friar Gate",
    "sg:city":"Derby",
    "sg:classifiers":[
        {
            "category":"Shopping",
            "subcategory":"Pharmacy",
            "type":"Retail Goods"
        }
    ],
    "sg:phone":"+44 1332 369222",
    "sg:postcode":"DE1 1FL",
    "sg:province":"Derbyshire",
    "sg:tags":[
        "pharmaceutical"
    ],
    "wof:name":"Ahead Recruitment Ltd",
    "wof:placetype":"venue"
},
  "geometry": {"coordinates":[-1.489923954,52.9251251221],"type":"Point"}
}