{
  "type": "Feature",
  "properties": {
    "addr:full":"The Long Ho Chilton Rd, Chearsley Aylesbury Buckinghamshire HP18 0DN",
    "addr:postcode":"hp18 0dn",
    "addr:street":"Chilton Rd",
    "iso:country":"GB",
    "sg:address":"The Long Ho Chilton Rd, Chearsley",
    "sg:city":"Aylesbury",
    "sg:classifiers":[
        {
            "category":"Home & Garden",
            "subcategory":"Hardware",
            "type":"Retail Goods"
        }
    ],
    "sg:phone":"+44 1844 202444",
    "sg:postcode":"HP18 0DN",
    "sg:province":"Buckinghamshire",
    "sg:tags":[
        "device",
        "fixing",
        "fastener"
    ],
    "wof:name":"Suction Systems Ltd",
    "wof:placetype":"venue"
},
  "geometry": {"coordinates":[-0.9614189863,51.7903747559],"type":"Point"}
}