{
  "type": "Feature",
  "properties": {
    "iso:country":"GB",
    "sg:address":"Unit 4 Junction Rd, Audnam",
    "sg:city":"Stourbridge",
    "sg:classifiers":[
        {
            "category":"Professional",
            "type":"Services"
        },
        {
            "category":"Fast Food",
            "type":"Food & Drink"
        }
    ],
    "sg:postcode":"DY8 4YJ",
    "sg:province":"Staffordshire",
    "sg:tags":[
        "away",
        "take",
        "caterer"
    ],
    "wof:name":"Newton,Jenny,",
    "wof:placetype":"venue"
},
  "geometry": {"coordinates":[-2.156527,52.472591],"type":"Point"}
}