{
  "type": "Feature",
  "properties": {
    "iso:country":"GB",
    "sg:address":"School Rd, Kinnerley",
    "sg:city":"Oswestry",
    "sg:classifiers":[
        {
            "category":"Education",
            "subcategory":"School",
            "type":"Public Place"
        }
    ],
    "sg:phone":"+44 1691 682289",
    "sg:postcode":"SY10 8DF",
    "sg:province":"Shropshire",
    "sg:tags":[
        "local",
        "authority"
    ],
    "wof:name":"Kinnerley C of E Primary School",
    "wof:placetype":"venue"
},
  "geometry": {"coordinates":[-2.982154,52.783306],"type":"Point"}
}