{
  "type": "Feature",
  "properties": {
    "iso:country":"GB",
    "sg:address":"Cumberland Road",
    "sg:city":"North Shields",
    "sg:classifiers":[
        {
            "category":"Travel",
            "subcategory":"Travel Agent",
            "type":"Entertainment"
        },
        {
            "category":"Bus Charters",
            "type":"Transportation"
        }
    ],
    "sg:phone":"+44 191 257 1500",
    "sg:postcode":"NE29 8RD",
    "sg:province":"Tyne and Wear",
    "sg:tags":[
        "hire",
        "coach"
    ],
    "wof:name":"NATIONAL HOLIDAYS LTD",
    "wof:placetype":"venue"
},
  "geometry": {"coordinates":[-1.488169,55.018314],"type":"Point"}
}