{
  "type": "Feature",
  "properties": {
    "addr:full":"Cuerdale Lane, Samlesbury Preston Lancashire PR5 0XA",
    "addr:postcode":"pr5 0xa",
    "addr:street":"Cuerdale Lane",
    "iso:country":"GB",
    "sg:address":"Cuerdale Lane, Samlesbury",
    "sg:city":"Preston",
    "sg:classifiers":[
        {
            "category":"Bars & Pubs",
            "type":"Food & Drink"
        }
    ],
    "sg:phone":"+44 1772 877217",
    "sg:postcode":"PR5 0XA",
    "sg:province":"Lancashire",
    "sg:tags":[
        "pubs",
        "house",
        "inn",
        "public",
        "activity"
    ],
    "wof:name":"New Hall Tavern",
    "wof:placetype":"venue"
},
  "geometry": {"coordinates":[-2.6037790775,53.766368866],"type":"Point"}
}