{
  "type": "Feature",
  "properties": {
    "addr:full":"15 Mursley Road, Swanbourne Milton Keynes Bedfordshire MK17 0SH",
    "addr:housenumber":"15",
    "addr:postcode":"mk17 0sh",
    "addr:street":"Mursley Road",
    "iso:country":"GB",
    "sg:address":"15 Mursley Road, Swanbourne",
    "sg:city":"Milton Keynes",
    "sg:classifiers":[
        {
            "category":"Building & Trades",
            "subcategory":"Construction",
            "type":"Services"
        }
    ],
    "sg:phone":"+44 1296 720202",
    "sg:postcode":"MK17 0SH",
    "sg:province":"Bedfordshire",
    "sg:tags":[
        "builder"
    ],
    "wof:name":"Workforce Building Contractors",
    "wof:placetype":"venue"
},
  "geometry": {"coordinates":[-0.831835,51.938828],"type":"Point"}
}