{
  "type": "Feature",
  "properties": {
    "iso:country":"GB",
    "sg:address":"167-169 Kensington High Street",
    "sg:city":"London",
    "sg:classifiers":[
        {
            "category":"Professional",
            "subcategory":"Engineering",
            "type":"Services"
        },
        {
            "category":"Professional",
            "subcategory":"Art Services",
            "type":"Services"
        }
    ],
    "sg:phone":"+44 20 7938 3131",
    "sg:postcode":"W8 6SH",
    "sg:province":"Greater London",
    "sg:tags":[
        "consulting",
        "graphic",
        "designer",
        "engineer"
    ],
    "wof:name":"Brown Beech & Associates Ltd.",
    "wof:placetype":"venue"
},
  "geometry": {"coordinates":[-0.194934994,51.5002708435],"type":"Point"}
}