{
  "type": "Feature",
  "properties": {
    "iso:country":"GB",
    "sg:address":"Wighill Grange",
    "sg:city":"Tadcaster",
    "sg:classifiers":[
        {
            "category":"Farming",
            "subcategory":"Livestock Farm",
            "type":"Manufacturing & Wholesale Goods"
        }
    ],
    "sg:postcode":"LS24 8BH",
    "sg:province":"North Yorkshire",
    "sg:tags":[
        "others"
    ],
    "wof:name":"G W Parkin",
    "wof:placetype":"venue"
},
  "geometry": {"coordinates":[-1.2783639431,53.9163856506],"type":"Point"}
}