{
  "type": "Feature",
  "properties": {
    "addr:full":"10 Bank Street Kilmarnock East Ayrshire KA1 1HA",
    "addr:housenumber":"10",
    "addr:postcode":"ka1 1ha",
    "addr:street":"Bank Street",
    "iso:country":"GB",
    "sg:address":"10 Bank Street",
    "sg:city":"Kilmarnock",
    "sg:classifiers":[
        {
            "category":"Shopping",
            "subcategory":"Florist",
            "type":"Retail Goods"
        }
    ],
    "sg:phone":"+44 1563 522233",
    "sg:postcode":"KA1 1HA",
    "sg:province":"East Ayrshire",
    "wof:name":"The Garden Shop",
    "wof:placetype":"venue"
},
  "geometry": {"coordinates":[-4.497362,55.609589],"type":"Point"}
}