{
  "type": "Feature",
  "properties": {
    "addr:full":"19 Maybury Rd Edinburgh City of Edinburgh EH4 8DX",
    "addr:housenumber":"19",
    "addr:postcode":"eh4 8dx",
    "addr:street":"Maybury Rd",
    "iso:country":"GB",
    "sg:address":"19 Maybury Rd",
    "sg:city":"Edinburgh",
    "sg:classifiers":[
        {
            "category":"Education",
            "subcategory":"Music School",
            "type":"Public Place"
        }
    ],
    "sg:postcode":"EH4 8DX",
    "sg:province":"City of Edinburgh",
    "sg:tags":[
        "conservatory"
    ],
    "wof:name":"Stewart,J,",
    "wof:placetype":"venue"
},
  "geometry": {"coordinates":[-3.3062200546,55.9596977234],"type":"Point"}
}