{
  "type": "Feature",
  "properties": {
    "addr:full":"Wilson St Blackburn Lancashire BB2 4AR",
    "addr:postcode":"bb2 4ar",
    "addr:street":"Wilson St",
    "iso:country":"GB",
    "sg:address":"Wilson St",
    "sg:city":"Blackburn",
    "sg:classifiers":[
        {
            "category":"Health Services",
            "subcategory":"Nursing And Care Facility",
            "type":"Services"
        }
    ],
    "sg:phone":"+44 1254 263229",
    "sg:postcode":"BB2 4AR",
    "sg:province":"Lancashire",
    "sg:tags":[
        "home"
    ],
    "wof:name":"St. Emmanuels Residential Home",
    "wof:placetype":"venue"
},
  "geometry": {"coordinates":[-2.4936890602,53.7372894287],"type":"Point"}
}