{
  "type": "Feature",
  "properties": {
    "addr:full":"17-19 Ipswich Street Stowmarket Suffolk IP14 1AH",
    "addr:housenumber":"17-19",
    "addr:postcode":"ip14 1ah",
    "addr:street":"Ipswich Street",
    "iso:country":"GB",
    "sg:address":"17-19 Ipswich Street",
    "sg:city":"Stowmarket",
    "sg:classifiers":[
        {
            "category":"Food & Beverages",
            "subcategory":"Bakery",
            "type":"Retail Goods"
        }
    ],
    "sg:phone":"+44 1449 612752",
    "sg:postcode":"IP14 1AH",
    "sg:province":"Suffolk",
    "sg:tags":[
        "baker"
    ],
    "wof:name":"The Bakers Oven",
    "wof:placetype":"venue"
},
  "geometry": {"coordinates":[0.996535,52.187336],"type":"Point"}
}