{
  "type": "Feature",
  "properties": {
    "iso:country":"GB",
    "sg:address":"109 Park Road",
    "sg:city":"Chorley",
    "sg:classifiers":[
        {
            "category":"Building & Trades",
            "subcategory":"Construction",
            "type":"Services"
        }
    ],
    "sg:postcode":"PR7 1QZ",
    "sg:province":"Lancashire",
    "sg:tags":[
        "roofing"
    ],
    "wof:name":"S N Roofing",
    "wof:placetype":"venue"
},
  "geometry": {"coordinates":[-2.6307120323,53.6595649719],"type":"Point"}
}