{
  "type": "Feature",
  "properties": {
    "iso:country":"GB",
    "sg:address":"Queen Alexandra Road",
    "sg:city":"High Wycombe",
    "sg:classifiers":[
        {
            "category":"Professional",
            "subcategory":"Lawyer & Legal Services",
            "type":"Services"
        }
    ],
    "sg:phone":"+44 1494 526161",
    "sg:postcode":"HP11 2TT",
    "sg:province":"Buckinghamshire",
    "sg:tags":[
        "advice",
        "counselling"
    ],
    "wof:name":"South Buckinghamshire N H S Trust",
    "wof:placetype":"venue"
},
  "geometry": {"coordinates":[-0.7553390265,51.6277618408],"type":"Point"}
}