{
  "type": "Feature",
  "properties": {
    "addr:full":"Unit 8 Huntsbank Business Park, Crewe Road, Wistaston Crewe Cheshire CW2 6QT",
    "addr:housenumber":"unit 8",
    "addr:postcode":"cw2 6qt",
    "addr:street":"Huntsbank Business Park Crewe Road",
    "iso:country":"GB",
    "sg:address":"Unit 8 Huntsbank Business Park, Crewe Road, Wistaston",
    "sg:city":"Crewe",
    "sg:classifiers":[
        {
            "category":"Manufacturing",
            "subcategory":"Wood Products",
            "type":"Manufacturing & Wholesale Goods"
        }
    ],
    "sg:postcode":"CW2 6QT",
    "sg:province":"Cheshire",
    "sg:tags":[
        "packaging",
        "crate",
        "pallets"
    ],
    "wof:name":"Packaging Services",
    "wof:placetype":"venue"
},
  "geometry": {"coordinates":[-2.4774401188,53.075340271],"type":"Point"}
}