{
  "type": "Feature",
  "properties": {
    "iso:country":"GB",
    "sg:address":"72 Home Farm Drive, Allestree",
    "sg:city":"Derby",
    "sg:classifiers":[
        {
            "category":"Education",
            "subcategory":"School",
            "type":"Public Place"
        }
    ],
    "sg:postcode":"DE22 2UP",
    "sg:province":"Derbyshire",
    "sg:tags":[
        "private",
        "tuition"
    ],
    "wof:name":"Elocution",
    "wof:placetype":"venue"
},
  "geometry": {"coordinates":[-1.477159,52.953217],"type":"Point"}
}