{
  "type": "Feature",
  "properties": {
    "iso:country":"GB",
    "sg:address":"County Horticulture & Work Training Unit, 27 Castle Gate",
    "sg:city":"Newark",
    "sg:classifiers":[
        {
            "category":"Government",
            "subcategory":"Office",
            "type":"Public Place"
        }
    ],
    "sg:phone":"+44 1636 612216",
    "sg:postcode":"NG24 1BA",
    "sg:province":"Nottinghamshire",
    "sg:tags":[
        "local"
    ],
    "wof:name":"Nottinghamshire County Council",
    "wof:placetype":"venue"
},
  "geometry": {"coordinates":[-0.811761,53.077065],"type":"Point"}
}