{
  "type": "Feature",
  "properties": {
    "iso:country":"GB",
    "sg:address":"Castle Zens, Ruan High Lanes",
    "sg:city":"Truro",
    "sg:classifiers":[
        {
            "category":"Farming",
            "subcategory":"Livestock Farm",
            "type":"Manufacturing & Wholesale Goods"
        }
    ],
    "sg:phone":"+44 1872 501277",
    "sg:postcode":"TR2 5JZ",
    "sg:province":"Cornwall",
    "sg:tags":[
        "others"
    ],
    "wof:name":"P W Berridge",
    "wof:placetype":"venue"
},
  "geometry": {"coordinates":[-4.942044,50.221596],"type":"Point"}
}