{
  "type": "Feature",
  "properties": {
    "iso:country":"GB",
    "sg:address":"31 Warwick Avenue, Whitefield",
    "sg:city":"Manchester",
    "sg:classifiers":[
        {
            "category":"Building & Trades",
            "subcategory":"Construction",
            "type":"Services"
        }
    ],
    "sg:postcode":"M45 6TU",
    "sg:province":"Lancashire",
    "sg:tags":[
        "builder"
    ],
    "wof:name":"D C Services",
    "wof:placetype":"venue"
},
  "geometry": {"coordinates":[-2.276355,53.543694],"type":"Point"}
}