{
  "type": "Feature",
  "properties": {
    "iso:country":"GB",
    "sg:address":"47 Chester Rd",
    "sg:city":"Northwich",
    "sg:classifiers":[
        {
            "category":"Shopping",
            "subcategory":"Pets & Pet Supplies",
            "type":"Retail Goods"
        }
    ],
    "sg:postcode":"CW8 1HG",
    "sg:province":"Cheshire",
    "wof:name":"Shaw,Elsie,",
    "wof:placetype":"venue"
},
  "geometry": {"coordinates":[-2.5235040188,53.2563552856],"type":"Point"}
}