{
  "type": "Feature",
  "properties": {
    "iso:country":"GB",
    "sg:address":"200a The Broadway",
    "sg:city":"Didcot",
    "sg:classifiers":[
        {
            "category":"Health Services",
            "subcategory":"Dentist",
            "type":"Services"
        }
    ],
    "sg:phone":"+44 1235 813245",
    "sg:postcode":"OX11 8RN",
    "sg:province":"Oxfordshire",
    "wof:name":"L F Taylor",
    "wof:placetype":"venue"
},
  "geometry": {"coordinates":[-1.2321150303,51.6023826599],"type":"Point"}
}