{
  "type": "Feature",
  "properties": {
    "addr:full":"9 Marine Parade Leigh-on-sea Essex SS9 2NA",
    "addr:housenumber":"9",
    "addr:postcode":"ss9 2na",
    "addr:street":"Marine Parade",
    "iso:country":"GB",
    "sg:address":"9 Marine Parade",
    "sg:city":"Leigh-on-sea",
    "sg:classifiers":[
        {
            "category":"Social Services",
            "subcategory":"Retirement Home",
            "type":"Services"
        }
    ],
    "sg:phone":"+44 1702 78245",
    "sg:postcode":"SS9 2NA",
    "sg:province":"Essex",
    "sg:tags":[
        "rest"
    ],
    "wof:name":"Memory House",
    "wof:placetype":"venue"
},
  "geometry": {"coordinates":[0.647187,51.542923],"type":"Point"}
}