{
  "type": "Feature",
  "properties": {
    "addr:full":"242 Fish Dam Lane Barnsley South Yorkshire S71 3EZ",
    "addr:housenumber":"242",
    "addr:postcode":"s71 3ez",
    "addr:street":"Fish Dam Lane;Yorkshire",
    "iso:country":"GB",
    "sg:address":"242 Fish Dam Lane",
    "sg:city":"Barnsley",
    "sg:classifiers":[
        {
            "category":"Shopping",
            "subcategory":"News",
            "type":"Retail Goods"
        }
    ],
    "sg:postcode":"S71 3EZ",
    "sg:province":"South Yorkshire",
    "sg:tags":[
        "newsagent"
    ],
    "wof:name":"Carlton Mini Market",
    "wof:placetype":"venue"
},
  "geometry": {"coordinates":[-1.445918,53.582413],"type":"Point"}
}