{
  "type": "Feature",
  "properties": {
    "iso:country":"GB",
    "sg:address":"85 Adelaide St",
    "sg:city":"Brierley Hill",
    "sg:classifiers":[
        {
            "category":"Manufacturing",
            "subcategory":"Petroleum Products",
            "type":"Manufacturing & Wholesale Goods"
        }
    ],
    "sg:phone":"+44 1384 263824",
    "sg:postcode":"DY5 3HL",
    "sg:province":"West Midlands",
    "sg:tags":[
        "double",
        "glazing"
    ],
    "wof:name":"Proseal Windows",
    "wof:placetype":"venue"
},
  "geometry": {"coordinates":[-2.124898,52.485504],"type":"Point"}
}