{
  "type": "Feature",
  "properties": {
    "addr:full":"26 Aylmer Road London Greater London N2 0BX",
    "addr:housenumber":"26",
    "addr:postcode":"n2 0bx",
    "addr:street":"Aylmer Road",
    "iso:country":"GB",
    "sg:address":"26 Aylmer Road",
    "sg:city":"London",
    "sg:classifiers":[
        {
            "category":"Communications",
            "subcategory":"News Services",
            "type":"Services"
        },
        {
            "category":"Government",
            "subcategory":"Post Office",
            "type":"Public Place"
        }
    ],
    "sg:phone":"+44 20 8341 0091",
    "sg:postcode":"N2 0BX",
    "sg:province":"Greater London",
    "sg:tags":[
        "photo",
        "photograph",
        "agency"
    ],
    "wof:name":"NEWSCLIP",
    "wof:placetype":"venue"
},
  "geometry": {"coordinates":[-0.1644770056,51.5828323364],"type":"Point"}
}