{
  "type": "Feature",
  "properties": {
    "addr:full":"65 Petty France Westminster Greater London SW1H 9EU",
    "addr:housenumber":"65",
    "addr:postcode":"sw1h 9eu",
    "addr:street":"Petty France",
    "iso:country":"GB",
    "sg:address":"65 Petty France",
    "sg:city":"Westminster",
    "sg:classifiers":[
        {
            "category":"Mining & Drilling",
            "type":"Manufacturing & Wholesale Goods"
        }
    ],
    "sg:phone":"+44 20 7222 0171",
    "sg:postcode":"SW1H 9EU",
    "sg:province":"Greater London",
    "sg:tags":[
        "oil",
        "petroleum"
    ],
    "wof:name":"Petrak Services Ltd",
    "wof:placetype":"venue"
},
  "geometry": {"coordinates":[-0.13743,51.499119],"type":"Point"}
}