{
  "type": "Feature",
  "properties": {
    "addr:full":"241 Longton Road, Trentham Stoke-on-trent Staffordshire ST4 8DQ",
    "addr:housenumber":"241",
    "addr:postcode":"staffordshire st4 8dq",
    "addr:street":"Longton Road",
    "iso:country":"GB",
    "sg:address":"241 Longton Road, Trentham",
    "sg:city":"Stoke-on-trent",
    "sg:classifiers":[
        {
            "category":"Social Services",
            "subcategory":"Retirement Home",
            "type":"Services"
        }
    ],
    "sg:phone":"+44 1782 657541",
    "sg:postcode":"ST4 8DQ",
    "sg:province":"Staffordshire",
    "sg:tags":[
        "residential",
        "care"
    ],
    "wof:name":"Lindly House Residential",
    "wof:placetype":"venue"
},
  "geometry": {"coordinates":[-2.178907,52.966457],"type":"Point"}
}