{
  "type": "Feature",
  "properties": {
    "iso:country":"GB",
    "sg:address":"11 Showell Circus Low Hill",
    "sg:city":"Wolverhampton",
    "sg:classifiers":[
        {
            "category":"Shopping",
            "subcategory":"Clothing, Apparel, & Fashions",
            "type":"Retail Goods"
        }
    ],
    "sg:postcode":"WV10 9BA",
    "sg:province":"Staffordshire",
    "sg:tags":[
        "clothing"
    ],
    "wof:name":"Chain Store Recycling Shop",
    "wof:placetype":"venue"
},
  "geometry": {"coordinates":[-2.113238,52.610088],"type":"Point"}
}