{
  "type": "Feature",
  "properties": {
    "iso:country":"GB",
    "sg:address":"53 Blossom Close, Longstone",
    "sg:city":"Newport",
    "sg:classifiers":[
        {
            "category":"Professional",
            "subcategory":"Management & Consulting",
            "type":"Services"
        }
    ],
    "sg:postcode":"NP18 2LT",
    "sg:province":"Monmouthshire",
    "sg:tags":[
        "consultant",
        "specialist"
    ],
    "wof:name":"Perfect Image Home Beauty",
    "wof:placetype":"venue"
},
  "geometry": {"coordinates":[-2.9156320095,51.6019821167],"type":"Point"}
}