{
  "type": "Feature",
  "properties": {
    "addr:full":"Woody's Yard, West Carr Road Attleborough Norfolk NR17 1AN",
    "addr:postcode":"nr17 1an",
    "addr:street":"West Carr Road",
    "iso:country":"GB",
    "sg:address":"Woody's Yard, West Carr Road",
    "sg:city":"Attleborough",
    "sg:classifiers":[
        {
            "category":"Professional",
            "subcategory":"Testing Lab",
            "type":"Services"
        }
    ],
    "sg:phone":"+44 1953 456451",
    "sg:postcode":"NR17 1AN",
    "sg:province":"Norfolk",
    "sg:tags":[
        "mot"
    ],
    "wof:name":"Woody's Haulage Ltd.",
    "wof:placetype":"venue"
},
  "geometry": {"coordinates":[0.98887,52.5131],"type":"Point"}
}