{
  "type": "Feature",
  "properties": {
    "iso:country":"GB",
    "sg:address":"Chichester Way",
    "sg:city":"Christchurch",
    "sg:classifiers":[
        {
            "category":"Professional",
            "subcategory":"Management & Consulting",
            "type":"Services"
        }
    ],
    "sg:postcode":"BH23 4BZ",
    "sg:province":"Dorset",
    "sg:tags":[
        "marketing",
        "consultant"
    ],
    "wof:name":"P P L Sales & Marketing",
    "wof:placetype":"venue"
},
  "geometry": {"coordinates":[-1.741119,50.727894],"type":"Point"}
}