{
  "type": "Feature",
  "properties": {
    "addr:full":"St Augustines Parade Bristol City of Bristol BS1 4UZ",
    "addr:postcode":"bs1 4uz",
    "addr:street":"St Augustines Parade",
    "iso:country":"GB",
    "sg:address":"St Augustines Parade",
    "sg:city":"Bristol",
    "sg:classifiers":[
        {
            "category":"Arts & Performance",
            "subcategory":"Theater",
            "type":"Entertainment"
        }
    ],
    "sg:phone":"+44 117 927 3077",
    "sg:postcode":"BS1 4UZ",
    "sg:province":"City of Bristol",
    "sg:tags":[
        "hall",
        "theatre",
        "concert"
    ],
    "wof:name":"The Bristol Hippodrome",
    "wof:placetype":"venue"
},
  "geometry": {"coordinates":[-2.5975849628,51.4539260864],"type":"Point"}
}