{
  "type": "Feature",
  "properties": {
    "iso:country":"GB",
    "sg:address":"Unit 16 Indoor Market, Market Hall Street",
    "sg:city":"Cannock",
    "sg:classifiers":[
        {
            "category":"Professional",
            "subcategory":"Detective & Security Services",
            "type":"Services"
        }
    ],
    "sg:phone":"+44 1543 577505",
    "sg:postcode":"WS11 1EB",
    "sg:province":"Staffordshire",
    "sg:tags":[
        "locksmith"
    ],
    "wof:name":"Key Bar Security",
    "wof:placetype":"venue"
},
  "geometry": {"coordinates":[-2.033145,52.690952],"type":"Point"}
}