{
  "type": "Feature",
  "properties": {
    "iso:country":"GB",
    "sg:address":"71 Fore St, Topsham",
    "sg:city":"Exeter",
    "sg:classifiers":[
        {
            "category":"Real Estate",
            "subcategory":"Real Estate Agent",
            "type":"Services"
        }
    ],
    "sg:phone":"+44 1392 875057",
    "sg:postcode":"EX3 0HQ",
    "sg:province":"Devon",
    "wof:name":"FULFORDS ESTATE AGENTS LTD",
    "wof:placetype":"venue"
},
  "geometry": {"coordinates":[-3.4659399986,50.6836662292],"type":"Point"}
}