{
  "type": "Feature",
  "properties": {
    "addr:full":"Steep Hill, Maidencombe Torquay Devon TQ1 4TS",
    "addr:postcode":"tq1 4ts",
    "addr:street":"Steep",
    "iso:country":"GB",
    "sg:address":"Steep Hill, Maidencombe",
    "sg:city":"Torquay",
    "sg:classifiers":[
        {
            "category":"Bars & Pubs",
            "type":"Food & Drink"
        }
    ],
    "sg:phone":"+44 1803 329155",
    "sg:postcode":"TQ1 4TS",
    "sg:province":"Devon",
    "sg:tags":[
        "pubs",
        "house",
        "inn",
        "public",
        "activity"
    ],
    "wof:name":"The Thatched Tavern Inn",
    "wof:placetype":"venue"
},
  "geometry": {"coordinates":[-3.517647028,50.5075492859],"type":"Point"}
}