{
  "type": "Feature",
  "properties": {
    "iso:country":"GB",
    "sg:address":"West Grey Lake, Part Lane",
    "sg:city":"Reading",
    "sg:classifiers":[
        {
            "category":"Retail",
            "subcategory":"Repair Shop",
            "type":"Services"
        }
    ],
    "sg:phone":"+44 118 988 7935",
    "sg:postcode":"RG7 1RU",
    "sg:province":"Berkshire",
    "sg:tags":[
        "maintenance"
    ],
    "wof:name":"Narest Management Services Ltd.",
    "wof:placetype":"venue"
},
  "geometry": {"coordinates":[-0.96033,51.363869],"type":"Point"}
}