{
  "type": "Feature",
  "properties": {
    "addr:full":"Croft 21a Ballachulish Highland PA39 4HS",
    "addr:housenumber":"21a",
    "addr:postcode":"pa39 4hs",
    "addr:street":"Croft",
    "iso:country":"GB",
    "sg:address":"Croft 21a",
    "sg:city":"Ballachulish",
    "sg:classifiers":[
        {
            "category":"Home & Garden",
            "subcategory":"Building Materials",
            "type":"Retail Goods"
        }
    ],
    "sg:phone":"+44 1855 811408",
    "sg:postcode":"PA39 4HS",
    "sg:province":"Highland",
    "sg:tags":[
        "fencing"
    ],
    "wof:name":"Derek Macpherson",
    "wof:placetype":"venue"
},
  "geometry": {"coordinates":[-5.1362099648,56.6780700684],"type":"Point"}
}