{
  "type": "Feature",
  "properties": {
    "addr:full":"The Manse, Kirkoswald Penrith Cumbria CA10 1EW",
    "addr:postcode":"ca10 1ew",
    "addr:street":"Kirkoswald",
    "iso:country":"GB",
    "sg:address":"The Manse, Kirkoswald",
    "sg:city":"Penrith",
    "sg:classifiers":[
        {
            "category":"Place Of Worship",
            "type":"Public Place"
        }
    ],
    "sg:phone":"+44 1768 898257",
    "sg:postcode":"CA10 1EW",
    "sg:province":"Cumbria",
    "wof:name":"Kirkoswald Methodist Church",
    "wof:placetype":"venue"
},
  "geometry": {"coordinates":[-2.693748951,54.7646484375],"type":"Point"}
}