{
  "type": "Feature",
  "properties": {
    "iso:country":"GB",
    "sg:address":"16 Oakland Road",
    "sg:city":"Leicester",
    "sg:classifiers":[
        {
            "category":"Shopping",
            "subcategory":"Clothing, Apparel, & Fashions",
            "type":"Retail Goods"
        }
    ],
    "sg:phone":"+44 116 274 6900",
    "sg:postcode":"LE2 6AN",
    "sg:province":"Leicestershire",
    "sg:tags":[
        "clothing",
        "wear",
        "leisure",
        "fabric"
    ],
    "wof:name":"Original Leisurewear Ltd.",
    "wof:placetype":"venue"
},
  "geometry": {"coordinates":[-1.125303,52.614285],"type":"Point"}
}