{
  "type": "Feature",
  "properties": {
    "iso:country":"GB",
    "sg:address":"376 Bowes Rd",
    "sg:city":"Friern Barnet",
    "sg:classifiers":[
        {
            "category":"Food & Beverages",
            "subcategory":"Supermarket",
            "type":"Retail Goods"
        }
    ],
    "sg:phone":"+44 20 8368 5675",
    "sg:postcode":"N11 1AH",
    "sg:province":"Greater London",
    "wof:name":"Misslebrook & Weston",
    "wof:placetype":"venue"
},
  "geometry": {"coordinates":[-0.135632,51.61636],"type":"Point"}
}