{
  "type": "Feature",
  "properties": {
    "iso:country":"GB",
    "sg:address":"6 Burnfield Road, Giffnock",
    "sg:city":"Glasgow",
    "sg:classifiers":[
        {
            "category":"Personal",
            "subcategory":"Beauty Salon",
            "type":"Services"
        }
    ],
    "sg:phone":"+44 141 638 6552",
    "sg:postcode":"G46 7TS",
    "sg:province":"East Renfrewshire",
    "sg:tags":[
        "unisex",
        "hairdresser"
    ],
    "wof:name":"Cartel Hair Design",
    "wof:placetype":"venue"
},
  "geometry": {"coordinates":[-4.2951231003,55.8065681458],"type":"Point"}
}