{
  "type": "Feature",
  "properties": {
    "iso:country":"GB",
    "sg:address":"Chancery La",
    "sg:city":"Kettering",
    "sg:classifiers":[
        {
            "category":"Health Services",
            "subcategory":"Clinic",
            "type":"Services"
        }
    ],
    "sg:phone":"+44 1832 733289",
    "sg:postcode":"NN14 4JL",
    "sg:province":"Northamptonshire",
    "sg:tags":[
        "nh"
    ],
    "wof:name":"Green Lane Health Clinic The",
    "wof:placetype":"venue"
},
  "geometry": {"coordinates":[-0.536835,52.39856],"type":"Point"}
}