{
  "type": "Feature",
  "properties": {
    "addr:full":"Cannon House, 30 Rutland Road Sheffield South Yorkshire S3 8DP",
    "addr:housenumber":"30",
    "addr:postcode":"s3 8dp",
    "addr:street":"Rutland Road",
    "iso:country":"GB",
    "sg:address":"Cannon House, 30 Rutland Road",
    "sg:city":"Sheffield",
    "sg:classifiers":[
        {
            "category":"Professional",
            "subcategory":"Accounting & Tax Preparation",
            "type":"Services"
        }
    ],
    "sg:phone":"+44 114 275 3030",
    "sg:postcode":"S3 8DP",
    "sg:province":"South Yorkshire",
    "sg:tags":[
        "accountant",
        "activity"
    ],
    "wof:name":"Wells Richardson Ltd",
    "wof:placetype":"venue"
},
  "geometry": {"coordinates":[-1.478087,53.39238],"type":"Point"}
}