{
  "type": "Feature",
  "properties": {
    "iso:country":"GB",
    "sg:address":"22-40 Cromwell St",
    "sg:city":"Coventry",
    "sg:classifiers":[
        {
            "category":"Professional",
            "subcategory":"Engineering",
            "type":"Services"
        }
    ],
    "sg:phone":"+44 24 7666 2477",
    "sg:postcode":"CV6 5EZ",
    "sg:province":"Warwickshire",
    "wof:name":"Transtec Machining Coventry",
    "wof:placetype":"venue"
},
  "geometry": {"coordinates":[-1.493636,52.420601],"type":"Point"}
}