{
  "type": "Feature",
  "properties": {
    "iso:country":"GB",
    "sg:address":"22 Battlefield Road",
    "sg:city":"Glasgow",
    "sg:classifiers":[
        {
            "category":"Personal",
            "subcategory":"Beauty Salon",
            "type":"Services"
        },
        {
            "category":"Personal",
            "subcategory":"Barber",
            "type":"Services"
        }
    ],
    "sg:phone":"+44 141 636 5003",
    "sg:postcode":"G42 9QH",
    "sg:province":"Glasgow City",
    "sg:tags":[
        "unisex",
        "hairdresser"
    ],
    "wof:name":"Helen Anderson",
    "wof:placetype":"venue"
},
  "geometry": {"coordinates":[-4.269287,55.82748],"type":"Point"}
}