{
  "type": "Feature",
  "properties": {
    "addr:full":"388 Dickenson Rd Manchester Greater Manchester M13 0WQ",
    "addr:housenumber":"388",
    "addr:postcode":"m13 0wq",
    "addr:street":"Dickenson Rd",
    "iso:country":"GB",
    "sg:address":"388 Dickenson Rd",
    "sg:city":"Manchester",
    "sg:classifiers":[
        {
            "category":"Food & Beverages",
            "subcategory":"Supermarket",
            "type":"Retail Goods"
        }
    ],
    "sg:phone":"+44 161 225 3885",
    "sg:postcode":"M13 0WQ",
    "sg:province":"Greater Manchester",
    "wof:name":"Costcutter",
    "wof:placetype":"venue"
},
  "geometry": {"coordinates":[-2.20109,53.456043],"type":"Point"}
}