{
  "type": "Feature",
  "properties": {
    "iso:country":"GB",
    "sg:address":"205 Shackleton Court, Whitney Close",
    "sg:city":"Staines",
    "sg:classifiers":[
        {
            "category":"Professional",
            "subcategory":"Business Services",
            "type":"Services"
        }
    ],
    "sg:phone":"+44 1784 255184",
    "sg:postcode":"TW19 7DF",
    "sg:province":"Berkshire",
    "sg:tags":[
        "shop",
        "cleaning"
    ],
    "wof:name":"J Clean",
    "wof:placetype":"venue"
},
  "geometry": {"coordinates":[-0.47386,51.45739],"type":"Point"}
}