{
  "type": "Feature",
  "properties": {
    "addr:full":"205 Shackleton Court, Whitney Close Staines Berkshire TW19 7DF",
    "addr:housenumber":"205",
    "addr:postcode":"berkshire tw19 7df",
    "addr:street":"Shackleton Court Whitney Close",
    "iso:country":"GB",
    "sg:address":"205 Shackleton Court, Whitney Close",
    "sg:city":"Staines",
    "sg:classifiers":[
        {
            "category":"Professional",
            "subcategory":"Business Services",
            "type":"Services"
        }
    ],
    "sg:phone":"+44 1784 255184",
    "sg:postcode":"TW19 7DF",
    "sg:province":"Berkshire",
    "sg:tags":[
        "shop",
        "cleaning"
    ],
    "wof:name":"J Clean",
    "wof:placetype":"venue"
},
  "geometry": {"coordinates":[-0.47386,51.45739],"type":"Point"}
}