{
  "type": "Feature",
  "properties": {
    "iso:country":"GB",
    "sg:address":"2 Orton Avenue, Woodston",
    "sg:city":"Peterborough",
    "sg:classifiers":[
        {
            "category":"Fast Food",
            "type":"Food & Drink"
        },
        {
            "category":"Food & Beverages",
            "subcategory":"Meat & Fish",
            "type":"Retail Goods"
        },
        {
            "category":"Food & Beverages",
            "subcategory":"Groceries & Convenience Stores",
            "type":"Retail Goods"
        }
    ],
    "sg:phone":"+44 1733 551133",
    "sg:postcode":"PE2 9HL",
    "sg:province":"Cambridgeshire",
    "sg:tags":[
        "shop",
        "away",
        "take",
        "chip"
    ],
    "wof:name":"The Crown Fish Bar",
    "wof:placetype":"venue"
},
  "geometry": {"coordinates":[-0.255388,52.558132],"type":"Point"}
}