{
  "type": "Feature",
  "properties": {
    "iso:country":"GB",
    "sg:address":"8 The Courtyard, Deeside Enterprise Centre, Rowleys Drive",
    "sg:city":"Deeside",
    "sg:classifiers":[
        {
            "category":"Shopping",
            "subcategory":"Optical Goods",
            "type":"Retail Goods"
        }
    ],
    "sg:phone":"+44 1244 813990",
    "sg:postcode":"CH5 1PP",
    "sg:province":"Flintshire",
    "sg:tags":[
        "medical"
    ],
    "wof:name":"Alan Williams Cl Ltd.",
    "wof:placetype":"venue"
},
  "geometry": {"coordinates":[-3.024988,53.20248],"type":"Point"}
}