{
  "type": "Feature",
  "properties": {
    "addr:full":"The Baldwins, Framilode Gloucester Gloucestershire GL2 7LL",
    "addr:postcode":"gl2 7ll",
    "iso:country":"GB",
    "sg:address":"The Baldwins, Framilode",
    "sg:city":"Gloucester",
    "sg:classifiers":[
        {
            "category":"Recreation",
            "subcategory":"Fishing",
            "type":"Entertainment"
        }
    ],
    "sg:postcode":"GL2 7LL",
    "sg:province":"Gloucestershire",
    "sg:tags":[
        "angling"
    ],
    "wof:name":"Clark,Charles Henry,",
    "wof:placetype":"venue"
},
  "geometry": {"coordinates":[-2.372701,51.792171],"type":"Point"}
}