{
  "type": "Feature",
  "properties": {
    "iso:country":"GB",
    "sg:address":"Cae Fali",
    "sg:city":"Holyhead",
    "sg:classifiers":[
        {
            "category":"Health Services",
            "subcategory":"Doctor",
            "type":"Services"
        }
    ],
    "sg:phone":"+44 1407 720798",
    "sg:postcode":"LL65 4RS",
    "sg:province":"Isle of Anglesey",
    "sg:tags":[
        "practitioners"
    ],
    "wof:name":"Bryngwran Surgery",
    "wof:placetype":"venue"
},
  "geometry": {"coordinates":[-4.41088,53.255581],"type":"Point"}
}