{
  "type": "Feature",
  "properties": {
    "addr:full":"Sherwood Road Birmingham West Midlands B28 0EX",
    "addr:postcode":"b28 0ex",
    "addr:street":"Sherwood Road",
    "iso:country":"GB",
    "sg:address":"Sherwood Road",
    "sg:city":"Birmingham",
    "sg:classifiers":[
        {
            "category":"Arena",
            "subcategory":"Sports Club",
            "type":"Entertainment"
        }
    ],
    "sg:phone":"+44 121 624 2727",
    "sg:postcode":"B28 0EX",
    "sg:province":"West Midlands",
    "wof:name":"Moor Green Football Club",
    "wof:placetype":"venue"
},
  "geometry": {"coordinates":[-1.849474,52.428665],"type":"Point"}
}