{
  "type": "Feature",
  "properties": {
    "iso:country":"GB",
    "sg:address":"Newlands Road",
    "sg:city":"Luton",
    "sg:classifiers":[
        {
            "category":"Arena",
            "subcategory":"Sports Club",
            "type":"Entertainment"
        }
    ],
    "sg:phone":"+44 1582 720355",
    "sg:postcode":"LU1 4BQ",
    "sg:province":"Bedfordshire",
    "sg:website":"http://www.lutonrugby.com",
    "wof:name":"Luton Rugby Football Club",
    "wof:placetype":"venue"
},
  "geometry": {"coordinates":[-0.434254,51.866455],"type":"Point"}
}