{
  "type": "Feature",
  "properties": {
    "iso:country":"GB",
    "sg:address":"Station App, Crofton Road",
    "sg:city":"Orpington",
    "sg:classifiers":[
        {
            "category":"Professional",
            "subcategory":"Printing & Photocopies",
            "type":"Services"
        }
    ],
    "sg:postcode":"BR6 0SU",
    "sg:province":"Kent",
    "sg:tags":[
        "trophy"
    ],
    "wof:name":"Top Awards",
    "wof:placetype":"venue"
},
  "geometry": {"coordinates":[0.10108,51.37804],"type":"Point"}
}