{
  "type": "Feature",
  "properties": {
    "iso:country":"GB",
    "sg:address":"33 Montgomery Street",
    "sg:city":"Hove",
    "sg:classifiers":[
        {
            "category":"Bars & Pubs",
            "type":"Food & Drink"
        }
    ],
    "sg:phone":"+44 1273 272212",
    "sg:postcode":"BN3 5BF",
    "sg:province":"East Sussex",
    "sg:tags":[
        "pubs",
        "inn"
    ],
    "wof:name":"The Eclipse Public House",
    "wof:placetype":"venue"
},
  "geometry": {"coordinates":[-0.1787710041,50.8341255188],"type":"Point"}
}