{
  "type": "Feature",
  "properties": {
    "addr:full":"Aylesbeare Nature Reserve, Aylesbeare Exeter Devon EX5 2JS",
    "addr:postcode":"ex5 2js",
    "iso:country":"GB",
    "sg:address":"Aylesbeare Nature Reserve, Aylesbeare",
    "sg:city":"Exeter",
    "sg:classifiers":[
        {
            "category":"Organizations",
            "subcategory":"Non-profit Organization",
            "type":"Services"
        }
    ],
    "sg:phone":"+44 1395 233655",
    "sg:postcode":"EX5 2JS",
    "sg:province":"Devon",
    "sg:tags":[
        "organisation",
        "voluntary",
        "charity"
    ],
    "wof:name":"Royal Society for the Protection of Birds",
    "wof:placetype":"venue"
},
  "geometry": {"coordinates":[-3.362879,50.719501],"type":"Point"}
}