{
  "type": "Feature",
  "properties": {
    "iso:country":"GB",
    "sg:address":"158 Brynglas Road",
    "sg:city":"Newport",
    "sg:classifiers":[
        {
            "category":"Professional",
            "subcategory":"Art Services",
            "type":"Services"
        },
        {
            "category":"Building & Trades",
            "subcategory":"Construction",
            "type":"Services"
        }
    ],
    "sg:phone":"+44 1633 858921",
    "sg:postcode":"NP20 5QG",
    "sg:province":"Newport",
    "sg:tags":[
        "decorator",
        "painter"
    ],
    "wof:name":"D N Decorra",
    "wof:placetype":"venue"
},
  "geometry": {"coordinates":[-2.997844,51.602894],"type":"Point"}
}