{
  "type": "Feature",
  "properties": {
    "addr:full":"Unit 6, The Off Quay Building Newcastle Upon Tyne Tyne and Wear NE6 1LH",
    "addr:housenumber":"unit 6",
    "addr:postcode":"ne6 1lh",
    "addr:street":"The Off",
    "iso:country":"GB",
    "sg:address":"Unit 6, The Off Quay Building",
    "sg:city":"Newcastle Upon Tyne",
    "sg:classifiers":[
        {
            "category":"Health Services",
            "subcategory":"Dentist",
            "type":"Services"
        }
    ],
    "sg:phone":"+44 191 265 4930",
    "sg:postcode":"NE6 1LH",
    "sg:province":"Tyne and Wear",
    "sg:tags":[
        "technician",
        "dental"
    ],
    "wof:name":"R.J Elliott",
    "wof:placetype":"venue"
},
  "geometry": {"coordinates":[-1.5908600092,54.9740982056],"type":"Point"}
}