{
  "type": "Feature",
  "properties": {
    "addr:full":"Dyfrig Street Shotts North Lanarkshire ML7 4DH",
    "addr:postcode":"ml7 4dh",
    "addr:street":"Dyfrig Street",
    "iso:country":"GB",
    "sg:address":"Dyfrig Street",
    "sg:city":"Shotts",
    "sg:classifiers":[
        {
            "category":"Professional",
            "subcategory":"Employment Agencies",
            "type":"Services"
        }
    ],
    "sg:phone":"+44 1501 676700",
    "sg:postcode":"ML7 4DH",
    "sg:province":"North Lanarkshire",
    "sg:tags":[
        "consultant"
    ],
    "wof:name":"Jobcentre",
    "wof:placetype":"venue"
},
  "geometry": {"coordinates":[-3.8001339436,55.8253707886],"type":"Point"}
}