{
  "type": "Feature",
  "properties": {
    "addr:full":"19 Trinity Square Llandudno Conwy LL30 2RD",
    "addr:housenumber":"19",
    "addr:postcode":"ll30 2rd",
    "addr:street":"Trinity Square",
    "iso:country":"GB",
    "sg:address":"19 Trinity Square",
    "sg:city":"Llandudno",
    "sg:classifiers":[
        {
            "category":"Professional",
            "subcategory":"Engineering",
            "type":"Services"
        }
    ],
    "sg:postcode":"LL30 2RD",
    "sg:province":"Conwy",
    "sg:tags":[
        "design",
        "engineer"
    ],
    "wof:name":"Dts Consulting Ltd",
    "wof:placetype":"venue"
},
  "geometry": {"coordinates":[-3.82863,53.322334],"type":"Point"}
}