{
  "type": "Feature",
  "properties": {
    "iso:country":"GB",
    "sg:address":"Thurston Ho, 80 Lincoln Rd",
    "sg:city":"Peterborough",
    "sg:classifiers":[
        {
            "category":"Education",
            "subcategory":"Special Training",
            "type":"Public Place"
        }
    ],
    "sg:phone":"+44 1733 559152",
    "sg:postcode":"PE1 2SN",
    "sg:province":"Cambridgeshire",
    "sg:tags":[
        "product",
        "centre"
    ],
    "wof:name":"Hospitality & Catering Training Partnership",
    "wof:placetype":"venue"
},
  "geometry": {"coordinates":[-0.2436199933,52.5793495178],"type":"Point"}
}