{
  "type": "Feature",
  "properties": {
    "iso:country":"GB",
    "sg:address":"Rhos Road, Penyffordd",
    "sg:city":"Chester",
    "sg:classifiers":[
        {
            "category":"Bars & Pubs",
            "type":"Food & Drink"
        }
    ],
    "sg:phone":"+44 1244 551051",
    "sg:postcode":"CH4 0JR",
    "sg:province":"Cheshire",
    "sg:tags":[
        "pubs",
        "inn"
    ],
    "wof:name":"A Sheppard",
    "wof:placetype":"venue"
},
  "geometry": {"coordinates":[-3.0469460487,53.1495018005],"type":"Point"}
}