{
  "type": "Feature",
  "properties": {
    "iso:country":"GB",
    "sg:address":"123 Coates Road, Eastrea",
    "sg:city":"Peterborough",
    "sg:classifiers":[
        {
            "category":"Building & Trades",
            "subcategory":"Cleaning & Sanitation",
            "type":"Services"
        }
    ],
    "sg:phone":"+44 1733 205641",
    "sg:postcode":"PE7 2BD",
    "sg:province":"Cambridgeshire",
    "sg:tags":[
        "dry",
        "control",
        "damp",
        "rot"
    ],
    "wof:name":"Prodec Building Contractor",
    "wof:placetype":"venue"
},
  "geometry": {"coordinates":[-0.0808169991,52.5596809387],"type":"Point"}
}