{
  "type": "Feature",
  "properties": {
    "iso:country":"GB",
    "sg:address":"540 Lordship Lane",
    "sg:city":"London",
    "sg:classifiers":[
        {
            "category":"Food & Beverages",
            "subcategory":"Liquor & Beverages",
            "type":"Retail Goods"
        }
    ],
    "sg:phone":"+44 20 8881 6643",
    "sg:postcode":"N22 5BY",
    "sg:province":"Greater London",
    "sg:tags":[
        "beer",
        "wine",
        "spirit",
        "wines"
    ],
    "wof:name":"Lordship Free Off Licence",
    "wof:placetype":"venue"
},
  "geometry": {"coordinates":[-0.096423,51.598511],"type":"Point"}
}