{
  "type": "Feature",
  "properties": {
    "iso:country":"GB",
    "sg:address":"Westfield Medical Centre, 2 St Martins Terr",
    "sg:city":"Leeds",
    "sg:classifiers":[
        {
            "category":"Health Services",
            "subcategory":"Doctor",
            "type":"Services"
        }
    ],
    "sg:phone":"+44 113 262 0058",
    "sg:postcode":"LS7 4JB",
    "sg:province":"West Yorkshire",
    "sg:tags":[
        "practitioners"
    ],
    "wof:name":"Babu, P",
    "wof:placetype":"venue"
},
  "geometry": {"coordinates":[-1.53208,53.82169],"type":"Point"}
}