{
  "type": "Feature",
  "properties": {
    "addr:full":"39 Ivanhoe Avenue, Attleborough Nuneaton Leicestershire CV11 4RW",
    "addr:housenumber":"39",
    "addr:postcode":"cv11 4rw",
    "addr:street":"Ivanhoe Avenue",
    "iso:country":"GB",
    "sg:address":"39 Ivanhoe Avenue, Attleborough",
    "sg:city":"Nuneaton",
    "sg:classifiers":[
        {
            "category":"Retail",
            "subcategory":"Driving School",
            "type":"Services"
        }
    ],
    "sg:postcode":"CV11 4RW",
    "sg:province":"Leicestershire",
    "wof:name":"Borough School of Motoring",
    "wof:placetype":"venue"
},
  "geometry": {"coordinates":[-1.4505230188,52.5099487305],"type":"Point"}
}