{
  "type": "Feature",
  "properties": {
    "addr:full":"Southlands, Cosheston Pembroke Dock Pembrokeshire SA72 4TU",
    "addr:housenumber":"cosheston",
    "addr:postcode":"sa72 4tu",
    "iso:country":"GB",
    "sg:address":"Southlands, Cosheston",
    "sg:city":"Pembroke Dock",
    "sg:classifiers":[
        {
            "category":"Farming",
            "subcategory":"Fish & Marine Products",
            "type":"Manufacturing & Wholesale Goods"
        }
    ],
    "sg:postcode":"SA72 4TU",
    "sg:province":"Pembrokeshire",
    "sg:tags":[
        "fishmonger"
    ],
    "wof:name":"N A Viles",
    "wof:placetype":"venue"
},
  "geometry": {"coordinates":[-4.8887791634,51.6971282959],"type":"Point"}
}