{
  "type": "Feature",
  "properties": {
    "addr:full":"8 Larkfield Way Brighton East Sussex BN1 8EF",
    "addr:housenumber":"8",
    "addr:postcode":"bn1 8ef",
    "addr:street":"Larkfield Way",
    "iso:country":"GB",
    "sg:address":"8 Larkfield Way",
    "sg:city":"Brighton",
    "sg:classifiers":[
        {
            "category":"Home & Garden",
            "subcategory":"Building Materials",
            "type":"Retail Goods"
        },
        {
            "category":"Building & Trades",
            "subcategory":"Construction",
            "type":"Services"
        }
    ],
    "sg:phone":"+44 1273 381830",
    "sg:postcode":"BN1 8EF",
    "sg:province":"East Sussex",
    "sg:tags":[
        "dry",
        "plasterers",
        "installers",
        "lining",
        "insulation",
        "screeders"
    ],
    "wof:name":"N S Benn Plastering Services",
    "wof:placetype":"venue"
},
  "geometry": {"coordinates":[-0.1397490054,50.8549766541],"type":"Point"}
}