{
  "type": "Feature",
  "properties": {
    "addr:full":"Po Box 16, Euclid Crescent Dundee Dundee City DD1 1HU",
    "addr:housenumber":"po box 16",
    "addr:postcode":"dd1 1hu",
    "addr:street":"Euclid Crescent",
    "iso:country":"GB",
    "sg:address":"Po Box 16, Euclid Crescent",
    "sg:city":"Dundee",
    "sg:classifiers":[
        {
            "category":"Education",
            "subcategory":"School",
            "type":"Public Place"
        }
    ],
    "sg:phone":"+44 1382 202921",
    "sg:postcode":"DD1 1HU",
    "sg:province":"Dundee City",
    "sg:tags":[
        "independent",
        "preparatory"
    ],
    "wof:name":"High School of Dundee",
    "wof:placetype":"venue"
},
  "geometry": {"coordinates":[-2.9676089287,56.4613761902],"type":"Point"}
}