{
  "type": "Feature",
  "properties": {
    "iso:country":"GB",
    "sg:address":"4 Caledfwlch, Cwmifor",
    "sg:city":"Llandeilo",
    "sg:classifiers":[
        {
            "category":"Building & Trades",
            "subcategory":"Cleaning & Sanitation",
            "type":"Services"
        }
    ],
    "sg:postcode":"SA19 7BT",
    "sg:province":"Carmarthenshire",
    "sg:tags":[
        "steam"
    ],
    "wof:name":"Simon Hall",
    "wof:placetype":"venue"
},
  "geometry": {"coordinates":[-3.993757,51.951466],"type":"Point"}
}