{
  "type": "Feature",
  "properties": {
    "addr:full":"The Cottage, Lenton Grantham Leicestershire NG33 4HE",
    "addr:postcode":"ng33 4he",
    "iso:country":"GB",
    "sg:address":"The Cottage, Lenton",
    "sg:city":"Grantham",
    "sg:classifiers":[
        {
            "category":"Food & Beverages",
            "subcategory":"Liquor & Beverages",
            "type":"Retail Goods"
        }
    ],
    "sg:postcode":"NG33 4HE",
    "sg:province":"Leicestershire",
    "sg:tags":[
        "beer",
        "spirit",
        "wines"
    ],
    "wof:name":"A K Finch-Noyes & Co.",
    "wof:placetype":"venue"
},
  "geometry": {"coordinates":[-0.4787890017,52.8613815308],"type":"Point"}
}