{
  "type": "Feature",
  "properties": {
    "iso:country":"GB",
    "sg:address":"551 Rayleigh Road",
    "sg:city":"Leigh-on-sea",
    "sg:classifiers":[
        {
            "category":"Food & Beverages",
            "subcategory":"Meat & Fish",
            "type":"Retail Goods"
        }
    ],
    "sg:phone":"+44 1702 525238",
    "sg:postcode":"SS9 5HP",
    "sg:province":"Essex",
    "sg:tags":[
        "chip"
    ],
    "wof:name":"Yu Chinese Take Away",
    "wof:placetype":"venue"
},
  "geometry": {"coordinates":[0.638802,51.572845],"type":"Point"}
}