{
  "type": "Feature",
  "properties": {
    "addr:full":"241 Foley Road West Sutton Coldfield Staffordshire B74 3NU",
    "addr:housenumber":"241",
    "addr:postcode":"b74 3nu",
    "addr:street":"Foley Road West",
    "iso:country":"GB",
    "sg:address":"241 Foley Road West",
    "sg:city":"Sutton Coldfield",
    "sg:classifiers":[
        {
            "category":"Professional",
            "subcategory":"Computer Services",
            "type":"Services"
        }
    ],
    "sg:postcode":"B74 3NU",
    "sg:province":"Staffordshire",
    "sg:tags":[
        "system",
        "software"
    ],
    "wof:name":"Potters Cross Ltd",
    "wof:placetype":"venue"
},
  "geometry": {"coordinates":[-1.901031,52.582081],"type":"Point"}
}