{
  "type": "Feature",
  "properties": {
    "addr:full":"80 Mill Gate Newark Nottinghamshire NG24 4TY",
    "addr:housenumber":"80",
    "addr:postcode":"ng24 4ty",
    "addr:street":"Mill Gate",
    "iso:country":"GB",
    "sg:address":"80 Mill Gate",
    "sg:city":"Newark",
    "sg:classifiers":[
        {
            "category":"Personal",
            "type":"Services"
        }
    ],
    "sg:phone":"+44 1636 640410",
    "sg:postcode":"NG24 4TY",
    "sg:province":"Nottinghamshire",
    "sg:tags":[
        "gift"
    ],
    "wof:name":"K L S Ltd.",
    "wof:placetype":"venue"
},
  "geometry": {"coordinates":[-0.8184310198,53.073348999],"type":"Point"}
}