{
  "type": "Feature",
  "properties": {
    "addr:full":"Galley Hill Road Waltham Abbey Essex EN9 2AG",
    "addr:postcode":"en9 2ag",
    "addr:street":"Galley Hill Road",
    "iso:country":"GB",
    "sg:address":"Galley Hill Road",
    "sg:city":"Waltham Abbey",
    "sg:classifiers":[
        {
            "category":"Building & Trades",
            "subcategory":"Equipment Rental",
            "type":"Services"
        }
    ],
    "sg:phone":"+44 1992 890990",
    "sg:postcode":"EN9 2AG",
    "sg:province":"Essex",
    "sg:tags":[
        "plant",
        "machinery"
    ],
    "wof:name":"Orbital Equipment Ltd.",
    "wof:placetype":"venue"
},
  "geometry": {"coordinates":[0.0156950001,51.6915512085],"type":"Point"}
}