{
  "type": "Feature",
  "properties": {
    "iso:country":"GB",
    "sg:address":"110 Kitts Green Rd",
    "sg:city":"Birmingham",
    "sg:classifiers":[
        {
            "category":"Personal",
            "subcategory":"Beauty Salon",
            "type":"Services"
        }
    ],
    "sg:phone":"+44 121 785 2406",
    "sg:postcode":"B33 9HT",
    "sg:province":"West Midlands",
    "sg:tags":[
        "unisex",
        "hairdresser"
    ],
    "wof:name":"Clipper Snippers",
    "wof:placetype":"venue"
},
  "geometry": {"coordinates":[-1.78788,52.485863],"type":"Point"}
}