{
  "type": "Feature",
  "properties": {
    "iso:country":"GB",
    "sg:address":"Unit Apex Court, Woodlands",
    "sg:city":"Bristol",
    "sg:classifiers":[
        {
            "category":"Real Estate",
            "subcategory":"Surveying",
            "type":"Services"
        }
    ],
    "sg:phone":"+44 1454 456630",
    "sg:postcode":"BS32 4JT",
    "sg:province":"Gloucestershire",
    "sg:tags":[
        "surveyor",
        "quantity"
    ],
    "wof:name":"Henry Riley & Son",
    "wof:placetype":"venue"
},
  "geometry": {"coordinates":[-2.545937,51.556488],"type":"Point"}
}