{
  "type": "Feature",
  "properties": {
    "iso:country":"GB",
    "sg:address":"28 Greenacres, Freckleton",
    "sg:city":"Preston",
    "sg:classifiers":[
        {
            "category":"Retail",
            "subcategory":"Driving School",
            "type":"Services"
        }
    ],
    "sg:postcode":"PR4 1PS",
    "sg:province":"Lancashire",
    "wof:name":"Ray Shannon",
    "wof:placetype":"venue"
},
  "geometry": {"coordinates":[-2.880749,53.752731],"type":"Point"}
}