{
  "type": "Feature",
  "properties": {
    "addr:full":"39 Oreston Road, Plymstock Plymouth Devon PL9 7JX",
    "addr:housenumber":"39",
    "addr:postcode":"pl9 7jx",
    "addr:street":"Oreston Road",
    "iso:country":"GB",
    "sg:address":"39 Oreston Road, Plymstock",
    "sg:city":"Plymouth",
    "sg:classifiers":[
        {
            "category":"Building & Trades",
            "subcategory":"Construction",
            "type":"Services"
        }
    ],
    "sg:phone":"+44 1752 491025",
    "sg:postcode":"PL9 7JX",
    "sg:province":"Devon",
    "sg:tags":[
        "roofing"
    ],
    "wof:name":"John Lane Felt Roofing",
    "wof:placetype":"venue"
},
  "geometry": {"coordinates":[-4.105667,50.362751],"type":"Point"}
}