{
  "type": "Feature",
  "properties": {
    "addr:full":"45 Windmill Road Brentford Greater London TW8 0QQ",
    "addr:housenumber":"45",
    "addr:postcode":"tw8 0qq",
    "addr:street":"Windmill Road",
    "iso:country":"GB",
    "sg:address":"45 Windmill Road",
    "sg:city":"Brentford",
    "sg:classifiers":[
        {
            "category":"Shopping",
            "subcategory":"Antiques",
            "type":"Retail Goods"
        }
    ],
    "sg:postcode":"TW8 0QQ",
    "sg:province":"Greater London",
    "wof:name":"Antique Restorations",
    "wof:placetype":"venue"
},
  "geometry": {"coordinates":[-0.3082340062,51.4890594482],"type":"Point"}
}