{
  "type": "Feature",
  "properties": {
    "iso:country":"GB",
    "sg:address":"Rathbone House, 22 Tanfield Road",
    "sg:city":"Croydon",
    "sg:classifiers":[
        {
            "category":"Banks & Credit Unions",
            "subcategory":"Financial Services",
            "type":"Services"
        }
    ],
    "sg:phone":"+44 20 8240 4487",
    "sg:postcode":"CR0 1AL",
    "sg:province":"Surrey",
    "sg:tags":[
        "adviser",
        "independent"
    ],
    "wof:name":"Baker Gladstone & York Ltd.",
    "wof:placetype":"venue"
},
  "geometry": {"coordinates":[-0.1034990028,51.3675613403],"type":"Point"}
}