{
  "type": "Feature",
  "properties": {
    "addr:full":"A11, Snetterton Norwich Norfolk NR16 2JY",
    "addr:postcode":"nr16 2jy",
    "addr:street":"Norwich",
    "iso:country":"GB",
    "sg:address":"A11, Snetterton",
    "sg:city":"Norwich",
    "sg:classifiers":[
        {
            "category":"Restaurant",
            "type":"Food & Drink"
        }
    ],
    "sg:phone":"+44 1953 888247",
    "sg:postcode":"NR16 2JY",
    "sg:province":"Norfolk",
    "wof:name":"Little Chef",
    "wof:placetype":"venue"
},
  "geometry": {"coordinates":[0.840446,52.446205],"type":"Point"}
}