{
  "type": "Feature",
  "properties": {
    "iso:country":"GB",
    "sg:address":"59 Cranmer Bank",
    "sg:city":"Leeds",
    "sg:classifiers":[
        {
            "category":"Government",
            "subcategory":"Post Office",
            "type":"Public Place"
        }
    ],
    "sg:phone":"+44 113 268 3289",
    "sg:postcode":"LS17 5JD",
    "sg:province":"North Yorkshire",
    "wof:name":"Cranmer Bank Sub Post Office",
    "wof:placetype":"venue"
},
  "geometry": {"coordinates":[-1.557978,53.84774],"type":"Point"}
}