{
  "type": "Feature",
  "properties": {
    "addr:full":"Nelson Pl Sidcup Kent DA14 6DZ",
    "addr:postcode":"da14 6dz",
    "addr:street":"Nelson Pl",
    "iso:country":"GB",
    "sg:address":"Nelson Pl",
    "sg:city":"Sidcup",
    "sg:classifiers":[
        {
            "category":"Community Center",
            "subcategory":"Youth",
            "type":"Public Place"
        }
    ],
    "sg:phone":"+44 20 8309 9344",
    "sg:postcode":"DA14 6DZ",
    "sg:province":"Kent",
    "sg:tags":[
        "organisation",
        "centre"
    ],
    "wof:name":"Worx The",
    "wof:placetype":"venue"
},
  "geometry": {"coordinates":[0.10253,51.425564],"type":"Point"}
}