{
  "type": "Feature",
  "properties": {
    "addr:full":"176 Stamford Brook Arches, Ravenscourt Park Hammersmith Greater London W6 0TQ",
    "addr:housenumber":"176",
    "addr:postcode":"w6 0tq",
    "addr:street":"Stamford Brook Arches Ravenscourt Park",
    "iso:country":"GB",
    "sg:address":"176 Stamford Brook Arches, Ravenscourt Park",
    "sg:city":"Hammersmith",
    "sg:classifiers":[
        {
            "category":"Retail",
            "subcategory":"Auto Repair",
            "type":"Services"
        }
    ],
    "sg:phone":"+44 20 8563 0638",
    "sg:postcode":"W6 0TQ",
    "sg:province":"Greater London",
    "sg:tags":[
        "modification",
        "garage"
    ],
    "wof:name":"Addis Motors",
    "wof:placetype":"venue"
},
  "geometry": {"coordinates":[-0.22942,51.496151],"type":"Point"}
}