{
  "type": "Feature",
  "properties": {
    "iso:country":"GB",
    "sg:address":"102 Station Road, Crayford",
    "sg:city":"Dartford",
    "sg:classifiers":[
        {
            "category":"Building & Trades",
            "subcategory":"Construction",
            "type":"Services"
        }
    ],
    "sg:phone":"+44 1322 554792",
    "sg:postcode":"DA1 3QG",
    "sg:province":"Kent",
    "sg:tags":[
        "builder"
    ],
    "wof:name":"P J M Partnership Ltd.",
    "wof:placetype":"venue"
},
  "geometry": {"coordinates":[0.18019,51.446735],"type":"Point"}
}