{
  "type": "Feature",
  "properties": {
    "iso:country":"GB",
    "sg:address":"24 Parsons Street",
    "sg:city":"Banbury",
    "sg:classifiers":[
        {
            "category":"Personal",
            "subcategory":"Beauty Salon",
            "type":"Services"
        }
    ],
    "sg:phone":"+44 1295 263636",
    "sg:postcode":"OX16 5LY",
    "sg:province":"Oxfordshire",
    "sg:tags":[
        "unisex",
        "hairdresser"
    ],
    "wof:name":"Annmareque",
    "wof:placetype":"venue"
},
  "geometry": {"coordinates":[-1.3361799717,52.0621414185],"type":"Point"}
}