{
  "type": "Feature",
  "properties": {
    "iso:country":"GB",
    "sg:address":"Little Burrows, Throwleigh",
    "sg:city":"Okehampton",
    "sg:classifiers":[
        {
            "category":"Shopping",
            "subcategory":"Pharmacy",
            "type":"Retail Goods"
        }
    ],
    "sg:phone":"+44 1647 231305",
    "sg:postcode":"EX20 2HX",
    "sg:province":"Devon",
    "sg:tags":[
        "medicine",
        "therapy"
    ],
    "wof:name":"Richard Knapp",
    "wof:placetype":"venue"
},
  "geometry": {"coordinates":[-3.887203,50.701202],"type":"Point"}
}