{
  "type": "Feature",
  "properties": {
    "iso:country":"GB",
    "sg:address":"43 Bath St",
    "sg:city":"Leamington Spa",
    "sg:classifiers":[
        {
            "category":"Professional",
            "subcategory":"Printing & Photocopies",
            "type":"Services"
        }
    ],
    "sg:phone":"+44 1926 886776",
    "sg:postcode":"CV31 3AG",
    "sg:province":"Warwickshire",
    "sg:tags":[
        "printer"
    ],
    "wof:name":"Master Printers",
    "wof:placetype":"venue"
},
  "geometry": {"coordinates":[-1.5321749449,52.2845039368],"type":"Point"}
}