{
  "type": "Feature",
  "properties": {
    "addr:full":"Waverley House, High Street Fort William Highland PH33 6XX",
    "addr:postcode":"ph33 6xx",
    "addr:street":"High Street",
    "iso:country":"GB",
    "sg:address":"Waverley House, High Street",
    "sg:city":"Fort William",
    "sg:classifiers":[
        {
            "category":"Professional",
            "subcategory":"Employment Agencies",
            "type":"Services"
        }
    ],
    "sg:phone":"+44 1397 902000",
    "sg:postcode":"PH33 6XX",
    "sg:province":"Highland",
    "sg:tags":[
        "consultant",
        "recruitment"
    ],
    "wof:name":"Jobcentre Plus",
    "wof:placetype":"venue"
},
  "geometry": {"coordinates":[-5.109314,56.819016],"type":"Point"}
}