{
  "type": "Feature",
  "properties": {
    "addr:full":"1 Arden Street Stratford-upon-avon Warwickshire CV37 6PA",
    "addr:housenumber":"1",
    "addr:postcode":"cv37 6pa",
    "addr:street":"Arden Street",
    "iso:country":"GB",
    "sg:address":"1 Arden Street",
    "sg:city":"Stratford-upon-avon",
    "sg:classifiers":[
        {
            "category":"Bars & Pubs",
            "type":"Food & Drink"
        }
    ],
    "sg:phone":"+44 1789 297641",
    "sg:postcode":"CV37 6PA",
    "sg:province":"Warwickshire",
    "sg:tags":[
        "pubs",
        "inn"
    ],
    "wof:name":"Froth & Elbow",
    "wof:placetype":"venue"
},
  "geometry": {"coordinates":[-1.712362,52.193275],"type":"Point"}
}