{
  "type": "Feature",
  "properties": {
    "iso:country":"GB",
    "sg:address":"53 Symington Street, Leadhills",
    "sg:city":"Biggar",
    "sg:classifiers":[
        {
            "category":"Utilities",
            "subcategory":"Fuel Oil & Lpg",
            "type":"Services"
        }
    ],
    "sg:phone":"+44 1659 74321",
    "sg:postcode":"ML12 6YE",
    "sg:province":"Dumfries and Galloway",
    "wof:name":"R M Weir",
    "wof:placetype":"venue"
},
  "geometry": {"coordinates":[-3.761161,55.421017],"type":"Point"}
}