{
  "type": "Feature",
  "properties": {
    "addr:full":"25 Manor Road, Hatfield Doncaster South Yorkshire DN7 6SA",
    "addr:housenumber":"25",
    "addr:postcode":"dn7 6sa",
    "addr:street":"Manor Road",
    "iso:country":"GB",
    "sg:address":"25 Manor Road, Hatfield",
    "sg:city":"Doncaster",
    "sg:classifiers":[
        {
            "category":"Autos & Motor Vehicles",
            "subcategory":"Fuel & Gas Station",
            "type":"Retail Goods"
        }
    ],
    "sg:phone":"+44 1302 840274",
    "sg:postcode":"DN7 6SA",
    "sg:province":"South Yorkshire",
    "sg:tags":[
        "petrol",
        "filling"
    ],
    "wof:name":"Manor Road Filling Station",
    "wof:placetype":"venue"
},
  "geometry": {"coordinates":[-0.9983450174,53.5780181885],"type":"Point"}
}