{
  "type": "Feature",
  "properties": {
    "addr:full":"140a Whiteladies Road, Clifton Bristol City of Bristol BS8 2RU",
    "addr:housenumber":"140a",
    "addr:postcode":"bs8 2ru",
    "addr:street":"Whiteladies Road",
    "iso:country":"GB",
    "sg:address":"140a Whiteladies Road, Clifton",
    "sg:city":"Bristol",
    "sg:classifiers":[
        {
            "category":"Shopping",
            "subcategory":"Department Store",
            "type":"Retail Goods"
        }
    ],
    "sg:phone":"+44 117 973 5552",
    "sg:postcode":"BS8 2RU",
    "sg:province":"City of Bristol",
    "wof:name":"Woolworths Plc",
    "wof:placetype":"venue"
},
  "geometry": {"coordinates":[-2.614166975,51.4691467285],"type":"Point"}
}