{
  "type": "Feature",
  "properties": {
    "iso:country":"GB",
    "sg:address":"54 Halifax Rd, Brierfield",
    "sg:city":"Nelson",
    "sg:classifiers":[
        {
            "category":"Shopping",
            "subcategory":"Shoes",
            "type":"Retail Goods"
        }
    ],
    "sg:postcode":"BB9 5BB",
    "sg:province":"Lancashire",
    "wof:name":"Birro's",
    "wof:placetype":"venue"
},
  "geometry": {"coordinates":[-2.2313940525,53.8239021301],"type":"Point"}
}