{
  "type": "Feature",
  "properties": {
    "addr:full":"24b Union Road Ryde Isle of Wight PO33 2ER",
    "addr:housenumber":"24b",
    "addr:postcode":"po33 2er",
    "addr:street":"Union Road",
    "iso:country":"GB",
    "sg:address":"24b Union Road",
    "sg:city":"Ryde",
    "sg:classifiers":[
        {
            "category":"Personal",
            "subcategory":"Psychics & Astrologers",
            "type":"Services"
        }
    ],
    "sg:postcode":"PO33 2ER",
    "sg:province":"Isle of Wight",
    "sg:tags":[
        "clairvoyant",
        "palmist"
    ],
    "wof:name":"Fortunes",
    "wof:placetype":"venue"
},
  "geometry": {"coordinates":[-1.161384,50.731205],"type":"Point"}
}