{
  "type": "Feature",
  "properties": {
    "addr:full":"3c Normandy Street Alton Hampshire GU34 1DD",
    "addr:housenumber":"3c",
    "addr:postcode":"gu34 1dd",
    "addr:street":"Normandy Street",
    "iso:country":"GB",
    "sg:address":"3c Normandy Street",
    "sg:city":"Alton",
    "sg:classifiers":[
        {
            "category":"Shopping",
            "subcategory":"Books",
            "type":"Retail Goods"
        }
    ],
    "sg:phone":"+44 1420 87801",
    "sg:postcode":"GU34 1DD",
    "sg:province":"Hampshire",
    "sg:tags":[
        "bookseller"
    ],
    "wof:name":"Little Green Dragon Book & Art Materials Shop",
    "wof:placetype":"venue"
},
  "geometry": {"coordinates":[-0.9732149839,51.1502304077],"type":"Point"}
}