{
  "type": "Feature",
  "properties": {
    "addr:full":"Sefton Ho, Junction La Ormskirk Lancashire L40 5SW",
    "addr:postcode":"l40 5sw",
    "addr:street":"Junction La Ormskirk",
    "iso:country":"GB",
    "sg:address":"Sefton Ho, Junction La",
    "sg:city":"Ormskirk",
    "sg:classifiers":[
        {
            "category":"Health Services",
            "subcategory":"Hospital",
            "type":"Services"
        }
    ],
    "sg:phone":"+44 1772 865965",
    "sg:postcode":"L40 5SW",
    "sg:province":"Lancashire",
    "sg:tags":[
        "ambulance"
    ],
    "wof:name":"Lancashire Ambulance Service",
    "wof:placetype":"venue"
},
  "geometry": {"coordinates":[-2.83926,53.596329],"type":"Point"}
}