{
  "type": "Feature",
  "properties": {
    "addr:full":"69 Maidstone Rd Rochester Kent ME1 1RL",
    "addr:housenumber":"69",
    "addr:postcode":"me1 1rl",
    "addr:street":"Maidstone Rd",
    "iso:country":"GB",
    "sg:address":"69 Maidstone Rd",
    "sg:city":"Rochester",
    "sg:classifiers":[
        {
            "category":"Restaurant",
            "type":"Food & Drink"
        }
    ],
    "sg:phone":"+44 1634 409930",
    "sg:postcode":"ME1 1RL",
    "sg:province":"Kent",
    "wof:name":"Harringtons Restaurant",
    "wof:placetype":"venue"
},
  "geometry": {"coordinates":[0.5038239956,51.3847160339],"type":"Point"}
}