{
  "type": "Feature",
  "properties": {
    "addr:full":"Maclaren House, Talbot Rd, Stretford Manchester Cheshire M32 0FP",
    "addr:postcode":"m32 0fp",
    "addr:street":"Talbot Rd",
    "iso:country":"GB",
    "sg:address":"Maclaren House, Talbot Rd, Stretford",
    "sg:city":"Manchester",
    "sg:classifiers":[
        {
            "category":"Building & Trades",
            "subcategory":"Construction",
            "type":"Services"
        }
    ],
    "sg:phone":"+44 161 610 8888",
    "sg:postcode":"M32 0FP",
    "sg:province":"Cheshire",
    "sg:tags":[
        "contractor"
    ],
    "wof:name":"Matthew Hall",
    "wof:placetype":"venue"
},
  "geometry": {"coordinates":[-2.292059,53.45594],"type":"Point"}
}