{
  "type": "Feature",
  "properties": {
    "iso:country":"GB",
    "sg:address":"Prentis Quay, Gas Road",
    "sg:city":"Sittingbourne",
    "sg:classifiers":[
        {
            "category":"Home & Garden",
            "subcategory":"Building Materials",
            "type":"Retail Goods"
        },
        {
            "category":"Building & Trades",
            "subcategory":"Electrical",
            "type":"Services"
        }
    ],
    "sg:phone":"+44 1795 470592",
    "sg:postcode":"ME10 2QD",
    "sg:province":"Kent",
    "sg:tags":[
        "equipment",
        "operating",
        "door",
        "barrier",
        "gate"
    ],
    "wof:name":"Mcnealy Brown Ltd",
    "wof:placetype":"venue"
},
  "geometry": {"coordinates":[0.7335950136,51.3463478088],"type":"Point"}
}