{
  "type": "Feature",
  "properties": {
    "iso:country":"GB",
    "sg:address":"46 Sir Georges Road",
    "sg:city":"Southampton",
    "sg:classifiers":[
        {
            "category":"Building & Trades",
            "subcategory":"Cleaning & Sanitation",
            "type":"Services"
        }
    ],
    "sg:phone":"+44 23 8022 3613",
    "sg:postcode":"SO15 3AT",
    "sg:province":"Hampshire",
    "sg:tags":[
        "contracting",
        "commercial"
    ],
    "wof:name":"ALISTAIR DONALDSON & CO",
    "wof:placetype":"venue"
},
  "geometry": {"coordinates":[-1.422508955,50.9112052917],"type":"Point"}
}