{
  "type": "Feature",
  "properties": {
    "iso:country":"GB",
    "sg:address":"55 Christchurch Road",
    "sg:city":"Ringwood",
    "sg:classifiers":[
        {
            "category":"Shopping",
            "subcategory":"Hobbies, Toys, & Games",
            "type":"Retail Goods"
        },
        {
            "category":"Professional",
            "subcategory":"Business Services",
            "type":"Services"
        }
    ],
    "sg:phone":"+44 1425 473036",
    "sg:postcode":"BH24 1DH",
    "sg:province":"Dorset",
    "sg:tags":[
        "shop",
        "import",
        "toy",
        "export",
        "agent"
    ],
    "wof:name":"Streets Prams & Toys",
    "wof:placetype":"venue"
},
  "geometry": {"coordinates":[-1.7885789871,50.8442840576],"type":"Point"}
}