{
  "type": "Feature",
  "properties": {
    "addr:full":"66 Westfield Road, Ealing London Greater London W13 9JA",
    "addr:housenumber":"66",
    "addr:postcode":"w13 9ja",
    "addr:street":"Westfield Road",
    "iso:country":"GB",
    "sg:address":"66 Westfield Road, Ealing",
    "sg:city":"London",
    "sg:classifiers":[
        {
            "category":"Personal",
            "type":"Services"
        }
    ],
    "sg:phone":"+44 20 8840 3155",
    "sg:postcode":"W13 9JA",
    "sg:province":"Greater London",
    "sg:tags":[
        "wedding"
    ],
    "wof:name":"Gillian Shaw Photographer",
    "wof:placetype":"venue"
},
  "geometry": {"coordinates":[-0.3219470084,51.5067138672],"type":"Point"}
}