{
  "type": "Feature",
  "properties": {
    "addr:full":"86 Penny Meadow Ashton-under-lyne Greater Manchester OL6 6EP",
    "addr:housenumber":"86",
    "addr:postcode":"ol6 6ep",
    "addr:street":"Penny Meadow",
    "iso:country":"GB",
    "sg:address":"86 Penny Meadow",
    "sg:city":"Ashton-under-lyne",
    "sg:classifiers":[
        {
            "category":"Communications",
            "type":"Services"
        }
    ],
    "sg:postcode":"OL6 6EP",
    "sg:province":"Greater Manchester",
    "sg:tags":[
        "telecommunication"
    ],
    "wof:name":"G Comm",
    "wof:placetype":"venue"
},
  "geometry": {"coordinates":[-2.0906391144,53.489944458],"type":"Point"}
}