{
  "type": "Feature",
  "properties": {
    "addr:full":"North Street, The Harbour Folkestone Kent CT19 6AF",
    "addr:postcode":"ct19 6af",
    "addr:street":"North Street The Harbour",
    "iso:country":"GB",
    "sg:address":"North Street, The Harbour",
    "sg:city":"Folkestone",
    "sg:classifiers":[
        {
            "category":"Sports & Exercise",
            "subcategory":"Sports Center",
            "type":"Entertainment"
        },
        {
            "category":"Arena",
            "subcategory":"Sports Club",
            "type":"Entertainment"
        }
    ],
    "sg:phone":"+44 1303 251574",
    "sg:postcode":"CT19 6AF",
    "sg:province":"Kent",
    "sg:tags":[
        "activity",
        "watersport"
    ],
    "wof:name":"Folkestone Yacht & Motor Boat Club",
    "wof:placetype":"venue"
},
  "geometry": {"coordinates":[1.1866600513,51.0810813904],"type":"Point"}
}