{
  "type": "Feature",
  "properties": {
    "iso:country":"GB",
    "sg:address":"130 Ferry Road, Hullbridge",
    "sg:city":"Hockley",
    "sg:classifiers":[
        {
            "category":"Banks & Credit Unions",
            "subcategory":"Financial Services",
            "type":"Services"
        }
    ],
    "sg:phone":"+44 1702 479790",
    "sg:postcode":"SS5 6EU",
    "sg:province":"Essex",
    "sg:tags":[
        "consultant"
    ],
    "wof:name":"Estuary Financial Management",
    "wof:placetype":"venue"
},
  "geometry": {"coordinates":[0.613475,51.623161],"type":"Point"}
}