{
  "type": "Feature",
  "properties": {
    "iso:country":"GB",
    "sg:address":"157 Mowbray Road",
    "sg:city":"Cambridge",
    "sg:classifiers":[
        {
            "category":"Travel",
            "subcategory":"Hotels & Motels",
            "type":"Entertainment"
        }
    ],
    "sg:phone":"+44 1223 244300",
    "sg:postcode":"CB1 7SP",
    "sg:province":"Cambridgeshire",
    "sg:tags":[
        "house",
        "guest"
    ],
    "wof:name":"Dykelands Guest House",
    "wof:placetype":"venue"
},
  "geometry": {"coordinates":[0.152665,52.18647],"type":"Point"}
}