{
  "type": "Feature",
  "properties": {
    "addr:full":"18 Parkland View, Yeadon Leeds West Yorkshire LS19 7DZ",
    "addr:housenumber":"18",
    "addr:postcode":"ls19 7dz",
    "addr:street":"Parkland View Yeadon Leeds West",
    "iso:country":"GB",
    "sg:address":"18 Parkland View, Yeadon",
    "sg:city":"Leeds",
    "sg:classifiers":[
        {
            "category":"Building & Trades",
            "subcategory":"Plumbing",
            "type":"Services"
        }
    ],
    "sg:postcode":"LS19 7DZ",
    "sg:province":"West Yorkshire",
    "sg:tags":[
        "central",
        "heating"
    ],
    "wof:name":"Blades,Christopher,",
    "wof:placetype":"venue"
},
  "geometry": {"coordinates":[-1.6887819767,53.8628540039],"type":"Point"}
}