{
  "type": "Feature",
  "properties": {
    "addr:full":"The Dairy, Lower Park Road Tenby Pembrokeshire SA70 7NG",
    "addr:postcode":"sa70 7ng",
    "addr:street":"Lower Park Road",
    "iso:country":"GB",
    "sg:address":"The Dairy, Lower Park Road",
    "sg:city":"Tenby",
    "sg:classifiers":[
        {
            "category":"Farming",
            "subcategory":"Dairy Farm",
            "type":"Manufacturing & Wholesale Goods"
        }
    ],
    "sg:phone":"+44 1834 842426",
    "sg:postcode":"SA70 7NG",
    "sg:province":"Pembrokeshire",
    "wof:name":"Craigs Dairy Ltd.",
    "wof:placetype":"venue"
},
  "geometry": {"coordinates":[-4.7066540718,51.6718215942],"type":"Point"}
}