{
  "type": "Feature",
  "properties": {
    "addr:full":"Rear Of 138 Birkin Ave Nottingham Nottinghamshire NG7 5GH",
    "addr:postcode":"ng7 5gh",
    "addr:street":"Birkin Ave",
    "iso:country":"GB",
    "sg:address":"Rear Of 138 Birkin Ave",
    "sg:city":"Nottingham",
    "sg:classifiers":[
        {
            "category":"Retail",
            "subcategory":"Auto Repair",
            "type":"Services"
        }
    ],
    "sg:postcode":"NG7 5GH",
    "sg:province":"Nottinghamshire",
    "sg:tags":[
        "modification",
        "garage"
    ],
    "wof:name":"McKenzie",
    "wof:placetype":"venue"
},
  "geometry": {"coordinates":[-1.1740100384,52.9659194946],"type":"Point"}
}