{
  "type": "Feature",
  "properties": {
    "iso:country":"GB",
    "sg:address":"1 Wyncroft Court, Barwick In Elmet",
    "sg:city":"Leeds",
    "sg:classifiers":[
        {
            "category":"Professional",
            "subcategory":"Detective & Security Services",
            "type":"Services"
        }
    ],
    "sg:phone":"+44 113 281 1216",
    "sg:postcode":"LS15 4PD",
    "sg:province":"West Yorkshire",
    "sg:tags":[
        "locksmith"
    ],
    "wof:name":"Lock 'N' Door Master",
    "wof:placetype":"venue"
},
  "geometry": {"coordinates":[-1.397513032,53.8274726868],"type":"Point"}
}