{
  "type": "Feature",
  "properties": {
    "addr:full":"65 Shepherds Bush Road, Hammersmith London Greater London W6 7LS",
    "addr:housenumber":"65",
    "addr:postcode":"w6 7ls",
    "addr:street":"Shepherds Bush Road",
    "iso:country":"GB",
    "sg:address":"65 Shepherds Bush Road, Hammersmith",
    "sg:city":"London",
    "sg:classifiers":[
        {
            "category":"Travel",
            "subcategory":"Hotels & Motels",
            "type":"Entertainment"
        }
    ],
    "sg:postcode":"W6 7LS",
    "sg:province":"Greater London",
    "wof:name":"Margariets Ltd.",
    "wof:placetype":"venue"
},
  "geometry": {"coordinates":[-0.222499,51.502151],"type":"Point"}
}