{
  "type": "Feature",
  "properties": {
    "addr:full":"Pasture Rd, Moreton Wirral Merseyside CH46 7TQ",
    "addr:postcode":"ch46 7tq",
    "addr:street":"Pasture Rd",
    "iso:country":"GB",
    "sg:address":"Pasture Rd, Moreton",
    "sg:city":"Wirral",
    "sg:classifiers":[
        {
            "category":"Place Of Worship",
            "type":"Public Place"
        }
    ],
    "sg:phone":"+44 151 678 6666",
    "sg:postcode":"CH46 7TQ",
    "sg:province":"Merseyside",
    "wof:name":"Moreton Methodist Church",
    "wof:placetype":"venue"
},
  "geometry": {"coordinates":[-3.111923933,53.4019355774],"type":"Point"}
}