{
  "type": "Feature",
  "properties": {
    "addr:full":"Merriments Lane, Hurst Green Etchingham East Sussex TN19 7RG",
    "addr:postcode":"tn19 7rg",
    "addr:street":"Merriments Lane",
    "iso:country":"GB",
    "sg:address":"Merriments Lane, Hurst Green",
    "sg:city":"Etchingham",
    "sg:classifiers":[
        {
            "category":"Home & Garden",
            "subcategory":"Garden Supply",
            "type":"Retail Goods"
        }
    ],
    "sg:phone":"+44 1580 860100",
    "sg:postcode":"TN19 7RG",
    "sg:province":"East Sussex",
    "sg:tags":[
        "merchant",
        "seed"
    ],
    "wof:name":"Buckhurst Farm",
    "wof:placetype":"venue"
},
  "geometry": {"coordinates":[0.4853990078,51.0273628235],"type":"Point"}
}