{
  "type": "Feature",
  "properties": {
    "iso:country":"GB",
    "sg:address":"5 Kirkgate",
    "sg:city":"Tadcaster",
    "sg:classifiers":[
        {
            "category":"Professional",
            "subcategory":"Engineering",
            "type":"Services"
        }
    ],
    "sg:phone":"+44 1937 834812",
    "sg:postcode":"LS24 9AQ",
    "sg:province":"North Yorkshire",
    "sg:tags":[
        "consulting",
        "engineer"
    ],
    "wof:name":"Peters Associates",
    "wof:placetype":"venue"
},
  "geometry": {"coordinates":[-1.261697,53.884003],"type":"Point"}
}