{
  "type": "Feature",
  "properties": {
    "addr:full":"14 Webster Clo Rotherham South Yorkshire S61 2BW",
    "addr:housenumber":"14",
    "addr:postcode":"s61 2bw",
    "addr:street":"Webster Clo",
    "iso:country":"GB",
    "sg:address":"14 Webster Clo",
    "sg:city":"Rotherham",
    "sg:classifiers":[
        {
            "category":"Shopping",
            "subcategory":"Party Supplies",
            "type":"Retail Goods"
        }
    ],
    "sg:phone":"+44 1709 516515",
    "sg:postcode":"S61 2BW",
    "sg:province":"South Yorkshire",
    "sg:tags":[
        "inflatables",
        "bouncy",
        "castle"
    ],
    "wof:name":"Anthonys Castle Hire",
    "wof:placetype":"venue"
},
  "geometry": {"coordinates":[-1.407163,53.4412],"type":"Point"}
}