{
  "type": "Feature",
  "properties": {
    "addr:full":"28 Halewood Av Newcastle Upon Tyne Tyne and Wear NE3 3RX",
    "addr:housenumber":"28",
    "addr:postcode":"ne3 3rx",
    "addr:street":"Halewood Av",
    "iso:country":"GB",
    "sg:address":"28 Halewood Av",
    "sg:city":"Newcastle Upon Tyne",
    "sg:classifiers":[
        {
            "category":"Food & Beverages",
            "subcategory":"Meat & Fish",
            "type":"Retail Goods"
        }
    ],
    "sg:phone":"+44 191 286 0104",
    "sg:postcode":"NE3 3RX",
    "sg:province":"Tyne and Wear",
    "sg:tags":[
        "butcher"
    ],
    "wof:name":"P Bird",
    "wof:placetype":"venue"
},
  "geometry": {"coordinates":[-1.6524089575,55.0060882568],"type":"Point"}
}