{
  "type": "Feature",
  "properties": {
    "addr:full":"The Moorings, Longboat Lane Stourport-on-severn Worcestershire DY13 8AE",
    "addr:postcode":"dy13 8ae",
    "addr:street":"Longboat Lane",
    "iso:country":"GB",
    "sg:address":"The Moorings, Longboat Lane",
    "sg:city":"Stourport-on-severn",
    "sg:classifiers":[
        {
            "category":"Professional",
            "type":"Services"
        }
    ],
    "sg:phone":"+44 1299 825746",
    "sg:postcode":"DY13 8AE",
    "sg:province":"Worcestershire",
    "sg:tags":[
        "caterer"
    ],
    "wof:name":"R F B Catering Hire",
    "wof:placetype":"venue"
},
  "geometry": {"coordinates":[-2.281167,52.338997],"type":"Point"}
}