{
  "type": "Feature",
  "properties": {
    "addr:full":"Narcot Lane Chalfont St Giles Buckinghamshire HP8 4DX",
    "addr:postcode":"hp8 4dx",
    "addr:street":"Narcot Lane;St Giles",
    "iso:country":"GB",
    "sg:address":"Narcot Lane",
    "sg:city":"Chalfont St Giles",
    "sg:classifiers":[
        {
            "category":"Transit Center",
            "subcategory":"Passenger",
            "type":"Transportation"
        },
        {
            "category":"Retail",
            "subcategory":"Pet Boarding",
            "type":"Services"
        }
    ],
    "sg:phone":"+44 1494 873455",
    "sg:postcode":"HP8 4DX",
    "sg:province":"Buckinghamshire",
    "sg:tags":[
        "kennel",
        "catteries"
    ],
    "wof:name":"Crossleigh Boarding Kennels & Cattery",
    "wof:placetype":"venue"
},
  "geometry": {"coordinates":[-0.580709,51.62653],"type":"Point"}
}