{
  "type": "Feature",
  "properties": {
    "iso:country":"GB",
    "sg:address":"7 Silk Street",
    "sg:city":"Leigh",
    "sg:classifiers":[
        {
            "category":"Home & Garden",
            "subcategory":"Furniture",
            "type":"Retail Goods"
        }
    ],
    "sg:phone":"+44 1942 673324",
    "sg:postcode":"WN7 1AW",
    "sg:province":"Lancashire",
    "wof:name":"Fazackerley (Leigh) Ltd.",
    "wof:placetype":"venue"
},
  "geometry": {"coordinates":[-2.516463995,53.4966583252],"type":"Point"}
}