{
  "type": "Feature",
  "properties": {
    "iso:country":"GB",
    "sg:address":"72 Park Avenue North",
    "sg:city":"Northampton",
    "sg:classifiers":[
        {
            "category":"Building & Trades",
            "subcategory":"Construction",
            "type":"Services"
        }
    ],
    "sg:phone":"+44 1604 721813",
    "sg:postcode":"NN3 2JD",
    "sg:province":"Northamptonshire",
    "sg:tags":[
        "roofing"
    ],
    "wof:name":"Abacus Roofing",
    "wof:placetype":"venue"
},
  "geometry": {"coordinates":[-0.869937,52.253029],"type":"Point"}
}