{
  "type": "Feature",
  "properties": {
    "iso:country":"GB",
    "sg:address":"James Dunn Ho, Schoolhill",
    "sg:city":"Aberdeen",
    "sg:classifiers":[
        {
            "category":"Government",
            "subcategory":"Office",
            "type":"Public Place"
        }
    ],
    "sg:phone":"+44 1224 646333",
    "sg:postcode":"AB10 1JT",
    "sg:province":"Aberdeen City",
    "sg:tags":[
        "local"
    ],
    "wof:name":"Aberdeen City Council",
    "wof:placetype":"venue"
},
  "geometry": {"coordinates":[-2.10053,57.147831],"type":"Point"}
}