{
  "type": "Feature",
  "properties": {
    "addr:full":"119b High Street London Greater London E11 2RL",
    "addr:housenumber":"119b",
    "addr:postcode":"e11 2rl",
    "addr:street":"High Street",
    "iso:country":"GB",
    "sg:address":"119b High Street",
    "sg:city":"London",
    "sg:classifiers":[
        {
            "category":"Shopping",
            "subcategory":"Shoes",
            "type":"Retail Goods"
        }
    ],
    "sg:phone":"+44 20 8518 8830",
    "sg:postcode":"E11 2RL",
    "sg:province":"Greater London",
    "sg:tags":[
        "shop"
    ],
    "wof:name":"Lello Bacio Ltd.",
    "wof:placetype":"venue"
},
  "geometry": {"coordinates":[0.0277100001,51.5766487122],"type":"Point"}
}