{
  "type": "Feature",
  "properties": {
    "iso:country":"GB",
    "sg:address":"329 High Street",
    "sg:city":"Cheltenham",
    "sg:classifiers":[
        {
            "category":"Restaurant",
            "type":"Food & Drink"
        }
    ],
    "sg:postcode":"GL50 3HS",
    "sg:province":"Gloucestershire",
    "wof:name":"Thang Long Vietnamese Restaurant",
    "wof:placetype":"venue"
},
  "geometry": {"coordinates":[-2.079927,51.903538],"type":"Point"}
}