{
  "type": "Feature",
  "properties": {
    "addr:full":"120 Lea Hall, Stechford Birmingham West Midlands B33 8JT",
    "addr:housenumber":"120",
    "addr:postcode":"b33 8jt",
    "addr:street":"Lea Hall",
    "iso:country":"GB",
    "sg:address":"120 Lea Hall, Stechford",
    "sg:city":"Birmingham",
    "sg:classifiers":[
        {
            "category":"Professional",
            "type":"Services"
        }
    ],
    "sg:postcode":"B33 8JT",
    "sg:province":"West Midlands",
    "sg:tags":[
        "entertainer"
    ],
    "wof:name":"Paul Edwards",
    "wof:placetype":"venue"
},
  "geometry": {"coordinates":[-1.8092089891,52.4822998047],"type":"Point"}
}