{
  "type": "Feature",
  "properties": {
    "addr:full":"90 Manton Road Corby Northamptonshire NN17 4JL",
    "addr:housenumber":"90",
    "addr:postcode":"nn17 4jl",
    "addr:street":"Manton Road",
    "iso:country":"GB",
    "sg:address":"90 Manton Road",
    "sg:city":"Corby",
    "sg:classifiers":[
        {
            "category":"Manufacturing",
            "subcategory":"Wood Products",
            "type":"Manufacturing & Wholesale Goods"
        }
    ],
    "sg:phone":"+44 1536 206299",
    "sg:postcode":"NN17 4JL",
    "sg:province":"Northamptonshire",
    "sg:tags":[
        "packaging",
        "crate",
        "pallets"
    ],
    "wof:name":"Watermark Packaging Ltd.",
    "wof:placetype":"venue"
},
  "geometry": {"coordinates":[-0.683709,52.505798],"type":"Point"}
}