{
  "type": "Feature",
  "properties": {
    "iso:country":"GB",
    "sg:address":"Llakceih House, Rectory Avenue",
    "sg:city":"Rochford",
    "sg:classifiers":[
        {
            "category":"Building & Trades",
            "subcategory":"Cleaning & Sanitation",
            "type":"Services"
        }
    ],
    "sg:phone":"+44 1702 541845",
    "sg:postcode":"SS4 3TB",
    "sg:province":"Essex",
    "sg:tags":[
        "commercial"
    ],
    "wof:name":"L & L Cleaning Services Ltd.",
    "wof:placetype":"venue"
},
  "geometry": {"coordinates":[0.6882,51.598373],"type":"Point"}
}