{
  "type": "Feature",
  "properties": {
    "addr:full":"1a Iliffe Street London Greater London SE17 3LJ",
    "addr:housenumber":"1a",
    "addr:postcode":"se17 3lj",
    "addr:street":"Iliffe Street",
    "iso:country":"GB",
    "sg:address":"1a Iliffe Street",
    "sg:city":"London",
    "sg:classifiers":[
        {
            "category":"Real Estate",
            "subcategory":"Architect",
            "type":"Services"
        }
    ],
    "sg:phone":"+44 20 7708 2567",
    "sg:postcode":"SE17 3LJ",
    "sg:province":"Greater London",
    "wof:name":"Cottrell & Vermeulen",
    "wof:placetype":"venue"
},
  "geometry": {"coordinates":[-0.1013249978,51.4893379211],"type":"Point"}
}