{
  "type": "Feature",
  "properties": {
    "iso:country":"GB",
    "sg:address":"Berkshire House, Thames Side",
    "sg:city":"Windsor",
    "sg:classifiers":[
        {
            "category":"Retail",
            "subcategory":"Auto Rental",
            "type":"Services"
        }
    ],
    "sg:phone":"+44 1753 840077",
    "sg:postcode":"SL4 1QN",
    "sg:province":"Berkshire",
    "sg:tags":[
        "car",
        "hire",
        "truck"
    ],
    "wof:name":"Highway Vehicle Leasing",
    "wof:placetype":"venue"
},
  "geometry": {"coordinates":[-0.606767,51.486336],"type":"Point"}
}