{
  "type": "Feature",
  "properties": {
    "addr:full":"312 Nottingham Road, Selston Nottingham Derbyshire NG16 6AD",
    "addr:housenumber":"312",
    "addr:postcode":"ng16 6ad",
    "addr:street":"Nottingham Road",
    "iso:country":"GB",
    "sg:address":"312 Nottingham Road, Selston",
    "sg:city":"Nottingham",
    "sg:classifiers":[
        {
            "category":"Professional",
            "subcategory":"Art Services",
            "type":"Services"
        }
    ],
    "sg:postcode":"NG16 6AD",
    "sg:province":"Derbyshire",
    "sg:tags":[
        "photographer"
    ],
    "wof:name":"P B Shooter",
    "wof:placetype":"venue"
},
  "geometry": {"coordinates":[-1.293069005,53.0677108765],"type":"Point"}
}