{
  "type": "Feature",
  "properties": {
    "iso:country":"GB",
    "sg:address":"Ibex House, Minories",
    "sg:city":"London",
    "sg:classifiers":[
        {
            "category":"Fast Food",
            "type":"Food & Drink"
        }
    ],
    "sg:phone":"+44 20 7702 0530",
    "sg:postcode":"EC3N 1DD",
    "sg:province":"Greater London",
    "sg:tags":[
        "away",
        "take"
    ],
    "wof:name":"Lizio",
    "wof:placetype":"venue"
},
  "geometry": {"coordinates":[-0.0755890012,51.5126419067],"type":"Point"}
}