{
  "type": "Feature",
  "properties": {
    "addr:full":"Rectory Lane, Worlingham Beccles Norfolk NR34 7RF",
    "addr:postcode":"nr34 7rf",
    "addr:street":"Rectory Lane",
    "iso:country":"GB",
    "sg:address":"Rectory Lane, Worlingham",
    "sg:city":"Beccles",
    "sg:classifiers":[
        {
            "category":"Education",
            "subcategory":"School",
            "type":"Public Place"
        },
        {
            "category":"Government",
            "subcategory":"Office",
            "type":"Public Place"
        }
    ],
    "sg:phone":"+44 1502 712375",
    "sg:postcode":"NR34 7RF",
    "sg:province":"Norfolk",
    "sg:tags":[
        "local",
        "authority"
    ],
    "wof:name":"Worlingham Primary School",
    "wof:placetype":"venue"
},
  "geometry": {"coordinates":[1.5951399803,52.4520111084],"type":"Point"}
}