{
  "type": "Feature",
  "properties": {
    "addr:full":"18 Frithville Gardens London Greater London W12 7JN",
    "addr:housenumber":"18",
    "addr:postcode":"w12 7jn",
    "addr:street":"Frithville Gardens",
    "iso:country":"GB",
    "sg:address":"18 Frithville Gardens",
    "sg:city":"London",
    "sg:classifiers":[
        {
            "category":"Health Services",
            "subcategory":"Doctor",
            "type":"Services"
        }
    ],
    "sg:phone":"+44 20 8749 0402",
    "sg:postcode":"W12 7JN",
    "sg:province":"Greater London",
    "sg:tags":[
        "practitioners"
    ],
    "wof:name":"R S Rawal",
    "wof:placetype":"venue"
},
  "geometry": {"coordinates":[-0.226787,51.506355],"type":"Point"}
}