{
  "type": "Feature",
  "properties": {
    "addr:full":"Stanton Rd Ilkeston Derbyshire DE7 5FW",
    "addr:postcode":"de7 5fw",
    "addr:street":"Stanton Rd",
    "iso:country":"GB",
    "sg:address":"Stanton Rd",
    "sg:city":"Ilkeston",
    "sg:classifiers":[
        {
            "category":"Bars & Pubs",
            "type":"Food & Drink"
        },
        {
            "category":"Community Center",
            "subcategory":"Social",
            "type":"Public Place"
        }
    ],
    "sg:phone":"+44 115 932 3139",
    "sg:postcode":"DE7 5FW",
    "sg:province":"Derbyshire",
    "sg:tags":[
        "pubs",
        "house",
        "inn",
        "activity"
    ],
    "wof:name":"Finn M'Couls",
    "wof:placetype":"venue"
},
  "geometry": {"coordinates":[-1.3071639538,52.9657936096],"type":"Point"}
}