{
  "type": "Feature",
  "properties": {
    "addr:full":"26 High Street Ross-on-wye Gloucestershire HR9 5BZ",
    "addr:housenumber":"26",
    "addr:postcode":"hr9 5bz",
    "addr:street":"High Street",
    "iso:country":"GB",
    "sg:address":"26 High Street",
    "sg:city":"Ross-on-wye",
    "sg:classifiers":[
        {
            "category":"Fast Food",
            "type":"Food & Drink"
        }
    ],
    "sg:phone":"+44 1989 562671",
    "sg:postcode":"HR9 5BZ",
    "sg:province":"Gloucestershire",
    "sg:tags":[
        "away",
        "meal",
        "outlet",
        "take"
    ],
    "wof:name":"Golden Horse",
    "wof:placetype":"venue"
},
  "geometry": {"coordinates":[-2.5838699341,51.9136505127],"type":"Point"}
}