{
  "type": "Feature",
  "properties": {
    "iso:country":"GB",
    "sg:address":"Property House, Lister Lane",
    "sg:city":"Halifax",
    "sg:classifiers":[
        {
            "category":"Real Estate",
            "subcategory":"Surveying",
            "type":"Services"
        },
        {
            "category":"Real Estate",
            "subcategory":"Real Estate Agent",
            "type":"Services"
        }
    ],
    "sg:phone":"+44 1422 364300",
    "sg:postcode":"HX1 5AS",
    "sg:province":"West Yorkshire",
    "sg:tags":[
        "surveyor",
        "valuer"
    ],
    "wof:name":"Walker Singleton (Property Management) Ltd.",
    "wof:placetype":"venue"
},
  "geometry": {"coordinates":[-1.865914,53.722511],"type":"Point"}
}