{
  "type": "Feature",
  "properties": {
    "iso:country":"GB",
    "sg:address":"St Andrew Street",
    "sg:city":"Castle Douglas",
    "sg:classifiers":[
        {
            "category":"Shopping",
            "subcategory":"Used Merchandise",
            "type":"Retail Goods"
        }
    ],
    "sg:postcode":"DG7 1EN",
    "sg:province":"Dumfries and Galloway",
    "sg:tags":[
        "furniture"
    ],
    "wof:name":"Hazels",
    "wof:placetype":"venue"
},
  "geometry": {"coordinates":[-3.931359,54.938782],"type":"Point"}
}