{
  "type": "Feature",
  "properties": {
    "iso:country":"GB",
    "sg:address":"Chester Road Garage, Greenbank",
    "sg:city":"Northwich",
    "sg:classifiers":[
        {
            "category":"Shopping",
            "type":"Retail Goods"
        }
    ],
    "sg:postcode":"CW8 4AL",
    "sg:province":"Cheshire",
    "sg:tags":[
        "part",
        "accessory"
    ],
    "wof:name":"Sexton Bros (Motors) Ltd",
    "wof:placetype":"venue"
},
  "geometry": {"coordinates":[-2.527964,53.254902],"type":"Point"}
}