{
  "type": "Feature",
  "properties": {
    "addr:full":"Eaton House, Stoke Prior Lane Leominster Herefordshire HR6 0NA",
    "addr:postcode":"lane;hr6 0na",
    "addr:street":"Stoke Prior",
    "iso:country":"GB",
    "sg:address":"Eaton House, Stoke Prior Lane",
    "sg:city":"Leominster",
    "sg:classifiers":[
        {
            "category":"Professional",
            "subcategory":"Accounting & Tax Preparation",
            "type":"Services"
        }
    ],
    "sg:phone":"+44 1568 615638",
    "sg:postcode":"HR6 0NA",
    "sg:province":"Herefordshire",
    "sg:tags":[
        "accountant",
        "activity"
    ],
    "sg:website":"http://www.lloydrichards.com",
    "wof:name":"Lloyd Richards Ltd.",
    "wof:placetype":"venue"
},
  "geometry": {"coordinates":[-2.7021501064,52.206161499],"type":"Point"}
}