{
  "type": "Feature",
  "properties": {
    "addr:full":"69 St Mary St Southampton Hampshire SO14 1NW",
    "addr:housenumber":"69",
    "addr:postcode":"so14 1nw",
    "addr:street":"St Mary St",
    "iso:country":"GB",
    "sg:address":"69 St Mary St",
    "sg:city":"Southampton",
    "sg:classifiers":[
        {
            "category":"Shopping",
            "subcategory":"Used Merchandise",
            "type":"Retail Goods"
        }
    ],
    "sg:phone":"+44 23 8090 0013",
    "sg:postcode":"SO14 1NW",
    "sg:province":"Hampshire",
    "sg:tags":[
        "shop",
        "second-hand"
    ],
    "wof:name":"Ace Appliances",
    "wof:placetype":"venue"
},
  "geometry": {"coordinates":[-1.3967590332,50.905708313],"type":"Point"}
}