{
  "type": "Feature",
  "properties": {
    "addr:full":"94 Whitechapel Rd Whitechapel Greater London E1 1JQ",
    "addr:housenumber":"94",
    "addr:postcode":"e1 1jq",
    "addr:street":"Whitechapel Rd",
    "iso:country":"GB",
    "sg:address":"94 Whitechapel Rd",
    "sg:city":"Whitechapel",
    "sg:classifiers":[
        {
            "category":"Banks & Credit Unions",
            "subcategory":"Bureau De Change",
            "type":"Services"
        }
    ],
    "sg:phone":"+44 20 7392 2153",
    "sg:postcode":"E1 1JQ",
    "sg:province":"Greater London",
    "wof:name":"YAAH",
    "wof:placetype":"venue"
},
  "geometry": {"coordinates":[-0.065188,51.517708],"type":"Point"}
}