{
  "type": "Feature",
  "properties": {
    "iso:country":"GB",
    "sg:address":"Survey House, Brockley Rise",
    "sg:city":"London",
    "sg:classifiers":[
        {
            "category":"Real Estate",
            "subcategory":"Real Estate Operator",
            "type":"Services"
        }
    ],
    "sg:phone":"+44 20 8690 2242",
    "sg:postcode":"SE23 1LL",
    "sg:province":"Greater London",
    "sg:tags":[
        "letting",
        "agent"
    ],
    "wof:name":"Burnet Ware & Graves",
    "wof:placetype":"venue"
},
  "geometry": {"coordinates":[-0.038927,51.4512557983],"type":"Point"}
}