{
  "type": "Feature",
  "properties": {
    "iso:country":"GB",
    "sg:address":"131 North End",
    "sg:city":"Croydon",
    "sg:classifiers":[
        {
            "category":"Shopping",
            "subcategory":"Shoes",
            "type":"Retail Goods"
        }
    ],
    "sg:phone":"+44 20 8760 9919",
    "sg:postcode":"CR0 1TL",
    "sg:province":"Surrey",
    "sg:tags":[
        "shop"
    ],
    "wof:name":"Sole Trader",
    "wof:placetype":"venue"
},
  "geometry": {"coordinates":[-0.1022170037,51.3769721985],"type":"Point"}
}