{
  "type": "Feature",
  "properties": {
    "addr:full":"Barrow Rd, Business Park, Barrow Rd, Sileby Loughborough Leicestershire LE12 7LR",
    "addr:postcode":"le12 7lr",
    "addr:street":"Barrow Rd Business Park Barrow Rd",
    "iso:country":"GB",
    "sg:address":"Barrow Rd, Business Park, Barrow Rd, Sileby",
    "sg:city":"Loughborough",
    "sg:classifiers":[
        {
            "category":"Professional",
            "subcategory":"Accounting & Tax Preparation",
            "type":"Services"
        }
    ],
    "sg:phone":"+44 1509 813936",
    "sg:postcode":"LE12 7LR",
    "sg:province":"Leicestershire",
    "sg:tags":[
        "accountant"
    ],
    "wof:name":"R Pathak & Co",
    "wof:placetype":"venue"
},
  "geometry": {"coordinates":[-1.118487,52.738361],"type":"Point"}
}