{
  "type": "Feature",
  "properties": {
    "iso:country":"GB",
    "sg:address":"Foxbury House, 1 Foxbury Road",
    "sg:city":"Bromley",
    "sg:classifiers":[
        {
            "category":"Manufacturing",
            "subcategory":"Tools & Machinery",
            "type":"Manufacturing & Wholesale Goods"
        }
    ],
    "sg:phone":"+44 20 8313 3411",
    "sg:postcode":"BR1 4DG",
    "sg:province":"Kent",
    "sg:tags":[
        "society",
        "friendly"
    ],
    "wof:name":"International Passenger Protection Ltd.",
    "wof:placetype":"venue"
},
  "geometry": {"coordinates":[0.019185,51.41563],"type":"Point"}
}