{
  "type": "Feature",
  "properties": {
    "addr:full":"77 Hullbridge Road, South Woodham Ferrers Chelmsford Essex CM3 5LJ",
    "addr:housenumber":"77",
    "addr:postcode":"cm3 5lj",
    "addr:street":"Hullbridge Road",
    "iso:country":"GB",
    "sg:address":"77 Hullbridge Road, South Woodham Ferrers",
    "sg:city":"Chelmsford",
    "sg:classifiers":[
        {
            "category":"Personal",
            "subcategory":"Beauty Salon",
            "type":"Services"
        }
    ],
    "sg:phone":"+44 1245 327145",
    "sg:postcode":"CM3 5LJ",
    "sg:province":"Essex",
    "sg:tags":[
        "unisex",
        "hairdresser"
    ],
    "wof:name":"Amici Salon",
    "wof:placetype":"venue"
},
  "geometry": {"coordinates":[0.609612,51.648209],"type":"Point"}
}