{
  "type": "Feature",
  "properties": {
    "iso:country":"GB",
    "sg:address":"3 John St",
    "sg:city":"Stockport",
    "sg:classifiers":[
        {
            "category":"Building & Trades",
            "subcategory":"Construction",
            "type":"Services"
        }
    ],
    "sg:phone":"+44 161 427 5268",
    "sg:postcode":"SK6 6BR",
    "sg:province":"Cheshire",
    "sg:tags":[
        "roofing"
    ],
    "wof:name":"Classic Roofing",
    "wof:placetype":"venue"
},
  "geometry": {"coordinates":[-2.0608730316,53.3929748535],"type":"Point"}
}