{
  "type": "Feature",
  "properties": {
    "iso:country":"GB",
    "sg:address":"Stanley Gro, Penwortham",
    "sg:city":"Preston",
    "sg:classifiers":[
        {
            "category":"Education",
            "subcategory":"School",
            "type":"Public Place"
        }
    ],
    "sg:phone":"+44 1772 742331",
    "sg:postcode":"PR1 0JH",
    "sg:province":"Lancashire",
    "sg:tags":[
        "local",
        "authority"
    ],
    "wof:name":"St Teresas R C Primary School",
    "wof:placetype":"venue"
},
  "geometry": {"coordinates":[-2.738781929,53.7480964661],"type":"Point"}
}