{
  "type": "Feature",
  "properties": {
    "addr:full":"Bridge Street Avoch Highland IV9 8PP",
    "addr:postcode":"iv9 8pp",
    "addr:street":"Bridge Street",
    "iso:country":"GB",
    "sg:address":"Bridge Street",
    "sg:city":"Avoch",
    "sg:classifiers":[
        {
            "category":"Bars & Pubs",
            "type":"Food & Drink"
        },
        {
            "category":"Community Center",
            "subcategory":"Social",
            "type":"Public Place"
        }
    ],
    "sg:phone":"+44 1381 620246",
    "sg:postcode":"IV9 8PP",
    "sg:province":"Highland",
    "sg:tags":[
        "pubs",
        "house",
        "inn",
        "activity"
    ],
    "wof:name":"Station Hotel",
    "wof:placetype":"venue"
},
  "geometry": {"coordinates":[-4.1726388931,57.5673599243],"type":"Point"}
}