{
  "type": "Feature",
  "properties": {
    "addr:full":"Angel Place, 187 Fore Street, Edmonton London Greater London N18 2UD",
    "addr:housenumber":"187",
    "addr:postcode":"n18 2ud",
    "addr:street":"Angel;Fore Street",
    "iso:country":"GB",
    "sg:address":"Angel Place, 187 Fore Street, Edmonton",
    "sg:city":"London",
    "sg:classifiers":[
        {
            "category":"Professional",
            "subcategory":"Advertising",
            "type":"Services"
        }
    ],
    "sg:phone":"+44 20 8803 2425",
    "sg:postcode":"N18 2UD",
    "sg:province":"Greater London",
    "sg:tags":[
        "agency"
    ],
    "wof:name":"Ward Lester Display Co. Ltd.",
    "wof:placetype":"venue"
},
  "geometry": {"coordinates":[-0.06442,51.61517],"type":"Point"}
}