{
  "type": "Feature",
  "properties": {
    "addr:full":"Time House 22, The Arcade Okehampton Devon EX20 1EX",
    "addr:housenumber":"22",
    "addr:postcode":"ex20 1ex",
    "addr:street":"The Arcade",
    "iso:country":"GB",
    "sg:address":"Time House 22, The Arcade",
    "sg:city":"Okehampton",
    "sg:classifiers":[
        {
            "category":"Shopping",
            "subcategory":"Jewelry",
            "type":"Retail Goods"
        },
        {
            "category":"Shopping",
            "subcategory":"Comic Books",
            "type":"Retail Goods"
        }
    ],
    "sg:phone":"+44 1837 52700",
    "sg:postcode":"EX20 1EX",
    "sg:province":"Devon",
    "sg:tags":[
        "jeweller",
        "sale",
        "jewellery"
    ],
    "wof:name":"BRYAN B WILLIAMSON",
    "wof:placetype":"venue"
},
  "geometry": {"coordinates":[-4.002209,50.738632],"type":"Point"}
}