{
  "type": "Feature",
  "properties": {
    "addr:full":"Reed Healthcare Publishing, Quadrant House, The Quadrant Sutton Surrey SM2 5AS",
    "addr:postcode":"sm2 5as",
    "addr:street":"The Quadrant",
    "iso:country":"GB",
    "sg:address":"Reed Healthcare Publishing, Quadrant House, The Quadrant",
    "sg:city":"Sutton",
    "sg:classifiers":[
        {
            "category":"Communications",
            "subcategory":"Newspaper",
            "type":"Services"
        }
    ],
    "sg:phone":"+44 20 8652 8879",
    "sg:postcode":"SM2 5AS",
    "sg:province":"Surrey",
    "sg:tags":[
        "magazine"
    ],
    "wof:name":"Practice Nurse",
    "wof:placetype":"venue"
},
  "geometry": {"coordinates":[-0.1895350069,51.3592796326],"type":"Point"}
}