{
  "type": "Feature",
  "properties": {
    "addr:full":"21 High Street Heckmondwike West Yorkshire WF16 0JA",
    "addr:housenumber":"21",
    "addr:postcode":"wf16 0ja",
    "addr:street":"High Street",
    "iso:country":"GB",
    "sg:address":"21 High Street",
    "sg:city":"Heckmondwike",
    "sg:classifiers":[
        {
            "category":"Home & Garden",
            "subcategory":"Household Appliances",
            "type":"Retail Goods"
        }
    ],
    "sg:phone":"+44 1924 402975",
    "sg:postcode":"WF16 0JA",
    "sg:province":"West Yorkshire",
    "sg:tags":[
        "repairs",
        "electrical",
        "domestic",
        "servicing"
    ],
    "wof:name":"H & J Electrical",
    "wof:placetype":"venue"
},
  "geometry": {"coordinates":[-1.670921,53.707748],"type":"Point"}
}