{
  "type": "Feature",
  "properties": {
    "iso:country":"GB",
    "sg:address":"20 Cleveland Square",
    "sg:city":"Middlesbrough",
    "sg:classifiers":[
        {
            "category":"Health Services",
            "subcategory":"Doctor",
            "type":"Services"
        }
    ],
    "sg:phone":"+44 1642 242746",
    "sg:postcode":"TS1 2NX",
    "sg:province":"North Yorkshire",
    "sg:tags":[
        "practitioners"
    ],
    "wof:name":"Muddappa McAnulty & Lau",
    "wof:placetype":"venue"
},
  "geometry": {"coordinates":[-1.234949,54.574791],"type":"Point"}
}