{
  "type": "Feature",
  "properties": {
    "iso:country":"GB",
    "sg:address":"30 Manchester Rd",
    "sg:city":"Burnley",
    "sg:classifiers":[
        {
            "category":"Shopping",
            "subcategory":"Optician",
            "type":"Retail Goods"
        }
    ],
    "sg:phone":"+44 1282 433636",
    "sg:postcode":"BB11 1HH",
    "sg:province":"Lancashire",
    "wof:name":"Neil Bye",
    "wof:placetype":"venue"
},
  "geometry": {"coordinates":[-2.243347,53.788239],"type":"Point"}
}