{
  "type": "Feature",
  "properties": {
    "iso:country":"GB",
    "sg:address":"Ezenridge Farm, Bere Alston",
    "sg:city":"Yelverton",
    "sg:classifiers":[
        {
            "category":"Farming",
            "subcategory":"Livestock Farm",
            "type":"Manufacturing & Wholesale Goods"
        }
    ],
    "sg:phone":"+44 1822 840420",
    "sg:postcode":"PL20 7ET",
    "sg:province":"Devon",
    "sg:tags":[
        "others"
    ],
    "wof:name":"John F Horn",
    "wof:placetype":"venue"
},
  "geometry": {"coordinates":[-4.189649,50.480156],"type":"Point"}
}