{
  "type": "Feature",
  "properties": {
    "addr:full":"8 Brentfield Road Dartford Kent DA1 1YJ",
    "addr:housenumber":"8",
    "addr:postcode":"da1 1yj",
    "addr:street":"Brentfield Road",
    "iso:country":"GB",
    "sg:address":"8 Brentfield Road",
    "sg:city":"Dartford",
    "sg:classifiers":[
        {
            "category":"Utilities",
            "subcategory":"Telephone",
            "type":"Services"
        },
        {
            "category":"Communications",
            "type":"Services"
        }
    ],
    "sg:phone":"+44 1322 275346",
    "sg:postcode":"DA1 1YJ",
    "sg:province":"Kent",
    "sg:tags":[
        "telecom",
        "telecommunication"
    ],
    "wof:name":"P K Communication Services Ltd.",
    "wof:placetype":"venue"
},
  "geometry": {"coordinates":[0.2366160005,51.4426612854],"type":"Point"}
}