{
  "type": "Feature",
  "properties": {
    "addr:full":"52 Thames Avenue Guisborough North Yorkshire TS14 8AF",
    "addr:housenumber":"52",
    "addr:postcode":"ts14 8af",
    "addr:street":"Thames Avenue",
    "iso:country":"GB",
    "sg:address":"52 Thames Avenue",
    "sg:city":"Guisborough",
    "sg:classifiers":[
        {
            "category":"Building & Trades",
            "subcategory":"Plumbing",
            "type":"Services"
        }
    ],
    "sg:postcode":"TS14 8AF",
    "sg:province":"North Yorkshire",
    "sg:tags":[
        "heating"
    ],
    "wof:name":"Guisborough Plumbing & Heating",
    "wof:placetype":"venue"
},
  "geometry": {"coordinates":[-1.0697749853,54.5301361084],"type":"Point"}
}