{
  "type": "Feature",
  "properties": {
    "addr:full":"74 Maltings Place Fulham Greater London SW6 2BY",
    "addr:housenumber":"74",
    "addr:postcode":"sw6 2by",
    "addr:street":"Maltings Place",
    "iso:country":"GB",
    "sg:address":"74 Maltings Place",
    "sg:city":"Fulham",
    "sg:classifiers":[
        {
            "category":"Shopping",
            "type":"Retail Goods"
        }
    ],
    "sg:phone":"+44 20 7384 3800",
    "sg:postcode":"SW6 2BY",
    "sg:province":"Greater London",
    "sg:tags":[
        "part",
        "accessory"
    ],
    "wof:name":"Stirling Finish International",
    "wof:placetype":"venue"
},
  "geometry": {"coordinates":[-0.1882639974,51.4747505188],"type":"Point"}
}