{
  "type": "Feature",
  "properties": {
    "iso:country":"GB",
    "sg:address":"Eldon Way",
    "sg:city":"Newcastle-upon-tyne",
    "sg:classifiers":[
        {
            "category":"Professional",
            "subcategory":"Computer Services",
            "type":"Services"
        }
    ],
    "sg:postcode":"NE1 7XS",
    "sg:province":"Tyne and Wear",
    "sg:tags":[
        "system",
        "software"
    ],
    "wof:name":"Computer Forum Ltd.",
    "wof:placetype":"venue"
},
  "geometry": {"coordinates":[-1.6142170429,54.9744262695],"type":"Point"}
}