{
  "type": "Feature",
  "properties": {
    "iso:country":"GB",
    "sg:address":"13 Bank Place, Pill",
    "sg:city":"Bristol",
    "sg:classifiers":[
        {
            "category":"Bars & Pubs",
            "type":"Food & Drink"
        }
    ],
    "sg:phone":"+44 1275 374926",
    "sg:postcode":"BS20 0AQ",
    "sg:province":"Somerset",
    "sg:tags":[
        "pubs",
        "inn"
    ],
    "wof:name":"Star Inn",
    "wof:placetype":"venue"
},
  "geometry": {"coordinates":[-2.6851,51.479786],"type":"Point"}
}