{
  "type": "Feature",
  "properties": {
    "addr:full":"Chartwell House, Pinfold Road Bourne Lincolnshire PE10 9HT",
    "addr:postcode":"pe10 9ht",
    "addr:street":"Pinfold Road",
    "iso:country":"GB",
    "sg:address":"Chartwell House, Pinfold Road",
    "sg:city":"Bourne",
    "sg:classifiers":[
        {
            "category":"Building & Trades",
            "subcategory":"Construction",
            "type":"Services"
        }
    ],
    "sg:phone":"+44 1778 426969",
    "sg:postcode":"PE10 9HT",
    "sg:province":"Lincolnshire",
    "sg:tags":[
        "roofing"
    ],
    "wof:name":"The General Roofing Co. Ltd.",
    "wof:placetype":"venue"
},
  "geometry": {"coordinates":[-0.3622669876,52.7694396973],"type":"Point"}
}