{
  "type": "Feature",
  "properties": {
    "addr:full":"Stort House, River Way Harlow Essex CM20 2DW",
    "addr:postcode":"cm20 2dw",
    "addr:street":"River Way",
    "iso:country":"GB",
    "sg:address":"Stort House, River Way",
    "sg:city":"Harlow",
    "sg:classifiers":[
        {
            "category":"Retail",
            "subcategory":"Auto Rental",
            "type":"Services"
        }
    ],
    "sg:phone":"+44 1279 641040",
    "sg:postcode":"CM20 2DW",
    "sg:province":"Essex",
    "sg:tags":[
        "car"
    ],
    "wof:name":"P C H International Ltd.",
    "wof:placetype":"venue"
},
  "geometry": {"coordinates":[0.128907,51.793797],"type":"Point"}
}