{
  "type": "Feature",
  "properties": {
    "addr:full":"Arco Ho, 2 Peartree La Dudley West Midlands DY2 0QU",
    "addr:housenumber":"2",
    "addr:postcode":"dy2 0qu",
    "addr:street":"Peartree La Dudley",
    "iso:country":"GB",
    "sg:address":"Arco Ho, 2 Peartree La",
    "sg:city":"Dudley",
    "sg:classifiers":[
        {
            "category":"Professional",
            "subcategory":"Business Services",
            "type":"Services"
        }
    ],
    "sg:phone":"+44 1384 211962",
    "sg:postcode":"DY2 0QU",
    "sg:province":"West Midlands",
    "sg:tags":[
        "import",
        "export",
        "agent"
    ],
    "wof:name":"Durann Ltd",
    "wof:placetype":"venue"
},
  "geometry": {"coordinates":[-2.083509,52.509521],"type":"Point"}
}