{
  "type": "Feature",
  "properties": {
    "iso:country":"GB",
    "sg:address":"Unit 1, Maritime Close, Medway City Estate",
    "sg:city":"Rochester",
    "sg:classifiers":[
        {
            "category":"Home & Garden",
            "subcategory":"Hardware",
            "type":"Retail Goods"
        }
    ],
    "sg:phone":"+44 1634 291000",
    "sg:postcode":"ME2 4AZ",
    "sg:province":"Kent",
    "sg:tags":[
        "equipment",
        "welding"
    ],
    "wof:name":"Electraweld Ltd.",
    "wof:placetype":"venue"
},
  "geometry": {"coordinates":[0.5131899714,51.4006118774],"type":"Point"}
}