{
  "type": "Feature",
  "properties": {
    "iso:country":"GB",
    "sg:address":"15a Welbeck Road",
    "sg:city":"Southport",
    "sg:classifiers":[
        {
            "category":"Building & Trades",
            "subcategory":"Plumbing",
            "type":"Services"
        },
        {
            "category":"Building & Trades",
            "subcategory":"Construction",
            "type":"Services"
        }
    ],
    "sg:phone":"+44 1704 568002",
    "sg:postcode":"PR8 4AE",
    "sg:province":"Lancashire",
    "sg:tags":[
        "central",
        "installation",
        "system",
        "servicing",
        "heating"
    ],
    "wof:name":"Richard Ferguson",
    "wof:placetype":"venue"
},
  "geometry": {"coordinates":[-3.014514,53.632408],"type":"Point"}
}