{
  "type": "Feature",
  "properties": {
    "addr:full":"1 Saville Chambers, 5 North St Newcastle-upon-tyne Tyne and Wear NE1 8DF",
    "addr:housenumber":"1;5",
    "addr:postcode":"ne1 8df",
    "addr:street":"Saville Chambers;North St",
    "iso:country":"GB",
    "sg:address":"1 Saville Chambers, 5 North St",
    "sg:city":"Newcastle-upon-tyne",
    "sg:classifiers":[
        {
            "category":"Building & Trades",
            "subcategory":"Construction",
            "type":"Services"
        }
    ],
    "sg:postcode":"NE1 8DF",
    "sg:province":"Tyne and Wear",
    "sg:tags":[
        "builder"
    ],
    "wof:name":"Memberset Ltd",
    "wof:placetype":"venue"
},
  "geometry": {"coordinates":[-1.6110960245,54.9761428833],"type":"Point"}
}