{
  "type": "Feature",
  "properties": {
    "addr:full":"The Manse, 3 Bickham Rd Plymouth Devon PL5 1SA",
    "addr:housenumber":"3",
    "addr:postcode":"pl5 1sa",
    "addr:street":"Bickham Rd",
    "iso:country":"GB",
    "sg:address":"The Manse, 3 Bickham Rd",
    "sg:city":"Plymouth",
    "sg:classifiers":[
        {
            "category":"Place Of Worship",
            "type":"Public Place"
        }
    ],
    "sg:phone":"+44 1752 361975",
    "sg:postcode":"PL5 1SA",
    "sg:province":"Devon",
    "wof:name":"St Budeaux Baptist Church",
    "wof:placetype":"venue"
},
  "geometry": {"coordinates":[-4.1856398582,50.4081687927],"type":"Point"}
}