{
  "type": "Feature",
  "properties": {
    "addr:full":"12 Park Drive Bradford West Yorkshire BD9 4DR",
    "addr:housenumber":"12",
    "addr:postcode":"bd9 4dr",
    "addr:street":"Park Drive",
    "iso:country":"GB",
    "sg:address":"12 Park Drive",
    "sg:city":"Bradford",
    "sg:classifiers":[
        {
            "category":"Travel",
            "subcategory":"Hotels & Motels",
            "type":"Entertainment"
        }
    ],
    "sg:phone":"+44 1274 480194",
    "sg:postcode":"BD9 4DR",
    "sg:province":"West Yorkshire",
    "wof:name":"PARK DRIVE HOTEL",
    "wof:placetype":"venue"
},
  "geometry": {"coordinates":[-1.7789740562,53.8170166016],"type":"Point"}
}