{
  "type": "Feature",
  "properties": {
    "addr:full":"Ord House, East Ord Berwick-upon-tweed Northumberland TD15 2NS",
    "addr:postcode":"td15 2ns",
    "addr:street":"East",
    "iso:country":"GB",
    "sg:address":"Ord House, East Ord",
    "sg:city":"Berwick-upon-tweed",
    "sg:classifiers":[
        {
            "category":"Autos & Motor Vehicles",
            "subcategory":"Auto Supplies",
            "type":"Retail Goods"
        },
        {
            "category":"Recreation",
            "subcategory":"Campground",
            "type":"Entertainment"
        }
    ],
    "sg:phone":"+44 1289 305288",
    "sg:postcode":"TD15 2NS",
    "sg:province":"Northumberland",
    "sg:tags":[
        "caravan",
        "park",
        "accessory"
    ],
    "wof:name":"G & E Marshall Caravans",
    "wof:placetype":"venue"
},
  "geometry": {"coordinates":[-1.99495399,55.7601585388],"type":"Point"}
}