{
  "type": "Feature",
  "properties": {
    "iso:country":"GB",
    "sg:address":"West St",
    "sg:city":"Market Rasen",
    "sg:classifiers":[
        {
            "category":"Bus Charters",
            "type":"Transportation"
        }
    ],
    "sg:phone":"+44 1652 678366",
    "sg:postcode":"LN7 6EL",
    "sg:province":"Lincolnshire",
    "sg:tags":[
        "hire",
        "coach"
    ],
    "wof:name":"J R Dent Coaches",
    "wof:placetype":"venue"
},
  "geometry": {"coordinates":[-0.4298810065,53.5042877197],"type":"Point"}
}