{
  "type": "Feature",
  "properties": {
    "addr:full":"Henysgoldy, Gwalchmai Holyhead Isle of Anglesey LL65 4SG",
    "addr:postcode":"ll65 4sg",
    "addr:street":"Holyhead",
    "iso:country":"GB",
    "sg:address":"Henysgoldy, Gwalchmai",
    "sg:city":"Holyhead",
    "sg:classifiers":[
        {
            "category":"Building & Trades",
            "subcategory":"Equipment Rental",
            "type":"Services"
        },
        {
            "category":"Building & Trades",
            "subcategory":"Construction",
            "type":"Services"
        }
    ],
    "sg:phone":"+44 1407 720293",
    "sg:postcode":"LL65 4SG",
    "sg:province":"Isle of Anglesey",
    "sg:tags":[
        "plant",
        "machinery"
    ],
    "wof:name":"Rowlands Plant",
    "wof:placetype":"venue"
},
  "geometry": {"coordinates":[-4.4184908867,53.2590789795],"type":"Point"}
}