{
  "type": "Feature",
  "properties": {
    "iso:country":"GB",
    "sg:address":"Cranbrook Rd, Highgate",
    "sg:city":"Cranbrook",
    "sg:classifiers":[
        {
            "category":"Home & Garden",
            "subcategory":"Furniture",
            "type":"Retail Goods"
        }
    ],
    "sg:phone":"+44 1580 752118",
    "sg:postcode":"TN18 4AS",
    "sg:province":"East Sussex",
    "wof:name":"H H Hill",
    "wof:placetype":"venue"
},
  "geometry": {"coordinates":[0.509215,51.050739],"type":"Point"}
}