{
  "type": "Feature",
  "properties": {
    "addr:full":"73 Cavendish Street Worcester Worcestershire WR5 3DX",
    "addr:housenumber":"73",
    "addr:postcode":"wr5 3dx",
    "addr:street":"Cavendish Street",
    "iso:country":"GB",
    "sg:address":"73 Cavendish Street",
    "sg:city":"Worcester",
    "sg:classifiers":[
        {
            "category":"Professional",
            "subcategory":"Art Services",
            "type":"Services"
        }
    ],
    "sg:phone":"+44 1905 359856",
    "sg:postcode":"WR5 3DX",
    "sg:province":"Worcestershire",
    "sg:tags":[
        "graphic",
        "designer"
    ],
    "wof:name":"Groupious Design",
    "wof:placetype":"venue"
},
  "geometry": {"coordinates":[-2.2163350582,52.1770019531],"type":"Point"}
}