{
  "type": "Feature",
  "properties": {
    "iso:country":"GB",
    "sg:address":"County Hall",
    "sg:city":"Northallerton",
    "sg:classifiers":[
        {
            "category":"Community Center",
            "subcategory":"Youth",
            "type":"Public Place"
        }
    ],
    "sg:phone":"+44 1609 778772",
    "sg:postcode":"DL7 8AD",
    "sg:province":"North Yorkshire",
    "sg:tags":[
        "organisation",
        "centre"
    ],
    "wof:name":"Youth Enquiry Service The",
    "wof:placetype":"venue"
},
  "geometry": {"coordinates":[-1.43916,54.333019],"type":"Point"}
}