{
  "type": "Feature",
  "properties": {
    "addr:full":"16 Lamb St Whitechapel Greater London E1 6EA",
    "addr:housenumber":"16",
    "addr:postcode":"e1 6ea",
    "addr:street":"Lamb St",
    "iso:country":"GB",
    "sg:address":"16 Lamb St",
    "sg:city":"Whitechapel",
    "sg:classifiers":[
        {
            "category":"Professional",
            "subcategory":"Management & Consulting",
            "type":"Services"
        }
    ],
    "sg:phone":"+44 20 7247 6690",
    "sg:postcode":"E1 6EA",
    "sg:province":"Greater London",
    "sg:tags":[
        "consultant",
        "business"
    ],
    "wof:name":"Aegis Risk Management Practices Ltd",
    "wof:placetype":"venue"
},
  "geometry": {"coordinates":[-0.0745960027,51.520111084],"type":"Point"}
}