{
  "type": "Feature",
  "properties": {
    "iso:country":"GB",
    "sg:address":"9 Hastings Rd",
    "sg:city":"Cranbrook",
    "sg:classifiers":[
        {
            "category":"Home & Garden",
            "subcategory":"Hardware",
            "type":"Retail Goods"
        }
    ],
    "sg:phone":"+44 1580 241179",
    "sg:postcode":"TN17 4LS",
    "sg:province":"Kent",
    "sg:tags":[
        "equipment",
        "heating"
    ],
    "wof:name":"Tour Energy Controls",
    "wof:placetype":"venue"
},
  "geometry": {"coordinates":[0.626775,51.047642],"type":"Point"}
}