{
  "type": "Feature",
  "properties": {
    "addr:full":"Falcon House, 2 Elmsway, Bollington Macclesfield Cheshire SK10 5NP",
    "addr:housenumber":"2",
    "addr:postcode":"sk10 5np",
    "addr:street":"Elmsway",
    "iso:country":"GB",
    "sg:address":"Falcon House, 2 Elmsway, Bollington",
    "sg:city":"Macclesfield",
    "sg:classifiers":[
        {
            "category":"Communications",
            "subcategory":"Film & Video Production",
            "type":"Services"
        }
    ],
    "sg:postcode":"SK10 5NP",
    "sg:province":"Cheshire",
    "sg:tags":[
        "illustrator",
        "artist"
    ],
    "wof:name":"Fine Art & Illustration Studio",
    "wof:placetype":"venue"
},
  "geometry": {"coordinates":[-2.092238903,53.2984695435],"type":"Point"}
}