{
  "type": "Feature",
  "properties": {
    "addr:full":"102 Ocean Road South Shields Tyne and Wear NE33 2JF",
    "addr:housenumber":"102",
    "addr:postcode":"ne33 2jf",
    "addr:street":"Ocean Road",
    "iso:country":"GB",
    "sg:address":"102 Ocean Road",
    "sg:city":"South Shields",
    "sg:classifiers":[
        {
            "category":"Food & Beverages",
            "subcategory":"Meat & Fish",
            "type":"Retail Goods"
        },
        {
            "category":"Food & Beverages",
            "subcategory":"Groceries & Convenience Stores",
            "type":"Retail Goods"
        }
    ],
    "sg:phone":"+44 191 454 5152",
    "sg:postcode":"NE33 2JF",
    "sg:province":"Tyne and Wear",
    "sg:tags":[
        "shop",
        "chip"
    ],
    "wof:name":"Red Hut",
    "wof:placetype":"venue"
},
  "geometry": {"coordinates":[-1.4278509617,54.9996109009],"type":"Point"}
}