{
  "type": "Feature",
  "properties": {
    "iso:country":"GB",
    "sg:address":"21 Widmore Rd",
    "sg:city":"Bromley",
    "sg:classifiers":[
        {
            "category":"Building & Trades",
            "subcategory":"Construction",
            "type":"Services"
        }
    ],
    "sg:phone":"+44 20 8466 9477",
    "sg:postcode":"BR1 1RW",
    "sg:province":"Kent",
    "sg:tags":[
        "flooring"
    ],
    "wof:name":"Fashion Floors",
    "wof:placetype":"venue"
},
  "geometry": {"coordinates":[0.0166149996,51.4062080383],"type":"Point"}
}