{
  "type": "Feature",
  "properties": {
    "iso:country":"GB",
    "sg:address":"York House",
    "sg:city":"Stourbridge",
    "sg:classifiers":[
        {
            "category":"Professional",
            "type":"Services"
        }
    ],
    "sg:phone":"+44 1384 444894",
    "sg:postcode":"DY8 4DE",
    "sg:province":"Staffordshire",
    "sg:tags":[
        "shopfitters"
    ],
    "wof:name":"Chadwick Shopfitting & Building Co. Ltd.",
    "wof:placetype":"venue"
},
  "geometry": {"coordinates":[-2.1531488895,52.4679908752],"type":"Point"}
}