{
  "type": "Feature",
  "properties": {
    "addr:full":"Unit E2 Raceview Business Centre, Hambridge Road Newbury Berkshire RG14 5SA",
    "addr:housenumber":"e2 raceview business centre",
    "addr:postcode":"rg14 5sa",
    "addr:street":"Hambridge Road",
    "iso:country":"GB",
    "sg:address":"Unit E2 Raceview Business Centre, Hambridge Road",
    "sg:city":"Newbury",
    "sg:classifiers":[
        {
            "category":"Professional",
            "subcategory":"Detective & Security Services",
            "type":"Services"
        }
    ],
    "sg:phone":"+44 1635 33144",
    "sg:postcode":"RG14 5SA",
    "sg:province":"Berkshire",
    "sg:tags":[
        "alarm",
        "burglar",
        "system"
    ],
    "wof:name":"Css Alarms Ltd.",
    "wof:placetype":"venue"
},
  "geometry": {"coordinates":[-1.3258719444,51.405872345],"type":"Point"}
}