{
  "type": "Feature",
  "properties": {
    "addr:full":"11 Seagrave Road London Greater London SW6 1RP",
    "addr:housenumber":"11",
    "addr:postcode":"sw6 1rp",
    "addr:street":"Seagrave Road",
    "iso:country":"GB",
    "sg:address":"11 Seagrave Road",
    "sg:city":"London",
    "sg:classifiers":[
        {
            "category":"Autos & Motor Vehicles",
            "subcategory":"Motorcycle Sales",
            "type":"Retail Goods"
        }
    ],
    "sg:phone":"+44 20 7385 4121",
    "sg:postcode":"SW6 1RP",
    "sg:province":"Greater London",
    "sg:tags":[
        "chauffeur",
        "driven",
        "car"
    ],
    "wof:name":"R I M Transport",
    "wof:placetype":"venue"
},
  "geometry": {"coordinates":[-0.1969989985,51.4864234924],"type":"Point"}
}