{
  "type": "Feature",
  "properties": {
    "iso:country":"GB",
    "sg:address":"3 Norton House, Mace Street",
    "sg:city":"London",
    "sg:classifiers":[
        {
            "category":"Building & Trades",
            "subcategory":"Construction",
            "type":"Services"
        }
    ],
    "sg:postcode":"E2 0ST",
    "sg:province":"Greater London",
    "sg:tags":[
        "builder"
    ],
    "wof:name":"Plotgate Ltd",
    "wof:placetype":"venue"
},
  "geometry": {"coordinates":[-0.04478,51.530289],"type":"Point"}
}