{
  "type": "Feature",
  "properties": {
    "addr:full":"105 Delph Lane, Delph Oldham Lancashire OL3 5UP",
    "addr:housenumber":"105",
    "addr:postcode":"ol3 5up",
    "addr:street":"Delph Lane",
    "iso:country":"GB",
    "sg:address":"105 Delph Lane, Delph",
    "sg:city":"Oldham",
    "sg:classifiers":[
        {
            "category":"Communications",
            "subcategory":"Film & Video Production",
            "type":"Services"
        }
    ],
    "sg:phone":"+44 1457 873752",
    "sg:postcode":"OL3 5UP",
    "sg:province":"Lancashire",
    "sg:tags":[
        "recording",
        "studio"
    ],
    "wof:name":"Smooth Operations",
    "wof:placetype":"venue"
},
  "geometry": {"coordinates":[-2.0170838833,53.5716171265],"type":"Point"}
}