{
  "type": "Feature",
  "properties": {
    "addr:full":"169 Templehill Troon South Ayrshire KA10 6BH",
    "addr:housenumber":"169",
    "addr:postcode":"ka10 6bh",
    "addr:street":"Templehill Troon",
    "iso:country":"GB",
    "sg:address":"169 Templehill",
    "sg:city":"Troon",
    "sg:classifiers":[
        {
            "category":"Bars & Pubs",
            "type":"Food & Drink"
        }
    ],
    "sg:phone":"+44 1292 312668",
    "sg:postcode":"KA10 6BH",
    "sg:province":"South Ayrshire",
    "sg:tags":[
        "pubs",
        "inn"
    ],
    "wof:name":"The Harbour Bar",
    "wof:placetype":"venue"
},
  "geometry": {"coordinates":[-4.670299,55.54417],"type":"Point"}
}