{
  "type": "Feature",
  "properties": {
    "addr:full":"Brindley Road Cannock Staffordshire WS12 4LL",
    "addr:postcode":"ws12 4ll",
    "addr:street":"Brindley Road",
    "iso:country":"GB",
    "sg:address":"Brindley Road",
    "sg:city":"Cannock",
    "sg:classifiers":[
        {
            "category":"Autos & Motor Vehicles",
            "subcategory":"Automobile Sales",
            "type":"Retail Goods"
        }
    ],
    "sg:phone":"+44 1543 424243",
    "sg:postcode":"WS12 4LL",
    "sg:province":"Staffordshire",
    "sg:tags":[
        "car"
    ],
    "wof:name":"Tower Motor Company",
    "wof:placetype":"venue"
},
  "geometry": {"coordinates":[-2.017599,52.727501],"type":"Point"}
}