{
  "type": "Feature",
  "properties": {
    "iso:country":"GB",
    "sg:address":"28 Norwich Road, Aylsham",
    "sg:city":"Norwich",
    "sg:classifiers":[
        {
            "category":"Autos & Motor Vehicles",
            "subcategory":"Automobile Sales",
            "type":"Retail Goods"
        }
    ],
    "sg:phone":"+44 1263 733116",
    "sg:postcode":"NR11 6BW",
    "sg:province":"Norfolk",
    "sg:tags":[
        "car"
    ],
    "wof:name":"Aylsham Motor Co. Ltd.",
    "wof:placetype":"venue"
},
  "geometry": {"coordinates":[1.25396,52.791622],"type":"Point"}
}