{
  "type": "Feature",
  "properties": {
    "iso:country":"GB",
    "sg:address":"25 Presley Way, Crownhill",
    "sg:city":"Milton Keynes",
    "sg:classifiers":[
        {
            "category":"Personal",
            "type":"Services"
        }
    ],
    "sg:phone":"+44 1908 262636",
    "sg:postcode":"MK8 0ES",
    "sg:province":"Buckinghamshire",
    "sg:tags":[
        "wedding"
    ],
    "wof:name":"Piccione Fashions U K Ltd.",
    "wof:placetype":"venue"
},
  "geometry": {"coordinates":[-0.798425,52.027336],"type":"Point"}
}