{
  "type": "Feature",
  "properties": {
    "iso:country":"GB",
    "sg:address":"7 Ashbrook Close",
    "sg:city":"Uttoxeter",
    "sg:classifiers":[
        {
            "category":"Bus Charters",
            "type":"Transportation"
        }
    ],
    "sg:postcode":"ST14 8UL",
    "sg:province":"Derbyshire",
    "sg:tags":[
        "hire",
        "coach"
    ],
    "wof:name":"Afton Holidays",
    "wof:placetype":"venue"
},
  "geometry": {"coordinates":[-1.865366,52.890854],"type":"Point"}
}