{
  "type": "Feature",
  "properties": {
    "addr:full":"45 The Oval Godalming Surrey GU7 3JZ",
    "addr:housenumber":"45",
    "addr:postcode":"gu7 3jz",
    "addr:street":"The Oval Godalming",
    "iso:country":"GB",
    "sg:address":"45 The Oval",
    "sg:city":"Godalming",
    "sg:classifiers":[
        {
            "category":"Shopping",
            "subcategory":"Clothing, Apparel, & Fashions",
            "type":"Retail Goods"
        }
    ],
    "sg:postcode":"GU7 3JZ",
    "sg:province":"Surrey",
    "sg:tags":[
        "clothing",
        "fabric"
    ],
    "wof:name":"N Wilson",
    "wof:placetype":"venue"
},
  "geometry": {"coordinates":[-0.602872,51.196663],"type":"Point"}
}