{
  "type": "Feature",
  "properties": {
    "addr:full":"6 Parklands Clo Kettering Northamptonshire NN14 1LG",
    "addr:housenumber":"6",
    "addr:postcode":"nn14 1lg",
    "addr:street":"Parklands Clo",
    "iso:country":"GB",
    "sg:address":"6 Parklands Clo",
    "sg:city":"Kettering",
    "sg:classifiers":[
        {
            "category":"Banks & Credit Unions",
            "subcategory":"Financial Services",
            "type":"Services"
        }
    ],
    "sg:phone":"+44 1536 710697",
    "sg:postcode":"NN14 1LG",
    "sg:province":"Northamptonshire",
    "sg:tags":[
        "adviser"
    ],
    "wof:name":"Success Planners",
    "wof:placetype":"venue"
},
  "geometry": {"coordinates":[-0.8005279899,52.397605896],"type":"Point"}
}