{
  "type": "Feature",
  "properties": {
    "addr:full":"Unit 10 Colemeadow Road, Northmoons Moat Redditch Warwickshire B98 9PB",
    "addr:housenumber":"unit 10",
    "addr:postcode":"b98 9pb",
    "addr:street":"Colemeadow Road Northmoons",
    "iso:country":"GB",
    "sg:address":"Unit 10 Colemeadow Road, Northmoons Moat",
    "sg:city":"Redditch",
    "sg:classifiers":[
        {
            "category":"Home & Garden",
            "subcategory":"Household Appliances",
            "type":"Retail Goods"
        }
    ],
    "sg:phone":"+44 1527 61034",
    "sg:postcode":"B98 9PB",
    "sg:province":"Warwickshire",
    "sg:tags":[
        "cleaner",
        "domestic",
        "vacuum"
    ],
    "wof:name":"Kirby (U K) Ltd.",
    "wof:placetype":"venue"
},
  "geometry": {"coordinates":[-1.890987,52.31472],"type":"Point"}
}