{
  "type": "Feature",
  "properties": {
    "addr:full":"13 Market Street Ellon Aberdeenshire AB41 9JD",
    "addr:housenumber":"13",
    "addr:postcode":"ab41 9jd",
    "addr:street":"Market Street",
    "iso:country":"GB",
    "sg:address":"13 Market Street",
    "sg:city":"Ellon",
    "sg:classifiers":[
        {
            "category":"Communications",
            "type":"Services"
        }
    ],
    "sg:phone":"+44 1358 722033",
    "sg:postcode":"AB41 9JD",
    "sg:province":"Aberdeenshire",
    "sg:tags":[
        "tv",
        "video",
        "radio"
    ],
    "wof:name":"Ythan Tv Service",
    "wof:placetype":"venue"
},
  "geometry": {"coordinates":[-2.0712049007,57.3645935059],"type":"Point"}
}