{
  "type": "Feature",
  "properties": {
    "addr:full":"Kilburn Terrace, Junction Rd Eastbourne East Sussex BN21 3QY",
    "addr:postcode":"bn21 3qy",
    "addr:street":"Kilburn Terrace Junction Rd",
    "iso:country":"GB",
    "sg:address":"Kilburn Terrace, Junction Rd",
    "sg:city":"Eastbourne",
    "sg:classifiers":[
        {
            "category":"Place Of Worship",
            "type":"Public Place"
        }
    ],
    "sg:phone":"+44 1323 644278",
    "sg:postcode":"BN21 3QY",
    "sg:province":"East Sussex",
    "wof:name":"Christian Outreach Centre",
    "wof:placetype":"venue"
},
  "geometry": {"coordinates":[0.2853499949,50.766910553],"type":"Point"}
}