{
  "type": "Feature",
  "properties": {
    "iso:country":"GB",
    "sg:address":"10a Bath St",
    "sg:city":"Edinburgh",
    "sg:classifiers":[
        {
            "category":"Personal",
            "subcategory":"Beauty Salon",
            "type":"Services"
        }
    ],
    "sg:postcode":"EH15 1EY",
    "sg:province":"City of Edinburgh",
    "sg:tags":[
        "unisex",
        "hairdresser"
    ],
    "wof:name":"Maison Avis",
    "wof:placetype":"venue"
},
  "geometry": {"coordinates":[-3.11369,55.953445],"type":"Point"}
}