{
  "type": "Feature",
  "properties": {
    "addr:full":"34 High Street Manchester Greater Manchester M4 1AH",
    "addr:housenumber":"34",
    "addr:postcode":"m4 1ah",
    "addr:street":"High Street",
    "iso:country":"GB",
    "sg:address":"34 High Street",
    "sg:city":"Manchester",
    "sg:classifiers":[
        {
            "category":"Professional",
            "subcategory":"Lawyer & Legal Services",
            "type":"Services"
        }
    ],
    "sg:phone":"+44 161 832 4781",
    "sg:postcode":"M4 1AH",
    "sg:province":"Greater Manchester",
    "sg:tags":[
        "solicitor"
    ],
    "wof:name":"ANTHONY HODARI & CO",
    "wof:placetype":"venue"
},
  "geometry": {"coordinates":[-2.239027,53.483124],"type":"Point"}
}