{
  "type": "Feature",
  "properties": {
    "iso:country":"GB",
    "sg:address":"59 Chartswell Road, Wigston",
    "sg:city":"Leicester",
    "sg:classifiers":[
        {
            "category":"Professional",
            "subcategory":"Computer Services",
            "type":"Services"
        }
    ],
    "sg:postcode":"LE18 2FS",
    "sg:province":"Leicestershire",
    "sg:tags":[
        "system",
        "software"
    ],
    "wof:name":"Downtown Computers Ltd.",
    "wof:placetype":"venue"
},
  "geometry": {"coordinates":[-1.1142890453,52.5829811096],"type":"Point"}
}