{
  "type": "Feature",
  "properties": {
    "iso:country":"GB",
    "sg:address":"Chessetts House, Chessetts Wood Road, Lapworth",
    "sg:city":"Solihull",
    "sg:classifiers":[
        {
            "category":"Professional",
            "subcategory":"Business Services",
            "type":"Services"
        }
    ],
    "sg:phone":"+44 1564 782534",
    "sg:postcode":"B94 6ES",
    "sg:province":"Warwickshire",
    "sg:tags":[
        "import",
        "export",
        "agent"
    ],
    "wof:name":"Amuze International Ltd.",
    "wof:placetype":"venue"
},
  "geometry": {"coordinates":[-1.733897,52.359516],"type":"Point"}
}