{
  "type": "Feature",
  "properties": {
    "iso:country":"GB",
    "sg:address":"Unit 4 Pumpfield Road",
    "sg:city":"Liverpool",
    "sg:classifiers":[
        {
            "category":"Shopping",
            "subcategory":"Computers & Home Electronics",
            "type":"Retail Goods"
        }
    ],
    "sg:phone":"+44 151 255 0946",
    "sg:postcode":"L3 6BA",
    "sg:province":"Merseyside",
    "sg:tags":[
        "hi-fi",
        "equipment",
        "mnfr"
    ],
    "wof:name":"Morgan Audio Systems Ltd.",
    "wof:placetype":"venue"
},
  "geometry": {"coordinates":[-2.9905838966,53.4151649475],"type":"Point"}
}