{
  "type": "Feature",
  "properties": {
    "addr:full":"Unit 34 20 James Road, Tyseley Birmingham West Midlands B11 2BA",
    "addr:housenumber":"unit;20",
    "addr:postcode":"b11 2ba",
    "addr:street":"James Road",
    "iso:country":"GB",
    "sg:address":"Unit 34 20 James Road, Tyseley",
    "sg:city":"Birmingham",
    "sg:classifiers":[
        {
            "category":"Professional",
            "subcategory":"Engineering",
            "type":"Services"
        }
    ],
    "sg:phone":"+44 121 706 6626",
    "sg:postcode":"B11 2BA",
    "sg:province":"West Midlands",
    "sg:tags":[
        "precision",
        "engineer"
    ],
    "wof:name":"D W R Precision Engineering Ltd.",
    "wof:placetype":"venue"
},
  "geometry": {"coordinates":[-1.839659,52.459728],"type":"Point"}
}