{
  "type": "Feature",
  "properties": {
    "addr:full":"Roundthorn Industrial Estate, Tilson Road Manchester Cheshire M23 9PH",
    "addr:housenumber":"estate",
    "addr:postcode":"m23 9ph",
    "addr:street":"Tilson Road",
    "iso:country":"GB",
    "sg:address":"Roundthorn Industrial Estate, Tilson Road",
    "sg:city":"Manchester",
    "sg:classifiers":[
        {
            "category":"Professional",
            "subcategory":"Engineering",
            "type":"Services"
        },
        {
            "category":"Wholesale",
            "subcategory":"Machinery & Supplies",
            "type":"Manufacturing & Wholesale Goods"
        }
    ],
    "sg:phone":"+44 161 253 3737",
    "sg:postcode":"M23 9PH",
    "sg:province":"Cheshire",
    "sg:tags":[
        "consulting",
        "pump",
        "engineer"
    ],
    "wof:name":"John Crane",
    "wof:placetype":"venue"
},
  "geometry": {"coordinates":[-2.2964799404,53.3892250061],"type":"Point"}
}