{
  "type": "Feature",
  "properties": {
    "addr:full":"Orchard House, 114-118 Cherry Orchard Road Croydon Surrey CR0 6BA",
    "addr:housenumber":"114-118",
    "addr:postcode":"cr0 6ba",
    "addr:street":"Cherry Orchard Road",
    "iso:country":"GB",
    "sg:address":"Orchard House, 114-118 Cherry Orchard Road",
    "sg:city":"Croydon",
    "sg:classifiers":[
        {
            "category":"Government",
            "subcategory":"Post Office",
            "type":"Public Place"
        }
    ],
    "sg:phone":"+44 20 8649 7555",
    "sg:postcode":"CR0 6BA",
    "sg:province":"Surrey",
    "sg:tags":[
        "messenger",
        "courier"
    ],
    "wof:name":"Delos Pythian Ltd.",
    "wof:placetype":"venue"
},
  "geometry": {"coordinates":[-0.089956,51.378323],"type":"Point"}
}