{
  "type": "Feature",
  "properties": {
    "addr:full":"20 Handbridge Chester Cheshire CH4 7JE",
    "addr:housenumber":"20",
    "addr:postcode":"ch4 7je",
    "iso:country":"GB",
    "sg:address":"20 Handbridge",
    "sg:city":"Chester",
    "sg:classifiers":[
        {
            "category":"Shopping",
            "subcategory":"Antiques",
            "type":"Retail Goods"
        }
    ],
    "sg:phone":"+44 1244 677088",
    "sg:postcode":"CH4 7JE",
    "sg:province":"Cheshire",
    "wof:name":"Pearl Antiques",
    "wof:placetype":"venue"
},
  "geometry": {"coordinates":[-2.8882670403,53.1846237183],"type":"Point"}
}