{
  "type": "Feature",
  "properties": {
    "iso:country":"GB",
    "sg:address":"London House, Primrose Hill",
    "sg:city":"Preston",
    "sg:classifiers":[
        {
            "category":"Banks & Credit Unions",
            "subcategory":"Financial Services",
            "type":"Services"
        }
    ],
    "sg:phone":"+44 1772 202626",
    "sg:postcode":"PR1 4BX",
    "sg:province":"Lancashire",
    "sg:tags":[
        "consultant"
    ],
    "wof:name":"Clifton Corporate Finance Ltd.",
    "wof:placetype":"venue"
},
  "geometry": {"coordinates":[-2.684374094,53.758934021],"type":"Point"}
}