{
  "type": "Feature",
  "properties": {
    "addr:full":"6 Queen Street, Pontrhydyfen Port Talbot Neath Port Talbot SA12 9TF",
    "addr:housenumber":"6",
    "addr:postcode":"sa12 9tf",
    "addr:street":"Queen Street",
    "iso:country":"GB",
    "sg:address":"6 Queen Street, Pontrhydyfen",
    "sg:city":"Port Talbot",
    "sg:classifiers":[
        {
            "category":"Shopping",
            "subcategory":"News",
            "type":"Retail Goods"
        },
        {
            "category":"Government",
            "subcategory":"Post Office",
            "type":"Public Place"
        }
    ],
    "sg:phone":"+44 1639 896213",
    "sg:postcode":"SA12 9TF",
    "sg:province":"Neath Port Talbot",
    "sg:tags":[
        "newsagent"
    ],
    "wof:name":"Pontrhydyfen Post Office",
    "wof:placetype":"venue"
},
  "geometry": {"coordinates":[-3.7466580868,51.6364250183],"type":"Point"}
}