{
  "type": "Feature",
  "properties": {
    "addr:full":"Peckforton Rd, Beeston Tarporley Cheshire CW6 9TR",
    "addr:postcode":"cw6 9tr",
    "addr:street":"Peckforton Rd",
    "iso:country":"GB",
    "sg:address":"Peckforton Rd, Beeston",
    "sg:city":"Tarporley",
    "sg:classifiers":[
        {
            "category":"Education",
            "subcategory":"Special Training",
            "type":"Public Place"
        },
        {
            "category":"Government",
            "subcategory":"Office",
            "type":"Public Place"
        }
    ],
    "sg:phone":"+44 1829 260535",
    "sg:postcode":"CW6 9TR",
    "sg:province":"Cheshire",
    "sg:tags":[
        "product",
        "local",
        "centre"
    ],
    "wof:name":"Cheshire County Council",
    "wof:placetype":"venue"
},
  "geometry": {"coordinates":[-2.6833329201,53.1227340698],"type":"Point"}
}