{
  "type": "Feature",
  "properties": {
    "iso:country":"GB",
    "sg:address":"16 Crewe St",
    "sg:city":"Chester",
    "sg:classifiers":[
        {
            "category":"Bars & Pubs",
            "type":"Food & Drink"
        }
    ],
    "sg:postcode":"CH1 3BP",
    "sg:province":"Cheshire",
    "sg:tags":[
        "pubs",
        "inn"
    ],
    "wof:name":"Marsh,S,",
    "wof:placetype":"venue"
},
  "geometry": {"coordinates":[-2.881861,53.195137],"type":"Point"}
}