{
  "type": "Feature",
  "properties": {
    "addr:full":"26 Main Avenue, Moor Park Northwood Greater London HA6 2HJ",
    "addr:housenumber":"26",
    "addr:postcode":"ha6 2hj",
    "addr:street":"Main Avenue Moor Park",
    "iso:country":"GB",
    "sg:address":"26 Main Avenue, Moor Park",
    "sg:city":"Northwood",
    "sg:classifiers":[
        {
            "category":"Personal",
            "subcategory":"Beauty Salon",
            "type":"Services"
        }
    ],
    "sg:phone":"+44 1923 823944",
    "sg:postcode":"HA6 2HJ",
    "sg:province":"Greater London",
    "sg:tags":[
        "ladies",
        "lady",
        "hairdresser"
    ],
    "wof:name":"Sally Darvill",
    "wof:placetype":"venue"
},
  "geometry": {"coordinates":[-0.434607,51.629467],"type":"Point"}
}