{
  "type": "Feature",
  "properties": {
    "addr:full":"Ruckley Ford, Foxcote Bath Somerset BA3 5YA",
    "addr:postcode":"ba3 5ya",
    "iso:country":"GB",
    "sg:address":"Ruckley Ford, Foxcote",
    "sg:city":"Bath",
    "sg:classifiers":[
        {
            "category":"Farming",
            "subcategory":"Livestock Farm",
            "type":"Manufacturing & Wholesale Goods"
        }
    ],
    "sg:postcode":"BA3 5YA",
    "sg:province":"Somerset",
    "sg:tags":[
        "others"
    ],
    "wof:name":"S Small",
    "wof:placetype":"venue"
},
  "geometry": {"coordinates":[-2.4074389935,51.2978858948],"type":"Point"}
}