{
  "type": "Feature",
  "properties": {
    "iso:country":"GB",
    "sg:address":"28 Paul Street",
    "sg:city":"London",
    "sg:classifiers":[
        {
            "category":"Restaurant",
            "type":"Food & Drink"
        }
    ],
    "sg:phone":"+44 20 7739 4729",
    "sg:postcode":"EC2A 4LB",
    "sg:province":"Greater London",
    "wof:name":"Jackies Dining Room",
    "wof:placetype":"venue"
},
  "geometry": {"coordinates":[-0.0846310034,51.5228614807],"type":"Point"}
}