{
  "type": "Feature",
  "properties": {
    "addr:full":"33 Upper Green East Mitcham Greater London CR4 2PF",
    "addr:housenumber":"33",
    "addr:postcode":"cr4 2pf",
    "addr:street":"Upper Green East",
    "iso:country":"GB",
    "sg:address":"33 Upper Green East",
    "sg:city":"Mitcham",
    "sg:classifiers":[
        {
            "category":"Professional",
            "subcategory":"Printing & Photocopies",
            "type":"Services"
        }
    ],
    "sg:postcode":"CR4 2PF",
    "sg:province":"Greater London",
    "sg:tags":[
        "printer"
    ],
    "wof:name":"B D L PRINT GROUP LTD",
    "wof:placetype":"venue"
},
  "geometry": {"coordinates":[-0.1629869938,51.4050941467],"type":"Point"}
}