{
  "type": "Feature",
  "properties": {
    "iso:country":"GB",
    "sg:address":"58 Bridgnorth Road, Wollaston",
    "sg:city":"Stourbridge",
    "sg:classifiers":[
        {
            "category":"Bars & Pubs",
            "type":"Food & Drink"
        }
    ],
    "sg:phone":"+44 1384 394330",
    "sg:postcode":"DY8 3QG",
    "sg:province":"Staffordshire",
    "sg:tags":[
        "pubs",
        "inn"
    ],
    "wof:name":"The Waterloo Inn",
    "wof:placetype":"venue"
},
  "geometry": {"coordinates":[-2.1633241177,52.4604187012],"type":"Point"}
}