{
  "type": "Feature",
  "properties": {
    "addr:full":"121 Princess Street Manchester Greater Manchester M1 7AD",
    "addr:housenumber":"121",
    "addr:postcode":"m1 7ad",
    "addr:street":"Princess Street",
    "iso:country":"GB",
    "sg:address":"121 Princess Street",
    "sg:city":"Manchester",
    "sg:classifiers":[
        {
            "category":"Professional",
            "subcategory":"Art Services",
            "type":"Services"
        }
    ],
    "sg:phone":"+44 161 236 8709",
    "sg:postcode":"M1 7AD",
    "sg:province":"Greater Manchester",
    "sg:tags":[
        "photographer"
    ],
    "wof:name":"Harris Darkrooms",
    "wof:placetype":"venue"
},
  "geometry": {"coordinates":[-2.2385001183,53.4762001038],"type":"Point"}
}