{
  "type": "Feature",
  "properties": {
    "iso:country":"GB",
    "sg:address":"22 Greendale Gro",
    "sg:city":"Manchester",
    "sg:classifiers":[
        {
            "category":"Building & Trades",
            "subcategory":"Construction",
            "type":"Services"
        }
    ],
    "sg:phone":"+44 161 320 5676",
    "sg:postcode":"M34 7EW",
    "sg:province":"Greater Manchester",
    "sg:tags":[
        "roofing"
    ],
    "wof:name":"Dawtect Roofing",
    "wof:placetype":"venue"
},
  "geometry": {"coordinates":[-2.098467,53.440315],"type":"Point"}
}