{
  "type": "Feature",
  "properties": {
    "addr:full":"Redbar Yelverton Devon PL20 6BB",
    "addr:housenumber":"yelverton",
    "addr:postcode":"pl20 6bb",
    "addr:street":"Devon",
    "iso:country":"GB",
    "sg:address":"Redbar",
    "sg:city":"Yelverton",
    "sg:classifiers":[
        {
            "category":"Professional",
            "type":"Services"
        }
    ],
    "sg:phone":"+44 1822 852346",
    "sg:postcode":"PL20 6BB",
    "sg:province":"Devon",
    "sg:tags":[
        "entertainer"
    ],
    "wof:name":"Jacolly Puppet Theatre",
    "wof:placetype":"venue"
},
  "geometry": {"coordinates":[-4.087859,50.492378],"type":"Point"}
}