{
  "type": "Feature",
  "properties": {
    "addr:full":"39 Tarnbrook Dr Blackpool Lancashire FY3 7QB",
    "addr:housenumber":"39",
    "addr:postcode":"fy3 7qb",
    "addr:street":"Tarnbrook Dr",
    "iso:country":"GB",
    "sg:address":"39 Tarnbrook Dr",
    "sg:city":"Blackpool",
    "sg:classifiers":[
        {
            "category":"Building & Trades",
            "subcategory":"Construction",
            "type":"Services"
        }
    ],
    "sg:phone":"+44 1253 301753",
    "sg:postcode":"FY3 7QB",
    "sg:province":"Lancashire",
    "sg:tags":[
        "contractor",
        "paving",
        "driveway"
    ],
    "wof:name":"Crowther Landscapes",
    "wof:placetype":"venue"
},
  "geometry": {"coordinates":[-3.0140910149,53.8280181885],"type":"Point"}
}