{
  "type": "Feature",
  "properties": {
    "addr:full":"31 Ritch Rd Snodland Kent ME6 5PU",
    "addr:housenumber":"31",
    "addr:postcode":"me6 5pu",
    "addr:street":"Ritch Rd",
    "iso:country":"GB",
    "sg:address":"31 Ritch Rd",
    "sg:city":"Snodland",
    "sg:classifiers":[
        {
            "category":"Professional",
            "subcategory":"Detective & Security Services",
            "type":"Services"
        }
    ],
    "sg:postcode":"ME6 5PU",
    "sg:province":"Kent",
    "wof:name":"Cushing,Darren,",
    "wof:placetype":"venue"
},
  "geometry": {"coordinates":[0.429268986,51.3273620605],"type":"Point"}
}