{
  "type": "Feature",
  "properties": {
    "addr:full":"Lys Mill Watlington Oxfordshire OX49 5EP",
    "addr:postcode":"ox49 5ep",
    "addr:street":"Lys",
    "iso:country":"GB",
    "sg:address":"Lys Mill",
    "sg:city":"Watlington",
    "sg:classifiers":[
        {
            "category":"Retail",
            "subcategory":"Auto Repair",
            "type":"Services"
        }
    ],
    "sg:phone":"+44 1491 613303",
    "sg:postcode":"OX49 5EP",
    "sg:province":"Oxfordshire",
    "sg:tags":[
        "modification",
        "garage"
    ],
    "wof:name":"F W 4x4 Workshops",
    "wof:placetype":"venue"
},
  "geometry": {"coordinates":[-1.005681,51.644085],"type":"Point"}
}