{
  "type": "Feature",
  "properties": {
    "addr:full":"1 Albert Road, Richmond Hill Bournemouth Dorset BH1 1BZ",
    "addr:housenumber":"1",
    "addr:postcode":"bh1 1bz",
    "addr:street":"Albert Road",
    "iso:country":"GB",
    "sg:address":"1 Albert Road, Richmond Hill",
    "sg:city":"Bournemouth",
    "sg:classifiers":[
        {
            "category":"Place Of Worship",
            "type":"Public Place"
        }
    ],
    "sg:phone":"+44 1202 551013",
    "sg:postcode":"BH1 1BZ",
    "sg:province":"Dorset",
    "wof:name":"Sacred Heart",
    "wof:placetype":"venue"
},
  "geometry": {"coordinates":[-1.876979,50.72065],"type":"Point"}
}