{
  "type": "Feature",
  "properties": {
    "addr:full":"49-55 High Street Southend-on-sea Essex SS1 1HZ",
    "addr:housenumber":"49-55",
    "addr:postcode":"ss1 1hz",
    "addr:street":"High Street",
    "iso:country":"GB",
    "sg:address":"49-55 High Street",
    "sg:city":"Southend-on-sea",
    "sg:classifiers":[
        {
            "category":"Shopping",
            "subcategory":"Books",
            "type":"Retail Goods"
        }
    ],
    "sg:phone":"+44 1702 437480",
    "sg:postcode":"SS1 1HZ",
    "sg:province":"Essex",
    "sg:tags":[
        "bookseller"
    ],
    "wof:name":"Waterstones Booksellers",
    "wof:placetype":"venue"
},
  "geometry": {"coordinates":[0.713691,51.535877],"type":"Point"}
}