{
  "type": "Feature",
  "properties": {
    "addr:full":"608a Wolseley Road Plymouth Devon PL5 1TE",
    "addr:housenumber":"608a",
    "addr:postcode":"pl5 1te",
    "addr:street":"Wolseley Road",
    "iso:country":"GB",
    "sg:address":"608a Wolseley Road",
    "sg:city":"Plymouth",
    "sg:classifiers":[
        {
            "category":"Professional",
            "subcategory":"Lawyer & Legal Services",
            "type":"Services"
        }
    ],
    "sg:postcode":"PL5 1TE",
    "sg:province":"Devon",
    "sg:tags":[
        "solicitor"
    ],
    "wof:name":"Tim Reeves",
    "wof:placetype":"venue"
},
  "geometry": {"coordinates":[-4.185363,50.401508],"type":"Point"}
}