{
  "type": "Feature",
  "properties": {
    "iso:country":"GB",
    "sg:address":"11 New St",
    "sg:city":"Grimsby",
    "sg:classifiers":[
        {
            "category":"Professional",
            "subcategory":"Lawyer & Legal Services",
            "type":"Services"
        }
    ],
    "sg:phone":"+44 1472 340001",
    "sg:postcode":"DN31 1HQ",
    "sg:province":"Lincolnshire",
    "sg:tags":[
        "advice",
        "counselling"
    ],
    "wof:name":"Alcohol Counselling Service",
    "wof:placetype":"venue"
},
  "geometry": {"coordinates":[-0.082954,53.565399],"type":"Point"}
}