{
  "type": "Feature",
  "properties": {
    "addr:full":"91 North App Watford Hertfordshire WD25 0EL",
    "addr:housenumber":"91",
    "addr:postcode":"wd25 0el",
    "addr:street":"North",
    "iso:country":"GB",
    "sg:address":"91 North App",
    "sg:city":"Watford",
    "sg:classifiers":[
        {
            "category":"Shopping",
            "subcategory":"Pharmacy",
            "type":"Retail Goods"
        }
    ],
    "sg:phone":"+44 1923 673136",
    "sg:postcode":"WD25 0EL",
    "sg:province":"Hertfordshire",
    "sg:tags":[
        "pharmacist",
        "chemist"
    ],
    "wof:name":"Chemilab Pharmacy",
    "wof:placetype":"venue"
},
  "geometry": {"coordinates":[-0.4014840126,51.6910247803],"type":"Point"}
}