{
  "type": "Feature",
  "properties": {
    "addr:full":"106 Wake Green Road Birmingham West Midlands B13 9PZ",
    "addr:housenumber":"106",
    "addr:postcode":"b13 9pz",
    "addr:street":"Wake Green Road",
    "iso:country":"GB",
    "sg:address":"106 Wake Green Road",
    "sg:city":"Birmingham",
    "sg:classifiers":[
        {
            "category":"Farming",
            "subcategory":"Nursery",
            "type":"Manufacturing & Wholesale Goods"
        },
        {
            "category":"Education",
            "subcategory":"Preschool",
            "type":"Public Place"
        }
    ],
    "sg:phone":"+44 121 449 3673",
    "sg:postcode":"B13 9PZ",
    "sg:province":"West Midlands",
    "sg:tags":[
        "school",
        "creche"
    ],
    "wof:name":"Catherine House Day Nursery",
    "wof:placetype":"venue"
},
  "geometry": {"coordinates":[-1.866929,52.441147],"type":"Point"}
}