{
  "type": "Feature",
  "properties": {
    "addr:full":"15 Fairfields, Great Kingshill High Wycombe Buckinghamshire HP15 6EP",
    "addr:housenumber":"15",
    "addr:postcode":"hp15 6ep",
    "addr:street":"Fairfields Great",
    "iso:country":"GB",
    "sg:address":"15 Fairfields, Great Kingshill",
    "sg:city":"High Wycombe",
    "sg:classifiers":[
        {
            "category":"Professional",
            "subcategory":"Engineering",
            "type":"Services"
        },
        {
            "category":"Building & Trades",
            "subcategory":"Electrical",
            "type":"Services"
        }
    ],
    "sg:phone":"+44 1494 712008",
    "sg:postcode":"HP15 6EP",
    "sg:province":"Buckinghamshire",
    "sg:tags":[
        "engineer",
        "electrician",
        "contractor"
    ],
    "wof:name":"John Percival",
    "wof:placetype":"venue"
},
  "geometry": {"coordinates":[-0.7283790112,51.6767272949],"type":"Point"}
}