{
  "type": "Feature",
  "properties": {
    "addr:full":"16 New College Pde Hampstead Greater London NW3 5EP",
    "addr:housenumber":"16",
    "addr:postcode":"nw3 5ep",
    "addr:street":"New College Pde",
    "iso:country":"GB",
    "sg:address":"16 New College Pde",
    "sg:city":"Hampstead",
    "sg:classifiers":[
        {
            "category":"Health Services",
            "subcategory":"Dentist",
            "type":"Services"
        }
    ],
    "sg:phone":"+44 20 7722 9737",
    "sg:postcode":"NW3 5EP",
    "sg:province":"Greater London",
    "wof:name":"T Lewis",
    "wof:placetype":"venue"
},
  "geometry": {"coordinates":[-0.1768530011,51.5452842712],"type":"Point"}
}