{
  "type": "Feature",
  "properties": {
    "addr:full":"26 Main St Nottingham Nottinghamshire NG14 7AG",
    "addr:housenumber":"26",
    "addr:postcode":"ng14 7ag",
    "addr:street":"Main St",
    "iso:country":"GB",
    "sg:address":"26 Main St",
    "sg:city":"Nottingham",
    "sg:classifiers":[
        {
            "category":"Fast Food",
            "type":"Food & Drink"
        }
    ],
    "sg:phone":"+44 115 966 4922",
    "sg:postcode":"NG14 7AG",
    "sg:province":"Nottinghamshire",
    "sg:tags":[
        "away",
        "take"
    ],
    "wof:name":"Neelam Balti House",
    "wof:placetype":"venue"
},
  "geometry": {"coordinates":[-0.987304,52.991596],"type":"Point"}
}