{
  "type": "Feature",
  "properties": {
    "addr:full":"36 Parade Leamington Spa Warwickshire CV32 4DN",
    "addr:housenumber":"36",
    "addr:postcode":"cv32 4dn",
    "addr:street":"Parade",
    "iso:country":"GB",
    "sg:address":"36 Parade",
    "sg:city":"Leamington Spa",
    "sg:classifiers":[
        {
            "category":"Shopping",
            "subcategory":"Baby Store",
            "type":"Retail Goods"
        }
    ],
    "sg:phone":"+44 1926 430180",
    "sg:postcode":"CV32 4DN",
    "sg:province":"Warwickshire",
    "sg:tags":[
        "babywear",
        "childrens"
    ],
    "wof:name":"Adams Childrenswear Ltd.",
    "wof:placetype":"venue"
},
  "geometry": {"coordinates":[-1.5361089706,52.2923431396],"type":"Point"}
}