{
  "type": "Feature",
  "properties": {
    "addr:full":"25 Laburnum Avenue, Atherton Manchester Greater Manchester M46 9DY",
    "addr:housenumber":"25",
    "addr:postcode":"m46 9dy",
    "addr:street":"Laburnum Avenue",
    "iso:country":"GB",
    "sg:address":"25 Laburnum Avenue, Atherton",
    "sg:city":"Manchester",
    "sg:classifiers":[
        {
            "category":"Building & Trades",
            "subcategory":"Construction",
            "type":"Services"
        }
    ],
    "sg:phone":"+44 1942 884663",
    "sg:postcode":"M46 9DY",
    "sg:province":"Greater Manchester",
    "sg:tags":[
        "builder",
        "joiner",
        "carpenter"
    ],
    "wof:name":"Bill Mercer",
    "wof:placetype":"venue"
},
  "geometry": {"coordinates":[-2.48121,53.526958],"type":"Point"}
}