{
  "type": "Feature",
  "properties": {
    "iso:country":"GB",
    "sg:address":"11a High Street",
    "sg:city":"Ledbury",
    "sg:classifiers":[
        {
            "category":"Communications",
            "subcategory":"Newspaper",
            "type":"Services"
        }
    ],
    "sg:phone":"+44 1531 633233",
    "sg:postcode":"HR8 1DS",
    "sg:province":"Gloucestershire",
    "sg:tags":[
        "magazine"
    ],
    "wof:name":"Ledbury Reporter & Malvern Gazette",
    "wof:placetype":"venue"
},
  "geometry": {"coordinates":[-2.4224040508,52.0364646912],"type":"Point"}
}