{
  "type": "Feature",
  "properties": {
    "iso:country":"GB",
    "sg:address":"19 Rhodfa Terrace, Troedyrhiw",
    "sg:city":"Merthyr Tydfil",
    "sg:classifiers":[
        {
            "category":"Utilities",
            "subcategory":"Fuel Oil & Lpg",
            "type":"Services"
        }
    ],
    "sg:phone":"+44 1443 690065",
    "sg:postcode":"CF48 4JG",
    "sg:province":"Caerphilly",
    "sg:tags":[
        "coal",
        "smokeless"
    ],
    "wof:name":"P G Fuels",
    "wof:placetype":"venue"
},
  "geometry": {"coordinates":[-3.346194,51.714531],"type":"Point"}
}