{
  "type": "Feature",
  "properties": {
    "iso:country":"GB",
    "sg:address":"70 Alton Road",
    "sg:city":"Fleet",
    "sg:classifiers":[
        {
            "category":"Building & Trades",
            "subcategory":"Plumbing",
            "type":"Services"
        }
    ],
    "sg:phone":"+44 1252 624003",
    "sg:postcode":"GU51 3HW",
    "sg:province":"Hampshire",
    "sg:tags":[
        "central",
        "heating"
    ],
    "wof:name":"B & C Plumbing & Heating",
    "wof:placetype":"venue"
},
  "geometry": {"coordinates":[-0.818978,51.277306],"type":"Point"}
}