{
  "type": "Feature",
  "properties": {
    "iso:country":"GB",
    "sg:address":"37 St Marys Rd",
    "sg:city":"Market Harborough",
    "sg:classifiers":[
        {
            "category":"Shopping",
            "subcategory":"Department Store",
            "type":"Retail Goods"
        }
    ],
    "sg:postcode":"LE16 7DS",
    "sg:province":"Leicestershire",
    "wof:name":"J R Cycles",
    "wof:placetype":"venue"
},
  "geometry": {"coordinates":[-0.9178429842,52.4781570435],"type":"Point"}
}