{
  "type": "Feature",
  "properties": {
    "iso:country":"GB",
    "sg:address":"4 High Street",
    "sg:city":"Ringwood",
    "sg:classifiers":[
        {
            "category":"Food & Beverages",
            "subcategory":"Fruits & Vegetables",
            "type":"Retail Goods"
        }
    ],
    "sg:postcode":"BH24 1AF",
    "sg:province":"Dorset",
    "sg:tags":[
        "greengrocer"
    ],
    "wof:name":"Dave Thebe",
    "wof:placetype":"venue"
},
  "geometry": {"coordinates":[-1.7913819551,50.8461456299],"type":"Point"}
}