{
  "type": "Feature",
  "properties": {
    "addr:full":"Unit 25 Marathon Pl, Moss Side Indust Est Preston Lancashire PR5 3QN",
    "addr:housenumber":"unit 25",
    "addr:postcode":"pr5 3qn",
    "addr:street":"Marathon Pl;Side Indust Est",
    "iso:country":"GB",
    "sg:address":"Unit 25 Marathon Pl, Moss Side Indust Est",
    "sg:city":"Preston",
    "sg:classifiers":[
        {
            "category":"Retail",
            "subcategory":"Veterinary Services",
            "type":"Services"
        }
    ],
    "sg:phone":"+44 1772 436777",
    "sg:postcode":"PR5 3QN",
    "sg:province":"Lancashire",
    "sg:tags":[
        "pharmacy"
    ],
    "wof:name":"C-Vet",
    "wof:placetype":"venue"
},
  "geometry": {"coordinates":[-2.6308400631,53.7457618713],"type":"Point"}
}