{
  "type": "Feature",
  "properties": {
    "addr:full":"Townfootfarm, West Woodburn Hexham Northumberland NE48 2SH",
    "addr:postcode":"ne48 2sh",
    "addr:street":"West",
    "iso:country":"GB",
    "sg:address":"Townfootfarm, West Woodburn",
    "sg:city":"Hexham",
    "sg:classifiers":[
        {
            "category":"Farming",
            "subcategory":"Livestock Farm",
            "type":"Manufacturing & Wholesale Goods"
        }
    ],
    "sg:phone":"+44 1434 270214",
    "sg:postcode":"NE48 2SH",
    "sg:province":"Northumberland",
    "sg:tags":[
        "others"
    ],
    "wof:name":"R J & J Raine",
    "wof:placetype":"venue"
},
  "geometry": {"coordinates":[-2.170279026,55.1757850647],"type":"Point"}
}