{
  "type": "Feature",
  "properties": {
    "iso:country":"GB",
    "sg:address":"Living Store, Market Sq",
    "sg:city":"Burnley",
    "sg:classifiers":[
        {
            "category":"Shopping",
            "subcategory":"Shoes",
            "type":"Retail Goods"
        }
    ],
    "sg:postcode":"BB11 1DL",
    "sg:province":"Lancashire",
    "sg:tags":[
        "shop"
    ],
    "wof:name":"B S C Stores Ltd",
    "wof:placetype":"venue"
},
  "geometry": {"coordinates":[-2.243809,53.78801],"type":"Point"}
}