{
  "type": "Feature",
  "properties": {
    "iso:country":"GB",
    "sg:address":"85 Old Rd",
    "sg:city":"Oxford",
    "sg:classifiers":[
        {
            "category":"Place Of Worship",
            "type":"Public Place"
        }
    ],
    "sg:phone":"+44 1865 762536",
    "sg:postcode":"OX3 7LB",
    "sg:province":"Oxfordshire",
    "wof:name":"Headington All Saints Vicarage",
    "wof:placetype":"venue"
},
  "geometry": {"coordinates":[-1.2203270197,51.7528610229],"type":"Point"}
}