{
  "type": "Feature",
  "properties": {
    "addr:full":"Dallingridge, Nursery Lane, Nutley Uckfield East Sussex TN22 3NS",
    "addr:postcode":"tn22 3ns",
    "addr:street":"Lane",
    "iso:country":"GB",
    "sg:address":"Dallingridge, Nursery Lane, Nutley",
    "sg:city":"Uckfield",
    "sg:classifiers":[
        {
            "category":"Professional",
            "subcategory":"Art Services",
            "type":"Services"
        }
    ],
    "sg:phone":"+44 1825 733377",
    "sg:postcode":"TN22 3NS",
    "sg:province":"East Sussex",
    "sg:tags":[
        "photographer"
    ],
    "wof:name":"Lance Dixon Photography",
    "wof:placetype":"venue"
},
  "geometry": {"coordinates":[0.0554249994,51.0315628052],"type":"Point"}
}