{
  "type": "Feature",
  "properties": {
    "addr:full":"6 Victoria Terrace, Newbridge Newport Blaenau Gwent NP11 4ET",
    "addr:housenumber":"6",
    "addr:postcode":"np11 4et",
    "addr:street":"Victoria Terrace",
    "iso:country":"GB",
    "sg:address":"6 Victoria Terrace, Newbridge",
    "sg:city":"Newport",
    "sg:classifiers":[
        {
            "category":"Food & Beverages",
            "subcategory":"Meat & Fish",
            "type":"Retail Goods"
        }
    ],
    "sg:phone":"+44 1495 243209",
    "sg:postcode":"NP11 4ET",
    "sg:province":"Blaenau Gwent",
    "sg:tags":[
        "butcher"
    ],
    "wof:name":"Jeffrey E Brown",
    "wof:placetype":"venue"
},
  "geometry": {"coordinates":[-3.144686,51.66515],"type":"Point"}
}