{
  "type": "Feature",
  "properties": {
    "iso:country":"GB",
    "sg:address":"3 Northumberland Street",
    "sg:city":"Edinburgh",
    "sg:classifiers":[
        {
            "category":"Professional",
            "subcategory":"Management & Consulting",
            "type":"Services"
        }
    ],
    "sg:phone":"+44 131 556 0101",
    "sg:postcode":"EH3 6LL",
    "sg:province":"City of Edinburgh",
    "sg:tags":[
        "consultant",
        "business"
    ],
    "wof:name":"William Roe Associates",
    "wof:placetype":"venue"
},
  "geometry": {"coordinates":[-3.1968040466,55.9573745728],"type":"Point"}
}