{
  "type": "Feature",
  "properties": {
    "iso:country":"GB",
    "sg:address":"Bishops Road",
    "sg:city":"Peterborough",
    "sg:classifiers":[
        {
            "category":"Community Center",
            "type":"Public Place"
        }
    ],
    "sg:phone":"+44 1733 452643",
    "sg:postcode":"PE1 5BW",
    "sg:province":"Cambridgeshire",
    "sg:tags":[
        "recreation",
        "leisure",
        "centre"
    ],
    "wof:name":"Embankment Athletics Track",
    "wof:placetype":"venue"
},
  "geometry": {"coordinates":[-0.231328994,52.5724563599],"type":"Point"}
}