{
  "type": "Feature",
  "properties": {
    "iso:country":"GB",
    "sg:address":"The Corn Mill, Prestbury",
    "sg:city":"Macclesfield",
    "sg:classifiers":[
        {
            "category":"Retail",
            "subcategory":"Auto Repair",
            "type":"Services"
        }
    ],
    "sg:phone":"+44 1625 828411",
    "sg:postcode":"SK10 4DG",
    "sg:province":"Cheshire",
    "sg:tags":[
        "modification",
        "garage"
    ],
    "wof:name":"Rose,J & P,(Garages) Ltd",
    "wof:placetype":"venue"
},
  "geometry": {"coordinates":[-2.150668,53.28997],"type":"Point"}
}