{
  "type": "Feature",
  "properties": {
    "iso:country":"GB",
    "sg:address":"26 Reighton Avenue",
    "sg:city":"York",
    "sg:classifiers":[
        {
            "category":"Building & Trades",
            "subcategory":"Construction",
            "type":"Services"
        }
    ],
    "sg:postcode":"YO30 5QN",
    "sg:province":"North Yorkshire",
    "sg:tags":[
        "glazier",
        "decorator",
        "painter"
    ],
    "wof:name":"Duncan A Bailey",
    "wof:placetype":"venue"
},
  "geometry": {"coordinates":[-1.1040869951,53.9781608582],"type":"Point"}
}