{
  "type": "Feature",
  "properties": {
    "iso:country":"GB",
    "sg:address":"121 Lower Street",
    "sg:city":"Pulborough",
    "sg:classifiers":[
        {
            "category":"Retail",
            "subcategory":"Veterinary Services",
            "type":"Services"
        }
    ],
    "sg:phone":"+44 1798 872089",
    "sg:postcode":"RH20 2BP",
    "sg:province":"West Sussex",
    "sg:tags":[
        "surgeon",
        "activity"
    ],
    "wof:name":"Arun Veterinary Group",
    "wof:placetype":"venue"
},
  "geometry": {"coordinates":[-0.49897,50.957169],"type":"Point"}
}