{
  "type": "Feature",
  "properties": {
    "addr:full":"34 Winterslow Road, Porton Salisbury Hampshire SP4 0LF",
    "addr:housenumber":"34",
    "addr:postcode":"sp4 0lf",
    "addr:street":"Winterslow Road",
    "iso:country":"GB",
    "sg:address":"34 Winterslow Road, Porton",
    "sg:city":"Salisbury",
    "sg:classifiers":[
        {
            "category":"Shopping",
            "subcategory":"Department Store",
            "type":"Retail Goods"
        },
        {
            "category":"Government",
            "subcategory":"Post Office",
            "type":"Public Place"
        }
    ],
    "sg:phone":"+44 1980 610258",
    "sg:postcode":"SP4 0LF",
    "sg:province":"Hampshire",
    "wof:name":"Porton Post Office & Village Store",
    "wof:placetype":"venue"
},
  "geometry": {"coordinates":[-1.7322479486,51.1282997131],"type":"Point"}
}