{
  "type": "Feature",
  "properties": {
    "iso:country":"GB",
    "sg:address":"2 Oxford Street",
    "sg:city":"Whitley Bay",
    "sg:classifiers":[
        {
            "category":"Education",
            "subcategory":"Dance Studio",
            "type":"Public Place"
        }
    ],
    "sg:phone":"+44 191 253 4466",
    "sg:postcode":"NE26 1AE",
    "sg:province":"Northumberland",
    "sg:tags":[
        "school",
        "dancing"
    ],
    "wof:name":"NORTH OF ENGLAND COLLEGE OF DANCE",
    "wof:placetype":"venue"
},
  "geometry": {"coordinates":[-1.446573019,55.0455627441],"type":"Point"}
}