{
  "type": "Feature",
  "properties": {
    "iso:country":"GB",
    "sg:address":"84 Hewlett Road",
    "sg:city":"Cheltenham",
    "sg:classifiers":[
        {
            "category":"Shopping",
            "subcategory":"Mobile Phones",
            "type":"Retail Goods"
        }
    ],
    "sg:phone":"+44 1242 224605",
    "sg:postcode":"GL52 6AR",
    "sg:province":"Gloucestershire",
    "wof:name":"Capstone Communications",
    "wof:placetype":"venue"
},
  "geometry": {"coordinates":[-2.0649240017,51.8999633789],"type":"Point"}
}