{
  "type": "Feature",
  "properties": {
    "addr:full":"33 Cornwall Crescent London Greater London W11 1PJ",
    "addr:housenumber":"33",
    "addr:postcode":"w11 1pj",
    "addr:street":"Cornwall Crescent",
    "iso:country":"GB",
    "sg:address":"33 Cornwall Crescent",
    "sg:city":"London",
    "sg:classifiers":[
        {
            "category":"Professional",
            "subcategory":"Art Services",
            "type":"Services"
        }
    ],
    "sg:phone":"+44 20 7467 0080",
    "sg:postcode":"W11 1PJ",
    "sg:province":"Greater London",
    "sg:tags":[
        "consultant",
        "graphic",
        "design",
        "designer"
    ],
    "sg:website":"http://www.cada.co.uk",
    "wof:name":"Bullitt Design Consultants",
    "wof:placetype":"venue"
},
  "geometry": {"coordinates":[-0.2107429951,51.5148239136],"type":"Point"}
}