{
  "type": "Feature",
  "properties": {
    "iso:country":"GB",
    "sg:address":"11-12 Maclaren Place",
    "sg:city":"Glasgow",
    "sg:classifiers":[
        {
            "category":"Cafe",
            "type":"Food & Drink"
        }
    ],
    "sg:phone":"+44 141 637 2311",
    "sg:postcode":"G44 3RZ",
    "sg:province":"East Renfrewshire",
    "sg:tags":[
        "tea",
        "room"
    ],
    "wof:name":"The Derby",
    "wof:placetype":"venue"
},
  "geometry": {"coordinates":[-4.270009,55.802856],"type":"Point"}
}