{
  "type": "Feature",
  "properties": {
    "iso:country":"GB",
    "sg:address":"19 Pelham Road, Sherwood Rise",
    "sg:city":"Nottingham",
    "sg:classifiers":[
        {
            "category":"Professional",
            "subcategory":"Business Services",
            "type":"Services"
        }
    ],
    "sg:postcode":"NG5 1AP",
    "sg:province":"Nottinghamshire",
    "sg:tags":[
        "holding"
    ],
    "wof:name":"Alarmcord Ltd",
    "wof:placetype":"venue"
},
  "geometry": {"coordinates":[-1.155901,52.970928],"type":"Point"}
}