{
  "type": "Feature",
  "properties": {
    "iso:country":"GB",
    "sg:address":"21 East Street",
    "sg:city":"Okehampton",
    "sg:classifiers":[
        {
            "category":"Food & Beverages",
            "subcategory":"Bakery",
            "type":"Retail Goods"
        }
    ],
    "sg:phone":"+44 1837 52888",
    "sg:postcode":"EX20 1AT",
    "sg:province":"Devon",
    "sg:tags":[
        "shop",
        "baker"
    ],
    "wof:name":"W T Endacott Ltd",
    "wof:placetype":"venue"
},
  "geometry": {"coordinates":[-3.999707,50.739609],"type":"Point"}
}