{
  "type": "Feature",
  "properties": {
    "iso:country":"GB",
    "sg:address":"The Rhond, Hoveton",
    "sg:city":"Norwich",
    "sg:classifiers":[
        {
            "category":"Recreation",
            "subcategory":"Boat Charter",
            "type":"Entertainment"
        }
    ],
    "sg:postcode":"NR12 8UE",
    "sg:province":"Norfolk",
    "sg:tags":[
        "excursion"
    ],
    "wof:name":"Camelot Craft Ltd.",
    "wof:placetype":"venue"
},
  "geometry": {"coordinates":[1.414644,52.714527],"type":"Point"}
}