{
  "type": "Feature",
  "properties": {
    "addr:full":"Gwrhyd Road, Rhiwfawr Swansea Carmarthenshire SA9 2SE",
    "addr:postcode":"sa9 2se",
    "addr:street":"Gwrhyd Road Rhiwfawr",
    "iso:country":"GB",
    "sg:address":"Gwrhyd Road, Rhiwfawr",
    "sg:city":"Swansea",
    "sg:classifiers":[
        {
            "category":"Utilities",
            "subcategory":"Recycling",
            "type":"Services"
        }
    ],
    "sg:phone":"+44 1639 830617",
    "sg:postcode":"SA9 2SE",
    "sg:province":"Carmarthenshire",
    "sg:tags":[
        "merchant",
        "waste"
    ],
    "wof:name":"P & M Birch",
    "wof:placetype":"venue"
},
  "geometry": {"coordinates":[-3.8211729527,51.7860145569],"type":"Point"}
}