{
  "type": "Feature",
  "properties": {
    "iso:country":"GB",
    "sg:address":"P O Box 20, Lowdham",
    "sg:city":"Nottingham",
    "sg:classifiers":[
        {
            "category":"Building & Trades",
            "subcategory":"Construction",
            "type":"Services"
        }
    ],
    "sg:phone":"+44 115 966 5000",
    "sg:postcode":"NG14 7HG",
    "sg:province":"Nottinghamshire",
    "sg:tags":[
        "builder"
    ],
    "wof:name":"Cms Group Services",
    "wof:placetype":"venue"
},
  "geometry": {"coordinates":[-0.9911440015,53.0160179138],"type":"Point"}
}