{
  "type": "Feature",
  "properties": {
    "addr:full":"Unit C, Ashford Works Industrial Estate Fordingbridge Dorset SP6 1DA",
    "addr:housenumber":"unit c",
    "addr:postcode":"sp6 1da",
    "addr:street":"Ashford Works Industrial Estate",
    "iso:country":"GB",
    "sg:address":"Unit C, Ashford Works Industrial Estate",
    "sg:city":"Fordingbridge",
    "sg:classifiers":[
        {
            "category":"Manufacturing",
            "subcategory":"Building Materials",
            "type":"Manufacturing & Wholesale Goods"
        }
    ],
    "sg:phone":"+44 1425 652848",
    "sg:postcode":"SP6 1DA",
    "sg:province":"Dorset",
    "sg:tags":[
        "tube",
        "manipulator",
        "bender"
    ],
    "wof:name":"New Forest Coppersmiths",
    "wof:placetype":"venue"
},
  "geometry": {"coordinates":[-1.791652,50.926819],"type":"Point"}
}