{
  "type": "Feature",
  "properties": {
    "iso:country":"GB",
    "sg:address":"123 Wallgate",
    "sg:city":"Wigan",
    "sg:classifiers":[
        {
            "category":"Building & Trades",
            "subcategory":"Equipment Rental",
            "type":"Services"
        }
    ],
    "sg:phone":"+44 1942 824300",
    "sg:postcode":"WN3 4AA",
    "sg:province":"Lancashire",
    "sg:tags":[
        "hire",
        "centre"
    ],
    "wof:name":"Hss Hire Shops",
    "wof:placetype":"venue"
},
  "geometry": {"coordinates":[-2.637474,53.542583],"type":"Point"}
}