{
  "type": "Feature",
  "properties": {
    "iso:country":"GB",
    "sg:address":"Wingfield Castle",
    "sg:city":"Diss",
    "sg:classifiers":[
        {
            "category":"Farming",
            "subcategory":"Livestock Farm",
            "type":"Manufacturing & Wholesale Goods"
        }
    ],
    "sg:postcode":"IP21 5RB",
    "sg:province":"Norfolk",
    "sg:tags":[
        "stud"
    ],
    "wof:name":"Friesian Horse Association of Great Britain & Ireland Ltd.",
    "wof:placetype":"venue"
},
  "geometry": {"coordinates":[1.27072,52.347076],"type":"Point"}
}