{
  "type": "Feature",
  "properties": {
    "addr:full":"Unit 1, Netherfield Mills, Calder Rd Dewsbury West Yorkshire WF13 3JS",
    "addr:housenumber":"unit 1",
    "addr:postcode":"wf13 3js",
    "addr:street":"Netherfield Mills Calder Rd",
    "iso:country":"GB",
    "sg:address":"Unit 1, Netherfield Mills, Calder Rd",
    "sg:city":"Dewsbury",
    "sg:classifiers":[
        {
            "category":"Home & Garden",
            "subcategory":"Building Materials",
            "type":"Retail Goods"
        }
    ],
    "sg:phone":"+44 1924 466977",
    "sg:postcode":"WF13 3JS",
    "sg:province":"West Yorkshire",
    "sg:tags":[
        "foam"
    ],
    "wof:name":"Alpha Foam Converters",
    "wof:placetype":"venue"
},
  "geometry": {"coordinates":[-1.657583952,53.6947250366],"type":"Point"}
}