{
  "type": "Feature",
  "properties": {
    "addr:full":"27-29 Slindon Top Road, Slindon Arundel West Sussex BN18 0RR",
    "addr:housenumber":"27-29",
    "addr:postcode":"bn18 0rr",
    "addr:street":"Slindon Top Road",
    "iso:country":"GB",
    "sg:address":"27-29 Slindon Top Road, Slindon",
    "sg:city":"Arundel",
    "sg:classifiers":[
        {
            "category":"Government",
            "subcategory":"Post Office",
            "type":"Public Place"
        }
    ],
    "sg:postcode":"BN18 0RR",
    "sg:province":"West Sussex",
    "wof:name":"Slindon Post Office",
    "wof:placetype":"venue"
},
  "geometry": {"coordinates":[-0.628764,50.86227],"type":"Point"}
}