{
  "type": "Feature",
  "properties": {
    "addr:full":"17 Sherborne Road Yeovil Somerset BA21 4HD",
    "addr:housenumber":"17",
    "addr:postcode":"ba21 4hd",
    "addr:street":"Sherborne Road",
    "iso:country":"GB",
    "sg:address":"17 Sherborne Road",
    "sg:city":"Yeovil",
    "sg:classifiers":[
        {
            "category":"Communications",
            "type":"Services"
        }
    ],
    "sg:phone":"+44 1935 411440",
    "sg:postcode":"BA21 4HD",
    "sg:province":"Somerset",
    "sg:tags":[
        "telecommunication"
    ],
    "wof:name":"Airwaves Communications (South West) Ltd.",
    "wof:placetype":"venue"
},
  "geometry": {"coordinates":[-2.6247580051,50.9428901672],"type":"Point"}
}