{
  "type": "Feature",
  "properties": {
    "iso:country":"GB",
    "sg:address":"67 Uverdale Rd",
    "sg:city":"West Brompton",
    "sg:classifiers":[
        {
            "category":"Home & Garden",
            "subcategory":"Carpets & Floor Coverings",
            "type":"Retail Goods"
        }
    ],
    "sg:phone":"+44 20 7376 3136",
    "sg:postcode":"SW10 0SN",
    "sg:province":"Greater London",
    "sg:tags":[
        "carpets",
        "rug",
        "matting"
    ],
    "wof:name":"Rare Carpet Galleries",
    "wof:placetype":"venue"
},
  "geometry": {"coordinates":[-0.181939,51.478863],"type":"Point"}
}