{
  "type": "Feature",
  "properties": {
    "iso:country":"GB",
    "sg:address":"The Drift",
    "sg:city":"Cambridge",
    "sg:classifiers":[
        {
            "category":"Sports & Exercise",
            "subcategory":"Tennis Court",
            "type":"Entertainment"
        }
    ],
    "sg:postcode":"CB3 7TE",
    "sg:province":"Cambridgeshire",
    "sg:tags":[
        "breakdown",
        "recovery"
    ],
    "wof:name":"Caxton Gibbet Recovery Service",
    "wof:placetype":"venue"
},
  "geometry": {"coordinates":[-0.0553129986,52.2005996704],"type":"Point"}
}