{
  "type": "Feature",
  "properties": {
    "addr:full":"Cavendish House, Sydenham Road Guildford Surrey GU1 3RX",
    "addr:postcode":"gu1 3rx",
    "addr:street":"Sydenham Road",
    "iso:country":"GB",
    "sg:address":"Cavendish House, Sydenham Road",
    "sg:city":"Guildford",
    "sg:classifiers":[
        {
            "category":"Professional",
            "subcategory":"Business Services",
            "type":"Services"
        }
    ],
    "sg:phone":"+44 1483 573888",
    "sg:postcode":"GU1 3RX",
    "sg:province":"Surrey",
    "sg:tags":[
        "tile",
        "stockist"
    ],
    "wof:name":"Tile Depot",
    "wof:placetype":"venue"
},
  "geometry": {"coordinates":[-0.565984,51.237095],"type":"Point"}
}