{
  "type": "Feature",
  "properties": {
    "addr:full":"Concorde House, Colndale Road, Colnbrook Slough Berkshire SL3 0HQ",
    "addr:postcode":"sl3 0hq",
    "addr:street":"Colndale Road",
    "iso:country":"GB",
    "sg:address":"Concorde House, Colndale Road, Colnbrook",
    "sg:city":"Slough",
    "sg:classifiers":[
        {
            "category":"Autos & Motor Vehicles",
            "subcategory":"Fuel & Gas Station",
            "type":"Retail Goods"
        },
        {
            "category":"Professional",
            "type":"Services"
        },
        {
            "category":"Building & Trades",
            "subcategory":"Cleaning & Sanitation",
            "type":"Services"
        }
    ],
    "sg:phone":"+44 870 840 0611",
    "sg:postcode":"SL3 0HQ",
    "sg:province":"Berkshire",
    "sg:tags":[
        "transportation",
        "transfer",
        "commercial",
        "aircraft",
        "airport",
        "maintenance"
    ],
    "wof:name":"FERNLEY AIRPORT SERVICES LTD",
    "wof:placetype":"venue"
},
  "geometry": {"coordinates":[-0.5160400271,51.4761962891],"type":"Point"}
}