{
  "type": "Feature",
  "properties": {
    "addr:full":"21 The Broadway Bedford Bedfordshire MK40 2TL",
    "addr:housenumber":"21",
    "addr:postcode":"mk40 2tl",
    "addr:street":"The Broadway",
    "iso:country":"GB",
    "sg:address":"21 The Broadway",
    "sg:city":"Bedford",
    "sg:classifiers":[
        {
            "category":"Communications",
            "type":"Services"
        }
    ],
    "sg:phone":"+44 1234 356323",
    "sg:postcode":"MK40 2TL",
    "sg:province":"Bedfordshire",
    "sg:tags":[
        "tv",
        "video",
        "radio"
    ],
    "wof:name":"Tavistock Sound & Vision",
    "wof:placetype":"venue"
},
  "geometry": {"coordinates":[-0.4681479931,52.1400642395],"type":"Point"}
}