{
  "type": "Feature",
  "properties": {
    "addr:full":"209 Station Road Harrow Greater London HA1 2TP",
    "addr:housenumber":"209",
    "addr:postcode":"ha1 2tp",
    "addr:street":"Station Road",
    "iso:country":"GB",
    "sg:address":"209 Station Road",
    "sg:city":"Harrow",
    "sg:classifiers":[
        {
            "category":"Communications",
            "type":"Services"
        }
    ],
    "sg:phone":"+44 20 8427 1464",
    "sg:postcode":"HA1 2TP",
    "sg:province":"Greater London",
    "sg:tags":[
        "telecommunication"
    ],
    "wof:name":"Eclipse Telecome",
    "wof:placetype":"venue"
},
  "geometry": {"coordinates":[-0.332195,51.584538],"type":"Point"}
}