{
  "type": "Feature",
  "properties": {
    "addr:full":"46 Longdown House, Snodhurst Avenue Chatham Kent ME5 0TA",
    "addr:housenumber":"46",
    "addr:postcode":"me5 0ta",
    "addr:street":"Longdown House Snodhurst Avenue",
    "iso:country":"GB",
    "sg:address":"46 Longdown House, Snodhurst Avenue",
    "sg:city":"Chatham",
    "sg:classifiers":[
        {
            "category":"Food & Beverages",
            "subcategory":"Specialty",
            "type":"Retail Goods"
        }
    ],
    "sg:postcode":"ME5 0TA",
    "sg:province":"Kent",
    "sg:tags":[
        "product",
        "health"
    ],
    "wof:name":"Healthy Living",
    "wof:placetype":"venue"
},
  "geometry": {"coordinates":[0.51934,51.35313],"type":"Point"}
}