{
  "type": "Feature",
  "properties": {
    "addr:full":"344 Lymington Road Christchurch Dorset BH23 5EY",
    "addr:housenumber":"344",
    "addr:postcode":"bh23 5ey",
    "addr:street":"Lymington Road",
    "iso:country":"GB",
    "sg:address":"344 Lymington Road",
    "sg:city":"Christchurch",
    "sg:classifiers":[
        {
            "category":"Food & Beverages",
            "subcategory":"Fruits & Vegetables",
            "type":"Retail Goods"
        }
    ],
    "sg:phone":"+44 1425 274057",
    "sg:postcode":"BH23 5EY",
    "sg:province":"Dorset",
    "sg:tags":[
        "greengrocer"
    ],
    "wof:name":"Williams Fruits",
    "wof:placetype":"venue"
},
  "geometry": {"coordinates":[-1.699281,50.741676],"type":"Point"}
}