{
  "type": "Feature",
  "properties": {
    "iso:country":"GB",
    "sg:address":"Cottis Yard",
    "sg:city":"Rochford",
    "sg:classifiers":[
        {
            "category":"Manufacturing",
            "subcategory":"Lumber",
            "type":"Manufacturing & Wholesale Goods"
        }
    ],
    "sg:phone":"+44 1702 548180",
    "sg:postcode":"SS4 1ND",
    "sg:province":"Essex",
    "sg:tags":[
        "importer",
        "merchants",
        "agent",
        "timber"
    ],
    "wof:name":"Purdeys Timber Co. Ltd.",
    "wof:placetype":"venue"
},
  "geometry": {"coordinates":[0.7013890147,51.5832214355],"type":"Point"}
}