{
  "type": "Feature",
  "properties": {
    "addr:full":"15 Duncan Close, Moulton Park Northampton Northamptonshire NN3 6WL",
    "addr:housenumber":"15",
    "addr:postcode":"nn3 6wl",
    "addr:street":"Duncan Close;Park",
    "iso:country":"GB",
    "sg:address":"15 Duncan Close, Moulton Park",
    "sg:city":"Northampton",
    "sg:classifiers":[
        {
            "category":"Professional",
            "subcategory":"Accounting & Tax Preparation",
            "type":"Services"
        }
    ],
    "sg:phone":"+44 1604 790646",
    "sg:postcode":"NN3 6WL",
    "sg:province":"Northamptonshire",
    "sg:tags":[
        "accountant"
    ],
    "wof:name":"Webb & Co.",
    "wof:placetype":"venue"
},
  "geometry": {"coordinates":[-0.879743,52.278076],"type":"Point"}
}