{
  "type": "Feature",
  "properties": {
    "iso:country":"GB",
    "sg:address":"162 Windmill Road",
    "sg:city":"Coventry",
    "sg:classifiers":[
        {
            "category":"Building & Trades",
            "subcategory":"Construction",
            "type":"Services"
        }
    ],
    "sg:postcode":"CV6 7BE",
    "sg:province":"Warwickshire",
    "sg:tags":[
        "builder"
    ],
    "wof:name":"Coventry Builders",
    "wof:placetype":"venue"
},
  "geometry": {"coordinates":[-1.480899,52.444435],"type":"Point"}
}