{
  "type": "Feature",
  "properties": {
    "iso:country":"GB",
    "sg:address":"P S B House, Williamson Street",
    "sg:city":"Stoke-on-trent",
    "sg:classifiers":[
        {
            "category":"Shopping",
            "subcategory":"Party Supplies",
            "type":"Retail Goods"
        }
    ],
    "sg:phone":"+44 1782 833520",
    "sg:postcode":"ST6 6AS",
    "sg:province":"Staffordshire",
    "sg:tags":[
        "marquees",
        "floor",
        "tent"
    ],
    "wof:name":"Event Marquees Ltd.",
    "wof:placetype":"venue"
},
  "geometry": {"coordinates":[-2.210083,53.055473],"type":"Point"}
}