{
  "type": "Feature",
  "properties": {
    "addr:full":"25 High St, Newbridge Newport Blaenau Gwent NP11 4FH",
    "addr:housenumber":"25",
    "addr:postcode":"np11 4fh",
    "addr:street":"High St",
    "iso:country":"GB",
    "sg:address":"25 High St, Newbridge",
    "sg:city":"Newport",
    "sg:classifiers":[
        {
            "category":"Recreation",
            "subcategory":"Amusement Park",
            "type":"Entertainment"
        }
    ],
    "sg:phone":"+44 1823 337162",
    "sg:postcode":"NP11 4FH",
    "sg:province":"Blaenau Gwent",
    "sg:tags":[
        "arcade"
    ],
    "wof:name":"Sunvalley",
    "wof:placetype":"venue"
},
  "geometry": {"coordinates":[-3.1466159821,51.6644554138],"type":"Point"}
}