{
  "type": "Feature",
  "properties": {
    "addr:full":"Boundary La Manchester Cheshire M15 6GE",
    "addr:postcode":"m15 6ge",
    "addr:street":"Boundary La Manchester",
    "iso:country":"GB",
    "sg:address":"Boundary La",
    "sg:city":"Manchester",
    "sg:classifiers":[
        {
            "category":"Bars & Pubs",
            "type":"Food & Drink"
        }
    ],
    "sg:postcode":"M15 6GE",
    "sg:province":"Cheshire",
    "sg:tags":[
        "pubs",
        "inn"
    ],
    "wof:name":"Gamecock (The)",
    "wof:placetype":"venue"
},
  "geometry": {"coordinates":[-2.236649,53.464806],"type":"Point"}
}