{
  "type": "Feature",
  "properties": {
    "addr:full":"35 Penfold Road, Edmonton London Greater London N9 8EH",
    "addr:housenumber":"35",
    "addr:postcode":"n9 8eh",
    "addr:street":"Penfold Road Edmonton",
    "iso:country":"GB",
    "sg:address":"35 Penfold Road, Edmonton",
    "sg:city":"London",
    "sg:classifiers":[
        {
            "category":"Retail",
            "subcategory":"Auto Repair",
            "type":"Services"
        }
    ],
    "sg:postcode":"N9 8EH",
    "sg:province":"Greater London",
    "sg:tags":[
        "engine",
        "car",
        "specialist"
    ],
    "wof:name":"Auto Mobile Tuning",
    "wof:placetype":"venue"
},
  "geometry": {"coordinates":[-0.042492,51.631962],"type":"Point"}
}