{
  "type": "Feature",
  "properties": {
    "addr:full":"Station Road Harleston Norfolk IP20 9ES",
    "addr:postcode":"ip20 9es",
    "addr:street":"Station Road",
    "iso:country":"GB",
    "sg:address":"Station Road",
    "sg:city":"Harleston",
    "sg:classifiers":[
        {
            "category":"Retail",
            "subcategory":"Auto Repair",
            "type":"Services"
        }
    ],
    "sg:postcode":"IP20 9ES",
    "sg:province":"Norfolk",
    "sg:tags":[
        "modification",
        "garage"
    ],
    "wof:name":"Lodge Motors",
    "wof:placetype":"venue"
},
  "geometry": {"coordinates":[1.30297,52.405457],"type":"Point"}
}