{
  "type": "Feature",
  "properties": {
    "addr:full":"24 Piccadilly Stoke On Trent Staffordshire ST1 1EG",
    "addr:housenumber":"24",
    "addr:postcode":"st1 1eg",
    "addr:street":"Piccadilly Stoke On",
    "iso:country":"GB",
    "sg:address":"24 Piccadilly",
    "sg:city":"Stoke On Trent",
    "sg:classifiers":[
        {
            "category":"Shopping",
            "subcategory":"Gifts & Souvenirs",
            "type":"Retail Goods"
        }
    ],
    "sg:phone":"+44 1782 207080",
    "sg:postcode":"ST1 1EG",
    "sg:province":"Staffordshire",
    "sg:tags":[
        "shop"
    ],
    "wof:name":"Fascination",
    "wof:placetype":"venue"
},
  "geometry": {"coordinates":[-2.1767990589,53.0249137878],"type":"Point"}
}