{
  "type": "Feature",
  "properties": {
    "addr:full":"Montrose Avenue Glasgow Glasgow City G32 8BZ",
    "addr:postcode":"g32 8bz",
    "addr:street":"Montrose Avenue",
    "iso:country":"GB",
    "sg:address":"Montrose Avenue",
    "sg:city":"Glasgow",
    "sg:classifiers":[
        {
            "category":"Education",
            "subcategory":"School",
            "type":"Public Place"
        }
    ],
    "sg:phone":"+44 141 641 6840",
    "sg:postcode":"G32 8BZ",
    "sg:province":"Glasgow City",
    "sg:tags":[
        "local",
        "authority"
    ],
    "wof:name":"St Joachim's R C Primary School",
    "wof:placetype":"venue"
},
  "geometry": {"coordinates":[-4.153468,55.833961],"type":"Point"}
}