{
  "type": "Feature",
  "properties": {
    "addr:full":"Unit 1, D G S Trading Estate, Castle Lane Derby Derbyshire DE73 1DY",
    "addr:housenumber":"unit 1 d g",
    "addr:postcode":"de73 1dy",
    "addr:street":"S Trading Estate Castle Lane",
    "iso:country":"GB",
    "sg:address":"Unit 1, D G S Trading Estate, Castle Lane",
    "sg:city":"Derby",
    "sg:classifiers":[
        {
            "category":"Building & Trades",
            "subcategory":"Plumbing",
            "type":"Services"
        },
        {
            "category":"Home & Garden",
            "subcategory":"Hardware",
            "type":"Retail Goods"
        }
    ],
    "sg:phone":"+44 1332 862241",
    "sg:postcode":"DE73 1DY",
    "sg:province":"Derbyshire",
    "sg:tags":[
        "merchant",
        "plumbers'"
    ],
    "wof:name":"D G S Hardware Ltd.",
    "wof:placetype":"venue"
},
  "geometry": {"coordinates":[-1.4250500202,52.8240013123],"type":"Point"}
}