{
  "type": "Feature",
  "properties": {
    "addr:full":"Hollins Farm, Middleham Leyburn North Yorkshire DL8 4PX",
    "addr:postcode":"dl8 4px",
    "addr:street":"Hollins",
    "iso:country":"GB",
    "sg:address":"Hollins Farm, Middleham",
    "sg:city":"Leyburn",
    "sg:classifiers":[
        {
            "category":"Farming",
            "subcategory":"Farm",
            "type":"Manufacturing & Wholesale Goods"
        }
    ],
    "sg:phone":"+44 1969 623267",
    "sg:postcode":"DL8 4PX",
    "sg:province":"North Yorkshire",
    "sg:tags":[
        "mixed",
        "crop"
    ],
    "wof:name":"Richard Scrope",
    "wof:placetype":"venue"
},
  "geometry": {"coordinates":[-1.8053189516,54.2852554321],"type":"Point"}
}