{
  "type": "Feature",
  "properties": {
    "addr:full":"Bryer Ash Business Park, Bradford Rd Trowbridge Wiltshire BA14 8AW",
    "addr:postcode":"ba14 8aw",
    "addr:street":"Business Park Bradford Rd",
    "iso:country":"GB",
    "sg:address":"Bryer Ash Business Park, Bradford Rd",
    "sg:city":"Trowbridge",
    "sg:classifiers":[
        {
            "category":"Professional",
            "subcategory":"Lawyer & Legal Services",
            "type":"Services"
        }
    ],
    "sg:phone":"+44 1225 777464",
    "sg:postcode":"BA14 8AW",
    "sg:province":"Wiltshire",
    "sg:tags":[
        "solicitor"
    ],
    "wof:name":"Withy King",
    "wof:placetype":"venue"
},
  "geometry": {"coordinates":[-2.2083740234,51.3153419495],"type":"Point"}
}