{
  "type": "Feature",
  "properties": {
    "iso:country":"GB",
    "sg:address":"The Manor, Chitterne",
    "sg:city":"Warminster",
    "sg:classifiers":[
        {
            "category":"Farming",
            "subcategory":"Livestock Farm",
            "type":"Manufacturing & Wholesale Goods"
        }
    ],
    "sg:phone":"+44 1985 850287",
    "sg:postcode":"BA12 0LT",
    "sg:province":"Somerset",
    "sg:tags":[
        "others"
    ],
    "wof:name":"William L B Wallis",
    "wof:placetype":"venue"
},
  "geometry": {"coordinates":[-2.013602,51.193939],"type":"Point"}
}