{
  "type": "Feature",
  "properties": {
    "iso:country":"GB",
    "sg:address":"Burnsall Road",
    "sg:city":"Coventry",
    "sg:classifiers":[
        {
            "category":"Manufacturing",
            "subcategory":"Metals",
            "type":"Manufacturing & Wholesale Goods"
        },
        {
            "category":"Manufacturing",
            "subcategory":"Tools & Machinery",
            "type":"Manufacturing & Wholesale Goods"
        }
    ],
    "sg:phone":"+44 24 7671 7683",
    "sg:postcode":"CV5 6BU",
    "sg:province":"West Midlands",
    "sg:tags":[
        "steel",
        "fabricator",
        "design",
        "maker"
    ],
    "wof:name":"Powergrade Ltd",
    "wof:placetype":"venue"
},
  "geometry": {"coordinates":[-1.548793,52.396336],"type":"Point"}
}