{
  "type": "Feature",
  "properties": {
    "addr:full":"136 Walton Road East Molesey Greater London KT8 0HP",
    "addr:housenumber":"136",
    "addr:postcode":"kt8 0hp",
    "addr:street":"Walton Road",
    "iso:country":"GB",
    "sg:address":"136 Walton Road",
    "sg:city":"East Molesey",
    "sg:classifiers":[
        {
            "category":"Shopping",
            "subcategory":"Department Store",
            "type":"Retail Goods"
        }
    ],
    "sg:phone":"+44 20 8979 4350",
    "sg:postcode":"KT8 0HP",
    "sg:province":"Greater London",
    "wof:name":"Woolworths",
    "wof:placetype":"venue"
},
  "geometry": {"coordinates":[-0.3556610048,51.4003181458],"type":"Point"}
}