{
  "type": "Feature",
  "properties": {
    "iso:country":"GB",
    "sg:address":"Unit 7 47 Byron St",
    "sg:city":"Dundee",
    "sg:classifiers":[
        {
            "category":"Retail",
            "subcategory":"Auto Repair",
            "type":"Services"
        }
    ],
    "sg:phone":"+44 1382 828088",
    "sg:postcode":"DD3 6QT",
    "sg:province":"Dundee City",
    "sg:tags":[
        "modification",
        "garage"
    ],
    "wof:name":"Abertay Autos",
    "wof:placetype":"venue"
},
  "geometry": {"coordinates":[-2.985721,56.472778],"type":"Point"}
}