{
  "type": "Feature",
  "properties": {
    "iso:country":"GB",
    "sg:address":"P O Box 428",
    "sg:city":"West Wickham",
    "sg:classifiers":[
        {
            "category":"Professional",
            "subcategory":"Management & Consulting",
            "type":"Services"
        }
    ],
    "sg:phone":"+44 20 8325 9715",
    "sg:postcode":"BR4 0PD",
    "sg:province":"Kent",
    "sg:tags":[
        "consultant",
        "energy",
        "conservation"
    ],
    "wof:name":"Maks Consultancy Ltd.",
    "wof:placetype":"venue"
},
  "geometry": {"coordinates":[-0.009324,51.374588],"type":"Point"}
}