{
  "type": "Feature",
  "properties": {
    "addr:full":"14 St Oswalds Street Liverpool Merseyside L13 2BY",
    "addr:housenumber":"14",
    "addr:postcode":"l13 2by",
    "addr:street":"St Oswalds Street",
    "iso:country":"GB",
    "sg:address":"14 St Oswalds Street",
    "sg:city":"Liverpool",
    "sg:classifiers":[
        {
            "category":"Shopping",
            "subcategory":"Pharmacy",
            "type":"Retail Goods"
        }
    ],
    "sg:phone":"+44 151 228 3108",
    "sg:postcode":"L13 2BY",
    "sg:province":"Merseyside",
    "sg:tags":[
        "pharmacist",
        "chemist"
    ],
    "wof:name":"Houghton & Lappin Ltd.",
    "wof:placetype":"venue"
},
  "geometry": {"coordinates":[-2.9146249294,53.412940979],"type":"Point"}
}