{
  "type": "Feature",
  "properties": {
    "iso:country":"GB",
    "sg:address":"Unit 1 Hillcroft Farm, Easterton Sands",
    "sg:city":"Devizes",
    "sg:classifiers":[
        {
            "category":"Professional",
            "subcategory":"Engineering",
            "type":"Services"
        }
    ],
    "sg:postcode":"SN10 4PY",
    "sg:province":"Wiltshire",
    "sg:tags":[
        "contractor",
        "electrical",
        "engineer"
    ],
    "wof:name":"Mercer Holdings",
    "wof:placetype":"venue"
},
  "geometry": {"coordinates":[-1.9711740017,51.2950706482],"type":"Point"}
}