{
  "type": "Feature",
  "properties": {
    "iso:country":"GB",
    "sg:address":"Unit A, The Brambles, Bramble Road",
    "sg:city":"Swindon",
    "sg:classifiers":[
        {
            "category":"Autos & Motor Vehicles",
            "subcategory":"Automobile Sales",
            "type":"Retail Goods"
        }
    ],
    "sg:phone":"+44 1793 487300",
    "sg:postcode":"SN2 8DS",
    "sg:province":"Wiltshire",
    "sg:tags":[
        "commercial"
    ],
    "wof:name":"Commercial Aspects Ltd.",
    "wof:placetype":"venue"
},
  "geometry": {"coordinates":[-1.7653,51.574009],"type":"Point"}
}