{
  "type": "Feature",
  "properties": {
    "addr:full":"80 Hendon Way Cricklewood Greater London NW2 2NG",
    "addr:housenumber":"80",
    "addr:postcode":"nw2 2ng",
    "addr:street":"Hendon Way",
    "iso:country":"GB",
    "sg:address":"80 Hendon Way",
    "sg:city":"Cricklewood",
    "sg:classifiers":[
        {
            "category":"Travel",
            "subcategory":"Hotels & Motels",
            "type":"Entertainment"
        }
    ],
    "sg:phone":"+44 20 8458 4636",
    "sg:postcode":"NW2 2NG",
    "sg:province":"Greater London",
    "sg:tags":[
        "house",
        "guest"
    ],
    "wof:name":"Clarendon Guest House",
    "wof:placetype":"venue"
},
  "geometry": {"coordinates":[-0.2048410028,51.5641670227],"type":"Point"}
}