{
  "type": "Feature",
  "properties": {
    "iso:country":"GB",
    "sg:address":"10 Morrab Road",
    "sg:city":"Penzance",
    "sg:classifiers":[
        {
            "category":"Travel",
            "subcategory":"Hotels & Motels",
            "type":"Entertainment"
        }
    ],
    "sg:phone":"+44 1736 362727",
    "sg:postcode":"TR18 4EZ",
    "sg:province":"Cornwall",
    "sg:tags":[
        "house",
        "guest"
    ],
    "wof:name":"Kimberley House",
    "wof:placetype":"venue"
},
  "geometry": {"coordinates":[-5.539208889,50.117023468],"type":"Point"}
}