{
  "type": "Feature",
  "properties": {
    "iso:country":"GB",
    "sg:address":"Bridewell Lane",
    "sg:city":"Bury St Edmunds",
    "sg:classifiers":[
        {
            "category":"Education",
            "subcategory":"School",
            "type":"Public Place"
        }
    ],
    "sg:phone":"+44 1284 754840",
    "sg:postcode":"IP33 1RE",
    "sg:province":"Suffolk",
    "sg:tags":[
        "local",
        "authority"
    ],
    "wof:name":"Guildhall Feoffement County Primary School",
    "wof:placetype":"venue"
},
  "geometry": {"coordinates":[0.715915,52.243061],"type":"Point"}
}