{
  "type": "Feature",
  "properties": {
    "addr:full":"Roseleigh Avenue Maidstone Kent ME16 0BD",
    "addr:postcode":"me16 0bd",
    "addr:street":"Roseleigh Avenue",
    "iso:country":"GB",
    "sg:address":"Roseleigh Avenue",
    "sg:city":"Maidstone",
    "sg:classifiers":[
        {
            "category":"Organizations",
            "subcategory":"Non-profit Organization",
            "type":"Services"
        }
    ],
    "sg:phone":"+44 1622 685097",
    "sg:postcode":"ME16 0BD",
    "sg:province":"Kent",
    "sg:tags":[
        "organisation",
        "voluntary",
        "charity"
    ],
    "wof:name":"Roseleigh Day Centre",
    "wof:placetype":"venue"
},
  "geometry": {"coordinates":[0.49736,51.277576],"type":"Point"}
}