{
  "type": "Feature",
  "properties": {
    "iso:country":"GB",
    "sg:address":"56 Fore St, Praze",
    "sg:city":"Camborne",
    "sg:classifiers":[
        {
            "category":"Utilities",
            "type":"Services"
        }
    ],
    "sg:phone":"+44 1209 831539",
    "sg:postcode":"TR14 0JU",
    "sg:province":"Cornwall",
    "sg:tags":[
        "internet"
    ],
    "wof:name":"Duchy Computer Services",
    "wof:placetype":"venue"
},
  "geometry": {"coordinates":[-5.311739,50.174828],"type":"Point"}
}