{
  "type": "Feature",
  "properties": {
    "iso:country":"GB",
    "sg:address":"39 Green La",
    "sg:city":"Ilford",
    "sg:classifiers":[
        {
            "category":"Real Estate",
            "subcategory":"Developer",
            "type":"Services"
        }
    ],
    "sg:postcode":"IG1 1XG",
    "sg:province":"Essex",
    "sg:tags":[
        "property"
    ],
    "wof:name":"Advance Foam Ltd",
    "wof:placetype":"venue"
},
  "geometry": {"coordinates":[0.08492,51.558861],"type":"Point"}
}