{
  "type": "Feature",
  "properties": {
    "iso:country":"GB",
    "sg:address":"New Life Centre, Monkton Road",
    "sg:city":"Prestwick",
    "sg:classifiers":[
        {
            "category":"Organizations",
            "subcategory":"Religious Organization",
            "type":"Services"
        }
    ],
    "sg:phone":"+44 1292 671038",
    "sg:postcode":"KA9 2PA",
    "sg:province":"South Ayrshire",
    "sg:tags":[
        "organisation"
    ],
    "wof:name":"New Life Christian Fellowship",
    "wof:placetype":"venue"
},
  "geometry": {"coordinates":[-4.604234,55.50877],"type":"Point"}
}