{
  "type": "Feature",
  "properties": {
    "addr:full":"100 Anwell St Hoddesdon Essex EN11 8TZ",
    "addr:housenumber":"100",
    "addr:postcode":"en11 8tz",
    "addr:street":"Anwell St",
    "iso:country":"GB",
    "sg:address":"100 Anwell St",
    "sg:city":"Hoddesdon",
    "sg:classifiers":[
        {
            "category":"Professional",
            "subcategory":"Detective & Security Services",
            "type":"Services"
        }
    ],
    "sg:phone":"+44 1992 303011",
    "sg:postcode":"EN11 8TZ",
    "sg:province":"Essex",
    "wof:name":"Barnard Fitch Security Services Ltd",
    "wof:placetype":"venue"
},
  "geometry": {"coordinates":[-0.011182,51.76543],"type":"Point"}
}