{
  "type": "Feature",
  "properties": {
    "addr:full":"Briestfield Road, Grange Moor Wakefield West Yorkshire WF4 4DX",
    "addr:postcode":"wf4 4dx",
    "addr:street":"Briestfield Road;West",
    "iso:country":"GB",
    "sg:address":"Briestfield Road, Grange Moor",
    "sg:city":"Wakefield",
    "sg:classifiers":[
        {
            "category":"Retail",
            "subcategory":"Emissions Testing",
            "type":"Services"
        },
        {
            "category":"Professional",
            "subcategory":"Testing Lab",
            "type":"Services"
        }
    ],
    "sg:phone":"+44 1924 840336",
    "sg:postcode":"WF4 4DX",
    "sg:province":"West Yorkshire",
    "sg:tags":[
        "mot"
    ],
    "wof:name":"J Wright & Sons Ltd",
    "wof:placetype":"venue"
},
  "geometry": {"coordinates":[-1.6664479971,53.6426734924],"type":"Point"}
}