{
  "type": "Feature",
  "properties": {
    "addr:full":"23 Market Pl Gerrards Cross Buckinghamshire SL9 9EA",
    "addr:housenumber":"23",
    "addr:postcode":"sl9 9ea",
    "addr:street":"Market Pl",
    "iso:country":"GB",
    "sg:address":"23 Market Pl",
    "sg:city":"Gerrards Cross",
    "sg:classifiers":[
        {
            "category":"Food & Beverages",
            "subcategory":"Liquor & Beverages",
            "type":"Retail Goods"
        }
    ],
    "sg:phone":"+44 1753 882082",
    "sg:postcode":"SL9 9EA",
    "sg:province":"Buckinghamshire",
    "sg:tags":[
        "beer",
        "spirit",
        "wines"
    ],
    "wof:name":"Thresher",
    "wof:placetype":"venue"
},
  "geometry": {"coordinates":[-0.5594109893,51.6067276001],"type":"Point"}
}