{
  "type": "Feature",
  "properties": {
    "addr:full":"124 Irish St Dumfries Dumfries and Galloway DG1 2AW",
    "addr:housenumber":"124",
    "addr:postcode":"dg1 2aw",
    "addr:street":"Irish St",
    "iso:country":"GB",
    "sg:address":"124 Irish St",
    "sg:city":"Dumfries",
    "sg:classifiers":[
        {
            "category":"Social Services",
            "type":"Services"
        }
    ],
    "sg:phone":"+44 1387 223000",
    "sg:postcode":"DG1 2AW",
    "sg:province":"Dumfries and Galloway",
    "sg:tags":[
        "benefit",
        "agency"
    ],
    "wof:name":"Benefits Agency",
    "wof:placetype":"venue"
},
  "geometry": {"coordinates":[-3.6123189926,55.0689125061],"type":"Point"}
}