{
  "type": "Feature",
  "properties": {
    "addr:full":"4 Stanley Road London Greater London SW19 8RF",
    "addr:housenumber":"4",
    "addr:postcode":"sw19 8rf",
    "addr:street":"Stanley Road",
    "iso:country":"GB",
    "sg:address":"4 Stanley Road",
    "sg:city":"London",
    "sg:classifiers":[
        {
            "category":"Fast Food",
            "type":"Food & Drink"
        }
    ],
    "sg:phone":"+44 20 8543 5060",
    "sg:postcode":"SW19 8RF",
    "sg:province":"Greater London",
    "sg:tags":[
        "away",
        "take"
    ],
    "wof:name":"Wimbledon Kebabs",
    "wof:placetype":"venue"
},
  "geometry": {"coordinates":[-0.199606,51.419338],"type":"Point"}
}