{
  "type": "Feature",
  "properties": {
    "addr:full":"Cambria Court, 231 Stratford Road Birmingham West Midlands B28 9AA",
    "addr:housenumber":"231",
    "addr:postcode":"b28 9aa",
    "addr:street":"Cambria;Stratford Road",
    "iso:country":"GB",
    "sg:address":"Cambria Court, 231 Stratford Road",
    "sg:city":"Birmingham",
    "sg:classifiers":[
        {
            "category":"Communications",
            "type":"Services"
        }
    ],
    "sg:phone":"+44 121 777 0707",
    "sg:postcode":"B28 9AA",
    "sg:province":"West Midlands",
    "sg:tags":[
        "audio-visual"
    ],
    "wof:name":"Presentation Warehouse Ltd.",
    "wof:placetype":"venue"
},
  "geometry": {"coordinates":[-1.8462589979,52.4345703125],"type":"Point"}
}