{
  "type": "Feature",
  "properties": {
    "addr:full":"Lyleston Farm, Cardross Dumbarton Argyll and Bute G82 5HE",
    "addr:housenumber":"cardross",
    "addr:postcode":"g82 5he",
    "addr:street":"Dumbarton",
    "iso:country":"GB",
    "sg:address":"Lyleston Farm, Cardross",
    "sg:city":"Dumbarton",
    "sg:classifiers":[
        {
            "category":"Farming",
            "subcategory":"Farm",
            "type":"Manufacturing & Wholesale Goods"
        }
    ],
    "sg:phone":"+44 1389 841347",
    "sg:postcode":"G82 5HE",
    "sg:province":"Argyll and Bute",
    "sg:tags":[
        "mixed",
        "crop"
    ],
    "wof:name":"J FILSHIE",
    "wof:placetype":"venue"
},
  "geometry": {"coordinates":[-4.654734,55.963436],"type":"Point"}
}