{
  "type": "Feature",
  "properties": {
    "addr:full":"Britain Street Dunstable Bedfordshire LU5 4JA",
    "addr:postcode":"lu5 4ja",
    "addr:street":"Britain Street",
    "iso:country":"GB",
    "sg:address":"Britain Street",
    "sg:city":"Dunstable",
    "sg:classifiers":[
        {
            "category":"Education",
            "subcategory":"School",
            "type":"Public Place"
        }
    ],
    "sg:phone":"+44 1582 661158",
    "sg:postcode":"LU5 4JA",
    "sg:province":"Bedfordshire",
    "sg:tags":[
        "local",
        "authority"
    ],
    "wof:name":"Priory Middle School",
    "wof:placetype":"venue"
},
  "geometry": {"coordinates":[-0.514941,51.884315],"type":"Point"}
}