{
  "type": "Feature",
  "properties": {
    "iso:country":"GB",
    "sg:address":"Maple Ho, 149 Tottenham Court Rd",
    "sg:city":"West End",
    "sg:classifiers":[
        {
            "category":"Wholesale",
            "subcategory":"Books, Periodicals, & Newspapers",
            "type":"Manufacturing & Wholesale Goods"
        }
    ],
    "sg:phone":"+44 20 7896 2700",
    "sg:postcode":"W1P 9LL",
    "sg:province":"Hampshire",
    "sg:tags":[
        "publishing"
    ],
    "wof:name":"FT Media & Telecoms",
    "wof:placetype":"venue"
},
  "geometry": {"coordinates":[-0.13899,51.50758],"type":"Point"}
}