{
  "type": "Feature",
  "properties": {
    "addr:full":"29 Church Street Walton-on-thames Surrey KT12 2QP",
    "addr:housenumber":"29",
    "addr:postcode":"kt12 2qp",
    "addr:street":"Church Street",
    "iso:country":"GB",
    "sg:address":"29 Church Street",
    "sg:city":"Walton-on-thames",
    "sg:classifiers":[
        {
            "category":"Wholesale",
            "subcategory":"Toys & Hobbies",
            "type":"Manufacturing & Wholesale Goods"
        },
        {
            "category":"Shopping",
            "subcategory":"Florist",
            "type":"Retail Goods"
        }
    ],
    "sg:phone":"+44 1932 244600",
    "sg:postcode":"KT12 2QP",
    "sg:province":"Surrey",
    "sg:tags":[
        "balloon",
        "novelty"
    ],
    "wof:name":"Bissons Blooms",
    "wof:placetype":"venue"
},
  "geometry": {"coordinates":[-0.418381,51.387074],"type":"Point"}
}