{
  "type": "Feature",
  "properties": {
    "iso:country":"GB",
    "sg:address":"32a Addington St",
    "sg:city":"Margate",
    "sg:classifiers":[
        {
            "category":"Shopping",
            "subcategory":"Department Store",
            "type":"Retail Goods"
        }
    ],
    "sg:postcode":"CT9 1QU",
    "sg:province":"Kent",
    "wof:name":"Kirby's Novelty Games Ltd",
    "wof:placetype":"venue"
},
  "geometry": {"coordinates":[1.385567,51.387516],"type":"Point"}
}