{
  "type": "Feature",
  "properties": {
    "addr:full":"Tanzaro Ho Ardwick Grn North Manchester Greater Manchester M12 6FZ",
    "addr:postcode":"m12 6fz",
    "addr:street":"Ardwick Grn North",
    "iso:country":"GB",
    "sg:address":"Tanzaro Ho Ardwick Grn North",
    "sg:city":"Manchester",
    "sg:classifiers":[
        {
            "category":"Professional",
            "subcategory":"Management & Consulting",
            "type":"Services"
        }
    ],
    "sg:postcode":"M12 6FZ",
    "sg:province":"Greater Manchester",
    "sg:tags":[
        "consultant",
        "training"
    ],
    "wof:name":"Avante",
    "wof:placetype":"venue"
},
  "geometry": {"coordinates":[-2.222435,53.469074],"type":"Point"}
}