{
  "type": "Feature",
  "properties": {
    "iso:country":"GB",
    "sg:address":"40 St Andrews Square",
    "sg:city":"Droitwich",
    "sg:classifiers":[
        {
            "category":"Shopping",
            "subcategory":"Clothing, Apparel, & Fashions",
            "type":"Retail Goods"
        }
    ],
    "sg:phone":"+44 1905 771514",
    "sg:postcode":"WR9 8HE",
    "sg:province":"Worcestershire",
    "sg:tags":[
        "shop",
        "lingerie",
        "hosiery"
    ],
    "wof:name":"Kate Barclay",
    "wof:placetype":"venue"
},
  "geometry": {"coordinates":[-2.1487390995,52.2685585022],"type":"Point"}
}