{
  "type": "Feature",
  "properties": {
    "addr:full":"4 Queens Annes Court, Peascod Street Windsor Berkshire SL4 1DG",
    "addr:housenumber":"4",
    "addr:postcode":"sl4 1dg",
    "addr:street":"Queens Annes Court Peascod Street",
    "iso:country":"GB",
    "sg:address":"4 Queens Annes Court, Peascod Street",
    "sg:city":"Windsor",
    "sg:classifiers":[
        {
            "category":"Shopping",
            "subcategory":"Luggage & Leather Goods",
            "type":"Retail Goods"
        }
    ],
    "sg:phone":"+44 1753 622286",
    "sg:postcode":"SL4 1DG",
    "sg:province":"Berkshire",
    "sg:tags":[
        "shop",
        "leathergoods"
    ],
    "wof:name":"Highclere Retail Ltd.",
    "wof:placetype":"venue"
},
  "geometry": {"coordinates":[-0.612228,51.481735],"type":"Point"}
}