{
  "type": "Feature",
  "properties": {
    "iso:country":"GB",
    "sg:address":"16 Thorncroft, Englefield Grn",
    "sg:city":"Egham",
    "sg:classifiers":[
        {
            "category":"Retail",
            "subcategory":"Auto Repair",
            "type":"Services"
        }
    ],
    "sg:postcode":"TW20 0SB",
    "sg:province":"Surrey",
    "sg:tags":[
        "electrician"
    ],
    "wof:name":"Brian Dolan",
    "wof:placetype":"venue"
},
  "geometry": {"coordinates":[-0.57492,51.424053],"type":"Point"}
}