{
  "type": "Feature",
  "properties": {
    "addr:full":"157 Dunstable Road Luton Bedfordshire LU1 1BW",
    "addr:housenumber":"157",
    "addr:postcode":"lu1 1bw",
    "addr:street":"Dunstable Road",
    "iso:country":"GB",
    "sg:address":"157 Dunstable Road",
    "sg:city":"Luton",
    "sg:classifiers":[
        {
            "category":"Shopping",
            "subcategory":"Gifts & Souvenirs",
            "type":"Retail Goods"
        }
    ],
    "sg:phone":"+44 1582 457540",
    "sg:postcode":"LU1 1BW",
    "sg:province":"Bedfordshire",
    "sg:tags":[
        "shop"
    ],
    "wof:name":"Giftique Enterprises",
    "wof:placetype":"venue"
},
  "geometry": {"coordinates":[-0.427292,51.884247],"type":"Point"}
}