{
  "type": "Feature",
  "properties": {
    "addr:full":"102 Palace Rd East Molesey Greater London KT8 9DU",
    "addr:housenumber":"102",
    "addr:postcode":"kt8 9du",
    "addr:street":"Palace Rd",
    "iso:country":"GB",
    "sg:address":"102 Palace Rd",
    "sg:city":"East Molesey",
    "sg:classifiers":[
        {
            "category":"Professional",
            "subcategory":"Management & Consulting",
            "type":"Services"
        }
    ],
    "sg:phone":"+44 20 8224 0641",
    "sg:postcode":"KT8 9DU",
    "sg:province":"Greater London",
    "sg:tags":[
        "consultant",
        "business"
    ],
    "wof:name":"Management House Ltd (The)",
    "wof:placetype":"venue"
},
  "geometry": {"coordinates":[-0.3544879854,51.4049072266],"type":"Point"}
}