{
  "type": "Feature",
  "properties": {
    "addr:full":"9 Maplewood Newcastle-upon-tyne Tyne and Wear NE6 4NP",
    "addr:housenumber":"9",
    "addr:postcode":"ne6 4np",
    "addr:street":"Maplewood",
    "iso:country":"GB",
    "sg:address":"9 Maplewood",
    "sg:city":"Newcastle-upon-tyne",
    "sg:classifiers":[
        {
            "category":"Organizations",
            "subcategory":"Community Association",
            "type":"Services"
        },
        {
            "category":"Organizations",
            "subcategory":"Non-profit Organization",
            "type":"Services"
        }
    ],
    "sg:phone":"+44 191 276 3545",
    "sg:postcode":"NE6 4NP",
    "sg:province":"Tyne and Wear",
    "sg:tags":[
        "associations",
        "voluntary",
        "organisation",
        "co-operatives",
        "societies",
        "trust",
        "housing",
        "charity"
    ],
    "wof:name":"NEW ERA HOUSING ASSOCIATION LIMITED",
    "wof:placetype":"venue"
},
  "geometry": {"coordinates":[-1.5588099957,54.987651825],"type":"Point"}
}