{
  "type": "Feature",
  "properties": {
    "iso:country":"GB",
    "sg:address":"Westfield Lodge, Westfield Lane, Barlborough",
    "sg:city":"Chesterfield",
    "sg:classifiers":[
        {
            "category":"Home & Garden",
            "subcategory":"Garden Supply",
            "type":"Retail Goods"
        }
    ],
    "sg:phone":"+44 1246 810393",
    "sg:postcode":"S43 4TP",
    "sg:province":"Derbyshire",
    "sg:tags":[
        "nursery",
        "centre"
    ],
    "wof:name":"Springbank Nurseries",
    "wof:placetype":"venue"
},
  "geometry": {"coordinates":[-1.288594,53.286156],"type":"Point"}
}