{
  "type": "Feature",
  "properties": {
    "addr:full":"Springfield House Medical Centre, 275 Huddersfield Rd Oldham Lancashire OL4 2RJ",
    "addr:housenumber":"275",
    "addr:postcode":"ol4 2rj",
    "addr:street":"Huddersfield Rd",
    "iso:country":"GB",
    "sg:address":"Springfield House Medical Centre, 275 Huddersfield Rd",
    "sg:city":"Oldham",
    "sg:classifiers":[
        {
            "category":"Health Services",
            "subcategory":"Doctor",
            "type":"Services"
        }
    ],
    "sg:phone":"+44 161 633 2333",
    "sg:postcode":"OL4 2RJ",
    "sg:province":"Lancashire",
    "sg:tags":[
        "practitioners"
    ],
    "wof:name":"Milton, M H",
    "wof:placetype":"venue"
},
  "geometry": {"coordinates":[-2.0836799145,53.5486717224],"type":"Point"}
}