{
  "type": "Feature",
  "properties": {
    "iso:country":"GB",
    "sg:address":"15 Bowling Green Lane",
    "sg:city":"London",
    "sg:classifiers":[
        {
            "category":"Professional",
            "subcategory":"Art Services",
            "type":"Services"
        }
    ],
    "sg:phone":"+44 20 7336 6111",
    "sg:postcode":"EC1R 0DB",
    "sg:province":"Greater London",
    "sg:tags":[
        "graphic",
        "designer"
    ],
    "wof:name":"Acrobat",
    "wof:placetype":"venue"
},
  "geometry": {"coordinates":[-0.1067190021,51.5248985291],"type":"Point"}
}