{
  "type": "Feature",
  "properties": {
    "iso:country":"GB",
    "sg:address":"Unit 4 2 Trostre Industrial Estate, Trostre Road",
    "sg:city":"Llanelli",
    "sg:classifiers":[
        {
            "category":"Professional",
            "subcategory":"Research",
            "type":"Services"
        }
    ],
    "sg:phone":"+44 1554 749330",
    "sg:postcode":"SA14 9UU",
    "sg:province":"Carmarthenshire",
    "sg:tags":[
        "organisation"
    ],
    "wof:name":"Metal Reduction Processing Ltd.",
    "wof:placetype":"venue"
},
  "geometry": {"coordinates":[-4.1462,51.678478],"type":"Point"}
}