{
  "type": "Feature",
  "properties": {
    "iso:country":"GB",
    "sg:address":"Glen Orchy",
    "sg:city":"Dalmally",
    "sg:classifiers":[
        {
            "category":"Farming",
            "subcategory":"Livestock Farm",
            "type":"Manufacturing & Wholesale Goods"
        }
    ],
    "sg:phone":"+44 1838 200221",
    "sg:postcode":"PA33 1BD",
    "sg:province":"Argyll and Bute",
    "sg:tags":[
        "others"
    ],
    "wof:name":"GLEN ORCHY FARM",
    "wof:placetype":"venue"
},
  "geometry": {"coordinates":[-4.985869,56.401409],"type":"Point"}
}