{
  "type": "Feature",
  "properties": {
    "iso:country":"GB",
    "sg:address":"Ogmore Terrace",
    "sg:city":"Bridgend",
    "sg:classifiers":[
        {
            "category":"Communications",
            "subcategory":"Film & Video Production",
            "type":"Services"
        },
        {
            "category":"Wholesale",
            "subcategory":"Construction Materials",
            "type":"Manufacturing & Wholesale Goods"
        }
    ],
    "sg:phone":"+44 1656 655010",
    "sg:postcode":"CF31 1SU",
    "sg:province":"Bridgend",
    "sg:tags":[
        "merchant",
        "glass",
        "mirror"
    ],
    "wof:name":"PENYBONT GLASS PRODUCTS LTD",
    "wof:placetype":"venue"
},
  "geometry": {"coordinates":[-3.575014,51.507786],"type":"Point"}
}