{
  "type": "Feature",
  "properties": {
    "iso:country":"GB",
    "sg:address":"Unit 7 Warren House",
    "sg:city":"Aylesbury",
    "sg:classifiers":[
        {
            "category":"Professional",
            "subcategory":"Detective & Security Services",
            "type":"Services"
        },
        {
            "category":"Building & Trades",
            "subcategory":"Locksmith",
            "type":"Services"
        },
        {
            "category":"Organizations",
            "subcategory":"Non-profit Organization",
            "type":"Services"
        }
    ],
    "sg:postcode":"HP19 8DB",
    "sg:province":"Buckinghamshire",
    "sg:tags":[
        "alarm",
        "system"
    ],
    "wof:name":"Security Matters Ltd.",
    "wof:placetype":"venue"
},
  "geometry": {"coordinates":[-0.8443890214,51.8231887817],"type":"Point"}
}