{
  "type": "Feature",
  "properties": {
    "addr:full":"The Street, Kettleburgh Woodbridge Suffolk IP13 7JP",
    "addr:postcode":"ip13 7jp",
    "addr:street":"The Street",
    "iso:country":"GB",
    "sg:address":"The Street, Kettleburgh",
    "sg:city":"Woodbridge",
    "sg:classifiers":[
        {
            "category":"Government",
            "subcategory":"Post Office",
            "type":"Public Place"
        }
    ],
    "sg:phone":"+44 1728 723657",
    "sg:postcode":"IP13 7JP",
    "sg:province":"Suffolk",
    "wof:name":"KETTLEBURGH POST OFFICE",
    "wof:placetype":"venue"
},
  "geometry": {"coordinates":[1.2946759462,52.1600646973],"type":"Point"}
}