{
  "type": "Feature",
  "properties": {
    "iso:country":"GB",
    "sg:address":"106 Beckenham Road",
    "sg:city":"Beckenham",
    "sg:classifiers":[
        {
            "category":"Sports & Exercise",
            "subcategory":"Sports Center",
            "type":"Entertainment"
        }
    ],
    "sg:phone":"+44 20 8663 0630",
    "sg:postcode":"BR3 4RH",
    "sg:province":"Kent",
    "sg:tags":[
        "shop",
        "good"
    ],
    "wof:name":"The Runners Shop",
    "wof:placetype":"venue"
},
  "geometry": {"coordinates":[-0.043039,51.409389],"type":"Point"}
}