{
  "type": "Feature",
  "properties": {
    "addr:full":"34 Acton Street Stoke-on-trent Staffordshire ST1 6NX",
    "addr:housenumber":"34",
    "addr:postcode":"st1 6nx",
    "addr:street":"Acton Street",
    "iso:country":"GB",
    "sg:address":"34 Acton Street",
    "sg:city":"Stoke-on-trent",
    "sg:classifiers":[
        {
            "category":"Personal",
            "subcategory":"Barber",
            "type":"Services"
        }
    ],
    "sg:phone":"+44 1782 263644",
    "sg:postcode":"ST1 6NX",
    "sg:province":"Staffordshire",
    "sg:tags":[
        "men's",
        "hairdresser"
    ],
    "wof:name":"Giovanni of Italy",
    "wof:placetype":"venue"
},
  "geometry": {"coordinates":[-2.1683828831,53.0346221924],"type":"Point"}
}