{
  "type": "Feature",
  "properties": {
    "addr:full":"6 The Big Peg, Warstone Lane Birmingham West Midlands B18 6NA",
    "addr:housenumber":"6",
    "addr:postcode":"b18 6na",
    "addr:street":"The;Warstone Lane",
    "iso:country":"GB",
    "sg:address":"6 The Big Peg, Warstone Lane",
    "sg:city":"Birmingham",
    "sg:classifiers":[
        {
            "category":"Personal",
            "subcategory":"Beauty Salon",
            "type":"Services"
        },
        {
            "category":"Personal",
            "subcategory":"Barber",
            "type":"Services"
        }
    ],
    "sg:phone":"+44 121 236 8081",
    "sg:postcode":"B18 6NA",
    "sg:province":"West Midlands",
    "sg:tags":[
        "unisex",
        "hairdresser"
    ],
    "wof:name":"HAIR CITY ONE",
    "wof:placetype":"venue"
},
  "geometry": {"coordinates":[-1.914723,52.487774],"type":"Point"}
}