{
  "type": "Feature",
  "properties": {
    "iso:country":"GB",
    "sg:address":"Cobbetts, Station Road",
    "sg:city":"Pulborough",
    "sg:classifiers":[
        {
            "category":"Real Estate",
            "subcategory":"Developer",
            "type":"Services"
        }
    ],
    "sg:phone":"+44 1798 873902",
    "sg:postcode":"RH20 1AH",
    "sg:province":"West Sussex",
    "sg:tags":[
        "property"
    ],
    "wof:name":"Cobbetts Developments Ltd.",
    "wof:placetype":"venue"
},
  "geometry": {"coordinates":[-0.514909,50.957394],"type":"Point"}
}