{
  "type": "Feature",
  "properties": {
    "iso:country":"GB",
    "sg:address":"140 Portway, Stratford",
    "sg:city":"London",
    "sg:classifiers":[
        {
            "category":"Wholesale",
            "subcategory":"Office Equipment",
            "type":"Manufacturing & Wholesale Goods"
        },
        {
            "category":"Social Services",
            "subcategory":"Job Training",
            "type":"Services"
        }
    ],
    "sg:phone":"+44 20 8472 4157",
    "sg:postcode":"E15 3QW",
    "sg:province":"Greater London",
    "sg:tags":[
        "epos",
        "register",
        "cash",
        "accessory"
    ],
    "wof:name":"Romar & Co",
    "wof:placetype":"venue"
},
  "geometry": {"coordinates":[0.015651,51.536907],"type":"Point"}
}