{
  "type": "Feature",
  "properties": {
    "iso:country":"GB",
    "sg:address":"14 Beresford Road",
    "sg:city":"North Shields",
    "sg:classifiers":[
        {
            "category":"Building & Trades",
            "subcategory":"Cleaning & Sanitation",
            "type":"Services"
        }
    ],
    "sg:phone":"+44 191 297 1738",
    "sg:postcode":"NE30 3JQ",
    "sg:province":"Tyne and Wear",
    "sg:tags":[
        "cleaner",
        "window"
    ],
    "wof:name":"David Carr",
    "wof:placetype":"venue"
},
  "geometry": {"coordinates":[-1.4462430477,55.0328865051],"type":"Point"}
}