{
  "type": "Feature",
  "properties": {
    "addr:full":"60 Poulton Road Wallasey Merseyside CH44 9DH",
    "addr:housenumber":"60",
    "addr:postcode":"ch44 9dh",
    "addr:street":"Poulton Road",
    "iso:country":"GB",
    "sg:address":"60 Poulton Road",
    "sg:city":"Wallasey",
    "sg:classifiers":[
        {
            "category":"Building & Trades",
            "subcategory":"Construction",
            "type":"Services"
        }
    ],
    "sg:phone":"+44 151 638 4865",
    "sg:postcode":"CH44 9DH",
    "sg:province":"Merseyside",
    "sg:tags":[
        "glazier"
    ],
    "wof:name":"Picton Glass & Joinery",
    "wof:placetype":"venue"
},
  "geometry": {"coordinates":[-3.029098,53.412159],"type":"Point"}
}