{
  "type": "Feature",
  "properties": {
    "addr:full":"The Cross, Burley Ringwood Dorset BH24 4AB",
    "addr:postcode":"bh24 4ab",
    "addr:street":"The Cross",
    "iso:country":"GB",
    "sg:address":"The Cross, Burley",
    "sg:city":"Ringwood",
    "sg:classifiers":[
        {
            "category":"Shopping",
            "subcategory":"Department Store",
            "type":"Retail Goods"
        },
        {
            "category":"Shopping",
            "subcategory":"Gifts & Souvenirs",
            "type":"Retail Goods"
        }
    ],
    "sg:postcode":"BH24 4AB",
    "sg:province":"Dorset",
    "sg:tags":[
        "shop"
    ],
    "wof:name":"Soreceress Apprentice",
    "wof:placetype":"venue"
},
  "geometry": {"coordinates":[-1.7000050545,50.8272438049],"type":"Point"}
}