{
  "type": "Feature",
  "properties": {
    "iso:country":"GB",
    "sg:address":"Aylsham, Borlum Bridge, Drumnadrochit",
    "sg:city":"Inverness",
    "sg:classifiers":[
        {
            "category":"Landmark",
            "subcategory":"Tourist Information",
            "type":"Public Place"
        }
    ],
    "sg:phone":"+44 1456 450550",
    "sg:postcode":"IV63 6UN",
    "sg:province":"Highland",
    "sg:tags":[
        "tour",
        "guide",
        "sightseeing"
    ],
    "wof:name":"Loch Ness Travel",
    "wof:placetype":"venue"
},
  "geometry": {"coordinates":[-4.480116,57.330429],"type":"Point"}
}