{
  "type": "Feature",
  "properties": {
    "addr:full":"High Farm, Front Street, Great Lumley Chester-le-street Durham DH3 4JE",
    "addr:postcode":"dh3 4je",
    "addr:street":"High;Front Street;Chester-Le-Street",
    "iso:country":"GB",
    "sg:address":"High Farm, Front Street, Great Lumley",
    "sg:city":"Chester-le-street",
    "sg:classifiers":[
        {
            "category":"Professional",
            "subcategory":"Computer Services",
            "type":"Services"
        }
    ],
    "sg:postcode":"DH3 4JE",
    "sg:province":"Durham",
    "sg:tags":[
        "consultant"
    ],
    "wof:name":"Dualage Services Ltd.",
    "wof:placetype":"venue"
},
  "geometry": {"coordinates":[-1.5408960581,54.8365859985],"type":"Point"}
}