{
  "type": "Feature",
  "properties": {
    "iso:country":"GB",
    "sg:address":"20 Sycamore Lane, Bretton",
    "sg:city":"Wakefield",
    "sg:classifiers":[
        {
            "category":"Farming",
            "subcategory":"Dairy Farm",
            "type":"Manufacturing & Wholesale Goods"
        },
        {
            "category":"Farming",
            "subcategory":"Livestock Farm",
            "type":"Manufacturing & Wholesale Goods"
        }
    ],
    "sg:phone":"+44 1924 830231",
    "sg:postcode":"WF4 4JZ",
    "sg:province":"West Yorkshire",
    "sg:tags":[
        "others",
        "farmer"
    ],
    "wof:name":"B & R Cotterill",
    "wof:placetype":"venue"
},
  "geometry": {"coordinates":[-1.5656960011,53.6195831299],"type":"Point"}
}