{
  "type": "Feature",
  "properties": {
    "addr:full":"1a Longacres St Albans Hertfordshire AL4 0DJ",
    "addr:housenumber":"1a",
    "addr:postcode":"al4 0dj",
    "addr:street":"Longacres",
    "iso:country":"GB",
    "sg:address":"1a Longacres",
    "sg:city":"St Albans",
    "sg:classifiers":[
        {
            "category":"Professional",
            "subcategory":"Computer Services",
            "type":"Services"
        }
    ],
    "sg:phone":"+44 1727 860396",
    "sg:postcode":"AL4 0DJ",
    "sg:province":"Hertfordshire",
    "sg:tags":[
        "system",
        "software"
    ],
    "wof:name":"Neville & Co (Agencies)",
    "wof:placetype":"venue"
},
  "geometry": {"coordinates":[-0.2986269891,51.7517585754],"type":"Point"}
}