{
  "type": "Feature",
  "properties": {
    "iso:country":"GB",
    "sg:address":"121-129 Victoria Road",
    "sg:city":"Horley",
    "sg:classifiers":[
        {
            "category":"Professional",
            "type":"Services"
        }
    ],
    "sg:phone":"+44 1293 786100",
    "sg:postcode":"RH6 7AS",
    "sg:province":"Surrey",
    "sg:tags":[
        "caterer"
    ],
    "wof:name":"L S G Sky Chefs U K Ltd.",
    "wof:placetype":"venue"
},
  "geometry": {"coordinates":[-0.164921,51.172092],"type":"Point"}
}