{
  "type": "Feature",
  "properties": {
    "addr:full":"1 Thrushes Bush, High Laver Harlow Essex CM17 0NS",
    "addr:housenumber":"1",
    "addr:postcode":"cm17 0ns",
    "addr:street":"Thrushes Bush High Laver",
    "iso:country":"GB",
    "sg:address":"1 Thrushes Bush, High Laver",
    "sg:city":"Harlow",
    "sg:classifiers":[
        {
            "category":"Farming",
            "subcategory":"Poultry Farm",
            "type":"Manufacturing & Wholesale Goods"
        }
    ],
    "sg:postcode":"CM17 0NS",
    "sg:province":"Essex",
    "sg:tags":[
        "game"
    ],
    "wof:name":"Edmunds,M F & A,",
    "wof:placetype":"venue"
},
  "geometry": {"coordinates":[0.1732500046,51.7615509033],"type":"Point"}
}