{
  "type": "Feature",
  "properties": {
    "addr:full":"2 Princes Building Bath Bath and North East Somerset BA1 2ED",
    "addr:housenumber":"2",
    "addr:postcode":"ba1 2ed",
    "addr:street":"Princes Building Bath",
    "iso:country":"GB",
    "sg:address":"2 Princes Building",
    "sg:city":"Bath",
    "sg:classifiers":[
        {
            "category":"Communications",
            "type":"Services"
        }
    ],
    "sg:postcode":"BA1 2ED",
    "sg:province":"Bath and North East Somerset",
    "sg:tags":[
        "data",
        "network"
    ],
    "wof:name":"Crew 90 Ltd.",
    "wof:placetype":"venue"
},
  "geometry": {"coordinates":[-2.363927,51.382381],"type":"Point"}
}