{
  "type": "Feature",
  "properties": {
    "addr:full":"80 New Street, Town Centre West Bromwich West Midlands B70 7QA",
    "addr:housenumber":"80",
    "addr:postcode":"b70 7qa",
    "addr:street":"New Street",
    "iso:country":"GB",
    "sg:address":"80 New Street, Town Centre",
    "sg:city":"West Bromwich",
    "sg:classifiers":[
        {
            "category":"Retail",
            "subcategory":"Funeral Services",
            "type":"Services"
        }
    ],
    "sg:postcode":"B70 7QA",
    "sg:province":"West Midlands",
    "wof:name":"George Webb & Son",
    "wof:placetype":"venue"
},
  "geometry": {"coordinates":[-1.989776,52.520741],"type":"Point"}
}