{
  "type": "Feature",
  "properties": {
    "iso:country":"GB",
    "sg:address":"Ground Floor, Annexe Christchurch House",
    "sg:city":"Coventry",
    "sg:classifiers":[
        {
            "category":"Social Services",
            "type":"Services"
        }
    ],
    "sg:phone":"+44 24 7663 3066",
    "sg:postcode":"CV1 2GA",
    "sg:province":"West Midlands",
    "sg:tags":[
        "health",
        "authority"
    ],
    "wof:name":"Health Promotion Services",
    "wof:placetype":"venue"
},
  "geometry": {"coordinates":[-1.5077680349,52.4069862366],"type":"Point"}
}