{
  "type": "Feature",
  "properties": {
    "addr:full":"44 Palmerston Road Aberdeen Aberdeen City AB1 2QN",
    "addr:housenumber":"44",
    "addr:postcode":"ab1 2qn",
    "addr:street":"Palmerston Road",
    "iso:country":"GB",
    "sg:address":"44 Palmerston Road",
    "sg:city":"Aberdeen",
    "sg:classifiers":[
        {
            "category":"Food & Beverages",
            "subcategory":"Meat & Fish",
            "type":"Retail Goods"
        }
    ],
    "sg:phone":"+44 1224 571073",
    "sg:postcode":"AB1 2QN",
    "sg:province":"Aberdeen City",
    "sg:tags":[
        "merchant"
    ],
    "wof:name":"Gar Fish Ltd.",
    "wof:placetype":"venue"
},
  "geometry": {"coordinates":[-2.096715,57.140759],"type":"Point"}
}