{
  "type": "Feature",
  "properties": {
    "iso:country":"GB",
    "sg:address":"Spalding Road Business Park",
    "sg:city":"Bourne",
    "sg:classifiers":[
        {
            "category":"Real Estate",
            "subcategory":"Real Estate Operator",
            "type":"Services"
        },
        {
            "category":"Freight",
            "type":"Transportation"
        }
    ],
    "sg:phone":"+44 1778 425640",
    "sg:postcode":"PE10 9LF",
    "sg:province":"Lincolnshire",
    "sg:tags":[
        "haulage",
        "letting",
        "agent",
        "road"
    ],
    "wof:name":"Bradshaws Haulage",
    "wof:placetype":"venue"
},
  "geometry": {"coordinates":[-0.3688639998,52.7660255432],"type":"Point"}
}