{
  "type": "Feature",
  "properties": {
    "iso:country":"GB",
    "sg:address":"119 Merton Rd",
    "sg:city":"London",
    "sg:classifiers":[
        {
            "category":"Shopping",
            "subcategory":"Department Store",
            "type":"Retail Goods"
        }
    ],
    "sg:postcode":"SW19 1ED",
    "sg:province":"Greater London",
    "wof:name":"Gathergood,A,",
    "wof:placetype":"venue"
},
  "geometry": {"coordinates":[-0.194113,51.41935],"type":"Point"}
}