{
  "type": "Feature",
  "properties": {
    "addr:full":"Breakwater Road Bude Cornwall EX23 8SD",
    "addr:postcode":"ex23 8sd",
    "addr:street":"Breakwater Road",
    "iso:country":"GB",
    "sg:address":"Breakwater Road",
    "sg:city":"Bude",
    "sg:classifiers":[
        {
            "category":"Travel",
            "subcategory":"Hotels & Motels",
            "type":"Entertainment"
        }
    ],
    "sg:phone":"+44 1288 352005",
    "sg:postcode":"EX23 8SD",
    "sg:province":"Cornwall",
    "wof:name":"Falcon Hotel",
    "wof:placetype":"venue"
},
  "geometry": {"coordinates":[-4.5499157906,50.8283576965],"type":"Point"}
}