{
  "type": "Feature",
  "properties": {
    "iso:country":"GB",
    "sg:address":"27 Lineholt Close, Oakenshaw",
    "sg:city":"Redditch",
    "sg:classifiers":[
        {
            "category":"Manufacturing",
            "subcategory":"Petroleum Products",
            "type":"Manufacturing & Wholesale Goods"
        }
    ],
    "sg:phone":"+44 1527 403645",
    "sg:postcode":"B98 7YT",
    "sg:province":"Warwickshire",
    "sg:tags":[
        "double",
        "glazing"
    ],
    "wof:name":"Alvista Systems Ltd",
    "wof:placetype":"venue"
},
  "geometry": {"coordinates":[-1.922704,52.281418],"type":"Point"}
}