{
  "type": "Feature",
  "properties": {
    "iso:country":"GB",
    "sg:address":"155 North Street",
    "sg:city":"Bristol",
    "sg:classifiers":[
        {
            "category":"Personal",
            "type":"Services"
        }
    ],
    "sg:phone":"+44 117 963 4884",
    "sg:postcode":"BS3 1EZ",
    "sg:province":"City of Bristol",
    "sg:tags":[
        "tailor"
    ],
    "wof:name":"Salvatore Tailoring",
    "wof:placetype":"venue"
},
  "geometry": {"coordinates":[-2.602129,51.441349],"type":"Point"}
}