{
  "type": "Feature",
  "properties": {
    "addr:full":"439 Old London Road Hastings East Sussex TN35 5BH",
    "addr:housenumber":"439",
    "addr:postcode":"tn35 5bh",
    "addr:street":"Old London Road",
    "iso:country":"GB",
    "sg:address":"439 Old London Road",
    "sg:city":"Hastings",
    "sg:classifiers":[
        {
            "category":"Shopping",
            "subcategory":"Florist",
            "type":"Retail Goods"
        }
    ],
    "sg:postcode":"TN35 5BH",
    "sg:province":"East Sussex",
    "wof:name":"Ore Village Florists",
    "wof:placetype":"venue"
},
  "geometry": {"coordinates":[0.6094959974,50.8735733032],"type":"Point"}
}