{
  "type": "Feature",
  "properties": {
    "iso:country":"GB",
    "sg:address":"Chapleton",
    "sg:city":"Arbroath",
    "sg:classifiers":[
        {
            "category":"Manufacturing",
            "subcategory":"Metals",
            "type":"Manufacturing & Wholesale Goods"
        }
    ],
    "sg:postcode":"DD11 4RP",
    "sg:province":"Angus",
    "sg:tags":[
        "blacksmith",
        "forgemasters"
    ],
    "wof:name":"D N & R Cameron",
    "wof:placetype":"venue"
},
  "geometry": {"coordinates":[-2.617503,56.594402],"type":"Point"}
}