{
  "type": "Feature",
  "properties": {
    "iso:country":"GB",
    "sg:address":"56 Market Street, Hoylake",
    "sg:city":"Wirral",
    "sg:classifiers":[
        {
            "category":"Real Estate",
            "subcategory":"Real Estate Agent",
            "type":"Services"
        }
    ],
    "sg:phone":"+44 151 632 5901",
    "sg:postcode":"CH47 3BB",
    "sg:province":"Merseyside",
    "wof:name":"Michael L Green Estate Agents",
    "wof:placetype":"venue"
},
  "geometry": {"coordinates":[-3.1757090092,53.3938789368],"type":"Point"}
}