{
  "type": "Feature",
  "properties": {
    "addr:full":"1a Elmwood Avenue Hockley Essex SS5 4ND",
    "addr:housenumber":"1a",
    "addr:postcode":"ss5 4nd",
    "addr:street":"Elmwood Avenue",
    "iso:country":"GB",
    "sg:address":"1a Elmwood Avenue",
    "sg:city":"Hockley",
    "sg:classifiers":[
        {
            "category":"Building & Trades",
            "subcategory":"Construction",
            "type":"Services"
        }
    ],
    "sg:phone":"+44 1702 203639",
    "sg:postcode":"SS5 4ND",
    "sg:province":"Essex",
    "sg:tags":[
        "builder"
    ],
    "wof:name":"Wilson & Coker",
    "wof:placetype":"venue"
},
  "geometry": {"coordinates":[0.661386013,51.5942497253],"type":"Point"}
}