{
  "type": "Feature",
  "properties": {
    "addr:full":"45 Thames Drive Leigh-on-sea Essex SS9 2XQ",
    "addr:housenumber":"45",
    "addr:postcode":"ss9 2xq",
    "addr:street":"Thames Drive Leigh-On-Sea",
    "iso:country":"GB",
    "sg:address":"45 Thames Drive",
    "sg:city":"Leigh-on-sea",
    "sg:classifiers":[
        {
            "category":"Professional",
            "subcategory":"Management & Consulting",
            "type":"Services"
        }
    ],
    "sg:phone":"+44 1702 716384",
    "sg:postcode":"SS9 2XQ",
    "sg:province":"Essex",
    "sg:tags":[
        "fire",
        "consultant",
        "protection"
    ],
    "wof:name":"Williams Fire & Hazard Control Inc",
    "wof:placetype":"venue"
},
  "geometry": {"coordinates":[0.6302829981,51.5465316772],"type":"Point"}
}