{
  "type": "Feature",
  "properties": {
    "addr:full":"Butchers Shops, Dorington Shrewsbury Shropshire SY5 7JD",
    "addr:postcode":"sy5 7jd",
    "addr:street":"Dorington",
    "iso:country":"GB",
    "sg:address":"Butchers Shops, Dorington",
    "sg:city":"Shrewsbury",
    "sg:classifiers":[
        {
            "category":"Food & Beverages",
            "subcategory":"Meat & Fish",
            "type":"Retail Goods"
        }
    ],
    "sg:phone":"+44 1743 718215",
    "sg:postcode":"SY5 7JD",
    "sg:province":"Shropshire",
    "sg:tags":[
        "butcher"
    ],
    "wof:name":"C G Sadd",
    "wof:placetype":"venue"
},
  "geometry": {"coordinates":[-2.76972,52.620468],"type":"Point"}
}