{
  "type": "Feature",
  "properties": {
    "iso:country":"GB",
    "sg:address":"50 Westways, Bedhampton",
    "sg:city":"Havant",
    "sg:classifiers":[
        {
            "category":"Manufacturing",
            "subcategory":"Paper Products",
            "type":"Manufacturing & Wholesale Goods"
        }
    ],
    "sg:phone":"+44 23 9247 5156",
    "sg:postcode":"PO9 3LN",
    "sg:province":"Hampshire",
    "sg:tags":[
        "cardboard"
    ],
    "wof:name":"Peter E Wright",
    "wof:placetype":"venue"
},
  "geometry": {"coordinates":[-1.006569,50.858238],"type":"Point"}
}