{
  "type": "Feature",
  "properties": {
    "iso:country":"GB",
    "sg:address":"Broomhill Health Centre, Hadston Rd",
    "sg:city":"Morpeth",
    "sg:classifiers":[
        {
            "category":"Health Services",
            "subcategory":"Doctor",
            "type":"Services"
        }
    ],
    "sg:phone":"+44 1670 760229",
    "sg:postcode":"NE65 9SF",
    "sg:province":"Northumberland",
    "sg:tags":[
        "practitioners"
    ],
    "wof:name":"Watkins, G W",
    "wof:placetype":"venue"
},
  "geometry": {"coordinates":[-1.592879,55.295349],"type":"Point"}
}