{
  "type": "Feature",
  "properties": {
    "iso:country":"GB",
    "sg:address":"Rufus Court Row, Northgate St",
    "sg:city":"Chester",
    "sg:classifiers":[
        {
            "category":"Banks & Credit Unions",
            "subcategory":"Bank",
            "type":"Services"
        }
    ],
    "sg:phone":"+44 1244 401150",
    "sg:postcode":"CH1 2JB",
    "sg:province":"Cheshire",
    "sg:tags":[
        "broker",
        "mortgage"
    ],
    "wof:name":"Homelink Mortgage Services",
    "wof:placetype":"venue"
},
  "geometry": {"coordinates":[-2.892994,53.193668],"type":"Point"}
}