{
  "type": "Feature",
  "properties": {
    "addr:full":"31 Linefield Road Carnoustie Angus DD7 6DP",
    "addr:housenumber":"31",
    "addr:postcode":"dd7 6dp",
    "addr:street":"Linefield Road",
    "iso:country":"GB",
    "sg:address":"31 Linefield Road",
    "sg:city":"Carnoustie",
    "sg:classifiers":[
        {
            "category":"Health Services",
            "subcategory":"Podiatrist",
            "type":"Services"
        }
    ],
    "sg:phone":"+44 1241 853634",
    "sg:postcode":"DD7 6DP",
    "sg:province":"Angus",
    "sg:tags":[
        "podiatrists",
        "chiropodist"
    ],
    "wof:name":"Alexander Robertson Ramsay",
    "wof:placetype":"venue"
},
  "geometry": {"coordinates":[-2.6984069347,56.5064849854],"type":"Point"}
}