{
  "type": "Feature",
  "properties": {
    "addr:full":"12 - 14 Westbury Drive Brentwood Essex CM14 4JZ",
    "addr:housenumber":"14",
    "addr:postcode":"cm14 4jz",
    "addr:street":"Westbury Drive",
    "iso:country":"GB",
    "sg:address":"12 - 14 Westbury Drive",
    "sg:city":"Brentwood",
    "sg:classifiers":[
        {
            "category":"Professional",
            "subcategory":"Secretarial Services",
            "type":"Services"
        }
    ],
    "sg:postcode":"CM14 4JZ",
    "sg:province":"Essex",
    "wof:name":"The E T S Business Centre",
    "wof:placetype":"venue"
},
  "geometry": {"coordinates":[0.295615,51.617867],"type":"Point"}
}