{
  "type": "Feature",
  "properties": {
    "addr:full":"Sycamore Court, Robert Hall Street Leicester Leicestershire LE4 5RB",
    "addr:postcode":"le4 5rb",
    "addr:street":"Sycamore Court Robert Hall Street",
    "iso:country":"GB",
    "sg:address":"Sycamore Court, Robert Hall Street",
    "sg:city":"Leicester",
    "sg:classifiers":[
        {
            "category":"Organizations",
            "subcategory":"Community Association",
            "type":"Services"
        }
    ],
    "sg:phone":"+44 116 261 0663",
    "sg:postcode":"LE4 5RB",
    "sg:province":"Leicestershire",
    "sg:tags":[
        "co-operatives",
        "society",
        "housing",
        "trust"
    ],
    "sg:website":"http://www.lha.org.uk",
    "wof:name":"Leicester Housing Association Ltd",
    "wof:placetype":"venue"
},
  "geometry": {"coordinates":[-1.129275,52.658688],"type":"Point"}
}