{
  "type": "Feature",
  "properties": {
    "addr:full":"6 Crescent Rd Southport Lancashire PR8 4SR",
    "addr:housenumber":"6",
    "addr:postcode":"pr8 4sr",
    "addr:street":"Crescent Rd",
    "iso:country":"GB",
    "sg:address":"6 Crescent Rd",
    "sg:city":"Southport",
    "sg:classifiers":[
        {
            "category":"Professional",
            "subcategory":"Computer Services",
            "type":"Services"
        }
    ],
    "sg:phone":"+44 1704 563553",
    "sg:postcode":"PR8 4SR",
    "sg:province":"Lancashire",
    "sg:tags":[
        "consultant"
    ],
    "wof:name":"Gary Cardus Enterprises",
    "wof:placetype":"venue"
},
  "geometry": {"coordinates":[-3.012789,53.62965],"type":"Point"}
}