{
  "type": "Feature",
  "properties": {
    "addr:full":"Cae Coch, Llanrhaeadr Denbigh Conwy LL16 4NP",
    "addr:postcode":"ll16 4np",
    "addr:street":"Llanrhaeadr",
    "iso:country":"GB",
    "sg:address":"Cae Coch, Llanrhaeadr",
    "sg:city":"Denbigh",
    "sg:classifiers":[
        {
            "category":"Farming",
            "subcategory":"Livestock Farm",
            "type":"Manufacturing & Wholesale Goods"
        }
    ],
    "sg:phone":"+44 1745 890285",
    "sg:postcode":"LL16 4NP",
    "sg:province":"Conwy",
    "sg:tags":[
        "others"
    ],
    "wof:name":"H T Roberts",
    "wof:placetype":"venue"
},
  "geometry": {"coordinates":[-3.373324,53.159065],"type":"Point"}
}