{
  "type": "Feature",
  "properties": {
    "addr:full":"Eastside, Scotch Corner Richmond North Yorkshire DL10 6NS",
    "addr:postcode":"dl10 6ns",
    "addr:street":"Corner",
    "iso:country":"GB",
    "sg:address":"Eastside, Scotch Corner",
    "sg:city":"Richmond",
    "sg:classifiers":[
        {
            "category":"Autos & Motor Vehicles",
            "subcategory":"Auto Supplies",
            "type":"Retail Goods"
        }
    ],
    "sg:phone":"+44 1748 850469",
    "sg:postcode":"DL10 6NS",
    "sg:province":"North Yorkshire",
    "sg:tags":[
        "towing",
        "eqpt",
        "trailer"
    ],
    "wof:name":"Northern Trailer Sales Ltd.",
    "wof:placetype":"venue"
},
  "geometry": {"coordinates":[-1.666507,54.442867],"type":"Point"}
}