{
  "type": "Feature",
  "properties": {
    "addr:full":"52 Ashbourne Drive Pontefract North Yorkshire WF8 3RA",
    "addr:housenumber":"52",
    "addr:postcode":"wf8 3ra",
    "addr:street":"Ashbourne Drive",
    "iso:country":"GB",
    "sg:address":"52 Ashbourne Drive",
    "sg:city":"Pontefract",
    "sg:classifiers":[
        {
            "category":"Building & Trades",
            "subcategory":"Construction",
            "type":"Services"
        }
    ],
    "sg:phone":"+44 1977 799917",
    "sg:postcode":"WF8 3RA",
    "sg:province":"North Yorkshire",
    "sg:tags":[
        "contractor",
        "paving",
        "driveway"
    ],
    "wof:name":"County Paving Ltd",
    "wof:placetype":"venue"
},
  "geometry": {"coordinates":[-1.3078540564,53.6773529053],"type":"Point"}
}