{
  "type": "Feature",
  "properties": {
    "addr:full":"27-28 Sun Street Hitchin Bedfordshire SG5 1AH",
    "addr:housenumber":"27-28",
    "addr:postcode":"sg5 1ah",
    "addr:street":"Sun Street",
    "iso:country":"GB",
    "sg:address":"27-28 Sun Street",
    "sg:city":"Hitchin",
    "sg:classifiers":[
        {
            "category":"Shopping",
            "subcategory":"Stationery & Office Supplies",
            "type":"Retail Goods"
        }
    ],
    "sg:phone":"+44 1462 420209",
    "sg:postcode":"SG5 1AH",
    "sg:province":"Bedfordshire",
    "sg:tags":[
        "item",
        "promotional"
    ],
    "wof:name":"Laserart Promotions",
    "wof:placetype":"venue"
},
  "geometry": {"coordinates":[-0.278876,51.946747],"type":"Point"}
}