{
  "type": "Feature",
  "properties": {
    "addr:full":"229 Powder Mill Lane Twickenham Greater London TW2 6EH",
    "addr:housenumber":"229",
    "addr:postcode":"tw2 6eh",
    "addr:street":"Powder Mill Lane",
    "iso:country":"GB",
    "sg:address":"229 Powder Mill Lane",
    "sg:city":"Twickenham",
    "sg:classifiers":[
        {
            "category":"Retail",
            "subcategory":"Laundry & Dry Cleaning",
            "type":"Services"
        }
    ],
    "sg:phone":"+44 20 8296 9069",
    "sg:postcode":"TW2 6EH",
    "sg:province":"Greater London",
    "sg:tags":[
        "alteration"
    ],
    "wof:name":"Quality Cleaners",
    "wof:placetype":"venue"
},
  "geometry": {"coordinates":[-0.378624,51.449287],"type":"Point"}
}