{
  "type": "Feature",
  "properties": {
    "addr:full":"403 Central Dr Blackpool Lancashire FY1 6LE",
    "addr:housenumber":"403",
    "addr:postcode":"fy1 6le",
    "addr:street":"Central Dr",
    "iso:country":"GB",
    "sg:address":"403 Central Dr",
    "sg:city":"Blackpool",
    "sg:classifiers":[
        {
            "category":"Food & Beverages",
            "subcategory":"Fruits & Vegetables",
            "type":"Retail Goods"
        }
    ],
    "sg:postcode":"FY1 6LE",
    "sg:province":"Lancashire",
    "sg:tags":[
        "greengrocer"
    ],
    "wof:name":"Donnelly,Jim,",
    "wof:placetype":"venue"
},
  "geometry": {"coordinates":[-3.045286,53.803864],"type":"Point"}
}