{
  "type": "Feature",
  "properties": {
    "iso:country":"GB",
    "sg:address":"20 Shelfield Lane",
    "sg:city":"Rochdale",
    "sg:classifiers":[
        {
            "category":"Professional",
            "subcategory":"Accounting & Tax Preparation",
            "type":"Services"
        }
    ],
    "sg:postcode":"OL11 5YD",
    "sg:province":"Lancashire",
    "sg:tags":[
        "accountant"
    ],
    "wof:name":"Stephen Hobson",
    "wof:placetype":"venue"
},
  "geometry": {"coordinates":[-2.203659,53.621532],"type":"Point"}
}