{
  "type": "Feature",
  "properties": {
    "addr:full":"17a Quarry Hill Road Tonbridge Kent TN9 2RN",
    "addr:housenumber":"17a",
    "addr:postcode":"tn9 2rn",
    "addr:street":"Quarry Hill Road",
    "iso:country":"GB",
    "sg:address":"17a Quarry Hill Road",
    "sg:city":"Tonbridge",
    "sg:classifiers":[
        {
            "category":"Real Estate",
            "subcategory":"Surveying",
            "type":"Services"
        }
    ],
    "sg:phone":"+44 1732 364261",
    "sg:postcode":"TN9 2RN",
    "sg:province":"Kent",
    "sg:tags":[
        "surveyor",
        "quantity"
    ],
    "wof:name":"Selby & Sanders",
    "wof:placetype":"venue"
},
  "geometry": {"coordinates":[0.2691760063,51.1897583008],"type":"Point"}
}