{
  "type": "Feature",
  "properties": {
    "iso:country":"GB",
    "sg:address":"Ardgoil, Whitelea Road",
    "sg:city":"Kilmacolm",
    "sg:classifiers":[
        {
            "category":"Manufacturing",
            "subcategory":"Lumber",
            "type":"Manufacturing & Wholesale Goods"
        }
    ],
    "sg:postcode":"PA13 4HH",
    "sg:province":"Inverclyde",
    "sg:tags":[
        "importer",
        "merchants",
        "agent",
        "timber"
    ],
    "wof:name":"Edmiston & Mitchells",
    "wof:placetype":"venue"
},
  "geometry": {"coordinates":[-4.6301999092,55.8926010132],"type":"Point"}
}