{
  "type": "Feature",
  "properties": {
    "iso:country":"GB",
    "sg:address":"25 Rutland Rd",
    "sg:city":"Bedford",
    "sg:classifiers":[
        {
            "category":"Autos & Motor Vehicles",
            "subcategory":"Motorcycle Sales",
            "type":"Retail Goods"
        }
    ],
    "sg:phone":"+44 1234 307529",
    "sg:postcode":"MK40 1DG",
    "sg:province":"Bedfordshire",
    "sg:tags":[
        "chauffeur",
        "driven",
        "car"
    ],
    "wof:name":"Dial A Ferrari Wedding Hire",
    "wof:placetype":"venue"
},
  "geometry": {"coordinates":[-0.475778,52.136253],"type":"Point"}
}