{
  "type": "Feature",
  "properties": {
    "iso:country":"GB",
    "sg:address":"44 Finkle Street",
    "sg:city":"Kendal",
    "sg:classifiers":[
        {
            "category":"Shopping",
            "subcategory":"Hobbies, Toys, & Games",
            "type":"Retail Goods"
        }
    ],
    "sg:phone":"+44 1539 723264",
    "sg:postcode":"LA9 4AB",
    "sg:province":"Cumbria",
    "sg:tags":[
        "shop",
        "toy",
        "sale"
    ],
    "wof:name":"O'LOUGHLIN'S",
    "wof:placetype":"venue"
},
  "geometry": {"coordinates":[-2.745604,54.328156],"type":"Point"}
}