{
  "type": "Feature",
  "properties": {
    "iso:country":"GB",
    "sg:address":"Mawr-dre, King St",
    "sg:city":"Northwich",
    "sg:classifiers":[
        {
            "category":"Building & Trades",
            "subcategory":"Construction",
            "type":"Services"
        }
    ],
    "sg:phone":"+44 1606 42149",
    "sg:postcode":"CW9 7RW",
    "sg:province":"Cheshire",
    "sg:tags":[
        "builder"
    ],
    "wof:name":"K A Robbins",
    "wof:placetype":"venue"
},
  "geometry": {"coordinates":[-2.5119988918,53.260471344],"type":"Point"}
}