{
  "type": "Feature",
  "properties": {
    "addr:full":"161 Turners Hill Waltham Cross Essex EN8 9BH",
    "addr:housenumber":"161",
    "addr:postcode":"en8 9bh",
    "addr:street":"Turners Hill Waltham Cross",
    "iso:country":"GB",
    "sg:address":"161 Turners Hill",
    "sg:city":"Waltham Cross",
    "sg:classifiers":[
        {
            "category":"Health Services",
            "subcategory":"Doctor",
            "type":"Services"
        }
    ],
    "sg:phone":"+44 1992 624696",
    "sg:postcode":"EN8 9BH",
    "sg:province":"Essex",
    "sg:tags":[
        "practitioners"
    ],
    "wof:name":"Sengupta, N",
    "wof:placetype":"venue"
},
  "geometry": {"coordinates":[-0.0344320014,51.7046089172],"type":"Point"}
}