{
  "type": "Feature",
  "properties": {
    "addr:full":"51-53 Laurel Gro Sunderland Tyne and Wear SR2 9EE",
    "addr:housenumber":"51-53",
    "addr:postcode":"sr2 9ee",
    "addr:street":"Laurel Gro",
    "iso:country":"GB",
    "sg:address":"51-53 Laurel Gro",
    "sg:city":"Sunderland",
    "sg:classifiers":[
        {
            "category":"Shopping",
            "subcategory":"News",
            "type":"Retail Goods"
        }
    ],
    "sg:phone":"+44 191 528 3984",
    "sg:postcode":"SR2 9EE",
    "sg:province":"Tyne and Wear",
    "sg:tags":[
        "newsagent"
    ],
    "wof:name":"M S Dhillon & Sons",
    "wof:placetype":"venue"
},
  "geometry": {"coordinates":[-1.386397,54.886139],"type":"Point"}
}