{
  "type": "Feature",
  "properties": {
    "iso:country":"GB",
    "sg:address":"Challaborough",
    "sg:city":"Kingsbridge",
    "sg:classifiers":[
        {
            "category":"Recreation",
            "subcategory":"Campground",
            "type":"Entertainment"
        }
    ],
    "sg:postcode":"TQ7 4HT",
    "sg:province":"Devon",
    "sg:tags":[
        "holiday",
        "centre",
        "camp"
    ],
    "wof:name":"Bigbury Bay Holiday Park",
    "wof:placetype":"venue"
},
  "geometry": {"coordinates":[-3.844585,50.315041],"type":"Point"}
}