{
  "type": "Feature",
  "properties": {
    "iso:country":"GB",
    "sg:address":"152 Park Road South",
    "sg:city":"Newton-le-willows",
    "sg:classifiers":[
        {
            "category":"Place Of Worship",
            "subcategory":"Synagogue",
            "type":"Public Place"
        }
    ],
    "sg:phone":"+44 1925 227211",
    "sg:postcode":"WA12 8HX",
    "sg:province":"Cheshire",
    "sg:tags":[
        "top",
        "sunroof",
        "vinyl"
    ],
    "wof:name":"Valentine Holdings Ltd",
    "wof:placetype":"venue"
},
  "geometry": {"coordinates":[-2.619491,53.450996],"type":"Point"}
}