{
  "type": "Feature",
  "properties": {
    "iso:country":"GB",
    "sg:address":"Brompton Ralph",
    "sg:city":"Taunton",
    "sg:classifiers":[
        {
            "category":"Government",
            "subcategory":"Post Office",
            "type":"Public Place"
        }
    ],
    "sg:phone":"+44 1984 623267",
    "sg:postcode":"TA4 2RU",
    "sg:province":"Devon",
    "wof:name":"Brompton Ralph Village Shop & Post Offic",
    "wof:placetype":"venue"
},
  "geometry": {"coordinates":[-3.3077299595,51.0820808411],"type":"Point"}
}