{
  "type": "Feature",
  "properties": {
    "addr:full":"10 Clive Avenue, Goring-by-sea Worthing West Sussex BN12 4SG",
    "addr:housenumber":"10",
    "addr:postcode":"bn12 4sg",
    "addr:street":"Clive Avenue",
    "iso:country":"GB",
    "sg:address":"10 Clive Avenue, Goring-by-sea",
    "sg:city":"Worthing",
    "sg:classifiers":[
        {
            "category":"Health Services",
            "subcategory":"Nursing And Care Facility",
            "type":"Services"
        }
    ],
    "sg:phone":"+44 1903 245550",
    "sg:postcode":"BN12 4SG",
    "sg:province":"West Sussex",
    "sg:tags":[
        "home"
    ],
    "wof:name":"Sussex Clinic Ltd.",
    "wof:placetype":"venue"
},
  "geometry": {"coordinates":[-0.424129,50.815079],"type":"Point"}
}