{
  "type": "Feature",
  "properties": {
    "iso:country":"GB",
    "sg:address":"9-10 Gabriels Hill",
    "sg:city":"Maidstone",
    "sg:classifiers":[
        {
            "category":"Shopping",
            "subcategory":"Department Store",
            "type":"Retail Goods"
        }
    ],
    "sg:phone":"+44 1622 691157",
    "sg:postcode":"ME15 6HL",
    "sg:province":"Kent",
    "wof:name":"Poundstop",
    "wof:placetype":"venue"
},
  "geometry": {"coordinates":[0.5233110189,51.2611999512],"type":"Point"}
}