{
  "type": "Feature",
  "properties": {
    "addr:full":"5-7 Eastfield Road Slough Berkshire SL1 7EH",
    "addr:housenumber":"5-7",
    "addr:postcode":"sl1 7eh",
    "addr:street":"Eastfield Road",
    "iso:country":"GB",
    "sg:address":"5-7 Eastfield Road",
    "sg:city":"Slough",
    "sg:classifiers":[
        {
            "category":"Manufacturing",
            "subcategory":"Metals",
            "type":"Manufacturing & Wholesale Goods"
        }
    ],
    "sg:phone":"+44 1628 662186",
    "sg:postcode":"SL1 7EH",
    "sg:province":"Berkshire",
    "sg:tags":[
        "fabricator",
        "aluminium",
        "mnfrs"
    ],
    "wof:name":"B D C Developments Ltd.",
    "wof:placetype":"venue"
},
  "geometry": {"coordinates":[-0.668704,51.52644],"type":"Point"}
}