{
  "type": "Feature",
  "properties": {
    "addr:full":"Tontine St Blackburn Lancashire BB1 7ED",
    "addr:postcode":"bb1 7ed",
    "addr:street":"Tontine St",
    "iso:country":"GB",
    "sg:address":"Tontine St",
    "sg:city":"Blackburn",
    "sg:classifiers":[
        {
            "category":"Autos & Motor Vehicles",
            "subcategory":"Auto Supplies",
            "type":"Retail Goods"
        }
    ],
    "sg:phone":"+44 1254 56348",
    "sg:postcode":"BB1 7ED",
    "sg:province":"Lancashire",
    "sg:tags":[
        "windscreen"
    ],
    "wof:name":"Auto Windscreens",
    "wof:placetype":"venue"
},
  "geometry": {"coordinates":[-2.4841279984,53.7514076233],"type":"Point"}
}