{
  "type": "Feature",
  "properties": {
    "addr:full":"3 Clarendon Ct Warrington Cheshire WA2 8QP",
    "addr:housenumber":"3",
    "addr:postcode":"wa2 8qp",
    "addr:street":"Clarendon Ct",
    "iso:country":"GB",
    "sg:address":"3 Clarendon Ct",
    "sg:city":"Warrington",
    "sg:classifiers":[
        {
            "category":"Recreation",
            "subcategory":"Water Park",
            "type":"Entertainment"
        }
    ],
    "sg:phone":"+44 1925 245183",
    "sg:postcode":"WA2 8QP",
    "sg:province":"Cheshire",
    "sg:tags":[
        "sport"
    ],
    "wof:name":"High Surf Jet Ski's",
    "wof:placetype":"venue"
},
  "geometry": {"coordinates":[-2.6076030731,53.4216957092],"type":"Point"}
}