{
  "type": "Feature",
  "properties": {
    "addr:full":"66 Burnham Drive, Whetstone Leicester Leicestershire LE8 6HY",
    "addr:housenumber":"66",
    "addr:postcode":"le8 6hy",
    "addr:street":"Burnham Drive",
    "iso:country":"GB",
    "sg:address":"66 Burnham Drive, Whetstone",
    "sg:city":"Leicester",
    "sg:classifiers":[
        {
            "category":"Manufacturing",
            "subcategory":"Metals",
            "type":"Manufacturing & Wholesale Goods"
        }
    ],
    "sg:phone":"+44 116 275 1598",
    "sg:postcode":"LE8 6HY",
    "sg:province":"Leicestershire",
    "sg:tags":[
        "die-casting"
    ],
    "wof:name":"DEMAN Services Company",
    "wof:placetype":"venue"
},
  "geometry": {"coordinates":[-1.1749960184,52.5630378723],"type":"Point"}
}