{
  "type": "Feature",
  "properties": {
    "addr:full":"10 St Peters Terr Bath Somerset BA2 3BU",
    "addr:housenumber":"10",
    "addr:postcode":"ba2 3bu",
    "addr:street":"St",
    "iso:country":"GB",
    "sg:address":"10 St Peters Terr",
    "sg:city":"Bath",
    "sg:classifiers":[
        {
            "category":"Government",
            "subcategory":"Post Office",
            "type":"Public Place"
        }
    ],
    "sg:phone":"+44 1225 425133",
    "sg:postcode":"BA2 3BU",
    "sg:province":"Somerset",
    "wof:name":"East Twerton Sub Post Office",
    "wof:placetype":"venue"
},
  "geometry": {"coordinates":[-2.371119,51.381031],"type":"Point"}
}