{
  "type": "Feature",
  "properties": {
    "addr:full":"35 Station Road Wolverhampton Shropshire WV8 1BY",
    "addr:housenumber":"35",
    "addr:postcode":"wv8 1by",
    "addr:street":"Station Road",
    "iso:country":"GB",
    "sg:address":"35 Station Road",
    "sg:city":"Wolverhampton",
    "sg:classifiers":[
        {
            "category":"Building & Trades",
            "subcategory":"Construction",
            "type":"Services"
        }
    ],
    "sg:phone":"+44 1902 844116",
    "sg:postcode":"WV8 1BY",
    "sg:province":"Shropshire",
    "sg:tags":[
        "builder"
    ],
    "wof:name":"Robert J Meyrick & Son",
    "wof:placetype":"venue"
},
  "geometry": {"coordinates":[-2.2014029026,52.6291236877],"type":"Point"}
}