{
  "type": "Feature",
  "properties": {
    "addr:full":"67-69 High St Liverpool Merseyside L15 8HE",
    "addr:housenumber":"67-69",
    "addr:postcode":"l15 8he",
    "addr:street":"High St",
    "iso:country":"GB",
    "sg:address":"67-69 High St",
    "sg:city":"Liverpool",
    "sg:classifiers":[
        {
            "category":"Restaurant",
            "type":"Food & Drink"
        }
    ],
    "sg:phone":"+44 151 734 4769",
    "sg:postcode":"L15 8HE",
    "sg:province":"Merseyside",
    "wof:name":"Cuffs",
    "wof:placetype":"venue"
},
  "geometry": {"coordinates":[-2.919089,53.398777],"type":"Point"}
}