{
  "type": "Feature",
  "properties": {
    "addr:full":"100 Alcester Street Birmingham West Midlands B12 0QB",
    "addr:housenumber":"100",
    "addr:postcode":"b12 0qb",
    "addr:street":"Alcester Street",
    "iso:country":"GB",
    "sg:address":"100 Alcester Street",
    "sg:city":"Birmingham",
    "sg:classifiers":[
        {
            "category":"Wholesale",
            "subcategory":"Sporting Goods",
            "type":"Manufacturing & Wholesale Goods"
        },
        {
            "category":"Parking",
            "subcategory":"Bicycle",
            "type":"Transportation"
        }
    ],
    "sg:phone":"+44 121 622 0180",
    "sg:postcode":"B12 0QB",
    "sg:province":"West Midlands",
    "sg:tags":[
        "wholesaler",
        "mnfrs",
        "manufacturer",
        "cycle"
    ],
    "wof:name":"Reece Cycles plc",
    "wof:placetype":"venue"
},
  "geometry": {"coordinates":[-1.887346983,52.4696578979],"type":"Point"}
}