{
  "type": "Feature",
  "properties": {
    "iso:country":"GB",
    "sg:address":"Clitheroe Rd",
    "sg:city":"Clitheroe",
    "sg:classifiers":[
        {
            "category":"Bars & Pubs",
            "type":"Food & Drink"
        }
    ],
    "sg:phone":"+44 1200 423262",
    "sg:postcode":"BB7 3HP",
    "sg:province":"Lancashire",
    "sg:tags":[
        "pubs",
        "inn"
    ],
    "wof:name":"Sun Inn The",
    "wof:placetype":"venue"
},
  "geometry": {"coordinates":[-2.4142789841,53.8909034729],"type":"Point"}
}