{
  "type": "Feature",
  "properties": {
    "addr:full":"Isd Finance Room 303, Mowden Hall Darlington Durham DL3 9BG",
    "addr:housenumber":"303",
    "addr:postcode":"dl3 9bg",
    "addr:street":"Mowden Hall",
    "iso:country":"GB",
    "sg:address":"Isd Finance Room 303, Mowden Hall",
    "sg:city":"Darlington",
    "sg:classifiers":[
        {
            "category":"Banks & Credit Unions",
            "subcategory":"Investment Brokerage",
            "type":"Services"
        },
        {
            "category":"Government",
            "subcategory":"Office",
            "type":"Public Place"
        }
    ],
    "sg:phone":"+44 1325 745745",
    "sg:postcode":"DL3 9BG",
    "sg:province":"Durham",
    "sg:tags":[
        "central",
        "pension"
    ],
    "wof:name":"Department for Education",
    "wof:placetype":"venue"
},
  "geometry": {"coordinates":[-1.5905599594,54.5325088501],"type":"Point"}
}