{
  "type": "Feature",
  "properties": {
    "addr:full":"30 Greystone Road, Penketh Warrington Cheshire WA5 2ER",
    "addr:housenumber":"30",
    "addr:postcode":"wa5 2er",
    "addr:street":"Greystone Road",
    "iso:country":"GB",
    "sg:address":"30 Greystone Road, Penketh",
    "sg:city":"Warrington",
    "sg:classifiers":[
        {
            "category":"Shopping",
            "type":"Retail Goods"
        }
    ],
    "sg:postcode":"WA5 2ER",
    "sg:province":"Cheshire",
    "sg:tags":[
        "bag"
    ],
    "wof:name":"Hall Packaging",
    "wof:placetype":"venue"
},
  "geometry": {"coordinates":[-2.654401,53.384781],"type":"Point"}
}