{
  "type": "Feature",
  "properties": {
    "addr:full":"1 Bishops Bridge, Saxilby Rd Lincoln Lincolnshire LN1 2BG",
    "addr:housenumber":"1",
    "addr:postcode":"ln1 2bg",
    "addr:street":"Bishops Bridge Saxilby Rd",
    "iso:country":"GB",
    "sg:address":"1 Bishops Bridge, Saxilby Rd",
    "sg:city":"Lincoln",
    "sg:classifiers":[
        {
            "category":"Health Services",
            "subcategory":"Chiropractor",
            "type":"Services"
        }
    ],
    "sg:phone":"+44 1522 521817",
    "sg:postcode":"LN1 2BG",
    "sg:province":"Lincolnshire",
    "wof:name":"Andrea Barr M.R.S.S",
    "wof:placetype":"venue"
},
  "geometry": {"coordinates":[-0.655976,53.271435],"type":"Point"}
}