{
  "type": "Feature",
  "properties": {
    "addr:full":"140-141 Western International Mk, T Southall Greater London UB2 5XF",
    "addr:housenumber":"140-141",
    "addr:postcode":"ub2 5xf",
    "addr:street":"Western International Mk T Southall",
    "iso:country":"GB",
    "sg:address":"140-141 Western International Mk, T",
    "sg:city":"Southall",
    "sg:classifiers":[
        {
            "category":"Food & Beverages",
            "subcategory":"Groceries & Convenience Stores",
            "type":"Retail Goods"
        }
    ],
    "sg:phone":"+44 20 8848 4537",
    "sg:postcode":"UB2 5XF",
    "sg:province":"Greater London",
    "sg:tags":[
        "merchant",
        "potato"
    ],
    "wof:name":"J H Bridges",
    "wof:placetype":"venue"
},
  "geometry": {"coordinates":[-0.39019,51.500015],"type":"Point"}
}