{
  "type": "Feature",
  "properties": {
    "addr:full":"Foundry Garage Trimdon Station Durham TS29 6AP",
    "addr:postcode":"ts29 6ap",
    "iso:country":"GB",
    "sg:address":"Foundry Garage",
    "sg:city":"Trimdon Station",
    "sg:classifiers":[
        {
            "category":"Autos & Motor Vehicles",
            "subcategory":"Automobile Sales",
            "type":"Retail Goods"
        }
    ],
    "sg:phone":"+44 1429 880571",
    "sg:postcode":"TS29 6AP",
    "sg:province":"Durham",
    "sg:tags":[
        "car"
    ],
    "wof:name":"Matt Watchman Motors Ltd.",
    "wof:placetype":"venue"
},
  "geometry": {"coordinates":[-1.4082260132,54.6999130249],"type":"Point"}
}