{
  "type": "Feature",
  "properties": {
    "addr:full":"Care Of Worthing Superstore, Newland Street Worthing West Sussex BN11 1JU",
    "addr:postcode":"bn11 1ju",
    "addr:street":"Newland Street",
    "iso:country":"GB",
    "sg:address":"Care Of Worthing Superstore, Newland Street",
    "sg:city":"Worthing",
    "sg:classifiers":[
        {
            "category":"Travel",
            "subcategory":"Travel Agent",
            "type":"Entertainment"
        }
    ],
    "sg:phone":"+44 1903 286500",
    "sg:postcode":"BN11 1JU",
    "sg:province":"West Sussex",
    "wof:name":"Travelcare",
    "wof:placetype":"venue"
},
  "geometry": {"coordinates":[-0.3754239976,50.8136253357],"type":"Point"}
}