{
  "type": "Feature",
  "properties": {
    "iso:country":"GB",
    "sg:address":"Style Farm, Turf Drove, Turves",
    "sg:city":"Peterborough",
    "sg:classifiers":[
        {
            "category":"Transit Center",
            "subcategory":"Passenger",
            "type":"Transportation"
        }
    ],
    "sg:phone":"+44 1733 840598",
    "sg:postcode":"PE7 2DJ",
    "sg:province":"Cambridgeshire",
    "sg:tags":[
        "boarding",
        "kennel",
        "catteries"
    ],
    "wof:name":"Frozzydyke Boarding Kennels & Cattery",
    "wof:placetype":"venue"
},
  "geometry": {"coordinates":[-0.0179399997,52.5531082153],"type":"Point"}
}