{
  "type": "Feature",
  "properties": {
    "iso:country":"GB",
    "sg:address":"Unit 2 Higherford Mill, Gisburn Road, Barrowford",
    "sg:city":"Nelson",
    "sg:classifiers":[
        {
            "category":"Recreation",
            "subcategory":"Amusement Park",
            "type":"Entertainment"
        },
        {
            "category":"Recreation",
            "subcategory":"Water Park",
            "type":"Entertainment"
        }
    ],
    "sg:phone":"+44 1257 232325",
    "sg:postcode":"BB9 6JH",
    "sg:province":"Lancashire",
    "sg:tags":[
        "theme",
        "arcade"
    ],
    "wof:name":"Bee Line Amusements",
    "wof:placetype":"venue"
},
  "geometry": {"coordinates":[-2.2107899189,53.8563919067],"type":"Point"}
}