{
  "type": "Feature",
  "properties": {
    "iso:country":"GB",
    "sg:address":"Hasler House, 90 High St",
    "sg:city":"Dunmow",
    "sg:classifiers":[
        {
            "category":"Professional",
            "type":"Services"
        }
    ],
    "sg:phone":"+44 1371 874898",
    "sg:postcode":"CM6 1AP",
    "sg:province":"Essex",
    "sg:tags":[
        "repair",
        "tech",
        "maintenance"
    ],
    "wof:name":"Active Group Services",
    "wof:placetype":"venue"
},
  "geometry": {"coordinates":[0.365556,51.869492],"type":"Point"}
}