{
  "type": "Feature",
  "properties": {
    "addr:full":"Rainbow Bridge, 74 Aldersbrook Road London Greater London E12 5DL",
    "addr:housenumber":"74",
    "addr:postcode":"e12 5dl",
    "addr:street":"Rainbow;Aldersbrook Road",
    "iso:country":"GB",
    "sg:address":"Rainbow Bridge, 74 Aldersbrook Road",
    "sg:city":"London",
    "sg:classifiers":[
        {
            "category":"Organizations",
            "subcategory":"Non-profit Organization",
            "type":"Services"
        }
    ],
    "sg:phone":"+44 20 8532 9370",
    "sg:postcode":"E12 5DL",
    "sg:province":"Greater London",
    "sg:tags":[
        "organisation",
        "voluntary",
        "charity"
    ],
    "wof:name":"Barnardo's",
    "wof:placetype":"venue"
},
  "geometry": {"coordinates":[0.03767,51.560791],"type":"Point"}
}