{
  "type": "Feature",
  "properties": {
    "iso:country":"GB",
    "sg:address":"11 Queensway, Worsbrough Bridge",
    "sg:city":"Barnsley",
    "sg:classifiers":[
        {
            "category":"Shopping",
            "subcategory":"Pharmacy",
            "type":"Retail Goods"
        }
    ],
    "sg:postcode":"S70 5EN",
    "sg:province":"South Yorkshire",
    "sg:tags":[
        "pharmacist",
        "chemist"
    ],
    "wof:name":"M Donald Wood Ltd.",
    "wof:placetype":"venue"
},
  "geometry": {"coordinates":[-1.464155,53.531406],"type":"Point"}
}