{
  "type": "Feature",
  "properties": {
    "addr:full":"The Park, Lower Slaughter Cheltenham Gloucestershire GL54 2HP",
    "addr:postcode":"gl54 2hp",
    "addr:street":"Park",
    "iso:country":"GB",
    "sg:address":"The Park, Lower Slaughter",
    "sg:city":"Cheltenham",
    "sg:classifiers":[
        {
            "category":"Personal",
            "subcategory":"Adult",
            "type":"Services"
        }
    ],
    "sg:phone":"+44 1451 810303",
    "sg:postcode":"GL54 2HP",
    "sg:province":"Gloucestershire",
    "sg:tags":[
        "equestrian"
    ],
    "wof:name":"Rimell Racing",
    "wof:placetype":"venue"
},
  "geometry": {"coordinates":[-1.7612589598,51.9014205933],"type":"Point"}
}