{
  "type": "Feature",
  "properties": {
    "iso:country":"GB",
    "sg:address":"22-26 High St",
    "sg:city":"Romford",
    "sg:classifiers":[
        {
            "category":"Manufacturing",
            "subcategory":"Textiles",
            "type":"Manufacturing & Wholesale Goods"
        }
    ],
    "sg:phone":"+44 1708 722142",
    "sg:postcode":"RM1 1HR",
    "sg:province":"Essex",
    "sg:tags":[
        "made-up"
    ],
    "wof:name":"Brentfords",
    "wof:placetype":"venue"
},
  "geometry": {"coordinates":[0.1792950034,51.5780830383],"type":"Point"}
}