{
  "type": "Feature",
  "properties": {
    "addr:full":"Tearnside Cottage, Kirkby Lonsdale Carnforth Cumbria LA6 2PU",
    "addr:postcode":"la6 2pu",
    "iso:country":"GB",
    "sg:address":"Tearnside Cottage, Kirkby Lonsdale",
    "sg:city":"Carnforth",
    "sg:classifiers":[
        {
            "category":"Manufacturing",
            "subcategory":"Lumber",
            "type":"Manufacturing & Wholesale Goods"
        }
    ],
    "sg:phone":"+44 15242 71027",
    "sg:postcode":"LA6 2PU",
    "sg:province":"Cumbria",
    "sg:tags":[
        "importer",
        "merchants",
        "agent",
        "timber"
    ],
    "wof:name":"P Irving & Son",
    "wof:placetype":"venue"
},
  "geometry": {"coordinates":[-2.5982739925,54.2020187378],"type":"Point"}
}