{
  "type": "Feature",
  "properties": {
    "iso:country":"GB",
    "sg:address":"Albion Road",
    "sg:city":"Dewsbury",
    "sg:classifiers":[
        {
            "category":"Organizations",
            "subcategory":"Membership Organization",
            "type":"Services"
        }
    ],
    "sg:phone":"+44 1924 462606",
    "sg:postcode":"WF12 0HD",
    "sg:province":"West Yorkshire",
    "sg:tags":[
        "club",
        "social"
    ],
    "wof:name":"Thornhill Edge Working Mens Club",
    "wof:placetype":"venue"
},
  "geometry": {"coordinates":[-1.6219329834,53.6587142944],"type":"Point"}
}