{
  "type": "Feature",
  "properties": {
    "addr:full":"Bilton Court, Queensway Wellingborough Northamptonshire NN8 3FR",
    "addr:postcode":"nn8 3fr",
    "addr:street":"Bilton Court",
    "iso:country":"GB",
    "sg:address":"Bilton Court, Queensway",
    "sg:city":"Wellingborough",
    "sg:classifiers":[
        {
            "category":"Organizations",
            "subcategory":"Community Association",
            "type":"Services"
        }
    ],
    "sg:phone":"+44 1933 401613",
    "sg:postcode":"NN8 3FR",
    "sg:province":"Northamptonshire",
    "sg:tags":[
        "associations",
        "housing",
        "co-operatives",
        "society",
        "trust",
        "societies"
    ],
    "wof:name":"ANCHOR TRUST",
    "wof:placetype":"venue"
},
  "geometry": {"coordinates":[-0.720139,52.301319],"type":"Point"}
}