{
  "type": "Feature",
  "properties": {
    "addr:full":"Alfreton Road Sutton-in-ashfield Nottinghamshire NG17 1FW",
    "addr:postcode":"ng17 1fw",
    "addr:street":"Alfreton Road",
    "iso:country":"GB",
    "sg:address":"Alfreton Road",
    "sg:city":"Sutton-in-ashfield",
    "sg:classifiers":[
        {
            "category":"Autos & Motor Vehicles",
            "subcategory":"Auto Supplies",
            "type":"Retail Goods"
        }
    ],
    "sg:phone":"+44 1623 554456",
    "sg:postcode":"NG17 1FW",
    "sg:province":"Nottinghamshire",
    "sg:tags":[
        "gearbox"
    ],
    "wof:name":"Grosvenor Trans-Gears",
    "wof:placetype":"venue"
},
  "geometry": {"coordinates":[-1.2731209993,53.1227989197],"type":"Point"}
}