{
  "type": "Feature",
  "properties": {
    "addr:full":"78 Thames Dr Leigh On Sea Essex SS9 2XD",
    "addr:housenumber":"78",
    "addr:postcode":"ss9 2xd",
    "addr:street":"Thames Dr",
    "iso:country":"GB",
    "sg:address":"78 Thames Dr",
    "sg:city":"Leigh On Sea",
    "sg:classifiers":[
        {
            "category":"Professional",
            "subcategory":"Accounting & Tax Preparation",
            "type":"Services"
        }
    ],
    "sg:phone":"+44 1702 714155",
    "sg:postcode":"SS9 2XD",
    "sg:province":"Essex",
    "sg:tags":[
        "consultant"
    ],
    "wof:name":"K Bell",
    "wof:placetype":"venue"
},
  "geometry": {"coordinates":[0.6305189729,51.5455741882],"type":"Point"}
}