{
  "type": "Feature",
  "properties": {
    "iso:country":"GB",
    "sg:address":"1 Russell Pde, Golders Green Rd",
    "sg:city":"Golders Green",
    "sg:classifiers":[
        {
            "category":"Shopping",
            "subcategory":"Books",
            "type":"Retail Goods"
        }
    ],
    "sg:phone":"+44 20 8458 6314",
    "sg:postcode":"NW11 9NN",
    "sg:province":"Greater London",
    "wof:name":"Lund Humphries Ltd",
    "wof:placetype":"venue"
},
  "geometry": {"coordinates":[-0.206899,51.577591],"type":"Point"}
}