{
  "type": "Feature",
  "properties": {
    "iso:country":"GB",
    "sg:address":"113 Church Street",
    "sg:city":"London",
    "sg:classifiers":[
        {
            "category":"Shopping",
            "subcategory":"Pharmacy",
            "type":"Retail Goods"
        }
    ],
    "sg:phone":"+44 20 7723 9600",
    "sg:postcode":"NW8 8HA",
    "sg:province":"Greater London",
    "sg:tags":[
        "pharmacist",
        "chemist"
    ],
    "wof:name":"Pharm Medica Ltd.",
    "wof:placetype":"venue"
},
  "geometry": {"coordinates":[-0.1716919988,51.522277832],"type":"Point"}
}