{
  "type": "Feature",
  "properties": {
    "iso:country":"GB",
    "sg:address":"Bircher Hall, Bircher",
    "sg:city":"Leominster",
    "sg:classifiers":[
        {
            "category":"Shopping",
            "subcategory":"Bicycles & Sporting Goods",
            "type":"Retail Goods"
        }
    ],
    "sg:phone":"+44 1568 780808",
    "sg:postcode":"HR6 0AX",
    "sg:province":"Herefordshire",
    "sg:tags":[
        "equipment",
        "gym",
        "sport"
    ],
    "wof:name":"Air Bounce Trampolines",
    "wof:placetype":"venue"
},
  "geometry": {"coordinates":[-2.7693860531,52.2869567871],"type":"Point"}
}