{
  "type": "Feature",
  "properties": {
    "addr:full":"152 Corn Street Witney Oxfordshire OX28 6BY",
    "addr:housenumber":"152",
    "addr:postcode":"ox28 6by",
    "addr:street":"Corn Street",
    "iso:country":"GB",
    "sg:address":"152 Corn Street",
    "sg:city":"Witney",
    "sg:classifiers":[
        {
            "category":"Restaurant",
            "type":"Food & Drink"
        }
    ],
    "sg:phone":"+44 1993 703285",
    "sg:postcode":"OX28 6BY",
    "sg:province":"Oxfordshire",
    "sg:tags":[
        "-",
        "chinese"
    ],
    "wof:name":"The Water Margin",
    "wof:placetype":"venue"
},
  "geometry": {"coordinates":[-1.492894,51.784779],"type":"Point"}
}