{
  "type": "Feature",
  "properties": {
    "iso:country":"GB",
    "sg:address":"202 Warstones Road",
    "sg:city":"Wolverhampton",
    "sg:classifiers":[
        {
            "category":"Building & Trades",
            "subcategory":"Construction",
            "type":"Services"
        }
    ],
    "sg:phone":"+44 1902 341396",
    "sg:postcode":"WV4 4LF",
    "sg:province":"Staffordshire",
    "sg:tags":[
        "glazier"
    ],
    "wof:name":"William Thomas Humpherson",
    "wof:placetype":"venue"
},
  "geometry": {"coordinates":[-2.169134,52.560444],"type":"Point"}
}