{
  "type": "Feature",
  "properties": {
    "addr:full":"2a Charford Road Bromsgrove Worcestershire B60 3LU",
    "addr:housenumber":"2a",
    "addr:postcode":"b60 3lu",
    "addr:street":"Charford Road",
    "iso:country":"GB",
    "sg:address":"2a Charford Road",
    "sg:city":"Bromsgrove",
    "sg:classifiers":[
        {
            "category":"Place Of Worship",
            "type":"Public Place"
        }
    ],
    "sg:phone":"+44 1527 832530",
    "sg:postcode":"B60 3LU",
    "sg:province":"Worcestershire",
    "wof:name":"St Peters R C Church",
    "wof:placetype":"venue"
},
  "geometry": {"coordinates":[-2.0696849823,52.326625824],"type":"Point"}
}