{
  "type": "Feature",
  "properties": {
    "iso:country":"GB",
    "sg:address":"542 Sheffield Rd",
    "sg:city":"Chesterfield",
    "sg:classifiers":[
        {
            "category":"Health Services",
            "subcategory":"Dentist",
            "type":"Services"
        }
    ],
    "sg:phone":"+44 1246 450668",
    "sg:postcode":"S41 8LX",
    "sg:province":"Derbyshire",
    "wof:name":"S J Kemp",
    "wof:placetype":"venue"
},
  "geometry": {"coordinates":[-1.4273890257,53.2525482178],"type":"Point"}
}