{
  "type": "Feature",
  "properties": {
    "addr:full":"Grenville Workshops, Grenville Rd Archway Greater London N19 4EH",
    "addr:postcode":"n19 4eh",
    "addr:street":"Grenville Rd",
    "iso:country":"GB",
    "sg:address":"Grenville Workshops, Grenville Rd",
    "sg:city":"Archway",
    "sg:classifiers":[
        {
            "category":"Shopping",
            "subcategory":"Clothing, Apparel, & Fashions",
            "type":"Retail Goods"
        }
    ],
    "sg:phone":"+44 7956 364317",
    "sg:postcode":"N19 4EH",
    "sg:province":"Greater London",
    "sg:tags":[
        "clothing",
        "fabric"
    ],
    "wof:name":"Exani London Ltd",
    "wof:placetype":"venue"
},
  "geometry": {"coordinates":[-0.1211799979,51.5685195923],"type":"Point"}
}