{
  "type": "Feature",
  "properties": {
    "iso:country":"GB",
    "sg:address":"661 Fulham Road",
    "sg:city":"London",
    "sg:classifiers":[
        {
            "category":"Professional",
            "subcategory":"Management & Consulting",
            "type":"Services"
        }
    ],
    "sg:phone":"+44 20 7736 3360",
    "sg:postcode":"SW6 5PZ",
    "sg:province":"Greater London",
    "sg:tags":[
        "marketing",
        "consultant"
    ],
    "wof:name":"S T A S Associates",
    "wof:placetype":"venue"
},
  "geometry": {"coordinates":[-0.199868,51.47879],"type":"Point"}
}