{
  "type": "Feature",
  "properties": {
    "addr:full":"Wisteria House, Wisteria Way, Churchdown Gloucester Gloucestershire GL3 1LQ",
    "addr:postcode":"gl3 1lq",
    "addr:street":"Wisteria Way",
    "iso:country":"GB",
    "sg:address":"Wisteria House, Wisteria Way, Churchdown",
    "sg:city":"Gloucester",
    "sg:classifiers":[
        {
            "category":"Professional",
            "subcategory":"Employment Agencies",
            "type":"Services"
        }
    ],
    "sg:phone":"+44 1452 857494",
    "sg:postcode":"GL3 1LQ",
    "sg:province":"Gloucestershire",
    "sg:tags":[
        "introduction"
    ],
    "wof:name":"New Horizons",
    "wof:placetype":"venue"
},
  "geometry": {"coordinates":[-2.1891300678,51.8878593445],"type":"Point"}
}