{
  "type": "Feature",
  "properties": {
    "addr:full":"Gayton Road, Bawsey King's Lynn Norfolk PE32 1EP",
    "addr:postcode":"pe32 1ep",
    "addr:street":"Gayton Road;Lynn",
    "iso:country":"GB",
    "sg:address":"Gayton Road, Bawsey",
    "sg:city":"King's Lynn",
    "sg:classifiers":[
        {
            "category":"Bars & Pubs",
            "type":"Food & Drink"
        }
    ],
    "sg:phone":"+44 1553 630527",
    "sg:postcode":"PE32 1EP",
    "sg:province":"Norfolk",
    "sg:tags":[
        "pubs",
        "inn",
        "-",
        "restaurant"
    ],
    "wof:name":"The Sandboy",
    "wof:placetype":"venue"
},
  "geometry": {"coordinates":[0.47686,52.751122],"type":"Point"}
}