{
  "type": "Feature",
  "properties": {
    "addr:full":"8 Flowerpot La Norwich Norfolk NR15 2TS",
    "addr:housenumber":"8",
    "addr:postcode":"nr15 2ts",
    "addr:street":"Flowerpot La Norwich",
    "iso:country":"GB",
    "sg:address":"8 Flowerpot La",
    "sg:city":"Norwich",
    "sg:classifiers":[
        {
            "category":"Social Services",
            "type":"Services"
        }
    ],
    "sg:phone":"+44 1508 530820",
    "sg:postcode":"NR15 2TS",
    "sg:province":"Norfolk",
    "wof:name":"Rayleen",
    "wof:placetype":"venue"
},
  "geometry": {"coordinates":[1.228321,52.485107],"type":"Point"}
}