{
  "type": "Feature",
  "properties": {
    "iso:country":"GB",
    "sg:address":"24 Paddington St",
    "sg:city":"West End",
    "sg:classifiers":[
        {
            "category":"Food & Beverages",
            "subcategory":"Specialty",
            "type":"Retail Goods"
        }
    ],
    "sg:phone":"+44 20 7935 3924",
    "sg:postcode":"W1M 4DR",
    "sg:province":"Hampshire",
    "sg:tags":[
        "product",
        "health"
    ],
    "wof:name":"Wholefood",
    "wof:placetype":"venue"
},
  "geometry": {"coordinates":[-0.155001,51.520718],"type":"Point"}
}