{
  "type": "Feature",
  "properties": {
    "addr:full":"Park Grounds Farm, Whitehill Lane, Wootton Bassett Swindon Wiltshire SN4 7SB",
    "addr:postcode":"sn4 7sb",
    "addr:street":"Park;Whitehill Lane",
    "iso:country":"GB",
    "sg:address":"Park Grounds Farm, Whitehill Lane, Wootton Bassett",
    "sg:city":"Swindon",
    "sg:classifiers":[
        {
            "category":"Farming",
            "subcategory":"Livestock Farm",
            "type":"Manufacturing & Wholesale Goods"
        }
    ],
    "sg:postcode":"SN4 7SB",
    "sg:province":"Wiltshire",
    "sg:tags":[
        "others"
    ],
    "wof:name":"G Brown",
    "wof:placetype":"venue"
},
  "geometry": {"coordinates":[-1.903224,51.54266],"type":"Point"}
}