{
  "type": "Feature",
  "properties": {
    "iso:country":"GB",
    "sg:address":"7 Rushes Lane, Lubenham",
    "sg:city":"Market Harborough",
    "sg:classifiers":[
        {
            "category":"Autos & Motor Vehicles",
            "subcategory":"Auto Supplies",
            "type":"Retail Goods"
        }
    ],
    "sg:phone":"+44 1858 431444",
    "sg:postcode":"LE16 9TN",
    "sg:province":"Leicestershire",
    "sg:tags":[
        "electric"
    ],
    "wof:name":"Phoenix Motor Rewinds Ltd",
    "wof:placetype":"venue"
},
  "geometry": {"coordinates":[-0.963204,52.479523],"type":"Point"}
}