{
  "type": "Feature",
  "properties": {
    "addr:full":"Old Statin Close Coalville Leicestershire LE67 3FH",
    "addr:postcode":"le67 3fh",
    "addr:street":"Statin Close",
    "iso:country":"GB",
    "sg:address":"Old Statin Close",
    "sg:city":"Coalville",
    "sg:classifiers":[
        {
            "category":"Shopping",
            "subcategory":"Computers & Home Electronics",
            "type":"Retail Goods"
        }
    ],
    "sg:phone":"+44 1530 814060",
    "sg:postcode":"LE67 3FH",
    "sg:province":"Leicestershire",
    "sg:tags":[
        "electrical"
    ],
    "wof:name":"City Electrical Factors Ltd.",
    "wof:placetype":"venue"
},
  "geometry": {"coordinates":[-1.3723059893,52.7187843323],"type":"Point"}
}