{
  "type": "Feature",
  "properties": {
    "iso:country":"GB",
    "sg:address":"Unit 1-5 Enterprise Busns Park, Hawkins Lane",
    "sg:city":"Burton-on-trent",
    "sg:classifiers":[
        {
            "category":"Manufacturing",
            "subcategory":"Petroleum Products",
            "type":"Manufacturing & Wholesale Goods"
        }
    ],
    "sg:phone":"+44 1283 517626",
    "sg:postcode":"DE14 1QG",
    "sg:province":"Derbyshire",
    "sg:tags":[
        "double",
        "glazing"
    ],
    "wof:name":"Herron Windows (U K) Ltd.",
    "wof:placetype":"venue"
},
  "geometry": {"coordinates":[-1.62758,52.816292],"type":"Point"}
}