{
  "type": "Feature",
  "properties": {
    "addr:full":"97-101 Hackney Road London Greater London E2 8ET",
    "addr:housenumber":"97-101",
    "addr:postcode":"e2 8et",
    "addr:street":"Hackney Road",
    "iso:country":"GB",
    "sg:address":"97-101 Hackney Road",
    "sg:city":"London",
    "sg:classifiers":[
        {
            "category":"Shopping",
            "subcategory":"Stationery & Office Supplies",
            "type":"Retail Goods"
        }
    ],
    "sg:phone":"+44 20 7256 1269",
    "sg:postcode":"E2 8ET",
    "sg:province":"Greater London",
    "sg:tags":[
        "equipment"
    ],
    "wof:name":"Andrews Office Equipment",
    "wof:placetype":"venue"
},
  "geometry": {"coordinates":[-0.073939,51.530251],"type":"Point"}
}