{
  "type": "Feature",
  "properties": {
    "addr:full":"373 Harrow Road London Greater London W9 3NA",
    "addr:housenumber":"373",
    "addr:postcode":"w9 3na",
    "addr:street":"Harrow Road",
    "iso:country":"GB",
    "sg:address":"373 Harrow Road",
    "sg:city":"London",
    "sg:classifiers":[
        {
            "category":"Home & Garden",
            "subcategory":"Carpets & Floor Coverings",
            "type":"Retail Goods"
        }
    ],
    "sg:phone":"+44 20 8964 9929",
    "sg:postcode":"W9 3NA",
    "sg:province":"Greater London",
    "sg:tags":[
        "carpets",
        "rug",
        "matting"
    ],
    "wof:name":"Waldolf Carpet Rags & Vinyl",
    "wof:placetype":"venue"
},
  "geometry": {"coordinates":[-0.2025700063,51.5245361328],"type":"Point"}
}