{
  "type": "Feature",
  "properties": {
    "iso:country":"GB",
    "sg:address":"78 Connaught Road",
    "sg:city":"Sutton",
    "sg:classifiers":[
        {
            "category":"Building & Trades",
            "subcategory":"Landscaping Services",
            "type":"Services"
        }
    ],
    "sg:phone":"+44 20 8641 5377",
    "sg:postcode":"SM1 3PQ",
    "sg:province":"Surrey",
    "sg:tags":[
        "landscape",
        "contractor"
    ],
    "wof:name":"Connaught Garden Fencing",
    "wof:placetype":"venue"
},
  "geometry": {"coordinates":[-0.177813,51.37466],"type":"Point"}
}