{
  "type": "Feature",
  "properties": {
    "iso:country":"GB",
    "sg:address":"Kings Dock Street",
    "sg:city":"Liverpool",
    "sg:classifiers":[
        {
            "category":"Home & Garden",
            "subcategory":"Carpets & Floor Coverings",
            "type":"Retail Goods"
        }
    ],
    "sg:phone":"+44 151 709 8557",
    "sg:postcode":"L1 8LE",
    "sg:province":"Merseyside",
    "sg:tags":[
        "textile",
        "floorcoverings"
    ],
    "wof:name":"A J Beer & Co. (Warrington) Ltd.",
    "wof:placetype":"venue"
},
  "geometry": {"coordinates":[-2.98424,53.397568],"type":"Point"}
}