{
  "type": "Feature",
  "properties": {
    "addr:full":"60 Hednesford Street Cannock Staffordshire WS11 1DJ",
    "addr:housenumber":"60",
    "addr:postcode":"ws11 1dj",
    "addr:street":"Hednesford Street",
    "iso:country":"GB",
    "sg:address":"60 Hednesford Street",
    "sg:city":"Cannock",
    "sg:classifiers":[
        {
            "category":"Health Services",
            "subcategory":"Doctor",
            "type":"Services"
        }
    ],
    "sg:phone":"+44 1543 503121",
    "sg:postcode":"WS11 1DJ",
    "sg:province":"Staffordshire",
    "sg:tags":[
        "practitioners"
    ],
    "wof:name":"L Hulme & Partners",
    "wof:placetype":"venue"
},
  "geometry": {"coordinates":[-2.024309,52.689121],"type":"Point"}
}