{
  "type": "Feature",
  "properties": {
    "iso:country":"GB",
    "sg:address":"Trenton Works, Hewell Road",
    "sg:city":"Redditch",
    "sg:classifiers":[
        {
            "category":"Building & Trades",
            "subcategory":"Construction",
            "type":"Services"
        }
    ],
    "sg:phone":"+44 1527 62729",
    "sg:postcode":"B97 6AR",
    "sg:province":"Warwickshire",
    "sg:tags":[
        "builder"
    ],
    "wof:name":"Melley & Dalton Ltd.",
    "wof:placetype":"venue"
},
  "geometry": {"coordinates":[-1.9412670135,52.30727005],"type":"Point"}
}