{
  "type": "Feature",
  "properties": {
    "iso:country":"GB",
    "sg:address":"Beech Hill Road",
    "sg:city":"Sheffield",
    "sg:classifiers":[
        {
            "category":"Education",
            "subcategory":"School",
            "type":"Public Place"
        }
    ],
    "sg:phone":"+44 114 266 0936",
    "sg:postcode":"S10 2SA",
    "sg:province":"South Yorkshire",
    "sg:tags":[
        "college"
    ],
    "wof:name":"Broomhill Infant School",
    "wof:placetype":"venue"
},
  "geometry": {"coordinates":[-1.494384,53.377628],"type":"Point"}
}