{
  "type": "Feature",
  "properties": {
    "addr:full":"Peel Pl Off Old Mill La Barnsley South Yorkshire S71 1LU",
    "addr:postcode":"s71 1lu",
    "addr:street":"Peel Pl Off Old;La Barnsley South",
    "iso:country":"GB",
    "sg:address":"Peel Pl Off Old Mill La",
    "sg:city":"Barnsley",
    "sg:classifiers":[
        {
            "category":"Building & Trades",
            "subcategory":"Construction",
            "type":"Services"
        }
    ],
    "sg:postcode":"S71 1LU",
    "sg:province":"South Yorkshire",
    "sg:tags":[
        "joinery"
    ],
    "wof:name":"Adams,Ken,",
    "wof:placetype":"venue"
},
  "geometry": {"coordinates":[-1.471094,53.562309],"type":"Point"}
}