{
  "type": "Feature",
  "properties": {
    "addr:full":"24 Riverton Road Bridgwater Somerset TA7 8BP",
    "addr:housenumber":"24",
    "addr:postcode":"ta7 8bp",
    "addr:street":"Riverton Road",
    "iso:country":"GB",
    "sg:address":"24 Riverton Road",
    "sg:city":"Bridgwater",
    "sg:classifiers":[
        {
            "category":"Building & Trades",
            "subcategory":"Construction",
            "type":"Services"
        }
    ],
    "sg:phone":"+44 1278 684711",
    "sg:postcode":"TA7 8BP",
    "sg:province":"Somerset",
    "sg:tags":[
        "builder"
    ],
    "wof:name":"Peter Clayton",
    "wof:placetype":"venue"
},
  "geometry": {"coordinates":[-2.9429869652,51.1507797241],"type":"Point"}
}