{
  "type": "Feature",
  "properties": {
    "addr:full":"29 Berkeley Letchworth Hertfordshire SG6 2HA",
    "addr:housenumber":"29",
    "addr:postcode":"sg6 2ha",
    "addr:street":"Berkeley Letchworth",
    "iso:country":"GB",
    "sg:address":"29 Berkeley",
    "sg:city":"Letchworth",
    "sg:classifiers":[
        {
            "category":"Building & Trades",
            "subcategory":"Cleaning & Sanitation",
            "type":"Services"
        }
    ],
    "sg:phone":"+44 1462 627527",
    "sg:postcode":"SG6 2HA",
    "sg:province":"Hertfordshire",
    "sg:tags":[
        "dry",
        "control",
        "damp",
        "rot"
    ],
    "wof:name":"Collis Damp & Timber Treatment",
    "wof:placetype":"venue"
},
  "geometry": {"coordinates":[-0.221678,51.970287],"type":"Point"}
}