{
  "type": "Feature",
  "properties": {
    "addr:full":"Unit 1 Grisedale Court, Woburn Road Industrial Estate, Kempston Bedford Bedfordshire MK42 7EE",
    "addr:housenumber":"unit 1",
    "addr:postcode":"mk42 7ee",
    "addr:street":"Grisedale Court Woburn Road Industrial Estate",
    "iso:country":"GB",
    "sg:address":"Unit 1 Grisedale Court, Woburn Road Industrial Estate, Kempston",
    "sg:city":"Bedford",
    "sg:classifiers":[
        {
            "category":"Manufacturing",
            "subcategory":"Rubber & Plastics",
            "type":"Manufacturing & Wholesale Goods"
        }
    ],
    "sg:phone":"+44 1234 843310",
    "sg:postcode":"MK42 7EE",
    "sg:province":"Bedfordshire",
    "sg:tags":[
        "injection",
        "moulding"
    ],
    "wof:name":"Emblem Mouldings Ltd.",
    "wof:placetype":"venue"
},
  "geometry": {"coordinates":[-0.496809,52.107506],"type":"Point"}
}