{
  "type": "Feature",
  "properties": {
    "addr:full":"Fern House Wisbech Cambridgeshire PE13 1PL",
    "addr:postcode":"pe13 1pl",
    "iso:country":"GB",
    "sg:address":"Fern House",
    "sg:city":"Wisbech",
    "sg:classifiers":[
        {
            "category":"Professional",
            "subcategory":"Computer Services",
            "type":"Services"
        }
    ],
    "sg:postcode":"PE13 1PL",
    "sg:province":"Cambridgeshire",
    "sg:tags":[
        "system",
        "software"
    ],
    "wof:name":"A B Computers of Whittlesey",
    "wof:placetype":"venue"
},
  "geometry": {"coordinates":[0.157227993,52.6696891785],"type":"Point"}
}