{
  "type": "Feature",
  "properties": {
    "addr:full":"12 Bogwood Court, Mayfield Dalkeith City of Edinburgh EH22 5DG",
    "addr:housenumber":"12",
    "addr:postcode":"eh22 5dg",
    "addr:street":"Bogwood Court",
    "iso:country":"GB",
    "sg:address":"12 Bogwood Court, Mayfield",
    "sg:city":"Dalkeith",
    "sg:classifiers":[
        {
            "category":"Cinema",
            "subcategory":"Movie Rental",
            "type":"Entertainment"
        }
    ],
    "sg:postcode":"EH22 5DG",
    "sg:province":"City of Edinburgh",
    "sg:tags":[
        "video",
        "library"
    ],
    "wof:name":"Movie Magic",
    "wof:placetype":"venue"
},
  "geometry": {"coordinates":[-3.040583,55.874023],"type":"Point"}
}