{
  "type": "Feature",
  "properties": {
    "iso:country":"GB",
    "sg:address":"6 Princess Street",
    "sg:city":"Burnham-on-sea",
    "sg:classifiers":[
        {
            "category":"Government",
            "subcategory":"Office",
            "type":"Public Place"
        }
    ],
    "sg:phone":"+44 1278 783057",
    "sg:postcode":"TA8 1EH",
    "sg:province":"Somerset",
    "sg:tags":[
        "local",
        "agency",
        "education",
        "authority"
    ],
    "wof:name":"Burnham Community Education Centre",
    "wof:placetype":"venue"
},
  "geometry": {"coordinates":[-2.996397,51.238266],"type":"Point"}
}