{
  "type": "Feature",
  "properties": {
    "addr:full":"Unit 7c The Lakes Business Park, Lampluch Road Cockermouth Cumbria CA13 0QT",
    "addr:housenumber":"unit 7c",
    "addr:postcode":"ca13 0qt",
    "addr:street":"Business Park Lampluch Road",
    "iso:country":"GB",
    "sg:address":"Unit 7c The Lakes Business Park, Lampluch Road",
    "sg:city":"Cockermouth",
    "sg:classifiers":[
        {
            "category":"Organizations",
            "subcategory":"Non-profit Organization",
            "type":"Services"
        }
    ],
    "sg:phone":"+44 1900 828012",
    "sg:postcode":"CA13 0QT",
    "sg:province":"Cumbria",
    "sg:tags":[
        "organisation",
        "voluntary",
        "charity"
    ],
    "wof:name":"West Cumbria Crossroads Caring for Carers Ltd.",
    "wof:placetype":"venue"
},
  "geometry": {"coordinates":[-3.372229,54.65601],"type":"Point"}
}