{
  "type": "Feature",
  "properties": {
    "addr:full":"Stainforth Settle North Yorkshire BD24 9PJ",
    "addr:housenumber":"stainforth",
    "addr:postcode":"bd24 9pj",
    "addr:street":"Settle",
    "iso:country":"GB",
    "sg:address":"Stainforth",
    "sg:city":"Settle",
    "sg:classifiers":[
        {
            "category":"Real Estate",
            "subcategory":"Surveying",
            "type":"Services"
        }
    ],
    "sg:phone":"+44 1729 822255",
    "sg:postcode":"BD24 9PJ",
    "sg:province":"North Yorkshire",
    "sg:tags":[
        "surveyor",
        "valuer"
    ],
    "wof:name":"Andrew Mills & Co. Ltd.",
    "wof:placetype":"venue"
},
  "geometry": {"coordinates":[-2.277606,54.069759],"type":"Point"}
}