{
  "type": "Feature",
  "properties": {
    "addr:full":"Unit 5 Bradford West Yorkshire BD3 8HD",
    "addr:housenumber":"unit 5",
    "addr:postcode":"bd3 8hd",
    "addr:street":"Bradford West",
    "iso:country":"GB",
    "sg:address":"Unit 5",
    "sg:city":"Bradford",
    "sg:classifiers":[
        {
            "category":"Retail",
            "subcategory":"Auto Repair",
            "type":"Services"
        }
    ],
    "sg:phone":"+44 1274 664662",
    "sg:postcode":"BD3 8HD",
    "sg:province":"West Yorkshire",
    "sg:tags":[
        "body",
        "garage",
        "modification",
        "car"
    ],
    "wof:name":"N & D Cutts",
    "wof:placetype":"venue"
},
  "geometry": {"coordinates":[-1.7122600079,53.7972183228],"type":"Point"}
}