{
  "type": "Feature",
  "properties": {
    "addr:full":"14 Ryefields, Thurston Bury St Edmunds Suffolk IP31 3TD",
    "addr:housenumber":"14",
    "addr:postcode":"ip31 3td",
    "addr:street":"Ryefields Thurston",
    "iso:country":"GB",
    "sg:address":"14 Ryefields, Thurston",
    "sg:city":"Bury St Edmunds",
    "sg:classifiers":[
        {
            "category":"Wholesale",
            "subcategory":"Electrical",
            "type":"Manufacturing & Wholesale Goods"
        }
    ],
    "sg:phone":"+44 1359 233290",
    "sg:postcode":"IP31 3TD",
    "sg:province":"Suffolk",
    "sg:tags":[
        "equipment",
        "refrigeration"
    ],
    "wof:name":"Abbey Industrial Fans Ltd.",
    "wof:placetype":"venue"
},
  "geometry": {"coordinates":[0.813553,52.2505],"type":"Point"}
}