{
  "type": "Feature",
  "properties": {
    "addr:full":"16 Parc Y Nant, Nantgarw Cardiff Caerphilly CF15 7TJ",
    "addr:housenumber":"16",
    "addr:postcode":"cf15 7tj",
    "addr:street":"Parc Y Nant Nantgarw",
    "iso:country":"GB",
    "sg:address":"16 Parc Y Nant, Nantgarw",
    "sg:city":"Cardiff",
    "sg:classifiers":[
        {
            "category":"Building & Trades",
            "subcategory":"Construction",
            "type":"Services"
        }
    ],
    "sg:phone":"+44 1443 841386",
    "sg:postcode":"CF15 7TJ",
    "sg:province":"Caerphilly",
    "sg:tags":[
        "dry",
        "lining",
        "plasterers",
        "screeders"
    ],
    "wof:name":"Parc Plasterers Ltd.",
    "wof:placetype":"venue"
},
  "geometry": {"coordinates":[-3.26493,51.561298],"type":"Point"}
}