{
  "type": "Feature",
  "properties": {
    "iso:country":"GB",
    "sg:address":"Unit 9 Harrier Road, Humber Bridge Industrial Estate",
    "sg:city":"Barton-upon-humber",
    "sg:classifiers":[
        {
            "category":"Parking",
            "subcategory":"Bicycle",
            "type":"Transportation"
        }
    ],
    "sg:phone":"+44 1652 660000",
    "sg:postcode":"DN18 5RP",
    "sg:province":"Lincolnshire",
    "sg:tags":[
        "wholesaler",
        "cycle",
        "manufacturer",
        "accessory"
    ],
    "sg:website":"http://www.weldtite.co.uk",
    "wof:name":"Weldtite Products Ltd",
    "wof:placetype":"venue"
},
  "geometry": {"coordinates":[-0.428055,53.688869],"type":"Point"}
}