{
  "type": "Feature",
  "properties": {
    "iso:country":"GB",
    "sg:address":"60 Station Road",
    "sg:city":"Westgate-on-sea",
    "sg:classifiers":[
        {
            "category":"Food & Beverages",
            "subcategory":"Meat & Fish",
            "type":"Retail Goods"
        },
        {
            "category":"Food & Beverages",
            "subcategory":"Groceries & Convenience Stores",
            "type":"Retail Goods"
        }
    ],
    "sg:phone":"+44 1843 834154",
    "sg:postcode":"CT8 8QY",
    "sg:province":"Kent",
    "sg:tags":[
        "shop",
        "chip"
    ],
    "wof:name":"Westgate Fish & Chips",
    "wof:placetype":"venue"
},
  "geometry": {"coordinates":[1.3372980356,51.3815002441],"type":"Point"}
}