{
  "type": "Feature",
  "properties": {
    "addr:full":"2 Station Close Potters Bar Greater London EN6 1TL",
    "addr:housenumber":"2",
    "addr:postcode":"en6 1tl",
    "addr:street":"Station Close",
    "iso:country":"GB",
    "sg:address":"2 Station Close",
    "sg:city":"Potters Bar",
    "sg:classifiers":[
        {
            "category":"Professional",
            "subcategory":"Art Services",
            "type":"Services"
        }
    ],
    "sg:phone":"+44 1707 660097",
    "sg:postcode":"EN6 1TL",
    "sg:province":"Greater London",
    "sg:tags":[
        "photographer"
    ],
    "wof:name":"Stones Computer Sales Ltd.",
    "wof:placetype":"venue"
},
  "geometry": {"coordinates":[-0.1916549951,51.6976966858],"type":"Point"}
}