{
  "type": "Feature",
  "properties": {
    "iso:country":"GB",
    "sg:address":"Reynalton",
    "sg:city":"Kilgetty",
    "sg:classifiers":[
        {
            "category":"Recreation",
            "subcategory":"Campground",
            "type":"Entertainment"
        }
    ],
    "sg:postcode":"SA68 0PE",
    "sg:province":"Pembrokeshire",
    "sg:tags":[
        "caravan",
        "park"
    ],
    "wof:name":"Beachdean Leisure Park",
    "wof:placetype":"venue"
},
  "geometry": {"coordinates":[-4.714563,51.732834],"type":"Point"}
}