{
  "type": "Feature",
  "properties": {
    "iso:country":"GB",
    "sg:address":"20 Ferrers Wy",
    "sg:city":"Derby",
    "sg:classifiers":[
        {
            "category":"Professional",
            "subcategory":"Business Services",
            "type":"Services"
        }
    ],
    "sg:phone":"+44 1332 728592",
    "sg:postcode":"DE22 2AB",
    "sg:province":"Derbyshire",
    "sg:tags":[
        "fleet",
        "management",
        "vehicle"
    ],
    "wof:name":"Automotive Leasing Ltd.",
    "wof:placetype":"venue"
},
  "geometry": {"coordinates":[-1.4861830473,52.9464836121],"type":"Point"}
}