{
  "type": "Feature",
  "properties": {
    "addr:full":"Old Post Office, School Road, Little Totham Maldon Essex CM9 8JJ",
    "addr:postcode":"cm9 8jj",
    "addr:street":"School Road",
    "iso:country":"GB",
    "sg:address":"Old Post Office, School Road, Little Totham",
    "sg:city":"Maldon",
    "sg:classifiers":[
        {
            "category":"Professional",
            "subcategory":"Art Services",
            "type":"Services"
        }
    ],
    "sg:phone":"+44 1621 891665",
    "sg:postcode":"CM9 8JJ",
    "sg:province":"Essex",
    "sg:tags":[
        "interior",
        "photographer",
        "graphic",
        "designer"
    ],
    "wof:name":"H J Short",
    "wof:placetype":"venue"
},
  "geometry": {"coordinates":[0.7379199862,51.773399353],"type":"Point"}
}