{
  "type": "Feature",
  "properties": {
    "addr:full":"Brook Cottage, Arlestone La, Arleston Brook Telford Shropshire TF1 2LA",
    "addr:postcode":"tf1 2la",
    "addr:street":"Arlestone La Arleston",
    "iso:country":"GB",
    "sg:address":"Brook Cottage, Arlestone La, Arleston Brook",
    "sg:city":"Telford",
    "sg:classifiers":[
        {
            "category":"Building & Trades",
            "subcategory":"Construction",
            "type":"Services"
        }
    ],
    "sg:phone":"+44 1952 502681",
    "sg:postcode":"TF1 2LA",
    "sg:province":"Shropshire",
    "sg:tags":[
        "joiner",
        "carpenter"
    ],
    "wof:name":"H O Hedges",
    "wof:placetype":"venue"
},
  "geometry": {"coordinates":[-2.5018639565,52.696346283],"type":"Point"}
}