{
  "type": "Feature",
  "properties": {
    "iso:country":"GB",
    "sg:address":"42 Kersey Road, Flushing",
    "sg:city":"Falmouth",
    "sg:classifiers":[
        {
            "category":"Government",
            "subcategory":"Post Office",
            "type":"Public Place"
        }
    ],
    "sg:phone":"+44 1326 374301",
    "sg:postcode":"TR11 5TR",
    "sg:province":"Cornwall",
    "wof:name":"Flushing Post Office",
    "wof:placetype":"venue"
},
  "geometry": {"coordinates":[-5.069826,50.164593],"type":"Point"}
}