{
  "type": "Feature",
  "properties": {
    "iso:country":"GB",
    "sg:address":"P O Box 63",
    "sg:city":"Wallington",
    "sg:classifiers":[
        {
            "category":"Professional",
            "type":"Services"
        },
        {
            "category":"Wholesale",
            "subcategory":"Music Publishers",
            "type":"Manufacturing & Wholesale Goods"
        }
    ],
    "sg:postcode":"SM6 9YP",
    "sg:province":"Surrey",
    "sg:tags":[
        "entertainer",
        "record"
    ],
    "wof:name":"Upbeat Recordings Ltd.",
    "wof:placetype":"venue"
},
  "geometry": {"coordinates":[-0.149898,51.360123],"type":"Point"}
}