{
  "type": "Feature",
  "properties": {
    "addr:full":"28 High Street South, Crail Anstruther Fife KY10 3TE",
    "addr:housenumber":"28",
    "addr:postcode":"ky10 3te",
    "addr:street":"High Street South",
    "iso:country":"GB",
    "sg:address":"28 High Street South, Crail",
    "sg:city":"Anstruther",
    "sg:classifiers":[
        {
            "category":"Shopping",
            "subcategory":"Department Store",
            "type":"Retail Goods"
        },
        {
            "category":"Shopping",
            "subcategory":"Gifts & Souvenirs",
            "type":"Retail Goods"
        }
    ],
    "sg:phone":"+44 1333 450330",
    "sg:postcode":"KY10 3TE",
    "sg:province":"Fife",
    "sg:tags":[
        "shop"
    ],
    "wof:name":"The Beehive",
    "wof:placetype":"venue"
},
  "geometry": {"coordinates":[-2.701419,56.223541],"type":"Point"}
}