{
  "type": "Feature",
  "properties": {
    "addr:full":"The Gillingham Surgery, Newbury Gillingham Dorset SP8 4XS",
    "addr:postcode":"sp8 4xs",
    "addr:street":"Newbury",
    "iso:country":"GB",
    "sg:address":"The Gillingham Surgery, Newbury",
    "sg:city":"Gillingham",
    "sg:classifiers":[
        {
            "category":"Shopping",
            "subcategory":"Pharmacy",
            "type":"Retail Goods"
        }
    ],
    "sg:phone":"+44 1747 826709",
    "sg:postcode":"SP8 4XS",
    "sg:province":"Dorset",
    "sg:tags":[
        "pharmacist",
        "chemist"
    ],
    "wof:name":"Surgery Pharmacy the",
    "wof:placetype":"venue"
},
  "geometry": {"coordinates":[-2.27862,51.038097],"type":"Point"}
}