{
  "type": "Feature",
  "properties": {
    "addr:full":"5 New Street, Frankwell Shrewsbury Shropshire SY3 8JN",
    "addr:housenumber":"5",
    "addr:postcode":"sy3 8jn",
    "addr:street":"New Street",
    "iso:country":"GB",
    "sg:address":"5 New Street, Frankwell",
    "sg:city":"Shrewsbury",
    "sg:classifiers":[
        {
            "category":"Restaurant",
            "type":"Food & Drink"
        }
    ],
    "sg:phone":"+44 1743 235182",
    "sg:postcode":"SY3 8JN",
    "sg:province":"Shropshire",
    "sg:tags":[
        "italian"
    ],
    "wof:name":"Giuseppe Italian Restaurant",
    "wof:placetype":"venue"
},
  "geometry": {"coordinates":[-2.761523,52.710999],"type":"Point"}
}