{
  "type": "Feature",
  "properties": {
    "addr:full":"80 Aldershot Road, Church Crookham Fleet Hampshire GU52 8LE",
    "addr:housenumber":"80",
    "addr:postcode":"gu52 8le",
    "addr:street":"Aldershot Road",
    "iso:country":"GB",
    "sg:address":"80 Aldershot Road, Church Crookham",
    "sg:city":"Fleet",
    "sg:classifiers":[
        {
            "category":"Manufacturing",
            "subcategory":"Metals",
            "type":"Manufacturing & Wholesale Goods"
        },
        {
            "category":"Manufacturing",
            "subcategory":"Furniture",
            "type":"Manufacturing & Wholesale Goods"
        }
    ],
    "sg:postcode":"GU52 8LE",
    "sg:province":"Hampshire",
    "sg:tags":[
        "polishing",
        "heat",
        "-",
        "treatment",
        "french"
    ],
    "wof:name":"Abercorn Workshop",
    "wof:placetype":"venue"
},
  "geometry": {"coordinates":[-0.8400679827,51.2593040466],"type":"Point"}
}