{
  "type": "Feature",
  "properties": {
    "addr:full":"The Square, Trefnant Denbigh Conwy LL16 5TY",
    "addr:postcode":"ll16 5ty",
    "addr:street":"The Square",
    "iso:country":"GB",
    "sg:address":"The Square, Trefnant",
    "sg:city":"Denbigh",
    "sg:classifiers":[
        {
            "category":"Government",
            "subcategory":"Post Office",
            "type":"Public Place"
        },
        {
            "category":"Food & Beverages",
            "subcategory":"Meat & Fish",
            "type":"Retail Goods"
        }
    ],
    "sg:phone":"+44 1745 730142",
    "sg:postcode":"LL16 5TY",
    "sg:province":"Conwy",
    "sg:tags":[
        "chip"
    ],
    "wof:name":"Trefnant Post Office",
    "wof:placetype":"venue"
},
  "geometry": {"coordinates":[-3.4296739101,53.229019165],"type":"Point"}
}