{
  "type": "Feature",
  "properties": {
    "addr:full":"Ederline Avenue London Greater London SW16 4RZ",
    "addr:postcode":"sw16 4rz",
    "addr:street":"Avenue",
    "iso:country":"GB",
    "sg:address":"Ederline Avenue",
    "sg:city":"London",
    "sg:classifiers":[
        {
            "category":"Farming",
            "subcategory":"Nursery",
            "type":"Manufacturing & Wholesale Goods"
        },
        {
            "category":"Arena",
            "subcategory":"Sports Club",
            "type":"Entertainment"
        }
    ],
    "sg:phone":"+44 20 8764 2531",
    "sg:postcode":"SW16 4RZ",
    "sg:province":"Greater London",
    "sg:tags":[
        "creche"
    ],
    "wof:name":"Norbury Park Lawn Tennis Club",
    "wof:placetype":"venue"
},
  "geometry": {"coordinates":[-0.1143139973,51.4052658081],"type":"Point"}
}