{
  "type": "Feature",
  "properties": {
    "addr:full":"Southfield Road, Kirkmuirhill Lanark South Lanarkshire ML11 9SA",
    "addr:postcode":"ml11 9sa",
    "addr:street":"Southfield Road Kirkmuirhill",
    "iso:country":"GB",
    "sg:address":"Southfield Road, Kirkmuirhill",
    "sg:city":"Lanark",
    "sg:classifiers":[
        {
            "category":"Government",
            "subcategory":"City Hall",
            "type":"Public Place"
        },
        {
            "category":"Government",
            "subcategory":"Office",
            "type":"Public Place"
        }
    ],
    "sg:phone":"+44 1555 893086",
    "sg:postcode":"ML11 9SA",
    "sg:province":"South Lanarkshire",
    "sg:tags":[
        "local"
    ],
    "wof:name":"Blackwood Hall",
    "wof:placetype":"venue"
},
  "geometry": {"coordinates":[-3.7813839912,55.673866272],"type":"Point"}
}