{
  "type": "Feature",
  "properties": {
    "addr:full":"29 Ambleside Close, Heswall Wirral Merseyside CH61 3XG",
    "addr:housenumber":"29",
    "addr:postcode":"ch61 3xg",
    "addr:street":"Ambleside Close",
    "iso:country":"GB",
    "sg:address":"29 Ambleside Close, Heswall",
    "sg:city":"Wirral",
    "sg:classifiers":[
        {
            "category":"Real Estate",
            "subcategory":"Developer",
            "type":"Services"
        }
    ],
    "sg:postcode":"CH61 3XG",
    "sg:province":"Merseyside",
    "sg:tags":[
        "property"
    ],
    "wof:name":"Alan Don Properties",
    "wof:placetype":"venue"
},
  "geometry": {"coordinates":[-3.0962669849,53.3537521362],"type":"Point"}
}