{
  "type": "Feature",
  "properties": {
    "iso:country":"GB",
    "sg:address":"Ellers House, 92 Market Street",
    "sg:city":"Ulverston",
    "sg:classifiers":[
        {
            "category":"Professional",
            "subcategory":"Lawyer & Legal Services",
            "type":"Services"
        }
    ],
    "sg:phone":"+44 1229 582283",
    "sg:postcode":"LA12 7LT",
    "sg:province":"Cumbria",
    "sg:tags":[
        "solicitor"
    ],
    "wof:name":"Denby & Co",
    "wof:placetype":"venue"
},
  "geometry": {"coordinates":[-3.093625,54.195663],"type":"Point"}
}