{
  "type": "Feature",
  "properties": {
    "addr:full":"Greenacre Place, Bannockburn Stirling Falkirk FK7 8PA",
    "addr:postcode":"fk7 8pa",
    "addr:street":"Greenacre Place",
    "iso:country":"GB",
    "sg:address":"Greenacre Place, Bannockburn",
    "sg:city":"Stirling",
    "sg:classifiers":[
        {
            "category":"Education",
            "subcategory":"Library",
            "type":"Public Place"
        },
        {
            "category":"Government",
            "subcategory":"Office",
            "type":"Public Place"
        }
    ],
    "sg:phone":"+44 1786 812286",
    "sg:postcode":"FK7 8PA",
    "sg:province":"Falkirk",
    "sg:tags":[
        "book",
        "local"
    ],
    "wof:name":"Bannockburn Library",
    "wof:placetype":"venue"
},
  "geometry": {"coordinates":[-3.9110839367,56.0899658203],"type":"Point"}
}