{
  "type": "Feature",
  "properties": {
    "iso:country":"GB",
    "sg:address":"21 Rossington Avenue",
    "sg:city":"Blackpool",
    "sg:classifiers":[
        {
            "category":"Building & Trades",
            "subcategory":"Construction",
            "type":"Services"
        }
    ],
    "sg:phone":"+44 1253 356462",
    "sg:postcode":"FY2 0DN",
    "sg:province":"Lancashire",
    "sg:tags":[
        "builder"
    ],
    "wof:name":"R W Jones Builders",
    "wof:placetype":"venue"
},
  "geometry": {"coordinates":[-3.032241106,53.8525352478],"type":"Point"}
}