{
  "type": "Feature",
  "properties": {
    "addr:full":"1m Albany Park Camberley Hampshire GU16 7PE",
    "addr:postcode":"gu16 7pe",
    "iso:country":"GB",
    "sg:address":"1m Albany Park",
    "sg:city":"Camberley",
    "sg:classifiers":[
        {
            "category":"Manufacturing",
            "subcategory":"Rubber & Plastics",
            "type":"Manufacturing & Wholesale Goods"
        }
    ],
    "sg:phone":"+44 1276 64446",
    "sg:postcode":"GU16 7PE",
    "sg:province":"Hampshire",
    "sg:tags":[
        "injection",
        "moulding"
    ],
    "wof:name":"Courtridge Ltd.",
    "wof:placetype":"venue"
},
  "geometry": {"coordinates":[-0.7509800196,51.3177566528],"type":"Point"}
}