{
  "type": "Feature",
  "properties": {
    "addr:full":"6 Scot Lane, Aspull Wigan Lancashire WN2 1YX",
    "addr:housenumber":"6",
    "addr:postcode":"wn2 1yx",
    "addr:street":"Scot Lane",
    "iso:country":"GB",
    "sg:address":"6 Scot Lane, Aspull",
    "sg:city":"Wigan",
    "sg:classifiers":[
        {
            "category":"Health Services",
            "subcategory":"Dentist",
            "type":"Services"
        }
    ],
    "sg:phone":"+44 1942 833595",
    "sg:postcode":"WN2 1YX",
    "sg:province":"Lancashire",
    "wof:name":"D R Pryce Dental Surgery",
    "wof:placetype":"venue"
},
  "geometry": {"coordinates":[-2.584643,53.569317],"type":"Point"}
}