{
  "type": "Feature",
  "properties": {
    "iso:country":"GB",
    "sg:address":"2278 Coventry Road, Sheldon",
    "sg:city":"Birmingham",
    "sg:classifiers":[
        {
            "category":"Restaurant",
            "type":"Food & Drink"
        }
    ],
    "sg:phone":"+44 121 722 2080",
    "sg:postcode":"B26 3JR",
    "sg:province":"West Midlands",
    "sg:tags":[
        "indian"
    ],
    "wof:name":"Titash International Tandoori",
    "wof:placetype":"venue"
},
  "geometry": {"coordinates":[-1.77719,52.451633],"type":"Point"}
}