{
  "type": "Feature",
  "properties": {
    "addr:full":"New Mill Street Dudley West Midlands DY2 8PB",
    "addr:postcode":"dy2 8pb",
    "addr:street":"New Mill Street",
    "iso:country":"GB",
    "sg:address":"New Mill Street",
    "sg:city":"Dudley",
    "sg:classifiers":[
        {
            "category":"Autos & Motor Vehicles",
            "subcategory":"Auto Supplies",
            "type":"Retail Goods"
        }
    ],
    "sg:phone":"+44 1384 257761",
    "sg:postcode":"DY2 8PB",
    "sg:province":"West Midlands",
    "sg:tags":[
        "tyre"
    ],
    "wof:name":"Hi-Q Tyre Services",
    "wof:placetype":"venue"
},
  "geometry": {"coordinates":[-2.083106,52.508595],"type":"Point"}
}