{
  "type": "Feature",
  "properties": {
    "addr:full":"White Hart Lodge, High Street, Ludgershall Aylesbury Buckinghamshire HP18 9PF",
    "addr:postcode":"hp18 9pf",
    "addr:street":"High Street",
    "iso:country":"GB",
    "sg:address":"White Hart Lodge, High Street, Ludgershall",
    "sg:city":"Aylesbury",
    "sg:classifiers":[
        {
            "category":"Manufacturing",
            "subcategory":"Toys & Sporting Goods",
            "type":"Manufacturing & Wholesale Goods"
        },
        {
            "category":"Shopping",
            "subcategory":"Hobbies, Toys, & Games",
            "type":"Retail Goods"
        }
    ],
    "sg:phone":"+44 1844 238033",
    "sg:postcode":"HP18 9PF",
    "sg:province":"Buckinghamshire",
    "sg:tags":[
        "product",
        "games",
        "manufacturer"
    ],
    "wof:name":"Cheatwell Games",
    "wof:placetype":"venue"
},
  "geometry": {"coordinates":[-1.04429,51.851749],"type":"Point"}
}