{
  "type": "Feature",
  "properties": {
    "iso:country":"GB",
    "sg:address":"45 Curlew St",
    "sg:city":"Southwark",
    "sg:classifiers":[
        {
            "category":"Recreation",
            "subcategory":"Gun Range",
            "type":"Entertainment"
        }
    ],
    "sg:phone":"+44 20 7234 0600",
    "sg:postcode":"SE1 2ND",
    "sg:province":"Greater London",
    "sg:tags":[
        "operator",
        "tour"
    ],
    "wof:name":"Galileo World Hotels & Cruise Ships",
    "wof:placetype":"venue"
},
  "geometry": {"coordinates":[-0.073369,51.5028],"type":"Point"}
}