{
  "type": "Feature",
  "properties": {
    "addr:full":"12220 Great Horton Road Bradford West Yorkshire BD7 4PL",
    "addr:housenumber":"12220",
    "addr:postcode":"bd7 4pl",
    "addr:street":"Great Horton Road",
    "iso:country":"GB",
    "sg:address":"12220 Great Horton Road",
    "sg:city":"Bradford",
    "sg:classifiers":[
        {
            "category":"Shopping",
            "subcategory":"Pharmacy",
            "type":"Retail Goods"
        }
    ],
    "sg:phone":"+44 1274 571822",
    "sg:postcode":"BD7 4PL",
    "sg:province":"West Yorkshire",
    "sg:tags":[
        "pharmacist",
        "chemist"
    ],
    "wof:name":"Handfore Ltd.",
    "wof:placetype":"venue"
},
  "geometry": {"coordinates":[-1.810199,53.7729],"type":"Point"}
}