{
  "type": "Feature",
  "properties": {
    "addr:full":"1 Old Hall Street Liverpool Merseyside L3 9HH",
    "addr:housenumber":"1",
    "addr:postcode":"l3 9hh",
    "addr:street":"Old Hall Street",
    "iso:country":"GB",
    "sg:address":"1 Old Hall Street",
    "sg:city":"Liverpool",
    "sg:classifiers":[
        {
            "category":"Professional",
            "subcategory":"Management & Consulting",
            "type":"Services"
        }
    ],
    "sg:phone":"+44 151 334 1223",
    "sg:postcode":"L3 9HH",
    "sg:province":"Merseyside",
    "sg:tags":[
        "marketing",
        "consultant"
    ],
    "wof:name":"Admaster Towncentre Marketing",
    "wof:placetype":"venue"
},
  "geometry": {"coordinates":[-2.992997,53.408337],"type":"Point"}
}