{
  "type": "Feature",
  "properties": {
    "iso:country":"GB",
    "sg:address":"Copley Lane, Copley",
    "sg:city":"Bishop Auckland",
    "sg:classifiers":[
        {
            "category":"Transit Center",
            "subcategory":"Passenger",
            "type":"Transportation"
        }
    ],
    "sg:phone":"+44 1388 718161",
    "sg:postcode":"DL13 5LW",
    "sg:province":"Durham",
    "sg:tags":[
        "boarding",
        "kennel",
        "catteries"
    ],
    "wof:name":"Glencrest Boarding Kennels & Cattery",
    "wof:placetype":"venue"
},
  "geometry": {"coordinates":[-1.8649090528,54.6231536865],"type":"Point"}
}