{
  "type": "Feature",
  "properties": {
    "addr:full":"9 Castleton Road Wigston Leicestershire LE18 1FQ",
    "addr:housenumber":"9",
    "addr:postcode":"le18 1fq",
    "addr:street":"Castleton Road",
    "iso:country":"GB",
    "sg:address":"9 Castleton Road",
    "sg:city":"Wigston",
    "sg:classifiers":[
        {
            "category":"Building & Trades",
            "subcategory":"Plumbing",
            "type":"Services"
        }
    ],
    "sg:postcode":"LE18 1FQ",
    "sg:province":"Leicestershire",
    "sg:tags":[
        "heating"
    ],
    "wof:name":"B S Plumbing & Heating Services",
    "wof:placetype":"venue"
},
  "geometry": {"coordinates":[-1.1109739542,52.5919723511],"type":"Point"}
}