{
  "type": "Feature",
  "properties": {
    "iso:country":"GB",
    "sg:address":"Stockport Road",
    "sg:city":"Hyde",
    "sg:classifiers":[
        {
            "category":"Social Services",
            "subcategory":"Retirement Home",
            "type":"Services"
        }
    ],
    "sg:phone":"+44 161 368 2615",
    "sg:postcode":"SK14 5EZ",
    "sg:province":"Cheshire",
    "sg:tags":[
        "rest"
    ],
    "wof:name":"Bowlacre Home",
    "wof:placetype":"venue"
},
  "geometry": {"coordinates":[-2.069984,53.445107],"type":"Point"}
}