{
  "type": "Feature",
  "properties": {
    "iso:country":"GB",
    "sg:address":"2 The Crescent",
    "sg:city":"Wembley",
    "sg:classifiers":[
        {
            "category":"Retail",
            "subcategory":"Laundry & Dry Cleaning",
            "type":"Services"
        }
    ],
    "sg:phone":"+44 20 8908 2744",
    "sg:postcode":"HA0 3JR",
    "sg:province":"Greater London",
    "sg:tags":[
        "home",
        "ironing"
    ],
    "wof:name":"Crescent",
    "wof:placetype":"venue"
},
  "geometry": {"coordinates":[-0.3208720088,51.5669288635],"type":"Point"}
}