{
  "type": "Feature",
  "properties": {
    "iso:country":"GB",
    "sg:address":"Fairfield Court, Brookland",
    "sg:city":"Romney Marsh",
    "sg:classifiers":[
        {
            "category":"Home & Garden",
            "subcategory":"Garden Supply",
            "type":"Retail Goods"
        }
    ],
    "sg:phone":"+44 1797 344731",
    "sg:postcode":"TN29 9RX",
    "sg:province":"Kent",
    "sg:tags":[
        "turfing"
    ],
    "wof:name":"Fairfield Turf Ltd.",
    "wof:placetype":"venue"
},
  "geometry": {"coordinates":[0.8347110152,50.9978523254],"type":"Point"}
}