{
  "type": "Feature",
  "properties": {
    "addr:full":"48 Church Street, Caversham Reading Berkshire RG4 8AU",
    "addr:housenumber":"48",
    "addr:postcode":"rg4 8au",
    "addr:street":"Church Street",
    "iso:country":"GB",
    "sg:address":"48 Church Street, Caversham",
    "sg:city":"Reading",
    "sg:classifiers":[
        {
            "category":"Personal",
            "subcategory":"Beauty Salon",
            "type":"Services"
        }
    ],
    "sg:phone":"+44 118 947 3340",
    "sg:postcode":"RG4 8AU",
    "sg:province":"Berkshire",
    "sg:tags":[
        "unisex",
        "hairdresser"
    ],
    "wof:name":"Harris & Paul",
    "wof:placetype":"venue"
},
  "geometry": {"coordinates":[-0.973263,51.467613],"type":"Point"}
}