{
  "type": "Feature",
  "properties": {
    "addr:full":"Dawson Street Heywood Lancashire OL10 4PU",
    "addr:postcode":"ol10 4pu",
    "addr:street":"Dawson Street",
    "iso:country":"GB",
    "sg:address":"Dawson Street",
    "sg:city":"Heywood",
    "sg:classifiers":[
        {
            "category":"Food & Beverages",
            "subcategory":"Supermarket",
            "type":"Retail Goods"
        }
    ],
    "sg:phone":"+44 1706 360036",
    "sg:postcode":"OL10 4PU",
    "sg:province":"Lancashire",
    "wof:name":"WM MORRISON SUPERMARKETS P L C",
    "wof:placetype":"venue"
},
  "geometry": {"coordinates":[-2.2234098911,53.5940513611],"type":"Point"}
}