{
  "type": "Feature",
  "properties": {
    "addr:full":"288 Strathtay Road Perth Perth and Kinross PH1 2JU",
    "addr:housenumber":"288",
    "addr:postcode":"ph1 2ju",
    "addr:street":"Strathtay Road",
    "iso:country":"GB",
    "sg:address":"288 Strathtay Road",
    "sg:city":"Perth",
    "sg:classifiers":[
        {
            "category":"Retail",
            "subcategory":"Auto Repair",
            "type":"Services"
        }
    ],
    "sg:phone":"+44 1738 627800",
    "sg:postcode":"PH1 2JU",
    "sg:province":"Perth and Kinross",
    "sg:tags":[
        "body",
        "car"
    ],
    "wof:name":"Donald Kirk Ltd.",
    "wof:placetype":"venue"
},
  "geometry": {"coordinates":[-3.4744799137,56.4068412781],"type":"Point"}
}