{
  "type": "Feature",
  "properties": {
    "iso:country":"GB",
    "sg:address":"196 High Street",
    "sg:city":"Guildford",
    "sg:classifiers":[
        {
            "category":"Shopping",
            "subcategory":"Crafts & Fabrics",
            "type":"Retail Goods"
        }
    ],
    "sg:phone":"+44 1483 572550",
    "sg:postcode":"GU1 3HZ",
    "sg:province":"Surrey",
    "sg:tags":[
        "shop",
        "needlecraft",
        "wool",
        "retailer"
    ],
    "wof:name":"Pandora Wools",
    "wof:placetype":"venue"
},
  "geometry": {"coordinates":[-0.569428,51.236504],"type":"Point"}
}