{
  "type": "Feature",
  "properties": {
    "iso:country":"GB",
    "sg:address":"Special Educational Needs Section, Poplar Rd",
    "sg:city":"Cleethorpes",
    "sg:classifiers":[
        {
            "category":"Government",
            "subcategory":"Office",
            "type":"Public Place"
        }
    ],
    "sg:phone":"+44 1472 323166",
    "sg:postcode":"DN35 8BH",
    "sg:province":"Lincolnshire",
    "sg:tags":[
        "local"
    ],
    "wof:name":"North East Lincolnshire Council",
    "wof:placetype":"venue"
},
  "geometry": {"coordinates":[-0.039359,53.55949],"type":"Point"}
}