{
  "type": "Feature",
  "properties": {
    "iso:country":"GB",
    "sg:address":"St Tynewydd Road",
    "sg:city":"Barry",
    "sg:classifiers":[
        {
            "category":"Retail",
            "subcategory":"Veterinary Services",
            "type":"Services"
        }
    ],
    "sg:phone":"+44 1446 733406",
    "sg:postcode":"CF62 8AZ",
    "sg:province":"The Vale of Glamorgan",
    "sg:tags":[
        "surgeon"
    ],
    "wof:name":"The Animals Health Centre",
    "wof:placetype":"venue"
},
  "geometry": {"coordinates":[-3.2705190182,51.4094543457],"type":"Point"}
}