{
  "type": "Feature",
  "properties": {
    "addr:full":"High St Swindon Wiltshire SN4 7AB",
    "addr:postcode":"sn4 7ab",
    "addr:street":"High St",
    "iso:country":"GB",
    "sg:address":"High St",
    "sg:city":"Swindon",
    "sg:classifiers":[
        {
            "category":"Government",
            "subcategory":"Police Station",
            "type":"Public Place"
        }
    ],
    "sg:phone":"+44 1793 852213",
    "sg:postcode":"SN4 7AB",
    "sg:province":"Wiltshire",
    "sg:tags":[
        "support"
    ],
    "wof:name":"Wootton Bassett Police Station",
    "wof:placetype":"venue"
},
  "geometry": {"coordinates":[-1.8992209435,51.5454521179],"type":"Point"}
}