{
  "type": "Feature",
  "properties": {
    "addr:full":"The Pavilion 46 Horkstow Rd Barton Upon Humber Lincolnshire DN18 5DZ",
    "addr:housenumber":"46",
    "addr:postcode":"dn18 5dz",
    "addr:street":"Horkstow Rd",
    "iso:country":"GB",
    "sg:address":"The Pavilion 46 Horkstow Rd",
    "sg:city":"Barton Upon Humber",
    "sg:classifiers":[
        {
            "category":"Shopping",
            "subcategory":"Pharmacy",
            "type":"Retail Goods"
        }
    ],
    "sg:phone":"+44 1652 660617",
    "sg:postcode":"DN18 5DZ",
    "sg:province":"Lincolnshire",
    "sg:tags":[
        "medicine",
        "therapy"
    ],
    "wof:name":"The Gentle Touch",
    "wof:placetype":"venue"
},
  "geometry": {"coordinates":[-0.4432410002,53.6844482422],"type":"Point"}
}