{
  "type": "Feature",
  "properties": {
    "iso:country":"GB",
    "sg:address":"Town Cass",
    "sg:city":"Keswick",
    "sg:classifiers":[
        {
            "category":"Recreation",
            "subcategory":"Campground",
            "type":"Entertainment"
        }
    ],
    "sg:phone":"+44 17687 72878",
    "sg:postcode":"CA12 5EW",
    "sg:province":"Cumbria",
    "sg:tags":[
        "caravan",
        "park"
    ],
    "wof:name":"Lakeside Holiday Park",
    "wof:placetype":"venue"
},
  "geometry": {"coordinates":[-3.1389639378,54.6017303467],"type":"Point"}
}