{
  "type": "Feature",
  "properties": {
    "addr:full":"Baird Street Glasgow Glasgow City G4 0AG",
    "addr:postcode":"g4 0ag",
    "addr:street":"Baird Street",
    "iso:country":"GB",
    "sg:address":"Baird Street",
    "sg:city":"Glasgow",
    "sg:classifiers":[
        {
            "category":"Shopping",
            "subcategory":"Computers & Home Electronics",
            "type":"Retail Goods"
        }
    ],
    "sg:phone":"+44 141 552 0009",
    "sg:postcode":"G4 0AG",
    "sg:province":"Glasgow City",
    "wof:name":"Time Computers Ltd.",
    "wof:placetype":"venue"
},
  "geometry": {"coordinates":[-4.24507,55.868351],"type":"Point"}
}