{
  "type": "Feature",
  "properties": {
    "addr:full":"Denmark House, Brick Close Milton Keynes Buckinghamshire MK11 3DP",
    "addr:postcode":"mk11 3dp",
    "addr:street":"Brick Close",
    "iso:country":"GB",
    "sg:address":"Denmark House, Brick Close",
    "sg:city":"Milton Keynes",
    "sg:classifiers":[
        {
            "category":"Manufacturing",
            "subcategory":"Wood Products",
            "type":"Manufacturing & Wholesale Goods"
        }
    ],
    "sg:phone":"+44 1908 261333",
    "sg:postcode":"MK11 3DP",
    "sg:province":"Buckinghamshire",
    "sg:tags":[
        "packaging",
        "crate",
        "pallets"
    ],
    "wof:name":"Danisco Flexible",
    "wof:placetype":"venue"
},
  "geometry": {"coordinates":[-0.8196989894,52.0422515869],"type":"Point"}
}