{
  "type": "Feature",
  "properties": {
    "iso:country":"GB",
    "sg:address":"5 Freemantle Business Centre, 152 Millbrook Road East",
    "sg:city":"Southampton",
    "sg:classifiers":[
        {
            "category":"Real Estate",
            "subcategory":"Architect",
            "type":"Services"
        }
    ],
    "sg:postcode":"SO15 1JR",
    "sg:province":"Hampshire",
    "wof:name":"Tony Oldfield Architects Ltd",
    "wof:placetype":"venue"
},
  "geometry": {"coordinates":[-1.407319,50.909939],"type":"Point"}
}