{
  "type": "Feature",
  "properties": {
    "addr:full":"33 Roath Court Road Cardiff Cardiff CF24 3SD",
    "addr:housenumber":"33",
    "addr:postcode":"cf24 3sd",
    "addr:street":"Roath Court Road",
    "iso:country":"GB",
    "sg:address":"33 Roath Court Road",
    "sg:city":"Cardiff",
    "sg:classifiers":[
        {
            "category":"Education",
            "subcategory":"Music School",
            "type":"Public Place"
        }
    ],
    "sg:postcode":"CF24 3SD",
    "sg:province":"Cardiff",
    "sg:tags":[
        "teacher"
    ],
    "wof:name":"Kathryn Fathers",
    "wof:placetype":"venue"
},
  "geometry": {"coordinates":[-3.160382,51.492188],"type":"Point"}
}