{
  "type": "Feature",
  "properties": {
    "addr:full":"15 Box Lane, Acton Wrexham Wrexham LL12 8BY",
    "addr:housenumber":"15",
    "addr:postcode":"ll12 8by",
    "addr:street":"Box Lane",
    "iso:country":"GB",
    "sg:address":"15 Box Lane, Acton",
    "sg:city":"Wrexham",
    "sg:classifiers":[
        {
            "category":"Retail",
            "subcategory":"Repair Shop",
            "type":"Services"
        },
        {
            "category":"Manufacturing",
            "subcategory":"Furniture",
            "type":"Manufacturing & Wholesale Goods"
        }
    ],
    "sg:phone":"+44 1978 264484",
    "sg:postcode":"LL12 8BY",
    "sg:province":"Wrexham",
    "sg:tags":[
        "mnfr",
        "upholsterer"
    ],
    "wof:name":"Barrie Joseph Shovelton",
    "wof:placetype":"venue"
},
  "geometry": {"coordinates":[-2.9885590076,53.0610351562],"type":"Point"}
}