{
  "type": "Feature",
  "properties": {
    "iso:country":"GB",
    "sg:address":"41 Thorn Rd",
    "sg:city":"Worthing",
    "sg:classifiers":[
        {
            "category":"Professional",
            "subcategory":"Engineering",
            "type":"Services"
        }
    ],
    "sg:phone":"+44 1903 216277",
    "sg:postcode":"BN11 3ND",
    "sg:province":"West Sussex",
    "sg:tags":[
        "civil",
        "engineer"
    ],
    "wof:name":"Hynes Construction",
    "wof:placetype":"venue"
},
  "geometry": {"coordinates":[-0.380742,50.809795],"type":"Point"}
}