{
  "type": "Feature",
  "properties": {
    "addr:full":"Pepperbox Works, Herriard Basingstoke Hampshire RG25 2PQ",
    "addr:postcode":"rg25 2pq",
    "iso:country":"GB",
    "sg:address":"Pepperbox Works, Herriard",
    "sg:city":"Basingstoke",
    "sg:classifiers":[
        {
            "category":"Manufacturing",
            "subcategory":"Tools & Machinery",
            "type":"Manufacturing & Wholesale Goods"
        }
    ],
    "sg:phone":"+44 1256 381239",
    "sg:postcode":"RG25 2PQ",
    "sg:province":"Hampshire",
    "sg:tags":[
        "design",
        "maker"
    ],
    "wof:name":"Advanced Precision Tools Ltd.",
    "wof:placetype":"venue"
},
  "geometry": {"coordinates":[-1.044324,51.203754],"type":"Point"}
}