{
  "type": "Feature",
  "properties": {
    "addr:full":"396 Heol Las Clo, Birchgrove Swansea Neath Port Talbot SA7 9DP",
    "addr:housenumber":"396",
    "addr:postcode":"sa7 9dp",
    "addr:street":"Heol Las Clo",
    "iso:country":"GB",
    "sg:address":"396 Heol Las Clo, Birchgrove",
    "sg:city":"Swansea",
    "sg:classifiers":[
        {
            "category":"Bars & Pubs",
            "type":"Food & Drink"
        },
        {
            "category":"Building & Trades",
            "subcategory":"Cleaning & Sanitation",
            "type":"Services"
        }
    ],
    "sg:phone":"+44 1792 771181",
    "sg:postcode":"SA7 9DP",
    "sg:province":"Neath Port Talbot",
    "sg:tags":[
        "pubs",
        "inn",
        "sweep",
        "chimney"
    ],
    "wof:name":"Bartlett,Eric,",
    "wof:placetype":"venue"
},
  "geometry": {"coordinates":[-3.887969,51.669994],"type":"Point"}
}