{
  "type": "Feature",
  "properties": {
    "addr:full":"Elm Road North Shields Tyne and Wear NE29 8SA",
    "addr:postcode":"ne29 8sa",
    "addr:street":"Elm Road",
    "iso:country":"GB",
    "sg:address":"Elm Road",
    "sg:city":"North Shields",
    "sg:classifiers":[
        {
            "category":"Manufacturing",
            "subcategory":"Tools & Machinery",
            "type":"Manufacturing & Wholesale Goods"
        }
    ],
    "sg:phone":"+44 191 258 2821",
    "sg:postcode":"NE29 8SA",
    "sg:province":"Tyne and Wear",
    "sg:tags":[
        "monitoring",
        "temperature",
        "thermometer"
    ],
    "wof:name":"Elmwood Sensors Ltd.",
    "wof:placetype":"venue"
},
  "geometry": {"coordinates":[-1.491889,55.019096],"type":"Point"}
}