{
  "type": "Feature",
  "properties": {
    "addr:full":"26 Sumner Street, Shaw Oldham Lancashire OL2 8RY",
    "addr:housenumber":"26",
    "addr:postcode":"ol2 8ry",
    "addr:street":"Sumner Street",
    "iso:country":"GB",
    "sg:address":"26 Sumner Street, Shaw",
    "sg:city":"Oldham",
    "sg:classifiers":[
        {
            "category":"Building & Trades",
            "subcategory":"Construction",
            "type":"Services"
        }
    ],
    "sg:phone":"+44 1706 849721",
    "sg:postcode":"OL2 8RY",
    "sg:province":"Lancashire",
    "sg:tags":[
        "joiner",
        "carpenter"
    ],
    "wof:name":"Nick Warburton",
    "wof:placetype":"venue"
},
  "geometry": {"coordinates":[-2.096477,53.572102],"type":"Point"}
}