{
  "type": "Feature",
  "properties": {
    "addr:full":"229 Abbey Lane Leicester Leicestershire LE4 5QH",
    "addr:housenumber":"229",
    "addr:postcode":"le4 5qh",
    "addr:street":"Abbey Lane",
    "iso:country":"GB",
    "sg:address":"229 Abbey Lane",
    "sg:city":"Leicester",
    "sg:classifiers":[
        {
            "category":"Autos & Motor Vehicles",
            "subcategory":"Automobile Sales",
            "type":"Retail Goods"
        }
    ],
    "sg:postcode":"LE4 5QH",
    "sg:province":"Leicestershire",
    "sg:tags":[
        "car"
    ],
    "wof:name":"Avalon Motor Co.",
    "wof:placetype":"venue"
},
  "geometry": {"coordinates":[-1.133868,52.657364],"type":"Point"}
}