{
  "type": "Feature",
  "properties": {
    "addr:full":"2 Chiswick Park Station London Greater London W4 5EB",
    "addr:housenumber":"2",
    "addr:postcode":"w4 5eb",
    "addr:street":"Chiswick Park",
    "iso:country":"GB",
    "sg:address":"2 Chiswick Park Station",
    "sg:city":"London",
    "sg:classifiers":[
        {
            "category":"Shopping",
            "subcategory":"Antiques",
            "type":"Retail Goods"
        }
    ],
    "sg:phone":"+44 20 8995 8930",
    "sg:postcode":"W4 5EB",
    "sg:province":"Greater London",
    "wof:name":"Chiswick Art Shop",
    "wof:placetype":"venue"
},
  "geometry": {"coordinates":[-0.2697120011,51.4929542542],"type":"Point"}
}