{
  "type": "Feature",
  "properties": {
    "addr:full":"40a Mkt Pl Wokingham Berkshire RG40 1AT",
    "addr:housenumber":"40a",
    "addr:postcode":"pl;rg40 1at",
    "addr:street":"Mkt",
    "iso:country":"GB",
    "sg:address":"40a Mkt Pl",
    "sg:city":"Wokingham",
    "sg:classifiers":[
        {
            "category":"Professional",
            "subcategory":"Art Services",
            "type":"Services"
        }
    ],
    "sg:postcode":"RG40 1AT",
    "sg:province":"Berkshire",
    "sg:tags":[
        "photographer"
    ],
    "wof:name":"Kodak Processing",
    "wof:placetype":"venue"
},
  "geometry": {"coordinates":[-0.821899,51.41338],"type":"Point"}
}