{
  "type": "Feature",
  "properties": {
    "addr:full":"13 Castle Terr Edinburgh City of Edinburgh EH1 2DP",
    "addr:housenumber":"13",
    "addr:postcode":"eh1 2dp",
    "addr:street":"Castle Terr",
    "iso:country":"GB",
    "sg:address":"13 Castle Terr",
    "sg:city":"Edinburgh",
    "sg:classifiers":[
        {
            "category":"Building & Trades",
            "subcategory":"Construction",
            "type":"Services"
        }
    ],
    "sg:postcode":"EH1 2DP",
    "sg:province":"City of Edinburgh",
    "sg:tags":[
        "builder"
    ],
    "wof:name":"Rider Associates Ltd",
    "wof:placetype":"venue"
},
  "geometry": {"coordinates":[-3.204767,55.948132],"type":"Point"}
}