{
  "type": "Feature",
  "properties": {
    "addr:full":"27 Fairley Street Glasgow Glasgow City G51 2SN",
    "addr:housenumber":"27",
    "addr:postcode":"g51 2sn",
    "addr:street":"Fairley Street",
    "iso:country":"GB",
    "sg:address":"27 Fairley Street",
    "sg:city":"Glasgow",
    "sg:classifiers":[
        {
            "category":"Professional",
            "type":"Services"
        }
    ],
    "sg:phone":"+44 141 427 2061",
    "sg:postcode":"G51 2SN",
    "sg:province":"Glasgow City",
    "sg:tags":[
        "shopfitters"
    ],
    "wof:name":"Regent Shopfitter",
    "wof:placetype":"venue"
},
  "geometry": {"coordinates":[-4.303561,55.85334],"type":"Point"}
}