{
  "type": "Feature",
  "properties": {
    "addr:full":"Quarry Cottage, Walworth Darlington Durham DL2 2LY",
    "addr:postcode":"dl2 2ly",
    "iso:country":"GB",
    "sg:address":"Quarry Cottage, Walworth",
    "sg:city":"Darlington",
    "sg:classifiers":[
        {
            "category":"Professional",
            "subcategory":"Accounting & Tax Preparation",
            "type":"Services"
        },
        {
            "category":"Real Estate",
            "subcategory":"Architect",
            "type":"Services"
        }
    ],
    "sg:phone":"+44 1325 486144",
    "sg:postcode":"DL2 2LY",
    "sg:province":"Durham",
    "sg:tags":[
        "accountant"
    ],
    "wof:name":"Solid Ideas Ltd.",
    "wof:placetype":"venue"
},
  "geometry": {"coordinates":[-1.644929,54.566303],"type":"Point"}
}