{
  "type": "Feature",
  "properties": {
    "iso:country":"GB",
    "sg:address":"Unit 18 Elmdon Trading Estate",
    "sg:city":"Birmingham",
    "sg:classifiers":[
        {
            "category":"Freight",
            "type":"Transportation"
        }
    ],
    "sg:phone":"+44 121 780 3800",
    "sg:postcode":"B37 7HE",
    "sg:province":"West Midlands",
    "sg:tags":[
        "forwarders"
    ],
    "wof:name":"All Ways Forward (Cheltenham) Ltd.",
    "wof:placetype":"venue"
},
  "geometry": {"coordinates":[-1.747839,52.46611],"type":"Point"}
}