{
  "type": "Feature",
  "properties": {
    "addr:full":"3 Barfield Close Winchester Hampshire SO23 9SQ",
    "addr:housenumber":"3",
    "addr:postcode":"so23 9sq",
    "addr:street":"Barfield Close",
    "iso:country":"GB",
    "sg:address":"3 Barfield Close",
    "sg:city":"Winchester",
    "sg:classifiers":[
        {
            "category":"Retail",
            "subcategory":"Veterinary Services",
            "type":"Services"
        }
    ],
    "sg:phone":"+44 870 243 0384",
    "sg:postcode":"SO23 9SQ",
    "sg:province":"Hampshire",
    "sg:tags":[
        "pharmacy"
    ],
    "wof:name":"Vetark Products Ltd.",
    "wof:placetype":"venue"
},
  "geometry": {"coordinates":[-1.307161,51.05661],"type":"Point"}
}