{
  "type": "Feature",
  "properties": {
    "iso:country":"GB",
    "sg:address":"Windsor Road, Treforest",
    "sg:city":"Pontypridd",
    "sg:classifiers":[
        {
            "category":"Shopping",
            "subcategory":"Computers & Home Electronics",
            "type":"Retail Goods"
        }
    ],
    "sg:phone":"+44 1443 493169",
    "sg:postcode":"CF37 1BX",
    "sg:province":"Caerphilly",
    "sg:tags":[
        "electrical"
    ],
    "wof:name":"Troy Electrical Supplies",
    "wof:placetype":"venue"
},
  "geometry": {"coordinates":[-3.3309590816,51.5975494385],"type":"Point"}
}