{
  "type": "Feature",
  "properties": {
    "iso:country":"GB",
    "sg:address":"Mazars The Atrium",
    "sg:city":"Luton",
    "sg:classifiers":[
        {
            "category":"Professional",
            "subcategory":"Computer Services",
            "type":"Services"
        }
    ],
    "sg:phone":"+44 1582 477839",
    "sg:postcode":"LU1 3BE",
    "sg:province":"Bedfordshire",
    "sg:tags":[
        "system",
        "software"
    ],
    "wof:name":"Komputers in Action Ltd.",
    "wof:placetype":"venue"
},
  "geometry": {"coordinates":[-0.415615,51.881336],"type":"Point"}
}