{
  "type": "Feature",
  "properties": {
    "addr:full":"789-791 Commercial Road London Greater London E14 7HG",
    "addr:housenumber":"789-791",
    "addr:postcode":"e14 7hg",
    "addr:street":"Commercial Road",
    "iso:country":"GB",
    "sg:address":"789-791 Commercial Road",
    "sg:city":"London",
    "sg:classifiers":[
        {
            "category":"Shopping",
            "subcategory":"Bicycles & Sporting Goods",
            "type":"Retail Goods"
        }
    ],
    "sg:phone":"+44 20 7987 4246",
    "sg:postcode":"E14 7HG",
    "sg:province":"Greater London",
    "sg:tags":[
        "equipment",
        "camping"
    ],
    "wof:name":"Cover",
    "wof:placetype":"venue"
},
  "geometry": {"coordinates":[-0.030708,51.512508],"type":"Point"}
}