{
  "type": "Feature",
  "properties": {
    "iso:country":"GB",
    "sg:address":"100 King Avenue, Holland On Sea",
    "sg:city":"Clacton-on-sea",
    "sg:classifiers":[
        {
            "category":"Real Estate",
            "subcategory":"Surveying",
            "type":"Services"
        }
    ],
    "sg:phone":"+44 1255 812200",
    "sg:postcode":"CO15 5EP",
    "sg:province":"Essex",
    "sg:tags":[
        "surveyor",
        "valuer"
    ],
    "wof:name":"Leslie J Long",
    "wof:placetype":"venue"
},
  "geometry": {"coordinates":[1.1820060015,51.8026542664],"type":"Point"}
}