{
  "type": "Feature",
  "properties": {
    "addr:full":"7 Hill Street Haverfordwest Pembrokeshire SA61 1QQ",
    "addr:housenumber":"7",
    "addr:postcode":"sa61 1qq",
    "addr:street":"Hill Street",
    "iso:country":"GB",
    "sg:address":"7 Hill Street",
    "sg:city":"Haverfordwest",
    "sg:classifiers":[
        {
            "category":"Cinema",
            "subcategory":"Movie Rental",
            "type":"Entertainment"
        }
    ],
    "sg:phone":"+44 1437 763793",
    "sg:postcode":"SA61 1QQ",
    "sg:province":"Pembrokeshire",
    "sg:tags":[
        "video",
        "library"
    ],
    "wof:name":"Star Video",
    "wof:placetype":"venue"
},
  "geometry": {"coordinates":[-4.9711561203,51.8001174927],"type":"Point"}
}