{
  "type": "Feature",
  "properties": {
    "addr:full":"15 Courtenay Road, Parkstone Poole Dorset BH14 0HD",
    "addr:housenumber":"15",
    "addr:postcode":"bh14 0hd",
    "addr:street":"Courtenay Road",
    "iso:country":"GB",
    "sg:address":"15 Courtenay Road, Parkstone",
    "sg:city":"Poole",
    "sg:classifiers":[
        {
            "category":"Building & Trades",
            "subcategory":"Construction",
            "type":"Services"
        }
    ],
    "sg:phone":"+44 1202 743778",
    "sg:postcode":"BH14 0HD",
    "sg:province":"Dorset",
    "sg:tags":[
        "roofing",
        "bricklaying"
    ],
    "wof:name":"David R Allison",
    "wof:placetype":"venue"
},
  "geometry": {"coordinates":[-1.9474309683,50.7260780334],"type":"Point"}
}