{
  "type": "Feature",
  "properties": {
    "iso:country":"GB",
    "sg:address":"12 York Gate",
    "sg:city":"London",
    "sg:classifiers":[
        {
            "category":"Real Estate",
            "subcategory":"Real Estate Agent",
            "type":"Services"
        }
    ],
    "sg:postcode":"NW1 4QS",
    "sg:province":"Greater London",
    "wof:name":"Nextluxury Ltd",
    "wof:placetype":"venue"
},
  "geometry": {"coordinates":[-0.15284,51.523335],"type":"Point"}
}