{
  "type": "Feature",
  "properties": {
    "addr:full":"66 Dundonald Av Abergele Conwy LL22 7PG",
    "addr:housenumber":"66",
    "addr:postcode":"ll22 7pg",
    "addr:street":"Dundonald Av",
    "iso:country":"GB",
    "sg:address":"66 Dundonald Av",
    "sg:city":"Abergele",
    "sg:classifiers":[
        {
            "category":"Building & Trades",
            "subcategory":"Plumbing",
            "type":"Services"
        }
    ],
    "sg:phone":"+44 1745 833481",
    "sg:postcode":"LL22 7PG",
    "sg:province":"Conwy",
    "sg:tags":[
        "heating"
    ],
    "wof:name":"E Morris",
    "wof:placetype":"venue"
},
  "geometry": {"coordinates":[-3.5810580254,53.291557312],"type":"Point"}
}