{
  "type": "Feature",
  "properties": {
    "iso:country":"GB",
    "sg:address":"Lichfield Road",
    "sg:city":"Bristol",
    "sg:classifiers":[
        {
            "category":"Education",
            "subcategory":"School",
            "type":"Public Place"
        },
        {
            "category":"Government",
            "subcategory":"Office",
            "type":"Public Place"
        }
    ],
    "sg:phone":"+44 117 977 5736",
    "sg:postcode":"BS4 4BJ",
    "sg:province":"City of Bristol",
    "sg:tags":[
        "local",
        "authority"
    ],
    "wof:name":"St. Anne's Park Primary School",
    "wof:placetype":"venue"
},
  "geometry": {"coordinates":[-2.5419340134,51.4518966675],"type":"Point"}
}