{
  "type": "Feature",
  "properties": {
    "iso:country":"GB",
    "sg:address":"Solway House, Moss Bay Rd",
    "sg:city":"Workington",
    "sg:classifiers":[
        {
            "category":"Professional",
            "subcategory":"Employment Agencies",
            "type":"Services"
        }
    ],
    "sg:phone":"+44 1900 607320",
    "sg:postcode":"CA14 3XH",
    "sg:province":"Cumbria",
    "sg:tags":[
        "consultant"
    ],
    "wof:name":"Onsite Scotia",
    "wof:placetype":"venue"
},
  "geometry": {"coordinates":[-3.556824,54.635418],"type":"Point"}
}