{
  "type": "Feature",
  "properties": {
    "iso:country":"GB",
    "sg:address":"80 Northfield Road, Church Crookham",
    "sg:city":"Fleet",
    "sg:classifiers":[
        {
            "category":"Building & Trades",
            "subcategory":"Construction",
            "type":"Services"
        }
    ],
    "sg:phone":"+44 1252 816981",
    "sg:postcode":"GU52 6EB",
    "sg:province":"Hampshire",
    "sg:tags":[
        "contractor"
    ],
    "wof:name":"Sewer Sealing Services Ltd.",
    "wof:placetype":"venue"
},
  "geometry": {"coordinates":[-0.823101,51.265247],"type":"Point"}
}