{
  "type": "Feature",
  "properties": {
    "addr:full":"9 West Park Avenue, Savick Estate Preston Lancashire PR2 1UH",
    "addr:housenumber":"9",
    "addr:postcode":"pr2 1uh",
    "addr:street":"West Park Avenue Savick Estate",
    "iso:country":"GB",
    "sg:address":"9 West Park Avenue, Savick Estate",
    "sg:city":"Preston",
    "sg:classifiers":[
        {
            "category":"Cinema",
            "subcategory":"Movie Rental",
            "type":"Entertainment"
        }
    ],
    "sg:postcode":"PR2 1UH",
    "sg:province":"Lancashire",
    "sg:tags":[
        "video",
        "library"
    ],
    "wof:name":"10 To 10 Video",
    "wof:placetype":"venue"
},
  "geometry": {"coordinates":[-2.7545158863,53.7695274353],"type":"Point"}
}