{
  "type": "Feature",
  "properties": {
    "addr:full":"30 Bligh Clo Teignmouth Devon TQ14 9NQ",
    "addr:housenumber":"30",
    "addr:postcode":"tq14 9nq",
    "addr:street":"Bligh Clo",
    "iso:country":"GB",
    "sg:address":"30 Bligh Clo",
    "sg:city":"Teignmouth",
    "sg:classifiers":[
        {
            "category":"Building & Trades",
            "subcategory":"Plumbing",
            "type":"Services"
        }
    ],
    "sg:phone":"+44 1626 770120",
    "sg:postcode":"TQ14 9NQ",
    "sg:province":"Devon",
    "sg:tags":[
        "central",
        "heating"
    ],
    "wof:name":"Osborne Gas Service",
    "wof:placetype":"venue"
},
  "geometry": {"coordinates":[-3.5094199181,50.5605812073],"type":"Point"}
}