{
  "type": "Feature",
  "properties": {
    "addr:full":"14 Highview Street Dudley West Midlands DY2 7JR",
    "addr:housenumber":"14",
    "addr:postcode":"dy2 7jr",
    "addr:street":"Highview Street",
    "iso:country":"GB",
    "sg:address":"14 Highview Street",
    "sg:city":"Dudley",
    "sg:classifiers":[
        {
            "category":"Cinema",
            "subcategory":"Movie Rental",
            "type":"Entertainment"
        }
    ],
    "sg:postcode":"DY2 7JR",
    "sg:province":"West Midlands",
    "sg:tags":[
        "video",
        "library"
    ],
    "wof:name":"Nilu Videos",
    "wof:placetype":"venue"
},
  "geometry": {"coordinates":[-2.071245,52.508053],"type":"Point"}
}