{
  "type": "Feature",
  "properties": {
    "iso:country":"GB",
    "sg:address":"Stoken Farm, Steventon",
    "sg:city":"Basingstoke",
    "sg:classifiers":[
        {
            "category":"Building & Trades",
            "subcategory":"Construction",
            "type":"Services"
        }
    ],
    "sg:phone":"+44 1256 398585",
    "sg:postcode":"RG25 3BD",
    "sg:province":"Hampshire",
    "sg:tags":[
        "fork",
        "lift",
        "truck"
    ],
    "wof:name":"Bolne Ltd.",
    "wof:placetype":"venue"
},
  "geometry": {"coordinates":[-1.220016,51.228638],"type":"Point"}
}