{
  "type": "Feature",
  "properties": {
    "addr:full":"Green End, Braughing Ware Hertfordshire SG11 2PE",
    "addr:postcode":"sg11 2pe",
    "addr:street":"Green End",
    "iso:country":"GB",
    "sg:address":"Green End, Braughing",
    "sg:city":"Ware",
    "sg:classifiers":[
        {
            "category":"Bars & Pubs",
            "type":"Food & Drink"
        }
    ],
    "sg:postcode":"SG11 2PE",
    "sg:province":"Hertfordshire",
    "sg:tags":[
        "pubs",
        "house",
        "inn",
        "public",
        "activity"
    ],
    "wof:name":"J Adams",
    "wof:placetype":"venue"
},
  "geometry": {"coordinates":[0.028915,51.906616],"type":"Point"}
}