{
  "type": "Feature",
  "properties": {
    "addr:full":"27 Allan Park Road Edinburgh City of Edinburgh EH14 1LH",
    "addr:housenumber":"27",
    "addr:postcode":"eh14 1lh",
    "addr:street":"Allan Park Road",
    "iso:country":"GB",
    "sg:address":"27 Allan Park Road",
    "sg:city":"Edinburgh",
    "sg:classifiers":[
        {
            "category":"Professional",
            "subcategory":"Management & Consulting",
            "type":"Services"
        }
    ],
    "sg:phone":"+44 131 443 2192",
    "sg:postcode":"EH14 1LH",
    "sg:province":"City of Edinburgh",
    "sg:tags":[
        "consultant",
        "business"
    ],
    "wof:name":"Raeburn Consultancy Ltd.",
    "wof:placetype":"venue"
},
  "geometry": {"coordinates":[-3.2426578999,55.9257392883],"type":"Point"}
}