{
  "type": "Feature",
  "properties": {
    "addr:full":"279 Bolton Road, Atherton Manchester Greater Manchester M46 9HG",
    "addr:housenumber":"279",
    "addr:postcode":"m46 9hg",
    "addr:street":"Bolton Road",
    "iso:country":"GB",
    "sg:address":"279 Bolton Road, Atherton",
    "sg:city":"Manchester",
    "sg:classifiers":[
        {
            "category":"Farming",
            "subcategory":"Nursery",
            "type":"Manufacturing & Wholesale Goods"
        },
        {
            "category":"Education",
            "subcategory":"Preschool",
            "type":"Public Place"
        }
    ],
    "sg:phone":"+44 1942 896102",
    "sg:postcode":"M46 9HG",
    "sg:province":"Greater Manchester",
    "sg:tags":[
        "school",
        "creche"
    ],
    "wof:name":"Little Acorns Private Nursery School",
    "wof:placetype":"venue"
},
  "geometry": {"coordinates":[-2.472338,53.530842],"type":"Point"}
}