{
  "type": "Feature",
  "properties": {
    "iso:country":"GB",
    "sg:address":"4 Green Terrace",
    "sg:city":"Sunderland",
    "sg:classifiers":[
        {
            "category":"Personal",
            "subcategory":"Beauty Salon",
            "type":"Services"
        }
    ],
    "sg:postcode":"SR1 3PZ",
    "sg:province":"Tyne and Wear",
    "sg:tags":[
        "unisex",
        "hairdresser"
    ],
    "wof:name":"Patricia Sinclair Hair & Beauty Clinic",
    "wof:placetype":"venue"
},
  "geometry": {"coordinates":[-1.3883470297,54.9036750793],"type":"Point"}
}