{
  "type": "Feature",
  "properties": {
    "iso:country":"GB",
    "sg:address":"Unit 2 100 Colliery Road, Creswell",
    "sg:city":"Worksop",
    "sg:classifiers":[
        {
            "category":"Retail",
            "subcategory":"Auto Repair",
            "type":"Services"
        }
    ],
    "sg:postcode":"S80 4BX",
    "sg:province":"Nottinghamshire",
    "sg:tags":[
        "body",
        "car"
    ],
    "wof:name":"N J Bodyworks",
    "wof:placetype":"venue"
},
  "geometry": {"coordinates":[-1.219121,53.257095],"type":"Point"}
}