{
  "type": "Feature",
  "properties": {
    "iso:country":"GB",
    "sg:address":"6 Whitefield Rd",
    "sg:city":"Leicester",
    "sg:classifiers":[
        {
            "category":"Wholesale",
            "subcategory":"Scrap",
            "type":"Manufacturing & Wholesale Goods"
        }
    ],
    "sg:phone":"+44 116 261 1341",
    "sg:postcode":"LE4 5PZ",
    "sg:province":"Leicestershire",
    "sg:tags":[
        "car",
        "breaker",
        "dismantlers"
    ],
    "wof:name":"Japnade Auto Salvage",
    "wof:placetype":"venue"
},
  "geometry": {"coordinates":[-1.130468,52.659641],"type":"Point"}
}