{
  "type": "Feature",
  "properties": {
    "iso:country":"GB",
    "sg:address":"129 Church Lane, Charnock Richard",
    "sg:city":"Chorley",
    "sg:classifiers":[
        {
            "category":"Shopping",
            "subcategory":"News",
            "type":"Retail Goods"
        },
        {
            "category":"Government",
            "subcategory":"Post Office",
            "type":"Public Place"
        }
    ],
    "sg:postcode":"PR7 5NA",
    "sg:province":"Lancashire",
    "sg:tags":[
        "newsagent"
    ],
    "wof:name":"Charnock Richard Village Store & Post Office",
    "wof:placetype":"venue"
},
  "geometry": {"coordinates":[-2.673724,53.635975],"type":"Point"}
}