{
  "type": "Feature",
  "properties": {
    "iso:country":"GB",
    "sg:address":"22 Highgate Street, Oldhill",
    "sg:city":"Cradley Heath",
    "sg:classifiers":[
        {
            "category":"Bars & Pubs",
            "type":"Food & Drink"
        }
    ],
    "sg:postcode":"B64 5RY",
    "sg:province":"West Midlands",
    "sg:tags":[
        "pubs",
        "inn"
    ],
    "wof:name":"The Wolverhampton & Dudley Breweries Plc",
    "wof:placetype":"venue"
},
  "geometry": {"coordinates":[-2.065521,52.477695],"type":"Point"}
}