{
  "type": "Feature",
  "properties": {
    "iso:country":"GB",
    "sg:address":"Atherstone Road, Hartshill",
    "sg:city":"Nuneaton",
    "sg:classifiers":[
        {
            "category":"Transit Center",
            "subcategory":"Passenger",
            "type":"Transportation"
        },
        {
            "category":"Retail",
            "subcategory":"Pet Boarding",
            "type":"Services"
        }
    ],
    "sg:phone":"+44 24 7639 3034",
    "sg:postcode":"CV10 0TB",
    "sg:province":"Leicestershire",
    "sg:tags":[
        "kennel",
        "catteries"
    ],
    "wof:name":"Holmleigh",
    "wof:placetype":"venue"
},
  "geometry": {"coordinates":[-1.526326,52.537121],"type":"Point"}
}