{
  "type": "Feature",
  "properties": {
    "addr:full":"170 Sword Street Glasgow Glasgow City G31 1SE",
    "addr:housenumber":"170",
    "addr:postcode":"g31 1se",
    "addr:street":"Sword Street",
    "iso:country":"GB",
    "sg:address":"170 Sword Street",
    "sg:city":"Glasgow",
    "sg:classifiers":[
        {
            "category":"Personal",
            "subcategory":"Beauty Salon",
            "type":"Services"
        }
    ],
    "sg:phone":"+44 141 556 4550",
    "sg:postcode":"G31 1SE",
    "sg:province":"Glasgow City",
    "sg:tags":[
        "unisex",
        "hairdresser"
    ],
    "wof:name":"Alternative Hair Co.",
    "wof:placetype":"venue"
},
  "geometry": {"coordinates":[-4.2217798233,55.8582801819],"type":"Point"}
}