{
  "type": "Feature",
  "properties": {
    "addr:full":"Capstan House, High Street Llangefni Gwynedd LL77 7NA",
    "addr:postcode":"ll77 7na",
    "addr:street":"High Street",
    "iso:country":"GB",
    "sg:address":"Capstan House, High Street",
    "sg:city":"Llangefni",
    "sg:classifiers":[
        {
            "category":"Shopping",
            "subcategory":"Thrift Store",
            "type":"Retail Goods"
        }
    ],
    "sg:phone":"+44 1248 724747",
    "sg:postcode":"LL77 7NA",
    "sg:province":"Gwynedd",
    "sg:tags":[
        "shop",
        "charity"
    ],
    "wof:name":"Tenovus Cancer Charity",
    "wof:placetype":"venue"
},
  "geometry": {"coordinates":[-4.3128051758,53.2558898926],"type":"Point"}
}