{
  "type": "Feature",
  "properties": {
    "addr:full":"99 Central Av Hounslow Greater London TW3 2RQ",
    "addr:housenumber":"99",
    "addr:postcode":"tw3 2rq",
    "addr:street":"Central Av Hounslow",
    "iso:country":"GB",
    "sg:address":"99 Central Av",
    "sg:city":"Hounslow",
    "sg:classifiers":[
        {
            "category":"Home & Garden",
            "subcategory":"Home Furnishings",
            "type":"Retail Goods"
        }
    ],
    "sg:phone":"+44 20 8893 3339",
    "sg:postcode":"TW3 2RQ",
    "sg:province":"Greater London",
    "sg:tags":[
        "blind",
        "curtain",
        "fitting"
    ],
    "wof:name":"Designs By Norelle",
    "wof:placetype":"venue"
},
  "geometry": {"coordinates":[-0.351648,51.461628],"type":"Point"}
}