{
  "type": "Feature",
  "properties": {
    "addr:full":"8 Riverside Close, Seaforth Bootle Merseyside L20 4QG",
    "addr:housenumber":"8",
    "addr:postcode":"l20 4qg",
    "addr:street":"Riverside Close",
    "iso:country":"GB",
    "sg:address":"8 Riverside Close, Seaforth",
    "sg:city":"Bootle",
    "sg:classifiers":[
        {
            "category":"Utilities",
            "subcategory":"Telephone",
            "type":"Services"
        },
        {
            "category":"Organizations",
            "subcategory":"Non-profit Organization",
            "type":"Services"
        }
    ],
    "sg:phone":"+44 151 944 2716",
    "sg:postcode":"L20 4QG",
    "sg:province":"Merseyside",
    "sg:tags":[
        "organisation",
        "helpline",
        "voluntary",
        "charity"
    ],
    "wof:name":"Autism Initiatives",
    "wof:placetype":"venue"
},
  "geometry": {"coordinates":[-3.0086560249,53.4599723816],"type":"Point"}
}