{
  "type": "Feature",
  "properties": {
    "addr:full":"Bede Way Peterlee Durham SR8 1BU",
    "addr:postcode":"sr8 1bu",
    "addr:street":"Bede Way",
    "iso:country":"GB",
    "sg:address":"Bede Way",
    "sg:city":"Peterlee",
    "sg:classifiers":[
        {
            "category":"Travel",
            "subcategory":"Hotels & Motels",
            "type":"Entertainment"
        }
    ],
    "sg:phone":"+44 191 586 2161",
    "sg:postcode":"SR8 1BU",
    "sg:province":"Durham",
    "wof:name":"Peterlee Lodge Hotel",
    "wof:placetype":"venue"
},
  "geometry": {"coordinates":[-1.336999,54.759506],"type":"Point"}
}