{
  "type": "Feature",
  "properties": {
    "iso:country":"GB",
    "sg:address":"3 Kingfield Road",
    "sg:city":"Woking",
    "sg:classifiers":[
        {
            "category":"Fast Food",
            "type":"Food & Drink"
        }
    ],
    "sg:phone":"+44 1483 768902",
    "sg:postcode":"GU22 9EH",
    "sg:province":"Surrey",
    "sg:tags":[
        "away",
        "meal",
        "outlet",
        "take"
    ],
    "wof:name":"Curry Centre Tandoori",
    "wof:placetype":"venue"
},
  "geometry": {"coordinates":[-0.556179,51.307304],"type":"Point"}
}