{
  "type": "Feature",
  "properties": {
    "addr:full":"85 Cheap Street Sherborne Dorset DT9 3BA",
    "addr:housenumber":"85",
    "addr:postcode":"dt9 3ba",
    "addr:street":"Cheap Street",
    "iso:country":"GB",
    "sg:address":"85 Cheap Street",
    "sg:city":"Sherborne",
    "sg:classifiers":[
        {
            "category":"Shopping",
            "subcategory":"Shoes",
            "type":"Retail Goods"
        }
    ],
    "sg:phone":"+44 1935 812283",
    "sg:postcode":"DT9 3BA",
    "sg:province":"Dorset",
    "sg:tags":[
        "shop",
        "retailer",
        "footwear"
    ],
    "wof:name":"Cemes Davies",
    "wof:placetype":"venue"
},
  "geometry": {"coordinates":[-2.515829,50.947891],"type":"Point"}
}