{
  "type": "Feature",
  "properties": {
    "iso:country":"GB",
    "sg:address":"48 Heathfield Road, Sunnybank",
    "sg:city":"Bury",
    "sg:classifiers":[
        {
            "category":"Education",
            "subcategory":"Music School",
            "type":"Public Place"
        }
    ],
    "sg:postcode":"BL9 8HB",
    "sg:province":"Lancashire",
    "sg:tags":[
        "teacher"
    ],
    "wof:name":"Catherine Fleming",
    "wof:placetype":"venue"
},
  "geometry": {"coordinates":[-2.2916009426,53.5605926514],"type":"Point"}
}