{
  "type": "Feature",
  "properties": {
    "iso:country":"GB",
    "sg:address":"Main Road",
    "sg:city":"Chichester",
    "sg:classifiers":[
        {
            "category":"Home & Garden",
            "subcategory":"Hardware",
            "type":"Retail Goods"
        },
        {
            "category":"Farming",
            "subcategory":"Farm",
            "type":"Manufacturing & Wholesale Goods"
        }
    ],
    "sg:phone":"+44 1243 514545",
    "sg:postcode":"PO20 7BY",
    "sg:province":"West Sussex",
    "sg:tags":[
        "lawnmowers",
        "egg",
        "machinery",
        "producer"
    ],
    "wof:name":"Sidlesham Mowers",
    "wof:placetype":"venue"
},
  "geometry": {"coordinates":[-0.825534,50.795074],"type":"Point"}
}