{
  "type": "Feature",
  "properties": {
    "addr:full":"108-114 Myddleton Rd Wood Green Greater London N22 4NQ",
    "addr:housenumber":"108-114",
    "addr:postcode":"n22 4nq",
    "addr:street":"Myddleton Rd",
    "iso:country":"GB",
    "sg:address":"108-114 Myddleton Rd",
    "sg:city":"Wood Green",
    "sg:classifiers":[
        {
            "category":"Manufacturing",
            "subcategory":"Apparel",
            "type":"Manufacturing & Wholesale Goods"
        }
    ],
    "sg:phone":"+44 20 8881 0310",
    "sg:postcode":"N22 4NQ",
    "sg:province":"Greater London",
    "sg:tags":[
        "garment",
        "designer"
    ],
    "wof:name":"Aprilspring Design",
    "wof:placetype":"venue"
},
  "geometry": {"coordinates":[-0.1184350029,51.6065940857],"type":"Point"}
}