{
  "type": "Feature",
  "properties": {
    "iso:country":"GB",
    "sg:address":"10 New Walk Terrace",
    "sg:city":"York",
    "sg:classifiers":[
        {
            "category":"Retail",
            "subcategory":"Portrait Studio",
            "type":"Services"
        },
        {
            "category":"Professional",
            "subcategory":"Art Services",
            "type":"Services"
        }
    ],
    "sg:phone":"+44 1904 630112",
    "sg:postcode":"YO10 4BG",
    "sg:province":"North Yorkshire",
    "sg:tags":[
        "photographer",
        "commercial"
    ],
    "wof:name":"KENNETH SHELTON",
    "wof:placetype":"venue"
},
  "geometry": {"coordinates":[-1.0764139891,53.949924469],"type":"Point"}
}