{
  "type": "Feature",
  "properties": {
    "addr:full":"85 Grange Rd Smethwick West Midlands B66 4NG",
    "addr:housenumber":"85",
    "addr:postcode":"b66 4ng",
    "addr:street":"Grange Rd",
    "iso:country":"GB",
    "sg:address":"85 Grange Rd",
    "sg:city":"Smethwick",
    "sg:classifiers":[
        {
            "category":"Building & Trades",
            "subcategory":"Construction",
            "type":"Services"
        }
    ],
    "sg:phone":"+44 121 558 6095",
    "sg:postcode":"B66 4NG",
    "sg:province":"West Midlands",
    "sg:tags":[
        "builder"
    ],
    "wof:name":"G S Builders",
    "wof:placetype":"venue"
},
  "geometry": {"coordinates":[-1.9670259953,52.484954834],"type":"Point"}
}