{
  "type": "Feature",
  "properties": {
    "iso:country":"GB",
    "sg:address":"11 St James Road",
    "sg:city":"Hereford",
    "sg:classifiers":[
        {
            "category":"Building & Trades",
            "subcategory":"Construction",
            "type":"Services"
        }
    ],
    "sg:postcode":"HR1 2QS",
    "sg:province":"Herefordshire",
    "sg:tags":[
        "roofing",
        "contracting"
    ],
    "wof:name":"Ian Stuart Roofing",
    "wof:placetype":"venue"
},
  "geometry": {"coordinates":[-2.706929,52.051891],"type":"Point"}
}