{
  "type": "Feature",
  "properties": {
    "iso:country":"GB",
    "sg:address":"Orchards, School La",
    "sg:city":"Woodbridge",
    "sg:classifiers":[
        {
            "category":"Real Estate",
            "subcategory":"Architect",
            "type":"Services"
        }
    ],
    "sg:phone":"+44 1728 747427",
    "sg:postcode":"IP13 0ES",
    "sg:province":"Suffolk",
    "sg:tags":[
        "naval"
    ],
    "wof:name":"Bruce Roberts Designs",
    "wof:placetype":"venue"
},
  "geometry": {"coordinates":[1.357282,52.152851],"type":"Point"}
}