{
  "type": "Feature",
  "properties": {
    "iso:country":"GB",
    "sg:address":"City Branch",
    "sg:city":"Glasgow",
    "sg:classifiers":[
        {
            "category":"Government",
            "subcategory":"Post Office",
            "type":"Public Place"
        }
    ],
    "sg:phone":"+44 845 722 3344",
    "sg:postcode":"G2 7AA",
    "sg:province":"Glasgow City",
    "wof:name":"Post Office Ltd.",
    "wof:placetype":"venue"
},
  "geometry": {"coordinates":[-4.2624,55.86116],"type":"Point"}
}