{
  "type": "Feature",
  "properties": {
    "iso:country":"GB",
    "sg:address":"6 Magdalene Pl",
    "sg:city":"Edinburgh",
    "sg:classifiers":[
        {
            "category":"Professional",
            "type":"Services"
        }
    ],
    "sg:phone":"+44 131 669 2612",
    "sg:postcode":"EH15 3BJ",
    "sg:province":"City of Edinburgh",
    "sg:tags":[
        "caterer"
    ],
    "wof:name":"Variety Buffets",
    "wof:placetype":"venue"
},
  "geometry": {"coordinates":[-3.114912,55.938766],"type":"Point"}
}