{
  "type": "Feature",
  "properties": {
    "iso:country":"GB",
    "sg:address":"Midwife, 81 Victoria Rd",
    "sg:city":"Swansea",
    "sg:classifiers":[
        {
            "category":"Shopping",
            "subcategory":"Baby Store",
            "type":"Retail Goods"
        }
    ],
    "sg:phone":"+44 1792 873201",
    "sg:postcode":"SA5 4SY",
    "sg:province":"Swansea",
    "sg:tags":[
        "midwife"
    ],
    "wof:name":"D M Gibbins",
    "wof:placetype":"venue"
},
  "geometry": {"coordinates":[-4.01746,51.63987],"type":"Point"}
}