{
  "type": "Feature",
  "properties": {
    "addr:full":"39a Middlewich Road Sandbach Cheshire CW11 1DH",
    "addr:housenumber":"39a",
    "addr:postcode":"cw11 1dh",
    "addr:street":"Middlewich Road",
    "iso:country":"GB",
    "sg:address":"39a Middlewich Road",
    "sg:city":"Sandbach",
    "sg:classifiers":[
        {
            "category":"Manufacturing",
            "subcategory":"Textiles",
            "type":"Manufacturing & Wholesale Goods"
        }
    ],
    "sg:phone":"+44 800 281217",
    "sg:postcode":"CW11 1DH",
    "sg:province":"Cheshire",
    "sg:tags":[
        "mnfr",
        "rug",
        "carpet"
    ],
    "wof:name":"Quality Cleaning Services",
    "wof:placetype":"venue"
},
  "geometry": {"coordinates":[-2.3675711155,53.1450462341],"type":"Point"}
}