{
  "type": "Feature",
  "properties": {
    "addr:full":"2 Troon Walk Sheffield South Yorkshire S25 2TE",
    "addr:housenumber":"2",
    "addr:postcode":"s25 2te",
    "addr:street":"Troon Walk",
    "iso:country":"GB",
    "sg:address":"2 Troon Walk",
    "sg:city":"Sheffield",
    "sg:classifiers":[
        {
            "category":"Professional",
            "type":"Services"
        }
    ],
    "sg:phone":"+44 1909 568215",
    "sg:postcode":"S25 2TE",
    "sg:province":"South Yorkshire",
    "sg:tags":[
        "repair",
        "tech",
        "maintenance"
    ],
    "wof:name":"Interface Systems",
    "wof:placetype":"venue"
},
  "geometry": {"coordinates":[-1.207226,53.36499],"type":"Point"}
}