{
  "type": "Feature",
  "properties": {
    "addr:full":"118 Falsgrave Road Scarborough North Yorkshire YO12 5BD",
    "addr:housenumber":"118",
    "addr:postcode":"yo12 5bd",
    "addr:street":"Falsgrave Road",
    "iso:country":"GB",
    "sg:address":"118 Falsgrave Road",
    "sg:city":"Scarborough",
    "sg:classifiers":[
        {
            "category":"Retail",
            "subcategory":"Auto Repair",
            "type":"Services"
        }
    ],
    "sg:phone":"+44 1723 362858",
    "sg:postcode":"YO12 5BD",
    "sg:province":"North Yorkshire",
    "sg:tags":[
        "modification",
        "garage"
    ],
    "wof:name":"Falsgrave Garage",
    "wof:placetype":"venue"
},
  "geometry": {"coordinates":[-0.4149389863,54.2774963379],"type":"Point"}
}