{
  "type": "Feature",
  "properties": {
    "iso:country":"GB",
    "sg:address":"Lochside Indust Est, Irongray Rd",
    "sg:city":"Dumfries",
    "sg:classifiers":[
        {
            "category":"Wholesale",
            "subcategory":"Scrap",
            "type":"Manufacturing & Wholesale Goods"
        }
    ],
    "sg:phone":"+44 1387 721777",
    "sg:postcode":"DG2 0HS",
    "sg:province":"Dumfries and Galloway",
    "sg:tags":[
        "waste",
        "metal"
    ],
    "wof:name":"Rosefield Salvage & Engineering Co",
    "wof:placetype":"venue"
},
  "geometry": {"coordinates":[-3.6660790443,55.1090202332],"type":"Point"}
}