{
  "type": "Feature",
  "properties": {
    "addr:full":"47 Lower St Stansted Essex CM24 8LN",
    "addr:housenumber":"47",
    "addr:postcode":"cm24 8ln",
    "addr:street":"Lower St",
    "iso:country":"GB",
    "sg:address":"47 Lower St",
    "sg:city":"Stansted",
    "sg:classifiers":[
        {
            "category":"Professional",
            "type":"Services"
        }
    ],
    "sg:phone":"+44 1279 647160",
    "sg:postcode":"CM24 8LN",
    "sg:province":"Essex",
    "sg:tags":[
        "writer"
    ],
    "wof:name":"Documentation Engineering Associates Ltd",
    "wof:placetype":"venue"
},
  "geometry": {"coordinates":[0.2004729956,51.9040260315],"type":"Point"}
}