{
  "type": "Feature",
  "properties": {
    "iso:country":"GB",
    "sg:address":"67a Huddersfield Rd",
    "sg:city":"Holmfirth",
    "sg:classifiers":[
        {
            "category":"Shopping",
            "subcategory":"Gifts & Souvenirs",
            "type":"Retail Goods"
        }
    ],
    "sg:postcode":"HD9 3AZ",
    "sg:province":"South Yorkshire",
    "sg:tags":[
        "shop"
    ],
    "wof:name":"Senior Stephen",
    "wof:placetype":"venue"
},
  "geometry": {"coordinates":[-1.787556,53.570438],"type":"Point"}
}