{
  "type": "Feature",
  "properties": {
    "addr:full":"Corner Of Spanish City, High Street Mablethorpe Lincolnshire LN12 1AL",
    "addr:postcode":"ln12 1al",
    "addr:street":"Corner;High Street",
    "iso:country":"GB",
    "sg:address":"Corner Of Spanish City, High Street",
    "sg:city":"Mablethorpe",
    "sg:classifiers":[
        {
            "category":"Food & Beverages",
            "subcategory":"Meat & Fish",
            "type":"Retail Goods"
        }
    ],
    "sg:phone":"+44 1507 473093",
    "sg:postcode":"LN12 1AL",
    "sg:province":"Lincolnshire",
    "sg:tags":[
        "chip"
    ],
    "wof:name":"Pete's Fish & Chips",
    "wof:placetype":"venue"
},
  "geometry": {"coordinates":[0.258197,53.340668],"type":"Point"}
}