{
  "type": "Feature",
  "properties": {
    "iso:country":"GB",
    "sg:address":"3 Kingston Row",
    "sg:city":"Birmingham",
    "sg:classifiers":[
        {
            "category":"Professional",
            "subcategory":"Lawyer & Legal Services",
            "type":"Services"
        }
    ],
    "sg:phone":"+44 121 233 1999",
    "sg:postcode":"B1 2NU",
    "sg:province":"West Midlands",
    "sg:tags":[
        "advice",
        "counselling"
    ],
    "wof:name":"Birmingham & District Mediation Service",
    "wof:placetype":"venue"
},
  "geometry": {"coordinates":[-1.912876,52.480125],"type":"Point"}
}