{
  "type": "Feature",
  "properties": {
    "addr:full":"2 Frodsham Square Chester Cheshire CH1 3JS",
    "addr:housenumber":"2",
    "addr:postcode":"ch1 3js",
    "addr:street":"Frodsham",
    "iso:country":"GB",
    "sg:address":"2 Frodsham Square",
    "sg:city":"Chester",
    "sg:classifiers":[
        {
            "category":"Shopping",
            "subcategory":"Optician",
            "type":"Retail Goods"
        }
    ],
    "sg:phone":"+44 1244 316896",
    "sg:postcode":"CH1 3JS",
    "sg:province":"Cheshire",
    "wof:name":"Jonathon Bryan Opticians",
    "wof:placetype":"venue"
},
  "geometry": {"coordinates":[-2.8886489868,53.193069458],"type":"Point"}
}