{
  "type": "Feature",
  "properties": {
    "iso:country":"GB",
    "sg:address":"101 Broadway West",
    "sg:city":"Leigh-on-sea",
    "sg:classifiers":[
        {
            "category":"Shopping",
            "subcategory":"Shoes",
            "type":"Retail Goods"
        }
    ],
    "sg:phone":"+44 1702 76695",
    "sg:postcode":"SS9 2SU",
    "sg:province":"Essex",
    "sg:tags":[
        "shop"
    ],
    "wof:name":"Pellini Shoes Ltd.",
    "wof:placetype":"venue"
},
  "geometry": {"coordinates":[0.650995,51.548481],"type":"Point"}
}