{
  "type": "Feature",
  "properties": {
    "addr:full":"11 Central Square Cardiff Cardiff CF10 1EP",
    "addr:housenumber":"11",
    "addr:postcode":"cf10 1ep",
    "addr:street":"Central Square",
    "iso:country":"GB",
    "sg:address":"11 Central Square",
    "sg:city":"Cardiff",
    "sg:classifiers":[
        {
            "category":"Travel",
            "subcategory":"Travel Agent",
            "type":"Entertainment"
        }
    ],
    "sg:phone":"+44 29 2039 7973",
    "sg:postcode":"CF10 1EP",
    "sg:province":"Cardiff",
    "wof:name":"Airticket Centres Ltd.",
    "wof:placetype":"venue"
},
  "geometry": {"coordinates":[-3.1794610023,51.4763259888],"type":"Point"}
}