{
  "type": "Feature",
  "properties": {
    "iso:country":"GB",
    "sg:address":"Clayton Manor, Victoria Gardens",
    "sg:city":"Burgess Hill",
    "sg:classifiers":[
        {
            "category":"Education",
            "subcategory":"Special Training",
            "type":"Public Place"
        }
    ],
    "sg:phone":"+44 1444 246226",
    "sg:postcode":"RH15 9NB",
    "sg:province":"East Sussex",
    "sg:tags":[
        "product",
        "centre"
    ],
    "wof:name":"Quadrant Systems Ltd.",
    "wof:placetype":"venue"
},
  "geometry": {"coordinates":[-0.139174,50.95533],"type":"Point"}
}