{
  "type": "Feature",
  "properties": {
    "addr:full":"82 Penrhiwceiber Road Mountain Ash Rhondda, Cynon, Taff CF45 3SL",
    "addr:housenumber":"82",
    "addr:postcode":"cf45 3sl",
    "addr:street":"Penrhiwceiber Road;Cynon Taff",
    "iso:country":"GB",
    "sg:address":"82 Penrhiwceiber Road",
    "sg:city":"Mountain Ash",
    "sg:classifiers":[
        {
            "category":"Food & Beverages",
            "subcategory":"Fruits & Vegetables",
            "type":"Retail Goods"
        },
        {
            "category":"Food & Beverages",
            "subcategory":"Groceries & Convenience Stores",
            "type":"Retail Goods"
        }
    ],
    "sg:phone":"+44 1443 473235",
    "sg:postcode":"CF45 3SL",
    "sg:province":"Rhondda, Cynon, Taff",
    "sg:tags":[
        "greengrocer"
    ],
    "wof:name":"MORTON LLOYD",
    "wof:placetype":"venue"
},
  "geometry": {"coordinates":[-3.364745,51.671238],"type":"Point"}
}