{
  "type": "Feature",
  "properties": {
    "addr:full":"10 Raby Close, Tividale Oldbury West Midlands B69 1US",
    "addr:housenumber":"10",
    "addr:postcode":"b69 1us",
    "addr:street":"Raby Close",
    "iso:country":"GB",
    "sg:address":"10 Raby Close, Tividale",
    "sg:city":"Oldbury",
    "sg:classifiers":[
        {
            "category":"Professional",
            "type":"Services"
        }
    ],
    "sg:postcode":"B69 1US",
    "sg:province":"West Midlands",
    "sg:tags":[
        "reflexologists"
    ],
    "wof:name":"Foot Flex",
    "wof:placetype":"venue"
},
  "geometry": {"coordinates":[-2.060354948,52.5065841675],"type":"Point"}
}