{
  "type": "Feature",
  "properties": {
    "iso:country":"GB",
    "sg:address":"The Boatyard, Mansion Lane",
    "sg:city":"Iver",
    "sg:classifiers":[
        {
            "category":"Professional",
            "subcategory":"Management & Consulting",
            "type":"Services"
        }
    ],
    "sg:phone":"+44 1753 650978",
    "sg:postcode":"SL0 9RG",
    "sg:province":"Berkshire",
    "sg:tags":[
        "consultant",
        "specialist"
    ],
    "wof:name":"The Talon Salon",
    "wof:placetype":"venue"
},
  "geometry": {"coordinates":[-0.510574,51.520699],"type":"Point"}
}