{
  "type": "Feature",
  "properties": {
    "iso:country":"GB",
    "sg:address":"245 Maida Vale",
    "sg:city":"Maida Vale",
    "sg:classifiers":[
        {
            "category":"Sports & Exercise",
            "subcategory":"Gym",
            "type":"Entertainment"
        }
    ],
    "sg:phone":"+44 20 7625 4636",
    "sg:postcode":"W9 1QJ",
    "sg:province":"Greater London",
    "sg:tags":[
        "fitness",
        "health",
        "centre"
    ],
    "wof:name":"Maidavale Health Club",
    "wof:placetype":"venue"
},
  "geometry": {"coordinates":[-0.186539,51.532406],"type":"Point"}
}