{
  "type": "Feature",
  "properties": {
    "iso:country":"GB",
    "sg:address":"The Porthouse, 75 Lowesmoor",
    "sg:city":"Worcester",
    "sg:classifiers":[
        {
            "category":"Real Estate",
            "subcategory":"Developer",
            "type":"Services"
        }
    ],
    "sg:postcode":"WR1 2RS",
    "sg:province":"Worcestershire",
    "sg:tags":[
        "property"
    ],
    "wof:name":"Lowesmoor Wharf Developments Ltd.",
    "wof:placetype":"venue"
},
  "geometry": {"coordinates":[-2.2199790478,52.1897201538],"type":"Point"}
}