{
  "type": "Feature",
  "properties": {
    "addr:full":"377 Fulwood Road Sheffield South Yorkshire S10 3GA",
    "addr:housenumber":"377",
    "addr:postcode":"s10 3ga",
    "addr:street":"Fulwood Road",
    "iso:country":"GB",
    "sg:address":"377 Fulwood Road",
    "sg:city":"Sheffield",
    "sg:classifiers":[
        {
            "category":"Restaurant",
            "type":"Food & Drink"
        }
    ],
    "sg:phone":"+44 114 263 0922",
    "sg:postcode":"S10 3GA",
    "sg:province":"South Yorkshire",
    "sg:tags":[
        "oriental"
    ],
    "wof:name":"Chinastyle Ltd",
    "wof:placetype":"venue"
},
  "geometry": {"coordinates":[-1.534349,53.367352],"type":"Point"}
}