{
  "type": "Feature",
  "properties": {
    "addr:full":"12 Hill Street Richmond Greater London TW9 1TN",
    "addr:housenumber":"12",
    "addr:postcode":"tw9 1tn",
    "addr:street":"Hill Street",
    "iso:country":"GB",
    "sg:address":"12 Hill Street",
    "sg:city":"Richmond",
    "sg:classifiers":[
        {
            "category":"Coffee & Tea",
            "type":"Food & Drink"
        }
    ],
    "sg:phone":"+44 20 8332 9801",
    "sg:postcode":"TW9 1TN",
    "sg:province":"Greater London",
    "wof:name":"Whittards of Chelsea",
    "wof:placetype":"venue"
},
  "geometry": {"coordinates":[-0.306092,51.459202],"type":"Point"}
}