{
  "type": "Feature",
  "properties": {
    "iso:country":"GB",
    "sg:address":"Unit 3 Off Freemans Rd, Portslade",
    "sg:city":"Brighton",
    "sg:classifiers":[
        {
            "category":"Autos & Motor Vehicles",
            "subcategory":"Motorcycle Sales",
            "type":"Retail Goods"
        }
    ],
    "sg:phone":"+44 1273 420045",
    "sg:postcode":"BN41 1SL",
    "sg:province":"East Sussex",
    "wof:name":"T.P.G. Motor Cycles Limited",
    "wof:placetype":"venue"
},
  "geometry": {"coordinates":[-0.206189,50.835064],"type":"Point"}
}