{
  "type": "Feature",
  "properties": {
    "addr:full":"15 Littleworth Road, Downley High Wycombe Buckinghamshire HP13 5XF",
    "addr:housenumber":"15",
    "addr:postcode":"hp13 5xf",
    "addr:street":"Littleworth Road",
    "iso:country":"GB",
    "sg:address":"15 Littleworth Road, Downley",
    "sg:city":"High Wycombe",
    "sg:classifiers":[
        {
            "category":"Fast Food",
            "type":"Food & Drink"
        }
    ],
    "sg:phone":"+44 1494 524215",
    "sg:postcode":"HP13 5XF",
    "sg:province":"Buckinghamshire",
    "sg:tags":[
        "away",
        "take"
    ],
    "wof:name":"Siew May Chinese Takeaway",
    "wof:placetype":"venue"
},
  "geometry": {"coordinates":[-0.772431016,51.6450767517],"type":"Point"}
}