{
  "type": "Feature",
  "properties": {
    "addr:full":"Burcote Wood Farm, Wood Burcote Towcester Buckinghamshire NN12 8TA",
    "addr:postcode":"nn12 8ta",
    "addr:street":"Burcote;Wood",
    "iso:country":"GB",
    "sg:address":"Burcote Wood Farm, Wood Burcote",
    "sg:city":"Towcester",
    "sg:classifiers":[
        {
            "category":"Food & Beverages",
            "subcategory":"Farmers Market",
            "type":"Retail Goods"
        }
    ],
    "sg:phone":"+44 1327 359578",
    "sg:postcode":"NN12 8TA",
    "sg:province":"Buckinghamshire",
    "sg:tags":[
        "farm",
        "shop",
        "pyo"
    ],
    "wof:name":"Burcote Wood Business Park Ltd.",
    "wof:placetype":"venue"
},
  "geometry": {"coordinates":[-0.992574,52.112671],"type":"Point"}
}