{
  "type": "Feature",
  "properties": {
    "iso:country":"GB",
    "sg:address":"614 Willenhall Road",
    "sg:city":"Willenhall",
    "sg:classifiers":[
        {
            "category":"Building & Trades",
            "subcategory":"Equipment Rental",
            "type":"Services"
        }
    ],
    "sg:phone":"+44 1902 604744",
    "sg:postcode":"WV13 3RA",
    "sg:province":"West Midlands",
    "sg:tags":[
        "hire",
        "centre"
    ],
    "wof:name":"Relko Tool Hire & Repair Ltd.",
    "wof:placetype":"venue"
},
  "geometry": {"coordinates":[-2.074734,52.583988],"type":"Point"}
}