{
  "type": "Feature",
  "properties": {
    "addr:full":"Cadwst Mawr, Llandrollo Corwen Conwy LL21 0TD",
    "addr:postcode":"ll21 0td",
    "addr:street":"Corwen",
    "iso:country":"GB",
    "sg:address":"Cadwst Mawr, Llandrollo",
    "sg:city":"Corwen",
    "sg:classifiers":[
        {
            "category":"Farming",
            "subcategory":"Livestock Farm",
            "type":"Manufacturing & Wholesale Goods"
        }
    ],
    "sg:phone":"+44 1490 440207",
    "sg:postcode":"LL21 0TD",
    "sg:province":"Conwy",
    "sg:tags":[
        "others"
    ],
    "wof:name":"John Wyn Jones",
    "wof:placetype":"venue"
},
  "geometry": {"coordinates":[-3.373668,52.980648],"type":"Point"}
}