{
  "type": "Feature",
  "properties": {
    "addr:full":"Swallow Corner, Guildford Rd, Pirbright Woking Surrey GU24 0LW",
    "addr:postcode":"gu24 0lw",
    "addr:street":"Guildford Rd",
    "iso:country":"GB",
    "sg:address":"Swallow Corner, Guildford Rd, Pirbright",
    "sg:city":"Woking",
    "sg:classifiers":[
        {
            "category":"Building & Trades",
            "subcategory":"Construction",
            "type":"Services"
        }
    ],
    "sg:phone":"+44 1483 486348",
    "sg:postcode":"GU24 0LW",
    "sg:province":"Surrey",
    "sg:tags":[
        "roofing"
    ],
    "wof:name":"Eaves Sure Ltd",
    "wof:placetype":"venue"
},
  "geometry": {"coordinates":[-0.645086,51.298618],"type":"Point"}
}