{
  "type": "Feature",
  "properties": {
    "iso:country":"GB",
    "sg:address":"10 Sutton Road",
    "sg:city":"Birmingham",
    "sg:classifiers":[
        {
            "category":"Education",
            "subcategory":"School",
            "type":"Public Place"
        }
    ],
    "sg:phone":"+44 121 373 7400",
    "sg:postcode":"B23 6QL",
    "sg:province":"West Midlands",
    "sg:tags":[
        "independent",
        "preparatory"
    ],
    "wof:name":"Highclare School Ltd",
    "wof:placetype":"venue"
},
  "geometry": {"coordinates":[-1.836556,52.527489],"type":"Point"}
}