{
  "type": "Feature",
  "properties": {
    "addr:full":"42 St Albans Road Reigate Surrey RH2 9LN",
    "addr:housenumber":"42",
    "addr:postcode":"rh2 9ln",
    "addr:street":"St Albans Road",
    "iso:country":"GB",
    "sg:address":"42 St Albans Road",
    "sg:city":"Reigate",
    "sg:classifiers":[
        {
            "category":"Health Services",
            "subcategory":"Health Practitioner",
            "type":"Services"
        }
    ],
    "sg:phone":"+44 1737 244202",
    "sg:postcode":"RH2 9LN",
    "sg:province":"Surrey",
    "sg:tags":[
        "osteopath"
    ],
    "wof:name":"Susan J Smith Registered Osteopath",
    "wof:placetype":"venue"
},
  "geometry": {"coordinates":[-0.207738,51.245464],"type":"Point"}
}