{
  "type": "Feature",
  "properties": {
    "addr:full":"Field Gate, Bainbridge Leyburn North Yorkshire DL8 3EP",
    "addr:postcode":"dl8 3ep",
    "addr:street":"Field Gate",
    "iso:country":"GB",
    "sg:address":"Field Gate, Bainbridge",
    "sg:city":"Leyburn",
    "sg:classifiers":[
        {
            "category":"Farming",
            "subcategory":"Livestock Farm",
            "type":"Manufacturing & Wholesale Goods"
        }
    ],
    "sg:phone":"+44 1969 650267",
    "sg:postcode":"DL8 3EP",
    "sg:province":"North Yorkshire",
    "sg:tags":[
        "others"
    ],
    "wof:name":"A Lambert",
    "wof:placetype":"venue"
},
  "geometry": {"coordinates":[-2.1025710106,54.3091659546],"type":"Point"}
}