{
  "type": "Feature",
  "properties": {
    "addr:full":"54 Lower Guildford Rd Woking Surrey GU21 2EN",
    "addr:housenumber":"54",
    "addr:postcode":"gu21 2en",
    "addr:street":"Lower Guildford Rd",
    "iso:country":"GB",
    "sg:address":"54 Lower Guildford Rd",
    "sg:city":"Woking",
    "sg:classifiers":[
        {
            "category":"Building & Trades",
            "subcategory":"Construction",
            "type":"Services"
        }
    ],
    "sg:phone":"+44 1483 473690",
    "sg:postcode":"GU21 2EN",
    "sg:province":"Surrey",
    "sg:tags":[
        "joinery"
    ],
    "wof:name":"Mair Valletta",
    "wof:placetype":"venue"
},
  "geometry": {"coordinates":[-0.613361,51.316261],"type":"Point"}
}