{
  "type": "Feature",
  "properties": {
    "iso:country":"GB",
    "sg:address":"1 Rushmead Clo",
    "sg:city":"Canterbury",
    "sg:classifiers":[
        {
            "category":"Social Services",
            "subcategory":"Job Training",
            "type":"Services"
        }
    ],
    "sg:phone":"+44 1227 455257",
    "sg:postcode":"CT2 7RP",
    "sg:province":"Kent",
    "sg:tags":[
        "translator",
        "interpreter"
    ],
    "wof:name":"A L Technical Translations",
    "wof:placetype":"venue"
},
  "geometry": {"coordinates":[1.067136,51.287937],"type":"Point"}
}