{
  "type": "Feature",
  "properties": {
    "addr:full":"4 Station Road, Wombourne Wolverhampton Shropshire WV5 9EL",
    "addr:housenumber":"4",
    "addr:postcode":"wv5 9el",
    "addr:street":"Station Road",
    "iso:country":"GB",
    "sg:address":"4 Station Road, Wombourne",
    "sg:city":"Wolverhampton",
    "sg:classifiers":[
        {
            "category":"Shopping",
            "subcategory":"Mobile Phones",
            "type":"Retail Goods"
        }
    ],
    "sg:phone":"+44 1902 896666",
    "sg:postcode":"WV5 9EL",
    "sg:province":"Shropshire",
    "wof:name":"Price Cellular Security Ltd.",
    "wof:placetype":"venue"
},
  "geometry": {"coordinates":[-2.186829,52.53717],"type":"Point"}
}