{
  "type": "Feature",
  "properties": {
    "addr:full":"242 Chertsey La Staines Berkshire TW18 3NF",
    "addr:housenumber":"242",
    "addr:postcode":"tw18 3nf",
    "addr:street":"Chertsey La Staines",
    "iso:country":"GB",
    "sg:address":"242 Chertsey La",
    "sg:city":"Staines",
    "sg:classifiers":[
        {
            "category":"Professional",
            "subcategory":"Engineering",
            "type":"Services"
        }
    ],
    "sg:postcode":"TW18 3NF",
    "sg:province":"Berkshire",
    "sg:tags":[
        "precision",
        "engineer"
    ],
    "wof:name":"Pullen Precision Engineering Ltd",
    "wof:placetype":"venue"
},
  "geometry": {"coordinates":[-0.5115860105,51.4137458801],"type":"Point"}
}