{
  "type": "Feature",
  "properties": {
    "addr:full":"7 Church Road Welwyn Garden City Hertfordshire AL8 6NT",
    "addr:housenumber":"7",
    "addr:postcode":"al8 6nt",
    "addr:street":"Church Road",
    "iso:country":"GB",
    "sg:address":"7 Church Road",
    "sg:city":"Welwyn Garden City",
    "sg:classifiers":[
        {
            "category":"Professional",
            "subcategory":"Business Services",
            "type":"Services"
        }
    ],
    "sg:phone":"+44 1707 373330",
    "sg:postcode":"AL8 6NT",
    "sg:province":"Hertfordshire",
    "sg:tags":[
        "holding"
    ],
    "wof:name":"Omega (U K) Holdings Ltd.",
    "wof:placetype":"venue"
},
  "geometry": {"coordinates":[-0.2067690045,51.8000640869],"type":"Point"}
}