{
  "type": "Feature",
  "properties": {
    "addr:full":"2 Derwent Street Consett Durham DH8 8LU",
    "addr:housenumber":"2",
    "addr:postcode":"dh8 8lu",
    "addr:street":"Derwent Street",
    "iso:country":"GB",
    "sg:address":"2 Derwent Street",
    "sg:city":"Consett",
    "sg:classifiers":[
        {
            "category":"Cinema",
            "subcategory":"Movie Rental",
            "type":"Entertainment"
        }
    ],
    "sg:phone":"+44 1207 591230",
    "sg:postcode":"DH8 8LU",
    "sg:province":"Durham",
    "sg:tags":[
        "video",
        "library"
    ],
    "wof:name":"Sight & Sound Video",
    "wof:placetype":"venue"
},
  "geometry": {"coordinates":[-1.848419,54.860989],"type":"Point"}
}