{
  "type": "Feature",
  "properties": {
    "iso:country":"GB",
    "sg:address":"Long Street, Williton",
    "sg:city":"Taunton",
    "sg:classifiers":[
        {
            "category":"Organizations",
            "subcategory":"Community Association",
            "type":"Services"
        },
        {
            "category":"Organizations",
            "subcategory":"Membership Organization",
            "type":"Services"
        }
    ],
    "sg:phone":"+44 1984 632643",
    "sg:postcode":"TA4 4QN",
    "sg:province":"Devon",
    "sg:tags":[
        "club",
        "social"
    ],
    "wof:name":"Williton Social Club",
    "wof:placetype":"venue"
},
  "geometry": {"coordinates":[-3.312388,51.164505],"type":"Point"}
}