{
  "type": "Feature",
  "properties": {
    "addr:full":"133 Taunton Road Bridgwater Somerset TA6 6BD",
    "addr:housenumber":"133",
    "addr:postcode":"ta6 6bd",
    "addr:street":"Taunton Road",
    "iso:country":"GB",
    "sg:address":"133 Taunton Road",
    "sg:city":"Bridgwater",
    "sg:classifiers":[
        {
            "category":"Shopping",
            "subcategory":"Department Store",
            "type":"Retail Goods"
        }
    ],
    "sg:postcode":"TA6 6BD",
    "sg:province":"Somerset",
    "wof:name":"Mini Market",
    "wof:placetype":"venue"
},
  "geometry": {"coordinates":[-2.998955965,51.1206741333],"type":"Point"}
}