{
  "type": "Feature",
  "properties": {
    "addr:full":"4 Bay View Rd, Newton Porthcawl Bridgend CF36 5NF",
    "addr:housenumber":"4",
    "addr:postcode":"cf36 5nf",
    "addr:street":"Bay View Rd",
    "iso:country":"GB",
    "sg:address":"4 Bay View Rd, Newton",
    "sg:city":"Porthcawl",
    "sg:classifiers":[
        {
            "category":"Arena",
            "subcategory":"Sports Club",
            "type":"Entertainment"
        }
    ],
    "sg:phone":"+44 1656 788593",
    "sg:postcode":"CF36 5NF",
    "sg:province":"Bridgend",
    "wof:name":"Porthcawl Power Boat & Ski Club",
    "wof:placetype":"venue"
},
  "geometry": {"coordinates":[-3.678482,51.479164],"type":"Point"}
}