{
  "type": "Feature",
  "properties": {
    "addr:full":"9 Logie Mill Edinburgh City of Edinburgh EH7 4HG",
    "addr:housenumber":"9",
    "addr:postcode":"eh7 4hg",
    "addr:street":"Logie Mill Edinburgh",
    "iso:country":"GB",
    "sg:address":"9 Logie Mill",
    "sg:city":"Edinburgh",
    "sg:classifiers":[
        {
            "category":"Education",
            "subcategory":"Special Training",
            "type":"Public Place"
        }
    ],
    "sg:postcode":"EH7 4HG",
    "sg:province":"City of Edinburgh",
    "sg:tags":[
        "product",
        "centre"
    ],
    "wof:name":"Hospitality Training Foundation",
    "wof:placetype":"venue"
},
  "geometry": {"coordinates":[-3.194582,55.965698],"type":"Point"}
}