{
  "type": "Feature",
  "properties": {
    "iso:country":"GB",
    "sg:address":"Unit 4 Marville Ct Thackers Way, Deeping St. James",
    "sg:city":"Peterborough",
    "sg:classifiers":[
        {
            "category":"Manufacturing",
            "subcategory":"Textiles",
            "type":"Manufacturing & Wholesale Goods"
        }
    ],
    "sg:postcode":"PE6 8HP",
    "sg:province":"Cambridgeshire",
    "sg:tags":[
        "knitwear"
    ],
    "wof:name":"Gore,Margaret,",
    "wof:placetype":"venue"
},
  "geometry": {"coordinates":[-0.3028399944,52.6790008545],"type":"Point"}
}