{
  "type": "Feature",
  "properties": {
    "addr:full":"32 Brookes Road, Flitwick Bedford Bedfordshire MK45 1BX",
    "addr:housenumber":"32",
    "addr:postcode":"mk45 1bx",
    "addr:street":"Brookes Road",
    "iso:country":"GB",
    "sg:address":"32 Brookes Road, Flitwick",
    "sg:city":"Bedford",
    "sg:classifiers":[
        {
            "category":"Personal",
            "subcategory":"Beauty Salon",
            "type":"Services"
        }
    ],
    "sg:phone":"+44 1525 715086",
    "sg:postcode":"MK45 1BX",
    "sg:province":"Bedfordshire",
    "sg:tags":[
        "lady",
        "hairdresser"
    ],
    "wof:name":"Romalas",
    "wof:placetype":"venue"
},
  "geometry": {"coordinates":[-0.492552,52.006153],"type":"Point"}
}