{
  "type": "Feature",
  "properties": {
    "addr:full":"1 Station Road South, Padgate Warrington Cheshire WA2 0PD",
    "addr:housenumber":"1",
    "addr:postcode":"wa2 0pd",
    "addr:street":"Station Road South Padgate",
    "iso:country":"GB",
    "sg:address":"1 Station Road South, Padgate",
    "sg:city":"Warrington",
    "sg:classifiers":[
        {
            "category":"Shopping",
            "subcategory":"Pharmacy",
            "type":"Retail Goods"
        }
    ],
    "sg:phone":"+44 1925 827236",
    "sg:postcode":"WA2 0PD",
    "sg:province":"Cheshire",
    "sg:tags":[
        "pharmacist",
        "chemist"
    ],
    "wof:name":"Hills Pharmacy",
    "wof:placetype":"venue"
},
  "geometry": {"coordinates":[-2.5566580296,53.4067077637],"type":"Point"}
}