{
  "type": "Feature",
  "properties": {
    "addr:full":"77 Ellison Lane Cambridge Cambridgeshire CB3 7XH",
    "addr:housenumber":"77",
    "addr:postcode":"cb3 7xh",
    "addr:street":"Ellison Lane",
    "iso:country":"GB",
    "sg:address":"77 Ellison Lane",
    "sg:city":"Cambridge",
    "sg:classifiers":[
        {
            "category":"Building & Trades",
            "subcategory":"Plumbing",
            "type":"Services"
        }
    ],
    "sg:phone":"+44 1954 210240",
    "sg:postcode":"CB3 7XH",
    "sg:province":"Cambridgeshire",
    "sg:tags":[
        "heating"
    ],
    "wof:name":"Michael John Moxon",
    "wof:placetype":"venue"
},
  "geometry": {"coordinates":[0.005996,52.216179],"type":"Point"}
}