{
  "type": "Feature",
  "properties": {
    "addr:full":"52 Maynards, Whittlesford Cambridge Cambridgeshire CB2 4PN",
    "addr:housenumber":"52",
    "addr:postcode":"cb2 4pn",
    "addr:street":"Maynards Whittlesford",
    "iso:country":"GB",
    "sg:address":"52 Maynards, Whittlesford",
    "sg:city":"Cambridge",
    "sg:classifiers":[
        {
            "category":"Shopping",
            "subcategory":"Books",
            "type":"Retail Goods"
        }
    ],
    "sg:phone":"+44 1223 833300",
    "sg:postcode":"CB2 4PN",
    "sg:province":"Cambridgeshire",
    "wof:name":"DVT Publishing",
    "wof:placetype":"venue"
},
  "geometry": {"coordinates":[0.2112949938,52.1319236755],"type":"Point"}
}