{
  "type": "Feature",
  "properties": {
    "addr:full":"5 Onslow Parade, Hampden Square, Southgate London Greater London N14 5JN",
    "addr:housenumber":"5",
    "addr:postcode":"n14 5jn",
    "addr:street":"Onslow Parade",
    "iso:country":"GB",
    "sg:address":"5 Onslow Parade, Hampden Square, Southgate",
    "sg:city":"London",
    "sg:classifiers":[
        {
            "category":"Building & Trades",
            "subcategory":"Construction",
            "type":"Services"
        }
    ],
    "sg:phone":"+44 20 8361 3132",
    "sg:postcode":"N14 5JN",
    "sg:province":"Greater London",
    "sg:tags":[
        "flooring"
    ],
    "wof:name":"Sanger Flooring Ltd",
    "wof:placetype":"venue"
},
  "geometry": {"coordinates":[-0.130588,51.63319],"type":"Point"}
}