{
  "type": "Feature",
  "properties": {
    "iso:country":"GB",
    "sg:address":"Wigley Bush Lane, South Weald",
    "sg:city":"Brentwood",
    "sg:classifiers":[
        {
            "category":"Education",
            "subcategory":"School",
            "type":"Public Place"
        }
    ],
    "sg:phone":"+44 1277 215577",
    "sg:postcode":"CM14 5QN",
    "sg:province":"Essex",
    "sg:tags":[
        "local",
        "authority"
    ],
    "wof:name":"St Peter's C Of E Primary School",
    "wof:placetype":"venue"
},
  "geometry": {"coordinates":[0.270778,51.613525],"type":"Point"}
}