{
  "type": "Feature",
  "properties": {
    "addr:full":"361 Coventry Road Birmingham West Midlands B10 0SH",
    "addr:housenumber":"361",
    "addr:postcode":"b10 0sh",
    "addr:street":"Coventry Road",
    "iso:country":"GB",
    "sg:address":"361 Coventry Road",
    "sg:city":"Birmingham",
    "sg:classifiers":[
        {
            "category":"Government",
            "subcategory":"Post Office",
            "type":"Public Place"
        }
    ],
    "sg:phone":"+44 121 772 6211",
    "sg:postcode":"B10 0SH",
    "sg:province":"West Midlands",
    "wof:name":"Small Heath Post Office",
    "wof:placetype":"venue"
},
  "geometry": {"coordinates":[-1.8635599613,52.4718971252],"type":"Point"}
}