{
  "type": "Feature",
  "properties": {
    "iso:country":"GB",
    "sg:address":"6 Pittville Lawn",
    "sg:city":"Cheltenham",
    "sg:classifiers":[
        {
            "category":"Farming",
            "subcategory":"Nursery",
            "type":"Manufacturing & Wholesale Goods"
        }
    ],
    "sg:postcode":"GL52 2BD",
    "sg:province":"Gloucestershire",
    "sg:tags":[
        "creche"
    ],
    "wof:name":"Falcon Day Nursery",
    "wof:placetype":"venue"
},
  "geometry": {"coordinates":[-2.0696051121,51.9046974182],"type":"Point"}
}