{
  "type": "Feature",
  "properties": {
    "iso:country":"GB",
    "sg:address":"9 Bellfield Avenue",
    "sg:city":"Musselburgh",
    "sg:classifiers":[
        {
            "category":"Building & Trades",
            "subcategory":"Construction",
            "type":"Services"
        }
    ],
    "sg:postcode":"EH21 6QU",
    "sg:province":"City of Edinburgh",
    "sg:tags":[
        "decorator",
        "painter"
    ],
    "wof:name":"Andrew Young Painter & Decorator",
    "wof:placetype":"venue"
},
  "geometry": {"coordinates":[-3.061052,55.941208],"type":"Point"}
}