{
  "type": "Feature",
  "properties": {
    "addr:full":"Unit D5 Braintree Indust Est, Braintree Rd Ruislip Greater London HA4 0EJ",
    "addr:housenumber":"d5",
    "addr:postcode":"ha4 0ej",
    "addr:street":"Indust Est;Rd",
    "iso:country":"GB",
    "sg:address":"Unit D5 Braintree Indust Est, Braintree Rd",
    "sg:city":"Ruislip",
    "sg:classifiers":[
        {
            "category":"Professional",
            "subcategory":"Engineering",
            "type":"Services"
        }
    ],
    "sg:phone":"+44 20 8841 1540",
    "sg:postcode":"HA4 0EJ",
    "sg:province":"Greater London",
    "wof:name":"Rep Engineering",
    "wof:placetype":"venue"
},
  "geometry": {"coordinates":[-0.4262790084,51.5758857727],"type":"Point"}
}