{
  "type": "Feature",
  "properties": {
    "addr:full":"Unit 1 Tolsons Mill Lichfield St, Fazeley Tamworth Staffordshire B78 3QA",
    "addr:housenumber":"unit 1",
    "addr:postcode":"b78 3qa",
    "addr:street":"Tolsons Mill Lichfield St",
    "iso:country":"GB",
    "sg:address":"Unit 1 Tolsons Mill Lichfield St, Fazeley",
    "sg:city":"Tamworth",
    "sg:classifiers":[
        {
            "category":"Professional",
            "subcategory":"Management & Consulting",
            "type":"Services"
        }
    ],
    "sg:postcode":"B78 3QA",
    "sg:province":"Staffordshire",
    "sg:tags":[
        "consultant",
        "promotion",
        "direct",
        "sale"
    ],
    "wof:name":"Chess Sales  &  Marketing Ltd",
    "wof:placetype":"venue"
},
  "geometry": {"coordinates":[-1.703699,52.615551],"type":"Point"}
}