{
  "type": "Feature",
  "properties": {
    "addr:full":"13 Lowbourne, Whitchurch Bristol City of Bristol BS14 0AN",
    "addr:housenumber":"13",
    "addr:postcode":"bs14 0an",
    "addr:street":"Lowbourne Whitchurch",
    "iso:country":"GB",
    "sg:address":"13 Lowbourne, Whitchurch",
    "sg:city":"Bristol",
    "sg:classifiers":[
        {
            "category":"Building & Trades",
            "subcategory":"Construction",
            "type":"Services"
        }
    ],
    "sg:postcode":"BS14 0AN",
    "sg:province":"City of Bristol",
    "sg:tags":[
        "roofing"
    ],
    "wof:name":"S R Francis & Son",
    "wof:placetype":"venue"
},
  "geometry": {"coordinates":[-2.5772418976,51.4163780212],"type":"Point"}
}