{
  "type": "Feature",
  "properties": {
    "addr:full":"5 New Mill Road Kilmarnock East Ayrshire KA1 3JG",
    "addr:housenumber":"5",
    "addr:postcode":"ka1 3jg",
    "addr:street":"New Mill Road",
    "iso:country":"GB",
    "sg:address":"5 New Mill Road",
    "sg:city":"Kilmarnock",
    "sg:classifiers":[
        {
            "category":"Building & Trades",
            "subcategory":"Construction",
            "type":"Services"
        }
    ],
    "sg:phone":"+44 1563 522298",
    "sg:postcode":"KA1 3JG",
    "sg:province":"East Ayrshire",
    "sg:tags":[
        "contractor"
    ],
    "wof:name":"Forbes & Whiteford Ltd.",
    "wof:placetype":"venue"
},
  "geometry": {"coordinates":[-4.487175,55.604279],"type":"Point"}
}