{
  "type": "Feature",
  "properties": {
    "addr:full":"Woodcotes La, Darlton Newark Nottinghamshire NG22 0TH",
    "addr:postcode":"ng22 0th",
    "iso:country":"GB",
    "sg:address":"Woodcotes La, Darlton",
    "sg:city":"Newark",
    "sg:classifiers":[
        {
            "category":"Freight",
            "type":"Transportation"
        }
    ],
    "sg:postcode":"NG22 0TH",
    "sg:province":"Nottinghamshire",
    "sg:tags":[
        "haulage",
        "road"
    ],
    "wof:name":"Thompson,Jenny,",
    "wof:placetype":"venue"
},
  "geometry": {"coordinates":[-0.8414620161,53.2538299561],"type":"Point"}
}