{
  "type": "Feature",
  "properties": {
    "addr:full":"76 Reads Avenue Blackpool Lancashire FY1 4DE",
    "addr:housenumber":"76",
    "addr:postcode":"fy1 4de",
    "addr:street":"Reads Avenue",
    "iso:country":"GB",
    "sg:address":"76 Reads Avenue",
    "sg:city":"Blackpool",
    "sg:classifiers":[
        {
            "category":"Travel",
            "subcategory":"Hotels & Motels",
            "type":"Entertainment"
        }
    ],
    "sg:phone":"+44 1253 621687",
    "sg:postcode":"FY1 4DE",
    "sg:province":"Lancashire",
    "wof:name":"Kendrick Private Hotel",
    "wof:placetype":"venue"
},
  "geometry": {"coordinates":[-3.0449869633,53.8138504028],"type":"Point"}
}