{
  "type": "Feature",
  "properties": {
    "iso:country":"GB",
    "sg:address":"285 Linthorpe Road",
    "sg:city":"Middlesbrough",
    "sg:classifiers":[
        {
            "category":"Fast Food",
            "type":"Food & Drink"
        }
    ],
    "sg:phone":"+44 1642 220299",
    "sg:postcode":"TS1 4AP",
    "sg:province":"North Yorkshire",
    "sg:tags":[
        "away",
        "take"
    ],
    "wof:name":"Tasty Mac's",
    "wof:placetype":"venue"
},
  "geometry": {"coordinates":[-1.23974,54.568199],"type":"Point"}
}