{
  "type": "Feature",
  "properties": {
    "iso:country":"GB",
    "sg:address":"17 Thorburn Road",
    "sg:city":"Northampton",
    "sg:classifiers":[
        {
            "category":"Health Services",
            "subcategory":"Health Practitioner",
            "type":"Services"
        }
    ],
    "sg:postcode":"NN3 3DA",
    "sg:province":"Northamptonshire",
    "sg:tags":[
        "hypnotherapists"
    ],
    "wof:name":"Margaret de-Banke",
    "wof:placetype":"venue"
},
  "geometry": {"coordinates":[-0.8414999843,52.2495155334],"type":"Point"}
}