{
  "type": "Feature",
  "properties": {
    "addr:full":"43-55 Milford Street Salisbury Wiltshire SP1 2BP",
    "addr:housenumber":"43-55",
    "addr:postcode":"sp1 2bp",
    "addr:street":"Milford Street",
    "iso:country":"GB",
    "sg:address":"43-55 Milford Street",
    "sg:city":"Salisbury",
    "sg:classifiers":[
        {
            "category":"Government",
            "subcategory":"Court House",
            "type":"Public Place"
        }
    ],
    "sg:phone":"+44 1722 333225",
    "sg:postcode":"SP1 2BP",
    "sg:province":"Wiltshire",
    "wof:name":"Clerk to the Justices",
    "wof:placetype":"venue"
},
  "geometry": {"coordinates":[-1.791293,51.068642],"type":"Point"}
}