{
  "type": "Feature",
  "properties": {
    "addr:full":"63 Fields Road, Alsager Stoke-on-trent Cheshire ST7 2LX",
    "addr:housenumber":"63",
    "addr:postcode":"st7 2lx",
    "addr:street":"Fields Road",
    "iso:country":"GB",
    "sg:address":"63 Fields Road, Alsager",
    "sg:city":"Stoke-on-trent",
    "sg:classifiers":[
        {
            "category":"Health Services",
            "subcategory":"Nursing And Care Facility",
            "type":"Services"
        }
    ],
    "sg:postcode":"ST7 2LX",
    "sg:province":"Cheshire",
    "sg:tags":[
        "home"
    ],
    "wof:name":"Grosvenor House Nursing Home",
    "wof:placetype":"venue"
},
  "geometry": {"coordinates":[-2.2990989685,53.0940742493],"type":"Point"}
}