{
  "type": "Feature",
  "properties": {
    "iso:country":"GB",
    "sg:address":"82a Burgess Road",
    "sg:city":"Southampton",
    "sg:classifiers":[
        {
            "category":"Building & Trades",
            "subcategory":"Cleaning & Sanitation",
            "type":"Services"
        }
    ],
    "sg:phone":"+44 23 8076 9636",
    "sg:postcode":"SO16 7PP",
    "sg:province":"Hampshire",
    "sg:tags":[
        "contracting",
        "commercial"
    ],
    "wof:name":"A C Cleaning",
    "wof:placetype":"venue"
},
  "geometry": {"coordinates":[-1.400702,50.937302],"type":"Point"}
}