{
  "type": "Feature",
  "properties": {
    "iso:country":"GB",
    "sg:address":"Millhouse Sidings, Hale Road",
    "sg:city":"Widnes",
    "sg:classifiers":[
        {
            "category":"Military Area",
            "subcategory":"Air Force Base",
            "type":"Public Place"
        }
    ],
    "sg:phone":"+44 151 424 5577",
    "sg:postcode":"WA8 0TL",
    "sg:province":"Cheshire",
    "sg:tags":[
        "taxi",
        "hire",
        "private"
    ],
    "wof:name":"Widnes Taxis",
    "wof:placetype":"venue"
},
  "geometry": {"coordinates":[-2.733244,53.374031],"type":"Point"}
}