{
  "type": "Feature",
  "properties": {
    "addr:full":"6 Blakeley Grove, Clifton Moor York North Yorkshire YO30 4UB",
    "addr:housenumber":"6",
    "addr:postcode":"yo30 4ub",
    "addr:street":"Blakeley Grove",
    "iso:country":"GB",
    "sg:address":"6 Blakeley Grove, Clifton Moor",
    "sg:city":"York",
    "sg:classifiers":[
        {
            "category":"Taxi",
            "type":"Transportation"
        }
    ],
    "sg:phone":"+44 1904 690142",
    "sg:postcode":"YO30 4UB",
    "sg:province":"North Yorkshire",
    "sg:tags":[
        "mini",
        "cab"
    ],
    "wof:name":"A1 Dale's Executive Travel",
    "wof:placetype":"venue"
},
  "geometry": {"coordinates":[-1.1059670448,53.9889183044],"type":"Point"}
}