{
  "type": "Feature",
  "properties": {
    "iso:country":"GB",
    "sg:address":"32 Vicarage Walk",
    "sg:city":"Yeovil",
    "sg:classifiers":[
        {
            "category":"Banks & Credit Unions",
            "subcategory":"Bank",
            "type":"Services"
        },
        {
            "category":"Banks & Credit Unions",
            "subcategory":"Financial Services",
            "type":"Services"
        }
    ],
    "sg:phone":"+44 1935 706103",
    "sg:postcode":"BA20 1EX",
    "sg:province":"Somerset",
    "sg:tags":[
        "building",
        "society",
        "institution"
    ],
    "wof:name":"Alliance & Leicester plc",
    "wof:placetype":"venue"
},
  "geometry": {"coordinates":[-2.713765,50.971558],"type":"Point"}
}