{
  "type": "Feature",
  "properties": {
    "iso:country":"GB",
    "sg:address":"Unit 8 Langley Park Industrial E, State, North Street Langley Mill",
    "sg:city":"Nottingham",
    "sg:classifiers":[
        {
            "category":"Professional",
            "subcategory":"Computer Services",
            "type":"Services"
        }
    ],
    "sg:phone":"+44 1773 533108",
    "sg:postcode":"NG16 4BS",
    "sg:province":"Derbyshire",
    "sg:tags":[
        "development",
        "system",
        "software"
    ],
    "wof:name":"The Computer Room",
    "wof:placetype":"venue"
},
  "geometry": {"coordinates":[-1.3343889713,53.0182189941],"type":"Point"}
}