{
  "type": "Feature",
  "properties": {
    "addr:full":"5 Forbes Road Edinburgh City of Edinburgh EH10 4EF",
    "addr:housenumber":"5",
    "addr:postcode":"eh10 4ef",
    "addr:street":"Forbes Road",
    "iso:country":"GB",
    "sg:address":"5 Forbes Road",
    "sg:city":"Edinburgh",
    "sg:classifiers":[
        {
            "category":"Farming",
            "subcategory":"Nursery",
            "type":"Manufacturing & Wholesale Goods"
        },
        {
            "category":"Social Services",
            "subcategory":"Child Care",
            "type":"Services"
        }
    ],
    "sg:phone":"+44 131 229 5511",
    "sg:postcode":"EH10 4EF",
    "sg:province":"City of Edinburgh",
    "sg:tags":[
        "creche"
    ],
    "wof:name":"Forbes Childrens Nursery",
    "wof:placetype":"venue"
},
  "geometry": {"coordinates":[-3.20729,55.935055],"type":"Point"}
}