{
  "type": "Feature",
  "properties": {
    "iso:country":"GB",
    "sg:address":"Melbourn Road",
    "sg:city":"Royston",
    "sg:classifiers":[
        {
            "category":"Retail",
            "subcategory":"Auto Repair",
            "type":"Services"
        }
    ],
    "sg:phone":"+44 1763 243131",
    "sg:postcode":"SG8 7DF",
    "sg:province":"Bedfordshire",
    "sg:tags":[
        "modification",
        "garage"
    ],
    "wof:name":"H Precious & Son",
    "wof:placetype":"venue"
},
  "geometry": {"coordinates":[-0.017104,52.05645],"type":"Point"}
}