{
  "type": "Feature",
  "properties": {
    "iso:country":"GB",
    "sg:address":"104 City Road",
    "sg:city":"Bradford",
    "sg:classifiers":[
        {
            "category":"Government",
            "subcategory":"Post Office",
            "type":"Public Place"
        }
    ],
    "sg:postcode":"BD8 8JT",
    "sg:province":"West Yorkshire",
    "wof:name":"CITY ROAD SUB POST OFFICE",
    "wof:placetype":"venue"
},
  "geometry": {"coordinates":[-1.76617,53.798031],"type":"Point"}
}