{
  "type": "Feature",
  "properties": {
    "iso:country":"GB",
    "sg:address":"Pennine House",
    "sg:city":"Washington",
    "sg:classifiers":[
        {
            "category":"Professional",
            "subcategory":"Employment Agencies",
            "type":"Services"
        }
    ],
    "sg:phone":"+44 191 451 3255",
    "sg:postcode":"NE37 1LY",
    "sg:province":"Tyne and Wear",
    "sg:tags":[
        "consultant"
    ],
    "wof:name":"Employment Service Jobcentre",
    "wof:placetype":"venue"
},
  "geometry": {"coordinates":[-1.534340024,54.8964309692],"type":"Point"}
}