{
  "type": "Feature",
  "properties": {
    "iso:country":"GB",
    "sg:address":"40 Church Street",
    "sg:city":"Lancaster",
    "sg:classifiers":[
        {
            "category":"Shopping",
            "subcategory":"Jewelry",
            "type":"Retail Goods"
        },
        {
            "category":"Shopping",
            "subcategory":"Comic Books",
            "type":"Retail Goods"
        }
    ],
    "sg:phone":"+44 1524 381020",
    "sg:postcode":"LA1 1LH",
    "sg:province":"Lancashire",
    "sg:tags":[
        "jeweller",
        "sale",
        "jewellery"
    ],
    "wof:name":"R Banks-Lyon Jewellers",
    "wof:placetype":"venue"
},
  "geometry": {"coordinates":[-2.800769,54.049843],"type":"Point"}
}