{
  "type": "Feature",
  "properties": {
    "addr:full":"1 Fern Av Prestatyn Denbighshire LL19 9DN",
    "addr:housenumber":"1",
    "addr:postcode":"ll19 9dn",
    "addr:street":"Fern Av Prestatyn",
    "iso:country":"GB",
    "sg:address":"1 Fern Av",
    "sg:city":"Prestatyn",
    "sg:classifiers":[
        {
            "category":"Health Services",
            "subcategory":"Dentist",
            "type":"Services"
        }
    ],
    "sg:phone":"+44 1745 887098",
    "sg:postcode":"LL19 9DN",
    "sg:province":"Denbighshire",
    "wof:name":"Dental Practice The",
    "wof:placetype":"venue"
},
  "geometry": {"coordinates":[-3.4020409584,53.3325042725],"type":"Point"}
}