{
  "type": "Feature",
  "properties": {
    "iso:country":"GB",
    "sg:address":"16-18 East Street",
    "sg:city":"Shoreham-by-sea",
    "sg:classifiers":[
        {
            "category":"Personal",
            "subcategory":"Beauty Salon",
            "type":"Services"
        },
        {
            "category":"Sports & Exercise",
            "subcategory":"Gym",
            "type":"Entertainment"
        }
    ],
    "sg:phone":"+44 1273 464809",
    "sg:postcode":"BN43 5ZE",
    "sg:province":"West Sussex",
    "sg:tags":[
        "fitness",
        "health",
        "centre"
    ],
    "wof:name":"Proforma Toning & Beauty Studio",
    "wof:placetype":"venue"
},
  "geometry": {"coordinates":[-0.274165,50.832039],"type":"Point"}
}