{
  "type": "Feature",
  "properties": {
    "iso:country":"GB",
    "sg:address":"5 Quality Corner, Seaton",
    "sg:city":"Workington",
    "sg:classifiers":[
        {
            "category":"Professional",
            "subcategory":"Art Services",
            "type":"Services"
        },
        {
            "category":"Building & Trades",
            "subcategory":"Construction",
            "type":"Services"
        }
    ],
    "sg:phone":"+44 1900 605847",
    "sg:postcode":"CA14 1HZ",
    "sg:province":"Cumbria",
    "sg:tags":[
        "decorator",
        "painter"
    ],
    "wof:name":"Ronald Knowles",
    "wof:placetype":"venue"
},
  "geometry": {"coordinates":[-3.524929,54.66201],"type":"Point"}
}