{
  "type": "Feature",
  "properties": {
    "addr:full":"4 Bank St Ashford Kent TN23 1BX",
    "addr:housenumber":"4",
    "addr:postcode":"tn23 1bx",
    "addr:street":"Bank St",
    "iso:country":"GB",
    "sg:address":"4 Bank St",
    "sg:city":"Ashford",
    "sg:classifiers":[
        {
            "category":"Sports & Exercise",
            "subcategory":"Sports Center",
            "type":"Entertainment"
        }
    ],
    "sg:phone":"+44 1233 640917",
    "sg:postcode":"TN23 1BX",
    "sg:province":"Kent",
    "sg:tags":[
        "shop",
        "good"
    ],
    "wof:name":"G'Day Sport",
    "wof:placetype":"venue"
},
  "geometry": {"coordinates":[0.870958,51.148411],"type":"Point"}
}