{
  "type": "Feature",
  "properties": {
    "addr:full":"Fountain Close Birmingham West Midlands B31 4NF",
    "addr:postcode":"b31 4nf",
    "addr:street":"Fountain Close",
    "iso:country":"GB",
    "sg:address":"Fountain Close",
    "sg:city":"Birmingham",
    "sg:classifiers":[
        {
            "category":"Manufacturing",
            "subcategory":"Furniture",
            "type":"Manufacturing & Wholesale Goods"
        }
    ],
    "sg:phone":"+44 121 477 6735",
    "sg:postcode":"B31 4NF",
    "sg:province":"West Midlands",
    "sg:tags":[
        "polishing",
        "french"
    ],
    "wof:name":"Andrew Fisher French Polishing",
    "wof:placetype":"venue"
},
  "geometry": {"coordinates":[-1.9841790199,52.3881645203],"type":"Point"}
}