{
  "type": "Feature",
  "properties": {
    "iso:country":"GB",
    "sg:address":"3 Glenfield Place, Glencairn Industrial Estate",
    "sg:city":"Kilmarnock",
    "sg:classifiers":[
        {
            "category":"Shopping",
            "subcategory":"Crafts & Fabrics",
            "type":"Retail Goods"
        }
    ],
    "sg:phone":"+44 1563 541138",
    "sg:postcode":"KA1 4AY",
    "sg:province":"East Ayrshire",
    "sg:tags":[
        "knitwear",
        "yarn"
    ],
    "wof:name":"Shanter Textiles Ltd.",
    "wof:placetype":"venue"
},
  "geometry": {"coordinates":[-4.494698,55.600838],"type":"Point"}
}