{
  "type": "Feature",
  "properties": {
    "addr:full":"Charing Cross Station, Strand Holborn Greater London WC2N 5HS",
    "addr:postcode":"wc2n 5hs",
    "addr:street":"Charing Cross Station Strand",
    "iso:country":"GB",
    "sg:address":"Charing Cross Station, Strand",
    "sg:city":"Holborn",
    "sg:classifiers":[
        {
            "category":"Shopping",
            "subcategory":"Clothing, Apparel, & Fashions",
            "type":"Retail Goods"
        }
    ],
    "sg:phone":"+44 20 7839 8979",
    "sg:postcode":"WC2N 5HS",
    "sg:province":"Greater London",
    "sg:tags":[
        "lingerie",
        "hosiery"
    ],
    "wof:name":"Knickerbox",
    "wof:placetype":"venue"
},
  "geometry": {"coordinates":[-0.12478,51.508308],"type":"Point"}
}