{
  "type": "Feature",
  "properties": {
    "iso:country":"GB",
    "sg:address":"Loop Road North",
    "sg:city":"Whitehaven",
    "sg:classifiers":[
        {
            "category":"Autos & Motor Vehicles",
            "subcategory":"Fuel & Gas Station",
            "type":"Retail Goods"
        }
    ],
    "sg:phone":"+44 1946 66363",
    "sg:postcode":"CA28 6EA",
    "sg:province":"Cumbria",
    "sg:tags":[
        "hr",
        "petrol"
    ],
    "wof:name":"Pelican Self Serve",
    "wof:placetype":"venue"
},
  "geometry": {"coordinates":[-3.578099,54.560982],"type":"Point"}
}