{
  "type": "Feature",
  "properties": {
    "addr:full":"186-188 New Road High Wycombe Buckinghamshire HP12 4RG",
    "addr:housenumber":"186-188",
    "addr:postcode":"hp12 4rg",
    "addr:street":"New Road",
    "iso:country":"GB",
    "sg:address":"186-188 New Road",
    "sg:city":"High Wycombe",
    "sg:classifiers":[
        {
            "category":"Food & Beverages",
            "subcategory":"Supermarket",
            "type":"Retail Goods"
        }
    ],
    "sg:phone":"+44 1494 530681",
    "sg:postcode":"HP12 4RG",
    "sg:province":"Buckinghamshire",
    "wof:name":"Squirrel Lane Store",
    "wof:placetype":"venue"
},
  "geometry": {"coordinates":[-0.7844020128,51.6205215454],"type":"Point"}
}