{
  "type": "Feature",
  "properties": {
    "addr:full":"6 Castle Street Edinburgh City of Edinburgh EH2 3AT",
    "addr:housenumber":"6",
    "addr:postcode":"eh2 3at",
    "addr:street":"Castle Street",
    "iso:country":"GB",
    "sg:address":"6 Castle Street",
    "sg:city":"Edinburgh",
    "sg:classifiers":[
        {
            "category":"Government",
            "subcategory":"Office",
            "type":"Public Place"
        }
    ],
    "sg:phone":"+44 131 226 1662",
    "sg:postcode":"EH2 3AT",
    "sg:province":"City of Edinburgh",
    "sg:tags":[
        "chamber",
        "commerce"
    ],
    "wof:name":"Castle Rock Business Centre",
    "wof:placetype":"venue"
},
  "geometry": {"coordinates":[-3.2030088902,55.9512290955],"type":"Point"}
}