{
  "type": "Feature",
  "properties": {
    "iso:country":"GB",
    "sg:address":"Rose Hill",
    "sg:city":"Dymock",
    "sg:classifiers":[
        {
            "category":"Farming",
            "subcategory":"Farm",
            "type":"Manufacturing & Wholesale Goods"
        }
    ],
    "sg:phone":"+44 1531 890216",
    "sg:postcode":"GL18 2EF",
    "sg:province":"Gloucestershire",
    "sg:tags":[
        "mixed",
        "crop"
    ],
    "wof:name":"M F Bennion",
    "wof:placetype":"venue"
},
  "geometry": {"coordinates":[-2.439709,51.978809],"type":"Point"}
}