{
  "type": "Feature",
  "properties": {
    "addr:full":"23 Stratford Avenue Newcastle Staffordshire ST5 0JS",
    "addr:housenumber":"23",
    "addr:postcode":"st5 0js",
    "addr:street":"Stratford Avenue",
    "iso:country":"GB",
    "sg:address":"23 Stratford Avenue",
    "sg:city":"Newcastle",
    "sg:classifiers":[
        {
            "category":"Professional",
            "subcategory":"Accounting & Tax Preparation",
            "type":"Services"
        }
    ],
    "sg:postcode":"ST5 0JS",
    "sg:province":"Staffordshire",
    "sg:tags":[
        "accountant"
    ],
    "wof:name":"A J Business Services",
    "wof:placetype":"venue"
},
  "geometry": {"coordinates":[-2.210998,53.024132],"type":"Point"}
}