{
  "type": "Feature",
  "properties": {
    "iso:country":"GB",
    "sg:address":"238 Brook Street, Broughty Ferry",
    "sg:city":"Dundee",
    "sg:classifiers":[
        {
            "category":"Food & Beverages",
            "subcategory":"Fruits & Vegetables",
            "type":"Retail Goods"
        }
    ],
    "sg:postcode":"DD5 2AH",
    "sg:province":"Angus",
    "sg:tags":[
        "greengrocer"
    ],
    "wof:name":"White Betty",
    "wof:placetype":"venue"
},
  "geometry": {"coordinates":[-2.873942,56.467022],"type":"Point"}
}