{
  "type": "Feature",
  "properties": {
    "iso:country":"GB",
    "sg:address":"Sheddingdean Neighb'hood Cntr, Maple Drive",
    "sg:city":"Burgess Hill",
    "sg:classifiers":[
        {
            "category":"Shopping",
            "subcategory":"Pharmacy",
            "type":"Retail Goods"
        }
    ],
    "sg:phone":"+44 1444 870339",
    "sg:postcode":"RH15 8AP",
    "sg:province":"East Sussex",
    "sg:tags":[
        "pharmacist",
        "chemist"
    ],
    "wof:name":"Jessica's Chemist",
    "wof:placetype":"venue"
},
  "geometry": {"coordinates":[-0.12552,50.9655],"type":"Point"}
}