{
  "type": "Feature",
  "properties": {
    "addr:full":"Lea Road Northampton Northamptonshire NN1 4PF",
    "addr:postcode":"nn1 4pf",
    "addr:street":"Lea Road",
    "iso:country":"GB",
    "sg:address":"Lea Road",
    "sg:city":"Northampton",
    "sg:classifiers":[
        {
            "category":"Place Of Worship",
            "type":"Public Place"
        }
    ],
    "sg:phone":"+44 1604 627002",
    "sg:postcode":"NN1 4PF",
    "sg:province":"Northamptonshire",
    "wof:name":"Abington Christian Centre",
    "wof:placetype":"venue"
},
  "geometry": {"coordinates":[-0.875392,52.246964],"type":"Point"}
}