{
  "type": "Feature",
  "properties": {
    "iso:country":"GB",
    "sg:address":"Pennyford Lane, Wootton Wawen",
    "sg:city":"Solihull",
    "sg:classifiers":[
        {
            "category":"Sports & Exercise",
            "subcategory":"Stables",
            "type":"Entertainment"
        }
    ],
    "sg:postcode":"B95 6EZ",
    "sg:province":"Warwickshire",
    "sg:tags":[
        "education",
        "equestrian"
    ],
    "wof:name":"Field Farm",
    "wof:placetype":"venue"
},
  "geometry": {"coordinates":[-1.7774089575,52.2667312622],"type":"Point"}
}