{
  "type": "Feature",
  "properties": {
    "addr:full":"6 Lowdon Close, Keep Hill High Wycombe Buckinghamshire HP11 1DN",
    "addr:housenumber":"6",
    "addr:postcode":"hp11 1dn",
    "addr:street":"Lowdon Close Keep Hill",
    "iso:country":"GB",
    "sg:address":"6 Lowdon Close, Keep Hill",
    "sg:city":"High Wycombe",
    "sg:classifiers":[
        {
            "category":"Professional",
            "type":"Services"
        },
        {
            "category":"Professional",
            "subcategory":"Art Services",
            "type":"Services"
        }
    ],
    "sg:phone":"+44 1494 472833",
    "sg:postcode":"HP11 1DN",
    "sg:province":"Buckinghamshire",
    "sg:tags":[
        "interior",
        "furnishers",
        "designer"
    ],
    "wof:name":"Gyoker Designs",
    "wof:placetype":"venue"
},
  "geometry": {"coordinates":[-0.7372649908,51.6194114685],"type":"Point"}
}