{
  "type": "Feature",
  "properties": {
    "addr:full":"10 Ivygreen Road, Chorlton Cum Hardy Manchester Cheshire M21 9ET",
    "addr:housenumber":"10",
    "addr:postcode":"m21 9et",
    "addr:street":"Ivygreen Road",
    "iso:country":"GB",
    "sg:address":"10 Ivygreen Road, Chorlton Cum Hardy",
    "sg:city":"Manchester",
    "sg:classifiers":[
        {
            "category":"Home & Garden",
            "subcategory":"Carpets & Floor Coverings",
            "type":"Retail Goods"
        }
    ],
    "sg:postcode":"M21 9ET",
    "sg:province":"Cheshire",
    "sg:tags":[
        "cleaner",
        "upholstery"
    ],
    "wof:name":"Masterclean Services",
    "wof:placetype":"venue"
},
  "geometry": {"coordinates":[-2.2843410969,53.4376983643],"type":"Point"}
}