{
  "type": "Feature",
  "properties": {
    "iso:country":"GB",
    "sg:address":"35 Beacon Road, Romiley",
    "sg:city":"Stockport",
    "sg:classifiers":[
        {
            "category":"Shopping",
            "subcategory":"News",
            "type":"Retail Goods"
        }
    ],
    "sg:postcode":"SK6 3ET",
    "sg:province":"Cheshire",
    "sg:tags":[
        "newsagent"
    ],
    "wof:name":"Tonys News",
    "wof:placetype":"venue"
},
  "geometry": {"coordinates":[-2.103286,53.407173],"type":"Point"}
}