{
  "type": "Feature",
  "properties": {
    "addr:full":"5 Gresham Clo Plymouth Devon PL5 4QD",
    "addr:housenumber":"5",
    "addr:postcode":"pl5 4qd",
    "iso:country":"GB",
    "sg:address":"5 Gresham Clo",
    "sg:city":"Plymouth",
    "sg:classifiers":[
        {
            "category":"Shopping",
            "subcategory":"Hobbies, Toys, & Games",
            "type":"Retail Goods"
        }
    ],
    "sg:phone":"+44 1752 781563",
    "sg:postcode":"PL5 4QD",
    "sg:province":"Devon",
    "sg:tags":[
        "stamp"
    ],
    "wof:name":"M A M Stamps & Coins",
    "wof:placetype":"venue"
},
  "geometry": {"coordinates":[-4.1496310234,50.4322738647],"type":"Point"}
}