{
  "type": "Feature",
  "properties": {
    "addr:full":"7 Shute Park, Marlborough Kingsbridge Devon TQ7 3SU",
    "addr:housenumber":"7",
    "addr:postcode":"tq7 3su",
    "addr:street":"Shute Park",
    "iso:country":"GB",
    "sg:address":"7 Shute Park, Marlborough",
    "sg:city":"Kingsbridge",
    "sg:classifiers":[
        {
            "category":"Building & Trades",
            "subcategory":"Construction",
            "type":"Services"
        }
    ],
    "sg:postcode":"TQ7 3SU",
    "sg:province":"Devon",
    "sg:tags":[
        "builder"
    ],
    "wof:name":"Martin Pepperell",
    "wof:placetype":"venue"
},
  "geometry": {"coordinates":[-3.8126399517,50.2419509888],"type":"Point"}
}