{
  "type": "Feature",
  "properties": {
    "iso:country":"GB",
    "sg:address":"103 Maldon Road, Tiptree",
    "sg:city":"Colchester",
    "sg:classifiers":[
        {
            "category":"Education",
            "subcategory":"School",
            "type":"Public Place"
        }
    ],
    "sg:phone":"+44 1621 815445",
    "sg:postcode":"CO5 0PG",
    "sg:province":"Essex",
    "sg:tags":[
        "local",
        "authority"
    ],
    "wof:name":"Tiptree Heath County Primary School",
    "wof:placetype":"venue"
},
  "geometry": {"coordinates":[0.738923,51.806091],"type":"Point"}
}