{
  "type": "Feature",
  "properties": {
    "iso:country":"GB",
    "sg:address":"68 Manchester Road",
    "sg:city":"Oldham",
    "sg:classifiers":[
        {
            "category":"Professional",
            "subcategory":"Accounting & Tax Preparation",
            "type":"Services"
        }
    ],
    "sg:postcode":"OL9 7AU",
    "sg:province":"Lancashire",
    "sg:tags":[
        "accountant"
    ],
    "wof:name":"Grundy Anderson & Kershaw",
    "wof:placetype":"venue"
},
  "geometry": {"coordinates":[-2.1338219643,53.5310821533],"type":"Point"}
}