{
  "type": "Feature",
  "properties": {
    "addr:full":"105 Queens Rd Reading Berkshire RG1 4DA",
    "addr:housenumber":"105",
    "addr:postcode":"rg1 4da",
    "addr:street":"Queens Rd",
    "iso:country":"GB",
    "sg:address":"105 Queens Rd",
    "sg:city":"Reading",
    "sg:classifiers":[
        {
            "category":"Professional",
            "subcategory":"Employment Agencies",
            "type":"Services"
        }
    ],
    "sg:phone":"+44 118 950 5022",
    "sg:postcode":"RG1 4DA",
    "sg:province":"Berkshire",
    "sg:tags":[
        "consultant"
    ],
    "wof:name":"James Baker Associates",
    "wof:placetype":"venue"
},
  "geometry": {"coordinates":[-0.9611020088,51.4539031982],"type":"Point"}
}