{
  "type": "Feature",
  "properties": {
    "iso:country":"GB",
    "sg:address":"Chesters Grn, Morton Bagot",
    "sg:city":"Studley",
    "sg:classifiers":[
        {
            "category":"Building & Trades",
            "subcategory":"Landscaping Services",
            "type":"Services"
        }
    ],
    "sg:phone":"+44 1527 852675",
    "sg:postcode":"B80 7EB",
    "sg:province":"Warwickshire",
    "sg:tags":[
        "forestry",
        "surgeon",
        "tree"
    ],
    "wof:name":"W S Ross & Sons",
    "wof:placetype":"venue"
},
  "geometry": {"coordinates":[-1.892036,52.266304],"type":"Point"}
}