{
  "type": "Feature",
  "properties": {
    "addr:full":"4 Coles Lane Sutton Coldfield West Midlands B72 1NE",
    "addr:housenumber":"4",
    "addr:postcode":"b72 1ne",
    "addr:street":"Coles Lane",
    "iso:country":"GB",
    "sg:address":"4 Coles Lane",
    "sg:city":"Sutton Coldfield",
    "sg:classifiers":[
        {
            "category":"Professional",
            "subcategory":"Engineering",
            "type":"Services"
        }
    ],
    "sg:phone":"+44 121 355 0221",
    "sg:postcode":"B72 1NE",
    "sg:province":"West Midlands",
    "sg:tags":[
        "civil",
        "engineer"
    ],
    "wof:name":"McBrine Structures (Midlands) Ltd.",
    "wof:placetype":"venue"
},
  "geometry": {"coordinates":[-1.823316,52.557716],"type":"Point"}
}