{
  "type": "Feature",
  "properties": {
    "iso:country":"GB",
    "sg:address":"Leedon House, Billington Road",
    "sg:city":"Leighton Buzzard",
    "sg:classifiers":[
        {
            "category":"Manufacturing",
            "subcategory":"Wood Products",
            "type":"Manufacturing & Wholesale Goods"
        },
        {
            "category":"Manufacturing",
            "subcategory":"Building Materials",
            "type":"Manufacturing & Wholesale Goods"
        }
    ],
    "sg:phone":"+44 1525 379909",
    "sg:postcode":"LU7 4TN",
    "sg:province":"Bedfordshire",
    "sg:tags":[
        "mnfr",
        "maker",
        "cabinet"
    ],
    "sg:website":"http://www.customconsoles.co.uk",
    "wof:name":"Custom Consoles Ltd",
    "wof:placetype":"venue"
},
  "geometry": {"coordinates":[-0.656709,51.913086],"type":"Point"}
}