{
  "type": "Feature",
  "properties": {
    "iso:country":"GB",
    "sg:address":"Vicarage Lane",
    "sg:city":"Rochester",
    "sg:classifiers":[
        {
            "category":"Banks & Credit Unions",
            "subcategory":"Financial Services",
            "type":"Services"
        }
    ],
    "sg:phone":"+44 1634 256999",
    "sg:postcode":"ME3 9TW",
    "sg:province":"Kent",
    "sg:tags":[
        "adviser"
    ],
    "wof:name":"De Glanville Thomas",
    "wof:placetype":"venue"
},
  "geometry": {"coordinates":[0.5643010139,51.4193115234],"type":"Point"}
}