{
  "type": "Feature",
  "properties": {
    "addr:full":"1 Huntington Terrace Road Cannock Staffordshire WS11 2HA",
    "addr:housenumber":"1",
    "addr:postcode":"ws11 2ha",
    "addr:street":"Huntington Terrace Road",
    "iso:country":"GB",
    "sg:address":"1 Huntington Terrace Road",
    "sg:city":"Cannock",
    "sg:classifiers":[
        {
            "category":"Food & Beverages",
            "subcategory":"Groceries & Convenience Stores",
            "type":"Retail Goods"
        }
    ],
    "sg:phone":"+44 1543 571150",
    "sg:postcode":"WS11 2HA",
    "sg:province":"Staffordshire",
    "wof:name":"A & S Nakhwal",
    "wof:placetype":"venue"
},
  "geometry": {"coordinates":[-2.0210180283,52.7001152039],"type":"Point"}
}