{
  "type": "Feature",
  "properties": {
    "iso:country":"GB",
    "sg:address":"45 St Martins Precinct, Church Street, Caversham",
    "sg:city":"Reading",
    "sg:classifiers":[
        {
            "category":"Shopping",
            "subcategory":"Pharmacy",
            "type":"Retail Goods"
        }
    ],
    "sg:phone":"+44 118 947 1602",
    "sg:postcode":"RG4 8BA",
    "sg:province":"Berkshire",
    "sg:tags":[
        "pharmacist",
        "chemist"
    ],
    "wof:name":"Boots the Chemists",
    "wof:placetype":"venue"
},
  "geometry": {"coordinates":[-0.967664,51.474174],"type":"Point"}
}