{
  "type": "Feature",
  "properties": {
    "addr:full":"130 Alcester Road, Moseley Birmingham West Midlands B13 8EE",
    "addr:housenumber":"130",
    "addr:postcode":"b13 8ee",
    "addr:street":"Alcester Road",
    "iso:country":"GB",
    "sg:address":"130 Alcester Road, Moseley",
    "sg:city":"Birmingham",
    "sg:classifiers":[
        {
            "category":"Real Estate",
            "subcategory":"Surveying",
            "type":"Services"
        }
    ],
    "sg:phone":"+44 121 449 2499",
    "sg:postcode":"B13 8EE",
    "sg:province":"West Midlands",
    "sg:tags":[
        "surveyor",
        "valuer"
    ],
    "wof:name":"Ian Currall & Partners",
    "wof:placetype":"venue"
},
  "geometry": {"coordinates":[-1.887751,52.448475],"type":"Point"}
}