{
  "type": "Feature",
  "properties": {
    "iso:country":"GB",
    "sg:address":"290 Elgin Avenue, Maida Vale",
    "sg:city":"London",
    "sg:classifiers":[
        {
            "category":"Real Estate",
            "subcategory":"Real Estate Agent",
            "type":"Services"
        }
    ],
    "sg:postcode":"W9 1JS",
    "sg:province":"Greater London",
    "wof:name":"Ashley Milton Ltd.",
    "wof:placetype":"venue"
},
  "geometry": {"coordinates":[-0.1858559996,51.5299034119],"type":"Point"}
}