{
  "type": "Feature",
  "properties": {
    "addr:full":"57 Howlands Welwyn Garden City Hertfordshire AL7 4RA",
    "addr:housenumber":"57",
    "addr:postcode":"al7 4ra",
    "addr:street":"Howlands Welwyn",
    "iso:country":"GB",
    "sg:address":"57 Howlands",
    "sg:city":"Welwyn Garden City",
    "sg:classifiers":[
        {
            "category":"Shopping",
            "subcategory":"Musical Instruments",
            "type":"Retail Goods"
        }
    ],
    "sg:postcode":"AL7 4RA",
    "sg:province":"Hertfordshire",
    "wof:name":"D C J Grosser",
    "wof:placetype":"venue"
},
  "geometry": {"coordinates":[-0.1768029928,51.7882461548],"type":"Point"}
}