{
  "type": "Feature",
  "properties": {
    "iso:country":"GB",
    "sg:address":"288 Queenstown Road, Battersea",
    "sg:city":"London",
    "sg:classifiers":[
        {
            "category":"Professional",
            "subcategory":"Management & Consulting",
            "type":"Services"
        }
    ],
    "sg:postcode":"SW8 4LT",
    "sg:province":"Greater London",
    "sg:tags":[
        "consultant",
        "business"
    ],
    "wof:name":"Radicle Contracts Ltd",
    "wof:placetype":"venue"
},
  "geometry": {"coordinates":[-0.148108,51.476715],"type":"Point"}
}