{
  "type": "Feature",
  "properties": {
    "iso:country":"GB",
    "sg:address":"16 Trebblepark Walk",
    "sg:city":"Kingsbridge",
    "sg:classifiers":[
        {
            "category":"Health Services",
            "subcategory":"Health Practitioner",
            "type":"Services"
        }
    ],
    "sg:phone":"+44 1548 853499",
    "sg:postcode":"TQ7 1QR",
    "sg:province":"Devon",
    "sg:tags":[
        "homoeopathic"
    ],
    "wof:name":"Myra Harvey Homoeopath",
    "wof:placetype":"venue"
},
  "geometry": {"coordinates":[-3.780395,50.28857],"type":"Point"}
}