{
  "type": "Feature",
  "properties": {
    "addr:full":"Twyford Crescent, Acton London Greater London W3 9PP",
    "addr:postcode":"w3 9pp",
    "addr:street":"Twyford Crescent",
    "iso:country":"GB",
    "sg:address":"Twyford Crescent, Acton",
    "sg:city":"London",
    "sg:classifiers":[
        {
            "category":"Education",
            "subcategory":"School",
            "type":"Public Place"
        },
        {
            "category":"Government",
            "subcategory":"Office",
            "type":"Public Place"
        }
    ],
    "sg:phone":"+44 20 8752 0141",
    "sg:postcode":"W3 9PP",
    "sg:province":"Greater London",
    "sg:tags":[
        "local",
        "authority"
    ],
    "wof:name":"Twyford Church of England High School",
    "wof:placetype":"venue"
},
  "geometry": {"coordinates":[-0.2802,51.508949],"type":"Point"}
}