{
  "type": "Feature",
  "properties": {
    "addr:full":"Kerelaw Depot, Kerelaw Rd Stevenston North Ayrshire KA20 4AS",
    "addr:postcode":"ka20 4as",
    "addr:street":"Kerelaw Rd",
    "iso:country":"GB",
    "sg:address":"Kerelaw Depot, Kerelaw Rd",
    "sg:city":"Stevenston",
    "sg:classifiers":[
        {
            "category":"Farming",
            "subcategory":"Farm",
            "type":"Manufacturing & Wholesale Goods"
        }
    ],
    "sg:phone":"+44 1294 463785",
    "sg:postcode":"KA20 4AS",
    "sg:province":"North Ayrshire",
    "sg:tags":[
        "mixed",
        "crop"
    ],
    "wof:name":"Matthew Watt",
    "wof:placetype":"venue"
},
  "geometry": {"coordinates":[-4.75814,55.64365],"type":"Point"}
}