{
  "type": "Feature",
  "properties": {
    "addr:full":"232 Queens Rd Halifax West Yorkshire HX1 4NE",
    "addr:housenumber":"232",
    "addr:postcode":"hx1 4ne",
    "addr:street":"Queens Rd",
    "iso:country":"GB",
    "sg:address":"232 Queens Rd",
    "sg:city":"Halifax",
    "sg:classifiers":[
        {
            "category":"Personal",
            "subcategory":"Barber",
            "type":"Services"
        }
    ],
    "sg:postcode":"HX1 4NE",
    "sg:province":"West Yorkshire",
    "sg:tags":[
        "men's",
        "hairdresser"
    ],
    "wof:name":"Geoff's Barber Shop",
    "wof:placetype":"venue"
},
  "geometry": {"coordinates":[-1.8813509941,53.7237625122],"type":"Point"}
}