{
  "type": "Feature",
  "properties": {
    "addr:full":"Merrywalks Shopping Centre, King Street Stroud Gloucestershire GL5 1RR",
    "addr:postcode":"gl5 1rr",
    "addr:street":"King Street",
    "iso:country":"GB",
    "sg:address":"Merrywalks Shopping Centre, King Street",
    "sg:city":"Stroud",
    "sg:classifiers":[
        {
            "category":"Food & Beverages",
            "subcategory":"Supermarket",
            "type":"Retail Goods"
        }
    ],
    "sg:phone":"+44 1453 766221",
    "sg:postcode":"GL5 1RR",
    "sg:province":"Gloucestershire",
    "wof:name":"Somerfield",
    "wof:placetype":"venue"
},
  "geometry": {"coordinates":[-2.232441,51.744934],"type":"Point"}
}