{
  "type": "Feature",
  "properties": {
    "iso:country":"GB",
    "sg:address":"Marquis Road",
    "sg:city":"Aberdeen",
    "sg:classifiers":[
        {
            "category":"Community Center",
            "type":"Public Place"
        },
        {
            "category":"Community Center",
            "subcategory":"Youth",
            "type":"Public Place"
        },
        {
            "category":"Government",
            "subcategory":"Office",
            "type":"Public Place"
        }
    ],
    "sg:phone":"+44 1224 485983",
    "sg:postcode":"AB24 2QY",
    "sg:province":"Aberdeen City",
    "sg:tags":[
        "local",
        "centre"
    ],
    "wof:name":"Woodside Community Centre",
    "wof:placetype":"venue"
},
  "geometry": {"coordinates":[-2.121194,57.16975],"type":"Point"}
}