{
  "type": "Feature",
  "properties": {
    "addr:full":"120 High Street East Wallsend Tyne and Wear NE28 7RH",
    "addr:housenumber":"120",
    "addr:postcode":"ne28 7rh",
    "addr:street":"High Street East",
    "iso:country":"GB",
    "sg:address":"120 High Street East",
    "sg:city":"Wallsend",
    "sg:classifiers":[
        {
            "category":"Restaurant",
            "type":"Food & Drink"
        }
    ],
    "sg:phone":"+44 191 295 3949",
    "sg:postcode":"NE28 7RH",
    "sg:province":"Tyne and Wear",
    "sg:tags":[
        "indian",
        "-"
    ],
    "wof:name":"Light Of India",
    "wof:placetype":"venue"
},
  "geometry": {"coordinates":[-1.529097,54.991726],"type":"Point"}
}