{
  "type": "Feature",
  "properties": {
    "addr:full":"27 Guthrie Port Arbroath Angus DD11 1RW",
    "addr:housenumber":"27",
    "addr:postcode":"dd11 1rw",
    "addr:street":"Guthrie Port",
    "iso:country":"GB",
    "sg:address":"27 Guthrie Port",
    "sg:city":"Arbroath",
    "sg:classifiers":[
        {
            "category":"Shopping",
            "subcategory":"Discount & Variety Stores",
            "type":"Retail Goods"
        }
    ],
    "sg:postcode":"DD11 1RW",
    "sg:province":"Angus",
    "sg:tags":[
        "shop",
        "model"
    ],
    "wof:name":"Burnett,Alister,",
    "wof:placetype":"venue"
},
  "geometry": {"coordinates":[-2.5846478939,56.5627593994],"type":"Point"}
}