{
  "type": "Feature",
  "properties": {
    "addr:full":"Adur Boatyard, Old Shoreham Rd Shoreham By Sea West Sussex BN43 5TA",
    "addr:postcode":"bn43 5ta",
    "addr:street":"Old Shoreham Rd",
    "iso:country":"GB",
    "sg:address":"Adur Boatyard, Old Shoreham Rd",
    "sg:city":"Shoreham By Sea",
    "sg:classifiers":[
        {
            "category":"Wholesale",
            "subcategory":"Groceries",
            "type":"Manufacturing & Wholesale Goods"
        },
        {
            "category":"Utilities",
            "subcategory":"Natural Gas",
            "type":"Services"
        }
    ],
    "sg:phone":"+44 1273 454831",
    "sg:postcode":"BN43 5TA",
    "sg:province":"West Sussex",
    "sg:tags":[
        "repair",
        "food",
        "drink",
        "petrol",
        "pump",
        "supplier"
    ],
    "wof:name":"Sofitam Pump Services Ltd",
    "wof:placetype":"venue"
},
  "geometry": {"coordinates":[-0.2764689922,50.8319168091],"type":"Point"}
}