{
  "type": "Feature",
  "properties": {
    "iso:country":"GB",
    "sg:address":"Hardway",
    "sg:city":"Bruton",
    "sg:classifiers":[
        {
            "category":"Bars & Pubs",
            "type":"Food & Drink"
        }
    ],
    "sg:phone":"+44 1749 812200",
    "sg:postcode":"BA10 0LN",
    "sg:province":"Somerset",
    "sg:tags":[
        "pubs",
        "inn"
    ],
    "wof:name":"The Bull Inn",
    "wof:placetype":"venue"
},
  "geometry": {"coordinates":[-2.4524390697,51.1128845215],"type":"Point"}
}