{
  "type": "Feature",
  "properties": {
    "addr:full":"103 Lower Lickhill Road Stourport-on-severn Worcestershire DY13 8UQ",
    "addr:housenumber":"103",
    "addr:postcode":"dy13 8uq",
    "addr:street":"Lower Lickhill Road",
    "iso:country":"GB",
    "sg:address":"103 Lower Lickhill Road",
    "sg:city":"Stourport-on-severn",
    "sg:classifiers":[
        {
            "category":"Shopping",
            "type":"Retail Goods"
        }
    ],
    "sg:phone":"+44 1299 877515",
    "sg:postcode":"DY13 8UQ",
    "sg:province":"Worcestershire",
    "sg:tags":[
        "part",
        "accessory"
    ],
    "wof:name":"Lickhill Car Spares",
    "wof:placetype":"venue"
},
  "geometry": {"coordinates":[-2.2923851013,52.3467216492],"type":"Point"}
}