{
  "type": "Feature",
  "properties": {
    "addr:full":"64 Gillinggate Kendal Cumbria LA9 4JB",
    "addr:housenumber":"64",
    "addr:postcode":"la9 4jb",
    "addr:street":"Gillinggate Kendal",
    "iso:country":"GB",
    "sg:address":"64 Gillinggate",
    "sg:city":"Kendal",
    "sg:classifiers":[
        {
            "category":"Professional",
            "subcategory":"Lawyer & Legal Services",
            "type":"Services"
        }
    ],
    "sg:phone":"+44 1539 725823",
    "sg:postcode":"LA9 4JB",
    "sg:province":"Cumbria",
    "wof:name":"Just Wills",
    "wof:placetype":"venue"
},
  "geometry": {"coordinates":[-2.750557,54.323387],"type":"Point"}
}