{
  "type": "Feature",
  "properties": {
    "addr:full":"176 Urban Road, Hexthorpe Doncaster South Yorkshire DN4 0EZ",
    "addr:housenumber":"176",
    "addr:postcode":"dn4 0ez",
    "addr:street":"Urban Road",
    "iso:country":"GB",
    "sg:address":"176 Urban Road, Hexthorpe",
    "sg:city":"Doncaster",
    "sg:classifiers":[
        {
            "category":"Home & Garden",
            "subcategory":"Household Appliances",
            "type":"Retail Goods"
        }
    ],
    "sg:phone":"+44 1302 811833",
    "sg:postcode":"DN4 0EZ",
    "sg:province":"South Yorkshire",
    "sg:tags":[
        "electrical"
    ],
    "wof:name":"Appliance Services",
    "wof:placetype":"venue"
},
  "geometry": {"coordinates":[-1.15366,53.514267],"type":"Point"}
}