{
  "type": "Feature",
  "properties": {
    "addr:full":"The Cloisters, Formby Liverpool Lancashire L37 3PX",
    "addr:postcode":"l37 3px",
    "iso:country":"GB",
    "sg:address":"The Cloisters, Formby",
    "sg:city":"Liverpool",
    "sg:classifiers":[
        {
            "category":"Community Center",
            "type":"Public Place"
        }
    ],
    "sg:phone":"+44 1704 872727",
    "sg:postcode":"L37 3PX",
    "sg:province":"Lancashire",
    "sg:tags":[
        "recreation",
        "leisure",
        "centre"
    ],
    "wof:name":"Victoria Leisure Formby",
    "wof:placetype":"venue"
},
  "geometry": {"coordinates":[-3.0604000092,53.5579795837],"type":"Point"}
}