{
  "type": "Feature",
  "properties": {
    "iso:country":"GB",
    "sg:address":"Landmark House, Cleveleys Avenue",
    "sg:city":"Thornton-cleveleys",
    "sg:classifiers":[
        {
            "category":"Real Estate",
            "subcategory":"Real Estate Agent",
            "type":"Services"
        }
    ],
    "sg:phone":"+44 1253 858222",
    "sg:postcode":"FY5 2UH",
    "sg:province":"Lancashire",
    "wof:name":"Noblett Walker",
    "wof:placetype":"venue"
},
  "geometry": {"coordinates":[-3.035789,53.888325],"type":"Point"}
}