{
  "type": "Feature",
  "properties": {
    "iso:country":"GB",
    "sg:address":"Unit 11, Penllyn Workshops",
    "sg:city":"Bala",
    "sg:classifiers":[
        {
            "category":"Shopping",
            "subcategory":"Books",
            "type":"Retail Goods"
        }
    ],
    "sg:postcode":"LL23 7SW",
    "sg:province":"Gwynedd",
    "wof:name":"Bloodaxe Books Ltd.",
    "wof:placetype":"venue"
},
  "geometry": {"coordinates":[-3.595467,52.912148],"type":"Point"}
}