{
  "type": "Feature",
  "properties": {
    "addr:full":"8 Woolwich Rd Greenwich Greater London SE10 0JU",
    "addr:housenumber":"8",
    "addr:postcode":"se10 0ju",
    "addr:street":"Woolwich Rd",
    "iso:country":"GB",
    "sg:address":"8 Woolwich Rd",
    "sg:city":"Greenwich",
    "sg:classifiers":[
        {
            "category":"Food & Beverages",
            "subcategory":"Candy",
            "type":"Retail Goods"
        }
    ],
    "sg:phone":"+44 20 8858 0578",
    "sg:postcode":"SE10 0JU",
    "sg:province":"Greater London",
    "sg:tags":[
        "confectioner"
    ],
    "wof:name":"Sadikali S",
    "wof:placetype":"venue"
},
  "geometry": {"coordinates":[0.012754,51.486076],"type":"Point"}
}