{
  "type": "Feature",
  "properties": {
    "iso:country":"GB",
    "sg:address":"Higher Creason Farm, Peter Tavy",
    "sg:city":"Tavistock",
    "sg:classifiers":[
        {
            "category":"Farming",
            "subcategory":"Livestock Farm",
            "type":"Manufacturing & Wholesale Goods"
        }
    ],
    "sg:postcode":"PL19 9ND",
    "sg:province":"Devon",
    "sg:tags":[
        "others"
    ],
    "wof:name":"S G Palmer & Sons",
    "wof:placetype":"venue"
},
  "geometry": {"coordinates":[-4.100562,50.579411],"type":"Point"}
}