{
  "type": "Feature",
  "properties": {
    "addr:full":"Tor Road, Springfield Newquay Cornwall TR7 1RL",
    "addr:postcode":"tr7 1rl",
    "addr:street":"Tor Road",
    "iso:country":"GB",
    "sg:address":"Tor Road, Springfield",
    "sg:city":"Newquay",
    "sg:classifiers":[
        {
            "category":"Manufacturing",
            "subcategory":"Metals",
            "type":"Manufacturing & Wholesale Goods"
        }
    ],
    "sg:postcode":"TR7 1RL",
    "sg:province":"Cornwall",
    "wof:name":"Newquay Electro-Plating",
    "wof:placetype":"venue"
},
  "geometry": {"coordinates":[-5.0778989792,50.4134941101],"type":"Point"}
}