{
  "type": "Feature",
  "properties": {
    "addr:full":"2 Romney Close, Brightlingsea Colchester Essex CO7 0RJ",
    "addr:housenumber":"2",
    "addr:postcode":"co7 0rj",
    "addr:street":"Romney Close",
    "iso:country":"GB",
    "sg:address":"2 Romney Close, Brightlingsea",
    "sg:city":"Colchester",
    "sg:classifiers":[
        {
            "category":"Retail",
            "subcategory":"Repair Shop",
            "type":"Services"
        }
    ],
    "sg:phone":"+44 1206 303249",
    "sg:postcode":"CO7 0RJ",
    "sg:province":"Essex",
    "sg:tags":[
        "upholsterer"
    ],
    "wof:name":"Christopher J Tatum Upholsterer",
    "wof:placetype":"venue"
},
  "geometry": {"coordinates":[1.020846,51.822639],"type":"Point"}
}