{
  "type": "Feature",
  "properties": {
    "addr:full":"40/15 Hardengreen Bus. Pk, Dalhousie Rd Dalkeith City of Edinburgh EH22 3NX",
    "addr:housenumber":"40 / 15",
    "addr:postcode":"eh22 3nx",
    "addr:street":"Hardengreen Bus. Pk Dalhousie Rd",
    "iso:country":"GB",
    "sg:address":"40/15 Hardengreen Bus. Pk, Dalhousie Rd",
    "sg:city":"Dalkeith",
    "sg:classifiers":[
        {
            "category":"Professional",
            "subcategory":"Business Services",
            "type":"Services"
        }
    ],
    "sg:postcode":"EH22 3NX",
    "sg:province":"City of Edinburgh",
    "sg:tags":[
        "shop",
        "cleaning"
    ],
    "wof:name":"Manhattan Cleaning Services Ltd",
    "wof:placetype":"venue"
},
  "geometry": {"coordinates":[-3.0835690498,55.8837165833],"type":"Point"}
}