{
  "type": "Feature",
  "properties": {
    "addr:full":"25 Parkfield Road Oakham Leicestershire LE15 6PE",
    "addr:housenumber":"25",
    "addr:postcode":"le15 6pe",
    "addr:street":"Parkfield Road",
    "iso:country":"GB",
    "sg:address":"25 Parkfield Road",
    "sg:city":"Oakham",
    "sg:classifiers":[
        {
            "category":"Home & Garden",
            "subcategory":"Building Materials",
            "type":"Retail Goods"
        }
    ],
    "sg:phone":"+44 1572 722540",
    "sg:postcode":"LE15 6PE",
    "sg:province":"Leicestershire",
    "sg:tags":[
        "gate",
        "door",
        "barrier"
    ],
    "wof:name":"Timber Creations",
    "wof:placetype":"venue"
},
  "geometry": {"coordinates":[-0.740096,52.671917],"type":"Point"}
}