{
  "type": "Feature",
  "properties": {
    "iso:country":"GB",
    "sg:address":"93 Lindsay Park",
    "sg:city":"Burnley",
    "sg:classifiers":[
        {
            "category":"Health Services",
            "subcategory":"Dentist",
            "type":"Services"
        }
    ],
    "sg:phone":"+44 1282 458340",
    "sg:postcode":"BB10 3SQ",
    "sg:province":"Lancashire",
    "wof:name":"J P C Bate",
    "wof:placetype":"venue"
},
  "geometry": {"coordinates":[-2.197619915,53.7899627686],"type":"Point"}
}