{
  "type": "Feature",
  "properties": {
    "addr:full":"93 Brighton St Wallasey Merseyside CH44 6QL",
    "addr:housenumber":"93",
    "addr:postcode":"ch44 6ql",
    "addr:street":"Brighton St",
    "iso:country":"GB",
    "sg:address":"93 Brighton St",
    "sg:city":"Wallasey",
    "sg:classifiers":[
        {
            "category":"Food & Beverages",
            "subcategory":"Liquor & Beverages",
            "type":"Retail Goods"
        }
    ],
    "sg:phone":"+44 151 638 1092",
    "sg:postcode":"CH44 6QL",
    "sg:province":"Merseyside",
    "sg:tags":[
        "beer",
        "spirit",
        "wines"
    ],
    "wof:name":"Off Licence",
    "wof:placetype":"venue"
},
  "geometry": {"coordinates":[-3.0226249695,53.4142379761],"type":"Point"}
}