{
  "type": "Feature",
  "properties": {
    "addr:full":"14 Worcester Court, Mannesman Close, Enterprise Park, Llansamlet Swansea Neath Port Talbot SA7 9AH",
    "addr:housenumber":"14",
    "addr:postcode":"sa7 9ah",
    "addr:street":"Worcester Court Mannesman Close Enterprise Park",
    "iso:country":"GB",
    "sg:address":"14 Worcester Court, Mannesman Close, Enterprise Park, Llansamlet",
    "sg:city":"Swansea",
    "sg:classifiers":[
        {
            "category":"Home & Garden",
            "subcategory":"Furniture",
            "type":"Retail Goods"
        }
    ],
    "sg:phone":"+44 1792 793397",
    "sg:postcode":"SA7 9AH",
    "sg:province":"Neath Port Talbot",
    "wof:name":"The Pine Factory",
    "wof:placetype":"venue"
},
  "geometry": {"coordinates":[-3.9049789906,51.6587181091],"type":"Point"}
}