{
  "type": "Feature",
  "properties": {
    "addr:full":"124a Lower Dock St Newport East Riding of Yorkshire NP9 1EG",
    "addr:housenumber":"124a",
    "addr:postcode":"np9 1eg",
    "addr:street":"Lower Dock St",
    "iso:country":"GB",
    "sg:address":"124a Lower Dock St",
    "sg:city":"Newport",
    "sg:classifiers":[
        {
            "category":"Home & Garden",
            "subcategory":"Home Furnishings",
            "type":"Retail Goods"
        }
    ],
    "sg:postcode":"NP9 1EG",
    "sg:province":"East Riding of Yorkshire",
    "sg:tags":[
        "beds",
        "bedding",
        "blanket"
    ],
    "wof:name":"West Coast Waterbeds Ltd",
    "wof:placetype":"venue"
},
  "geometry": {"coordinates":[-2.9901928902,51.5832862854],"type":"Point"}
}