{
  "type": "Feature",
  "properties": {
    "addr:full":"Backwell Hill Ho, Off Chelby Batch Bristol Somerset BS48 3DA",
    "addr:postcode":"bs48 3da",
    "addr:street":"Backwell Hill;Off Chelby Batch",
    "iso:country":"GB",
    "sg:address":"Backwell Hill Ho, Off Chelby Batch",
    "sg:city":"Bristol",
    "sg:classifiers":[
        {
            "category":"Professional",
            "type":"Services"
        }
    ],
    "sg:phone":"+44 1275 463695",
    "sg:postcode":"BS48 3DA",
    "sg:province":"Somerset",
    "sg:tags":[
        "caterer"
    ],
    "wof:name":"Clifton Caterers",
    "wof:placetype":"venue"
},
  "geometry": {"coordinates":[-2.724124,51.419338],"type":"Point"}
}