{
  "type": "Feature",
  "properties": {
    "addr:full":"4 The Rhiw Centre Bridgend Bridgend CF31 1JJ",
    "addr:housenumber":"4",
    "addr:postcode":"cf31 1jj",
    "addr:street":"The Rhiw Centre",
    "iso:country":"GB",
    "sg:address":"4 The Rhiw Centre",
    "sg:city":"Bridgend",
    "sg:classifiers":[
        {
            "category":"Shopping",
            "subcategory":"Shoes",
            "type":"Retail Goods"
        }
    ],
    "sg:phone":"+44 1656 668706",
    "sg:postcode":"CF31 1JJ",
    "sg:province":"Bridgend",
    "sg:tags":[
        "shop"
    ],
    "wof:name":"Shoe Express",
    "wof:placetype":"venue"
},
  "geometry": {"coordinates":[-3.568896,51.504807],"type":"Point"}
}