{
  "type": "Feature",
  "properties": {
    "iso:country":"GB",
    "sg:address":"Miall Street Mills, Miall Street, Pellon",
    "sg:city":"Halifax",
    "sg:classifiers":[
        {
            "category":"Shopping",
            "subcategory":"Used Merchandise",
            "type":"Retail Goods"
        }
    ],
    "sg:postcode":"HX1 4RE",
    "sg:province":"West Yorkshire",
    "sg:tags":[
        "shop",
        "second-hand"
    ],
    "wof:name":"Halifax Sell It Centre",
    "wof:placetype":"venue"
},
  "geometry": {"coordinates":[-1.879494,53.727695],"type":"Point"}
}