{
  "type": "Feature",
  "properties": {
    "addr:full":"Home Farm, Warrington Olney Buckinghamshire MK46 4HN",
    "addr:postcode":"mk46 4hn",
    "iso:country":"GB",
    "sg:address":"Home Farm, Warrington",
    "sg:city":"Olney",
    "sg:classifiers":[
        {
            "category":"Travel",
            "subcategory":"Hotels & Motels",
            "type":"Entertainment"
        },
        {
            "category":"Bars & Pubs",
            "subcategory":"Hookah Bar",
            "type":"Food & Drink"
        }
    ],
    "sg:phone":"+44 1234 711655",
    "sg:postcode":"MK46 4HN",
    "sg:province":"Buckinghamshire",
    "sg:tags":[
        "self",
        "holiday",
        "catering"
    ],
    "wof:name":"The Old Stone Barn",
    "wof:placetype":"venue"
},
  "geometry": {"coordinates":[-0.701843977,52.1534690857],"type":"Point"}
}