{
  "type": "Feature",
  "properties": {
    "iso:country":"GB",
    "sg:address":"Unit 10, Acre Ridge Estatesalcombe Road M",
    "sg:city":"Alfreton",
    "sg:classifiers":[
        {
            "category":"Government",
            "subcategory":"Post Office",
            "type":"Public Place"
        }
    ],
    "sg:phone":"+44 1773 521621",
    "sg:postcode":"DE55 7RG",
    "sg:province":"Derbyshire",
    "sg:tags":[
        "messenger",
        "courier"
    ],
    "wof:name":"Interlink",
    "wof:placetype":"venue"
},
  "geometry": {"coordinates":[-1.3730540276,53.1014480591],"type":"Point"}
}