{
  "type": "Feature",
  "properties": {
    "addr:full":"Castle Road East Oldbury West Midlands B68 9BG",
    "addr:postcode":"b68 9bg",
    "addr:street":"Castle Road East Oldbury",
    "iso:country":"GB",
    "sg:address":"Castle Road East",
    "sg:city":"Oldbury",
    "sg:classifiers":[
        {
            "category":"Education",
            "subcategory":"School",
            "type":"Public Place"
        }
    ],
    "sg:phone":"+44 121 429 2542",
    "sg:postcode":"B68 9BG",
    "sg:province":"West Midlands",
    "sg:tags":[
        "local",
        "authority"
    ],
    "wof:name":"Sandwell Metropolitan Borough Council",
    "wof:placetype":"venue"
},
  "geometry": {"coordinates":[-1.9873000383,52.469078064],"type":"Point"}
}