{
  "type": "Feature",
  "properties": {
    "addr:full":"1 Dunlop Road Dereham Norfolk NR19 2XL",
    "addr:housenumber":"1",
    "addr:postcode":"nr19 2xl",
    "addr:street":"Dunlop Road",
    "iso:country":"GB",
    "sg:address":"1 Dunlop Road",
    "sg:city":"Dereham",
    "sg:classifiers":[
        {
            "category":"Building & Trades",
            "subcategory":"Construction",
            "type":"Services"
        }
    ],
    "sg:postcode":"NR19 2XL",
    "sg:province":"Norfolk",
    "sg:tags":[
        "decorator",
        "painter"
    ],
    "wof:name":"Clifford Hugh Green",
    "wof:placetype":"venue"
},
  "geometry": {"coordinates":[0.9290400147,52.6859169006],"type":"Point"}
}