{
  "type": "Feature",
  "properties": {
    "iso:country":"GB",
    "sg:address":"1 North Parade, Yate",
    "sg:city":"Bristol",
    "sg:classifiers":[
        {
            "category":"Banks & Credit Unions",
            "subcategory":"Bank",
            "type":"Services"
        }
    ],
    "sg:phone":"+44 1454 322510",
    "sg:postcode":"BS37 4XD",
    "sg:province":"Gloucestershire",
    "wof:name":"Lloyds Tsb Bank Plc",
    "wof:placetype":"venue"
},
  "geometry": {"coordinates":[-2.409615,51.5392],"type":"Point"}
}