{
  "type": "Feature",
  "properties": {
    "addr:full":"36 Queen Street Deal Kent CT14 6EY",
    "addr:housenumber":"36",
    "addr:postcode":"ct14 6ey",
    "addr:street":"Queen Street Deal",
    "iso:country":"GB",
    "sg:address":"36 Queen Street",
    "sg:city":"Deal",
    "sg:classifiers":[
        {
            "category":"Cinema",
            "subcategory":"Movie Theater",
            "type":"Entertainment"
        }
    ],
    "sg:phone":"+44 1304 361165",
    "sg:postcode":"CT14 6EY",
    "sg:province":"Kent",
    "wof:name":"Flicks Cinema",
    "wof:placetype":"venue"
},
  "geometry": {"coordinates":[1.4010390043,51.2230072021],"type":"Point"}
}