{
  "type": "Feature",
  "properties": {
    "addr:full":"80 Manor Road Lancing West Sussex BN15 0HD",
    "addr:housenumber":"80",
    "addr:postcode":"bn15 0hd",
    "addr:street":"Manor Road",
    "iso:country":"GB",
    "sg:address":"80 Manor Road",
    "sg:city":"Lancing",
    "sg:classifiers":[
        {
            "category":"Shopping",
            "subcategory":"Discount & Variety Stores",
            "type":"Retail Goods"
        }
    ],
    "sg:phone":"+44 1903 754850",
    "sg:postcode":"BN15 0HD",
    "sg:province":"West Sussex",
    "sg:tags":[
        "shop",
        "model"
    ],
    "wof:name":"J Morris",
    "wof:placetype":"venue"
},
  "geometry": {"coordinates":[-0.327278,50.837517],"type":"Point"}
}