{
  "type": "Feature",
  "properties": {
    "addr:full":"6 Ingswell Avenue, Notton Wakefield West Yorkshire WF4 2NG",
    "addr:housenumber":"6",
    "addr:postcode":"wf4 2ng",
    "addr:street":"Ingswell Avenue;West",
    "iso:country":"GB",
    "sg:address":"6 Ingswell Avenue, Notton",
    "sg:city":"Wakefield",
    "sg:classifiers":[
        {
            "category":"Professional",
            "subcategory":"Computer Services",
            "type":"Services"
        }
    ],
    "sg:phone":"+44 1226 722873",
    "sg:postcode":"WF4 2NG",
    "sg:province":"West Yorkshire",
    "sg:tags":[
        "consultant"
    ],
    "wof:name":"On-With-It Ltd.",
    "wof:placetype":"venue"
},
  "geometry": {"coordinates":[-1.4719949961,53.6137657166],"type":"Point"}
}