{
  "type": "Feature",
  "properties": {
    "addr:full":"81 Faulkeners Way, Trimley St Mary Felixstowe Suffolk IP11 0FE",
    "addr:housenumber":"81",
    "addr:postcode":"ip11 0fe",
    "addr:street":"Faulkeners Way",
    "iso:country":"GB",
    "sg:address":"81 Faulkeners Way, Trimley St Mary",
    "sg:city":"Felixstowe",
    "sg:classifiers":[
        {
            "category":"Shopping",
            "subcategory":"News",
            "type":"Retail Goods"
        }
    ],
    "sg:phone":"+44 1394 271188",
    "sg:postcode":"IP11 0FE",
    "sg:province":"Suffolk",
    "sg:tags":[
        "newsagent"
    ],
    "wof:name":"Farmlands Papershop",
    "wof:placetype":"venue"
},
  "geometry": {"coordinates":[1.322457,51.980984],"type":"Point"}
}