{
  "type": "Feature",
  "properties": {
    "addr:full":"31 Headley Road Liphook Hampshire GU30 7NS",
    "addr:housenumber":"31",
    "addr:postcode":"gu30 7ns",
    "addr:street":"Headley Road",
    "iso:country":"GB",
    "sg:address":"31 Headley Road",
    "sg:city":"Liphook",
    "sg:classifiers":[
        {
            "category":"Professional",
            "subcategory":"Secretarial Services",
            "type":"Services"
        }
    ],
    "sg:postcode":"GU30 7NS",
    "sg:province":"Hampshire",
    "wof:name":"Byword",
    "wof:placetype":"venue"
},
  "geometry": {"coordinates":[-0.8043609858,51.0789222717],"type":"Point"}
}