{
  "type": "Feature",
  "properties": {
    "addr:full":"Christchurch Lane, Little Drayton Market Drayton Shropshire TF9 1DZ",
    "addr:postcode":"tf9 1dz",
    "addr:street":"Christchurch Lane",
    "iso:country":"GB",
    "sg:address":"Christchurch Lane, Little Drayton",
    "sg:city":"Market Drayton",
    "sg:classifiers":[
        {
            "category":"Manufacturing",
            "subcategory":"Petroleum Products",
            "type":"Manufacturing & Wholesale Goods"
        },
        {
            "category":"Building & Trades",
            "subcategory":"Construction",
            "type":"Services"
        }
    ],
    "sg:phone":"+44 1630 655717",
    "sg:postcode":"TF9 1DZ",
    "sg:province":"Shropshire",
    "sg:tags":[
        "double",
        "glazing",
        "installers"
    ],
    "sg:website":"http://www.focus-annex-solutions.co.uk",
    "wof:name":"Focus Windows Fascias Cladding Soffits",
    "wof:placetype":"venue"
},
  "geometry": {"coordinates":[-2.5015540123,52.8990631104],"type":"Point"}
}