{
  "type": "Feature",
  "properties": {
    "iso:country":"GB",
    "sg:address":"658 Stannington Road",
    "sg:city":"Sheffield",
    "sg:classifiers":[
        {
            "category":"Home & Garden",
            "subcategory":"Hardware",
            "type":"Retail Goods"
        }
    ],
    "sg:phone":"+44 114 234 0241",
    "sg:postcode":"S6 6AE",
    "sg:province":"South Yorkshire",
    "wof:name":"Stannington Hardware",
    "wof:placetype":"venue"
},
  "geometry": {"coordinates":[-1.54137,53.39397],"type":"Point"}
}