{
  "type": "Feature",
  "properties": {
    "iso:country":"GB",
    "sg:address":"Unit 10, Mill House Works",
    "sg:city":"Sowerby Bridge",
    "sg:classifiers":[
        {
            "category":"Home & Garden",
            "subcategory":"Hardware",
            "type":"Retail Goods"
        }
    ],
    "sg:phone":"+44 1422 839957",
    "sg:postcode":"HX6 3LN",
    "sg:province":"West Yorkshire",
    "sg:tags":[
        "retailer",
        "lighting"
    ],
    "wof:name":"Direct House Supplies",
    "wof:placetype":"venue"
},
  "geometry": {"coordinates":[-1.8998320103,53.709312439],"type":"Point"}
}