{
  "type": "Feature",
  "properties": {
    "addr:full":"Bellows Road Shopping Centre, Rawmarsh Rotherham South Yorkshire S62 6NG",
    "addr:postcode":"s62 6ng",
    "addr:street":"Bellows",
    "iso:country":"GB",
    "sg:address":"Bellows Road Shopping Centre, Rawmarsh",
    "sg:city":"Rotherham",
    "sg:classifiers":[
        {
            "category":"Restaurant",
            "type":"Food & Drink"
        }
    ],
    "sg:phone":"+44 1709 527084",
    "sg:postcode":"S62 6NG",
    "sg:province":"South Yorkshire",
    "sg:tags":[
        "indian"
    ],
    "wof:name":"Mughal Curry Centre",
    "wof:placetype":"venue"
},
  "geometry": {"coordinates":[-1.344042,53.459492],"type":"Point"}
}