{
  "type": "Feature",
  "properties": {
    "iso:country":"GB",
    "sg:address":"12 Amber Business Village, Amber Close",
    "sg:city":"Tamworth",
    "sg:classifiers":[
        {
            "category":"Wholesale",
            "subcategory":"Vending Machines",
            "type":"Manufacturing & Wholesale Goods"
        }
    ],
    "sg:phone":"+44 1827 67733",
    "sg:postcode":"B77 4RP",
    "sg:province":"Staffordshire",
    "sg:tags":[
        "rental",
        "sale",
        "supply"
    ],
    "sg:website":"http://www.avs-uk.co.uk",
    "wof:name":"Associated Vending Services Ltd",
    "wof:placetype":"venue"
},
  "geometry": {"coordinates":[-1.64893,52.62656],"type":"Point"}
}