{
  "type": "Feature",
  "properties": {
    "addr:full":"9 Bream Road Lydney Gloucestershire GL15 5HP",
    "addr:housenumber":"9",
    "addr:postcode":"gl15 5hp",
    "addr:street":"Bream Road",
    "iso:country":"GB",
    "sg:address":"9 Bream Road",
    "sg:city":"Lydney",
    "sg:classifiers":[
        {
            "category":"Farming",
            "subcategory":"Nursery",
            "type":"Manufacturing & Wholesale Goods"
        },
        {
            "category":"Government",
            "subcategory":"Office",
            "type":"Public Place"
        }
    ],
    "sg:postcode":"GL15 5HP",
    "sg:province":"Gloucestershire",
    "sg:tags":[
        "creche",
        "agency",
        "education",
        "authority"
    ],
    "wof:name":"Headlands Day Nursery",
    "wof:placetype":"venue"
},
  "geometry": {"coordinates":[-2.534831,51.725624],"type":"Point"}
}