{
  "type": "Feature",
  "properties": {
    "iso:country":"GB",
    "sg:address":"134 Eastend Road",
    "sg:city":"London",
    "sg:classifiers":[
        {
            "category":"Food & Beverages",
            "subcategory":"Meat & Fish",
            "type":"Retail Goods"
        }
    ],
    "sg:phone":"+44 20 8883 6187",
    "sg:postcode":"N2 0RZ",
    "sg:province":"Greater London",
    "sg:tags":[
        "butcher"
    ],
    "wof:name":"Grahams",
    "wof:placetype":"venue"
},
  "geometry": {"coordinates":[-0.180379,51.592331],"type":"Point"}
}