{
  "type": "Feature",
  "properties": {
    "iso:country":"GB",
    "sg:address":"Meat Inspectors Office, 79-83 Charterhouse St",
    "sg:city":"Clerkenwell",
    "sg:classifiers":[
        {
            "category":"Government",
            "subcategory":"Office",
            "type":"Public Place"
        }
    ],
    "sg:phone":"+44 20 7253 3254",
    "sg:postcode":"EC1M 6HJ",
    "sg:province":"Greater London",
    "sg:tags":[
        "local"
    ],
    "wof:name":"Corporation of London",
    "wof:placetype":"venue"
},
  "geometry": {"coordinates":[-0.10265,51.519489],"type":"Point"}
}