{
  "type": "Feature",
  "properties": {
    "addr:full":"Bryn Awell, Pen Y Ball Hill Holywell Denbighshire CH8 8LD",
    "addr:postcode":"ch8 8ld",
    "addr:street":"Hill",
    "iso:country":"GB",
    "sg:address":"Bryn Awell, Pen Y Ball Hill",
    "sg:city":"Holywell",
    "sg:classifiers":[
        {
            "category":"Real Estate",
            "subcategory":"Architect",
            "type":"Services"
        }
    ],
    "sg:postcode":"CH8 8LD",
    "sg:province":"Denbighshire",
    "wof:name":"Ashpark Engineering Services Ltd",
    "wof:placetype":"venue"
},
  "geometry": {"coordinates":[-3.201473,53.243526],"type":"Point"}
}