{
  "type": "Feature",
  "properties": {
    "addr:full":"96 High St Carshalton Surrey SM5 3AE",
    "addr:housenumber":"96",
    "addr:postcode":"sm5 3ae",
    "addr:street":"High St",
    "iso:country":"GB",
    "sg:address":"96 High St",
    "sg:city":"Carshalton",
    "sg:classifiers":[
        {
            "category":"Education",
            "subcategory":"Dance Studio",
            "type":"Public Place"
        }
    ],
    "sg:phone":"+44 20 8669 7022",
    "sg:postcode":"SM5 3AE",
    "sg:province":"Surrey",
    "sg:tags":[
        "toning"
    ],
    "wof:name":"Shapers Toning Tables",
    "wof:placetype":"venue"
},
  "geometry": {"coordinates":[-0.1596129984,51.3655319214],"type":"Point"}
}