{
  "type": "Feature",
  "properties": {
    "addr:full":"29 Ray St Heanor Derbyshire DE75 7GE",
    "addr:housenumber":"29",
    "addr:postcode":"de75 7ge",
    "addr:street":"Ray St",
    "iso:country":"GB",
    "sg:address":"29 Ray St",
    "sg:city":"Heanor",
    "sg:classifiers":[
        {
            "category":"Food & Beverages",
            "subcategory":"Liquor & Beverages",
            "type":"Retail Goods"
        }
    ],
    "sg:postcode":"DE75 7GE",
    "sg:province":"Derbyshire",
    "sg:tags":[
        "beer",
        "spirit",
        "wines"
    ],
    "wof:name":"Jenny Wrens",
    "wof:placetype":"venue"
},
  "geometry": {"coordinates":[-1.355781,53.013439],"type":"Point"}
}