{
  "type": "Feature",
  "properties": {
    "iso:country":"GB",
    "sg:address":"191 Roehampton Lane",
    "sg:city":"London",
    "sg:classifiers":[
        {
            "category":"Health Services",
            "subcategory":"Doctor",
            "type":"Services"
        }
    ],
    "sg:phone":"+44 20 8788 1188",
    "sg:postcode":"SW15 4HN",
    "sg:province":"Greater London",
    "sg:tags":[
        "practitioners"
    ],
    "wof:name":"Roehampton Lane Surgery",
    "wof:placetype":"venue"
},
  "geometry": {"coordinates":[-0.242898,51.451263],"type":"Point"}
}