{
  "type": "Feature",
  "properties": {
    "addr:full":"19 Meadow Gate Bourne Lincolnshire PE10 9EZ",
    "addr:housenumber":"19",
    "addr:postcode":"pe10 9ez",
    "addr:street":"Meadow Gate Bourne",
    "iso:country":"GB",
    "sg:address":"19 Meadow Gate",
    "sg:city":"Bourne",
    "sg:classifiers":[
        {
            "category":"Building & Trades",
            "subcategory":"Plumbing",
            "type":"Services"
        }
    ],
    "sg:phone":"+44 1778 394114",
    "sg:postcode":"PE10 9EZ",
    "sg:province":"Lincolnshire",
    "sg:tags":[
        "heating"
    ],
    "wof:name":"Sherwin R D",
    "wof:placetype":"venue"
},
  "geometry": {"coordinates":[-0.375656,52.770912],"type":"Point"}
}