{
  "type": "Feature",
  "properties": {
    "addr:full":"3 Rona Close Crawley West Sussex RH11 9DD",
    "addr:housenumber":"3",
    "addr:postcode":"rh11 9dd",
    "addr:street":"Rona Close",
    "iso:country":"GB",
    "sg:address":"3 Rona Close",
    "sg:city":"Crawley",
    "sg:classifiers":[
        {
            "category":"Home & Garden",
            "subcategory":"Carpets & Floor Coverings",
            "type":"Retail Goods"
        }
    ],
    "sg:phone":"+44 1293 549901",
    "sg:postcode":"RH11 9DD",
    "sg:province":"West Sussex",
    "sg:tags":[
        "carpets",
        "rug",
        "matting"
    ],
    "wof:name":"M A Flooring & Carpets",
    "wof:placetype":"venue"
},
  "geometry": {"coordinates":[-0.206042,51.103275],"type":"Point"}
}