{
  "type": "Feature",
  "properties": {
    "addr:full":"Tunstall Richmond North Yorkshire DL10 7QZ",
    "addr:postcode":"dl10 7qz",
    "addr:street":"Yorkshire",
    "iso:country":"GB",
    "sg:address":"Tunstall",
    "sg:city":"Richmond",
    "sg:classifiers":[
        {
            "category":"Retail",
            "subcategory":"Auto Repair",
            "type":"Services"
        }
    ],
    "sg:phone":"+44 1748 818216",
    "sg:postcode":"DL10 7QZ",
    "sg:province":"North Yorkshire",
    "sg:tags":[
        "modification",
        "garage"
    ],
    "wof:name":"Tunstall Garage",
    "wof:placetype":"venue"
},
  "geometry": {"coordinates":[-1.6676199436,54.3579368591],"type":"Point"}
}