{
  "type": "Feature",
  "properties": {
    "iso:country":"GB",
    "sg:address":"16 Harehills Lane",
    "sg:city":"Leeds",
    "sg:classifiers":[
        {
            "category":"Health Services",
            "subcategory":"Nursing And Care Facility",
            "type":"Services"
        }
    ],
    "sg:phone":"+44 113 262 2997",
    "sg:postcode":"LS7 4HD",
    "sg:province":"West Yorkshire",
    "sg:tags":[
        "home"
    ],
    "wof:name":"Oak Villa",
    "wof:placetype":"venue"
},
  "geometry": {"coordinates":[-1.527264,53.82254],"type":"Point"}
}