{
  "type": "Feature",
  "properties": {
    "addr:full":"Stanton Mill, Bath Lane Mansfield Nottinghamshire NG18 2BZ",
    "addr:postcode":"ng18 2bz",
    "addr:street":"Stanton Mill Bath Lane",
    "iso:country":"GB",
    "sg:address":"Stanton Mill, Bath Lane",
    "sg:city":"Mansfield",
    "sg:classifiers":[
        {
            "category":"Home & Garden",
            "subcategory":"Home Furnishings",
            "type":"Retail Goods"
        }
    ],
    "sg:phone":"+44 1623 643235",
    "sg:postcode":"NG18 2BZ",
    "sg:province":"Nottinghamshire",
    "sg:tags":[
        "tube",
        "fitting",
        "stockist"
    ],
    "wof:name":"Tubes Fittings Valves Ltd.",
    "wof:placetype":"venue"
},
  "geometry": {"coordinates":[-1.201743,53.144024],"type":"Point"}
}