{
  "type": "Feature",
  "properties": {
    "iso:country":"GB",
    "sg:address":"Church Lane",
    "sg:city":"Norwich",
    "sg:classifiers":[
        {
            "category":"Professional",
            "subcategory":"Accounting & Tax Preparation",
            "type":"Services"
        }
    ],
    "sg:postcode":"NR12 8SH",
    "sg:province":"Norfolk",
    "sg:tags":[
        "accountant"
    ],
    "wof:name":"Michael Pritchard & Co",
    "wof:placetype":"venue"
},
  "geometry": {"coordinates":[1.387575,52.714436],"type":"Point"}
}