{
  "type": "Feature",
  "properties": {
    "addr:full":"42 Mount Stewart Avenue Harrow Greater London HA3 0JU",
    "addr:housenumber":"42",
    "addr:postcode":"ha3 0ju",
    "addr:street":"Mount Stewart Avenue",
    "iso:country":"GB",
    "sg:address":"42 Mount Stewart Avenue",
    "sg:city":"Harrow",
    "sg:classifiers":[
        {
            "category":"Professional",
            "subcategory":"Computer Services",
            "type":"Services"
        }
    ],
    "sg:postcode":"HA3 0JU",
    "sg:province":"Greater London",
    "sg:tags":[
        "system",
        "software"
    ],
    "wof:name":"Simcon (Computer Systems) Ltd.",
    "wof:placetype":"venue"
},
  "geometry": {"coordinates":[-0.302797,51.577637],"type":"Point"}
}