{
  "type": "Feature",
  "properties": {
    "iso:country":"GB",
    "sg:address":"5 Oakham Way",
    "sg:city":"Solihull",
    "sg:classifiers":[
        {
            "category":"Retail",
            "subcategory":"Driving School",
            "type":"Services"
        }
    ],
    "sg:phone":"+44 121 742 3789",
    "sg:postcode":"B92 8ST",
    "sg:province":"West Midlands",
    "wof:name":"C W S Driving School",
    "wof:placetype":"venue"
},
  "geometry": {"coordinates":[-1.7882189751,52.4385108948],"type":"Point"}
}