{
  "type": "Feature",
  "properties": {
    "addr:full":"15 Dunstall Street Scunthorpe Lincolnshire DN15 6LD",
    "addr:housenumber":"15",
    "addr:postcode":"dn15 6ld",
    "addr:street":"Dunstall Street",
    "iso:country":"GB",
    "sg:address":"15 Dunstall Street",
    "sg:city":"Scunthorpe",
    "sg:classifiers":[
        {
            "category":"Personal",
            "subcategory":"Beauty Salon",
            "type":"Services"
        }
    ],
    "sg:phone":"+44 1724 270930",
    "sg:postcode":"DN15 6LD",
    "sg:province":"Lincolnshire",
    "wof:name":"Hayley's Beauty Spa",
    "wof:placetype":"venue"
},
  "geometry": {"coordinates":[-0.6526439786,53.5905532837],"type":"Point"}
}