{
  "type": "Feature",
  "properties": {
    "addr:full":"25 Princes Pavement Birkenhead Merseyside CH41 2XY",
    "addr:housenumber":"25",
    "addr:postcode":"ch41 2xy",
    "addr:street":"Princes Pavement",
    "iso:country":"GB",
    "sg:address":"25 Princes Pavement",
    "sg:city":"Birkenhead",
    "sg:classifiers":[
        {
            "category":"Personal",
            "subcategory":"Beauty Salon",
            "type":"Services"
        }
    ],
    "sg:postcode":"CH41 2XY",
    "sg:province":"Merseyside",
    "sg:tags":[
        "unisex",
        "hairdresser"
    ],
    "wof:name":"Hairlines",
    "wof:placetype":"venue"
},
  "geometry": {"coordinates":[-3.025489,53.392567],"type":"Point"}
}