{
  "type": "Feature",
  "properties": {
    "iso:country":"GB",
    "sg:address":"Windsor Rd",
    "sg:city":"Gravesend",
    "sg:classifiers":[
        {
            "category":"Social Services",
            "type":"Services"
        }
    ],
    "sg:phone":"+44 1474 333178",
    "sg:postcode":"DA12 5BW",
    "sg:province":"Kent",
    "wof:name":"Kings Farm Centre",
    "wof:placetype":"venue"
},
  "geometry": {"coordinates":[0.36957,51.419201],"type":"Point"}
}