{
  "type": "Feature",
  "properties": {
    "addr:full":"Fairholme, Bridgemarsh Lane, Althorne Chelmsford Essex CM3 6DQ",
    "addr:postcode":"cm3 6dq",
    "addr:street":"Bridgemarsh Lane",
    "iso:country":"GB",
    "sg:address":"Fairholme, Bridgemarsh Lane, Althorne",
    "sg:city":"Chelmsford",
    "sg:classifiers":[
        {
            "category":"Recreation",
            "subcategory":"Marina",
            "type":"Entertainment"
        }
    ],
    "sg:phone":"+44 1621 740414",
    "sg:postcode":"CM3 6DQ",
    "sg:province":"Essex",
    "sg:tags":[
        "activity"
    ],
    "wof:name":"Bridgmarsh Marine",
    "wof:placetype":"venue"
},
  "geometry": {"coordinates":[0.75297,51.646339],"type":"Point"}
}