{
  "type": "Feature",
  "properties": {
    "iso:country":"GB",
    "sg:address":"Springfields, School Road",
    "sg:city":"King's Lynn",
    "sg:classifiers":[
        {
            "category":"Home & Garden",
            "subcategory":"Garden Supply",
            "type":"Retail Goods"
        }
    ],
    "sg:phone":"+44 1945 880438",
    "sg:postcode":"PE34 4QZ",
    "sg:province":"Lincolnshire",
    "sg:tags":[
        "turfing"
    ],
    "wof:name":"Parkland Turf Supplies",
    "wof:placetype":"venue"
},
  "geometry": {"coordinates":[0.28677,52.694561],"type":"Point"}
}