{
  "type": "Feature",
  "properties": {
    "addr:full":"Royston Terrace Edinburgh City of Edinburgh EH3 5QP",
    "addr:postcode":"eh3 5qp",
    "addr:street":"Royston Terrace",
    "iso:country":"GB",
    "sg:address":"Royston Terrace",
    "sg:city":"Edinburgh",
    "sg:classifiers":[
        {
            "category":"Autos & Motor Vehicles",
            "subcategory":"Auto Supplies",
            "type":"Retail Goods"
        },
        {
            "category":"Retail",
            "subcategory":"Auto Repair",
            "type":"Services"
        }
    ],
    "sg:phone":"+44 131 552 4173",
    "sg:postcode":"EH3 5QP",
    "sg:province":"City of Edinburgh",
    "sg:tags":[
        "modification",
        "garage",
        "component"
    ],
    "wof:name":"T C Juner & Son",
    "wof:placetype":"venue"
},
  "geometry": {"coordinates":[-3.2075140476,55.9706039429],"type":"Point"}
}