{
  "type": "Feature",
  "properties": {
    "iso:country":"GB",
    "sg:address":"Dollaston, Crundale",
    "sg:city":"Haverfordwest",
    "sg:classifiers":[
        {
            "category":"Farming",
            "subcategory":"Livestock Farm",
            "type":"Manufacturing & Wholesale Goods"
        },
        {
            "category":"Farming",
            "subcategory":"Farm",
            "type":"Manufacturing & Wholesale Goods"
        }
    ],
    "sg:phone":"+44 1437 731359",
    "sg:postcode":"SA62 4EL",
    "sg:province":"Pembrokeshire",
    "sg:tags":[
        "mixed",
        "crop",
        "others"
    ],
    "wof:name":"J C Lewis",
    "wof:placetype":"venue"
},
  "geometry": {"coordinates":[-4.948219,51.824329],"type":"Point"}
}