{
  "type": "Feature",
  "properties": {
    "iso:country":"GB",
    "sg:address":"1-2 Coney Hill Parade",
    "sg:city":"Gloucester",
    "sg:classifiers":[
        {
            "category":"Food & Beverages",
            "subcategory":"Groceries & Convenience Stores",
            "type":"Retail Goods"
        }
    ],
    "sg:phone":"+44 1452 530550",
    "sg:postcode":"GL4 7QD",
    "sg:province":"Gloucestershire",
    "wof:name":"H & H Superstores",
    "wof:placetype":"venue"
},
  "geometry": {"coordinates":[-2.212999,51.852238],"type":"Point"}
}