{
  "type": "Feature",
  "properties": {
    "iso:country":"GB",
    "sg:address":"Unit 1, Hemlock Park",
    "sg:city":"Cannock",
    "sg:classifiers":[
        {
            "category":"Manufacturing",
            "subcategory":"Metals",
            "type":"Manufacturing & Wholesale Goods"
        }
    ],
    "sg:phone":"+44 1543 577757",
    "sg:postcode":"WS11 2GA",
    "sg:province":"Staffordshire",
    "sg:tags":[
        "fabricator",
        "aluminium",
        "mnfrs"
    ],
    "wof:name":"Douglas Commercial Fabrications Ltd.",
    "wof:placetype":"venue"
},
  "geometry": {"coordinates":[-1.995534,52.69838],"type":"Point"}
}