{
  "type": "Feature",
  "properties": {
    "addr:full":"13 Lune Street Preston Lancashire PR1 2JU",
    "addr:housenumber":"13",
    "addr:postcode":"pr1 2ju",
    "addr:street":"Lune Street",
    "iso:country":"GB",
    "sg:address":"13 Lune Street",
    "sg:city":"Preston",
    "sg:classifiers":[
        {
            "category":"Professional",
            "subcategory":"Lawyer & Legal Services",
            "type":"Services"
        }
    ],
    "sg:phone":"+44 1772 201761",
    "sg:postcode":"PR1 2JU",
    "sg:province":"Lancashire",
    "sg:tags":[
        "solicitor"
    ],
    "wof:name":"Gowling Seddon Taylor & Cooper",
    "wof:placetype":"venue"
},
  "geometry": {"coordinates":[-2.703372,53.758766],"type":"Point"}
}