{
  "type": "Feature",
  "properties": {
    "addr:full":"28 Marine Road Prestatyn Denbighshire LL19 7HD",
    "addr:housenumber":"28",
    "addr:postcode":"ll19 7hd",
    "addr:street":"Marine Road",
    "iso:country":"GB",
    "sg:address":"28 Marine Road",
    "sg:city":"Prestatyn",
    "sg:classifiers":[
        {
            "category":"Travel",
            "subcategory":"Hotels & Motels",
            "type":"Entertainment"
        }
    ],
    "sg:phone":"+44 1745 887359",
    "sg:postcode":"LL19 7HD",
    "sg:province":"Denbighshire",
    "sg:tags":[
        "house",
        "guest"
    ],
    "wof:name":"Roughsedge Guest House",
    "wof:placetype":"venue"
},
  "geometry": {"coordinates":[-3.404276,53.338215],"type":"Point"}
}