{
  "type": "Feature",
  "properties": {
    "iso:country":"GB",
    "sg:address":"Unit 2, 29 Market Street, Little Lever",
    "sg:city":"Bolton",
    "sg:classifiers":[
        {
            "category":"Fast Food",
            "type":"Food & Drink"
        }
    ],
    "sg:phone":"+44 1204 705712",
    "sg:postcode":"BL3 1HH",
    "sg:province":"Lancashire",
    "sg:tags":[
        "away",
        "take"
    ],
    "wof:name":"Jitar Indian Take Away",
    "wof:placetype":"venue"
},
  "geometry": {"coordinates":[-2.369917,53.561436],"type":"Point"}
}