{
  "type": "Feature",
  "properties": {
    "addr:full":"70 Dunsmore Road Walton-on-thames Surrey KT12 2LJ",
    "addr:housenumber":"70",
    "addr:postcode":"kt12 2lj",
    "addr:street":"Dunsmore Road",
    "iso:country":"GB",
    "sg:address":"70 Dunsmore Road",
    "sg:city":"Walton-on-thames",
    "sg:classifiers":[
        {
            "category":"Professional",
            "subcategory":"Art Services",
            "type":"Services"
        },
        {
            "category":"Building & Trades",
            "subcategory":"Construction",
            "type":"Services"
        }
    ],
    "sg:postcode":"KT12 2LJ",
    "sg:province":"Surrey",
    "sg:tags":[
        "decorator",
        "painter"
    ],
    "wof:name":"D W C COLLINGWOOD & SON",
    "wof:placetype":"venue"
},
  "geometry": {"coordinates":[-0.4131940007,51.3953094482],"type":"Point"}
}