{
  "type": "Feature",
  "properties": {
    "addr:full":"13 Millans Park Ambleside Cumbria LA22 9AG",
    "addr:housenumber":"13",
    "addr:postcode":"la22 9ag",
    "addr:street":"Millans Park Ambleside",
    "iso:country":"GB",
    "sg:address":"13 Millans Park",
    "sg:city":"Ambleside",
    "sg:classifiers":[
        {
            "category":"Professional",
            "subcategory":"Engineering",
            "type":"Services"
        },
        {
            "category":"Real Estate",
            "subcategory":"Architect",
            "type":"Services"
        }
    ],
    "sg:phone":"+44 1977 613447",
    "sg:postcode":"LA22 9AG",
    "sg:province":"Cumbria",
    "sg:tags":[
        "engineer",
        "structural"
    ],
    "wof:name":"GOODALL ASSOCIATES LTD",
    "wof:placetype":"venue"
},
  "geometry": {"coordinates":[-2.9642798901,54.4331321716],"type":"Point"}
}