{
  "type": "Feature",
  "properties": {
    "addr:full":"86 Alderway Mansfield Derbyshire NG20 8PT",
    "addr:housenumber":"86",
    "addr:postcode":"ng20 8pt",
    "addr:street":"Alderway Mansfield",
    "iso:country":"GB",
    "sg:address":"86 Alderway",
    "sg:city":"Mansfield",
    "sg:classifiers":[
        {
            "category":"Building & Trades",
            "subcategory":"Construction",
            "type":"Services"
        }
    ],
    "sg:postcode":"NG20 8PT",
    "sg:province":"Derbyshire",
    "sg:tags":[
        "builder"
    ],
    "wof:name":"Staniforth & Butler",
    "wof:placetype":"venue"
},
  "geometry": {"coordinates":[-1.217809,53.202969],"type":"Point"}
}