{
  "type": "Feature",
  "properties": {
    "iso:country":"GB",
    "sg:address":"Unit 16 Mole Business Park, Randalls Rd",
    "sg:city":"Leatherhead",
    "sg:classifiers":[
        {
            "category":"Utilities",
            "subcategory":"Refuse",
            "type":"Services"
        }
    ],
    "sg:phone":"+44 1372 361643",
    "sg:postcode":"KT22 7BA",
    "sg:province":"Surrey",
    "sg:tags":[
        "disposal",
        "waste"
    ],
    "wof:name":"Initail Medical Services",
    "wof:placetype":"venue"
},
  "geometry": {"coordinates":[-0.329419,51.29636],"type":"Point"}
}