{
  "type": "Feature",
  "properties": {
    "addr:full":"Oxford Street Bilston West Midlands WS10 0AA",
    "addr:postcode":"ws10 0aa",
    "addr:street":"Oxford Street",
    "iso:country":"GB",
    "sg:address":"Oxford Street",
    "sg:city":"Bilston",
    "sg:classifiers":[
        {
            "category":"Building & Trades",
            "subcategory":"Cleaning & Sanitation",
            "type":"Services"
        }
    ],
    "sg:phone":"+44 1902 679276",
    "sg:postcode":"WS10 0AA",
    "sg:province":"West Midlands",
    "sg:tags":[
        "blast"
    ],
    "wof:name":"Ultrablast",
    "wof:placetype":"venue"
},
  "geometry": {"coordinates":[-2.071945,52.565674],"type":"Point"}
}