{
  "type": "Feature",
  "properties": {
    "iso:country":"GB",
    "sg:address":"4 Ace Parade, Hook Road",
    "sg:city":"Chessington",
    "sg:classifiers":[
        {
            "category":"Restaurant",
            "type":"Food & Drink"
        }
    ],
    "sg:phone":"+44 20 8397 0708",
    "sg:postcode":"KT9 1DR",
    "sg:province":"Surrey",
    "sg:tags":[
        "mediterranean",
        "-"
    ],
    "wof:name":"The Seahorse",
    "wof:placetype":"venue"
},
  "geometry": {"coordinates":[-0.308645,51.361874],"type":"Point"}
}