{
  "type": "Feature",
  "properties": {
    "iso:country":"GB",
    "sg:address":"64 High Street",
    "sg:city":"Stone",
    "sg:classifiers":[
        {
            "category":"Professional",
            "subcategory":"Accounting & Tax Preparation",
            "type":"Services"
        }
    ],
    "sg:phone":"+44 1785 812659",
    "sg:postcode":"ST15 8AU",
    "sg:province":"Staffordshire",
    "sg:tags":[
        "accountant",
        "chartered"
    ],
    "wof:name":"Wintons Ltd.",
    "wof:placetype":"venue"
},
  "geometry": {"coordinates":[-2.1483440399,52.9030647278],"type":"Point"}
}