{
  "type": "Feature",
  "properties": {
    "iso:country":"GB",
    "sg:address":"16 Selbourne Square",
    "sg:city":"Godstone",
    "sg:classifiers":[
        {
            "category":"Bus Charters",
            "type":"Transportation"
        }
    ],
    "sg:phone":"+44 1883 743453",
    "sg:postcode":"RH9 8AT",
    "sg:province":"Surrey",
    "sg:tags":[
        "hire",
        "coach"
    ],
    "wof:name":"Grants of Godstone",
    "wof:placetype":"venue"
},
  "geometry": {"coordinates":[-0.062951,51.255199],"type":"Point"}
}