{
  "type": "Feature",
  "properties": {
    "addr:full":"5 Sunderland Road Durham Durham DH1 2LH",
    "addr:housenumber":"5",
    "addr:postcode":"dh1 2lh",
    "addr:street":"Sunderland Road",
    "iso:country":"GB",
    "sg:address":"5 Sunderland Road",
    "sg:city":"Durham",
    "sg:classifiers":[
        {
            "category":"Food & Beverages",
            "subcategory":"Fruits & Vegetables",
            "type":"Retail Goods"
        }
    ],
    "sg:postcode":"DH1 2LH",
    "sg:province":"Durham",
    "sg:tags":[
        "greengrocer"
    ],
    "wof:name":"Greenwells",
    "wof:placetype":"venue"
},
  "geometry": {"coordinates":[-1.5550210476,54.7791824341],"type":"Point"}
}