{
  "type": "Feature",
  "properties": {
    "iso:country":"GB",
    "sg:address":"2 The Cross, Lymm",
    "sg:city":"Warrington",
    "sg:classifiers":[
        {
            "category":"Shopping",
            "subcategory":"Stationery & Office Supplies",
            "type":"Retail Goods"
        }
    ],
    "sg:phone":"+44 1925 754976",
    "sg:postcode":"WA13 9HP",
    "sg:province":"Cheshire",
    "wof:name":"Linkwell Partnerships Ltd.",
    "wof:placetype":"venue"
},
  "geometry": {"coordinates":[-2.477437,53.381992],"type":"Point"}
}