{
  "type": "Feature",
  "properties": {
    "addr:full":"9 Downsview Cotts, Cooksbridge Lewes East Sussex BN8 4TA",
    "addr:housenumber":"9;cotts cooksbridge",
    "addr:postcode":"bn8 4ta",
    "addr:street":"Downsview",
    "iso:country":"GB",
    "sg:address":"9 Downsview Cotts, Cooksbridge",
    "sg:city":"Lewes",
    "sg:classifiers":[
        {
            "category":"Building & Trades",
            "subcategory":"Landscaping Services",
            "type":"Services"
        }
    ],
    "sg:phone":"+44 1273 473646",
    "sg:postcode":"BN8 4TA",
    "sg:province":"East Sussex",
    "sg:tags":[
        "gardening"
    ],
    "wof:name":"Homes in Bloom Ltd.",
    "wof:placetype":"venue"
},
  "geometry": {"coordinates":[-0.0168910008,50.9715652466],"type":"Point"}
}