{
  "type": "Feature",
  "properties": {
    "addr:full":"48 Rood Lane, Clowne Chesterfield Derbyshire S43 4BP",
    "addr:housenumber":"48",
    "addr:postcode":"s43 4bp",
    "addr:street":"Rood Lane",
    "iso:country":"GB",
    "sg:address":"48 Rood Lane, Clowne",
    "sg:city":"Chesterfield",
    "sg:classifiers":[
        {
            "category":"Retail",
            "subcategory":"Repair Shop",
            "type":"Services"
        }
    ],
    "sg:phone":"+44 1246 812200",
    "sg:postcode":"S43 4BP",
    "sg:province":"Derbyshire",
    "sg:tags":[
        "maintenance"
    ],
    "wof:name":"Kinsey Builders",
    "wof:placetype":"venue"
},
  "geometry": {"coordinates":[-1.2612689734,53.2707595825],"type":"Point"}
}