{
  "type": "Feature",
  "properties": {
    "addr:full":"A R D Business Park, Polo Grounds Pontypool Monmouthshire NP4 0TW",
    "addr:postcode":"np4 0tw",
    "addr:street":"A R D Business Park Polo",
    "iso:country":"GB",
    "sg:address":"A R D Business Park, Polo Grounds",
    "sg:city":"Pontypool",
    "sg:classifiers":[
        {
            "category":"Professional",
            "subcategory":"Engineering",
            "type":"Services"
        }
    ],
    "sg:phone":"+44 1495 755698",
    "sg:postcode":"NP4 0TW",
    "sg:province":"Monmouthshire",
    "sg:tags":[
        "contractor",
        "electrical",
        "engineer"
    ],
    "wof:name":"Strand Electrical Services",
    "wof:placetype":"venue"
},
  "geometry": {"coordinates":[-3.0431900024,51.703086853],"type":"Point"}
}