{
  "type": "Feature",
  "properties": {
    "iso:country":"GB",
    "sg:address":"The Lawns, Grosmont",
    "sg:city":"Abergavenny",
    "sg:classifiers":[
        {
            "category":"Farming",
            "subcategory":"Livestock Farm",
            "type":"Manufacturing & Wholesale Goods"
        }
    ],
    "sg:postcode":"NP7 8ES",
    "sg:province":"Herefordshire",
    "sg:tags":[
        "others"
    ],
    "wof:name":"J H Ferneyhough",
    "wof:placetype":"venue"
},
  "geometry": {"coordinates":[-2.868297,51.916309],"type":"Point"}
}