{
  "type": "Feature",
  "properties": {
    "iso:country":"GB",
    "sg:address":"50 Walsgrave Road",
    "sg:city":"Coventry",
    "sg:classifiers":[
        {
            "category":"Place Of Worship",
            "type":"Public Place"
        }
    ],
    "sg:phone":"+44 24 7663 6874",
    "sg:postcode":"CV2 4BG",
    "sg:province":"Warwickshire",
    "wof:name":"St Margaret Church",
    "wof:placetype":"venue"
},
  "geometry": {"coordinates":[-1.485688,52.410084],"type":"Point"}
}