{
  "type": "Feature",
  "properties": {
    "addr:full":"190 Plumstead High Street London Greater London SE18 1JH",
    "addr:housenumber":"190",
    "addr:postcode":"se18 1jh",
    "addr:street":"High Street",
    "iso:country":"GB",
    "sg:address":"190 Plumstead High Street",
    "sg:city":"London",
    "sg:classifiers":[
        {
            "category":"Autos & Motor Vehicles",
            "subcategory":"Fuel & Gas Station",
            "type":"Retail Goods"
        }
    ],
    "sg:phone":"+44 20 8854 0644",
    "sg:postcode":"SE18 1JH",
    "sg:province":"Greater London",
    "sg:tags":[
        "petrol",
        "filling"
    ],
    "wof:name":"Lakedale Service Station",
    "wof:placetype":"venue"
},
  "geometry": {"coordinates":[0.095208,51.486721],"type":"Point"}
}