{
  "type": "Feature",
  "properties": {
    "addr:full":"Unit 1, Mullacott Cross Industrial Estate Ilfracombe Devon EX34 8PL",
    "addr:housenumber":"unit 1",
    "addr:postcode":"ex34 8pl",
    "addr:street":"Mullacott Cross Industrial Estate",
    "iso:country":"GB",
    "sg:address":"Unit 1, Mullacott Cross Industrial Estate",
    "sg:city":"Ilfracombe",
    "sg:classifiers":[
        {
            "category":"Manufacturing",
            "subcategory":"Rubber & Plastics",
            "type":"Manufacturing & Wholesale Goods"
        }
    ],
    "sg:phone":"+44 1271 865100",
    "sg:postcode":"EX34 8PL",
    "sg:province":"Devon",
    "sg:tags":[
        "injection",
        "moulding"
    ],
    "wof:name":"J B D Plastics Ltd.",
    "wof:placetype":"venue"
},
  "geometry": {"coordinates":[-4.126199,51.178886],"type":"Point"}
}