{
  "type": "Feature",
  "properties": {
    "iso:country":"GB",
    "sg:address":"15 Harpitt Close, Willand",
    "sg:city":"Cullompton",
    "sg:classifiers":[
        {
            "category":"Home & Garden",
            "subcategory":"Home Furnishings",
            "type":"Retail Goods"
        }
    ],
    "sg:postcode":"EX15 2RX",
    "sg:province":"Devon",
    "sg:tags":[
        "furnishers",
        "planner",
        "kitchen"
    ],
    "wof:name":"B S C Installations",
    "wof:placetype":"venue"
},
  "geometry": {"coordinates":[-3.3754279613,50.8834838867],"type":"Point"}
}