{
  "type": "Feature",
  "properties": {
    "addr:full":"Barncluith Business Centre, Townhead Street Hamilton South Lanarkshire ML3 7DP",
    "addr:postcode":"ml3 7dp",
    "addr:street":"Townhead Street",
    "iso:country":"GB",
    "sg:address":"Barncluith Business Centre, Townhead Street",
    "sg:city":"Hamilton",
    "sg:classifiers":[
        {
            "category":"Government",
            "subcategory":"Office",
            "type":"Public Place"
        }
    ],
    "sg:phone":"+44 1698 426882",
    "sg:postcode":"ML3 7DP",
    "sg:province":"South Lanarkshire",
    "sg:tags":[
        "chamber",
        "commerce"
    ],
    "wof:name":"Hamilton & Clydesdale Chamber of Commerce",
    "wof:placetype":"venue"
},
  "geometry": {"coordinates":[-4.052891,55.777321],"type":"Point"}
}