{
  "type": "Feature",
  "properties": {
    "addr:full":"Craigview Ho, 50 Main St St Andrews Fife KY16 9SA",
    "addr:housenumber":"50",
    "addr:postcode":"ky16 9sa",
    "addr:street":"Main St",
    "iso:country":"GB",
    "sg:address":"Craigview Ho, 50 Main St",
    "sg:city":"St Andrews",
    "sg:classifiers":[
        {
            "category":"Bus Charters",
            "type":"Transportation"
        }
    ],
    "sg:phone":"+44 1334 850255",
    "sg:postcode":"KY16 9SA",
    "sg:province":"Fife",
    "sg:tags":[
        "hire",
        "coach"
    ],
    "wof:name":"North Fife Travel",
    "wof:placetype":"venue"
},
  "geometry": {"coordinates":[-2.796194,56.33931],"type":"Point"}
}