{
  "type": "Feature",
  "properties": {
    "addr:full":"32 Montrose Rd Harrow Greater London HA3 7DU",
    "addr:housenumber":"32",
    "addr:postcode":"ha3 7du",
    "addr:street":"Montrose Rd",
    "iso:country":"GB",
    "sg:address":"32 Montrose Rd",
    "sg:city":"Harrow",
    "sg:classifiers":[
        {
            "category":"Building & Trades",
            "subcategory":"Plumbing",
            "type":"Services"
        }
    ],
    "sg:phone":"+44 20 8427 8517",
    "sg:postcode":"HA3 7DU",
    "sg:province":"Greater London",
    "sg:tags":[
        "heating"
    ],
    "wof:name":"I D C S",
    "wof:placetype":"venue"
},
  "geometry": {"coordinates":[-0.333846,51.597904],"type":"Point"}
}