{
  "type": "Feature",
  "properties": {
    "iso:country":"GB",
    "sg:address":"561 Earlham Rd",
    "sg:city":"Norwich",
    "sg:classifiers":[
        {
            "category":"Health Services",
            "subcategory":"Dentist",
            "type":"Services"
        }
    ],
    "sg:postcode":"NR4 7TF",
    "sg:province":"Norfolk",
    "wof:name":"Goorwitch,M H,",
    "wof:placetype":"venue"
},
  "geometry": {"coordinates":[1.2486900091,52.628818512],"type":"Point"}
}