{
  "type": "Feature",
  "properties": {
    "addr:full":"Risings, Sandy Lane, Hartley Wintney Hook Berkshire RG27 8DN",
    "addr:postcode":"rg27 8dn",
    "addr:street":"Risings Sandy Lane",
    "iso:country":"GB",
    "sg:address":"Risings, Sandy Lane, Hartley Wintney",
    "sg:city":"Hook",
    "sg:classifiers":[
        {
            "category":"Organizations",
            "subcategory":"Non-profit Organization",
            "type":"Services"
        }
    ],
    "sg:phone":"+44 1252 845765",
    "sg:postcode":"RG27 8DN",
    "sg:province":"Berkshire",
    "sg:tags":[
        "organisation",
        "voluntary",
        "charity"
    ],
    "wof:name":"ASBAH Office",
    "wof:placetype":"venue"
},
  "geometry": {"coordinates":[-0.9007539749,51.3058280945],"type":"Point"}
}