{
  "type": "Feature",
  "properties": {
    "iso:country":"GB",
    "sg:address":"Field House Farm, Kettlesing",
    "sg:city":"Harrogate",
    "sg:classifiers":[
        {
            "category":"Farming",
            "subcategory":"Dairy Farm",
            "type":"Manufacturing & Wholesale Goods"
        }
    ],
    "sg:phone":"+44 1423 770423",
    "sg:postcode":"HG3 2LR",
    "sg:province":"North Yorkshire",
    "wof:name":"E & D Whiteoak & Son",
    "wof:placetype":"venue"
},
  "geometry": {"coordinates":[-1.654735,54.011986],"type":"Point"}
}