{
  "type": "Feature",
  "properties": {
    "iso:country":"GB",
    "sg:address":"117 Green Street",
    "sg:city":"London",
    "sg:classifiers":[
        {
            "category":"Shopping",
            "subcategory":"Clothing, Apparel, & Fashions",
            "type":"Retail Goods"
        }
    ],
    "sg:phone":"+44 20 8475 0037",
    "sg:postcode":"E7 8JF",
    "sg:province":"Greater London",
    "sg:tags":[
        "shop"
    ],
    "wof:name":"Khubsoorat-Uk Ltd.",
    "wof:placetype":"venue"
},
  "geometry": {"coordinates":[0.0323060006,51.5442962646],"type":"Point"}
}