{
  "type": "Feature",
  "properties": {
    "addr:full":"Ropewalk Lincoln Lincolnshire LN6 7DQ",
    "addr:postcode":"ln6 7dq",
    "addr:street":"Ropewalk Lincoln",
    "iso:country":"GB",
    "sg:address":"Ropewalk",
    "sg:city":"Lincoln",
    "sg:classifiers":[
        {
            "category":"Professional",
            "subcategory":"Business Services",
            "type":"Services"
        }
    ],
    "sg:postcode":"LN6 7DQ",
    "sg:province":"Lincolnshire",
    "sg:tags":[
        "holding"
    ],
    "wof:name":"Harrisons & Crosfield",
    "wof:placetype":"venue"
},
  "geometry": {"coordinates":[-0.547324,53.226315],"type":"Point"}
}