{
  "type": "Feature",
  "properties": {
    "addr:full":"64-66 East Avenue Hayes Greater London UB3 2HP",
    "addr:housenumber":"64-66",
    "addr:postcode":"ub3 2hp",
    "addr:street":"East Avenue",
    "iso:country":"GB",
    "sg:address":"64-66 East Avenue",
    "sg:city":"Hayes",
    "sg:classifiers":[
        {
            "category":"Autos & Motor Vehicles",
            "subcategory":"Auto Supplies",
            "type":"Retail Goods"
        }
    ],
    "sg:phone":"+44 20 8561 1200",
    "sg:postcode":"UB3 2HP",
    "sg:province":"Greater London",
    "sg:tags":[
        "tyre"
    ],
    "wof:name":"Total Tyre & Support Services Ltd.",
    "wof:placetype":"venue"
},
  "geometry": {"coordinates":[-0.416276,51.509174],"type":"Point"}
}