{
  "type": "Feature",
  "properties": {
    "addr:full":"239a Wimbledon Park Road London Greater London SW18 5RJ",
    "addr:housenumber":"239a",
    "addr:postcode":"sw18 5rj",
    "addr:street":"Wimbledon Park Road",
    "iso:country":"GB",
    "sg:address":"239a Wimbledon Park Road",
    "sg:city":"London",
    "sg:classifiers":[
        {
            "category":"Personal",
            "subcategory":"Beauty Salon",
            "type":"Services"
        }
    ],
    "sg:phone":"+44 20 8874 2291",
    "sg:postcode":"SW18 5RJ",
    "sg:province":"Greater London",
    "sg:tags":[
        "unisex",
        "hairdresser"
    ],
    "wof:name":"Richard Hairdressers",
    "wof:placetype":"venue"
},
  "geometry": {"coordinates":[-0.2060119957,51.444984436],"type":"Point"}
}