{
  "type": "Feature",
  "properties": {
    "addr:full":"352 High St Orpington Kent BR6 0NQ",
    "addr:housenumber":"352",
    "addr:postcode":"br6 0nq",
    "addr:street":"High St",
    "iso:country":"GB",
    "sg:address":"352 High St",
    "sg:city":"Orpington",
    "sg:classifiers":[
        {
            "category":"Real Estate",
            "subcategory":"Real Estate Agent",
            "type":"Services"
        }
    ],
    "sg:postcode":"BR6 0NQ",
    "sg:province":"Kent",
    "wof:name":"Bell & Bell",
    "wof:placetype":"venue"
},
  "geometry": {"coordinates":[0.09749,51.373268],"type":"Point"}
}