{
  "type": "Feature",
  "properties": {
    "addr:full":"Colbourne Close, Burscough Ormskirk Lancashire L40 4LB",
    "addr:postcode":"l40 4lb",
    "addr:street":"Colbourne Close",
    "iso:country":"GB",
    "sg:address":"Colbourne Close, Burscough",
    "sg:city":"Ormskirk",
    "sg:classifiers":[
        {
            "category":"Education",
            "subcategory":"School",
            "type":"Public Place"
        },
        {
            "category":"Government",
            "subcategory":"Office",
            "type":"Public Place"
        }
    ],
    "sg:phone":"+44 1704 895403",
    "sg:postcode":"L40 4LB",
    "sg:province":"Lancashire",
    "sg:tags":[
        "local",
        "authority"
    ],
    "wof:name":"Burscough County Primary School",
    "wof:placetype":"venue"
},
  "geometry": {"coordinates":[-2.839108,53.602024],"type":"Point"}
}