{
  "type": "Feature",
  "properties": {
    "iso:country":"GB",
    "sg:address":"Tennyson Ho, 159-163 Great Portland St",
    "sg:city":"West End",
    "sg:classifiers":[
        {
            "category":"Professional",
            "subcategory":"Business Services",
            "type":"Services"
        }
    ],
    "sg:phone":"+44 20 7631 5360",
    "sg:postcode":"W1N 5FD",
    "sg:province":"Hampshire",
    "sg:tags":[
        "trade"
    ],
    "wof:name":"British Association Of Clothing Machinery Manufacturers",
    "wof:placetype":"venue"
},
  "geometry": {"coordinates":[-0.13899,51.50758],"type":"Point"}
}