{
  "type": "Feature",
  "properties": {
    "iso:country":"GB",
    "sg:address":"Shrewley Common, Shrewley",
    "sg:city":"Warwick",
    "sg:classifiers":[
        {
            "category":"Bars & Pubs",
            "type":"Food & Drink"
        }
    ],
    "sg:phone":"+44 1926 842283",
    "sg:postcode":"CV35 7AY",
    "sg:province":"Warwickshire",
    "sg:tags":[
        "pubs",
        "inn"
    ],
    "wof:name":"The Durham Ox Inn",
    "wof:placetype":"venue"
},
  "geometry": {"coordinates":[-1.67228,52.305992],"type":"Point"}
}