{
  "type": "Feature",
  "properties": {
    "iso:country":"GB",
    "sg:address":"Hillcrest Mount, Rose",
    "sg:city":"Truro",
    "sg:classifiers":[
        {
            "category":"Professional",
            "subcategory":"Management & Consulting",
            "type":"Services"
        }
    ],
    "sg:postcode":"TR4 9PP",
    "sg:province":"Cornwall",
    "sg:tags":[
        "fire",
        "consultant",
        "protection"
    ],
    "wof:name":"Keith Gathercole",
    "wof:placetype":"venue"
},
  "geometry": {"coordinates":[-5.126889,50.350986],"type":"Point"}
}