{
  "type": "Feature",
  "properties": {
    "addr:full":"High Barn, Midgeley Lane Knaresborough North Yorkshire HG5 8NY",
    "addr:postcode":"hg5 8ny",
    "addr:street":"Midgeley Lane",
    "iso:country":"GB",
    "sg:address":"High Barn, Midgeley Lane",
    "sg:city":"Knaresborough",
    "sg:classifiers":[
        {
            "category":"Professional",
            "subcategory":"Management & Consulting",
            "type":"Services"
        }
    ],
    "sg:postcode":"HG5 8NY",
    "sg:province":"North Yorkshire",
    "sg:tags":[
        "project"
    ],
    "wof:name":"Encia Remediation Ltd.",
    "wof:placetype":"venue"
},
  "geometry": {"coordinates":[-1.466372,54.008289],"type":"Point"}
}