{
  "type": "Feature",
  "properties": {
    "addr:full":"Bromford Mills, 210 Bromford Lane, Erdington Birmingham West Midlands B24 8DL",
    "addr:housenumber":"210",
    "addr:postcode":"b24 8dl",
    "addr:street":"Bromford Lane",
    "iso:country":"GB",
    "sg:address":"Bromford Mills, 210 Bromford Lane, Erdington",
    "sg:city":"Birmingham",
    "sg:classifiers":[
        {
            "category":"Wholesale",
            "subcategory":"Groceries",
            "type":"Manufacturing & Wholesale Goods"
        }
    ],
    "sg:phone":"+44 121 327 6146",
    "sg:postcode":"B24 8DL",
    "sg:province":"West Midlands",
    "sg:tags":[
        "food",
        "supplier",
        "drink"
    ],
    "wof:name":"Sovereign Foodservice Ltd.",
    "wof:placetype":"venue"
},
  "geometry": {"coordinates":[-1.83356,52.510368],"type":"Point"}
}