{
  "type": "Feature",
  "properties": {
    "addr:full":"7a Market Street Crediton Devon EX17 2EE",
    "addr:housenumber":"7a",
    "addr:postcode":"ex17 2ee",
    "addr:street":"Market Street",
    "iso:country":"GB",
    "sg:address":"7a Market Street",
    "sg:city":"Crediton",
    "sg:classifiers":[
        {
            "category":"Professional",
            "subcategory":"Computer Services",
            "type":"Services"
        }
    ],
    "sg:phone":"+44 1363 774761",
    "sg:postcode":"EX17 2EE",
    "sg:province":"Devon",
    "sg:tags":[
        "system",
        "software"
    ],
    "wof:name":"Fred Oliver",
    "wof:placetype":"venue"
},
  "geometry": {"coordinates":[-3.658308,50.791286],"type":"Point"}
}