{
  "type": "Feature",
  "properties": {
    "addr:full":"41 Falcon Rd London Greater London SW11 2PH",
    "addr:housenumber":"41",
    "addr:postcode":"sw11 2ph",
    "addr:street":"Falcon Rd",
    "iso:country":"GB",
    "sg:address":"41 Falcon Rd",
    "sg:city":"London",
    "sg:classifiers":[
        {
            "category":"Fast Food",
            "type":"Food & Drink"
        }
    ],
    "sg:postcode":"SW11 2PH",
    "sg:province":"Greater London",
    "sg:tags":[
        "away",
        "take"
    ],
    "wof:name":"Chicken Delight",
    "wof:placetype":"venue"
},
  "geometry": {"coordinates":[-0.170941,51.46883],"type":"Point"}
}