{
  "type": "Feature",
  "properties": {
    "iso:country":"GB",
    "sg:address":"Wyevale Garden Centre, Paddock Wood",
    "sg:city":"Tonbridge",
    "sg:classifiers":[
        {
            "category":"Shopping",
            "subcategory":"Pets & Pet Supplies",
            "type":"Retail Goods"
        }
    ],
    "sg:phone":"+44 1892 834860",
    "sg:postcode":"TN12 6QJ",
    "sg:province":"Kent",
    "wof:name":"Jackswood Pet & Aquatic Centre",
    "wof:placetype":"venue"
},
  "geometry": {"coordinates":[0.393539995,51.1797027588],"type":"Point"}
}