{
  "type": "Feature",
  "properties": {
    "iso:country":"GB",
    "sg:address":"20 Blackfriars Rd",
    "sg:city":"Wisbech",
    "sg:classifiers":[
        {
            "category":"Health Services",
            "subcategory":"Clinic",
            "type":"Services"
        }
    ],
    "sg:phone":"+44 1945 584444",
    "sg:postcode":"PE13 1AT",
    "sg:province":"Cambridgeshire",
    "sg:tags":[
        "abuse",
        "drug"
    ],
    "wof:name":"Bridgegate Drug Advice Agency",
    "wof:placetype":"venue"
},
  "geometry": {"coordinates":[0.162829,52.665401],"type":"Point"}
}