{
  "type": "Feature",
  "properties": {
    "iso:country":"GB",
    "sg:address":"Queen Street",
    "sg:city":"Pontypool",
    "sg:classifiers":[
        {
            "category":"Sports & Exercise",
            "subcategory":"Tennis Court",
            "type":"Entertainment"
        }
    ],
    "sg:phone":"+44 1495 791321",
    "sg:postcode":"NP4 9NG",
    "sg:province":"Monmouthshire",
    "sg:tags":[
        "breakdown",
        "recovery"
    ],
    "wof:name":"Belle Vue Garage",
    "wof:placetype":"venue"
},
  "geometry": {"coordinates":[-3.045849,51.704475],"type":"Point"}
}