{
  "type": "Feature",
  "properties": {
    "iso:country":"GB",
    "sg:address":"80a-80b High Street",
    "sg:city":"Southwold",
    "sg:classifiers":[
        {
            "category":"Deli",
            "type":"Food & Drink"
        },
        {
            "category":"Food & Beverages",
            "subcategory":"Meat & Fish",
            "type":"Retail Goods"
        }
    ],
    "sg:phone":"+44 1502 722312",
    "sg:postcode":"IP18 6DP",
    "sg:province":"Suffolk",
    "sg:tags":[
        "delicatessen",
        "butcher"
    ],
    "wof:name":"The Black Olive",
    "wof:placetype":"venue"
},
  "geometry": {"coordinates":[1.678073,52.326878],"type":"Point"}
}