{
  "type": "Feature",
  "properties": {
    "iso:country":"GB",
    "sg:address":"2 Als Street",
    "sg:city":"Llanelli",
    "sg:classifiers":[
        {
            "category":"Building & Trades",
            "subcategory":"Construction",
            "type":"Services"
        }
    ],
    "sg:phone":"+44 1554 772326",
    "sg:postcode":"SA15 1SN",
    "sg:province":"Carmarthenshire",
    "sg:tags":[
        "monumental",
        "mason"
    ],
    "wof:name":"Thomas J Lloyd",
    "wof:placetype":"venue"
},
  "geometry": {"coordinates":[-4.157125,51.681908],"type":"Point"}
}