{
  "type": "Feature",
  "properties": {
    "iso:country":"GB",
    "sg:address":"17 The Grove, Bomere Heath",
    "sg:city":"Shrewsbury",
    "sg:classifiers":[
        {
            "category":"Building & Trades",
            "subcategory":"Construction",
            "type":"Services"
        }
    ],
    "sg:postcode":"SY4 3QW",
    "sg:province":"Shropshire",
    "sg:tags":[
        "decorator",
        "painter"
    ],
    "wof:name":"John Pryce",
    "wof:placetype":"venue"
},
  "geometry": {"coordinates":[-2.78371,52.772789],"type":"Point"}
}