{
  "type": "Feature",
  "properties": {
    "addr:full":"137 Harrison Road Leicester Leicestershire LE4 6NP",
    "addr:housenumber":"137",
    "addr:postcode":"le4 6np",
    "addr:street":"Harrison Road",
    "iso:country":"GB",
    "sg:address":"137 Harrison Road",
    "sg:city":"Leicester",
    "sg:classifiers":[
        {
            "category":"Shopping",
            "subcategory":"Clothing, Apparel, & Fashions",
            "type":"Retail Goods"
        }
    ],
    "sg:phone":"+44 116 268 2944",
    "sg:postcode":"LE4 6NP",
    "sg:province":"Leicestershire",
    "sg:tags":[
        "clothing",
        "fabric"
    ],
    "wof:name":"Vishal Fashions",
    "wof:placetype":"venue"
},
  "geometry": {"coordinates":[-1.115885973,52.6526641846],"type":"Point"}
}