{
  "type": "Feature",
  "properties": {
    "iso:country":"GB",
    "sg:address":"38 High Street",
    "sg:city":"Tenterden",
    "sg:classifiers":[
        {
            "category":"Shopping",
            "subcategory":"Photographic Equipment",
            "type":"Retail Goods"
        }
    ],
    "sg:postcode":"TN30 6AR",
    "sg:province":"Kent",
    "sg:tags":[
        "supply"
    ],
    "wof:name":"David Larkin",
    "wof:placetype":"venue"
},
  "geometry": {"coordinates":[0.6873300076,51.0683021545],"type":"Point"}
}