{
  "type": "Feature",
  "properties": {
    "iso:country":"GB",
    "sg:address":"36 Gainsborough Rd, Blackdam",
    "sg:city":"Basingstoke",
    "sg:classifiers":[
        {
            "category":"Building & Trades",
            "subcategory":"Construction",
            "type":"Services"
        }
    ],
    "sg:postcode":"RG21 3EG",
    "sg:province":"Hampshire",
    "sg:tags":[
        "decorator",
        "painter"
    ],
    "wof:name":"Hearne,Barry,",
    "wof:placetype":"venue"
},
  "geometry": {"coordinates":[-1.0769319534,51.2554321289],"type":"Point"}
}