{
  "type": "Feature",
  "properties": {
    "iso:country":"GB",
    "sg:address":"Unit 8 Wylds Road",
    "sg:city":"Bridgwater",
    "sg:classifiers":[
        {
            "category":"Recreation",
            "subcategory":"Go Karts",
            "type":"Entertainment"
        }
    ],
    "sg:phone":"+44 1278 431919",
    "sg:postcode":"TA6 4DH",
    "sg:province":"Somerset",
    "sg:tags":[
        "karting"
    ],
    "wof:name":"Karting World (South West) Ltd.",
    "wof:placetype":"venue"
},
  "geometry": {"coordinates":[-2.992689,51.139999],"type":"Point"}
}