{
  "type": "Feature",
  "properties": {
    "addr:full":"Dawson House, 128-130 Carshalton Road Sutton Surrey SM1 4TW",
    "addr:housenumber":"128-130",
    "addr:postcode":"sm1 4tw",
    "addr:street":"Carshalton Road",
    "iso:country":"GB",
    "sg:address":"Dawson House, 128-130 Carshalton Road",
    "sg:city":"Sutton",
    "sg:classifiers":[
        {
            "category":"Military Area",
            "subcategory":"Air Force Base",
            "type":"Public Place"
        },
        {
            "category":"Manufacturing",
            "subcategory":"Electronics",
            "type":"Manufacturing & Wholesale Goods"
        },
        {
            "category":"Building & Trades",
            "subcategory":"Construction",
            "type":"Services"
        },
        {
            "category":"Professional",
            "subcategory":"Computer Services",
            "type":"Services"
        }
    ],
    "sg:phone":"+44 20 8643 1126",
    "sg:postcode":"SM1 4TW",
    "sg:province":"Surrey",
    "sg:tags":[
        "manufacture",
        "mnfr",
        "management",
        "component",
        "system",
        "equipment",
        "traffic",
        "electronic",
        "software"
    ],
    "wof:name":"Semi Conductor Supplies International Ltd",
    "wof:placetype":"venue"
},
  "geometry": {"coordinates":[-0.185462,51.36248],"type":"Point"}
}