{
  "type": "Feature",
  "properties": {
    "addr:full":"Nunnery Depot, Woodbourn Road Sheffield South Yorkshire S9 3LS",
    "addr:postcode":"s9 3ls",
    "addr:street":"Woodbourn Road",
    "iso:country":"GB",
    "sg:address":"Nunnery Depot, Woodbourn Road",
    "sg:city":"Sheffield",
    "sg:classifiers":[
        {
            "category":"Bus Charters",
            "type":"Transportation"
        }
    ],
    "sg:phone":"+44 114 276 7575",
    "sg:postcode":"S9 3LS",
    "sg:province":"South Yorkshire",
    "sg:tags":[
        "coach"
    ],
    "wof:name":"South Yorkshire Supertram Ltd.",
    "wof:placetype":"venue"
},
  "geometry": {"coordinates":[-1.4406199455,53.3857307434],"type":"Point"}
}