{
  "type": "Feature",
  "properties": {
    "iso:country":"GB",
    "sg:address":"5-7 Market Row",
    "sg:city":"Saffron Walden",
    "sg:classifiers":[
        {
            "category":"Shopping",
            "subcategory":"Optician",
            "type":"Retail Goods"
        },
        {
            "category":"Health Services",
            "subcategory":"Optometrist",
            "type":"Services"
        }
    ],
    "sg:phone":"+44 1799 523655",
    "sg:postcode":"CB10 1HB",
    "sg:province":"Cambridgeshire",
    "sg:tags":[
        "opthalmic"
    ],
    "wof:name":"Walden Opticians",
    "wof:placetype":"venue"
},
  "geometry": {"coordinates":[0.2408179939,52.0232582092],"type":"Point"}
}