{
  "type": "Feature",
  "properties": {
    "addr:full":"Church Street, Chasetown Burntwood Staffordshire WS7 8QL",
    "addr:postcode":"ws7 8ql",
    "addr:street":"Church Street",
    "iso:country":"GB",
    "sg:address":"Church Street, Chasetown",
    "sg:city":"Burntwood",
    "sg:classifiers":[
        {
            "category":"Arena",
            "subcategory":"Sports Club",
            "type":"Entertainment"
        }
    ],
    "sg:phone":"+44 1543 682222",
    "sg:postcode":"WS7 8QL",
    "sg:province":"Staffordshire",
    "wof:name":"Chasetown Football Club Ltd.",
    "wof:placetype":"venue"
},
  "geometry": {"coordinates":[-1.923684,52.671738],"type":"Point"}
}