{
  "type": "Feature",
  "properties": {
    "addr:full":"76 Fountayne Road London Greater London N16 7DT",
    "addr:housenumber":"76",
    "addr:postcode":"n16 7dt",
    "addr:street":"Fountayne Road",
    "iso:country":"GB",
    "sg:address":"76 Fountayne Road",
    "sg:city":"London",
    "sg:classifiers":[
        {
            "category":"Food & Beverages",
            "subcategory":"Supermarket",
            "type":"Retail Goods"
        }
    ],
    "sg:phone":"+44 20 8806 5839",
    "sg:postcode":"N16 7DT",
    "sg:province":"Greater London",
    "wof:name":"Londis Store",
    "wof:placetype":"venue"
},
  "geometry": {"coordinates":[-0.0670889989,51.56275177],"type":"Point"}
}