{
  "type": "Feature",
  "properties": {
    "addr:full":"261 Manchester Road Northwich Cheshire CW9 7NE",
    "addr:housenumber":"261",
    "addr:postcode":"cw9 7ne",
    "addr:street":"Manchester Road",
    "iso:country":"GB",
    "sg:address":"261 Manchester Road",
    "sg:city":"Northwich",
    "sg:classifiers":[
        {
            "category":"Freight",
            "type":"Transportation"
        }
    ],
    "sg:postcode":"CW9 7NE",
    "sg:province":"Cheshire",
    "sg:tags":[
        "haulage",
        "road"
    ],
    "wof:name":"Quick Shift Recovery Ltd.",
    "wof:placetype":"venue"
},
  "geometry": {"coordinates":[-2.480209,53.266994],"type":"Point"}
}