{
  "type": "Feature",
  "properties": {
    "iso:country":"GB",
    "sg:address":"3 High Street, Irchester",
    "sg:city":"Wellingborough",
    "sg:classifiers":[
        {
            "category":"Organizations",
            "subcategory":"Community Association",
            "type":"Services"
        },
        {
            "category":"Organizations",
            "subcategory":"Membership Organization",
            "type":"Services"
        }
    ],
    "sg:phone":"+44 1933 353064",
    "sg:postcode":"NN29 7AA",
    "sg:province":"Bedfordshire",
    "sg:tags":[
        "club",
        "social"
    ],
    "wof:name":"Irchester Working Mens Club",
    "wof:placetype":"venue"
},
  "geometry": {"coordinates":[-0.645019,52.281059],"type":"Point"}
}