{
  "type": "Feature",
  "properties": {
    "iso:country":"GB",
    "sg:address":"Elm Farm, Bretton Lane, Bretton",
    "sg:city":"Chester",
    "sg:classifiers":[
        {
            "category":"Farming",
            "subcategory":"Livestock Farm",
            "type":"Manufacturing & Wholesale Goods"
        }
    ],
    "sg:postcode":"CH4 0DX",
    "sg:province":"Cheshire",
    "sg:tags":[
        "others"
    ],
    "wof:name":"Malcolm J Chaloner",
    "wof:placetype":"venue"
},
  "geometry": {"coordinates":[-2.9666199684,53.1688117981],"type":"Point"}
}