{
  "type": "Feature",
  "properties": {
    "iso:country":"GB",
    "sg:address":"Avalon House, 15 Sywell Village, Sywell",
    "sg:city":"Northampton",
    "sg:classifiers":[
        {
            "category":"Professional",
            "subcategory":"Management & Consulting",
            "type":"Services"
        },
        {
            "category":"Banks & Credit Unions",
            "subcategory":"Financial Services",
            "type":"Services"
        }
    ],
    "sg:phone":"+44 1604 492922",
    "sg:postcode":"NN6 0BQ",
    "sg:province":"Northamptonshire",
    "sg:tags":[
        "consultant",
        "finance",
        "business"
    ],
    "wof:name":"AVALON FINANCE",
    "wof:placetype":"venue"
},
  "geometry": {"coordinates":[-0.8144530058,52.2911987305],"type":"Point"}
}