{
  "type": "Feature",
  "properties": {
    "iso:country":"GB",
    "sg:address":"9 Old Market St",
    "sg:city":"King's Lynn",
    "sg:classifiers":[
        {
            "category":"Bars & Pubs",
            "type":"Food & Drink"
        }
    ],
    "sg:phone":"+44 1553 763297",
    "sg:postcode":"PE30 1NL",
    "sg:province":"Norfolk",
    "sg:tags":[
        "pubs",
        "inn"
    ],
    "wof:name":"Unique Pub Co Plc (The)",
    "wof:placetype":"venue"
},
  "geometry": {"coordinates":[0.399824,52.753647],"type":"Point"}
}