{
  "type": "Feature",
  "properties": {
    "addr:full":"Abden Street, Radcliffe Manchester Greater Manchester M26 3AT",
    "addr:postcode":"m26 3at",
    "addr:street":"Abden Street",
    "iso:country":"GB",
    "sg:address":"Abden Street, Radcliffe",
    "sg:city":"Manchester",
    "sg:classifiers":[
        {
            "category":"Government",
            "subcategory":"Office",
            "type":"Public Place"
        }
    ],
    "sg:phone":"+44 161 724 8337",
    "sg:postcode":"M26 3AT",
    "sg:province":"Greater Manchester",
    "sg:tags":[
        "education",
        "agency",
        "authority"
    ],
    "wof:name":"Sensory Support Service",
    "wof:placetype":"venue"
},
  "geometry": {"coordinates":[-2.330654,53.561996],"type":"Point"}
}