{
  "type": "Feature",
  "properties": {
    "iso:country":"GB",
    "sg:address":"Lawrence Road, Worle",
    "sg:city":"Weston-super-mare",
    "sg:classifiers":[
        {
            "category":"Community Center",
            "type":"Public Place"
        }
    ],
    "sg:phone":"+44 1934 515681",
    "sg:postcode":"BS22 6TU",
    "sg:province":"Somerset",
    "sg:tags":[
        "centre"
    ],
    "wof:name":"Worle Community Centre",
    "wof:placetype":"venue"
},
  "geometry": {"coordinates":[-2.930114,51.35936],"type":"Point"}
}