{
  "type": "Feature",
  "properties": {
    "addr:full":"52 Three Springs Road Pershore Worcestershire WR10 1HS",
    "addr:housenumber":"52",
    "addr:postcode":"wr10 1hs",
    "addr:street":"Three Springs Road",
    "iso:country":"GB",
    "sg:address":"52 Three Springs Road",
    "sg:city":"Pershore",
    "sg:classifiers":[
        {
            "category":"Shopping",
            "subcategory":"Computers & Home Electronics",
            "type":"Retail Goods"
        },
        {
            "category":"Communications",
            "type":"Services"
        }
    ],
    "sg:phone":"+44 1386 553151",
    "sg:postcode":"WR10 1HS",
    "sg:province":"Worcestershire",
    "sg:tags":[
        "radio",
        "television",
        "aerial",
        "audio-visual"
    ],
    "wof:name":"Aerial Erection Service",
    "wof:placetype":"venue"
},
  "geometry": {"coordinates":[-2.088109,52.109131],"type":"Point"}
}