{
  "type": "Feature",
  "properties": {
    "iso:country":"GB",
    "sg:address":"Wood Barn Farm, Mutfordwood Lane, Carlton Colville",
    "sg:city":"Lowestoft",
    "sg:classifiers":[
        {
            "category":"Utilities",
            "subcategory":"Refuse",
            "type":"Services"
        }
    ],
    "sg:postcode":"NR33 8HD",
    "sg:province":"Suffolk",
    "sg:tags":[
        "skip",
        "hire"
    ],
    "wof:name":"Charles R Hales",
    "wof:placetype":"venue"
},
  "geometry": {"coordinates":[1.701601,52.45232],"type":"Point"}
}