{
  "type": "Feature",
  "properties": {
    "iso:country":"GB",
    "sg:address":"Birch House, 23-25 St Edward Street",
    "sg:city":"Leek",
    "sg:classifiers":[
        {
            "category":"Cafe",
            "type":"Food & Drink"
        }
    ],
    "sg:phone":"+44 1538 373751",
    "sg:postcode":"ST13 5DR",
    "sg:province":"Staffordshire",
    "sg:tags":[
        "tea",
        "room"
    ],
    "wof:name":"Den Engel",
    "wof:placetype":"venue"
},
  "geometry": {"coordinates":[-2.026437,53.105743],"type":"Point"}
}