{
  "type": "Feature",
  "properties": {
    "addr:full":"50 High Street Dunmow Essex CM6 1AW",
    "addr:housenumber":"50",
    "addr:postcode":"cm6 1aw",
    "addr:street":"High Street",
    "iso:country":"GB",
    "sg:address":"50 High Street",
    "sg:city":"Dunmow",
    "sg:classifiers":[
        {
            "category":"Food & Beverages",
            "subcategory":"Meat & Fish",
            "type":"Retail Goods"
        },
        {
            "category":"Food & Beverages",
            "subcategory":"Groceries & Convenience Stores",
            "type":"Retail Goods"
        }
    ],
    "sg:phone":"+44 1371 872895",
    "sg:postcode":"CM6 1AW",
    "sg:province":"Essex",
    "sg:tags":[
        "shop",
        "chip"
    ],
    "wof:name":"Edwards Fish & Chips",
    "wof:placetype":"venue"
},
  "geometry": {"coordinates":[0.36414,51.870796],"type":"Point"}
}