{
  "type": "Feature",
  "properties": {
    "addr:full":"Chapelbank Works Workington Cumbria CA14 5AE",
    "addr:postcode":"ca14 5ae",
    "addr:street":"Workington",
    "iso:country":"GB",
    "sg:address":"Chapelbank Works",
    "sg:city":"Workington",
    "sg:classifiers":[
        {
            "category":"Freight",
            "type":"Transportation"
        }
    ],
    "sg:phone":"+44 1900 604375",
    "sg:postcode":"CA14 5AE",
    "sg:province":"Cumbria",
    "sg:tags":[
        "haulage",
        "road"
    ],
    "wof:name":"A D Boyes",
    "wof:placetype":"venue"
},
  "geometry": {"coordinates":[-3.5500020981,54.6389808655],"type":"Point"}
}