{
  "type": "Feature",
  "properties": {
    "iso:country":"GB",
    "sg:address":"Fareham Baptist Church, Gosport Rd",
    "sg:city":"Fareham",
    "sg:classifiers":[
        {
            "category":"Place Of Worship",
            "type":"Public Place"
        }
    ],
    "sg:phone":"+44 1329 230659",
    "sg:postcode":"PO16 0QW",
    "sg:province":"Hampshire",
    "wof:name":"Churches & Other Places of Worship",
    "wof:placetype":"venue"
},
  "geometry": {"coordinates":[-1.174099,50.852734],"type":"Point"}
}