{
  "type": "Feature",
  "properties": {
    "addr:full":"Coupar, Angus Blairgowrie Angus PH13 9DP",
    "addr:postcode":"ph13 9dp",
    "iso:country":"GB",
    "sg:address":"Coupar, Angus",
    "sg:city":"Blairgowrie",
    "sg:classifiers":[
        {
            "category":"Health Services",
            "subcategory":"Doctor",
            "type":"Services"
        },
        {
            "category":"Health Services",
            "subcategory":"Clinic",
            "type":"Services"
        }
    ],
    "sg:phone":"+44 1828 627318",
    "sg:postcode":"PH13 9DP",
    "sg:province":"Angus",
    "sg:tags":[
        "nh",
        "practitioners"
    ],
    "wof:name":"Trades Lane Health Centre",
    "wof:placetype":"venue"
},
  "geometry": {"coordinates":[-3.33616,56.587749],"type":"Point"}
}