{
  "type": "Feature",
  "properties": {
    "addr:full":"Berkley House, 86 High Street Carshalton Surrey SM5 3AE",
    "addr:housenumber":"86",
    "addr:postcode":"sm5 3ae",
    "addr:street":"High Street",
    "iso:country":"GB",
    "sg:address":"Berkley House, 86 High Street",
    "sg:city":"Carshalton",
    "sg:classifiers":[
        {
            "category":"Professional",
            "subcategory":"Business Services",
            "type":"Services"
        }
    ],
    "sg:postcode":"SM5 3AE",
    "sg:province":"Surrey",
    "sg:tags":[
        "agent",
        "manufacturers'"
    ],
    "wof:name":"Mathew Bros",
    "wof:placetype":"venue"
},
  "geometry": {"coordinates":[-0.1599249989,51.3654785156],"type":"Point"}
}