{
  "type": "Feature",
  "properties": {
    "iso:country":"GB",
    "sg:address":"Woodfield Road, Balby",
    "sg:city":"Doncaster",
    "sg:classifiers":[
        {
            "category":"Manufacturing",
            "subcategory":"Lumber",
            "type":"Manufacturing & Wholesale Goods"
        }
    ],
    "sg:phone":"+44 1302 850444",
    "sg:postcode":"DN4 8EP",
    "sg:province":"South Yorkshire",
    "sg:tags":[
        "importer",
        "merchants",
        "agent",
        "timber"
    ],
    "wof:name":"Adrian Welch",
    "wof:placetype":"venue"
},
  "geometry": {"coordinates":[-1.153874,53.502899],"type":"Point"}
}