{
  "type": "Feature",
  "properties": {
    "iso:country":"GB",
    "sg:address":"79 Oving Road",
    "sg:city":"Chichester",
    "sg:classifiers":[
        {
            "category":"Home & Garden",
            "subcategory":"Household Appliances",
            "type":"Retail Goods"
        }
    ],
    "sg:phone":"+44 1329 825111",
    "sg:postcode":"PO19 7EW",
    "sg:province":"West Sussex",
    "sg:tags":[
        "electrical"
    ],
    "wof:name":"A1 Services",
    "wof:placetype":"venue"
},
  "geometry": {"coordinates":[-0.7605720162,50.8372993469],"type":"Point"}
}