{
  "type": "Feature",
  "properties": {
    "addr:full":"Unit 1, 107 Village Farm Industrial Estate, Pyle Bridgend Bridgend CF33 6NU",
    "addr:housenumber":"unit 1 107;estate",
    "addr:postcode":"cf33 6nu",
    "addr:street":"Village;Pyle",
    "iso:country":"GB",
    "sg:address":"Unit 1, 107 Village Farm Industrial Estate, Pyle",
    "sg:city":"Bridgend",
    "sg:classifiers":[
        {
            "category":"Manufacturing",
            "subcategory":"Building Materials",
            "type":"Manufacturing & Wholesale Goods"
        }
    ],
    "sg:phone":"+44 1656 742632",
    "sg:postcode":"CF33 6NU",
    "sg:province":"Bridgend",
    "sg:tags":[
        "concrete",
        "product"
    ],
    "wof:name":"Red Circle Slabs",
    "wof:placetype":"venue"
},
  "geometry": {"coordinates":[-3.687571,51.524128],"type":"Point"}
}