{
  "type": "Feature",
  "properties": {
    "addr:full":"87 Regent St West End Hampshire W1R 7LF",
    "addr:housenumber":"87",
    "addr:postcode":"w1r 7lf",
    "addr:street":"Regent St",
    "iso:country":"GB",
    "sg:address":"87 Regent St",
    "sg:city":"West End",
    "sg:classifiers":[
        {
            "category":"Travel",
            "subcategory":"Travel Agent",
            "type":"Entertainment"
        }
    ],
    "sg:phone":"+44 20 7287 6334",
    "sg:postcode":"W1R 7LF",
    "sg:province":"Hampshire",
    "wof:name":"Polish Air Tours",
    "wof:placetype":"venue"
},
  "geometry": {"coordinates":[-0.1374460012,51.5098686218],"type":"Point"}
}