{
  "type": "Feature",
  "properties": {
    "iso:country":"GB",
    "sg:address":"1a Bardsley Rd, Earlstrees Indust Est",
    "sg:city":"Corby",
    "sg:classifiers":[
        {
            "category":"Wholesale",
            "subcategory":"Meat",
            "type":"Manufacturing & Wholesale Goods"
        }
    ],
    "sg:phone":"+44 1536 204464",
    "sg:postcode":"NN17 4AR",
    "sg:province":"Northamptonshire",
    "sg:tags":[
        "-"
    ],
    "wof:name":"Helmsley Meat Ltd",
    "wof:placetype":"venue"
},
  "geometry": {"coordinates":[-0.703489,52.509998],"type":"Point"}
}