{
  "type": "Feature",
  "properties": {
    "iso:country":"GB",
    "sg:address":"21 Midhurst Road",
    "sg:city":"Sheffield",
    "sg:classifiers":[
        {
            "category":"Health Services",
            "subcategory":"Nursing And Care Facility",
            "type":"Services"
        }
    ],
    "sg:phone":"+44 114 285 5345",
    "sg:postcode":"S6 1EY",
    "sg:province":"South Yorkshire",
    "sg:tags":[
        "home"
    ],
    "wof:name":"Midhurst Residential Home",
    "wof:placetype":"venue"
},
  "geometry": {"coordinates":[-1.501265049,53.4244728088],"type":"Point"}
}