{
  "type": "Feature",
  "properties": {
    "addr:full":"Crown Ho, North Circular Rd Willesden Greater London NW10 7PN",
    "addr:postcode":"nw10 7pn",
    "addr:street":"North Circular Rd",
    "iso:country":"GB",
    "sg:address":"Crown Ho, North Circular Rd",
    "sg:city":"Willesden",
    "sg:classifiers":[
        {
            "category":"Professional",
            "subcategory":"Business Services",
            "type":"Services"
        }
    ],
    "sg:phone":"+44 20 8961 6333",
    "sg:postcode":"NW10 7PN",
    "sg:province":"Greater London",
    "sg:tags":[
        "import",
        "export",
        "agent"
    ],
    "wof:name":"Hi-Flyer UK Ltd",
    "wof:placetype":"venue"
},
  "geometry": {"coordinates":[-0.2843399942,51.537399292],"type":"Point"}
}