{
  "type": "Feature",
  "properties": {
    "iso:country":"GB",
    "sg:address":"32 Washington Street",
    "sg:city":"Glasgow",
    "sg:classifiers":[
        {
            "category":"Professional",
            "type":"Services"
        }
    ],
    "sg:phone":"+44 141 221 9329",
    "sg:postcode":"G3 8AZ",
    "sg:province":"Glasgow City",
    "sg:tags":[
        "valuer",
        "auctioneer"
    ],
    "wof:name":"CARPET AUCTIONEERS (SCOTLAND) LTD",
    "wof:placetype":"venue"
},
  "geometry": {"coordinates":[-4.268763,55.858017],"type":"Point"}
}