{
  "type": "Feature",
  "properties": {
    "iso:country":"GB",
    "sg:address":"The Park Clinic, Earl Road",
    "sg:city":"Mold",
    "sg:classifiers":[
        {
            "category":"Health Services",
            "subcategory":"Health Practitioner",
            "type":"Services"
        }
    ],
    "sg:phone":"+44 1352 753331",
    "sg:postcode":"CH7 1AX",
    "sg:province":"Denbighshire",
    "sg:tags":[
        "osteopath"
    ],
    "wof:name":"Ianto D Powell Osteopath",
    "wof:placetype":"venue"
},
  "geometry": {"coordinates":[-3.146954,53.163956],"type":"Point"}
}