{
  "type": "Feature",
  "properties": {
    "iso:country":"GB",
    "sg:address":"1 Queen Street, Swinton",
    "sg:city":"Mexborough",
    "sg:classifiers":[
        {
            "category":"Shopping",
            "subcategory":"Gifts & Souvenirs",
            "type":"Retail Goods"
        }
    ],
    "sg:phone":"+44 1709 587812",
    "sg:postcode":"S64 8LZ",
    "sg:province":"South Yorkshire",
    "sg:tags":[
        "shop"
    ],
    "wof:name":"Something Special",
    "wof:placetype":"venue"
},
  "geometry": {"coordinates":[-1.3134880066,53.4880828857],"type":"Point"}
}