{
  "type": "Feature",
  "properties": {
    "addr:full":"Upper Mains, Echt Westhill Aberdeen City AB32 7AR",
    "addr:postcode":"ab32 7ar",
    "addr:street":"Upper Mains",
    "iso:country":"GB",
    "sg:address":"Upper Mains, Echt",
    "sg:city":"Westhill",
    "sg:classifiers":[
        {
            "category":"Farming",
            "subcategory":"Farm",
            "type":"Manufacturing & Wholesale Goods"
        }
    ],
    "sg:phone":"+44 1330 860520",
    "sg:postcode":"AB32 7AR",
    "sg:province":"Aberdeen City",
    "sg:tags":[
        "mixed",
        "crop"
    ],
    "wof:name":"A Chalmers & Son",
    "wof:placetype":"venue"
},
  "geometry": {"coordinates":[-2.2926840782,57.1494445801],"type":"Point"}
}