{
  "type": "Feature",
  "properties": {
    "iso:country":"GB",
    "sg:address":"12 Blackden Close",
    "sg:city":"Belper",
    "sg:classifiers":[
        {
            "category":"Professional",
            "subcategory":"Engineering",
            "type":"Services"
        }
    ],
    "sg:phone":"+44 1773 827150",
    "sg:postcode":"DE56 0DL",
    "sg:province":"Derbyshire",
    "sg:tags":[
        "agricultural",
        "engineer"
    ],
    "wof:name":"Pb Electrical",
    "wof:placetype":"venue"
},
  "geometry": {"coordinates":[-1.449024,53.027588],"type":"Point"}
}