{
  "type": "Feature",
  "properties": {
    "iso:country":"GB",
    "sg:address":"151a High St, Kings Heath",
    "sg:city":"Birmingham",
    "sg:classifiers":[
        {
            "category":"Shopping",
            "subcategory":"Shoes",
            "type":"Retail Goods"
        }
    ],
    "sg:postcode":"B14 7DG",
    "sg:province":"West Midlands",
    "sg:tags":[
        "shop"
    ],
    "wof:name":"Stead & Simpson Ltd",
    "wof:placetype":"venue"
},
  "geometry": {"coordinates":[-1.892779,52.43409],"type":"Point"}
}