{
  "type": "Feature",
  "properties": {
    "iso:country":"GB",
    "sg:address":"The Old Manor House, Bridge Street",
    "sg:city":"Saxmundham",
    "sg:classifiers":[
        {
            "category":"Professional",
            "subcategory":"Management & Consulting",
            "type":"Services"
        }
    ],
    "sg:postcode":"IP17 2PG",
    "sg:province":"Suffolk",
    "sg:tags":[
        "marketing",
        "consultant"
    ],
    "wof:name":"John Cowie Partnership",
    "wof:placetype":"venue"
},
  "geometry": {"coordinates":[1.498165,52.231876],"type":"Point"}
}