{
  "type": "Feature",
  "properties": {
    "iso:country":"GB",
    "sg:address":"Griffin House",
    "sg:city":"Manchester",
    "sg:classifiers":[
        {
            "category":"Social Services",
            "subcategory":"Job Training",
            "type":"Services"
        }
    ],
    "sg:phone":"+44 161 498 6054",
    "sg:postcode":"M23 9GP",
    "sg:province":"Cheshire",
    "sg:tags":[
        "technology",
        "management",
        "traffic"
    ],
    "wof:name":"South Manchester Electric Gate & Barrier",
    "wof:placetype":"venue"
},
  "geometry": {"coordinates":[-2.29648,53.389225],"type":"Point"}
}