{
  "type": "Feature",
  "properties": {
    "addr:full":"10 Goose Gate Nottingham Nottinghamshire NG1 1FF",
    "addr:housenumber":"10",
    "addr:postcode":"ng1 1ff",
    "addr:street":"Goose Gate",
    "iso:country":"GB",
    "sg:address":"10 Goose Gate",
    "sg:city":"Nottingham",
    "sg:classifiers":[
        {
            "category":"Shopping",
            "subcategory":"Gifts & Souvenirs",
            "type":"Retail Goods"
        }
    ],
    "sg:postcode":"NG1 1FF",
    "sg:province":"Nottinghamshire",
    "sg:tags":[
        "shop"
    ],
    "wof:name":"Corbett,M,",
    "wof:placetype":"venue"
},
  "geometry": {"coordinates":[-1.1425149441,52.9536972046],"type":"Point"}
}