{
  "type": "Feature",
  "properties": {
    "addr:full":"The Rutlands, Ladys Drove Wisbech Cambridgeshire PE14 8DF",
    "addr:postcode":"pe14 8df",
    "addr:street":"Ladys Drove",
    "iso:country":"GB",
    "sg:address":"The Rutlands, Ladys Drove",
    "sg:city":"Wisbech",
    "sg:classifiers":[
        {
            "category":"Professional",
            "subcategory":"Art Services",
            "type":"Services"
        },
        {
            "category":"Building & Trades",
            "subcategory":"Construction",
            "type":"Services"
        }
    ],
    "sg:phone":"+44 1945 464750",
    "sg:postcode":"PE14 8DF",
    "sg:province":"Cambridgeshire",
    "sg:tags":[
        "builder",
        "decorator",
        "painter"
    ],
    "wof:name":"R J Bates",
    "wof:placetype":"venue"
},
  "geometry": {"coordinates":[0.21003,52.645081],"type":"Point"}
}