{
  "type": "Feature",
  "properties": {
    "iso:country":"GB",
    "sg:address":"Copyhold Lodge, Copyhold Lane, Cuckfield",
    "sg:city":"Haywards Heath",
    "sg:classifiers":[
        {
            "category":"Arts & Performance",
            "subcategory":"Music",
            "type":"Entertainment"
        }
    ],
    "sg:phone":"+44 1444 440048",
    "sg:postcode":"RH17 5ED",
    "sg:province":"East Sussex",
    "sg:tags":[
        "mobile",
        "disco"
    ],
    "wof:name":"Sonic Zone Discos",
    "wof:placetype":"venue"
},
  "geometry": {"coordinates":[-0.140629,51.010815],"type":"Point"}
}