{
  "type": "Feature",
  "properties": {
    "addr:full":"42 Dorchester Rd Weymouth Dorset DT4 7JZ",
    "addr:housenumber":"42",
    "addr:postcode":"dt4 7jz",
    "addr:street":"Dorchester Rd",
    "iso:country":"GB",
    "sg:address":"42 Dorchester Rd",
    "sg:city":"Weymouth",
    "sg:classifiers":[
        {
            "category":"Professional",
            "subcategory":"Accounting & Tax Preparation",
            "type":"Services"
        }
    ],
    "sg:postcode":"DT4 7JZ",
    "sg:province":"Dorset",
    "sg:tags":[
        "accountant"
    ],
    "wof:name":"Reville,H J,",
    "wof:placetype":"venue"
},
  "geometry": {"coordinates":[-2.4550409317,50.6233024597],"type":"Point"}
}