{
  "type": "Feature",
  "properties": {
    "addr:full":"40 Thomas St, St Pauls Bristol City of Bristol BS2 9LL",
    "addr:housenumber":"40",
    "addr:postcode":"bs2 9ll",
    "addr:street":"Thomas St",
    "iso:country":"GB",
    "sg:address":"40 Thomas St, St Pauls",
    "sg:city":"Bristol",
    "sg:classifiers":[
        {
            "category":"Organizations",
            "subcategory":"Non-profit Organization",
            "type":"Services"
        }
    ],
    "sg:postcode":"BS2 9LL",
    "sg:province":"City of Bristol",
    "sg:tags":[
        "organisation",
        "voluntary",
        "charity"
    ],
    "wof:name":"Our Chance N.S.F. Bristol",
    "wof:placetype":"venue"
},
  "geometry": {"coordinates":[-2.578124,51.465179],"type":"Point"}
}