{
  "type": "Feature",
  "properties": {
    "addr:full":"22 Broadway, Westminster London Greater London SW1H 0BH",
    "addr:housenumber":"22",
    "addr:postcode":"sw1h 0bh",
    "addr:street":"Broadway",
    "iso:country":"GB",
    "sg:address":"22 Broadway, Westminster",
    "sg:city":"London",
    "sg:classifiers":[
        {
            "category":"Autos & Motor Vehicles",
            "subcategory":"Auto Supplies",
            "type":"Retail Goods"
        },
        {
            "category":"Communications",
            "type":"Services"
        }
    ],
    "sg:phone":"+44 20 7222 1531",
    "sg:postcode":"SW1H 0BH",
    "sg:province":"Greater London",
    "sg:tags":[
        "tv",
        "machine",
        "video",
        "dictation",
        "radio"
    ],
    "wof:name":"The Dictating Machine Co. Ltd.",
    "wof:placetype":"venue"
},
  "geometry": {"coordinates":[-0.1337350011,51.4990386963],"type":"Point"}
}