{
  "type": "Feature",
  "properties": {
    "addr:full":"106 Mary St Sheffield South Yorkshire S1 4RU",
    "addr:housenumber":"106",
    "addr:postcode":"s1 4ru",
    "addr:street":"Mary St",
    "iso:country":"GB",
    "sg:address":"106 Mary St",
    "sg:city":"Sheffield",
    "sg:classifiers":[
        {
            "category":"Communications",
            "subcategory":"Film & Video Production",
            "type":"Services"
        }
    ],
    "sg:phone":"+44 114 281 2051",
    "sg:postcode":"S1 4RU",
    "sg:province":"South Yorkshire",
    "sg:tags":[
        "illustrator",
        "artist"
    ],
    "wof:name":"Loft The",
    "wof:placetype":"venue"
},
  "geometry": {"coordinates":[-1.467854,53.374146],"type":"Point"}
}