{
  "type": "Feature",
  "properties": {
    "iso:country":"GB",
    "sg:address":"Gas Lane",
    "sg:city":"Bristol",
    "sg:classifiers":[
        {
            "category":"Professional",
            "subcategory":"Testing Lab",
            "type":"Services"
        }
    ],
    "sg:phone":"+44 117 941 4999",
    "sg:postcode":"BS2 0QL",
    "sg:province":"City of Bristol",
    "sg:tags":[
        "mot"
    ],
    "wof:name":"M A D Motor Cycles",
    "wof:placetype":"venue"
},
  "geometry": {"coordinates":[-2.574469,51.450722],"type":"Point"}
}