{
  "type": "Feature",
  "properties": {
    "iso:country":"GB",
    "sg:address":"54 Southgate",
    "sg:city":"Hartlepool",
    "sg:classifiers":[
        {
            "category":"Building & Trades",
            "subcategory":"Construction",
            "type":"Services"
        }
    ],
    "sg:postcode":"TS24 0JJ",
    "sg:province":"Durham",
    "sg:tags":[
        "decorator",
        "painter"
    ],
    "wof:name":"Morrows Artexing & Decorating Services",
    "wof:placetype":"venue"
},
  "geometry": {"coordinates":[-1.187816,54.69611],"type":"Point"}
}