{
  "type": "Feature",
  "properties": {
    "addr:full":"115 Billy Lows Lane Potters Bar Greater London EN6 1UY",
    "addr:housenumber":"115",
    "addr:postcode":"en6 1uy",
    "addr:street":"Billy Lows Lane",
    "iso:country":"GB",
    "sg:address":"115 Billy Lows Lane",
    "sg:city":"Potters Bar",
    "sg:classifiers":[
        {
            "category":"Professional",
            "subcategory":"Accounting & Tax Preparation",
            "type":"Services"
        }
    ],
    "sg:postcode":"EN6 1UY",
    "sg:province":"Greater London",
    "sg:tags":[
        "consultant"
    ],
    "wof:name":"Professional V A T Consultants",
    "wof:placetype":"venue"
},
  "geometry": {"coordinates":[-0.1786399931,51.6999053955],"type":"Point"}
}