{
  "type": "Feature",
  "properties": {
    "addr:full":"11 Westbourne Avenue, Whitefield Manchester Lancashire M45 7RY",
    "addr:housenumber":"11",
    "addr:postcode":"m45 7ry",
    "addr:street":"Westbourne Avenue",
    "iso:country":"GB",
    "sg:address":"11 Westbourne Avenue, Whitefield",
    "sg:city":"Manchester",
    "sg:classifiers":[
        {
            "category":"Building & Trades",
            "subcategory":"Construction",
            "type":"Services"
        }
    ],
    "sg:phone":"+44 161 796 8175",
    "sg:postcode":"M45 7RY",
    "sg:province":"Lancashire",
    "sg:tags":[
        "builder"
    ],
    "wof:name":"D & R Construction",
    "wof:placetype":"venue"
},
  "geometry": {"coordinates":[-2.3046200275,53.5543632507],"type":"Point"}
}