{
  "type": "Feature",
  "properties": {
    "iso:country":"GB",
    "sg:address":"Springwell Building, Horden",
    "sg:city":"Peterlee",
    "sg:classifiers":[
        {
            "category":"Shopping",
            "subcategory":"Shoes",
            "type":"Retail Goods"
        }
    ],
    "sg:phone":"+44 191 586 3854",
    "sg:postcode":"SR8 4SD",
    "sg:province":"Durham",
    "sg:tags":[
        "shop"
    ],
    "wof:name":"Wearside Footwear",
    "wof:placetype":"venue"
},
  "geometry": {"coordinates":[-1.311139,54.75956],"type":"Point"}
}