{
  "type": "Feature",
  "properties": {
    "addr:full":"366 Main Rd, Biggin Hill Westerham Kent TN16 2HN",
    "addr:housenumber":"366",
    "addr:postcode":"tn16 2hn",
    "addr:street":"Main Rd",
    "iso:country":"GB",
    "sg:address":"366 Main Rd, Biggin Hill",
    "sg:city":"Westerham",
    "sg:classifiers":[
        {
            "category":"Building & Trades",
            "subcategory":"Pest Control",
            "type":"Services"
        }
    ],
    "sg:phone":"+44 1959 76321",
    "sg:postcode":"TN16 2HN",
    "sg:province":"Kent",
    "sg:tags":[
        "vermin"
    ],
    "wof:name":"Protec Pest & Hygiene Specialists Ltd",
    "wof:placetype":"venue"
},
  "geometry": {"coordinates":[0.0525600016,51.2999954224],"type":"Point"}
}