{
  "type": "Feature",
  "properties": {
    "addr:full":"Stanhope Square Holsworthy Cornwall EX22 6DR",
    "addr:postcode":"ex22 6dr",
    "addr:street":"Stanhope Square",
    "iso:country":"GB",
    "sg:address":"Stanhope Square",
    "sg:city":"Holsworthy",
    "sg:classifiers":[
        {
            "category":"Transit Center",
            "subcategory":"Freight",
            "type":"Transportation"
        },
        {
            "category":"Shopping",
            "subcategory":"News",
            "type":"Retail Goods"
        }
    ],
    "sg:phone":"+44 1409 253363",
    "sg:postcode":"EX22 6DR",
    "sg:province":"Cornwall",
    "sg:tags":[
        "shop",
        "craft",
        "newsagent",
        "centre"
    ],
    "wof:name":"Maria Gent",
    "wof:placetype":"venue"
},
  "geometry": {"coordinates":[-4.3527340889,50.8100128174],"type":"Point"}
}