{
  "type": "Feature",
  "properties": {
    "iso:country":"GB",
    "sg:address":"50 Alston Drive, Bradwell Abbey",
    "sg:city":"Milton Keynes",
    "sg:classifiers":[
        {
            "category":"Building & Trades",
            "subcategory":"Construction",
            "type":"Services"
        }
    ],
    "sg:postcode":"MK13 9HB",
    "sg:province":"Buckinghamshire",
    "sg:tags":[
        "builder"
    ],
    "wof:name":"Wildforce Ltd.",
    "wof:placetype":"venue"
},
  "geometry": {"coordinates":[-0.797439,52.046413],"type":"Point"}
}