{
  "type": "Feature",
  "properties": {
    "iso:country":"GB",
    "sg:address":"25 Park Rise",
    "sg:city":"Hove",
    "sg:classifiers":[
        {
            "category":"Building & Trades",
            "subcategory":"Construction",
            "type":"Services"
        }
    ],
    "sg:phone":"+44 1273 709264",
    "sg:postcode":"BN3 8PG",
    "sg:province":"East Sussex",
    "sg:tags":[
        "dry",
        "lining",
        "plasterers",
        "screeders"
    ],
    "wof:name":"Quality Plastering",
    "wof:placetype":"venue"
},
  "geometry": {"coordinates":[-0.194444,50.850609],"type":"Point"}
}