{
  "type": "Feature",
  "properties": {
    "addr:full":"47 Bridge Street Morpeth Northumberland NE61 1PE",
    "addr:housenumber":"47",
    "addr:postcode":"ne61 1pe",
    "addr:street":"Bridge Street",
    "iso:country":"GB",
    "sg:address":"47 Bridge Street",
    "sg:city":"Morpeth",
    "sg:classifiers":[
        {
            "category":"Bars & Pubs",
            "type":"Food & Drink"
        }
    ],
    "sg:phone":"+44 1670 512089",
    "sg:postcode":"NE61 1PE",
    "sg:province":"Northumberland",
    "sg:tags":[
        "pubs",
        "inn"
    ],
    "wof:name":"The Black Bull",
    "wof:placetype":"venue"
},
  "geometry": {"coordinates":[-1.687745,55.167408],"type":"Point"}
}