{
  "type": "Feature",
  "properties": {
    "addr:full":"No 5 Oxford House, Oxford Road Wokingham Berkshire RG41 2YE",
    "addr:postcode":"rg41 2ye",
    "addr:street":"Oxford Road",
    "iso:country":"GB",
    "sg:address":"No 5 Oxford House, Oxford Road",
    "sg:city":"Wokingham",
    "sg:classifiers":[
        {
            "category":"Professional",
            "subcategory":"Management & Consulting",
            "type":"Services"
        }
    ],
    "sg:postcode":"RG41 2YE",
    "sg:province":"Berkshire",
    "sg:tags":[
        "marketing",
        "consultant"
    ],
    "wof:name":"Giant Clam Ltd",
    "wof:placetype":"venue"
},
  "geometry": {"coordinates":[-0.8455200195,51.4127197266],"type":"Point"}
}