{
  "type": "Feature",
  "properties": {
    "addr:full":"2 Jermyn Drive Sheffield Derbyshire S12 4QF",
    "addr:housenumber":"2",
    "addr:postcode":"s12 4qf",
    "addr:street":"Jermyn Drive",
    "iso:country":"GB",
    "sg:address":"2 Jermyn Drive",
    "sg:city":"Sheffield",
    "sg:classifiers":[
        {
            "category":"Building & Trades",
            "subcategory":"Landscaping Services",
            "type":"Services"
        }
    ],
    "sg:phone":"+44 114 248 4623",
    "sg:postcode":"S12 4QF",
    "sg:province":"Derbyshire",
    "sg:tags":[
        "forestry",
        "surgeon",
        "tree"
    ],
    "wof:name":"A W OTTER & SON",
    "wof:placetype":"venue"
},
  "geometry": {"coordinates":[-1.3929920197,53.346370697],"type":"Point"}
}