{
  "type": "Feature",
  "properties": {
    "addr:full":"33 High Road, Leavesden Watford Hertfordshire WD25 7AE",
    "addr:housenumber":"33",
    "addr:postcode":"wd25 7ae",
    "addr:street":"High Road",
    "iso:country":"GB",
    "sg:address":"33 High Road, Leavesden",
    "sg:city":"Watford",
    "sg:classifiers":[
        {
            "category":"Professional",
            "subcategory":"Art Services",
            "type":"Services"
        }
    ],
    "sg:postcode":"WD25 7AE",
    "sg:province":"Hertfordshire",
    "sg:tags":[
        "model",
        "maker"
    ],
    "wof:name":"Darnell Models",
    "wof:placetype":"venue"
},
  "geometry": {"coordinates":[-0.4123919904,51.6878166199],"type":"Point"}
}