{
  "type": "Feature",
  "properties": {
    "iso:country":"GB",
    "sg:address":"82 Slater Road, Bentley Heath",
    "sg:city":"Solihull",
    "sg:classifiers":[
        {
            "category":"Arts & Performance",
            "subcategory":"Music",
            "type":"Entertainment"
        }
    ],
    "sg:phone":"+44 121 745 9983",
    "sg:postcode":"B93 8AJ",
    "sg:province":"Warwickshire",
    "sg:tags":[
        "mobile",
        "disco"
    ],
    "wof:name":"Mirror Image Disco",
    "wof:placetype":"venue"
},
  "geometry": {"coordinates":[-1.7598190308,52.380607605],"type":"Point"}
}