{
  "type": "Feature",
  "properties": {
    "addr:full":"Goldsmiths Wharf Grays Essex RM17 6HY",
    "addr:postcode":"rm17 6hy",
    "iso:country":"GB",
    "sg:address":"Goldsmiths Wharf",
    "sg:city":"Grays",
    "sg:classifiers":[
        {
            "category":"Retail",
            "subcategory":"Auto Repair",
            "type":"Services"
        }
    ],
    "sg:postcode":"RM17 6HY",
    "sg:province":"Essex",
    "sg:tags":[
        "modification",
        "garage"
    ],
    "wof:name":"Orsett Vehicle Repairers",
    "wof:placetype":"venue"
},
  "geometry": {"coordinates":[0.31868,51.474232],"type":"Point"}
}