{
  "type": "Feature",
  "properties": {
    "addr:full":"P O Box 156, Chearsley Aylesbury Buckinghamshire HP18 0DQ",
    "addr:housenumber":"156",
    "addr:postcode":"hp18 0dq",
    "addr:street":"P O Box;Chearsley Aylesbury",
    "iso:country":"GB",
    "sg:address":"P O Box 156, Chearsley",
    "sg:city":"Aylesbury",
    "sg:classifiers":[
        {
            "category":"Shopping",
            "subcategory":"Computers & Home Electronics",
            "type":"Retail Goods"
        }
    ],
    "sg:postcode":"HP18 0DQ",
    "sg:province":"Buckinghamshire",
    "wof:name":"Laurence Urdang Inc",
    "wof:placetype":"venue"
},
  "geometry": {"coordinates":[-0.9614199996,51.7903709412],"type":"Point"}
}