{
  "type": "Feature",
  "properties": {
    "addr:full":"44 Ferriby Road Hessle East Riding of Yorkshire HU13 0HT",
    "addr:housenumber":"44",
    "addr:postcode":"hu13 0ht",
    "addr:street":"Ferriby Road",
    "iso:country":"GB",
    "sg:address":"44 Ferriby Road",
    "sg:city":"Hessle",
    "sg:classifiers":[
        {
            "category":"Farming",
            "subcategory":"Nursery",
            "type":"Manufacturing & Wholesale Goods"
        }
    ],
    "sg:phone":"+44 1482 643565",
    "sg:postcode":"HU13 0HT",
    "sg:province":"East Riding of Yorkshire",
    "sg:tags":[
        "creche"
    ],
    "wof:name":"Hessle Pre-School Nursery",
    "wof:placetype":"venue"
},
  "geometry": {"coordinates":[-0.441465,53.722683],"type":"Point"}
}