{
  "type": "Feature",
  "properties": {
    "addr:full":"23 Jarnac Court Dalkeith City of Edinburgh EH22 1HU",
    "addr:housenumber":"23",
    "addr:postcode":"eh22 1hu",
    "addr:street":"Jarnac Court",
    "iso:country":"GB",
    "sg:address":"23 Jarnac Court",
    "sg:city":"Dalkeith",
    "sg:classifiers":[
        {
            "category":"Real Estate",
            "subcategory":"Real Estate Agent",
            "type":"Services"
        }
    ],
    "sg:phone":"+44 131 663 7266",
    "sg:postcode":"EH22 1HU",
    "sg:province":"City of Edinburgh",
    "wof:name":"Lister Marshall",
    "wof:placetype":"venue"
},
  "geometry": {"coordinates":[-3.0693919659,55.8937644958],"type":"Point"}
}