{
  "type": "Feature",
  "properties": {
    "iso:country":"GB",
    "sg:address":"184 London Road",
    "sg:city":"Cheltenham",
    "sg:classifiers":[
        {
            "category":"Bars & Pubs",
            "type":"Food & Drink"
        },
        {
            "category":"Community Center",
            "subcategory":"Social",
            "type":"Public Place"
        }
    ],
    "sg:phone":"+44 1242 526038",
    "sg:postcode":"GL52 6HJ",
    "sg:province":"Gloucestershire",
    "sg:tags":[
        "pubs",
        "house",
        "inn",
        "activity"
    ],
    "wof:name":"Beaufort Arms",
    "wof:placetype":"venue"
},
  "geometry": {"coordinates":[-2.060949,51.89122],"type":"Point"}
}