{
  "type": "Feature",
  "properties": {
    "addr:full":"6 The Triangle, Bitterne Park Southampton Hampshire SO18 1FZ",
    "addr:housenumber":"6",
    "addr:postcode":"so18 1fz",
    "addr:street":"The Triangle",
    "iso:country":"GB",
    "sg:address":"6 The Triangle, Bitterne Park",
    "sg:city":"Southampton",
    "sg:classifiers":[
        {
            "category":"Shopping",
            "subcategory":"Baby Store",
            "type":"Retail Goods"
        }
    ],
    "sg:postcode":"SO18 1FZ",
    "sg:province":"Hampshire",
    "sg:tags":[
        "babywear",
        "childrens"
    ],
    "wof:name":"Bambey's Babycare",
    "wof:placetype":"venue"
},
  "geometry": {"coordinates":[-1.376161,50.924484],"type":"Point"}
}