{
  "type": "Feature",
  "properties": {
    "iso:country":"GB",
    "sg:address":"Fryern Ho, 125 Winchester Rd",
    "sg:city":"Eastleigh",
    "sg:classifiers":[
        {
            "category":"Building & Trades",
            "subcategory":"Construction",
            "type":"Services"
        }
    ],
    "sg:phone":"+44 23 8026 1126",
    "sg:postcode":"SO53 2DR",
    "sg:province":"Hampshire",
    "sg:tags":[
        "builder"
    ],
    "wof:name":"Finch (GB) Ltd",
    "wof:placetype":"venue"
},
  "geometry": {"coordinates":[-1.37407,50.987961],"type":"Point"}
}