{
  "type": "Feature",
  "properties": {
    "addr:full":"8 Ascot Close, Hadrian Park Estate Wallsend Tyne and Wear NE28 9QU",
    "addr:housenumber":"8",
    "addr:postcode":"ne28 9qu",
    "addr:street":"Ascot Close Hadrian Park Estate",
    "iso:country":"GB",
    "sg:address":"8 Ascot Close, Hadrian Park Estate",
    "sg:city":"Wallsend",
    "sg:classifiers":[
        {
            "category":"Professional",
            "subcategory":"Art Services",
            "type":"Services"
        },
        {
            "category":"Building & Trades",
            "subcategory":"Construction",
            "type":"Services"
        }
    ],
    "sg:phone":"+44 191 262 3789",
    "sg:postcode":"NE28 9QU",
    "sg:province":"Tyne and Wear",
    "sg:tags":[
        "decorator",
        "painter"
    ],
    "wof:name":"William Toole",
    "wof:placetype":"venue"
},
  "geometry": {"coordinates":[-1.5187400579,55.0113639832],"type":"Point"}
}