{
  "type": "Feature",
  "properties": {
    "iso:country":"GB",
    "sg:address":"Georgian House, 81 Carolgate",
    "sg:city":"Retford",
    "sg:classifiers":[
        {
            "category":"Organizations",
            "subcategory":"Non-profit Organization",
            "type":"Services"
        }
    ],
    "sg:phone":"+44 1777 708090",
    "sg:postcode":"DN22 6EH",
    "sg:province":"Nottinghamshire",
    "sg:tags":[
        "organisation",
        "voluntary",
        "charity"
    ],
    "wof:name":"Education Africa",
    "wof:placetype":"venue"
},
  "geometry": {"coordinates":[-0.941425,53.319817],"type":"Point"}
}