{
  "type": "Feature",
  "properties": {
    "addr:full":"Norfolk House, Priestley Road Basingstoke Hampshire RG24 9NY",
    "addr:postcode":"rg24 9ny",
    "addr:street":"Priestley Road",
    "iso:country":"GB",
    "sg:address":"Norfolk House, Priestley Road",
    "sg:city":"Basingstoke",
    "sg:classifiers":[
        {
            "category":"Insurance",
            "subcategory":"Insurance Agent",
            "type":"Services"
        }
    ],
    "sg:phone":"+44 870 544 8866",
    "sg:postcode":"RG24 9NY",
    "sg:province":"Hampshire",
    "wof:name":"A A Insurance Services Ltd.",
    "wof:placetype":"venue"
},
  "geometry": {"coordinates":[-1.105546,51.277355],"type":"Point"}
}