{
  "type": "Feature",
  "properties": {
    "iso:country":"GB",
    "sg:address":"36a Mayfield Grove, Reddish",
    "sg:city":"Stockport",
    "sg:classifiers":[
        {
            "category":"Farming",
            "subcategory":"Farm",
            "type":"Manufacturing & Wholesale Goods"
        }
    ],
    "sg:phone":"+44 161 480 8456",
    "sg:postcode":"SK5 7JB",
    "sg:province":"Cheshire",
    "sg:tags":[
        "agricultural"
    ],
    "wof:name":"Bollegraaf Sales & Service",
    "wof:placetype":"venue"
},
  "geometry": {"coordinates":[-2.151634,53.427513],"type":"Point"}
}