{
  "type": "Feature",
  "properties": {
    "iso:country":"GB",
    "sg:address":"24 Howberry Road",
    "sg:city":"Edgware",
    "sg:classifiers":[
        {
            "category":"Shopping",
            "subcategory":"Clothing, Apparel, & Fashions",
            "type":"Retail Goods"
        }
    ],
    "sg:postcode":"HA8 6ST",
    "sg:province":"Greater London",
    "sg:tags":[
        "ladieswear"
    ],
    "wof:name":"Jeff's Clothes Show",
    "wof:placetype":"venue"
},
  "geometry": {"coordinates":[-0.297224,51.609161],"type":"Point"}
}