{
  "type": "Feature",
  "properties": {
    "addr:full":"4a Nugent Industrial Park, Cray Av Orpington Kent BR5 3RP",
    "addr:housenumber":"4a",
    "addr:postcode":"br5 3rp",
    "addr:street":"Nugent Industrial Park Cray Av Orpington",
    "iso:country":"GB",
    "sg:address":"4a Nugent Industrial Park, Cray Av",
    "sg:city":"Orpington",
    "sg:classifiers":[
        {
            "category":"Wholesale",
            "subcategory":"Vending Machines",
            "type":"Manufacturing & Wholesale Goods"
        }
    ],
    "sg:phone":"+44 1689 875231",
    "sg:postcode":"BR5 3RP",
    "sg:province":"Kent",
    "sg:tags":[
        "sale"
    ],
    "wof:name":"T M Group PLC",
    "wof:placetype":"venue"
},
  "geometry": {"coordinates":[0.1130999997,51.3929405212],"type":"Point"}
}