{
  "type": "Feature",
  "properties": {
    "addr:full":"9 Bosparva Lane, Leedstown Hayle Cornwall TR27 6DN",
    "addr:housenumber":"9",
    "addr:postcode":"tr27 6dn",
    "addr:street":"Bosparva Lane",
    "iso:country":"GB",
    "sg:address":"9 Bosparva Lane, Leedstown",
    "sg:city":"Hayle",
    "sg:phone":"+44 1209 831259",
    "sg:postcode":"TR27 6DN",
    "sg:province":"Cornwall",
    "wof:name":"S J & J A Hall",
    "wof:placetype":"venue"
},
  "geometry": {"coordinates":[-5.3511629105,50.1635284424],"type":"Point"}
}