{
  "type": "Feature",
  "properties": {
    "iso:country":"GB",
    "sg:address":"85 High Street",
    "sg:city":"Tunbridge Wells",
    "sg:classifiers":[
        {
            "category":"Education",
            "subcategory":"Special Training",
            "type":"Public Place"
        }
    ],
    "sg:phone":"+44 1892 513191",
    "sg:postcode":"TN1 1YG",
    "sg:province":"Kent",
    "sg:tags":[
        "product",
        "centre"
    ],
    "wof:name":"E S I",
    "wof:placetype":"venue"
},
  "geometry": {"coordinates":[0.2602500021,51.1272392273],"type":"Point"}
}