{
  "type": "Feature",
  "properties": {
    "addr:full":"Summerhill Education Centre, Stronsay Dr Aberdeen Aberdeen City AB15 6JA",
    "addr:postcode":"ab15 6ja",
    "addr:street":"Stronsay Dr",
    "iso:country":"GB",
    "sg:address":"Summerhill Education Centre, Stronsay Dr",
    "sg:city":"Aberdeen",
    "sg:classifiers":[
        {
            "category":"Banks & Credit Unions",
            "subcategory":"Financial Services",
            "type":"Services"
        }
    ],
    "sg:phone":"+44 1224 209208",
    "sg:postcode":"AB15 6JA",
    "sg:province":"Aberdeen City",
    "sg:tags":[
        "consultant"
    ],
    "wof:name":"Co-Operative Wholesale Society (Scotland",
    "wof:placetype":"venue"
},
  "geometry": {"coordinates":[-2.16346,57.150669],"type":"Point"}
}