{
  "type": "Feature",
  "properties": {
    "iso:country":"GB",
    "sg:address":"Care Of Drivers Jonas, 18 Maddox Street",
    "sg:city":"London",
    "sg:classifiers":[
        {
            "category":"Building & Trades",
            "subcategory":"Cleaning & Sanitation",
            "type":"Services"
        }
    ],
    "sg:phone":"+44 20 7499 3501",
    "sg:postcode":"W1S 1PH",
    "sg:province":"Greater London",
    "sg:tags":[
        "facility"
    ],
    "wof:name":"Pollen Estate Site Office",
    "wof:placetype":"venue"
},
  "geometry": {"coordinates":[-0.14192,51.513371],"type":"Point"}
}