{
  "type": "Feature",
  "properties": {
    "addr:full":"Winchester Rd Eastleigh Hampshire SO50 7HD",
    "addr:postcode":"so50 7hd",
    "addr:street":"Winchester Rd",
    "iso:country":"GB",
    "sg:address":"Winchester Rd",
    "sg:city":"Eastleigh",
    "sg:classifiers":[
        {
            "category":"Manufacturing",
            "subcategory":"Buildings",
            "type":"Manufacturing & Wholesale Goods"
        }
    ],
    "sg:phone":"+44 23 8069 2204",
    "sg:postcode":"SO50 7HD",
    "sg:province":"Hampshire",
    "sg:tags":[
        "mobile",
        "home"
    ],
    "wof:name":"Hill View",
    "wof:placetype":"venue"
},
  "geometry": {"coordinates":[-1.2978420258,50.9660682678],"type":"Point"}
}