{
  "type": "Feature",
  "properties": {
    "addr:full":"4 Haithwaite, Two Mile Ash Milton Keynes Buckinghamshire MK8 8LJ",
    "addr:housenumber":"4",
    "addr:postcode":"mk8 8lj",
    "addr:street":"Haithwaite Two Mile Ash",
    "iso:country":"GB",
    "sg:address":"4 Haithwaite, Two Mile Ash",
    "sg:city":"Milton Keynes",
    "sg:classifiers":[
        {
            "category":"Shopping",
            "subcategory":"Beauty & Cosmetics",
            "type":"Retail Goods"
        }
    ],
    "sg:postcode":"MK8 8LJ",
    "sg:province":"Buckinghamshire",
    "sg:tags":[
        "equipment",
        "supply",
        "hairdressing"
    ],
    "wof:name":"Professional Hairdressing Distributors",
    "wof:placetype":"venue"
},
  "geometry": {"coordinates":[-0.80614,52.037369],"type":"Point"}
}