{
  "type": "Feature",
  "properties": {
    "addr:full":"41 Bradford Rd, Stanningley Pudsey West Yorkshire LS28 6AT",
    "addr:housenumber":"41",
    "addr:postcode":"ls28 6at",
    "addr:street":"Bradford Rd;West",
    "iso:country":"GB",
    "sg:address":"41 Bradford Rd, Stanningley",
    "sg:city":"Pudsey",
    "sg:classifiers":[
        {
            "category":"Bars & Pubs",
            "type":"Food & Drink"
        }
    ],
    "sg:phone":"+44 113 257 4889",
    "sg:postcode":"LS28 6AT",
    "sg:province":"West Yorkshire",
    "sg:tags":[
        "pubs",
        "inn"
    ],
    "wof:name":"Punch Retail Ltd",
    "wof:placetype":"venue"
},
  "geometry": {"coordinates":[-1.6701120138,53.8049697876],"type":"Point"}
}