{
  "type": "Feature",
  "properties": {
    "iso:country":"GB",
    "sg:address":"50 Kneller Road, Brockley",
    "sg:city":"London",
    "sg:classifiers":[
        {
            "category":"Professional",
            "subcategory":"Engineering",
            "type":"Services"
        },
        {
            "category":"Retail",
            "subcategory":"Repair Shop",
            "type":"Services"
        }
    ],
    "sg:phone":"+44 20 8691 3659",
    "sg:postcode":"SE4 2AP",
    "sg:province":"Greater London",
    "sg:tags":[
        "engineer",
        "electrical",
        "maintenance",
        "contractor"
    ],
    "wof:name":"Fellows Maintenance Ltd.",
    "wof:placetype":"venue"
},
  "geometry": {"coordinates":[-0.0383539982,51.4601478577],"type":"Point"}
}