{
  "type": "Feature",
  "properties": {
    "addr:full":"166a Glyn Road London Greater London E5 0JE",
    "addr:housenumber":"166a",
    "addr:postcode":"e5 0je",
    "addr:street":"Glyn Road",
    "iso:country":"GB",
    "sg:address":"166a Glyn Road",
    "sg:city":"London",
    "sg:classifiers":[
        {
            "category":"Manufacturing",
            "subcategory":"Printing",
            "type":"Manufacturing & Wholesale Goods"
        }
    ],
    "sg:phone":"+44 20 8986 4424",
    "sg:postcode":"E5 0JE",
    "sg:province":"Greater London",
    "sg:tags":[
        "bookbinder"
    ],
    "wof:name":"Homerton Bookbinders",
    "wof:placetype":"venue"
},
  "geometry": {"coordinates":[-0.041045,51.552959],"type":"Point"}
}