{
  "type": "Feature",
  "properties": {
    "iso:country":"GB",
    "sg:address":"5 Rigbys Court",
    "sg:city":"Norwich",
    "sg:classifiers":[
        {
            "category":"Professional",
            "subcategory":"Lawyer & Legal Services",
            "type":"Services"
        }
    ],
    "sg:phone":"+44 1603 441111",
    "sg:postcode":"NR2 1NT",
    "sg:province":"Norfolk",
    "sg:tags":[
        "solicitor"
    ],
    "wof:name":"Coles",
    "wof:placetype":"venue"
},
  "geometry": {"coordinates":[1.350073,52.573448],"type":"Point"}
}