{
  "type": "Feature",
  "properties": {
    "addr:full":"66 Main Street, Wheldrake York North Yorkshire YO19 6AA",
    "addr:housenumber":"66",
    "addr:postcode":"yo19 6aa",
    "addr:street":"Main Street",
    "iso:country":"GB",
    "sg:address":"66 Main Street, Wheldrake",
    "sg:city":"York",
    "sg:classifiers":[
        {
            "category":"Farming",
            "subcategory":"Nursery",
            "type":"Manufacturing & Wholesale Goods"
        }
    ],
    "sg:phone":"+44 1904 448604",
    "sg:postcode":"YO19 6AA",
    "sg:province":"North Yorkshire",
    "sg:tags":[
        "creche"
    ],
    "wof:name":"Blythe Farm Day Nursery",
    "wof:placetype":"venue"
},
  "geometry": {"coordinates":[-1.058159,53.833401],"type":"Point"}
}