{
  "type": "Feature",
  "properties": {
    "addr:full":"Newhall Road Stoke-on-trent Staffordshire ST3 1NE",
    "addr:postcode":"st3 1ne",
    "addr:street":"Newhall Road",
    "iso:country":"GB",
    "sg:address":"Newhall Road",
    "sg:city":"Stoke-on-trent",
    "sg:classifiers":[
        {
            "category":"Retail",
            "subcategory":"Auto Repair",
            "type":"Services"
        }
    ],
    "sg:phone":"+44 1782 310757",
    "sg:postcode":"ST3 1NE",
    "sg:province":"Staffordshire",
    "sg:tags":[
        "modification",
        "garage"
    ],
    "wof:name":"Newhall Road Garage",
    "wof:placetype":"venue"
},
  "geometry": {"coordinates":[-2.120949,52.98315],"type":"Point"}
}