{
  "type": "Feature",
  "properties": {
    "addr:full":"53 Oxford Street Pontypridd Caerphilly CF37 1RU",
    "addr:housenumber":"53",
    "addr:postcode":"cf37 1ru",
    "addr:street":"Oxford Street",
    "iso:country":"GB",
    "sg:address":"53 Oxford Street",
    "sg:city":"Pontypridd",
    "sg:classifiers":[
        {
            "category":"Building & Trades",
            "subcategory":"Construction",
            "type":"Services"
        }
    ],
    "sg:postcode":"CF37 1RU",
    "sg:province":"Caerphilly",
    "sg:tags":[
        "builder"
    ],
    "wof:name":"P Allen",
    "wof:placetype":"venue"
},
  "geometry": {"coordinates":[-3.3286020756,51.5909919739],"type":"Point"}
}