{
  "type": "Feature",
  "properties": {
    "addr:full":"Unit 10 Redfern Industrial Estate, Dawson Street Hyde Cheshire SK14 1RD",
    "addr:housenumber":"unit 10;estate",
    "addr:postcode":"sk14 1rd",
    "addr:street":"Redfern Industrial;Dawson Street",
    "iso:country":"GB",
    "sg:address":"Unit 10 Redfern Industrial Estate, Dawson Street",
    "sg:city":"Hyde",
    "sg:classifiers":[
        {
            "category":"Manufacturing",
            "subcategory":"Rubber & Plastics",
            "type":"Manufacturing & Wholesale Goods"
        }
    ],
    "sg:phone":"+44 161 368 2016",
    "sg:postcode":"SK14 1RD",
    "sg:province":"Cheshire",
    "sg:tags":[
        "injection",
        "moulding"
    ],
    "wof:name":"Donlin Engineering Ltd.",
    "wof:placetype":"venue"
},
  "geometry": {"coordinates":[-2.074819,53.446045],"type":"Point"}
}