{
  "type": "Feature",
  "properties": {
    "iso:country":"GB",
    "sg:address":"73 Ferry Street",
    "sg:city":"Montrose",
    "sg:classifiers":[
        {
            "category":"Professional",
            "subcategory":"Engineering",
            "type":"Services"
        }
    ],
    "sg:phone":"+44 1674 678765",
    "sg:postcode":"DD10 8DA",
    "sg:province":"Aberdeenshire",
    "wof:name":"K M O S Ltd.",
    "wof:placetype":"venue"
},
  "geometry": {"coordinates":[-2.465522,56.706528],"type":"Point"}
}