{
  "type": "Feature",
  "properties": {
    "iso:country":"GB",
    "sg:address":"6 Grover Walk, Corringham",
    "sg:city":"Stanford-le-hope",
    "sg:classifiers":[
        {
            "category":"Shopping",
            "subcategory":"News",
            "type":"Retail Goods"
        }
    ],
    "sg:postcode":"SS17 7LY",
    "sg:province":"Essex",
    "sg:tags":[
        "newsagent"
    ],
    "wof:name":"Eagle News",
    "wof:placetype":"venue"
},
  "geometry": {"coordinates":[0.427798,51.513992],"type":"Point"}
}