{
  "type": "Feature",
  "properties": {
    "addr:full":"1 Hastings Street Luton Bedfordshire LU1 5BA",
    "addr:housenumber":"1",
    "addr:postcode":"lu1 5ba",
    "addr:street":"Hastings Street",
    "iso:country":"GB",
    "sg:address":"1 Hastings Street",
    "sg:city":"Luton",
    "sg:classifiers":[
        {
            "category":"Communications",
            "type":"Services"
        }
    ],
    "sg:phone":"+44 1582 637400",
    "sg:postcode":"LU1 5BA",
    "sg:province":"Bedfordshire",
    "sg:tags":[
        "broadcasting"
    ],
    "wof:name":"Bbc Three Counties Radio",
    "wof:placetype":"venue"
},
  "geometry": {"coordinates":[-0.418869,51.877151],"type":"Point"}
}