{
  "type": "Feature",
  "properties": {
    "addr:full":"Unit 22, Solent Industrial Estate, Hedge End Southampton Hampshire SO30 2FX",
    "addr:housenumber":"unit 22",
    "addr:postcode":"so30 2fx",
    "addr:street":"Solent Industrial Estate",
    "iso:country":"GB",
    "sg:address":"Unit 22, Solent Industrial Estate, Hedge End",
    "sg:city":"Southampton",
    "sg:classifiers":[
        {
            "category":"Manufacturing",
            "subcategory":"Metals",
            "type":"Manufacturing & Wholesale Goods"
        }
    ],
    "sg:phone":"+44 1489 788810",
    "sg:postcode":"SO30 2FX",
    "sg:province":"Hampshire",
    "sg:tags":[
        "steel",
        "fabricator",
        "erectors"
    ],
    "wof:name":"The Southampton Steel Joist Co",
    "wof:placetype":"venue"
},
  "geometry": {"coordinates":[-1.30325,50.924629],"type":"Point"}
}