{
  "type": "Feature",
  "properties": {
    "addr:full":"17 Elgar Close Uxbridge Greater London UB10 8HN",
    "addr:housenumber":"17",
    "addr:postcode":"ub10 8hn",
    "addr:street":"Elgar Close",
    "iso:country":"GB",
    "sg:address":"17 Elgar Close",
    "sg:city":"Uxbridge",
    "sg:classifiers":[
        {
            "category":"Building & Trades",
            "subcategory":"Plumbing",
            "type":"Services"
        }
    ],
    "sg:phone":"+44 1895 636076",
    "sg:postcode":"UB10 8HN",
    "sg:province":"Greater London",
    "sg:tags":[
        "heating"
    ],
    "wof:name":"Emergency Plumbing",
    "wof:placetype":"venue"
},
  "geometry": {"coordinates":[-0.456062,51.568314],"type":"Point"}
}