{
  "type": "Feature",
  "properties": {
    "addr:full":"Doveridge, South St Colyton Devon EX24 6PS",
    "addr:postcode":"ex24 6ps",
    "addr:street":"St",
    "iso:country":"GB",
    "sg:address":"Doveridge, South St",
    "sg:city":"Colyton",
    "sg:classifiers":[
        {
            "category":"Health Services",
            "subcategory":"Nursing And Care Facility",
            "type":"Services"
        }
    ],
    "sg:phone":"+44 1297 553811",
    "sg:postcode":"EX24 6PS",
    "sg:province":"Devon",
    "sg:tags":[
        "home"
    ],
    "wof:name":"Dovecare Domicilliary Care Services",
    "wof:placetype":"venue"
},
  "geometry": {"coordinates":[-3.070244,50.740337],"type":"Point"}
}