{
  "type": "Feature",
  "properties": {
    "iso:country":"GB",
    "sg:address":"The Counting Ho, 61 Charlotte St, St. Pauls Sq",
    "sg:city":"Birmingham",
    "sg:classifiers":[
        {
            "category":"Professional",
            "subcategory":"Business Services",
            "type":"Services"
        }
    ],
    "sg:postcode":"B3 1PX",
    "sg:province":"West Midlands",
    "sg:tags":[
        "planning",
        "supervisor"
    ],
    "wof:name":"Francis Projects Ltd",
    "wof:placetype":"venue"
},
  "geometry": {"coordinates":[-1.9060499668,52.4843788147],"type":"Point"}
}