{
  "type": "Feature",
  "properties": {
    "iso:country":"GB",
    "sg:address":"66 Bloomfield Avenue",
    "sg:city":"Luton",
    "sg:classifiers":[
        {
            "category":"Health Services",
            "subcategory":"Hospice",
            "type":"Services"
        }
    ],
    "sg:phone":"+44 1582 488425",
    "sg:postcode":"LU2 0PU",
    "sg:province":"Bedfordshire",
    "wof:name":"Hospice at Home Volunteers",
    "wof:placetype":"venue"
},
  "geometry": {"coordinates":[-0.39517,51.890392],"type":"Point"}
}