{
  "type": "Feature",
  "properties": {
    "addr:full":"199 County Road, Walton Liverpool Merseyside L4 5PB",
    "addr:housenumber":"199",
    "addr:postcode":"l4 5pb",
    "addr:street":"County Road",
    "iso:country":"GB",
    "sg:address":"199 County Road, Walton",
    "sg:city":"Liverpool",
    "sg:classifiers":[
        {
            "category":"Home & Garden",
            "subcategory":"Home Furnishings",
            "type":"Retail Goods"
        },
        {
            "category":"Building & Trades",
            "subcategory":"Construction",
            "type":"Services"
        }
    ],
    "sg:postcode":"L4 5PB",
    "sg:province":"Merseyside",
    "sg:tags":[
        "mantelpiece",
        "joinery",
        "fireplace",
        "carpentry"
    ],
    "wof:name":"D R G CARPENTRY",
    "wof:placetype":"venue"
},
  "geometry": {"coordinates":[-2.969637,53.444118],"type":"Point"}
}