{
  "type": "Feature",
  "properties": {
    "addr:full":"Bartholomew Av Goole East Riding of Yorkshire DN14 6AW",
    "addr:postcode":"dn14 6aw",
    "addr:street":"Bartholomew Av Goole",
    "iso:country":"GB",
    "sg:address":"Bartholomew Av",
    "sg:city":"Goole",
    "sg:classifiers":[
        {
            "category":"Health Services",
            "subcategory":"Nursing And Care Facility",
            "type":"Services"
        }
    ],
    "sg:phone":"+44 1405 763749",
    "sg:postcode":"DN14 6AW",
    "sg:province":"East Riding of Yorkshire",
    "sg:tags":[
        "home"
    ],
    "wof:name":"Windsor Court",
    "wof:placetype":"venue"
},
  "geometry": {"coordinates":[-0.882384,53.70747],"type":"Point"}
}