{
  "type": "Feature",
  "properties": {
    "iso:country":"GB",
    "sg:address":"Langham House, 302 Regent Street",
    "sg:city":"London",
    "sg:classifiers":[
        {
            "category":"Education",
            "subcategory":"Special Training",
            "type":"Public Place"
        }
    ],
    "sg:phone":"+44 20 7625 5211",
    "sg:postcode":"W1B 3HH",
    "sg:province":"Greater London",
    "sg:tags":[
        "product",
        "centre"
    ],
    "wof:name":"National Association of Paralegals Vocational Offi",
    "wof:placetype":"venue"
},
  "geometry": {"coordinates":[-0.142385,51.516544],"type":"Point"}
}