{
  "type": "Feature",
  "properties": {
    "iso:country":"GB",
    "sg:address":"185a Warwick Road",
    "sg:city":"Solihull",
    "sg:classifiers":[
        {
            "category":"Manufacturing",
            "subcategory":"Tools & Machinery",
            "type":"Manufacturing & Wholesale Goods"
        },
        {
            "category":"Insurance",
            "subcategory":"Insurance Agent",
            "type":"Services"
        }
    ],
    "sg:phone":"+44 121 706 1980",
    "sg:postcode":"B92 7AW",
    "sg:province":"West Midlands",
    "sg:tags":[
        "society",
        "friendly"
    ],
    "wof:name":"Property & General Insurance Consultants Ltd.",
    "wof:placetype":"venue"
},
  "geometry": {"coordinates":[-1.804448,52.436932],"type":"Point"}
}