{
  "type": "Feature",
  "properties": {
    "addr:full":"Granada Trading Estate, Park St Oldbury West Midlands B69 4LD",
    "addr:postcode":"b69 4ld",
    "addr:street":"Trading Estate Park St",
    "iso:country":"GB",
    "sg:address":"Granada Trading Estate, Park St",
    "sg:city":"Oldbury",
    "sg:classifiers":[
        {
            "category":"Manufacturing",
            "subcategory":"Metals",
            "type":"Manufacturing & Wholesale Goods"
        }
    ],
    "sg:phone":"+44 121 552 4359",
    "sg:postcode":"B69 4LD",
    "sg:province":"West Midlands",
    "sg:tags":[
        "die-casting"
    ],
    "wof:name":"Industrial Impregnations",
    "wof:placetype":"venue"
},
  "geometry": {"coordinates":[-2.017314,52.497925],"type":"Point"}
}