{
  "type": "Feature",
  "properties": {
    "addr:full":"150 Goldhawk Road London Greater London W12 8HH",
    "addr:housenumber":"150",
    "addr:postcode":"w12 8hh",
    "addr:street":"Goldhawk Road",
    "iso:country":"GB",
    "sg:address":"150 Goldhawk Road",
    "sg:city":"London",
    "sg:classifiers":[
        {
            "category":"Communications",
            "subcategory":"Film & Video Production",
            "type":"Services"
        }
    ],
    "sg:phone":"+44 20 8932 3200",
    "sg:postcode":"W12 8HH",
    "sg:province":"Greater London",
    "sg:tags":[
        "recording",
        "studio"
    ],
    "wof:name":"The Town House",
    "wof:placetype":"venue"
},
  "geometry": {"coordinates":[-0.2316900045,51.5014762878],"type":"Point"}
}