{
  "type": "Feature",
  "properties": {
    "addr:full":"101 St Helens Avenue, Benson Wallingford Oxfordshire OX10 6RU",
    "addr:housenumber":"101",
    "addr:postcode":"ox10 6ru",
    "addr:street":"St Helens Avenue",
    "iso:country":"GB",
    "sg:address":"101 St Helens Avenue, Benson",
    "sg:city":"Wallingford",
    "sg:classifiers":[
        {
            "category":"Professional",
            "subcategory":"Employment Agencies",
            "type":"Services"
        }
    ],
    "sg:postcode":"OX10 6RU",
    "sg:province":"Oxfordshire",
    "sg:tags":[
        "agricultural",
        "advice"
    ],
    "wof:name":"P C Beable",
    "wof:placetype":"venue"
},
  "geometry": {"coordinates":[-1.1067249775,51.6179580688],"type":"Point"}
}