{
  "type": "Feature",
  "properties": {
    "iso:country":"GB",
    "sg:address":"Middlehill, Clova",
    "sg:city":"Kirriemuir",
    "sg:classifiers":[
        {
            "category":"Farming",
            "subcategory":"Livestock Farm",
            "type":"Manufacturing & Wholesale Goods"
        },
        {
            "category":"Farming",
            "subcategory":"Farm",
            "type":"Manufacturing & Wholesale Goods"
        }
    ],
    "sg:phone":"+44 1575 540262",
    "sg:postcode":"DD8 4QP",
    "sg:province":"Angus",
    "sg:tags":[
        "mixed",
        "crop",
        "others"
    ],
    "wof:name":"Donald Robertson Hood",
    "wof:placetype":"venue"
},
  "geometry": {"coordinates":[-2.9983489513,56.67552948],"type":"Point"}
}