{
  "type": "Feature",
  "properties": {
    "iso:country":"GB",
    "sg:address":"High Street",
    "sg:city":"Bishops Stortford",
    "sg:classifiers":[
        {
            "category":"Professional",
            "subcategory":"Lawyer & Legal Services",
            "type":"Services"
        }
    ],
    "sg:phone":"+44 1279 755200",
    "sg:postcode":"CM23 2LU",
    "sg:province":"Essex",
    "sg:tags":[
        "solicitor"
    ],
    "wof:name":"Stanley Tee & Co.",
    "wof:placetype":"venue"
},
  "geometry": {"coordinates":[0.158173,51.871273],"type":"Point"}
}