{
  "type": "Feature",
  "properties": {
    "addr:full":"Balkholme Hall, Balkholme Goole East Riding of Yorkshire DN14 7XH",
    "addr:postcode":"dn14 7xh",
    "addr:street":"Balkholme",
    "iso:country":"GB",
    "sg:address":"Balkholme Hall, Balkholme",
    "sg:city":"Goole",
    "sg:classifiers":[
        {
            "category":"Farming",
            "subcategory":"Livestock Farm",
            "type":"Manufacturing & Wholesale Goods"
        }
    ],
    "sg:phone":"+44 1430 410332",
    "sg:postcode":"DN14 7XH",
    "sg:province":"East Riding of Yorkshire",
    "sg:tags":[
        "breeder"
    ],
    "wof:name":"Edward Wright",
    "wof:placetype":"venue"
},
  "geometry": {"coordinates":[-0.805701,53.74369],"type":"Point"}
}