{
  "type": "Feature",
  "properties": {
    "iso:country":"GB",
    "sg:address":"1-3 Prince Of Wales Road",
    "sg:city":"Cromer",
    "sg:classifiers":[
        {
            "category":"Retail",
            "subcategory":"Auto Repair",
            "type":"Services"
        }
    ],
    "sg:phone":"+44 1263 514858",
    "sg:postcode":"NR27 9HR",
    "sg:province":"Norfolk",
    "sg:tags":[
        "modification",
        "garage"
    ],
    "wof:name":"R  & B  Autos Ltd.",
    "wof:placetype":"venue"
},
  "geometry": {"coordinates":[1.298347,52.932549],"type":"Point"}
}