{
  "type": "Feature",
  "properties": {
    "addr:full":"Unit 7 Mullacott Cross Industri, Al Estate Ilfracombe Devon EX34 8PL",
    "addr:housenumber":"unit 7",
    "addr:postcode":"ex34 8pl",
    "addr:street":"Mullacott Cross Industri Al Estate",
    "iso:country":"GB",
    "sg:address":"Unit 7 Mullacott Cross Industri, Al Estate",
    "sg:city":"Ilfracombe",
    "sg:classifiers":[
        {
            "category":"Retail",
            "subcategory":"Auto Repair",
            "type":"Services"
        }
    ],
    "sg:phone":"+44 1271 863321",
    "sg:postcode":"EX34 8PL",
    "sg:province":"Devon",
    "sg:tags":[
        "body",
        "garage",
        "modification",
        "car"
    ],
    "wof:name":"Mullacott Cross Accident Repair Centre",
    "wof:placetype":"venue"
},
  "geometry": {"coordinates":[-4.126199,51.178886],"type":"Point"}
}