{
  "type": "Feature",
  "properties": {
    "addr:full":"479-481 Stratford Rd Birmingham West Midlands B11 4LE",
    "addr:housenumber":"479-481",
    "addr:postcode":"b11 4le",
    "addr:street":"Stratford Rd",
    "iso:country":"GB",
    "sg:address":"479-481 Stratford Rd",
    "sg:city":"Birmingham",
    "sg:classifiers":[
        {
            "category":"Food & Beverages",
            "subcategory":"Supermarket",
            "type":"Retail Goods"
        }
    ],
    "sg:phone":"+44 121 772 1384",
    "sg:postcode":"B11 4LE",
    "sg:province":"West Midlands",
    "wof:name":"Paylo Discount",
    "wof:placetype":"venue"
},
  "geometry": {"coordinates":[-1.8671319485,52.4545898438],"type":"Point"}
}