{
  "type": "Feature",
  "properties": {
    "addr:full":"Dearne Valley Technical Park, Pontefract Road, Broomhill Barnsley South Yorkshire S73 0YG",
    "addr:postcode":"s73 0yg",
    "addr:street":"Dearne;Pontefract Road;Yorkshire",
    "iso:country":"GB",
    "sg:address":"Dearne Valley Technical Park, Pontefract Road, Broomhill",
    "sg:city":"Barnsley",
    "sg:classifiers":[
        {
            "category":"Professional",
            "subcategory":"Engineering",
            "type":"Services"
        }
    ],
    "sg:phone":"+44 1226 270564",
    "sg:postcode":"S73 0YG",
    "sg:province":"South Yorkshire",
    "wof:name":"Manvers Engineering Ltd.",
    "wof:placetype":"venue"
},
  "geometry": {"coordinates":[-1.3835949898,53.5148162842],"type":"Point"}
}