{
  "type": "Feature",
  "properties": {
    "addr:full":"Unit 1 Kilbury Drive Worcester Worcestershire WR5 2NE",
    "addr:housenumber":"unit 1",
    "addr:postcode":"wr5 2ne",
    "addr:street":"Kilbury Drive",
    "iso:country":"GB",
    "sg:address":"Unit 1 Kilbury Drive",
    "sg:city":"Worcester",
    "sg:classifiers":[
        {
            "category":"Shopping",
            "subcategory":"News",
            "type":"Retail Goods"
        }
    ],
    "sg:postcode":"WR5 2NE",
    "sg:province":"Worcestershire",
    "sg:tags":[
        "newsagent"
    ],
    "wof:name":"Butterworths",
    "wof:placetype":"venue"
},
  "geometry": {"coordinates":[-2.1834409237,52.1827278137],"type":"Point"}
}