{
  "type": "Feature",
  "properties": {
    "addr:full":"20 Princess Road, Regents Park London Greater London NW1 8JJ",
    "addr:housenumber":"20",
    "addr:postcode":"nw1 8jj",
    "addr:street":"Princess Road",
    "iso:country":"GB",
    "sg:address":"20 Princess Road, Regents Park",
    "sg:city":"London",
    "sg:classifiers":[
        {
            "category":"Organizations",
            "subcategory":"Non-profit Organization",
            "type":"Services"
        }
    ],
    "sg:phone":"+44 20 7722 4461",
    "sg:postcode":"NW1 8JJ",
    "sg:province":"Greater London",
    "sg:tags":[
        "organisation",
        "voluntary",
        "charity"
    ],
    "wof:name":"Keratec",
    "wof:placetype":"venue"
},
  "geometry": {"coordinates":[-0.152054,51.538902],"type":"Point"}
}