{
  "type": "Feature",
  "properties": {
    "addr:full":"Wigan Road, Leyland Preston Lancashire PR5 2UD",
    "addr:postcode":"pr5 2ud",
    "addr:street":"Wigan Road",
    "iso:country":"GB",
    "sg:address":"Wigan Road, Leyland",
    "sg:city":"Preston",
    "sg:classifiers":[
        {
            "category":"Building & Trades",
            "subcategory":"Landscaping Services",
            "type":"Services"
        }
    ],
    "sg:phone":"+44 1772 422044",
    "sg:postcode":"PR5 2UD",
    "sg:province":"Lancashire",
    "sg:tags":[
        "landscape",
        "contractor"
    ],
    "wof:name":"J Mallinson (Ormskirk) Ltd.",
    "wof:placetype":"venue"
},
  "geometry": {"coordinates":[-2.69349,53.695339],"type":"Point"}
}