{
  "type": "Feature",
  "properties": {
    "iso:country":"GB",
    "sg:address":"Sandsclose, Moresby Pks",
    "sg:city":"Whitehaven",
    "sg:classifiers":[
        {
            "category":"Home & Garden",
            "subcategory":"Garden Supply",
            "type":"Retail Goods"
        },
        {
            "category":"Farming",
            "subcategory":"Farm",
            "type":"Manufacturing & Wholesale Goods"
        }
    ],
    "sg:postcode":"CA28 8XU",
    "sg:province":"Cumbria",
    "sg:tags":[
        "mixed",
        "bulb",
        "crop",
        "grower"
    ],
    "wof:name":"D C & A Fisher",
    "wof:placetype":"venue"
},
  "geometry": {"coordinates":[-3.556414,54.544064],"type":"Point"}
}