{
  "type": "Feature",
  "properties": {
    "addr:full":"64 Fallside Road, Bothwell Glasgow Glasgow City G71 8BG",
    "addr:housenumber":"64",
    "addr:postcode":"g71 8bg",
    "addr:street":"Fallside Road",
    "iso:country":"GB",
    "sg:address":"64 Fallside Road, Bothwell",
    "sg:city":"Glasgow",
    "sg:classifiers":[
        {
            "category":"Freight",
            "type":"Transportation"
        }
    ],
    "sg:phone":"+44 1698 811886",
    "sg:postcode":"G71 8BG",
    "sg:province":"Glasgow City",
    "sg:tags":[
        "haulage",
        "road"
    ],
    "wof:name":"Mainline Haulage Ltd.",
    "wof:placetype":"venue"
},
  "geometry": {"coordinates":[-4.064761,55.813992],"type":"Point"}
}