{
  "type": "Feature",
  "properties": {
    "iso:country":"GB",
    "sg:address":"G & B Corner, Blackbird Road, Ravensbridge Drive",
    "sg:city":"Leicester",
    "sg:classifiers":[
        {
            "category":"Shopping",
            "subcategory":"Stationery & Office Supplies",
            "type":"Retail Goods"
        },
        {
            "category":"Shopping",
            "subcategory":"Computers & Home Electronics",
            "type":"Retail Goods"
        }
    ],
    "sg:phone":"+44 116 251 9933",
    "sg:postcode":"LE4 0BX",
    "sg:province":"Leicestershire",
    "sg:tags":[
        "equipment",
        "consumables"
    ],
    "wof:name":"G & B Office Services Group Ltd.",
    "wof:placetype":"venue"
},
  "geometry": {"coordinates":[-1.1458400488,52.6472206116],"type":"Point"}
}