{
  "type": "Feature",
  "properties": {
    "addr:full":"Southfield Road Loughborough Leicestershire LE11 2TU",
    "addr:postcode":"le11 2tu",
    "addr:street":"Southfield Road",
    "iso:country":"GB",
    "sg:address":"Southfield Road",
    "sg:city":"Loughborough",
    "sg:classifiers":[
        {
            "category":"Government",
            "subcategory":"Office",
            "type":"Public Place"
        }
    ],
    "sg:phone":"+44 1509 263151",
    "sg:postcode":"LE11 2TU",
    "sg:province":"Leicestershire",
    "sg:tags":[
        "local"
    ],
    "wof:name":"CHARNWOOD BOROUGH COUNCIL",
    "wof:placetype":"venue"
},
  "geometry": {"coordinates":[-1.205824,52.76886],"type":"Point"}
}