{
  "type": "Feature",
  "properties": {
    "addr:full":"33 Shopping Precinct, Palace Gardens Enfield Greater London EN2 6SN",
    "addr:postcode":"en2 6sn",
    "addr:street":"Palace Gardens",
    "iso:country":"GB",
    "sg:address":"33 Shopping Precinct, Palace Gardens",
    "sg:city":"Enfield",
    "sg:classifiers":[
        {
            "category":"Shopping",
            "subcategory":"Bicycles & Sporting Goods",
            "type":"Retail Goods"
        },
        {
            "category":"Sports & Exercise",
            "subcategory":"Sports Center",
            "type":"Entertainment"
        }
    ],
    "sg:phone":"+44 20 8367 7697",
    "sg:postcode":"EN2 6SN",
    "sg:province":"Greater London",
    "sg:tags":[
        "shop",
        "sale"
    ],
    "sg:website":"http://www.jjb.co.uk",
    "wof:name":"J J B Sports Plc",
    "wof:placetype":"venue"
},
  "geometry": {"coordinates":[-0.087649,51.653107],"type":"Point"}
}