{
  "type": "Feature",
  "properties": {
    "addr:full":"Coppice Ho, 5 Coppice Mead Hitchin Bedfordshire SG5 4JX",
    "addr:housenumber":"5",
    "addr:postcode":"sg5 4jx",
    "addr:street":"Coppice Mead",
    "iso:country":"GB",
    "sg:address":"Coppice Ho, 5 Coppice Mead",
    "sg:city":"Hitchin",
    "sg:classifiers":[
        {
            "category":"Communications",
            "type":"Services"
        }
    ],
    "sg:phone":"+44 1462 730152",
    "sg:postcode":"SG5 4JX",
    "sg:province":"Bedfordshire",
    "sg:tags":[
        "system",
        "music",
        "public",
        "address"
    ],
    "wof:name":"Mobile Electronics Ltd",
    "wof:placetype":"venue"
},
  "geometry": {"coordinates":[-0.2844080031,51.9524345398],"type":"Point"}
}