{
  "type": "Feature",
  "properties": {
    "iso:country":"GB",
    "sg:address":"Battle Rd",
    "sg:city":"St Leonards On Sea",
    "sg:classifiers":[
        {
            "category":"Place Of Worship",
            "type":"Public Place"
        }
    ],
    "sg:phone":"+44 1424 422350",
    "sg:postcode":"TN37 7BE",
    "sg:province":"East Sussex",
    "wof:name":"Hollington Methodist Church",
    "wof:placetype":"venue"
},
  "geometry": {"coordinates":[0.5416849852,50.8891334534],"type":"Point"}
}