{
  "type": "Feature",
  "properties": {
    "addr:full":"436 London Rd Grays Essex RM20 4DB",
    "addr:housenumber":"436",
    "addr:postcode":"rm20 4db",
    "addr:street":"London Rd",
    "iso:country":"GB",
    "sg:address":"436 London Rd",
    "sg:city":"Grays",
    "sg:classifiers":[
        {
            "category":"Freight",
            "type":"Transportation"
        }
    ],
    "sg:phone":"+44 1375 393856",
    "sg:postcode":"RM20 4DB",
    "sg:province":"Essex",
    "sg:tags":[
        "haulage",
        "road"
    ],
    "wof:name":"Jackson Contracts",
    "wof:placetype":"venue"
},
  "geometry": {"coordinates":[0.2962670028,51.477104187],"type":"Point"}
}