{
  "type": "Feature",
  "properties": {
    "addr:full":"17 Newtown Road Highbridge Somerset TA9 3HX",
    "addr:housenumber":"17",
    "addr:postcode":"ta9 3hx",
    "addr:street":"Newtown Road",
    "iso:country":"GB",
    "sg:address":"17 Newtown Road",
    "sg:city":"Highbridge",
    "sg:classifiers":[
        {
            "category":"Bars & Pubs",
            "type":"Food & Drink"
        }
    ],
    "sg:phone":"+44 1278 783440",
    "sg:postcode":"TA9 3HX",
    "sg:province":"Somerset",
    "sg:tags":[
        "pubs",
        "inn"
    ],
    "wof:name":"The Globe Inn",
    "wof:placetype":"venue"
},
  "geometry": {"coordinates":[-2.977818,51.220722],"type":"Point"}
}