{
  "type": "Feature",
  "properties": {
    "addr:full":"Mill Wynd Haddington East Lothian EH41 4DB",
    "addr:postcode":"eh41 4db",
    "addr:street":"Mill Wynd",
    "iso:country":"GB",
    "sg:address":"Mill Wynd",
    "sg:city":"Haddington",
    "sg:classifiers":[
        {
            "category":"Community Center",
            "type":"Public Place"
        },
        {
            "category":"Government",
            "subcategory":"Office",
            "type":"Public Place"
        }
    ],
    "sg:phone":"+44 1620 826800",
    "sg:postcode":"EH41 4DB",
    "sg:province":"East Lothian",
    "sg:tags":[
        "recreation",
        "local",
        "leisure",
        "centre"
    ],
    "wof:name":"Aubigny Sports Centre",
    "wof:placetype":"venue"
},
  "geometry": {"coordinates":[-2.778129,55.95203],"type":"Point"}
}