{
  "type": "Feature",
  "properties": {
    "iso:country":"GB",
    "sg:address":"Unit 68, North Western St",
    "sg:city":"Manchester",
    "sg:classifiers":[
        {
            "category":"Wholesale",
            "subcategory":"Furniture",
            "type":"Manufacturing & Wholesale Goods"
        }
    ],
    "sg:phone":"+44 161 273 2088",
    "sg:postcode":"M12 6DX",
    "sg:province":"Greater Manchester",
    "sg:tags":[
        "shop",
        "fitting"
    ],
    "wof:name":"Shopmate Design",
    "wof:placetype":"venue"
},
  "geometry": {"coordinates":[-2.22389,53.476048],"type":"Point"}
}