{
  "type": "Feature",
  "properties": {
    "addr:full":"16 High Street Welshpool Shropshire SY21 7JP",
    "addr:housenumber":"16",
    "addr:postcode":"sy21 7jp",
    "addr:street":"High Street",
    "iso:country":"GB",
    "sg:address":"16 High Street",
    "sg:city":"Welshpool",
    "sg:classifiers":[
        {
            "category":"Bars & Pubs",
            "type":"Food & Drink"
        }
    ],
    "sg:phone":"+44 1938 553711",
    "sg:postcode":"SY21 7JP",
    "sg:province":"Shropshire",
    "sg:tags":[
        "pubs",
        "inn"
    ],
    "wof:name":"Kevin & Adele Anthony",
    "wof:placetype":"venue"
},
  "geometry": {"coordinates":[-3.150841,52.66058],"type":"Point"}
}