{
  "type": "Feature",
  "properties": {
    "iso:country":"GB",
    "sg:address":"Nursling Street, Nursling",
    "sg:city":"Southampton",
    "sg:classifiers":[
        {
            "category":"Education",
            "subcategory":"School",
            "type":"Public Place"
        }
    ],
    "sg:phone":"+44 23 8073 2289",
    "sg:postcode":"SO16 0XH",
    "sg:province":"Hampshire",
    "sg:tags":[
        "local",
        "authority"
    ],
    "wof:name":"Nursling Primary School",
    "wof:placetype":"venue"
},
  "geometry": {"coordinates":[-1.4726890326,50.9449462891],"type":"Point"}
}