{
  "type": "Feature",
  "properties": {
    "addr:full":"New Street Llanelli Carmarthenshire SA15 2BS",
    "addr:postcode":"sa15 2bs",
    "addr:street":"New Street",
    "iso:country":"GB",
    "sg:address":"New Street",
    "sg:city":"Llanelli",
    "sg:classifiers":[
        {
            "category":"Bars & Pubs",
            "type":"Food & Drink"
        }
    ],
    "sg:phone":"+44 1554 776155",
    "sg:postcode":"SA15 2BS",
    "sg:province":"Carmarthenshire",
    "sg:tags":[
        "pubs",
        "house",
        "inn",
        "public",
        "activity"
    ],
    "wof:name":"Biddulph Arms",
    "wof:placetype":"venue"
},
  "geometry": {"coordinates":[-4.1515040398,51.6685447693],"type":"Point"}
}