{
  "type": "Feature",
  "properties": {
    "addr:full":"371-373 Holland Rd, Holland On Sea Clacton On Sea Essex CO15 6PD",
    "addr:housenumber":"371-373",
    "addr:postcode":"co15 6pd",
    "addr:street":"Holland Rd",
    "iso:country":"GB",
    "sg:address":"371-373 Holland Rd, Holland On Sea",
    "sg:city":"Clacton On Sea",
    "sg:classifiers":[
        {
            "category":"Social Services",
            "type":"Services"
        }
    ],
    "sg:phone":"+44 1255 813481",
    "sg:postcode":"CO15 6PD",
    "sg:province":"Essex",
    "sg:tags":[
        "disability"
    ],
    "wof:name":"Michael Tosh Mobility Vehicles",
    "wof:placetype":"venue"
},
  "geometry": {"coordinates":[1.181372,51.80291],"type":"Point"}
}