{
  "type": "Feature",
  "properties": {
    "addr:full":"243 Upper Rainham Road Hornchurch Essex RM12 4EY",
    "addr:housenumber":"243",
    "addr:postcode":"rm12 4ey",
    "addr:street":"Upper Rainham Road",
    "iso:country":"GB",
    "sg:address":"243 Upper Rainham Road",
    "sg:city":"Hornchurch",
    "sg:classifiers":[
        {
            "category":"Building & Trades",
            "subcategory":"Construction",
            "type":"Services"
        }
    ],
    "sg:postcode":"RM12 4EY",
    "sg:province":"Essex",
    "sg:tags":[
        "builder"
    ],
    "wof:name":"M P Brown Builders",
    "wof:placetype":"venue"
},
  "geometry": {"coordinates":[0.1892970055,51.55676651],"type":"Point"}
}