{
  "type": "Feature",
  "properties": {
    "addr:full":"60 Magdalen Road Oxford Oxfordshire OX4 1RB",
    "addr:housenumber":"60",
    "addr:postcode":"ox4 1rb",
    "addr:street":"Magdalen Road",
    "iso:country":"GB",
    "sg:address":"60 Magdalen Road",
    "sg:city":"Oxford",
    "sg:classifiers":[
        {
            "category":"Organizations",
            "subcategory":"Non-profit Organization",
            "type":"Services"
        }
    ],
    "sg:phone":"+44 1865 722122",
    "sg:postcode":"OX4 1RB",
    "sg:province":"Oxfordshire",
    "sg:tags":[
        "organisation",
        "voluntary",
        "charity"
    ],
    "wof:name":"The Samaritans",
    "wof:placetype":"venue"
},
  "geometry": {"coordinates":[-1.2370749712,51.741481781],"type":"Point"}
}