{
  "type": "Feature",
  "properties": {
    "addr:full":"Ash Grove Mold Denbighshire CH7 1XG",
    "addr:postcode":"ch7 1xg",
    "addr:street":"Ash Grove",
    "iso:country":"GB",
    "sg:address":"Ash Grove",
    "sg:city":"Mold",
    "sg:classifiers":[
        {
            "category":"Health Services",
            "subcategory":"Hospital",
            "type":"Services"
        }
    ],
    "sg:phone":"+44 1352 758744",
    "sg:postcode":"CH7 1XG",
    "sg:province":"Denbighshire",
    "wof:name":"Mold Community Hospital",
    "wof:placetype":"venue"
},
  "geometry": {"coordinates":[-3.1491498947,53.1688652039],"type":"Point"}
}