{
  "type": "Feature",
  "properties": {
    "addr:full":"South End, Goxhill Barrow-upon-humber Lincolnshire DN19 7NA",
    "addr:postcode":"dn19 7na",
    "addr:street":"Barrow-Upon-Humber",
    "iso:country":"GB",
    "sg:address":"South End, Goxhill",
    "sg:city":"Barrow-upon-humber",
    "sg:classifiers":[
        {
            "category":"Structure",
            "subcategory":"Warehouse",
            "type":"Public Place"
        }
    ],
    "sg:phone":"+44 1469 530345",
    "sg:postcode":"DN19 7NA",
    "sg:province":"Lincolnshire",
    "wof:name":"S J Barrick Ltd.",
    "wof:placetype":"venue"
},
  "geometry": {"coordinates":[-0.326049,53.670254],"type":"Point"}
}