{
  "type": "Feature",
  "properties": {
    "iso:country":"GB",
    "sg:address":"26 Lord Street",
    "sg:city":"Liverpool",
    "sg:classifiers":[
        {
            "category":"Retail",
            "subcategory":"Photofinishing",
            "type":"Services"
        }
    ],
    "sg:phone":"+44 151 709 3136",
    "sg:postcode":"L2 1TA",
    "sg:province":"Merseyside",
    "sg:tags":[
        "photographic",
        "processor"
    ],
    "wof:name":"The Print Inn",
    "wof:placetype":"venue"
},
  "geometry": {"coordinates":[-2.988581,53.405132],"type":"Point"}
}