{
  "type": "Feature",
  "properties": {
    "iso:country":"GB",
    "sg:address":"50 Walter Road",
    "sg:city":"Swansea",
    "sg:classifiers":[
        {
            "category":"Professional",
            "subcategory":"Engineering",
            "type":"Services"
        }
    ],
    "sg:phone":"+44 1792 460049",
    "sg:postcode":"SA1 5PW",
    "sg:province":"Neath Port Talbot",
    "sg:tags":[
        "consulting",
        "engineer"
    ],
    "wof:name":"Alan Sutton & Co",
    "wof:placetype":"venue"
},
  "geometry": {"coordinates":[-3.9579460621,51.6189804077],"type":"Point"}
}