{
  "type": "Feature",
  "properties": {
    "addr:full":"998 Foleshill Rd Coventry Warwickshire CV6 6EN",
    "addr:housenumber":"998",
    "addr:postcode":"cv6 6en",
    "addr:street":"Foleshill Rd",
    "iso:country":"GB",
    "sg:address":"998 Foleshill Rd",
    "sg:city":"Coventry",
    "sg:classifiers":[
        {
            "category":"Personal",
            "subcategory":"Day Spa",
            "type":"Services"
        }
    ],
    "sg:postcode":"CV6 6EN",
    "sg:province":"Warwickshire",
    "sg:tags":[
        "whirlpool"
    ],
    "wof:name":"Multi-Spas & Aire-Spas Uk",
    "wof:placetype":"venue"
},
  "geometry": {"coordinates":[-1.4898890257,52.4423713684],"type":"Point"}
}