{
  "type": "Feature",
  "properties": {
    "iso:country":"GB",
    "sg:address":"Prince Morris House, Unit 5 Bumpers Farm Industrial Estate",
    "sg:city":"Chippenham",
    "sg:classifiers":[
        {
            "category":"Professional",
            "subcategory":"Business Services",
            "type":"Services"
        }
    ],
    "sg:phone":"+44 1249 445526",
    "sg:postcode":"SN14 6LH",
    "sg:province":"Gloucestershire",
    "sg:tags":[
        "import",
        "export",
        "agent"
    ],
    "wof:name":"International Furnishing Concept",
    "wof:placetype":"venue"
},
  "geometry": {"coordinates":[-2.142954,51.468189],"type":"Point"}
}