{
  "type": "Feature",
  "properties": {
    "iso:country":"GB",
    "sg:address":"112 Fraser Avenue",
    "sg:city":"Inverkeithing",
    "sg:classifiers":[
        {
            "category":"Food & Beverages",
            "subcategory":"Fruits & Vegetables",
            "type":"Retail Goods"
        },
        {
            "category":"Food & Beverages",
            "subcategory":"Groceries & Convenience Stores",
            "type":"Retail Goods"
        }
    ],
    "sg:phone":"+44 1383 412979",
    "sg:postcode":"KY11 1EH",
    "sg:province":"Fife",
    "sg:tags":[
        "grocer",
        "greengrocer"
    ],
    "wof:name":"Shad Superstore",
    "wof:placetype":"venue"
},
  "geometry": {"coordinates":[-3.388477,56.031319],"type":"Point"}
}