{
  "type": "Feature",
  "properties": {
    "addr:full":"145 Breck Road Liverpool Merseyside L4 2QZ",
    "addr:housenumber":"145",
    "addr:postcode":"l4 2qz",
    "addr:street":"Breck Road",
    "iso:country":"GB",
    "sg:address":"145 Breck Road",
    "sg:city":"Liverpool",
    "sg:classifiers":[
        {
            "category":"Food & Beverages",
            "subcategory":"Meat & Fish",
            "type":"Retail Goods"
        }
    ],
    "sg:phone":"+44 151 263 5035",
    "sg:postcode":"L4 2QZ",
    "sg:province":"Merseyside",
    "sg:tags":[
        "chip"
    ],
    "wof:name":"S Paraskeva",
    "wof:placetype":"venue"
},
  "geometry": {"coordinates":[-2.954045,53.424725],"type":"Point"}
}