{
  "type": "Feature",
  "properties": {
    "iso:country":"GB",
    "sg:address":"471-475 Princess Rd",
    "sg:city":"Manchester",
    "sg:classifiers":[
        {
            "category":"Health Services",
            "subcategory":"Doctor",
            "type":"Services"
        }
    ],
    "sg:phone":"+44 161 445 7805",
    "sg:postcode":"M20 1BH",
    "sg:province":"Greater Manchester",
    "sg:tags":[
        "practitioners"
    ],
    "wof:name":"Drs Williams Unwin & White",
    "wof:placetype":"venue"
},
  "geometry": {"coordinates":[-2.2437949181,53.4405174255],"type":"Point"}
}