{
  "type": "Feature",
  "properties": {
    "iso:country":"GB",
    "sg:address":"67 Flixton Rd, Urmston",
    "sg:city":"Manchester",
    "sg:classifiers":[
        {
            "category":"Retail",
            "subcategory":"Auto Repair",
            "type":"Services"
        }
    ],
    "sg:phone":"+44 161 747 4970",
    "sg:postcode":"M41 5AN",
    "sg:province":"Cheshire",
    "sg:tags":[
        "modification",
        "garage"
    ],
    "wof:name":"A & T Auto Service Centre",
    "wof:placetype":"venue"
},
  "geometry": {"coordinates":[-2.359215,53.448074],"type":"Point"}
}