{
  "type": "Feature",
  "properties": {
    "addr:full":"3 Chestnut Avenue London Greater London E7 0JQ",
    "addr:housenumber":"3",
    "addr:postcode":"e7 0jq",
    "addr:street":"Chestnut Avenue",
    "iso:country":"GB",
    "sg:address":"3 Chestnut Avenue",
    "sg:city":"London",
    "sg:classifiers":[
        {
            "category":"Retail",
            "subcategory":"Auto Repair",
            "type":"Services"
        }
    ],
    "sg:phone":"+44 20 8519 1920",
    "sg:postcode":"E7 0JQ",
    "sg:province":"Greater London",
    "sg:tags":[
        "electrical",
        "centre"
    ],
    "wof:name":"Quick Start",
    "wof:placetype":"venue"
},
  "geometry": {"coordinates":[0.0255490001,51.5522651672],"type":"Point"}
}