{
  "type": "Feature",
  "properties": {
    "addr:full":"Memorial Road, Hanham Bristol City of Bristol BS15 3LA",
    "addr:postcode":"bs15 3la",
    "addr:street":"Memorial Road",
    "iso:country":"GB",
    "sg:address":"Memorial Road, Hanham",
    "sg:city":"Bristol",
    "sg:classifiers":[
        {
            "category":"Education",
            "subcategory":"School",
            "type":"Public Place"
        }
    ],
    "sg:phone":"+44 117 967 5565",
    "sg:postcode":"BS15 3LA",
    "sg:province":"City of Bristol",
    "sg:tags":[
        "local",
        "authority"
    ],
    "wof:name":"Christchurch C of E Primary School",
    "wof:placetype":"venue"
},
  "geometry": {"coordinates":[-2.5163469315,51.4495506287],"type":"Point"}
}