{
  "type": "Feature",
  "properties": {
    "addr:full":"Reedley House, Burnley Road, Brierfield Nelson Lancashire BB9 5HX",
    "addr:postcode":"bb9 5hx",
    "addr:street":"Burnley Road",
    "iso:country":"GB",
    "sg:address":"Reedley House, Burnley Road, Brierfield",
    "sg:city":"Nelson",
    "sg:classifiers":[
        {
            "category":"Retail",
            "subcategory":"Funeral Services",
            "type":"Services"
        }
    ],
    "sg:phone":"+44 1282 614777",
    "sg:postcode":"BB9 5HX",
    "sg:province":"Lancashire",
    "wof:name":"Helliwells Funeral Service",
    "wof:placetype":"venue"
},
  "geometry": {"coordinates":[-2.2342839241,53.8236045837],"type":"Point"}
}