{
  "type": "Feature",
  "properties": {
    "iso:country":"GB",
    "sg:address":"34 Newmarket Street",
    "sg:city":"Ayr",
    "sg:classifiers":[
        {
            "category":"Manufacturing",
            "subcategory":"Tools & Machinery",
            "type":"Manufacturing & Wholesale Goods"
        },
        {
            "category":"Insurance",
            "subcategory":"Insurance Agent",
            "type":"Services"
        }
    ],
    "sg:postcode":"KA7 1LP",
    "sg:province":"South Ayrshire",
    "sg:tags":[
        "society",
        "friendly"
    ],
    "wof:name":"R G Christian Insurrance",
    "wof:placetype":"venue"
},
  "geometry": {"coordinates":[-4.630468,55.463558],"type":"Point"}
}