{
  "type": "Feature",
  "properties": {
    "iso:country":"GB",
    "sg:address":"71 Gorsty Hill Road, Rowley Regis, Warley",
    "sg:city":"Smethwick",
    "sg:classifiers":[
        {
            "category":"Bars & Pubs",
            "type":"Food & Drink"
        },
        {
            "category":"Community Center",
            "subcategory":"Social",
            "type":"Public Place"
        }
    ],
    "sg:phone":"+44 121 561 2196",
    "sg:postcode":"B65 0HA",
    "sg:province":"West Midlands",
    "sg:tags":[
        "pubs",
        "house",
        "inn",
        "activity"
    ],
    "wof:name":"Bell & Bear Inn",
    "wof:placetype":"venue"
},
  "geometry": {"coordinates":[-2.0475139618,52.4692497253],"type":"Point"}
}