{
  "type": "Feature",
  "properties": {
    "addr:full":"61 Liverpool Rd Stoke On Trent Staffordshire ST4 1AQ",
    "addr:housenumber":"61",
    "addr:postcode":"st4 1aq",
    "addr:street":"Liverpool Rd",
    "iso:country":"GB",
    "sg:address":"61 Liverpool Rd",
    "sg:city":"Stoke On Trent",
    "sg:classifiers":[
        {
            "category":"Place Of Worship",
            "type":"Public Place"
        }
    ],
    "sg:phone":"+44 1782 415670",
    "sg:postcode":"ST4 1AQ",
    "sg:province":"Staffordshire",
    "wof:name":"Guru Nanak Guardwara",
    "wof:placetype":"venue"
},
  "geometry": {"coordinates":[-2.1855039597,53.0068893433],"type":"Point"}
}