{
  "type": "Feature",
  "properties": {
    "addr:full":"22 Winchester Road Bromley Kent BR2 0PZ",
    "addr:housenumber":"22",
    "addr:postcode":"br2 0pz",
    "addr:street":"Winchester Road",
    "iso:country":"GB",
    "sg:address":"22 Winchester Road",
    "sg:city":"Bromley",
    "sg:classifiers":[
        {
            "category":"Professional",
            "subcategory":"Engineering",
            "type":"Services"
        }
    ],
    "sg:phone":"+44 20 8402 9630",
    "sg:postcode":"BR2 0PZ",
    "sg:province":"Kent",
    "sg:tags":[
        "consultant",
        "structural"
    ],
    "wof:name":"Stephen J Hyde",
    "wof:placetype":"venue"
},
  "geometry": {"coordinates":[0.007374,51.399117],"type":"Point"}
}