{
  "type": "Feature",
  "properties": {
    "addr:full":"Bay House, Market Place Saxmundham Suffolk IP17 1AG",
    "addr:postcode":"ip17 1ag",
    "addr:street":"Market Place",
    "iso:country":"GB",
    "sg:address":"Bay House, Market Place",
    "sg:city":"Saxmundham",
    "sg:classifiers":[
        {
            "category":"Fast Food",
            "type":"Food & Drink"
        }
    ],
    "sg:phone":"+44 1728 603500",
    "sg:postcode":"IP17 1AG",
    "sg:province":"Suffolk",
    "sg:tags":[
        "away",
        "take"
    ],
    "wof:name":"J P Rolse",
    "wof:placetype":"venue"
},
  "geometry": {"coordinates":[1.492014,52.21571],"type":"Point"}
}