{
  "type": "Feature",
  "properties": {
    "addr:full":"Unit 5 Zenith Buildings Dudnance La Redruth Cornwall TR15 3QY",
    "addr:housenumber":"unit 5 zenith buildings",
    "addr:postcode":"tr15 3qy",
    "addr:street":"Dudnance La Redruth",
    "iso:country":"GB",
    "sg:address":"Unit 5 Zenith Buildings Dudnance La",
    "sg:city":"Redruth",
    "sg:classifiers":[
        {
            "category":"Retail",
            "subcategory":"Repair Shop",
            "type":"Services"
        }
    ],
    "sg:phone":"+44 1209 610008",
    "sg:postcode":"TR15 3QY",
    "sg:province":"Cornwall",
    "sg:tags":[
        "radio",
        "television",
        "video"
    ],
    "wof:name":"Zenith Electronics",
    "wof:placetype":"venue"
},
  "geometry": {"coordinates":[-5.2294340134,50.232509613],"type":"Point"}
}