{
  "type": "Feature",
  "properties": {
    "addr:full":"Centrum House, 101-103 Fleet Rd Fleet Dorset GU13 8PD",
    "addr:housenumber":"101-103",
    "addr:postcode":"gu13 8pd",
    "addr:street":"Fleet Rd",
    "iso:country":"GB",
    "sg:address":"Centrum House, 101-103 Fleet Rd",
    "sg:city":"Fleet",
    "sg:classifiers":[
        {
            "category":"Professional",
            "subcategory":"Computer Services",
            "type":"Services"
        }
    ],
    "sg:phone":"+44 1252 622161",
    "sg:postcode":"GU13 8PD",
    "sg:province":"Dorset",
    "sg:tags":[
        "system",
        "software"
    ],
    "wof:name":"EDS",
    "wof:placetype":"venue"
},
  "geometry": {"coordinates":[-0.83769,51.284702],"type":"Point"}
}