{
  "type": "Feature",
  "properties": {
    "addr:full":"Walsgrave Rd Coventry Warwickshire CV2 4BG",
    "addr:postcode":"cv2 4bg",
    "addr:street":"Walsgrave Rd",
    "iso:country":"GB",
    "sg:address":"Walsgrave Rd",
    "sg:city":"Coventry",
    "sg:classifiers":[
        {
            "category":"Place Of Worship",
            "type":"Public Place"
        }
    ],
    "sg:phone":"+44 24 7644 3691",
    "sg:postcode":"CV2 4BG",
    "sg:province":"Warwickshire",
    "sg:website":"http://www.fish.co.uk",
    "wof:name":"Stoke St Michael C Of E Church",
    "wof:placetype":"venue"
},
  "geometry": {"coordinates":[-1.486669,52.409985],"type":"Point"}
}