{
  "type": "Feature",
  "properties": {
    "addr:full":"Hunwick Works, Hunwick Crook Durham DL15 0LB",
    "addr:postcode":"dl15 0lb",
    "iso:country":"GB",
    "sg:address":"Hunwick Works, Hunwick",
    "sg:city":"Crook",
    "sg:classifiers":[
        {
            "category":"Wholesale",
            "subcategory":"Chemicals & Plastics",
            "type":"Manufacturing & Wholesale Goods"
        }
    ],
    "sg:phone":"+44 1388 458459",
    "sg:postcode":"DL15 0LB",
    "sg:province":"Durham",
    "sg:tags":[
        "product",
        "allied"
    ],
    "wof:name":"Dycat International",
    "wof:placetype":"venue"
},
  "geometry": {"coordinates":[-1.7074240446,54.6869659424],"type":"Point"}
}