{
  "type": "Feature",
  "properties": {
    "addr:full":"Studio 13 Cockpit Yard, Northing Street London Greater London WC1N 2NT",
    "addr:postcode":"wc1n 2nt",
    "addr:street":"Cockpit Yard Northing Street",
    "iso:country":"GB",
    "sg:address":"Studio 13 Cockpit Yard, Northing Street",
    "sg:city":"London",
    "sg:classifiers":[
        {
            "category":"Communications",
            "subcategory":"Film & Video Production",
            "type":"Services"
        }
    ],
    "sg:postcode":"WC1N 2NT",
    "sg:province":"Greater London",
    "sg:tags":[
        "illustrator",
        "artist"
    ],
    "wof:name":"Alex Green",
    "wof:placetype":"venue"
},
  "geometry": {"coordinates":[-0.1158400029,51.5218086243],"type":"Point"}
}