{
  "type": "Feature",
  "properties": {
    "addr:full":"44 High Street Whitchurch Cheshire SY13 1BB",
    "addr:housenumber":"44",
    "addr:postcode":"sy13 1bb",
    "addr:street":"High Street",
    "iso:country":"GB",
    "sg:address":"44 High Street",
    "sg:city":"Whitchurch",
    "sg:classifiers":[
        {
            "category":"Shopping",
            "subcategory":"Gifts & Souvenirs",
            "type":"Retail Goods"
        }
    ],
    "sg:postcode":"SY13 1BB",
    "sg:province":"Cheshire",
    "sg:tags":[
        "shop"
    ],
    "wof:name":"J Davies & N Prunier",
    "wof:placetype":"venue"
},
  "geometry": {"coordinates":[-2.684726,52.969841],"type":"Point"}
}