{
  "type": "Feature",
  "properties": {
    "iso:country":"GB",
    "sg:address":"P O Box 980",
    "sg:city":"Gerrards Cross",
    "sg:classifiers":[
        {
            "category":"Professional",
            "subcategory":"Testing Lab",
            "type":"Services"
        }
    ],
    "sg:phone":"+44 1753 883101",
    "sg:postcode":"SL9 9XN",
    "sg:province":"Buckinghamshire",
    "sg:tags":[
        "pregnancy"
    ],
    "wof:name":"Christian Action Research & Education (Care)",
    "wof:placetype":"venue"
},
  "geometry": {"coordinates":[-0.559829,51.605949],"type":"Point"}
}