{
  "type": "Feature",
  "properties": {
    "addr:full":"Beeches Swimming Pool & Fitness Centre, Beeches Rd Birmingham West Midlands B42 2HQ",
    "addr:postcode":"b42 2hq",
    "addr:street":"Beeches Rd",
    "iso:country":"GB",
    "sg:address":"Beeches Swimming Pool & Fitness Centre, Beeches Rd",
    "sg:city":"Birmingham",
    "sg:classifiers":[
        {
            "category":"Government",
            "subcategory":"Office",
            "type":"Public Place"
        }
    ],
    "sg:phone":"+44 121 358 6296",
    "sg:postcode":"B42 2HQ",
    "sg:province":"West Midlands",
    "sg:tags":[
        "local"
    ],
    "wof:name":"Birmingham City Council",
    "wof:placetype":"venue"
},
  "geometry": {"coordinates":[-1.9121,52.53791],"type":"Point"}
}