{
  "type": "Feature",
  "properties": {
    "addr:full":"Midway, Leasam La Rye East Sussex TN31 7UE",
    "addr:postcode":"tn31 7ue",
    "addr:street":"La",
    "iso:country":"GB",
    "sg:address":"Midway, Leasam La",
    "sg:city":"Rye",
    "sg:classifiers":[
        {
            "category":"Professional",
            "subcategory":"Computer Services",
            "type":"Services"
        }
    ],
    "sg:phone":"+44 1797 222505",
    "sg:postcode":"TN31 7UE",
    "sg:province":"East Sussex",
    "sg:tags":[
        "system",
        "software"
    ],
    "wof:name":"Core Computers",
    "wof:placetype":"venue"
},
  "geometry": {"coordinates":[0.731398,50.962387],"type":"Point"}
}