{
  "type": "Feature",
  "properties": {
    "addr:full":"Leylandhayes Wellington Devon TA21 9NX",
    "addr:postcode":"ta21 9nx",
    "iso:country":"GB",
    "sg:address":"Leylandhayes",
    "sg:city":"Wellington",
    "sg:classifiers":[
        {
            "category":"Organizations",
            "subcategory":"Non-profit Organization",
            "type":"Services"
        }
    ],
    "sg:phone":"+44 1823 662965",
    "sg:postcode":"TA21 9NX",
    "sg:province":"Devon",
    "sg:tags":[
        "organisation",
        "voluntary",
        "charity"
    ],
    "wof:name":"S S A F A Forces Help",
    "wof:placetype":"venue"
},
  "geometry": {"coordinates":[-3.241579,50.943439],"type":"Point"}
}