{
  "type": "Feature",
  "properties": {
    "addr:full":"17 Beechdale Road Bedford Bedfordshire MK42 9NH",
    "addr:housenumber":"17",
    "addr:postcode":"mk42 9nh",
    "addr:street":"Beechdale Road",
    "iso:country":"GB",
    "sg:address":"17 Beechdale Road",
    "sg:city":"Bedford",
    "sg:classifiers":[
        {
            "category":"Retail",
            "subcategory":"Auto Repair",
            "type":"Services"
        }
    ],
    "sg:phone":"+44 1234 219226",
    "sg:postcode":"MK42 9NH",
    "sg:province":"Bedfordshire",
    "sg:tags":[
        "engine",
        "car",
        "specialist"
    ],
    "wof:name":"Auto Mek",
    "wof:placetype":"venue"
},
  "geometry": {"coordinates":[-0.464166,52.122841],"type":"Point"}
}