{
  "type": "Feature",
  "properties": {
    "addr:full":"Hartley Centre, 267 Barking Rd, East Ham East Ham Greater London E6 1LB",
    "addr:housenumber":"267",
    "addr:postcode":"e6 1lb",
    "addr:street":"Barking Rd;Ham",
    "iso:country":"GB",
    "sg:address":"Hartley Centre, 267 Barking Rd, East Ham",
    "sg:city":"East Ham",
    "sg:classifiers":[
        {
            "category":"Personal",
            "type":"Services"
        }
    ],
    "sg:phone":"+44 20 8252 0656",
    "sg:postcode":"E6 1LB",
    "sg:province":"Greater London",
    "sg:tags":[
        "slimming",
        "product"
    ],
    "wof:name":"Slimming World",
    "wof:placetype":"venue"
},
  "geometry": {"coordinates":[0.04915,51.532242],"type":"Point"}
}