{
  "type": "Feature",
  "properties": {
    "addr:full":"Strathmore House, Charles Bowman Avenue, Claverhouse Industrial Park Dundee Dundee City DD4 9UB",
    "addr:postcode":"dd4 9ub",
    "addr:street":"Charles Bowman Avenue Claverhouse Industrial Park",
    "iso:country":"GB",
    "sg:address":"Strathmore House, Charles Bowman Avenue, Claverhouse Industrial Park",
    "sg:city":"Dundee",
    "sg:classifiers":[
        {
            "category":"Shopping",
            "subcategory":"Computers & Home Electronics",
            "type":"Retail Goods"
        },
        {
            "category":"Home & Garden",
            "subcategory":"Furniture",
            "type":"Retail Goods"
        }
    ],
    "sg:phone":"+44 1382 509080",
    "sg:postcode":"DD4 9UB",
    "sg:province":"Dundee City",
    "wof:name":"Samuel Bruce Ltd",
    "wof:placetype":"venue"
},
  "geometry": {"coordinates":[-2.9537990093,56.4929389954],"type":"Point"}
}