{
  "type": "Feature",
  "properties": {
    "addr:full":"60 Kennedy Road Barking Essex IG11 7XH",
    "addr:housenumber":"60",
    "addr:postcode":"ig11 7xh",
    "addr:street":"Kennedy Road",
    "iso:country":"GB",
    "sg:address":"60 Kennedy Road",
    "sg:city":"Barking",
    "sg:classifiers":[
        {
            "category":"Arts & Performance",
            "subcategory":"Music",
            "type":"Entertainment"
        }
    ],
    "sg:phone":"+44 20 8591 1534",
    "sg:postcode":"IG11 7XH",
    "sg:province":"Essex",
    "sg:tags":[
        "mobile",
        "disco"
    ],
    "wof:name":"Zippy's Disco",
    "wof:placetype":"venue"
},
  "geometry": {"coordinates":[0.093019,51.532639],"type":"Point"}
}