{
  "type": "Feature",
  "properties": {
    "iso:country":"GB",
    "sg:address":"134 Corve St",
    "sg:city":"Ludlow",
    "sg:classifiers":[
        {
            "category":"Personal",
            "subcategory":"Barber",
            "type":"Services"
        }
    ],
    "sg:phone":"+44 1584 876343",
    "sg:postcode":"SY8 2PG",
    "sg:province":"Herefordshire",
    "sg:tags":[
        "men's",
        "hairdresser"
    ],
    "wof:name":"Mr Bens Barbers",
    "wof:placetype":"venue"
},
  "geometry": {"coordinates":[-2.718791,52.370613],"type":"Point"}
}