{
  "type": "Feature",
  "properties": {
    "addr:full":"3 Newfield Gardens Marlow Berkshire SL7 1JN",
    "addr:housenumber":"3",
    "addr:postcode":"sl7 1jn",
    "addr:street":"Newfield Gardens",
    "iso:country":"GB",
    "sg:address":"3 Newfield Gardens",
    "sg:city":"Marlow",
    "sg:classifiers":[
        {
            "category":"Building & Trades",
            "subcategory":"Landscaping Services",
            "type":"Services"
        }
    ],
    "sg:phone":"+44 1628 484579",
    "sg:postcode":"SL7 1JN",
    "sg:province":"Berkshire",
    "sg:tags":[
        "landscape",
        "contractor"
    ],
    "wof:name":"Bucks Grass Roots",
    "wof:placetype":"venue"
},
  "geometry": {"coordinates":[-0.7650570273,51.5743865967],"type":"Point"}
}