{
  "type": "Feature",
  "properties": {
    "iso:country":"GB",
    "sg:address":"2 Hightrees Court, Main Road, Gilwern",
    "sg:city":"Abergavenny",
    "sg:classifiers":[
        {
            "category":"Real Estate",
            "subcategory":"Surveying",
            "type":"Services"
        }
    ],
    "sg:postcode":"NP7 0AJ",
    "sg:province":"Herefordshire",
    "sg:tags":[
        "surveyor",
        "quantity"
    ],
    "wof:name":"S J Davies",
    "wof:placetype":"venue"
},
  "geometry": {"coordinates":[-3.091039,51.825275],"type":"Point"}
}