{
  "type": "Feature",
  "properties": {
    "addr:full":"2 Hightrees Court, Main Road, Gilwern Abergavenny Herefordshire NP7 0AJ",
    "addr:housenumber":"2",
    "addr:postcode":"np7 0aj",
    "addr:street":"Hightrees Court Main Road",
    "iso:country":"GB",
    "sg:address":"2 Hightrees Court, Main Road, Gilwern",
    "sg:city":"Abergavenny",
    "sg:classifiers":[
        {
            "category":"Real Estate",
            "subcategory":"Surveying",
            "type":"Services"
        }
    ],
    "sg:postcode":"NP7 0AJ",
    "sg:province":"Herefordshire",
    "sg:tags":[
        "surveyor",
        "quantity"
    ],
    "wof:name":"S J Davies",
    "wof:placetype":"venue"
},
  "geometry": {"coordinates":[-3.091039,51.825275],"type":"Point"}
}