{
  "type": "Feature",
  "properties": {
    "iso:country":"GB",
    "sg:address":"27 Firs Close",
    "sg:city":"Forest Hill",
    "sg:classifiers":[
        {
            "category":"Wholesale",
            "subcategory":"Books, Periodicals, & Newspapers",
            "type":"Manufacturing & Wholesale Goods"
        }
    ],
    "sg:postcode":"SE23 1BB",
    "sg:province":"Greater London",
    "sg:tags":[
        "publishing"
    ],
    "wof:name":"Goldweb Communications Ltd",
    "wof:placetype":"venue"
},
  "geometry": {"coordinates":[-0.043765001,51.4444351196],"type":"Point"}
}