{
  "type": "Feature",
  "properties": {
    "addr:full":"21b Bancroft Hitchin Bedfordshire SG5 1JW",
    "addr:housenumber":"21b",
    "addr:postcode":"sg5 1jw",
    "addr:street":"Bancroft",
    "iso:country":"GB",
    "sg:address":"21b Bancroft",
    "sg:city":"Hitchin",
    "sg:classifiers":[
        {
            "category":"Shopping",
            "subcategory":"Pharmacy",
            "type":"Retail Goods"
        }
    ],
    "sg:phone":"+44 1462 450101",
    "sg:postcode":"SG5 1JW",
    "sg:province":"Bedfordshire",
    "sg:tags":[
        "pharmacist",
        "chemist"
    ],
    "wof:name":"Bell Chemist",
    "wof:placetype":"venue"
},
  "geometry": {"coordinates":[-0.2772009969,51.9501037598],"type":"Point"}
}