{
  "type": "Feature",
  "properties": {
    "addr:full":"36a Princess Street Knutsford Cheshire WA16 6BN",
    "addr:housenumber":"36a",
    "addr:postcode":"wa16 6bn",
    "addr:street":"Princess Street",
    "iso:country":"GB",
    "sg:address":"36a Princess Street",
    "sg:city":"Knutsford",
    "sg:classifiers":[
        {
            "category":"Shopping",
            "subcategory":"Gifts & Souvenirs",
            "type":"Retail Goods"
        }
    ],
    "sg:phone":"+44 1565 751477",
    "sg:postcode":"WA16 6BN",
    "sg:province":"Cheshire",
    "sg:tags":[
        "shop"
    ],
    "wof:name":"The House of Wares",
    "wof:placetype":"venue"
},
  "geometry": {"coordinates":[-2.375647068,53.3046684265],"type":"Point"}
}