{
  "type": "Feature",
  "properties": {
    "addr:full":"1 Okement Units Okehampton Devon EX20 1UB",
    "addr:housenumber":"1",
    "addr:postcode":"ex20 1ub",
    "addr:street":"Okement Units",
    "iso:country":"GB",
    "sg:address":"1 Okement Units",
    "sg:city":"Okehampton",
    "sg:classifiers":[
        {
            "category":"Professional",
            "subcategory":"Testing Lab",
            "type":"Services"
        },
        {
            "category":"Home & Garden",
            "subcategory":"Building Materials",
            "type":"Retail Goods"
        }
    ],
    "sg:phone":"+44 1837 54446",
    "sg:postcode":"EX20 1UB",
    "sg:province":"Devon",
    "sg:tags":[
        "access",
        "laboratory",
        "equipment"
    ],
    "wof:name":"ELEMENTAL MICROANALYSIS LTD",
    "wof:placetype":"venue"
},
  "geometry": {"coordinates":[-3.9969489574,50.7423400879],"type":"Point"}
}