{
  "type": "Feature",
  "properties": {
    "addr:full":"Stuntney Hall, Soham Road, Stuntney Ely Cambridgeshire CB7 5TL",
    "addr:postcode":"cb7 5tl",
    "addr:street":"Soham Road",
    "iso:country":"GB",
    "sg:address":"Stuntney Hall, Soham Road, Stuntney",
    "sg:city":"Ely",
    "sg:classifiers":[
        {
            "category":"Farming",
            "subcategory":"Livestock Farm",
            "type":"Manufacturing & Wholesale Goods"
        },
        {
            "category":"Farming",
            "subcategory":"Farm",
            "type":"Manufacturing & Wholesale Goods"
        }
    ],
    "sg:phone":"+44 1353 662202",
    "sg:postcode":"CB7 5TL",
    "sg:province":"Cambridgeshire",
    "sg:tags":[
        "mixed",
        "others"
    ],
    "wof:name":"Cole Ambrose Ltd",
    "wof:placetype":"venue"
},
  "geometry": {"coordinates":[0.3569400012,52.3179893494],"type":"Point"}
}