{
  "type": "Feature",
  "properties": {
    "iso:country":"GB",
    "sg:address":"1 Park View, Hockley Heath",
    "sg:city":"Solihull",
    "sg:classifiers":[
        {
            "category":"Arts & Performance",
            "subcategory":"Music",
            "type":"Entertainment"
        }
    ],
    "sg:phone":"+44 7887 696028",
    "sg:postcode":"B94 6PE",
    "sg:province":"Warwickshire",
    "sg:tags":[
        "mobile",
        "disco"
    ],
    "wof:name":"Dave's Mobile Disco",
    "wof:placetype":"venue"
},
  "geometry": {"coordinates":[-1.775423,52.354511],"type":"Point"}
}