{
  "type": "Feature",
  "properties": {
    "iso:country":"GB",
    "sg:address":"44 Manor Park, Sticklepath",
    "sg:city":"Barnstaple",
    "sg:classifiers":[
        {
            "category":"Professional",
            "subcategory":"Art Services",
            "type":"Services"
        }
    ],
    "sg:phone":"+44 1271 322982",
    "sg:postcode":"EX31 2DH",
    "sg:province":"Devon",
    "sg:tags":[
        "framing"
    ],
    "wof:name":"North Devon Framing",
    "wof:placetype":"venue"
},
  "geometry": {"coordinates":[-4.078553,51.070972],"type":"Point"}
}