{
  "type": "Feature",
  "properties": {
    "addr:full":"2 St Modwens Walk, The Precinct Burton-on-trent Derbyshire DE14 1HL",
    "addr:housenumber":"2",
    "addr:postcode":"de14 1hl",
    "addr:street":"St Modwens Walk The Precinct",
    "iso:country":"GB",
    "sg:address":"2 St Modwens Walk, The Precinct",
    "sg:city":"Burton-on-trent",
    "sg:classifiers":[
        {
            "category":"Shopping",
            "subcategory":"Department Store",
            "type":"Retail Goods"
        }
    ],
    "sg:phone":"+44 1283 543451",
    "sg:postcode":"DE14 1HL",
    "sg:province":"Derbyshire",
    "wof:name":"Marks & Spencer Plc",
    "wof:placetype":"venue"
},
  "geometry": {"coordinates":[-1.63164,52.801868],"type":"Point"}
}