{
  "type": "Feature",
  "properties": {
    "addr:full":"Abbotsbury Road Eastleigh Hampshire SO50 8NZ",
    "addr:postcode":"so50 8nz",
    "addr:street":"Abbotsbury Road",
    "iso:country":"GB",
    "sg:address":"Abbotsbury Road",
    "sg:city":"Eastleigh",
    "sg:classifiers":[
        {
            "category":"Education",
            "subcategory":"School",
            "type":"Public Place"
        }
    ],
    "sg:phone":"+44 23 8060 1773",
    "sg:postcode":"SO50 8NZ",
    "sg:province":"Hampshire",
    "sg:tags":[
        "local",
        "authority"
    ],
    "wof:name":"Stoke Park Infants School",
    "wof:placetype":"venue"
},
  "geometry": {"coordinates":[-1.323874,50.967331],"type":"Point"}
}