{
  "type": "Feature",
  "properties": {
    "iso:country":"GB",
    "sg:address":"13 Greenlands Road",
    "sg:city":"Weybridge",
    "sg:classifiers":[
        {
            "category":"Building & Trades",
            "subcategory":"Landscaping Services",
            "type":"Services"
        }
    ],
    "sg:postcode":"KT13 8PP",
    "sg:province":"Surrey",
    "sg:tags":[
        "landscape",
        "contractor"
    ],
    "wof:name":"Vincenzo Mantio",
    "wof:placetype":"venue"
},
  "geometry": {"coordinates":[-0.4523420036,51.3768463135],"type":"Point"}
}