{
  "type": "Feature",
  "properties": {
    "addr:full":"52 Higher Market St Bolton Lancashire BL4 9BB",
    "addr:housenumber":"52",
    "addr:postcode":"bl4 9bb",
    "addr:street":"Higher Market St",
    "iso:country":"GB",
    "sg:address":"52 Higher Market St",
    "sg:city":"Bolton",
    "sg:classifiers":[
        {
            "category":"Fast Food",
            "type":"Food & Drink"
        }
    ],
    "sg:phone":"+44 1204 700477",
    "sg:postcode":"BL4 9BB",
    "sg:province":"Lancashire",
    "sg:tags":[
        "away",
        "take"
    ],
    "wof:name":"Julies Brunch Box",
    "wof:placetype":"venue"
},
  "geometry": {"coordinates":[-2.391182,53.545513],"type":"Point"}
}