{
  "type": "Feature",
  "properties": {
    "iso:country":"GB",
    "sg:address":"The Airfield",
    "sg:city":"Bridgwater",
    "sg:classifiers":[
        {
            "category":"Manufacturing",
            "subcategory":"Lumber",
            "type":"Manufacturing & Wholesale Goods"
        }
    ],
    "sg:postcode":"TA7 0JS",
    "sg:province":"Somerset",
    "sg:tags":[
        "importer",
        "merchants",
        "agent",
        "timber"
    ],
    "wof:name":"Industrial Concrete Products",
    "wof:placetype":"venue"
},
  "geometry": {"coordinates":[-2.90855,51.100601],"type":"Point"}
}