{
  "type": "Feature",
  "properties": {
    "iso:country":"GB",
    "sg:address":"11 Lower Hollyhead Road",
    "sg:city":"Coventry",
    "sg:classifiers":[
        {
            "category":"Retail",
            "subcategory":"Funeral Services",
            "type":"Services"
        }
    ],
    "sg:phone":"+44 24 7622 5826",
    "sg:postcode":"CV1 3AX",
    "sg:province":"West Midlands",
    "wof:name":"CO-OPERATIVE FUNERAL SERVICES",
    "wof:placetype":"venue"
},
  "geometry": {"coordinates":[-1.5168960094,52.4087181091],"type":"Point"}
}