{
  "type": "Feature",
  "properties": {
    "addr:full":"350 Old Bath Road Cheltenham Gloucestershire GL53 9AF",
    "addr:housenumber":"350",
    "addr:postcode":"gl53 9af",
    "addr:street":"Old Bath Road",
    "iso:country":"GB",
    "sg:address":"350 Old Bath Road",
    "sg:city":"Cheltenham",
    "sg:classifiers":[
        {
            "category":"Banks & Credit Unions",
            "subcategory":"Financial Services",
            "type":"Services"
        }
    ],
    "sg:phone":"+44 1242 227172",
    "sg:postcode":"GL53 9AF",
    "sg:province":"Gloucestershire",
    "sg:tags":[
        "adviser",
        "independent"
    ],
    "wof:name":"Global Business Finance",
    "wof:placetype":"venue"
},
  "geometry": {"coordinates":[-2.074295,51.87302],"type":"Point"}
}