{
  "type": "Feature",
  "properties": {
    "iso:country":"GB",
    "sg:address":"1 Huntingdon Rd, Thrapston",
    "sg:city":"Kettering",
    "sg:classifiers":[
        {
            "category":"Bars & Pubs",
            "type":"Food & Drink"
        }
    ],
    "sg:phone":"+44 1832 734440",
    "sg:postcode":"NN14 4NF",
    "sg:province":"Northamptonshire",
    "sg:tags":[
        "pubs",
        "inn"
    ],
    "wof:name":"The Masons Arms",
    "wof:placetype":"venue"
},
  "geometry": {"coordinates":[-0.533413,52.396339],"type":"Point"}
}