{
  "type": "Feature",
  "properties": {
    "addr:full":"30 Pendyffryn Llandudno Junction Conwy LL31 9AS",
    "addr:housenumber":"30",
    "addr:postcode":"ll31 9as",
    "addr:street":"Pendyffryn Llandudno Junction",
    "iso:country":"GB",
    "sg:address":"30 Pendyffryn",
    "sg:city":"Llandudno Junction",
    "sg:classifiers":[
        {
            "category":"Taxi",
            "type":"Transportation"
        }
    ],
    "sg:phone":"+44 1492 581487",
    "sg:postcode":"LL31 9AS",
    "sg:province":"Conwy",
    "sg:tags":[
        "mini",
        "cab"
    ],
    "wof:name":"Alison Thompson",
    "wof:placetype":"venue"
},
  "geometry": {"coordinates":[-3.7942109108,53.2871742249],"type":"Point"}
}