{
  "type": "Feature",
  "properties": {
    "addr:full":"High Street, Curry Rivel Langport Somerset TA10 0EY",
    "addr:postcode":"ta10 0ey",
    "addr:street":"High Street",
    "iso:country":"GB",
    "sg:address":"High Street, Curry Rivel",
    "sg:city":"Langport",
    "sg:classifiers":[
        {
            "category":"Travel",
            "subcategory":"Hotels & Motels",
            "type":"Entertainment"
        }
    ],
    "sg:postcode":"TA10 0EY",
    "sg:province":"Somerset",
    "sg:tags":[
        "house",
        "guest"
    ],
    "wof:name":"Hillards Farm",
    "wof:placetype":"venue"
},
  "geometry": {"coordinates":[-2.8639640808,51.0241508484],"type":"Point"}
}