{
  "type": "Feature",
  "properties": {
    "addr:full":"57 Warton Road London Greater London E15 2JY",
    "addr:housenumber":"57",
    "addr:postcode":"e15 2jy",
    "addr:street":"Warton Road",
    "iso:country":"GB",
    "sg:address":"57 Warton Road",
    "sg:city":"London",
    "sg:classifiers":[
        {
            "category":"Wholesale",
            "subcategory":"Scrap",
            "type":"Manufacturing & Wholesale Goods"
        },
        {
            "category":"Shopping",
            "type":"Retail Goods"
        }
    ],
    "sg:phone":"+44 20 8503 0002",
    "sg:postcode":"E15 2JY",
    "sg:province":"Greater London",
    "sg:tags":[
        "car",
        "part",
        "breaker",
        "accessory",
        "dismantlers"
    ],
    "wof:name":"Japanese Parts Centre",
    "wof:placetype":"venue"
},
  "geometry": {"coordinates":[-0.0095619997,51.5389099121],"type":"Point"}
}