{
  "type": "Feature",
  "properties": {
    "addr:full":"10 Dukes Lane Brighton East Sussex BN1 1BG",
    "addr:housenumber":"10",
    "addr:postcode":"bn1 1bg",
    "addr:street":"Dukes Lane",
    "iso:country":"GB",
    "sg:address":"10 Dukes Lane",
    "sg:city":"Brighton",
    "sg:classifiers":[
        {
            "category":"Restaurant",
            "type":"Food & Drink"
        }
    ],
    "sg:phone":"+44 1273 325945",
    "sg:postcode":"BN1 1BG",
    "sg:province":"East Sussex",
    "wof:name":"Barker",
    "wof:placetype":"venue"
},
  "geometry": {"coordinates":[-0.142683,50.822701],"type":"Point"}
}