{
  "type": "Feature",
  "properties": {
    "iso:country":"GB",
    "sg:address":"47 Kidsgrove Bank, Kidsgrove",
    "sg:city":"Stoke-on-trent",
    "sg:classifiers":[
        {
            "category":"Retail",
            "subcategory":"Auto Repair",
            "type":"Services"
        }
    ],
    "sg:phone":"+44 1782 784756",
    "sg:postcode":"ST7 4HB",
    "sg:province":"Cheshire",
    "sg:tags":[
        "engine",
        "car",
        "specialist"
    ],
    "wof:name":"Computa Tune",
    "wof:placetype":"venue"
},
  "geometry": {"coordinates":[-2.2246448994,53.0813751221],"type":"Point"}
}