{
  "type": "Feature",
  "properties": {
    "addr:full":"143-149 Union Street Aberdeen Aberdeen City AB9 1UH",
    "addr:housenumber":"143-149",
    "addr:postcode":"ab9 1uh",
    "addr:street":"Union Street",
    "iso:country":"GB",
    "sg:address":"143-149 Union Street",
    "sg:city":"Aberdeen",
    "sg:classifiers":[
        {
            "category":"Shopping",
            "subcategory":"Department Store",
            "type":"Retail Goods"
        }
    ],
    "sg:phone":"+44 1224 581065",
    "sg:postcode":"AB9 1UH",
    "sg:province":"Aberdeen City",
    "wof:name":"Littlewoods Stores Ltd",
    "wof:placetype":"venue"
},
  "geometry": {"coordinates":[-2.1178269386,57.1409797668],"type":"Point"}
}