{
  "type": "Feature",
  "properties": {
    "addr:full":"Riverview Park, Fambridge Road, Althorne Chelmsford Essex CM3 6DE",
    "addr:postcode":"cm3 6de",
    "addr:street":"Fambridge Road",
    "iso:country":"GB",
    "sg:address":"Riverview Park, Fambridge Road, Althorne",
    "sg:city":"Chelmsford",
    "sg:classifiers":[
        {
            "category":"Manufacturing",
            "subcategory":"Buildings",
            "type":"Manufacturing & Wholesale Goods"
        }
    ],
    "sg:phone":"+44 1621 741272",
    "sg:postcode":"CM3 6DE",
    "sg:province":"Essex",
    "sg:tags":[
        "mobile",
        "home"
    ],
    "wof:name":"The Berkeley Leisure Group Ltd",
    "wof:placetype":"venue"
},
  "geometry": {"coordinates":[0.76038,51.659233],"type":"Point"}
}