{
  "type": "Feature",
  "properties": {
    "addr:full":"Riverside, Crossbank Road King's Lynn Norfolk PE30 2AQ",
    "addr:postcode":"pe30 2aq",
    "addr:street":"Crossbank Road",
    "iso:country":"GB",
    "sg:address":"Riverside, Crossbank Road",
    "sg:city":"King's Lynn",
    "sg:classifiers":[
        {
            "category":"Farming",
            "subcategory":"Fish & Marine Products",
            "type":"Manufacturing & Wholesale Goods"
        }
    ],
    "sg:phone":"+44 1553 769176",
    "sg:postcode":"PE30 2AQ",
    "sg:province":"Norfolk",
    "sg:tags":[
        "fishmonger"
    ],
    "wof:name":"John Lake Shellfish",
    "wof:placetype":"venue"
},
  "geometry": {"coordinates":[0.418327,52.757504],"type":"Point"}
}