{
  "type": "Feature",
  "properties": {
    "addr:full":"4-8 Lonsdale Street Carlisle Cumbria CA1 1DB",
    "addr:housenumber":"4-8",
    "addr:postcode":"ca1 1db",
    "addr:street":"Lonsdale Street",
    "iso:country":"GB",
    "sg:address":"4-8 Lonsdale Street",
    "sg:city":"Carlisle",
    "sg:classifiers":[
        {
            "category":"Real Estate",
            "subcategory":"Real Estate Agent",
            "type":"Services"
        }
    ],
    "sg:postcode":"CA1 1DB",
    "sg:province":"Cumbria",
    "wof:name":"Reeds Rains Ltd.",
    "wof:placetype":"venue"
},
  "geometry": {"coordinates":[-2.932321,54.893948],"type":"Point"}
}