{
  "type": "Feature",
  "properties": {
    "addr:full":"74-76 Station Road Harrow Greater London HA1 2SQ",
    "addr:housenumber":"74-76",
    "addr:postcode":"ha1 2sq",
    "addr:street":"Station Road",
    "iso:country":"GB",
    "sg:address":"74-76 Station Road",
    "sg:city":"Harrow",
    "sg:classifiers":[
        {
            "category":"Autos & Motor Vehicles",
            "subcategory":"Auto Supplies",
            "type":"Retail Goods"
        }
    ],
    "sg:phone":"+44 20 8427 2149",
    "sg:postcode":"HA1 2SQ",
    "sg:province":"Greater London",
    "sg:tags":[
        "tyre"
    ],
    "wof:name":"Harrow Tyre Service Ltd.",
    "wof:placetype":"venue"
},
  "geometry": {"coordinates":[-0.3319639862,51.5875358582],"type":"Point"}
}