{
  "type": "Feature",
  "properties": {
    "addr:full":"6 Castle Street Beaumaris Isle of Anglesey LL58 8AP",
    "addr:housenumber":"6",
    "addr:postcode":"ll58 8ap",
    "addr:street":"Castle Street",
    "iso:country":"GB",
    "sg:address":"6 Castle Street",
    "sg:city":"Beaumaris",
    "sg:classifiers":[
        {
            "category":"Health Services",
            "subcategory":"Dentist",
            "type":"Services"
        }
    ],
    "sg:phone":"+44 1248 811041",
    "sg:postcode":"LL58 8AP",
    "sg:province":"Isle of Anglesey",
    "wof:name":"Beaumaris Dental Health Care",
    "wof:placetype":"venue"
},
  "geometry": {"coordinates":[-4.0909137726,53.2641029358],"type":"Point"}
}