{
  "type": "Feature",
  "properties": {
    "addr:full":"Unit A Harrier Park Peterborough Cambridgeshire PE2 6YQ",
    "addr:housenumber":"unit a",
    "addr:postcode":"pe2 6yq",
    "addr:street":"Harrier Park Peterborough",
    "iso:country":"GB",
    "sg:address":"Unit A Harrier Park",
    "sg:city":"Peterborough",
    "sg:classifiers":[
        {
            "category":"Wholesale",
            "subcategory":"Toys & Hobbies",
            "type":"Manufacturing & Wholesale Goods"
        }
    ],
    "sg:phone":"+44 1733 362300",
    "sg:postcode":"PE2 6YQ",
    "sg:province":"Cambridgeshire",
    "sg:tags":[
        "game"
    ],
    "wof:name":"Toy Wizards Ltd.",
    "wof:placetype":"venue"
},
  "geometry": {"coordinates":[-0.3107590079,52.5366439819],"type":"Point"}
}