{
  "type": "Feature",
  "properties": {
    "addr:full":"17a Clarence St Staines Berkshire TW18 4SU",
    "addr:housenumber":"17a",
    "addr:postcode":"tw18 4su",
    "addr:street":"Clarence St",
    "iso:country":"GB",
    "sg:address":"17a Clarence St",
    "sg:city":"Staines",
    "sg:classifiers":[
        {
            "category":"Taxi",
            "type":"Transportation"
        }
    ],
    "sg:phone":"+44 1784 465555",
    "sg:postcode":"TW18 4SU",
    "sg:province":"Berkshire",
    "sg:tags":[
        "mini",
        "cab"
    ],
    "wof:name":"Royal Cars",
    "wof:placetype":"venue"
},
  "geometry": {"coordinates":[-0.514680028,51.43384552],"type":"Point"}
}