{
  "type": "Feature",
  "properties": {
    "addr:full":"Filling Station, Shaw Rd, Royton Oldham Lancashire OL2 6PG",
    "addr:postcode":"ol2 6pg",
    "addr:street":"Shaw Rd",
    "iso:country":"GB",
    "sg:address":"Filling Station, Shaw Rd, Royton",
    "sg:city":"Oldham",
    "sg:classifiers":[
        {
            "category":"Autos & Motor Vehicles",
            "subcategory":"Automobile Sales",
            "type":"Retail Goods"
        }
    ],
    "sg:postcode":"OL2 6PG",
    "sg:province":"Lancashire",
    "sg:tags":[
        "car"
    ],
    "wof:name":"Pendlebury,Ian,",
    "wof:placetype":"venue"
},
  "geometry": {"coordinates":[-2.1033699512,53.5708198547],"type":"Point"}
}