{
  "type": "Feature",
  "properties": {
    "iso:country":"GB",
    "sg:address":"196 Hertford Road, Edmonton",
    "sg:city":"London",
    "sg:classifiers":[
        {
            "category":"Home & Garden",
            "subcategory":"Hardware",
            "type":"Retail Goods"
        }
    ],
    "sg:postcode":"N9 7EL",
    "sg:province":"Greater London",
    "sg:tags":[
        "retailer",
        "diy"
    ],
    "wof:name":"Burridges D I Y",
    "wof:placetype":"venue"
},
  "geometry": {"coordinates":[-0.055722,51.630417],"type":"Point"}
}