{
  "type": "Feature",
  "properties": {
    "iso:country":"GB",
    "sg:address":"3 Bank Mansions, Golders Green Cres",
    "sg:city":"London",
    "sg:classifiers":[
        {
            "category":"Professional",
            "subcategory":"Management & Consulting",
            "type":"Services"
        }
    ],
    "sg:postcode":"NW11 8LE",
    "sg:province":"Greater London",
    "sg:tags":[
        "consultant",
        "business"
    ],
    "wof:name":"Starfish Consultants Ltd",
    "wof:placetype":"venue"
},
  "geometry": {"coordinates":[-0.19675,51.57283],"type":"Point"}
}