{
  "type": "Feature",
  "properties": {
    "iso:country":"GB",
    "sg:address":"86 Argyll Rd",
    "sg:city":"Ripley",
    "sg:classifiers":[
        {
            "category":"Bus Charters",
            "type":"Transportation"
        }
    ],
    "sg:phone":"+44 1773 749324",
    "sg:postcode":"DE5 3LH",
    "sg:province":"Derbyshire",
    "sg:tags":[
        "hire",
        "coach"
    ],
    "wof:name":"M H Travel",
    "wof:placetype":"venue"
},
  "geometry": {"coordinates":[-1.401293,53.051582],"type":"Point"}
}