{
  "type": "Feature",
  "properties": {
    "iso:country":"GB",
    "sg:address":"221 Duckworth Street",
    "sg:city":"Darwen",
    "sg:classifiers":[
        {
            "category":"Health Services",
            "subcategory":"Optometrist",
            "type":"Services"
        }
    ],
    "sg:phone":"+44 1254 702149",
    "sg:postcode":"BB3 1AU",
    "sg:province":"Lancashire",
    "sg:tags":[
        "optician"
    ],
    "wof:name":"Keegan Opticians Ltd.",
    "wof:placetype":"venue"
},
  "geometry": {"coordinates":[-2.4691450596,53.6972732544],"type":"Point"}
}