{
  "type": "Feature",
  "properties": {
    "iso:country":"GB",
    "sg:address":"17 Rosse Field",
    "sg:city":"Barrow In Furness",
    "sg:classifiers":[
        {
            "category":"Home & Garden",
            "subcategory":"Building Materials",
            "type":"Retail Goods"
        }
    ],
    "sg:phone":"+44 1229 831853",
    "sg:postcode":"LA13 9RF",
    "sg:province":"Cumbria",
    "sg:tags":[
        "insulation",
        "installers"
    ],
    "wof:name":"S Reader",
    "wof:placetype":"venue"
},
  "geometry": {"coordinates":[-3.1972470284,54.1139221191],"type":"Point"}
}