{
  "type": "Feature",
  "properties": {
    "iso:country":"GB",
    "sg:address":"Blackburn St Health Centre, Blackburn Street, Radcliffe",
    "sg:city":"Manchester",
    "sg:classifiers":[
        {
            "category":"Health Services",
            "subcategory":"Doctor",
            "type":"Services"
        }
    ],
    "sg:phone":"+44 161 723 2062",
    "sg:postcode":"M26 1WS",
    "sg:province":"Greater Manchester",
    "sg:tags":[
        "practitioners"
    ],
    "wof:name":"A J Behrana",
    "wof:placetype":"venue"
},
  "geometry": {"coordinates":[-2.326564,53.560265],"type":"Point"}
}