{
  "type": "Feature",
  "properties": {
    "iso:country":"GB",
    "sg:address":"Unit 1 Stag Business Park, 164-166 Christchurch Ro",
    "sg:city":"Ringwood",
    "sg:classifiers":[
        {
            "category":"Professional",
            "subcategory":"Engineering",
            "type":"Services"
        }
    ],
    "sg:postcode":"BH24 3AS",
    "sg:province":"Dorset",
    "sg:tags":[
        "contractor",
        "electrical",
        "engineer"
    ],
    "wof:name":"Conger Electrical",
    "wof:placetype":"venue"
},
  "geometry": {"coordinates":[-1.792989,50.846329],"type":"Point"}
}