{
  "type": "Feature",
  "properties": {
    "iso:country":"GB",
    "sg:address":"Adisson Industrial Estate, Newburn Bridge Road",
    "sg:city":"Blaydon-on-tyne",
    "sg:classifiers":[
        {
            "category":"Home & Garden",
            "subcategory":"Building Materials",
            "type":"Retail Goods"
        }
    ],
    "sg:phone":"+44 191 414 7999",
    "sg:postcode":"NE21 4TE",
    "sg:province":"Tyne and Wear",
    "sg:tags":[
        "ventilator",
        "ventilation",
        "system"
    ],
    "wof:name":"G Peddie Engineers Ltd.",
    "wof:placetype":"venue"
},
  "geometry": {"coordinates":[-1.7380479574,54.9734153748],"type":"Point"}
}