{
  "type": "Feature",
  "properties": {
    "iso:country":"GB",
    "sg:address":"466 Fulham Rd",
    "sg:city":"London",
    "sg:classifiers":[
        {
            "category":"Cafe",
            "type":"Food & Drink"
        }
    ],
    "sg:postcode":"SW6 1BY",
    "sg:province":"Greater London",
    "sg:tags":[
        "tea",
        "room"
    ],
    "wof:name":"Stamford Bridge Cafe",
    "wof:placetype":"venue"
},
  "geometry": {"coordinates":[-0.1947930008,51.480178833],"type":"Point"}
}