{
  "type": "Feature",
  "properties": {
    "addr:full":"Devon House, Eastbourne Rd, Blindley Heath Lingfield Surrey RH7 6JJ",
    "addr:postcode":"rh7 6jj",
    "addr:street":"Eastbourne Rd",
    "iso:country":"GB",
    "sg:address":"Devon House, Eastbourne Rd, Blindley Heath",
    "sg:city":"Lingfield",
    "sg:classifiers":[
        {
            "category":"Military Area",
            "subcategory":"Air Force Base",
            "type":"Public Place"
        }
    ],
    "sg:phone":"+44 20 8771 9696",
    "sg:postcode":"RH7 6JJ",
    "sg:province":"Surrey",
    "sg:tags":[
        "consultant",
        "conditioning",
        "mnfrs"
    ],
    "wof:name":"D.B. Airtech Ltd",
    "wof:placetype":"venue"
},
  "geometry": {"coordinates":[-0.0571990013,51.2043609619],"type":"Point"}
}