{
  "type": "Feature",
  "properties": {
    "addr:full":"29-31 Golders Grn Road London Greater London NW11 8EE",
    "addr:housenumber":"29-31",
    "addr:postcode":"nw11 8ee",
    "addr:street":"Golders Grn Road",
    "iso:country":"GB",
    "sg:address":"29-31 Golders Grn Road",
    "sg:city":"London",
    "sg:classifiers":[
        {
            "category":"Shopping",
            "subcategory":"Used Merchandise",
            "type":"Retail Goods"
        }
    ],
    "sg:phone":"+44 20 8458 0898",
    "sg:postcode":"NW11 8EE",
    "sg:province":"Greater London",
    "sg:tags":[
        "shop",
        "second-hand"
    ],
    "wof:name":"Amy's Ardware",
    "wof:placetype":"venue"
},
  "geometry": {"coordinates":[-0.1973260045,51.572052002],"type":"Point"}
}