{
  "type": "Feature",
  "properties": {
    "iso:country":"GB",
    "sg:address":"Church House, Combe In Teignhead",
    "sg:city":"Newton Abbot",
    "sg:classifiers":[
        {
            "category":"Professional",
            "subcategory":"Art Services",
            "type":"Services"
        }
    ],
    "sg:phone":"+44 1626 873748",
    "sg:postcode":"TQ12 4RA",
    "sg:province":"Devon",
    "sg:tags":[
        "framing"
    ],
    "wof:name":"Madryn Studios",
    "wof:placetype":"venue"
},
  "geometry": {"coordinates":[-3.6076591015,50.5288696289],"type":"Point"}
}