{
  "type": "Feature",
  "properties": {
    "addr:full":"Elbow Lane, Hertford Heath Hertford Hertfordshire SG13 7QA",
    "addr:postcode":"sg13 7qa",
    "addr:street":"Elbow Lane",
    "iso:country":"GB",
    "sg:address":"Elbow Lane, Hertford Heath",
    "sg:city":"Hertford",
    "sg:classifiers":[
        {
            "category":"Professional",
            "subcategory":"Engineering",
            "type":"Services"
        }
    ],
    "sg:postcode":"SG13 7QA",
    "sg:province":"Hertfordshire",
    "sg:tags":[
        "civil",
        "engineer"
    ],
    "wof:name":"Ladkarn Construction Ltd.",
    "wof:placetype":"venue"
},
  "geometry": {"coordinates":[-0.0460450016,51.7823257446],"type":"Point"}
}