{
  "type": "Feature",
  "properties": {
    "addr:full":"Doctors Surgery, 599 Wilmslow Road Manchester Greater Manchester M20 3QD",
    "addr:housenumber":"599",
    "addr:postcode":"m20 3qd",
    "addr:street":"Wilmslow Road",
    "iso:country":"GB",
    "sg:address":"Doctors Surgery, 599 Wilmslow Road",
    "sg:city":"Manchester",
    "sg:classifiers":[
        {
            "category":"Health Services",
            "subcategory":"Doctor",
            "type":"Services"
        }
    ],
    "sg:postcode":"M20 3QD",
    "sg:province":"Greater Manchester",
    "sg:tags":[
        "practitioners"
    ],
    "wof:name":"Lionel A Michael",
    "wof:placetype":"venue"
},
  "geometry": {"coordinates":[-2.2278690338,53.4346084595],"type":"Point"}
}