{
  "type": "Feature",
  "properties": {
    "iso:country":"GB",
    "sg:address":"31 Market Pl, Gt Bridge",
    "sg:city":"Tipton",
    "sg:classifiers":[
        {
            "category":"Retail",
            "subcategory":"Repair Shop",
            "type":"Services"
        }
    ],
    "sg:phone":"+44 121 529 1140",
    "sg:postcode":"DY4 7EJ",
    "sg:province":"West Midlands",
    "sg:tags":[
        "upholsterer"
    ],
    "wof:name":"Sahni,Daram,",
    "wof:placetype":"venue"
},
  "geometry": {"coordinates":[-2.036401,52.530018],"type":"Point"}
}