{
  "type": "Feature",
  "properties": {
    "addr:full":"17 Lester Close, Hr Compton Plymouth Devon PL3 6PX",
    "addr:housenumber":"17",
    "addr:postcode":"pl3 6px",
    "addr:street":"Lester Close",
    "iso:country":"GB",
    "sg:address":"17 Lester Close, Hr Compton",
    "sg:city":"Plymouth",
    "sg:classifiers":[
        {
            "category":"Health Services",
            "subcategory":"Podiatrist",
            "type":"Services"
        }
    ],
    "sg:postcode":"PL3 6PX",
    "sg:province":"Devon",
    "sg:tags":[
        "podiatrists",
        "chiropodist"
    ],
    "wof:name":"A P Rogers",
    "wof:placetype":"venue"
},
  "geometry": {"coordinates":[-4.112719059,50.3915634155],"type":"Point"}
}