{
  "type": "Feature",
  "properties": {
    "addr:full":"88 Cavendish Avenue Colchester Essex CO2 8BT",
    "addr:housenumber":"88",
    "addr:postcode":"co2 8bt",
    "addr:street":"Cavendish Avenue",
    "iso:country":"GB",
    "sg:address":"88 Cavendish Avenue",
    "sg:city":"Colchester",
    "sg:classifiers":[
        {
            "category":"Professional",
            "subcategory":"Management & Consulting",
            "type":"Services"
        }
    ],
    "sg:phone":"+44 1206 868457",
    "sg:postcode":"CO2 8BT",
    "sg:province":"Essex",
    "sg:tags":[
        "consultant",
        "training",
        "business"
    ],
    "wof:name":"Anglia Development Services Ltd.",
    "wof:placetype":"venue"
},
  "geometry": {"coordinates":[0.9198669791,51.8741607666],"type":"Point"}
}