{
  "type": "Feature",
  "properties": {
    "addr:full":"25 Granville Road Eastbourne East Sussex BN20 7HB",
    "addr:housenumber":"25",
    "addr:postcode":"bn20 7hb",
    "addr:street":"Granville Road",
    "iso:country":"GB",
    "sg:address":"25 Granville Road",
    "sg:city":"Eastbourne",
    "sg:classifiers":[
        {
            "category":"Real Estate",
            "subcategory":"Architect",
            "type":"Services"
        }
    ],
    "sg:phone":"+44 1323 727788",
    "sg:postcode":"BN20 7HB",
    "sg:province":"East Sussex",
    "wof:name":"Raymond Smith Partnership",
    "wof:placetype":"venue"
},
  "geometry": {"coordinates":[0.2750450075,50.7587089539],"type":"Point"}
}