{
  "type": "Feature",
  "properties": {
    "addr:full":"1 Flour Square, Lockhill Grimsby Lincolnshire DN31 3LS",
    "addr:housenumber":"1",
    "addr:postcode":"dn31 3ls",
    "addr:street":"Flour Square Lockhill",
    "iso:country":"GB",
    "sg:address":"1 Flour Square, Lockhill",
    "sg:city":"Grimsby",
    "sg:classifiers":[
        {
            "category":"Retail",
            "subcategory":"Auto Rental",
            "type":"Services"
        }
    ],
    "sg:postcode":"DN31 3LS",
    "sg:province":"Lincolnshire",
    "sg:tags":[
        "car"
    ],
    "wof:name":"M R Batchelor",
    "wof:placetype":"venue"
},
  "geometry": {"coordinates":[-0.0779839978,53.5757255554],"type":"Point"}
}