{
  "type": "Feature",
  "properties": {
    "addr:full":"12 West Road Westcliff-on-sea Essex SS0 9DA",
    "addr:housenumber":"12",
    "addr:postcode":"ss0 9da",
    "addr:street":"West Road",
    "iso:country":"GB",
    "sg:address":"12 West Road",
    "sg:city":"Westcliff-on-sea",
    "sg:classifiers":[
        {
            "category":"Health Services",
            "subcategory":"Doctor",
            "type":"Services"
        }
    ],
    "sg:postcode":"SS0 9DA",
    "sg:province":"Essex",
    "sg:tags":[
        "practitioners"
    ],
    "wof:name":"West Road Surgery",
    "wof:placetype":"venue"
},
  "geometry": {"coordinates":[0.6940609813,51.5439720154],"type":"Point"}
}